{
  "type": "Feature",
  "properties": {
    "gn:admin1_code":"90.0",
    "gn:asciiname":"Bol'shaya Mochga",
    "gn:country_code":"RU",
    "gn:dem":117,
    "gn:feature_class":"P",
    "gn:feature_code":"PPL",
    "gn:name":"Bol\u2019shaya Mochga",
    "gn:population":0,
    "gn:timezone":"Asia/Yekaterinburg",
    "iso:country":"RU",
    "name:rus_x_preferred":[
        "\u0411\u043e\u043b\u044c\u0448\u0430\u044f \u041c\u043e\u0447\u0433\u0430"
    ],
    "name:und_x_variant":[
        "Bol\u2019shaya Mochga",
        "\u0411\u043e\u043b\u044c\u0448\u0430\u044f \u041c\u043e\u0447\u0433\u0430"
    ],
    "wof:name":"Bol'shaya Mochga",
    "wof:placetype":"locality"
},
  "geometry": {"coordinates":[55.6054,58.992],"type":"Point"}
}