{
  "type": "Feature",
  "properties": {
    "gn:admin1_code":"93",
    "gn:asciiname":"Ust'-Kurlych",
    "gn:country_code":"RU",
    "gn:dem":465,
    "gn:feature_class":"P",
    "gn:feature_code":"PPL",
    "gn:name":"Ust\u2019-Kurlych",
    "gn:population":0,
    "gn:timezone":"Asia/Chita",
    "iso:country":"RU",
    "name:eng_x_preferred":[
        "Ust'-Kurlych"
    ],
    "name:nor_x_preferred":[
        "Ust-Kurlytsj"
    ],
    "name:rus_x_preferred":[
        "\u0423\u0441\u0442\u044c-\u041a\u0443\u0440\u043b\u044b\u0447"
    ],
    "name:und_x_variant":[
        "Ust\u2019-Kurlych"
    ],
    "wof:name":"Ust'-Kurlych",
    "wof:placetype":"locality"
},
  "geometry": {"coordinates":[117.46078,52.16497],"type":"Point"}
}