{
  "type": "Feature",
  "properties": {
    "gn:admin1_code":"90",
    "gn:asciiname":"Rodionovo",
    "gn:country_code":"RU",
    "gn:dem":172,
    "gn:feature_class":"P",
    "gn:feature_code":"PPL",
    "gn:name":"Rodionovo",
    "gn:population":0,
    "gn:timezone":"Asia/Yekaterinburg",
    "iso:country":"RU",
    "name:rus_x_preferred":[
        "\u0420\u043e\u0434\u0438\u043e\u043d\u043e\u0432\u043e"
    ],
    "name:und_x_variant":[
        "\u0420\u043e\u0434\u0438\u043e\u043d\u043e\u0432\u043e"
    ],
    "wof:name":"Rodionovo",
    "wof:placetype":"locality"
},
  "geometry": {"coordinates":[56.9483,57.5902],"type":"Point"}
}