{
  "type": "Feature",
  "properties": {
    "gn:admin1_code":"21.0",
    "gn:asciiname":"Butyrki",
    "gn:country_code":"RU",
    "gn:dem":106,
    "gn:feature_class":"P",
    "gn:feature_code":"PPL",
    "gn:name":"Butyrki",
    "gn:population":0,
    "gn:timezone":"Europe/Moscow",
    "iso:country":"RU",
    "name:rus_x_preferred":[
        "\u0411\u0443\u0442\u044b\u0440\u043a\u0438"
    ],
    "name:und_x_variant":[
        "\u0411\u0443\u0442\u044b\u0440\u043a\u0438"
    ],
    "wof:name":"Butyrki",
    "wof:placetype":"locality"
},
  "geometry": {"coordinates":[41.51967,57.20579],"type":"Point"}
}