{
  "type": "Feature",
  "properties": {
    "gn:admin1_code":"16",
    "gn:asciiname":"Novoye Yadrino",
    "gn:country_code":"RU",
    "gn:dem":135,
    "gn:feature_class":"P",
    "gn:feature_code":"PPL",
    "gn:name":"Novoye Yadrino",
    "gn:population":0,
    "gn:timezone":"Europe/Moscow",
    "iso:country":"RU",
    "name:rus_x_preferred":[
        "\u041d\u043e\u0432\u043e\u0435 \u042f\u0434\u0440\u0438\u043d\u043e"
    ],
    "wof:name":"Novoye Yadrino",
    "wof:placetype":"locality"
},
  "geometry": {"coordinates":[46.3371,55.99527],"type":"Point"}
}