{
  "type": "Feature",
  "properties": {
    "gn:admin1_code":"83",
    "gn:asciiname":"Gorki",
    "gn:country_code":"RU",
    "gn:dem":200,
    "gn:feature_class":"P",
    "gn:feature_code":"PPL",
    "gn:name":"Gorki",
    "gn:population":0,
    "gn:timezone":"Europe/Moscow",
    "iso:country":"RU",
    "name:aze_x_preferred":[
        "Qorki"
    ],
    "name:bel_x_preferred":[
        "\u0413\u043e\u0440\u043a\u0456"
    ],
    "name:bul_x_preferred":[
        "\u0413\u043e\u0440\u043a\u0438"
    ],
    "name:cat_x_preferred":[
        "Gorki"
    ],
    "name:ceb_x_preferred":[
        "Gorki"
    ],
    "name:ces_x_preferred":[
        "Gorki"
    ],
    "name:dan_x_preferred":[
        "Gorki"
    ],
    "name:deu_x_preferred":[
        "Gorki"
    ],
    "name:eng_x_preferred":[
        "Gorki"
    ],
    "name:epo_x_preferred":[
        "Gorki"
    ],
    "name:est_x_preferred":[
        "Gorki"
    ],
    "name:fin_x_preferred":[
        "Gorki"
    ],
    "name:fra_x_preferred":[
        "Gorki"
    ],
    "name:heb_x_preferred":[
        "\u05d2\u05d5\u05e8\u05e7\u05d9"
    ],
    "name:hun_x_preferred":[
        "Gorki"
    ],
    "name:hye_x_preferred":[
        "\u0533\u0578\u0580\u056f\u056b"
    ],
    "name:ita_x_preferred":[
        "Gorki"
    ],
    "name:lav_x_preferred":[
        "Gorki"
    ],
    "name:mon_x_preferred":[
        "\u0413\u043e\u0440\u044c\u043a\u0438\u0439"
    ],
    "name:nld_x_preferred":[
        "Gorki"
    ],
    "name:nor_x_preferred":[
        "Gorki"
    ],
    "name:pol_x_preferred":[
        "Gorki"
    ],
    "name:rus_x_preferred":[
        "\u0413\u043e\u0440\u043a\u0438"
    ],
    "name:spa_x_preferred":[
        "Gorki"
    ],
    "name:srp_x_preferred":[
        "\u0413\u043e\u0440\u043a\u0438"
    ],
    "name:swe_x_preferred":[
        "Gorki"
    ],
    "name:ukr_x_preferred":[
        "\u0413\u043e\u0440\u043a\u0438"
    ],
    "wof:name":"Gorki",
    "wof:placetype":"locality"
},
  "geometry": {"coordinates":[39.38449,56.58142],"type":"Point"}
}