{
  "type": "Feature",
  "properties": {
    "gn:admin1_code":"88",
    "gn:asciiname":"Maloye Semino",
    "gn:country_code":"RU",
    "gn:dem":116,
    "gn:feature_class":"P",
    "gn:feature_code":"PPL",
    "gn:name":"Maloye S\u00ebmino",
    "gn:population":0,
    "gn:timezone":"Europe/Moscow",
    "iso:country":"RU",
    "name:rus_x_preferred":[
        "\u041c\u0430\u043b\u043e\u0435 \u0421\u0451\u043c\u0438\u043d\u043e"
    ],
    "name:und_x_variant":[
        "Maloye S\u00ebmino"
    ],
    "wof:name":"Maloye Semino",
    "wof:placetype":"locality"
},
  "geometry": {"coordinates":[38.39323,58.1052],"type":"Point"}
}