{
  "type": "Feature",
  "properties": {
    "gn:admin1_code":"51.0",
    "gn:asciiname":"Shishadeyevo",
    "gn:country_code":"RU",
    "gn:dem":136,
    "gn:feature_class":"P",
    "gn:feature_code":"PPL",
    "gn:name":"Shishadeyevo",
    "gn:population":0,
    "gn:timezone":"Europe/Moscow",
    "iso:country":"RU",
    "name:rus_x_preferred":[
        "\u0428\u0438\u0448\u0430\u0434\u0435\u0435\u0432\u043e"
    ],
    "wof:name":"Shishadeyevo",
    "wof:placetype":"locality"
},
  "geometry": {"coordinates":[44.75807,54.66172],"type":"Point"}
}