{
  "type": "Feature",
  "properties": {
    "gn:admin1_code":"46.0",
    "gn:asciiname":"Staroye Pole",
    "gn:country_code":"RU",
    "gn:dem":145,
    "gn:feature_class":"P",
    "gn:feature_code":"PPL",
    "gn:name":"Staroye Pole",
    "gn:population":0,
    "gn:timezone":"Europe/Moscow",
    "iso:country":"RU",
    "name:rus_x_preferred":[
        "\u0421\u0442\u0430\u0440\u043e\u0435 \u041f\u043e\u043b\u0435"
    ],
    "wof:name":"Staroye Pole",
    "wof:placetype":"locality"
},
  "geometry": {"coordinates":[44.31809000000001,54.35576],"type":"Point"}
}