{
  "type": "Feature",
  "properties": {
    "gn:admin1_code":"52",
    "gn:asciiname":"Lubenskoye",
    "gn:country_code":"RU",
    "gn:dem":205,
    "gn:feature_class":"P",
    "gn:feature_code":"PPL",
    "gn:name":"Lubenskoye",
    "gn:population":0,
    "gn:timezone":"Europe/Moscow",
    "iso:country":"RU",
    "name:eng_x_preferred":[
        "Lubenskoye"
    ],
    "name:nor_x_preferred":[
        "Lubenskoje"
    ],
    "name:rus_x_preferred":[
        "\u041b\u0443\u0431\u0435\u043d\u0441\u043a\u043e\u0435"
    ],
    "name:und_x_variant":[
        "Lubinskoye",
        "\u041b\u0443\u0431\u0435\u043d\u0441\u043a\u043e\u0435",
        "Lubenskoye"
    ],
    "wof:name":"Lubenskoye",
    "wof:placetype":"locality"
},
  "geometry": {"coordinates":[35.10764,58.63119],"type":"Point"}
}