{
  "type": "Feature",
  "properties": {
    "gn:admin1_code":"38",
    "gn:asciiname":"Svet",
    "gn:cc2":"RU",
    "gn:country_code":"RU",
    "gn:dem":3,
    "gn:feature_class":"P",
    "gn:feature_code":"PPL",
    "gn:name":"Svet",
    "gn:population":0,
    "gn:timezone":"Europe/Moscow",
    "iso:country":"RU",
    "name:und_x_variant":[
        "Kommunisticheskiy Svet",
        "Svet"
    ],
    "wof:name":"Svet",
    "wof:placetype":"locality"
},
  "geometry": {"coordinates":[38.41806,45.93306],"type":"Point"}
}