{
  "type": "Feature",
  "properties": {
    "gn:admin1_code":"55",
    "gn:asciiname":"Gumarovo",
    "gn:country_code":"RU",
    "gn:dem":204,
    "gn:feature_class":"P",
    "gn:feature_code":"PPL",
    "gn:name":"Gumarovo",
    "gn:population":0,
    "gn:timezone":"Asia/Yekaterinburg",
    "iso:country":"RU",
    "name:rus_x_preferred":[
        "\u0413\u0443\u043c\u0430\u0440\u043e\u0432\u043e"
    ],
    "wof:name":"Gumarovo",
    "wof:placetype":"locality"
},
  "geometry": {"coordinates":[57.3693,51.5018],"type":"Point"}
}