{
  "type": "Feature",
  "properties": {
    "gn:admin1_code":"70",
    "gn:asciiname":"Tashla",
    "gn:cc2":"RU",
    "gn:country_code":"RU",
    "gn:dem":290,
    "gn:feature_class":"P",
    "gn:feature_code":"PPL",
    "gn:name":"Tashla",
    "gn:population":0,
    "gn:timezone":"Europe/Moscow",
    "iso:country":"RU",
    "name:und_x_variant":[
        "Tashli",
        "Tashla"
    ],
    "wof:name":"Tashla",
    "wof:placetype":"locality"
},
  "geometry": {"coordinates":[42.11611,45.08111],"type":"Point"}
}