{
  "type": "Feature",
  "properties": {
    "gn:admin1_code":"72",
    "gn:asciiname":"Osvobozhdeniye",
    "gn:country_code":"RU",
    "gn:dem":118,
    "gn:feature_class":"P",
    "gn:feature_code":"PPL",
    "gn:name":"Osvobozhdeniye",
    "gn:population":0,
    "gn:timezone":"Europe/Moscow",
    "iso:country":"RU",
    "wof:name":"Osvobozhdeniye",
    "wof:placetype":"locality"
},
  "geometry": {"coordinates":[41.89529,53.06973000000001],"type":"Point"}
}