{
  "type": "Feature",
  "properties": {
    "gn:admin1_code":"85",
    "gn:asciiname":"Myaksa",
    "gn:country_code":"RU",
    "gn:dem":134,
    "gn:feature_class":"P",
    "gn:feature_code":"PPL",
    "gn:name":"Myaksa",
    "gn:population":1143,
    "gn:timezone":"Europe/Moscow",
    "iso:country":"RU",
    "name:eng_x_preferred":[
        "Myaksa"
    ],
    "name:nor_x_preferred":[
        "Mjaksa"
    ],
    "name:rus_x_preferred":[
        "\u041c\u044f\u043a\u0441\u0430"
    ],
    "wof:name":"Myaksa",
    "wof:placetype":"locality",
    "wof:population":1143
},
  "geometry": {"coordinates":[38.1938,58.8889],"type":"Point"}
}