{
  "type": "Feature",
  "properties": {
    "gn:admin1_code":"42.0",
    "gn:asciiname":"Chudskoye",
    "gn:country_code":"RU",
    "gn:dem":113,
    "gn:feature_class":"P",
    "gn:feature_code":"PPL",
    "gn:name":"Chudskoye",
    "gn:population":0,
    "gn:timezone":"Europe/Moscow",
    "iso:country":"RU",
    "name:rus_x_preferred":[
        "\u0427\u0443\u0434\u0441\u043a\u043e\u0435"
    ],
    "name:und_x_variant":[
        "\u0427\u0443\u0434\u0441\u043a\u043e\u0435"
    ],
    "wof:name":"Chudskoye",
    "wof:placetype":"locality"
},
  "geometry": {"coordinates":[34.28028,59.79306],"type":"Point"}
}