{
  "type": "Feature",
  "properties": {
    "gn:admin1_code":"54",
    "gn:asciiname":"Khmarovka",
    "gn:country_code":"RU",
    "gn:dem":116,
    "gn:feature_class":"P",
    "gn:feature_code":"PPL",
    "gn:name":"Khmarovka",
    "gn:population":0,
    "gn:timezone":"Asia/Omsk",
    "iso:country":"RU",
    "name:eng_x_preferred":[
        "Khmarovka"
    ],
    "name:nor_x_preferred":[
        "Sjarovka"
    ],
    "name:rus_x_preferred":[
        "\u0428\u0430\u0440\u043e\u0432\u043a\u0430"
    ],
    "name:rus_x_variant":[
        "\u0425\u043c\u0430\u0440\u043e\u0432\u043a\u0430"
    ],
    "name:und_x_variant":[
        "Khmarinskiy"
    ],
    "wof:name":"Khmarovka",
    "wof:placetype":"locality"
},
  "geometry": {"coordinates":[71.56983000000002,54.54303],"type":"Point"}
}