{
  "type": "Feature",
  "properties": {
    "gn:admin1_code":"80.0",
    "gn:asciiname":"Chernaya Rechka",
    "gn:country_code":"RU",
    "gn:dem":78,
    "gn:feature_class":"P",
    "gn:feature_code":"PPL",
    "gn:name":"Ch\u00ebrnaya Rechka",
    "gn:population":0,
    "gn:timezone":"Europe/Samara",
    "iso:country":"RU",
    "name:rus_x_preferred":[
        "\u0427\u00eb\u0440\u043d\u0430\u044f \u0420\u0435\u0447\u043a\u0430"
    ],
    "name:und_x_variant":[
        "Ch\u00ebrnaya Rechka"
    ],
    "wof:name":"Chernaya Rechka",
    "wof:placetype":"locality"
},
  "geometry": {"coordinates":[54.096,56.3272],"type":"Point"}
}