{
  "type": "Feature",
  "properties": {
    "gn:admin1_code":"24.0",
    "gn:asciiname":"Balkovskiy",
    "gn:country_code":"RU",
    "gn:dem":76,
    "gn:feature_class":"P",
    "gn:feature_code":"PPL",
    "gn:name":"Balkovskiy",
    "gn:population":0,
    "gn:timezone":"Europe/Moscow",
    "iso:country":"RU",
    "name:eng_x_preferred":[
        "Balkovskiy"
    ],
    "name:nor_x_preferred":[
        "Balkovskij"
    ],
    "name:rus_x_preferred":[
        "\u0411\u0430\u043b\u043a\u043e\u0432\u0441\u043a\u0438\u0439"
    ],
    "name:und_x_variant":[
        "Baga Chanosovsk",
        "Khara-Buluk"
    ],
    "wof:name":"Balkovskiy",
    "wof:placetype":"locality"
},
  "geometry": {"coordinates":[44.41944,46.72],"type":"Point"}
}