{
  "type": "Feature",
  "properties": {
    "gn:admin1_code":"28",
    "gn:asciiname":"Kallimyaki",
    "gn:country_code":"RU",
    "gn:dem":8,
    "gn:feature_class":"P",
    "gn:feature_code":"PPL",
    "gn:name":"Kallimyaki",
    "gn:population":0,
    "gn:timezone":"Europe/Moscow",
    "iso:country":"RU",
    "name:fin_x_preferred":[
        "Mikli"
    ],
    "name:rus_x_preferred":[
        "\u041a\u0430\u043b\u043b\u0438\u043c\u044f\u043a\u0438"
    ],
    "wof:name":"Kallimyaki",
    "wof:placetype":"locality"
},
  "geometry": {"coordinates":[30.34184,61.52867],"type":"Point"}
}