{
  "type": "Feature",
  "properties": {
    "gn:admin1_code":"88",
    "gn:asciiname":"Boronukovo",
    "gn:country_code":"RU",
    "gn:dem":156,
    "gn:feature_class":"P",
    "gn:feature_code":"PPL",
    "gn:name":"Boronukovo",
    "gn:population":0,
    "gn:timezone":"Europe/Moscow",
    "iso:country":"RU",
    "name:rus_x_preferred":[
        "\u0411\u043e\u0440\u043e\u043d\u0443\u043a\u043e\u0432\u043e"
    ],
    "wof:name":"Boronukovo",
    "wof:placetype":"locality"
},
  "geometry": {"coordinates":[39.22645,56.74165],"type":"Point"}
}