{
  "type": "Feature",
  "properties": {
    "gn:admin1_code":"29",
    "gn:asciiname":"Ust'-Sosnovka",
    "gn:country_code":"RU",
    "gn:dem":93,
    "gn:feature_class":"P",
    "gn:feature_code":"PPL",
    "gn:name":"Ust\u2019-Sosnovka",
    "gn:population":0,
    "gn:timezone":"Asia/Novokuznetsk",
    "iso:country":"RU",
    "name:eng_x_preferred":[
        "Ust'-Sosnovka"
    ],
    "name:rus_x_preferred":[
        "\u0423\u0441\u0442\u044c-\u0421\u043e\u0441\u043d\u043e\u0432\u043a\u0430"
    ],
    "name:rus_x_variant":[
        "\u0423\u0441\u0442\u044c-\u0421\u043e\u0441\u043a\u043e\u0432\u043a\u0430"
    ],
    "name:und_x_variant":[
        "Ust\u2019-Sosnovka"
    ],
    "wof:name":"Ust'-Sosnovka",
    "wof:placetype":"locality"
},
  "geometry": {"coordinates":[84.98044,56.08349000000001],"type":"Point"}
}