{
  "type": "Feature",
  "properties": {
    "gn:admin1_code":"11",
    "gn:asciiname":"Khara-Guzhatka",
    "gn:country_code":"RU",
    "gn:dem":741,
    "gn:feature_class":"P",
    "gn:feature_code":"PPL",
    "gn:name":"Khara-Guzhatka",
    "gn:population":0,
    "gn:timezone":"Asia/Irkutsk",
    "iso:country":"RU",
    "name:rus_x_preferred":[
        "\u0425\u0430\u0440\u0430-\u0413\u0443\u0436\u0430\u0442\u043a\u0430"
    ],
    "name:und_x_variant":[
        "\u0425\u0430\u0440\u0430-\u0413\u0443\u0436\u0430\u0442\u043a\u0430"
    ],
    "wof:name":"Khara-Guzhatka",
    "wof:placetype":"locality"
},
  "geometry": {"coordinates":[108.46666999999999,51.51667],"type":"Point"}
}