{
  "type": "Feature",
  "properties": {
    "gn:admin1_code":"77",
    "gn:asciiname":"Staroye",
    "gn:country_code":"RU",
    "gn:dem":194,
    "gn:feature_class":"P",
    "gn:feature_code":"PPL",
    "gn:name":"Staroye",
    "gn:population":0,
    "gn:timezone":"Europe/Moscow",
    "iso:country":"RU",
    "name:rus_x_preferred":[
        "\u0421\u0442\u0430\u0440\u043e\u0435"
    ],
    "name:und_x_variant":[
        "\u0421\u0442\u0430\u0440\u043e\u0435"
    ],
    "wof:name":"Staroye",
    "wof:placetype":"locality"
},
  "geometry": {"coordinates":[34.61194,57.51778],"type":"Point"}
}