{
  "type": "Feature",
  "properties": {
    "gn:admin1_code":"73",
    "gn:admin2_code":"Al'met'yevskiy Rayon",
    "gn:asciiname":"Nagornoye",
    "gn:country_code":"RU",
    "gn:dem":129,
    "gn:feature_class":"P",
    "gn:feature_code":"PPL",
    "gn:name":"Nagornoye",
    "gn:population":0,
    "gn:timezone":"Europe/Moscow",
    "iso:country":"RU",
    "name:eng_x_preferred":[
        "Nagornoye"
    ],
    "name:nor_x_preferred":[
        "Nagornoje"
    ],
    "name:rus_x_preferred":[
        "\u041d\u0430\u0433\u043e\u0440\u043d\u043e\u0435"
    ],
    "wof:name":"Nagornoye",
    "wof:placetype":"locality"
},
  "geometry": {"coordinates":[52.03823,54.88121999999999],"type":"Point"}
}