{
  "type": "Feature",
  "properties": {
    "gn:admin1_code":"77",
    "gn:asciiname":"Ivanovskoye",
    "gn:country_code":"RU",
    "gn:dem":149,
    "gn:feature_class":"P",
    "gn:feature_code":"PPL",
    "gn:name":"Ivanovskoye",
    "gn:population":0,
    "gn:timezone":"Europe/Moscow",
    "iso:country":"RU",
    "name:nor_x_preferred":[
        "Ivanovskoje"
    ],
    "name:rus_x_preferred":[
        "\u0418\u0432\u0430\u043d\u043e\u0432\u0441\u043a\u043e\u0435"
    ],
    "wof:name":"Ivanovskoye",
    "wof:placetype":"locality"
},
  "geometry": {"coordinates":[35.36692,56.37025],"type":"Point"}
}