{
  "type": "Feature",
  "properties": {
    "gn:admin1_code":"80.0",
    "gn:asciiname":"Andreyevtsy",
    "gn:country_code":"RU",
    "gn:dem":157,
    "gn:feature_class":"P",
    "gn:feature_code":"PPL",
    "gn:name":"Andreyevtsy",
    "gn:population":0,
    "gn:timezone":"Europe/Samara",
    "iso:country":"RU",
    "name:eng_x_preferred":[
        "Andreyevtsy"
    ],
    "name:nor_x_preferred":[
        "Andrejevtsy"
    ],
    "name:rus_x_preferred":[
        "\u0410\u043d\u0434\u0440\u0435\u0435\u0432\u0446\u044b"
    ],
    "name:und_x_variant":[
        "\u0410\u043d\u0434\u0440\u0435\u0435\u0432\u0446\u044b",
        "Andreyevtsy"
    ],
    "wof:name":"Andreyevtsy",
    "wof:placetype":"locality"
},
  "geometry": {"coordinates":[51.6613,57.4753],"type":"Point"}
}