{
  "type": "Feature",
  "properties": {
    "gn:admin1_code":"77",
    "gn:asciiname":"Novosel'tsy",
    "gn:country_code":"RU",
    "gn:dem":132,
    "gn:feature_class":"P",
    "gn:feature_code":"PPL",
    "gn:name":"Novosel\u2019tsy",
    "gn:population":0,
    "gn:timezone":"Europe/Moscow",
    "iso:country":"RU",
    "name:nor_x_preferred":[
        "Novoseltsy"
    ],
    "name:rus_x_preferred":[
        "\u041d\u043e\u0432\u043e\u0441\u0435\u043b\u044c\u0446\u044b"
    ],
    "name:und_x_variant":[
        "Novosel\u2019tsy"
    ],
    "wof:name":"Novosel'tsy",
    "wof:placetype":"locality"
},
  "geometry": {"coordinates":[35.60408,56.96345],"type":"Point"}
}