{
  "type": "Feature",
  "properties": {
    "gn:admin1_code":"81",
    "gn:asciiname":"Yenganayevo",
    "gn:country_code":"RU",
    "gn:dem":58,
    "gn:feature_class":"P",
    "gn:feature_code":"PPL",
    "gn:name":"Yenganayevo",
    "gn:population":0,
    "gn:timezone":"Europe/Ulyanovsk",
    "iso:country":"RU",
    "name:eng_x_preferred":[
        "Yenganayevo"
    ],
    "name:nor_x_preferred":[
        "Jenganajevo"
    ],
    "name:rus_x_preferred":[
        "\u0415\u043d\u0433\u0430\u043d\u0430\u0435\u0432\u043e"
    ],
    "wof:name":"Yenganayevo",
    "wof:placetype":"locality"
},
  "geometry": {"coordinates":[48.89667,54.43189],"type":"Point"}
}