{
  "type": "Feature",
  "properties": {
    "gn:admin1_code":"61.0",
    "gn:asciiname":"Malyy Dubovoy",
    "gn:country_code":"RU",
    "gn:dem":61,
    "gn:feature_class":"P",
    "gn:feature_code":"PPL",
    "gn:name":"Malyy Dubovoy",
    "gn:population":0,
    "gn:timezone":"Europe/Moscow",
    "iso:country":"RU",
    "wof:name":"Malyy Dubovoy",
    "wof:placetype":"locality"
},
  "geometry": {"coordinates":[41.50056,48.54833],"type":"Point"}
}