{
  "type": "Feature",
  "properties": {
    "gn:admin1_code":"37",
    "gn:asciiname":"Karavayevo",
    "gn:country_code":"RU",
    "gn:dem":113,
    "gn:feature_class":"P",
    "gn:feature_code":"PPL",
    "gn:name":"Karavayevo",
    "gn:population":0,
    "gn:timezone":"Europe/Moscow",
    "iso:country":"RU",
    "name:eng_x_preferred":[
        "Karavayevo"
    ],
    "name:nor_x_preferred":[
        "Karavajevo"
    ],
    "name:rus_x_preferred":[
        "\u041a\u0430\u0440\u0430\u0432\u0430\u0435\u0432\u043e"
    ],
    "wof:name":"Karavayevo",
    "wof:placetype":"locality"
},
  "geometry": {"coordinates":[41.07417,57.73639],"type":"Point"}
}