{
  "type": "Feature",
  "properties": {
    "gn:admin1_code":"10",
    "gn:asciiname":"Kul'nevo",
    "gn:country_code":"RU",
    "gn:dem":182,
    "gn:feature_class":"P",
    "gn:feature_code":"PPL",
    "gn:name":"Kul\u2019n\u00ebvo",
    "gn:population":0,
    "gn:timezone":"Europe/Moscow",
    "iso:country":"RU",
    "name:eng_x_preferred":[
        "Kul'n\u00ebvo"
    ],
    "name:nor_x_preferred":[
        "Kulnevo"
    ],
    "name:rus_x_preferred":[
        "\u041a\u0443\u043b\u044c\u043d\u0435\u0432\u043e"
    ],
    "name:rus_x_variant":[
        "\u041a\u0443\u043b\u044c\u043d\u0451\u0432\u043e"
    ],
    "name:und_x_variant":[
        "Kul\u2019n\u00ebvo"
    ],
    "wof:name":"Kul'nevo",
    "wof:placetype":"locality"
},
  "geometry": {"coordinates":[33.5364,53.1952],"type":"Point"}
}