{
  "type": "Feature",
  "properties": {
    "gn:admin1_code":"54",
    "gn:asciiname":"Stepanikha",
    "gn:country_code":"RU",
    "gn:dem":106,
    "gn:feature_class":"P",
    "gn:feature_code":"PPL",
    "gn:name":"Stepanikha",
    "gn:population":0,
    "gn:timezone":"Asia/Omsk",
    "iso:country":"RU",
    "name:rus_x_preferred":[
        "\u0421\u0442\u0435\u043f\u0430\u043d\u0438\u0445\u0430"
    ],
    "wof:name":"Stepanikha",
    "wof:placetype":"locality"
},
  "geometry": {"coordinates":[71.03333000000001,56.38333000000001],"type":"Point"}
}