{
  "type": "Feature",
  "properties": {
    "gn:admin1_code":"42",
    "gn:asciiname":"Panevo",
    "gn:country_code":"RU",
    "gn:dem":32,
    "gn:feature_class":"P",
    "gn:feature_code":"PPL",
    "gn:name":"Pan\u00ebvo",
    "gn:population":0,
    "gn:timezone":"Europe/Moscow",
    "iso:country":"RU",
    "name:rus_x_preferred":[
        "\u041f\u0430\u043d\u0451\u0432\u043e"
    ],
    "name:und_x_variant":[
        "Pan\u00ebvo",
        "\u041f\u0430\u043d\u0451\u0432\u043e"
    ],
    "wof:name":"Panevo",
    "wof:placetype":"locality"
},
  "geometry": {"coordinates":[32.37309,59.79618000000001],"type":"Point"}
}