{
  "type": "Feature",
  "properties": {
    "gn:admin1_code":"21",
    "gn:asciiname":"Petel'nikovo",
    "gn:country_code":"RU",
    "gn:dem":111,
    "gn:feature_class":"P",
    "gn:feature_code":"PPL",
    "gn:name":"Petel\u2019nikovo",
    "gn:population":0,
    "gn:timezone":"Europe/Moscow",
    "iso:country":"RU",
    "name:nor_x_preferred":[
        "Petelnikovo"
    ],
    "name:rus_x_preferred":[
        "\u041f\u0435\u0442\u0435\u043b\u044c\u043d\u0438\u043a\u043e\u0432\u043e"
    ],
    "name:und_x_variant":[
        "Petelinikovo",
        "Petel\u2019nikovo"
    ],
    "wof:name":"Petel'nikovo",
    "wof:placetype":"locality"
},
  "geometry": {"coordinates":[42.08943,56.986],"type":"Point"}
}