{
  "type": "Feature",
  "properties": {
    "gn:admin1_code":"54",
    "gn:asciiname":"Barvenovka",
    "gn:country_code":"RU",
    "gn:dem":119,
    "gn:feature_class":"P",
    "gn:feature_code":"PPL",
    "gn:name":"Barvenovka",
    "gn:population":0,
    "gn:timezone":"Asia/Omsk",
    "iso:country":"RU",
    "name:eng_x_preferred":[
        "Barvenovka"
    ],
    "name:nor_x_preferred":[
        "Barvenovka"
    ],
    "name:rus_x_preferred":[
        "\u0411\u0430\u0440\u0432\u0435\u043d\u043e\u0432\u043a\u0430"
    ],
    "name:und_x_variant":[
        "Barvenkovski",
        "Barvenkovo",
        "\u0411\u0430\u0440\u0432\u0435\u043d\u043e\u0432\u043a\u0430",
        "Barvenovka"
    ],
    "wof:name":"Barvenovka",
    "wof:placetype":"locality"
},
  "geometry": {"coordinates":[71.56639,54.13111],"type":"Point"}
}