{
  "type": "Feature",
  "properties": {
    "gn:admin1_code":"59",
    "gn:asciiname":"Grushevoye",
    "gn:country_code":"RU",
    "gn:dem":82,
    "gn:feature_class":"P",
    "gn:feature_code":"PPL",
    "gn:name":"Grushevoye",
    "gn:population":0,
    "gn:timezone":"Asia/Vladivostok",
    "iso:country":"RU",
    "name:rus_x_preferred":[
        "\u0413\u0440\u0443\u0448\u0435\u0432\u043e\u0435"
    ],
    "name:und_x_variant":[
        "\u0413\u0440\u0443\u0448\u0435\u0432\u043e\u0435"
    ],
    "wof:name":"Grushevoye",
    "wof:placetype":"locality"
},
  "geometry": {"coordinates":[133.61508999999998,45.82944000000001],"type":"Point"}
}