{
  "type": "Feature",
  "properties": {
    "gn:admin1_code":"47",
    "gn:asciiname":"Ostrozhki",
    "gn:country_code":"RU",
    "gn:dem":180,
    "gn:feature_class":"P",
    "gn:feature_code":"PPL",
    "gn:name":"Ostrozhki",
    "gn:population":0,
    "gn:timezone":"Europe/Moscow",
    "iso:country":"RU",
    "name:rus_x_preferred":[
        "\u041e\u0441\u0442\u0440\u043e\u0436\u043a\u0438"
    ],
    "name:und_x_variant":[
        "Ostrazhki",
        "Ostrozhki"
    ],
    "wof:name":"Ostrozhki",
    "wof:placetype":"locality"
},
  "geometry": {"coordinates":[37.78144,55.21644000000001],"type":"Point"}
}