{
  "type": "Feature",
  "properties": {
    "gn:admin1_code":"52",
    "gn:asciiname":"Ostov",
    "gn:country_code":"RU",
    "gn:dem":81,
    "gn:feature_class":"P",
    "gn:feature_code":"PPL",
    "gn:name":"Ostov",
    "gn:population":0,
    "gn:timezone":"Europe/Moscow",
    "iso:country":"RU",
    "name:rus_x_preferred":[
        "\u041e\u0441\u0442\u043e\u0432"
    ],
    "name:und_x_variant":[
        "\u041e\u0441\u0442\u043e\u0432"
    ],
    "wof:name":"Ostov",
    "wof:placetype":"locality"
},
  "geometry": {"coordinates":[30.43333,58.63333000000001],"type":"Point"}
}