{
  "type": "Feature",
  "properties": {
    "gn:admin1_code":"42",
    "gn:asciiname":"Kazychenskaya",
    "gn:country_code":"RU",
    "gn:dem":187,
    "gn:feature_class":"P",
    "gn:feature_code":"PPL",
    "gn:name":"Kazychenskaya",
    "gn:population":0,
    "gn:timezone":"Europe/Moscow",
    "iso:country":"RU",
    "name:rus_x_preferred":[
        "\u041a\u0430\u0437\u044b\u0447\u0435\u043d\u0441\u043a\u0430\u044f"
    ],
    "wof:name":"Kazychenskaya",
    "wof:placetype":"locality"
},
  "geometry": {"coordinates":[35.0587,60.39615],"type":"Point"}
}