{
  "type": "Feature",
  "properties": {
    "gn:admin1_code":"54",
    "gn:asciiname":"Sulu-Terek",
    "gn:country_code":"RU",
    "gn:dem":120,
    "gn:feature_class":"P",
    "gn:feature_code":"PPL",
    "gn:name":"Sulu-Terek",
    "gn:population":0,
    "gn:timezone":"Asia/Omsk",
    "iso:country":"RU",
    "name:rus_x_preferred":[
        "\u0421\u0443\u043b\u0443-\u0422\u0435\u0440\u0435\u043a"
    ],
    "name:und_x_variant":[
        "\u0421\u0443\u043b\u0443-\u0422\u0435\u0440\u0435\u043a",
        "Aul Nomer Dva"
    ],
    "wof:name":"Sulu-Terek",
    "wof:placetype":"locality"
},
  "geometry": {"coordinates":[71.5547,55.6537],"type":"Point"}
}