{
  "type": "Feature",
  "properties": {
    "gn:admin1_code":"47",
    "gn:asciiname":"Dubki",
    "gn:country_code":"RU",
    "gn:dem":139,
    "gn:feature_class":"P",
    "gn:feature_code":"PPL",
    "gn:name":"Dubki",
    "gn:population":63,
    "gn:timezone":"Europe/Moscow",
    "iso:country":"RU",
    "name:eng_x_preferred":[
        "Dubki"
    ],
    "name:rus_x_preferred":[
        "\u0414\u0443\u0431\u043a\u0438"
    ],
    "wof:name":"Dubki",
    "wof:placetype":"locality",
    "wof:population":63
},
  "geometry": {"coordinates":[37.61813,56.59101999999999],"type":"Point"}
}