{
  "type": "Feature",
  "properties": {
    "gn:admin1_code":"80",
    "gn:asciiname":"Novaya Kazmaska",
    "gn:country_code":"RU",
    "gn:dem":121,
    "gn:feature_class":"P",
    "gn:feature_code":"PPL",
    "gn:name":"Novaya Kazmaska",
    "gn:population":0,
    "gn:timezone":"Europe/Samara",
    "iso:country":"RU",
    "name:eng_x_preferred":[
        "Novaya Kazmaska"
    ],
    "name:rus_x_preferred":[
        "\u041d\u043e\u0432.\u041a\u0430\u0437\u043c\u0430\u0441\u043a\u0430"
    ],
    "name:rus_x_variant":[
        "\u041d\u043e\u0432\u0430\u044f \u041a\u0430\u0437\u043c\u0430\u0441\u043a\u0430"
    ],
    "name:udm_x_preferred":[
        "Vyl' Kaz'mas"
    ],
    "name:und_x_variant":[
        "Novaya Kazamaska",
        "Novaya Kazmaska"
    ],
    "wof:name":"Novaya Kazmaska",
    "wof:placetype":"locality"
},
  "geometry": {"coordinates":[53.53211,56.8236],"type":"Point"}
}