{
  "type": "Feature",
  "properties": {
    "gn:admin1_code":"51",
    "gn:asciiname":"Tret'ye Pole",
    "gn:country_code":"RU",
    "gn:dem":141,
    "gn:feature_class":"P",
    "gn:feature_code":"PPL",
    "gn:name":"Tret\u2019ye Pole",
    "gn:population":0,
    "gn:timezone":"Europe/Moscow",
    "iso:country":"RU",
    "name:rus_x_preferred":[
        "\u0422\u0440\u0435\u0442\u044c\u0435 \u041f\u043e\u043b\u0435"
    ],
    "name:und_x_variant":[
        "Tret\u2019ye Pole"
    ],
    "wof:name":"Tret'ye Pole",
    "wof:placetype":"locality"
},
  "geometry": {"coordinates":[42.8022,55.912],"type":"Point"}
}