{
  "type": "Feature",
  "properties": {
    "gn:admin1_code":"83",
    "gn:asciiname":"Gruzdevo",
    "gn:country_code":"RU",
    "gn:dem":79,
    "gn:feature_class":"P",
    "gn:feature_code":"PPL",
    "gn:name":"Gruzdevo",
    "gn:population":0,
    "gn:timezone":"Europe/Moscow",
    "iso:country":"RU",
    "name:und_x_variant":[
        "Gruzdeva",
        "Gruzdevskiy Pos\u00eblok",
        "Gruzdevo"
    ],
    "wof:name":"Gruzdevo",
    "wof:placetype":"locality"
},
  "geometry": {"coordinates":[42.75376,56.13465],"type":"Point"}
}