{
  "type": "Feature",
  "properties": {
    "gn:admin1_code":"05",
    "gn:asciiname":"Krestovozdvizhenka",
    "gn:country_code":"RU",
    "gn:dem":155,
    "gn:feature_class":"P",
    "gn:feature_code":"PPL",
    "gn:name":"Krestovozdvizhenka",
    "gn:population":0,
    "gn:timezone":"Asia/Yakutsk",
    "iso:country":"RU",
    "name:eng_x_preferred":[
        "Krestovozdvizhenka"
    ],
    "name:nor_x_preferred":[
        "Krestovozdvizjenka"
    ],
    "name:rus_x_preferred":[
        "\u041a\u0440\u0435\u0441\u0442\u043e\u0432\u043e\u0437\u0434\u0432\u0438\u0436\u0435\u043d\u043a\u0430"
    ],
    "name:und_x_variant":[
        "Nishniy-U\u2019rtuy",
        "Krestovozdvizhenskiy",
        "Nizhniy Urtuy",
        "Krestovozdvizhenskoye",
        "Nizhniy Ukhtuy",
        "\u041a\u0440\u0435\u0441\u0442\u043e\u0432\u043e\u0437\u0434\u0432\u0438\u0436\u0435\u043d\u043a\u0430",
        "Krestovozdvizhenka"
    ],
    "wof:name":"Krestovozdvizhenka",
    "wof:placetype":"locality"
},
  "geometry": {"coordinates":[127.96778999999999,49.77529000000001],"type":"Point"}
}