{
  "type": "Feature",
  "properties": {
    "gn:admin1_code":"69",
    "gn:asciiname":"Staro-Prigarina",
    "gn:country_code":"RU",
    "gn:dem":183,
    "gn:feature_class":"P",
    "gn:feature_code":"PPL",
    "gn:name":"Staro-Prigarina",
    "gn:population":0,
    "gn:timezone":"Europe/Moscow",
    "iso:country":"RU",
    "name:rus_x_preferred":[
        "\u0421\u0442\u0430\u0440\u043e-\u041f\u0440\u0438\u0433\u0430\u0440\u0438\u043d\u0430"
    ],
    "name:und_x_variant":[
        "Staro-Prigarino",
        "Staro-Prigarina",
        "\u0421\u0442\u0430\u0440\u043e-\u041f\u0440\u0438\u0433\u0430\u0440\u0438\u043d\u0430"
    ],
    "wof:name":"Staro-Prigarina",
    "wof:placetype":"locality"
},
  "geometry": {"coordinates":[31.88345,55.55999],"type":"Point"}
}