{
  "type": "Feature",
  "properties": {
    "gn:admin1_code":"77",
    "gn:asciiname":"Volkovo",
    "gn:country_code":"RU",
    "gn:dem":165,
    "gn:feature_class":"P",
    "gn:feature_code":"PPL",
    "gn:name":"Volkovo",
    "gn:population":0,
    "gn:timezone":"Europe/Moscow",
    "iso:country":"RU",
    "name:rus_x_preferred":[
        "\u0412\u043e\u043b\u043a\u043e\u0432\u043e"
    ],
    "name:und_x_variant":[
        "\u0412\u043e\u043b\u043a\u043e\u0432\u043e"
    ],
    "wof:name":"Volkovo",
    "wof:placetype":"locality"
},
  "geometry": {"coordinates":[36.71667,57.63333000000001],"type":"Point"}
}