{
  "type": "Feature",
  "properties": {
    "gn:admin1_code":"69",
    "gn:asciiname":"Khokhly",
    "gn:country_code":"RU",
    "gn:dem":208,
    "gn:feature_class":"P",
    "gn:feature_code":"PPL",
    "gn:name":"Khokhly",
    "gn:population":0,
    "gn:timezone":"Europe/Moscow",
    "iso:country":"RU",
    "name:rus_x_preferred":[
        "\u0425\u043e\u0445\u043b\u044b"
    ],
    "wof:name":"Khokhly",
    "wof:placetype":"locality"
},
  "geometry": {"coordinates":[32.13972,55.51139000000001],"type":"Point"}
}