{
  "type": "Feature",
  "properties": {
    "gn:admin1_code":"17",
    "gn:asciiname":"Inchkha",
    "gn:country_code":"RU",
    "gn:dem":250,
    "gn:feature_class":"P",
    "gn:feature_code":"PPL",
    "gn:name":"Inchkha",
    "gn:population":0,
    "gn:timezone":"Europe/Moscow",
    "iso:country":"RU",
    "name:rus_x_preferred":[
        "\u0418\u043d\u0447\u0445\u0430"
    ],
    "name:und_x_variant":[
        "Inchka",
        "Inchkha"
    ],
    "wof:name":"Inchkha",
    "wof:placetype":"locality"
},
  "geometry": {"coordinates":[46.76615,43.0969],"type":"Point"}
}