{
  "type": "Feature",
  "properties": {
    "gn:admin1_code":"34",
    "gn:asciiname":"Kostyurko",
    "gn:cc2":"RU",
    "gn:country_code":"RU",
    "gn:dem":92,
    "gn:feature_class":"P",
    "gn:feature_code":"PPL",
    "gn:name":"Kostyurko",
    "gn:population":0,
    "gn:timezone":"Europe/Moscow",
    "iso:country":"RU",
    "name:und_x_variant":[
        "Kostyuk",
        "Kostjurko"
    ],
    "wof:name":"Kostyurko",
    "wof:placetype":"locality"
},
  "geometry": {"coordinates":[56.86666999999999,66.83333],"type":"Point"}
}