{
  "type": "Feature",
  "properties": {
    "gn:admin1_code":"1",
    "gn:asciiname":"Ternovskiy",
    "gn:country_code":"RU",
    "gn:dem":311,
    "gn:feature_class":"P",
    "gn:feature_code":"PPL",
    "gn:name":"Ternovskiy",
    "gn:population":0,
    "gn:timezone":"Europe/Moscow",
    "iso:country":"RU",
    "wof:name":"Ternovskiy",
    "wof:placetype":"locality"
},
  "geometry": {"coordinates":[39.88944,44.43194],"type":"Point"}
}