{
  "type": "Feature",
  "properties": {
    "gn:admin1_code":"42",
    "gn:asciiname":"Lukhtuy",
    "gn:country_code":"RU",
    "gn:dem":90,
    "gn:feature_class":"P",
    "gn:feature_code":"PPL",
    "gn:name":"Lukhtuy",
    "gn:population":0,
    "gn:timezone":"Europe/Moscow",
    "iso:country":"RU",
    "name:rus_x_preferred":[
        "\u041b\u0443\u0445\u0442\u0443\u0439"
    ],
    "name:und_x_variant":[
        "\u041b\u0443\u0445\u0442\u0443\u0439"
    ],
    "wof:name":"Lukhtuy",
    "wof:placetype":"locality"
},
  "geometry": {"coordinates":[33.85,59.75],"type":"Point"}
}