{
  "type": "Feature",
  "properties": {
    "gn:admin1_code":"93",
    "gn:asciiname":"Gutay",
    "gn:country_code":"RU",
    "gn:dem":689,
    "gn:feature_class":"P",
    "gn:feature_code":"PPL",
    "gn:name":"Gutay",
    "gn:population":0,
    "gn:timezone":"Asia/Chita",
    "iso:country":"RU",
    "name:eng_x_preferred":[
        "Gutay"
    ],
    "name:nor_x_preferred":[
        "Gutaj"
    ],
    "name:rus_x_preferred":[
        "\u0413\u0443\u0442\u0430\u0439"
    ],
    "name:und_x_variant":[
        "Chikoy",
        "Gutai",
        "\u0413\u0443\u0442\u0430\u0439",
        "Gutay"
    ],
    "wof:name":"Gutay",
    "wof:placetype":"locality"
},
  "geometry": {"coordinates":[108.19708,49.99626],"type":"Point"}
}