{
  "type": "Feature",
  "properties": {
    "gn:admin1_code":"85",
    "gn:asciiname":"Tikhonovo",
    "gn:country_code":"RU",
    "gn:dem":122,
    "gn:feature_class":"P",
    "gn:feature_code":"PPL",
    "gn:name":"Tikhonovo",
    "gn:population":0,
    "gn:timezone":"Europe/Moscow",
    "iso:country":"RU",
    "name:rus_x_preferred":[
        "\u0422\u0438\u0445\u043e\u043d\u043e\u0432\u043e"
    ],
    "wof:name":"Tikhonovo",
    "wof:placetype":"locality"
},
  "geometry": {"coordinates":[38.34815,59.83506],"type":"Point"}
}