{
  "type": "Feature",
  "properties": {
    "gn:admin1_code":"61",
    "gn:asciiname":"Kupriyanov",
    "gn:country_code":"RU",
    "gn:dem":78,
    "gn:feature_class":"P",
    "gn:feature_code":"PPL",
    "gn:name":"Kupriyanov",
    "gn:population":0,
    "gn:timezone":"Europe/Moscow",
    "iso:country":"RU",
    "name:rus_x_preferred":[
        "\u041a\u0443\u043f\u0440\u0438\u044f\u043d\u043e\u0432"
    ],
    "name:und_x_variant":[
        "\u041a\u0443\u043f\u0440\u0438\u044f\u043d\u043e\u0432"
    ],
    "wof:name":"Kupriyanov",
    "wof:placetype":"locality"
},
  "geometry": {"coordinates":[43.54528,46.99278],"type":"Point"}
}