{
  "type": "Feature",
  "properties": {
    "gn:admin1_code":"71.0",
    "gn:asciiname":"Yeremina",
    "gn:country_code":"RU",
    "gn:dem":69,
    "gn:feature_class":"P",
    "gn:feature_code":"PPL",
    "gn:name":"Yeremina",
    "gn:population":0,
    "gn:timezone":"Asia/Yekaterinburg",
    "iso:country":"RU",
    "name:rus_x_preferred":[
        "\u0415\u0440\u0435\u043c\u0438\u043d\u0430"
    ],
    "wof:name":"Yeremina",
    "wof:placetype":"locality"
},
  "geometry": {"coordinates":[63.31133000000001,57.58897],"type":"Point"}
}