{
  "type": "Feature",
  "properties": {
    "gn:admin1_code":"34",
    "gn:asciiname":"Tobysh",
    "gn:cc2":"RU",
    "gn:country_code":"RU",
    "gn:dem":150,
    "gn:feature_class":"P",
    "gn:feature_code":"PPL",
    "gn:name":"Tobysh",
    "gn:population":0,
    "gn:timezone":"Europe/Moscow",
    "iso:country":"RU",
    "name:und_x_variant":[
        "Tobish",
        "Tobysh"
    ],
    "wof:name":"Tobysh",
    "wof:placetype":"locality"
},
  "geometry": {"coordinates":[52.83333,63.31667],"type":"Point"}
}