{
  "type": "Feature",
  "properties": {
    "gn:admin1_code":"61",
    "gn:asciiname":"Krupskiy",
    "gn:country_code":"RU",
    "gn:dem":69,
    "gn:feature_class":"P",
    "gn:feature_code":"PPL",
    "gn:name":"Krupskiy",
    "gn:population":0,
    "gn:timezone":"Europe/Moscow",
    "iso:country":"RU",
    "name:eng_x_preferred":[
        "Krupskiy"
    ],
    "name:nor_x_preferred":[
        "Krupskij"
    ],
    "name:rus_x_preferred":[
        "\u041a\u0440\u0443\u043f\u0441\u043a\u0438\u0439"
    ],
    "name:und_x_variant":[
        "Krupskoy",
        "\u041a\u0440\u0443\u043f\u0441\u043a\u0438\u0439",
        "Krupskiy"
    ],
    "wof:name":"Krupskiy",
    "wof:placetype":"locality"
},
  "geometry": {"coordinates":[41.90503,46.18828],"type":"Point"}
}