{
  "type": "Feature",
  "properties": {
    "gn:admin1_code":"71",
    "gn:asciiname":"Moskalka",
    "gn:country_code":"RU",
    "gn:dem":128,
    "gn:feature_class":"P",
    "gn:feature_code":"PPL",
    "gn:name":"Moskalka",
    "gn:population":0,
    "gn:timezone":"Asia/Yekaterinburg",
    "iso:country":"RU",
    "name:eng_x_preferred":[
        "Moskalka"
    ],
    "name:nor_x_preferred":[
        "Maskalka"
    ],
    "name:rus_x_preferred":[
        "\u041c\u0430\u0441\u043a\u0430\u043b\u043a\u0430"
    ],
    "name:rus_x_variant":[
        "\u041c\u043e\u0441\u043a\u0430\u043b\u043a\u0430"
    ],
    "name:und_x_variant":[
        "Moskalna"
    ],
    "wof:name":"Moskalka",
    "wof:placetype":"locality"
},
  "geometry": {"coordinates":[61.28209,58.33577],"type":"Point"}
}