{
  "type": "Feature",
  "properties": {
    "gn:admin1_code":"8.0",
    "gn:asciiname":"Bol'shegordino",
    "gn:country_code":"RU",
    "gn:dem":176,
    "gn:feature_class":"P",
    "gn:feature_code":"PPL",
    "gn:name":"Bol\u2019shegordino",
    "gn:population":0,
    "gn:timezone":"Asia/Yekaterinburg",
    "iso:country":"RU",
    "name:rus_x_preferred":[
        "\u0411\u043e\u043b\u044c\u0448\u0435\u0433\u043e\u0440\u0434\u0438\u043d\u043e"
    ],
    "name:und_x_variant":[
        "Bol\u2019shoye Gordino",
        "Bol\u2019shegordino"
    ],
    "wof:name":"Bol'shegordino",
    "wof:placetype":"locality"
},
  "geometry": {"coordinates":[56.69676,56.21034],"type":"Point"}
}