{
  "type": "Feature",
  "properties": {
    "gn:admin1_code":"64",
    "gn:asciiname":"Konbuusu",
    "gn:country_code":"RU",
    "gn:dem":39,
    "gn:feature_class":"P",
    "gn:feature_code":"PPL",
    "gn:name":"Konbuusu",
    "gn:population":0,
    "gn:timezone":"Asia/Tokyo",
    "iso:country":"RU",
    "name:jpn_x_preferred":[
        "\u30b3\u30f3\u30d6\u30a6\u30b9"
    ],
    "name:jpn_x_variant":[
        "\u3053\u3093\u3076\u3046\u3059"
    ],
    "name:und_x_variant":[
        "Povorotnaya",
        "Kombuusu",
        "Konbuusu"
    ],
    "wof:name":"Konbuusu",
    "wof:placetype":"locality"
},
  "geometry": {"coordinates":[146.65360999999999,43.71472],"type":"Point"}
}