{
  "type": "Feature",
  "properties": {
    "gn:admin1_code":"70.0",
    "gn:asciiname":"Zarya Sotsializma",
    "gn:country_code":"RU",
    "gn:dem":11,
    "gn:feature_class":"P",
    "gn:feature_code":"PPL",
    "gn:name":"Zarya Sotsializma",
    "gn:population":0,
    "gn:timezone":"Europe/Moscow",
    "iso:country":"RU",
    "wof:name":"Zarya Sotsializma",
    "wof:placetype":"locality"
},
  "geometry": {"coordinates":[45.50167,45.0225],"type":"Point"}
}