{
  "type": "Feature",
  "properties": {
    "gn:admin1_code":"38",
    "gn:asciiname":"Prokhladnyy",
    "gn:cc2":"RU",
    "gn:country_code":"RU",
    "gn:dem":583,
    "gn:feature_class":"P",
    "gn:feature_code":"PPL",
    "gn:name":"Prokhladnyy",
    "gn:population":0,
    "gn:timezone":"Europe/Moscow",
    "iso:country":"RU",
    "name:und_x_variant":[
        "Krasnoye Znamya"
    ],
    "wof:name":"Prokhladnyy",
    "wof:placetype":"locality"
},
  "geometry": {"coordinates":[41.54417,44.48306],"type":"Point"}
}