{
  "type": "Feature",
  "properties": {
    "gn:admin1_code":"75",
    "gn:asciiname":"Lugovskoye",
    "gn:cc2":"RU",
    "gn:country_code":"RU",
    "gn:dem":59,
    "gn:feature_class":"P",
    "gn:feature_code":"PPL",
    "gn:name":"Lugovskoye",
    "gn:population":0,
    "gn:timezone":"Asia/Tomsk",
    "iso:country":"RU",
    "name:eng_x_preferred":[
        "Lugovskoye"
    ],
    "name:nor_x_preferred":[
        "Lugovskoje"
    ],
    "name:rus_x_preferred":[
        "\u041b\u0443\u0433\u043e\u0432\u0441\u043a\u043e\u0435"
    ],
    "name:und_x_variant":[
        "Kuz\u2019mina",
        "Lugovskaya",
        "Lugovaya",
        "\u041b\u0443\u0433\u043e\u0432\u0441\u043a\u043e\u0435",
        "Lugovskoye"
    ],
    "wof:name":"Lugovskoye",
    "wof:placetype":"locality"
},
  "geometry": {"coordinates":[81.64166999999998,58.90194],"type":"Point"}
}