{
  "type": "Feature",
  "properties": {
    "gn:admin1_code":"63",
    "gn:asciiname":"Evenki",
    "gn:country_code":"RU",
    "gn:dem":206,
    "gn:feature_class":"P",
    "gn:feature_code":"PPL",
    "gn:name":"Evenki",
    "gn:population":0,
    "gn:timezone":"Asia/Vladivostok",
    "iso:country":"RU",
    "name:bar_x_preferred":[
        "Evenki"
    ],
    "name:deu_x_preferred":[
        "Evenki"
    ],
    "name:fra_x_preferred":[
        "Evenk"
    ],
    "name:rus_x_preferred":[
        "\u042d\u0432\u0435\u043d\u043a\u0438"
    ],
    "name:spa_x_preferred":[
        "Evenki"
    ],
    "name:tur_x_preferred":[
        "Evenki"
    ],
    "name:und_x_variant":[
        "\u042d\u0432\u0435\u043d\u043a\u0438"
    ],
    "wof:name":"Evenki",
    "wof:placetype":"locality"
},
  "geometry": {"coordinates":[132.81666999999999,59.68333000000001],"type":"Point"}
}