{
  "type": "Feature",
  "properties": {
    "gn:admin1_code":"13",
    "gn:asciiname":"Karsy",
    "gn:country_code":"RU",
    "gn:dem":222,
    "gn:feature_class":"P",
    "gn:feature_code":"PPL",
    "gn:name":"Karsy",
    "gn:population":0,
    "gn:timezone":"Asia/Yekaterinburg",
    "iso:country":"RU",
    "name:eng_x_preferred":[
        "Karsy"
    ],
    "name:nor_x_preferred":[
        "Karsy"
    ],
    "name:rus_x_preferred":[
        "\u041a\u0430\u0440\u0441\u044b"
    ],
    "name:und_x_variant":[
        "Krasinskiy",
        "Karsinskiy",
        "\u041a\u0430\u0440\u0441\u044b",
        "Karsy"
    ],
    "wof:name":"Karsy",
    "wof:placetype":"locality"
},
  "geometry": {"coordinates":[61.4156,54.2499],"type":"Point"}
}