{
  "type": "Feature",
  "properties": {
    "gn:admin1_code":"55",
    "gn:asciiname":"Pyatiozerka",
    "gn:country_code":"RU",
    "gn:dem":228,
    "gn:feature_class":"P",
    "gn:feature_code":"PPL",
    "gn:name":"Pyatioz\u00ebrka",
    "gn:population":0,
    "gn:timezone":"Asia/Yekaterinburg",
    "iso:country":"RU",
    "name:rus_x_preferred":[
        "\u041f\u044f\u0442\u0438\u043e\u0437\u0451\u0440\u043a\u0430"
    ],
    "name:und_x_variant":[
        "Pyatioz\u00ebrka"
    ],
    "wof:name":"Pyatiozerka",
    "wof:placetype":"locality"
},
  "geometry": {"coordinates":[54.61666999999999,52.16667],"type":"Point"}
}