{
  "type": "Feature",
  "properties": {
    "gn:admin1_code":"41.0",
    "gn:asciiname":"Kur'yanov",
    "gn:country_code":"RU",
    "gn:dem":193,
    "gn:feature_class":"P",
    "gn:feature_code":"PPL",
    "gn:name":"Kur\u2019yanov",
    "gn:population":0,
    "gn:timezone":"Europe/Moscow",
    "iso:country":"RU",
    "name:rus_x_preferred":[
        "\u041a\u0443\u0440\u044c\u044f\u043d\u043e\u0432"
    ],
    "name:und_x_variant":[
        "Kur\u2019yanov",
        "\u041a\u0443\u0440\u044c\u044f\u043d\u043e\u0432"
    ],
    "wof:name":"Kur'yanov",
    "wof:placetype":"locality"
},
  "geometry": {"coordinates":[35.7738,51.592],"type":"Point"}
}