{
  "type": "Feature",
  "properties": {
    "gn:admin1_code":"76",
    "gn:asciiname":"Spasskoye-Durnovo",
    "gn:country_code":"RU",
    "gn:dem":229,
    "gn:feature_class":"P",
    "gn:feature_code":"PPL",
    "gn:name":"Spasskoye-Durnovo",
    "gn:population":0,
    "gn:timezone":"Europe/Moscow",
    "iso:country":"RU",
    "name:rus_x_preferred":[
        "\u0421\u043f\u0430\u0441\u0441\u043a\u043e\u0435-\u0414\u0443\u0440\u043d\u043e\u0432\u043e"
    ],
    "name:und_x_variant":[
        "\u0421\u043f\u0430\u0441\u0441\u043a\u043e\u0435-\u0414\u0443\u0440\u043d\u043e\u0432\u043e"
    ],
    "wof:name":"Spasskoye-Durnovo",
    "wof:placetype":"locality"
},
  "geometry": {"coordinates":[37.42278,53.3524],"type":"Point"}
}