{
  "type": "Feature",
  "properties": {
    "gn:admin1_code":"52",
    "gn:asciiname":"Lapushnitsy",
    "gn:country_code":"RU",
    "gn:dem":68,
    "gn:feature_class":"P",
    "gn:feature_code":"PPL",
    "gn:name":"Lapushnitsy",
    "gn:population":0,
    "gn:timezone":"Europe/Moscow",
    "iso:country":"RU",
    "name:rus_x_preferred":[
        "\u041b\u0430\u043f\u0443\u0448\u043d\u0438\u0446\u044b"
    ],
    "name:und_x_variant":[
        "\u041b\u0430\u043f\u0443\u0448\u043d\u0438\u0446\u044b"
    ],
    "wof:name":"Lapushnitsy",
    "wof:placetype":"locality"
},
  "geometry": {"coordinates":[30.10275,58.4591],"type":"Point"}
}