{
  "type": "Feature",
  "properties": {
    "gn:admin1_code":"78",
    "gn:asciiname":"Patrusheva",
    "gn:country_code":"RU",
    "gn:dem":84,
    "gn:feature_class":"P",
    "gn:feature_code":"PPL",
    "gn:name":"Patrusheva",
    "gn:population":0,
    "gn:timezone":"Asia/Yekaterinburg",
    "iso:country":"RU",
    "name:rus_x_preferred":[
        "\u041f\u0430\u0442\u0440\u0443\u0448\u0435\u0432\u0430"
    ],
    "name:und_x_variant":[
        "\u041f\u0430\u0442\u0440\u0443\u0448\u0435\u0432\u0430"
    ],
    "wof:name":"Patrusheva",
    "wof:placetype":"locality"
},
  "geometry": {"coordinates":[65.5343,57.0932],"type":"Point"}
}