{
  "type": "Feature",
  "properties": {
    "gn:admin1_code":"42",
    "gn:asciiname":"Vagoshka",
    "gn:country_code":"RU",
    "gn:dem":70,
    "gn:feature_class":"P",
    "gn:feature_code":"PPL",
    "gn:name":"Vagoshka",
    "gn:population":0,
    "gn:timezone":"Europe/Moscow",
    "iso:country":"RU",
    "name:rus_x_preferred":[
        "\u0412\u0430\u0433\u043e\u0448\u043a\u0430"
    ],
    "wof:name":"Vagoshka",
    "wof:placetype":"locality"
},
  "geometry": {"coordinates":[28.7736,58.8805],"type":"Point"}
}