{
  "type": "Feature",
  "properties": {
    "gn:admin1_code":"62.0",
    "gn:asciiname":"Bol'shaya Lubyanka",
    "gn:country_code":"RU",
    "gn:dem":165,
    "gn:feature_class":"P",
    "gn:feature_code":"PPL",
    "gn:name":"Bol\u2019shaya Lubyanka",
    "gn:population":0,
    "gn:timezone":"Europe/Moscow",
    "iso:country":"RU",
    "name:rus_x_preferred":[
        "\u0411\u043e\u043b\u044c\u0448\u0430\u044f \u041b\u0443\u0431\u044f\u043d\u043a\u0430"
    ],
    "name:und_x_variant":[
        "Bol\u2019shaya Lubyanka"
    ],
    "wof:name":"Bol'shaya Lubyanka",
    "wof:placetype":"locality"
},
  "geometry": {"coordinates":[39.3532,54.2803],"type":"Point"}
}