{
  "type": "Feature",
  "properties": {
    "gn:admin1_code":"47",
    "gn:asciiname":"Korsakovo",
    "gn:country_code":"RU",
    "gn:dem":193,
    "gn:feature_class":"P",
    "gn:feature_code":"PPL",
    "gn:name":"Korsakovo",
    "gn:population":0,
    "gn:timezone":"Europe/Moscow",
    "iso:country":"RU",
    "name:rus_x_preferred":[
        "\u041a\u043e\u0440\u0441\u0430\u043a\u043e\u0432\u043e"
    ],
    "name:und_x_variant":[
        "\u041a\u043e\u0440\u0441\u0430\u043a\u043e\u0432\u043e"
    ],
    "wof:name":"Korsakovo",
    "wof:placetype":"locality"
},
  "geometry": {"coordinates":[36.59671,55.86848000000001],"type":"Point"}
}