{
  "type": "Feature",
  "properties": {
    "gn:admin1_code":"60",
    "gn:asciiname":"Panomka",
    "gn:country_code":"RU",
    "gn:dem":71,
    "gn:feature_class":"P",
    "gn:feature_code":"PPL",
    "gn:name":"Panomka",
    "gn:population":0,
    "gn:timezone":"Europe/Moscow",
    "iso:country":"RU",
    "name:rus_x_preferred":[
        "\u041f\u0430\u043d\u043e\u043c\u043a\u0430"
    ],
    "name:und_x_variant":[
        "\u041f\u0430\u043d\u043e\u043c\u043a\u0430"
    ],
    "wof:name":"Panomka",
    "wof:placetype":"locality"
},
  "geometry": {"coordinates":[30.16185,57.89564],"type":"Point"}
}