{
  "type": "Feature",
  "properties": {
    "gn:admin1_code":"60",
    "gn:asciiname":"Ul'diga",
    "gn:country_code":"RU",
    "gn:dem":70,
    "gn:feature_class":"P",
    "gn:feature_code":"PPL",
    "gn:name":"Ul\u2019diga",
    "gn:population":0,
    "gn:timezone":"Europe/Moscow",
    "iso:country":"RU",
    "name:rus_x_preferred":[
        "\u0423\u043b\u044c\u0434\u0438\u0433\u0430"
    ],
    "name:und_x_variant":[
        "Ul\u2019diga",
        "\u0423\u043b\u044c\u0434\u0438\u0433\u0430"
    ],
    "wof:name":"Ul'diga",
    "wof:placetype":"locality"
},
  "geometry": {"coordinates":[28.16462000000001,58.82985],"type":"Point"}
}