{
  "type": "Feature",
  "properties": {
    "gn:admin1_code":"60",
    "gn:asciiname":"Meshokol'",
    "gn:country_code":"RU",
    "gn:dem":33,
    "gn:feature_class":"P",
    "gn:feature_code":"PPL",
    "gn:name":"Meshokol\u2019",
    "gn:population":0,
    "gn:timezone":"Europe/Moscow",
    "iso:country":"RU",
    "name:rus_x_preferred":[
        "\u041c\u0435\u0448\u043e\u043a\u043e\u043b\u044c"
    ],
    "name:und_x_variant":[
        "Meshokol\u2019",
        "\u041c\u0435\u0448\u043e\u043a\u043e\u043b\u044c"
    ],
    "wof:name":"Meshokol'",
    "wof:placetype":"locality"
},
  "geometry": {"coordinates":[28.05249,58.09488],"type":"Point"}
}