{
  "type": "Feature",
  "properties": {
    "gn:admin1_code":"53",
    "gn:asciiname":"Dosino",
    "gn:country_code":"RU",
    "gn:dem":131,
    "gn:feature_class":"P",
    "gn:feature_code":"PPL",
    "gn:name":"Dosino",
    "gn:population":0,
    "gn:timezone":"Asia/Novosibirsk",
    "iso:country":"RU",
    "name:rus_x_preferred":[
        "\u0414\u043e\u0441\u0438\u043d\u043e"
    ],
    "wof:name":"Dosino",
    "wof:placetype":"locality"
},
  "geometry": {"coordinates":[78.63333,56.03333000000001],"type":"Point"}
}