{
  "type": "Feature",
  "properties": {
    "gn:admin1_code":"33.0",
    "gn:asciiname":"Grebenevshchina",
    "gn:country_code":"RU",
    "gn:dem":126,
    "gn:feature_class":"P",
    "gn:feature_code":"PPL",
    "gn:name":"Greben\u00ebvshchina",
    "gn:population":0,
    "gn:timezone":"Europe/Kirov",
    "iso:country":"RU",
    "name:rus_x_preferred":[
        "\u0413\u0440\u0435\u0431\u0435\u043d\u0451\u0432\u0449\u0438\u043d\u0430"
    ],
    "name:und_x_variant":[
        "Greben\u00ebvshchina",
        "\u0413\u0440\u0435\u0431\u0435\u043d\u0451\u0432\u0449\u0438\u043d\u0430"
    ],
    "wof:name":"Grebenevshchina",
    "wof:placetype":"locality"
},
  "geometry": {"coordinates":[48.45662,58.63873],"type":"Point"}
}