{
  "type": "Feature",
  "properties": {
    "gn:admin1_code":"77.0",
    "gn:asciiname":"Staroye Shilkovo",
    "gn:country_code":"RU",
    "gn:dem":209,
    "gn:feature_class":"P",
    "gn:feature_code":"PPL",
    "gn:name":"Staroye Shilkovo",
    "gn:population":0,
    "gn:timezone":"Europe/Moscow",
    "iso:country":"RU",
    "name:rus_x_preferred":[
        "\u0421\u0442\u0430\u0440\u043e\u0435 \u0428\u0438\u043b\u043a\u043e\u0432\u043e"
    ],
    "wof:name":"Staroye Shilkovo",
    "wof:placetype":"locality"
},
  "geometry": {"coordinates":[36.9128,58.4259],"type":"Point"}
}