{
  "type": "Feature",
  "properties": {
    "gn:admin1_code":"41.0",
    "gn:asciiname":"Balychevka",
    "gn:country_code":"RU",
    "gn:dem":231,
    "gn:feature_class":"P",
    "gn:feature_code":"PPL",
    "gn:name":"Balych\u00ebvka",
    "gn:population":0,
    "gn:timezone":"Europe/Moscow",
    "iso:country":"RU",
    "name:nor_x_preferred":[
        "Balytsjovka"
    ],
    "name:rus_x_preferred":[
        "\u0411\u0430\u043b\u044b\u0447\u0451\u0432\u043a\u0430"
    ],
    "name:und_x_variant":[
        "Balych\u00ebvka"
    ],
    "wof:name":"Balychevka",
    "wof:placetype":"locality"
},
  "geometry": {"coordinates":[36.71249,52.08055],"type":"Point"}
}