{
  "type": "Feature",
  "properties": {
    "gn:admin1_code":"13",
    "gn:asciiname":"Tatysh",
    "gn:country_code":"RU",
    "gn:dem":271,
    "gn:feature_class":"P",
    "gn:feature_code":"PPL",
    "gn:name":"Tatysh",
    "gn:population":0,
    "gn:timezone":"Asia/Yekaterinburg",
    "iso:country":"RU",
    "name:eng_x_preferred":[
        "Tatysh"
    ],
    "name:nor_x_preferred":[
        "Tatysj"
    ],
    "name:rus_x_preferred":[
        "\u0422\u0430\u0442\u044b\u0448"
    ],
    "wof:name":"Tatysh",
    "wof:placetype":"locality"
},
  "geometry": {"coordinates":[60.6449,55.6651],"type":"Point"}
}