{
  "type": "Feature",
  "properties": {
    "gn:admin1_code":"86.0",
    "gn:asciiname":"Dubovikovo",
    "gn:country_code":"RU",
    "gn:dem":164,
    "gn:feature_class":"P",
    "gn:feature_code":"PPL",
    "gn:name":"Dubovikovo",
    "gn:population":0,
    "gn:timezone":"Europe/Moscow",
    "iso:country":"RU",
    "name:rus_x_preferred":[
        "\u0414\u0443\u0431\u043e\u0432\u0438\u043a\u043e\u0432\u043e"
    ],
    "name:und_x_variant":[
        "Dubovikovka",
        "Dubovikovo"
    ],
    "wof:name":"Dubovikovo",
    "wof:placetype":"locality"
},
  "geometry": {"coordinates":[40.30611,50.01583],"type":"Point"}
}