{
  "type": "Feature",
  "properties": {
    "gn:country":"RU",
    "gn:fcode":"PPL",
    "gn:pop":3825,
    "iso:country":"RU",
    "name:ara_x_preferred":[
        "\u0628\u064a\u0644\u064a\u062a\u0633\u0627"
    ],
    "name:azb_x_preferred":[
        "\u0628\u0644\u06cc\u062a\u0633\u0627"
    ],
    "name:bul_x_preferred":[
        "\u0411\u0435\u043b\u0438\u0446\u0430"
    ],
    "name:ceb_x_preferred":[
        "Belitsa"
    ],
    "name:ces_x_preferred":[
        "Belica"
    ],
    "name:ckb_x_preferred":[
        "\u0628\u06ce\u0644\u06cc\u062a\u0633\u0627"
    ],
    "name:deu_x_preferred":[
        "Beliza"
    ],
    "name:eng_x_preferred":[
        "Betlitsa"
    ],
    "name:fas_x_preferred":[
        "\u0628\u0644\u06cc\u062a\u0633\u0627"
    ],
    "name:fra_x_preferred":[
        "Belitsa"
    ],
    "name:hye_x_preferred":[
        "\u0532\u0565\u056c\u056b\u0581\u0561"
    ],
    "name:kaz_x_preferred":[
        "\u0411\u0435\u043b\u0438\u0446\u0430"
    ],
    "name:mkd_x_preferred":[
        "\u0411\u0435\u043b\u0438\u0446\u0430"
    ],
    "name:nld_x_preferred":[
        "Belitsa"
    ],
    "name:nor_x_preferred":[
        "Betlitsa"
    ],
    "name:pol_x_preferred":[
        "Belica"
    ],
    "name:por_x_preferred":[
        "Belitsa"
    ],
    "name:ron_x_preferred":[
        "Beli\u021ba"
    ],
    "name:rus_x_preferred":[
        "\u0411\u0435\u0442\u043b\u0438\u0446\u0430"
    ],
    "name:rus_x_variant":[
        "\u0411\u0435\u043b\u0438\u0446\u0430"
    ],
    "name:spa_x_preferred":[
        "Belitsa"
    ],
    "name:srp_x_preferred":[
        "\u0411\u0435\u043b\u0438\u0446\u0430"
    ],
    "name:swe_x_preferred":[
        "Belitsa"
    ],
    "name:tur_x_preferred":[
        "Beli\u00e7a"
    ],
    "name:ukr_x_preferred":[
        "\u0411\u0435\u043b\u0438\u0446\u044f"
    ],
    "name:unk_x_variant":[
        "\u0411\u0435\u0442\u043b\u0438\u0446\u0430"
    ],
    "name:vie_x_preferred":[
        "Belitsa"
    ],
    "name:war_x_preferred":[
        "Belitsa"
    ],
    "name:zho_x_preferred":[
        "\u8c9d\u5229\u5bdf"
    ],
    "qs:name":"Belitsa",
    "qs:name_adm0":"Russia",
    "qs:name_adm1":"Smolensk Oblast",
    "qs:photos_9r":0,
    "qs:photos_sr":0,
    "qs:placetype":"Town",
    "qs:pop_sr":"4",
    "wd:wordcount":1511,
    "wof:name":"Belitsa",
    "wof:placetype":"locality",
    "wof:population":3825
},
  "geometry": {"coordinates":[33.95875,54.00946],"type":"Point"}
}