{
  "type": "Feature",
  "properties": {
    "gn:country":"RU",
    "gn:fcode":"PPL",
    "gn:pop":3825,
    "iso:country":"RU",
    "name:eng_x_preferred":[
        "Betlitsa"
    ],
    "name:nor_x_preferred":[
        "Betlitsa"
    ],
    "name:rus_x_preferred":[
        "\u0411\u0435\u0442\u043b\u0438\u0446\u0430"
    ],
    "name:unk_x_variant":[
        "\u0411\u0435\u0442\u043b\u0438\u0446\u0430"
    ],
    "qs:name":"Belitsa",
    "qs:name_adm0":"Russia",
    "qs:name_adm1":"Smolensk Oblast",
    "qs:photos_9r":0,
    "qs:photos_sr":0,
    "qs:placetype":"Town",
    "qs:pop_sr":"4",
    "wd:wordcount":1511,
    "wof:name":"Belitsa",
    "wof:placetype":"locality",
    "wof:population":3825
},
  "geometry": {"coordinates":[33.95875,54.00946],"type":"Point"}
}