{
  "type": "Feature",
  "properties": {
    "gn:admin1_code":"12",
    "gn:asciiname":"Ul'yanovskoye",
    "gn:country_code":"RU",
    "gn:dem":74,
    "gn:feature_class":"P",
    "gn:feature_code":"PPL",
    "gn:name":"Ul\u2019yanovskoye",
    "gn:population":0,
    "gn:timezone":"Europe/Moscow",
    "iso:country":"RU",
    "name:rus_x_preferred":[
        "\u0423\u043b\u044c\u044f\u043d\u043e\u0432\u0441\u043a\u043e\u0435"
    ],
    "name:und_x_variant":[
        "Ul\u2019yanovskoye"
    ],
    "wof:name":"Ul'yanovskoye",
    "wof:placetype":"locality"
},
  "geometry": {"coordinates":[45.60294,43.62999],"type":"Point"}
}