{
  "type": "Feature",
  "properties": {
    "gn:admin1_code":"62",
    "gn:asciiname":"Zimenki",
    "gn:country_code":"RU",
    "gn:dem":121,
    "gn:feature_class":"P",
    "gn:feature_code":"PPL",
    "gn:name":"Zimenki",
    "gn:population":0,
    "gn:timezone":"Europe/Moscow",
    "iso:country":"RU",
    "name:rus_x_preferred":[
        "\u0417\u0438\u043c\u0435\u043d\u043a\u0438"
    ],
    "wof:name":"Zimenki",
    "wof:placetype":"locality"
},
  "geometry": {"coordinates":[39.5205,54.6473],"type":"Point"}
}