{
  "type": "Feature",
  "properties": {
    "gn:admin1_code":"73",
    "gn:asciiname":"Savochkino",
    "gn:country_code":"RU",
    "gn:dem":218,
    "gn:feature_class":"P",
    "gn:feature_code":"PPL",
    "gn:name":"Savochkino",
    "gn:population":0,
    "gn:timezone":"Europe/Moscow",
    "iso:country":"RU",
    "name:rus_x_preferred":[
        "\u0421\u0430\u0432\u043e\u0447\u043a\u0438\u043d\u043e"
    ],
    "name:und_x_variant":[
        "\u0421\u0430\u0432\u043e\u0447\u043a\u0438\u043d\u043e"
    ],
    "wof:name":"Savochkino",
    "wof:placetype":"locality"
},
  "geometry": {"coordinates":[52.38871,54.54386],"type":"Point"}
}