{
  "type": "Feature",
  "properties": {
    "gn:admin1_code":"10",
    "gn:asciiname":"Borozdino",
    "gn:country_code":"RU",
    "gn:dem":186,
    "gn:feature_class":"P",
    "gn:feature_code":"PPL",
    "gn:name":"Borozdino",
    "gn:population":0,
    "gn:timezone":"Europe/Moscow",
    "iso:country":"RU",
    "name:rus_x_preferred":[
        "\u0411\u043e\u0440\u043e\u0437\u0434\u0438\u043d\u043e"
    ],
    "name:und_x_variant":[
        "\u0411\u043e\u0440\u043e\u0437\u0434\u0438\u043d\u043e",
        "Boroznino",
        "Borozdnino"
    ],
    "wof:name":"Borozdino",
    "wof:placetype":"locality"
},
  "geometry": {"coordinates":[32.98057,52.77101999999999],"type":"Point"}
}