{
  "type": "Feature",
  "properties": {
    "gn:admin1_code":"47",
    "gn:asciiname":"Yelgozino",
    "gn:country_code":"RU",
    "gn:dem":222,
    "gn:feature_class":"P",
    "gn:feature_code":"PPL",
    "gn:name":"Yelgozino",
    "gn:population":0,
    "gn:timezone":"Europe/Moscow",
    "iso:country":"RU",
    "name:eng_x_preferred":[
        "Yelgozino"
    ],
    "name:nor_x_preferred":[
        "Jelgozino"
    ],
    "name:rus_x_preferred":[
        "\u0415\u043b\u0433\u043e\u0437\u0438\u043d\u043e"
    ],
    "wof:name":"Yelgozino",
    "wof:placetype":"locality"
},
  "geometry": {"coordinates":[36.36081,56.23494],"type":"Point"}
}