{
  "type": "Feature",
  "properties": {
    "gn:admin1_code":"83",
    "gn:asciiname":"Zhelud'yevo",
    "gn:country_code":"RU",
    "gn:dem":127,
    "gn:feature_class":"P",
    "gn:feature_code":"PPL",
    "gn:name":"Zhelud\u2019yevo",
    "gn:population":0,
    "gn:timezone":"Europe/Moscow",
    "iso:country":"RU",
    "name:und_x_variant":[
        "Zhelud\u2019vevo",
        "Zhelud\u2019yevo"
    ],
    "wof:name":"Zhelud'yevo",
    "wof:placetype":"locality"
},
  "geometry": {"coordinates":[39.11808,55.97496],"type":"Point"}
}