{
  "type": "Feature",
  "properties": {
    "gn:admin1_code":"77",
    "gn:asciiname":"Klesty",
    "gn:country_code":"RU",
    "gn:dem":224,
    "gn:feature_class":"P",
    "gn:feature_code":"PPL",
    "gn:name":"Klesty",
    "gn:population":0,
    "gn:timezone":"Europe/Moscow",
    "iso:country":"RU",
    "name:rus_x_preferred":[
        "\u041a\u043b\u0435\u0441\u0442\u044b"
    ],
    "wof:name":"Klesty",
    "wof:placetype":"locality"
},
  "geometry": {"coordinates":[33.21295,56.18509],"type":"Point"}
}