{
  "type": "Feature",
  "properties": {
    "gn:admin1_code":"85",
    "gn:asciiname":"Grozilovo",
    "gn:country_code":"RU",
    "gn:dem":127,
    "gn:feature_class":"P",
    "gn:feature_code":"PPL",
    "gn:name":"Grozilovo",
    "gn:population":0,
    "gn:timezone":"Europe/Moscow",
    "iso:country":"RU",
    "name:rus_x_preferred":[
        "\u0413\u0440\u043e\u0437\u0438\u043b\u043e\u0432\u043e"
    ],
    "wof:name":"Grozilovo",
    "wof:placetype":"locality"
},
  "geometry": {"coordinates":[39.127,59.7505],"type":"Point"}
}