{
  "type": "Feature",
  "properties": {
    "gn:admin1_code":"40",
    "gn:asciiname":"Beloyarskoye",
    "gn:country_code":"RU",
    "gn:dem":129,
    "gn:feature_class":"P",
    "gn:feature_code":"PPL",
    "gn:name":"Beloyarskoye",
    "gn:population":0,
    "gn:timezone":"Asia/Yekaterinburg",
    "iso:country":"RU",
    "name:eng_x_preferred":[
        "Beloyarskoye"
    ],
    "name:nor_x_preferred":[
        "Belojarskoje"
    ],
    "name:rus_x_preferred":[
        "\u0411\u0435\u043b\u043e\u044f\u0440\u0441\u043a\u043e\u0435"
    ],
    "name:und_x_variant":[
        "\u0411\u0435\u043b\u043e\u044f\u0440\u0441\u043a\u043e\u0435",
        "Beloyarskoye"
    ],
    "wof:name":"Beloyarskoye",
    "wof:placetype":"locality"
},
  "geometry": {"coordinates":[62.37,55.328],"type":"Point"}
}