{
  "type": "Feature",
  "properties": {
    "gn:admin1_code":"76",
    "gn:asciiname":"Prudy",
    "gn:country_code":"RU",
    "gn:dem":196,
    "gn:feature_class":"P",
    "gn:feature_code":"PPL",
    "gn:name":"Prudy",
    "gn:population":0,
    "gn:timezone":"Europe/Moscow",
    "iso:country":"RU",
    "name:rus_x_preferred":[
        "\u041f\u0440\u0443\u0434\u044b"
    ],
    "wof:name":"Prudy",
    "wof:placetype":"locality"
},
  "geometry": {"coordinates":[38.2715,53.53675],"type":"Point"}
}