{
  "type": "Feature",
  "properties": {
    "gn:admin1_code":"8",
    "gn:asciiname":"Novoznamenskaya Pervaya",
    "gn:country_code":"RU",
    "gn:dem":237,
    "gn:feature_class":"P",
    "gn:feature_code":"PPL",
    "gn:name":"Novoznamenskaya Pervaya",
    "gn:population":0,
    "gn:timezone":"Asia/Yekaterinburg",
    "iso:country":"RU",
    "name:rus_x_preferred":[
        "\u041d\u043e\u0432\u043e\u0437\u043d\u0430\u043c\u0435\u043d\u0441\u043a\u0430\u044f \u041f\u0435\u0440\u0432\u0430\u044f"
    ],
    "name:und_x_variant":[
        "Novoznamenskoye Pervoye",
        "Novoznamenka Pervaya",
        "Novoznamenskaya Pervaya"
    ],
    "wof:name":"Novoznamenskaya Pervaya",
    "wof:placetype":"locality"
},
  "geometry": {"coordinates":[56.01931999999999,52.73248],"type":"Point"}
}