{
  "type": "Feature",
  "properties": {
    "gn:admin1_code":"75",
    "gn:asciiname":"Zimnik",
    "gn:country_code":"RU",
    "gn:dem":44,
    "gn:feature_class":"P",
    "gn:feature_code":"PPL",
    "gn:name":"Zimnik",
    "gn:population":0,
    "gn:timezone":"Asia/Tomsk",
    "iso:country":"RU",
    "name:pol_x_preferred":[
        "Zimnik"
    ],
    "name:ukr_x_preferred":[
        "\u0417\u0456\u043c\u043d\u0438\u043a"
    ],
    "wof:name":"Zimnik",
    "wof:placetype":"locality"
},
  "geometry": {"coordinates":[79.93333,59.45],"type":"Point"}
}