{
  "type": "Feature",
  "properties": {
    "gn:admin1_code":"90",
    "gn:asciiname":"Gorka",
    "gn:cc2":"RU",
    "gn:country_code":"RU",
    "gn:dem":106,
    "gn:feature_class":"P",
    "gn:feature_code":"PPL",
    "gn:name":"Gorka",
    "gn:population":0,
    "gn:timezone":"Asia/Yekaterinburg",
    "iso:country":"RU",
    "name:rus_x_preferred":[
        "\u0413\u043e\u0440\u043a\u0430"
    ],
    "name:und_x_variant":[
        "Gorki",
        "Gorka"
    ],
    "wof:name":"Gorka",
    "wof:placetype":"locality"
},
  "geometry": {"coordinates":[55.46666999999999,56.41667],"type":"Point"}
}