{
  "type": "Feature",
  "properties": {
    "gn:admin1_code":"51.0",
    "gn:asciiname":"Voskresen'ye",
    "gn:country_code":"RU",
    "gn:dem":90,
    "gn:feature_class":"P",
    "gn:feature_code":"PPL",
    "gn:name":"Voskresen\u2019ye",
    "gn:population":0,
    "gn:timezone":"Europe/Moscow",
    "iso:country":"RU",
    "wof:name":"Voskresen'ye",
    "wof:placetype":"locality"
},
  "geometry": {"coordinates":[43.34856,56.98145],"type":"Point"}
}