{
  "type": "Feature",
  "properties": {
    "gn:admin1_code":"71",
    "gn:asciiname":"Lomanaya Noga",
    "gn:country_code":"RU",
    "gn:dem":382,
    "gn:feature_class":"P",
    "gn:feature_code":"PPL",
    "gn:name":"Lomanaya Noga",
    "gn:population":0,
    "gn:timezone":"Asia/Yekaterinburg",
    "iso:country":"RU",
    "name:rus_x_preferred":[
        "\u041b\u043e\u043c\u0430\u043d\u0430\u044f \u041d\u043e\u0433\u0430"
    ],
    "name:und_x_variant":[
        "Novaya Derevnya",
        "Lomanaya Noga",
        "\u041b\u043e\u043c\u0430\u043d\u0430\u044f \u041d\u043e\u0433\u0430"
    ],
    "wof:name":"Lomanaya Noga",
    "wof:placetype":"locality"
},
  "geometry": {"coordinates":[57.44806,56.34072],"type":"Point"}
}