{
  "type": "Feature",
  "properties": {
    "gn:admin1_code":"46",
    "gn:asciiname":"Znamenskoye",
    "gn:country_code":"RU",
    "gn:dem":203,
    "gn:feature_class":"P",
    "gn:feature_code":"PPL",
    "gn:name":"Znamenskoye",
    "gn:population":0,
    "gn:timezone":"Europe/Moscow",
    "iso:country":"RU",
    "name:rus_x_preferred":[
        "\u0417\u043d\u0430\u043c\u0435\u043d\u0441\u043a\u043e\u0435"
    ],
    "wof:name":"Znamenskoye",
    "wof:placetype":"locality"
},
  "geometry": {"coordinates":[45.83969,54.78086999999999],"type":"Point"}
}