{
  "type": "Feature",
  "properties": {
    "gn:admin1_code":"47.0",
    "gn:asciiname":"Bab'i",
    "gn:country_code":"RU",
    "gn:dem":248,
    "gn:feature_class":"P",
    "gn:feature_code":"PPL",
    "gn:name":"Bab\u2019i",
    "gn:population":0,
    "gn:timezone":"Europe/Moscow",
    "iso:country":"RU",
    "name:nor_x_preferred":[
        "Babi"
    ],
    "name:rus_x_preferred":[
        "\u0411\u0430\u0431\u044c\u0438"
    ],
    "name:und_x_variant":[
        "Bab\u2019ye",
        "Bab\u2019i"
    ],
    "wof:name":"Bab'i",
    "wof:placetype":"locality"
},
  "geometry": {"coordinates":[35.42278,55.29083000000001],"type":"Point"}
}