{
  "type": "Feature",
  "properties": {
    "gn:country":"RU",
    "gn:fcode":"PPL",
    "gn:pop":8091,
    "iso:country":"RU",
    "name:eng_x_preferred":[
        "Novoshakhtinsky"
    ],
    "name:hye_x_preferred":[
        "\u0546\u0578\u057e\u0578\u0577\u0561\u056d\u057f\u056b\u0576\u057d\u056f\u056b\u0575"
    ],
    "name:nor_x_preferred":[
        "Novosjakhtinskij"
    ],
    "name:rus_x_preferred":[
        "\u041d\u043e\u0432\u043e\u0448\u0430\u0445\u0442\u0438\u043d\u0441\u043a\u0438\u0439"
    ],
    "name:unk_x_variant":[
        "\u041d\u043e\u0432\u043e\u0448\u0430\u0445\u0442\u0438\u043d\u0441\u043a\u0438\u0439"
    ],
    "qs:name":"Novoshakhtinskiy",
    "qs:name_adm0":"Russia",
    "qs:name_adm1":"Primorsky Krai",
    "qs:photos_9r":0,
    "qs:photos_sr":0,
    "qs:placetype":"Town",
    "qs:pop_sr":"5",
    "wof:name":"Novoshakhtinskiy",
    "wof:placetype":"locality",
    "wof:population":8091
},
  "geometry": {"coordinates":[132.16583,44.02576],"type":"Point"}
}