{
  "type": "Feature",
  "properties": {
    "gn:admin1_code":"3",
    "gn:asciiname":"Russkaya Yulya",
    "gn:country_code":"RU",
    "gn:dem":471,
    "gn:feature_class":"P",
    "gn:feature_code":"PPL",
    "gn:name":"Russkaya Yulya",
    "gn:population":0,
    "gn:timezone":"Asia/Omsk",
    "iso:country":"RU",
    "name:rus_x_preferred":[
        "\u0420\u0443\u0441\u0441\u043a\u0430\u044f \u042e\u043b\u044f"
    ],
    "name:und_x_variant":[
        "\u0420\u0443\u0441\u0441\u043a\u0430\u044f \u042e\u043b\u044f"
    ],
    "wof:name":"Russkaya Yulya",
    "wof:placetype":"locality"
},
  "geometry": {"coordinates":[86.81667,51.75],"type":"Point"}
}