{
  "type": "Feature",
  "properties": {
    "gn:admin1_code":"53",
    "gn:asciiname":"L'nozavod",
    "gn:country_code":"RU",
    "gn:dem":121,
    "gn:feature_class":"P",
    "gn:feature_code":"PPL",
    "gn:name":"L\u2019nozavod",
    "gn:population":0,
    "gn:timezone":"Asia/Novosibirsk",
    "iso:country":"RU",
    "name:rus_x_preferred":[
        "\u041b\u044c\u043d\u043e\u0437\u0430\u0432\u043e\u0434"
    ],
    "name:und_x_variant":[
        "L\u2019nozavod"
    ],
    "wof:name":"L'nozavod",
    "wof:placetype":"locality"
},
  "geometry": {"coordinates":[83.7992,55.1558],"type":"Point"}
}