{
  "type": "Feature",
  "properties": {
    "gn:admin1_code":"23",
    "gn:asciiname":"Furmanovka",
    "gn:cc2":"RU",
    "gn:country_code":"RU",
    "gn:dem":76,
    "gn:feature_class":"P",
    "gn:feature_code":"PPL",
    "gn:name":"Furmanovka",
    "gn:population":0,
    "gn:timezone":"Europe/Kaliningrad",
    "iso:country":"RU",
    "name:rus_x_preferred":[
        "\u0424\u0443\u0440\u043c\u0430\u043d\u043e\u0432\u043a\u0430"
    ],
    "name:und_x_variant":[
        "Zavety",
        "Kattenau",
        "Furmanovka",
        "\u0424\u0443\u0440\u043c\u0430\u043d\u043e\u0432\u043a\u0430"
    ],
    "wof:name":"Furmanovka",
    "wof:placetype":"locality"
},
  "geometry": {"coordinates":[22.42583,54.66944],"type":"Point"}
}