{
  "type": "Feature",
  "properties": {
    "gn:admin1_code":"45.0",
    "gn:asciiname":"Malyy Lyazhdur",
    "gn:country_code":"RU",
    "gn:dem":132,
    "gn:feature_class":"P",
    "gn:feature_code":"PPL",
    "gn:name":"Malyy Lyazhdur",
    "gn:population":0,
    "gn:timezone":"Europe/Moscow",
    "iso:country":"RU",
    "name:rus_x_preferred":[
        "\u041c\u0430\u043b\u044b\u0439 \u041b\u044f\u0436\u0434\u0443\u0440"
    ],
    "wof:name":"Malyy Lyazhdur",
    "wof:placetype":"locality"
},
  "geometry": {"coordinates":[49.26944,56.83556],"type":"Point"}
}