{
  "type": "Feature",
  "properties": {
    "gn:admin1_code":"42",
    "gn:admin2_code":"6695196",
    "gn:asciiname":"Mezhevoye",
    "gn:cc2":"RU",
    "gn:country_code":"RU",
    "gn:dem":62,
    "gn:feature_class":"P",
    "gn:feature_code":"PPL",
    "gn:name":"Mezhevoye",
    "gn:population":0,
    "gn:timezone":"Europe/Moscow",
    "iso:country":"RU",
    "name:fin_x_preferred":[
        "Markkola"
    ],
    "name:rus_x_historical":[
        "\u041c\u0430\u0440\u043a\u043e\u043b\u0430"
    ],
    "name:rus_x_preferred":[
        "\u041c\u0435\u0436\u0435\u0432\u043e\u0435"
    ],
    "name:rus_x_variant":[
        "\u041c\u0430\u0440\u043a\u043e\u043b\u0430"
    ],
    "name:und_x_variant":[
        "Markola",
        "Mezhevoye"
    ],
    "wof:name":"Mezhevoye",
    "wof:placetype":"locality"
},
  "geometry": {"coordinates":[30.03333,60.61666999999999],"type":"Point"}
}