{
  "type": "Feature",
  "properties": {
    "gn:admin1_code":"62",
    "gn:asciiname":"Zykeyevo",
    "gn:country_code":"RU",
    "gn:dem":99,
    "gn:feature_class":"P",
    "gn:feature_code":"PPL",
    "gn:name":"Zykeyevo",
    "gn:population":0,
    "gn:timezone":"Europe/Moscow",
    "iso:country":"RU",
    "name:rus_x_preferred":[
        "\u0417\u044b\u043a\u0435\u0435\u0432\u043e"
    ],
    "wof:name":"Zykeyevo",
    "wof:placetype":"locality"
},
  "geometry": {"coordinates":[40.7758,54.5687],"type":"Point"}
}