{
  "type": "Feature",
  "properties": {
    "gn:admin1_code":"10",
    "gn:asciiname":"Uvel'ye",
    "gn:country_code":"RU",
    "gn:dem":140,
    "gn:feature_class":"P",
    "gn:feature_code":"PPL",
    "gn:name":"Uvel\u2019ye",
    "gn:population":331,
    "gn:timezone":"Europe/Moscow",
    "iso:country":"RU",
    "name:eng_x_preferred":[
        "Uvel'ye"
    ],
    "name:nor_x_preferred":[
        "Uvelje"
    ],
    "name:rus_x_preferred":[
        "\u0423\u0432\u0435\u043b\u044c\u0435"
    ],
    "name:und_x_variant":[
        "Uvel\u2019ye"
    ],
    "wof:name":"Uvel'ye",
    "wof:placetype":"locality",
    "wof:population":331
},
  "geometry": {"coordinates":[31.6604,52.7832],"type":"Point"}
}