{
  "type": "Feature",
  "properties": {
    "gn:admin1_code":"68",
    "gn:asciiname":"Razdol'noye",
    "gn:country_code":"RU",
    "gn:dem":142,
    "gn:feature_class":"P",
    "gn:feature_code":"PPL",
    "gn:name":"Razdol\u2019noye",
    "gn:population":0,
    "gn:timezone":"Europe/Moscow",
    "iso:country":"RU",
    "name:rus_x_preferred":[
        "\u0420\u0430\u0437\u0434\u043e\u043b\u044c\u043d\u043e\u0435"
    ],
    "name:und_x_variant":[
        "Raszdol\u2019noye",
        "Razdol\u2019noye"
    ],
    "wof:name":"Razdol'noye",
    "wof:placetype":"locality"
},
  "geometry": {"coordinates":[44.53613,43.69818],"type":"Point"}
}