{
  "type": "Feature",
  "properties": {
    "gn:admin1_code":"8",
    "gn:asciiname":"Tepyanovo",
    "gn:country_code":"RU",
    "gn:dem":390,
    "gn:feature_class":"P",
    "gn:feature_code":"PPL",
    "gn:name":"Tepyanovo",
    "gn:population":0,
    "gn:timezone":"Asia/Yekaterinburg",
    "iso:country":"RU",
    "name:rus_x_preferred":[
        "\u0422\u0435\u043f\u044f\u043d\u043e\u0432\u043e"
    ],
    "name:und_x_variant":[
        "Tepyankova",
        "Tepyanova",
        "Tepyanovo"
    ],
    "wof:name":"Tepyanovo",
    "wof:placetype":"locality"
},
  "geometry": {"coordinates":[58.5541,53.1401],"type":"Point"}
}