{
  "type": "Feature",
  "properties": {
    "gn:admin1_code":"8",
    "gn:asciiname":"Tepyanovo",
    "gn:country_code":"RU",
    "gn:dem":390,
    "gn:feature_class":"P",
    "gn:feature_code":"PPL",
    "gn:name":"Tepyanovo",
    "gn:population":0,
    "gn:timezone":"Asia/Yekaterinburg",
    "iso:country":"RU",
    "name:aze_x_preferred":[
        "T\u0259p\u0259n"
    ],
    "name:bak_x_preferred":[
        "\u0422\u04d9\u043f\u04d9\u043d"
    ],
    "name:che_x_preferred":[
        "\u0422\u0435\u043f\u044f\u043d\u043e\u0432\u043e"
    ],
    "name:hye_x_preferred":[
        "\u054f\u0565\u057a\u0575\u0561\u0576\u0578\u057e\u0578"
    ],
    "name:kat_x_preferred":[
        "\u10e2\u10d4\u10de\u10d8\u10d0\u10dc\u10dd\u10d5\u10dd"
    ],
    "name:kaz_x_preferred":[
        "\u0422\u0435\u043f\u044f\u043d"
    ],
    "name:kir_x_preferred":[
        "\u0422\u0435\u043f\u044f\u043d"
    ],
    "name:rus_x_preferred":[
        "\u0422\u0435\u043f\u044f\u043d\u043e\u0432\u043e"
    ],
    "name:tat_x_preferred":[
        "\u0422\u04d9\u043f\u04d9\u043d"
    ],
    "name:ukr_x_preferred":[
        "\u0422\u0435\u043f'\u044f\u043d\u043e\u0432\u043e"
    ],
    "name:und_x_variant":[
        "Tepyankova",
        "Tepyanova",
        "Tepyanovo"
    ],
    "wof:name":"Tepyanovo",
    "wof:placetype":"locality"
},
  "geometry": {"coordinates":[58.5541,53.1401],"type":"Point"}
}