{
  "type": "Feature",
  "properties": {
    "gn:admin1_code":"25",
    "gn:asciiname":"Savinsk",
    "gn:country_code":"RU",
    "gn:dem":159,
    "gn:feature_class":"P",
    "gn:feature_code":"PPL",
    "gn:name":"Savinsk",
    "gn:population":0,
    "gn:timezone":"Europe/Moscow",
    "iso:country":"RU",
    "name:rus_x_preferred":[
        "\u0421\u0430\u0432\u0438\u043d\u0441\u043a"
    ],
    "name:und_x_variant":[
        "Savinskoye",
        "Savinsk"
    ],
    "wof:name":"Savinsk",
    "wof:placetype":"locality"
},
  "geometry": {"coordinates":[35.72116,54.02851],"type":"Point"}
}