{
  "type": "Feature",
  "properties": {
    "gn:admin1_code":"38",
    "gn:asciiname":"Dyurso",
    "gn:country_code":"RU",
    "gn:dem":13,
    "gn:feature_class":"P",
    "gn:feature_code":"PPL",
    "gn:name":"Dyurso",
    "gn:population":0,
    "gn:timezone":"Europe/Moscow",
    "iso:country":"RU",
    "name:rus_x_preferred":[
        "\u0414\u044e\u0440\u0441\u043e"
    ],
    "wof:name":"Dyurso",
    "wof:placetype":"locality"
},
  "geometry": {"coordinates":[37.56769,44.69],"type":"Point"}
}