{
  "type": "Feature",
  "properties": {
    "gn:admin1_code":"8.0",
    "gn:asciiname":"Bogolyubovka",
    "gn:country_code":"RU",
    "gn:dem":158,
    "gn:feature_class":"P",
    "gn:feature_code":"PPL",
    "gn:name":"Bogolyubovka",
    "gn:population":0,
    "gn:timezone":"Asia/Yekaterinburg",
    "iso:country":"RU",
    "name:bak_x_preferred":[
        "\u0411\u043e\u0433\u043e\u043b\u044e\u0431\u043e\u0432\u043a\u0430"
    ],
    "name:che_x_preferred":[
        "\u0411\u043e\u0433\u043e\u043b\u044e\u0431\u043e\u0432\u043a\u0430"
    ],
    "name:hye_x_preferred":[
        "\u0532\u0578\u0563\u0578\u056c\u0575\u0578\u0582\u0562\u0578\u057e\u056f\u0561"
    ],
    "name:kaz_x_preferred":[
        "\u0411\u043e\u0433\u043e\u043b\u044e\u0431\u043e\u0432\u043a\u0430"
    ],
    "name:rus_x_preferred":[
        "\u0411\u043e\u0433\u043e\u043b\u044e\u0431\u043e\u0432\u043a\u0430"
    ],
    "name:tat_x_preferred":[
        "\u0411\u04e9\u0433\u0435\u043b\u04d9\u04af"
    ],
    "name:ukr_x_preferred":[
        "\u0411\u043e\u0433\u043e\u043b\u044e\u0431\u043e\u0432\u043a\u0430"
    ],
    "wof:name":"Bogolyubovka",
    "wof:placetype":"locality"
},
  "geometry": {"coordinates":[55.39652,53.79669000000001],"type":"Point"}
}