{
  "type": "Feature",
  "properties": {
    "gn:admin1_code":"86",
    "gn:asciiname":"Nizhnyaya Vereyka",
    "gn:country_code":"RU",
    "gn:dem":104,
    "gn:feature_class":"P",
    "gn:feature_code":"PPL",
    "gn:name":"Nizhnyaya Vereyka",
    "gn:population":0,
    "gn:timezone":"Europe/Moscow",
    "iso:country":"RU",
    "name:rus_x_preferred":[
        "\u041d\u0438\u0436\u043d\u044f\u044f \u0412\u0435\u0440\u0435\u0439\u043a\u0430"
    ],
    "name:und_x_variant":[
        "Nizhnyava Vereyka",
        "Nizhnyaya Vereyka"
    ],
    "wof:name":"Nizhnyaya Vereyka",
    "wof:placetype":"locality"
},
  "geometry": {"coordinates":[39.0551,51.97516],"type":"Point"}
}