{
  "type": "Feature",
  "properties": {
    "gn:admin1_code":"05",
    "gn:asciiname":"Filimoshka",
    "gn:cc2":"RU",
    "gn:country_code":"RU",
    "gn:dem":308,
    "gn:feature_class":"P",
    "gn:feature_code":"PPL",
    "gn:name":"Filimoshka",
    "gn:population":0,
    "gn:timezone":"Asia/Yakutsk",
    "iso:country":"RU",
    "name:rus_x_preferred":[
        "\u0424\u0438\u043b\u0438\u043c\u043e\u0448\u043a\u0430"
    ],
    "name:und_x_variant":[
        "Zimovka Borisova",
        "Filimoshka"
    ],
    "wof:name":"Filimoshka",
    "wof:placetype":"locality"
},
  "geometry": {"coordinates":[127.91667,54.15],"type":"Point"}
}