{
  "type": "Feature",
  "properties": {
    "gn:admin1_code":"90",
    "gn:asciiname":"Shitova",
    "gn:country_code":"RU",
    "gn:dem":229,
    "gn:feature_class":"P",
    "gn:feature_code":"PPL",
    "gn:name":"Shitova",
    "gn:population":0,
    "gn:timezone":"Asia/Yekaterinburg",
    "iso:country":"RU",
    "wof:name":"Shitova",
    "wof:placetype":"locality"
},
  "geometry": {"coordinates":[54.05,59.46666999999999],"type":"Point"}
}