{
  "type": "Feature",
  "properties": {
    "gn:admin1_code":"70.0",
    "gn:asciiname":"Belousov",
    "gn:country_code":"RU",
    "gn:dem":291,
    "gn:feature_class":"P",
    "gn:feature_code":"PPL",
    "gn:name":"Belousov",
    "gn:population":0,
    "gn:timezone":"Europe/Moscow",
    "iso:country":"RU",
    "name:rus_x_preferred":[
        "\u0411\u0435\u043b\u043e\u0443\u0441\u043e\u0432"
    ],
    "wof:name":"Belousov",
    "wof:placetype":"locality"
},
  "geometry": {"coordinates":[43.59278,45.27528],"type":"Point"}
}