{
  "type": "Feature",
  "properties": {
    "gn:admin1_code":"8",
    "gn:asciiname":"Utyaganovo",
    "gn:country_code":"RU",
    "gn:dem":92,
    "gn:feature_class":"P",
    "gn:feature_code":"PPL",
    "gn:name":"Utyaganovo",
    "gn:population":0,
    "gn:timezone":"Asia/Yekaterinburg",
    "iso:country":"RU",
    "name:und_x_variant":[
        "Utyaganova",
        "Utyaganovo"
    ],
    "wof:name":"Utyaganovo",
    "wof:placetype":"locality"
},
  "geometry": {"coordinates":[55.54167,55.83141],"type":"Point"}
}