{
  "type": "Feature",
  "properties": {
    "gn:admin1_code":"76",
    "gn:asciiname":"Osinovka",
    "gn:country_code":"RU",
    "gn:dem":223,
    "gn:feature_class":"P",
    "gn:feature_code":"PPL",
    "gn:name":"Osinovka",
    "gn:population":0,
    "gn:timezone":"Europe/Moscow",
    "iso:country":"RU",
    "name:ceb_x_preferred":[
        "Osinovka"
    ],
    "name:lav_x_preferred":[
        "Osinovka"
    ],
    "name:swe_x_preferred":[
        "Osinovka"
    ],
    "wof:name":"Osinovka",
    "wof:placetype":"locality"
},
  "geometry": {"coordinates":[37.89361,53.74139],"type":"Point"}
}