{
  "type": "Feature",
  "properties": {
    "gn:admin1_code":"76",
    "gn:asciiname":"Vostochnyye Khutora",
    "gn:country_code":"RU",
    "gn:dem":181,
    "gn:feature_class":"P",
    "gn:feature_code":"PPL",
    "gn:name":"Vostochnyye Khutora",
    "gn:population":0,
    "gn:timezone":"Europe/Moscow",
    "iso:country":"RU",
    "name:rus_x_preferred":[
        "\u0412\u043e\u0441\u0442\u043e\u0447\u043d\u044b\u0435 \u0425\u0443\u0442\u043e\u0440\u0430"
    ],
    "wof:name":"Vostochnyye Khutora",
    "wof:placetype":"locality"
},
  "geometry": {"coordinates":[38.2893,53.5373],"type":"Point"}
}