{
  "type": "Feature",
  "properties": {
    "gn:admin1_code":"52",
    "gn:asciiname":"Stroilovo",
    "gn:country_code":"RU",
    "gn:dem":129,
    "gn:feature_class":"P",
    "gn:feature_code":"PPL",
    "gn:name":"Stroilovo",
    "gn:population":0,
    "gn:timezone":"Europe/Moscow",
    "iso:country":"RU",
    "name:rus_x_preferred":[
        "\u0421\u0442\u0440\u043e\u0438\u043b\u043e\u0432\u043e"
    ],
    "wof:name":"Stroilovo",
    "wof:placetype":"locality"
},
  "geometry": {"coordinates":[32.4493,57.5316],"type":"Point"}
}