{
  "type": "Feature",
  "properties": {
    "gn:admin1_code":"20",
    "gn:asciiname":"Topka",
    "gn:country_code":"RU",
    "gn:dem":475,
    "gn:feature_class":"P",
    "gn:feature_code":"PPL",
    "gn:name":"Topka",
    "gn:population":0,
    "gn:timezone":"Asia/Irkutsk",
    "iso:country":"RU",
    "name:eng_x_preferred":[
        "Topka"
    ],
    "name:nor_x_preferred":[
        "Topka"
    ],
    "name:rus_x_preferred":[
        "\u0422\u043e\u043f\u043a\u0430"
    ],
    "wof:name":"Topka",
    "wof:placetype":"locality"
},
  "geometry": {"coordinates":[102.8408,52.93858],"type":"Point"}
}