{
  "type": "Feature",
  "properties": {
    "gn:admin1_code":"25",
    "gn:asciiname":"Batinki",
    "gn:country_code":"RU",
    "gn:dem":203,
    "gn:feature_class":"P",
    "gn:feature_code":"PPL",
    "gn:name":"Batinki",
    "gn:population":0,
    "gn:timezone":"Europe/Moscow",
    "iso:country":"RU",
    "name:nor_x_preferred":[
        "Batinki"
    ],
    "name:rus_x_preferred":[
        "\u0411\u0430\u0442\u0438\u043d\u043a\u0438"
    ],
    "wof:name":"Batinki",
    "wof:placetype":"locality"
},
  "geometry": {"coordinates":[37.13222,54.65194],"type":"Point"}
}