{
  "type": "Feature",
  "properties": {
    "gn:admin1_code":"13",
    "gn:asciiname":"Solodyanka",
    "gn:country_code":"RU",
    "gn:dem":370,
    "gn:feature_class":"P",
    "gn:feature_code":"PPL",
    "gn:name":"Solodyanka",
    "gn:population":0,
    "gn:timezone":"Asia/Yekaterinburg",
    "iso:country":"RU",
    "name:rus_x_preferred":[
        "\u0421\u043e\u043b\u043e\u0434\u044f\u043d\u043a\u0430"
    ],
    "name:und_x_variant":[
        "\u0421\u043e\u043b\u043e\u0434\u044f\u043d\u043a\u0430"
    ],
    "wof:name":"Solodyanka",
    "wof:placetype":"locality"
},
  "geometry": {"coordinates":[59.4439,53.4582],"type":"Point"}
}