{
  "type": "Feature",
  "properties": {
    "gn:admin1_code":"25",
    "gn:asciiname":"Kuftino",
    "gn:country_code":"RU",
    "gn:dem":169,
    "gn:feature_class":"P",
    "gn:feature_code":"PPL",
    "gn:name":"Kuftino",
    "gn:population":0,
    "gn:timezone":"Europe/Moscow",
    "iso:country":"RU",
    "name:rus_x_preferred":[
        "\u041a\u0443\u0444\u0442\u0438\u043d\u043e"
    ],
    "name:und_x_variant":[
        "\u041a\u0443\u0444\u0442\u0438\u043d\u043e"
    ],
    "wof:name":"Kuftino",
    "wof:placetype":"locality"
},
  "geometry": {"coordinates":[36.0825,55.06639000000001],"type":"Point"}
}