{
  "type": "Feature",
  "properties": {
    "gn:admin1_code":"91",
    "gn:asciiname":"Ostyatskaya",
    "gn:country_code":"RU",
    "gn:dem":75,
    "gn:feature_class":"P",
    "gn:feature_code":"PPL",
    "gn:name":"Ostyatskaya",
    "gn:population":0,
    "gn:timezone":"Asia/Krasnoyarsk",
    "iso:country":"RU",
    "name:rus_x_preferred":[
        "\u041e\u0441\u0442\u044f\u0442\u0441\u043a\u0430\u044f"
    ],
    "wof:name":"Ostyatskaya",
    "wof:placetype":"locality"
},
  "geometry": {"coordinates":[91.33333,59.16667],"type":"Point"}
}