{
  "type": "Feature",
  "properties": {
    "gn:admin1_code":"88",
    "gn:asciiname":"Vasil'yevskaya",
    "gn:country_code":"RU",
    "gn:dem":118,
    "gn:feature_class":"P",
    "gn:feature_code":"PPL",
    "gn:name":"Vasil\u2019yevskaya",
    "gn:population":0,
    "gn:timezone":"Europe/Moscow",
    "iso:country":"RU",
    "name:rus_x_preferred":[
        "\u0412\u0430\u0441\u0438\u043b\u044c\u0435\u0432\u0441\u043a\u0430\u044f"
    ],
    "name:und_x_variant":[
        "Vasil\u2019yevskaya",
        "\u0412\u0430\u0441\u0438\u043b\u044c\u0435\u0432\u0441\u043a\u0430\u044f"
    ],
    "wof:name":"Vasil'yevskaya",
    "wof:placetype":"locality"
},
  "geometry": {"coordinates":[38.352,57.6948],"type":"Point"}
}