{
  "type": "Feature",
  "properties": {
    "gn:admin1_code":"52",
    "gn:asciiname":"Yukhino",
    "gn:country_code":"RU",
    "gn:dem":147,
    "gn:feature_class":"P",
    "gn:feature_code":"PPL",
    "gn:name":"Yukhino",
    "gn:population":0,
    "gn:timezone":"Europe/Moscow",
    "iso:country":"RU",
    "name:rus_x_preferred":[
        "\u042e\u0445\u0438\u043d\u043e"
    ],
    "name:und_x_variant":[
        "Yurkino",
        "Yukhino"
    ],
    "wof:name":"Yukhino",
    "wof:placetype":"locality"
},
  "geometry": {"coordinates":[35.63983,58.55087],"type":"Point"}
}