{
  "type": "Feature",
  "properties": {
    "gn:admin1_code":"77",
    "gn:asciiname":"Kulovo",
    "gn:country_code":"RU",
    "gn:dem":145,
    "gn:feature_class":"P",
    "gn:feature_code":"PPL",
    "gn:name":"Kulovo",
    "gn:population":0,
    "gn:timezone":"Europe/Moscow",
    "iso:country":"RU",
    "name:eng_x_preferred":[
        "Kulovo"
    ],
    "name:nor_x_preferred":[
        "Kulovo"
    ],
    "name:rus_x_preferred":[
        "\u041a\u0443\u043b\u043e\u0432\u043e"
    ],
    "name:und_x_variant":[
        "\u041a\u0443\u043b\u043e\u0432\u043e",
        "Kulovo"
    ],
    "wof:name":"Kulovo",
    "wof:placetype":"locality"
},
  "geometry": {"coordinates":[36.68333,57.46666999999999],"type":"Point"}
}