{
  "type": "Feature",
  "properties": {
    "gn:admin1_code":"54",
    "gn:asciiname":"Yelizavetino",
    "gn:country_code":"RU",
    "gn:dem":113,
    "gn:feature_class":"P",
    "gn:feature_code":"PPL",
    "gn:name":"Yelizavetino",
    "gn:population":0,
    "gn:timezone":"Asia/Omsk",
    "iso:country":"RU",
    "name:rus_x_preferred":[
        "\u0415\u043b\u0438\u0437\u0430\u0432\u0435\u0442\u0438\u043d\u043e"
    ],
    "name:und_x_variant":[
        "\u0415\u043b\u0438\u0437\u0430\u0432\u0435\u0442\u0438\u043d\u043e",
        "Yelizavetino Vtoroye"
    ],
    "wof:name":"Yelizavetino",
    "wof:placetype":"locality"
},
  "geometry": {"coordinates":[72.07689000000001,54.49999],"type":"Point"}
}