{
  "type": "Feature",
  "properties": {
    "gn:admin1_code":"85",
    "gn:asciiname":"Svatkovo",
    "gn:country_code":"RU",
    "gn:dem":179,
    "gn:feature_class":"P",
    "gn:feature_code":"PPL",
    "gn:name":"Svatkovo",
    "gn:population":0,
    "gn:timezone":"Europe/Moscow",
    "iso:country":"RU",
    "name:rus_x_preferred":[
        "\u0421\u0432\u0430\u0442\u043a\u043e\u0432\u043e"
    ],
    "wof:name":"Svatkovo",
    "wof:placetype":"locality"
},
  "geometry": {"coordinates":[38.6736,59.3073],"type":"Point"}
}