{
  "type": "Feature",
  "properties": {
    "gn:admin1_code":"42.0",
    "gn:asciiname":"Chazheshno",
    "gn:country_code":"RU",
    "gn:dem":25,
    "gn:feature_class":"P",
    "gn:feature_code":"PPL",
    "gn:name":"Chazheshno",
    "gn:population":0,
    "gn:timezone":"Europe/Moscow",
    "iso:country":"RU",
    "name:rus_x_preferred":[
        "\u0427\u0430\u0436\u0435\u0448\u043d\u043e"
    ],
    "name:und_x_variant":[
        "\u0427\u0430\u0436\u0435\u0448\u043d\u043e"
    ],
    "wof:name":"Chazheshno",
    "wof:placetype":"locality"
},
  "geometry": {"coordinates":[32.24819,59.73962],"type":"Point"}
}