{
  "type": "Feature",
  "properties": {
    "gn:admin1_code":"77.0",
    "gn:asciiname":"Buchkovo",
    "gn:country_code":"RU",
    "gn:dem":225,
    "gn:feature_class":"P",
    "gn:feature_code":"PPL",
    "gn:name":"Buchkovo",
    "gn:population":0,
    "gn:timezone":"Europe/Moscow",
    "iso:country":"RU",
    "name:rus_x_preferred":[
        "\u0411\u0443\u0447\u043a\u043e\u0432\u043e"
    ],
    "wof:name":"Buchkovo",
    "wof:placetype":"locality"
},
  "geometry": {"coordinates":[33.45893,56.73806999999999],"type":"Point"}
}