{
  "type": "Feature",
  "properties": {
    "gn:admin1_code":"56",
    "gn:asciiname":"Milyatino",
    "gn:country_code":"RU",
    "gn:dem":217,
    "gn:feature_class":"P",
    "gn:feature_code":"PPL",
    "gn:name":"Milyatino",
    "gn:population":0,
    "gn:timezone":"Europe/Moscow",
    "iso:country":"RU",
    "name:rus_x_preferred":[
        "\u041c\u0438\u043b\u044f\u0442\u0438\u043d\u043e"
    ],
    "name:und_x_variant":[
        "\u041c\u0438\u043b\u044f\u0442\u0438\u043d\u043e"
    ],
    "wof:name":"Milyatino",
    "wof:placetype":"locality"
},
  "geometry": {"coordinates":[36.17389,53.42944],"type":"Point"}
}