{
  "type": "Feature",
  "properties": {
    "gn:admin1_code":"47.0",
    "gn:asciiname":"Fedorovka",
    "gn:cc2":"RU",
    "gn:country_code":"RU",
    "gn:dem":189,
    "gn:feature_class":"P",
    "gn:feature_code":"PPL",
    "gn:name":"F\u00ebdorovka",
    "gn:population":0,
    "gn:timezone":"Europe/Moscow",
    "iso:country":"RU",
    "name:eng_x_preferred":[
        "F\u00ebdorovka"
    ],
    "name:nor_x_preferred":[
        "Fedorovka"
    ],
    "name:rus_x_preferred":[
        "\u0424\u0435\u0434\u043e\u0440\u043e\u0432\u043a\u0430"
    ],
    "name:rus_x_variant":[
        "\u0424\u0451\u0434\u043e\u0440\u043e\u0432\u043a\u0430"
    ],
    "name:und_x_variant":[
        "Annenka",
        "Fedorovki",
        "F\u00ebdorovka",
        "\u0424\u0451\u0434\u043e\u0440\u043e\u0432\u043a\u0430"
    ],
    "wof:name":"Fedorovka",
    "wof:placetype":"locality"
},
  "geometry": {"coordinates":[37.23333,56.25],"type":"Point"}
}