{
  "type": "Feature",
  "properties": {
    "gn:admin1_code":"55.0",
    "gn:asciiname":"Anan'yevka",
    "gn:country_code":"RU",
    "gn:dem":124,
    "gn:feature_class":"P",
    "gn:feature_code":"PPL",
    "gn:name":"Anan\u2019yevka",
    "gn:population":0,
    "gn:timezone":"Asia/Yekaterinburg",
    "iso:country":"RU",
    "name:nor_x_preferred":[
        "Ananjevka"
    ],
    "name:rus_x_preferred":[
        "\u0410\u043d\u0430\u043d\u044c\u0435\u0432\u043a\u0430"
    ],
    "name:und_x_variant":[
        "Anan\u2019yevka"
    ],
    "wof:name":"Anan'yevka",
    "wof:placetype":"locality"
},
  "geometry": {"coordinates":[53.43333000000001,52.71666999999999],"type":"Point"}
}