{
  "type": "Feature",
  "properties": {
    "gn:admin1_code":"78",
    "gn:asciiname":"Lopushino",
    "gn:cc2":"RU",
    "gn:country_code":"RU",
    "gn:dem":135,
    "gn:feature_class":"P",
    "gn:feature_code":"PPL",
    "gn:name":"Lopushino",
    "gn:population":0,
    "gn:timezone":"Asia/Yekaterinburg",
    "iso:country":"RU",
    "name:eng_x_preferred":[
        "Lopushino"
    ],
    "name:nor_x_preferred":[
        "Lapusjina"
    ],
    "name:rus_x_preferred":[
        "\u041b\u0430\u043f\u0443\u0448\u0438\u043d\u0430"
    ],
    "name:rus_x_variant":[
        "\u041b\u043e\u043f\u0443\u0448\u0438\u043d\u043e"
    ],
    "name:und_x_variant":[
        "Lapushino"
    ],
    "wof:name":"Lopushino",
    "wof:placetype":"locality"
},
  "geometry": {"coordinates":[68.16667,56.16667],"type":"Point"}
}