{
  "type": "Feature",
  "properties": {
    "gn:admin1_code":"90.0",
    "gn:asciiname":"Volegi",
    "gn:country_code":"RU",
    "gn:dem":201,
    "gn:feature_class":"P",
    "gn:feature_code":"PPL",
    "gn:name":"Volegi",
    "gn:population":0,
    "gn:timezone":"Asia/Yekaterinburg",
    "iso:country":"RU",
    "name:rus_x_preferred":[
        "\u0412\u043e\u043b\u0435\u0433\u0438"
    ],
    "wof:name":"Volegi",
    "wof:placetype":"locality"
},
  "geometry": {"coordinates":[55.085,58.2189],"type":"Point"}
}