{
  "type": "Feature",
  "properties": {
    "gn:admin1_code":"47.0",
    "gn:asciiname":"Chernevo",
    "gn:country_code":"RU",
    "gn:dem":200,
    "gn:feature_class":"P",
    "gn:feature_code":"PPL",
    "gn:name":"Chern\u00ebvo",
    "gn:population":0,
    "gn:timezone":"Europe/Moscow",
    "iso:country":"RU",
    "name:eng_x_preferred":[
        "Chern\u00ebvo"
    ],
    "name:nor_x_preferred":[
        "Tsjernevo"
    ],
    "name:rus_x_preferred":[
        "\u0427\u0435\u0440\u043d\u0435\u0432\u043e"
    ],
    "name:rus_x_variant":[
        "\u0427\u0435\u0440\u043d\u0451\u0432\u043e"
    ],
    "name:und_x_variant":[
        "Chern\u00ebvo",
        "\u0427\u0435\u0440\u043d\u0451\u0432\u043e"
    ],
    "wof:name":"Chernevo",
    "wof:placetype":"locality"
},
  "geometry": {"coordinates":[35.72014,55.87951999999999],"type":"Point"}
}