{
  "type": "Feature",
  "properties": {
    "gn:admin1_code":"59",
    "gn:asciiname":"Dushkino",
    "gn:country_code":"RU",
    "gn:dem":67,
    "gn:feature_class":"P",
    "gn:feature_code":"PPL",
    "gn:name":"Dushkino",
    "gn:population":456,
    "gn:timezone":"Asia/Vladivostok",
    "iso:country":"RU",
    "name:rus_x_preferred":[
        "\u0414\u0443\u0448\u043a\u0438\u043d\u043e"
    ],
    "name:und_x_variant":[
        "\u0414\u0443\u0448\u043a\u0438\u043d\u043e"
    ],
    "wof:name":"Dushkino",
    "wof:placetype":"locality",
    "wof:population":456
},
  "geometry": {"coordinates":[132.69811000000001,42.92884],"type":"Point"}
}