{
  "type": "Feature",
  "properties": {
    "gn:admin1_code":"62",
    "gn:asciiname":"Protury",
    "gn:country_code":"RU",
    "gn:dem":150,
    "gn:feature_class":"P",
    "gn:feature_code":"PPL",
    "gn:name":"Protury",
    "gn:population":0,
    "gn:timezone":"Europe/Moscow",
    "iso:country":"RU",
    "name:rus_x_preferred":[
        "\u041f\u0440\u043e\u0442\u0443\u0440\u044b"
    ],
    "name:und_x_variant":[
        "Novoselki",
        "Protury",
        "\u041f\u0440\u043e\u0442\u0443\u0440\u044b"
    ],
    "wof:name":"Protury",
    "wof:placetype":"locality"
},
  "geometry": {"coordinates":[42.2156,54.6308],"type":"Point"}
}