{
  "type": "Feature",
  "properties": {
    "gn:admin1_code":"10",
    "gn:asciiname":"Pesochnya",
    "gn:country_code":"RU",
    "gn:dem":194,
    "gn:feature_class":"P",
    "gn:feature_code":"PPL",
    "gn:name":"Pesochnya",
    "gn:population":0,
    "gn:timezone":"Europe/Moscow",
    "iso:country":"RU",
    "name:eng_x_preferred":[
        "Pesochnya"
    ],
    "name:nor_x_preferred":[
        "Pesotsjnja"
    ],
    "name:rus_x_preferred":[
        "\u041f\u0435\u0441\u043e\u0447\u043d\u044f"
    ],
    "name:und_x_variant":[
        "Pesochnaya"
    ],
    "wof:name":"Pesochnya",
    "wof:placetype":"locality"
},
  "geometry": {"coordinates":[34.9838,53.16917],"type":"Point"}
}