{
  "type": "Feature",
  "properties": {
    "gn:admin1_code":"46",
    "gn:asciiname":"Krasnyy Shadym",
    "gn:country_code":"RU",
    "gn:dem":194,
    "gn:feature_class":"P",
    "gn:feature_code":"PPL",
    "gn:name":"Krasnyy Shadym",
    "gn:population":0,
    "gn:timezone":"Europe/Moscow",
    "iso:country":"RU",
    "name:rus_x_preferred":[
        "\u041a\u0440\u0430\u0441\u043d\u044b\u0439 \u0428\u0430\u0434\u044b\u043c"
    ],
    "name:und_x_variant":[
        "Krasny Shadym",
        "Krasnyy Shadym"
    ],
    "wof:name":"Krasnyy Shadym",
    "wof:placetype":"locality"
},
  "geometry": {"coordinates":[44.0978,53.848],"type":"Point"}
}