{
  "type": "Feature",
  "properties": {
    "gn:admin1_code":"63",
    "gn:asciiname":"Aallaakh",
    "gn:country_code":"RU",
    "gn:dem":164,
    "gn:feature_class":"P",
    "gn:feature_code":"PPL",
    "gn:name":"Aallaakh",
    "gn:population":0,
    "gn:timezone":"Asia/Yakutsk",
    "iso:country":"RU",
    "name:eng_x_preferred":[
        "Aallaakh"
    ],
    "name:rus_x_preferred":[
        "\u0410\u043b\u043b\u0430\u0445"
    ],
    "name:rus_x_variant":[
        "\u0410\u0430\u043b\u043b\u0430\u0430\u0445"
    ],
    "wof:name":"Aallaakh",
    "wof:placetype":"locality"
},
  "geometry": {"coordinates":[131.61601000000002,60.7209],"type":"Point"}
}