{
  "type": "Feature",
  "properties": {
    "gn:admin1_code":"71",
    "gn:asciiname":"Kos'ya",
    "gn:country_code":"RU",
    "gn:dem":260,
    "gn:feature_class":"P",
    "gn:feature_code":"PPL",
    "gn:name":"Kos\u2019ya",
    "gn:population":0,
    "gn:timezone":"Asia/Yekaterinburg",
    "iso:country":"RU",
    "name:eng_x_preferred":[
        "Kos'ya"
    ],
    "name:nor_x_preferred":[
        "Kosia"
    ],
    "name:rus_x_preferred":[
        "\u041a\u043e\u0441\u044c\u044f"
    ],
    "name:und_x_variant":[
        "Kuchum",
        "Kosiya Poselok",
        "Kos\u2019ya",
        "\u041a\u043e\u0441\u044c\u044f"
    ],
    "wof:name":"Kos'ya",
    "wof:placetype":"locality"
},
  "geometry": {"coordinates":[59.3503,58.7958],"type":"Point"}
}