{
  "type": "Feature",
  "properties": {
    "gn:admin1_code":"10",
    "gn:asciiname":"Simontovka",
    "gn:country_code":"RU",
    "gn:dem":183,
    "gn:feature_class":"P",
    "gn:feature_code":"PPL",
    "gn:name":"Simontovka",
    "gn:population":0,
    "gn:timezone":"Europe/Moscow",
    "iso:country":"RU",
    "name:rus_x_preferred":[
        "\u0421\u0438\u043c\u043e\u043d\u0442\u043e\u0432\u043a\u0430"
    ],
    "wof:name":"Simontovka",
    "wof:placetype":"locality"
},
  "geometry": {"coordinates":[32.7704,53.04104],"type":"Point"}
}