{
  "type": "Feature",
  "properties": {
    "gn:admin1_code":"85",
    "gn:asciiname":"Kichino",
    "gn:country_code":"RU",
    "gn:dem":128,
    "gn:feature_class":"P",
    "gn:feature_code":"PPL",
    "gn:name":"Kichino",
    "gn:population":0,
    "gn:timezone":"Europe/Moscow",
    "iso:country":"RU",
    "name:rus_x_preferred":[
        "\u041a\u0438\u0447\u0438\u043d\u043e"
    ],
    "wof:name":"Kichino",
    "wof:placetype":"locality"
},
  "geometry": {"coordinates":[38.3645,59.1925],"type":"Point"}
}