{
  "type": "Feature",
  "properties": {
    "gn:admin1_code":"33",
    "gn:asciiname":"Moronovo",
    "gn:country_code":"RU",
    "gn:dem":150,
    "gn:feature_class":"P",
    "gn:feature_code":"PPL",
    "gn:name":"Moronovo",
    "gn:population":0,
    "gn:timezone":"Europe/Kirov",
    "iso:country":"RU",
    "name:rus_x_preferred":[
        "\u041c\u043e\u0440\u043e\u043d\u043e\u0432\u043e"
    ],
    "wof:name":"Moronovo",
    "wof:placetype":"locality"
},
  "geometry": {"coordinates":[49.6547,57.6289],"type":"Point"}
}