{
  "type": "Feature",
  "properties": {
    "gn:admin1_code":"13",
    "gn:asciiname":"Pecherkin",
    "gn:country_code":"RU",
    "gn:dem":238,
    "gn:feature_class":"P",
    "gn:feature_code":"PPL",
    "gn:name":"Pecherkin",
    "gn:population":0,
    "gn:timezone":"Asia/Yekaterinburg",
    "iso:country":"RU",
    "name:rus_x_preferred":[
        "\u041f\u0435\u0447\u0435\u0440\u043a\u0438\u043d"
    ],
    "name:und_x_variant":[
        "\u041f\u0435\u0447\u0435\u0440\u043a\u0438\u043d"
    ],
    "wof:name":"Pecherkin",
    "wof:placetype":"locality"
},
  "geometry": {"coordinates":[61.43333000000001,54.61666999999999],"type":"Point"}
}