{
  "type": "Feature",
  "properties": {
    "gn:admin1_code":"8",
    "gn:asciiname":"Yangi-Yul",
    "gn:country_code":"RU",
    "gn:dem":150,
    "gn:feature_class":"P",
    "gn:feature_code":"PPL",
    "gn:name":"Yangi-Yul",
    "gn:population":0,
    "gn:timezone":"Asia/Yekaterinburg",
    "iso:country":"RU",
    "name:bak_x_preferred":[
        "\u042f\u04a3\u044b \u042e\u043b"
    ],
    "name:che_x_preferred":[
        "\u042f\u043d\u0433\u0438-\u042e\u043b"
    ],
    "name:hye_x_preferred":[
        "\u0545\u0561\u0576\u0563\u056b-\u0545\u0578\u0582\u056c"
    ],
    "name:kaz_x_preferred":[
        "\u042f\u043d\u0433\u0438-\u042e\u043b"
    ],
    "name:kir_x_preferred":[
        "\u042f\u043d\u0433\u0438-\u042e\u043b"
    ],
    "name:rus_x_preferred":[
        "\u042f\u043d\u0433\u0438-\u042e\u043b"
    ],
    "name:tat_x_preferred":[
        "\u042f\u04a3\u0430 \u042e\u043b"
    ],
    "name:ukr_x_preferred":[
        "\u042f\u043d\u0433\u0456-\u042e\u043b"
    ],
    "wof:name":"Yangi-Yul",
    "wof:placetype":"locality"
},
  "geometry": {"coordinates":[55.55,52.58333],"type":"Point"}
}