{
  "type": "Feature",
  "properties": {
    "gn:admin1_code":"88",
    "gn:asciiname":"Yam",
    "gn:country_code":"RU",
    "gn:dem":123,
    "gn:feature_class":"P",
    "gn:feature_code":"PPL",
    "gn:name":"Yam",
    "gn:population":0,
    "gn:timezone":"Europe/Moscow",
    "iso:country":"RU",
    "name:cat_x_preferred":[
        "Yam"
    ],
    "name:ceb_x_preferred":[
        "Yam"
    ],
    "name:fas_x_preferred":[
        "\u06cc\u0645"
    ],
    "name:jpn_x_preferred":[
        "\u30e4\u30e0"
    ],
    "name:spa_x_preferred":[
        "Yam"
    ],
    "name:swe_x_preferred":[
        "Yam"
    ],
    "name:tgl_x_preferred":[
        "Yam"
    ],
    "name:tur_x_preferred":[
        "Yam"
    ],
    "wof:name":"Yam",
    "wof:placetype":"locality"
},
  "geometry": {"coordinates":[40.01393,57.91429],"type":"Point"}
}