{
  "type": "Feature",
  "properties": {
    "gn:admin1_code":"47",
    "gn:asciiname":"Obukhovo",
    "gn:country_code":"RU",
    "gn:dem":126,
    "gn:feature_class":"P",
    "gn:feature_code":"PPL",
    "gn:name":"Obukhovo",
    "gn:population":0,
    "gn:timezone":"Europe/Moscow",
    "iso:country":"RU",
    "name:bel_x_preferred":[
        "\u0410\u0431\u0443\u0445\u0430\u0432\u0430"
    ],
    "name:deu_x_preferred":[
        "Obuchowo"
    ],
    "name:ita_x_preferred":[
        "Obuchovo"
    ],
    "name:rus_x_preferred":[
        "\u041e\u0431\u0443\u0445\u043e\u0432\u043e"
    ],
    "name:swe_x_preferred":[
        "Obuchovo"
    ],
    "name:ukr_x_preferred":[
        "\u041e\u0431\u0443\u0445\u043e\u0432\u043e"
    ],
    "wof:name":"Obukhovo",
    "wof:placetype":"locality"
},
  "geometry": {"coordinates":[39.76008,55.19956],"type":"Point"}
}