{
  "type": "Feature",
  "properties": {
    "gn:admin1_code":"56",
    "gn:asciiname":"Malyye Ozerki",
    "gn:country_code":"RU",
    "gn:dem":254,
    "gn:feature_class":"P",
    "gn:feature_code":"PPL",
    "gn:name":"Malyye Ozerki",
    "gn:population":0,
    "gn:timezone":"Europe/Moscow",
    "iso:country":"RU",
    "name:rus_x_preferred":[
        "\u041c\u0430\u043b\u044b\u0435 \u041e\u0437\u0435\u0440\u043a\u0438"
    ],
    "name:und_x_variant":[
        "Malayye Ozerki",
        "Malyye Ozerki"
    ],
    "wof:name":"Malyye Ozerki",
    "wof:placetype":"locality"
},
  "geometry": {"coordinates":[37.44948,53.20346],"type":"Point"}
}