{
  "type": "Feature",
  "properties": {
    "gn:admin1_code":"62",
    "gn:asciiname":"Lebyazhiy Bor",
    "gn:country_code":"RU",
    "gn:dem":90,
    "gn:feature_class":"P",
    "gn:feature_code":"PPL",
    "gn:name":"Lebyazhiy Bor",
    "gn:population":0,
    "gn:timezone":"Europe/Moscow",
    "iso:country":"RU",
    "name:rus_x_preferred":[
        "\u041b\u0435\u0431\u044f\u0436\u0438\u0439 \u0411\u043e\u0440"
    ],
    "name:und_x_variant":[
        "\u041b\u0435\u0431\u044f\u0436\u0438\u0439 \u0411\u043e\u0440"
    ],
    "wof:name":"Lebyazhiy Bor",
    "wof:placetype":"locality"
},
  "geometry": {"coordinates":[41.94342,54.76512],"type":"Point"}
}