{
  "type": "Feature",
  "properties": {
    "gn:admin1_code":"91",
    "gn:asciiname":"Novonikolayevskoye",
    "gn:country_code":"RU",
    "gn:dem":165,
    "gn:feature_class":"P",
    "gn:feature_code":"PPL",
    "gn:name":"Novonikolayevskoye",
    "gn:population":0,
    "gn:timezone":"Asia/Krasnoyarsk",
    "iso:country":"RU",
    "name:eng_x_preferred":[
        "Novonikolayevskoye"
    ],
    "name:rus_x_preferred":[
        "\u041d\u043e\u0432\u043e\u043d\u0438\u043a\u043e\u043b\u0430\u0435\u0432\u0441\u043a\u0430\u044f"
    ],
    "name:rus_x_variant":[
        "\u041d\u043e\u0432\u043e\u043d\u0438\u043a\u043e\u043b\u043e\u0435\u0432\u0441\u043a\u043e\u0435",
        "\u041d\u043e\u0432\u043e\u043d\u0438\u043a\u043e\u043b\u0430\u0435\u0432\u0441\u043a\u043e\u0435"
    ],
    "name:und_x_variant":[
        "Novo-Nikolayevskaya"
    ],
    "wof:name":"Novonikolayevskoye",
    "wof:placetype":"locality"
},
  "geometry": {"coordinates":[92.438,57.8682],"type":"Point"}
}