{
  "type": "Feature",
  "properties": {
    "gn:admin1_code":"20",
    "gn:asciiname":"Zolotoye Ust'ye",
    "gn:country_code":"RU",
    "gn:dem":761,
    "gn:feature_class":"P",
    "gn:feature_code":"PPL",
    "gn:name":"Zolotoye Ust\u2019ye",
    "gn:population":0,
    "gn:timezone":"Asia/Irkutsk",
    "iso:country":"RU",
    "wof:name":"Zolotoye Ust'ye",
    "wof:placetype":"locality"
},
  "geometry": {"coordinates":[116.91667,58.73333],"type":"Point"}
}