{
  "type": "Feature",
  "properties": {
    "gn:admin1_code":"69",
    "gn:asciiname":"Novaya Sosnovka",
    "gn:country_code":"RU",
    "gn:dem":232,
    "gn:feature_class":"P",
    "gn:feature_code":"PPL",
    "gn:name":"Novaya Sosnovka",
    "gn:population":0,
    "gn:timezone":"Europe/Moscow",
    "iso:country":"RU",
    "name:rus_x_preferred":[
        "\u041d\u043e\u0432\u0430\u044f \u0421\u043e\u0441\u043d\u043e\u0432\u043a\u0430"
    ],
    "wof:name":"Novaya Sosnovka",
    "wof:placetype":"locality"
},
  "geometry": {"coordinates":[33.33492,54.38661],"type":"Point"}
}