{
  "type": "Feature",
  "properties": {
    "gn:asciiname":"Podlip'ye",
    "gn:country_code":"RU",
    "gn:dem":40,
    "gn:feature_class":"P",
    "gn:feature_code":"PPL",
    "gn:name":"Podlip'ye",
    "gn:population":0,
    "gn:timezone":"Europe/Moscow",
    "iso:country":"RU",
    "wof:name":"Podlip'ye",
    "wof:placetype":"locality"
},
  "geometry": {"coordinates":[27.83841,58.46287],"type":"Point"}
}