{
  "type": "Feature",
  "properties": {
    "gn:admin1_code":"62",
    "gn:asciiname":"Dmitriyevskiy Khutor",
    "gn:country_code":"RU",
    "gn:dem":150,
    "gn:feature_class":"P",
    "gn:feature_code":"PPL",
    "gn:name":"Dmitriyevskiy Khutor",
    "gn:population":0,
    "gn:timezone":"Europe/Moscow",
    "iso:country":"RU",
    "name:rus_x_preferred":[
        "\u0414\u043c\u0438\u0442\u0440\u0438\u0435\u0432\u0441\u043a\u0438\u0439 \u0425\u0443\u0442\u043e\u0440"
    ],
    "name:und_x_variant":[
        "Dmitriyevka",
        "Dmitriyevskiy Khutor"
    ],
    "wof:name":"Dmitriyevskiy Khutor",
    "wof:placetype":"locality"
},
  "geometry": {"coordinates":[39.77091,53.7745],"type":"Point"}
}