{
  "type": "Feature",
  "properties": {
    "gn:admin1_code":"80.0",
    "gn:asciiname":"Chemoshur",
    "gn:country_code":"RU",
    "gn:dem":199,
    "gn:feature_class":"P",
    "gn:feature_code":"PPL",
    "gn:name":"Chemoshur",
    "gn:population":0,
    "gn:timezone":"Europe/Samara",
    "iso:country":"RU",
    "name:eng_x_preferred":[
        "Chimoshur"
    ],
    "name:nor_x_preferred":[
        "Tsjemosjur"
    ],
    "name:rus_x_preferred":[
        "\u0427\u0435\u043c\u043e\u0448\u0443\u0440"
    ],
    "name:und_x_variant":[
        "Chimoshur",
        "Chemoshur"
    ],
    "wof:name":"Chemoshur",
    "wof:placetype":"locality"
},
  "geometry": {"coordinates":[53.0839,57.4098],"type":"Point"}
}