{
  "type": "Feature",
  "properties": {
    "gn:admin1_code":"53",
    "gn:asciiname":"L'nikha",
    "gn:country_code":"RU",
    "gn:dem":157,
    "gn:feature_class":"P",
    "gn:feature_code":"PPL",
    "gn:name":"L\u2019nikha",
    "gn:population":0,
    "gn:timezone":"Asia/Novosibirsk",
    "iso:country":"RU",
    "name:eng_x_preferred":[
        "L'nikha"
    ],
    "name:nor_x_preferred":[
        "Lnikha"
    ],
    "name:rus_x_preferred":[
        "\u041b\u044c\u043d\u0438\u0445\u0430"
    ],
    "name:und_x_variant":[
        "\u041b\u044c\u043d\u0438\u0445\u0430",
        "L\u2019nikha"
    ],
    "wof:name":"L'nikha",
    "wof:placetype":"locality"
},
  "geometry": {"coordinates":[83.6301,55.1175],"type":"Point"}
}