{
  "type": "Feature",
  "properties": {
    "gn:admin1_code":"59.0",
    "gn:asciiname":"Oleniy",
    "gn:country_code":"RU",
    "gn:dem":27,
    "gn:feature_class":"P",
    "gn:feature_code":"PPL",
    "gn:name":"Oleniy",
    "gn:population":0,
    "gn:timezone":"Asia/Vladivostok",
    "iso:country":"RU",
    "name:rus_x_preferred":[
        "\u041e\u043b\u0435\u043d\u0438\u0439"
    ],
    "name:und_x_variant":[
        "\u041e\u043b\u0435\u043d\u0438\u0439"
    ],
    "wof:name":"Oleniy",
    "wof:placetype":"locality"
},
  "geometry": {"coordinates":[132.29476,43.35232],"type":"Point"}
}