{
  "type": "Feature",
  "properties": {
    "gn:admin1_code":"42.0",
    "gn:asciiname":"Bol'shoy Brod",
    "gn:country_code":"RU",
    "gn:dem":63,
    "gn:feature_class":"P",
    "gn:feature_code":"PPL",
    "gn:name":"Bol\u2019shoy Brod",
    "gn:population":0,
    "gn:timezone":"Europe/Moscow",
    "iso:country":"RU",
    "name:rus_x_preferred":[
        "\u0411\u043e\u043b\u044c\u0448\u043e\u0439 \u0411\u0440\u043e\u0434"
    ],
    "name:und_x_variant":[
        "Bol\u2019shoy Brod",
        "\u0411\u043e\u043b\u044c\u0448\u043e\u0439 \u0411\u0440\u043e\u0434"
    ],
    "wof:name":"Bol'shoy Brod",
    "wof:placetype":"locality"
},
  "geometry": {"coordinates":[29.89106,58.56598],"type":"Point"}
}