{
  "type": "Feature",
  "properties": {
    "gn:admin1_code":"33.0",
    "gn:asciiname":"Arskoye",
    "gn:country_code":"RU",
    "gn:dem":158,
    "gn:feature_class":"P",
    "gn:feature_code":"PPL",
    "gn:name":"Arskoye",
    "gn:population":0,
    "gn:timezone":"Europe/Kirov",
    "iso:country":"RU",
    "name:eng_x_preferred":[
        "Arskoye"
    ],
    "name:nor_x_preferred":[
        "Arskoje"
    ],
    "name:rus_x_preferred":[
        "\u0410\u0440\u0441\u043a\u043e\u0435"
    ],
    "wof:name":"Arskoye",
    "wof:placetype":"locality"
},
  "geometry": {"coordinates":[50.29372,57.48396],"type":"Point"}
}