{
  "type": "Feature",
  "properties": {
    "gn:admin1_code":"81",
    "gn:asciiname":"Bezrechnyy",
    "gn:country_code":"RU",
    "gn:dem":175,
    "gn:feature_class":"P",
    "gn:feature_code":"PPL",
    "gn:name":"Bezrechnyy",
    "gn:population":0,
    "gn:timezone":"Europe/Ulyanovsk",
    "iso:country":"RU",
    "name:rus_x_preferred":[
        "\u0411\u0435\u0437\u0440\u0435\u0447\u043d\u044b\u0439"
    ],
    "name:und_x_variant":[
        "Svobodnyy Trud"
    ],
    "wof:name":"Bezrechnyy",
    "wof:placetype":"locality"
},
  "geometry": {"coordinates":[47.9029,54.2337],"type":"Point"}
}