{
  "type": "Feature",
  "properties": {
    "gn:admin1_code":"69.0",
    "gn:asciiname":"Fedyayevo",
    "gn:country_code":"RU",
    "gn:dem":226,
    "gn:feature_class":"P",
    "gn:feature_code":"PPL",
    "gn:name":"Fedyayevo",
    "gn:population":0,
    "gn:timezone":"Europe/Moscow",
    "iso:country":"RU",
    "name:rus_x_preferred":[
        "\u0424\u0435\u0434\u044f\u0435\u0432\u043e"
    ],
    "wof:name":"Fedyayevo",
    "wof:placetype":"locality"
},
  "geometry": {"coordinates":[34.44388,55.49001],"type":"Point"}
}