{
  "type": "Feature",
  "properties": {
    "gn:admin1_code":"65",
    "gn:asciiname":"Novaya Orlovka",
    "gn:country_code":"RU",
    "gn:dem":65,
    "gn:feature_class":"P",
    "gn:feature_code":"PPL",
    "gn:name":"Novaya Orlovka",
    "gn:population":0,
    "gn:timezone":"Europe/Samara",
    "iso:country":"RU",
    "name:rus_x_preferred":[
        "\u041d\u043e\u0432\u0430\u044f \u041e\u0440\u043b\u043e\u0432\u043a\u0430"
    ],
    "name:und_x_variant":[
        "Orlovskiy",
        "Orlovka",
        "Novaya Orlovka"
    ],
    "wof:name":"Novaya Orlovka",
    "wof:placetype":"locality"
},
  "geometry": {"coordinates":[50.80659,53.63358],"type":"Point"}
}