{
  "type": "Feature",
  "properties": {
    "gn:admin1_code":"37",
    "gn:asciiname":"Tok",
    "gn:country_code":"RU",
    "gn:dem":183,
    "gn:feature_class":"P",
    "gn:feature_code":"PPL",
    "gn:name":"Tok",
    "gn:population":0,
    "gn:timezone":"Europe/Moscow",
    "iso:country":"RU",
    "name:bul_x_preferred":[
        "\u0422\u043e\u043a"
    ],
    "name:ceb_x_preferred":[
        "Tok"
    ],
    "name:ces_x_preferred":[
        "Tok"
    ],
    "name:deu_x_preferred":[
        "Tok"
    ],
    "name:rus_x_preferred":[
        "\u0422\u043e\u043a"
    ],
    "name:slk_x_preferred":[
        "Tok"
    ],
    "name:slv_x_preferred":[
        "Tok"
    ],
    "name:srp_x_preferred":[
        "\u0422\u043e\u043a"
    ],
    "name:swe_x_preferred":[
        "Tok"
    ],
    "name:tur_x_preferred":[
        "Tok"
    ],
    "name:ukr_x_preferred":[
        "\u0422\u043e\u043a"
    ],
    "name:uzb_x_preferred":[
        "Tok"
    ],
    "wof:name":"Tok",
    "wof:placetype":"locality"
},
  "geometry": {"coordinates":[41.36598,58.23315],"type":"Point"}
}