{
  "type": "Feature",
  "properties": {
    "gn:admin1_code":"33.0",
    "gn:asciiname":"Deminskaya",
    "gn:country_code":"RU",
    "gn:dem":137,
    "gn:feature_class":"P",
    "gn:feature_code":"PPL",
    "gn:name":"D\u00ebminskaya",
    "gn:population":0,
    "gn:timezone":"Europe/Kirov",
    "iso:country":"RU",
    "name:rus_x_preferred":[
        "\u0414\u0451\u043c\u0438\u043d\u0441\u043a\u0430\u044f"
    ],
    "name:und_x_variant":[
        "D\u00ebminskaya",
        "\u0414\u0451\u043c\u0438\u043d\u0441\u043a\u0430\u044f"
    ],
    "wof:name":"Deminskaya",
    "wof:placetype":"locality"
},
  "geometry": {"coordinates":[48.2553,58.3003],"type":"Point"}
}