{
  "type": "Feature",
  "properties": {
    "gn:admin1_code":"90.0",
    "gn:asciiname":"Artyuzhata",
    "gn:country_code":"RU",
    "gn:dem":127,
    "gn:feature_class":"P",
    "gn:feature_code":"PPL",
    "gn:name":"Artyuzhata",
    "gn:population":0,
    "gn:timezone":"Asia/Yekaterinburg",
    "iso:country":"RU",
    "name:nor_x_preferred":[
        "Artjuzjata"
    ],
    "name:rus_x_preferred":[
        "\u0410\u0440\u0442\u044e\u0436\u0430\u0442\u0430"
    ],
    "wof:name":"Artyuzhata",
    "wof:placetype":"locality"
},
  "geometry": {"coordinates":[55.16667,58.06667],"type":"Point"}
}