{
  "type": "Feature",
  "properties": {
    "gn:admin1_code":"73",
    "gn:asciiname":"Kas'ki",
    "gn:country_code":"RU",
    "gn:dem":241,
    "gn:feature_class":"P",
    "gn:feature_code":"PPL",
    "gn:name":"Kas\u2019ki",
    "gn:population":0,
    "gn:timezone":"Europe/Moscow",
    "iso:country":"RU",
    "name:rus_x_preferred":[
        "\u041a\u0430\u0441\u044c\u043a\u0438"
    ],
    "name:und_x_variant":[
        "Kas\u2019ki",
        "\u041a\u0430\u0441\u044c\u043a\u0438"
    ],
    "wof:name":"Kas'ki",
    "wof:placetype":"locality"
},
  "geometry": {"coordinates":[52.42966,55.07464],"type":"Point"}
}