{
  "type": "Feature",
  "properties": {
    "gn:admin1_code":"76.0",
    "gn:asciiname":"Boloto",
    "gn:country_code":"RU",
    "gn:dem":173,
    "gn:feature_class":"P",
    "gn:feature_code":"PPL",
    "gn:name":"Boloto",
    "gn:population":0,
    "gn:timezone":"Europe/Moscow",
    "iso:country":"RU",
    "name:che_x_preferred":[
        "\u0411\u043e\u043b\u043e\u0442\u043e"
    ],
    "name:eng_x_preferred":[
        "Boloto"
    ],
    "name:nor_x_preferred":[
        "Boloto"
    ],
    "name:rus_x_preferred":[
        "\u0411\u043e\u043b\u043e\u0442\u043e"
    ],
    "wof:name":"Boloto",
    "wof:placetype":"locality"
},
  "geometry": {"coordinates":[36.31327,53.8057],"type":"Point"}
}