{
  "type": "Feature",
  "properties": {
    "gn:admin1_code":"77",
    "gn:asciiname":"Komkino",
    "gn:country_code":"RU",
    "gn:dem":210,
    "gn:feature_class":"P",
    "gn:feature_code":"PPL",
    "gn:name":"Komkino",
    "gn:population":0,
    "gn:timezone":"Europe/Moscow",
    "iso:country":"RU",
    "name:che_x_preferred":[
        "\u041a\u043e\u043c\u043a\u0438\u043d\u043e"
    ],
    "name:rus_x_preferred":[
        "\u041a\u043e\u043c\u043a\u0438\u043d\u043e"
    ],
    "wof:name":"Komkino",
    "wof:placetype":"locality"
},
  "geometry": {"coordinates":[33.42629,57.67457],"type":"Point"}
}