{
  "type": "Feature",
  "properties": {
    "gn:admin1_code":"38",
    "gn:asciiname":"Krupskiy",
    "gn:country_code":"RU",
    "gn:dem":101,
    "gn:feature_class":"P",
    "gn:feature_code":"PPL",
    "gn:name":"Krupskiy",
    "gn:population":0,
    "gn:timezone":"Europe/Moscow",
    "iso:country":"RU",
    "name:rus_x_preferred":[
        "\u041a\u0440\u0443\u043f\u0441\u043a\u0438\u0439"
    ],
    "wof:name":"Krupskiy",
    "wof:placetype":"locality"
},
  "geometry": {"coordinates":[40.77333,45.34361],"type":"Point"}
}