{
  "type": "Feature",
  "properties": {
    "gn:admin1_code":"80",
    "gn:asciiname":"Verkhniy Sylyz'",
    "gn:country_code":"RU",
    "gn:dem":201,
    "gn:feature_class":"P",
    "gn:feature_code":"PPL",
    "gn:name":"Verkhniy Sylyz\u2019",
    "gn:population":0,
    "gn:timezone":"Europe/Samara",
    "iso:country":"RU",
    "name:rus_x_preferred":[
        "\u0412\u0435\u0440\u0445\u043d\u0438\u0439 \u0421\u044b\u043b\u044b\u0437\u044c"
    ],
    "name:und_x_variant":[
        "Verkhniy Sylyz\u2019"
    ],
    "wof:name":"Verkhniy Sylyz'",
    "wof:placetype":"locality"
},
  "geometry": {"coordinates":[53.8283,57.5463],"type":"Point"}
}