{
  "type": "Feature",
  "properties": {
    "gn:admin1_code":"47",
    "gn:asciiname":"Volkovo",
    "gn:country_code":"RU",
    "gn:dem":132,
    "gn:feature_class":"P",
    "gn:feature_code":"PPL",
    "gn:name":"Volkovo",
    "gn:population":0,
    "gn:timezone":"Europe/Moscow",
    "iso:country":"RU",
    "name:bel_x_preferred":[
        "\u0412\u043e\u043b\u043a\u0430\u0432\u0430"
    ],
    "name:est_x_preferred":[
        "Volkovo"
    ],
    "name:hye_x_preferred":[
        "\u054e\u0578\u056c\u056f\u0578\u057e\u0578"
    ],
    "name:rus_x_preferred":[
        "\u0412\u043e\u043b\u043a\u043e\u0432\u043e"
    ],
    "name:tat_x_preferred":[
        "\u0412\u043e\u043b\u043a\u043e\u0432\u043e"
    ],
    "name:ukr_x_preferred":[
        "\u0412\u043e\u043b\u043a\u043e\u0432\u043e"
    ],
    "name:und_x_variant":[
        "Volkova",
        "Volkovo"
    ],
    "wof:name":"Volkovo",
    "wof:placetype":"locality"
},
  "geometry": {"coordinates":[37.39313,54.85658000000001],"type":"Point"}
}