{
  "type": "Feature",
  "properties": {
    "gn:admin1_code":"32",
    "gn:asciiname":"Komarovy",
    "gn:cc2":"RU",
    "gn:country_code":"RU",
    "gn:dem":45,
    "gn:feature_class":"P",
    "gn:feature_code":"PPL",
    "gn:name":"Komarovy",
    "gn:population":0,
    "gn:timezone":"Asia/Yekaterinburg",
    "iso:country":"RU",
    "name:rus_x_preferred":[
        "\u041a\u043e\u043c\u0430\u0440\u043e\u0432\u044b"
    ],
    "name:und_x_variant":[
        "Komarovo",
        "Komarovy"
    ],
    "wof:name":"Komarovy",
    "wof:placetype":"locality"
},
  "geometry": {"coordinates":[75.83333,60.43333000000001],"type":"Point"}
}