{
  "type": "Feature",
  "properties": {
    "gn:admin1_code":"20",
    "gn:asciiname":"Yakovskaya",
    "gn:country_code":"RU",
    "gn:dem":214,
    "gn:feature_class":"P",
    "gn:feature_code":"PPL",
    "gn:name":"Yakovskaya",
    "gn:population":0,
    "gn:timezone":"Asia/Irkutsk",
    "iso:country":"RU",
    "name:rus_x_preferred":[
        "\u042f\u043a\u043e\u0432\u0441\u043a\u0430\u044f"
    ],
    "name:und_x_variant":[
        "Yakovskaya Zaimka",
        "Yakovskaya"
    ],
    "wof:name":"Yakovskaya",
    "wof:placetype":"locality"
},
  "geometry": {"coordinates":[98.39830000000001,56.4485],"type":"Point"}
}