{
  "type": "Feature",
  "properties": {
    "gn:admin1_code":"92",
    "gn:asciiname":"Anagvay",
    "gn:country_code":"RU",
    "gn:dem":873,
    "gn:feature_class":"P",
    "gn:feature_code":"PPL",
    "gn:name":"Anagvay",
    "gn:population":0,
    "gn:timezone":"Asia/Kamchatka",
    "iso:country":"RU",
    "name:nor_x_preferred":[
        "Anagvaj"
    ],
    "name:rus_x_preferred":[
        "\u0410\u043d\u0430\u0433\u0432\u0430\u0439"
    ],
    "name:und_x_variant":[
        "Achagvay",
        "Anagvay"
    ],
    "wof:name":"Anagvay",
    "wof:placetype":"locality"
},
  "geometry": {"coordinates":[158.80000000000001,56.06667],"type":"Point"}
}