{
  "type": "Feature",
  "properties": {
    "gn:admin1_code":"56.0",
    "gn:asciiname":"Bogoslovka",
    "gn:country_code":"RU",
    "gn:dem":208,
    "gn:feature_class":"P",
    "gn:feature_code":"PPL",
    "gn:name":"Bogoslovka",
    "gn:population":0,
    "gn:timezone":"Europe/Moscow",
    "iso:country":"RU",
    "name:rus_x_preferred":[
        "\u0411\u043e\u0433\u043e\u0441\u043b\u043e\u0432\u043a\u0430"
    ],
    "name:und_x_variant":[
        "\u0411\u043e\u0433\u043e\u0441\u043b\u043e\u0432\u043a\u0430"
    ],
    "wof:name":"Bogoslovka",
    "wof:placetype":"locality"
},
  "geometry": {"coordinates":[37.22778,53.255],"type":"Point"}
}