{
  "type": "Feature",
  "properties": {
    "gn:admin1_code":"84",
    "gn:asciiname":"Volzhanka",
    "gn:country_code":"RU",
    "gn:dem":21,
    "gn:feature_class":"P",
    "gn:feature_code":"PPL",
    "gn:name":"Volzhanka",
    "gn:population":0,
    "gn:timezone":"Europe/Volgograd",
    "iso:country":"RU",
    "name:rus_x_preferred":[
        "\u0412\u043e\u043b\u0436\u0430\u043d\u043a\u0430"
    ],
    "name:und_x_variant":[
        "Krasnooktyabr\u2019skiy",
        "Volzhanka"
    ],
    "wof:name":"Volzhanka",
    "wof:placetype":"locality"
},
  "geometry": {"coordinates":[44.777,48.9015],"type":"Point"}
}