{
  "type": "Feature",
  "properties": {
    "gn:admin1_code":"75",
    "gn:asciiname":"Moiseyevka",
    "gn:country_code":"RU",
    "gn:dem":74,
    "gn:feature_class":"P",
    "gn:feature_code":"PPL",
    "gn:name":"Moiseyevka",
    "gn:population":0,
    "gn:timezone":"Asia/Tomsk",
    "iso:country":"RU",
    "name:rus_x_preferred":[
        "\u041c\u043e\u0438\u0441\u0435\u0435\u0432\u043a\u0430"
    ],
    "name:und_x_variant":[
        "\u041c\u043e\u0438\u0441\u0435\u0435\u0432\u043a\u0430"
    ],
    "wof:name":"Moiseyevka",
    "wof:placetype":"locality"
},
  "geometry": {"coordinates":[79.11667,58.16667],"type":"Point"}
}