{
  "type": "Feature",
  "properties": {
    "gn:admin1_code":"12",
    "gn:asciiname":"Nokhchi-Keloy",
    "gn:country_code":"RU",
    "gn:dem":1128,
    "gn:feature_class":"P",
    "gn:feature_code":"PPL",
    "gn:name":"Nokhchi-Keloy",
    "gn:population":0,
    "gn:timezone":"Europe/Moscow",
    "iso:country":"RU",
    "name:che_x_preferred":[
        "Noh\u00e7i-Keloj"
    ],
    "name:che_x_variant":[
        "Nox\u00e7-Kela",
        "Nox\u00e7-Keloy",
        "\u041d\u043e\u0445\u0447-\u041a\u0435\u043b\u0430",
        "\u041d\u043e\u0445\u0447-\u041a\u0435\u043b\u043e\u0439"
    ],
    "name:rus_x_preferred":[
        "\u041d\u043e\u0445\u0447\u0438-\u041a\u0435\u043b\u043e\u0439"
    ],
    "wof:name":"Nokhchi-Keloy",
    "wof:placetype":"locality"
},
  "geometry": {"coordinates":[45.93239000000001,42.75855],"type":"Point"}
}