{
  "type": "Feature",
  "properties": {
    "gn:admin1_code":"73.0",
    "gn:asciiname":"Burbash",
    "gn:country_code":"RU",
    "gn:dem":155,
    "gn:feature_class":"P",
    "gn:feature_code":"PPL",
    "gn:name":"Burbash",
    "gn:population":0,
    "gn:timezone":"Europe/Moscow",
    "iso:country":"RU",
    "name:eng_x_preferred":[
        "Burbash"
    ],
    "name:nor_x_preferred":[
        "Burbasj"
    ],
    "name:rus_x_preferred":[
        "\u0411\u0443\u0440\u0431\u0430\u0448"
    ],
    "name:und_x_variant":[
        "\u0411\u0443\u0440\u0431\u0430\u0448",
        "Burbash"
    ],
    "wof:name":"Burbash",
    "wof:placetype":"locality"
},
  "geometry": {"coordinates":[50.4081,56.2985],"type":"Point"}
}