{
  "type": "Feature",
  "properties": {
    "gn:admin1_code":"65",
    "gn:asciiname":"Sadovka",
    "gn:country_code":"RU",
    "gn:dem":42,
    "gn:feature_class":"P",
    "gn:feature_code":"PPL",
    "gn:name":"Sadovka",
    "gn:population":0,
    "gn:timezone":"Europe/Samara",
    "iso:country":"RU",
    "name:rus_x_preferred":[
        "\u0421\u0430\u0434\u043e\u0432\u043a\u0430"
    ],
    "name:und_x_variant":[
        "\u0421\u0430\u0434\u043e\u0432\u043a\u0430"
    ],
    "wof:name":"Sadovka",
    "wof:placetype":"locality"
},
  "geometry": {"coordinates":[49.9614,52.3629],"type":"Point"}
}