{
  "type": "Feature",
  "properties": {
    "gn:admin1_code":"51",
    "gn:asciiname":"Smirnovo",
    "gn:country_code":"RU",
    "gn:dem":146,
    "gn:feature_class":"P",
    "gn:feature_code":"PPL",
    "gn:name":"Smirnovo",
    "gn:population":0,
    "gn:timezone":"Europe/Moscow",
    "iso:country":"RU",
    "name:rus_x_preferred":[
        "\u0421\u043c\u0438\u0440\u043d\u043e\u0432\u043e"
    ],
    "wof:name":"Smirnovo",
    "wof:placetype":"locality"
},
  "geometry": {"coordinates":[46.98498,57.62868],"type":"Point"}
}