{
  "type": "Feature",
  "properties": {
    "gn:admin1_code":"88",
    "gn:asciiname":"Perechki",
    "gn:country_code":"RU",
    "gn:dem":145,
    "gn:feature_class":"P",
    "gn:feature_code":"PPL",
    "gn:name":"Perechki",
    "gn:population":0,
    "gn:timezone":"Europe/Moscow",
    "iso:country":"RU",
    "name:rus_x_preferred":[
        "\u041f\u0435\u0440\u0435\u0447\u043a\u0438"
    ],
    "wof:name":"Perechki",
    "wof:placetype":"locality"
},
  "geometry": {"coordinates":[39.8491,57.1117],"type":"Point"}
}