{
  "type": "Feature",
  "properties": {
    "gn:admin1_code":"38",
    "gn:asciiname":"Sredniye Chuburki",
    "gn:country_code":"RU",
    "gn:dem":26,
    "gn:feature_class":"P",
    "gn:feature_code":"PPL",
    "gn:name":"Sredniye Chuburki",
    "gn:population":0,
    "gn:timezone":"Europe/Moscow",
    "iso:country":"RU",
    "name:rus_x_preferred":[
        "\u0421\u0440\u0435\u0434\u043d\u0438e \u0427\u0443\u0431\u0443\u0440\u043a\u0438"
    ],
    "name:und_x_variant":[
        "\u0421\u0440\u0435\u0434\u043d\u0438e \u0427\u0443\u0431\u0443\u0440\u043a\u0438"
    ],
    "wof:name":"Sredniye Chuburki",
    "wof:placetype":"locality"
},
  "geometry": {"coordinates":[39.3103,46.7359],"type":"Point"}
}