{
  "type": "Feature",
  "properties": {
    "gn:admin1_code":"5.0",
    "gn:asciiname":"Mokhovaya Pad'",
    "gn:country_code":"RU",
    "gn:dem":154,
    "gn:feature_class":"P",
    "gn:feature_code":"PPL",
    "gn:name":"Mokhovaya Pad\u2019",
    "gn:population":0,
    "gn:timezone":"Asia/Yakutsk",
    "iso:country":"RU",
    "name:rus_x_preferred":[
        "\u041c\u043e\u0445\u043e\u0432\u0430\u044f \u041f\u0430\u0434\u044c"
    ],
    "name:und_x_variant":[
        "Mokhovaya Pad\u2019"
    ],
    "wof:name":"Mokhovaya Pad'",
    "wof:placetype":"locality"
},
  "geometry": {"coordinates":[127.61319,50.37003],"type":"Point"}
}