{
  "type": "Feature",
  "properties": {
    "gn:admin1_code":"42",
    "gn:asciiname":"Khuttuze",
    "gn:country_code":"RU",
    "gn:dem":83,
    "gn:feature_class":"P",
    "gn:feature_code":"PPL",
    "gn:name":"Khuttuze",
    "gn:population":0,
    "gn:timezone":"Europe/Moscow",
    "iso:country":"RU",
    "name:fin_x_preferred":[
        "Huttunen"
    ],
    "name:rus_x_preferred":[
        "\u0425\u0443\u0442\u0442\u0443\u0437\u0435"
    ],
    "wof:name":"Khuttuze",
    "wof:placetype":"locality"
},
  "geometry": {"coordinates":[30.55,60.13333000000001],"type":"Point"}
}