{
  "type": "Feature",
  "properties": {
    "gn:admin1_code":"88",
    "gn:asciiname":"Garmonovo",
    "gn:country_code":"RU",
    "gn:dem":143,
    "gn:feature_class":"P",
    "gn:feature_code":"PPL",
    "gn:name":"Garmonovo",
    "gn:population":0,
    "gn:timezone":"Europe/Moscow",
    "iso:country":"RU",
    "name:rus_x_preferred":[
        "\u0413\u0430\u0440\u043c\u043e\u043d\u043e\u0432\u043e"
    ],
    "wof:name":"Garmonovo",
    "wof:placetype":"locality"
},
  "geometry": {"coordinates":[39.16779,57.88886],"type":"Point"}
}