{
  "type": "Feature",
  "properties": {
    "gn:admin1_code":"62",
    "gn:asciiname":"Mikhei",
    "gn:country_code":"RU",
    "gn:dem":143,
    "gn:feature_class":"P",
    "gn:feature_code":"PPL",
    "gn:name":"Mikhei",
    "gn:population":0,
    "gn:timezone":"Europe/Moscow",
    "iso:country":"RU",
    "name:rus_x_preferred":[
        "\u041c\u0438\u0445\u0435\u0438"
    ],
    "name:und_x_variant":[
        "Mikhay",
        "Mikhey",
        "Mikhei"
    ],
    "wof:name":"Mikhei",
    "wof:placetype":"locality"
},
  "geometry": {"coordinates":[40.7636,54.0098],"type":"Point"}
}