{
  "type": "Feature",
  "properties": {
    "gn:admin1_code":"80.0",
    "gn:asciiname":"Balma",
    "gn:country_code":"RU",
    "gn:dem":95,
    "gn:feature_class":"P",
    "gn:feature_code":"PPL",
    "gn:name":"Balma",
    "gn:population":0,
    "gn:timezone":"Europe/Samara",
    "iso:country":"RU",
    "name:eng_x_preferred":[
        "Balma"
    ],
    "name:nor_x_preferred":[
        "Balma"
    ],
    "name:rus_x_preferred":[
        "\u0411\u0430\u043b\u043c\u0430"
    ],
    "name:und_x_variant":[
        "Udmurtskaya Balma",
        "Bolma",
        "\u0411\u0430\u043b\u043c\u0430",
        "Balma"
    ],
    "wof:name":"Balma",
    "wof:placetype":"locality"
},
  "geometry": {"coordinates":[51.36613,57.03066],"type":"Point"}
}