{
  "type": "Feature",
  "properties": {
    "gn:admin1_code":"80.0",
    "gn:asciiname":"Balma",
    "gn:country_code":"RU",
    "gn:dem":95,
    "gn:feature_class":"P",
    "gn:feature_code":"PPL",
    "gn:name":"Balma",
    "gn:population":0,
    "gn:timezone":"Europe/Samara",
    "iso:country":"RU",
    "name:arg_x_preferred":[
        "Balma"
    ],
    "name:bug_x_preferred":[
        "Balma"
    ],
    "name:cat_x_preferred":[
        "Balmar"
    ],
    "name:ceb_x_preferred":[
        "Balma"
    ],
    "name:deu_x_preferred":[
        "Balma"
    ],
    "name:eng_x_preferred":[
        "Balma"
    ],
    "name:eus_x_preferred":[
        "Balmar"
    ],
    "name:fra_x_preferred":[
        "Balma"
    ],
    "name:hun_x_preferred":[
        "Balma"
    ],
    "name:ita_x_preferred":[
        "Balma"
    ],
    "name:jpn_x_preferred":[
        "\u30d0\u30eb\u30de"
    ],
    "name:lat_x_preferred":[
        "Balma"
    ],
    "name:mlg_x_preferred":[
        "Balma"
    ],
    "name:msa_x_preferred":[
        "Balma"
    ],
    "name:nld_x_preferred":[
        "Balma"
    ],
    "name:nor_x_preferred":[
        "Balma"
    ],
    "name:oci_x_preferred":[
        "Balmar"
    ],
    "name:pol_x_preferred":[
        "Balma"
    ],
    "name:ron_x_preferred":[
        "Balma"
    ],
    "name:rus_x_preferred":[
        "\u0411\u0430\u043b\u043c\u0430"
    ],
    "name:rus_x_variant":[
        "\u0411\u0430\u043b\u044c\u043c\u0430"
    ],
    "name:slk_x_preferred":[
        "Balma"
    ],
    "name:spa_x_preferred":[
        "Balma"
    ],
    "name:sqi_x_preferred":[
        "Balma"
    ],
    "name:srp_x_preferred":[
        "\u0411\u0430\u043b\u043c\u0430"
    ],
    "name:swe_x_preferred":[
        "Balma"
    ],
    "name:ukr_x_preferred":[
        "\u0411\u0430\u043b\u044c\u043c\u0430"
    ],
    "name:und_x_variant":[
        "Udmurtskaya Balma",
        "Bolma",
        "\u0411\u0430\u043b\u043c\u0430",
        "Balma"
    ],
    "name:vie_x_preferred":[
        "Balma"
    ],
    "name:war_x_preferred":[
        "Balma"
    ],
    "name:zho_x_preferred":[
        "\u5df4\u5c14\u9a6c"
    ],
    "wof:name":"Balma",
    "wof:placetype":"locality"
},
  "geometry": {"coordinates":[51.36613,57.03066],"type":"Point"}
}