{
  "type": "Feature",
  "properties": {
    "gn:admin1_code":"61",
    "gn:asciiname":"Tsentral'nyy",
    "gn:country_code":"RU",
    "gn:dem":91,
    "gn:feature_class":"P",
    "gn:feature_code":"PPL",
    "gn:name":"Tsentral\u2019nyy",
    "gn:population":0,
    "gn:timezone":"Europe/Moscow",
    "iso:country":"RU",
    "name:und_x_variant":[
        "Tsentral\u2019ny",
        "Tsentral\u2019nyy"
    ],
    "wof:name":"Tsentral'nyy",
    "wof:placetype":"locality"
},
  "geometry": {"coordinates":[41.07972,46.70361],"type":"Point"}
}