{
  "type": "Feature",
  "properties": {
    "gn:admin1_code":"61",
    "gn:asciiname":"Grushinskiy",
    "gn:country_code":"RU",
    "gn:dem":105,
    "gn:feature_class":"P",
    "gn:feature_code":"PPL",
    "gn:name":"Grushinskiy",
    "gn:population":0,
    "gn:timezone":"Europe/Moscow",
    "iso:country":"RU",
    "name:rus_x_preferred":[
        "\u0413\u0440\u0443\u0448\u0438\u043d\u0441\u043a\u0438\u0439"
    ],
    "name:und_x_variant":[
        "Verkhniye Grushki",
        "Grushenskiy",
        "Grushinskiy",
        "\u0413\u0440\u0443\u0448\u0438\u043d\u0441\u043a\u0438\u0439"
    ],
    "wof:name":"Grushinskiy",
    "wof:placetype":"locality"
},
  "geometry": {"coordinates":[41.76933,49.36578],"type":"Point"}
}