{
  "type": "Feature",
  "properties": {
    "gn:admin1_code":"6",
    "gn:asciiname":"Koskovo",
    "gn:country_code":"RU",
    "gn:dem":19,
    "gn:feature_class":"P",
    "gn:feature_code":"PPL",
    "gn:name":"Koskovo",
    "gn:population":0,
    "gn:timezone":"Europe/Moscow",
    "iso:country":"RU",
    "name:eng_x_preferred":[
        "Koskovo"
    ],
    "name:nor_x_preferred":[
        "Koskovo"
    ],
    "name:rus_x_preferred":[
        "\u041a\u043e\u0441\u043a\u043e\u0432\u043e"
    ],
    "wof:name":"Koskovo",
    "wof:placetype":"locality"
},
  "geometry": {"coordinates":[41.3621,64.33800000000001],"type":"Point"}
}