{
  "type": "Feature",
  "properties": {
    "gn:admin1_code":"69.0",
    "gn:asciiname":"Bernak",
    "gn:country_code":"RU",
    "gn:dem":176,
    "gn:feature_class":"P",
    "gn:feature_code":"PPL",
    "gn:name":"Bernak",
    "gn:population":0,
    "gn:timezone":"Europe/Moscow",
    "iso:country":"RU",
    "name:nor_x_preferred":[
        "Bernak"
    ],
    "name:rus_x_preferred":[
        "\u0411\u0435\u0440\u043d\u0430\u043a"
    ],
    "wof:name":"Bernak",
    "wof:placetype":"locality"
},
  "geometry": {"coordinates":[31.18333,55.41667],"type":"Point"}
}