{
  "type": "Feature",
  "properties": {
    "gn:admin1_code":"85.0",
    "gn:asciiname":"Cheremukhovo",
    "gn:cc2":"RU",
    "gn:country_code":"RU",
    "gn:dem":150,
    "gn:feature_class":"P",
    "gn:feature_code":"PPL",
    "gn:name":"Cher\u00ebmukhovo",
    "gn:population":0,
    "gn:timezone":"Europe/Moscow",
    "iso:country":"RU",
    "name:rus_x_preferred":[
        "\u0427\u0435\u0440\u0451\u043c\u0443\u0445\u043e\u0432\u043e"
    ],
    "name:und_x_variant":[
        "Chertun\u2019ya",
        "Cher\u00ebmukhovo"
    ],
    "wof:name":"Cheremukhovo",
    "wof:placetype":"locality"
},
  "geometry": {"coordinates":[40.18333,59.96666999999999],"type":"Point"}
}