{
  "type": "Feature",
  "properties": {
    "gn:admin1_code":"59.0",
    "gn:asciiname":"Solovey-Klyuch",
    "gn:country_code":"RU",
    "gn:dem":81,
    "gn:feature_class":"P",
    "gn:feature_code":"PPL",
    "gn:name":"Solovey-Klyuch",
    "gn:population":0,
    "gn:timezone":"Asia/Vladivostok",
    "iso:country":"RU",
    "name:rus_x_preferred":[
        "\u0421\u043e\u043b\u043e\u0432\u0435\u0439-\u041a\u043b\u044e\u0447"
    ],
    "wof:name":"Solovey-Klyuch",
    "wof:placetype":"locality"
},
  "geometry": {"coordinates":[132.03999999999999,43.39],"type":"Point"}
}