{
  "type": "Feature",
  "properties": {
    "gn:admin1_code":"47",
    "gn:asciiname":"Solntsevo",
    "gn:cc2":"RU",
    "gn:country_code":"RU",
    "gn:dem":136,
    "gn:feature_class":"P",
    "gn:feature_code":"PPL",
    "gn:name":"Solntsevo",
    "gn:population":0,
    "gn:timezone":"Europe/Moscow",
    "iso:country":"RU",
    "name:bel_x_preferred":[
        "\u0421\u043e\u043d\u0446\u0430\u0432\u0430"
    ],
    "name:ceb_x_preferred":[
        "\u0421\u043e\u043b\u043d\u0446\u0435\u0432\u043e"
    ],
    "name:deu_x_preferred":[
        "Solnzewo"
    ],
    "name:hye_x_preferred":[
        "\u054d\u0578\u056c\u0576\u0581\u0587\u0578"
    ],
    "name:ita_x_preferred":[
        "Solncevo"
    ],
    "name:nld_x_preferred":[
        "Solntsevo"
    ],
    "name:rus_x_preferred":[
        "\u0421\u043e\u043b\u043d\u0446\u0435\u0432\u043e"
    ],
    "name:ukr_x_preferred":[
        "\u0421\u043e\u043d\u0446\u0435\u0432\u0435"
    ],
    "name:und_x_variant":[
        "Sontsevo",
        "Solntsevo",
        "\u0421\u043e\u043b\u043d\u0446\u0435\u0432\u043e"
    ],
    "wof:name":"Solntsevo",
    "wof:placetype":"locality"
},
  "geometry": {"coordinates":[37.88333,56.61666999999999],"type":"Point"}
}