{
  "type": "Feature",
  "properties": {
    "gn:admin1_code":"21.0",
    "gn:asciiname":"Matrokhino",
    "gn:country_code":"RU",
    "gn:dem":96,
    "gn:feature_class":"P",
    "gn:feature_code":"PPL",
    "gn:name":"Matrokhino",
    "gn:population":0,
    "gn:timezone":"Europe/Moscow",
    "iso:country":"RU",
    "name:rus_x_preferred":[
        "\u041c\u0430\u0442\u0440\u043e\u0445\u0438\u043d\u043e"
    ],
    "wof:name":"Matrokhino",
    "wof:placetype":"locality"
},
  "geometry": {"coordinates":[41.30508,56.98414],"type":"Point"}
}