{
  "type": "Feature",
  "properties": {
    "gn:admin1_code":"73.0",
    "gn:asciiname":"Atabayevo",
    "gn:country_code":"RU",
    "gn:dem":84,
    "gn:feature_class":"P",
    "gn:feature_code":"PPL",
    "gn:name":"Atabayevo",
    "gn:population":0,
    "gn:timezone":"Europe/Moscow",
    "iso:country":"RU",
    "name:eng_x_preferred":[
        "Atabayevo"
    ],
    "name:nor_x_preferred":[
        "Atabajevo"
    ],
    "name:rus_x_preferred":[
        "\u0410\u0442\u0430\u0431\u0430\u0435\u0432\u043e"
    ],
    "name:und_x_variant":[
        "Atabaevo"
    ],
    "wof:name":"Atabayevo",
    "wof:placetype":"locality"
},
  "geometry": {"coordinates":[49.3558,55.2884],"type":"Point"}
}