{
  "type": "Feature",
  "properties": {
    "gn:admin1_code":"43",
    "gn:asciiname":"Yelizavetovka",
    "gn:country_code":"RU",
    "gn:dem":227,
    "gn:feature_class":"P",
    "gn:feature_code":"PPL",
    "gn:name":"Yelizavetovka",
    "gn:population":0,
    "gn:timezone":"Europe/Moscow",
    "iso:country":"RU",
    "name:rus_x_preferred":[
        "\u0415\u043b\u0438\u0437\u0430\u0432\u0435\u0442\u043e\u0432\u043a\u0430"
    ],
    "wof:name":"Yelizavetovka",
    "wof:placetype":"locality"
},
  "geometry": {"coordinates":[38.50306,52.92444],"type":"Point"}
}