{
  "type": "Feature",
  "properties": {
    "gn:admin1_code":"33.0",
    "gn:asciiname":"Malyye Chemodanovy",
    "gn:country_code":"RU",
    "gn:dem":123,
    "gn:feature_class":"P",
    "gn:feature_code":"PPL",
    "gn:name":"Malyye Chemodanovy",
    "gn:population":0,
    "gn:timezone":"Europe/Kirov",
    "iso:country":"RU",
    "name:rus_x_preferred":[
        "\u041c\u0430\u043b\u044b\u0435 \u0427\u0435\u043c\u043e\u0434\u0430\u043d\u043e\u0432\u044b"
    ],
    "wof:name":"Malyye Chemodanovy",
    "wof:placetype":"locality"
},
  "geometry": {"coordinates":[48.51635,58.64423000000001],"type":"Point"}
}