{
  "type": "Feature",
  "properties": {
    "gn:admin1_code":"8",
    "gn:asciiname":"Kyzyl-Yul",
    "gn:country_code":"RU",
    "gn:dem":191,
    "gn:feature_class":"P",
    "gn:feature_code":"PPL",
    "gn:name":"Kyzyl-Yul",
    "gn:population":0,
    "gn:timezone":"Asia/Yekaterinburg",
    "iso:country":"RU",
    "name:rus_x_preferred":[
        "\u041a\u044b\u0437\u044b\u043b-\u042e\u043b"
    ],
    "name:und_x_variant":[
        "Kzyl-Yul",
        "Kyzyl-Yul"
    ],
    "wof:name":"Kyzyl-Yul",
    "wof:placetype":"locality"
},
  "geometry": {"coordinates":[54.91667,53.86666999999999],"type":"Point"}
}