{
  "type": "Feature",
  "properties": {
    "gn:admin1_code":"6",
    "gn:asciiname":"Volost'",
    "gn:country_code":"RU",
    "gn:dem":23,
    "gn:feature_class":"P",
    "gn:feature_code":"PPL",
    "gn:name":"Volost\u2019",
    "gn:population":0,
    "gn:timezone":"Europe/Moscow",
    "iso:country":"RU",
    "wof:name":"Volost'",
    "wof:placetype":"locality"
},
  "geometry": {"coordinates":[44.16667,64.15000000000001],"type":"Point"}
}