{
  "type": "Feature",
  "properties": {
    "gn:admin1_code":"8",
    "gn:asciiname":"Novovasil'yevskiy",
    "gn:country_code":"RU",
    "gn:dem":502,
    "gn:feature_class":"P",
    "gn:feature_code":"PPL",
    "gn:name":"Novovasil\u2019yevskiy",
    "gn:population":0,
    "gn:timezone":"Asia/Yekaterinburg",
    "iso:country":"RU",
    "name:rus_x_preferred":[
        "\u041d\u043e\u0432\u043e\u0432\u0430\u0441\u0438\u043b\u044c\u0435\u0432\u0441\u043a\u0438\u0439"
    ],
    "name:und_x_variant":[
        "Novovasil\u2019yevskiy",
        "\u041d\u043e\u0432\u043e\u0432\u0430\u0441\u0438\u043b\u044c\u0435\u0432\u0441\u043a\u0438\u0439"
    ],
    "wof:name":"Novovasil'yevskiy",
    "wof:placetype":"locality"
},
  "geometry": {"coordinates":[57.55,51.96667],"type":"Point"}
}