{
  "type": "Feature",
  "properties": {
    "gn:admin1_code":"55.0",
    "gn:asciiname":"Artamonovka",
    "gn:country_code":"RU",
    "gn:dem":195,
    "gn:feature_class":"P",
    "gn:feature_code":"PPL",
    "gn:name":"Artamonovka",
    "gn:population":0,
    "gn:timezone":"Asia/Yekaterinburg",
    "iso:country":"RU",
    "name:nor_x_preferred":[
        "Artamonovka"
    ],
    "name:rus_x_preferred":[
        "\u0410\u0440\u0442\u0430\u043c\u043e\u043d\u043e\u0432\u043a\u0430"
    ],
    "wof:name":"Artamonovka",
    "wof:placetype":"locality"
},
  "geometry": {"coordinates":[53.23333,53.81667],"type":"Point"}
}