{
  "type": "Feature",
  "properties": {
    "gn:admin1_code":"85",
    "gn:asciiname":"Nikulino",
    "gn:country_code":"RU",
    "gn:dem":137,
    "gn:feature_class":"P",
    "gn:feature_code":"PPL",
    "gn:name":"Nikulino",
    "gn:population":0,
    "gn:timezone":"Europe/Moscow",
    "iso:country":"RU",
    "name:rus_x_preferred":[
        "\u041d\u0438\u043a\u0443\u043b\u0438\u043d\u043e"
    ],
    "wof:name":"Nikulino",
    "wof:placetype":"locality"
},
  "geometry": {"coordinates":[40.16103,59.09826],"type":"Point"}
}