{
  "type": "Feature",
  "properties": {
    "gn:admin1_code":"8",
    "gn:asciiname":"Kuseyevo",
    "gn:country_code":"RU",
    "gn:dem":433,
    "gn:feature_class":"P",
    "gn:feature_code":"PPL",
    "gn:name":"Kuseyevo",
    "gn:population":0,
    "gn:timezone":"Asia/Yekaterinburg",
    "iso:country":"RU",
    "name:eng_x_preferred":[
        "Kuseyevo"
    ],
    "name:nor_x_preferred":[
        "Kusejevo"
    ],
    "name:rus_x_preferred":[
        "\u041a\u0443\u0441\u0435\u0435\u0432\u043e"
    ],
    "name:und_x_variant":[
        "Kusiyeva",
        "\u041a\u0443\u0441\u0435\u0435\u0432\u043e",
        "Kuseyevo"
    ],
    "wof:name":"Kuseyevo",
    "wof:placetype":"locality"
},
  "geometry": {"coordinates":[58.42417,52.98389],"type":"Point"}
}