{
  "type": "Feature",
  "properties": {
    "gn:admin1_code":"77",
    "gn:asciiname":"Shikhurovo",
    "gn:country_code":"RU",
    "gn:dem":140,
    "gn:feature_class":"P",
    "gn:feature_code":"PPL",
    "gn:name":"Shikhurovo",
    "gn:population":0,
    "gn:timezone":"Europe/Moscow",
    "iso:country":"RU",
    "name:rus_x_preferred":[
        "\u0428\u0438\u0445\u0443\u0440\u043e\u0432\u043e"
    ],
    "wof:name":"Shikhurovo",
    "wof:placetype":"locality"
},
  "geometry": {"coordinates":[37.3161,57.4327],"type":"Point"}
}