{
  "type": "Feature",
  "properties": {
    "gn:admin1_code":"17",
    "gn:asciiname":"Chayka",
    "gn:country_code":"RU",
    "gn:dem":-12,
    "gn:feature_class":"P",
    "gn:feature_code":"PPL",
    "gn:name":"Chayka",
    "gn:population":0,
    "gn:timezone":"Europe/Moscow",
    "iso:country":"RU",
    "name:rus_x_preferred":[
        "\u0427\u0430\u0439\u043a\u0430"
    ],
    "name:und_x_variant":[
        "\u0427\u0430\u0439\u043a\u0430"
    ],
    "wof:name":"Chayka",
    "wof:placetype":"locality"
},
  "geometry": {"coordinates":[47.71683,42.70304],"type":"Point"}
}