{
  "type": "Feature",
  "properties": {
    "gn:admin1_code":"17",
    "gn:asciiname":"Chayka",
    "gn:country_code":"RU",
    "gn:dem":-12,
    "gn:feature_class":"P",
    "gn:feature_code":"PPL",
    "gn:name":"Chayka",
    "gn:population":0,
    "gn:timezone":"Europe/Moscow",
    "iso:country":"RU",
    "name:bel_x_preferred":[
        "\u0427\u0430\u0439\u043a\u0430"
    ],
    "name:bul_x_preferred":[
        "\u0427\u0430\u0439\u043a\u0430"
    ],
    "name:ceb_x_preferred":[
        "Chayka"
    ],
    "name:ces_x_preferred":[
        "\u010cajka"
    ],
    "name:deu_x_preferred":[
        "Tschaika"
    ],
    "name:ell_x_preferred":[
        "\u0393\u03bb\u03ac\u03c1\u03bf\u03c2"
    ],
    "name:hun_x_preferred":[
        "Csajka"
    ],
    "name:hye_x_preferred":[
        "\u0543\u0561\u0575\u0568"
    ],
    "name:ita_x_preferred":[
        "\u010caika"
    ],
    "name:jpn_x_preferred":[
        "\u30c1\u30e3\u30a4\u30ab"
    ],
    "name:rus_x_preferred":[
        "\u0427\u0430\u0439\u043a\u0430"
    ],
    "name:slk_x_preferred":[
        "\u010cajka"
    ],
    "name:swe_x_preferred":[
        "Chayka"
    ],
    "name:tat_x_preferred":[
        "\u0410\u043a\u0447\u0430\u0440\u043b\u0430\u043a"
    ],
    "name:ukr_x_preferred":[
        "\u0427\u0430\u0439\u043a\u0430"
    ],
    "name:und_x_variant":[
        "\u0427\u0430\u0439\u043a\u0430"
    ],
    "wof:name":"Chayka",
    "wof:placetype":"locality"
},
  "geometry": {"coordinates":[47.71683,42.70304],"type":"Point"}
}