{
  "type": "Feature",
  "properties": {
    "gn:admin1_code":"62",
    "gn:asciiname":"Naberezhnaya",
    "gn:country_code":"RU",
    "gn:dem":102,
    "gn:feature_class":"P",
    "gn:feature_code":"PPL",
    "gn:name":"Naberezhnaya",
    "gn:population":0,
    "gn:timezone":"Europe/Moscow",
    "iso:country":"RU",
    "name:rus_x_preferred":[
        "\u041d\u0430\u0431\u0435\u0440\u0435\u0436\u043d\u0430\u044f"
    ],
    "wof:name":"Naberezhnaya",
    "wof:placetype":"locality"
},
  "geometry": {"coordinates":[40.1484,53.8865],"type":"Point"}
}