{
  "type": "Feature",
  "properties": {
    "gn:admin1_code":"79.0",
    "gn:asciiname":"Orta-Adyr",
    "gn:country_code":"RU",
    "gn:dem":1721,
    "gn:feature_class":"P",
    "gn:feature_code":"PPL",
    "gn:name":"Orta-Adyr",
    "gn:population":0,
    "gn:timezone":"Asia/Krasnoyarsk",
    "iso:country":"RU",
    "name:rus_x_preferred":[
        "\u041e\u0440\u0442\u0430-\u0410\u0434\u044b\u0440"
    ],
    "wof:name":"Orta-Adyr",
    "wof:placetype":"locality"
},
  "geometry": {"coordinates":[95.4006,50.4542],"type":"Point"}
}