{
  "type": "Feature",
  "properties": {
    "gn:admin1_code":"77",
    "gn:asciiname":"Soroga",
    "gn:country_code":"RU",
    "gn:dem":213,
    "gn:feature_class":"P",
    "gn:feature_code":"PPL",
    "gn:name":"Soroga",
    "gn:population":0,
    "gn:timezone":"Europe/Moscow",
    "iso:country":"RU",
    "name:eng_x_preferred":[
        "Soroga"
    ],
    "name:nor_x_preferred":[
        "Soroga"
    ],
    "name:rus_x_preferred":[
        "\u0421\u043e\u0440\u043e\u0433\u0430"
    ],
    "name:und_x_variant":[
        "\u0421\u043e\u0440\u043e\u0433\u0430",
        "Soroga"
    ],
    "wof:name":"Soroga",
    "wof:placetype":"locality"
},
  "geometry": {"coordinates":[33.17902,57.17703],"type":"Point"}
}