{
  "type": "Feature",
  "properties": {
    "gn:admin1_code":"84",
    "gn:asciiname":"Krasnoye Znamya",
    "gn:country_code":"RU",
    "gn:dem":83,
    "gn:feature_class":"P",
    "gn:feature_code":"PPL",
    "gn:name":"Krasnoye Znamya",
    "gn:population":0,
    "gn:timezone":"Europe/Volgograd",
    "iso:country":"RU",
    "name:rus_x_preferred":[
        "\u041a\u0440\u0430\u0441\u043d\u043e\u0435 \u0417\u043d\u0430\u043c\u044f"
    ],
    "name:und_x_variant":[
        "\u041a\u0440\u0430\u0441\u043d\u043e\u0435 \u0417\u043d\u0430\u043c\u044f"
    ],
    "wof:name":"Krasnoye Znamya",
    "wof:placetype":"locality"
},
  "geometry": {"coordinates":[44.78333,49.95],"type":"Point"}
}