{
  "type": "Feature",
  "properties": {
    "gn:admin1_code":"37.0",
    "gn:asciiname":"Maloye Fedorkovo",
    "gn:country_code":"RU",
    "gn:dem":143,
    "gn:feature_class":"P",
    "gn:feature_code":"PPL",
    "gn:name":"Maloye Fedorkovo",
    "gn:population":0,
    "gn:timezone":"Europe/Moscow",
    "iso:country":"RU",
    "name:nor_x_preferred":[
        "Maloje Fedorkovo"
    ],
    "name:rus_x_preferred":[
        "\u041c\u0430\u043b\u043e\u0435 \u0424\u0435\u0434\u043e\u0440\u043a\u043e\u0432\u043e"
    ],
    "name:und_x_variant":[
        "F\u00ebdorovka",
        "Fedorkovo",
        "Maloye Fedorkovo"
    ],
    "wof:name":"Maloye Fedorkovo",
    "wof:placetype":"locality"
},
  "geometry": {"coordinates":[41.69347,58.66031],"type":"Point"}
}