{
  "type": "Feature",
  "properties": {
    "gn:country":"RU",
    "gn:fcode":"PPL",
    "gn:pop":0,
    "iso:country":"RU",
    "name:eng_x_preferred":[
        "Lychkovo"
    ],
    "name:nor_x_preferred":[
        "Lytsjkovo"
    ],
    "name:rus_x_preferred":[
        "\u041b\u044b\u0447\u043a\u043e\u0432\u043e"
    ],
    "qs:name":"Lychkovo",
    "qs:name_adm0":"Russia",
    "qs:name_adm1":"Novgorod Oblast",
    "qs:photos_9k":1,
    "qs:photos_9r":1,
    "qs:photos_all":1,
    "qs:photos_sr":0,
    "qs:placetype":"Town",
    "qs:pop_sr":"4",
    "wof:name":"Lychkovo",
    "wof:placetype":"locality",
    "wof:population":0
},
  "geometry": {"coordinates":[32.40385,57.91965],"type":"Point"}
}