{
  "type": "Feature",
  "properties": {
    "gn:admin1_code":"88",
    "gn:asciiname":"Skorodumovo",
    "gn:country_code":"RU",
    "gn:dem":106,
    "gn:feature_class":"P",
    "gn:feature_code":"PPL",
    "gn:name":"Skorodumovo",
    "gn:population":0,
    "gn:timezone":"Europe/Moscow",
    "iso:country":"RU",
    "name:rus_x_preferred":[
        "\u0421\u043a\u043e\u0440\u043e\u0434\u0443\u043c\u043e\u0432\u043e"
    ],
    "name:und_x_variant":[
        "\u0421\u043a\u043e\u0440\u043e\u0434\u0443\u043c\u043e\u0432\u043e"
    ],
    "wof:name":"Skorodumovo",
    "wof:placetype":"locality"
},
  "geometry": {"coordinates":[38.91286,58.00762],"type":"Point"}
}