{
  "type": "Feature",
  "properties": {
    "gn:admin1_code":"20",
    "gn:asciiname":"Korchat",
    "gn:country_code":"RU",
    "gn:dem":578,
    "gn:feature_class":"P",
    "gn:feature_code":"PPL",
    "gn:name":"Korchat",
    "gn:population":0,
    "gn:timezone":"Asia/Irkutsk",
    "iso:country":"RU",
    "name:rus_x_preferred":[
        "\u041a\u043e\u0440\u0447\u0430\u0442"
    ],
    "name:und_x_variant":[
        "\u041a\u043e\u0440\u0447\u0430\u0442"
    ],
    "wof:name":"Korchat",
    "wof:placetype":"locality"
},
  "geometry": {"coordinates":[99.25,54.46666999999999],"type":"Point"}
}