{
  "type": "Feature",
  "properties": {
    "gn:admin1_code":"8",
    "gn:asciiname":"Kadyrovo",
    "gn:country_code":"RU",
    "gn:dem":283,
    "gn:feature_class":"P",
    "gn:feature_code":"PPL",
    "gn:name":"Kadyrovo",
    "gn:population":0,
    "gn:timezone":"Asia/Yekaterinburg",
    "iso:country":"RU",
    "name:bak_x_preferred":[
        "\u04a0\u04d9\u0499\u0435\u0440"
    ],
    "name:che_x_preferred":[
        "\u041a\u0430\u0434\u044b\u0440\u043e\u0432\u043e"
    ],
    "name:hye_x_preferred":[
        "\u053f\u0561\u0564\u056b\u0580\u0578\u057e\u0578"
    ],
    "name:kat_x_preferred":[
        "\u10d9\u10d0\u10d3\u10d8\u10e0\u10dd\u10d5\u10dd"
    ],
    "name:kaz_x_preferred":[
        "\u041a\u0430\u0434\u044b\u0440"
    ],
    "name:kir_x_preferred":[
        "\u041a\u0430\u0434\u044b\u0440"
    ],
    "name:rus_x_preferred":[
        "\u041a\u0430\u0434\u044b\u0440\u043e\u0432\u043e"
    ],
    "name:tat_x_preferred":[
        "\u041a\u0430\u0437\u044b\u0440"
    ],
    "name:und_x_variant":[
        "Kadyrova",
        "Kadyrovo",
        "\u041a\u0430\u0434\u044b\u0440\u043e\u0432\u043e"
    ],
    "wof:name":"Kadyrovo",
    "wof:placetype":"locality"
},
  "geometry": {"coordinates":[56.26391,52.74811999999999],"type":"Point"}
}