{
  "type": "Feature",
  "properties": {
    "gn:admin1_code":"8",
    "gn:asciiname":"Kadyrovo",
    "gn:country_code":"RU",
    "gn:dem":283,
    "gn:feature_class":"P",
    "gn:feature_code":"PPL",
    "gn:name":"Kadyrovo",
    "gn:population":0,
    "gn:timezone":"Asia/Yekaterinburg",
    "iso:country":"RU",
    "name:rus_x_preferred":[
        "\u041a\u0430\u0434\u044b\u0440\u043e\u0432\u043e"
    ],
    "name:und_x_variant":[
        "Kadyrova",
        "Kadyrovo",
        "\u041a\u0430\u0434\u044b\u0440\u043e\u0432\u043e"
    ],
    "wof:name":"Kadyrovo",
    "wof:placetype":"locality"
},
  "geometry": {"coordinates":[56.26391,52.74811999999999],"type":"Point"}
}