{
  "type": "Feature",
  "properties": {
    "gn:admin1_code":"80",
    "gn:asciiname":"Ryabchik",
    "gn:country_code":"RU",
    "gn:dem":129,
    "gn:feature_class":"P",
    "gn:feature_code":"PPL",
    "gn:name":"Ryabchik",
    "gn:population":0,
    "gn:timezone":"Europe/Moscow",
    "iso:country":"RU",
    "wof:name":"Ryabchik",
    "wof:placetype":"locality"
},
  "geometry": {"coordinates":[52.76667,56.36666999999999],"type":"Point"}
}