{
  "type": "Feature",
  "properties": {
    "gn:admin1_code":"52",
    "gn:asciiname":"Novyy Borok",
    "gn:country_code":"RU",
    "gn:dem":47,
    "gn:feature_class":"P",
    "gn:feature_code":"PPL",
    "gn:name":"Novyy Borok",
    "gn:population":0,
    "gn:timezone":"Europe/Moscow",
    "iso:country":"RU",
    "name:rus_x_preferred":[
        "\u041d\u043e\u0432\u044b\u0439 \u0411\u043e\u0440\u043e\u043a"
    ],
    "name:und_x_variant":[
        "Novy Borok",
        "Novyy Borok",
        "\u041d\u043e\u0432\u044b\u0439 \u0411\u043e\u0440\u043e\u043a"
    ],
    "wof:name":"Novyy Borok",
    "wof:placetype":"locality"
},
  "geometry": {"coordinates":[30.74324,58.40617],"type":"Point"}
}