{
  "type": "Feature",
  "properties": {
    "gn:admin1_code":"52",
    "gn:asciiname":"Shepelevo",
    "gn:country_code":"RU",
    "gn:dem":217,
    "gn:feature_class":"P",
    "gn:feature_code":"PPL",
    "gn:name":"Shepel\u00ebvo",
    "gn:population":0,
    "gn:timezone":"Europe/Moscow",
    "iso:country":"RU",
    "name:rus_x_preferred":[
        "\u0428\u0435\u043f\u0435\u043b\u0451\u0432\u043e"
    ],
    "name:und_x_variant":[
        "Shepel\u00ebvo"
    ],
    "wof:name":"Shepelevo",
    "wof:placetype":"locality"
},
  "geometry": {"coordinates":[32.55197,57.43301999999999],"type":"Point"}
}