{
  "type": "Feature",
  "properties": {
    "gn:admin1_code":"41",
    "gn:asciiname":"Lukashevka",
    "gn:country_code":"RU",
    "gn:dem":183,
    "gn:feature_class":"P",
    "gn:feature_code":"PPL",
    "gn:name":"Lukash\u00ebvka",
    "gn:population":0,
    "gn:timezone":"Europe/Moscow",
    "iso:country":"RU",
    "name:rus_x_preferred":[
        "\u041b\u0443\u043a\u0430\u0448\u0451\u0432\u043a\u0430"
    ],
    "name:und_x_variant":[
        "Lukashevka Bredikhino",
        "Lukash\u00ebvka",
        "\u041b\u0443\u043a\u0430\u0448\u0451\u0432\u043a\u0430"
    ],
    "wof:name":"Lukashevka",
    "wof:placetype":"locality"
},
  "geometry": {"coordinates":[35.6839,51.6099],"type":"Point"}
}