{
  "type": "Feature",
  "properties": {
    "gn:admin1_code":"37",
    "gn:asciiname":"Shedrino",
    "gn:country_code":"RU",
    "gn:dem":161,
    "gn:feature_class":"P",
    "gn:feature_code":"PPL",
    "gn:name":"Shedrino",
    "gn:population":0,
    "gn:timezone":"Europe/Moscow",
    "iso:country":"RU",
    "name:rus_x_preferred":[
        "\u0428\u0435\u0434\u0440\u0438\u043d\u043e"
    ],
    "wof:name":"Shedrino",
    "wof:placetype":"locality"
},
  "geometry": {"coordinates":[42.4026,58.6175],"type":"Point"}
}