{
  "type": "Feature",
  "properties": {
    "gn:admin1_code":"52",
    "gn:asciiname":"Torbasino",
    "gn:country_code":"RU",
    "gn:dem":146,
    "gn:feature_class":"P",
    "gn:feature_code":"PPL",
    "gn:name":"Torbasino",
    "gn:population":0,
    "gn:timezone":"Europe/Moscow",
    "iso:country":"RU",
    "name:eng_x_preferred":[
        "Torbasino"
    ],
    "name:nor_x_preferred":[
        "Gorbino"
    ],
    "name:rus_x_preferred":[
        "\u0413\u043e\u0440\u0431\u0438\u043d\u043e"
    ],
    "wof:name":"Torbasino",
    "wof:placetype":"locality"
},
  "geometry": {"coordinates":[34.38885,58.18861999999999],"type":"Point"}
}