{
  "type": "Feature",
  "properties": {
    "gn:admin1_code":"6",
    "gn:asciiname":"Pole",
    "gn:country_code":"RU",
    "gn:dem":14,
    "gn:feature_class":"P",
    "gn:feature_code":"PPL",
    "gn:name":"Pole",
    "gn:population":0,
    "gn:timezone":"Europe/Moscow",
    "iso:country":"RU",
    "name:ceb_x_preferred":[
        "Pole"
    ],
    "name:ces_x_preferred":[
        "Pole"
    ],
    "name:deu_x_preferred":[
        "Pole"
    ],
    "name:eng_x_preferred":[
        "Pole"
    ],
    "name:fas_x_preferred":[
        "\u0642\u0637\u0628\u06cc"
    ],
    "name:fra_x_preferred":[
        "Pole"
    ],
    "name:heb_x_preferred":[
        "\u05e7\u05d5\u05d8\u05d1"
    ],
    "name:ita_x_preferred":[
        "Pole"
    ],
    "name:nld_x_preferred":[
        "Wandelstok#Poles"
    ],
    "name:nor_x_preferred":[
        "Pole"
    ],
    "name:pol_x_preferred":[
        "Pole"
    ],
    "name:rus_x_preferred":[
        "\u041f\u043e\u043b\u0435"
    ],
    "name:slk_x_preferred":[
        "Pole"
    ],
    "name:swe_x_preferred":[
        "Pole"
    ],
    "name:und_x_variant":[
        "\u041f\u043e\u043b\u0435",
        "Pole"
    ],
    "wof:name":"Pole",
    "wof:placetype":"locality"
},
  "geometry": {"coordinates":[39.2553,63.62973],"type":"Point"}
}