{
  "type": "Feature",
  "properties": {
    "gn:admin1_code":"33",
    "gn:asciiname":"Frolovskaya",
    "gn:country_code":"RU",
    "gn:dem":221,
    "gn:feature_class":"P",
    "gn:feature_code":"PPL",
    "gn:name":"Frolovskaya",
    "gn:population":0,
    "gn:timezone":"Europe/Kirov",
    "iso:country":"RU",
    "name:rus_x_preferred":[
        "\u0424\u0440\u043e\u043b\u043e\u0432\u0441\u043a\u0430\u044f"
    ],
    "name:und_x_variant":[
        "\u0424\u0440\u043e\u043b\u043e\u0432\u0441\u043a\u0430\u044f"
    ],
    "wof:name":"Frolovskaya",
    "wof:placetype":"locality"
},
  "geometry": {"coordinates":[53.14556,58.72944],"type":"Point"}
}