{
  "type": "Feature",
  "properties": {
    "gn:admin1_code":"17",
    "gn:asciiname":"Kutan Nogay",
    "gn:country_code":"RU",
    "gn:dem":-12,
    "gn:feature_class":"P",
    "gn:feature_code":"PPL",
    "gn:name":"Kutan Nogay",
    "gn:population":0,
    "gn:timezone":"Europe/Moscow",
    "iso:country":"RU",
    "name:rus_x_preferred":[
        "\u041a\u0443\u0442\u0430\u043d \u041d\u043e\u0433\u0430\u0439"
    ],
    "wof:name":"Kutan Nogay",
    "wof:placetype":"locality"
},
  "geometry": {"coordinates":[46.91927,43.45641],"type":"Point"}
}