{
  "type": "Feature",
  "properties": {
    "gn:admin1_code":"63",
    "gn:asciiname":"Mankyy-Tolono",
    "gn:country_code":"RU",
    "gn:dem":136,
    "gn:feature_class":"P",
    "gn:feature_code":"PPL",
    "gn:name":"Mankyy-Tolono",
    "gn:population":0,
    "gn:timezone":"Asia/Yakutsk",
    "iso:country":"RU",
    "name:rus_x_preferred":[
        "\u041c\u0430\u043d\u043a\u044b\u0439-\u0422\u043e\u043b\u043e\u043d\u043e"
    ],
    "wof:name":"Mankyy-Tolono",
    "wof:placetype":"locality"
},
  "geometry": {"coordinates":[127.416,62.8532],"type":"Point"}
}