{
  "type": "Feature",
  "properties": {
    "gn:admin1_code":"65",
    "gn:asciiname":"Novyy Shungut",
    "gn:country_code":"RU",
    "gn:dem":143,
    "gn:feature_class":"P",
    "gn:feature_code":"PPL",
    "gn:name":"Novyy Shungut",
    "gn:population":0,
    "gn:timezone":"Europe/Samara",
    "iso:country":"RU",
    "name:rus_x_preferred":[
        "\u041d\u043e\u0432\u044b\u0439 \u0428\u0443\u043d\u0433\u0443\u0442"
    ],
    "wof:name":"Novyy Shungut",
    "wof:placetype":"locality"
},
  "geometry": {"coordinates":[51.5514,53.986],"type":"Point"}
}