{
  "type": "Feature",
  "properties": {
    "gn:admin1_code":"51",
    "gn:asciiname":"Mirkhoyevo",
    "gn:country_code":"RU",
    "gn:dem":146,
    "gn:feature_class":"P",
    "gn:feature_code":"PPL",
    "gn:name":"Mirkhoyevo",
    "gn:population":0,
    "gn:timezone":"Europe/Moscow",
    "iso:country":"RU",
    "name:rus_x_preferred":[
        "\u041c\u0438\u0440\u0445\u043e\u0435\u0432\u043e"
    ],
    "name:und_x_variant":[
        "Mameshevo",
        "Mirkhoyevo"
    ],
    "wof:name":"Mirkhoyevo",
    "wof:placetype":"locality"
},
  "geometry": {"coordinates":[45.92309,55.49884],"type":"Point"}
}