{
  "type": "Feature",
  "properties": {
    "gn:admin1_code":"20",
    "gn:asciiname":"Serova",
    "gn:country_code":"RU",
    "gn:dem":437,
    "gn:feature_class":"P",
    "gn:feature_code":"PPL",
    "gn:name":"Serova",
    "gn:population":0,
    "gn:timezone":"Asia/Irkutsk",
    "iso:country":"RU",
    "name:rus_x_preferred":[
        "\u0421\u0435\u0440\u043e\u0432\u0430"
    ],
    "wof:name":"Serova",
    "wof:placetype":"locality"
},
  "geometry": {"coordinates":[103.21666999999999,54.56667],"type":"Point"}
}