{
  "type": "Feature",
  "properties": {
    "gn:admin1_code":"42",
    "gn:asciiname":"Voronino",
    "gn:country_code":"RU",
    "gn:dem":81,
    "gn:feature_class":"P",
    "gn:feature_code":"PPL",
    "gn:name":"Voronino",
    "gn:population":0,
    "gn:timezone":"Europe/Moscow",
    "iso:country":"RU",
    "name:rus_x_preferred":[
        "\u0412\u043e\u0440\u043e\u043d\u0438\u043d\u043e"
    ],
    "name:und_x_variant":[
        "\u0412\u043e\u0440\u043e\u043d\u0438\u043d\u043e"
    ],
    "wof:name":"Voronino",
    "wof:placetype":"locality"
},
  "geometry": {"coordinates":[28.4157,58.9058],"type":"Point"}
}