{
  "type": "Feature",
  "properties": {
    "gn:admin1_code":"51.0",
    "gn:asciiname":"Vypolzovo",
    "gn:country_code":"RU",
    "gn:dem":76,
    "gn:feature_class":"P",
    "gn:feature_code":"PPL",
    "gn:name":"Vypolzovo",
    "gn:population":0,
    "gn:timezone":"Europe/Moscow",
    "iso:country":"RU",
    "name:rus_x_preferred":[
        "\u0412\u044b\u043f\u043e\u043b\u0437\u043e\u0432\u043e"
    ],
    "name:tgk_x_preferred":[
        "\u0412\u0438\u043f\u043e\u043b\u0437\u043e\u0432\u043e"
    ],
    "wof:name":"Vypolzovo",
    "wof:placetype":"locality"
},
  "geometry": {"coordinates":[43.33796,56.64147],"type":"Point"}
}