{
  "type": "Feature",
  "properties": {
    "gn:admin1_code":"45.0",
    "gn:asciiname":"Veden'kino",
    "gn:country_code":"RU",
    "gn:dem":141,
    "gn:feature_class":"P",
    "gn:feature_code":"PPL",
    "gn:name":"Veden\u2019kino",
    "gn:population":0,
    "gn:timezone":"Europe/Moscow",
    "iso:country":"RU",
    "name:rus_x_preferred":[
        "\u0412\u0435\u0434\u0435\u043d\u044c\u043a\u0438\u043d\u043e"
    ],
    "name:und_x_variant":[
        "Veden\u2019kino"
    ],
    "wof:name":"Veden'kino",
    "wof:placetype":"locality"
},
  "geometry": {"coordinates":[48.86028,56.91611],"type":"Point"}
}