{
  "type": "Feature",
  "properties": {
    "gn:admin1_code":"10",
    "gn:asciiname":"Rechechka",
    "gn:country_code":"RU",
    "gn:dem":171,
    "gn:feature_class":"P",
    "gn:feature_code":"PPL",
    "gn:name":"Rechechka",
    "gn:population":0,
    "gn:timezone":"Europe/Moscow",
    "iso:country":"RU",
    "name:rus_x_preferred":[
        "\u0420\u0435\u0447\u0435\u0447\u043a\u0430"
    ],
    "wof:name":"Rechechka",
    "wof:placetype":"locality"
},
  "geometry": {"coordinates":[32.06556,52.68639],"type":"Point"}
}