{
  "type": "Feature",
  "properties": {
    "gn:admin1_code":"61",
    "gn:asciiname":"Veselo-Voznesenka",
    "gn:country_code":"RU",
    "gn:dem":22,
    "gn:feature_class":"P",
    "gn:feature_code":"PPL",
    "gn:name":"Ves\u00eblo-Voznesenka",
    "gn:population":0,
    "gn:timezone":"Europe/Moscow",
    "iso:country":"RU",
    "name:eng_x_preferred":[
        "Ves\u00eblo-Voznesenka"
    ],
    "name:nor_x_preferred":[
        "Veselo-Voznesenka"
    ],
    "name:rus_x_preferred":[
        "\u0412\u0435\u0441\u0435\u043b\u043e-\u0412\u043e\u0437\u043d\u0435\u0441\u0435\u043d\u043a\u0430"
    ],
    "name:ukr_x_preferred":[
        "Ves\u2019olo-Voznesenka"
    ],
    "name:und_x_variant":[
        "Platovo",
        "Veselo-Vozneseyevka",
        "Veselo-Voznesenskaya",
        "Ves\u00eblo-Voznesenka"
    ],
    "wof:name":"Veselo-Voznesenka",
    "wof:placetype":"locality"
},
  "geometry": {"coordinates":[38.3418,47.14541],"type":"Point"}
}