{
  "type": "Feature",
  "properties": {
    "gn:admin1_code":"73",
    "gn:asciiname":"Verkhniy Bersut",
    "gn:country_code":"RU",
    "gn:dem":105,
    "gn:feature_class":"P",
    "gn:feature_code":"PPL",
    "gn:name":"Verkhniy Bersut",
    "gn:population":0,
    "gn:timezone":"Europe/Moscow",
    "iso:country":"RU",
    "name:eng_x_preferred":[
        "Verkhniy Bersut"
    ],
    "name:nor_x_preferred":[
        "Verkhnij Bersut"
    ],
    "name:rus_x_preferred":[
        "\u0412\u0435\u0440\u0445\u043d\u0438\u0439 \u0411\u0435\u0440\u0441\u0443\u0442"
    ],
    "name:und_x_variant":[
        "\u0412\u0435\u0440\u0445\u043d\u0438\u0439 \u0411\u0435\u0440\u0441\u0443\u0442"
    ],
    "wof:name":"Verkhniy Bersut",
    "wof:placetype":"locality"
},
  "geometry": {"coordinates":[50.80343,55.72136999999999],"type":"Point"}
}