{
  "type": "Feature",
  "properties": {
    "gn:admin1_code":"47",
    "gn:asciiname":"Kuryn'",
    "gn:country_code":"RU",
    "gn:dem":180,
    "gn:feature_class":"P",
    "gn:feature_code":"PPL",
    "gn:name":"Kuryn\u2019",
    "gn:population":0,
    "gn:timezone":"Europe/Moscow",
    "iso:country":"RU",
    "name:rus_x_preferred":[
        "\u041a\u0443\u0440\u044b\u043d\u044c"
    ],
    "name:und_x_variant":[
        "Kuryn\u2019",
        "\u041a\u0443\u0440\u044b\u043d\u044c"
    ],
    "wof:name":"Kuryn'",
    "wof:placetype":"locality"
},
  "geometry": {"coordinates":[35.88472,55.6725],"type":"Point"}
}