{
  "type": "Feature",
  "properties": {
    "gn:admin1_code":"80",
    "gn:asciiname":"Kochish",
    "gn:country_code":"RU",
    "gn:dem":230,
    "gn:feature_class":"P",
    "gn:feature_code":"PPL",
    "gn:name":"Kochish",
    "gn:population":0,
    "gn:timezone":"Europe/Samara",
    "iso:country":"RU",
    "name:eng_x_preferred":[
        "Kochish"
    ],
    "name:nor_x_preferred":[
        "Kotsjisj"
    ],
    "name:rus_x_preferred":[
        "\u041a\u043e\u0447\u0438\u0448"
    ],
    "name:und_x_variant":[
        "\u041a\u043e\u0447\u0438\u0448",
        "Kochish"
    ],
    "wof:name":"Kochish",
    "wof:placetype":"locality"
},
  "geometry": {"coordinates":[52.52247,57.2442],"type":"Point"}
}