{
  "type": "Feature",
  "properties": {
    "gn:admin1_code":"29",
    "gn:asciiname":"Klenovka",
    "gn:country_code":"RU",
    "gn:dem":169,
    "gn:feature_class":"P",
    "gn:feature_code":"PPL",
    "gn:name":"Kl\u00ebnovka",
    "gn:population":0,
    "gn:timezone":"Asia/Novokuznetsk",
    "iso:country":"RU",
    "name:che_x_preferred":[
        "\u041a\u043b\u0435\u043d\u043e\u0432\u043a\u0430"
    ],
    "name:rus_x_preferred":[
        "\u041a\u043b\u0451\u043d\u043e\u0432\u043a\u0430"
    ],
    "name:rus_x_variant":[
        "\u041a\u043b\u0435\u043d\u043e\u0432\u043a\u0430"
    ],
    "name:und_x_variant":[
        "Kl\u00ebnovka",
        "\u041a\u043b\u0451\u043d\u043e\u0432\u043a\u0430"
    ],
    "wof:name":"Klenovka",
    "wof:placetype":"locality"
},
  "geometry": {"coordinates":[84.66916999999999,55.68417],"type":"Point"}
}