{
  "type": "Feature",
  "properties": {
    "gn:admin1_code":"10",
    "gn:asciiname":"Smorodinets",
    "gn:country_code":"RU",
    "gn:dem":196,
    "gn:feature_class":"P",
    "gn:feature_code":"PPL",
    "gn:name":"Smorodinets",
    "gn:population":0,
    "gn:timezone":"Europe/Moscow",
    "iso:country":"RU",
    "name:rus_x_preferred":[
        "\u0421\u043c\u043e\u0440\u043e\u0434\u0438\u043d\u0435\u0446"
    ],
    "wof:name":"Smorodinets",
    "wof:placetype":"locality"
},
  "geometry": {"coordinates":[33.1472,53.1935],"type":"Point"}
}