{
  "type": "Feature",
  "properties": {
    "gn:admin1_code":"69",
    "gn:asciiname":"Bol'shoye Polushino",
    "gn:country_code":"RU",
    "gn:dem":209,
    "gn:feature_class":"P",
    "gn:feature_code":"PPL",
    "gn:name":"Bol\u2019shoye Polushino",
    "gn:population":0,
    "gn:timezone":"Europe/Moscow",
    "iso:country":"RU",
    "wof:name":"Bol'shoye Polushino",
    "wof:placetype":"locality"
},
  "geometry": {"coordinates":[34.9819,55.21148],"type":"Point"}
}