{
  "type": "Feature",
  "properties": {
    "gn:admin1_code":"81",
    "gn:asciiname":"Urzhumskoye",
    "gn:country_code":"RU",
    "gn:dem":133,
    "gn:feature_class":"P",
    "gn:feature_code":"PPL",
    "gn:name":"Urzhumskoye",
    "gn:population":0,
    "gn:timezone":"Europe/Ulyanovsk",
    "iso:country":"RU",
    "name:eng_x_preferred":[
        "Urzhumskoye"
    ],
    "name:nor_x_preferred":[
        "Urzjumskoje"
    ],
    "name:rus_x_preferred":[
        "\u0423\u0440\u0436\u0443\u043c\u0441\u043a\u043e\u0435"
    ],
    "name:und_x_variant":[
        "Urzhu"
    ],
    "wof:name":"Urzhumskoye",
    "wof:placetype":"locality"
},
  "geometry": {"coordinates":[47.8388,54.2901],"type":"Point"}
}