{
  "type": "Feature",
  "properties": {
    "gn:admin1_code":"42",
    "gn:asciiname":"Izori",
    "gn:country_code":"RU",
    "gn:dem":44,
    "gn:feature_class":"P",
    "gn:feature_code":"PPL",
    "gn:name":"Izori",
    "gn:population":0,
    "gn:timezone":"Europe/Moscow",
    "iso:country":"RU",
    "name:nor_x_preferred":[
        "Izori"
    ],
    "name:rus_x_preferred":[
        "\u0418\u0437\u043e\u0440\u0438"
    ],
    "wof:name":"Izori",
    "wof:placetype":"locality"
},
  "geometry": {"coordinates":[29.08095,59.11824],"type":"Point"}
}