{
  "type": "Feature",
  "properties": {
    "gn:admin1_code":"75",
    "gn:asciiname":"Mokhovo",
    "gn:cc2":"RU",
    "gn:country_code":"RU",
    "gn:dem":72,
    "gn:feature_class":"P",
    "gn:feature_code":"PPL",
    "gn:name":"Mokhovo",
    "gn:population":0,
    "gn:timezone":"Asia/Tomsk",
    "iso:country":"RU",
    "name:che_x_preferred":[
        "\u041c\u043e\u0445\u043e\u0432\u043e"
    ],
    "name:eng_x_preferred":[
        "Mokhovo"
    ],
    "name:nor_x_preferred":[
        "Mokhovo"
    ],
    "name:rus_x_preferred":[
        "\u041c\u043e\u0445\u043e\u0432\u043e"
    ],
    "name:und_x_variant":[
        "Mokhova",
        "\u041c\u043e\u0445\u043e\u0432\u043e",
        "Mokhovo"
    ],
    "wof:name":"Mokhovo",
    "wof:placetype":"locality"
},
  "geometry": {"coordinates":[83.80611,58.43944000000001],"type":"Point"}
}