{
  "type": "Feature",
  "properties": {
    "gn:admin1_code":"46",
    "gn:asciiname":"Desyatyy Oktyabr'",
    "gn:country_code":"RU",
    "gn:dem":156,
    "gn:feature_class":"P",
    "gn:feature_code":"PPL",
    "gn:name":"Desyatyy Oktyabr\u2019",
    "gn:population":0,
    "gn:timezone":"Europe/Moscow",
    "iso:country":"RU",
    "name:rus_x_preferred":[
        "\u0414\u0435\u0441\u044f\u0442\u044b\u0439 \u041e\u043a\u0442\u044f\u0431\u0440\u044c"
    ],
    "name:und_x_variant":[
        "Desyatyy Oktyabr\u2019",
        "\u0414\u0435\u0441\u044f\u0442\u044b\u0439 \u041e\u043a\u0442\u044f\u0431\u0440\u044c"
    ],
    "wof:name":"Desyatyy Oktyabr'",
    "wof:placetype":"locality"
},
  "geometry": {"coordinates":[45.217,54.0311],"type":"Point"}
}