{
  "type": "Feature",
  "properties": {
    "gn:admin1_code":"76",
    "gn:asciiname":"Artakovo",
    "gn:country_code":"RU",
    "gn:dem":213,
    "gn:feature_class":"P",
    "gn:feature_code":"PPL",
    "gn:name":"Artakovo",
    "gn:population":0,
    "gn:timezone":"Europe/Moscow",
    "iso:country":"RU",
    "name:nor_x_preferred":[
        "Artakovo"
    ],
    "name:rus_x_preferred":[
        "\u0410\u0440\u0442\u0430\u043a\u043e\u0432\u043e"
    ],
    "wof:name":"Artakovo",
    "wof:placetype":"locality"
},
  "geometry": {"coordinates":[36.86583,53.77194],"type":"Point"}
}