{
  "type": "Feature",
  "properties": {
    "gn:admin1_code":"6",
    "gn:asciiname":"Mikshina Gora",
    "gn:country_code":"RU",
    "gn:dem":97,
    "gn:feature_class":"P",
    "gn:feature_code":"PPL",
    "gn:name":"Mikshina Gora",
    "gn:population":0,
    "gn:timezone":"Europe/Moscow",
    "iso:country":"RU",
    "name:eng_x_preferred":[
        "Mikshina Gora"
    ],
    "name:nor_x_preferred":[
        "Miksjina Gora"
    ],
    "name:rus_x_preferred":[
        "\u041c\u0438\u043a\u0448\u0438\u043d\u0430 \u0413\u043e\u0440\u0430"
    ],
    "name:und_x_variant":[
        "Mishkina Gora",
        "\u041c\u0438\u043a\u0448\u0438\u043d\u0430 \u0413\u043e\u0440\u0430",
        "Mikshina Gora"
    ],
    "wof:name":"Mikshina Gora",
    "wof:placetype":"locality"
},
  "geometry": {"coordinates":[48.98494,62.13144000000001],"type":"Point"}
}