{
  "type": "Feature",
  "properties": {
    "gn:admin1_code":"10",
    "gn:asciiname":"Staraya Guta",
    "gn:country_code":"RU",
    "gn:dem":167,
    "gn:feature_class":"P",
    "gn:feature_code":"PPL",
    "gn:name":"Staraya Guta",
    "gn:population":0,
    "gn:timezone":"Europe/Moscow",
    "iso:country":"RU",
    "name:eng_x_preferred":[
        "Staraya Guta"
    ],
    "name:nor_x_preferred":[
        "Staraja Guta"
    ],
    "name:rus_x_preferred":[
        "\u0421\u0442\u0430\u0440\u0430\u044f \u0413\u0443\u0442\u0430"
    ],
    "name:und_x_variant":[
        "\u0421\u0442\u0430\u0440\u0430\u044f \u0413\u0443\u0442\u0430",
        "Staraya Guta"
    ],
    "wof:name":"Staraya Guta",
    "wof:placetype":"locality"
},
  "geometry": {"coordinates":[32.53349,52.81919],"type":"Point"}
}