{
  "type": "Feature",
  "properties": {
    "gn:admin1_code":"69",
    "gn:asciiname":"Odrino",
    "gn:country_code":"RU",
    "gn:dem":219,
    "gn:feature_class":"P",
    "gn:feature_code":"PPL",
    "gn:name":"Odrino",
    "gn:population":0,
    "gn:timezone":"Europe/Moscow",
    "iso:country":"RU",
    "name:rus_x_preferred":[
        "\u041e\u0434\u0440\u0438\u043d\u043e"
    ],
    "name:und_x_variant":[
        "Adrino",
        "Andrino",
        "Adrina",
        "Odrino"
    ],
    "wof:name":"Odrino",
    "wof:placetype":"locality"
},
  "geometry": {"coordinates":[30.84941,54.89477],"type":"Point"}
}