{
  "type": "Feature",
  "properties": {
    "gn:admin1_code":"93",
    "gn:asciiname":"Vozdvizhenka",
    "gn:country_code":"RU",
    "gn:dem":836,
    "gn:feature_class":"P",
    "gn:feature_code":"PPL",
    "gn:name":"Vozdvizhenka",
    "gn:population":0,
    "gn:timezone":"Asia/Chita",
    "iso:country":"RU",
    "name:ceb_x_preferred":[
        "Vozdvizhenka"
    ],
    "name:rus_x_preferred":[
        "\u0412\u043e\u0437\u0434\u0432\u0438\u0436\u0435\u043d\u043a\u0430"
    ],
    "wof:name":"Vozdvizhenka",
    "wof:placetype":"locality"
},
  "geometry": {"coordinates":[119.54798,51.28972],"type":"Point"}
}