{
  "type": "Feature",
  "properties": {
    "gn:admin1_code":"27",
    "gn:asciiname":"Nikolinskoye",
    "gn:country_code":"RU",
    "gn:dem":1298,
    "gn:feature_class":"P",
    "gn:feature_code":"PPL",
    "gn:name":"Nikolinskoye",
    "gn:population":0,
    "gn:timezone":"Europe/Moscow",
    "iso:country":"RU",
    "name:rus_x_preferred":[
        "\u041d\u0438\u043a\u043e\u043b\u0438\u043d\u0441\u043a\u043e\u0435"
    ],
    "name:und_x_variant":[
        "\u041d\u0438\u043a\u043e\u043b\u0438\u043d\u0441\u043a\u043e\u0435"
    ],
    "wof:name":"Nikolinskoye",
    "wof:placetype":"locality"
},
  "geometry": {"coordinates":[41.76861,43.7175],"type":"Point"}
}