{
  "type": "Feature",
  "properties": {
    "gn:admin1_code":"52",
    "gn:asciiname":"Sapunov Bor",
    "gn:country_code":"RU",
    "gn:dem":24,
    "gn:feature_class":"P",
    "gn:feature_code":"PPL",
    "gn:name":"Sapunov Bor",
    "gn:population":0,
    "gn:timezone":"Europe/Moscow",
    "iso:country":"RU",
    "name:rus_x_preferred":[
        "\u0421\u0430\u043f\u0443\u043d\u043e\u0432 \u0411\u043e\u0440"
    ],
    "name:und_x_variant":[
        "\u0421\u0430\u043f\u0443\u043d\u043e\u0432 \u0411\u043e\u0440"
    ],
    "wof:name":"Sapunov Bor",
    "wof:placetype":"locality"
},
  "geometry": {"coordinates":[31.17494000000001,58.43293000000001],"type":"Point"}
}