{
  "type": "Feature",
  "properties": {
    "gn:admin1_code":"47.0",
    "gn:asciiname":"Tatishhevo",
    "gn:country_code":"RU",
    "gn:dem":149,
    "gn:feature_class":"P",
    "gn:feature_code":"PPL",
    "gn:name":"Tatishhevo",
    "gn:population":410,
    "gn:timezone":"Europe/Moscow",
    "iso:country":"RU",
    "name:eng_x_preferred":[
        "Tatishhevo"
    ],
    "name:rus_x_preferred":[
        "\u0422\u0430\u0442\u0438\u0449\u0435\u0432\u043e"
    ],
    "wof:name":"Tatishhevo",
    "wof:placetype":"locality",
    "wof:population":410
},
  "geometry": {"coordinates":[37.50415,56.39737],"type":"Point"}
}