{
  "type": "Feature",
  "properties": {
    "gn:admin1_code":"53",
    "gn:asciiname":"Bortsovo",
    "gn:country_code":"RU",
    "gn:dem":202,
    "gn:feature_class":"P",
    "gn:feature_code":"PPL",
    "gn:name":"Bortsovo",
    "gn:population":0,
    "gn:timezone":"Asia/Novosibirsk",
    "iso:country":"RU",
    "name:eng_x_preferred":[
        "Bortsovo"
    ],
    "name:nor_x_preferred":[
        "Bortsovo"
    ],
    "name:rus_x_preferred":[
        "\u0411\u043e\u0440\u0446\u043e\u0432\u043e"
    ],
    "wof:name":"Bortsovo",
    "wof:placetype":"locality"
},
  "geometry": {"coordinates":[84.0895,55.1504],"type":"Point"}
}