{
  "type": "Feature",
  "properties": {
    "gn:admin1_code":"34",
    "gn:asciiname":"Yuzhnyy Dzhebol",
    "gn:country_code":"RU",
    "gn:dem":138,
    "gn:feature_class":"P",
    "gn:feature_code":"PPL",
    "gn:name":"Yuzhnyy Dzhebol",
    "gn:population":0,
    "gn:timezone":"Europe/Moscow",
    "iso:country":"RU",
    "wof:name":"Yuzhnyy Dzhebol",
    "wof:placetype":"locality"
},
  "geometry": {"coordinates":[56.73333,62.31667],"type":"Point"}
}