{
  "type": "Feature",
  "properties": {
    "gn:admin1_code":"77",
    "gn:asciiname":"Kolodkino",
    "gn:country_code":"RU",
    "gn:dem":129,
    "gn:feature_class":"P",
    "gn:feature_code":"PPL",
    "gn:name":"Kolodkino",
    "gn:population":0,
    "gn:timezone":"Europe/Moscow",
    "iso:country":"RU",
    "name:rus_x_preferred":[
        "\u041a\u043e\u043b\u043e\u0434\u043a\u0438\u043d\u043e"
    ],
    "wof:name":"Kolodkino",
    "wof:placetype":"locality"
},
  "geometry": {"coordinates":[36.9949,56.683],"type":"Point"}
}