{
  "type": "Feature",
  "properties": {
    "gn:admin1_code":"4",
    "gn:asciiname":"Krasnyy Altay",
    "gn:country_code":"RU",
    "gn:dem":274,
    "gn:feature_class":"P",
    "gn:feature_code":"PPL",
    "gn:name":"Krasnyy Altay",
    "gn:population":0,
    "gn:timezone":"Asia/Barnaul",
    "iso:country":"RU",
    "name:rus_x_preferred":[
        "\u041a\u0440\u0430\u0441\u043d\u044b\u0439 \u0410\u043b\u0442\u0430\u0439"
    ],
    "name:und_x_variant":[
        "\u041a\u0440\u0430\u0441\u043d\u044b\u0439 \u0410\u043b\u0442\u0430\u0439"
    ],
    "wof:name":"Krasnyy Altay",
    "wof:placetype":"locality"
},
  "geometry": {"coordinates":[80.31667,52.28333],"type":"Point"}
}