{
  "type": "Feature",
  "properties": {
    "gn:country":"RU",
    "gn:fcode":"PPL",
    "gn:population":0,
    "iso:country":"RU",
    "name:rus_x_preferred":[
        "\u041f\u0435\u0442\u0440\u043e\u0432\u0441\u043a\u0438\u0439"
    ],
    "name:und_x_variant":[
        "Bol\u2019shiye Otary"
    ],
    "qs:name":"Petrovskij",
    "qs:name_adm0":"Russia",
    "qs:name_adm1":"Tatarstan Republic",
    "qs:photos_9r":0,
    "qs:photos_sr":0,
    "qs:placetype":"Town",
    "qs:pop_sr":"0",
    "wof:name":"Petrovskij",
    "wof:placetype":"locality",
    "wof:population":0
},
  "geometry": {"coordinates":[49.11519,55.67787],"type":"Point"}
}