{
  "type": "Feature",
  "properties": {
    "gn:admin1_code":"54",
    "gn:asciiname":"Kindigil'",
    "gn:country_code":"RU",
    "gn:dem":113,
    "gn:feature_class":"P",
    "gn:feature_code":"PPL",
    "gn:name":"Kindigil\u2019",
    "gn:population":0,
    "gn:timezone":"Asia/Omsk",
    "iso:country":"RU",
    "name:rus_x_preferred":[
        "\u041a\u0438\u043d\u0434\u0438\u0433\u0438\u043b\u044c"
    ],
    "name:und_x_variant":[
        "Kindigil\u2019",
        "\u041a\u0438\u043d\u0434\u0438\u0433\u0438\u043b\u044c"
    ],
    "wof:name":"Kindigil'",
    "wof:placetype":"locality"
},
  "geometry": {"coordinates":[71.61667,54.45],"type":"Point"}
}