{
  "type": "Feature",
  "properties": {
    "gn:admin1_code":"21.0",
    "gn:asciiname":"Bogatishchi",
    "gn:country_code":"RU",
    "gn:dem":111,
    "gn:feature_class":"P",
    "gn:feature_code":"PPL",
    "gn:name":"Bogatishchi",
    "gn:population":0,
    "gn:timezone":"Europe/Moscow",
    "iso:country":"RU",
    "name:rus_x_preferred":[
        "\u0411\u043e\u0433\u0430\u0442\u0438\u0449\u0438"
    ],
    "name:und_x_variant":[
        "Bogatishche",
        "Bogatishchi"
    ],
    "wof:name":"Bogatishchi",
    "wof:placetype":"locality"
},
  "geometry": {"coordinates":[41.87052,56.85762],"type":"Point"}
}