{
  "type": "Feature",
  "properties": {
    "gn:admin1_code":"62.0",
    "gn:asciiname":"Chichkino",
    "gn:country_code":"RU",
    "gn:dem":169,
    "gn:feature_class":"P",
    "gn:feature_code":"PPL",
    "gn:name":"Chichkino",
    "gn:population":0,
    "gn:timezone":"Europe/Moscow",
    "iso:country":"RU",
    "name:rus_x_preferred":[
        "\u0427\u0438\u0447\u043a\u0438\u043d\u043e"
    ],
    "name:und_x_variant":[
        "\u0427\u0438\u0447\u043a\u0438\u043d\u043e"
    ],
    "wof:name":"Chichkino",
    "wof:placetype":"locality"
},
  "geometry": {"coordinates":[39.71028,54.42471999999999],"type":"Point"}
}