{
  "type": "Feature",
  "properties": {
    "gn:admin1_code":"60",
    "gn:asciiname":"Pupovo",
    "gn:country_code":"RU",
    "gn:dem":89,
    "gn:feature_class":"P",
    "gn:feature_code":"PPL",
    "gn:name":"Pupovo",
    "gn:population":0,
    "gn:timezone":"Europe/Moscow",
    "iso:country":"RU",
    "name:rus_x_preferred":[
        "\u041f\u0443\u043f\u043e\u0432\u043e"
    ],
    "wof:name":"Pupovo",
    "wof:placetype":"locality"
},
  "geometry": {"coordinates":[28.78969,57.01156999999999],"type":"Point"}
}