{
  "type": "Feature",
  "properties": {
    "gn:admin1_code":"33.0",
    "gn:asciiname":"Karintorf",
    "gn:country_code":"RU",
    "gn:dem":120,
    "gn:feature_class":"P",
    "gn:feature_code":"PPL",
    "gn:name":"Karintorf",
    "gn:population":0,
    "gn:timezone":"Europe/Kirov",
    "iso:country":"RU",
    "name:rus_x_preferred":[
        "\u041a\u0430\u0440\u0438\u043d\u0442\u043e\u0440\u0444"
    ],
    "wof:name":"Karintorf",
    "wof:placetype":"locality"
},
  "geometry": {"coordinates":[50.24394,58.61489],"type":"Point"}
}