{
  "type": "Feature",
  "properties": {
    "gn:admin1_code":"73",
    "gn:asciiname":"Yantsevary",
    "gn:country_code":"RU",
    "gn:dem":81,
    "gn:feature_class":"P",
    "gn:feature_code":"PPL",
    "gn:name":"Yantsevary",
    "gn:population":0,
    "gn:timezone":"Europe/Moscow",
    "iso:country":"RU",
    "name:eng_x_preferred":[
        "Yantsevary"
    ],
    "name:nor_x_preferred":[
        "Jantsevary"
    ],
    "name:rus_x_preferred":[
        "\u042f\u043d\u0446\u0435\u0432\u0430\u0440\u044b"
    ],
    "name:und_x_variant":[
        "Yantsovar"
    ],
    "wof:name":"Yantsevary",
    "wof:placetype":"locality"
},
  "geometry": {"coordinates":[50.13859,55.76441],"type":"Point"}
}