{
  "type": "Feature",
  "properties": {
    "gn:admin1_code":"65",
    "gn:asciiname":"Kalinovyy Klyuch",
    "gn:country_code":"RU",
    "gn:dem":153,
    "gn:feature_class":"P",
    "gn:feature_code":"PPL",
    "gn:name":"Kalinovyy Klyuch",
    "gn:population":0,
    "gn:timezone":"Europe/Samara",
    "iso:country":"RU",
    "name:rus_x_preferred":[
        "\u041a\u0430\u043b\u0438\u043d\u043e\u0432\u044b\u0439 \u041a\u043b\u044e\u0447"
    ],
    "wof:name":"Kalinovyy Klyuch",
    "wof:placetype":"locality"
},
  "geometry": {"coordinates":[51.1643,53.7131],"type":"Point"}
}