{
  "type": "Feature",
  "properties": {
    "gn:admin1_code":"25.0",
    "gn:asciiname":"Bortniki",
    "gn:country_code":"RU",
    "gn:dem":203,
    "gn:feature_class":"P",
    "gn:feature_code":"PPL",
    "gn:name":"Bortniki",
    "gn:population":0,
    "gn:timezone":"Europe/Moscow",
    "iso:country":"RU",
    "name:nor_x_preferred":[
        "Bortniki"
    ],
    "name:rus_x_preferred":[
        "\u0411\u043e\u0440\u0442\u043d\u0438\u043a\u0438"
    ],
    "wof:name":"Bortniki",
    "wof:placetype":"locality"
},
  "geometry": {"coordinates":[36.31878,54.72743000000001],"type":"Point"}
}