{
  "type": "Feature",
  "properties": {
    "gn:admin1_code":"77",
    "gn:asciiname":"Kaloshino",
    "gn:country_code":"RU",
    "gn:dem":153,
    "gn:feature_class":"P",
    "gn:feature_code":"PPL",
    "gn:name":"Kaloshino",
    "gn:population":0,
    "gn:timezone":"Europe/Moscow",
    "iso:country":"RU",
    "name:nor_x_preferred":[
        "Kalosjino"
    ],
    "name:rus_x_preferred":[
        "\u041a\u0430\u043b\u043e\u0448\u0438\u043d\u043e"
    ],
    "wof:name":"Kaloshino",
    "wof:placetype":"locality"
},
  "geometry": {"coordinates":[35.6662,56.56177],"type":"Point"}
}