{
  "type": "Feature",
  "properties": {
    "gn:admin1_code":"8",
    "gn:asciiname":"Murzabulatova",
    "gn:cc2":"RU",
    "gn:country_code":"RU",
    "gn:dem":498,
    "gn:feature_class":"P",
    "gn:feature_code":"PPL",
    "gn:name":"Murzabulatova",
    "gn:population":0,
    "gn:timezone":"Asia/Yekaterinburg",
    "iso:country":"RU",
    "name:rus_x_preferred":[
        "\u041c\u0443\u0440\u0437\u0430\u0431\u0443\u043b\u0430\u0442\u043e\u0432\u0430"
    ],
    "name:und_x_variant":[
        "Murzabulatovo",
        "Murzabulatova",
        "\u041c\u0443\u0440\u0437\u0430\u0431\u0443\u043b\u0430\u0442\u043e\u0432\u0430"
    ],
    "wof:name":"Murzabulatova",
    "wof:placetype":"locality"
},
  "geometry": {"coordinates":[58.01667,52.53333000000001],"type":"Point"}
}