{
  "type": "Feature",
  "properties": {
    "gn:admin1_code":"16",
    "gn:asciiname":"Anatkasy",
    "gn:country_code":"RU",
    "gn:dem":152,
    "gn:feature_class":"P",
    "gn:feature_code":"PPL",
    "gn:name":"Anatkasy",
    "gn:population":0,
    "gn:timezone":"Europe/Moscow",
    "iso:country":"RU",
    "name:rus_x_preferred":[
        "\u0410\u043d\u0430\u0442\u043a\u0430\u0441\u044b"
    ],
    "wof:name":"Anatkasy",
    "wof:placetype":"locality"
},
  "geometry": {"coordinates":[46.9194,56.0858],"type":"Point"}
}