{
  "type": "Feature",
  "properties": {
    "gn:admin1_code":"80",
    "gn:asciiname":"Prokhorovo",
    "gn:country_code":"RU",
    "gn:dem":202,
    "gn:feature_class":"P",
    "gn:feature_code":"PPL",
    "gn:name":"Prokhorovo",
    "gn:population":0,
    "gn:timezone":"Europe/Samara",
    "iso:country":"RU",
    "name:eng_x_preferred":[
        "Prokhorovo"
    ],
    "name:nor_x_preferred":[
        "Prokhorovo"
    ],
    "name:rus_x_preferred":[
        "\u041f\u0440\u043e\u0445\u043e\u0440\u043e\u0432\u043e"
    ],
    "name:und_x_variant":[
        "Prokhorovtsy",
        "\u041f\u0440\u043e\u0445\u043e\u0440\u043e\u0432\u043e",
        "Prokhorovo"
    ],
    "wof:name":"Prokhorovo",
    "wof:placetype":"locality"
},
  "geometry": {"coordinates":[52.8056,57.7607],"type":"Point"}
}