{
  "type": "Feature",
  "properties": {
    "gn:admin1_code":"38",
    "gn:asciiname":"Novokarskiy",
    "gn:country_code":"RU",
    "gn:dem":166,
    "gn:feature_class":"P",
    "gn:feature_code":"PPL",
    "gn:name":"Novokarskiy",
    "gn:population":0,
    "gn:timezone":"Europe/Moscow",
    "iso:country":"RU",
    "name:rus_x_preferred":[
        "\u041d\u043e\u0432\u043e\u043a\u0430\u0440\u0441\u043a\u0438\u0439"
    ],
    "name:und_x_variant":[
        "\u041d\u043e\u0432\u043e\u043a\u0430\u0440\u0441\u043a\u0438\u0439"
    ],
    "wof:name":"Novokarskiy",
    "wof:placetype":"locality"
},
  "geometry": {"coordinates":[41.1433,45.2085],"type":"Point"}
}