{
  "type": "Feature",
  "properties": {
    "gn:admin1_code":"53",
    "gn:asciiname":"Novostroyka",
    "gn:country_code":"RU",
    "gn:dem":169,
    "gn:feature_class":"P",
    "gn:feature_code":"PPL",
    "gn:name":"Novostroyka",
    "gn:population":0,
    "gn:timezone":"Asia/Novosibirsk",
    "iso:country":"RU",
    "name:eng_x_preferred":[
        "Novostroyka"
    ],
    "name:nor_x_preferred":[
        "Novostrojka"
    ],
    "name:rus_x_preferred":[
        "\u041d\u043e\u0432\u043e\u0441\u0442\u0440\u043e\u0439\u043a\u0430"
    ],
    "name:und_x_variant":[
        "Kamenka",
        "\u041d\u043e\u0432\u043e\u0441\u0442\u0440\u043e\u0439\u043a\u0430",
        "Novostroyka"
    ],
    "wof:name":"Novostroyka",
    "wof:placetype":"locality"
},
  "geometry": {"coordinates":[82.26439999999999,53.8951],"type":"Point"}
}