{
  "type": "Feature",
  "properties": {
    "gn:admin1_code":"60",
    "gn:asciiname":"Kriplyanka",
    "gn:country_code":"RU",
    "gn:dem":151,
    "gn:feature_class":"P",
    "gn:feature_code":"PPL",
    "gn:name":"Kriplyanka",
    "gn:population":0,
    "gn:timezone":"Europe/Moscow",
    "iso:country":"RU",
    "name:rus_x_preferred":[
        "\u041a\u0440\u0438\u043f\u043b\u044f\u043d\u043a\u0430"
    ],
    "name:und_x_variant":[
        "\u041a\u0440\u0438\u043f\u043b\u044f\u043d\u043a\u0430"
    ],
    "wof:name":"Kriplyanka",
    "wof:placetype":"locality"
},
  "geometry": {"coordinates":[30.6125,56.2815],"type":"Point"}
}