{
  "type": "Feature",
  "properties": {
    "gn:admin1_code":"65",
    "gn:asciiname":"Panikla",
    "gn:country_code":"RU",
    "gn:dem":162,
    "gn:feature_class":"P",
    "gn:feature_code":"PPL",
    "gn:name":"Panikla",
    "gn:population":0,
    "gn:timezone":"Europe/Samara",
    "iso:country":"RU",
    "name:rus_x_preferred":[
        "\u041f\u0430\u043d\u0438\u043a\u043b\u0430"
    ],
    "wof:name":"Panikla",
    "wof:placetype":"locality"
},
  "geometry": {"coordinates":[52.291,53.9777],"type":"Point"}
}