{
  "type": "Feature",
  "properties": {
    "gn:admin1_code":"85",
    "gn:asciiname":"Vveden'ye-Sysoyevo",
    "gn:country_code":"RU",
    "gn:dem":199,
    "gn:feature_class":"P",
    "gn:feature_code":"PPL",
    "gn:name":"Vveden\u2019ye-Sysoyevo",
    "gn:population":0,
    "gn:timezone":"Europe/Moscow",
    "iso:country":"RU",
    "name:und_x_variant":[
        "Sysoyevo",
        "Vveden\u2019ye-Sysoyevo"
    ],
    "wof:name":"Vveden'ye-Sysoyevo",
    "wof:placetype":"locality"
},
  "geometry": {"coordinates":[43.16325,59.64927],"type":"Point"}
}