{
  "type": "Feature",
  "properties": {
    "gn:admin1_code":"69",
    "gn:asciiname":"Kopyl'niki",
    "gn:country_code":"RU",
    "gn:dem":206,
    "gn:feature_class":"P",
    "gn:feature_code":"PPL",
    "gn:name":"Kopyl\u2019niki",
    "gn:population":0,
    "gn:timezone":"Europe/Moscow",
    "iso:country":"RU",
    "name:rus_x_preferred":[
        "\u041a\u043e\u043f\u044b\u043b\u044c\u043d\u0438\u043a\u0438"
    ],
    "name:und_x_variant":[
        "Kopyl\u2019niki"
    ],
    "wof:name":"Kopyl'niki",
    "wof:placetype":"locality"
},
  "geometry": {"coordinates":[31.43658,55.57822],"type":"Point"}
}