{
  "type": "Feature",
  "properties": {
    "gn:admin1_code":"24",
    "gn:asciiname":"Privol'nyy",
    "gn:country_code":"RU",
    "gn:dem":-7,
    "gn:feature_class":"P",
    "gn:feature_code":"PPL",
    "gn:name":"Privol\u2019nyy",
    "gn:population":0,
    "gn:timezone":"Europe/Moscow",
    "iso:country":"RU",
    "name:eng_x_preferred":[
        "Privol'nyy"
    ],
    "name:nor_x_preferred":[
        "Privolnyj"
    ],
    "name:rus_x_preferred":[
        "Privol\u2019nyy"
    ],
    "name:rus_x_variant":[
        "\u041f\u0440\u0438\u0432\u043e\u043b\u044c\u043d\u044b\u0439"
    ],
    "name:und_x_variant":[
        "\u041f\u0440\u0438\u0432\u043e\u043b\u044c\u043d\u044b\u0439",
        "Privol\u2019nyy"
    ],
    "wof:name":"Privol'nyy",
    "wof:placetype":"locality"
},
  "geometry": {"coordinates":[45.7228,46.5727],"type":"Point"}
}