{
  "type": "Feature",
  "properties": {
    "gn:admin1_code":"13",
    "gn:asciiname":"Malaya Ul'trakova",
    "gn:country_code":"RU",
    "gn:dem":276,
    "gn:feature_class":"P",
    "gn:feature_code":"PPL",
    "gn:name":"Malaya Ul\u2019trakova",
    "gn:population":0,
    "gn:timezone":"Asia/Yekaterinburg",
    "iso:country":"RU",
    "name:eng_x_preferred":[
        "Malaya Ul'trakova"
    ],
    "name:nor_x_preferred":[
        "Mal.Ultrakova"
    ],
    "name:rus_x_preferred":[
        "\u041c\u0430\u043b.\u0423\u043b\u044c\u0442\u0440\u0430\u043a\u043e\u0432\u0430"
    ],
    "name:rus_x_variant":[
        "\u041c\u0430\u043b\u0430\u044f \u0423\u043b\u044c\u0442\u0440\u0430\u043a\u043e\u0432\u0430"
    ],
    "name:und_x_variant":[
        "Malaya Ul\u2019trakova",
        "\u041c\u0430\u043b\u0430\u044f \u0423\u043b\u044c\u0442\u0440\u0430\u043a\u043e\u0432\u0430"
    ],
    "wof:name":"Malaya Ul'trakova",
    "wof:placetype":"locality"
},
  "geometry": {"coordinates":[60.769,55.4078],"type":"Point"}
}