{
  "type": "Feature",
  "properties": {
    "gn:admin1_code":"90.0",
    "gn:asciiname":"Galyukova",
    "gn:country_code":"RU",
    "gn:dem":211,
    "gn:feature_class":"P",
    "gn:feature_code":"PPL",
    "gn:name":"Galyukova",
    "gn:population":0,
    "gn:timezone":"Asia/Yekaterinburg",
    "iso:country":"RU",
    "name:che_x_preferred":[
        "\u0413\u0430\u043b\u044e\u043a\u043e\u0432\u0430"
    ],
    "name:koi_x_preferred":[
        "\u0413\u0430\u043b\u044e\u043a"
    ],
    "name:rus_x_preferred":[
        "\u0413\u0430\u043b\u044e\u043a\u043e\u0432\u0430"
    ],
    "wof:name":"Galyukova",
    "wof:placetype":"locality"
},
  "geometry": {"coordinates":[54.7154,58.7445],"type":"Point"}
}