{
  "type": "Feature",
  "properties": {
    "gn:admin1_code":"85",
    "gn:asciiname":"Matoshkino",
    "gn:country_code":"RU",
    "gn:dem":190,
    "gn:feature_class":"P",
    "gn:feature_code":"PPL",
    "gn:name":"Matoshkino",
    "gn:population":0,
    "gn:timezone":"Europe/Moscow",
    "iso:country":"RU",
    "name:rus_x_preferred":[
        "\u041c\u0430\u0442\u043e\u0448\u043a\u0438\u043d\u043e"
    ],
    "wof:name":"Matoshkino",
    "wof:placetype":"locality"
},
  "geometry": {"coordinates":[40.72283,59.21624],"type":"Point"}
}