{
  "type": "Feature",
  "properties": {
    "gn:admin1_code":"34",
    "gn:asciiname":"Verkhniy Vyl'yb",
    "gn:country_code":"RU",
    "gn:dem":148,
    "gn:feature_class":"P",
    "gn:feature_code":"PPL",
    "gn:name":"Verkhniy Vyl\u2019yb",
    "gn:population":0,
    "gn:timezone":"Europe/Moscow",
    "iso:country":"RU",
    "wof:name":"Verkhniy Vyl'yb",
    "wof:placetype":"locality"
},
  "geometry": {"coordinates":[49.45546,63.48986],"type":"Point"}
}