{
  "type": "Feature",
  "properties": {
    "gn:admin1_code":"25",
    "gn:asciiname":"Manino",
    "gn:country_code":"RU",
    "gn:dem":246,
    "gn:feature_class":"P",
    "gn:feature_code":"PPL",
    "gn:name":"Manino",
    "gn:population":0,
    "gn:timezone":"Europe/Moscow",
    "iso:country":"RU",
    "name:rus_x_preferred":[
        "\u041c\u0430\u043d\u0438\u043d\u043e"
    ],
    "wof:name":"Manino",
    "wof:placetype":"locality"
},
  "geometry": {"coordinates":[35.71667,55.28333000000001],"type":"Point"}
}