{
  "type": "Feature",
  "properties": {
    "gn:country":"RU",
    "gn:fcode":"PPL",
    "gn:population":3463,
    "iso:country":"RU",
    "name:eng_x_preferred":[
        "Pichayevo"
    ],
    "name:nor_x_preferred":[
        "Pitsjajevo"
    ],
    "name:rus_x_preferred":[
        "\u041f\u0438\u0447\u0430\u0435\u0432\u043e"
    ],
    "name:und_x_variant":[
        "Pichayevo Pervoye"
    ],
    "qs:name":"Pichayevo",
    "qs:name_adm0":"Russia",
    "qs:name_adm1":"Tambov Oblast",
    "qs:photos_9r":0,
    "qs:photos_sr":0,
    "qs:placetype":"Town",
    "qs:pop_sr":"4",
    "wd:wordcount":40,
    "wof:name":"Pichayevo",
    "wof:placetype":"locality",
    "wof:population":3463
},
  "geometry": {"coordinates":[42.20323,53.23627],"type":"Point"}
}