{
  "type": "Feature",
  "properties": {
    "gn:admin1_code":"56",
    "gn:asciiname":"Poselki",
    "gn:country_code":"RU",
    "gn:dem":212,
    "gn:feature_class":"P",
    "gn:feature_code":"PPL",
    "gn:name":"Pos\u00eblki",
    "gn:population":0,
    "gn:timezone":"Europe/Moscow",
    "iso:country":"RU",
    "name:rus_x_preferred":[
        "\u041f\u043e\u0441\u0451\u043b\u043a\u0438"
    ],
    "name:und_x_variant":[
        "Pos\u00eblki"
    ],
    "wof:name":"Poselki",
    "wof:placetype":"locality"
},
  "geometry": {"coordinates":[36.58333,52.73333],"type":"Point"}
}