{
  "type": "Feature",
  "properties": {
    "gn:admin1_code":"16",
    "gn:asciiname":"Ryndino",
    "gn:country_code":"RU",
    "gn:dem":174,
    "gn:feature_class":"P",
    "gn:feature_code":"PPL",
    "gn:name":"Ryndino",
    "gn:population":0,
    "gn:timezone":"Europe/Moscow",
    "iso:country":"RU",
    "name:rus_x_preferred":[
        "\u0420\u044b\u043d\u0434\u0438\u043d\u043e"
    ],
    "wof:name":"Ryndino",
    "wof:placetype":"locality"
},
  "geometry": {"coordinates":[46.31289,55.08082],"type":"Point"}
}