{
  "type": "Feature",
  "properties": {
    "gn:admin1_code":"60.0",
    "gn:asciiname":"Gorushka",
    "gn:country_code":"RU",
    "gn:dem":51,
    "gn:feature_class":"P",
    "gn:feature_code":"PPL",
    "gn:name":"Gorushka",
    "gn:population":0,
    "gn:timezone":"Europe/Moscow",
    "iso:country":"RU",
    "name:rus_x_preferred":[
        "\u0413\u043e\u0440\u0443\u0448\u043a\u0430"
    ],
    "name:und_x_variant":[
        "Bol\u2019shaya Gorushka",
        "Gorushka"
    ],
    "wof:name":"Gorushka",
    "wof:placetype":"locality"
},
  "geometry": {"coordinates":[28.4201,57.673],"type":"Point"}
}