{
  "type": "Feature",
  "properties": {
    "gn:admin1_code":"9.0",
    "gn:asciiname":"Druzhnyy Vtoroy",
    "gn:country_code":"RU",
    "gn:dem":151,
    "gn:feature_class":"P",
    "gn:feature_code":"PPL",
    "gn:name":"Druzhnyy Vtoroy",
    "gn:population":0,
    "gn:timezone":"Europe/Moscow",
    "iso:country":"RU",
    "name:rus_x_preferred":[
        "\u0414\u0440\u0443\u0436\u043d\u044b\u0439 \u0412\u0442\u043e\u0440\u043e\u0439"
    ],
    "name:und_x_variant":[
        "Druzhnyy",
        "Druzhnyy Vtoroy"
    ],
    "wof:name":"Druzhnyy Vtoroy",
    "wof:placetype":"locality"
},
  "geometry": {"coordinates":[37.2742,50.92977],"type":"Point"}
}