{
  "type": "Feature",
  "properties": {
    "gn:admin1_code":"73",
    "gn:asciiname":"Artamonovka",
    "gn:country_code":"RU",
    "gn:dem":89,
    "gn:feature_class":"P",
    "gn:feature_code":"PPL",
    "gn:name":"Artamonovka",
    "gn:population":0,
    "gn:timezone":"Europe/Moscow",
    "iso:country":"RU",
    "name:rus_x_preferred":[
        "\u0410\u0440\u0442\u0430\u043c\u043e\u043d\u043e\u0432\u043a\u0430"
    ],
    "name:und_x_variant":[
        "\u0410\u0440\u0442\u0430\u043c\u043e\u043d\u043e\u0432\u043a\u0430"
    ],
    "wof:name":"Artamonovka",
    "wof:placetype":"locality"
},
  "geometry": {"coordinates":[52.787,55.5358],"type":"Point"}
}