{
  "type": "Feature",
  "properties": {
    "gn:admin1_code":"47",
    "gn:asciiname":"Troitskoye",
    "gn:country_code":"RU",
    "gn:dem":154,
    "gn:feature_class":"P",
    "gn:feature_code":"PPL",
    "gn:name":"Troitskoye",
    "gn:population":0,
    "gn:timezone":"Europe/Moscow",
    "iso:country":"RU",
    "wof:name":"Troitskoye",
    "wof:placetype":"locality"
},
  "geometry": {"coordinates":[36.64666,55.65476],"type":"Point"}
}