{
  "type": "Feature",
  "properties": {
    "gn:admin1_code":"59",
    "gn:asciiname":"Konyushkova",
    "gn:country_code":"RU",
    "gn:dem":22,
    "gn:feature_class":"P",
    "gn:feature_code":"PPL",
    "gn:name":"Konyushkova",
    "gn:population":0,
    "gn:timezone":"Asia/Vladivostok",
    "iso:country":"RU",
    "name:rus_x_preferred":[
        "\u041a\u043e\u043d\u044e\u0448\u043a\u043e\u0432\u0430"
    ],
    "name:und_x_variant":[
        "Konyushkovo",
        "Konyushkova"
    ],
    "wof:name":"Konyushkova",
    "wof:placetype":"locality"
},
  "geometry": {"coordinates":[132.35678999999999,42.86647],"type":"Point"}
}