{
  "type": "Feature",
  "properties": {
    "gn:admin1_code":"23",
    "gn:asciiname":"Zelenaya Dolina",
    "gn:country_code":"RU",
    "gn:dem":17,
    "gn:feature_class":"P",
    "gn:feature_code":"PPL",
    "gn:name":"Zel\u00ebnaya Dolina",
    "gn:population":0,
    "gn:timezone":"Europe/Kaliningrad",
    "iso:country":"RU",
    "wof:name":"Zelenaya Dolina",
    "wof:placetype":"locality"
},
  "geometry": {"coordinates":[22.01222000000001,54.77333],"type":"Point"}
}