{
  "type": "Feature",
  "properties": {
    "gn:admin1_code":"81",
    "gn:asciiname":"Krotovka",
    "gn:country_code":"RU",
    "gn:dem":119,
    "gn:feature_class":"P",
    "gn:feature_code":"PPL",
    "gn:name":"Krotovka",
    "gn:population":0,
    "gn:timezone":"Europe/Ulyanovsk",
    "iso:country":"RU",
    "name:nor_x_preferred":[
        "Krotovka"
    ],
    "name:rus_x_preferred":[
        "\u041a\u0440\u043e\u0442\u043e\u0432\u043a\u0430"
    ],
    "wof:name":"Krotovka",
    "wof:placetype":"locality"
},
  "geometry": {"coordinates":[48.14491,54.30095],"type":"Point"}
}