{
  "type": "Feature",
  "properties": {
    "gn:admin1_code":"85",
    "gn:asciiname":"Derevyagino",
    "gn:country_code":"RU",
    "gn:dem":151,
    "gn:feature_class":"P",
    "gn:feature_code":"PPL",
    "gn:name":"Derevyagino",
    "gn:population":0,
    "gn:timezone":"Europe/Moscow",
    "iso:country":"RU",
    "name:rus_x_preferred":[
        "\u0414\u0435\u0440\u0435\u0432\u044f\u0433\u0438\u043d\u043e"
    ],
    "wof:name":"Derevyagino",
    "wof:placetype":"locality"
},
  "geometry": {"coordinates":[39.22105,59.09582],"type":"Point"}
}