{
  "type": "Feature",
  "properties": {
    "gn:admin1_code":"13",
    "gn:asciiname":"Uyelgi",
    "gn:country_code":"RU",
    "gn:dem":176,
    "gn:feature_class":"P",
    "gn:feature_code":"PPL",
    "gn:name":"Uyelgi",
    "gn:population":0,
    "gn:timezone":"Asia/Yekaterinburg",
    "iso:country":"RU",
    "name:rus_x_preferred":[
        "\u0423\u0435\u043b\u0433\u0438"
    ],
    "wof:name":"Uyelgi",
    "wof:placetype":"locality"
},
  "geometry": {"coordinates":[61.557,55.8486],"type":"Point"}
}