{
  "type": "Feature",
  "properties": {
    "gn:admin1_code":"10",
    "gn:asciiname":"Chausy",
    "gn:country_code":"RU",
    "gn:dem":131,
    "gn:feature_class":"P",
    "gn:feature_code":"PPL",
    "gn:name":"Chausy",
    "gn:population":0,
    "gn:timezone":"Europe/Moscow",
    "iso:country":"RU",
    "name:rus_x_preferred":[
        "\u0427\u0430\u0443\u0441\u044b"
    ],
    "name:und_x_variant":[
        "\u0427\u0430\u0443\u0441\u044b"
    ],
    "wof:name":"Chausy",
    "wof:placetype":"locality"
},
  "geometry": {"coordinates":[32.07972,52.10972],"type":"Point"}
}