{
  "type": "Feature",
  "properties": {
    "gn:admin1_code":"52",
    "gn:asciiname":"Mukhina",
    "gn:country_code":"RU",
    "gn:dem":25,
    "gn:feature_class":"P",
    "gn:feature_code":"PPL",
    "gn:name":"Mukhina",
    "gn:population":0,
    "gn:timezone":"Europe/Moscow",
    "iso:country":"RU",
    "name:rus_x_preferred":[
        "\u041c\u0443\u0445\u0438\u043d\u0430"
    ],
    "name:und_x_variant":[
        "\u041c\u0443\u0445\u0438\u043d\u0430"
    ],
    "wof:name":"Mukhina",
    "wof:placetype":"locality"
},
  "geometry": {"coordinates":[31.28333,58.03333000000001],"type":"Point"}
}