{
  "type": "Feature",
  "properties": {
    "gn:admin1_code":"73",
    "gn:asciiname":"Staryy Varyash",
    "gn:country_code":"RU",
    "gn:dem":85,
    "gn:feature_class":"P",
    "gn:feature_code":"PPL",
    "gn:name":"Staryy Varyash",
    "gn:population":0,
    "gn:timezone":"Europe/Moscow",
    "iso:country":"RU",
    "name:rus_x_preferred":[
        "\u0421\u0442\u0430\u0440\u044b\u0439 \u0412\u0430\u0440\u044f\u0448"
    ],
    "name:und_x_variant":[
        "\u0421\u0442\u0430\u0440\u044b\u0439 \u0412\u0430\u0440\u044f\u0448"
    ],
    "wof:name":"Staryy Varyash",
    "wof:placetype":"locality"
},
  "geometry": {"coordinates":[53.2229,55.3271],"type":"Point"}
}