{
  "type": "Feature",
  "properties": {
    "gn:admin1_code":"90.0",
    "gn:asciiname":"Dymka",
    "gn:country_code":"RU",
    "gn:dem":152,
    "gn:feature_class":"P",
    "gn:feature_code":"PPL",
    "gn:name":"Dymka",
    "gn:population":0,
    "gn:timezone":"Asia/Yekaterinburg",
    "iso:country":"RU",
    "name:hye_x_preferred":[
        "\u0534\u056b\u0574\u056f\u0561"
    ],
    "name:ron_x_preferred":[
        "Dimca"
    ],
    "name:rus_x_preferred":[
        "\u0414\u044b\u043c\u043a\u0430"
    ],
    "name:ukr_x_preferred":[
        "\u0414\u0438\u043c\u043a\u0430"
    ],
    "name:und_x_variant":[
        "\u0414\u044b\u043c\u043a\u0430"
    ],
    "wof:name":"Dymka",
    "wof:placetype":"locality"
},
  "geometry": {"coordinates":[55.0324,58.4228],"type":"Point"}
}