{
  "type": "Feature",
  "properties": {
    "gn:admin1_code":"61.0",
    "gn:asciiname":"Obraztsovyy",
    "gn:country_code":"RU",
    "gn:dem":79,
    "gn:feature_class":"P",
    "gn:feature_code":"PPL",
    "gn:name":"Obraztsovyy",
    "gn:population":0,
    "gn:timezone":"Europe/Moscow",
    "iso:country":"RU",
    "name:rus_x_preferred":[
        "\u041e\u0431\u0440\u0430\u0437\u0446\u043e\u0432\u044b\u0439"
    ],
    "wof:name":"Obraztsovyy",
    "wof:placetype":"locality"
},
  "geometry": {"coordinates":[40.96365,46.48709],"type":"Point"}
}