{
  "type": "Feature",
  "properties": {
    "gn:admin1_code":"90",
    "gn:asciiname":"Verkhniy Kultym",
    "gn:country_code":"RU",
    "gn:dem":166,
    "gn:feature_class":"P",
    "gn:feature_code":"PPL",
    "gn:name":"Verkhniy Kultym",
    "gn:population":0,
    "gn:timezone":"Asia/Yekaterinburg",
    "iso:country":"RU",
    "name:eng_x_preferred":[
        "Verkhniy Kultym"
    ],
    "name:nor_x_preferred":[
        "Verkh-Kultym"
    ],
    "name:rus_x_preferred":[
        "\u0412\u0435\u0440\u0445-\u041a\u0443\u043b\u0442\u044b\u043c"
    ],
    "name:rus_x_variant":[
        "\u0412\u0435\u0440\u0445\u043d\u0438\u0439 \u041a\u0443\u043b\u0442\u044b\u043c"
    ],
    "wof:name":"Verkhniy Kultym",
    "wof:placetype":"locality"
},
  "geometry": {"coordinates":[57.4253,57.7759],"type":"Point"}
}