{
  "type": "Feature",
  "properties": {
    "gn:admin1_code":"37",
    "gn:asciiname":"Tabuchevo",
    "gn:country_code":"RU",
    "gn:dem":185,
    "gn:feature_class":"P",
    "gn:feature_code":"PPL",
    "gn:name":"Tabuchevo",
    "gn:population":0,
    "gn:timezone":"Europe/Moscow",
    "iso:country":"RU",
    "name:rus_x_preferred":[
        "\u0422a\u0431\u0443\u0447\u0435\u0432\u043e"
    ],
    "name:und_x_variant":[
        "Tobachevo"
    ],
    "wof:name":"Tabuchevo",
    "wof:placetype":"locality"
},
  "geometry": {"coordinates":[42.86799,58.32601],"type":"Point"}
}