{
  "type": "Feature",
  "properties": {
    "gn:admin1_code":"89.0",
    "gn:asciiname":"Nayfel'd",
    "gn:country_code":"RU",
    "gn:dem":63,
    "gn:feature_class":"P",
    "gn:feature_code":"PPL",
    "gn:name":"Nayfel\u2019d",
    "gn:population":0,
    "gn:timezone":"Asia/Vladivostok",
    "iso:country":"RU",
    "name:rus_x_preferred":[
        "\u041d\u0430\u0439\u0444\u0435\u043b\u044c\u0434"
    ],
    "name:und_x_variant":[
        "Nayfel\u2019d"
    ],
    "wof:name":"Nayfel'd",
    "wof:placetype":"locality"
},
  "geometry": {"coordinates":[133.09888999999998,48.49237],"type":"Point"}
}