{
  "type": "Feature",
  "properties": {
    "gn:country":"RU",
    "gn:fcode":"PPL",
    "gn:pop":4031,
    "iso:country":"RU",
    "name:eng_x_preferred":[
        "Inderka"
    ],
    "name:nor_x_preferred":[
        "Inderka"
    ],
    "name:rus_x_preferred":[
        "\u0418\u043d\u0434\u0435\u0440\u043a\u0430"
    ],
    "name:unk_x_variant":[
        "\u0418\u043d\u0434\u0435\u0440\u043a\u0430"
    ],
    "qs:name":"Inderka",
    "qs:photos_9r":0,
    "qs:photos_sr":0,
    "qs:pop_sr":"4",
    "wof:name":"Inderka",
    "wof:placetype":"locality",
    "wof:population":4031
},
  "geometry": {"coordinates":[46.25824,53.24846],"type":"Point"}
}