{
  "type": "Feature",
  "properties": {
    "gn:admin1_code":"88",
    "gn:asciiname":"Subayevo",
    "gn:country_code":"RU",
    "gn:dem":188,
    "gn:feature_class":"P",
    "gn:feature_code":"PPL",
    "gn:name":"Subayevo",
    "gn:population":0,
    "gn:timezone":"Europe/Moscow",
    "iso:country":"RU",
    "name:rus_x_preferred":[
        "\u0421\u0443\u0431\u0430\u0435\u0432\u043e"
    ],
    "name:und_x_variant":[
        "Sumbayevo",
        "Subayevo"
    ],
    "wof:name":"Subayevo",
    "wof:placetype":"locality"
},
  "geometry": {"coordinates":[40.10463,58.09276],"type":"Point"}
}