{
  "type": "Feature",
  "properties": {
    "gn:admin1_code":"85",
    "gn:asciiname":"Maloye Zales'ye",
    "gn:country_code":"RU",
    "gn:dem":170,
    "gn:feature_class":"P",
    "gn:feature_code":"PPL",
    "gn:name":"Maloye Zales\u2019ye",
    "gn:population":0,
    "gn:timezone":"Europe/Moscow",
    "iso:country":"RU",
    "name:rus_x_preferred":[
        "\u041c\u0430\u043b\u043e\u0435 \u0417\u0430\u043b\u0435\u0441\u044c\u0435"
    ],
    "name:und_x_variant":[
        "Maloye Zales\u2019ye"
    ],
    "wof:name":"Maloye Zales'ye",
    "wof:placetype":"locality"
},
  "geometry": {"coordinates":[41.29834,59.64021999999999],"type":"Point"}
}