{
  "type": "Feature",
  "properties": {
    "gn:admin1_code":"85",
    "gn:asciiname":"Polukhino",
    "gn:country_code":"RU",
    "gn:dem":151,
    "gn:feature_class":"P",
    "gn:feature_code":"PPL",
    "gn:name":"Polukhino",
    "gn:population":0,
    "gn:timezone":"Europe/Moscow",
    "iso:country":"RU",
    "name:rus_x_preferred":[
        "\u041f\u043e\u043b\u0443\u0445\u0438\u043d\u043e"
    ],
    "wof:name":"Polukhino",
    "wof:placetype":"locality"
},
  "geometry": {"coordinates":[40.98864,58.72409],"type":"Point"}
}