{
  "type": "Feature",
  "properties": {
    "gn:admin1_code":"29",
    "gn:asciiname":"Benzherep Pervyy",
    "gn:country_code":"RU",
    "gn:dem":272,
    "gn:feature_class":"P",
    "gn:feature_code":"PPL",
    "gn:name":"Benzherep Pervyy",
    "gn:population":0,
    "gn:timezone":"Asia/Novokuznetsk",
    "iso:country":"RU",
    "name:nor_x_preferred":[
        "Benzjerep Pervyj"
    ],
    "name:rus_x_preferred":[
        "\u0411\u0435\u043d\u0436\u0435\u0440\u0435\u043f \u041f\u0435\u0440\u0432\u044b\u0439"
    ],
    "wof:name":"Benzherep Pervyy",
    "wof:placetype":"locality"
},
  "geometry": {"coordinates":[87.0001,53.3243],"type":"Point"}
}