{
  "type": "Feature",
  "properties": {
    "gn:admin1_code":"53",
    "gn:asciiname":"Kazanak",
    "gn:country_code":"RU",
    "gn:dem":122,
    "gn:feature_class":"P",
    "gn:feature_code":"PPL",
    "gn:name":"Kazanak",
    "gn:population":0,
    "gn:timezone":"Asia/Novosibirsk",
    "iso:country":"RU",
    "name:eng_x_preferred":[
        "Kazanak"
    ],
    "name:nor_x_preferred":[
        "Kazanak"
    ],
    "name:rus_x_preferred":[
        "\u041a\u0430\u0437\u0430\u043d\u0430\u043a"
    ],
    "name:und_x_variant":[
        "Kayzanak",
        "\u041a\u0430\u0437\u0430\u043d\u0430\u043a",
        "Kazanak"
    ],
    "wof:name":"Kazanak",
    "wof:placetype":"locality"
},
  "geometry": {"coordinates":[79.15765999999998,54.18545],"type":"Point"}
}