{
  "type": "Feature",
  "properties": {
    "gn:admin1_code":"20",
    "gn:asciiname":"Bokholdyy",
    "gn:cc2":"RU",
    "gn:country_code":"RU",
    "gn:dem":566,
    "gn:feature_class":"P",
    "gn:feature_code":"PPL",
    "gn:name":"Bokholdyy",
    "gn:population":0,
    "gn:timezone":"Asia/Irkutsk",
    "iso:country":"RU",
    "name:rus_x_preferred":[
        "\u0411\u043e\u0445\u043e\u043b\u0434\u044b\u0439"
    ],
    "name:und_x_variant":[
        "Bokholdy",
        "Bokholdyy",
        "\u0411\u043e\u0445\u043e\u043b\u0434\u044b\u0439"
    ],
    "wof:name":"Bokholdyy",
    "wof:placetype":"locality"
},
  "geometry": {"coordinates":[99.86667,54.26667],"type":"Point"}
}