{
  "type": "Feature",
  "properties": {
    "gn:admin1_code":"88",
    "gn:asciiname":"Tsarevo",
    "gn:country_code":"RU",
    "gn:dem":130,
    "gn:feature_class":"P",
    "gn:feature_code":"PPL",
    "gn:name":"Tsar\u00ebvo",
    "gn:population":0,
    "gn:timezone":"Europe/Moscow",
    "iso:country":"RU",
    "name:rus_x_preferred":[
        "\u0426\u0430\u0440\u0451\u0432\u043e"
    ],
    "name:und_x_variant":[
        "Tsar\u00ebvo",
        "\u0426\u0430\u0440\u0451\u0432\u043e"
    ],
    "wof:name":"Tsarevo",
    "wof:placetype":"locality"
},
  "geometry": {"coordinates":[38.07675,58.10621],"type":"Point"}
}