{
  "type": "Feature",
  "properties": {
    "iso:country":"RU",
    "name:fin_x_preferred":[
        "T\u00e4r\u00f6l\u00e4"
    ],
    "name:fra_x_preferred":[
        "Tiarlevo"
    ],
    "name:kor_x_preferred":[
        "\ud0f8\ub97c\ub808\ubcf4 \uc790\uce58\uad6c"
    ],
    "name:rus_x_preferred":[
        "\u0422\u044f\u0440\u043b\u0435\u0432\u043e"
    ],
    "wof:name":"Tyarlevo",
    "wof:placetype":"neighbourhood"
},
  "geometry": {"coordinates":[30.45009790661341,59.70431123026579],"type":"Point"}
}