{
  "type": "Feature",
  "properties": {
    "gn:admin1_code":"47.0",
    "gn:asciiname":"Bel'kovo",
    "gn:country_code":"RU",
    "gn:dem":117,
    "gn:feature_class":"P",
    "gn:feature_code":"PPL",
    "gn:name":"Bel\u2019kovo",
    "gn:population":0,
    "gn:timezone":"Europe/Moscow",
    "iso:country":"RU",
    "name:nor_x_preferred":[
        "Belkovo"
    ],
    "name:rus_x_preferred":[
        "\u0411\u0435\u043b\u044c\u043a\u043e\u0432\u043e"
    ],
    "name:und_x_variant":[
        "Bel\u2019kovo"
    ],
    "wof:name":"Bel'kovo",
    "wof:placetype":"locality"
},
  "geometry": {"coordinates":[38.49456,55.38152],"type":"Point"}
}