{
  "type": "Feature",
  "properties": {
    "gn:admin1_code":"69",
    "gn:asciiname":"Khar'kovo",
    "gn:country_code":"RU",
    "gn:dem":200,
    "gn:feature_class":"P",
    "gn:feature_code":"PPL",
    "gn:name":"Khar\u2019kovo",
    "gn:population":0,
    "gn:timezone":"Europe/Moscow",
    "iso:country":"RU",
    "name:rus_x_preferred":[
        "\u0425\u0430\u0440\u044c\u043a\u043e\u0432\u043e"
    ],
    "name:und_x_variant":[
        "Khar\u2019kovo",
        "\u0425\u0430\u0440\u044c\u043a\u043e\u0432\u043e"
    ],
    "wof:name":"Khar'kovo",
    "wof:placetype":"locality"
},
  "geometry": {"coordinates":[33.45417,55.16806],"type":"Point"}
}