{
  "type": "Feature",
  "properties": {
    "gn:admin1_code":"4",
    "gn:asciiname":"Romanovo",
    "gn:cc2":"RU",
    "gn:country_code":"RU",
    "gn:dem":200,
    "gn:feature_class":"P",
    "gn:feature_code":"PPL",
    "gn:name":"Romanovo",
    "gn:population":0,
    "gn:timezone":"Asia/Barnaul",
    "iso:country":"RU",
    "name:eng_x_preferred":[
        "Romanovo"
    ],
    "name:nor_x_preferred":[
        "Romanovo"
    ],
    "name:rus_x_preferred":[
        "\u0420\u043e\u043c\u0430\u043d\u043e\u0432\u043e"
    ],
    "name:und_x_variant":[
        "Romanova"
    ],
    "wof:name":"Romanovo",
    "wof:placetype":"locality"
},
  "geometry": {"coordinates":[83.36667,52.41667],"type":"Point"}
}