{
  "type": "Feature",
  "properties": {
    "gn:admin1_code":"10",
    "gn:asciiname":"Kholopets",
    "gn:country_code":"RU",
    "gn:dem":139,
    "gn:feature_class":"P",
    "gn:feature_code":"PPL",
    "gn:name":"Kholopets",
    "gn:population":0,
    "gn:timezone":"Europe/Moscow",
    "iso:country":"RU",
    "name:rus_x_preferred":[
        "\u0425\u043e\u043b\u043e\u043f\u0435\u0446"
    ],
    "name:und_x_variant":[
        "\u0425\u043e\u043b\u043e\u043f\u0435\u0446"
    ],
    "wof:name":"Kholopets",
    "wof:placetype":"locality"
},
  "geometry": {"coordinates":[33.23496,52.59149],"type":"Point"}
}