{
  "type": "Feature",
  "properties": {
    "gn:admin1_code":"25",
    "gn:asciiname":"Shupilovka",
    "gn:country_code":"RU",
    "gn:dem":192,
    "gn:feature_class":"P",
    "gn:feature_code":"PPL",
    "gn:name":"Shupilovka",
    "gn:population":0,
    "gn:timezone":"Europe/Moscow",
    "iso:country":"RU",
    "name:rus_x_preferred":[
        "\u0428\u0443\u043f\u0438\u043b\u043e\u0432\u043a\u0430"
    ],
    "name:und_x_variant":[
        "Shipilovka",
        "Shupilovka",
        "\u0428\u0443\u043f\u0438\u043b\u043e\u0432\u043a\u0430"
    ],
    "wof:name":"Shupilovka",
    "wof:placetype":"locality"
},
  "geometry": {"coordinates":[34.48783,53.95916999999999],"type":"Point"}
}