{
  "type": "Feature",
  "properties": {
    "gn:admin1_code":"28",
    "gn:asciiname":"Pushnoy",
    "gn:country_code":"RU",
    "gn:dem":23,
    "gn:feature_class":"P",
    "gn:feature_code":"PPL",
    "gn:name":"Pushnoy",
    "gn:population":0,
    "gn:timezone":"Europe/Moscow",
    "iso:country":"RU",
    "name:rus_x_preferred":[
        "\u041f\u0443\u0448\u043d\u043e\u0439"
    ],
    "wof:name":"Pushnoy",
    "wof:placetype":"locality"
},
  "geometry": {"coordinates":[34.76667,62.83333],"type":"Point"}
}