{
  "type": "Feature",
  "properties": {
    "gn:admin1_code":"67.0",
    "gn:asciiname":"Chapayevo",
    "gn:cc2":"RU",
    "gn:country_code":"RU",
    "gn:dem":76,
    "gn:feature_class":"P",
    "gn:feature_code":"PPL",
    "gn:name":"Chapayevo",
    "gn:population":0,
    "gn:timezone":"Europe/Saratov",
    "iso:country":"RU",
    "name:rus_x_preferred":[
        "\u0427\u0430\u043f\u0430\u0435\u0432\u043e"
    ],
    "name:und_x_variant":[
        "Lindenau",
        "Chapayevo",
        "\u0427\u0430\u043f\u0430\u0435\u0432\u043e"
    ],
    "wof:name":"Chapayevo",
    "wof:placetype":"locality"
},
  "geometry": {"coordinates":[46.35,51.03333],"type":"Point"}
}