{
  "type": "Feature",
  "properties": {
    "gn:admin1_code":"69",
    "gn:asciiname":"Pazhoga",
    "gn:country_code":"RU",
    "gn:dem":171,
    "gn:feature_class":"P",
    "gn:feature_code":"PPL",
    "gn:name":"Pazhoga",
    "gn:population":0,
    "gn:timezone":"Europe/Moscow",
    "iso:country":"RU",
    "name:rus_x_preferred":[
        "\u041f\u0430\u0436\u043e\u0433\u0430"
    ],
    "wof:name":"Pazhoga",
    "wof:placetype":"locality"
},
  "geometry": {"coordinates":[32.38355,53.90623000000001],"type":"Point"}
}