{
  "type": "Feature",
  "properties": {
    "gn:admin1_code":"33.0",
    "gn:asciiname":"Bessolki",
    "gn:country_code":"RU",
    "gn:dem":164,
    "gn:feature_class":"P",
    "gn:feature_code":"PPL",
    "gn:name":"Bessolki",
    "gn:population":0,
    "gn:timezone":"Europe/Kirov",
    "iso:country":"RU",
    "name:nor_x_preferred":[
        "Bessolki"
    ],
    "name:rus_x_preferred":[
        "\u0411\u0435\u0441\u0441\u043e\u043b\u043a\u0438"
    ],
    "wof:name":"Bessolki",
    "wof:placetype":"locality"
},
  "geometry": {"coordinates":[49.82967,58.45033000000001],"type":"Point"}
}