{
  "type": "Feature",
  "properties": {
    "gn:admin1_code":"42",
    "gn:asciiname":"Ul'yanino",
    "gn:country_code":"RU",
    "gn:dem":42,
    "gn:feature_class":"P",
    "gn:feature_code":"PPL",
    "gn:name":"Ul\u2019yanino",
    "gn:population":0,
    "gn:timezone":"Europe/Moscow",
    "iso:country":"RU",
    "name:und_x_variant":[
        "Uljanino",
        "Ul\u2019yanino"
    ],
    "wof:name":"Ul'yanino",
    "wof:placetype":"locality"
},
  "geometry": {"coordinates":[33.26197,60.1119],"type":"Point"}
}