{
  "type": "Feature",
  "properties": {
    "gn:admin1_code":"33",
    "gn:asciiname":"Zamezhnitsa",
    "gn:country_code":"RU",
    "gn:dem":164,
    "gn:feature_class":"P",
    "gn:feature_code":"PPL",
    "gn:name":"Zamezhnitsa",
    "gn:population":0,
    "gn:timezone":"Europe/Kirov",
    "iso:country":"RU",
    "name:eng_x_preferred":[
        "Zamezhnitsa"
    ],
    "name:nor_x_preferred":[
        "Zamezjnitsa"
    ],
    "name:rus_x_preferred":[
        "\u0417\u0430\u043c\u0435\u0436\u043d\u0438\u0446\u0430"
    ],
    "wof:name":"Zamezhnitsa",
    "wof:placetype":"locality"
},
  "geometry": {"coordinates":[49.1507,58.96531],"type":"Point"}
}