{
  "type": "Feature",
  "properties": {
    "gn:admin1_code":"8.0",
    "gn:asciiname":"Aksakovo",
    "gn:country_code":"RU",
    "gn:dem":157,
    "gn:feature_class":"P",
    "gn:feature_code":"PPL",
    "gn:name":"Aksakovo",
    "gn:population":0,
    "gn:timezone":"Asia/Yekaterinburg",
    "iso:country":"RU",
    "name:nor_x_preferred":[
        "Aksakovo"
    ],
    "name:rus_x_preferred":[
        "\u0410\u043a\u0441\u0430\u043a\u043e\u0432\u043e"
    ],
    "wof:name":"Aksakovo",
    "wof:placetype":"locality"
},
  "geometry": {"coordinates":[56.20838000000001,54.33221],"type":"Point"}
}