{
  "type": "Feature",
  "properties": {
    "gn:admin1_code":"30",
    "gn:asciiname":"Srednyaya Ekan'",
    "gn:country_code":"RU",
    "gn:dem":158,
    "gn:feature_class":"P",
    "gn:feature_code":"PPL",
    "gn:name":"Srednyaya Ekan\u2019",
    "gn:population":0,
    "gn:timezone":"Asia/Vladivostok",
    "iso:country":"RU",
    "name:rus_x_preferred":[
        "\u0421\u0440\u0435\u0434\u043d\u044f\u044f \u042d\u043a\u0430\u043d\u044c"
    ],
    "name:und_x_variant":[
        "Srednyaya Ekan\u2019"
    ],
    "wof:name":"Srednyaya Ekan'",
    "wof:placetype":"locality"
},
  "geometry": {"coordinates":[137.09999999999999,50.45],"type":"Point"}
}