{
  "type": "Feature",
  "properties": {
    "gn:admin1_code":"90.0",
    "gn:asciiname":"Pesterevo",
    "gn:country_code":"RU",
    "gn:dem":136,
    "gn:feature_class":"P",
    "gn:feature_code":"PPL",
    "gn:name":"Pesterevo",
    "gn:population":0,
    "gn:timezone":"Asia/Yekaterinburg",
    "iso:country":"RU",
    "name:rus_x_preferred":[
        "\u041f\u0435\u0441\u0442\u0435\u0440\u0435\u0432\u043e"
    ],
    "wof:name":"Pesterevo",
    "wof:placetype":"locality"
},
  "geometry": {"coordinates":[54.77526999999999,57.86051],"type":"Point"}
}