{
  "type": "Feature",
  "properties": {
    "gn:admin1_code":"90.0",
    "gn:asciiname":"Ust'-Pizya",
    "gn:country_code":"RU",
    "gn:dem":94,
    "gn:feature_class":"P",
    "gn:feature_code":"PPL",
    "gn:name":"Ust\u2019-Pizya",
    "gn:population":0,
    "gn:timezone":"Asia/Yekaterinburg",
    "iso:country":"RU",
    "name:eng_x_preferred":[
        "Ust'-Pizya"
    ],
    "name:nor_x_preferred":[
        "Ust-Pizia"
    ],
    "name:rus_x_preferred":[
        "\u0423\u0441\u0442\u044c-\u041f\u0438\u0437\u044f"
    ],
    "name:und_x_variant":[
        "Ust\u2019-Pizya"
    ],
    "wof:name":"Ust'-Pizya",
    "wof:placetype":"locality"
},
  "geometry": {"coordinates":[55.5892,57.5101],"type":"Point"}
}