{
  "type": "Feature",
  "properties": {
    "gn:admin1_code":"6",
    "gn:asciiname":"Plesovskaya",
    "gn:country_code":"RU",
    "gn:dem":123,
    "gn:feature_class":"P",
    "gn:feature_code":"PPL",
    "gn:name":"Plesovskaya",
    "gn:population":0,
    "gn:timezone":"Europe/Moscow",
    "iso:country":"RU",
    "name:rus_x_preferred":[
        "\u041f\u043b\u0435\u0441\u043e\u0432\u0441\u043a\u0430\u044f"
    ],
    "name:und_x_variant":[
        "Ploskaya",
        "Plesovskaya",
        "\u041f\u043b\u0435\u0441\u043e\u0432\u0441\u043a\u0430\u044f"
    ],
    "wof:name":"Plesovskaya",
    "wof:placetype":"locality"
},
  "geometry": {"coordinates":[41.2485,61.0278],"type":"Point"}
}