{
  "type": "Feature",
  "properties": {
    "gn:admin1_code":"85",
    "gn:asciiname":"Yarygino",
    "gn:country_code":"RU",
    "gn:dem":115,
    "gn:feature_class":"P",
    "gn:feature_code":"PPL",
    "gn:name":"Yarygino",
    "gn:population":0,
    "gn:timezone":"Europe/Moscow",
    "iso:country":"RU",
    "name:rus_x_preferred":[
        "\u042f\u0440\u0443\u0433\u0438\u043d\u043e"
    ],
    "name:und_x_variant":[
        "\u042f\u0440\u0443\u0433\u0438\u043d\u043e"
    ],
    "wof:name":"Yarygino",
    "wof:placetype":"locality"
},
  "geometry": {"coordinates":[39.8732,59.276],"type":"Point"}
}