{
  "type": "Feature",
  "properties": {
    "gn:admin1_code":"28",
    "gn:asciiname":"Lisman",
    "gn:country_code":"RU",
    "gn:dem":118,
    "gn:feature_class":"P",
    "gn:feature_code":"PPL",
    "gn:name":"Lisman",
    "gn:population":0,
    "gn:timezone":"Europe/Moscow",
    "iso:country":"RU",
    "name:fin_x_preferred":[
        "Lismanselk\u00e4"
    ],
    "name:rus_x_preferred":[
        "\u041b\u0438\u0441\u043c\u0430\u043d"
    ],
    "wof:name":"Lisman",
    "wof:placetype":"locality"
},
  "geometry": {"coordinates":[32.65635,61.88545],"type":"Point"}
}