{
  "type": "Feature",
  "properties": {
    "gn:admin1_code":"69",
    "gn:asciiname":"Gromovo",
    "gn:country_code":"RU",
    "gn:dem":228,
    "gn:feature_class":"P",
    "gn:feature_code":"PPL",
    "gn:name":"Gromovo",
    "gn:population":0,
    "gn:timezone":"Europe/Moscow",
    "iso:country":"RU",
    "name:rus_x_preferred":[
        "\u0413\u0440\u043e\u043c\u043e\u0432\u043e"
    ],
    "name:und_x_variant":[
        "\u0413\u0440\u043e\u043c\u043e\u0432\u043e"
    ],
    "wof:name":"Gromovo",
    "wof:placetype":"locality"
},
  "geometry": {"coordinates":[33.32564,54.79639],"type":"Point"}
}