{
  "type": "Feature",
  "properties": {
    "gn:country":"RU",
    "gn:fcode":"PPL",
    "gn:pop":0,
    "iso:country":"RU",
    "name:rus_x_preferred":[
        "\u0413\u043e\u043b\u0443\u0431\u0430\u044f \u0411\u0443\u0445\u0442\u0430"
    ],
    "name:unk_x_variant":[
        "Solntsedar"
    ],
    "qs:name":"Golubaya Bukhta",
    "qs:name_adm0":"Russia",
    "qs:name_adm1":"Krasnodar Krai",
    "qs:photos":188,
    "qs:photos_1k":38,
    "qs:photos_9k":1,
    "qs:photos_9r":4,
    "qs:photos_all":188,
    "qs:photos_sr":4,
    "qs:placetype":"Town",
    "qs:pop_sr":"0",
    "wd:wordcount":132,
    "wof:name":"Golubaya Bukhta",
    "wof:placetype":"locality",
    "wof:population":0
},
  "geometry": {"coordinates":[37.98917,44.58111],"type":"Point"}
}