{
  "type": "Feature",
  "properties": {
    "gn:admin1_code":"23",
    "gn:asciiname":"Gromovo",
    "gn:country_code":"RU",
    "gn:dem":1,
    "gn:feature_class":"P",
    "gn:feature_code":"PPL",
    "gn:name":"Gromovo",
    "gn:population":0,
    "gn:timezone":"Europe/Kaliningrad",
    "iso:country":"RU",
    "name:eng_x_preferred":[
        "Gromovo"
    ],
    "name:nor_x_preferred":[
        "Gromovo"
    ],
    "name:rus_x_preferred":[
        "\u0413\u0440\u043e\u043c\u043e\u0432\u043e"
    ],
    "name:und_x_variant":[
        "Lauknen",
        "Hohenbruch",
        "\u0413\u0440\u043e\u043c\u043e\u0432\u043e",
        "Gromovo"
    ],
    "wof:name":"Gromovo",
    "wof:placetype":"locality"
},
  "geometry": {"coordinates":[21.41692,54.96897],"type":"Point"}
}