{
  "type": "Feature",
  "properties": {
    "gn:admin1_code":"16",
    "gn:asciiname":"Khornzor",
    "gn:country_code":"RU",
    "gn:dem":148,
    "gn:feature_class":"P",
    "gn:feature_code":"PPL",
    "gn:name":"Khornzor",
    "gn:population":0,
    "gn:timezone":"Europe/Moscow",
    "iso:country":"RU",
    "name:rus_x_preferred":[
        "\u0425\u043e\u0440\u043d\u0437\u043e\u0440"
    ],
    "name:und_x_variant":[
        "Khori-Zory",
        "Khornzor",
        "\u0425\u043e\u0440\u043d\u0437\u043e\u0440"
    ],
    "wof:name":"Khornzor",
    "wof:placetype":"locality"
},
  "geometry": {"coordinates":[46.63611,55.7712],"type":"Point"}
}