{
  "type": "Feature",
  "properties": {
    "gn:admin1_code":"90",
    "gn:asciiname":"Yezhovo",
    "gn:country_code":"RU",
    "gn:dem":194,
    "gn:feature_class":"P",
    "gn:feature_code":"PPL",
    "gn:name":"Yezhovo",
    "gn:population":0,
    "gn:timezone":"Asia/Yekaterinburg",
    "iso:country":"RU",
    "name:rus_x_preferred":[
        "\u0415\u0436\u043e\u0432\u043e"
    ],
    "wof:name":"Yezhovo",
    "wof:placetype":"locality"
},
  "geometry": {"coordinates":[57.0377,57.6323],"type":"Point"}
}