{
  "type": "Feature",
  "properties": {
    "gn:admin1_code":"85",
    "gn:asciiname":"Mezhurki",
    "gn:country_code":"RU",
    "gn:dem":133,
    "gn:feature_class":"P",
    "gn:feature_code":"PPL",
    "gn:name":"Mezhurki",
    "gn:population":0,
    "gn:timezone":"Europe/Moscow",
    "iso:country":"RU",
    "name:eng_x_preferred":[
        "Mezhurki"
    ],
    "name:nor_x_preferred":[
        "Mezjurki"
    ],
    "name:rus_x_preferred":[
        "\u041c\u0435\u0436\u0443\u0440\u043a\u0438"
    ],
    "name:und_x_variant":[
        "Lesouchastok Mezhurki",
        "Ploskovo"
    ],
    "wof:name":"Mezhurki",
    "wof:placetype":"locality"
},
  "geometry": {"coordinates":[39.3916,60.2505],"type":"Point"}
}