{
  "type": "Feature",
  "properties": {
    "gn:admin1_code":"57",
    "gn:asciiname":"Rostovka",
    "gn:country_code":"RU",
    "gn:dem":159,
    "gn:feature_class":"P",
    "gn:feature_code":"PPL",
    "gn:name":"Rostovka",
    "gn:population":0,
    "gn:timezone":"Europe/Moscow",
    "iso:country":"RU",
    "name:rus_x_preferred":[
        "\u0420\u043e\u0441\u0442\u043e\u0432\u043a\u0430"
    ],
    "name:und_x_variant":[
        "\u0420\u043e\u0441\u0442\u043e\u0432\u043a\u0430"
    ],
    "wof:name":"Rostovka",
    "wof:placetype":"locality"
},
  "geometry": {"coordinates":[43.57139,52.87389],"type":"Point"}
}