{
  "type": "Feature",
  "properties": {
    "gn:admin1_code":"8.0",
    "gn:asciiname":"Bulat",
    "gn:country_code":"RU",
    "gn:dem":162,
    "gn:feature_class":"P",
    "gn:feature_code":"PPL",
    "gn:name":"Bulat",
    "gn:population":0,
    "gn:timezone":"Asia/Yekaterinburg",
    "iso:country":"RU",
    "name:rus_x_preferred":[
        "\u0411\u0443\u043b\u0430\u0442"
    ],
    "name:und_x_variant":[
        "Bulatovo",
        "Bulat",
        "\u0411\u0443\u043b\u0430\u0442"
    ],
    "wof:name":"Bulat",
    "wof:placetype":"locality"
},
  "geometry": {"coordinates":[54.11666999999999,54.65],"type":"Point"}
}