{
  "type": "Feature",
  "properties": {
    "gn:admin1_code":"53",
    "gn:asciiname":"Ulybino",
    "gn:country_code":"RU",
    "gn:dem":160,
    "gn:feature_class":"P",
    "gn:feature_code":"PPL",
    "gn:name":"Ulybino",
    "gn:population":0,
    "gn:timezone":"Asia/Novosibirsk",
    "iso:country":"RU",
    "name:eng_x_preferred":[
        "Ulybino"
    ],
    "name:nor_x_preferred":[
        "Ulybino"
    ],
    "name:rus_x_preferred":[
        "\u0423\u043b\u044b\u0431\u0438\u043d\u043e"
    ],
    "name:und_x_variant":[
        "Ulybina",
        "Ulybino"
    ],
    "wof:name":"Ulybino",
    "wof:placetype":"locality"
},
  "geometry": {"coordinates":[82.9222,54.5834],"type":"Point"}
}