{
  "type": "Feature",
  "properties": {
    "gn:admin1_code":"47",
    "gn:asciiname":"Prudno",
    "gn:country_code":"RU",
    "gn:dem":138,
    "gn:feature_class":"P",
    "gn:feature_code":"PPL",
    "gn:name":"Prudno",
    "gn:population":0,
    "gn:timezone":"Europe/Moscow",
    "iso:country":"RU",
    "name:rus_x_preferred":[
        "\u041f\u0440\u0443\u0434\u043d\u043e"
    ],
    "wof:name":"Prudno",
    "wof:placetype":"locality"
},
  "geometry": {"coordinates":[37.81278,55.00717],"type":"Point"}
}