{
  "type": "Feature",
  "properties": {
    "gn:admin1_code":"13",
    "gn:asciiname":"Khudayberdinskiy",
    "gn:country_code":"RU",
    "gn:dem":248,
    "gn:feature_class":"P",
    "gn:feature_code":"PPL",
    "gn:name":"Khudayberdinskiy",
    "gn:population":0,
    "gn:timezone":"Asia/Yekaterinburg",
    "iso:country":"RU",
    "name:eng_x_preferred":[
        "Khudayberdinskiy"
    ],
    "name:nor_x_preferred":[
        "Khudajberdinskij"
    ],
    "name:rus_x_preferred":[
        "\u0425\u0443\u0434\u0430\u0439\u0431\u0435\u0440\u0434\u0438\u043d\u0441\u043a\u0438\u0439"
    ],
    "name:und_x_variant":[
        "Simonovykh",
        "Khudayberdinsk",
        "\u0425\u0443\u0434\u0430\u0439\u0431\u0435\u0440\u0434\u0438\u043d\u0441\u043a\u0438\u0439",
        "Khudayberdinskiy"
    ],
    "wof:name":"Khudayberdinskiy",
    "wof:placetype":"locality"
},
  "geometry": {"coordinates":[60.9178,55.6103],"type":"Point"}
}