{
  "type": "Feature",
  "properties": {
    "gn:admin1_code":"61",
    "gn:asciiname":"Gusev",
    "gn:country_code":"RU",
    "gn:dem":42,
    "gn:feature_class":"P",
    "gn:feature_code":"PPL",
    "gn:name":"Gusev",
    "gn:population":0,
    "gn:timezone":"Europe/Moscow",
    "iso:country":"RU",
    "name:bel_x_preferred":[
        "\u0413\u0443\u0441\u0435\u045e"
    ],
    "name:bos_x_preferred":[
        "Gusev"
    ],
    "name:ceb_x_preferred":[
        "Gusev"
    ],
    "name:deu_x_preferred":[
        "Gusev"
    ],
    "name:fra_x_preferred":[
        "Goussev"
    ],
    "name:hrv_x_preferred":[
        "Gusev"
    ],
    "name:hye_x_preferred":[
        "\u0533\u0578\u0582\u057d\u0587"
    ],
    "name:ita_x_preferred":[
        "Gusev"
    ],
    "name:lit_x_preferred":[
        "Gusevas"
    ],
    "name:nds_x_preferred":[
        "Gusev"
    ],
    "name:nld_x_preferred":[
        "Gusev"
    ],
    "name:pol_x_preferred":[
        "Gusiew"
    ],
    "name:por_x_preferred":[
        "Gusev"
    ],
    "name:rus_x_preferred":[
        "\u0413\u0443\u0441\u0435\u0432"
    ],
    "name:slv_x_preferred":[
        "Gusev"
    ],
    "name:ukr_x_preferred":[
        "\u0413\u0443\u0441\u0454\u0432"
    ],
    "name:und_x_variant":[
        "Verkhniy Gusev",
        "Gusev",
        "\u0413\u0443\u0441\u0435\u0432"
    ],
    "wof:name":"Gusev",
    "wof:placetype":"locality"
},
  "geometry": {"coordinates":[40.5013,48.4451],"type":"Point"}
}