{
  "type": "Feature",
  "properties": {
    "gn:admin1_code":"21.0",
    "gn:asciiname":"Degtyarka",
    "gn:country_code":"RU",
    "gn:dem":152,
    "gn:feature_class":"P",
    "gn:feature_code":"PPL",
    "gn:name":"Degtyarka",
    "gn:population":0,
    "gn:timezone":"Europe/Moscow",
    "iso:country":"RU",
    "name:nor_x_preferred":[
        "Degtjarka"
    ],
    "name:rus_x_preferred":[
        "\u0414\u0435\u0433\u0442\u044f\u0440\u043a\u0430"
    ],
    "wof:name":"Degtyarka",
    "wof:placetype":"locality"
},
  "geometry": {"coordinates":[40.37043,57.0825],"type":"Point"}
}