{
  "type": "Feature",
  "properties": {
    "gn:admin1_code":"84",
    "gn:asciiname":"Kamenskiy",
    "gn:country_code":"RU",
    "gn:dem":172,
    "gn:feature_class":"P",
    "gn:feature_code":"PPL",
    "gn:name":"Kamenskiy",
    "gn:population":0,
    "gn:timezone":"Europe/Volgograd",
    "iso:country":"RU",
    "name:eng_x_preferred":[
        "Kamenka"
    ],
    "name:nor_x_preferred":[
        "Kamenskij"
    ],
    "name:rus_x_preferred":[
        "\u041a\u0430\u043c\u0435\u043d\u0441\u043a\u0438\u0439"
    ],
    "name:und_x_variant":[
        "Khutor Kammenoy",
        "Kamennoy",
        "Kamenka",
        "Kamenskiy",
        "Kemenskiy"
    ],
    "wof:name":"Kamenskiy",
    "wof:placetype":"locality"
},
  "geometry": {"coordinates":[41.6038,50.2056],"type":"Point"}
}