{
  "type": "Feature",
  "properties": {
    "gn:admin1_code":"42",
    "gn:asciiname":"Gruzino",
    "gn:country_code":"RU",
    "gn:dem":64,
    "gn:feature_class":"P",
    "gn:feature_code":"PPL",
    "gn:name":"Gruzino",
    "gn:population":0,
    "gn:timezone":"Europe/Moscow",
    "iso:country":"RU",
    "name:rus_x_preferred":[
        "\u0413\u0440\u0443\u0437\u0438\u043d\u043e"
    ],
    "name:und_x_variant":[
        "Grusino",
        "Gruzino",
        "\u0413\u0440\u0443\u0437\u0438\u043d\u043e"
    ],
    "wof:name":"Gruzino",
    "wof:placetype":"locality"
},
  "geometry": {"coordinates":[33.84295,59.95144000000001],"type":"Point"}
}