{
  "type": "Feature",
  "properties": {
    "gn:admin1_code":"43",
    "gn:asciiname":"Zubovskiy",
    "gn:country_code":"RU",
    "gn:dem":203,
    "gn:feature_class":"P",
    "gn:feature_code":"PPL",
    "gn:name":"Zubovskiy",
    "gn:population":0,
    "gn:timezone":"Europe/Moscow",
    "iso:country":"RU",
    "name:rus_x_preferred":[
        "\u0417\u0443\u0431\u043e\u0432\u0441\u043a\u0438\u0439"
    ],
    "name:und_x_variant":[
        "\u0417\u0443\u0431\u043e\u0432\u0441\u043a\u0438\u0439"
    ],
    "wof:name":"Zubovskiy",
    "wof:placetype":"locality"
},
  "geometry": {"coordinates":[38.7876,53.4201],"type":"Point"}
}