{
  "type": "Feature",
  "properties": {
    "gn:admin1_code":"61",
    "gn:asciiname":"Ust'-Proval'skiy",
    "gn:country_code":"RU",
    "gn:dem":69,
    "gn:feature_class":"P",
    "gn:feature_code":"PPL",
    "gn:name":"Ust\u2019-Proval\u2019skiy",
    "gn:population":0,
    "gn:timezone":"Europe/Moscow",
    "iso:country":"RU",
    "wof:name":"Ust'-Proval'skiy",
    "wof:placetype":"locality"
},
  "geometry": {"coordinates":[41.14639,48.16167],"type":"Point"}
}