{
  "type": "Feature",
  "properties": {
    "gn:admin1_code":"10",
    "gn:asciiname":"Kurnyavtsevo",
    "gn:country_code":"RU",
    "gn:dem":178,
    "gn:feature_class":"P",
    "gn:feature_code":"PPL",
    "gn:name":"Kurnyavtsevo",
    "gn:population":0,
    "gn:timezone":"Europe/Moscow",
    "iso:country":"RU",
    "name:rus_x_preferred":[
        "\u041a\u0443\u0440\u043d\u044f\u0432\u0446\u0435\u0432\u043e"
    ],
    "name:und_x_variant":[
        "Balakhonovka",
        "Kurnyavtseva",
        "Kurnyavtsevo",
        "\u041a\u0443\u0440\u043d\u044f\u0432\u0446\u0435\u0432\u043e"
    ],
    "wof:name":"Kurnyavtsevo",
    "wof:placetype":"locality"
},
  "geometry": {"coordinates":[34.28793,53.22166],"type":"Point"}
}