{
  "type": "Feature",
  "properties": {
    "gn:admin1_code":"47",
    "gn:asciiname":"Podbereznoye",
    "gn:country_code":"RU",
    "gn:dem":144,
    "gn:feature_class":"P",
    "gn:feature_code":"PPL",
    "gn:name":"Podbereznoye",
    "gn:population":0,
    "gn:timezone":"Europe/Moscow",
    "iso:country":"RU",
    "name:rus_x_preferred":[
        "\u041f\u043e\u0434\u0431\u0435\u0440\u0435\u0437\u043d\u043e\u0435"
    ],
    "name:und_x_variant":[
        "Podberezno",
        "Podbereznoye"
    ],
    "wof:name":"Podbereznoye",
    "wof:placetype":"locality"
},
  "geometry": {"coordinates":[38.05035,55.47439],"type":"Point"}
}