{
  "type": "Feature",
  "properties": {
    "gn:admin1_code":"38.0",
    "gn:asciiname":"Ayukov",
    "gn:country_code":"RU",
    "gn:dem":176,
    "gn:feature_class":"P",
    "gn:feature_code":"PPL",
    "gn:name":"Ayukov",
    "gn:population":0,
    "gn:timezone":"Europe/Moscow",
    "iso:country":"RU",
    "name:rus_x_preferred":[
        "(( \u0410\u044e\u043a\u043e\u0432 ))"
    ],
    "wof:name":"Ayukov",
    "wof:placetype":"locality"
},
  "geometry": {"coordinates":[39.03,44.48],"type":"Point"}
}