{
  "type": "Feature",
  "properties": {
    "gn:admin1_code":"77",
    "gn:asciiname":"Drozdovo",
    "gn:country_code":"RU",
    "gn:dem":260,
    "gn:feature_class":"P",
    "gn:feature_code":"PPL",
    "gn:name":"Drozdovo",
    "gn:population":0,
    "gn:timezone":"Europe/Moscow",
    "iso:country":"RU",
    "name:rus_x_preferred":[
        "\u0414\u0440\u043e\u0437\u0434\u043e\u0432\u043e"
    ],
    "name:und_x_variant":[
        "\u0414\u0440\u043e\u0437\u0434\u043e\u0432\u043e"
    ],
    "wof:name":"Drozdovo",
    "wof:placetype":"locality"
},
  "geometry": {"coordinates":[34.3477,57.33047],"type":"Point"}
}