{
  "type": "Feature",
  "properties": {
    "gn:admin1_code":"86.0",
    "gn:asciiname":"Alekseyevskiy Pervyy",
    "gn:country_code":"RU",
    "gn:dem":165,
    "gn:feature_class":"P",
    "gn:feature_code":"PPL",
    "gn:name":"Alekseyevskiy Pervyy",
    "gn:population":0,
    "gn:timezone":"Europe/Moscow",
    "iso:country":"RU",
    "name:nor_x_preferred":[
        "Aleksejevskij Pervyj"
    ],
    "name:rus_x_preferred":[
        "\u0410\u043b\u0435\u043a\u0441\u0435\u0435\u0432\u0441\u043a\u0438\u0439 \u041f\u0435\u0440\u0432\u044b\u0439"
    ],
    "wof:name":"Alekseyevskiy Pervyy",
    "wof:placetype":"locality"
},
  "geometry": {"coordinates":[40.24306,51.66722],"type":"Point"}
}