{
  "type": "Feature",
  "properties": {
    "gn:admin1_code":"61",
    "gn:asciiname":"Rudukhina-Balka",
    "gn:country_code":"RU",
    "gn:dem":86,
    "gn:feature_class":"P",
    "gn:feature_code":"PPL",
    "gn:name":"Rudukhina-Balka",
    "gn:population":0,
    "gn:timezone":"Europe/Moscow",
    "iso:country":"RU",
    "name:rus_x_preferred":[
        "\u0420\u0443\u0434\u0443\u0445\u0438\u043d\u0430-\u0411\u0430\u043b\u043a\u0430"
    ],
    "wof:name":"Rudukhina-Balka",
    "wof:placetype":"locality"
},
  "geometry": {"coordinates":[40.42111,47.04111],"type":"Point"}
}