{
  "type": "Feature",
  "properties": {
    "gn:admin1_code":"41.0",
    "gn:asciiname":"Rovni",
    "gn:country_code":"RU",
    "gn:dem":239,
    "gn:feature_class":"P",
    "gn:feature_code":"PPL",
    "gn:name":"Rovni",
    "gn:population":0,
    "gn:timezone":"Europe/Moscow",
    "iso:country":"RU",
    "name:ceb_x_preferred":[
        "Rovni"
    ],
    "name:ell_x_preferred":[
        "\u03a1\u03cc\u03b2\u03bd\u03b9"
    ],
    "name:fas_x_preferred":[
        "\u0631\u0648\u0648\u0646\u06cc"
    ],
    "name:fra_x_preferred":[
        "Rovni"
    ],
    "name:msa_x_preferred":[
        "Rovni"
    ],
    "name:nld_x_preferred":[
        "Rovni"
    ],
    "name:por_x_preferred":[
        "Rovni"
    ],
    "name:slv_x_preferred":[
        "Rovni"
    ],
    "name:srp_x_preferred":[
        "\u0420\u043e\u0432\u043d\u0438"
    ],
    "wof:name":"Rovni",
    "wof:placetype":"locality"
},
  "geometry": {"coordinates":[35.96167,51.3075],"type":"Point"}
}