{
  "type": "Feature",
  "properties": {
    "gn:admin1_code":"42.0",
    "gn:asciiname":"Primernoye",
    "gn:country_code":"RU",
    "gn:dem":56,
    "gn:feature_class":"P",
    "gn:feature_code":"PPL",
    "gn:name":"Primernoye",
    "gn:population":0,
    "gn:timezone":"Europe/Moscow",
    "iso:country":"RU",
    "name:rus_x_preferred":[
        "\u041f\u0440\u0438\u043c\u0435\u0440\u043d\u043e\u0435"
    ],
    "wof:name":"Primernoye",
    "wof:placetype":"locality"
},
  "geometry": {"coordinates":[30.89333,59.38556],"type":"Point"}
}