{
  "type": "Feature",
  "properties": {
    "gn:admin1_code":"45.0",
    "gn:asciiname":"Zyablitsevo",
    "gn:country_code":"RU",
    "gn:dem":158,
    "gn:feature_class":"P",
    "gn:feature_code":"PPL",
    "gn:name":"Zyablitsevo",
    "gn:population":0,
    "gn:timezone":"Europe/Moscow",
    "iso:country":"RU",
    "name:rus_x_preferred":[
        "\u0417\u044f\u0431\u043b\u0438\u0446\u0435\u0432\u043e"
    ],
    "name:und_x_variant":[
        "Zablitsevo"
    ],
    "wof:name":"Zyablitsevo",
    "wof:placetype":"locality"
},
  "geometry": {"coordinates":[49.63824,56.61224],"type":"Point"}
}