{
  "type": "Feature",
  "properties": {
    "gn:admin1_code":"71",
    "gn:asciiname":"Alap",
    "gn:country_code":"RU",
    "gn:dem":240,
    "gn:feature_class":"P",
    "gn:feature_code":"PPL",
    "gn:name":"Alap",
    "gn:population":0,
    "gn:timezone":"Asia/Yekaterinburg",
    "iso:country":"RU",
    "name:rus_x_preferred":[
        "\u0410\u043b\u0430\u043f"
    ],
    "wof:name":"Alap",
    "wof:placetype":"locality"
},
  "geometry": {"coordinates":[58.0192,56.9036],"type":"Point"}
}