{
  "type": "Feature",
  "properties": {
    "gn:admin1_code":"42",
    "gn:asciiname":"Sredniye Mandrogi",
    "gn:country_code":"RU",
    "gn:dem":27,
    "gn:feature_class":"P",
    "gn:feature_code":"PPL",
    "gn:name":"Sredniye Mandrogi",
    "gn:population":0,
    "gn:timezone":"Europe/Moscow",
    "iso:country":"RU",
    "name:rus_x_preferred":[
        "\u0421\u0440\u0435\u0434\u043d\u0438\u0435 \u041c\u0430\u043d\u0434\u0440\u043e\u0433\u0438"
    ],
    "name:und_x_variant":[
        "Mandrogi",
        "Sredniye Mandrogi",
        "\u0421\u0440\u0435\u0434\u043d\u0438\u0435 \u041c\u0430\u043d\u0434\u0440\u043e\u0433\u0438"
    ],
    "wof:name":"Sredniye Mandrogi",
    "wof:placetype":"locality"
},
  "geometry": {"coordinates":[33.78646,60.87765],"type":"Point"}
}