{
  "type": "Feature",
  "properties": {
    "gn:admin1_code":"8",
    "gn:asciiname":"Kardykskiy",
    "gn:country_code":"RU",
    "gn:dem":512,
    "gn:feature_class":"P",
    "gn:feature_code":"PPL",
    "gn:name":"Kardykskiy",
    "gn:population":0,
    "gn:timezone":"Asia/Yekaterinburg",
    "iso:country":"RU",
    "name:rus_x_preferred":[
        "\u041a\u0430\u0440\u0434\u044b\u043a\u0441\u043a\u0438\u0439"
    ],
    "wof:name":"Kardykskiy",
    "wof:placetype":"locality"
},
  "geometry": {"coordinates":[57.43333000000001,53.46666999999999],"type":"Point"}
}