{
  "type": "Feature",
  "properties": {
    "gn:admin1_code":"47",
    "gn:asciiname":"Psarevo",
    "gn:country_code":"RU",
    "gn:dem":152,
    "gn:feature_class":"P",
    "gn:feature_code":"PPL",
    "gn:name":"Psar\u00ebvo",
    "gn:population":0,
    "gn:timezone":"Europe/Moscow",
    "iso:country":"RU",
    "name:rus_x_preferred":[
        "\u041f\u0441\u0430\u0440\u0451\u0432\u043e"
    ],
    "name:und_x_variant":[
        "Psar\u00ebvo",
        "\u041f\u0441\u0430\u0440\u0451\u0432\u043e"
    ],
    "wof:name":"Psarevo",
    "wof:placetype":"locality"
},
  "geometry": {"coordinates":[38.41667,55.08333],"type":"Point"}
}