{
  "type": "Feature",
  "properties": {
    "gn:admin1_code":"05",
    "gn:asciiname":"Men'shikova",
    "gn:country_code":"RU",
    "gn:dem":330,
    "gn:feature_class":"P",
    "gn:feature_code":"PPL",
    "gn:name":"Men\u2019shikova",
    "gn:population":0,
    "gn:timezone":"Asia/Yakutsk",
    "iso:country":"RU",
    "name:rus_x_preferred":[
        "\u041c\u0435\u043d\u044c\u0448\u0438\u043a\u043e\u0432\u0430"
    ],
    "name:und_x_variant":[
        "Men\u2019shikova"
    ],
    "wof:name":"Men'shikova",
    "wof:placetype":"locality"
},
  "geometry": {"coordinates":[128.94224,53.23042],"type":"Point"}
}