{
  "type": "Feature",
  "properties": {
    "gn:admin1_code":"8",
    "gn:asciiname":"Mirkov",
    "gn:country_code":"RU",
    "gn:dem":543,
    "gn:feature_class":"P",
    "gn:feature_code":"PPL",
    "gn:name":"Mirkov",
    "gn:population":0,
    "gn:timezone":"Asia/Yekaterinburg",
    "iso:country":"RU",
    "name:rus_x_preferred":[
        "\u041c\u0438\u0440\u043a\u043e\u0432"
    ],
    "wof:name":"Mirkov",
    "wof:placetype":"locality"
},
  "geometry": {"coordinates":[58.53333000000001,54.25],"type":"Point"}
}