{
  "type": "Feature",
  "properties": {
    "gn:admin1_code":"10",
    "gn:asciiname":"Novogeorgiyevskiy",
    "gn:country_code":"RU",
    "gn:dem":202,
    "gn:feature_class":"P",
    "gn:feature_code":"PPL",
    "gn:name":"Novogeorgiyevskiy",
    "gn:population":0,
    "gn:timezone":"Europe/Moscow",
    "iso:country":"RU",
    "wof:name":"Novogeorgiyevskiy",
    "wof:placetype":"locality"
},
  "geometry": {"coordinates":[34.28697,52.84624],"type":"Point"}
}