{
  "type": "Feature",
  "properties": {
    "gn:admin1_code":"21",
    "gn:asciiname":"Chentsy",
    "gn:country_code":"RU",
    "gn:dem":124,
    "gn:feature_class":"P",
    "gn:feature_code":"PPL",
    "gn:name":"Chentsy",
    "gn:population":0,
    "gn:timezone":"Europe/Moscow",
    "iso:country":"RU",
    "name:rus_x_preferred":[
        "\u0427\u0435\u043d\u0446\u044b"
    ],
    "wof:name":"Chentsy",
    "wof:placetype":"locality"
},
  "geometry": {"coordinates":[39.82139,56.89422],"type":"Point"}
}