{
  "type": "Feature",
  "properties": {
    "gn:admin1_code":"62.0",
    "gn:asciiname":"Bogoroditskoye",
    "gn:country_code":"RU",
    "gn:dem":162,
    "gn:feature_class":"P",
    "gn:feature_code":"PPL",
    "gn:name":"Bogoroditskoye",
    "gn:population":0,
    "gn:timezone":"Europe/Moscow",
    "iso:country":"RU",
    "name:rus_x_preferred":[
        "\u0411\u043e\u0433\u043e\u0440\u043e\u0434\u0438\u0446\u043a\u043e\u0435"
    ],
    "name:und_x_variant":[
        "Bogoroditskiy",
        "Bogoroditskiy Gay"
    ],
    "wof:name":"Bogoroditskoye",
    "wof:placetype":"locality"
},
  "geometry": {"coordinates":[40.5793,53.5517],"type":"Point"}
}