{
  "type": "Feature",
  "properties": {
    "gn:admin1_code":"4",
    "gn:asciiname":"Tundrikha",
    "gn:country_code":"RU",
    "gn:dem":165,
    "gn:feature_class":"P",
    "gn:feature_code":"PPL",
    "gn:name":"Tundrikha",
    "gn:population":0,
    "gn:timezone":"Asia/Barnaul",
    "iso:country":"RU",
    "name:eng_x_preferred":[
        "Tundrikha"
    ],
    "name:nor_x_preferred":[
        "Tundrikha"
    ],
    "name:rus_x_preferred":[
        "\u0422\u0443\u043d\u0434\u0440\u0438\u0445\u0430"
    ],
    "name:und_x_variant":[
        "Tundrikhi",
        "Tundrikha"
    ],
    "wof:name":"Tundrikha",
    "wof:placetype":"locality"
},
  "geometry": {"coordinates":[84.54111,53.99166999999999],"type":"Point"}
}