{
  "type": "Feature",
  "properties": {
    "gn:admin1_code":"52",
    "gn:asciiname":"Oleshnya",
    "gn:country_code":"RU",
    "gn:dem":45,
    "gn:feature_class":"P",
    "gn:feature_code":"PPL",
    "gn:name":"Oleshnya",
    "gn:population":0,
    "gn:timezone":"Europe/Moscow",
    "iso:country":"RU",
    "name:rus_x_preferred":[
        "\u041e\u043b\u0435\u0448\u043d\u044f"
    ],
    "wof:name":"Oleshnya",
    "wof:placetype":"locality"
},
  "geometry": {"coordinates":[32.36108,58.39563],"type":"Point"}
}