{
  "type": "Feature",
  "properties": {
    "gn:admin1_code":"9",
    "gn:asciiname":"Streletskoye",
    "gn:country_code":"RU",
    "gn:dem":157,
    "gn:feature_class":"P",
    "gn:feature_code":"PPL",
    "gn:name":"Streletskoye",
    "gn:population":0,
    "gn:timezone":"Europe/Moscow",
    "iso:country":"RU",
    "name:rus_x_preferred":[
        "\u0421\u0442\u0440\u0435\u043b\u0435\u0442\u0441\u043a\u043e\u0435"
    ],
    "wof:name":"Streletskoye",
    "wof:placetype":"locality"
},
  "geometry": {"coordinates":[36.46922,50.64102000000001],"type":"Point"}
}