{
  "type": "Feature",
  "properties": {
    "gn:admin1_code":"71",
    "gn:asciiname":"Dymkovskoye",
    "gn:country_code":"RU",
    "gn:dem":80,
    "gn:feature_class":"P",
    "gn:feature_code":"PPL",
    "gn:name":"Dymkovskoye",
    "gn:population":0,
    "gn:timezone":"Asia/Yekaterinburg",
    "iso:country":"RU",
    "name:eng_x_preferred":[
        "Dymkovskoye"
    ],
    "name:nor_x_preferred":[
        "Dymkovskoje"
    ],
    "name:rus_x_preferred":[
        "\u0414\u044b\u043c\u043a\u043e\u0432\u0441\u043a\u043e\u0435"
    ],
    "name:und_x_variant":[
        "Dymkovo"
    ],
    "wof:name":"Dymkovskoye",
    "wof:placetype":"locality"
},
  "geometry": {"coordinates":[63.0698,58.06935],"type":"Point"}
}