{
  "type": "Feature",
  "properties": {
    "gn:admin1_code":"23",
    "gn:asciiname":"Kazantsevo",
    "gn:country_code":"RU",
    "gn:dem":23,
    "gn:feature_class":"P",
    "gn:feature_code":"PPL",
    "gn:name":"Kazantsevo",
    "gn:population":0,
    "gn:timezone":"Europe/Kaliningrad",
    "iso:country":"RU",
    "name:rus_x_preferred":[
        "\u041a\u0430\u0437\u0430\u043d\u0446\u0435\u0432\u043e"
    ],
    "name:und_x_variant":[
        "\u041a\u0430\u0437\u0430\u043d\u0446\u0435\u0432\u043e"
    ],
    "wof:name":"Kazantsevo",
    "wof:placetype":"locality"
},
  "geometry": {"coordinates":[21.67944,54.6775],"type":"Point"}
}