{
  "type": "Feature",
  "properties": {
    "gn:admin1_code":"3",
    "gn:asciiname":"Karatorbok",
    "gn:country_code":"RU",
    "gn:dem":474,
    "gn:feature_class":"P",
    "gn:feature_code":"PPL",
    "gn:name":"Karatorbok",
    "gn:population":0,
    "gn:timezone":"Asia/Omsk",
    "iso:country":"RU",
    "name:rus_x_preferred":[
        "\u041a\u0430\u0440\u0430\u0442\u043e\u0440\u0431\u043e\u043a"
    ],
    "name:und_x_variant":[
        "\u041a\u0430\u0440\u0430\u0442\u043e\u0440\u0431\u043e\u043a"
    ],
    "wof:name":"Karatorbok",
    "wof:placetype":"locality"
},
  "geometry": {"coordinates":[86.33833,51.81667],"type":"Point"}
}