{
  "type": "Feature",
  "properties": {
    "gn:admin1_code":"52.0",
    "gn:asciiname":"Astrilovo",
    "gn:country_code":"RU",
    "gn:dem":61,
    "gn:feature_class":"P",
    "gn:feature_code":"PPL",
    "gn:name":"Astrilovo",
    "gn:population":0,
    "gn:timezone":"Europe/Moscow",
    "iso:country":"RU",
    "name:eng_x_preferred":[
        "Astrilovo"
    ],
    "name:nor_x_preferred":[
        "Astrilovo"
    ],
    "name:rus_x_preferred":[
        "\u0410\u0441\u0442\u0440\u0438\u043b\u043e\u0432\u043e"
    ],
    "wof:name":"Astrilovo",
    "wof:placetype":"locality"
},
  "geometry": {"coordinates":[31.07472000000001,57.77398],"type":"Point"}
}