{
  "type": "Feature",
  "properties": {
    "gn:admin1_code":"63",
    "gn:asciiname":"Kurumkan",
    "gn:country_code":"RU",
    "gn:dem":426,
    "gn:feature_class":"P",
    "gn:feature_code":"PPL",
    "gn:name":"Kurumkan",
    "gn:population":0,
    "gn:timezone":"Asia/Yakutsk",
    "iso:country":"RU",
    "name:eng_x_preferred":[
        "Kurumkan"
    ],
    "name:nor_x_preferred":[
        "Kurumkan"
    ],
    "name:rus_x_preferred":[
        "\u041a\u0443\u0440\u0443\u043c\u043a\u0430\u043d"
    ],
    "name:und_x_variant":[
        "\u041a\u0443\u0440\u0443\u043c\u043a\u0430\u043d",
        "Kurumkan"
    ],
    "wof:name":"Kurumkan",
    "wof:placetype":"locality"
},
  "geometry": {"coordinates":[123.80110000000001,57.83467],"type":"Point"}
}