{
  "type": "Feature",
  "properties": {
    "gn:admin1_code":"63",
    "gn:asciiname":"Kurumkan",
    "gn:country_code":"RU",
    "gn:dem":426,
    "gn:feature_class":"P",
    "gn:feature_code":"PPL",
    "gn:name":"Kurumkan",
    "gn:population":0,
    "gn:timezone":"Asia/Yakutsk",
    "iso:country":"RU",
    "name:bel_x_preferred":[
        "\u041a\u0443\u0440\u0443\u043c\u043a\u0430\u043d"
    ],
    "name:bxr_x_preferred":[
        "\u0425\u0443\u0440\u0430\u043c\u0445\u0430\u0430\u043d"
    ],
    "name:ceb_x_preferred":[
        "Kurumkan"
    ],
    "name:che_x_preferred":[
        "\u041a\u0443\u0440\u0443\u043c\u043a\u0430\u043d"
    ],
    "name:deu_x_preferred":[
        "Kurumkan"
    ],
    "name:eng_x_preferred":[
        "Kurumkan"
    ],
    "name:mon_x_preferred":[
        "\u0425\u0443\u0440\u0430\u043c\u0445\u0430\u0430\u043d \u0441\u0443\u0443\u0440\u0438\u043d"
    ],
    "name:nor_x_preferred":[
        "Kurumkan"
    ],
    "name:rus_x_preferred":[
        "\u041a\u0443\u0440\u0443\u043c\u043a\u0430\u043d"
    ],
    "name:ukr_x_preferred":[
        "\u041a\u0443\u0440\u0443\u043c\u043a\u0430\u043d"
    ],
    "wof:name":"Kurumkan",
    "wof:placetype":"locality"
},
  "geometry": {"coordinates":[123.80110000000001,57.83467],"type":"Point"}
}