{
  "type": "Feature",
  "properties": {
    "gn:admin1_code":"87",
    "gn:asciiname":"Tambey",
    "gn:country_code":"RU",
    "gn:dem":6,
    "gn:feature_class":"P",
    "gn:feature_code":"PPL",
    "gn:name":"Tambey",
    "gn:population":0,
    "gn:timezone":"Asia/Yekaterinburg",
    "iso:country":"RU",
    "name:eng_x_preferred":[
        "Tambey"
    ],
    "name:nor_x_preferred":[
        "Tambej"
    ],
    "name:rus_x_preferred":[
        "\u0422\u0430\u043c\u0431\u0435\u0439"
    ],
    "name:und_x_variant":[
        "Faktoriya Tambey",
        "Tambei"
    ],
    "wof:name":"Tambey",
    "wof:placetype":"locality"
},
  "geometry": {"coordinates":[71.81513000000002,71.47645],"type":"Point"}
}