{
  "type": "Feature",
  "properties": {
    "gn:admin1_code":"57.0",
    "gn:asciiname":"Nadezhdinka",
    "gn:country_code":"RU",
    "gn:dem":216,
    "gn:feature_class":"P",
    "gn:feature_code":"PPL",
    "gn:name":"Nadezhdinka",
    "gn:population":0,
    "gn:timezone":"Europe/Moscow",
    "iso:country":"RU",
    "name:rus_x_preferred":[
        "\u041d\u0430\u0434\u0435\u0436\u0434\u0438\u043d\u043a\u0430"
    ],
    "wof:name":"Nadezhdinka",
    "wof:placetype":"locality"
},
  "geometry": {"coordinates":[45.0005,53.63601],"type":"Point"}
}