{
  "type": "Feature",
  "properties": {
    "gn:admin1_code":"30",
    "gn:asciiname":"Voronezhskoye Vtoroye",
    "gn:country_code":"RU",
    "gn:dem":54,
    "gn:feature_class":"P",
    "gn:feature_code":"PPL",
    "gn:name":"Voronezhskoye Vtoroye",
    "gn:population":0,
    "gn:timezone":"Asia/Vladivostok",
    "iso:country":"RU",
    "name:rus_x_preferred":[
        "\u0412\u043e\u0440\u043e\u043d\u0435\u0436\u0441\u043a\u043e\u0435 \u0412\u0442\u043e\u0440\u043e\u0435"
    ],
    "name:und_x_variant":[
        "Voronezhskoye",
        "Voronezhskoye Vtoroye"
    ],
    "wof:name":"Voronezhskoye Vtoroye",
    "wof:placetype":"locality"
},
  "geometry": {"coordinates":[135.06573,48.62231],"type":"Point"}
}