{
  "type": "Feature",
  "properties": {
    "gn:admin1_code":"73.0",
    "gn:asciiname":"Bishevo",
    "gn:country_code":"RU",
    "gn:dem":71,
    "gn:feature_class":"P",
    "gn:feature_code":"PPL",
    "gn:name":"Bishevo",
    "gn:population":0,
    "gn:timezone":"Europe/Moscow",
    "iso:country":"RU",
    "name:rus_x_preferred":[
        "\u0411\u0438\u0448\u0435\u0432\u043e"
    ],
    "wof:name":"Bishevo",
    "wof:placetype":"locality"
},
  "geometry": {"coordinates":[48.44737,55.23148000000001],"type":"Point"}
}