{
  "type": "Feature",
  "properties": {
    "gn:admin1_code":"10",
    "gn:asciiname":"Novozheyevka",
    "gn:country_code":"RU",
    "gn:dem":181,
    "gn:feature_class":"P",
    "gn:feature_code":"PPL",
    "gn:name":"Novozheyevka",
    "gn:population":0,
    "gn:timezone":"Europe/Moscow",
    "iso:country":"RU",
    "name:rus_x_preferred":[
        "\u041d\u043e\u0432\u043e\u0436\u0435\u0435\u0432\u043a\u0430"
    ],
    "name:und_x_variant":[
        "Novozzheyeva",
        "Novozzheyev",
        "Novozheyevka"
    ],
    "wof:name":"Novozheyevka",
    "wof:placetype":"locality"
},
  "geometry": {"coordinates":[33.0364,53.4963],"type":"Point"}
}