{
  "type": "Feature",
  "properties": {
    "gn:admin1_code":"76.0",
    "gn:asciiname":"Brusna",
    "gn:country_code":"RU",
    "gn:dem":215,
    "gn:feature_class":"P",
    "gn:feature_code":"PPL",
    "gn:name":"Brusna",
    "gn:population":0,
    "gn:timezone":"Europe/Moscow",
    "iso:country":"RU",
    "name:rus_x_preferred":[
        "\u0411\u0440\u0443\u0441\u043d\u0430"
    ],
    "name:und_x_variant":[
        "\u0411\u0440\u0443\u0441\u043d\u0430"
    ],
    "wof:name":"Brusna",
    "wof:placetype":"locality"
},
  "geometry": {"coordinates":[36.6214,53.94519],"type":"Point"}
}