{
  "type": "Feature",
  "properties": {
    "gn:admin1_code":"77",
    "gn:asciiname":"Iyevtsevo",
    "gn:country_code":"RU",
    "gn:dem":156,
    "gn:feature_class":"P",
    "gn:feature_code":"PPL",
    "gn:name":"Iyevtsevo",
    "gn:population":0,
    "gn:timezone":"Europe/Moscow",
    "iso:country":"RU",
    "name:rus_x_preferred":[
        "\u0418\u0435\u0432\u0446\u0435\u0432\u043e"
    ],
    "name:und_x_variant":[
        "\u0418\u0435\u0432\u0446\u0435\u0432\u043e"
    ],
    "wof:name":"Iyevtsevo",
    "wof:placetype":"locality"
},
  "geometry": {"coordinates":[34.81225999999999,57.43955],"type":"Point"}
}