{
  "type": "Feature",
  "properties": {
    "gn:admin1_code":"28",
    "gn:asciiname":"Ryakyali",
    "gn:country_code":"RU",
    "gn:dem":79,
    "gn:feature_class":"P",
    "gn:feature_code":"PPL",
    "gn:name":"Ryakyali",
    "gn:population":0,
    "gn:timezone":"Europe/Moscow",
    "iso:country":"RU",
    "name:rus_x_preferred":[
        "\u0420\u044f\u043a\u044f\u043b\u0438"
    ],
    "wof:name":"Ryakyali",
    "wof:placetype":"locality"
},
  "geometry": {"coordinates":[31.15,61.78333000000001],"type":"Point"}
}