{
  "type": "Feature",
  "properties": {
    "gn:admin1_code":"53",
    "gn:asciiname":"Rasskazovo",
    "gn:country_code":"RU",
    "gn:dem":111,
    "gn:feature_class":"P",
    "gn:feature_code":"PPL",
    "gn:name":"Rasskazovo",
    "gn:population":0,
    "gn:timezone":"Asia/Novosibirsk",
    "iso:country":"RU",
    "name:eng_x_preferred":[
        "Rasskazovo"
    ],
    "name:nor_x_preferred":[
        "Rasskazovo"
    ],
    "name:rus_x_preferred":[
        "\u0420\u0430\u0441\u0441\u043a\u0430\u0437\u043e\u0432\u043e"
    ],
    "name:und_x_variant":[
        "Rasskazovskiy",
        "\u0420\u0430\u0441\u0441\u043a\u0430\u0437\u043e\u0432\u043e",
        "Rasskazovo"
    ],
    "wof:name":"Rasskazovo",
    "wof:placetype":"locality"
},
  "geometry": {"coordinates":[77.92273,53.66541],"type":"Point"}
}