{
  "type": "Feature",
  "properties": {
    "gn:admin1_code":"51.0",
    "gn:asciiname":"Pyatnitsy",
    "gn:country_code":"RU",
    "gn:dem":111,
    "gn:feature_class":"P",
    "gn:feature_code":"PPL",
    "gn:name":"Pyatnitsy",
    "gn:population":0,
    "gn:timezone":"Europe/Moscow",
    "iso:country":"RU",
    "name:rus_x_preferred":[
        "\u041f\u044f\u0442\u043d\u0438\u0446\u044b"
    ],
    "wof:name":"Pyatnitsy",
    "wof:placetype":"locality"
},
  "geometry": {"coordinates":[43.39151,55.39424],"type":"Point"}
}