{
  "type": "Feature",
  "properties": {
    "gn:admin1_code":"71.0",
    "gn:asciiname":"Ishchina",
    "gn:country_code":"RU",
    "gn:dem":95,
    "gn:feature_class":"P",
    "gn:feature_code":"PPL",
    "gn:name":"Ishchina",
    "gn:population":0,
    "gn:timezone":"Asia/Yekaterinburg",
    "iso:country":"RU",
    "name:rus_x_preferred":[
        "\u0418\u0449\u0438\u043d\u0430"
    ],
    "name:und_x_variant":[
        "\u0418\u0449\u0438\u043d\u0430",
        "Ishchina"
    ],
    "wof:name":"Ishchina",
    "wof:placetype":"locality"
},
  "geometry": {"coordinates":[62.5504,59.17475],"type":"Point"}
}