{
  "type": "Feature",
  "properties": {
    "gn:admin1_code":"21.0",
    "gn:asciiname":"Palkino",
    "gn:country_code":"RU",
    "gn:dem":106,
    "gn:feature_class":"P",
    "gn:feature_code":"PPL",
    "gn:name":"Palkino",
    "gn:population":0,
    "gn:timezone":"Europe/Moscow",
    "iso:country":"RU",
    "name:rus_x_preferred":[
        "\u041f\u0430\u043b\u043a\u0438\u043d\u043e"
    ],
    "wof:name":"Palkino",
    "wof:placetype":"locality"
},
  "geometry": {"coordinates":[42.24196,57.06289],"type":"Point"}
}