{
  "type": "Feature",
  "properties": {
    "gn:admin1_code":"28",
    "gn:asciiname":"Lukin-Navolok",
    "gn:cc2":"RU",
    "gn:country_code":"RU",
    "gn:dem":27,
    "gn:feature_class":"P",
    "gn:feature_code":"PPL",
    "gn:name":"Lukin-Navolok",
    "gn:population":0,
    "gn:timezone":"Europe/Moscow",
    "iso:country":"RU",
    "name:eng_x_preferred":[
        "Lukin-Navolok"
    ],
    "name:fin_x_preferred":[
        "Lukinniemi"
    ],
    "name:nor_x_preferred":[
        "Lukin-Navolok"
    ],
    "name:rus_x_preferred":[
        "\u041b\u0443\u043a\u0438\u043d-\u041d\u0430\u0432\u043e\u043b\u043e\u043a"
    ],
    "name:und_x_variant":[
        "\u041b\u0443\u043a\u0438\u043d-\u041d\u0430\u0432\u043e\u043b\u043e\u043a",
        "Lukin-Navolok"
    ],
    "wof:name":"Lukin-Navolok",
    "wof:placetype":"locality"
},
  "geometry": {"coordinates":[34.58333,62.21666999999999],"type":"Point"}
}