{
  "type": "Feature",
  "properties": {
    "gn:admin1_code":"77",
    "gn:asciiname":"Khotilitsy",
    "gn:country_code":"RU",
    "gn:dem":234,
    "gn:feature_class":"P",
    "gn:feature_code":"PPL",
    "gn:name":"Khotilitsy",
    "gn:population":0,
    "gn:timezone":"Europe/Moscow",
    "iso:country":"RU",
    "name:eng_x_preferred":[
        "Khotilitsy"
    ],
    "name:nor_x_preferred":[
        "Khotilitsy"
    ],
    "name:rus_x_preferred":[
        "\u0425\u043e\u0442\u0438\u043b\u0438\u0446\u044b"
    ],
    "wof:name":"Khotilitsy",
    "wof:placetype":"locality"
},
  "geometry": {"coordinates":[31.88845,56.64849],"type":"Point"}
}