{
  "type": "Feature",
  "properties": {
    "gn:admin1_code":"76",
    "gn:asciiname":"Mostovaya",
    "gn:country_code":"RU",
    "gn:dem":211,
    "gn:feature_class":"P",
    "gn:feature_code":"PPL",
    "gn:name":"Mostovaya",
    "gn:population":0,
    "gn:timezone":"Europe/Moscow",
    "iso:country":"RU",
    "name:rus_x_preferred":[
        "\u041c\u043e\u0441\u0442\u043e\u0432\u0430\u044f"
    ],
    "name:und_x_variant":[
        "\u041c\u043e\u0441\u0442\u043e\u0432\u0430\u044f"
    ],
    "wof:name":"Mostovaya",
    "wof:placetype":"locality"
},
  "geometry": {"coordinates":[37.90802,53.83991],"type":"Point"}
}