{
  "type": "Feature",
  "properties": {
    "gn:country":"RU",
    "gn:fcode":"PPLX",
    "gn:population":1026,
    "iso:country":"RU",
    "name:fin_x_preferred":[
        "Yl\u00e4 Osselki"
    ],
    "name:rus_x_preferred":[
        "\u0412\u0435\u0440\u0445\u043d\u0438\u0435 \u041e\u0441\u0435\u043b\u044c\u043a\u0438"
    ],
    "qs:name":"Verkhniye Osel\u2019ki",
    "qs:photos_9r":0,
    "qs:photos_sr":0,
    "qs:pop_sr":"3",
    "wof:name":"Verkhniye Osel\u2019ki",
    "wof:placetype":"neighbourhood",
    "wof:population":1026
},
  "geometry": {"coordinates":[30.44938,60.24948],"type":"Point"}
}