{
  "type": "Feature",
  "properties": {
    "gn:country":"RU",
    "gn:fcode":"PPL",
    "gn:pop":2986,
    "iso:country":"RU",
    "name:eng_x_preferred":[
        "Pyatovskiy"
    ],
    "name:nor_x_preferred":[
        "Pjatovskij"
    ],
    "name:rus_x_preferred":[
        "\u041f\u044f\u0442\u043e\u0432\u0441\u043a\u0438\u0439"
    ],
    "name:unk_x_variant":[
        "\u041f\u044f\u0442\u043e\u0432\u0441\u043a\u0438\u0439"
    ],
    "qs:name":"Pyatovskiy",
    "qs:name_adm0":"Russia",
    "qs:name_adm1":"Kaluga Oblast",
    "qs:photos_9k":1,
    "qs:photos_9r":1,
    "qs:photos_all":1,
    "qs:photos_sr":0,
    "qs:placetype":"Town",
    "qs:pop_sr":"4",
    "wof:name":"Pyatovskiy",
    "wof:placetype":"locality",
    "wof:population":2986
},
  "geometry": {"coordinates":[36.05634,54.68908],"type":"Point"}
}