{
  "type": "Feature",
  "properties": {
    "gn:admin1_code":"84",
    "gn:asciiname":"Novoakhtubinskiy",
    "gn:cc2":"RU",
    "gn:country_code":"RU",
    "gn:dem":49,
    "gn:feature_class":"P",
    "gn:feature_code":"PPL",
    "gn:name":"Novoakhtubinskiy",
    "gn:population":0,
    "gn:timezone":"Europe/Volgograd",
    "iso:country":"RU",
    "name:rus_x_preferred":[
        "\u041d\u043e\u0432\u043e\u0430\u0445\u0442\u0443\u0431\u0438\u043d\u0441\u043a\u0438\u0439"
    ],
    "name:und_x_variant":[
        "Otorvanovka",
        "Novoakhtubinskiy",
        "\u041d\u043e\u0432\u043e\u0430\u0445\u0442\u0443\u0431\u0438\u043d\u0441\u043a\u0438\u0439"
    ],
    "wof:name":"Novoakhtubinskiy",
    "wof:placetype":"locality"
},
  "geometry": {"coordinates":[43.76278,48.56861],"type":"Point"}
}