{
  "type": "Feature",
  "properties": {
    "gn:admin1_code":"33.0",
    "gn:asciiname":"Shevniny",
    "gn:country_code":"RU",
    "gn:dem":116,
    "gn:feature_class":"P",
    "gn:feature_code":"PPL",
    "gn:name":"Shevniny",
    "gn:population":0,
    "gn:timezone":"Europe/Kirov",
    "iso:country":"RU",
    "name:rus_x_preferred":[
        "\u0428\u0435\u0432\u043d\u0438\u043d\u044b"
    ],
    "wof:name":"Shevniny",
    "wof:placetype":"locality"
},
  "geometry": {"coordinates":[48.80184000000001,58.41076],"type":"Point"}
}