{
  "type": "Feature",
  "properties": {
    "gn:admin1_code":"90",
    "gn:asciiname":"Marasany",
    "gn:country_code":"RU",
    "gn:dem":122,
    "gn:feature_class":"P",
    "gn:feature_code":"PPL",
    "gn:name":"Marasany",
    "gn:population":0,
    "gn:timezone":"Asia/Yekaterinburg",
    "iso:country":"RU",
    "name:eng_x_preferred":[
        "Marasany"
    ],
    "name:nor_x_preferred":[
        "Marasany"
    ],
    "name:rus_x_preferred":[
        "\u041c\u0430\u0440\u0430\u0441\u0430\u043d\u044b"
    ],
    "wof:name":"Marasany",
    "wof:placetype":"locality"
},
  "geometry": {"coordinates":[54.3954,57.4443],"type":"Point"}
}