{
  "type": "Feature",
  "properties": {
    "gn:admin1_code":"0.0",
    "gn:asciiname":"Krasnovol'skoye",
    "gn:cc2":"RU",
    "gn:country_code":"RU",
    "gn:dem":238,
    "gn:feature_class":"P",
    "gn:feature_code":"PPL",
    "gn:name":"Krasnovol'skoye",
    "gn:population":0,
    "gn:timezone":"Europe/Moscow",
    "iso:country":"RU",
    "name:und_x_variant":[
        "Navalishino",
        "Krasnovol'sk"
    ],
    "wof:name":"Krasnovol'skoye",
    "wof:placetype":"locality"
},
  "geometry": {"coordinates":[39.92861,43.56361],"type":"Point"}
}