{
  "type": "Feature",
  "properties": {
    "gn:admin1_code":"73",
    "gn:asciiname":"Tubulga",
    "gn:country_code":"RU",
    "gn:dem":156,
    "gn:feature_class":"P",
    "gn:feature_code":"PPL",
    "gn:name":"Tubulga",
    "gn:population":0,
    "gn:timezone":"Europe/Moscow",
    "iso:country":"RU",
    "name:rus_x_preferred":[
        "\u0422\u0443\u0431\u0443\u043b\u0433\u0430"
    ],
    "wof:name":"Tubulga",
    "wof:placetype":"locality"
},
  "geometry": {"coordinates":[50.74721,55.22769],"type":"Point"}
}