{
  "type": "Feature",
  "properties": {
    "gn:admin1_code":"90",
    "gn:asciiname":"Makaryata",
    "gn:country_code":"RU",
    "gn:dem":156,
    "gn:feature_class":"P",
    "gn:feature_code":"PPL",
    "gn:name":"Makaryata",
    "gn:population":0,
    "gn:timezone":"Asia/Yekaterinburg",
    "iso:country":"RU",
    "name:che_x_preferred":[
        "\u041c\u0430\u043a\u0430\u0440\u044f\u0442\u0430"
    ],
    "name:rus_x_preferred":[
        "\u041c\u0430\u043a\u0430\u0440\u044f\u0442\u0430"
    ],
    "wof:name":"Makaryata",
    "wof:placetype":"locality"
},
  "geometry": {"coordinates":[57.757,57.5335],"type":"Point"}
}