{
  "type": "Feature",
  "properties": {
    "gn:admin1_code":"45",
    "gn:asciiname":"Kukshenery",
    "gn:country_code":"RU",
    "gn:dem":59,
    "gn:feature_class":"P",
    "gn:feature_code":"PPL",
    "gn:name":"Kukshenery",
    "gn:population":0,
    "gn:timezone":"Europe/Moscow",
    "iso:country":"RU",
    "name:rus_x_preferred":[
        "\u041a\u0443\u043a\u0448\u0435\u043d\u0435\u0440\u044b"
    ],
    "name:und_x_variant":[
        "Kokshamary",
        "Kukshenery"
    ],
    "wof:name":"Kukshenery",
    "wof:placetype":"locality"
},
  "geometry": {"coordinates":[48.21167,55.94751],"type":"Point"}
}