{
  "type": "Feature",
  "properties": {
    "gn:admin1_code":"33",
    "gn:asciiname":"Kolpashino",
    "gn:country_code":"RU",
    "gn:dem":233,
    "gn:feature_class":"P",
    "gn:feature_code":"PPL",
    "gn:name":"Kolpashino",
    "gn:population":0,
    "gn:timezone":"Europe/Kirov",
    "iso:country":"RU",
    "name:rus_x_preferred":[
        "\u041a\u043e\u043b\u043f\u0430\u0448\u0438\u043d\u043e"
    ],
    "name:und_x_variant":[
        "Kolpashinskaya",
        "Kolpashino"
    ],
    "wof:name":"Kolpashino",
    "wof:placetype":"locality"
},
  "geometry": {"coordinates":[52.48275,58.9442],"type":"Point"}
}