{
  "type": "Feature",
  "properties": {
    "gn:admin1_code":"91",
    "gn:asciiname":"Makovskoye",
    "gn:country_code":"RU",
    "gn:dem":142,
    "gn:feature_class":"P",
    "gn:feature_code":"PPL",
    "gn:name":"Makovskoye",
    "gn:population":0,
    "gn:timezone":"Asia/Krasnoyarsk",
    "iso:country":"RU",
    "name:eng_x_preferred":[
        "Makovskoye"
    ],
    "name:nor_x_preferred":[
        "Makovskoje"
    ],
    "name:rus_x_preferred":[
        "\u041c\u0430\u043a\u043e\u0432\u0441\u043a\u043e\u0435"
    ],
    "wof:name":"Makovskoye",
    "wof:placetype":"locality"
},
  "geometry": {"coordinates":[90.87361,58.18666999999999],"type":"Point"}
}