{
  "type": "Feature",
  "properties": {
    "gn:admin1_code":"88",
    "gn:asciiname":"Zhuravlevo",
    "gn:country_code":"RU",
    "gn:dem":112,
    "gn:feature_class":"P",
    "gn:feature_code":"PPL",
    "gn:name":"Zhuravl\u00ebvo",
    "gn:population":0,
    "gn:timezone":"Europe/Moscow",
    "iso:country":"RU",
    "name:rus_x_preferred":[
        "\u0416\u0443\u0440\u0430\u0432\u043b\u0451\u0432\u043e"
    ],
    "name:und_x_variant":[
        "Zhuravl\u00ebvo"
    ],
    "wof:name":"Zhuravlevo",
    "wof:placetype":"locality"
},
  "geometry": {"coordinates":[38.32695,57.99569],"type":"Point"}
}