{
  "type": "Feature",
  "properties": {
    "gn:admin1_code":"60.0",
    "gn:asciiname":"Aleksandrova Sloboda",
    "gn:country_code":"RU",
    "gn:dem":90,
    "gn:feature_class":"P",
    "gn:feature_code":"PPL",
    "gn:name":"Aleksandrova Sloboda",
    "gn:population":0,
    "gn:timezone":"Europe/Moscow",
    "iso:country":"RU",
    "name:nor_x_preferred":[
        "Aleksandrova Sloboda"
    ],
    "name:rus_x_preferred":[
        "\u0410\u043b\u0435\u043a\u0441\u0430\u043d\u0434\u0440\u043e\u0432\u0430 \u0421\u043b\u043e\u0431\u043e\u0434\u0430"
    ],
    "wof:name":"Aleksandrova Sloboda",
    "wof:placetype":"locality"
},
  "geometry": {"coordinates":[28.56201,56.99063],"type":"Point"}
}