{
  "type": "Feature",
  "properties": {
    "gn:admin1_code":"73",
    "gn:asciiname":"Ak-Su",
    "gn:country_code":"RU",
    "gn:dem":246,
    "gn:feature_class":"P",
    "gn:feature_code":"PPL",
    "gn:name":"Ak-Su",
    "gn:population":0,
    "gn:timezone":"Europe/Moscow",
    "iso:country":"RU",
    "name:rus_x_preferred":[
        "\u0410\u043a-\u0421\u0443"
    ],
    "wof:name":"Ak-Su",
    "wof:placetype":"locality"
},
  "geometry": {"coordinates":[52.7253,54.8253],"type":"Point"}
}