{
  "type": "Feature",
  "properties": {
    "gn:admin1_code":"41",
    "gn:asciiname":"Slobodka",
    "gn:country_code":"RU",
    "gn:dem":154,
    "gn:feature_class":"P",
    "gn:feature_code":"PPL",
    "gn:name":"Slobodka",
    "gn:population":0,
    "gn:timezone":"Europe/Moscow",
    "iso:country":"RU",
    "name:rus_x_preferred":[
        "\u0421\u043b\u043e\u0431\u043e\u0434\u043a\u0430"
    ],
    "wof:name":"Slobodka",
    "wof:placetype":"locality"
},
  "geometry": {"coordinates":[34.7325,51.4823],"type":"Point"}
}