{
  "type": "Feature",
  "properties": {
    "gn:admin1_code":"19.0",
    "gn:asciiname":"Pyaling",
    "gn:country_code":"RU",
    "gn:dem":1613,
    "gn:feature_class":"P",
    "gn:feature_code":"PPL",
    "gn:name":"Pyaling",
    "gn:population":0,
    "gn:timezone":"Europe/Moscow",
    "iso:country":"RU",
    "wof:name":"Pyaling",
    "wof:placetype":"locality"
},
  "geometry": {"coordinates":[44.98639,42.82278],"type":"Point"}
}