{
  "type": "Feature",
  "properties": {
    "gn:admin1_code":"85.0",
    "gn:asciiname":"Chistikovo",
    "gn:country_code":"RU",
    "gn:dem":182,
    "gn:feature_class":"P",
    "gn:feature_code":"PPL",
    "gn:name":"Chistikovo",
    "gn:population":0,
    "gn:timezone":"Europe/Moscow",
    "iso:country":"RU",
    "name:eng_x_preferred":[
        "Chistikovo"
    ],
    "name:nor_x_preferred":[
        "Tsjistikovo"
    ],
    "name:rus_x_preferred":[
        "\u0427\u0438\u0441\u0442\u0438\u043a\u043e\u0432\u043e"
    ],
    "name:und_x_variant":[
        "Chistikova"
    ],
    "wof:name":"Chistikovo",
    "wof:placetype":"locality"
},
  "geometry": {"coordinates":[35.9352,59.7188],"type":"Point"}
}