{
  "type": "Feature",
  "properties": {
    "gn:admin1_code":"77",
    "gn:asciiname":"Mokreni",
    "gn:country_code":"RU",
    "gn:dem":161,
    "gn:feature_class":"P",
    "gn:feature_code":"PPL",
    "gn:name":"Mokreni",
    "gn:population":0,
    "gn:timezone":"Europe/Moscow",
    "iso:country":"RU",
    "name:rus_x_preferred":[
        "\u041c\u043e\u043a\u0440\u0435\u043d\u0438"
    ],
    "name:und_x_variant":[
        "\u041c\u043e\u043a\u0440\u0435\u043d\u0438"
    ],
    "wof:name":"Mokreni",
    "wof:placetype":"locality"
},
  "geometry": {"coordinates":[37.1438,58.0545],"type":"Point"}
}