{
  "type": "Feature",
  "properties": {
    "gn:admin1_code":"53",
    "gn:asciiname":"Nazarovo",
    "gn:country_code":"RU",
    "gn:dem":108,
    "gn:feature_class":"P",
    "gn:feature_code":"PPL",
    "gn:name":"Nazarovo",
    "gn:population":0,
    "gn:timezone":"Asia/Novosibirsk",
    "iso:country":"RU",
    "name:rus_x_preferred":[
        "\u041d\u0430\u0437\u0430\u0440\u043e\u0432\u043e"
    ],
    "name:und_x_variant":[
        "Nazarova",
        "Nazarovo",
        "\u041d\u0430\u0437\u0430\u0440\u043e\u0432\u043e"
    ],
    "wof:name":"Nazarovo",
    "wof:placetype":"locality"
},
  "geometry": {"coordinates":[77.55696,55.66667],"type":"Point"}
}