{
  "type": "Feature",
  "properties": {
    "gn:admin1_code":"8",
    "gn:asciiname":"Beloroyevka",
    "gn:country_code":"RU",
    "gn:dem":204,
    "gn:feature_class":"P",
    "gn:feature_code":"PPL",
    "gn:name":"Beloroyevka",
    "gn:population":0,
    "gn:timezone":"Asia/Yekaterinburg",
    "iso:country":"RU",
    "name:rus_x_preferred":[
        "\u0411\u0435\u043b\u043e\u0440\u043e\u0435\u0432\u043a\u0430"
    ],
    "wof:name":"Beloroyevka",
    "wof:placetype":"locality"
},
  "geometry": {"coordinates":[56.0451,53.8399],"type":"Point"}
}