{
  "type": "Feature",
  "properties": {
    "gn:admin1_code":"4",
    "gn:asciiname":"Alambay",
    "gn:country_code":"RU",
    "gn:dem":218,
    "gn:feature_class":"P",
    "gn:feature_code":"PPL",
    "gn:name":"Alambay",
    "gn:population":0,
    "gn:timezone":"Asia/Barnaul",
    "iso:country":"RU",
    "name:che_x_preferred":[
        "\u0410\u043b\u0430\u043c\u0431\u0430\u0439"
    ],
    "name:eng_x_preferred":[
        "Alambay"
    ],
    "name:nor_x_preferred":[
        "Alambaj"
    ],
    "name:rus_x_preferred":[
        "\u0410\u043b\u0430\u043c\u0431\u0430\u0439"
    ],
    "name:und_x_variant":[
        "Alambayskiy"
    ],
    "wof:name":"Alambay",
    "wof:placetype":"locality"
},
  "geometry": {"coordinates":[85.3647,54.0394],"type":"Point"}
}