{
  "type": "Feature",
  "properties": {
    "gn:admin1_code":"56",
    "gn:asciiname":"Zelenaya Dubrava",
    "gn:country_code":"RU",
    "gn:dem":219,
    "gn:feature_class":"P",
    "gn:feature_code":"PPL",
    "gn:name":"Zel\u00ebnaya Dubrava",
    "gn:population":0,
    "gn:timezone":"Europe/Moscow",
    "iso:country":"RU",
    "name:rus_x_preferred":[
        "\u0417\u0435\u043b\u0451\u043d\u0430\u044f \u0414\u0443\u0431\u0440\u0430\u0432\u0430"
    ],
    "name:und_x_variant":[
        "Zel\u00ebnaya Dubrava"
    ],
    "wof:name":"Zelenaya Dubrava",
    "wof:placetype":"locality"
},
  "geometry": {"coordinates":[35.3738,52.5727],"type":"Point"}
}