{
  "type": "Feature",
  "properties": {
    "gn:admin1_code":"77",
    "gn:asciiname":"Ignatikha",
    "gn:country_code":"RU",
    "gn:dem":205,
    "gn:feature_class":"P",
    "gn:feature_code":"PPL",
    "gn:name":"Ignatikha",
    "gn:population":0,
    "gn:timezone":"Europe/Moscow",
    "iso:country":"RU",
    "name:rus_x_preferred":[
        "\u0418\u0433\u043d\u0430\u0442\u0438\u0445\u0430"
    ],
    "wof:name":"Ignatikha",
    "wof:placetype":"locality"
},
  "geometry": {"coordinates":[34.53793,57.3661],"type":"Point"}
}