{
  "type": "Feature",
  "properties": {
    "gn:admin1_code":"69",
    "gn:asciiname":"Sobolevo",
    "gn:country_code":"RU",
    "gn:dem":193,
    "gn:feature_class":"P",
    "gn:feature_code":"PPL",
    "gn:name":"Sobolevo",
    "gn:population":0,
    "gn:timezone":"Europe/Moscow",
    "iso:country":"RU",
    "name:rus_x_preferred":[
        "\u0421\u043e\u0431\u043e\u043b\u0435\u0432\u043e"
    ],
    "name:und_x_variant":[
        "\u0421\u043e\u0431\u043e\u043b\u0435\u0432\u043e"
    ],
    "wof:name":"Sobolevo",
    "wof:placetype":"locality"
},
  "geometry": {"coordinates":[31.89768,54.43015],"type":"Point"}
}