{
  "type": "Feature",
  "properties": {
    "gn:admin1_code":"61",
    "gn:asciiname":"Kugeyskiy",
    "gn:country_code":"RU",
    "gn:dem":49,
    "gn:feature_class":"P",
    "gn:feature_code":"PPL",
    "gn:name":"Kugeyskiy",
    "gn:population":0,
    "gn:timezone":"Europe/Moscow",
    "iso:country":"RU",
    "name:rus_x_preferred":[
        "\u041a\u0443\u0433\u0435\u0439\u0441\u043a\u0438\u0439"
    ],
    "name:und_x_variant":[
        "Kugo-Yeya",
        "\u041a\u0443\u0433\u0435\u0439\u0441\u043a\u0438\u0439",
        "Kugoyeyskiy"
    ],
    "wof:name":"Kugeyskiy",
    "wof:placetype":"locality"
},
  "geometry": {"coordinates":[40.50391,46.46256],"type":"Point"}
}