{
  "type": "Feature",
  "properties": {
    "gn:admin1_code":"10",
    "gn:asciiname":"Zabolot'ye",
    "gn:country_code":"RU",
    "gn:dem":184,
    "gn:feature_class":"P",
    "gn:feature_code":"PPL",
    "gn:name":"Zabolot\u2019ye",
    "gn:population":0,
    "gn:timezone":"Europe/Moscow",
    "iso:country":"RU",
    "name:rus_x_preferred":[
        "\u0417\u0430\u0431\u043e\u043b\u043e\u0442\u044c\u0435"
    ],
    "name:rus_x_variant":[
        "Zabolot\u2019ye"
    ],
    "wof:name":"Zabolot'ye",
    "wof:placetype":"locality"
},
  "geometry": {"coordinates":[32.99403,52.63041],"type":"Point"}
}