{
  "type": "Feature",
  "properties": {
    "gn:admin1_code":"76.0",
    "gn:asciiname":"Budyrovka",
    "gn:country_code":"RU",
    "gn:dem":191,
    "gn:feature_class":"P",
    "gn:feature_code":"PPL",
    "gn:name":"Budyrovka",
    "gn:population":0,
    "gn:timezone":"Europe/Moscow",
    "iso:country":"RU",
    "name:rus_x_preferred":[
        "\u0411\u0443\u0434\u044b\u0440\u043e\u0432\u043a\u0430"
    ],
    "name:und_x_variant":[
        "\u0411\u0443\u0434\u044b\u0440\u043e\u0432\u043a\u0430"
    ],
    "wof:name":"Budyrovka",
    "wof:placetype":"locality"
},
  "geometry": {"coordinates":[38.52173,53.65042],"type":"Point"}
}