{
  "type": "Feature",
  "properties": {
    "gn:admin1_code":"24.0",
    "gn:asciiname":"Baga-Bukhus",
    "gn:country_code":"RU",
    "gn:dem":6,
    "gn:feature_class":"P",
    "gn:feature_code":"PPL",
    "gn:name":"Baga-Bukhus",
    "gn:population":0,
    "gn:timezone":"Europe/Moscow",
    "iso:country":"RU",
    "name:nor_x_preferred":[
        "Baga-Bukhus"
    ],
    "name:rus_x_preferred":[
        "\u0411\u0430\u0433\u0430-\u0411\u0443\u0445\u0443\u0441"
    ],
    "wof:name":"Baga-Bukhus",
    "wof:placetype":"locality"
},
  "geometry": {"coordinates":[44.99889,48.01639],"type":"Point"}
}