{
  "type": "Feature",
  "properties": {
    "gn:admin1_code":"56",
    "gn:asciiname":"Krivtsovo Vtoroye",
    "gn:country_code":"RU",
    "gn:dem":240,
    "gn:feature_class":"P",
    "gn:feature_code":"PPL",
    "gn:name":"Krivtsovo Vtoroye",
    "gn:population":0,
    "gn:timezone":"Europe/Moscow",
    "iso:country":"RU",
    "name:rus_x_preferred":[
        "\u041a\u0440\u0438\u0432\u0446\u043e\u0432\u043e \u0412\u0442\u043e\u0440\u043e\u0435"
    ],
    "name:und_x_variant":[
        "\u041a\u0440\u0438\u0432\u0446\u043e\u0432\u043e \u0412\u0442\u043e\u0440\u043e\u0435"
    ],
    "wof:name":"Krivtsovo Vtoroye",
    "wof:placetype":"locality"
},
  "geometry": {"coordinates":[36.4992,52.9701],"type":"Point"}
}