{
  "type": "Feature",
  "properties": {
    "gn:admin1_code":"69.0",
    "gn:asciiname":"Fefelovo",
    "gn:country_code":"RU",
    "gn:dem":200,
    "gn:feature_class":"P",
    "gn:feature_code":"PPL",
    "gn:name":"Fefelovo",
    "gn:population":0,
    "gn:timezone":"Europe/Moscow",
    "iso:country":"RU",
    "name:rus_x_preferred":[
        "\u0424\u0435\u0444\u0435\u043b\u043e\u0432o"
    ],
    "name:und_x_variant":[
        "Fefelova"
    ],
    "wof:name":"Fefelovo",
    "wof:placetype":"locality"
},
  "geometry": {"coordinates":[32.04848,55.06807],"type":"Point"}
}