{
  "type": "Feature",
  "properties": {
    "gn:admin1_code":"15",
    "gn:asciiname":"Kuyveyem",
    "gn:cc2":"RU",
    "gn:country_code":"RU",
    "gn:dem":16,
    "gn:feature_class":"P",
    "gn:feature_code":"PPL",
    "gn:name":"Kuyveyem",
    "gn:population":0,
    "gn:timezone":"Asia/Anadyr",
    "iso:country":"RU",
    "name:rus_x_preferred":[
        "\u041a\u0443\u0439\u0432\u0435\u0435\u043c"
    ],
    "name:und_x_variant":[
        "Kuyzeyen",
        "Kuyveyem",
        "\u041a\u0443\u0439\u0432\u0435\u0435\u043c"
    ],
    "wof:name":"Kuyveyem",
    "wof:placetype":"locality"
},
  "geometry": {"coordinates":[-175.48333,64.90000000000001],"type":"Point"}
}