{
  "type": "Feature",
  "properties": {
    "gn:admin1_code":"10",
    "gn:asciiname":"Kolodezki",
    "gn:country_code":"RU",
    "gn:dem":145,
    "gn:feature_class":"P",
    "gn:feature_code":"PPL",
    "gn:name":"Kolodezki",
    "gn:population":0,
    "gn:timezone":"Europe/Moscow",
    "iso:country":"RU",
    "name:rus_x_preferred":[
        "\u041a\u043e\u043b\u043e\u0434\u0435\u0437\u043a\u0438"
    ],
    "name:und_x_variant":[
        "\u041a\u043e\u043b\u043e\u0434\u0435\u0437\u043a\u0438",
        "Kolodezskiy"
    ],
    "wof:name":"Kolodezki",
    "wof:placetype":"locality"
},
  "geometry": {"coordinates":[33.12965,52.35978],"type":"Point"}
}