{
  "type": "Feature",
  "properties": {
    "gn:country":"RU",
    "gn:fcode":"PPL",
    "gn:population":861,
    "iso:country":"RU",
    "name:ara_x_preferred":[
        "\u0623\u064a\u0627\u062a"
    ],
    "name:ceb_x_preferred":[
        "Ayat'"
    ],
    "name:che_x_preferred":[
        "\u0410\u044f\u0442\u044c"
    ],
    "name:eng_x_preferred":[
        "Ayat'"
    ],
    "name:nld_x_preferred":[
        "Ajat"
    ],
    "name:rus_x_preferred":[
        "\u0410\u044f\u0442\u044c"
    ],
    "name:tat_x_preferred":[
        "\u0410\u044f\u0442\u044c"
    ],
    "name:ukr_x_preferred":[
        "\u0410\u044f\u0442\u044c"
    ],
    "name:und_x_variant":[
        "Ayat\u2019"
    ],
    "qs:name":"Ayat'",
    "qs:name_adm0":"Russia",
    "qs:name_adm1":"Sverdlovsk Oblast",
    "qs:photos_9r":0,
    "qs:photos_sr":0,
    "qs:placetype":"Town",
    "qs:pop_sr":"2",
    "wof:name":"Ayat'",
    "wof:placetype":"locality",
    "wof:population":861
},
  "geometry": {"coordinates":[60.2334,57.0336],"type":"Point"}
}