{
  "type": "Feature",
  "properties": {
    "gn:admin1_code":"28",
    "gn:asciiname":"Petrov Navolok",
    "gn:cc2":"RU",
    "gn:country_code":"RU",
    "gn:dem":125,
    "gn:feature_class":"P",
    "gn:feature_code":"PPL",
    "gn:name":"Petrov Navolok",
    "gn:population":0,
    "gn:timezone":"Europe/Moscow",
    "iso:country":"RU",
    "name:rus_x_preferred":[
        "\u041f\u0435\u0442\u0440\u043e\u0432 \u041d\u0430\u0432\u043e\u043b\u043e\u043a"
    ],
    "name:und_x_variant":[
        "Krasnaya Zvezda",
        "Petrov Navolok",
        "\u041f\u0435\u0442\u0440\u043e\u0432 \u041d\u0430\u0432\u043e\u043b\u043e\u043a"
    ],
    "wof:name":"Petrov Navolok",
    "wof:placetype":"locality"
},
  "geometry": {"coordinates":[33.18333,63.48333],"type":"Point"}
}