{
  "type": "Feature",
  "properties": {
    "gn:admin1_code":"65",
    "gn:asciiname":"Novoklyuchevskiy",
    "gn:country_code":"RU",
    "gn:dem":80,
    "gn:feature_class":"P",
    "gn:feature_code":"PPL",
    "gn:name":"Novoklyuchevskiy",
    "gn:population":0,
    "gn:timezone":"Europe/Samara",
    "iso:country":"RU",
    "name:rus_x_preferred":[
        "\u041d\u043e\u0432\u043e\u043a\u043b\u044e\u0447\u0435\u0432\u0441\u043a\u0438\u0439"
    ],
    "wof:name":"Novoklyuchevskiy",
    "wof:placetype":"locality"
},
  "geometry": {"coordinates":[51.4287,54.1456],"type":"Point"}
}