{
  "type": "Feature",
  "properties": {
    "gn:admin1_code":"53",
    "gn:asciiname":"Mauk",
    "gn:country_code":"RU",
    "gn:dem":113,
    "gn:feature_class":"P",
    "gn:feature_code":"PPL",
    "gn:name":"Mauk",
    "gn:population":0,
    "gn:timezone":"Asia/Novosibirsk",
    "iso:country":"RU",
    "name:eng_x_preferred":[
        "Mauk"
    ],
    "name:nor_x_preferred":[
        "Mauk"
    ],
    "name:rus_x_preferred":[
        "\u041c\u0430\u0443\u043a"
    ],
    "name:und_x_variant":[
        "\u041c\u0430\u0443\u043a",
        "Mauk"
    ],
    "wof:name":"Mauk",
    "wof:placetype":"locality"
},
  "geometry": {"coordinates":[78.7582,55.07964000000001],"type":"Point"}
}