{
  "type": "Feature",
  "properties": {
    "gn:admin1_code":"52",
    "gn:asciiname":"Novaya Mel'nitsa",
    "gn:country_code":"RU",
    "gn:dem":26,
    "gn:feature_class":"P",
    "gn:feature_code":"PPL",
    "gn:name":"Novaya Mel\u2019nitsa",
    "gn:population":0,
    "gn:timezone":"Europe/Moscow",
    "iso:country":"RU",
    "name:rus_x_preferred":[
        "\u041d\u043e\u0432\u0430\u044f \u041c\u0435\u043b\u044c\u043d\u0438\u0446\u0430"
    ],
    "name:und_x_variant":[
        "Novaya Mel\u2019nitsa",
        "\u041d\u043e\u0432\u0430\u044f \u041c\u0435\u043b\u044c\u043d\u0438\u0446\u0430"
    ],
    "wof:name":"Novaya Mel'nitsa",
    "wof:placetype":"locality"
},
  "geometry": {"coordinates":[31.20522,58.5217],"type":"Point"}
}