{
  "type": "Feature",
  "properties": {
    "gn:country":"RU",
    "gn:fcode":"PPL",
    "gn:population":1019,
    "iso:country":"RU",
    "name:eng_x_preferred":[
        "Krasnyy Bogatyr'"
    ],
    "name:nor_x_preferred":[
        "Krasnyj Bogatyr"
    ],
    "name:rus_x_preferred":[
        "\u041a\u0440\u0430\u0441\u043d\u044b\u0439 \u0411\u043e\u0433\u0430\u0442\u044b\u0440\u044c"
    ],
    "name:und_x_variant":[
        "Krasnyy Bogatyr\u2019"
    ],
    "qs:name":"Krasnyy Bogatyr'",
    "qs:name_adm0":"Russia",
    "qs:name_adm1":"Vladimir Oblast",
    "qs:photos_9r":0,
    "qs:photos_sr":0,
    "qs:placetype":"Town",
    "qs:pop_sr":"3",
    "wof:name":"Krasnyy Bogatyr'",
    "wof:placetype":"locality",
    "wof:population":1019
},
  "geometry": {"coordinates":[41.12958,56.01453],"type":"Point"}
}