{
  "type": "Feature",
  "properties": {
    "gn:admin1_code":"6",
    "gn:asciiname":"Ivakinskaya",
    "gn:country_code":"RU",
    "gn:dem":158,
    "gn:feature_class":"P",
    "gn:feature_code":"PPL",
    "gn:name":"Ivakinskaya",
    "gn:population":0,
    "gn:timezone":"Europe/Moscow",
    "iso:country":"RU",
    "name:eng_x_preferred":[
        "Ivakinskaya"
    ],
    "name:nor_x_preferred":[
        "Ivakinskaja"
    ],
    "name:rus_x_preferred":[
        "\u0418\u0432\u0430\u043a\u0438\u043d\u0441\u043a\u0430\u044f"
    ],
    "wof:name":"Ivakinskaya",
    "wof:placetype":"locality"
},
  "geometry": {"coordinates":[40.5141,61.0616],"type":"Point"}
}