{
  "type": "Feature",
  "properties": {
    "gn:admin1_code":"44",
    "gn:asciiname":"Myakit",
    "gn:country_code":"RU",
    "gn:dem":716,
    "gn:feature_class":"P",
    "gn:feature_code":"PPL",
    "gn:name":"Myakit",
    "gn:population":0,
    "gn:timezone":"Asia/Magadan",
    "iso:country":"RU",
    "name:eng_x_preferred":[
        "Myakit"
    ],
    "name:nor_x_preferred":[
        "Mjakit"
    ],
    "name:rus_x_preferred":[
        "\u041c\u044f\u043a\u0438\u0442"
    ],
    "wof:name":"Myakit",
    "wof:placetype":"locality"
},
  "geometry": {"coordinates":[152.08951000000005,61.40951999999999],"type":"Point"}
}