{
  "type": "Feature",
  "properties": {
    "gn:admin1_code":"77",
    "gn:asciiname":"Polokhovo",
    "gn:country_code":"RU",
    "gn:dem":181,
    "gn:feature_class":"P",
    "gn:feature_code":"PPL",
    "gn:name":"Polokhovo",
    "gn:population":0,
    "gn:timezone":"Europe/Moscow",
    "iso:country":"RU",
    "name:rus_x_preferred":[
        "\u041f\u043e\u043b\u043e\u0445\u043e\u0432\u043e"
    ],
    "wof:name":"Polokhovo",
    "wof:placetype":"locality"
},
  "geometry": {"coordinates":[34.31555,57.79038000000001],"type":"Point"}
}