{
  "type": "Feature",
  "properties": {
    "gn:admin1_code":"76",
    "gn:asciiname":"Oktyabr'",
    "gn:country_code":"RU",
    "gn:dem":248,
    "gn:feature_class":"P",
    "gn:feature_code":"PPL",
    "gn:name":"Oktyabr\u2019",
    "gn:population":0,
    "gn:timezone":"Europe/Moscow",
    "iso:country":"RU",
    "wof:name":"Oktyabr'",
    "wof:placetype":"locality"
},
  "geometry": {"coordinates":[37.27131,53.27511],"type":"Point"}
}