{
  "type": "Feature",
  "properties": {
    "gn:admin1_code":"25",
    "gn:asciiname":"Protasovo",
    "gn:country_code":"RU",
    "gn:dem":197,
    "gn:feature_class":"P",
    "gn:feature_code":"PPL",
    "gn:name":"Protasovo",
    "gn:population":0,
    "gn:timezone":"Europe/Moscow",
    "iso:country":"RU",
    "name:che_x_preferred":[
        "\u041f\u0440\u043e\u0442\u0430\u0441\u043e\u0432\u043e"
    ],
    "name:rus_x_preferred":[
        "\u041f\u0440\u043e\u0442\u0430\u0441\u043e\u0432\u043e"
    ],
    "wof:name":"Protasovo",
    "wof:placetype":"locality"
},
  "geometry": {"coordinates":[35.38009,54.15744],"type":"Point"}
}