{
  "type": "Feature",
  "properties": {
    "gn:admin1_code":"62.0",
    "gn:asciiname":"Borshchevka",
    "gn:country_code":"RU",
    "gn:dem":119,
    "gn:feature_class":"P",
    "gn:feature_code":"PPL",
    "gn:name":"Borshch\u00ebvka",
    "gn:population":0,
    "gn:timezone":"Europe/Moscow",
    "iso:country":"RU",
    "name:rus_x_preferred":[
        "\u0411\u043e\u0440\u0449\u0451\u0432\u043a\u0430"
    ],
    "name:und_x_variant":[
        "Borshch\u00ebvka",
        "\u0411\u043e\u0440\u0449\u0451\u0432\u043a\u0430"
    ],
    "wof:name":"Borshchevka",
    "wof:placetype":"locality"
},
  "geometry": {"coordinates":[39.70119,53.59202],"type":"Point"}
}