{
  "type": "Feature",
  "properties": {
    "gn:admin1_code":"25.0",
    "gn:asciiname":"Filippovka",
    "gn:country_code":"RU",
    "gn:dem":215,
    "gn:feature_class":"P",
    "gn:feature_code":"PPL",
    "gn:name":"Filippovka",
    "gn:population":0,
    "gn:timezone":"Europe/Moscow",
    "iso:country":"RU",
    "name:bak_x_preferred":[
        "\u0424\u0438\u043b\u0438\u043f\u043f\u043e\u0432\u043a\u0430"
    ],
    "name:che_x_preferred":[
        "\u0424\u0438\u043b\u0438\u043f\u043f\u043e\u0432\u043a\u0430"
    ],
    "name:hye_x_preferred":[
        "\u0556\u056b\u056c\u056b\u057a\u0578\u057e\u056f\u0561"
    ],
    "name:kaz_x_preferred":[
        "\u0424\u0438\u043b\u0438\u043f\u043f\u043e\u0432\u043a\u0430"
    ],
    "name:kir_x_preferred":[
        "\u0424\u0438\u043b\u0438\u043f\u043f\u043e\u0432\u043a\u0430"
    ],
    "name:myv_x_preferred":[
        "\u0424\u0438\u043b\u0438\u043f\u043f\u043e\u0432\u043a\u0430"
    ],
    "name:nor_x_preferred":[
        "Filippovka"
    ],
    "name:pol_x_preferred":[
        "Filippowka"
    ],
    "name:rus_x_preferred":[
        "\u0424\u0438\u043b\u0438\u043f\u043f\u043e\u0432\u043a\u0430"
    ],
    "name:tat_x_preferred":[
        "\u0424\u0438\u043b\u0438\u043f\u043f\u043e\u0432\u043a\u0430"
    ],
    "name:ukr_x_preferred":[
        "\u0424\u0456\u043b\u0456\u043f\u043f\u043e\u0432\u043a\u0430"
    ],
    "name:und_x_variant":[
        "Filipovka",
        "Filippovka"
    ],
    "wof:name":"Filippovka",
    "wof:placetype":"locality"
},
  "geometry": {"coordinates":[36.76414000000001,54.89799],"type":"Point"}
}