{
  "type": "Feature",
  "properties": {
    "gn:admin1_code":"91",
    "gn:asciiname":"Kozino",
    "gn:country_code":"RU",
    "gn:dem":376,
    "gn:feature_class":"P",
    "gn:feature_code":"PPL",
    "gn:name":"Kozino",
    "gn:population":0,
    "gn:timezone":"Asia/Krasnoyarsk",
    "iso:country":"RU",
    "name:eng_x_preferred":[
        "Kozino"
    ],
    "name:nor_x_preferred":[
        "Kozino"
    ],
    "name:rus_x_preferred":[
        "\u041a\u043e\u0437\u0438\u043d\u043e"
    ],
    "name:und_x_variant":[
        "Kozina",
        "Kozino"
    ],
    "wof:name":"Kozino",
    "wof:placetype":"locality"
},
  "geometry": {"coordinates":[92.67055999999999,54.43944000000001],"type":"Point"}
}