{
  "type": "Feature",
  "properties": {
    "gn:admin1_code":"80",
    "gn:asciiname":"Tylovay Russkiy",
    "gn:country_code":"RU",
    "gn:dem":226,
    "gn:feature_class":"P",
    "gn:feature_code":"PPL",
    "gn:name":"Tylovay Russkiy",
    "gn:population":0,
    "gn:timezone":"Europe/Samara",
    "iso:country":"RU",
    "wof:name":"Tylovay Russkiy",
    "wof:placetype":"locality"
},
  "geometry": {"coordinates":[52.71821,57.12381],"type":"Point"}
}