{
  "type": "Feature",
  "properties": {
    "gn:admin1_code":"28",
    "gn:asciiname":"Pechkinvaraka",
    "gn:country_code":"RU",
    "gn:dem":146,
    "gn:feature_class":"P",
    "gn:feature_code":"PPL",
    "gn:name":"Pechkinvaraka",
    "gn:population":0,
    "gn:timezone":"Europe/Moscow",
    "iso:country":"RU",
    "name:fin_x_preferred":[
        "Petskavaara"
    ],
    "name:rus_x_preferred":[
        "\u041f\u0435\u0447\u043a\u0438\u043d\u0432\u0430\u0440\u0430\u043a\u0430"
    ],
    "wof:name":"Pechkinvaraka",
    "wof:placetype":"locality"
},
  "geometry": {"coordinates":[33.42985,64.56179],"type":"Point"}
}