{
  "type": "Feature",
  "properties": {
    "gn:country":"RU",
    "gn:fcode":"PPL",
    "gn:pop":0,
    "iso:country":"RU",
    "name:bel_x_preferred":[
        "\u041a\u0430\u043b\u044c\u0446\u043e\u0432\u0430"
    ],
    "name:deu_x_preferred":[
        "Kolzowo"
    ],
    "name:nld_x_preferred":[
        "Koltsovo"
    ],
    "name:rus_x_preferred":[
        "\u041a\u043e\u043b\u044c\u0446\u043e\u0432\u043e"
    ],
    "name:ukr_x_preferred":[
        "\u041a\u043e\u043b\u044c\u0446\u043e\u0432\u043e"
    ],
    "name:unk_x_variant":[
        "\u041a\u043e\u043b\u044c\u0446\u043e\u0432\u043e"
    ],
    "qs:name":"Kol'tsovo",
    "qs:name_adm0":"Russia",
    "qs:name_adm1":"Kaluga Oblast",
    "qs:photos_9r":0,
    "qs:photos_sr":0,
    "qs:placetype":"Town",
    "qs:pop_sr":"0",
    "wd:wordcount":42,
    "wof:name":"Kol'tsovo",
    "wof:placetype":"locality",
    "wof:population":0
},
  "geometry": {"coordinates":[35.59413,54.75917],"type":"Point"}
}