{
  "type": "Feature",
  "properties": {
    "gn:admin1_code":"60",
    "gn:asciiname":"Karelovo",
    "gn:country_code":"RU",
    "gn:dem":116,
    "gn:feature_class":"P",
    "gn:feature_code":"PPL",
    "gn:name":"Karelovo",
    "gn:population":0,
    "gn:timezone":"Europe/Moscow",
    "iso:country":"RU",
    "name:rus_x_preferred":[
        "\u041a\u0430\u0440\u0435\u043b\u043e\u0432\u043e"
    ],
    "wof:name":"Karelovo",
    "wof:placetype":"locality"
},
  "geometry": {"coordinates":[30.16149,56.78756],"type":"Point"}
}