{
  "type": "Feature",
  "properties": {
    "gn:admin1_code":"85.0",
    "gn:asciiname":"Bol'shaya Mushnya",
    "gn:country_code":"RU",
    "gn:dem":143,
    "gn:feature_class":"P",
    "gn:feature_code":"PPL",
    "gn:name":"Bol\u2019shaya Mushnya",
    "gn:population":0,
    "gn:timezone":"Europe/Moscow",
    "iso:country":"RU",
    "name:rus_x_preferred":[
        "\u0411\u043e\u043b\u044c\u0448\u0430\u044f \u041c\u0443\u0448\u043d\u044f"
    ],
    "name:und_x_variant":[
        "Bol\u2019shaya Mushnya"
    ],
    "wof:name":"Bol'shaya Mushnya",
    "wof:placetype":"locality"
},
  "geometry": {"coordinates":[38.37291,59.38773000000001],"type":"Point"}
}