{
  "type": "Feature",
  "properties": {
    "gn:admin1_code":"84",
    "gn:asciiname":"Tarakanov",
    "gn:country_code":"RU",
    "gn:dem":28,
    "gn:feature_class":"P",
    "gn:feature_code":"PPL",
    "gn:name":"Tarakanov",
    "gn:population":0,
    "gn:timezone":"Europe/Volgograd",
    "iso:country":"RU",
    "wof:name":"Tarakanov",
    "wof:placetype":"locality"
},
  "geometry": {"coordinates":[46.66667,49.83333],"type":"Point"}
}