{
  "type": "Feature",
  "properties": {
    "gn:admin1_code":"62",
    "gn:asciiname":"Yerneyevo",
    "gn:country_code":"RU",
    "gn:dem":97,
    "gn:feature_class":"P",
    "gn:feature_code":"PPL",
    "gn:name":"Yerneyevo",
    "gn:population":0,
    "gn:timezone":"Europe/Moscow",
    "iso:country":"RU",
    "name:rus_x_preferred":[
        "\u0415\u0440\u043d\u0435\u0435\u0432\u043e"
    ],
    "wof:name":"Yerneyevo",
    "wof:placetype":"locality"
},
  "geometry": {"coordinates":[42.0568,54.1571],"type":"Point"}
}