{
  "type": "Feature",
  "properties": {
    "gn:admin1_code":"76",
    "gn:asciiname":"Kolomenka",
    "gn:country_code":"RU",
    "gn:dem":221,
    "gn:feature_class":"P",
    "gn:feature_code":"PPL",
    "gn:name":"Kolomenka",
    "gn:population":0,
    "gn:timezone":"Europe/Moscow",
    "iso:country":"RU",
    "name:rus_x_preferred":[
        "\u041a\u043e\u043b\u043e\u043c\u0435\u043d\u043a\u0430"
    ],
    "name:und_x_variant":[
        "\u041a\u043e\u043b\u043e\u043c\u0435\u043d\u043a\u0430"
    ],
    "wof:name":"Kolomenka",
    "wof:placetype":"locality"
},
  "geometry": {"coordinates":[37.2951,53.37404],"type":"Point"}
}