{
  "type": "Feature",
  "properties": {
    "gn:admin1_code":"16",
    "gn:asciiname":"Pochenary",
    "gn:country_code":"RU",
    "gn:dem":112,
    "gn:feature_class":"P",
    "gn:feature_code":"PPL",
    "gn:name":"Pochenary",
    "gn:population":0,
    "gn:timezone":"Europe/Moscow",
    "iso:country":"RU",
    "name:und_x_variant":[
        "\u041f\u043e\u0447\u0435\u043d\u0430\u0440\u044b"
    ],
    "wof:name":"Pochenary",
    "wof:placetype":"locality"
},
  "geometry": {"coordinates":[46.33306,55.89722],"type":"Point"}
}