{
  "type": "Feature",
  "properties": {
    "gn:admin1_code":"76",
    "gn:asciiname":"Supruty",
    "gn:country_code":"RU",
    "gn:dem":146,
    "gn:feature_class":"P",
    "gn:feature_code":"PPL",
    "gn:name":"Supruty",
    "gn:population":0,
    "gn:timezone":"Europe/Moscow",
    "iso:country":"RU",
    "name:eng_x_preferred":[
        "Supruty"
    ],
    "name:nor_x_preferred":[
        "Supruty"
    ],
    "name:rus_x_preferred":[
        "\u0421\u0443\u043f\u0440\u0443\u0442\u044b"
    ],
    "name:und_x_variant":[
        "Suprut",
        "\u0421\u0443\u043f\u0440\u0443\u0442\u044b",
        "Supruty"
    ],
    "wof:name":"Supruty",
    "wof:placetype":"locality"
},
  "geometry": {"coordinates":[37.18843,54.00476],"type":"Point"}
}