{
  "type": "Feature",
  "properties": {
    "gn:admin1_code":"42",
    "gn:asciiname":"Krakol'ye",
    "gn:country_code":"RU",
    "gn:dem":7,
    "gn:feature_class":"P",
    "gn:feature_code":"PPL",
    "gn:name":"Krakol\u2019ye",
    "gn:population":0,
    "gn:timezone":"Europe/Moscow",
    "iso:country":"RU",
    "name:ces_x_preferred":[
        "Krakolje"
    ],
    "name:eng_x_preferred":[
        "Krakol'ye"
    ],
    "name:est_x_preferred":[
        "Krakolje"
    ],
    "name:fin_x_preferred":[
        "Joenper\u00e4"
    ],
    "name:koi_x_preferred":[
        "\u0419\u044b\u0433\u044b\u043f\u0435\u0440\u044f"
    ],
    "name:kom_x_preferred":[
        "\u0419\u044b\u0433\u044b\u043f\u0435\u0440\u044f"
    ],
    "name:nor_x_preferred":[
        "Krakolje"
    ],
    "name:rus_x_preferred":[
        "\u041a\u0440\u0430\u043a\u043e\u043b\u044c\u0435"
    ],
    "name:und_x_variant":[
        "Krakol\u2019ye"
    ],
    "wof:name":"Krakol'ye",
    "wof:placetype":"locality"
},
  "geometry": {"coordinates":[28.28658,59.64346999999999],"type":"Point"}
}