{
  "type": "Feature",
  "properties": {
    "gn:admin1_code":"6.0",
    "gn:asciiname":"Tropinskaya",
    "gn:country_code":"RU",
    "gn:dem":49,
    "gn:feature_class":"P",
    "gn:feature_code":"PPL",
    "gn:name":"Tropinskaya",
    "gn:population":0,
    "gn:timezone":"Europe/Moscow",
    "iso:country":"RU",
    "name:rus_x_preferred":[
        "\u0422\u0440\u043e\u043f\u0438\u043d\u0441\u043a\u0430\u044f"
    ],
    "wof:name":"Tropinskaya",
    "wof:placetype":"locality"
},
  "geometry": {"coordinates":[45.2149,62.0174],"type":"Point"}
}