{
  "type": "Feature",
  "properties": {
    "gn:admin1_code":"54",
    "gn:asciiname":"Dachnyy",
    "gn:country_code":"RU",
    "gn:dem":119,
    "gn:feature_class":"P",
    "gn:feature_code":"PPL",
    "gn:name":"Dachnyy",
    "gn:population":0,
    "gn:timezone":"Asia/Omsk",
    "iso:country":"RU",
    "name:rus_x_preferred":[
        "\u0414\u0430\u0447\u043d\u044b\u0439"
    ],
    "name:und_x_variant":[
        "\u0414\u0430\u0447\u043d\u044b\u0439"
    ],
    "wof:name":"Dachnyy",
    "wof:placetype":"locality"
},
  "geometry": {"coordinates":[73.34569999999999,55.2525],"type":"Point"}
}