{
  "type": "Feature",
  "properties": {
    "gn:admin1_code":"70",
    "gn:asciiname":"Russkiy Khutor",
    "gn:country_code":"RU",
    "gn:dem":16,
    "gn:feature_class":"P",
    "gn:feature_code":"PPL",
    "gn:name":"Russkiy Khutor",
    "gn:population":0,
    "gn:timezone":"Europe/Moscow",
    "iso:country":"RU",
    "name:rus_x_preferred":[
        "\u0420\u0443\u0441\u0441\u043a\u0438\u0439 \u0425\u0443\u0442\u043e\u0440"
    ],
    "name:und_x_variant":[
        "\u0420\u0443\u0441\u0441\u043a\u0438\u0439 \u0425\u0443\u0442\u043e\u0440"
    ],
    "wof:name":"Russkiy Khutor",
    "wof:placetype":"locality"
},
  "geometry": {"coordinates":[45.56516,44.78806],"type":"Point"}
}