{
  "type": "Feature",
  "properties": {
    "gn:admin1_code":"62",
    "gn:asciiname":"Shushpanovo",
    "gn:country_code":"RU",
    "gn:dem":124,
    "gn:feature_class":"P",
    "gn:feature_code":"PPL",
    "gn:name":"Shushpanovo",
    "gn:population":0,
    "gn:timezone":"Europe/Moscow",
    "iso:country":"RU",
    "name:nor_x_preferred":[
        "Sjusjpanovo"
    ],
    "name:rus_x_preferred":[
        "\u0428\u0443\u0448\u043f\u0430\u043d\u043e\u0432\u043e"
    ],
    "name:und_x_variant":[
        "Shushpanovo"
    ],
    "wof:name":"Shushpanovo",
    "wof:placetype":"locality"
},
  "geometry": {"coordinates":[39.50713,54.84021],"type":"Point"}
}