{
  "type": "Feature",
  "properties": {
    "gn:admin1_code":"90",
    "gn:asciiname":"Frolovo",
    "gn:country_code":"RU",
    "gn:dem":218,
    "gn:feature_class":"P",
    "gn:feature_code":"PPL",
    "gn:name":"Frolovo",
    "gn:population":0,
    "gn:timezone":"Asia/Yekaterinburg",
    "iso:country":"RU",
    "name:rus_x_preferred":[
        "\u0424\u0440\u043e\u043b\u043e\u0432\u043e"
    ],
    "name:und_x_variant":[
        "\u0424\u0440\u043e\u043b\u043e\u0432\u043e"
    ],
    "wof:name":"Frolovo",
    "wof:placetype":"locality"
},
  "geometry": {"coordinates":[56.9009,57.8544],"type":"Point"}
}