{
  "type": "Feature",
  "properties": {
    "gn:admin1_code":"77",
    "gn:asciiname":"Ketkovo",
    "gn:country_code":"RU",
    "gn:dem":147,
    "gn:feature_class":"P",
    "gn:feature_code":"PPL",
    "gn:name":"Ketkovo",
    "gn:population":0,
    "gn:timezone":"Europe/Moscow",
    "iso:country":"RU",
    "name:rus_x_preferred":[
        "\u041a\u0435\u0442\u043a\u043e\u0432\u043e"
    ],
    "wof:name":"Ketkovo",
    "wof:placetype":"locality"
},
  "geometry": {"coordinates":[38.1839,57.3084],"type":"Point"}
}