{
  "type": "Feature",
  "properties": {
    "gn:admin1_code":"25.0",
    "gn:asciiname":"Lipiliny Dvory",
    "gn:country_code":"RU",
    "gn:dem":210,
    "gn:feature_class":"P",
    "gn:feature_code":"PPL",
    "gn:name":"Lipiliny Dvory",
    "gn:population":0,
    "gn:timezone":"Europe/Moscow",
    "iso:country":"RU",
    "name:rus_x_preferred":[
        "\u041b\u0438\u043f\u0438\u043b\u0438\u043d\u044b \u0414\u0432\u043e\u0440\u044b"
    ],
    "name:und_x_variant":[
        "\u041b\u0438\u043f\u0438\u043b\u0438\u043d\u044b \u0414\u0432\u043e\u0440\u044b"
    ],
    "wof:name":"Lipiliny Dvory",
    "wof:placetype":"locality"
},
  "geometry": {"coordinates":[35.84804000000001,54.51455],"type":"Point"}
}