{
  "type": "Feature",
  "properties": {
    "gn:admin1_code":"40",
    "gn:asciiname":"Dryannovo",
    "gn:country_code":"RU",
    "gn:dem":139,
    "gn:feature_class":"P",
    "gn:feature_code":"PPL",
    "gn:name":"Dryannovo",
    "gn:population":0,
    "gn:timezone":"Asia/Yekaterinburg",
    "iso:country":"RU",
    "name:eng_x_preferred":[
        "Dryannovo"
    ],
    "name:nor_x_preferred":[
        "Drjannovo"
    ],
    "name:rus_x_preferred":[
        "\u0414\u0440\u044f\u043d\u043d\u043e\u0432\u043e"
    ],
    "name:und_x_variant":[
        "Dryankovskoye",
        "Dryankovo"
    ],
    "wof:name":"Dryannovo",
    "wof:placetype":"locality"
},
  "geometry": {"coordinates":[63.4359,56.2707],"type":"Point"}
}