{
  "type": "Feature",
  "properties": {
    "gn:admin1_code":"88.0",
    "gn:asciiname":"D'yakonovo",
    "gn:country_code":"RU",
    "gn:dem":113,
    "gn:feature_class":"P",
    "gn:feature_code":"PPL",
    "gn:name":"D\u2019yakonovo",
    "gn:population":0,
    "gn:timezone":"Europe/Moscow",
    "iso:country":"RU",
    "name:rus_x_preferred":[
        "\u0414\u044c\u044f\u043a\u043e\u043d\u043e\u0432\u043e"
    ],
    "name:und_x_variant":[
        "D\u2019yakonovo"
    ],
    "wof:name":"D'yakonovo",
    "wof:placetype":"locality"
},
  "geometry": {"coordinates":[39.08333,58.48333],"type":"Point"}
}