{
  "type": "Feature",
  "properties": {
    "gn:admin1_code":"53",
    "gn:asciiname":"Shchukino",
    "gn:country_code":"RU",
    "gn:dem":107,
    "gn:feature_class":"P",
    "gn:feature_code":"PPL",
    "gn:name":"Shchukino",
    "gn:population":0,
    "gn:timezone":"Asia/Novosibirsk",
    "iso:country":"RU",
    "name:eng_x_preferred":[
        "Shchukino"
    ],
    "name:nor_x_preferred":[
        "Sjtsjukino"
    ],
    "name:rus_x_preferred":[
        "\u0429\u0443\u043a\u0438\u043d\u043e"
    ],
    "name:und_x_variant":[
        "Shchukinskiy",
        "\u0429\u0443\u043a\u0438\u043d\u043e",
        "Shchukino"
    ],
    "wof:name":"Shchukino",
    "wof:placetype":"locality"
},
  "geometry": {"coordinates":[83.3877,55.6718],"type":"Point"}
}