{
  "type": "Feature",
  "properties": {
    "gn:admin1_code":"93",
    "gn:asciiname":"Kirocha",
    "gn:country_code":"RU",
    "gn:dem":532,
    "gn:feature_class":"P",
    "gn:feature_code":"PPL",
    "gn:name":"Kirocha",
    "gn:population":0,
    "gn:timezone":"Asia/Chita",
    "iso:country":"RU",
    "name:eng_x_preferred":[
        "Kirocha"
    ],
    "name:nor_x_preferred":[
        "Kirotsja"
    ],
    "name:rus_x_preferred":[
        "\u041a\u0438\u0440\u043e\u0447\u0430"
    ],
    "name:und_x_variant":[
        "Kiroch\u2019",
        "Kirochi"
    ],
    "wof:name":"Kirocha",
    "wof:placetype":"locality"
},
  "geometry": {"coordinates":[115.83832,51.59917],"type":"Point"}
}