{
  "type": "Feature",
  "properties": {
    "gn:admin1_code":"19.0",
    "gn:asciiname":"Mazanty",
    "gn:country_code":"RU",
    "gn:dem":1358,
    "gn:feature_class":"P",
    "gn:feature_code":"PPL",
    "gn:name":"Mazanty",
    "gn:population":0,
    "gn:timezone":"Europe/Moscow",
    "iso:country":"RU",
    "wof:name":"Mazanty",
    "wof:placetype":"locality"
},
  "geometry": {"coordinates":[45.10917,42.92389],"type":"Point"}
}