{
  "type": "Feature",
  "properties": {
    "gn:admin1_code":"38.0",
    "gn:asciiname":"Glivenko",
    "gn:country_code":"RU",
    "gn:dem":73,
    "gn:feature_class":"P",
    "gn:feature_code":"PPL",
    "gn:name":"Glivenko",
    "gn:population":0,
    "gn:timezone":"Europe/Moscow",
    "iso:country":"RU",
    "name:rus_x_preferred":[
        "\u0413\u043b\u0438\u0432\u0435\u043d\u043a\u043e"
    ],
    "wof:name":"Glivenko",
    "wof:placetype":"locality"
},
  "geometry": {"coordinates":[39.63943,44.90473],"type":"Point"}
}