{
  "type": "Feature",
  "properties": {
    "gn:country":"RU",
    "gn:fcode":"PPL",
    "gn:pop":0,
    "iso:country":"RU",
    "name:eng_x_preferred":[
        "Kryukovo"
    ],
    "name:nor_x_preferred":[
        "Krjukovo"
    ],
    "name:rus_x_preferred":[
        "\u041a\u0440\u044e\u043a\u043e\u0432\u043e"
    ],
    "name:sco_x_preferred":[
        "Kryukovo"
    ],
    "name:ukr_x_preferred":[
        "\u041a\u0440\u044e\u043a\u043e\u0432\u0435"
    ],
    "name:unk_x_variant":[
        "\u041a\u0440\u044e\u043a\u043e\u0432\u043e"
    ],
    "qs:name":"Kryukovo",
    "qs:name_adm0":"Russia",
    "qs:name_adm1":"Moscow Oblast",
    "qs:photos_9k":1,
    "qs:photos_9r":1,
    "qs:photos_all":6,
    "qs:photos_sr":0,
    "qs:placetype":"Town",
    "qs:pop_sr":"0",
    "wd:wordcount":48,
    "wof:name":"Kryukovo",
    "wof:placetype":"locality",
    "wof:population":0
},
  "geometry": {"coordinates":[37.54701,55.09918],"type":"Point"}
}