{
  "type": "Feature",
  "properties": {
    "gn:admin1_code":"8",
    "gn:asciiname":"Nazarkino",
    "gn:country_code":"RU",
    "gn:dem":193,
    "gn:feature_class":"P",
    "gn:feature_code":"PPL",
    "gn:name":"Nazarkino",
    "gn:population":0,
    "gn:timezone":"Asia/Yekaterinburg",
    "iso:country":"RU",
    "name:eng_x_preferred":[
        "Nazarkino"
    ],
    "name:nor_x_preferred":[
        "Nazarkino"
    ],
    "name:rus_x_preferred":[
        "\u041d\u0430\u0437\u0430\u0440\u043a\u0438\u043d\u043e"
    ],
    "name:und_x_variant":[
        "Nazarovskiy"
    ],
    "wof:name":"Nazarkino",
    "wof:placetype":"locality"
},
  "geometry": {"coordinates":[56.48711,52.2969],"type":"Point"}
}