{
  "type": "Feature",
  "properties": {
    "gn:admin1_code":"93",
    "gn:asciiname":"Pamyat'-Lenina",
    "gn:country_code":"RU",
    "gn:dem":692,
    "gn:feature_class":"P",
    "gn:feature_code":"PPL",
    "gn:name":"Pamyat\u2019-Lenina",
    "gn:population":0,
    "gn:timezone":"Asia/Chita",
    "iso:country":"RU",
    "name:rus_x_preferred":[
        "\u041f\u0430\u043c\u044f\u0442\u044c-\u041b\u0435\u043d\u0438\u043d\u0430"
    ],
    "name:und_x_variant":[
        "Pamyati Lenina",
        "Pamyat\u2019-Lenina",
        "\u041f\u0430\u043c\u044f\u0442\u044c-\u041b\u0435\u043d\u0438\u043d\u0430"
    ],
    "wof:name":"Pamyat'-Lenina",
    "wof:placetype":"locality"
},
  "geometry": {"coordinates":[113.41667,52.16667],"type":"Point"}
}