{
  "type": "Feature",
  "properties": {
    "gn:admin1_code":"84",
    "gn:asciiname":"Lysov",
    "gn:country_code":"RU",
    "gn:dem":45,
    "gn:feature_class":"P",
    "gn:feature_code":"PPL",
    "gn:name":"Lysov",
    "gn:population":0,
    "gn:timezone":"Europe/Volgograd",
    "iso:country":"RU",
    "name:eng_x_preferred":[
        "Lysov"
    ],
    "name:nor_x_preferred":[
        "Lysov"
    ],
    "name:rus_x_preferred":[
        "\u041b\u044b\u0441\u043e\u0432"
    ],
    "wof:name":"Lysov",
    "wof:placetype":"locality"
},
  "geometry": {"coordinates":[43.17076,48.65168],"type":"Point"}
}