{
  "type": "Feature",
  "properties": {
    "gn:admin1_code":"85",
    "gn:asciiname":"Konevo",
    "gn:country_code":"RU",
    "gn:dem":142,
    "gn:feature_class":"P",
    "gn:feature_code":"PPL",
    "gn:name":"Kon\u00ebvo",
    "gn:population":0,
    "gn:timezone":"Europe/Moscow",
    "iso:country":"RU",
    "name:bul_x_preferred":[
        "\u041a\u043e\u043d\u0435\u0432\u043e"
    ],
    "name:ceb_x_preferred":[
        "Konevo"
    ],
    "name:deu_x_preferred":[
        "Konewo"
    ],
    "name:eng_x_preferred":[
        "Kon\u00ebvo"
    ],
    "name:fra_x_preferred":[
        "Konevo"
    ],
    "name:nor_x_preferred":[
        "Konevo"
    ],
    "name:pol_x_preferred":[
        "Koniewo"
    ],
    "name:ron_x_preferred":[
        "Konevo"
    ],
    "name:rus_x_preferred":[
        "\u041a\u043e\u043d\u0435\u0432\u043e"
    ],
    "name:rus_x_variant":[
        "\u041a\u043e\u043d\u0451\u0432\u043e"
    ],
    "name:swe_x_preferred":[
        "Konevo"
    ],
    "name:ukr_x_preferred":[
        "\u041a\u043e\u043d\u0435\u0432\u043e"
    ],
    "name:und_x_variant":[
        "Shubach",
        "Kon\u00ebvo",
        "\u041a\u043e\u043d\u0451\u0432\u043e"
    ],
    "wof:name":"Konevo",
    "wof:placetype":"locality"
},
  "geometry": {"coordinates":[38.2233,60.3659],"type":"Point"}
}