{
  "type": "Feature",
  "properties": {
    "gn:admin1_code":"80",
    "gn:asciiname":"Molchany",
    "gn:country_code":"RU",
    "gn:dem":132,
    "gn:feature_class":"P",
    "gn:feature_code":"PPL",
    "gn:name":"Molchany",
    "gn:population":0,
    "gn:timezone":"Europe/Samara",
    "iso:country":"RU",
    "name:eng_x_preferred":[
        "Molchany"
    ],
    "name:nor_x_preferred":[
        "Moltsjany"
    ],
    "name:rus_x_preferred":[
        "\u041c\u043e\u043b\u0447\u0430\u043d\u044b"
    ],
    "name:und_x_variant":[
        "\u041c\u043e\u043b\u0447\u0430\u043d\u044b",
        "Molchany"
    ],
    "wof:name":"Molchany",
    "wof:placetype":"locality"
},
  "geometry": {"coordinates":[53.64014,56.87522],"type":"Point"}
}