{
  "type": "Feature",
  "properties": {
    "gn:admin1_code":"60",
    "gn:asciiname":"Sharanski",
    "gn:country_code":"RU",
    "gn:dem":53,
    "gn:feature_class":"P",
    "gn:feature_code":"PPL",
    "gn:name":"Sharanski",
    "gn:population":0,
    "gn:timezone":"Europe/Moscow",
    "iso:country":"RU",
    "name:che_x_preferred":[
        "\u0428\u0430\u0440\u0430\u043d\u0441\u043a\u0438"
    ],
    "name:rus_x_preferred":[
        "\u0428\u0430\u0440\u0430\u043d\u0441\u043a\u0438"
    ],
    "wof:name":"Sharanski",
    "wof:placetype":"locality"
},
  "geometry": {"coordinates":[28.2361,57.5384],"type":"Point"}
}