{
  "type": "Feature",
  "properties": {
    "gn:admin1_code":"88",
    "gn:asciiname":"Rozhdestveno",
    "gn:country_code":"RU",
    "gn:dem":129,
    "gn:feature_class":"P",
    "gn:feature_code":"PPL",
    "gn:name":"Rozhdestveno",
    "gn:population":0,
    "gn:timezone":"Europe/Moscow",
    "iso:country":"RU",
    "name:ceb_x_preferred":[
        "Rozhdestveno"
    ],
    "name:eng_x_preferred":[
        "Rozhdestveno"
    ],
    "name:nor_x_preferred":[
        "Rozjdestveno"
    ],
    "name:rus_x_preferred":[
        "\u0420\u043e\u0436\u0434\u0435\u0441\u0442\u0432\u0435\u043d\u043e"
    ],
    "name:und_x_variant":[
        "Rozhestvennoye",
        "Rozhdestveno"
    ],
    "wof:name":"Rozhdestveno",
    "wof:placetype":"locality"
},
  "geometry": {"coordinates":[40.38884,57.37261],"type":"Point"}
}