{
  "type": "Feature",
  "properties": {
    "gn:admin1_code":"73.0",
    "gn:asciiname":"Chetyrchi",
    "gn:country_code":"RU",
    "gn:dem":91,
    "gn:feature_class":"P",
    "gn:feature_code":"PPL",
    "gn:name":"Chetyrchi",
    "gn:population":0,
    "gn:timezone":"Europe/Moscow",
    "iso:country":"RU",
    "name:rus_x_preferred":[
        "\u0427\u0435\u0442\u044b\u0440\u0447\u0438"
    ],
    "name:und_x_variant":[
        "\u0427\u0435\u0442\u044b\u0440\u0447\u0438"
    ],
    "wof:name":"Chetyrchi",
    "wof:placetype":"locality"
},
  "geometry": {"coordinates":[50.94884,55.43038000000001],"type":"Point"}
}