{
  "type": "Feature",
  "properties": {
    "gn:admin1_code":"28",
    "gn:asciiname":"Varlov Les",
    "gn:cc2":"RU",
    "gn:country_code":"RU",
    "gn:dem":119,
    "gn:feature_class":"P",
    "gn:feature_code":"PPL",
    "gn:name":"Varlov Les",
    "gn:population":0,
    "gn:timezone":"Europe/Moscow",
    "iso:country":"RU",
    "name:eng_x_preferred":[
        "Varlov Les"
    ],
    "name:fin_x_preferred":[
        "Varloila"
    ],
    "name:nor_x_preferred":[
        "Varlov Les"
    ],
    "name:rus_x_preferred":[
        "\u0412\u0430\u0440\u043b\u043e\u0432 \u041b\u0435\u0441"
    ],
    "name:und_x_variant":[
        "Varlov-Ves",
        "Varlov Les"
    ],
    "wof:name":"Varlov Les",
    "wof:placetype":"locality"
},
  "geometry": {"coordinates":[32.8862,61.412],"type":"Point"}
}