{
  "type": "Feature",
  "properties": {
    "gn:admin1_code":"52",
    "gn:asciiname":"Dunayevshchina",
    "gn:country_code":"RU",
    "gn:dem":227,
    "gn:feature_class":"P",
    "gn:feature_code":"PPL",
    "gn:name":"Dunayevshchina",
    "gn:population":0,
    "gn:timezone":"Europe/Moscow",
    "iso:country":"RU",
    "name:rus_x_preferred":[
        "\u0414\u0443\u043d\u0430\u0435\u0432\u0449\u0438\u043d\u0430"
    ],
    "wof:name":"Dunayevshchina",
    "wof:placetype":"locality"
},
  "geometry": {"coordinates":[32.96965,57.68535],"type":"Point"}
}