{
  "type": "Feature",
  "properties": {
    "gn:admin1_code":"45.0",
    "gn:asciiname":"Nursola",
    "gn:country_code":"RU",
    "gn:dem":189,
    "gn:feature_class":"P",
    "gn:feature_code":"PPL",
    "gn:name":"Nursola",
    "gn:population":0,
    "gn:timezone":"Europe/Moscow",
    "iso:country":"RU",
    "name:rus_x_preferred":[
        "\u041d\u0443\u0440\u0441\u043e\u043b\u0430"
    ],
    "wof:name":"Nursola",
    "wof:placetype":"locality"
},
  "geometry": {"coordinates":[48.83472,56.785],"type":"Point"}
}