{
  "type": "Feature",
  "properties": {
    "gn:admin1_code":"77",
    "gn:asciiname":"Mikhaylovo-Chirikovo",
    "gn:country_code":"RU",
    "gn:dem":121,
    "gn:feature_class":"P",
    "gn:feature_code":"PPL",
    "gn:name":"Mikhaylovo-Chirikovo",
    "gn:population":0,
    "gn:timezone":"Europe/Moscow",
    "iso:country":"RU",
    "name:rus_x_preferred":[
        "\u041c\u0438\u0445\u0430\u0439\u043b\u043e\u0432\u043e-\u0427\u0438\u0440\u0438\u043a\u043e\u0432\u043e"
    ],
    "name:und_x_variant":[
        "\u041c\u0438\u0445\u0430\u0439\u043b\u043e\u0432\u043e-\u0427\u0438\u0440\u0438\u043a\u043e\u0432\u043e"
    ],
    "wof:name":"Mikhaylovo-Chirikovo",
    "wof:placetype":"locality"
},
  "geometry": {"coordinates":[37.98333,56.88333000000001],"type":"Point"}
}