{
  "type": "Feature",
  "properties": {
    "gn:admin1_code":"25",
    "gn:asciiname":"Spass",
    "gn:country_code":"RU",
    "gn:dem":209,
    "gn:feature_class":"P",
    "gn:feature_code":"PPL",
    "gn:name":"Spass",
    "gn:population":0,
    "gn:timezone":"Europe/Moscow",
    "iso:country":"RU",
    "name:und_x_variant":[
        "Spas"
    ],
    "wof:name":"Spass",
    "wof:placetype":"locality"
},
  "geometry": {"coordinates":[36.76843,54.32267],"type":"Point"}
}