{
  "type": "Feature",
  "properties": {
    "gn:admin1_code":"46",
    "gn:asciiname":"Kalasevo",
    "gn:country_code":"RU",
    "gn:dem":111,
    "gn:feature_class":"P",
    "gn:feature_code":"PPL",
    "gn:name":"Kalasevo",
    "gn:population":0,
    "gn:timezone":"Europe/Moscow",
    "iso:country":"RU",
    "name:eng_x_preferred":[
        "Kalasevo"
    ],
    "name:nor_x_preferred":[
        "Kalasevo"
    ],
    "name:rus_x_preferred":[
        "\u041a\u0430\u043b\u0430\u0441\u0435\u0432\u043e"
    ],
    "name:und_x_variant":[
        "Kalasiev"
    ],
    "wof:name":"Kalasevo",
    "wof:placetype":"locality"
},
  "geometry": {"coordinates":[46.03641,54.78077],"type":"Point"}
}