{
  "type": "Feature",
  "properties": {
    "gn:admin1_code":"78",
    "gn:asciiname":"Volostnaya",
    "gn:country_code":"RU",
    "gn:dem":116,
    "gn:feature_class":"P",
    "gn:feature_code":"PPL",
    "gn:name":"Volostnaya",
    "gn:population":0,
    "gn:timezone":"Asia/Yekaterinburg",
    "iso:country":"RU",
    "name:rus_x_preferred":[
        "\u0412\u043e\u043b\u043e\u0441\u0442\u043d\u0430\u044f"
    ],
    "wof:name":"Volostnaya",
    "wof:placetype":"locality"
},
  "geometry": {"coordinates":[70.8066,56.1505],"type":"Point"}
}