{
  "type": "Feature",
  "properties": {
    "gn:admin1_code":"91",
    "gn:asciiname":"Geologicheskiy",
    "gn:country_code":"RU",
    "gn:dem":3,
    "gn:feature_class":"P",
    "gn:feature_code":"PPL",
    "gn:name":"Geologicheskiy",
    "gn:population":0,
    "gn:timezone":"Asia/Krasnoyarsk",
    "iso:country":"RU",
    "name:rus_x_preferred":[
        "\u0413\u0435\u043e\u043b\u043e\u0433\u0438\u0447\u0435\u0441\u043a\u0438\u0439"
    ],
    "wof:name":"Geologicheskiy",
    "wof:placetype":"locality"
},
  "geometry": {"coordinates":[84.36667,69.40000000000001],"type":"Point"}
}