{
  "type": "Feature",
  "properties": {
    "gn:admin1_code":"80",
    "gn:asciiname":"Kypka",
    "gn:country_code":"RU",
    "gn:dem":165,
    "gn:feature_class":"P",
    "gn:feature_code":"PPL",
    "gn:name":"Kypka",
    "gn:population":0,
    "gn:timezone":"Europe/Samara",
    "iso:country":"RU",
    "name:eng_x_preferred":[
        "Kypka"
    ],
    "name:nor_x_preferred":[
        "Kypka"
    ],
    "name:rus_x_preferred":[
        "\u041a\u044b\u043f\u043a\u0430"
    ],
    "name:und_x_variant":[
        "Kurka",
        "Kypka"
    ],
    "wof:name":"Kypka",
    "wof:placetype":"locality"
},
  "geometry": {"coordinates":[52.4611,58.0783],"type":"Point"}
}