{
  "type": "Feature",
  "properties": {
    "gn:admin1_code":"76",
    "gn:asciiname":"Khorosheye Polevo",
    "gn:country_code":"RU",
    "gn:dem":191,
    "gn:feature_class":"P",
    "gn:feature_code":"PPL",
    "gn:name":"Khorosheye Pol\u00ebvo",
    "gn:population":0,
    "gn:timezone":"Europe/Moscow",
    "iso:country":"RU",
    "name:rus_x_preferred":[
        "\u0425\u043e\u0440\u043e\u0448\u0435\u0435 \u041f\u043e\u043b\u0451\u0432\u043e"
    ],
    "name:und_x_variant":[
        "Khoroshe-Polevo",
        "Khorosheye Pol\u00ebvo",
        "\u0425\u043e\u0440\u043e\u0448\u0435\u0435 \u041f\u043e\u043b\u0451\u0432\u043e"
    ],
    "wof:name":"Khorosheye Polevo",
    "wof:placetype":"locality"
},
  "geometry": {"coordinates":[37.06013,53.64515],"type":"Point"}
}