{
  "type": "Feature",
  "properties": {
    "gn:admin1_code":"60",
    "gn:asciiname":"Korobovo",
    "gn:country_code":"RU",
    "gn:dem":93,
    "gn:feature_class":"P",
    "gn:feature_code":"PPL",
    "gn:name":"Korobovo",
    "gn:population":0,
    "gn:timezone":"Europe/Moscow",
    "iso:country":"RU",
    "name:rus_x_preferred":[
        "\u041a\u043e\u0440\u043e\u0431\u043e\u0432\u043e"
    ],
    "wof:name":"Korobovo",
    "wof:placetype":"locality"
},
  "geometry": {"coordinates":[28.96182,57.38171],"type":"Point"}
}