{
  "type": "Feature",
  "properties": {
    "gn:admin1_code":"91",
    "gn:asciiname":"Berezhki",
    "gn:country_code":"RU",
    "gn:dem":199,
    "gn:feature_class":"P",
    "gn:feature_code":"PPL",
    "gn:name":"Berezhki",
    "gn:population":0,
    "gn:timezone":"Asia/Krasnoyarsk",
    "iso:country":"RU",
    "name:nor_x_preferred":[
        "Berezjki"
    ],
    "name:rus_x_preferred":[
        "\u0411\u0435\u0440\u0435\u0436\u043a\u0438"
    ],
    "name:und_x_variant":[
        "Kan-Perevoz",
        "Berezhki"
    ],
    "wof:name":"Berezhki",
    "wof:placetype":"locality"
},
  "geometry": {"coordinates":[95.63722,56.23056],"type":"Point"}
}