{
  "type": "Feature",
  "properties": {
    "gn:admin1_code":"89",
    "gn:asciiname":"Pashkovo",
    "gn:country_code":"RU",
    "gn:dem":88,
    "gn:feature_class":"P",
    "gn:feature_code":"PPL",
    "gn:name":"Pashkovo",
    "gn:population":0,
    "gn:timezone":"Asia/Vladivostok",
    "iso:country":"RU",
    "name:eng_x_preferred":[
        "Pashkovo"
    ],
    "name:nor_x_preferred":[
        "Pasjkovo"
    ],
    "name:rus_x_preferred":[
        "\u041f\u0430\u0448\u043a\u043e\u0432\u043e"
    ],
    "name:und_x_variant":[
        "Pashkova"
    ],
    "wof:name":"Pashkovo",
    "wof:placetype":"locality"
},
  "geometry": {"coordinates":[130.65258,48.88962],"type":"Point"}
}