{
  "type": "Feature",
  "properties": {
    "gn:admin1_code":"56",
    "gn:asciiname":"Podpolovedskoye",
    "gn:country_code":"RU",
    "gn:dem":248,
    "gn:feature_class":"P",
    "gn:feature_code":"PPL",
    "gn:name":"Podpolovedskoye",
    "gn:population":0,
    "gn:timezone":"Europe/Moscow",
    "iso:country":"RU",
    "wof:name":"Podpolovedskoye",
    "wof:placetype":"locality"
},
  "geometry": {"coordinates":[36.61625,53.15536],"type":"Point"}
}