{
  "type": "Feature",
  "properties": {
    "gn:admin1_code":"46",
    "gn:asciiname":"Staroye Pshenevo",
    "gn:country_code":"RU",
    "gn:dem":166,
    "gn:feature_class":"P",
    "gn:feature_code":"PPL",
    "gn:name":"Staroye Pshen\u00ebvo",
    "gn:population":0,
    "gn:timezone":"Europe/Moscow",
    "iso:country":"RU",
    "name:rus_x_preferred":[
        "\u0421\u0442\u0430\u0440\u043e\u0435 \u041f\u0448\u0435\u043d\u0451\u0432\u043e"
    ],
    "name:und_x_variant":[
        "Staroye Pshen\u00ebvo"
    ],
    "wof:name":"Staroye Pshenevo",
    "wof:placetype":"locality"
},
  "geometry": {"coordinates":[44.21114,54.10917],"type":"Point"}
}