{
  "type": "Feature",
  "properties": {
    "gn:admin1_code":"85",
    "gn:asciiname":"Vasil'yevskaya",
    "gn:cc2":"RU",
    "gn:country_code":"RU",
    "gn:dem":246,
    "gn:feature_class":"P",
    "gn:feature_code":"PPL",
    "gn:name":"Vasil'yevskaya",
    "gn:population":0,
    "gn:timezone":"Europe/Moscow",
    "iso:country":"RU",
    "name:und_x_variant":[
        "Vasiljevskaja"
    ],
    "wof:name":"Vasil'yevskaya",
    "wof:placetype":"locality"
},
  "geometry": {"coordinates":[35.55889000000001,60.53056],"type":"Point"}
}