{
  "type": "Feature",
  "properties": {
    "gn:admin1_code":"53",
    "gn:asciiname":"Novokarasuk",
    "gn:country_code":"RU",
    "gn:dem":106,
    "gn:feature_class":"P",
    "gn:feature_code":"PPL",
    "gn:name":"Novokarasuk",
    "gn:population":0,
    "gn:timezone":"Asia/Novosibirsk",
    "iso:country":"RU",
    "name:eng_x_preferred":[
        "Novokarasuk"
    ],
    "name:nor_x_preferred":[
        "Novokarasuk"
    ],
    "name:rus_x_preferred":[
        "\u041d\u043e\u0432\u043e\u043a\u0430\u0440\u0430\u0441\u0443\u043a"
    ],
    "name:und_x_variant":[
        "Novyy Karasuk"
    ],
    "wof:name":"Novokarasuk",
    "wof:placetype":"locality"
},
  "geometry": {"coordinates":[77.38713,53.59476],"type":"Point"}
}