{
  "type": "Feature",
  "properties": {
    "gn:admin1_code":"77",
    "gn:asciiname":"Kozhukhovo",
    "gn:country_code":"RU",
    "gn:dem":234,
    "gn:feature_class":"P",
    "gn:feature_code":"PPL",
    "gn:name":"Kozhukhovo",
    "gn:population":0,
    "gn:timezone":"Europe/Moscow",
    "iso:country":"RU",
    "name:rus_x_preferred":[
        "\u041a\u043e\u0436\u0443\u0445\u043e\u0432\u043e"
    ],
    "wof:name":"Kozhukhovo",
    "wof:placetype":"locality"
},
  "geometry": {"coordinates":[33.2901,56.40138],"type":"Point"}
}