{
  "type": "Feature",
  "properties": {
    "gn:admin1_code":"72",
    "gn:asciiname":"Umet",
    "gn:country_code":"RU",
    "gn:dem":191,
    "gn:feature_class":"P",
    "gn:feature_code":"PPL",
    "gn:name":"Um\u00ebt",
    "gn:population":0,
    "gn:timezone":"Europe/Moscow",
    "iso:country":"RU",
    "name:eng_x_preferred":[
        "Um\u00ebt"
    ],
    "name:nor_x_preferred":[
        "Umet"
    ],
    "name:rus_x_preferred":[
        "\u0423\u043c\u0435\u0442"
    ],
    "name:und_x_variant":[
        "Um\u00ebt"
    ],
    "wof:name":"Umet",
    "wof:placetype":"locality"
},
  "geometry": {"coordinates":[42.96732,52.56309],"type":"Point"}
}