{
  "type": "Feature",
  "properties": {
    "gn:admin1_code":"56",
    "gn:asciiname":"Solntse",
    "gn:country_code":"RU",
    "gn:dem":221,
    "gn:feature_class":"P",
    "gn:feature_code":"PPL",
    "gn:name":"Solntse",
    "gn:population":0,
    "gn:timezone":"Europe/Moscow",
    "iso:country":"RU",
    "name:mkd_x_preferred":[
        "\u0421\u043e\u043d\u0446\u0435"
    ],
    "name:rus_x_preferred":[
        "\u0421\u043e\u043b\u043d\u0446\u0435"
    ],
    "name:ukr_x_preferred":[
        "\u0421\u043e\u043d\u0446\u0435"
    ],
    "wof:name":"Solntse",
    "wof:placetype":"locality"
},
  "geometry": {"coordinates":[35.75909,52.85936],"type":"Point"}
}