{
  "type": "Feature",
  "properties": {
    "gn:country":"RU",
    "gn:fcode":"PPL",
    "gn:population":3500,
    "iso:country":"RU",
    "name:eng_x_preferred":[
        "Barsuki"
    ],
    "name:rus_x_preferred":[
        "\u0411\u0430\u0440\u0441\u0443\u043a\u0438"
    ],
    "qs:name":"Barsuki",
    "qs:name_adm0":"Russia",
    "qs:name_adm1":"Tula Oblast",
    "qs:photos_9k":1,
    "qs:photos_9r":2,
    "qs:photos_all":52,
    "qs:photos_sr":0,
    "qs:placetype":"Town",
    "qs:pop_sr":"4",
    "wd:wordcount":951,
    "wof:name":"Barsuki",
    "wof:placetype":"locality",
    "wof:population":3500
},
  "geometry": {"coordinates":[37.48746,54.26548],"type":"Point"}
}