{
  "type": "Feature",
  "properties": {
    "gn:admin1_code":"88",
    "gn:asciiname":"Medlevo",
    "gn:country_code":"RU",
    "gn:dem":119,
    "gn:feature_class":"P",
    "gn:feature_code":"PPL",
    "gn:name":"Medlevo",
    "gn:population":0,
    "gn:timezone":"Europe/Moscow",
    "iso:country":"RU",
    "name:rus_x_preferred":[
        "\u041c\u0435\u0434\u043b\u0435\u0432\u043e"
    ],
    "wof:name":"Medlevo",
    "wof:placetype":"locality"
},
  "geometry": {"coordinates":[37.93333,57.61666999999999],"type":"Point"}
}