{
  "type": "Feature",
  "properties": {
    "gn:admin1_code":"61",
    "gn:asciiname":"Andreyanovka",
    "gn:country_code":"RU",
    "gn:dem":157,
    "gn:feature_class":"P",
    "gn:feature_code":"PPL",
    "gn:name":"Andreyanovka",
    "gn:population":0,
    "gn:timezone":"Europe/Moscow",
    "iso:country":"RU",
    "name:nor_x_preferred":[
        "Andrejanovka"
    ],
    "name:rus_x_preferred":[
        "\u0410\u043d\u0434\u0440\u0435\u044f\u043d\u043e\u0432\u043a\u0430"
    ],
    "wof:name":"Andreyanovka",
    "wof:placetype":"locality"
},
  "geometry": {"coordinates":[40.14062,49.22009],"type":"Point"}
}