{
  "type": "Feature",
  "properties": {
    "gn:admin1_code":"41",
    "gn:asciiname":"Pervoye Rozhdestvenskoye",
    "gn:country_code":"RU",
    "gn:dem":200,
    "gn:feature_class":"P",
    "gn:feature_code":"PPL",
    "gn:name":"Pervoye Rozhdestvenskoye",
    "gn:population":0,
    "gn:timezone":"Europe/Moscow",
    "iso:country":"RU",
    "name:rus_x_preferred":[
        "\u041f\u0435\u0440\u0432\u043e\u0435 \u0420\u043e\u0436\u0434\u0435\u0441\u0442\u0432\u0435\u043d\u0441\u043a\u043e\u0435"
    ],
    "name:und_x_variant":[
        "Dolzhinka",
        "Pervoye Rozhdestvenskoye",
        "\u041f\u0435\u0440\u0432\u043e\u0435 \u0420\u043e\u0436\u0434\u0435\u0441\u0442\u0432\u0435\u043d\u0441\u043a\u043e\u0435"
    ],
    "wof:name":"Pervoye Rozhdestvenskoye",
    "wof:placetype":"locality"
},
  "geometry": {"coordinates":[35.8777,52.0139],"type":"Point"}
}