{
  "type": "Feature",
  "properties": {
    "gn:admin1_code":"60",
    "gn:asciiname":"Zelenino",
    "gn:country_code":"RU",
    "gn:dem":79,
    "gn:feature_class":"P",
    "gn:feature_code":"PPL",
    "gn:name":"Zelenino",
    "gn:population":0,
    "gn:timezone":"Europe/Moscow",
    "iso:country":"RU",
    "name:rus_x_preferred":[
        "\u0417\u0435\u043b\u0435\u043d\u0438\u043d\u043e"
    ],
    "name:und_x_variant":[
        "Zelenina",
        "Zelenino"
    ],
    "wof:name":"Zelenino",
    "wof:placetype":"locality"
},
  "geometry": {"coordinates":[28.97446,57.58917],"type":"Point"}
}