{
  "type": "Feature",
  "properties": {
    "gn:admin1_code":"61",
    "gn:asciiname":"Koshayevka",
    "gn:country_code":"RU",
    "gn:dem":73,
    "gn:feature_class":"P",
    "gn:feature_code":"PPL",
    "gn:name":"Koshayevka",
    "gn:population":0,
    "gn:timezone":"Europe/Moscow",
    "iso:country":"RU",
    "name:rus_x_preferred":[
        "\u041a\u043e\u0448\u0430\u0435\u0432\u043a\u0430"
    ],
    "wof:name":"Koshayevka",
    "wof:placetype":"locality"
},
  "geometry": {"coordinates":[40.54791,49.19246],"type":"Point"}
}