{
  "type": "Feature",
  "properties": {
    "gn:admin1_code":"33.0",
    "gn:asciiname":"Sheromovo",
    "gn:country_code":"RU",
    "gn:dem":156,
    "gn:feature_class":"P",
    "gn:feature_code":"PPL",
    "gn:name":"Sheromovo",
    "gn:population":0,
    "gn:timezone":"Europe/Kirov",
    "iso:country":"RU",
    "name:rus_x_preferred":[
        "\u0428\u0435\u0440\u043e\u043c\u043e\u0432\u043e"
    ],
    "name:und_x_variant":[
        "\u0428\u0435\u0440\u043e\u043c\u043e\u0432\u043e"
    ],
    "wof:name":"Sheromovo",
    "wof:placetype":"locality"
},
  "geometry": {"coordinates":[50.12631,58.29928],"type":"Point"}
}