{
  "type": "Feature",
  "properties": {
    "gn:admin1_code":"60",
    "gn:asciiname":"Astratovo",
    "gn:country_code":"RU",
    "gn:dem":68,
    "gn:feature_class":"P",
    "gn:feature_code":"PPL",
    "gn:name":"Astratovo",
    "gn:population":0,
    "gn:timezone":"Europe/Moscow",
    "iso:country":"RU",
    "name:rus_x_preferred":[
        "\u0410\u0441\u0442\u0440\u0430\u0442\u043e\u0432\u043e"
    ],
    "wof:name":"Astratovo",
    "wof:placetype":"locality"
},
  "geometry": {"coordinates":[28.55386,57.15478],"type":"Point"}
}