{
  "type": "Feature",
  "properties": {
    "gn:admin1_code":"75",
    "gn:asciiname":"Kedrach",
    "gn:country_code":"RU",
    "gn:dem":80,
    "gn:feature_class":"P",
    "gn:feature_code":"PPL",
    "gn:name":"Kedrach",
    "gn:population":0,
    "gn:timezone":"Asia/Tomsk",
    "iso:country":"RU",
    "name:rus_x_preferred":[
        "\u041a\u0435\u0434\u0440\u0430\u0447"
    ],
    "name:und_x_variant":[
        "\u041a\u0435\u0434\u0440\u0430\u0447"
    ],
    "wof:name":"Kedrach",
    "wof:placetype":"locality"
},
  "geometry": {"coordinates":[80.31667,58.15],"type":"Point"}
}