{
  "type": "Feature",
  "properties": {
    "gn:admin1_code":"90.0",
    "gn:asciiname":"Bizyar",
    "gn:country_code":"RU",
    "gn:dem":216,
    "gn:feature_class":"P",
    "gn:feature_code":"PPL",
    "gn:name":"Bizyar",
    "gn:population":0,
    "gn:timezone":"Asia/Yekaterinburg",
    "iso:country":"RU",
    "name:che_x_preferred":[
        "\u0411\u0438\u0437\u044f\u0440"
    ],
    "name:eng_x_preferred":[
        "Bizyar"
    ],
    "name:nor_x_preferred":[
        "Biziar"
    ],
    "name:rus_x_preferred":[
        "\u0411\u0438\u0437\u044f\u0440"
    ],
    "wof:name":"Bizyar",
    "wof:placetype":"locality"
},
  "geometry": {"coordinates":[56.1423,57.5219],"type":"Point"}
}