{
  "type": "Feature",
  "properties": {
    "gn:admin1_code":"45",
    "gn:asciiname":"Pinzhedur",
    "gn:country_code":"RU",
    "gn:dem":94,
    "gn:feature_class":"P",
    "gn:feature_code":"PPL",
    "gn:name":"Pinzhedur",
    "gn:population":0,
    "gn:timezone":"Europe/Moscow",
    "iso:country":"RU",
    "name:rus_x_preferred":[
        "\u041f\u0438\u043d\u0436\u0435\u0434\u0443\u0440"
    ],
    "wof:name":"Pinzhedur",
    "wof:placetype":"locality"
},
  "geometry": {"coordinates":[46.68443,56.71515],"type":"Point"}
}