{
  "type": "Feature",
  "properties": {
    "gn:admin1_code":"38",
    "gn:asciiname":"Volna",
    "gn:country_code":"RU",
    "gn:dem":33,
    "gn:feature_class":"P",
    "gn:feature_code":"PPL",
    "gn:name":"Volna",
    "gn:population":0,
    "gn:timezone":"Europe/Moscow",
    "iso:country":"RU",
    "name:rus_x_preferred":[
        "\u0412\u043e\u043b\u043d\u0430"
    ],
    "name:und_x_variant":[
        "Sovkhoz Bulgas",
        "Volna"
    ],
    "wof:name":"Volna",
    "wof:placetype":"locality"
},
  "geometry": {"coordinates":[36.71062,45.12704],"type":"Point"}
}