{
  "type": "Feature",
  "properties": {
    "gn:admin1_code":"38",
    "gn:asciiname":"Volna",
    "gn:country_code":"RU",
    "gn:dem":33,
    "gn:feature_class":"P",
    "gn:feature_code":"PPL",
    "gn:name":"Volna",
    "gn:population":0,
    "gn:timezone":"Europe/Moscow",
    "iso:country":"RU",
    "name:bul_x_preferred":[
        "\u0412\u044a\u043b\u043d\u0430"
    ],
    "name:ces_x_preferred":[
        "Volna"
    ],
    "name:deu_x_preferred":[
        "Wolna"
    ],
    "name:fin_x_preferred":[
        "Volna"
    ],
    "name:fra_x_preferred":[
        "Volna"
    ],
    "name:ind_x_preferred":[
        "Volna"
    ],
    "name:jpn_x_preferred":[
        "\u30f4\u30a9\u30eb\u30ca"
    ],
    "name:por_x_preferred":[
        "Volna"
    ],
    "name:rus_x_preferred":[
        "\u0433\u043e\u0440\u0430 \u0412\u043e\u043b\u043d\u0430"
    ],
    "name:rus_x_variant":[
        "\u0412\u043e\u043b\u043d\u0430"
    ],
    "name:swe_x_preferred":[
        "Volna"
    ],
    "name:tur_x_preferred":[
        "Volna"
    ],
    "name:ukr_x_preferred":[
        "\u0412\u043e\u043b\u043d\u0430"
    ],
    "name:und_x_variant":[
        "Sovkhoz Bulgas"
    ],
    "name:urd_x_preferred":[
        "\u0648\u0648\u0644\u0646\u0627"
    ],
    "name:vie_x_preferred":[
        "N\u00fai Volna"
    ],
    "name:zho_cn_x_preferred":[
        "\u6c83\u7eb3\u5c71"
    ],
    "name:zho_tw_x_preferred":[
        "\u706b\u5c71"
    ],
    "name:zho_x_preferred":[
        "\u6ce2\u6d6a\u904b\u8f09\u706b\u7bad"
    ],
    "wof:name":"Volna",
    "wof:placetype":"locality"
},
  "geometry": {"coordinates":[36.71062,45.12704],"type":"Point"}
}