{
  "type": "Feature",
  "properties": {
    "gn:admin1_code":"69",
    "gn:asciiname":"Gryadki",
    "gn:country_code":"RU",
    "gn:dem":205,
    "gn:feature_class":"P",
    "gn:feature_code":"PPL",
    "gn:name":"Gryadki",
    "gn:population":0,
    "gn:timezone":"Europe/Moscow",
    "iso:country":"RU",
    "name:rus_x_preferred":[
        "\u0413\u0440\u044f\u0434\u043a\u0438"
    ],
    "wof:name":"Gryadki",
    "wof:placetype":"locality"
},
  "geometry": {"coordinates":[34.07308,54.80435],"type":"Point"}
}