{
  "type": "Feature",
  "properties": {
    "gn:admin1_code":"47",
    "gn:asciiname":"Satino-Russkoye",
    "gn:country_code":"RU",
    "gn:dem":185,
    "gn:feature_class":"P",
    "gn:feature_code":"PPL",
    "gn:name":"Satino-Russkoye",
    "gn:population":75,
    "gn:timezone":"Europe/Moscow",
    "iso:country":"RU",
    "name:rus_x_preferred":[
        "\u0421\u0430\u0442\u0438\u043d\u043e-\u0420\u0443\u0441\u0441\u043a\u043e\u0435"
    ],
    "name:und_x_variant":[
        "\u0421\u0430\u0442\u0438\u043d\u043e-\u0420\u0443\u0441\u0441\u043a\u043e\u0435"
    ],
    "wof:name":"Satino-Russkoye",
    "wof:placetype":"locality",
    "wof:population":75
},
  "geometry": {"coordinates":[37.34295,55.37300000000001],"type":"Point"}
}