{
  "type": "Feature",
  "properties": {
    "gn:admin1_code":"84.0",
    "gn:asciiname":"Churzin",
    "gn:country_code":"RU",
    "gn:dem":24,
    "gn:feature_class":"P",
    "gn:feature_code":"PPL",
    "gn:name":"Churzin",
    "gn:population":0,
    "gn:timezone":"Europe/Volgograd",
    "iso:country":"RU",
    "name:rus_x_preferred":[
        "\u0427\u0443\u0440\u0437\u0438\u043d"
    ],
    "name:und_x_variant":[
        "\u0427\u0443\u0440\u0437\u0438\u043d"
    ],
    "wof:name":"Churzin",
    "wof:placetype":"locality"
},
  "geometry": {"coordinates":[46.53333,49.73333],"type":"Point"}
}