{
  "type": "Feature",
  "properties": {
    "gn:admin1_code":"17",
    "gn:admin2_code":"583776",
    "gn:asciiname":"Tsoloda",
    "gn:country_code":"RU",
    "gn:dem":2165,
    "gn:feature_class":"P",
    "gn:feature_code":"PPL",
    "gn:name":"Tsoloda",
    "gn:population":0,
    "gn:timezone":"Europe/Moscow",
    "iso:country":"RU",
    "name:rus_x_preferred":[
        "\u0426\u043e\u043b\u043e\u0434\u0430"
    ],
    "name:und_x_variant":[
        "\u0426\u043e\u043b\u043e\u0434\u0430"
    ],
    "wof:name":"Tsoloda",
    "wof:placetype":"locality"
},
  "geometry": {"coordinates":[46.36626,42.63827],"type":"Point"}
}