{
  "type": "Feature",
  "properties": {
    "gn:admin1_code":"69",
    "gn:asciiname":"Bratki",
    "gn:country_code":"RU",
    "gn:dem":252,
    "gn:feature_class":"P",
    "gn:feature_code":"PPL",
    "gn:name":"Bratki",
    "gn:population":0,
    "gn:timezone":"Europe/Moscow",
    "iso:country":"RU",
    "name:rus_x_preferred":[
        "\u0411\u0440\u0430\u0442\u043a\u0438"
    ],
    "name:und_x_variant":[
        "\u0411\u0440\u0430\u0442\u043a\u0438"
    ],
    "wof:name":"Bratki",
    "wof:placetype":"locality"
},
  "geometry": {"coordinates":[34.9375,55.265],"type":"Point"}
}