{
  "type": "Feature",
  "properties": {
    "gn:admin1_code":"75",
    "gn:asciiname":"Vorono-Pashnya",
    "gn:country_code":"RU",
    "gn:dem":148,
    "gn:feature_class":"P",
    "gn:feature_code":"PPL",
    "gn:name":"Vorono-Pashnya",
    "gn:population":0,
    "gn:timezone":"Asia/Tomsk",
    "iso:country":"RU",
    "name:eng_x_preferred":[
        "Vorono-Pashnya"
    ],
    "name:nor_x_preferred":[
        "Voronino-Pasjnja"
    ],
    "name:rus_x_preferred":[
        "\u0412\u043e\u0440\u043e\u043d\u0438\u043d\u043e-\u041f\u0430\u0448\u043d\u044f"
    ],
    "name:und_x_variant":[
        "Vorono-Pashennoye",
        "Vorono-Pashino"
    ],
    "wof:name":"Vorono-Pashnya",
    "wof:placetype":"locality"
},
  "geometry": {"coordinates":[85.89435999999998,56.89914],"type":"Point"}
}