{
  "type": "Feature",
  "properties": {
    "gn:admin1_code":"76",
    "gn:asciiname":"Korsakovo",
    "gn:country_code":"RU",
    "gn:dem":185,
    "gn:feature_class":"P",
    "gn:feature_code":"PPL",
    "gn:name":"Korsakovo",
    "gn:population":0,
    "gn:timezone":"Europe/Moscow",
    "iso:country":"RU",
    "name:rus_x_preferred":[
        "\u041a\u043e\u0440\u0441\u0430\u043a\u043e\u0432\u043e"
    ],
    "wof:name":"Korsakovo",
    "wof:placetype":"locality"
},
  "geometry": {"coordinates":[38.32573,53.76115],"type":"Point"}
}