{
  "type": "Feature",
  "properties": {
    "gn:admin1_code":"65",
    "gn:asciiname":"Novo-Gol'kovskiy",
    "gn:country_code":"RU",
    "gn:dem":62,
    "gn:feature_class":"P",
    "gn:feature_code":"PPL",
    "gn:name":"Novo-Gol\u2019kovskiy",
    "gn:population":0,
    "gn:timezone":"Europe/Samara",
    "iso:country":"RU",
    "name:rus_x_preferred":[
        "\u041d\u043e\u0432\u043e-\u0413\u043e\u043b\u044c\u043a\u043e\u0432\u0441\u043a\u0438\u0439"
    ],
    "name:und_x_variant":[
        "Novy Gol\u2019kovskiy",
        "Novo-Gol\u2019kovskiy",
        "\u041d\u043e\u0432\u043e-\u0413\u043e\u043b\u044c\u043a\u043e\u0432\u0441\u043a\u0438\u0439"
    ],
    "wof:name":"Novo-Gol'kovskiy",
    "wof:placetype":"locality"
},
  "geometry": {"coordinates":[51.21667,52.76667],"type":"Point"}
}