{
  "type": "Feature",
  "properties": {
    "gn:admin1_code":"25",
    "gn:asciiname":"Krivskoye",
    "gn:country_code":"RU",
    "gn:dem":143,
    "gn:feature_class":"P",
    "gn:feature_code":"PPL",
    "gn:name":"Krivskoye",
    "gn:population":0,
    "gn:timezone":"Europe/Moscow",
    "iso:country":"RU",
    "name:eng_x_preferred":[
        "Krivskoye"
    ],
    "name:nor_x_preferred":[
        "Krivskoje"
    ],
    "name:rus_x_preferred":[
        "\u041a\u0440\u0438\u0432\u0441\u043a\u043e\u0435"
    ],
    "name:und_x_variant":[
        "\u041a\u0440\u0438\u0432\u0441\u043a\u043e\u0435",
        "Krivskoye"
    ],
    "wof:name":"Krivskoye",
    "wof:placetype":"locality"
},
  "geometry": {"coordinates":[36.53722,55.13639000000001],"type":"Point"}
}