{
  "type": "Feature",
  "properties": {
    "gn:admin1_code":"33",
    "gn:asciiname":"Lyumpanur",
    "gn:country_code":"RU",
    "gn:dem":111,
    "gn:feature_class":"P",
    "gn:feature_code":"PPL",
    "gn:name":"Lyumpanur",
    "gn:population":0,
    "gn:timezone":"Europe/Kirov",
    "iso:country":"RU",
    "name:eng_x_preferred":[
        "Lyumpanur"
    ],
    "name:nor_x_preferred":[
        "Ljumpanur"
    ],
    "name:rus_x_preferred":[
        "\u041b\u044e\u043c\u043f\u0430\u043d\u0443\u0440"
    ],
    "name:und_x_variant":[
        "Lvumpanur\u2019",
        "\u041b\u044e\u043c\u043f\u0430\u043d\u0443\u0440",
        "Lyumpanur"
    ],
    "wof:name":"Lyumpanur",
    "wof:placetype":"locality"
},
  "geometry": {"coordinates":[46.84964,56.96675],"type":"Point"}
}