{
  "type": "Feature",
  "properties": {
    "gn:admin1_code":"81",
    "gn:asciiname":"Kommuna",
    "gn:country_code":"RU",
    "gn:dem":162,
    "gn:feature_class":"P",
    "gn:feature_code":"PPL",
    "gn:name":"Kommuna",
    "gn:population":0,
    "gn:timezone":"Europe/Ulyanovsk",
    "iso:country":"RU",
    "name:rus_x_preferred":[
        "\u041a\u043e\u043c\u043c\u0443\u043d\u0430"
    ],
    "name:und_x_variant":[
        "\u041a\u043e\u043c\u043c\u0443\u043d\u0430"
    ],
    "wof:name":"Kommuna",
    "wof:placetype":"locality"
},
  "geometry": {"coordinates":[47.8385,53.8901],"type":"Point"}
}