{
  "type": "Feature",
  "properties": {
    "gn:admin1_code":"16",
    "gn:asciiname":"Novyye Yamashi",
    "gn:country_code":"RU",
    "gn:dem":131,
    "gn:feature_class":"P",
    "gn:feature_code":"PPL",
    "gn:name":"Novyye Yamashi",
    "gn:population":0,
    "gn:timezone":"Europe/Moscow",
    "iso:country":"RU",
    "name:rus_x_preferred":[
        "\u041d\u043e\u0432\u044b\u0435 \u042f\u043c\u0430\u0448\u0438"
    ],
    "wof:name":"Novyye Yamashi",
    "wof:placetype":"locality"
},
  "geometry": {"coordinates":[47.5303,55.7246],"type":"Point"}
}