{
  "type": "Feature",
  "properties": {
    "gn:admin1_code":"37.0",
    "gn:asciiname":"Berezovets",
    "gn:country_code":"RU",
    "gn:dem":97,
    "gn:feature_class":"P",
    "gn:feature_code":"PPL",
    "gn:name":"Ber\u00ebzovets",
    "gn:population":0,
    "gn:timezone":"Europe/Moscow",
    "iso:country":"RU",
    "name:eng_x_preferred":[
        "Ber\u00ebzovets"
    ],
    "name:rus_x_preferred":[
        "\u0411\u0435\u0440\u0435\u0437\u043e\u0432\u0435\u0446"
    ],
    "name:rus_x_variant":[
        "\u0411\u0435\u0440\u0451\u0437\u043e\u0432\u0435\u0446"
    ],
    "wof:name":"Berezovets",
    "wof:placetype":"locality"
},
  "geometry": {"coordinates":[43.16587,57.57487],"type":"Point"}
}