{
  "type": "Feature",
  "properties": {
    "gn:admin1_code":"37",
    "gn:asciiname":"Pervaya Klobukovskaya",
    "gn:country_code":"RU",
    "gn:dem":174,
    "gn:feature_class":"P",
    "gn:feature_code":"PPL",
    "gn:name":"Pervaya Klobukovskaya",
    "gn:population":0,
    "gn:timezone":"Europe/Moscow",
    "iso:country":"RU",
    "name:rus_x_preferred":[
        "\u041f\u0435\u0440\u0432\u0430\u044f \u041a\u043b\u043e\u0431\u0443\u043a\u043e\u0432\u0441\u043a\u0430\u044f"
    ],
    "name:und_x_variant":[
        "Klobukovskaya",
        "Pervaya Klobukovskaya",
        "Klobukovskaya Pervaya"
    ],
    "wof:name":"Pervaya Klobukovskaya",
    "wof:placetype":"locality"
},
  "geometry": {"coordinates":[47.21154,59.0843],"type":"Point"}
}