{
  "type": "Feature",
  "properties": {
    "gn:admin1_code":"61",
    "gn:asciiname":"Sulatskov",
    "gn:country_code":"RU",
    "gn:dem":34,
    "gn:feature_class":"P",
    "gn:feature_code":"PPL",
    "gn:name":"Sulatskov",
    "gn:population":0,
    "gn:timezone":"Europe/Moscow",
    "iso:country":"RU",
    "name:rus_x_preferred":[
        "\u0421\u0443\u043b\u0430\u0442\u0441\u043a\u043e\u0432"
    ],
    "name:und_x_variant":[
        "\u0421\u0443\u043b\u0430\u0442\u0441\u043a\u043e\u0432"
    ],
    "wof:name":"Sulatskov",
    "wof:placetype":"locality"
},
  "geometry": {"coordinates":[41.95222,47.77139],"type":"Point"}
}