{
  "type": "Feature",
  "properties": {
    "gn:admin1_code":"33",
    "gn:asciiname":"Shalagi",
    "gn:country_code":"RU",
    "gn:dem":92,
    "gn:feature_class":"P",
    "gn:feature_code":"PPL",
    "gn:name":"Shalagi",
    "gn:population":0,
    "gn:timezone":"Europe/Kirov",
    "iso:country":"RU",
    "name:rus_x_preferred":[
        "\u0428\u0430\u043b\u0430\u0433\u0438"
    ],
    "wof:name":"Shalagi",
    "wof:placetype":"locality"
},
  "geometry": {"coordinates":[49.6034,57.5281],"type":"Point"}
}