{
  "type": "Feature",
  "properties": {
    "gn:admin1_code":"90",
    "gn:asciiname":"Syuzyan'",
    "gn:country_code":"RU",
    "gn:dem":155,
    "gn:feature_class":"P",
    "gn:feature_code":"PPL",
    "gn:name":"Syuzyan\u2019",
    "gn:population":0,
    "gn:timezone":"Asia/Yekaterinburg",
    "iso:country":"RU",
    "name:rus_x_preferred":[
        "\u0421\u044e\u0437\u044f\u043d\u044c"
    ],
    "name:und_x_variant":[
        "Syuzyan\u2019",
        "Syuzan"
    ],
    "wof:name":"Syuzyan'",
    "wof:placetype":"locality"
},
  "geometry": {"coordinates":[55.7717,56.8467],"type":"Point"}
}