{
  "type": "Feature",
  "properties": {
    "gn:country":"RU",
    "gn:fcode":"PPL",
    "gn:pop":1362,
    "iso:country":"RU",
    "name:eng_x_preferred":[
        "Goritsy"
    ],
    "name:nor_x_preferred":[
        "Goritsy"
    ],
    "name:rus_x_preferred":[
        "\u0413\u043e\u0440\u0438\u0446\u044b"
    ],
    "name:unk_x_variant":[
        "\u0413\u043e\u0440\u0438\u0446\u044b"
    ],
    "qs:name":"Goritsj",
    "qs:name_adm0":"Russia",
    "qs:name_adm1":"Vologda Oblast",
    "qs:photos":92,
    "qs:photos_1k":19,
    "qs:photos_9k":1,
    "qs:photos_9r":3,
    "qs:photos_all":92,
    "qs:photos_sr":3,
    "qs:placetype":"Town",
    "qs:pop_sr":"3",
    "wof:name":"Goritsj",
    "wof:placetype":"locality",
    "wof:population":1362
},
  "geometry": {"coordinates":[38.26016,59.86949],"type":"Point"}
}