{
  "type": "Feature",
  "properties": {
    "gn:admin1_code":"33",
    "gn:asciiname":"Shuravintsy",
    "gn:country_code":"RU",
    "gn:dem":182,
    "gn:feature_class":"P",
    "gn:feature_code":"PPL",
    "gn:name":"Shuravintsy",
    "gn:population":0,
    "gn:timezone":"Europe/Kirov",
    "iso:country":"RU",
    "name:rus_x_preferred":[
        "\u0428\u0443\u0440\u0430\u0432\u0438\u043d\u0446\u044b"
    ],
    "wof:name":"Shuravintsy",
    "wof:placetype":"locality"
},
  "geometry": {"coordinates":[50.0262,58.0683],"type":"Point"}
}