{
  "type": "Feature",
  "properties": {
    "gn:admin1_code":"40",
    "gn:asciiname":"Chebaki",
    "gn:country_code":"RU",
    "gn:dem":142,
    "gn:feature_class":"P",
    "gn:feature_code":"PPL",
    "gn:name":"Chebaki",
    "gn:population":0,
    "gn:timezone":"Asia/Yekaterinburg",
    "iso:country":"RU",
    "name:eng_x_preferred":[
        "Chebaki"
    ],
    "name:nor_x_preferred":[
        "Tsjebaki"
    ],
    "name:rus_x_preferred":[
        "\u0427\u0435\u0431\u0430\u043a\u0438"
    ],
    "name:und_x_variant":[
        "\u0427\u0435\u0431\u0430\u043a\u0438",
        "Chebaki"
    ],
    "wof:name":"Chebaki",
    "wof:placetype":"locality"
},
  "geometry": {"coordinates":[67.27417,55.06861],"type":"Point"}
}