{
  "type": "Feature",
  "properties": {
    "gn:admin1_code":"52",
    "gn:asciiname":"Grigornoye",
    "gn:country_code":"RU",
    "gn:dem":115,
    "gn:feature_class":"P",
    "gn:feature_code":"PPL",
    "gn:name":"Grigornoye",
    "gn:population":0,
    "gn:timezone":"Europe/Moscow",
    "iso:country":"RU",
    "name:rus_x_preferred":[
        "\u0413\u0440\u0438\u0433\u043e\u0440\u043d\u043e\u0435"
    ],
    "wof:name":"Grigornoye",
    "wof:placetype":"locality"
},
  "geometry": {"coordinates":[31.94241,57.26523],"type":"Point"}
}