{
  "type": "Feature",
  "properties": {
    "gn:admin1_code":"56.0",
    "gn:asciiname":"Durnovo",
    "gn:country_code":"RU",
    "gn:dem":221,
    "gn:feature_class":"P",
    "gn:feature_code":"PPL",
    "gn:name":"Durnovo",
    "gn:population":0,
    "gn:timezone":"Europe/Moscow",
    "iso:country":"RU",
    "name:rus_x_preferred":[
        "\u0414\u0443\u0440\u043d\u043e\u0432\u043e"
    ],
    "name:und_x_variant":[
        "\u0414\u0443\u0440\u043d\u043e\u0432\u043e"
    ],
    "wof:name":"Durnovo",
    "wof:placetype":"locality"
},
  "geometry": {"coordinates":[36.2831,52.68252],"type":"Point"}
}