{
  "type": "Feature",
  "properties": {
    "gn:admin1_code":"38.0",
    "gn:asciiname":"Belyayevskiy",
    "gn:country_code":"RU",
    "gn:dem":34,
    "gn:feature_class":"P",
    "gn:feature_code":"PPL",
    "gn:name":"Belyayevskiy",
    "gn:population":0,
    "gn:timezone":"Europe/Moscow",
    "iso:country":"RU",
    "name:nor_x_preferred":[
        "Beljaevskij"
    ],
    "name:rus_x_preferred":[
        "\u0411\u0435\u043b\u044f\u0435\u0432\u0441\u043a\u0438\u0439"
    ],
    "name:und_x_variant":[
        "Belyavevskiy",
        "Belyayevskiy Pervyy",
        "Belyayevskiy",
        "Belyavskiy"
    ],
    "wof:name":"Belyayevskiy",
    "wof:placetype":"locality"
},
  "geometry": {"coordinates":[39.48996,45.01659],"type":"Point"}
}