{
  "type": "Feature",
  "properties": {
    "gn:admin1_code":"51",
    "gn:asciiname":"Iskusovo",
    "gn:country_code":"RU",
    "gn:dem":195,
    "gn:feature_class":"P",
    "gn:feature_code":"PPL",
    "gn:name":"Iskusovo",
    "gn:population":0,
    "gn:timezone":"Europe/Moscow",
    "iso:country":"RU",
    "name:rus_x_preferred":[
        "\u0418\u0441\u043a\u0443\u0441\u043e\u0432\u043e"
    ],
    "wof:name":"Iskusovo",
    "wof:placetype":"locality"
},
  "geometry": {"coordinates":[42.8056,55.8006],"type":"Point"}
}