{
  "type": "Feature",
  "properties": {
    "gn:admin1_code":"21",
    "gn:asciiname":"Maloye Perepechino",
    "gn:country_code":"RU",
    "gn:dem":113,
    "gn:feature_class":"P",
    "gn:feature_code":"PPL",
    "gn:name":"Maloye Perepechino",
    "gn:population":0,
    "gn:timezone":"Europe/Moscow",
    "iso:country":"RU",
    "name:rus_x_preferred":[
        "\u041c\u0430\u043b\u043e\u0435 \u041f\u0435\u0440\u0435\u043f\u0435\u0447\u0438\u043d\u043e"
    ],
    "name:und_x_variant":[
        "\u041c\u0430\u043b\u043e\u0435 \u041f\u0435\u0440\u0435\u043f\u0435\u0447\u0438\u043d\u043e"
    ],
    "wof:name":"Maloye Perepechino",
    "wof:placetype":"locality"
},
  "geometry": {"coordinates":[40.95,56.75],"type":"Point"}
}