{
  "type": "Feature",
  "properties": {
    "gn:admin1_code":"47",
    "gn:asciiname":"Novyy Byt",
    "gn:country_code":"RU",
    "gn:dem":163,
    "gn:feature_class":"P",
    "gn:feature_code":"PPL",
    "gn:name":"Novyy Byt",
    "gn:population":0,
    "gn:timezone":"Europe/Moscow",
    "iso:country":"RU",
    "name:rus_x_preferred":[
        "\u041d\u043e\u0432\u044b\u0439 \u0411\u044b\u0442"
    ],
    "name:und_x_variant":[
        "\u041d\u043e\u0432\u044b\u0439 \u0411\u044b\u0442"
    ],
    "wof:name":"Novyy Byt",
    "wof:placetype":"locality"
},
  "geometry": {"coordinates":[37.86667,55.91667],"type":"Point"}
}