{
  "type": "Feature",
  "properties": {
    "gn:admin1_code":"25",
    "gn:asciiname":"Satino",
    "gn:country_code":"RU",
    "gn:dem":171,
    "gn:feature_class":"P",
    "gn:feature_code":"PPL",
    "gn:name":"Satino",
    "gn:population":0,
    "gn:timezone":"Europe/Moscow",
    "iso:country":"RU",
    "name:rus_x_preferred":[
        "\u0421\u0430\u0442\u0438\u043d\u043e"
    ],
    "name:und_x_variant":[
        "\u0421\u0430\u0442\u0438\u043d\u043e"
    ],
    "wof:name":"Satino",
    "wof:placetype":"locality"
},
  "geometry": {"coordinates":[36.33028,55.20361],"type":"Point"}
}