{
  "type": "Feature",
  "properties": {
    "gn:admin1_code":"61",
    "gn:asciiname":"Kreydovskiy",
    "gn:country_code":"RU",
    "gn:dem":86,
    "gn:feature_class":"P",
    "gn:feature_code":"PPL",
    "gn:name":"Kreydovskiy",
    "gn:population":0,
    "gn:timezone":"Europe/Moscow",
    "iso:country":"RU",
    "name:rus_x_preferred":[
        "\u041a\u0440\u0435\u0439\u0434\u043e\u0432\u0441\u043a\u0438\u0439"
    ],
    "name:und_x_variant":[
        "\u041a\u0440\u0435\u0439\u0434\u043e\u0432\u0441\u043a\u0438\u0439"
    ],
    "wof:name":"Kreydovskiy",
    "wof:placetype":"locality"
},
  "geometry": {"coordinates":[40.76823,49.26322],"type":"Point"}
}