{
  "type": "Feature",
  "properties": {
    "gn:admin1_code":"69.0",
    "gn:asciiname":"Bol'shaya Pechishenka",
    "gn:country_code":"RU",
    "gn:dem":188,
    "gn:feature_class":"P",
    "gn:feature_code":"PPL",
    "gn:name":"Bol\u2019shaya Pechish\u00ebnka",
    "gn:population":0,
    "gn:timezone":"Europe/Moscow",
    "iso:country":"RU",
    "name:rus_x_preferred":[
        "\u0411\u043e\u043b\u044c\u0448\u0430\u044f \u041f\u0435\u0447\u0438\u0448\u0451\u043d\u043a\u0430"
    ],
    "name:und_x_variant":[
        "Bol\u2019shaya Pechish\u00ebnka"
    ],
    "wof:name":"Bol'shaya Pechishenka",
    "wof:placetype":"locality"
},
  "geometry": {"coordinates":[34.71667,55.71666999999999],"type":"Point"}
}