{
  "type": "Feature",
  "properties": {
    "gn:admin1_code":"16",
    "gn:asciiname":"Krasnomayskaya",
    "gn:country_code":"RU",
    "gn:dem":122,
    "gn:feature_class":"P",
    "gn:feature_code":"PPL",
    "gn:name":"Krasnomayskaya",
    "gn:population":0,
    "gn:timezone":"Europe/Moscow",
    "iso:country":"RU",
    "name:rus_x_preferred":[
        "\u041a\u0440\u0430\u0441\u043d\u043e\u043c\u0430\u0439\u0441\u043a\u0430\u044f"
    ],
    "name:und_x_variant":[
        "Pekhorka",
        "Krasnomayskaya"
    ],
    "wof:name":"Krasnomayskaya",
    "wof:placetype":"locality"
},
  "geometry": {"coordinates":[46.17155,55.03075],"type":"Point"}
}