{
  "type": "Feature",
  "properties": {
    "gn:admin1_code":"55",
    "gn:asciiname":"Shumayevo",
    "gn:country_code":"RU",
    "gn:dem":73,
    "gn:feature_class":"P",
    "gn:feature_code":"PPL",
    "gn:name":"Shumayevo",
    "gn:population":0,
    "gn:timezone":"Asia/Yekaterinburg",
    "iso:country":"RU",
    "name:eng_x_preferred":[
        "Shumayevo"
    ],
    "name:nor_x_preferred":[
        "Sjumajevo"
    ],
    "name:rus_x_preferred":[
        "\u0428\u0443\u043c\u0430\u0435\u0432\u043e"
    ],
    "name:und_x_variant":[
        "Shumayevskiy"
    ],
    "wof:name":"Shumayevo",
    "wof:placetype":"locality"
},
  "geometry": {"coordinates":[52.87412,51.76451],"type":"Point"}
}