{
  "type": "Feature",
  "properties": {
    "gn:admin1_code":"47",
    "gn:asciiname":"Pleshkino",
    "gn:country_code":"RU",
    "gn:dem":176,
    "gn:feature_class":"P",
    "gn:feature_code":"PPL",
    "gn:name":"Pleshkino",
    "gn:population":0,
    "gn:timezone":"Europe/Moscow",
    "iso:country":"RU",
    "name:rus_x_preferred":[
        "\u041f\u043b\u0435\u0448\u043a\u0438\u043d\u043e"
    ],
    "wof:name":"Pleshkino",
    "wof:placetype":"locality"
},
  "geometry": {"coordinates":[37.58429,55.03445],"type":"Point"}
}