{
  "type": "Feature",
  "properties": {
    "gn:admin1_code":"45.0",
    "gn:asciiname":"Podgornyye Shari",
    "gn:country_code":"RU",
    "gn:dem":122,
    "gn:feature_class":"P",
    "gn:feature_code":"PPL",
    "gn:name":"Podgornyye Shari",
    "gn:population":0,
    "gn:timezone":"Europe/Moscow",
    "iso:country":"RU",
    "name:rus_x_preferred":[
        "\u041f\u043e\u0434\u0433\u043e\u0440\u043d\u044b\u0435 \u0428\u0430\u0440\u0438"
    ],
    "name:und_x_variant":[
        "\u041f\u043e\u0434\u0433\u043e\u0440\u043d\u044b\u0435 \u0428\u0430\u0440\u0438"
    ],
    "wof:name":"Podgornyye Shari",
    "wof:placetype":"locality"
},
  "geometry": {"coordinates":[48.80194,56.17194],"type":"Point"}
}