{
  "type": "Feature",
  "properties": {
    "gn:admin1_code":"52",
    "gn:asciiname":"Polist'",
    "gn:country_code":"RU",
    "gn:dem":27,
    "gn:feature_class":"P",
    "gn:feature_code":"PPL",
    "gn:name":"Polist\u2019",
    "gn:population":0,
    "gn:timezone":"Europe/Moscow",
    "iso:country":"RU",
    "name:rus_x_preferred":[
        "\u041f\u043e\u043b\u0438\u0441\u0442\u044c"
    ],
    "name:und_x_variant":[
        "Plevatitsa",
        "Polist\u2019",
        "\u041f\u043e\u043b\u0438\u0441\u0442\u044c"
    ],
    "wof:name":"Polist'",
    "wof:placetype":"locality"
},
  "geometry": {"coordinates":[31.28333,57.93333000000001],"type":"Point"}
}