{
  "type": "Feature",
  "properties": {
    "gn:country":"RU",
    "gn:fcode":"PPL",
    "gn:population":0,
    "iso:country":"RU",
    "name:rus_x_preferred":[
        "\u041f\u0440\u043e\u043d\u0441\u043a\u043e\u0435"
    ],
    "qs:name":"Pronskoye",
    "qs:name_adm0":"Russia",
    "qs:name_adm1":"Moscow Oblast",
    "qs:photos_9r":0,
    "qs:photos_sr":0,
    "qs:placetype":"Town",
    "qs:pop_sr":"0",
    "wd:wordcount":41,
    "wof:name":"Pronskoye",
    "wof:placetype":"locality",
    "wof:population":0
},
  "geometry": {"coordinates":[36.72044,55.63757],"type":"Point"}
}