{
  "type": "Feature",
  "properties": {
    "gn:admin1_code":"81",
    "gn:asciiname":"Slava",
    "gn:country_code":"RU",
    "gn:dem":115,
    "gn:feature_class":"P",
    "gn:feature_code":"PPL",
    "gn:name":"Slava",
    "gn:population":0,
    "gn:timezone":"Europe/Ulyanovsk",
    "iso:country":"RU",
    "name:rus_x_preferred":[
        "\u0421\u043b\u0430\u0432\u0430"
    ],
    "name:und_x_variant":[
        "\u0421\u043b\u0430\u0432\u0430"
    ],
    "wof:name":"Slava",
    "wof:placetype":"locality"
},
  "geometry": {"coordinates":[49.81667,53.93333000000001],"type":"Point"}
}