{
  "type": "Feature",
  "properties": {
    "gn:admin1_code":"77",
    "gn:asciiname":"Naydenka",
    "gn:country_code":"RU",
    "gn:dem":198,
    "gn:feature_class":"P",
    "gn:feature_code":"PPL",
    "gn:name":"Naydenka",
    "gn:population":0,
    "gn:timezone":"Europe/Moscow",
    "iso:country":"RU",
    "name:rus_x_preferred":[
        "\u041d\u0430\u0439\u0434\u0435\u043d\u043a\u0430"
    ],
    "wof:name":"Naydenka",
    "wof:placetype":"locality"
},
  "geometry": {"coordinates":[36.73,58.3467],"type":"Point"}
}