{
  "type": "Feature",
  "properties": {
    "gn:admin1_code":"57",
    "gn:asciiname":"Shurinovka Russkaya",
    "gn:country_code":"RU",
    "gn:dem":206,
    "gn:feature_class":"P",
    "gn:feature_code":"PPL",
    "gn:name":"Shurinovka Russkaya",
    "gn:population":0,
    "gn:timezone":"Europe/Moscow",
    "iso:country":"RU",
    "name:rus_x_preferred":[
        "\u0428\u0443\u0440\u0438\u043d\u043e\u0432\u043a\u0430 \u0420\u0443\u0441\u0441\u043a\u0430\u044f"
    ],
    "name:und_x_variant":[
        "Shurinovka Tatarskaya",
        "Shurinovka Russkaya",
        "\u0428\u0443\u0440\u0438\u043d\u043e\u0432\u043a\u0430 \u0420\u0443\u0441\u0441\u043a\u0430\u044f"
    ],
    "wof:name":"Shurinovka Russkaya",
    "wof:placetype":"locality"
},
  "geometry": {"coordinates":[43.06753,53.76005],"type":"Point"}
}