{
  "type": "Feature",
  "properties": {
    "gn:admin1_code":"6.0",
    "gn:asciiname":"Dunayevo Selo",
    "gn:country_code":"RU",
    "gn:dem":158,
    "gn:feature_class":"P",
    "gn:feature_code":"PPL",
    "gn:name":"Dunayevo Selo",
    "gn:population":0,
    "gn:timezone":"Europe/Moscow",
    "iso:country":"RU",
    "name:rus_x_preferred":[
        "\u0414\u0443\u043d\u0430\u0435\u0432\u043e \u0421\u0435\u043b\u043e"
    ],
    "wof:name":"Dunayevo Selo",
    "wof:placetype":"locality"
},
  "geometry": {"coordinates":[45.1641,62.4191],"type":"Point"}
}