{
  "type": "Feature",
  "properties": {
    "gn:admin1_code":"42",
    "gn:asciiname":"Lomonosovo",
    "gn:cc2":"RU",
    "gn:country_code":"RU",
    "gn:dem":9,
    "gn:feature_class":"P",
    "gn:feature_code":"PPL",
    "gn:name":"Lomonosovo",
    "gn:population":0,
    "gn:timezone":"Europe/Moscow",
    "iso:country":"RU",
    "name:fin_x_preferred":[
        "Santajoki"
    ],
    "name:rus_x_preferred":[
        "\u041b\u043e\u043c\u043e\u043d\u043e\u0441\u043e\u0432\u043e"
    ],
    "name:und_x_variant":[
        "Santayoki",
        "Pukki",
        "Santvioki",
        "Santaioki",
        "Lomonosovo",
        "\u041b\u043e\u043c\u043e\u043d\u043e\u0441\u043e\u0432\u043e",
        "Santajoki"
    ],
    "wof:name":"Lomonosovo",
    "wof:placetype":"locality"
},
  "geometry": {"coordinates":[28.21667,60.56667],"type":"Point"}
}