{
  "type": "Feature",
  "properties": {
    "gn:admin1_code":"10.0",
    "gn:asciiname":"Bolotikhovo",
    "gn:country_code":"RU",
    "gn:dem":170,
    "gn:feature_class":"P",
    "gn:feature_code":"PPL",
    "gn:name":"Bolotikhovo",
    "gn:population":0,
    "gn:timezone":"Europe/Moscow",
    "iso:country":"RU",
    "name:rus_x_preferred":[
        "\u0411\u043e\u043b\u043e\u0442\u0438\u0445\u043e\u0432\u043e"
    ],
    "name:und_x_variant":[
        "Bolot\u2019khovo",
        "Bolotikhovo"
    ],
    "wof:name":"Bolotikhovo",
    "wof:placetype":"locality"
},
  "geometry": {"coordinates":[33.5936,53.17109],"type":"Point"}
}