{
  "type": "Feature",
  "properties": {
    "gn:admin1_code":"85",
    "gn:asciiname":"Irdanovo",
    "gn:country_code":"RU",
    "gn:dem":180,
    "gn:feature_class":"P",
    "gn:feature_code":"PPL",
    "gn:name":"Irdanovo",
    "gn:population":0,
    "gn:timezone":"Europe/Moscow",
    "iso:country":"RU",
    "name:eng_x_preferred":[
        "Irdanovo"
    ],
    "name:nor_x_preferred":[
        "Irdanovo"
    ],
    "name:rus_x_preferred":[
        "\u0418\u0440\u0434\u0430\u043d\u043e\u0432\u043e"
    ],
    "name:und_x_variant":[
        "Irdatovo"
    ],
    "wof:name":"Irdanovo",
    "wof:placetype":"locality"
},
  "geometry": {"coordinates":[45.51174,59.5498],"type":"Point"}
}