{
  "type": "Feature",
  "properties": {
    "gn:admin1_code":"33",
    "gn:asciiname":"Trushkiny",
    "gn:country_code":"RU",
    "gn:dem":166,
    "gn:feature_class":"P",
    "gn:feature_code":"PPL",
    "gn:name":"Trushkiny",
    "gn:population":0,
    "gn:timezone":"Europe/Kirov",
    "iso:country":"RU",
    "name:rus_x_preferred":[
        "\u0422\u0440\u0443\u0448\u043a\u0438\u043d\u044b"
    ],
    "wof:name":"Trushkiny",
    "wof:placetype":"locality"
},
  "geometry": {"coordinates":[49.8845,58.3184],"type":"Point"}
}