{
  "type": "Feature",
  "properties": {
    "gn:admin1_code":"8",
    "gn:asciiname":"Gadel'bayevo",
    "gn:country_code":"RU",
    "gn:dem":532,
    "gn:feature_class":"P",
    "gn:feature_code":"PPL",
    "gn:name":"Gadel\u2019bayevo",
    "gn:population":0,
    "gn:timezone":"Asia/Yekaterinburg",
    "iso:country":"RU",
    "name:rus_x_preferred":[
        "\u0413\u0430\u0434\u0435\u043b\u044c\u0431\u0430\u0435\u0432\u043e"
    ],
    "name:und_x_variant":[
        "Nizhneye Gadel\u2019bayevo",
        "Gadel\u2019bayevo",
        "Gabel\u2019bayevo"
    ],
    "wof:name":"Gadel'bayevo",
    "wof:placetype":"locality"
},
  "geometry": {"coordinates":[57.9333,52.6144],"type":"Point"}
}