{
  "type": "Feature",
  "properties": {
    "gn:admin1_code":"12",
    "gn:asciiname":"Obil'nyy",
    "gn:country_code":"RU",
    "gn:dem":62,
    "gn:feature_class":"P",
    "gn:feature_code":"PPL",
    "gn:name":"Obil\u2019nyy",
    "gn:population":0,
    "gn:timezone":"Europe/Moscow",
    "iso:country":"RU",
    "name:rus_x_preferred":[
        "\u041e\u0431\u0438\u043b\u044c\u043d\u044b\u0439"
    ],
    "name:und_x_variant":[
        "Obil\u2019nyy"
    ],
    "wof:name":"Obil'nyy",
    "wof:placetype":"locality"
},
  "geometry": {"coordinates":[45.74892,43.57961],"type":"Point"}
}