{
  "type": "Feature",
  "properties": {
    "gn:admin1_code":"41",
    "gn:asciiname":"Sukhareva",
    "gn:country_code":"RU",
    "gn:dem":185,
    "gn:feature_class":"P",
    "gn:feature_code":"PPL",
    "gn:name":"Sukhar\u00ebva",
    "gn:population":0,
    "gn:timezone":"Europe/Moscow",
    "iso:country":"RU",
    "name:rus_x_preferred":[
        "\u0421\u0443\u0445\u0430\u0440\u0451\u0432\u0430"
    ],
    "name:und_x_variant":[
        "Sukhar\u00ebva",
        "Sukharevo"
    ],
    "wof:name":"Sukhareva",
    "wof:placetype":"locality"
},
  "geometry": {"coordinates":[35.5785,52.15600000000001],"type":"Point"}
}