{
  "type": "Feature",
  "properties": {
    "gn:admin1_code":"57",
    "gn:asciiname":"Vorona",
    "gn:country_code":"RU",
    "gn:dem":186,
    "gn:feature_class":"P",
    "gn:feature_code":"PPL",
    "gn:name":"Vorona",
    "gn:population":0,
    "gn:timezone":"Europe/Moscow",
    "iso:country":"RU",
    "name:eng_x_preferred":[
        "Vorona"
    ],
    "name:nor_x_preferred":[
        "Vorona"
    ],
    "name:rus_x_preferred":[
        "\u0412\u043e\u0440\u043e\u043d\u0430"
    ],
    "wof:name":"Vorona",
    "wof:placetype":"locality"
},
  "geometry": {"coordinates":[43.42968,53.2501],"type":"Point"}
}