{
  "type": "Feature",
  "properties": {
    "gn:admin1_code":"60",
    "gn:asciiname":"Tyut'kovo",
    "gn:country_code":"RU",
    "gn:dem":88,
    "gn:feature_class":"P",
    "gn:feature_code":"PPL",
    "gn:name":"Tyut\u2019kovo",
    "gn:population":0,
    "gn:timezone":"Europe/Moscow",
    "iso:country":"RU",
    "name:rus_x_preferred":[
        "\u0422\u044e\u0442\u044c\u043a\u043e\u0432\u043e"
    ],
    "name:und_x_variant":[
        "Tyut\u2019kova",
        "Tyut\u2019kovo"
    ],
    "wof:name":"Tyut'kovo",
    "wof:placetype":"locality"
},
  "geometry": {"coordinates":[30.16489,57.6316],"type":"Point"}
}