{
  "type": "Feature",
  "properties": {
    "gn:admin1_code":"25",
    "gn:asciiname":"Lychevo",
    "gn:country_code":"RU",
    "gn:dem":151,
    "gn:feature_class":"P",
    "gn:feature_code":"PPL",
    "gn:name":"Lych\u00ebvo",
    "gn:population":0,
    "gn:timezone":"Europe/Moscow",
    "iso:country":"RU",
    "name:nor_x_preferred":[
        "Lytsjovo"
    ],
    "name:rus_x_preferred":[
        "\u041b\u044b\u0447\u0451\u0432\u043e"
    ],
    "name:und_x_variant":[
        "Lych\u00ebvo"
    ],
    "wof:name":"Lychevo",
    "wof:placetype":"locality"
},
  "geometry": {"coordinates":[36.11743,54.71675],"type":"Point"}
}