{
  "type": "Feature",
  "properties": {
    "gn:admin1_code":"51",
    "gn:asciiname":"Bezhanovo",
    "gn:country_code":"RU",
    "gn:dem":176,
    "gn:feature_class":"P",
    "gn:feature_code":"PPL",
    "gn:name":"Bezhanovo",
    "gn:population":0,
    "gn:timezone":"Europe/Moscow",
    "iso:country":"RU",
    "name:bul_x_preferred":[
        "\u0411\u0435\u0436\u0430\u043d\u043e\u0432\u043e"
    ],
    "name:fra_x_preferred":[
        "Bejanovo"
    ],
    "name:ron_x_preferred":[
        "Bejanovo"
    ],
    "name:rus_x_preferred":[
        "\u0411\u0435\u0436\u0430\u043d\u043e\u0432\u043e"
    ],
    "name:ukr_x_preferred":[
        "\u0411\u0435\u0436\u0430\u043d\u043e\u0432\u043e"
    ],
    "wof:name":"Bezhanovo",
    "wof:placetype":"locality"
},
  "geometry": {"coordinates":[42.6049,55.8747],"type":"Point"}
}