{
  "type": "Feature",
  "properties": {
    "iso:country":"RU",
    "qs:name":"Tver'",
    "qs:name_adm0":"Russia",
    "qs:name_adm1":"Tver Oblast",
    "qs:photos":1928,
    "qs:photos_1k":391,
    "qs:photos_9k":9,
    "qs:photos_9r":9,
    "qs:photos_all":1928,
    "qs:photos_sr":15,
    "qs:placetype":"Town",
    "qs:pop_sr":"0",
    "wd:wordcount":4267,
    "wof:name":"Tver'",
    "wof:placetype":"locality"
},
  "geometry": {"coordinates":[35.903491,56.86061],"type":"Point"}
}