{
  "type": "Feature",
  "properties": {
    "gn:admin1_code":"83",
    "gn:asciiname":"Obrashchikha",
    "gn:country_code":"RU",
    "gn:dem":184,
    "gn:feature_class":"P",
    "gn:feature_code":"PPL",
    "gn:name":"Obrashchikha",
    "gn:population":0,
    "gn:timezone":"Europe/Moscow",
    "iso:country":"RU",
    "name:rus_x_preferred":[
        "\u041e\u0431\u0440\u0430\u0449\u0438\u0445\u0430"
    ],
    "name:und_x_variant":[
        "Obrazchikha",
        "Obrashchikha"
    ],
    "wof:name":"Obrashchikha",
    "wof:placetype":"locality"
},
  "geometry": {"coordinates":[40.11857,56.32904],"type":"Point"}
}