{
  "type": "Feature",
  "properties": {
    "gn:country":"RU",
    "gn:fcode":"PPL",
    "gn:population":14482,
    "iso:country":"RU",
    "name:bel_x_preferred":[
        "\u041f\u0430\u0441\u0451\u043b\u0430\u043a \u041a\u043b\u0456\u043c\u0430\u0432\u0430"
    ],
    "name:ceb_x_preferred":[
        "Klimovo"
    ],
    "name:che_x_preferred":[
        "\u041a\u043b\u0438\u043c\u043e\u0432\u043e"
    ],
    "name:deu_x_preferred":[
        "Klimowo"
    ],
    "name:eng_x_preferred":[
        "Klimovo"
    ],
    "name:fin_x_preferred":[
        "Klimovo"
    ],
    "name:ita_x_preferred":[
        "Klimovo"
    ],
    "name:jpn_x_preferred":[
        "\u30af\u30ea\u30fc\u30e2\u30d5"
    ],
    "name:lav_x_preferred":[
        "K\u013cimova"
    ],
    "name:nld_x_preferred":[
        "Klimovo"
    ],
    "name:nor_x_preferred":[
        "Klimovo"
    ],
    "name:pol_x_preferred":[
        "Klimowo"
    ],
    "name:rus_x_preferred":[
        "\u041a\u043b\u0438\u043c\u043e\u0432\u043e"
    ],
    "name:ukr_x_preferred":[
        "\u041a\u043b\u0438\u043c\u043e\u0432\u043e"
    ],
    "name:und_x_variant":[
        "Klimov"
    ],
    "qs:name":"Klimovo",
    "qs:photos_9r":0,
    "qs:photos_sr":0,
    "qs:pop_sr":"6",
    "wd:wordcount":23,
    "wof:name":"Klimovo",
    "wof:placetype":"locality",
    "wof:population":14482
},
  "geometry": {"coordinates":[32.19233,52.38053],"type":"Point"}
}