{
  "type": "Feature",
  "properties": {
    "gn:admin1_code":"60",
    "gn:asciiname":"Shmoyly",
    "gn:country_code":"RU",
    "gn:dem":63,
    "gn:feature_class":"P",
    "gn:feature_code":"PPL",
    "gn:name":"Shmoyly",
    "gn:population":0,
    "gn:timezone":"Europe/Moscow",
    "iso:country":"RU",
    "name:rus_x_preferred":[
        "\u0428\u043c\u043e\u0439\u043b\u044b"
    ],
    "wof:name":"Shmoyly",
    "wof:placetype":"locality"
},
  "geometry": {"coordinates":[28.49031,57.34486],"type":"Point"}
}