{
  "type": "Feature",
  "properties": {
    "gn:admin1_code":"46.0",
    "gn:asciiname":"Krasnoflotets",
    "gn:country_code":"RU",
    "gn:dem":146,
    "gn:feature_class":"P",
    "gn:feature_code":"PPL",
    "gn:name":"Krasnoflotets",
    "gn:population":0,
    "gn:timezone":"Europe/Moscow",
    "iso:country":"RU",
    "name:rus_x_preferred":[
        "\u041a\u0440\u0430\u0441\u043d\u043e\u0444\u043b\u043e\u0442\u0435\u0446"
    ],
    "wof:name":"Krasnoflotets",
    "wof:placetype":"locality"
},
  "geometry": {"coordinates":[44.0713,54.50892],"type":"Point"}
}