{
  "type": "Feature",
  "properties": {
    "gn:admin1_code":"49",
    "gn:asciiname":"Luostari",
    "gn:country_code":"RU",
    "gn:dem":20,
    "gn:feature_class":"P",
    "gn:feature_code":"PPL",
    "gn:name":"Luostari",
    "gn:population":0,
    "gn:timezone":"Europe/Moscow",
    "iso:country":"RU",
    "name:che_x_preferred":[
        "\u041b\u0443\u043e\u0441\u0442\u0430\u0440\u0438"
    ],
    "name:eng_x_preferred":[
        "Luostari"
    ],
    "name:fin_x_preferred":[
        "Luostari"
    ],
    "name:ita_x_preferred":[
        "Luostari"
    ],
    "name:nor_x_preferred":[
        "Luostari"
    ],
    "name:pol_x_preferred":[
        "\u0141uostari"
    ],
    "name:rus_x_preferred":[
        "\u041b\u0443\u043e\u0441\u0442\u0430\u0440\u0438"
    ],
    "name:srp_x_preferred":[
        "\u041b\u0443\u043e\u0441\u0442\u0430\u0440\u0438"
    ],
    "name:swe_x_preferred":[
        "Luostari"
    ],
    "name:ukr_x_preferred":[
        "\u041b\u0443\u043e\u0441\u0442\u0430\u0440\u0456"
    ],
    "name:und_x_variant":[
        "Yl\u00e4luostari"
    ],
    "wof:name":"Luostari",
    "wof:placetype":"locality"
},
  "geometry": {"coordinates":[31.04955,69.42196],"type":"Point"}
}