{
  "type": "Feature",
  "properties": {
    "gn:admin1_code":"38",
    "gn:asciiname":"Romashki",
    "gn:country_code":"RU",
    "gn:dem":28,
    "gn:feature_class":"P",
    "gn:feature_code":"PPL",
    "gn:name":"Romashki",
    "gn:population":0,
    "gn:timezone":"Europe/Moscow",
    "iso:country":"RU",
    "name:rus_x_preferred":[
        "\u0420\u043e\u043c\u0430\u0448\u043a\u0438"
    ],
    "name:und_x_variant":[
        "Romanshki",
        "Romashki",
        "\u0420\u043e\u043c\u0430\u0448\u043a\u0438"
    ],
    "wof:name":"Romashki",
    "wof:placetype":"locality"
},
  "geometry": {"coordinates":[39.22782,46.37894],"type":"Point"}
}