{
  "type": "Feature",
  "properties": {
    "gn:admin1_code":"8.0",
    "gn:asciiname":"Baimovo",
    "gn:country_code":"RU",
    "gn:dem":566,
    "gn:feature_class":"P",
    "gn:feature_code":"PPL",
    "gn:name":"Baimovo",
    "gn:population":0,
    "gn:timezone":"Asia/Yekaterinburg",
    "iso:country":"RU",
    "name:aze_x_preferred":[
        "Bay\u0131m"
    ],
    "name:bak_x_preferred":[
        "\u0411\u0430\u0439\u044b\u043c"
    ],
    "name:che_x_preferred":[
        "\u0411\u0430\u0438\u043c\u043e\u0432\u043e"
    ],
    "name:eng_x_preferred":[
        "Baimovo"
    ],
    "name:hye_x_preferred":[
        "\u0532\u0561\u056b\u0574\u0578\u057e\u0578"
    ],
    "name:kat_x_preferred":[
        "\u10d1\u10d0\u10d8\u10db\u10dd\u10d5\u10dd"
    ],
    "name:kaz_x_preferred":[
        "\u0411\u0430\u0439\u044b\u043c"
    ],
    "name:kir_x_preferred":[
        "\u0411\u0430\u0439\u044b\u043c"
    ],
    "name:nor_x_preferred":[
        "Baimovo"
    ],
    "name:rus_x_preferred":[
        "\u0411\u0430\u0438\u043c\u043e\u0432\u043e"
    ],
    "name:tat_x_preferred":[
        "\u0411\u0430\u0435\u043c"
    ],
    "name:ukr_x_preferred":[
        "\u0411\u0430\u0457\u043c\u043e\u0432\u043e"
    ],
    "name:und_x_variant":[
        "Baimova",
        "\u0411\u0430\u0438\u043c\u043e\u0432\u043e",
        "Baimovo"
    ],
    "wof:name":"Baimovo",
    "wof:placetype":"locality"
},
  "geometry": {"coordinates":[57.9962,52.8643],"type":"Point"}
}