{
  "type": "Feature",
  "properties": {
    "gn:admin1_code":"76.0",
    "gn:asciiname":"Bakino",
    "gn:country_code":"RU",
    "gn:dem":153,
    "gn:feature_class":"P",
    "gn:feature_code":"PPL",
    "gn:name":"Bakino",
    "gn:population":0,
    "gn:timezone":"Europe/Moscow",
    "iso:country":"RU",
    "name:nor_x_preferred":[
        "Bakino"
    ],
    "name:rus_x_preferred":[
        "\u0411\u0430\u043a\u0438\u043d\u043e"
    ],
    "wof:name":"Bakino",
    "wof:placetype":"locality"
},
  "geometry": {"coordinates":[36.10285,53.72015],"type":"Point"}
}