{
  "type": "Feature",
  "properties": {
    "gn:admin1_code":"77",
    "gn:asciiname":"Zavody",
    "gn:country_code":"RU",
    "gn:dem":136,
    "gn:feature_class":"P",
    "gn:feature_code":"PPL",
    "gn:name":"Zavody",
    "gn:population":0,
    "gn:timezone":"Europe/Moscow",
    "iso:country":"RU",
    "name:rus_x_preferred":[
        "\u0417\u0430\u0432\u043e\u0434\u044b"
    ],
    "name:und_x_variant":[
        "\u0417\u0430\u0432\u043e\u0434\u044b"
    ],
    "wof:name":"Zavody",
    "wof:placetype":"locality"
},
  "geometry": {"coordinates":[37.0317,57.3464],"type":"Point"}
}