{
  "type": "Feature",
  "properties": {
    "gn:admin1_code":"11",
    "gn:asciiname":"Khurtaga",
    "gn:country_code":"RU",
    "gn:dem":938,
    "gn:feature_class":"P",
    "gn:feature_code":"PPL",
    "gn:name":"Khurtaga",
    "gn:population":0,
    "gn:timezone":"Asia/Irkutsk",
    "iso:country":"RU",
    "name:eng_x_preferred":[
        "Khurtaga"
    ],
    "name:nor_x_preferred":[
        "Khurtuga"
    ],
    "name:rus_x_preferred":[
        "\u0425\u0443\u0440\u0442\u0443\u0433\u0430"
    ],
    "name:rus_x_variant":[
        "\u0425\u0443\u0440\u0442\u0430\u0433\u0430"
    ],
    "name:und_x_variant":[
        "Khurtarga"
    ],
    "wof:name":"Khurtaga",
    "wof:placetype":"locality"
},
  "geometry": {"coordinates":[103.94159999999999,50.4442],"type":"Point"}
}