{
  "type": "Feature",
  "properties": {
    "gn:admin1_code":"23",
    "gn:asciiname":"Brigadnoye",
    "gn:country_code":"RU",
    "gn:dem":9,
    "gn:feature_class":"P",
    "gn:feature_code":"PPL",
    "gn:name":"Brigadnoye",
    "gn:population":0,
    "gn:timezone":"Europe/Kaliningrad",
    "iso:country":"RU",
    "name:rus_x_preferred":[
        "\u0411\u0440\u0438\u0433\u0430\u0434\u043d\u043e\u0435"
    ],
    "name:und_x_variant":[
        "Schakaulack",
        "Malaya Lipovka",
        "Brigadnoye"
    ],
    "wof:name":"Brigadnoye",
    "wof:placetype":"locality"
},
  "geometry": {"coordinates":[21.05229,54.82038000000001],"type":"Point"}
}