{
  "type": "Feature",
  "properties": {
    "gn:admin1_code":"57.0",
    "gn:asciiname":"Chernoyar",
    "gn:country_code":"RU",
    "gn:dem":107,
    "gn:feature_class":"P",
    "gn:feature_code":"PPL",
    "gn:name":"Chernoyar",
    "gn:population":0,
    "gn:timezone":"Europe/Moscow",
    "iso:country":"RU",
    "name:eng_x_preferred":[
        "Chernoyar"
    ],
    "name:nor_x_preferred":[
        "Tsjernojar"
    ],
    "name:rus_x_preferred":[
        "\u0427\u0435\u0440\u043d\u043e\u044f\u0440"
    ],
    "name:und_x_variant":[
        "Chernyar"
    ],
    "wof:name":"Chernoyar",
    "wof:placetype":"locality"
},
  "geometry": {"coordinates":[42.2494,53.80385],"type":"Point"}
}