{
  "type": "Feature",
  "properties": {
    "gn:admin1_code":"91",
    "gn:asciiname":"Talaya",
    "gn:country_code":"RU",
    "gn:dem":227,
    "gn:feature_class":"P",
    "gn:feature_code":"PPL",
    "gn:name":"Talaya",
    "gn:population":0,
    "gn:timezone":"Asia/Krasnoyarsk",
    "iso:country":"RU",
    "name:bel_x_preferred":[
        "\u0422\u0430\u043b\u0430\u044f"
    ],
    "name:che_x_preferred":[
        "\u0422\u0430\u043b\u0430\u044f"
    ],
    "name:deu_x_preferred":[
        "Talaja"
    ],
    "name:eng_x_preferred":[
        "Talaya"
    ],
    "name:hye_x_preferred":[
        "\u054f\u0561\u056c\u0561\u0575\u0561"
    ],
    "name:ita_x_preferred":[
        "Talaja"
    ],
    "name:pol_x_preferred":[
        "Ta\u0142aja"
    ],
    "name:rus_x_preferred":[
        "\u0422\u0430\u043b\u0430\u044f"
    ],
    "name:rus_x_variant":[
        "\u0422\u0430\u043b\u043e\u0435"
    ],
    "name:und_x_variant":[
        "Tal\u2019skoye"
    ],
    "wof:name":"Talaya",
    "wof:placetype":"locality"
},
  "geometry": {"coordinates":[92.7525,56.48556],"type":"Point"}
}