{
  "type": "Feature",
  "properties": {
    "gn:admin1_code":"4",
    "gn:asciiname":"Barsukovo",
    "gn:country_code":"RU",
    "gn:dem":124,
    "gn:feature_class":"P",
    "gn:feature_code":"PPL",
    "gn:name":"Barsukovo",
    "gn:population":0,
    "gn:timezone":"Asia/Barnaul",
    "iso:country":"RU",
    "name:eng_x_preferred":[
        "Barsukovo"
    ],
    "name:nor_x_preferred":[
        "Barsukovo"
    ],
    "name:rus_x_preferred":[
        "\u0411\u0430\u0440\u0441\u0443\u043a\u043e\u0432\u043e"
    ],
    "name:und_x_variant":[
        "\u0411\u0430\u0440\u0441\u0443\u043a\u043e\u0432\u043e",
        "Barsukovo"
    ],
    "wof:name":"Barsukovo",
    "wof:placetype":"locality"
},
  "geometry": {"coordinates":[83.2752,53.5001],"type":"Point"}
}