{
  "type": "Feature",
  "properties": {
    "iso:country":"RU",
    "qs:name":"Ivan'kovo",
    "qs:name_adm0":"Russia",
    "qs:name_adm1":"Moscow Oblast",
    "qs:photos":73,
    "qs:photos_1k":15,
    "qs:photos_9k":1,
    "qs:photos_9r":2,
    "qs:photos_all":73,
    "qs:photos_sr":2,
    "qs:placetype":"Suburb",
    "qs:pop_sr":"0",
    "wof:name":"Ivan'kovo",
    "wof:placetype":"neighbourhood"
},
  "geometry": {"coordinates":[37.1858175,56.7501935],"type":"Point"}
}