{
  "type": "Feature",
  "properties": {
    "gn:admin1_code":"49.0",
    "gn:asciiname":"Babino",
    "gn:country_code":"RU",
    "gn:dem":142,
    "gn:feature_class":"P",
    "gn:feature_code":"PPL",
    "gn:name":"Babino",
    "gn:population":0,
    "gn:timezone":"Europe/Moscow",
    "iso:country":"RU",
    "name:ceb_x_preferred":[
        "Babino"
    ],
    "name:est_x_preferred":[
        "Babino"
    ],
    "name:fin_x_preferred":[
        "Akkala"
    ],
    "name:fra_x_preferred":[
        "Babino"
    ],
    "name:hye_x_preferred":[
        "\u0532\u0561\u0562\u056b\u0576\u0578"
    ],
    "name:mkd_x_preferred":[
        "\u0411\u0430\u0431\u0438\u043d\u043e"
    ],
    "name:nor_x_preferred":[
        "Babino"
    ],
    "name:pol_x_preferred":[
        "Babino"
    ],
    "name:rus_x_preferred":[
        "\u0411\u0430\u0431\u0438\u043d\u043e"
    ],
    "name:slv_x_preferred":[
        "Babino"
    ],
    "name:srp_x_preferred":[
        "\u0411\u0430\u0431\u0438\u043d\u043e"
    ],
    "name:swe_x_preferred":[
        "Babino"
    ],
    "name:ukr_x_preferred":[
        "\u0411\u0430\u0431\u0438\u043d\u043e"
    ],
    "wof:name":"Babino",
    "wof:placetype":"locality"
},
  "geometry": {"coordinates":[31.85,67.55],"type":"Point"}
}