{
  "type": "Feature",
  "properties": {
    "gn:admin1_code":"60",
    "gn:asciiname":"Gryazkovo",
    "gn:country_code":"RU",
    "gn:dem":66,
    "gn:feature_class":"P",
    "gn:feature_code":"PPL",
    "gn:name":"Gryazkovo",
    "gn:population":0,
    "gn:timezone":"Europe/Moscow",
    "iso:country":"RU",
    "name:rus_x_preferred":[
        "\u0413\u0440\u044f\u0437\u043a\u043e\u0432\u043e"
    ],
    "name:und_x_variant":[
        "Gryazkova",
        "Gryazkovo"
    ],
    "wof:name":"Gryazkovo",
    "wof:placetype":"locality"
},
  "geometry": {"coordinates":[29.17816,58.59874],"type":"Point"}
}