{
  "type": "Feature",
  "properties": {
    "gn:admin1_code":"45",
    "gn:asciiname":"Kordemuchash",
    "gn:country_code":"RU",
    "gn:dem":141,
    "gn:feature_class":"P",
    "gn:feature_code":"PPL",
    "gn:name":"Kordemuchash",
    "gn:population":0,
    "gn:timezone":"Europe/Moscow",
    "iso:country":"RU",
    "name:rus_x_preferred":[
        "\u041a\u043e\u0440\u0434\u0435\u043c\u0443\u0447\u0430\u0448"
    ],
    "name:und_x_variant":[
        "Kordemushan",
        "Kordemuchash"
    ],
    "wof:name":"Kordemuchash",
    "wof:placetype":"locality"
},
  "geometry": {"coordinates":[48.45917,56.89944000000001],"type":"Point"}
}