{
  "type": "Feature",
  "properties": {
    "gn:admin1_code":"61",
    "gn:asciiname":"Chicherin",
    "gn:country_code":"RU",
    "gn:dem":43,
    "gn:feature_class":"P",
    "gn:feature_code":"PPL",
    "gn:name":"Chicherin",
    "gn:population":0,
    "gn:timezone":"Europe/Moscow",
    "iso:country":"RU",
    "name:rus_x_preferred":[
        "\u0427\u0438\u0447\u0435\u0440\u0438\u043d"
    ],
    "wof:name":"Chicherin",
    "wof:placetype":"locality"
},
  "geometry": {"coordinates":[40.82241,46.38176],"type":"Point"}
}