{
  "type": "Feature",
  "properties": {
    "gn:admin1_code":"61",
    "gn:asciiname":"Illarionov",
    "gn:country_code":"RU",
    "gn:dem":82,
    "gn:feature_class":"P",
    "gn:feature_code":"PPL",
    "gn:name":"Illarionov",
    "gn:population":0,
    "gn:timezone":"Europe/Moscow",
    "iso:country":"RU",
    "name:eng_x_preferred":[
        "Illarionov"
    ],
    "name:nor_x_preferred":[
        "Illarionov"
    ],
    "name:rus_x_preferred":[
        "\u0418\u043b\u043b\u0430\u0440\u0438\u043e\u043d\u043e\u0432"
    ],
    "name:und_x_variant":[
        "\u0418\u043b\u043b\u0430\u0440\u0438\u043e\u043d\u043e\u0432",
        "Illarionov"
    ],
    "wof:name":"Illarionov",
    "wof:placetype":"locality"
},
  "geometry": {"coordinates":[42.00051,49.13693],"type":"Point"}
}