{
  "type": "Feature",
  "properties": {
    "gn:admin1_code":"4",
    "gn:asciiname":"Sverdlovskoye",
    "gn:country_code":"RU",
    "gn:dem":177,
    "gn:feature_class":"P",
    "gn:feature_code":"PPL",
    "gn:name":"Sverdlovskoye",
    "gn:population":0,
    "gn:timezone":"Asia/Barnaul",
    "iso:country":"RU",
    "name:eng_x_preferred":[
        "Sverdlovskoye"
    ],
    "name:nor_x_preferred":[
        "Sverdlovskoje"
    ],
    "name:rus_x_preferred":[
        "\u0421\u0432\u0435\u0440\u0434\u043b\u043e\u0432\u0441\u043a\u043e\u0435"
    ],
    "name:und_x_variant":[
        "Bogoslovka",
        "Bogoslovskiy",
        "\u0421\u0432\u0435\u0440\u0434\u043b\u043e\u0432\u0441\u043a\u043e\u0435",
        "Sverdlovskoye"
    ],
    "wof:name":"Sverdlovskoye",
    "wof:placetype":"locality"
},
  "geometry": {"coordinates":[79.66800000000001,53.3266],"type":"Point"}
}