{
  "type": "Feature",
  "properties": {
    "gn:admin1_code":"85.0",
    "gn:asciiname":"Mikhalkovo",
    "gn:country_code":"RU",
    "gn:dem":133,
    "gn:feature_class":"P",
    "gn:feature_code":"PPL",
    "gn:name":"Mikhalkovo",
    "gn:population":0,
    "gn:timezone":"Europe/Moscow",
    "iso:country":"RU",
    "name:rus_x_preferred":[
        "\u041c\u0438\u0445\u0430\u043b\u043a\u043e\u0432\u043e"
    ],
    "wof:name":"Mikhalkovo",
    "wof:placetype":"locality"
},
  "geometry": {"coordinates":[40.96795,58.83739],"type":"Point"}
}