{
  "type": "Feature",
  "properties": {
    "gn:admin1_code":"53",
    "gn:asciiname":"Maynak",
    "gn:country_code":"RU",
    "gn:dem":133,
    "gn:feature_class":"P",
    "gn:feature_code":"PPL",
    "gn:name":"Maynak",
    "gn:population":0,
    "gn:timezone":"Asia/Novosibirsk",
    "iso:country":"RU",
    "name:rus_x_preferred":[
        "\u041c\u0430\u0439\u043d\u0430\u043a"
    ],
    "wof:name":"Maynak",
    "wof:placetype":"locality"
},
  "geometry": {"coordinates":[80.48333000000002,55.63333000000001],"type":"Point"}
}