{
  "type": "Feature",
  "properties": {
    "gn:admin1_code":"8.0",
    "gn:asciiname":"Andreyevskoye",
    "gn:country_code":"RU",
    "gn:dem":205,
    "gn:feature_class":"P",
    "gn:feature_code":"PPL",
    "gn:name":"Andreyevskoye",
    "gn:population":0,
    "gn:timezone":"Asia/Yekaterinburg",
    "iso:country":"RU",
    "name:nor_x_preferred":[
        "Andrejevskoje"
    ],
    "name:rus_x_preferred":[
        "\u0410\u043d\u0434\u0440\u0435\u0435\u0432\u0441\u043a\u043e\u0435"
    ],
    "wof:name":"Andreyevskoye",
    "wof:placetype":"locality"
},
  "geometry": {"coordinates":[56.53333000000001,55.23333],"type":"Point"}
}