{
  "type": "Feature",
  "properties": {
    "gn:country":"RU",
    "gn:fcode":"PPL",
    "gn:population":6689,
    "iso:country":"RU",
    "name:che_x_preferred":[
        "\u0427\u0435\u0440\u043d\u044c"
    ],
    "name:deu_x_preferred":[
        "Tschern"
    ],
    "name:eng_x_preferred":[
        "Chern'"
    ],
    "name:eng_x_variant":[
        "Tchern"
    ],
    "name:fra_x_preferred":[
        "Tchern"
    ],
    "name:hye_x_preferred":[
        "\u0549\u0565\u0580\u0576"
    ],
    "name:ita_x_preferred":[
        "\u010cern'"
    ],
    "name:jpn_x_preferred":[
        "\u30c1\u30a7\u30eb\u30cb"
    ],
    "name:nor_x_preferred":[
        "Tsjern"
    ],
    "name:rus_x_preferred":[
        "\u0427\u0435\u0440\u043d\u044c"
    ],
    "qs_pg:aaroncc":"RU",
    "qs_pg:gn_country":"RU",
    "qs_pg:gn_fcode":"PPL",
    "qs_pg:gn_pop":6689,
    "qs_pg:name":"Chern\u2019",
    "qs_pg:photos_9r":0,
    "qs_pg:photos_sr":0,
    "qs_pg:pop_sr":5,
    "qs_pg:qs_pg_placetype":"locality",
    "wof:name":"Chern\u2019",
    "wof:placetype":"locality",
    "wof:population":6689
},
  "geometry": {"coordinates":[36.9145,53.45232],"type":"Point"}
}