{
  "type": "Feature",
  "properties": {
    "gn:admin1_code":"77",
    "gn:asciiname":"Baragino",
    "gn:country_code":"RU",
    "gn:dem":208,
    "gn:feature_class":"P",
    "gn:feature_code":"PPL",
    "gn:name":"Baragino",
    "gn:population":0,
    "gn:timezone":"Europe/Moscow",
    "iso:country":"RU",
    "name:nor_x_preferred":[
        "Baragino"
    ],
    "name:rus_x_preferred":[
        "\u0411\u0430\u0440\u0430\u0433\u0438\u043d\u043e"
    ],
    "wof:name":"Baragino",
    "wof:placetype":"locality"
},
  "geometry": {"coordinates":[33.43673,56.86745],"type":"Point"}
}