{
  "type": "Feature",
  "properties": {
    "gn:admin1_code":"25",
    "gn:admin2_code":"525083",
    "gn:asciiname":"Moshchiny",
    "gn:country_code":"RU",
    "gn:dem":193,
    "gn:feature_class":"P",
    "gn:feature_code":"PPL",
    "gn:name":"Moshchiny",
    "gn:population":0,
    "gn:timezone":"Europe/Moscow",
    "iso:country":"RU",
    "name:rus_x_preferred":[
        "\u041c\u043e\u0449\u0438\u043d\u044b"
    ],
    "name:und_x_variant":[
        "\u041c\u043e\u0449\u0438\u043d\u044b"
    ],
    "wof:name":"Moshchiny",
    "wof:placetype":"locality"
},
  "geometry": {"coordinates":[34.99111,54.59083],"type":"Point"}
}