{
  "type": "Feature",
  "properties": {
    "gn:admin1_code":"93",
    "gn:asciiname":"Vtoraya Sukhaya",
    "gn:country_code":"RU",
    "gn:dem":675,
    "gn:feature_class":"P",
    "gn:feature_code":"PPL",
    "gn:name":"Vtoraya Sukhaya",
    "gn:population":0,
    "gn:timezone":"Asia/Chita",
    "iso:country":"RU",
    "name:rus_x_preferred":[
        "\u0412\u0442\u043e\u0440\u0430\u044f \u0421\u0443\u0445\u0430\u044f"
    ],
    "wof:name":"Vtoraya Sukhaya",
    "wof:placetype":"locality"
},
  "geometry": {"coordinates":[118.67999,53.86921],"type":"Point"}
}