{
  "type": "Feature",
  "properties": {
    "gn:admin1_code":"32",
    "gn:asciiname":"Pakhra",
    "gn:cc2":"RU",
    "gn:country_code":"RU",
    "gn:dem":149,
    "gn:feature_class":"P",
    "gn:feature_code":"PPL",
    "gn:name":"Pakhra",
    "gn:population":0,
    "gn:timezone":"Asia/Yekaterinburg",
    "iso:country":"RU",
    "name:rus_x_preferred":[
        "\u041f\u0430\u0445\u0440\u0430"
    ],
    "name:und_x_variant":[
        "Yurty Pakhrinskiye",
        "Pakhra"
    ],
    "wof:name":"Pakhra",
    "wof:placetype":"locality"
},
  "geometry": {"coordinates":[67.05,62.58333],"type":"Point"}
}