{
  "type": "Feature",
  "properties": {
    "gn:admin1_code":"31",
    "gn:asciiname":"Nizhnyaya Baza",
    "gn:cc2":"RU",
    "gn:country_code":"RU",
    "gn:dem":466,
    "gn:feature_class":"P",
    "gn:feature_code":"PPL",
    "gn:name":"Nizhnyaya Baza",
    "gn:population":0,
    "gn:timezone":"Asia/Krasnoyarsk",
    "iso:country":"RU",
    "name:rus_x_preferred":[
        "\u041d\u0438\u0436\u043d\u044f\u044f \u0411\u0430\u0437\u0430"
    ],
    "name:und_x_variant":[
        "Baza",
        "Sukhanov",
        "Nizhnyaya Baza",
        "\u041d\u0438\u0436\u043d\u044f\u044f \u0411\u0430\u0437\u0430"
    ],
    "wof:name":"Nizhnyaya Baza",
    "wof:placetype":"locality"
},
  "geometry": {"coordinates":[90.33806,53.22361],"type":"Point"}
}