{
  "type": "Feature",
  "properties": {
    "gn:admin1_code":"72.0",
    "gn:asciiname":"Chernovka",
    "gn:country_code":"RU",
    "gn:dem":131,
    "gn:feature_class":"P",
    "gn:feature_code":"PPL",
    "gn:name":"Chernovka",
    "gn:population":0,
    "gn:timezone":"Europe/Moscow",
    "iso:country":"RU",
    "name:che_x_preferred":[
        "\u0427\u0435\u0440\u043d\u043e\u0432\u043a\u0430"
    ],
    "name:rus_x_preferred":[
        "\u0427\u0435\u0440\u043d\u043e\u0432\u043a\u0430"
    ],
    "name:und_x_variant":[
        "Chernyayevka",
        "Chernovka"
    ],
    "wof:name":"Chernovka",
    "wof:placetype":"locality"
},
  "geometry": {"coordinates":[40.8103,52.1282],"type":"Point"}
}