{
  "type": "Feature",
  "properties": {
    "gn:admin1_code":"71",
    "gn:asciiname":"Stadukhino",
    "gn:country_code":"RU",
    "gn:dem":267,
    "gn:feature_class":"P",
    "gn:feature_code":"PPL",
    "gn:name":"Stadukhino",
    "gn:population":0,
    "gn:timezone":"Asia/Yekaterinburg",
    "iso:country":"RU",
    "name:eng_x_preferred":[
        "Stadukhino"
    ],
    "name:nor_x_preferred":[
        "Stadukhino"
    ],
    "name:rus_x_preferred":[
        "\u0421\u0442\u0430\u0434\u0443\u0445\u0438\u043d\u043e"
    ],
    "name:und_x_variant":[
        "Stadukhina",
        "\u0421\u0442\u0430\u0434\u0443\u0445\u0438\u043d\u043e",
        "Stadukhino"
    ],
    "wof:name":"Stadukhino",
    "wof:placetype":"locality"
},
  "geometry": {"coordinates":[58.65664,56.19927],"type":"Point"}
}