{
  "type": "Feature",
  "properties": {
    "gn:admin1_code":"65",
    "gn:asciiname":"Znamya Truda",
    "gn:country_code":"RU",
    "gn:dem":66,
    "gn:feature_class":"P",
    "gn:feature_code":"PPL",
    "gn:name":"Znamya Truda",
    "gn:population":0,
    "gn:timezone":"Europe/Samara",
    "iso:country":"RU",
    "name:rus_x_preferred":[
        "\u0417\u043d\u0430\u043c\u044f \u0422\u0440\u0443\u0434\u0430"
    ],
    "name:und_x_variant":[
        "Znamya Bratskogo Truda",
        "Znamya Truda"
    ],
    "wof:name":"Znamya Truda",
    "wof:placetype":"locality"
},
  "geometry": {"coordinates":[50.70196,52.72048],"type":"Point"}
}