{
  "type": "Feature",
  "properties": {
    "gn:admin1_code":"47",
    "gn:asciiname":"Stolbishchevo",
    "gn:country_code":"RU",
    "gn:dem":191,
    "gn:feature_class":"P",
    "gn:feature_code":"PPL",
    "gn:name":"Stolbishchevo",
    "gn:population":0,
    "gn:timezone":"Europe/Moscow",
    "iso:country":"RU",
    "name:rus_x_preferred":[
        "\u0421\u0442\u043e\u043b\u0431\u0438\u0449\u0435\u0432\u043e"
    ],
    "name:und_x_variant":[
        "\u0421\u0442\u043e\u043b\u0431\u0438\u0449\u0435\u0432\u043e"
    ],
    "wof:name":"Stolbishchevo",
    "wof:placetype":"locality"
},
  "geometry": {"coordinates":[37.71667,55.26667],"type":"Point"}
}