{
  "type": "Feature",
  "properties": {
    "gn:admin1_code":"77.0",
    "gn:asciiname":"Glebovo",
    "gn:country_code":"RU",
    "gn:dem":171,
    "gn:feature_class":"P",
    "gn:feature_code":"PPL",
    "gn:name":"Glebovo",
    "gn:population":0,
    "gn:timezone":"Europe/Moscow",
    "iso:country":"RU",
    "name:nor_x_preferred":[
        "Glebovo"
    ],
    "name:rus_x_preferred":[
        "\u0413\u043b\u0435\u0431\u043e\u0432\u043e"
    ],
    "wof:name":"Glebovo",
    "wof:placetype":"locality"
},
  "geometry": {"coordinates":[35.30129,56.28388],"type":"Point"}
}