{
  "type": "Feature",
  "properties": {
    "gn:admin1_code":"60",
    "gn:asciiname":"Zheglovo",
    "gn:country_code":"RU",
    "gn:dem":152,
    "gn:feature_class":"P",
    "gn:feature_code":"PPL",
    "gn:name":"Zheglovo",
    "gn:population":0,
    "gn:timezone":"Europe/Moscow",
    "iso:country":"RU",
    "name:rus_x_preferred":[
        "\u0416\u0435\u0433\u043b\u043e\u0432\u043e"
    ],
    "wof:name":"Zheglovo",
    "wof:placetype":"locality"
},
  "geometry": {"coordinates":[29.15,56.182],"type":"Point"}
}