{
  "type": "Feature",
  "properties": {
    "gn:admin1_code":"8",
    "gn:asciiname":"Urazovo",
    "gn:country_code":"RU",
    "gn:dem":461,
    "gn:feature_class":"P",
    "gn:feature_code":"PPL",
    "gn:name":"Urazovo",
    "gn:population":0,
    "gn:timezone":"Asia/Yekaterinburg",
    "iso:country":"RU",
    "name:ceb_x_preferred":[
        "Urazovo"
    ],
    "name:che_x_preferred":[
        "\u0423\u0440\u0430\u0437\u043e\u0432\u043e"
    ],
    "name:eng_x_preferred":[
        "Urazovo"
    ],
    "name:fra_x_preferred":[
        "Ourazovo"
    ],
    "name:ita_x_preferred":[
        "Urazovo"
    ],
    "name:nor_x_preferred":[
        "Urazovo"
    ],
    "name:rus_x_preferred":[
        "\u0423\u0440\u0430\u0437\u043e\u0432\u043e"
    ],
    "name:tgk_x_preferred":[
        "\u0423\u0440\u0430\u0437\u043e\u0432\u043e"
    ],
    "name:ukr_x_preferred":[
        "\u0423\u0440\u0430\u0437\u043e\u0432\u043e"
    ],
    "name:und_x_variant":[
        "Urazova",
        "Urazovo"
    ],
    "wof:name":"Urazovo",
    "wof:placetype":"locality"
},
  "geometry": {"coordinates":[59.1312,54.2673],"type":"Point"}
}