{
  "type": "Feature",
  "properties": {
    "gn:admin1_code":"6",
    "gn:asciiname":"Pekhtusovo",
    "gn:country_code":"RU",
    "gn:dem":91,
    "gn:feature_class":"P",
    "gn:feature_code":"PPL",
    "gn:name":"Pekhtusovo",
    "gn:population":0,
    "gn:timezone":"Europe/Moscow",
    "iso:country":"RU",
    "name:rus_x_preferred":[
        "\u041f\u0435\u0445\u0442\u0443\u0441\u043e\u0432\u043e"
    ],
    "name:und_x_variant":[
        "\u041f\u0435\u0445\u0442\u0443\u0441\u043e\u0432\u043e"
    ],
    "wof:name":"Pekhtusovo",
    "wof:placetype":"locality"
},
  "geometry": {"coordinates":[38.31667,62.28333000000001],"type":"Point"}
}