{
  "type": "Feature",
  "properties": {
    "gn:admin1_code":"6",
    "gn:asciiname":"Pochinok Volochinskiy",
    "gn:country_code":"RU",
    "gn:dem":117,
    "gn:feature_class":"P",
    "gn:feature_code":"PPL",
    "gn:name":"Pochinok Volochinskiy",
    "gn:population":0,
    "gn:timezone":"Europe/Moscow",
    "iso:country":"RU",
    "wof:name":"Pochinok Volochinskiy",
    "wof:placetype":"locality"
},
  "geometry": {"coordinates":[44.75,61.16667],"type":"Point"}
}