{
  "type": "Feature",
  "properties": {
    "gn:admin1_code":"33",
    "gn:asciiname":"Chistovrazh'ye",
    "gn:country_code":"RU",
    "gn:dem":145,
    "gn:feature_class":"P",
    "gn:feature_code":"PPL",
    "gn:name":"Chistovrazh\u2019ye",
    "gn:population":0,
    "gn:timezone":"Europe/Kirov",
    "iso:country":"RU",
    "name:rus_x_preferred":[
        "\u0427\u0438\u0441\u0442\u043e\u0432\u0440\u0430\u0436\u044c\u0435"
    ],
    "name:und_x_variant":[
        "Chistovrazh\u2019ye"
    ],
    "wof:name":"Chistovrazh'ye",
    "wof:placetype":"locality"
},
  "geometry": {"coordinates":[49.3283,57.4076],"type":"Point"}
}