{
  "type": "Feature",
  "properties": {
    "gn:admin1_code":"71",
    "gn:asciiname":"Tyumenskaya",
    "gn:country_code":"RU",
    "gn:dem":94,
    "gn:feature_class":"P",
    "gn:feature_code":"PPL",
    "gn:name":"Tyumenskaya",
    "gn:population":0,
    "gn:timezone":"Asia/Yekaterinburg",
    "iso:country":"RU",
    "name:rus_x_preferred":[
        "\u0422\u044e\u043c\u0435\u043d\u0441\u043a\u0430\u044f"
    ],
    "name:und_x_variant":[
        "Tyumenskiy",
        "Tyunenskiy",
        "Tyumenskaya"
    ],
    "wof:name":"Tyumenskaya",
    "wof:placetype":"locality"
},
  "geometry": {"coordinates":[61.84251,58.92074],"type":"Point"}
}