{
  "type": "Feature",
  "properties": {
    "gn:admin1_code":"51",
    "gn:asciiname":"Bol'shaya Voroshilovka",
    "gn:country_code":"RU",
    "gn:dem":127,
    "gn:feature_class":"P",
    "gn:feature_code":"PPL",
    "gn:name":"Bol\u2019shaya Voroshilovka",
    "gn:population":0,
    "gn:timezone":"Europe/Moscow",
    "iso:country":"RU",
    "name:rus_x_preferred":[
        "\u0411\u043e\u043b\u044c\u0448\u0430\u044f \u0412\u043e\u0440\u043e\u0448\u0438\u043b\u043e\u0432\u043a\u0430"
    ],
    "name:und_x_variant":[
        "Bol\u2019shaya Voroshilovka",
        "\u0411\u043e\u043b\u044c\u0448\u0430\u044f \u0412\u043e\u0440\u043e\u0448\u0438\u043b\u043e\u0432\u043a\u0430"
    ],
    "wof:name":"Bol'shaya Voroshilovka",
    "wof:placetype":"locality"
},
  "geometry": {"coordinates":[45.7955,57.5179],"type":"Point"}
}