{
  "type": "Feature",
  "properties": {
    "gn:admin1_code":"77",
    "gn:asciiname":"Zakharikhino",
    "gn:country_code":"RU",
    "gn:dem":226,
    "gn:feature_class":"P",
    "gn:feature_code":"PPL",
    "gn:name":"Zakharikhino",
    "gn:population":0,
    "gn:timezone":"Europe/Moscow",
    "iso:country":"RU",
    "name:rus_x_preferred":[
        "\u0417\u0430\u0445\u0430\u0440\u0438\u0445\u0438\u043d\u043e"
    ],
    "name:und_x_variant":[
        "\u0417\u0430\u0445\u0430\u0440\u0438\u0445\u0438\u043d\u043e"
    ],
    "wof:name":"Zakharikhino",
    "wof:placetype":"locality"
},
  "geometry": {"coordinates":[31.57897,56.79436],"type":"Point"}
}