{
  "type": "Feature",
  "properties": {
    "gn:admin1_code":"90",
    "gn:asciiname":"Komarikha",
    "gn:country_code":"RU",
    "gn:dem":127,
    "gn:feature_class":"P",
    "gn:feature_code":"PPL",
    "gn:name":"Komarikha",
    "gn:population":0,
    "gn:timezone":"Asia/Yekaterinburg",
    "iso:country":"RU",
    "name:che_x_preferred":[
        "\u041a\u043e\u043c\u0430\u0440\u0438\u0445\u0430"
    ],
    "name:eng_x_preferred":[
        "Komarikha"
    ],
    "name:nor_x_preferred":[
        "Komarikha"
    ],
    "name:rus_x_preferred":[
        "\u041a\u043e\u043c\u0430\u0440\u0438\u0445\u0430"
    ],
    "name:und_x_variant":[
        "Komarakha"
    ],
    "wof:name":"Komarikha",
    "wof:placetype":"locality"
},
  "geometry": {"coordinates":[55.8475,58.6527],"type":"Point"}
}