{
  "type": "Feature",
  "properties": {
    "gn:admin1_code":"88",
    "gn:asciiname":"Afineyevo",
    "gn:country_code":"RU",
    "gn:dem":143,
    "gn:feature_class":"P",
    "gn:feature_code":"PPL",
    "gn:name":"Afineyevo",
    "gn:population":0,
    "gn:timezone":"Europe/Moscow",
    "iso:country":"RU",
    "name:rus_x_preferred":[
        "\u0410\u0444\u0438\u043d\u0435\u0435\u0432\u043e"
    ],
    "name:und_x_variant":[
        "Afineyev",
        "Afineyevo"
    ],
    "wof:name":"Afineyevo",
    "wof:placetype":"locality"
},
  "geometry": {"coordinates":[39.84169,57.5215],"type":"Point"}
}