{
  "type": "Feature",
  "properties": {
    "gn:admin1_code":"20",
    "gn:asciiname":"Metlyayeva",
    "gn:country_code":"RU",
    "gn:dem":432,
    "gn:feature_class":"P",
    "gn:feature_code":"PPL",
    "gn:name":"Metlyayeva",
    "gn:population":0,
    "gn:timezone":"Asia/Irkutsk",
    "iso:country":"RU",
    "name:eng_x_preferred":[
        "Metlyayeva"
    ],
    "name:nor_x_preferred":[
        "Metljaeva"
    ],
    "name:rus_x_preferred":[
        "\u041c\u0435\u0442\u043b\u044f\u0435\u0432\u0430"
    ],
    "name:und_x_variant":[
        "Verkhneye Myatlevo",
        "Metlyayevo",
        "Metlyayeva"
    ],
    "wof:name":"Metlyayeva",
    "wof:placetype":"locality"
},
  "geometry": {"coordinates":[102.8468,54.1243],"type":"Point"}
}