{
  "type": "Feature",
  "properties": {
    "gn:admin1_code":"69",
    "gn:asciiname":"Sopinki",
    "gn:country_code":"RU",
    "gn:dem":208,
    "gn:feature_class":"P",
    "gn:feature_code":"PPL",
    "gn:name":"Sopinki",
    "gn:population":0,
    "gn:timezone":"Europe/Moscow",
    "iso:country":"RU",
    "name:rus_x_preferred":[
        "\u0421\u043e\u043f\u0438\u043d\u043a\u0438"
    ],
    "wof:name":"Sopinki",
    "wof:placetype":"locality"
},
  "geometry": {"coordinates":[31.66667,55.61666999999999],"type":"Point"}
}