{
  "type": "Feature",
  "properties": {
    "gn:admin1_code":"73.0",
    "gn:asciiname":"Bolgar Nomer Dva",
    "gn:country_code":"RU",
    "gn:dem":199,
    "gn:feature_class":"P",
    "gn:feature_code":"PPL",
    "gn:name":"Bolgar Nomer Dva",
    "gn:population":0,
    "gn:timezone":"Europe/Moscow",
    "iso:country":"RU",
    "name:rus_x_preferred":[
        "\u0411\u043e\u043b\u0433\u0430\u0440 \u041d\u043e\u043c\u0435\u0440 \u0414\u0432\u0430"
    ],
    "name:und_x_variant":[
        "Bolgar Vtoroy",
        "\u0411\u043e\u043b\u0433\u0430\u0440 \u041d\u043e\u043c\u0435\u0440 \u0414\u0432\u0430"
    ],
    "wof:name":"Bolgar Nomer Dva",
    "wof:placetype":"locality"
},
  "geometry": {"coordinates":[52.39758,55.06117],"type":"Point"}
}