{
  "type": "Feature",
  "properties": {
    "gn:admin1_code":"8",
    "gn:asciiname":"Kumurly",
    "gn:country_code":"RU",
    "gn:dem":119,
    "gn:feature_class":"P",
    "gn:feature_code":"PPL",
    "gn:name":"Kumurly",
    "gn:population":0,
    "gn:timezone":"Asia/Yekaterinburg",
    "iso:country":"RU",
    "name:eng_x_preferred":[
        "Kumurly"
    ],
    "name:nor_x_preferred":[
        "Kumurly"
    ],
    "name:rus_x_preferred":[
        "\u041a\u0443\u043c\u0443\u0440\u043b\u044b"
    ],
    "name:und_x_variant":[
        "\u041a\u0443\u043c\u0443\u0440\u043b\u044b",
        "Kumurly"
    ],
    "wof:name":"Kumurly",
    "wof:placetype":"locality"
},
  "geometry": {"coordinates":[56.5724,54.5042],"type":"Point"}
}