{
  "type": "Feature",
  "properties": {
    "gn:admin1_code":"8",
    "gn:asciiname":"Kumurly",
    "gn:country_code":"RU",
    "gn:dem":119,
    "gn:feature_class":"P",
    "gn:feature_code":"PPL",
    "gn:name":"Kumurly",
    "gn:population":0,
    "gn:timezone":"Asia/Yekaterinburg",
    "iso:country":"RU",
    "name:aze_x_preferred":[
        "K\u00f6m\u0259rli"
    ],
    "name:bak_x_preferred":[
        "\u041a\u04e9\u043c\u04d9\u0440\u043b\u0435"
    ],
    "name:che_x_preferred":[
        "\u041a\u0443\u043c\u0443\u0440\u043b\u044b"
    ],
    "name:eng_x_preferred":[
        "Kumurly"
    ],
    "name:hye_x_preferred":[
        "\u053f\u0578\u0582\u0574\u0578\u0582\u0580\u056c\u056b"
    ],
    "name:kat_x_preferred":[
        "\u10d9\u10e3\u10db\u10e3\u10e0\u10da\u10d8"
    ],
    "name:kaz_x_preferred":[
        "\u041a\u0443\u043c\u0443\u0440\u043b\u044b"
    ],
    "name:kir_x_preferred":[
        "\u041a\u0443\u043c\u0443\u0440\u043b\u044b"
    ],
    "name:nor_x_preferred":[
        "Kumurly"
    ],
    "name:rus_x_preferred":[
        "\u041a\u0443\u043c\u0443\u0440\u043b\u044b"
    ],
    "name:tat_x_preferred":[
        "\u041a\u04e9\u043c\u04d9\u0440\u043b\u0435"
    ],
    "name:ukr_x_preferred":[
        "\u041a\u0443\u043c\u0443\u0440\u043b\u0438"
    ],
    "name:und_x_variant":[
        "\u041a\u0443\u043c\u0443\u0440\u043b\u044b",
        "Kumurly"
    ],
    "wof:name":"Kumurly",
    "wof:placetype":"locality"
},
  "geometry": {"coordinates":[56.5724,54.5042],"type":"Point"}
}