{
  "type": "Feature",
  "properties": {
    "gn:admin1_code":"80",
    "gn:asciiname":"Pentegi",
    "gn:country_code":"RU",
    "gn:dem":110,
    "gn:feature_class":"P",
    "gn:feature_code":"PPL",
    "gn:name":"Pentegi",
    "gn:population":0,
    "gn:timezone":"Europe/Samara",
    "iso:country":"RU",
    "name:nor_x_preferred":[
        "Pentegi"
    ],
    "name:rus_x_preferred":[
        "\u041f\u0435\u043d\u0442\u0435\u0433\u0438"
    ],
    "wof:name":"Pentegi",
    "wof:placetype":"locality"
},
  "geometry": {"coordinates":[53.5137,56.28183000000001],"type":"Point"}
}