{
  "type": "Feature",
  "properties": {
    "gn:admin1_code":"9.0",
    "gn:asciiname":"Chapayev",
    "gn:country_code":"RU",
    "gn:dem":175,
    "gn:feature_class":"P",
    "gn:feature_code":"PPL",
    "gn:name":"Chapayev",
    "gn:population":0,
    "gn:timezone":"Europe/Moscow",
    "iso:country":"RU",
    "name:rus_x_preferred":[
        "\u0427\u0430\u043f\u0430\u0435\u0432"
    ],
    "wof:name":"Chapayev",
    "wof:placetype":"locality"
},
  "geometry": {"coordinates":[36.12056,50.88639000000001],"type":"Point"}
}