{
  "type": "Feature",
  "properties": {
    "gn:admin1_code":"51",
    "gn:asciiname":"Podnov'ye",
    "gn:country_code":"RU",
    "gn:dem":106,
    "gn:feature_class":"P",
    "gn:feature_code":"PPL",
    "gn:name":"Podnov\u2019ye",
    "gn:population":0,
    "gn:timezone":"Europe/Moscow",
    "iso:country":"RU",
    "name:rus_x_preferred":[
        "\u041f\u043e\u0434\u043d\u043e\u0432\u044c\u0435"
    ],
    "name:und_x_variant":[
        "Podnov\u2019ye"
    ],
    "wof:name":"Podnov'ye",
    "wof:placetype":"locality"
},
  "geometry": {"coordinates":[44.09244,56.3061],"type":"Point"}
}