{
  "type": "Feature",
  "properties": {
    "gn:admin1_code":"90.0",
    "gn:asciiname":"Zaytsy",
    "gn:country_code":"RU",
    "gn:dem":147,
    "gn:feature_class":"P",
    "gn:feature_code":"PPL",
    "gn:name":"Zaytsy",
    "gn:population":0,
    "gn:timezone":"Asia/Yekaterinburg",
    "iso:country":"RU",
    "name:che_x_preferred":[
        "\u0417\u0430\u0439\u0446\u044b"
    ],
    "name:rus_x_preferred":[
        "\u0417\u0430\u0439\u0446\u044b"
    ],
    "wof:name":"Zaytsy",
    "wof:placetype":"locality"
},
  "geometry": {"coordinates":[55.3107,58.0323],"type":"Point"}
}