{
  "type": "Feature",
  "properties": {
    "gn:admin1_code":"83",
    "gn:asciiname":"Yanevo",
    "gn:country_code":"RU",
    "gn:dem":142,
    "gn:feature_class":"P",
    "gn:feature_code":"PPL",
    "gn:name":"Yanevo",
    "gn:population":0,
    "gn:timezone":"Europe/Moscow",
    "iso:country":"RU",
    "name:eng_x_preferred":[
        "Yanevo"
    ],
    "name:nor_x_preferred":[
        "Janevo"
    ],
    "name:rus_x_preferred":[
        "\u042f\u043d\u0435\u0432\u043e"
    ],
    "wof:name":"Yanevo",
    "wof:placetype":"locality"
},
  "geometry": {"coordinates":[40.32242,56.42966],"type":"Point"}
}