{
  "type": "Feature",
  "properties": {
    "gn:admin1_code":"71",
    "gn:asciiname":"Taushankova",
    "gn:country_code":"RU",
    "gn:dem":83,
    "gn:feature_class":"P",
    "gn:feature_code":"PPL",
    "gn:name":"Taushankova",
    "gn:population":0,
    "gn:timezone":"Asia/Yekaterinburg",
    "iso:country":"RU",
    "name:rus_x_preferred":[
        "\u0422\u0430\u0443\u0448\u0430\u043d\u043a\u043e\u0432\u0430"
    ],
    "name:und_x_variant":[
        "Taushankovo",
        "Taushankova"
    ],
    "wof:name":"Taushankova",
    "wof:placetype":"locality"
},
  "geometry": {"coordinates":[60.87779000000001,59.46737],"type":"Point"}
}