{
  "type": "Feature",
  "properties": {
    "gn:admin1_code":"60",
    "gn:asciiname":"Raikhino",
    "gn:country_code":"RU",
    "gn:dem":69,
    "gn:feature_class":"P",
    "gn:feature_code":"PPL",
    "gn:name":"Raikhino",
    "gn:population":0,
    "gn:timezone":"Europe/Moscow",
    "iso:country":"RU",
    "name:rus_x_preferred":[
        "\u0420\u0430\u0438\u0445\u0438\u043d\u043e"
    ],
    "wof:name":"Raikhino",
    "wof:placetype":"locality"
},
  "geometry": {"coordinates":[28.1114,57.43054],"type":"Point"}
}