{
  "type": "Feature",
  "properties": {
    "gn:admin1_code":"71",
    "gn:asciiname":"Nagornaya",
    "gn:country_code":"RU",
    "gn:dem":170,
    "gn:feature_class":"P",
    "gn:feature_code":"PPL",
    "gn:name":"Nagornaya",
    "gn:population":0,
    "gn:timezone":"Asia/Yekaterinburg",
    "iso:country":"RU",
    "name:rus_x_preferred":[
        "\u041d\u0430\u0433\u043e\u0440\u043d\u0430\u044f"
    ],
    "wof:name":"Nagornaya",
    "wof:placetype":"locality"
},
  "geometry": {"coordinates":[61.8159,57.6104],"type":"Point"}
}