{
  "type": "Feature",
  "properties": {
    "gn:admin1_code":"65",
    "gn:asciiname":"Lopatino",
    "gn:country_code":"RU",
    "gn:dem":44,
    "gn:feature_class":"P",
    "gn:feature_code":"PPL",
    "gn:name":"Lopatino",
    "gn:population":0,
    "gn:timezone":"Europe/Samara",
    "iso:country":"RU",
    "name:rus_x_preferred":[
        "\u041b\u043e\u043f\u0430\u0442\u0438\u043d\u043e"
    ],
    "wof:name":"Lopatino",
    "wof:placetype":"locality"
},
  "geometry": {"coordinates":[50.62681,53.6225],"type":"Point"}
}