{
  "type": "Feature",
  "properties": {
    "gn:admin1_code":"38",
    "gn:asciiname":"Mayskoye",
    "gn:country_code":"RU",
    "gn:dem":392,
    "gn:feature_class":"P",
    "gn:feature_code":"PPL",
    "gn:name":"Mayskoye",
    "gn:population":0,
    "gn:timezone":"Europe/Moscow",
    "iso:country":"RU",
    "name:rus_x_preferred":[
        "\u041c\u0430\u0439\u0441\u043a\u043e\u0435"
    ],
    "name:und_x_variant":[
        "Mayskiy",
        "Mayskoye"
    ],
    "wof:name":"Mayskoye",
    "wof:placetype":"locality"
},
  "geometry": {"coordinates":[41.1796,44.5868],"type":"Point"}
}