{
  "type": "Feature",
  "properties": {
    "gn:admin1_code":"62",
    "gn:asciiname":"Breyevo",
    "gn:country_code":"RU",
    "gn:dem":123,
    "gn:feature_class":"P",
    "gn:feature_code":"PPL",
    "gn:name":"Breyevo",
    "gn:population":0,
    "gn:timezone":"Europe/Moscow",
    "iso:country":"RU",
    "name:rus_x_preferred":[
        "\u0411\u0440\u0435\u0435\u0432\u043e"
    ],
    "wof:name":"Breyevo",
    "wof:placetype":"locality"
},
  "geometry": {"coordinates":[41.3446,54.841],"type":"Point"}
}