{
  "type": "Feature",
  "properties": {
    "gn:admin1_code":"25",
    "gn:asciiname":"Pokhvisnevo",
    "gn:country_code":"RU",
    "gn:dem":139,
    "gn:feature_class":"P",
    "gn:feature_code":"PPL",
    "gn:name":"Pokhvisnevo",
    "gn:population":0,
    "gn:timezone":"Europe/Moscow",
    "iso:country":"RU",
    "name:rus_x_preferred":[
        "\u041f\u043e\u0445\u0432\u0438\u0441\u043d\u0435\u0432\u043e"
    ],
    "wof:name":"Pokhvisnevo",
    "wof:placetype":"locality"
},
  "geometry": {"coordinates":[37.09018,54.73784000000001],"type":"Point"}
}