{
  "type": "Feature",
  "properties": {
    "gn:admin1_code":"91",
    "gn:asciiname":"Vishnyakovo-Kateyul'",
    "gn:country_code":"RU",
    "gn:dem":247,
    "gn:feature_class":"P",
    "gn:feature_code":"PPL",
    "gn:name":"Vishnyakovo-Kateyul\u2019",
    "gn:population":0,
    "gn:timezone":"Asia/Krasnoyarsk",
    "iso:country":"RU",
    "name:eng_x_preferred":[
        "Vishnyakovo-Kateyul'"
    ],
    "name:nor_x_preferred":[
        "Visjnjakovo-Katejul"
    ],
    "name:rus_x_preferred":[
        "\u0412\u0438\u0448\u043d\u044f\u043a\u043e\u0432\u043e-\u041a\u0430\u0442\u0435\u044e\u043b"
    ],
    "name:und_x_variant":[
        "Kateyul\u2019-Vishnyakova",
        "Vishnyakova",
        "Vishnyakovo-Kateyul\u2019"
    ],
    "wof:name":"Vishnyakovo-Kateyul'",
    "wof:placetype":"locality"
},
  "geometry": {"coordinates":[89.46213,56.30941],"type":"Point"}
}