{
  "type": "Feature",
  "properties": {
    "gn:admin1_code":"77",
    "gn:asciiname":"Malyye Smenki",
    "gn:country_code":"RU",
    "gn:dem":153,
    "gn:feature_class":"P",
    "gn:feature_code":"PPL",
    "gn:name":"Malyye Smenki",
    "gn:population":0,
    "gn:timezone":"Europe/Moscow",
    "iso:country":"RU",
    "name:rus_x_preferred":[
        "\u041c\u0430\u043b\u044b\u0435 \u0421\u043c\u0435\u043d\u043a\u0438"
    ],
    "wof:name":"Malyye Smenki",
    "wof:placetype":"locality"
},
  "geometry": {"coordinates":[37.285,57.8798],"type":"Point"}
}