{
  "type": "Feature",
  "properties": {
    "gn:admin1_code":"6",
    "gn:asciiname":"Shchel'ya",
    "gn:country_code":"RU",
    "gn:dem":24,
    "gn:feature_class":"P",
    "gn:feature_code":"PPL",
    "gn:name":"Shchel\u2019ya",
    "gn:population":0,
    "gn:timezone":"Europe/Moscow",
    "iso:country":"RU",
    "name:rus_x_preferred":[
        "\u0429\u0435\u043b\u044c\u044f"
    ],
    "name:und_x_variant":[
        "Shchel\u2019",
        "Shchel\u2019ye",
        "Shchel\u2019ya"
    ],
    "wof:name":"Shchel'ya",
    "wof:placetype":"locality"
},
  "geometry": {"coordinates":[43.7681,64.7062],"type":"Point"}
}