{
  "type": "Feature",
  "properties": {
    "gn:admin1_code":"61",
    "gn:asciiname":"Novikovka",
    "gn:country_code":"RU",
    "gn:dem":141,
    "gn:feature_class":"P",
    "gn:feature_code":"PPL",
    "gn:name":"Novikovka",
    "gn:population":0,
    "gn:timezone":"Europe/Moscow",
    "iso:country":"RU",
    "name:rus_x_preferred":[
        "\u041d\u043e\u0432\u0438\u043a\u043e\u0432\u043a\u0430"
    ],
    "name:und_x_variant":[
        "\u041d\u043e\u0432\u0438\u043a\u043e\u0432\u043a\u0430"
    ],
    "wof:name":"Novikovka",
    "wof:placetype":"locality"
},
  "geometry": {"coordinates":[39.08417,47.74667],"type":"Point"}
}