{
  "type": "Feature",
  "properties": {
    "gn:admin1_code":"8",
    "gn:asciiname":"Plodopitomnik",
    "gn:country_code":"RU",
    "gn:dem":298,
    "gn:feature_class":"P",
    "gn:feature_code":"PPL",
    "gn:name":"Plodopitomnik",
    "gn:population":0,
    "gn:timezone":"Asia/Yekaterinburg",
    "iso:country":"RU",
    "name:rus_x_preferred":[
        "\u041f\u043b\u043e\u0434\u043e\u043f\u0438\u0442\u043e\u043c\u043d\u0438\u043a"
    ],
    "wof:name":"Plodopitomnik",
    "wof:placetype":"locality"
},
  "geometry": {"coordinates":[53.9518,53.8981],"type":"Point"}
}