{
  "type": "Feature",
  "properties": {
    "gn:admin1_code":"60",
    "gn:asciiname":"Tsybino",
    "gn:country_code":"RU",
    "gn:dem":100,
    "gn:feature_class":"P",
    "gn:feature_code":"PPL",
    "gn:name":"Tsybino",
    "gn:population":0,
    "gn:timezone":"Europe/Moscow",
    "iso:country":"RU",
    "name:rus_x_preferred":[
        "\u0426\u044b\u0431\u0438\u043d\u043e"
    ],
    "wof:name":"Tsybino",
    "wof:placetype":"locality"
},
  "geometry": {"coordinates":[28.4423,56.84591999999999],"type":"Point"}
}