{
  "type": "Feature",
  "properties": {
    "gn:country":"RU",
    "gn:fcode":"PPL",
    "gn:population":7256,
    "iso:country":"RU",
    "name:nor_x_preferred":[
        "Gizel"
    ],
    "name:rus_x_preferred":[
        "\u0413\u0438\u0437\u0435\u043b\u044c"
    ],
    "qs:name":"Gizel\u2019",
    "qs:photos_9r":0,
    "qs:photos_sr":0,
    "qs:pop_sr":"5",
    "wof:name":"Gizel\u2019",
    "wof:placetype":"locality",
    "wof:population":7256
},
  "geometry": {"coordinates":[44.57083,43.04],"type":"Point"}
}