{
  "type": "Feature",
  "properties": {
    "gn:admin1_code":"20",
    "gn:asciiname":"Teterinskoye",
    "gn:country_code":"RU",
    "gn:dem":636,
    "gn:feature_class":"P",
    "gn:feature_code":"PPL",
    "gn:name":"Teterinskoye",
    "gn:population":0,
    "gn:timezone":"Asia/Irkutsk",
    "iso:country":"RU",
    "wof:name":"Teterinskoye",
    "wof:placetype":"locality"
},
  "geometry": {"coordinates":[114.28333000000001,57.96666999999999],"type":"Point"}
}