{
  "type": "Feature",
  "properties": {
    "gn:admin1_code":"76.0",
    "gn:asciiname":"Bel'tsy",
    "gn:country_code":"RU",
    "gn:dem":195,
    "gn:feature_class":"P",
    "gn:feature_code":"PPL",
    "gn:name":"Bel\u2019tsy",
    "gn:population":0,
    "gn:timezone":"Europe/Moscow",
    "iso:country":"RU",
    "name:eng_x_preferred":[
        "Bel'tsy"
    ],
    "name:nor_x_preferred":[
        "Beltsy"
    ],
    "name:rus_x_preferred":[
        "\u0411\u0435\u043b\u044c\u0446\u044b"
    ],
    "name:und_x_variant":[
        "Bel\u2019tsy"
    ],
    "wof:name":"Bel'tsy",
    "wof:placetype":"locality"
},
  "geometry": {"coordinates":[38.42845,54.35665],"type":"Point"}
}