{
  "type": "Feature",
  "properties": {
    "gn:admin1_code":"77",
    "gn:asciiname":"Igumenka",
    "gn:country_code":"RU",
    "gn:dem":159,
    "gn:feature_class":"P",
    "gn:feature_code":"PPL",
    "gn:name":"Igumenka",
    "gn:population":0,
    "gn:timezone":"Europe/Moscow",
    "iso:country":"RU",
    "name:nor_x_preferred":[
        "Igumenka"
    ],
    "name:rus_x_preferred":[
        "\u0418\u0433\u0443\u043c\u0435\u043d\u043a\u0430"
    ],
    "wof:name":"Igumenka",
    "wof:placetype":"locality"
},
  "geometry": {"coordinates":[35.17391,56.58902],"type":"Point"}
}