{
  "type": "Feature",
  "properties": {
    "gn:admin1_code":"62",
    "gn:asciiname":"Vasilevka",
    "gn:country_code":"RU",
    "gn:dem":156,
    "gn:feature_class":"P",
    "gn:feature_code":"PPL",
    "gn:name":"Vasil\u00ebvka",
    "gn:population":0,
    "gn:timezone":"Europe/Moscow",
    "iso:country":"RU",
    "name:rus_x_preferred":[
        "\u0412\u0430\u0441\u0438\u043b\u0451\u0432\u043a\u0430"
    ],
    "name:und_x_variant":[
        "Vasil\u00ebvka"
    ],
    "wof:name":"Vasilevka",
    "wof:placetype":"locality"
},
  "geometry": {"coordinates":[40.2497,53.7351],"type":"Point"}
}