{
  "type": "Feature",
  "properties": {
    "gn:admin1_code":"73",
    "gn:asciiname":"Naratly",
    "gn:country_code":"RU",
    "gn:dem":106,
    "gn:feature_class":"P",
    "gn:feature_code":"PPL",
    "gn:name":"Naratly",
    "gn:population":0,
    "gn:timezone":"Europe/Moscow",
    "iso:country":"RU",
    "name:rus_x_preferred":[
        "\u041d\u0430\u0440\u0430\u0442\u043b\u044b"
    ],
    "name:und_x_variant":[
        "Mosteyevo",
        "Masteyevo",
        "Naratly",
        "\u041d\u0430\u0440\u0430\u0442\u043b\u044b"
    ],
    "wof:name":"Naratly",
    "wof:placetype":"locality"
},
  "geometry": {"coordinates":[53.78686999999999,55.46961999999999],"type":"Point"}
}