{
  "type": "Feature",
  "properties": {
    "gn:admin1_code":"61.0",
    "gn:asciiname":"Kryuchkin",
    "gn:country_code":"RU",
    "gn:dem":69,
    "gn:feature_class":"P",
    "gn:feature_code":"PPL",
    "gn:name":"Kryuchkin",
    "gn:population":0,
    "gn:timezone":"Europe/Moscow",
    "iso:country":"RU",
    "name:rus_x_preferred":[
        "\u041a\u0440\u044e\u0447\u043a\u0438\u043d"
    ],
    "name:und_x_variant":[
        "\u041a\u0440\u044e\u0447\u043a\u0438\u043d"
    ],
    "wof:name":"Kryuchkin",
    "wof:placetype":"locality"
},
  "geometry": {"coordinates":[39.08111,47.54889],"type":"Point"}
}