{
  "type": "Feature",
  "properties": {
    "gn:admin1_code":"60",
    "gn:asciiname":"Kalistovo",
    "gn:country_code":"RU",
    "gn:dem":124,
    "gn:feature_class":"P",
    "gn:feature_code":"PPL",
    "gn:name":"Kalistovo",
    "gn:population":0,
    "gn:timezone":"Europe/Moscow",
    "iso:country":"RU",
    "name:rus_x_preferred":[
        "\u041a\u0430\u043b\u0438\u0441\u0442\u043e\u0432\u043e"
    ],
    "name:und_x_variant":[
        "\u041a\u0430\u043b\u0438\u0441\u0442\u043e\u0432\u043e"
    ],
    "wof:name":"Kalistovo",
    "wof:placetype":"locality"
},
  "geometry": {"coordinates":[30.1134,56.8617],"type":"Point"}
}