{
  "type": "Feature",
  "properties": {
    "gn:admin1_code":"47",
    "gn:asciiname":"Ivanovskoye",
    "gn:country_code":"RU",
    "gn:dem":140,
    "gn:feature_class":"P",
    "gn:feature_code":"PPL",
    "gn:name":"Ivanovskoye",
    "gn:population":0,
    "gn:timezone":"Europe/Moscow",
    "iso:country":"RU",
    "name:rus_x_preferred":[
        "\u0418\u0432\u0430\u043d\u043e\u0432\u0441\u043a\u043e\u0435"
    ],
    "name:und_x_variant":[
        "\u0418\u0432\u0430\u043d\u043e\u0432\u0441\u043a\u043e\u0435"
    ],
    "wof:name":"Ivanovskoye",
    "wof:placetype":"locality"
},
  "geometry": {"coordinates":[36.91667,55.86666999999999],"type":"Point"}
}