{
  "type": "Feature",
  "properties": {
    "gn:admin1_code":"47",
    "gn:asciiname":"Denisikha",
    "gn:country_code":"RU",
    "gn:dem":238,
    "gn:feature_class":"P",
    "gn:feature_code":"PPL",
    "gn:name":"Denisikha",
    "gn:population":0,
    "gn:timezone":"Europe/Moscow",
    "iso:country":"RU",
    "name:rus_x_preferred":[
        "\u0414\u0435\u043d\u0438\u0441\u0438\u0445\u0430"
    ],
    "name:und_x_variant":[
        "\u0414\u0435\u043d\u0438\u0441\u0438\u0445\u0430"
    ],
    "wof:name":"Denisikha",
    "wof:placetype":"locality"
},
  "geometry": {"coordinates":[36.43574,55.82518],"type":"Point"}
}