{
  "type": "Feature",
  "properties": {
    "gn:admin1_code":"10",
    "gn:asciiname":"Gusli",
    "gn:country_code":"RU",
    "gn:dem":192,
    "gn:feature_class":"P",
    "gn:feature_code":"PPL",
    "gn:name":"Gusli",
    "gn:population":0,
    "gn:timezone":"Europe/Moscow",
    "iso:country":"RU",
    "name:rus_x_preferred":[
        "\u0413\u0443\u0441\u043b\u0438"
    ],
    "name:und_x_variant":[
        "\u0413\u0443\u0441\u043b\u0438"
    ],
    "wof:name":"Gusli",
    "wof:placetype":"locality"
},
  "geometry": {"coordinates":[32.75614,52.61814],"type":"Point"}
}