{
  "type": "Feature",
  "properties": {
    "gn:admin1_code":"10",
    "gn:asciiname":"Gusli",
    "gn:country_code":"RU",
    "gn:dem":192,
    "gn:feature_class":"P",
    "gn:feature_code":"PPL",
    "gn:name":"Gusli",
    "gn:population":0,
    "gn:timezone":"Europe/Moscow",
    "iso:country":"RU",
    "name:bel_x_preferred":[
        "\u0413\u0443\u0441\u043b\u0456"
    ],
    "name:bre_x_preferred":[
        "Gousli"
    ],
    "name:cat_x_preferred":[
        "Gusli"
    ],
    "name:ces_x_preferred":[
        "Gusli"
    ],
    "name:chv_x_preferred":[
        "\u041a\u0115\u0441\u043b\u0435"
    ],
    "name:deu_x_preferred":[
        "Gusli"
    ],
    "name:epo_x_preferred":[
        "Guzlio"
    ],
    "name:est_x_preferred":[
        "Gusli"
    ],
    "name:fra_x_preferred":[
        "Gousli"
    ],
    "name:heb_x_preferred":[
        "\u05d2\u05d5\u05e1\u05dc\u05d9"
    ],
    "name:ita_x_preferred":[
        "Gusli"
    ],
    "name:jpn_x_preferred":[
        "\u30b0\u30fc\u30b9\u30ea"
    ],
    "name:kat_x_preferred":[
        "\u10d2\u10e3\u10e1\u10da\u10d8"
    ],
    "name:kaz_x_preferred":[
        "\u0413\u0443\u0441\u043b\u0438"
    ],
    "name:lit_x_preferred":[
        "Gusl\u0117s"
    ],
    "name:mhr_x_preferred":[
        "\u041a\u04f1\u0441\u043b\u0435"
    ],
    "name:pol_x_preferred":[
        "Gusli"
    ],
    "name:rus_x_preferred":[
        "\u0413\u0443\u0441\u043b\u0438"
    ],
    "name:slk_x_preferred":[
        "Gusli"
    ],
    "name:spa_x_preferred":[
        "Gusli"
    ],
    "name:swe_x_preferred":[
        "Gusli"
    ],
    "name:tur_x_preferred":[
        "Gusli"
    ],
    "name:ukr_x_preferred":[
        "\u0413\u0443\u0441\u043b\u0456"
    ],
    "name:und_x_variant":[
        "\u0413\u0443\u0441\u043b\u0438"
    ],
    "wof:name":"Gusli",
    "wof:placetype":"locality"
},
  "geometry": {"coordinates":[32.75614,52.61814],"type":"Point"}
}