{
  "type": "Feature",
  "properties": {
    "gn:admin1_code":"16",
    "gn:asciiname":"Toysi Vtoryye",
    "gn:country_code":"RU",
    "gn:dem":161,
    "gn:feature_class":"P",
    "gn:feature_code":"PPL",
    "gn:name":"Toysi Vtoryye",
    "gn:population":0,
    "gn:timezone":"Europe/Moscow",
    "iso:country":"RU",
    "name:rus_x_preferred":[
        "\u0422\u043e\u0439\u0441\u0438 \u0412\u0442\u043e\u0440\u044b\u0435"
    ],
    "name:und_x_variant":[
        "Toyzi Vtoryye"
    ],
    "wof:name":"Toysi Vtoryye",
    "wof:placetype":"locality"
},
  "geometry": {"coordinates":[47.69613,55.85599000000001],"type":"Point"}
}