{
  "type": "Feature",
  "properties": {
    "gn:admin1_code":"65",
    "gn:asciiname":"Beregovoy",
    "gn:country_code":"RU",
    "gn:dem":95,
    "gn:feature_class":"P",
    "gn:feature_code":"PPL",
    "gn:name":"Beregovoy",
    "gn:population":0,
    "gn:timezone":"Europe/Samara",
    "iso:country":"RU",
    "name:rus_x_preferred":[
        "\u0411\u0435\u0440\u0435\u0433\u043e\u0432\u043e\u0439"
    ],
    "wof:name":"Beregovoy",
    "wof:placetype":"locality"
},
  "geometry": {"coordinates":[48.4915,53.5861],"type":"Point"}
}