{
  "type": "Feature",
  "properties": {
    "gn:admin1_code":"33.0",
    "gn:asciiname":"Omelichi",
    "gn:country_code":"RU",
    "gn:dem":137,
    "gn:feature_class":"P",
    "gn:feature_code":"PPL",
    "gn:name":"Omelichi",
    "gn:population":0,
    "gn:timezone":"Europe/Kirov",
    "iso:country":"RU",
    "name:che_x_preferred":[
        "\u041e\u043c\u0435\u043b\u0438\u0447\u0438"
    ],
    "name:rus_x_preferred":[
        "\u041e\u043c\u0435\u043b\u0438\u0447\u0438"
    ],
    "wof:name":"Omelichi",
    "wof:placetype":"locality"
},
  "geometry": {"coordinates":[48.46914,58.34763],"type":"Point"}
}