{
  "type": "Feature",
  "properties": {
    "gn:admin1_code":"90",
    "gn:asciiname":"Pashevo",
    "gn:country_code":"RU",
    "gn:dem":180,
    "gn:feature_class":"P",
    "gn:feature_code":"PPL",
    "gn:name":"Pashevo",
    "gn:population":0,
    "gn:timezone":"Asia/Yekaterinburg",
    "iso:country":"RU",
    "name:eng_x_preferred":[
        "Pashevo"
    ],
    "name:nor_x_preferred":[
        "Pasjevo"
    ],
    "name:rus_x_preferred":[
        "\u041f\u0430\u0448\u0435\u0432\u043e"
    ],
    "wof:name":"Pashevo",
    "wof:placetype":"locality"
},
  "geometry": {"coordinates":[57.7419,57.3511],"type":"Point"}
}