{
  "type": "Feature",
  "properties": {
    "gn:admin1_code":"84",
    "gn:asciiname":"Sizov",
    "gn:country_code":"RU",
    "gn:dem":53,
    "gn:feature_class":"P",
    "gn:feature_code":"PPL",
    "gn:name":"Sizov",
    "gn:population":0,
    "gn:timezone":"Europe/Volgograd",
    "iso:country":"RU",
    "name:eng_x_preferred":[
        "Sizov"
    ],
    "name:nor_x_preferred":[
        "Sizov"
    ],
    "name:rus_x_preferred":[
        "\u0421\u0438\u0437\u043e\u0432"
    ],
    "wof:name":"Sizov",
    "wof:placetype":"locality"
},
  "geometry": {"coordinates":[42.28601,48.14131],"type":"Point"}
}