{
  "type": "Feature",
  "properties": {
    "gn:admin1_code":"70",
    "gn:asciiname":"Svoboda",
    "gn:cc2":"RU",
    "gn:country_code":"RU",
    "gn:dem":470,
    "gn:feature_class":"P",
    "gn:feature_code":"PPL",
    "gn:name":"Svoboda",
    "gn:population":0,
    "gn:timezone":"Europe/Moscow",
    "iso:country":"RU",
    "name:rus_x_preferred":[
        "\u0421\u0432\u043e\u0431\u043e\u0434\u0430"
    ],
    "name:und_x_variant":[
        "Svobodnyy Kirkil\u2019",
        "Svoboda",
        "\u0421\u0432\u043e\u0431\u043e\u0434\u0430"
    ],
    "wof:name":"Svoboda",
    "wof:placetype":"locality"
},
  "geometry": {"coordinates":[42.76556,44.15333],"type":"Point"}
}