{
  "type": "Feature",
  "properties": {
    "gn:admin1_code":"61",
    "gn:asciiname":"Krasnyy Kon'",
    "gn:country_code":"RU",
    "gn:dem":80,
    "gn:feature_class":"P",
    "gn:feature_code":"PPL",
    "gn:name":"Krasnyy Kon\u2019",
    "gn:population":0,
    "gn:timezone":"Europe/Moscow",
    "iso:country":"RU",
    "name:rus_x_preferred":[
        "\u041a\u0440\u0430\u0441\u043d\u044b\u0439 \u041a\u043e\u043d\u044c"
    ],
    "name:und_x_variant":[
        "Verkhovoy Kon\u2019",
        "Krasny Kon\u2019",
        "Krasnyy Kon\u2019",
        "\u041a\u0440\u0430\u0441\u043d\u044b\u0439 \u041a\u043e\u043d\u044c"
    ],
    "wof:name":"Krasnyy Kon'",
    "wof:placetype":"locality"
},
  "geometry": {"coordinates":[40.89028,46.94722],"type":"Point"}
}