{
  "type": "Feature",
  "properties": {
    "gn:admin1_code":"47",
    "gn:asciiname":"Polukhanovo",
    "gn:country_code":"RU",
    "gn:dem":152,
    "gn:feature_class":"P",
    "gn:feature_code":"PPL",
    "gn:name":"Polukhanovo",
    "gn:population":0,
    "gn:timezone":"Europe/Moscow",
    "iso:country":"RU",
    "name:rus_x_preferred":[
        "\u041f\u043e\u043b\u0443\u0445\u0430\u043d\u043e\u0432\u043e"
    ],
    "wof:name":"Polukhanovo",
    "wof:placetype":"locality"
},
  "geometry": {"coordinates":[36.6737,56.3528],"type":"Point"}
}