{
  "type": "Feature",
  "properties": {
    "gn:admin1_code":"91",
    "gn:asciiname":"Poligus",
    "gn:country_code":"RU",
    "gn:dem":130,
    "gn:feature_class":"P",
    "gn:feature_code":"PPL",
    "gn:name":"Poligus",
    "gn:population":0,
    "gn:timezone":"Asia/Krasnoyarsk",
    "iso:country":"RU",
    "name:che_x_preferred":[
        "\u041f\u043e\u043b\u0438\u0433\u0443\u0441"
    ],
    "name:eng_x_preferred":[
        "Poligus"
    ],
    "name:nor_x_preferred":[
        "Poligus"
    ],
    "name:rus_x_preferred":[
        "\u041f\u043e\u043b\u0438\u0433\u0443\u0441"
    ],
    "name:tat_x_preferred":[
        "\u041f\u043e\u043b\u0438\u0433\u0443\u0441"
    ],
    "wof:name":"Poligus",
    "wof:placetype":"locality"
},
  "geometry": {"coordinates":[94.65591999999999,61.98934000000001],"type":"Point"}
}