{
  "type": "Feature",
  "properties": {
    "gn:admin1_code":"20",
    "gn:asciiname":"Yangel'",
    "gn:country_code":"RU",
    "gn:dem":320,
    "gn:feature_class":"P",
    "gn:feature_code":"PPL",
    "gn:name":"Yangel\u2019",
    "gn:population":0,
    "gn:timezone":"Asia/Irkutsk",
    "iso:country":"RU",
    "name:rus_x_preferred":[
        "\u042f\u043d\u0433\u0435\u043b\u044c"
    ],
    "name:und_x_variant":[
        "Yangel\u2019"
    ],
    "wof:name":"Yangel'",
    "wof:placetype":"locality"
},
  "geometry": {"coordinates":[103.64570000000001,57.0558],"type":"Point"}
}