{
  "type": "Feature",
  "properties": {
    "gn:admin1_code":"20",
    "gn:asciiname":"Yangel'",
    "gn:country_code":"RU",
    "gn:dem":320,
    "gn:feature_class":"P",
    "gn:feature_code":"PPL",
    "gn:name":"Yangel\u2019",
    "gn:population":0,
    "gn:timezone":"Asia/Irkutsk",
    "iso:country":"RU",
    "name:bul_x_preferred":[
        "\u042f\u043d\u0433\u0435\u043b"
    ],
    "name:cat_x_preferred":[
        "Yangel'"
    ],
    "name:ces_x_preferred":[
        "Yangel'"
    ],
    "name:deu_x_preferred":[
        "Yangel'"
    ],
    "name:fas_x_preferred":[
        "\u06cc\u0646\u06af\u0644"
    ],
    "name:ita_x_preferred":[
        "Cratere Yangel'"
    ],
    "name:rus_x_preferred":[
        "\u042f\u043d\u0433\u0435\u043b\u044c"
    ],
    "name:spa_x_preferred":[
        "Yangel'"
    ],
    "name:und_x_variant":[
        "Yangel\u2019"
    ],
    "name:zho_x_preferred":[
        "\u626c\u683c\u5229\u9668\u77f3\u5751"
    ],
    "wof:name":"Yangel'",
    "wof:placetype":"locality"
},
  "geometry": {"coordinates":[103.64570000000001,57.0558],"type":"Point"}
}