{
  "type": "Feature",
  "properties": {
    "gn:admin1_code":"4",
    "gn:asciiname":"Oskovtsy",
    "gn:country_code":"RU",
    "gn:dem":99,
    "gn:feature_class":"P",
    "gn:feature_code":"PPL",
    "gn:name":"Oskovtsy",
    "gn:population":0,
    "gn:timezone":"Asia/Barnaul",
    "iso:country":"RU",
    "name:rus_x_preferred":[
        "\u041e\u0441\u043a\u043e\u0432\u0446\u044b"
    ],
    "wof:name":"Oskovtsy",
    "wof:placetype":"locality"
},
  "geometry": {"coordinates":[79.46666999999999,52.86666999999999],"type":"Point"}
}