{
  "type": "Feature",
  "properties": {
    "gn:admin1_code":"84.0",
    "gn:asciiname":"Erdeshkin",
    "gn:country_code":"RU",
    "gn:dem":80,
    "gn:feature_class":"P",
    "gn:feature_code":"PPL",
    "gn:name":"Erdeshkin",
    "gn:population":0,
    "gn:timezone":"Europe/Volgograd",
    "iso:country":"RU",
    "name:rus_x_preferred":[
        "\u042d\u0440\u0434\u0435\u0448\u043a\u0438\u043d"
    ],
    "wof:name":"Erdeshkin",
    "wof:placetype":"locality"
},
  "geometry": {"coordinates":[44.36444,48.44111],"type":"Point"}
}