{
  "type": "Feature",
  "properties": {
    "gn:admin1_code":"6.0",
    "gn:asciiname":"Reka Yemtsa",
    "gn:country_code":"RU",
    "gn:dem":69,
    "gn:feature_class":"P",
    "gn:feature_code":"PPL",
    "gn:name":"Reka Yemtsa",
    "gn:population":0,
    "gn:timezone":"Europe/Moscow",
    "iso:country":"RU",
    "name:eng_x_preferred":[
        "Reka Yemtsa"
    ],
    "name:nor_x_preferred":[
        "Reka-Jemtsa"
    ],
    "name:rus_x_preferred":[
        "\u0420\u0435\u043a\u0430-\u0415\u043c\u0446\u0430"
    ],
    "name:rus_x_variant":[
        "\u0420\u0435\u043a\u0430 \u0415\u043c\u0446\u0430"
    ],
    "name:und_x_variant":[
        "Pos\u00eblok Reki Yemtsa"
    ],
    "wof:name":"Reka Yemtsa",
    "wof:placetype":"locality"
},
  "geometry": {"coordinates":[40.30563,62.96389],"type":"Point"}
}