{
  "type": "Feature",
  "properties": {
    "gn:admin1_code":"54",
    "gn:asciiname":"Tishanka",
    "gn:country_code":"RU",
    "gn:dem":115,
    "gn:feature_class":"P",
    "gn:feature_code":"PPL",
    "gn:name":"Tishanka",
    "gn:population":0,
    "gn:timezone":"Asia/Omsk",
    "iso:country":"RU",
    "name:eng_x_preferred":[
        "Tishanka"
    ],
    "name:nor_x_preferred":[
        "Tisjanka"
    ],
    "name:rus_x_preferred":[
        "\u0422\u0438\u0448\u0430\u043d\u043a\u0430"
    ],
    "wof:name":"Tishanka",
    "wof:placetype":"locality"
},
  "geometry": {"coordinates":[72.9072,54.3118],"type":"Point"}
}