{
  "type": "Feature",
  "properties": {
    "gn:admin1_code":"71.0",
    "gn:asciiname":"Imennovskiy",
    "gn:country_code":"RU",
    "gn:dem":240,
    "gn:feature_class":"P",
    "gn:feature_code":"PPL",
    "gn:name":"Imennovskiy",
    "gn:population":0,
    "gn:timezone":"Asia/Yekaterinburg",
    "iso:country":"RU",
    "name:eng_x_preferred":[
        "Imennovskiy"
    ],
    "name:nor_x_preferred":[
        "Imennovskij"
    ],
    "name:rus_x_preferred":[
        "\u0418\u043c\u0435\u043d\u043d\u043e\u0432\u0441\u043a\u0438\u0439"
    ],
    "name:und_x_variant":[
        "Bol\u2019she-Imennovskiy",
        "Bol\u2019shoy Imennovskiy"
    ],
    "wof:name":"Imennovskiy",
    "wof:placetype":"locality"
},
  "geometry": {"coordinates":[59.48667,58.61028],"type":"Point"}
}