{
  "type": "Feature",
  "properties": {
    "gn:admin1_code":"42",
    "gn:asciiname":"Ozereshno",
    "gn:country_code":"RU",
    "gn:dem":54,
    "gn:feature_class":"P",
    "gn:feature_code":"PPL",
    "gn:name":"Ozereshno",
    "gn:population":0,
    "gn:timezone":"Europe/Moscow",
    "iso:country":"RU",
    "name:eng_x_preferred":[
        "Ozereshno"
    ],
    "name:nor_x_preferred":[
        "Ozeresjno"
    ],
    "name:rus_x_preferred":[
        "\u041e\u0437\u0435\u0440\u0435\u0448\u043d\u043e"
    ],
    "name:und_x_variant":[
        "Ozereshino"
    ],
    "wof:name":"Ozereshno",
    "wof:placetype":"locality"
},
  "geometry": {"coordinates":[30.40694,59.16833000000001],"type":"Point"}
}