{
  "type": "Feature",
  "properties": {
    "gn:admin1_code":"52",
    "gn:asciiname":"Gorushka",
    "gn:country_code":"RU",
    "gn:dem":96,
    "gn:feature_class":"P",
    "gn:feature_code":"PPL",
    "gn:name":"Gorushka",
    "gn:population":0,
    "gn:timezone":"Europe/Moscow",
    "iso:country":"RU",
    "name:rus_x_preferred":[
        "\u0413\u043e\u0440\u0443\u0448\u043a\u0430"
    ],
    "name:und_x_variant":[
        "\u0413\u043e\u0440\u0443\u0448\u043a\u0430"
    ],
    "wof:name":"Gorushka",
    "wof:placetype":"locality"
},
  "geometry": {"coordinates":[32.89129000000001,58.75416],"type":"Point"}
}