{
  "type": "Feature",
  "properties": {
    "gn:admin1_code":"68.0",
    "gn:asciiname":"Akhsau",
    "gn:country_code":"RU",
    "gn:dem":1476,
    "gn:feature_class":"P",
    "gn:feature_code":"PPL",
    "gn:name":"Akhsau",
    "gn:population":0,
    "gn:timezone":"Europe/Moscow",
    "iso:country":"RU",
    "name:eng_x_preferred":[
        "Akhsau"
    ],
    "name:nor_x_preferred":[
        "Akhsau"
    ],
    "name:rus_x_preferred":[
        "\u0410\u0445\u0441\u0430\u0443"
    ],
    "name:und_x_variant":[
        "\u0410\u0445\u0441\u0430\u0443",
        "Akhsau"
    ],
    "wof:name":"Akhsau",
    "wof:placetype":"locality"
},
  "geometry": {"coordinates":[43.72108,42.95824],"type":"Point"}
}