{
  "type": "Feature",
  "properties": {
    "gn:admin1_code":"7.0",
    "gn:asciiname":"Pshenichnyy",
    "gn:country_code":"RU",
    "gn:dem":-21,
    "gn:feature_class":"P",
    "gn:feature_code":"PPL",
    "gn:name":"Pshenichnyy",
    "gn:population":0,
    "gn:timezone":"Europe/Astrakhan",
    "iso:country":"RU",
    "name:rus_x_preferred":[
        "\u041f\u0448\u0435\u043d\u0438\u0447\u043d\u044b\u0439"
    ],
    "wof:name":"Pshenichnyy",
    "wof:placetype":"locality"
},
  "geometry": {"coordinates":[46.11918,48.23564],"type":"Point"}
}