{
  "type": "Feature",
  "properties": {
    "gn:admin1_code":"84.0",
    "gn:asciiname":"Borodino",
    "gn:country_code":"RU",
    "gn:dem":110,
    "gn:feature_class":"P",
    "gn:feature_code":"PPL",
    "gn:name":"Borodino",
    "gn:population":0,
    "gn:timezone":"Europe/Volgograd",
    "iso:country":"RU",
    "name:rus_x_preferred":[
        "\u0411\u043e\u0440\u043e\u0434\u0438\u043d\u043e"
    ],
    "name:und_x_variant":[
        "Borodin",
        "Borodino"
    ],
    "wof:name":"Borodino",
    "wof:placetype":"locality"
},
  "geometry": {"coordinates":[44.12038,48.88204],"type":"Point"}
}