{
  "type": "Feature",
  "properties": {
    "gn:admin1_code":"42",
    "gn:asciiname":"Zamosh'ye",
    "gn:country_code":"RU",
    "gn:dem":79,
    "gn:feature_class":"P",
    "gn:feature_code":"PPL",
    "gn:name":"Zamosh\u2019ye",
    "gn:population":0,
    "gn:timezone":"Europe/Moscow",
    "iso:country":"RU",
    "name:rus_x_preferred":[
        "\u0417\u0430\u043c\u043e\u0448\u044c\u0435"
    ],
    "name:und_x_variant":[
        "Zamosh\u2019ye"
    ],
    "wof:name":"Zamosh'ye",
    "wof:placetype":"locality"
},
  "geometry": {"coordinates":[28.7978,58.914],"type":"Point"}
}