{
  "type": "Feature",
  "properties": {
    "gn:admin1_code":"57",
    "gn:asciiname":"Tatarskaya Pendelka",
    "gn:country_code":"RU",
    "gn:dem":246,
    "gn:feature_class":"P",
    "gn:feature_code":"PPL",
    "gn:name":"Tatarskaya Pendelka",
    "gn:population":0,
    "gn:timezone":"Europe/Moscow",
    "iso:country":"RU",
    "name:eng_x_preferred":[
        "Tatarskaya Pendelka"
    ],
    "name:nor_x_preferred":[
        "Tat.Pendelka"
    ],
    "name:rus_x_preferred":[
        "\u0422\u0430\u0442.\u041f\u0435\u043d\u0434\u0435\u043b\u043a\u0430"
    ],
    "name:rus_x_variant":[
        "\u0422\u0430\u0442\u0430\u0440\u0441\u043a\u0430\u044f \u041f\u0435\u043d\u0434\u0435\u043b\u043a\u0430"
    ],
    "name:und_x_variant":[
        "Pendelka"
    ],
    "wof:name":"Tatarskaya Pendelka",
    "wof:placetype":"locality"
},
  "geometry": {"coordinates":[46.23736,53.03396],"type":"Point"}
}