{
  "type": "Feature",
  "properties": {
    "gn:admin1_code":"37.0",
    "gn:asciiname":"Fefelovo",
    "gn:country_code":"RU",
    "gn:dem":142,
    "gn:feature_class":"P",
    "gn:feature_code":"PPL",
    "gn:name":"Fefelovo",
    "gn:population":0,
    "gn:timezone":"Europe/Moscow",
    "iso:country":"RU",
    "name:eng_x_preferred":[
        "Fefelovo"
    ],
    "name:nor_x_preferred":[
        "Fefelovo"
    ],
    "name:rus_x_preferred":[
        "\u0424\u0435\u0444\u0435\u043b\u043e\u0432\u043e"
    ],
    "name:und_x_variant":[
        "Fefelova"
    ],
    "wof:name":"Fefelovo",
    "wof:placetype":"locality"
},
  "geometry": {"coordinates":[41.27165,58.18481],"type":"Point"}
}