{
  "type": "Feature",
  "properties": {
    "gn:admin1_code":"05",
    "gn:asciiname":"Lapri",
    "gn:country_code":"RU",
    "gn:dem":645,
    "gn:feature_class":"P",
    "gn:feature_code":"PPL",
    "gn:name":"Lapri",
    "gn:population":0,
    "gn:timezone":"Asia/Yakutsk",
    "iso:country":"RU",
    "name:che_x_preferred":[
        "\u041b\u0430\u043f\u0440\u0438"
    ],
    "name:eng_x_preferred":[
        "Lapri"
    ],
    "name:nor_x_preferred":[
        "Lapri"
    ],
    "name:rus_x_preferred":[
        "\u041b\u0430\u043f\u0440\u0438"
    ],
    "name:und_x_variant":[
        "Lopri"
    ],
    "wof:name":"Lapri",
    "wof:placetype":"locality"
},
  "geometry": {"coordinates":[124.90821,55.69445],"type":"Point"}
}