{
  "type": "Feature",
  "properties": {
    "gn:admin1_code":"62",
    "gn:asciiname":"Maloye Aleshkino",
    "gn:country_code":"RU",
    "gn:dem":168,
    "gn:feature_class":"P",
    "gn:feature_code":"PPL",
    "gn:name":"Maloye Al\u00ebshkino",
    "gn:population":0,
    "gn:timezone":"Europe/Moscow",
    "iso:country":"RU",
    "name:rus_x_preferred":[
        "\u041c\u0430\u043b\u043e\u0435 \u0410\u043b\u0451\u0448\u043a\u0438\u043d\u043e"
    ],
    "name:und_x_variant":[
        "Maloye Al\u00ebshkino"
    ],
    "wof:name":"Maloye Aleshkino",
    "wof:placetype":"locality"
},
  "geometry": {"coordinates":[38.9933,54.6065],"type":"Point"}
}