{
  "type": "Feature",
  "properties": {
    "gn:admin1_code":"29.0",
    "gn:asciiname":"Ulus-Mozzhukha",
    "gn:country_code":"RU",
    "gn:dem":113,
    "gn:feature_class":"P",
    "gn:feature_code":"PPL",
    "gn:name":"Ulus-Mozzhukha",
    "gn:population":0,
    "gn:timezone":"Asia/Novokuznetsk",
    "iso:country":"RU",
    "name:rus_x_preferred":[
        "\u0423\u043b\u0443\u0441-\u041c\u043e\u0437\u0436\u0443\u0445\u0430"
    ],
    "wof:name":"Ulus-Mozzhukha",
    "wof:placetype":"locality"
},
  "geometry": {"coordinates":[85.9452,55.4018],"type":"Point"}
}