{
  "type": "Feature",
  "properties": {
    "gn:admin1_code":"90",
    "gn:asciiname":"Sharvol'",
    "gn:country_code":"RU",
    "gn:dem":173,
    "gn:feature_class":"P",
    "gn:feature_code":"PPL",
    "gn:name":"Sharvol\u2019",
    "gn:population":0,
    "gn:timezone":"Asia/Yekaterinburg",
    "iso:country":"RU",
    "name:eng_x_preferred":[
        "Sharvol'"
    ],
    "name:nor_x_preferred":[
        "Sjarvol"
    ],
    "name:rus_x_preferred":[
        "\u0428\u0430\u0440\u0432\u043e\u043b\u044c"
    ],
    "name:und_x_variant":[
        "Sharvon",
        "Sharvol\u2019"
    ],
    "wof:name":"Sharvol'",
    "wof:placetype":"locality"
},
  "geometry": {"coordinates":[55.2359,59.317],"type":"Point"}
}