{
  "type": "Feature",
  "properties": {
    "gn:admin1_code":"69",
    "gn:asciiname":"Kiryakino",
    "gn:country_code":"RU",
    "gn:dem":193,
    "gn:feature_class":"P",
    "gn:feature_code":"PPL",
    "gn:name":"Kiryakino",
    "gn:population":0,
    "gn:timezone":"Europe/Moscow",
    "iso:country":"RU",
    "name:rus_x_preferred":[
        "\u041a\u0438\u0440\u044f\u043a\u0438\u043d\u043e"
    ],
    "wof:name":"Kiryakino",
    "wof:placetype":"locality"
},
  "geometry": {"coordinates":[32.1032,55.5466],"type":"Point"}
}