{
  "type": "Feature",
  "properties": {
    "gn:admin1_code":"67",
    "gn:asciiname":"Shutareva",
    "gn:country_code":"RU",
    "gn:dem":84,
    "gn:feature_class":"P",
    "gn:feature_code":"PPL",
    "gn:name":"Shutar\u00ebva",
    "gn:population":0,
    "gn:timezone":"Europe/Saratov",
    "iso:country":"RU",
    "name:rus_x_preferred":[
        "\u0428\u0443\u0442\u0430\u0440\u0451\u0432\u0430"
    ],
    "name:und_x_variant":[
        "Shutar\u00ebva"
    ],
    "wof:name":"Shutareva",
    "wof:placetype":"locality"
},
  "geometry": {"coordinates":[48.66667,50.73333],"type":"Point"}
}