{
  "type": "Feature",
  "properties": {
    "gn:admin1_code":"8",
    "gn:asciiname":"Taukay-Gayna",
    "gn:country_code":"RU",
    "gn:dem":272,
    "gn:feature_class":"P",
    "gn:feature_code":"PPL",
    "gn:name":"Taukay-Gayna",
    "gn:population":0,
    "gn:timezone":"Asia/Yekaterinburg",
    "iso:country":"RU",
    "name:rus_x_preferred":[
        "\u0422\u0430\u0443\u043a\u0430\u0439-\u0413\u0430\u0439\u043d\u0430"
    ],
    "name:und_x_variant":[
        "Taukay-Gayny"
    ],
    "wof:name":"Taukay-Gayna",
    "wof:placetype":"locality"
},
  "geometry": {"coordinates":[54.9569,53.4601],"type":"Point"}
}