{
  "type": "Feature",
  "properties": {
    "gn:admin1_code":"55",
    "gn:asciiname":"Kayapkulovo",
    "gn:country_code":"RU",
    "gn:dem":117,
    "gn:feature_class":"P",
    "gn:feature_code":"PPL",
    "gn:name":"Kayapkulovo",
    "gn:population":0,
    "gn:timezone":"Asia/Yekaterinburg",
    "iso:country":"RU",
    "name:rus_x_preferred":[
        "\u041a\u0430\u044f\u043f\u043a\u0443\u043b\u043e\u0432\u043e"
    ],
    "wof:name":"Kayapkulovo",
    "wof:placetype":"locality"
},
  "geometry": {"coordinates":[54.16667,52.65],"type":"Point"}
}