{
  "type": "Feature",
  "properties": {
    "gn:admin1_code":"60",
    "gn:asciiname":"Udachino",
    "gn:country_code":"RU",
    "gn:dem":132,
    "gn:feature_class":"P",
    "gn:feature_code":"PPL",
    "gn:name":"Udachino",
    "gn:population":0,
    "gn:timezone":"Europe/Moscow",
    "iso:country":"RU",
    "name:rus_x_preferred":[
        "\u0423\u0434\u0430\u0447\u0438\u043d\u043e"
    ],
    "name:und_x_variant":[
        "\u0423\u0434\u0430\u0447\u0438\u043d\u043e"
    ],
    "wof:name":"Udachino",
    "wof:placetype":"locality"
},
  "geometry": {"coordinates":[30.9154,56.3192],"type":"Point"}
}