{
  "type": "Feature",
  "properties": {
    "gn:admin1_code":"53",
    "gn:asciiname":"Vozdvizhenka",
    "gn:country_code":"RU",
    "gn:dem":107,
    "gn:feature_class":"P",
    "gn:feature_code":"PPL",
    "gn:name":"Vozdvizhenka",
    "gn:population":0,
    "gn:timezone":"Asia/Novosibirsk",
    "iso:country":"RU",
    "name:eng_x_preferred":[
        "Vozdvizhenka"
    ],
    "name:nor_x_preferred":[
        "Vozdvizjenka"
    ],
    "name:rus_x_preferred":[
        "\u0412\u043e\u0437\u0434\u0432\u0438\u0436\u0435\u043d\u043a\u0430"
    ],
    "wof:name":"Vozdvizhenka",
    "wof:placetype":"locality"
},
  "geometry": {"coordinates":[75.28623,55.28301],"type":"Point"}
}