{
  "type": "Feature",
  "properties": {
    "gn:admin1_code":"6",
    "gn:asciiname":"Guzhevo",
    "gn:country_code":"RU",
    "gn:dem":127,
    "gn:feature_class":"P",
    "gn:feature_code":"PPL",
    "gn:name":"Guzhevo",
    "gn:population":0,
    "gn:timezone":"Europe/Moscow",
    "iso:country":"RU",
    "name:rus_x_preferred":[
        "\u0413\u0443\u0436\u0435\u0432\u043e"
    ],
    "name:und_x_variant":[
        "\u0413\u0443\u0436\u0435\u0432\u043e"
    ],
    "wof:name":"Guzhevo",
    "wof:placetype":"locality"
},
  "geometry": {"coordinates":[38.95282,61.57773],"type":"Point"}
}