{
  "type": "Feature",
  "properties": {
    "gn:admin1_code":"72.0",
    "gn:asciiname":"Gavrilovka",
    "gn:country_code":"RU",
    "gn:dem":158,
    "gn:feature_class":"P",
    "gn:feature_code":"PPL",
    "gn:name":"Gavrilovka",
    "gn:population":0,
    "gn:timezone":"Europe/Moscow",
    "iso:country":"RU",
    "name:rus_x_preferred":[
        "\u0413\u0430\u0432\u0440\u0438\u043b\u043e\u0432\u043a\u0430"
    ],
    "name:und_x_variant":[
        "Novyye Donskiye",
        "Gavrilovka"
    ],
    "wof:name":"Gavrilovka",
    "wof:placetype":"locality"
},
  "geometry": {"coordinates":[41.56124000000001,52.1356],"type":"Point"}
}