{
  "type": "Feature",
  "properties": {
    "gn:admin1_code":"77",
    "gn:asciiname":"Gladkoye",
    "gn:country_code":"RU",
    "gn:dem":232,
    "gn:feature_class":"P",
    "gn:feature_code":"PPL",
    "gn:name":"Gladkoye",
    "gn:population":0,
    "gn:timezone":"Europe/Moscow",
    "iso:country":"RU",
    "name:rus_x_preferred":[
        "\u0413\u043b\u0430\u0434\u043a\u043e\u0435"
    ],
    "name:und_x_variant":[
        "\u0413\u043b\u0430\u0434\u043a\u043e\u0435"
    ],
    "wof:name":"Gladkoye",
    "wof:placetype":"locality"
},
  "geometry": {"coordinates":[33.2326,56.98862],"type":"Point"}
}