{
  "type": "Feature",
  "properties": {
    "gn:admin1_code":"24.0",
    "gn:asciiname":"Badzhankinovskiy",
    "gn:country_code":"RU",
    "gn:dem":117,
    "gn:feature_class":"P",
    "gn:feature_code":"PPL",
    "gn:name":"Badzhankinovskiy",
    "gn:population":0,
    "gn:timezone":"Europe/Moscow",
    "iso:country":"RU",
    "name:nor_x_preferred":[
        "Badzjankinovskij"
    ],
    "name:rus_x_preferred":[
        "\u0411\u0430\u0434\u0436\u0430\u043d\u043a\u0438\u043d\u043e\u0432\u0441\u043a\u0438\u0439"
    ],
    "wof:name":"Badzhankinovskiy",
    "wof:placetype":"locality"
},
  "geometry": {"coordinates":[44.4575,46.09778],"type":"Point"}
}