{
  "type": "Feature",
  "properties": {
    "gn:admin1_code":"33",
    "gn:asciiname":"Izipovka",
    "gn:country_code":"RU",
    "gn:dem":94,
    "gn:feature_class":"P",
    "gn:feature_code":"PPL",
    "gn:name":"Izipovka",
    "gn:population":0,
    "gn:timezone":"Europe/Kirov",
    "iso:country":"RU",
    "name:rus_x_preferred":[
        "\u0418\u0437\u0438\u043f\u043e\u0432\u043a\u0430"
    ],
    "wof:name":"Izipovka",
    "wof:placetype":"locality"
},
  "geometry": {"coordinates":[47.87714,57.82633000000001],"type":"Point"}
}