{
  "type": "Feature",
  "properties": {
    "gn:admin1_code":"47.0",
    "gn:asciiname":"Savino",
    "gn:country_code":"RU",
    "gn:dem":171,
    "gn:feature_class":"P",
    "gn:feature_code":"PPL",
    "gn:name":"Savino",
    "gn:population":0,
    "gn:timezone":"Europe/Moscow",
    "iso:country":"RU",
    "name:ceb_x_preferred":[
        "Savino"
    ],
    "name:deu_x_preferred":[
        "Savino"
    ],
    "name:ita_x_preferred":[
        "Savino"
    ],
    "name:pol_x_preferred":[
        "Savino"
    ],
    "wof:name":"Savino",
    "wof:placetype":"locality"
},
  "geometry": {"coordinates":[37.99663,54.975],"type":"Point"}
}