{
  "type": "Feature",
  "properties": {
    "gn:admin1_code":"88.0",
    "gn:asciiname":"Antonovo",
    "gn:country_code":"RU",
    "gn:dem":142,
    "gn:feature_class":"P",
    "gn:feature_code":"PPL",
    "gn:name":"Antonovo",
    "gn:population":0,
    "gn:timezone":"Europe/Moscow",
    "iso:country":"RU",
    "name:azb_x_preferred":[
        "\u0627\u0646\u062a\u0648\u0646\u0648\u0648"
    ],
    "name:bul_x_preferred":[
        "\u0410\u043d\u0442\u043e\u043d\u043e\u0432\u043e"
    ],
    "name:ckb_x_preferred":[
        "\u0626\u0627\u0646\u062a\u06c6\u0646\u06c6\u06a4\u06c6"
    ],
    "name:deu_x_preferred":[
        "Antonowo"
    ],
    "name:fas_x_preferred":[
        "\u0622\u0646\u062a\u0648\u0646\u0648\u0641\u0648"
    ],
    "name:kaz_x_preferred":[
        "\u0410\u043d\u0442\u043e\u043d\u043e\u0432\u043e"
    ],
    "name:nld_x_preferred":[
        "Antonovo"
    ],
    "name:nor_x_preferred":[
        "Antonovo"
    ],
    "name:pol_x_preferred":[
        "Antonowo"
    ],
    "name:por_x_preferred":[
        "Antonovo"
    ],
    "name:ron_x_preferred":[
        "Antonovo"
    ],
    "name:rus_x_preferred":[
        "\u0410\u043d\u0442\u043e\u043d\u043e\u0432\u043e"
    ],
    "name:spa_x_preferred":[
        "Antonovo"
    ],
    "name:srp_x_preferred":[
        "\u0410\u043d\u0442\u043e\u043d\u043e\u0432\u043e"
    ],
    "name:tur_x_preferred":[
        "Yaylak\u00f6y"
    ],
    "name:ukr_x_preferred":[
        "\u0410\u043d\u0442\u043e\u043d\u043e\u0432\u043e"
    ],
    "name:vie_x_preferred":[
        "Antonovo"
    ],
    "name:war_x_preferred":[
        "Antonovo"
    ],
    "name:zho_x_preferred":[
        "\u5b89\u6771\u8afe\u6c83"
    ],
    "wof:name":"Antonovo",
    "wof:placetype":"locality"
},
  "geometry": {"coordinates":[39.03164,57.93481],"type":"Point"}
}