{
  "type": "Feature",
  "properties": {
    "gn:admin1_code":"31",
    "gn:asciiname":"Polovinka",
    "gn:cc2":"RU",
    "gn:country_code":"RU",
    "gn:dem":525,
    "gn:feature_class":"P",
    "gn:feature_code":"PPL",
    "gn:name":"Polovinka",
    "gn:population":0,
    "gn:timezone":"Asia/Krasnoyarsk",
    "iso:country":"RU",
    "name:eng_x_preferred":[
        "Polovinka"
    ],
    "name:nor_x_preferred":[
        "Polovinka"
    ],
    "name:rus_x_preferred":[
        "\u041f\u043e\u043b\u043e\u0432\u0438\u043d\u043a\u0430"
    ],
    "name:und_x_variant":[
        "Palovinka"
    ],
    "wof:name":"Polovinka",
    "wof:placetype":"locality"
},
  "geometry": {"coordinates":[89.31889,54.52472],"type":"Point"}
}