{
  "type": "Feature",
  "properties": {
    "gn:admin1_code":"47",
    "gn:asciiname":"Gusenevo",
    "gn:country_code":"RU",
    "gn:dem":246,
    "gn:feature_class":"P",
    "gn:feature_code":"PPL",
    "gn:name":"Gusenevo",
    "gn:population":0,
    "gn:timezone":"Europe/Moscow",
    "iso:country":"RU",
    "name:rus_x_preferred":[
        "\u0413\u0443\u0441\u0435\u043d\u0435\u0432\u043e"
    ],
    "wof:name":"Gusenevo",
    "wof:placetype":"locality"
},
  "geometry": {"coordinates":[36.2016,56.0368],"type":"Point"}
}