{
  "type": "Feature",
  "properties": {
    "gn:admin1_code":"51",
    "gn:asciiname":"Tipayki",
    "gn:country_code":"RU",
    "gn:dem":129,
    "gn:feature_class":"P",
    "gn:feature_code":"PPL",
    "gn:name":"Tipayki",
    "gn:population":0,
    "gn:timezone":"Europe/Volgograd",
    "iso:country":"RU",
    "name:rus_x_preferred":[
        "\u0422\u0438\u043f\u0430\u0439\u043a\u0438"
    ],
    "name:und_x_variant":[
        "\u0422\u0438\u043f\u0430\u0439\u043a\u0438"
    ],
    "wof:name":"Tipayki",
    "wof:placetype":"locality"
},
  "geometry": {"coordinates":[46.7157,57.36600000000001],"type":"Point"}
}