{
  "type": "Feature",
  "properties": {
    "gn:admin1_code":"11",
    "gn:asciiname":"Khilgantuy",
    "gn:cc2":"RU",
    "gn:country_code":"RU",
    "gn:dem":608,
    "gn:feature_class":"P",
    "gn:feature_code":"PPL",
    "gn:name":"Khilgantuy",
    "gn:population":0,
    "gn:timezone":"Asia/Irkutsk",
    "iso:country":"RU",
    "name:eng_x_preferred":[
        "Khilgantuy"
    ],
    "name:nor_x_preferred":[
        "Khilgantuj"
    ],
    "name:rus_x_preferred":[
        "\u0425\u0438\u043b\u0433\u0430\u043d\u0442\u0443\u0439"
    ],
    "name:und_x_variant":[
        "Khilganta",
        "\u0425\u0438\u043b\u0433\u0430\u043d\u0442\u0443\u0439",
        "Khilgantuy"
    ],
    "wof:name":"Khilgantuy",
    "wof:placetype":"locality"
},
  "geometry": {"coordinates":[106.88833,50.43056],"type":"Point"}
}