{
  "type": "Feature",
  "properties": {
    "gn:admin1_code":"8",
    "gn:asciiname":"Osipovskiy",
    "gn:country_code":"RU",
    "gn:dem":136,
    "gn:feature_class":"P",
    "gn:feature_code":"PPL",
    "gn:name":"Osipovskiy",
    "gn:population":0,
    "gn:timezone":"Asia/Yekaterinburg",
    "iso:country":"RU",
    "name:rus_x_preferred":[
        "\u041e\u0441\u0438\u043f\u043e\u0432\u0441\u043a\u0438\u0439"
    ],
    "name:und_x_variant":[
        "\u041e\u0441\u0438\u043f\u043e\u0432\u0441\u043a\u0438\u0439"
    ],
    "wof:name":"Osipovskiy",
    "wof:placetype":"locality"
},
  "geometry": {"coordinates":[55.85,53.48333],"type":"Point"}
}