{
  "type": "Feature",
  "properties": {
    "gn:admin1_code":"76",
    "gn:asciiname":"Zakopy",
    "gn:country_code":"RU",
    "gn:dem":163,
    "gn:feature_class":"P",
    "gn:feature_code":"PPL",
    "gn:name":"Zakopy",
    "gn:population":0,
    "gn:timezone":"Europe/Moscow",
    "iso:country":"RU",
    "name:eng_x_preferred":[
        "Zakopy"
    ],
    "name:nor_x_preferred":[
        "Zakopy"
    ],
    "name:rus_x_preferred":[
        "\u0417\u0430\u043a\u043e\u043f\u044b"
    ],
    "wof:name":"Zakopy",
    "wof:placetype":"locality"
},
  "geometry": {"coordinates":[37.92694,53.19971999999999],"type":"Point"}
}