{
  "type": "Feature",
  "properties": {
    "gn:admin1_code":"85",
    "gn:asciiname":"Vidakhino",
    "gn:country_code":"RU",
    "gn:dem":165,
    "gn:feature_class":"P",
    "gn:feature_code":"PPL",
    "gn:name":"Vidakhino",
    "gn:population":0,
    "gn:timezone":"Europe/Moscow",
    "iso:country":"RU",
    "name:eng_x_preferred":[
        "Vidakhino"
    ],
    "name:nor_x_preferred":[
        "Vidakhino"
    ],
    "name:rus_x_preferred":[
        "\u0412\u0438\u0434\u0430\u0445\u0438\u043d\u043e"
    ],
    "wof:name":"Vidakhino",
    "wof:placetype":"locality"
},
  "geometry": {"coordinates":[46.88333,60.71666999999999],"type":"Point"}
}