{
  "type": "Feature",
  "properties": {
    "gn:admin1_code":"65",
    "gn:asciiname":"Laskarevka",
    "gn:country_code":"RU",
    "gn:dem":87,
    "gn:feature_class":"P",
    "gn:feature_code":"PPL",
    "gn:name":"Laskar\u00ebvka",
    "gn:population":0,
    "gn:timezone":"Europe/Samara",
    "iso:country":"RU",
    "name:rus_x_preferred":[
        "\u041b\u0430\u0441\u043a\u0430\u0440\u00eb\u0432\u043a\u0430"
    ],
    "name:und_x_variant":[
        "Laskar\u00ebvka",
        "Bereznyaki"
    ],
    "wof:name":"Laskarevka",
    "wof:placetype":"locality"
},
  "geometry": {"coordinates":[51.724,53.2266],"type":"Point"}
}