{
  "type": "Feature",
  "properties": {
    "gn:admin1_code":"60",
    "gn:asciiname":"Poletayevo",
    "gn:country_code":"RU",
    "gn:dem":101,
    "gn:feature_class":"P",
    "gn:feature_code":"PPL",
    "gn:name":"Poletayevo",
    "gn:population":0,
    "gn:timezone":"Europe/Moscow",
    "iso:country":"RU",
    "name:rus_x_preferred":[
        "\u041f\u043e\u043b\u0435\u0442\u0430\u0435\u0432\u043e"
    ],
    "wof:name":"Poletayevo",
    "wof:placetype":"locality"
},
  "geometry": {"coordinates":[28.37445,56.66598000000001],"type":"Point"}
}