{
  "type": "Feature",
  "properties": {
    "gn:admin1_code":"71",
    "gn:asciiname":"Cheboltasovo",
    "gn:country_code":"RU",
    "gn:dem":62,
    "gn:feature_class":"P",
    "gn:feature_code":"PPL",
    "gn:name":"Cheboltasovo",
    "gn:population":0,
    "gn:timezone":"Asia/Yekaterinburg",
    "iso:country":"RU",
    "name:eng_x_preferred":[
        "Cheboltasovo"
    ],
    "name:nor_x_preferred":[
        "Tsjeboltasovo"
    ],
    "name:rus_x_preferred":[
        "\u0427\u0435\u0431\u043e\u043b\u0442\u0430\u0441\u043e\u0432\u043e"
    ],
    "name:und_x_variant":[
        "Cheboltasova"
    ],
    "wof:name":"Cheboltasovo",
    "wof:placetype":"locality"
},
  "geometry": {"coordinates":[63.88136,58.00697],"type":"Point"}
}