{
  "type": "Feature",
  "properties": {
    "gn:admin1_code":"43",
    "gn:asciiname":"Starodubovskiy",
    "gn:country_code":"RU",
    "gn:dem":175,
    "gn:feature_class":"P",
    "gn:feature_code":"PPL",
    "gn:name":"Starodubovskiy",
    "gn:population":0,
    "gn:timezone":"Europe/Moscow",
    "iso:country":"RU",
    "name:rus_x_preferred":[
        "\u0421\u0442\u0430\u0440\u043e\u0434\u0443\u0431\u043e\u0432\u0441\u043a\u0438\u0439"
    ],
    "wof:name":"Starodubovskiy",
    "wof:placetype":"locality"
},
  "geometry": {"coordinates":[39.0642,52.2549],"type":"Point"}
}