{
  "type": "Feature",
  "properties": {
    "gn:admin1_code":"80",
    "gn:asciiname":"Kochukovo",
    "gn:country_code":"RU",
    "gn:dem":199,
    "gn:feature_class":"P",
    "gn:feature_code":"PPL",
    "gn:name":"Kochukovo",
    "gn:population":0,
    "gn:timezone":"Europe/Samara",
    "iso:country":"RU",
    "name:rus_x_preferred":[
        "\u041a\u043e\u0447\u0443\u043a\u043e\u0432\u043e"
    ],
    "name:und_x_variant":[
        "\u041a\u043e\u0447\u0443\u043a\u043e\u0432\u043e"
    ],
    "wof:name":"Kochukovo",
    "wof:placetype":"locality"
},
  "geometry": {"coordinates":[52.0504,57.9518],"type":"Point"}
}