{
  "type": "Feature",
  "properties": {
    "gn:admin1_code":"77",
    "gn:asciiname":"Dor",
    "gn:country_code":"RU",
    "gn:dem":162,
    "gn:feature_class":"P",
    "gn:feature_code":"PPL",
    "gn:name":"Dor",
    "gn:population":0,
    "gn:timezone":"Europe/Moscow",
    "iso:country":"RU",
    "name:rus_x_preferred":[
        "\u0414\u043e\u0440"
    ],
    "name:und_x_variant":[
        "\u0414\u043e\u0440"
    ],
    "wof:name":"Dor",
    "wof:placetype":"locality"
},
  "geometry": {"coordinates":[37.1648,58.1127],"type":"Point"}
}