{
  "type": "Feature",
  "properties": {
    "gn:admin1_code":"90.0",
    "gn:asciiname":"Altynnoye",
    "gn:country_code":"RU",
    "gn:dem":257,
    "gn:feature_class":"P",
    "gn:feature_code":"PPL",
    "gn:name":"Altynnoye",
    "gn:population":0,
    "gn:timezone":"Asia/Yekaterinburg",
    "iso:country":"RU",
    "name:eng_x_preferred":[
        "Altynnoye"
    ],
    "name:nor_x_preferred":[
        "Altynnoje"
    ],
    "name:rus_x_preferred":[
        "\u0410\u043b\u0442\u044b\u043d\u043d\u043e\u0435"
    ],
    "wof:name":"Altynnoye",
    "wof:placetype":"locality"
},
  "geometry": {"coordinates":[57.1398,56.8179],"type":"Point"}
}