{
  "type": "Feature",
  "properties": {
    "gn:admin1_code":"76",
    "gn:asciiname":"Myshenki",
    "gn:country_code":"RU",
    "gn:dem":233,
    "gn:feature_class":"P",
    "gn:feature_code":"PPL",
    "gn:name":"Mysh\u00ebnki",
    "gn:population":0,
    "gn:timezone":"Europe/Moscow",
    "iso:country":"RU",
    "name:rus_x_preferred":[
        "\u041c\u044b\u0448\u0451\u043d\u043a\u0438"
    ],
    "name:und_x_variant":[
        "Mysh\u00ebnki"
    ],
    "wof:name":"Myshenki",
    "wof:placetype":"locality"
},
  "geometry": {"coordinates":[37.44456,54.71041999999999],"type":"Point"}
}