{
  "type": "Feature",
  "properties": {
    "gn:country":"RU",
    "gn:fcode":"PPL",
    "gn:pop":0,
    "iso:country":"RU",
    "name:eng_x_preferred":[
        "Beregovoye"
    ],
    "name:nor_x_preferred":[
        "Beregovoje"
    ],
    "name:rus_x_preferred":[
        "\u0411\u0435\u0440\u0435\u0433\u043e\u0432\u043e\u0435"
    ],
    "name:unk_x_variant":[
        "Beregovaya"
    ],
    "qs:name":"Beregovoye",
    "qs:name_adm0":"Russia",
    "qs:name_adm1":"Krasnodar Krai",
    "qs:photos":101,
    "qs:photos_1k":20,
    "qs:photos_9k":1,
    "qs:photos_9r":3,
    "qs:photos_all":101,
    "qs:photos_sr":3,
    "qs:placetype":"Town",
    "qs:pop_sr":"0",
    "wd:wordcount":397,
    "wof:name":"Beregovoye",
    "wof:placetype":"locality",
    "wof:population":0
},
  "geometry": {"coordinates":[38.3637,44.4181],"type":"Point"}
}