{
  "type": "Feature",
  "properties": {
    "gn:admin1_code":"73",
    "gn:asciiname":"Kzyl-Kech",
    "gn:country_code":"RU",
    "gn:dem":81,
    "gn:feature_class":"P",
    "gn:feature_code":"PPL",
    "gn:name":"Kzyl-Kech",
    "gn:population":0,
    "gn:timezone":"Europe/Moscow",
    "iso:country":"RU",
    "name:rus_x_preferred":[
        "\u041a\u0437\u044b\u043b-\u041a\u0435\u0447"
    ],
    "name:und_x_variant":[
        "\u041a\u0437\u044b\u043b-\u041a\u0435\u0447"
    ],
    "wof:name":"Kzyl-Kech",
    "wof:placetype":"locality"
},
  "geometry": {"coordinates":[51.5774,54.8988],"type":"Point"}
}