{
  "type": "Feature",
  "properties": {
    "gn:admin1_code":"38.0",
    "gn:asciiname":"Mostovyanskiy",
    "gn:country_code":"RU",
    "gn:dem":-1,
    "gn:feature_class":"P",
    "gn:feature_code":"PPL",
    "gn:name":"Mostovyanskiy",
    "gn:population":0,
    "gn:timezone":"Europe/Moscow",
    "iso:country":"RU",
    "name:rus_x_preferred":[
        "\u041c\u043e\u0441\u0442\u043e\u0432\u044f\u043d\u0441\u043a\u0438\u0439"
    ],
    "wof:name":"Mostovyanskiy",
    "wof:placetype":"locality"
},
  "geometry": {"coordinates":[37.75373,45.58176],"type":"Point"}
}