{
  "type": "Feature",
  "properties": {
    "gn:admin1_code":"41",
    "gn:asciiname":"Testovo",
    "gn:country_code":"RU",
    "gn:dem":177,
    "gn:feature_class":"P",
    "gn:feature_code":"PPL",
    "gn:name":"Testovo",
    "gn:population":0,
    "gn:timezone":"Europe/Moscow",
    "iso:country":"RU",
    "name:eng_x_preferred":[
        "Testovo"
    ],
    "name:nor_x_preferred":[
        "Titovo"
    ],
    "name:rus_x_preferred":[
        "\u0422\u0438\u0442\u043e\u0432\u043e"
    ],
    "wof:name":"Testovo",
    "wof:placetype":"locality"
},
  "geometry": {"coordinates":[36.64222,51.78083],"type":"Point"}
}