{
  "type": "Feature",
  "properties": {
    "gn:admin1_code":"77",
    "gn:asciiname":"Shinkovo",
    "gn:country_code":"RU",
    "gn:dem":159,
    "gn:feature_class":"P",
    "gn:feature_code":"PPL",
    "gn:name":"Shinkovo",
    "gn:population":0,
    "gn:timezone":"Europe/Moscow",
    "iso:country":"RU",
    "name:rus_x_preferred":[
        "\u0428\u0438\u043d\u043a\u043e\u0432\u043e"
    ],
    "name:und_x_variant":[
        "Shinkino",
        "Shinkovo",
        "\u0428\u0438\u043d\u043a\u043e\u0432\u043e"
    ],
    "wof:name":"Shinkovo",
    "wof:placetype":"locality"
},
  "geometry": {"coordinates":[31.50898,56.05071],"type":"Point"}
}