{
  "type": "Feature",
  "properties": {
    "gn:admin1_code":"73",
    "gn:asciiname":"Kadybash",
    "gn:country_code":"RU",
    "gn:dem":106,
    "gn:feature_class":"P",
    "gn:feature_code":"PPL",
    "gn:name":"Kadybash",
    "gn:population":0,
    "gn:timezone":"Europe/Moscow",
    "iso:country":"RU",
    "name:eng_x_preferred":[
        "Kadybash"
    ],
    "name:nor_x_preferred":[
        "Kadybasj"
    ],
    "name:rus_x_preferred":[
        "\u041a\u0430\u0434\u044b\u0431\u0430\u0448"
    ],
    "name:und_x_variant":[
        "Kadybashevo"
    ],
    "wof:name":"Kadybash",
    "wof:placetype":"locality"
},
  "geometry": {"coordinates":[53.42264,56.15836],"type":"Point"}
}