{
  "type": "Feature",
  "properties": {
    "gn:admin1_code":"93",
    "gn:asciiname":"Ushmun",
    "gn:country_code":"RU",
    "gn:dem":668,
    "gn:feature_class":"P",
    "gn:feature_code":"PPL",
    "gn:name":"Ushmun",
    "gn:population":0,
    "gn:timezone":"Asia/Chita",
    "iso:country":"RU",
    "name:eng_x_preferred":[
        "Ushmun"
    ],
    "name:nor_x_preferred":[
        "Usjmun"
    ],
    "name:rus_x_preferred":[
        "\u0423\u0448\u043c\u0443\u043d"
    ],
    "name:und_x_variant":[
        "Ushumun",
        "Ushmin",
        "Ushmun"
    ],
    "wof:name":"Ushmun",
    "wof:placetype":"locality"
},
  "geometry": {"coordinates":[118.36196,51.68216],"type":"Point"}
}