{
  "type": "Feature",
  "properties": {
    "gn:admin1_code":"88",
    "gn:asciiname":"Mikhalevo",
    "gn:country_code":"RU",
    "gn:dem":198,
    "gn:feature_class":"P",
    "gn:feature_code":"PPL",
    "gn:name":"Mikhal\u00ebvo",
    "gn:population":0,
    "gn:timezone":"Europe/Moscow",
    "iso:country":"RU",
    "name:rus_x_preferred":[
        "\u041c\u0438\u0445\u0430\u043b\u0451\u0432\u043e"
    ],
    "name:und_x_variant":[
        "Mikhal\u00ebvo"
    ],
    "wof:name":"Mikhalevo",
    "wof:placetype":"locality"
},
  "geometry": {"coordinates":[39.1426,56.688],"type":"Point"}
}