{
  "type": "Feature",
  "properties": {
    "gn:admin1_code":"73",
    "gn:asciiname":"Yulbat",
    "gn:country_code":"RU",
    "gn:dem":113,
    "gn:feature_class":"P",
    "gn:feature_code":"PPL",
    "gn:name":"Yulbat",
    "gn:population":0,
    "gn:timezone":"Europe/Moscow",
    "iso:country":"RU",
    "name:rus_x_preferred":[
        "\u042e\u043b\u0431\u0430\u0442"
    ],
    "wof:name":"Yulbat",
    "wof:placetype":"locality"
},
  "geometry": {"coordinates":[50.46528,55.95194],"type":"Point"}
}