{
  "type": "Feature",
  "properties": {
    "gn:admin1_code":"78",
    "gn:asciiname":"Maloye Bokovo",
    "gn:cc2":"RU",
    "gn:country_code":"RU",
    "gn:dem":110,
    "gn:feature_class":"P",
    "gn:feature_code":"PPL",
    "gn:name":"Maloye Bokovo",
    "gn:population":0,
    "gn:timezone":"Asia/Yekaterinburg",
    "iso:country":"RU",
    "name:eng_x_preferred":[
        "Maloye Bokovo"
    ],
    "name:nor_x_preferred":[
        "Bokova"
    ],
    "name:rus_x_preferred":[
        "\u0411\u043e\u043a\u043e\u0432\u0430"
    ],
    "name:rus_x_variant":[
        "\u041c\u0430\u043b\u043e\u0435 \u0411\u043e\u043a\u043e\u0432\u043e"
    ],
    "name:und_x_variant":[
        "Bokovo"
    ],
    "wof:name":"Maloye Bokovo",
    "wof:placetype":"locality"
},
  "geometry": {"coordinates":[70.36667,56.13333000000001],"type":"Point"}
}