{
  "type": "Feature",
  "properties": {
    "gn:admin1_code":"88",
    "gn:asciiname":"Serkovo",
    "gn:country_code":"RU",
    "gn:dem":141,
    "gn:feature_class":"P",
    "gn:feature_code":"PPL",
    "gn:name":"Serkovo",
    "gn:population":0,
    "gn:timezone":"Europe/Moscow",
    "iso:country":"RU",
    "name:rus_x_preferred":[
        "\u0421\u0435\u0440\u043a\u043e\u0432\u043e"
    ],
    "wof:name":"Serkovo",
    "wof:placetype":"locality"
},
  "geometry": {"coordinates":[40.32184,58.11071],"type":"Point"}
}