{
  "type": "Feature",
  "properties": {
    "gn:admin1_code":"33",
    "gn:asciiname":"Sukhorech'ye",
    "gn:country_code":"RU",
    "gn:dem":124,
    "gn:feature_class":"P",
    "gn:feature_code":"PPL",
    "gn:name":"Sukhorech\u2019ye",
    "gn:population":0,
    "gn:timezone":"Europe/Kirov",
    "iso:country":"RU",
    "name:rus_x_preferred":[
        "\u0421\u0443\u0445\u043e\u0440\u0435\u0447\u044c\u0435"
    ],
    "name:und_x_variant":[
        "Sukhorech\u2019ye",
        "\u0421\u0443\u0445\u043e\u0440\u0435\u0447\u044c\u0435"
    ],
    "wof:name":"Sukhorech'ye",
    "wof:placetype":"locality"
},
  "geometry": {"coordinates":[48.28333,57.31667],"type":"Point"}
}