{
  "type": "Feature",
  "properties": {
    "gn:admin1_code":"42",
    "gn:asciiname":"Malyye Bornitsy",
    "gn:country_code":"RU",
    "gn:dem":138,
    "gn:feature_class":"P",
    "gn:feature_code":"PPL",
    "gn:name":"Malyye Bornitsy",
    "gn:population":0,
    "gn:timezone":"Europe/Moscow",
    "iso:country":"RU",
    "name:fin_x_preferred":[
        "Vilhosi"
    ],
    "name:nor_x_preferred":[
        "Malye Bornitsy"
    ],
    "name:rus_x_preferred":[
        "\u041c\u0430\u043b\u044b\u0435 \u0411\u043e\u0440\u043d\u0438\u0446\u044b"
    ],
    "wof:name":"Malyye Bornitsy",
    "wof:placetype":"locality"
},
  "geometry": {"coordinates":[29.87593,59.51379],"type":"Point"}
}