{
  "type": "Feature",
  "properties": {
    "gn:admin1_code":"56",
    "gn:asciiname":"Dolgoye",
    "gn:country_code":"RU",
    "gn:dem":250,
    "gn:feature_class":"P",
    "gn:feature_code":"PPL",
    "gn:name":"Dolgoye",
    "gn:population":0,
    "gn:timezone":"Europe/Moscow",
    "iso:country":"RU",
    "name:rus_x_preferred":[
        "\u0414\u043e\u043b\u0433\u043e\u0435"
    ],
    "wof:name":"Dolgoye",
    "wof:placetype":"locality"
},
  "geometry": {"coordinates":[36.91125,53.21233],"type":"Point"}
}