{
  "type": "Feature",
  "properties": {
    "gn:admin1_code":"56",
    "gn:asciiname":"Golubets",
    "gn:country_code":"RU",
    "gn:dem":220,
    "gn:feature_class":"P",
    "gn:feature_code":"PPL",
    "gn:name":"Golubets",
    "gn:population":0,
    "gn:timezone":"Europe/Moscow",
    "iso:country":"RU",
    "name:rus_x_preferred":[
        "\u0413\u043e\u043b\u0443\u0431\u0435\u0446"
    ],
    "wof:name":"Golubets",
    "wof:placetype":"locality"
},
  "geometry": {"coordinates":[36.74,52.4323],"type":"Point"}
}