{
  "type": "Feature",
  "properties": {
    "gn:admin1_code":"75.0",
    "gn:asciiname":"Petrovskiy Uchastok",
    "gn:country_code":"RU",
    "gn:dem":89,
    "gn:feature_class":"P",
    "gn:feature_code":"PPL",
    "gn:name":"Petrovskiy Uchastok",
    "gn:population":0,
    "gn:timezone":"Asia/Tomsk",
    "iso:country":"RU",
    "name:rus_x_preferred":[
        "\u041f\u0435\u0442\u0440\u043e\u0432\u0441\u043a\u0438\u0439 \u0423\u0447\u0430\u0441\u0442\u043e\u043a"
    ],
    "name:und_x_variant":[
        "Uchastok Petrovskiy"
    ],
    "wof:name":"Petrovskiy Uchastok",
    "wof:placetype":"locality"
},
  "geometry": {"coordinates":[84.7925,56.51862],"type":"Point"}
}