{
  "type": "Feature",
  "properties": {
    "gn:admin1_code":"59",
    "gn:asciiname":"De-Friz",
    "gn:country_code":"RU",
    "gn:dem":14,
    "gn:feature_class":"P",
    "gn:feature_code":"PPL",
    "gn:name":"De-Friz",
    "gn:population":0,
    "gn:timezone":"Asia/Vladivostok",
    "iso:country":"RU",
    "name:rus_x_preferred":[
        "\u0414\u0435-\u0424\u0440\u0438\u0437"
    ],
    "name:und_x_variant":[
        "\u0414\u0435-\u0424\u0440\u0438\u0437"
    ],
    "wof:name":"De-Friz",
    "wof:placetype":"locality"
},
  "geometry": {"coordinates":[131.99298999999999,43.27907],"type":"Point"}
}