{
  "type": "Feature",
  "properties": {
    "gn:admin1_code":"54",
    "gn:asciiname":"Muromtsevo",
    "gn:country_code":"RU",
    "gn:dem":85,
    "gn:feature_class":"P",
    "gn:feature_code":"PPL",
    "gn:name":"Muromtsevo",
    "gn:population":0,
    "gn:timezone":"Asia/Omsk",
    "iso:country":"RU",
    "name:rus_x_preferred":[
        "\u041c\u0443\u0440\u043e\u043c\u0446\u0435\u0432\u043e"
    ],
    "name:und_x_variant":[
        "Petropavlovskiy",
        "Petropavlovka",
        "Muromtsevo"
    ],
    "wof:name":"Muromtsevo",
    "wof:placetype":"locality"
},
  "geometry": {"coordinates":[75.2895,56.4028],"type":"Point"}
}