{
  "type": "Feature",
  "properties": {
    "gn:admin1_code":"8.0",
    "gn:asciiname":"Sredniy Kachmash",
    "gn:country_code":"RU",
    "gn:dem":154,
    "gn:feature_class":"P",
    "gn:feature_code":"PPL",
    "gn:name":"Sredniy Kachmash",
    "gn:population":0,
    "gn:timezone":"Asia/Yekaterinburg",
    "iso:country":"RU",
    "name:rus_x_preferred":[
        "\u0421\u0440\u0435\u0434\u043d\u0438\u0439 \u041a\u0430\u0447\u043c\u0430\u0448"
    ],
    "wof:name":"Sredniy Kachmash",
    "wof:placetype":"locality"
},
  "geometry": {"coordinates":[54.6863,56.0379],"type":"Point"}
}