{
  "type": "Feature",
  "properties": {
    "gn:admin1_code":"90.0",
    "gn:asciiname":"Verkhnyaya Shestaya",
    "gn:country_code":"RU",
    "gn:dem":122,
    "gn:feature_class":"P",
    "gn:feature_code":"PPL",
    "gn:name":"Verkhnyaya Shestaya",
    "gn:population":0,
    "gn:timezone":"Asia/Yekaterinburg",
    "iso:country":"RU",
    "name:rus_x_preferred":[
        "\u0412\u0435\u0440\u0445\u043d\u044f\u044f \u0428\u0435\u0441\u0442\u0430\u044f"
    ],
    "wof:name":"Verkhnyaya Shestaya",
    "wof:placetype":"locality"
},
  "geometry": {"coordinates":[54.51588,57.30157],"type":"Point"}
}