{
  "type": "Feature",
  "properties": {
    "gn:admin1_code":"3",
    "gn:asciiname":"Ust'-Yulya",
    "gn:country_code":"RU",
    "gn:dem":442,
    "gn:feature_class":"P",
    "gn:feature_code":"PPL",
    "gn:name":"Ust\u2019-Yulya",
    "gn:population":0,
    "gn:timezone":"Asia/Omsk",
    "iso:country":"RU",
    "wof:name":"Ust'-Yulya",
    "wof:placetype":"locality"
},
  "geometry": {"coordinates":[86.84999999999999,51.83333],"type":"Point"}
}