{
  "type": "Feature",
  "properties": {
    "gn:admin1_code":"41",
    "gn:asciiname":"Maleyevka",
    "gn:country_code":"RU",
    "gn:dem":185,
    "gn:feature_class":"P",
    "gn:feature_code":"PPL",
    "gn:name":"Maleyevka",
    "gn:population":0,
    "gn:timezone":"Europe/Moscow",
    "iso:country":"RU",
    "name:eng_x_preferred":[
        "Maleyevka"
    ],
    "name:nor_x_preferred":[
        "Malejevka"
    ],
    "name:rus_x_preferred":[
        "\u041c\u0430\u043b\u0435\u0435\u0432\u043a\u0430"
    ],
    "wof:name":"Maleyevka",
    "wof:placetype":"locality"
},
  "geometry": {"coordinates":[35.23,51.5811],"type":"Point"}
}