{
  "type": "Feature",
  "properties": {
    "gn:admin1_code":"63",
    "gn:asciiname":"Byyangnyr",
    "gn:country_code":"RU",
    "gn:dem":34,
    "gn:feature_class":"P",
    "gn:feature_code":"PPL",
    "gn:name":"Byyangnyr",
    "gn:population":0,
    "gn:timezone":"Asia/Magadan",
    "iso:country":"RU",
    "name:rus_x_preferred":[
        "\u0411\u044b\u044f\u043d\u0433\u043d\u044b\u0440"
    ],
    "name:und_x_variant":[
        "\u0411\u044b\u044f\u043d\u0433\u043d\u044b\u0440"
    ],
    "wof:name":"Byyangnyr",
    "wof:placetype":"locality"
},
  "geometry": {"coordinates":[145.38333,69.93333],"type":"Point"}
}