{
  "type": "Feature",
  "properties": {
    "gn:admin1_code":"63",
    "gn:asciiname":"Ust'-Chara",
    "gn:country_code":"RU",
    "gn:dem":131,
    "gn:feature_class":"P",
    "gn:feature_code":"PPL",
    "gn:name":"Ust\u2019-Chara",
    "gn:population":0,
    "gn:timezone":"Asia/Yakutsk",
    "iso:country":"RU",
    "name:eng_x_preferred":[
        "Ust'-Chara"
    ],
    "name:nor_x_preferred":[
        "Ust-Tsjara"
    ],
    "name:rus_x_preferred":[
        "\u0423\u0441\u0442\u044c-\u0427\u0430\u0440\u0430"
    ],
    "name:und_x_variant":[
        "Ust\u2019-Charinskoye",
        "Ust\u2019-Chara"
    ],
    "wof:name":"Ust'-Chara",
    "wof:placetype":"locality"
},
  "geometry": {"coordinates":[120.89709000000001,60.31368000000001],"type":"Point"}
}