{
  "type": "Feature",
  "properties": {
    "gn:admin1_code":"8.0",
    "gn:asciiname":"Baymurzino",
    "gn:country_code":"RU",
    "gn:dem":402,
    "gn:feature_class":"P",
    "gn:feature_code":"PPL",
    "gn:name":"Baymurzino",
    "gn:population":0,
    "gn:timezone":"Asia/Yekaterinburg",
    "iso:country":"RU",
    "name:aze_x_preferred":[
        "B\u0259ymirz\u0259"
    ],
    "name:bak_x_preferred":[
        "\u0411\u0430\u0439\u043c\u044b\u0440\u0499\u0430"
    ],
    "name:che_x_preferred":[
        "\u0411\u0430\u0439\u043c\u0443\u0440\u0437\u0438\u043d\u043e"
    ],
    "name:eng_x_preferred":[
        "Baymurzino"
    ],
    "name:hye_x_preferred":[
        "\u0532\u0561\u0575\u0574\u0578\u0582\u0580\u0566\u056b\u0576\u0578"
    ],
    "name:kaz_x_preferred":[
        "\u0411\u0430\u0439\u043c\u0443\u0440\u0437\u0438\u043d\u043e"
    ],
    "name:kir_x_preferred":[
        "\u0411\u0430\u0439\u043c\u0443\u0440\u0437\u0438\u043d\u043e"
    ],
    "name:nor_x_preferred":[
        "Bajmurzino"
    ],
    "name:rus_x_preferred":[
        "\u0411\u0430\u0439\u043c\u0443\u0440\u0437\u0438\u043d\u043e"
    ],
    "name:tat_x_preferred":[
        "\u0411\u0430\u0439\u043c\u043e\u0440\u0437\u0430"
    ],
    "name:ukr_x_preferred":[
        "\u0411\u0430\u0439\u043c\u0443\u0440\u0437\u0456\u043d\u043e"
    ],
    "name:und_x_variant":[
        "\u0411\u0430\u0439\u043c\u0443\u0440\u0437\u0438\u043d\u043e",
        "Baymurzino"
    ],
    "wof:name":"Baymurzino",
    "wof:placetype":"locality"
},
  "geometry": {"coordinates":[58.43389000000001,52.43556],"type":"Point"}
}