{
  "type": "Feature",
  "properties": {
    "gn:admin1_code":"69.0",
    "gn:asciiname":"Demchenki",
    "gn:country_code":"RU",
    "gn:dem":171,
    "gn:feature_class":"P",
    "gn:feature_code":"PPL",
    "gn:name":"Demch\u00ebnki",
    "gn:population":0,
    "gn:timezone":"Europe/Moscow",
    "iso:country":"RU",
    "name:rus_x_preferred":[
        "\u0414\u0435\u043c\u0447\u0451\u043d\u043a\u0438"
    ],
    "name:und_x_variant":[
        "Demch\u00ebnki"
    ],
    "wof:name":"Demchenki",
    "wof:placetype":"locality"
},
  "geometry": {"coordinates":[31.06667,55.68333000000001],"type":"Point"}
}