{
  "type": "Feature",
  "properties": {
    "gn:admin1_code":"10",
    "gn:asciiname":"Revny",
    "gn:country_code":"RU",
    "gn:dem":162,
    "gn:feature_class":"P",
    "gn:feature_code":"PPL",
    "gn:name":"Revny",
    "gn:population":0,
    "gn:timezone":"Europe/Moscow",
    "iso:country":"RU",
    "name:rus_x_preferred":[
        "\u0420\u0435\u0432\u043d\u044b"
    ],
    "name:und_x_variant":[
        "Rovnoye",
        "Revny"
    ],
    "wof:name":"Revny",
    "wof:placetype":"locality"
},
  "geometry": {"coordinates":[34.27548,52.98944],"type":"Point"}
}