{
  "type": "Feature",
  "properties": {
    "gn:admin1_code":"41",
    "gn:asciiname":"Nikipelovka",
    "gn:country_code":"RU",
    "gn:dem":160,
    "gn:feature_class":"P",
    "gn:feature_code":"PPL",
    "gn:name":"Nikipelovka",
    "gn:population":0,
    "gn:timezone":"Europe/Moscow",
    "iso:country":"RU",
    "name:rus_x_preferred":[
        "\u041d\u0438\u043a\u0438\u043f\u0435\u043b\u043e\u0432\u043a\u0430"
    ],
    "wof:name":"Nikipelovka",
    "wof:placetype":"locality"
},
  "geometry": {"coordinates":[34.9358,51.4165],"type":"Point"}
}