{
  "type": "Feature",
  "properties": {
    "gn:admin1_code":"34",
    "gn:asciiname":"Parnachevykh",
    "gn:cc2":"RU",
    "gn:country_code":"RU",
    "gn:dem":182,
    "gn:feature_class":"P",
    "gn:feature_code":"PPL",
    "gn:name":"Parnach\u00ebvykh",
    "gn:population":0,
    "gn:timezone":"Europe/Moscow",
    "iso:country":"RU",
    "name:rus_x_preferred":[
        "\u041f\u0430\u0440\u043d\u0430\u0447\u0451\u0432\u044b\u0445"
    ],
    "name:und_x_variant":[
        "Parnachovy",
        "Parnachovykh",
        "Parnach\u00ebvykh"
    ],
    "wof:name":"Parnachevykh",
    "wof:placetype":"locality"
},
  "geometry": {"coordinates":[49.81667,60.65],"type":"Point"}
}