{
  "type": "Feature",
  "properties": {
    "gn:admin1_code":"52",
    "gn:asciiname":"Izvoznoye",
    "gn:country_code":"RU",
    "gn:dem":126,
    "gn:feature_class":"P",
    "gn:feature_code":"PPL",
    "gn:name":"Izvoznoye",
    "gn:population":0,
    "gn:timezone":"Europe/Moscow",
    "iso:country":"RU",
    "name:rus_x_preferred":[
        "\u0418\u0437\u0432\u043e\u0437\u043d\u043e\u0435"
    ],
    "name:und_x_variant":[
        "Izvozna",
        "Izvozno",
        "Izvoznoye"
    ],
    "wof:name":"Izvoznoye",
    "wof:placetype":"locality"
},
  "geometry": {"coordinates":[31.46301,57.06522],"type":"Point"}
}