{
  "type": "Feature",
  "properties": {
    "gn:admin1_code":"8",
    "gn:asciiname":"Kayrakly",
    "gn:country_code":"RU",
    "gn:dem":341,
    "gn:feature_class":"P",
    "gn:feature_code":"PPL",
    "gn:name":"Kayrakly",
    "gn:population":0,
    "gn:timezone":"Asia/Yekaterinburg",
    "iso:country":"RU",
    "name:eng_x_preferred":[
        "Kayrakly"
    ],
    "name:nor_x_preferred":[
        "Kajrakly"
    ],
    "name:rus_x_preferred":[
        "\u041a\u0430\u0439\u0440\u0430\u043a\u043b\u044b"
    ],
    "name:und_x_variant":[
        "\u041a\u0430\u0439\u0440\u0430\u043a\u043b\u044b",
        "Kayrakly"
    ],
    "wof:name":"Kayrakly",
    "wof:placetype":"locality"
},
  "geometry": {"coordinates":[54.53333000000001,53.93333000000001],"type":"Point"}
}