{
  "type": "Feature",
  "properties": {
    "gn:admin1_code":"8",
    "gn:asciiname":"Kayrakly",
    "gn:country_code":"RU",
    "gn:dem":341,
    "gn:feature_class":"P",
    "gn:feature_code":"PPL",
    "gn:name":"Kayrakly",
    "gn:population":0,
    "gn:timezone":"Asia/Yekaterinburg",
    "iso:country":"RU",
    "name:bak_x_preferred":[
        "\u04a0\u0430\u0439\u0440\u0430\u04a1\u043b\u044b"
    ],
    "name:che_x_preferred":[
        "\u041a\u0430\u0439\u0440\u0430\u043a\u043b\u044b"
    ],
    "name:chv_x_preferred":[
        "\u041a\u0430\u0439\u0440\u0430\u043a\u043b\u0103"
    ],
    "name:eng_x_preferred":[
        "Kayrakly"
    ],
    "name:hye_x_preferred":[
        "\u053f\u0561\u0575\u0580\u0561\u056f\u056c\u056b"
    ],
    "name:kat_x_preferred":[
        "\u10d9\u10d0\u10d8\u10e0\u10d0\u10d9\u10da\u10d8"
    ],
    "name:kaz_x_preferred":[
        "\u041a\u0430\u0439\u0440\u0430\u043a\u043b\u044b"
    ],
    "name:kir_x_preferred":[
        "\u041a\u0430\u0439\u0440\u0430\u043a\u043b\u044b"
    ],
    "name:nor_x_preferred":[
        "Kajrakly"
    ],
    "name:rus_x_preferred":[
        "\u041a\u0430\u0439\u0440\u0430\u043a\u043b\u044b"
    ],
    "name:tat_x_preferred":[
        "\u041a\u0430\u0439\u0440\u0430\u043a\u043b\u044b"
    ],
    "name:ukr_x_preferred":[
        "\u041a\u0430\u0439\u0440\u0430\u043a\u043b\u0438"
    ],
    "wof:name":"Kayrakly",
    "wof:placetype":"locality"
},
  "geometry": {"coordinates":[54.53333000000001,53.93333000000001],"type":"Point"}
}