{
  "type": "Feature",
  "properties": {
    "gn:admin1_code":"23.0",
    "gn:asciiname":"Babushkino",
    "gn:country_code":"RU",
    "gn:dem":45,
    "gn:feature_class":"P",
    "gn:feature_code":"PPL",
    "gn:name":"Babushkino",
    "gn:population":0,
    "gn:timezone":"Europe/Kaliningrad",
    "iso:country":"RU",
    "name:eng_x_preferred":[
        "Babushkino"
    ],
    "name:nor_x_preferred":[
        "Babusjkino"
    ],
    "name:rus_x_preferred":[
        "\u0411\u0430\u0431\u0443\u0448\u043a\u0438\u043d\u043e"
    ],
    "name:und_x_variant":[
        "Eichrode",
        "Gross Degesen",
        "Degesen",
        "Babu\u0161kino",
        "Gross Degezen"
    ],
    "wof:name":"Babushkino",
    "wof:placetype":"locality"
},
  "geometry": {"coordinates":[22.62833,54.68167],"type":"Point"}
}