{
  "type": "Feature",
  "properties": {
    "gn:admin1_code":"73",
    "gn:asciiname":"Bol'shoy Atmas",
    "gn:country_code":"RU",
    "gn:dem":93,
    "gn:feature_class":"P",
    "gn:feature_code":"PPL",
    "gn:name":"Bol\u2019shoy Atmas",
    "gn:population":0,
    "gn:timezone":"Europe/Moscow",
    "iso:country":"RU",
    "name:rus_x_preferred":[
        "\u0411\u043e\u043b\u044c\u0448\u043e\u0439 \u0410\u0442\u043c\u0430\u0441"
    ],
    "name:und_x_variant":[
        "Bol\u2019shoy Atmas",
        "\u0411\u043e\u043b\u044c\u0448\u043e\u0439 \u0410\u0442\u043c\u0430\u0441"
    ],
    "wof:name":"Bol'shoy Atmas",
    "wof:placetype":"locality"
},
  "geometry": {"coordinates":[50.11479,55.5712],"type":"Point"}
}