{
  "type": "Feature",
  "properties": {
    "gn:admin1_code":"90",
    "gn:asciiname":"Nizhnyaya Iskil'da",
    "gn:country_code":"RU",
    "gn:dem":216,
    "gn:feature_class":"P",
    "gn:feature_code":"PPL",
    "gn:name":"Nizhnyaya Iskil\u2019da",
    "gn:population":0,
    "gn:timezone":"Asia/Yekaterinburg",
    "iso:country":"RU",
    "name:rus_x_preferred":[
        "\u041d\u0438\u0436\u043d\u044f\u044f \u0418\u0441\u043a\u0438\u043b\u044c\u0434\u0430"
    ],
    "name:und_x_variant":[
        "Nizhnyaya Iskil\u2019da"
    ],
    "wof:name":"Nizhnyaya Iskil'da",
    "wof:placetype":"locality"
},
  "geometry": {"coordinates":[56.01403000000001,56.91669],"type":"Point"}
}