{
  "type": "Feature",
  "properties": {
    "gn:country":"RU",
    "gn:fcode":"PPL",
    "gn:pop":983,
    "iso:country":"RU",
    "name:eng_x_preferred":[
        "Vorontsovka"
    ],
    "name:nor_x_preferred":[
        "Vorontsovka"
    ],
    "name:rus_x_preferred":[
        "\u0412\u043e\u0440\u043e\u043d\u0446\u043e\u0432\u043a\u0430"
    ],
    "name:unk_x_variant":[
        "Vorontsovskiy"
    ],
    "qs:name":"Vorontsovka",
    "qs:photos_9r":0,
    "qs:photos_sr":0,
    "qs:pop_sr":"2",
    "wof:name":"Vorontsovka",
    "wof:placetype":"locality",
    "wof:population":983
},
  "geometry": {"coordinates":[60.23788,59.65796],"type":"Point"}
}