{
  "type": "Feature",
  "properties": {
    "gn:admin1_code":"85",
    "gn:asciiname":"Verkhneye Aleshkovo",
    "gn:country_code":"RU",
    "gn:dem":94,
    "gn:feature_class":"P",
    "gn:feature_code":"PPL",
    "gn:name":"Verkhneye Al\u00ebshkovo",
    "gn:population":0,
    "gn:timezone":"Europe/Moscow",
    "iso:country":"RU",
    "name:rus_x_preferred":[
        "\u0412\u0435\u0440\u0445\u043d\u0435\u0435 \u0410\u043b\u0451\u0448\u043a\u043e\u0432\u043e"
    ],
    "name:und_x_variant":[
        "Verkhneye Al\u00ebshkovo"
    ],
    "wof:name":"Verkhneye Aleshkovo",
    "wof:placetype":"locality"
},
  "geometry": {"coordinates":[46.2751,60.4953],"type":"Point"}
}