{
  "type": "Feature",
  "properties": {
    "gn:admin1_code":"6",
    "gn:asciiname":"Zimnegorskiy",
    "gn:country_code":"RU",
    "gn:dem":-9999,
    "gn:feature_class":"P",
    "gn:feature_code":"PPL",
    "gn:name":"Zimnegorskiy",
    "gn:population":0,
    "gn:timezone":"Europe/Moscow",
    "iso:country":"RU",
    "name:eng_x_preferred":[
        "Zimnegorskiy"
    ],
    "name:nor_x_preferred":[
        "Zimnegorskij"
    ],
    "name:rus_x_preferred":[
        "\u0417\u0438\u043c\u043d\u0435\u0433\u043e\u0440\u0441\u043a\u0438\u0439"
    ],
    "wof:name":"Zimnegorskiy",
    "wof:placetype":"locality"
},
  "geometry": {"coordinates":[39.71266,65.4795],"type":"Point"}
}