{
  "type": "Feature",
  "properties": {
    "gn:admin1_code":"61",
    "gn:asciiname":"Zemtsov",
    "gn:country_code":"RU",
    "gn:dem":90,
    "gn:feature_class":"P",
    "gn:feature_code":"PPL",
    "gn:name":"Zemtsov",
    "gn:population":0,
    "gn:timezone":"Europe/Moscow",
    "iso:country":"RU",
    "name:und_x_variant":[
        "Staryy Zemtsov",
        "Zemtsov"
    ],
    "wof:name":"Zemtsov",
    "wof:placetype":"locality"
},
  "geometry": {"coordinates":[41.82048,49.20716],"type":"Point"}
}