{
  "type": "Feature",
  "properties": {
    "gn:admin1_code":"33.0",
    "gn:asciiname":"Petrino",
    "gn:country_code":"RU",
    "gn:dem":137,
    "gn:feature_class":"P",
    "gn:feature_code":"PPL",
    "gn:name":"Petrino",
    "gn:population":0,
    "gn:timezone":"Europe/Kirov",
    "iso:country":"RU",
    "name:rus_x_preferred":[
        "\u041f\u0435\u0442\u0440\u0438\u043d\u043e"
    ],
    "name:und_x_variant":[
        "Petrenki"
    ],
    "wof:name":"Petrino",
    "wof:placetype":"locality"
},
  "geometry": {"coordinates":[50.2941,58.7615],"type":"Point"}
}