{
  "type": "Feature",
  "properties": {
    "gn:admin1_code":"91",
    "gn:asciiname":"Shivera",
    "gn:country_code":"RU",
    "gn:dem":159,
    "gn:feature_class":"P",
    "gn:feature_code":"PPL",
    "gn:name":"Shivera",
    "gn:population":0,
    "gn:timezone":"Asia/Krasnoyarsk",
    "iso:country":"RU",
    "name:eng_x_preferred":[
        "Shivera"
    ],
    "name:nor_x_preferred":[
        "Sjivera"
    ],
    "name:rus_x_preferred":[
        "\u0428\u0438\u0432\u0435\u0440\u0430"
    ],
    "name:und_x_variant":[
        "Shiverskaya",
        "Shivera"
    ],
    "wof:name":"Shivera",
    "wof:placetype":"locality"
},
  "geometry": {"coordinates":[93.48528,56.32417],"type":"Point"}
}