{
  "type": "Feature",
  "properties": {
    "gn:admin1_code":"53",
    "gn:asciiname":"Boltovo",
    "gn:country_code":"RU",
    "gn:dem":202,
    "gn:feature_class":"P",
    "gn:feature_code":"PPL",
    "gn:name":"Boltovo",
    "gn:population":0,
    "gn:timezone":"Asia/Novosibirsk",
    "iso:country":"RU",
    "name:eng_x_preferred":[
        "Boltovo"
    ],
    "name:nor_x_preferred":[
        "Boltovo"
    ],
    "name:rus_x_preferred":[
        "\u0411\u043e\u043b\u0442\u043e\u0432\u043e"
    ],
    "name:und_x_variant":[
        "Boltovskoye"
    ],
    "wof:name":"Boltovo",
    "wof:placetype":"locality"
},
  "geometry": {"coordinates":[82.2667,54.0307],"type":"Point"}
}