{
  "type": "Feature",
  "properties": {
    "gn:admin1_code":"55",
    "gn:asciiname":"Rabochiy",
    "gn:country_code":"RU",
    "gn:dem":111,
    "gn:feature_class":"P",
    "gn:feature_code":"PPL",
    "gn:name":"Rabochiy",
    "gn:population":0,
    "gn:timezone":"Asia/Yekaterinburg",
    "iso:country":"RU",
    "name:rus_x_preferred":[
        "\u0420\u0430\u0431\u043e\u0447\u0438\u0439"
    ],
    "wof:name":"Rabochiy",
    "wof:placetype":"locality"
},
  "geometry": {"coordinates":[52.4774,53.3596],"type":"Point"}
}