{
  "type": "Feature",
  "properties": {
    "gn:admin1_code":"15",
    "gn:asciiname":"Ikechurun",
    "gn:cc2":"RU",
    "gn:country_code":"RU",
    "gn:dem":329,
    "gn:feature_class":"P",
    "gn:feature_code":"PPL",
    "gn:name":"Ikechurun",
    "gn:population":0,
    "gn:timezone":"Asia/Anadyr",
    "iso:country":"RU",
    "name:rus_x_preferred":[
        "\u0418\u043a\u0435\u0447\u0443\u0440\u0443\u043d"
    ],
    "name:und_x_variant":[
        "Koehuren",
        "Ikychuren",
        "Ikechurun"
    ],
    "wof:name":"Ikechurun",
    "wof:placetype":"locality"
},
  "geometry": {"coordinates":[171.01667,66.55],"type":"Point"}
}