{
  "type": "Feature",
  "properties": {
    "gn:admin1_code":"56.0",
    "gn:asciiname":"Agarkovo",
    "gn:country_code":"RU",
    "gn:dem":165,
    "gn:feature_class":"P",
    "gn:feature_code":"PPL",
    "gn:name":"Agarkovo",
    "gn:population":0,
    "gn:timezone":"Europe/Moscow",
    "iso:country":"RU",
    "name:nor_x_preferred":[
        "Agarkovo"
    ],
    "name:rus_x_preferred":[
        "\u0410\u0433\u0430\u0440\u043a\u043e\u0432\u043e"
    ],
    "wof:name":"Agarkovo",
    "wof:placetype":"locality"
},
  "geometry": {"coordinates":[36.79284000000001,52.2522],"type":"Point"}
}