{
  "type": "Feature",
  "properties": {
    "gn:admin1_code":"8",
    "gn:asciiname":"Khlebodarovka",
    "gn:country_code":"RU",
    "gn:dem":130,
    "gn:feature_class":"P",
    "gn:feature_code":"PPL",
    "gn:name":"Khlebodarovka",
    "gn:population":0,
    "gn:timezone":"Asia/Yekaterinburg",
    "iso:country":"RU",
    "name:rus_x_preferred":[
        "\u0425\u043b\u0435\u0431\u043e\u0434\u0430\u0440\u043e\u0432\u043a\u0430"
    ],
    "name:und_x_variant":[
        "\u0425\u043b\u0435\u0431\u043e\u0434\u0430\u0440\u043e\u0432\u043a\u0430"
    ],
    "wof:name":"Khlebodarovka",
    "wof:placetype":"locality"
},
  "geometry": {"coordinates":[55.0001,54.7384],"type":"Point"}
}