{
  "type": "Feature",
  "properties": {
    "gn:admin1_code":"72",
    "gn:asciiname":"Nadezhdino",
    "gn:country_code":"RU",
    "gn:dem":194,
    "gn:feature_class":"P",
    "gn:feature_code":"PPL",
    "gn:name":"Nadezhdino",
    "gn:population":0,
    "gn:timezone":"Europe/Moscow",
    "iso:country":"RU",
    "name:rus_x_preferred":[
        "\u041d\u0430\u0434\u0435\u0436\u0434\u0438\u043d\u043e"
    ],
    "name:und_x_variant":[
        "\u041d\u0430\u0434\u0435\u0436\u0434\u0438\u043d\u043e"
    ],
    "wof:name":"Nadezhdino",
    "wof:placetype":"locality"
},
  "geometry": {"coordinates":[42.12613,52.58487],"type":"Point"}
}