{
  "type": "Feature",
  "properties": {
    "gn:admin1_code":"77.0",
    "gn:asciiname":"Bol'shoye Mecheno",
    "gn:country_code":"RU",
    "gn:dem":236,
    "gn:feature_class":"P",
    "gn:feature_code":"PPL",
    "gn:name":"Bol\u2019shoye Mecheno",
    "gn:population":0,
    "gn:timezone":"Europe/Moscow",
    "iso:country":"RU",
    "name:rus_x_preferred":[
        "\u0411\u043e\u043b\u044c\u0448\u043e\u0435 \u041c\u0435\u0447\u0435\u043d\u043e"
    ],
    "name:und_x_variant":[
        "Mecheno",
        "Bol\u2019shoye Mecheno"
    ],
    "wof:name":"Bol'shoye Mecheno",
    "wof:placetype":"locality"
},
  "geometry": {"coordinates":[33.67955,56.13798000000001],"type":"Point"}
}