{
  "type": "Feature",
  "properties": {
    "gn:admin1_code":"42.0",
    "gn:asciiname":"Sel'tso",
    "gn:country_code":"RU",
    "gn:dem":151,
    "gn:feature_class":"P",
    "gn:feature_code":"PPL",
    "gn:name":"Sel\u2019tso",
    "gn:population":0,
    "gn:timezone":"Europe/Moscow",
    "iso:country":"RU",
    "name:fin_x_preferred":[
        "Seltso"
    ],
    "name:rus_x_preferred":[
        "\u0421\u0435\u043b\u044c\u0446\u043e"
    ],
    "name:und_x_variant":[
        "Sel\u2019tso"
    ],
    "wof:name":"Sel'tso",
    "wof:placetype":"locality"
},
  "geometry": {"coordinates":[29.53269,59.62735],"type":"Point"}
}