{
  "type": "Feature",
  "properties": {
    "gn:admin1_code":"25.0",
    "gn:asciiname":"Adamovskoye",
    "gn:country_code":"RU",
    "gn:dem":163,
    "gn:feature_class":"P",
    "gn:feature_code":"PPL",
    "gn:name":"Adamovskoye",
    "gn:population":0,
    "gn:timezone":"Europe/Moscow",
    "iso:country":"RU",
    "name:eng_x_preferred":[
        "Adamovskoye"
    ],
    "name:nor_x_preferred":[
        "Adamovskoje"
    ],
    "name:rus_x_preferred":[
        "\u0410\u0434\u0430\u043c\u043e\u0432\u0441\u043a\u043e\u0435"
    ],
    "name:und_x_variant":[
        "Adamovskoe"
    ],
    "wof:name":"Adamovskoye",
    "wof:placetype":"locality"
},
  "geometry": {"coordinates":[35.94943,54.86403000000001],"type":"Point"}
}