{
  "type": "Feature",
  "properties": {
    "gn:admin1_code":"51",
    "gn:asciiname":"Pelya-Kazennaya",
    "gn:country_code":"RU",
    "gn:dem":116,
    "gn:feature_class":"P",
    "gn:feature_code":"PPL",
    "gn:name":"Pelya-Kaz\u00ebnnaya",
    "gn:population":0,
    "gn:timezone":"Europe/Moscow",
    "iso:country":"RU",
    "name:rus_x_preferred":[
        "\u041f\u0435\u043b\u044f-\u041a\u0430\u0437\u0451\u043d\u043d\u0430\u044f"
    ],
    "name:und_x_variant":[
        "Pelya-Kaz\u00ebnnaya",
        "\u041f\u0435\u043b\u044f-\u041a\u0430\u0437\u0451\u043d\u043d\u0430\u044f"
    ],
    "wof:name":"Pelya-Kazennaya",
    "wof:placetype":"locality"
},
  "geometry": {"coordinates":[45.0296,54.6713],"type":"Point"}
}