{
  "type": "Feature",
  "properties": {
    "gn:admin1_code":"4.0",
    "gn:asciiname":"Chegon",
    "gn:country_code":"RU",
    "gn:dem":735,
    "gn:feature_class":"P",
    "gn:feature_code":"PPL",
    "gn:name":"Chegon",
    "gn:population":0,
    "gn:timezone":"Asia/Barnaul",
    "iso:country":"RU",
    "name:rus_x_preferred":[
        "\u0427\u0435\u0433\u043e\u043d"
    ],
    "wof:name":"Chegon",
    "wof:placetype":"locality"
},
  "geometry": {"coordinates":[84.7072,51.4642],"type":"Point"}
}