{
  "type": "Feature",
  "properties": {
    "gn:admin1_code":"37.0",
    "gn:asciiname":"Semino",
    "gn:country_code":"RU",
    "gn:dem":178,
    "gn:feature_class":"P",
    "gn:feature_code":"PPL",
    "gn:name":"S\u00ebmino",
    "gn:population":0,
    "gn:timezone":"Europe/Moscow",
    "iso:country":"RU",
    "name:rus_x_preferred":[
        "\u0421\u0451\u043c\u0438\u043d\u043e"
    ],
    "name:und_x_variant":[
        "S\u00ebmino",
        "\u0421\u0451\u043c\u0438\u043d\u043e"
    ],
    "wof:name":"Semino",
    "wof:placetype":"locality"
},
  "geometry": {"coordinates":[41.89544,57.93044],"type":"Point"}
}