{
  "type": "Feature",
  "properties": {
    "gn:admin1_code":"46",
    "gn:asciiname":"Belotroitskiy",
    "gn:country_code":"RU",
    "gn:dem":147,
    "gn:feature_class":"P",
    "gn:feature_code":"PPL",
    "gn:name":"Belotroitskiy",
    "gn:population":0,
    "gn:timezone":"Europe/Moscow",
    "iso:country":"RU",
    "name:rus_x_preferred":[
        "\u0411\u0435\u043b\u043e\u0442\u0440\u043e\u0438\u0446\u043a\u0438\u0439"
    ],
    "name:und_x_variant":[
        "\u0411\u0435\u043b\u043e\u0442\u0440\u043e\u0438\u0446\u043a\u0438\u0439"
    ],
    "wof:name":"Belotroitskiy",
    "wof:placetype":"locality"
},
  "geometry": {"coordinates":[45.5057,54.268],"type":"Point"}
}