{
  "type": "Feature",
  "properties": {
    "gn:admin1_code":"90",
    "gn:asciiname":"Verkhniy Lel'",
    "gn:country_code":"RU",
    "gn:dem":146,
    "gn:feature_class":"P",
    "gn:feature_code":"PPL",
    "gn:name":"Verkhniy L\u00ebl\u2019",
    "gn:population":0,
    "gn:timezone":"Asia/Yekaterinburg",
    "iso:country":"RU",
    "name:eng_x_preferred":[
        "Verkhniy L\u00ebl'"
    ],
    "name:nor_x_preferred":[
        "Verkh-Lel"
    ],
    "name:rus_x_preferred":[
        "\u0412\u0435\u0440\u0445-\u041b\u0435\u043b\u044c"
    ],
    "name:rus_x_variant":[
        "\u0412\u0435\u0440\u0445\u043d\u0438\u0439 \u041b\u0451\u043b\u044c"
    ],
    "name:und_x_variant":[
        "Verkhniy L\u00ebl\u2019"
    ],
    "wof:name":"Verkhniy Lel'",
    "wof:placetype":"locality"
},
  "geometry": {"coordinates":[54.815,59.9793],"type":"Point"}
}