{
  "type": "Feature",
  "properties": {
    "gn:admin1_code":"28",
    "gn:asciiname":"Piksi",
    "gn:country_code":"RU",
    "gn:dem":140,
    "gn:feature_class":"P",
    "gn:feature_code":"PPL",
    "gn:name":"Piksi",
    "gn:population":0,
    "gn:timezone":"Europe/Moscow",
    "iso:country":"RU",
    "name:fin_x_preferred":[
        "Piksi"
    ],
    "name:ita_x_preferred":[
        "Piksi barbarulna"
    ],
    "name:nld_x_preferred":[
        "Piksi"
    ],
    "name:rus_x_preferred":[
        "\u041f\u0438\u043a\u0441\u0438"
    ],
    "name:rus_x_variant":[
        "Piksi"
    ],
    "name:spa_x_preferred":[
        "Piksi"
    ],
    "wof:name":"Piksi",
    "wof:placetype":"locality"
},
  "geometry": {"coordinates":[30.53873,65.40741],"type":"Point"}
}