{
  "type": "Feature",
  "properties": {
    "gn:admin1_code":"61.0",
    "gn:asciiname":"Kolesnikov",
    "gn:country_code":"RU",
    "gn:dem":43,
    "gn:feature_class":"P",
    "gn:feature_code":"PPL",
    "gn:name":"Kolesnikov",
    "gn:population":0,
    "gn:timezone":"Europe/Moscow",
    "iso:country":"RU",
    "name:bel_x_preferred":[
        "\u041a\u0430\u043b\u0435\u0441\u043d\u0456\u043a\u0430\u045e"
    ],
    "name:deu_x_preferred":[
        "Kolesnikow"
    ],
    "name:fra_x_preferred":[
        "Kolesnikov"
    ],
    "name:rus_x_preferred":[
        "\u041a\u043e\u043b\u0435\u0441\u043d\u0438\u043a\u043e\u0432"
    ],
    "name:tat_x_preferred":[
        "\u041a\u043e\u043b\u0435\u0441\u043d\u0438\u043a\u043e\u0432"
    ],
    "name:ukr_x_preferred":[
        "Kolesnykov"
    ],
    "name:ukr_x_variant":[
        "\u041a\u043e\u043b\u0435\u0441\u043d\u0438\u043a\u043e\u0432"
    ],
    "name:und_x_variant":[
        "Kolesnikovo"
    ],
    "wof:name":"Kolesnikov",
    "wof:placetype":"locality"
},
  "geometry": {"coordinates":[38.37261,47.41522],"type":"Point"}
}