{
  "type": "Feature",
  "properties": {
    "gn:admin1_code":"12.0",
    "gn:asciiname":"Manaroy",
    "gn:country_code":"RU",
    "gn:dem":1491,
    "gn:feature_class":"P",
    "gn:feature_code":"PPL",
    "gn:name":"Manaroy",
    "gn:population":0,
    "gn:timezone":"Europe/Moscow",
    "iso:country":"RU",
    "wof:name":"Manaroy",
    "wof:placetype":"locality"
},
  "geometry": {"coordinates":[45.39222,42.78444],"type":"Point"}
}