{
  "type": "Feature",
  "properties": {
    "gn:admin1_code":"56",
    "gn:asciiname":"Yurty Livenskiye",
    "gn:country_code":"RU",
    "gn:dem":153,
    "gn:feature_class":"P",
    "gn:feature_code":"PPL",
    "gn:name":"Yurty Livenskiye",
    "gn:population":0,
    "gn:timezone":"Europe/Moscow",
    "iso:country":"RU",
    "name:und_x_variant":[
        "Yurly Livenskiye",
        "Yurty Livenskiye"
    ],
    "wof:name":"Yurty Livenskiye",
    "wof:placetype":"locality"
},
  "geometry": {"coordinates":[37.35688,52.55993],"type":"Point"}
}