{
  "type": "Feature",
  "properties": {
    "gn:admin1_code":"4",
    "gn:asciiname":"Plakhino",
    "gn:country_code":"RU",
    "gn:dem":121,
    "gn:feature_class":"P",
    "gn:feature_code":"PPL",
    "gn:name":"Plakhino",
    "gn:population":0,
    "gn:timezone":"Asia/Barnaul",
    "iso:country":"RU",
    "name:rus_x_preferred":[
        "\u041f\u043b\u0430\u0445\u0438\u043d\u043e"
    ],
    "wof:name":"Plakhino",
    "wof:placetype":"locality"
},
  "geometry": {"coordinates":[82.61667,53.45],"type":"Point"}
}