{
  "type": "Feature",
  "properties": {
    "gn:admin1_code":"80",
    "gn:asciiname":"Kesshur",
    "gn:country_code":"RU",
    "gn:dem":274,
    "gn:feature_class":"P",
    "gn:feature_code":"PPL",
    "gn:name":"Kesshur",
    "gn:population":0,
    "gn:timezone":"Europe/Samara",
    "iso:country":"RU",
    "name:rus_x_preferred":[
        "\u041a\u0435\u0441\u0448\u0443\u0440"
    ],
    "name:und_x_variant":[
        "\u041a\u0435\u0441\u0448\u0443\u0440"
    ],
    "wof:name":"Kesshur",
    "wof:placetype":"locality"
},
  "geometry": {"coordinates":[52.7135,57.30361],"type":"Point"}
}