{
  "type": "Feature",
  "properties": {
    "gn:admin1_code":"52",
    "gn:asciiname":"Khalshchagino",
    "gn:country_code":"RU",
    "gn:dem":147,
    "gn:feature_class":"P",
    "gn:feature_code":"PPL",
    "gn:name":"Khalshchagino",
    "gn:population":0,
    "gn:timezone":"Europe/Moscow",
    "iso:country":"RU",
    "name:rus_x_preferred":[
        "\u0425\u0430\u043b\u0449\u0430\u0433\u0438\u043d\u043e"
    ],
    "name:und_x_variant":[
        "Kholshchanino",
        "Khalshchagino",
        "\u0425\u0430\u043b\u0449\u0430\u0433\u0438\u043d\u043e"
    ],
    "wof:name":"Khalshchagino",
    "wof:placetype":"locality"
},
  "geometry": {"coordinates":[34.66479,58.14313000000001],"type":"Point"}
}