{
  "type": "Feature",
  "properties": {
    "gn:admin1_code":"47",
    "gn:asciiname":"Rodniki",
    "gn:country_code":"RU",
    "gn:dem":149,
    "gn:feature_class":"P",
    "gn:feature_code":"PPL",
    "gn:name":"Rodniki",
    "gn:population":0,
    "gn:timezone":"Europe/Moscow",
    "iso:country":"RU",
    "name:rus_x_preferred":[
        "\u0420\u043e\u0434\u043d\u0438\u043a\u0438"
    ],
    "name:sco_x_preferred":[
        "Rodniki"
    ],
    "name:und_x_variant":[
        "Zhidovinova"
    ],
    "wof:name":"Rodniki",
    "wof:placetype":"locality"
},
  "geometry": {"coordinates":[37.64797,54.89447],"type":"Point"}
}