{
  "type": "Feature",
  "properties": {
    "gn:admin1_code":"60",
    "gn:asciiname":"Shablavino",
    "gn:country_code":"RU",
    "gn:dem":99,
    "gn:feature_class":"P",
    "gn:feature_code":"PPL",
    "gn:name":"Shablavino",
    "gn:population":0,
    "gn:timezone":"Europe/Moscow",
    "iso:country":"RU",
    "name:rus_x_preferred":[
        "\u0428\u0430\u0431\u043b\u0430\u0432\u0438\u043d\u043e"
    ],
    "wof:name":"Shablavino",
    "wof:placetype":"locality"
},
  "geometry": {"coordinates":[28.66272,56.66109],"type":"Point"}
}