{
  "type": "Feature",
  "properties": {
    "gn:admin1_code":"54",
    "gn:asciiname":"Lyubomirovka",
    "gn:country_code":"RU",
    "gn:dem":103,
    "gn:feature_class":"P",
    "gn:feature_code":"PPL",
    "gn:name":"Lyubomirovka",
    "gn:population":0,
    "gn:timezone":"Asia/Omsk",
    "iso:country":"RU",
    "name:eng_x_preferred":[
        "Lyubomirovka"
    ],
    "name:nor_x_preferred":[
        "Ljubomirovka"
    ],
    "name:rus_x_preferred":[
        "\u041b\u044e\u0431\u043e\u043c\u0438\u0440\u043e\u0432\u043a\u0430"
    ],
    "name:und_x_variant":[
        "Lyubomirskoye",
        "Lyubimovka",
        "Lyubomirovka"
    ],
    "wof:name":"Lyubomirovka",
    "wof:placetype":"locality"
},
  "geometry": {"coordinates":[73.58508,54.42741],"type":"Point"}
}