{
  "type": "Feature",
  "properties": {
    "gn:admin1_code":"85",
    "gn:asciiname":"Ostrovskaya",
    "gn:country_code":"RU",
    "gn:dem":172,
    "gn:feature_class":"P",
    "gn:feature_code":"PPL",
    "gn:name":"Ostrovskaya",
    "gn:population":0,
    "gn:timezone":"Europe/Moscow",
    "iso:country":"RU",
    "name:rus_x_preferred":[
        "\u041e\u0441\u0442\u0440\u043e\u0432\u0441\u043a\u0430\u044f"
    ],
    "wof:name":"Ostrovskaya",
    "wof:placetype":"locality"
},
  "geometry": {"coordinates":[38.5072,60.2135],"type":"Point"}
}