{
  "type": "Feature",
  "properties": {
    "gn:admin1_code":"54",
    "gn:asciiname":"Nekrasovka",
    "gn:country_code":"RU",
    "gn:dem":110,
    "gn:feature_class":"P",
    "gn:feature_code":"PPL",
    "gn:name":"Nekrasovka",
    "gn:population":0,
    "gn:timezone":"Asia/Omsk",
    "iso:country":"RU",
    "name:ceb_x_preferred":[
        "Nekrasovka"
    ],
    "name:eng_x_preferred":[
        "Nekrasovskiy"
    ],
    "name:nld_x_preferred":[
        "Nekrasovka"
    ],
    "name:nor_x_preferred":[
        "Nekrasovka"
    ],
    "name:rus_x_preferred":[
        "\u041d\u0435\u043a\u0440\u0430\u0441\u043e\u0432\u043a\u0430"
    ],
    "name:und_x_variant":[
        "Nekrasovskiy",
        "Nekrasovka",
        "\u041d\u0435\u043a\u0440\u0430\u0441\u043e\u0432\u043a\u0430",
        "Ferma Tri"
    ],
    "wof:name":"Nekrasovka",
    "wof:placetype":"locality"
},
  "geometry": {"coordinates":[74.99008000000001,55.69955],"type":"Point"}
}