{
  "type": "Feature",
  "properties": {
    "gn:admin1_code":"85",
    "gn:asciiname":"Filisovo",
    "gn:country_code":"RU",
    "gn:dem":144,
    "gn:feature_class":"P",
    "gn:feature_code":"PPL",
    "gn:name":"Filisovo",
    "gn:population":0,
    "gn:timezone":"Europe/Moscow",
    "iso:country":"RU",
    "name:rus_x_preferred":[
        "\u0424\u0438\u043b\u0438\u0441\u043e\u0432\u043e"
    ],
    "name:und_x_variant":[
        "\u0424\u0438\u043b\u0438\u0441\u043e\u0432\u043e"
    ],
    "wof:name":"Filisovo",
    "wof:placetype":"locality"
},
  "geometry": {"coordinates":[39.53,59.5075],"type":"Point"}
}