{
  "type": "Feature",
  "properties": {
    "gn:admin1_code":"73",
    "gn:asciiname":"Danaurovka",
    "gn:country_code":"RU",
    "gn:dem":152,
    "gn:feature_class":"P",
    "gn:feature_code":"PPL",
    "gn:name":"Danaurovka",
    "gn:population":0,
    "gn:timezone":"Europe/Moscow",
    "iso:country":"RU",
    "name:rus_x_preferred":[
        "\u0414\u0430\u043d\u0430\u0443\u0440\u043e\u0432\u043a\u0430"
    ],
    "wof:name":"Danaurovka",
    "wof:placetype":"locality"
},
  "geometry": {"coordinates":[50.0698,55.9367],"type":"Point"}
}