{
  "type": "Feature",
  "properties": {
    "gn:admin1_code":"21",
    "gn:asciiname":"Myshkino",
    "gn:country_code":"RU",
    "gn:dem":111,
    "gn:feature_class":"P",
    "gn:feature_code":"PPL",
    "gn:name":"Myshkino",
    "gn:population":0,
    "gn:timezone":"Europe/Moscow",
    "iso:country":"RU",
    "name:rus_x_preferred":[
        "\u041c\u044b\u0448\u043a\u0438\u043d\u043e"
    ],
    "wof:name":"Myshkino",
    "wof:placetype":"locality"
},
  "geometry": {"coordinates":[39.93485,56.78919000000001],"type":"Point"}
}