{
  "type": "Feature",
  "properties": {
    "gn:admin1_code":"90",
    "gn:asciiname":"Sofonkova",
    "gn:country_code":"RU",
    "gn:dem":161,
    "gn:feature_class":"P",
    "gn:feature_code":"PPL",
    "gn:name":"Sofonkova",
    "gn:population":0,
    "gn:timezone":"Asia/Yekaterinburg",
    "iso:country":"RU",
    "name:rus_x_preferred":[
        "\u0421\u043e\u0444\u043e\u043d\u043a\u043e\u0432\u0430"
    ],
    "name:und_x_variant":[
        "Sofronova",
        "Sofonkova"
    ],
    "wof:name":"Sofonkova",
    "wof:placetype":"locality"
},
  "geometry": {"coordinates":[54.5303,58.9314],"type":"Point"}
}