{
  "type": "Feature",
  "properties": {
    "gn:admin1_code":"63",
    "gn:asciiname":"Chanoyu",
    "gn:country_code":"RU",
    "gn:dem":234,
    "gn:feature_class":"P",
    "gn:feature_code":"PPL",
    "gn:name":"Chanoyu",
    "gn:population":0,
    "gn:timezone":"Asia/Yakutsk",
    "iso:country":"RU",
    "name:eng_x_preferred":[
        "Chanoyu"
    ],
    "name:nor_x_preferred":[
        "Tsjanoju"
    ],
    "name:rus_x_preferred":[
        "\u0427\u0430\u043d\u043e\u044e"
    ],
    "wof:name":"Chanoyu",
    "wof:placetype":"locality"
},
  "geometry": {"coordinates":[130.88333,61.16667],"type":"Point"}
}