{
  "type": "Feature",
  "properties": {
    "gn:admin1_code":"85",
    "gn:asciiname":"Bol'shiye Slobody",
    "gn:country_code":"RU",
    "gn:dem":140,
    "gn:feature_class":"P",
    "gn:feature_code":"PPL",
    "gn:name":"Bol\u2019shiye Slobody",
    "gn:population":0,
    "gn:timezone":"Europe/Moscow",
    "iso:country":"RU",
    "name:rus_x_preferred":[
        "\u0411\u043e\u043b\u044c\u0448\u0438\u0435 \u0421\u043b\u043e\u0431\u043e\u0434\u044b"
    ],
    "name:und_x_variant":[
        "Bol\u2019shiye Slobody",
        "\u0411\u043e\u043b\u044c\u0448\u0438\u0435 \u0421\u043b\u043e\u0431\u043e\u0434\u044b"
    ],
    "wof:name":"Bol'shiye Slobody",
    "wof:placetype":"locality"
},
  "geometry": {"coordinates":[46.455,60.7573],"type":"Point"}
}