{
  "type": "Feature",
  "properties": {
    "gn:admin1_code":"51.0",
    "gn:asciiname":"Bol'shaya Kozlyana",
    "gn:country_code":"RU",
    "gn:dem":138,
    "gn:feature_class":"P",
    "gn:feature_code":"PPL",
    "gn:name":"Bol\u2019shaya Kozlyana",
    "gn:population":0,
    "gn:timezone":"Europe/Moscow",
    "iso:country":"RU",
    "name:rus_x_preferred":[
        "\u0411\u043e\u043b\u044c\u0448\u0430\u044f \u041a\u043e\u0437\u043b\u044f\u043d\u0430"
    ],
    "name:und_x_variant":[
        "Bol\u2019shaya Kozlyana",
        "\u0411\u043e\u043b\u044c\u0448\u0430\u044f \u041a\u043e\u0437\u043b\u044f\u043d\u0430"
    ],
    "wof:name":"Bol'shaya Kozlyana",
    "wof:placetype":"locality"
},
  "geometry": {"coordinates":[45.86428,57.67004],"type":"Point"}
}