{
  "type": "Feature",
  "properties": {
    "gn:admin1_code":"10.0",
    "gn:asciiname":"Bryanovka",
    "gn:country_code":"RU",
    "gn:dem":174,
    "gn:feature_class":"P",
    "gn:feature_code":"PPL",
    "gn:name":"Bryanovka",
    "gn:population":0,
    "gn:timezone":"Europe/Moscow",
    "iso:country":"RU",
    "name:rus_x_preferred":[
        "\u0411\u0440\u044f\u043d\u043e\u0432\u043a\u0430"
    ],
    "wof:name":"Bryanovka",
    "wof:placetype":"locality"
},
  "geometry": {"coordinates":[33.481,53.0975],"type":"Point"}
}