{
  "type": "Feature",
  "properties": {
    "gn:admin1_code":"30",
    "gn:asciiname":"Sogda",
    "gn:country_code":"RU",
    "gn:dem":692,
    "gn:feature_class":"P",
    "gn:feature_code":"PPL",
    "gn:name":"Sogda",
    "gn:population":0,
    "gn:timezone":"Asia/Vladivostok",
    "iso:country":"RU",
    "name:eng_x_preferred":[
        "Sogda"
    ],
    "name:nor_x_preferred":[
        "Sogda"
    ],
    "name:rus_x_preferred":[
        "\u0421\u043e\u0433\u0434\u0430"
    ],
    "name:und_x_variant":[
        "\u0421\u043e\u0433\u0434\u0430"
    ],
    "wof:name":"Sogda",
    "wof:placetype":"locality"
},
  "geometry": {"coordinates":[132.26588000000001,50.41759],"type":"Point"}
}