{
  "type": "Feature",
  "properties": {
    "gn:admin1_code":"77",
    "gn:asciiname":"Rameshka",
    "gn:country_code":"RU",
    "gn:dem":149,
    "gn:feature_class":"P",
    "gn:feature_code":"PPL",
    "gn:name":"Rameshka",
    "gn:population":0,
    "gn:timezone":"Europe/Moscow",
    "iso:country":"RU",
    "name:rus_x_preferred":[
        "\u0420\u0430\u043c\u0435\u0448\u043a\u0430"
    ],
    "wof:name":"Rameshka",
    "wof:placetype":"locality"
},
  "geometry": {"coordinates":[38.3003,57.3058],"type":"Point"}
}