{
  "type": "Feature",
  "properties": {
    "gn:admin1_code":"91",
    "gn:asciiname":"Sosnovka",
    "gn:country_code":"RU",
    "gn:dem":234,
    "gn:feature_class":"P",
    "gn:feature_code":"PPL",
    "gn:name":"Sosnovka",
    "gn:population":0,
    "gn:timezone":"Asia/Krasnoyarsk",
    "iso:country":"RU",
    "name:eng_x_preferred":[
        "Sosnovka"
    ],
    "name:nor_x_preferred":[
        "Sosnovka"
    ],
    "name:rus_x_preferred":[
        "\u0421\u043e\u0441\u043d\u043e\u0432\u043a\u0430"
    ],
    "wof:name":"Sosnovka",
    "wof:placetype":"locality"
},
  "geometry": {"coordinates":[97.5381,56.4543],"type":"Point"}
}