{
  "type": "Feature",
  "properties": {
    "gn:admin1_code":"33.0",
    "gn:asciiname":"Krutikovshchina",
    "gn:country_code":"RU",
    "gn:dem":141,
    "gn:feature_class":"P",
    "gn:feature_code":"PPL",
    "gn:name":"Krutikovshchina",
    "gn:population":0,
    "gn:timezone":"Europe/Kirov",
    "iso:country":"RU",
    "name:rus_x_preferred":[
        "\u041a\u0440\u0443\u0442\u0438\u043a\u043e\u0432\u0449\u0438\u043d\u0430"
    ],
    "wof:name":"Krutikovshchina",
    "wof:placetype":"locality"
},
  "geometry": {"coordinates":[48.68659,58.23141999999999],"type":"Point"}
}