{
  "type": "Feature",
  "properties": {
    "gn:admin1_code":"21.0",
    "gn:asciiname":"Postninskiy",
    "gn:country_code":"RU",
    "gn:dem":125,
    "gn:feature_class":"P",
    "gn:feature_code":"PPL",
    "gn:name":"Postninskiy",
    "gn:population":0,
    "gn:timezone":"Europe/Moscow",
    "iso:country":"RU",
    "name:rus_x_preferred":[
        "\u041f\u043e\u0441\u0442\u043d\u0438\u043d\u0441\u043a\u0438\u0439"
    ],
    "name:und_x_variant":[
        "\u041f\u043e\u0441\u0442\u043d\u0438\u043d\u0441\u043a\u0438\u0439"
    ],
    "wof:name":"Postninskiy",
    "wof:placetype":"locality"
},
  "geometry": {"coordinates":[41.70417,57.13758000000001],"type":"Point"}
}