{
  "type": "Feature",
  "properties": {
    "gn:admin1_code":"88",
    "gn:asciiname":"Ostashkino",
    "gn:country_code":"RU",
    "gn:dem":102,
    "gn:feature_class":"P",
    "gn:feature_code":"PPL",
    "gn:name":"Ostashkino",
    "gn:population":0,
    "gn:timezone":"Europe/Moscow",
    "iso:country":"RU",
    "name:rus_x_preferred":[
        "\u041e\u0441\u0442\u0430\u0448\u043a\u0438\u043d\u043e"
    ],
    "wof:name":"Ostashkino",
    "wof:placetype":"locality"
},
  "geometry": {"coordinates":[39.81503,57.31023],"type":"Point"}
}