{
  "type": "Feature",
  "properties": {
    "gn:admin1_code":"91",
    "gn:asciiname":"Osharovo",
    "gn:country_code":"RU",
    "gn:dem":244,
    "gn:feature_class":"P",
    "gn:feature_code":"PPL",
    "gn:name":"Osharovo",
    "gn:population":0,
    "gn:timezone":"Asia/Krasnoyarsk",
    "iso:country":"RU",
    "name:eng_x_preferred":[
        "Osharovo"
    ],
    "name:nor_x_preferred":[
        "Osjarovo"
    ],
    "name:rus_x_preferred":[
        "\u041e\u0448\u0430\u0440\u043e\u0432\u043e"
    ],
    "wof:name":"Osharovo",
    "wof:placetype":"locality"
},
  "geometry": {"coordinates":[96.74890000000001,56.2761],"type":"Point"}
}