{
  "type": "Feature",
  "properties": {
    "gn:admin1_code":"33",
    "gn:asciiname":"Mitroki",
    "gn:country_code":"RU",
    "gn:dem":140,
    "gn:feature_class":"P",
    "gn:feature_code":"PPL",
    "gn:name":"Mitroki",
    "gn:population":0,
    "gn:timezone":"Europe/Kirov",
    "iso:country":"RU",
    "name:rus_x_preferred":[
        "\u041c\u0438\u0442\u0440\u043e\u043a\u0438"
    ],
    "name:und_x_variant":[
        "\u041c\u0438\u0442\u0440\u043e\u043a\u0438"
    ],
    "wof:name":"Mitroki",
    "wof:placetype":"locality"
},
  "geometry": {"coordinates":[51.08209,58.03418000000001],"type":"Point"}
}