{
  "type": "Feature",
  "properties": {
    "gn:admin1_code":"85",
    "gn:asciiname":"Prokopovo",
    "gn:country_code":"RU",
    "gn:dem":121,
    "gn:feature_class":"P",
    "gn:feature_code":"PPL",
    "gn:name":"Prokopovo",
    "gn:population":0,
    "gn:timezone":"Europe/Moscow",
    "iso:country":"RU",
    "name:rus_x_preferred":[
        "\u041f\u0440\u043e\u043a\u043e\u043f\u043e\u0432\u043e"
    ],
    "wof:name":"Prokopovo",
    "wof:placetype":"locality"
},
  "geometry": {"coordinates":[39.9442,59.6112],"type":"Point"}
}