{
  "type": "Feature",
  "properties": {
    "gn:admin1_code":"90.0",
    "gn:asciiname":"Bogorodsk",
    "gn:country_code":"RU",
    "gn:dem":196,
    "gn:feature_class":"P",
    "gn:feature_code":"PPL",
    "gn:name":"Bogorodsk",
    "gn:population":0,
    "gn:timezone":"Asia/Yekaterinburg",
    "iso:country":"RU",
    "name:eng_x_preferred":[
        "Bogorodsk"
    ],
    "name:nor_x_preferred":[
        "Bogorodsk"
    ],
    "name:rus_x_preferred":[
        "\u0411\u043e\u0433\u043e\u0440\u043e\u0434\u0441\u043a"
    ],
    "name:und_x_variant":[
        "Bogorodskoye",
        "Bogorodsk"
    ],
    "wof:name":"Bogorodsk",
    "wof:placetype":"locality"
},
  "geometry": {"coordinates":[56.93736,56.69761999999999],"type":"Point"}
}