{
  "type": "Feature",
  "properties": {
    "gn:admin1_code":"90",
    "gn:asciiname":"Kedrovo",
    "gn:country_code":"RU",
    "gn:dem":140,
    "gn:feature_class":"P",
    "gn:feature_code":"PPL",
    "gn:name":"Kedrovo",
    "gn:population":0,
    "gn:timezone":"Asia/Yekaterinburg",
    "iso:country":"RU",
    "name:rus_x_preferred":[
        "\u041a\u0435\u0434\u0440\u043e\u0432\u043e"
    ],
    "name:und_x_variant":[
        "Proryv",
        "Kedrovo"
    ],
    "wof:name":"Kedrovo",
    "wof:placetype":"locality"
},
  "geometry": {"coordinates":[56.325,59.5173],"type":"Point"}
}