{
  "type": "Feature",
  "properties": {
    "gn:admin1_code":"93",
    "gn:asciiname":"Posel'skoye",
    "gn:country_code":"RU",
    "gn:dem":652,
    "gn:feature_class":"P",
    "gn:feature_code":"PPL",
    "gn:name":"Posel\u2019skoye",
    "gn:population":0,
    "gn:timezone":"Asia/Chita",
    "iso:country":"RU",
    "name:eng_x_preferred":[
        "Posel'skoye"
    ],
    "name:nor_x_preferred":[
        "Poselskoje"
    ],
    "name:rus_x_preferred":[
        "\u041f\u043e\u0441\u0435\u043b\u044c\u0441\u043a\u043e\u0435"
    ],
    "name:und_x_variant":[
        "Posel\u2019skoye"
    ],
    "wof:name":"Posel'skoye",
    "wof:placetype":"locality"
},
  "geometry": {"coordinates":[117.3172,52.4926],"type":"Point"}
}