{
  "type": "Feature",
  "properties": {
    "gn:admin1_code":"9",
    "gn:asciiname":"Krasnyy Vyselok",
    "gn:country_code":"RU",
    "gn:dem":128,
    "gn:feature_class":"P",
    "gn:feature_code":"PPL",
    "gn:name":"Krasnyy Vys\u00eblok",
    "gn:population":0,
    "gn:timezone":"Europe/Moscow",
    "iso:country":"RU",
    "name:rus_x_preferred":[
        "\u041a\u0440\u0430\u0441\u043d\u044b\u0439 \u0412\u044b\u0441\u0451\u043b\u043e\u043a"
    ],
    "name:und_x_variant":[
        "Krasnyy Vys\u00eblok"
    ],
    "wof:name":"Krasnyy Vyselok",
    "wof:placetype":"locality"
},
  "geometry": {"coordinates":[37.76841,50.95592],"type":"Point"}
}