{
  "type": "Feature",
  "properties": {
    "gn:admin1_code":"55",
    "gn:asciiname":"Karachevo",
    "gn:country_code":"RU",
    "gn:dem":124,
    "gn:feature_class":"P",
    "gn:feature_code":"PPL",
    "gn:name":"Karachevo",
    "gn:population":0,
    "gn:timezone":"Asia/Yekaterinburg",
    "iso:country":"RU",
    "name:rus_x_preferred":[
        "\u041a\u0430\u0440\u0430\u0447\u0435\u0432\u043e"
    ],
    "name:und_x_variant":[
        "\u041a\u0430\u0440\u0430\u0447\u0435\u0432\u043e"
    ],
    "wof:name":"Karachevo",
    "wof:placetype":"locality"
},
  "geometry": {"coordinates":[52.2935,53.1351],"type":"Point"}
}