{
  "type": "Feature",
  "properties": {
    "gn:admin1_code":"4",
    "gn:asciiname":"Ust'yanka",
    "gn:country_code":"RU",
    "gn:dem":267,
    "gn:feature_class":"P",
    "gn:feature_code":"PPL",
    "gn:name":"Ust\u2019yanka",
    "gn:population":0,
    "gn:timezone":"Asia/Barnaul",
    "iso:country":"RU",
    "name:eng_x_preferred":[
        "Ust'yanka"
    ],
    "name:nor_x_preferred":[
        "Ustjanka"
    ],
    "name:rus_x_preferred":[
        "\u0423\u0441\u0442\u044c\u044f\u043d\u043a\u0430"
    ],
    "name:und_x_variant":[
        "Ust\u2019-Yanskoye",
        "Ust\u2019yanskaya",
        "Ust\u2019yanka"
    ],
    "wof:name":"Ust'yanka",
    "wof:placetype":"locality"
},
  "geometry": {"coordinates":[81.60339999999999,51.14534],"type":"Point"}
}