{
  "type": "Feature",
  "properties": {
    "gn:country":"RU",
    "gn:fcode":"PPL",
    "gn:pop":3000,
    "iso:country":"RU",
    "name:ara_x_preferred":[
        "\u0623\u0628\u0631\u0627\u0648-\u062f\u064a\u0648\u0631\u0633\u0648"
    ],
    "name:dut_x_preferred":[
        "Abraoe-Djurso"
    ],
    "name:eng_x_preferred":[
        "Abrau-Dyurso"
    ],
    "name:est_x_preferred":[
        "Abrau-Djurso"
    ],
    "name:fre_x_preferred":[
        "Abraou-Diourso"
    ],
    "name:ger_x_preferred":[
        "Abrau-Djurso"
    ],
    "name:lit_x_preferred":[
        "Abrau-Diursu"
    ],
    "name:nor_x_preferred":[
        "Abrau-Djurso"
    ],
    "name:rus_x_preferred":[
        "\u0410\u0431\u0440\u0430\u0443-\u0414\u044e\u0440\u0441\u043e"
    ],
    "name:spa_x_preferred":[
        "Abr\u00e1u-Diurs\u00f3"
    ],
    "name:ukr_x_preferred":[
        "\u0410\u0431\u0440\u0430\u0443-\u0414\u044e\u0440\u0441\u043e"
    ],
    "qs:name":"Abrau-Dyurso",
    "qs:name_adm0":"Russia",
    "qs:name_adm1":"Krasnodar Krai",
    "qs:photos":183,
    "qs:photos_1k":37,
    "qs:photos_9k":1,
    "qs:photos_9r":4,
    "qs:photos_all":183,
    "qs:photos_sr":4,
    "qs:placetype":"Town",
    "qs:pop_sr":"4",
    "wd:wordcount":644,
    "wof:name":"Abrau-Dyurso",
    "wof:placetype":"locality",
    "wof:population":3000
},
  "geometry": {"coordinates":[37.60098,44.69973],"type":"Point"}
}