{
  "type": "Feature",
  "properties": {
    "gn:admin1_code":"6",
    "gn:asciiname":"Kisherma",
    "gn:country_code":"RU",
    "gn:dem":86,
    "gn:feature_class":"P",
    "gn:feature_code":"PPL",
    "gn:name":"Kisherma",
    "gn:population":0,
    "gn:timezone":"Europe/Moscow",
    "iso:country":"RU",
    "name:eng_x_preferred":[
        "Kisherma"
    ],
    "name:nor_x_preferred":[
        "Kisjerma"
    ],
    "name:rus_x_preferred":[
        "\u041a\u0438\u0448\u0435\u0440\u043c\u0430"
    ],
    "name:und_x_variant":[
        "Kisheromskoye",
        "\u041a\u0438\u0448\u0435\u0440\u043c\u0430",
        "Kisherma"
    ],
    "wof:name":"Kisherma",
    "wof:placetype":"locality"
},
  "geometry": {"coordinates":[41.6868,61.1848],"type":"Point"}
}