{
  "type": "Feature",
  "properties": {
    "gn:admin1_code":"65.0",
    "gn:asciiname":"Yelkhi",
    "gn:country_code":"RU",
    "gn:dem":84,
    "gn:feature_class":"P",
    "gn:feature_code":"PPL",
    "gn:name":"Yelkhi",
    "gn:population":0,
    "gn:timezone":"Europe/Samara",
    "iso:country":"RU",
    "name:rus_x_preferred":[
        "\u0415\u043b\u0445\u0438"
    ],
    "wof:name":"Yelkhi",
    "wof:placetype":"locality"
},
  "geometry": {"coordinates":[50.84873,53.88014],"type":"Point"}
}