{
  "type": "Feature",
  "properties": {
    "gn:admin1_code":"17",
    "gn:asciiname":"Imeni Kirova",
    "gn:country_code":"RU",
    "gn:dem":-10,
    "gn:feature_class":"P",
    "gn:feature_code":"PPL",
    "gn:name":"Imeni Kirova",
    "gn:population":0,
    "gn:timezone":"Europe/Moscow",
    "iso:country":"RU",
    "name:ceb_x_preferred":[
        "Imeni Kirova"
    ],
    "name:rus_x_preferred":[
        "\u0418\u043c\u0435\u043d\u0438 \u041a\u0438\u0440\u043e\u0432\u0430"
    ],
    "name:swe_x_preferred":[
        "Imeni Kirova"
    ],
    "name:und_x_variant":[
        "\u0418\u043c\u0435\u043d\u0438 \u041a\u0438\u0440\u043e\u0432\u0430"
    ],
    "wof:name":"Imeni Kirova",
    "wof:placetype":"locality"
},
  "geometry": {"coordinates":[46.70564,43.86396],"type":"Point"}
}