{
  "type": "Feature",
  "properties": {
    "gn:admin1_code":"42",
    "gn:asciiname":"Maloye Kikerino",
    "gn:country_code":"RU",
    "gn:dem":136,
    "gn:feature_class":"P",
    "gn:feature_code":"PPL",
    "gn:name":"Maloye Kikerino",
    "gn:population":0,
    "gn:timezone":"Europe/Moscow",
    "iso:country":"RU",
    "name:fin_x_preferred":[
        "Pieni-Kikkeri"
    ],
    "name:nor_x_preferred":[
        "Maloje Kikerino"
    ],
    "name:rus_x_preferred":[
        "\u041c\u0430\u043b\u043e\u0435 \u041a\u0438\u043a\u0435\u0440\u0438\u043d\u043e"
    ],
    "wof:name":"Maloye Kikerino",
    "wof:placetype":"locality"
},
  "geometry": {"coordinates":[29.5927,59.46731],"type":"Point"}
}