{
  "type": "Feature",
  "properties": {
    "gn:admin1_code":"83",
    "gn:asciiname":"Yefimovskoye",
    "gn:cc2":"RU",
    "gn:country_code":"RU",
    "gn:dem":128,
    "gn:feature_class":"P",
    "gn:feature_code":"PPL",
    "gn:name":"Yefimovskoye",
    "gn:population":0,
    "gn:timezone":"Europe/Moscow",
    "iso:country":"RU",
    "name:und_x_variant":[
        "Tashchilovo",
        "Yefimovskoye"
    ],
    "wof:name":"Yefimovskoye",
    "wof:placetype":"locality"
},
  "geometry": {"coordinates":[40.56667,55.98333],"type":"Point"}
}