{
  "type": "Feature",
  "properties": {
    "gn:admin1_code":"45.0",
    "gn:asciiname":"Apshatnur",
    "gn:country_code":"RU",
    "gn:dem":157,
    "gn:feature_class":"P",
    "gn:feature_code":"PPL",
    "gn:name":"Apshatnur",
    "gn:population":0,
    "gn:timezone":"Europe/Moscow",
    "iso:country":"RU",
    "name:eng_x_preferred":[
        "Apshatnur"
    ],
    "name:nor_x_preferred":[
        "Apsjatnur"
    ],
    "name:rus_x_preferred":[
        "\u0410\u043f\u0448\u0430\u0442\u043d\u0443\u0440"
    ],
    "name:und_x_variant":[
        "\u0410\u043f\u0448\u0430\u0442\u043d\u0443\u0440",
        "Apshatnur"
    ],
    "wof:name":"Apshatnur",
    "wof:placetype":"locality"
},
  "geometry": {"coordinates":[48.56972,57.03444],"type":"Point"}
}