{
  "type": "Feature",
  "properties": {
    "gn:admin1_code":"67",
    "gn:asciiname":"Obliv",
    "gn:country_code":"RU",
    "gn:dem":32,
    "gn:feature_class":"P",
    "gn:feature_code":"PPL",
    "gn:name":"Obliv",
    "gn:population":0,
    "gn:timezone":"Europe/Saratov",
    "iso:country":"RU",
    "name:rus_x_preferred":[
        "\u041e\u0431\u043b\u0438\u0432"
    ],
    "name:und_x_variant":[
        "\u041e\u0431\u043b\u0438\u0432"
    ],
    "wof:name":"Obliv",
    "wof:placetype":"locality"
},
  "geometry": {"coordinates":[47.97637,50.62593],"type":"Point"}
}