{
  "type": "Feature",
  "properties": {
    "gn:admin1_code":"38",
    "gn:asciiname":"Bakanskaya",
    "gn:country_code":"RU",
    "gn:dem":66,
    "gn:feature_class":"P",
    "gn:feature_code":"PPL",
    "gn:name":"Bakanskaya",
    "gn:population":0,
    "gn:timezone":"Europe/Moscow",
    "iso:country":"RU",
    "name:nor_x_preferred":[
        "Bakanskaja"
    ],
    "name:rus_x_preferred":[
        "\u0411\u0430\u043a\u0430\u043d\u0441\u043a\u0430\u044f"
    ],
    "wof:name":"Bakanskaya",
    "wof:placetype":"locality"
},
  "geometry": {"coordinates":[37.87603,44.87034],"type":"Point"}
}