{
  "type": "Feature",
  "properties": {
    "gn:admin1_code":"89.0",
    "gn:asciiname":"Devyatyy Kilometr",
    "gn:country_code":"RU",
    "gn:dem":141,
    "gn:feature_class":"P",
    "gn:feature_code":"PPL",
    "gn:name":"Devyatyy Kilometr",
    "gn:population":0,
    "gn:timezone":"Asia/Vladivostok",
    "iso:country":"RU",
    "name:rus_x_preferred":[
        "\u0414\u0435\u0432\u044f\u0442\u044b\u0439 \u041a\u0438\u043b\u043e\u043c\u0435\u0442\u0440"
    ],
    "wof:name":"Devyatyy Kilometr",
    "wof:placetype":"locality"
},
  "geometry": {"coordinates":[132.83591000000001,48.75852],"type":"Point"}
}