{
  "type": "Feature",
  "properties": {
    "gn:admin1_code":"76.0",
    "gn:asciiname":"Bogateyevo",
    "gn:cc2":"RU",
    "gn:country_code":"RU",
    "gn:dem":185,
    "gn:feature_class":"P",
    "gn:feature_code":"PPL",
    "gn:name":"Bogateyevo",
    "gn:population":0,
    "gn:timezone":"Europe/Moscow",
    "iso:country":"RU",
    "name:und_x_variant":[
        "Bogateyevo-Bogdanovka"
    ],
    "wof:name":"Bogateyevo",
    "wof:placetype":"locality"
},
  "geometry": {"coordinates":[37.70889,53.67639000000001],"type":"Point"}
}