{
  "type": "Feature",
  "properties": {
    "gn:admin1_code":"13",
    "gn:asciiname":"Vandyshevka",
    "gn:country_code":"RU",
    "gn:dem":311,
    "gn:feature_class":"P",
    "gn:feature_code":"PPL",
    "gn:name":"Vandyshevka",
    "gn:population":0,
    "gn:timezone":"Asia/Yekaterinburg",
    "iso:country":"RU",
    "name:rus_x_preferred":[
        "\u0412\u0430\u043d\u0434\u044b\u0448\u0435\u0432\u043a\u0430"
    ],
    "name:und_x_variant":[
        "Vandyshev",
        "Vandyshevka"
    ],
    "wof:name":"Vandyshevka",
    "wof:placetype":"locality"
},
  "geometry": {"coordinates":[60.0923,54.3361],"type":"Point"}
}