{
  "type": "Feature",
  "properties": {
    "gn:admin1_code":"4.0",
    "gn:asciiname":"Poteryayevskiy",
    "gn:country_code":"RU",
    "gn:dem":215,
    "gn:feature_class":"P",
    "gn:feature_code":"PPL",
    "gn:name":"Poteryayevskiy",
    "gn:population":0,
    "gn:timezone":"Asia/Barnaul",
    "iso:country":"RU",
    "name:rus_x_preferred":[
        "\u041f\u043e\u0442\u0435\u0440\u044f\u0435\u0432\u0441\u043a\u0438\u0439"
    ],
    "wof:name":"Poteryayevskiy",
    "wof:placetype":"locality"
},
  "geometry": {"coordinates":[81.7578,52.9706],"type":"Point"}
}