{
  "type": "Feature",
  "properties": {
    "gn:admin1_code":"71",
    "gn:asciiname":"Gur'yeva",
    "gn:country_code":"RU",
    "gn:dem":79,
    "gn:feature_class":"P",
    "gn:feature_code":"PPL",
    "gn:name":"Gur\u2019yeva",
    "gn:population":0,
    "gn:timezone":"Asia/Yekaterinburg",
    "iso:country":"RU",
    "name:rus_x_preferred":[
        "\u0413\u0443\u0440\u044c\u0435\u0432\u0430"
    ],
    "name:und_x_variant":[
        "Gur\u2019yeva",
        "\u0413\u0443\u0440\u044c\u0435\u0432\u0430"
    ],
    "wof:name":"Gur'yeva",
    "wof:placetype":"locality"
},
  "geometry": {"coordinates":[62.61666999999999,59.66667],"type":"Point"}
}