{
  "type": "Feature",
  "properties": {
    "gn:admin1_code":"29",
    "gn:asciiname":"Taydonskiy",
    "gn:country_code":"RU",
    "gn:dem":144,
    "gn:feature_class":"P",
    "gn:feature_code":"PPL",
    "gn:name":"Taydonskiy",
    "gn:population":0,
    "gn:timezone":"Asia/Novokuznetsk",
    "iso:country":"RU",
    "name:eng_x_preferred":[
        "Taydonskiy"
    ],
    "name:nor_x_preferred":[
        "Tajdonskij"
    ],
    "name:rus_x_preferred":[
        "\u0422\u0430\u0439\u0434\u043e\u043d\u0441\u043a\u0438\u0439"
    ],
    "name:und_x_variant":[
        "Ulumanda"
    ],
    "wof:name":"Taydonskiy",
    "wof:placetype":"locality"
},
  "geometry": {"coordinates":[87.2594,54.90951999999999],"type":"Point"}
}