{
  "type": "Feature",
  "properties": {
    "gn:admin1_code":"73",
    "gn:asciiname":"Aktuba",
    "gn:country_code":"RU",
    "gn:dem":274,
    "gn:feature_class":"P",
    "gn:feature_code":"PPL",
    "gn:name":"Aktuba",
    "gn:population":0,
    "gn:timezone":"Europe/Moscow",
    "iso:country":"RU",
    "name:rus_x_preferred":[
        "\u0410\u043a\u0442\u0443\u0431\u0430"
    ],
    "name:und_x_variant":[
        "\u0410\u043a\u0442\u0443\u0431\u0430"
    ],
    "wof:name":"Aktuba",
    "wof:placetype":"locality"
},
  "geometry": {"coordinates":[52.7753,54.815],"type":"Point"}
}