{
  "type": "Feature",
  "properties": {
    "gn:admin1_code":"77",
    "gn:asciiname":"Gostinitsa",
    "gn:country_code":"RU",
    "gn:dem":178,
    "gn:feature_class":"P",
    "gn:feature_code":"PPL",
    "gn:name":"Gostinitsa",
    "gn:population":0,
    "gn:timezone":"Europe/Moscow",
    "iso:country":"RU",
    "name:rus_x_preferred":[
        "\u0413\u043e\u0441\u0442\u0438\u043d\u0438\u0446\u0430"
    ],
    "name:und_x_variant":[
        "\u0413\u043e\u0441\u0442\u0438\u043d\u0438\u0446\u0430"
    ],
    "wof:name":"Gostinitsa",
    "wof:placetype":"locality"
},
  "geometry": {"coordinates":[36.0348,58.0335],"type":"Point"}
}