{
  "type": "Feature",
  "properties": {
    "gn:admin1_code":"85.0",
    "gn:asciiname":"Bol'shoy Yerogodskiy Pochinok",
    "gn:country_code":"RU",
    "gn:dem":160,
    "gn:feature_class":"P",
    "gn:feature_code":"PPL",
    "gn:name":"Bol\u2019shoy Yerogodskiy Pochinok",
    "gn:population":0,
    "gn:timezone":"Europe/Moscow",
    "iso:country":"RU",
    "name:rus_x_preferred":[
        "\u0411\u043e\u043b\u044c\u0448\u043e\u0439 \u0415\u0440\u043e\u0433\u043e\u0434\u0441\u043a\u0438\u0439 \u041f\u043e\u0447\u0438\u043d\u043e\u043a"
    ],
    "name:und_x_variant":[
        "Bol\u2019she-Yerogodskiy",
        "Verkhne-Yerogodskoye",
        "Bol\u2019she Yerogodskiy Pervyy",
        "Bol\u2019shoy Verkhne-Yerogodskiy Pochinok",
        "Bol\u2019she-Yerogodskiy Pochinok",
        "Bol\u2019shoy Yerogodskiy Pochinok",
        "\u0411\u043e\u043b\u044c\u0448\u043e\u0439 \u0415\u0440\u043e\u0433\u043e\u0434\u0441\u043a\u0438\u0439 \u041f\u043e\u0447\u0438\u043d\u043e\u043a"
    ],
    "wof:name":"Bol'shoy Yerogodskiy Pochinok",
    "wof:placetype":"locality"
},
  "geometry": {"coordinates":[45.33242,61.03713000000001],"type":"Point"}
}