{
  "type": "Feature",
  "properties": {
    "gn:admin1_code":"37",
    "gn:asciiname":"Kordomets",
    "gn:country_code":"RU",
    "gn:dem":156,
    "gn:feature_class":"P",
    "gn:feature_code":"PPL",
    "gn:name":"Kordomets",
    "gn:population":0,
    "gn:timezone":"Europe/Moscow",
    "iso:country":"RU",
    "name:rus_x_preferred":[
        "\u041a\u043e\u0440\u0434\u043e\u043c\u0435\u0446"
    ],
    "name:und_x_variant":[
        "\u041a\u043e\u0440\u0434\u043e\u043c\u0435\u0446"
    ],
    "wof:name":"Kordomets",
    "wof:placetype":"locality"
},
  "geometry": {"coordinates":[42.9135,58.1381],"type":"Point"}
}