{
  "type": "Feature",
  "properties": {
    "gn:admin1_code":"47.0",
    "gn:asciiname":"Blagoveshchen'ye",
    "gn:country_code":"RU",
    "gn:dem":248,
    "gn:feature_class":"P",
    "gn:feature_code":"PPL",
    "gn:name":"Blagoveshchen\u2019ye",
    "gn:population":10,
    "gn:timezone":"Europe/Moscow",
    "iso:country":"RU",
    "name:eng_x_preferred":[
        "Blagoveshchen\u2019ye"
    ],
    "name:rus_x_preferred":[
        "\u0411\u043b\u0430\u0433\u043e\u0432\u0435\u0449\u0435\u043d\u044c\u0435"
    ],
    "wof:name":"Blagoveshchen'ye",
    "wof:placetype":"locality",
    "wof:population":10
},
  "geometry": {"coordinates":[38.08166,56.32311],"type":"Point"}
}