{
  "type": "Feature",
  "properties": {
    "gn:admin1_code":"86",
    "gn:asciiname":"Kulishovka",
    "gn:country_code":"RU",
    "gn:dem":89,
    "gn:feature_class":"P",
    "gn:feature_code":"PPL",
    "gn:name":"Kulishovka",
    "gn:population":0,
    "gn:timezone":"Europe/Moscow",
    "iso:country":"RU",
    "name:rus_x_preferred":[
        "\u041a\u0443\u043b\u0438\u0448\u043e\u0432\u043a\u0430"
    ],
    "name:und_x_variant":[
        "Kuleshevka",
        "Kulishovka",
        "\u041a\u0443\u043b\u0438\u0448\u043e\u0432\u043a\u0430"
    ],
    "wof:name":"Kulishovka",
    "wof:placetype":"locality"
},
  "geometry": {"coordinates":[39.27757,50.34549000000001],"type":"Point"}
}