{
  "type": "Feature",
  "properties": {
    "gn:admin1_code":"63",
    "gn:admin2_code":"Verkhoyansky District (undefined)",
    "gn:asciiname":"Balagannakh",
    "gn:country_code":"RU",
    "gn:dem":138,
    "gn:feature_class":"P",
    "gn:feature_code":"PPL",
    "gn:name":"Balagannakh",
    "gn:population":0,
    "gn:timezone":"Asia/Vladivostok",
    "iso:country":"RU",
    "name:nor_x_preferred":[
        "Balagannakh"
    ],
    "name:rus_x_preferred":[
        "\u0411\u0430\u043b\u0430\u0433\u0430\u043d\u043d\u0430\u0445"
    ],
    "wof:name":"Balagannakh",
    "wof:placetype":"locality"
},
  "geometry": {"coordinates":[134.46666999999999,67.61667],"type":"Point"}
}