{
  "type": "Feature",
  "properties": {
    "gn:admin1_code":"44",
    "gn:asciiname":"Ugulan",
    "gn:country_code":"RU",
    "gn:dem":27,
    "gn:feature_class":"P",
    "gn:feature_code":"PPL",
    "gn:name":"Ugulan",
    "gn:population":0,
    "gn:timezone":"Asia/Magadan",
    "iso:country":"RU",
    "wof:name":"Ugulan",
    "wof:placetype":"locality"
},
  "geometry": {"coordinates":[155.16666999999995,60.46666999999999],"type":"Point"}
}