{
  "type": "Feature",
  "properties": {
    "gn:admin1_code":"53",
    "gn:asciiname":"Kas'kovskiy",
    "gn:country_code":"RU",
    "gn:dem":148,
    "gn:feature_class":"P",
    "gn:feature_code":"PPL",
    "gn:name":"Kas\u2019kovskiy",
    "gn:population":0,
    "gn:timezone":"Asia/Novosibirsk",
    "iso:country":"RU",
    "name:eng_x_preferred":[
        "Kas'kovskiy"
    ],
    "name:nor_x_preferred":[
        "Kaskovskij"
    ],
    "name:rus_x_preferred":[
        "\u041a\u0430\u0441\u044c\u043a\u043e\u0432\u0441\u043a\u0438\u0439"
    ],
    "name:und_x_variant":[
        "Kas\u2019kovka",
        "Kas\u2019kovskiy"
    ],
    "wof:name":"Kas'kovskiy",
    "wof:placetype":"locality"
},
  "geometry": {"coordinates":[81.32340000000001,55.3944],"type":"Point"}
}