{
  "type": "Feature",
  "properties": {
    "gn:admin1_code":"60",
    "gn:asciiname":"Khordyshevo",
    "gn:country_code":"RU",
    "gn:dem":162,
    "gn:feature_class":"P",
    "gn:feature_code":"PPL",
    "gn:name":"Khordyshevo",
    "gn:population":0,
    "gn:timezone":"Europe/Moscow",
    "iso:country":"RU",
    "name:rus_x_preferred":[
        "\u0425\u043e\u0440\u0434\u044b\u0448\u0435\u0432\u043e"
    ],
    "wof:name":"Khordyshevo",
    "wof:placetype":"locality"
},
  "geometry": {"coordinates":[29.2763,56.4852],"type":"Point"}
}