{
  "type": "Feature",
  "properties": {
    "gn:admin1_code":"20",
    "gn:asciiname":"Makarovo",
    "gn:cc2":"RU",
    "gn:country_code":"RU",
    "gn:dem":259,
    "gn:feature_class":"P",
    "gn:feature_code":"PPL",
    "gn:name":"Makarovo",
    "gn:population":0,
    "gn:timezone":"Asia/Irkutsk",
    "iso:country":"RU",
    "name:eng_x_preferred":[
        "Makarovo"
    ],
    "name:nor_x_preferred":[
        "Makarovo"
    ],
    "name:rus_x_preferred":[
        "\u041c\u0430\u043a\u0430\u0440\u043e\u0432\u043e"
    ],
    "name:und_x_variant":[
        "Makarovskoye",
        "\u041c\u0430\u043a\u0430\u0440\u043e\u0432\u043e",
        "Makarovo"
    ],
    "wof:name":"Makarovo",
    "wof:placetype":"locality"
},
  "geometry": {"coordinates":[107.83444,57.4825],"type":"Point"}
}