{
  "type": "Feature",
  "properties": {
    "gn:admin1_code":"20",
    "gn:asciiname":"Kirkey",
    "gn:country_code":"RU",
    "gn:dem":502,
    "gn:feature_class":"P",
    "gn:feature_code":"PPL",
    "gn:name":"Kirkey",
    "gn:population":0,
    "gn:timezone":"Asia/Irkutsk",
    "iso:country":"RU",
    "name:eng_x_preferred":[
        "Kirkey"
    ],
    "name:nor_x_preferred":[
        "Kirkej"
    ],
    "name:rus_x_preferred":[
        "\u041a\u0438\u0440\u043a\u0435\u0439"
    ],
    "name:und_x_variant":[
        "Khirkhey"
    ],
    "wof:name":"Kirkey",
    "wof:placetype":"locality"
},
  "geometry": {"coordinates":[102.4053,53.2417],"type":"Point"}
}