{
  "type": "Feature",
  "properties": {
    "gn:admin1_code":"80",
    "gn:asciiname":"Tabani",
    "gn:cc2":"RU",
    "gn:country_code":"RU",
    "gn:dem":101,
    "gn:feature_class":"P",
    "gn:feature_code":"PPL",
    "gn:name":"Tabani",
    "gn:population":0,
    "gn:timezone":"Europe/Samara",
    "iso:country":"RU",
    "name:und_x_variant":[
        "Taban",
        "Tabani"
    ],
    "wof:name":"Tabani",
    "wof:placetype":"locality"
},
  "geometry": {"coordinates":[52.21667,56.68333000000001],"type":"Point"}
}