{
  "type": "Feature",
  "properties": {
    "gn:admin1_code":"60",
    "gn:asciiname":"Kapustino",
    "gn:country_code":"RU",
    "gn:dem":45,
    "gn:feature_class":"P",
    "gn:feature_code":"PPL",
    "gn:name":"Kapustino",
    "gn:population":0,
    "gn:timezone":"Europe/Moscow",
    "iso:country":"RU",
    "name:rus_x_preferred":[
        "\u041a\u0430\u043f\u0443\u0441\u0442\u0438\u043d\u043e"
    ],
    "wof:name":"Kapustino",
    "wof:placetype":"locality"
},
  "geometry": {"coordinates":[28.16709,57.65856],"type":"Point"}
}