{
  "type": "Feature",
  "properties": {
    "gn:admin1_code":"54",
    "gn:asciiname":"Dzhartargul'",
    "gn:country_code":"RU",
    "gn:dem":101,
    "gn:feature_class":"P",
    "gn:feature_code":"PPL",
    "gn:name":"Dzhartargul\u2019",
    "gn:population":0,
    "gn:timezone":"Asia/Omsk",
    "iso:country":"RU",
    "name:eng_x_preferred":[
        "Dzhartargul'"
    ],
    "name:nor_x_preferred":[
        "Dzjartargul"
    ],
    "name:rus_x_preferred":[
        "\u0414\u0436\u0430\u0440\u0442\u0430\u0440\u0433\u0443\u043b\u044c"
    ],
    "name:und_x_variant":[
        "Dzhaltyrgul\u2019",
        "Dzhamyrgul\u2019",
        "Dzhartargul\u2019",
        "Dzhartagul\u2019"
    ],
    "wof:name":"Dzhartargul'",
    "wof:placetype":"locality"
},
  "geometry": {"coordinates":[75.57608,54.3799],"type":"Point"}
}