{
  "type": "Feature",
  "properties": {
    "gn:admin1_code":"51",
    "gn:asciiname":"Kerzhenets",
    "gn:country_code":"RU",
    "gn:dem":99,
    "gn:feature_class":"P",
    "gn:feature_code":"PPL",
    "gn:name":"Kerzhenets",
    "gn:population":0,
    "gn:timezone":"Europe/Moscow",
    "iso:country":"RU",
    "name:ceb_x_preferred":[
        "Kerzhenets"
    ],
    "name:eng_x_preferred":[
        "Kerzhenets"
    ],
    "name:nor_x_preferred":[
        "Kerzjenets"
    ],
    "name:rus_x_preferred":[
        "\u041a\u0435\u0440\u0436\u0435\u043d\u0435\u0446"
    ],
    "wof:name":"Kerzhenets",
    "wof:placetype":"locality"
},
  "geometry": {"coordinates":[44.62806,56.90991],"type":"Point"}
}