{
  "type": "Feature",
  "properties": {
    "gn:admin1_code":"84",
    "gn:asciiname":"Skabelinskiy",
    "gn:country_code":"RU",
    "gn:dem":86,
    "gn:feature_class":"P",
    "gn:feature_code":"PPL",
    "gn:name":"Skabelinskiy",
    "gn:population":0,
    "gn:timezone":"Europe/Volgograd",
    "iso:country":"RU",
    "name:rus_x_preferred":[
        "\u0421\u043a\u0430\u0431\u0435\u043b\u0438\u043d\u0441\u043a\u0438\u0439"
    ],
    "name:und_x_variant":[
        "Skobelinskiy",
        "Skabelinskiy"
    ],
    "wof:name":"Skabelinskiy",
    "wof:placetype":"locality"
},
  "geometry": {"coordinates":[42.0246,50.9358],"type":"Point"}
}