{
  "type": "Feature",
  "properties": {
    "gn:admin1_code":"34",
    "gn:asciiname":"Malvavom",
    "gn:cc2":"RU",
    "gn:country_code":"RU",
    "gn:dem":82,
    "gn:feature_class":"P",
    "gn:feature_code":"PPL",
    "gn:name":"Malvavom",
    "gn:population":0,
    "gn:timezone":"Europe/Moscow",
    "iso:country":"RU",
    "name:rus_x_preferred":[
        "\u041c\u0430\u043b\u0432\u0430\u0432\u043e\u043c"
    ],
    "name:und_x_variant":[
        "Molvavom",
        "Mal\u2019vi-yu-vom",
        "Malvavom"
    ],
    "wof:name":"Malvavom",
    "wof:placetype":"locality"
},
  "geometry": {"coordinates":[59.36666999999999,66.75],"type":"Point"}
}