{
  "type": "Feature",
  "properties": {
    "gn:admin1_code":"75",
    "gn:asciiname":"Rybinsk",
    "gn:cc2":"RU",
    "gn:country_code":"RU",
    "gn:dem":79,
    "gn:feature_class":"P",
    "gn:feature_code":"PPL",
    "gn:name":"Rybinsk",
    "gn:population":0,
    "gn:timezone":"Asia/Tomsk",
    "iso:country":"RU",
    "name:eng_x_preferred":[
        "Rybinsk"
    ],
    "name:nor_x_preferred":[
        "Rybinsk"
    ],
    "name:rus_x_preferred":[
        "\u0420\u044b\u0431\u0438\u043d\u0441\u043a"
    ],
    "name:und_x_variant":[
        "Rybinskiy",
        "\u0420\u044b\u0431\u0438\u043d\u0441\u043a",
        "Rybinsk"
    ],
    "wof:name":"Rybinsk",
    "wof:placetype":"locality"
},
  "geometry": {"coordinates":[84.735,58.38806],"type":"Point"}
}