{
  "type": "Feature",
  "properties": {
    "gn:admin1_code":"41.0",
    "gn:asciiname":"Staraya Belitsa",
    "gn:country_code":"RU",
    "gn:dem":164,
    "gn:feature_class":"P",
    "gn:feature_code":"PPL",
    "gn:name":"Staraya Belitsa",
    "gn:population":0,
    "gn:timezone":"Europe/Moscow",
    "iso:country":"RU",
    "name:eng_x_preferred":[
        "Staraya Belitsa"
    ],
    "name:nor_x_preferred":[
        "Staraja Belitsa"
    ],
    "name:rus_x_preferred":[
        "\u0421\u0442\u0430\u0440\u0430\u044f \u0411\u0435\u043b\u0438\u0446\u0430"
    ],
    "name:und_x_variant":[
        "\u0421\u0442\u0430\u0440\u0430\u044f \u0411\u0435\u043b\u0438\u0446\u0430",
        "Staraya Belitsa"
    ],
    "wof:name":"Staraya Belitsa",
    "wof:placetype":"locality"
},
  "geometry": {"coordinates":[35.1917,51.9923],"type":"Point"}
}