{
  "type": "Feature",
  "properties": {
    "gn:admin1_code":"24",
    "gn:asciiname":"Tsagan-Talga",
    "gn:country_code":"RU",
    "gn:dem":6,
    "gn:feature_class":"P",
    "gn:feature_code":"PPL",
    "gn:name":"Tsagan-Talga",
    "gn:population":0,
    "gn:timezone":"Europe/Moscow",
    "iso:country":"RU",
    "name:und_x_variant":[
        "Tsagan-Tolga",
        "Tsagan-Talga"
    ],
    "wof:name":"Tsagan-Talga",
    "wof:placetype":"locality"
},
  "geometry": {"coordinates":[45.05911,47.72905],"type":"Point"}
}