{
  "type": "Feature",
  "properties": {
    "gn:admin1_code":"69",
    "gn:asciiname":"Kozilovo",
    "gn:cc2":"RU",
    "gn:country_code":"RU",
    "gn:dem":236,
    "gn:feature_class":"P",
    "gn:feature_code":"PPL",
    "gn:name":"Kozilovo",
    "gn:population":0,
    "gn:timezone":"Europe/Moscow",
    "iso:country":"RU",
    "name:rus_x_preferred":[
        "\u041a\u043e\u0437\u0438\u043b\u043e\u0432\u043e"
    ],
    "name:und_x_variant":[
        "Kozilova",
        "Kozilovo"
    ],
    "wof:name":"Kozilovo",
    "wof:placetype":"locality"
},
  "geometry": {"coordinates":[33.41667,55.48333],"type":"Point"}
}