{
  "type": "Feature",
  "properties": {
    "gn:admin1_code":"20",
    "gn:asciiname":"Ryabinovyy",
    "gn:country_code":"RU",
    "gn:dem":583,
    "gn:feature_class":"P",
    "gn:feature_code":"PPL",
    "gn:name":"Ryabinovyy",
    "gn:population":0,
    "gn:timezone":"Asia/Irkutsk",
    "iso:country":"RU",
    "name:rus_x_preferred":[
        "\u0420\u044f\u0431\u0438\u043d\u043e\u0432\u044b\u0439"
    ],
    "wof:name":"Ryabinovyy",
    "wof:placetype":"locality"
},
  "geometry": {"coordinates":[97.74720000000001,55.2258],"type":"Point"}
}