{
  "type": "Feature",
  "properties": {
    "gn:admin1_code":"33",
    "gn:asciiname":"Tarasovskiy",
    "gn:country_code":"RU",
    "gn:dem":139,
    "gn:feature_class":"P",
    "gn:feature_code":"PPL",
    "gn:name":"Tarasovskiy",
    "gn:population":0,
    "gn:timezone":"Europe/Kirov",
    "iso:country":"RU",
    "name:rus_x_preferred":[
        "\u0422\u0430\u0440\u0430\u0441\u043e\u0432\u0441\u043a\u0438\u0439"
    ],
    "name:und_x_variant":[
        "Staro-Tarasovskiy",
        "Staroye Tarasovo",
        "Tarasovskiy"
    ],
    "wof:name":"Tarasovskiy",
    "wof:placetype":"locality"
},
  "geometry": {"coordinates":[49.68307,57.13757],"type":"Point"}
}