{
  "type": "Feature",
  "properties": {
    "gn:admin1_code":"70",
    "gn:asciiname":"Gor'kaya Balka",
    "gn:country_code":"RU",
    "gn:dem":171,
    "gn:feature_class":"P",
    "gn:feature_code":"PPL",
    "gn:name":"Gor\u2019kaya Balka",
    "gn:population":0,
    "gn:timezone":"Europe/Moscow",
    "iso:country":"RU",
    "name:eng_x_preferred":[
        "Gor'kaya Balka"
    ],
    "name:nor_x_preferred":[
        "Gorkaja Balka"
    ],
    "name:rus_x_preferred":[
        "\u0413\u043e\u0440\u044c\u043a\u0430\u044f \u0411\u0430\u043b\u043a\u0430"
    ],
    "name:und_x_variant":[
        "Gor\u2019kaya Balka"
    ],
    "wof:name":"Gor'kaya Balka",
    "wof:placetype":"locality"
},
  "geometry": {"coordinates":[43.985,44.27222],"type":"Point"}
}