{
  "type": "Feature",
  "properties": {
    "gn:admin1_code":"76",
    "gn:asciiname":"Prishnya",
    "gn:country_code":"RU",
    "gn:dem":225,
    "gn:feature_class":"P",
    "gn:feature_code":"PPL",
    "gn:name":"Prishnya",
    "gn:population":0,
    "gn:timezone":"Europe/Moscow",
    "iso:country":"RU",
    "name:rus_x_preferred":[
        "\u041f\u0440\u0438\u0448\u043d\u044f"
    ],
    "name:und_x_variant":[
        "\u041f\u0440\u0438\u0448\u043d\u044f"
    ],
    "wof:name":"Prishnya",
    "wof:placetype":"locality"
},
  "geometry": {"coordinates":[37.31472,53.92845],"type":"Point"}
}