{
  "type": "Feature",
  "properties": {
    "gn:admin1_code":"51",
    "gn:asciiname":"Maloye Igolkino",
    "gn:country_code":"RU",
    "gn:dem":172,
    "gn:feature_class":"P",
    "gn:feature_code":"PPL",
    "gn:name":"Maloye Igolkino",
    "gn:population":0,
    "gn:timezone":"Europe/Moscow",
    "iso:country":"RU",
    "name:rus_x_preferred":[
        "\u041c\u0430\u043b\u043e\u0435 \u0418\u0433\u043e\u043b\u043a\u0438\u043d\u043e"
    ],
    "name:und_x_variant":[
        "Malaya Igolkina",
        "Maloye Igolkino"
    ],
    "wof:name":"Maloye Igolkino",
    "wof:placetype":"locality"
},
  "geometry": {"coordinates":[42.8909,55.9094],"type":"Point"}
}