{
  "type": "Feature",
  "properties": {
    "gn:admin1_code":"37.0",
    "gn:asciiname":"Sungurova",
    "gn:country_code":"RU",
    "gn:dem":117,
    "gn:feature_class":"P",
    "gn:feature_code":"PPL",
    "gn:name":"Sungurova",
    "gn:population":0,
    "gn:timezone":"Europe/Moscow",
    "iso:country":"RU",
    "name:rus_x_preferred":[
        "\u0421\u0443\u043d\u0433\u0443\u0440\u043e\u0432\u0430"
    ],
    "wof:name":"Sungurova",
    "wof:placetype":"locality"
},
  "geometry": {"coordinates":[41.39034,57.48965],"type":"Point"}
}