{
  "type": "Feature",
  "properties": {
    "gn:admin1_code":"90",
    "gn:asciiname":"Moskali",
    "gn:country_code":"RU",
    "gn:dem":164,
    "gn:feature_class":"P",
    "gn:feature_code":"PPL",
    "gn:name":"Moskali",
    "gn:population":0,
    "gn:timezone":"Asia/Yekaterinburg",
    "iso:country":"RU",
    "name:eng_x_preferred":[
        "Moskali"
    ],
    "name:nor_x_preferred":[
        "Moskali"
    ],
    "name:rus_x_preferred":[
        "\u041c\u043e\u0441\u043a\u0430\u043b\u0438"
    ],
    "name:und_x_variant":[
        "\u041c\u043e\u0441\u043a\u0430\u043b\u0438"
    ],
    "wof:name":"Moskali",
    "wof:placetype":"locality"
},
  "geometry": {"coordinates":[55.5409,60.29095],"type":"Point"}
}