{
  "type": "Feature",
  "properties": {
    "gn:admin1_code":"30",
    "gn:asciiname":"Khol'dzhekta",
    "gn:country_code":"RU",
    "gn:dem":6,
    "gn:feature_class":"P",
    "gn:feature_code":"PPL",
    "gn:name":"Khol\u2019dzhekta",
    "gn:population":0,
    "gn:timezone":"Asia/Vladivostok",
    "iso:country":"RU",
    "name:rus_x_preferred":[
        "\u0425\u043e\u043b\u044c\u0434\u0436\u0435\u043a\u0442\u0430"
    ],
    "name:und_x_variant":[
        "Khol\u2019dzhekta",
        "\u0425\u043e\u043b\u044c\u0434\u0436\u0435\u043a\u0442\u0430"
    ],
    "wof:name":"Khol'dzhekta",
    "wof:placetype":"locality"
},
  "geometry": {"coordinates":[139.96666999999999,51.71667],"type":"Point"}
}