{
  "type": "Feature",
  "properties": {
    "gn:admin1_code":"91",
    "gn:asciiname":"Karamyshevo",
    "gn:cc2":"RU",
    "gn:country_code":"RU",
    "gn:dem":290,
    "gn:feature_class":"P",
    "gn:feature_code":"PPL",
    "gn:name":"Karamyshevo",
    "gn:population":0,
    "gn:timezone":"Asia/Krasnoyarsk",
    "iso:country":"RU",
    "name:rus_x_preferred":[
        "\u041a\u0430\u0440\u0430\u043c\u044b\u0448\u0435\u0432\u043e"
    ],
    "name:sco_x_preferred":[
        "Karamyshevo"
    ],
    "name:und_x_variant":[
        "Karamysheva",
        "Karamyshevo"
    ],
    "wof:name":"Karamyshevo",
    "wof:placetype":"locality"
},
  "geometry": {"coordinates":[100.91667,57.56667],"type":"Point"}
}