{
  "type": "Feature",
  "properties": {
    "gn:admin1_code":"73.0",
    "gn:asciiname":"Cherki-Grishino",
    "gn:country_code":"RU",
    "gn:dem":72,
    "gn:feature_class":"P",
    "gn:feature_code":"PPL",
    "gn:name":"Cherki-Grishino",
    "gn:population":0,
    "gn:timezone":"Europe/Moscow",
    "iso:country":"RU",
    "name:eng_x_preferred":[
        "Cherki-Grishino"
    ],
    "name:nor_x_preferred":[
        "Tsjerki-Grisjino"
    ],
    "name:rus_x_preferred":[
        "\u0427\u0435\u0440\u043a\u0438-\u0413\u0440\u0438\u0448\u0438\u043d\u043e"
    ],
    "name:und_x_variant":[
        "Chirki-Grishino"
    ],
    "wof:name":"Cherki-Grishino",
    "wof:placetype":"locality"
},
  "geometry": {"coordinates":[48.30241,55.04968],"type":"Point"}
}