{
  "type": "Feature",
  "properties": {
    "gn:admin1_code":"69.0",
    "gn:asciiname":"Bykovo",
    "gn:cc2":"RU",
    "gn:country_code":"RU",
    "gn:dem":225,
    "gn:feature_class":"P",
    "gn:feature_code":"PPL",
    "gn:name":"Bykovo",
    "gn:population":0,
    "gn:timezone":"Europe/Moscow",
    "iso:country":"RU",
    "name:ara_x_preferred":[
        "\u0628\u064a\u0643\u0648\u0641\u0648"
    ],
    "name:ceb_x_preferred":[
        "Bykowo"
    ],
    "name:deu_x_preferred":[
        "Bykowo"
    ],
    "name:fra_x_preferred":[
        "Bykovo"
    ],
    "name:hye_x_preferred":[
        "\u0532\u056b\u056f\u0578\u057e\u0578"
    ],
    "name:ita_x_preferred":[
        "Bykovo"
    ],
    "name:lav_x_preferred":[
        "Bikova"
    ],
    "name:rus_x_preferred":[
        "\u0411\u044b\u043a\u043e\u0432\u043e"
    ],
    "name:sco_x_preferred":[
        "Bykovo"
    ],
    "name:slk_x_preferred":[
        "Bykovo"
    ],
    "name:ukr_x_preferred":[
        "\u0411\u0438\u043a\u043e\u0432\u043e"
    ],
    "name:und_x_variant":[
        "Bykova",
        "Bykovo",
        "\u0411\u044b\u043a\u043e\u0432\u043e"
    ],
    "wof:name":"Bykovo",
    "wof:placetype":"locality"
},
  "geometry": {"coordinates":[33.13028,55.4925],"type":"Point"}
}