{
  "type": "Feature",
  "properties": {
    "gn:admin1_code":"69.0",
    "gn:asciiname":"Bykovo",
    "gn:cc2":"RU",
    "gn:country_code":"RU",
    "gn:dem":225,
    "gn:feature_class":"P",
    "gn:feature_code":"PPL",
    "gn:name":"Bykovo",
    "gn:population":0,
    "gn:timezone":"Europe/Moscow",
    "iso:country":"RU",
    "name:rus_x_preferred":[
        "\u0411\u044b\u043a\u043e\u0432\u043e"
    ],
    "name:und_x_variant":[
        "Bykova",
        "Bykovo",
        "\u0411\u044b\u043a\u043e\u0432\u043e"
    ],
    "wof:name":"Bykovo",
    "wof:placetype":"locality"
},
  "geometry": {"coordinates":[33.13028,55.4925],"type":"Point"}
}