{
  "type": "Feature",
  "properties": {
    "gn:admin1_code":"75",
    "gn:asciiname":"Novaya Burka",
    "gn:country_code":"RU",
    "gn:dem":125,
    "gn:feature_class":"P",
    "gn:feature_code":"PPL",
    "gn:name":"Novaya Burka",
    "gn:population":0,
    "gn:timezone":"Asia/Tomsk",
    "iso:country":"RU",
    "name:eng_x_preferred":[
        "Novaya Burka"
    ],
    "name:nor_x_preferred":[
        "Nov.Burka"
    ],
    "name:rus_x_preferred":[
        "\u041d\u043e\u0432.\u0411\u0443\u0440\u043a\u0430"
    ],
    "name:rus_x_variant":[
        "\u041d\u043e\u0432\u0430\u044f \u0411\u0443\u0440\u043a\u0430"
    ],
    "wof:name":"Novaya Burka",
    "wof:placetype":"locality"
},
  "geometry": {"coordinates":[81.0522,56.9186],"type":"Point"}
}