{
  "type": "Feature",
  "properties": {
    "gn:admin1_code":"51.0",
    "gn:asciiname":"Beletskiy",
    "gn:country_code":"RU",
    "gn:dem":203,
    "gn:feature_class":"P",
    "gn:feature_code":"PPL",
    "gn:name":"Beletskiy",
    "gn:population":0,
    "gn:timezone":"Europe/Moscow",
    "iso:country":"RU",
    "name:rus_x_preferred":[
        "\u0411\u0435\u043b\u0435\u0446\u043a\u0438\u0439"
    ],
    "wof:name":"Beletskiy",
    "wof:placetype":"locality"
},
  "geometry": {"coordinates":[44.8044,54.94931999999999],"type":"Point"}
}