{
  "type": "Feature",
  "properties": {
    "gn:admin1_code":"69",
    "gn:asciiname":"Svaly",
    "gn:country_code":"RU",
    "gn:dem":199,
    "gn:feature_class":"P",
    "gn:feature_code":"PPL",
    "gn:name":"Svaly",
    "gn:population":0,
    "gn:timezone":"Europe/Moscow",
    "iso:country":"RU",
    "name:rus_x_preferred":[
        "\u0421\u0432\u0430\u043b\u044b"
    ],
    "wof:name":"Svaly",
    "wof:placetype":"locality"
},
  "geometry": {"coordinates":[32.29746,54.36751],"type":"Point"}
}