{
  "type": "Feature",
  "properties": {
    "gn:admin1_code":"21.0",
    "gn:asciiname":"Shepelino",
    "gn:country_code":"RU",
    "gn:dem":124,
    "gn:feature_class":"P",
    "gn:feature_code":"PPL",
    "gn:name":"Shepelino",
    "gn:population":0,
    "gn:timezone":"Europe/Moscow",
    "iso:country":"RU",
    "name:nor_x_preferred":[
        "Sjepelino"
    ],
    "name:rus_x_preferred":[
        "\u0428\u0435\u043f\u0435\u043b\u0438\u043d\u043e"
    ],
    "wof:name":"Shepelino",
    "wof:placetype":"locality"
},
  "geometry": {"coordinates":[42.83834,56.99603000000001],"type":"Point"}
}