{
  "type": "Feature",
  "properties": {
    "gn:admin1_code":"44",
    "gn:asciiname":"Bylar",
    "gn:cc2":"RU",
    "gn:country_code":"RU",
    "gn:dem":510,
    "gn:feature_class":"P",
    "gn:feature_code":"PPL",
    "gn:name":"Bylar",
    "gn:population":0,
    "gn:timezone":"Asia/Magadan",
    "iso:country":"RU",
    "name:rus_x_preferred":[
        "\u0411\u044b\u043b\u0430\u0440"
    ],
    "name:und_x_variant":[
        "Bolar",
        "Bylar"
    ],
    "wof:name":"Bylar",
    "wof:placetype":"locality"
},
  "geometry": {"coordinates":[148.03333000000001,62.16667],"type":"Point"}
}