{
  "type": "Feature",
  "properties": {
    "gn:admin1_code":"77",
    "gn:asciiname":"Glazkovo",
    "gn:country_code":"RU",
    "gn:dem":189,
    "gn:feature_class":"P",
    "gn:feature_code":"PPL",
    "gn:name":"Glazkovo",
    "gn:population":0,
    "gn:timezone":"Europe/Moscow",
    "iso:country":"RU",
    "name:rus_x_preferred":[
        "\u0413\u043b\u0430\u0437\u043a\u043e\u0432\u043e"
    ],
    "wof:name":"Glazkovo",
    "wof:placetype":"locality"
},
  "geometry": {"coordinates":[32.90823,56.13164],"type":"Point"}
}