{
  "type": "Feature",
  "properties": {
    "gn:admin1_code":"42.0",
    "gn:asciiname":"Belenok",
    "gn:country_code":"RU",
    "gn:dem":70,
    "gn:feature_class":"P",
    "gn:feature_code":"PPL",
    "gn:name":"Belenok",
    "gn:population":0,
    "gn:timezone":"Europe/Moscow",
    "iso:country":"RU",
    "name:nor_x_preferred":[
        "Belenok"
    ],
    "name:rus_x_preferred":[
        "\u0411\u0435\u043b\u0435\u043d\u043e\u043a"
    ],
    "wof:name":"Belenok",
    "wof:placetype":"locality"
},
  "geometry": {"coordinates":[30.65,58.85],"type":"Point"}
}