{
  "type": "Feature",
  "properties": {
    "gn:admin1_code":"77",
    "gn:asciiname":"Marinino",
    "gn:country_code":"RU",
    "gn:dem":145,
    "gn:feature_class":"P",
    "gn:feature_code":"PPL",
    "gn:name":"Marinino",
    "gn:population":0,
    "gn:timezone":"Europe/Moscow",
    "iso:country":"RU",
    "name:rus_x_preferred":[
        "\u041c\u0430\u0440\u0438\u043d\u0438\u043d\u043e"
    ],
    "wof:name":"Marinino",
    "wof:placetype":"locality"
},
  "geometry": {"coordinates":[37.0923,58.5172],"type":"Point"}
}