{
  "type": "Feature",
  "properties": {
    "gn:admin1_code":"67",
    "gn:asciiname":"Voroshilovo",
    "gn:country_code":"RU",
    "gn:dem":76,
    "gn:feature_class":"P",
    "gn:feature_code":"PPL",
    "gn:name":"Voroshilovo",
    "gn:population":0,
    "gn:timezone":"Europe/Saratov",
    "iso:country":"RU",
    "name:bak_x_preferred":[
        "\u0412\u043e\u0440\u043e\u0448\u0438\u043b\u043e\u0432"
    ],
    "name:che_x_preferred":[
        "\u0412\u043e\u0440\u043e\u0448\u0438\u043b\u043e\u0432\u043e"
    ],
    "name:eng_x_preferred":[
        "Voroshilovo"
    ],
    "name:hye_x_preferred":[
        "\u054e\u0578\u0580\u0578\u0577\u056b\u056c\u0578\u057e\u0578"
    ],
    "name:kaz_x_preferred":[
        "\u0412\u043e\u0440\u043e\u0448\u0438\u043b"
    ],
    "name:kir_x_preferred":[
        "\u0412\u043e\u0440\u043e\u0448\u0438\u043b"
    ],
    "name:nor_x_preferred":[
        "Vorosjilovo"
    ],
    "name:rus_x_preferred":[
        "\u0412\u043e\u0440\u043e\u0448\u0438\u043b\u043e\u0432\u043e"
    ],
    "name:tat_x_preferred":[
        "\u0412\u043e\u0440\u043e\u0448\u0438\u043b\u043e\u0432\u043e"
    ],
    "name:ukr_x_preferred":[
        "\u0412\u043e\u0440\u043e\u0448\u0438\u043b\u043e\u0432\u043e"
    ],
    "name:und_x_variant":[
        "Medemtal\u2019",
        "Voroshilevo"
    ],
    "wof:name":"Voroshilovo",
    "wof:placetype":"locality"
},
  "geometry": {"coordinates":[46.62887,51.10781],"type":"Point"}
}