{
  "type": "Feature",
  "properties": {
    "gn:admin1_code":"90",
    "gn:asciiname":"Polchino",
    "gn:country_code":"RU",
    "gn:dem":148,
    "gn:feature_class":"P",
    "gn:feature_code":"PPL",
    "gn:name":"Polchino",
    "gn:population":0,
    "gn:timezone":"Asia/Yekaterinburg",
    "iso:country":"RU",
    "name:rus_x_preferred":[
        "\u041f\u043e\u043b\u0447\u0438\u043d\u043e"
    ],
    "wof:name":"Polchino",
    "wof:placetype":"locality"
},
  "geometry": {"coordinates":[57.4359,57.4297],"type":"Point"}
}