{
  "type": "Feature",
  "properties": {
    "gn:admin1_code":"81",
    "gn:asciiname":"Lynevka",
    "gn:country_code":"RU",
    "gn:dem":215,
    "gn:feature_class":"P",
    "gn:feature_code":"PPL",
    "gn:name":"Lyn\u00ebvka",
    "gn:population":0,
    "gn:timezone":"Europe/Ulyanovsk",
    "iso:country":"RU",
    "name:rus_x_preferred":[
        "\u041b\u044b\u043d\u0451\u0432\u043a\u0430"
    ],
    "name:und_x_variant":[
        "Lyn\u00ebvka",
        "\u041b\u044b\u043d\u0451\u0432\u043a\u0430"
    ],
    "wof:name":"Lynevka",
    "wof:placetype":"locality"
},
  "geometry": {"coordinates":[47.33517,53.20096],"type":"Point"}
}