{
  "type": "Feature",
  "properties": {
    "gn:admin1_code":"37",
    "gn:asciiname":"Anchurikha",
    "gn:country_code":"RU",
    "gn:dem":125,
    "gn:feature_class":"P",
    "gn:feature_code":"PPL",
    "gn:name":"Anchurikha",
    "gn:population":0,
    "gn:timezone":"Europe/Moscow",
    "iso:country":"RU",
    "name:rus_x_preferred":[
        "\u0410\u043d\u0447\u0443\u0440\u0438\u0445\u0430"
    ],
    "name:und_x_variant":[
        "\u0410\u043d\u0447\u0443\u0440\u0438\u0445\u0430"
    ],
    "wof:name":"Anchurikha",
    "wof:placetype":"locality"
},
  "geometry": {"coordinates":[45.896,58.1424],"type":"Point"}
}