{
  "type": "Feature",
  "properties": {
    "gn:admin1_code":"69.0",
    "gn:asciiname":"Babenki",
    "gn:country_code":"RU",
    "gn:dem":219,
    "gn:feature_class":"P",
    "gn:feature_code":"PPL",
    "gn:name":"Babenki",
    "gn:population":0,
    "gn:timezone":"Europe/Moscow",
    "iso:country":"RU",
    "name:nor_x_preferred":[
        "Babenki"
    ],
    "name:rus_x_preferred":[
        "\u0411\u0430\u0431\u0435\u043d\u043a\u0438"
    ],
    "wof:name":"Babenki",
    "wof:placetype":"locality"
},
  "geometry": {"coordinates":[34.2821,54.88918],"type":"Point"}
}