{
  "type": "Feature",
  "properties": {
    "gn:admin1_code":"85",
    "gn:asciiname":"Bol'shoye Chertishchevo",
    "gn:country_code":"RU",
    "gn:dem":151,
    "gn:feature_class":"P",
    "gn:feature_code":"PPL",
    "gn:name":"Bol\u2019shoye Chertishchevo",
    "gn:population":0,
    "gn:timezone":"Europe/Moscow",
    "iso:country":"RU",
    "name:rus_x_preferred":[
        "\u0411\u043e\u043b\u044c\u0448\u043e\u0435 \u0427\u0435\u0440\u0442\u0438\u0449\u0435\u0432\u043e"
    ],
    "name:und_x_variant":[
        "Bol\u2019shoye Chertishchevo",
        "\u0411\u043e\u043b\u044c\u0448\u043e\u0435 \u0427\u0435\u0440\u0442\u0438\u0449\u0435\u0432\u043e"
    ],
    "wof:name":"Bol'shoye Chertishchevo",
    "wof:placetype":"locality"
},
  "geometry": {"coordinates":[39.54463,59.15368],"type":"Point"}
}