{
  "type": "Feature",
  "properties": {
    "gn:admin1_code":"6",
    "gn:asciiname":"Timoshchel'ye",
    "gn:country_code":"RU",
    "gn:dem":10,
    "gn:feature_class":"P",
    "gn:feature_code":"PPL",
    "gn:name":"Timoshchel\u2019ye",
    "gn:population":0,
    "gn:timezone":"Europe/Moscow",
    "iso:country":"RU",
    "name:rus_x_preferred":[
        "\u0422\u0438\u043c\u043e\u0449\u0435\u043b\u044c\u0435"
    ],
    "name:und_x_variant":[
        "Timoshchel\u2019skoye",
        "Timoshchel\u2019skaya",
        "Timoshchel\u2019ye"
    ],
    "wof:name":"Timoshchel'ye",
    "wof:placetype":"locality"
},
  "geometry": {"coordinates":[44.4294,65.6319],"type":"Point"}
}