{
  "type": "Feature",
  "properties": {
    "gn:admin1_code":"6",
    "gn:asciiname":"Larkino",
    "gn:country_code":"RU",
    "gn:dem":104,
    "gn:feature_class":"P",
    "gn:feature_code":"PPL",
    "gn:name":"Larkino",
    "gn:population":0,
    "gn:timezone":"Europe/Moscow",
    "iso:country":"RU",
    "name:eng_x_preferred":[
        "Larkino"
    ],
    "name:nor_x_preferred":[
        "Larkino"
    ],
    "name:rus_x_preferred":[
        "\u041b\u0430\u0440\u044c\u043a\u0438\u043d\u043e"
    ],
    "name:rus_x_variant":[
        "\u041b\u0430\u0440\u043a\u0438\u043d\u043e"
    ],
    "name:und_x_variant":[
        "Larkinskoe",
        "Larkina"
    ],
    "wof:name":"Larkino",
    "wof:placetype":"locality"
},
  "geometry": {"coordinates":[49.12276,64.64494999999999],"type":"Point"}
}