{
  "type": "Feature",
  "properties": {
    "gn:admin1_code":"37.0",
    "gn:asciiname":"Bokovo",
    "gn:country_code":"RU",
    "gn:dem":169,
    "gn:feature_class":"P",
    "gn:feature_code":"PPL",
    "gn:name":"Bokovo",
    "gn:population":0,
    "gn:timezone":"Europe/Moscow",
    "iso:country":"RU",
    "name:nor_x_preferred":[
        "Bokovo"
    ],
    "name:rus_x_preferred":[
        "\u0411\u043e\u043a\u043e\u0432\u043e"
    ],
    "name:und_x_variant":[
        "Bykova"
    ],
    "wof:name":"Bokovo",
    "wof:placetype":"locality"
},
  "geometry": {"coordinates":[41.71046,58.32568000000001],"type":"Point"}
}