{
  "type": "Feature",
  "properties": {
    "gn:admin1_code":"91",
    "gn:asciiname":"Sergeyeva",
    "gn:cc2":"RU",
    "gn:country_code":"RU",
    "gn:dem":54,
    "gn:feature_class":"P",
    "gn:feature_code":"PPL",
    "gn:name":"Sergeyeva",
    "gn:population":0,
    "gn:timezone":"Asia/Krasnoyarsk",
    "iso:country":"RU",
    "name:eng_x_preferred":[
        "Sergeyeva"
    ],
    "name:nor_x_preferred":[
        "Sergejevo"
    ],
    "name:rus_x_preferred":[
        "\u0421\u0435\u0440\u0433\u0435\u0435\u0432\u043e"
    ],
    "name:rus_x_variant":[
        "\u0421\u0435\u0440\u0433\u0435\u0435\u0432\u0430"
    ],
    "name:und_x_variant":[
        "Sergeyevo",
        "Sergeyevka",
        "Sergeyeva"
    ],
    "wof:name":"Sergeyeva",
    "wof:placetype":"locality"
},
  "geometry": {"coordinates":[90.83360999999999,59.65306],"type":"Point"}
}