{
  "type": "Feature",
  "properties": {
    "gn:admin1_code":"20",
    "gn:asciiname":"Tal'yany",
    "gn:country_code":"RU",
    "gn:dem":514,
    "gn:feature_class":"P",
    "gn:feature_code":"PPL",
    "gn:name":"Tal\u2019yany",
    "gn:population":0,
    "gn:timezone":"Asia/Irkutsk",
    "iso:country":"RU",
    "name:eng_x_preferred":[
        "Tal'yany"
    ],
    "name:nor_x_preferred":[
        "Taljany"
    ],
    "name:rus_x_preferred":[
        "\u0422\u0430\u043b\u044c\u044f\u043d\u044b"
    ],
    "name:und_x_variant":[
        "Tal\u2019yan",
        "Tal\u2019yany"
    ],
    "wof:name":"Tal'yany",
    "wof:placetype":"locality"
},
  "geometry": {"coordinates":[103.26336000000001,52.19558],"type":"Point"}
}