{
  "type": "Feature",
  "properties": {
    "gn:admin1_code":"90.0",
    "gn:asciiname":"Selyanki",
    "gn:country_code":"RU",
    "gn:dem":159,
    "gn:feature_class":"P",
    "gn:feature_code":"PPL",
    "gn:name":"Selyanki",
    "gn:population":0,
    "gn:timezone":"Asia/Yekaterinburg",
    "iso:country":"RU",
    "name:rus_x_preferred":[
        "\u0421\u0435\u043b\u044f\u043d\u043a\u0438"
    ],
    "wof:name":"Selyanki",
    "wof:placetype":"locality"
},
  "geometry": {"coordinates":[55.7439,58.2793],"type":"Point"}
}