{
  "type": "Feature",
  "properties": {
    "gn:admin1_code":"16",
    "gn:asciiname":"Novorodionovka",
    "gn:country_code":"RU",
    "gn:dem":155,
    "gn:feature_class":"P",
    "gn:feature_code":"PPL",
    "gn:name":"Novorodionovka",
    "gn:population":0,
    "gn:timezone":"Europe/Moscow",
    "iso:country":"RU",
    "name:rus_x_preferred":[
        "\u041d\u043e\u0432\u043e\u0440\u043e\u0434\u0438\u043e\u043d\u043e\u0432\u043a\u0430"
    ],
    "wof:name":"Novorodionovka",
    "wof:placetype":"locality"
},
  "geometry": {"coordinates":[48.2064,55.8684],"type":"Point"}
}