{
  "type": "Feature",
  "properties": {
    "gn:admin1_code":"77",
    "gn:asciiname":"Bratkovo",
    "gn:country_code":"RU",
    "gn:dem":148,
    "gn:feature_class":"P",
    "gn:feature_code":"PPL",
    "gn:name":"Bratkovo",
    "gn:population":0,
    "gn:timezone":"Europe/Moscow",
    "iso:country":"RU",
    "name:rus_x_preferred":[
        "\u0411\u0440\u0430\u0442\u043a\u043e\u0432\u043e"
    ],
    "wof:name":"Bratkovo",
    "wof:placetype":"locality"
},
  "geometry": {"coordinates":[38.223,57.3253],"type":"Point"}
}