{
  "type": "Feature",
  "properties": {
    "gn:admin1_code":"37",
    "gn:asciiname":"Lebedishino",
    "gn:country_code":"RU",
    "gn:dem":142,
    "gn:feature_class":"P",
    "gn:feature_code":"PPL",
    "gn:name":"Lebedishino",
    "gn:population":0,
    "gn:timezone":"Europe/Moscow",
    "iso:country":"RU",
    "name:rus_x_preferred":[
        "\u041b\u0435\u0431\u0435\u0434\u0438\u0448\u0438\u043d\u043e"
    ],
    "wof:name":"Lebedishino",
    "wof:placetype":"locality"
},
  "geometry": {"coordinates":[46.2636,58.7831],"type":"Point"}
}