{
  "type": "Feature",
  "properties": {
    "gn:admin1_code":"85",
    "gn:asciiname":"Grishkino",
    "gn:country_code":"RU",
    "gn:dem":117,
    "gn:feature_class":"P",
    "gn:feature_code":"PPL",
    "gn:name":"Grishkino",
    "gn:population":0,
    "gn:timezone":"Europe/Moscow",
    "iso:country":"RU",
    "name:che_x_preferred":[
        "\u0413\u0440\u0438\u0448\u043a\u0438\u043d\u043e"
    ],
    "name:eng_x_preferred":[
        "Grishkino"
    ],
    "name:nor_x_preferred":[
        "Grisjkino"
    ],
    "name:rus_x_preferred":[
        "\u0413\u0440\u0438\u0448\u043a\u0438\u043d\u043e"
    ],
    "wof:name":"Grishkino",
    "wof:placetype":"locality"
},
  "geometry": {"coordinates":[37.1293,58.9606],"type":"Point"}
}