{
  "type": "Feature",
  "properties": {
    "gn:admin1_code":"85",
    "gn:asciiname":"Dernovo",
    "gn:country_code":"RU",
    "gn:dem":87,
    "gn:feature_class":"P",
    "gn:feature_code":"PPL",
    "gn:name":"Dernovo",
    "gn:population":0,
    "gn:timezone":"Europe/Moscow",
    "iso:country":"RU",
    "name:rus_x_preferred":[
        "\u0414\u0435\u0440\u043d\u043e\u0432\u043e"
    ],
    "name:und_x_variant":[
        "\u0414\u0435\u0440\u043d\u043e\u0432\u043e"
    ],
    "wof:name":"Dernovo",
    "wof:placetype":"locality"
},
  "geometry": {"coordinates":[46.6361,60.466],"type":"Point"}
}