{
  "type": "Feature",
  "properties": {
    "gn:admin1_code":"52",
    "gn:asciiname":"Il'ichevo",
    "gn:country_code":"RU",
    "gn:dem":62,
    "gn:feature_class":"P",
    "gn:feature_code":"PPL",
    "gn:name":"Il\u2019ich\u00ebvo",
    "gn:population":0,
    "gn:timezone":"Europe/Moscow",
    "iso:country":"RU",
    "name:rus_x_preferred":[
        "\u0418\u043b\u044c\u0438\u0447\u0451\u0432\u043e"
    ],
    "name:und_x_variant":[
        "Nizhneye Zakhomut\u2019ye",
        "Novoye Zakhomut\u2019ye",
        "Il\u2019ich\u00ebvo",
        "\u0418\u043b\u044c\u0438\u0447\u0451\u0432\u043e"
    ],
    "wof:name":"Il'ichevo",
    "wof:placetype":"locality"
},
  "geometry": {"coordinates":[32.56843,58.72454000000001],"type":"Point"}
}