{
  "type": "Feature",
  "properties": {
    "gn:admin1_code":"8",
    "gn:asciiname":"Ismagilovo",
    "gn:country_code":"RU",
    "gn:dem":161,
    "gn:feature_class":"P",
    "gn:feature_code":"PPL",
    "gn:name":"Ismagilovo",
    "gn:population":0,
    "gn:timezone":"Asia/Yekaterinburg",
    "iso:country":"RU",
    "name:rus_x_preferred":[
        "\u0418\u0441\u043c\u0430\u0433\u0438\u043b\u043e\u0432\u043e"
    ],
    "name:und_x_variant":[
        "Ismaylova",
        "Ismagilovo",
        "\u0418\u0441\u043c\u0430\u0433\u0438\u043b\u043e\u0432\u043e"
    ],
    "wof:name":"Ismagilovo",
    "wof:placetype":"locality"
},
  "geometry": {"coordinates":[55.95714,54.16831],"type":"Point"}
}