{
  "type": "Feature",
  "properties": {
    "gn:admin1_code":"76",
    "gn:asciiname":"Gretsovo",
    "gn:country_code":"RU",
    "gn:dem":213,
    "gn:feature_class":"P",
    "gn:feature_code":"PPL",
    "gn:name":"Gretsovo",
    "gn:population":0,
    "gn:timezone":"Europe/Moscow",
    "iso:country":"RU",
    "name:rus_x_preferred":[
        "\u0413\u0440\u0435\u0446\u043e\u0432\u043e"
    ],
    "name:und_x_variant":[
        "\u0413\u0440\u0435\u0446\u043e\u0432\u043e"
    ],
    "wof:name":"Gretsovo",
    "wof:placetype":"locality"
},
  "geometry": {"coordinates":[37.97313,54.24763000000001],"type":"Point"}
}