{
  "type": "Feature",
  "properties": {
    "gn:admin1_code":"41",
    "gn:asciiname":"Ol'khovka",
    "gn:country_code":"RU",
    "gn:dem":224,
    "gn:feature_class":"P",
    "gn:feature_code":"PPL",
    "gn:name":"Ol\u2019khovka",
    "gn:population":0,
    "gn:timezone":"Europe/Moscow",
    "iso:country":"RU",
    "name:rus_x_preferred":[
        "\u041e\u043b\u044c\u0445\u043e\u0432\u043a\u0430"
    ],
    "name:und_x_variant":[
        "Ol\u2019khovka"
    ],
    "wof:name":"Ol'khovka",
    "wof:placetype":"locality"
},
  "geometry": {"coordinates":[35.2463,52.3719],"type":"Point"}
}