{
  "type": "Feature",
  "properties": {
    "gn:admin1_code":"73",
    "gn:asciiname":"Staroye Al'met'yevo",
    "gn:country_code":"RU",
    "gn:dem":102,
    "gn:feature_class":"P",
    "gn:feature_code":"PPL",
    "gn:name":"Staroye Al\u2019met\u2019yevo",
    "gn:population":0,
    "gn:timezone":"Europe/Moscow",
    "iso:country":"RU",
    "name:rus_x_preferred":[
        "\u0421\u0442\u0430\u0440\u043e\u0435 \u0410\u043b\u044c\u043c\u0435\u0442\u044c\u0435\u0432\u043e"
    ],
    "name:und_x_variant":[
        "Staroye Al\u2019met\u2019yevo",
        "\u0421\u0442\u0430\u0440\u043e\u0435 \u0410\u043b\u044c\u043c\u0435\u0442\u044c\u0435\u0432\u043e"
    ],
    "wof:name":"Staroye Al'met'yevo",
    "wof:placetype":"locality"
},
  "geometry": {"coordinates":[53.7748,55.3707],"type":"Point"}
}