{
  "type": "Feature",
  "properties": {
    "gn:admin1_code":"88",
    "gn:asciiname":"Lyakhovo",
    "gn:country_code":"RU",
    "gn:dem":145,
    "gn:feature_class":"P",
    "gn:feature_code":"PPL",
    "gn:name":"Lyakhovo",
    "gn:population":0,
    "gn:timezone":"Europe/Moscow",
    "iso:country":"RU",
    "name:bel_x_preferred":[
        "\u041b\u044f\u0445\u0430\u0432\u0430"
    ],
    "name:bul_x_preferred":[
        "\u041b\u044f\u0445\u043e\u0432\u043e"
    ],
    "name:fra_x_preferred":[
        "Lyakhovo"
    ],
    "name:rus_x_preferred":[
        "\u041b\u044f\u0445\u043e\u0432\u043e"
    ],
    "name:ukr_x_preferred":[
        "\u041b\u044f\u0445\u043e\u0432\u043e"
    ],
    "name:und_x_variant":[
        "\u041b\u044f\u0445\u043e\u0432\u043e"
    ],
    "wof:name":"Lyakhovo",
    "wof:placetype":"locality"
},
  "geometry": {"coordinates":[38.919,57.1935],"type":"Point"}
}