{
  "type": "Feature",
  "properties": {
    "gn:admin1_code":"85",
    "gn:asciiname":"Tsepelevo",
    "gn:country_code":"RU",
    "gn:dem":165,
    "gn:feature_class":"P",
    "gn:feature_code":"PPL",
    "gn:name":"Tsepel\u00ebvo",
    "gn:population":0,
    "gn:timezone":"Europe/Moscow",
    "iso:country":"RU",
    "name:und_x_variant":[
        "Tsypel\u00ebvo",
        "Tsepel\u00ebvo"
    ],
    "wof:name":"Tsepelevo",
    "wof:placetype":"locality"
},
  "geometry": {"coordinates":[40.77364,58.75288000000001],"type":"Point"}
}