{
  "type": "Feature",
  "properties": {
    "gn:admin1_code":"31",
    "gn:asciiname":"Kalinino",
    "gn:cc2":"RU",
    "gn:country_code":"RU",
    "gn:dem":247,
    "gn:feature_class":"P",
    "gn:feature_code":"PPL",
    "gn:name":"Kalinino",
    "gn:population":0,
    "gn:timezone":"Asia/Krasnoyarsk",
    "iso:country":"RU",
    "name:eng_x_preferred":[
        "Kalinino"
    ],
    "name:nor_x_preferred":[
        "Kalinino"
    ],
    "name:rus_x_preferred":[
        "\u041a\u0430\u043b\u0438\u043d\u0438\u043d\u043e"
    ],
    "name:und_x_variant":[
        "Ust\u2019-Tasheba",
        "Tasheba",
        "\u041a\u0430\u043b\u0438\u043d\u0438\u043d\u043e",
        "Kalinino"
    ],
    "wof:name":"Kalinino",
    "wof:placetype":"locality"
},
  "geometry": {"coordinates":[91.3875,53.73833000000001],"type":"Point"}
}