{
  "type": "Feature",
  "properties": {
    "gn:admin1_code":"51",
    "gn:asciiname":"Vishnevaya",
    "gn:country_code":"RU",
    "gn:dem":175,
    "gn:feature_class":"P",
    "gn:feature_code":"PPL",
    "gn:name":"Vishn\u00ebvaya",
    "gn:population":0,
    "gn:timezone":"Europe/Moscow",
    "iso:country":"RU",
    "name:und_x_variant":[
        "Ter-Klopovka",
        "Vishn\u00ebvaya"
    ],
    "wof:name":"Vishnevaya",
    "wof:placetype":"locality"
},
  "geometry": {"coordinates":[43.09116,55.1532],"type":"Point"}
}