{
  "type": "Feature",
  "properties": {
    "gn:admin1_code":"33",
    "gn:asciiname":"Rogozino",
    "gn:country_code":"RU",
    "gn:dem":218,
    "gn:feature_class":"P",
    "gn:feature_code":"PPL",
    "gn:name":"Rogozino",
    "gn:population":0,
    "gn:timezone":"Europe/Kirov",
    "iso:country":"RU",
    "name:fra_x_preferred":[
        "Rogozino"
    ],
    "name:pol_x_preferred":[
        "Rogozino"
    ],
    "name:rus_x_preferred":[
        "\u0420\u043e\u0433\u043e\u0437\u0438\u043d\u043e"
    ],
    "name:ukr_x_preferred":[
        "\u0420\u043e\u0491\u043e\u0437\u0456\u043d\u043e"
    ],
    "name:und_x_variant":[
        "\u0420\u043e\u0433\u043e\u0437\u0438\u043d\u043e"
    ],
    "wof:name":"Rogozino",
    "wof:placetype":"locality"
},
  "geometry": {"coordinates":[48.67274000000001,59.58158],"type":"Point"}
}