{
  "type": "Feature",
  "properties": {
    "gn:admin1_code":"38.0",
    "gn:asciiname":"Sheychenko",
    "gn:country_code":"RU",
    "gn:dem":493,
    "gn:feature_class":"P",
    "gn:feature_code":"PPL",
    "gn:name":"Sheychenko",
    "gn:population":0,
    "gn:timezone":"Europe/Moscow",
    "iso:country":"RU",
    "wof:name":"Sheychenko",
    "wof:placetype":"locality"
},
  "geometry": {"coordinates":[41.58333,44.28583],"type":"Point"}
}