{
  "type": "Feature",
  "properties": {
    "gn:admin1_code":"77",
    "gn:asciiname":"Peretrusovo",
    "gn:country_code":"RU",
    "gn:dem":127,
    "gn:feature_class":"P",
    "gn:feature_code":"PPL",
    "gn:name":"Peretrusovo",
    "gn:population":0,
    "gn:timezone":"Europe/Moscow",
    "iso:country":"RU",
    "name:eng_x_preferred":[
        "Peretrusovo"
    ],
    "name:nor_x_preferred":[
        "Peretrusovo"
    ],
    "name:rus_x_preferred":[
        "\u041f\u0435\u0440\u0435\u0442\u0440\u0443\u0441\u043e\u0432\u043e"
    ],
    "wof:name":"Peretrusovo",
    "wof:placetype":"locality"
},
  "geometry": {"coordinates":[36.88333,56.85],"type":"Point"}
}