{
  "type": "Feature",
  "properties": {
    "gn:admin1_code":"46",
    "gn:asciiname":"Turchaninovskiy",
    "gn:country_code":"RU",
    "gn:dem":239,
    "gn:feature_class":"P",
    "gn:feature_code":"PPL",
    "gn:name":"Turchaninovskiy",
    "gn:population":0,
    "gn:timezone":"Europe/Moscow",
    "iso:country":"RU",
    "name:rus_x_preferred":[
        "\u0422\u0443\u0440\u0447\u0430\u043d\u0438\u043d\u043e\u0432\u0441\u043a\u0438\u0439"
    ],
    "name:und_x_variant":[
        "\u0422\u0443\u0440\u0447\u0430\u043d\u0438\u043d\u043e\u0432\u0441\u043a\u0438\u0439"
    ],
    "wof:name":"Turchaninovskiy",
    "wof:placetype":"locality"
},
  "geometry": {"coordinates":[44.082,53.7356],"type":"Point"}
}