{
  "type": "Feature",
  "properties": {
    "gn:admin1_code":"25.0",
    "gn:admin2_code":"527404",
    "gn:asciiname":"Beklemishchevo",
    "gn:country_code":"RU",
    "gn:dem":181,
    "gn:feature_class":"P",
    "gn:feature_code":"PPL",
    "gn:name":"Beklemishchevo",
    "gn:population":0,
    "gn:timezone":"Europe/Moscow",
    "iso:country":"RU",
    "name:eng_x_preferred":[
        "Beklemishchevo"
    ],
    "name:nor_x_preferred":[
        "Beklemisjtsjevo"
    ],
    "name:rus_x_preferred":[
        "\u0411\u0435\u043a\u043b\u0435\u043c\u0438\u0449\u0435\u0432\u043e"
    ],
    "name:und_x_variant":[
        "Biklemishevo",
        "Biklimishevo",
        "\u0411\u0435\u043a\u043b\u0435\u043c\u0438\u0449\u0435\u0432\u043e",
        "Beklemishchevo"
    ],
    "wof:name":"Beklemishchevo",
    "wof:placetype":"locality"
},
  "geometry": {"coordinates":[35.22639,54.49056],"type":"Point"}
}