{
  "type": "Feature",
  "properties": {
    "gn:admin1_code":"70",
    "gn:asciiname":"Plavnenskiy",
    "gn:country_code":"RU",
    "gn:dem":10,
    "gn:feature_class":"P",
    "gn:feature_code":"PPL",
    "gn:name":"Plavnenskiy",
    "gn:population":0,
    "gn:timezone":"Europe/Moscow",
    "iso:country":"RU",
    "name:rus_x_preferred":[
        "\u041f\u043b\u0430\u0432\u043d\u0435\u043d\u0441\u043a\u0438\u0439"
    ],
    "wof:name":"Plavnenskiy",
    "wof:placetype":"locality"
},
  "geometry": {"coordinates":[45.46417,45.08861],"type":"Point"}
}