{
  "type": "Feature",
  "properties": {
    "gn:admin1_code":"63",
    "gn:asciiname":"Metis",
    "gn:country_code":"RU",
    "gn:dem":210,
    "gn:feature_class":"P",
    "gn:feature_code":"PPL",
    "gn:name":"Metis",
    "gn:population":0,
    "gn:timezone":"Asia/Vladivostok",
    "iso:country":"RU",
    "name:rus_x_preferred":[
        "\u041c\u0435\u0442\u0438\u0441"
    ],
    "name:und_x_variant":[
        "\u041c\u0435\u0442\u0438\u0441"
    ],
    "wof:name":"Metis",
    "wof:placetype":"locality"
},
  "geometry": {"coordinates":[136.45141000000001,67.48357],"type":"Point"}
}