{
  "type": "Feature",
  "properties": {
    "gn:admin1_code":"63",
    "gn:asciiname":"Metis",
    "gn:country_code":"RU",
    "gn:dem":210,
    "gn:feature_class":"P",
    "gn:feature_code":"PPL",
    "gn:name":"Metis",
    "gn:population":0,
    "gn:timezone":"Asia/Vladivostok",
    "iso:country":"RU",
    "name:als_x_preferred":[
        "Metis"
    ],
    "name:bel_x_preferred":[
        "\u041c\u0435\u0442\u044b\u0434\u0430"
    ],
    "name:bul_x_preferred":[
        "\u041c\u0435\u0442\u0438\u0441"
    ],
    "name:cat_x_preferred":[
        "Metis"
    ],
    "name:ces_x_preferred":[
        "Metis"
    ],
    "name:deu_x_preferred":[
        "Metis"
    ],
    "name:ell_x_preferred":[
        "\u039c\u03ae\u03c4\u03b9\u03c2"
    ],
    "name:epo_x_preferred":[
        "Metiso"
    ],
    "name:fas_x_preferred":[
        "\u0645\u062a\u06cc\u0633"
    ],
    "name:fin_x_preferred":[
        "Metis"
    ],
    "name:fra_x_preferred":[
        "M\u00e9tis"
    ],
    "name:glg_x_preferred":[
        "Metis"
    ],
    "name:heb_x_preferred":[
        "\u05de\u05d8\u05d9\u05e1"
    ],
    "name:hrv_x_preferred":[
        "Metis"
    ],
    "name:hun_x_preferred":[
        "M\u00e9tisz"
    ],
    "name:hye_x_preferred":[
        "\u0544\u0565\u057f\u056b\u057d"
    ],
    "name:ita_x_preferred":[
        "Metis"
    ],
    "name:jpn_x_preferred":[
        "\u30e1\u30c6\u30a3\u30b9"
    ],
    "name:kor_x_preferred":[
        "\uba54\ud2f0\uc2a4"
    ],
    "name:lat_x_preferred":[
        "Metis"
    ],
    "name:ltz_x_preferred":[
        "Metis"
    ],
    "name:nds_x_preferred":[
        "Metis"
    ],
    "name:nld_x_preferred":[
        "Metis"
    ],
    "name:pol_x_preferred":[
        "Metis"
    ],
    "name:por_x_preferred":[
        "M\u00e9tis"
    ],
    "name:ron_x_preferred":[
        "Metis"
    ],
    "name:rus_x_preferred":[
        "\u041c\u0435\u0442\u0438\u0441"
    ],
    "name:slk_x_preferred":[
        "Metis"
    ],
    "name:spa_x_preferred":[
        "Metis"
    ],
    "name:srp_x_preferred":[
        "\u041c\u0435\u0442\u0438\u0441"
    ],
    "name:swe_x_preferred":[
        "Metis"
    ],
    "name:tgl_x_preferred":[
        "Metis"
    ],
    "name:tur_x_preferred":[
        "Metis"
    ],
    "name:ukr_x_preferred":[
        "\u041c\u0435\u0442\u0438\u0441"
    ],
    "wof:name":"Metis",
    "wof:placetype":"locality"
},
  "geometry": {"coordinates":[136.45141000000001,67.48357],"type":"Point"}
}