{
  "type": "Feature",
  "properties": {
    "gn:admin1_code":"90.0",
    "gn:asciiname":"Verkhniye Novinki",
    "gn:country_code":"RU",
    "gn:dem":121,
    "gn:feature_class":"P",
    "gn:feature_code":"PPL",
    "gn:name":"Verkhniye Novinki",
    "gn:population":0,
    "gn:timezone":"Asia/Yekaterinburg",
    "iso:country":"RU",
    "name:rus_x_preferred":[
        "\u0412\u0435\u0440\u0445\u043d\u0438\u0435 \u041d\u043e\u0432\u0438\u043d\u043a\u0438"
    ],
    "wof:name":"Verkhniye Novinki",
    "wof:placetype":"locality"
},
  "geometry": {"coordinates":[56.6274,59.5342],"type":"Point"}
}