{
  "type": "Feature",
  "properties": {
    "gn:admin1_code":"51",
    "gn:asciiname":"Pushkino",
    "gn:country_code":"RU",
    "gn:dem":147,
    "gn:feature_class":"P",
    "gn:feature_code":"PPL",
    "gn:name":"Pushkino",
    "gn:population":0,
    "gn:timezone":"Europe/Moscow",
    "iso:country":"RU",
    "name:rus_x_preferred":[
        "\u041f\u0443\u0448\u043a\u0438\u043d\u043e"
    ],
    "name:und_x_variant":[
        "\u041f\u0443\u0448\u043a\u0438\u043d\u043e"
    ],
    "wof:name":"Pushkino",
    "wof:placetype":"locality"
},
  "geometry": {"coordinates":[45.088,57.1372],"type":"Point"}
}