{
  "type": "Feature",
  "properties": {
    "gn:admin1_code":"75",
    "gn:asciiname":"Voronova",
    "gn:country_code":"RU",
    "gn:dem":126,
    "gn:feature_class":"P",
    "gn:feature_code":"PPL",
    "gn:name":"Voronova",
    "gn:population":0,
    "gn:timezone":"Asia/Tomsk",
    "iso:country":"RU",
    "name:rus_x_preferred":[
        "\u0412\u043e\u0440\u043e\u043d\u043e\u0432\u0430"
    ],
    "wof:name":"Voronova",
    "wof:placetype":"locality"
},
  "geometry": {"coordinates":[85.21710999999998,56.34033],"type":"Point"}
}