{
  "type": "Feature",
  "properties": {
    "gn:admin1_code":"85",
    "gn:asciiname":"Rovdino",
    "gn:country_code":"RU",
    "gn:dem":83,
    "gn:feature_class":"P",
    "gn:feature_code":"PPL",
    "gn:name":"Rovdino",
    "gn:population":0,
    "gn:timezone":"Europe/Moscow",
    "iso:country":"RU",
    "name:rus_x_preferred":[
        "\u0420\u043e\u0432\u0434\u0438\u043d\u043e"
    ],
    "name:und_x_variant":[
        "\u0420\u043e\u0432\u0434\u0438\u043d\u043e"
    ],
    "wof:name":"Rovdino",
    "wof:placetype":"locality"
},
  "geometry": {"coordinates":[45.80211,60.70229000000001],"type":"Point"}
}