{
  "type": "Feature",
  "properties": {
    "gn:admin1_code":"54",
    "gn:asciiname":"Agapovka",
    "gn:country_code":"RU",
    "gn:dem":117,
    "gn:feature_class":"P",
    "gn:feature_code":"PPL",
    "gn:name":"Agapovka",
    "gn:population":0,
    "gn:timezone":"Asia/Omsk",
    "iso:country":"RU",
    "name:nor_x_preferred":[
        "Agapovka"
    ],
    "name:rus_x_preferred":[
        "\u0410\u0433\u0430\u043f\u043e\u0432\u043a\u0430"
    ],
    "wof:name":"Agapovka",
    "wof:placetype":"locality"
},
  "geometry": {"coordinates":[71.70756,54.9971],"type":"Point"}
}