{
  "type": "Feature",
  "properties": {
    "gn:admin1_code":"72.0",
    "gn:asciiname":"Bol'shaya Alekseyevka",
    "gn:country_code":"RU",
    "gn:dem":136,
    "gn:feature_class":"P",
    "gn:feature_code":"PPL",
    "gn:name":"Bol\u2019shaya Alekseyevka",
    "gn:population":0,
    "gn:timezone":"Europe/Moscow",
    "iso:country":"RU",
    "name:rus_x_preferred":[
        "Bol\u2019shaya Alekseyevka"
    ],
    "name:rus_x_variant":[
        "\u0411\u043e\u043b\u044c\u0448\u0430\u044f \u0410\u043b\u0435\u043a\u0441\u0435\u0435\u0432\u043a\u0430"
    ],
    "name:und_x_variant":[
        "Bol\u2019shaya Alekseyevka",
        "\u0411\u043e\u043b\u044c\u0448\u0430\u044f \u0410\u043b\u0435\u043a\u0441\u0435\u0435\u0432\u043a\u0430"
    ],
    "wof:name":"Bol'shaya Alekseyevka",
    "wof:placetype":"locality"
},
  "geometry": {"coordinates":[40.0078,52.6095],"type":"Point"}
}