{
  "type": "Feature",
  "properties": {
    "gn:admin1_code":"86",
    "gn:asciiname":"Gorokhovka",
    "gn:country_code":"RU",
    "gn:dem":114,
    "gn:feature_class":"P",
    "gn:feature_code":"PPL",
    "gn:name":"Gorokhovka",
    "gn:population":0,
    "gn:timezone":"Europe/Moscow",
    "iso:country":"RU",
    "name:rus_x_preferred":[
        "\u0413\u043e\u0440\u043e\u0445\u043e\u0432\u043a\u0430"
    ],
    "name:und_x_variant":[
        "\u0413\u043e\u0440\u043e\u0445\u043e\u0432\u043a\u0430"
    ],
    "wof:name":"Gorokhovka",
    "wof:placetype":"locality"
},
  "geometry": {"coordinates":[40.4767,51.8244],"type":"Point"}
}