{
  "type": "Feature",
  "properties": {
    "gn:admin1_code":"90.0",
    "gn:asciiname":"Tikhonyata",
    "gn:country_code":"RU",
    "gn:dem":143,
    "gn:feature_class":"P",
    "gn:feature_code":"PPL",
    "gn:name":"Tikhonyata",
    "gn:population":0,
    "gn:timezone":"Asia/Yekaterinburg",
    "iso:country":"RU",
    "name:che_x_preferred":[
        "\u0422\u0438\u0445\u043e\u043d\u044f\u0442\u0430"
    ],
    "name:rus_x_preferred":[
        "\u0422\u0438\u0445\u043e\u043d\u044f\u0442\u0430"
    ],
    "wof:name":"Tikhonyata",
    "wof:placetype":"locality"
},
  "geometry": {"coordinates":[54.815,58.7421],"type":"Point"}
}