{
  "type": "Feature",
  "properties": {
    "gn:admin1_code":"0",
    "gn:asciiname":"Imeni Stalina",
    "gn:country_code":"RU",
    "gn:dem":233,
    "gn:feature_class":"P",
    "gn:feature_code":"PPL",
    "gn:name":"Imeni Stalina",
    "gn:population":0,
    "gn:timezone":"Europe/Moscow",
    "iso:country":"RU",
    "name:rus_x_preferred":[
        "\u0418\u043c\u0435\u043d\u0438 \u0421\u0442\u0430\u043b\u0438\u043d\u0430"
    ],
    "wof:name":"Imeni Stalina",
    "wof:placetype":"locality"
},
  "geometry": {"coordinates":[34.91,52.78083],"type":"Point"}
}