{
  "type": "Feature",
  "properties": {
    "gn:country":"RU",
    "gn:fcode":"PPL",
    "gn:pop":0,
    "iso:country":"RU",
    "name:rus_x_preferred":[
        "\u041a\u0438\u0441\u0435\u043b\u0451\u0432\u043e"
    ],
    "name:unk_x_variant":[
        "Kisel\u00ebvo"
    ],
    "qs:name":"Kiselevo",
    "qs:name_adm0":"Russia",
    "qs:name_adm1":"Moscow Oblast",
    "qs:photos_9k":1,
    "qs:photos_9r":1,
    "qs:photos_all":22,
    "qs:photos_sr":0,
    "qs:placetype":"Town",
    "qs:pop_sr":"0",
    "wd:wordcount":35,
    "wof:name":"Kiselevo",
    "wof:placetype":"locality",
    "wof:population":0
},
  "geometry": {"coordinates":[37.33933,55.34827],"type":"Point"}
}