{
  "type": "Feature",
  "properties": {
    "gn:admin1_code":"69",
    "gn:asciiname":"Ozhogino",
    "gn:country_code":"RU",
    "gn:dem":195,
    "gn:feature_class":"P",
    "gn:feature_code":"PPL",
    "gn:name":"Ozhogino",
    "gn:population":0,
    "gn:timezone":"Europe/Moscow",
    "iso:country":"RU",
    "name:rus_x_preferred":[
        "\u041e\u0436\u043e\u0433\u0438\u043d\u043e"
    ],
    "name:und_x_variant":[
        "\u041e\u0436\u043e\u0433\u0438\u043d\u043e"
    ],
    "wof:name":"Ozhogino",
    "wof:placetype":"locality"
},
  "geometry": {"coordinates":[31.41542,55.38458000000001],"type":"Point"}
}