{
  "type": "Feature",
  "properties": {
    "gn:admin1_code":"21",
    "gn:asciiname":"Semeykino",
    "gn:country_code":"RU",
    "gn:dem":94,
    "gn:feature_class":"P",
    "gn:feature_code":"PPL",
    "gn:name":"Semeykino",
    "gn:population":0,
    "gn:timezone":"Europe/Moscow",
    "iso:country":"RU",
    "name:eng_x_preferred":[
        "Semeykino"
    ],
    "name:nor_x_preferred":[
        "Semejkino"
    ],
    "name:rus_x_preferred":[
        "\u0421\u0435\u043c\u0435\u0439\u043a\u0438\u043d\u043e"
    ],
    "name:und_x_variant":[
        "Semekino",
        "\u0421\u0435\u043c\u0435\u0439\u043a\u0438\u043d\u043e",
        "Semeykino"
    ],
    "wof:name":"Semeykino",
    "wof:placetype":"locality"
},
  "geometry": {"coordinates":[41.34193,56.80756],"type":"Point"}
}