{
  "type": "Feature",
  "properties": {
    "gn:admin1_code":"69",
    "gn:asciiname":"Kurovshchina",
    "gn:country_code":"RU",
    "gn:dem":185,
    "gn:feature_class":"P",
    "gn:feature_code":"PPL",
    "gn:name":"Kurovshchina",
    "gn:population":0,
    "gn:timezone":"Europe/Moscow",
    "iso:country":"RU",
    "name:rus_x_preferred":[
        "\u041a\u0443\u0440\u043e\u0432\u0449\u0438\u043d\u0430"
    ],
    "name:und_x_variant":[
        "\u041a\u0443\u0440\u043e\u0432\u0449\u0438\u043d\u0430"
    ],
    "wof:name":"Kurovshchina",
    "wof:placetype":"locality"
},
  "geometry": {"coordinates":[31.50781,54.20528],"type":"Point"}
}