{
  "type": "Feature",
  "properties": {
    "gn:admin1_code":"34.0",
    "gn:asciiname":"Chulovo",
    "gn:country_code":"RU",
    "gn:dem":146,
    "gn:feature_class":"P",
    "gn:feature_code":"PPL",
    "gn:name":"Chulovo",
    "gn:population":0,
    "gn:timezone":"Europe/Moscow",
    "iso:country":"RU",
    "name:rus_x_preferred":[
        "\u0427\u0443\u043b\u043e\u0432\u043e"
    ],
    "name:und_x_variant":[
        "\u0427\u0443\u043b\u043e\u0432\u043e"
    ],
    "wof:name":"Chulovo",
    "wof:placetype":"locality"
},
  "geometry": {"coordinates":[49.13333,60.01667],"type":"Point"}
}