{
  "type": "Feature",
  "properties": {
    "gn:country":"RU",
    "gn:fcode":"PPL",
    "gn:population":0,
    "iso:country":"RU",
    "name:rus_x_preferred":[
        "\u041c\u043e\u0442\u043e\u0432\u0438\u043b\u043e\u0432\u043e"
    ],
    "qs:name":"Motovilovo",
    "qs:name_adm0":"Russia",
    "qs:name_adm1":"Ryazan Oblast",
    "qs:photos_9r":0,
    "qs:photos_sr":0,
    "qs:placetype":"Town",
    "qs:pop_sr":"0",
    "wof:name":"Motovilovo",
    "wof:placetype":"locality",
    "wof:population":0
},
  "geometry": {"coordinates":[39.0278,54.4869],"type":"Point"}
}