{
  "type": "Feature",
  "properties": {
    "gn:admin1_code":"56",
    "gn:asciiname":"Krasnoye",
    "gn:country_code":"RU",
    "gn:dem":210,
    "gn:feature_class":"P",
    "gn:feature_code":"PPL",
    "gn:name":"Krasnoye",
    "gn:population":0,
    "gn:timezone":"Europe/Moscow",
    "iso:country":"RU",
    "name:rus_x_preferred":[
        "\u041a\u0440\u0430\u0441\u043d\u043e\u0435"
    ],
    "name:und_x_variant":[
        "Pervoye Krasnoye",
        "Krasnoye Pervoye",
        "Pervoye",
        "Krasnoye",
        "Krasnoye Vtoroye",
        "Vtoroye Krasnoye"
    ],
    "wof:name":"Krasnoye",
    "wof:placetype":"locality"
},
  "geometry": {"coordinates":[36.84166,52.25104],"type":"Point"}
}