{
  "type": "Feature",
  "properties": {
    "gn:admin1_code":"51.0",
    "gn:asciiname":"Maloye Chukhovo",
    "gn:country_code":"RU",
    "gn:dem":90,
    "gn:feature_class":"P",
    "gn:feature_code":"PPL",
    "gn:name":"Maloye Chukhovo",
    "gn:population":0,
    "gn:timezone":"Europe/Moscow",
    "iso:country":"RU",
    "name:nor_x_preferred":[
        "Maloje Tsjukhovo"
    ],
    "name:rus_x_preferred":[
        "\u041c\u0430\u043b\u043e\u0435 \u0427\u0443\u0445\u043e\u0432\u043e"
    ],
    "wof:name":"Maloye Chukhovo",
    "wof:placetype":"locality"
},
  "geometry": {"coordinates":[43.13997,56.65744],"type":"Point"}
}