{
  "type": "Feature",
  "properties": {
    "gn:admin1_code":"77",
    "gn:asciiname":"Vorylevo",
    "gn:country_code":"RU",
    "gn:dem":156,
    "gn:feature_class":"P",
    "gn:feature_code":"PPL",
    "gn:name":"Vorylevo",
    "gn:population":0,
    "gn:timezone":"Europe/Moscow",
    "iso:country":"RU",
    "name:rus_x_preferred":[
        "\u0412\u043e\u0440\u044b\u043b\u0435\u0432\u043e"
    ],
    "name:und_x_variant":[
        "\u0412\u043e\u0440\u044b\u043b\u0435\u0432\u043e"
    ],
    "wof:name":"Vorylevo",
    "wof:placetype":"locality"
},
  "geometry": {"coordinates":[36.7631,57.7192],"type":"Point"}
}