{
  "type": "Feature",
  "properties": {
    "gn:admin1_code":"15",
    "gn:asciiname":"Siginik",
    "gn:country_code":"RU",
    "gn:dem":3,
    "gn:feature_class":"P",
    "gn:feature_code":"PPL",
    "gn:name":"Siginik",
    "gn:population":0,
    "gn:timezone":"Asia/Anadyr",
    "iso:country":"RU",
    "name:rus_x_preferred":[
        "\u0421\u0438\u0433\u0438\u043d\u0438\u043a"
    ],
    "wof:name":"Siginik",
    "wof:placetype":"locality"
},
  "geometry": {"coordinates":[-174.05000000000001,64.55],"type":"Point"}
}