{
  "type": "Feature",
  "properties": {
    "gn:admin1_code":"21",
    "gn:asciiname":"Skrylovo",
    "gn:country_code":"RU",
    "gn:dem":139,
    "gn:feature_class":"P",
    "gn:feature_code":"PPL",
    "gn:name":"Skrylovo",
    "gn:population":0,
    "gn:timezone":"Europe/Moscow",
    "iso:country":"RU",
    "name:rus_x_preferred":[
        "\u0421\u043a\u0440\u044b\u043b\u043e\u0432\u043e"
    ],
    "wof:name":"Skrylovo",
    "wof:placetype":"locality"
},
  "geometry": {"coordinates":[41.66912,57.12402],"type":"Point"}
}