{
  "type": "Feature",
  "properties": {
    "gn:admin1_code":"60",
    "gn:asciiname":"Krasnyy Lug",
    "gn:cc2":"RU",
    "gn:country_code":"RU",
    "gn:dem":89,
    "gn:feature_class":"P",
    "gn:feature_code":"PPL",
    "gn:name":"Krasnyy Lug",
    "gn:population":0,
    "gn:timezone":"Europe/Moscow",
    "iso:country":"RU",
    "name:rus_x_preferred":[
        "\u041a\u0440\u0430\u0441\u043d\u044b\u0439 \u041b\u0443\u0433"
    ],
    "name:und_x_variant":[
        "Krasny Lug",
        "Krasnyy Lug"
    ],
    "wof:name":"Krasnyy Lug",
    "wof:placetype":"locality"
},
  "geometry": {"coordinates":[30.45,57.56667],"type":"Point"}
}