{
  "type": "Feature",
  "properties": {
    "gn:admin1_code":"45.0",
    "gn:asciiname":"Shoya-Kuznetsovo",
    "gn:country_code":"RU",
    "gn:dem":108,
    "gn:feature_class":"P",
    "gn:feature_code":"PPL",
    "gn:name":"Shoya-Kuznetsovo",
    "gn:population":0,
    "gn:timezone":"Europe/Moscow",
    "iso:country":"RU",
    "name:rus_x_preferred":[
        "\u0428\u043e\u044f-\u041a\u0443\u0437\u043d\u0435\u0446\u043e\u0432\u043e"
    ],
    "name:und_x_variant":[
        "\u0428\u043e\u044f-\u041a\u0443\u0437\u043d\u0435\u0446\u043e\u0432\u043e"
    ],
    "wof:name":"Shoya-Kuznetsovo",
    "wof:placetype":"locality"
},
  "geometry": {"coordinates":[48.0732,56.6893],"type":"Point"}
}