{
  "type": "Feature",
  "properties": {
    "gn:admin1_code":"69.0",
    "gn:asciiname":"Asel'ye",
    "gn:country_code":"RU",
    "gn:dem":220,
    "gn:feature_class":"P",
    "gn:feature_code":"PPL",
    "gn:name":"Asel\u2019ye",
    "gn:population":0,
    "gn:timezone":"Europe/Moscow",
    "iso:country":"RU",
    "name:rus_x_preferred":[
        "\u0410\u0441\u0435\u043b\u044c\u0435"
    ],
    "name:und_x_variant":[
        "Asel\u2019ye"
    ],
    "wof:name":"Asel'ye",
    "wof:placetype":"locality"
},
  "geometry": {"coordinates":[33.2406,53.9414],"type":"Point"}
}