{
  "type": "Feature",
  "properties": {
    "gn:admin1_code":"90",
    "gn:asciiname":"Mul'kovo",
    "gn:country_code":"RU",
    "gn:dem":124,
    "gn:feature_class":"P",
    "gn:feature_code":"PPL",
    "gn:name":"Mul\u2019kovo",
    "gn:population":0,
    "gn:timezone":"Asia/Yekaterinburg",
    "iso:country":"RU",
    "name:rus_x_preferred":[
        "\u041c\u0443\u043b\u044c\u043a\u043e\u0432\u043e"
    ],
    "name:und_x_variant":[
        "Mul\u2019kovo"
    ],
    "wof:name":"Mul'kovo",
    "wof:placetype":"locality"
},
  "geometry": {"coordinates":[57.663,58.2844],"type":"Point"}
}