{
  "type": "Feature",
  "properties": {
    "gn:admin1_code":"60",
    "gn:asciiname":"Tereshkovo",
    "gn:country_code":"RU",
    "gn:dem":217,
    "gn:feature_class":"P",
    "gn:feature_code":"PPL",
    "gn:name":"Tereshkovo",
    "gn:population":0,
    "gn:timezone":"Europe/Moscow",
    "iso:country":"RU",
    "name:rus_x_preferred":[
        "\u0422\u0435\u0440\u0435\u0448\u043a\u043e\u0432\u043e"
    ],
    "wof:name":"Tereshkovo",
    "wof:placetype":"locality"
},
  "geometry": {"coordinates":[29.8561,56.3466],"type":"Point"}
}