{
  "type": "Feature",
  "properties": {
    "gn:admin1_code":"56",
    "gn:asciiname":"Vtoraya Lunacharka",
    "gn:country_code":"RU",
    "gn:dem":237,
    "gn:feature_class":"P",
    "gn:feature_code":"PPL",
    "gn:name":"Vtoraya Lunacharka",
    "gn:population":0,
    "gn:timezone":"Europe/Moscow",
    "iso:country":"RU",
    "wof:name":"Vtoraya Lunacharka",
    "wof:placetype":"locality"
},
  "geometry": {"coordinates":[36.76667,52.68333000000001],"type":"Point"}
}