{
  "type": "Feature",
  "properties": {
    "gn:admin1_code":"72.0",
    "gn:asciiname":"Derben'",
    "gn:country_code":"RU",
    "gn:dem":134,
    "gn:feature_class":"P",
    "gn:feature_code":"PPL",
    "gn:name":"Derben\u2019",
    "gn:population":0,
    "gn:timezone":"Europe/Moscow",
    "iso:country":"RU",
    "name:rus_x_preferred":[
        "\u0414\u0435\u0440\u0431\u0435\u043d\u044c"
    ],
    "name:und_x_variant":[
        "Derben\u2019",
        "\u0414\u0435\u0440\u0431\u0435\u043d\u044c"
    ],
    "wof:name":"Derben'",
    "wof:placetype":"locality"
},
  "geometry": {"coordinates":[42.67799,52.54667],"type":"Point"}
}