{
  "type": "Feature",
  "properties": {
    "gn:admin1_code":"20",
    "gn:asciiname":"Ulus Ubukhan",
    "gn:cc2":"RU",
    "gn:country_code":"RU",
    "gn:dem":542,
    "gn:feature_class":"P",
    "gn:feature_code":"PPL",
    "gn:name":"Ulus Ubukhan",
    "gn:population":0,
    "gn:timezone":"Asia/Irkutsk",
    "iso:country":"RU",
    "name:und_x_variant":[
        "Ubukhan",
        "Ulus Ubukhan"
    ],
    "wof:name":"Ulus Ubukhan",
    "wof:placetype":"locality"
},
  "geometry": {"coordinates":[107.88333,53.76667],"type":"Point"}
}