{
  "type": "Feature",
  "properties": {
    "gn:admin1_code":"25",
    "gn:asciiname":"Anopochkin",
    "gn:country_code":"RU",
    "gn:dem":194,
    "gn:feature_class":"P",
    "gn:feature_code":"PPL",
    "gn:name":"Anopochkin",
    "gn:population":0,
    "gn:timezone":"Europe/Moscow",
    "iso:country":"RU",
    "name:nor_x_preferred":[
        "Anopotsjkin"
    ],
    "name:rus_x_preferred":[
        "\u0410\u043d\u043e\u043f\u043e\u0447\u043a\u0438\u043d"
    ],
    "wof:name":"Anopochkin",
    "wof:placetype":"locality"
},
  "geometry": {"coordinates":[35.03611,53.44556],"type":"Point"}
}