{
  "type": "Feature",
  "properties": {
    "gn:admin1_code":"85.0",
    "gn:asciiname":"Srednyaya",
    "gn:country_code":"RU",
    "gn:dem":107,
    "gn:feature_class":"P",
    "gn:feature_code":"PPL",
    "gn:name":"Srednyaya",
    "gn:population":0,
    "gn:timezone":"Europe/Moscow",
    "iso:country":"RU",
    "name:rus_x_preferred":[
        "\u0421\u0440\u0435\u0434\u043d\u044f\u044f"
    ],
    "wof:name":"Srednyaya",
    "wof:placetype":"locality"
},
  "geometry": {"coordinates":[37.8454,60.3299],"type":"Point"}
}