{
  "type": "Feature",
  "properties": {
    "gn:admin1_code":"38",
    "gn:asciiname":"Kamchatka",
    "gn:country_code":"RU",
    "gn:dem":27,
    "gn:feature_class":"P",
    "gn:feature_code":"PPL",
    "gn:name":"Kamchatka",
    "gn:population":0,
    "gn:timezone":"Europe/Moscow",
    "iso:country":"RU",
    "name:rus_x_preferred":[
        "\u041a\u0430\u043c\u0447\u0430\u0442\u0441\u043a\u044f \u043e\u0431\u043b\u0430\u0441\u0442\u044c"
    ],
    "name:rus_x_variant":[
        "\u041a\u0430\u043c\u0447\u0430\u0442\u043a\u0430"
    ],
    "name:und_x_variant":[
        "\u041a\u0430\u043c\u0447\u0430\u0442\u043a\u0430",
        "Kamchatka"
    ],
    "wof:name":"Kamchatka",
    "wof:placetype":"locality"
},
  "geometry": {"coordinates":[37.63154,44.70676],"type":"Point"}
}