{
  "type": "Feature",
  "properties": {
    "gn:admin1_code":"38",
    "gn:asciiname":"Lavrenenkova Polyana",
    "gn:country_code":"RU",
    "gn:dem":237,
    "gn:feature_class":"P",
    "gn:feature_code":"PPL",
    "gn:name":"Lavrenenkova Polyana",
    "gn:population":0,
    "gn:timezone":"Europe/Moscow",
    "iso:country":"RU",
    "name:rus_x_preferred":[
        "\u041b\u0430\u0432\u0440\u0435\u043d\u0435\u043d\u043a\u043e\u0432\u0430 \u041f\u043e\u043b\u044f\u043d\u0430"
    ],
    "wof:name":"Lavrenenkova Polyana",
    "wof:placetype":"locality"
},
  "geometry": {"coordinates":[38.6836,44.5879],"type":"Point"}
}