{
  "type": "Feature",
  "properties": {
    "gn:admin1_code":"57.0",
    "gn:asciiname":"Atmis",
    "gn:country_code":"RU",
    "gn:dem":155,
    "gn:feature_class":"P",
    "gn:feature_code":"PPL",
    "gn:name":"Atmis",
    "gn:population":0,
    "gn:timezone":"Europe/Moscow",
    "iso:country":"RU",
    "name:eng_x_preferred":[
        "Atmis"
    ],
    "name:nor_x_preferred":[
        "Atmis"
    ],
    "name:rus_x_preferred":[
        "\u0410\u0442\u043c\u0438\u0441"
    ],
    "name:und_x_variant":[
        "Atmiss",
        "\u0410\u0442\u043c\u0438\u0441",
        "Atmis"
    ],
    "wof:name":"Atmis",
    "wof:placetype":"locality"
},
  "geometry": {"coordinates":[43.925,53.48083000000001],"type":"Point"}
}