{
  "type": "Feature",
  "properties": {
    "gn:admin1_code":"84",
    "gn:asciiname":"Shaposhnikovo",
    "gn:cc2":"RU",
    "gn:country_code":"RU",
    "gn:dem":170,
    "gn:feature_class":"P",
    "gn:feature_code":"PPL",
    "gn:name":"Shaposhnikovo",
    "gn:population":0,
    "gn:timezone":"Europe/Volgograd",
    "iso:country":"RU",
    "name:rus_x_preferred":[
        "\u0428\u0430\u043f\u043e\u0448\u043d\u0438\u043a\u043e\u0432\u043e"
    ],
    "name:und_x_variant":[
        "Shaposhinkova",
        "Shaposhnikovo",
        "\u0428\u0430\u043f\u043e\u0448\u043d\u0438\u043a\u043e\u0432\u043e"
    ],
    "wof:name":"Shaposhnikovo",
    "wof:placetype":"locality"
},
  "geometry": {"coordinates":[44.38333,50.93333],"type":"Point"}
}