{
  "type": "Feature",
  "properties": {
    "gn:admin1_code":"54",
    "gn:asciiname":"Kokchinsk",
    "gn:country_code":"RU",
    "gn:dem":114,
    "gn:feature_class":"P",
    "gn:feature_code":"PPL",
    "gn:name":"Kokchinsk",
    "gn:population":0,
    "gn:timezone":"Asia/Omsk",
    "iso:country":"RU",
    "name:rus_x_preferred":[
        "\u041a\u043e\u043a\u0447\u0438\u043d\u0441\u043a"
    ],
    "name:und_x_variant":[
        "\u041a\u043e\u043a\u0447\u0438\u043d\u0441\u043a"
    ],
    "wof:name":"Kokchinsk",
    "wof:placetype":"locality"
},
  "geometry": {"coordinates":[72.58540000000001,54.363],"type":"Point"}
}