{
  "type": "Feature",
  "properties": {
    "gn:admin1_code":"34",
    "gn:asciiname":"Kopsa",
    "gn:country_code":"RU",
    "gn:dem":161,
    "gn:feature_class":"P",
    "gn:feature_code":"PPL",
    "gn:name":"Kopsa",
    "gn:population":0,
    "gn:timezone":"Europe/Moscow",
    "iso:country":"RU",
    "name:eng_x_preferred":[
        "Kopsa"
    ],
    "name:nor_x_preferred":[
        "Kopsa"
    ],
    "name:rus_x_preferred":[
        "\u041a\u043e\u043f\u0441\u0430"
    ],
    "name:und_x_variant":[
        "\u041a\u043e\u043f\u0441\u0430",
        "Kopsa"
    ],
    "wof:name":"Kopsa",
    "wof:placetype":"locality"
},
  "geometry": {"coordinates":[49.63777,61.18126],"type":"Point"}
}