{
  "type": "Feature",
  "properties": {
    "gn:admin1_code":"86.0",
    "gn:asciiname":"Deyevka",
    "gn:cc2":"RU",
    "gn:country_code":"RU",
    "gn:dem":137,
    "gn:feature_class":"P",
    "gn:feature_code":"PPL",
    "gn:name":"Deyevka",
    "gn:population":0,
    "gn:timezone":"Europe/Moscow",
    "iso:country":"RU",
    "name:rus_x_preferred":[
        "\u0414\u0435\u0435\u0432\u043a\u0430"
    ],
    "name:und_x_variant":[
        "Slava",
        "Deyevka",
        "\u0414\u0435\u0435\u0432\u043a\u0430"
    ],
    "wof:name":"Deyevka",
    "wof:placetype":"locality"
},
  "geometry": {"coordinates":[40.82333,51.30833],"type":"Point"}
}