{
  "type": "Feature",
  "properties": {
    "gn:country":"RU",
    "gn:fcode":"PPL",
    "gn:pop":0,
    "iso:country":"RU",
    "name:che_x_preferred":[
        "\u041c\u043e\u0440\u043e\u0437\u043e\u0432\u043a\u0430"
    ],
    "name:eng_x_preferred":[
        "Morozovo"
    ],
    "name:nor_x_preferred":[
        "Morozovo"
    ],
    "name:rus_x_preferred":[
        "\u041c\u043e\u0440\u043e\u0437\u043e\u0432\u043e"
    ],
    "name:rus_x_variant":[
        "\u041c\u043e\u0440\u043e\u0437\u043e\u0432\u043a\u0430"
    ],
    "name:unk_x_variant":[
        "Morozova"
    ],
    "qs:name":"Morozovka",
    "qs:name_adm0":"Russia",
    "qs:name_adm1":"Novosibirsk Oblast",
    "qs:photos_9r":0,
    "qs:photos_sr":0,
    "qs:placetype":"Town",
    "qs:pop_sr":"0",
    "wof:name":"Morozovka",
    "wof:placetype":"locality",
    "wof:population":0
},
  "geometry": {"coordinates":[83.2186,54.766],"type":"Point"}
}