{
  "type": "Feature",
  "properties": {
    "gn:admin1_code":"62.0",
    "gn:asciiname":"Barakovo",
    "gn:country_code":"RU",
    "gn:dem":118,
    "gn:feature_class":"P",
    "gn:feature_code":"PPL",
    "gn:name":"Barakovo",
    "gn:population":0,
    "gn:timezone":"Europe/Moscow",
    "iso:country":"RU",
    "name:eng_x_preferred":[
        "Barakovo"
    ],
    "name:nor_x_preferred":[
        "Barakovo"
    ],
    "name:rus_x_preferred":[
        "\u0411\u0430\u0440\u0430\u043a\u043e\u0432\u043e"
    ],
    "name:und_x_variant":[
        "\u0411\u0430\u0440\u0430\u043a\u043e\u0432\u043e",
        "Barakovo"
    ],
    "wof:name":"Barakovo",
    "wof:placetype":"locality"
},
  "geometry": {"coordinates":[39.1743,54.6212],"type":"Point"}
}