{
  "type": "Feature",
  "properties": {
    "gn:admin1_code":"77",
    "gn:asciiname":"Staroye Stashchino",
    "gn:country_code":"RU",
    "gn:dem":142,
    "gn:feature_class":"P",
    "gn:feature_code":"PPL",
    "gn:name":"Staroye Stashchino",
    "gn:population":0,
    "gn:timezone":"Europe/Moscow",
    "iso:country":"RU",
    "name:rus_x_preferred":[
        "\u0421\u0442\u0430\u0440\u043e\u0435 \u0421\u0442\u0430\u0449\u0438\u043d\u043e"
    ],
    "name:und_x_variant":[
        "\u0421\u0442\u0430\u0440\u043e\u0435 \u0421\u0442\u0430\u0449\u0438\u043d\u043e"
    ],
    "wof:name":"Staroye Stashchino",
    "wof:placetype":"locality"
},
  "geometry": {"coordinates":[37.4768,57.4811],"type":"Point"}
}