{
  "type": "Feature",
  "properties": {
    "gn:admin1_code":"61",
    "gn:asciiname":"Papchino",
    "gn:cc2":"RU",
    "gn:country_code":"RU",
    "gn:dem":124,
    "gn:feature_class":"P",
    "gn:feature_code":"PPL",
    "gn:name":"Papchino",
    "gn:population":0,
    "gn:timezone":"Europe/Moscow",
    "iso:country":"RU",
    "name:rus_x_preferred":[
        "\u041f\u0430\u043f\u0447\u0438\u043d\u043e"
    ],
    "name:und_x_variant":[
        "Panchinskiy",
        "Papchino"
    ],
    "wof:name":"Papchino",
    "wof:placetype":"locality"
},
  "geometry": {"coordinates":[39.5025,47.63611],"type":"Point"}
}