{
  "type": "Feature",
  "properties": {
    "gn:admin1_code":"33",
    "gn:asciiname":"Sutyaga",
    "gn:country_code":"RU",
    "gn:dem":185,
    "gn:feature_class":"P",
    "gn:feature_code":"PPL",
    "gn:name":"Sutyaga",
    "gn:population":0,
    "gn:timezone":"Europe/Kirov",
    "iso:country":"RU",
    "name:rus_x_preferred":[
        "\u0421\u0443\u0442\u044f\u0433\u0430"
    ],
    "wof:name":"Sutyaga",
    "wof:placetype":"locality"
},
  "geometry": {"coordinates":[49.4128,57.9997],"type":"Point"}
}