{
  "type": "Feature",
  "properties": {
    "gn:admin1_code":"47",
    "gn:asciiname":"Ostritsy",
    "gn:country_code":"RU",
    "gn:dem":216,
    "gn:feature_class":"P",
    "gn:feature_code":"PPL",
    "gn:name":"Ostritsy",
    "gn:population":0,
    "gn:timezone":"Europe/Moscow",
    "iso:country":"RU",
    "name:rus_x_preferred":[
        "\u041e\u0441\u0442\u0440\u0438\u0446\u044b"
    ],
    "name:und_x_variant":[
        "Ostritsa",
        "Ostritsy",
        "\u041e\u0441\u0442\u0440\u0438\u0446\u044b"
    ],
    "wof:name":"Ostritsy",
    "wof:placetype":"locality"
},
  "geometry": {"coordinates":[35.43527,55.67913000000001],"type":"Point"}
}