{
  "type": "Feature",
  "properties": {
    "gn:admin1_code":"60",
    "gn:asciiname":"Melenka",
    "gn:country_code":"RU",
    "gn:dem":108,
    "gn:feature_class":"P",
    "gn:feature_code":"PPL",
    "gn:name":"Melenka",
    "gn:population":0,
    "gn:timezone":"Europe/Moscow",
    "iso:country":"RU",
    "name:rus_x_preferred":[
        "\u041c\u0435\u043b\u0435\u043d\u043a\u0430"
    ],
    "wof:name":"Melenka",
    "wof:placetype":"locality"
},
  "geometry": {"coordinates":[28.9406,57.27262],"type":"Point"}
}