{
  "type": "Feature",
  "properties": {
    "gn:admin1_code":"71",
    "gn:asciiname":"Chubarovskoye",
    "gn:country_code":"RU",
    "gn:dem":72,
    "gn:feature_class":"P",
    "gn:feature_code":"PPL",
    "gn:name":"Chubarovskoye",
    "gn:population":0,
    "gn:timezone":"Asia/Yekaterinburg",
    "iso:country":"RU",
    "name:eng_x_preferred":[
        "Chubarovskoye"
    ],
    "name:nor_x_preferred":[
        "Tsjubarovskoje"
    ],
    "name:rus_x_preferred":[
        "\u0427\u0443\u0431\u0430\u0440\u043e\u0432\u0441\u043a\u043e\u0435"
    ],
    "wof:name":"Chubarovskoye",
    "wof:placetype":"locality"
},
  "geometry": {"coordinates":[63.50207,57.6446],"type":"Point"}
}