{
  "type": "Feature",
  "properties": {
    "gn:admin1_code":"76",
    "gn:asciiname":"Zavodskiy Khutor",
    "gn:country_code":"RU",
    "gn:dem":165,
    "gn:feature_class":"P",
    "gn:feature_code":"PPL",
    "gn:name":"Zavodskiy Khutor",
    "gn:population":0,
    "gn:timezone":"Europe/Moscow",
    "iso:country":"RU",
    "name:und_x_variant":[
        "Zavodiskiy Khutor",
        "Zavodskiy Khutor"
    ],
    "wof:name":"Zavodskiy Khutor",
    "wof:placetype":"locality"
},
  "geometry": {"coordinates":[36.52162,53.39735],"type":"Point"}
}