{
  "type": "Feature",
  "properties": {
    "gn:admin1_code":"43.0",
    "gn:asciiname":"Drobyshevo",
    "gn:country_code":"RU",
    "gn:dem":184,
    "gn:feature_class":"P",
    "gn:feature_code":"PPL",
    "gn:name":"Drobysh\u00ebvo",
    "gn:population":0,
    "gn:timezone":"Europe/Moscow",
    "iso:country":"RU",
    "name:rus_x_preferred":[
        "\u0414\u0440\u043e\u0431\u044b\u0448\u0451\u0432\u043e"
    ],
    "name:und_x_variant":[
        "Drobysh\u00ebvo",
        "\u0414\u0440\u043e\u0431\u044b\u0448\u0451\u0432\u043e"
    ],
    "wof:name":"Drobyshevo",
    "wof:placetype":"locality"
},
  "geometry": {"coordinates":[37.90395,52.16678],"type":"Point"}
}