{
  "type": "Feature",
  "properties": {
    "gn:admin1_code":"38.0",
    "gn:asciiname":"Novotroitskiy",
    "gn:country_code":"RU",
    "gn:dem":3,
    "gn:feature_class":"P",
    "gn:feature_code":"PPL",
    "gn:name":"Novotroitskiy",
    "gn:population":0,
    "gn:timezone":"Europe/Moscow",
    "iso:country":"RU",
    "name:rus_x_preferred":[
        "\u041d\u043e\u0432\u043e\u0442\u0440\u043e\u0438\u0446\u0441\u043a\u0438\u0439"
    ],
    "wof:name":"Novotroitskiy",
    "wof:placetype":"locality"
},
  "geometry": {"coordinates":[38.00793,45.03092],"type":"Point"}
}