{
  "type": "Feature",
  "properties": {
    "gn:admin1_code":"52",
    "gn:asciiname":"Peskova",
    "gn:country_code":"RU",
    "gn:dem":61,
    "gn:feature_class":"P",
    "gn:feature_code":"PPL",
    "gn:name":"Peskova",
    "gn:population":0,
    "gn:timezone":"Europe/Moscow",
    "iso:country":"RU",
    "name:eng_x_preferred":[
        "Peskova"
    ],
    "name:nor_x_preferred":[
        "Peskova"
    ],
    "name:rus_x_preferred":[
        "\u041f\u0435\u0441\u043a\u043e\u0432\u0430"
    ],
    "name:und_x_variant":[
        "Piskovo",
        "Piskova"
    ],
    "wof:name":"Peskova",
    "wof:placetype":"locality"
},
  "geometry": {"coordinates":[30.90596,57.97594],"type":"Point"}
}