{
  "type": "Feature",
  "properties": {
    "gn:admin1_code":"33",
    "gn:asciiname":"Babkintsy",
    "gn:country_code":"RU",
    "gn:dem":155,
    "gn:feature_class":"P",
    "gn:feature_code":"PPL",
    "gn:name":"Babkintsy",
    "gn:population":0,
    "gn:timezone":"Europe/Kirov",
    "iso:country":"RU",
    "name:nor_x_preferred":[
        "Babkintsy"
    ],
    "name:rus_x_preferred":[
        "\u0411\u0430\u0431\u043a\u0438\u043d\u0446\u044b"
    ],
    "name:und_x_variant":[
        "Bybintsy"
    ],
    "wof:name":"Babkintsy",
    "wof:placetype":"locality"
},
  "geometry": {"coordinates":[49.88628,58.12844000000001],"type":"Point"}
}