{
  "type": "Feature",
  "properties": {
    "gn:admin1_code":"54",
    "gn:asciiname":"Chebakly",
    "gn:country_code":"RU",
    "gn:dem":74,
    "gn:feature_class":"P",
    "gn:feature_code":"PPL",
    "gn:name":"Chebakly",
    "gn:population":0,
    "gn:timezone":"Asia/Omsk",
    "iso:country":"RU",
    "name:eng_x_preferred":[
        "Chebakly"
    ],
    "name:nor_x_preferred":[
        "Tsjebakly"
    ],
    "name:rus_x_preferred":[
        "\u0427\u0435\u0431\u0430\u043a\u043b\u044b"
    ],
    "name:und_x_variant":[
        "\u0427\u0435\u0431\u0430\u043a\u043b\u044b",
        "Chebakly"
    ],
    "wof:name":"Chebakly",
    "wof:placetype":"locality"
},
  "geometry": {"coordinates":[73.07401,57.09262],"type":"Point"}
}