{
  "type": "Feature",
  "properties": {
    "gn:admin1_code":"77.0",
    "gn:asciiname":"Raslovo",
    "gn:country_code":"RU",
    "gn:dem":147,
    "gn:feature_class":"P",
    "gn:feature_code":"PPL",
    "gn:name":"Raslovo",
    "gn:population":0,
    "gn:timezone":"Europe/Moscow",
    "iso:country":"RU",
    "name:eng_x_preferred":[
        "Raslovo"
    ],
    "name:rus_x_preferred":[
        "\u0420\u0430\u0441\u043b\u043e\u0432\u043e"
    ],
    "wof:name":"Raslovo",
    "wof:placetype":"locality"
},
  "geometry": {"coordinates":[35.85362,56.77324],"type":"Point"}
}