{
  "type": "Feature",
  "properties": {
    "gn:admin1_code":"29",
    "gn:asciiname":"Tashtagol",
    "gn:country_code":"RU",
    "gn:dem":660,
    "gn:feature_class":"P",
    "gn:feature_code":"PPL",
    "gn:name":"Tashtagol",
    "gn:population":0,
    "gn:timezone":"Asia/Novokuznetsk",
    "iso:country":"RU",
    "name:ara_x_preferred":[
        "\u062a\u0627\u0634\u062a\u0627\u063a\u0648\u0644"
    ],
    "name:azb_x_preferred":[
        "\u062a\u0627\u0634\u062a\u0627\u0642\u0648\u0644"
    ],
    "name:bel_x_preferred":[
        "\u0422\u0430\u0448\u0442\u0430\u0433\u043e\u043b"
    ],
    "name:bul_x_preferred":[
        "\u0422\u0430\u0449\u0430\u0433\u043e\u043b"
    ],
    "name:ceb_x_preferred":[
        "Tashtagol"
    ],
    "name:che_x_preferred":[
        "\u0422\u0430\u0448\u0442\u0430\u0433\u043e\u043b"
    ],
    "name:deu_x_preferred":[
        "Taschtagol"
    ],
    "name:eng_x_preferred":[
        "Shalym"
    ],
    "name:epo_x_preferred":[
        "Ta\u015dtagol"
    ],
    "name:est_x_preferred":[
        "Ta\u0161tagol"
    ],
    "name:fas_x_preferred":[
        "\u062a\u0627\u0634\u062a\u0627\u06af\u0648\u0644"
    ],
    "name:fra_x_preferred":[
        "Tachtagol"
    ],
    "name:haw_x_preferred":[
        "Ras\u016bap\u014d"
    ],
    "name:hsb_x_preferred":[
        "Ta\u0161tagol"
    ],
    "name:ita_x_preferred":[
        "Ta\u0161tagol"
    ],
    "name:lit_x_preferred":[
        "Ta\u0161tagolas"
    ],
    "name:nld_x_preferred":[
        "Tasjtagol"
    ],
    "name:nno_x_preferred":[
        "Tasjtagol"
    ],
    "name:nor_x_preferred":[
        "Sjalym"
    ],
    "name:nor_x_variant":[
        "Tasjtagol"
    ],
    "name:oss_x_preferred":[
        "\u0422\u0430\u0448\u0442\u0430\u0433\u043e\u043b"
    ],
    "name:pol_x_preferred":[
        "Tasztago\u0142"
    ],
    "name:rus_x_preferred":[
        "\u0428\u0430\u043b\u044b\u043c"
    ],
    "name:rus_x_variant":[
        "\u0422\u0430\u0448\u0442\u0430\u0433\u043e\u043b"
    ],
    "name:srp_x_preferred":[
        "\u0422\u0430\u0448\u0442\u0430\u0433\u043e\u043b"
    ],
    "name:tat_x_preferred":[
        "\u0422\u0430\u0448\u0442\u0430\u0433\u043e\u043b"
    ],
    "name:tgk_x_preferred":[
        "\u0422\u0430\u0448\u0442\u0430\u0433\u043e\u043b"
    ],
    "name:tgl_x_preferred":[
        "Tashtagol"
    ],
    "name:tur_x_preferred":[
        "Ta\u015ftagol"
    ],
    "name:ukr_x_preferred":[
        "\u0422\u0430\u0448\u0442\u0430\u0433\u043e\u043b"
    ],
    "name:und_x_variant":[
        "\u0422\u0430\u0448\u0442\u0430\u0433\u043e\u043b",
        "Shalym"
    ],
    "name:vep_x_preferred":[
        "Ta\u0161tagol"
    ],
    "name:war_x_preferred":[
        "Tashtagol"
    ],
    "name:zho_x_preferred":[
        "\u5854\u4ec0\u5854\u6208\u723e"
    ],
    "wof:name":"Tashtagol",
    "wof:placetype":"locality"
},
  "geometry": {"coordinates":[87.9272,52.8612],"type":"Point"}
}