{
  "type": "Feature",
  "properties": {
    "gn:admin1_code":"29",
    "gn:asciiname":"Tashtagol",
    "gn:country_code":"RU",
    "gn:dem":660,
    "gn:feature_class":"P",
    "gn:feature_code":"PPL",
    "gn:name":"Tashtagol",
    "gn:population":0,
    "gn:timezone":"Asia/Novokuznetsk",
    "iso:country":"RU",
    "name:eng_x_preferred":[
        "Shalym"
    ],
    "name:nor_x_preferred":[
        "Sjalym"
    ],
    "name:rus_x_preferred":[
        "\u0428\u0430\u043b\u044b\u043c"
    ],
    "name:rus_x_variant":[
        "\u0422\u0430\u0448\u0442\u0430\u0433\u043e\u043b"
    ],
    "name:und_x_variant":[
        "\u0422\u0430\u0448\u0442\u0430\u0433\u043e\u043b",
        "Shalym"
    ],
    "wof:name":"Tashtagol",
    "wof:placetype":"locality"
},
  "geometry": {"coordinates":[87.9272,52.8612],"type":"Point"}
}