{
  "type": "Feature",
  "properties": {
    "gn:admin1_code":"9.0",
    "gn:asciiname":"Dragunka",
    "gn:country_code":"RU",
    "gn:dem":161,
    "gn:feature_class":"P",
    "gn:feature_code":"PPL",
    "gn:name":"Dragunka",
    "gn:population":0,
    "gn:timezone":"Europe/Moscow",
    "iso:country":"RU",
    "name:rus_x_preferred":[
        "\u0414\u0440\u0430\u0433\u0443\u043d\u043a\u0430"
    ],
    "name:und_x_variant":[
        "Dragunovka",
        "Dragunskoye",
        "Dragunka"
    ],
    "wof:name":"Dragunka",
    "wof:placetype":"locality"
},
  "geometry": {"coordinates":[35.9517,51.0268],"type":"Point"}
}