{
  "type": "Feature",
  "properties": {
    "gn:admin1_code":"69",
    "gn:asciiname":"Granki",
    "gn:country_code":"RU",
    "gn:dem":185,
    "gn:feature_class":"P",
    "gn:feature_code":"PPL",
    "gn:name":"Granki",
    "gn:population":0,
    "gn:timezone":"Europe/Moscow",
    "iso:country":"RU",
    "name:rus_x_preferred":[
        "\u0413\u0440\u0430\u043d\u043a\u0438"
    ],
    "wof:name":"Granki",
    "wof:placetype":"locality"
},
  "geometry": {"coordinates":[31.43944,54.85333000000001],"type":"Point"}
}