{
  "type": "Feature",
  "properties": {
    "gn:admin1_code":"57.0",
    "gn:asciiname":"Chemizovka",
    "gn:country_code":"RU",
    "gn:dem":266,
    "gn:feature_class":"P",
    "gn:feature_code":"PPL",
    "gn:name":"Chemizovka",
    "gn:population":0,
    "gn:timezone":"Europe/Moscow",
    "iso:country":"RU",
    "name:rus_x_preferred":[
        "\u0427\u0435\u043c\u0438\u0437\u043e\u0432\u043a\u0430"
    ],
    "wof:name":"Chemizovka",
    "wof:placetype":"locality"
},
  "geometry": {"coordinates":[45.81667,52.85],"type":"Point"}
}