{
  "type": "Feature",
  "properties": {
    "gn:admin1_code":"13",
    "gn:asciiname":"Utyabayeva",
    "gn:country_code":"RU",
    "gn:dem":234,
    "gn:feature_class":"P",
    "gn:feature_code":"PPL",
    "gn:name":"Utyabayeva",
    "gn:population":0,
    "gn:timezone":"Asia/Yekaterinburg",
    "iso:country":"RU",
    "name:rus_x_preferred":[
        "\u0423\u0442\u044f\u0431\u0430\u0435\u0432\u0430"
    ],
    "wof:name":"Utyabayeva",
    "wof:placetype":"locality"
},
  "geometry": {"coordinates":[60.8396,55.5646],"type":"Point"}
}