{
  "type": "Feature",
  "properties": {
    "gn:admin1_code":"10",
    "gn:asciiname":"Chikhovka",
    "gn:country_code":"RU",
    "gn:dem":143,
    "gn:feature_class":"P",
    "gn:feature_code":"PPL",
    "gn:name":"Chikhovka",
    "gn:population":0,
    "gn:timezone":"Europe/Moscow",
    "iso:country":"RU",
    "name:rus_x_preferred":[
        "\u0427\u0438\u0445\u043e\u0432\u043a\u0430"
    ],
    "wof:name":"Chikhovka",
    "wof:placetype":"locality"
},
  "geometry": {"coordinates":[31.9039,52.8893],"type":"Point"}
}