{
  "type": "Feature",
  "properties": {
    "gn:admin1_code":"78",
    "gn:asciiname":"Roshchino",
    "gn:country_code":"RU",
    "gn:dem":103,
    "gn:feature_class":"P",
    "gn:feature_code":"PPL",
    "gn:name":"Roshchino",
    "gn:population":0,
    "gn:timezone":"Asia/Yekaterinburg",
    "iso:country":"RU",
    "name:rus_x_preferred":[
        "\u0420\u043e\u0449\u0438\u043d\u043e"
    ],
    "wof:name":"Roshchino",
    "wof:placetype":"locality"
},
  "geometry": {"coordinates":[65.4278,57.1558],"type":"Point"}
}