{
  "type": "Feature",
  "properties": {
    "gn:admin1_code":"83",
    "gn:asciiname":"Neklyudovo",
    "gn:country_code":"RU",
    "gn:dem":152,
    "gn:feature_class":"P",
    "gn:feature_code":"PPL",
    "gn:name":"Neklyudovo",
    "gn:population":0,
    "gn:timezone":"Europe/Moscow",
    "iso:country":"RU",
    "name:eng_x_preferred":[
        "Neklyudovo"
    ],
    "name:nor_x_preferred":[
        "Nekljudovo"
    ],
    "name:rus_x_preferred":[
        "\u041d\u0435\u043a\u043b\u044e\u0434\u043e\u0432\u043e"
    ],
    "wof:name":"Neklyudovo",
    "wof:placetype":"locality"
},
  "geometry": {"coordinates":[40.52077,55.83818],"type":"Point"}
}