{
  "type": "Feature",
  "properties": {
    "gn:admin1_code":"88",
    "gn:asciiname":"Maloye Kotovo",
    "gn:country_code":"RU",
    "gn:dem":106,
    "gn:feature_class":"P",
    "gn:feature_code":"PPL",
    "gn:name":"Maloye Kotovo",
    "gn:population":0,
    "gn:timezone":"Europe/Moscow",
    "iso:country":"RU",
    "name:rus_x_preferred":[
        "\u041c\u0430\u043b\u043e\u0435 \u041a\u043e\u0442\u043e\u0432\u043e"
    ],
    "name:und_x_variant":[
        "\u041c\u0430\u043b\u043e\u0435 \u041a\u043e\u0442\u043e\u0432\u043e"
    ],
    "wof:name":"Maloye Kotovo",
    "wof:placetype":"locality"
},
  "geometry": {"coordinates":[38.7444,57.9944],"type":"Point"}
}