{
  "type": "Feature",
  "properties": {
    "gn:admin1_code":"12.0",
    "gn:admin2_code":"516779",
    "gn:asciiname":"Amduk",
    "gn:country_code":"RU",
    "gn:dem":674,
    "gn:feature_class":"P",
    "gn:feature_code":"PPL",
    "gn:name":"\u0410\u043c\u0434\u0443\u043a",
    "gn:population":0,
    "gn:timezone":"Europe/Moscow",
    "iso:country":"RU",
    "name:nor_x_preferred":[
        "Amduk"
    ],
    "name:rus_x_preferred":[
        "\u0410\u043c\u0434\u0443\u043a"
    ],
    "wof:name":"Amduk",
    "wof:placetype":"locality"
},
  "geometry": {"coordinates":[46.09,43.11],"type":"Point"}
}