{
  "type": "Feature",
  "properties": {
    "gn:admin1_code":"56",
    "gn:asciiname":"Semendyayevskiy",
    "gn:country_code":"RU",
    "gn:dem":228,
    "gn:feature_class":"P",
    "gn:feature_code":"PPL",
    "gn:name":"Semendyayevskiy",
    "gn:population":0,
    "gn:timezone":"Europe/Moscow",
    "iso:country":"RU",
    "name:rus_x_preferred":[
        "\u0421\u0435\u043c\u0435\u043d\u0434\u044f\u0435\u0432\u0441\u043a\u0438\u0439"
    ],
    "name:und_x_variant":[
        "\u0421\u0435\u043c\u0435\u043d\u0434\u044f\u0435\u0432\u0441\u043a\u0438\u0439"
    ],
    "wof:name":"Semendyayevskiy",
    "wof:placetype":"locality"
},
  "geometry": {"coordinates":[36.35578,52.87596],"type":"Point"}
}