{
  "type": "Feature",
  "properties": {
    "gn:admin1_code":"77",
    "gn:asciiname":"Kul'nevo",
    "gn:country_code":"RU",
    "gn:dem":209,
    "gn:feature_class":"P",
    "gn:feature_code":"PPL",
    "gn:name":"Kul\u2019nevo",
    "gn:population":0,
    "gn:timezone":"Europe/Moscow",
    "iso:country":"RU",
    "name:eng_x_preferred":[
        "Kul'nevo"
    ],
    "name:nor_x_preferred":[
        "Kulnevo"
    ],
    "name:rus_x_preferred":[
        "\u041a\u0443\u043b\u044c\u043d\u0435\u0432\u043e"
    ],
    "name:und_x_variant":[
        "\u041a\u0443\u043b\u044c\u043d\u0435\u0432\u043e",
        "Kul\u2019nevo"
    ],
    "wof:name":"Kul'nevo",
    "wof:placetype":"locality"
},
  "geometry": {"coordinates":[34.14550999999999,56.10485],"type":"Point"}
}