{
  "type": "Feature",
  "properties": {
    "gn:country":"RU",
    "gn:fcode":"PPL",
    "gn:population":0,
    "iso:country":"RU",
    "name:rus_x_preferred":[
        "\u0421\u043e\u0432\u044c\u044f\u043a\u0438"
    ],
    "name:und_x_variant":[
        "Sov\u2019yaki"
    ],
    "qs:name":"Sov'yaki",
    "qs:name_adm0":"Russia",
    "qs:name_adm1":"Kaluga Oblast",
    "qs:photos":419,
    "qs:photos_1k":85,
    "qs:photos_9k":2,
    "qs:photos_9r":5,
    "qs:photos_all":419,
    "qs:photos_sr":6,
    "qs:placetype":"Town",
    "qs:pop_sr":"0",
    "wof:name":"Sov'yaki",
    "wof:placetype":"locality",
    "wof:population":0
},
  "geometry": {"coordinates":[36.43222,55.22806],"type":"Point"}
}