{
  "type": "Feature",
  "properties": {
    "gn:admin1_code":"57",
    "gn:asciiname":"Michurinskiy",
    "gn:country_code":"RU",
    "gn:dem":147,
    "gn:feature_class":"P",
    "gn:feature_code":"PPL",
    "gn:name":"Michurinskiy",
    "gn:population":0,
    "gn:timezone":"Europe/Moscow",
    "iso:country":"RU",
    "name:rus_x_preferred":[
        "\u041c\u0438\u0447\u0443\u0440\u0438\u043d\u0441\u043a\u0438\u0439"
    ],
    "wof:name":"Michurinskiy",
    "wof:placetype":"locality"
},
  "geometry": {"coordinates":[44.924,53.1091],"type":"Point"}
}