{
  "type": "Feature",
  "properties": {
    "gn:admin1_code":"77",
    "gn:asciiname":"Novosadovaya",
    "gn:country_code":"RU",
    "gn:dem":177,
    "gn:feature_class":"P",
    "gn:feature_code":"PPL",
    "gn:name":"Novosadovaya",
    "gn:population":0,
    "gn:timezone":"Europe/Moscow",
    "iso:country":"RU",
    "name:rus_x_preferred":[
        "\u041d\u043e\u0432\u043e\u0441\u0430\u0434\u043e\u0432\u0430\u044f"
    ],
    "name:und_x_variant":[
        "Svinkino",
        "Novosadovaya",
        "\u041d\u043e\u0432\u043e\u0441\u0430\u0434\u043e\u0432\u0430\u044f"
    ],
    "wof:name":"Novosadovaya",
    "wof:placetype":"locality"
},
  "geometry": {"coordinates":[34.30043,58.0159],"type":"Point"}
}