{
  "type": "Feature",
  "properties": {
    "gn:admin1_code":"42",
    "gn:asciiname":"Peushalovo",
    "gn:country_code":"RU",
    "gn:dem":129,
    "gn:feature_class":"P",
    "gn:feature_code":"PPL",
    "gn:name":"Peushalovo",
    "gn:population":0,
    "gn:timezone":"Europe/Moscow",
    "iso:country":"RU",
    "name:fin_x_preferred":[
        "Peussala"
    ],
    "name:nor_x_preferred":[
        "Peusjalovo"
    ],
    "name:rus_x_preferred":[
        "\u041f\u0435\u0443\u0448\u0430\u043b\u043e\u0432\u043e"
    ],
    "name:und_x_variant":[
        "Pedshelevo",
        "Peushel\u00ebvo",
        "Peushalovo"
    ],
    "wof:name":"Peushalovo",
    "wof:placetype":"locality"
},
  "geometry": {"coordinates":[29.84983,59.62553000000001],"type":"Point"}
}