{
  "type": "Feature",
  "properties": {
    "gn:admin1_code":"33.0",
    "gn:asciiname":"Bol'shiye Koromyslovy",
    "gn:country_code":"RU",
    "gn:dem":130,
    "gn:feature_class":"P",
    "gn:feature_code":"PPL",
    "gn:name":"Bol\u2019shiye Koromyslovy",
    "gn:population":0,
    "gn:timezone":"Europe/Kirov",
    "iso:country":"RU",
    "name:rus_x_preferred":[
        "\u0411\u043e\u043b\u044c\u0448\u0438\u0435 \u041a\u043e\u0440\u043e\u043c\u044b\u0441\u043b\u043e\u0432\u044b"
    ],
    "name:und_x_variant":[
        "Bol\u2019shiye Koromyslovy",
        "\u0411\u043e\u043b\u044c\u0448\u0438\u0435 \u041a\u043e\u0440\u043e\u043c\u044b\u0441\u043b\u043e\u0432\u044b"
    ],
    "wof:name":"Bol'shiye Koromyslovy",
    "wof:placetype":"locality"
},
  "geometry": {"coordinates":[48.30492,58.22614],"type":"Point"}
}