{
  "type": "Feature",
  "properties": {
    "gn:admin1_code":"85",
    "gn:asciiname":"Pogost",
    "gn:country_code":"RU",
    "gn:dem":150,
    "gn:feature_class":"P",
    "gn:feature_code":"PPL",
    "gn:name":"Pogost",
    "gn:population":0,
    "gn:timezone":"Europe/Moscow",
    "iso:country":"RU",
    "name:eng_x_preferred":[
        "Pogost"
    ],
    "name:nor_x_preferred":[
        "Pogost"
    ],
    "name:rus_x_preferred":[
        "\u041f\u043e\u0433\u043e\u0441\u0442"
    ],
    "name:und_x_variant":[
        "Kalininskaya",
        "Kalinino",
        "\u041f\u043e\u0433\u043e\u0441\u0442",
        "Pogost"
    ],
    "wof:name":"Pogost",
    "wof:placetype":"locality"
},
  "geometry": {"coordinates":[42.45793,59.89415],"type":"Point"}
}