{
  "type": "Feature",
  "properties": {
    "gn:admin1_code":"85",
    "gn:asciiname":"Pogost",
    "gn:country_code":"RU",
    "gn:dem":150,
    "gn:feature_class":"P",
    "gn:feature_code":"PPL",
    "gn:name":"Pogost",
    "gn:population":0,
    "gn:timezone":"Europe/Moscow",
    "iso:country":"RU",
    "name:bel_x_preferred":[
        "\u041f\u0430\u0433\u043e\u0441\u0442"
    ],
    "name:ces_x_preferred":[
        "Pogost"
    ],
    "name:dan_x_preferred":[
        "Pogost"
    ],
    "name:eng_x_preferred":[
        "Pogost"
    ],
    "name:fra_x_preferred":[
        "Pogost"
    ],
    "name:jpn_x_preferred":[
        "\u30dd\u30b4\u30b9\u30c8"
    ],
    "name:lit_x_preferred":[
        "Vals\u010dius"
    ],
    "name:nld_x_preferred":[
        "Pogost"
    ],
    "name:nor_x_preferred":[
        "Pogost"
    ],
    "name:pol_x_preferred":[
        "Pohost"
    ],
    "name:rus_x_preferred":[
        "\u041f\u043e\u0433\u043e\u0441\u0442"
    ],
    "name:spa_x_preferred":[
        "Pogost"
    ],
    "name:swe_x_preferred":[
        "Pogost"
    ],
    "name:ukr_x_preferred":[
        "\u041f\u043e\u0433\u043e\u0441\u0442"
    ],
    "name:und_x_variant":[
        "Kalininskaya",
        "Kalinino"
    ],
    "wof:name":"Pogost",
    "wof:placetype":"locality"
},
  "geometry": {"coordinates":[42.45793,59.89415],"type":"Point"}
}