{
  "type": "Feature",
  "properties": {
    "gn:admin1_code":"41.0",
    "gn:asciiname":"Chetvertoye Ukolovo",
    "gn:country_code":"RU",
    "gn:dem":184,
    "gn:feature_class":"P",
    "gn:feature_code":"PPL",
    "gn:name":"Chetv\u00ebrtoye Ukolovo",
    "gn:population":0,
    "gn:timezone":"Europe/Moscow",
    "iso:country":"RU",
    "name:rus_x_preferred":[
        "\u0427\u0435\u0442\u0432\u0451\u0440\u0442\u043e\u0435 \u0423\u043a\u043e\u043b\u043e\u0432\u043e"
    ],
    "name:und_x_variant":[
        "Chetv\u00ebrtoye Ukolovo",
        "\u0427\u0435\u0442\u0432\u0451\u0440\u0442\u043e\u0435 \u0423\u043a\u043e\u043b\u043e\u0432\u043e"
    ],
    "wof:name":"Chetvertoye Ukolovo",
    "wof:placetype":"locality"
},
  "geometry": {"coordinates":[36.4267,52.0073],"type":"Point"}
}