{
  "type": "Feature",
  "properties": {
    "gn:admin1_code":"90.0",
    "gn:asciiname":"Zarechnaya",
    "gn:country_code":"RU",
    "gn:dem":162,
    "gn:feature_class":"P",
    "gn:feature_code":"PPL",
    "gn:name":"Zarechnaya",
    "gn:population":0,
    "gn:timezone":"Asia/Yekaterinburg",
    "iso:country":"RU",
    "name:rus_x_preferred":[
        "\u0417\u0430\u0440\u0435\u0447\u043d\u0430\u044f"
    ],
    "wof:name":"Zarechnaya",
    "wof:placetype":"locality"
},
  "geometry": {"coordinates":[54.4332,59.4389],"type":"Point"}
}