{
  "type": "Feature",
  "properties": {
    "gn:admin1_code":"77",
    "gn:asciiname":"Boyarshchina",
    "gn:country_code":"RU",
    "gn:dem":234,
    "gn:feature_class":"P",
    "gn:feature_code":"PPL",
    "gn:name":"Boyarshchina",
    "gn:population":0,
    "gn:timezone":"Europe/Moscow",
    "iso:country":"RU",
    "name:rus_x_preferred":[
        "\u0411\u043e\u044f\u0440\u0449\u0438\u043d\u0430"
    ],
    "name:und_x_variant":[
        "\u0411\u043e\u044f\u0440\u0449\u0438\u043d\u0430"
    ],
    "wof:name":"Boyarshchina",
    "wof:placetype":"locality"
},
  "geometry": {"coordinates":[33.30226,55.91168],"type":"Point"}
}