{
  "type": "Feature",
  "properties": {
    "gn:admin1_code":"20",
    "gn:asciiname":"Kakha",
    "gn:country_code":"RU",
    "gn:dem":430,
    "gn:feature_class":"P",
    "gn:feature_code":"PPL",
    "gn:name":"Kakha",
    "gn:population":0,
    "gn:timezone":"Asia/Irkutsk",
    "iso:country":"RU",
    "name:eng_x_preferred":[
        "Kakha"
    ],
    "name:fas_x_preferred":[
        "\u06a9\u062e\u0627"
    ],
    "name:nor_x_preferred":[
        "Kakha"
    ],
    "name:rus_x_preferred":[
        "\u041a\u0430\u0445\u0430"
    ],
    "wof:name":"Kakha",
    "wof:placetype":"locality"
},
  "geometry": {"coordinates":[103.9503,53.4372],"type":"Point"}
}