{
  "type": "Feature",
  "properties": {
    "gn:admin1_code":"13",
    "gn:asciiname":"Nizhnyaya Satka",
    "gn:country_code":"RU",
    "gn:dem":398,
    "gn:feature_class":"P",
    "gn:feature_code":"PPL",
    "gn:name":"Nizhnyaya Satka",
    "gn:population":0,
    "gn:timezone":"Asia/Yekaterinburg",
    "iso:country":"RU",
    "name:rus_x_preferred":[
        "\u041d\u0438\u0436\u043d\u044f\u044f \u0421\u0430\u0442\u043a\u0430"
    ],
    "wof:name":"Nizhnyaya Satka",
    "wof:placetype":"locality"
},
  "geometry": {"coordinates":[59.0485,55.1528],"type":"Point"}
}