{
  "type": "Feature",
  "properties": {
    "gn:admin1_code":"4",
    "gn:asciiname":"Davydovskiy",
    "gn:country_code":"RU",
    "gn:dem":217,
    "gn:feature_class":"P",
    "gn:feature_code":"PPL",
    "gn:name":"Davydovskiy",
    "gn:population":0,
    "gn:timezone":"Asia/Barnaul",
    "iso:country":"RU",
    "name:rus_x_preferred":[
        "\u0414\u0430\u0432\u044b\u0434\u043e\u0432\u0441\u043a\u0438\u0439"
    ],
    "name:und_x_variant":[
        "\u0414\u0430\u0432\u044b\u0434\u043e\u0432\u0441\u043a\u0438\u0439"
    ],
    "wof:name":"Davydovskiy",
    "wof:placetype":"locality"
},
  "geometry": {"coordinates":[79.88333,53.88333000000001],"type":"Point"}
}