{
  "type": "Feature",
  "properties": {
    "gn:admin1_code":"25",
    "gn:asciiname":"Kumovo",
    "gn:cc2":"RU",
    "gn:country_code":"RU",
    "gn:dem":189,
    "gn:feature_class":"P",
    "gn:feature_code":"PPL",
    "gn:name":"Kumovo",
    "gn:population":0,
    "gn:timezone":"Europe/Moscow",
    "iso:country":"RU",
    "name:rus_x_preferred":[
        "\u041a\u0443\u043c\u043e\u0432\u043e"
    ],
    "name:und_x_variant":[
        "Novyy Mushkan",
        "Kumovo"
    ],
    "wof:name":"Kumovo",
    "wof:placetype":"locality"
},
  "geometry": {"coordinates":[35.68694,53.82111],"type":"Point"}
}