{
  "type": "Feature",
  "properties": {
    "gn:country":"RU",
    "gn:fcode":"PPL",
    "gn:pop":0,
    "iso:country":"RU",
    "name:eng_x_preferred":[
        "Sidorovskoye"
    ],
    "name:nor_x_preferred":[
        "Sidorovskoje"
    ],
    "name:rus_x_preferred":[
        "\u0421\u0438\u0434\u043e\u0440\u043e\u0432\u0441\u043a\u043e\u0435"
    ],
    "name:unk_x_variant":[
        "Siderovo"
    ],
    "qs:name":"Sidorovskoye",
    "qs:name_adm0":"Russia",
    "qs:name_adm1":"Kostroma Oblast",
    "qs:photos_9r":0,
    "qs:photos_sr":0,
    "qs:placetype":"Town",
    "qs:pop_sr":"0",
    "wof:name":"Sidorovskoye",
    "wof:placetype":"locality",
    "wof:population":0
},
  "geometry": {"coordinates":[41.21754,57.45026],"type":"Point"}
}