{
  "type": "Feature",
  "properties": {
    "gn:admin1_code":"91",
    "gn:asciiname":"Kulakovo",
    "gn:cc2":"RU",
    "gn:country_code":"RU",
    "gn:dem":94,
    "gn:feature_class":"P",
    "gn:feature_code":"PPL",
    "gn:name":"Kulakovo",
    "gn:population":0,
    "gn:timezone":"Asia/Krasnoyarsk",
    "iso:country":"RU",
    "name:eng_x_preferred":[
        "Kulakovo"
    ],
    "name:nor_x_preferred":[
        "Kulakovo"
    ],
    "name:rus_x_preferred":[
        "\u041a\u0443\u043b\u0430\u043a\u043e\u0432\u043e"
    ],
    "name:und_x_variant":[
        "Kulakova",
        "Kulakovo"
    ],
    "wof:name":"Kulakovo",
    "wof:placetype":"locality"
},
  "geometry": {"coordinates":[93.76416999999999,58.09139],"type":"Point"}
}