{
  "type": "Feature",
  "properties": {
    "gn:admin1_code":"28",
    "gn:asciiname":"Pirkhonen",
    "gn:country_code":"RU",
    "gn:dem":75,
    "gn:feature_class":"P",
    "gn:feature_code":"PPL",
    "gn:name":"Pirkhonen",
    "gn:population":0,
    "gn:timezone":"Europe/Moscow",
    "iso:country":"RU",
    "name:fin_x_preferred":[
        "Haravaselk\u00e4"
    ],
    "name:rus_x_preferred":[
        "\u041f\u0438\u0440\u0445\u043e\u043d\u0435\u043d"
    ],
    "wof:name":"Pirkhonen",
    "wof:placetype":"locality"
},
  "geometry": {"coordinates":[31.01667,61.85],"type":"Point"}
}