{
  "type": "Feature",
  "properties": {
    "gn:admin1_code":"43",
    "gn:asciiname":"Surki",
    "gn:country_code":"RU",
    "gn:dem":159,
    "gn:feature_class":"P",
    "gn:feature_code":"PPL",
    "gn:name":"Surki",
    "gn:population":0,
    "gn:timezone":"Europe/Moscow",
    "iso:country":"RU",
    "name:eng_x_preferred":[
        "Surki"
    ],
    "name:nor_x_preferred":[
        "Surki"
    ],
    "name:rus_x_preferred":[
        "\u0421\u0443\u0440\u043a\u0438"
    ],
    "name:und_x_variant":[
        "\u0421\u0443\u0440\u043a\u0438",
        "Surki"
    ],
    "wof:name":"Surki",
    "wof:placetype":"locality"
},
  "geometry": {"coordinates":[39.39341,53.08438],"type":"Point"}
}