{
  "type": "Feature",
  "properties": {
    "gn:admin1_code":"32",
    "gn:asciiname":"Kal'manovy",
    "gn:country_code":"RU",
    "gn:dem":27,
    "gn:feature_class":"P",
    "gn:feature_code":"PPL",
    "gn:name":"Kal\u2019manovy",
    "gn:population":0,
    "gn:timezone":"Asia/Yekaterinburg",
    "iso:country":"RU",
    "name:eng_x_preferred":[
        "Kal'manovy"
    ],
    "name:nor_x_preferred":[
        "Kalmanovo"
    ],
    "name:rus_x_preferred":[
        "\u041a\u0430\u043b\u044c\u043c\u0430\u043d\u043e\u0432\u043e"
    ],
    "name:rus_x_variant":[
        "\u041a\u0430\u043b\u044c\u043c\u0430\u043d\u043e\u0432\u044b"
    ],
    "name:und_x_variant":[
        "Yurty Kol\u2019manovskiye",
        "Kal\u2019manovskiy",
        "Kal\u2019manovy"
    ],
    "wof:name":"Kal'manovy",
    "wof:placetype":"locality"
},
  "geometry": {"coordinates":[67.43333,61.65],"type":"Point"}
}