{
  "type": "Feature",
  "properties": {
    "gn:admin1_code":"69",
    "gn:asciiname":"Kartavshchina",
    "gn:country_code":"RU",
    "gn:dem":193,
    "gn:feature_class":"P",
    "gn:feature_code":"PPL",
    "gn:name":"Kartavshchina",
    "gn:population":0,
    "gn:timezone":"Europe/Moscow",
    "iso:country":"RU",
    "name:eng_x_preferred":[
        "Kartavshchina"
    ],
    "name:nor_x_preferred":[
        "Kartavsjina"
    ],
    "name:rus_x_preferred":[
        "\u041a\u0430\u0440\u0442\u0430\u0432\u0448\u0438\u043d\u0430"
    ],
    "name:rus_x_variant":[
        "\u041a\u0430\u0440\u0442\u0430\u0432\u0449\u0438\u043d\u0430"
    ],
    "name:und_x_variant":[
        "\u041a\u0430\u0440\u0442\u0430\u0432\u0449\u0438\u043d\u0430"
    ],
    "wof:name":"Kartavshchina",
    "wof:placetype":"locality"
},
  "geometry": {"coordinates":[31.58635,55.60311],"type":"Point"}
}