{
  "type": "Feature",
  "properties": {
    "gn:admin1_code":"55",
    "gn:asciiname":"Nizhnesakmarskiy",
    "gn:country_code":"RU",
    "gn:dem":113,
    "gn:feature_class":"P",
    "gn:feature_code":"PPL",
    "gn:name":"Nizhnesakmarskiy",
    "gn:population":0,
    "gn:timezone":"Asia/Yekaterinburg",
    "iso:country":"RU",
    "name:rus_x_preferred":[
        "\u041d\u0438\u0436\u043d\u0435\u0441\u0430\u043a\u043c\u0430\u0440\u0441\u043a\u0438\u0439"
    ],
    "name:und_x_variant":[
        "Sovkhoz Sakmarskiy",
        "Nizhnesakmarskiy"
    ],
    "wof:name":"Nizhnesakmarskiy",
    "wof:placetype":"locality"
},
  "geometry": {"coordinates":[55.2201,51.9055],"type":"Point"}
}