{
  "type": "Feature",
  "properties": {
    "gn:admin1_code":"28",
    "gn:asciiname":"Kolgostrov",
    "gn:country_code":"RU",
    "gn:dem":32,
    "gn:feature_class":"P",
    "gn:feature_code":"PPL",
    "gn:name":"Kolgostrov",
    "gn:population":0,
    "gn:timezone":"Europe/Moscow",
    "iso:country":"RU",
    "name:fin_x_preferred":[
        "Kolksaari"
    ],
    "name:rus_x_preferred":[
        "\u041a\u043e\u043b\u0433\u043e\u0441\u0442\u0440\u043e\u0432"
    ],
    "wof:name":"Kolgostrov",
    "wof:placetype":"locality"
},
  "geometry": {"coordinates":[34.65266,62.41135],"type":"Point"}
}