{
  "type": "Feature",
  "properties": {
    "gn:admin1_code":"12",
    "gn:admin2_code":"Botlikhskiy Rayon",
    "gn:asciiname":"Tasuta",
    "gn:country_code":"RU",
    "gn:dem":1614,
    "gn:feature_class":"P",
    "gn:feature_code":"PPL",
    "gn:name":"Tasuta",
    "gn:population":0,
    "gn:timezone":"Europe/Moscow",
    "iso:country":"RU",
    "name:rus_x_preferred":[
        "\u0422\u0430\u0441\u0443\u0442\u0430"
    ],
    "name:und_x_variant":[
        "\u0422\u0430\u0441\u0443\u0442\u0430"
    ],
    "wof:name":"Tasuta",
    "wof:placetype":"locality"
},
  "geometry": {"coordinates":[46.22568,42.71731],"type":"Point"}
}