{
  "type": "Feature",
  "properties": {
    "gn:admin1_code":"77",
    "gn:asciiname":"Olisovo",
    "gn:country_code":"RU",
    "gn:dem":274,
    "gn:feature_class":"P",
    "gn:feature_code":"PPL",
    "gn:name":"Olisovo",
    "gn:population":0,
    "gn:timezone":"Europe/Moscow",
    "iso:country":"RU",
    "name:rus_x_preferred":[
        "\u041e\u043b\u0438\u0441\u043e\u0432\u043e"
    ],
    "wof:name":"Olisovo",
    "wof:placetype":"locality"
},
  "geometry": {"coordinates":[32.94869,56.76106],"type":"Point"}
}