{
  "type": "Feature",
  "properties": {
    "gn:country":"RU",
    "gn:fcode":"ADM3",
    "gn:population":0,
    "iso:country":"RU",
    "name:rus_x_preferred":[
        "\u041b\u0435\u043d\u0438\u043d\u0441\u043a\u0438\u0439 \u0420\u0430\u0439\u043e\u043d"
    ],
    "qs:name":"Leninskiy Rayon",
    "qs:photos_9r":0,
    "qs:photos_sr":0,
    "qs:pop_sr":"0",
    "wof:name":"Leninskiy Rayon",
    "wof:placetype":"localadmin",
    "wof:population":0
},
  "geometry": {"coordinates":[61.49702,55.11518],"type":"Point"}
}