{
  "type": "Feature",
  "properties": {
    "gn:admin1_code":"73",
    "gn:asciiname":"Zirekle-Yelga",
    "gn:country_code":"RU",
    "gn:dem":228,
    "gn:feature_class":"P",
    "gn:feature_code":"PPL",
    "gn:name":"Zirekle-Yelga",
    "gn:population":0,
    "gn:timezone":"Europe/Moscow",
    "iso:country":"RU",
    "name:rus_x_preferred":[
        "\u0417\u0438\u0440\u0435\u043a\u043b\u0435-\u0415\u043b\u0433\u0430"
    ],
    "wof:name":"Zirekle-Yelga",
    "wof:placetype":"locality"
},
  "geometry": {"coordinates":[53.0922,54.9242],"type":"Point"}
}