{
  "type": "Feature",
  "properties": {
    "gn:admin1_code":"67",
    "gn:asciiname":"Yuzhnyy",
    "gn:country_code":"RU",
    "gn:dem":96,
    "gn:feature_class":"P",
    "gn:feature_code":"PPL",
    "gn:name":"Yuzhnyy",
    "gn:population":0,
    "gn:timezone":"Europe/Saratov",
    "iso:country":"RU",
    "name:rus_x_preferred":[
        "\u042e\u0436\u043d\u044b\u0439"
    ],
    "wof:name":"Yuzhnyy",
    "wof:placetype":"locality"
},
  "geometry": {"coordinates":[48.394,51.488],"type":"Point"}
}