{
  "type": "Feature",
  "properties": {
    "gn:admin1_code":"20",
    "gn:asciiname":"Pridorozhnyy",
    "gn:country_code":"RU",
    "gn:dem":465,
    "gn:feature_class":"P",
    "gn:feature_code":"PPL",
    "gn:name":"Pridorozhnyy",
    "gn:population":0,
    "gn:timezone":"Asia/Irkutsk",
    "iso:country":"RU",
    "name:rus_x_preferred":[
        "\u041f\u0440\u0438\u0434\u043e\u0440\u043e\u0436\u043d\u044b\u0439"
    ],
    "wof:name":"Pridorozhnyy",
    "wof:placetype":"locality"
},
  "geometry": {"coordinates":[101.29465,56.69495],"type":"Point"}
}