{
  "type": "Feature",
  "properties": {
    "gn:admin1_code":"16",
    "gn:asciiname":"Shchamaly",
    "gn:country_code":"RU",
    "gn:dem":98,
    "gn:feature_class":"P",
    "gn:feature_code":"PPL",
    "gn:name":"Shchamaly",
    "gn:population":0,
    "gn:timezone":"Europe/Moscow",
    "iso:country":"RU",
    "name:rus_x_preferred":[
        "\u0429\u0430\u043c\u0430\u043b\u044b"
    ],
    "wof:name":"Shchamaly",
    "wof:placetype":"locality"
},
  "geometry": {"coordinates":[48.0266,55.913],"type":"Point"}
}