{
  "type": "Feature",
  "properties": {
    "gn:admin1_code":"90",
    "gn:asciiname":"Pes'yanka",
    "gn:country_code":"RU",
    "gn:dem":170,
    "gn:feature_class":"P",
    "gn:feature_code":"PPL",
    "gn:name":"Pes\u2019yanka",
    "gn:population":0,
    "gn:timezone":"Asia/Yekaterinburg",
    "iso:country":"RU",
    "name:rus_x_preferred":[
        "\u041f\u0435\u0441\u044c\u044f\u043d\u043a\u0430"
    ],
    "name:und_x_variant":[
        "Pes\u2019yanka"
    ],
    "wof:name":"Pes'yanka",
    "wof:placetype":"locality"
},
  "geometry": {"coordinates":[57.7902,57.5576],"type":"Point"}
}