{
  "type": "Feature",
  "properties": {
    "gn:admin1_code":"88.0",
    "gn:asciiname":"Berezino",
    "gn:country_code":"RU",
    "gn:dem":154,
    "gn:feature_class":"P",
    "gn:feature_code":"PPL",
    "gn:name":"Berezino",
    "gn:population":0,
    "gn:timezone":"Europe/Moscow",
    "iso:country":"RU",
    "name:nor_x_preferred":[
        "Berezina"
    ],
    "name:rus_x_preferred":[
        "\u0411\u0435\u0440\u0435\u0437\u0438\u043d\u043e"
    ],
    "name:und_x_variant":[
        "Berezina",
        "Berezino",
        "\u0411\u0435\u0440\u0435\u0437\u0438\u043d\u043e"
    ],
    "wof:name":"Berezino",
    "wof:placetype":"locality"
},
  "geometry": {"coordinates":[38.85392,57.56800000000001],"type":"Point"}
}