{
  "type": "Feature",
  "properties": {
    "gn:admin1_code":"54",
    "gn:asciiname":"Plotbishche",
    "gn:country_code":"RU",
    "gn:dem":78,
    "gn:feature_class":"P",
    "gn:feature_code":"PPL",
    "gn:name":"Plotbishche",
    "gn:population":0,
    "gn:timezone":"Asia/Omsk",
    "iso:country":"RU",
    "name:eng_x_preferred":[
        "Plotbishche"
    ],
    "name:nor_x_preferred":[
        "Plotbisjtsje"
    ],
    "name:rus_x_preferred":[
        "\u041f\u043b\u043e\u0442\u0431\u0438\u0449\u0435"
    ],
    "name:und_x_variant":[
        "Plotbishe"
    ],
    "wof:name":"Plotbishche",
    "wof:placetype":"locality"
},
  "geometry": {"coordinates":[75.47886,56.37648000000001],"type":"Point"}
}