{
  "type": "Feature",
  "properties": {
    "gn:admin1_code":"80",
    "gn:asciiname":"Mukhino",
    "gn:country_code":"RU",
    "gn:dem":187,
    "gn:feature_class":"P",
    "gn:feature_code":"PPL",
    "gn:name":"Mukhino",
    "gn:population":0,
    "gn:timezone":"Europe/Samara",
    "iso:country":"RU",
    "name:hye_x_preferred":[
        "\u0544\u0578\u0582\u056d\u056b\u0576\u0578"
    ],
    "name:rus_x_preferred":[
        "\u041c\u0443\u0445\u0438\u043d\u043e"
    ],
    "name:ukr_x_preferred":[
        "\u041c\u0443\u0445\u0456\u043d\u043e"
    ],
    "wof:name":"Mukhino",
    "wof:placetype":"locality"
},
  "geometry": {"coordinates":[52.65,57.48333],"type":"Point"}
}