{
  "type": "Feature",
  "properties": {
    "gn:admin1_code":"69",
    "gn:asciiname":"Kholmets",
    "gn:country_code":"RU",
    "gn:dem":219,
    "gn:feature_class":"P",
    "gn:feature_code":"PPL",
    "gn:name":"Kholmets",
    "gn:population":0,
    "gn:timezone":"Europe/Moscow",
    "iso:country":"RU",
    "name:rus_x_preferred":[
        "\u0425\u043e\u043b\u043c\u0435\u0446"
    ],
    "name:und_x_variant":[
        "\u0425\u043e\u043b\u043c\u0435\u0446"
    ],
    "wof:name":"Kholmets",
    "wof:placetype":"locality"
},
  "geometry": {"coordinates":[33.41196,54.627],"type":"Point"}
}