{
  "type": "Feature",
  "properties": {
    "gn:admin1_code":"20.0",
    "gn:asciiname":"Verkhnyaya Idyga",
    "gn:country_code":"RU",
    "gn:dem":619,
    "gn:feature_class":"P",
    "gn:feature_code":"PPL",
    "gn:name":"Verkhnyaya Idyga",
    "gn:population":0,
    "gn:timezone":"Asia/Irkutsk",
    "iso:country":"RU",
    "name:rus_x_preferred":[
        "\u0412\u0435\u0440\u0445\u043d\u044f\u044f \u0418\u0434\u044b\u0433\u0430"
    ],
    "wof:name":"Verkhnyaya Idyga",
    "wof:placetype":"locality"
},
  "geometry": {"coordinates":[104.56,52.92306],"type":"Point"}
}