{
  "type": "Feature",
  "properties": {
    "gn:admin1_code":"9",
    "gn:asciiname":"Zorinskiye Dvory",
    "gn:country_code":"RU",
    "gn:dem":231,
    "gn:feature_class":"P",
    "gn:feature_code":"PPL",
    "gn:name":"Zorinskiye Dvory",
    "gn:population":0,
    "gn:timezone":"Europe/Moscow",
    "iso:country":"RU",
    "wof:name":"Zorinskiye Dvory",
    "wof:placetype":"locality"
},
  "geometry": {"coordinates":[36.30291,51.07735],"type":"Point"}
}