{
  "type": "Feature",
  "properties": {
    "gn:admin1_code":"76",
    "gn:asciiname":"Bazdyrevo",
    "gn:country_code":"RU",
    "gn:dem":216,
    "gn:feature_class":"P",
    "gn:feature_code":"PPL",
    "gn:name":"Bazdyrevo",
    "gn:population":0,
    "gn:timezone":"Europe/Moscow",
    "iso:country":"RU",
    "name:nor_x_preferred":[
        "Bazdyrevo"
    ],
    "name:rus_x_preferred":[
        "\u0411\u0430\u0437\u0434\u044b\u0440\u0435\u0432\u043e"
    ],
    "wof:name":"Bazdyrevo",
    "wof:placetype":"locality"
},
  "geometry": {"coordinates":[36.75417,53.86666999999999],"type":"Point"}
}