{
  "type": "Feature",
  "properties": {
    "gn:admin1_code":"53",
    "gn:asciiname":"Sto Trinadtsatyy Kilometr",
    "gn:country_code":"RU",
    "gn:dem":169,
    "gn:feature_class":"P",
    "gn:feature_code":"PPL",
    "gn:name":"Sto Trinadtsatyy Kilometr",
    "gn:population":0,
    "gn:timezone":"Asia/Novosibirsk",
    "iso:country":"RU",
    "name:rus_x_preferred":[
        "\u0421\u0442\u043e \u0422\u0440\u0438\u043d\u0430\u0434\u0446\u0430\u0442\u044b\u0439 \u041a\u0438\u043b\u043e\u043c\u0435\u0442\u0440"
    ],
    "name:rus_x_variant":[
        "113 \u043a\u043c"
    ],
    "wof:name":"Sto Trinadtsatyy Kilometr",
    "wof:placetype":"locality"
},
  "geometry": {"coordinates":[84.2328,55.2448],"type":"Point"}
}