{
  "type": "Feature",
  "properties": {
    "gn:admin1_code":"85",
    "gn:asciiname":"Shemyakino",
    "gn:country_code":"RU",
    "gn:dem":147,
    "gn:feature_class":"P",
    "gn:feature_code":"PPL",
    "gn:name":"Shemyakino",
    "gn:population":0,
    "gn:timezone":"Europe/Moscow",
    "iso:country":"RU",
    "name:rus_x_preferred":[
        "\u0428\u0435\u043c\u044f\u043a\u0438\u043d\u043e"
    ],
    "wof:name":"Shemyakino",
    "wof:placetype":"locality"
},
  "geometry": {"coordinates":[39.8021,60.109],"type":"Point"}
}