{
  "type": "Feature",
  "properties": {
    "gn:admin1_code":"59.0",
    "gn:asciiname":"Kamenushka",
    "gn:country_code":"RU",
    "gn:dem":88,
    "gn:feature_class":"P",
    "gn:feature_code":"PPL",
    "gn:name":"Kamenushka",
    "gn:population":0,
    "gn:timezone":"Asia/Vladivostok",
    "iso:country":"RU",
    "name:rus_x_preferred":[
        "\u041a\u0430\u043c\u0435\u043d\u0443\u0448\u043a\u0430"
    ],
    "wof:name":"Kamenushka",
    "wof:placetype":"locality"
},
  "geometry": {"coordinates":[132.23203999999998,43.62313],"type":"Point"}
}