{
  "type": "Feature",
  "properties": {
    "gn:admin1_code":"10",
    "gn:asciiname":"Chakov",
    "gn:country_code":"RU",
    "gn:dem":180,
    "gn:feature_class":"P",
    "gn:feature_code":"PPL",
    "gn:name":"Chakov",
    "gn:population":0,
    "gn:timezone":"Europe/Moscow",
    "iso:country":"RU",
    "name:rus_x_preferred":[
        "\u0427\u0430\u043a\u043e\u0432"
    ],
    "name:und_x_variant":[
        "\u0427\u0430\u043a\u043e\u0432"
    ],
    "wof:name":"Chakov",
    "wof:placetype":"locality"
},
  "geometry": {"coordinates":[33.0557,52.4672],"type":"Point"}
}