{
  "type": "Feature",
  "properties": {
    "gn:admin1_code":"69",
    "gn:asciiname":"Ozhogi",
    "gn:country_code":"RU",
    "gn:dem":189,
    "gn:feature_class":"P",
    "gn:feature_code":"PPL",
    "gn:name":"Ozhogi",
    "gn:population":0,
    "gn:timezone":"Europe/Moscow",
    "iso:country":"RU",
    "name:rus_x_preferred":[
        "\u041e\u0436\u043e\u0433\u0438"
    ],
    "wof:name":"Ozhogi",
    "wof:placetype":"locality"
},
  "geometry": {"coordinates":[32.4424,53.92718000000001],"type":"Point"}
}