{
  "type": "Feature",
  "properties": {
    "gn:admin1_code":"47.0",
    "gn:asciiname":"Dyatlovo",
    "gn:country_code":"RU",
    "gn:dem":243,
    "gn:feature_class":"P",
    "gn:feature_code":"PPL",
    "gn:name":"Dyatlovo",
    "gn:population":0,
    "gn:timezone":"Europe/Moscow",
    "iso:country":"RU",
    "name:rus_x_preferred":[
        "\u0414\u044f\u0442\u043b\u043e\u0432\u043e"
    ],
    "wof:name":"Dyatlovo",
    "wof:placetype":"locality"
},
  "geometry": {"coordinates":[35.51314,55.94797],"type":"Point"}
}