{
  "type": "Feature",
  "properties": {
    "gn:admin1_code":"53",
    "gn:asciiname":"Vesnyanka",
    "gn:country_code":"RU",
    "gn:dem":116,
    "gn:feature_class":"P",
    "gn:feature_code":"PPL",
    "gn:name":"Vesnyanka",
    "gn:population":0,
    "gn:timezone":"Asia/Novosibirsk",
    "iso:country":"RU",
    "name:eng_x_preferred":[
        "Vesnyanka"
    ],
    "name:nor_x_preferred":[
        "Vesnjanka"
    ],
    "name:rus_x_preferred":[
        "\u0412\u0435\u0441\u043d\u044f\u043d\u043a\u0430"
    ],
    "wof:name":"Vesnyanka",
    "wof:placetype":"locality"
},
  "geometry": {"coordinates":[78.12626,55.54702],"type":"Point"}
}