{
  "type": "Feature",
  "properties": {
    "gn:admin1_code":"33",
    "gn:asciiname":"Pessemer'",
    "gn:country_code":"RU",
    "gn:dem":130,
    "gn:feature_class":"P",
    "gn:feature_code":"PPL",
    "gn:name":"Pessemer\u2019",
    "gn:population":0,
    "gn:timezone":"Europe/Kirov",
    "iso:country":"RU",
    "name:rus_x_preferred":[
        "\u041f\u0435\u0441\u0441\u0435\u043c\u0435\u0440\u044c"
    ],
    "name:und_x_variant":[
        "Pesimer\u2019",
        "Pesemer\u2019",
        "Pessemer\u2019",
        "\u041f\u0435\u0441\u0441\u0435\u043c\u0435\u0440\u044c"
    ],
    "wof:name":"Pessemer'",
    "wof:placetype":"locality"
},
  "geometry": {"coordinates":[49.246,57.2333],"type":"Point"}
}