{
  "type": "Feature",
  "properties": {
    "gn:admin1_code":"10",
    "gn:asciiname":"Bor",
    "gn:country_code":"RU",
    "gn:dem":159,
    "gn:feature_class":"P",
    "gn:feature_code":"PPL",
    "gn:name":"Bor",
    "gn:population":0,
    "gn:timezone":"Europe/Moscow",
    "iso:country":"RU",
    "name:rus_x_preferred":[
        "\u0411\u043e\u0440"
    ],
    "name:und_x_variant":[
        "\u0411\u043e\u0440",
        "Krasnyy Bor"
    ],
    "wof:name":"Bor",
    "wof:placetype":"locality"
},
  "geometry": {"coordinates":[33.86375,52.34354],"type":"Point"}
}