{
  "type": "Feature",
  "properties": {
    "gn:admin1_code":"60",
    "gn:asciiname":"Izrakino",
    "gn:country_code":"RU",
    "gn:dem":121,
    "gn:feature_class":"P",
    "gn:feature_code":"PPL",
    "gn:name":"Izrakino",
    "gn:population":0,
    "gn:timezone":"Europe/Moscow",
    "iso:country":"RU",
    "name:rus_x_preferred":[
        "\u0418\u0437\u0440\u0430\u043a\u0438\u043d\u043e"
    ],
    "wof:name":"Izrakino",
    "wof:placetype":"locality"
},
  "geometry": {"coordinates":[30.10028,56.39083],"type":"Point"}
}