{
  "type": "Feature",
  "properties": {
    "gn:admin1_code":"69",
    "gn:asciiname":"Nizhnyaya Yasennaya",
    "gn:cc2":"RU",
    "gn:country_code":"RU",
    "gn:dem":168,
    "gn:feature_class":"P",
    "gn:feature_code":"PPL",
    "gn:name":"Nizhnyaya Yasennaya",
    "gn:population":0,
    "gn:timezone":"Europe/Moscow",
    "iso:country":"RU",
    "name:rus_x_preferred":[
        "\u041d\u0438\u0436\u043d\u044f\u044f \u042f\u0441\u0435\u043d\u043d\u0430\u044f"
    ],
    "name:und_x_variant":[
        "Novo-Yasennaya",
        "Nizhnyaya Yasennaya"
    ],
    "wof:name":"Nizhnyaya Yasennaya",
    "wof:placetype":"locality"
},
  "geometry": {"coordinates":[31.96667,54.78333000000001],"type":"Point"}
}