{
  "type": "Feature",
  "properties": {
    "gn:admin1_code":"17.0",
    "gn:asciiname":"Kyurek",
    "gn:country_code":"RU",
    "gn:dem":1048,
    "gn:feature_class":"P",
    "gn:feature_code":"PPL",
    "gn:name":"Kyurek",
    "gn:population":0,
    "gn:timezone":"Europe/Moscow",
    "iso:country":"RU",
    "name:rus_x_preferred":[
        "\u041a\u044e\u0440\u0435\u043a"
    ],
    "name:und_x_variant":[
        "Kuregrik",
        "Kyurek"
    ],
    "wof:name":"Kyurek",
    "wof:placetype":"locality"
},
  "geometry": {"coordinates":[47.85934,41.95258],"type":"Point"}
}