{
  "type": "Feature",
  "properties": {
    "gn:admin1_code":"90.0",
    "gn:asciiname":"Ageyevo",
    "gn:country_code":"RU",
    "gn:dem":233,
    "gn:feature_class":"P",
    "gn:feature_code":"PPL",
    "gn:name":"Ageyevo",
    "gn:population":0,
    "gn:timezone":"Asia/Yekaterinburg",
    "iso:country":"RU",
    "name:rus_x_preferred":[
        "\u0410\u0433\u0435\u0435\u0432\u043e"
    ],
    "wof:name":"Ageyevo",
    "wof:placetype":"locality"
},
  "geometry": {"coordinates":[54.38509000000001,57.98065],"type":"Point"}
}