{
  "type": "Feature",
  "properties": {
    "gn:admin1_code":"53",
    "gn:asciiname":"Verkhniy Suzun",
    "gn:country_code":"RU",
    "gn:dem":234,
    "gn:feature_class":"P",
    "gn:feature_code":"PPL",
    "gn:name":"Verkhniy Suzun",
    "gn:population":0,
    "gn:timezone":"Asia/Novosibirsk",
    "iso:country":"RU",
    "wof:name":"Verkhniy Suzun",
    "wof:placetype":"locality"
},
  "geometry": {"coordinates":[82.73333000000002,54.13333000000001],"type":"Point"}
}