{
  "type": "Feature",
  "properties": {
    "gn:admin1_code":"78",
    "gn:asciiname":"Shipakova",
    "gn:country_code":"RU",
    "gn:dem":121,
    "gn:feature_class":"P",
    "gn:feature_code":"PPL",
    "gn:name":"Shipakova",
    "gn:population":0,
    "gn:timezone":"Asia/Yekaterinburg",
    "iso:country":"RU",
    "name:eng_x_preferred":[
        "Shipakova"
    ],
    "name:nor_x_preferred":[
        "Sjipakovo"
    ],
    "name:rus_x_preferred":[
        "\u0428\u0438\u043f\u0430\u043a\u043e\u0432\u043e"
    ],
    "name:rus_x_variant":[
        "\u0428\u0438\u043f\u0430\u043a\u043e\u0432\u0430"
    ],
    "name:und_x_variant":[
        "Shipakovo"
    ],
    "wof:name":"Shipakova",
    "wof:placetype":"locality"
},
  "geometry": {"coordinates":[67.63791999999999,56.84645],"type":"Point"}
}