{
  "type": "Feature",
  "properties": {
    "gn:admin1_code":"21.0",
    "gn:asciiname":"Solodikhino",
    "gn:country_code":"RU",
    "gn:dem":122,
    "gn:feature_class":"P",
    "gn:feature_code":"PPL",
    "gn:name":"Solodikhino",
    "gn:population":0,
    "gn:timezone":"Europe/Moscow",
    "iso:country":"RU",
    "name:nor_x_preferred":[
        "Solodikhino"
    ],
    "name:rus_x_preferred":[
        "\u0421\u043e\u043b\u043e\u0434\u0438\u0445\u0438\u043d\u043e"
    ],
    "wof:name":"Solodikhino",
    "wof:placetype":"locality"
},
  "geometry": {"coordinates":[42.79281,56.86276],"type":"Point"}
}