{
  "type": "Feature",
  "properties": {
    "gn:admin1_code":"84",
    "gn:asciiname":"Krasnopartizanskiy",
    "gn:country_code":"RU",
    "gn:dem":108,
    "gn:feature_class":"P",
    "gn:feature_code":"PPL",
    "gn:name":"Krasnopartizanskiy",
    "gn:population":0,
    "gn:timezone":"Europe/Volgograd",
    "iso:country":"RU",
    "name:rus_x_preferred":[
        "\u041a\u0440\u0430\u0441\u043d\u043e\u043f\u0430\u0440\u0442\u0438\u0437\u0430\u043d\u0441\u043a\u0438\u0439"
    ],
    "wof:name":"Krasnopartizanskiy",
    "wof:placetype":"locality"
},
  "geometry": {"coordinates":[44.25683,48.16597],"type":"Point"}
}