{
  "type": "Feature",
  "properties": {
    "gn:admin1_code":"55",
    "gn:asciiname":"Zhulamansay",
    "gn:country_code":"RU",
    "gn:dem":332,
    "gn:feature_class":"P",
    "gn:feature_code":"PPL",
    "gn:name":"Zhulamansay",
    "gn:population":0,
    "gn:timezone":"Asia/Yekaterinburg",
    "iso:country":"RU",
    "name:eng_x_preferred":[
        "Zhulamansay"
    ],
    "name:nor_x_preferred":[
        "Zjulamansaj"
    ],
    "name:rus_x_preferred":[
        "\u0416\u0443\u043b\u0430\u043c\u0430\u043d\u0441\u0430\u0439"
    ],
    "wof:name":"Zhulamansay",
    "wof:placetype":"locality"
},
  "geometry": {"coordinates":[59.5562,51.6941],"type":"Point"}
}