{
  "type": "Feature",
  "properties": {
    "gn:admin1_code":"80",
    "gn:asciiname":"Puzhmoil",
    "gn:country_code":"RU",
    "gn:dem":166,
    "gn:feature_class":"P",
    "gn:feature_code":"PPL",
    "gn:name":"Puzhmoil",
    "gn:population":0,
    "gn:timezone":"Europe/Samara",
    "iso:country":"RU",
    "name:rus_x_preferred":[
        "\u041f\u0443\u0436\u043c\u043e\u0438\u043b"
    ],
    "name:und_x_variant":[
        "Puzhma",
        "Puzhmoil",
        "\u041f\u0443\u0436\u043c\u043e\u0438\u043b"
    ],
    "wof:name":"Puzhmoil",
    "wof:placetype":"locality"
},
  "geometry": {"coordinates":[52.07549,56.79429],"type":"Point"}
}