{
  "type": "Feature",
  "properties": {
    "gn:admin1_code":"15",
    "gn:asciiname":"Vilyuneyskaya",
    "gn:cc2":"RU",
    "gn:country_code":"RU",
    "gn:dem":8,
    "gn:feature_class":"P",
    "gn:feature_code":"PPL",
    "gn:name":"Vilyuneyskaya",
    "gn:population":0,
    "gn:timezone":"Asia/Anadyr",
    "iso:country":"RU",
    "name:und_x_variant":[
        "Vilyuneyskaya Kul\u2019tbaza",
        "Vilyuneyskava Kul\u2019tbuza",
        "Vilyuneyskaya Kul\u2019tbuza",
        "Vilyuneyskay",
        "Vilyuneyskaya"
    ],
    "wof:name":"Vilyuneyskaya",
    "wof:placetype":"locality"
},
  "geometry": {"coordinates":[175.25,62.16667],"type":"Point"}
}