{
  "type": "Feature",
  "properties": {
    "gn:admin1_code":"23.0",
    "gn:asciiname":"Borskoye",
    "gn:country_code":"RU",
    "gn:dem":24,
    "gn:feature_class":"P",
    "gn:feature_code":"PPL",
    "gn:name":"Borskoye",
    "gn:population":0,
    "gn:timezone":"Europe/Kaliningrad",
    "iso:country":"RU",
    "name:eng_x_preferred":[
        "Borskoye"
    ],
    "name:nor_x_preferred":[
        "Borskoje"
    ],
    "name:rus_x_preferred":[
        "\u0411\u043e\u0440\u0441\u043a\u043e\u0435"
    ],
    "name:und_x_variant":[
        "Schiewenau",
        "Borskoe",
        "Shivenau",
        "\u0411\u043e\u0440\u0441\u043a\u043e\u0435",
        "Borskoye"
    ],
    "wof:name":"Borskoye",
    "wof:placetype":"locality"
},
  "geometry": {"coordinates":[20.96241,54.667],"type":"Point"}
}