{
  "type": "Feature",
  "properties": {
    "gn:admin1_code":"90",
    "gn:asciiname":"Pol'ko",
    "gn:country_code":"RU",
    "gn:dem":194,
    "gn:feature_class":"P",
    "gn:feature_code":"PPL",
    "gn:name":"Pol\u2019ko",
    "gn:population":0,
    "gn:timezone":"Asia/Yekaterinburg",
    "iso:country":"RU",
    "name:rus_x_preferred":[
        "\u041f\u043e\u043b\u044c\u043a\u043e"
    ],
    "name:und_x_variant":[
        "Pol\u2019ka",
        "Pol\u2019ko"
    ],
    "wof:name":"Pol'ko",
    "wof:placetype":"locality"
},
  "geometry": {"coordinates":[57.4218,57.0762],"type":"Point"}
}