{
  "type": "Feature",
  "properties": {
    "gn:admin1_code":"42",
    "gn:asciiname":"Razmetelevo",
    "gn:country_code":"RU",
    "gn:dem":56,
    "gn:feature_class":"P",
    "gn:feature_code":"PPL",
    "gn:name":"Razmetelevo",
    "gn:population":0,
    "gn:timezone":"Europe/Moscow",
    "iso:country":"RU",
    "name:fin_x_preferred":[
        "Rosmittala"
    ],
    "name:rus_x_preferred":[
        "\u0420\u0430\u0437\u043c\u0435\u0442\u0435\u043b\u0435\u0432\u043e"
    ],
    "name:und_x_variant":[
        "Razmitelevo",
        "Rozmitelevo",
        "Razmetelevo",
        "\u0420\u0430\u0437\u043c\u0435\u0442\u0435\u043b\u0435\u0432\u043e"
    ],
    "wof:name":"Razmetelevo",
    "wof:placetype":"locality"
},
  "geometry": {"coordinates":[30.67514000000001,59.90038000000001],"type":"Point"}
}