{
  "type": "Feature",
  "properties": {
    "gn:admin1_code":"13",
    "gn:asciiname":"Biryukovskiy",
    "gn:cc2":"RU",
    "gn:country_code":"RU",
    "gn:dem":267,
    "gn:feature_class":"P",
    "gn:feature_code":"PPL",
    "gn:name":"Biryukovskiy",
    "gn:population":0,
    "gn:timezone":"Asia/Yekaterinburg",
    "iso:country":"RU",
    "name:eng_x_preferred":[
        "Biryukovskiy"
    ],
    "name:rus_x_preferred":[
        "\u0411\u0438\u0440\u044e\u043a\u043e\u0432\u0441\u043a\u0430\u044f"
    ],
    "name:rus_x_variant":[
        "\u0411\u0438\u0440\u044e\u043a\u043e\u0432\u0441\u043a\u0438\u0439"
    ],
    "name:und_x_variant":[
        "Beryukovka",
        "Biryukovka"
    ],
    "wof:name":"Biryukovskiy",
    "wof:placetype":"locality"
},
  "geometry": {"coordinates":[60.24222,54.14139],"type":"Point"}
}