{
  "type": "Feature",
  "properties": {
    "gn:admin1_code":"25.0",
    "gn:asciiname":"Poselok Koshnyaki",
    "gn:country_code":"RU",
    "gn:dem":206,
    "gn:feature_class":"P",
    "gn:feature_code":"PPL",
    "gn:name":"Pos\u00eblok Koshnyaki",
    "gn:population":0,
    "gn:timezone":"Europe/Moscow",
    "iso:country":"RU",
    "name:rus_x_preferred":[
        "\u041f\u043e\u0441\u0451\u043b\u043e\u043a \u041a\u043e\u0448\u043d\u044f\u043a\u0438"
    ],
    "name:und_x_variant":[
        "Pos\u00eblok Koshnyaki"
    ],
    "wof:name":"Poselok Koshnyaki",
    "wof:placetype":"locality"
},
  "geometry": {"coordinates":[35.47124,54.95145],"type":"Point"}
}