{
  "type": "Feature",
  "properties": {
    "gn:admin1_code":"73",
    "gn:asciiname":"Malaya Chegodayka",
    "gn:country_code":"RU",
    "gn:dem":98,
    "gn:feature_class":"P",
    "gn:feature_code":"PPL",
    "gn:name":"Malaya Chegodayka",
    "gn:population":0,
    "gn:timezone":"Europe/Moscow",
    "iso:country":"RU",
    "name:rus_x_preferred":[
        "\u041c\u0430\u043b\u0430\u044f \u0427\u0435\u0433\u043e\u0434\u0430\u0439\u043a\u0430"
    ],
    "wof:name":"Malaya Chegodayka",
    "wof:placetype":"locality"
},
  "geometry": {"coordinates":[51.5397,54.652],"type":"Point"}
}