{
  "type": "Feature",
  "properties": {
    "gn:admin1_code":"6",
    "gn:asciiname":"Zhukova",
    "gn:country_code":"RU",
    "gn:dem":32,
    "gn:feature_class":"P",
    "gn:feature_code":"PPL",
    "gn:name":"Zhukova",
    "gn:population":0,
    "gn:timezone":"Europe/Moscow",
    "iso:country":"RU",
    "name:rus_x_preferred":[
        "\u0416\u0443\u043a\u043e\u0432\u0430"
    ],
    "name:und_x_variant":[
        "Zhukogorskoye",
        "Zhukovo",
        "Zhukova"
    ],
    "wof:name":"Zhukova",
    "wof:placetype":"locality"
},
  "geometry": {"coordinates":[44.7208,65.5339],"type":"Point"}
}