{
  "type": "Feature",
  "properties": {
    "gn:admin1_code":"76",
    "gn:asciiname":"Kaverino",
    "gn:country_code":"RU",
    "gn:dem":208,
    "gn:feature_class":"P",
    "gn:feature_code":"PPL",
    "gn:name":"Kaverino",
    "gn:population":0,
    "gn:timezone":"Europe/Moscow",
    "iso:country":"RU",
    "name:rus_x_preferred":[
        "\u041a\u0430\u0432\u0435\u0440\u0438\u043d\u043e"
    ],
    "wof:name":"Kaverino",
    "wof:placetype":"locality"
},
  "geometry": {"coordinates":[37.77062,54.71189],"type":"Point"}
}