{
  "type": "Feature",
  "properties": {
    "gn:admin1_code":"34",
    "gn:asciiname":"Shilovskaya",
    "gn:country_code":"RU",
    "gn:dem":116,
    "gn:feature_class":"P",
    "gn:feature_code":"PPL",
    "gn:name":"Shilovskaya",
    "gn:population":0,
    "gn:timezone":"Europe/Moscow",
    "iso:country":"RU",
    "name:rus_x_preferred":[
        "\u0428\u0438\u043b\u043e\u0432\u0441\u043a\u0430\u044f"
    ],
    "name:und_x_variant":[
        "\u0428\u0438\u043b\u043e\u0432\u0441\u043a\u0430\u044f"
    ],
    "wof:name":"Shilovskaya",
    "wof:placetype":"locality"
},
  "geometry": {"coordinates":[49.03333,60.63333000000001],"type":"Point"}
}