{
  "type": "Feature",
  "properties": {
    "gn:admin1_code":"60",
    "gn:asciiname":"Soplinovo",
    "gn:country_code":"RU",
    "gn:dem":154,
    "gn:feature_class":"P",
    "gn:feature_code":"PPL",
    "gn:name":"Soplinovo",
    "gn:population":0,
    "gn:timezone":"Europe/Moscow",
    "iso:country":"RU",
    "name:rus_x_preferred":[
        "\u0421\u043e\u043f\u043b\u0438\u043d\u043e\u0432\u043e"
    ],
    "wof:name":"Soplinovo",
    "wof:placetype":"locality"
},
  "geometry": {"coordinates":[30.61667000000001,56.01667],"type":"Point"}
}