{
  "type": "Feature",
  "properties": {
    "gn:admin1_code":"91",
    "gn:asciiname":"Kedrovka",
    "gn:country_code":"RU",
    "gn:dem":222,
    "gn:feature_class":"P",
    "gn:feature_code":"PPL",
    "gn:name":"Kedrovka",
    "gn:population":0,
    "gn:timezone":"Asia/Krasnoyarsk",
    "iso:country":"RU",
    "name:rus_x_preferred":[
        "\u041a\u0435\u0434\u0440\u043e\u0432\u043a\u0430"
    ],
    "wof:name":"Kedrovka",
    "wof:placetype":"locality"
},
  "geometry": {"coordinates":[89.72278,56.55333],"type":"Point"}
}