{
  "type": "Feature",
  "properties": {
    "gn:admin1_code":"56",
    "gn:asciiname":"Zolotoye Dno",
    "gn:country_code":"RU",
    "gn:dem":228,
    "gn:feature_class":"P",
    "gn:feature_code":"PPL",
    "gn:name":"Zolotoye Dno",
    "gn:population":0,
    "gn:timezone":"Europe/Moscow",
    "iso:country":"RU",
    "name:rus_x_preferred":[
        "\u0417\u043e\u043b\u043e\u0442\u043e\u0435 \u0414\u043d\u043e"
    ],
    "wof:name":"Zolotoye Dno",
    "wof:placetype":"locality"
},
  "geometry": {"coordinates":[35.5084,52.4917],"type":"Point"}
}