{
  "type": "Feature",
  "properties": {
    "gn:admin1_code":"42",
    "gn:asciiname":"Khapo-Oye",
    "gn:country_code":"RU",
    "gn:dem":40,
    "gn:feature_class":"P",
    "gn:feature_code":"PPL",
    "gn:name":"Khapo-Oye",
    "gn:population":0,
    "gn:timezone":"Europe/Moscow",
    "iso:country":"RU",
    "name:fin_x_preferred":[
        "Haapoja"
    ],
    "name:rus_x_preferred":[
        "\u0425\u0430\u043f\u043e-\u041e\u0435"
    ],
    "name:und_x_variant":[
        "Khaboye",
        "Khapo-Oye",
        "\u0425\u0430\u043f\u043e-\u041e\u0435"
    ],
    "wof:name":"Khapo-Oye",
    "wof:placetype":"locality"
},
  "geometry": {"coordinates":[30.75481,59.88146999999999],"type":"Point"}
}