{
  "type": "Feature",
  "properties": {
    "gn:admin1_code":"33.0",
    "gn:asciiname":"Bol'shaya Korotayevshchina",
    "gn:country_code":"RU",
    "gn:dem":201,
    "gn:feature_class":"P",
    "gn:feature_code":"PPL",
    "gn:name":"Bol\u2019shaya Korotayevshchina",
    "gn:population":0,
    "gn:timezone":"Europe/Kirov",
    "iso:country":"RU",
    "name:rus_x_preferred":[
        "\u0411\u043e\u043b\u044c\u0448\u0430\u044f \u041a\u043e\u0440\u043e\u0442\u0430\u0435\u0432\u0449\u0438\u043d\u0430"
    ],
    "name:und_x_variant":[
        "Bol\u2019shaya Korotayevshchina",
        "\u0411\u043e\u043b\u044c\u0448\u0430\u044f \u041a\u043e\u0440\u043e\u0442\u0430\u0435\u0432\u0449\u0438\u043d\u0430"
    ],
    "wof:name":"Bol'shaya Korotayevshchina",
    "wof:placetype":"locality"
},
  "geometry": {"coordinates":[48.47778,59.14518],"type":"Point"}
}