{
  "type": "Feature",
  "properties": {
    "gn:admin1_code":"46",
    "gn:asciiname":"Mizeryane",
    "gn:country_code":"RU",
    "gn:dem":168,
    "gn:feature_class":"P",
    "gn:feature_code":"PPL",
    "gn:name":"Mizeryane",
    "gn:population":0,
    "gn:timezone":"Europe/Moscow",
    "iso:country":"RU",
    "name:rus_x_preferred":[
        "\u041c\u0438\u0437\u0435\u0440\u044f\u043d\u0435"
    ],
    "name:und_x_variant":[
        "Mizeryan\u2019",
        "Mizeryane"
    ],
    "wof:name":"Mizeryane",
    "wof:placetype":"locality"
},
  "geometry": {"coordinates":[44.64354,54.28027],"type":"Point"}
}