{
  "type": "Feature",
  "properties": {
    "gn:admin1_code":"20",
    "gn:asciiname":"Cheremshanka",
    "gn:country_code":"RU",
    "gn:dem":373,
    "gn:feature_class":"P",
    "gn:feature_code":"PPL",
    "gn:name":"Cheremshanka",
    "gn:population":0,
    "gn:timezone":"Asia/Irkutsk",
    "iso:country":"RU",
    "name:ceb_x_preferred":[
        "\u0427\u0435\u0440\u0435\u043c\u0448\u0430\u043d\u043a\u0430"
    ],
    "name:eng_x_preferred":[
        "Cheremshanka"
    ],
    "name:hye_x_preferred":[
        "\u0549\u0565\u0580\u0565\u0574\u0577\u0561\u0576\u056f\u0561"
    ],
    "name:kaz_x_preferred":[
        "\u0427\u0435\u0440\u0435\u043c\u0448\u0430\u043d\u043a\u0430"
    ],
    "name:nor_x_preferred":[
        "Tsjeremsjanka"
    ],
    "name:rus_x_preferred":[
        "\u0427\u0435\u0440\u0435\u043c\u0448\u0430\u043d\u043a\u0430"
    ],
    "name:ukr_x_preferred":[
        "\u0427\u0435\u0440\u0435\u043c\u0448\u0430\u043d\u043a\u0430"
    ],
    "wof:name":"Cheremshanka",
    "wof:placetype":"locality"
},
  "geometry": {"coordinates":[97.4781,56.0976],"type":"Point"}
}