{
  "type": "Feature",
  "properties": {
    "gn:admin1_code":"33.0",
    "gn:asciiname":"Yarovtsy",
    "gn:country_code":"RU",
    "gn:dem":141,
    "gn:feature_class":"P",
    "gn:feature_code":"PPL",
    "gn:name":"Yarovtsy",
    "gn:population":0,
    "gn:timezone":"Europe/Kirov",
    "iso:country":"RU",
    "name:rus_x_preferred":[
        "\u042f\u0440\u043e\u0432\u0446\u044b"
    ],
    "wof:name":"Yarovtsy",
    "wof:placetype":"locality"
},
  "geometry": {"coordinates":[48.19098,58.27077],"type":"Point"}
}