{
  "type": "Feature",
  "properties": {
    "gn:admin1_code":"90",
    "gn:asciiname":"Verkhnyaya Davydovka",
    "gn:country_code":"RU",
    "gn:dem":128,
    "gn:feature_class":"P",
    "gn:feature_code":"PPL",
    "gn:name":"Verkhnyaya Davydovka",
    "gn:population":0,
    "gn:timezone":"Asia/Yekaterinburg",
    "iso:country":"RU",
    "name:rus_x_preferred":[
        "\u0412\u0435\u0440\u0445\u043d\u044f\u044f \u0414\u0430\u0432\u044b\u0434\u043e\u0432\u043a\u0430"
    ],
    "wof:name":"Verkhnyaya Davydovka",
    "wof:placetype":"locality"
},
  "geometry": {"coordinates":[55.3264,57.3443],"type":"Point"}
}