{
  "type": "Feature",
  "properties": {
    "gn:admin1_code":"54",
    "gn:asciiname":"Zhar-Agach",
    "gn:country_code":"RU",
    "gn:dem":87,
    "gn:feature_class":"P",
    "gn:feature_code":"PPL",
    "gn:name":"Zhar-Agach",
    "gn:population":0,
    "gn:timezone":"Asia/Omsk",
    "iso:country":"RU",
    "name:eng_x_preferred":[
        "Zhar-Agach"
    ],
    "name:nor_x_preferred":[
        "Zjaragatsj"
    ],
    "name:rus_x_preferred":[
        "\u0416\u0430\u0440\u0430\u0433\u0430\u0447"
    ],
    "name:rus_x_variant":[
        "\u0416\u0430\u0440-\u0410\u0433\u0430\u0447"
    ],
    "name:und_x_variant":[
        "\u0416\u0430\u0440-\u0410\u0433\u0430\u0447"
    ],
    "wof:name":"Zhar-Agach",
    "wof:placetype":"locality"
},
  "geometry": {"coordinates":[74.51536999999998,54.3642],"type":"Point"}
}