{
  "type": "Feature",
  "properties": {
    "gn:admin1_code":"23",
    "gn:asciiname":"Vasil'kovo",
    "gn:country_code":"RU",
    "gn:dem":19,
    "gn:feature_class":"P",
    "gn:feature_code":"PPL",
    "gn:name":"Vasil\u2019kovo",
    "gn:population":0,
    "gn:timezone":"Europe/Kaliningrad",
    "iso:country":"RU",
    "name:und_x_variant":[
        "Kerschnehnen",
        "Vasil\u2019kovo"
    ],
    "wof:name":"Vasil'kovo",
    "wof:placetype":"locality"
},
  "geometry": {"coordinates":[20.40101,54.8905],"type":"Point"}
}