{
  "type": "Feature",
  "properties": {
    "gn:admin1_code":"69",
    "gn:asciiname":"Shen'kovka",
    "gn:country_code":"RU",
    "gn:dem":187,
    "gn:feature_class":"P",
    "gn:feature_code":"PPL",
    "gn:name":"Shen\u2019kovka",
    "gn:population":0,
    "gn:timezone":"Europe/Moscow",
    "iso:country":"RU",
    "name:rus_x_preferred":[
        "\u0428\u0435\u043d\u044c\u043a\u043e\u0432\u043a\u0430"
    ],
    "name:und_x_variant":[
        "Shen\u2019kovka"
    ],
    "wof:name":"Shen'kovka",
    "wof:placetype":"locality"
},
  "geometry": {"coordinates":[31.99959,54.22612],"type":"Point"}
}