{
  "type": "Feature",
  "properties": {
    "gn:admin1_code":"61",
    "gn:asciiname":"Sukhosarmatka",
    "gn:country_code":"RU",
    "gn:dem":45,
    "gn:feature_class":"P",
    "gn:feature_code":"PPL",
    "gn:name":"Sukhosarmatka",
    "gn:population":0,
    "gn:timezone":"Europe/Moscow",
    "iso:country":"RU",
    "name:rus_x_preferred":[
        "\u0421\u0443\u0445\u043e\u0441\u0430\u0440\u043c\u0430\u0442\u043a\u0430"
    ],
    "name:und_x_variant":[
        "Sukhosarmatskiy",
        "Sukhosarmatka"
    ],
    "wof:name":"Sukhosarmatka",
    "wof:placetype":"locality"
},
  "geometry": {"coordinates":[38.79002,47.31767],"type":"Point"}
}