{
  "type": "Feature",
  "properties": {
    "gn:admin1_code":"83.0",
    "gn:asciiname":"Teremets",
    "gn:country_code":"RU",
    "gn:dem":160,
    "gn:feature_class":"P",
    "gn:feature_code":"PPL",
    "gn:name":"Teremets",
    "gn:population":0,
    "gn:timezone":"Europe/Moscow",
    "iso:country":"RU",
    "name:rus_x_preferred":[
        "\u0422\u0435\u0440\u0435\u043c\u0435\u0446"
    ],
    "wof:name":"Teremets",
    "wof:placetype":"locality"
},
  "geometry": {"coordinates":[40.17568,56.26065],"type":"Point"}
}