{
  "type": "Feature",
  "properties": {
    "gn:admin1_code":"30",
    "gn:asciiname":"Kukhtuy",
    "gn:cc2":"RU",
    "gn:country_code":"RU",
    "gn:dem":43,
    "gn:feature_class":"P",
    "gn:feature_code":"PPL",
    "gn:name":"Kukhtuy",
    "gn:population":0,
    "gn:timezone":"Asia/Vladivostok",
    "iso:country":"RU",
    "name:eng_x_preferred":[
        "Kukhtuy"
    ],
    "name:nor_x_preferred":[
        "Kukhtuj"
    ],
    "name:rus_x_preferred":[
        "\u041a\u0443\u0445\u0442\u0443\u0439"
    ],
    "name:und_x_variant":[
        "Kukhtuyskaya Gruppa",
        "\u041a\u0443\u0445\u0442\u0443\u0439",
        "Kukhtuy"
    ],
    "wof:name":"Kukhtuy",
    "wof:placetype":"locality"
},
  "geometry": {"coordinates":[143.09999999999999,59.63333000000001],"type":"Point"}
}