{
  "type": "Feature",
  "properties": {
    "gn:admin1_code":"30",
    "gn:asciiname":"Kukhtuy",
    "gn:cc2":"RU",
    "gn:country_code":"RU",
    "gn:dem":43,
    "gn:feature_class":"P",
    "gn:feature_code":"PPL",
    "gn:name":"Kukhtuy",
    "gn:population":0,
    "gn:timezone":"Asia/Vladivostok",
    "iso:country":"RU",
    "name:ara_x_preferred":[
        "\u0643\u0648\u0643\u062a\u064a"
    ],
    "name:ben_x_preferred":[
        "\u0995\u09c1\u0996\u09a4\u09c1\u09df"
    ],
    "name:ell_x_preferred":[
        "\u039a\u03bf\u03c5\u03c7\u03c4\u03bf\u03cd\u03b9"
    ],
    "name:eng_x_preferred":[
        "Kukhtuy"
    ],
    "name:fas_x_preferred":[
        "\u06a9\u0648\u062e\u062a\u0648\u06cc"
    ],
    "name:fra_x_preferred":[
        "Kukhtuy"
    ],
    "name:heb_x_preferred":[
        "\u05e7\u05d5\u05d7\u05d8\u05d5\u05d9"
    ],
    "name:hin_x_preferred":[
        "\u0915\u0941\u0916\u094d\u0924\u0941\u092f\u0942"
    ],
    "name:hun_x_preferred":[
        "Kukhtuy"
    ],
    "name:ind_x_preferred":[
        "Kukhtuy"
    ],
    "name:jpn_x_preferred":[
        "\u30af\u30d5\u30c8\u30a5\u30a4\u5ddd"
    ],
    "name:kor_x_preferred":[
        "\ucfe0\ud06c\ud22c\uc774"
    ],
    "name:nor_x_preferred":[
        "Kukhtuj"
    ],
    "name:pol_x_preferred":[
        "Kukhtuy"
    ],
    "name:por_x_preferred":[
        "Kukhtuy"
    ],
    "name:rus_x_preferred":[
        "\u041a\u0443\u0445\u0442\u0443\u0439"
    ],
    "name:spa_x_preferred":[
        "Kukhtuy"
    ],
    "name:swe_x_preferred":[
        "Kukhtuy"
    ],
    "name:tur_x_preferred":[
        "Kukhtuy"
    ],
    "name:ukr_x_preferred":[
        "\u041a\u0443\u0445\u0442\u0443\u0439"
    ],
    "name:und_x_variant":[
        "Kukhtuyskaya Gruppa"
    ],
    "name:urd_x_preferred":[
        "\u06a9\u0648\u06a9\u06be\u0679\u0627\u0626\u06d2"
    ],
    "name:vie_x_preferred":[
        "S\u00f4ng Kukhtuy"
    ],
    "wof:name":"Kukhtuy",
    "wof:placetype":"locality"
},
  "geometry": {"coordinates":[143.09999999999999,59.63333],"type":"Point"}
}