{
  "type": "Feature",
  "properties": {
    "gn:admin1_code":"61",
    "gn:asciiname":"Manych",
    "gn:country_code":"RU",
    "gn:dem":36,
    "gn:feature_class":"P",
    "gn:feature_code":"PPL",
    "gn:name":"Manych",
    "gn:population":0,
    "gn:timezone":"Europe/Moscow",
    "iso:country":"RU",
    "name:eng_x_preferred":[
        "Manych"
    ],
    "name:nor_x_preferred":[
        "Manytsj"
    ],
    "name:rus_x_preferred":[
        "\u041c\u0430\u043d\u044b\u0447"
    ],
    "name:und_x_variant":[
        "Gryazelechebnitsa",
        "\u041c\u0430\u043d\u044b\u0447",
        "Manych"
    ],
    "wof:name":"Manych",
    "wof:placetype":"locality"
},
  "geometry": {"coordinates":[42.7133,46.4325],"type":"Point"}
}