{
  "type": "Feature",
  "properties": {
    "gn:admin1_code":"54",
    "gn:asciiname":"Bel'dezh Nomer Dvenadtsat'",
    "gn:country_code":"RU",
    "gn:dem":116,
    "gn:feature_class":"P",
    "gn:feature_code":"PPL",
    "gn:name":"Bel\u2019dezh Nomer Dvenadtsat\u2019",
    "gn:population":0,
    "gn:timezone":"Asia/Omsk",
    "iso:country":"RU",
    "name:nor_x_preferred":[
        "Beldezj Nomer Dvenadtsat"
    ],
    "name:rus_x_preferred":[
        "\u0411\u0435\u043b\u044c\u0434\u0435\u0436 \u041d\u043e\u043c\u0435\u0440 \u0414\u0432\u0435\u043d\u0430\u0434\u0446\u0430\u0442\u044c"
    ],
    "name:und_x_variant":[
        "Bel\u2019dezh Nomer Dvenadtsat",
        "Bel\u2019dezh Nomer Dvenadtsat\u2019"
    ],
    "wof:name":"Bel'dezh Nomer Dvenadtsat'",
    "wof:placetype":"locality"
},
  "geometry": {"coordinates":[71.88389000000002,54.39225],"type":"Point"}
}