{
  "type": "Feature",
  "properties": {
    "gn:admin1_code":"86",
    "gn:asciiname":"Poddubnoye",
    "gn:country_code":"RU",
    "gn:dem":111,
    "gn:feature_class":"P",
    "gn:feature_code":"PPL",
    "gn:name":"Poddubnoye",
    "gn:population":0,
    "gn:timezone":"Europe/Moscow",
    "iso:country":"RU",
    "name:eng_x_preferred":[
        "Poddubnaya"
    ],
    "name:nor_x_preferred":[
        "Poddubnoje"
    ],
    "name:rus_x_preferred":[
        "\u041f\u043e\u0434\u0434\u0443\u0431\u043d\u043e\u0435"
    ],
    "name:rus_x_variant":[
        "\u041f\u043e\u0434\u0434\u0443\u0431\u043d\u0430\u044f"
    ],
    "wof:name":"Poddubnoye",
    "wof:placetype":"locality"
},
  "geometry": {"coordinates":[39.3774,49.89985],"type":"Point"}
}