{
  "type": "Feature",
  "properties": {
    "gn:admin1_code":"69",
    "gn:asciiname":"Melekhovo",
    "gn:country_code":"RU",
    "gn:dem":192,
    "gn:feature_class":"P",
    "gn:feature_code":"PPL",
    "gn:name":"Melekhovo",
    "gn:population":0,
    "gn:timezone":"Europe/Moscow",
    "iso:country":"RU",
    "name:rus_x_preferred":[
        "\u041c\u0435\u043b\u0435\u0445\u043e\u0432\u043e"
    ],
    "name:und_x_variant":[
        "\u041c\u0435\u043b\u0435\u0445\u043e\u0432\u043e",
        "Melekhova"
    ],
    "wof:name":"Melekhovo",
    "wof:placetype":"locality"
},
  "geometry": {"coordinates":[34.77304,55.65086],"type":"Point"}
}