{
  "type": "Feature",
  "properties": {
    "gn:admin1_code":"76",
    "gn:asciiname":"Shchepot'yevo",
    "gn:country_code":"RU",
    "gn:dem":205,
    "gn:feature_class":"P",
    "gn:feature_code":"PPL",
    "gn:name":"Shchepot\u2019yevo",
    "gn:population":0,
    "gn:timezone":"Europe/Moscow",
    "iso:country":"RU",
    "name:rus_x_preferred":[
        "\u0429\u0435\u043f\u043e\u0442\u044c\u0435\u0432\u043e"
    ],
    "name:und_x_variant":[
        "Shchepot\u2019yevo"
    ],
    "wof:name":"Shchepot'yevo",
    "wof:placetype":"locality"
},
  "geometry": {"coordinates":[37.29898,54.534],"type":"Point"}
}