{
  "type": "Feature",
  "properties": {
    "gn:admin1_code":"81",
    "gn:asciiname":"Novyy Uren'",
    "gn:country_code":"RU",
    "gn:dem":126,
    "gn:feature_class":"P",
    "gn:feature_code":"PPL",
    "gn:name":"Novyy Uren\u2019",
    "gn:population":0,
    "gn:timezone":"Europe/Ulyanovsk",
    "iso:country":"RU",
    "name:eng_x_preferred":[
        "Novyy Uren'"
    ],
    "name:nor_x_preferred":[
        "Novyj Uren"
    ],
    "name:rus_x_preferred":[
        "\u041d\u043e\u0432\u044b\u0439 \u0423\u0440\u0435\u043d\u044c"
    ],
    "name:und_x_variant":[
        "Novy Uren\u2019",
        "Novyy Uren\u2019"
    ],
    "wof:name":"Novyy Uren'",
    "wof:placetype":"locality"
},
  "geometry": {"coordinates":[48.13671,54.42205],"type":"Point"}
}