{
  "type": "Feature",
  "properties": {
    "gn:admin1_code":"71",
    "gn:asciiname":"Novaya Tal'tiya",
    "gn:country_code":"RU",
    "gn:dem":213,
    "gn:feature_class":"P",
    "gn:feature_code":"PPL",
    "gn:name":"Novaya Tal\u2019tiya",
    "gn:population":0,
    "gn:timezone":"Asia/Yekaterinburg",
    "iso:country":"RU",
    "name:rus_x_preferred":[
        "\u041d\u043e\u0432\u0430\u044f \u0422\u0430\u043b\u044c\u0442\u0438\u044f"
    ],
    "name:und_x_variant":[
        "Novaya Tal\u2019tiya"
    ],
    "wof:name":"Novaya Tal'tiya",
    "wof:placetype":"locality"
},
  "geometry": {"coordinates":[60.06667,60.68333000000001],"type":"Point"}
}