{
  "type": "Feature",
  "properties": {
    "gn:admin1_code":"29",
    "gn:asciiname":"Kulebakino",
    "gn:country_code":"RU",
    "gn:dem":236,
    "gn:feature_class":"P",
    "gn:feature_code":"PPL",
    "gn:name":"Kulebakino",
    "gn:population":0,
    "gn:timezone":"Asia/Novokuznetsk",
    "iso:country":"RU",
    "name:eng_x_preferred":[
        "Kulebakino"
    ],
    "name:nor_x_preferred":[
        "Kulebakino"
    ],
    "name:rus_x_preferred":[
        "\u041a\u0443\u043b\u0435\u0431\u0430\u043a\u0438\u043d\u043e"
    ],
    "name:und_x_variant":[
        "Listvyazhkina",
        "\u041a\u0443\u043b\u0435\u0431\u0430\u043a\u0438\u043d\u043e",
        "Kulebakino"
    ],
    "wof:name":"Kulebakino",
    "wof:placetype":"locality"
},
  "geometry": {"coordinates":[85.8349,54.4108],"type":"Point"}
}