{
  "type": "Feature",
  "properties": {
    "gn:admin1_code":"8",
    "gn:asciiname":"Melekasovo",
    "gn:country_code":"RU",
    "gn:dem":222,
    "gn:feature_class":"P",
    "gn:feature_code":"PPL",
    "gn:name":"Melekasovo",
    "gn:population":0,
    "gn:timezone":"Asia/Yekaterinburg",
    "iso:country":"RU",
    "name:rus_x_preferred":[
        "\u041c\u0435\u043b\u0435\u043a\u0430\u0441\u043e\u0432\u043e"
    ],
    "name:und_x_variant":[
        "Melekes",
        "Melekasovo"
    ],
    "wof:name":"Melekasovo",
    "wof:placetype":"locality"
},
  "geometry": {"coordinates":[57.97657,55.92914],"type":"Point"}
}