{
  "type": "Feature",
  "properties": {
    "gn:admin1_code":"89.0",
    "gn:asciiname":"Solnechnaya",
    "gn:country_code":"RU",
    "gn:dem":476,
    "gn:feature_class":"P",
    "gn:feature_code":"PPL",
    "gn:name":"Solnechnaya",
    "gn:population":0,
    "gn:timezone":"Asia/Vladivostok",
    "iso:country":"RU",
    "name:rus_x_preferred":[
        "\u0421\u043e\u043b\u043d\u0435\u0447\u043d\u0430\u044f"
    ],
    "wof:name":"Solnechnaya",
    "wof:placetype":"locality"
},
  "geometry": {"coordinates":[131.73509000000001,49.23881],"type":"Point"}
}