{
  "type": "Feature",
  "properties": {
    "gn:admin1_code":"56",
    "gn:asciiname":"Volkonsk",
    "gn:country_code":"RU",
    "gn:dem":197,
    "gn:feature_class":"P",
    "gn:feature_code":"PPL",
    "gn:name":"Volkonsk",
    "gn:population":0,
    "gn:timezone":"Europe/Moscow",
    "iso:country":"RU",
    "name:rus_x_preferred":[
        "\u0412\u043e\u043b\u043a\u043e\u043d\u0441\u043a"
    ],
    "name:und_x_variant":[
        "Volkonskoye"
    ],
    "wof:name":"Volkonsk",
    "wof:placetype":"locality"
},
  "geometry": {"coordinates":[35.1468,52.5876],"type":"Point"}
}