{
  "type": "Feature",
  "properties": {
    "gn:admin1_code":"33",
    "gn:asciiname":"Zubtsovo",
    "gn:country_code":"RU",
    "gn:dem":96,
    "gn:feature_class":"P",
    "gn:feature_code":"PPL",
    "gn:name":"Zubtsovo",
    "gn:population":0,
    "gn:timezone":"Europe/Kirov",
    "iso:country":"RU",
    "name:rus_x_preferred":[
        "\u0417\u0443\u0431\u0446\u043e\u0432\u043e"
    ],
    "wof:name":"Zubtsovo",
    "wof:placetype":"locality"
},
  "geometry": {"coordinates":[47.30395,56.99788],"type":"Point"}
}