{
  "type": "Feature",
  "properties": {
    "gn:admin1_code":"80.0",
    "gn:asciiname":"Parzinskoye Sel'skoye Professional'no-tekhnicheskoye Uchilishche Nomer Sem'",
    "gn:country_code":"RU",
    "gn:dem":204,
    "gn:feature_class":"P",
    "gn:feature_code":"PPL",
    "gn:name":"Parzinskoye Sel\u2019skoye Professional\u2019no-tekhnicheskoye Uchilishche Nomer Sem\u2019",
    "gn:population":0,
    "gn:timezone":"Europe/Samara",
    "iso:country":"RU",
    "name:rus_x_preferred":[
        "\u041f\u0430\u0440\u0437\u0438\u043d\u0441\u043a\u043e\u0435 \u0421\u0435\u043b\u044c\u0441\u043a\u043e\u0435 \u041f\u0440\u043e\u0444\u0435\u0441\u0441\u0438\u043e\u043d\u0430\u043b\u044c\u043d\u043e-\u0442\u0435\u0445\u043d\u0438\u0447\u0435\u0441\u043a\u043e\u0435 \u0423\u0447\u0438\u043b\u0438\u0449\u0435 \u041d\u043e\u043c\u0435\u0440 \u0421\u0435\u043c\u044c"
    ],
    "name:und_x_variant":[
        "Parzinskoye Sel\u2019skoye Professional\u2019no-tekhnicheskoye Uchilishche Nomer Sem\u2019"
    ],
    "wof:name":"Parzinskoye Sel'skoye Professional'no-tekhnicheskoye Uchilishche Nomer Sem'",
    "wof:placetype":"locality"
},
  "geometry": {"coordinates":[52.5334,57.9096],"type":"Point"}
}