{
  "type": "Feature",
  "properties": {
    "gn:admin1_code":"53",
    "gn:asciiname":"Zhirnovka",
    "gn:country_code":"RU",
    "gn:dem":135,
    "gn:feature_class":"P",
    "gn:feature_code":"PPL",
    "gn:name":"Zhirnovka",
    "gn:population":0,
    "gn:timezone":"Asia/Novosibirsk",
    "iso:country":"RU",
    "name:eng_x_preferred":[
        "Zhirnovka"
    ],
    "name:nor_x_preferred":[
        "Zjirnovka"
    ],
    "name:rus_x_preferred":[
        "\u0416\u0438\u0440\u043d\u043e\u0432\u043a\u0430"
    ],
    "name:und_x_variant":[
        "\u0416\u0438\u0440\u043d\u043e\u0432\u043a\u0430",
        "Zhirnovka"
    ],
    "wof:name":"Zhirnovka",
    "wof:placetype":"locality"
},
  "geometry": {"coordinates":[81.9898,56.0457],"type":"Point"}
}