{
  "type": "Feature",
  "properties": {
    "gn:admin1_code":"24.0",
    "gn:asciiname":"Konnyy",
    "gn:country_code":"RU",
    "gn:dem":0,
    "gn:feature_class":"P",
    "gn:feature_code":"PPL",
    "gn:name":"Konnyy",
    "gn:population":0,
    "gn:timezone":"Europe/Moscow",
    "iso:country":"RU",
    "name:rus_x_preferred":[
        "\u041a\u043e\u043d\u043d\u044b\u0439"
    ],
    "name:und_x_variant":[
        "\u041a\u043e\u043d\u043d\u044b\u0439"
    ],
    "wof:name":"Konnyy",
    "wof:placetype":"locality"
},
  "geometry": {"coordinates":[45.15417,46.92611],"type":"Point"}
}