{
  "type": "Feature",
  "properties": {
    "gn:admin1_code":"88",
    "gn:asciiname":"Panteleyevo",
    "gn:country_code":"RU",
    "gn:dem":146,
    "gn:feature_class":"P",
    "gn:feature_code":"PPL",
    "gn:name":"Panteleyevo",
    "gn:population":0,
    "gn:timezone":"Europe/Moscow",
    "iso:country":"RU",
    "name:rus_x_preferred":[
        "\u041f\u0430\u043d\u0442\u0435\u043b\u0435\u0435\u0432\u043e"
    ],
    "name:und_x_variant":[
        "Panteleyero",
        "Panteleyevo",
        "\u041f\u0430\u043d\u0442\u0435\u043b\u0435\u0435\u0432\u043e"
    ],
    "wof:name":"Panteleyevo",
    "wof:placetype":"locality"
},
  "geometry": {"coordinates":[37.55565,57.81807],"type":"Point"}
}