{
  "type": "Feature",
  "properties": {
    "gn:admin1_code":"76.0",
    "gn:asciiname":"Veselevo",
    "gn:country_code":"RU",
    "gn:dem":155,
    "gn:feature_class":"P",
    "gn:feature_code":"PPL",
    "gn:name":"Veselevo",
    "gn:population":0,
    "gn:timezone":"Europe/Moscow",
    "iso:country":"RU",
    "name:und_x_variant":[
        "Veselovo",
        "Veselevo"
    ],
    "wof:name":"Veselevo",
    "wof:placetype":"locality"
},
  "geometry": {"coordinates":[37.26693,54.78754],"type":"Point"}
}