{
  "type": "Feature",
  "properties": {
    "gn:admin1_code":"16",
    "gn:asciiname":"Izambayevo",
    "gn:country_code":"RU",
    "gn:dem":185,
    "gn:feature_class":"P",
    "gn:feature_code":"PPL",
    "gn:name":"Izambayevo",
    "gn:population":0,
    "gn:timezone":"Europe/Moscow",
    "iso:country":"RU",
    "name:rus_x_preferred":[
        "\u0418\u0437\u0430\u043c\u0431\u0430\u0435\u0432\u043e"
    ],
    "name:und_x_variant":[
        "\u0418\u0437\u0430\u043c\u0431\u0430\u0435\u0432\u043e"
    ],
    "wof:name":"Izambayevo",
    "wof:placetype":"locality"
},
  "geometry": {"coordinates":[46.4417,56.0144],"type":"Point"}
}