{
  "type": "Feature",
  "properties": {
    "gn:admin1_code":"68.0",
    "gn:asciiname":"Saurkh",
    "gn:country_code":"RU",
    "gn:dem":2409,
    "gn:feature_class":"P",
    "gn:feature_code":"PPL",
    "gn:name":"Saurkh",
    "gn:population":0,
    "gn:timezone":"Europe/Moscow",
    "iso:country":"RU",
    "wof:name":"Saurkh",
    "wof:placetype":"locality"
},
  "geometry": {"coordinates":[44.16917,42.66111],"type":"Point"}
}