{
  "type": "Feature",
  "properties": {
    "gn:admin1_code":"20",
    "gn:asciiname":"Gogolin",
    "gn:cc2":"RU",
    "gn:country_code":"RU",
    "gn:dem":544,
    "gn:feature_class":"P",
    "gn:feature_code":"PPL",
    "gn:name":"Gogolin",
    "gn:population":0,
    "gn:timezone":"Asia/Irkutsk",
    "iso:country":"RU",
    "name:rus_x_preferred":[
        "\u0413\u043e\u0433\u043e\u043b\u0438\u043d"
    ],
    "name:und_x_variant":[
        "Gagolin",
        "Gogolin",
        "\u0413\u043e\u0433\u043e\u043b\u0438\u043d"
    ],
    "wof:name":"Gogolin",
    "wof:placetype":"locality"
},
  "geometry": {"coordinates":[101.41667,55.21666999999999],"type":"Point"}
}