{
  "type": "Feature",
  "properties": {
    "gn:admin1_code":"20",
    "gn:asciiname":"Gogolin",
    "gn:cc2":"RU",
    "gn:country_code":"RU",
    "gn:dem":544,
    "gn:feature_class":"P",
    "gn:feature_code":"PPL",
    "gn:name":"Gogolin",
    "gn:population":0,
    "gn:timezone":"Asia/Irkutsk",
    "iso:country":"RU",
    "name:bak_x_preferred":[
        "\u0413\u043e\u0433\u043e\u043b\u0438\u043d"
    ],
    "name:bul_x_preferred":[
        "\u0413\u043e\u0433\u043e\u043b\u0438\u043d"
    ],
    "name:ceb_x_preferred":[
        "Gogolin"
    ],
    "name:ces_x_preferred":[
        "Gogolin"
    ],
    "name:deu_x_preferred":[
        "Gogolin"
    ],
    "name:epo_x_preferred":[
        "Gogolin"
    ],
    "name:fra_x_preferred":[
        "Gogolin"
    ],
    "name:ita_x_preferred":[
        "Gogolin"
    ],
    "name:jav_x_preferred":[
        "Gogolin"
    ],
    "name:msa_x_preferred":[
        "Gogolin"
    ],
    "name:nld_x_preferred":[
        "Gogolin"
    ],
    "name:pol_x_preferred":[
        "Gogolin"
    ],
    "name:por_x_preferred":[
        "Gogolin"
    ],
    "name:ron_x_preferred":[
        "Gogolin"
    ],
    "name:rus_x_preferred":[
        "\u0413\u043e\u0433\u043e\u043b\u0438\u043d"
    ],
    "name:slk_x_preferred":[
        "Gogolin"
    ],
    "name:srp_x_preferred":[
        "\u0413\u043e\u0433\u043e\u043b\u0438\u043d"
    ],
    "name:szl_x_preferred":[
        "Gogolin"
    ],
    "name:tha_x_preferred":[
        "\u0e01\u0e2d\u0e01\u0e2d\u0e25\u0e34\u0e19"
    ],
    "name:ukr_x_preferred":[
        "\u0413\u043e\u0433\u043e\u043b\u0456\u043d"
    ],
    "name:und_x_variant":[
        "Gagolin"
    ],
    "name:vie_x_preferred":[
        "Gogolin"
    ],
    "name:zho_x_preferred":[
        "\u6208\u6208\u6797"
    ],
    "wof:name":"Gogolin",
    "wof:placetype":"locality"
},
  "geometry": {"coordinates":[101.41667,55.21666999999999],"type":"Point"}
}