{
  "type": "Feature",
  "properties": {
    "gn:admin1_code":"50",
    "gn:asciiname":"Tarasovo",
    "gn:country_code":"RU",
    "gn:dem":41,
    "gn:feature_class":"P",
    "gn:feature_code":"PPL",
    "gn:name":"Tarasovo",
    "gn:population":0,
    "gn:timezone":"Europe/Moscow",
    "iso:country":"RU",
    "name:che_x_preferred":[
        "\u0422\u0430\u0440\u0430\u0441\u043e\u0432\u043e"
    ],
    "name:eng_x_preferred":[
        "Tarasovo"
    ],
    "name:nor_x_preferred":[
        "Tarasovo"
    ],
    "name:rus_x_preferred":[
        "\u0422\u0430\u0440\u0430\u0441\u043e\u0432\u043e"
    ],
    "name:und_x_variant":[
        "Vyselok Tarasov",
        "Tarasov",
        "Tarasovo"
    ],
    "wof:name":"Tarasovo",
    "wof:placetype":"locality"
},
  "geometry": {"coordinates":[46.78193,66.21422],"type":"Point"}
}