{
  "type": "Feature",
  "properties": {
    "gn:admin1_code":"38",
    "gn:asciiname":"Kaplin-Gridin",
    "gn:country_code":"RU",
    "gn:dem":41,
    "gn:feature_class":"P",
    "gn:feature_code":"PPL",
    "gn:name":"Kaplin-Gridin",
    "gn:population":0,
    "gn:timezone":"Europe/Moscow",
    "iso:country":"RU",
    "wof:name":"Kaplin-Gridin",
    "wof:placetype":"locality"
},
  "geometry": {"coordinates":[40.06667,45.79972],"type":"Point"}
}