{
  "type": "Feature",
  "properties": {
    "gn:admin1_code":"80",
    "gn:asciiname":"Pavlushata",
    "gn:country_code":"RU",
    "gn:dem":214,
    "gn:feature_class":"P",
    "gn:feature_code":"PPL",
    "gn:name":"Pavlushata",
    "gn:population":0,
    "gn:timezone":"Europe/Samara",
    "iso:country":"RU",
    "name:rus_x_preferred":[
        "\u041f\u0430\u0432\u043b\u0443\u0448\u0430\u0442\u0430"
    ],
    "wof:name":"Pavlushata",
    "wof:placetype":"locality"
},
  "geometry": {"coordinates":[53.0812,58.2784],"type":"Point"}
}