{
  "type": "Feature",
  "properties": {
    "gn:admin1_code":"52.0",
    "gn:asciiname":"Drachevo",
    "gn:country_code":"RU",
    "gn:dem":151,
    "gn:feature_class":"P",
    "gn:feature_code":"PPL",
    "gn:name":"Drach\u00ebvo",
    "gn:population":0,
    "gn:timezone":"Europe/Moscow",
    "iso:country":"RU",
    "name:rus_x_preferred":[
        "\u0414\u0440\u0430\u0447\u0451\u0432\u043e"
    ],
    "name:und_x_variant":[
        "Drach\u00ebvo",
        "\u0414\u0440\u0430\u0447\u0451\u0432\u043e"
    ],
    "wof:name":"Drachevo",
    "wof:placetype":"locality"
},
  "geometry": {"coordinates":[35.34403,58.76339],"type":"Point"}
}