{
  "type": "Feature",
  "properties": {
    "gn:admin1_code":"56",
    "gn:asciiname":"Korogodino",
    "gn:country_code":"RU",
    "gn:dem":181,
    "gn:feature_class":"P",
    "gn:feature_code":"PPL",
    "gn:name":"Korogodino",
    "gn:population":0,
    "gn:timezone":"Europe/Moscow",
    "iso:country":"RU",
    "name:rus_x_preferred":[
        "\u041a\u043e\u0440\u043e\u0433\u043e\u0434\u0438\u043d\u043e"
    ],
    "name:und_x_variant":[
        "Karagodino"
    ],
    "wof:name":"Korogodino",
    "wof:placetype":"locality"
},
  "geometry": {"coordinates":[36.69814,52.24682],"type":"Point"}
}