{
  "type": "Feature",
  "properties": {
    "gn:admin1_code":"76",
    "gn:asciiname":"Dulevo",
    "gn:country_code":"RU",
    "gn:dem":179,
    "gn:feature_class":"P",
    "gn:feature_code":"PPL",
    "gn:name":"Dulevo",
    "gn:population":0,
    "gn:timezone":"Europe/Moscow",
    "iso:country":"RU",
    "name:nor_x_preferred":[
        "Dulevo"
    ],
    "name:rus_x_preferred":[
        "\u0414\u0443\u043b\u0435\u0432\u043e"
    ],
    "wof:name":"Dulevo",
    "wof:placetype":"locality"
},
  "geometry": {"coordinates":[36.94712,54.45986],"type":"Point"}
}