{
  "type": "Feature",
  "properties": {
    "gn:admin1_code":"63",
    "gn:asciiname":"Andrey-Kyuyel'",
    "gn:country_code":"RU",
    "gn:dem":28,
    "gn:feature_class":"P",
    "gn:feature_code":"PPL",
    "gn:name":"Andrey-Kyuyel\u2019",
    "gn:population":0,
    "gn:timezone":"Asia/Magadan",
    "iso:country":"RU",
    "name:nor_x_preferred":[
        "Andrej-Kjuel"
    ],
    "name:rus_x_preferred":[
        "\u0410\u043d\u0434\u0440\u0435\u0439-\u041a\u044e\u0435\u043b\u044c"
    ],
    "name:und_x_variant":[
        "Andrey-Kyuyel\u2019"
    ],
    "wof:name":"Andrey-Kyuyel'",
    "wof:placetype":"locality"
},
  "geometry": {"coordinates":[151.43333000000001,68.76666999999999],"type":"Point"}
}