{
  "type": "Feature",
  "properties": {
    "gn:admin1_code":"67.0",
    "gn:asciiname":"Alfer'yevka",
    "gn:country_code":"RU",
    "gn:dem":209,
    "gn:feature_class":"P",
    "gn:feature_code":"PPL",
    "gn:name":"Alfer\u2019yevka",
    "gn:population":0,
    "gn:timezone":"Europe/Saratov",
    "iso:country":"RU",
    "name:nor_x_preferred":[
        "Alferjevka"
    ],
    "name:rus_x_preferred":[
        "\u0410\u043b\u0444\u0435\u0440\u044c\u0435\u0432\u043a\u0430"
    ],
    "name:und_x_variant":[
        "Alf\u00ebrovka",
        "Alfer\u2019yevka"
    ],
    "wof:name":"Alfer'yevka",
    "wof:placetype":"locality"
},
  "geometry": {"coordinates":[46.55,52.54083000000001],"type":"Point"}
}