{
  "type": "Feature",
  "properties": {
    "gn:admin1_code":"24",
    "gn:asciiname":"Mokta",
    "gn:cc2":"RU",
    "gn:country_code":"RU",
    "gn:dem":-5,
    "gn:feature_class":"P",
    "gn:feature_code":"PPL",
    "gn:name":"Mokta",
    "gn:population":0,
    "gn:timezone":"Europe/Moscow",
    "iso:country":"RU",
    "name:rus_x_preferred":[
        "\u041c\u043e\u043a\u0442\u0430"
    ],
    "name:und_x_variant":[
        "Mokto",
        "Mokta"
    ],
    "wof:name":"Mokta",
    "wof:placetype":"locality"
},
  "geometry": {"coordinates":[45.5575,47.14167],"type":"Point"}
}