{
  "type": "Feature",
  "properties": {
    "gn:admin1_code":"43",
    "gn:asciiname":"Krasninskiy",
    "gn:country_code":"RU",
    "gn:dem":220,
    "gn:feature_class":"P",
    "gn:feature_code":"PPL",
    "gn:name":"Krasninskiy",
    "gn:population":0,
    "gn:timezone":"Europe/Moscow",
    "iso:country":"RU",
    "name:rus_x_preferred":[
        "\u041a\u0440\u0430\u0441\u043d\u0438\u043d\u0441\u043a\u0438\u0439"
    ],
    "wof:name":"Krasninskiy",
    "wof:placetype":"locality"
},
  "geometry": {"coordinates":[38.77723,52.84871],"type":"Point"}
}