{
  "type": "Feature",
  "properties": {
    "gn:admin1_code":"11",
    "gn:asciiname":"Ulus Bukseken",
    "gn:cc2":"RU",
    "gn:country_code":"RU",
    "gn:dem":560,
    "gn:feature_class":"P",
    "gn:feature_code":"PPL",
    "gn:name":"Ulus Bukseken",
    "gn:population":0,
    "gn:timezone":"Asia/Irkutsk",
    "iso:country":"RU",
    "name:und_x_variant":[
        "Bukseken",
        "Ulus Bukseken"
    ],
    "wof:name":"Ulus Bukseken",
    "wof:placetype":"locality"
},
  "geometry": {"coordinates":[110.16667,54.03333000000001],"type":"Point"}
}