{
  "type": "Feature",
  "properties": {
    "gn:admin1_code":"51.0",
    "gn:asciiname":"Savino",
    "gn:country_code":"RU",
    "gn:dem":94,
    "gn:feature_class":"P",
    "gn:feature_code":"PPL",
    "gn:name":"Savino",
    "gn:population":0,
    "gn:timezone":"Europe/Moscow",
    "iso:country":"RU",
    "name:nor_x_preferred":[
        "Savino"
    ],
    "name:rus_x_preferred":[
        "\u0421\u0430\u0432\u0438\u043d\u043e"
    ],
    "wof:name":"Savino",
    "wof:placetype":"locality"
},
  "geometry": {"coordinates":[43.55769,56.74927],"type":"Point"}
}