{
  "type": "Feature",
  "properties": {
    "gn:admin1_code":"47",
    "gn:asciiname":"Plutalovo",
    "gn:country_code":"RU",
    "gn:dem":175,
    "gn:feature_class":"P",
    "gn:feature_code":"PPL",
    "gn:name":"Plutalovo",
    "gn:population":0,
    "gn:timezone":"Europe/Moscow",
    "iso:country":"RU",
    "name:rus_x_preferred":[
        "\u041f\u043b\u0443\u0442\u0430\u043b\u043e\u0432\u043e"
    ],
    "name:und_x_variant":[
        "\u041f\u043b\u0443\u0442\u0430\u043b\u043e\u0432\u043e"
    ],
    "wof:name":"Plutalovo",
    "wof:placetype":"locality"
},
  "geometry": {"coordinates":[39.07743,54.78445],"type":"Point"}
}