{
  "type": "Feature",
  "properties": {
    "gn:admin1_code":"69.0",
    "gn:asciiname":"Gavrilovo",
    "gn:country_code":"RU",
    "gn:dem":250,
    "gn:feature_class":"P",
    "gn:feature_code":"PPL",
    "gn:name":"Gavrilovo",
    "gn:population":0,
    "gn:timezone":"Europe/Moscow",
    "iso:country":"RU",
    "name:che_x_preferred":[
        "\u0413\u0430\u0432\u0440\u0438\u043b\u043e\u0432\u043e"
    ],
    "name:fin_x_preferred":[
        "K\u00e4m\u00e4r\u00e4"
    ],
    "name:hye_x_preferred":[
        "\u0533\u0561\u057e\u0580\u056b\u056c\u0578\u057e\u0578"
    ],
    "name:rus_x_preferred":[
        "\u0413\u0430\u0432\u0440\u0438\u043b\u043e\u0432\u043e"
    ],
    "wof:name":"Gavrilovo",
    "wof:placetype":"locality"
},
  "geometry": {"coordinates":[32.31610999999999,55.36389000000001],"type":"Point"}
}