{
  "type": "Feature",
  "properties": {
    "gn:admin1_code":"23",
    "gn:asciiname":"Dunayevka",
    "gn:country_code":"RU",
    "gn:dem":60,
    "gn:feature_class":"P",
    "gn:feature_code":"PPL",
    "gn:name":"Dunayevka",
    "gn:population":0,
    "gn:timezone":"Europe/Kaliningrad",
    "iso:country":"RU",
    "name:rus_x_preferred":[
        "\u0414\u0443\u043d\u0430\u0435\u0432\u043a\u0430"
    ],
    "name:und_x_variant":[
        "Lopsienen",
        "Dunayevka"
    ],
    "wof:name":"Dunayevka",
    "wof:placetype":"locality"
},
  "geometry": {"coordinates":[20.18497,54.87924],"type":"Point"}
}