{
  "type": "Feature",
  "properties": {
    "gn:admin1_code":"8",
    "gn:asciiname":"Yamangulovo",
    "gn:country_code":"RU",
    "gn:dem":277,
    "gn:feature_class":"P",
    "gn:feature_code":"PPL",
    "gn:name":"Yamangulovo",
    "gn:population":0,
    "gn:timezone":"Asia/Yekaterinburg",
    "iso:country":"RU",
    "name:rus_x_preferred":[
        "\u042f\u043c\u0430\u043d\u0433\u0443\u043b\u043e\u0432\u043e"
    ],
    "name:und_x_variant":[
        "Yamangulova"
    ],
    "wof:name":"Yamangulovo",
    "wof:placetype":"locality"
},
  "geometry": {"coordinates":[55.91667,52.55],"type":"Point"}
}