{
  "type": "Feature",
  "properties": {
    "gn:admin1_code":"61.0",
    "gn:asciiname":"Krasnovskiy",
    "gn:country_code":"RU",
    "gn:dem":138,
    "gn:feature_class":"P",
    "gn:feature_code":"PPL",
    "gn:name":"Krasnovskiy",
    "gn:population":0,
    "gn:timezone":"Europe/Moscow",
    "iso:country":"RU",
    "name:rus_x_preferred":[
        "\u041a\u0440\u0430\u0441\u043d\u043e\u0432\u0441\u043a\u0438\u0439"
    ],
    "wof:name":"Krasnovskiy",
    "wof:placetype":"locality"
},
  "geometry": {"coordinates":[40.54373,48.78413],"type":"Point"}
}