{
  "type": "Feature",
  "properties": {
    "gn:admin1_code":"84",
    "gn:asciiname":"Sis'kovskiy",
    "gn:country_code":"RU",
    "gn:dem":69,
    "gn:feature_class":"P",
    "gn:feature_code":"PPL",
    "gn:name":"Sis\u2019kovskiy",
    "gn:population":0,
    "gn:timezone":"Europe/Volgograd",
    "iso:country":"RU",
    "name:rus_x_preferred":[
        "Sis\u2019kovskiy"
    ],
    "name:rus_x_variant":[
        "\u0421\u0438\u0441\u044c\u043a\u043e\u0432\u0441\u043a\u0438\u0439",
        "Sis\u2019kov",
        "Khutor Sis\u2019kov"
    ],
    "name:und_x_variant":[
        "Khutor Sis\u2019kov",
        "Sis\u2019kovskiy",
        "Sis\u2019kov"
    ],
    "wof:name":"Sis'kovskiy",
    "wof:placetype":"locality"
},
  "geometry": {"coordinates":[42.3758,49.8928],"type":"Point"}
}