{
  "type": "Feature",
  "properties": {
    "gn:admin1_code":"56",
    "gn:asciiname":"Podgorodnyaya Pervaya",
    "gn:country_code":"RU",
    "gn:dem":233,
    "gn:feature_class":"P",
    "gn:feature_code":"PPL",
    "gn:name":"Podgorodnyaya Pervaya",
    "gn:population":0,
    "gn:timezone":"Europe/Moscow",
    "iso:country":"RU",
    "name:rus_x_preferred":[
        "\u041f\u043e\u0434\u0433\u043e\u0440\u043e\u0434\u043d\u044f\u044f \u041f\u0435\u0440\u0432\u0430\u044f"
    ],
    "wof:name":"Podgorodnyaya Pervaya",
    "wof:placetype":"locality"
},
  "geometry": {"coordinates":[36.4371,52.4018],"type":"Point"}
}