{
  "type": "Feature",
  "properties": {
    "gn:admin1_code":"51",
    "gn:asciiname":"Sapun",
    "gn:country_code":"RU",
    "gn:dem":190,
    "gn:feature_class":"P",
    "gn:feature_code":"PPL",
    "gn:name":"Sapun",
    "gn:population":0,
    "gn:timezone":"Europe/Moscow",
    "iso:country":"RU",
    "name:rus_x_preferred":[
        "\u0421\u0430\u043f\u0443\u043d"
    ],
    "wof:name":"Sapun",
    "wof:placetype":"locality"
},
  "geometry": {"coordinates":[42.6018,55.917],"type":"Point"}
}