{
  "type": "Feature",
  "properties": {
    "gn:admin1_code":"24.0",
    "gn:asciiname":"Kushchevka",
    "gn:country_code":"RU",
    "gn:dem":-4,
    "gn:feature_class":"P",
    "gn:feature_code":"PPL",
    "gn:name":"Kushchevka",
    "gn:population":0,
    "gn:timezone":"Europe/Moscow",
    "iso:country":"RU",
    "name:rus_x_preferred":[
        "\u041a\u0443\u0449\u0435\u0432\u043a\u0430"
    ],
    "name:und_x_variant":[
        "\u041a\u0443\u0449\u0435\u0432\u043a\u0430"
    ],
    "wof:name":"Kushchevka",
    "wof:placetype":"locality"
},
  "geometry": {"coordinates":[45.135,46.48528],"type":"Point"}
}