{
  "type": "Feature",
  "properties": {
    "gn:admin1_code":"56",
    "gn:asciiname":"Zhernovets",
    "gn:country_code":"RU",
    "gn:dem":226,
    "gn:feature_class":"P",
    "gn:feature_code":"PPL",
    "gn:name":"Zhernovets",
    "gn:population":0,
    "gn:timezone":"Europe/Moscow",
    "iso:country":"RU",
    "name:und_x_variant":[
        "Verkhniy Zhernovets",
        "Zhenovets",
        "Zhernovets"
    ],
    "wof:name":"Zhernovets",
    "wof:placetype":"locality"
},
  "geometry": {"coordinates":[37.19287,52.51597],"type":"Point"}
}