{
  "type": "Feature",
  "properties": {
    "gn:admin1_code":"61.0",
    "gn:asciiname":"Komar'kov",
    "gn:country_code":"RU",
    "gn:dem":71,
    "gn:feature_class":"P",
    "gn:feature_code":"PPL",
    "gn:name":"Komar\u2019kov",
    "gn:population":0,
    "gn:timezone":"Europe/Moscow",
    "iso:country":"RU",
    "name:eng_x_preferred":[
        "Komar'kov"
    ],
    "name:nor_x_preferred":[
        "Komarkov"
    ],
    "name:rus_x_preferred":[
        "\u041a\u043e\u043c\u0430\u0440\u044c\u043a\u043e\u0432"
    ],
    "name:und_x_variant":[
        "\u041a\u043e\u043c\u0430\u0440\u044c\u043a\u043e\u0432",
        "Komar\u2019kov"
    ],
    "wof:name":"Komar'kov",
    "wof:placetype":"locality"
},
  "geometry": {"coordinates":[42.0456,46.9653],"type":"Point"}
}