{
  "type": "Feature",
  "properties": {
    "gn:admin1_code":"4.0",
    "gn:asciiname":"Krasnoyarka",
    "gn:country_code":"RU",
    "gn:dem":293,
    "gn:feature_class":"P",
    "gn:feature_code":"PPL",
    "gn:name":"Krasnoyarka",
    "gn:population":0,
    "gn:timezone":"Asia/Barnaul",
    "iso:country":"RU",
    "name:rus_x_preferred":[
        "\u041a\u0440\u0430\u0441\u043d\u043e\u044f\u0440\u043a\u0430"
    ],
    "wof:name":"Krasnoyarka",
    "wof:placetype":"locality"
},
  "geometry": {"coordinates":[81.46040000000001,52.0891],"type":"Point"}
}