{
  "type": "Feature",
  "properties": {
    "gn:admin1_code":"20",
    "gn:asciiname":"Vydrino",
    "gn:country_code":"RU",
    "gn:dem":210,
    "gn:feature_class":"P",
    "gn:feature_code":"PPL",
    "gn:name":"Vydrino",
    "gn:population":0,
    "gn:timezone":"Asia/Irkutsk",
    "iso:country":"RU",
    "name:eng_x_preferred":[
        "Vydrino"
    ],
    "name:nor_x_preferred":[
        "Vydrino"
    ],
    "name:rus_x_preferred":[
        "\u0412\u044b\u0434\u0440\u0438\u043d\u043e"
    ],
    "name:und_x_variant":[
        "Bydrino",
        "Vidrina"
    ],
    "wof:name":"Vydrino",
    "wof:placetype":"locality"
},
  "geometry": {"coordinates":[99.02549999999999,56.8369],"type":"Point"}
}