{
  "type": "Feature",
  "properties": {
    "gn:admin1_code":"8.0",
    "gn:asciiname":"Chetyrman",
    "gn:country_code":"RU",
    "gn:dem":110,
    "gn:feature_class":"P",
    "gn:feature_code":"PPL",
    "gn:name":"Chetyrman",
    "gn:population":0,
    "gn:timezone":"Asia/Yekaterinburg",
    "iso:country":"RU",
    "name:rus_x_preferred":[
        "\u0427\u0435\u0442\u044b\u0440\u043c\u0430\u043d"
    ],
    "name:und_x_variant":[
        "Chetyrmanova",
        "Chetyrmanovo",
        "Chetyrman"
    ],
    "wof:name":"Chetyrman",
    "wof:placetype":"locality"
},
  "geometry": {"coordinates":[55.2982,56.1554],"type":"Point"}
}