{
  "type": "Feature",
  "properties": {
    "gn:admin1_code":"47",
    "gn:asciiname":"Kholopovo",
    "gn:country_code":"RU",
    "gn:dem":274,
    "gn:feature_class":"P",
    "gn:feature_code":"PPL",
    "gn:name":"Kholopovo",
    "gn:population":0,
    "gn:timezone":"Europe/Moscow",
    "iso:country":"RU",
    "name:rus_x_preferred":[
        "\u0425\u043e\u043b\u043e\u043f\u043e\u0432\u043e"
    ],
    "name:und_x_variant":[
        "\u0425\u043e\u043b\u043e\u043f\u043e\u0432\u043e"
    ],
    "wof:name":"Kholopovo",
    "wof:placetype":"locality"
},
  "geometry": {"coordinates":[35.31528,55.50028],"type":"Point"}
}