{
  "type": "Feature",
  "properties": {
    "gn:admin1_code":"16",
    "gn:asciiname":"Staryye Vysli",
    "gn:country_code":"RU",
    "gn:dem":138,
    "gn:feature_class":"P",
    "gn:feature_code":"PPL",
    "gn:name":"Staryye Vysli",
    "gn:population":0,
    "gn:timezone":"Europe/Moscow",
    "iso:country":"RU",
    "name:rus_x_preferred":[
        "\u0421\u0442\u0430\u0440\u044b\u0435 \u0412\u044b\u0441\u043b\u0438"
    ],
    "name:und_x_variant":[
        "Stayye Vysli",
        "Staryye Vysli",
        "\u0421\u0442\u0430\u0440\u044b\u0435 \u0412\u044b\u0441\u043b\u0438"
    ],
    "wof:name":"Staryye Vysli",
    "wof:placetype":"locality"
},
  "geometry": {"coordinates":[47.32073,55.22015],"type":"Point"}
}