{
  "type": "Feature",
  "properties": {
    "gn:admin1_code":"28",
    "gn:asciiname":"Jokela",
    "gn:cc2":"RU",
    "gn:country_code":"RU",
    "gn:dem":261,
    "gn:feature_class":"P",
    "gn:feature_code":"PPL",
    "gn:name":"Jokela",
    "gn:population":0,
    "gn:timezone":"Europe/Moscow",
    "iso:country":"RU",
    "name:dan_x_preferred":[
        "Jokela"
    ],
    "name:deu_x_preferred":[
        "Jokela"
    ],
    "name:epo_x_preferred":[
        "Jokela"
    ],
    "name:est_x_preferred":[
        "Jokela"
    ],
    "name:fin_x_preferred":[
        "Jokela"
    ],
    "name:lav_x_preferred":[
        "Jokela"
    ],
    "name:por_x_preferred":[
        "Jokela"
    ],
    "name:ron_x_preferred":[
        "Jokela"
    ],
    "name:swe_x_preferred":[
        "Jokela"
    ],
    "name:und_x_variant":[
        "Iokela",
        "Yokela"
    ],
    "wof:name":"Jokela",
    "wof:placetype":"locality"
},
  "geometry": {"coordinates":[29.84985,66.53603000000001],"type":"Point"}
}