{
  "type": "Feature",
  "properties": {
    "gn:admin1_code":"51",
    "gn:asciiname":"Mikhalenino",
    "gn:country_code":"RU",
    "gn:dem":122,
    "gn:feature_class":"P",
    "gn:feature_code":"PPL",
    "gn:name":"Mikhalenino",
    "gn:population":0,
    "gn:timezone":"Europe/Moscow",
    "iso:country":"RU",
    "name:eng_x_preferred":[
        "Mikhalenino"
    ],
    "name:nor_x_preferred":[
        "Mikhalenino"
    ],
    "name:rus_x_preferred":[
        "\u041c\u0438\u0445\u0430\u043b\u0435\u043d\u0438\u043d\u043e"
    ],
    "wof:name":"Mikhalenino",
    "wof:placetype":"locality"
},
  "geometry": {"coordinates":[45.05727,57.4295],"type":"Point"}
}