{
  "type": "Feature",
  "properties": {
    "gn:admin1_code":"33.0",
    "gn:asciiname":"Blokhichi",
    "gn:country_code":"RU",
    "gn:dem":146,
    "gn:feature_class":"P",
    "gn:feature_code":"PPL",
    "gn:name":"Blokhichi",
    "gn:population":0,
    "gn:timezone":"Europe/Kirov",
    "iso:country":"RU",
    "name:rus_x_preferred":[
        "\u0411\u043b\u043e\u0445\u0438\u0447\u0438"
    ],
    "wof:name":"Blokhichi",
    "wof:placetype":"locality"
},
  "geometry": {"coordinates":[47.99982,58.80796],"type":"Point"}
}