{
  "type": "Feature",
  "properties": {
    "gn:admin1_code":"61",
    "gn:asciiname":"Novobakhmutskiy",
    "gn:country_code":"RU",
    "gn:dem":136,
    "gn:feature_class":"P",
    "gn:feature_code":"PPL",
    "gn:name":"Novobakhmutskiy",
    "gn:population":0,
    "gn:timezone":"Europe/Moscow",
    "iso:country":"RU",
    "name:rus_x_preferred":[
        "\u041d\u043e\u0432\u043e\u0431\u0430\u0445\u043c\u0443\u0442\u0441\u043a\u0438\u0439"
    ],
    "wof:name":"Novobakhmutskiy",
    "wof:placetype":"locality"
},
  "geometry": {"coordinates":[38.87593,47.7775],"type":"Point"}
}