{
  "type": "Feature",
  "properties": {
    "gn:admin1_code":"05",
    "gn:asciiname":"Innokent'yevka",
    "gn:country_code":"RU",
    "gn:dem":212,
    "gn:feature_class":"P",
    "gn:feature_code":"PPL",
    "gn:name":"Innokent\u2019yevka",
    "gn:population":0,
    "gn:timezone":"Asia/Yakutsk",
    "iso:country":"RU",
    "name:rus_x_preferred":[
        "\u0418\u043d\u043d\u043e\u043a\u0435\u043d\u0442\u044c\u0435\u0432\u043a\u0430"
    ],
    "name:und_x_variant":[
        "Innokent\u2019evka",
        "Innokent\u2019yevka"
    ],
    "wof:name":"Innokent'yevka",
    "wof:placetype":"locality"
},
  "geometry": {"coordinates":[129.17674,49.97174],"type":"Point"}
}