{
  "type": "Feature",
  "properties": {
    "gn:admin1_code":"54",
    "gn:asciiname":"Zalesnaya",
    "gn:country_code":"RU",
    "gn:dem":115,
    "gn:feature_class":"P",
    "gn:feature_code":"PPL",
    "gn:name":"Zalesnaya",
    "gn:population":0,
    "gn:timezone":"Asia/Omsk",
    "iso:country":"RU",
    "name:che_x_preferred":[
        "\u0417\u0430\u043b\u0435\u0441\u043d\u0438"
    ],
    "name:eng_x_preferred":[
        "Zalesnaya"
    ],
    "name:nor_x_preferred":[
        "Malinovka"
    ],
    "name:rus_x_preferred":[
        "\u041c\u0430\u043b\u0438\u043d\u043e\u0432\u043a\u0430"
    ],
    "name:rus_x_variant":[
        "\u0417\u0430\u043b\u0435\u0441\u043d\u0430\u044f"
    ],
    "name:und_x_variant":[
        "Malinovka",
        "Zalesnaya",
        "\u0417\u0430\u043b\u0435\u0441\u043d\u0430\u044f"
    ],
    "wof:name":"Zalesnaya",
    "wof:placetype":"locality"
},
  "geometry": {"coordinates":[72.57467,55.66816],"type":"Point"}
}