{
  "type": "Feature",
  "properties": {
    "gn:admin1_code":"69",
    "gn:asciiname":"Golochevo",
    "gn:country_code":"RU",
    "gn:dem":218,
    "gn:feature_class":"P",
    "gn:feature_code":"PPL",
    "gn:name":"Golochevo",
    "gn:population":0,
    "gn:timezone":"Europe/Moscow",
    "iso:country":"RU",
    "name:rus_x_preferred":[
        "\u0413\u043e\u043b\u043e\u0447\u0435\u0432\u043e"
    ],
    "name:und_x_variant":[
        "\u0413\u043e\u043b\u043e\u0447\u0435\u0432\u043e",
        "Golochevo"
    ],
    "wof:name":"Golochevo",
    "wof:placetype":"locality"
},
  "geometry": {"coordinates":[32.4353,55.2447],"type":"Point"}
}