{
  "type": "Feature",
  "properties": {
    "gn:admin1_code":"88",
    "gn:asciiname":"Kocherovo",
    "gn:country_code":"RU",
    "gn:dem":123,
    "gn:feature_class":"P",
    "gn:feature_code":"PPL",
    "gn:name":"Kocherovo",
    "gn:population":0,
    "gn:timezone":"Europe/Moscow",
    "iso:country":"RU",
    "name:rus_x_preferred":[
        "\u041a\u043e\u0447\u0435\u0440\u043e\u0432\u043e"
    ],
    "wof:name":"Kocherovo",
    "wof:placetype":"locality"
},
  "geometry": {"coordinates":[38.69407,57.82849],"type":"Point"}
}