{
  "type": "Feature",
  "properties": {
    "gn:admin1_code":"73.0",
    "gn:asciiname":"Koshlauch",
    "gn:country_code":"RU",
    "gn:dem":135,
    "gn:feature_class":"P",
    "gn:feature_code":"PPL",
    "gn:name":"Koshlauch",
    "gn:population":0,
    "gn:timezone":"Europe/Moscow",
    "iso:country":"RU",
    "name:bul_x_preferred":[
        "\u041a\u0443\u0448\u043b\u0430\u0443\u0447"
    ],
    "name:che_x_preferred":[
        "\u041a\u043e\u0448\u043b\u0430\u0443\u0447"
    ],
    "name:chv_x_preferred":[
        "\u041a\u0443\u0448\u043b\u0430\u0432\u0103\u0448"
    ],
    "name:rus_x_preferred":[
        "\u041a\u043e\u0448\u043b\u0430\u0443\u0447"
    ],
    "name:tat_x_preferred":[
        "\u041a\u0443\u0448\u043b\u0430\u0432\u044b\u0447"
    ],
    "name:und_x_variant":[
        "\u041a\u043e\u0448\u043b\u0430\u0443\u0447"
    ],
    "wof:name":"Koshlauch",
    "wof:placetype":"locality"
},
  "geometry": {"coordinates":[49.56158,56.15881],"type":"Point"}
}