{
  "type": "Feature",
  "properties": {
    "gn:admin1_code":"71",
    "gn:asciiname":"Kazarovo",
    "gn:cc2":"RU",
    "gn:country_code":"RU",
    "gn:dem":57,
    "gn:feature_class":"P",
    "gn:feature_code":"PPL",
    "gn:name":"Kazarovo",
    "gn:population":0,
    "gn:timezone":"Asia/Yekaterinburg",
    "iso:country":"RU",
    "name:rus_x_preferred":[
        "\u041a\u0430\u0437\u0430\u0440\u043e\u0432\u043e"
    ],
    "name:und_x_variant":[
        "Kazarova",
        "Kazarovo",
        "\u041a\u0430\u0437\u0430\u0440\u043e\u0432\u043e"
    ],
    "wof:name":"Kazarovo",
    "wof:placetype":"locality"
},
  "geometry": {"coordinates":[64.68333,58.53333000000001],"type":"Point"}
}