{
  "type": "Feature",
  "properties": {
    "gn:admin1_code":"85",
    "gn:asciiname":"Gorka Mal'gina",
    "gn:country_code":"RU",
    "gn:dem":161,
    "gn:feature_class":"P",
    "gn:feature_code":"PPL",
    "gn:name":"Gorka Mal\u2019gina",
    "gn:population":0,
    "gn:timezone":"Europe/Moscow",
    "iso:country":"RU",
    "name:rus_x_preferred":[
        "\u0413\u043e\u0440\u043a\u0430 \u041c\u0430\u043b\u044c\u0433\u0438\u043d\u0430"
    ],
    "name:und_x_variant":[
        "Malygina Gorka",
        "Gorka Mal\u2019gina",
        "\u0413\u043e\u0440\u043a\u0430 \u041c\u0430\u043b\u044c\u0433\u0438\u043d\u0430"
    ],
    "wof:name":"Gorka Mal'gina",
    "wof:placetype":"locality"
},
  "geometry": {"coordinates":[41.87314,60.37674000000001],"type":"Point"}
}