{
  "type": "Feature",
  "properties": {
    "gn:admin1_code":"10",
    "gn:asciiname":"Borysh'ye",
    "gn:country_code":"RU",
    "gn:dem":181,
    "gn:feature_class":"P",
    "gn:feature_code":"PPL",
    "gn:name":"Borysh\u2019ye",
    "gn:population":0,
    "gn:timezone":"Europe/Moscow",
    "iso:country":"RU",
    "name:rus_x_preferred":[
        "\u0411\u043e\u0440\u044b\u0448\u044c\u0435"
    ],
    "name:und_x_variant":[
        "Borysh\u2019ye"
    ],
    "wof:name":"Borysh'ye",
    "wof:placetype":"locality"
},
  "geometry": {"coordinates":[33.86972,53.27444000000001],"type":"Point"}
}