{
  "type": "Feature",
  "properties": {
    "gn:admin1_code":"56",
    "gn:asciiname":"Repka",
    "gn:country_code":"RU",
    "gn:dem":218,
    "gn:feature_class":"P",
    "gn:feature_code":"PPL",
    "gn:name":"Repka",
    "gn:population":0,
    "gn:timezone":"Europe/Moscow",
    "iso:country":"RU",
    "name:rus_x_preferred":[
        "\u0420\u0435\u043f\u043a\u0430"
    ],
    "wof:name":"Repka",
    "wof:placetype":"locality"
},
  "geometry": {"coordinates":[36.0286,52.6387],"type":"Point"}
}