{
  "type": "Feature",
  "properties": {
    "gn:admin1_code":"62",
    "gn:asciiname":"Kolobovo",
    "gn:country_code":"RU",
    "gn:dem":140,
    "gn:feature_class":"P",
    "gn:feature_code":"PPL",
    "gn:name":"Kolobovo",
    "gn:population":0,
    "gn:timezone":"Europe/Moscow",
    "iso:country":"RU",
    "name:ceb_x_preferred":[
        "Kolobovo"
    ],
    "name:che_x_preferred":[
        "\u041a\u043e\u043b\u043e\u0431\u043e\u0432\u043e"
    ],
    "name:ita_x_preferred":[
        "Kolobovo"
    ],
    "name:rus_x_preferred":[
        "\u041a\u043e\u043b\u043e\u0431\u043e\u0432\u043e"
    ],
    "name:tgk_x_preferred":[
        "\u041a\u043e\u043b\u043e\u0431\u043e\u0432\u043e"
    ],
    "name:und_x_variant":[
        "\u041a\u043e\u043b\u043e\u0431\u043e\u0432\u043e"
    ],
    "wof:name":"Kolobovo",
    "wof:placetype":"locality"
},
  "geometry": {"coordinates":[40.1792,53.3509],"type":"Point"}
}