{
  "type": "Feature",
  "properties": {
    "gn:admin1_code":"88",
    "gn:asciiname":"Privolzh'ye",
    "gn:country_code":"RU",
    "gn:dem":133,
    "gn:feature_class":"P",
    "gn:feature_code":"PPL",
    "gn:name":"Privolzh\u2019ye",
    "gn:population":0,
    "gn:timezone":"Europe/Moscow",
    "iso:country":"RU",
    "name:rus_x_preferred":[
        "\u041f\u0440\u0438\u0432\u043e\u043b\u0436\u044c\u0435"
    ],
    "name:und_x_variant":[
        "Privolzh\u2019ye"
    ],
    "wof:name":"Privolzh'ye",
    "wof:placetype":"locality"
},
  "geometry": {"coordinates":[39.21229,57.98945],"type":"Point"}
}