{
  "type": "Feature",
  "properties": {
    "gn:admin1_code":"37",
    "gn:asciiname":"Yemskoye",
    "gn:country_code":"RU",
    "gn:dem":138,
    "gn:feature_class":"P",
    "gn:feature_code":"PPL",
    "gn:name":"Yemskoye",
    "gn:population":0,
    "gn:timezone":"Europe/Moscow",
    "iso:country":"RU",
    "name:rus_x_preferred":[
        "\u0415\u043c\u0441\u043a\u043e\u0435"
    ],
    "name:und_x_variant":[
        "\u0415\u043c\u0441\u043a\u043e\u0435"
    ],
    "wof:name":"Yemskoye",
    "wof:placetype":"locality"
},
  "geometry": {"coordinates":[46.7229,59.2004],"type":"Point"}
}