{
  "type": "Feature",
  "properties": {
    "gn:admin1_code":"80",
    "gn:asciiname":"Meshcheryaki",
    "gn:country_code":"RU",
    "gn:dem":157,
    "gn:feature_class":"P",
    "gn:feature_code":"PPL",
    "gn:name":"Meshcheryaki",
    "gn:population":0,
    "gn:timezone":"Europe/Samara",
    "iso:country":"RU",
    "name:nor_x_preferred":[
        "Mesjtsjerjaki"
    ],
    "name:rus_x_preferred":[
        "\u041c\u0435\u0449\u0435\u0440\u044f\u043a\u0438"
    ],
    "wof:name":"Meshcheryaki",
    "wof:placetype":"locality"
},
  "geometry": {"coordinates":[53.31547,56.74154],"type":"Point"}
}