{
  "type": "Feature",
  "properties": {
    "gn:admin1_code":"61",
    "gn:asciiname":"Strepetov",
    "gn:country_code":"RU",
    "gn:dem":23,
    "gn:feature_class":"P",
    "gn:feature_code":"PPL",
    "gn:name":"Strepetov",
    "gn:population":0,
    "gn:timezone":"Europe/Moscow",
    "iso:country":"RU",
    "name:rus_x_preferred":[
        "\u0421\u0442\u0440\u0435\u043f\u0435\u0442\u043e\u0432"
    ],
    "wof:name":"Strepetov",
    "wof:placetype":"locality"
},
  "geometry": {"coordinates":[42.5268,46.5822],"type":"Point"}
}