{
  "type": "Feature",
  "properties": {
    "gn:admin1_code":"46.0",
    "gn:asciiname":"Popovka",
    "gn:country_code":"RU",
    "gn:dem":173,
    "gn:feature_class":"P",
    "gn:feature_code":"PPL",
    "gn:name":"Popovka",
    "gn:population":0,
    "gn:timezone":"Europe/Moscow",
    "iso:country":"RU",
    "name:ceb_x_preferred":[
        "Popovka"
    ],
    "name:est_x_preferred":[
        "Popovka"
    ],
    "name:swe_x_preferred":[
        "Popovka"
    ],
    "wof:name":"Popovka",
    "wof:placetype":"locality"
},
  "geometry": {"coordinates":[43.52228,54.7788],"type":"Point"}
}