{
  "type": "Feature",
  "properties": {
    "gn:admin1_code":"65",
    "gn:asciiname":"Krest'yanskiy",
    "gn:country_code":"RU",
    "gn:dem":38,
    "gn:feature_class":"P",
    "gn:feature_code":"PPL",
    "gn:name":"Krest\u2019yanskiy",
    "gn:population":0,
    "gn:timezone":"Europe/Samara",
    "iso:country":"RU",
    "name:rus_x_preferred":[
        "\u041a\u0440\u0435\u0441\u0442\u044c\u044f\u043d\u0441\u043a\u0438\u0439"
    ],
    "name:und_x_variant":[
        "Krest\u2019yanskiy"
    ],
    "wof:name":"Krest'yanskiy",
    "wof:placetype":"locality"
},
  "geometry": {"coordinates":[50.74776,53.02241],"type":"Point"}
}