{
  "type": "Feature",
  "properties": {
    "gn:admin1_code":"67",
    "gn:asciiname":"Kuchumbetovo",
    "gn:cc2":"RU",
    "gn:country_code":"RU",
    "gn:dem":51,
    "gn:feature_class":"P",
    "gn:feature_code":"PPL",
    "gn:name":"Kuchumbetovo",
    "gn:population":0,
    "gn:timezone":"Europe/Saratov",
    "iso:country":"RU",
    "name:eng_x_preferred":[
        "Kuchumbetovo"
    ],
    "name:nor_x_preferred":[
        "Kutsjumbetovo"
    ],
    "name:rus_x_preferred":[
        "\u041a\u0443\u0447\u0443\u043c\u0431\u0435\u0442\u043e\u0432\u043e"
    ],
    "name:und_x_variant":[
        "Kochumbetovo",
        "Kuchembetova",
        "\u041a\u0443\u0447\u0443\u043c\u0431\u0435\u0442\u043e\u0432\u043e",
        "Kuchumbetovo"
    ],
    "wof:name":"Kuchumbetovo",
    "wof:placetype":"locality"
},
  "geometry": {"coordinates":[50.33333,51.68333],"type":"Point"}
}