{
  "type": "Feature",
  "properties": {
    "gn:admin1_code":"52.0",
    "gn:asciiname":"Barevo",
    "gn:country_code":"RU",
    "gn:dem":86,
    "gn:feature_class":"P",
    "gn:feature_code":"PPL",
    "gn:name":"Barevo",
    "gn:population":0,
    "gn:timezone":"Europe/Moscow",
    "iso:country":"RU",
    "name:nor_x_preferred":[
        "Barevo"
    ],
    "name:rus_x_preferred":[
        "\u0411\u0430\u0440\u0435\u0432\u043e"
    ],
    "wof:name":"Barevo",
    "wof:placetype":"locality"
},
  "geometry": {"coordinates":[30.76667,57.68333000000001],"type":"Point"}
}