{
  "type": "Feature",
  "properties": {
    "gn:admin1_code":"47",
    "gn:asciiname":"Khokhlevo",
    "gn:country_code":"RU",
    "gn:dem":148,
    "gn:feature_class":"P",
    "gn:feature_code":"PPL",
    "gn:name":"Khokhlevo",
    "gn:population":0,
    "gn:timezone":"Europe/Moscow",
    "iso:country":"RU",
    "name:rus_x_preferred":[
        "\u0425\u043e\u0445\u043b\u0435\u0432\u043e"
    ],
    "name:und_x_variant":[
        "\u0425\u043e\u0445\u043b\u0435\u0432\u043e"
    ],
    "wof:name":"Khokhlevo",
    "wof:placetype":"locality"
},
  "geometry": {"coordinates":[39.11048,55.4044],"type":"Point"}
}