{
  "type": "Feature",
  "properties": {
    "gn:admin1_code":"73.0",
    "gn:asciiname":"Bol'shoy Chekmak",
    "gn:country_code":"RU",
    "gn:dem":79,
    "gn:feature_class":"P",
    "gn:feature_code":"PPL",
    "gn:name":"Bol\u2019shoy Chekmak",
    "gn:population":0,
    "gn:timezone":"Europe/Moscow",
    "iso:country":"RU",
    "name:eng_x_preferred":[
        "Bol'shoy Chekmak"
    ],
    "name:nor_x_preferred":[
        "Bolsjoj Tsjekman"
    ],
    "name:rus_x_preferred":[
        "\u0411\u043e\u043b\u044c\u0448\u043e\u0439 \u0427\u0435\u043a\u043c\u0430\u043d"
    ],
    "name:rus_x_variant":[
        "\u0411\u043e\u043b\u044c\u0448\u043e\u0439 \u0427\u0435\u043a\u043c\u0430\u043a"
    ],
    "name:und_x_variant":[
        "Bol\u2019shoy Chakmak",
        "Bol\u2019shoy Chekmak"
    ],
    "wof:name":"Bol'shoy Chekmak",
    "wof:placetype":"locality"
},
  "geometry": {"coordinates":[53.15306,55.22361],"type":"Point"}
}