{
  "type": "Feature",
  "properties": {
    "gn:admin1_code":"56",
    "gn:asciiname":"Chermoshnoye",
    "gn:country_code":"RU",
    "gn:dem":223,
    "gn:feature_class":"P",
    "gn:feature_code":"PPL",
    "gn:name":"Chermoshnoye",
    "gn:population":0,
    "gn:timezone":"Europe/Moscow",
    "iso:country":"RU",
    "name:rus_x_preferred":[
        "\u0427\u0435\u0440\u043c\u043e\u0448\u043d\u043e\u0435"
    ],
    "wof:name":"Chermoshnoye",
    "wof:placetype":"locality"
},
  "geometry": {"coordinates":[36.179,52.4412],"type":"Point"}
}