{
  "type": "Feature",
  "properties": {
    "gn:admin1_code":"79",
    "gn:asciiname":"Ongacha",
    "gn:country_code":"RU",
    "gn:dem":1368,
    "gn:feature_class":"P",
    "gn:feature_code":"PPL",
    "gn:name":"Ongacha",
    "gn:population":0,
    "gn:timezone":"Asia/Krasnoyarsk",
    "iso:country":"RU",
    "name:eng_x_preferred":[
        "Ongacha"
    ],
    "name:nor_x_preferred":[
        "Ongatsja"
    ],
    "name:rus_x_preferred":[
        "\u041e\u043d\u0433\u0430\u0447\u0430"
    ],
    "wof:name":"Ongacha",
    "wof:placetype":"locality"
},
  "geometry": {"coordinates":[93.68333,51.18333],"type":"Point"}
}