{
  "type": "Feature",
  "properties": {
    "gn:admin1_code":"52",
    "gn:asciiname":"Maloye Zamosh'ye",
    "gn:country_code":"RU",
    "gn:dem":48,
    "gn:feature_class":"P",
    "gn:feature_code":"PPL",
    "gn:name":"Maloye Zamosh\u2019ye",
    "gn:population":0,
    "gn:timezone":"Europe/Moscow",
    "iso:country":"RU",
    "name:rus_x_preferred":[
        "\u041c\u0430\u043b\u043e\u0435 \u0417\u0430\u043c\u043e\u0448\u044c\u0435"
    ],
    "name:und_x_variant":[
        "Maloye Zamosh\u2019ye"
    ],
    "wof:name":"Maloye Zamosh'ye",
    "wof:placetype":"locality"
},
  "geometry": {"coordinates":[31.30825,58.81728],"type":"Point"}
}