{
  "type": "Feature",
  "properties": {
    "gn:admin1_code":"10",
    "gn:asciiname":"Staroye Zaduben'ye",
    "gn:country_code":"RU",
    "gn:dem":179,
    "gn:feature_class":"P",
    "gn:feature_code":"PPL",
    "gn:name":"Staroye Zaduben\u2019ye",
    "gn:population":0,
    "gn:timezone":"Europe/Moscow",
    "iso:country":"RU",
    "name:rus_x_preferred":[
        "\u0421\u0442\u0430\u0440\u043e\u0435 \u0417\u0430\u0434\u0443\u0431\u0435\u043d\u044c\u0435"
    ],
    "name:und_x_variant":[
        "Staraya Zaduben\u2019ye",
        "Staroye Zaduben\u2019ye",
        "\u0421\u0442\u0430\u0440\u043e\u0435 \u0417\u0430\u0434\u0443\u0431\u0435\u043d\u044c\u0435"
    ],
    "wof:name":"Staroye Zaduben'ye",
    "wof:placetype":"locality"
},
  "geometry": {"coordinates":[33.04567,52.7918],"type":"Point"}
}