{
  "type": "Feature",
  "properties": {
    "gn:admin1_code":"76",
    "gn:asciiname":"Zhizhel'na Pervaya",
    "gn:country_code":"RU",
    "gn:dem":134,
    "gn:feature_class":"P",
    "gn:feature_code":"PPL",
    "gn:name":"Zhizhel\u2019na Pervaya",
    "gn:population":0,
    "gn:timezone":"Europe/Moscow",
    "iso:country":"RU",
    "name:und_x_variant":[
        "Pervaya Zhizhelna",
        "Zhizhel\u2019na Pervaya"
    ],
    "wof:name":"Zhizhel'na Pervaya",
    "wof:placetype":"locality"
},
  "geometry": {"coordinates":[38.02103,54.71456],"type":"Point"}
}