{
  "type": "Feature",
  "properties": {
    "gn:admin1_code":"63",
    "gn:asciiname":"Nel'keskan",
    "gn:country_code":"RU",
    "gn:dem":233,
    "gn:feature_class":"P",
    "gn:feature_code":"PPL",
    "gn:name":"Nel\u2019keskan",
    "gn:population":0,
    "gn:timezone":"Asia/Yakutsk",
    "iso:country":"RU",
    "name:rus_x_preferred":[
        "\u041d\u0435\u043b\u044c\u043a\u0435\u0441\u043a\u0430\u043d"
    ],
    "name:und_x_variant":[
        "Nel\u2019keskan",
        "\u041d\u0435\u043b\u044c\u043a\u0435\u0441\u043a\u0430\u043d"
    ],
    "wof:name":"Nel'keskan",
    "wof:placetype":"locality"
},
  "geometry": {"coordinates":[121.84999999999999,67.28333000000001],"type":"Point"}
}