{
  "type": "Feature",
  "properties": {
    "gn:admin1_code":"85",
    "gn:asciiname":"Mikheyevo",
    "gn:country_code":"RU",
    "gn:dem":163,
    "gn:feature_class":"P",
    "gn:feature_code":"PPL",
    "gn:name":"Mikheyevo",
    "gn:population":0,
    "gn:timezone":"Europe/Moscow",
    "iso:country":"RU",
    "name:eng_x_preferred":[
        "Mikheyevo"
    ],
    "name:nor_x_preferred":[
        "Mikhejevo"
    ],
    "name:rus_x_preferred":[
        "\u041c\u0438\u0445\u0435\u0435\u0432\u043e"
    ],
    "name:und_x_variant":[
        "\u041c\u0438\u0445\u0435\u0435\u0432\u043e",
        "Mikheyevo"
    ],
    "wof:name":"Mikheyevo",
    "wof:placetype":"locality"
},
  "geometry": {"coordinates":[41.37121,59.57825],"type":"Point"}
}