{
  "type": "Feature",
  "properties": {
    "gn:country":"RU",
    "gn:fcode":"PPL",
    "gn:population":0,
    "iso:country":"RU",
    "name:rus_x_preferred":[
        "Landysh\u00ebvka"
    ],
    "name:rus_x_variant":[
        "\u041b\u0430\u043d\u0434\u044b\u0448\u0451\u0432\u043a\u0430"
    ],
    "name:und_x_variant":[
        "Krutishche"
    ],
    "qs:name":"Landysh\u00ebvka",
    "qs:name_adm0":"Russia",
    "qs:name_adm1":"Lipetsk Oblast",
    "qs:photos_9r":0,
    "qs:photos_sr":0,
    "qs:placetype":"Town",
    "qs:pop_sr":"0",
    "wof:name":"Landysh\u00ebvka",
    "wof:placetype":"locality",
    "wof:population":0
},
  "geometry": {"coordinates":[40.2099,52.0001],"type":"Point"}
}