{
  "type": "Feature",
  "properties": {
    "gn:admin1_code":"61",
    "gn:asciiname":"Remontnyy",
    "gn:cc2":"RU",
    "gn:country_code":"RU",
    "gn:dem":13,
    "gn:feature_class":"P",
    "gn:feature_code":"PPL",
    "gn:name":"Remontnyy",
    "gn:population":0,
    "gn:timezone":"Europe/Moscow",
    "iso:country":"RU",
    "name:rus_x_preferred":[
        "\u0420\u0435\u043c\u043e\u043d\u0442\u043d\u044b\u0439"
    ],
    "name:und_x_variant":[
        "Remontny",
        "Remontnyy",
        "\u0420\u0435\u043c\u043e\u043d\u0442\u043d\u044b\u0439"
    ],
    "wof:name":"Remontnyy",
    "wof:placetype":"locality"
},
  "geometry": {"coordinates":[41.5875,46.79361],"type":"Point"}
}