{
  "type": "Feature",
  "properties": {
    "gn:admin1_code":"47",
    "gn:asciiname":"Sogolevo",
    "gn:country_code":"RU",
    "gn:dem":215,
    "gn:feature_class":"P",
    "gn:feature_code":"PPL",
    "gn:name":"Sogolevo",
    "gn:population":0,
    "gn:timezone":"Europe/Moscow",
    "iso:country":"RU",
    "name:rus_x_preferred":[
        "\u0421\u043e\u0433\u043e\u043b\u0435\u0432\u043e"
    ],
    "name:und_x_variant":[
        "Soglevo",
        "Sogolevo",
        "\u0421\u043e\u0433\u043e\u043b\u0435\u0432\u043e"
    ],
    "wof:name":"Sogolevo",
    "wof:placetype":"locality"
},
  "geometry": {"coordinates":[36.93333,56.35],"type":"Point"}
}