{
  "type": "Feature",
  "properties": {
    "gn:admin1_code":"78",
    "gn:asciiname":"Taygach",
    "gn:country_code":"RU",
    "gn:dem":62,
    "gn:feature_class":"P",
    "gn:feature_code":"PPL",
    "gn:name":"Taygach",
    "gn:population":0,
    "gn:timezone":"Asia/Yekaterinburg",
    "iso:country":"RU",
    "name:eng_x_preferred":[
        "Taygach"
    ],
    "name:nor_x_preferred":[
        "Tangatsji"
    ],
    "name:rus_x_preferred":[
        "\u0422\u0430\u043d\u0433\u0430\u0447\u0438"
    ],
    "wof:name":"Taygach",
    "wof:placetype":"locality"
},
  "geometry": {"coordinates":[66.01666999999999,57.33333],"type":"Point"}
}