{
  "type": "Feature",
  "properties": {
    "gn:admin1_code":"55.0",
    "gn:asciiname":"Novyy Kumak",
    "gn:country_code":"RU",
    "gn:dem":198,
    "gn:feature_class":"P",
    "gn:feature_code":"PPL",
    "gn:name":"Novyy Kumak",
    "gn:population":0,
    "gn:timezone":"Asia/Yekaterinburg",
    "iso:country":"RU",
    "name:eng_x_preferred":[
        "Novyy Kumak"
    ],
    "name:nor_x_preferred":[
        "Nov.Kumak"
    ],
    "name:rus_x_preferred":[
        "\u041d\u043e\u0432.\u041a\u0443\u043c\u0430\u043a"
    ],
    "name:rus_x_variant":[
        "\u041d\u043e\u0432\u044b\u0439 \u041a\u0443\u043c\u0430\u043a"
    ],
    "name:und_x_variant":[
        "\u041d\u043e\u0432\u044b\u0439 \u041a\u0443\u043c\u0430\u043a"
    ],
    "wof:name":"Novyy Kumak",
    "wof:placetype":"locality"
},
  "geometry": {"coordinates":[58.68023,51.24047],"type":"Point"}
}