{
  "type": "Feature",
  "properties": {
    "gn:admin1_code":"8.0",
    "gn:asciiname":"Askarova",
    "gn:country_code":"RU",
    "gn:dem":537,
    "gn:feature_class":"P",
    "gn:feature_code":"PPL",
    "gn:name":"Askarova",
    "gn:population":0,
    "gn:timezone":"Asia/Yekaterinburg",
    "iso:country":"RU",
    "name:nor_x_preferred":[
        "Askarova"
    ],
    "name:rus_x_preferred":[
        "\u0410\u0441\u043a\u0430\u0440\u043e\u0432\u0430"
    ],
    "wof:name":"Askarova",
    "wof:placetype":"locality"
},
  "geometry": {"coordinates":[57.26667,53.58333],"type":"Point"}
}