{
  "type": "Feature",
  "properties": {
    "gn:admin1_code":"53",
    "gn:asciiname":"Granit",
    "gn:country_code":"RU",
    "gn:dem":141,
    "gn:feature_class":"P",
    "gn:feature_code":"PPL",
    "gn:name":"Granit",
    "gn:population":0,
    "gn:timezone":"Asia/Novosibirsk",
    "iso:country":"RU",
    "name:rus_x_preferred":[
        "\u0413\u0440\u0430\u043d\u0438\u0442"
    ],
    "name:und_x_variant":[
        "\u0413\u0440\u0430\u043d\u0438\u0442"
    ],
    "wof:name":"Granit",
    "wof:placetype":"locality"
},
  "geometry": {"coordinates":[84.59999999999999,55.14666999999999],"type":"Point"}
}