{
  "type": "Feature",
  "properties": {
    "gn:admin1_code":"93",
    "gn:asciiname":"Zakharovo",
    "gn:country_code":"RU",
    "gn:dem":813,
    "gn:feature_class":"P",
    "gn:feature_code":"PPL",
    "gn:name":"Zakharovo",
    "gn:population":0,
    "gn:timezone":"Asia/Chita",
    "iso:country":"RU",
    "name:eng_x_preferred":[
        "Zakharovo"
    ],
    "name:nor_x_preferred":[
        "Zakharovo"
    ],
    "name:rus_x_preferred":[
        "\u0417\u0430\u0445\u0430\u0440\u043e\u0432\u043e"
    ],
    "name:und_x_variant":[
        "Zakharova",
        "Zakharovo"
    ],
    "wof:name":"Zakharovo",
    "wof:placetype":"locality"
},
  "geometry": {"coordinates":[109.38030999999999,50.53585],"type":"Point"}
}