{
  "type": "Feature",
  "properties": {
    "gn:admin1_code":"4",
    "gn:asciiname":"Obskoye",
    "gn:country_code":"RU",
    "gn:dem":115,
    "gn:feature_class":"P",
    "gn:feature_code":"PPL",
    "gn:name":"Obskoye",
    "gn:population":0,
    "gn:timezone":"Asia/Barnaul",
    "iso:country":"RU",
    "name:eng_x_preferred":[
        "Obskoye"
    ],
    "name:nor_x_preferred":[
        "Obskoje"
    ],
    "name:rus_x_preferred":[
        "\u041e\u0431\u0441\u043a\u043e\u0435"
    ],
    "wof:name":"Obskoye",
    "wof:placetype":"locality"
},
  "geometry": {"coordinates":[81.6812,53.6556],"type":"Point"}
}