{
  "type": "Feature",
  "properties": {
    "gn:admin1_code":"41.0",
    "gn:asciiname":"Dezhevka",
    "gn:country_code":"RU",
    "gn:dem":172,
    "gn:feature_class":"P",
    "gn:feature_code":"PPL",
    "gn:name":"Dezh\u00ebvka",
    "gn:population":0,
    "gn:timezone":"Europe/Moscow",
    "iso:country":"RU",
    "name:rus_x_preferred":[
        "\u0414\u0435\u0436\u0451\u0432\u043a\u0430"
    ],
    "name:und_x_variant":[
        "Dezhovka",
        "Dezh\u00ebvka"
    ],
    "wof:name":"Dezhevka",
    "wof:placetype":"locality"
},
  "geometry": {"coordinates":[36.823,51.34997],"type":"Point"}
}