{
  "type": "Feature",
  "properties": {
    "gn:admin1_code":"63",
    "gn:asciiname":"Terekhpreekh",
    "gn:cc2":"RU",
    "gn:country_code":"RU",
    "gn:dem":481,
    "gn:feature_class":"P",
    "gn:feature_code":"PPL",
    "gn:name":"Terekhpreekh",
    "gn:population":0,
    "gn:timezone":"Asia/Yakutsk",
    "iso:country":"RU",
    "name:und_x_variant":[
        "Tirekhtyakh",
        "Terekhpreekh"
    ],
    "wof:name":"Terekhpreekh",
    "wof:placetype":"locality"
},
  "geometry": {"coordinates":[131.05833000000001,65.90083],"type":"Point"}
}