{
  "type": "Feature",
  "properties": {
    "gn:admin1_code":"37",
    "gn:asciiname":"Stafurovo",
    "gn:country_code":"RU",
    "gn:dem":170,
    "gn:feature_class":"P",
    "gn:feature_code":"PPL",
    "gn:name":"Stafurovo",
    "gn:population":0,
    "gn:timezone":"Europe/Moscow",
    "iso:country":"RU",
    "name:rus_x_preferred":[
        "\u0421\u0442\u0430\u0444\u0443\u0440\u043e\u0432\u043e"
    ],
    "name:und_x_variant":[
        "\u0421\u0442\u0430\u0444\u0443\u0440\u043e\u0432\u043e"
    ],
    "wof:name":"Stafurovo",
    "wof:placetype":"locality"
},
  "geometry": {"coordinates":[42.4012,58.9063],"type":"Point"}
}