{
  "type": "Feature",
  "properties": {
    "gn:admin1_code":"88",
    "gn:asciiname":"Rusinovskaya",
    "gn:country_code":"RU",
    "gn:dem":127,
    "gn:feature_class":"P",
    "gn:feature_code":"PPL",
    "gn:name":"Rusinovskaya",
    "gn:population":0,
    "gn:timezone":"Europe/Moscow",
    "iso:country":"RU",
    "name:rus_x_preferred":[
        "\u0420\u0443\u0441\u0438\u043d\u043e\u0432\u0441\u043a\u0430\u044f"
    ],
    "name:und_x_variant":[
        "\u0420\u0443\u0441\u0438\u043d\u043e\u0432\u0441\u043a\u0430\u044f"
    ],
    "wof:name":"Rusinovskaya",
    "wof:placetype":"locality"
},
  "geometry": {"coordinates":[38.2532,57.9162],"type":"Point"}
}