{
  "type": "Feature",
  "properties": {
    "gn:admin1_code":"20",
    "gn:asciiname":"Novokiyevsk",
    "gn:country_code":"RU",
    "gn:dem":284,
    "gn:feature_class":"P",
    "gn:feature_code":"PPL",
    "gn:name":"Novokiyevsk",
    "gn:population":0,
    "gn:timezone":"Asia/Irkutsk",
    "iso:country":"RU",
    "name:eng_x_preferred":[
        "Novokiyevskiy"
    ],
    "name:rus_x_preferred":[
        "\u041d\u043e\u0432\u043e\u043a\u0438\u0435\u0432\u0441\u043a"
    ],
    "name:und_x_variant":[
        "Novokiyevsk"
    ],
    "wof:name":"Novokiyevsk",
    "wof:placetype":"locality"
},
  "geometry": {"coordinates":[98.6691,55.6679],"type":"Point"}
}