{
  "type": "Feature",
  "properties": {
    "gn:admin1_code":"77",
    "gn:asciiname":"Radunka",
    "gn:country_code":"RU",
    "gn:dem":164,
    "gn:feature_class":"P",
    "gn:feature_code":"PPL",
    "gn:name":"Radunka",
    "gn:population":0,
    "gn:timezone":"Europe/Moscow",
    "iso:country":"RU",
    "name:rus_x_preferred":[
        "\u0420\u0430\u0434\u0443\u043d\u043a\u0430"
    ],
    "name:und_x_variant":[
        "\u0420\u0430\u0434\u0443\u043d\u043a\u0430"
    ],
    "wof:name":"Radunka",
    "wof:placetype":"locality"
},
  "geometry": {"coordinates":[34.42151,57.73157],"type":"Point"}
}