{
  "type": "Feature",
  "properties": {
    "gn:admin1_code":"23",
    "gn:asciiname":"Znamenka",
    "gn:country_code":"RU",
    "gn:dem":129,
    "gn:feature_class":"P",
    "gn:feature_code":"PPL",
    "gn:name":"Znamenka",
    "gn:population":0,
    "gn:timezone":"Europe/Kaliningrad",
    "iso:country":"RU",
    "wof:name":"Znamenka",
    "wof:placetype":"locality"
},
  "geometry": {"coordinates":[22.51306,54.48139000000001],"type":"Point"}
}