{
  "type": "Feature",
  "properties": {
    "gn:admin1_code":"30",
    "gn:asciiname":"Durmin",
    "gn:country_code":"RU",
    "gn:dem":75,
    "gn:feature_class":"P",
    "gn:feature_code":"PPL",
    "gn:name":"Durmin",
    "gn:population":0,
    "gn:timezone":"Asia/Vladivostok",
    "iso:country":"RU",
    "name:eng_x_preferred":[
        "Durmin"
    ],
    "name:nor_x_preferred":[
        "Durmin"
    ],
    "name:rus_x_preferred":[
        "\u0414\u0443\u0440\u043c\u0438\u043d"
    ],
    "name:und_x_variant":[
        "Verkhne Durminskiy",
        "Durmin 27-y",
        "Verkhniy Durminskiy Lespromkhoz",
        "Durmin 61 km",
        "Verkhne Durminskiy Lespromkhoz",
        "Durminskiy"
    ],
    "wof:name":"Durmin",
    "wof:placetype":"locality"
},
  "geometry": {"coordinates":[135.84591,48.08589],"type":"Point"}
}