{
  "type": "Feature",
  "properties": {
    "gn:admin1_code":"78",
    "gn:asciiname":"Kostyleva",
    "gn:country_code":"RU",
    "gn:dem":89,
    "gn:feature_class":"P",
    "gn:feature_code":"PPL",
    "gn:name":"Kostyl\u00ebva",
    "gn:population":0,
    "gn:timezone":"Asia/Yekaterinburg",
    "iso:country":"RU",
    "name:eng_x_preferred":[
        "Kostyl\u00ebvo"
    ],
    "name:nor_x_preferred":[
        "Kostyleva"
    ],
    "name:rus_x_preferred":[
        "\u041a\u043e\u0441\u0442\u044b\u043b\u0435\u0432\u0430"
    ],
    "name:rus_x_variant":[
        "\u041a\u043e\u0441\u0442\u044b\u043b\u0451\u0432\u0430"
    ],
    "name:und_x_variant":[
        "Kostyl\u00ebva"
    ],
    "wof:name":"Kostyleva",
    "wof:placetype":"locality"
},
  "geometry": {"coordinates":[70.04116999999999,56.26825],"type":"Point"}
}