{
  "type": "Feature",
  "properties": {
    "gn:admin1_code":"86.0",
    "gn:asciiname":"Fedorovskiy",
    "gn:country_code":"RU",
    "gn:dem":138,
    "gn:feature_class":"P",
    "gn:feature_code":"PPL",
    "gn:name":"F\u00ebdorovskiy",
    "gn:population":0,
    "gn:timezone":"Europe/Moscow",
    "iso:country":"RU",
    "name:rus_x_preferred":[
        "\u0424\u0451\u0434\u043e\u0440\u043e\u0432\u0441\u043a\u0438\u0439"
    ],
    "name:und_x_variant":[
        "F\u00ebdorovskiy",
        "\u0424\u0451\u0434\u043e\u0440\u043e\u0432\u0441\u043a\u0438\u0439"
    ],
    "wof:name":"Fedorovskiy",
    "wof:placetype":"locality"
},
  "geometry": {"coordinates":[40.01972,50.90722],"type":"Point"}
}