{
  "type": "Feature",
  "properties": {
    "gn:admin1_code":"25.0",
    "gn:asciiname":"Losevo",
    "gn:country_code":"RU",
    "gn:dem":242,
    "gn:feature_class":"P",
    "gn:feature_code":"PPL",
    "gn:name":"Losevo",
    "gn:population":0,
    "gn:timezone":"Europe/Moscow",
    "iso:country":"RU",
    "name:deu_x_preferred":[
        "Lossewo"
    ],
    "name:rus_x_preferred":[
        "\u041b\u043e\u0441\u0435\u0432\u043e"
    ],
    "name:spa_x_preferred":[
        "L\u00f3sevo"
    ],
    "name:und_x_variant":[
        "\u041b\u043e\u0441\u0435\u0432\u043e"
    ],
    "wof:name":"Losevo",
    "wof:placetype":"locality"
},
  "geometry": {"coordinates":[34.88,54.4125],"type":"Point"}
}