{
  "type": "Feature",
  "properties": {
    "gn:admin1_code":"28.0",
    "gn:asciiname":"Gitoyla",
    "gn:country_code":"RU",
    "gn:dem":13,
    "gn:feature_class":"P",
    "gn:feature_code":"PPL",
    "gn:name":"Gitoyla",
    "gn:population":0,
    "gn:timezone":"Europe/Moscow",
    "iso:country":"RU",
    "name:fin_x_preferred":[
        "Hitoila"
    ],
    "name:rus_x_preferred":[
        "\u0413\u0438\u0442\u043e\u0439\u043b\u0430"
    ],
    "wof:name":"Gitoyla",
    "wof:placetype":"locality"
},
  "geometry": {"coordinates":[32.83333,60.98333],"type":"Point"}
}