{
  "type": "Feature",
  "properties": {
    "gn:admin1_code":"42",
    "gn:asciiname":"Lipnaya Gorka",
    "gn:country_code":"RU",
    "gn:dem":47,
    "gn:feature_class":"P",
    "gn:feature_code":"PPL",
    "gn:name":"Lipnaya Gorka",
    "gn:population":0,
    "gn:timezone":"Europe/Moscow",
    "iso:country":"RU",
    "name:eng_x_preferred":[
        "Lipnaya Gorka"
    ],
    "name:nor_x_preferred":[
        "Lipnaja Gorka"
    ],
    "name:rus_x_preferred":[
        "\u041b\u0438\u043f\u043d\u0430\u044f \u0413\u043e\u0440\u043a\u0430"
    ],
    "wof:name":"Lipnaya Gorka",
    "wof:placetype":"locality"
},
  "geometry": {"coordinates":[33.18559,59.58749],"type":"Point"}
}