{
  "type": "Feature",
  "properties": {
    "gn:admin1_code":"43.0",
    "gn:asciiname":"Bratovshchina",
    "gn:country_code":"RU",
    "gn:dem":184,
    "gn:feature_class":"P",
    "gn:feature_code":"PPL",
    "gn:name":"Bratovshchina",
    "gn:population":0,
    "gn:timezone":"Europe/Moscow",
    "iso:country":"RU",
    "name:rus_x_preferred":[
        "\u0411\u0440\u0430\u0442\u043e\u0432\u0449\u0438\u043d\u0430"
    ],
    "wof:name":"Bratovshchina",
    "wof:placetype":"locality"
},
  "geometry": {"coordinates":[38.3364,52.30706],"type":"Point"}
}