{
  "type": "Feature",
  "properties": {
    "gn:admin1_code":"21",
    "gn:asciiname":"Nesterovo",
    "gn:country_code":"RU",
    "gn:dem":123,
    "gn:feature_class":"P",
    "gn:feature_code":"PPL",
    "gn:name":"Nesterovo",
    "gn:population":0,
    "gn:timezone":"Europe/Moscow",
    "iso:country":"RU",
    "name:rus_x_preferred":[
        "\u041d\u0435\u0441\u0442\u0435\u0440\u043e\u0432\u043e"
    ],
    "name:und_x_variant":[
        "\u041d\u0435\u0441\u0442\u0435\u0440\u043e\u0432\u043e"
    ],
    "wof:name":"Nesterovo",
    "wof:placetype":"locality"
},
  "geometry": {"coordinates":[41.93333,57.03333000000001],"type":"Point"}
}