{
  "type": "Feature",
  "properties": {
    "gn:admin1_code":"81",
    "gn:asciiname":"Novoannenkovskiy",
    "gn:country_code":"RU",
    "gn:dem":157,
    "gn:feature_class":"P",
    "gn:feature_code":"PPL",
    "gn:name":"Novoannenkovskiy",
    "gn:population":0,
    "gn:timezone":"Europe/Ulyanovsk",
    "iso:country":"RU",
    "name:rus_x_preferred":[
        "\u041d\u043e\u0432\u043e\u0430\u043d\u043d\u0435\u043d\u043a\u043e\u0432\u0441\u043a\u0438\u0439"
    ],
    "name:und_x_variant":[
        "Opytnaya Stantsiya"
    ],
    "wof:name":"Novoannenkovskiy",
    "wof:placetype":"locality"
},
  "geometry": {"coordinates":[47.4474,54.1008],"type":"Point"}
}