{
  "type": "Feature",
  "properties": {
    "gn:admin1_code":"85.0",
    "gn:asciiname":"Chuksha",
    "gn:country_code":"RU",
    "gn:dem":165,
    "gn:feature_class":"P",
    "gn:feature_code":"PPL",
    "gn:name":"Chuksha",
    "gn:population":0,
    "gn:timezone":"Europe/Moscow",
    "iso:country":"RU",
    "name:rus_x_preferred":[
        "\u0427\u0443\u043a\u0448\u0430"
    ],
    "name:und_x_variant":[
        "\u0427\u0443\u043a\u0448\u0430"
    ],
    "wof:name":"Chuksha",
    "wof:placetype":"locality"
},
  "geometry": {"coordinates":[37.96052,59.47535],"type":"Point"}
}