{
  "type": "Feature",
  "properties": {
    "gn:admin1_code":"77.0",
    "gn:asciiname":"Bol'shaya Perevoloka",
    "gn:country_code":"RU",
    "gn:dem":240,
    "gn:feature_class":"P",
    "gn:feature_code":"PPL",
    "gn:name":"Bol\u2019shaya Perevoloka",
    "gn:population":0,
    "gn:timezone":"Europe/Moscow",
    "iso:country":"RU",
    "name:rus_x_preferred":[
        "\u0411\u043e\u043b\u044c\u0448\u0430\u044f \u041f\u0435\u0440\u0435\u0432\u043e\u043b\u043e\u043a\u0430"
    ],
    "name:und_x_variant":[
        "Bol\u2019shaya Perevoloka"
    ],
    "wof:name":"Bol'shaya Perevoloka",
    "wof:placetype":"locality"
},
  "geometry": {"coordinates":[32.23568,56.97613000000001],"type":"Point"}
}