{
  "type": "Feature",
  "properties": {
    "gn:admin1_code":"67",
    "gn:asciiname":"Yelan'",
    "gn:country_code":"RU",
    "gn:dem":201,
    "gn:feature_class":"P",
    "gn:feature_code":"PPL",
    "gn:name":"Yelan\u2019",
    "gn:population":0,
    "gn:timezone":"Europe/Saratov",
    "iso:country":"RU",
    "name:eng_x_preferred":[
        "Yelan'"
    ],
    "name:nor_x_preferred":[
        "Jelan"
    ],
    "name:rus_x_preferred":[
        "\u0415\u043b\u0430\u043d\u044c"
    ],
    "name:und_x_variant":[
        "Yelan\u2019"
    ],
    "wof:name":"Yelan'",
    "wof:placetype":"locality"
},
  "geometry": {"coordinates":[44.18148,52.20979000000001],"type":"Point"}
}