{
  "type": "Feature",
  "properties": {
    "gn:admin1_code":"43",
    "gn:asciiname":"Srednyaya Dolina",
    "gn:country_code":"RU",
    "gn:dem":133,
    "gn:feature_class":"P",
    "gn:feature_code":"PPL",
    "gn:name":"Srednyaya Dolina",
    "gn:population":0,
    "gn:timezone":"Europe/Moscow",
    "iso:country":"RU",
    "name:rus_x_preferred":[
        "\u0421\u0440\u0435\u0434\u043d\u044f\u044f \u0414\u043e\u043b\u0438\u043d\u0430"
    ],
    "name:und_x_variant":[
        "\u0421\u0440\u0435\u0434\u043d\u044f\u044f \u0414\u043e\u043b\u0438\u043d\u0430"
    ],
    "wof:name":"Srednyaya Dolina",
    "wof:placetype":"locality"
},
  "geometry": {"coordinates":[38.9756,52.0857],"type":"Point"}
}