{
  "type": "Feature",
  "properties": {
    "gn:admin1_code":"21.0",
    "gn:asciiname":"Polovchinnovo",
    "gn:country_code":"RU",
    "gn:dem":132,
    "gn:feature_class":"P",
    "gn:feature_code":"PPL",
    "gn:name":"Polovchinnovo",
    "gn:population":0,
    "gn:timezone":"Europe/Moscow",
    "iso:country":"RU",
    "name:rus_x_preferred":[
        "\u041f\u043e\u043b\u043e\u0432\u0447\u0438\u043d\u043d\u043e\u0432\u043e"
    ],
    "name:und_x_variant":[
        "\u041f\u043e\u043b\u043e\u0432\u0447\u0438\u043d\u043d\u043e\u0432\u043e"
    ],
    "wof:name":"Polovchinnovo",
    "wof:placetype":"locality"
},
  "geometry": {"coordinates":[41.76816,57.06058],"type":"Point"}
}