{
  "type": "Feature",
  "properties": {
    "gn:admin1_code":"56",
    "gn:asciiname":"Nizhneye Skvorcheye",
    "gn:cc2":"RU",
    "gn:country_code":"RU",
    "gn:dem":192,
    "gn:feature_class":"P",
    "gn:feature_code":"PPL",
    "gn:name":"Nizhneye Skvorcheye",
    "gn:population":0,
    "gn:timezone":"Europe/Moscow",
    "iso:country":"RU",
    "name:rus_x_preferred":[
        "\u041d\u0438\u0436\u043d\u0435\u0435 \u0421\u043a\u0432\u043e\u0440\u0447\u0435\u0435"
    ],
    "name:und_x_variant":[
        "Nizhne-Skvorcheye",
        "Nizhneye Skvorcheye"
    ],
    "wof:name":"Nizhneye Skvorcheye",
    "wof:placetype":"locality"
},
  "geometry": {"coordinates":[36.85,52.86666999999999],"type":"Point"}
}