{
  "type": "Feature",
  "properties": {
    "gn:admin1_code":"84",
    "gn:asciiname":"Lobynets",
    "gn:country_code":"RU",
    "gn:dem":159,
    "gn:feature_class":"P",
    "gn:feature_code":"PPL",
    "gn:name":"Lobynets",
    "gn:population":0,
    "gn:timezone":"Europe/Volgograd",
    "iso:country":"RU",
    "name:rus_x_preferred":[
        "\u041b\u043e\u0431\u044b\u043d\u0435\u0446"
    ],
    "name:und_x_variant":[
        "\u041b\u043e\u0431\u044b\u043d\u0435\u0446"
    ],
    "wof:name":"Lobynets",
    "wof:placetype":"locality"
},
  "geometry": {"coordinates":[44.9453,50.36548],"type":"Point"}
}