{
  "type": "Feature",
  "properties": {
    "gn:admin1_code":"55",
    "gn:asciiname":"Kazancha",
    "gn:country_code":"RU",
    "gn:dem":308,
    "gn:feature_class":"P",
    "gn:feature_code":"PPL",
    "gn:name":"Kazancha",
    "gn:population":0,
    "gn:timezone":"Asia/Yekaterinburg",
    "iso:country":"RU",
    "name:eng_x_preferred":[
        "Kazancha"
    ],
    "name:nor_x_preferred":[
        "Kazantsja"
    ],
    "name:rus_x_preferred":[
        "\u041a\u0430\u0437\u0430\u043d\u0447\u0430"
    ],
    "name:und_x_variant":[
        "Kazanche"
    ],
    "wof:name":"Kazancha",
    "wof:placetype":"locality"
},
  "geometry": {"coordinates":[60.7763,51.062],"type":"Point"}
}