{
  "type": "Feature",
  "properties": {
    "gn:admin1_code":"61",
    "gn:asciiname":"Novopavlovskiy",
    "gn:country_code":"RU",
    "gn:dem":53,
    "gn:feature_class":"P",
    "gn:feature_code":"PPL",
    "gn:name":"Novopavlovskiy",
    "gn:population":0,
    "gn:timezone":"Europe/Moscow",
    "iso:country":"RU",
    "name:rus_x_preferred":[
        "\u041d\u043e\u0432\u043e\u043f\u0430\u0432\u043b\u043e\u0432\u0441\u043a\u0438\u0439"
    ],
    "name:ukr_x_preferred":[
        "Novopavlovs\u2019kyy"
    ],
    "name:und_x_variant":[
        "Pavlovskiy",
        "Novopavlovskiy"
    ],
    "wof:name":"Novopavlovskiy",
    "wof:placetype":"locality"
},
  "geometry": {"coordinates":[38.38338,47.50008],"type":"Point"}
}