{
  "type": "Feature",
  "properties": {
    "gn:admin1_code":"13",
    "gn:asciiname":"Zaozernyy",
    "gn:country_code":"RU",
    "gn:dem":328,
    "gn:feature_class":"P",
    "gn:feature_code":"PPL",
    "gn:name":"Zaoz\u00ebrnyy",
    "gn:population":0,
    "gn:timezone":"Asia/Yekaterinburg",
    "iso:country":"RU",
    "wof:name":"Zaozernyy",
    "wof:placetype":"locality"
},
  "geometry": {"coordinates":[60.53404000000001,52.55779],"type":"Point"}
}