{
  "type": "Feature",
  "properties": {
    "gn:admin1_code":"70",
    "gn:asciiname":"Prokhladnyy",
    "gn:country_code":"RU",
    "gn:dem":584,
    "gn:feature_class":"P",
    "gn:feature_code":"PPL",
    "gn:name":"Prokhladnyy",
    "gn:population":0,
    "gn:timezone":"Europe/Moscow",
    "iso:country":"RU",
    "wof:name":"Prokhladnyy",
    "wof:placetype":"locality"
},
  "geometry": {"coordinates":[42.23306,44.45],"type":"Point"}
}