{
  "type": "Feature",
  "properties": {
    "gn:admin1_code":"85",
    "gn:asciiname":"Seletskaya",
    "gn:country_code":"RU",
    "gn:dem":181,
    "gn:feature_class":"P",
    "gn:feature_code":"PPL",
    "gn:name":"Seletskaya",
    "gn:population":0,
    "gn:timezone":"Europe/Moscow",
    "iso:country":"RU",
    "name:rus_x_preferred":[
        "\u0421\u0435\u043b\u0435\u0446\u043a\u0430\u044f"
    ],
    "name:und_x_variant":[
        "\u0421\u0435\u043b\u0435\u0446\u043a\u0430\u044f"
    ],
    "wof:name":"Seletskaya",
    "wof:placetype":"locality"
},
  "geometry": {"coordinates":[38.66265,59.26319],"type":"Point"}
}