{
  "type": "Feature",
  "properties": {
    "gn:admin1_code":"51",
    "gn:asciiname":"Men'shchikovo",
    "gn:country_code":"RU",
    "gn:dem":152,
    "gn:feature_class":"P",
    "gn:feature_code":"PPL",
    "gn:name":"Men\u2019shchikovo",
    "gn:population":0,
    "gn:timezone":"Europe/Moscow",
    "iso:country":"RU",
    "name:eng_x_preferred":[
        "Men'shchikovo"
    ],
    "name:nor_x_preferred":[
        "Mensjikovo"
    ],
    "name:rus_x_preferred":[
        "\u041c\u0435\u043d\u044c\u0448\u0438\u043a\u043e\u0432\u043e"
    ],
    "name:rus_x_variant":[
        "\u041c\u0435\u043d\u044c\u0449\u0438\u043a\u043e\u0432\u043e"
    ],
    "name:und_x_variant":[
        "Men\u2019shikovo",
        "Men\u2019shikov",
        "Men\u2019shchikovo",
        "\u041c\u0435\u043d\u044c\u0449\u0438\u043a\u043e\u0432\u043e"
    ],
    "wof:name":"Men'shchikovo",
    "wof:placetype":"locality"
},
  "geometry": {"coordinates":[43.55143,55.70618],"type":"Point"}
}