{
  "type": "Feature",
  "properties": {
    "gn:admin1_code":"41.0",
    "gn:asciiname":"Belitino",
    "gn:country_code":"RU",
    "gn:dem":164,
    "gn:feature_class":"P",
    "gn:feature_code":"PPL",
    "gn:name":"Belitino",
    "gn:population":0,
    "gn:timezone":"Europe/Moscow",
    "iso:country":"RU",
    "name:nor_x_preferred":[
        "Beliteno"
    ],
    "name:rus_x_preferred":[
        "\u0411\u0435\u043b\u0438\u0442\u0438\u043d\u043e"
    ],
    "name:und_x_variant":[
        "Belitino"
    ],
    "wof:name":"Belitino",
    "wof:placetype":"locality"
},
  "geometry": {"coordinates":[34.917,52.0326],"type":"Point"}
}