{
  "type": "Feature",
  "properties": {
    "gn:admin1_code":"16",
    "gn:asciiname":"Staryye Shal'tyamy",
    "gn:country_code":"RU",
    "gn:dem":152,
    "gn:feature_class":"P",
    "gn:feature_code":"PPL",
    "gn:name":"Staryye Shal\u2019tyamy",
    "gn:population":0,
    "gn:timezone":"Europe/Moscow",
    "iso:country":"RU",
    "name:rus_x_preferred":[
        "\u0421\u0442\u0430\u0440\u044b\u0435 \u0428\u0430\u043b\u044c\u0442\u044f\u043c\u044b"
    ],
    "name:und_x_variant":[
        "Staryye Shal\u2019tyamy"
    ],
    "wof:name":"Staryye Shal'tyamy",
    "wof:placetype":"locality"
},
  "geometry": {"coordinates":[47.49449,55.37828],"type":"Point"}
}