{
  "type": "Feature",
  "properties": {
    "gn:admin1_code":"41",
    "gn:asciiname":"Zhuravinka",
    "gn:country_code":"RU",
    "gn:dem":183,
    "gn:feature_class":"P",
    "gn:feature_code":"PPL",
    "gn:name":"Zhuravinka",
    "gn:population":0,
    "gn:timezone":"Europe/Moscow",
    "iso:country":"RU",
    "name:rus_x_preferred":[
        "\u0416\u0443\u0440\u0430\u0432\u0438\u043d\u043a\u0430"
    ],
    "name:und_x_variant":[
        "Zhuravlinka"
    ],
    "wof:name":"Zhuravinka",
    "wof:placetype":"locality"
},
  "geometry": {"coordinates":[35.6018,52.0801],"type":"Point"}
}