{
  "type": "Feature",
  "properties": {
    "gn:admin1_code":"80",
    "gn:asciiname":"Lyali",
    "gn:country_code":"RU",
    "gn:dem":107,
    "gn:feature_class":"P",
    "gn:feature_code":"PPL",
    "gn:name":"Lyali",
    "gn:population":0,
    "gn:timezone":"Europe/Samara",
    "iso:country":"RU",
    "name:rus_x_preferred":[
        "\u041b\u044f\u043b\u0438"
    ],
    "name:und_x_variant":[
        "\u041b\u044f\u043b\u0438"
    ],
    "wof:name":"Lyali",
    "wof:placetype":"locality"
},
  "geometry": {"coordinates":[52.8051,56.15118],"type":"Point"}
}