{
  "type": "Feature",
  "properties": {
    "gn:admin1_code":"85",
    "gn:asciiname":"Zolotavtsevo",
    "gn:country_code":"RU",
    "gn:dem":102,
    "gn:feature_class":"P",
    "gn:feature_code":"PPL",
    "gn:name":"Zolotavtsevo",
    "gn:population":0,
    "gn:timezone":"Europe/Moscow",
    "iso:country":"RU",
    "name:rus_x_preferred":[
        "\u0417\u043e\u043b\u043e\u0442\u0430\u0432\u0446\u0435\u0432\u043e"
    ],
    "name:und_x_variant":[
        "\u0417\u043e\u043b\u043e\u0442\u0430\u0432\u0446\u0435\u0432\u043e"
    ],
    "wof:name":"Zolotavtsevo",
    "wof:placetype":"locality"
},
  "geometry": {"coordinates":[46.2516,60.7972],"type":"Point"}
}