{
  "type": "Feature",
  "properties": {
    "gn:admin1_code":"37",
    "gn:asciiname":"Sokhino",
    "gn:country_code":"RU",
    "gn:dem":135,
    "gn:feature_class":"P",
    "gn:feature_code":"PPL",
    "gn:name":"Sokhino",
    "gn:population":0,
    "gn:timezone":"Europe/Moscow",
    "iso:country":"RU",
    "name:rus_x_preferred":[
        "\u0421\u043e\u0445\u0438\u043d\u043e"
    ],
    "wof:name":"Sokhino",
    "wof:placetype":"locality"
},
  "geometry": {"coordinates":[42.0052,58.4768],"type":"Point"}
}