{
  "type": "Feature",
  "properties": {
    "gn:admin1_code":"73.0",
    "gn:asciiname":"Bol'shiye Kovali",
    "gn:country_code":"RU",
    "gn:dem":113,
    "gn:feature_class":"P",
    "gn:feature_code":"PPL",
    "gn:name":"Bol\u2019shiye Kovali",
    "gn:population":0,
    "gn:timezone":"Europe/Moscow",
    "iso:country":"RU",
    "name:rus_x_preferred":[
        "\u0411\u043e\u043b\u044c\u0448\u0438\u0435 \u041a\u043e\u0432\u0430\u043b\u0438"
    ],
    "name:und_x_variant":[
        "Bol\u2019shiye Kovali"
    ],
    "wof:name":"Bol'shiye Kovali",
    "wof:placetype":"locality"
},
  "geometry": {"coordinates":[49.06111,56.02833],"type":"Point"}
}