{
  "type": "Feature",
  "properties": {
    "gn:admin1_code":"91",
    "gn:asciiname":"Kursk",
    "gn:country_code":"RU",
    "gn:dem":461,
    "gn:feature_class":"P",
    "gn:feature_code":"PPL",
    "gn:name":"Kursk",
    "gn:population":0,
    "gn:timezone":"Asia/Krasnoyarsk",
    "iso:country":"RU",
    "name:rus_x_preferred":[
        "\u041a\u0443\u0440\u0441\u043a"
    ],
    "wof:name":"Kursk",
    "wof:placetype":"locality"
},
  "geometry": {"coordinates":[91.49944000000001,54.58139],"type":"Point"}
}