{
  "type": "Feature",
  "properties": {
    "gn:admin1_code":"23",
    "gn:asciiname":"Zhavoronkovo",
    "gn:country_code":"RU",
    "gn:dem":20,
    "gn:feature_class":"P",
    "gn:feature_code":"PPL",
    "gn:name":"Zhavoronkovo",
    "gn:population":0,
    "gn:timezone":"Europe/Kaliningrad",
    "iso:country":"RU",
    "name:und_x_variant":[
        "Vurbel\u2019n",
        "Wirbeln",
        "Zhavoronkovo"
    ],
    "wof:name":"Zhavoronkovo",
    "wof:placetype":"locality"
},
  "geometry": {"coordinates":[21.55847,54.6812],"type":"Point"}
}