{
  "type": "Feature",
  "properties": {
    "gn:admin1_code":"42",
    "gn:asciiname":"Onstapel'",
    "gn:country_code":"RU",
    "gn:dem":101,
    "gn:feature_class":"P",
    "gn:feature_code":"PPL",
    "gn:name":"Onstapel\u2019",
    "gn:population":0,
    "gn:timezone":"Europe/Moscow",
    "iso:country":"RU",
    "name:rus_x_preferred":[
        "\u041e\u043d\u0441\u0442\u0430\u043f\u0435\u043b\u044c"
    ],
    "name:und_x_variant":[
        "Onstapel\u2019"
    ],
    "wof:name":"Onstapel'",
    "wof:placetype":"locality"
},
  "geometry": {"coordinates":[28.91857000000001,59.40673],"type":"Point"}
}