{
  "type": "Feature",
  "properties": {
    "gn:admin1_code":"70",
    "gn:asciiname":"Rempl'",
    "gn:country_code":"RU",
    "gn:dem":207,
    "gn:feature_class":"P",
    "gn:feature_code":"PPL",
    "gn:name":"Rempl\u2019",
    "gn:population":0,
    "gn:timezone":"Europe/Moscow",
    "iso:country":"RU",
    "name:rus_x_preferred":[
        "\u0420\u0435\u043c\u043f\u043b\u044c"
    ],
    "name:und_x_variant":[
        "Rempl\u2019",
        "\u0420\u0435\u043c\u043f\u043b\u044c"
    ],
    "wof:name":"Rempl'",
    "wof:placetype":"locality"
},
  "geometry": {"coordinates":[44.2275,44.08361],"type":"Point"}
}