{
  "type": "Feature",
  "properties": {
    "gn:admin1_code":"13",
    "gn:asciiname":"Chekurova",
    "gn:country_code":"RU",
    "gn:dem":165,
    "gn:feature_class":"P",
    "gn:feature_code":"PPL",
    "gn:name":"Chekurova",
    "gn:population":0,
    "gn:timezone":"Asia/Yekaterinburg",
    "iso:country":"RU",
    "name:eng_x_preferred":[
        "Chekurova"
    ],
    "name:nor_x_preferred":[
        "Tsjekurova"
    ],
    "name:rus_x_preferred":[
        "\u0427\u0435\u043a\u0443\u0440\u043e\u0432\u0430"
    ],
    "name:und_x_variant":[
        "\u0427\u0435\u043a\u0443\u0440\u043e\u0432\u0430",
        "Chekurova"
    ],
    "wof:name":"Chekurova",
    "wof:placetype":"locality"
},
  "geometry": {"coordinates":[61.70083,56.03972],"type":"Point"}
}