{
  "type": "Feature",
  "properties": {
    "gn:admin1_code":"25",
    "gn:admin2_code":"11205600",
    "gn:asciiname":"Shevnevo",
    "gn:country_code":"RU",
    "gn:dem":203,
    "gn:feature_class":"P",
    "gn:feature_code":"PPL",
    "gn:name":"Shevnevo",
    "gn:population":0,
    "gn:timezone":"Europe/Moscow",
    "iso:country":"RU",
    "name:eng_x_preferred":[
        "Shevnevo"
    ],
    "name:rus_x_preferred":[
        "\u0428\u0435\u0432\u043d\u0435\u0432\u043e"
    ],
    "wof:name":"Shevnevo",
    "wof:placetype":"locality"
},
  "geometry": {"coordinates":[35.57611,55.12028000000001],"type":"Point"}
}