{
  "type": "Feature",
  "properties": {
    "gn:admin1_code":"33",
    "gn:asciiname":"Korobovshchina",
    "gn:country_code":"RU",
    "gn:dem":166,
    "gn:feature_class":"P",
    "gn:feature_code":"PPL",
    "gn:name":"Korobovshchina",
    "gn:population":0,
    "gn:timezone":"Europe/Kirov",
    "iso:country":"RU",
    "name:rus_x_preferred":[
        "\u041a\u043e\u0440\u043e\u0431\u043e\u0432\u0449\u0438\u043d\u0430"
    ],
    "name:und_x_variant":[
        "\u041a\u043e\u0440\u043e\u0431\u043e\u0432\u0449\u0438\u043d\u0430"
    ],
    "wof:name":"Korobovshchina",
    "wof:placetype":"locality"
},
  "geometry": {"coordinates":[49.37635,58.1277],"type":"Point"}
}