{
  "type": "Feature",
  "properties": {
    "gn:admin1_code":"52",
    "gn:asciiname":"Maglino",
    "gn:country_code":"RU",
    "gn:dem":173,
    "gn:feature_class":"P",
    "gn:feature_code":"PPL",
    "gn:name":"Maglino",
    "gn:population":0,
    "gn:timezone":"Europe/Moscow",
    "iso:country":"RU",
    "name:rus_x_preferred":[
        "\u041c\u0430\u0433\u043b\u0438\u043d\u043e"
    ],
    "name:und_x_variant":[
        "\u041c\u0430\u0433\u043b\u0438\u043d\u043e"
    ],
    "wof:name":"Maglino",
    "wof:placetype":"locality"
},
  "geometry": {"coordinates":[34.39079,58.66903000000001],"type":"Point"}
}