{
  "type": "Feature",
  "properties": {
    "gn:admin1_code":"7",
    "gn:asciiname":"Kaspiy",
    "gn:country_code":"RU",
    "gn:dem":-25,
    "gn:feature_class":"P",
    "gn:feature_code":"PPL",
    "gn:name":"Kaspiy",
    "gn:population":0,
    "gn:timezone":"Europe/Astrakhan",
    "iso:country":"RU",
    "name:eng_x_preferred":[
        "Kaspiy"
    ],
    "name:nor_x_preferred":[
        "Kaspij"
    ],
    "name:rus_x_preferred":[
        "\u041a\u0430\u0441\u043f\u0438\u0439"
    ],
    "wof:name":"Kaspiy",
    "wof:placetype":"locality"
},
  "geometry": {"coordinates":[48.3611,46.0525],"type":"Point"}
}