{
  "type": "Feature",
  "properties": {
    "gn:country":"RU",
    "gn:fcode":"PPL",
    "gn:pop":300,
    "iso:country":"RU",
    "name:rus_x_preferred":[
        "\u0421\u0442\u0430\u0440\u044b\u0435 \u041a\u0443\u0437\u044c\u043c\u0451\u043d\u043a\u0438"
    ],
    "name:unk_x_variant":[
        "\u0421\u0442\u0430\u0440\u044b\u0435 \u041a\u0443\u0437\u044c\u043c\u0451\u043d\u043a\u0438"
    ],
    "qs:name":"Staryye Kuz\u2019m\u00ebnki",
    "qs:photos_9r":0,
    "qs:photos_sr":0,
    "qs:pop_sr":"2",
    "wof:name":"Staryye Kuz\u2019m\u00ebnki",
    "wof:placetype":"locality",
    "wof:population":300
},
  "geometry": {"coordinates":[37.40928,55.04188],"type":"Point"}
}