{
  "type": "Feature",
  "properties": {
    "gn:admin1_code":"43",
    "gn:asciiname":"Gryaznovka",
    "gn:country_code":"RU",
    "gn:dem":184,
    "gn:feature_class":"P",
    "gn:feature_code":"PPL",
    "gn:name":"Gryaznovka",
    "gn:population":0,
    "gn:timezone":"Europe/Moscow",
    "iso:country":"RU",
    "name:rus_x_preferred":[
        "\u0413\u0440\u044f\u0437\u043d\u043e\u0432\u043a\u0430"
    ],
    "name:und_x_variant":[
        "Gryaznovo"
    ],
    "wof:name":"Gryaznovka",
    "wof:placetype":"locality"
},
  "geometry": {"coordinates":[39.24075,52.80574],"type":"Point"}
}