{
  "type": "Feature",
  "properties": {
    "gn:admin1_code":"86",
    "gn:asciiname":"Podlesnyy",
    "gn:country_code":"RU",
    "gn:dem":151,
    "gn:feature_class":"P",
    "gn:feature_code":"PPL",
    "gn:name":"Podlesnyy",
    "gn:population":0,
    "gn:timezone":"Europe/Moscow",
    "iso:country":"RU",
    "name:eng_x_preferred":[
        "Podlesnyy"
    ],
    "name:nor_x_preferred":[
        "Podlesnyj"
    ],
    "name:rus_x_preferred":[
        "\u041f\u043e\u0434\u043b\u0435\u0441\u043d\u044b\u0439"
    ],
    "name:und_x_variant":[
        "Kaganovich",
        "Podlesnyy"
    ],
    "wof:name":"Podlesnyy",
    "wof:placetype":"locality"
},
  "geometry": {"coordinates":[39.56848,51.80692],"type":"Point"}
}