{
  "type": "Feature",
  "properties": {
    "gn:admin1_code":"8.0",
    "gn:asciiname":"Ablyazovo",
    "gn:country_code":"RU",
    "gn:dem":558,
    "gn:feature_class":"P",
    "gn:feature_code":"PPL",
    "gn:name":"Ablyazovo",
    "gn:population":0,
    "gn:timezone":"Asia/Yekaterinburg",
    "iso:country":"RU",
    "name:che_x_preferred":[
        "\u0410\u0431\u043b\u044f\u0437\u043e\u0432\u043e"
    ],
    "name:nor_x_preferred":[
        "Abljazovo"
    ],
    "name:rus_x_preferred":[
        "\u0410\u0431\u043b\u044f\u0437\u043e\u0432\u043e"
    ],
    "name:tat_x_preferred":[
        "\u04d8\u0431\u043b\u04d9\u0437"
    ],
    "name:und_x_variant":[
        "Ablyazova",
        "Ablyazovo"
    ],
    "wof:name":"Ablyazovo",
    "wof:placetype":"locality"
},
  "geometry": {"coordinates":[58.81667,54.06667],"type":"Point"}
}