{
  "type": "Feature",
  "properties": {
    "gn:admin1_code":"28",
    "gn:asciiname":"Shaverki",
    "gn:cc2":"RU",
    "gn:country_code":"RU",
    "gn:dem":219,
    "gn:feature_class":"P",
    "gn:feature_code":"PPL",
    "gn:name":"Shaverki",
    "gn:population":0,
    "gn:timezone":"Europe/Moscow",
    "iso:country":"RU",
    "name:fin_x_preferred":[
        "Suoverkka"
    ],
    "name:rus_x_preferred":[
        "\u0428\u0430\u0432\u0435\u0440\u043a\u0438"
    ],
    "name:und_x_variant":[
        "\u0428\u0430\u0432\u0435\u0440\u043a\u0438"
    ],
    "wof:name":"Shaverki",
    "wof:placetype":"locality"
},
  "geometry": {"coordinates":[31.43333,63.25],"type":"Point"}
}