{
  "type": "Feature",
  "properties": {
    "gn:admin1_code":"61",
    "gn:asciiname":"Sulinskiy",
    "gn:country_code":"RU",
    "gn:dem":115,
    "gn:feature_class":"P",
    "gn:feature_code":"PPL",
    "gn:name":"Sulinskiy",
    "gn:population":0,
    "gn:timezone":"Europe/Moscow",
    "iso:country":"RU",
    "name:rus_x_preferred":[
        "\u0421\u0443\u043b\u0438\u043d\u0441\u043a\u0438\u0439"
    ],
    "wof:name":"Sulinskiy",
    "wof:placetype":"locality"
},
  "geometry": {"coordinates":[40.06149,47.8644],"type":"Point"}
}