{
  "type": "Feature",
  "properties": {
    "gn:admin1_code":"85",
    "gn:asciiname":"Puchnino",
    "gn:cc2":"RU",
    "gn:country_code":"RU",
    "gn:dem":154,
    "gn:feature_class":"P",
    "gn:feature_code":"PPL",
    "gn:name":"Puchnino",
    "gn:population":0,
    "gn:timezone":"Europe/Moscow",
    "iso:country":"RU",
    "name:rus_x_preferred":[
        "\u041f\u0443\u0447\u043d\u0438\u043d\u043e"
    ],
    "name:und_x_variant":[
        "Putschnino",
        "Puchnino",
        "\u041f\u0443\u0447\u043d\u0438\u043d\u043e"
    ],
    "wof:name":"Puchnino",
    "wof:placetype":"locality"
},
  "geometry": {"coordinates":[34.89722,59.15556],"type":"Point"}
}