{
  "type": "Feature",
  "properties": {
    "gn:admin1_code":"91",
    "gn:admin2_code":"1512216",
    "gn:asciiname":"Vysokogorodetsk",
    "gn:country_code":"RU",
    "gn:dem":282,
    "gn:elevation":"282.0",
    "gn:feature_class":"P",
    "gn:feature_code":"PPL",
    "gn:name":"Vysokogorodetsk",
    "gn:population":169,
    "gn:timezone":"Asia/Krasnoyarsk",
    "iso:country":"RU",
    "name:rus_x_colloquial":[
        "\u0413\u043e\u0440\u043e\u0434\u0435\u0446\u043a"
    ],
    "name:rus_x_historical":[
        "\u041a\u0430\u043d\u0430\u0440\u0430\u0439\u0447\u0438\u043a"
    ],
    "name:rus_x_preferred":[
        "\u0412\u044b\u0441\u043e\u043a\u043e\u0433\u043e\u0440\u043e\u0434\u0435\u0446\u043a"
    ],
    "name:rus_x_variant":[
        "\u0412-\u0413\u043e\u0440\u043e\u0434\u0435\u0446\u043a",
        "\u0413\u043e\u0440\u043e\u0434\u0435\u0446\u043a",
        "\u041a\u0430\u043d\u0430\u0440\u0430\u0439\u0447\u0438\u043a"
    ],
    "name:und_x_variant":[
        "Vysoko-Gorodetskaya"
    ],
    "wof:name":"Vysokogorodetsk",
    "wof:placetype":"locality",
    "wof:population":169
},
  "geometry": {"coordinates":[96.29123,56.71169],"type":"Point"}
}