{
  "type": "Feature",
  "properties": {
    "gn:admin1_code":"91",
    "gn:asciiname":"Kolon",
    "gn:country_code":"RU",
    "gn:dem":161,
    "gn:feature_class":"P",
    "gn:feature_code":"PPL",
    "gn:name":"Kolon",
    "gn:population":0,
    "gn:timezone":"Asia/Krasnoyarsk",
    "iso:country":"RU",
    "name:eng_x_preferred":[
        "Kolon"
    ],
    "name:nor_x_preferred":[
        "Kolon"
    ],
    "name:rus_x_preferred":[
        "\u041a\u043e\u043b\u043e\u043d"
    ],
    "wof:name":"Kolon",
    "wof:placetype":"locality"
},
  "geometry": {"coordinates":[95.10722,57.0175],"type":"Point"}
}