{
  "type": "Feature",
  "properties": {
    "gn:admin1_code":"54",
    "gn:asciiname":"Novokolomzino",
    "gn:cc2":"RU",
    "gn:country_code":"RU",
    "gn:dem":115,
    "gn:feature_class":"P",
    "gn:feature_code":"PPL",
    "gn:name":"Novokolomzino",
    "gn:population":0,
    "gn:timezone":"Asia/Omsk",
    "iso:country":"RU",
    "name:rus_x_preferred":[
        "\u041d\u043e\u0432\u043e\u043a\u043e\u043b\u043e\u043c\u0437\u0438\u043d\u043e"
    ],
    "name:und_x_variant":[
        "Novoye Kolomzino",
        "Kolomzino",
        "Novokolomzino",
        "\u041d\u043e\u0432\u043e\u043a\u043e\u043b\u043e\u043c\u0437\u0438\u043d\u043e"
    ],
    "wof:name":"Novokolomzino",
    "wof:placetype":"locality"
},
  "geometry": {"coordinates":[71.98971999999998,54.34806],"type":"Point"}
}