{
  "type": "Feature",
  "properties": {
    "gn:admin1_code":"77",
    "gn:asciiname":"Kunilovo",
    "gn:country_code":"RU",
    "gn:dem":221,
    "gn:feature_class":"P",
    "gn:feature_code":"PPL",
    "gn:name":"Kunilovo",
    "gn:population":0,
    "gn:timezone":"Europe/Moscow",
    "iso:country":"RU",
    "name:rus_x_preferred":[
        "\u041a\u0443\u043d\u0438\u043b\u043e\u0432\u043e"
    ],
    "wof:name":"Kunilovo",
    "wof:placetype":"locality"
},
  "geometry": {"coordinates":[34.46299,56.97116],"type":"Point"}
}