{
  "type": "Feature",
  "properties": {
    "gn:admin1_code":"88",
    "gn:asciiname":"Kraynovo",
    "gn:country_code":"RU",
    "gn:dem":148,
    "gn:feature_class":"P",
    "gn:feature_code":"PPL",
    "gn:name":"Kraynovo",
    "gn:population":0,
    "gn:timezone":"Europe/Moscow",
    "iso:country":"RU",
    "name:rus_x_preferred":[
        "\u041a\u0440\u0430\u0439\u043d\u043e\u0432\u043e"
    ],
    "name:und_x_variant":[
        "Kobel\u00ebvo",
        "Kraynovo"
    ],
    "wof:name":"Kraynovo",
    "wof:placetype":"locality"
},
  "geometry": {"coordinates":[38.08333,57.61666999999999],"type":"Point"}
}