{
  "type": "Feature",
  "properties": {
    "gn:admin1_code":"11",
    "gn:asciiname":"Kuytun",
    "gn:country_code":"RU",
    "gn:dem":687,
    "gn:feature_class":"P",
    "gn:feature_code":"PPL",
    "gn:name":"Kuytun",
    "gn:population":500,
    "gn:timezone":"Asia/Irkutsk",
    "iso:country":"RU",
    "name:ara_x_preferred":[
        "\u0643\u064a\u0648\u062a\u0648\u0646"
    ],
    "name:ceb_x_preferred":[
        "Kuytun Shi"
    ],
    "name:deu_x_preferred":[
        "Kuytun"
    ],
    "name:eng_x_preferred":[
        "Kuytun"
    ],
    "name:fin_x_preferred":[
        "Kuytun"
    ],
    "name:fra_x_preferred":[
        "Kuitun"
    ],
    "name:ita_x_preferred":[
        "Kuytun"
    ],
    "name:jpn_x_preferred":[
        "\u30af\u30a4\u30c8\u30a5\u30f3\u5e02"
    ],
    "name:kik_x_preferred":[
        "Kuytun"
    ],
    "name:kor_x_preferred":[
        "\ucfe0\uc774\ud230\uc2dc"
    ],
    "name:nor_x_preferred":[
        "Kujtun"
    ],
    "name:nor_x_variant":[
        "Kuitun"
    ],
    "name:pol_x_preferred":[
        "Kuytun"
    ],
    "name:rus_x_preferred":[
        "\u041a\u0443\u0439\u0442\u0443\u043d"
    ],
    "name:spa_x_preferred":[
        "Kuytun"
    ],
    "name:srp_x_preferred":[
        "\u041a\u0443\u0458\u0442\u0443\u0435\u043d"
    ],
    "name:swe_x_preferred":[
        "K\u00fcytun"
    ],
    "name:tur_x_preferred":[
        "Kuytun"
    ],
    "name:uig_x_preferred":[
        "\u0643\u06c8\u064a\u062a\u06c7\u0646 \u0634\u06d5\u06be\u0649\u0631\u0649"
    ],
    "name:und_x_variant":[
        "Kuytunskoye",
        "Kuitun",
        "Kuytumskoye",
        "\u041a\u0443\u0439\u0442\u0443\u043d",
        "Kuytun"
    ],
    "name:urd_x_preferred":[
        "\u06a9\u0648\u0626\u062a\u0648\u0646"
    ],
    "name:vie_x_preferred":[
        "Kuytun"
    ],
    "name:war_x_preferred":[
        "Kuitun"
    ],
    "name:zho_x_preferred":[
        "\u594e\u5c6f\u5e02"
    ],
    "wof:name":"Kuytun",
    "wof:placetype":"locality",
    "wof:population":500
},
  "geometry": {"coordinates":[107.75377,51.52592],"type":"Point"}
}