{
  "type": "Feature",
  "properties": {
    "gn:admin1_code":"11",
    "gn:asciiname":"Kuytun",
    "gn:country_code":"RU",
    "gn:dem":687,
    "gn:feature_class":"P",
    "gn:feature_code":"PPL",
    "gn:name":"Kuytun",
    "gn:population":500,
    "gn:timezone":"Asia/Irkutsk",
    "iso:country":"RU",
    "name:eng_x_preferred":[
        "Kuytun"
    ],
    "name:nor_x_preferred":[
        "Kujtun"
    ],
    "name:rus_x_preferred":[
        "\u041a\u0443\u0439\u0442\u0443\u043d"
    ],
    "name:und_x_variant":[
        "Kuytunskoye",
        "Kuitun",
        "Kuytumskoye",
        "\u041a\u0443\u0439\u0442\u0443\u043d",
        "Kuytun"
    ],
    "wof:name":"Kuytun",
    "wof:placetype":"locality",
    "wof:population":500
},
  "geometry": {"coordinates":[107.75377,51.52592],"type":"Point"}
}