{
  "type": "Feature",
  "properties": {
    "gn:admin1_code":"33",
    "gn:asciiname":"Vysokovtsy",
    "gn:country_code":"RU",
    "gn:dem":215,
    "gn:feature_class":"P",
    "gn:feature_code":"PPL",
    "gn:name":"Vysokovtsy",
    "gn:population":0,
    "gn:timezone":"Europe/Kirov",
    "iso:country":"RU",
    "name:eng_x_preferred":[
        "Vysokovtsy"
    ],
    "name:nor_x_preferred":[
        "Vysokovo"
    ],
    "name:rus_x_preferred":[
        "\u0412\u044b\u0441\u043e\u043a\u043e\u0432\u043e"
    ],
    "name:und_x_variant":[
        "Vysokovtsy Vtoryye"
    ],
    "wof:name":"Vysokovtsy",
    "wof:placetype":"locality"
},
  "geometry": {"coordinates":[51.60198,59.46847],"type":"Point"}
}