{
  "type": "Feature",
  "properties": {
    "gn:admin1_code":"69",
    "gn:asciiname":"Podgornaya",
    "gn:cc2":"RU",
    "gn:country_code":"RU",
    "gn:dem":226,
    "gn:feature_class":"P",
    "gn:feature_code":"PPL",
    "gn:name":"Podgornaya",
    "gn:population":0,
    "gn:timezone":"Europe/Moscow",
    "iso:country":"RU",
    "name:rus_x_preferred":[
        "\u041f\u043e\u0434\u0433\u043e\u0440\u043d\u0430\u044f"
    ],
    "name:und_x_variant":[
        "Pogibelka",
        "Podgornaya"
    ],
    "wof:name":"Podgornaya",
    "wof:placetype":"locality"
},
  "geometry": {"coordinates":[33.18,54.59194],"type":"Point"}
}