{
  "type": "Feature",
  "properties": {
    "gn:admin1_code":"21",
    "gn:asciiname":"Popovskoye",
    "gn:country_code":"RU",
    "gn:dem":117,
    "gn:feature_class":"P",
    "gn:feature_code":"PPL",
    "gn:name":"Popovskoye",
    "gn:population":0,
    "gn:timezone":"Europe/Moscow",
    "iso:country":"RU",
    "name:rus_x_preferred":[
        "\u041f\u043e\u043f\u043e\u0432\u0441\u043a\u043e\u0435"
    ],
    "name:und_x_variant":[
        "Popovskaya",
        "Popovskoye",
        "\u041f\u043e\u043f\u043e\u0432\u0441\u043a\u043e\u0435"
    ],
    "wof:name":"Popovskoye",
    "wof:placetype":"locality"
},
  "geometry": {"coordinates":[41.20425,57.08091999999999],"type":"Point"}
}