{
  "type": "Feature",
  "properties": {
    "gn:admin1_code":"12.0",
    "gn:asciiname":"Chalkhon-Chu",
    "gn:country_code":"RU",
    "gn:dem":1014,
    "gn:feature_class":"P",
    "gn:feature_code":"PPL",
    "gn:name":"Chalkhon-Chu",
    "gn:population":0,
    "gn:timezone":"Europe/Moscow",
    "iso:country":"RU",
    "name:rus_x_preferred":[
        "\u0427\u0430\u043b\u0445\u043e\u043d-\u0427\u0443"
    ],
    "wof:name":"Chalkhon-Chu",
    "wof:placetype":"locality"
},
  "geometry": {"coordinates":[45.74639000000001,42.92056],"type":"Point"}
}