{
  "type": "Feature",
  "properties": {
    "gn:admin1_code":"84",
    "gn:asciiname":"Kudryashev",
    "gn:country_code":"RU",
    "gn:dem":169,
    "gn:feature_class":"P",
    "gn:feature_code":"PPL",
    "gn:name":"Kudryash\u00ebv",
    "gn:population":0,
    "gn:timezone":"Europe/Volgograd",
    "iso:country":"RU",
    "name:rus_x_preferred":[
        "\u041a\u0443\u0434\u0440\u044f\u0448\u0451\u0432"
    ],
    "name:und_x_variant":[
        "Kudryash\u00ebv",
        "\u041a\u0443\u0434\u0440\u044f\u0448\u0451\u0432"
    ],
    "wof:name":"Kudryashev",
    "wof:placetype":"locality"
},
  "geometry": {"coordinates":[44.35,49.86667],"type":"Point"}
}