{
  "type": "Feature",
  "properties": {
    "gn:admin1_code":"83",
    "gn:asciiname":"Koptsevo",
    "gn:country_code":"RU",
    "gn:dem":121,
    "gn:feature_class":"P",
    "gn:feature_code":"PPL",
    "gn:name":"Koptsevo",
    "gn:population":0,
    "gn:timezone":"Europe/Moscow",
    "iso:country":"RU",
    "name:rus_x_preferred":[
        "\u041a\u043e\u043f\u0446\u043e\u0432\u043e"
    ],
    "name:und_x_variant":[
        "Koptsovo",
        "Koptsevo"
    ],
    "wof:name":"Koptsevo",
    "wof:placetype":"locality"
},
  "geometry": {"coordinates":[41.9121,56.13093000000001],"type":"Point"}
}