{
  "type": "Feature",
  "properties": {
    "gn:admin1_code":"52",
    "gn:asciiname":"Galicheno",
    "gn:country_code":"RU",
    "gn:dem":244,
    "gn:feature_class":"P",
    "gn:feature_code":"PPL",
    "gn:name":"Galicheno",
    "gn:population":0,
    "gn:timezone":"Europe/Moscow",
    "iso:country":"RU",
    "name:rus_x_preferred":[
        "\u0413\u0430\u043b\u0438\u0447\u0435\u043d\u043e"
    ],
    "wof:name":"Galicheno",
    "wof:placetype":"locality"
},
  "geometry": {"coordinates":[32.24156,57.28842],"type":"Point"}
}