{
  "type": "Feature",
  "properties": {
    "gn:admin1_code":"73",
    "gn:asciiname":"Kzyl-Mesha",
    "gn:country_code":"RU",
    "gn:dem":106,
    "gn:feature_class":"P",
    "gn:feature_code":"PPL",
    "gn:name":"Kzyl-Mesha",
    "gn:population":0,
    "gn:timezone":"Europe/Moscow",
    "iso:country":"RU",
    "name:rus_x_preferred":[
        "\u041a\u0437\u044b\u043b-\u041c\u0435\u0448\u0430"
    ],
    "name:und_x_variant":[
        "Bukmysh",
        "Kzyl-Mesha",
        "Kyzyl-Mesha"
    ],
    "wof:name":"Kzyl-Mesha",
    "wof:placetype":"locality"
},
  "geometry": {"coordinates":[50.3632,56.076],"type":"Point"}
}