{
  "type": "Feature",
  "properties": {
    "gn:admin1_code":"05",
    "gn:asciiname":"Poduval'noye",
    "gn:country_code":"RU",
    "gn:dem":137,
    "gn:feature_class":"P",
    "gn:feature_code":"PPL",
    "gn:name":"Poduval\u2019noye",
    "gn:population":0,
    "gn:timezone":"Asia/Yakutsk",
    "iso:country":"RU",
    "name:eng_x_preferred":[
        "Poduval'noye"
    ],
    "name:nor_x_preferred":[
        "Poduvalnoje"
    ],
    "name:rus_x_preferred":[
        "\u041f\u043e\u0434\u0443\u0432\u0430\u043b\u044c\u043d\u043e\u0435"
    ],
    "name:und_x_variant":[
        "Poduval\u2019noye"
    ],
    "wof:name":"Poduval'noye",
    "wof:placetype":"locality"
},
  "geometry": {"coordinates":[127.80867000000001,49.97972],"type":"Point"}
}