{
  "type": "Feature",
  "properties": {
    "gn:admin1_code":"93",
    "gn:asciiname":"Gorda",
    "gn:country_code":"RU",
    "gn:dem":618,
    "gn:feature_class":"P",
    "gn:feature_code":"PPL",
    "gn:name":"Gorda",
    "gn:population":0,
    "gn:timezone":"Asia/Chita",
    "iso:country":"RU",
    "name:rus_x_preferred":[
        "\u0413\u043e\u0440\u0434\u0430"
    ],
    "name:spa_x_preferred":[
        "Gorda"
    ],
    "wof:name":"Gorda",
    "wof:placetype":"locality"
},
  "geometry": {"coordinates":[118.88809999999999,50.1682],"type":"Point"}
}