{
  "type": "Feature",
  "properties": {
    "gn:admin1_code":"84",
    "gn:asciiname":"Mukovnin",
    "gn:country_code":"RU",
    "gn:dem":132,
    "gn:feature_class":"P",
    "gn:feature_code":"PPL",
    "gn:name":"Mukovnin",
    "gn:population":0,
    "gn:timezone":"Europe/Volgograd",
    "iso:country":"RU",
    "name:eng_x_preferred":[
        "Mukovnin"
    ],
    "name:nor_x_preferred":[
        "Mukovnin"
    ],
    "name:rus_x_preferred":[
        "\u041c\u0443\u043a\u043e\u0432\u043d\u0438\u043d"
    ],
    "name:und_x_variant":[
        "Mukovninskiy",
        "Mukovkin"
    ],
    "wof:name":"Mukovnin",
    "wof:placetype":"locality"
},
  "geometry": {"coordinates":[43.2717,49.08647],"type":"Point"}
}