{
  "type": "Feature",
  "properties": {
    "gn:admin1_code":"10.0",
    "gn:asciiname":"Brovnichi",
    "gn:country_code":"RU",
    "gn:dem":152,
    "gn:feature_class":"P",
    "gn:feature_code":"PPL",
    "gn:name":"Brovnichi",
    "gn:population":0,
    "gn:timezone":"Europe/Moscow",
    "iso:country":"RU",
    "name:rus_x_preferred":[
        "\u0411\u0440\u043e\u0432\u043d\u0438\u0447\u0438"
    ],
    "name:und_x_variant":[
        "\u0411\u0440\u043e\u0432\u043d\u0438\u0447\u0438"
    ],
    "wof:name":"Brovnichi",
    "wof:placetype":"locality"
},
  "geometry": {"coordinates":[32.31199,52.23225],"type":"Point"}
}