{
  "type": "Feature",
  "properties": {
    "gn:admin1_code":"64.0",
    "gn:asciiname":"Sanatornoye",
    "gn:country_code":"RU",
    "gn:dem":96,
    "gn:feature_class":"P",
    "gn:feature_code":"PPL",
    "gn:name":"Sanatornoye",
    "gn:population":0,
    "gn:timezone":"Asia/Sakhalin",
    "iso:country":"RU",
    "name:rus_x_preferred":[
        "\u0421\u0430\u043d\u0430\u0442\u043e\u0440\u043d\u043e\u0435"
    ],
    "wof:name":"Sanatornoye",
    "wof:placetype":"locality"
},
  "geometry": {"coordinates":[142.63078000000004,47.10297],"type":"Point"}
}