{
  "type": "Feature",
  "properties": {
    "gn:admin1_code":"4",
    "gn:asciiname":"Talitsa",
    "gn:country_code":"RU",
    "gn:dem":292,
    "gn:feature_class":"P",
    "gn:feature_code":"PPL",
    "gn:name":"Talitsa",
    "gn:population":0,
    "gn:timezone":"Asia/Barnaul",
    "iso:country":"RU",
    "name:rus_x_preferred":[
        "\u0422\u0430\u043b\u0438\u0446\u0430"
    ],
    "wof:name":"Talitsa",
    "wof:placetype":"locality"
},
  "geometry": {"coordinates":[85.06659999999999,54.3001],"type":"Point"}
}