{
  "type": "Feature",
  "properties": {
    "gn:admin1_code":"67.0",
    "gn:asciiname":"Borono-Mikhaylovka",
    "gn:country_code":"RU",
    "gn:dem":176,
    "gn:feature_class":"P",
    "gn:feature_code":"PPL",
    "gn:name":"Borono-Mikhaylovka",
    "gn:population":0,
    "gn:timezone":"Europe/Saratov",
    "iso:country":"RU",
    "name:eng_x_preferred":[
        "Borono-Mikhaylovka"
    ],
    "name:nor_x_preferred":[
        "Borono-Mikhajlovka"
    ],
    "name:rus_x_preferred":[
        "\u0411\u043e\u0440\u043e\u043d\u043e-\u041c\u0438\u0445\u0430\u0439\u043b\u043e\u0432\u043a\u0430"
    ],
    "name:und_x_variant":[
        "Barono-Mikhaylovka",
        "\u0411\u043e\u0440\u043e\u043d\u043e-\u041c\u0438\u0445\u0430\u0439\u043b\u043e\u0432\u043a\u0430",
        "Borono-Mikhaylovka"
    ],
    "wof:name":"Borono-Mikhaylovka",
    "wof:placetype":"locality"
},
  "geometry": {"coordinates":[43.17975,52.14452],"type":"Point"}
}