{
  "type": "Feature",
  "properties": {
    "gn:admin1_code":"61.0",
    "gn:asciiname":"Aleksandrovo-Markovo",
    "gn:country_code":"RU",
    "gn:dem":20,
    "gn:feature_class":"P",
    "gn:feature_code":"PPL",
    "gn:name":"Aleksandrovo-Markovo",
    "gn:population":0,
    "gn:timezone":"Europe/Moscow",
    "iso:country":"RU",
    "name:nor_x_preferred":[
        "Aleksandrovo-Markovo"
    ],
    "name:rus_x_preferred":[
        "\u0410\u043b\u0435\u043a\u0441\u0430\u043d\u0434\u0440\u043e\u0432\u043e-\u041c\u0430\u0440\u043a\u043e\u0432\u043e"
    ],
    "name:und_x_variant":[
        "Aleksandro-Markovskiy",
        "Aleksandrovo-Markovo"
    ],
    "wof:name":"Aleksandrovo-Markovo",
    "wof:placetype":"locality"
},
  "geometry": {"coordinates":[38.55651,47.23134],"type":"Point"}
}