{
  "type": "Feature",
  "properties": {
    "gn:admin1_code":"69",
    "gn:asciiname":"Anan'ino",
    "gn:country_code":"RU",
    "gn:dem":210,
    "gn:feature_class":"P",
    "gn:feature_code":"PPL",
    "gn:name":"Anan\u2019ino",
    "gn:population":0,
    "gn:timezone":"Europe/Moscow",
    "iso:country":"RU",
    "name:nor_x_preferred":[
        "Ananino"
    ],
    "name:rus_x_preferred":[
        "\u0410\u043d\u0430\u043d\u044c\u0438\u043d\u043e"
    ],
    "name:und_x_variant":[
        "Anan\u2019ino"
    ],
    "wof:name":"Anan'ino",
    "wof:placetype":"locality"
},
  "geometry": {"coordinates":[32.56264,54.4586],"type":"Point"}
}