{
  "type": "Feature",
  "properties": {
    "gn:admin1_code":"21",
    "gn:asciiname":"Ganshino",
    "gn:country_code":"RU",
    "gn:dem":113,
    "gn:feature_class":"P",
    "gn:feature_code":"PPL",
    "gn:name":"Ganshino",
    "gn:population":0,
    "gn:timezone":"Europe/Moscow",
    "iso:country":"RU",
    "name:rus_x_preferred":[
        "\u0413\u0430\u043d\u0448\u0438\u043d\u043e"
    ],
    "wof:name":"Ganshino",
    "wof:placetype":"locality"
},
  "geometry": {"coordinates":[40.33164,56.61444],"type":"Point"}
}