{
  "type": "Feature",
  "properties": {
    "gn:admin1_code":"33",
    "gn:asciiname":"Sodom",
    "gn:country_code":"RU",
    "gn:dem":182,
    "gn:feature_class":"P",
    "gn:feature_code":"PPL",
    "gn:name":"Sodom",
    "gn:population":0,
    "gn:timezone":"Europe/Kirov",
    "iso:country":"RU",
    "name:deu_x_preferred":[
        "Sodom"
    ],
    "name:heb_x_preferred":[
        "\u05e1\u05d3\u05d5\u05dd"
    ],
    "name:ind_x_preferred":[
        "Sodom"
    ],
    "name:ita_x_preferred":[
        "Sodom"
    ],
    "name:jpn_x_preferred":[
        "\u30bd\u30c9\u30e0"
    ],
    "name:nld_x_preferred":[
        "Sodom"
    ],
    "name:por_x_preferred":[
        "Sodom"
    ],
    "name:rus_x_preferred":[
        "\u0421\u043e\u0434\u043e\u043c"
    ],
    "name:srp_x_preferred":[
        "\u0421\u043e\u0434\u043e\u043c"
    ],
    "name:ukr_x_preferred":[
        "\u0421\u043e\u0434\u043e\u043c"
    ],
    "wof:name":"Sodom",
    "wof:placetype":"locality"
},
  "geometry": {"coordinates":[47.42183,58.68482],"type":"Point"}
}