{
  "type": "Feature",
  "properties": {
    "gn:admin1_code":"33",
    "gn:asciiname":"Sodom",
    "gn:country_code":"RU",
    "gn:dem":182,
    "gn:feature_class":"P",
    "gn:feature_code":"PPL",
    "gn:name":"Sodom",
    "gn:population":0,
    "gn:timezone":"Europe/Kirov",
    "iso:country":"RU",
    "name:rus_x_preferred":[
        "\u0421\u043e\u0434\u043e\u043c"
    ],
    "name:und_x_variant":[
        "\u0421\u043e\u0434\u043e\u043c"
    ],
    "wof:name":"Sodom",
    "wof:placetype":"locality"
},
  "geometry": {"coordinates":[47.42183,58.68482],"type":"Point"}
}