{
  "type": "Feature",
  "properties": {
    "gn:admin1_code":"77",
    "gn:asciiname":"Sizhinskoye",
    "gn:country_code":"RU",
    "gn:dem":245,
    "gn:feature_class":"P",
    "gn:feature_code":"PPL",
    "gn:name":"Sizhinskoye",
    "gn:population":0,
    "gn:timezone":"Europe/Moscow",
    "iso:country":"RU",
    "name:rus_x_preferred":[
        "\u0421\u0438\u0436\u0438\u043d\u0441\u043a\u043e\u0435"
    ],
    "wof:name":"Sizhinskoye",
    "wof:placetype":"locality"
},
  "geometry": {"coordinates":[33.54020999999999,56.76027],"type":"Point"}
}