{
  "type": "Feature",
  "properties": {
    "gn:admin1_code":"63",
    "gn:asciiname":"Urasalakh",
    "gn:country_code":"RU",
    "gn:dem":273,
    "gn:feature_class":"P",
    "gn:feature_code":"PPL",
    "gn:name":"Urasalakh",
    "gn:population":0,
    "gn:timezone":"Asia/Yakutsk",
    "iso:country":"RU",
    "name:eng_x_preferred":[
        "Urasalakh"
    ],
    "name:nor_x_preferred":[
        "Urasalakh"
    ],
    "name:rus_x_preferred":[
        "\u0423\u0440\u0430\u0441\u0430\u043b\u0430\u0445"
    ],
    "name:und_x_variant":[
        "Urasalaakh",
        "Urasalakh"
    ],
    "wof:name":"Urasalakh",
    "wof:placetype":"locality"
},
  "geometry": {"coordinates":[131.25541000000001,61.31202],"type":"Point"}
}