{
  "type": "Feature",
  "properties": {
    "gn:admin1_code":"37",
    "gn:asciiname":"Mikhali",
    "gn:country_code":"RU",
    "gn:dem":151,
    "gn:feature_class":"P",
    "gn:feature_code":"PPL",
    "gn:name":"Mikhali",
    "gn:population":0,
    "gn:timezone":"Europe/Moscow",
    "iso:country":"RU",
    "name:eng_x_preferred":[
        "Mikhali"
    ],
    "name:nor_x_preferred":[
        "Mikhali"
    ],
    "name:rus_x_preferred":[
        "\u041c\u0438\u0445\u0430\u043b\u0438"
    ],
    "wof:name":"Mikhali",
    "wof:placetype":"locality"
},
  "geometry": {"coordinates":[47.17512,59.0205],"type":"Point"}
}