{
  "type": "Feature",
  "properties": {
    "gn:admin1_code":"33",
    "gn:asciiname":"Dryagino",
    "gn:country_code":"RU",
    "gn:dem":145,
    "gn:feature_class":"P",
    "gn:feature_code":"PPL",
    "gn:name":"Dryagino",
    "gn:population":0,
    "gn:timezone":"Europe/Kirov",
    "iso:country":"RU",
    "name:rus_x_preferred":[
        "\u0414\u0440\u044f\u0433\u0438\u043d\u043e"
    ],
    "wof:name":"Dryagino",
    "wof:placetype":"locality"
},
  "geometry": {"coordinates":[48.0488,60.5741],"type":"Point"}
}