{
  "type": "Feature",
  "properties": {
    "gn:admin1_code":"93",
    "gn:asciiname":"Kozlovo",
    "gn:country_code":"RU",
    "gn:dem":680,
    "gn:feature_class":"P",
    "gn:feature_code":"PPL",
    "gn:name":"Kozlovo",
    "gn:population":0,
    "gn:timezone":"Asia/Chita",
    "iso:country":"RU",
    "name:eng_x_preferred":[
        "Kozlovo"
    ],
    "name:nor_x_preferred":[
        "Kozlovo"
    ],
    "name:rus_x_preferred":[
        "\u041a\u043e\u0437\u043b\u043e\u0432\u043e"
    ],
    "wof:name":"Kozlovo",
    "wof:placetype":"locality"
},
  "geometry": {"coordinates":[118.93177,51.20655],"type":"Point"}
}