{
  "type": "Feature",
  "properties": {
    "gn:admin1_code":"77",
    "gn:asciiname":"Kleshnevo",
    "gn:country_code":"RU",
    "gn:dem":187,
    "gn:feature_class":"P",
    "gn:feature_code":"PPL",
    "gn:name":"Kleshn\u00ebvo",
    "gn:population":0,
    "gn:timezone":"Europe/Moscow",
    "iso:country":"RU",
    "name:rus_x_preferred":[
        "\u041a\u043b\u0435\u0448\u043d\u0451\u0432\u043e"
    ],
    "name:und_x_variant":[
        "Kleshn\u00ebvo",
        "\u041a\u043b\u0435\u0448\u043d\u0451\u0432\u043e"
    ],
    "wof:name":"Kleshnevo",
    "wof:placetype":"locality"
},
  "geometry": {"coordinates":[34.46556,56.25963],"type":"Point"}
}