{
  "type": "Feature",
  "properties": {
    "gn:admin1_code":"65",
    "gn:asciiname":"Krasnaya Niva",
    "gn:country_code":"RU",
    "gn:dem":157,
    "gn:feature_class":"P",
    "gn:feature_code":"PPL",
    "gn:name":"Krasnaya Niva",
    "gn:population":0,
    "gn:timezone":"Europe/Samara",
    "iso:country":"RU",
    "name:rus_x_preferred":[
        "\u041a\u0440\u0430\u0441\u043d\u0430\u044f \u041d\u0438\u0432\u0430"
    ],
    "wof:name":"Krasnaya Niva",
    "wof:placetype":"locality"
},
  "geometry": {"coordinates":[49.7159,52.5227],"type":"Point"}
}