{
  "type": "Feature",
  "properties": {
    "gn:admin1_code":"77",
    "gn:asciiname":"Moshenka",
    "gn:country_code":"RU",
    "gn:dem":213,
    "gn:feature_class":"P",
    "gn:feature_code":"PPL",
    "gn:name":"Mosh\u00ebnka",
    "gn:population":0,
    "gn:timezone":"Europe/Moscow",
    "iso:country":"RU",
    "name:rus_x_preferred":[
        "\u041c\u043e\u0448\u0451\u043d\u043a\u0430"
    ],
    "name:und_x_variant":[
        "Mosh\u00ebnka"
    ],
    "wof:name":"Moshenka",
    "wof:placetype":"locality"
},
  "geometry": {"coordinates":[33.26318,57.36228000000001],"type":"Point"}
}