{
  "type": "Feature",
  "properties": {
    "gn:admin1_code":"10",
    "gn:asciiname":"Udol'ye",
    "gn:country_code":"RU",
    "gn:dem":149,
    "gn:feature_class":"P",
    "gn:feature_code":"PPL",
    "gn:name":"Udol\u2019ye",
    "gn:population":0,
    "gn:timezone":"Europe/Moscow",
    "iso:country":"RU",
    "name:rus_x_preferred":[
        "\u0423\u0434\u043e\u043b\u044c\u0435"
    ],
    "name:rus_x_variant":[
        "Udol\u2019ye"
    ],
    "name:und_x_variant":[
        "Udol\u2019ye",
        "\u0423\u0434\u043e\u043b\u044c\u0435"
    ],
    "wof:name":"Udol'ye",
    "wof:placetype":"locality"
},
  "geometry": {"coordinates":[33.61762,52.52984],"type":"Point"}
}