{
  "type": "Feature",
  "properties": {
    "gn:admin1_code":"85",
    "gn:asciiname":"Poteryayevo",
    "gn:country_code":"RU",
    "gn:dem":167,
    "gn:feature_class":"P",
    "gn:feature_code":"PPL",
    "gn:name":"Poteryayevo",
    "gn:population":0,
    "gn:timezone":"Europe/Moscow",
    "iso:country":"RU",
    "name:rus_x_preferred":[
        "\u041f\u043e\u0442\u0435\u0440\u044f\u0435\u0432\u043e"
    ],
    "name:und_x_variant":[
        "\u041f\u043e\u0442\u0435\u0440\u044f\u0435\u0432\u043e"
    ],
    "wof:name":"Poteryayevo",
    "wof:placetype":"locality"
},
  "geometry": {"coordinates":[38.6476,59.3014],"type":"Point"}
}