{
  "type": "Feature",
  "properties": {
    "gn:admin1_code":"8",
    "gn:asciiname":"Staryy Kyzyl-Yar",
    "gn:country_code":"RU",
    "gn:dem":117,
    "gn:feature_class":"P",
    "gn:feature_code":"PPL",
    "gn:name":"Staryy Kyzyl-Yar",
    "gn:population":0,
    "gn:timezone":"Asia/Yekaterinburg",
    "iso:country":"RU",
    "name:rus_x_preferred":[
        "\u0421\u0442\u0430\u0440\u044b\u0439 \u041a\u044b\u0437\u044b\u043b-\u042f\u0440"
    ],
    "name:und_x_variant":[
        "\u0421\u0442\u0430\u0440\u043e\u043a\u0437\u044b\u043b-\u042f\u0440",
        "Starokzyl-Yar",
        "Staryy Kyzyl-Yar"
    ],
    "wof:name":"Staryy Kyzyl-Yar",
    "wof:placetype":"locality"
},
  "geometry": {"coordinates":[56.15608,56.24424000000001],"type":"Point"}
}