{
  "type": "Feature",
  "properties": {
    "gn:admin1_code":"29",
    "gn:asciiname":"Krutaya",
    "gn:country_code":"RU",
    "gn:dem":293,
    "gn:feature_class":"P",
    "gn:feature_code":"PPL",
    "gn:name":"Krutaya",
    "gn:population":0,
    "gn:timezone":"Asia/Novokuznetsk",
    "iso:country":"RU",
    "name:rus_x_preferred":[
        "\u041a\u0440\u0443\u0442\u0430\u044f"
    ],
    "name:und_x_variant":[
        "\u041a\u0440\u0443\u0442\u0430\u044f"
    ],
    "wof:name":"Krutaya",
    "wof:placetype":"locality"
},
  "geometry": {"coordinates":[87.17200000000003,53.2817],"type":"Point"}
}