{
  "type": "Feature",
  "properties": {
    "gn:admin1_code":"32",
    "gn:asciiname":"Kar'yegan",
    "gn:country_code":"RU",
    "gn:dem":38,
    "gn:feature_class":"P",
    "gn:feature_code":"PPL",
    "gn:name":"Kar\u2019yegan",
    "gn:population":0,
    "gn:timezone":"Asia/Yekaterinburg",
    "iso:country":"RU",
    "name:eng_x_preferred":[
        "Kar'yegan"
    ],
    "name:nor_x_preferred":[
        "Karjegan"
    ],
    "name:rus_x_preferred":[
        "\u041a\u0430\u0440\u044c\u0435\u0433\u0430\u043d"
    ],
    "name:und_x_variant":[
        "Kar\u2019yegan"
    ],
    "wof:name":"Kar'yegan",
    "wof:placetype":"locality"
},
  "geometry": {"coordinates":[72.58333,60.96666999999999],"type":"Point"}
}