{
  "type": "Feature",
  "properties": {
    "gn:admin1_code":"6.0",
    "gn:asciiname":"Chukhari",
    "gn:country_code":"RU",
    "gn:dem":68,
    "gn:feature_class":"P",
    "gn:feature_code":"PPL",
    "gn:name":"Chukhari",
    "gn:population":0,
    "gn:timezone":"Europe/Moscow",
    "iso:country":"RU",
    "name:rus_x_preferred":[
        "\u0427\u0443\u0445\u0430\u0440\u0438"
    ],
    "name:und_x_variant":[
        "Chukhary",
        "Chukhari"
    ],
    "wof:name":"Chukhari",
    "wof:placetype":"locality"
},
  "geometry": {"coordinates":[47.5207,64.84139999999999],"type":"Point"}
}