{
  "type": "Feature",
  "properties": {
    "gn:admin1_code":"33",
    "gn:asciiname":"Syrda",
    "gn:country_code":"RU",
    "gn:dem":141,
    "gn:feature_class":"P",
    "gn:feature_code":"PPL",
    "gn:name":"Syrda",
    "gn:population":0,
    "gn:timezone":"Europe/Kirov",
    "iso:country":"RU",
    "name:rus_x_preferred":[
        "\u0421\u044b\u0440\u0434\u0430"
    ],
    "wof:name":"Syrda",
    "wof:placetype":"locality"
},
  "geometry": {"coordinates":[49.45399000000001,58.12413000000001],"type":"Point"}
}