{
  "type": "Feature",
  "properties": {
    "gn:admin1_code":"9",
    "gn:asciiname":"Zavalishcheno",
    "gn:country_code":"RU",
    "gn:dem":121,
    "gn:feature_class":"P",
    "gn:feature_code":"PPL",
    "gn:name":"Zavalishcheno",
    "gn:population":0,
    "gn:timezone":"Europe/Moscow",
    "iso:country":"RU",
    "name:rus_x_preferred":[
        "\u0417\u0430\u0432\u0430\u043b\u0438\u0449\u0435\u043d\u043e"
    ],
    "wof:name":"Zavalishcheno",
    "wof:placetype":"locality"
},
  "geometry": {"coordinates":[37.8242,51.04171],"type":"Point"}
}