{
  "type": "Feature",
  "properties": {
    "gn:admin1_code":"91",
    "gn:asciiname":"Verkhnyaya Mishkina",
    "gn:country_code":"RU",
    "gn:dem":407,
    "gn:feature_class":"P",
    "gn:feature_code":"PPL",
    "gn:name":"Verkhnyaya Mishkina",
    "gn:population":0,
    "gn:timezone":"Asia/Krasnoyarsk",
    "iso:country":"RU",
    "wof:name":"Verkhnyaya Mishkina",
    "wof:placetype":"locality"
},
  "geometry": {"coordinates":[93.24445,54.02212],"type":"Point"}
}