{
  "type": "Feature",
  "properties": {
    "gn:admin1_code":"9.0",
    "gn:asciiname":"Khoroshiy",
    "gn:country_code":"RU",
    "gn:dem":235,
    "gn:feature_class":"P",
    "gn:feature_code":"PPL",
    "gn:name":"Khoroshiy",
    "gn:population":0,
    "gn:timezone":"Europe/Moscow",
    "iso:country":"RU",
    "name:rus_x_preferred":[
        "\u0425\u043e\u0440\u043e\u0448\u0438\u0439"
    ],
    "wof:name":"Khoroshiy",
    "wof:placetype":"locality"
},
  "geometry": {"coordinates":[36.94422,50.99905],"type":"Point"}
}