{
  "type": "Feature",
  "properties": {
    "gn:admin1_code":"37.0",
    "gn:asciiname":"Dubyany",
    "gn:country_code":"RU",
    "gn:dem":189,
    "gn:feature_class":"P",
    "gn:feature_code":"PPL",
    "gn:name":"Dubyany",
    "gn:population":0,
    "gn:timezone":"Europe/Moscow",
    "iso:country":"RU",
    "name:rus_x_preferred":[
        "\u0414\u0443\u0431\u044f\u043d\u044b"
    ],
    "name:und_x_variant":[
        "\u0414\u0443\u0431\u044f\u043d\u044b"
    ],
    "wof:name":"Dubyany",
    "wof:placetype":"locality"
},
  "geometry": {"coordinates":[42.34441,58.07584],"type":"Point"}
}