{
  "type": "Feature",
  "properties": {
    "gn:admin1_code":"76.0",
    "gn:asciiname":"Baranovka",
    "gn:country_code":"RU",
    "gn:dem":209,
    "gn:feature_class":"P",
    "gn:feature_code":"PPL",
    "gn:name":"Baranovka",
    "gn:population":0,
    "gn:timezone":"Europe/Moscow",
    "iso:country":"RU",
    "name:nor_x_preferred":[
        "Baranovka"
    ],
    "name:rus_x_preferred":[
        "\u0411\u0430\u0440\u0430\u043d\u043e\u0432\u043a\u0430"
    ],
    "wof:name":"Baranovka",
    "wof:placetype":"locality"
},
  "geometry": {"coordinates":[38.66387,53.36039],"type":"Point"}
}