{
  "type": "Feature",
  "properties": {
    "gn:admin1_code":"71",
    "gn:asciiname":"Verkhnyaya Poldnevaya",
    "gn:country_code":"RU",
    "gn:dem":153,
    "gn:feature_class":"P",
    "gn:feature_code":"PPL",
    "gn:name":"Verkhnyaya Poldnevaya",
    "gn:population":0,
    "gn:timezone":"Asia/Yekaterinburg",
    "iso:country":"RU",
    "name:eng_x_preferred":[
        "Verkhnyaya Poldnevaya"
    ],
    "name:nor_x_preferred":[
        "Verkh.Poldnevaja"
    ],
    "name:rus_x_preferred":[
        "\u0412\u0435\u0440\u0445.\u041f\u043e\u043b\u0434\u043d\u0435\u0432\u0430\u044f"
    ],
    "name:rus_x_variant":[
        "\u0412\u0435\u0440\u0445\u043d\u044f\u044f \u041f\u043e\u043b\u0434\u043d\u0435\u0432\u0430\u044f"
    ],
    "name:und_x_variant":[
        "Verkhne-Poldnevaya"
    ],
    "wof:name":"Verkhnyaya Poldnevaya",
    "wof:placetype":"locality"
},
  "geometry": {"coordinates":[62.1846,56.6461],"type":"Point"}
}