{
  "type": "Feature",
  "properties": {
    "gn:admin1_code":"85",
    "gn:asciiname":"Ostretsovo",
    "gn:country_code":"RU",
    "gn:dem":144,
    "gn:feature_class":"P",
    "gn:feature_code":"PPL",
    "gn:name":"Ostretsovo",
    "gn:population":0,
    "gn:timezone":"Europe/Moscow",
    "iso:country":"RU",
    "name:rus_x_preferred":[
        "\u041e\u0441\u0442\u0440\u0435\u0446\u043e\u0432\u043e"
    ],
    "name:und_x_variant":[
        "\u041e\u0441\u0442\u0440\u0435\u0446\u043e\u0432\u043e"
    ],
    "wof:name":"Ostretsovo",
    "wof:placetype":"locality"
},
  "geometry": {"coordinates":[40.70426,59.28451999999999],"type":"Point"}
}