{
  "type": "Feature",
  "properties": {
    "gn:admin1_code":"6.0",
    "gn:asciiname":"Panitsa",
    "gn:country_code":"RU",
    "gn:dem":18,
    "gn:feature_class":"P",
    "gn:feature_code":"PPL",
    "gn:name":"Panitsa",
    "gn:population":0,
    "gn:timezone":"Europe/Moscow",
    "iso:country":"RU",
    "name:rus_x_preferred":[
        "\u041f\u0430\u043d\u0438\u0446\u0430"
    ],
    "wof:name":"Panitsa",
    "wof:placetype":"locality"
},
  "geometry": {"coordinates":[42.6419,62.96100000000001],"type":"Point"}
}