{
  "type": "Feature",
  "properties": {
    "gn:admin1_code":"88",
    "gn:asciiname":"Myagkaya",
    "gn:country_code":"RU",
    "gn:dem":103,
    "gn:feature_class":"P",
    "gn:feature_code":"PPL",
    "gn:name":"Myagkaya",
    "gn:population":0,
    "gn:timezone":"Europe/Moscow",
    "iso:country":"RU",
    "name:rus_x_preferred":[
        "\u041c\u044f\u0433\u043a\u0430\u044f"
    ],
    "wof:name":"Myagkaya",
    "wof:placetype":"locality"
},
  "geometry": {"coordinates":[38.77455,58.06709],"type":"Point"}
}