{
  "type": "Feature",
  "properties": {
    "gn:admin1_code":"53",
    "gn:asciiname":"Novotroitsk",
    "gn:country_code":"RU",
    "gn:dem":105,
    "gn:feature_class":"P",
    "gn:feature_code":"PPL",
    "gn:name":"Novotroitsk",
    "gn:population":0,
    "gn:timezone":"Asia/Novosibirsk",
    "iso:country":"RU",
    "name:eng_x_preferred":[
        "Novotroitskiy"
    ],
    "name:nor_x_preferred":[
        "Novotroitsk"
    ],
    "name:rus_x_preferred":[
        "\u041d\u043e\u0432\u043e\u0442\u0440\u043e\u0438\u0446\u043a"
    ],
    "name:und_x_variant":[
        "Novotroitskiy",
        "Novotroitsk"
    ],
    "wof:name":"Novotroitsk",
    "wof:placetype":"locality"
},
  "geometry": {"coordinates":[75.99455999999998,55.33769],"type":"Point"}
}