{
  "type": "Feature",
  "properties": {
    "gn:country":"RU",
    "gn:fcode":"PPL",
    "gn:population":4711,
    "iso:country":"RU",
    "name:bel_x_preferred":[
        "\u0411\u044f\u0436\u0430\u043d\u0456\u0446\u044b"
    ],
    "name:cat_x_preferred":[
        "Bejanitsi"
    ],
    "name:ceb_x_preferred":[
        "Bezhanitsy"
    ],
    "name:che_x_preferred":[
        "\u0411\u0435\u0436\u0430\u043d\u0438\u0446\u044b"
    ],
    "name:deu_x_preferred":[
        "Beschanizy"
    ],
    "name:eng_x_preferred":[
        "Bezhanitsy"
    ],
    "name:est_x_preferred":[
        "Be\u017eanits\u00f5"
    ],
    "name:fin_x_preferred":[
        "Be\u017eanitsy"
    ],
    "name:ita_x_preferred":[
        "Be\u017eanicy"
    ],
    "name:nld_x_preferred":[
        "Bezjanitsy"
    ],
    "name:pol_x_preferred":[
        "Bie\u017canice"
    ],
    "name:rus_x_preferred":[
        "\u0411\u0435\u0436\u0430\u043d\u0438\u0446\u044b"
    ],
    "name:srp_x_preferred":[
        "\u0411\u0435\u0436\u0430\u043d\u0438\u0446\u0438"
    ],
    "qs:name":"Bezhanitsy",
    "qs:photos_9r":0,
    "qs:photos_sr":0,
    "qs:pop_sr":"4",
    "wd:wordcount":1139,
    "wof:name":"Bezhanitsy",
    "wof:placetype":"locality",
    "wof:population":4711
},
  "geometry": {"coordinates":[29.89065,56.9767],"type":"Point"}
}