{
  "type": "Feature",
  "properties": {
    "gn:admin1_code":"91.0",
    "gn:asciiname":"Staryye Yamki",
    "gn:country_code":"RU",
    "gn:dem":452,
    "gn:feature_class":"P",
    "gn:feature_code":"PPL",
    "gn:name":"Staryye Yamki",
    "gn:population":0,
    "gn:timezone":"Asia/Krasnoyarsk",
    "iso:country":"RU",
    "name:rus_x_preferred":[
        "\u0421\u0442\u0430\u0440\u044b\u0435 \u042f\u043c\u043a\u0438"
    ],
    "wof:name":"Staryye Yamki",
    "wof:placetype":"locality"
},
  "geometry": {"coordinates":[90.44361000000001,55.19944],"type":"Point"}
}