{
  "type": "Feature",
  "properties": {
    "gn:country":"RU",
    "gn:fcode":"PPL",
    "gn:pop":0,
    "iso:country":"RU",
    "name:che_x_preferred":[
        "\u0422\u0430\u043b\u0430\u0433\u0438"
    ],
    "name:deu_x_preferred":[
        "Talagi"
    ],
    "name:eng_x_preferred":[
        "Talagi"
    ],
    "name:ita_x_preferred":[
        "Talagi"
    ],
    "name:nor_x_preferred":[
        "Talagi"
    ],
    "name:rus_x_preferred":[
        "\u0422\u0430\u043b\u0430\u0433\u0438"
    ],
    "qs:name":"Talagi",
    "qs:name_adm0":"Russia",
    "qs:name_adm1":"Arkhangelsk Oblast",
    "qs:photos_9k":1,
    "qs:photos_9r":1,
    "qs:photos_all":6,
    "qs:photos_sr":0,
    "qs:placetype":"Town",
    "qs:pop_sr":"0",
    "wof:name":"Talagi",
    "wof:placetype":"locality",
    "wof:population":0
},
  "geometry": {"coordinates":[40.6283,64.61499999999999],"type":"Point"}
}