{
  "type": "Feature",
  "properties": {
    "gn:admin1_code":"85",
    "gn:asciiname":"Davydovka",
    "gn:country_code":"RU",
    "gn:dem":141,
    "gn:feature_class":"P",
    "gn:feature_code":"PPL",
    "gn:name":"Davydovka",
    "gn:population":0,
    "gn:timezone":"Europe/Moscow",
    "iso:country":"RU",
    "name:che_x_preferred":[
        "\u0414\u0430\u0432\u044b\u0434\u043e\u0432\u043a\u0430"
    ],
    "name:rus_x_preferred":[
        "\u0414\u0430\u0432\u044b\u0434\u043e\u0432\u043a\u0430"
    ],
    "wof:name":"Davydovka",
    "wof:placetype":"locality"
},
  "geometry": {"coordinates":[36.304,59.6159],"type":"Point"}
}