{
  "type": "Feature",
  "properties": {
    "gn:admin1_code":"51",
    "gn:asciiname":"Sel'skaya Maza",
    "gn:country_code":"RU",
    "gn:dem":69,
    "gn:feature_class":"P",
    "gn:feature_code":"PPL",
    "gn:name":"Sel\u2019skaya Maza",
    "gn:population":0,
    "gn:timezone":"Europe/Moscow",
    "iso:country":"RU",
    "name:eng_x_preferred":[
        "Sel'skaya Maza"
    ],
    "name:nor_x_preferred":[
        "Selskaja Maza"
    ],
    "name:rus_x_preferred":[
        "\u0421\u0435\u043b\u044c\u0441\u043a\u0430\u044f \u041c\u0430\u0437\u0430"
    ],
    "name:und_x_variant":[
        "Sel\u2019skaya Maza"
    ],
    "wof:name":"Sel'skaya Maza",
    "wof:placetype":"locality"
},
  "geometry": {"coordinates":[45.20657,56.15164],"type":"Point"}
}