{
  "type": "Feature",
  "properties": {
    "gn:admin1_code":"54",
    "gn:asciiname":"Zaborskoye",
    "gn:country_code":"RU",
    "gn:dem":92,
    "gn:feature_class":"P",
    "gn:feature_code":"PPL",
    "gn:name":"Zaborskoye",
    "gn:population":0,
    "gn:timezone":"Asia/Omsk",
    "iso:country":"RU",
    "wof:name":"Zaborskoye",
    "wof:placetype":"locality"
},
  "geometry": {"coordinates":[73.51666999999998,57.61666999999999],"type":"Point"}
}