{
  "type": "Feature",
  "properties": {
    "gn:admin1_code":"60",
    "gn:asciiname":"Vadrino",
    "gn:country_code":"RU",
    "gn:dem":52,
    "gn:feature_class":"P",
    "gn:feature_code":"PPL",
    "gn:name":"Vadrino",
    "gn:population":0,
    "gn:timezone":"Europe/Moscow",
    "iso:country":"RU",
    "name:rus_x_preferred":[
        "\u0412\u0430\u0434\u0440\u0438\u043d\u043e"
    ],
    "wof:name":"Vadrino",
    "wof:placetype":"locality"
},
  "geometry": {"coordinates":[28.31326,57.60945],"type":"Point"}
}