{
  "type": "Feature",
  "properties": {
    "gn:admin1_code":"42",
    "gn:asciiname":"Volodarskoye",
    "gn:country_code":"RU",
    "gn:dem":71,
    "gn:feature_class":"P",
    "gn:feature_code":"PPL",
    "gn:name":"Volodarskoye",
    "gn:population":0,
    "gn:timezone":"Europe/Moscow",
    "iso:country":"RU",
    "name:eng_x_preferred":[
        "Volodarskoye"
    ],
    "name:nor_x_preferred":[
        "Volodarskoje"
    ],
    "name:rus_x_preferred":[
        "\u0412\u043e\u043b\u043e\u0434\u0430\u0440\u0441\u043a\u043e\u0435"
    ],
    "wof:name":"Volodarskoye",
    "wof:placetype":"locality"
},
  "geometry": {"coordinates":[29.88935,58.5214],"type":"Point"}
}