{
  "type": "Feature",
  "properties": {
    "gn:admin1_code":"60",
    "gn:asciiname":"Lug",
    "gn:country_code":"RU",
    "gn:dem":244,
    "gn:feature_class":"P",
    "gn:feature_code":"PPL",
    "gn:name":"Lug",
    "gn:population":0,
    "gn:timezone":"Europe/Moscow",
    "iso:country":"RU",
    "name:eng_x_preferred":[
        "Lug"
    ],
    "name:nor_x_preferred":[
        "Lug"
    ],
    "name:rus_x_preferred":[
        "\u041b\u0443\u0433"
    ],
    "name:und_x_variant":[
        "\u041b\u0443\u0433",
        "Lug"
    ],
    "wof:name":"Lug",
    "wof:placetype":"locality"
},
  "geometry": {"coordinates":[29.84667,56.83795],"type":"Point"}
}