{
  "type": "Feature",
  "properties": {
    "gn:admin1_code":"41",
    "gn:asciiname":"Zabolotovka",
    "gn:country_code":"RU",
    "gn:dem":137,
    "gn:feature_class":"P",
    "gn:feature_code":"PPL",
    "gn:name":"Zabolotovka",
    "gn:population":0,
    "gn:timezone":"Europe/Moscow",
    "iso:country":"RU",
    "name:rus_x_preferred":[
        "\u0417\u0430\u0431\u043e\u043b\u043e\u0442\u043e\u0432\u043a\u0430"
    ],
    "wof:name":"Zabolotovka",
    "wof:placetype":"locality"
},
  "geometry": {"coordinates":[34.3861,51.3371],"type":"Point"}
}