{
  "type": "Feature",
  "properties": {
    "gn:admin1_code":"13",
    "gn:asciiname":"Istrut'",
    "gn:country_code":"RU",
    "gn:dem":290,
    "gn:feature_class":"P",
    "gn:feature_code":"PPL",
    "gn:name":"Istrut\u2019",
    "gn:population":0,
    "gn:timezone":"Asia/Yekaterinburg",
    "iso:country":"RU",
    "name:rus_x_preferred":[
        "\u0418\u0441\u0442\u0440\u0443\u0442\u044c"
    ],
    "name:und_x_variant":[
        "Istrut\u2019"
    ],
    "wof:name":"Istrut'",
    "wof:placetype":"locality"
},
  "geometry": {"coordinates":[58.97,55.24194],"type":"Point"}
}