{
  "type": "Feature",
  "properties": {
    "gn:admin1_code":"72",
    "gn:asciiname":"Krym",
    "gn:country_code":"RU",
    "gn:dem":156,
    "gn:feature_class":"P",
    "gn:feature_code":"PPL",
    "gn:name":"Krym",
    "gn:population":0,
    "gn:timezone":"Europe/Moscow",
    "iso:country":"RU",
    "name:ceb_x_preferred":[
        "Krym"
    ],
    "name:ces_x_preferred":[
        "Krym"
    ],
    "name:pol_x_preferred":[
        "Krym"
    ],
    "name:rus_x_preferred":[
        "\u041a\u0440\u044b\u043c"
    ],
    "name:slk_x_preferred":[
        "Krym"
    ],
    "name:szl_x_preferred":[
        "Krym"
    ],
    "name:vie_x_preferred":[
        "Krym"
    ],
    "wof:name":"Krym",
    "wof:placetype":"locality"
},
  "geometry": {"coordinates":[40.94194,51.98139000000001],"type":"Point"}
}