{
  "type": "Feature",
  "properties": {
    "gn:admin1_code":"22",
    "gn:asciiname":"Dzhulat",
    "gn:country_code":"RU",
    "gn:dem":247,
    "gn:feature_class":"P",
    "gn:feature_code":"PPL",
    "gn:name":"Dzhulat",
    "gn:population":0,
    "gn:timezone":"Europe/Moscow",
    "iso:country":"RU",
    "name:rus_x_preferred":[
        "\u0414\u0436\u0443\u043b\u0430\u0442"
    ],
    "wof:name":"Dzhulat",
    "wof:placetype":"locality"
},
  "geometry": {"coordinates":[44.09093,43.61541],"type":"Point"}
}