{
  "type": "Feature",
  "properties": {
    "gn:admin1_code":"6.0",
    "gn:asciiname":"Abramkovo",
    "gn:country_code":"RU",
    "gn:dem":26,
    "gn:feature_class":"P",
    "gn:feature_code":"PPL",
    "gn:name":"Abramkovo",
    "gn:population":0,
    "gn:timezone":"Europe/Moscow",
    "iso:country":"RU",
    "name:che_x_preferred":[
        "\u0410\u0431\u0440\u0430\u043c\u043a\u043e\u0432\u043e"
    ],
    "name:eng_x_preferred":[
        "Abramkovo"
    ],
    "name:hye_x_preferred":[
        "\u0531\u0562\u0580\u0561\u0574\u056f\u0578\u057e\u0578"
    ],
    "name:nor_x_preferred":[
        "Abramkovo"
    ],
    "name:rus_x_preferred":[
        "\u0410\u0431\u0440\u0430\u043c\u043a\u043e\u0432\u043e"
    ],
    "name:ukr_x_preferred":[
        "\u0410\u0431\u0440\u0430\u043c\u043a\u043e\u0432\u043e"
    ],
    "name:und_x_variant":[
        "Abramkova"
    ],
    "wof:name":"Abramkovo",
    "wof:placetype":"locality"
},
  "geometry": {"coordinates":[45.1019,62.0908],"type":"Point"}
}