{
  "type": "Feature",
  "properties": {
    "gn:admin1_code":"41",
    "gn:asciiname":"Kosoy Khutor",
    "gn:country_code":"RU",
    "gn:dem":179,
    "gn:feature_class":"P",
    "gn:feature_code":"PPL",
    "gn:name":"Kosoy Khutor",
    "gn:population":0,
    "gn:timezone":"Europe/Moscow",
    "iso:country":"RU",
    "name:rus_x_preferred":[
        "\u041a\u043e\u0441\u043e\u0439 \u0425\u0443\u0442\u043e\u0440"
    ],
    "wof:name":"Kosoy Khutor",
    "wof:placetype":"locality"
},
  "geometry": {"coordinates":[35.6559,51.7401],"type":"Point"}
}