{
  "type": "Feature",
  "properties": {
    "gn:admin1_code":"20",
    "gn:asciiname":"Vtoraya Uda",
    "gn:country_code":"RU",
    "gn:dem":421,
    "gn:feature_class":"P",
    "gn:feature_code":"PPL",
    "gn:name":"Vtoraya Uda",
    "gn:population":0,
    "gn:timezone":"Asia/Irkutsk",
    "iso:country":"RU",
    "wof:name":"Vtoraya Uda",
    "wof:placetype":"locality"
},
  "geometry": {"coordinates":[99.13333,54.83333],"type":"Point"}
}