{
  "type": "Feature",
  "properties": {
    "gn:admin1_code":"10",
    "gn:asciiname":"Bogatyrevo",
    "gn:country_code":"RU",
    "gn:dem":186,
    "gn:feature_class":"P",
    "gn:feature_code":"PPL",
    "gn:name":"Bogatyrevo",
    "gn:population":0,
    "gn:timezone":"Europe/Moscow",
    "iso:country":"RU",
    "name:rus_x_preferred":[
        "\u0411\u043e\u0433\u0430\u0442\u044b\u0440\u0435\u0432\u043e"
    ],
    "wof:name":"Bogatyrevo",
    "wof:placetype":"locality"
},
  "geometry": {"coordinates":[34.74152,52.97717],"type":"Point"}
}