{
  "type": "Feature",
  "properties": {
    "gn:admin1_code":"73",
    "gn:asciiname":"Sergiyevskoye",
    "gn:cc2":"RU",
    "gn:country_code":"RU",
    "gn:dem":70,
    "gn:feature_class":"P",
    "gn:feature_code":"PPL",
    "gn:name":"Sergiyevskoye",
    "gn:population":0,
    "gn:timezone":"Europe/Moscow",
    "iso:country":"RU",
    "name:und_x_variant":[
        "Sergeyevskoye"
    ],
    "wof:name":"Sergiyevskoye",
    "wof:placetype":"locality"
},
  "geometry": {"coordinates":[49.93167,55.21806],"type":"Point"}
}