{
  "type": "Feature",
  "properties": {
    "gn:admin1_code":"45",
    "gn:asciiname":"Irnur",
    "gn:country_code":"RU",
    "gn:dem":144,
    "gn:feature_class":"P",
    "gn:feature_code":"PPL",
    "gn:name":"Irnur",
    "gn:population":0,
    "gn:timezone":"Europe/Moscow",
    "iso:country":"RU",
    "name:eng_x_preferred":[
        "Irnur"
    ],
    "name:nor_x_preferred":[
        "Irnur"
    ],
    "name:rus_x_preferred":[
        "\u0418\u0440\u043d\u0443\u0440"
    ],
    "wof:name":"Irnur",
    "wof:placetype":"locality"
},
  "geometry": {"coordinates":[49.29806,56.6925],"type":"Point"}
}