{
  "type": "Feature",
  "properties": {
    "gn:admin1_code":"69",
    "gn:asciiname":"Bokari",
    "gn:country_code":"RU",
    "gn:dem":232,
    "gn:feature_class":"P",
    "gn:feature_code":"PPL",
    "gn:name":"Bokari",
    "gn:population":0,
    "gn:timezone":"Europe/Moscow",
    "iso:country":"RU",
    "name:rus_x_preferred":[
        "\u0411\u043e\u043a\u0430\u0440\u0438"
    ],
    "name:und_x_variant":[
        "\u0411\u043e\u043a\u0430\u0440\u0438"
    ],
    "wof:name":"Bokari",
    "wof:placetype":"locality"
},
  "geometry": {"coordinates":[34.90525,55.2274],"type":"Point"}
}