{
  "type": "Feature",
  "properties": {
    "gn:admin1_code":"37",
    "gn:asciiname":"Kuznetsovo",
    "gn:country_code":"RU",
    "gn:dem":200,
    "gn:feature_class":"P",
    "gn:feature_code":"PPL",
    "gn:name":"Kuznetsovo",
    "gn:population":0,
    "gn:timezone":"Europe/Moscow",
    "iso:country":"RU",
    "name:rus_x_preferred":[
        "\u041a\u0443\u0437\u043d\u0435\u0446\u043e\u0432\u043e"
    ],
    "name:und_x_variant":[
        "Krovopuskovo",
        "Kuznetsovo",
        "\u041a\u0443\u0437\u043d\u0435\u0446\u043e\u0432\u043e",
        "Kravopuskovo"
    ],
    "wof:name":"Kuznetsovo",
    "wof:placetype":"locality"
},
  "geometry": {"coordinates":[42.44508,58.82613000000001],"type":"Point"}
}