{
  "type": "Feature",
  "properties": {
    "gn:admin1_code":"31",
    "gn:asciiname":"Tayezhnaya",
    "gn:country_code":"RU",
    "gn:dem":578,
    "gn:feature_class":"P",
    "gn:feature_code":"PPL",
    "gn:name":"Tayezhnaya",
    "gn:population":0,
    "gn:timezone":"Asia/Krasnoyarsk",
    "iso:country":"RU",
    "name:eng_x_preferred":[
        "Tayezhnaya"
    ],
    "name:nor_x_preferred":[
        "Tajezjnaja"
    ],
    "name:rus_x_preferred":[
        "\u0422\u0430\u0435\u0436\u043d\u0430\u044f"
    ],
    "name:und_x_variant":[
        "Voroshilovo"
    ],
    "wof:name":"Tayezhnaya",
    "wof:placetype":"locality"
},
  "geometry": {"coordinates":[90.95508,54.14775],"type":"Point"}
}