{
  "type": "Feature",
  "properties": {
    "gn:admin1_code":"75",
    "gn:asciiname":"Porosino",
    "gn:country_code":"RU",
    "gn:dem":88,
    "gn:feature_class":"P",
    "gn:feature_code":"PPL",
    "gn:name":"Porosino",
    "gn:population":0,
    "gn:timezone":"Asia/Tomsk",
    "iso:country":"RU",
    "name:eng_x_preferred":[
        "Porosinskiy"
    ],
    "name:nor_x_preferred":[
        "Porosino"
    ],
    "name:rus_x_preferred":[
        "\u041f\u043e\u0440\u043e\u0441\u0438\u043d\u043e"
    ],
    "wof:name":"Porosino",
    "wof:placetype":"locality"
},
  "geometry": {"coordinates":[84.76023000000001,56.54928],"type":"Point"}
}