{
  "type": "Feature",
  "properties": {
    "gn:admin1_code":"69",
    "gn:asciiname":"Chuvidovo",
    "gn:country_code":"RU",
    "gn:dem":227,
    "gn:feature_class":"P",
    "gn:feature_code":"PPL",
    "gn:name":"Chuvidovo",
    "gn:population":0,
    "gn:timezone":"Europe/Moscow",
    "iso:country":"RU",
    "name:rus_x_preferred":[
        "\u0427\u0443\u0432\u0438\u0434\u043e\u0432\u043e"
    ],
    "wof:name":"Chuvidovo",
    "wof:placetype":"locality"
},
  "geometry": {"coordinates":[35.09667,55.65583],"type":"Point"}
}