{
  "type": "Feature",
  "properties": {
    "gn:admin1_code":"41",
    "gn:asciiname":"Staraya Pershina",
    "gn:country_code":"RU",
    "gn:dem":157,
    "gn:feature_class":"P",
    "gn:feature_code":"PPL",
    "gn:name":"Staraya Pershina",
    "gn:population":0,
    "gn:timezone":"Europe/Moscow",
    "iso:country":"RU",
    "name:rus_x_preferred":[
        "\u0421\u0442\u0430\u0440\u0430\u044f \u041f\u0435\u0440\u0448\u0438\u043d\u0430"
    ],
    "name:und_x_variant":[
        "Staroye Pershino"
    ],
    "wof:name":"Staraya Pershina",
    "wof:placetype":"locality"
},
  "geometry": {"coordinates":[35.137,52.0996],"type":"Point"}
}