{
  "type": "Feature",
  "properties": {
    "gn:admin1_code":"52",
    "gn:asciiname":"Vyderka",
    "gn:country_code":"RU",
    "gn:dem":68,
    "gn:feature_class":"P",
    "gn:feature_code":"PPL",
    "gn:name":"Vyderka",
    "gn:population":0,
    "gn:timezone":"Europe/Moscow",
    "iso:country":"RU",
    "name:rus_x_preferred":[
        "\u0412\u044b\u0434\u0435\u0440\u043a\u0430"
    ],
    "wof:name":"Vyderka",
    "wof:placetype":"locality"
},
  "geometry": {"coordinates":[32.29072,57.91992],"type":"Point"}
}