{
  "type": "Feature",
  "properties": {
    "gn:admin1_code":"43.0",
    "gn:asciiname":"Gagarino",
    "gn:country_code":"RU",
    "gn:dem":115,
    "gn:feature_class":"P",
    "gn:feature_code":"PPL",
    "gn:name":"Gagarino",
    "gn:population":0,
    "gn:timezone":"Europe/Moscow",
    "iso:country":"RU",
    "name:msa_x_preferred":[
        "Gagarino"
    ],
    "name:rus_x_preferred":[
        "\u0413\u0430\u0433\u0430\u0440\u0438\u043d\u043e"
    ],
    "wof:name":"Gagarino",
    "wof:placetype":"locality"
},
  "geometry": {"coordinates":[38.94993,52.74553],"type":"Point"}
}