{
  "type": "Feature",
  "properties": {
    "gn:admin1_code":"57.0",
    "gn:asciiname":"Desyataya Artel'",
    "gn:country_code":"RU",
    "gn:dem":132,
    "gn:feature_class":"P",
    "gn:feature_code":"PPL",
    "gn:name":"Desyataya Artel\u2019",
    "gn:population":0,
    "gn:timezone":"Europe/Moscow",
    "iso:country":"RU",
    "name:rus_x_preferred":[
        "\u0414\u0435\u0441\u044f\u0442\u0430\u044f \u0410\u0440\u0442\u0435\u043b\u044c"
    ],
    "name:und_x_variant":[
        "Desyataya Artel\u2019"
    ],
    "wof:name":"Desyataya Artel'",
    "wof:placetype":"locality"
},
  "geometry": {"coordinates":[45.05204000000001,53.26981],"type":"Point"}
}