{
  "type": "Feature",
  "properties": {
    "gn:admin1_code":"56",
    "gn:asciiname":"Timiryazevo",
    "gn:country_code":"RU",
    "gn:dem":227,
    "gn:feature_class":"P",
    "gn:feature_code":"PPL",
    "gn:name":"Timiryazevo",
    "gn:population":0,
    "gn:timezone":"Europe/Moscow",
    "iso:country":"RU",
    "name:rus_x_preferred":[
        "\u0422\u0438\u043c\u0438\u0440\u044f\u0437\u0435\u0432\u043e"
    ],
    "wof:name":"Timiryazevo",
    "wof:placetype":"locality"
},
  "geometry": {"coordinates":[36.70364,52.62148000000001],"type":"Point"}
}