{
  "type": "Feature",
  "properties": {
    "gn:admin1_code":"77",
    "gn:asciiname":"Mikashikha",
    "gn:cc2":"RU",
    "gn:country_code":"RU",
    "gn:dem":182,
    "gn:feature_class":"P",
    "gn:feature_code":"PPL",
    "gn:name":"Mikashikha",
    "gn:population":0,
    "gn:timezone":"Europe/Moscow",
    "iso:country":"RU",
    "name:rus_x_preferred":[
        "\u041c\u0438\u043a\u0430\u0448\u0438\u0445\u0430"
    ],
    "name:und_x_variant":[
        "Mikatikha",
        "Mikashikha"
    ],
    "wof:name":"Mikashikha",
    "wof:placetype":"locality"
},
  "geometry": {"coordinates":[35.39611,57.91944],"type":"Point"}
}