{
  "type": "Feature",
  "properties": {
    "gn:admin1_code":"56",
    "gn:asciiname":"Gurovskiy",
    "gn:country_code":"RU",
    "gn:dem":196,
    "gn:feature_class":"P",
    "gn:feature_code":"PPL",
    "gn:name":"Gurovskiy",
    "gn:population":0,
    "gn:timezone":"Europe/Moscow",
    "iso:country":"RU",
    "name:rus_x_preferred":[
        "\u0413\u0443\u0440\u043e\u0432\u0441\u043a\u0438\u0439"
    ],
    "name:und_x_variant":[
        "\u0413\u0443\u0440\u043e\u0432\u0441\u043a\u0438\u0439"
    ],
    "wof:name":"Gurovskiy",
    "wof:placetype":"locality"
},
  "geometry": {"coordinates":[35.0188,52.5345],"type":"Point"}
}