{
  "type": "Feature",
  "properties": {
    "gn:admin1_code":"4",
    "gn:asciiname":"Kateshino",
    "gn:cc2":"RU",
    "gn:country_code":"RU",
    "gn:dem":136,
    "gn:feature_class":"P",
    "gn:feature_code":"PPL",
    "gn:name":"Kateshino",
    "gn:population":0,
    "gn:timezone":"Asia/Barnaul",
    "iso:country":"RU",
    "name:rus_x_preferred":[
        "\u041a\u0430\u0442\u0435\u0448\u0438\u043d\u043e"
    ],
    "name:und_x_variant":[
        "Koteshin",
        "Kategaina",
        "Kateshino",
        "\u041a\u0430\u0442\u0435\u0448\u0438\u043d\u043e"
    ],
    "wof:name":"Kateshino",
    "wof:placetype":"locality"
},
  "geometry": {"coordinates":[79.95,53.73333],"type":"Point"}
}