{
  "type": "Feature",
  "properties": {
    "gn:admin1_code":"61",
    "gn:asciiname":"Morozov",
    "gn:country_code":"RU",
    "gn:dem":80,
    "gn:feature_class":"P",
    "gn:feature_code":"PPL",
    "gn:name":"Morozov",
    "gn:population":0,
    "gn:timezone":"Europe/Moscow",
    "iso:country":"RU",
    "name:rus_x_preferred":[
        "\u041c\u043e\u0440\u043e\u0437\u043e\u0432"
    ],
    "name:und_x_variant":[
        "\u041c\u043e\u0440\u043e\u0437\u043e\u0432"
    ],
    "wof:name":"Morozov",
    "wof:placetype":"locality"
},
  "geometry": {"coordinates":[41.89309,48.33015],"type":"Point"}
}