{
  "type": "Feature",
  "properties": {
    "gn:admin1_code":"47",
    "gn:asciiname":"Litvinovo",
    "gn:country_code":"RU",
    "gn:dem":236,
    "gn:feature_class":"P",
    "gn:feature_code":"PPL",
    "gn:name":"Litvinovo",
    "gn:population":0,
    "gn:timezone":"Europe/Moscow",
    "iso:country":"RU",
    "name:rus_x_preferred":[
        "\u041b\u0438\u0442\u0432\u0438\u043d\u043e\u0432\u043e"
    ],
    "wof:name":"Litvinovo",
    "wof:placetype":"locality"
},
  "geometry": {"coordinates":[36.2007,56.059],"type":"Point"}
}