{
  "type": "Feature",
  "properties": {
    "gn:admin1_code":"7",
    "gn:asciiname":"Zaton",
    "gn:cc2":"RU",
    "gn:country_code":"RU",
    "gn:dem":-25,
    "gn:feature_class":"P",
    "gn:feature_code":"PPL",
    "gn:name":"Zaton",
    "gn:population":0,
    "gn:timezone":"Europe/Astrakhan",
    "iso:country":"RU",
    "name:eng_x_preferred":[
        "Zaton"
    ],
    "name:nor_x_preferred":[
        "Zaton"
    ],
    "name:rus_x_preferred":[
        "\u0417\u0430\u0442\u043e\u043d"
    ],
    "name:und_x_variant":[
        "Aul Zatonskiy",
        "Zaton"
    ],
    "wof:name":"Zaton",
    "wof:placetype":"locality"
},
  "geometry": {"coordinates":[48.15583,45.9025],"type":"Point"}
}