{
  "type": "Feature",
  "properties": {
    "gn:admin1_code":"7",
    "gn:asciiname":"Zaton",
    "gn:cc2":"RU",
    "gn:country_code":"RU",
    "gn:dem":-25,
    "gn:feature_class":"P",
    "gn:feature_code":"PPL",
    "gn:name":"Zaton",
    "gn:population":0,
    "gn:timezone":"Europe/Astrakhan",
    "iso:country":"RU",
    "name:bel_x_preferred":[
        "\u0417\u0430\u0442\u043e\u043d"
    ],
    "name:bos_x_preferred":[
        "Zaton"
    ],
    "name:ceb_x_preferred":[
        "Zaton"
    ],
    "name:deu_x_preferred":[
        "Zaton"
    ],
    "name:eng_x_preferred":[
        "Zaton"
    ],
    "name:fra_x_preferred":[
        "Zaton"
    ],
    "name:hrv_x_preferred":[
        "Zaton"
    ],
    "name:hun_x_preferred":[
        "Zaton"
    ],
    "name:hye_x_preferred":[
        "\u0536\u0561\u057f\u0578\u0576"
    ],
    "name:ita_x_preferred":[
        "Zaton"
    ],
    "name:nld_x_preferred":[
        "Zaton"
    ],
    "name:nor_x_preferred":[
        "Zaton"
    ],
    "name:rus_x_preferred":[
        "\u0417\u0430\u0442\u043e\u043d"
    ],
    "name:slv_x_preferred":[
        "Zaton"
    ],
    "name:srp_x_preferred":[
        "\u0417\u0430\u0442\u043e\u043d"
    ],
    "name:swe_x_preferred":[
        "Zaton"
    ],
    "name:ukr_x_preferred":[
        "\u0417\u0430\u0442\u043e\u043d"
    ],
    "name:und_x_variant":[
        "Aul Zatonskiy",
        "Zaton"
    ],
    "wof:name":"Zaton",
    "wof:placetype":"locality"
},
  "geometry": {"coordinates":[48.15583,45.9025],"type":"Point"}
}