{
  "type": "Feature",
  "properties": {
    "gn:admin1_code":"9",
    "gn:asciiname":"Sidorkin",
    "gn:country_code":"RU",
    "gn:dem":125,
    "gn:feature_class":"P",
    "gn:feature_code":"PPL",
    "gn:name":"Sidorkin",
    "gn:population":0,
    "gn:timezone":"Europe/Moscow",
    "iso:country":"RU",
    "name:rus_x_preferred":[
        "\u0421\u0438\u0434\u043e\u0440\u043a\u0438\u043d"
    ],
    "wof:name":"Sidorkin",
    "wof:placetype":"locality"
},
  "geometry": {"coordinates":[38.606,50.5973],"type":"Point"}
}