{
  "type": "Feature",
  "properties": {
    "gn:admin1_code":"12.0",
    "gn:asciiname":"Irzugu",
    "gn:country_code":"RU",
    "gn:dem":983,
    "gn:feature_class":"P",
    "gn:feature_code":"PPL",
    "gn:name":"Irzugu",
    "gn:population":0,
    "gn:timezone":"Europe/Moscow",
    "iso:country":"RU",
    "name:rus_x_preferred":[
        "\u0418\u0440\u0437\u0443\u0433\u0443"
    ],
    "wof:name":"Irzugu",
    "wof:placetype":"locality"
},
  "geometry": {"coordinates":[45.78667,42.81083],"type":"Point"}
}