{
  "type": "Feature",
  "properties": {
    "gn:admin1_code":"20",
    "gn:asciiname":"Fominovskaya",
    "gn:country_code":"RU",
    "gn:dem":501,
    "gn:feature_class":"P",
    "gn:feature_code":"PPL",
    "gn:name":"Fominovskaya",
    "gn:population":0,
    "gn:timezone":"Asia/Irkutsk",
    "iso:country":"RU",
    "name:rus_x_preferred":[
        "\u0424\u043e\u043c\u0438\u043d\u043e\u0432\u0441\u043a\u0430\u044f"
    ],
    "name:und_x_variant":[
        "\u0424\u043e\u043c\u0438\u043d\u043e\u0432\u0441\u043a\u0430\u044f"
    ],
    "wof:name":"Fominovskaya",
    "wof:placetype":"locality"
},
  "geometry": {"coordinates":[104.75,54.35],"type":"Point"}
}