{
  "type": "Feature",
  "properties": {
    "gn:admin1_code":"44",
    "gn:asciiname":"Neksikan",
    "gn:country_code":"RU",
    "gn:dem":608,
    "gn:feature_class":"P",
    "gn:feature_code":"PPL",
    "gn:name":"Neksikan",
    "gn:population":0,
    "gn:timezone":"Asia/Magadan",
    "iso:country":"RU",
    "name:eng_x_preferred":[
        "Neksikan"
    ],
    "name:nor_x_preferred":[
        "Neksikan"
    ],
    "name:rus_x_preferred":[
        "\u041d\u0435\u043a\u0441\u0438\u043a\u0430\u043d"
    ],
    "name:und_x_variant":[
        "\u041d\u0435\u043a\u0441\u0438\u043a\u0430\u043d"
    ],
    "wof:name":"Neksikan",
    "wof:placetype":"locality"
},
  "geometry": {"coordinates":[147.76713999999996,62.66851],"type":"Point"}
}