{
  "type": "Feature",
  "properties": {
    "gn:admin1_code":"33",
    "gn:asciiname":"Shishiner'",
    "gn:country_code":"RU",
    "gn:dem":87,
    "gn:feature_class":"P",
    "gn:feature_code":"PPL",
    "gn:name":"Shishiner\u2019",
    "gn:population":0,
    "gn:timezone":"Europe/Kirov",
    "iso:country":"RU",
    "name:eng_x_preferred":[
        "Shishiner'"
    ],
    "name:nor_x_preferred":[
        "Sjisjiner"
    ],
    "name:rus_x_preferred":[
        "\u0428\u0438\u0448\u0438\u043d\u0435\u0440\u044c"
    ],
    "name:und_x_variant":[
        "Shishiner\u2019"
    ],
    "wof:name":"Shishiner'",
    "wof:placetype":"locality"
},
  "geometry": {"coordinates":[50.5573,56.6567],"type":"Point"}
}