{
  "type": "Feature",
  "properties": {
    "gn:admin1_code":"43",
    "gn:asciiname":"Verkhneye Sukhinino",
    "gn:country_code":"RU",
    "gn:dem":175,
    "gn:feature_class":"P",
    "gn:feature_code":"PPL",
    "gn:name":"Verkhneye Sukhinino",
    "gn:population":0,
    "gn:timezone":"Europe/Moscow",
    "iso:country":"RU",
    "wof:name":"Verkhneye Sukhinino",
    "wof:placetype":"locality"
},
  "geometry": {"coordinates":[38.65,52.96666999999999],"type":"Point"}
}