{
  "type": "Feature",
  "properties": {
    "gn:admin1_code":"75",
    "gn:asciiname":"Il'ino",
    "gn:country_code":"RU",
    "gn:dem":50,
    "gn:feature_class":"P",
    "gn:feature_code":"PPL",
    "gn:name":"Il\u2019ino",
    "gn:population":0,
    "gn:timezone":"Asia/Tomsk",
    "iso:country":"RU",
    "name:eng_x_preferred":[
        "Il'ino"
    ],
    "name:nor_x_preferred":[
        "Ilino"
    ],
    "name:rus_x_preferred":[
        "\u0418\u043b\u044c\u0438\u043d\u043e"
    ],
    "name:und_x_variant":[
        "Il\u2019ino"
    ],
    "wof:name":"Il'ino",
    "wof:placetype":"locality"
},
  "geometry": {"coordinates":[81.20166999999999,59.09139],"type":"Point"}
}