{
  "type": "Feature",
  "properties": {
    "gn:admin1_code":"05",
    "gn:asciiname":"Dmitriyevka",
    "gn:country_code":"RU",
    "gn:dem":142,
    "gn:feature_class":"P",
    "gn:feature_code":"PPL",
    "gn:name":"Dmitriyevka",
    "gn:population":0,
    "gn:timezone":"Asia/Yakutsk",
    "iso:country":"RU",
    "name:eng_x_preferred":[
        "Dmitriyevka"
    ],
    "name:nor_x_preferred":[
        "Dmitrijevka"
    ],
    "name:rus_x_preferred":[
        "\u0414\u043c\u0438\u0442\u0440\u0438\u0435\u0432\u043a\u0430"
    ],
    "wof:name":"Dmitriyevka",
    "wof:placetype":"locality"
},
  "geometry": {"coordinates":[127.93057,50.40954],"type":"Point"}
}