{
  "type": "Feature",
  "properties": {
    "gn:admin1_code":"33.0",
    "gn:asciiname":"Kazennaya",
    "gn:country_code":"RU",
    "gn:dem":140,
    "gn:feature_class":"P",
    "gn:feature_code":"PPL",
    "gn:name":"Kaz\u00ebnnaya",
    "gn:population":0,
    "gn:timezone":"Europe/Kirov",
    "iso:country":"RU",
    "name:rus_x_preferred":[
        "\u041a\u0430\u0437\u0451\u043d\u043d\u0430\u044f"
    ],
    "name:und_x_variant":[
        "Kaz\u00ebnnaya",
        "\u041a\u0430\u0437\u0451\u043d\u043d\u0430\u044f"
    ],
    "wof:name":"Kazennaya",
    "wof:placetype":"locality"
},
  "geometry": {"coordinates":[48.0732,58.38983],"type":"Point"}
}