{
  "type": "Feature",
  "properties": {
    "gn:admin1_code":"88",
    "gn:asciiname":"Novoye Gostilovo",
    "gn:country_code":"RU",
    "gn:dem":133,
    "gn:feature_class":"P",
    "gn:feature_code":"PPL",
    "gn:name":"Novoye Gostilovo",
    "gn:population":0,
    "gn:timezone":"Europe/Moscow",
    "iso:country":"RU",
    "name:rus_x_preferred":[
        "\u041d\u043e\u0432\u043e\u0435 \u0413\u043e\u0441\u0442\u0438\u043b\u043e\u0432\u043e"
    ],
    "name:und_x_variant":[
        "\u041d\u043e\u0432\u043e\u0435 \u0413\u043e\u0441\u0442\u0438\u043b\u043e\u0432\u043e"
    ],
    "wof:name":"Novoye Gostilovo",
    "wof:placetype":"locality"
},
  "geometry": {"coordinates":[38.99403,57.80219],"type":"Point"}
}