{
  "type": "Feature",
  "properties": {
    "gn:admin1_code":"43",
    "gn:asciiname":"Poddubrovka",
    "gn:country_code":"RU",
    "gn:dem":113,
    "gn:feature_class":"P",
    "gn:feature_code":"PPL",
    "gn:name":"Poddubrovka",
    "gn:population":0,
    "gn:timezone":"Europe/Moscow",
    "iso:country":"RU",
    "name:eng_x_preferred":[
        "Poddubrovka"
    ],
    "name:nor_x_preferred":[
        "Poddubrovka"
    ],
    "name:rus_x_preferred":[
        "\u041f\u043e\u0434\u0434\u0443\u0431\u0440\u043e\u0432\u043a\u0430"
    ],
    "wof:name":"Poddubrovka",
    "wof:placetype":"locality"
},
  "geometry": {"coordinates":[39.54792,52.13062],"type":"Point"}
}