{
  "type": "Feature",
  "properties": {
    "gn:admin1_code":"16",
    "gn:asciiname":"Shatrakasy",
    "gn:country_code":"RU",
    "gn:dem":147,
    "gn:feature_class":"P",
    "gn:feature_code":"PPL",
    "gn:name":"Shatrakasy",
    "gn:population":0,
    "gn:timezone":"Europe/Moscow",
    "iso:country":"RU",
    "name:eng_x_preferred":[
        "Shatrakasy"
    ],
    "name:nor_x_preferred":[
        "Tsjurakkasy"
    ],
    "name:rus_x_preferred":[
        "\u0427\u0443\u0440\u0430\u043a\u043a\u0430\u0441\u044b"
    ],
    "name:rus_x_variant":[
        "\u0428\u0430\u0442\u0440\u0430\u043a\u0430\u0441\u044b"
    ],
    "name:und_x_variant":[
        "\u0428\u0430\u0442\u0440\u0430\u043a\u0430\u0441\u044b"
    ],
    "wof:name":"Shatrakasy",
    "wof:placetype":"locality"
},
  "geometry": {"coordinates":[46.8593,56.108],"type":"Point"}
}