{
  "type": "Feature",
  "properties": {
    "gn:admin1_code":"83",
    "gn:asciiname":"Kharlamovo",
    "gn:country_code":"RU",
    "gn:dem":96,
    "gn:feature_class":"P",
    "gn:feature_code":"PPL",
    "gn:name":"Kharlamovo",
    "gn:population":0,
    "gn:timezone":"Europe/Moscow",
    "iso:country":"RU",
    "name:rus_x_preferred":[
        "\u0425\u0430\u0440\u043b\u0430\u043c\u043e\u0432\u043e"
    ],
    "wof:name":"Kharlamovo",
    "wof:placetype":"locality"
},
  "geometry": {"coordinates":[40.98097,56.46229],"type":"Point"}
}