{
  "type": "Feature",
  "properties": {
    "gn:admin1_code":"77",
    "gn:asciiname":"Panyutino",
    "gn:country_code":"RU",
    "gn:dem":114,
    "gn:feature_class":"P",
    "gn:feature_code":"PPL",
    "gn:name":"Panyutino",
    "gn:population":0,
    "gn:timezone":"Europe/Moscow",
    "iso:country":"RU",
    "name:rus_x_preferred":[
        "\u041f\u0430\u043d\u044e\u0442\u0438\u043d\u043e"
    ],
    "name:und_x_variant":[
        "\u041f\u0430\u043d\u044e\u0442\u0438\u043d\u043e"
    ],
    "wof:name":"Panyutino",
    "wof:placetype":"locality"
},
  "geometry": {"coordinates":[37.8529,57.1023],"type":"Point"}
}