{
  "type": "Feature",
  "properties": {
    "gn:admin1_code":"20",
    "gn:asciiname":"Kolomyanka",
    "gn:country_code":"RU",
    "gn:dem":558,
    "gn:feature_class":"P",
    "gn:feature_code":"PPL",
    "gn:name":"Kolomyanka",
    "gn:population":0,
    "gn:timezone":"Asia/Irkutsk",
    "iso:country":"RU",
    "name:rus_x_preferred":[
        "\u041a\u043e\u043b\u043e\u043c\u044f\u043d\u043a\u0430"
    ],
    "name:und_x_variant":[
        "Kolominka",
        "Kolomyanka",
        "\u041a\u043e\u043b\u043e\u043c\u044f\u043d\u043a\u0430"
    ],
    "wof:name":"Kolomyanka",
    "wof:placetype":"locality"
},
  "geometry": {"coordinates":[102.81667,53.41667],"type":"Point"}
}