{
  "type": "Feature",
  "properties": {
    "gn:admin1_code":"20",
    "gn:asciiname":"Staryy Alzamay",
    "gn:country_code":"RU",
    "gn:dem":317,
    "gn:feature_class":"P",
    "gn:feature_code":"PPL",
    "gn:name":"Staryy Alzamay",
    "gn:population":0,
    "gn:timezone":"Asia/Irkutsk",
    "iso:country":"RU",
    "name:rus_x_preferred":[
        "\u0421\u0442\u0430\u0440\u044b\u0439 \u0410\u043b\u0437\u0430\u043c\u0430\u0439"
    ],
    "name:und_x_variant":[
        "\u0421\u0442\u0430\u0440\u044b\u0439 \u0410\u043b\u0437\u0430\u043c\u0430\u0439"
    ],
    "wof:name":"Staryy Alzamay",
    "wof:placetype":"locality"
},
  "geometry": {"coordinates":[98.60120000000001,55.595],"type":"Point"}
}