{
  "type": "Feature",
  "properties": {
    "gn:admin1_code":"77",
    "gn:asciiname":"Pechetovo",
    "gn:country_code":"RU",
    "gn:dem":142,
    "gn:feature_class":"P",
    "gn:feature_code":"PPL",
    "gn:name":"Pechetovo",
    "gn:population":0,
    "gn:timezone":"Europe/Moscow",
    "iso:country":"RU",
    "name:rus_x_preferred":[
        "\u041f\u0435\u0447\u0435\u0442\u043e\u0432\u043e"
    ],
    "wof:name":"Pechetovo",
    "wof:placetype":"locality"
},
  "geometry": {"coordinates":[37.0039,57.1409],"type":"Point"}
}