{
  "type": "Feature",
  "properties": {
    "gn:admin1_code":"37",
    "gn:asciiname":"Turilovo",
    "gn:country_code":"RU",
    "gn:dem":177,
    "gn:feature_class":"P",
    "gn:feature_code":"PPL",
    "gn:name":"Turilovo",
    "gn:population":0,
    "gn:timezone":"Europe/Moscow",
    "iso:country":"RU",
    "name:eng_x_preferred":[
        "Turilovo"
    ],
    "name:nor_x_preferred":[
        "Turilovo"
    ],
    "name:rus_x_preferred":[
        "\u0422\u0443\u0440\u0438\u043b\u043e\u0432\u043e"
    ],
    "name:und_x_variant":[
        "\u0422\u0443\u0440\u0438\u043b\u043e\u0432\u043e",
        "Turilovo"
    ],
    "wof:name":"Turilovo",
    "wof:placetype":"locality"
},
  "geometry": {"coordinates":[42.70757,58.20564],"type":"Point"}
}