{
  "type": "Feature",
  "properties": {
    "gn:admin1_code":"63",
    "gn:asciiname":"Arga-Khalva",
    "gn:country_code":"RU",
    "gn:dem":227,
    "gn:feature_class":"P",
    "gn:feature_code":"PPL",
    "gn:name":"Arga-Khalva",
    "gn:population":0,
    "gn:timezone":"Asia/Vladivostok",
    "iso:country":"RU",
    "name:nor_x_preferred":[
        "Arga-Khalva"
    ],
    "name:rus_x_preferred":[
        "\u0410\u0440\u0433\u0430-\u0425\u0430\u043b\u0432\u0430"
    ],
    "wof:name":"Arga-Khalva",
    "wof:placetype":"locality"
},
  "geometry": {"coordinates":[132.92694,66.41611],"type":"Point"}
}