{
  "type": "Feature",
  "properties": {
    "gn:admin1_code":"23",
    "gn:asciiname":"Izmailovskoye",
    "gn:country_code":"RU",
    "gn:dem":18,
    "gn:feature_class":"P",
    "gn:feature_code":"PPL",
    "gn:name":"Izmailovskoye",
    "gn:population":0,
    "gn:timezone":"Europe/Kaliningrad",
    "iso:country":"RU",
    "name:rus_x_preferred":[
        "\u0418\u0437\u043c\u0430\u0438\u043b\u043e\u0432\u0441\u043a\u043e\u0435"
    ],
    "name:und_x_variant":[
        "\u0418\u0437\u043c\u0430\u0438\u043b\u043e\u0432\u0441\u043a\u043e\u0435"
    ],
    "wof:name":"Izmailovskoye",
    "wof:placetype":"locality"
},
  "geometry": {"coordinates":[20.86639,54.74417],"type":"Point"}
}