{
  "type": "Feature",
  "properties": {
    "gn:admin1_code":"77",
    "gn:asciiname":"Selyayevo",
    "gn:country_code":"RU",
    "gn:dem":220,
    "gn:feature_class":"P",
    "gn:feature_code":"PPL",
    "gn:name":"Selyayevo",
    "gn:population":0,
    "gn:timezone":"Europe/Moscow",
    "iso:country":"RU",
    "name:nor_x_preferred":[
        "Seljaevo"
    ],
    "name:rus_x_preferred":[
        "\u0421\u0435\u043b\u044f\u0435\u0432\u043e"
    ],
    "wof:name":"Selyayevo",
    "wof:placetype":"locality"
},
  "geometry": {"coordinates":[35.22142,56.04381],"type":"Point"}
}