{
  "type": "Feature",
  "properties": {
    "gn:admin1_code":"47",
    "gn:asciiname":"Vlasovo",
    "gn:country_code":"RU",
    "gn:dem":148,
    "gn:feature_class":"P",
    "gn:feature_code":"PPL",
    "gn:name":"Vlasovo",
    "gn:population":0,
    "gn:timezone":"Europe/Moscow",
    "iso:country":"RU",
    "name:ceb_x_preferred":[
        "Vlasovo"
    ],
    "name:fra_x_preferred":[
        "Vlasovo"
    ],
    "name:msa_x_preferred":[
        "Vlasovo"
    ],
    "name:por_x_preferred":[
        "Vlasovo"
    ],
    "name:slv_x_preferred":[
        "Vlasovo"
    ],
    "name:sqi_x_preferred":[
        "Vllasova"
    ],
    "name:srp_x_preferred":[
        "\u0412\u043b\u0430\u0441\u043e\u0432\u043e"
    ],
    "wof:name":"Vlasovo",
    "wof:placetype":"locality"
},
  "geometry": {"coordinates":[36.63211,55.64928000000001],"type":"Point"}
}