{
  "type": "Feature",
  "properties": {
    "gn:admin1_code":"33",
    "gn:asciiname":"Nikolayevskoye",
    "gn:country_code":"RU",
    "gn:dem":175,
    "gn:feature_class":"P",
    "gn:feature_code":"PPL",
    "gn:name":"Nikolayevskoye",
    "gn:population":0,
    "gn:timezone":"Europe/Kirov",
    "iso:country":"RU",
    "name:eng_x_preferred":[
        "Nikolayevskoye"
    ],
    "name:nor_x_preferred":[
        "Nikolajevskoje"
    ],
    "name:rus_x_preferred":[
        "\u041d\u0438\u043a\u043e\u043b\u0430\u0435\u0432\u0441\u043a\u043e\u0435"
    ],
    "wof:name":"Nikolayevskoye",
    "wof:placetype":"locality"
},
  "geometry": {"coordinates":[46.67961,58.52025],"type":"Point"}
}