{
  "type": "Feature",
  "properties": {
    "gn:admin1_code":"84",
    "gn:asciiname":"Konev",
    "gn:cc2":"RU",
    "gn:country_code":"RU",
    "gn:dem":5,
    "gn:feature_class":"P",
    "gn:feature_code":"PPL",
    "gn:name":"Kon\u00ebv",
    "gn:population":0,
    "gn:timezone":"Europe/Volgograd",
    "iso:country":"RU",
    "name:rus_x_preferred":[
        "\u041a\u043e\u043d\u0451\u0432"
    ],
    "name:und_x_variant":[
        "Kon\u00ebv",
        "\u041a\u043e\u043d\u0451\u0432"
    ],
    "wof:name":"Konev",
    "wof:placetype":"locality"
},
  "geometry": {"coordinates":[45.17111,48.16278],"type":"Point"}
}