{
  "type": "Feature",
  "properties": {
    "gn:admin1_code":"24.0",
    "gn:asciiname":"Andratinskiy",
    "gn:country_code":"RU",
    "gn:dem":-15,
    "gn:feature_class":"P",
    "gn:feature_code":"PPL",
    "gn:name":"Andratinskiy",
    "gn:population":0,
    "gn:timezone":"Europe/Moscow",
    "iso:country":"RU",
    "name:eng_x_preferred":[
        "Andratinskiy"
    ],
    "name:nor_x_preferred":[
        "Andratinskij"
    ],
    "name:rus_x_preferred":[
        "\u0410\u043d\u0434\u0440\u0430\u0442\u0438\u043d\u0441\u043a\u0438\u0439"
    ],
    "name:und_x_variant":[
        "Andra-Ata",
        "\u0410\u043d\u0434\u0440\u0430\u0442\u0438\u043d\u0441\u043a\u0438\u0439",
        "Andratinskiy"
    ],
    "wof:name":"Andratinskiy",
    "wof:placetype":"locality"
},
  "geometry": {"coordinates":[46.33266,44.9509],"type":"Point"}
}