{
  "type": "Feature",
  "properties": {
    "gn:admin1_code":"53",
    "gn:asciiname":"Stepanovka Vtoraya",
    "gn:country_code":"RU",
    "gn:dem":107,
    "gn:feature_class":"P",
    "gn:feature_code":"PPL",
    "gn:name":"Stepanovka Vtoraya",
    "gn:population":0,
    "gn:timezone":"Asia/Novosibirsk",
    "iso:country":"RU",
    "name:eng_x_preferred":[
        "Stepanovka Vtoraya"
    ],
    "name:nor_x_preferred":[
        "Stepanovka"
    ],
    "name:rus_x_preferred":[
        "\u0421\u0442\u0435\u043f\u0430\u043d\u043e\u0432\u043a\u0430"
    ],
    "name:rus_x_variant":[
        "\u0421\u0442\u0435\u043f\u0430\u043d\u043e\u0432\u043a\u0430 \u0412\u0442\u043e\u0440\u0430\u044f",
        "\u0421\u0442\u0435\u043f\u0430\u043d\u043e\u0432\u043a\u0430 2-\u044f"
    ],
    "name:und_x_variant":[
        "Vtoraya Stepanovka",
        "Stepanovka",
        "Stepanovka Vtoraya",
        "\u0421\u0442\u0435\u043f\u0430\u043d\u043e\u0432\u043a\u0430 \u0412\u0442\u043e\u0440\u0430\u044f"
    ],
    "wof:name":"Stepanovka Vtoraya",
    "wof:placetype":"locality"
},
  "geometry": {"coordinates":[75.51441,55.22847],"type":"Point"}
}