{
  "type": "Feature",
  "properties": {
    "gn:admin1_code":"77",
    "gn:asciiname":"Polovtsovo",
    "gn:country_code":"RU",
    "gn:dem":195,
    "gn:feature_class":"P",
    "gn:feature_code":"PPL",
    "gn:name":"Polovtsovo",
    "gn:population":0,
    "gn:timezone":"Europe/Moscow",
    "iso:country":"RU",
    "name:rus_x_preferred":[
        "\u041f\u043e\u043b\u043e\u0432\u0446\u043e\u0432\u043e"
    ],
    "name:und_x_variant":[
        "Polovtsevo",
        "Polovtsovo"
    ],
    "wof:name":"Polovtsovo",
    "wof:placetype":"locality"
},
  "geometry": {"coordinates":[32.75188,56.21855],"type":"Point"}
}