{
  "type": "Feature",
  "properties": {
    "gn:country":"RU",
    "gn:fcode":"PPL",
    "gn:population":548,
    "iso:country":"RU",
    "name:eng_x_preferred":[
        "Fadyushina"
    ],
    "name:epo_x_preferred":[
        "Fadju\u015dina"
    ],
    "name:nor_x_preferred":[
        "Fadjusjina"
    ],
    "name:rus_x_preferred":[
        "\u0424\u0430\u0434\u044e\u0448\u0438\u043d\u0430"
    ],
    "name:und_x_variant":[
        "Fodyushina"
    ],
    "qs:name":"Fadyushino",
    "qs:name_adm0":"Russia",
    "qs:name_adm1":"Sverdlovsk Oblast",
    "qs:photos_9r":0,
    "qs:photos_sr":0,
    "qs:placetype":"Town",
    "qs:pop_sr":"2",
    "wof:name":"Fadyushino",
    "wof:placetype":"locality",
    "wof:population":548
},
  "geometry": {"coordinates":[62.7286,56.7876],"type":"Point"}
}