{
  "type": "Feature",
  "properties": {
    "gn:admin1_code":"46",
    "gn:asciiname":"Yamshchina",
    "gn:country_code":"RU",
    "gn:dem":175,
    "gn:feature_class":"P",
    "gn:feature_code":"PPL",
    "gn:name":"Yamshchina",
    "gn:population":0,
    "gn:timezone":"Europe/Moscow",
    "iso:country":"RU",
    "name:eng_x_preferred":[
        "Yamshchina"
    ],
    "name:nor_x_preferred":[
        "Jamsjtsjina"
    ],
    "name:rus_x_preferred":[
        "\u042f\u043c\u0449\u0438\u043d\u0430"
    ],
    "name:und_x_variant":[
        "\u042f\u043c\u0449\u0438\u043d\u0430",
        "Yamshchina"
    ],
    "wof:name":"Yamshchina",
    "wof:placetype":"locality"
},
  "geometry": {"coordinates":[44.2532,53.9604],"type":"Point"}
}