{
  "type": "Feature",
  "properties": {
    "gn:country":"RU",
    "gn:fcode":"PPL",
    "gn:population":600,
    "iso:country":"RU",
    "name:eng_x_preferred":[
        "Yunda"
    ],
    "name:nor_x_preferred":[
        "Junda"
    ],
    "name:rus_x_preferred":[
        "\u042e\u043d\u0434\u0430"
    ],
    "name:und_x_variant":[
        "Bol\u2019shaya Yunda"
    ],
    "qs:name":"Yunda",
    "qs:photos_9r":0,
    "qs:photos_sr":0,
    "qs:pop_sr":"2",
    "wof:name":"Yunda",
    "wof:placetype":"locality",
    "wof:population":600
},
  "geometry": {"coordinates":[52.8957,57.8822],"type":"Point"}
}