{
  "type": "Feature",
  "properties": {
    "gn:country":"RU",
    "gn:fcode":"PPL",
    "gn:pop":5928,
    "iso:country":"RU",
    "name:eng_x_preferred":[
        "Sokol"
    ],
    "name:nor_x_preferred":[
        "Sokol"
    ],
    "name:rus_x_preferred":[
        "\u0421\u043e\u043a\u043e\u043b"
    ],
    "name:unk_x_variant":[
        "\u0421\u043e\u043a\u043e\u043b"
    ],
    "qs:name":"Sokol",
    "qs:name_adm0":"Russia",
    "qs:name_adm1":"Buryatia Republic",
    "qs:photos_9k":1,
    "qs:photos_9r":1,
    "qs:photos_all":7,
    "qs:photos_sr":0,
    "qs:placetype":"Town",
    "qs:pop_sr":"5",
    "wd:wordcount":2486,
    "wof:name":"Sokol",
    "wof:placetype":"locality",
    "wof:population":5928
},
  "geometry": {"coordinates":[107.44437000000001,51.80036],"type":"Point"}
}