{
  "type": "Feature",
  "properties": {
    "gn:country":"RU",
    "gn:fcode":"PPL",
    "gn:population":5928,
    "iso:country":"RU",
    "name:ast_x_preferred":[
        "Sokol"
    ],
    "name:ben_x_preferred":[
        "\u09b8\u09cb\u0995\u09cb\u09b2"
    ],
    "name:bul_x_preferred":[
        "\u0421\u043e\u043a\u043e\u043b"
    ],
    "name:cat_x_preferred":[
        "Sokol"
    ],
    "name:ces_x_preferred":[
        "Sokol"
    ],
    "name:cym_x_preferred":[
        "Sokol"
    ],
    "name:dan_x_preferred":[
        "Sokol"
    ],
    "name:deu_x_preferred":[
        "Sokol"
    ],
    "name:ell_x_preferred":[
        "\u03a3\u03bf\u03ba\u03cc\u03bb"
    ],
    "name:ell_x_variant":[
        "\u03a3\u03cc\u03ba\u03bf\u03bb"
    ],
    "name:eng_x_preferred":[
        "Sokol"
    ],
    "name:epo_x_preferred":[
        "Sokol-movado"
    ],
    "name:fas_x_preferred":[
        "\u0628\u0627\u0634\u06af\u0627\u0647 \u0633\u0648\u06a9\u0648\u0644"
    ],
    "name:fra_x_preferred":[
        "Sokol"
    ],
    "name:heb_x_preferred":[
        "\u05e1\u05d5\u05e7\u05d5\u05dc"
    ],
    "name:hin_x_preferred":[
        "\u0938\u094b\u0915\u094b\u0932"
    ],
    "name:hrv_x_preferred":[
        "Sokol"
    ],
    "name:hye_x_preferred":[
        "\u054d\u0578\u056f\u0578\u056c\u0575\u0561\u0576 \u0577\u0561\u0580\u056a\u0578\u0582\u0574"
    ],
    "name:ind_x_preferred":[
        "Sokol"
    ],
    "name:ita_x_preferred":[
        "Sokol"
    ],
    "name:jpn_x_preferred":[
        "\u30bd\u30b3\u30eb"
    ],
    "name:mkd_x_preferred":[
        "\u0421\u043e\u043a\u043e\u043b"
    ],
    "name:nld_x_preferred":[
        "Sokol"
    ],
    "name:nno_x_preferred":[
        "Sokol"
    ],
    "name:nob_x_preferred":[
        "Sokol"
    ],
    "name:nor_x_preferred":[
        "Sokol"
    ],
    "name:pol_x_preferred":[
        "Sok\u00f3\u0142"
    ],
    "name:ron_x_preferred":[
        "Sokol"
    ],
    "name:rus_x_preferred":[
        "\u0421\u043e\u043a\u043e\u043b"
    ],
    "name:rus_x_variant":[
        "\u0421\u043e\u043a\u043e\u043b\u044c\u0441\u043a\u043e\u0435 \u0434\u0432\u0438\u0436\u0435\u043d\u0438\u0435"
    ],
    "name:slv_x_preferred":[
        "Sokol"
    ],
    "name:spa_x_preferred":[
        "Sokol"
    ],
    "name:swe_x_preferred":[
        "Sokol"
    ],
    "name:ukr_x_preferred":[
        "\u0421\u043e\u043a\u0456\u043b"
    ],
    "name:urd_x_preferred":[
        "\u0633\u0648\u06a9\u0648\u0644"
    ],
    "name:vie_x_preferred":[
        "Sokol"
    ],
    "name:zho_x_preferred":[
        "\u7d22\u79d1\u5c14"
    ],
    "qs:name":"Sokol",
    "qs:name_adm0":"Russia",
    "qs:name_adm1":"Buryatia Republic",
    "qs:photos_9k":1,
    "qs:photos_9r":1,
    "qs:photos_all":7,
    "qs:photos_sr":0,
    "qs:placetype":"Town",
    "qs:pop_sr":"5",
    "wd:wordcount":2486,
    "wof:name":"Sokol",
    "wof:placetype":"locality",
    "wof:population":5928
},
  "geometry": {"coordinates":[107.44437000000001,51.80036],"type":"Point"}
}