{
  "type": "Feature",
  "properties": {
    "gn:admin1_code":"90",
    "gn:asciiname":"Pastukhovo",
    "gn:country_code":"RU",
    "gn:dem":198,
    "gn:feature_class":"P",
    "gn:feature_code":"PPL",
    "gn:name":"Pastukhovo",
    "gn:population":0,
    "gn:timezone":"Asia/Yekaterinburg",
    "iso:country":"RU",
    "name:rus_x_preferred":[
        "\u041f\u0430\u0441\u0442\u0443\u0445\u043e\u0432\u043e"
    ],
    "name:und_x_variant":[
        "Pastukhova",
        "Pastukhovo"
    ],
    "wof:name":"Pastukhovo",
    "wof:placetype":"locality"
},
  "geometry": {"coordinates":[57.622,56.9677],"type":"Point"}
}