{
  "type": "Feature",
  "properties": {
    "gn:admin1_code":"51",
    "gn:asciiname":"Vagan'kovo",
    "gn:country_code":"RU",
    "gn:dem":71,
    "gn:feature_class":"P",
    "gn:feature_code":"PPL",
    "gn:name":"Vagan\u2019kovo",
    "gn:population":0,
    "gn:timezone":"Europe/Moscow",
    "iso:country":"RU",
    "name:eng_x_preferred":[
        "Vagan'kovo"
    ],
    "name:nor_x_preferred":[
        "Vagankovo"
    ],
    "name:rus_x_preferred":[
        "\u0412\u0430\u0433\u0430\u043d\u044c\u043a\u043e\u0432\u043e"
    ],
    "name:und_x_variant":[
        "Vagan\u2019kova",
        "Vagan\u2019kovo"
    ],
    "wof:name":"Vagan'kovo",
    "wof:placetype":"locality"
},
  "geometry": {"coordinates":[44.34349,56.2129],"type":"Point"}
}