{
  "type": "Feature",
  "properties": {
    "gn:admin1_code":"52",
    "gn:asciiname":"Iglinka",
    "gn:country_code":"RU",
    "gn:dem":70,
    "gn:feature_class":"P",
    "gn:feature_code":"PPL",
    "gn:name":"Iglinka",
    "gn:population":0,
    "gn:timezone":"Europe/Moscow",
    "iso:country":"RU",
    "name:rus_x_preferred":[
        "\u0418\u0433\u043b\u0438\u043d\u043a\u0430"
    ],
    "name:und_x_variant":[
        "\u0418\u0433\u043b\u0438\u043d\u043a\u0430"
    ],
    "wof:name":"Iglinka",
    "wof:placetype":"locality"
},
  "geometry": {"coordinates":[32.26667,58.98333],"type":"Point"}
}