{
  "type": "Feature",
  "properties": {
    "gn:admin1_code":"75",
    "gn:asciiname":"Komarovka",
    "gn:cc2":"RU",
    "gn:country_code":"RU",
    "gn:dem":101,
    "gn:feature_class":"P",
    "gn:feature_code":"PPL",
    "gn:name":"Komarovka",
    "gn:population":0,
    "gn:timezone":"Asia/Tomsk",
    "iso:country":"RU",
    "name:rus_x_preferred":[
        "\u041a\u043e\u043c\u0430\u0440\u043e\u0432\u043a\u0430"
    ],
    "name:und_x_variant":[
        "Komarovskiy",
        "Komarovka",
        "\u041a\u043e\u043c\u0430\u0440\u043e\u0432\u043a\u0430"
    ],
    "wof:name":"Komarovka",
    "wof:placetype":"locality"
},
  "geometry": {"coordinates":[81.66667,57.36666999999999],"type":"Point"}
}