{
  "type": "Feature",
  "properties": {
    "gn:admin1_code":"42",
    "gn:asciiname":"Tetoy Gora-Gora",
    "gn:cc2":"RU",
    "gn:country_code":"RU",
    "gn:dem":197,
    "gn:feature_class":"P",
    "gn:feature_code":"PPL",
    "gn:name":"Tetoy Gora-Gora",
    "gn:population":0,
    "gn:timezone":"Europe/Moscow",
    "iso:country":"RU",
    "name:und_x_variant":[
        "Gora",
        "Tetoy Gora-Gora"
    ],
    "wof:name":"Tetoy Gora-Gora",
    "wof:placetype":"locality"
},
  "geometry": {"coordinates":[35.21667,60.86666999999999],"type":"Point"}
}