{
  "type": "Feature",
  "properties": {
    "gn:admin1_code":"37",
    "gn:asciiname":"Bol'shaya Izbenka",
    "gn:country_code":"RU",
    "gn:dem":196,
    "gn:feature_class":"P",
    "gn:feature_code":"PPL",
    "gn:name":"Bol\u2019shaya Izbenka",
    "gn:population":0,
    "gn:timezone":"Europe/Moscow",
    "iso:country":"RU",
    "name:rus_x_preferred":[
        "\u0411\u043e\u043b\u044c\u0448\u0430\u044f \u0418\u0437\u0431\u0435\u043d\u043a\u0430"
    ],
    "name:und_x_variant":[
        "Bol\u2019shaya Izbenka",
        "\u0411\u043e\u043b\u044c\u0448\u0430\u044f \u0418\u0437\u0431\u0435\u043d\u043a\u0430"
    ],
    "wof:name":"Bol'shaya Izbenka",
    "wof:placetype":"locality"
},
  "geometry": {"coordinates":[45.122,58.8514],"type":"Point"}
}