{
  "type": "Feature",
  "properties": {
    "gn:admin1_code":"33",
    "gn:asciiname":"Volosnitsa",
    "gn:country_code":"RU",
    "gn:dem":173,
    "gn:feature_class":"P",
    "gn:feature_code":"PPL",
    "gn:name":"Volosnitsa",
    "gn:population":0,
    "gn:timezone":"Europe/Kirov",
    "iso:country":"RU",
    "name:eng_x_preferred":[
        "Volosnitsa"
    ],
    "name:nor_x_preferred":[
        "Volosnitsa"
    ],
    "name:rus_x_preferred":[
        "\u0412\u043e\u043b\u043e\u0441\u043d\u0438\u0446\u0430"
    ],
    "wof:name":"Volosnitsa",
    "wof:placetype":"locality"
},
  "geometry": {"coordinates":[52.55428000000001,59.64449000000001],"type":"Point"}
}