{
  "type": "Feature",
  "properties": {
    "gn:admin1_code":"77",
    "gn:asciiname":"Rylovo",
    "gn:country_code":"RU",
    "gn:dem":231,
    "gn:feature_class":"P",
    "gn:feature_code":"PPL",
    "gn:name":"Rylovo",
    "gn:population":0,
    "gn:timezone":"Europe/Moscow",
    "iso:country":"RU",
    "name:rus_x_preferred":[
        "\u0420\u044b\u043b\u043e\u0432\u043e"
    ],
    "name:und_x_variant":[
        "\u0420\u044b\u043b\u043e\u0432\u043e"
    ],
    "wof:name":"Rylovo",
    "wof:placetype":"locality"
},
  "geometry": {"coordinates":[33.50451,56.59962],"type":"Point"}
}