{
  "type": "Feature",
  "properties": {
    "gn:admin1_code":"43.0",
    "gn:asciiname":"Chechery",
    "gn:country_code":"RU",
    "gn:dem":128,
    "gn:feature_class":"P",
    "gn:feature_code":"PPL",
    "gn:name":"Chech\u00ebry",
    "gn:population":0,
    "gn:timezone":"Europe/Moscow",
    "iso:country":"RU",
    "name:rus_x_preferred":[
        "\u0427\u0435\u0447\u0451\u0440\u044b"
    ],
    "name:und_x_variant":[
        "Chech\u00ebry"
    ],
    "wof:name":"Chechery",
    "wof:placetype":"locality"
},
  "geometry": {"coordinates":[39.9452,52.7884],"type":"Point"}
}