{
  "type": "Feature",
  "properties": {
    "gn:admin1_code":"80",
    "gn:asciiname":"Omutnitsa",
    "gn:country_code":"RU",
    "gn:dem":148,
    "gn:feature_class":"P",
    "gn:feature_code":"PPL",
    "gn:name":"Omutnitsa",
    "gn:population":0,
    "gn:timezone":"Europe/Samara",
    "iso:country":"RU",
    "name:eng_x_preferred":[
        "Omutnitsa"
    ],
    "name:nor_x_preferred":[
        "Omutnitsa"
    ],
    "name:rus_x_preferred":[
        "\u041e\u043c\u0443\u0442\u043d\u0438\u0446\u0430"
    ],
    "name:und_x_variant":[
        "\u041e\u043c\u0443\u0442\u043d\u0438\u0446\u0430",
        "Omutnitsa"
    ],
    "wof:name":"Omutnitsa",
    "wof:placetype":"locality"
},
  "geometry": {"coordinates":[52.9131,58.0763],"type":"Point"}
}