{
  "type": "Feature",
  "properties": {
    "gn:admin1_code":"41.0",
    "gn:asciiname":"Ivanovskiy",
    "gn:country_code":"RU",
    "gn:dem":214,
    "gn:feature_class":"P",
    "gn:feature_code":"PPL",
    "gn:name":"Ivanovskiy",
    "gn:population":0,
    "gn:timezone":"Europe/Moscow",
    "iso:country":"RU",
    "name:rus_x_preferred":[
        "\u0418\u0432\u0430\u043d\u043e\u0432\u0441\u043a\u0438\u0439"
    ],
    "name:und_x_variant":[
        "Ivanovka",
        "Ivanovskiy",
        "\u0418\u0432\u0430\u043d\u043e\u0432\u0441\u043a\u0438\u0439"
    ],
    "wof:name":"Ivanovskiy",
    "wof:placetype":"locality"
},
  "geometry": {"coordinates":[35.8196,51.9297],"type":"Point"}
}