{
  "type": "Feature",
  "properties": {
    "gn:admin1_code":"87",
    "gn:asciiname":"Parovat",
    "gn:cc2":"RU",
    "gn:country_code":"RU",
    "gn:dem":17,
    "gn:feature_class":"P",
    "gn:feature_code":"PPL",
    "gn:name":"Parovat",
    "gn:population":0,
    "gn:timezone":"Asia/Yekaterinburg",
    "iso:country":"RU",
    "name:eng_x_preferred":[
        "Parovat"
    ],
    "name:nor_x_preferred":[
        "Parovat"
    ],
    "name:rus_x_preferred":[
        "\u041f\u0430\u0440\u043e\u0432\u0430\u0442"
    ],
    "name:und_x_variant":[
        "Paravat",
        "Paravatskiye",
        "\u041f\u0430\u0440\u043e\u0432\u0430\u0442",
        "Parovat"
    ],
    "wof:name":"Parovat",
    "wof:placetype":"locality"
},
  "geometry": {"coordinates":[65.93333,65.96666999999999],"type":"Point"}
}