{
  "type": "Feature",
  "properties": {
    "gn:admin1_code":"41",
    "gn:asciiname":"Kotovo",
    "gn:country_code":"RU",
    "gn:dem":205,
    "gn:feature_class":"P",
    "gn:feature_code":"PPL",
    "gn:name":"Kotovo",
    "gn:population":0,
    "gn:timezone":"Europe/Moscow",
    "iso:country":"RU",
    "name:hye_x_preferred":[
        "\u053f\u0578\u057f\u0578\u057e\u0578"
    ],
    "name:rus_x_preferred":[
        "\u041a\u043e\u0442\u043e\u0432\u043e"
    ],
    "wof:name":"Kotovo",
    "wof:placetype":"locality"
},
  "geometry": {"coordinates":[36.42593,51.26958],"type":"Point"}
}