{
  "type": "Feature",
  "properties": {
    "gn:admin1_code":"51",
    "gn:asciiname":"Strelka",
    "gn:country_code":"RU",
    "gn:dem":84,
    "gn:feature_class":"P",
    "gn:feature_code":"PPL",
    "gn:name":"Strelka",
    "gn:population":0,
    "gn:timezone":"Europe/Moscow",
    "iso:country":"RU",
    "name:rus_x_preferred":[
        "\u0421\u0442\u0440\u0435\u043b\u043a\u0430"
    ],
    "name:und_x_variant":[
        "\u0421\u0442\u0440\u0435\u043b\u043a\u0430"
    ],
    "wof:name":"Strelka",
    "wof:placetype":"locality"
},
  "geometry": {"coordinates":[41.84535,55.16241],"type":"Point"}
}