{
  "type": "Feature",
  "properties": {
    "gn:admin1_code":"51",
    "gn:asciiname":"Strelka",
    "gn:country_code":"RU",
    "gn:dem":84,
    "gn:feature_class":"P",
    "gn:feature_code":"PPL",
    "gn:name":"Strelka",
    "gn:population":0,
    "gn:timezone":"Europe/Moscow",
    "iso:country":"RU",
    "name:ceb_x_preferred":[
        "Strelka"
    ],
    "name:deu_x_preferred":[
        "Strelka"
    ],
    "name:est_x_preferred":[
        "Strelka"
    ],
    "name:hye_x_preferred":[
        "\u054d\u057f\u0580\u0565\u056c\u056f\u0561"
    ],
    "name:ita_x_preferred":[
        "Strelka"
    ],
    "name:rus_x_preferred":[
        "\u0421\u0442\u0440\u0435\u043b\u043a\u0430"
    ],
    "name:slk_x_preferred":[
        "Strelka"
    ],
    "name:swe_x_preferred":[
        "Strelka"
    ],
    "name:ukr_x_preferred":[
        "\u0421\u0442\u0440\u0454\u043b\u043a\u0430"
    ],
    "name:ukr_x_variant":[
        "\u0421\u0442\u0440\u0456\u043b\u043a\u0430"
    ],
    "name:urd_x_preferred":[
        "\u0627\u0633\u0679\u0631\u06cc\u0644\u06a9\u0627"
    ],
    "name:vie_x_preferred":[
        "Strelka"
    ],
    "name:zho_cn_x_preferred":[
        "\u65af\u7279\u96f7\u5c14\u5361"
    ],
    "name:zho_tw_x_preferred":[
        "\u65af\u7279\u5217\u723e\u5361"
    ],
    "wof:name":"Strelka",
    "wof:placetype":"locality"
},
  "geometry": {"coordinates":[41.84535,55.16241],"type":"Point"}
}