{
  "type": "Feature",
  "properties": {
    "gn:admin1_code":"73.0",
    "gn:asciiname":"Berezovaya Griva",
    "gn:country_code":"RU",
    "gn:dem":98,
    "gn:feature_class":"P",
    "gn:feature_code":"PPL",
    "gn:name":"Ber\u00ebzovaya Griva",
    "gn:population":0,
    "gn:timezone":"Europe/Moscow",
    "iso:country":"RU",
    "name:nor_x_preferred":[
        "Berjozovaja Griva"
    ],
    "name:rus_x_preferred":[
        "\u0411\u0435\u0440\u0451\u0437\u043e\u0432\u0430\u044f \u0413\u0440\u0438\u0432\u0430"
    ],
    "name:und_x_variant":[
        "Ber\u00ebzovaya Griva"
    ],
    "wof:name":"Berezovaya Griva",
    "wof:placetype":"locality"
},
  "geometry": {"coordinates":[49.7438,55.2021],"type":"Point"}
}