{
  "type": "Feature",
  "properties": {
    "gn:admin1_code":"86",
    "gn:asciiname":"Repin Kut",
    "gn:country_code":"RU",
    "gn:dem":119,
    "gn:feature_class":"P",
    "gn:feature_code":"PPL",
    "gn:name":"Repin Kut",
    "gn:population":0,
    "gn:timezone":"Europe/Moscow",
    "iso:country":"RU",
    "name:rus_x_preferred":[
        "\u0420\u0435\u043f\u0438\u043d \u041a\u0443\u0442"
    ],
    "wof:name":"Repin Kut",
    "wof:placetype":"locality"
},
  "geometry": {"coordinates":[38.4756,51.1591],"type":"Point"}
}