{
  "type": "Feature",
  "properties": {
    "gn:admin1_code":"64",
    "gn:asciiname":"Kruglovo",
    "gn:country_code":"RU",
    "gn:dem":30,
    "gn:feature_class":"P",
    "gn:feature_code":"PPL",
    "gn:name":"Kruglovo",
    "gn:population":0,
    "gn:timezone":"Asia/Tokyo",
    "iso:country":"RU",
    "name:rus_x_preferred":[
        "\u041a\u0440\u0443\u0433\u043b\u043e\u0432\u043e"
    ],
    "name:und_x_variant":[
        "Shiranukatomari",
        "Siranukatomari",
        "Kruglovo"
    ],
    "wof:name":"Kruglovo",
    "wof:placetype":"locality"
},
  "geometry": {"coordinates":[146.46666999999999,44.38333],"type":"Point"}
}