{
  "type": "Feature",
  "properties": {
    "gn:admin1_code":"85",
    "gn:asciiname":"Volodino",
    "gn:country_code":"RU",
    "gn:dem":141,
    "gn:feature_class":"P",
    "gn:feature_code":"PPL",
    "gn:name":"Volodino",
    "gn:population":0,
    "gn:timezone":"Europe/Moscow",
    "iso:country":"RU",
    "name:che_x_preferred":[
        "\u0412\u043e\u043b\u043e\u0434\u0438\u043d\u043e"
    ],
    "name:eng_x_preferred":[
        "Volodino"
    ],
    "name:nor_x_preferred":[
        "Volodino"
    ],
    "name:rus_x_preferred":[
        "\u0412\u043e\u043b\u043e\u0434\u0438\u043d\u043e"
    ],
    "wof:name":"Volodino",
    "wof:placetype":"locality"
},
  "geometry": {"coordinates":[35.8227,59.409],"type":"Point"}
}