{
  "type": "Feature",
  "properties": {
    "gn:admin1_code":"90.0",
    "gn:asciiname":"Batashata",
    "gn:country_code":"RU",
    "gn:dem":150,
    "gn:feature_class":"P",
    "gn:feature_code":"PPL",
    "gn:name":"Batashata",
    "gn:population":0,
    "gn:timezone":"Asia/Yekaterinburg",
    "iso:country":"RU",
    "name:nor_x_preferred":[
        "Batasjata"
    ],
    "name:rus_x_preferred":[
        "\u0411\u0430\u0442\u0430\u0448\u0430\u0442\u0430"
    ],
    "wof:name":"Batashata",
    "wof:placetype":"locality"
},
  "geometry": {"coordinates":[57.0627,58.7464],"type":"Point"}
}