{
  "type": "Feature",
  "properties": {
    "gn:admin1_code":"25",
    "gn:asciiname":"Strelkovka",
    "gn:country_code":"RU",
    "gn:dem":125,
    "gn:feature_class":"P",
    "gn:feature_code":"PPL",
    "gn:name":"Strelkovka",
    "gn:population":0,
    "gn:timezone":"Europe/Moscow",
    "iso:country":"RU",
    "name:rus_x_preferred":[
        "\u0421\u0442\u0440\u0435\u043b\u043a\u043e\u0432\u043a\u0430"
    ],
    "name:und_x_variant":[
        "\u0421\u0442\u0440\u0435\u043b\u043a\u043e\u0432\u043a\u0430"
    ],
    "wof:name":"Strelkovka",
    "wof:placetype":"locality"
},
  "geometry": {"coordinates":[36.72639,54.99916999999999],"type":"Point"}
}