{
  "type": "Feature",
  "properties": {
    "gn:admin1_code":"69.0",
    "gn:asciiname":"Bol'shiye Lyzki",
    "gn:country_code":"RU",
    "gn:dem":194,
    "gn:feature_class":"P",
    "gn:feature_code":"PPL",
    "gn:name":"Bol\u2019shiye Lyzki",
    "gn:population":136,
    "gn:timezone":"Europe/Moscow",
    "iso:country":"RU",
    "name:eng_x_preferred":[
        "Bol'shiye Lyzki"
    ],
    "name:nor_x_preferred":[
        "Bolsjije Lyzki"
    ],
    "name:rus_x_preferred":[
        "\u0411\u043e\u043b\u044c\u0448\u0438\u0435 \u041b\u044b\u0437\u043a\u0438"
    ],
    "name:und_x_variant":[
        "Bol\u2019shiye Lyzki"
    ],
    "wof:name":"Bol'shiye Lyzki",
    "wof:placetype":"locality",
    "wof:population":136
},
  "geometry": {"coordinates":[32.07937,54.20464000000001],"type":"Point"}
}