{
  "type": "Feature",
  "properties": {
    "gn:admin1_code":"10",
    "gn:asciiname":"Kucheyevo",
    "gn:country_code":"RU",
    "gn:dem":177,
    "gn:feature_class":"P",
    "gn:feature_code":"PPL",
    "gn:name":"Kucheyevo",
    "gn:population":0,
    "gn:timezone":"Europe/Moscow",
    "iso:country":"RU",
    "name:rus_x_preferred":[
        "\u041a\u0443\u0447\u0435\u0435\u0432\u043e"
    ],
    "wof:name":"Kucheyevo",
    "wof:placetype":"locality"
},
  "geometry": {"coordinates":[33.68626,53.20695],"type":"Point"}
}