{
  "type": "Feature",
  "properties": {
    "gn:admin1_code":"46",
    "gn:asciiname":"Novotyaglovka",
    "gn:country_code":"RU",
    "gn:dem":170,
    "gn:feature_class":"P",
    "gn:feature_code":"PPL",
    "gn:name":"Novotyaglovka",
    "gn:population":0,
    "gn:timezone":"Europe/Moscow",
    "iso:country":"RU",
    "name:rus_x_preferred":[
        "\u041d\u043e\u0432\u043e\u0442\u044f\u0433\u043b\u043e\u0432\u043a\u0430"
    ],
    "name:und_x_variant":[
        "Novaya Tyaglovka",
        "Novotyaglovka"
    ],
    "wof:name":"Novotyaglovka",
    "wof:placetype":"locality"
},
  "geometry": {"coordinates":[45.3377,53.92321999999999],"type":"Point"}
}