{
  "type": "Feature",
  "properties": {
    "gn:admin1_code":"91.0",
    "gn:asciiname":"Puzyreva",
    "gn:country_code":"RU",
    "gn:dem":179,
    "gn:feature_class":"P",
    "gn:feature_code":"PPL",
    "gn:name":"Puzyr\u00ebva",
    "gn:population":0,
    "gn:timezone":"Asia/Krasnoyarsk",
    "iso:country":"RU",
    "name:rus_x_preferred":[
        "\u041f\u0443\u0437\u044b\u0440\u00eb\u0432\u0430"
    ],
    "name:und_x_variant":[
        "Puzyr\u00ebva"
    ],
    "wof:name":"Puzyreva",
    "wof:placetype":"locality"
},
  "geometry": {"coordinates":[93.15956,55.96841],"type":"Point"}
}