{
  "type": "Feature",
  "properties": {
    "gn:admin1_code":"52.0",
    "gn:asciiname":"Dubki",
    "gn:country_code":"RU",
    "gn:dem":209,
    "gn:feature_class":"P",
    "gn:feature_code":"PPL",
    "gn:name":"Dubki",
    "gn:population":0,
    "gn:timezone":"Europe/Moscow",
    "iso:country":"RU",
    "name:rus_x_preferred":[
        "\u0414\u0443\u0431\u043a\u0438"
    ],
    "name:und_x_variant":[
        "P\u00ebsiy Konets",
        "Dubki"
    ],
    "wof:name":"Dubki",
    "wof:placetype":"locality"
},
  "geometry": {"coordinates":[32.73547,57.67895],"type":"Point"}
}