{
  "type": "Feature",
  "properties": {
    "gn:admin1_code":"37.0",
    "gn:asciiname":"Semenkovo",
    "gn:country_code":"RU",
    "gn:dem":113,
    "gn:feature_class":"P",
    "gn:feature_code":"PPL",
    "gn:name":"Semenkovo",
    "gn:population":0,
    "gn:timezone":"Europe/Moscow",
    "iso:country":"RU",
    "name:rus_x_preferred":[
        "\u0421\u0435\u043c\u0435\u043d\u043a\u043e\u0432\u043e"
    ],
    "name:und_x_variant":[
        "\u0421\u0435\u043c\u0435\u043d\u043a\u043e\u0432\u043e"
    ],
    "wof:name":"Semenkovo",
    "wof:placetype":"locality"
},
  "geometry": {"coordinates":[41.08152000000001,57.72216],"type":"Point"}
}