{
  "type": "Feature",
  "properties": {
    "gn:admin1_code":"85",
    "gn:asciiname":"Trofankovo",
    "gn:country_code":"RU",
    "gn:dem":108,
    "gn:feature_class":"P",
    "gn:feature_code":"PPL",
    "gn:name":"Trofankovo",
    "gn:population":0,
    "gn:timezone":"Europe/Moscow",
    "iso:country":"RU",
    "name:rus_x_preferred":[
        "\u0422\u0440\u043e\u0444\u0430\u043d\u043a\u043e\u0432\u043e"
    ],
    "name:und_x_variant":[
        "\u0422\u0440\u043e\u0444\u0430\u043d\u043a\u043e\u0432\u043e"
    ],
    "wof:name":"Trofankovo",
    "wof:placetype":"locality"
},
  "geometry": {"coordinates":[37.3496,58.8737],"type":"Point"}
}