{
  "type": "Feature",
  "properties": {
    "gn:country":"RU",
    "gn:fcode":"PPL",
    "gn:population":3098,
    "iso:country":"RU",
    "name:eng_x_preferred":[
        "Prokovsino"
    ],
    "name:fin_x_preferred":[
        "Kuippina"
    ],
    "name:nor_x_preferred":[
        "Kipen"
    ],
    "name:rus_x_preferred":[
        "\u041a\u0438\u043f\u0435\u043d\u044c"
    ],
    "name:und_x_variant":[
        "Verkhnyaya Kipen\u2019"
    ],
    "qs:name":"Kipen\u2019",
    "qs:photos_9r":0,
    "qs:photos_sr":0,
    "qs:pop_sr":"4",
    "wof:name":"Kipen\u2019",
    "wof:placetype":"locality",
    "wof:population":3098
},
  "geometry": {"coordinates":[29.85311,59.67649],"type":"Point"}
}