{
  "type": "Feature",
  "properties": {
    "gn:admin1_code":"55",
    "gn:asciiname":"Rucheyek",
    "gn:country_code":"RU",
    "gn:dem":120,
    "gn:feature_class":"P",
    "gn:feature_code":"PPL",
    "gn:name":"Rucheyek",
    "gn:population":0,
    "gn:timezone":"Asia/Yekaterinburg",
    "iso:country":"RU",
    "name:rus_x_preferred":[
        "\u0420\u0443\u0447\u0435\u0435\u043a"
    ],
    "name:und_x_variant":[
        "\u0420\u0443\u0447\u0435\u0435\u043a"
    ],
    "wof:name":"Rucheyek",
    "wof:placetype":"locality"
},
  "geometry": {"coordinates":[52.6989,53.4971],"type":"Point"}
}