{
  "type": "Feature",
  "properties": {
    "gn:admin1_code":"60.0",
    "gn:asciiname":"Bulavkino",
    "gn:country_code":"RU",
    "gn:dem":191,
    "gn:feature_class":"P",
    "gn:feature_code":"PPL",
    "gn:name":"Bulavkino",
    "gn:population":0,
    "gn:timezone":"Europe/Moscow",
    "iso:country":"RU",
    "name:rus_x_preferred":[
        "\u0411\u0443\u043b\u0430\u0432\u043a\u0438\u043d\u043e"
    ],
    "name:und_x_variant":[
        "Bulavkina",
        "Bulavkino"
    ],
    "wof:name":"Bulavkino",
    "wof:placetype":"locality"
},
  "geometry": {"coordinates":[31.13369,55.92189000000001],"type":"Point"}
}