{
  "type": "Feature",
  "properties": {
    "gn:admin1_code":"33",
    "gn:asciiname":"Pozikovo",
    "gn:country_code":"RU",
    "gn:dem":106,
    "gn:feature_class":"P",
    "gn:feature_code":"PPL",
    "gn:name":"Pozikovo",
    "gn:population":0,
    "gn:timezone":"Europe/Kirov",
    "iso:country":"RU",
    "name:rus_x_preferred":[
        "\u041f\u043e\u0437\u0438\u043a\u043e\u0432\u043e"
    ],
    "wof:name":"Pozikovo",
    "wof:placetype":"locality"
},
  "geometry": {"coordinates":[47.11635,57.00971],"type":"Point"}
}