{
  "type": "Feature",
  "properties": {
    "gn:admin1_code":"33",
    "gn:asciiname":"Panikhiny",
    "gn:country_code":"RU",
    "gn:dem":169,
    "gn:feature_class":"P",
    "gn:feature_code":"PPL",
    "gn:name":"Panikhiny",
    "gn:population":0,
    "gn:timezone":"Europe/Kirov",
    "iso:country":"RU",
    "name:rus_x_preferred":[
        "\u041f\u0430\u043d\u0438\u0445\u0438\u043d\u044b"
    ],
    "name:und_x_variant":[
        "Panikhino",
        "Panikhiny"
    ],
    "wof:name":"Panikhiny",
    "wof:placetype":"locality"
},
  "geometry": {"coordinates":[46.82517,58.38342],"type":"Point"}
}