{
  "type": "Feature",
  "properties": {
    "gn:admin1_code":"60",
    "gn:asciiname":"Podberezkino",
    "gn:country_code":"RU",
    "gn:dem":71,
    "gn:feature_class":"P",
    "gn:feature_code":"PPL",
    "gn:name":"Podber\u00ebzkino",
    "gn:population":0,
    "gn:timezone":"Europe/Moscow",
    "iso:country":"RU",
    "name:rus_x_preferred":[
        "\u041f\u043e\u0434\u0431\u0435\u0440\u0451\u0437\u043a\u0438\u043d\u043e"
    ],
    "name:und_x_variant":[
        "Podber\u00ebzkino"
    ],
    "wof:name":"Podberezkino",
    "wof:placetype":"locality"
},
  "geometry": {"coordinates":[28.48917,57.41682],"type":"Point"}
}