{
  "type": "Feature",
  "properties": {
    "gn:admin1_code":"68",
    "gn:asciiname":"Tmenikau",
    "gn:cc2":"RU",
    "gn:country_code":"RU",
    "gn:dem":1732,
    "gn:feature_class":"P",
    "gn:feature_code":"PPL",
    "gn:name":"Tmenikau",
    "gn:population":0,
    "gn:timezone":"Europe/Moscow",
    "iso:country":"RU",
    "name:rus_x_preferred":[
        "\u0422\u043c\u0435\u043d\u0438\u043a\u0430\u0443"
    ],
    "name:und_x_variant":[
        "Temenikau",
        "Tmenikau",
        "\u0422\u043c\u0435\u043d\u0438\u043a\u0430\u0443"
    ],
    "wof:name":"Tmenikau",
    "wof:placetype":"locality"
},
  "geometry": {"coordinates":[44.49306,42.82833],"type":"Point"}
}