{
  "type": "Feature",
  "properties": {
    "gn:admin1_code":"65",
    "gn:asciiname":"Shipovka",
    "gn:country_code":"RU",
    "gn:dem":48,
    "gn:feature_class":"P",
    "gn:feature_code":"PPL",
    "gn:name":"Shipovka",
    "gn:population":0,
    "gn:timezone":"Europe/Samara",
    "iso:country":"RU",
    "name:rus_x_preferred":[
        "\u0428\u0438\u043f\u043e\u0432\u043a\u0430"
    ],
    "name:und_x_variant":[
        "\u0428\u0438\u043f\u043e\u0432\u043a\u0430"
    ],
    "wof:name":"Shipovka",
    "wof:placetype":"locality"
},
  "geometry": {"coordinates":[51.692,53.5541],"type":"Point"}
}