{
  "type": "Feature",
  "properties": {
    "gn:admin1_code":"52",
    "gn:asciiname":"Losinaya Golova",
    "gn:country_code":"RU",
    "gn:dem":72,
    "gn:feature_class":"P",
    "gn:feature_code":"PPL",
    "gn:name":"Losinaya Golova",
    "gn:population":0,
    "gn:timezone":"Europe/Moscow",
    "iso:country":"RU",
    "name:rus_x_preferred":[
        "\u041b\u043e\u0441\u0438\u043d\u0430\u044f \u0413\u043e\u043b\u043e\u0432\u0430"
    ],
    "wof:name":"Losinaya Golova",
    "wof:placetype":"locality"
},
  "geometry": {"coordinates":[31.2525,57.1274],"type":"Point"}
}