{
  "type": "Feature",
  "properties": {
    "gn:admin1_code":"86",
    "gn:asciiname":"Valentinovka",
    "gn:country_code":"RU",
    "gn:dem":134,
    "gn:feature_class":"P",
    "gn:feature_code":"PPL",
    "gn:name":"Valentinovka",
    "gn:population":0,
    "gn:timezone":"Europe/Moscow",
    "iso:country":"RU",
    "name:rus_x_preferred":[
        "\u0412\u0430\u043b\u0435\u043d\u0442\u0438\u043d\u043e\u0432\u043a\u0430"
    ],
    "wof:name":"Valentinovka",
    "wof:placetype":"locality"
},
  "geometry": {"coordinates":[39.74897,49.93538],"type":"Point"}
}