{
  "type": "Feature",
  "properties": {
    "gn:admin1_code":"90",
    "gn:asciiname":"Zhivyye",
    "gn:country_code":"RU",
    "gn:dem":171,
    "gn:feature_class":"P",
    "gn:feature_code":"PPL",
    "gn:name":"Zhivyye",
    "gn:population":0,
    "gn:timezone":"Asia/Yekaterinburg",
    "iso:country":"RU",
    "name:che_x_preferred":[
        "\u0416\u0438\u0432\u044b\u0435"
    ],
    "name:eng_x_preferred":[
        "Zhivyye"
    ],
    "name:nor_x_preferred":[
        "Zjivye"
    ],
    "name:rus_x_preferred":[
        "\u0416\u0438\u0432\u044b\u0435"
    ],
    "name:und_x_variant":[
        "Zhivy"
    ],
    "wof:name":"Zhivyye",
    "wof:placetype":"locality"
},
  "geometry": {"coordinates":[54.7751,58.7766],"type":"Point"}
}