{
  "type": "Feature",
  "properties": {
    "gn:admin1_code":"47",
    "gn:asciiname":"Dolgomost'yevo",
    "gn:country_code":"RU",
    "gn:dem":112,
    "gn:feature_class":"P",
    "gn:feature_code":"PPL",
    "gn:name":"Dolgomost\u2019yevo",
    "gn:population":0,
    "gn:timezone":"Europe/Moscow",
    "iso:country":"RU",
    "name:rus_x_preferred":[
        "\u0414\u043e\u043b\u0433\u043e\u043c\u043e\u0441\u0442\u044c\u0435\u0432\u043e"
    ],
    "name:und_x_variant":[
        "Dolgomost\u2019ye",
        "Dolgomost\u2019yevo",
        "\u0414\u043e\u043b\u0433\u043e\u043c\u043e\u0441\u0442\u044c\u0435\u0432\u043e"
    ],
    "wof:name":"Dolgomost'yevo",
    "wof:placetype":"locality"
},
  "geometry": {"coordinates":[39.34693,54.84849000000001],"type":"Point"}
}