{
  "type": "Feature",
  "properties": {
    "gn:admin1_code":"31",
    "gn:asciiname":"Izykhskiye Kopi",
    "gn:country_code":"RU",
    "gn:dem":286,
    "gn:feature_class":"P",
    "gn:feature_code":"PPL",
    "gn:name":"Izykhskiye Kopi",
    "gn:population":0,
    "gn:timezone":"Asia/Krasnoyarsk",
    "iso:country":"RU",
    "name:eng_x_preferred":[
        "Izykhskiye Kopi"
    ],
    "name:nor_x_preferred":[
        "Izykhskije-Kopi"
    ],
    "name:rus_x_preferred":[
        "\u0418\u0437\u044b\u0445\u0441\u043a\u0438\u0435-\u041a\u043e\u043f\u0438"
    ],
    "name:rus_x_variant":[
        "\u0418\u0437\u044b\u0445\u0441\u043a\u0438\u0435 \u041a\u043e\u043f\u0438"
    ],
    "name:und_x_variant":[
        "\u0418\u0437\u044b\u0445\u0441\u043a\u0438\u0435 \u041a\u043e\u043f\u0438"
    ],
    "wof:name":"Izykhskiye Kopi",
    "wof:placetype":"locality"
},
  "geometry": {"coordinates":[91.28,53.55222],"type":"Point"}
}