{
  "type": "Feature",
  "properties": {
    "gn:admin1_code":"67",
    "gn:asciiname":"Vladykino",
    "gn:country_code":"RU",
    "gn:dem":172,
    "gn:feature_class":"P",
    "gn:feature_code":"PPL",
    "gn:name":"Vladykino",
    "gn:population":0,
    "gn:timezone":"Europe/Saratov",
    "iso:country":"RU",
    "name:eng_x_preferred":[
        "Vladykino"
    ],
    "name:nor_x_preferred":[
        "Vladykino"
    ],
    "name:rus_x_preferred":[
        "\u0412\u043b\u0430\u0434\u044b\u043a\u0438\u043d\u043e"
    ],
    "name:ukr_x_preferred":[
        "\u0412\u043b\u0430\u0434\u0438\u043a\u0456\u043d\u043e"
    ],
    "wof:name":"Vladykino",
    "wof:placetype":"locality"
},
  "geometry": {"coordinates":[43.49678,52.32827],"type":"Point"}
}