{
  "type": "Feature",
  "properties": {
    "gn:admin1_code":"8",
    "gn:asciiname":"Novoaltybayevo",
    "gn:country_code":"RU",
    "gn:dem":100,
    "gn:feature_class":"P",
    "gn:feature_code":"PPL",
    "gn:name":"Novoaltybayevo",
    "gn:population":0,
    "gn:timezone":"Asia/Yekaterinburg",
    "iso:country":"RU",
    "name:bak_x_preferred":[
        "\u042f\u04a3\u044b \u0410\u043b\u0442\u044b\u0431\u0430\u0439"
    ],
    "name:che_x_preferred":[
        "\u041d\u043e\u0432\u043e\u0430\u043b\u0442\u044b\u0431\u0430\u0435\u0432\u043e"
    ],
    "name:hye_x_preferred":[
        "\u0546\u0578\u057e\u0578\u0561\u056c\u057f\u056b\u0562\u0561\u0587\u0578"
    ],
    "name:kaz_x_preferred":[
        "\u0416\u0430\u04a3\u0430 \u0430\u043b\u0442\u044b\u0431\u0430"
    ],
    "name:kir_x_preferred":[
        "\u0416\u0430\u04a3\u044b \u0430\u043b\u0442\u044b\u0431\u0430"
    ],
    "name:rus_x_preferred":[
        "\u041d\u043e\u0432\u043e\u0430\u043b\u0442\u044b\u0431\u0430\u0435\u0432\u043e"
    ],
    "name:tat_x_preferred":[
        "\u042f\u04a3\u0430 \u0410\u043b\u0442\u044b\u0431\u0430\u0439"
    ],
    "name:und_x_variant":[
        "Novoye Altybayevo",
        "Novoaltybayevo"
    ],
    "wof:name":"Novoaltybayevo",
    "wof:placetype":"locality"
},
  "geometry": {"coordinates":[55.01429,55.76944],"type":"Point"}
}