{
  "type": "Feature",
  "properties": {
    "gn:admin1_code":"53",
    "gn:asciiname":"Stanovka",
    "gn:country_code":"RU",
    "gn:dem":230,
    "gn:feature_class":"P",
    "gn:feature_code":"PPL",
    "gn:name":"Stanovka",
    "gn:population":0,
    "gn:timezone":"Asia/Novosibirsk",
    "iso:country":"RU",
    "name:rus_x_preferred":[
        "\u0421\u0442\u0430\u043d\u043e\u0432\u043a\u0430"
    ],
    "name:und_x_variant":[
        "\u0421\u0442\u0430\u043d\u043e\u0432\u043a\u0430"
    ],
    "wof:name":"Stanovka",
    "wof:placetype":"locality"
},
  "geometry": {"coordinates":[83.95,54.78333000000001],"type":"Point"}
}