{
  "type": "Feature",
  "properties": {
    "gn:admin1_code":"60",
    "gn:asciiname":"Vas'kovo",
    "gn:country_code":"RU",
    "gn:dem":197,
    "gn:feature_class":"P",
    "gn:feature_code":"PPL",
    "gn:name":"Vas\u2019kovo",
    "gn:population":0,
    "gn:timezone":"Europe/Moscow",
    "iso:country":"RU",
    "name:eng_x_preferred":[
        "Vas'kovo"
    ],
    "name:nor_x_preferred":[
        "Vaskovo"
    ],
    "name:rus_x_preferred":[
        "\u0412\u0430\u0441\u044c\u043a\u043e\u0432\u043e"
    ],
    "name:und_x_variant":[
        "Vas\u2019kova",
        "Vas\u2019kovo"
    ],
    "wof:name":"Vas'kovo",
    "wof:placetype":"locality"
},
  "geometry": {"coordinates":[31.18944,56.40256],"type":"Point"}
}