{
  "type": "Feature",
  "properties": {
    "gn:admin1_code":"23",
    "gn:asciiname":"Pugachevo",
    "gn:country_code":"RU",
    "gn:dem":159,
    "gn:feature_class":"P",
    "gn:feature_code":"PPL",
    "gn:name":"Pugach\u00ebvo",
    "gn:population":0,
    "gn:timezone":"Europe/Kaliningrad",
    "iso:country":"RU",
    "name:rus_x_preferred":[
        "\u041f\u0443\u0433\u0430\u0447\u0451\u0432\u043e"
    ],
    "name:und_x_variant":[
        "Pugach\u00ebvo"
    ],
    "wof:name":"Pugachevo",
    "wof:placetype":"locality"
},
  "geometry": {"coordinates":[22.52611,54.43417],"type":"Point"}
}