{
  "type": "Feature",
  "properties": {
    "gn:admin1_code":"05",
    "gn:asciiname":"Prigorodnyy",
    "gn:cc2":"RU",
    "gn:country_code":"RU",
    "gn:dem":346,
    "gn:feature_class":"P",
    "gn:feature_code":"PPL",
    "gn:name":"Prigorodnyy",
    "gn:population":0,
    "gn:timezone":"Asia/Yakutsk",
    "iso:country":"RU",
    "name:eng_x_preferred":[
        "Prigorodnyy"
    ],
    "name:nor_x_preferred":[
        "Prigorodnyj"
    ],
    "name:rus_x_preferred":[
        "\u041f\u0440\u0438\u0433\u043e\u0440\u043e\u0434\u043d\u044b\u0439"
    ],
    "name:und_x_variant":[
        "Prigorodnoye Khoz",
        "\u041f\u0440\u0438\u0433\u043e\u0440\u043e\u0434\u043d\u044b\u0439",
        "Prigorodnyy"
    ],
    "wof:name":"Prigorodnyy",
    "wof:placetype":"locality"
},
  "geometry": {"coordinates":[125.76667,53.38333000000001],"type":"Point"}
}