{
  "type": "Feature",
  "properties": {
    "gn:admin1_code":"59",
    "gn:asciiname":"Bussevka",
    "gn:country_code":"RU",
    "gn:dem":131,
    "gn:feature_class":"P",
    "gn:feature_code":"PPL",
    "gn:name":"Bussevka",
    "gn:population":0,
    "gn:timezone":"Asia/Vladivostok",
    "iso:country":"RU",
    "name:eng_x_preferred":[
        "Bussevka"
    ],
    "name:nor_x_preferred":[
        "Bussevka"
    ],
    "name:rus_x_preferred":[
        "\u0411\u0443\u0441\u0441\u0435\u0432\u043a\u0430"
    ],
    "name:und_x_variant":[
        "Buseyevka",
        "\u0411\u0443\u0441\u0441\u0435\u0432\u043a\u0430",
        "Bussevka"
    ],
    "wof:name":"Bussevka",
    "wof:placetype":"locality"
},
  "geometry": {"coordinates":[132.98195000000001,44.63504],"type":"Point"}
}