{
  "type": "Feature",
  "properties": {
    "gn:admin1_code":"33",
    "gn:asciiname":"Malyye Durnikhintsy",
    "gn:country_code":"RU",
    "gn:dem":160,
    "gn:feature_class":"P",
    "gn:feature_code":"PPL",
    "gn:name":"Malyye Durnikhintsy",
    "gn:population":0,
    "gn:timezone":"Europe/Kirov",
    "iso:country":"RU",
    "name:rus_x_preferred":[
        "\u041c\u0430\u043b\u044b\u0435 \u0414\u0443\u0440\u043d\u0438\u0445\u0438\u043d\u0446\u044b"
    ],
    "wof:name":"Malyye Durnikhintsy",
    "wof:placetype":"locality"
},
  "geometry": {"coordinates":[49.5411,58.4848],"type":"Point"}
}