{
  "type": "Feature",
  "properties": {
    "gn:admin1_code":"55",
    "gn:asciiname":"Soyedinennyy",
    "gn:country_code":"RU",
    "gn:dem":183,
    "gn:feature_class":"P",
    "gn:feature_code":"PPL",
    "gn:name":"Soyedin\u00ebnnyy",
    "gn:population":0,
    "gn:timezone":"Asia/Yekaterinburg",
    "iso:country":"RU",
    "name:rus_x_preferred":[
        "\u0421\u043e\u0435\u0434\u0438\u043d\u0451\u043d\u043d\u044b\u0439"
    ],
    "name:und_x_variant":[
        "Soyedin\u00ebnnyy",
        "\u0421\u043e\u0435\u0434\u0438\u043d\u0451\u043d\u043d\u044b\u0439"
    ],
    "wof:name":"Soyedinennyy",
    "wof:placetype":"locality"
},
  "geometry": {"coordinates":[54.95,52.33333],"type":"Point"}
}