{
  "type": "Feature",
  "properties": {
    "gn:admin1_code":"42",
    "gn:asciiname":"Kitkovo",
    "gn:country_code":"RU",
    "gn:dem":80,
    "gn:feature_class":"P",
    "gn:feature_code":"PPL",
    "gn:name":"Kitkovo",
    "gn:population":0,
    "gn:timezone":"Europe/Moscow",
    "iso:country":"RU",
    "name:rus_x_preferred":[
        "\u041a\u0438\u0442\u043a\u043e\u0432\u043e"
    ],
    "name:und_x_variant":[
        "\u041a\u0438\u0442\u043a\u043e\u0432\u043e"
    ],
    "wof:name":"Kitkovo",
    "wof:placetype":"locality"
},
  "geometry": {"coordinates":[28.5695,58.937],"type":"Point"}
}