{
  "type": "Feature",
  "properties": {
    "gn:admin1_code":"60",
    "gn:asciiname":"Dolgaya",
    "gn:country_code":"RU",
    "gn:dem":108,
    "gn:feature_class":"P",
    "gn:feature_code":"PPL",
    "gn:name":"Dolgaya",
    "gn:population":0,
    "gn:timezone":"Europe/Moscow",
    "iso:country":"RU",
    "name:rus_x_preferred":[
        "\u0414\u043e\u043b\u0433\u0430\u044f"
    ],
    "name:und_x_variant":[
        "\u0414\u043e\u043b\u0433\u0430\u044f"
    ],
    "wof:name":"Dolgaya",
    "wof:placetype":"locality"
},
  "geometry": {"coordinates":[30.7804,56.379],"type":"Point"}
}