{
  "type": "Feature",
  "properties": {
    "gn:country":"RU",
    "gn:fcode":"PPL",
    "gn:population":0,
    "iso:country":"RU",
    "name:fin_x_preferred":[
        "Osmola"
    ],
    "name:rus_x_preferred":[
        "\u041d\u043e\u0432\u043e\u043b\u0438\u0441\u0438\u043d\u043e"
    ],
    "qs:name":"Novolisino",
    "qs:name_adm0":"Russia",
    "qs:name_adm1":"Leningrad Oblast",
    "qs:photos_9k":1,
    "qs:photos_9r":1,
    "qs:photos_all":6,
    "qs:photos_sr":0,
    "qs:placetype":"Town",
    "qs:pop_sr":"0",
    "wof:name":"Novolisino",
    "wof:placetype":"locality",
    "wof:population":0
},
  "geometry": {"coordinates":[30.76,59.5575],"type":"Point"}
}