{
  "type": "Feature",
  "properties": {
    "gn:admin1_code":"49",
    "gn:asciiname":"Korabel'noye",
    "gn:country_code":"RU",
    "gn:dem":48,
    "gn:feature_class":"P",
    "gn:feature_code":"PPL",
    "gn:name":"Korabel\u2019noye",
    "gn:population":0,
    "gn:timezone":"Europe/Moscow",
    "iso:country":"RU",
    "name:eng_x_preferred":[
        "Korabel'noye"
    ],
    "name:nor_x_preferred":[
        "Korabelnoje"
    ],
    "name:rus_x_preferred":[
        "\u041a\u043e\u0440\u0430\u0431\u0435\u043b\u044c\u043d\u043e\u0435"
    ],
    "name:und_x_variant":[
        "Korabelnoy",
        "Korabel\u2019noye"
    ],
    "wof:name":"Korabel'noye",
    "wof:placetype":"locality"
},
  "geometry": {"coordinates":[41.27425,67.00238],"type":"Point"}
}