{
  "type": "Feature",
  "properties": {
    "gn:admin1_code":"51",
    "gn:asciiname":"Tolba",
    "gn:country_code":"RU",
    "gn:dem":138,
    "gn:feature_class":"P",
    "gn:feature_code":"PPL",
    "gn:name":"Tolba",
    "gn:population":0,
    "gn:timezone":"Europe/Moscow",
    "iso:country":"RU",
    "name:eng_x_preferred":[
        "Tolba"
    ],
    "name:nor_x_preferred":[
        "Tolba"
    ],
    "name:rus_x_preferred":[
        "\u0422\u043e\u043b\u0431\u0430"
    ],
    "wof:name":"Tolba",
    "wof:placetype":"locality"
},
  "geometry": {"coordinates":[45.29222,55.62111],"type":"Point"}
}