{
  "type": "Feature",
  "properties": {
    "gn:admin1_code":"37.0",
    "gn:asciiname":"Lyakino",
    "gn:country_code":"RU",
    "gn:dem":158,
    "gn:feature_class":"P",
    "gn:feature_code":"PPL",
    "gn:name":"Lyakino",
    "gn:population":0,
    "gn:timezone":"Europe/Moscow",
    "iso:country":"RU",
    "name:rus_x_preferred":[
        "\u041b\u044f\u043a\u0438\u043d\u043e"
    ],
    "name:und_x_variant":[
        "\u041b\u044f\u043a\u0438\u043d\u043e"
    ],
    "wof:name":"Lyakino",
    "wof:placetype":"locality"
},
  "geometry": {"coordinates":[41.5322,57.47431],"type":"Point"}
}