{
  "type": "Feature",
  "properties": {
    "gn:admin1_code":"24.0",
    "gn:asciiname":"Ulan-Malch",
    "gn:country_code":"RU",
    "gn:dem":49,
    "gn:feature_class":"P",
    "gn:feature_code":"PPL",
    "gn:name":"Ulan-Malch",
    "gn:population":0,
    "gn:timezone":"Europe/Moscow",
    "iso:country":"RU",
    "wof:name":"Ulan-Malch",
    "wof:placetype":"locality"
},
  "geometry": {"coordinates":[45.00389000000001,45.63583],"type":"Point"}
}