{
  "type": "Feature",
  "properties": {
    "gn:admin1_code":"56",
    "gn:asciiname":"Opeka",
    "gn:country_code":"RU",
    "gn:dem":215,
    "gn:feature_class":"P",
    "gn:feature_code":"PPL",
    "gn:name":"Opeka",
    "gn:population":0,
    "gn:timezone":"Europe/Moscow",
    "iso:country":"RU",
    "name:rus_x_preferred":[
        "\u041e\u043f\u0435\u043a\u0430"
    ],
    "wof:name":"Opeka",
    "wof:placetype":"locality"
},
  "geometry": {"coordinates":[35.3584,52.3955],"type":"Point"}
}