{
  "type": "Feature",
  "properties": {
    "gn:admin1_code":"23",
    "gn:asciiname":"Minskoye",
    "gn:country_code":"RU",
    "gn:dem":46,
    "gn:feature_class":"P",
    "gn:feature_code":"PPL",
    "gn:name":"Minskoye",
    "gn:population":0,
    "gn:timezone":"Europe/Kaliningrad",
    "iso:country":"RU",
    "name:rus_x_preferred":[
        "\u041c\u0438\u043d\u0441\u043a\u043e\u0435"
    ],
    "wof:name":"Minskoye",
    "wof:placetype":"locality"
},
  "geometry": {"coordinates":[20.19583,54.91139],"type":"Point"}
}