{
  "type": "Feature",
  "properties": {
    "gn:admin1_code":"62",
    "gn:asciiname":"Shirokiy",
    "gn:country_code":"RU",
    "gn:dem":171,
    "gn:feature_class":"P",
    "gn:feature_code":"PPL",
    "gn:name":"Shirokiy",
    "gn:population":0,
    "gn:timezone":"Europe/Moscow",
    "iso:country":"RU",
    "name:rus_x_preferred":[
        "\u0428\u0438\u0440\u043e\u043a\u0438\u0439"
    ],
    "name:und_x_variant":[
        "\u0428\u0438\u0440\u043e\u043a\u0438\u0439"
    ],
    "wof:name":"Shirokiy",
    "wof:placetype":"locality"
},
  "geometry": {"coordinates":[39.17188,53.87415],"type":"Point"}
}