{
  "type": "Feature",
  "properties": {
    "gn:admin1_code":"85",
    "gn:asciiname":"Toki",
    "gn:country_code":"RU",
    "gn:dem":155,
    "gn:feature_class":"P",
    "gn:feature_code":"PPL",
    "gn:name":"Toki",
    "gn:population":0,
    "gn:timezone":"Europe/Moscow",
    "iso:country":"RU",
    "name:ceb_x_preferred":[
        "Toki"
    ],
    "name:deu_x_preferred":[
        "Toki"
    ],
    "name:eus_x_preferred":[
        "Toki"
    ],
    "name:fra_x_preferred":[
        "Toki"
    ],
    "name:ita_x_preferred":[
        "Toki"
    ],
    "name:jpn_x_preferred":[
        "\u30c8\u30ad"
    ],
    "name:mlg_x_preferred":[
        "Toki"
    ],
    "name:pol_x_preferred":[
        "Toki"
    ],
    "name:rus_x_preferred":[
        "\u0422\u043e\u043a\u0438"
    ],
    "name:spa_x_preferred":[
        "Toki"
    ],
    "name:swe_x_preferred":[
        "Toki"
    ],
    "name:ukr_x_preferred":[
        "\u0422\u043e\u043a\u0456"
    ],
    "wof:name":"Toki",
    "wof:placetype":"locality"
},
  "geometry": {"coordinates":[36.4711,58.59],"type":"Point"}
}