{
  "type": "Feature",
  "properties": {
    "gn:admin1_code":"85",
    "gn:asciiname":"Toki",
    "gn:country_code":"RU",
    "gn:dem":155,
    "gn:feature_class":"P",
    "gn:feature_code":"PPL",
    "gn:name":"Toki",
    "gn:population":0,
    "gn:timezone":"Europe/Moscow",
    "iso:country":"RU",
    "name:rus_x_preferred":[
        "\u0422\u043e\u043a\u0438"
    ],
    "name:und_x_variant":[
        "\u0422\u043e\u043a\u0438"
    ],
    "wof:name":"Toki",
    "wof:placetype":"locality"
},
  "geometry": {"coordinates":[36.4711,58.59],"type":"Point"}
}