{
  "type": "Feature",
  "properties": {
    "gn:admin1_code":"62",
    "gn:asciiname":"Mishukovo",
    "gn:country_code":"RU",
    "gn:dem":123,
    "gn:feature_class":"P",
    "gn:feature_code":"PPL",
    "gn:name":"Mishukovo",
    "gn:population":0,
    "gn:timezone":"Europe/Moscow",
    "iso:country":"RU",
    "name:rus_x_preferred":[
        "\u041c\u0438\u0448\u0443\u043a\u043e\u0432\u043e"
    ],
    "name:und_x_variant":[
        "\u041c\u0438\u0448\u0443\u043a\u043e\u0432\u043e"
    ],
    "wof:name":"Mishukovo",
    "wof:placetype":"locality"
},
  "geometry": {"coordinates":[41.70797,54.97785],"type":"Point"}
}