{
  "type": "Feature",
  "properties": {
    "gn:admin1_code":"8",
    "gn:asciiname":"Nikifarovo",
    "gn:country_code":"RU",
    "gn:dem":122,
    "gn:feature_class":"P",
    "gn:feature_code":"PPL",
    "gn:name":"Nikifarovo",
    "gn:population":0,
    "gn:timezone":"Asia/Yekaterinburg",
    "iso:country":"RU",
    "name:eng_x_preferred":[
        "Nikiforovo"
    ],
    "name:nor_x_preferred":[
        "Nikifarovo"
    ],
    "name:rus_x_preferred":[
        "\u041d\u0438\u043a\u0438\u0444\u0430\u0440\u043e\u0432\u043e"
    ],
    "name:und_x_variant":[
        "Nikiforova",
        "Nikiforovo",
        "Nikifarovo"
    ],
    "wof:name":"Nikifarovo",
    "wof:placetype":"locality"
},
  "geometry": {"coordinates":[54.71666999999999,53.81667],"type":"Point"}
}