{
  "type": "Feature",
  "properties": {
    "gn:admin1_code":"8",
    "gn:asciiname":"Nikifarovo",
    "gn:country_code":"RU",
    "gn:dem":122,
    "gn:feature_class":"P",
    "gn:feature_code":"PPL",
    "gn:name":"Nikifarovo",
    "gn:population":0,
    "gn:timezone":"Asia/Yekaterinburg",
    "iso:country":"RU",
    "name:bak_x_preferred":[
        "\u041d\u0438\u043a\u0438\u0444\u0430\u0440"
    ],
    "name:che_x_preferred":[
        "\u041d\u0438\u043a\u0438\u0444\u0430\u0440\u043e\u0432\u043e"
    ],
    "name:eng_x_preferred":[
        "Nikiforovo"
    ],
    "name:hye_x_preferred":[
        "\u0546\u056b\u056f\u056b\u0586\u0561\u0580\u0578\u057e\u0578"
    ],
    "name:kat_x_preferred":[
        "\u10dc\u10d8\u10d9\u10d8\u10e4\u10d0\u10e0\u10dd\u10d5\u10dd"
    ],
    "name:kaz_x_preferred":[
        "\u041d\u0438\u043a\u0438\u0444\u0430\u0440"
    ],
    "name:kir_x_preferred":[
        "\u041d\u0438\u043a\u0438\u0444\u0430\u0440"
    ],
    "name:nor_x_preferred":[
        "Nikifarovo"
    ],
    "name:rus_x_preferred":[
        "\u041d\u0438\u043a\u0438\u0444\u0430\u0440\u043e\u0432\u043e"
    ],
    "name:tat_x_preferred":[
        "\u041d\u0438\u043a\u0438\u0444\u0430\u0440"
    ],
    "name:ukr_x_preferred":[
        "\u041d\u0456\u043a\u0456\u0444\u0430\u0440\u043e\u0432\u043e"
    ],
    "name:und_x_variant":[
        "Nikiforova"
    ],
    "wof:name":"Nikifarovo",
    "wof:placetype":"locality"
},
  "geometry": {"coordinates":[54.71666999999999,53.81667],"type":"Point"}
}