{
  "type": "Feature",
  "properties": {
    "gn:admin1_code":"41",
    "gn:asciiname":"Vtoroy Zelenyy Sad",
    "gn:country_code":"RU",
    "gn:dem":222,
    "gn:feature_class":"P",
    "gn:feature_code":"PPL",
    "gn:name":"Vtoroy Zel\u00ebnyy Sad",
    "gn:population":0,
    "gn:timezone":"Europe/Moscow",
    "iso:country":"RU",
    "name:rus_x_preferred":[
        "\u0412\u0442\u043e\u0440\u043e\u0439 \u0417\u0435\u043b\u0451\u043d\u044b\u0439 \u0421\u0430\u0434"
    ],
    "name:und_x_variant":[
        "Vtoroy Zel\u00ebnyy Sad",
        "Zel\u00ebnyy Sad Vtoroy"
    ],
    "wof:name":"Vtoroy Zelenyy Sad",
    "wof:placetype":"locality"
},
  "geometry": {"coordinates":[34.7884,51.953],"type":"Point"}
}