{
  "type": "Feature",
  "properties": {
    "gn:admin1_code":"77",
    "gn:asciiname":"Pustoshka",
    "gn:country_code":"RU",
    "gn:dem":238,
    "gn:feature_class":"P",
    "gn:feature_code":"PPL",
    "gn:name":"Pustoshka",
    "gn:population":0,
    "gn:timezone":"Europe/Moscow",
    "iso:country":"RU",
    "name:bel_x_preferred":[
        "\u041f\u0443\u0441\u0442\u043e\u0448\u043a\u0430"
    ],
    "name:rus_x_preferred":[
        "\u041f\u0443\u0441\u0442\u043e\u0448\u043a\u0430"
    ],
    "name:ukr_x_preferred":[
        "\u041f\u0443\u0441\u0442\u043e\u0448\u043a\u0430"
    ],
    "wof:name":"Pustoshka",
    "wof:placetype":"locality"
},
  "geometry": {"coordinates":[33.45861,56.17694],"type":"Point"}
}