{
  "type": "Feature",
  "properties": {
    "gn:admin1_code":"88",
    "gn:asciiname":"Kabychikha",
    "gn:country_code":"RU",
    "gn:dem":104,
    "gn:feature_class":"P",
    "gn:feature_code":"PPL",
    "gn:name":"Kabychikha",
    "gn:population":0,
    "gn:timezone":"Europe/Moscow",
    "iso:country":"RU",
    "name:rus_x_preferred":[
        "\u041a\u0430\u0431\u044b\u0447\u0438\u0445\u0430"
    ],
    "wof:name":"Kabychikha",
    "wof:placetype":"locality"
},
  "geometry": {"coordinates":[39.43591,57.5999],"type":"Point"}
}