{
  "type": "Feature",
  "properties": {
    "gn:admin1_code":"17.0",
    "gn:asciiname":"Firgil'",
    "gn:country_code":"RU",
    "gn:dem":662,
    "gn:feature_class":"P",
    "gn:feature_code":"PPL",
    "gn:name":"Firgil\u2019",
    "gn:population":0,
    "gn:timezone":"Europe/Moscow",
    "iso:country":"RU",
    "name:rus_x_preferred":[
        "\u0424\u0438\u0440\u0433\u0438\u043b\u044c"
    ],
    "name:und_x_variant":[
        "Fergil\u2019",
        "Firgil\u2019"
    ],
    "wof:name":"Firgil'",
    "wof:placetype":"locality"
},
  "geometry": {"coordinates":[48.02587,41.92507],"type":"Point"}
}