{
  "type": "Feature",
  "properties": {
    "gn:admin1_code":"34",
    "gn:asciiname":"Sokolovo",
    "gn:country_code":"RU",
    "gn:dem":35,
    "gn:feature_class":"P",
    "gn:feature_code":"PPL",
    "gn:name":"Sokolovo",
    "gn:population":0,
    "gn:timezone":"Europe/Moscow",
    "iso:country":"RU",
    "name:eng_x_preferred":[
        "Sokolovo"
    ],
    "name:nor_x_preferred":[
        "Sokolovo"
    ],
    "name:rus_x_preferred":[
        "\u0421\u043e\u043a\u043e\u043b\u043e\u0432\u043e"
    ],
    "name:und_x_variant":[
        "Sokolova",
        "\u0421\u043e\u043a\u043e\u043b\u043e\u0432\u043e",
        "Sokolovo"
    ],
    "wof:name":"Sokolovo",
    "wof:placetype":"locality"
},
  "geometry": {"coordinates":[57.01937,65.34728],"type":"Point"}
}