{
  "type": "Feature",
  "properties": {
    "gn:admin1_code":"20",
    "gn:asciiname":"Konstantinovo",
    "gn:country_code":"RU",
    "gn:dem":548,
    "gn:feature_class":"P",
    "gn:feature_code":"PPL",
    "gn:name":"Konstantinovo",
    "gn:population":0,
    "gn:timezone":"Asia/Irkutsk",
    "iso:country":"RU",
    "name:rus_x_preferred":[
        "\u041a\u043e\u043d\u0441\u0442\u0430\u043d\u0442\u0438\u043d\u043e\u0432\u043e"
    ],
    "name:und_x_variant":[
        "\u041a\u043e\u043d\u0441\u0442\u0430\u043d\u0442\u0438\u043d\u043e\u0432\u043e"
    ],
    "wof:name":"Konstantinovo",
    "wof:placetype":"locality"
},
  "geometry": {"coordinates":[104.01667,55.73333],"type":"Point"}
}