{
  "type": "Feature",
  "properties": {
    "gn:admin1_code":"72",
    "gn:asciiname":"Karavaino",
    "gn:country_code":"RU",
    "gn:dem":164,
    "gn:feature_class":"P",
    "gn:feature_code":"PPL",
    "gn:name":"Karavaino",
    "gn:population":0,
    "gn:timezone":"Europe/Moscow",
    "iso:country":"RU",
    "name:eng_x_preferred":[
        "Karavaino"
    ],
    "name:nor_x_preferred":[
        "Karavaino"
    ],
    "name:rus_x_preferred":[
        "\u041a\u0430\u0440\u0430\u0432\u0430\u0438\u043d\u043e"
    ],
    "name:und_x_variant":[
        "\u041a\u0430\u0440\u0430\u0432\u0430\u0438\u043d\u043e",
        "Karavaino"
    ],
    "wof:name":"Karavaino",
    "wof:placetype":"locality"
},
  "geometry": {"coordinates":[42.2069,52.4232],"type":"Point"}
}