{
  "type": "Feature",
  "properties": {
    "gn:admin1_code":"51",
    "gn:asciiname":"Krupin",
    "gn:country_code":"RU",
    "gn:dem":126,
    "gn:feature_class":"P",
    "gn:feature_code":"PPL",
    "gn:name":"Krupin",
    "gn:population":0,
    "gn:timezone":"Europe/Moscow",
    "iso:country":"RU",
    "name:deu_x_preferred":[
        "Krupin"
    ],
    "name:fra_x_preferred":[
        "Krupin"
    ],
    "name:pol_x_preferred":[
        "Krupin"
    ],
    "name:rus_x_preferred":[
        "\u041a\u0440\u0443\u043f\u0438\u043d"
    ],
    "name:ukr_x_preferred":[
        "\u041a\u0440\u0443\u043f\u0456\u043d"
    ],
    "wof:name":"Krupin",
    "wof:placetype":"locality"
},
  "geometry": {"coordinates":[46.3053,57.5523],"type":"Point"}
}