{
  "type": "Feature",
  "properties": {
    "gn:admin1_code":"47",
    "gn:asciiname":"Yel'digino",
    "gn:country_code":"RU",
    "gn:dem":179,
    "gn:feature_class":"P",
    "gn:feature_code":"PPL",
    "gn:name":"Yel\u2019digino",
    "gn:population":2100,
    "gn:timezone":"Europe/Moscow",
    "iso:country":"RU",
    "name:rus_x_preferred":[
        "\u0415\u043b\u044c\u0434\u0438\u0433\u0438\u043d\u043e"
    ],
    "name:und_x_variant":[
        "Yel\u2019digino",
        "Shkol\u2019nyy"
    ],
    "wof:name":"Yel'digino",
    "wof:placetype":"locality",
    "wof:population":2100
},
  "geometry": {"coordinates":[37.81667,56.11666999999999],"type":"Point"}
}