{
  "type": "Feature",
  "properties": {
    "gn:admin1_code":"43.0",
    "gn:asciiname":"Devyatoye Yanvarya",
    "gn:country_code":"RU",
    "gn:dem":172,
    "gn:feature_class":"P",
    "gn:feature_code":"PPL",
    "gn:name":"Devyatoye Yanvarya",
    "gn:population":0,
    "gn:timezone":"Europe/Moscow",
    "iso:country":"RU",
    "name:rus_x_preferred":[
        "\u0414\u0435\u0432\u044f\u0442\u043e\u0435 \u042f\u043d\u0432\u0430\u0440\u044f"
    ],
    "name:und_x_variant":[
        "\u0414\u0435\u0432\u044f\u0442\u043e\u0435 \u042f\u043d\u0432\u0430\u0440\u044f"
    ],
    "wof:name":"Devyatoye Yanvarya",
    "wof:placetype":"locality"
},
  "geometry": {"coordinates":[38.08833,51.93694],"type":"Point"}
}