{
  "type": "Feature",
  "properties": {
    "gn:admin1_code":"11.0",
    "gn:asciiname":"Talyn-Bulak",
    "gn:country_code":"RU",
    "gn:dem":745,
    "gn:feature_class":"P",
    "gn:feature_code":"PPL",
    "gn:name":"Talyn-Bulak",
    "gn:population":0,
    "gn:timezone":"Asia/Irkutsk",
    "iso:country":"RU",
    "name:rus_x_preferred":[
        "\u0422\u0430\u043b\u044b\u043d-\u0411\u0443\u043b\u0430\u043a"
    ],
    "wof:name":"Talyn-Bulak",
    "wof:placetype":"locality"
},
  "geometry": {"coordinates":[105.83969999999999,50.839],"type":"Point"}
}