{
  "type": "Feature",
  "properties": {
    "gn:admin1_code":"93",
    "gn:asciiname":"Undino-Posel'ye",
    "gn:country_code":"RU",
    "gn:dem":551,
    "gn:feature_class":"P",
    "gn:feature_code":"PPL",
    "gn:name":"Undino-Posel\u2019ye",
    "gn:population":0,
    "gn:timezone":"Asia/Chita",
    "iso:country":"RU",
    "name:eng_x_preferred":[
        "Undino-Posel'ye"
    ],
    "name:nor_x_preferred":[
        "Undino-Poselje"
    ],
    "name:rus_x_preferred":[
        "\u0423\u043d\u0434\u0438\u043d\u043e-\u041f\u043e\u0441\u0435\u043b\u044c\u0435"
    ],
    "name:und_x_variant":[
        "Udinskoye Poselye",
        "Undinskoye Posel\u2019ye",
        "Undino-Posel\u2019ye"
    ],
    "wof:name":"Undino-Posel'ye",
    "wof:placetype":"locality"
},
  "geometry": {"coordinates":[116.23988,51.42192],"type":"Point"}
}