{
  "type": "Feature",
  "properties": {
    "gn:admin1_code":"33",
    "gn:asciiname":"Laptenki",
    "gn:country_code":"RU",
    "gn:dem":112,
    "gn:feature_class":"P",
    "gn:feature_code":"PPL",
    "gn:name":"Laptenki",
    "gn:population":0,
    "gn:timezone":"Europe/Kirov",
    "iso:country":"RU",
    "name:eng_x_preferred":[
        "Laptenki"
    ],
    "name:nor_x_preferred":[
        "Laptenki"
    ],
    "name:rus_x_preferred":[
        "\u041b\u0430\u043f\u0442\u0435\u043d\u043a\u0438"
    ],
    "name:und_x_variant":[
        "\u041b\u0430\u043f\u0442\u0435\u043d\u043a\u0438",
        "Laptenki"
    ],
    "wof:name":"Laptenki",
    "wof:placetype":"locality"
},
  "geometry": {"coordinates":[47.61126,57.80484000000001],"type":"Point"}
}