{
  "type": "Feature",
  "properties": {
    "gn:country":"RU",
    "gn:fcode":"PPL",
    "gn:population":0,
    "iso:country":"RU",
    "name:azb_x_preferred":[
        "\u067e\u0631\u0698\u0648\u0627\u0644\u0633\u06a9\u0648\u06cc"
    ],
    "name:bel_x_preferred":[
        "\u041f\u0440\u0436\u044d\u0432\u0430\u043b\u044c\u0441\u043a\u0430\u0435"
    ],
    "name:ceb_x_preferred":[
        "Przheval'skoye"
    ],
    "name:che_x_preferred":[
        "\u041f\u0440\u0436\u0435\u0432\u0430\u043b\u044c\u0441\u043a\u043e\u0435"
    ],
    "name:eng_x_preferred":[
        "Przheval'skoye"
    ],
    "name:eng_x_variant":[
        "Przhevalskoye"
    ],
    "name:hye_x_preferred":[
        "\u054a\u0580\u056a\u0587\u0561\u056c\u057d\u056f\u0578\u0565"
    ],
    "name:nld_x_preferred":[
        "Przjevalskoe"
    ],
    "name:nor_x_preferred":[
        "Przjevalskoje"
    ],
    "name:pol_x_preferred":[
        "Pr\u017cewalskoje"
    ],
    "name:rus_x_preferred":[
        "\u041f\u0440\u0436\u0435\u0432\u0430\u043b\u044c\u0441\u043a\u043e\u0435"
    ],
    "name:spa_x_preferred":[
        "Przhev\u00e1lskoye"
    ],
    "name:srp_x_preferred":[
        "\u041f\u0440\u0436\u0435\u0432\u0430\u0459\u0441\u043a\u043e\u0458\u0435"
    ],
    "name:und_x_variant":[
        "Sloboda"
    ],
    "name:zho_x_preferred":[
        "\u666e\u71b1\u74e6\u5229\u65af\u79d1\u8036"
    ],
    "qs:name":"Przheval'skoye",
    "qs:name_adm0":"Russia",
    "qs:name_adm1":"Smolensk Oblast",
    "qs:photos_9k":1,
    "qs:photos_9r":1,
    "qs:photos_all":12,
    "qs:photos_sr":0,
    "qs:placetype":"Town",
    "qs:pop_sr":"0",
    "wof:name":"Przheval'skoye",
    "wof:placetype":"locality",
    "wof:population":0
},
  "geometry": {"coordinates":[31.84819,55.50874],"type":"Point"}
}