{
  "type": "Feature",
  "properties": {
    "gn:admin1_code":"72",
    "gn:asciiname":"Podlesnoye",
    "gn:country_code":"RU",
    "gn:dem":126,
    "gn:feature_class":"P",
    "gn:feature_code":"PPL",
    "gn:name":"Podlesnoye",
    "gn:population":0,
    "gn:timezone":"Europe/Moscow",
    "iso:country":"RU",
    "name:bak_x_preferred":[
        "\u041f\u043e\u0434\u043b\u0435\u0441\u043d\u044b\u0439"
    ],
    "name:che_x_preferred":[
        "\u041f\u043e\u0434\u043b\u0435\u0441\u043d\u0438"
    ],
    "name:eng_x_preferred":[
        "Podlesnoye"
    ],
    "name:hye_x_preferred":[
        "\u054a\u0578\u0564\u056c\u0565\u057d\u0576\u0578\u0565"
    ],
    "name:kaz_x_preferred":[
        "\u041f\u043e\u0434\u043b\u0435\u0441\u043d\u043e\u0435"
    ],
    "name:nor_x_preferred":[
        "Podlesnoje"
    ],
    "name:rus_x_preferred":[
        "\u041f\u043e\u0434\u043b\u0435\u0441\u043d\u043e\u0435"
    ],
    "name:tat_x_preferred":[
        "\u041f\u043e\u0434\u043b\u0435\u0441\u043d\u043e\u0435"
    ],
    "name:ukr_x_preferred":[
        "\u041f\u0456\u0434\u043b\u0456\u0441\u043d\u0435"
    ],
    "name:und_x_variant":[
        "Novyye Pupki",
        "Kazinki",
        "Malyye Pupki",
        "Podlesnoye"
    ],
    "wof:name":"Podlesnoye",
    "wof:placetype":"locality"
},
  "geometry": {"coordinates":[41.243,53.16476],"type":"Point"}
}