{
  "type": "Feature",
  "properties": {
    "gn:admin1_code":"61",
    "gn:asciiname":"Talloverov",
    "gn:country_code":"RU",
    "gn:dem":100,
    "gn:feature_class":"P",
    "gn:feature_code":"PPL",
    "gn:name":"Talloverov",
    "gn:population":0,
    "gn:timezone":"Europe/Moscow",
    "iso:country":"RU",
    "name:und_x_variant":[
        "Taloverov",
        "Talloverov"
    ],
    "wof:name":"Talloverov",
    "wof:placetype":"locality"
},
  "geometry": {"coordinates":[41.28886,49.01619],"type":"Point"}
}