{
  "type": "Feature",
  "properties": {
    "gn:admin1_code":"10",
    "gn:asciiname":"Berezina",
    "gn:country_code":"RU",
    "gn:dem":171,
    "gn:feature_class":"P",
    "gn:feature_code":"PPL",
    "gn:name":"Berezina",
    "gn:population":0,
    "gn:timezone":"Europe/Moscow",
    "iso:country":"RU",
    "name:nor_x_preferred":[
        "Berezina"
    ],
    "name:rus_x_preferred":[
        "\u0411\u0435\u0440\u0435\u0437\u0438\u043d\u0430"
    ],
    "wof:name":"Berezina",
    "wof:placetype":"locality"
},
  "geometry": {"coordinates":[32.91583,52.28333],"type":"Point"}
}