{
  "type": "Feature",
  "properties": {
    "gn:admin1_code":"86",
    "gn:asciiname":"Yasenovka",
    "gn:country_code":"RU",
    "gn:dem":117,
    "gn:feature_class":"P",
    "gn:feature_code":"PPL",
    "gn:name":"Yasenovka",
    "gn:population":0,
    "gn:timezone":"Europe/Moscow",
    "iso:country":"RU",
    "name:eng_x_preferred":[
        "Yasenovka"
    ],
    "name:nor_x_preferred":[
        "Jasenovka"
    ],
    "name:rus_x_preferred":[
        "\u042f\u0441\u0435\u043d\u043e\u0432\u043a\u0430"
    ],
    "name:und_x_variant":[
        "Yasinovka"
    ],
    "wof:name":"Yasenovka",
    "wof:placetype":"locality"
},
  "geometry": {"coordinates":[40.8082,50.5294],"type":"Point"}
}