{
  "type": "Feature",
  "properties": {
    "gn:country":"RU",
    "gn:fcode":"PPL",
    "gn:population":2022,
    "iso:country":"RU",
    "name:azb_x_preferred":[
        "\u0631\u0627\u062f\u0686\u0646\u06a9\u0648"
    ],
    "name:bel_x_preferred":[
        "\u0420\u0430\u0434\u0447\u0430\u043d\u043a\u0430"
    ],
    "name:ceb_x_preferred":[
        "Radchenko"
    ],
    "name:che_x_preferred":[
        "\u0420\u0430\u0434\u0447\u0435\u043d\u043a\u043e"
    ],
    "name:crh_x_preferred":[
        "Rad\u00e7enko"
    ],
    "name:eng_x_preferred":[
        "Radchenko"
    ],
    "name:fin_x_preferred":[
        "Radt\u0161enko"
    ],
    "name:hye_x_preferred":[
        "\u054c\u0561\u0564\u0579\u0565\u0576\u056f\u0578"
    ],
    "name:nld_x_preferred":[
        "Radchenko"
    ],
    "name:nor_x_preferred":[
        "Radtsjenko"
    ],
    "name:pol_x_preferred":[
        "Radczenko"
    ],
    "name:rus_x_preferred":[
        "\u0420\u0430\u0434\u0447\u0435\u043d\u043a\u043e"
    ],
    "name:spa_x_preferred":[
        "R\u00e1dchenko"
    ],
    "name:srp_x_preferred":[
        "\u0420\u0430\u0434\u0447\u0435\u043d\u043a\u043e"
    ],
    "name:ukr_x_preferred":[
        "\u0420\u0430\u0434\u0447\u0435\u043d\u043a\u043e"
    ],
    "name:und_x_variant":[
        "Tos"
    ],
    "qs:name":"Radchenko",
    "qs:name_adm0":"Russia",
    "qs:name_adm1":"Tver Oblast",
    "qs:photos_9k":1,
    "qs:photos_9r":1,
    "qs:photos_all":13,
    "qs:photos_sr":0,
    "qs:placetype":"Town",
    "qs:pop_sr":"4",
    "wd:wordcount":91,
    "wof:name":"Radchenko",
    "wof:placetype":"locality",
    "wof:population":2022
},
  "geometry": {"coordinates":[36.37178,56.68027],"type":"Point"}
}