{
  "type": "Feature",
  "properties": {
    "gn:country":"RU",
    "gn:fcode":"PPL",
    "gn:population":2022,
    "iso:country":"RU",
    "name:che_x_preferred":[
        "\u0420\u0430\u0434\u0447\u0435\u043d\u043a\u043e"
    ],
    "name:eng_x_preferred":[
        "Radchenko"
    ],
    "name:fin_x_preferred":[
        "Radt\u0161enko"
    ],
    "name:nor_x_preferred":[
        "Radtsjenko"
    ],
    "name:pol_x_preferred":[
        "Radczenko"
    ],
    "name:rus_x_preferred":[
        "\u0420\u0430\u0434\u0447\u0435\u043d\u043a\u043e"
    ],
    "name:srp_x_preferred":[
        "\u0420\u0430\u0434\u0447\u0435\u043d\u043a\u043e"
    ],
    "name:und_x_variant":[
        "Tos"
    ],
    "qs:name":"Radchenko",
    "qs:name_adm0":"Russia",
    "qs:name_adm1":"Tver Oblast",
    "qs:photos_9k":1,
    "qs:photos_9r":1,
    "qs:photos_all":13,
    "qs:photos_sr":0,
    "qs:placetype":"Town",
    "qs:pop_sr":"4",
    "wd:wordcount":91,
    "wof:name":"Radchenko",
    "wof:placetype":"locality",
    "wof:population":2022
},
  "geometry": {"coordinates":[36.37178,56.68027],"type":"Point"}
}