{
  "type": "Feature",
  "properties": {
    "gn:admin1_code":"42.0",
    "gn:asciiname":"Fedotovskaya",
    "gn:country_code":"RU",
    "gn:dem":194,
    "gn:feature_class":"P",
    "gn:feature_code":"PPL",
    "gn:name":"Fedotovskaya",
    "gn:population":0,
    "gn:timezone":"Europe/Moscow",
    "iso:country":"RU",
    "name:rus_x_preferred":[
        "\u0424\u0435\u0434\u043e\u0442\u043e\u0432\u0441\u043a\u0430\u044f"
    ],
    "name:und_x_variant":[
        "\u0424\u0435\u0434\u043e\u0442\u043e\u0432\u0441\u043a\u0430\u044f"
    ],
    "wof:name":"Fedotovskaya",
    "wof:placetype":"locality"
},
  "geometry": {"coordinates":[35.07623,60.41887],"type":"Point"}
}