{
  "type": "Feature",
  "properties": {
    "gn:admin1_code":"9.0",
    "gn:asciiname":"Setnoye",
    "gn:country_code":"RU",
    "gn:dem":128,
    "gn:feature_class":"P",
    "gn:feature_code":"PPL",
    "gn:name":"Setnoye",
    "gn:population":0,
    "gn:timezone":"Europe/Moscow",
    "iso:country":"RU",
    "name:rus_x_preferred":[
        "\u0421\u0435\u0442\u043d\u043e\u0435"
    ],
    "wof:name":"Setnoye",
    "wof:placetype":"locality"
},
  "geometry": {"coordinates":[37.16861,50.75212],"type":"Point"}
}