{
  "type": "Feature",
  "properties": {
    "gn:country":"RU",
    "gn:fcode":"PPL",
    "gn:pop":4000,
    "iso:country":"RU",
    "name:nor_x_preferred":[
        "Novyj Kostek"
    ],
    "name:rus_x_preferred":[
        "\u041d\u043e\u0432\u044b\u0439 \u041a\u043e\u0441\u0442\u0435\u043a"
    ],
    "name:unk_x_variant":[
        "\u041d\u043e\u0432\u044b\u0439 \u041a\u043e\u0441\u0442\u0435\u043a"
    ],
    "qs:name":"Noviy Kostek",
    "qs:name_adm0":"Russia",
    "qs:name_adm1":"Dagestan Republic",
    "qs:photos_9r":0,
    "qs:photos_sr":0,
    "qs:placetype":"Town",
    "qs:pop_sr":"4",
    "wof:name":"Noviy Kostek",
    "wof:placetype":"locality",
    "wof:population":4000
},
  "geometry": {"coordinates":[46.82466,43.3353],"type":"Point"}
}