{
  "type": "Feature",
  "properties": {
    "gn:admin1_code":"80.0",
    "gn:asciiname":"Yegorovtsy",
    "gn:country_code":"RU",
    "gn:dem":142,
    "gn:feature_class":"P",
    "gn:feature_code":"PPL",
    "gn:name":"Yegorovtsy",
    "gn:population":0,
    "gn:timezone":"Europe/Samara",
    "iso:country":"RU",
    "name:rus_x_preferred":[
        "\u0415\u0433\u043e\u0440\u043e\u0432\u0446\u044b"
    ],
    "wof:name":"Yegorovtsy",
    "wof:placetype":"locality"
},
  "geometry": {"coordinates":[52.2101,57.4206],"type":"Point"}
}