{
  "type": "Feature",
  "properties": {
    "gn:admin1_code":"60",
    "gn:asciiname":"Kablishche",
    "gn:country_code":"RU",
    "gn:dem":38,
    "gn:feature_class":"P",
    "gn:feature_code":"PPL",
    "gn:name":"Kablishche",
    "gn:population":0,
    "gn:timezone":"Europe/Moscow",
    "iso:country":"RU",
    "name:rus_x_preferred":[
        "\u041a\u0430\u0431\u043b\u0438\u0449\u0435"
    ],
    "name:und_x_variant":[
        "\u041a\u0430\u0431\u043b\u0438\u0449\u0435"
    ],
    "wof:name":"Kablishche",
    "wof:placetype":"locality"
},
  "geometry": {"coordinates":[28.0721,58.1341],"type":"Point"}
}