{
  "type": "Feature",
  "properties": {
    "gn:admin1_code":"25",
    "gn:asciiname":"Krasnyy Kholm",
    "gn:country_code":"RU",
    "gn:dem":240,
    "gn:feature_class":"P",
    "gn:feature_code":"PPL",
    "gn:name":"Krasnyy Kholm",
    "gn:population":0,
    "gn:timezone":"Europe/Moscow",
    "iso:country":"RU",
    "name:rus_x_preferred":[
        "\u041a\u0440\u0430\u0441\u043d\u044b\u0439 \u0425\u043e\u043b\u043c"
    ],
    "name:und_x_variant":[
        "Krasny Kholm",
        "Krasnyy Kholm",
        "\u041a\u0440\u0430\u0441\u043d\u044b\u0439 \u0425\u043e\u043b\u043c"
    ],
    "wof:name":"Krasnyy Kholm",
    "wof:placetype":"locality"
},
  "geometry": {"coordinates":[34.55417,54.32545],"type":"Point"}
}