{
  "type": "Feature",
  "properties": {
    "gn:admin1_code":"33",
    "gn:asciiname":"Kazakovo",
    "gn:country_code":"RU",
    "gn:dem":155,
    "gn:feature_class":"P",
    "gn:feature_code":"PPL",
    "gn:name":"Kazakovo",
    "gn:population":0,
    "gn:timezone":"Europe/Kirov",
    "iso:country":"RU",
    "name:rus_x_preferred":[
        "\u041a\u0430\u0437\u0430\u043a\u043e\u0432\u043e"
    ],
    "name:und_x_variant":[
        "Kozakovo",
        "Kazakovo",
        "\u041a\u0430\u0437\u0430\u043a\u043e\u0432\u043e"
    ],
    "wof:name":"Kazakovo",
    "wof:placetype":"locality"
},
  "geometry": {"coordinates":[48.6492,57.2321],"type":"Point"}
}