{
  "type": "Feature",
  "properties": {
    "gn:admin1_code":"16",
    "gn:asciiname":"Khyrkasy",
    "gn:country_code":"RU",
    "gn:dem":144,
    "gn:feature_class":"P",
    "gn:feature_code":"PPL",
    "gn:name":"Khyrkasy",
    "gn:population":0,
    "gn:timezone":"Europe/Moscow",
    "iso:country":"RU",
    "name:rus_x_preferred":[
        "\u0425\u044b\u0440\u043a\u0430\u0441\u044b"
    ],
    "name:und_x_variant":[
        "\u0425\u044b\u0440\u043a\u0430\u0441\u044b"
    ],
    "wof:name":"Khyrkasy",
    "wof:placetype":"locality"
},
  "geometry": {"coordinates":[46.816,56.1329],"type":"Point"}
}