{
  "type": "Feature",
  "properties": {
    "gn:admin1_code":"25.0",
    "gn:asciiname":"Belikovo",
    "gn:country_code":"RU",
    "gn:dem":199,
    "gn:feature_class":"P",
    "gn:feature_code":"PPL",
    "gn:name":"Belikovo",
    "gn:population":0,
    "gn:timezone":"Europe/Moscow",
    "iso:country":"RU",
    "name:nor_x_preferred":[
        "Belikovo"
    ],
    "name:rus_x_preferred":[
        "\u0411\u0435\u043b\u0438\u043a\u043e\u0432\u043e"
    ],
    "name:und_x_variant":[
        "Belikova",
        "Belikovo"
    ],
    "wof:name":"Belikovo",
    "wof:placetype":"locality"
},
  "geometry": {"coordinates":[36.76104,54.74533],"type":"Point"}
}