{
  "type": "Feature",
  "properties": {
    "gn:admin1_code":"8",
    "gn:asciiname":"Starokhazino",
    "gn:country_code":"RU",
    "gn:dem":95,
    "gn:feature_class":"P",
    "gn:feature_code":"PPL",
    "gn:name":"Starokhazino",
    "gn:population":0,
    "gn:timezone":"Asia/Yekaterinburg",
    "iso:country":"RU",
    "name:rus_x_preferred":[
        "\u0421\u0442\u0430\u0440\u043e\u0445\u0430\u0437\u0438\u043d\u043e"
    ],
    "name:und_x_variant":[
        "Staroye Khazino",
        "Starokhazino",
        "\u0421\u0442\u0430\u0440\u043e\u0445\u0430\u0437\u0438\u043d\u043e"
    ],
    "wof:name":"Starokhazino",
    "wof:placetype":"locality"
},
  "geometry": {"coordinates":[54.3248,55.63623000000001],"type":"Point"}
}