{
  "type": "Feature",
  "properties": {
    "gn:admin1_code":"60",
    "gn:asciiname":"Krinev'ye",
    "gn:country_code":"RU",
    "gn:dem":57,
    "gn:feature_class":"P",
    "gn:feature_code":"PPL",
    "gn:name":"Krinev\u2019ye",
    "gn:population":0,
    "gn:timezone":"Europe/Moscow",
    "iso:country":"RU",
    "name:rus_x_preferred":[
        "\u041a\u0440\u0438\u043d\u0435\u0432\u044c\u0435"
    ],
    "name:und_x_variant":[
        "Krinev\u2019ye",
        "\u041a\u0440\u0438\u043d\u0435\u0432\u044c\u0435"
    ],
    "wof:name":"Krinev'ye",
    "wof:placetype":"locality"
},
  "geometry": {"coordinates":[28.0552,58.9279],"type":"Point"}
}