{
  "type": "Feature",
  "properties": {
    "gn:admin1_code":"67",
    "gn:asciiname":"Urusovka",
    "gn:country_code":"RU",
    "gn:dem":174,
    "gn:feature_class":"P",
    "gn:feature_code":"PPL",
    "gn:name":"Urusovka",
    "gn:population":0,
    "gn:timezone":"Europe/Saratov",
    "iso:country":"RU",
    "name:rus_x_preferred":[
        "\u0423\u0440\u0443\u0441\u043e\u0432\u043a\u0430"
    ],
    "wof:name":"Urusovka",
    "wof:placetype":"locality"
},
  "geometry": {"coordinates":[44.18307,51.39635],"type":"Point"}
}