{
  "type": "Feature",
  "properties": {
    "gn:admin1_code":"73",
    "gn:asciiname":"Khasanovka",
    "gn:country_code":"RU",
    "gn:dem":174,
    "gn:feature_class":"P",
    "gn:feature_code":"PPL",
    "gn:name":"Khasanovka",
    "gn:population":0,
    "gn:timezone":"Europe/Moscow",
    "iso:country":"RU",
    "name:rus_x_preferred":[
        "\u0425\u0430\u0441\u0430\u043d\u043e\u0432\u043a\u0430"
    ],
    "wof:name":"Khasanovka",
    "wof:placetype":"locality"
},
  "geometry": {"coordinates":[50.8951,56.0268],"type":"Point"}
}