{
  "type": "Feature",
  "properties": {
    "gn:admin1_code":"8",
    "gn:asciiname":"Yekaterinoslavka",
    "gn:country_code":"RU",
    "gn:dem":125,
    "gn:feature_class":"P",
    "gn:feature_code":"PPL",
    "gn:name":"Yekaterinoslavka",
    "gn:population":0,
    "gn:timezone":"Asia/Yekaterinburg",
    "iso:country":"RU",
    "name:rus_x_preferred":[
        "\u0415\u043a\u0430\u0442\u0435\u0440\u0438\u043d\u043e\u0441\u043b\u0430\u0432\u043a\u0430"
    ],
    "name:und_x_variant":[
        "\u0415\u043a\u0430\u0442\u0435\u0440\u0438\u043d\u043e\u0441\u043b\u0430\u0432\u043a\u0430"
    ],
    "wof:name":"Yekaterinoslavka",
    "wof:placetype":"locality"
},
  "geometry": {"coordinates":[55.1347,54.4247],"type":"Point"}
}