{
  "type": "Feature",
  "properties": {
    "gn:admin1_code":"23",
    "gn:asciiname":"Malinniki",
    "gn:country_code":"RU",
    "gn:dem":11,
    "gn:feature_class":"P",
    "gn:feature_code":"PPL",
    "gn:name":"Malinniki",
    "gn:population":0,
    "gn:timezone":"Europe/Kaliningrad",
    "iso:country":"RU",
    "name:azb_x_preferred":[
        "\u0645\u0627\u0644\u06cc\u0646\u0646\u0642\u06a9\u06cc"
    ],
    "name:ceb_x_preferred":[
        "Malinniki"
    ],
    "name:fas_x_preferred":[
        "\u0645\u0627\u0644\u06cc\u0646\u0646\u06af\u06a9\u06cc"
    ],
    "name:lit_x_preferred":[
        "Malinikai"
    ],
    "name:nld_x_preferred":[
        "Malinniki"
    ],
    "name:pol_x_preferred":[
        "Malinniki"
    ],
    "name:rus_x_preferred":[
        "\u041c\u0430\u043b\u0438\u043d\u043d\u0438\u043a\u0438"
    ],
    "name:ukr_x_preferred":[
        "\u041c\u0430\u043b\u0456\u043d\u043d\u0438\u043a\u0438"
    ],
    "name:und_x_variant":[
        "\u041c\u0430\u043b\u0438\u043d\u043d\u0438\u043a\u0438"
    ],
    "wof:name":"Malinniki",
    "wof:placetype":"locality"
},
  "geometry": {"coordinates":[20.74558,54.71975],"type":"Point"}
}