{
  "type": "Feature",
  "properties": {
    "gn:admin1_code":"6",
    "gn:asciiname":"Shestakovskaya",
    "gn:country_code":"RU",
    "gn:dem":70,
    "gn:feature_class":"P",
    "gn:feature_code":"PPL",
    "gn:name":"Shestakovskaya",
    "gn:population":0,
    "gn:timezone":"Europe/Moscow",
    "iso:country":"RU",
    "name:rus_x_preferred":[
        "\u0428\u0435\u0441\u0442\u0430\u043a\u043e\u0432\u0441\u043a\u0430\u044f"
    ],
    "wof:name":"Shestakovskaya",
    "wof:placetype":"locality"
},
  "geometry": {"coordinates":[46.52744000000001,61.62728000000001],"type":"Point"}
}