{
  "type": "Feature",
  "properties": {
    "gn:admin1_code":"8",
    "gn:asciiname":"Novomunasipovo",
    "gn:country_code":"RU",
    "gn:dem":333,
    "gn:feature_class":"P",
    "gn:feature_code":"PPL",
    "gn:name":"Novomunasipovo",
    "gn:population":0,
    "gn:timezone":"Asia/Yekaterinburg",
    "iso:country":"RU",
    "name:rus_x_preferred":[
        "\u041d\u043e\u0432\u043e\u043c\u0443\u043d\u0430\u0441\u0438\u043f\u043e\u0432\u043e"
    ],
    "name:und_x_variant":[
        "Novomunasypovo",
        "Novomunasipovo"
    ],
    "wof:name":"Novomunasipovo",
    "wof:placetype":"locality"
},
  "geometry": {"coordinates":[57.5452,53.2354],"type":"Point"}
}