{
  "type": "Feature",
  "properties": {
    "gn:admin1_code":"8",
    "gn:asciiname":"Novomunasipovo",
    "gn:country_code":"RU",
    "gn:dem":333,
    "gn:feature_class":"P",
    "gn:feature_code":"PPL",
    "gn:name":"Novomunasipovo",
    "gn:population":0,
    "gn:timezone":"Asia/Yekaterinburg",
    "iso:country":"RU",
    "name:bak_x_preferred":[
        "\u042f\u04a3\u044b \u041c\u043e\u043d\u0430\u0441\u0438\u043f"
    ],
    "name:che_x_preferred":[
        "\u041d\u043e\u0432\u043e\u043c\u0443\u043d\u0430\u0441\u0438\u043f\u043e\u0432\u043e"
    ],
    "name:hye_x_preferred":[
        "\u0546\u0578\u057e\u0578\u0574\u0578\u0582\u0576\u0561\u057d\u056b\u057a\u0578\u057e\u0578"
    ],
    "name:kat_x_preferred":[
        "\u10dc\u10dd\u10d5\u10dd\u10db\u10e3\u10dc\u10d0\u10e1\u10d8\u10de\u10dd\u10d5\u10dd"
    ],
    "name:kaz_x_preferred":[
        "\u0416\u0430\u04a3\u0430 \u043c\u0443\u043d\u0430\u0441\u0438\u043f"
    ],
    "name:kir_x_preferred":[
        "\u0416\u0430\u04a3\u044b \u043c\u0443\u043d\u0430\u0441\u0438\u043f"
    ],
    "name:rus_x_preferred":[
        "\u041d\u043e\u0432\u043e\u043c\u0443\u043d\u0430\u0441\u0438\u043f\u043e\u0432\u043e"
    ],
    "name:tat_x_preferred":[
        "\u042f\u04a3\u0430 \u041c\u043e\u043d\u0430\u0441\u044b\u0439\u043f"
    ],
    "name:ukr_x_preferred":[
        "\u041d\u043e\u0432\u043e\u043c\u0443\u043d\u0430\u0441\u0456\u043f\u043e\u0432\u043e"
    ],
    "name:und_x_variant":[
        "Novomunasypovo",
        "Novomunasipovo"
    ],
    "wof:name":"Novomunasipovo",
    "wof:placetype":"locality"
},
  "geometry": {"coordinates":[57.5452,53.2354],"type":"Point"}
}