{
  "type": "Feature",
  "properties": {
    "gn:admin1_code":"42.0",
    "gn:asciiname":"Ganino",
    "gn:cc2":"RU",
    "gn:country_code":"RU",
    "gn:dem":71,
    "gn:feature_class":"P",
    "gn:feature_code":"PPL",
    "gn:name":"Ganino",
    "gn:population":0,
    "gn:timezone":"Europe/Moscow",
    "iso:country":"RU",
    "name:rus_x_preferred":[
        "\u0413\u0430\u043d\u0438\u043d\u043e"
    ],
    "name:und_x_variant":[
        "Ganina",
        "Ganino",
        "\u0413\u0430\u043d\u0438\u043d\u043e"
    ],
    "wof:name":"Ganino",
    "wof:placetype":"locality"
},
  "geometry": {"coordinates":[35.41667,60.95],"type":"Point"}
}