{
  "type": "Feature",
  "properties": {
    "gn:admin1_code":"20.0",
    "gn:asciiname":"Baygan",
    "gn:country_code":"RU",
    "gn:dem":391,
    "gn:feature_class":"P",
    "gn:feature_code":"PPL",
    "gn:name":"Baygan",
    "gn:population":0,
    "gn:timezone":"Asia/Irkutsk",
    "iso:country":"RU",
    "name:rus_x_preferred":[
        "\u0411\u0430\u0439\u0433\u0430\u043d"
    ],
    "wof:name":"Baygan",
    "wof:placetype":"locality"
},
  "geometry": {"coordinates":[103.413,53.5866],"type":"Point"}
}