{
  "type": "Feature",
  "properties": {
    "gn:admin1_code":"85.0",
    "gn:asciiname":"Koton'yevo",
    "gn:country_code":"RU",
    "gn:dem":164,
    "gn:feature_class":"P",
    "gn:feature_code":"PPL",
    "gn:name":"Koton\u2019yevo",
    "gn:population":0,
    "gn:timezone":"Europe/Moscow",
    "iso:country":"RU",
    "name:rus_x_preferred":[
        "\u041a\u043e\u0442\u043e\u043d\u044c\u0435\u0432\u043e"
    ],
    "name:und_x_variant":[
        "Koton\u2019yevo"
    ],
    "wof:name":"Koton'yevo",
    "wof:placetype":"locality"
},
  "geometry": {"coordinates":[36.195,60.1123],"type":"Point"}
}