{
  "type": "Feature",
  "properties": {
    "gn:admin1_code":"25.0",
    "gn:asciiname":"Chiplyayevo",
    "gn:country_code":"RU",
    "gn:dem":238,
    "gn:feature_class":"P",
    "gn:feature_code":"PPL",
    "gn:name":"Chiplyayevo",
    "gn:population":0,
    "gn:timezone":"Europe/Moscow",
    "iso:country":"RU",
    "name:rus_x_preferred":[
        "\u0427\u0438\u043f\u043b\u044f\u0435\u0432\u043e"
    ],
    "name:und_x_variant":[
        "\u0427\u0438\u043f\u043b\u044f\u0435\u0432\u043e"
    ],
    "wof:name":"Chiplyayevo",
    "wof:placetype":"locality"
},
  "geometry": {"coordinates":[34.19398,54.39164],"type":"Point"}
}