{
  "type": "Feature",
  "properties": {
    "gn:admin1_code":"10",
    "gn:asciiname":"Zelenyy Kut",
    "gn:country_code":"RU",
    "gn:dem":125,
    "gn:feature_class":"P",
    "gn:feature_code":"PPL",
    "gn:name":"Zel\u00ebnyy Kut",
    "gn:population":0,
    "gn:timezone":"Europe/Moscow",
    "iso:country":"RU",
    "name:rus_x_preferred":[
        "\u0417\u0435\u043b\u00eb\u043d\u044b\u0439 \u041a\u0443\u0442"
    ],
    "name:und_x_variant":[
        "Zel\u00ebnyy Kut"
    ],
    "wof:name":"Zelenyy Kut",
    "wof:placetype":"locality"
},
  "geometry": {"coordinates":[31.9213,52.1674],"type":"Point"}
}