{
  "type": "Feature",
  "properties": {
    "gn:admin1_code":"8",
    "gn:asciiname":"Kuterem",
    "gn:country_code":"RU",
    "gn:dem":132,
    "gn:feature_class":"P",
    "gn:feature_code":"PPL",
    "gn:name":"Kuterem",
    "gn:population":0,
    "gn:timezone":"Asia/Yekaterinburg",
    "iso:country":"RU",
    "name:eng_x_preferred":[
        "Kuterem"
    ],
    "name:nor_x_preferred":[
        "Kuterem"
    ],
    "name:rus_x_preferred":[
        "\u041a\u0443\u0442\u0435\u0440\u0435\u043c"
    ],
    "name:und_x_variant":[
        "Kutereli"
    ],
    "wof:name":"Kuterem",
    "wof:placetype":"locality"
},
  "geometry": {"coordinates":[54.52436,55.99681999999999],"type":"Point"}
}