{
  "type": "Feature",
  "properties": {
    "gn:admin1_code":"85",
    "gn:asciiname":"Fryazino",
    "gn:country_code":"RU",
    "gn:dem":148,
    "gn:feature_class":"P",
    "gn:feature_code":"PPL",
    "gn:name":"Fryazino",
    "gn:population":0,
    "gn:timezone":"Europe/Moscow",
    "iso:country":"RU",
    "name:ara_x_preferred":[
        "\u0641\u0631\u064a\u0627\u0632\u064a\u0646\u0648"
    ],
    "name:azb_x_preferred":[
        "\u0641\u0631\u06cc\u0627\u0632\u06cc\u0646\u0648"
    ],
    "name:aze_x_preferred":[
        "Fryazino"
    ],
    "name:bak_x_preferred":[
        "\u0424\u0440\u044f\u0437\u0438\u043d\u043e"
    ],
    "name:bel_x_preferred":[
        "\u0424\u0440\u0430\u0437\u0456\u043d\u0430"
    ],
    "name:bul_x_preferred":[
        "\u0424\u0440\u044f\u0437\u0438\u043d\u043e"
    ],
    "name:cat_x_preferred":[
        "Fri\u00e0zino"
    ],
    "name:ceb_x_preferred":[
        "Fryazino"
    ],
    "name:ces_x_preferred":[
        "Frjazino"
    ],
    "name:chv_x_preferred":[
        "\u0424\u0440\u044f\u0437\u0438\u043d\u043e"
    ],
    "name:deu_x_preferred":[
        "Frjasino"
    ],
    "name:epo_x_preferred":[
        "Frjazino"
    ],
    "name:est_x_preferred":[
        "Frjazino"
    ],
    "name:fas_x_preferred":[
        "\u0641\u0631\u06cc\u0627\u0632\u06cc\u0646\u0648"
    ],
    "name:fin_x_preferred":[
        "Frjazino"
    ],
    "name:fra_x_preferred":[
        "Friazino"
    ],
    "name:hsb_x_preferred":[
        "Frjazino"
    ],
    "name:ita_x_preferred":[
        "Frjazino"
    ],
    "name:jpn_x_preferred":[
        "\u30d5\u30ea\u30e3\u30b8\u30ce"
    ],
    "name:kor_x_preferred":[
        "\ud504\ub7b4\uc9c0\ub178"
    ],
    "name:nld_x_preferred":[
        "Frjazino"
    ],
    "name:nno_x_preferred":[
        "Frjazino"
    ],
    "name:nor_x_preferred":[
        "Frjazino"
    ],
    "name:pnb_x_preferred":[
        "\u0641\u0631\u06cc\u0627\u0632\u06cc\u0646\u0648"
    ],
    "name:pol_x_preferred":[
        "Friazino"
    ],
    "name:por_x_preferred":[
        "Friazino"
    ],
    "name:ron_x_preferred":[
        "Freazino"
    ],
    "name:rus_x_preferred":[
        "\u0424\u0440\u044f\u0437\u0438\u043d\u043e"
    ],
    "name:spa_x_preferred":[
        "Fri\u00e1zino"
    ],
    "name:srp_x_preferred":[
        "\u0424\u0440\u0458\u0430\u0437\u0438\u043d\u043e"
    ],
    "name:tat_x_preferred":[
        "\u0424\u0440\u044f\u0437\u0438\u043d\u043e"
    ],
    "name:tgl_x_preferred":[
        "Fryazino"
    ],
    "name:tur_x_preferred":[
        "Fryazino"
    ],
    "name:ukr_x_preferred":[
        "\u0424\u0440\u044f\u0437\u0456\u043d\u043e"
    ],
    "name:vie_x_preferred":[
        "Fryazino"
    ],
    "name:war_x_preferred":[
        "Fryazino"
    ],
    "name:xal_x_preferred":[
        "\u0424\u0440\u044f\u0437\u0438\u043d\u043e \u0431\u0430\u043b\u04bb\u0441\u043d"
    ],
    "name:zho_x_preferred":[
        "\u5f17\u91cc\u4e9e\u6fdf\u8afe"
    ],
    "wof:name":"Fryazino",
    "wof:placetype":"locality"
},
  "geometry": {"coordinates":[35.26371,58.97366],"type":"Point"}
}