{
  "type": "Feature",
  "properties": {
    "gn:admin1_code":"61",
    "gn:asciiname":"Kargal'skaya",
    "gn:country_code":"RU",
    "gn:dem":17,
    "gn:feature_class":"P",
    "gn:feature_code":"PPL",
    "gn:name":"Kargal\u2019skaya",
    "gn:population":0,
    "gn:timezone":"Europe/Moscow",
    "iso:country":"RU",
    "name:rus_x_preferred":[
        "\u041a\u0430\u0440\u0433\u0430\u043b\u044c\u0441\u043a\u0430\u044f"
    ],
    "name:und_x_variant":[
        "Karagal\u2019skaya",
        "Kargal\u2019skaya"
    ],
    "wof:name":"Kargal'skaya",
    "wof:placetype":"locality"
},
  "geometry": {"coordinates":[41.92857,47.52077],"type":"Point"}
}