{
  "type": "Feature",
  "properties": {
    "gn:admin1_code":"21.0",
    "gn:asciiname":"Krokhino Novoye",
    "gn:country_code":"RU",
    "gn:dem":112,
    "gn:feature_class":"P",
    "gn:feature_code":"PPL",
    "gn:name":"Krokhino Novoye",
    "gn:population":0,
    "gn:timezone":"Europe/Moscow",
    "iso:country":"RU",
    "name:und_x_variant":[
        "Krokhino",
        "Krokhino Novoye"
    ],
    "wof:name":"Krokhino Novoye",
    "wof:placetype":"locality"
},
  "geometry": {"coordinates":[41.64894,56.94667],"type":"Point"}
}