{
  "type": "Feature",
  "properties": {
    "gn:admin1_code":"78",
    "gn:asciiname":"Ingalinskoye",
    "gn:country_code":"RU",
    "gn:dem":64,
    "gn:feature_class":"P",
    "gn:feature_code":"PPL",
    "gn:name":"Ingalinskoye",
    "gn:population":0,
    "gn:timezone":"Asia/Yekaterinburg",
    "iso:country":"RU",
    "name:eng_x_preferred":[
        "Ingalinskoye"
    ],
    "name:nor_x_preferred":[
        "Ingalinskoje"
    ],
    "name:rus_x_preferred":[
        "\u0418\u043d\u0433\u0430\u043b\u0438\u043d\u0441\u043a\u043e\u0435"
    ],
    "name:und_x_variant":[
        "Ingalinskiye"
    ],
    "wof:name":"Ingalinskoye",
    "wof:placetype":"locality"
},
  "geometry": {"coordinates":[65.94769000000001,56.42443000000001],"type":"Point"}
}