{
  "type": "Feature",
  "properties": {
    "gn:admin1_code":"25",
    "gn:asciiname":"Babanovka",
    "gn:country_code":"RU",
    "gn:dem":184,
    "gn:feature_class":"P",
    "gn:feature_code":"PPL",
    "gn:name":"Babanovka",
    "gn:population":0,
    "gn:timezone":"Europe/Moscow",
    "iso:country":"RU",
    "name:nor_x_preferred":[
        "Babanovka"
    ],
    "name:rus_x_preferred":[
        "\u0411\u0430\u0431\u0430\u043d\u043e\u0432\u043a\u0430"
    ],
    "wof:name":"Babanovka",
    "wof:placetype":"locality"
},
  "geometry": {"coordinates":[34.47447,53.96373000000001],"type":"Point"}
}