{
  "type": "Feature",
  "properties": {
    "gn:admin1_code":"77",
    "gn:asciiname":"Yerogneyevka",
    "gn:country_code":"RU",
    "gn:dem":145,
    "gn:feature_class":"P",
    "gn:feature_code":"PPL",
    "gn:name":"Yerogneyevka",
    "gn:population":0,
    "gn:timezone":"Europe/Moscow",
    "iso:country":"RU",
    "name:rus_x_preferred":[
        "\u0415\u0440\u043e\u0433\u043d\u0435\u0435\u0432\u043a\u0430"
    ],
    "wof:name":"Yerogneyevka",
    "wof:placetype":"locality"
},
  "geometry": {"coordinates":[36.8697,57.4628],"type":"Point"}
}