{
  "type": "Feature",
  "properties": {
    "gn:admin1_code":"30",
    "gn:asciiname":"Sivakchan",
    "gn:country_code":"RU",
    "gn:dem":352,
    "gn:feature_class":"P",
    "gn:feature_code":"PPL",
    "gn:name":"Sivakchan",
    "gn:population":0,
    "gn:timezone":"Asia/Vladivostok",
    "iso:country":"RU",
    "name:rus_x_preferred":[
        "\u0421\u0438\u0432\u0430\u043a\u0447\u0430\u043d"
    ],
    "wof:name":"Sivakchan",
    "wof:placetype":"locality"
},
  "geometry": {"coordinates":[136.84299999999999,55.94324],"type":"Point"}
}