{
  "type": "Feature",
  "properties": {
    "gn:admin1_code":"29",
    "gn:asciiname":"Solomatovo",
    "gn:country_code":"RU",
    "gn:dem":112,
    "gn:feature_class":"P",
    "gn:feature_code":"PPL",
    "gn:name":"Solomatovo",
    "gn:population":0,
    "gn:timezone":"Asia/Novokuznetsk",
    "iso:country":"RU",
    "name:eng_x_preferred":[
        "Solomatovo"
    ],
    "name:nor_x_preferred":[
        "Salomatovo"
    ],
    "name:rus_x_preferred":[
        "\u0421\u0430\u043b\u043e\u043c\u0430\u0442\u043e\u0432\u043e"
    ],
    "name:rus_x_variant":[
        "\u0421\u043e\u043b\u043e\u043c\u0430\u0442\u043e\u0432\u043e"
    ],
    "name:und_x_variant":[
        "Salomatovo",
        "Salomatova",
        "Solomatovo",
        "\u0421\u043e\u043b\u043e\u043c\u0430\u0442\u043e\u0432\u043e"
    ],
    "wof:name":"Solomatovo",
    "wof:placetype":"locality"
},
  "geometry": {"coordinates":[85.02,55.9291],"type":"Point"}
}