{
  "type": "Feature",
  "properties": {
    "gn:admin1_code":"42",
    "gn:asciiname":"Smerdovitsy",
    "gn:country_code":"RU",
    "gn:dem":125,
    "gn:feature_class":"P",
    "gn:feature_code":"PPL",
    "gn:name":"Smerdovitsy",
    "gn:population":0,
    "gn:timezone":"Europe/Moscow",
    "iso:country":"RU",
    "name:nor_x_preferred":[
        "Smerdovitsy"
    ],
    "name:rus_x_preferred":[
        "\u0421\u043c\u0435\u0440\u0434\u043e\u0432\u0438\u0446\u044b"
    ],
    "wof:name":"Smerdovitsy",
    "wof:placetype":"locality"
},
  "geometry": {"coordinates":[29.1971,59.40316],"type":"Point"}
}