{
  "type": "Feature",
  "properties": {
    "gn:admin1_code":"90.0",
    "gn:asciiname":"Srednyaya Golovnikha",
    "gn:country_code":"RU",
    "gn:dem":119,
    "gn:feature_class":"P",
    "gn:feature_code":"PPL",
    "gn:name":"Srednyaya Golovnikha",
    "gn:population":0,
    "gn:timezone":"Asia/Yekaterinburg",
    "iso:country":"RU",
    "name:rus_x_preferred":[
        "\u0421\u0440\u0435\u0434\u043d\u044f\u044f \u0413\u043e\u043b\u043e\u0432\u043d\u0438\u0445\u0430"
    ],
    "wof:name":"Srednyaya Golovnikha",
    "wof:placetype":"locality"
},
  "geometry": {"coordinates":[54.89149000000001,57.21515],"type":"Point"}
}