{
  "type": "Feature",
  "properties": {
    "gn:admin1_code":"67",
    "gn:asciiname":"Iznair",
    "gn:country_code":"RU",
    "gn:dem":134,
    "gn:feature_class":"P",
    "gn:feature_code":"PPL",
    "gn:name":"Iznair",
    "gn:population":0,
    "gn:timezone":"Europe/Saratov",
    "iso:country":"RU",
    "name:rus_x_preferred":[
        "\u0418\u0437\u043d\u0430\u0438\u0440"
    ],
    "wof:name":"Iznair",
    "wof:placetype":"locality"
},
  "geometry": {"coordinates":[43.46454,52.34588],"type":"Point"}
}