{
  "type": "Feature",
  "properties": {
    "gn:admin1_code":"88",
    "gn:asciiname":"Voskresenskoye",
    "gn:country_code":"RU",
    "gn:dem":137,
    "gn:feature_class":"P",
    "gn:feature_code":"PPL",
    "gn:name":"Voskresenskoye",
    "gn:population":0,
    "gn:timezone":"Europe/Moscow",
    "iso:country":"RU",
    "name:rus_x_preferred":[
        "\u0412\u043e\u0441\u043a\u0440\u0435\u0441\u0435\u043d\u0441\u043a\u043e\u0435"
    ],
    "name:und_x_variant":[
        "\u0412\u043e\u0441\u043a\u0440\u0435\u0441\u0435\u043d\u0441\u043a\u043e\u0435"
    ],
    "wof:name":"Voskresenskoye",
    "wof:placetype":"locality"
},
  "geometry": {"coordinates":[37.9233,57.7499],"type":"Point"}
}