{
  "type": "Feature",
  "properties": {
    "gn:admin1_code":"69",
    "gn:asciiname":"Mishino",
    "gn:country_code":"RU",
    "gn:dem":219,
    "gn:feature_class":"P",
    "gn:feature_code":"PPL",
    "gn:name":"Mishino",
    "gn:population":0,
    "gn:timezone":"Europe/Moscow",
    "iso:country":"RU",
    "name:rus_x_preferred":[
        "\u041c\u0438\u0448\u0438\u043d\u043e"
    ],
    "name:und_x_variant":[
        "Mishina",
        "Mishino",
        "\u041c\u0438\u0448\u0438\u043d\u043e"
    ],
    "wof:name":"Mishino",
    "wof:placetype":"locality"
},
  "geometry": {"coordinates":[35.04972,55.35778000000001],"type":"Point"}
}