{
  "type": "Feature",
  "properties": {
    "gn:admin1_code":"83",
    "gn:asciiname":"Staroye Kubayevo",
    "gn:country_code":"RU",
    "gn:dem":152,
    "gn:feature_class":"P",
    "gn:feature_code":"PPL",
    "gn:name":"Staroye Kubayevo",
    "gn:population":0,
    "gn:timezone":"Europe/Moscow",
    "iso:country":"RU",
    "name:rus_x_preferred":[
        "\u0421\u0442\u0430\u0440\u043e\u0435 \u041a\u0443\u0431\u0430\u0435\u0432\u043e"
    ],
    "name:und_x_variant":[
        "Starokubayevo"
    ],
    "wof:name":"Staroye Kubayevo",
    "wof:placetype":"locality"
},
  "geometry": {"coordinates":[41.2248,55.8984],"type":"Point"}
}