{
  "type": "Feature",
  "properties": {
    "gn:admin1_code":"80",
    "gn:asciiname":"Mushkovay",
    "gn:country_code":"RU",
    "gn:dem":169,
    "gn:feature_class":"P",
    "gn:feature_code":"PPL",
    "gn:name":"Mushkovay",
    "gn:population":0,
    "gn:timezone":"Europe/Samara",
    "iso:country":"RU",
    "name:eng_x_preferred":[
        "Mushkovay"
    ],
    "name:nor_x_preferred":[
        "Musjkovaj"
    ],
    "name:rus_x_preferred":[
        "\u041c\u0443\u0448\u043a\u043e\u0432\u0430\u0439"
    ],
    "name:und_x_variant":[
        "\u041c\u0443\u0448\u043a\u043e\u0432\u0430\u0439",
        "Mushkovay"
    ],
    "wof:name":"Mushkovay",
    "wof:placetype":"locality"
},
  "geometry": {"coordinates":[52.52882,57.06079],"type":"Point"}
}