{
  "type": "Feature",
  "properties": {
    "gn:admin1_code":"8",
    "gn:asciiname":"Klimentovka",
    "gn:country_code":"RU",
    "gn:dem":185,
    "gn:feature_class":"P",
    "gn:feature_code":"PPL",
    "gn:name":"Klimentovka",
    "gn:population":0,
    "gn:timezone":"Asia/Yekaterinburg",
    "iso:country":"RU",
    "name:bak_x_preferred":[
        "\u041a\u043b\u0438\u043c\u0435\u043d\u0442\u043e\u0432\u043a\u0430"
    ],
    "name:che_x_preferred":[
        "\u041a\u043b\u0438\u043c\u0435\u043d\u0442\u043e\u0432\u043a\u0430"
    ],
    "name:hye_x_preferred":[
        "\u053f\u056c\u056b\u0574\u0565\u0576\u057f\u0578\u057e\u056f\u0561"
    ],
    "name:kaz_x_preferred":[
        "\u041a\u043b\u0438\u043c\u0435\u043d\u0442\u043e\u0432\u043a\u0430"
    ],
    "name:kir_x_preferred":[
        "\u041a\u043b\u0438\u043c\u0435\u043d\u0442\u043e\u0432\u043a\u0430"
    ],
    "name:rus_x_preferred":[
        "\u041a\u043b\u0438\u043c\u0435\u043d\u0442\u043e\u0432\u043a\u0430"
    ],
    "name:tat_x_preferred":[
        "\u041a\u043b\u0438\u043c\u0435\u043d\u0442\u043e\u0432\u043a\u0430"
    ],
    "name:und_x_variant":[
        "\u041a\u043b\u0438\u043c\u0435\u043d\u0442\u043e\u0432\u043a\u0430"
    ],
    "wof:name":"Klimentovka",
    "wof:placetype":"locality"
},
  "geometry": {"coordinates":[54.7641,54.857],"type":"Point"}
}