{
  "type": "Feature",
  "properties": {
    "gn:admin1_code":"77",
    "gn:asciiname":"Prokof'yevo",
    "gn:country_code":"RU",
    "gn:dem":251,
    "gn:feature_class":"P",
    "gn:feature_code":"PPL",
    "gn:name":"Prokof\u2019yevo",
    "gn:population":0,
    "gn:timezone":"Europe/Moscow",
    "iso:country":"RU",
    "name:rus_x_preferred":[
        "\u041f\u0440\u043e\u043a\u043e\u0444\u044c\u0435\u0432\u043e"
    ],
    "name:und_x_variant":[
        "Prokof\u2019yevo"
    ],
    "wof:name":"Prokof'yevo",
    "wof:placetype":"locality"
},
  "geometry": {"coordinates":[34.46667,57.15],"type":"Point"}
}