{
  "type": "Feature",
  "properties": {
    "gn:admin1_code":"54",
    "gn:asciiname":"Aul-Baba",
    "gn:country_code":"RU",
    "gn:dem":100,
    "gn:feature_class":"P",
    "gn:feature_code":"PPL",
    "gn:name":"Aul-Baba",
    "gn:population":0,
    "gn:timezone":"Asia/Omsk",
    "iso:country":"RU",
    "name:nor_x_preferred":[
        "Aul-Baba"
    ],
    "name:rus_x_preferred":[
        "\u0410\u0443\u043b-\u0411\u0430\u0431\u0430"
    ],
    "wof:name":"Aul-Baba",
    "wof:placetype":"locality"
},
  "geometry": {"coordinates":[73.71666999999999,55.91667],"type":"Point"}
}