{
  "type": "Feature",
  "properties": {
    "gn:admin1_code":"71",
    "gn:asciiname":"Pushkarevo Pervoye",
    "gn:country_code":"RU",
    "gn:dem":64,
    "gn:feature_class":"P",
    "gn:feature_code":"PPL",
    "gn:name":"Pushkar\u00ebvo Pervoye",
    "gn:population":0,
    "gn:timezone":"Asia/Yekaterinburg",
    "iso:country":"RU",
    "name:eng_x_preferred":[
        "Pushkar\u00ebvo Pervoye"
    ],
    "name:nor_x_preferred":[
        "Pusjkarevo 1-je"
    ],
    "name:rus_x_preferred":[
        "\u041f\u0443\u0448\u043a\u0430\u0440\u0435\u0432\u043e 1-\u0435"
    ],
    "name:rus_x_variant":[
        "\u041f\u0443\u0448\u043a\u0430\u0440\u0451\u0432\u043e \u041f\u0435\u0440\u0432\u043e\u0435"
    ],
    "name:und_x_variant":[
        "Pushkar\u00ebva",
        "Pushkar\u00ebvo",
        "Pushkar\u00ebvo Pervoye",
        "\u041f\u0443\u0448\u043a\u0430\u0440\u0451\u0432\u043e \u041f\u0435\u0440\u0432\u043e\u0435"
    ],
    "wof:name":"Pushkarevo Pervoye",
    "wof:placetype":"locality"
},
  "geometry": {"coordinates":[64.02346,57.77773000000001],"type":"Point"}
}