{
  "type": "Feature",
  "properties": {
    "gn:admin1_code":"33.0",
    "gn:asciiname":"Tepki",
    "gn:country_code":"RU",
    "gn:dem":121,
    "gn:feature_class":"P",
    "gn:feature_code":"PPL",
    "gn:name":"T\u00ebpki",
    "gn:population":0,
    "gn:timezone":"Europe/Kirov",
    "iso:country":"RU",
    "name:rus_x_preferred":[
        "\u0422\u0451\u043f\u043a\u0438"
    ],
    "name:und_x_variant":[
        "T\u00ebpki"
    ],
    "wof:name":"Tepki",
    "wof:placetype":"locality"
},
  "geometry": {"coordinates":[48.25717,58.38454],"type":"Point"}
}