{
  "type": "Feature",
  "properties": {
    "gn:admin1_code":"78",
    "gn:asciiname":"Semenovo",
    "gn:country_code":"RU",
    "gn:dem":80,
    "gn:feature_class":"P",
    "gn:feature_code":"PPL",
    "gn:name":"Sem\u00ebnovo",
    "gn:population":0,
    "gn:timezone":"Asia/Yekaterinburg",
    "iso:country":"RU",
    "name:eng_x_preferred":[
        "Sem\u00ebnovo"
    ],
    "name:nor_x_preferred":[
        "Semenovo"
    ],
    "name:rus_x_preferred":[
        "\u0421\u0435\u043c\u0435\u043d\u043e\u0432\u043e"
    ],
    "name:rus_x_variant":[
        "\u0421\u0435\u043c\u0451\u043d\u043e\u0432\u043e"
    ],
    "name:und_x_variant":[
        "Semenova",
        "Sem\u00ebnovo",
        "\u0421\u0435\u043c\u0451\u043d\u043e\u0432\u043e"
    ],
    "wof:name":"Semenovo",
    "wof:placetype":"locality"
},
  "geometry": {"coordinates":[66.69934000000001,56.51473000000001],"type":"Point"}
}