{
  "type": "Feature",
  "properties": {
    "gn:admin1_code":"33.0",
    "gn:asciiname":"Bragi",
    "gn:country_code":"RU",
    "gn:dem":123,
    "gn:feature_class":"P",
    "gn:feature_code":"PPL",
    "gn:name":"Bragi",
    "gn:population":0,
    "gn:timezone":"Europe/Kirov",
    "iso:country":"RU",
    "name:rus_x_preferred":[
        "\u0411\u0440\u0430\u0433\u0438"
    ],
    "wof:name":"Bragi",
    "wof:placetype":"locality"
},
  "geometry": {"coordinates":[48.48588,57.7214],"type":"Point"}
}