{
  "type": "Feature",
  "properties": {
    "gn:admin1_code":"33.0",
    "gn:asciiname":"Bragi",
    "gn:country_code":"RU",
    "gn:dem":123,
    "gn:feature_class":"P",
    "gn:feature_code":"PPL",
    "gn:name":"Bragi",
    "gn:population":0,
    "gn:timezone":"Europe/Kirov",
    "iso:country":"RU",
    "name:als_x_preferred":[
        "Bragi"
    ],
    "name:ara_x_preferred":[
        "\u0628\u0631\u0627\u063a\u064a"
    ],
    "name:bel_x_preferred":[
        "\u0411\u0440\u0430\u0433\u0456"
    ],
    "name:bos_x_preferred":[
        "Bragi"
    ],
    "name:bre_x_preferred":[
        "Bragi"
    ],
    "name:bul_x_preferred":[
        "\u0411\u0440\u0430\u0433\u0438"
    ],
    "name:cat_x_preferred":[
        "Bragi"
    ],
    "name:ces_x_preferred":[
        "Bragi"
    ],
    "name:dan_x_preferred":[
        "Brage"
    ],
    "name:deu_x_preferred":[
        "Bragi"
    ],
    "name:ell_x_preferred":[
        "\u039c\u03c0\u03c1\u03ac\u03b3\u03ba\u03b9"
    ],
    "name:epo_x_preferred":[
        "Bragi"
    ],
    "name:eus_x_preferred":[
        "Bragi"
    ],
    "name:fas_x_preferred":[
        "\u0628\u0631\u0627\u06af\u06cc"
    ],
    "name:fin_x_preferred":[
        "Bragi"
    ],
    "name:fra_x_preferred":[
        "Bragi"
    ],
    "name:glg_x_preferred":[
        "Bragi"
    ],
    "name:heb_x_preferred":[
        "\u05d1\u05e8\u05d2\u05d9"
    ],
    "name:hrv_x_preferred":[
        "Bragi"
    ],
    "name:hun_x_preferred":[
        "Bragi"
    ],
    "name:isl_x_preferred":[
        "Bragi"
    ],
    "name:ita_x_preferred":[
        "Bragi"
    ],
    "name:jpn_x_preferred":[
        "\u30d6\u30e9\u30ae"
    ],
    "name:kat_x_preferred":[
        "\u10d1\u10e0\u10d0\u10d2\u10d8"
    ],
    "name:kor_x_preferred":[
        "\ube0c\ub77c\uae30"
    ],
    "name:lav_x_preferred":[
        "Br\u0101gi"
    ],
    "name:lit_x_preferred":[
        "Bragis"
    ],
    "name:nld_x_preferred":[
        "Bragi"
    ],
    "name:nno_x_preferred":[
        "Brage"
    ],
    "name:nor_x_preferred":[
        "Brage"
    ],
    "name:pol_x_preferred":[
        "Bragi"
    ],
    "name:por_x_preferred":[
        "Bragi"
    ],
    "name:ron_x_preferred":[
        "Bragi"
    ],
    "name:rus_x_preferred":[
        "\u0411\u0440\u0430\u0433\u0438"
    ],
    "name:sco_x_preferred":[
        "Bragi"
    ],
    "name:spa_x_preferred":[
        "Bragi"
    ],
    "name:srp_x_preferred":[
        "\u0411\u0440\u0430\u0433\u0438"
    ],
    "name:swe_x_preferred":[
        "Brage"
    ],
    "name:tur_x_preferred":[
        "Bragi"
    ],
    "name:ukr_x_preferred":[
        "\u0411\u0440\u0430\u0433\u0456"
    ],
    "name:zho_x_preferred":[
        "\u5e03\u62c9\u57fa"
    ],
    "wof:name":"Bragi",
    "wof:placetype":"locality"
},
  "geometry": {"coordinates":[48.48588,57.7214],"type":"Point"}
}