{
  "type": "Feature",
  "properties": {
    "gn:admin1_code":"1",
    "gn:asciiname":"Zarevo",
    "gn:cc2":"RU",
    "gn:country_code":"RU",
    "gn:dem":83,
    "gn:feature_class":"P",
    "gn:feature_code":"PPL",
    "gn:name":"Zarevo",
    "gn:population":0,
    "gn:timezone":"Europe/Moscow",
    "iso:country":"RU",
    "name:und_x_variant":[
        "Novyy Rudenkov",
        "Novo-Rudenkov",
        "Novo-Rudenko",
        "Zarevo"
    ],
    "wof:name":"Zarevo",
    "wof:placetype":"locality"
},
  "geometry": {"coordinates":[40.075,45.00694],"type":"Point"}
}