{
  "type": "Feature",
  "properties": {
    "gn:admin1_code":"52",
    "gn:asciiname":"Konotoptsy",
    "gn:country_code":"RU",
    "gn:dem":98,
    "gn:feature_class":"P",
    "gn:feature_code":"PPL",
    "gn:name":"Konotoptsy",
    "gn:population":0,
    "gn:timezone":"Europe/Moscow",
    "iso:country":"RU",
    "name:rus_x_preferred":[
        "\u041a\u043e\u043d\u043e\u0442\u043e\u043f\u0446\u044b"
    ],
    "wof:name":"Konotoptsy",
    "wof:placetype":"locality"
},
  "geometry": {"coordinates":[30.6832,57.8203],"type":"Point"}
}