{
  "type": "Feature",
  "properties": {
    "gn:country":"RU",
    "gn:fcode":"PPL",
    "gn:pop":500,
    "iso:country":"RU",
    "name:eng_x_preferred":[
        "Bezengi"
    ],
    "name:nor_x_preferred":[
        "Bezengi"
    ],
    "name:rus_x_preferred":[
        "\u0411\u0435\u0437\u0435\u043d\u0433\u0438"
    ],
    "name:unk_x_variant":[
        "Bezingi"
    ],
    "qs:name":"Bezengi",
    "qs:photos_9r":0,
    "qs:photos_sr":0,
    "qs:pop_sr":"2",
    "wof:name":"Bezengi",
    "wof:placetype":"locality",
    "wof:population":500
},
  "geometry": {"coordinates":[43.2876,43.21712],"type":"Point"}
}