{
  "type": "Feature",
  "properties": {
    "gn:admin1_code":"33.0",
    "gn:asciiname":"Telitsyno",
    "gn:country_code":"RU",
    "gn:dem":142,
    "gn:feature_class":"P",
    "gn:feature_code":"PPL",
    "gn:name":"Telitsyno",
    "gn:population":0,
    "gn:timezone":"Europe/Kirov",
    "iso:country":"RU",
    "name:rus_x_preferred":[
        "\u0422\u0435\u043b\u0438\u0446\u044b\u043d\u043e"
    ],
    "wof:name":"Telitsyno",
    "wof:placetype":"locality"
},
  "geometry": {"coordinates":[48.71333,57.27944],"type":"Point"}
}