{
  "type": "Feature",
  "properties": {
    "gn:admin1_code":"56",
    "gn:asciiname":"Shatilova",
    "gn:country_code":"RU",
    "gn:dem":235,
    "gn:feature_class":"P",
    "gn:feature_code":"PPL",
    "gn:name":"Shatilova",
    "gn:population":0,
    "gn:timezone":"Europe/Moscow",
    "iso:country":"RU",
    "name:rus_x_preferred":[
        "\u0428\u0430\u0442\u0438\u043b\u043e\u0432\u0430"
    ],
    "wof:name":"Shatilova",
    "wof:placetype":"locality"
},
  "geometry": {"coordinates":[37.20918,52.71888000000001],"type":"Point"}
}