{
  "type": "Feature",
  "properties": {
    "gn:admin1_code":"28",
    "gn:asciiname":"Ruokoyarvi",
    "gn:country_code":"RU",
    "gn:dem":33,
    "gn:feature_class":"P",
    "gn:feature_code":"PPL",
    "gn:name":"Ruokoyarvi",
    "gn:population":0,
    "gn:timezone":"Europe/Moscow",
    "iso:country":"RU",
    "name:fin_x_preferred":[
        "Ruokoj\u00e4rvi"
    ],
    "name:rus_x_preferred":[
        "\u0420\u0443\u043e\u043a\u043e\u044f\u0440\u0432\u0438"
    ],
    "wof:name":"Ruokoyarvi",
    "wof:placetype":"locality"
},
  "geometry": {"coordinates":[31.3876,61.7312],"type":"Point"}
}