{
  "type": "Feature",
  "properties": {
    "gn:admin1_code":"76",
    "gn:asciiname":"Yasenok-Murav'yevka",
    "gn:country_code":"RU",
    "gn:dem":203,
    "gn:feature_class":"P",
    "gn:feature_code":"PPL",
    "gn:name":"Yasenok-Murav\u2019y\u00ebvka",
    "gn:population":0,
    "gn:timezone":"Europe/Moscow",
    "iso:country":"RU",
    "name:rus_x_preferred":[
        "\u042f\u0441\u0435\u043d\u043e\u043a-\u041c\u0443\u0440\u0430\u0432\u044c\u0451\u0432\u043a\u0430"
    ],
    "name:und_x_variant":[
        "Yasenok-Murav\u2019y\u00ebvka",
        "Yasenok Muravlyanka"
    ],
    "wof:name":"Yasenok-Murav'yevka",
    "wof:placetype":"locality"
},
  "geometry": {"coordinates":[38.36424,54.1891],"type":"Point"}
}