{
  "type": "Feature",
  "properties": {
    "gn:admin1_code":"90",
    "gn:asciiname":"Samova",
    "gn:country_code":"RU",
    "gn:dem":191,
    "gn:feature_class":"P",
    "gn:feature_code":"PPL",
    "gn:name":"Samova",
    "gn:population":0,
    "gn:timezone":"Asia/Yekaterinburg",
    "iso:country":"RU",
    "name:rus_x_preferred":[
        "\u0421\u0430\u043c\u043e\u0432\u0430"
    ],
    "name:und_x_variant":[
        "\u0421\u0430\u043c\u043e\u0432\u0430"
    ],
    "wof:name":"Samova",
    "wof:placetype":"locality"
},
  "geometry": {"coordinates":[54.95,58.48333],"type":"Point"}
}