{
  "type": "Feature",
  "properties": {
    "gn:admin1_code":"85",
    "gn:asciiname":"Velyushevo",
    "gn:country_code":"RU",
    "gn:dem":165,
    "gn:feature_class":"P",
    "gn:feature_code":"PPL",
    "gn:name":"Velyushevo",
    "gn:population":0,
    "gn:timezone":"Europe/Moscow",
    "iso:country":"RU",
    "name:rus_x_preferred":[
        "\u0412\u0435\u043b\u044e\u0448\u0435\u0432\u043e"
    ],
    "name:und_x_variant":[
        "\u0412\u0435\u043b\u044e\u0448\u0435\u0432\u043e"
    ],
    "wof:name":"Velyushevo",
    "wof:placetype":"locality"
},
  "geometry": {"coordinates":[39.01213,59.02696],"type":"Point"}
}