{
  "type": "Feature",
  "properties": {
    "gn:admin1_code":"85",
    "gn:asciiname":"Podvoloch'ye",
    "gn:country_code":"RU",
    "gn:dem":117,
    "gn:feature_class":"P",
    "gn:feature_code":"PPL",
    "gn:name":"Podvoloch\u2019ye",
    "gn:population":0,
    "gn:timezone":"Europe/Moscow",
    "iso:country":"RU",
    "name:rus_x_preferred":[
        "\u041f\u043e\u0434\u0432\u043e\u043b\u043e\u0447\u044c\u0435"
    ],
    "name:und_x_variant":[
        "Podvoloch\u2019ye",
        "\u041f\u043e\u0434\u0432\u043e\u043b\u043e\u0447\u044c\u0435"
    ],
    "wof:name":"Podvoloch'ye",
    "wof:placetype":"locality"
},
  "geometry": {"coordinates":[46.58625,60.64955],"type":"Point"}
}