{
  "type": "Feature",
  "properties": {
    "gn:admin1_code":"52.0",
    "gn:asciiname":"Chuvasheva Gora",
    "gn:country_code":"RU",
    "gn:dem":180,
    "gn:feature_class":"P",
    "gn:feature_code":"PPL",
    "gn:name":"Chuvasheva Gora",
    "gn:population":0,
    "gn:timezone":"Europe/Moscow",
    "iso:country":"RU",
    "name:eng_x_preferred":[
        "Chuvasheva Gora"
    ],
    "name:nor_x_preferred":[
        "Tsjuvasjeva Gora"
    ],
    "name:rus_x_preferred":[
        "\u0427\u0443\u0432\u0430\u0448\u0435\u0432\u0430 \u0413\u043e\u0440\u0430"
    ],
    "wof:name":"Chuvasheva Gora",
    "wof:placetype":"locality"
},
  "geometry": {"coordinates":[34.95,58.35],"type":"Point"}
}