{
  "type": "Feature",
  "properties": {
    "gn:admin1_code":"40",
    "gn:asciiname":"Kondinskoye",
    "gn:country_code":"RU",
    "gn:dem":68,
    "gn:feature_class":"P",
    "gn:feature_code":"PPL",
    "gn:name":"Kondinskoye",
    "gn:population":0,
    "gn:timezone":"Asia/Yekaterinburg",
    "iso:country":"RU",
    "name:eng_x_preferred":[
        "Kondinskoye"
    ],
    "name:nor_x_preferred":[
        "Kondinskoje"
    ],
    "name:rus_x_preferred":[
        "\u041a\u043e\u043d\u0434\u0438\u043d\u0441\u043a\u043e\u0435"
    ],
    "name:und_x_variant":[
        "\u041a\u043e\u043d\u0434\u0438\u043d\u0441\u043a\u043e\u0435",
        "Kondinskoye"
    ],
    "wof:name":"Kondinskoye",
    "wof:placetype":"locality"
},
  "geometry": {"coordinates":[64.4254,56.0943],"type":"Point"}
}