{
  "type": "Feature",
  "properties": {
    "gn:admin1_code":"69",
    "gn:asciiname":"Maleyevo",
    "gn:country_code":"RU",
    "gn:dem":245,
    "gn:feature_class":"P",
    "gn:feature_code":"PPL",
    "gn:name":"Maleyevo",
    "gn:population":0,
    "gn:timezone":"Europe/Moscow",
    "iso:country":"RU",
    "name:rus_x_preferred":[
        "\u041c\u0430\u043b\u0435\u0435\u0432\u043e"
    ],
    "wof:name":"Maleyevo",
    "wof:placetype":"locality"
},
  "geometry": {"coordinates":[33.75806,55.69416999999999],"type":"Point"}
}