{
  "type": "Feature",
  "properties": {
    "gn:admin1_code":"4",
    "gn:asciiname":"Mishikha",
    "gn:country_code":"RU",
    "gn:dem":225,
    "gn:feature_class":"P",
    "gn:feature_code":"PPL",
    "gn:name":"Mishikha",
    "gn:population":0,
    "gn:timezone":"Asia/Barnaul",
    "iso:country":"RU",
    "name:eng_x_preferred":[
        "Mishikha"
    ],
    "name:nor_x_preferred":[
        "Misjikha"
    ],
    "name:rus_x_preferred":[
        "\u041c\u0438\u0448\u0438\u0445\u0430"
    ],
    "wof:name":"Mishikha",
    "wof:placetype":"locality"
},
  "geometry": {"coordinates":[85.55410000000001,53.7415],"type":"Point"}
}