{
  "type": "Feature",
  "properties": {
    "gn:admin1_code":"28",
    "gn:asciiname":"Kivisalmi",
    "gn:country_code":"RU",
    "gn:dem":152,
    "gn:feature_class":"P",
    "gn:feature_code":"PPL",
    "gn:name":"Kivisalmi",
    "gn:population":0,
    "gn:timezone":"Europe/Moscow",
    "iso:country":"RU",
    "name:rus_x_preferred":[
        "\u041a\u0438\u0432\u0438\u0441\u0430\u043b\u043c\u0438"
    ],
    "name:und_x_variant":[
        "\u041a\u0438\u0432\u0438\u0441\u0430\u043b\u043c\u0438"
    ],
    "wof:name":"Kivisalmi",
    "wof:placetype":"locality"
},
  "geometry": {"coordinates":[31.36974,62.54526],"type":"Point"}
}