{
  "type": "Feature",
  "properties": {
    "gn:admin1_code":"83",
    "gn:asciiname":"Sosnitsy",
    "gn:country_code":"RU",
    "gn:dem":78,
    "gn:feature_class":"P",
    "gn:feature_code":"PPL",
    "gn:name":"Sosnitsy",
    "gn:population":0,
    "gn:timezone":"Europe/Moscow",
    "iso:country":"RU",
    "name:rus_x_preferred":[
        "\u0421\u043e\u0441\u043d\u0438\u0446\u044b"
    ],
    "name:und_x_variant":[
        "Sosnitsa",
        "Sosnitsy",
        "\u0421\u043e\u0441\u043d\u0438\u0446\u044b"
    ],
    "wof:name":"Sosnitsy",
    "wof:placetype":"locality"
},
  "geometry": {"coordinates":[42.2652,55.7974],"type":"Point"}
}