{
  "type": "Feature",
  "properties": {
    "gn:admin1_code":"60",
    "gn:asciiname":"Pol'shino",
    "gn:country_code":"RU",
    "gn:dem":154,
    "gn:feature_class":"P",
    "gn:feature_code":"PPL",
    "gn:name":"Pol\u2019shino",
    "gn:population":0,
    "gn:timezone":"Europe/Moscow",
    "iso:country":"RU",
    "name:rus_x_preferred":[
        "\u041f\u043e\u043b\u044c\u0448\u0438\u043d\u043e"
    ],
    "name:und_x_variant":[
        "Pal\u2019shino",
        "Pol\u2019shino"
    ],
    "wof:name":"Pol'shino",
    "wof:placetype":"locality"
},
  "geometry": {"coordinates":[30.08096,56.77918],"type":"Point"}
}