{
  "type": "Feature",
  "properties": {
    "gn:admin1_code":"80",
    "gn:asciiname":"Nizhniy Syr'yez",
    "gn:country_code":"RU",
    "gn:dem":126,
    "gn:feature_class":"P",
    "gn:feature_code":"PPL",
    "gn:name":"Nizhniy Syr\u2019yez",
    "gn:population":0,
    "gn:timezone":"Europe/Samara",
    "iso:country":"RU",
    "name:rus_x_preferred":[
        "\u041d\u0438\u0436\u043d\u0438\u0439 \u0421\u044b\u0440\u044c\u0435\u0437"
    ],
    "name:und_x_variant":[
        "Syr\u2019yez",
        "Nizhniy Syr\u2019yez"
    ],
    "wof:name":"Nizhniy Syr'yez",
    "wof:placetype":"locality"
},
  "geometry": {"coordinates":[52.5533,56.29856],"type":"Point"}
}