{
  "type": "Feature",
  "properties": {
    "gn:admin1_code":"28",
    "gn:asciiname":"Tolloreka",
    "gn:country_code":"RU",
    "gn:dem":111,
    "gn:feature_class":"P",
    "gn:feature_code":"PPL",
    "gn:name":"Tolloreka",
    "gn:population":0,
    "gn:timezone":"Europe/Moscow",
    "iso:country":"RU",
    "name:eng_x_preferred":[
        "Tolloreka"
    ],
    "name:fin_x_preferred":[
        "Tollojoki"
    ],
    "name:nor_x_preferred":[
        "Talloreka"
    ],
    "name:rus_x_preferred":[
        "\u0422\u0430\u043b\u043b\u043e\u0440\u0435\u043a\u0430"
    ],
    "name:und_x_variant":[
        "Talloreka",
        "Tolloreka"
    ],
    "wof:name":"Tolloreka",
    "wof:placetype":"locality"
},
  "geometry": {"coordinates":[30.53431,64.89161],"type":"Point"}
}