{
  "type": "Feature",
  "properties": {
    "gn:admin1_code":"4",
    "gn:asciiname":"Novokamenka",
    "gn:country_code":"RU",
    "gn:dem":289,
    "gn:feature_class":"P",
    "gn:feature_code":"PPL",
    "gn:name":"Novokamenka",
    "gn:population":0,
    "gn:timezone":"Asia/Barnaul",
    "iso:country":"RU",
    "name:che_x_preferred":[
        "\u041d\u043e\u0432\u043e\u043a\u0430\u043c\u0435\u043d\u043a\u0430"
    ],
    "name:rus_x_preferred":[
        "\u041d\u043e\u0432\u043e\u043a\u0430\u043c\u0435\u043d\u043a\u0430"
    ],
    "name:und_x_variant":[
        "\u041d\u043e\u0432\u043e\u043a\u0430\u043c\u0435\u043d\u043a\u0430"
    ],
    "wof:name":"Novokamenka",
    "wof:placetype":"locality"
},
  "geometry": {"coordinates":[84.95,54.13333000000001],"type":"Point"}
}