{
  "type": "Feature",
  "properties": {
    "gn:admin1_code":"88",
    "gn:asciiname":"Baskachi",
    "gn:country_code":"RU",
    "gn:dem":118,
    "gn:feature_class":"P",
    "gn:feature_code":"PPL",
    "gn:name":"Baskachi",
    "gn:population":0,
    "gn:timezone":"Europe/Moscow",
    "iso:country":"RU",
    "name:rus_x_preferred":[
        "\u0411\u0430\u0441\u043a\u0430\u0447\u0438"
    ],
    "name:und_x_variant":[
        "\u0411\u0430\u0441\u043a\u0430\u0447\u0438"
    ],
    "wof:name":"Baskachi",
    "wof:placetype":"locality"
},
  "geometry": {"coordinates":[38.3504,57.5812],"type":"Point"}
}