{
  "type": "Feature",
  "properties": {
    "gn:admin1_code":"60.0",
    "gn:asciiname":"Molochkovo-Dubenets",
    "gn:country_code":"RU",
    "gn:dem":36,
    "gn:feature_class":"P",
    "gn:feature_code":"PPL",
    "gn:name":"Molochkovo-Dubenets",
    "gn:population":11,
    "gn:timezone":"Europe/Moscow",
    "iso:country":"RU",
    "name:che_x_preferred":[
        "\u041c\u043e\u043b\u043e\u0447\u043a\u043e\u0432\u043e-\u0414\u0443\u0431\u0435\u043d\u0435\u0446"
    ],
    "name:rus_x_preferred":[
        "\u041c\u043e\u043b\u043e\u0447\u043a\u043e\u0432\u043e-\u0414\u0443\u0431\u0435\u043d\u0435\u0446"
    ],
    "name:rus_x_variant":[
        "\u041c\u043e\u043b\u043e\u0447\u043a\u043e\u0432\u043e"
    ],
    "wof:name":"Molochkovo-Dubenets",
    "wof:placetype":"locality",
    "wof:population":11
},
  "geometry": {"coordinates":[27.93512,57.8504],"type":"Point"}
}