{
  "type": "Feature",
  "properties": {
    "gn:admin1_code":"61",
    "gn:asciiname":"Kopanskiy",
    "gn:country_code":"RU",
    "gn:dem":102,
    "gn:feature_class":"P",
    "gn:feature_code":"PPL",
    "gn:name":"Kopanskiy",
    "gn:population":0,
    "gn:timezone":"Europe/Moscow",
    "iso:country":"RU",
    "name:rus_x_preferred":[
        "\u041a\u043e\u043f\u0430\u043d\u0441\u043a\u0438\u0439"
    ],
    "name:und_x_variant":[
        "\u041a\u043e\u043f\u0430\u043d\u0441\u043a\u0438\u0439"
    ],
    "wof:name":"Kopanskiy",
    "wof:placetype":"locality"
},
  "geometry": {"coordinates":[42.6287,46.892],"type":"Point"}
}