{
  "type": "Feature",
  "properties": {
    "gn:admin1_code":"60",
    "gn:asciiname":"Miritinitsy",
    "gn:country_code":"RU",
    "gn:dem":230,
    "gn:feature_class":"P",
    "gn:feature_code":"PPL",
    "gn:name":"Miritinitsy",
    "gn:population":0,
    "gn:timezone":"Europe/Moscow",
    "iso:country":"RU",
    "name:eng_x_preferred":[
        "Miritinitsy"
    ],
    "name:nor_x_preferred":[
        "Maritinitsy"
    ],
    "name:rus_x_preferred":[
        "\u041c\u0430\u0440\u0438\u0442\u0438\u043d\u0438\u0446\u044b"
    ],
    "name:rus_x_variant":[
        "\u041c\u0438\u0440\u0438\u0442\u0438\u043d\u0438\u0446\u044b"
    ],
    "name:und_x_variant":[
        "\u041c\u0438\u0440\u0438\u0442\u0438\u043d\u0438\u0446\u044b"
    ],
    "wof:name":"Miritinitsy",
    "wof:placetype":"locality"
},
  "geometry": {"coordinates":[29.83177,56.64607],"type":"Point"}
}