{
  "type": "Feature",
  "properties": {
    "gn:admin1_code":"6",
    "gn:asciiname":"Yurkinskaya",
    "gn:country_code":"RU",
    "gn:dem":80,
    "gn:feature_class":"P",
    "gn:feature_code":"PPL",
    "gn:name":"Yurkinskaya",
    "gn:population":0,
    "gn:timezone":"Europe/Moscow",
    "iso:country":"RU",
    "name:eng_x_preferred":[
        "Yurkinskaya"
    ],
    "name:nor_x_preferred":[
        "Jurkinskaja"
    ],
    "name:rus_x_preferred":[
        "\u042e\u0440\u043a\u0438\u043d\u0441\u043a\u0430\u044f"
    ],
    "name:und_x_variant":[
        "Yurkinskaya Vystavka"
    ],
    "wof:name":"Yurkinskaya",
    "wof:placetype":"locality"
},
  "geometry": {"coordinates":[45.87242,61.95689],"type":"Point"}
}