{
  "type": "Feature",
  "properties": {
    "gn:admin1_code":"51.0",
    "gn:asciiname":"Demikha",
    "gn:country_code":"RU",
    "gn:dem":113,
    "gn:feature_class":"P",
    "gn:feature_code":"PPL",
    "gn:name":"D\u00ebmikha",
    "gn:population":0,
    "gn:timezone":"Europe/Moscow",
    "iso:country":"RU",
    "name:rus_x_preferred":[
        "\u0414\u0451\u043c\u0438\u0445\u0430"
    ],
    "name:und_x_variant":[
        "D\u00ebmikha"
    ],
    "wof:name":"Demikha",
    "wof:placetype":"locality"
},
  "geometry": {"coordinates":[44.54422,57.09916],"type":"Point"}
}