{
  "type": "Feature",
  "properties": {
    "gn:admin1_code":"75",
    "gn:asciiname":"Pavlovskiy",
    "gn:country_code":"RU",
    "gn:dem":94,
    "gn:feature_class":"P",
    "gn:feature_code":"PPL",
    "gn:name":"Pavlovskiy",
    "gn:population":0,
    "gn:timezone":"Asia/Tomsk",
    "iso:country":"RU",
    "name:rus_x_preferred":[
        "\u041f\u0430\u0432\u043b\u043e\u0432\u0441\u043a\u0438\u0439"
    ],
    "name:und_x_variant":[
        "\u041f\u0430\u0432\u043b\u043e\u0432\u0441\u043a\u0438\u0439"
    ],
    "wof:name":"Pavlovskiy",
    "wof:placetype":"locality"
},
  "geometry": {"coordinates":[80.98333000000002,57.48333],"type":"Point"}
}