{
  "type": "Feature",
  "properties": {
    "gn:admin1_code":"8",
    "gn:asciiname":"Urman-Bishkadak",
    "gn:country_code":"RU",
    "gn:dem":183,
    "gn:feature_class":"P",
    "gn:feature_code":"PPL",
    "gn:name":"Urman-Bishkadak",
    "gn:population":0,
    "gn:timezone":"Asia/Yekaterinburg",
    "iso:country":"RU",
    "name:eng_x_preferred":[
        "Urman-Bashkadak"
    ],
    "name:nor_x_preferred":[
        "Urman-Bisjkadak"
    ],
    "name:rus_x_preferred":[
        "\u0423\u0440\u043c\u0430\u043d-\u0411\u0438\u0448\u043a\u0430\u0434\u0430\u043a"
    ],
    "name:und_x_variant":[
        "Urman-Bishkadak"
    ],
    "wof:name":"Urman-Bishkadak",
    "wof:placetype":"locality"
},
  "geometry": {"coordinates":[56.07815,53.52652],"type":"Point"}
}