{
  "type": "Feature",
  "properties": {
    "gn:admin1_code":"13",
    "gn:asciiname":"Nesterovo",
    "gn:country_code":"RU",
    "gn:dem":368,
    "gn:feature_class":"P",
    "gn:feature_code":"PPL",
    "gn:name":"Nesterovo",
    "gn:population":0,
    "gn:timezone":"Asia/Yekaterinburg",
    "iso:country":"RU",
    "name:eng_x_preferred":[
        "Nesterovo"
    ],
    "name:nor_x_preferred":[
        "Nesterovo"
    ],
    "name:rus_x_preferred":[
        "\u041d\u0435\u0441\u0442\u0435\u0440\u043e\u0432\u043e"
    ],
    "name:und_x_variant":[
        "Nesterova",
        "\u041d\u0435\u0441\u0442\u0435\u0440\u043e\u0432\u043e",
        "Nesterovo"
    ],
    "wof:name":"Nesterovo",
    "wof:placetype":"locality"
},
  "geometry": {"coordinates":[59.4642,55.8531],"type":"Point"}
}