{
  "type": "Feature",
  "properties": {
    "gn:admin1_code":"8",
    "gn:asciiname":"Starokuktovo",
    "gn:cc2":"RU",
    "gn:country_code":"RU",
    "gn:dem":117,
    "gn:feature_class":"P",
    "gn:feature_code":"PPL",
    "gn:name":"Starokuktovo",
    "gn:population":0,
    "gn:timezone":"Asia/Yekaterinburg",
    "iso:country":"RU",
    "name:eng_x_preferred":[
        "Starokuktovo"
    ],
    "name:nor_x_preferred":[
        "Starokuktovo"
    ],
    "name:rus_x_preferred":[
        "\u0421\u0442\u0430\u0440\u043e\u043a\u0443\u043a\u0442\u043e\u0432\u043e"
    ],
    "name:und_x_variant":[
        "Staroye Kuktovo"
    ],
    "wof:name":"Starokuktovo",
    "wof:placetype":"locality"
},
  "geometry": {"coordinates":[54.22806,55.46639],"type":"Point"}
}