{
  "type": "Feature",
  "properties": {
    "gn:admin1_code":"54",
    "gn:asciiname":"Bobrovka",
    "gn:country_code":"RU",
    "gn:dem":110,
    "gn:feature_class":"P",
    "gn:feature_code":"PPL",
    "gn:name":"Bobrovka",
    "gn:population":0,
    "gn:timezone":"Asia/Omsk",
    "iso:country":"RU",
    "name:rus_x_preferred":[
        "\u0411\u043e\u0431\u0440\u043e\u0432\u043a\u0430"
    ],
    "name:und_x_variant":[
        "Verkhne Bobrovskiy",
        "Verkhnyaya Bobrovka",
        "Bobrovka"
    ],
    "wof:name":"Bobrovka",
    "wof:placetype":"locality"
},
  "geometry": {"coordinates":[74.69074000000001,57.15],"type":"Point"}
}