{
  "type": "Feature",
  "properties": {
    "gn:admin1_code":"53",
    "gn:asciiname":"Kurilovka",
    "gn:country_code":"RU",
    "gn:dem":297,
    "gn:feature_class":"P",
    "gn:feature_code":"PPL",
    "gn:name":"Kurilovka",
    "gn:population":0,
    "gn:timezone":"Asia/Novosibirsk",
    "iso:country":"RU",
    "name:eng_x_preferred":[
        "Kurilovka"
    ],
    "name:nor_x_preferred":[
        "Kurilovka"
    ],
    "name:rus_x_preferred":[
        "\u041a\u0443\u0440\u0438\u043b\u043e\u0432\u043a\u0430"
    ],
    "wof:name":"Kurilovka",
    "wof:placetype":"locality"
},
  "geometry": {"coordinates":[82.7595,54.2147],"type":"Point"}
}