{
  "type": "Feature",
  "properties": {
    "gn:admin1_code":"77",
    "gn:asciiname":"Buzany",
    "gn:country_code":"RU",
    "gn:dem":268,
    "gn:feature_class":"P",
    "gn:feature_code":"PPL",
    "gn:name":"Buzany",
    "gn:population":0,
    "gn:timezone":"Europe/Moscow",
    "iso:country":"RU",
    "name:rus_x_preferred":[
        "\u0411\u0443\u0437\u0430\u043d\u044b"
    ],
    "name:und_x_variant":[
        "\u0411\u0443\u0437\u0430\u043d\u044b"
    ],
    "wof:name":"Buzany",
    "wof:placetype":"locality"
},
  "geometry": {"coordinates":[31.9912,57.0195],"type":"Point"}
}