{
  "type": "Feature",
  "properties": {
    "gn:admin1_code":"33",
    "gn:asciiname":"Nagor'ye",
    "gn:country_code":"RU",
    "gn:dem":168,
    "gn:feature_class":"P",
    "gn:feature_code":"PPL",
    "gn:name":"Nagor\u2019ye",
    "gn:population":0,
    "gn:timezone":"Europe/Kirov",
    "iso:country":"RU",
    "name:rus_x_preferred":[
        "\u041d\u0430\u0433\u043e\u0440\u044c\u0435"
    ],
    "name:und_x_variant":[
        "Nagor\u2019ye"
    ],
    "wof:name":"Nagor'ye",
    "wof:placetype":"locality"
},
  "geometry": {"coordinates":[49.0728,58.8103],"type":"Point"}
}