{
  "type": "Feature",
  "properties": {
    "gn:admin1_code":"73",
    "gn:asciiname":"Klyuchi-Sap",
    "gn:country_code":"RU",
    "gn:dem":142,
    "gn:feature_class":"P",
    "gn:feature_code":"PPL",
    "gn:name":"Klyuchi-Sap",
    "gn:population":0,
    "gn:timezone":"Europe/Moscow",
    "iso:country":"RU",
    "name:eng_x_preferred":[
        "Klyuchi-Sap"
    ],
    "name:nor_x_preferred":[
        "Kljutsji-Sap"
    ],
    "name:rus_x_preferred":[
        "\u041a\u043b\u044e\u0447\u0438-\u0421\u0430\u043f"
    ],
    "name:und_x_variant":[
        "Klyuch-Sap"
    ],
    "wof:name":"Klyuchi-Sap",
    "wof:placetype":"locality"
},
  "geometry": {"coordinates":[49.4255,56.4212],"type":"Point"}
}