{
  "type": "Feature",
  "properties": {
    "gn:admin1_code":"47.0",
    "gn:asciiname":"Fedotovo",
    "gn:country_code":"RU",
    "gn:dem":123,
    "gn:feature_class":"P",
    "gn:feature_code":"PPL",
    "gn:name":"Fedotovo",
    "gn:population":0,
    "gn:timezone":"Europe/Moscow",
    "iso:country":"RU",
    "name:rus_x_preferred":[
        "\u0424\u0435\u0434\u043e\u0442\u043e\u0432\u043e"
    ],
    "name:und_x_variant":[
        "\u0424\u0435\u0434\u043e\u0442\u043e\u0432\u043e"
    ],
    "wof:name":"Fedotovo",
    "wof:placetype":"locality"
},
  "geometry": {"coordinates":[38.67515,55.3236],"type":"Point"}
}