{
  "type": "Feature",
  "properties": {
    "gn:admin1_code":"37",
    "gn:asciiname":"Serapikha",
    "gn:country_code":"RU",
    "gn:dem":170,
    "gn:feature_class":"P",
    "gn:feature_code":"PPL",
    "gn:name":"Serapikha",
    "gn:population":0,
    "gn:timezone":"Europe/Moscow",
    "iso:country":"RU",
    "name:eng_x_preferred":[
        "Serapikha"
    ],
    "name:nor_x_preferred":[
        "Serapikha"
    ],
    "name:rus_x_preferred":[
        "\u0421\u0435\u0440\u0430\u043f\u0438\u0445\u0430"
    ],
    "name:und_x_variant":[
        "\u0421\u0435\u0440\u0430\u043f\u0438\u0445\u0430",
        "Serapikha"
    ],
    "wof:name":"Serapikha",
    "wof:placetype":"locality"
},
  "geometry": {"coordinates":[42.73834,58.67629],"type":"Point"}
}