{
  "type": "Feature",
  "properties": {
    "gn:admin1_code":"10",
    "gn:asciiname":"Trudovik",
    "gn:country_code":"RU",
    "gn:dem":178,
    "gn:feature_class":"P",
    "gn:feature_code":"PPL",
    "gn:name":"Trudovik",
    "gn:population":0,
    "gn:timezone":"Europe/Moscow",
    "iso:country":"RU",
    "name:rus_x_preferred":[
        "\u0422\u0440\u0443\u0434\u043e\u0432\u0438\u043a"
    ],
    "name:und_x_variant":[
        "\u0422\u0440\u0443\u0434\u043e\u0432\u0438\u043a"
    ],
    "wof:name":"Trudovik",
    "wof:placetype":"locality"
},
  "geometry": {"coordinates":[32.71845,52.87543],"type":"Point"}
}