{
  "type": "Feature",
  "properties": {
    "gn:admin1_code":"63",
    "gn:asciiname":"Boraka",
    "gn:country_code":"RU",
    "gn:dem":1211,
    "gn:feature_class":"P",
    "gn:feature_code":"PPL",
    "gn:name":"Boraka",
    "gn:population":0,
    "gn:timezone":"Asia/Magadan",
    "iso:country":"RU",
    "name:rus_x_preferred":[
        "\u0411\u043e\u0440\u0430\u043a\u0430"
    ],
    "wof:name":"Boraka",
    "wof:placetype":"locality"
},
  "geometry": {"coordinates":[141.19999999999999,65.45],"type":"Point"}
}