{
  "type": "Feature",
  "properties": {
    "gn:admin1_code":"71",
    "gn:asciiname":"Koksharova",
    "gn:country_code":"RU",
    "gn:dem":99,
    "gn:feature_class":"P",
    "gn:feature_code":"PPL",
    "gn:name":"Koksharova",
    "gn:population":0,
    "gn:timezone":"Asia/Yekaterinburg",
    "iso:country":"RU",
    "name:rus_x_preferred":[
        "\u041a\u043e\u043a\u0448\u0430\u0440\u043e\u0432\u0430"
    ],
    "name:und_x_variant":[
        "Koksharovskiy",
        "Koksharova"
    ],
    "wof:name":"Koksharova",
    "wof:placetype":"locality"
},
  "geometry": {"coordinates":[62.5815,56.8521],"type":"Point"}
}