{
  "type": "Feature",
  "properties": {
    "gn:admin1_code":"72.0",
    "gn:asciiname":"Chemberevka",
    "gn:country_code":"RU",
    "gn:dem":155,
    "gn:feature_class":"P",
    "gn:feature_code":"PPL",
    "gn:name":"Chemberevka",
    "gn:population":0,
    "gn:timezone":"Europe/Moscow",
    "iso:country":"RU",
    "name:rus_x_preferred":[
        "\u0427\u0435\u043c\u0431\u0435\u0440\u0435\u0432\u043a\u0430"
    ],
    "name:und_x_variant":[
        "\u0427\u0435\u043c\u0431\u0435\u0440\u0435\u0432\u043a\u0430"
    ],
    "wof:name":"Chemberevka",
    "wof:placetype":"locality"
},
  "geometry": {"coordinates":[42.61972,51.85222],"type":"Point"}
}