{
  "type": "Feature",
  "properties": {
    "gn:admin1_code":"37",
    "gn:asciiname":"Kuzyug",
    "gn:country_code":"RU",
    "gn:dem":168,
    "gn:feature_class":"P",
    "gn:feature_code":"PPL",
    "gn:name":"Kuzyug",
    "gn:population":0,
    "gn:timezone":"Europe/Moscow",
    "iso:country":"RU",
    "name:rus_x_preferred":[
        "\u041a\u0443\u0437\u044e\u0433"
    ],
    "wof:name":"Kuzyug",
    "wof:placetype":"locality"
},
  "geometry": {"coordinates":[46.19504000000001,59.08012],"type":"Point"}
}