{
  "type": "Feature",
  "properties": {
    "gn:admin1_code":"56.0",
    "gn:asciiname":"Pavlodar",
    "gn:country_code":"RU",
    "gn:dem":231,
    "gn:feature_class":"P",
    "gn:feature_code":"PPL",
    "gn:name":"Pavlodar",
    "gn:population":0,
    "gn:timezone":"Europe/Moscow",
    "iso:country":"RU",
    "name:rus_x_preferred":[
        "\u041f\u0430\u0432\u043b\u043e\u0434\u0430\u0440"
    ],
    "name:und_x_variant":[
        "Dvoriki",
        "Pavlodar",
        "\u041f\u0430\u0432\u043b\u043e\u0434\u0430\u0440"
    ],
    "wof:name":"Pavlodar",
    "wof:placetype":"locality"
},
  "geometry": {"coordinates":[35.6725,53.53093000000001],"type":"Point"}
}