{
  "type": "Feature",
  "properties": {
    "gn:admin1_code":"46.0",
    "gn:asciiname":"Rep'yevka",
    "gn:country_code":"RU",
    "gn:dem":197,
    "gn:feature_class":"P",
    "gn:feature_code":"PPL",
    "gn:name":"Rep\u2019yevka",
    "gn:population":0,
    "gn:timezone":"Europe/Moscow",
    "iso:country":"RU",
    "name:rus_x_preferred":[
        "\u0420\u0435\u043f\u044c\u0435\u0432\u043a\u0430"
    ],
    "name:und_x_variant":[
        "Rep\u2019yevka"
    ],
    "wof:name":"Rep'yevka",
    "wof:placetype":"locality"
},
  "geometry": {"coordinates":[44.97147,54.3191],"type":"Point"}
}