{
  "type": "Feature",
  "properties": {
    "gn:admin1_code":"52.0",
    "gn:asciiname":"Bol'shiye Dorki",
    "gn:country_code":"RU",
    "gn:dem":45,
    "gn:feature_class":"P",
    "gn:feature_code":"PPL",
    "gn:name":"Bol\u2019shiye Dorki",
    "gn:population":0,
    "gn:timezone":"Europe/Moscow",
    "iso:country":"RU",
    "name:rus_x_preferred":[
        "\u0411\u043e\u043b\u044c\u0448\u0438\u0435 \u0414\u043e\u0440\u043a\u0438"
    ],
    "name:und_x_variant":[
        "Bol\u2019shiye Dorki"
    ],
    "wof:name":"Bol'shiye Dorki",
    "wof:placetype":"locality"
},
  "geometry": {"coordinates":[31.91839,58.58452],"type":"Point"}
}