{
  "type": "Feature",
  "properties": {
    "gn:admin1_code":"62",
    "gn:asciiname":"Tupik",
    "gn:country_code":"RU",
    "gn:dem":149,
    "gn:feature_class":"P",
    "gn:feature_code":"PPL",
    "gn:name":"Tupik",
    "gn:population":0,
    "gn:timezone":"Europe/Moscow",
    "iso:country":"RU",
    "name:rus_x_preferred":[
        "\u0422\u0443\u043f\u0438\u043a"
    ],
    "name:und_x_variant":[
        "Merdushinskiy Tupik",
        "Tupik"
    ],
    "wof:name":"Tupik",
    "wof:placetype":"locality"
},
  "geometry": {"coordinates":[42.3893,54.9221],"type":"Point"}
}