{
  "type": "Feature",
  "properties": {
    "gn:admin1_code":"9",
    "gn:asciiname":"Stanovoye",
    "gn:country_code":"RU",
    "gn:dem":226,
    "gn:feature_class":"P",
    "gn:feature_code":"PPL",
    "gn:name":"Stanovoye",
    "gn:population":0,
    "gn:timezone":"Europe/Moscow",
    "iso:country":"RU",
    "name:rus_x_preferred":[
        "\u0421\u0442\u0430\u043d\u043e\u0432\u043e\u0435"
    ],
    "name:und_x_variant":[
        "Stanovoy"
    ],
    "wof:name":"Stanovoye",
    "wof:placetype":"locality"
},
  "geometry": {"coordinates":[38.2881,50.9462],"type":"Point"}
}