{
  "type": "Feature",
  "properties": {
    "gn:admin1_code":"64",
    "gn:asciiname":"Kef",
    "gn:cc2":"RU",
    "gn:country_code":"RU",
    "gn:dem":23,
    "gn:feature_class":"P",
    "gn:feature_code":"PPL",
    "gn:name":"Kef",
    "gn:population":0,
    "gn:timezone":"Asia/Sakhalin",
    "iso:country":"RU",
    "name:ceb_x_preferred":[
        "Kef"
    ],
    "name:fin_x_preferred":[
        "Kef"
    ],
    "name:rus_x_preferred":[
        "\u041a\u0435\u0444"
    ],
    "name:swe_x_preferred":[
        "Kef"
    ],
    "name:und_x_variant":[
        "Kefvo",
        "Kef",
        "\u041a\u0435\u0444"
    ],
    "wof:name":"Kef",
    "wof:placetype":"locality"
},
  "geometry": {"coordinates":[141.94999999999999,53.45],"type":"Point"}
}