{
  "type": "Feature",
  "properties": {
    "gn:admin1_code":"85.0",
    "gn:asciiname":"Demina",
    "gn:country_code":"RU",
    "gn:dem":29,
    "gn:feature_class":"P",
    "gn:feature_code":"PPL",
    "gn:name":"D\u00ebmina",
    "gn:population":0,
    "gn:timezone":"Europe/Moscow",
    "iso:country":"RU",
    "name:rus_x_preferred":[
        "\u0414\u0451\u043c\u0438\u043d\u0430"
    ],
    "name:und_x_variant":[
        "Dimina",
        "D\u00ebmina",
        "\u0414\u0451\u043c\u0438\u043d\u0430"
    ],
    "wof:name":"Demina",
    "wof:placetype":"locality"
},
  "geometry": {"coordinates":[36.61464,61.28809],"type":"Point"}
}