{
  "type": "Feature",
  "properties": {
    "gn:admin1_code":"7",
    "gn:asciiname":"Mansur",
    "gn:country_code":"RU",
    "gn:dem":-24,
    "gn:feature_class":"P",
    "gn:feature_code":"PPL",
    "gn:name":"Mansur",
    "gn:population":0,
    "gn:timezone":"Europe/Astrakhan",
    "iso:country":"RU",
    "name:ara_x_preferred":[
        "\u0645\u0646\u0635\u0648\u0631"
    ],
    "name:rus_x_preferred":[
        "\u041c\u0430\u043d\u0441\u0443\u0440"
    ],
    "wof:name":"Mansur",
    "wof:placetype":"locality"
},
  "geometry": {"coordinates":[47.9553,46.232],"type":"Point"}
}