{
  "type": "Feature",
  "properties": {
    "gn:admin1_code":"61",
    "gn:asciiname":"Krutyanskiy",
    "gn:country_code":"RU",
    "gn:dem":177,
    "gn:feature_class":"P",
    "gn:feature_code":"PPL",
    "gn:name":"Krutyanskiy",
    "gn:population":0,
    "gn:timezone":"Europe/Moscow",
    "iso:country":"RU",
    "name:rus_x_preferred":[
        "\u041a\u0440\u0443\u0442\u044f\u043d\u0441\u043a\u0438\u0439"
    ],
    "wof:name":"Krutyanskiy",
    "wof:placetype":"locality"
},
  "geometry": {"coordinates":[41.46583,49.23111],"type":"Point"}
}