{
  "type": "Feature",
  "properties": {
    "gn:admin1_code":"90",
    "gn:asciiname":"Urmy",
    "gn:country_code":"RU",
    "gn:dem":198,
    "gn:feature_class":"P",
    "gn:feature_code":"PPL",
    "gn:name":"Urmy",
    "gn:population":0,
    "gn:timezone":"Asia/Yekaterinburg",
    "iso:country":"RU",
    "name:rus_x_preferred":[
        "\u0423\u0440\u043c\u044b"
    ],
    "wof:name":"Urmy",
    "wof:placetype":"locality"
},
  "geometry": {"coordinates":[56.9977,57.6113],"type":"Point"}
}