{
  "type": "Feature",
  "properties": {
    "gn:admin1_code":"42.0",
    "gn:asciiname":"Nagornoye",
    "gn:country_code":"RU",
    "gn:dem":44,
    "gn:feature_class":"P",
    "gn:feature_code":"PPL",
    "gn:name":"Nagornoye",
    "gn:population":0,
    "gn:timezone":"Europe/Moscow",
    "iso:country":"RU",
    "name:fin_x_preferred":[
        "Lavola"
    ],
    "wof:name":"Nagornoye",
    "wof:placetype":"locality"
},
  "geometry": {"coordinates":[29.41074,60.49943],"type":"Point"}
}