{
  "type": "Feature",
  "properties": {
    "gn:admin1_code":"8",
    "gn:asciiname":"Novyy Kal'chir",
    "gn:country_code":"RU",
    "gn:dem":169,
    "gn:feature_class":"P",
    "gn:feature_code":"PPL",
    "gn:name":"Novyy Kal\u2019chir",
    "gn:population":0,
    "gn:timezone":"Asia/Yekaterinburg",
    "iso:country":"RU",
    "name:rus_x_preferred":[
        "\u041d\u043e\u0432\u044b\u0439 \u041a\u0430\u043b\u044c\u0447\u0438\u0440"
    ],
    "name:und_x_variant":[
        "Novyy Kal\u2019chir",
        "\u041d\u043e\u0432\u044b\u0439 \u041a\u0430\u043b\u044c\u0447\u0438\u0440"
    ],
    "wof:name":"Novyy Kal'chir",
    "wof:placetype":"locality"
},
  "geometry": {"coordinates":[55.9043,54.0772],"type":"Point"}
}