{
  "type": "Feature",
  "properties": {
    "gn:admin1_code":"61",
    "gn:asciiname":"Bogrovskiy",
    "gn:country_code":"RU",
    "gn:dem":196,
    "gn:feature_class":"P",
    "gn:feature_code":"PPL",
    "gn:name":"Bogrovskiy",
    "gn:population":0,
    "gn:timezone":"Europe/Moscow",
    "iso:country":"RU",
    "name:rus_x_preferred":[
        "\u0411\u043e\u0433\u0440\u043e\u0432\u0441\u043a\u0438\u0439"
    ],
    "name:und_x_variant":[
        "\u0411\u043e\u0433\u0440\u043e\u0432\u0441\u043a\u0438\u0439"
    ],
    "wof:name":"Bogrovskiy",
    "wof:placetype":"locality"
},
  "geometry": {"coordinates":[40.415,49.54861],"type":"Point"}
}