{
  "type": "Feature",
  "properties": {
    "gn:gn_country":"RU",
    "gn:gn_fcode":"PPL",
    "gn:gn_pop":5585,
    "gn:population":5585,
    "iso:country":"RU",
    "name:ara_x_preferred":[
        "\u062a\u0634\u064a\u0631\u062f\u064a\u0646"
    ],
    "name:azb_x_preferred":[
        "\u0686\u0627\u0631\u062f\u06cc\u0646"
    ],
    "name:aze_x_preferred":[
        "\u00c7erd\u0131n"
    ],
    "name:bel_x_preferred":[
        "\u0427\u0430\u0440\u0434\u044b\u043d\u044c"
    ],
    "name:bul_x_preferred":[
        "\u0427\u0435\u0440\u0434\u0438\u043d"
    ],
    "name:che_x_preferred":[
        "\u0427\u0435\u0440\u0434\u044b\u043d\u044c"
    ],
    "name:chi_x_preferred":[
        "\u5207\u723e\u767b"
    ],
    "name:cze_x_preferred":[
        "\u010cerdy\u0148"
    ],
    "name:dut_x_preferred":[
        "Cherdyn"
    ],
    "name:eng_x_preferred":[
        "Cherdyn'"
    ],
    "name:epo_x_preferred":[
        "\u0108erdinj"
    ],
    "name:est_x_preferred":[
        "T\u0161erd\u00f5n"
    ],
    "name:fin_x_preferred":[
        "T\u0161erdyn"
    ],
    "name:fre_x_preferred":[
        "Tcherdyne"
    ],
    "name:ger_x_preferred":[
        "Tscherdyn"
    ],
    "name:hrv_x_preferred":[
        "\u010cerdinj"
    ],
    "name:hsb_x_preferred":[
        "\u010cerdy\u0144"
    ],
    "name:hun_x_preferred":[
        "Cserdiny"
    ],
    "name:ita_x_preferred":[
        "\u010cerdyn'"
    ],
    "name:jpn_x_preferred":[
        "\u30c1\u30a7\u30eb\u30c9\u30a5\u30a4\u30cb"
    ],
    "name:koi_x_preferred":[
        "\u0427\u0435\u0440\u0434\u044b\u043d"
    ],
    "name:kom_x_preferred":[
        "\u0427\u0435\u0440\u0434\u0456\u043d"
    ],
    "name:lat_x_preferred":[
        "Tserdinum"
    ],
    "name:mhr_x_preferred":[
        "\u0427\u0435\u0440\u0434\u044b\u043d\u044c"
    ],
    "name:nno_x_preferred":[
        "Tsjerdyn"
    ],
    "name:nob_x_preferred":[
        "Tsjerdyn"
    ],
    "name:nor_x_preferred":[
        "Tsjerdyn"
    ],
    "name:per_x_preferred":[
        "\u0686\u0631\u062f\u06cc\u0646\u060c \u067e\u0631\u0645"
    ],
    "name:por_x_preferred":[
        "Cherdyn"
    ],
    "name:rus_x_preferred":[
        "\u0427\u0435\u0440\u0434\u044b\u043d\u044c"
    ],
    "name:spa_x_preferred":[
        "Cherdyn"
    ],
    "name:srp_x_preferred":[
        "\u0427\u0435\u0440\u0434\u0438\u045a"
    ],
    "name:tat_x_preferred":[
        "\u0427\u04d9\u0440\u0434\u04d9\u043d"
    ],
    "name:tgk_x_preferred":[
        "\u0427\u0435\u0440\u0434\u0438\u043d"
    ],
    "name:tgl_x_preferred":[
        "Cherdyn"
    ],
    "name:ukr_x_preferred":[
        "\u0427\u0435\u0440\u0434\u0438\u043d\u044c"
    ],
    "name:unk_x_variant":[
        "Tscherdyn"
    ],
    "name:vep_x_preferred":[
        "\u010cerdin'"
    ],
    "name:war_x_preferred":[
        "Cherdyn"
    ],
    "qs_pg:aaroncc":"RU",
    "qs_pg:gn_country":"RU",
    "qs_pg:gn_fcode":"PPL",
    "qs_pg:gn_pop":5585,
    "qs_pg:name":"Cherdyn\u2019",
    "qs_pg:photos_9r":0,
    "qs_pg:photos_sr":0,
    "qs_pg:pop_sr":5,
    "qs_pg:qs_pg_placetype":"locality",
    "wof:name":"Cherdyn\u2019",
    "wof:placetype":"locality",
    "wof:population":5585
},
  "geometry": {"coordinates":[56.47868,60.40295],"type":"Point"}
}