{
  "type": "Feature",
  "properties": {
    "gn:admin1_code":"42",
    "gn:asciiname":"Novo-Oktyabr'skoye",
    "gn:country_code":"RU",
    "gn:dem":37,
    "gn:feature_class":"P",
    "gn:feature_code":"PPL",
    "gn:name":"Novo-Oktyabr\u2019skoye",
    "gn:population":0,
    "gn:timezone":"Europe/Moscow",
    "iso:country":"RU",
    "name:rus_x_preferred":[
        "\u041d\u043e\u0432\u043e-\u041e\u043a\u0442\u044f\u0431\u0440\u044c\u0441\u043a\u043e\u0435"
    ],
    "name:und_x_variant":[
        "Novoye Oktyabr\u2019skoye",
        "Novo-Oktyabr\u2019skoye"
    ],
    "wof:name":"Novo-Oktyabr'skoye",
    "wof:placetype":"locality"
},
  "geometry": {"coordinates":[32.31944,59.9132],"type":"Point"}
}