{
  "type": "Feature",
  "properties": {
    "gn:admin1_code":"71",
    "gn:asciiname":"Gurino",
    "gn:country_code":"RU",
    "gn:dem":198,
    "gn:feature_class":"P",
    "gn:feature_code":"PPL",
    "gn:name":"Gurino",
    "gn:population":0,
    "gn:timezone":"Asia/Yekaterinburg",
    "iso:country":"RU",
    "name:che_x_preferred":[
        "\u0413\u0443\u0440\u0438\u043d\u043e"
    ],
    "name:rus_x_preferred":[
        "\u0413\u0443\u0440\u0438\u043d\u043e"
    ],
    "name:und_x_variant":[
        "Gurina",
        "Gurino"
    ],
    "wof:name":"Gurino",
    "wof:placetype":"locality"
},
  "geometry": {"coordinates":[61.35478000000001,57.54326],"type":"Point"}
}