{
  "type": "Feature",
  "properties": {
    "gn:admin1_code":"33.0",
    "gn:asciiname":"Zachernushka",
    "gn:country_code":"RU",
    "gn:dem":116,
    "gn:feature_class":"P",
    "gn:feature_code":"PPL",
    "gn:name":"Zachernushka",
    "gn:population":0,
    "gn:timezone":"Europe/Kirov",
    "iso:country":"RU",
    "name:rus_x_preferred":[
        "\u0417\u0430\u0447\u0435\u0440\u043d\u0443\u0448\u043a\u0430"
    ],
    "wof:name":"Zachernushka",
    "wof:placetype":"locality"
},
  "geometry": {"coordinates":[49.04265,58.68068],"type":"Point"}
}