{
  "type": "Feature",
  "properties": {
    "gn:admin1_code":"73",
    "gn:admin2_code":"499980",
    "gn:asciiname":"Tatarskoye Mordovo",
    "gn:country_code":"RU",
    "gn:dem":87,
    "gn:feature_class":"P",
    "gn:feature_code":"PPL",
    "gn:name":"Tatarskoye Mordovo",
    "gn:population":0,
    "gn:timezone":"Europe/Moscow",
    "iso:country":"RU",
    "name:rus_x_preferred":[
        "\u0422\u0430\u0442\u0430\u0440\u0441\u043a\u043e\u0435 \u041c\u043e\u0440\u0434\u043e\u0432\u043e"
    ],
    "name:und_x_variant":[
        "Yanavyl"
    ],
    "wof:name":"Tatarskoye Mordovo",
    "wof:placetype":"locality"
},
  "geometry": {"coordinates":[50.66644,55.57671],"type":"Point"}
}