{
  "type": "Feature",
  "properties": {
    "gn:admin1_code":"37",
    "gn:asciiname":"Pezhenga-Sinyakovo",
    "gn:country_code":"RU",
    "gn:dem":198,
    "gn:feature_class":"P",
    "gn:feature_code":"PPL",
    "gn:name":"Pezhenga-Sinyakovo",
    "gn:population":0,
    "gn:timezone":"Europe/Moscow",
    "iso:country":"RU",
    "name:rus_x_preferred":[
        "\u041f\u0435\u0436\u0435\u043d\u0433\u0430-\u0421\u0438\u043d\u044f\u043a\u043e\u0432\u043e"
    ],
    "name:und_x_variant":[
        "Sinyakovo",
        "Pezhenga-Sinyakovo"
    ],
    "wof:name":"Pezhenga-Sinyakovo",
    "wof:placetype":"locality"
},
  "geometry": {"coordinates":[44.18319,59.1609],"type":"Point"}
}