{
  "type": "Feature",
  "properties": {
    "gn:admin1_code":"69",
    "gn:asciiname":"Osipovo",
    "gn:cc2":"RU",
    "gn:country_code":"RU",
    "gn:dem":196,
    "gn:feature_class":"P",
    "gn:feature_code":"PPL",
    "gn:name":"Osipovo",
    "gn:population":0,
    "gn:timezone":"Europe/Moscow",
    "iso:country":"RU",
    "name:rus_x_preferred":[
        "\u041e\u0441\u0438\u043f\u043e\u0432\u043e"
    ],
    "name:und_x_variant":[
        "Osipova",
        "Osipovo"
    ],
    "wof:name":"Osipovo",
    "wof:placetype":"locality"
},
  "geometry": {"coordinates":[33.35722,55.21556],"type":"Point"}
}