{
  "type": "Feature",
  "properties": {
    "gn:admin1_code":"53",
    "gn:asciiname":"Biaza",
    "gn:country_code":"RU",
    "gn:dem":112,
    "gn:feature_class":"P",
    "gn:feature_code":"PPL",
    "gn:name":"Biaza",
    "gn:population":0,
    "gn:timezone":"Asia/Novosibirsk",
    "iso:country":"RU",
    "name:eng_x_preferred":[
        "Biaza"
    ],
    "name:nor_x_preferred":[
        "Biaza"
    ],
    "name:rus_x_preferred":[
        "\u0411\u0438\u0430\u0437\u0430"
    ],
    "name:und_x_variant":[
        "Biyaza",
        "\u0411\u0438\u0430\u0437\u0430",
        "Biaza"
    ],
    "wof:name":"Biaza",
    "wof:placetype":"locality"
},
  "geometry": {"coordinates":[78.29914000000002,56.59639],"type":"Point"}
}