{
  "type": "Feature",
  "properties": {
    "gn:admin1_code":"91",
    "gn:asciiname":"Novogeorgiyevka",
    "gn:country_code":"RU",
    "gn:dem":380,
    "gn:feature_class":"P",
    "gn:feature_code":"PPL",
    "gn:name":"Novogeorgiyevka",
    "gn:population":0,
    "gn:timezone":"Asia/Krasnoyarsk",
    "iso:country":"RU",
    "name:rus_x_preferred":[
        "\u041d\u043e\u0432\u043e\u0433\u0435\u043e\u0440\u0433\u0438\u0435\u0432\u043a\u0430"
    ],
    "wof:name":"Novogeorgiyevka",
    "wof:placetype":"locality"
},
  "geometry": {"coordinates":[93.3276,53.8279],"type":"Point"}
}