{
  "type": "Feature",
  "properties": {
    "gn:admin1_code":"62",
    "gn:asciiname":"Gorbatovo",
    "gn:country_code":"RU",
    "gn:dem":194,
    "gn:feature_class":"P",
    "gn:feature_code":"PPL",
    "gn:name":"Gorbatovo",
    "gn:population":0,
    "gn:timezone":"Europe/Moscow",
    "iso:country":"RU",
    "name:rus_x_preferred":[
        "\u0413\u043e\u0440\u0431\u0430\u0442\u043e\u0432\u043e"
    ],
    "name:und_x_variant":[
        "Gorbatova",
        "Gorbatovo",
        "\u0413\u043e\u0440\u0431\u0430\u0442\u043e\u0432\u043e"
    ],
    "wof:name":"Gorbatovo",
    "wof:placetype":"locality"
},
  "geometry": {"coordinates":[38.80248,54.15988],"type":"Point"}
}