{
  "type": "Feature",
  "properties": {
    "gn:admin1_code":"4",
    "gn:asciiname":"Svet",
    "gn:country_code":"RU",
    "gn:dem":222,
    "gn:feature_class":"P",
    "gn:feature_code":"PPL",
    "gn:name":"Svet",
    "gn:population":0,
    "gn:timezone":"Asia/Barnaul",
    "iso:country":"RU",
    "name:deu_x_preferred":[
        "Svet"
    ],
    "name:rus_x_preferred":[
        "\u0421\u0432\u0435\u0442"
    ],
    "name:slk_x_preferred":[
        "Svet"
    ],
    "name:slv_x_preferred":[
        "Svet"
    ],
    "wof:name":"Svet",
    "wof:placetype":"locality"
},
  "geometry": {"coordinates":[80.73333000000002,53.76667],"type":"Point"}
}