{
  "type": "Feature",
  "properties": {
    "gn:admin1_code":"17.0",
    "gn:asciiname":"Adzhimazhagatyurt",
    "gn:country_code":"RU",
    "gn:dem":40,
    "gn:feature_class":"P",
    "gn:feature_code":"PPL",
    "gn:name":"Adzhimazhagatyurt",
    "gn:population":0,
    "gn:timezone":"Europe/Moscow",
    "iso:country":"RU",
    "name:nor_x_preferred":[
        "Adzjimazjagatjurt"
    ],
    "name:rus_x_preferred":[
        "\u0410\u0434\u0436\u0438\u043c\u0430\u0436\u0430\u0433\u0430\u0442\u044e\u0440\u0442"
    ],
    "name:und_x_variant":[
        "Mazhagat-Yurt",
        "Adzhi-Madzhi-Gat-Yurt",
        "Adzhimazhagatyurt"
    ],
    "wof:name":"Adzhimazhagatyurt",
    "wof:placetype":"locality"
},
  "geometry": {"coordinates":[46.50783,43.35055],"type":"Point"}
}