{
  "type": "Feature",
  "properties": {
    "gn:admin1_code":"24",
    "gn:asciiname":"Levyy Ostrov",
    "gn:country_code":"RU",
    "gn:dem":22,
    "gn:feature_class":"P",
    "gn:feature_code":"PPL",
    "gn:name":"Levyy Ostrov",
    "gn:population":0,
    "gn:timezone":"Europe/Moscow",
    "iso:country":"RU",
    "name:rus_x_preferred":[
        "\u041b\u0435\u0432\u044b\u0439 \u041e\u0441\u0442\u0440\u043e\u0432"
    ],
    "name:und_x_variant":[
        "\u041b\u0435\u0432\u044b\u0439 \u041e\u0441\u0442\u0440\u043e\u0432"
    ],
    "wof:name":"Levyy Ostrov",
    "wof:placetype":"locality"
},
  "geometry": {"coordinates":[43.4583,46.0059],"type":"Point"}
}