{
  "type": "Feature",
  "properties": {
    "gn:admin1_code":"71.0",
    "gn:asciiname":"Bol'shedvorova",
    "gn:country_code":"RU",
    "gn:dem":65,
    "gn:feature_class":"P",
    "gn:feature_code":"PPL",
    "gn:name":"Bol\u2019shedvorova",
    "gn:population":0,
    "gn:timezone":"Asia/Yekaterinburg",
    "iso:country":"RU",
    "name:rus_x_preferred":[
        "\u0411\u043e\u043b\u044c\u0448\u0435\u0434\u0432\u043e\u0440\u043e\u0432\u0430"
    ],
    "name:und_x_variant":[
        "Bol\u2019shedvorova"
    ],
    "wof:name":"Bol'shedvorova",
    "wof:placetype":"locality"
},
  "geometry": {"coordinates":[63.3852,57.6013],"type":"Point"}
}