{
  "type": "Feature",
  "properties": {
    "gn:admin1_code":"10",
    "gn:asciiname":"Prudovka",
    "gn:country_code":"RU",
    "gn:dem":142,
    "gn:feature_class":"P",
    "gn:feature_code":"PPL",
    "gn:name":"Prudovka",
    "gn:population":0,
    "gn:timezone":"Europe/Moscow",
    "iso:country":"RU",
    "name:rus_x_preferred":[
        "\u041f\u0440\u0443\u0434\u043e\u0432\u043a\u0430"
    ],
    "wof:name":"Prudovka",
    "wof:placetype":"locality"
},
  "geometry": {"coordinates":[31.6684,52.6009],"type":"Point"}
}