{
  "type": "Feature",
  "properties": {
    "gn:admin1_code":"90.0",
    "gn:asciiname":"Bryukhovo",
    "gn:country_code":"RU",
    "gn:dem":158,
    "gn:feature_class":"P",
    "gn:feature_code":"PPL",
    "gn:name":"Bryukhovo",
    "gn:population":0,
    "gn:timezone":"Asia/Yekaterinburg",
    "iso:country":"RU",
    "name:che_x_preferred":[
        "\u0411\u0440\u044e\u0445\u043e\u0432\u043e"
    ],
    "name:eng_x_preferred":[
        "Bryukhovo"
    ],
    "name:nor_x_preferred":[
        "Brjukhovo"
    ],
    "name:rus_x_preferred":[
        "\u0411\u0440\u044e\u0445\u043e\u0432\u043e"
    ],
    "name:und_x_variant":[
        "Bryukhov"
    ],
    "wof:name":"Bryukhovo",
    "wof:placetype":"locality"
},
  "geometry": {"coordinates":[54.83878000000001,56.86431],"type":"Point"}
}