{
  "type": "Feature",
  "properties": {
    "gn:country":"RU",
    "gn:fcode":"PPL",
    "gn:population":2949,
    "iso:country":"RU",
    "name:ceb_x_preferred":[
        "Tyulyachinskiy Rayon"
    ],
    "name:che_x_preferred":[
        "\u0422\u044e\u043b\u044f\u0447\u0438\u043d \u043a\u04c0\u043e\u0448\u0442"
    ],
    "name:deu_x_preferred":[
        "Tjuljatschinski rajon"
    ],
    "name:eng_x_preferred":[
        "Tyulyachi"
    ],
    "name:eng_x_variant":[
        "Tyulyachinsky District"
    ],
    "name:est_x_preferred":[
        "Tjuljat\u0161i rajoon"
    ],
    "name:hun_x_preferred":[
        "Tyuljacsi j\u00e1r\u00e1s"
    ],
    "name:hye_x_preferred":[
        "\u054f\u0575\u0578\u0582\u056c\u0575\u0561\u0579\u056b\u0576\u057d\u056f\u056b \u0577\u0580\u057b\u0561\u0576"
    ],
    "name:mhr_x_preferred":[
        "\u0422\u044e\u043b\u044f\u0447\u0438 \u043a\u0443\u043d\u0434\u0435\u043c"
    ],
    "name:nld_x_preferred":[
        "Tjuljatsjinskiy rayon"
    ],
    "name:nor_x_preferred":[
        "Tjuljatsji"
    ],
    "name:por_x_preferred":[
        "Tyulyachinsky"
    ],
    "name:rus_x_preferred":[
        "\u0422\u044e\u043b\u044f\u0447\u0438"
    ],
    "name:rus_x_variant":[
        "\u0422\u044e\u043b\u044f\u0447\u0438\u043d\u0441\u043a\u0438\u0439 \u0440\u0430\u0439\u043e\u043d"
    ],
    "name:tat_x_preferred":[
        "\u0422\u0435\u043b\u04d9\u0447\u0435 \u0440\u0430\u0439\u043e\u043d\u044b"
    ],
    "name:ukr_x_preferred":[
        "\u0422\u044e\u043b\u044f\u0447\u0438\u043d\u0441\u044c\u043a\u0438\u0439 \u0440\u0430\u0439\u043e\u043d"
    ],
    "name:vie_x_preferred":[
        "Tyulyachinsky"
    ],
    "name:zho_x_preferred":[
        "\u79cb\u5229\u4e9e\u6b3d\u65af\u57fa\u5340"
    ],
    "qs:name":"Tyulyachi",
    "qs:photos_9r":0,
    "qs:photos_sr":0,
    "qs:pop_sr":"4",
    "wd:wordcount":1033,
    "wof:name":"Tyulyachi",
    "wof:placetype":"locality",
    "wof:population":2949
},
  "geometry": {"coordinates":[50.23992,55.89125],"type":"Point"}
}