{
  "type": "Feature",
  "properties": {
    "gn:country":"RU",
    "gn:fcode":"PPL",
    "gn:pop":2949,
    "iso:country":"RU",
    "name:eng_x_preferred":[
        "Tyulyachi"
    ],
    "name:nor_x_preferred":[
        "Tjuljatsji"
    ],
    "name:rus_x_preferred":[
        "\u0422\u044e\u043b\u044f\u0447\u0438"
    ],
    "name:unk_x_variant":[
        "\u0422\u044e\u043b\u044f\u0447\u0438"
    ],
    "qs:name":"Tyulyachi",
    "qs:photos_9r":0,
    "qs:photos_sr":0,
    "qs:pop_sr":"4",
    "wd:wordcount":1033,
    "wof:name":"Tyulyachi",
    "wof:placetype":"locality",
    "wof:population":2949
},
  "geometry": {"coordinates":[50.23992,55.89125],"type":"Point"}
}