{
  "type": "Feature",
  "properties": {
    "gn:admin1_code":"61.0",
    "gn:asciiname":"Kozlova Balka",
    "gn:country_code":"RU",
    "gn:dem":103,
    "gn:feature_class":"P",
    "gn:feature_code":"PPL",
    "gn:name":"Kozlova Balka",
    "gn:population":0,
    "gn:timezone":"Europe/Moscow",
    "iso:country":"RU",
    "name:rus_x_preferred":[
        "\u041a\u043e\u0437\u043b\u043e\u0432\u0430 \u0411\u0430\u043b\u043a\u0430"
    ],
    "wof:name":"Kozlova Balka",
    "wof:placetype":"locality"
},
  "geometry": {"coordinates":[40.65148,46.68003],"type":"Point"}
}