{
  "type": "Feature",
  "properties": {
    "gn:admin1_code":"85",
    "gn:asciiname":"Podrashchen'ye",
    "gn:country_code":"RU",
    "gn:dem":182,
    "gn:feature_class":"P",
    "gn:feature_code":"PPL",
    "gn:name":"Podrashchen\u2019ye",
    "gn:population":0,
    "gn:timezone":"Europe/Moscow",
    "iso:country":"RU",
    "name:rus_x_preferred":[
        "\u041f\u043e\u0434\u0440\u0430\u0449\u0435\u043d\u044c\u0435"
    ],
    "name:und_x_variant":[
        "Podrashchen\u2019ye"
    ],
    "wof:name":"Podrashchen'ye",
    "wof:placetype":"locality"
},
  "geometry": {"coordinates":[40.51667,60.08333],"type":"Point"}
}