{
  "type": "Feature",
  "properties": {
    "gn:admin1_code":"69",
    "gn:asciiname":"Leonovo",
    "gn:cc2":"RU",
    "gn:country_code":"RU",
    "gn:dem":226,
    "gn:feature_class":"P",
    "gn:feature_code":"PPL",
    "gn:name":"Leonovo",
    "gn:population":0,
    "gn:timezone":"Europe/Moscow",
    "iso:country":"RU",
    "name:rus_x_preferred":[
        "\u041b\u0435\u043e\u043d\u043e\u0432\u043e"
    ],
    "name:und_x_variant":[
        "Leonova",
        "Leonovo"
    ],
    "wof:name":"Leonovo",
    "wof:placetype":"locality"
},
  "geometry": {"coordinates":[33.11944,55.36333000000001],"type":"Point"}
}