{
  "type": "Feature",
  "properties": {
    "gn:admin1_code":"8.0",
    "gn:asciiname":"Abeysaz",
    "gn:country_code":"RU",
    "gn:dem":537,
    "gn:feature_class":"P",
    "gn:feature_code":"PPL",
    "gn:name":"Abeysaz",
    "gn:population":0,
    "gn:timezone":"Asia/Yekaterinburg",
    "iso:country":"RU",
    "name:nor_x_preferred":[
        "Abejsaz"
    ],
    "name:rus_x_preferred":[
        "\u0410\u0431\u0435\u0439\u0441\u0430\u0437"
    ],
    "wof:name":"Abeysaz",
    "wof:placetype":"locality"
},
  "geometry": {"coordinates":[58.21666999999999,52.43333000000001],"type":"Point"}
}