{
  "type": "Feature",
  "properties": {
    "gn:admin1_code":"69.0",
    "gn:asciiname":"Dobrikovo",
    "gn:country_code":"RU",
    "gn:dem":178,
    "gn:feature_class":"P",
    "gn:feature_code":"PPL",
    "gn:name":"Dobrikovo",
    "gn:population":0,
    "gn:timezone":"Europe/Moscow",
    "iso:country":"RU",
    "name:rus_x_preferred":[
        "\u0414\u043e\u0431\u0440\u0438\u043a\u043e\u0432\u043e"
    ],
    "wof:name":"Dobrikovo",
    "wof:placetype":"locality"
},
  "geometry": {"coordinates":[32.51615,54.76971],"type":"Point"}
}