{
  "type": "Feature",
  "properties": {
    "gn:admin1_code":"23",
    "gn:asciiname":"Izvilino",
    "gn:country_code":"RU",
    "gn:dem":22,
    "gn:feature_class":"P",
    "gn:feature_code":"PPL",
    "gn:name":"Izvilino",
    "gn:population":0,
    "gn:timezone":"Europe/Kaliningrad",
    "iso:country":"RU",
    "name:rus_x_preferred":[
        "\u0418\u0437\u0432\u0438\u043b\u0438\u043d\u043e"
    ],
    "wof:name":"Izvilino",
    "wof:placetype":"locality"
},
  "geometry": {"coordinates":[21.47972,54.60624],"type":"Point"}
}