{
  "type": "Feature",
  "properties": {
    "gn:admin1_code":"77.0",
    "gn:asciiname":"Bol'shoye Cheresovo",
    "gn:country_code":"RU",
    "gn:dem":231,
    "gn:feature_class":"P",
    "gn:feature_code":"PPL",
    "gn:name":"Bol\u2019shoye Cheresovo",
    "gn:population":0,
    "gn:timezone":"Europe/Moscow",
    "iso:country":"RU",
    "name:rus_x_preferred":[
        "\u0411\u043e\u043b\u044c\u0448\u043e\u0435 \u0427\u0435\u0440\u0435\u0441\u043e\u0432\u043e"
    ],
    "name:und_x_variant":[
        "Bol\u2019shoye Cheresovo",
        "\u0411\u043e\u043b\u044c\u0448\u043e\u0435 \u0427\u0435\u0440\u0435\u0441\u043e\u0432\u043e"
    ],
    "wof:name":"Bol'shoye Cheresovo",
    "wof:placetype":"locality"
},
  "geometry": {"coordinates":[31.85,56.71666999999999],"type":"Point"}
}