{
  "type": "Feature",
  "properties": {
    "gn:admin1_code":"20.0",
    "gn:asciiname":"Novogromovo",
    "gn:country_code":"RU",
    "gn:dem":602,
    "gn:feature_class":"P",
    "gn:feature_code":"PPL",
    "gn:name":"Novogromovo",
    "gn:population":0,
    "gn:timezone":"Asia/Irkutsk",
    "iso:country":"RU",
    "name:rus_x_preferred":[
        "\u041d\u043e\u0432\u043e\u0433\u0440\u043e\u043c\u043e\u0432\u043e"
    ],
    "wof:name":"Novogromovo",
    "wof:placetype":"locality"
},
  "geometry": {"coordinates":[102.95529999999999,53.1804],"type":"Point"}
}