{
  "type": "Feature",
  "properties": {
    "gn:admin1_code":"73",
    "gn:asciiname":"Ozhbuy",
    "gn:country_code":"RU",
    "gn:dem":142,
    "gn:feature_class":"P",
    "gn:feature_code":"PPL",
    "gn:name":"Ozhbuy",
    "gn:population":0,
    "gn:timezone":"Europe/Moscow",
    "iso:country":"RU",
    "name:rus_x_preferred":[
        "\u041e\u0436\u0431\u0443\u0439"
    ],
    "wof:name":"Ozhbuy",
    "wof:placetype":"locality"
},
  "geometry": {"coordinates":[53.2836,55.9459],"type":"Point"}
}