{
  "type": "Feature",
  "properties": {
    "gn:admin1_code":"42.0",
    "gn:asciiname":"Filippovichi",
    "gn:country_code":"RU",
    "gn:dem":55,
    "gn:feature_class":"P",
    "gn:feature_code":"PPL",
    "gn:name":"Filippovichi",
    "gn:population":0,
    "gn:timezone":"Europe/Moscow",
    "iso:country":"RU",
    "name:rus_x_preferred":[
        "\u0424\u0438\u043b\u0438\u043f\u043f\u043e\u0432\u0438\u0447\u0438"
    ],
    "wof:name":"Filippovichi",
    "wof:placetype":"locality"
},
  "geometry": {"coordinates":[30.66667,58.95],"type":"Point"}
}