{
  "type": "Feature",
  "properties": {
    "gn:admin1_code":"16",
    "gn:asciiname":"Kyuregasi",
    "gn:country_code":"RU",
    "gn:dem":170,
    "gn:feature_class":"P",
    "gn:feature_code":"PPL",
    "gn:name":"Kyuregasi",
    "gn:population":0,
    "gn:timezone":"Europe/Moscow",
    "iso:country":"RU",
    "name:rus_x_preferred":[
        "\u041a\u044e\u0440\u0435\u0433\u0430\u0441\u0438"
    ],
    "name:und_x_variant":[
        "\u041a\u044e\u0440\u0435\u0433\u0430\u0441\u0438",
        "Kyuregasy"
    ],
    "wof:name":"Kyuregasi",
    "wof:placetype":"locality"
},
  "geometry": {"coordinates":[46.8489,56.0956],"type":"Point"}
}