{
  "type": "Feature",
  "properties": {
    "gn:admin1_code":"49",
    "gn:asciiname":"Pil'skiy",
    "gn:country_code":"RU",
    "gn:dem":-9999,
    "gn:feature_class":"P",
    "gn:feature_code":"PPL",
    "gn:name":"Pil\u2019skiy",
    "gn:population":0,
    "gn:timezone":"Europe/Moscow",
    "iso:country":"RU",
    "name:rus_x_preferred":[
        "\u041f\u0438\u043b\u044c\u0441\u043a\u0438\u0439"
    ],
    "name:und_x_variant":[
        "Pilski",
        "Pil\u2019skiy"
    ],
    "wof:name":"Pil'skiy",
    "wof:placetype":"locality"
},
  "geometry": {"coordinates":[34.16699000000001,66.78085],"type":"Point"}
}