{
  "type": "Feature",
  "properties": {
    "gn:admin1_code":"75",
    "gn:asciiname":"Mumyshevo",
    "gn:country_code":"RU",
    "gn:dem":54,
    "gn:feature_class":"P",
    "gn:feature_code":"PPL",
    "gn:name":"Mumyshevo",
    "gn:population":0,
    "gn:timezone":"Asia/Tomsk",
    "iso:country":"RU",
    "name:eng_x_preferred":[
        "Mumyshevo"
    ],
    "name:nor_x_preferred":[
        "Mumysjevo"
    ],
    "name:rus_x_preferred":[
        "\u041c\u0443\u043c\u044b\u0448\u0435\u0432\u043e"
    ],
    "name:und_x_variant":[
        "\u041c\u0443\u043c\u044b\u0448\u0435\u0432\u043e",
        "Mumyshevo"
    ],
    "wof:name":"Mumyshevo",
    "wof:placetype":"locality"
},
  "geometry": {"coordinates":[81.8875,58.63417],"type":"Point"}
}