{
  "type": "Feature",
  "properties": {
    "gn:admin1_code":"69",
    "gn:asciiname":"Ovsyaniki",
    "gn:country_code":"RU",
    "gn:dem":182,
    "gn:feature_class":"P",
    "gn:feature_code":"PPL",
    "gn:name":"Ovsyaniki",
    "gn:population":0,
    "gn:timezone":"Europe/Moscow",
    "iso:country":"RU",
    "name:und_x_variant":[
        "Obsyaniki"
    ],
    "wof:name":"Ovsyaniki",
    "wof:placetype":"locality"
},
  "geometry": {"coordinates":[34.51457,55.73046],"type":"Point"}
}