{
  "type": "Feature",
  "properties": {
    "gn:admin1_code":"53",
    "gn:asciiname":"Krasnoye Ozero",
    "gn:cc2":"RU",
    "gn:country_code":"RU",
    "gn:dem":127,
    "gn:feature_class":"P",
    "gn:feature_code":"PPL",
    "gn:name":"Krasnoye Ozero",
    "gn:population":0,
    "gn:timezone":"Asia/Novosibirsk",
    "iso:country":"RU",
    "name:rus_x_preferred":[
        "\u041a\u0440\u0430\u0441\u043d\u043e\u0435 \u041e\u0437\u0435\u0440\u043e"
    ],
    "name:und_x_variant":[
        "Krasno-Ozernyy",
        "Krasnoye Ozero"
    ],
    "wof:name":"Krasnoye Ozero",
    "wof:placetype":"locality"
},
  "geometry": {"coordinates":[83.88333,55.73333],"type":"Point"}
}