{
  "type": "Feature",
  "properties": {
    "gn:admin1_code":"34.0",
    "gn:asciiname":"Rakinskaya",
    "gn:country_code":"RU",
    "gn:dem":136,
    "gn:feature_class":"P",
    "gn:feature_code":"PPL",
    "gn:name":"Rakinskaya",
    "gn:population":0,
    "gn:timezone":"Europe/Moscow",
    "iso:country":"RU",
    "name:eng_x_preferred":[
        "Rakinskaya"
    ],
    "name:nor_x_preferred":[
        "Bor"
    ],
    "name:rus_x_preferred":[
        "\u0411\u043e\u0440"
    ],
    "name:rus_x_variant":[
        "\u0420\u0430\u043a\u0438\u043d\u0441\u043a\u0430\u044f"
    ],
    "name:und_x_variant":[
        "Bor-Rakinskiy"
    ],
    "wof:name":"Rakinskaya",
    "wof:placetype":"locality"
},
  "geometry": {"coordinates":[49.21657,60.65273000000001],"type":"Point"}
}