{
  "type": "Feature",
  "properties": {
    "gn:admin1_code":"90.0",
    "gn:asciiname":"Bol'shaya Kuzya",
    "gn:country_code":"RU",
    "gn:dem":195,
    "gn:feature_class":"P",
    "gn:feature_code":"PPL",
    "gn:name":"Bol\u2019shaya Kuzya",
    "gn:population":0,
    "gn:timezone":"Asia/Yekaterinburg",
    "iso:country":"RU",
    "name:rus_x_preferred":[
        "\u0411\u043e\u043b\u044c\u0448\u0430\u044f \u041a\u0443\u0437\u044f"
    ],
    "name:und_x_variant":[
        "Bol\u2019shaya Kuzya",
        "\u0411\u043e\u043b\u044c\u0448\u0430\u044f \u041a\u0443\u0437\u044f"
    ],
    "wof:name":"Bol'shaya Kuzya",
    "wof:placetype":"locality"
},
  "geometry": {"coordinates":[55.8135,57.1378],"type":"Point"}
}