{
  "type": "Feature",
  "properties": {
    "gn:admin1_code":"8",
    "gn:asciiname":"Shadali",
    "gn:country_code":"RU",
    "gn:dem":93,
    "gn:feature_class":"P",
    "gn:feature_code":"PPL",
    "gn:name":"Shadali",
    "gn:population":0,
    "gn:timezone":"Asia/Yekaterinburg",
    "iso:country":"RU",
    "name:rus_x_preferred":[
        "\u0428\u0430\u0434\u0430\u043b\u0438"
    ],
    "name:und_x_variant":[
        "\u0428\u0430\u0434\u0430\u043b\u0438"
    ],
    "wof:name":"Shadali",
    "wof:placetype":"locality"
},
  "geometry": {"coordinates":[54.47235,55.6949],"type":"Point"}
}