{
  "type": "Feature",
  "properties": {
    "gn:admin1_code":"69",
    "gn:asciiname":"Novyy Gorodok",
    "gn:cc2":"RU",
    "gn:country_code":"RU",
    "gn:dem":229,
    "gn:feature_class":"P",
    "gn:feature_code":"PPL",
    "gn:name":"Novyy Gorodok",
    "gn:population":0,
    "gn:timezone":"Europe/Moscow",
    "iso:country":"RU",
    "name:rus_x_preferred":[
        "\u041d\u043e\u0432\u044b\u0439 \u0413\u043e\u0440\u043e\u0434\u043e\u043a"
    ],
    "name:und_x_variant":[
        "Novy Gorodok",
        "Novyy Gorodok"
    ],
    "wof:name":"Novyy Gorodok",
    "wof:placetype":"locality"
},
  "geometry": {"coordinates":[33.71667,54.91667],"type":"Point"}
}