{
  "type": "Feature",
  "properties": {
    "gn:admin1_code":"77",
    "gn:asciiname":"Patrakovo",
    "gn:country_code":"RU",
    "gn:dem":202,
    "gn:feature_class":"P",
    "gn:feature_code":"PPL",
    "gn:name":"Patrakovo",
    "gn:population":0,
    "gn:timezone":"Europe/Moscow",
    "iso:country":"RU",
    "name:rus_x_preferred":[
        "\u041f\u0430\u0442\u0440\u0430\u043a\u043e\u0432\u043e"
    ],
    "wof:name":"Patrakovo",
    "wof:placetype":"locality"
},
  "geometry": {"coordinates":[34.69534,56.75165],"type":"Point"}
}