{
  "type": "Feature",
  "properties": {
    "gn:admin1_code":"88",
    "gn:asciiname":"Kholm",
    "gn:country_code":"RU",
    "gn:dem":140,
    "gn:feature_class":"P",
    "gn:feature_code":"PPL",
    "gn:name":"Kholm",
    "gn:population":0,
    "gn:timezone":"Europe/Moscow",
    "iso:country":"RU",
    "name:eng_x_preferred":[
        "Kholm"
    ],
    "name:nor_x_preferred":[
        "Kholm"
    ],
    "name:rus_x_preferred":[
        "\u0425\u043e\u043b\u043c"
    ],
    "name:und_x_variant":[
        "Kholm-Pyatnitskiy",
        "\u0425\u043e\u043b\u043c",
        "Kholm"
    ],
    "wof:name":"Kholm",
    "wof:placetype":"locality"
},
  "geometry": {"coordinates":[39.5184,58.28724],"type":"Point"}
}