{
  "type": "Feature",
  "properties": {
    "gn:admin1_code":"84",
    "gn:asciiname":"Lagutin",
    "gn:country_code":"RU",
    "gn:dem":47,
    "gn:feature_class":"P",
    "gn:feature_code":"PPL",
    "gn:name":"Lagutin",
    "gn:population":0,
    "gn:timezone":"Europe/Volgograd",
    "iso:country":"RU",
    "name:rus_x_preferred":[
        "\u041b\u0430\u0433\u0443\u0442\u0438\u043d"
    ],
    "name:und_x_variant":[
        "\u041b\u0430\u0433\u0443\u0442\u0438\u043d"
    ],
    "wof:name":"Lagutin",
    "wof:placetype":"locality"
},
  "geometry": {"coordinates":[42.40944,48.49694],"type":"Point"}
}