{
  "type": "Feature",
  "properties": {
    "gn:admin1_code":"60",
    "gn:asciiname":"Plavno",
    "gn:country_code":"RU",
    "gn:dem":210,
    "gn:feature_class":"P",
    "gn:feature_code":"PPL",
    "gn:name":"Plavno",
    "gn:population":0,
    "gn:timezone":"Europe/Moscow",
    "iso:country":"RU",
    "name:hrv_x_preferred":[
        "Plavno"
    ],
    "name:hun_x_preferred":[
        "Plavno"
    ],
    "name:rus_x_preferred":[
        "\u041f\u043b\u0430\u0432\u043d\u043e"
    ],
    "name:slk_x_preferred":[
        "Plavno"
    ],
    "name:und_x_variant":[
        "\u041f\u043b\u0430\u0432\u043d\u043e"
    ],
    "wof:name":"Plavno",
    "wof:placetype":"locality"
},
  "geometry": {"coordinates":[29.4545,56.845],"type":"Point"}
}