{
  "type": "Feature",
  "properties": {
    "gn:admin1_code":"73",
    "gn:asciiname":"Maloye Kobzevo",
    "gn:country_code":"RU",
    "gn:dem":74,
    "gn:feature_class":"P",
    "gn:feature_code":"PPL",
    "gn:name":"Maloye Kobzevo",
    "gn:population":0,
    "gn:timezone":"Europe/Moscow",
    "iso:country":"RU",
    "name:rus_x_preferred":[
        "\u041c\u0430\u043b\u043e\u0435 \u041a\u043e\u0431\u0437\u0435\u0432\u043e"
    ],
    "wof:name":"Maloye Kobzevo",
    "wof:placetype":"locality"
},
  "geometry": {"coordinates":[48.31667,55.45],"type":"Point"}
}