{
  "type": "Feature",
  "properties": {
    "gn:admin1_code":"33.0",
    "gn:asciiname":"Luginovka",
    "gn:country_code":"RU",
    "gn:dem":150,
    "gn:feature_class":"P",
    "gn:feature_code":"PPL",
    "gn:name":"Luginovka",
    "gn:population":0,
    "gn:timezone":"Europe/Kirov",
    "iso:country":"RU",
    "name:rus_x_preferred":[
        "\u041b\u0443\u0433\u0438\u043d\u043e\u0432\u043a\u0430"
    ],
    "wof:name":"Luginovka",
    "wof:placetype":"locality"
},
  "geometry": {"coordinates":[48.88549,58.55138],"type":"Point"}
}