{
  "type": "Feature",
  "properties": {
    "gn:admin1_code":"45",
    "gn:asciiname":"Malyy Sabaner",
    "gn:country_code":"RU",
    "gn:dem":173,
    "gn:feature_class":"P",
    "gn:feature_code":"PPL",
    "gn:name":"Malyy Sabaner",
    "gn:population":0,
    "gn:timezone":"Europe/Moscow",
    "iso:country":"RU",
    "name:rus_x_preferred":[
        "\u041c\u0430\u043b\u044b\u0439 \u0421\u0430\u0431\u0430\u043d\u0435\u0440"
    ],
    "name:und_x_variant":[
        "Malyy Sabiner",
        "Malyy Sabaner",
        "\u041c\u0430\u043b\u044b\u0439 \u0421\u0430\u0431\u0430\u043d\u0435\u0440"
    ],
    "wof:name":"Malyy Sabaner",
    "wof:placetype":"locality"
},
  "geometry": {"coordinates":[48.92056,56.84333],"type":"Point"}
}