{
  "type": "Feature",
  "properties": {
    "gn:admin1_code":"54",
    "gn:asciiname":"Pesochno",
    "gn:cc2":"RU",
    "gn:country_code":"RU",
    "gn:dem":119,
    "gn:feature_class":"P",
    "gn:feature_code":"PPL",
    "gn:name":"Pesochno",
    "gn:population":0,
    "gn:timezone":"Asia/Omsk",
    "iso:country":"RU",
    "name:rus_x_preferred":[
        "\u041f\u0435\u0441\u043e\u0447\u043d\u043e"
    ],
    "name:und_x_variant":[
        "Pesochnyy",
        "Pesochno"
    ],
    "wof:name":"Pesochno",
    "wof:placetype":"locality"
},
  "geometry": {"coordinates":[76.23333000000002,56.86666999999999],"type":"Point"}
}