{
  "type": "Feature",
  "properties": {
    "gn:admin1_code":"88",
    "gn:asciiname":"Kargashino",
    "gn:country_code":"RU",
    "gn:dem":170,
    "gn:feature_class":"P",
    "gn:feature_code":"PPL",
    "gn:name":"Kargashino",
    "gn:population":0,
    "gn:timezone":"Europe/Moscow",
    "iso:country":"RU",
    "name:rus_x_preferred":[
        "\u041a\u0430\u0440\u0433\u0430\u0448\u0438\u043d\u043e"
    ],
    "name:und_x_variant":[
        "\u041a\u0430\u0440\u0433\u0430\u0448\u0438\u043d\u043e"
    ],
    "wof:name":"Kargashino",
    "wof:placetype":"locality"
},
  "geometry": {"coordinates":[38.4659,57.0647],"type":"Point"}
}