{
  "type": "Feature",
  "properties": {
    "gn:admin1_code":"8.0",
    "gn:asciiname":"Burangulovo",
    "gn:country_code":"RU",
    "gn:dem":554,
    "gn:feature_class":"P",
    "gn:feature_code":"PPL",
    "gn:name":"Burangulovo",
    "gn:population":0,
    "gn:timezone":"Asia/Yekaterinburg",
    "iso:country":"RU",
    "name:aze_x_preferred":[
        "Buranqol"
    ],
    "name:bak_x_preferred":[
        "\u0411\u0443\u0440\u0430\u043d\u0493\u043e\u043b"
    ],
    "name:che_x_preferred":[
        "\u0411\u0443\u0440\u0430\u043d\u0433\u0443\u043b\u043e\u0432\u043e"
    ],
    "name:eng_x_preferred":[
        "Burangulovo"
    ],
    "name:hye_x_preferred":[
        "\u0532\u0578\u0582\u0580\u0561\u0576\u0563\u0578\u0582\u056c\u0578\u057e\u0578"
    ],
    "name:kat_x_preferred":[
        "\u10d1\u10e3\u10e0\u10d0\u10dc\u10d2\u10e3\u10da\u10dd\u10d5\u10dd"
    ],
    "name:kaz_x_preferred":[
        "\u0411\u0443\u0440\u0430\u043d\u0433\u04af\u043b"
    ],
    "name:kir_x_preferred":[
        "\u0411\u0443\u0440\u0430\u043d\u0433\u04af\u043b"
    ],
    "name:nor_x_preferred":[
        "Burangulovo"
    ],
    "name:rus_x_preferred":[
        "\u0411\u0443\u0440\u0430\u043d\u0433\u0443\u043b\u043e\u0432\u043e"
    ],
    "name:tat_x_preferred":[
        "\u0411\u0443\u0440\u0430\u043d\u0433\u0443\u043b"
    ],
    "name:ukr_x_preferred":[
        "\u0411\u0443\u0440\u0430\u043d\u0433\u0443\u043b\u043e\u0432\u043e"
    ],
    "wof:name":"Burangulovo",
    "wof:placetype":"locality"
},
  "geometry": {"coordinates":[58.3478,53.4718],"type":"Point"}
}