{
  "type": "Feature",
  "properties": {
    "gn:admin1_code":"8.0",
    "gn:asciiname":"Burangulovo",
    "gn:country_code":"RU",
    "gn:dem":554,
    "gn:feature_class":"P",
    "gn:feature_code":"PPL",
    "gn:name":"Burangulovo",
    "gn:population":0,
    "gn:timezone":"Asia/Yekaterinburg",
    "iso:country":"RU",
    "name:eng_x_preferred":[
        "Burangulovo"
    ],
    "name:nor_x_preferred":[
        "Burangulovo"
    ],
    "name:rus_x_preferred":[
        "\u0411\u0443\u0440\u0430\u043d\u0433\u0443\u043b\u043e\u0432\u043e"
    ],
    "name:und_x_variant":[
        "\u0411\u0443\u0440\u0430\u043d\u0433\u0443\u043b\u043e\u0432\u043e",
        "Burangulovo"
    ],
    "wof:name":"Burangulovo",
    "wof:placetype":"locality"
},
  "geometry": {"coordinates":[58.3478,53.4718],"type":"Point"}
}