{
  "type": "Feature",
  "properties": {
    "gn:country":"RU",
    "gn:fcode":"PPL",
    "gn:pop":2860,
    "iso:country":"RU",
    "name:nor_x_preferred":[
        "Kuminskij"
    ],
    "name:rus_x_preferred":[
        "\u041a\u0443\u043c\u0438\u043d\u0441\u043a\u0438\u0439"
    ],
    "name:unk_x_variant":[
        "\u041a\u0443\u043c\u0438\u043d\u0441\u043a\u0438\u0439"
    ],
    "qs:name":"Kuminskiy",
    "qs:photos_9r":0,
    "qs:photos_sr":0,
    "qs:pop_sr":"4",
    "wof:name":"Kuminskiy",
    "wof:placetype":"locality",
    "wof:population":2860
},
  "geometry": {"coordinates":[66.56667,58.66667],"type":"Point"}
}