{
  "type": "Feature",
  "properties": {
    "gn:admin1_code":"63",
    "gn:asciiname":"Khadysa",
    "gn:country_code":"RU",
    "gn:dem":122,
    "gn:feature_class":"P",
    "gn:feature_code":"PPL",
    "gn:name":"Khadysa",
    "gn:population":0,
    "gn:timezone":"Asia/Vladivostok",
    "iso:country":"RU",
    "name:rus_x_preferred":[
        "\u0425\u0430\u0434\u044b\u0441\u0430"
    ],
    "name:und_x_variant":[
        "\u0425\u0430\u0434\u044b\u0441\u0430"
    ],
    "wof:name":"Khadysa",
    "wof:placetype":"locality"
},
  "geometry": {"coordinates":[135.19999999999999,68.46666999999999],"type":"Point"}
}