{
  "type": "Feature",
  "properties": {
    "gn:admin1_code":"77",
    "gn:asciiname":"Dmitrovka",
    "gn:country_code":"RU",
    "gn:dem":178,
    "gn:feature_class":"P",
    "gn:feature_code":"PPL",
    "gn:name":"Dmitrovka",
    "gn:population":0,
    "gn:timezone":"Europe/Moscow",
    "iso:country":"RU",
    "name:rus_x_preferred":[
        "\u0414\u043c\u0438\u0442\u0440\u043e\u0432\u043a\u0430"
    ],
    "name:und_x_variant":[
        "\u0414\u043c\u0438\u0442\u0440\u043e\u0432\u043a\u0430"
    ],
    "wof:name":"Dmitrovka",
    "wof:placetype":"locality"
},
  "geometry": {"coordinates":[37.0442,58.2431],"type":"Point"}
}