{
  "type": "Feature",
  "properties": {
    "gn:admin1_code":"10.0",
    "gn:asciiname":"Poboynaya",
    "gn:country_code":"RU",
    "gn:dem":190,
    "gn:feature_class":"P",
    "gn:feature_code":"PPL",
    "gn:name":"Poboynaya",
    "gn:population":0,
    "gn:timezone":"Europe/Moscow",
    "iso:country":"RU",
    "name:rus_x_preferred":[
        "\u041f\u043e\u0431\u043e\u0439\u043d\u0430\u044f"
    ],
    "wof:name":"Poboynaya",
    "wof:placetype":"locality"
},
  "geometry": {"coordinates":[33.46562,53.6817],"type":"Point"}
}