{
  "type": "Feature",
  "properties": {
    "gn:admin1_code":"62",
    "gn:asciiname":"Ogibalovo",
    "gn:country_code":"RU",
    "gn:dem":179,
    "gn:feature_class":"P",
    "gn:feature_code":"PPL",
    "gn:name":"Ogibalovo",
    "gn:population":0,
    "gn:timezone":"Europe/Moscow",
    "iso:country":"RU",
    "name:rus_x_preferred":[
        "\u041e\u0433\u0438\u0431\u0430\u043b\u043e\u0432\u043e"
    ],
    "wof:name":"Ogibalovo",
    "wof:placetype":"locality"
},
  "geometry": {"coordinates":[38.90728,54.04657],"type":"Point"}
}