{
  "type": "Feature",
  "properties": {
    "iso:country":"RU",
    "name:rus_x_preferred":[
        "\u0413\u043e\u0440\u0435\u043b\u043e\u0432\u043e"
    ],
    "wof:name":"Gorelovo",
    "wof:placetype":"neighbourhood"
},
  "geometry": {"coordinates":[30.13487023946109,59.77988251299035],"type":"Point"}
}