{
  "type": "Feature",
  "properties": {
    "gn:admin1_code":"88",
    "gn:asciiname":"Smentsevo",
    "gn:country_code":"RU",
    "gn:dem":115,
    "gn:feature_class":"P",
    "gn:feature_code":"PPL",
    "gn:name":"Smentsevo",
    "gn:population":8,
    "gn:timezone":"Europe/Moscow",
    "iso:country":"RU",
    "name:rus_x_preferred":[
        "\u0421\u043c\u0435\u043d\u0446\u0435\u0432\u043e"
    ],
    "name:und_x_variant":[
        "\u0421\u043c\u0435\u043d\u0446\u0435\u0432\u043e"
    ],
    "wof:name":"Smentsevo",
    "wof:placetype":"locality",
    "wof:population":8
},
  "geometry": {"coordinates":[38.42576,57.99344],"type":"Point"}
}