{
  "type": "Feature",
  "properties": {
    "gn:admin1_code":"93",
    "gn:asciiname":"Shapka",
    "gn:country_code":"RU",
    "gn:dem":495,
    "gn:feature_class":"P",
    "gn:feature_code":"PPL",
    "gn:name":"Shapka",
    "gn:population":0,
    "gn:timezone":"Asia/Chita",
    "iso:country":"RU",
    "name:rus_x_preferred":[
        "\u0428\u0430\u043f\u043a\u0430"
    ],
    "name:und_x_variant":[
        "Shanka",
        "Shapka"
    ],
    "wof:name":"Shapka",
    "wof:placetype":"locality"
},
  "geometry": {"coordinates":[117.03351000000001,52.16267],"type":"Point"}
}