{
  "type": "Feature",
  "properties": {
    "gn:admin1_code":"73",
    "gn:asciiname":"Staryy Tokmak",
    "gn:country_code":"RU",
    "gn:dem":66,
    "gn:feature_class":"P",
    "gn:feature_code":"PPL",
    "gn:name":"Staryy Tokmak",
    "gn:population":0,
    "gn:timezone":"Europe/Moscow",
    "iso:country":"RU",
    "name:eng_x_preferred":[
        "Staryy Tokmak"
    ],
    "name:nor_x_preferred":[
        "Staryj Tokmak"
    ],
    "name:rus_x_preferred":[
        "\u0421\u0442\u0430\u0440\u044b\u0439 \u0422\u043e\u043a\u043c\u0430\u043a"
    ],
    "name:und_x_variant":[
        "Stary Tokmak"
    ],
    "wof:name":"Staryy Tokmak",
    "wof:placetype":"locality"
},
  "geometry": {"coordinates":[51.98247,55.39136],"type":"Point"}
}