{
  "type": "Feature",
  "properties": {
    "gn:admin1_code":"91.0",
    "gn:asciiname":"Nyasha",
    "gn:country_code":"RU",
    "gn:dem":128,
    "gn:feature_class":"P",
    "gn:feature_code":"PPL",
    "gn:name":"Nyasha",
    "gn:population":0,
    "gn:timezone":"Asia/Krasnoyarsk",
    "iso:country":"RU",
    "name:rus_x_preferred":[
        "\u041d\u044f\u0448\u0430"
    ],
    "wof:name":"Nyasha",
    "wof:placetype":"locality"
},
  "geometry": {"coordinates":[93.17278,56.08714000000001],"type":"Point"}
}