{
  "type": "Feature",
  "properties": {
    "gn:admin1_code":"55",
    "gn:asciiname":"Kisla",
    "gn:country_code":"RU",
    "gn:dem":137,
    "gn:feature_class":"P",
    "gn:feature_code":"PPL",
    "gn:name":"Kisla",
    "gn:population":0,
    "gn:timezone":"Asia/Yekaterinburg",
    "iso:country":"RU",
    "name:eng_x_preferred":[
        "Kisla"
    ],
    "name:nor_x_preferred":[
        "Kisla"
    ],
    "name:rus_x_preferred":[
        "\u041a\u0438\u0441\u043b\u0430"
    ],
    "name:und_x_variant":[
        "\u041a\u0438\u0441\u043b\u0430",
        "Kisla"
    ],
    "wof:name":"Kisla",
    "wof:placetype":"locality"
},
  "geometry": {"coordinates":[52.85263000000001,53.65445],"type":"Point"}
}