{
  "type": "Feature",
  "properties": {
    "gn:admin1_code":"75",
    "gn:asciiname":"Chernaya Rechka",
    "gn:country_code":"RU",
    "gn:dem":80,
    "gn:feature_class":"P",
    "gn:feature_code":"PPL",
    "gn:name":"Ch\u00ebrnaya Rechka",
    "gn:population":0,
    "gn:timezone":"Asia/Tomsk",
    "iso:country":"RU",
    "name:eng_x_preferred":[
        "Ch\u00ebrnaya Rechka"
    ],
    "name:rus_x_preferred":[
        "\u0427\u0435\u0440\u043d\u0430\u044f \u0420\u0435\u0447\u043a\u0430"
    ],
    "name:rus_x_variant":[
        "\u0427\u0451\u0440\u043d\u0430\u044f \u0420\u0435\u0447\u043a\u0430"
    ],
    "name:und_x_variant":[
        "Yurty Chernorechenskiye"
    ],
    "wof:name":"Chernaya Rechka",
    "wof:placetype":"locality"
},
  "geometry": {"coordinates":[84.91428000000001,56.39995],"type":"Point"}
}