{
  "type": "Feature",
  "properties": {
    "gn:admin1_code":"93",
    "gn:asciiname":"Bil'chir",
    "gn:country_code":"RU",
    "gn:dem":860,
    "gn:feature_class":"P",
    "gn:feature_code":"PPL",
    "gn:name":"Bil\u2019chir",
    "gn:population":0,
    "gn:timezone":"Asia/Chita",
    "iso:country":"RU",
    "name:rus_x_preferred":[
        "\u0411\u0438\u043b\u044c\u0447\u0438\u0440"
    ],
    "name:und_x_variant":[
        "Bil\u2019chir"
    ],
    "wof:name":"Bil'chir",
    "wof:placetype":"locality"
},
  "geometry": {"coordinates":[107.81667,50.05],"type":"Point"}
}