{
  "type": "Feature",
  "properties": {
    "gn:admin1_code":"8.0",
    "gn:asciiname":"Burtakovka",
    "gn:country_code":"RU",
    "gn:dem":246,
    "gn:feature_class":"P",
    "gn:feature_code":"PPL",
    "gn:name":"Burtakovka",
    "gn:population":0,
    "gn:timezone":"Asia/Yekaterinburg",
    "iso:country":"RU",
    "name:rus_x_preferred":[
        "\u0411\u0443\u0440\u0442\u0430\u043a\u043e\u0432\u043a\u0430"
    ],
    "name:und_x_variant":[
        "Bartukovka",
        "Burtakovka",
        "\u0411\u0443\u0440\u0442\u0430\u043a\u043e\u0432\u043a\u0430"
    ],
    "wof:name":"Burtakovka",
    "wof:placetype":"locality"
},
  "geometry": {"coordinates":[58.10944,55.89889],"type":"Point"}
}