{
  "type": "Feature",
  "properties": {
    "gn:admin1_code":"69",
    "gn:asciiname":"Pyzhovka",
    "gn:country_code":"RU",
    "gn:dem":225,
    "gn:feature_class":"P",
    "gn:feature_code":"PPL",
    "gn:name":"Pyzhovka",
    "gn:population":0,
    "gn:timezone":"Europe/Moscow",
    "iso:country":"RU",
    "name:rus_x_preferred":[
        "\u041f\u044b\u0436\u043e\u0432\u043a\u0430"
    ],
    "name:und_x_variant":[
        "Chernoye"
    ],
    "wof:name":"Pyzhovka",
    "wof:placetype":"locality"
},
  "geometry": {"coordinates":[34.48103,55.18247],"type":"Point"}
}