{
  "type": "Feature",
  "properties": {
    "gn:admin1_code":"54",
    "gn:asciiname":"Khmelevka",
    "gn:country_code":"RU",
    "gn:dem":128,
    "gn:feature_class":"P",
    "gn:feature_code":"PPL",
    "gn:name":"Khmel\u00ebvka",
    "gn:population":0,
    "gn:timezone":"Asia/Omsk",
    "iso:country":"RU",
    "name:eng_x_preferred":[
        "Khmel\u00ebvka"
    ],
    "name:nor_x_preferred":[
        "Khmelevka"
    ],
    "name:rus_x_preferred":[
        "\u0425\u043c\u0435\u043b\u0435\u0432\u043a\u0430"
    ],
    "name:rus_x_variant":[
        "\u0425\u043c\u0435\u043b\u0451\u0432\u043a\u0430"
    ],
    "name:und_x_variant":[
        "Khmelevskiy"
    ],
    "wof:name":"Khmelevka",
    "wof:placetype":"locality"
},
  "geometry": {"coordinates":[75.26853,56.82304],"type":"Point"}
}