{
  "type": "Feature",
  "properties": {
    "gn:admin1_code":"41",
    "gn:asciiname":"Khvorostyanka",
    "gn:country_code":"RU",
    "gn:dem":163,
    "gn:feature_class":"P",
    "gn:feature_code":"PPL",
    "gn:name":"Khvorostyanka",
    "gn:population":0,
    "gn:timezone":"Europe/Moscow",
    "iso:country":"RU",
    "name:rus_x_preferred":[
        "\u0425\u0432\u043e\u0440\u043e\u0441\u0442\u044f\u043d\u043a\u0430"
    ],
    "wof:name":"Khvorostyanka",
    "wof:placetype":"locality"
},
  "geometry": {"coordinates":[37.3161,51.8678],"type":"Point"}
}