{
  "type": "Feature",
  "properties": {
    "gn:admin1_code":"56",
    "gn:asciiname":"Pavlovskiy",
    "gn:country_code":"RU",
    "gn:dem":198,
    "gn:feature_class":"P",
    "gn:feature_code":"PPL",
    "gn:name":"Pavlovskiy",
    "gn:population":0,
    "gn:timezone":"Europe/Moscow",
    "iso:country":"RU",
    "wof:name":"Pavlovskiy",
    "wof:placetype":"locality"
},
  "geometry": {"coordinates":[36.00889,53.31916999999999],"type":"Point"}
}