{
  "type": "Feature",
  "properties": {
    "gn:admin1_code":"38",
    "gn:asciiname":"Pervoye Maya",
    "gn:cc2":"RU",
    "gn:country_code":"RU",
    "gn:dem":95,
    "gn:feature_class":"P",
    "gn:feature_code":"PPL",
    "gn:name":"Pervoye Maya",
    "gn:population":0,
    "gn:timezone":"Europe/Moscow",
    "iso:country":"RU",
    "name:ceb_x_preferred":[
        "Pervoye Maya"
    ],
    "name:swe_x_preferred":[
        "Pervoye Maya"
    ],
    "name:und_x_variant":[
        "Pervomayskiy"
    ],
    "wof:name":"Pervoye Maya",
    "wof:placetype":"locality"
},
  "geometry": {"coordinates":[40.83306,45.38306],"type":"Point"}
}