{
  "type": "Feature",
  "properties": {
    "gn:admin1_code":"65",
    "gn:asciiname":"V'yushkovo",
    "gn:country_code":"RU",
    "gn:dem":128,
    "gn:feature_class":"P",
    "gn:feature_code":"PPL",
    "gn:name":"V\u2019yushkovo",
    "gn:population":0,
    "gn:timezone":"Europe/Samara",
    "iso:country":"RU",
    "name:rus_x_preferred":[
        "V\u2019yushkovo"
    ],
    "name:rus_x_variant":[
        "\u0412\u044c\u044e\u0448\u043a\u043e\u0432\u043e",
        "V\u2019yushkov"
    ],
    "wof:name":"V'yushkovo",
    "wof:placetype":"locality"
},
  "geometry": {"coordinates":[49.7225,52.6886],"type":"Point"}
}