{
  "type": "Feature",
  "properties": {
    "gn:admin1_code":"15",
    "gn:asciiname":"Meynynytum",
    "gn:cc2":"RU",
    "gn:country_code":"RU",
    "gn:dem":-9999,
    "gn:feature_class":"P",
    "gn:feature_code":"PPL",
    "gn:name":"Meynynytum",
    "gn:population":0,
    "gn:timezone":"Asia/Anadyr",
    "iso:country":"RU",
    "name:rus_x_preferred":[
        "\u041c\u0435\u0439\u043d\u044b\u043d\u044b\u0442\u0443\u043c"
    ],
    "name:und_x_variant":[
        "Meyn\u00f6n\u00f6tum",
        "Meynynytum"
    ],
    "wof:name":"Meynynytum",
    "wof:placetype":"locality"
},
  "geometry": {"coordinates":[-179.69999999999999,65.13333],"type":"Point"}
}