{
  "type": "Feature",
  "properties": {
    "gn:admin1_code":"88.0",
    "gn:asciiname":"Dakar'",
    "gn:country_code":"RU",
    "gn:dem":123,
    "gn:feature_class":"P",
    "gn:feature_code":"PPL",
    "gn:name":"Dakar\u2019",
    "gn:population":0,
    "gn:timezone":"Europe/Moscow",
    "iso:country":"RU",
    "name:rus_x_preferred":[
        "\u0414\u0430\u043a\u0430\u0440\u044c"
    ],
    "name:und_x_variant":[
        "Dakar\u2019",
        "\u0414\u0430\u043a\u0430\u0440\u044c"
    ],
    "wof:name":"Dakar'",
    "wof:placetype":"locality"
},
  "geometry": {"coordinates":[40.33326,58.16346],"type":"Point"}
}