{
  "type": "Feature",
  "properties": {
    "gn:admin1_code":"47",
    "gn:asciiname":"Malyye Semenychi",
    "gn:country_code":"RU",
    "gn:dem":181,
    "gn:feature_class":"P",
    "gn:feature_code":"PPL",
    "gn:name":"Malyye Sem\u00ebnychi",
    "gn:population":0,
    "gn:timezone":"Europe/Moscow",
    "iso:country":"RU",
    "name:rus_x_preferred":[
        "\u041c\u0430\u043b\u044b\u0435 \u0421\u0435\u043c\u0451\u043d\u044b\u0447\u0438"
    ],
    "name:und_x_variant":[
        "Malyye Sem\u00ebnychi",
        "\u041c\u0430\u043b\u044b\u0435 \u0421\u0435\u043c\u0451\u043d\u044b\u0447\u0438"
    ],
    "wof:name":"Malyye Semenychi",
    "wof:placetype":"locality"
},
  "geometry": {"coordinates":[36.68444,55.46312],"type":"Point"}
}