{
  "type": "Feature",
  "properties": {
    "gn:admin1_code":"84",
    "gn:asciiname":"Solov'yevskiy",
    "gn:country_code":"RU",
    "gn:dem":99,
    "gn:feature_class":"P",
    "gn:feature_code":"PPL",
    "gn:name":"Solov\u2019y\u00ebvskiy",
    "gn:population":0,
    "gn:timezone":"Europe/Volgograd",
    "iso:country":"RU",
    "name:rus_x_preferred":[
        "\u0421\u043e\u043b\u043e\u0432\u044c\u0451\u0432\u0441\u043a\u0438\u0439"
    ],
    "name:und_x_variant":[
        "Solov\u2019y\u00ebv",
        "Solov\u2019y\u00ebvskiy"
    ],
    "wof:name":"Solov'yevskiy",
    "wof:placetype":"locality"
},
  "geometry": {"coordinates":[42.6408,50.3831],"type":"Point"}
}