{
  "type": "Feature",
  "properties": {
    "gn:admin1_code":"38",
    "gn:asciiname":"Novoukrainskiy",
    "gn:country_code":"RU",
    "gn:dem":282,
    "gn:feature_class":"P",
    "gn:feature_code":"PPL",
    "gn:name":"Novoukrainskiy",
    "gn:population":0,
    "gn:timezone":"Europe/Moscow",
    "iso:country":"RU",
    "wof:name":"Novoukrainskiy",
    "wof:placetype":"locality"
},
  "geometry": {"coordinates":[41.00444,44.76583],"type":"Point"}
}