{
  "type": "Feature",
  "properties": {
    "gn:admin1_code":"77",
    "gn:asciiname":"Zaytsevo",
    "gn:country_code":"RU",
    "gn:dem":84,
    "gn:feature_class":"P",
    "gn:feature_code":"PPL",
    "gn:name":"Zaytsevo",
    "gn:population":0,
    "gn:timezone":"Europe/Moscow",
    "iso:country":"RU",
    "name:rus_x_preferred":[
        "\u0417\u0430\u0439\u0446\u0435\u0432\u043e"
    ],
    "wof:name":"Zaytsevo",
    "wof:placetype":"locality"
},
  "geometry": {"coordinates":[31.09168,56.88165],"type":"Point"}
}