{
  "type": "Feature",
  "properties": {
    "gn:admin1_code":"71",
    "gn:asciiname":"Fomina",
    "gn:country_code":"RU",
    "gn:dem":76,
    "gn:feature_class":"P",
    "gn:feature_code":"PPL",
    "gn:name":"Fomina",
    "gn:population":0,
    "gn:timezone":"Asia/Yekaterinburg",
    "iso:country":"RU",
    "name:rus_x_preferred":[
        "\u0424\u043e\u043c\u0438\u043d\u0430"
    ],
    "name:und_x_variant":[
        "\u0424\u043e\u043c\u0438\u043d\u0430"
    ],
    "wof:name":"Fomina",
    "wof:placetype":"locality"
},
  "geometry": {"coordinates":[62.63333000000001,57.38333000000001],"type":"Point"}
}