{
  "type": "Feature",
  "properties": {
    "gn:admin1_code":"11",
    "gn:asciiname":"Undur-Mayla",
    "gn:country_code":"RU",
    "gn:dem":765,
    "gn:feature_class":"P",
    "gn:feature_code":"PPL",
    "gn:name":"Undur-Mayla",
    "gn:population":0,
    "gn:timezone":"Asia/Irkutsk",
    "iso:country":"RU",
    "wof:name":"Undur-Mayla",
    "wof:placetype":"locality"
},
  "geometry": {"coordinates":[109.73333,52.36667],"type":"Point"}
}