{
  "type": "Feature",
  "properties": {
    "gn:admin1_code":"77",
    "gn:asciiname":"Novyye Polya",
    "gn:country_code":"RU",
    "gn:dem":230,
    "gn:feature_class":"P",
    "gn:feature_code":"PPL",
    "gn:name":"Novyye Polya",
    "gn:population":0,
    "gn:timezone":"Europe/Moscow",
    "iso:country":"RU",
    "name:rus_x_preferred":[
        "\u041d\u043e\u0432\u044b\u0435 \u041f\u043e\u043b\u044f"
    ],
    "name:und_x_variant":[
        "\u041d\u043e\u0432\u044b\u0435 \u041f\u043e\u043b\u044f"
    ],
    "wof:name":"Novyye Polya",
    "wof:placetype":"locality"
},
  "geometry": {"coordinates":[33.46667,57.05],"type":"Point"}
}