{
  "type": "Feature",
  "properties": {
    "gn:admin1_code":"85.0",
    "gn:asciiname":"Argunovo",
    "gn:country_code":"RU",
    "gn:dem":152,
    "gn:feature_class":"P",
    "gn:feature_code":"PPL",
    "gn:name":"Argunovo",
    "gn:population":0,
    "gn:timezone":"Europe/Moscow",
    "iso:country":"RU",
    "name:nor_x_preferred":[
        "Argunjovo"
    ],
    "name:rus_x_preferred":[
        "\u0410\u0440\u0433\u0443\u043d\u043e\u0432\u043e"
    ],
    "name:und_x_variant":[
        "Argutevo",
        "Argunovo",
        "\u0410\u0440\u0433\u0443\u043d\u043e\u0432\u043e",
        "Argun\u00ebvo"
    ],
    "wof:name":"Argunovo",
    "wof:placetype":"locality"
},
  "geometry": {"coordinates":[38.90761,59.86596],"type":"Point"}
}