{
  "type": "Feature",
  "properties": {
    "gn:admin1_code":"80.0",
    "gn:asciiname":"Dyrpa",
    "gn:country_code":"RU",
    "gn:dem":205,
    "gn:feature_class":"P",
    "gn:feature_code":"PPL",
    "gn:name":"Dyrpa",
    "gn:population":0,
    "gn:timezone":"Europe/Samara",
    "iso:country":"RU",
    "name:eng_x_preferred":[
        "Dyrpa"
    ],
    "name:nor_x_preferred":[
        "Dyrla"
    ],
    "name:rus_x_preferred":[
        "\u0414\u044b\u0440\u043b\u0430"
    ],
    "name:rus_x_variant":[
        "\u0414\u044b\u0440\u043f\u0430"
    ],
    "name:und_x_variant":[
        "Dyrpinskaya"
    ],
    "wof:name":"Dyrpa",
    "wof:placetype":"locality"
},
  "geometry": {"coordinates":[53.4228,58.0522],"type":"Point"}
}