{
  "type": "Feature",
  "properties": {
    "gn:admin1_code":"52",
    "gn:asciiname":"Krivandino",
    "gn:country_code":"RU",
    "gn:dem":167,
    "gn:feature_class":"P",
    "gn:feature_code":"PPL",
    "gn:name":"Krivandino",
    "gn:population":0,
    "gn:timezone":"Europe/Moscow",
    "iso:country":"RU",
    "name:rus_x_preferred":[
        "\u041a\u0440\u0438\u0432\u0430\u043d\u0434\u0438\u043d\u043e"
    ],
    "name:und_x_variant":[
        "\u041a\u0440\u0438\u0432\u0430\u043d\u0434\u0438\u043d\u043e"
    ],
    "wof:name":"Krivandino",
    "wof:placetype":"locality"
},
  "geometry": {"coordinates":[34.63333,58.98333],"type":"Point"}
}