{
  "type": "Feature",
  "properties": {
    "gn:admin1_code":"30",
    "gn:asciiname":"Yagdyn'ya",
    "gn:country_code":"RU",
    "gn:dem":392,
    "gn:feature_class":"P",
    "gn:feature_code":"PPL",
    "gn:name":"Yagdyn\u2019ya",
    "gn:population":0,
    "gn:timezone":"Asia/Vladivostok",
    "iso:country":"RU",
    "name:eng_x_preferred":[
        "Yagdyn'ya"
    ],
    "name:nor_x_preferred":[
        "Jagdynja"
    ],
    "name:rus_x_preferred":[
        "\u042f\u0433\u0434\u044b\u043d\u044c\u044f"
    ],
    "name:und_x_variant":[
        "Yagdyn\u2019ya"
    ],
    "wof:name":"Yagdyn'ya",
    "wof:placetype":"locality"
},
  "geometry": {"coordinates":[132.40061,50.59657],"type":"Point"}
}