{
  "type": "Feature",
  "properties": {
    "gn:admin1_code":"25",
    "gn:asciiname":"Vesniny",
    "gn:country_code":"RU",
    "gn:dem":196,
    "gn:feature_class":"P",
    "gn:feature_code":"PPL",
    "gn:name":"Vesniny",
    "gn:population":0,
    "gn:timezone":"Europe/Moscow",
    "iso:country":"RU",
    "name:eng_x_preferred":[
        "Vesniny"
    ],
    "name:nor_x_preferred":[
        "Vesniny"
    ],
    "name:rus_x_preferred":[
        "\u0412\u0435\u0441\u043d\u0438\u043d\u044b"
    ],
    "wof:name":"Vesniny",
    "wof:placetype":"locality"
},
  "geometry": {"coordinates":[35.44312,53.62893],"type":"Point"}
}