{
  "type": "Feature",
  "properties": {
    "gn:admin1_code":"33",
    "gn:asciiname":"Shesteryata",
    "gn:country_code":"RU",
    "gn:dem":158,
    "gn:feature_class":"P",
    "gn:feature_code":"PPL",
    "gn:name":"Shesteryata",
    "gn:population":0,
    "gn:timezone":"Europe/Kirov",
    "iso:country":"RU",
    "name:rus_x_preferred":[
        "\u0428\u0435\u0441\u0442\u0435\u0440\u044f\u0442\u0430"
    ],
    "wof:name":"Shesteryata",
    "wof:placetype":"locality"
},
  "geometry": {"coordinates":[49.8824,58.0786],"type":"Point"}
}