{
  "type": "Feature",
  "properties": {
    "gn:admin1_code":"56",
    "gn:asciiname":"Yarishche",
    "gn:country_code":"RU",
    "gn:dem":210,
    "gn:feature_class":"P",
    "gn:feature_code":"PPL",
    "gn:name":"Yarishche",
    "gn:population":0,
    "gn:timezone":"Europe/Moscow",
    "iso:country":"RU",
    "name:eng_x_preferred":[
        "Yarishche"
    ],
    "name:nor_x_preferred":[
        "Jarisjtsje"
    ],
    "name:rus_x_preferred":[
        "\u042f\u0440\u0438\u0449\u0435"
    ],
    "name:und_x_variant":[
        "Yarishe"
    ],
    "wof:name":"Yarishche",
    "wof:placetype":"locality"
},
  "geometry": {"coordinates":[37.14221,52.24767],"type":"Point"}
}