{
  "type": "Feature",
  "properties": {
    "gn:admin1_code":"16",
    "gn:asciiname":"Adikasy",
    "gn:country_code":"RU",
    "gn:dem":151,
    "gn:feature_class":"P",
    "gn:feature_code":"PPL",
    "gn:name":"Adikasy",
    "gn:population":0,
    "gn:timezone":"Europe/Moscow",
    "iso:country":"RU",
    "name:rus_x_preferred":[
        "\u0410\u0434\u0438\u043a\u0430\u0441\u044b"
    ],
    "name:und_x_variant":[
        "\u0410\u0434\u0438\u043a\u0430\u0441\u044b"
    ],
    "wof:name":"Adikasy",
    "wof:placetype":"locality"
},
  "geometry": {"coordinates":[46.6074,56.1261],"type":"Point"}
}