{
  "type": "Feature",
  "properties": {
    "gn:admin1_code":"45.0",
    "gn:asciiname":"Mashlach",
    "gn:country_code":"RU",
    "gn:dem":190,
    "gn:feature_class":"P",
    "gn:feature_code":"PPL",
    "gn:name":"Mashlach",
    "gn:population":0,
    "gn:timezone":"Europe/Moscow",
    "iso:country":"RU",
    "name:rus_x_preferred":[
        "\u041c\u0430\u0448\u043b\u0430\u0447"
    ],
    "wof:name":"Mashlach",
    "wof:placetype":"locality"
},
  "geometry": {"coordinates":[48.86917,56.70111],"type":"Point"}
}