{
  "type": "Feature",
  "properties": {
    "gn:admin1_code":"83.0",
    "gn:asciiname":"Kozlovka",
    "gn:country_code":"RU",
    "gn:dem":112,
    "gn:feature_class":"P",
    "gn:feature_code":"PPL",
    "gn:name":"Kozlovka",
    "gn:population":0,
    "gn:timezone":"Europe/Moscow",
    "iso:country":"RU",
    "name:ara_x_preferred":[
        "\u0643\u0648\u0632\u0644\u0648\u0641\u0643\u0627"
    ],
    "wof:name":"Kozlovka",
    "wof:placetype":"locality"
},
  "geometry": {"coordinates":[41.90195,56.38033000000001],"type":"Point"}
}