{
  "type": "Feature",
  "properties": {
    "gn:admin1_code":"33",
    "gn:asciiname":"Alebino",
    "gn:country_code":"RU",
    "gn:dem":77,
    "gn:feature_class":"P",
    "gn:feature_code":"PPL",
    "gn:name":"Alebino",
    "gn:population":0,
    "gn:timezone":"Europe/Kirov",
    "iso:country":"RU",
    "name:rus_x_preferred":[
        "\u0410\u043b\u0435\u0431\u0438\u043d\u043e"
    ],
    "name:und_x_variant":[
        "\u0410\u043b\u0435\u0431\u0438\u043d\u043e"
    ],
    "wof:name":"Alebino",
    "wof:placetype":"locality"
},
  "geometry": {"coordinates":[47.076,60.3209],"type":"Point"}
}