{
  "type": "Feature",
  "properties": {
    "gn:admin1_code":"70",
    "gn:asciiname":"Radkovka",
    "gn:country_code":"RU",
    "gn:dem":127,
    "gn:feature_class":"P",
    "gn:feature_code":"PPL",
    "gn:name":"Radkovka",
    "gn:population":0,
    "gn:timezone":"Europe/Moscow",
    "iso:country":"RU",
    "name:rus_x_preferred":[
        "\u0420\u0430\u0434\u043a\u043e\u0432\u043a\u0430"
    ],
    "wof:name":"Radkovka",
    "wof:placetype":"locality"
},
  "geometry": {"coordinates":[44.02722,44.50528],"type":"Point"}
}