{
  "type": "Feature",
  "properties": {
    "gn:country":"RU",
    "gn:fcode":"PPL",
    "gn:pop":17359,
    "iso:country":"RU",
    "name:ara_x_preferred":[
        "\u064a\u0627\u0633\u0646\u064a"
    ],
    "name:azb_x_preferred":[
        "\u06cc\u0627\u0633\u0646\u06cc"
    ],
    "name:aze_x_preferred":[
        "Yasn\u0131y"
    ],
    "name:bak_x_preferred":[
        "\u042f\u0441\u043d\u044b\u0439"
    ],
    "name:bel_x_preferred":[
        "\u042f\u0441\u043d\u044b"
    ],
    "name:bul_x_preferred":[
        "\u042f\u0441\u043d\u0438"
    ],
    "name:cat_x_preferred":[
        "Iasni"
    ],
    "name:ceb_x_preferred":[
        "Yasnyy"
    ],
    "name:che_x_preferred":[
        "\u042f\u0441\u043d\u044b\u0439"
    ],
    "name:ckb_x_preferred":[
        "\u06cc\u0627\u0633\u0646\u06cc"
    ],
    "name:deu_x_preferred":[
        "Jasny"
    ],
    "name:eng_x_preferred":[
        "Yasnyy"
    ],
    "name:eng_x_variant":[
        "Yasny"
    ],
    "name:epo_x_preferred":[
        "Jasnij"
    ],
    "name:fas_x_preferred":[
        "\u06cc\u0627\u0633\u0646\u06cc"
    ],
    "name:fin_x_preferred":[
        "Jasnyi"
    ],
    "name:fra_x_preferred":[
        "Iasny"
    ],
    "name:haw_x_preferred":[
        "Kasini"
    ],
    "name:heb_x_preferred":[
        "\u05d9\u05d0\u05e1\u05e0\u05d9"
    ],
    "name:hrv_x_preferred":[
        "Jasnij"
    ],
    "name:hsb_x_preferred":[
        "Jasnyj"
    ],
    "name:ita_x_preferred":[
        "Jasnyj"
    ],
    "name:jpn_x_preferred":[
        "\u30e4\u30fc\u30b9\u30cc\u30a4"
    ],
    "name:mhr_x_preferred":[
        "\u042f\u0441\u043d\u044b\u0439"
    ],
    "name:nld_x_preferred":[
        "Jasniy"
    ],
    "name:nno_x_preferred":[
        "Jasnyj"
    ],
    "name:nob_x_preferred":[
        "Jasnyj"
    ],
    "name:nor_x_preferred":[
        "Jasnyj"
    ],
    "name:pol_x_preferred":[
        "Jasnyj"
    ],
    "name:rus_x_preferred":[
        "\u042f\u0441\u043d\u044b\u0439"
    ],
    "name:srp_x_preferred":[
        "\u0408\u0430\u0441\u043d\u0438"
    ],
    "name:swe_x_preferred":[
        "Jasnyj"
    ],
    "name:tat_x_preferred":[
        "\u042f\u0441\u043d\u044b\u0439"
    ],
    "name:tgl_x_preferred":[
        "Yasny"
    ],
    "name:tur_x_preferred":[
        "Yasni"
    ],
    "name:ukr_x_preferred":[
        "\u042f\u0441\u043d\u0438\u0439"
    ],
    "name:vep_x_preferred":[
        "Jasnii"
    ],
    "name:war_x_preferred":[
        "Yasny"
    ],
    "name:zho_x_preferred":[
        "\u4e9e\u65af\u5167"
    ],
    "qs:name":"Yasnyy",
    "qs:photos_9r":0,
    "qs:photos_sr":0,
    "qs:pop_sr":"6",
    "wof:name":"Yasnyy",
    "wof:placetype":"locality",
    "wof:population":17359
},
  "geometry": {"coordinates":[59.8742,51.0333],"type":"Point"}
}