{
  "type": "Feature",
  "properties": {
    "gn:admin1_code":"8",
    "gn:asciiname":"Zavodyanka",
    "gn:country_code":"RU",
    "gn:dem":114,
    "gn:feature_class":"P",
    "gn:feature_code":"PPL",
    "gn:name":"Zavodyanka",
    "gn:population":0,
    "gn:timezone":"Asia/Yekaterinburg",
    "iso:country":"RU",
    "name:rus_x_preferred":[
        "\u0417\u0430\u0432\u043e\u0434\u044f\u043d\u043a\u0430"
    ],
    "name:und_x_variant":[
        "\u0417\u0430\u0432\u043e\u0434\u044f\u043d\u043a\u0430"
    ],
    "wof:name":"Zavodyanka",
    "wof:placetype":"locality"
},
  "geometry": {"coordinates":[55.49428,54.62884],"type":"Point"}
}