{
  "type": "Feature",
  "properties": {
    "gn:admin1_code":"4.0",
    "gn:asciiname":"Uzhlep",
    "gn:country_code":"RU",
    "gn:dem":250,
    "gn:feature_class":"P",
    "gn:feature_code":"PPL",
    "gn:name":"Uzhlep",
    "gn:population":0,
    "gn:timezone":"Asia/Barnaul",
    "iso:country":"RU",
    "name:rus_x_preferred":[
        "\u0423\u0436\u043b\u0435\u043f"
    ],
    "wof:name":"Uzhlep",
    "wof:placetype":"locality"
},
  "geometry": {"coordinates":[86.19589999999999,52.2499],"type":"Point"}
}