{
  "type": "Feature",
  "properties": {
    "gn:admin1_code":"34",
    "gn:asciiname":"Pokcha",
    "gn:country_code":"RU",
    "gn:dem":95,
    "gn:feature_class":"P",
    "gn:feature_code":"PPL",
    "gn:name":"Pokcha",
    "gn:population":0,
    "gn:timezone":"Europe/Moscow",
    "iso:country":"RU",
    "name:eng_x_preferred":[
        "Pokcha"
    ],
    "name:nor_x_preferred":[
        "Poktsjar"
    ],
    "name:rus_x_preferred":[
        "\u041f\u043e\u043a\u0447\u0430\u0440"
    ],
    "name:rus_x_variant":[
        "\u041f\u043e\u043a\u0447\u0430"
    ],
    "wof:name":"Pokcha",
    "wof:placetype":"locality"
},
  "geometry": {"coordinates":[56.12061,62.9422],"type":"Point"}
}