{
  "type": "Feature",
  "properties": {
    "gn:admin1_code":"91",
    "gn:asciiname":"Salba",
    "gn:country_code":"RU",
    "gn:dem":319,
    "gn:feature_class":"P",
    "gn:feature_code":"PPL",
    "gn:name":"Salba",
    "gn:population":0,
    "gn:timezone":"Asia/Krasnoyarsk",
    "iso:country":"RU",
    "name:eng_x_preferred":[
        "Salba"
    ],
    "name:nor_x_preferred":[
        "Salba"
    ],
    "name:rus_x_preferred":[
        "\u0421\u0430\u043b\u0431\u0430"
    ],
    "wof:name":"Salba",
    "wof:placetype":"locality"
},
  "geometry": {"coordinates":[92.59999999999999,53.23333],"type":"Point"}
}