{
  "type": "Feature",
  "properties": {
    "gn:admin1_code":"52.0",
    "gn:asciiname":"Andryushino",
    "gn:country_code":"RU",
    "gn:dem":194,
    "gn:feature_class":"P",
    "gn:feature_code":"PPL",
    "gn:name":"Andryushino",
    "gn:population":0,
    "gn:timezone":"Europe/Moscow",
    "iso:country":"RU",
    "name:nor_x_preferred":[
        "Andrjusjino"
    ],
    "name:rus_x_preferred":[
        "\u0410\u043d\u0434\u0440\u044e\u0448\u0438\u043d\u043e"
    ],
    "name:und_x_variant":[
        "Andryushina",
        "Andryushino"
    ],
    "wof:name":"Andryushino",
    "wof:placetype":"locality"
},
  "geometry": {"coordinates":[34.76809,58.4302],"type":"Point"}
}