{
  "type": "Feature",
  "properties": {
    "gn:admin1_code":"11",
    "gn:asciiname":"Shanaga",
    "gn:country_code":"RU",
    "gn:dem":700,
    "gn:feature_class":"P",
    "gn:feature_code":"PPL",
    "gn:name":"Shanaga",
    "gn:population":0,
    "gn:timezone":"Asia/Irkutsk",
    "iso:country":"RU",
    "name:eng_x_preferred":[
        "Shanaga"
    ],
    "name:nor_x_preferred":[
        "Sjanaga"
    ],
    "name:rus_x_preferred":[
        "\u0428\u0430\u043d\u0430\u0433\u0430"
    ],
    "name:und_x_variant":[
        "\u0428\u0430\u043d\u0430\u0433\u0430",
        "Shanaga"
    ],
    "wof:name":"Shanaga",
    "wof:placetype":"locality"
},
  "geometry": {"coordinates":[108.14910999999999,50.83098],"type":"Point"}
}