{
  "type": "Feature",
  "properties": {
    "gn:admin1_code":"56",
    "gn:asciiname":"Krasnogor'ye",
    "gn:country_code":"RU",
    "gn:dem":177,
    "gn:feature_class":"P",
    "gn:feature_code":"PPL",
    "gn:name":"Krasnogor\u2019ye",
    "gn:population":0,
    "gn:timezone":"Europe/Moscow",
    "iso:country":"RU",
    "name:rus_x_preferred":[
        "\u041a\u0440\u0430\u0441\u043d\u043e\u0433\u043e\u0440\u044c\u0435"
    ],
    "name:und_x_variant":[
        "Krasnogor\u2019ye"
    ],
    "wof:name":"Krasnogor'ye",
    "wof:placetype":"locality"
},
  "geometry": {"coordinates":[37.2469,52.12692],"type":"Point"}
}