{
  "type": "Feature",
  "properties": {
    "gn:admin1_code":"20",
    "gn:asciiname":"Moloy",
    "gn:country_code":"RU",
    "gn:dem":714,
    "gn:feature_class":"P",
    "gn:feature_code":"PPL",
    "gn:name":"Moloy",
    "gn:population":0,
    "gn:timezone":"Asia/Irkutsk",
    "iso:country":"RU",
    "name:bug_x_preferred":[
        "Moloy"
    ],
    "name:cat_x_preferred":[
        "Moloy"
    ],
    "name:ceb_x_preferred":[
        "Moloy"
    ],
    "name:deu_x_preferred":[
        "Moloy"
    ],
    "name:eus_x_preferred":[
        "Moloy"
    ],
    "name:fra_x_preferred":[
        "Moloy"
    ],
    "name:hun_x_preferred":[
        "Moloy"
    ],
    "name:ind_x_preferred":[
        "Moloy"
    ],
    "name:ita_x_preferred":[
        "Moloy"
    ],
    "name:kaz_x_preferred":[
        "\u041c\u043e\u043b\u0443\u0430"
    ],
    "name:lat_x_preferred":[
        "Moloy"
    ],
    "name:mlg_x_preferred":[
        "Moloy"
    ],
    "name:msa_x_preferred":[
        "Moloy"
    ],
    "name:nld_x_preferred":[
        "Moloy"
    ],
    "name:oci_x_preferred":[
        "Moloy"
    ],
    "name:pms_x_preferred":[
        "Moloy"
    ],
    "name:pol_x_preferred":[
        "Moloy"
    ],
    "name:por_x_preferred":[
        "Moloy"
    ],
    "name:ron_x_preferred":[
        "Moloy"
    ],
    "name:rus_x_preferred":[
        "\u041c\u043e\u043b\u043e\u0439"
    ],
    "name:rus_x_variant":[
        "\u041c\u043e\u043b\u0443\u0430"
    ],
    "name:slk_x_preferred":[
        "Moloy"
    ],
    "name:spa_x_preferred":[
        "Moloy"
    ],
    "name:swe_x_preferred":[
        "Moloy"
    ],
    "name:ukr_x_preferred":[
        "\u041c\u043e\u043b\u0443\u0430"
    ],
    "name:und_x_variant":[
        "Moloy Pervyy",
        "Moloy",
        "\u041c\u043e\u043b\u043e\u0439"
    ],
    "name:uzb_x_preferred":[
        "Moloy"
    ],
    "name:vie_x_preferred":[
        "Moloy"
    ],
    "name:vol_x_preferred":[
        "Moloy"
    ],
    "name:war_x_preferred":[
        "Moloy"
    ],
    "name:zho_x_preferred":[
        "\u83ab\u5362\u74e6"
    ],
    "wof:name":"Moloy",
    "wof:placetype":"locality"
},
  "geometry": {"coordinates":[105.29222,53.03861],"type":"Point"}
}