{
  "type": "Feature",
  "properties": {
    "gn:admin1_code":"13",
    "gn:asciiname":"Popovo",
    "gn:country_code":"RU",
    "gn:dem":260,
    "gn:feature_class":"P",
    "gn:feature_code":"PPL",
    "gn:name":"Popovo",
    "gn:population":0,
    "gn:timezone":"Asia/Yekaterinburg",
    "iso:country":"RU",
    "name:bul_x_preferred":[
        "\u041f\u043e\u043f\u043e\u0432\u043e"
    ],
    "name:ceb_x_preferred":[
        "Popovo"
    ],
    "name:eng_x_preferred":[
        "Popovo"
    ],
    "name:fra_x_preferred":[
        "Popovo"
    ],
    "name:hye_x_preferred":[
        "\u054a\u0578\u057a\u0578\u057e\u0578"
    ],
    "name:nld_x_preferred":[
        "Popovo"
    ],
    "name:nor_x_preferred":[
        "Popovo"
    ],
    "name:por_x_preferred":[
        "Popovo"
    ],
    "name:ron_x_preferred":[
        "Popovo"
    ],
    "name:rus_x_preferred":[
        "\u041f\u043e\u043f\u043e\u0432\u043e"
    ],
    "name:swe_x_preferred":[
        "Popovo"
    ],
    "name:ukr_x_preferred":[
        "\u041f\u043e\u043f\u043e\u0432\u0435"
    ],
    "name:und_x_variant":[
        "Popovka"
    ],
    "name:vie_x_preferred":[
        "Popovo"
    ],
    "wof:name":"Popovo",
    "wof:placetype":"locality"
},
  "geometry": {"coordinates":[60.7185,54.6457],"type":"Point"}
}