{
  "type": "Feature",
  "properties": {
    "gn:admin1_code":"88",
    "gn:asciiname":"Kabatovo",
    "gn:country_code":"RU",
    "gn:dem":116,
    "gn:feature_class":"P",
    "gn:feature_code":"PPL",
    "gn:name":"Kabatovo",
    "gn:population":0,
    "gn:timezone":"Europe/Moscow",
    "iso:country":"RU",
    "name:rus_x_preferred":[
        "\u041a\u0430\u0431\u0430\u0442\u043e\u0432\u043e"
    ],
    "name:und_x_variant":[
        "Kabotovo",
        "Kabatovo"
    ],
    "wof:name":"Kabatovo",
    "wof:placetype":"locality"
},
  "geometry": {"coordinates":[39.42511,57.95014000000001],"type":"Point"}
}