{
  "type": "Feature",
  "properties": {
    "gn:admin1_code":"8",
    "gn:asciiname":"Kurovskiy",
    "gn:country_code":"RU",
    "gn:dem":162,
    "gn:feature_class":"P",
    "gn:feature_code":"PPL",
    "gn:name":"Kurovskiy",
    "gn:population":0,
    "gn:timezone":"Asia/Yekaterinburg",
    "iso:country":"RU",
    "name:rus_x_preferred":[
        "\u041a\u0443\u0440\u043e\u0432\u0441\u043a\u0438\u0439"
    ],
    "name:und_x_variant":[
        "\u041a\u0443\u0440\u043e\u0432\u0441\u043a\u0438\u0439"
    ],
    "wof:name":"Kurovskiy",
    "wof:placetype":"locality"
},
  "geometry": {"coordinates":[55.792,54.8325],"type":"Point"}
}