{
  "type": "Feature",
  "properties": {
    "gn:admin1_code":"84",
    "gn:asciiname":"Ryzhov",
    "gn:country_code":"RU",
    "gn:dem":25,
    "gn:feature_class":"P",
    "gn:feature_code":"PPL",
    "gn:name":"Ryzhov",
    "gn:population":0,
    "gn:timezone":"Europe/Volgograd",
    "iso:country":"RU",
    "name:rus_x_preferred":[
        "\u0420\u044b\u0436\u043e\u0432"
    ],
    "name:und_x_variant":[
        "\u0420\u044b\u0436\u043e\u0432"
    ],
    "wof:name":"Ryzhov",
    "wof:placetype":"locality"
},
  "geometry": {"coordinates":[45.91667,49.48333],"type":"Point"}
}