{
  "type": "Feature",
  "properties": {
    "gn:admin1_code":"55",
    "gn:asciiname":"Paradeyevo",
    "gn:country_code":"RU",
    "gn:dem":189,
    "gn:feature_class":"P",
    "gn:feature_code":"PPL",
    "gn:name":"Paradeyevo",
    "gn:population":0,
    "gn:timezone":"Asia/Yekaterinburg",
    "iso:country":"RU",
    "name:eng_x_preferred":[
        "Paradeyevo"
    ],
    "name:nor_x_preferred":[
        "Paradejevo"
    ],
    "name:rus_x_preferred":[
        "\u041f\u0430\u0440\u0430\u0434\u0435\u0435\u0432\u043e"
    ],
    "wof:name":"Paradeyevo",
    "wof:placetype":"locality"
},
  "geometry": {"coordinates":[55.11666999999999,52.78333000000001],"type":"Point"}
}