{
  "type": "Feature",
  "properties": {
    "gn:admin1_code":"60",
    "gn:asciiname":"Voytekhi",
    "gn:country_code":"RU",
    "gn:dem":89,
    "gn:feature_class":"P",
    "gn:feature_code":"PPL",
    "gn:name":"Voytekhi",
    "gn:population":0,
    "gn:timezone":"Europe/Moscow",
    "iso:country":"RU",
    "name:rus_x_preferred":[
        "\u0412\u043e\u0439\u0442\u0435\u0445\u0438"
    ],
    "wof:name":"Voytekhi",
    "wof:placetype":"locality"
},
  "geometry": {"coordinates":[28.60445,56.91181],"type":"Point"}
}