{
  "type": "Feature",
  "properties": {
    "gn:admin1_code":"90.0",
    "gn:asciiname":"Levina",
    "gn:country_code":"RU",
    "gn:dem":193,
    "gn:feature_class":"P",
    "gn:feature_code":"PPL",
    "gn:name":"Levina",
    "gn:population":0,
    "gn:timezone":"Asia/Yekaterinburg",
    "iso:country":"RU",
    "name:deu_x_preferred":[
        "Lewina"
    ],
    "name:hun_x_preferred":[
        "Levina"
    ],
    "name:rus_x_preferred":[
        "\u041b\u0435\u0432\u0438\u043d\u0430"
    ],
    "wof:name":"Levina",
    "wof:placetype":"locality"
},
  "geometry": {"coordinates":[56.6038,59.819],"type":"Point"}
}