{
  "type": "Feature",
  "properties": {
    "gn:admin1_code":"86",
    "gn:asciiname":"Golovin",
    "gn:country_code":"RU",
    "gn:dem":168,
    "gn:feature_class":"P",
    "gn:feature_code":"PPL",
    "gn:name":"Golovin",
    "gn:population":0,
    "gn:timezone":"Europe/Moscow",
    "iso:country":"RU",
    "name:azb_x_preferred":[
        "\u0642\u0648\u0644\u0648\u0648\u06cc\u0646"
    ],
    "name:bel_x_preferred":[
        "\u0413\u0430\u043b\u0430\u0432\u0456\u043d"
    ],
    "name:ceb_x_preferred":[
        "Golovin"
    ],
    "name:ces_x_preferred":[
        "Golovin"
    ],
    "name:deu_x_preferred":[
        "Golovin"
    ],
    "name:est_x_preferred":[
        "Golovin"
    ],
    "name:fra_x_preferred":[
        "Golovine"
    ],
    "name:ita_x_preferred":[
        "Golovin"
    ],
    "name:lav_x_preferred":[
        "Golovins"
    ],
    "name:rus_x_preferred":[
        "\u0413\u043e\u043b\u043e\u0432\u0438\u043d"
    ],
    "name:slv_x_preferred":[
        "Golovin"
    ],
    "name:spa_x_preferred":[
        "Golov\u00edn"
    ],
    "name:swe_x_preferred":[
        "Golovin"
    ],
    "name:ukr_x_preferred":[
        "\u0413\u043e\u043b\u043e\u0432\u0456\u043d"
    ],
    "wof:name":"Golovin",
    "wof:placetype":"locality"
},
  "geometry": {"coordinates":[38.4738,51.3242],"type":"Point"}
}