{
  "type": "Feature",
  "properties": {
    "gn:admin1_code":"88",
    "gn:asciiname":"Pribylovo",
    "gn:country_code":"RU",
    "gn:dem":134,
    "gn:feature_class":"P",
    "gn:feature_code":"PPL",
    "gn:name":"Pribylovo",
    "gn:population":0,
    "gn:timezone":"Europe/Moscow",
    "iso:country":"RU",
    "name:rus_x_preferred":[
        "\u041f\u0440\u0438\u0431\u044b\u043b\u043e\u0432\u043e"
    ],
    "wof:name":"Pribylovo",
    "wof:placetype":"locality"
},
  "geometry": {"coordinates":[38.9071,57.7096],"type":"Point"}
}