{
  "type": "Feature",
  "properties": {
    "gn:admin1_code":"13",
    "gn:asciiname":"Lugovskoy",
    "gn:cc2":"RU",
    "gn:country_code":"RU",
    "gn:dem":185,
    "gn:feature_class":"P",
    "gn:feature_code":"PPL",
    "gn:name":"Lugovskoy",
    "gn:population":0,
    "gn:timezone":"Asia/Yekaterinburg",
    "iso:country":"RU",
    "name:eng_x_preferred":[
        "Lugovskoy"
    ],
    "name:nor_x_preferred":[
        "Lugovaja"
    ],
    "name:rus_x_preferred":[
        "\u041b\u0443\u0433\u043e\u0432\u0430\u044f"
    ],
    "name:rus_x_variant":[
        "\u041b\u0443\u0433\u043e\u0432\u0441\u043a\u043e\u0439"
    ],
    "name:und_x_variant":[
        "Lugovoye",
        "Lugovskiy",
        "Lugovskoy",
        "\u041b\u0443\u0433\u043e\u0432\u0441\u043a\u043e\u0439"
    ],
    "wof:name":"Lugovskoy",
    "wof:placetype":"locality"
},
  "geometry": {"coordinates":[61.21666999999999,54.38333000000001],"type":"Point"}
}