{
  "type": "Feature",
  "properties": {
    "gn:admin1_code":"69",
    "gn:asciiname":"Ploskaya",
    "gn:cc2":"RU",
    "gn:country_code":"RU",
    "gn:dem":252,
    "gn:feature_class":"P",
    "gn:feature_code":"PPL",
    "gn:name":"Ploskaya",
    "gn:population":0,
    "gn:timezone":"Europe/Moscow",
    "iso:country":"RU",
    "name:rus_x_preferred":[
        "\u041f\u043b\u043e\u0441\u043a\u0430\u044f"
    ],
    "name:und_x_variant":[
        "Ployekaya",
        "Ploskaya",
        "\u041f\u043b\u043e\u0441\u043a\u0430\u044f"
    ],
    "wof:name":"Ploskaya",
    "wof:placetype":"locality"
},
  "geometry": {"coordinates":[33.38722,55.35528000000001],"type":"Point"}
}