{
  "type": "Feature",
  "properties": {
    "gn:admin1_code":"53",
    "gn:asciiname":"Borzinskiy",
    "gn:country_code":"RU",
    "gn:dem":169,
    "gn:feature_class":"P",
    "gn:feature_code":"PPL",
    "gn:name":"Borzinskiy",
    "gn:population":0,
    "gn:timezone":"Asia/Novosibirsk",
    "iso:country":"RU",
    "name:rus_x_preferred":[
        "\u0411\u043e\u0440\u0437\u0438\u043d\u0441\u043a\u0438\u0439"
    ],
    "wof:name":"Borzinskiy",
    "wof:placetype":"locality"
},
  "geometry": {"coordinates":[84.34999999999999,55.85],"type":"Point"}
}