{
  "type": "Feature",
  "properties": {
    "gn:admin1_code":"61",
    "gn:asciiname":"Prostornyy",
    "gn:country_code":"RU",
    "gn:dem":81,
    "gn:feature_class":"P",
    "gn:feature_code":"PPL",
    "gn:name":"Prostornyy",
    "gn:population":0,
    "gn:timezone":"Europe/Moscow",
    "iso:country":"RU",
    "name:rus_x_preferred":[
        "\u041f\u0440\u043e\u0441\u0442\u043e\u0440\u043d\u044b\u0439"
    ],
    "name:und_x_variant":[
        "\u041f\u0440\u043e\u0441\u0442\u043e\u0440\u043d\u044b\u0439"
    ],
    "wof:name":"Prostornyy",
    "wof:placetype":"locality"
},
  "geometry": {"coordinates":[42.15611,47.42028],"type":"Point"}
}