{
  "type": "Feature",
  "properties": {
    "gn:admin1_code":"64",
    "gn:asciiname":"Pondebari",
    "gn:country_code":"RU",
    "gn:dem":32,
    "gn:feature_class":"P",
    "gn:feature_code":"PPL",
    "gn:name":"Pondebari",
    "gn:population":0,
    "gn:timezone":"Asia/Magadan",
    "iso:country":"RU",
    "name:jpn_x_preferred":[
        "\u30dd\u30f3\u30c7\u30d0\u30ea"
    ],
    "name:jpn_x_variant":[
        "\u307d\u3093\u3067\u3070\u308a"
    ],
    "name:rus_x_preferred":[
        "\u041f\u043e\u043d\u0434\u0435\u0431\u0430\u0440\u0438"
    ],
    "wof:name":"Pondebari",
    "wof:placetype":"locality"
},
  "geometry": {"coordinates":[146.62257,43.73897],"type":"Point"}
}