{
  "type": "Feature",
  "properties": {
    "gn:admin1_code":"72",
    "gn:asciiname":"Mel'guny",
    "gn:country_code":"RU",
    "gn:dem":145,
    "gn:feature_class":"P",
    "gn:feature_code":"PPL",
    "gn:name":"Mel\u2019guny",
    "gn:population":0,
    "gn:timezone":"Europe/Moscow",
    "iso:country":"RU",
    "name:rus_x_preferred":[
        "Mel\u2019guny"
    ],
    "name:rus_x_variant":[
        "\u041c\u0435\u043b\u044c\u0433\u0443\u043d\u044b",
        "Mil\u2019guny"
    ],
    "name:und_x_variant":[
        "Mil\u2019guny",
        "Mel\u2019guny",
        "\u041c\u0435\u043b\u044c\u0433\u0443\u043d\u044b"
    ],
    "wof:name":"Mel'guny",
    "wof:placetype":"locality"
},
  "geometry": {"coordinates":[40.8672,52.1571],"type":"Point"}
}