{
  "type": "Feature",
  "properties": {
    "gn:country":"RU",
    "gn:fcode":"PPL",
    "gn:pop":200,
    "iso:country":"RU",
    "name:rus_x_preferred":[
        "\u0411\u043e\u043b\u0442\u0438\u043d\u043e"
    ],
    "name:unk_x_variant":[
        "\u0411\u043e\u043b\u0442\u0438\u043d\u043e"
    ],
    "qs:name":"Boltino",
    "qs:photos_9r":0,
    "qs:photos_sr":0,
    "qs:pop_sr":"1",
    "wof:name":"Boltino",
    "wof:placetype":"locality",
    "wof:population":200
},
  "geometry": {"coordinates":[37.66167,55.96444],"type":"Point"}
}