{
  "type": "Feature",
  "properties": {
    "gn:admin1_code":"52",
    "gn:asciiname":"Malyye Udrai",
    "gn:country_code":"RU",
    "gn:dem":54,
    "gn:feature_class":"P",
    "gn:feature_code":"PPL",
    "gn:name":"Malyye Udrai",
    "gn:population":0,
    "gn:timezone":"Europe/Moscow",
    "iso:country":"RU",
    "name:rus_x_preferred":[
        "\u041c\u0430\u043b\u044b\u0435 \u0423\u0434\u0440\u0430\u0438"
    ],
    "name:und_x_variant":[
        "\u041c\u0430\u043b\u044b\u0435 \u0423\u0434\u0440\u0430\u0438"
    ],
    "wof:name":"Malyye Udrai",
    "wof:placetype":"locality"
},
  "geometry": {"coordinates":[30.1646,58.65619],"type":"Point"}
}