{
  "type": "Feature",
  "properties": {
    "gn:admin1_code":"85.0",
    "gn:asciiname":"Chesnokovo",
    "gn:country_code":"RU",
    "gn:dem":147,
    "gn:feature_class":"P",
    "gn:feature_code":"PPL",
    "gn:name":"Chesnokovo",
    "gn:population":0,
    "gn:timezone":"Europe/Moscow",
    "iso:country":"RU",
    "name:che_x_preferred":[
        "\u0427\u0435\u0441\u043d\u043e\u043a\u043e\u0432\u043e"
    ],
    "name:rus_x_preferred":[
        "\u0427\u0435\u0441\u043d\u043e\u043a\u043e\u0432\u043e"
    ],
    "wof:name":"Chesnokovo",
    "wof:placetype":"locality"
},
  "geometry": {"coordinates":[37.8977,60.399],"type":"Point"}
}