{
  "type": "Feature",
  "properties": {
    "gn:admin1_code":"33",
    "gn:asciiname":"Ostryy Mys",
    "gn:country_code":"RU",
    "gn:dem":145,
    "gn:feature_class":"P",
    "gn:feature_code":"PPL",
    "gn:name":"Ostryy Mys",
    "gn:population":0,
    "gn:timezone":"Europe/Kirov",
    "iso:country":"RU",
    "name:rus_x_preferred":[
        "\u041e\u0441\u0442\u0440\u044b\u0439 \u041c\u044b\u0441"
    ],
    "wof:name":"Ostryy Mys",
    "wof:placetype":"locality"
},
  "geometry": {"coordinates":[50.76667,57.43333000000001],"type":"Point"}
}