{
  "type": "Feature",
  "properties": {
    "gn:admin1_code":"41",
    "gn:asciiname":"Krasnyy Kut",
    "gn:country_code":"RU",
    "gn:dem":189,
    "gn:feature_class":"P",
    "gn:feature_code":"PPL",
    "gn:name":"Krasnyy Kut",
    "gn:population":0,
    "gn:timezone":"Europe/Moscow",
    "iso:country":"RU",
    "name:rus_x_preferred":[
        "\u041a\u0440\u0430\u0441\u043d\u044b\u0439 \u041a\u0443\u0442"
    ],
    "wof:name":"Krasnyy Kut",
    "wof:placetype":"locality"
},
  "geometry": {"coordinates":[34.74444,52.03472],"type":"Point"}
}