{
  "type": "Feature",
  "properties": {
    "gn:country":"RU",
    "gn:fcode":"PPL",
    "gn:population":250,
    "iso:country":"RU",
    "name:rus_x_preferred":[
        "\u0421\u0442\u0430\u0440\u044b\u0439 \u041c\u0435\u0434\u0432\u0435\u0434\u044c"
    ],
    "name:und_x_variant":[
        "Stary Medved\u2019"
    ],
    "qs:name":"Staryy Medved\u2019",
    "qs:photos_9r":0,
    "qs:photos_sr":0,
    "qs:pop_sr":"2",
    "wof:name":"Staryy Medved\u2019",
    "wof:placetype":"locality",
    "wof:population":250
},
  "geometry": {"coordinates":[30.49237,58.29737],"type":"Point"}
}