{
  "type": "Feature",
  "properties": {
    "gn:admin1_code":"46.0",
    "gn:asciiname":"Apraksino",
    "gn:country_code":"RU",
    "gn:dem":139,
    "gn:feature_class":"P",
    "gn:feature_code":"PPL",
    "gn:name":"Apraksino",
    "gn:population":0,
    "gn:timezone":"Europe/Moscow",
    "iso:country":"RU",
    "name:nor_x_preferred":[
        "Apraksino"
    ],
    "name:rus_x_preferred":[
        "\u0410\u043f\u0440\u0430\u043a\u0441\u0438\u043d\u043e"
    ],
    "wof:name":"Apraksino",
    "wof:placetype":"locality"
},
  "geometry": {"coordinates":[45.78045,54.50271],"type":"Point"}
}