{
  "type": "Feature",
  "properties": {
    "gn:admin1_code":"55",
    "gn:asciiname":"Peredovka",
    "gn:country_code":"RU",
    "gn:dem":79,
    "gn:feature_class":"P",
    "gn:feature_code":"PPL",
    "gn:name":"Peredovka",
    "gn:population":0,
    "gn:timezone":"Asia/Yekaterinburg",
    "iso:country":"RU",
    "name:rus_x_preferred":[
        "\u041f\u0435\u0440\u0435\u0434\u043e\u0432\u043a\u0430"
    ],
    "wof:name":"Peredovka",
    "wof:placetype":"locality"
},
  "geometry": {"coordinates":[52.282,53.6729],"type":"Point"}
}