{
  "type": "Feature",
  "properties": {
    "gn:admin1_code":"62",
    "gn:asciiname":"Krasnyy Poselok",
    "gn:country_code":"RU",
    "gn:dem":121,
    "gn:feature_class":"P",
    "gn:feature_code":"PPL",
    "gn:name":"Krasnyy Pos\u00eblok",
    "gn:population":0,
    "gn:timezone":"Europe/Moscow",
    "iso:country":"RU",
    "name:rus_x_preferred":[
        "\u041a\u0440\u0430\u0441\u043d\u044b\u0439 \u041f\u043e\u0441\u0451\u043b\u043e\u043a"
    ],
    "name:und_x_variant":[
        "Krasnyy Pos\u00eblok"
    ],
    "wof:name":"Krasnyy Poselok",
    "wof:placetype":"locality"
},
  "geometry": {"coordinates":[39.2511,54.217],"type":"Point"}
}