{
  "type": "Feature",
  "properties": {
    "gn:admin1_code":"62",
    "gn:asciiname":"Michurovka",
    "gn:country_code":"RU",
    "gn:dem":173,
    "gn:feature_class":"P",
    "gn:feature_code":"PPL",
    "gn:name":"Michurovka",
    "gn:population":0,
    "gn:timezone":"Europe/Moscow",
    "iso:country":"RU",
    "name:rus_x_preferred":[
        "\u041c\u0438\u0447\u0443\u0440\u043e\u0432\u043a\u0430"
    ],
    "name:und_x_variant":[
        "\u041c\u0438\u0447\u0443\u0440\u043e\u0432\u043a\u0430"
    ],
    "wof:name":"Michurovka",
    "wof:placetype":"locality"
},
  "geometry": {"coordinates":[39.6182,54.0453],"type":"Point"}
}