{
  "type": "Feature",
  "properties": {
    "gn:admin1_code":"56",
    "gn:asciiname":"Lyuboshch'",
    "gn:country_code":"RU",
    "gn:dem":191,
    "gn:feature_class":"P",
    "gn:feature_code":"PPL",
    "gn:name":"Lyuboshch\u2019",
    "gn:population":0,
    "gn:timezone":"Europe/Moscow",
    "iso:country":"RU",
    "name:rus_x_preferred":[
        "\u041b\u044e\u0431\u043e\u0449\u044c"
    ],
    "name:und_x_variant":[
        "Lyuboshch\u2019",
        "\u041b\u044e\u0431\u043e\u0449\u044c"
    ],
    "wof:name":"Lyuboshch'",
    "wof:placetype":"locality"
},
  "geometry": {"coordinates":[34.8862,52.4357],"type":"Point"}
}