{
  "type": "Feature",
  "properties": {
    "gn:admin1_code":"52.0",
    "gn:asciiname":"Bel'-Dva",
    "gn:country_code":"RU",
    "gn:dem":125,
    "gn:feature_class":"P",
    "gn:feature_code":"PPL",
    "gn:name":"Bel\u2019-Dva",
    "gn:population":0,
    "gn:timezone":"Europe/Moscow",
    "iso:country":"RU",
    "name:nor_x_preferred":[
        "Bel Vtoraja"
    ],
    "name:rus_x_preferred":[
        "\u0411\u0435\u043b\u044c-\u0414\u0432\u0430"
    ],
    "name:und_x_variant":[
        "Bel\u2019",
        "Bel\u2019 Vtoraya",
        "Bel\u2019-Dva"
    ],
    "wof:name":"Bel'-Dva",
    "wof:placetype":"locality"
},
  "geometry": {"coordinates":[32.42921,57.47600000000001],"type":"Point"}
}