{
  "type": "Feature",
  "properties": {
    "gn:admin1_code":"52",
    "gn:asciiname":"Kukanovo",
    "gn:country_code":"RU",
    "gn:dem":24,
    "gn:feature_class":"P",
    "gn:feature_code":"PPL",
    "gn:name":"Kukanovo",
    "gn:population":0,
    "gn:timezone":"Europe/Moscow",
    "iso:country":"RU",
    "name:rus_x_preferred":[
        "\u041a\u0443\u043a\u0430\u043d\u043e\u0432\u043e"
    ],
    "name:und_x_variant":[
        "\u041a\u0443\u043a\u0430\u043d\u043e\u0432\u043e"
    ],
    "wof:name":"Kukanovo",
    "wof:placetype":"locality"
},
  "geometry": {"coordinates":[31.01565,58.39736],"type":"Point"}
}