{
  "type": "Feature",
  "properties": {
    "gn:admin1_code":"69",
    "gn:asciiname":"Staraya Matsilevka",
    "gn:cc2":"RU",
    "gn:country_code":"RU",
    "gn:dem":189,
    "gn:feature_class":"P",
    "gn:feature_code":"PPL",
    "gn:name":"Staraya Matsil\u00ebvka",
    "gn:population":0,
    "gn:timezone":"Europe/Moscow",
    "iso:country":"RU",
    "name:rus_x_preferred":[
        "\u0421\u0442\u0430\u0440\u0430\u044f \u041c\u0430\u0446\u0438\u043b\u0451\u0432\u043a\u0430"
    ],
    "name:und_x_variant":[
        "Bol\u2019shaya Matselovka",
        "Matsil\u00ebva Pervaya",
        "Matsil\u00ebvka",
        "Matsylevka",
        "Staraya Matsil\u00ebvka"
    ],
    "wof:name":"Staraya Matsilevka",
    "wof:placetype":"locality"
},
  "geometry": {"coordinates":[32.48583,53.60667],"type":"Point"}
}