{
  "type": "Feature",
  "properties": {
    "gn:admin1_code":"41",
    "gn:asciiname":"Revolyutsionnoye",
    "gn:country_code":"RU",
    "gn:dem":219,
    "gn:feature_class":"P",
    "gn:feature_code":"PPL",
    "gn:name":"Revolyutsionnoye",
    "gn:population":0,
    "gn:timezone":"Europe/Moscow",
    "iso:country":"RU",
    "name:rus_x_preferred":[
        "\u0420\u0435\u0432\u043e\u043b\u044e\u0446\u0438\u043e\u043d\u043d\u043e\u0435"
    ],
    "wof:name":"Revolyutsionnoye",
    "wof:placetype":"locality"
},
  "geometry": {"coordinates":[36.48131,52.10742],"type":"Point"}
}