{
  "type": "Feature",
  "properties": {
    "gn:admin1_code":"38",
    "gn:asciiname":"Razdol'nyy",
    "gn:country_code":"RU",
    "gn:dem":294,
    "gn:feature_class":"P",
    "gn:feature_code":"PPL",
    "gn:name":"Razdol\u2019nyy",
    "gn:population":0,
    "gn:timezone":"Europe/Moscow",
    "iso:country":"RU",
    "name:rus_x_preferred":[
        "\u0420\u0430\u0437\u0434\u043e\u043b\u044c\u043d\u044b\u0439"
    ],
    "name:und_x_variant":[
        "Razdol\u2019nyy"
    ],
    "wof:name":"Razdol'nyy",
    "wof:placetype":"locality"
},
  "geometry": {"coordinates":[41.03727,44.80944],"type":"Point"}
}