{
  "type": "Feature",
  "properties": {
    "gn:admin1_code":"77",
    "gn:asciiname":"Kostromino",
    "gn:country_code":"RU",
    "gn:dem":180,
    "gn:feature_class":"P",
    "gn:feature_code":"PPL",
    "gn:name":"Kostromino",
    "gn:population":0,
    "gn:timezone":"Europe/Moscow",
    "iso:country":"RU",
    "name:nor_x_preferred":[
        "Kostromino"
    ],
    "name:rus_x_preferred":[
        "\u041a\u043e\u0441\u0442\u0440\u043e\u043c\u0438\u043d\u043e"
    ],
    "wof:name":"Kostromino",
    "wof:placetype":"locality"
},
  "geometry": {"coordinates":[35.00326,56.6275],"type":"Point"}
}