{
  "type": "Feature",
  "properties": {
    "gn:admin1_code":"11",
    "gn:asciiname":"Shelikova",
    "gn:country_code":"RU",
    "gn:dem":971,
    "gn:feature_class":"P",
    "gn:feature_code":"PPL",
    "gn:name":"Shelikova",
    "gn:population":0,
    "gn:timezone":"Asia/Irkutsk",
    "iso:country":"RU",
    "name:rus_x_preferred":[
        "\u0428\u0435\u043b\u0438\u043a\u043e\u0432\u0430"
    ],
    "name:und_x_variant":[
        "\u0428\u0435\u043b\u0438\u043a\u043e\u0432\u0430"
    ],
    "wof:name":"Shelikova",
    "wof:placetype":"locality"
},
  "geometry": {"coordinates":[102.16667,52.08333],"type":"Point"}
}