{
  "type": "Feature",
  "properties": {
    "gn:admin1_code":"86.0",
    "gn:asciiname":"Mirolyubiye",
    "gn:country_code":"RU",
    "gn:dem":126,
    "gn:feature_class":"P",
    "gn:feature_code":"PPL",
    "gn:name":"Mirolyubiye",
    "gn:population":0,
    "gn:timezone":"Europe/Moscow",
    "iso:country":"RU",
    "name:eng_x_preferred":[
        "Mirolyubiye"
    ],
    "name:nor_x_preferred":[
        "Miroljubije"
    ],
    "name:rus_x_preferred":[
        "\u041c\u0438\u0440\u043e\u043b\u044e\u0431\u0438\u0435"
    ],
    "wof:name":"Mirolyubiye",
    "wof:placetype":"locality"
},
  "geometry": {"coordinates":[42.31735,51.49376],"type":"Point"}
}