{
  "type": "Feature",
  "properties": {
    "gn:admin1_code":"90.0",
    "gn:asciiname":"Zagar'ye",
    "gn:country_code":"RU",
    "gn:dem":144,
    "gn:feature_class":"P",
    "gn:feature_code":"PPL",
    "gn:name":"Zagar\u2019ye",
    "gn:population":0,
    "gn:timezone":"Asia/Yekaterinburg",
    "iso:country":"RU",
    "name:rus_x_preferred":[
        "\u0417\u0430\u0433\u0430\u0440\u044c\u0435"
    ],
    "name:und_x_variant":[
        "Zagar\u2019ye"
    ],
    "wof:name":"Zagar'ye",
    "wof:placetype":"locality"
},
  "geometry": {"coordinates":[54.918,58.9275],"type":"Point"}
}