{
  "type": "Feature",
  "properties": {
    "gn:admin1_code":"17",
    "gn:asciiname":"Novyy Aul",
    "gn:country_code":"RU",
    "gn:dem":221,
    "gn:feature_class":"P",
    "gn:feature_code":"PPL",
    "gn:name":"Novyy Aul",
    "gn:population":0,
    "gn:timezone":"Europe/Moscow",
    "iso:country":"RU",
    "name:aze_x_preferred":[
        "Yeni Aul"
    ],
    "name:eng_x_preferred":[
        "Novyy Aul"
    ],
    "name:rus_x_preferred":[
        "\u041d\u043e\u0432\u044b\u0439 \u0410\u0443\u043b"
    ],
    "name:rus_x_variant":[
        "\u041d\u043e\u0432.\u0410\u0443\u043b"
    ],
    "name:und_x_variant":[
        "Tsiynkhyur",
        "Novyy Aul"
    ],
    "wof:name":"Novyy Aul",
    "wof:placetype":"locality"
},
  "geometry": {"coordinates":[48.39462,41.73196],"type":"Point"}
}