{
  "type": "Feature",
  "properties": {
    "gn:admin1_code":"38",
    "gn:asciiname":"Kuban'",
    "gn:country_code":"RU",
    "gn:dem":71,
    "gn:feature_class":"P",
    "gn:feature_code":"PPL",
    "gn:name":"Kuban\u2019",
    "gn:population":0,
    "gn:timezone":"Europe/Moscow",
    "iso:country":"RU",
    "name:rus_x_preferred":[
        "\u041a\u0443\u0431\u0430\u043d\u044c"
    ],
    "name:und_x_variant":[
        "Kuban\u2019",
        "\u041a\u0443\u0431\u0430\u043d\u044c"
    ],
    "wof:name":"Kuban'",
    "wof:placetype":"locality"
},
  "geometry": {"coordinates":[40.4105,45.3539],"type":"Point"}
}