{
  "type": "Feature",
  "properties": {
    "gn:admin1_code":"25.0",
    "gn:asciiname":"Dretovo",
    "gn:country_code":"RU",
    "gn:dem":146,
    "gn:feature_class":"P",
    "gn:feature_code":"PPL",
    "gn:name":"Dretovo",
    "gn:population":0,
    "gn:timezone":"Europe/Moscow",
    "iso:country":"RU",
    "name:rus_x_preferred":[
        "\u0414\u0440\u0435\u0442\u043e\u0432\u043e"
    ],
    "name:und_x_variant":[
        "Dretova",
        "Dretovo"
    ],
    "wof:name":"Dretovo",
    "wof:placetype":"locality"
},
  "geometry": {"coordinates":[35.6075,53.88542],"type":"Point"}
}