{
  "type": "Feature",
  "properties": {
    "gn:admin1_code":"52",
    "gn:asciiname":"Krasota",
    "gn:country_code":"RU",
    "gn:dem":217,
    "gn:feature_class":"P",
    "gn:feature_code":"PPL",
    "gn:name":"Krasota",
    "gn:population":0,
    "gn:timezone":"Europe/Moscow",
    "iso:country":"RU",
    "name:rus_x_preferred":[
        "\u041a\u0440\u0430\u0441\u043e\u0442\u0430"
    ],
    "wof:name":"Krasota",
    "wof:placetype":"locality"
},
  "geometry": {"coordinates":[32.9784,57.503],"type":"Point"}
}