{
  "type": "Feature",
  "properties": {
    "gn:admin1_code":"88",
    "gn:asciiname":"Petrakovo",
    "gn:country_code":"RU",
    "gn:dem":144,
    "gn:feature_class":"P",
    "gn:feature_code":"PPL",
    "gn:name":"Petrakovo",
    "gn:population":0,
    "gn:timezone":"Europe/Moscow",
    "iso:country":"RU",
    "name:rus_x_preferred":[
        "\u041f\u0435\u0442\u0440\u0430\u043a\u043e\u0432\u043e"
    ],
    "wof:name":"Petrakovo",
    "wof:placetype":"locality"
},
  "geometry": {"coordinates":[38.4716,57.43899999999999],"type":"Point"}
}