{
  "type": "Feature",
  "properties": {
    "gn:admin1_code":"76",
    "gn:asciiname":"Nizhniye Prisady",
    "gn:country_code":"RU",
    "gn:dem":157,
    "gn:feature_class":"P",
    "gn:feature_code":"PPL",
    "gn:name":"Nizhniye Prisady",
    "gn:population":0,
    "gn:timezone":"Europe/Moscow",
    "iso:country":"RU",
    "name:rus_x_preferred":[
        "\u041d\u0438\u0436\u043d\u0438\u0435 \u041f\u0440\u0438\u0441\u0430\u0434\u044b"
    ],
    "wof:name":"Nizhniye Prisady",
    "wof:placetype":"locality"
},
  "geometry": {"coordinates":[37.75932,54.13599],"type":"Point"}
}