{
  "type": "Feature",
  "properties": {
    "gn:admin1_code":"80.0",
    "gn:asciiname":"Akarshur",
    "gn:country_code":"RU",
    "gn:dem":162,
    "gn:feature_class":"P",
    "gn:feature_code":"PPL",
    "gn:name":"Akarshur",
    "gn:population":0,
    "gn:timezone":"Europe/Samara",
    "iso:country":"RU",
    "name:nor_x_preferred":[
        "Akarsjur"
    ],
    "name:rus_x_preferred":[
        "\u0410\u043a\u0430\u0440\u0448\u0443\u0440"
    ],
    "name:und_x_variant":[
        "Akashur",
        "Akarshur"
    ],
    "wof:name":"Akarshur",
    "wof:placetype":"locality"
},
  "geometry": {"coordinates":[52.59214,56.48506999999999],"type":"Point"}
}