{
  "type": "Feature",
  "properties": {
    "gn:admin1_code":"44",
    "gn:asciiname":"Ayan-Yuryakh",
    "gn:country_code":"RU",
    "gn:dem":919,
    "gn:feature_class":"P",
    "gn:feature_code":"PPL",
    "gn:name":"Ayan-Yuryakh",
    "gn:population":0,
    "gn:timezone":"Asia/Magadan",
    "iso:country":"RU",
    "name:nor_x_preferred":[
        "Ajan-Jurjakh"
    ],
    "name:rus_x_preferred":[
        "\u0410\u044f\u043d-\u042e\u0440\u044f\u0445"
    ],
    "name:und_x_variant":[
        "Ayan Yaryakh",
        "Ayan-Yuryakh"
    ],
    "wof:name":"Ayan-Yuryakh",
    "wof:placetype":"locality"
},
  "geometry": {"coordinates":[145.61667,63.16667],"type":"Point"}
}