{
  "type": "Feature",
  "properties": {
    "gn:admin1_code":"43",
    "gn:asciiname":"Tul'skoye",
    "gn:country_code":"RU",
    "gn:dem":198,
    "gn:feature_class":"P",
    "gn:feature_code":"PPL",
    "gn:name":"Tul\u2019skoye",
    "gn:population":0,
    "gn:timezone":"Europe/Moscow",
    "iso:country":"RU",
    "name:eng_x_preferred":[
        "Tul'skoye"
    ],
    "name:nor_x_preferred":[
        "Tulskoje"
    ],
    "name:rus_x_preferred":[
        "\u0422\u0443\u043b\u044c\u0441\u043a\u043e\u0435"
    ],
    "name:und_x_variant":[
        "Tul\u2019skaya",
        "Tul\u2019skoye"
    ],
    "wof:name":"Tul'skoye",
    "wof:placetype":"locality"
},
  "geometry": {"coordinates":[38.35601,52.21585],"type":"Point"}
}