{
  "type": "Feature",
  "properties": {
    "gn:admin1_code":"73",
    "gn:asciiname":"Malyye Klyuchi",
    "gn:country_code":"RU",
    "gn:dem":120,
    "gn:feature_class":"P",
    "gn:feature_code":"PPL",
    "gn:name":"Malyye Klyuchi",
    "gn:population":0,
    "gn:timezone":"Europe/Moscow",
    "iso:country":"RU",
    "name:rus_x_preferred":[
        "\u041c\u0430\u043b\u044b\u0435 \u041a\u043b\u044e\u0447\u0438"
    ],
    "wof:name":"Malyye Klyuchi",
    "wof:placetype":"locality"
},
  "geometry": {"coordinates":[48.72154000000001,55.97048],"type":"Point"}
}