{
  "type": "Feature",
  "properties": {
    "gn:admin1_code":"76",
    "gn:asciiname":"Orlik",
    "gn:country_code":"RU",
    "gn:dem":253,
    "gn:feature_class":"P",
    "gn:feature_code":"PPL",
    "gn:name":"Orlik",
    "gn:population":0,
    "gn:timezone":"Europe/Moscow",
    "iso:country":"RU",
    "name:bel_x_preferred":[
        "\u041e\u0440\u043b\u0456\u043a"
    ],
    "name:ceb_x_preferred":[
        "Orlik"
    ],
    "name:deu_x_preferred":[
        "Orlik"
    ],
    "name:fra_x_preferred":[
        "Orlik"
    ],
    "name:hye_x_preferred":[
        "\u0555\u0580\u056c\u056b\u056f"
    ],
    "name:ita_x_preferred":[
        "Orlik"
    ],
    "name:jpn_x_preferred":[
        "\u30aa\u30eb\u30ea\u30af"
    ],
    "name:nld_x_preferred":[
        "Orlik"
    ],
    "name:pol_x_preferred":[
        "Orlik"
    ],
    "name:rus_x_preferred":[
        "\u041e\u0440\u043b\u0438\u043a"
    ],
    "name:slk_x_preferred":[
        "Orlik"
    ],
    "name:spa_x_preferred":[
        "Orlik"
    ],
    "name:swe_x_preferred":[
        "Orlik"
    ],
    "name:ukr_x_preferred":[
        "\u041e\u0440\u043b\u0438\u043a"
    ],
    "wof:name":"Orlik",
    "wof:placetype":"locality"
},
  "geometry": {"coordinates":[37.00615,53.49543000000001],"type":"Point"}
}