{
  "type": "Feature",
  "properties": {
    "gn:admin1_code":"76",
    "gn:asciiname":"Orlik",
    "gn:country_code":"RU",
    "gn:dem":253,
    "gn:feature_class":"P",
    "gn:feature_code":"PPL",
    "gn:name":"Orlik",
    "gn:population":0,
    "gn:timezone":"Europe/Moscow",
    "iso:country":"RU",
    "name:rus_x_preferred":[
        "\u041e\u0440\u043b\u0438\u043a"
    ],
    "name:und_x_variant":[
        "\u041e\u0440\u043b\u0438\u043a"
    ],
    "wof:name":"Orlik",
    "wof:placetype":"locality"
},
  "geometry": {"coordinates":[37.00615,53.49543000000001],"type":"Point"}
}