{
  "type": "Feature",
  "properties": {
    "gn:admin1_code":"63",
    "gn:asciiname":"Khobol",
    "gn:country_code":"RU",
    "gn:dem":477,
    "gn:feature_class":"P",
    "gn:feature_code":"PPL",
    "gn:name":"Khobol",
    "gn:population":0,
    "gn:timezone":"Asia/Yakutsk",
    "iso:country":"RU",
    "name:rus_x_preferred":[
        "\u0425\u043e\u0431\u043e\u043b"
    ],
    "wof:name":"Khobol",
    "wof:placetype":"locality"
},
  "geometry": {"coordinates":[130.16666999999998,67.11667],"type":"Point"}
}