{
  "type": "Feature",
  "properties": {
    "gn:admin1_code":"42",
    "gn:asciiname":"Letoshitsy",
    "gn:country_code":"RU",
    "gn:dem":118,
    "gn:feature_class":"P",
    "gn:feature_code":"PPL",
    "gn:name":"Letoshitsy",
    "gn:population":0,
    "gn:timezone":"Europe/Moscow",
    "iso:country":"RU",
    "name:nor_x_preferred":[
        "Letosjitsy"
    ],
    "name:rus_x_preferred":[
        "\u041b\u0435\u0442\u043e\u0448\u0438\u0446\u044b"
    ],
    "wof:name":"Letoshitsy",
    "wof:placetype":"locality"
},
  "geometry": {"coordinates":[29.27548,59.36818],"type":"Point"}
}