{
  "type": "Feature",
  "properties": {
    "gn:admin1_code":"77",
    "gn:asciiname":"Syrkino",
    "gn:country_code":"RU",
    "gn:dem":118,
    "gn:feature_class":"P",
    "gn:feature_code":"PPL",
    "gn:name":"Syrkino",
    "gn:population":0,
    "gn:timezone":"Europe/Moscow",
    "iso:country":"RU",
    "name:rus_x_preferred":[
        "\u0421\u044b\u0440\u043a\u0438\u043d\u043e"
    ],
    "wof:name":"Syrkino",
    "wof:placetype":"locality"
},
  "geometry": {"coordinates":[37.2915,57.1481],"type":"Point"}
}