{
  "type": "Feature",
  "properties": {
    "gn:admin1_code":"16.0",
    "gn:asciiname":"Asakasy",
    "gn:country_code":"RU",
    "gn:dem":111,
    "gn:feature_class":"P",
    "gn:feature_code":"PPL",
    "gn:name":"Asakasy",
    "gn:population":0,
    "gn:timezone":"Europe/Moscow",
    "iso:country":"RU",
    "name:nor_x_preferred":[
        "Asakasy"
    ],
    "name:rus_x_preferred":[
        "\u0410\u0441\u0430\u043a\u0430\u0441\u044b"
    ],
    "wof:name":"Asakasy",
    "wof:placetype":"locality"
},
  "geometry": {"coordinates":[46.88876,55.70183000000001],"type":"Point"}
}