{
  "type": "Feature",
  "properties": {
    "gn:admin1_code":"88",
    "gn:asciiname":"Prokshino",
    "gn:country_code":"RU",
    "gn:dem":125,
    "gn:feature_class":"P",
    "gn:feature_code":"PPL",
    "gn:name":"Prokshino",
    "gn:population":0,
    "gn:timezone":"Europe/Moscow",
    "iso:country":"RU",
    "name:rus_x_preferred":[
        "\u041f\u0440\u043e\u043a\u0448\u0438\u043d\u043e"
    ],
    "wof:name":"Prokshino",
    "wof:placetype":"locality"
},
  "geometry": {"coordinates":[39.05815,57.72141],"type":"Point"}
}