{
  "type": "Feature",
  "properties": {
    "gn:admin1_code":"12",
    "gn:asciiname":"Koshkel'dy",
    "gn:country_code":"RU",
    "gn:dem":118,
    "gn:feature_class":"P",
    "gn:feature_code":"PPL",
    "gn:name":"Koshkel\u2019dy",
    "gn:population":0,
    "gn:timezone":"Europe/Moscow",
    "iso:country":"RU",
    "name:che_x_preferred":[
        "Qo\u015fkelda"
    ],
    "name:che_x_variant":[
        "\u041a\u0445\u043e\u0448\u043a\u0435\u043b\u0434\u0430"
    ],
    "name:rus_x_preferred":[
        "\u041a\u043e\u0448\u043a\u0435\u043b\u044c\u0434\u044b"
    ],
    "name:rus_x_variant":[
        "Ko\u0161kel\u2019dy"
    ],
    "name:und_x_variant":[
        "Gerga",
        "Qqo\u015fkelda",
        "Gergi",
        "Koshkel\u2019dy"
    ],
    "wof:name":"Koshkel'dy",
    "wof:placetype":"locality"
},
  "geometry": {"coordinates":[46.35266,43.25023],"type":"Point"}
}