{
  "type": "Feature",
  "properties": {
    "gn:admin1_code":"51.0",
    "gn:asciiname":"Pestovo",
    "gn:country_code":"RU",
    "gn:dem":88,
    "gn:feature_class":"P",
    "gn:feature_code":"PPL",
    "gn:name":"Pestovo",
    "gn:population":0,
    "gn:timezone":"Europe/Moscow",
    "iso:country":"RU",
    "name:nor_x_preferred":[
        "Pestovo"
    ],
    "name:rus_x_preferred":[
        "\u041f\u0435\u0441\u0442\u043e\u0432\u043e"
    ],
    "wof:name":"Pestovo",
    "wof:placetype":"locality"
},
  "geometry": {"coordinates":[43.83949000000001,56.55928],"type":"Point"}
}