{
  "type": "Feature",
  "properties": {
    "gn:admin1_code":"91",
    "gn:asciiname":"Lokshino",
    "gn:country_code":"RU",
    "gn:dem":321,
    "gn:feature_class":"P",
    "gn:feature_code":"PPL",
    "gn:name":"Lokshino",
    "gn:population":0,
    "gn:timezone":"Asia/Krasnoyarsk",
    "iso:country":"RU",
    "name:eng_x_preferred":[
        "Lokshino"
    ],
    "name:nor_x_preferred":[
        "Loksjino"
    ],
    "name:rus_x_preferred":[
        "\u041b\u043e\u043a\u0448\u0438\u043d\u043e"
    ],
    "name:und_x_variant":[
        "Lakshina"
    ],
    "wof:name":"Lokshino",
    "wof:placetype":"locality"
},
  "geometry": {"coordinates":[89.68944,55.47028],"type":"Point"}
}