{
  "type": "Feature",
  "properties": {
    "gn:admin1_code":"56",
    "gn:asciiname":"Shumova",
    "gn:country_code":"RU",
    "gn:dem":203,
    "gn:feature_class":"P",
    "gn:feature_code":"PPL",
    "gn:name":"Shumova",
    "gn:population":0,
    "gn:timezone":"Europe/Moscow",
    "iso:country":"RU",
    "name:rus_x_preferred":[
        "\u0428\u0443\u043c\u043e\u0432\u0430"
    ],
    "name:und_x_variant":[
        "Shumovo",
        "Shumova"
    ],
    "wof:name":"Shumova",
    "wof:placetype":"locality"
},
  "geometry": {"coordinates":[36.22083,53.24936999999999],"type":"Point"}
}