{
  "type": "Feature",
  "properties": {
    "gn:admin1_code":"21",
    "gn:asciiname":"Zakomel'ye",
    "gn:country_code":"RU",
    "gn:dem":121,
    "gn:feature_class":"P",
    "gn:feature_code":"PPL",
    "gn:name":"Zakomel\u2019ye",
    "gn:population":0,
    "gn:timezone":"Europe/Moscow",
    "iso:country":"RU",
    "name:rus_x_preferred":[
        "\u0417\u0430\u043a\u043e\u043c\u0435\u043b\u044c\u0435"
    ],
    "name:und_x_variant":[
        "Zokomel\u2019ye",
        "Zakomel\u2019ye"
    ],
    "wof:name":"Zakomel'ye",
    "wof:placetype":"locality"
},
  "geometry": {"coordinates":[40.14287,56.57286],"type":"Point"}
}