{
  "type": "Feature",
  "properties": {
    "gn:admin1_code":"85",
    "gn:asciiname":"Berezhok",
    "gn:country_code":"RU",
    "gn:dem":122,
    "gn:feature_class":"P",
    "gn:feature_code":"PPL",
    "gn:name":"Berezhok",
    "gn:population":0,
    "gn:timezone":"Europe/Moscow",
    "iso:country":"RU",
    "name:rus_x_preferred":[
        "\u0411\u0435\u0440\u0435\u0436\u043e\u043a"
    ],
    "name:und_x_variant":[
        "\u0411\u0435\u0440\u0435\u0436\u043e\u043a"
    ],
    "wof:name":"Berezhok",
    "wof:placetype":"locality"
},
  "geometry": {"coordinates":[36.4934,59.5711],"type":"Point"}
}