{
  "type": "Feature",
  "properties": {
    "gn:admin1_code":"63",
    "gn:asciiname":"Kuyurdu",
    "gn:country_code":"RU",
    "gn:dem":335,
    "gn:feature_class":"P",
    "gn:feature_code":"PPL",
    "gn:name":"Kuyurdu",
    "gn:population":0,
    "gn:timezone":"Asia/Yakutsk",
    "iso:country":"RU",
    "name:rus_x_preferred":[
        "\u041a\u0443\u044e\u0440\u0434\u0443"
    ],
    "wof:name":"Kuyurdu",
    "wof:placetype":"locality"
},
  "geometry": {"coordinates":[112.84999999999999,61.63333000000001],"type":"Point"}
}