{
  "type": "Feature",
  "properties": {
    "gn:admin1_code":"79",
    "gn:asciiname":"Chalaaty",
    "gn:country_code":"RU",
    "gn:dem":1821,
    "gn:feature_class":"P",
    "gn:feature_code":"PPL",
    "gn:name":"Chalaaty",
    "gn:population":0,
    "gn:timezone":"Asia/Krasnoyarsk",
    "iso:country":"RU",
    "wof:name":"Chalaaty",
    "wof:placetype":"locality"
},
  "geometry": {"coordinates":[93.26667,50.85],"type":"Point"}
}