{
  "type": "Feature",
  "properties": {
    "gn:admin1_code":"90.0",
    "gn:asciiname":"Zaosinovo",
    "gn:country_code":"RU",
    "gn:dem":93,
    "gn:feature_class":"P",
    "gn:feature_code":"PPL",
    "gn:name":"Zaosinovo",
    "gn:population":0,
    "gn:timezone":"Asia/Yekaterinburg",
    "iso:country":"RU",
    "name:che_x_preferred":[
        "\u0417\u0430\u043e\u0441\u0438\u043d\u043e\u0432\u043e"
    ],
    "name:rus_x_preferred":[
        "\u0417\u0430\u043e\u0441\u0438\u043d\u043e\u0432\u043e"
    ],
    "wof:name":"Zaosinovo",
    "wof:placetype":"locality"
},
  "geometry": {"coordinates":[55.9875,57.9912],"type":"Point"}
}