{
  "type": "Feature",
  "properties": {
    "gn:admin1_code":"8",
    "gn:asciiname":"Yelantub",
    "gn:country_code":"RU",
    "gn:dem":284,
    "gn:feature_class":"P",
    "gn:feature_code":"PPL",
    "gn:name":"Yelantub",
    "gn:population":0,
    "gn:timezone":"Asia/Yekaterinburg",
    "iso:country":"RU",
    "name:eng_x_preferred":[
        "Yelantub"
    ],
    "name:nor_x_preferred":[
        "Jelantub"
    ],
    "name:rus_x_preferred":[
        "\u0415\u043b\u0430\u043d\u0442\u0443\u0431"
    ],
    "wof:name":"Yelantub",
    "wof:placetype":"locality"
},
  "geometry": {"coordinates":[57.85678000000001,55.63721],"type":"Point"}
}