{
  "type": "Feature",
  "properties": {
    "gn:admin1_code":"52",
    "gn:asciiname":"Serkino",
    "gn:country_code":"RU",
    "gn:dem":154,
    "gn:feature_class":"P",
    "gn:feature_code":"PPL",
    "gn:name":"Serkino",
    "gn:population":0,
    "gn:timezone":"Europe/Moscow",
    "iso:country":"RU",
    "name:rus_x_preferred":[
        "\u0421\u0435\u0440\u043a\u0438\u043d\u043e"
    ],
    "name:und_x_variant":[
        "\u0421\u0435\u0440\u043a\u0438\u043d\u043e"
    ],
    "wof:name":"Serkino",
    "wof:placetype":"locality"
},
  "geometry": {"coordinates":[33.53333,59.06667],"type":"Point"}
}