{
  "type": "Feature",
  "properties": {
    "gn:admin1_code":"10",
    "gn:asciiname":"Andrynki",
    "gn:country_code":"RU",
    "gn:dem":208,
    "gn:feature_class":"P",
    "gn:feature_code":"PPL",
    "gn:name":"Andrynki",
    "gn:population":0,
    "gn:timezone":"Europe/Moscow",
    "iso:country":"RU",
    "name:nor_x_preferred":[
        "Andrynki"
    ],
    "name:rus_x_preferred":[
        "\u0410\u043d\u0434\u0440\u044b\u043d\u043a\u0438"
    ],
    "wof:name":"Andrynki",
    "wof:placetype":"locality"
},
  "geometry": {"coordinates":[34.90147,52.72169],"type":"Point"}
}