{
  "type": "Feature",
  "properties": {
    "gn:admin1_code":"20",
    "gn:asciiname":"Lebedeva",
    "gn:country_code":"RU",
    "gn:dem":813,
    "gn:feature_class":"P",
    "gn:feature_code":"PPL",
    "gn:name":"Lebedeva",
    "gn:population":0,
    "gn:timezone":"Asia/Irkutsk",
    "iso:country":"RU",
    "name:rus_x_preferred":[
        "\u041b\u0435\u0431\u0435\u0434\u0435\u0432\u0430"
    ],
    "wof:name":"Lebedeva",
    "wof:placetype":"locality"
},
  "geometry": {"coordinates":[99.2636,54.0497],"type":"Point"}
}