{
  "type": "Feature",
  "properties": {
    "gn:admin1_code":"20",
    "gn:asciiname":"Tyret' Vtoraya",
    "gn:country_code":"RU",
    "gn:dem":463,
    "gn:feature_class":"P",
    "gn:feature_code":"PPL",
    "gn:name":"Tyret\u2019 Vtoraya",
    "gn:population":0,
    "gn:timezone":"Asia/Irkutsk",
    "iso:country":"RU",
    "name:rus_x_preferred":[
        "\u0422\u044b\u0440\u0435\u0442\u044c \u0412\u0442\u043e\u0440\u0430\u044f"
    ],
    "name:und_x_variant":[
        "Vtoraya Tyret\u2019",
        "Tyret\u2019 Vtoroye",
        "Tyret\u2019 Vtoraya"
    ],
    "wof:name":"Tyret' Vtoraya",
    "wof:placetype":"locality"
},
  "geometry": {"coordinates":[102.3207,53.7214],"type":"Point"}
}