{
  "type": "Feature",
  "properties": {
    "gn:admin1_code":"8",
    "gn:asciiname":"Novopokrovskiy",
    "gn:country_code":"RU",
    "gn:dem":555,
    "gn:feature_class":"P",
    "gn:feature_code":"PPL",
    "gn:name":"Novopokrovskiy",
    "gn:population":0,
    "gn:timezone":"Asia/Yekaterinburg",
    "iso:country":"RU",
    "name:eng_x_preferred":[
        "Novopokrovskiy"
    ],
    "name:nor_x_preferred":[
        "Novopokrovskij"
    ],
    "name:rus_x_preferred":[
        "\u041d\u043e\u0432\u043e\u043f\u043e\u043a\u0440\u043e\u0432\u0441\u043a\u0438\u0439"
    ],
    "name:und_x_variant":[
        "Pokrovskoye"
    ],
    "wof:name":"Novopokrovskiy",
    "wof:placetype":"locality"
},
  "geometry": {"coordinates":[57.1701,52.4721],"type":"Point"}
}