{
  "type": "Feature",
  "properties": {
    "gn:admin1_code":"60",
    "gn:asciiname":"Glushnevo",
    "gn:country_code":"RU",
    "gn:dem":186,
    "gn:feature_class":"P",
    "gn:feature_code":"PPL",
    "gn:name":"Glushnevo",
    "gn:population":0,
    "gn:timezone":"Europe/Moscow",
    "iso:country":"RU",
    "name:rus_x_preferred":[
        "\u0413\u043b\u0443\u0448\u043d\u0435\u0432\u043e"
    ],
    "name:und_x_variant":[
        "\u0413\u043b\u0443\u0448\u043d\u0435\u0432\u043e"
    ],
    "wof:name":"Glushnevo",
    "wof:placetype":"locality"
},
  "geometry": {"coordinates":[29.2711,56.7307],"type":"Point"}
}