{
  "type": "Feature",
  "properties": {
    "gn:admin1_code":"77",
    "gn:asciiname":"Komlevo",
    "gn:country_code":"RU",
    "gn:dem":171,
    "gn:feature_class":"P",
    "gn:feature_code":"PPL",
    "gn:name":"Komlevo",
    "gn:population":0,
    "gn:timezone":"Europe/Moscow",
    "iso:country":"RU",
    "name:rus_x_preferred":[
        "\u041a\u043e\u043c\u043b\u0435\u0432\u043e"
    ],
    "name:und_x_variant":[
        "\u041a\u043e\u043c\u043b\u0435\u0432\u043e"
    ],
    "wof:name":"Komlevo",
    "wof:placetype":"locality"
},
  "geometry": {"coordinates":[37.2738,58.4349],"type":"Point"}
}