{
  "type": "Feature",
  "properties": {
    "gn:admin1_code":"55",
    "gn:asciiname":"Studentsy",
    "gn:country_code":"RU",
    "gn:dem":135,
    "gn:feature_class":"P",
    "gn:feature_code":"PPL",
    "gn:name":"Studentsy",
    "gn:population":0,
    "gn:timezone":"Asia/Yekaterinburg",
    "iso:country":"RU",
    "name:eng_x_preferred":[
        "Studentsy"
    ],
    "name:nor_x_preferred":[
        "Studentsy"
    ],
    "name:rus_x_preferred":[
        "\u0421\u0442\u0443\u0434\u0435\u043d\u0446\u044b"
    ],
    "name:und_x_variant":[
        "Studentskiy",
        "Studenetski",
        "Studentsy"
    ],
    "wof:name":"Studentsy",
    "wof:placetype":"locality"
},
  "geometry": {"coordinates":[55.85859,51.86593],"type":"Point"}
}