{
  "type": "Feature",
  "properties": {
    "gn:admin1_code":"47.0",
    "gn:asciiname":"Pushkino",
    "gn:country_code":"RU",
    "gn:dem":149,
    "gn:feature_class":"P",
    "gn:feature_code":"PPL",
    "gn:name":"Pushkino",
    "gn:population":0,
    "gn:timezone":"Europe/Moscow",
    "iso:country":"RU",
    "name:ceb_x_preferred":[
        "Pushkino"
    ],
    "name:rus_x_preferred":[
        "\u041f\u0443\u0448\u043a\u0438\u043d\u043e"
    ],
    "name:sco_x_preferred":[
        "Pushkino"
    ],
    "name:swe_x_preferred":[
        "Pushkino"
    ],
    "name:und_x_variant":[
        "\u041f\u0443\u0448\u043a\u0438\u043d\u043e"
    ],
    "wof:name":"Pushkino",
    "wof:placetype":"locality"
},
  "geometry": {"coordinates":[37.36025,55.53806],"type":"Point"}
}