{
  "type": "Feature",
  "properties": {
    "gn:admin1_code":"53",
    "gn:asciiname":"Novoyarkovskiy",
    "gn:cc2":"RU",
    "gn:country_code":"RU",
    "gn:dem":122,
    "gn:feature_class":"P",
    "gn:feature_code":"PPL",
    "gn:name":"Novoyarkovskiy",
    "gn:population":0,
    "gn:timezone":"Asia/Novosibirsk",
    "iso:country":"RU",
    "name:und_x_variant":[
        "Novo-Yarokovskiy",
        "Novoyarkovskiy"
    ],
    "wof:name":"Novoyarkovskiy",
    "wof:placetype":"locality"
},
  "geometry": {"coordinates":[79.61667,54.71666999999999],"type":"Point"}
}