{
  "type": "Feature",
  "properties": {
    "gn:admin1_code":"56",
    "gn:asciiname":"Kosareva",
    "gn:country_code":"RU",
    "gn:dem":196,
    "gn:feature_class":"P",
    "gn:feature_code":"PPL",
    "gn:name":"Kosareva",
    "gn:population":0,
    "gn:timezone":"Europe/Moscow",
    "iso:country":"RU",
    "name:rus_x_preferred":[
        "\u041a\u043e\u0441\u0430\u0440\u0435\u0432\u0430"
    ],
    "name:und_x_variant":[
        "\u041a\u043e\u0441\u0430\u0440\u0435\u0432\u0430"
    ],
    "wof:name":"Kosareva",
    "wof:placetype":"locality"
},
  "geometry": {"coordinates":[35.8131,52.6028],"type":"Point"}
}