{
  "type": "Feature",
  "properties": {
    "gn:admin1_code":"85.0",
    "gn:asciiname":"Boyarskoye",
    "gn:country_code":"RU",
    "gn:dem":170,
    "gn:feature_class":"P",
    "gn:feature_code":"PPL",
    "gn:name":"Boyarskoye",
    "gn:population":0,
    "gn:timezone":"Europe/Moscow",
    "iso:country":"RU",
    "name:rus_x_preferred":[
        "\u0411\u043e\u044f\u0440\u0441\u043a\u043e\u0435"
    ],
    "wof:name":"Boyarskoye",
    "wof:placetype":"locality"
},
  "geometry": {"coordinates":[40.23333,59.95],"type":"Point"}
}