{
  "type": "Feature",
  "properties": {
    "gn:admin1_code":"52.0",
    "gn:asciiname":"Bol'shoy Latovets",
    "gn:country_code":"RU",
    "gn:dem":61,
    "gn:feature_class":"P",
    "gn:feature_code":"PPL",
    "gn:name":"Bol\u2019shoy Latovets",
    "gn:population":0,
    "gn:timezone":"Europe/Moscow",
    "iso:country":"RU",
    "name:rus_x_preferred":[
        "\u0411\u043e\u043b\u044c\u0448\u043e\u0439 \u041b\u0430\u0442\u043e\u0432\u0435\u0446"
    ],
    "name:und_x_variant":[
        "Bol\u2019shoy Latovets"
    ],
    "wof:name":"Bol'shoy Latovets",
    "wof:placetype":"locality"
},
  "geometry": {"coordinates":[30.26988,58.71965],"type":"Point"}
}