{
  "type": "Feature",
  "properties": {
    "gn:admin1_code":"17",
    "gn:admin2_code":"557977",
    "gn:asciiname":"Askhabil'-Kuli",
    "gn:country_code":"RU",
    "gn:dem":1420,
    "gn:feature_class":"P",
    "gn:feature_code":"PPL",
    "gn:name":"Askhabil\u2019-Kuli",
    "gn:population":0,
    "gn:timezone":"Europe/Moscow",
    "iso:country":"RU",
    "name:nor_x_preferred":[
        "Askhabil-Kuli"
    ],
    "name:rus_x_preferred":[
        "\u0410\u0441\u0445\u0430\u0431\u0438\u043b\u044c-\u041a\u0443\u043b\u0438"
    ],
    "name:und_x_variant":[
        "Askhabil\u2019-Kuli"
    ],
    "wof:name":"Askhabil'-Kuli",
    "wof:placetype":"locality"
},
  "geometry": {"coordinates":[46.85417,42.41],"type":"Point"}
}