{
  "type": "Feature",
  "properties": {
    "gn:admin1_code":"56",
    "gn:asciiname":"Yevlanovo",
    "gn:country_code":"RU",
    "gn:dem":175,
    "gn:feature_class":"P",
    "gn:feature_code":"PPL",
    "gn:name":"Yevlanovo",
    "gn:population":0,
    "gn:timezone":"Europe/Moscow",
    "iso:country":"RU",
    "name:eng_x_preferred":[
        "Yevlanovo"
    ],
    "name:nor_x_preferred":[
        "Jevlanovo"
    ],
    "name:rus_x_preferred":[
        "\u0415\u0432\u043b\u0430\u043d\u043e\u0432\u043e"
    ],
    "name:und_x_variant":[
        "Yevlanova",
        "Yevlanovo"
    ],
    "wof:name":"Yevlanovo",
    "wof:placetype":"locality"
},
  "geometry": {"coordinates":[37.40712,52.21756],"type":"Point"}
}