{
  "type": "Feature",
  "properties": {
    "gn:admin1_code":"64",
    "gn:asciiname":"Polyakovo",
    "gn:country_code":"RU",
    "gn:dem":9,
    "gn:feature_class":"P",
    "gn:feature_code":"PPL",
    "gn:name":"Polyakovo",
    "gn:population":0,
    "gn:timezone":"Asia/Sakhalin",
    "iso:country":"RU",
    "name:rus_x_preferred":[
        "\u041f\u043e\u043b\u044f\u043a\u043e\u0432\u043e"
    ],
    "name:und_x_variant":[
        "Izruchnoye",
        "Tei",
        "Zusui",
        "Polyakovo",
        "\u041f\u043e\u043b\u044f\u043a\u043e\u0432\u043e"
    ],
    "wof:name":"Polyakovo",
    "wof:placetype":"locality"
},
  "geometry": {"coordinates":[142.03748000000004,47.01435],"type":"Point"}
}