{
  "type": "Feature",
  "properties": {
    "gn:admin1_code":"63",
    "gn:asciiname":"Bychila",
    "gn:country_code":"RU",
    "gn:dem":56,
    "gn:feature_class":"P",
    "gn:feature_code":"PPL",
    "gn:name":"Bychila",
    "gn:population":0,
    "gn:timezone":"Asia/Magadan",
    "iso:country":"RU",
    "name:rus_x_preferred":[
        "\u0411\u044b\u0447\u0438\u043b\u0430"
    ],
    "name:und_x_variant":[
        "\u0411\u044b\u0447\u0438\u043b\u0430"
    ],
    "wof:name":"Bychila",
    "wof:placetype":"locality"
},
  "geometry": {"coordinates":[152.28333000000001,68.93333],"type":"Point"}
}