{
  "type": "Feature",
  "properties": {
    "gn:admin1_code":"8",
    "gn:asciiname":"Munasovo",
    "gn:country_code":"RU",
    "gn:dem":215,
    "gn:feature_class":"P",
    "gn:feature_code":"PPL",
    "gn:name":"Munasovo",
    "gn:population":0,
    "gn:timezone":"Asia/Yekaterinburg",
    "iso:country":"RU",
    "name:bak_x_preferred":[
        "\u041c\u043e\u043d\u0430\u0441"
    ],
    "name:che_x_preferred":[
        "\u041c\u0443\u043d\u0430\u0441\u043e\u0432\u043e"
    ],
    "name:hye_x_preferred":[
        "\u0544\u0578\u0582\u0576\u0561\u057d\u0578\u057e\u0578"
    ],
    "name:kat_x_preferred":[
        "\u10db\u10e3\u10dc\u10d0\u10e1\u10dd\u10d5\u10dd"
    ],
    "name:kaz_x_preferred":[
        "\u041c\u0443\u043d\u0430\u0441"
    ],
    "name:kir_x_preferred":[
        "\u041c\u0443\u043d\u0430\u0441"
    ],
    "name:rus_x_preferred":[
        "\u041c\u0443\u043d\u0430\u0441\u043e\u0432\u043e"
    ],
    "name:tat_x_preferred":[
        "\u041c\u043e\u043d\u0430\u0441"
    ],
    "name:und_x_variant":[
        "Manasova",
        "Munasovo"
    ],
    "wof:name":"Munasovo",
    "wof:placetype":"locality"
},
  "geometry": {"coordinates":[58.59222,55.7525],"type":"Point"}
}