{
  "type": "Feature",
  "properties": {
    "gn:admin1_code":"8",
    "gn:asciiname":"Munasovo",
    "gn:country_code":"RU",
    "gn:dem":215,
    "gn:feature_class":"P",
    "gn:feature_code":"PPL",
    "gn:name":"Munasovo",
    "gn:population":0,
    "gn:timezone":"Asia/Yekaterinburg",
    "iso:country":"RU",
    "name:rus_x_preferred":[
        "\u041c\u0443\u043d\u0430\u0441\u043e\u0432\u043e"
    ],
    "name:und_x_variant":[
        "Manasova",
        "Munasovo",
        "\u041c\u0443\u043d\u0430\u0441\u043e\u0432\u043e"
    ],
    "wof:name":"Munasovo",
    "wof:placetype":"locality"
},
  "geometry": {"coordinates":[58.59222,55.7525],"type":"Point"}
}