{
  "type": "Feature",
  "properties": {
    "gn:admin1_code":"4",
    "gn:asciiname":"Malaya Shelkovka",
    "gn:country_code":"RU",
    "gn:dem":256,
    "gn:feature_class":"P",
    "gn:feature_code":"PPL",
    "gn:name":"Malaya Shelkovka",
    "gn:population":0,
    "gn:timezone":"Asia/Barnaul",
    "iso:country":"RU",
    "name:eng_x_preferred":[
        "Malaya Shelkovka"
    ],
    "name:nor_x_preferred":[
        "Mal.Sjelkovka"
    ],
    "name:rus_x_preferred":[
        "\u041c\u0430\u043b.\u0428\u0435\u043b\u043a\u043e\u0432\u043a\u0430"
    ],
    "name:rus_x_variant":[
        "\u041c\u0430\u043b\u0430\u044f \u0428\u0435\u043b\u043a\u043e\u0432\u043a\u0430"
    ],
    "name:und_x_variant":[
        "Maloye Shelkovnikovo"
    ],
    "wof:name":"Malaya Shelkovka",
    "wof:placetype":"locality"
},
  "geometry": {"coordinates":[80.7533,51.4949],"type":"Point"}
}