{
  "type": "Feature",
  "properties": {
    "gn:admin1_code":"45",
    "gn:asciiname":"Malyy Puyal",
    "gn:country_code":"RU",
    "gn:dem":118,
    "gn:feature_class":"P",
    "gn:feature_code":"PPL",
    "gn:name":"Malyy Puyal",
    "gn:population":0,
    "gn:timezone":"Europe/Moscow",
    "iso:country":"RU",
    "name:rus_x_preferred":[
        "\u041c\u0430\u043b\u044b\u0439 \u041f\u0443\u044f\u043b"
    ],
    "wof:name":"Malyy Puyal",
    "wof:placetype":"locality"
},
  "geometry": {"coordinates":[48.11444,56.85389],"type":"Point"}
}