{
  "type": "Feature",
  "properties": {
    "gn:admin1_code":"63",
    "gn:asciiname":"Khampa",
    "gn:country_code":"RU",
    "gn:dem":200,
    "gn:feature_class":"P",
    "gn:feature_code":"PPL",
    "gn:name":"Khampa",
    "gn:population":0,
    "gn:timezone":"Asia/Yakutsk",
    "iso:country":"RU",
    "name:eng_x_preferred":[
        "Khampa"
    ],
    "name:nor_x_preferred":[
        "Khampa"
    ],
    "name:rus_x_preferred":[
        "\u0425\u0430\u043c\u043f\u0430"
    ],
    "name:und_x_variant":[
        "\u0425\u0430\u043c\u043f\u0430",
        "Khampa"
    ],
    "wof:name":"Khampa",
    "wof:placetype":"locality"
},
  "geometry": {"coordinates":[124.0932,62.10224],"type":"Point"}
}