{
  "type": "Feature",
  "properties": {
    "gn:admin1_code":"32",
    "gn:asciiname":"Kinyaminy Vtoryye",
    "gn:country_code":"RU",
    "gn:dem":42,
    "gn:feature_class":"P",
    "gn:feature_code":"PPL",
    "gn:name":"Kinyaminy Vtoryye",
    "gn:population":0,
    "gn:timezone":"Asia/Yekaterinburg",
    "iso:country":"RU",
    "name:rus_x_preferred":[
        "\u041a\u0438\u043d\u044f\u043c\u0438\u043d\u044b \u0412\u0442\u043e\u0440\u044b\u0435"
    ],
    "wof:name":"Kinyaminy Vtoryye",
    "wof:placetype":"locality"
},
  "geometry": {"coordinates":[74.58333,60.28333000000001],"type":"Point"}
}