{
  "type": "Feature",
  "properties": {
    "gn:admin1_code":"85",
    "gn:asciiname":"Minino",
    "gn:country_code":"RU",
    "gn:dem":122,
    "gn:feature_class":"P",
    "gn:feature_code":"PPL",
    "gn:name":"Minino",
    "gn:population":0,
    "gn:timezone":"Europe/Moscow",
    "iso:country":"RU",
    "name:che_x_preferred":[
        "\u041c\u0438\u043d\u0438\u043d\u043e"
    ],
    "name:rus_x_preferred":[
        "\u041c\u0438\u043d\u0438\u043d\u043e"
    ],
    "name:und_x_variant":[
        "\u041c\u0438\u043d\u0438\u043d\u043e"
    ],
    "wof:name":"Minino",
    "wof:placetype":"locality"
},
  "geometry": {"coordinates":[39.1439,59.7411],"type":"Point"}
}