{
  "type": "Feature",
  "properties": {
    "gn:admin1_code":"69",
    "gn:asciiname":"Mikhalinovo",
    "gn:country_code":"RU",
    "gn:dem":197,
    "gn:feature_class":"P",
    "gn:feature_code":"PPL",
    "gn:name":"Mikhalinovo",
    "gn:population":0,
    "gn:timezone":"Europe/Moscow",
    "iso:country":"RU",
    "name:rus_x_preferred":[
        "\u041c\u0438\u0445\u0430\u043b\u0438\u043d\u043e\u0432\u043e"
    ],
    "name:und_x_variant":[
        "\u041c\u0438\u0445\u0430\u043b\u0438\u043d\u043e\u0432\u043e"
    ],
    "wof:name":"Mikhalinovo",
    "wof:placetype":"locality"
},
  "geometry": {"coordinates":[32.85,53.78333000000001],"type":"Point"}
}