{
  "type": "Feature",
  "properties": {
    "gn:admin1_code":"54",
    "gn:asciiname":"Lesnogorskiy",
    "gn:country_code":"RU",
    "gn:dem":114,
    "gn:feature_class":"P",
    "gn:feature_code":"PPL",
    "gn:name":"Lesnogorskiy",
    "gn:population":0,
    "gn:timezone":"Asia/Omsk",
    "iso:country":"RU",
    "name:rus_x_preferred":[
        "\u041b\u0435\u0441\u043d\u043e\u0433\u043e\u0440\u0441\u043a\u0438\u0439"
    ],
    "name:und_x_variant":[
        "\u041b\u0435\u0441\u043d\u043e\u0433\u043e\u0440\u0441\u043a\u0438\u0439"
    ],
    "wof:name":"Lesnogorskiy",
    "wof:placetype":"locality"
},
  "geometry": {"coordinates":[72.18519999999999,54.8459],"type":"Point"}
}