{
  "type": "Feature",
  "properties": {
    "gn:admin1_code":"81",
    "gn:asciiname":"Volostnikovka",
    "gn:country_code":"RU",
    "gn:dem":60,
    "gn:feature_class":"P",
    "gn:feature_code":"PPL",
    "gn:name":"Volostnikovka",
    "gn:population":0,
    "gn:timezone":"Europe/Ulyanovsk",
    "iso:country":"RU",
    "name:eng_x_preferred":[
        "Volostnikovka"
    ],
    "name:nor_x_preferred":[
        "Volostnikovka"
    ],
    "name:rus_x_preferred":[
        "\u0412\u043e\u043b\u043e\u0441\u0442\u043d\u0438\u043a\u043e\u0432\u043a\u0430"
    ],
    "wof:name":"Volostnikovka",
    "wof:placetype":"locality"
},
  "geometry": {"coordinates":[49.03333,54.73333],"type":"Point"}
}