{
  "type": "Feature",
  "properties": {
    "gn:admin1_code":"61",
    "gn:asciiname":"Bani",
    "gn:country_code":"RU",
    "gn:dem":220,
    "gn:feature_class":"P",
    "gn:feature_code":"PPL",
    "gn:name":"Bani",
    "gn:population":0,
    "gn:timezone":"Europe/Moscow",
    "iso:country":"RU",
    "name:nor_x_preferred":[
        "Bani"
    ],
    "name:rus_x_preferred":[
        "\u0411\u0430\u043d\u0438"
    ],
    "wof:name":"Bani",
    "wof:placetype":"locality"
},
  "geometry": {"coordinates":[40.16361,49.62889000000001],"type":"Point"}
}