{
  "type": "Feature",
  "properties": {
    "gn:admin1_code":"52.0",
    "gn:asciiname":"Bragin Ostrov",
    "gn:country_code":"RU",
    "gn:dem":65,
    "gn:feature_class":"P",
    "gn:feature_code":"PPL",
    "gn:name":"Bragin Ostrov",
    "gn:population":0,
    "gn:timezone":"Europe/Moscow",
    "iso:country":"RU",
    "name:rus_x_preferred":[
        "\u0411\u0440\u0430\u0433\u0438\u043d \u041e\u0441\u0442\u0440\u043e\u0432"
    ],
    "name:und_x_variant":[
        "\u0411\u0440\u0430\u0433\u0438\u043d \u041e\u0441\u0442\u0440\u043e\u0432"
    ],
    "wof:name":"Bragin Ostrov",
    "wof:placetype":"locality"
},
  "geometry": {"coordinates":[32.23333,59.05],"type":"Point"}
}