{
  "type": "Feature",
  "properties": {
    "gn:admin1_code":"28",
    "gn:asciiname":"Salma",
    "gn:cc2":"RU",
    "gn:country_code":"RU",
    "gn:dem":130,
    "gn:feature_class":"P",
    "gn:feature_code":"PPL",
    "gn:name":"Salma",
    "gn:population":0,
    "gn:timezone":"Europe/Moscow",
    "iso:country":"RU",
    "name:ara_x_preferred":[
        "\u0633\u0644\u0645\u0649"
    ],
    "name:deu_x_preferred":[
        "Salma"
    ],
    "name:fin_x_preferred":[
        "Salmivaara"
    ],
    "name:fra_x_preferred":[
        "Salma"
    ],
    "name:isl_x_preferred":[
        "Salma"
    ],
    "name:nno_x_preferred":[
        "Salma"
    ],
    "name:nor_x_preferred":[
        "Salma"
    ],
    "name:rus_x_preferred":[
        "\u0421\u0430\u043b\u043c\u0430"
    ],
    "name:rus_x_variant":[
        "\u0421\u0430\u043b\u044c\u043c\u0430"
    ],
    "name:spa_x_preferred":[
        "Salma"
    ],
    "name:ukr_x_preferred":[
        "\u0421\u0430\u043b\u044c\u043c\u0430"
    ],
    "name:und_x_variant":[
        "Salmavaara"
    ],
    "wof:name":"Salma",
    "wof:placetype":"locality"
},
  "geometry": {"coordinates":[32.13333,65.81667],"type":"Point"}
}