{
  "type": "Feature",
  "properties": {
    "gn:admin1_code":"77",
    "gn:asciiname":"Ladygino",
    "gn:country_code":"RU",
    "gn:dem":133,
    "gn:feature_class":"P",
    "gn:feature_code":"PPL",
    "gn:name":"Ladygino",
    "gn:population":0,
    "gn:timezone":"Europe/Moscow",
    "iso:country":"RU",
    "name:rus_x_preferred":[
        "\u041b\u0430\u0434\u044b\u0433\u0438\u043d\u043e"
    ],
    "wof:name":"Ladygino",
    "wof:placetype":"locality"
},
  "geometry": {"coordinates":[37.9404,57.3425],"type":"Point"}
}