{
  "type": "Feature",
  "properties": {
    "gn:admin1_code":"77",
    "gn:asciiname":"Gorovakha",
    "gn:cc2":"RU",
    "gn:country_code":"RU",
    "gn:dem":253,
    "gn:feature_class":"P",
    "gn:feature_code":"PPL",
    "gn:name":"Gorovakha",
    "gn:population":0,
    "gn:timezone":"Europe/Moscow",
    "iso:country":"RU",
    "name:rus_x_preferred":[
        "\u0413\u043e\u0440\u043e\u0432\u0430\u0445\u0430"
    ],
    "name:und_x_variant":[
        "Gorovkha",
        "Gorovakha"
    ],
    "wof:name":"Gorovakha",
    "wof:placetype":"locality"
},
  "geometry": {"coordinates":[33.56556,56.59222],"type":"Point"}
}