{
  "type": "Feature",
  "properties": {
    "gn:admin1_code":"84",
    "gn:asciiname":"Trud-Rassvet",
    "gn:country_code":"RU",
    "gn:dem":134,
    "gn:feature_class":"P",
    "gn:feature_code":"PPL",
    "gn:name":"Trud-Rassvet",
    "gn:population":0,
    "gn:timezone":"Europe/Volgograd",
    "iso:country":"RU",
    "name:rus_x_preferred":[
        "\u0422\u0440\u0443\u0434-\u0420\u0430\u0441\u0441\u0432\u0435\u0442"
    ],
    "wof:name":"Trud-Rassvet",
    "wof:placetype":"locality"
},
  "geometry": {"coordinates":[42.9056,50.3718],"type":"Point"}
}