{
  "type": "Feature",
  "properties": {
    "gn:admin1_code":"43",
    "gn:asciiname":"Kuvyazevo",
    "gn:country_code":"RU",
    "gn:dem":124,
    "gn:feature_class":"P",
    "gn:feature_code":"PPL",
    "gn:name":"Kuvyazevo",
    "gn:population":0,
    "gn:timezone":"Europe/Moscow",
    "iso:country":"RU",
    "name:rus_x_preferred":[
        "\u041a\u0443\u0432\u044f\u0437\u0435\u0432\u043e"
    ],
    "wof:name":"Kuvyazevo",
    "wof:placetype":"locality"
},
  "geometry": {"coordinates":[40.0752,52.862],"type":"Point"}
}