{
  "type": "Feature",
  "properties": {
    "gn:admin1_code":"9",
    "gn:asciiname":"Shirokoye",
    "gn:country_code":"RU",
    "gn:dem":125,
    "gn:feature_class":"P",
    "gn:feature_code":"PPL",
    "gn:name":"Shirokoye",
    "gn:population":0,
    "gn:timezone":"Europe/Moscow",
    "iso:country":"RU",
    "name:rus_x_preferred":[
        "\u0428\u0438\u0440\u043e\u043a\u043e\u0435"
    ],
    "wof:name":"Shirokoye",
    "wof:placetype":"locality"
},
  "geometry": {"coordinates":[38.5148,51.0193],"type":"Point"}
}