{
  "type": "Feature",
  "properties": {
    "gn:admin1_code":"90",
    "gn:asciiname":"Suchkovskaya",
    "gn:country_code":"RU",
    "gn:dem":169,
    "gn:feature_class":"P",
    "gn:feature_code":"PPL",
    "gn:name":"Suchkovskaya",
    "gn:population":0,
    "gn:timezone":"Asia/Yekaterinburg",
    "iso:country":"RU",
    "name:rus_x_preferred":[
        "\u0421\u0443\u0447\u043a\u043e\u0432\u0441\u043a\u0430\u044f"
    ],
    "name:und_x_variant":[
        "\u0421\u0443\u0447\u043a\u043e\u0432\u0441\u043a\u0430\u044f"
    ],
    "wof:name":"Suchkovskaya",
    "wof:placetype":"locality"
},
  "geometry": {"coordinates":[53.86666999999999,59.51667],"type":"Point"}
}