{
  "type": "Feature",
  "properties": {
    "gn:admin1_code":"54",
    "gn:asciiname":"Georgiyevka",
    "gn:country_code":"RU",
    "gn:dem":143,
    "gn:feature_class":"P",
    "gn:feature_code":"PPL",
    "gn:name":"Georgiyevka",
    "gn:population":0,
    "gn:timezone":"Asia/Omsk",
    "iso:country":"RU",
    "name:rus_x_preferred":[
        "\u0413\u0435\u043e\u0440\u0433\u0438\u0435\u0432\u043a\u0430"
    ],
    "name:und_x_variant":[
        "\u0413\u0435\u043e\u0440\u0433\u0438\u0435\u0432\u043a\u0430"
    ],
    "wof:name":"Georgiyevka",
    "wof:placetype":"locality"
},
  "geometry": {"coordinates":[75.15000000000001,56.75],"type":"Point"}
}