{
  "type": "Feature",
  "properties": {
    "gn:admin1_code":"57",
    "gn:asciiname":"Yermolayevka",
    "gn:country_code":"RU",
    "gn:dem":232,
    "gn:feature_class":"P",
    "gn:feature_code":"PPL",
    "gn:name":"Yermolayevka",
    "gn:population":0,
    "gn:timezone":"Europe/Moscow",
    "iso:country":"RU",
    "name:aze_x_preferred":[
        "Ermolayevka"
    ],
    "name:bak_x_preferred":[
        "\u0415\u0440\u043c\u043e\u043b\u0430\u0435\u0432\u043a\u0430"
    ],
    "name:che_x_preferred":[
        "\u0415\u0440\u043c\u043e\u043b\u0430\u0435\u0432\u043a\u0430"
    ],
    "name:chv_x_preferred":[
        "\u0415\u0440\u043c\u043e\u043b\u0430\u0435\u0432\u043a\u0430"
    ],
    "name:hye_x_preferred":[
        "\u0535\u0580\u0574\u0578\u056c\u0561\u0587\u056f\u0561"
    ],
    "name:kaz_x_preferred":[
        "\u0415\u0440\u043c\u043e\u043b\u0430\u0435\u0432\u043a\u0430"
    ],
    "name:kir_x_preferred":[
        "\u0415\u0440\u043c\u043e\u043b\u0430\u0435\u0432\u043a\u0430"
    ],
    "name:rus_x_preferred":[
        "\u0415\u0440\u043c\u043e\u043b\u0430\u0435\u0432\u043a\u0430"
    ],
    "name:tat_x_preferred":[
        "\u0415\u0440\u043c\u043e\u043b\u0430\u0435\u0432\u043a\u0430"
    ],
    "name:ukr_x_preferred":[
        "\u0404\u0440\u043c\u043e\u043b\u0430\u0454\u0432\u043a\u0430"
    ],
    "name:und_x_variant":[
        "Pervaya Yermolayevka",
        "Yermolayevka"
    ],
    "wof:name":"Yermolayevka",
    "wof:placetype":"locality"
},
  "geometry": {"coordinates":[44.8225,52.8106],"type":"Point"}
}