{
  "type": "Feature",
  "properties": {
    "gn:country":"RU",
    "gn:fcode":"ADM3",
    "gn:pop":0,
    "iso:country":"RU",
    "name:rus_x_preferred":[
        "\u041e\u043a\u0442\u044f\u0431\u0440\u044c\u0441\u043a\u0438\u0439 \u0420\u0430\u0439\u043e\u043d"
    ],
    "name:unk_x_variant":[
        "Stalinskiy Rayon"
    ],
    "qs:name":"Oktyabr\u2019skiy Rayon",
    "qs:photos_9r":0,
    "qs:photos_sr":0,
    "qs:pop_sr":"0",
    "wof:name":"Oktyabr\u2019skiy Rayon",
    "wof:placetype":"localadmin",
    "wof:population":0
},
  "geometry": {"coordinates":[104.33333,52.26667],"type":"Point"}
}