{
  "type": "Feature",
  "properties": {
    "gn:admin1_code":"37",
    "gn:asciiname":"Ramennaya",
    "gn:country_code":"RU",
    "gn:dem":174,
    "gn:feature_class":"P",
    "gn:feature_code":"PPL",
    "gn:name":"Ramennaya",
    "gn:population":0,
    "gn:timezone":"Europe/Moscow",
    "iso:country":"RU",
    "name:rus_x_preferred":[
        "\u0420\u0430\u043c\u0435\u043d\u043d\u0430\u044f"
    ],
    "name:und_x_variant":[
        "\u0420\u0430\u043c\u0435\u043d\u043d\u0430\u044f"
    ],
    "wof:name":"Ramennaya",
    "wof:placetype":"locality"
},
  "geometry": {"coordinates":[44.81667,58.61666999999999],"type":"Point"}
}