{
  "type": "Feature",
  "properties": {
    "gn:admin1_code":"31",
    "gn:asciiname":"Verkhniy Askiz",
    "gn:country_code":"RU",
    "gn:dem":435,
    "gn:feature_class":"P",
    "gn:feature_code":"PPL",
    "gn:name":"Verkhniy Askiz",
    "gn:population":0,
    "gn:timezone":"Asia/Krasnoyarsk",
    "iso:country":"RU",
    "name:eng_x_preferred":[
        "Verkhniy Askiz"
    ],
    "name:nor_x_preferred":[
        "Verkh.Askiz"
    ],
    "name:rus_x_preferred":[
        "\u0412\u0435\u0440\u0445.\u0410\u0441\u043a\u0438\u0437"
    ],
    "wof:name":"Verkhniy Askiz",
    "wof:placetype":"locality"
},
  "geometry": {"coordinates":[90.18312,53.1609],"type":"Point"}
}