{
  "type": "Feature",
  "properties": {
    "gn:admin1_code":"47.0",
    "gn:asciiname":"Fominskoye",
    "gn:country_code":"RU",
    "gn:dem":223,
    "gn:feature_class":"P",
    "gn:feature_code":"PPL",
    "gn:name":"Fominskoye",
    "gn:population":0,
    "gn:timezone":"Europe/Moscow",
    "iso:country":"RU",
    "name:rus_x_preferred":[
        "\u0424\u043e\u043c\u0438\u043d\u0441\u043a\u043e\u0435"
    ],
    "name:und_x_variant":[
        "\u0424\u043e\u043c\u0438\u043d\u0441\u043a\u043e\u0435"
    ],
    "wof:name":"Fominskoye",
    "wof:placetype":"locality"
},
  "geometry": {"coordinates":[37.01667,56.33333],"type":"Point"}
}