{
  "type": "Feature",
  "properties": {
    "gn:admin1_code":"69",
    "gn:asciiname":"Lapino",
    "gn:country_code":"RU",
    "gn:dem":212,
    "gn:feature_class":"P",
    "gn:feature_code":"PPL",
    "gn:name":"Lapino",
    "gn:population":0,
    "gn:timezone":"Europe/Moscow",
    "iso:country":"RU",
    "name:rus_x_preferred":[
        "\u041b\u0430\u043f\u0438\u043d\u043e"
    ],
    "name:und_x_variant":[
        "Lapinskiye",
        "Lapino"
    ],
    "wof:name":"Lapino",
    "wof:placetype":"locality"
},
  "geometry": {"coordinates":[33.14001,54.41771],"type":"Point"}
}