{
  "type": "Feature",
  "properties": {
    "gn:admin1_code":"77",
    "gn:asciiname":"Zhalybnya",
    "gn:country_code":"RU",
    "gn:dem":213,
    "gn:feature_class":"P",
    "gn:feature_code":"PPL",
    "gn:name":"Zhalybnya",
    "gn:population":0,
    "gn:timezone":"Europe/Moscow",
    "iso:country":"RU",
    "name:rus_x_preferred":[
        "\u0416\u0430\u043b\u044b\u0431\u043d\u044f"
    ],
    "wof:name":"Zhalybnya",
    "wof:placetype":"locality"
},
  "geometry": {"coordinates":[32.77079000000001,57.29469],"type":"Point"}
}