{
  "type": "Feature",
  "properties": {
    "gn:admin1_code":"49",
    "gn:asciiname":"Songel'skiy",
    "gn:country_code":"RU",
    "gn:dem":104,
    "gn:feature_class":"P",
    "gn:feature_code":"PPL",
    "gn:name":"Songel\u2019skiy",
    "gn:population":0,
    "gn:timezone":"Europe/Moscow",
    "iso:country":"RU",
    "name:fin_x_preferred":[
        "Songelski"
    ],
    "name:und_x_variant":[
        "Sangel\u2019skiy",
        "Pogost Sangel\u2019skiy",
        "Songel\u2019skiy",
        "\u0421\u043e\u043d\u0433\u0435\u043b\u044c\u0441\u043a\u0438\u0439"
    ],
    "wof:name":"Songel'skiy",
    "wof:placetype":"locality"
},
  "geometry": {"coordinates":[30.4826,68.74273000000001],"type":"Point"}
}