{
  "type": "Feature",
  "properties": {
    "gn:admin1_code":"10",
    "gn:asciiname":"Profintern",
    "gn:country_code":"RU",
    "gn:dem":152,
    "gn:feature_class":"P",
    "gn:feature_code":"PPL",
    "gn:name":"Profintern",
    "gn:population":0,
    "gn:timezone":"Europe/Moscow",
    "iso:country":"RU",
    "name:rus_x_preferred":[
        "\u041f\u0440\u043e\u0444\u0438\u043d\u0442\u0435\u0440\u043d"
    ],
    "name:und_x_variant":[
        "\u041f\u0440\u043e\u0444\u0438\u043d\u0442\u0435\u0440\u043d"
    ],
    "wof:name":"Profintern",
    "wof:placetype":"locality"
},
  "geometry": {"coordinates":[33.57465999999999,52.54309],"type":"Point"}
}