{
  "type": "Feature",
  "properties": {
    "gn:admin1_code":"10",
    "gn:asciiname":"Profintern",
    "gn:country_code":"RU",
    "gn:dem":152,
    "gn:feature_class":"P",
    "gn:feature_code":"PPL",
    "gn:name":"Profintern",
    "gn:population":0,
    "gn:timezone":"Europe/Moscow",
    "iso:country":"RU",
    "name:bul_x_preferred":[
        "\u041f\u0440\u043e\u0444\u0441\u044a\u044e\u0437\u0435\u043d \u0438\u043d\u0442\u0435\u0440\u043d\u0430\u0446\u0438\u043e\u043d\u0430\u043b"
    ],
    "name:fas_x_preferred":[
        "\u067e\u0631\u0648\u0641\u06cc\u0646\u062a\u0631\u0646"
    ],
    "name:jpn_x_preferred":[
        "\u8d64\u8272\u52b4\u50cd\u7d44\u5408\u30a4\u30f3\u30bf\u30fc\u30ca\u30b7\u30e7\u30ca\u30eb"
    ],
    "name:nld_x_preferred":[
        "Profintern"
    ],
    "name:pol_x_preferred":[
        "Profintern"
    ],
    "name:rus_x_preferred":[
        "\u041f\u0440\u043e\u0444\u0438\u043d\u0442\u0435\u0440\u043d"
    ],
    "name:zho_x_preferred":[
        "\u8d64\u8272\u804c\u5de5\u56fd\u9645"
    ],
    "wof:name":"Profintern",
    "wof:placetype":"locality"
},
  "geometry": {"coordinates":[33.57465999999999,52.54309],"type":"Point"}
}