{
  "type": "Feature",
  "properties": {
    "gn:admin1_code":"63",
    "gn:asciiname":"Ostenga",
    "gn:country_code":"RU",
    "gn:dem":7,
    "gn:feature_class":"P",
    "gn:feature_code":"PPL",
    "gn:name":"Ostenga",
    "gn:population":0,
    "gn:timezone":"Asia/Magadan",
    "iso:country":"RU",
    "name:eng_x_preferred":[
        "Ostenga"
    ],
    "name:nor_x_preferred":[
        "Ojotung"
    ],
    "name:rus_x_preferred":[
        "\u041e\u0439\u043e\u0442\u0443\u043d\u0433"
    ],
    "name:rus_x_variant":[
        "\u041e\u0441\u0442\u0435\u043d\u0433\u0430"
    ],
    "name:und_x_variant":[
        "Oy\u00ebtuonga",
        "Oyetun",
        "Oyotun",
        "Oyotung",
        "Setun",
        "Ostenga",
        "\u041e\u0441\u0442\u0435\u043d\u0433\u0430"
    ],
    "wof:name":"Ostenga",
    "wof:placetype":"locality"
},
  "geometry": {"coordinates":[148.6833,70.65231],"type":"Point"}
}