{
  "type": "Feature",
  "properties": {
    "gn:admin1_code":"33.0",
    "gn:asciiname":"Rekhino",
    "gn:country_code":"RU",
    "gn:dem":124,
    "gn:feature_class":"P",
    "gn:feature_code":"PPL",
    "gn:name":"Rekhino",
    "gn:population":0,
    "gn:timezone":"Europe/Kirov",
    "iso:country":"RU",
    "name:rus_x_preferred":[
        "\u0420\u0435\u0445\u0438\u043d\u043e"
    ],
    "wof:name":"Rekhino",
    "wof:placetype":"locality"
},
  "geometry": {"coordinates":[50.8304,58.4582],"type":"Point"}
}