{
  "type": "Feature",
  "properties": {
    "gn:admin1_code":"25",
    "gn:asciiname":"Sigovo",
    "gn:country_code":"RU",
    "gn:dem":206,
    "gn:feature_class":"P",
    "gn:feature_code":"PPL",
    "gn:name":"Sigovo",
    "gn:population":0,
    "gn:timezone":"Europe/Moscow",
    "iso:country":"RU",
    "name:rus_x_preferred":[
        "\u0421\u0438\u0433\u043e\u0432\u043e"
    ],
    "name:und_x_variant":[
        "\u0421\u0438\u0433\u043e\u0432\u043e"
    ],
    "wof:name":"Sigovo",
    "wof:placetype":"locality"
},
  "geometry": {"coordinates":[35.38389,54.90611],"type":"Point"}
}