{
  "type": "Feature",
  "properties": {
    "gn:admin1_code":"59.0",
    "gn:asciiname":"Sibirtsevo Tret'ye",
    "gn:country_code":"RU",
    "gn:dem":118,
    "gn:feature_class":"P",
    "gn:feature_code":"PPL",
    "gn:name":"Sibirtsevo Tret\u2019ye",
    "gn:population":0,
    "gn:timezone":"Asia/Vladivostok",
    "iso:country":"RU",
    "name:rus_x_preferred":[
        "\u0421\u0438\u0431\u0438\u0440\u0446\u0435\u0432\u043e \u0422\u0440\u0435\u0442\u044c\u0435"
    ],
    "name:und_x_variant":[
        "Sibirtsevo Tret\u2019ye"
    ],
    "wof:name":"Sibirtsevo Tret'ye",
    "wof:placetype":"locality"
},
  "geometry": {"coordinates":[132.43646000000001,44.16797],"type":"Point"}
}