{
  "type": "Feature",
  "properties": {
    "gn:admin1_code":"37",
    "gn:asciiname":"Yeremino",
    "gn:country_code":"RU",
    "gn:dem":166,
    "gn:feature_class":"P",
    "gn:feature_code":"PPL",
    "gn:name":"Yer\u00ebmino",
    "gn:population":0,
    "gn:timezone":"Europe/Moscow",
    "iso:country":"RU",
    "name:rus_x_preferred":[
        "\u0415\u0440\u0451\u043c\u0438\u043d\u043e"
    ],
    "name:und_x_variant":[
        "Yer\u00ebmino"
    ],
    "wof:name":"Yeremino",
    "wof:placetype":"locality"
},
  "geometry": {"coordinates":[46.3166,58.9002],"type":"Point"}
}