{
  "type": "Feature",
  "properties": {
    "gn:admin1_code":"8.0",
    "gn:asciiname":"Asakty",
    "gn:country_code":"RU",
    "gn:dem":157,
    "gn:feature_class":"P",
    "gn:feature_code":"PPL",
    "gn:name":"Asakty",
    "gn:population":0,
    "gn:timezone":"Asia/Yekaterinburg",
    "iso:country":"RU",
    "name:nor_x_preferred":[
        "Asakty"
    ],
    "name:rus_x_preferred":[
        "\u0410\u0441\u0430\u043a\u0442\u044b"
    ],
    "wof:name":"Asakty",
    "wof:placetype":"locality"
},
  "geometry": {"coordinates":[56.75,54.56667],"type":"Point"}
}