{
  "type": "Feature",
  "properties": {
    "gn:admin1_code":"8.0",
    "gn:asciiname":"Abdulmambetovo",
    "gn:country_code":"RU",
    "gn:dem":386,
    "gn:feature_class":"P",
    "gn:feature_code":"PPL",
    "gn:name":"Abdulmambetovo",
    "gn:population":0,
    "gn:timezone":"Asia/Yekaterinburg",
    "iso:country":"RU",
    "name:eng_x_preferred":[
        "Abdulmambetovo"
    ],
    "name:nor_x_preferred":[
        "Abdulmambetovo"
    ],
    "name:rus_x_preferred":[
        "\u0410\u0431\u0434\u0443\u043b\u043c\u0430\u043c\u0431\u0435\u0442\u043e\u0432\u043e"
    ],
    "name:und_x_variant":[
        "Abdulmanbetova",
        "Abdulmambetova",
        "\u0410\u0431\u0434\u0443\u043b\u043c\u0430\u043c\u0431\u0435\u0442\u043e\u0432\u043e",
        "Abdulmambetovo"
    ],
    "wof:name":"Abdulmambetovo",
    "wof:placetype":"locality"
},
  "geometry": {"coordinates":[58.5436,53.1059],"type":"Point"}
}