{
  "type": "Feature",
  "properties": {
    "gn:admin1_code":"9.0",
    "gn:asciiname":"Druzhnyy Pervyy",
    "gn:country_code":"RU",
    "gn:dem":149,
    "gn:feature_class":"P",
    "gn:feature_code":"PPL",
    "gn:name":"Druzhnyy Pervyy",
    "gn:population":0,
    "gn:timezone":"Europe/Moscow",
    "iso:country":"RU",
    "name:rus_x_preferred":[
        "\u0414\u0440\u0443\u0436\u043d\u044b\u0439 \u041f\u0435\u0440\u0432\u044b\u0439"
    ],
    "name:und_x_variant":[
        "Korotkoye"
    ],
    "wof:name":"Druzhnyy Pervyy",
    "wof:placetype":"locality"
},
  "geometry": {"coordinates":[37.26901,50.91779],"type":"Point"}
}