{
  "type": "Feature",
  "properties": {
    "gn:admin1_code":"88",
    "gn:asciiname":"Bakhmatovo",
    "gn:country_code":"RU",
    "gn:dem":129,
    "gn:feature_class":"P",
    "gn:feature_code":"PPL",
    "gn:name":"Bakhmatovo",
    "gn:population":0,
    "gn:timezone":"Europe/Moscow",
    "iso:country":"RU",
    "name:rus_x_preferred":[
        "\u0411\u0430\u0445\u043c\u0430\u0442\u043e\u0432\u043e"
    ],
    "name:und_x_variant":[
        "\u0411\u0430\u0445\u043c\u0430\u0442\u043e\u0432\u043e"
    ],
    "wof:name":"Bakhmatovo",
    "wof:placetype":"locality"
},
  "geometry": {"coordinates":[38.9001,57.6905],"type":"Point"}
}