{
  "type": "Feature",
  "properties": {
    "gn:admin1_code":"42",
    "gn:asciiname":"Tumishche",
    "gn:country_code":"RU",
    "gn:dem":38,
    "gn:feature_class":"P",
    "gn:feature_code":"PPL",
    "gn:name":"Tumishche",
    "gn:population":0,
    "gn:timezone":"Europe/Moscow",
    "iso:country":"RU",
    "wof:name":"Tumishche",
    "wof:placetype":"locality"
},
  "geometry": {"coordinates":[33.27032,59.97681],"type":"Point"}
}