{
  "type": "Feature",
  "properties": {
    "gn:admin1_code":"53",
    "gn:asciiname":"Gorbunovo",
    "gn:country_code":"RU",
    "gn:dem":118,
    "gn:feature_class":"P",
    "gn:feature_code":"PPL",
    "gn:name":"Gorbunovo",
    "gn:population":0,
    "gn:timezone":"Asia/Novosibirsk",
    "iso:country":"RU",
    "name:che_x_preferred":[
        "\u0413\u043e\u0440\u0431\u0443\u043d\u043e\u0432\u043e"
    ],
    "name:eng_x_preferred":[
        "Gorbunovo"
    ],
    "name:nor_x_preferred":[
        "Gorbunovo"
    ],
    "name:rus_x_preferred":[
        "\u0413\u043e\u0440\u0431\u0443\u043d\u043e\u0432\u043e"
    ],
    "name:und_x_variant":[
        "Gorbunova",
        "\u0413\u043e\u0440\u0431\u0443\u043d\u043e\u0432\u043e",
        "Gorbunovo"
    ],
    "wof:name":"Gorbunovo",
    "wof:placetype":"locality"
},
  "geometry": {"coordinates":[78.71663000000002,55.51051999999999],"type":"Point"}
}