{
  "type": "Feature",
  "properties": {
    "gn:admin1_code":"55",
    "gn:asciiname":"Logachevka",
    "gn:country_code":"RU",
    "gn:dem":115,
    "gn:feature_class":"P",
    "gn:feature_code":"PPL",
    "gn:name":"Logach\u00ebvka",
    "gn:population":0,
    "gn:timezone":"Asia/Yekaterinburg",
    "iso:country":"RU",
    "name:eng_x_preferred":[
        "Logach\u00ebvka"
    ],
    "name:nor_x_preferred":[
        "Logatsjevka"
    ],
    "name:rus_x_preferred":[
        "\u041b\u043e\u0433\u0430\u0447\u0435\u0432\u043a\u0430"
    ],
    "name:rus_x_variant":[
        "\u041b\u043e\u0433\u0430\u0447\u0451\u0432\u043a\u0430"
    ],
    "name:und_x_variant":[
        "Logach\u00ebvka",
        "\u041b\u043e\u0433\u0430\u0447\u0451\u0432\u043a\u0430"
    ],
    "wof:name":"Logachevka",
    "wof:placetype":"locality"
},
  "geometry": {"coordinates":[52.338,52.3734],"type":"Point"}
}