{
  "type": "Feature",
  "properties": {
    "gn:admin1_code":"8",
    "gn:asciiname":"Akhmetka",
    "gn:country_code":"RU",
    "gn:dem":131,
    "gn:feature_class":"P",
    "gn:feature_code":"PPL",
    "gn:name":"Akhmetka",
    "gn:population":0,
    "gn:timezone":"Asia/Yekaterinburg",
    "iso:country":"RU",
    "name:rus_x_preferred":[
        "\u0410\u0445\u043c\u0435\u0442\u043a\u0430"
    ],
    "name:und_x_variant":[
        "\u0410\u0445\u043c\u0435\u0442\u043a\u0430"
    ],
    "wof:name":"Akhmetka",
    "wof:placetype":"locality"
},
  "geometry": {"coordinates":[56.393,54.0504],"type":"Point"}
}