{
  "type": "Feature",
  "properties": {
    "gn:admin1_code":"5.0",
    "gn:asciiname":"Uglegorsk",
    "gn:country_code":"RU",
    "gn:dem":238,
    "gn:feature_class":"P",
    "gn:feature_code":"PPL",
    "gn:name":"Uglegorsk",
    "gn:population":0,
    "gn:timezone":"Asia/Yakutsk",
    "iso:country":"RU",
    "name:ben_x_preferred":[
        "\u0989\u0997\u09cd\u09b2\u09c7\u0997\u09b0\u09cd\u09b8\u09cd\u0995"
    ],
    "name:ell_x_preferred":[
        "\u039f\u03cd\u03b3\u03ba\u03bb\u03b5\u03c1\u03b3\u03ba\u03bf\u03c1\u03c3\u03ba"
    ],
    "name:heb_x_preferred":[
        "\u05d0\u05d5\u05d2\u05dc\u05d2\u05d5\u05e8\u05e1\u05e7"
    ],
    "name:hin_x_preferred":[
        "\u0909\u0917\u094d\u0932\u0947\u0917\u094b\u0930\u094d\u0938\u094d\u0915"
    ],
    "name:hun_x_preferred":[
        "Uglegorsk"
    ],
    "name:ind_x_preferred":[
        "Uglegorsk"
    ],
    "name:spa_x_preferred":[
        "Uglegorsk"
    ],
    "name:vie_x_preferred":[
        "Uglegorsk"
    ],
    "wof:name":"Uglegorsk",
    "wof:placetype":"locality"
},
  "geometry": {"coordinates":[128.11472000000001,51.76694],"type":"Point"}
}