{
  "type": "Feature",
  "properties": {
    "gn:admin1_code":"5.0",
    "gn:asciiname":"Uglegorsk",
    "gn:country_code":"RU",
    "gn:dem":238,
    "gn:feature_class":"P",
    "gn:feature_code":"PPL",
    "gn:name":"Uglegorsk",
    "gn:population":0,
    "gn:timezone":"Asia/Yakutsk",
    "iso:country":"RU",
    "wof:name":"Uglegorsk",
    "wof:placetype":"locality"
},
  "geometry": {"coordinates":[128.11472000000001,51.76694000000001],"type":"Point"}
}