{
  "type": "Feature",
  "properties": {
    "gn:admin1_code":"57",
    "gn:asciiname":"Kochetovka",
    "gn:country_code":"RU",
    "gn:dem":185,
    "gn:feature_class":"P",
    "gn:feature_code":"PPL",
    "gn:name":"Kochetovka",
    "gn:population":0,
    "gn:timezone":"Europe/Moscow",
    "iso:country":"RU",
    "name:eng_x_preferred":[
        "Kochetovka"
    ],
    "name:nor_x_preferred":[
        "Kotsjetovka"
    ],
    "name:rus_x_preferred":[
        "\u041a\u043e\u0447\u0435\u0442\u043e\u0432\u043a\u0430"
    ],
    "name:und_x_variant":[
        "\u041a\u043e\u0447\u0435\u0442\u043e\u0432\u043a\u0430",
        "Kochetovka"
    ],
    "wof:name":"Kochetovka",
    "wof:placetype":"locality"
},
  "geometry": {"coordinates":[43.8838,53.29369000000001],"type":"Point"}
}