{
  "type": "Feature",
  "properties": {
    "gn:admin1_code":"88.0",
    "gn:asciiname":"Shakhanovo",
    "gn:country_code":"RU",
    "gn:dem":169,
    "gn:feature_class":"P",
    "gn:feature_code":"PPL",
    "gn:name":"Shakhanovo",
    "gn:population":0,
    "gn:timezone":"Europe/Moscow",
    "iso:country":"RU",
    "name:rus_x_preferred":[
        "\u0428\u0430\u0445\u0430\u043d\u043e\u0432\u043e"
    ],
    "wof:name":"Shakhanovo",
    "wof:placetype":"locality"
},
  "geometry": {"coordinates":[40.74472,58.51138],"type":"Point"}
}