{
  "type": "Feature",
  "properties": {
    "gn:admin1_code":"6",
    "gn:asciiname":"Osnovskaya",
    "gn:cc2":"RU",
    "gn:country_code":"RU",
    "gn:dem":68,
    "gn:feature_class":"P",
    "gn:feature_code":"PPL",
    "gn:name":"Osnovskaya",
    "gn:population":0,
    "gn:timezone":"Europe/Moscow",
    "iso:country":"RU",
    "name:eng_x_preferred":[
        "Osnovskaya"
    ],
    "name:nor_x_preferred":[
        "Osijevskaja"
    ],
    "name:rus_x_preferred":[
        "\u041e\u0441\u0438\u0435\u0432\u0441\u043a\u0430\u044f"
    ],
    "name:rus_x_variant":[
        "\u041e\u0441\u043d\u043e\u0432\u0441\u043a\u0430\u044f"
    ],
    "name:und_x_variant":[
        "Osnevskaya"
    ],
    "wof:name":"Osnovskaya",
    "wof:placetype":"locality"
},
  "geometry": {"coordinates":[42.23333,62.28333000000001],"type":"Point"}
}