{
  "type": "Feature",
  "properties": {
    "gn:admin1_code":"8",
    "gn:asciiname":"Lopatino",
    "gn:country_code":"RU",
    "gn:dem":108,
    "gn:feature_class":"P",
    "gn:feature_code":"PPL",
    "gn:name":"Lopatino",
    "gn:population":0,
    "gn:timezone":"Asia/Yekaterinburg",
    "iso:country":"RU",
    "name:rus_x_preferred":[
        "\u041b\u043e\u043f\u0430\u0442\u0438\u043d\u043e"
    ],
    "name:und_x_variant":[
        "\u041b\u043e\u043f\u0430\u0442\u0438\u043d\u043e"
    ],
    "wof:name":"Lopatino",
    "wof:placetype":"locality"
},
  "geometry": {"coordinates":[56.13148,54.82742],"type":"Point"}
}