{
  "type": "Feature",
  "properties": {
    "gn:admin1_code":"77",
    "gn:asciiname":"Malaya Perevoloka",
    "gn:country_code":"RU",
    "gn:dem":237,
    "gn:feature_class":"P",
    "gn:feature_code":"PPL",
    "gn:name":"Malaya Perevoloka",
    "gn:population":0,
    "gn:timezone":"Europe/Moscow",
    "iso:country":"RU",
    "name:rus_x_preferred":[
        "\u041c\u0430\u043b\u0430\u044f \u041f\u0435\u0440\u0435\u0432\u043e\u043b\u043e\u043a\u0430"
    ],
    "name:und_x_variant":[
        "Novaya Perevoloka",
        "Malaya Perevoloka"
    ],
    "wof:name":"Malaya Perevoloka",
    "wof:placetype":"locality"
},
  "geometry": {"coordinates":[32.21765,56.9724],"type":"Point"}
}