{
  "type": "Feature",
  "properties": {
    "gn:admin1_code":"47",
    "gn:asciiname":"Pobeda",
    "gn:country_code":"RU",
    "gn:dem":194,
    "gn:feature_class":"P",
    "gn:feature_code":"PPL",
    "gn:name":"Pobeda",
    "gn:population":0,
    "gn:timezone":"Europe/Moscow",
    "iso:country":"RU",
    "name:aze_x_preferred":[
        "Pobeda"
    ],
    "name:bul_x_preferred":[
        "\u041f\u043e\u0431\u0435\u0434\u0430"
    ],
    "name:cat_x_preferred":[
        "Pobeda"
    ],
    "name:ceb_x_preferred":[
        "Pobeda"
    ],
    "name:ces_x_preferred":[
        "Pob\u011bda"
    ],
    "name:deu_x_preferred":[
        "Pobeda"
    ],
    "name:est_x_preferred":[
        "Pobeda"
    ],
    "name:fra_x_preferred":[
        "Pobeda"
    ],
    "name:glg_x_preferred":[
        "Pobeda"
    ],
    "name:hun_x_preferred":[
        "Pobeda"
    ],
    "name:hye_x_preferred":[
        "\u054a\u0578\u0562\u0565\u0564\u0561"
    ],
    "name:ita_x_preferred":[
        "Pobeda"
    ],
    "name:kaz_x_preferred":[
        "\u041f\u043e\u0431\u0435\u0434\u0430"
    ],
    "name:kor_x_preferred":[
        "\ud3ec\ubca0\ub2e4"
    ],
    "name:lav_x_preferred":[
        "Pobeda"
    ],
    "name:mon_x_preferred":[
        "\u042f\u043b\u0430\u043b\u0442"
    ],
    "name:nld_x_preferred":[
        "Pobeda"
    ],
    "name:nor_x_preferred":[
        "Pobeda"
    ],
    "name:pol_x_preferred":[
        "Pobeda"
    ],
    "name:ron_x_preferred":[
        "Pobeda"
    ],
    "name:rus_x_preferred":[
        "\u041f\u043e\u0431\u0435\u0434\u0430"
    ],
    "name:spa_x_preferred":[
        "Pobeda"
    ],
    "name:srp_x_preferred":[
        "\u041f\u043e\u0431\u0435\u0434\u0430"
    ],
    "name:swe_x_preferred":[
        "Pobeda"
    ],
    "name:ukr_x_preferred":[
        "\u041f\u043e\u0431\u0435\u0434\u0430"
    ],
    "wof:name":"Pobeda",
    "wof:placetype":"locality"
},
  "geometry": {"coordinates":[36.51,55.33],"type":"Point"}
}