{
  "type": "Feature",
  "properties": {
    "gn:admin1_code":"83.0",
    "gn:asciiname":"Kotluchino",
    "gn:country_code":"RU",
    "gn:dem":178,
    "gn:feature_class":"P",
    "gn:feature_code":"PPL",
    "gn:name":"Kotluchino",
    "gn:population":0,
    "gn:timezone":"Europe/Moscow",
    "iso:country":"RU",
    "name:rus_x_preferred":[
        "\u041a\u043e\u0442\u043b\u0443\u0447\u0438\u043d\u043e"
    ],
    "wof:name":"Kotluchino",
    "wof:placetype":"locality"
},
  "geometry": {"coordinates":[40.00216,56.30807],"type":"Point"}
}