{
  "type": "Feature",
  "properties": {
    "gn:admin1_code":"47.0",
    "gn:asciiname":"Bespyatovo",
    "gn:country_code":"RU",
    "gn:dem":133,
    "gn:feature_class":"P",
    "gn:feature_code":"PPL",
    "gn:name":"Bespyatovo",
    "gn:population":0,
    "gn:timezone":"Europe/Moscow",
    "iso:country":"RU",
    "name:nor_x_preferred":[
        "Bespjatovo"
    ],
    "name:rus_x_preferred":[
        "\u0411\u0435\u0441\u043f\u044f\u0442\u043e\u0432\u043e"
    ],
    "wof:name":"Bespyatovo",
    "wof:placetype":"locality"
},
  "geometry": {"coordinates":[38.36696,55.23089],"type":"Point"}
}