{
  "type": "Feature",
  "properties": {
    "gn:admin1_code":"4.0",
    "gn:asciiname":"Teplyy Khutor",
    "gn:country_code":"RU",
    "gn:dem":320,
    "gn:feature_class":"P",
    "gn:feature_code":"PPL",
    "gn:name":"T\u00ebplyy Khutor",
    "gn:population":0,
    "gn:timezone":"Asia/Barnaul",
    "iso:country":"RU",
    "name:rus_x_preferred":[
        "\u0422\u00eb\u043f\u043b\u044b\u0439 \u0425\u0443\u0442\u043e\u0440"
    ],
    "name:und_x_variant":[
        "T\u00ebplyy Khutor"
    ],
    "wof:name":"Teplyy Khutor",
    "wof:placetype":"locality"
},
  "geometry": {"coordinates":[86.2409,53.5738],"type":"Point"}
}