{
  "type": "Feature",
  "properties": {
    "gn:admin1_code":"29.0",
    "gn:asciiname":"Zinchikha",
    "gn:country_code":"RU",
    "gn:dem":481,
    "gn:feature_class":"P",
    "gn:feature_code":"PPL",
    "gn:name":"Zinchikha",
    "gn:population":0,
    "gn:timezone":"Asia/Novokuznetsk",
    "iso:country":"RU",
    "name:rus_x_preferred":[
        "\u0417\u0438\u043d\u0447\u0438\u0445\u0430"
    ],
    "wof:name":"Zinchikha",
    "wof:placetype":"locality"
},
  "geometry": {"coordinates":[86.18640000000001,53.9798],"type":"Point"}
}