{
  "type": "Feature",
  "properties": {
    "gn:admin1_code":"37",
    "gn:asciiname":"Podel'",
    "gn:country_code":"RU",
    "gn:dem":187,
    "gn:feature_class":"P",
    "gn:feature_code":"PPL",
    "gn:name":"Podel\u2019",
    "gn:population":0,
    "gn:timezone":"Europe/Moscow",
    "iso:country":"RU",
    "name:rus_x_preferred":[
        "\u041f\u043e\u0434\u0435\u043b\u044c"
    ],
    "name:und_x_variant":[
        "Podel\u2019",
        "Poddel\u2019"
    ],
    "wof:name":"Podel'",
    "wof:placetype":"locality"
},
  "geometry": {"coordinates":[42.97942000000001,58.3875],"type":"Point"}
}