{
  "type": "Feature",
  "properties": {
    "gn:admin1_code":"51",
    "gn:asciiname":"Karandashi",
    "gn:country_code":"RU",
    "gn:dem":106,
    "gn:feature_class":"P",
    "gn:feature_code":"PPL",
    "gn:name":"Karandashi",
    "gn:population":0,
    "gn:timezone":"Europe/Moscow",
    "iso:country":"RU",
    "name:rus_x_preferred":[
        "\u041a\u0430\u0440\u0430\u043d\u0434\u0430\u0448\u0438"
    ],
    "wof:name":"Karandashi",
    "wof:placetype":"locality"
},
  "geometry": {"coordinates":[45.0289,57.3294],"type":"Point"}
}