{
  "type": "Feature",
  "properties": {
    "gn:admin1_code":"33",
    "gn:asciiname":"Ikhta",
    "gn:country_code":"RU",
    "gn:dem":103,
    "gn:feature_class":"P",
    "gn:feature_code":"PPL",
    "gn:name":"Ikhta",
    "gn:population":0,
    "gn:timezone":"Europe/Kirov",
    "iso:country":"RU",
    "name:eng_x_preferred":[
        "Ikhta"
    ],
    "name:nor_x_preferred":[
        "Ikhta"
    ],
    "name:rus_x_preferred":[
        "\u0418\u0445\u0442\u0430"
    ],
    "name:und_x_variant":[
        "Ikhtiol"
    ],
    "wof:name":"Ikhta",
    "wof:placetype":"locality"
},
  "geometry": {"coordinates":[47.36694,56.97861999999999],"type":"Point"}
}