{
  "type": "Feature",
  "properties": {
    "gn:admin1_code":"65.0",
    "gn:asciiname":"Trostyanka",
    "gn:country_code":"RU",
    "gn:dem":93,
    "gn:feature_class":"P",
    "gn:feature_code":"PPL",
    "gn:name":"Trostyanka",
    "gn:population":0,
    "gn:timezone":"Europe/Samara",
    "iso:country":"RU",
    "name:rus_x_preferred":[
        "\u0422\u0440\u043e\u0441\u0442\u044f\u043d\u043a\u0430"
    ],
    "wof:name":"Trostyanka",
    "wof:placetype":"locality"
},
  "geometry": {"coordinates":[50.89668,53.16085],"type":"Point"}
}