{
  "type": "Feature",
  "properties": {
    "gn:admin1_code":"47",
    "gn:asciiname":"Shelgunovo",
    "gn:country_code":"RU",
    "gn:dem":151,
    "gn:feature_class":"P",
    "gn:feature_code":"PPL",
    "gn:name":"Shelgunovo",
    "gn:population":0,
    "gn:timezone":"Europe/Moscow",
    "iso:country":"RU",
    "name:nor_x_preferred":[
        "Sjelgunovo"
    ],
    "name:rus_x_preferred":[
        "\u0428\u0435\u043b\u0433\u0443\u043d\u043e\u0432\u043e"
    ],
    "wof:name":"Shelgunovo",
    "wof:placetype":"locality"
},
  "geometry": {"coordinates":[35.60816,56.37178],"type":"Point"}
}