{
  "type": "Feature",
  "properties": {
    "gn:admin1_code":"29",
    "gn:asciiname":"Zhuravleva",
    "gn:country_code":"RU",
    "gn:dem":185,
    "gn:feature_class":"P",
    "gn:feature_code":"PPL",
    "gn:name":"Zhuravl\u00ebva",
    "gn:population":0,
    "gn:timezone":"Asia/Novokuznetsk",
    "iso:country":"RU",
    "wof:name":"Zhuravleva",
    "wof:placetype":"locality"
},
  "geometry": {"coordinates":[86.23496999999998,55.36742],"type":"Point"}
}