{
  "type": "Feature",
  "properties": {
    "gn:admin1_code":"52",
    "gn:asciiname":"Storonino",
    "gn:country_code":"RU",
    "gn:dem":85,
    "gn:feature_class":"P",
    "gn:feature_code":"PPL",
    "gn:name":"Storonino",
    "gn:population":0,
    "gn:timezone":"Europe/Moscow",
    "iso:country":"RU",
    "name:rus_x_preferred":[
        "\u0421\u0442\u043e\u0440\u043e\u043d\u0438\u043d\u043e"
    ],
    "wof:name":"Storonino",
    "wof:placetype":"locality"
},
  "geometry": {"coordinates":[33.31667,58.71666999999999],"type":"Point"}
}