{
  "type": "Feature",
  "properties": {
    "gn:admin1_code":"52.0",
    "gn:asciiname":"Avdeykovo",
    "gn:country_code":"RU",
    "gn:dem":188,
    "gn:feature_class":"P",
    "gn:feature_code":"PPL",
    "gn:name":"Avdeykovo",
    "gn:population":0,
    "gn:timezone":"Europe/Moscow",
    "iso:country":"RU",
    "name:nor_x_preferred":[
        "Avdejkovo"
    ],
    "name:rus_x_preferred":[
        "\u0410\u0432\u0434\u0435\u0439\u043a\u043e\u0432\u043e"
    ],
    "wof:name":"Avdeykovo",
    "wof:placetype":"locality"
},
  "geometry": {"coordinates":[35.41667,58.53333000000001],"type":"Point"}
}