{
  "type": "Feature",
  "properties": {
    "gn:admin1_code":"59",
    "gn:asciiname":"Beregovaya",
    "gn:country_code":"RU",
    "gn:dem":20,
    "gn:feature_class":"P",
    "gn:feature_code":"PPL",
    "gn:name":"Beregovaya",
    "gn:population":0,
    "gn:timezone":"Asia/Vladivostok",
    "iso:country":"RU",
    "name:eng_x_preferred":[
        "Beregovoy"
    ],
    "name:rus_x_preferred":[
        "\u0411\u0435\u0440\u0435\u0433\u043e\u0432\u0430\u044f"
    ],
    "name:rus_x_variant":[
        "\u0411\u0435\u0440\u0435\u0433\u043e\u0432\u043e\u0439"
    ],
    "name:und_x_variant":[
        "Beregovoy",
        "Beregovaya"
    ],
    "wof:name":"Beregovaya",
    "wof:placetype":"locality"
},
  "geometry": {"coordinates":[133.05826000000002,42.77344],"type":"Point"}
}