{
  "type": "Feature",
  "properties": {
    "gn:admin1_code":"77",
    "gn:asciiname":"Vyazovets",
    "gn:country_code":"RU",
    "gn:dem":134,
    "gn:feature_class":"P",
    "gn:feature_code":"PPL",
    "gn:name":"Vyazovets",
    "gn:population":0,
    "gn:timezone":"Europe/Moscow",
    "iso:country":"RU",
    "name:rus_x_preferred":[
        "\u0412\u044f\u0437\u043e\u0432\u0435\u0446"
    ],
    "name:und_x_variant":[
        "\u0412\u044f\u0437\u043e\u0432\u0435\u0446"
    ],
    "wof:name":"Vyazovets",
    "wof:placetype":"locality"
},
  "geometry": {"coordinates":[37.7676,57.4562],"type":"Point"}
}