{
  "type": "Feature",
  "properties": {
    "gn:admin1_code":"47",
    "gn:asciiname":"Gorshkovo",
    "gn:country_code":"RU",
    "gn:dem":187,
    "gn:feature_class":"P",
    "gn:feature_code":"PPL",
    "gn:name":"Gorshkovo",
    "gn:population":0,
    "gn:timezone":"Europe/Moscow",
    "iso:country":"RU",
    "name:rus_x_preferred":[
        "\u0413\u043e\u0440\u0448\u043a\u043e\u0432\u043e"
    ],
    "name:und_x_variant":[
        "\u0413\u043e\u0440\u0448\u043a\u043e\u0432\u043e"
    ],
    "wof:name":"Gorshkovo",
    "wof:placetype":"locality"
},
  "geometry": {"coordinates":[36.75154000000001,55.86565],"type":"Point"}
}