{
  "type": "Feature",
  "properties": {
    "gn:admin1_code":"21",
    "gn:asciiname":"Yergunitsy",
    "gn:country_code":"RU",
    "gn:dem":134,
    "gn:feature_class":"P",
    "gn:feature_code":"PPL",
    "gn:name":"Yergunitsy",
    "gn:population":0,
    "gn:timezone":"Europe/Moscow",
    "iso:country":"RU",
    "name:rus_x_preferred":[
        "\u0415\u0440\u0433\u0443\u043d\u0438\u0446\u044b"
    ],
    "wof:name":"Yergunitsy",
    "wof:placetype":"locality"
},
  "geometry": {"coordinates":[40.45817,56.72833000000001],"type":"Point"}
}