{
  "type": "Feature",
  "properties": {
    "gn:admin1_code":"21",
    "gn:asciiname":"Malaya Potykina",
    "gn:country_code":"RU",
    "gn:dem":124,
    "gn:feature_class":"P",
    "gn:feature_code":"PPL",
    "gn:name":"Malaya Potykina",
    "gn:population":0,
    "gn:timezone":"Europe/Moscow",
    "iso:country":"RU",
    "name:rus_x_preferred":[
        "\u041c\u0430\u043b\u0430\u044f \u041f\u043e\u0442\u044b\u043a\u0438\u043d\u0430"
    ],
    "name:und_x_variant":[
        "\u041c\u0430\u043b\u0430\u044f \u041f\u043e\u0442\u044b\u043a\u0438\u043d\u0430"
    ],
    "wof:name":"Malaya Potykina",
    "wof:placetype":"locality"
},
  "geometry": {"coordinates":[41.98333,57.31667],"type":"Point"}
}