{
  "type": "Feature",
  "properties": {
    "gn:admin1_code":"42",
    "gn:asciiname":"Shaglino",
    "gn:country_code":"RU",
    "gn:dem":77,
    "gn:feature_class":"P",
    "gn:feature_code":"PPL",
    "gn:name":"Shaglino",
    "gn:population":0,
    "gn:timezone":"Europe/Moscow",
    "iso:country":"RU",
    "name:fin_x_preferred":[
        "Saklina"
    ],
    "name:rus_x_preferred":[
        "\u0428\u0430\u0433\u043b\u0438\u043d\u043e"
    ],
    "wof:name":"Shaglino",
    "wof:placetype":"locality"
},
  "geometry": {"coordinates":[30.24833,59.59556],"type":"Point"}
}