{
  "type": "Feature",
  "properties": {
    "gn:admin1_code":"60.0",
    "gn:asciiname":"Koshnevo Aydarovskoye",
    "gn:country_code":"RU",
    "gn:dem":155,
    "gn:feature_class":"P",
    "gn:feature_code":"PPL",
    "gn:name":"Koshnevo Aydarovskoye",
    "gn:population":0,
    "gn:timezone":"Europe/Moscow",
    "iso:country":"RU",
    "name:rus_x_preferred":[
        "\u041a\u043e\u0448\u043d\u0435\u0432\u043e \u0410\u0439\u0434\u0430\u0440\u043e\u0432\u0441\u043a\u043e\u0435"
    ],
    "wof:name":"Koshnevo Aydarovskoye",
    "wof:placetype":"locality"
},
  "geometry": {"coordinates":[30.0497,56.589],"type":"Point"}
}