{
  "type": "Feature",
  "properties": {
    "gn:admin1_code":"17.0",
    "gn:admin2_code":"Buynakskiy Rayon",
    "gn:asciiname":"Akhsu",
    "gn:country_code":"RU",
    "gn:dem":1478,
    "gn:feature_class":"P",
    "gn:feature_code":"PPL",
    "gn:name":"Akhsu",
    "gn:population":0,
    "gn:timezone":"Europe/Moscow",
    "iso:country":"RU",
    "name:nor_x_preferred":[
        "Akhsu"
    ],
    "name:rus_x_preferred":[
        "\u0410\u0445\u0441\u0443"
    ],
    "name:und_x_variant":[
        "Agchu"
    ],
    "wof:name":"Akhsu",
    "wof:placetype":"locality"
},
  "geometry": {"coordinates":[46.69948,42.92126],"type":"Point"}
}