{
  "type": "Feature",
  "properties": {
    "gn:admin1_code":"79",
    "gn:asciiname":"Chirgaky-Aksy",
    "gn:cc2":"RU",
    "gn:country_code":"RU",
    "gn:dem":755,
    "gn:feature_class":"P",
    "gn:feature_code":"PPL",
    "gn:name":"Chirgaky-Aksy",
    "gn:population":0,
    "gn:timezone":"Asia/Krasnoyarsk",
    "iso:country":"RU",
    "name:rus_x_preferred":[
        "\u0427\u0438\u0440\u0433\u0430\u043a\u044b-\u0410\u043a\u0441\u044b"
    ],
    "name:und_x_variant":[
        "Chyrgaky",
        "Chirgaky-Aksy",
        "\u0427\u0438\u0440\u0433\u0430\u043a\u044b-\u0410\u043a\u0441\u044b"
    ],
    "wof:name":"Chirgaky-Aksy",
    "wof:placetype":"locality"
},
  "geometry": {"coordinates":[91.05,51.28333],"type":"Point"}
}