{
  "type": "Feature",
  "properties": {
    "gn:admin1_code":"60",
    "gn:asciiname":"Danilovo",
    "gn:country_code":"RU",
    "gn:dem":75,
    "gn:feature_class":"P",
    "gn:feature_code":"PPL",
    "gn:name":"Danilovo",
    "gn:population":0,
    "gn:timezone":"Europe/Moscow",
    "iso:country":"RU",
    "name:rus_x_preferred":[
        "\u0414\u0430\u043d\u0438\u043b\u043e\u0432\u043e"
    ],
    "wof:name":"Danilovo",
    "wof:placetype":"locality"
},
  "geometry": {"coordinates":[28.0411,57.11848000000001],"type":"Point"}
}