{
  "type": "Feature",
  "properties": {
    "gn:admin1_code":"21",
    "gn:asciiname":"Martynikha",
    "gn:country_code":"RU",
    "gn:dem":139,
    "gn:feature_class":"P",
    "gn:feature_code":"PPL",
    "gn:name":"Martynikha",
    "gn:population":0,
    "gn:timezone":"Europe/Moscow",
    "iso:country":"RU",
    "name:rus_x_preferred":[
        "\u041c\u0430\u0440\u0442\u044b\u043d\u0438\u0445\u0430"
    ],
    "name:und_x_variant":[
        "\u041c\u0430\u0440\u0442\u044b\u043d\u0438\u0445\u0430"
    ],
    "wof:name":"Martynikha",
    "wof:placetype":"locality"
},
  "geometry": {"coordinates":[41.68025,57.29253000000001],"type":"Point"}
}