{
  "type": "Feature",
  "properties": {
    "gn:admin1_code":"38",
    "gn:asciiname":"Protichka",
    "gn:country_code":"RU",
    "gn:dem":5,
    "gn:feature_class":"P",
    "gn:feature_code":"PPL",
    "gn:name":"Protichka",
    "gn:population":0,
    "gn:timezone":"Europe/Moscow",
    "iso:country":"RU",
    "name:rus_x_preferred":[
        "\u041f\u0440\u043e\u0442\u0438\u0447\u043a\u0430"
    ],
    "name:und_x_variant":[
        "Protoka",
        "Protichka",
        "\u041f\u0440\u043e\u0442\u0438\u0447\u043a\u0430"
    ],
    "wof:name":"Protichka",
    "wof:placetype":"locality"
},
  "geometry": {"coordinates":[38.07369,45.38202],"type":"Point"}
}