{
  "type": "Feature",
  "properties": {
    "gn:admin1_code":"45",
    "gn:asciiname":"Izikino",
    "gn:country_code":"RU",
    "gn:dem":166,
    "gn:feature_class":"P",
    "gn:feature_code":"PPL",
    "gn:name":"Izikino",
    "gn:population":0,
    "gn:timezone":"Europe/Moscow",
    "iso:country":"RU",
    "name:rus_x_preferred":[
        "\u0418\u0437\u0438\u043a\u0438\u043d\u043e"
    ],
    "name:und_x_variant":[
        "\u0418\u0437\u0438\u043a\u0438\u043d\u043e",
        "Izikino-Al\u00ebkhino"
    ],
    "wof:name":"Izikino",
    "wof:placetype":"locality"
},
  "geometry": {"coordinates":[46.3668,56.1471],"type":"Point"}
}