{
  "type": "Feature",
  "properties": {
    "gn:admin1_code":"8",
    "gn:asciiname":"Utarbayeva",
    "gn:cc2":"RU",
    "gn:country_code":"RU",
    "gn:dem":489,
    "gn:feature_class":"P",
    "gn:feature_code":"PPL",
    "gn:name":"Utarbayeva",
    "gn:population":0,
    "gn:timezone":"Asia/Yekaterinburg",
    "iso:country":"RU",
    "name:und_x_variant":[
        "Utarbayevo",
        "Utarbayeva"
    ],
    "wof:name":"Utarbayeva",
    "wof:placetype":"locality"
},
  "geometry": {"coordinates":[57.75,51.96667],"type":"Point"}
}