{
  "type": "Feature",
  "properties": {
    "gn:admin1_code":"41",
    "gn:asciiname":"Rubezhov",
    "gn:country_code":"RU",
    "gn:dem":142,
    "gn:feature_class":"P",
    "gn:feature_code":"PPL",
    "gn:name":"Rubezhov",
    "gn:population":0,
    "gn:timezone":"Europe/Moscow",
    "iso:country":"RU",
    "name:rus_x_preferred":[
        "\u0420\u0443\u0431\u0435\u0436\u043e\u0432"
    ],
    "wof:name":"Rubezhov",
    "wof:placetype":"locality"
},
  "geometry": {"coordinates":[34.1986,51.6586],"type":"Point"}
}