{
  "type": "Feature",
  "properties": {
    "gn:country":"RU",
    "gn:fcode":"PPL",
    "gn:pop":2006,
    "iso:country":"RU",
    "name:ceb_x_preferred":[
        "Fakel"
    ],
    "name:eng_x_preferred":[
        "Fakel"
    ],
    "name:nor_x_preferred":[
        "Fakel"
    ],
    "name:rus_x_preferred":[
        "\u0424\u0430\u043a\u0435\u043b"
    ],
    "name:spa_x_preferred":[
        "F\u00e1kel"
    ],
    "name:swe_x_preferred":[
        "Fakel"
    ],
    "name:unk_x_variant":[
        "Sergiyevskiy Zavod"
    ],
    "qs:name":"Fakel",
    "qs:photos_9r":0,
    "qs:photos_sr":0,
    "qs:pop_sr":"4",
    "wd:wordcount":68,
    "wof:name":"Fakel",
    "wof:placetype":"locality",
    "wof:population":2006
},
  "geometry": {"coordinates":[53.0251,57.631],"type":"Point"}
}