{
  "type": "Feature",
  "properties": {
    "gn:admin1_code":"77",
    "gn:asciiname":"Chertezh",
    "gn:country_code":"RU",
    "gn:dem":71,
    "gn:feature_class":"P",
    "gn:feature_code":"PPL",
    "gn:name":"Chert\u00ebzh",
    "gn:population":0,
    "gn:timezone":"Europe/Moscow",
    "iso:country":"RU",
    "name:rus_x_preferred":[
        "\u0427\u0435\u0440\u0442\u0451\u0436"
    ],
    "name:und_x_variant":[
        "Chert\u00ebzh",
        "\u0427\u0435\u0440\u0442\u0451\u0436"
    ],
    "wof:name":"Chertezh",
    "wof:placetype":"locality"
},
  "geometry": {"coordinates":[30.9749,56.9331],"type":"Point"}
}