{
  "type": "Feature",
  "properties": {
    "gn:admin1_code":"55.0",
    "gn:asciiname":"Alekseyevka",
    "gn:country_code":"RU",
    "gn:dem":64,
    "gn:feature_class":"P",
    "gn:feature_code":"PPL",
    "gn:name":"Alekseyevka",
    "gn:population":0,
    "gn:timezone":"Asia/Yekaterinburg",
    "iso:country":"RU",
    "name:eng_x_preferred":[
        "Alekseyevka"
    ],
    "name:nor_x_preferred":[
        "Aleksejevka"
    ],
    "name:rus_x_preferred":[
        "\u0410\u043b\u0435\u043a\u0441\u0435\u0435\u0432\u043a\u0430"
    ],
    "name:und_x_variant":[
        "Alekseyevskiy",
        "\u0410\u043b\u0435\u043a\u0441\u0435\u0435\u0432\u043a\u0430",
        "Alekseyevka"
    ],
    "wof:name":"Alekseyevka",
    "wof:placetype":"locality"
},
  "geometry": {"coordinates":[53.11637,51.70694],"type":"Point"}
}