{
  "type": "Feature",
  "properties": {
    "gn:admin1_code":"69",
    "gn:asciiname":"Novaya Vertka",
    "gn:country_code":"RU",
    "gn:dem":197,
    "gn:feature_class":"P",
    "gn:feature_code":"PPL",
    "gn:name":"Novaya V\u00ebrtka",
    "gn:population":0,
    "gn:timezone":"Europe/Moscow",
    "iso:country":"RU",
    "name:rus_x_preferred":[
        "\u041d\u043e\u0432\u0430\u044f \u0412\u0451\u0440\u0442\u043a\u0430"
    ],
    "name:und_x_variant":[
        "Novaya",
        "Staraya V\u00ebrtka",
        "V\u00ebrtka",
        "V\u00ebrtka-Novaya",
        "Novaya V\u00ebrtka"
    ],
    "wof:name":"Novaya Vertka",
    "wof:placetype":"locality"
},
  "geometry": {"coordinates":[32.33167,55.67227],"type":"Point"}
}