{
  "type": "Feature",
  "properties": {
    "gn:admin1_code":"81",
    "gn:asciiname":"Novyy Atlash",
    "gn:cc2":"RU",
    "gn:country_code":"RU",
    "gn:dem":152,
    "gn:feature_class":"P",
    "gn:feature_code":"PPL",
    "gn:name":"Novyy Atlash",
    "gn:population":0,
    "gn:timezone":"Europe/Ulyanovsk",
    "iso:country":"RU",
    "name:rus_x_preferred":[
        "\u041d\u043e\u0432\u044b\u0439 \u0410\u0442\u043b\u0430\u0448"
    ],
    "name:und_x_variant":[
        "Novaya Pavlovka",
        "Novy Altash",
        "Novyy Atlash",
        "\u041d\u043e\u0432\u044b\u0439 \u0410\u0442\u043b\u0430\u0448"
    ],
    "wof:name":"Novyy Atlash",
    "wof:placetype":"locality"
},
  "geometry": {"coordinates":[47.45,52.75],"type":"Point"}
}