{
  "type": "Feature",
  "properties": {
    "gn:admin1_code":"91",
    "gn:asciiname":"Kurganchiki",
    "gn:country_code":"RU",
    "gn:dem":263,
    "gn:feature_class":"P",
    "gn:feature_code":"PPL",
    "gn:name":"Kurganchiki",
    "gn:population":0,
    "gn:timezone":"Asia/Krasnoyarsk",
    "iso:country":"RU",
    "name:eng_x_preferred":[
        "Kurganchiki"
    ],
    "name:nor_x_preferred":[
        "Kurgantsjiki"
    ],
    "name:rus_x_preferred":[
        "\u041a\u0443\u0440\u0433\u0430\u043d\u0447\u0438\u043a\u0438"
    ],
    "wof:name":"Kurganchiki",
    "wof:placetype":"locality"
},
  "geometry": {"coordinates":[92.31667,53.96666999999999],"type":"Point"}
}