{
  "type": "Feature",
  "properties": {
    "gn:admin1_code":"61",
    "gn:asciiname":"Lagutniki",
    "gn:country_code":"RU",
    "gn:dem":22,
    "gn:feature_class":"P",
    "gn:feature_code":"PPL",
    "gn:name":"Lagutniki",
    "gn:population":0,
    "gn:timezone":"Europe/Moscow",
    "iso:country":"RU",
    "name:rus_x_preferred":[
        "\u041b\u0430\u0433\u0443\u0442\u043d\u0438\u043a\u0438"
    ],
    "wof:name":"Lagutniki",
    "wof:placetype":"locality"
},
  "geometry": {"coordinates":[42.0651,47.5223],"type":"Point"}
}