{
  "type": "Feature",
  "properties": {
    "gn:admin1_code":"62",
    "gn:asciiname":"Spirtzavodskoy",
    "gn:country_code":"RU",
    "gn:dem":97,
    "gn:feature_class":"P",
    "gn:feature_code":"PPL",
    "gn:name":"Spirtzavodskoy",
    "gn:population":0,
    "gn:timezone":"Europe/Moscow",
    "iso:country":"RU",
    "name:rus_x_preferred":[
        "\u0421\u043f\u0438\u0440\u0442\u0437\u0430\u0432\u043e\u0434\u0441\u043a\u043e\u0439"
    ],
    "wof:name":"Spirtzavodskoy",
    "wof:placetype":"locality"
},
  "geometry": {"coordinates":[40.2712,54.303],"type":"Point"}
}