{
  "type": "Feature",
  "properties": {
    "gn:admin1_code":"60",
    "gn:asciiname":"Staraya Mar'ina",
    "gn:country_code":"RU",
    "gn:dem":139,
    "gn:feature_class":"P",
    "gn:feature_code":"PPL",
    "gn:name":"Staraya Mar\u2019ina",
    "gn:population":0,
    "gn:timezone":"Europe/Moscow",
    "iso:country":"RU",
    "name:rus_x_preferred":[
        "\u0421\u0442\u0430\u0440\u0430\u044f \u041c\u0430\u0440\u044c\u0438\u043d\u0430"
    ],
    "name:und_x_variant":[
        "Staraya Mar\u2019ina"
    ],
    "wof:name":"Staraya Mar'ina",
    "wof:placetype":"locality"
},
  "geometry": {"coordinates":[30.11667000000001,56.33333],"type":"Point"}
}