{
  "type": "Feature",
  "properties": {
    "gn:admin1_code":"61",
    "gn:asciiname":"Kalinin",
    "gn:country_code":"RU",
    "gn:dem":41,
    "gn:feature_class":"P",
    "gn:feature_code":"PPL",
    "gn:name":"Kalinin",
    "gn:population":0,
    "gn:timezone":"Europe/Moscow",
    "iso:country":"RU",
    "name:eng_x_preferred":[
        "Kalinin"
    ],
    "name:nor_x_preferred":[
        "Kalinin"
    ],
    "name:rus_x_preferred":[
        "\u041a\u0430\u043b\u0438\u043d\u0438\u043d"
    ],
    "name:und_x_variant":[
        "\u041a\u0430\u043b\u0438\u043d\u0438\u043d",
        "Kalinin"
    ],
    "wof:name":"Kalinin",
    "wof:placetype":"locality"
},
  "geometry": {"coordinates":[42.1492,47.1697],"type":"Point"}
}