{
  "type": "Feature",
  "properties": {
    "gn:admin1_code":"51.0",
    "gn:asciiname":"Pomelikha",
    "gn:country_code":"RU",
    "gn:dem":153,
    "gn:feature_class":"P",
    "gn:feature_code":"PPL",
    "gn:name":"Pomelikha",
    "gn:population":0,
    "gn:timezone":"Europe/Moscow",
    "iso:country":"RU",
    "name:rus_x_preferred":[
        "\u041f\u043e\u043c\u0435\u043b\u0438\u0445\u0430"
    ],
    "name:und_x_variant":[
        "\u041f\u043e\u043c\u0435\u043b\u0438\u0445\u0430"
    ],
    "wof:name":"Pomelikha",
    "wof:placetype":"locality"
},
  "geometry": {"coordinates":[43.2652,55.44706],"type":"Point"}
}