{
  "type": "Feature",
  "properties": {
    "gn:admin1_code":"90",
    "gn:asciiname":"Kokorino",
    "gn:country_code":"RU",
    "gn:dem":143,
    "gn:feature_class":"P",
    "gn:feature_code":"PPL",
    "gn:name":"Kokorino",
    "gn:population":0,
    "gn:timezone":"Asia/Yekaterinburg",
    "iso:country":"RU",
    "name:eng_x_preferred":[
        "Kokorino"
    ],
    "name:nor_x_preferred":[
        "Kokorino"
    ],
    "name:rus_x_preferred":[
        "\u041a\u043e\u043a\u043e\u0440\u0438\u043d\u043e"
    ],
    "name:und_x_variant":[
        "Kosolapova"
    ],
    "wof:name":"Kokorino",
    "wof:placetype":"locality"
},
  "geometry": {"coordinates":[56.7953,59.7981],"type":"Point"}
}