{
  "type": "Feature",
  "properties": {
    "gn:admin1_code":"92",
    "gn:asciiname":"Krutoberegovo",
    "gn:country_code":"RU",
    "gn:dem":9,
    "gn:feature_class":"P",
    "gn:feature_code":"PPL",
    "gn:name":"Krutoberegovo",
    "gn:population":0,
    "gn:timezone":"Asia/Kamchatka",
    "iso:country":"RU",
    "name:eng_x_preferred":[
        "Krutoberegovo"
    ],
    "name:nor_x_preferred":[
        "Krutoberegovo"
    ],
    "name:rus_x_preferred":[
        "\u041a\u0440\u0443\u0442\u043e\u0431\u0435\u0440\u0435\u0433\u043e\u0432\u043e"
    ],
    "name:und_x_variant":[
        "Krutoberegovaya",
        "Krutoberegovo",
        "\u041a\u0440\u0443\u0442\u043e\u0431\u0435\u0440\u0435\u0433\u043e\u0432\u043e"
    ],
    "wof:name":"Krutoberegovo",
    "wof:placetype":"locality"
},
  "geometry": {"coordinates":[162.70246,56.25678000000001],"type":"Point"}
}