{
  "type": "Feature",
  "properties": {
    "gn:admin1_code":"90.0",
    "gn:asciiname":"Tishkino",
    "gn:country_code":"RU",
    "gn:dem":117,
    "gn:feature_class":"P",
    "gn:feature_code":"PPL",
    "gn:name":"Tishkino",
    "gn:population":0,
    "gn:timezone":"Asia/Yekaterinburg",
    "iso:country":"RU",
    "name:che_x_preferred":[
        "\u0422\u0438\u0448\u043a\u0438\u043d\u043e"
    ],
    "name:rus_x_preferred":[
        "\u0422\u0438\u0448\u043a\u0438\u043d\u043e"
    ],
    "wof:name":"Tishkino",
    "wof:placetype":"locality"
},
  "geometry": {"coordinates":[55.756,57.9152],"type":"Point"}
}