{
  "type": "Feature",
  "properties": {
    "gn:admin1_code":"10",
    "gn:asciiname":"Gladskoye",
    "gn:country_code":"RU",
    "gn:dem":185,
    "gn:feature_class":"P",
    "gn:feature_code":"PPL",
    "gn:name":"Gladskoye",
    "gn:population":0,
    "gn:timezone":"Europe/Moscow",
    "iso:country":"RU",
    "name:rus_x_preferred":[
        "\u0413\u043b\u0430\u0434\u0441\u043a\u043e\u0435"
    ],
    "wof:name":"Gladskoye",
    "wof:placetype":"locality"
},
  "geometry": {"coordinates":[34.72115,52.77723],"type":"Point"}
}