{
  "type": "Feature",
  "properties": {
    "gn:admin1_code":"9",
    "gn:asciiname":"Nizhnyaya Serebryanka",
    "gn:country_code":"RU",
    "gn:dem":89,
    "gn:feature_class":"P",
    "gn:feature_code":"PPL",
    "gn:name":"Nizhnyaya Serebryanka",
    "gn:population":0,
    "gn:timezone":"Europe/Moscow",
    "iso:country":"RU",
    "name:rus_x_preferred":[
        "\u041d\u0438\u0436\u043d\u044f\u044f \u0421\u0435\u0440\u0435\u0431\u0440\u044f\u043d\u043a\u0430"
    ],
    "name:und_x_variant":[
        "Nizhnyaya",
        "Novaya Serebryanka",
        "Nizhnyaya Serebryanka",
        "\u041d\u0438\u0436\u043d\u044f\u044f \u0421\u0435\u0440\u0435\u0431\u0440\u044f\u043d\u043a\u0430"
    ],
    "wof:name":"Nizhnyaya Serebryanka",
    "wof:placetype":"locality"
},
  "geometry": {"coordinates":[38.95701,49.82936],"type":"Point"}
}