{
  "type": "Feature",
  "properties": {
    "gn:admin1_code":"20",
    "gn:asciiname":"Pushkinskiy",
    "gn:country_code":"RU",
    "gn:dem":477,
    "gn:feature_class":"P",
    "gn:feature_code":"PPL",
    "gn:name":"Pushkinskiy",
    "gn:population":0,
    "gn:timezone":"Asia/Irkutsk",
    "iso:country":"RU",
    "name:eng_x_preferred":[
        "Pushkinskiy"
    ],
    "name:nor_x_preferred":[
        "Pusjkinskoje"
    ],
    "name:rus_x_preferred":[
        "\u041f\u0443\u0448\u043a\u0438\u043d\u0441\u043a\u043e\u0435"
    ],
    "name:rus_x_variant":[
        "\u041f\u0443\u0448\u043a\u0438\u043d\u0441\u043a\u0438\u0439"
    ],
    "wof:name":"Pushkinskiy",
    "wof:placetype":"locality"
},
  "geometry": {"coordinates":[99.27070000000001,54.5418],"type":"Point"}
}