{
  "type": "Feature",
  "properties": {
    "gn:admin1_code":"76",
    "gn:asciiname":"Poluektovo",
    "gn:country_code":"RU",
    "gn:dem":224,
    "gn:feature_class":"P",
    "gn:feature_code":"PPL",
    "gn:name":"Poluektovo",
    "gn:population":0,
    "gn:timezone":"Europe/Moscow",
    "iso:country":"RU",
    "name:rus_x_preferred":[
        "\u041f\u043e\u043b\u0443\u044d\u043a\u0442\u043e\u0432\u043e"
    ],
    "name:und_x_variant":[
        "\u041f\u043e\u043b\u0443\u044d\u043a\u0442\u043e\u0432\u043e"
    ],
    "wof:name":"Poluektovo",
    "wof:placetype":"locality"
},
  "geometry": {"coordinates":[36.61251,53.7494],"type":"Point"}
}