{
  "type": "Feature",
  "properties": {
    "gn:admin1_code":"77",
    "gn:asciiname":"Moshchanskoye",
    "gn:country_code":"RU",
    "gn:dem":148,
    "gn:feature_class":"P",
    "gn:feature_code":"PPL",
    "gn:name":"Moshchanskoye",
    "gn:population":0,
    "gn:timezone":"Europe/Moscow",
    "iso:country":"RU",
    "name:rus_x_preferred":[
        "\u041c\u043e\u0449\u0430\u043d\u0441\u043a\u043e\u0435"
    ],
    "name:und_x_variant":[
        "\u041c\u043e\u0449\u0430\u043d\u0441\u043a\u043e\u0435"
    ],
    "wof:name":"Moshchanskoye",
    "wof:placetype":"locality"
},
  "geometry": {"coordinates":[35.61595,58.35717],"type":"Point"}
}