{
  "type": "Feature",
  "properties": {
    "gn:admin1_code":"86",
    "gn:asciiname":"Verkhniy Byk",
    "gn:country_code":"RU",
    "gn:dem":134,
    "gn:feature_class":"P",
    "gn:feature_code":"PPL",
    "gn:name":"Verkhniy Byk",
    "gn:population":0,
    "gn:timezone":"Europe/Moscow",
    "iso:country":"RU",
    "name:eng_x_preferred":[
        "Verkhniy Byk"
    ],
    "name:nor_x_preferred":[
        "Verkhnij Byk"
    ],
    "name:rus_x_preferred":[
        "\u0412\u0435\u0440\u0445\u043d\u0438\u0439 \u0411\u044b\u043a"
    ],
    "wof:name":"Verkhniy Byk",
    "wof:placetype":"locality"
},
  "geometry": {"coordinates":[41.2715,50.713],"type":"Point"}
}