{
  "type": "Feature",
  "properties": {
    "gn:admin1_code":"8.0",
    "gn:asciiname":"Chekan-Tamak",
    "gn:country_code":"RU",
    "gn:dem":117,
    "gn:feature_class":"P",
    "gn:feature_code":"PPL",
    "gn:name":"Chekan-Tamak",
    "gn:population":0,
    "gn:timezone":"Asia/Yekaterinburg",
    "iso:country":"RU",
    "name:rus_x_preferred":[
        "\u0427\u0435\u043a\u0430\u043d-\u0422\u0430\u043c\u0430\u043a"
    ],
    "name:und_x_variant":[
        "\u0427\u0435\u043a\u0430\u043d-\u0422\u0430\u043c\u0430\u043a"
    ],
    "wof:name":"Chekan-Tamak",
    "wof:placetype":"locality"
},
  "geometry": {"coordinates":[53.63333000000001,54.85],"type":"Point"}
}