{
  "type": "Feature",
  "properties": {
    "gn:admin1_code":"91",
    "gn:asciiname":"Shigashet",
    "gn:country_code":"RU",
    "gn:dem":242,
    "gn:feature_class":"P",
    "gn:feature_code":"PPL",
    "gn:name":"Shigashet",
    "gn:population":0,
    "gn:timezone":"Asia/Krasnoyarsk",
    "iso:country":"RU",
    "name:eng_x_preferred":[
        "Shigashet"
    ],
    "name:nor_x_preferred":[
        "Tsjigasjet"
    ],
    "name:rus_x_preferred":[
        "\u0427\u0438\u0433\u0430\u0448\u0435\u0442"
    ],
    "name:rus_x_variant":[
        "\u0428\u0438\u0433\u0430\u0448\u0435\u0442"
    ],
    "wof:name":"Shigashet",
    "wof:placetype":"locality"
},
  "geometry": {"coordinates":[96.17545,57.17487],"type":"Point"}
}