{
  "type": "Feature",
  "properties": {
    "gn:admin1_code":"91.0",
    "gn:asciiname":"Vlast' Truda",
    "gn:country_code":"RU",
    "gn:dem":237,
    "gn:feature_class":"P",
    "gn:feature_code":"PPL",
    "gn:name":"Vlast\u2019 Truda",
    "gn:population":0,
    "gn:timezone":"Asia/Krasnoyarsk",
    "iso:country":"RU",
    "name:rus_x_preferred":[
        "\u0412\u043b\u0430\u0441\u0442\u044c \u0422\u0440\u0443\u0434\u0430"
    ],
    "name:und_x_variant":[
        "Vlast\u2019 Truda"
    ],
    "wof:name":"Vlast' Truda",
    "wof:placetype":"locality"
},
  "geometry": {"coordinates":[94.6717,55.8803],"type":"Point"}
}