{
  "type": "Feature",
  "properties": {
    "gn:admin1_code":"51.0",
    "gn:asciiname":"Lachinovo",
    "gn:country_code":"RU",
    "gn:dem":153,
    "gn:feature_class":"P",
    "gn:feature_code":"PPL",
    "gn:name":"Lachinovo",
    "gn:population":0,
    "gn:timezone":"Europe/Moscow",
    "iso:country":"RU",
    "name:rus_x_preferred":[
        "\u041b\u0430\u0447\u0438\u043d\u043e\u0432\u043e"
    ],
    "name:und_x_variant":[
        "\u041b\u0430\u0447\u0438\u043d\u043e\u0432\u043e"
    ],
    "wof:name":"Lachinovo",
    "wof:placetype":"locality"
},
  "geometry": {"coordinates":[43.24031,55.83519],"type":"Point"}
}