{
  "type": "Feature",
  "properties": {
    "gn:admin1_code":"60",
    "gn:asciiname":"Luzhi",
    "gn:country_code":"RU",
    "gn:dem":188,
    "gn:feature_class":"P",
    "gn:feature_code":"PPL",
    "gn:name":"Luzhi",
    "gn:population":0,
    "gn:timezone":"Europe/Moscow",
    "iso:country":"RU",
    "name:fra_x_preferred":[
        "Luzhi"
    ],
    "name:jpn_x_preferred":[
        "\u30ed\u30af\u76f4\u93ae"
    ],
    "name:rus_x_preferred":[
        "\u041b\u0443\u0436\u0438"
    ],
    "name:und_x_variant":[
        "\u041b\u0443\u0436\u0438"
    ],
    "name:wuu_x_preferred":[
        "\u752a\u76f4\u9547"
    ],
    "name:zho_x_preferred":[
        "\u752a\u76f4\u9547"
    ],
    "wof:name":"Luzhi",
    "wof:placetype":"locality"
},
  "geometry": {"coordinates":[29.8036,56.1875],"type":"Point"}
}