{
  "type": "Feature",
  "properties": {
    "gn:admin1_code":"52.0",
    "gn:asciiname":"Beglovo",
    "gn:country_code":"RU",
    "gn:dem":36,
    "gn:feature_class":"P",
    "gn:feature_code":"PPL",
    "gn:name":"Beglovo",
    "gn:population":0,
    "gn:timezone":"Europe/Moscow",
    "iso:country":"RU",
    "name:nor_x_preferred":[
        "Beglovo"
    ],
    "name:rus_x_preferred":[
        "\u0411\u0435\u0433\u043b\u043e\u0432\u043e"
    ],
    "name:und_x_variant":[
        "Beglova"
    ],
    "wof:name":"Beglovo",
    "wof:placetype":"locality"
},
  "geometry": {"coordinates":[32.28378,59.19498000000001],"type":"Point"}
}