{
  "type": "Feature",
  "properties": {
    "gn:admin1_code":"6.0",
    "gn:asciiname":"Toloknovo",
    "gn:country_code":"RU",
    "gn:dem":20,
    "gn:feature_class":"P",
    "gn:feature_code":"PPL",
    "gn:name":"Toloknovo",
    "gn:population":0,
    "gn:timezone":"Europe/Moscow",
    "iso:country":"RU",
    "name:rus_x_preferred":[
        "\u0422\u043e\u043b\u043e\u043a\u043d\u043e\u0432\u043e"
    ],
    "wof:name":"Toloknovo",
    "wof:placetype":"locality"
},
  "geometry": {"coordinates":[41.6198,63.6276],"type":"Point"}
}