{
  "type": "Feature",
  "properties": {
    "gn:admin1_code":"60",
    "gn:asciiname":"Borousy",
    "gn:country_code":"RU",
    "gn:dem":76,
    "gn:feature_class":"P",
    "gn:feature_code":"PPL",
    "gn:name":"Borousy",
    "gn:population":0,
    "gn:timezone":"Europe/Moscow",
    "iso:country":"RU",
    "name:rus_x_preferred":[
        "\u0411\u043e\u0440\u043e\u0443\u0441\u044b"
    ],
    "name:und_x_variant":[
        "Barausy",
        "Borousy"
    ],
    "wof:name":"Borousy",
    "wof:placetype":"locality"
},
  "geometry": {"coordinates":[28.10721,57.00791],"type":"Point"}
}