{
  "type": "Feature",
  "properties": {
    "gn:admin1_code":"88",
    "gn:asciiname":"Ivertsevo",
    "gn:country_code":"RU",
    "gn:dem":205,
    "gn:feature_class":"P",
    "gn:feature_code":"PPL",
    "gn:name":"Ivertsevo",
    "gn:population":0,
    "gn:timezone":"Europe/Moscow",
    "iso:country":"RU",
    "name:rus_x_preferred":[
        "\u0418\u0432\u0435\u0440\u0446\u0435\u0432\u043e"
    ],
    "wof:name":"Ivertsevo",
    "wof:placetype":"locality"
},
  "geometry": {"coordinates":[38.8661,57.0962],"type":"Point"}
}