{
  "type": "Feature",
  "properties": {
    "gn:admin1_code":"28",
    "gn:asciiname":"Kapanen",
    "gn:country_code":"RU",
    "gn:dem":14,
    "gn:feature_class":"P",
    "gn:feature_code":"PPL",
    "gn:name":"Kapanen",
    "gn:population":0,
    "gn:timezone":"Europe/Moscow",
    "iso:country":"RU",
    "name:fin_x_preferred":[
        "Kapanen"
    ],
    "name:lav_x_preferred":[
        "Kapanens"
    ],
    "name:rus_x_preferred":[
        "\u041a\u0430\u043f\u0430\u043d\u0435\u043d"
    ],
    "wof:name":"Kapanen",
    "wof:placetype":"locality"
},
  "geometry": {"coordinates":[31.75907,61.37156],"type":"Point"}
}