{
  "type": "Feature",
  "properties": {
    "gn:admin1_code":"28",
    "gn:asciiname":"Onigma",
    "gn:country_code":"RU",
    "gn:dem":177,
    "gn:feature_class":"P",
    "gn:feature_code":"PPL",
    "gn:name":"Onigma",
    "gn:population":0,
    "gn:timezone":"Europe/Moscow",
    "iso:country":"RU",
    "name:fin_x_preferred":[
        "Onihma"
    ],
    "name:rus_x_preferred":[
        "\u041e\u043d\u0438\u0433\u043c\u0430"
    ],
    "name:und_x_variant":[
        "\u041e\u043d\u0438\u0433\u043c\u0430"
    ],
    "wof:name":"Onigma",
    "wof:placetype":"locality"
},
  "geometry": {"coordinates":[33.4326,64.07025],"type":"Point"}
}