{
  "type": "Feature",
  "properties": {
    "gn:admin1_code":"29.0",
    "gn:asciiname":"Zagrinskoye",
    "gn:country_code":"RU",
    "gn:dem":288,
    "gn:feature_class":"P",
    "gn:feature_code":"PPL",
    "gn:name":"Zagrinskoye",
    "gn:population":0,
    "gn:timezone":"Asia/Novokuznetsk",
    "iso:country":"RU",
    "name:rus_x_preferred":[
        "\u0417\u0430\u0433\u0440\u0438\u043d\u0441\u043a\u043e\u0435"
    ],
    "wof:name":"Zagrinskoye",
    "wof:placetype":"locality"
},
  "geometry": {"coordinates":[86.5044,54.5978],"type":"Point"}
}