{
  "type": "Feature",
  "properties": {
    "gn:country":"RU",
    "gn:fcode":"PPL",
    "gn:population":4903,
    "iso:country":"RU",
    "name:che_x_preferred":[
        "\u0421\u044b\u0441\u043e\u0435\u0432\u043a\u0430"
    ],
    "name:eng_x_preferred":[
        "Novosysoyevka"
    ],
    "name:eng_x_variant":[
        "Sysoyevka"
    ],
    "name:nor_x_preferred":[
        "Novosysojevka"
    ],
    "name:rus_x_preferred":[
        "\u041d\u043e\u0432\u043e\u0441\u044b\u0441\u043e\u0435\u0432\u043a\u0430"
    ],
    "name:rus_x_variant":[
        "\u0421\u044b\u0441\u043e\u0435\u0432\u043a\u0430"
    ],
    "name:tat_x_preferred":[
        "\u0421\u044b\u0441\u043e\u0435\u0432\u043a\u0430"
    ],
    "qs:name":"Novosysoyevka",
    "qs:photos_9r":0,
    "qs:photos_sr":0,
    "qs:pop_sr":"4",
    "wof:name":"Novosysoyevka",
    "wof:placetype":"locality",
    "wof:population":4903
},
  "geometry": {"coordinates":[133.36420000000001,44.2347],"type":"Point"}
}