{
  "type": "Feature",
  "properties": {
    "gn:admin1_code":"67",
    "gn:asciiname":"Krepost' Uzen'",
    "gn:country_code":"RU",
    "gn:dem":30,
    "gn:feature_class":"P",
    "gn:feature_code":"PPL",
    "gn:name":"Krepost\u2019 Uzen\u2019",
    "gn:population":0,
    "gn:timezone":"Europe/Saratov",
    "iso:country":"RU",
    "name:eng_x_preferred":[
        "Krepost' Uzen'"
    ],
    "name:nor_x_preferred":[
        "Krepost Uzen"
    ],
    "name:rus_x_preferred":[
        "Krepost\u2019 Uzen\u2019"
    ],
    "name:rus_x_variant":[
        "\u041a\u0440\u0435\u043f\u043e\u0441\u0442\u044c \u0423\u0437\u0435\u043d\u044c"
    ],
    "name:und_x_variant":[
        "Fort Uzen"
    ],
    "wof:name":"Krepost' Uzen'",
    "wof:placetype":"locality"
},
  "geometry": {"coordinates":[48.0153,50.6983],"type":"Point"}
}