{
  "type": "Feature",
  "properties": {
    "gn:admin1_code":"76",
    "gn:asciiname":"Terebush",
    "gn:country_code":"RU",
    "gn:dem":209,
    "gn:feature_class":"P",
    "gn:feature_code":"PPL",
    "gn:name":"Terebush",
    "gn:population":0,
    "gn:timezone":"Europe/Moscow",
    "iso:country":"RU",
    "name:eng_x_preferred":[
        "Terebush"
    ],
    "name:nor_x_preferred":[
        "Terebusj"
    ],
    "name:rus_x_preferred":[
        "\u0422\u0435\u0440\u0435\u0431\u0443\u0448"
    ],
    "wof:name":"Terebush",
    "wof:placetype":"locality"
},
  "geometry": {"coordinates":[38.14993,54.27341],"type":"Point"}
}