{
  "type": "Feature",
  "properties": {
    "gn:admin1_code":"80",
    "gn:asciiname":"Karkalay",
    "gn:country_code":"RU",
    "gn:dem":226,
    "gn:feature_class":"P",
    "gn:feature_code":"PPL",
    "gn:name":"Karkalay",
    "gn:population":0,
    "gn:timezone":"Europe/Samara",
    "iso:country":"RU",
    "name:eng_x_preferred":[
        "Karkalay"
    ],
    "name:nor_x_preferred":[
        "Karkalaj"
    ],
    "name:rus_x_preferred":[
        "\u041a\u0430\u0440\u043a\u0430\u043b\u0430\u0439"
    ],
    "name:und_x_variant":[
        "\u041a\u0430\u0440\u043a\u0430\u043b\u0430\u0439",
        "Karkalay"
    ],
    "wof:name":"Karkalay",
    "wof:placetype":"locality"
},
  "geometry": {"coordinates":[52.1573,57.6628],"type":"Point"}
}