{
  "type": "Feature",
  "properties": {
    "gn:admin1_code":"20",
    "gn:asciiname":"Birka",
    "gn:cc2":"RU",
    "gn:country_code":"RU",
    "gn:dem":625,
    "gn:feature_class":"P",
    "gn:feature_code":"PPL",
    "gn:name":"Birka",
    "gn:population":0,
    "gn:timezone":"Asia/Irkutsk",
    "iso:country":"RU",
    "name:rus_x_preferred":[
        "\u0411\u0438\u0440\u043a\u0430"
    ],
    "name:und_x_variant":[
        "Birkinskaya",
        "Birka",
        "\u0411\u0438\u0440\u043a\u0430"
    ],
    "wof:name":"Birka",
    "wof:placetype":"locality"
},
  "geometry": {"coordinates":[103.48333,54.08333],"type":"Point"}
}