{
  "type": "Feature",
  "properties": {
    "gn:admin1_code":"20",
    "gn:asciiname":"Birka",
    "gn:cc2":"RU",
    "gn:country_code":"RU",
    "gn:dem":625,
    "gn:feature_class":"P",
    "gn:feature_code":"PPL",
    "gn:name":"Birka",
    "gn:population":0,
    "gn:timezone":"Asia/Irkutsk",
    "iso:country":"RU",
    "name:ara_x_preferred":[
        "\u0628\u064a\u0631\u0643\u0627"
    ],
    "name:bel_x_preferred":[
        "\u0411\u0456\u0440\u043a\u0430"
    ],
    "name:bul_x_preferred":[
        "\u0411\u0438\u0440\u043a\u0430"
    ],
    "name:cat_x_preferred":[
        "Birka"
    ],
    "name:ces_x_preferred":[
        "Birka"
    ],
    "name:cym_x_preferred":[
        "Birka"
    ],
    "name:dan_x_preferred":[
        "Birka"
    ],
    "name:deu_x_preferred":[
        "Birka"
    ],
    "name:epo_x_preferred":[
        "Birka"
    ],
    "name:eus_x_preferred":[
        "Birka"
    ],
    "name:fas_x_preferred":[
        "\u0628\u06cc\u0631\u06a9\u0627"
    ],
    "name:fin_x_preferred":[
        "Birka"
    ],
    "name:fra_x_preferred":[
        "Birka"
    ],
    "name:fry_x_preferred":[
        "Birka"
    ],
    "name:hrv_x_preferred":[
        "Birka"
    ],
    "name:hun_x_preferred":[
        "Birka"
    ],
    "name:ita_x_preferred":[
        "Birka"
    ],
    "name:jpn_x_preferred":[
        "\u30d3\u30eb\u30ab"
    ],
    "name:kat_x_preferred":[
        "\u10d1\u10d8\u10e0\u10d9\u10d0"
    ],
    "name:lat_x_preferred":[
        "Birca"
    ],
    "name:lit_x_preferred":[
        "Birka"
    ],
    "name:mai_x_preferred":[
        "\u092c\u093f\u0930\u094d\u0915\u093e"
    ],
    "name:mal_x_preferred":[
        "\u0d2c\u0d3f\u0d7c\u0d15"
    ],
    "name:nep_x_preferred":[
        "\u092c\u093f\u0930\u094d\u0915\u093e"
    ],
    "name:nno_x_preferred":[
        "Birka"
    ],
    "name:nor_x_preferred":[
        "Birka"
    ],
    "name:pol_x_preferred":[
        "Birka"
    ],
    "name:por_x_preferred":[
        "Birka"
    ],
    "name:ron_x_preferred":[
        "Birka"
    ],
    "name:rus_x_preferred":[
        "\u0411\u0438\u0440\u043a\u0430"
    ],
    "name:sco_x_preferred":[
        "Birka"
    ],
    "name:slk_x_preferred":[
        "Birka"
    ],
    "name:slv_x_preferred":[
        "Birka"
    ],
    "name:sqi_x_preferred":[
        "Birka"
    ],
    "name:swe_x_preferred":[
        "Birka"
    ],
    "name:tur_x_preferred":[
        "Birka"
    ],
    "name:ukr_x_preferred":[
        "\u0411\u0456\u0440\u043a\u0430"
    ],
    "name:und_x_variant":[
        "Birkinskaya",
        "Birka",
        "\u0411\u0438\u0440\u043a\u0430"
    ],
    "name:vie_x_preferred":[
        "Birka"
    ],
    "name:xmf_x_preferred":[
        "\u10d1\u10d8\u10e0\u10d9\u10d0"
    ],
    "name:zho_x_preferred":[
        "\u6bd4\u723e\u5361"
    ],
    "wof:name":"Birka",
    "wof:placetype":"locality"
},
  "geometry": {"coordinates":[103.48333,54.08333],"type":"Point"}
}