{
  "type": "Feature",
  "properties": {
    "gn:admin1_code":"38",
    "gn:asciiname":"Ust'-Dzhigutinka",
    "gn:country_code":"RU",
    "gn:dem":66,
    "gn:feature_class":"P",
    "gn:feature_code":"PPL",
    "gn:name":"Ust\u2019-Dzhigutinka",
    "gn:population":0,
    "gn:timezone":"Europe/Moscow",
    "iso:country":"RU",
    "name:rus_x_preferred":[
        "\u0423\u0441\u0442\u044c-\u0414\u0436\u0438\u0433\u0443\u0442\u0438\u043d\u043a\u0430"
    ],
    "name:und_x_variant":[
        "Ust\u2019-Dzhegutinskiy",
        "Ust\u2019-Dzhigutinskiy",
        "Ust\u2019-Dzhigutinka"
    ],
    "wof:name":"Ust'-Dzhigutinka",
    "wof:placetype":"locality"
},
  "geometry": {"coordinates":[40.21194000000001,45.78944],"type":"Point"}
}