{
  "type": "Feature",
  "properties": {
    "gn:admin1_code":"3",
    "gn:asciiname":"Barancha",
    "gn:country_code":"RU",
    "gn:dem":887,
    "gn:feature_class":"P",
    "gn:feature_code":"PPL",
    "gn:name":"Barancha",
    "gn:population":0,
    "gn:timezone":"Asia/Omsk",
    "iso:country":"RU",
    "name:nor_x_preferred":[
        "Barantsja"
    ],
    "name:rus_x_preferred":[
        "\u0411\u0430\u0440\u0430\u043d\u0447\u0430"
    ],
    "wof:name":"Barancha",
    "wof:placetype":"locality"
},
  "geometry": {"coordinates":[84.98333000000002,51.46667],"type":"Point"}
}