{
  "type": "Feature",
  "properties": {
    "gn:admin1_code":"38",
    "gn:asciiname":"Konovalovskiy",
    "gn:cc2":"RU",
    "gn:country_code":"RU",
    "gn:dem":77,
    "gn:feature_class":"P",
    "gn:feature_code":"PPL",
    "gn:name":"Konovalovskiy",
    "gn:population":0,
    "gn:timezone":"Europe/Moscow",
    "iso:country":"RU",
    "name:rus_x_preferred":[
        "\u041a\u043e\u043d\u043e\u0432\u0430\u043b\u043e\u0432\u0441\u043a\u0438\u0439"
    ],
    "name:und_x_variant":[
        "Konovalovsk",
        "Konovalovskiy",
        "\u041a\u043e\u043d\u043e\u0432\u0430\u043b\u043e\u0432\u0441\u043a\u0438\u0439"
    ],
    "wof:name":"Konovalovskiy",
    "wof:placetype":"locality"
},
  "geometry": {"coordinates":[40.2175,46.01667],"type":"Point"}
}