{
  "type": "Feature",
  "properties": {
    "gn:admin1_code":"8.0",
    "gn:asciiname":"Argamak",
    "gn:country_code":"RU",
    "gn:dem":142,
    "gn:feature_class":"P",
    "gn:feature_code":"PPL",
    "gn:name":"Argamak",
    "gn:population":0,
    "gn:timezone":"Asia/Yekaterinburg",
    "iso:country":"RU",
    "name:bak_x_preferred":[
        "\u0410\u0440\u0493\u044b\u043c\u0430\u04a1"
    ],
    "name:nor_x_preferred":[
        "Argamak"
    ],
    "name:rus_x_preferred":[
        "\u0410\u0440\u0433\u0430\u043c\u0430\u043a"
    ],
    "wof:name":"Argamak",
    "wof:placetype":"locality"
},
  "geometry": {"coordinates":[54.8892,55.46762],"type":"Point"}
}