{
  "type": "Feature",
  "properties": {
    "gn:admin1_code":"90",
    "gn:asciiname":"Yarino",
    "gn:country_code":"RU",
    "gn:dem":136,
    "gn:feature_class":"P",
    "gn:feature_code":"PPL",
    "gn:name":"Yarino",
    "gn:population":0,
    "gn:timezone":"Asia/Yekaterinburg",
    "iso:country":"RU",
    "name:eng_x_preferred":[
        "Yarino"
    ],
    "name:nor_x_preferred":[
        "Jarino"
    ],
    "name:rus_x_preferred":[
        "\u042f\u0440\u0438\u043d\u043e"
    ],
    "name:und_x_variant":[
        "Yarina"
    ],
    "wof:name":"Yarino",
    "wof:placetype":"locality"
},
  "geometry": {"coordinates":[55.0741,58.3312],"type":"Point"}
}