{
  "type": "Feature",
  "properties": {
    "gn:admin1_code":"70",
    "gn:asciiname":"Livenskiy",
    "gn:country_code":"RU",
    "gn:dem":217,
    "gn:feature_class":"P",
    "gn:feature_code":"PPL",
    "gn:name":"Livenskiy",
    "gn:population":0,
    "gn:timezone":"Europe/Moscow",
    "iso:country":"RU",
    "name:rus_x_preferred":[
        "\u041b\u0438\u0432\u0435\u043d\u0441\u043a\u0438\u0439"
    ],
    "wof:name":"Livenskiy",
    "wof:placetype":"locality"
},
  "geometry": {"coordinates":[43.685,44.46417],"type":"Point"}
}