{
  "type": "Feature",
  "properties": {
    "gn:admin1_code":"38.0",
    "gn:asciiname":"Ayluk",
    "gn:country_code":"RU",
    "gn:dem":290,
    "gn:feature_class":"P",
    "gn:feature_code":"PPL",
    "gn:name":"Ayluk",
    "gn:population":0,
    "gn:timezone":"Europe/Moscow",
    "iso:country":"RU",
    "name:rus_x_preferred":[
        "(( \u0410\u0439\u043b\u0443\u043a ))"
    ],
    "wof:name":"Ayluk",
    "wof:placetype":"locality"
},
  "geometry": {"coordinates":[39.23,44.03],"type":"Point"}
}