{
  "type": "Feature",
  "properties": {
    "gn:admin1_code":"77",
    "gn:asciiname":"Ivanovshchina",
    "gn:country_code":"RU",
    "gn:dem":209,
    "gn:feature_class":"P",
    "gn:feature_code":"PPL",
    "gn:name":"Ivanovshchina",
    "gn:population":0,
    "gn:timezone":"Europe/Moscow",
    "iso:country":"RU",
    "name:rus_x_preferred":[
        "\u0418\u0432\u0430\u043d\u043e\u0432\u0449\u0438\u043d\u0430"
    ],
    "wof:name":"Ivanovshchina",
    "wof:placetype":"locality"
},
  "geometry": {"coordinates":[32.77374,57.26534],"type":"Point"}
}