{
  "type": "Feature",
  "properties": {
    "gn:admin1_code":"90.0",
    "gn:asciiname":"Paleva",
    "gn:country_code":"RU",
    "gn:dem":158,
    "gn:feature_class":"P",
    "gn:feature_code":"PPL",
    "gn:name":"Paleva",
    "gn:population":0,
    "gn:timezone":"Asia/Yekaterinburg",
    "iso:country":"RU",
    "name:rus_x_preferred":[
        "\u041f\u0430\u043b\u0435\u0432\u0430"
    ],
    "wof:name":"Paleva",
    "wof:placetype":"locality"
},
  "geometry": {"coordinates":[54.3714,59.1356],"type":"Point"}
}