{
  "type": "Feature",
  "properties": {
    "gn:admin1_code":"85",
    "gn:asciiname":"Pogostishche",
    "gn:country_code":"RU",
    "gn:dem":125,
    "gn:feature_class":"P",
    "gn:feature_code":"PPL",
    "gn:name":"Pogostishche",
    "gn:population":0,
    "gn:timezone":"Europe/Moscow",
    "iso:country":"RU",
    "name:eng_x_preferred":[
        "Pogostishche"
    ],
    "name:nor_x_preferred":[
        "Pogostisjtsje"
    ],
    "name:rus_x_preferred":[
        "\u041f\u043e\u0433\u043e\u0441\u0442\u0438\u0449\u0435"
    ],
    "name:und_x_variant":[
        "\u041f\u043e\u0433\u043e\u0441\u0442\u0438\u0449\u0435",
        "Pogostishche"
    ],
    "wof:name":"Pogostishche",
    "wof:placetype":"locality"
},
  "geometry": {"coordinates":[38.726,60.3497],"type":"Point"}
}