{
  "type": "Feature",
  "properties": {
    "gn:admin1_code":"33",
    "gn:asciiname":"Znamenka",
    "gn:country_code":"RU",
    "gn:dem":108,
    "gn:feature_class":"P",
    "gn:feature_code":"PPL",
    "gn:name":"Znamenka",
    "gn:population":0,
    "gn:timezone":"Europe/Kirov",
    "iso:country":"RU",
    "name:eng_x_preferred":[
        "Znamenka"
    ],
    "name:nor_x_preferred":[
        "Znamenka"
    ],
    "name:rus_x_preferred":[
        "\u0417\u043d\u0430\u043c\u0435\u043d\u043a\u0430"
    ],
    "wof:name":"Znamenka",
    "wof:placetype":"locality"
},
  "geometry": {"coordinates":[47.83026,57.2449],"type":"Point"}
}