{
  "type": "Feature",
  "properties": {
    "gn:admin1_code":"9",
    "gn:asciiname":"Yablochkovo",
    "gn:country_code":"RU",
    "gn:dem":119,
    "gn:feature_class":"P",
    "gn:feature_code":"PPL",
    "gn:name":"Yablochkovo",
    "gn:population":0,
    "gn:timezone":"Europe/Moscow",
    "iso:country":"RU",
    "name:rus_x_preferred":[
        "\u042f\u0431\u043b\u043e\u0447\u043a\u043e\u0432\u043e"
    ],
    "name:und_x_variant":[
        "Yablochkova",
        "Yablokovo",
        "Yablochkovo"
    ],
    "wof:name":"Yablochkovo",
    "wof:placetype":"locality"
},
  "geometry": {"coordinates":[37.009,50.508],"type":"Point"}
}