{
  "type": "Feature",
  "properties": {
    "gn:admin1_code":"85",
    "gn:asciiname":"Zadnyaya Stupolokhta",
    "gn:country_code":"RU",
    "gn:dem":126,
    "gn:feature_class":"P",
    "gn:feature_code":"PPL",
    "gn:name":"Zadnyaya Stupolokhta",
    "gn:population":0,
    "gn:timezone":"Europe/Moscow",
    "iso:country":"RU",
    "name:rus_x_preferred":[
        "\u0417\u0430\u0434\u043d\u044f\u044f \u0421\u0442\u0443\u043f\u043e\u043b\u043e\u0445\u0442\u0430"
    ],
    "wof:name":"Zadnyaya Stupolokhta",
    "wof:placetype":"locality"
},
  "geometry": {"coordinates":[36.9943,59.5146],"type":"Point"}
}