{
  "type": "Feature",
  "properties": {
    "gn:admin1_code":"85",
    "gn:asciiname":"Mitinskoye",
    "gn:country_code":"RU",
    "gn:dem":131,
    "gn:feature_class":"P",
    "gn:feature_code":"PPL",
    "gn:name":"Mitinskoye",
    "gn:population":0,
    "gn:timezone":"Europe/Moscow",
    "iso:country":"RU",
    "name:rus_x_preferred":[
        "\u041c\u0438\u0442\u0438\u043d\u0441\u043a\u043e\u0435"
    ],
    "wof:name":"Mitinskoye",
    "wof:placetype":"locality"
},
  "geometry": {"coordinates":[38.6273,59.9717],"type":"Point"}
}