{
  "type": "Feature",
  "properties": {
    "gn:admin1_code":"52.0",
    "gn:asciiname":"Bugry",
    "gn:country_code":"RU",
    "gn:dem":179,
    "gn:feature_class":"P",
    "gn:feature_code":"PPL",
    "gn:name":"Bugry",
    "gn:population":0,
    "gn:timezone":"Europe/Moscow",
    "iso:country":"RU",
    "name:eng_x_preferred":[
        "Bugry"
    ],
    "name:nor_x_preferred":[
        "Bugry"
    ],
    "name:rus_x_preferred":[
        "\u0411\u0443\u0433\u0440\u044b"
    ],
    "name:und_x_variant":[
        "\u0411\u0443\u0433\u0440\u044b",
        "Bugry"
    ],
    "wof:name":"Bugry",
    "wof:placetype":"locality"
},
  "geometry": {"coordinates":[35.23552,58.75648],"type":"Point"}
}