{
  "type": "Feature",
  "properties": {
    "gn:admin1_code":"20",
    "gn:asciiname":"Undyrik",
    "gn:country_code":"RU",
    "gn:dem":574,
    "gn:feature_class":"P",
    "gn:feature_code":"PPL",
    "gn:name":"Undyrik",
    "gn:population":0,
    "gn:timezone":"Asia/Irkutsk",
    "iso:country":"RU",
    "name:eng_x_preferred":[
        "Undyrik"
    ],
    "name:nor_x_preferred":[
        "Undrik"
    ],
    "name:rus_x_preferred":[
        "\u0423\u043d\u0434\u0440\u0438\u043a"
    ],
    "wof:name":"Undyrik",
    "wof:placetype":"locality"
},
  "geometry": {"coordinates":[100.08333,54.28333000000001],"type":"Point"}
}