{
  "type": "Feature",
  "properties": {
    "gn:admin1_code":"53",
    "gn:asciiname":"Novokazarino",
    "gn:country_code":"RU",
    "gn:dem":114,
    "gn:feature_class":"P",
    "gn:feature_code":"PPL",
    "gn:name":"Novokazarino",
    "gn:population":0,
    "gn:timezone":"Asia/Novosibirsk",
    "iso:country":"RU",
    "name:eng_x_preferred":[
        "Novokazarino"
    ],
    "name:nor_x_preferred":[
        "Novokazarino"
    ],
    "name:rus_x_preferred":[
        "\u041d\u043e\u0432\u043e\u043a\u0430\u0437\u0430\u0440\u0438\u043d\u043e"
    ],
    "wof:name":"Novokazarino",
    "wof:placetype":"locality"
},
  "geometry": {"coordinates":[77.81475999999998,54.37195],"type":"Point"}
}