{
  "type": "Feature",
  "properties": {
    "gn:admin1_code":"17",
    "gn:admin2_code":"480804",
    "gn:asciiname":"Gadaichi",
    "gn:country_code":"RU",
    "gn:dem":1079,
    "gn:feature_class":"P",
    "gn:feature_code":"PPL",
    "gn:name":"Gadaichi",
    "gn:population":0,
    "gn:timezone":"Europe/Moscow",
    "iso:country":"RU",
    "name:rus_x_preferred":[
        "\u0413\u0430\u0434\u0430\u0438\u0447\u0438"
    ],
    "name:und_x_variant":[
        "\u0413\u0430\u0434\u0430\u0438\u0447\u0438"
    ],
    "wof:name":"Gadaichi",
    "wof:placetype":"locality"
},
  "geometry": {"coordinates":[46.07269,42.47028],"type":"Point"}
}