{
  "type": "Feature",
  "properties": {
    "gn:admin1_code":"71",
    "gn:asciiname":"Kukarskaya",
    "gn:country_code":"RU",
    "gn:dem":119,
    "gn:feature_class":"P",
    "gn:feature_code":"PPL",
    "gn:name":"Kukarskaya",
    "gn:population":0,
    "gn:timezone":"Asia/Yekaterinburg",
    "iso:country":"RU",
    "name:rus_x_preferred":[
        "\u041a\u0443\u043a\u0430\u0440\u0441\u043a\u0430\u044f"
    ],
    "wof:name":"Kukarskaya",
    "wof:placetype":"locality"
},
  "geometry": {"coordinates":[62.01667,58.46666999999999],"type":"Point"}
}