{
  "type": "Feature",
  "properties": {
    "gn:admin1_code":"8",
    "gn:asciiname":"Novotavlarovo",
    "gn:country_code":"RU",
    "gn:dem":237,
    "gn:feature_class":"P",
    "gn:feature_code":"PPL",
    "gn:name":"Novotavlarovo",
    "gn:population":0,
    "gn:timezone":"Asia/Yekaterinburg",
    "iso:country":"RU",
    "name:bak_x_preferred":[
        "\u042f\u04a3\u044b \u0422\u0430\u0443\u043b\u0430\u0440"
    ],
    "name:che_x_preferred":[
        "\u041d\u043e\u0432\u043e\u0442\u0430\u0432\u043b\u0430\u0440\u043e\u0432\u043e"
    ],
    "name:hye_x_preferred":[
        "\u0546\u0578\u057e\u0578\u057f\u0561\u057e\u056c\u0561\u0580\u0578\u057e\u0578"
    ],
    "name:kaz_x_preferred":[
        "\u0416\u0430\u04a3\u0430 \u0442\u0430\u0432\u043b\u0430\u0440"
    ],
    "name:kir_x_preferred":[
        "\u0416\u0430\u04a3\u044b \u0442\u0430\u0432\u043b\u0430\u0440"
    ],
    "name:rus_x_preferred":[
        "\u041d\u043e\u0432\u043e\u0442\u0430\u0432\u043b\u0430\u0440\u043e\u0432\u043e"
    ],
    "name:tat_x_preferred":[
        "\u042f\u04a3\u0430 \u0422\u0430\u0443\u043b\u0430\u0440"
    ],
    "name:und_x_variant":[
        "Novotavlyarovo",
        "Novotavlarovo",
        "\u041d\u043e\u0432\u043e\u0442\u0430\u0432\u043b\u0430\u0440\u043e\u0432\u043e"
    ],
    "wof:name":"Novotavlarovo",
    "wof:placetype":"locality"
},
  "geometry": {"coordinates":[54.16667,54.88333000000001],"type":"Point"}
}