{
  "type": "Feature",
  "properties": {
    "gn:admin1_code":"85",
    "gn:asciiname":"Ozhegovo",
    "gn:country_code":"RU",
    "gn:dem":125,
    "gn:feature_class":"P",
    "gn:feature_code":"PPL",
    "gn:name":"Ozhegovo",
    "gn:population":0,
    "gn:timezone":"Europe/Moscow",
    "iso:country":"RU",
    "name:rus_x_preferred":[
        "\u041e\u0436\u0435\u0433\u043e\u0432\u043e"
    ],
    "wof:name":"Ozhegovo",
    "wof:placetype":"locality"
},
  "geometry": {"coordinates":[38.7628,59.6474],"type":"Point"}
}