{
  "type": "Feature",
  "properties": {
    "gn:admin1_code":"25",
    "gn:asciiname":"Tarutino",
    "gn:country_code":"RU",
    "gn:dem":138,
    "gn:feature_class":"P",
    "gn:feature_code":"PPL",
    "gn:name":"Tarutino",
    "gn:population":0,
    "gn:timezone":"Europe/Moscow",
    "iso:country":"RU",
    "name:eng_x_preferred":[
        "Tarutino"
    ],
    "name:nor_x_preferred":[
        "Tarutino"
    ],
    "name:rus_x_preferred":[
        "\u0422\u0430\u0440\u0443\u0442\u0438\u043d\u043e"
    ],
    "wof:name":"Tarutino",
    "wof:placetype":"locality"
},
  "geometry": {"coordinates":[36.94098,55.12226999999999],"type":"Point"}
}