{
  "type": "Feature",
  "properties": {
    "gn:admin1_code":"9",
    "gn:asciiname":"Vysokiy",
    "gn:country_code":"RU",
    "gn:dem":229,
    "gn:feature_class":"P",
    "gn:feature_code":"PPL",
    "gn:name":"Vysokiy",
    "gn:population":0,
    "gn:timezone":"Europe/Moscow",
    "iso:country":"RU",
    "name:rus_x_preferred":[
        "\u0412\u044b\u0441\u043e\u043a\u0438\u0439"
    ],
    "name:und_x_variant":[
        "Vysokiy-Melavskiy"
    ],
    "wof:name":"Vysokiy",
    "wof:placetype":"locality"
},
  "geometry": {"coordinates":[37.3951,51.0857],"type":"Point"}
}