{
  "type": "Feature",
  "properties": {
    "gn:admin1_code":"44",
    "gn:asciiname":"Mirnyy",
    "gn:cc2":"RU",
    "gn:country_code":"RU",
    "gn:dem":752,
    "gn:feature_class":"P",
    "gn:feature_code":"PPL",
    "gn:name":"Mirnyy",
    "gn:population":0,
    "gn:timezone":"Asia/Magadan",
    "iso:country":"RU",
    "name:eng_x_preferred":[
        "Mirnyy"
    ],
    "name:nor_x_preferred":[
        "Mirnyj"
    ],
    "name:rus_x_preferred":[
        "\u041c\u0438\u0440\u043d\u044b\u0439"
    ],
    "name:und_x_variant":[
        "Stakhanovets",
        "Stakhanoverts"
    ],
    "wof:name":"Mirnyy",
    "wof:placetype":"locality"
},
  "geometry": {"coordinates":[147.91666999999995,63.11666999999999],"type":"Point"}
}