{
  "type": "Feature",
  "properties": {
    "gn:admin1_code":"44",
    "gn:asciiname":"Mirnyy",
    "gn:cc2":"RU",
    "gn:country_code":"RU",
    "gn:dem":752,
    "gn:feature_class":"P",
    "gn:feature_code":"PPL",
    "gn:name":"Mirnyy",
    "gn:population":0,
    "gn:timezone":"Asia/Magadan",
    "iso:country":"RU",
    "name:ben_x_preferred":[
        "\u09ae\u09bf\u09b0\u09a8\u09bf"
    ],
    "name:ell_x_preferred":[
        "\u039c\u03af\u03c1\u03bd\u03b9"
    ],
    "name:eng_x_preferred":[
        "Mirnyy"
    ],
    "name:hin_x_preferred":[
        "\u092e\u093f\u0930\u0928\u0940"
    ],
    "name:nor_x_preferred":[
        "Mirnyj"
    ],
    "name:rus_x_preferred":[
        "\u041c\u0438\u0440\u043d\u044b\u0439"
    ],
    "name:und_x_variant":[
        "Stakhanovets",
        "Stakhanoverts"
    ],
    "wof:name":"Mirnyy",
    "wof:placetype":"locality"
},
  "geometry": {"coordinates":[147.91667000000001,63.11667],"type":"Point"}
}