{
  "type": "Feature",
  "properties": {
    "gn:admin1_code":"63",
    "gn:asciiname":"Ynakhsyt",
    "gn:country_code":"RU",
    "gn:dem":119,
    "gn:feature_class":"P",
    "gn:feature_code":"PPL",
    "gn:name":"Ynakhsyt",
    "gn:population":0,
    "gn:timezone":"Asia/Yakutsk",
    "iso:country":"RU",
    "name:che_x_preferred":[
        "\u042b\u043d\u0430\u0445\u0441\u044b\u0442"
    ],
    "name:eng_x_preferred":[
        "Ynakhsyt"
    ],
    "name:nor_x_preferred":[
        "Ynakhsyt"
    ],
    "name:rus_x_preferred":[
        "\u042b\u043d\u0430\u0445\u0441\u044b\u0442"
    ],
    "name:sah_x_preferred":[
        "\u042b\u043d\u0430\u0445\u0441\u044b\u0442"
    ],
    "wof:name":"Ynakhsyt",
    "wof:placetype":"locality"
},
  "geometry": {"coordinates":[119.20652,63.56741],"type":"Point"}
}