{
  "type": "Feature",
  "properties": {
    "gn:admin1_code":"4",
    "gn:asciiname":"Pushtulim",
    "gn:country_code":"RU",
    "gn:dem":329,
    "gn:feature_class":"P",
    "gn:feature_code":"PPL",
    "gn:name":"Pushtulim",
    "gn:population":1000,
    "gn:timezone":"Asia/Barnaul",
    "iso:country":"RU",
    "name:eng_x_preferred":[
        "Pushtulim"
    ],
    "name:nor_x_preferred":[
        "Pusjtulim"
    ],
    "name:rus_x_preferred":[
        "\u041f\u0443\u0448\u0442\u0443\u043b\u0438\u043c"
    ],
    "name:und_x_variant":[
        "Pushtalim",
        "Pushtylim",
        "Pushtulim"
    ],
    "wof:name":"Pushtulim",
    "wof:placetype":"locality",
    "wof:population":1000
},
  "geometry": {"coordinates":[86.4278,53.2033],"type":"Point"}
}