{
  "type": "Feature",
  "properties": {
    "gn:admin1_code":"90",
    "gn:asciiname":"Shemeti",
    "gn:country_code":"RU",
    "gn:dem":158,
    "gn:feature_class":"P",
    "gn:feature_code":"PPL",
    "gn:name":"Shemeti",
    "gn:population":0,
    "gn:timezone":"Asia/Yekaterinburg",
    "iso:country":"RU",
    "name:che_x_preferred":[
        "\u0428\u0435\u043c\u0435\u0442\u0438"
    ],
    "name:eng_x_preferred":[
        "Shemeti"
    ],
    "name:nor_x_preferred":[
        "Sjemeti"
    ],
    "name:rus_x_preferred":[
        "\u0428\u0435\u043c\u0435\u0442\u0438"
    ],
    "name:und_x_variant":[
        "\u0428\u0435\u043c\u0435\u0442\u0438",
        "Shameti",
        "Shemeti"
    ],
    "wof:name":"Shemeti",
    "wof:placetype":"locality"
},
  "geometry": {"coordinates":[56.2396,58.3525],"type":"Point"}
}