{
  "type": "Feature",
  "properties": {
    "gn:admin1_code":"90.0",
    "gn:asciiname":"Bol'shoy Bereznik",
    "gn:country_code":"RU",
    "gn:dem":133,
    "gn:feature_class":"P",
    "gn:feature_code":"PPL",
    "gn:name":"Bol\u2019shoy Bereznik",
    "gn:population":0,
    "gn:timezone":"Asia/Yekaterinburg",
    "iso:country":"RU",
    "name:rus_x_preferred":[
        "\u0411\u043e\u043b\u044c\u0448\u043e\u0439 \u0411\u0435\u0440\u0435\u0437\u043d\u0438\u043a"
    ],
    "name:und_x_variant":[
        "Bol\u2019shoy Bereznik"
    ],
    "wof:name":"Bol'shoy Bereznik",
    "wof:placetype":"locality"
},
  "geometry": {"coordinates":[56.04509,56.49276999999999],"type":"Point"}
}