{
  "type": "Feature",
  "properties": {
    "gn:admin1_code":"69",
    "gn:asciiname":"Pneva",
    "gn:country_code":"RU",
    "gn:dem":171,
    "gn:feature_class":"P",
    "gn:feature_code":"PPL",
    "gn:name":"Pn\u00ebva",
    "gn:population":0,
    "gn:timezone":"Europe/Moscow",
    "iso:country":"RU",
    "name:rus_x_preferred":[
        "\u041f\u043d\u0451\u0432\u0430"
    ],
    "name:und_x_variant":[
        "Pn\u00ebva"
    ],
    "wof:name":"Pneva",
    "wof:placetype":"locality"
},
  "geometry": {"coordinates":[31.94424,53.91174],"type":"Point"}
}