{
  "type": "Feature",
  "properties": {
    "gn:admin1_code":"8",
    "gn:asciiname":"Taganayevo",
    "gn:country_code":"RU",
    "gn:dem":84,
    "gn:feature_class":"P",
    "gn:feature_code":"PPL",
    "gn:name":"Taganayevo",
    "gn:population":0,
    "gn:timezone":"Asia/Yekaterinburg",
    "iso:country":"RU",
    "name:rus_x_preferred":[
        "\u0422\u0430\u0433\u0430\u043d\u0430\u0435\u0432\u043e"
    ],
    "name:und_x_variant":[
        "\u0422\u0430\u0433\u0430\u043d\u0430\u0435\u0432\u043e"
    ],
    "wof:name":"Taganayevo",
    "wof:placetype":"locality"
},
  "geometry": {"coordinates":[55.8094,54.9987],"type":"Point"}
}