{
  "type": "Feature",
  "properties": {
    "gn:admin1_code":"61",
    "gn:asciiname":"Verkhniy Pikhovkin",
    "gn:country_code":"RU",
    "gn:dem":52,
    "gn:feature_class":"P",
    "gn:feature_code":"PPL",
    "gn:name":"Verkhniy Pikhovkin",
    "gn:population":0,
    "gn:timezone":"Europe/Moscow",
    "iso:country":"RU",
    "name:rus_x_preferred":[
        "\u0412\u0435\u0440\u0445\u043d\u0438\u0439 \u041f\u0438\u0445\u043e\u0432\u043a\u0438\u043d"
    ],
    "name:und_x_variant":[
        "Pikhovskiy",
        "Pikhovkin",
        "Verkhniy Pikhovkin",
        "Verkhne-Pikhovka"
    ],
    "wof:name":"Verkhniy Pikhovkin",
    "wof:placetype":"locality"
},
  "geometry": {"coordinates":[40.33125,48.55931],"type":"Point"}
}