{
  "type": "Feature",
  "properties": {
    "gn:admin1_code":"91",
    "gn:asciiname":"Krasnorechenskiy",
    "gn:country_code":"RU",
    "gn:dem":270,
    "gn:feature_class":"P",
    "gn:feature_code":"PPL",
    "gn:name":"Krasnorechenskiy",
    "gn:population":0,
    "gn:timezone":"Asia/Krasnoyarsk",
    "iso:country":"RU",
    "wof:name":"Krasnorechenskiy",
    "wof:placetype":"locality"
},
  "geometry": {"coordinates":[89.91639000000001,56.22333],"type":"Point"}
}