{
  "type": "Feature",
  "properties": {
    "gn:admin1_code":"77",
    "gn:asciiname":"Shchelkanikha",
    "gn:country_code":"RU",
    "gn:dem":152,
    "gn:feature_class":"P",
    "gn:feature_code":"PPL",
    "gn:name":"Shchelkanikha",
    "gn:population":0,
    "gn:timezone":"Europe/Moscow",
    "iso:country":"RU",
    "name:rus_x_preferred":[
        "\u0429\u0435\u043b\u043a\u0430\u043d\u0438\u0445\u0430"
    ],
    "name:und_x_variant":[
        "\u0429\u0435\u043b\u043a\u0430\u043d\u0438\u0445\u0430"
    ],
    "wof:name":"Shchelkanikha",
    "wof:placetype":"locality"
},
  "geometry": {"coordinates":[36.8987,58.5217],"type":"Point"}
}