{
  "type": "Feature",
  "properties": {
    "gn:admin1_code":"21",
    "gn:asciiname":"Prislonikha",
    "gn:country_code":"RU",
    "gn:dem":123,
    "gn:feature_class":"P",
    "gn:feature_code":"PPL",
    "gn:name":"Prislonikha",
    "gn:population":0,
    "gn:timezone":"Europe/Moscow",
    "iso:country":"RU",
    "name:rus_x_preferred":[
        "\u041f\u0440\u0438\u0441\u043b\u043e\u043d\u0438\u0445\u0430"
    ],
    "wof:name":"Prislonikha",
    "wof:placetype":"locality"
},
  "geometry": {"coordinates":[41.81893,57.03365],"type":"Point"}
}