{
  "type": "Feature",
  "properties": {
    "gn:admin1_code":"47.0",
    "gn:asciiname":"Gavshino",
    "gn:country_code":"RU",
    "gn:dem":187,
    "gn:feature_class":"P",
    "gn:feature_code":"PPL",
    "gn:name":"Gavshino",
    "gn:population":0,
    "gn:timezone":"Europe/Moscow",
    "iso:country":"RU",
    "name:rus_x_preferred":[
        "\u0413\u0430\u0432\u0448\u0438\u043d\u043e"
    ],
    "wof:name":"Gavshino",
    "wof:placetype":"locality"
},
  "geometry": {"coordinates":[36.02694,55.57083000000001],"type":"Point"}
}