{
  "type": "Feature",
  "properties": {
    "gn:admin1_code":"65.0",
    "gn:asciiname":"Cheremokhovka",
    "gn:country_code":"RU",
    "gn:dem":177,
    "gn:feature_class":"P",
    "gn:feature_code":"PPL",
    "gn:name":"Cher\u00ebmokhovka",
    "gn:population":0,
    "gn:timezone":"Europe/Samara",
    "iso:country":"RU",
    "name:rus_x_preferred":[
        "Cher\u00ebmokhovka"
    ],
    "name:rus_x_variant":[
        "\u0427\u0435\u0440\u0451\u043c\u043e\u0445\u043e\u0432\u043a\u0430",
        "Cher\u00ebmukhovka"
    ],
    "name:und_x_variant":[
        "Cheremokhovo"
    ],
    "wof:name":"Cheremokhovka",
    "wof:placetype":"locality"
},
  "geometry": {"coordinates":[48.2786,53.4518],"type":"Point"}
}