{
  "type": "Feature",
  "properties": {
    "gn:admin1_code":"85",
    "gn:asciiname":"Kukolovskaya",
    "gn:country_code":"RU",
    "gn:dem":117,
    "gn:feature_class":"P",
    "gn:feature_code":"PPL",
    "gn:name":"Kukolovskaya",
    "gn:population":0,
    "gn:timezone":"Europe/Moscow",
    "iso:country":"RU",
    "name:eng_x_preferred":[
        "Kukolovskaya"
    ],
    "name:nor_x_preferred":[
        "Kukolovskaja"
    ],
    "name:rus_x_preferred":[
        "\u041a\u0443\u043a\u043e\u043b\u043e\u0432\u0441\u043a\u0430\u044f"
    ],
    "wof:name":"Kukolovskaya",
    "wof:placetype":"locality"
},
  "geometry": {"coordinates":[42.05522,60.66986],"type":"Point"}
}