{
  "type": "Feature",
  "properties": {
    "gn:admin1_code":"47",
    "gn:asciiname":"Radogina Dacha",
    "gn:country_code":"RU",
    "gn:dem":209,
    "gn:feature_class":"P",
    "gn:feature_code":"PPL",
    "gn:name":"Radogina Dacha",
    "gn:population":0,
    "gn:timezone":"Europe/Moscow",
    "iso:country":"RU",
    "name:rus_x_preferred":[
        "\u0420\u0430\u0434\u043e\u0433\u0438\u043d\u0430 \u0414\u0430\u0447\u0430"
    ],
    "wof:name":"Radogina Dacha",
    "wof:placetype":"locality"
},
  "geometry": {"coordinates":[39.01667,55.28333000000001],"type":"Point"}
}