{
  "type": "Feature",
  "properties": {
    "gn:admin1_code":"69",
    "gn:asciiname":"Gvozdikovo",
    "gn:country_code":"RU",
    "gn:dem":208,
    "gn:feature_class":"P",
    "gn:feature_code":"PPL",
    "gn:name":"Gvozdikovo",
    "gn:population":0,
    "gn:timezone":"Europe/Moscow",
    "iso:country":"RU",
    "name:rus_x_preferred":[
        "\u0413\u0432\u043e\u0437\u0434\u0438\u043a\u043e\u0432\u043e"
    ],
    "wof:name":"Gvozdikovo",
    "wof:placetype":"locality"
},
  "geometry": {"coordinates":[33.89588,55.08065],"type":"Point"}
}