{
  "type": "Feature",
  "properties": {
    "gn:admin1_code":"10",
    "gn:asciiname":"Pushkari",
    "gn:country_code":"RU",
    "gn:dem":174,
    "gn:feature_class":"P",
    "gn:feature_code":"PPL",
    "gn:name":"Pushkari",
    "gn:population":0,
    "gn:timezone":"Europe/Moscow",
    "iso:country":"RU",
    "name:rus_x_preferred":[
        "\u041f\u0443\u0448\u043a\u0430\u0440\u0438"
    ],
    "name:und_x_variant":[
        "\u041f\u0443\u0448\u043a\u0430\u0440\u0438"
    ],
    "wof:name":"Pushkari",
    "wof:placetype":"locality"
},
  "geometry": {"coordinates":[33.23703,52.84958],"type":"Point"}
}