{
  "type": "Feature",
  "properties": {
    "gn:admin1_code":"90",
    "gn:asciiname":"Verkhniy Kysmyl",
    "gn:country_code":"RU",
    "gn:dem":181,
    "gn:feature_class":"P",
    "gn:feature_code":"PPL",
    "gn:name":"Verkhniy Kysmyl",
    "gn:population":0,
    "gn:timezone":"Asia/Yekaterinburg",
    "iso:country":"RU",
    "name:rus_x_preferred":[
        "\u0412\u0435\u0440\u0445\u043d\u0438\u0439 \u041a\u044b\u0441\u043c\u044b\u043b"
    ],
    "name:und_x_variant":[
        "Verkhniy Kyslym"
    ],
    "wof:name":"Verkhniy Kysmyl",
    "wof:placetype":"locality"
},
  "geometry": {"coordinates":[57.2502,57.8396],"type":"Point"}
}