{
  "type": "Feature",
  "properties": {
    "gn:admin1_code":"55",
    "gn:asciiname":"Kaman",
    "gn:country_code":"RU",
    "gn:dem":271,
    "gn:feature_class":"P",
    "gn:feature_code":"PPL",
    "gn:name":"Kaman",
    "gn:population":0,
    "gn:timezone":"Asia/Yekaterinburg",
    "iso:country":"RU",
    "name:rus_x_preferred":[
        "\u041a\u0430\u043c\u0430\u043d"
    ],
    "name:und_x_variant":[
        "\u041a\u0430\u043c\u0430\u043d"
    ],
    "wof:name":"Kaman",
    "wof:placetype":"locality"
},
  "geometry": {"coordinates":[59.58333,50.75],"type":"Point"}
}