{
  "type": "Feature",
  "properties": {
    "gn:admin1_code":"55",
    "gn:asciiname":"Kaman",
    "gn:country_code":"RU",
    "gn:dem":271,
    "gn:feature_class":"P",
    "gn:feature_code":"PPL",
    "gn:name":"Kaman",
    "gn:population":0,
    "gn:timezone":"Asia/Yekaterinburg",
    "iso:country":"RU",
    "name:ben_x_preferred":[
        "\u0995\u09be\u09ae\u09be\u09a8"
    ],
    "name:bpy_x_preferred":[
        "\u0995\u09be\u09ae\u09be\u09a8"
    ],
    "name:ceb_x_preferred":[
        "Kaman"
    ],
    "name:fra_x_preferred":[
        "Kaman"
    ],
    "name:min_x_preferred":[
        "Kaman"
    ],
    "name:new_x_preferred":[
        "\u0915\u092e\u0928"
    ],
    "name:nld_x_preferred":[
        "Kaman"
    ],
    "name:por_x_preferred":[
        "Kaman"
    ],
    "name:rus_x_preferred":[
        "\u041a\u0430\u043c\u0430\u043d"
    ],
    "name:swe_x_preferred":[
        "Kaman"
    ],
    "name:tur_x_preferred":[
        "Kaman"
    ],
    "name:vie_x_preferred":[
        "Kaman"
    ],
    "wof:name":"Kaman",
    "wof:placetype":"locality"
},
  "geometry": {"coordinates":[59.58333,50.75],"type":"Point"}
}