{
  "type": "Feature",
  "properties": {
    "gn:admin1_code":"47",
    "gn:asciiname":"Khvolovo",
    "gn:country_code":"RU",
    "gn:dem":184,
    "gn:feature_class":"P",
    "gn:feature_code":"PPL",
    "gn:name":"Khvolovo",
    "gn:population":0,
    "gn:timezone":"Europe/Moscow",
    "iso:country":"RU",
    "name:rus_x_preferred":[
        "\u0425\u0432\u043e\u043b\u043e\u0432\u043e"
    ],
    "name:und_x_variant":[
        "Khvalovo",
        "Khvolovo",
        "\u0425\u0432\u043e\u043b\u043e\u0432\u043e"
    ],
    "wof:name":"Khvolovo",
    "wof:placetype":"locality"
},
  "geometry": {"coordinates":[36.63845,55.87243],"type":"Point"}
}