{
  "type": "Feature",
  "properties": {
    "gn:admin1_code":"23",
    "gn:asciiname":"Panfilovo",
    "gn:country_code":"RU",
    "gn:dem":56,
    "gn:feature_class":"P",
    "gn:feature_code":"PPL",
    "gn:name":"Panfilovo",
    "gn:population":0,
    "gn:timezone":"Europe/Kaliningrad",
    "iso:country":"RU",
    "name:rus_x_preferred":[
        "\u041f\u0430\u043d\u0444\u0438\u043b\u043e\u0432\u043e"
    ],
    "name:ukr_x_preferred":[
        "\u041f\u0430\u043d\u0444\u0456\u043b\u043e\u0432\u043e"
    ],
    "name:und_x_variant":[
        "\u041f\u0430\u043d\u0444\u0438\u043b\u043e\u0432\u043e"
    ],
    "wof:name":"Panfilovo",
    "wof:placetype":"locality"
},
  "geometry": {"coordinates":[21.46639,54.37775],"type":"Point"}
}