{
  "type": "Feature",
  "properties": {
    "gn:admin1_code":"47.0",
    "gn:asciiname":"Ovchinki",
    "gn:country_code":"RU",
    "gn:dem":143,
    "gn:feature_class":"P",
    "gn:feature_code":"PPL",
    "gn:name":"Ovchinki",
    "gn:population":0,
    "gn:timezone":"Europe/Moscow",
    "iso:country":"RU",
    "name:rus_x_preferred":[
        "\u041e\u0432\u0447\u0438\u043d\u043a\u0438"
    ],
    "name:und_x_variant":[
        "\u041e\u0432\u0447\u0438\u043d\u043a\u0438"
    ],
    "wof:name":"Ovchinki",
    "wof:placetype":"locality"
},
  "geometry": {"coordinates":[37.69,55.43],"type":"Point"}
}