{
  "type": "Feature",
  "properties": {
    "gn:admin1_code":"9",
    "gn:asciiname":"Neklyudovo",
    "gn:country_code":"RU",
    "gn:dem":130,
    "gn:feature_class":"P",
    "gn:feature_code":"PPL",
    "gn:name":"Neklyudovo",
    "gn:population":0,
    "gn:timezone":"Europe/Moscow",
    "iso:country":"RU",
    "name:eng_x_preferred":[
        "Neklyudovo"
    ],
    "name:nor_x_preferred":[
        "Nekljudovo"
    ],
    "name:rus_x_preferred":[
        "\u041d\u0435\u043a\u043b\u044e\u0434\u043e\u0432\u043e"
    ],
    "name:und_x_variant":[
        "Neklyudove",
        "Neklyudovo"
    ],
    "wof:name":"Neklyudovo",
    "wof:placetype":"locality"
},
  "geometry": {"coordinates":[36.91007000000001,50.59112],"type":"Point"}
}