{
  "type": "Feature",
  "properties": {
    "gn:admin1_code":"67",
    "gn:asciiname":"Gusevo",
    "gn:country_code":"RU",
    "gn:dem":115,
    "gn:feature_class":"P",
    "gn:feature_code":"PPL",
    "gn:name":"Gusevo",
    "gn:population":0,
    "gn:timezone":"Europe/Saratov",
    "iso:country":"RU",
    "name:aze_x_preferred":[
        "Qusev"
    ],
    "name:bak_x_preferred":[
        "\u0413\u0443\u0441\u0435\u0432"
    ],
    "name:che_x_preferred":[
        "\u0413\u0443\u0441\u0435\u0432\u043e"
    ],
    "name:hye_x_preferred":[
        "\u0533\u0578\u0582\u057d\u0587\u0578"
    ],
    "name:kat_x_preferred":[
        "\u10d2\u10e3\u10e1\u10d4\u10d5\u10dd"
    ],
    "name:kaz_x_preferred":[
        "\u0413\u0443\u0441\u0435\u0432"
    ],
    "name:kir_x_preferred":[
        "\u0413\u0443\u0441"
    ],
    "name:rus_x_preferred":[
        "\u0413\u0443\u0441\u0435\u0432\u043e"
    ],
    "name:tat_x_preferred":[
        "\u0413\u0443\u0441\u0435\u0432\u043e"
    ],
    "name:ukr_x_preferred":[
        "\u0413\u0443\u0441\u0435\u0432\u043e"
    ],
    "wof:name":"Gusevo",
    "wof:placetype":"locality"
},
  "geometry": {"coordinates":[45.71328,50.85031],"type":"Point"}
}