{
  "type": "Feature",
  "properties": {
    "gn:admin1_code":"8",
    "gn:asciiname":"Kumlekul'",
    "gn:country_code":"RU",
    "gn:dem":93,
    "gn:feature_class":"P",
    "gn:feature_code":"PPL",
    "gn:name":"Kumlekul\u2019",
    "gn:population":0,
    "gn:timezone":"Asia/Yekaterinburg",
    "iso:country":"RU",
    "name:eng_x_preferred":[
        "Kumlekulevo"
    ],
    "name:nor_x_preferred":[
        "Kumlekul"
    ],
    "name:rus_x_preferred":[
        "\u041a\u0443\u043c\u043b\u0435\u043a\u0443\u043b\u044c"
    ],
    "name:und_x_variant":[
        "Kumlekul\u2019"
    ],
    "wof:name":"Kumlekul'",
    "wof:placetype":"locality"
},
  "geometry": {"coordinates":[55.8695,54.9484],"type":"Point"}
}