{
  "type": "Feature",
  "properties": {
    "gn:admin1_code":"59",
    "gn:asciiname":"Shakhterskiy",
    "gn:country_code":"RU",
    "gn:dem":37,
    "gn:feature_class":"P",
    "gn:feature_code":"PPL",
    "gn:name":"Shakht\u00ebrskiy",
    "gn:population":0,
    "gn:timezone":"Asia/Vladivostok",
    "iso:country":"RU",
    "name:rus_x_preferred":[
        "\u0428\u0430\u0445\u0442\u0451\u0440\u0441\u043a\u0438\u0439"
    ],
    "name:und_x_variant":[
        "Shakht\u00ebrskiy"
    ],
    "wof:name":"Shakhterskiy",
    "wof:placetype":"locality"
},
  "geometry": {"coordinates":[130.72376,42.72607],"type":"Point"}
}