{
  "type": "Feature",
  "properties": {
    "gn:admin1_code":"62",
    "gn:asciiname":"Letniki",
    "gn:country_code":"RU",
    "gn:dem":99,
    "gn:feature_class":"P",
    "gn:feature_code":"PPL",
    "gn:name":"Letniki",
    "gn:population":0,
    "gn:timezone":"Europe/Moscow",
    "iso:country":"RU",
    "name:eng_x_preferred":[
        "Letniki"
    ],
    "name:nor_x_preferred":[
        "Letniki"
    ],
    "name:rus_x_preferred":[
        "\u041b\u0435\u0442\u043d\u0438\u043a\u0438"
    ],
    "name:und_x_variant":[
        "Lotniki"
    ],
    "wof:name":"Letniki",
    "wof:placetype":"locality"
},
  "geometry": {"coordinates":[40.9056,54.1704],"type":"Point"}
}