{
  "type": "Feature",
  "properties": {
    "gn:admin1_code":"88",
    "gn:asciiname":"Voskresenka",
    "gn:country_code":"RU",
    "gn:dem":163,
    "gn:feature_class":"P",
    "gn:feature_code":"PPL",
    "gn:name":"Voskresenka",
    "gn:population":0,
    "gn:timezone":"Europe/Moscow",
    "iso:country":"RU",
    "name:che_x_preferred":[
        "\u0412\u043e\u0441\u043a\u0440\u0435\u0441\u0435\u043d\u043a\u0430"
    ],
    "name:rus_x_preferred":[
        "\u0412\u043e\u0441\u043a\u0440\u0435\u0441\u0435\u043d\u043a\u0430"
    ],
    "name:und_x_variant":[
        "Voskresenskoye"
    ],
    "wof:name":"Voskresenka",
    "wof:placetype":"locality"
},
  "geometry": {"coordinates":[38.4017,57.0698],"type":"Point"}
}