{
  "type": "Feature",
  "properties": {
    "gn:admin1_code":"4",
    "gn:asciiname":"Bekkerdinovka",
    "gn:country_code":"RU",
    "gn:dem":110,
    "gn:feature_class":"P",
    "gn:feature_code":"PPL",
    "gn:name":"Bekkerdinovka",
    "gn:population":0,
    "gn:timezone":"Asia/Barnaul",
    "iso:country":"RU",
    "name:rus_x_preferred":[
        "\u0411\u0435\u043a\u043a\u0435\u0440\u0434\u0438\u043d\u043e\u0432\u043a\u0430"
    ],
    "name:und_x_variant":[
        "\u0411\u0435\u043a\u043a\u0435\u0440\u0434\u0438\u043d\u043e\u0432\u043a\u0430"
    ],
    "wof:name":"Bekkerdinovka",
    "wof:placetype":"locality"
},
  "geometry": {"coordinates":[78.5557,53.1308],"type":"Point"}
}