{
  "type": "Feature",
  "properties": {
    "gn:admin1_code":"1",
    "gn:asciiname":"Groznyy",
    "gn:country_code":"RU",
    "gn:dem":244,
    "gn:feature_class":"P",
    "gn:feature_code":"PPL",
    "gn:name":"Groznyy",
    "gn:population":0,
    "gn:timezone":"Europe/Moscow",
    "iso:country":"RU",
    "name:rus_x_preferred":[
        "\u0413\u0440\u043e\u0437\u043d\u044b\u0439"
    ],
    "name:und_x_variant":[
        "\u0413\u0440\u043e\u0437\u043d\u044b\u0439"
    ],
    "wof:name":"Groznyy",
    "wof:placetype":"locality"
},
  "geometry": {"coordinates":[40.19361,44.64667],"type":"Point"}
}