{
  "type": "Feature",
  "properties": {
    "gn:admin1_code":"38.0",
    "gn:asciiname":"Bogmin",
    "gn:country_code":"RU",
    "gn:dem":2,
    "gn:feature_class":"P",
    "gn:feature_code":"PPL",
    "gn:name":"Bogmin",
    "gn:population":0,
    "gn:timezone":"Europe/Moscow",
    "iso:country":"RU",
    "name:rus_x_preferred":[
        "\u0411\u043e\u0433\u043c\u0438\u043d"
    ],
    "wof:name":"Bogmin",
    "wof:placetype":"locality"
},
  "geometry": {"coordinates":[38.05972,45.42444],"type":"Point"}
}