{
  "type": "Feature",
  "properties": {
    "gn:admin1_code":"56",
    "gn:asciiname":"Novoselennaya",
    "gn:country_code":"RU",
    "gn:dem":180,
    "gn:feature_class":"P",
    "gn:feature_code":"PPL",
    "gn:name":"Novoselennaya",
    "gn:population":0,
    "gn:timezone":"Europe/Moscow",
    "iso:country":"RU",
    "name:rus_x_preferred":[
        "\u041d\u043e\u0432\u043e\u0441\u0435\u043b\u0435\u043d\u043d\u0430\u044f"
    ],
    "name:und_x_variant":[
        "Voyekovo",
        "Novoselennaya"
    ],
    "wof:name":"Novoselennaya",
    "wof:placetype":"locality"
},
  "geometry": {"coordinates":[36.31947,52.94581],"type":"Point"}
}