{
  "type": "Feature",
  "properties": {
    "gn:admin1_code":"77",
    "gn:asciiname":"Goncharovka",
    "gn:country_code":"RU",
    "gn:dem":254,
    "gn:feature_class":"P",
    "gn:feature_code":"PPL",
    "gn:name":"Goncharovka",
    "gn:population":0,
    "gn:timezone":"Europe/Moscow",
    "iso:country":"RU",
    "name:rus_x_preferred":[
        "\u0413\u043e\u043d\u0447\u0430\u0440\u043e\u0432\u043a\u0430"
    ],
    "name:und_x_variant":[
        "\u0413\u043e\u043d\u0447\u0430\u0440\u043e\u0432\u043a\u0430"
    ],
    "wof:name":"Goncharovka",
    "wof:placetype":"locality"
},
  "geometry": {"coordinates":[33.5753,56.0236],"type":"Point"}
}