{
  "type": "Feature",
  "properties": {
    "gn:admin1_code":"77",
    "gn:asciiname":"Usad'ba",
    "gn:country_code":"RU",
    "gn:dem":149,
    "gn:feature_class":"P",
    "gn:feature_code":"PPL",
    "gn:name":"Usad\u2019ba",
    "gn:population":0,
    "gn:timezone":"Europe/Moscow",
    "iso:country":"RU",
    "name:rus_x_preferred":[
        "\u0423\u0441\u0430\u0434\u044c\u0431\u0430"
    ],
    "name:und_x_variant":[
        "Usad\u2019ba",
        "\u0423\u0441\u0430\u0434\u044c\u0431\u0430"
    ],
    "wof:name":"Usad'ba",
    "wof:placetype":"locality"
},
  "geometry": {"coordinates":[31.77755,57.08716],"type":"Point"}
}