{
  "type": "Feature",
  "properties": {
    "gn:admin1_code":"93",
    "gn:asciiname":"Narasun",
    "gn:country_code":"RU",
    "gn:dem":762,
    "gn:feature_class":"P",
    "gn:feature_code":"PPL",
    "gn:name":"Narasun",
    "gn:population":0,
    "gn:timezone":"Asia/Chita",
    "iso:country":"RU",
    "name:eng_x_preferred":[
        "Narasun"
    ],
    "name:nor_x_preferred":[
        "Narasun"
    ],
    "name:rus_x_preferred":[
        "\u041d\u0430\u0440\u0430\u0441\u0443\u043d"
    ],
    "name:und_x_variant":[
        "Narasunskiy",
        "\u041d\u0430\u0440\u0430\u0441\u0443\u043d",
        "Narasun"
    ],
    "wof:name":"Narasun",
    "wof:placetype":"locality"
},
  "geometry": {"coordinates":[112.97866999999999,50.09259],"type":"Point"}
}