{
  "type": "Feature",
  "properties": {
    "gn:admin1_code":"47",
    "gn:asciiname":"Goretovo",
    "gn:cc2":"RU",
    "gn:country_code":"RU",
    "gn:dem":190,
    "gn:feature_class":"P",
    "gn:feature_code":"PPL",
    "gn:name":"Goretovo",
    "gn:population":0,
    "gn:timezone":"Europe/Moscow",
    "iso:country":"RU",
    "name:eng_x_preferred":[
        "Goretovo"
    ],
    "name:nor_x_preferred":[
        "Goretovo"
    ],
    "name:rus_x_preferred":[
        "\u0413\u043e\u0440\u0435\u0442\u043e\u0432\u043e"
    ],
    "name:und_x_variant":[
        "Garetovo",
        "Bolshoye Goretovo",
        "Bol\u2019shoye Garetovo",
        "\u0413\u043e\u0440\u0435\u0442\u043e\u0432\u043e",
        "Goretovo"
    ],
    "wof:name":"Goretovo",
    "wof:placetype":"locality"
},
  "geometry": {"coordinates":[35.8075,55.61221999999999],"type":"Point"}
}