{
  "type": "Feature",
  "properties": {
    "gn:admin1_code":"40",
    "gn:asciiname":"Zarechnaya",
    "gn:cc2":"RU",
    "gn:country_code":"RU",
    "gn:dem":87,
    "gn:feature_class":"P",
    "gn:feature_code":"PPL",
    "gn:name":"Zarechnaya",
    "gn:population":0,
    "gn:timezone":"Asia/Yekaterinburg",
    "iso:country":"RU",
    "name:und_x_variant":[
        "Gryaznukha",
        "Zarechnaya"
    ],
    "wof:name":"Zarechnaya",
    "wof:placetype":"locality"
},
  "geometry": {"coordinates":[63.85389,55.58694000000001],"type":"Point"}
}