{
  "type": "Feature",
  "properties": {
    "gn:admin1_code":"37.0",
    "gn:asciiname":"Antonovskoye",
    "gn:country_code":"RU",
    "gn:dem":129,
    "gn:feature_class":"P",
    "gn:feature_code":"PPL",
    "gn:name":"Antonovskoye",
    "gn:population":0,
    "gn:timezone":"Europe/Moscow",
    "iso:country":"RU",
    "name:nor_x_preferred":[
        "Antonovskoje"
    ],
    "name:rus_x_preferred":[
        "\u0410\u043d\u0442\u043e\u043d\u043e\u0432\u0441\u043a\u043e\u0435"
    ],
    "wof:name":"Antonovskoye",
    "wof:placetype":"locality"
},
  "geometry": {"coordinates":[41.56302,57.46162],"type":"Point"}
}