{
  "type": "Feature",
  "properties": {
    "gn:admin1_code":"6.0",
    "gn:asciiname":"Ustreka",
    "gn:country_code":"RU",
    "gn:dem":10,
    "gn:feature_class":"P",
    "gn:feature_code":"PPL",
    "gn:name":"Ustreka",
    "gn:population":0,
    "gn:timezone":"Europe/Moscow",
    "iso:country":"RU",
    "name:rus_x_preferred":[
        "\u0423\u0441\u0442\u0440\u0435\u043a\u0430"
    ],
    "wof:name":"Ustreka",
    "wof:placetype":"locality"
},
  "geometry": {"coordinates":[41.9389,63.5569],"type":"Point"}
}