{
  "type": "Feature",
  "properties": {
    "gn:admin1_code":"80",
    "gn:asciiname":"Staryye Kopki",
    "gn:country_code":"RU",
    "gn:dem":154,
    "gn:feature_class":"P",
    "gn:feature_code":"PPL",
    "gn:name":"Staryye Kopki",
    "gn:population":0,
    "gn:timezone":"Europe/Samara",
    "iso:country":"RU",
    "name:rus_x_preferred":[
        "\u0421\u0442\u0430\u0440\u044b\u0435 \u041a\u043e\u043f\u043a\u0438"
    ],
    "name:und_x_variant":[
        "\u0421\u0442\u0430\u0440\u044b\u0435 \u041a\u043e\u043f\u043a\u0438"
    ],
    "wof:name":"Staryye Kopki",
    "wof:placetype":"locality"
},
  "geometry": {"coordinates":[51.63655,56.46109000000001],"type":"Point"}
}