{
  "type": "Feature",
  "properties": {
    "gn:admin1_code":"75",
    "gn:asciiname":"Stepanovka",
    "gn:country_code":"RU",
    "gn:dem":92,
    "gn:feature_class":"P",
    "gn:feature_code":"PPL",
    "gn:name":"Stepanovka",
    "gn:population":0,
    "gn:timezone":"Asia/Tomsk",
    "iso:country":"RU",
    "name:eng_x_preferred":[
        "Stepanovka"
    ],
    "name:nor_x_preferred":[
        "Stepanovka"
    ],
    "name:rus_x_preferred":[
        "\u0421\u0442\u0435\u043f\u0430\u043d\u043e\u0432\u043a\u0430"
    ],
    "wof:name":"Stepanovka",
    "wof:placetype":"locality"
},
  "geometry": {"coordinates":[86.76639,58.64306],"type":"Point"}
}