{
  "type": "Feature",
  "properties": {
    "gn:admin1_code":"88",
    "gn:asciiname":"Kovyrevo",
    "gn:country_code":"RU",
    "gn:dem":145,
    "gn:feature_class":"P",
    "gn:feature_code":"PPL",
    "gn:name":"Kovyr\u00ebvo",
    "gn:population":0,
    "gn:timezone":"Europe/Moscow",
    "iso:country":"RU",
    "name:rus_x_preferred":[
        "\u041a\u043e\u0432\u044b\u0440\u0451\u0432\u043e"
    ],
    "name:und_x_variant":[
        "Kovyr\u00ebvo"
    ],
    "wof:name":"Kovyrevo",
    "wof:placetype":"locality"
},
  "geometry": {"coordinates":[37.5071,57.791],"type":"Point"}
}