{
  "type": "Feature",
  "properties": {
    "gn:admin1_code":"83",
    "gn:asciiname":"Golovino",
    "gn:country_code":"RU",
    "gn:dem":155,
    "gn:feature_class":"P",
    "gn:feature_code":"PPL",
    "gn:name":"Golovino",
    "gn:population":0,
    "gn:timezone":"Europe/Moscow",
    "iso:country":"RU",
    "name:rus_x_preferred":[
        "\u0413\u043e\u043b\u043e\u0432\u0438\u043d\u043e"
    ],
    "name:und_x_variant":[
        "Pos\u00eblok Golovino",
        "Nizhniy Metiz",
        "Golovino",
        "\u0413\u043e\u043b\u043e\u0432\u0438\u043d\u043e"
    ],
    "wof:name":"Golovino",
    "wof:placetype":"locality"
},
  "geometry": {"coordinates":[40.44748,55.95255],"type":"Point"}
}