{
  "type": "Feature",
  "properties": {
    "gn:admin1_code":"46",
    "gn:asciiname":"Russkoye Yandovishche",
    "gn:country_code":"RU",
    "gn:dem":194,
    "gn:feature_class":"P",
    "gn:feature_code":"PPL",
    "gn:name":"Russkoye Yandovishche",
    "gn:population":0,
    "gn:timezone":"Europe/Moscow",
    "iso:country":"RU",
    "name:rus_x_preferred":[
        "\u0420\u0443\u0441\u0441\u043a\u043e\u0435 \u042f\u043d\u0434\u043e\u0432\u0438\u0449\u0435"
    ],
    "name:und_x_variant":[
        "\u0420\u0443\u0441\u0441\u043a\u043e\u0435 \u042f\u043d\u0434\u043e\u0432\u0438\u0449\u0435"
    ],
    "wof:name":"Russkoye Yandovishche",
    "wof:placetype":"locality"
},
  "geometry": {"coordinates":[44.3004,53.801],"type":"Point"}
}