{
  "type": "Feature",
  "properties": {
    "gn:admin1_code":"37.0",
    "gn:asciiname":"Arkhipino",
    "gn:country_code":"RU",
    "gn:dem":124,
    "gn:feature_class":"P",
    "gn:feature_code":"PPL",
    "gn:name":"Arkhipino",
    "gn:population":0,
    "gn:timezone":"Europe/Moscow",
    "iso:country":"RU",
    "name:nor_x_preferred":[
        "Arkhipino"
    ],
    "name:rus_x_preferred":[
        "\u0410\u0440\u0445\u0438\u043f\u0438\u043d\u043e"
    ],
    "wof:name":"Arkhipino",
    "wof:placetype":"locality"
},
  "geometry": {"coordinates":[41.41299,57.54809],"type":"Point"}
}