{
  "type": "Feature",
  "properties": {
    "gn:admin1_code":"66.0",
    "gn:asciiname":"Popovo",
    "gn:country_code":"RU",
    "gn:dem":56,
    "gn:feature_class":"P",
    "gn:feature_code":"PPL",
    "gn:name":"Popovo",
    "gn:population":0,
    "gn:timezone":"Europe/Moscow",
    "iso:country":"RU",
    "name:fin_x_preferred":[
        "Pappilanautio"
    ],
    "name:rus_x_preferred":[
        "\u041f\u043e\u043f\u043e\u0432\u043e"
    ],
    "name:und_x_variant":[
        "\u041f\u043e\u043f\u043e\u0432\u043e"
    ],
    "wof:name":"Popovo",
    "wof:placetype":"locality"
},
  "geometry": {"coordinates":[30.40363,59.66635],"type":"Point"}
}