{
  "type": "Feature",
  "properties": {
    "gn:admin1_code":"41",
    "gn:asciiname":"Lugovskoye",
    "gn:country_code":"RU",
    "gn:dem":187,
    "gn:feature_class":"P",
    "gn:feature_code":"PPL",
    "gn:name":"Lugovskoye",
    "gn:population":0,
    "gn:timezone":"Europe/Moscow",
    "iso:country":"RU",
    "name:rus_x_preferred":[
        "\u041b\u0443\u0433\u043e\u0432\u0441\u043a\u043e\u0435"
    ],
    "wof:name":"Lugovskoye",
    "wof:placetype":"locality"
},
  "geometry": {"coordinates":[37.2718,51.7781],"type":"Point"}
}