{
  "type": "Feature",
  "properties": {
    "gn:admin1_code":"21.0",
    "gn:asciiname":"Seminovo",
    "gn:country_code":"RU",
    "gn:dem":93,
    "gn:feature_class":"P",
    "gn:feature_code":"PPL",
    "gn:name":"Seminovo",
    "gn:population":0,
    "gn:timezone":"Europe/Moscow",
    "iso:country":"RU",
    "name:rus_x_preferred":[
        "\u0421\u0435\u043c\u0438\u043d\u043e\u0432\u043e"
    ],
    "wof:name":"Seminovo",
    "wof:placetype":"locality"
},
  "geometry": {"coordinates":[41.34461,56.91261],"type":"Point"}
}