{
  "type": "Feature",
  "properties": {
    "gn:admin1_code":"84",
    "gn:asciiname":"Makhinovskiy",
    "gn:country_code":"RU",
    "gn:dem":130,
    "gn:feature_class":"P",
    "gn:feature_code":"PPL",
    "gn:name":"Makhinovskiy",
    "gn:population":0,
    "gn:timezone":"Europe/Volgograd",
    "iso:country":"RU",
    "name:eng_x_preferred":[
        "Makhinovskiy"
    ],
    "name:nor_x_preferred":[
        "Makhinovskij"
    ],
    "name:rus_x_preferred":[
        "\u041c\u0430\u0445\u0438\u043d\u043e\u0432\u0441\u043a\u0438\u0439"
    ],
    "name:und_x_variant":[
        "\u041c\u0430\u0445\u0438\u043d\u043e\u0432\u0441\u043a\u0438\u0439",
        "Makhinovskiy"
    ],
    "wof:name":"Makhinovskiy",
    "wof:placetype":"locality"
},
  "geometry": {"coordinates":[43.1154,50.3857],"type":"Point"}
}