{
  "type": "Feature",
  "properties": {
    "gn:admin1_code":"21",
    "gn:asciiname":"Kharilovo",
    "gn:country_code":"RU",
    "gn:dem":149,
    "gn:feature_class":"P",
    "gn:feature_code":"PPL",
    "gn:name":"Kharilovo",
    "gn:population":0,
    "gn:timezone":"Europe/Moscow",
    "iso:country":"RU",
    "name:rus_x_preferred":[
        "\u0425\u0430\u0440\u0438\u043b\u043e\u0432\u043e"
    ],
    "wof:name":"Kharilovo",
    "wof:placetype":"locality"
},
  "geometry": {"coordinates":[40.08196,56.87886999999999],"type":"Point"}
}