{
  "type": "Feature",
  "properties": {
    "gn:admin1_code":"73",
    "gn:asciiname":"Oshtorma-Yum'ya",
    "gn:country_code":"RU",
    "gn:dem":121,
    "gn:feature_class":"P",
    "gn:feature_code":"PPL",
    "gn:name":"Oshtorma-Yum\u2019ya",
    "gn:population":0,
    "gn:timezone":"Europe/Moscow",
    "iso:country":"RU",
    "name:rus_x_preferred":[
        "\u041e\u0448\u0442\u043e\u0440\u043c\u0430-\u042e\u043c\u044c\u044f"
    ],
    "name:und_x_variant":[
        "Oshtorma-Yum\u2019ya"
    ],
    "wof:name":"Oshtorma-Yum'ya",
    "wof:placetype":"locality"
},
  "geometry": {"coordinates":[50.7327,56.1276],"type":"Point"}
}