{
  "type": "Feature",
  "properties": {
    "gn:admin1_code":"37.0",
    "gn:asciiname":"Bol'shaya Lipovitsa",
    "gn:country_code":"RU",
    "gn:dem":164,
    "gn:feature_class":"P",
    "gn:feature_code":"PPL",
    "gn:name":"Bol\u2019shaya Lipovitsa",
    "gn:population":0,
    "gn:timezone":"Europe/Moscow",
    "iso:country":"RU",
    "name:rus_x_preferred":[
        "\u0411\u043e\u043b\u044c\u0448\u0430\u044f \u041b\u0438\u043f\u043e\u0432\u0438\u0446\u0430"
    ],
    "name:und_x_variant":[
        "Bol\u2019shaya Lipovitsa",
        "\u0411\u043e\u043b\u044c\u0448\u0430\u044f \u041b\u0438\u043f\u043e\u0432\u0438\u0446\u0430"
    ],
    "wof:name":"Bol'shaya Lipovitsa",
    "wof:placetype":"locality"
},
  "geometry": {"coordinates":[44.28341,58.53854000000001],"type":"Point"}
}