{
  "type": "Feature",
  "properties": {
    "gn:admin1_code":"57",
    "gn:asciiname":"Pokrovo-Berezovka",
    "gn:country_code":"RU",
    "gn:dem":194,
    "gn:feature_class":"P",
    "gn:feature_code":"PPL",
    "gn:name":"Pokrovo-Ber\u00ebzovka",
    "gn:population":0,
    "gn:timezone":"Europe/Moscow",
    "iso:country":"RU",
    "name:eng_x_preferred":[
        "Pokrovo-Ber\u00ebzovka"
    ],
    "name:nor_x_preferred":[
        "Pokrovo-Berezovka"
    ],
    "name:rus_x_preferred":[
        "\u041f\u043e\u043a\u0440\u043e\u0432\u043e-\u0411\u0435\u0440\u0435\u0437\u043e\u0432\u043a\u0430"
    ],
    "name:rus_x_variant":[
        "\u041f\u043e\u043a\u0440\u043e\u0432\u043e-\u0411\u0435\u0440\u0451\u0437\u043e\u0432\u043a\u0430"
    ],
    "name:und_x_variant":[
        "Berezovka",
        "Pokrovo-Ber\u00ebzovka"
    ],
    "wof:name":"Pokrovo-Berezovka",
    "wof:placetype":"locality"
},
  "geometry": {"coordinates":[44.84457,52.76193000000001],"type":"Point"}
}