{
  "type": "Feature",
  "properties": {
    "gn:admin1_code":"21.0",
    "gn:asciiname":"Neupokoikha",
    "gn:country_code":"RU",
    "gn:dem":115,
    "gn:feature_class":"P",
    "gn:feature_code":"PPL",
    "gn:name":"Neupokoikha",
    "gn:population":0,
    "gn:timezone":"Europe/Moscow",
    "iso:country":"RU",
    "name:nor_x_preferred":[
        "Neupokoikha"
    ],
    "name:rus_x_preferred":[
        "\u041d\u0435\u0443\u043f\u043e\u043a\u043e\u0438\u0445\u0430"
    ],
    "wof:name":"Neupokoikha",
    "wof:placetype":"locality"
},
  "geometry": {"coordinates":[42.91407,56.97915],"type":"Point"}
}