{
  "type": "Feature",
  "properties": {
    "gn:admin1_code":"91",
    "gn:asciiname":"Novaya Dmitriyevka",
    "gn:country_code":"RU",
    "gn:dem":184,
    "gn:feature_class":"P",
    "gn:feature_code":"PPL",
    "gn:name":"Novaya Dmitriyevka",
    "gn:population":0,
    "gn:timezone":"Asia/Krasnoyarsk",
    "iso:country":"RU",
    "wof:name":"Novaya Dmitriyevka",
    "wof:placetype":"locality"
},
  "geometry": {"coordinates":[95.62333,56.98278000000001],"type":"Point"}
}