{
  "type": "Feature",
  "properties": {
    "gn:admin1_code":"77",
    "gn:asciiname":"Gubinka",
    "gn:country_code":"RU",
    "gn:dem":204,
    "gn:feature_class":"P",
    "gn:feature_code":"PPL",
    "gn:name":"Gubinka",
    "gn:population":0,
    "gn:timezone":"Europe/Moscow",
    "iso:country":"RU",
    "name:eng_x_preferred":[
        "Gubinka"
    ],
    "name:nor_x_preferred":[
        "Gubinka"
    ],
    "name:rus_x_preferred":[
        "\u0413\u0443\u0431\u0438\u043d\u043a\u0430"
    ],
    "name:und_x_variant":[
        "Gubinki"
    ],
    "wof:name":"Gubinka",
    "wof:placetype":"locality"
},
  "geometry": {"coordinates":[34.87207,56.09988000000001],"type":"Point"}
}