{
  "type": "Feature",
  "properties": {
    "gn:admin1_code":"60",
    "gn:asciiname":"Shishkino",
    "gn:country_code":"RU",
    "gn:dem":78,
    "gn:feature_class":"P",
    "gn:feature_code":"PPL",
    "gn:name":"Shishkino",
    "gn:population":0,
    "gn:timezone":"Europe/Moscow",
    "iso:country":"RU",
    "name:rus_x_preferred":[
        "\u0428\u0438\u0448\u043a\u0438\u043d\u043e"
    ],
    "wof:name":"Shishkino",
    "wof:placetype":"locality"
},
  "geometry": {"coordinates":[28.62998,56.88185],"type":"Point"}
}