{
  "type": "Feature",
  "properties": {
    "gn:admin1_code":"65.0",
    "gn:asciiname":"Iyerusalimskiy",
    "gn:country_code":"RU",
    "gn:dem":94,
    "gn:feature_class":"P",
    "gn:feature_code":"PPL",
    "gn:name":"Iyerusalimskiy",
    "gn:population":0,
    "gn:timezone":"Europe/Samara",
    "iso:country":"RU",
    "name:rus_x_preferred":[
        "\u0418\u0435\u0440\u0443\u0441\u0430\u043b\u0438\u043c\u0441\u043a\u0438\u0439"
    ],
    "name:und_x_variant":[
        "Ierusalimskiy",
        "Dachnyy"
    ],
    "wof:name":"Iyerusalimskiy",
    "wof:placetype":"locality"
},
  "geometry": {"coordinates":[49.3239,52.793],"type":"Point"}
}