{
  "type": "Feature",
  "properties": {
    "gn:admin1_code":"7",
    "gn:asciiname":"Trekhizbenka",
    "gn:country_code":"RU",
    "gn:dem":-26,
    "gn:feature_class":"P",
    "gn:feature_code":"PPL",
    "gn:name":"Tr\u00ebkhizbenka",
    "gn:population":0,
    "gn:timezone":"Europe/Astrakhan",
    "iso:country":"RU",
    "name:rus_x_preferred":[
        "\u0422\u0440\u0451\u0445\u0438\u0437\u0431\u0435\u043d\u043a\u0430"
    ],
    "name:und_x_variant":[
        "Verkhnyaya Tr\u00ebkhizbyanka",
        "Verkhnyaya Tr\u00ebkh-Izbenka",
        "Tr\u00ebkhizbenka"
    ],
    "wof:name":"Trekhizbenka",
    "wof:placetype":"locality"
},
  "geometry": {"coordinates":[48.35677,46.15475],"type":"Point"}
}