{
  "type": "Feature",
  "properties": {
    "gn:admin1_code":"8",
    "gn:asciiname":"Simkino",
    "gn:country_code":"RU",
    "gn:dem":101,
    "gn:feature_class":"P",
    "gn:feature_code":"PPL",
    "gn:name":"Simkino",
    "gn:population":0,
    "gn:timezone":"Asia/Yekaterinburg",
    "iso:country":"RU",
    "name:bak_x_preferred":[
        "\u0421\u0438\u043c\u043a\u04d9"
    ],
    "name:che_x_preferred":[
        "\u0421\u0438\u043c\u043a\u0438\u043d\u043e"
    ],
    "name:hye_x_preferred":[
        "\u054d\u056b\u0574\u056f\u056b\u0576\u0578"
    ],
    "name:kaz_x_preferred":[
        "\u0421\u0438\u043c\u043a\u0438\u043d\u043e"
    ],
    "name:kir_x_preferred":[
        "\u0421\u0438\u043c\u043a\u0438\u043d\u043e"
    ],
    "name:rus_x_preferred":[
        "\u0421\u0438\u043c\u043a\u0438\u043d\u043e"
    ],
    "name:tat_x_preferred":[
        "\u0421\u0438\u043c\u043a\u04d9"
    ],
    "wof:name":"Simkino",
    "wof:placetype":"locality"
},
  "geometry": {"coordinates":[55.63889,55.24722],"type":"Point"}
}