{
  "type": "Feature",
  "properties": {
    "gn:admin1_code":"20",
    "gn:asciiname":"Muksut",
    "gn:country_code":"RU",
    "gn:dem":496,
    "gn:feature_class":"P",
    "gn:feature_code":"PPL",
    "gn:name":"Muksut",
    "gn:population":0,
    "gn:timezone":"Asia/Irkutsk",
    "iso:country":"RU",
    "name:rus_x_preferred":[
        "\u041c\u0443\u043a\u0441\u0443\u0442"
    ],
    "wof:name":"Muksut",
    "wof:placetype":"locality"
},
  "geometry": {"coordinates":[98.97329999999999,54.8446],"type":"Point"}
}