{
  "type": "Feature",
  "properties": {
    "gn:admin1_code":"28",
    "gn:asciiname":"Peryamaya",
    "gn:cc2":"RU",
    "gn:country_code":"RU",
    "gn:dem":8,
    "gn:feature_class":"P",
    "gn:feature_code":"PPL",
    "gn:name":"Peryamaya",
    "gn:population":0,
    "gn:timezone":"Europe/Moscow",
    "iso:country":"RU",
    "name:fin_x_preferred":[
        "Per\u00e4maa"
    ],
    "name:rus_x_preferred":[
        "\u041f\u0435\u0440\u044f\u043c\u0430\u044f"
    ],
    "name:und_x_variant":[
        "Peryamaa",
        "Peryamaya"
    ],
    "wof:name":"Peryamaya",
    "wof:placetype":"locality"
},
  "geometry": {"coordinates":[31.86241,61.32036],"type":"Point"}
}