{
  "type": "Feature",
  "properties": {
    "gn:admin1_code":"77",
    "gn:asciiname":"Terekhovo",
    "gn:country_code":"RU",
    "gn:dem":181,
    "gn:feature_class":"P",
    "gn:feature_code":"PPL",
    "gn:name":"Terekhovo",
    "gn:population":0,
    "gn:timezone":"Europe/Moscow",
    "iso:country":"RU",
    "name:und_x_variant":[
        "Terechovo",
        "Terekhovo"
    ],
    "wof:name":"Terekhovo",
    "wof:placetype":"locality"
},
  "geometry": {"coordinates":[31.65606,56.1684],"type":"Point"}
}