{
  "type": "Feature",
  "properties": {
    "gn:admin1_code":"38.0",
    "gn:asciiname":"Pilenkovo",
    "gn:country_code":"RU",
    "gn:dem":64,
    "gn:feature_class":"P",
    "gn:feature_code":"PPL",
    "gn:name":"Pilenkovo",
    "gn:population":0,
    "gn:timezone":"Europe/Moscow",
    "iso:country":"RU",
    "wof:name":"Pilenkovo",
    "wof:placetype":"locality"
},
  "geometry": {"coordinates":[37.40028,45.11444],"type":"Point"}
}