{
  "type": "Feature",
  "properties": {
    "gn:admin1_code":"52",
    "gn:asciiname":"Ust'ye-Kirovskiy Zavod",
    "gn:country_code":"RU",
    "gn:dem":127,
    "gn:feature_class":"P",
    "gn:feature_code":"PPL",
    "gn:name":"Ust\u2019ye-Kirovskiy Zavod",
    "gn:population":0,
    "gn:timezone":"Europe/Moscow",
    "iso:country":"RU",
    "wof:name":"Ust'ye-Kirovskiy Zavod",
    "wof:placetype":"locality"
},
  "geometry": {"coordinates":[35.86667,58.75],"type":"Point"}
}