{
  "type": "Feature",
  "properties": {
    "gn:admin1_code":"47",
    "gn:asciiname":"Zorino",
    "gn:country_code":"RU",
    "gn:dem":211,
    "gn:feature_class":"P",
    "gn:feature_code":"PPL",
    "gn:name":"Zorino",
    "gn:population":0,
    "gn:timezone":"Europe/Moscow",
    "iso:country":"RU",
    "name:rus_x_preferred":[
        "\u0417\u043e\u0440\u0438\u043d\u043e"
    ],
    "wof:name":"Zorino",
    "wof:placetype":"locality"
},
  "geometry": {"coordinates":[36.7219,56.0082],"type":"Point"}
}