{
  "type": "Feature",
  "properties": {
    "gn:admin1_code":"69",
    "gn:asciiname":"Beli",
    "gn:country_code":"RU",
    "gn:dem":236,
    "gn:feature_class":"P",
    "gn:feature_code":"PPL",
    "gn:name":"Beli",
    "gn:population":0,
    "gn:timezone":"Europe/Moscow",
    "iso:country":"RU",
    "name:cat_x_preferred":[
        "Beli"
    ],
    "name:ceb_x_preferred":[
        "Beli"
    ],
    "name:cym_x_preferred":[
        "Beli"
    ],
    "name:deu_x_preferred":[
        "Beli"
    ],
    "name:fra_x_preferred":[
        "Beli"
    ],
    "name:ita_x_preferred":[
        "Beli"
    ],
    "name:nld_x_preferred":[
        "Beli"
    ],
    "name:rus_x_preferred":[
        "\u0411\u0435\u043b\u0438"
    ],
    "name:slv_x_preferred":[
        "Beli"
    ],
    "name:sqi_x_preferred":[
        "Beli"
    ],
    "name:srp_x_preferred":[
        "\u0411\u0435\u043b\u0438"
    ],
    "name:swe_x_preferred":[
        "Beli"
    ],
    "wof:name":"Beli",
    "wof:placetype":"locality"
},
  "geometry": {"coordinates":[34.64578,55.38709],"type":"Point"}
}