{
  "type": "Feature",
  "properties": {
    "gn:admin1_code":"88",
    "gn:asciiname":"Dubrovo",
    "gn:country_code":"RU",
    "gn:dem":97,
    "gn:feature_class":"P",
    "gn:feature_code":"PPL",
    "gn:name":"Dubrovo",
    "gn:population":0,
    "gn:timezone":"Europe/Moscow",
    "iso:country":"RU",
    "name:che_x_preferred":[
        "\u0414\u0443\u0431\u0440\u043e\u0432\u043e"
    ],
    "name:rus_x_preferred":[
        "\u0414\u0443\u0431\u0440\u043e\u0432\u043e"
    ],
    "wof:name":"Dubrovo",
    "wof:placetype":"locality"
},
  "geometry": {"coordinates":[39.53896,57.21146],"type":"Point"}
}