{
  "type": "Feature",
  "properties": {
    "gn:admin1_code":"49",
    "gn:asciiname":"Munozero",
    "gn:country_code":"RU",
    "gn:dem":130,
    "gn:feature_class":"P",
    "gn:feature_code":"PPL",
    "gn:name":"Munozero",
    "gn:population":0,
    "gn:timezone":"Europe/Moscow",
    "iso:country":"RU",
    "name:rus_x_preferred":[
        "\u041c\u0443\u043d\u043e\u0437\u0435\u0440\u043e"
    ],
    "wof:name":"Munozero",
    "wof:placetype":"locality"
},
  "geometry": {"coordinates":[34.67212,67.07015],"type":"Point"}
}