{
  "type": "Feature",
  "properties": {
    "gn:admin1_code":"67",
    "gn:asciiname":"Kubanka",
    "gn:country_code":"RU",
    "gn:dem":29,
    "gn:feature_class":"P",
    "gn:feature_code":"PPL",
    "gn:name":"Kubanka",
    "gn:population":0,
    "gn:timezone":"Europe/Saratov",
    "iso:country":"RU",
    "name:eng_x_preferred":[
        "Kubanka"
    ],
    "name:nor_x_preferred":[
        "Kubanka"
    ],
    "name:rus_x_preferred":[
        "\u041a\u0443\u0431\u0430\u043d\u043a\u0430"
    ],
    "name:und_x_variant":[
        "Kubaina",
        "\u041a\u0443\u0431\u0430\u043d\u043a\u0430",
        "Kubanka"
    ],
    "wof:name":"Kubanka",
    "wof:placetype":"locality"
},
  "geometry": {"coordinates":[48.01345,50.58801],"type":"Point"}
}