{
  "type": "Feature",
  "properties": {
    "gn:admin1_code":"90",
    "gn:asciiname":"Khmelevka",
    "gn:country_code":"RU",
    "gn:dem":173,
    "gn:feature_class":"P",
    "gn:feature_code":"PPL",
    "gn:name":"Khmel\u00ebvka",
    "gn:population":0,
    "gn:timezone":"Asia/Yekaterinburg",
    "iso:country":"RU",
    "name:rus_x_preferred":[
        "\u0425\u043c\u0435\u043b\u00eb\u0432\u043a\u0430"
    ],
    "name:rus_x_variant":[
        "Khmel\u00ebvka"
    ],
    "wof:name":"Khmelevka",
    "wof:placetype":"locality"
},
  "geometry": {"coordinates":[56.5342,57.5726],"type":"Point"}
}