{
  "type": "Feature",
  "properties": {
    "gn:admin1_code":"37",
    "gn:asciiname":"Staroye Samylovo",
    "gn:country_code":"RU",
    "gn:dem":159,
    "gn:feature_class":"P",
    "gn:feature_code":"PPL",
    "gn:name":"Staroye Samylovo",
    "gn:population":0,
    "gn:timezone":"Europe/Moscow",
    "iso:country":"RU",
    "name:rus_x_preferred":[
        "\u0421\u0442\u0430\u0440\u043e\u0435 \u0421\u0430\u043c\u044b\u043b\u043e\u0432\u043e"
    ],
    "wof:name":"Staroye Samylovo",
    "wof:placetype":"locality"
},
  "geometry": {"coordinates":[42.4052,58.9182],"type":"Point"}
}