{
  "type": "Feature",
  "properties": {
    "gn:admin1_code":"19.0",
    "gn:asciiname":"Dattykh",
    "gn:country_code":"RU",
    "gn:dem":641,
    "gn:feature_class":"P",
    "gn:feature_code":"PPL",
    "gn:name":"Dattykh",
    "gn:population":0,
    "gn:timezone":"Europe/Moscow",
    "iso:country":"RU",
    "name:eng_x_preferred":[
        "Dattykh"
    ],
    "name:nor_x_preferred":[
        "Dattykh"
    ],
    "name:rus_x_preferred":[
        "\u0414\u0430\u0442\u0442\u044b\u0445"
    ],
    "name:und_x_variant":[
        "Klyuchevoye"
    ],
    "wof:name":"Dattykh",
    "wof:placetype":"locality"
},
  "geometry": {"coordinates":[45.10039,43.02942],"type":"Point"}
}