{
  "type": "Feature",
  "properties": {
    "gn:admin1_code":"42",
    "gn:asciiname":"Pakhomovka",
    "gn:country_code":"RU",
    "gn:dem":107,
    "gn:feature_class":"P",
    "gn:feature_code":"PPL",
    "gn:name":"Pakhomovka",
    "gn:population":0,
    "gn:timezone":"Europe/Moscow",
    "iso:country":"RU",
    "name:fin_x_preferred":[
        "Venakontsa"
    ],
    "name:rus_x_preferred":[
        "\u041f\u0430\u0445\u043e\u043c\u043e\u0432\u043a\u0430"
    ],
    "name:und_x_variant":[
        "\u041f\u0430\u0445\u043e\u043c\u043e\u0432\u043a\u0430"
    ],
    "wof:name":"Pakhomovka",
    "wof:placetype":"locality"
},
  "geometry": {"coordinates":[28.51105,59.75986999999999],"type":"Point"}
}