{
  "type": "Feature",
  "properties": {
    "gn:admin1_code":"37",
    "gn:asciiname":"Kortyug",
    "gn:country_code":"RU",
    "gn:dem":172,
    "gn:feature_class":"P",
    "gn:feature_code":"PPL",
    "gn:name":"Kortyug",
    "gn:population":0,
    "gn:timezone":"Europe/Moscow",
    "iso:country":"RU",
    "name:rus_x_preferred":[
        "\u041a\u043e\u0440\u0442\u044e\u0433"
    ],
    "name:und_x_variant":[
        "\u041a\u043e\u0440\u0442\u044e\u0433"
    ],
    "wof:name":"Kortyug",
    "wof:placetype":"locality"
},
  "geometry": {"coordinates":[46.0998,59.1434],"type":"Point"}
}