{
  "type": "Feature",
  "properties": {
    "gn:admin1_code":"9",
    "gn:asciiname":"Grushevskiy",
    "gn:country_code":"RU",
    "gn:dem":197,
    "gn:feature_class":"P",
    "gn:feature_code":"PPL",
    "gn:name":"Grushevskiy",
    "gn:population":0,
    "gn:timezone":"Europe/Moscow",
    "iso:country":"RU",
    "name:rus_x_preferred":[
        "\u0413\u0440\u0443\u0448\u0435\u0432\u0441\u043a\u0438\u0439"
    ],
    "name:und_x_variant":[
        "Grushevskaya",
        "Grushevskiy"
    ],
    "wof:name":"Grushevskiy",
    "wof:placetype":"locality"
},
  "geometry": {"coordinates":[37.6197,50.4324],"type":"Point"}
}