{
  "type": "Feature",
  "properties": {
    "gn:admin1_code":"10",
    "gn:asciiname":"Kol'tsovka",
    "gn:country_code":"RU",
    "gn:dem":172,
    "gn:feature_class":"P",
    "gn:feature_code":"PPL",
    "gn:name":"Kol\u2019tsovka",
    "gn:population":0,
    "gn:timezone":"Europe/Moscow",
    "iso:country":"RU",
    "name:rus_x_preferred":[
        "\u041a\u043e\u043b\u044c\u0446\u043e\u0432\u043a\u0430"
    ],
    "name:und_x_variant":[
        "Kol\u2019tsovka",
        "\u041a\u043e\u043b\u044c\u0446\u043e\u0432\u043a\u0430"
    ],
    "wof:name":"Kol'tsovka",
    "wof:placetype":"locality"
},
  "geometry": {"coordinates":[34.47742,53.03271],"type":"Point"}
}