{
  "type": "Feature",
  "properties": {
    "gn:admin1_code":"47",
    "gn:asciiname":"Sipyagino",
    "gn:country_code":"RU",
    "gn:dem":191,
    "gn:feature_class":"P",
    "gn:feature_code":"PPL",
    "gn:name":"Sipyagino",
    "gn:population":0,
    "gn:timezone":"Europe/Moscow",
    "iso:country":"RU",
    "name:rus_x_preferred":[
        "\u0421\u0438\u043f\u044f\u0433\u0438\u043d\u043e"
    ],
    "name:und_x_variant":[
        "\u0421\u0438\u043f\u044f\u0433\u0438\u043d\u043e"
    ],
    "wof:name":"Sipyagino",
    "wof:placetype":"locality"
},
  "geometry": {"coordinates":[37.08575,55.37818000000001],"type":"Point"}
}