{
  "type": "Feature",
  "properties": {
    "gn:admin1_code":"25",
    "gn:asciiname":"Kuz'menki",
    "gn:country_code":"RU",
    "gn:dem":181,
    "gn:feature_class":"P",
    "gn:feature_code":"PPL",
    "gn:name":"Kuz\u2019menki",
    "gn:population":0,
    "gn:timezone":"Europe/Moscow",
    "iso:country":"RU",
    "name:rus_x_preferred":[
        "\u041a\u0443\u0437\u044c\u043c\u0435\u043d\u043a\u0438"
    ],
    "name:und_x_variant":[
        "Kuz\u2019menki"
    ],
    "wof:name":"Kuz'menki",
    "wof:placetype":"locality"
},
  "geometry": {"coordinates":[35.97778,54.31611],"type":"Point"}
}