{
  "type": "Feature",
  "properties": {
    "gn:admin1_code":"60",
    "gn:asciiname":"Grechukhi",
    "gn:country_code":"RU",
    "gn:dem":167,
    "gn:feature_class":"P",
    "gn:feature_code":"PPL",
    "gn:name":"Grechukhi",
    "gn:population":0,
    "gn:timezone":"Europe/Moscow",
    "iso:country":"RU",
    "name:rus_x_preferred":[
        "\u0413\u0440\u0435\u0447\u0443\u0445\u0438"
    ],
    "name:und_x_variant":[
        "\u0413\u0440\u0435\u0447\u0443\u0445\u0438"
    ],
    "wof:name":"Grechukhi",
    "wof:placetype":"locality"
},
  "geometry": {"coordinates":[29.1655,56.1349],"type":"Point"}
}