{
  "type": "Feature",
  "properties": {
    "gn:admin1_code":"8",
    "gn:asciiname":"Istrikovo",
    "gn:country_code":"RU",
    "gn:dem":105,
    "gn:feature_class":"P",
    "gn:feature_code":"PPL",
    "gn:name":"Istrikovo",
    "gn:population":0,
    "gn:timezone":"Asia/Yekaterinburg",
    "iso:country":"RU",
    "name:rus_x_preferred":[
        "\u0418\u0441\u0442\u0440\u0438\u043a\u043e\u0432\u043e"
    ],
    "name:und_x_variant":[
        "Istrikova",
        "Istrikovo"
    ],
    "wof:name":"Istrikovo",
    "wof:placetype":"locality"
},
  "geometry": {"coordinates":[56.48786,55.05074000000001],"type":"Point"}
}