{
  "type": "Feature",
  "properties": {
    "gn:admin1_code":"60",
    "gn:asciiname":"Gvozdovo",
    "gn:country_code":"RU",
    "gn:dem":116,
    "gn:feature_class":"P",
    "gn:feature_code":"PPL",
    "gn:name":"Gvozdovo",
    "gn:population":0,
    "gn:timezone":"Europe/Moscow",
    "iso:country":"RU",
    "name:rus_x_preferred":[
        "\u0413\u0432\u043e\u0437\u0434\u043e\u0432\u043e"
    ],
    "name:und_x_variant":[
        "Gvozdova",
        "Gvozdovo",
        "\u0413\u0432\u043e\u0437\u0434\u043e\u0432\u043e"
    ],
    "wof:name":"Gvozdovo",
    "wof:placetype":"locality"
},
  "geometry": {"coordinates":[30.27311,56.413],"type":"Point"}
}