{
  "type": "Feature",
  "properties": {
    "gn:admin1_code":"84",
    "gn:asciiname":"Karazhenskiy",
    "gn:country_code":"RU",
    "gn:dem":51,
    "gn:feature_class":"P",
    "gn:feature_code":"PPL",
    "gn:name":"Karazhenskiy",
    "gn:population":0,
    "gn:timezone":"Europe/Volgograd",
    "iso:country":"RU",
    "name:rus_x_preferred":[
        "\u041a\u0430\u0440\u0430\u0436\u0435\u043d\u0441\u043a\u0438\u0439"
    ],
    "wof:name":"Karazhenskiy",
    "wof:placetype":"locality"
},
  "geometry": {"coordinates":[43.02376,49.33892],"type":"Point"}
}