{
  "type": "Feature",
  "properties": {
    "gn:admin1_code":"73",
    "gn:asciiname":"Naberezhnyye Morkvashi",
    "gn:country_code":"RU",
    "gn:dem":67,
    "gn:feature_class":"P",
    "gn:feature_code":"PPL",
    "gn:name":"Naberezhnyye Morkvashi",
    "gn:population":0,
    "gn:timezone":"Europe/Moscow",
    "iso:country":"RU",
    "name:rus_x_preferred":[
        "\u041d\u0430\u0431\u0435\u0440\u0435\u0436\u043d\u044b\u0435 \u041c\u043e\u0440\u043a\u0432\u0430\u0448\u0438"
    ],
    "name:und_x_variant":[
        "Naberezhnyye Markvashi",
        "Markvashi",
        "Naberezhnyye Morkvashi",
        "\u041d\u0430\u0431\u0435\u0440\u0435\u0436\u043d\u044b\u0435 \u041c\u043e\u0440\u043a\u0432\u0430\u0448\u0438"
    ],
    "wof:name":"Naberezhnyye Morkvashi",
    "wof:placetype":"locality"
},
  "geometry": {"coordinates":[48.8509,55.7735],"type":"Point"}
}