{
  "type": "Feature",
  "properties": {
    "gn:admin1_code":"69",
    "gn:asciiname":"Kukharevo",
    "gn:country_code":"RU",
    "gn:dem":215,
    "gn:feature_class":"P",
    "gn:feature_code":"PPL",
    "gn:name":"Kukharevo",
    "gn:population":0,
    "gn:timezone":"Europe/Moscow",
    "iso:country":"RU",
    "name:rus_x_preferred":[
        "\u041a\u0443\u0445\u0430\u0440\u0435\u0432\u043e"
    ],
    "name:und_x_variant":[
        "\u041a\u0443\u0445\u0430\u0440\u0435\u0432\u043e"
    ],
    "wof:name":"Kukharevo",
    "wof:placetype":"locality"
},
  "geometry": {"coordinates":[32.76722,53.93806],"type":"Point"}
}