{
  "type": "Feature",
  "properties": {
    "gn:admin1_code":"31",
    "gn:asciiname":"Ust'-Khoiza",
    "gn:country_code":"RU",
    "gn:dem":642,
    "gn:feature_class":"P",
    "gn:feature_code":"PPL",
    "gn:name":"Ust\u2019-Khoiza",
    "gn:population":0,
    "gn:timezone":"Asia/Krasnoyarsk",
    "iso:country":"RU",
    "name:eng_x_preferred":[
        "Ust'-Khoiza"
    ],
    "name:nor_x_preferred":[
        "Ust-Khojza"
    ],
    "name:rus_x_preferred":[
        "\u0423\u0441\u0442\u044c-\u0425\u043e\u0439\u0437\u0430"
    ],
    "name:und_x_variant":[
        "Skotovod",
        "Ust\u2019-Khoiza"
    ],
    "wof:name":"Ust'-Khoiza",
    "wof:placetype":"locality"
},
  "geometry": {"coordinates":[89.91398000000002,53.13468],"type":"Point"}
}