{
  "type": "Feature",
  "properties": {
    "gn:admin1_code":"3",
    "gn:asciiname":"Put' Altaya",
    "gn:country_code":"RU",
    "gn:dem":1015,
    "gn:feature_class":"P",
    "gn:feature_code":"PPL",
    "gn:name":"Put\u2019 Altaya",
    "gn:population":0,
    "gn:timezone":"Asia/Omsk",
    "iso:country":"RU",
    "name:rus_x_preferred":[
        "\u041f\u0443\u0442\u044c \u0410\u043b\u0442\u0430\u044f"
    ],
    "name:und_x_variant":[
        "Put\u2019 Altaya",
        "\u041f\u0443\u0442\u044c \u0410\u043b\u0442\u0430\u044f"
    ],
    "wof:name":"Put' Altaya",
    "wof:placetype":"locality"
},
  "geometry": {"coordinates":[85.68333,51.36667],"type":"Point"}
}