{
  "type": "Feature",
  "properties": {
    "gn:admin1_code":"61",
    "gn:asciiname":"Pichugin",
    "gn:country_code":"RU",
    "gn:dem":82,
    "gn:feature_class":"P",
    "gn:feature_code":"PPL",
    "gn:name":"Pichugin",
    "gn:population":0,
    "gn:timezone":"Europe/Moscow",
    "iso:country":"RU",
    "name:deu_x_preferred":[
        "Pitschugin"
    ],
    "name:rus_x_preferred":[
        "\u041f\u0438\u0447\u0443\u0433\u0438\u043d"
    ],
    "name:slv_x_preferred":[
        "Pi\u010dugin"
    ],
    "name:ukr_x_preferred":[
        "\u041f\u0456\u0447\u0443\u0433\u0456\u043d"
    ],
    "wof:name":"Pichugin",
    "wof:placetype":"locality"
},
  "geometry": {"coordinates":[42.093,49.12561],"type":"Point"}
}