{
  "type": "Feature",
  "properties": {
    "gn:admin1_code":"60",
    "gn:asciiname":"Volkovo Vtoroye",
    "gn:country_code":"RU",
    "gn:dem":116,
    "gn:feature_class":"P",
    "gn:feature_code":"PPL",
    "gn:name":"Volkovo Vtoroye",
    "gn:population":0,
    "gn:timezone":"Europe/Moscow",
    "iso:country":"RU",
    "wof:name":"Volkovo Vtoroye",
    "wof:placetype":"locality"
},
  "geometry": {"coordinates":[30.65,56.46666999999999],"type":"Point"}
}