{
  "type": "Feature",
  "properties": {
    "gn:admin1_code":"30",
    "gn:asciiname":"Kharpichan",
    "gn:country_code":"RU",
    "gn:dem":94,
    "gn:feature_class":"P",
    "gn:feature_code":"PPL",
    "gn:name":"Kharpichan",
    "gn:population":0,
    "gn:timezone":"Asia/Vladivostok",
    "iso:country":"RU",
    "name:eng_x_preferred":[
        "Kharpichan"
    ],
    "name:nor_x_preferred":[
        "Kharpitsjan"
    ],
    "name:rus_x_preferred":[
        "\u0425\u0430\u0440\u043f\u0438\u0447\u0430\u043d"
    ],
    "wof:name":"Kharpichan",
    "wof:placetype":"locality"
},
  "geometry": {"coordinates":[136.52611000000002,51.29633],"type":"Point"}
}