{
  "type": "Feature",
  "properties": {
    "gn:admin1_code":"47.0",
    "gn:asciiname":"Buturlino",
    "gn:country_code":"RU",
    "gn:dem":124,
    "gn:feature_class":"P",
    "gn:feature_code":"PPL",
    "gn:name":"Buturlino",
    "gn:population":0,
    "gn:timezone":"Europe/Moscow",
    "iso:country":"RU",
    "name:eng_x_preferred":[
        "Buturlino"
    ],
    "name:nor_x_preferred":[
        "Buturlino"
    ],
    "name:rus_x_preferred":[
        "\u0411\u0443\u0442\u0443\u0440\u043b\u0438\u043d\u043e"
    ],
    "name:und_x_variant":[
        "Baturlino"
    ],
    "wof:name":"Buturlino",
    "wof:placetype":"locality"
},
  "geometry": {"coordinates":[37.48174,54.92777],"type":"Point"}
}