{
  "type": "Feature",
  "properties": {
    "gn:admin1_code":"84",
    "gn:asciiname":"Kukhtinskiy",
    "gn:country_code":"RU",
    "gn:dem":137,
    "gn:feature_class":"P",
    "gn:feature_code":"PPL",
    "gn:name":"Kukhtinskiy",
    "gn:population":0,
    "gn:timezone":"Europe/Volgograd",
    "iso:country":"RU",
    "name:rus_x_preferred":[
        "\u041a\u0443\u0445\u0442\u0438\u043d\u0441\u043a\u0438\u0439"
    ],
    "wof:name":"Kukhtinskiy",
    "wof:placetype":"locality"
},
  "geometry": {"coordinates":[42.2753,50.8162],"type":"Point"}
}