{
  "type": "Feature",
  "properties": {
    "gn:admin1_code":"42",
    "gn:asciiname":"Pereles'ye",
    "gn:country_code":"RU",
    "gn:dem":122,
    "gn:feature_class":"P",
    "gn:feature_code":"PPL",
    "gn:name":"Pereles\u2019ye",
    "gn:population":0,
    "gn:timezone":"Europe/Moscow",
    "iso:country":"RU",
    "name:fin_x_preferred":[
        "Perliisil\u00e4"
    ],
    "name:rus_x_preferred":[
        "\u041f\u0435\u0440\u0435\u043b\u0435\u0441\u044c\u0435"
    ],
    "name:und_x_variant":[
        "Pereles\u2019ye",
        "\u041f\u0435\u0440\u0435\u043b\u0435\u0441\u044c\u0435"
    ],
    "wof:name":"Pereles'ye",
    "wof:placetype":"locality"
},
  "geometry": {"coordinates":[29.55786,59.75415],"type":"Point"}
}