{
  "type": "Feature",
  "properties": {
    "gn:admin1_code":"52",
    "gn:asciiname":"Kir'kovo",
    "gn:country_code":"RU",
    "gn:dem":69,
    "gn:feature_class":"P",
    "gn:feature_code":"PPL",
    "gn:name":"Kir\u2019kovo",
    "gn:population":0,
    "gn:timezone":"Europe/Moscow",
    "iso:country":"RU",
    "name:rus_x_preferred":[
        "\u041a\u0438\u0440\u044c\u043a\u043e\u0432\u043e"
    ],
    "name:und_x_variant":[
        "Kir\u2019kovo",
        "\u041a\u0438\u0440\u044c\u043a\u043e\u0432\u043e"
    ],
    "wof:name":"Kir'kovo",
    "wof:placetype":"locality"
},
  "geometry": {"coordinates":[31.5499,57.4408],"type":"Point"}
}