{
  "type": "Feature",
  "properties": {
    "gn:admin1_code":"73",
    "gn:asciiname":"Zabugorovka",
    "gn:country_code":"RU",
    "gn:dem":303,
    "gn:feature_class":"P",
    "gn:feature_code":"PPL",
    "gn:name":"Zabugorovka",
    "gn:population":0,
    "gn:timezone":"Europe/Moscow",
    "iso:country":"RU",
    "name:eng_x_preferred":[
        "Zabugrovka"
    ],
    "name:nor_x_preferred":[
        "Zabugorovka"
    ],
    "name:rus_x_preferred":[
        "\u0417\u0430\u0431\u0443\u0433\u043e\u0440\u043e\u0432\u043a\u0430"
    ],
    "name:und_x_variant":[
        "Zabugrovka",
        "\u0417\u0430\u0431\u0443\u0433\u043e\u0440\u043e\u0432\u043a\u0430"
    ],
    "wof:name":"Zabugorovka",
    "wof:placetype":"locality"
},
  "geometry": {"coordinates":[52.786,54.50335],"type":"Point"}
}