{
  "type": "Feature",
  "properties": {
    "gn:admin1_code":"8.0",
    "gn:asciiname":"Sukholyad",
    "gn:country_code":"RU",
    "gn:dem":567,
    "gn:feature_class":"P",
    "gn:feature_code":"PPL",
    "gn:name":"Sukholyad",
    "gn:population":0,
    "gn:timezone":"Asia/Yekaterinburg",
    "iso:country":"RU",
    "name:rus_x_preferred":[
        "\u0421\u0443\u0445\u043e\u043b\u044f\u0434"
    ],
    "wof:name":"Sukholyad",
    "wof:placetype":"locality"
},
  "geometry": {"coordinates":[57.9367,53.6108],"type":"Point"}
}