{
  "type": "Feature",
  "properties": {
    "gn:admin1_code":"59.0",
    "gn:asciiname":"Elitnoye",
    "gn:country_code":"RU",
    "gn:dem":65,
    "gn:feature_class":"P",
    "gn:feature_code":"PPL",
    "gn:name":"Elitnoye",
    "gn:population":0,
    "gn:timezone":"Asia/Vladivostok",
    "iso:country":"RU",
    "name:rus_x_preferred":[
        "\u042d\u043b\u0438\u0442\u043d\u043e\u0435"
    ],
    "wof:name":"Elitnoye",
    "wof:placetype":"locality"
},
  "geometry": {"coordinates":[131.76419999999999,43.95994],"type":"Point"}
}