{
  "type": "Feature",
  "properties": {
    "gn:admin1_code":"63",
    "gn:asciiname":"Kameshkovo",
    "gn:country_code":"RU",
    "gn:dem":6,
    "gn:feature_class":"P",
    "gn:feature_code":"PPL",
    "gn:name":"Kameshkovo",
    "gn:population":0,
    "gn:timezone":"Asia/Magadan",
    "iso:country":"RU",
    "name:rus_x_preferred":[
        "\u041a\u0430\u043c\u0435\u0448\u043a\u043e\u0432\u043e"
    ],
    "name:und_x_variant":[
        "\u041a\u0430\u043c\u0435\u0448\u043a\u043e\u0432\u043e"
    ],
    "wof:name":"Kameshkovo",
    "wof:placetype":"locality"
},
  "geometry": {"coordinates":[147.41666999999995,70.03333000000001],"type":"Point"}
}