{
  "type": "Feature",
  "properties": {
    "gn:admin1_code":"53",
    "gn:asciiname":"Shaydurovo",
    "gn:country_code":"RU",
    "gn:dem":243,
    "gn:feature_class":"P",
    "gn:feature_code":"PPL",
    "gn:name":"Shaydurovo",
    "gn:population":0,
    "gn:timezone":"Asia/Novosibirsk",
    "iso:country":"RU",
    "name:eng_x_preferred":[
        "Shaydurovo"
    ],
    "name:nor_x_preferred":[
        "Sjajdurovo"
    ],
    "name:rus_x_preferred":[
        "\u0428\u0430\u0439\u0434\u0443\u0440\u043e\u0432\u043e"
    ],
    "name:und_x_variant":[
        "Shaydurova",
        "Shadurovo",
        "Shaydurovo"
    ],
    "wof:name":"Shaydurovo",
    "wof:placetype":"locality"
},
  "geometry": {"coordinates":[81.78660000000001,54.0122],"type":"Point"}
}