{
  "type": "Feature",
  "properties": {
    "gn:admin1_code":"61",
    "gn:asciiname":"Dubnyy",
    "gn:country_code":"RU",
    "gn:dem":83,
    "gn:feature_class":"P",
    "gn:feature_code":"PPL",
    "gn:name":"Dubnyy",
    "gn:population":0,
    "gn:timezone":"Europe/Moscow",
    "iso:country":"RU",
    "name:rus_x_preferred":[
        "\u0414\u0443\u0431\u043d\u044b\u0439"
    ],
    "wof:name":"Dubnyy",
    "wof:placetype":"locality"
},
  "geometry": {"coordinates":[40.55438,49.26367],"type":"Point"}
}