{
  "type": "Feature",
  "properties": {
    "gn:admin1_code":"69",
    "gn:asciiname":"Korobets",
    "gn:country_code":"RU",
    "gn:dem":191,
    "gn:feature_class":"P",
    "gn:feature_code":"PPL",
    "gn:name":"Korobets",
    "gn:population":0,
    "gn:timezone":"Europe/Moscow",
    "iso:country":"RU",
    "name:eng_x_preferred":[
        "Korobets"
    ],
    "name:nor_x_preferred":[
        "Korobets"
    ],
    "name:rus_x_preferred":[
        "\u041a\u043e\u0440\u043e\u0431\u0435\u0446"
    ],
    "wof:name":"Korobets",
    "wof:placetype":"locality"
},
  "geometry": {"coordinates":[33.46185999999999,54.51452],"type":"Point"}
}