{
  "type": "Feature",
  "properties": {
    "gn:admin1_code":"69",
    "gn:asciiname":"Titovka",
    "gn:country_code":"RU",
    "gn:dem":175,
    "gn:feature_class":"P",
    "gn:feature_code":"PPL",
    "gn:name":"Titovka",
    "gn:population":0,
    "gn:timezone":"Europe/Moscow",
    "iso:country":"RU",
    "name:ceb_x_preferred":[
        "Titovka"
    ],
    "name:hye_x_preferred":[
        "\u054f\u056b\u057f\u0578\u057e\u056f\u0561"
    ],
    "name:rus_x_preferred":[
        "\u0422\u0438\u0442\u043e\u0432\u043a\u0430"
    ],
    "name:swe_x_preferred":[
        "Titovka"
    ],
    "wof:name":"Titovka",
    "wof:placetype":"locality"
},
  "geometry": {"coordinates":[32.05649,53.8122],"type":"Point"}
}