{
  "type": "Feature",
  "properties": {
    "gn:country":"RU",
    "gn:fcode":"PPL",
    "gn:population":0,
    "iso:country":"RU",
    "name:rus_x_preferred":[
        "\u0424\u0435\u043d\u0438\u043d\u043e"
    ],
    "qs:name":"Fenino",
    "qs:name_adm0":"Russia",
    "qs:name_adm1":"Moscow Oblast",
    "qs:photos_9k":1,
    "qs:photos_9r":1,
    "qs:photos_all":9,
    "qs:photos_sr":0,
    "qs:placetype":"Town",
    "qs:pop_sr":"0",
    "wof:name":"Fenino",
    "wof:placetype":"locality",
    "wof:population":0
},
  "geometry": {"coordinates":[37.47854,55.0173],"type":"Point"}
}