{
  "type": "Feature",
  "properties": {
    "gn:admin1_code":"85",
    "gn:asciiname":"Kukino",
    "gn:country_code":"RU",
    "gn:dem":173,
    "gn:feature_class":"P",
    "gn:feature_code":"PPL",
    "gn:name":"Kukino",
    "gn:population":0,
    "gn:timezone":"Europe/Moscow",
    "iso:country":"RU",
    "name:rus_x_preferred":[
        "\u041a\u0443\u043a\u0438\u043d\u043e"
    ],
    "name:und_x_variant":[
        "\u041a\u0443\u043a\u0438\u043d\u043e"
    ],
    "wof:name":"Kukino",
    "wof:placetype":"locality"
},
  "geometry": {"coordinates":[38.63798,59.24951],"type":"Point"}
}