{
  "type": "Feature",
  "properties": {
    "gn:admin1_code":"29",
    "gn:asciiname":"Svet",
    "gn:country_code":"RU",
    "gn:dem":317,
    "gn:feature_class":"P",
    "gn:feature_code":"PPL",
    "gn:name":"Svet",
    "gn:population":0,
    "gn:timezone":"Asia/Novokuznetsk",
    "iso:country":"RU",
    "name:eng_x_preferred":[
        "Svet"
    ],
    "name:nor_x_preferred":[
        "Svet"
    ],
    "name:rus_x_preferred":[
        "\u0421\u0432\u0435\u0442"
    ],
    "wof:name":"Svet",
    "wof:placetype":"locality"
},
  "geometry": {"coordinates":[87.14165,54.23337],"type":"Point"}
}