{
  "type": "Feature",
  "properties": {
    "gn:admin1_code":"51",
    "gn:asciiname":"Lapushinskoye",
    "gn:country_code":"RU",
    "gn:dem":152,
    "gn:feature_class":"P",
    "gn:feature_code":"PPL",
    "gn:name":"Lapushinskoye",
    "gn:population":0,
    "gn:timezone":"Europe/Moscow",
    "iso:country":"RU",
    "name:rus_x_preferred":[
        "\u041b\u0430\u043f\u0443\u0448\u0438\u043d\u0441\u043a\u043e\u0435"
    ],
    "wof:name":"Lapushinskoye",
    "wof:placetype":"locality"
},
  "geometry": {"coordinates":[46.4904,57.947],"type":"Point"}
}