{
  "type": "Feature",
  "properties": {
    "gn:admin1_code":"16",
    "gn:asciiname":"Pshongi",
    "gn:country_code":"RU",
    "gn:dem":129,
    "gn:feature_class":"P",
    "gn:feature_code":"PPL",
    "gn:name":"Pshongi",
    "gn:population":0,
    "gn:timezone":"Europe/Moscow",
    "iso:country":"RU",
    "name:rus_x_preferred":[
        "\u041f\u0448\u043e\u043d\u0433\u0438"
    ],
    "wof:name":"Pshongi",
    "wof:placetype":"locality"
},
  "geometry": {"coordinates":[47.21827,55.80467],"type":"Point"}
}