{
  "type": "Feature",
  "properties": {
    "gn:admin1_code":"53",
    "gn:asciiname":"Bakmasikha",
    "gn:country_code":"RU",
    "gn:dem":124,
    "gn:feature_class":"P",
    "gn:feature_code":"PPL",
    "gn:name":"Bakmasikha",
    "gn:population":0,
    "gn:timezone":"Asia/Novosibirsk",
    "iso:country":"RU",
    "name:eng_x_preferred":[
        "Bakmasikha"
    ],
    "name:nor_x_preferred":[
        "Bakmasikha"
    ],
    "name:rus_x_preferred":[
        "\u0411\u0430\u043a\u043c\u0430\u0441\u0438\u0445\u0430"
    ],
    "wof:name":"Bakmasikha",
    "wof:placetype":"locality"
},
  "geometry": {"coordinates":[78.83712,55.15229],"type":"Point"}
}