{
  "type": "Feature",
  "properties": {
    "gn:admin1_code":"84",
    "gn:asciiname":"Talovka",
    "gn:country_code":"RU",
    "gn:dem":144,
    "gn:feature_class":"P",
    "gn:feature_code":"PPL",
    "gn:name":"Talovka",
    "gn:population":0,
    "gn:timezone":"Europe/Volgograd",
    "iso:country":"RU",
    "name:rus_x_preferred":[
        "\u0422\u0430\u043b\u043e\u0432\u043a\u0430"
    ],
    "wof:name":"Talovka",
    "wof:placetype":"locality"
},
  "geometry": {"coordinates":[43.5678,50.6063],"type":"Point"}
}