{
  "type": "Feature",
  "properties": {
    "gn:admin1_code":"60",
    "gn:asciiname":"Sorokino",
    "gn:country_code":"RU",
    "gn:dem":164,
    "gn:feature_class":"P",
    "gn:feature_code":"PPL",
    "gn:name":"Sorokino",
    "gn:population":0,
    "gn:timezone":"Europe/Moscow",
    "iso:country":"RU",
    "name:rus_x_preferred":[
        "\u0421\u043e\u0440\u043e\u043a\u0438\u043d\u043e"
    ],
    "name:und_x_variant":[
        "\u0421\u043e\u0440\u043e\u043a\u0438\u043d\u043e"
    ],
    "wof:name":"Sorokino",
    "wof:placetype":"locality"
},
  "geometry": {"coordinates":[30.2633,56.1087],"type":"Point"}
}