{
  "type": "Feature",
  "properties": {
    "gn:admin1_code":"47",
    "gn:asciiname":"Strelino",
    "gn:country_code":"RU",
    "gn:dem":188,
    "gn:feature_class":"P",
    "gn:feature_code":"PPL",
    "gn:name":"Strelino",
    "gn:population":0,
    "gn:timezone":"Europe/Moscow",
    "iso:country":"RU",
    "name:rus_x_preferred":[
        "\u0421\u0442\u0440\u0435\u043b\u0438\u043d\u043e"
    ],
    "name:und_x_variant":[
        "\u0421\u0442\u0440\u0435\u043b\u0438\u043d\u043e"
    ],
    "wof:name":"Strelino",
    "wof:placetype":"locality"
},
  "geometry": {"coordinates":[36.9192,56.1736],"type":"Point"}
}