{
  "type": "Feature",
  "properties": {
    "gn:admin1_code":"51.0",
    "gn:asciiname":"Bol'shoye Martovo",
    "gn:country_code":"RU",
    "gn:dem":101,
    "gn:feature_class":"P",
    "gn:feature_code":"PPL",
    "gn:name":"Bol\u2019shoye Martovo",
    "gn:population":0,
    "gn:timezone":"Europe/Moscow",
    "iso:country":"RU",
    "name:rus_x_preferred":[
        "\u0411\u043e\u043b\u044c\u0448\u043e\u0435 \u041c\u0430\u0440\u0442\u043e\u0432\u043e"
    ],
    "name:und_x_variant":[
        "Bol\u2019shoye Martovo"
    ],
    "wof:name":"Bol'shoye Martovo",
    "wof:placetype":"locality"
},
  "geometry": {"coordinates":[43.16079000000001,55.87279],"type":"Point"}
}