{
  "type": "Feature",
  "properties": {
    "gn:country":"RU",
    "gn:fcode":"PPL",
    "gn:pop":4163,
    "iso:country":"RU",
    "name:eng_x_preferred":[
        "Semiletka"
    ],
    "name:nor_x_preferred":[
        "Semiletka"
    ],
    "name:rus_x_preferred":[
        "\u0421\u0435\u043c\u0438\u043b\u0435\u0442\u043a\u0430"
    ],
    "name:unk_x_variant":[
        "\u0421\u0435\u043c\u0438\u043b\u0435\u0442\u043a\u0430"
    ],
    "qs:name":"Semiletka",
    "qs:photos_9r":0,
    "qs:photos_sr":0,
    "qs:pop_sr":"4",
    "wof:name":"Semiletka",
    "wof:placetype":"locality",
    "wof:population":4163
},
  "geometry": {"coordinates":[54.61528,55.36028],"type":"Point"}
}