{
  "type": "Feature",
  "properties": {
    "gn:admin1_code":"8",
    "gn:asciiname":"Molodezhnyy",
    "gn:country_code":"RU",
    "gn:dem":230,
    "gn:feature_class":"P",
    "gn:feature_code":"PPL",
    "gn:name":"Molod\u00ebzhnyy",
    "gn:population":0,
    "gn:timezone":"Asia/Yekaterinburg",
    "iso:country":"RU",
    "name:rus_x_preferred":[
        "\u041c\u043e\u043b\u043e\u0434\u0451\u0436\u043d\u044b\u0439"
    ],
    "name:und_x_variant":[
        "Molod\u00ebzhnyy"
    ],
    "wof:name":"Molodezhnyy",
    "wof:placetype":"locality"
},
  "geometry": {"coordinates":[58.23333,55.53333000000001],"type":"Point"}
}