{
  "type": "Feature",
  "properties": {
    "gn:admin1_code":"52",
    "gn:asciiname":"Yashcherovo",
    "gn:country_code":"RU",
    "gn:dem":227,
    "gn:feature_class":"P",
    "gn:feature_code":"PPL",
    "gn:name":"Yashcherovo",
    "gn:population":0,
    "gn:timezone":"Europe/Moscow",
    "iso:country":"RU",
    "name:und_x_variant":[
        "Yashcherova",
        "Yashcherovo"
    ],
    "wof:name":"Yashcherovo",
    "wof:placetype":"locality"
},
  "geometry": {"coordinates":[33.23722,58.025],"type":"Point"}
}