{
  "type": "Feature",
  "properties": {
    "gn:country":"RU",
    "gn:fcode":"PPL",
    "gn:pop":0,
    "iso:country":"RU",
    "name:che_x_preferred":[
        "\u041e\u0441\u044c\u043c\u0438\u043d\u043e"
    ],
    "name:eng_x_preferred":[
        "Os'mino"
    ],
    "name:eng_x_variant":[
        "Osmino"
    ],
    "name:est_x_preferred":[
        "Osmino"
    ],
    "name:nor_x_preferred":[
        "Osmino"
    ],
    "name:rus_x_preferred":[
        "\u041e\u0441\u044c\u043c\u0438\u043d\u043e"
    ],
    "name:unk_x_variant":[
        "\u041e\u0441\u044c\u043c\u0438\u043d\u043e"
    ],
    "qs:name":"Os'mino",
    "qs:name_adm0":"Russia",
    "qs:name_adm1":"Leningrad Oblast",
    "qs:photos_9r":0,
    "qs:photos_sr":0,
    "qs:placetype":"Town",
    "qs:pop_sr":"0",
    "wof:name":"Os'mino",
    "wof:placetype":"locality",
    "wof:population":0
},
  "geometry": {"coordinates":[29.09274,59.0133],"type":"Point"}
}