{
  "type": "Feature",
  "properties": {
    "gn:admin1_code":"47",
    "gn:asciiname":"Lovchikovo",
    "gn:country_code":"RU",
    "gn:dem":127,
    "gn:feature_class":"P",
    "gn:feature_code":"PPL",
    "gn:name":"Lovchikovo",
    "gn:population":0,
    "gn:timezone":"Europe/Moscow",
    "iso:country":"RU",
    "name:rus_x_preferred":[
        "\u041b\u043e\u0432\u0447\u0438\u043a\u043e\u0432\u043e"
    ],
    "wof:name":"Lovchikovo",
    "wof:placetype":"locality"
},
  "geometry": {"coordinates":[39.79439,55.22952],"type":"Point"}
}