{
  "type": "Feature",
  "properties": {
    "gn:admin1_code":"60",
    "gn:asciiname":"Pyzhovo",
    "gn:country_code":"RU",
    "gn:dem":99,
    "gn:feature_class":"P",
    "gn:feature_code":"PPL",
    "gn:name":"Pyzhovo",
    "gn:population":0,
    "gn:timezone":"Europe/Moscow",
    "iso:country":"RU",
    "name:rus_x_preferred":[
        "\u041f\u044b\u0436\u043e\u0432\u043e"
    ],
    "name:und_x_variant":[
        "P\u00f4\u0161eva",
        "Pyzheva",
        "P\u00f4\u017eeva",
        "Pyzhovo",
        "\u041f\u044b\u0436\u043e\u0432\u043e"
    ],
    "wof:name":"Pyzhovo",
    "wof:placetype":"locality"
},
  "geometry": {"coordinates":[27.84777,57.67072],"type":"Point"}
}