{
  "type": "Feature",
  "properties": {
    "gn:admin1_code":"16",
    "gn:asciiname":"Yaushi",
    "gn:country_code":"RU",
    "gn:dem":188,
    "gn:feature_class":"P",
    "gn:feature_code":"PPL",
    "gn:name":"Yaushi",
    "gn:population":0,
    "gn:timezone":"Europe/Moscow",
    "iso:country":"RU",
    "name:eng_x_preferred":[
        "Yaushi"
    ],
    "name:nor_x_preferred":[
        "Jausji"
    ],
    "name:rus_x_preferred":[
        "\u042f\u0443\u0448\u0438"
    ],
    "name:und_x_variant":[
        "Yaushevo",
        "Yaushi"
    ],
    "wof:name":"Yaushi",
    "wof:placetype":"locality"
},
  "geometry": {"coordinates":[47.09961,56.09025],"type":"Point"}
}