{
  "type": "Feature",
  "properties": {
    "gn:admin1_code":"6",
    "gn:asciiname":"Lyzhiny",
    "gn:country_code":"RU",
    "gn:dem":3,
    "gn:feature_class":"P",
    "gn:feature_code":"PPL",
    "gn:name":"Lyzhiny",
    "gn:population":0,
    "gn:timezone":"Europe/Moscow",
    "iso:country":"RU",
    "name:rus_x_preferred":[
        "\u041b\u044b\u0436\u0438\u043d\u044b"
    ],
    "name:und_x_variant":[
        "Lyshiny",
        "Lyzhiny",
        "\u041b\u044b\u0436\u0438\u043d\u044b"
    ],
    "wof:name":"Lyzhiny",
    "wof:placetype":"locality"
},
  "geometry": {"coordinates":[41.8112,64.2543],"type":"Point"}
}