{
  "type": "Feature",
  "properties": {
    "gn:admin1_code":"38",
    "gn:asciiname":"Shishev",
    "gn:cc2":"RU",
    "gn:country_code":"RU",
    "gn:dem":1,
    "gn:feature_class":"P",
    "gn:feature_code":"PPL",
    "gn:name":"Shishev",
    "gn:population":0,
    "gn:timezone":"Europe/Moscow",
    "iso:country":"RU",
    "name:rus_x_preferred":[
        "\u0428\u0438\u0448\u0435\u0432"
    ],
    "name:und_x_variant":[
        "Shishov",
        "Shishev",
        "\u0428\u0438\u0448\u0435\u0432"
    ],
    "wof:name":"Shishev",
    "wof:placetype":"locality"
},
  "geometry": {"coordinates":[38.45,45.83333],"type":"Point"}
}