{
  "type": "Feature",
  "properties": {
    "gn:admin1_code":"85",
    "gn:asciiname":"Golyshevo",
    "gn:country_code":"RU",
    "gn:dem":149,
    "gn:feature_class":"P",
    "gn:feature_code":"PPL",
    "gn:name":"Golysh\u00ebvo",
    "gn:population":0,
    "gn:timezone":"Europe/Moscow",
    "iso:country":"RU",
    "name:rus_x_preferred":[
        "\u0413\u043e\u043b\u044b\u0448\u0451\u0432\u043e"
    ],
    "name:und_x_variant":[
        "Golysh\u00ebvo"
    ],
    "wof:name":"Golyshevo",
    "wof:placetype":"locality"
},
  "geometry": {"coordinates":[38.4707,59.9053],"type":"Point"}
}