{
  "type": "Feature",
  "properties": {
    "gn:admin1_code":"76",
    "gn:asciiname":"Nizhnyaya Pchel'na",
    "gn:country_code":"RU",
    "gn:dem":235,
    "gn:feature_class":"P",
    "gn:feature_code":"PPL",
    "gn:name":"Nizhnyaya Pch\u00ebl\u2019na",
    "gn:population":0,
    "gn:timezone":"Europe/Moscow",
    "iso:country":"RU",
    "name:rus_x_preferred":[
        "\u041d\u0438\u0436\u043d\u044f\u044f \u041f\u0447\u0451\u043b\u044c\u043d\u0430"
    ],
    "name:und_x_variant":[
        "Nizhnyaya Pch\u00ebl\u2019na",
        "\u041d\u0438\u0436\u043d\u044f\u044f \u041f\u0447\u0451\u043b\u044c\u043d\u0430"
    ],
    "wof:name":"Nizhnyaya Pchel'na",
    "wof:placetype":"locality"
},
  "geometry": {"coordinates":[36.68365,53.88054],"type":"Point"}
}