{
  "type": "Feature",
  "properties": {
    "gn:admin1_code":"29",
    "gn:asciiname":"Tashelga",
    "gn:country_code":"RU",
    "gn:dem":501,
    "gn:feature_class":"P",
    "gn:feature_code":"PPL",
    "gn:name":"Tashelga",
    "gn:population":0,
    "gn:timezone":"Asia/Novokuznetsk",
    "iso:country":"RU",
    "name:eng_x_preferred":[
        "Tashelga"
    ],
    "name:nor_x_preferred":[
        "Tasjelga"
    ],
    "name:rus_x_preferred":[
        "\u0422\u0430\u0448\u0435\u043b\u0433\u0430"
    ],
    "name:und_x_variant":[
        "Tashilga"
    ],
    "wof:name":"Tashelga",
    "wof:placetype":"locality"
},
  "geometry": {"coordinates":[88.39789,53.45075],"type":"Point"}
}