{
  "type": "Feature",
  "properties": {
    "gn:admin1_code":"71",
    "gn:asciiname":"Posolka",
    "gn:country_code":"RU",
    "gn:dem":61,
    "gn:feature_class":"P",
    "gn:feature_code":"PPL",
    "gn:name":"Posolka",
    "gn:population":0,
    "gn:timezone":"Asia/Yekaterinburg",
    "iso:country":"RU",
    "name:rus_x_preferred":[
        "\u041f\u043e\u0441\u043e\u043b\u043a\u0430"
    ],
    "name:und_x_variant":[
        "\u041f\u043e\u0441\u043e\u043b\u043a\u0430"
    ],
    "wof:name":"Posolka",
    "wof:placetype":"locality"
},
  "geometry": {"coordinates":[64.80754,58.53186],"type":"Point"}
}