{
  "type": "Feature",
  "properties": {
    "gn:admin1_code":"28.0",
    "gn:asciiname":"Chalna",
    "gn:country_code":"RU",
    "gn:dem":45,
    "gn:feature_class":"P",
    "gn:feature_code":"PPL",
    "gn:name":"Chalna",
    "gn:population":0,
    "gn:timezone":"Europe/Moscow",
    "iso:country":"RU",
    "name:eng_x_preferred":[
        "Chalna"
    ],
    "name:fin_x_preferred":[
        "Tsalna"
    ],
    "name:fin_x_variant":[
        "Viitana"
    ],
    "name:krl_x_preferred":[
        "\u010calna"
    ],
    "name:nor_x_preferred":[
        "Tsjalna"
    ],
    "name:rus_x_preferred":[
        "\u0427\u0430\u043b\u043d\u0430"
    ],
    "wof:name":"Chalna",
    "wof:placetype":"locality"
},
  "geometry": {"coordinates":[34.0638,61.88399],"type":"Point"}
}