{
  "type": "Feature",
  "properties": {
    "gn:admin1_code":"69",
    "gn:asciiname":"Mezhniki",
    "gn:country_code":"RU",
    "gn:dem":222,
    "gn:feature_class":"P",
    "gn:feature_code":"PPL",
    "gn:name":"Mezhniki",
    "gn:population":0,
    "gn:timezone":"Europe/Moscow",
    "iso:country":"RU",
    "name:rus_x_preferred":[
        "\u041c\u0435\u0436\u043d\u0438\u043a\u0438"
    ],
    "wof:name":"Mezhniki",
    "wof:placetype":"locality"
},
  "geometry": {"coordinates":[32.33355,54.8677],"type":"Point"}
}