{
  "type": "Feature",
  "properties": {
    "gn:admin1_code":"55",
    "gn:asciiname":"Izhberda",
    "gn:country_code":"RU",
    "gn:dem":299,
    "gn:feature_class":"P",
    "gn:feature_code":"PPL",
    "gn:name":"Izhberda",
    "gn:population":0,
    "gn:timezone":"Asia/Yekaterinburg",
    "iso:country":"RU",
    "name:eng_x_preferred":[
        "Izhberda"
    ],
    "name:nor_x_preferred":[
        "Izjberda"
    ],
    "name:rus_x_preferred":[
        "\u0418\u0436\u0431\u0435\u0440\u0434\u0430"
    ],
    "name:und_x_variant":[
        "\u0418\u0436\u0431\u0435\u0440\u0434\u0430",
        "Izhberda"
    ],
    "wof:name":"Izhberda",
    "wof:placetype":"locality"
},
  "geometry": {"coordinates":[58.02896,51.29035],"type":"Point"}
}