{
  "type": "Feature",
  "properties": {
    "gn:admin1_code":"17.0",
    "gn:asciiname":"Berlik",
    "gn:country_code":"RU",
    "gn:dem":325,
    "gn:feature_class":"P",
    "gn:feature_code":"PPL",
    "gn:name":"Berlik",
    "gn:population":0,
    "gn:timezone":"Europe/Moscow",
    "iso:country":"RU",
    "name:nor_x_preferred":[
        "Berlik"
    ],
    "name:rus_x_preferred":[
        "\u0411\u0435\u0440\u043b\u0438\u043a"
    ],
    "wof:name":"Berlik",
    "wof:placetype":"locality"
},
  "geometry": {"coordinates":[47.43333,42.76667],"type":"Point"}
}