{
  "type": "Feature",
  "properties": {
    "gn:admin1_code":"85",
    "gn:asciiname":"Pyzheyevo",
    "gn:country_code":"RU",
    "gn:dem":144,
    "gn:feature_class":"P",
    "gn:feature_code":"PPL",
    "gn:name":"Pyzheyevo",
    "gn:population":0,
    "gn:timezone":"Europe/Moscow",
    "iso:country":"RU",
    "name:rus_x_preferred":[
        "\u041f\u044b\u0436\u0435\u0435\u0432\u043e"
    ],
    "wof:name":"Pyzheyevo",
    "wof:placetype":"locality"
},
  "geometry": {"coordinates":[38.5277,59.3685],"type":"Point"}
}