{
  "type": "Feature",
  "properties": {
    "gn:admin1_code":"91",
    "gn:asciiname":"Kulumys",
    "gn:cc2":"RU",
    "gn:country_code":"RU",
    "gn:dem":903,
    "gn:feature_class":"P",
    "gn:feature_code":"PPL",
    "gn:name":"Kulumys",
    "gn:population":0,
    "gn:timezone":"Asia/Krasnoyarsk",
    "iso:country":"RU",
    "name:eng_x_preferred":[
        "Kulumys"
    ],
    "name:nor_x_preferred":[
        "Kulumys"
    ],
    "name:rus_x_preferred":[
        "\u041a\u0443\u043b\u0443\u043c\u044b\u0441"
    ],
    "name:und_x_variant":[
        "Staryy Kulumys",
        "Kulumys"
    ],
    "wof:name":"Kulumys",
    "wof:placetype":"locality"
},
  "geometry": {"coordinates":[92.95,52.96666999999999],"type":"Point"}
}