{
  "type": "Feature",
  "properties": {
    "gn:admin1_code":"85",
    "gn:asciiname":"Novoselo",
    "gn:country_code":"RU",
    "gn:dem":121,
    "gn:feature_class":"P",
    "gn:feature_code":"PPL",
    "gn:name":"Novoselo",
    "gn:population":0,
    "gn:timezone":"Europe/Moscow",
    "iso:country":"RU",
    "name:eng_x_preferred":[
        "Novoselo"
    ],
    "name:nor_x_preferred":[
        "Novoselo"
    ],
    "name:rus_x_preferred":[
        "\u041d\u043e\u0432\u043e\u0441\u0435\u043b\u043e"
    ],
    "name:und_x_variant":[
        "Novoselovo"
    ],
    "wof:name":"Novoselo",
    "wof:placetype":"locality"
},
  "geometry": {"coordinates":[37.3857,60.4427],"type":"Point"}
}