{
  "type": "Feature",
  "properties": {
    "gn:admin1_code":"59",
    "gn:asciiname":"Bukhta Shirokaya",
    "gn:country_code":"RU",
    "gn:dem":30,
    "gn:feature_class":"P",
    "gn:feature_code":"PPL",
    "gn:name":"Bukhta Shirokaya",
    "gn:population":0,
    "gn:timezone":"Asia/Yakutsk",
    "iso:country":"RU",
    "name:rus_x_preferred":[
        "\u0411\u0443\u0445\u0442\u0430 \u0428\u0438\u0440\u043e\u043a\u0430\u044f"
    ],
    "name:und_x_variant":[
        "\u0411\u0443\u0445\u0442\u0430 \u0428\u0438\u0440\u043e\u043a\u0430\u044f"
    ],
    "wof:name":"Bukhta Shirokaya",
    "wof:placetype":"locality"
},
  "geometry": {"coordinates":[132.43292,42.87543],"type":"Point"}
}