{
  "type": "Feature",
  "properties": {
    "gn:admin1_code":"9.0",
    "gn:asciiname":"Shelayevo",
    "gn:country_code":"RU",
    "gn:dem":86,
    "gn:feature_class":"P",
    "gn:feature_code":"PPL",
    "gn:name":"Shelayevo",
    "gn:population":0,
    "gn:timezone":"Europe/Moscow",
    "iso:country":"RU",
    "name:eng_x_preferred":[
        "Shelayevo"
    ],
    "name:nor_x_preferred":[
        "Sjalajevo"
    ],
    "name:rus_x_preferred":[
        "\u0428\u0430\u043b\u0430\u0435\u0432\u043e"
    ],
    "wof:name":"Shelayevo",
    "wof:placetype":"locality"
},
  "geometry": {"coordinates":[38.07583,50.12222],"type":"Point"}
}