{
  "type": "Feature",
  "properties": {
    "gn:admin1_code":"75",
    "gn:asciiname":"Rodionovka",
    "gn:cc2":"RU",
    "gn:country_code":"RU",
    "gn:dem":67,
    "gn:feature_class":"P",
    "gn:feature_code":"PPL",
    "gn:name":"Rodionovka",
    "gn:population":0,
    "gn:timezone":"Asia/Tomsk",
    "iso:country":"RU",
    "name:che_x_preferred":[
        "\u0420\u043e\u0434\u0438\u043e\u043d\u043e\u0432\u043a\u0430"
    ],
    "name:eng_x_preferred":[
        "Rodionovka"
    ],
    "name:nor_x_preferred":[
        "Rodionovka"
    ],
    "name:rus_x_preferred":[
        "\u0420\u043e\u0434\u0438\u043e\u043d\u043e\u0432\u043a\u0430"
    ],
    "name:tgk_x_preferred":[
        "\u0420\u043e\u0434\u0438\u043e\u043d\u043e\u0432\u043a\u0430"
    ],
    "name:und_x_variant":[
        "Rodionovo",
        "\u0420\u043e\u0434\u0438\u043e\u043d\u043e\u0432\u043a\u0430",
        "Rodionovka"
    ],
    "wof:name":"Rodionovka",
    "wof:placetype":"locality"
},
  "geometry": {"coordinates":[83.51139000000001,58.43917],"type":"Point"}
}