{
  "type": "Feature",
  "properties": {
    "gn:admin1_code":"30",
    "gn:asciiname":"Mikhalitsyno",
    "gn:cc2":"RU",
    "gn:country_code":"RU",
    "gn:dem":26,
    "gn:feature_class":"P",
    "gn:feature_code":"PPL",
    "gn:name":"Mikhalitsyno",
    "gn:population":0,
    "gn:timezone":"Asia/Vladivostok",
    "iso:country":"RU",
    "name:rus_x_preferred":[
        "\u041c\u0438\u0445\u0430\u043b\u0438\u0446\u044b\u043d\u043e"
    ],
    "name:und_x_variant":[
        "Mikhaylitsino",
        "Mikhalitsino",
        "Mikhalitsyno"
    ],
    "wof:name":"Mikhalitsyno",
    "wof:placetype":"locality"
},
  "geometry": {"coordinates":[138.19999999999999,52.76667],"type":"Point"}
}