{
  "type": "Feature",
  "properties": {
    "gn:admin1_code":"33",
    "gn:asciiname":"Stolbovy",
    "gn:country_code":"RU",
    "gn:dem":176,
    "gn:feature_class":"P",
    "gn:feature_code":"PPL",
    "gn:name":"Stolbovy",
    "gn:population":0,
    "gn:timezone":"Europe/Kirov",
    "iso:country":"RU",
    "name:eng_x_preferred":[
        "Stolbovy"
    ],
    "name:nor_x_preferred":[
        "Stolbovy"
    ],
    "name:rus_x_preferred":[
        "\u0421\u0442\u043e\u043b\u0431\u043e\u0432\u044b"
    ],
    "wof:name":"Stolbovy",
    "wof:placetype":"locality"
},
  "geometry": {"coordinates":[48.10686,58.99074],"type":"Point"}
}