{
  "type": "Feature",
  "properties": {
    "gn:admin1_code":"91",
    "gn:asciiname":"Malyy Kaydat",
    "gn:cc2":"RU",
    "gn:country_code":"RU",
    "gn:dem":308,
    "gn:feature_class":"P",
    "gn:feature_code":"PPL",
    "gn:name":"Malyy Kaydat",
    "gn:population":0,
    "gn:timezone":"Asia/Krasnoyarsk",
    "iso:country":"RU",
    "name:eng_x_preferred":[
        "Malyy Kaydat"
    ],
    "name:nor_x_preferred":[
        "Mal.Kajdat"
    ],
    "name:rus_x_preferred":[
        "\u041c\u0430\u043b.\u041a\u0430\u0439\u0434\u0430\u0442"
    ],
    "name:rus_x_variant":[
        "\u041c\u0430\u043b\u044b\u0439 \u041a\u0430\u0439\u0434\u0430\u0442"
    ],
    "name:und_x_variant":[
        "Maly-Kaydat",
        "Malyy Kaydat"
    ],
    "wof:name":"Malyy Kaydat",
    "wof:placetype":"locality"
},
  "geometry": {"coordinates":[91.55333,55.97194],"type":"Point"}
}