{
  "type": "Feature",
  "properties": {
    "gn:admin1_code":"93",
    "gn:asciiname":"Mitrofanovo",
    "gn:country_code":"RU",
    "gn:dem":494,
    "gn:feature_class":"P",
    "gn:feature_code":"PPL",
    "gn:name":"Mitrofanovo",
    "gn:population":0,
    "gn:timezone":"Asia/Chita",
    "iso:country":"RU",
    "name:eng_x_preferred":[
        "Mitrofanovo"
    ],
    "name:nor_x_preferred":[
        "Mitrofanovo"
    ],
    "name:rus_x_preferred":[
        "\u041c\u0438\u0442\u0440\u043e\u0444\u0430\u043d\u043e\u0432\u043e"
    ],
    "name:und_x_variant":[
        "Mitrofanovskoye"
    ],
    "wof:name":"Mitrofanovo",
    "wof:placetype":"locality"
},
  "geometry": {"coordinates":[115.95466999999999,51.82209],"type":"Point"}
}