{
  "type": "Feature",
  "properties": {
    "gn:admin1_code":"61",
    "gn:asciiname":"Vinogradnyy",
    "gn:country_code":"RU",
    "gn:dem":22,
    "gn:feature_class":"P",
    "gn:feature_code":"PPL",
    "gn:name":"Vinogradnyy",
    "gn:population":0,
    "gn:timezone":"Europe/Moscow",
    "iso:country":"RU",
    "name:rus_x_preferred":[
        "\u0412\u0438\u043d\u043e\u0433\u0440\u0430\u0434\u043d\u044b\u0439"
    ],
    "name:und_x_variant":[
        "Vinogradny",
        "Vinogradnyy"
    ],
    "wof:name":"Vinogradnyy",
    "wof:placetype":"locality"
},
  "geometry": {"coordinates":[40.9149,48.0038],"type":"Point"}
}