{
  "type": "Feature",
  "properties": {
    "gn:admin1_code":"52",
    "gn:asciiname":"Kontsy",
    "gn:country_code":"RU",
    "gn:dem":50,
    "gn:feature_class":"P",
    "gn:feature_code":"PPL",
    "gn:name":"Kontsy",
    "gn:population":0,
    "gn:timezone":"Europe/Moscow",
    "iso:country":"RU",
    "name:eng_x_preferred":[
        "Kontsy"
    ],
    "name:nor_x_preferred":[
        "Kontsy"
    ],
    "name:rus_x_preferred":[
        "\u041a\u043e\u043d\u0446\u044b"
    ],
    "wof:name":"Kontsy",
    "wof:placetype":"locality"
},
  "geometry": {"coordinates":[32.905,58.82591],"type":"Point"}
}