{
  "type": "Feature",
  "properties": {
    "gn:admin1_code":"71",
    "gn:asciiname":"Fil'kino",
    "gn:country_code":"RU",
    "gn:dem":81,
    "gn:feature_class":"P",
    "gn:feature_code":"PPL",
    "gn:name":"Fil\u2019kino",
    "gn:population":0,
    "gn:timezone":"Asia/Yekaterinburg",
    "iso:country":"RU",
    "name:eng_x_preferred":[
        "Fil'kino"
    ],
    "name:nor_x_preferred":[
        "Filkino"
    ],
    "name:rus_x_preferred":[
        "\u0424\u0438\u043b\u044c\u043a\u0438\u043d\u043e"
    ],
    "name:und_x_variant":[
        "Fil\u2019kino"
    ],
    "wof:name":"Fil'kino",
    "wof:placetype":"locality"
},
  "geometry": {"coordinates":[60.70505,59.60006],"type":"Point"}
}