{
  "type": "Feature",
  "properties": {
    "gn:admin1_code":"76",
    "gn:asciiname":"Staroye Petrishchevo",
    "gn:country_code":"RU",
    "gn:dem":167,
    "gn:feature_class":"P",
    "gn:feature_code":"PPL",
    "gn:name":"Staroye Petrishchevo",
    "gn:population":0,
    "gn:timezone":"Europe/Moscow",
    "iso:country":"RU",
    "name:rus_x_preferred":[
        "\u0421\u0442\u0430\u0440\u043e\u0435 \u041f\u0435\u0442\u0440\u0438\u0449\u0435\u0432\u043e"
    ],
    "name:und_x_variant":[
        "\u0421\u0442\u0430\u0440\u043e\u0435 \u041f\u0435\u0442\u0440\u0438\u0449\u0435\u0432\u043e"
    ],
    "wof:name":"Staroye Petrishchevo",
    "wof:placetype":"locality"
},
  "geometry": {"coordinates":[37.29161,54.26264000000001],"type":"Point"}
}