{
  "type": "Feature",
  "properties": {
    "gn:admin1_code":"56",
    "gn:asciiname":"Komarnik",
    "gn:country_code":"RU",
    "gn:dem":244,
    "gn:feature_class":"P",
    "gn:feature_code":"PPL",
    "gn:name":"Komarnik",
    "gn:population":0,
    "gn:timezone":"Europe/Moscow",
    "iso:country":"RU",
    "name:rus_x_preferred":[
        "\u041a\u043e\u043c\u0430\u0440\u043d\u0438\u043a"
    ],
    "wof:name":"Komarnik",
    "wof:placetype":"locality"
},
  "geometry": {"coordinates":[35.5015,52.4842],"type":"Point"}
}