{
  "type": "Feature",
  "properties": {
    "gn:admin1_code":"52",
    "gn:asciiname":"Pravdukha",
    "gn:country_code":"RU",
    "gn:dem":67,
    "gn:feature_class":"P",
    "gn:feature_code":"PPL",
    "gn:name":"Pravdukha",
    "gn:population":0,
    "gn:timezone":"Europe/Moscow",
    "iso:country":"RU",
    "name:rus_x_preferred":[
        "\u041f\u0440\u0430\u0432\u0434\u0443\u0445\u0430"
    ],
    "name:und_x_variant":[
        "\u041f\u0440\u0430\u0432\u0434\u0443\u0445\u0430"
    ],
    "wof:name":"Pravdukha",
    "wof:placetype":"locality"
},
  "geometry": {"coordinates":[30.69431,58.07425],"type":"Point"}
}