{
  "type": "Feature",
  "properties": {
    "gn:admin1_code":"93",
    "gn:asciiname":"Chindagatay",
    "gn:country_code":"RU",
    "gn:dem":691,
    "gn:feature_class":"P",
    "gn:feature_code":"PPL",
    "gn:name":"Chindagatay",
    "gn:population":0,
    "gn:timezone":"Asia/Chita",
    "iso:country":"RU",
    "name:eng_x_preferred":[
        "Chindagatay"
    ],
    "name:nor_x_preferred":[
        "Tsjindagataj"
    ],
    "name:rus_x_preferred":[
        "\u0427\u0438\u043d\u0434\u0430\u0433\u0430\u0442\u0430\u0439"
    ],
    "name:und_x_variant":[
        "Chindagatai",
        "Chindagotuy",
        "\u0427\u0438\u043d\u0434\u0430\u0433\u0430\u0442\u0430\u0439",
        "Chindagatay"
    ],
    "wof:name":"Chindagatay",
    "wof:placetype":"locality"
},
  "geometry": {"coordinates":[118.23801,50.76626],"type":"Point"}
}