{
  "type": "Feature",
  "properties": {
    "gn:admin1_code":"76",
    "gn:asciiname":"Rassekino",
    "gn:country_code":"RU",
    "gn:dem":161,
    "gn:feature_class":"P",
    "gn:feature_code":"PPL",
    "gn:name":"Rassekino",
    "gn:population":0,
    "gn:timezone":"Europe/Moscow",
    "iso:country":"RU",
    "name:rus_x_preferred":[
        "\u0420\u0430\u0441\u0441\u0435\u043a\u0438\u043d\u043e"
    ],
    "name:und_x_variant":[
        "\u0420\u0430\u0441\u0441\u0435\u043a\u0438\u043d\u043e"
    ],
    "wof:name":"Rassekino",
    "wof:placetype":"locality"
},
  "geometry": {"coordinates":[38.773,53.7972],"type":"Point"}
}