{
  "type": "Feature",
  "properties": {
    "gn:admin1_code":"64",
    "gn:asciiname":"Mendeleyevo",
    "gn:country_code":"RU",
    "gn:dem":101,
    "gn:feature_class":"P",
    "gn:feature_code":"PPL",
    "gn:name":"Mendeleyevo",
    "gn:population":0,
    "gn:timezone":"Asia/Magadan",
    "iso:country":"RU",
    "name:rus_x_preferred":[
        "\u041c\u0435\u043d\u0434\u0435\u043b\u0435\u0435\u0432\u043e"
    ],
    "wof:name":"Mendeleyevo",
    "wof:placetype":"locality"
},
  "geometry": {"coordinates":[145.68039999999999,43.95343],"type":"Point"}
}