{
  "type": "Feature",
  "properties": {
    "gn:admin1_code":"85",
    "gn:asciiname":"Gridino",
    "gn:country_code":"RU",
    "gn:dem":157,
    "gn:feature_class":"P",
    "gn:feature_code":"PPL",
    "gn:name":"Gridino",
    "gn:population":0,
    "gn:timezone":"Europe/Moscow",
    "iso:country":"RU",
    "name:eng_x_preferred":[
        "Gridino"
    ],
    "name:nor_x_preferred":[
        "Gridino"
    ],
    "name:rus_x_preferred":[
        "\u0413\u0440\u0438\u0434\u0438\u043d\u043e"
    ],
    "wof:name":"Gridino",
    "wof:placetype":"locality"
},
  "geometry": {"coordinates":[40.97111,58.71194000000001],"type":"Point"}
}