{
  "type": "Feature",
  "properties": {
    "gn:admin1_code":"77",
    "gn:asciiname":"Aleshino",
    "gn:country_code":"RU",
    "gn:dem":232,
    "gn:feature_class":"P",
    "gn:feature_code":"PPL",
    "gn:name":"Al\u00ebshino",
    "gn:population":0,
    "gn:timezone":"Europe/Moscow",
    "iso:country":"RU",
    "name:nor_x_preferred":[
        "Aljosjino"
    ],
    "name:rus_x_preferred":[
        "\u0410\u043b\u0451\u0448\u0438\u043d\u043e"
    ],
    "name:und_x_variant":[
        "Al\u00ebshino"
    ],
    "wof:name":"Aleshino",
    "wof:placetype":"locality"
},
  "geometry": {"coordinates":[33.4916,56.91533],"type":"Point"}
}