{
  "type": "Feature",
  "properties": {
    "gn:admin1_code":"25.0",
    "gn:asciiname":"Poselok Sovkhoz Chkalovskiy",
    "gn:country_code":"RU",
    "gn:dem":200,
    "gn:feature_class":"P",
    "gn:feature_code":"PPL",
    "gn:name":"Pos\u00eblok Sovkhoz Chkalovskiy",
    "gn:population":0,
    "gn:timezone":"Europe/Moscow",
    "iso:country":"RU",
    "name:rus_x_preferred":[
        "\u041f\u043e\u0441\u0451\u043b\u043e\u043a \u0421\u043e\u0432\u0445\u043e\u0437 \u0427\u043a\u0430\u043b\u043e\u0432\u0441\u043a\u0438\u0439"
    ],
    "name:und_x_variant":[
        "Sovkhoz Chkalovskiy",
        "Pos\u00eblok Sovkhoz Chkalovskiy"
    ],
    "wof:name":"Poselok Sovkhoz Chkalovskiy",
    "wof:placetype":"locality"
},
  "geometry": {"coordinates":[35.88369,54.56068000000001],"type":"Point"}
}