{
  "type": "Feature",
  "properties": {
    "gn:admin1_code":"84",
    "gn:asciiname":"Shiryayevskiy",
    "gn:country_code":"RU",
    "gn:dem":75,
    "gn:feature_class":"P",
    "gn:feature_code":"PPL",
    "gn:name":"Shiryayevskiy",
    "gn:population":0,
    "gn:timezone":"Europe/Volgograd",
    "iso:country":"RU",
    "name:eng_x_preferred":[
        "Shiryayevskiy"
    ],
    "name:nor_x_preferred":[
        "Sjirjaevskij"
    ],
    "name:rus_x_preferred":[
        "\u0428\u0438\u0440\u044f\u0435\u0432\u0441\u043a\u0438\u0439"
    ],
    "name:und_x_variant":[
        "Shiryayskiy",
        "Shiryay"
    ],
    "wof:name":"Shiryayevskiy",
    "wof:placetype":"locality"
},
  "geometry": {"coordinates":[44.02252,49.58327],"type":"Point"}
}