{
  "type": "Feature",
  "properties": {
    "gn:admin1_code":"5.0",
    "gn:asciiname":"Kazachiy",
    "gn:country_code":"RU",
    "gn:dem":202,
    "gn:feature_class":"P",
    "gn:feature_code":"PPL",
    "gn:name":"Kazachiy",
    "gn:population":0,
    "gn:timezone":"Asia/Yakutsk",
    "iso:country":"RU",
    "name:rus_x_preferred":[
        "\u041a\u0430\u0437\u0430\u0447\u0438\u0439"
    ],
    "wof:name":"Kazachiy",
    "wof:placetype":"locality"
},
  "geometry": {"coordinates":[130.82435000000001,49.05517],"type":"Point"}
}