{
  "type": "Feature",
  "properties": {
    "gn:admin1_code":"53",
    "gn:asciiname":"Ust'-Lukovka",
    "gn:country_code":"RU",
    "gn:dem":136,
    "gn:feature_class":"P",
    "gn:feature_code":"PPL",
    "gn:name":"Ust\u2019-Lukovka",
    "gn:population":0,
    "gn:timezone":"Asia/Novosibirsk",
    "iso:country":"RU",
    "name:eng_x_preferred":[
        "Ust'-Lukovka"
    ],
    "name:nor_x_preferred":[
        "Ust-Lukovka"
    ],
    "name:rus_x_preferred":[
        "\u0423\u0441\u0442\u044c-\u041b\u0443\u043a\u043e\u0432\u043a\u0430"
    ],
    "name:und_x_variant":[
        "Ust\u2019-Lukovka"
    ],
    "wof:name":"Ust'-Lukovka",
    "wof:placetype":"locality"
},
  "geometry": {"coordinates":[81.7497,54.3879],"type":"Point"}
}