{
  "type": "Feature",
  "properties": {
    "gn:admin1_code":"20",
    "gn:asciiname":"Kharagun",
    "gn:country_code":"RU",
    "gn:dem":567,
    "gn:feature_class":"P",
    "gn:feature_code":"PPL",
    "gn:name":"Kharagun",
    "gn:population":0,
    "gn:timezone":"Asia/Irkutsk",
    "iso:country":"RU",
    "name:eng_x_preferred":[
        "Kharagun"
    ],
    "name:nor_x_preferred":[
        "Kharagun"
    ],
    "name:rus_x_preferred":[
        "\u0425\u0430\u0440\u0430\u0433\u0443\u043d"
    ],
    "wof:name":"Kharagun",
    "wof:placetype":"locality"
},
  "geometry": {"coordinates":[101.5763,53.3564],"type":"Point"}
}