{
  "type": "Feature",
  "properties": {
    "gn:admin1_code":"71.0",
    "gn:asciiname":"Novozykovo",
    "gn:country_code":"RU",
    "gn:dem":69,
    "gn:feature_class":"P",
    "gn:feature_code":"PPL",
    "gn:name":"Novozykovo",
    "gn:population":0,
    "gn:timezone":"Asia/Yekaterinburg",
    "iso:country":"RU",
    "name:rus_x_preferred":[
        "\u041d\u043e\u0432\u043e\u0437\u044b\u043a\u043e\u0432\u043e"
    ],
    "name:und_x_variant":[
        "\u041d\u043e\u0432\u043e\u0437\u044b\u043a\u043e\u0432\u043e",
        "Novozykovo"
    ],
    "wof:name":"Novozykovo",
    "wof:placetype":"locality"
},
  "geometry": {"coordinates":[62.9008,59.67799],"type":"Point"}
}