{
  "type": "Feature",
  "properties": {
    "gn:country":"RU",
    "gn:fcode":"PPL",
    "gn:population":0,
    "iso:country":"RU",
    "name:eng_x_preferred":[
        "Milovka"
    ],
    "name:nor_x_preferred":[
        "Milovka"
    ],
    "name:rus_x_preferred":[
        "\u041c\u0438\u043b\u043e\u0432\u043a\u0430"
    ],
    "qs:name":"Milovka",
    "qs:name_adm0":"Russia",
    "qs:name_adm1":"Bashkortostan Republic",
    "qs:photos_9k":1,
    "qs:photos_9r":4,
    "qs:photos_all":184,
    "qs:photos_sr":0,
    "qs:placetype":"Town",
    "qs:pop_sr":"0",
    "wof:name":"Milovka",
    "wof:placetype":"locality",
    "wof:population":0
},
  "geometry": {"coordinates":[55.83396,54.78042],"type":"Point"}
}