{
  "type": "Feature",
  "properties": {
    "gn:admin1_code":"45.0",
    "gn:asciiname":"Alashayka",
    "gn:country_code":"RU",
    "gn:dem":130,
    "gn:feature_class":"P",
    "gn:feature_code":"PPL",
    "gn:name":"Alashayka",
    "gn:population":0,
    "gn:timezone":"Europe/Moscow",
    "iso:country":"RU",
    "name:eng_x_preferred":[
        "Alashayka"
    ],
    "name:nor_x_preferred":[
        "Alasjajka"
    ],
    "name:rus_x_preferred":[
        "\u0410\u043b\u0430\u0448\u0430\u0439\u043a\u0430"
    ],
    "name:und_x_variant":[
        "Verkhnyaya Alashayka",
        "Alshayka",
        "\u0410\u043b\u0430\u0448\u0430\u0439\u043a\u0430",
        "Alashayka"
    ],
    "wof:name":"Alashayka",
    "wof:placetype":"locality"
},
  "geometry": {"coordinates":[49.49100000000001,56.7746],"type":"Point"}
}