{
  "type": "Feature",
  "properties": {
    "gn:admin1_code":"75",
    "gn:asciiname":"Novyy Trud",
    "gn:country_code":"RU",
    "gn:dem":164,
    "gn:feature_class":"P",
    "gn:feature_code":"PPL",
    "gn:name":"Novyy Trud",
    "gn:population":0,
    "gn:timezone":"Asia/Tomsk",
    "iso:country":"RU",
    "name:eng_x_preferred":[
        "Novyy Trud"
    ],
    "name:nor_x_preferred":[
        "Novyj Trud"
    ],
    "name:rus_x_preferred":[
        "\u041d\u043e\u0432\u044b\u0439 \u0422\u0440\u0443\u0434"
    ],
    "name:und_x_variant":[
        "\u041d\u043e\u0432\u044b\u0439 \u0422\u0440\u0443\u0434",
        "Novyy Trud"
    ],
    "wof:name":"Novyy Trud",
    "wof:placetype":"locality"
},
  "geometry": {"coordinates":[88.00360999999999,57.42778000000001],"type":"Point"}
}