{
  "type": "Feature",
  "properties": {
    "gn:admin1_code":"24",
    "gn:asciiname":"Syangerdyk",
    "gn:cc2":"RU",
    "gn:country_code":"RU",
    "gn:dem":6,
    "gn:feature_class":"P",
    "gn:feature_code":"PPL",
    "gn:name":"Syangerdyk",
    "gn:population":0,
    "gn:timezone":"Europe/Volgograd",
    "iso:country":"RU",
    "name:und_x_variant":[
        "Syangertsy",
        "Syangerdyk"
    ],
    "wof:name":"Syangerdyk",
    "wof:placetype":"locality"
},
  "geometry": {"coordinates":[44.90611,48.15806],"type":"Point"}
}