{
  "type": "Feature",
  "properties": {
    "gn:admin1_code":"85",
    "gn:asciiname":"Kushnikova",
    "gn:cc2":"RU",
    "gn:country_code":"RU",
    "gn:dem":171,
    "gn:feature_class":"P",
    "gn:feature_code":"PPL",
    "gn:name":"Kushnikova",
    "gn:population":0,
    "gn:timezone":"Europe/Moscow",
    "iso:country":"RU",
    "name:rus_x_preferred":[
        "\u041a\u0443\u0448\u043d\u0438\u043a\u043e\u0432\u0430"
    ],
    "name:und_x_variant":[
        "Kushnikovo",
        "Kushnikova"
    ],
    "wof:name":"Kushnikova",
    "wof:placetype":"locality"
},
  "geometry": {"coordinates":[39.88333,60.48333],"type":"Point"}
}