{
  "type": "Feature",
  "properties": {
    "gn:admin1_code":"60.0",
    "gn:asciiname":"Dubonovichi",
    "gn:country_code":"RU",
    "gn:dem":71,
    "gn:feature_class":"P",
    "gn:feature_code":"PPL",
    "gn:name":"Dubonovichi",
    "gn:population":0,
    "gn:timezone":"Europe/Moscow",
    "iso:country":"RU",
    "name:eng_x_preferred":[
        "Dubonovichi"
    ],
    "name:nor_x_preferred":[
        "Dubonovitsji"
    ],
    "name:rus_x_preferred":[
        "\u0414\u0443\u0431\u043e\u043d\u043e\u0432\u0438\u0447\u0438"
    ],
    "name:und_x_variant":[
        "Dubanovichi"
    ],
    "wof:name":"Dubonovichi",
    "wof:placetype":"locality"
},
  "geometry": {"coordinates":[28.829,57.8567],"type":"Point"}
}