{
  "type": "Feature",
  "properties": {
    "gn:admin1_code":"91.0",
    "gn:asciiname":"Ozernaya",
    "gn:country_code":"RU",
    "gn:dem":69,
    "gn:feature_class":"P",
    "gn:feature_code":"PPL",
    "gn:name":"Oz\u00ebrnaya",
    "gn:population":0,
    "gn:timezone":"Asia/Krasnoyarsk",
    "iso:country":"RU",
    "name:rus_x_preferred":[
        "\u041e\u0437\u0451\u0440\u043d\u0430\u044f"
    ],
    "name:und_x_variant":[
        "Oz\u00ebrnaya"
    ],
    "wof:name":"Ozernaya",
    "wof:placetype":"locality"
},
  "geometry": {"coordinates":[92.0714,58.4726],"type":"Point"}
}