{
  "type": "Feature",
  "properties": {
    "gn:admin1_code":"77",
    "gn:asciiname":"Stogovo",
    "gn:country_code":"RU",
    "gn:dem":144,
    "gn:feature_class":"P",
    "gn:feature_code":"PPL",
    "gn:name":"Stogovo",
    "gn:population":0,
    "gn:timezone":"Europe/Moscow",
    "iso:country":"RU",
    "name:aze_x_preferred":[
        "Stoqovo"
    ],
    "name:bul_x_preferred":[
        "\u0421\u0442\u043e\u0433\u043e\u0432\u043e"
    ],
    "name:fra_x_preferred":[
        "Stogovo"
    ],
    "name:hrv_x_preferred":[
        "Stogovo"
    ],
    "name:hye_x_preferred":[
        "\u054d\u057f\u0578\u0563\u0578\u057e\u0578"
    ],
    "name:kat_x_preferred":[
        "\u10e1\u10e2\u10dd\u10d2\u10dd\u10d5\u10dd"
    ],
    "name:mkd_x_preferred":[
        "\u0421\u0442\u043e\u0433\u043e\u0432\u043e"
    ],
    "name:myv_x_preferred":[
        "\u0421\u0442\u043e\u0433\u043e\u0432\u043e"
    ],
    "name:nno_x_preferred":[
        "Stogovo"
    ],
    "name:pol_x_preferred":[
        "Stogowo"
    ],
    "name:rus_x_preferred":[
        "\u0421\u0442\u043e\u0433\u043e\u0432\u043e"
    ],
    "name:sqi_x_preferred":[
        "Stogovo"
    ],
    "name:srp_x_preferred":[
        "\u0421\u0442\u043e\u0433\u043e\u0432\u043e"
    ],
    "name:swa_x_preferred":[
        "Stogovo"
    ],
    "name:ukr_x_preferred":[
        "\u0421\u0442\u043e\u0433\u043e\u0432\u043e"
    ],
    "name:und_x_variant":[
        "Uzmeni"
    ],
    "wof:name":"Stogovo",
    "wof:placetype":"locality"
},
  "geometry": {"coordinates":[36.52584,57.89298],"type":"Point"}
}