{
  "type": "Feature",
  "properties": {
    "gn:admin1_code":"77",
    "gn:asciiname":"Stogovo",
    "gn:country_code":"RU",
    "gn:dem":144,
    "gn:feature_class":"P",
    "gn:feature_code":"PPL",
    "gn:name":"Stogovo",
    "gn:population":0,
    "gn:timezone":"Europe/Moscow",
    "iso:country":"RU",
    "name:rus_x_preferred":[
        "\u0421\u0442\u043e\u0433\u043e\u0432\u043e"
    ],
    "name:und_x_variant":[
        "Uzmeni",
        "Stogovo",
        "\u0421\u0442\u043e\u0433\u043e\u0432\u043e"
    ],
    "wof:name":"Stogovo",
    "wof:placetype":"locality"
},
  "geometry": {"coordinates":[36.52584,57.89298],"type":"Point"}
}