{
  "type": "Feature",
  "properties": {
    "gn:admin1_code":"85",
    "gn:asciiname":"D'yakonovskoye",
    "gn:country_code":"RU",
    "gn:dem":124,
    "gn:feature_class":"P",
    "gn:feature_code":"PPL",
    "gn:name":"D\u2019yakonovskoye",
    "gn:population":0,
    "gn:timezone":"Europe/Moscow",
    "iso:country":"RU",
    "name:rus_x_preferred":[
        "\u0414\u044c\u044f\u043a\u043e\u043d\u043e\u0432\u0441\u043a\u043e\u0435"
    ],
    "name:und_x_variant":[
        "D\u2019yakonovskoye",
        "\u0414\u044c\u044f\u043a\u043e\u043d\u043e\u0432\u0441\u043a\u043e\u0435"
    ],
    "wof:name":"D'yakonovskoye",
    "wof:placetype":"locality"
},
  "geometry": {"coordinates":[38.40995,59.25955],"type":"Point"}
}