{
  "type": "Feature",
  "properties": {
    "gn:admin1_code":"72.0",
    "gn:asciiname":"Pervoye Maya",
    "gn:country_code":"RU",
    "gn:dem":169,
    "gn:feature_class":"P",
    "gn:feature_code":"PPL",
    "gn:name":"Pervoye Maya",
    "gn:population":0,
    "gn:timezone":"Europe/Moscow",
    "iso:country":"RU",
    "name:ceb_x_preferred":[
        "Pervoye Maya"
    ],
    "name:swe_x_preferred":[
        "Pervoye Maya"
    ],
    "wof:name":"Pervoye Maya",
    "wof:placetype":"locality"
},
  "geometry": {"coordinates":[41.24694,51.90139],"type":"Point"}
}