{
  "type": "Feature",
  "properties": {
    "gn:admin1_code":"10",
    "gn:asciiname":"Klubnichnyy",
    "gn:country_code":"RU",
    "gn:dem":166,
    "gn:feature_class":"P",
    "gn:feature_code":"PPL",
    "gn:name":"Klubnichnyy",
    "gn:population":0,
    "gn:timezone":"Europe/Moscow",
    "iso:country":"RU",
    "name:rus_x_preferred":[
        "\u041a\u043b\u0443\u0431\u043d\u0438\u0447\u043d\u044b\u0439"
    ],
    "name:und_x_variant":[
        "Svyatets",
        "Klubnichnyy"
    ],
    "wof:name":"Klubnichnyy",
    "wof:placetype":"locality"
},
  "geometry": {"coordinates":[32.14850999999999,52.68111],"type":"Point"}
}