{
  "type": "Feature",
  "properties": {
    "gn:admin1_code":"51",
    "gn:asciiname":"Ionovo",
    "gn:country_code":"RU",
    "gn:dem":140,
    "gn:feature_class":"P",
    "gn:feature_code":"PPL",
    "gn:name":"Ionovo",
    "gn:population":0,
    "gn:timezone":"Europe/Moscow",
    "iso:country":"RU",
    "name:eng_x_preferred":[
        "Ionovo"
    ],
    "name:nor_x_preferred":[
        "Ionovo"
    ],
    "name:rus_x_preferred":[
        "\u0418\u043e\u043d\u043e\u0432\u043e"
    ],
    "name:und_x_variant":[
        "\u0418\u043e\u043d\u043e\u0432\u043e",
        "Ionovo"
    ],
    "wof:name":"Ionovo",
    "wof:placetype":"locality"
},
  "geometry": {"coordinates":[45.2216,57.84032],"type":"Point"}
}