{
  "type": "Feature",
  "properties": {
    "gn:admin1_code":"47",
    "gn:asciiname":"Nekrasovo",
    "gn:cc2":"RU",
    "gn:country_code":"RU",
    "gn:dem":251,
    "gn:feature_class":"P",
    "gn:feature_code":"PPL",
    "gn:name":"Nekrasovo",
    "gn:population":0,
    "gn:timezone":"Europe/Moscow",
    "iso:country":"RU",
    "name:che_x_preferred":[
        "\u041d\u0435\u043a\u0440\u0430\u0441\u043e\u0432\u043e"
    ],
    "name:rus_x_preferred":[
        "\u041d\u0435\u043a\u0440\u0430\u0441\u043e\u0432\u043e"
    ],
    "name:und_x_variant":[
        "Krasiki",
        "Nekrasovo"
    ],
    "wof:name":"Nekrasovo",
    "wof:placetype":"locality"
},
  "geometry": {"coordinates":[35.35917,55.4475],"type":"Point"}
}