{
  "type": "Feature",
  "properties": {
    "gn:admin1_code":"51",
    "gn:asciiname":"Markovo",
    "gn:country_code":"RU",
    "gn:dem":117,
    "gn:feature_class":"P",
    "gn:feature_code":"PPL",
    "gn:name":"Markovo",
    "gn:population":0,
    "gn:timezone":"Europe/Moscow",
    "iso:country":"RU",
    "name:eng_x_preferred":[
        "Markovo"
    ],
    "name:nor_x_preferred":[
        "Markovo"
    ],
    "name:rus_x_preferred":[
        "\u041c\u0430\u0440\u043a\u043e\u0432\u043e"
    ],
    "name:und_x_variant":[
        "\u041c\u0430\u0440\u043a\u043e\u0432\u043e",
        "Markovo"
    ],
    "wof:name":"Markovo",
    "wof:placetype":"locality"
},
  "geometry": {"coordinates":[43.89539,57.18724],"type":"Point"}
}