{
  "type": "Feature",
  "properties": {
    "gn:admin1_code":"77",
    "gn:asciiname":"Artemovo",
    "gn:country_code":"RU",
    "gn:dem":137,
    "gn:feature_class":"P",
    "gn:feature_code":"PPL",
    "gn:name":"Artemovo",
    "gn:population":0,
    "gn:timezone":"Europe/Moscow",
    "iso:country":"RU",
    "name:rus_x_preferred":[
        "\u0410\u0440\u0442\u0435\u043c\u043e\u0432\u043e"
    ],
    "wof:name":"Artemovo",
    "wof:placetype":"locality"
},
  "geometry": {"coordinates":[37.5356,57.2473],"type":"Point"}
}