{
  "type": "Feature",
  "properties": {
    "gn:admin1_code":"56.0",
    "gn:asciiname":"Azarovka",
    "gn:country_code":"RU",
    "gn:dem":193,
    "gn:feature_class":"P",
    "gn:feature_code":"PPL",
    "gn:name":"Azarovka",
    "gn:population":0,
    "gn:timezone":"Europe/Moscow",
    "iso:country":"RU",
    "name:nor_x_preferred":[
        "Azarovka"
    ],
    "name:rus_x_preferred":[
        "\u0410\u0437\u0430\u0440\u043e\u0432\u043a\u0430"
    ],
    "wof:name":"Azarovka",
    "wof:placetype":"locality"
},
  "geometry": {"coordinates":[36.18368,52.73138],"type":"Point"}
}