{
  "type": "Feature",
  "properties": {
    "gn:admin1_code":"52",
    "gn:asciiname":"Malyye Vyazhishchi",
    "gn:country_code":"RU",
    "gn:dem":57,
    "gn:feature_class":"P",
    "gn:feature_code":"PPL",
    "gn:name":"Malyye Vyazhishchi",
    "gn:population":0,
    "gn:timezone":"Europe/Moscow",
    "iso:country":"RU",
    "name:rus_x_preferred":[
        "\u041c\u0430\u043b\u044b\u0435 \u0412\u044f\u0436\u0438\u0449\u0438"
    ],
    "wof:name":"Malyye Vyazhishchi",
    "wof:placetype":"locality"
},
  "geometry": {"coordinates":[31.83333,58.85],"type":"Point"}
}