{
  "type": "Feature",
  "properties": {
    "gn:admin1_code":"45.0",
    "gn:asciiname":"Poselok Kuz'mino",
    "gn:country_code":"RU",
    "gn:dem":80,
    "gn:feature_class":"P",
    "gn:feature_code":"PPL",
    "gn:name":"Pos\u00eblok Kuz\u2019mino",
    "gn:population":0,
    "gn:timezone":"Europe/Moscow",
    "iso:country":"RU",
    "name:rus_x_preferred":[
        "\u041f\u043e\u0441\u0451\u043b\u043e\u043a \u041a\u0443\u0437\u044c\u043c\u0438\u043d\u043e"
    ],
    "name:und_x_variant":[
        "Pos\u00eblok Kuz\u2019mino"
    ],
    "wof:name":"Poselok Kuz'mino",
    "wof:placetype":"locality"
},
  "geometry": {"coordinates":[46.0391,56.7986],"type":"Point"}
}