{
  "type": "Feature",
  "properties": {
    "gn:admin1_code":"40",
    "gn:asciiname":"Borovskoye",
    "gn:country_code":"RU",
    "gn:dem":77,
    "gn:feature_class":"P",
    "gn:feature_code":"PPL",
    "gn:name":"Borovskoye",
    "gn:population":0,
    "gn:timezone":"Asia/Yekaterinburg",
    "iso:country":"RU",
    "name:eng_x_preferred":[
        "Borovskoye"
    ],
    "name:nor_x_preferred":[
        "Borovskoje"
    ],
    "name:rus_x_preferred":[
        "\u0411\u043e\u0440\u043e\u0432\u0441\u043a\u043e\u0435"
    ],
    "name:und_x_variant":[
        "\u0411\u043e\u0440\u043e\u0432\u0441\u043a\u043e\u0435",
        "Borovskoye"
    ],
    "wof:name":"Borovskoye",
    "wof:placetype":"locality"
},
  "geometry": {"coordinates":[65.7525,55.80028000000001],"type":"Point"}
}