{
  "type": "Feature",
  "properties": {
    "gn:admin1_code":"40",
    "gn:asciiname":"Achikul'",
    "gn:country_code":"RU",
    "gn:dem":68,
    "gn:feature_class":"P",
    "gn:feature_code":"PPL",
    "gn:name":"Achikul\u2019",
    "gn:population":0,
    "gn:timezone":"Asia/Yekaterinburg",
    "iso:country":"RU",
    "name:eng_x_preferred":[
        "Achikul'"
    ],
    "name:nor_x_preferred":[
        "Atsjikul"
    ],
    "name:rus_x_preferred":[
        "\u0410\u0447\u0438\u043a\u0443\u043b\u044c"
    ],
    "name:und_x_variant":[
        "Anikul\u2019",
        "\u0410\u0447\u0438\u043a\u0443\u043b\u044c",
        "Achikul\u2019"
    ],
    "wof:name":"Achikul'",
    "wof:placetype":"locality"
},
  "geometry": {"coordinates":[65.485,55.75278],"type":"Point"}
}