{
  "type": "Feature",
  "properties": {
    "gn:admin1_code":"37",
    "gn:asciiname":"Il'ina",
    "gn:country_code":"RU",
    "gn:dem":201,
    "gn:feature_class":"P",
    "gn:feature_code":"PPL",
    "gn:name":"Il\u2019ina",
    "gn:population":0,
    "gn:timezone":"Europe/Moscow",
    "iso:country":"RU",
    "name:rus_x_preferred":[
        "\u0418\u043b\u044c\u0438\u043d\u0430"
    ],
    "name:und_x_variant":[
        "Il\u2019ina",
        "\u0418\u043b\u044c\u0438\u043d\u0430"
    ],
    "wof:name":"Il'ina",
    "wof:placetype":"locality"
},
  "geometry": {"coordinates":[42.28333,58.26667],"type":"Point"}
}