{
  "type": "Feature",
  "properties": {
    "gn:admin1_code":"88",
    "gn:asciiname":"Dubetskaya Dacha",
    "gn:country_code":"RU",
    "gn:dem":109,
    "gn:feature_class":"P",
    "gn:feature_code":"PPL",
    "gn:name":"Dubetskaya Dacha",
    "gn:population":0,
    "gn:timezone":"Europe/Moscow",
    "iso:country":"RU",
    "name:rus_x_preferred":[
        "\u0414\u0443\u0431\u0435\u0446\u043a\u0430\u044f \u0414\u0430\u0447\u0430"
    ],
    "name:und_x_variant":[
        "\u0414\u0443\u0431\u0435\u0446\u043a\u0430\u044f \u0414\u0430\u0447\u0430"
    ],
    "wof:name":"Dubetskaya Dacha",
    "wof:placetype":"locality"
},
  "geometry": {"coordinates":[38.20553,58.22384],"type":"Point"}
}