{
  "type": "Feature",
  "properties": {
    "gn:admin1_code":"21",
    "gn:asciiname":"Bol'shoye Bolsovo",
    "gn:country_code":"RU",
    "gn:dem":117,
    "gn:feature_class":"P",
    "gn:feature_code":"PPL",
    "gn:name":"Bol\u2019shoye Bolsovo",
    "gn:population":0,
    "gn:timezone":"Europe/Moscow",
    "iso:country":"RU",
    "name:rus_x_preferred":[
        "\u0411\u043e\u043b\u044c\u0448\u043e\u0435 \u0411\u043e\u043b\u0441\u043e\u0432\u043e"
    ],
    "name:und_x_variant":[
        "Bol\u2019shoye Bolovo",
        "Bol\u2019shoye Bolsovo"
    ],
    "wof:name":"Bol'shoye Bolsovo",
    "wof:placetype":"locality"
},
  "geometry": {"coordinates":[40.74736,56.80529],"type":"Point"}
}