{
  "type": "Feature",
  "properties": {
    "gn:admin1_code":"29.0",
    "gn:asciiname":"Afonin Klyuch",
    "gn:country_code":"RU",
    "gn:dem":360,
    "gn:feature_class":"P",
    "gn:feature_code":"PPL",
    "gn:name":"Afonin Klyuch",
    "gn:population":0,
    "gn:timezone":"Asia/Novokuznetsk",
    "iso:country":"RU",
    "name:rus_x_preferred":[
        "\u0410\u0444\u043e\u043d\u0438\u043d \u041a\u043b\u044e\u0447"
    ],
    "wof:name":"Afonin Klyuch",
    "wof:placetype":"locality"
},
  "geometry": {"coordinates":[86.5985,53.7591],"type":"Point"}
}