{
  "type": "Feature",
  "properties": {
    "gn:admin1_code":"6",
    "gn:asciiname":"Novgorodova",
    "gn:country_code":"RU",
    "gn:dem":149,
    "gn:feature_class":"P",
    "gn:feature_code":"PPL",
    "gn:name":"Novgorodova",
    "gn:population":0,
    "gn:timezone":"Europe/Moscow",
    "iso:country":"RU",
    "name:rus_x_preferred":[
        "\u041d\u043e\u0432\u0433\u043e\u0440\u043e\u0434\u043e\u0432\u0430"
    ],
    "name:und_x_variant":[
        "\u041d\u043e\u0432\u0433\u043e\u0440\u043e\u0434\u043e\u0432\u0430"
    ],
    "wof:name":"Novgorodova",
    "wof:placetype":"locality"
},
  "geometry": {"coordinates":[38.7651,61.62956],"type":"Point"}
}