{
  "type": "Feature",
  "properties": {
    "gn:admin1_code":"21",
    "gn:asciiname":"Lupolovo",
    "gn:country_code":"RU",
    "gn:dem":104,
    "gn:feature_class":"P",
    "gn:feature_code":"PPL",
    "gn:name":"Lupolovo",
    "gn:population":0,
    "gn:timezone":"Europe/Moscow",
    "iso:country":"RU",
    "name:nor_x_preferred":[
        "Lupolovo"
    ],
    "name:rus_x_preferred":[
        "\u041b\u0443\u043f\u043e\u043b\u043e\u0432\u043e"
    ],
    "name:und_x_variant":[
        "Lupulova"
    ],
    "wof:name":"Lupolovo",
    "wof:placetype":"locality"
},
  "geometry": {"coordinates":[42.70168,56.56381999999999],"type":"Point"}
}