{
  "type": "Feature",
  "properties": {
    "gn:admin1_code":"60",
    "gn:asciiname":"Ogorodtsy",
    "gn:country_code":"RU",
    "gn:dem":147,
    "gn:feature_class":"P",
    "gn:feature_code":"PPL",
    "gn:name":"Ogorodtsy",
    "gn:population":0,
    "gn:timezone":"Europe/Moscow",
    "iso:country":"RU",
    "name:eng_x_preferred":[
        "Ogorodtsy"
    ],
    "name:nor_x_preferred":[
        "Ogorodtsy"
    ],
    "name:rus_x_preferred":[
        "\u041e\u0433\u043e\u0440\u043e\u0434\u0446\u044b"
    ],
    "wof:name":"Ogorodtsy",
    "wof:placetype":"locality"
},
  "geometry": {"coordinates":[31.05948,56.42559],"type":"Point"}
}