{
  "type": "Feature",
  "properties": {
    "gn:admin1_code":"10",
    "gn:asciiname":"Kurgany",
    "gn:country_code":"RU",
    "gn:dem":140,
    "gn:feature_class":"P",
    "gn:feature_code":"PPL",
    "gn:name":"Kurgany",
    "gn:population":0,
    "gn:timezone":"Europe/Moscow",
    "iso:country":"RU",
    "name:rus_x_preferred":[
        "\u041a\u0443\u0440\u0433\u0430\u043d\u044b"
    ],
    "name:und_x_variant":[
        "\u041a\u0443\u0440\u0433\u0430\u043d\u044b"
    ],
    "wof:name":"Kurgany",
    "wof:placetype":"locality"
},
  "geometry": {"coordinates":[32.10420999999999,52.13815],"type":"Point"}
}