{
  "type": "Feature",
  "properties": {
    "gn:admin1_code":"8",
    "gn:asciiname":"Gusevka",
    "gn:country_code":"RU",
    "gn:dem":264,
    "gn:feature_class":"P",
    "gn:feature_code":"PPL",
    "gn:name":"Gusevka",
    "gn:population":0,
    "gn:timezone":"Asia/Yekaterinburg",
    "iso:country":"RU",
    "name:rus_x_preferred":[
        "\u0413\u0443\u0441\u0435\u0432\u043a\u0430"
    ],
    "name:und_x_variant":[
        "\u0413\u0443\u0441\u0435\u0432\u043a\u0430"
    ],
    "wof:name":"Gusevka",
    "wof:placetype":"locality"
},
  "geometry": {"coordinates":[58.1019,55.2397],"type":"Point"}
}