{
  "type": "Feature",
  "properties": {
    "gn:admin1_code":"47",
    "gn:asciiname":"Ul'yanovo",
    "gn:country_code":"RU",
    "gn:dem":259,
    "gn:feature_class":"P",
    "gn:feature_code":"PPL",
    "gn:name":"Ul\u2019yanovo",
    "gn:population":0,
    "gn:timezone":"Europe/Moscow",
    "iso:country":"RU",
    "name:und_x_variant":[
        "Ul\u2019yanovo Ploskoye",
        "Ul\u2019yanovo"
    ],
    "wof:name":"Ul'yanovo",
    "wof:placetype":"locality"
},
  "geometry": {"coordinates":[35.42946,55.62134],"type":"Point"}
}