{
  "type": "Feature",
  "properties": {
    "gn:admin1_code":"85",
    "gn:asciiname":"Golenevo",
    "gn:country_code":"RU",
    "gn:dem":174,
    "gn:feature_class":"P",
    "gn:feature_code":"PPL",
    "gn:name":"Golenevo",
    "gn:population":0,
    "gn:timezone":"Europe/Moscow",
    "iso:country":"RU",
    "name:rus_x_preferred":[
        "\u0413\u043e\u043b\u0435\u043d\u0435\u0432\u043e"
    ],
    "wof:name":"Golenevo",
    "wof:placetype":"locality"
},
  "geometry": {"coordinates":[39.9272,59.1098],"type":"Point"}
}