{
  "type": "Feature",
  "properties": {
    "gn:admin1_code":"90.0",
    "gn:asciiname":"Pirogovo",
    "gn:country_code":"RU",
    "gn:dem":196,
    "gn:feature_class":"P",
    "gn:feature_code":"PPL",
    "gn:name":"Pirogovo",
    "gn:population":0,
    "gn:timezone":"Asia/Yekaterinburg",
    "iso:country":"RU",
    "name:rus_x_preferred":[
        "\u041f\u0438\u0440\u043e\u0433\u043e\u0432\u043e"
    ],
    "wof:name":"Pirogovo",
    "wof:placetype":"locality"
},
  "geometry": {"coordinates":[54.8481,58.78],"type":"Point"}
}