{
  "type": "Feature",
  "properties": {
    "gn:admin1_code":"28",
    "gn:asciiname":"Ilmee",
    "gn:country_code":"RU",
    "gn:dem":86,
    "gn:feature_class":"P",
    "gn:feature_code":"PPL",
    "gn:name":"Ilmee",
    "gn:population":0,
    "gn:timezone":"Europe/Moscow",
    "iso:country":"RU",
    "name:fin_x_preferred":[
        "Ilmee"
    ],
    "name:rus_x_preferred":[
        "\u0418\u043b\u044c\u043c\u0435"
    ],
    "name:und_x_variant":[
        "Ilmeye",
        "Il\u2019me"
    ],
    "wof:name":"Ilmee",
    "wof:placetype":"locality"
},
  "geometry": {"coordinates":[29.36695,61.29887],"type":"Point"}
}