{
  "type": "Feature",
  "properties": {
    "gn:admin1_code":"67",
    "gn:asciiname":"Ozerki",
    "gn:country_code":"RU",
    "gn:dem":210,
    "gn:feature_class":"P",
    "gn:feature_code":"PPL",
    "gn:name":"Ozerki",
    "gn:population":0,
    "gn:timezone":"Europe/Saratov",
    "iso:country":"RU",
    "name:bel_x_preferred":[
        "\u0410\u0437\u0451\u0440\u043a\u0456"
    ],
    "name:ceb_x_preferred":[
        "Ozerki"
    ],
    "name:deu_x_preferred":[
        "Oserki"
    ],
    "name:eng_x_preferred":[
        "Ozerki"
    ],
    "name:fra_x_preferred":[
        "Ozerki"
    ],
    "name:hun_x_preferred":[
        "Ozerki"
    ],
    "name:hye_x_preferred":[
        "\u0555\u0566\u0565\u0580\u056f\u056b"
    ],
    "name:nor_x_preferred":[
        "Ozerki"
    ],
    "name:rus_x_preferred":[
        "\u041e\u0437\u0435\u0440\u043a\u0438"
    ],
    "name:ukr_x_preferred":[
        "\u041e\u0437\u0435\u0440\u043a\u0438"
    ],
    "name:und_x_variant":[
        "\u041e\u0437\u0435\u0440\u043a\u0438",
        "Ozerki"
    ],
    "wof:name":"Ozerki",
    "wof:placetype":"locality"
},
  "geometry": {"coordinates":[45.26969,51.53041],"type":"Point"}
}