{
  "type": "Feature",
  "properties": {
    "gn:admin1_code":"46.0",
    "gn:asciiname":"Verkhniy Kivchey",
    "gn:country_code":"RU",
    "gn:dem":195,
    "gn:feature_class":"P",
    "gn:feature_code":"PPL",
    "gn:name":"Verkhniy Kivchey",
    "gn:population":0,
    "gn:timezone":"Europe/Moscow",
    "iso:country":"RU",
    "name:rus_x_preferred":[
        "\u0412\u0435\u0440\u0445\u043d\u0438\u0439 \u041a\u0438\u0432\u0447\u0435\u0439"
    ],
    "wof:name":"Verkhniy Kivchey",
    "wof:placetype":"locality"
},
  "geometry": {"coordinates":[44.33306,54.52294000000001],"type":"Point"}
}