{
  "type": "Feature",
  "properties": {
    "gn:admin1_code":"62",
    "gn:asciiname":"Katagoshcha",
    "gn:country_code":"RU",
    "gn:dem":166,
    "gn:feature_class":"P",
    "gn:feature_code":"PPL",
    "gn:name":"Katagoshcha",
    "gn:population":0,
    "gn:timezone":"Europe/Moscow",
    "iso:country":"RU",
    "name:rus_x_preferred":[
        "\u041a\u0430\u0442\u0430\u0433\u043e\u0449\u0430"
    ],
    "name:und_x_variant":[
        "Kotogoshch",
        "Katogoshch",
        "Katagoshcha",
        "Katogoshcha"
    ],
    "wof:name":"Katagoshcha",
    "wof:placetype":"locality"
},
  "geometry": {"coordinates":[39.2395,54.3706],"type":"Point"}
}