{
  "type": "Feature",
  "properties": {
    "gn:admin1_code":"60",
    "gn:asciiname":"Olenino",
    "gn:country_code":"RU",
    "gn:dem":129,
    "gn:feature_class":"P",
    "gn:feature_code":"PPL",
    "gn:name":"Olenino",
    "gn:population":0,
    "gn:timezone":"Europe/Moscow",
    "iso:country":"RU",
    "name:rus_x_preferred":[
        "\u041e\u043b\u0435\u043d\u0438\u043d\u043e"
    ],
    "name:und_x_variant":[
        "\u041e\u043b\u0435\u043d\u0438\u043d\u043e"
    ],
    "wof:name":"Olenino",
    "wof:placetype":"locality"
},
  "geometry": {"coordinates":[29.899,56.902],"type":"Point"}
}