{
  "type": "Feature",
  "properties": {
    "gn:admin1_code":"85",
    "gn:asciiname":"Kholuy",
    "gn:country_code":"RU",
    "gn:dem":127,
    "gn:feature_class":"P",
    "gn:feature_code":"PPL",
    "gn:name":"Kholuy",
    "gn:population":0,
    "gn:timezone":"Europe/Moscow",
    "iso:country":"RU",
    "name:eng_x_preferred":[
        "Kholuy"
    ],
    "name:nor_x_preferred":[
        "Kholuj"
    ],
    "name:rus_x_preferred":[
        "\u0425\u043e\u043b\u0443\u0439"
    ],
    "name:und_x_variant":[
        "Kholui",
        "\u0425\u043e\u043b\u0443\u0439",
        "Kholuy"
    ],
    "wof:name":"Kholuy",
    "wof:placetype":"locality"
},
  "geometry": {"coordinates":[40.20878,60.4272],"type":"Point"}
}