{
  "type": "Feature",
  "properties": {
    "gn:admin1_code":"83",
    "gn:asciiname":"Boldinka",
    "gn:country_code":"RU",
    "gn:dem":177,
    "gn:feature_class":"P",
    "gn:feature_code":"PPL",
    "gn:name":"Boldinka",
    "gn:population":0,
    "gn:timezone":"Europe/Moscow",
    "iso:country":"RU",
    "name:rus_x_preferred":[
        "\u0411\u043e\u043b\u0434\u0438\u043d\u043a\u0430"
    ],
    "wof:name":"Boldinka",
    "wof:placetype":"locality"
},
  "geometry": {"coordinates":[39.60923,56.37935],"type":"Point"}
}