{
  "type": "Feature",
  "properties": {
    "gn:admin1_code":"53.0",
    "gn:asciiname":"Stantsiya Zherebtsovo",
    "gn:country_code":"RU",
    "gn:dem":150,
    "gn:feature_class":"P",
    "gn:feature_code":"PPL",
    "gn:name":"Stantsiya Zherebtsovo",
    "gn:population":0,
    "gn:timezone":"Asia/Novosibirsk",
    "iso:country":"RU",
    "name:rus_x_preferred":[
        "\u0421\u0442\u0430\u043d\u0446\u0438\u044f \u0416\u0435\u0440\u0435\u0431\u0446\u043e\u0432\u043e"
    ],
    "name:rus_x_variant":[
        "\u0416\u0435\u0440\u0435\u0431\u0446\u043e\u0432\u043e"
    ],
    "wof:name":"Stantsiya Zherebtsovo",
    "wof:placetype":"locality"
},
  "geometry": {"coordinates":[83.2654,55.0989],"type":"Point"}
}