{
  "type": "Feature",
  "properties": {
    "gn:admin1_code":"77.0",
    "gn:asciiname":"Denesikha",
    "gn:country_code":"RU",
    "gn:dem":235,
    "gn:feature_class":"P",
    "gn:feature_code":"PPL",
    "gn:name":"Denesikha",
    "gn:population":0,
    "gn:timezone":"Europe/Moscow",
    "iso:country":"RU",
    "name:rus_x_preferred":[
        "\u0414\u0435\u043d\u0435\u0441\u0438\u0445\u0430"
    ],
    "name:und_x_variant":[
        "Denisikha",
        "Denesikha",
        "\u0414\u0435\u043d\u0435\u0441\u0438\u0445\u0430"
    ],
    "wof:name":"Denesikha",
    "wof:placetype":"locality"
},
  "geometry": {"coordinates":[34.1965,56.76669],"type":"Point"}
}