{
  "type": "Feature",
  "properties": {
    "gn:admin1_code":"9.0",
    "gn:asciiname":"Slavgorodskoye",
    "gn:country_code":"RU",
    "gn:dem":182,
    "gn:feature_class":"P",
    "gn:feature_code":"PPL",
    "gn:name":"Slavgorodskoye",
    "gn:population":0,
    "gn:timezone":"Europe/Moscow",
    "iso:country":"RU",
    "name:rus_x_preferred":[
        "\u0421\u043b\u0430\u0432\u0433\u043e\u0440\u043e\u0434\u0441\u043a\u043e\u0435"
    ],
    "name:und_x_variant":[
        "Slavogorodskoye"
    ],
    "wof:name":"Slavgorodskoye",
    "wof:placetype":"locality"
},
  "geometry": {"coordinates":[38.8948,50.4764],"type":"Point"}
}