{
  "type": "Feature",
  "properties": {
    "gn:admin1_code":"25",
    "gn:asciiname":"Mezentsevo",
    "gn:country_code":"RU",
    "gn:dem":197,
    "gn:feature_class":"P",
    "gn:feature_code":"PPL",
    "gn:name":"Mezentsevo",
    "gn:population":0,
    "gn:timezone":"Europe/Moscow",
    "iso:country":"RU",
    "name:rus_x_preferred":[
        "\u041c\u0435\u0437\u0435\u043d\u0446\u0435\u0432\u043e"
    ],
    "wof:name":"Mezentsevo",
    "wof:placetype":"locality"
},
  "geometry": {"coordinates":[35.9369,54.40764],"type":"Point"}
}