{
  "type": "Feature",
  "properties": {
    "gn:admin1_code":"60",
    "gn:asciiname":"Turets",
    "gn:country_code":"RU",
    "gn:dem":69,
    "gn:feature_class":"P",
    "gn:feature_code":"PPL",
    "gn:name":"Turets",
    "gn:population":0,
    "gn:timezone":"Europe/Moscow",
    "iso:country":"RU",
    "name:rus_x_preferred":[
        "\u0422\u0443\u0440\u0435\u0446"
    ],
    "wof:name":"Turets",
    "wof:placetype":"locality"
},
  "geometry": {"coordinates":[28.7352,58.5684],"type":"Point"}
}