{
  "type": "Feature",
  "properties": {
    "gn:admin1_code":"45",
    "gn:asciiname":"Opytnoye Pole",
    "gn:country_code":"RU",
    "gn:dem":113,
    "gn:feature_class":"P",
    "gn:feature_code":"PPL",
    "gn:name":"Opytnoye Pole",
    "gn:population":0,
    "gn:timezone":"Europe/Moscow",
    "iso:country":"RU",
    "name:rus_x_preferred":[
        "\u041e\u043f\u044b\u0442\u043d\u043e\u0435 \u041f\u043e\u043b\u0435"
    ],
    "name:und_x_variant":[
        "\u041e\u043f\u044b\u0442\u043d\u043e\u0435 \u041f\u043e\u043b\u0435"
    ],
    "wof:name":"Opytnoye Pole",
    "wof:placetype":"locality"
},
  "geometry": {"coordinates":[47.73386,56.63367],"type":"Point"}
}