{
  "type": "Feature",
  "properties": {
    "gn:admin1_code":"84",
    "gn:asciiname":"Kommunist",
    "gn:cc2":"RU",
    "gn:country_code":"RU",
    "gn:dem":165,
    "gn:feature_class":"P",
    "gn:feature_code":"PPL",
    "gn:name":"Kommunist",
    "gn:population":0,
    "gn:timezone":"Europe/Volgograd",
    "iso:country":"RU",
    "name:hye_x_preferred":[
        "\u053f\u0578\u0574\u0578\u0582\u0576\u056b\u057d\u057f"
    ],
    "name:rus_x_preferred":[
        "\u041a\u043e\u043c\u043c\u0443\u043d\u0438\u0441\u0442"
    ],
    "name:rus_x_variant":[
        "\u0411\u043e\u043b\u044c\u0448\u0435\u0432\u0438\u043a"
    ],
    "name:ukr_x_preferred":[
        "\u0411\u0456\u043b\u044c\u0448\u043e\u0432\u0438\u043a"
    ],
    "name:und_x_variant":[
        "Gukkertal\u2019",
        "Kommunist"
    ],
    "wof:name":"Kommunist",
    "wof:placetype":"locality"
},
  "geometry": {"coordinates":[45.01667,50.98333],"type":"Point"}
}