{
  "type": "Feature",
  "properties": {
    "gn:admin1_code":"43",
    "gn:asciiname":"Vyglyadovka",
    "gn:country_code":"RU",
    "gn:dem":182,
    "gn:feature_class":"P",
    "gn:feature_code":"PPL",
    "gn:name":"Vyglyadovka",
    "gn:population":0,
    "gn:timezone":"Europe/Moscow",
    "iso:country":"RU",
    "name:rus_x_preferred":[
        "\u0412\u044b\u0433\u043b\u044f\u0434\u043e\u0432\u043a\u0430"
    ],
    "wof:name":"Vyglyadovka",
    "wof:placetype":"locality"
},
  "geometry": {"coordinates":[38.7439,52.7853],"type":"Point"}
}