{
  "type": "Feature",
  "properties": {
    "gn:admin1_code":"61",
    "gn:asciiname":"Veselyy Gay",
    "gn:country_code":"RU",
    "gn:dem":36,
    "gn:feature_class":"P",
    "gn:feature_code":"PPL",
    "gn:name":"Ves\u00eblyy Gay",
    "gn:population":0,
    "gn:timezone":"Europe/Moscow",
    "iso:country":"RU",
    "name:rus_x_preferred":[
        "\u0412\u0435\u0441\u0451\u043b\u044b\u0439 \u0413\u0430\u0439"
    ],
    "name:und_x_variant":[
        "Ves\u00eblyy Gay"
    ],
    "wof:name":"Veselyy Gay",
    "wof:placetype":"locality"
},
  "geometry": {"coordinates":[42.3061,47.3403],"type":"Point"}
}