{
  "type": "Feature",
  "properties": {
    "gn:admin1_code":"60",
    "gn:asciiname":"Lovyni",
    "gn:country_code":"RU",
    "gn:dem":47,
    "gn:feature_class":"P",
    "gn:feature_code":"PPL",
    "gn:name":"Lovyni",
    "gn:population":0,
    "gn:timezone":"Europe/Moscow",
    "iso:country":"RU",
    "name:rus_x_preferred":[
        "\u041b\u043e\u0432\u044b\u043d\u0438"
    ],
    "name:und_x_variant":[
        "Lavyn\u2019",
        "Lovyni",
        "\u041b\u043e\u0432\u044b\u043d\u0438"
    ],
    "wof:name":"Lovyni",
    "wof:placetype":"locality"
},
  "geometry": {"coordinates":[28.51379,58.67029],"type":"Point"}
}