{
  "type": "Feature",
  "properties": {
    "gn:admin1_code":"88",
    "gn:asciiname":"Roy",
    "gn:country_code":"RU",
    "gn:dem":126,
    "gn:feature_class":"P",
    "gn:feature_code":"PPL",
    "gn:name":"Roy",
    "gn:population":0,
    "gn:timezone":"Europe/Moscow",
    "iso:country":"RU",
    "name:deu_x_preferred":[
        "Roy"
    ],
    "name:fin_x_preferred":[
        "Roy"
    ],
    "name:nno_x_preferred":[
        "Roy"
    ],
    "name:nor_x_preferred":[
        "Roy"
    ],
    "name:rus_x_preferred":[
        "\u0420\u043e\u0439"
    ],
    "name:swe_x_preferred":[
        "Roy"
    ],
    "name:und_x_variant":[
        "\u0420\u043e\u0439"
    ],
    "wof:name":"Roy",
    "wof:placetype":"locality"
},
  "geometry": {"coordinates":[38.0703,58.1549],"type":"Point"}
}