{
  "type": "Feature",
  "properties": {
    "gn:admin1_code":"63",
    "gn:asciiname":"Sulgachchy",
    "gn:country_code":"RU",
    "gn:dem":140,
    "gn:feature_class":"P",
    "gn:feature_code":"PPL",
    "gn:name":"Sulgachchy",
    "gn:population":0,
    "gn:timezone":"Asia/Yakutsk",
    "iso:country":"RU",
    "name:che_x_preferred":[
        "\u0421\u0443\u043b\u0433\u0430\u0447\u0447\u044b"
    ],
    "name:eng_x_preferred":[
        "Sulgachchy"
    ],
    "name:nor_x_preferred":[
        "Sulgatsjtsjy"
    ],
    "name:rus_x_preferred":[
        "\u0421\u0443\u043b\u0433\u0430\u0447\u0447\u044b"
    ],
    "name:sah_x_preferred":[
        "\u0421\u0443\u043b\u0495\u0430\u0447\u0447\u044b"
    ],
    "name:ukr_x_preferred":[
        "\u0421\u0443\u043b\u0433\u0430\u0447\u0447\u0438"
    ],
    "name:und_x_variant":[
        "Sulgachi",
        "Sul\u2019gochin",
        "Sumachi",
        "Sul\u2019gachinskaya",
        "\u0421\u0443\u043b\u0433\u0430\u0447\u0447\u044b",
        "Sulgachchy"
    ],
    "wof:name":"Sulgachchy",
    "wof:placetype":"locality"
},
  "geometry": {"coordinates":[132.90491,61.53809],"type":"Point"}
}