{
  "type": "Feature",
  "properties": {
    "gn:admin1_code":"69",
    "gn:asciiname":"Strigino",
    "gn:country_code":"RU",
    "gn:dem":200,
    "gn:feature_class":"P",
    "gn:feature_code":"PPL",
    "gn:name":"Strigino",
    "gn:population":0,
    "gn:timezone":"Europe/Moscow",
    "iso:country":"RU",
    "name:eng_x_preferred":[
        "Strigino"
    ],
    "name:nor_x_preferred":[
        "Strigino"
    ],
    "name:rus_x_preferred":[
        "\u0421\u0442\u0440\u0438\u0433\u0438\u043d\u043e"
    ],
    "wof:name":"Strigino",
    "wof:placetype":"locality"
},
  "geometry": {"coordinates":[32.66332,54.44357],"type":"Point"}
}