{
  "type": "Feature",
  "properties": {
    "gn:admin1_code":"77",
    "gn:asciiname":"Lasheri",
    "gn:country_code":"RU",
    "gn:dem":208,
    "gn:feature_class":"P",
    "gn:feature_code":"PPL",
    "gn:name":"Lasheri",
    "gn:population":0,
    "gn:timezone":"Europe/Moscow",
    "iso:country":"RU",
    "name:rus_x_preferred":[
        "\u041b\u0430\u0448\u0435\u0440\u0438"
    ],
    "name:und_x_variant":[
        "\u041b\u0430\u0448\u0435\u0440\u0438"
    ],
    "wof:name":"Lasheri",
    "wof:placetype":"locality"
},
  "geometry": {"coordinates":[31.82844,56.53178000000001],"type":"Point"}
}