{
  "type": "Feature",
  "properties": {
    "gn:admin1_code":"33.0",
    "gn:asciiname":"Samsony",
    "gn:country_code":"RU",
    "gn:dem":92,
    "gn:feature_class":"P",
    "gn:feature_code":"PPL",
    "gn:name":"Samsony",
    "gn:population":0,
    "gn:timezone":"Europe/Kirov",
    "iso:country":"RU",
    "name:rus_x_preferred":[
        "\u0421\u0430\u043c\u0441\u043e\u043d\u044b"
    ],
    "wof:name":"Samsony",
    "wof:placetype":"locality"
},
  "geometry": {"coordinates":[48.07809,57.56041999999999],"type":"Point"}
}