{
  "type": "Feature",
  "properties": {
    "gn:admin1_code":"33.0",
    "gn:asciiname":"Sedel'nikovy",
    "gn:country_code":"RU",
    "gn:dem":193,
    "gn:feature_class":"P",
    "gn:feature_code":"PPL",
    "gn:name":"Sedel\u2019nikovy",
    "gn:population":0,
    "gn:timezone":"Europe/Kirov",
    "iso:country":"RU",
    "name:rus_x_preferred":[
        "\u0421\u0435\u0434\u0435\u043b\u044c\u043d\u0438\u043a\u043e\u0432\u044b"
    ],
    "name:und_x_variant":[
        "Sedel\u2019nikovy"
    ],
    "wof:name":"Sedel'nikovy",
    "wof:placetype":"locality"
},
  "geometry": {"coordinates":[48.46583,59.20861],"type":"Point"}
}