{
  "type": "Feature",
  "properties": {
    "gn:admin1_code":"76",
    "gn:asciiname":"Krasnaya Zar'ya",
    "gn:country_code":"RU",
    "gn:dem":257,
    "gn:feature_class":"P",
    "gn:feature_code":"PPL",
    "gn:name":"Krasnaya Zar\u2019ya",
    "gn:population":0,
    "gn:timezone":"Europe/Moscow",
    "iso:country":"RU",
    "name:rus_x_preferred":[
        "\u041a\u0440\u0430\u0441\u043d\u0430\u044f \u0417\u0430\u0440\u044c\u044f"
    ],
    "name:und_x_variant":[
        "Krasnaya Zar\u2019ya",
        "\u041a\u0440\u0430\u0441\u043d\u0430\u044f \u0417\u0430\u0440\u044c\u044f"
    ],
    "wof:name":"Krasnaya Zar'ya",
    "wof:placetype":"locality"
},
  "geometry": {"coordinates":[36.93444,54.20083],"type":"Point"}
}