{
  "type": "Feature",
  "properties": {
    "gn:admin1_code":"45.0",
    "gn:asciiname":"Bol'shoy Shaplak",
    "gn:country_code":"RU",
    "gn:dem":96,
    "gn:feature_class":"P",
    "gn:feature_code":"PPL",
    "gn:name":"Bol\u2019shoy Shaplak",
    "gn:population":0,
    "gn:timezone":"Europe/Moscow",
    "iso:country":"RU",
    "name:rus_x_preferred":[
        "\u0411\u043e\u043b\u044c\u0448\u043e\u0439 \u0428\u0430\u043f\u043b\u0430\u043a"
    ],
    "name:und_x_variant":[
        "Bol\u2019shoy Shaplak",
        "\u0411\u043e\u043b\u044c\u0448\u043e\u0439 \u0428\u0430\u043f\u043b\u0430\u043a"
    ],
    "wof:name":"Bol'shoy Shaplak",
    "wof:placetype":"locality"
},
  "geometry": {"coordinates":[47.90474,56.71101],"type":"Point"}
}