{
  "type": "Feature",
  "properties": {
    "gn:admin1_code":"91.0",
    "gn:asciiname":"Sosnovoye Ozero",
    "gn:country_code":"RU",
    "gn:dem":193,
    "gn:feature_class":"P",
    "gn:feature_code":"PPL",
    "gn:name":"Sosnovoye Ozero",
    "gn:population":0,
    "gn:timezone":"Asia/Krasnoyarsk",
    "iso:country":"RU",
    "name:rus_x_preferred":[
        "\u0421\u043e\u0441\u043d\u043e\u0432\u043e\u0435 \u041e\u0437\u0435\u0440\u043e"
    ],
    "wof:name":"Sosnovoye Ozero",
    "wof:placetype":"locality"
},
  "geometry": {"coordinates":[90.4517,56.3082],"type":"Point"}
}