{
  "type": "Feature",
  "properties": {
    "gn:admin1_code":"63",
    "gn:asciiname":"Taaktir",
    "gn:cc2":"RU",
    "gn:country_code":"RU",
    "gn:dem":489,
    "gn:feature_class":"P",
    "gn:feature_code":"PPL",
    "gn:name":"Taaktir",
    "gn:population":0,
    "gn:timezone":"Asia/Yakutsk",
    "iso:country":"RU",
    "name:und_x_variant":[
        "Tayaktir\u2019",
        "Taaktir"
    ],
    "wof:name":"Taaktir",
    "wof:placetype":"locality"
},
  "geometry": {"coordinates":[130.01667,67.09999999999999],"type":"Point"}
}