{
  "type": "Feature",
  "properties": {
    "gn:admin1_code":"67",
    "gn:asciiname":"Varfolomeyevka",
    "gn:country_code":"RU",
    "gn:dem":22,
    "gn:feature_class":"P",
    "gn:feature_code":"PPL",
    "gn:name":"Varfolomeyevka",
    "gn:population":0,
    "gn:timezone":"Europe/Saratov",
    "iso:country":"RU",
    "name:eng_x_preferred":[
        "Varfolomeyevka"
    ],
    "name:nor_x_preferred":[
        "Varfolomejevka"
    ],
    "name:rus_x_preferred":[
        "\u0412\u0430\u0440\u0444\u043e\u043b\u043e\u043c\u0435\u0435\u0432\u043a\u0430"
    ],
    "name:und_x_variant":[
        "Vorfolomeyevka",
        "Varfolomeyevka"
    ],
    "wof:name":"Varfolomeyevka",
    "wof:placetype":"locality"
},
  "geometry": {"coordinates":[48.19121,50.01881],"type":"Point"}
}