{
  "type": "Feature",
  "properties": {
    "gn:admin1_code":"62",
    "gn:asciiname":"Moseyevo",
    "gn:country_code":"RU",
    "gn:dem":120,
    "gn:feature_class":"P",
    "gn:feature_code":"PPL",
    "gn:name":"Moseyevo",
    "gn:population":0,
    "gn:timezone":"Europe/Moscow",
    "iso:country":"RU",
    "name:rus_x_preferred":[
        "\u041c\u043e\u0441\u0435\u0435\u0432\u043e"
    ],
    "name:und_x_variant":[
        "Matveyevo",
        "Moseyevo",
        "\u041c\u043e\u0441\u0435\u0435\u0432\u043e"
    ],
    "wof:name":"Moseyevo",
    "wof:placetype":"locality"
},
  "geometry": {"coordinates":[39.92422,55.17182],"type":"Point"}
}