{
  "type": "Feature",
  "properties": {
    "gn:admin1_code":"57",
    "gn:asciiname":"Lenino",
    "gn:country_code":"RU",
    "gn:dem":167,
    "gn:feature_class":"P",
    "gn:feature_code":"PPL",
    "gn:name":"Lenino",
    "gn:population":0,
    "gn:timezone":"Europe/Moscow",
    "iso:country":"RU",
    "name:bel_x_preferred":[
        "\u041b\u0435\u043d\u0456\u043d\u0430"
    ],
    "name:eng_x_preferred":[
        "Lenino"
    ],
    "name:kaz_x_preferred":[
        "\u041b\u0435\u043d\u0438\u043d\u043e"
    ],
    "name:nor_x_preferred":[
        "Lenino"
    ],
    "name:pol_x_preferred":[
        "Lenino"
    ],
    "name:rus_x_preferred":[
        "\u041b\u0435\u043d\u0438\u043d\u043e"
    ],
    "name:srp_x_preferred":[
        "\u041b\u0435\u045a\u0438\u043d\u043e"
    ],
    "name:ukr_x_preferred":[
        "\u041b\u0435\u043d\u0456\u043d\u043e"
    ],
    "name:und_x_variant":[
        "\u041b\u0435\u043d\u0438\u043d\u043e",
        "Lenino"
    ],
    "wof:name":"Lenino",
    "wof:placetype":"locality"
},
  "geometry": {"coordinates":[44.8913,53.03479],"type":"Point"}
}