{
  "type": "Feature",
  "properties": {
    "gn:admin1_code":"88",
    "gn:asciiname":"Selivanovo",
    "gn:country_code":"RU",
    "gn:dem":112,
    "gn:feature_class":"P",
    "gn:feature_code":"PPL",
    "gn:name":"Selivanovo",
    "gn:population":0,
    "gn:timezone":"Europe/Moscow",
    "iso:country":"RU",
    "name:rus_x_preferred":[
        "\u0421\u0435\u043b\u0438\u0432\u0430\u043d\u043e\u0432\u043e"
    ],
    "name:und_x_variant":[
        "\u0421\u0435\u043b\u0438\u0432\u0430\u043d\u043e\u0432\u043e"
    ],
    "wof:name":"Selivanovo",
    "wof:placetype":"locality"
},
  "geometry": {"coordinates":[38.4385,57.5867],"type":"Point"}
}