{
  "type": "Feature",
  "properties": {
    "gn:admin1_code":"56",
    "gn:asciiname":"Al'yanoye",
    "gn:country_code":"RU",
    "gn:dem":192,
    "gn:feature_class":"P",
    "gn:feature_code":"PPL",
    "gn:name":"Al\u2019yanoye",
    "gn:population":0,
    "gn:timezone":"Europe/Moscow",
    "iso:country":"RU",
    "name:nor_x_preferred":[
        "Aljanoje"
    ],
    "name:rus_x_preferred":[
        "\u0410\u043b\u044c\u044f\u043d\u043e\u0435"
    ],
    "name:und_x_variant":[
        "Zarya Svobody",
        "Allenaya",
        "Alleynaya",
        "Al\u2019yanoye"
    ],
    "wof:name":"Al'yanoye",
    "wof:placetype":"locality"
},
  "geometry": {"coordinates":[35.90096,53.15729],"type":"Point"}
}