{
  "type": "Feature",
  "properties": {
    "gn:admin1_code":"88.0",
    "gn:asciiname":"Pavlitsevo",
    "gn:country_code":"RU",
    "gn:dem":168,
    "gn:feature_class":"P",
    "gn:feature_code":"PPL",
    "gn:name":"Pavlitsevo",
    "gn:population":0,
    "gn:timezone":"Europe/Moscow",
    "iso:country":"RU",
    "name:rus_x_preferred":[
        "\u041f\u0430\u0432\u043b\u0438\u0446\u0435\u0432\u043e"
    ],
    "wof:name":"Pavlitsevo",
    "wof:placetype":"locality"
},
  "geometry": {"coordinates":[40.19733,58.37281],"type":"Point"}
}