{
  "type": "Feature",
  "properties": {
    "gn:admin1_code":"23",
    "gn:asciiname":"Zorino",
    "gn:country_code":"RU",
    "gn:dem":30,
    "gn:feature_class":"P",
    "gn:feature_code":"PPL",
    "gn:name":"Zorino",
    "gn:population":0,
    "gn:timezone":"Europe/Kaliningrad",
    "iso:country":"RU",
    "name:eng_x_preferred":[
        "Zorino"
    ],
    "name:nor_x_preferred":[
        "Zorino"
    ],
    "name:rus_x_preferred":[
        "\u0417\u043e\u0440\u0438\u043d\u043e"
    ],
    "wof:name":"Zorino",
    "wof:placetype":"locality"
},
  "geometry": {"coordinates":[21.21667,54.66917],"type":"Point"}
}