{
  "type": "Feature",
  "properties": {
    "gn:admin1_code":"60",
    "gn:asciiname":"Nikonikha",
    "gn:country_code":"RU",
    "gn:dem":196,
    "gn:feature_class":"P",
    "gn:feature_code":"PPL",
    "gn:name":"Nikonikha",
    "gn:population":0,
    "gn:timezone":"Europe/Moscow",
    "iso:country":"RU",
    "name:rus_x_preferred":[
        "\u041d\u0438\u043a\u043e\u043d\u0438\u0445\u0430"
    ],
    "name:und_x_variant":[
        "\u041d\u0438\u043a\u043e\u043d\u0438\u0445\u0430"
    ],
    "wof:name":"Nikonikha",
    "wof:placetype":"locality"
},
  "geometry": {"coordinates":[29.7433,56.2103],"type":"Point"}
}