{
  "type": "Feature",
  "properties": {
    "gn:admin1_code":"77.0",
    "gn:asciiname":"Bol'shaya Slatnya",
    "gn:country_code":"RU",
    "gn:dem":216,
    "gn:feature_class":"P",
    "gn:feature_code":"PPL",
    "gn:name":"Bol\u2019shaya Slatnya",
    "gn:population":0,
    "gn:timezone":"Europe/Moscow",
    "iso:country":"RU",
    "name:rus_x_preferred":[
        "\u0411\u043e\u043b\u044c\u0448\u0430\u044f \u0421\u043b\u0430\u0442\u043d\u044f"
    ],
    "name:und_x_variant":[
        "Slatnaya",
        "Slatnya",
        "Bol\u2019shaya Slatnya"
    ],
    "wof:name":"Bol'shaya Slatnya",
    "wof:placetype":"locality"
},
  "geometry": {"coordinates":[33.47427,56.37209],"type":"Point"}
}