{
  "type": "Feature",
  "properties": {
    "gn:admin1_code":"84",
    "gn:asciiname":"Lapshinskaya",
    "gn:country_code":"RU",
    "gn:dem":138,
    "gn:feature_class":"P",
    "gn:feature_code":"PPL",
    "gn:name":"Lapshinskaya",
    "gn:population":0,
    "gn:timezone":"Europe/Volgograd",
    "iso:country":"RU",
    "name:rus_x_preferred":[
        "\u041b\u0430\u043f\u0448\u0438\u043d\u0441\u043a\u0430\u044f"
    ],
    "name:und_x_variant":[
        "\u041b\u0430\u043f\u0448\u0438\u043d\u0441\u043a\u0430\u044f"
    ],
    "wof:name":"Lapshinskaya",
    "wof:placetype":"locality"
},
  "geometry": {"coordinates":[44.99688,50.3614],"type":"Point"}
}