{
  "type": "Feature",
  "properties": {
    "gn:admin1_code":"25",
    "gn:asciiname":"Khotisino",
    "gn:country_code":"RU",
    "gn:dem":181,
    "gn:feature_class":"P",
    "gn:feature_code":"PPL",
    "gn:name":"Khotisino",
    "gn:population":0,
    "gn:timezone":"Europe/Moscow",
    "iso:country":"RU",
    "name:rus_x_preferred":[
        "\u0425\u043e\u0442\u0438\u0441\u0438\u043d\u043e"
    ],
    "name:und_x_variant":[
        "\u0425\u043e\u0442\u0438\u0441\u0438\u043d\u043e"
    ],
    "wof:name":"Khotisino",
    "wof:placetype":"locality"
},
  "geometry": {"coordinates":[35.02937,53.94276],"type":"Point"}
}