{
  "type": "Feature",
  "properties": {
    "gn:asciiname":"Zamosh'ye",
    "gn:country_code":"RU",
    "gn:dem":33,
    "gn:feature_class":"P",
    "gn:feature_code":"PPL",
    "gn:name":"Zamosh'ye",
    "gn:population":0,
    "gn:timezone":"Europe/Moscow",
    "iso:country":"RU",
    "wof:name":"Zamosh'ye",
    "wof:placetype":"locality"
},
  "geometry": {"coordinates":[27.6059,58.28179],"type":"Point"}
}