{
  "type": "Feature",
  "properties": {
    "gn:admin1_code":"56.0",
    "gn:asciiname":"Chigirinovka",
    "gn:country_code":"RU",
    "gn:dem":188,
    "gn:feature_class":"P",
    "gn:feature_code":"PPL",
    "gn:name":"Chigirinovka",
    "gn:population":0,
    "gn:timezone":"Europe/Moscow",
    "iso:country":"RU",
    "name:rus_x_preferred":[
        "\u0427\u0438\u0433\u0438\u0440\u0438\u043d\u043e\u0432\u043a\u0430"
    ],
    "name:und_x_variant":[
        "\u0427\u0438\u0433\u0438\u0440\u0438\u043d\u043e\u0432\u043a\u0430"
    ],
    "wof:name":"Chigirinovka",
    "wof:placetype":"locality"
},
  "geometry": {"coordinates":[37.57139,52.89417],"type":"Point"}
}