{
  "type": "Feature",
  "properties": {
    "gn:admin1_code":"90",
    "gn:asciiname":"Nizhniy Syp",
    "gn:country_code":"RU",
    "gn:dem":160,
    "gn:feature_class":"P",
    "gn:feature_code":"PPL",
    "gn:name":"Nizhniy Syp",
    "gn:population":0,
    "gn:timezone":"Asia/Yekaterinburg",
    "iso:country":"RU",
    "name:eng_x_preferred":[
        "Nizhniy Syp"
    ],
    "name:nor_x_preferred":[
        "Nizj.Syp"
    ],
    "name:rus_x_preferred":[
        "\u041d\u0438\u0436.\u0421\u044b\u043f"
    ],
    "name:rus_x_variant":[
        "\u041d\u0438\u0436\u043d\u0438\u0439 \u0421\u044b\u043f"
    ],
    "wof:name":"Nizhniy Syp",
    "wof:placetype":"locality"
},
  "geometry": {"coordinates":[56.57139,56.96692],"type":"Point"}
}