{
  "type": "Feature",
  "properties": {
    "gn:admin1_code":"52",
    "gn:asciiname":"Pavlova",
    "gn:cc2":"RU",
    "gn:country_code":"RU",
    "gn:dem":202,
    "gn:feature_class":"P",
    "gn:feature_code":"PPL",
    "gn:name":"Pavlova",
    "gn:population":0,
    "gn:timezone":"Europe/Moscow",
    "iso:country":"RU",
    "name:und_x_variant":[
        "Pavlovo",
        "Pavlova"
    ],
    "wof:name":"Pavlova",
    "wof:placetype":"locality"
},
  "geometry": {"coordinates":[33.95,58.98333],"type":"Point"}
}