{
  "type": "Feature",
  "properties": {
    "gn:admin1_code":"52",
    "gn:asciiname":"Pavlova",
    "gn:cc2":"RU",
    "gn:country_code":"RU",
    "gn:dem":202,
    "gn:feature_class":"P",
    "gn:feature_code":"PPL",
    "gn:name":"Pavlova",
    "gn:population":0,
    "gn:timezone":"Europe/Moscow",
    "iso:country":"RU",
    "name:arg_x_preferred":[
        "Pavlova"
    ],
    "name:bul_x_preferred":[
        "\u041f\u0430\u0432\u043b\u043e\u0432\u0430"
    ],
    "name:ceb_x_preferred":[
        "\u041f\u0430\u0432\u043b\u043e\u0432\u0430"
    ],
    "name:deu_x_preferred":[
        "Pawlowa"
    ],
    "name:est_x_preferred":[
        "Pavlova"
    ],
    "name:ita_x_preferred":[
        "Pavlova"
    ],
    "name:jpn_x_preferred":[
        "\u30d1\u30f4\u30ed\u30ef"
    ],
    "name:kor_x_preferred":[
        "\ud30c\ube14\ub85c\ubc14"
    ],
    "name:nld_x_preferred":[
        "Pavlova"
    ],
    "name:por_x_preferred":[
        "Pavlova"
    ],
    "name:rus_x_preferred":[
        "\u041f\u0430\u0432\u043b\u043e\u0432\u0430"
    ],
    "name:ukr_x_preferred":[
        "\u041f\u0430\u0432\u043b\u043e\u0432\u0430"
    ],
    "name:und_x_variant":[
        "Pavlovo",
        "Pavlova"
    ],
    "wof:name":"Pavlova",
    "wof:placetype":"locality"
},
  "geometry": {"coordinates":[33.95,58.98333],"type":"Point"}
}