{
  "type": "Feature",
  "properties": {
    "gn:admin1_code":"76",
    "gn:asciiname":"Konyushino",
    "gn:country_code":"RU",
    "gn:dem":220,
    "gn:feature_class":"P",
    "gn:feature_code":"PPL",
    "gn:name":"Konyushino",
    "gn:population":0,
    "gn:timezone":"Europe/Moscow",
    "iso:country":"RU",
    "name:rus_x_preferred":[
        "\u041a\u043e\u043d\u044e\u0448\u0438\u043d\u043e"
    ],
    "name:und_x_variant":[
        "Konyusheno",
        "Konyushino"
    ],
    "wof:name":"Konyushino",
    "wof:placetype":"locality"
},
  "geometry": {"coordinates":[37.31163,54.76024],"type":"Point"}
}