{
  "type": "Feature",
  "properties": {
    "gn:admin1_code":"73",
    "gn:asciiname":"Chishma",
    "gn:country_code":"RU",
    "gn:dem":195,
    "gn:feature_class":"P",
    "gn:feature_code":"PPL",
    "gn:name":"Chishma",
    "gn:population":0,
    "gn:timezone":"Europe/Moscow",
    "iso:country":"RU",
    "name:rus_x_preferred":[
        "\u0427\u0438\u0448\u043c\u0430"
    ],
    "wof:name":"Chishma",
    "wof:placetype":"locality"
},
  "geometry": {"coordinates":[53.4909,55.4403],"type":"Point"}
}