{
  "type": "Feature",
  "properties": {
    "gn:admin1_code":"85",
    "gn:asciiname":"Velikodvorskaya",
    "gn:country_code":"RU",
    "gn:dem":191,
    "gn:feature_class":"P",
    "gn:feature_code":"PPL",
    "gn:name":"Velikodvorskaya",
    "gn:population":0,
    "gn:timezone":"Europe/Moscow",
    "iso:country":"RU",
    "name:eng_x_preferred":[
        "Velikodvorskaya"
    ],
    "name:nor_x_preferred":[
        "Velikodvorskaja"
    ],
    "name:rus_x_preferred":[
        "\u0412\u0435\u043b\u0438\u043a\u043e\u0434\u0432\u043e\u0440\u0441\u043a\u0430\u044f"
    ],
    "wof:name":"Velikodvorskaya",
    "wof:placetype":"locality"
},
  "geometry": {"coordinates":[42.17519,60.43205],"type":"Point"}
}