{
  "type": "Feature",
  "properties": {
    "gn:admin1_code":"42",
    "gn:asciiname":"Peregreb",
    "gn:country_code":"RU",
    "gn:dem":75,
    "gn:feature_class":"P",
    "gn:feature_code":"PPL",
    "gn:name":"Peregreb",
    "gn:population":0,
    "gn:timezone":"Europe/Moscow",
    "iso:country":"RU",
    "name:rus_x_preferred":[
        "\u041f\u0435\u0440\u0435\u0433\u0440\u0435\u0431"
    ],
    "wof:name":"Peregreb",
    "wof:placetype":"locality"
},
  "geometry": {"coordinates":[28.6711,58.90966],"type":"Point"}
}