{
  "type": "Feature",
  "properties": {
    "gn:admin1_code":"81.0",
    "gn:asciiname":"Borisova Polyana",
    "gn:country_code":"RU",
    "gn:dem":204,
    "gn:feature_class":"P",
    "gn:feature_code":"PPL",
    "gn:name":"Borisova Polyana",
    "gn:population":0,
    "gn:timezone":"Europe/Ulyanovsk",
    "iso:country":"RU",
    "name:rus_x_preferred":[
        "\u0411\u043e\u0440\u0438\u0441\u043e\u0432\u0430 \u041f\u043e\u043b\u044f\u043d\u0430"
    ],
    "wof:name":"Borisova Polyana",
    "wof:placetype":"locality"
},
  "geometry": {"coordinates":[46.5702,53.7691],"type":"Point"}
}