{
  "type": "Feature",
  "properties": {
    "gn:admin1_code":"85.0",
    "gn:asciiname":"Bardinskoye",
    "gn:country_code":"RU",
    "gn:dem":157,
    "gn:feature_class":"P",
    "gn:feature_code":"PPL",
    "gn:name":"Bardinskoye",
    "gn:population":0,
    "gn:timezone":"Europe/Moscow",
    "iso:country":"RU",
    "name:eng_x_preferred":[
        "Bardinskoye"
    ],
    "name:nor_x_preferred":[
        "Bardinskoje"
    ],
    "name:rus_x_preferred":[
        "\u0411\u0430\u0440\u0434\u0438\u043d\u0441\u043a\u043e\u0435"
    ],
    "name:und_x_variant":[
        "Bardinskaya",
        "\u0411\u0430\u0440\u0434\u0438\u043d\u0441\u043a\u043e\u0435",
        "Bardinskoye"
    ],
    "wof:name":"Bardinskoye",
    "wof:placetype":"locality"
},
  "geometry": {"coordinates":[35.7025,59.5359],"type":"Point"}
}