{
  "type": "Feature",
  "properties": {
    "gn:admin1_code":"50",
    "gn:asciiname":"Yekusha",
    "gn:cc2":"RU",
    "gn:country_code":"RU",
    "gn:dem":14,
    "gn:feature_class":"P",
    "gn:feature_code":"PPL",
    "gn:name":"Yekusha",
    "gn:population":0,
    "gn:timezone":"Europe/Moscow",
    "iso:country":"RU",
    "name:und_x_variant":[
        "Yekushi",
        "Yekusha"
    ],
    "wof:name":"Yekusha",
    "wof:placetype":"locality"
},
  "geometry": {"coordinates":[52.96666999999999,67.66667],"type":"Point"}
}