{
  "type": "Feature",
  "properties": {
    "gn:admin1_code":"3",
    "gn:asciiname":"Verkhnyaya Souzga",
    "gn:country_code":"RU",
    "gn:dem":341,
    "gn:feature_class":"P",
    "gn:feature_code":"PPL",
    "gn:name":"Verkhnyaya Souzga",
    "gn:population":0,
    "gn:timezone":"Asia/Omsk",
    "iso:country":"RU",
    "name:und_x_variant":[
        "Verkhnyaya Suuzga",
        "Verkhnyaya Souzga"
    ],
    "wof:name":"Verkhnyaya Souzga",
    "wof:placetype":"locality"
},
  "geometry": {"coordinates":[85.87448000000001,51.87775],"type":"Point"}
}