{
  "type": "Feature",
  "properties": {
    "gn:admin1_code":"90.0",
    "gn:asciiname":"Yashkino",
    "gn:country_code":"RU",
    "gn:dem":193,
    "gn:feature_class":"P",
    "gn:feature_code":"PPL",
    "gn:name":"Yashkino",
    "gn:population":0,
    "gn:timezone":"Asia/Yekaterinburg",
    "iso:country":"RU",
    "name:rus_x_preferred":[
        "\u042f\u0448\u043a\u0438\u043d\u043e"
    ],
    "wof:name":"Yashkino",
    "wof:placetype":"locality"
},
  "geometry": {"coordinates":[54.7928,58.8814],"type":"Point"}
}