{
  "type": "Feature",
  "properties": {
    "gn:admin1_code":"17.0",
    "gn:asciiname":"Buskri",
    "gn:country_code":"RU",
    "gn:dem":1370,
    "gn:feature_class":"P",
    "gn:feature_code":"PPL",
    "gn:name":"Buskri",
    "gn:population":0,
    "gn:timezone":"Europe/Moscow",
    "iso:country":"RU",
    "name:rus_x_preferred":[
        "\u0411\u0443\u0441\u043a\u0440\u0438"
    ],
    "wof:name":"Buskri",
    "wof:placetype":"locality"
},
  "geometry": {"coordinates":[47.66673,42.17359],"type":"Point"}
}