{
  "type": "Feature",
  "properties": {
    "gn:admin1_code":"72",
    "gn:asciiname":"Mordvinovka",
    "gn:country_code":"RU",
    "gn:dem":129,
    "gn:feature_class":"P",
    "gn:feature_code":"PPL",
    "gn:name":"Mordvinovka",
    "gn:population":0,
    "gn:timezone":"Europe/Moscow",
    "iso:country":"RU",
    "name:bak_x_preferred":[
        "\u041c\u043e\u0440\u0434\u0432\u0438\u043d\u043e\u0432\u043a\u0430"
    ],
    "name:che_x_preferred":[
        "\u041c\u043e\u0440\u0434\u0432\u0438\u043d\u043e\u0432\u043a\u0430"
    ],
    "name:hye_x_preferred":[
        "\u0544\u0578\u0580\u0564\u057e\u056b\u0576\u0578\u057e\u056f\u0561"
    ],
    "name:kaz_x_preferred":[
        "\u041c\u043e\u0440\u0434\u0432\u0438\u043d\u043e\u0432\u043a\u0430"
    ],
    "name:kir_x_preferred":[
        "\u041c\u043e\u0440\u0434\u0432\u0438\u043d\u043e\u0432\u043a\u0430"
    ],
    "name:rus_x_preferred":[
        "\u041c\u043e\u0440\u0434\u0432\u0438\u043d\u043e\u0432\u043a\u0430"
    ],
    "name:tat_x_preferred":[
        "\u041c\u043e\u0440\u0434\u0432\u0438\u043d\u043e\u0432\u043a\u0430"
    ],
    "wof:name":"Mordvinovka",
    "wof:placetype":"locality"
},
  "geometry": {"coordinates":[41.77138,52.02865],"type":"Point"}
}