{
  "type": "Feature",
  "properties": {
    "gn:admin1_code":"38",
    "gn:asciiname":"Zanko",
    "gn:country_code":"RU",
    "gn:dem":1,
    "gn:feature_class":"P",
    "gn:feature_code":"PPL",
    "gn:name":"Zanko",
    "gn:population":0,
    "gn:timezone":"Europe/Moscow",
    "iso:country":"RU",
    "wof:name":"Zanko",
    "wof:placetype":"locality"
},
  "geometry": {"coordinates":[38.39165,45.89739],"type":"Point"}
}