{
  "type": "Feature",
  "properties": {
    "gn:admin1_code":"41",
    "gn:asciiname":"Uspenka",
    "gn:country_code":"RU",
    "gn:dem":159,
    "gn:feature_class":"P",
    "gn:feature_code":"PPL",
    "gn:name":"Uspenka",
    "gn:population":0,
    "gn:timezone":"Europe/Moscow",
    "iso:country":"RU",
    "name:rus_x_preferred":[
        "\u0423\u0441\u043f\u0435\u043d\u043a\u0430"
    ],
    "name:und_x_variant":[
        "Uspenskoye",
        "Uspenka"
    ],
    "wof:name":"Uspenka",
    "wof:placetype":"locality"
},
  "geometry": {"coordinates":[35.7052,51.6577],"type":"Point"}
}