{
  "type": "Feature",
  "properties": {
    "gn:admin1_code":"60",
    "gn:asciiname":"Shipovo",
    "gn:country_code":"RU",
    "gn:dem":92,
    "gn:feature_class":"P",
    "gn:feature_code":"PPL",
    "gn:name":"Shipovo",
    "gn:population":0,
    "gn:timezone":"Europe/Moscow",
    "iso:country":"RU",
    "name:rus_x_preferred":[
        "\u0428\u0438\u043f\u043e\u0432\u043e"
    ],
    "wof:name":"Shipovo",
    "wof:placetype":"locality"
},
  "geometry": {"coordinates":[30.3383,57.2002],"type":"Point"}
}