{
  "type": "Feature",
  "properties": {
    "gn:admin1_code":"77",
    "gn:asciiname":"Kachevitsy",
    "gn:country_code":"RU",
    "gn:dem":191,
    "gn:feature_class":"P",
    "gn:feature_code":"PPL",
    "gn:name":"Kachevitsy",
    "gn:population":0,
    "gn:timezone":"Europe/Moscow",
    "iso:country":"RU",
    "name:rus_x_preferred":[
        "\u041a\u0430\u0447\u0435\u0432\u0438\u0446\u044b"
    ],
    "wof:name":"Kachevitsy",
    "wof:placetype":"locality"
},
  "geometry": {"coordinates":[32.03405,56.31629],"type":"Point"}
}