{
  "type": "Feature",
  "properties": {
    "gn:admin1_code":"21",
    "gn:asciiname":"Milyukovka",
    "gn:country_code":"RU",
    "gn:dem":94,
    "gn:feature_class":"P",
    "gn:feature_code":"PPL",
    "gn:name":"Milyukovka",
    "gn:population":0,
    "gn:timezone":"Europe/Moscow",
    "iso:country":"RU",
    "name:eng_x_preferred":[
        "Milyukovka"
    ],
    "name:nor_x_preferred":[
        "Miljukovka"
    ],
    "name:rus_x_preferred":[
        "\u041c\u0438\u043b\u044e\u043a\u043e\u0432\u043a\u0430"
    ],
    "name:und_x_variant":[
        "Milyukova"
    ],
    "wof:name":"Milyukovka",
    "wof:placetype":"locality"
},
  "geometry": {"coordinates":[41.48129,56.79624],"type":"Point"}
}