{
  "type": "Feature",
  "properties": {
    "gn:admin1_code":"71",
    "gn:asciiname":"Ilyasova",
    "gn:country_code":"RU",
    "gn:dem":64,
    "gn:feature_class":"P",
    "gn:feature_code":"PPL",
    "gn:name":"Ilyasova",
    "gn:population":0,
    "gn:timezone":"Asia/Yekaterinburg",
    "iso:country":"RU",
    "name:rus_x_preferred":[
        "\u0418\u043b\u044f\u0441\u043e\u0432\u0430"
    ],
    "wof:name":"Ilyasova",
    "wof:placetype":"locality"
},
  "geometry": {"coordinates":[63.23333,58.15],"type":"Point"}
}