{
  "type": "Feature",
  "properties": {
    "gn:admin1_code":"76",
    "gn:asciiname":"Kudrino",
    "gn:country_code":"RU",
    "gn:dem":178,
    "gn:feature_class":"P",
    "gn:feature_code":"PPL",
    "gn:name":"Kudrino",
    "gn:population":0,
    "gn:timezone":"Europe/Moscow",
    "iso:country":"RU",
    "name:rus_x_preferred":[
        "\u041a\u0443\u0434\u0440\u0438\u043d\u043e"
    ],
    "name:ukr_x_preferred":[
        "\u041a\u0443\u0434\u0440\u0456\u043d\u043e"
    ],
    "name:und_x_variant":[
        "\u041a\u0443\u0434\u0440\u0438\u043d\u043e"
    ],
    "wof:name":"Kudrino",
    "wof:placetype":"locality"
},
  "geometry": {"coordinates":[36.13544,53.93037],"type":"Point"}
}