{
  "type": "Feature",
  "properties": {
    "gn:admin1_code":"69",
    "gn:asciiname":"Ignatovo",
    "gn:cc2":"RU",
    "gn:country_code":"RU",
    "gn:dem":224,
    "gn:feature_class":"P",
    "gn:feature_code":"PPL",
    "gn:name":"Ignatovo",
    "gn:population":0,
    "gn:timezone":"Europe/Moscow",
    "iso:country":"RU",
    "name:bul_x_preferred":[
        "\u0418\u0433\u043d\u0430\u0442\u043e\u0432\u043e"
    ],
    "name:fas_x_preferred":[
        "\u0627\u06cc\u06af\u0646\u0627\u062a\u0648\u0648\u0648"
    ],
    "name:kaz_x_preferred":[
        "\u0418\u0433\u043d\u0430\u0442\u043e\u0432\u043e"
    ],
    "name:msa_x_preferred":[
        "Ignatovo"
    ],
    "name:ron_x_preferred":[
        "Ignatovo"
    ],
    "name:rus_x_preferred":[
        "\u0418\u0433\u043d\u0430\u0442\u043e\u0432\u043e"
    ],
    "name:ukr_x_preferred":[
        "\u0406\u0433\u043d\u0430\u0442\u043e\u0432\u043e"
    ],
    "name:und_x_variant":[
        "Ignatova",
        "Ignatovo",
        "\u0418\u0433\u043d\u0430\u0442\u043e\u0432\u043e"
    ],
    "wof:name":"Ignatovo",
    "wof:placetype":"locality"
},
  "geometry": {"coordinates":[35.16222,55.29833000000001],"type":"Point"}
}