{
  "type": "Feature",
  "properties": {
    "gn:admin1_code":"9",
    "gn:asciiname":"Chermenevka",
    "gn:country_code":"RU",
    "gn:dem":117,
    "gn:feature_class":"P",
    "gn:feature_code":"PPL",
    "gn:name":"Chermen\u00ebvka",
    "gn:population":0,
    "gn:timezone":"Europe/Moscow",
    "iso:country":"RU",
    "name:rus_x_preferred":[
        "\u0427\u0435\u0440\u043c\u0435\u043d\u00eb\u0432\u043a\u0430"
    ],
    "name:und_x_variant":[
        "Chermen\u00ebvka"
    ],
    "wof:name":"Chermenevka",
    "wof:placetype":"locality"
},
  "geometry": {"coordinates":[38.4143,50.7761],"type":"Point"}
}