{
  "type": "Feature",
  "properties": {
    "gn:admin1_code":"76",
    "gn:asciiname":"Vorodunovo",
    "gn:country_code":"RU",
    "gn:dem":208,
    "gn:feature_class":"P",
    "gn:feature_code":"PPL",
    "gn:name":"Vorodunovo",
    "gn:population":0,
    "gn:timezone":"Europe/Moscow",
    "iso:country":"RU",
    "name:rus_x_preferred":[
        "\u0412\u043e\u0440\u043e\u0434\u0443\u043d\u043e\u0432\u043e"
    ],
    "name:und_x_variant":[
        "Vyradunova",
        "Vyradunovo",
        "Vorodunovo"
    ],
    "wof:name":"Vorodunovo",
    "wof:placetype":"locality"
},
  "geometry": {"coordinates":[38.06493,54.48551],"type":"Point"}
}