{
  "type": "Feature",
  "properties": {
    "gn:admin1_code":"59",
    "gn:asciiname":"Novonikolayevka",
    "gn:country_code":"RU",
    "gn:dem":73,
    "gn:feature_class":"P",
    "gn:feature_code":"PPL",
    "gn:name":"Novonikolayevka",
    "gn:population":0,
    "gn:timezone":"Asia/Vladivostok",
    "iso:country":"RU",
    "name:eng_x_preferred":[
        "Novonikolayevka"
    ],
    "name:nor_x_preferred":[
        "Novonikolajevka"
    ],
    "name:rus_x_preferred":[
        "\u041d\u043e\u0432\u043e\u043d\u0438\u043a\u043e\u043b\u0430\u0435\u0432\u043a\u0430"
    ],
    "name:und_x_variant":[
        "Verkhne-Nikolayevka",
        "Novo-Nikolayevskiy",
        "Novo-Nikolayevskoye",
        "\u041d\u043e\u0432\u043e\u043d\u0438\u043a\u043e\u043b\u0430\u0435\u0432\u043a\u0430",
        "Staro-Nikolayevka",
        "Staraya Nikolayevka",
        "Novonikolayevka"
    ],
    "wof:name":"Novonikolayevka",
    "wof:placetype":"locality"
},
  "geometry": {"coordinates":[132.09729999999999,44.8903],"type":"Point"}
}