{
  "type": "Feature",
  "properties": {
    "gn:admin1_code":"83.0",
    "gn:asciiname":"Bol'shiye Lipki",
    "gn:country_code":"RU",
    "gn:dem":139,
    "gn:feature_class":"P",
    "gn:feature_code":"PPL",
    "gn:name":"Bol\u2019shiye Lipki",
    "gn:population":0,
    "gn:timezone":"Europe/Moscow",
    "iso:country":"RU",
    "wof:name":"Bol'shiye Lipki",
    "wof:placetype":"locality"
},
  "geometry": {"coordinates":[42.07065,56.25274],"type":"Point"}
}