{
  "type": "Feature",
  "properties": {
    "gn:admin1_code":"91",
    "gn:asciiname":"Ust'-Toylovka",
    "gn:country_code":"RU",
    "gn:dem":173,
    "gn:feature_class":"P",
    "gn:feature_code":"PPL",
    "gn:name":"Ust\u2019-Toylovka",
    "gn:population":0,
    "gn:timezone":"Asia/Krasnoyarsk",
    "iso:country":"RU",
    "name:eng_x_preferred":[
        "Ust'-Toylovka"
    ],
    "name:nor_x_preferred":[
        "Ust-Tojlovka"
    ],
    "name:rus_x_preferred":[
        "\u0423\u0441\u0442\u044c-\u0422\u043e\u0439\u043b\u043e\u0432\u043a\u0430"
    ],
    "name:und_x_variant":[
        "Ust\u2019-Taylonskiy",
        "Ust\u2019-Taylokskiy",
        "Ust\u2019-Toylovka"
    ],
    "wof:name":"Ust'-Toylovka",
    "wof:placetype":"locality"
},
  "geometry": {"coordinates":[89.18683,56.68062],"type":"Point"}
}