{
  "type": "Feature",
  "properties": {
    "gn:admin1_code":"24.0",
    "gn:asciiname":"Desyatiletiye Oktyabrya",
    "gn:country_code":"RU",
    "gn:dem":-18,
    "gn:feature_class":"P",
    "gn:feature_code":"PPL",
    "gn:name":"Desyatiletiye Oktyabrya",
    "gn:population":0,
    "gn:timezone":"Europe/Moscow",
    "iso:country":"RU",
    "name:rus_x_preferred":[
        "\u0414\u0435\u0441\u044f\u0442\u0438\u043b\u0435\u0442\u0438\u0435 \u041e\u043a\u0442\u044f\u0431\u0440\u044f"
    ],
    "wof:name":"Desyatiletiye Oktyabrya",
    "wof:placetype":"locality"
},
  "geometry": {"coordinates":[46.185,45.75194000000001],"type":"Point"}
}