{
  "type": "Feature",
  "properties": {
    "gn:admin1_code":"72",
    "gn:asciiname":"Grigor'yevka",
    "gn:country_code":"RU",
    "gn:dem":170,
    "gn:feature_class":"P",
    "gn:feature_code":"PPL",
    "gn:name":"Grigor\u2019yevka",
    "gn:population":0,
    "gn:timezone":"Europe/Moscow",
    "iso:country":"RU",
    "name:kir_x_preferred":[
        "\u0413\u0440\u0438\u0433\u043e\u0440\u044c\u0435\u0432\u043a\u0430"
    ],
    "name:rus_x_preferred":[
        "\u0413\u0440\u0438\u0433\u043e\u0440\u044c\u0435\u0432\u043a\u0430"
    ],
    "name:und_x_variant":[
        "Grigor\u2019yevka",
        "\u0413\u0440\u0438\u0433\u043e\u0440\u044c\u0435\u0432\u043a\u0430"
    ],
    "wof:name":"Grigor'yevka",
    "wof:placetype":"locality"
},
  "geometry": {"coordinates":[43.05037,52.63404],"type":"Point"}
}