{
  "type": "Feature",
  "properties": {
    "gn:admin1_code":"72.0",
    "gn:asciiname":"Bolotovka",
    "gn:country_code":"RU",
    "gn:dem":128,
    "gn:feature_class":"P",
    "gn:feature_code":"PPL",
    "gn:name":"Bolotovka",
    "gn:population":0,
    "gn:timezone":"Europe/Moscow",
    "iso:country":"RU",
    "name:rus_x_preferred":[
        "\u0411\u043e\u043b\u043e\u0442\u043e\u0432\u043a\u0430"
    ],
    "wof:name":"Bolotovka",
    "wof:placetype":"locality"
},
  "geometry": {"coordinates":[42.23333,52.36667],"type":"Point"}
}