{
  "type": "Feature",
  "properties": {
    "gn:admin1_code":"49",
    "gn:asciiname":"Kovd Zapon'ye",
    "gn:country_code":"RU",
    "gn:dem":1,
    "gn:feature_class":"P",
    "gn:feature_code":"PPL",
    "gn:name":"Kovd Zapon\u2019ye",
    "gn:population":0,
    "gn:timezone":"Europe/Moscow",
    "iso:country":"RU",
    "name:fin_x_preferred":[
        "Zaponjen Kouta"
    ],
    "name:rus_x_preferred":[
        "\u041a\u043e\u0432\u0434 \u0417\u0430\u043f\u043e\u043d\u044c\u0435"
    ],
    "name:und_x_variant":[
        "Novd Zapon\u2019ye",
        "Kovd Zapon\u2019ye"
    ],
    "wof:name":"Kovd Zapon'ye",
    "wof:placetype":"locality"
},
  "geometry": {"coordinates":[32.86182,66.6977],"type":"Point"}
}