{
  "type": "Feature",
  "properties": {
    "gn:admin1_code":"63",
    "gn:asciiname":"Krasnaya Tanda",
    "gn:country_code":"RU",
    "gn:dem":170,
    "gn:feature_class":"P",
    "gn:feature_code":"PPL",
    "gn:name":"Krasnaya Tanda",
    "gn:population":0,
    "gn:timezone":"Asia/Yakutsk",
    "iso:country":"RU",
    "name:rus_x_preferred":[
        "\u041a\u0440\u0430\u0441\u043d\u0430\u044f \u0422\u0430\u043d\u0434\u0430"
    ],
    "wof:name":"Krasnaya Tanda",
    "wof:placetype":"locality"
},
  "geometry": {"coordinates":[131.98333,62.63333000000001],"type":"Point"}
}