{
  "type": "Feature",
  "properties": {
    "gn:admin1_code":"77",
    "gn:asciiname":"Pishchulino",
    "gn:country_code":"RU",
    "gn:dem":145,
    "gn:feature_class":"P",
    "gn:feature_code":"PPL",
    "gn:name":"Pishchulino",
    "gn:population":0,
    "gn:timezone":"Europe/Moscow",
    "iso:country":"RU",
    "name:nor_x_preferred":[
        "Pisjtsjulino"
    ],
    "name:rus_x_preferred":[
        "\u041f\u0438\u0449\u0443\u043b\u0438\u043d\u043e"
    ],
    "wof:name":"Pishchulino",
    "wof:placetype":"locality"
},
  "geometry": {"coordinates":[35.51655,56.65175],"type":"Point"}
}