{
  "type": "Feature",
  "properties": {
    "gn:admin1_code":"7",
    "gn:asciiname":"Stepnoy",
    "gn:country_code":"RU",
    "gn:dem":-24,
    "gn:feature_class":"P",
    "gn:feature_code":"PPL",
    "gn:name":"Stepnoy",
    "gn:population":0,
    "gn:timezone":"Europe/Astrakhan",
    "iso:country":"RU",
    "name:eng_x_preferred":[
        "Stepnoy"
    ],
    "name:nor_x_preferred":[
        "Stepnoj"
    ],
    "name:rus_x_preferred":[
        "\u0421\u0442\u0435\u043f\u043d\u043e\u0439"
    ],
    "wof:name":"Stepnoy",
    "wof:placetype":"locality"
},
  "geometry": {"coordinates":[48.17829,46.69544000000001],"type":"Point"}
}