{
  "type": "Feature",
  "properties": {
    "gn:admin1_code":"51",
    "gn:asciiname":"Krutoberezhka",
    "gn:country_code":"RU",
    "gn:dem":107,
    "gn:feature_class":"P",
    "gn:feature_code":"PPL",
    "gn:name":"Krutoberezhka",
    "gn:population":0,
    "gn:timezone":"Europe/Moscow",
    "iso:country":"RU",
    "name:rus_x_preferred":[
        "\u041a\u0440\u0443\u0442\u043e\u0431\u0435\u0440\u0435\u0436\u043a\u0430"
    ],
    "name:und_x_variant":[
        "Krutoberezhskaya",
        "Krutoberezhka",
        "\u041a\u0440\u0443\u0442\u043e\u0431\u0435\u0440\u0435\u0436\u043a\u0430"
    ],
    "wof:name":"Krutoberezhka",
    "wof:placetype":"locality"
},
  "geometry": {"coordinates":[47.62658,57.87263000000001],"type":"Point"}
}