{
  "type": "Feature",
  "properties": {
    "gn:admin1_code":"34",
    "gn:asciiname":"Rusanovskaya",
    "gn:country_code":"RU",
    "gn:dem":125,
    "gn:feature_class":"P",
    "gn:feature_code":"PPL",
    "gn:name":"Rusanovskaya",
    "gn:population":0,
    "gn:timezone":"Europe/Moscow",
    "iso:country":"RU",
    "name:eng_x_preferred":[
        "Rusanovskaya"
    ],
    "name:nor_x_preferred":[
        "Rusanovskaja"
    ],
    "name:rus_x_preferred":[
        "\u0420\u0443\u0441\u0430\u043d\u043e\u0432\u0441\u043a\u0430\u044f"
    ],
    "wof:name":"Rusanovskaya",
    "wof:placetype":"locality"
},
  "geometry": {"coordinates":[52.86472,62.33364],"type":"Point"}
}