{
  "type": "Feature",
  "properties": {
    "gn:country":"RU",
    "gn:fcode":"PPL",
    "gn:population":0,
    "iso:country":"RU",
    "name:rus_x_preferred":[
        "\u041c\u0438\u0437\u0438\u043d\u043e\u0432\u043e"
    ],
    "qs:name":"Mizinovo",
    "qs:name_adm0":"Russia",
    "qs:name_adm1":"Moscow Oblast",
    "qs:photos_9k":1,
    "qs:photos_9r":1,
    "qs:photos_all":1,
    "qs:photos_sr":0,
    "qs:placetype":"Town",
    "qs:pop_sr":"0",
    "wof:name":"Mizinovo",
    "wof:placetype":"locality",
    "wof:population":0
},
  "geometry": {"coordinates":[38.20694,55.94972],"type":"Point"}
}