{
  "type": "Feature",
  "properties": {
    "gn:admin1_code":"69",
    "gn:asciiname":"Savrasovo",
    "gn:country_code":"RU",
    "gn:dem":241,
    "gn:feature_class":"P",
    "gn:feature_code":"PPL",
    "gn:name":"Savrasovo",
    "gn:population":0,
    "gn:timezone":"Europe/Moscow",
    "iso:country":"RU",
    "name:rus_x_preferred":[
        "\u0421\u0430\u0432\u0440\u0430\u0441\u043e\u0432\u043e"
    ],
    "wof:name":"Savrasovo",
    "wof:placetype":"locality"
},
  "geometry": {"coordinates":[33.61214,55.68977],"type":"Point"}
}