{
  "type": "Feature",
  "properties": {
    "gn:admin1_code":"33.0",
    "gn:asciiname":"Verkhniye Tolmachi",
    "gn:country_code":"RU",
    "gn:dem":133,
    "gn:feature_class":"P",
    "gn:feature_code":"PPL",
    "gn:name":"Verkhniye Tolmachi",
    "gn:population":0,
    "gn:timezone":"Europe/Kirov",
    "iso:country":"RU",
    "name:rus_x_preferred":[
        "\u0412\u0435\u0440\u0445\u043d\u0438\u0435 \u0422\u043e\u043b\u043c\u0430\u0447\u0438"
    ],
    "wof:name":"Verkhniye Tolmachi",
    "wof:placetype":"locality"
},
  "geometry": {"coordinates":[49.13342,58.77313],"type":"Point"}
}