{
  "type": "Feature",
  "properties": {
    "gn:admin1_code":"60",
    "gn:asciiname":"Verkhov'ye Vtoroye",
    "gn:country_code":"RU",
    "gn:dem":57,
    "gn:feature_class":"P",
    "gn:feature_code":"PPL",
    "gn:name":"Verkhov\u2019ye Vtoroye",
    "gn:population":0,
    "gn:timezone":"Europe/Moscow",
    "iso:country":"RU",
    "name:rus_x_preferred":[
        "\u0412\u0435\u0440\u0445\u043e\u0432\u044c\u0435 \u0412\u0442\u043e\u0440\u043e\u0435"
    ],
    "name:und_x_variant":[
        "Verkhov\u2019ye Vtoroye",
        "\u0412\u0435\u0440\u0445\u043e\u0432\u044c\u0435 \u0412\u0442\u043e\u0440\u043e\u0435"
    ],
    "wof:name":"Verkhov'ye Vtoroye",
    "wof:placetype":"locality"
},
  "geometry": {"coordinates":[28.3513,58.6035],"type":"Point"}
}