{
  "type": "Feature",
  "properties": {
    "gn:admin1_code":"55",
    "gn:asciiname":"Pervoye Maya",
    "gn:country_code":"RU",
    "gn:dem":78,
    "gn:feature_class":"P",
    "gn:feature_code":"PPL",
    "gn:name":"Pervoye Maya",
    "gn:population":0,
    "gn:timezone":"Asia/Yekaterinburg",
    "iso:country":"RU",
    "name:ceb_x_preferred":[
        "Pervoye Maya"
    ],
    "name:eng_x_preferred":[
        "Pervoye Maya"
    ],
    "name:nor_x_preferred":[
        "Pervoje-Maja"
    ],
    "name:rus_x_preferred":[
        "\u041f\u0435\u0440\u0432\u043e\u0435-\u041c\u0430\u044f"
    ],
    "name:rus_x_variant":[
        "\u041f\u0435\u0440\u0432\u043e\u0435 \u041c\u0430\u044f"
    ],
    "name:swe_x_preferred":[
        "Pervoye Maya"
    ],
    "name:und_x_variant":[
        "\u041f\u0435\u0440\u0432\u043e\u0435 \u041c\u0430\u044f"
    ],
    "wof:name":"Pervoye Maya",
    "wof:placetype":"locality"
},
  "geometry": {"coordinates":[52.6212,52.5702],"type":"Point"}
}