{
  "type": "Feature",
  "properties": {
    "gn:admin1_code":"67",
    "gn:asciiname":"Staraya Yablonka",
    "gn:cc2":"RU",
    "gn:country_code":"RU",
    "gn:dem":75,
    "gn:feature_class":"P",
    "gn:feature_code":"PPL",
    "gn:name":"Staraya Yablonka",
    "gn:population":0,
    "gn:timezone":"Europe/Saratov",
    "iso:country":"RU",
    "name:eng_x_preferred":[
        "Staraya Yablonka"
    ],
    "name:nor_x_preferred":[
        "Staraja Jablonka"
    ],
    "name:rus_x_preferred":[
        "\u0421\u0442\u0430\u0440\u0430\u044f \u042f\u0431\u043b\u043e\u043d\u043a\u0430"
    ],
    "name:und_x_variant":[
        "Staraya Yablonovka"
    ],
    "wof:name":"Staraya Yablonka",
    "wof:placetype":"locality"
},
  "geometry": {"coordinates":[48.06667,52.38333],"type":"Point"}
}