{
  "type": "Feature",
  "properties": {
    "gn:admin1_code":"45",
    "gn:asciiname":"Nizhneye Akcherino",
    "gn:country_code":"RU",
    "gn:dem":118,
    "gn:feature_class":"P",
    "gn:feature_code":"PPL",
    "gn:name":"Nizhneye Akcherino",
    "gn:population":0,
    "gn:timezone":"Europe/Moscow",
    "iso:country":"RU",
    "name:rus_x_preferred":[
        "\u041d\u0438\u0436\u043d\u0435\u0435 \u0410\u043a\u0447\u0435\u0440\u0438\u043d\u043e"
    ],
    "name:und_x_variant":[
        "Akcherino"
    ],
    "wof:name":"Nizhneye Akcherino",
    "wof:placetype":"locality"
},
  "geometry": {"coordinates":[46.30346,56.21361],"type":"Point"}
}