{
  "type": "Feature",
  "properties": {
    "gn:admin1_code":"12.0",
    "gn:asciiname":"Dan-Kale",
    "gn:country_code":"RU",
    "gn:dem":843,
    "gn:feature_class":"P",
    "gn:feature_code":"PPL",
    "gn:name":"Dan-Kale",
    "gn:population":0,
    "gn:timezone":"Europe/Moscow",
    "iso:country":"RU",
    "name:rus_x_preferred":[
        "\u0414\u0430\u043d-\u041a\u0430\u043b\u0435"
    ],
    "wof:name":"Dan-Kale",
    "wof:placetype":"locality"
},
  "geometry": {"coordinates":[45.63833,42.76889],"type":"Point"}
}