{
  "type": "Feature",
  "properties": {
    "gn:admin1_code":"86.0",
    "gn:asciiname":"Fisenkovo",
    "gn:country_code":"RU",
    "gn:dem":131,
    "gn:feature_class":"P",
    "gn:feature_code":"PPL",
    "gn:name":"Fis\u00ebnkovo",
    "gn:population":0,
    "gn:timezone":"Europe/Moscow",
    "iso:country":"RU",
    "name:rus_x_preferred":[
        "Fis\u00ebnkovo"
    ],
    "name:rus_x_variant":[
        "\u0424\u0438\u0441\u0451\u043d\u043a\u043e\u0432\u043e"
    ],
    "wof:name":"Fisenkovo",
    "wof:placetype":"locality"
},
  "geometry": {"coordinates":[39.83224000000001,49.90187],"type":"Point"}
}