{
  "type": "Feature",
  "properties": {
    "gn:admin1_code":"21.0",
    "gn:asciiname":"Klinovets",
    "gn:country_code":"RU",
    "gn:dem":122,
    "gn:feature_class":"P",
    "gn:feature_code":"PPL",
    "gn:name":"Klinovets",
    "gn:population":0,
    "gn:timezone":"Europe/Moscow",
    "iso:country":"RU",
    "name:rus_x_preferred":[
        "\u041a\u043b\u0438\u043d\u043e\u0432\u0435\u0446"
    ],
    "wof:name":"Klinovets",
    "wof:placetype":"locality"
},
  "geometry": {"coordinates":[41.84981,57.4052],"type":"Point"}
}