{
  "type": "Feature",
  "properties": {
    "gn:admin1_code":"61",
    "gn:asciiname":"Krestovskiye",
    "gn:country_code":"RU",
    "gn:dem":173,
    "gn:feature_class":"P",
    "gn:feature_code":"PPL",
    "gn:name":"Krestovskiye",
    "gn:population":0,
    "gn:timezone":"Europe/Moscow",
    "iso:country":"RU",
    "name:rus_x_preferred":[
        "\u041a\u0440\u0435\u0441\u0442\u043e\u0432\u0441\u043a\u0438\u0435"
    ],
    "name:und_x_variant":[
        "\u041a\u0440\u0435\u0441\u0442\u043e\u0432\u0441\u043a\u0438\u0435"
    ],
    "wof:name":"Krestovskiye",
    "wof:placetype":"locality"
},
  "geometry": {"coordinates":[43.63028,46.42861],"type":"Point"}
}