{
  "type": "Feature",
  "properties": {
    "gn:admin1_code":"37",
    "gn:asciiname":"Olonino",
    "gn:country_code":"RU",
    "gn:dem":145,
    "gn:feature_class":"P",
    "gn:feature_code":"PPL",
    "gn:name":"Olonino",
    "gn:population":0,
    "gn:timezone":"Europe/Moscow",
    "iso:country":"RU",
    "name:rus_x_preferred":[
        "\u041e\u043b\u043e\u043d\u0438\u043d\u043e"
    ],
    "name:und_x_variant":[
        "Olenino",
        "Olonino"
    ],
    "wof:name":"Olonino",
    "wof:placetype":"locality"
},
  "geometry": {"coordinates":[42.90407,58.03735],"type":"Point"}
}