{
  "type": "Feature",
  "properties": {
    "gn:admin1_code":"33",
    "gn:asciiname":"Fateyevo",
    "gn:country_code":"RU",
    "gn:dem":122,
    "gn:feature_class":"P",
    "gn:feature_code":"PPL",
    "gn:name":"Fateyevo",
    "gn:population":0,
    "gn:timezone":"Europe/Kirov",
    "iso:country":"RU",
    "name:eng_x_preferred":[
        "Fateyevo"
    ],
    "name:nor_x_preferred":[
        "Fatejevo"
    ],
    "name:rus_x_preferred":[
        "\u0424\u0430\u0442\u0435\u0435\u0432\u043e"
    ],
    "name:und_x_variant":[
        "Foteyevtsy",
        "\u0424\u0430\u0442\u0435\u0435\u0432\u043e",
        "Fateyevo"
    ],
    "wof:name":"Fateyevo",
    "wof:placetype":"locality"
},
  "geometry": {"coordinates":[49.95667,58.41051],"type":"Point"}
}