{
  "type": "Feature",
  "properties": {
    "gn:admin1_code":"6.0",
    "gn:asciiname":"Gorka-Ladkovshchina",
    "gn:country_code":"RU",
    "gn:dem":29,
    "gn:feature_class":"P",
    "gn:feature_code":"PPL",
    "gn:name":"Gorka-Ladkovshchina",
    "gn:population":0,
    "gn:timezone":"Europe/Moscow",
    "iso:country":"RU",
    "name:rus_x_preferred":[
        "\u0413\u043e\u0440\u043a\u0430-\u041b\u0430\u0434\u043a\u043e\u0432\u0449\u0438\u043d\u0430"
    ],
    "wof:name":"Gorka-Ladkovshchina",
    "wof:placetype":"locality"
},
  "geometry": {"coordinates":[41.5495,63.8002],"type":"Point"}
}