{
  "type": "Feature",
  "properties": {
    "gn:admin1_code":"73",
    "gn:asciiname":"Agrokul'tura",
    "gn:country_code":"RU",
    "gn:dem":139,
    "gn:feature_class":"P",
    "gn:feature_code":"PPL",
    "gn:name":"Agrokul\u2019tura",
    "gn:population":0,
    "gn:timezone":"Europe/Moscow",
    "iso:country":"RU",
    "name:rus_x_preferred":[
        "\u0410\u0433\u0440\u043e\u043a\u0443\u043b\u044c\u0442\u0443\u0440\u0430"
    ],
    "name:und_x_variant":[
        "Agrokul\u2019tura",
        "\u0410\u0433\u0440\u043e\u043a\u0443\u043b\u044c\u0442\u0443\u0440\u0430"
    ],
    "wof:name":"Agrokul'tura",
    "wof:placetype":"locality"
},
  "geometry": {"coordinates":[50.5724,55.3083],"type":"Point"}
}