{
  "type": "Feature",
  "properties": {
    "gn:admin1_code":"71.0",
    "gn:asciiname":"Baganova",
    "gn:country_code":"RU",
    "gn:dem":86,
    "gn:feature_class":"P",
    "gn:feature_code":"PPL",
    "gn:name":"Baganova",
    "gn:population":0,
    "gn:timezone":"Asia/Yekaterinburg",
    "iso:country":"RU",
    "name:rus_x_preferred":[
        "\u0411\u0430\u0433\u0430\u043d\u043e\u0432\u0430"
    ],
    "wof:name":"Baganova",
    "wof:placetype":"locality"
},
  "geometry": {"coordinates":[63.11865,57.45879],"type":"Point"}
}