{
  "type": "Feature",
  "properties": {
    "gn:admin1_code":"33",
    "gn:asciiname":"Popiralovo",
    "gn:country_code":"RU",
    "gn:dem":165,
    "gn:feature_class":"P",
    "gn:feature_code":"PPL",
    "gn:name":"Popiralovo",
    "gn:population":0,
    "gn:timezone":"Europe/Kirov",
    "iso:country":"RU",
    "name:rus_x_preferred":[
        "\u041f\u043e\u043f\u0438\u0440\u0430\u043b\u043e\u0432\u043e"
    ],
    "wof:name":"Popiralovo",
    "wof:placetype":"locality"
},
  "geometry": {"coordinates":[49.0971,59.0556],"type":"Point"}
}