{
  "type": "Feature",
  "properties": {
    "iso:country":"RU",
    "name:rus_x_preferred":[
        "\u0411\u0443\u0442\u044b\u0440\u0441\u043a\u0438\u0439"
    ],
    "wof:name":"Butyrsky",
    "wof:placetype":"neighbourhood"
},
  "geometry": {"coordinates":[37.58922766947211,55.81268744256456],"type":"Point"}
}