{
  "type": "Feature",
  "properties": {
    "gn:admin1_code":"51",
    "gn:asciiname":"Opalikha",
    "gn:country_code":"RU",
    "gn:dem":78,
    "gn:feature_class":"P",
    "gn:feature_code":"PPL",
    "gn:name":"Opalikha",
    "gn:population":0,
    "gn:timezone":"Europe/Moscow",
    "iso:country":"RU",
    "name:rus_x_preferred":[
        "\u041e\u043f\u0430\u043b\u0438\u0445\u0430"
    ],
    "name:und_x_variant":[
        "\u041e\u043f\u0430\u043b\u0438\u0445\u0430"
    ],
    "wof:name":"Opalikha",
    "wof:placetype":"locality"
},
  "geometry": {"coordinates":[44.12024,56.20256],"type":"Point"}
}