{
  "type": "Feature",
  "properties": {
    "gn:admin1_code":"71.0",
    "gn:asciiname":"Dobanchino",
    "gn:country_code":"RU",
    "gn:dem":63,
    "gn:feature_class":"P",
    "gn:feature_code":"PPL",
    "gn:name":"Dobanchino",
    "gn:population":0,
    "gn:timezone":"Asia/Yekaterinburg",
    "iso:country":"RU",
    "name:rus_x_preferred":[
        "\u0414\u043e\u0431\u0430\u043d\u0447\u0438\u043d\u043e"
    ],
    "wof:name":"Dobanchino",
    "wof:placetype":"locality"
},
  "geometry": {"coordinates":[63.71762,58.08815],"type":"Point"}
}