{
  "type": "Feature",
  "properties": {
    "gn:admin1_code":"21",
    "gn:asciiname":"Maritsyno",
    "gn:country_code":"RU",
    "gn:dem":130,
    "gn:feature_class":"P",
    "gn:feature_code":"PPL",
    "gn:name":"Maritsyno",
    "gn:population":0,
    "gn:timezone":"Europe/Moscow",
    "iso:country":"RU",
    "name:rus_x_preferred":[
        "\u041c\u0430\u0440\u0438\u0446\u044b\u043d\u043e"
    ],
    "name:und_x_variant":[
        "Maritsino",
        "Maritsyno"
    ],
    "wof:name":"Maritsyno",
    "wof:placetype":"locality"
},
  "geometry": {"coordinates":[41.26806,57.08891],"type":"Point"}
}