{
  "type": "Feature",
  "properties": {
    "gn:admin1_code":"60",
    "gn:asciiname":"Galukha",
    "gn:country_code":"RU",
    "gn:dem":94,
    "gn:feature_class":"P",
    "gn:feature_code":"PPL",
    "gn:name":"Galukha",
    "gn:population":0,
    "gn:timezone":"Europe/Moscow",
    "iso:country":"RU",
    "name:rus_x_preferred":[
        "\u0413\u0430\u043b\u0443\u0445\u0430"
    ],
    "wof:name":"Galukha",
    "wof:placetype":"locality"
},
  "geometry": {"coordinates":[28.69448,56.74035],"type":"Point"}
}