{
  "type": "Feature",
  "properties": {
    "gn:admin1_code":"53",
    "gn:asciiname":"Levaya Sosnovka",
    "gn:country_code":"RU",
    "gn:dem":194,
    "gn:feature_class":"P",
    "gn:feature_code":"PPL",
    "gn:name":"Levaya Sosnovka",
    "gn:population":0,
    "gn:timezone":"Asia/Novosibirsk",
    "iso:country":"RU",
    "name:rus_x_preferred":[
        "\u041b\u0435\u0432\u0430\u044f \u0421\u043e\u0441\u043d\u043e\u0432\u043a\u0430"
    ],
    "wof:name":"Levaya Sosnovka",
    "wof:placetype":"locality"
},
  "geometry": {"coordinates":[84.73333000000002,55.55],"type":"Point"}
}