{
  "type": "Feature",
  "properties": {
    "gn:admin1_code":"59",
    "gn:asciiname":"Kiparisovo",
    "gn:country_code":"RU",
    "gn:dem":12,
    "gn:feature_class":"P",
    "gn:feature_code":"PPL",
    "gn:name":"Kiparisovo",
    "gn:population":676,
    "gn:timezone":"Asia/Vladivostok",
    "iso:country":"RU",
    "name:eng_x_preferred":[
        "Kiparisovo Dva"
    ],
    "name:nor_x_preferred":[
        "Kiparisovo"
    ],
    "name:rus_x_preferred":[
        "\u041a\u0438\u043f\u0430\u0440\u0438\u0441\u043e\u0432\u043e"
    ],
    "name:und_x_variant":[
        "Kiparisovka",
        "Kiparisova",
        "Kiparesovo",
        "Kiparisovo Dva",
        "Kiparisovo-Vtoroye"
    ],
    "wof:name":"Kiparisovo",
    "wof:placetype":"locality",
    "wof:population":676
},
  "geometry": {"coordinates":[131.93178999999998,43.44835],"type":"Point"}
}