{
  "type": "Feature",
  "properties": {
    "gn:admin1_code":"88",
    "gn:asciiname":"Yashkurovo",
    "gn:country_code":"RU",
    "gn:dem":158,
    "gn:feature_class":"P",
    "gn:feature_code":"PPL",
    "gn:name":"Yashkurovo",
    "gn:population":0,
    "gn:timezone":"Europe/Moscow",
    "iso:country":"RU",
    "name:rus_x_preferred":[
        "\u042f\u0448\u043a\u0443\u0440\u043e\u0432\u043e"
    ],
    "wof:name":"Yashkurovo",
    "wof:placetype":"locality"
},
  "geometry": {"coordinates":[38.73353,57.18478],"type":"Point"}
}