{
  "type": "Feature",
  "properties": {
    "gn:admin1_code":"33.0",
    "gn:asciiname":"Dolgany",
    "gn:country_code":"RU",
    "gn:dem":150,
    "gn:feature_class":"P",
    "gn:feature_code":"PPL",
    "gn:name":"Dolgany",
    "gn:population":0,
    "gn:timezone":"Europe/Kirov",
    "iso:country":"RU",
    "name:rus_x_preferred":[
        "\u0414\u043e\u043b\u0433\u0430\u043d\u044b"
    ],
    "wof:name":"Dolgany",
    "wof:placetype":"locality"
},
  "geometry": {"coordinates":[50.29663,58.43603],"type":"Point"}
}