{
  "type": "Feature",
  "properties": {
    "gn:admin1_code":"20",
    "gn:asciiname":"Ust'-Khayga",
    "gn:country_code":"RU",
    "gn:dem":391,
    "gn:feature_class":"P",
    "gn:feature_code":"PPL",
    "gn:name":"Ust\u2019-Khayga",
    "gn:population":0,
    "gn:timezone":"Asia/Irkutsk",
    "iso:country":"RU",
    "name:rus_x_preferred":[
        "\u0423\u0441\u0442\u044c-\u0425\u0430\u0439\u0433\u0430"
    ],
    "name:und_x_variant":[
        "Ust\u2019-Khayga"
    ],
    "wof:name":"Ust'-Khayga",
    "wof:placetype":"locality"
},
  "geometry": {"coordinates":[103.7702,53.6592],"type":"Point"}
}