{
  "type": "Feature",
  "properties": {
    "gn:admin1_code":"60",
    "gn:asciiname":"Zelenyye Luga",
    "gn:country_code":"RU",
    "gn:dem":190,
    "gn:feature_class":"P",
    "gn:feature_code":"PPL",
    "gn:name":"Zel\u00ebnyye Luga",
    "gn:population":0,
    "gn:timezone":"Europe/Moscow",
    "iso:country":"RU",
    "name:und_x_variant":[
        "Zelenye Luga",
        "Zel\u00ebnyye Luga"
    ],
    "wof:name":"Zelenyye Luga",
    "wof:placetype":"locality"
},
  "geometry": {"coordinates":[30.24965,55.8887],"type":"Point"}
}