{
  "type": "Feature",
  "properties": {
    "gn:admin1_code":"60",
    "gn:asciiname":"Toroptsevo",
    "gn:country_code":"RU",
    "gn:dem":107,
    "gn:feature_class":"P",
    "gn:feature_code":"PPL",
    "gn:name":"Toroptsevo",
    "gn:population":0,
    "gn:timezone":"Europe/Moscow",
    "iso:country":"RU",
    "name:rus_x_preferred":[
        "\u0422\u043e\u0440\u043e\u043f\u0446\u0435\u0432\u043e"
    ],
    "wof:name":"Toroptsevo",
    "wof:placetype":"locality"
},
  "geometry": {"coordinates":[28.68197,56.66784000000001],"type":"Point"}
}