{
  "type": "Feature",
  "properties": {
    "gn:admin1_code":"8",
    "gn:asciiname":"Kutushevo",
    "gn:country_code":"RU",
    "gn:dem":167,
    "gn:feature_class":"P",
    "gn:feature_code":"PPL",
    "gn:name":"Kutushevo",
    "gn:population":0,
    "gn:timezone":"Asia/Yekaterinburg",
    "iso:country":"RU",
    "name:rus_x_preferred":[
        "\u041a\u0443\u0442\u0443\u0448\u0435\u0432\u043e"
    ],
    "wof:name":"Kutushevo",
    "wof:placetype":"locality"
},
  "geometry": {"coordinates":[55.9604,53.0086],"type":"Point"}
}