{
  "type": "Feature",
  "properties": {
    "gn:admin1_code":"42",
    "gn:asciiname":"Sakharova",
    "gn:country_code":"RU",
    "gn:dem":172,
    "gn:feature_class":"P",
    "gn:feature_code":"PPL",
    "gn:name":"Sakharova",
    "gn:population":0,
    "gn:timezone":"Europe/Moscow",
    "iso:country":"RU",
    "name:rus_x_preferred":[
        "\u0421\u0430\u0445\u0430\u0440\u043e\u0432\u0430"
    ],
    "wof:name":"Sakharova",
    "wof:placetype":"locality"
},
  "geometry": {"coordinates":[35.33333,59.61666999999999],"type":"Point"}
}