{
  "type": "Feature",
  "properties": {
    "gn:admin1_code":"38",
    "gn:asciiname":"Novo-Nikolayevskiy",
    "gn:country_code":"RU",
    "gn:dem":434,
    "gn:feature_class":"P",
    "gn:feature_code":"PPL",
    "gn:name":"Novo-Nikolayevskiy",
    "gn:population":0,
    "gn:timezone":"Europe/Moscow",
    "iso:country":"RU",
    "wof:name":"Novo-Nikolayevskiy",
    "wof:placetype":"locality"
},
  "geometry": {"coordinates":[41.49333,44.95833],"type":"Point"}
}