{
  "type": "Feature",
  "properties": {
    "gn:admin1_code":"62",
    "gn:asciiname":"Senin Pchel'nik",
    "gn:country_code":"RU",
    "gn:dem":88,
    "gn:feature_class":"P",
    "gn:feature_code":"PPL",
    "gn:name":"Senin Pchel\u2019nik",
    "gn:population":0,
    "gn:timezone":"Europe/Moscow",
    "iso:country":"RU",
    "name:rus_x_preferred":[
        "\u0421\u0435\u043d\u0438\u043d \u041f\u0447\u0435\u043b\u044c\u043d\u0438\u043a"
    ],
    "name:und_x_variant":[
        "Senin Pchel\u2019nik",
        "\u0421\u0435\u043d\u0438\u043d \u041f\u0447\u0435\u043b\u044c\u043d\u0438\u043a"
    ],
    "wof:name":"Senin Pchel'nik",
    "wof:placetype":"locality"
},
  "geometry": {"coordinates":[41.90503,54.81396],"type":"Point"}
}