{
  "type": "Feature",
  "properties": {
    "gn:admin1_code":"63",
    "gn:asciiname":"Dayya",
    "gn:cc2":"RU",
    "gn:country_code":"RU",
    "gn:dem":162,
    "gn:feature_class":"P",
    "gn:feature_code":"PPL",
    "gn:name":"Dayya",
    "gn:population":0,
    "gn:timezone":"Asia/Yakutsk",
    "iso:country":"RU",
    "name:rus_x_preferred":[
        "\u0414\u0430\u0439\u044f"
    ],
    "name:und_x_variant":[
        "Daya",
        "Dayya"
    ],
    "wof:name":"Dayya",
    "wof:placetype":"locality"
},
  "geometry": {"coordinates":[133.61667,61.95],"type":"Point"}
}