{
  "type": "Feature",
  "properties": {
    "gn:admin1_code":"8",
    "gn:asciiname":"Kanton",
    "gn:country_code":"RU",
    "gn:dem":150,
    "gn:feature_class":"P",
    "gn:feature_code":"PPL",
    "gn:name":"Kanton",
    "gn:population":0,
    "gn:timezone":"Asia/Yekaterinburg",
    "iso:country":"RU",
    "name:afr_x_preferred":[
        "Kanton"
    ],
    "name:als_x_preferred":[
        "Kanton"
    ],
    "name:ara_x_preferred":[
        "\u0643\u0627\u0646\u062a\u0648\u0646"
    ],
    "name:aze_x_preferred":[
        "Kanton"
    ],
    "name:bel_x_preferred":[
        "\u041a\u0430\u043d\u0442\u043e\u043d"
    ],
    "name:bos_x_preferred":[
        "Kanton"
    ],
    "name:bre_x_preferred":[
        "Kanton"
    ],
    "name:bul_x_preferred":[
        "\u041a\u0430\u043d\u0442\u043e\u043d"
    ],
    "name:ceb_x_preferred":[
        "Kanton"
    ],
    "name:ces_x_preferred":[
        "Kanton"
    ],
    "name:ckb_x_preferred":[
        "\u06a9\u0627\u0646\u062a\u06c6\u0646"
    ],
    "name:dan_x_preferred":[
        "Kanton"
    ],
    "name:deu_x_preferred":[
        "Kanton"
    ],
    "name:ell_x_preferred":[
        "\u039a\u03b1\u03bd\u03c4\u03cc\u03bd\u03b9"
    ],
    "name:epo_x_preferred":[
        "Kantono"
    ],
    "name:fas_x_preferred":[
        "\u06a9\u0627\u0646\u062a\u0648\u0646"
    ],
    "name:fin_x_preferred":[
        "Kantoni"
    ],
    "name:heb_x_preferred":[
        "\u05e7\u05e0\u05d8\u05d5\u05df"
    ],
    "name:hrv_x_preferred":[
        "Kanton"
    ],
    "name:hun_x_preferred":[
        "Kanton"
    ],
    "name:ind_x_preferred":[
        "Kanton"
    ],
    "name:isl_x_preferred":[
        "Kanton"
    ],
    "name:jpn_x_preferred":[
        "\u30ab\u30f3\u30c8\u30f3"
    ],
    "name:kaz_x_preferred":[
        "\u041a\u0430\u043d\u0442\u043e\u043d"
    ],
    "name:lit_x_preferred":[
        "Kantonas"
    ],
    "name:ltz_x_preferred":[
        "Kanton"
    ],
    "name:msa_x_preferred":[
        "Kanton"
    ],
    "name:nld_x_preferred":[
        "Kanton"
    ],
    "name:nno_x_preferred":[
        "Kanton"
    ],
    "name:nor_x_preferred":[
        "Kanton"
    ],
    "name:pol_x_preferred":[
        "Kanton"
    ],
    "name:por_x_preferred":[
        "Kanton"
    ],
    "name:rus_x_preferred":[
        "\u041a\u0430\u043d\u0442\u043e\u043d"
    ],
    "name:slk_x_preferred":[
        "Kanton"
    ],
    "name:slv_x_preferred":[
        "Kanton"
    ],
    "name:srp_x_preferred":[
        "\u041a\u0430\u043d\u0442\u043e\u043d"
    ],
    "name:swe_x_preferred":[
        "Kanton"
    ],
    "name:tat_x_preferred":[
        "Kanton"
    ],
    "name:ukr_x_preferred":[
        "\u041a\u0430\u043d\u0442\u043e\u043d"
    ],
    "name:und_x_variant":[
        "Kantonovo"
    ],
    "wof:name":"Kanton",
    "wof:placetype":"locality"
},
  "geometry": {"coordinates":[57.11626,55.62085],"type":"Point"}
}