{
  "type": "Feature",
  "properties": {
    "gn:admin1_code":"85",
    "gn:asciiname":"Velikiy Dvor",
    "gn:country_code":"RU",
    "gn:dem":145,
    "gn:feature_class":"P",
    "gn:feature_code":"PPL",
    "gn:name":"Velikiy Dvor",
    "gn:population":0,
    "gn:timezone":"Europe/Moscow",
    "iso:country":"RU",
    "name:und_x_variant":[
        "Almozerskiy Pogost",
        "Velikiy Dvor"
    ],
    "wof:name":"Velikiy Dvor",
    "wof:placetype":"locality"
},
  "geometry": {"coordinates":[36.78513,60.79076],"type":"Point"}
}