{
  "type": "Feature",
  "properties": {
    "gn:admin1_code":"68.0",
    "gn:asciiname":"Khodysta",
    "gn:country_code":"RU",
    "gn:dem":1603,
    "gn:feature_class":"P",
    "gn:feature_code":"PPL",
    "gn:name":"Khodysta",
    "gn:population":0,
    "gn:timezone":"Europe/Moscow",
    "iso:country":"RU",
    "name:eng_x_preferred":[
        "Khodysta"
    ],
    "name:nor_x_preferred":[
        "Kholst"
    ],
    "name:rus_x_preferred":[
        "\u0425\u043e\u043b\u0441\u0442"
    ],
    "name:rus_x_variant":[
        "\u0425\u043e\u0434\u044b\u0441\u0442\u0430"
    ],
    "wof:name":"Khodysta",
    "wof:placetype":"locality"
},
  "geometry": {"coordinates":[44.15722,42.82667],"type":"Point"}
}