{
  "type": "Feature",
  "properties": {
    "gn:admin1_code":"54",
    "gn:asciiname":"Kartashovo",
    "gn:country_code":"RU",
    "gn:dem":85,
    "gn:feature_class":"P",
    "gn:feature_code":"PPL",
    "gn:name":"Kartashovo",
    "gn:population":0,
    "gn:timezone":"Asia/Omsk",
    "iso:country":"RU",
    "name:eng_x_preferred":[
        "Kartash\u00ebvo"
    ],
    "name:nor_x_preferred":[
        "Kartasjevo"
    ],
    "name:rus_x_preferred":[
        "\u041a\u0430\u0440\u0442\u0430\u0448\u0435\u0432\u043e"
    ],
    "name:rus_x_variant":[
        "\u041a\u0430\u0440\u0442\u0430\u0448\u043e\u0432\u043e"
    ],
    "name:und_x_variant":[
        "Kartash\u00ebva",
        "Kartashovo",
        "Kartash\u00ebvo",
        "\u041a\u0430\u0440\u0442\u0430\u0448\u043e\u0432\u043e"
    ],
    "wof:name":"Kartashovo",
    "wof:placetype":"locality"
},
  "geometry": {"coordinates":[74.73656,56.11662],"type":"Point"}
}