{
  "type": "Feature",
  "properties": {
    "gn:admin1_code":"37",
    "gn:asciiname":"Gomonikha",
    "gn:country_code":"RU",
    "gn:dem":86,
    "gn:feature_class":"P",
    "gn:feature_code":"PPL",
    "gn:name":"Gomonikha",
    "gn:population":0,
    "gn:timezone":"Europe/Moscow",
    "iso:country":"RU",
    "name:rus_x_preferred":[
        "\u0413\u043e\u043c\u043e\u043d\u0438\u0445\u0430"
    ],
    "wof:name":"Gomonikha",
    "wof:placetype":"locality"
},
  "geometry": {"coordinates":[41.10466,57.60711],"type":"Point"}
}