{
  "type": "Feature",
  "properties": {
    "gn:admin1_code":"52.0",
    "gn:asciiname":"Astritovo",
    "gn:country_code":"RU",
    "gn:dem":56,
    "gn:feature_class":"P",
    "gn:feature_code":"PPL",
    "gn:name":"Astritovo",
    "gn:population":0,
    "gn:timezone":"Europe/Moscow",
    "iso:country":"RU",
    "name:eng_x_preferred":[
        "Astratovo"
    ],
    "name:nor_x_preferred":[
        "Astratovo"
    ],
    "name:rus_x_preferred":[
        "\u0410\u0441\u0442\u0440\u0438\u0442\u043e\u0432\u043e"
    ],
    "name:und_x_variant":[
        "Astratova",
        "Astritovo"
    ],
    "wof:name":"Astritovo",
    "wof:placetype":"locality"
},
  "geometry": {"coordinates":[31.35376,57.54301],"type":"Point"}
}