{
  "type": "Feature",
  "properties": {
    "gn:admin1_code":"25",
    "gn:asciiname":"Pavlovo",
    "gn:country_code":"RU",
    "gn:dem":148,
    "gn:feature_class":"P",
    "gn:feature_code":"PPL",
    "gn:name":"Pavlovo",
    "gn:population":0,
    "gn:timezone":"Europe/Moscow",
    "iso:country":"RU",
    "name:rus_x_preferred":[
        "\u041f\u0430\u0432\u043b\u043e\u0432\u043e"
    ],
    "name:und_x_variant":[
        "\u041f\u0430\u0432\u043b\u043e\u0432\u043e"
    ],
    "wof:name":"Pavlovo",
    "wof:placetype":"locality"
},
  "geometry": {"coordinates":[35.54672,53.90016],"type":"Point"}
}