{
  "type": "Feature",
  "properties": {
    "gn:admin1_code":"20",
    "gn:asciiname":"Khiginskaya",
    "gn:country_code":"RU",
    "gn:dem":520,
    "gn:feature_class":"P",
    "gn:feature_code":"PPL",
    "gn:name":"Khiginskaya",
    "gn:population":0,
    "gn:timezone":"Asia/Irkutsk",
    "iso:country":"RU",
    "name:rus_x_preferred":[
        "\u0425\u0438\u0433\u0438\u043d\u0441\u043a\u0430\u044f"
    ],
    "name:und_x_variant":[
        "Khiginskiy",
        "Khiginskaya"
    ],
    "wof:name":"Khiginskaya",
    "wof:placetype":"locality"
},
  "geometry": {"coordinates":[102.6794,53.1236],"type":"Point"}
}