{
  "type": "Feature",
  "properties": {
    "gn:admin1_code":"54",
    "gn:asciiname":"Alabota",
    "gn:country_code":"RU",
    "gn:dem":116,
    "gn:feature_class":"P",
    "gn:feature_code":"PPL",
    "gn:name":"Alabota",
    "gn:population":0,
    "gn:timezone":"Asia/Omsk",
    "iso:country":"RU",
    "name:eng_x_preferred":[
        "Alabota"
    ],
    "name:nor_x_preferred":[
        "Alabota"
    ],
    "name:rus_x_preferred":[
        "\u0410\u043b\u0430\u0431\u043e\u0442\u0430"
    ],
    "name:und_x_variant":[
        "\u0410\u043b\u0430\u0431\u043e\u0442\u0430",
        "Alabota"
    ],
    "wof:name":"Alabota",
    "wof:placetype":"locality"
},
  "geometry": {"coordinates":[73.76222,53.95056],"type":"Point"}
}