{
  "type": "Feature",
  "properties": {
    "gn:admin1_code":"72",
    "gn:asciiname":"Pokrovo-Marfino",
    "gn:country_code":"RU",
    "gn:dem":156,
    "gn:feature_class":"P",
    "gn:feature_code":"PPL",
    "gn:name":"Pokrovo-Marfino",
    "gn:population":0,
    "gn:timezone":"Europe/Moscow",
    "iso:country":"RU",
    "name:eng_x_preferred":[
        "Pokrove-Marfino"
    ],
    "name:nor_x_preferred":[
        "Pokrovo-Marfino"
    ],
    "name:rus_x_preferred":[
        "\u041f\u043e\u043a\u0440\u043e\u0432\u043e-\u041c\u0430\u0440\u0444\u0438\u043d\u043e"
    ],
    "name:und_x_variant":[
        "Pokrovskoye-Marfino"
    ],
    "wof:name":"Pokrovo-Marfino",
    "wof:placetype":"locality"
},
  "geometry": {"coordinates":[41.02729,52.41335],"type":"Point"}
}