{
  "type": "Feature",
  "properties": {
    "gn:admin1_code":"28",
    "gn:asciiname":"Kellola",
    "gn:country_code":"RU",
    "gn:dem":129,
    "gn:feature_class":"P",
    "gn:feature_code":"PPL",
    "gn:name":"Kellola",
    "gn:population":0,
    "gn:timezone":"Europe/Moscow",
    "iso:country":"RU",
    "name:rus_x_preferred":[
        "\u041a\u0435\u043b\u043b\u043e\u043b\u0430"
    ],
    "wof:name":"Kellola",
    "wof:placetype":"locality"
},
  "geometry": {"coordinates":[32.96619,62.89068],"type":"Point"}
}