{
  "type": "Feature",
  "properties": {
    "gn:admin1_code":"11",
    "gn:asciiname":"Amagalantuy",
    "gn:country_code":"RU",
    "gn:dem":709,
    "gn:feature_class":"P",
    "gn:feature_code":"PPL",
    "gn:name":"Amagalantuy",
    "gn:population":0,
    "gn:timezone":"Asia/Irkutsk",
    "iso:country":"RU",
    "name:rus_x_preferred":[
        "\u0410\u043c\u0430\u0433\u0430\u043b\u0430\u043d\u0442\u0443\u0439"
    ],
    "name:und_x_variant":[
        "Khokhyurta"
    ],
    "wof:name":"Amagalantuy",
    "wof:placetype":"locality"
},
  "geometry": {"coordinates":[108.04989999999999,50.8233],"type":"Point"}
}