{
  "type": "Feature",
  "properties": {
    "gn:admin1_code":"46.0",
    "gn:asciiname":"Veselyy",
    "gn:country_code":"RU",
    "gn:dem":180,
    "gn:feature_class":"P",
    "gn:feature_code":"PPL",
    "gn:name":"Ves\u00eblyy",
    "gn:population":0,
    "gn:timezone":"Europe/Moscow",
    "iso:country":"RU",
    "wof:name":"Veselyy",
    "wof:placetype":"locality"
},
  "geometry": {"coordinates":[43.01619,54.54793000000001],"type":"Point"}
}