{
  "type": "Feature",
  "properties": {
    "gn:admin1_code":"69",
    "gn:asciiname":"Turinshchina",
    "gn:country_code":"RU",
    "gn:dem":207,
    "gn:feature_class":"P",
    "gn:feature_code":"PPL",
    "gn:name":"Turinshchina",
    "gn:population":0,
    "gn:timezone":"Europe/Moscow",
    "iso:country":"RU",
    "name:rus_x_preferred":[
        "\u0422\u0443\u0440\u0438\u043d\u0449\u0438\u043d\u0430"
    ],
    "name:und_x_variant":[
        "Gurinshchina",
        "Turinshchina"
    ],
    "wof:name":"Turinshchina",
    "wof:placetype":"locality"
},
  "geometry": {"coordinates":[32.13936,54.75239000000001],"type":"Point"}
}