{
  "type": "Feature",
  "properties": {
    "gn:admin1_code":"41",
    "gn:asciiname":"Pokrovskoye",
    "gn:country_code":"RU",
    "gn:dem":158,
    "gn:feature_class":"P",
    "gn:feature_code":"PPL",
    "gn:name":"Pokrovskoye",
    "gn:population":0,
    "gn:timezone":"Europe/Moscow",
    "iso:country":"RU",
    "name:rus_x_preferred":[
        "\u041f\u043e\u043a\u0440\u043e\u0432\u0441\u043a\u043e\u0435"
    ],
    "name:und_x_variant":[
        "Pokrovka"
    ],
    "wof:name":"Pokrovskoye",
    "wof:placetype":"locality"
},
  "geometry": {"coordinates":[37.4524,51.4315],"type":"Point"}
}