{
  "type": "Feature",
  "properties": {
    "gn:admin1_code":"8",
    "gn:asciiname":"Itkulovo",
    "gn:country_code":"RU",
    "gn:dem":245,
    "gn:feature_class":"P",
    "gn:feature_code":"PPL",
    "gn:name":"Itkulovo",
    "gn:population":0,
    "gn:timezone":"Asia/Yekaterinburg",
    "iso:country":"RU",
    "name:eng_x_preferred":[
        "Itkulovo"
    ],
    "name:nor_x_preferred":[
        "Itkulovo"
    ],
    "name:rus_x_preferred":[
        "\u0418\u0442\u043a\u0443\u043b\u043e\u0432\u043e"
    ],
    "name:und_x_variant":[
        "Yuldashevo",
        "Itulovo",
        "\u0418\u0442\u043a\u0443\u043b\u043e\u0432\u043e",
        "Itkulovo"
    ],
    "wof:name":"Itkulovo",
    "wof:placetype":"locality"
},
  "geometry": {"coordinates":[56.84056,51.87325],"type":"Point"}
}