{
  "type": "Feature",
  "properties": {
    "gn:admin1_code":"60",
    "gn:asciiname":"Tiushi",
    "gn:country_code":"RU",
    "gn:dem":55,
    "gn:feature_class":"P",
    "gn:feature_code":"PPL",
    "gn:name":"Tiushi",
    "gn:population":0,
    "gn:timezone":"Europe/Moscow",
    "iso:country":"RU",
    "name:rus_x_preferred":[
        "\u0422\u0438\u0443\u0448\u0438"
    ],
    "wof:name":"Tiushi",
    "wof:placetype":"locality"
},
  "geometry": {"coordinates":[28.09176,57.56394],"type":"Point"}
}