{
  "type": "Feature",
  "properties": {
    "gn:admin1_code":"05",
    "gn:asciiname":"Preobrazhenovka",
    "gn:country_code":"RU",
    "gn:dem":201,
    "gn:feature_class":"P",
    "gn:feature_code":"PPL",
    "gn:name":"Preobrazhenovka",
    "gn:population":0,
    "gn:timezone":"Asia/Yakutsk",
    "iso:country":"RU",
    "name:eng_x_preferred":[
        "Preobrazhenovka"
    ],
    "name:nor_x_preferred":[
        "Preobrazjenovka"
    ],
    "name:rus_x_preferred":[
        "\u041f\u0440\u0435\u043e\u0431\u0440\u0430\u0436\u0435\u043d\u043e\u0432\u043a\u0430"
    ],
    "name:und_x_variant":[
        "Preobrazhenka"
    ],
    "wof:name":"Preobrazhenovka",
    "wof:placetype":"locality"
},
  "geometry": {"coordinates":[128.64706000000001,50.42945],"type":"Point"}
}