{
  "type": "Feature",
  "properties": {
    "gn:admin1_code":"51",
    "gn:asciiname":"Radyushata",
    "gn:country_code":"RU",
    "gn:dem":109,
    "gn:feature_class":"P",
    "gn:feature_code":"PPL",
    "gn:name":"Radyushata",
    "gn:population":0,
    "gn:timezone":"Europe/Moscow",
    "iso:country":"RU",
    "name:rus_x_preferred":[
        "\u0420\u0430\u0434\u044e\u0448\u0430\u0442\u0430"
    ],
    "wof:name":"Radyushata",
    "wof:placetype":"locality"
},
  "geometry": {"coordinates":[47.4593,57.6857],"type":"Point"}
}