{
  "type": "Feature",
  "properties": {
    "gn:admin1_code":"31",
    "gn:asciiname":"Chalgystag",
    "gn:country_code":"RU",
    "gn:dem":625,
    "gn:feature_class":"P",
    "gn:feature_code":"PPL",
    "gn:name":"Chalgystag",
    "gn:population":0,
    "gn:timezone":"Asia/Krasnoyarsk",
    "iso:country":"RU",
    "name:eng_x_preferred":[
        "Chalgystag"
    ],
    "name:nor_x_preferred":[
        "Tsjalgystag"
    ],
    "name:rus_x_preferred":[
        "\u0427\u0430\u043b\u0433\u044b\u0441\u0442\u0430\u0433"
    ],
    "name:und_x_variant":[
        "\u0427\u0430\u043b\u0433\u044b\u0441\u0442\u0430\u0433",
        "Chalgystag"
    ],
    "wof:name":"Chalgystag",
    "wof:placetype":"locality"
},
  "geometry": {"coordinates":[90.05500000000001,54.31528],"type":"Point"}
}