{
  "type": "Feature",
  "properties": {
    "gn:admin1_code":"61.0",
    "gn:asciiname":"Kholodnyy Polyachkov",
    "gn:country_code":"RU",
    "gn:dem":66,
    "gn:feature_class":"P",
    "gn:feature_code":"PPL",
    "gn:name":"Kholodnyy Polyachkov",
    "gn:population":0,
    "gn:timezone":"Europe/Moscow",
    "iso:country":"RU",
    "name:rus_x_preferred":[
        "\u0425\u043e\u043b\u043e\u0434\u043d\u044b\u0439 \u041f\u043e\u043b\u044f\u0447\u043a\u043e\u0432"
    ],
    "wof:name":"Kholodnyy Polyachkov",
    "wof:placetype":"locality"
},
  "geometry": {"coordinates":[41.1475,48.87167],"type":"Point"}
}