{
  "type": "Feature",
  "properties": {
    "gn:admin1_code":"25",
    "gn:asciiname":"Potapovo",
    "gn:country_code":"RU",
    "gn:dem":225,
    "gn:feature_class":"P",
    "gn:feature_code":"PPL",
    "gn:name":"Potapovo",
    "gn:population":0,
    "gn:timezone":"Europe/Moscow",
    "iso:country":"RU",
    "name:rus_x_preferred":[
        "\u041f\u043e\u0442\u0430\u043f\u043e\u0432\u043e"
    ],
    "name:und_x_variant":[
        "\u041f\u043e\u0442\u0430\u043f\u043e\u0432\u043e"
    ],
    "wof:name":"Potapovo",
    "wof:placetype":"locality"
},
  "geometry": {"coordinates":[35.18942,54.25048],"type":"Point"}
}