{
  "type": "Feature",
  "properties": {
    "gn:admin1_code":"83",
    "gn:asciiname":"Ramen'",
    "gn:country_code":"RU",
    "gn:dem":129,
    "gn:feature_class":"P",
    "gn:feature_code":"PPL",
    "gn:name":"Ramen\u2019",
    "gn:population":0,
    "gn:timezone":"Europe/Moscow",
    "iso:country":"RU",
    "name:rus_x_preferred":[
        "\u0420\u0430\u043c\u0435\u043d\u044c"
    ],
    "name:und_x_variant":[
        "Ramen\u2019ya",
        "Ramen\u2019ye",
        "Ramen\u2019"
    ],
    "wof:name":"Ramen'",
    "wof:placetype":"locality"
},
  "geometry": {"coordinates":[41.46667,55.18923],"type":"Point"}
}