{
  "type": "Feature",
  "properties": {
    "gn:admin1_code":"88",
    "gn:asciiname":"Kichibunikha",
    "gn:country_code":"RU",
    "gn:dem":181,
    "gn:feature_class":"P",
    "gn:feature_code":"PPL",
    "gn:name":"Kichibunikha",
    "gn:population":0,
    "gn:timezone":"Europe/Moscow",
    "iso:country":"RU",
    "name:rus_x_preferred":[
        "\u041a\u0438\u0447\u0438\u0431\u0443\u043d\u0438\u0445\u0430"
    ],
    "name:und_x_variant":[
        "Kichibukhina",
        "Kichibunikha"
    ],
    "wof:name":"Kichibunikha",
    "wof:placetype":"locality"
},
  "geometry": {"coordinates":[38.95538,56.68333000000001],"type":"Point"}
}