{
  "type": "Feature",
  "properties": {
    "gn:admin1_code":"55",
    "gn:asciiname":"Klenovyy",
    "gn:country_code":"RU",
    "gn:dem":106,
    "gn:feature_class":"P",
    "gn:feature_code":"PPL",
    "gn:name":"Klenovyy",
    "gn:population":0,
    "gn:timezone":"Asia/Yekaterinburg",
    "iso:country":"RU",
    "name:rus_x_preferred":[
        "\u041a\u043b\u0435\u043d\u043e\u0432\u044b\u0439"
    ],
    "name:und_x_variant":[
        "\u041a\u043b\u0435\u043d\u043e\u0432\u044b\u0439"
    ],
    "wof:name":"Klenovyy",
    "wof:placetype":"locality"
},
  "geometry": {"coordinates":[53.3853,52.3085],"type":"Point"}
}