{
  "type": "Feature",
  "properties": {
    "gn:admin1_code":"84",
    "gn:asciiname":"Lyalinskiy",
    "gn:country_code":"RU",
    "gn:dem":69,
    "gn:feature_class":"P",
    "gn:feature_code":"PPL",
    "gn:name":"Lyalinskiy",
    "gn:population":0,
    "gn:timezone":"Europe/Volgograd",
    "iso:country":"RU",
    "name:rus_x_preferred":[
        "\u041b\u044f\u043b\u0438\u043d\u0441\u043a\u0438\u0439"
    ],
    "name:und_x_variant":[
        "\u041b\u044f\u043b\u0438\u043d\u0441\u043a\u0438\u0439"
    ],
    "wof:name":"Lyalinskiy",
    "wof:placetype":"locality"
},
  "geometry": {"coordinates":[42.5919,49.9662],"type":"Point"}
}