{
  "type": "Feature",
  "properties": {
    "gn:admin1_code":"25",
    "gn:asciiname":"Konovka",
    "gn:country_code":"RU",
    "gn:dem":229,
    "gn:feature_class":"P",
    "gn:feature_code":"PPL",
    "gn:name":"Konovka",
    "gn:population":0,
    "gn:timezone":"Europe/Moscow",
    "iso:country":"RU",
    "name:rus_x_preferred":[
        "\u041a\u043e\u043d\u043e\u0432\u043a\u0430"
    ],
    "name:und_x_variant":[
        "\u041a\u043e\u043d\u043e\u0432\u043a\u0430"
    ],
    "wof:name":"Konovka",
    "wof:placetype":"locality"
},
  "geometry": {"coordinates":[34.54244,54.09254],"type":"Point"}
}