{
  "type": "Feature",
  "properties": {
    "gn:admin1_code":"16",
    "gn:asciiname":"Shibylgi",
    "gn:country_code":"RU",
    "gn:dem":132,
    "gn:feature_class":"P",
    "gn:feature_code":"PPL",
    "gn:name":"Shibylgi",
    "gn:population":0,
    "gn:timezone":"Europe/Moscow",
    "iso:country":"RU",
    "name:eng_x_preferred":[
        "Shibylgi"
    ],
    "name:nor_x_preferred":[
        "Sjibylgi"
    ],
    "name:rus_x_preferred":[
        "\u0428\u0438\u0431\u044b\u043b\u0433\u0438"
    ],
    "wof:name":"Shibylgi",
    "wof:placetype":"locality"
},
  "geometry": {"coordinates":[47.4402,55.6145],"type":"Point"}
}