{
  "type": "Feature",
  "properties": {
    "gn:admin1_code":"33",
    "gn:asciiname":"Gorshata",
    "gn:country_code":"RU",
    "gn:dem":154,
    "gn:feature_class":"P",
    "gn:feature_code":"PPL",
    "gn:name":"Gorshata",
    "gn:population":0,
    "gn:timezone":"Europe/Kirov",
    "iso:country":"RU",
    "name:rus_x_preferred":[
        "\u0413\u043e\u0440\u0448\u0430\u0442\u0430"
    ],
    "name:und_x_variant":[
        "\u0413\u043e\u0440\u0448\u0430\u0442\u0430"
    ],
    "wof:name":"Gorshata",
    "wof:placetype":"locality"
},
  "geometry": {"coordinates":[48.41667,59.18333000000001],"type":"Point"}
}