{
  "type": "Feature",
  "properties": {
    "gn:admin1_code":"61.0",
    "gn:asciiname":"Cherkasskiy",
    "gn:country_code":"RU",
    "gn:dem":51,
    "gn:feature_class":"P",
    "gn:feature_code":"PPL",
    "gn:name":"Cherkasskiy",
    "gn:population":0,
    "gn:timezone":"Europe/Moscow",
    "iso:country":"RU",
    "name:rus_x_preferred":[
        "\u0427\u0435\u0440\u043a\u0430\u0441\u0441\u043a\u0438\u0439"
    ],
    "name:und_x_variant":[
        "\u0427\u0435\u0440\u043a\u0430\u0441\u0441\u043a\u0438\u0439"
    ],
    "wof:name":"Cherkasskiy",
    "wof:placetype":"locality"
},
  "geometry": {"coordinates":[42.01838,48.02236],"type":"Point"}
}