{
  "type": "Feature",
  "properties": {
    "gn:admin1_code":"69",
    "gn:asciiname":"Krupenikha",
    "gn:country_code":"RU",
    "gn:dem":238,
    "gn:feature_class":"P",
    "gn:feature_code":"PPL",
    "gn:name":"Krupenikha",
    "gn:population":0,
    "gn:timezone":"Europe/Moscow",
    "iso:country":"RU",
    "name:rus_x_preferred":[
        "\u041a\u0440\u0443\u043f\u0435\u043d\u0438\u0445\u0430"
    ],
    "name:und_x_variant":[
        "\u041a\u0440\u0443\u043f\u0435\u043d\u0438\u0445\u0430"
    ],
    "wof:name":"Krupenikha",
    "wof:placetype":"locality"
},
  "geometry": {"coordinates":[33.95206,55.63156],"type":"Point"}
}