{
  "type": "Feature",
  "properties": {
    "gn:admin1_code":"56.0",
    "gn:asciiname":"Alyab'yevo",
    "gn:country_code":"RU",
    "gn:dem":175,
    "gn:feature_class":"P",
    "gn:feature_code":"PPL",
    "gn:name":"Alyab\u2019yevo",
    "gn:population":0,
    "gn:timezone":"Europe/Moscow",
    "iso:country":"RU",
    "name:nor_x_preferred":[
        "Aljabjevo"
    ],
    "name:rus_x_preferred":[
        "\u0410\u043b\u044f\u0431\u044c\u0435\u0432\u043e"
    ],
    "name:und_x_variant":[
        "Nizhneye Alyab\u2019yevo",
        "Alyab\u2019yevo"
    ],
    "wof:name":"Alyab'yevo",
    "wof:placetype":"locality"
},
  "geometry": {"coordinates":[36.82388,53.26461],"type":"Point"}
}