{
  "type": "Feature",
  "properties": {
    "gn:admin1_code":"8",
    "gn:asciiname":"Vladimiro-Nikolayevskiy",
    "gn:country_code":"RU",
    "gn:dem":560,
    "gn:feature_class":"P",
    "gn:feature_code":"PPL",
    "gn:name":"Vladimiro-Nikolayevskiy",
    "gn:population":0,
    "gn:timezone":"Asia/Yekaterinburg",
    "iso:country":"RU",
    "name:rus_x_preferred":[
        "\u0412\u043b\u0430\u0434\u0438\u043c\u0438\u0440\u043e-\u041d\u0438\u043a\u043e\u043b\u0430\u0435\u0432\u0441\u043a\u0438\u0439"
    ],
    "wof:name":"Vladimiro-Nikolayevskiy",
    "wof:placetype":"locality"
},
  "geometry": {"coordinates":[57.5717,52.095],"type":"Point"}
}