{
  "type": "Feature",
  "properties": {
    "gn:admin1_code":"8",
    "gn:asciiname":"Kushtiryakovo",
    "gn:country_code":"RU",
    "gn:dem":85,
    "gn:feature_class":"P",
    "gn:feature_code":"PPL",
    "gn:name":"Kushtiryakovo",
    "gn:population":0,
    "gn:timezone":"Asia/Yekaterinburg",
    "iso:country":"RU",
    "name:eng_x_preferred":[
        "Kushtiryakovo"
    ],
    "name:nor_x_preferred":[
        "Kusjtirjakovo"
    ],
    "name:rus_x_preferred":[
        "\u041a\u0443\u0448\u0442\u0438\u0440\u044f\u043a\u043e\u0432\u043e"
    ],
    "name:und_x_variant":[
        "Kushteryakovo",
        "\u041a\u0443\u0448\u0442\u0438\u0440\u044f\u043a\u043e\u0432\u043e",
        "Kushtiryakovo"
    ],
    "wof:name":"Kushtiryakovo",
    "wof:placetype":"locality"
},
  "geometry": {"coordinates":[53.40944,55.01778],"type":"Point"}
}