{
  "type": "Feature",
  "properties": {
    "gn:admin1_code":"33.0",
    "gn:asciiname":"Yedineniye",
    "gn:country_code":"RU",
    "gn:dem":115,
    "gn:feature_class":"P",
    "gn:feature_code":"PPL",
    "gn:name":"Yedineniye",
    "gn:population":0,
    "gn:timezone":"Europe/Kirov",
    "iso:country":"RU",
    "name:rus_x_preferred":[
        "\u0415\u0434\u0438\u043d\u0435\u043d\u0438\u0435"
    ],
    "wof:name":"Yedineniye",
    "wof:placetype":"locality"
},
  "geometry": {"coordinates":[50.26544000000001,58.48169],"type":"Point"}
}