{
  "type": "Feature",
  "properties": {
    "gn:admin1_code":"6.0",
    "gn:asciiname":"Poboishche",
    "gn:country_code":"RU",
    "gn:dem":1,
    "gn:feature_class":"P",
    "gn:feature_code":"PPL",
    "gn:name":"Poboishche",
    "gn:population":0,
    "gn:timezone":"Europe/Moscow",
    "iso:country":"RU",
    "name:rus_x_preferred":[
        "\u041f\u043e\u0431\u043e\u0438\u0449\u0435"
    ],
    "wof:name":"Poboishche",
    "wof:placetype":"locality"
},
  "geometry": {"coordinates":[41.5148,64.2796],"type":"Point"}
}