{
  "type": "Feature",
  "properties": {
    "gn:admin1_code":"63",
    "gn:asciiname":"El'gendzha",
    "gn:country_code":"RU",
    "gn:dem":641,
    "gn:feature_class":"P",
    "gn:feature_code":"PPL",
    "gn:name":"El\u2019gendzha",
    "gn:population":0,
    "gn:timezone":"Asia/Vladivostok",
    "iso:country":"RU",
    "name:eng_x_preferred":[
        "El'gendzha"
    ],
    "name:nor_x_preferred":[
        "Elgendzja"
    ],
    "name:rus_x_preferred":[
        "\u042d\u043b\u044c\u0433\u0435\u043d\u0434\u0436\u0430"
    ],
    "name:und_x_variant":[
        "El\u2019gendzha"
    ],
    "wof:name":"El'gendzha",
    "wof:placetype":"locality"
},
  "geometry": {"coordinates":[137.94945000000001,65.88413],"type":"Point"}
}