{
  "type": "Feature",
  "properties": {
    "gn:admin1_code":"5",
    "gn:asciiname":"Voron'zha",
    "gn:country_code":"RU",
    "gn:dem":146,
    "gn:feature_class":"P",
    "gn:feature_code":"PPL",
    "gn:name":"Voron\u2019zha",
    "gn:population":0,
    "gn:timezone":"Asia/Yakutsk",
    "iso:country":"RU",
    "name:eng_x_preferred":[
        "Voron'zha"
    ],
    "name:nor_x_preferred":[
        "Voronzja"
    ],
    "name:rus_x_preferred":[
        "\u0412\u043e\u0440\u043e\u043d\u0436\u0430"
    ],
    "name:und_x_variant":[
        "Voran\u2019zha",
        "Voron\u2019zha"
    ],
    "wof:name":"Voron'zha",
    "wof:placetype":"locality"
},
  "geometry": {"coordinates":[128.11282,51.1511],"type":"Point"}
}