{
  "type": "Feature",
  "properties": {
    "gn:admin1_code":"93",
    "gn:asciiname":"Ust'-Ozernaya",
    "gn:country_code":"RU",
    "gn:dem":761,
    "gn:feature_class":"P",
    "gn:feature_code":"PPL",
    "gn:name":"Ust\u2019-Oz\u00ebrnaya",
    "gn:population":0,
    "gn:timezone":"Asia/Chita",
    "iso:country":"RU",
    "name:eng_x_preferred":[
        "Ust'-Oz\u00ebrnoye"
    ],
    "name:nor_x_preferred":[
        "Ust-Ozernaja"
    ],
    "name:rus_x_preferred":[
        "\u0423\u0441\u0442\u044c-\u041e\u0437\u0435\u0440\u043d\u0430\u044f"
    ],
    "name:rus_x_variant":[
        "\u0423\u0441\u0442\u044c-\u041e\u0437\u0451\u0440\u043d\u0430\u044f"
    ],
    "name:und_x_variant":[
        "Ust\u2019-Oz\u00ebrnaya",
        "Ust\u2019-Oz\u00ebrnoye"
    ],
    "wof:name":"Ust'-Ozernaya",
    "wof:placetype":"locality"
},
  "geometry": {"coordinates":[117.09059999999999,50.7026],"type":"Point"}
}