{
  "type": "Feature",
  "properties": {
    "gn:admin1_code":"69",
    "gn:asciiname":"Slezino",
    "gn:country_code":"RU",
    "gn:dem":196,
    "gn:feature_class":"P",
    "gn:feature_code":"PPL",
    "gn:name":"Slezino",
    "gn:population":0,
    "gn:timezone":"Europe/Moscow",
    "iso:country":"RU",
    "name:rus_x_preferred":[
        "\u0421\u043b\u0435\u0437\u0438\u043d\u043e"
    ],
    "name:und_x_variant":[
        "\u0421\u043b\u0435\u0437\u0438\u043d\u043e",
        "Slizino"
    ],
    "wof:name":"Slezino",
    "wof:placetype":"locality"
},
  "geometry": {"coordinates":[32.91111,55.39222],"type":"Point"}
}