{
  "type": "Feature",
  "properties": {
    "gn:admin1_code":"6",
    "gn:asciiname":"Kushkopala",
    "gn:country_code":"RU",
    "gn:dem":25,
    "gn:feature_class":"P",
    "gn:feature_code":"PPL",
    "gn:name":"Kushkopala",
    "gn:population":0,
    "gn:timezone":"Europe/Moscow",
    "iso:country":"RU",
    "name:che_x_preferred":[
        "\u041a\u0443\u0448\u043a\u043e\u043f\u0430\u043b\u0430"
    ],
    "name:eng_x_preferred":[
        "Kushkopala"
    ],
    "name:nor_x_preferred":[
        "Kusjkopola"
    ],
    "name:rus_x_preferred":[
        "\u041a\u0443\u0448\u043a\u043e\u043f\u043e\u043b\u0430"
    ],
    "name:rus_x_variant":[
        "\u041a\u0443\u0448\u043a\u043e\u043f\u0430\u043b\u0430"
    ],
    "name:und_x_variant":[
        "Yedoma",
        "Kushkopola"
    ],
    "wof:name":"Kushkopala",
    "wof:placetype":"locality"
},
  "geometry": {"coordinates":[44.7459,63.8344],"type":"Point"}
}