{
  "type": "Feature",
  "properties": {
    "gn:admin1_code":"11",
    "gn:asciiname":"Khilgana",
    "gn:country_code":"RU",
    "gn:dem":476,
    "gn:feature_class":"P",
    "gn:feature_code":"PPL",
    "gn:name":"Khilgana",
    "gn:population":0,
    "gn:timezone":"Asia/Irkutsk",
    "iso:country":"RU",
    "name:eng_x_preferred":[
        "Khilgana"
    ],
    "name:nor_x_preferred":[
        "Khilgana"
    ],
    "name:rus_x_preferred":[
        "\u0425\u0438\u043b\u0433\u0430\u043d\u0430"
    ],
    "wof:name":"Khilgana",
    "wof:placetype":"locality"
},
  "geometry": {"coordinates":[110.09999999999999,53.88333000000001],"type":"Point"}
}