{
  "type": "Feature",
  "properties": {
    "gn:admin1_code":"88",
    "gn:asciiname":"Purlevo",
    "gn:country_code":"RU",
    "gn:dem":95,
    "gn:feature_class":"P",
    "gn:feature_code":"PPL",
    "gn:name":"Purlevo",
    "gn:population":0,
    "gn:timezone":"Europe/Moscow",
    "iso:country":"RU",
    "name:rus_x_preferred":[
        "\u041f\u0443\u0440\u043b\u0435\u0432\u043e"
    ],
    "wof:name":"Purlevo",
    "wof:placetype":"locality"
},
  "geometry": {"coordinates":[39.74105,57.28943],"type":"Point"}
}