{
  "type": "Feature",
  "properties": {
    "gn:admin1_code":"47",
    "gn:asciiname":"Leonovo",
    "gn:country_code":"RU",
    "gn:dem":223,
    "gn:feature_class":"P",
    "gn:feature_code":"PPL",
    "gn:name":"Leonovo",
    "gn:population":0,
    "gn:timezone":"Europe/Moscow",
    "iso:country":"RU",
    "name:rus_x_preferred":[
        "\u041b\u0435\u043e\u043d\u043e\u0432\u043e"
    ],
    "wof:name":"Leonovo",
    "wof:placetype":"locality"
},
  "geometry": {"coordinates":[38.28333,56.38333000000001],"type":"Point"}
}