{
  "type": "Feature",
  "properties": {
    "gn:admin1_code":"51",
    "gn:asciiname":"Maloye Kazarinovo",
    "gn:country_code":"RU",
    "gn:dem":144,
    "gn:feature_class":"P",
    "gn:feature_code":"PPL",
    "gn:name":"Maloye Kazarinovo",
    "gn:population":0,
    "gn:timezone":"Europe/Moscow",
    "iso:country":"RU",
    "name:rus_x_preferred":[
        "\u041c\u0430\u043b\u043e\u0435 \u041a\u0430\u0437\u0430\u0440\u0438\u043d\u043e\u0432\u043e"
    ],
    "name:und_x_variant":[
        "\u041c\u0430\u043b\u043e\u0435 \u041a\u0430\u0437\u0430\u0440\u0438\u043d\u043e\u0432\u043e"
    ],
    "wof:name":"Maloye Kazarinovo",
    "wof:placetype":"locality"
},
  "geometry": {"coordinates":[45.22581,55.03705],"type":"Point"}
}