{
  "type": "Feature",
  "properties": {
    "gn:admin1_code":"62",
    "gn:asciiname":"Vostochnyy",
    "gn:country_code":"RU",
    "gn:dem":150,
    "gn:feature_class":"P",
    "gn:feature_code":"PPL",
    "gn:name":"Vostochnyy",
    "gn:population":0,
    "gn:timezone":"Europe/Moscow",
    "iso:country":"RU",
    "name:rus_x_preferred":[
        "\u0412\u043e\u0441\u0442\u043e\u0447\u043d\u044b\u0439"
    ],
    "wof:name":"Vostochnyy",
    "wof:placetype":"locality"
},
  "geometry": {"coordinates":[39.3615,53.995],"type":"Point"}
}