{
  "type": "Feature",
  "properties": {
    "gn:admin1_code":"51",
    "gn:asciiname":"Okhlopkovo",
    "gn:country_code":"RU",
    "gn:dem":75,
    "gn:feature_class":"P",
    "gn:feature_code":"PPL",
    "gn:name":"Okhlopkovo",
    "gn:population":0,
    "gn:timezone":"Europe/Moscow",
    "iso:country":"RU",
    "name:nor_x_preferred":[
        "Okhlopkovo"
    ],
    "name:rus_x_preferred":[
        "\u041e\u0445\u043b\u043e\u043f\u043a\u043e\u0432\u043e"
    ],
    "wof:name":"Okhlopkovo",
    "wof:placetype":"locality"
},
  "geometry": {"coordinates":[43.08251,56.1851],"type":"Point"}
}