{
  "type": "Feature",
  "properties": {
    "gn:admin1_code":"46.0",
    "gn:asciiname":"Bugry",
    "gn:country_code":"RU",
    "gn:dem":144,
    "gn:feature_class":"P",
    "gn:feature_code":"PPL",
    "gn:name":"Bugry",
    "gn:population":0,
    "gn:timezone":"Europe/Moscow",
    "iso:country":"RU",
    "name:rus_x_preferred":[
        "\u0411\u0443\u0433\u0440\u044b"
    ],
    "wof:name":"Bugry",
    "wof:placetype":"locality"
},
  "geometry": {"coordinates":[45.04293,54.56312],"type":"Point"}
}