{
  "type": "Feature",
  "properties": {
    "gn:admin1_code":"64",
    "gn:asciiname":"Rybalka Brodyazhka",
    "gn:cc2":"RU",
    "gn:country_code":"RU",
    "gn:dem":4,
    "gn:feature_class":"P",
    "gn:feature_code":"PPL",
    "gn:name":"Rybalka Brodyazhka",
    "gn:population":0,
    "gn:timezone":"Asia/Sakhalin",
    "iso:country":"RU",
    "name:rus_x_preferred":[
        "\u0420\u044b\u0431\u0430\u043b\u043a\u0430 \u0411\u0440\u043e\u0434\u044f\u0436\u043a\u0430"
    ],
    "name:und_x_variant":[
        "Brodyazhka",
        "Rybalka Brodyazhka",
        "\u0420\u044b\u0431\u0430\u043b\u043a\u0430 \u0411\u0440\u043e\u0434\u044f\u0436\u043a\u0430"
    ],
    "wof:name":"Rybalka Brodyazhka",
    "wof:placetype":"locality"
},
  "geometry": {"coordinates":[142.06666999999999,50.68333],"type":"Point"}
}