{
  "type": "Feature",
  "properties": {
    "gn:admin1_code":"63",
    "gn:asciiname":"Orgolokh",
    "gn:country_code":"RU",
    "gn:dem":219,
    "gn:feature_class":"P",
    "gn:feature_code":"PPL",
    "gn:name":"Orgolokh",
    "gn:population":0,
    "gn:timezone":"Asia/Yakutsk",
    "iso:country":"RU",
    "name:rus_x_preferred":[
        "\u041e\u0440\u0433\u043e\u043b\u043e\u0445"
    ],
    "name:und_x_variant":[
        "\u041e\u0440\u0433\u043e\u043b\u043e\u0445"
    ],
    "wof:name":"Orgolokh",
    "wof:placetype":"locality"
},
  "geometry": {"coordinates":[128.61667,62.46666999999999],"type":"Point"}
}