{
  "type": "Feature",
  "properties": {
    "gn:admin1_code":"86.0",
    "gn:asciiname":"Nikanorovka",
    "gn:country_code":"RU",
    "gn:dem":101,
    "gn:feature_class":"P",
    "gn:feature_code":"PPL",
    "gn:name":"Nikanorovka",
    "gn:population":0,
    "gn:timezone":"Europe/Moscow",
    "iso:country":"RU",
    "name:rus_x_preferred":[
        "\u041d\u0438\u043a\u0430\u043d\u043e\u0440\u043e\u0432\u043a\u0430"
    ],
    "wof:name":"Nikanorovka",
    "wof:placetype":"locality"
},
  "geometry": {"coordinates":[39.79606,50.22168],"type":"Point"}
}