{
  "type": "Feature",
  "properties": {
    "gn:admin1_code":"51",
    "gn:asciiname":"Plashchener",
    "gn:country_code":"RU",
    "gn:dem":131,
    "gn:feature_class":"P",
    "gn:feature_code":"PPL",
    "gn:name":"Plashchener",
    "gn:population":0,
    "gn:timezone":"Europe/Moscow",
    "iso:country":"RU",
    "name:rus_x_preferred":[
        "\u041f\u043b\u0430\u0449\u0435\u043d\u0435\u0440"
    ],
    "wof:name":"Plashchener",
    "wof:placetype":"locality"
},
  "geometry": {"coordinates":[47.2311,57.7082],"type":"Point"}
}