{
  "type": "Feature",
  "properties": {
    "gn:admin1_code":"47",
    "gn:asciiname":"Maloye Il'inskoye",
    "gn:country_code":"RU",
    "gn:dem":186,
    "gn:feature_class":"P",
    "gn:feature_code":"PPL",
    "gn:name":"Maloye Il\u2019inskoye",
    "gn:population":0,
    "gn:timezone":"Europe/Moscow",
    "iso:country":"RU",
    "name:rus_x_preferred":[
        "\u041c\u0430\u043b\u043e\u0435 \u0418\u043b\u044c\u0438\u043d\u0441\u043a\u043e\u0435"
    ],
    "name:und_x_variant":[
        "Il\u2019inskaya",
        "Il\u2019inskoye",
        "Malo-Il\u2019inskoye",
        "Maloye Il\u2019inskoye"
    ],
    "wof:name":"Maloye Il'inskoye",
    "wof:placetype":"locality"
},
  "geometry": {"coordinates":[38.38888,54.66358],"type":"Point"}
}