{
  "type": "Feature",
  "properties": {
    "gn:admin1_code":"71",
    "gn:asciiname":"Molochnaya",
    "gn:country_code":"RU",
    "gn:dem":229,
    "gn:feature_class":"P",
    "gn:feature_code":"PPL",
    "gn:name":"Molochnaya",
    "gn:population":0,
    "gn:timezone":"Asia/Yekaterinburg",
    "iso:country":"RU",
    "name:rus_x_preferred":[
        "\u041c\u043e\u043b\u043e\u0447\u043d\u0430\u044f"
    ],
    "wof:name":"Molochnaya",
    "wof:placetype":"locality"
},
  "geometry": {"coordinates":[59.666,58.3088],"type":"Point"}
}