{
  "type": "Feature",
  "properties": {
    "gn:admin1_code":"25.0",
    "gn:asciiname":"Borniki",
    "gn:country_code":"RU",
    "gn:dem":207,
    "gn:feature_class":"P",
    "gn:feature_code":"PPL",
    "gn:name":"Borniki",
    "gn:population":0,
    "gn:timezone":"Europe/Moscow",
    "iso:country":"RU",
    "name:rus_x_preferred":[
        "\u0411\u043e\u0440\u043d\u0438\u043a\u0438"
    ],
    "wof:name":"Borniki",
    "wof:placetype":"locality"
},
  "geometry": {"coordinates":[35.18306,54.40917],"type":"Point"}
}