{
  "type": "Feature",
  "properties": {
    "gn:admin1_code":"76",
    "gn:asciiname":"Imeni Mossoveta",
    "gn:country_code":"RU",
    "gn:dem":215,
    "gn:feature_class":"P",
    "gn:feature_code":"PPL",
    "gn:name":"Imeni Mossoveta",
    "gn:population":0,
    "gn:timezone":"Europe/Moscow",
    "iso:country":"RU",
    "name:rus_x_preferred":[
        "\u0418\u043c\u0435\u043d\u0438 \u041c\u043e\u0441\u0441\u043e\u0432\u0435\u0442\u0430"
    ],
    "wof:name":"Imeni Mossoveta",
    "wof:placetype":"locality"
},
  "geometry": {"coordinates":[36.64278,53.78833],"type":"Point"}
}