{
  "type": "Feature",
  "properties": {
    "gn:admin1_code":"30",
    "gn:asciiname":"Chigul'bakh",
    "gn:country_code":"RU",
    "gn:dem":586,
    "gn:feature_class":"P",
    "gn:feature_code":"PPL",
    "gn:name":"Chigul\u2019bakh",
    "gn:population":0,
    "gn:timezone":"Asia/Vladivostok",
    "iso:country":"RU",
    "name:rus_x_preferred":[
        "\u0427\u0438\u0433\u0443\u043b\u044c\u0431\u0430\u0445"
    ],
    "name:und_x_variant":[
        "Uy",
        "Chibul\u2019byak",
        "Chabul\u2019byak",
        "Chigul\u2019bakh"
    ],
    "wof:name":"Chigul'bakh",
    "wof:placetype":"locality"
},
  "geometry": {"coordinates":[138.15000000000001,57.61666999999999],"type":"Point"}
}