{
  "type": "Feature",
  "properties": {
    "gn:admin1_code":"52",
    "gn:asciiname":"Velily",
    "gn:country_code":"RU",
    "gn:dem":118,
    "gn:feature_class":"P",
    "gn:feature_code":"PPL",
    "gn:name":"Velily",
    "gn:population":0,
    "gn:timezone":"Europe/Moscow",
    "iso:country":"RU",
    "name:eng_x_preferred":[
        "Velily"
    ],
    "name:nor_x_preferred":[
        "Velily"
    ],
    "name:rus_x_preferred":[
        "\u0412\u0435\u043b\u0438\u043b\u044b"
    ],
    "name:und_x_variant":[
        "Vilily",
        "Velily",
        "\u0412\u0435\u043b\u0438\u043b\u044b"
    ],
    "wof:name":"Velily",
    "wof:placetype":"locality"
},
  "geometry": {"coordinates":[31.90158,57.2127],"type":"Point"}
}