{
  "type": "Feature",
  "properties": {
    "gn:admin1_code":"86",
    "gn:asciiname":"Sevryukovka",
    "gn:country_code":"RU",
    "gn:dem":107,
    "gn:feature_class":"P",
    "gn:feature_code":"PPL",
    "gn:name":"Sevryukovka",
    "gn:population":0,
    "gn:timezone":"Europe/Moscow",
    "iso:country":"RU",
    "name:rus_x_preferred":[
        "\u0421\u0435\u0432\u0440\u044e\u043a\u043e\u0432\u043a\u0430"
    ],
    "name:und_x_variant":[
        "Gudovka",
        "Sevryukovka"
    ],
    "wof:name":"Sevryukovka",
    "wof:placetype":"locality"
},
  "geometry": {"coordinates":[39.13881,51.95576],"type":"Point"}
}