{
  "type": "Feature",
  "properties": {
    "gn:admin1_code":"21.0",
    "gn:asciiname":"Khotenovo",
    "gn:country_code":"RU",
    "gn:dem":120,
    "gn:feature_class":"P",
    "gn:feature_code":"PPL",
    "gn:name":"Khotenovo",
    "gn:population":0,
    "gn:timezone":"Europe/Moscow",
    "iso:country":"RU",
    "name:rus_x_preferred":[
        "\u0425\u043e\u0442\u0435\u043d\u043e\u0432\u043e"
    ],
    "wof:name":"Khotenovo",
    "wof:placetype":"locality"
},
  "geometry": {"coordinates":[41.92092,57.48361],"type":"Point"}
}