{
  "type": "Feature",
  "properties": {
    "gn:admin1_code":"41",
    "gn:asciiname":"Otreshkovo",
    "gn:country_code":"RU",
    "gn:dem":196,
    "gn:feature_class":"P",
    "gn:feature_code":"PPL",
    "gn:name":"Otreshkovo",
    "gn:population":0,
    "gn:timezone":"Europe/Moscow",
    "iso:country":"RU",
    "name:rus_x_preferred":[
        "\u041e\u0442\u0440\u0435\u0448\u043a\u043e\u0432\u043e"
    ],
    "name:und_x_variant":[
        "Bezobrazovka",
        "Gorodishche-Bezobrazovo",
        "Gorodishche",
        "Otreshkovo",
        "\u041e\u0442\u0440\u0435\u0448\u043a\u043e\u0432\u043e"
    ],
    "wof:name":"Otreshkovo",
    "wof:placetype":"locality"
},
  "geometry": {"coordinates":[36.53193,51.75045],"type":"Point"}
}