{
  "type": "Feature",
  "properties": {
    "gn:admin1_code":"63",
    "gn:asciiname":"Tyunnyuk-Anna",
    "gn:country_code":"RU",
    "gn:dem":209,
    "gn:feature_class":"P",
    "gn:feature_code":"PPL",
    "gn:name":"Tyunnyuk-Anna",
    "gn:population":0,
    "gn:timezone":"Asia/Yakutsk",
    "iso:country":"RU",
    "wof:name":"Tyunnyuk-Anna",
    "wof:placetype":"locality"
},
  "geometry": {"coordinates":[129.47855000000001,62.49573],"type":"Point"}
}