{
  "type": "Feature",
  "properties": {
    "gn:admin1_code":"60",
    "gn:asciiname":"Veret'ye Tret'ye",
    "gn:country_code":"RU",
    "gn:dem":97,
    "gn:feature_class":"P",
    "gn:feature_code":"PPL",
    "gn:name":"Veret\u2019y\u00eb Tret\u2019ye",
    "gn:population":0,
    "gn:timezone":"Europe/Moscow",
    "iso:country":"RU",
    "name:rus_x_preferred":[
        "\u0412\u0435\u0440\u0435\u0442\u044c\u0451 \u0422\u0440\u0435\u0442\u044c\u0435"
    ],
    "name:und_x_variant":[
        "Veret\u2019y\u00eb Tret\u2019ye"
    ],
    "wof:name":"Veret'ye Tret'ye",
    "wof:placetype":"locality"
},
  "geometry": {"coordinates":[30.49057,56.44483],"type":"Point"}
}