{
  "type": "Feature",
  "properties": {
    "gn:admin1_code":"21.0",
    "gn:asciiname":"Stoyanikha",
    "gn:country_code":"RU",
    "gn:dem":114,
    "gn:feature_class":"P",
    "gn:feature_code":"PPL",
    "gn:name":"Stoyanikha",
    "gn:population":0,
    "gn:timezone":"Europe/Moscow",
    "iso:country":"RU",
    "name:rus_x_preferred":[
        "\u0421\u0442\u043e\u044f\u043d\u0438\u0445\u0430"
    ],
    "name:und_x_variant":[
        "\u0421\u0442\u043e\u044f\u043d\u0438\u0445\u0430"
    ],
    "wof:name":"Stoyanikha",
    "wof:placetype":"locality"
},
  "geometry": {"coordinates":[42.54091,57.16206999999999],"type":"Point"}
}