{
  "type": "Feature",
  "properties": {
    "gn:admin1_code":"73",
    "gn:asciiname":"Kuzkeyevo",
    "gn:country_code":"RU",
    "gn:dem":107,
    "gn:feature_class":"P",
    "gn:feature_code":"PPL",
    "gn:name":"Kuzkeyevo",
    "gn:population":0,
    "gn:timezone":"Europe/Moscow",
    "iso:country":"RU",
    "name:eng_x_preferred":[
        "Kuzkeyevo"
    ],
    "name:nor_x_preferred":[
        "Kuzkejevo"
    ],
    "name:rus_x_preferred":[
        "\u041a\u0443\u0437\u043a\u0435\u0435\u0432\u043e"
    ],
    "name:und_x_variant":[
        "\u041a\u0443\u0437\u043a\u0435\u0435\u0432\u043e",
        "Kuzkeyevo"
    ],
    "wof:name":"Kuzkeyevo",
    "wof:placetype":"locality"
},
  "geometry": {"coordinates":[52.80435,55.77426],"type":"Point"}
}