{
  "type": "Feature",
  "properties": {
    "gn:admin1_code":"65",
    "gn:asciiname":"Gundorovka",
    "gn:country_code":"RU",
    "gn:dem":38,
    "gn:feature_class":"P",
    "gn:feature_code":"PPL",
    "gn:name":"Gundorovka",
    "gn:population":0,
    "gn:timezone":"Europe/Samara",
    "iso:country":"RU",
    "name:rus_x_preferred":[
        "\u0413\u0443\u043d\u0434\u043e\u0440\u043e\u0432\u043a\u0430"
    ],
    "name:und_x_variant":[
        "Gundarovka",
        "Gundorovka"
    ],
    "wof:name":"Gundorovka",
    "wof:placetype":"locality"
},
  "geometry": {"coordinates":[50.67629,53.71781],"type":"Point"}
}