{
  "type": "Feature",
  "properties": {
    "gn:admin1_code":"8",
    "gn:asciiname":"Khrustalevo",
    "gn:country_code":"RU",
    "gn:dem":285,
    "gn:feature_class":"P",
    "gn:feature_code":"PPL",
    "gn:name":"Khrustal\u00ebvo",
    "gn:population":0,
    "gn:timezone":"Asia/Yekaterinburg",
    "iso:country":"RU",
    "name:rus_x_preferred":[
        "\u0425\u0440\u0443\u0441\u0442\u0430\u043b\u00eb\u0432\u043e"
    ],
    "name:und_x_variant":[
        "Khrustal\u00ebvo"
    ],
    "wof:name":"Khrustalevo",
    "wof:placetype":"locality"
},
  "geometry": {"coordinates":[54.6511,54.0268],"type":"Point"}
}