{
  "type": "Feature",
  "properties": {
    "gn:admin1_code":"8",
    "gn:asciiname":"Khrustalevo",
    "gn:country_code":"RU",
    "gn:dem":285,
    "gn:feature_class":"P",
    "gn:feature_code":"PPL",
    "gn:name":"Khrustal\u00ebvo",
    "gn:population":0,
    "gn:timezone":"Asia/Yekaterinburg",
    "iso:country":"RU",
    "name:bak_x_preferred":[
        "\u0425\u0440\u0443\u0441\u0442\u0430\u043b\u0438"
    ],
    "name:che_x_preferred":[
        "\u0425\u0440\u0443\u0441\u0442\u0430\u043b\u0435\u0432\u043e"
    ],
    "name:hye_x_preferred":[
        "\u053d\u0580\u0578\u0582\u057d\u057f\u0561\u056c\u0587\u0578"
    ],
    "name:kat_x_preferred":[
        "\u10ee\u10e0\u10e3\u10e1\u10e2\u10d0\u10da\u10d4\u10d5\u10dd"
    ],
    "name:kaz_x_preferred":[
        "\u0425\u0440\u0443\u0441\u0442\u0430\u043b"
    ],
    "name:kir_x_preferred":[
        "\u0425\u0440\u0443\u0441\u0442\u0430\u043b"
    ],
    "name:rus_x_preferred":[
        "\u0425\u0440\u0443\u0441\u0442\u0430\u043b\u00eb\u0432\u043e"
    ],
    "name:rus_x_variant":[
        "\u0425\u0440\u0443\u0441\u0442\u0430\u043b\u0435\u0432\u043e"
    ],
    "name:tat_x_preferred":[
        "\u0425\u0440\u0443\u0441\u0442\u0430\u043b\u0438"
    ],
    "name:ukr_x_preferred":[
        "\u0425\u0440\u0443\u0441\u0442\u0430\u043b\u044c\u043e\u0432\u043e"
    ],
    "name:und_x_variant":[
        "Khrustal\u00ebvo"
    ],
    "wof:name":"Khrustalevo",
    "wof:placetype":"locality"
},
  "geometry": {"coordinates":[54.6511,54.0268],"type":"Point"}
}