{
  "type": "Feature",
  "properties": {
    "gn:admin1_code":"75",
    "gn:asciiname":"Mysovaya",
    "gn:country_code":"RU",
    "gn:dem":63,
    "gn:feature_class":"P",
    "gn:feature_code":"PPL",
    "gn:name":"Mysovaya",
    "gn:population":0,
    "gn:timezone":"Asia/Tomsk",
    "iso:country":"RU",
    "name:rus_x_preferred":[
        "\u041c\u044b\u0441\u043e\u0432\u0430\u044f"
    ],
    "wof:name":"Mysovaya",
    "wof:placetype":"locality"
},
  "geometry": {"coordinates":[82.13333,58.45],"type":"Point"}
}