{
  "type": "Feature",
  "properties": {
    "gn:country":"RU",
    "gn:fcode":"PPL",
    "gn:pop":4843,
    "iso:country":"RU",
    "name:eng_x_preferred":[
        "Amzya"
    ],
    "name:rus_x_preferred":[
        "\u0410\u043c\u0437\u044f"
    ],
    "qs:name":"Amzya",
    "qs:photos_9r":0,
    "qs:photos_sr":0,
    "qs:pop_sr":"4",
    "wof:name":"Amzya",
    "wof:placetype":"locality",
    "wof:population":4843
},
  "geometry": {"coordinates":[54.385,56.2346],"type":"Point"}
}