{
  "type": "Feature",
  "properties": {
    "gn:country":"RU",
    "gn:fcode":"PPL",
    "gn:population":4843,
    "iso:country":"RU",
    "name:ara_x_preferred":[
        "\u0623\u0645\u0632\u064a\u0627"
    ],
    "name:aze_x_preferred":[
        "\u018fmz\u0259"
    ],
    "name:bak_x_preferred":[
        "\u04d8\u043c\u0437\u04d9"
    ],
    "name:che_x_preferred":[
        "\u0410\u043c\u0437\u044f"
    ],
    "name:chv_x_preferred":[
        "\u042d\u043c\u00e7\u0435"
    ],
    "name:eng_x_preferred":[
        "Amzya"
    ],
    "name:hye_x_preferred":[
        "\u0531\u0574\u0566\u0575\u0561"
    ],
    "name:kat_x_preferred":[
        "\u10d0\u10db\u10d6\u10d8\u10d0"
    ],
    "name:kaz_x_preferred":[
        "\u0410\u043c\u0437\u044f"
    ],
    "name:kir_x_preferred":[
        "\u0410\u043c\u0437\u044f"
    ],
    "name:rus_x_preferred":[
        "\u0410\u043c\u0437\u044f"
    ],
    "name:tat_x_preferred":[
        "\u04d8\u043c\u0437\u04d9"
    ],
    "name:ukr_x_preferred":[
        "\u0410\u043c\u0437\u044f"
    ],
    "qs:name":"Amzya",
    "qs:photos_9r":0,
    "qs:photos_sr":0,
    "qs:pop_sr":"4",
    "wof:name":"Amzya",
    "wof:placetype":"locality",
    "wof:population":4843
},
  "geometry": {"coordinates":[54.385,56.2346],"type":"Point"}
}