{
  "type": "Feature",
  "properties": {
    "gn:admin1_code":"78",
    "gn:asciiname":"Solodilova",
    "gn:country_code":"RU",
    "gn:dem":98,
    "gn:feature_class":"P",
    "gn:feature_code":"PPL",
    "gn:name":"Solodilova",
    "gn:population":0,
    "gn:timezone":"Asia/Yekaterinburg",
    "iso:country":"RU",
    "name:eng_x_preferred":[
        "Solodilova"
    ],
    "name:nor_x_preferred":[
        "Solodilova"
    ],
    "name:rus_x_preferred":[
        "\u0421\u043e\u043b\u043e\u0434\u0438\u043b\u043e\u0432\u0430"
    ],
    "wof:name":"Solodilova",
    "wof:placetype":"locality"
},
  "geometry": {"coordinates":[68.22731,56.69017],"type":"Point"}
}