{
  "type": "Feature",
  "properties": {
    "gn:admin1_code":"78",
    "gn:asciiname":"Novosely",
    "gn:country_code":"RU",
    "gn:dem":134,
    "gn:feature_class":"P",
    "gn:feature_code":"PPL",
    "gn:name":"Novos\u00ebly",
    "gn:population":0,
    "gn:timezone":"Asia/Yekaterinburg",
    "iso:country":"RU",
    "name:rus_x_preferred":[
        "\u041d\u043e\u0432\u043e\u0441\u0451\u043b\u044b"
    ],
    "name:und_x_variant":[
        "Novos\u00ebly",
        "\u041d\u043e\u0432\u043e\u0441\u0451\u043b\u044b"
    ],
    "wof:name":"Novosely",
    "wof:placetype":"locality"
},
  "geometry": {"coordinates":[69.66280999999999,55.69626],"type":"Point"}
}