{
  "type": "Feature",
  "properties": {
    "gn:country":"RU",
    "gn:fcode":"PPL",
    "gn:pop":0,
    "iso:country":"RU",
    "name:eng_x_preferred":[
        "Khokhlovo"
    ],
    "name:nor_x_preferred":[
        "Khokhlovo"
    ],
    "name:rus_x_preferred":[
        "\u0425\u043e\u0445\u043b\u043e\u0432\u043e"
    ],
    "name:unk_x_variant":[
        "Khokhlova"
    ],
    "qs:name":"Khokhlovo",
    "qs:name_adm0":"Russia",
    "qs:name_adm1":"Tyumen Oblast",
    "qs:photos_9r":0,
    "qs:photos_sr":0,
    "qs:placetype":"Town",
    "qs:pop_sr":"0",
    "wd:wordcount":330,
    "wof:name":"Khokhlovo",
    "wof:placetype":"locality",
    "wof:population":0
},
  "geometry": {"coordinates":[66.38023,56.71528],"type":"Point"}
}