{
  "type": "Feature",
  "properties": {
    "gn:admin1_code":"42",
    "gn:admin2_code":"11103388",
    "gn:asciiname":"Novyy Pogorelets",
    "gn:country_code":"RU",
    "gn:dem":40,
    "gn:feature_class":"P",
    "gn:feature_code":"PPL",
    "gn:name":"Novyy Pogorelets",
    "gn:population":0,
    "gn:timezone":"Europe/Moscow",
    "iso:country":"RU",
    "name:rus_x_preferred":[
        "\u041d\u043e\u0432\u044b\u0439 \u041f\u043e\u0433\u043e\u0440\u0435\u043b\u0435\u0446"
    ],
    "name:und_x_variant":[
        "\u041d\u043e\u0432\u044b\u0439 \u041f\u043e\u0433\u043e\u0440\u0435\u043b\u0435\u0446"
    ],
    "wof:name":"Novyy Pogorelets",
    "wof:placetype":"locality"
},
  "geometry": {"coordinates":[33.39765999999999,59.65175],"type":"Point"}
}