{
  "type": "Feature",
  "properties": {
    "gn:admin1_code":"85",
    "gn:asciiname":"Izboishchi",
    "gn:country_code":"RU",
    "gn:dem":141,
    "gn:feature_class":"P",
    "gn:feature_code":"PPL",
    "gn:name":"Izboishchi",
    "gn:population":0,
    "gn:timezone":"Europe/Moscow",
    "iso:country":"RU",
    "name:eng_x_preferred":[
        "Izboishchi"
    ],
    "name:nor_x_preferred":[
        "Izboisjtsji"
    ],
    "name:rus_x_preferred":[
        "\u0418\u0437\u0431\u043e\u0438\u0449\u0438"
    ],
    "name:und_x_variant":[
        "Izboishche",
        "\u0418\u0437\u0431\u043e\u0438\u0449\u0438",
        "Izboishchi"
    ],
    "wof:name":"Izboishchi",
    "wof:placetype":"locality"
},
  "geometry": {"coordinates":[35.27567,58.98513000000001],"type":"Point"}
}