{
  "type": "Feature",
  "properties": {
    "gn:admin1_code":"54",
    "gn:asciiname":"Krasnousovo",
    "gn:country_code":"RU",
    "gn:dem":118,
    "gn:feature_class":"P",
    "gn:feature_code":"PPL",
    "gn:name":"Krasnousovo",
    "gn:population":0,
    "gn:timezone":"Asia/Omsk",
    "iso:country":"RU",
    "name:eng_x_preferred":[
        "Krasnousovo"
    ],
    "name:nor_x_preferred":[
        "Krasnousovo"
    ],
    "name:rus_x_preferred":[
        "\u041a\u0440\u0430\u0441\u043d\u043e\u0443\u0441\u043e\u0432\u043e"
    ],
    "wof:name":"Krasnousovo",
    "wof:placetype":"locality"
},
  "geometry": {"coordinates":[72.02663000000003,55.8633],"type":"Point"}
}