{
  "type": "Feature",
  "properties": {
    "gn:admin1_code":"8.0",
    "gn:asciiname":"Agirzya",
    "gn:country_code":"RU",
    "gn:dem":169,
    "gn:feature_class":"P",
    "gn:feature_code":"PPL",
    "gn:name":"Agirzya",
    "gn:population":0,
    "gn:timezone":"Asia/Yekaterinburg",
    "iso:country":"RU",
    "name:nor_x_preferred":[
        "Agirzia"
    ],
    "name:rus_x_preferred":[
        "\u0410\u0433\u0438\u0440\u0437\u044f"
    ],
    "wof:name":"Agirzya",
    "wof:placetype":"locality"
},
  "geometry": {"coordinates":[57.23732,55.58059],"type":"Point"}
}