{
  "type": "Feature",
  "properties": {
    "gn:admin1_code":"16",
    "gn:asciiname":"Khlesi",
    "gn:country_code":"RU",
    "gn:dem":117,
    "gn:feature_class":"P",
    "gn:feature_code":"PPL",
    "gn:name":"Khlesi",
    "gn:population":0,
    "gn:timezone":"Europe/Moscow",
    "iso:country":"RU",
    "name:rus_x_preferred":[
        "\u0425\u043b\u0435\u0441\u0438"
    ],
    "name:und_x_variant":[
        "\u0425\u043b\u0435\u0441\u0438"
    ],
    "wof:name":"Khlesi",
    "wof:placetype":"locality"
},
  "geometry": {"coordinates":[47.19101,55.74544],"type":"Point"}
}