{
  "type": "Feature",
  "properties": {
    "gn:admin1_code":"51",
    "gn:asciiname":"Letnevo",
    "gn:country_code":"RU",
    "gn:dem":89,
    "gn:feature_class":"P",
    "gn:feature_code":"PPL",
    "gn:name":"Letn\u00ebvo",
    "gn:population":0,
    "gn:timezone":"Europe/Moscow",
    "iso:country":"RU",
    "name:rus_x_preferred":[
        "\u041b\u0435\u0442\u043d\u0451\u0432\u043e"
    ],
    "name:und_x_variant":[
        "Letneva",
        "Letn\u00ebvo",
        "\u041b\u0435\u0442\u043d\u0451\u0432\u043e"
    ],
    "wof:name":"Letnevo",
    "wof:placetype":"locality"
},
  "geometry": {"coordinates":[44.90749,56.00016],"type":"Point"}
}