{
  "type": "Feature",
  "properties": {
    "gn:admin1_code":"8",
    "gn:asciiname":"Kovardy",
    "gn:country_code":"RU",
    "gn:dem":167,
    "gn:feature_class":"P",
    "gn:feature_code":"PPL",
    "gn:name":"Kovardy",
    "gn:population":0,
    "gn:timezone":"Asia/Yekaterinburg",
    "iso:country":"RU",
    "name:bak_x_preferred":[
        "\u04a0\u0430\u0443\u0430\u0440\u0499\u044b"
    ],
    "name:che_x_preferred":[
        "\u041a\u043e\u0432\u0430\u0440\u0434\u044b"
    ],
    "name:eng_x_preferred":[
        "Kovardy"
    ],
    "name:hye_x_preferred":[
        "\u053f\u0578\u057e\u0561\u0580\u0564\u056b"
    ],
    "name:kaz_x_preferred":[
        "\u041a\u043e\u0432\u0430\u0440\u0434\u044b"
    ],
    "name:kir_x_preferred":[
        "\u0416\u0430\u04a3\u044b \u041a\u043e\u0432\u0430\u0440\u0434\u044b"
    ],
    "name:nor_x_preferred":[
        "Kovardy"
    ],
    "name:rus_x_preferred":[
        "\u041a\u043e\u0432\u0430\u0440\u0434\u044b"
    ],
    "name:tat_x_preferred":[
        "\u041a\u044b\u0432\u0430\u0440\u0434\u044b"
    ],
    "name:ukr_x_preferred":[
        "\u041a\u043e\u0432\u0430\u0440\u0434\u0438"
    ],
    "name:und_x_variant":[
        "Kavardy",
        "\u041a\u043e\u0432\u0430\u0440\u0434\u044b",
        "Kovardy"
    ],
    "wof:name":"Kovardy",
    "wof:placetype":"locality"
},
  "geometry": {"coordinates":[56.75716,54.21005],"type":"Point"}
}