{
  "type": "Feature",
  "properties": {
    "gn:admin1_code":"41.0",
    "gn:asciiname":"Cheremushki",
    "gn:country_code":"RU",
    "gn:dem":226,
    "gn:feature_class":"P",
    "gn:feature_code":"PPL",
    "gn:name":"Cheremushki",
    "gn:population":0,
    "gn:timezone":"Europe/Moscow",
    "iso:country":"RU",
    "name:rus_x_preferred":[
        "\u0427\u0435\u0440\u0435\u043c\u0443\u0448\u043a\u0438"
    ],
    "name:und_x_variant":[
        "\u0427\u0435\u0440\u0435\u043c\u0443\u0448\u043a\u0438"
    ],
    "wof:name":"Cheremushki",
    "wof:placetype":"locality"
},
  "geometry": {"coordinates":[36.25655,51.60322],"type":"Point"}
}