{
  "type": "Feature",
  "properties": {
    "gn:admin1_code":"42",
    "gn:asciiname":"Khyutti",
    "gn:cc2":"RU",
    "gn:country_code":"RU",
    "gn:dem":1,
    "gn:feature_class":"P",
    "gn:feature_code":"PPL",
    "gn:name":"Khyutti",
    "gn:population":0,
    "gn:timezone":"Europe/Moscow",
    "iso:country":"RU",
    "name:rus_x_preferred":[
        "\u0425\u044e\u0442\u0442\u0438"
    ],
    "name:und_x_variant":[
        "Giuttelia",
        "Gyuttelya",
        "Hytt\u00e4l\u00e4",
        "Hytti",
        "Khyutti"
    ],
    "wof:name":"Khyutti",
    "wof:placetype":"locality"
},
  "geometry": {"coordinates":[28.63964,60.31114],"type":"Point"}
}