{
  "type": "Feature",
  "properties": {
    "gn:admin1_code":"23",
    "gn:asciiname":"Marinovka",
    "gn:country_code":"RU",
    "gn:dem":35,
    "gn:feature_class":"P",
    "gn:feature_code":"PPL",
    "gn:name":"Marinovka",
    "gn:population":0,
    "gn:timezone":"Europe/Kaliningrad",
    "iso:country":"RU",
    "name:rus_x_preferred":[
        "\u041c\u0430\u0440\u0438\u043d\u043e\u0432\u043a\u0430"
    ],
    "name:und_x_variant":[
        "\u041c\u0430\u0440\u0438\u043d\u043e\u0432\u043a\u0430"
    ],
    "wof:name":"Marinovka",
    "wof:placetype":"locality"
},
  "geometry": {"coordinates":[21.37583,54.43333000000001],"type":"Point"}
}