{
  "type": "Feature",
  "properties": {
    "gn:admin1_code":"61",
    "gn:asciiname":"Obukhov Nomer 4",
    "gn:country_code":"RU",
    "gn:dem":186,
    "gn:feature_class":"P",
    "gn:feature_code":"PPL",
    "gn:name":"Obukhov Nomer 4",
    "gn:population":0,
    "gn:timezone":"Europe/Moscow",
    "iso:country":"RU",
    "name:rus_x_preferred":[
        "\u041e\u0431\u0443\u0445\u043e\u0432 \u041d\u043e\u043c\u0435\u0440 \u0427\u0435\u0442\u044b\u0440\u0435"
    ],
    "name:rus_x_variant":[
        "\u041e\u0431\u0443\u0445\u043e\u0432 \u041d\u043e\u043c\u0435\u0440 4"
    ],
    "name:und_x_variant":[
        "Obukhov Nomer Chetyre",
        "\u041e\u0431\u0443\u0445\u043e\u0432 \u041d\u043e\u043c\u0435\u0440 \u0427\u0435\u0442\u044b\u0440\u0435",
        "Obukhov Nomer 4"
    ],
    "wof:name":"Obukhov Nomer 4",
    "wof:placetype":"locality"
},
  "geometry": {"coordinates":[40.34079000000001,48.06983],"type":"Point"}
}