{
  "type": "Feature",
  "properties": {
    "gn:admin1_code":"41.0",
    "gn:asciiname":"Glazovo",
    "gn:country_code":"RU",
    "gn:dem":170,
    "gn:feature_class":"P",
    "gn:feature_code":"PPL",
    "gn:name":"Glazovo",
    "gn:population":0,
    "gn:timezone":"Europe/Moscow",
    "iso:country":"RU",
    "name:rus_x_preferred":[
        "\u0413\u043b\u0430\u0437\u043e\u0432\u043e"
    ],
    "name:und_x_variant":[
        "\u0413\u043b\u0430\u0437\u043e\u0432\u043e"
    ],
    "wof:name":"Glazovo",
    "wof:placetype":"locality"
},
  "geometry": {"coordinates":[35.45806,51.90389],"type":"Point"}
}