{
  "type": "Feature",
  "properties": {
    "gn:admin1_code":"21.0",
    "gn:asciiname":"Okul'tsevo",
    "gn:country_code":"RU",
    "gn:dem":115,
    "gn:feature_class":"P",
    "gn:feature_code":"PPL",
    "gn:name":"Okul\u2019tsevo",
    "gn:population":0,
    "gn:timezone":"Europe/Moscow",
    "iso:country":"RU",
    "name:nor_x_preferred":[
        "Okultsevo"
    ],
    "name:rus_x_preferred":[
        "\u041e\u043a\u0443\u043b\u044c\u0446\u0435\u0432\u043e"
    ],
    "name:und_x_variant":[
        "Okul\u2019tsevo"
    ],
    "wof:name":"Okul'tsevo",
    "wof:placetype":"locality"
},
  "geometry": {"coordinates":[42.22525,56.84097],"type":"Point"}
}