{
  "type": "Feature",
  "properties": {
    "gn:admin1_code":"91",
    "gn:asciiname":"Shadrino",
    "gn:country_code":"RU",
    "gn:dem":619,
    "gn:feature_class":"P",
    "gn:feature_code":"PPL",
    "gn:name":"Shadrino",
    "gn:population":0,
    "gn:timezone":"Asia/Krasnoyarsk",
    "iso:country":"RU",
    "name:eng_x_preferred":[
        "Shadrino"
    ],
    "name:nor_x_preferred":[
        "Sjadrino"
    ],
    "name:rus_x_preferred":[
        "\u0428\u0430\u0434\u0440\u0438\u043d\u043e"
    ],
    "wof:name":"Shadrino",
    "wof:placetype":"locality"
},
  "geometry": {"coordinates":[91.95389,54.70056],"type":"Point"}
}