{
  "type": "Feature",
  "properties": {
    "gn:admin1_code":"70.0",
    "gn:asciiname":"Chavykin",
    "gn:cc2":"RU",
    "gn:country_code":"RU",
    "gn:dem":74,
    "gn:feature_class":"P",
    "gn:feature_code":"PPL",
    "gn:name":"Chavykin",
    "gn:population":0,
    "gn:timezone":"Europe/Moscow",
    "iso:country":"RU",
    "name:und_x_variant":[
        "Gor'kaya Balka"
    ],
    "wof:name":"Chavykin",
    "wof:placetype":"locality"
},
  "geometry": {"coordinates":[41.44306,45.77528],"type":"Point"}
}