{
  "type": "Feature",
  "properties": {
    "gn:admin1_code":"77",
    "gn:asciiname":"Bezhitsy",
    "gn:country_code":"RU",
    "gn:dem":139,
    "gn:feature_class":"P",
    "gn:feature_code":"PPL",
    "gn:name":"Bezhitsy",
    "gn:population":0,
    "gn:timezone":"Europe/Moscow",
    "iso:country":"RU",
    "name:rus_x_preferred":[
        "\u0411\u0435\u0436\u0438\u0446\u044b"
    ],
    "wof:name":"Bezhitsy",
    "wof:placetype":"locality"
},
  "geometry": {"coordinates":[36.5166,57.8174],"type":"Point"}
}