{
  "type": "Feature",
  "properties": {
    "gn:admin1_code":"10.0",
    "gn:asciiname":"Murav'i",
    "gn:country_code":"RU",
    "gn:dem":185,
    "gn:feature_class":"P",
    "gn:feature_code":"PPL",
    "gn:name":"Murav\u2019i",
    "gn:population":0,
    "gn:timezone":"Europe/Moscow",
    "iso:country":"RU",
    "name:rus_x_preferred":[
        "\u041c\u0443\u0440\u0430\u0432\u044c\u0438"
    ],
    "name:und_x_variant":[
        "Murav\u2019i"
    ],
    "wof:name":"Murav'i",
    "wof:placetype":"locality"
},
  "geometry": {"coordinates":[33.40378,53.13656999999999],"type":"Point"}
}