{
  "type": "Feature",
  "properties": {
    "gn:admin1_code":"45",
    "gn:asciiname":"Malaya Vacherma",
    "gn:country_code":"RU",
    "gn:dem":152,
    "gn:feature_class":"P",
    "gn:feature_code":"PPL",
    "gn:name":"Malaya Vacherma",
    "gn:population":0,
    "gn:timezone":"Europe/Moscow",
    "iso:country":"RU",
    "name:rus_x_preferred":[
        "\u041c\u0430\u043b\u0430\u044f \u0412\u0430\u0447\u0435\u0440\u043c\u0430"
    ],
    "name:und_x_variant":[
        "\u041c\u0430\u043b\u0430\u044f \u0412\u0430\u0447\u0435\u0440\u043c\u0430"
    ],
    "wof:name":"Malaya Vacherma",
    "wof:placetype":"locality"
},
  "geometry": {"coordinates":[49.61667,56.95],"type":"Point"}
}