{
  "type": "Feature",
  "properties": {
    "gn:admin1_code":"17",
    "gn:asciiname":"Maloa-Bredikhinskiy",
    "gn:country_code":"RU",
    "gn:dem":-11,
    "gn:feature_class":"P",
    "gn:feature_code":"PPL",
    "gn:name":"Maloa-Bredikhinskiy",
    "gn:population":0,
    "gn:timezone":"Europe/Moscow",
    "iso:country":"RU",
    "name:rus_x_preferred":[
        "\u041c\u0430\u043b\u043e\u0430-\u0411\u0440\u0435\u0434\u0438\u0445\u0438\u043d\u0441\u043a\u0438\u0439"
    ],
    "name:und_x_variant":[
        "\u041c\u0430\u043b\u043e\u0430-\u0411\u0440\u0435\u0434\u0438\u0445\u0438\u043d\u0441\u043a\u0438\u0439"
    ],
    "wof:name":"Maloa-Bredikhinskiy",
    "wof:placetype":"locality"
},
  "geometry": {"coordinates":[46.78333,43.95],"type":"Point"}
}