{
  "type": "Feature",
  "properties": {
    "gn:admin1_code":"70",
    "gn:asciiname":"Medvedev",
    "gn:country_code":"RU",
    "gn:dem":136,
    "gn:feature_class":"P",
    "gn:feature_code":"PPL",
    "gn:name":"Medvedev",
    "gn:population":0,
    "gn:timezone":"Europe/Moscow",
    "iso:country":"RU",
    "name:rus_x_preferred":[
        "\u041c\u0435\u0434\u0432\u0435\u0434\u0435\u0432"
    ],
    "wof:name":"Medvedev",
    "wof:placetype":"locality"
},
  "geometry": {"coordinates":[44.66282,43.85938],"type":"Point"}
}