{
  "type": "Feature",
  "properties": {
    "gn:admin1_code":"57.0",
    "gn:asciiname":"Dolgorukovo",
    "gn:country_code":"RU",
    "gn:dem":210,
    "gn:feature_class":"P",
    "gn:feature_code":"PPL",
    "gn:name":"Dolgorukovo",
    "gn:population":0,
    "gn:timezone":"Europe/Moscow",
    "iso:country":"RU",
    "name:deu_x_preferred":[
        "Dolgorukowo"
    ],
    "name:ita_x_preferred":[
        "Dolgorukovo"
    ],
    "name:rus_x_preferred":[
        "\u0414\u043e\u043b\u0433\u043e\u0440\u0443\u043a\u043e\u0432\u043e"
    ],
    "wof:name":"Dolgorukovo",
    "wof:placetype":"locality"
},
  "geometry": {"coordinates":[44.93194,53.92281],"type":"Point"}
}