{
  "type": "Feature",
  "properties": {
    "gn:admin1_code":"85",
    "gn:asciiname":"Pustosh'",
    "gn:country_code":"RU",
    "gn:dem":159,
    "gn:feature_class":"P",
    "gn:feature_code":"PPL",
    "gn:name":"Pustosh\u2019",
    "gn:population":0,
    "gn:timezone":"Europe/Moscow",
    "iso:country":"RU",
    "name:eng_x_preferred":[
        "Pustosh'"
    ],
    "name:nor_x_preferred":[
        "Pustosj"
    ],
    "name:rus_x_preferred":[
        "\u041f\u0443\u0441\u0442\u043e\u0448\u044c"
    ],
    "name:und_x_variant":[
        "Starovskaya Pustosh\u2019",
        "\u041f\u0443\u0441\u0442\u043e\u0448\u044c",
        "Pustosh\u2019"
    ],
    "wof:name":"Pustosh'",
    "wof:placetype":"locality"
},
  "geometry": {"coordinates":[42.73684,60.10032],"type":"Point"}
}