{
  "type": "Feature",
  "properties": {
    "gn:admin1_code":"78",
    "gn:asciiname":"Novoborovaya",
    "gn:country_code":"RU",
    "gn:dem":83,
    "gn:feature_class":"P",
    "gn:feature_code":"PPL",
    "gn:name":"Novoborovaya",
    "gn:population":0,
    "gn:timezone":"Asia/Yekaterinburg",
    "iso:country":"RU",
    "name:rus_x_preferred":[
        "\u041d\u043e\u0432\u043e\u0431\u043e\u0440\u043e\u0432\u0430\u044f"
    ],
    "wof:name":"Novoborovaya",
    "wof:placetype":"locality"
},
  "geometry": {"coordinates":[70.8326,57.0706],"type":"Point"}
}