{
  "type": "Feature",
  "properties": {
    "gn:admin1_code":"62.0",
    "gn:asciiname":"Degtyanoye",
    "gn:country_code":"RU",
    "gn:dem":149,
    "gn:feature_class":"P",
    "gn:feature_code":"PPL",
    "gn:name":"Degtyanoye",
    "gn:population":0,
    "gn:timezone":"Europe/Moscow",
    "iso:country":"RU",
    "name:eng_x_preferred":[
        "Degtyanoye"
    ],
    "name:nor_x_preferred":[
        "Degtjanoje"
    ],
    "name:rus_x_preferred":[
        "\u0414\u0435\u0433\u0442\u044f\u043d\u043e\u0435"
    ],
    "name:und_x_variant":[
        "Dyagtyanoye"
    ],
    "wof:name":"Degtyanoye",
    "wof:placetype":"locality"
},
  "geometry": {"coordinates":[40.2114,53.7264],"type":"Point"}
}