{
  "type": "Feature",
  "properties": {
    "gn:admin1_code":"65",
    "gn:asciiname":"Dom Vandyshevykh",
    "gn:country_code":"RU",
    "gn:dem":92,
    "gn:feature_class":"P",
    "gn:feature_code":"PPL",
    "gn:name":"Dom Vandyshevykh",
    "gn:population":0,
    "gn:timezone":"Europe/Samara",
    "iso:country":"RU",
    "name:rus_x_preferred":[
        "\u0414\u043e\u043c \u0412\u0430\u043d\u0434\u044b\u0448\u0435\u0432\u044b\u0445"
    ],
    "name:und_x_variant":[
        "\u0414\u043e\u043c \u0412\u0430\u043d\u0434\u044b\u0448\u0435\u0432\u044b\u0445"
    ],
    "wof:name":"Dom Vandyshevykh",
    "wof:placetype":"locality"
},
  "geometry": {"coordinates":[50.6727,52.0694],"type":"Point"}
}