{
  "type": "Feature",
  "properties": {
    "gn:admin1_code":"93",
    "gn:asciiname":"Kokuy-Komogortsevo",
    "gn:country_code":"RU",
    "gn:dem":554,
    "gn:feature_class":"P",
    "gn:feature_code":"PPL",
    "gn:name":"Kokuy-Komogortsevo",
    "gn:population":0,
    "gn:timezone":"Asia/Chita",
    "iso:country":"RU",
    "name:eng_x_preferred":[
        "Kokuy-Komogortsevo"
    ],
    "name:nor_x_preferred":[
        "Kokuj-Komogortsevo"
    ],
    "name:rus_x_preferred":[
        "\u041a\u043e\u043a\u0443\u0439-\u041a\u043e\u043c\u043e\u0433\u043e\u0440\u0446\u0435\u0432\u043e"
    ],
    "name:und_x_variant":[
        "Kokuy",
        "Komogortsevskoye",
        "Kokui",
        "Komogory",
        "\u041a\u043e\u043a\u0443\u0439-\u041a\u043e\u043c\u043e\u0433\u043e\u0440\u0446\u0435\u0432\u043e",
        "Kokuy-Komogortsevo"
    ],
    "wof:name":"Kokuy-Komogortsevo",
    "wof:placetype":"locality"
},
  "geometry": {"coordinates":[115.86190000000001,51.93424],"type":"Point"}
}