{
  "type": "Feature",
  "properties": {
    "gn:admin1_code":"16",
    "gn:asciiname":"Saruy",
    "gn:country_code":"RU",
    "gn:dem":135,
    "gn:feature_class":"P",
    "gn:feature_code":"PPL",
    "gn:name":"Saruy",
    "gn:population":0,
    "gn:timezone":"Europe/Moscow",
    "iso:country":"RU",
    "name:eng_x_preferred":[
        "Saruy"
    ],
    "name:nor_x_preferred":[
        "Saruj"
    ],
    "name:rus_x_preferred":[
        "\u0421\u0430\u0440\u0443\u0439"
    ],
    "name:und_x_variant":[
        "Soruy",
        "\u0421\u0430\u0440\u0443\u0439",
        "Saruy"
    ],
    "wof:name":"Saruy",
    "wof:placetype":"locality"
},
  "geometry": {"coordinates":[47.6768,55.72544],"type":"Point"}
}