{
  "type": "Feature",
  "properties": {
    "gn:admin1_code":"28",
    "gn:asciiname":"Sumerechi",
    "gn:country_code":"RU",
    "gn:dem":130,
    "gn:feature_class":"P",
    "gn:feature_code":"PPL",
    "gn:name":"Sumerechi",
    "gn:population":0,
    "gn:timezone":"Europe/Moscow",
    "iso:country":"RU",
    "name:fin_x_preferred":[
        "Sumeri"
    ],
    "name:rus_x_preferred":[
        "\u0421\u0443\u043c\u0435\u0440\u0435\u0447\u0438"
    ],
    "name:und_x_variant":[
        "\u0421\u0443\u043c\u0435\u0440\u0435\u0447\u0438"
    ],
    "wof:name":"Sumerechi",
    "wof:placetype":"locality"
},
  "geometry": {"coordinates":[34.35,63.35],"type":"Point"}
}