{
  "type": "Feature",
  "properties": {
    "gn:admin1_code":"34",
    "gn:asciiname":"Nizhniy Voch",
    "gn:country_code":"RU",
    "gn:dem":134,
    "gn:feature_class":"P",
    "gn:feature_code":"PPL",
    "gn:name":"Nizhniy Voch",
    "gn:population":0,
    "gn:timezone":"Europe/Moscow",
    "iso:country":"RU",
    "name:rus_x_preferred":[
        "\u041d\u0438\u0436\u043d\u0438\u0439 \u0412\u043e\u0447"
    ],
    "name:und_x_variant":[
        "Nizhnyaya Voch\u2019",
        "Nizhniy Voch",
        "\u041d\u0438\u0436\u043d\u0438\u0439 \u0412\u043e\u0447"
    ],
    "wof:name":"Nizhniy Voch",
    "wof:placetype":"locality"
},
  "geometry": {"coordinates":[54.17108,61.20914000000001],"type":"Point"}
}