{
  "type": "Feature",
  "properties": {
    "gn:admin1_code":"56",
    "gn:asciiname":"Bespdka",
    "gn:country_code":"RU",
    "gn:dem":249,
    "gn:feature_class":"P",
    "gn:feature_code":"PPL",
    "gn:name":"Bespdka",
    "gn:population":0,
    "gn:timezone":"Europe/Moscow",
    "iso:country":"RU",
    "name:nor_x_preferred":[
        "Bespdka"
    ],
    "name:rus_x_preferred":[
        "\u0411\u0435\u0441\u043f\u0434\u043a\u0430"
    ],
    "wof:name":"Bespdka",
    "wof:placetype":"locality"
},
  "geometry": {"coordinates":[35.35778,52.82861],"type":"Point"}
}