{
  "type": "Feature",
  "properties": {
    "gn:admin1_code":"43",
    "gn:asciiname":"Morevo",
    "gn:country_code":"RU",
    "gn:dem":212,
    "gn:feature_class":"P",
    "gn:feature_code":"PPL",
    "gn:name":"Mor\u00ebvo",
    "gn:population":0,
    "gn:timezone":"Europe/Moscow",
    "iso:country":"RU",
    "name:rus_x_preferred":[
        "\u041c\u043e\u0440\u0451\u0432\u043e"
    ],
    "name:und_x_variant":[
        "Mor\u00ebvo"
    ],
    "wof:name":"Morevo",
    "wof:placetype":"locality"
},
  "geometry": {"coordinates":[38.6069,52.778],"type":"Point"}
}