{
  "type": "Feature",
  "properties": {
    "gn:admin1_code":"8",
    "gn:asciiname":"Bash-Il'chikeyevo",
    "gn:country_code":"RU",
    "gn:dem":380,
    "gn:feature_class":"P",
    "gn:feature_code":"PPL",
    "gn:name":"Bash-Il\u2019chikeyevo",
    "gn:population":0,
    "gn:timezone":"Asia/Yekaterinburg",
    "iso:country":"RU",
    "name:nor_x_preferred":[
        "Basjkirskoje Iltsjikejevo"
    ],
    "name:rus_x_preferred":[
        "\u0411\u0430\u0448-\u0418\u043b\u044c\u0447\u0438\u043a\u0435\u0435\u0432\u043e"
    ],
    "name:und_x_variant":[
        "Il\u2019chikeyeva",
        "Bashkirskaya Il\u2019chikeyevo",
        "Il\u2019chikeyevo",
        "Bashkirskoye Il\u2019chikeyevo",
        "Bash-Il\u2019chikeyevo"
    ],
    "wof:name":"Bash-Il'chikeyevo",
    "wof:placetype":"locality"
},
  "geometry": {"coordinates":[58.4788,55.0684],"type":"Point"}
}