{
  "type": "Feature",
  "properties": {
    "gn:admin1_code":"57.0",
    "gn:asciiname":"Arshinovka",
    "gn:country_code":"RU",
    "gn:dem":150,
    "gn:feature_class":"P",
    "gn:feature_code":"PPL",
    "gn:name":"Arshinovka",
    "gn:population":0,
    "gn:timezone":"Europe/Moscow",
    "iso:country":"RU",
    "name:eng_x_preferred":[
        "Arshinovka"
    ],
    "name:nor_x_preferred":[
        "Arsjinovka"
    ],
    "name:rus_x_preferred":[
        "\u0410\u0440\u0448\u0438\u043d\u043e\u0432\u043a\u0430"
    ],
    "wof:name":"Arshinovka",
    "wof:placetype":"locality"
},
  "geometry": {"coordinates":[43.98228,53.60308000000001],"type":"Point"}
}