{
  "type": "Feature",
  "properties": {
    "gn:admin1_code":"84.0",
    "gn:asciiname":"Dyad'kin",
    "gn:country_code":"RU",
    "gn:dem":24,
    "gn:feature_class":"P",
    "gn:feature_code":"PPL",
    "gn:name":"Dyad\u2019kin",
    "gn:population":0,
    "gn:timezone":"Europe/Volgograd",
    "iso:country":"RU",
    "name:rus_x_preferred":[
        "\u0414\u044f\u0434\u044c\u043a\u0438\u043d"
    ],
    "name:und_x_variant":[
        "Dyad\u2019kin"
    ],
    "wof:name":"Dyad'kin",
    "wof:placetype":"locality"
},
  "geometry": {"coordinates":[45.91667,49.46667],"type":"Point"}
}