{
  "type": "Feature",
  "properties": {
    "gn:admin1_code":"16",
    "gn:asciiname":"Sin'yal-Shat'ma",
    "gn:country_code":"RU",
    "gn:dem":186,
    "gn:feature_class":"P",
    "gn:feature_code":"PPL",
    "gn:name":"Sin\u2019yal-Shat\u2019ma",
    "gn:population":0,
    "gn:timezone":"Europe/Moscow",
    "iso:country":"RU",
    "name:rus_x_preferred":[
        "\u0421\u0438\u043d\u044c\u044f\u043b-\u0428\u0430\u0442\u044c\u043c\u0430"
    ],
    "name:und_x_variant":[
        "Sin\u2019yaly",
        "Sin\u2019yal-Shat\u2019ma",
        "\u0421\u0438\u043d\u044c\u044f\u043b-\u0428\u0430\u0442\u044c\u043c\u0430"
    ],
    "wof:name":"Sin'yal-Shat'ma",
    "wof:placetype":"locality"
},
  "geometry": {"coordinates":[47.06215,55.85288000000001],"type":"Point"}
}