{
  "type": "Feature",
  "properties": {
    "gn:admin1_code":"69",
    "gn:asciiname":"Karakovichi",
    "gn:country_code":"RU",
    "gn:dem":184,
    "gn:feature_class":"P",
    "gn:feature_code":"PPL",
    "gn:name":"Karakovichi",
    "gn:population":0,
    "gn:timezone":"Europe/Moscow",
    "iso:country":"RU",
    "name:rus_x_preferred":[
        "\u041a\u0430\u0440\u0430\u043a\u043e\u0432\u0438\u0447\u0438"
    ],
    "name:und_x_variant":[
        "Krakovichi",
        "Karakovichi",
        "\u041a\u0430\u0440\u0430\u043a\u043e\u0432\u0438\u0447\u0438"
    ],
    "wof:name":"Karakovichi",
    "wof:placetype":"locality"
},
  "geometry": {"coordinates":[33.39484,54.07341],"type":"Point"}
}