{
  "type": "Feature",
  "properties": {
    "gn:admin1_code":"33",
    "gn:asciiname":"Berezhane",
    "gn:country_code":"RU",
    "gn:dem":102,
    "gn:feature_class":"P",
    "gn:feature_code":"PPL",
    "gn:name":"Berezhane",
    "gn:population":0,
    "gn:timezone":"Europe/Moscow",
    "iso:country":"RU",
    "name:rus_x_preferred":[
        "\u0411\u0435\u0440\u0435\u0436\u0430\u043d\u0435"
    ],
    "wof:name":"Berezhane",
    "wof:placetype":"locality"
},
  "geometry": {"coordinates":[47.4225,57.9807],"type":"Point"}
}