{
  "type": "Feature",
  "properties": {
    "gn:admin1_code":"85",
    "gn:asciiname":"Ostanino",
    "gn:country_code":"RU",
    "gn:dem":188,
    "gn:feature_class":"P",
    "gn:feature_code":"PPL",
    "gn:name":"Ostanino",
    "gn:population":0,
    "gn:timezone":"Europe/Moscow",
    "iso:country":"RU",
    "name:rus_x_preferred":[
        "\u041e\u0441\u0442\u0430\u043d\u0438\u043d\u043e"
    ],
    "name:und_x_variant":[
        "\u041e\u0441\u0442\u0430\u043d\u0438\u043d\u043e"
    ],
    "wof:name":"Ostanino",
    "wof:placetype":"locality"
},
  "geometry": {"coordinates":[40.34289,58.86059],"type":"Point"}
}