{
  "type": "Feature",
  "properties": {
    "gn:admin1_code":"88.0",
    "gn:asciiname":"Strugunovo",
    "gn:country_code":"RU",
    "gn:dem":99,
    "gn:feature_class":"P",
    "gn:feature_code":"PPL",
    "gn:name":"Strugunovo",
    "gn:population":0,
    "gn:timezone":"Europe/Moscow",
    "iso:country":"RU",
    "name:rus_x_preferred":[
        "\u0421\u0442\u0440\u0443\u0433\u0443\u043d\u043e\u0432\u043e"
    ],
    "wof:name":"Strugunovo",
    "wof:placetype":"locality"
},
  "geometry": {"coordinates":[40.74013,58.11359],"type":"Point"}
}