{
  "type": "Feature",
  "properties": {
    "gn:admin1_code":"34",
    "gn:asciiname":"Ust'-Soplesk",
    "gn:country_code":"RU",
    "gn:dem":68,
    "gn:feature_class":"P",
    "gn:feature_code":"PPL",
    "gn:name":"Ust\u2019-Soplesk",
    "gn:population":0,
    "gn:timezone":"Europe/Moscow",
    "iso:country":"RU",
    "name:eng_x_preferred":[
        "Ust'-Soplesk"
    ],
    "name:nor_x_preferred":[
        "Ust-Soplesk"
    ],
    "name:rus_x_preferred":[
        "\u0423\u0441\u0442\u044c-\u0421\u043e\u043f\u043b\u0435\u0441\u043a"
    ],
    "name:und_x_variant":[
        "Ust\u2019-Soplyas",
        "Ust\u2019-Sopliyas",
        "Ust\u2019-Soplesk"
    ],
    "wof:name":"Ust'-Soplesk",
    "wof:placetype":"locality"
},
  "geometry": {"coordinates":[57.69245,64.35823000000001],"type":"Point"}
}