{
  "type": "Feature",
  "properties": {
    "gn:admin1_code":"80",
    "gn:asciiname":"Gura",
    "gn:country_code":"RU",
    "gn:dem":152,
    "gn:feature_class":"P",
    "gn:feature_code":"PPL",
    "gn:name":"Gura",
    "gn:population":0,
    "gn:timezone":"Europe/Samara",
    "iso:country":"RU",
    "name:eng_x_preferred":[
        "Gura"
    ],
    "name:nor_x_preferred":[
        "Gura"
    ],
    "name:rus_x_preferred":[
        "\u0413\u0443\u0440\u0430"
    ],
    "name:und_x_variant":[
        "Gury",
        "Gure",
        "\u0413\u0443\u0440\u0430",
        "Gura"
    ],
    "wof:name":"Gura",
    "wof:placetype":"locality"
},
  "geometry": {"coordinates":[51.40499000000001,57.28403],"type":"Point"}
}