{
  "type": "Feature",
  "properties": {
    "gn:admin1_code":"54",
    "gn:asciiname":"Atrachi",
    "gn:country_code":"RU",
    "gn:dem":110,
    "gn:feature_class":"P",
    "gn:feature_code":"PPL",
    "gn:name":"Atrachi",
    "gn:population":0,
    "gn:timezone":"Asia/Omsk",
    "iso:country":"RU",
    "name:eng_x_preferred":[
        "Atrachi"
    ],
    "name:nor_x_preferred":[
        "Atratsji"
    ],
    "name:rus_x_preferred":[
        "\u0410\u0442\u0440\u0430\u0447\u0438"
    ],
    "wof:name":"Atrachi",
    "wof:placetype":"locality"
},
  "geometry": {"coordinates":[72.02963000000003,55.95573],"type":"Point"}
}