{
  "type": "Feature",
  "properties": {
    "gn:admin1_code":"90",
    "gn:asciiname":"Yel'shata",
    "gn:country_code":"RU",
    "gn:dem":166,
    "gn:feature_class":"P",
    "gn:feature_code":"PPL",
    "gn:name":"Yel\u2019shata",
    "gn:population":0,
    "gn:timezone":"Asia/Yekaterinburg",
    "iso:country":"RU",
    "name:eng_x_preferred":[
        "Yel'shata"
    ],
    "name:nor_x_preferred":[
        "Jelsjata"
    ],
    "name:rus_x_preferred":[
        "\u0415\u043b\u044c\u0448\u0430\u0442\u0430"
    ],
    "name:und_x_variant":[
        "Yel\u2019shata"
    ],
    "wof:name":"Yel'shata",
    "wof:placetype":"locality"
},
  "geometry": {"coordinates":[54.7288,57.46491999999999],"type":"Point"}
}