{
  "type": "Feature",
  "properties": {
    "gn:admin1_code":"61",
    "gn:asciiname":"Podzemgaz",
    "gn:country_code":"RU",
    "gn:dem":133,
    "gn:feature_class":"P",
    "gn:feature_code":"PPL",
    "gn:name":"Podzemgaz",
    "gn:population":0,
    "gn:timezone":"Europe/Moscow",
    "iso:country":"RU",
    "name:rus_x_preferred":[
        "\u041f\u043e\u0434\u0437\u0435\u043c\u0433\u0430\u0437"
    ],
    "wof:name":"Podzemgaz",
    "wof:placetype":"locality"
},
  "geometry": {"coordinates":[40.2156,48.2651],"type":"Point"}
}