{
  "type": "Feature",
  "properties": {
    "gn:admin1_code":"29",
    "gn:asciiname":"Antoninovka",
    "gn:country_code":"RU",
    "gn:dem":669,
    "gn:feature_class":"P",
    "gn:feature_code":"PPL",
    "gn:name":"Antoninovka",
    "gn:population":0,
    "gn:timezone":"Asia/Novokuznetsk",
    "iso:country":"RU",
    "name:eng_x_preferred":[
        "Antoninovka"
    ],
    "name:nor_x_preferred":[
        "Antoninovka"
    ],
    "name:rus_x_preferred":[
        "\u0410\u043d\u0442\u043e\u043d\u0438\u043d\u043e\u0432\u043a\u0430"
    ],
    "name:und_x_variant":[
        "\u0410\u043d\u0442\u043e\u043d\u0438\u043d\u043e\u0432\u043a\u0430",
        "Antoninovka"
    ],
    "wof:name":"Antoninovka",
    "wof:placetype":"locality"
},
  "geometry": {"coordinates":[88.81667,54.21666999999999],"type":"Point"}
}