{
  "type": "Feature",
  "properties": {
    "gn:admin1_code":"33.0",
    "gn:asciiname":"Bakhtenki",
    "gn:country_code":"RU",
    "gn:dem":134,
    "gn:feature_class":"P",
    "gn:feature_code":"PPL",
    "gn:name":"Bakhtenki",
    "gn:population":0,
    "gn:timezone":"Europe/Kirov",
    "iso:country":"RU",
    "name:nor_x_preferred":[
        "Bakhtenki"
    ],
    "name:rus_x_preferred":[
        "\u0411\u0430\u0445\u0442\u0435\u043d\u043a\u0438"
    ],
    "wof:name":"Bakhtenki",
    "wof:placetype":"locality"
},
  "geometry": {"coordinates":[48.5303,57.2163],"type":"Point"}
}