{
  "type": "Feature",
  "properties": {
    "gn:admin1_code":"90.0",
    "gn:asciiname":"Abrosy",
    "gn:country_code":"RU",
    "gn:dem":126,
    "gn:feature_class":"P",
    "gn:feature_code":"PPL",
    "gn:name":"Abrosy",
    "gn:population":0,
    "gn:timezone":"Asia/Yekaterinburg",
    "iso:country":"RU",
    "name:rus_x_preferred":[
        "\u0410\u0431\u0440\u043e\u0441\u044b"
    ],
    "wof:name":"Abrosy",
    "wof:placetype":"locality"
},
  "geometry": {"coordinates":[55.8943,58.233],"type":"Point"}
}