{
  "type": "Feature",
  "properties": {
    "gn:admin1_code":"37.0",
    "gn:asciiname":"Repishche",
    "gn:country_code":"RU",
    "gn:dem":113,
    "gn:feature_class":"P",
    "gn:feature_code":"PPL",
    "gn:name":"Repishche",
    "gn:population":0,
    "gn:timezone":"Europe/Moscow",
    "iso:country":"RU",
    "name:rus_x_preferred":[
        "\u0420\u0435\u043f\u0438\u0449\u0435"
    ],
    "wof:name":"Repishche",
    "wof:placetype":"locality"
},
  "geometry": {"coordinates":[41.09871,57.44422],"type":"Point"}
}