{
  "type": "Feature",
  "properties": {
    "gn:admin1_code":"73",
    "gn:asciiname":"Novyy Michan",
    "gn:country_code":"RU",
    "gn:dem":104,
    "gn:feature_class":"P",
    "gn:feature_code":"PPL",
    "gn:name":"Novyy Michan",
    "gn:population":0,
    "gn:timezone":"Europe/Moscow",
    "iso:country":"RU",
    "name:rus_x_preferred":[
        "\u041d\u043e\u0432\u044b\u0439 \u041c\u0438\u0447\u0430\u043d"
    ],
    "name:und_x_variant":[
        "Novyy Michen\u2019",
        "Novyy Michan",
        "\u041d\u043e\u0432\u044b\u0439 \u041c\u0438\u0447\u0430\u043d"
    ],
    "wof:name":"Novyy Michan",
    "wof:placetype":"locality"
},
  "geometry": {"coordinates":[50.2694,56.041],"type":"Point"}
}