{
  "type": "Feature",
  "properties": {
    "gn:admin1_code":"60.0",
    "gn:asciiname":"Telenchino",
    "gn:country_code":"RU",
    "gn:dem":160,
    "gn:feature_class":"P",
    "gn:feature_code":"PPL",
    "gn:name":"Telenchino",
    "gn:population":0,
    "gn:timezone":"Europe/Moscow",
    "iso:country":"RU",
    "name:rus_x_preferred":[
        "\u0422\u0435\u043b\u0435\u043d\u0447\u0438\u043d\u043e"
    ],
    "wof:name":"Telenchino",
    "wof:placetype":"locality"
},
  "geometry": {"coordinates":[28.60695,56.31723],"type":"Point"}
}