{
  "type": "Feature",
  "properties": {
    "gn:admin1_code":"77",
    "gn:asciiname":"Sheverdino",
    "gn:country_code":"RU",
    "gn:dem":201,
    "gn:feature_class":"P",
    "gn:feature_code":"PPL",
    "gn:name":"Sheverdino",
    "gn:population":0,
    "gn:timezone":"Europe/Moscow",
    "iso:country":"RU",
    "name:rus_x_preferred":[
        "\u0428\u0435\u0432\u0435\u0440\u0434\u0438\u043d\u043e"
    ],
    "wof:name":"Sheverdino",
    "wof:placetype":"locality"
},
  "geometry": {"coordinates":[32.3246,56.37542],"type":"Point"}
}