{
  "type": "Feature",
  "properties": {
    "gn:admin1_code":"29",
    "gn:asciiname":"Kulakovo",
    "gn:country_code":"RU",
    "gn:dem":204,
    "gn:feature_class":"P",
    "gn:feature_code":"PPL",
    "gn:name":"Kulakovo",
    "gn:population":0,
    "gn:timezone":"Asia/Novokuznetsk",
    "iso:country":"RU",
    "name:rus_x_preferred":[
        "\u041a\u0443\u043b\u0430\u043a\u043e\u0432\u043e"
    ],
    "wof:name":"Kulakovo",
    "wof:placetype":"locality"
},
  "geometry": {"coordinates":[85.1152,55.7873],"type":"Point"}
}