{
  "type": "Feature",
  "properties": {
    "gn:admin1_code":"69",
    "gn:asciiname":"Lyubovskiye Dvortsy",
    "gn:country_code":"RU",
    "gn:dem":188,
    "gn:feature_class":"P",
    "gn:feature_code":"PPL",
    "gn:name":"Lyubovskiye Dvortsy",
    "gn:population":0,
    "gn:timezone":"Europe/Moscow",
    "iso:country":"RU",
    "name:rus_x_preferred":[
        "\u041b\u044e\u0431\u043e\u0432\u0441\u043a\u0438\u0435 \u0414\u0432\u043e\u0440\u0446\u044b"
    ],
    "wof:name":"Lyubovskiye Dvortsy",
    "wof:placetype":"locality"
},
  "geometry": {"coordinates":[32.992,54.02],"type":"Point"}
}