{
  "type": "Feature",
  "properties": {
    "gn:admin1_code":"75",
    "gn:asciiname":"Lozunga",
    "gn:country_code":"RU",
    "gn:dem":51,
    "gn:feature_class":"P",
    "gn:feature_code":"PPL",
    "gn:name":"Lozunga",
    "gn:population":0,
    "gn:timezone":"Asia/Tomsk",
    "iso:country":"RU",
    "name:eng_x_preferred":[
        "Lozunga"
    ],
    "name:nor_x_preferred":[
        "Lozunga"
    ],
    "name:rus_x_preferred":[
        "\u041b\u043e\u0437\u0443\u043d\u0433\u0430"
    ],
    "wof:name":"Lozunga",
    "wof:placetype":"locality"
},
  "geometry": {"coordinates":[80.66611,58.98694],"type":"Point"}
}