{
  "type": "Feature",
  "properties": {
    "gn:admin1_code":"78",
    "gn:asciiname":"Gubina",
    "gn:country_code":"RU",
    "gn:dem":63,
    "gn:feature_class":"P",
    "gn:feature_code":"PPL",
    "gn:name":"Gubina",
    "gn:population":0,
    "gn:timezone":"Asia/Yekaterinburg",
    "iso:country":"RU",
    "name:eng_x_preferred":[
        "Gubino"
    ],
    "name:nor_x_preferred":[
        "Gubina"
    ],
    "name:rus_x_preferred":[
        "\u0413\u0443\u0431\u0438\u043d\u0430"
    ],
    "name:und_x_variant":[
        "Gubino",
        "Gubina",
        "\u0413\u0443\u0431\u0438\u043d\u0430"
    ],
    "wof:name":"Gubina",
    "wof:placetype":"locality"
},
  "geometry": {"coordinates":[65.9794,56.2017],"type":"Point"}
}