{
  "type": "Feature",
  "properties": {
    "gn:admin1_code":"10",
    "gn:asciiname":"Ivanov",
    "gn:country_code":"RU",
    "gn:dem":179,
    "gn:feature_class":"P",
    "gn:feature_code":"PPL",
    "gn:name":"Ivanov",
    "gn:population":0,
    "gn:timezone":"Europe/Moscow",
    "iso:country":"RU",
    "name:deu_x_preferred":[
        "Iwanow"
    ],
    "name:est_x_preferred":[
        "Ivanov"
    ],
    "name:pol_x_preferred":[
        "Iwanow"
    ],
    "name:rus_x_preferred":[
        "\u0418\u0432\u0430\u043d\u043e\u0432"
    ],
    "name:swe_x_preferred":[
        "Ivanov"
    ],
    "name:ukr_x_preferred":[
        "\u0406\u0432\u0430\u043d\u043e\u0432"
    ],
    "wof:name":"Ivanov",
    "wof:placetype":"locality"
},
  "geometry": {"coordinates":[32.5568,52.9209],"type":"Point"}
}