{
  "type": "Feature",
  "properties": {
    "gn:admin1_code":"93",
    "gn:asciiname":"Kombinat",
    "gn:country_code":"RU",
    "gn:dem":654,
    "gn:feature_class":"P",
    "gn:feature_code":"PPL",
    "gn:name":"Kombinat",
    "gn:population":0,
    "gn:timezone":"Asia/Chita",
    "iso:country":"RU",
    "name:rus_x_preferred":[
        "\u041a\u043e\u043c\u0431\u0438\u043d\u0430\u0442"
    ],
    "wof:name":"Kombinat",
    "wof:placetype":"locality"
},
  "geometry": {"coordinates":[116.40000000000001,51.23333],"type":"Point"}
}