{
  "type": "Feature",
  "properties": {
    "gn:admin1_code":"41.0",
    "gn:asciiname":"Rubanshchina",
    "gn:country_code":"RU",
    "gn:dem":157,
    "gn:feature_class":"P",
    "gn:feature_code":"PPL",
    "gn:name":"Rubanshchina",
    "gn:population":0,
    "gn:timezone":"Europe/Moscow",
    "iso:country":"RU",
    "name:rus_x_preferred":[
        "\u0420\u0443\u0431\u0430\u043d\u0449\u0438\u043d\u0430"
    ],
    "name:und_x_variant":[
        "\u0420\u0443\u0431\u0430\u043d\u0449\u0438\u043d\u0430"
    ],
    "wof:name":"Rubanshchina",
    "wof:placetype":"locality"
},
  "geometry": {"coordinates":[35.20972000000001,51.18833],"type":"Point"}
}