{
  "type": "Feature",
  "properties": {
    "gn:admin1_code":"25",
    "gn:asciiname":"Zbunovo",
    "gn:country_code":"RU",
    "gn:dem":197,
    "gn:feature_class":"P",
    "gn:feature_code":"PPL",
    "gn:name":"Zbunovo",
    "gn:population":0,
    "gn:timezone":"Europe/Moscow",
    "iso:country":"RU",
    "name:und_x_variant":[
        "Zbukovo",
        "Zbukozo",
        "Zubkovo",
        "Zubnovo",
        "Zbunovo"
    ],
    "wof:name":"Zbunovo",
    "wof:placetype":"locality"
},
  "geometry": {"coordinates":[35.3565,54.22355],"type":"Point"}
}