{
  "type": "Feature",
  "properties": {
    "gn:admin1_code":"11",
    "gn:asciiname":"Ulus Ulentuy",
    "gn:country_code":"RU",
    "gn:dem":576,
    "gn:feature_class":"P",
    "gn:feature_code":"PPL",
    "gn:name":"Ulus Ulentuy",
    "gn:population":0,
    "gn:timezone":"Asia/Irkutsk",
    "iso:country":"RU",
    "name:und_x_variant":[
        "Ulentuy",
        "Ulentui",
        "Ulus Ulentuy"
    ],
    "wof:name":"Ulus Ulentuy",
    "wof:placetype":"locality"
},
  "geometry": {"coordinates":[106.8625,50.46086],"type":"Point"}
}