{
  "type": "Feature",
  "properties": {
    "gn:admin1_code":"25",
    "gn:asciiname":"Uvalovka",
    "gn:country_code":"RU",
    "gn:dem":219,
    "gn:feature_class":"P",
    "gn:feature_code":"PPL",
    "gn:name":"Uvalovka",
    "gn:population":0,
    "gn:timezone":"Europe/Moscow",
    "iso:country":"RU",
    "name:und_x_variant":[
        "Uvalovo",
        "Uvalovka"
    ],
    "wof:name":"Uvalovka",
    "wof:placetype":"locality"
},
  "geometry": {"coordinates":[37.06949,54.64856],"type":"Point"}
}