{
  "type": "Feature",
  "properties": {
    "gn:admin1_code":"49",
    "gn:asciiname":"Kamenskiy",
    "gn:cc2":"RU",
    "gn:country_code":"RU",
    "gn:dem":227,
    "gn:feature_class":"P",
    "gn:feature_code":"PPL",
    "gn:name":"Kamenskiy",
    "gn:population":0,
    "gn:timezone":"Europe/Moscow",
    "iso:country":"RU",
    "name:rus_x_preferred":[
        "\u041a\u0430\u043c\u0435\u043d\u0441\u043a\u0438\u0439"
    ],
    "name:und_x_variant":[
        "Letnik Kamenskiy Pogost",
        "Izba Kamenka",
        "Kamenskiy Pogost",
        "Kamenka",
        "Kamenskiy",
        "\u041a\u0430\u043c\u0435\u043d\u0441\u043a\u0438\u0439"
    ],
    "wof:name":"Kamenskiy",
    "wof:placetype":"locality"
},
  "geometry": {"coordinates":[37.76667,67.26666999999999],"type":"Point"}
}