{
  "type": "Feature",
  "properties": {
    "gn:admin1_code":"60",
    "gn:asciiname":"Prishvino Vtoroye",
    "gn:country_code":"RU",
    "gn:dem":83,
    "gn:feature_class":"P",
    "gn:feature_code":"PPL",
    "gn:name":"Prishvino Vtoroye",
    "gn:population":0,
    "gn:timezone":"Europe/Moscow",
    "iso:country":"RU",
    "name:rus_x_preferred":[
        "\u041f\u0440\u0438\u0448\u0432\u0438\u043d\u043e \u0412\u0442\u043e\u0440\u043e\u0435"
    ],
    "wof:name":"Prishvino Vtoroye",
    "wof:placetype":"locality"
},
  "geometry": {"coordinates":[29.1688,56.9818],"type":"Point"}
}