{
  "type": "Feature",
  "properties": {
    "gn:admin1_code":"84",
    "gn:asciiname":"Krasnyy",
    "gn:country_code":"RU",
    "gn:dem":-6,
    "gn:feature_class":"P",
    "gn:feature_code":"PPL",
    "gn:name":"Krasnyy",
    "gn:population":0,
    "gn:timezone":"Europe/Volgograd",
    "iso:country":"RU",
    "name:eng_x_preferred":[
        "Krasnyy"
    ],
    "name:nor_x_preferred":[
        "Krasnyj"
    ],
    "name:rus_x_preferred":[
        "\u041a\u0440\u0430\u0441\u043d\u044b\u0439"
    ],
    "name:und_x_variant":[
        "Imeni Bud\u00ebnnogo"
    ],
    "wof:name":"Krasnyy",
    "wof:placetype":"locality"
},
  "geometry": {"coordinates":[44.80547,48.63475],"type":"Point"}
}