{
  "type": "Feature",
  "properties": {
    "gn:admin1_code":"05",
    "gn:asciiname":"Bryanta",
    "gn:cc2":"RU",
    "gn:country_code":"RU",
    "gn:dem":716,
    "gn:feature_class":"P",
    "gn:feature_code":"PPL",
    "gn:name":"Bryanta",
    "gn:population":0,
    "gn:timezone":"Asia/Yakutsk",
    "iso:country":"RU",
    "name:rus_x_preferred":[
        "\u0411\u0440\u044f\u043d\u0442\u0430"
    ],
    "name:und_x_variant":[
        "Zaimka Bryanta",
        "Bryanta"
    ],
    "wof:name":"Bryanta",
    "wof:placetype":"locality"
},
  "geometry": {"coordinates":[127.73333,55.58333],"type":"Point"}
}