{
  "type": "Feature",
  "properties": {
    "gn:admin1_code":"28",
    "gn:asciiname":"Kyukyamya",
    "gn:cc2":"RU",
    "gn:country_code":"RU",
    "gn:dem":159,
    "gn:feature_class":"P",
    "gn:feature_code":"PPL",
    "gn:name":"Kyukyamya",
    "gn:population":0,
    "gn:timezone":"Europe/Moscow",
    "iso:country":"RU",
    "name:fin_x_preferred":[
        "Tyr\u00e4m\u00e4"
    ],
    "wof:name":"Kyukyamya",
    "wof:placetype":"locality"
},
  "geometry": {"coordinates":[31.04187,62.13455],"type":"Point"}
}