{
  "type": "Feature",
  "properties": {
    "gn:admin1_code":"73",
    "gn:asciiname":"Turayevo",
    "gn:country_code":"RU",
    "gn:dem":112,
    "gn:feature_class":"P",
    "gn:feature_code":"PPL",
    "gn:name":"Turayevo",
    "gn:population":0,
    "gn:timezone":"Europe/Moscow",
    "iso:country":"RU",
    "name:eng_x_preferred":[
        "Turayevo"
    ],
    "name:nor_x_preferred":[
        "Turajevo"
    ],
    "name:rus_x_preferred":[
        "\u0422\u0443\u0440\u0430\u0435\u0432\u043e"
    ],
    "wof:name":"Turayevo",
    "wof:placetype":"locality"
},
  "geometry": {"coordinates":[52.57698000000001,55.95296],"type":"Point"}
}