{
  "type": "Feature",
  "properties": {
    "gn:admin1_code":"29",
    "gn:asciiname":"Byzovo",
    "gn:country_code":"RU",
    "gn:dem":194,
    "gn:feature_class":"P",
    "gn:feature_code":"PPL",
    "gn:name":"Byzovo",
    "gn:population":0,
    "gn:timezone":"Asia/Novokuznetsk",
    "iso:country":"RU",
    "name:rus_x_preferred":[
        "\u0411\u044b\u0437\u043e\u0432\u043e"
    ],
    "wof:name":"Byzovo",
    "wof:placetype":"locality"
},
  "geometry": {"coordinates":[87.1935,53.8752],"type":"Point"}
}