{
  "type": "Feature",
  "properties": {
    "gn:admin1_code":"32",
    "gn:asciiname":"Ruzitgort",
    "gn:country_code":"RU",
    "gn:dem":5,
    "gn:feature_class":"P",
    "gn:feature_code":"PPL",
    "gn:name":"Ruzitgort",
    "gn:population":0,
    "gn:timezone":"Asia/Yekaterinburg",
    "iso:country":"RU",
    "name:eng_x_preferred":[
        "Ruzitgort"
    ],
    "name:nor_x_preferred":[
        "Ruzitgort"
    ],
    "name:rus_x_preferred":[
        "\u0420\u0443\u0437\u0438\u0442\u0433\u043e\u0440\u0442"
    ],
    "wof:name":"Ruzitgort",
    "wof:placetype":"locality"
},
  "geometry": {"coordinates":[64.96666999999999,62.86666999999999],"type":"Point"}
}