{
  "type": "Feature",
  "properties": {
    "gn:admin1_code":"60.0",
    "gn:asciiname":"Belaya Niva",
    "gn:country_code":"RU",
    "gn:dem":148,
    "gn:feature_class":"P",
    "gn:feature_code":"PPL",
    "gn:name":"Belaya Niva",
    "gn:population":0,
    "gn:timezone":"Europe/Moscow",
    "iso:country":"RU",
    "name:nor_x_preferred":[
        "Belaja Niva"
    ],
    "name:rus_x_preferred":[
        "\u0411\u0435\u043b\u0430\u044f \u041d\u0438\u0432\u0430"
    ],
    "wof:name":"Belaya Niva",
    "wof:placetype":"locality"
},
  "geometry": {"coordinates":[30.81667,56.15],"type":"Point"}
}