{
  "type": "Feature",
  "properties": {
    "gn:admin1_code":"90",
    "gn:asciiname":"Taskaikha",
    "gn:cc2":"RU",
    "gn:country_code":"RU",
    "gn:dem":231,
    "gn:feature_class":"P",
    "gn:feature_code":"PPL",
    "gn:name":"Taskaikha",
    "gn:population":0,
    "gn:timezone":"Asia/Yekaterinburg",
    "iso:country":"RU",
    "name:und_x_variant":[
        "Gaskaikha",
        "Taskaikha"
    ],
    "wof:name":"Taskaikha",
    "wof:placetype":"locality"
},
  "geometry": {"coordinates":[58.25,59.05],"type":"Point"}
}