{
  "type": "Feature",
  "properties": {
    "gn:admin1_code":"34",
    "gn:asciiname":"Pozhegeshor",
    "gn:country_code":"RU",
    "gn:dem":185,
    "gn:feature_class":"P",
    "gn:feature_code":"PPL",
    "gn:name":"Pozhegeshor",
    "gn:population":0,
    "gn:timezone":"Europe/Moscow",
    "iso:country":"RU",
    "name:rus_x_preferred":[
        "\u041f\u043e\u0436\u0435\u0433\u0435\u0448\u043e\u0440"
    ],
    "wof:name":"Pozhegeshor",
    "wof:placetype":"locality"
},
  "geometry": {"coordinates":[49.45,61.51667],"type":"Point"}
}