{
  "type": "Feature",
  "properties": {
    "gn:admin1_code":"50.0",
    "gn:asciiname":"Chizha",
    "gn:country_code":"RU",
    "gn:dem":6,
    "gn:feature_class":"P",
    "gn:feature_code":"PPL",
    "gn:name":"Chizha",
    "gn:population":0,
    "gn:timezone":"Europe/Moscow",
    "iso:country":"RU",
    "name:eng_x_preferred":[
        "Chizha"
    ],
    "name:nor_x_preferred":[
        "Tsjizja"
    ],
    "name:rus_x_preferred":[
        "\u0427\u0438\u0436\u0430"
    ],
    "name:und_x_variant":[
        "Staraya Chizha"
    ],
    "wof:name":"Chizha",
    "wof:placetype":"locality"
},
  "geometry": {"coordinates":[44.34651,67.09220999999999],"type":"Point"}
}