{
  "type": "Feature",
  "properties": {
    "gn:admin1_code":"81",
    "gn:asciiname":"Novaya Bekshanka",
    "gn:country_code":"RU",
    "gn:dem":203,
    "gn:feature_class":"P",
    "gn:feature_code":"PPL",
    "gn:name":"Novaya Bekshanka",
    "gn:population":0,
    "gn:timezone":"Europe/Ulyanovsk",
    "iso:country":"RU",
    "name:eng_x_preferred":[
        "Novaya Bekshanka"
    ],
    "name:nor_x_preferred":[
        "Nov.Beksjanka"
    ],
    "name:rus_x_preferred":[
        "\u041d\u043e\u0432.\u0411\u0435\u043a\u0448\u0430\u043d\u043a\u0430"
    ],
    "name:rus_x_variant":[
        "\u041d\u043e\u0432\u0430\u044f \u0411\u0435\u043a\u0448\u0430\u043d\u043a\u0430"
    ],
    "wof:name":"Novaya Bekshanka",
    "wof:placetype":"locality"
},
  "geometry": {"coordinates":[47.05994000000001,53.38547],"type":"Point"}
}