{
  "type": "Feature",
  "properties": {
    "gn:admin1_code":"66.0",
    "gn:asciiname":"Novokandakopshino",
    "gn:country_code":"RU",
    "gn:dem":84,
    "gn:feature_class":"P",
    "gn:feature_code":"PPL",
    "gn:name":"Novokandakopshino",
    "gn:population":0,
    "gn:timezone":"Europe/Moscow",
    "iso:country":"RU",
    "name:fin_x_preferred":[
        "Kappisi"
    ],
    "name:rus_x_preferred":[
        "\u041d\u043e\u0432\u043e\u043a\u0430\u043d\u0434\u0430\u043a\u043e\u043f\u0448\u0438\u043d\u043e"
    ],
    "name:und_x_variant":[
        "\u041d\u043e\u0432\u043e\u043a\u0430\u043d\u0434\u0430\u043a\u043e\u043f\u0448\u0438\u043d\u043e"
    ],
    "wof:name":"Novokandakopshino",
    "wof:placetype":"locality"
},
  "geometry": {"coordinates":[30.28194,59.69778],"type":"Point"}
}