{
  "type": "Feature",
  "properties": {
    "gn:admin1_code":"73",
    "gn:asciiname":"Russkiye Kirmeni",
    "gn:country_code":"RU",
    "gn:dem":76,
    "gn:feature_class":"P",
    "gn:feature_code":"PPL",
    "gn:name":"Russkiye Kirmeni",
    "gn:population":0,
    "gn:timezone":"Europe/Moscow",
    "iso:country":"RU",
    "name:eng_x_preferred":[
        "Russkiye Kirmeni"
    ],
    "name:nor_x_preferred":[
        "Russkije Kirmeni"
    ],
    "name:rus_x_preferred":[
        "\u0420\u0443\u0441\u0441\u043a\u0438\u0435 \u041a\u0438\u0440\u043c\u0435\u043d\u0438"
    ],
    "name:und_x_variant":[
        "\u0420\u0443\u0441\u0441\u043a\u0438\u0435 \u041a\u0438\u0440\u043c\u0435\u043d\u0438",
        "Russkiye Kirmeni"
    ],
    "wof:name":"Russkiye Kirmeni",
    "wof:placetype":"locality"
},
  "geometry": {"coordinates":[51.18747000000001,55.63877],"type":"Point"}
}