{
  "type": "Feature",
  "properties": {
    "gn:admin1_code":"25.0",
    "gn:asciiname":"Felisovo",
    "gn:country_code":"RU",
    "gn:dem":196,
    "gn:feature_class":"P",
    "gn:feature_code":"PPL",
    "gn:name":"Felisovo",
    "gn:population":0,
    "gn:timezone":"Europe/Moscow",
    "iso:country":"RU",
    "name:rus_x_preferred":[
        "\u0424\u0435\u043b\u0438\u0441\u043e\u0432\u043e"
    ],
    "name:rus_x_variant":[
        "\u0424\u0435\u0434\u043e\u0441\u043e\u0432\u043e"
    ],
    "name:und_x_variant":[
        "Fedosovo",
        "Felisovo"
    ],
    "wof:name":"Felisovo",
    "wof:placetype":"locality"
},
  "geometry": {"coordinates":[36.45836,54.59551999999999],"type":"Point"}
}