{
  "type": "Feature",
  "properties": {
    "gn:admin1_code":"77",
    "gn:asciiname":"Krutiki",
    "gn:country_code":"RU",
    "gn:dem":210,
    "gn:feature_class":"P",
    "gn:feature_code":"PPL",
    "gn:name":"Krutiki",
    "gn:population":0,
    "gn:timezone":"Europe/Moscow",
    "iso:country":"RU",
    "name:che_x_preferred":[
        "\u041a\u0440\u0443\u0442\u0438\u043a\u0438"
    ],
    "name:rus_x_preferred":[
        "\u041a\u0440\u0443\u0442\u0438\u043a\u0438"
    ],
    "wof:name":"Krutiki",
    "wof:placetype":"locality"
},
  "geometry": {"coordinates":[32.38667,56.2875],"type":"Point"}
}