{
  "type": "Feature",
  "properties": {
    "gn:admin1_code":"59",
    "gn:asciiname":"Sydagou",
    "gn:country_code":"RU",
    "gn:dem":430,
    "gn:feature_class":"P",
    "gn:feature_code":"PPL",
    "gn:name":"Sydagou",
    "gn:population":0,
    "gn:timezone":"Asia/Vladivostok",
    "iso:country":"RU",
    "wof:name":"Sydagou",
    "wof:placetype":"locality"
},
  "geometry": {"coordinates":[133.96666999999999,43.88333],"type":"Point"}
}