{
  "type": "Feature",
  "properties": {
    "gn:admin1_code":"17",
    "gn:asciiname":"Akushinskiy",
    "gn:country_code":"RU",
    "gn:dem":-21,
    "gn:feature_class":"P",
    "gn:feature_code":"PPL",
    "gn:name":"Akushinskiy",
    "gn:population":0,
    "gn:timezone":"Europe/Moscow",
    "iso:country":"RU",
    "name:nor_x_preferred":[
        "Akusjinskij"
    ],
    "name:rus_x_preferred":[
        "\u0410\u043a\u0443\u0448\u0438\u043d\u0441\u043a\u0438\u0439"
    ],
    "wof:name":"Akushinskiy",
    "wof:placetype":"locality"
},
  "geometry": {"coordinates":[46.31972,44.16944],"type":"Point"}
}