{
  "type": "Feature",
  "properties": {
    "gn:admin1_code":"28",
    "gn:asciiname":"Kuokkaniyemi",
    "gn:cc2":"RU",
    "gn:country_code":"RU",
    "gn:dem":30,
    "gn:feature_class":"P",
    "gn:feature_code":"PPL",
    "gn:name":"Kuokkaniyemi",
    "gn:population":0,
    "gn:timezone":"Europe/Moscow",
    "iso:country":"RU",
    "name:eng_x_preferred":[
        "Kuokkaniyemi"
    ],
    "name:fin_x_preferred":[
        "Kuokkaniemi"
    ],
    "name:nor_x_preferred":[
        "Kuokkaniemi"
    ],
    "name:rus_x_preferred":[
        "\u041a\u0443\u043e\u043a\u043a\u0430\u043d\u0438\u044d\u043c\u0438"
    ],
    "name:rus_x_variant":[
        "\u041a\u0443\u043e\u043a\u043a\u0430\u043d\u0438\u0435\u043c\u0438"
    ],
    "wof:name":"Kuokkaniyemi",
    "wof:placetype":"locality"
},
  "geometry": {"coordinates":[30.36667000000001,61.65],"type":"Point"}
}