{
  "type": "Feature",
  "properties": {
    "gn:admin1_code":"69",
    "gn:asciiname":"Latarevo",
    "gn:country_code":"RU",
    "gn:dem":200,
    "gn:feature_class":"P",
    "gn:feature_code":"PPL",
    "gn:name":"Latarevo",
    "gn:population":0,
    "gn:timezone":"Europe/Moscow",
    "iso:country":"RU",
    "name:rus_x_preferred":[
        "\u041b\u0430\u0442\u0430\u0440\u0435\u0432\u043e"
    ],
    "wof:name":"Latarevo",
    "wof:placetype":"locality"
},
  "geometry": {"coordinates":[34.04472,54.79611],"type":"Point"}
}