{
  "type": "Feature",
  "properties": {
    "gn:admin1_code":"91",
    "gn:asciiname":"Novaya Il'inka",
    "gn:country_code":"RU",
    "gn:dem":302,
    "gn:feature_class":"P",
    "gn:feature_code":"PPL",
    "gn:name":"Novaya Il\u2019inka",
    "gn:population":0,
    "gn:timezone":"Asia/Krasnoyarsk",
    "iso:country":"RU",
    "name:eng_x_preferred":[
        "Novaya Il'inka"
    ],
    "name:nor_x_preferred":[
        "Nov.Ilinka"
    ],
    "name:rus_x_preferred":[
        "\u041d\u043e\u0432.\u0418\u043b\u044c\u0438\u043d\u043a\u0430"
    ],
    "name:rus_x_variant":[
        "\u041d\u043e\u0432\u0430\u044f \u0418\u043b\u044c\u0438\u043d\u043a\u0430"
    ],
    "name:und_x_variant":[
        "Novo-Il\u2019inskaya",
        "Novoil\u2019inka",
        "Novaya Il\u2019inka"
    ],
    "wof:name":"Novaya Il'inka",
    "wof:placetype":"locality"
},
  "geometry": {"coordinates":[90.7165,56.0754],"type":"Point"}
}