{
  "type": "Feature",
  "properties": {
    "gn:admin1_code":"90",
    "gn:asciiname":"Novozhilovo",
    "gn:country_code":"RU",
    "gn:dem":214,
    "gn:feature_class":"P",
    "gn:feature_code":"PPL",
    "gn:name":"Novozhilovo",
    "gn:population":0,
    "gn:timezone":"Asia/Yekaterinburg",
    "iso:country":"RU",
    "name:rus_x_preferred":[
        "\u041d\u043e\u0432\u043e\u0436\u0438\u043b\u043e\u0432\u043e"
    ],
    "name:und_x_variant":[
        "Novozhilova",
        "Novozhilovo",
        "\u041d\u043e\u0432\u043e\u0436\u0438\u043b\u043e\u0432\u043e"
    ],
    "wof:name":"Novozhilovo",
    "wof:placetype":"locality"
},
  "geometry": {"coordinates":[55.2559,59.7313],"type":"Point"}
}