{
  "type": "Feature",
  "properties": {
    "gn:admin1_code":"17",
    "gn:asciiname":"Mitagi",
    "gn:country_code":"RU",
    "gn:dem":646,
    "gn:feature_class":"P",
    "gn:feature_code":"PPL",
    "gn:name":"Mitagi",
    "gn:population":0,
    "gn:timezone":"Europe/Moscow",
    "iso:country":"RU",
    "name:eng_x_preferred":[
        "Mitagi"
    ],
    "name:nor_x_preferred":[
        "Mitagi"
    ],
    "name:rus_x_preferred":[
        "\u041c\u0438\u0442\u0430\u0433\u0438"
    ],
    "name:und_x_variant":[
        "\u041c\u0438\u0442\u0430\u0433\u0438",
        "Mitagi"
    ],
    "wof:name":"Mitagi",
    "wof:placetype":"locality"
},
  "geometry": {"coordinates":[48.19083,42.01736],"type":"Point"}
}