{
  "type": "Feature",
  "properties": {
    "gn:admin1_code":"20.0",
    "gn:asciiname":"Kharaygun",
    "gn:country_code":"RU",
    "gn:dem":556,
    "gn:feature_class":"P",
    "gn:feature_code":"PPL",
    "gn:name":"Kharaygun",
    "gn:population":0,
    "gn:timezone":"Asia/Irkutsk",
    "iso:country":"RU",
    "name:rus_x_preferred":[
        "\u0425\u0430\u0440\u0430\u0439\u0433\u0443\u043d"
    ],
    "wof:name":"Kharaygun",
    "wof:placetype":"locality"
},
  "geometry": {"coordinates":[102.224,54.0665],"type":"Point"}
}