{
  "type": "Feature",
  "properties": {
    "gn:admin1_code":"80.0",
    "gn:asciiname":"Gaintsy",
    "gn:country_code":"RU",
    "gn:dem":164,
    "gn:feature_class":"P",
    "gn:feature_code":"PPL",
    "gn:name":"Gaintsy",
    "gn:population":0,
    "gn:timezone":"Europe/Samara",
    "iso:country":"RU",
    "name:rus_x_preferred":[
        "\u0413\u0430\u0438\u043d\u0446\u044b"
    ],
    "wof:name":"Gaintsy",
    "wof:placetype":"locality"
},
  "geometry": {"coordinates":[52.2139,57.6933],"type":"Point"}
}