{
  "type": "Feature",
  "properties": {
    "gn:admin1_code":"76",
    "gn:asciiname":"Popovkino",
    "gn:country_code":"RU",
    "gn:dem":234,
    "gn:feature_class":"P",
    "gn:feature_code":"PPL",
    "gn:name":"Popovkino",
    "gn:population":0,
    "gn:timezone":"Europe/Moscow",
    "iso:country":"RU",
    "name:rus_x_preferred":[
        "\u041f\u043e\u043f\u043e\u0432\u043a\u0438\u043d\u043e"
    ],
    "wof:name":"Popovkino",
    "wof:placetype":"locality"
},
  "geometry": {"coordinates":[37.43655,54.37678],"type":"Point"}
}