{
  "type": "Feature",
  "properties": {
    "gn:admin1_code":"60",
    "gn:asciiname":"Bol'shoye Kortovo",
    "gn:country_code":"RU",
    "gn:dem":82,
    "gn:feature_class":"P",
    "gn:feature_code":"PPL",
    "gn:name":"Bol\u2019shoye Kortovo",
    "gn:population":0,
    "gn:timezone":"Europe/Moscow",
    "iso:country":"RU",
    "name:rus_x_preferred":[
        "\u0411\u043e\u043b\u044c\u0448\u043e\u0435 \u041a\u043e\u0440\u0442\u043e\u0432\u043e"
    ],
    "name:und_x_variant":[
        "Bol\u2019shoye Korotovo",
        "Bol\u2019shoye Kortovo"
    ],
    "wof:name":"Bol'shoye Kortovo",
    "wof:placetype":"locality"
},
  "geometry": {"coordinates":[28.5269,57.04734000000001],"type":"Point"}
}