{
  "type": "Feature",
  "properties": {
    "gn:country":"RU",
    "gn:fcode":"PPL",
    "gn:population":0,
    "iso:country":"RU",
    "name:nor_x_preferred":[
        "Belogorje"
    ],
    "name:rus_x_preferred":[
        "\u0411\u0435\u043b\u043e\u0433\u043e\u0440\u044c\u0435"
    ],
    "name:und_x_variant":[
        "Belogor\u2019ye"
    ],
    "qs:name":"Belogor'ye",
    "qs:name_adm0":"Russia",
    "qs:name_adm1":"Voronezh Oblast",
    "qs:photos_9k":1,
    "qs:photos_9r":1,
    "qs:photos_all":10,
    "qs:photos_sr":0,
    "qs:placetype":"Town",
    "qs:pop_sr":"0",
    "wof:name":"Belogor'ye",
    "wof:placetype":"locality",
    "wof:population":0
},
  "geometry": {"coordinates":[38.2225,51.7279],"type":"Point"}
}