{
  "type": "Feature",
  "properties": {
    "gn:admin1_code":"11",
    "gn:asciiname":"Khabarzhan",
    "gn:country_code":"RU",
    "gn:dem":473,
    "gn:feature_class":"P",
    "gn:feature_code":"PPL",
    "gn:name":"Khabarzhan",
    "gn:population":0,
    "gn:timezone":"Asia/Irkutsk",
    "iso:country":"RU",
    "name:rus_x_preferred":[
        "\u0425\u0430\u0431\u0430\u0440\u0436\u0430\u043d"
    ],
    "wof:name":"Khabarzhan",
    "wof:placetype":"locality"
},
  "geometry": {"coordinates":[110.03333000000001,53.71666999999999],"type":"Point"}
}