{
  "type": "Feature",
  "properties": {
    "gn:admin1_code":"10",
    "gn:asciiname":"Novaya Milech'",
    "gn:country_code":"RU",
    "gn:dem":176,
    "gn:feature_class":"P",
    "gn:feature_code":"PPL",
    "gn:name":"Novaya Milech\u2019",
    "gn:population":0,
    "gn:timezone":"Europe/Moscow",
    "iso:country":"RU",
    "name:rus_x_preferred":[
        "\u041d\u043e\u0432\u0430\u044f \u041c\u0438\u043b\u0435\u0447\u044c"
    ],
    "name:und_x_variant":[
        "Novaya Milech\u2019",
        "\u041d\u043e\u0432\u0430\u044f \u041c\u0438\u043b\u0435\u0447\u044c"
    ],
    "wof:name":"Novaya Milech'",
    "wof:placetype":"locality"
},
  "geometry": {"coordinates":[33.77093,52.89195],"type":"Point"}
}