{
  "type": "Feature",
  "properties": {
    "gn:admin1_code":"38",
    "gn:asciiname":"Pobeditel'",
    "gn:country_code":"RU",
    "gn:dem":36,
    "gn:feature_class":"P",
    "gn:feature_code":"PPL",
    "gn:name":"Pobeditel\u2019",
    "gn:population":0,
    "gn:timezone":"Europe/Moscow",
    "iso:country":"RU",
    "name:rus_x_preferred":[
        "\u041f\u043e\u0431\u0435\u0434\u0438\u0442\u0435\u043b\u044c"
    ],
    "name:und_x_variant":[
        "Pobeditel\u2019"
    ],
    "wof:name":"Pobeditel'",
    "wof:placetype":"locality"
},
  "geometry": {"coordinates":[39.0986,45.12382],"type":"Point"}
}