{
  "type": "Feature",
  "properties": {
    "gn:admin1_code":"52",
    "gn:asciiname":"Goluzino",
    "gn:country_code":"RU",
    "gn:dem":56,
    "gn:feature_class":"P",
    "gn:feature_code":"PPL",
    "gn:name":"Goluzino",
    "gn:population":0,
    "gn:timezone":"Europe/Moscow",
    "iso:country":"RU",
    "name:rus_x_preferred":[
        "\u0413\u043e\u043b\u0443\u0437\u0438\u043d\u043e"
    ],
    "wof:name":"Goluzino",
    "wof:placetype":"locality"
},
  "geometry": {"coordinates":[31.32541,57.59405],"type":"Point"}
}