{
  "type": "Feature",
  "properties": {
    "gn:admin1_code":"63",
    "gn:asciiname":"Nuoragane",
    "gn:country_code":"RU",
    "gn:dem":172,
    "gn:feature_class":"P",
    "gn:feature_code":"PPL",
    "gn:name":"Nuoragane",
    "gn:population":0,
    "gn:timezone":"Asia/Yakutsk",
    "iso:country":"RU",
    "name:che_x_preferred":[
        "\u041d\u0443\u043e\u0440\u0430\u0433\u0430\u043d\u0430"
    ],
    "name:eng_x_preferred":[
        "Nuoragane"
    ],
    "name:hye_x_preferred":[
        "\u0546\u0578\u0580\u0561\u0563\u0561\u0576\u0561"
    ],
    "name:nor_x_preferred":[
        "Nuoragana"
    ],
    "name:rus_x_preferred":[
        "\u041d\u0443\u043e\u0440\u0430\u0433\u0430\u043d\u0430"
    ],
    "name:rus_x_variant":[
        "\u041d\u0443\u043e\u0440\u0430\u0433\u0430\u043d\u0435"
    ],
    "name:sah_x_preferred":[
        "\u041d\u0443\u043e\u0440\u0430\u0495\u0430\u043d\u0430"
    ],
    "name:und_x_variant":[
        "Noragona",
        "Nuoragane",
        "\u041d\u0443\u043e\u0440\u0430\u0433\u0430\u043d\u0435"
    ],
    "wof:name":"Nuoragane",
    "wof:placetype":"locality"
},
  "geometry": {"coordinates":[131.07683,62.15344],"type":"Point"}
}