{
  "type": "Feature",
  "properties": {
    "gn:admin1_code":"52",
    "gn:asciiname":"Porozhki",
    "gn:country_code":"RU",
    "gn:dem":36,
    "gn:feature_class":"P",
    "gn:feature_code":"PPL",
    "gn:name":"Porozhki",
    "gn:population":0,
    "gn:timezone":"Europe/Moscow",
    "iso:country":"RU",
    "name:rus_x_preferred":[
        "\u041f\u043e\u0440\u043e\u0436\u043a\u0438"
    ],
    "name:und_x_variant":[
        "\u041f\u043e\u0440\u043e\u0436\u043a\u0438"
    ],
    "wof:name":"Porozhki",
    "wof:placetype":"locality"
},
  "geometry": {"coordinates":[30.02324,58.03838],"type":"Point"}
}