{
  "type": "Feature",
  "properties": {
    "gn:admin1_code":"77",
    "gn:asciiname":"Zaluch'ye",
    "gn:country_code":"RU",
    "gn:dem":209,
    "gn:feature_class":"P",
    "gn:feature_code":"PPL",
    "gn:name":"Zaluch\u2019ye",
    "gn:population":0,
    "gn:timezone":"Europe/Moscow",
    "iso:country":"RU",
    "wof:name":"Zaluch'ye",
    "wof:placetype":"locality"
},
  "geometry": {"coordinates":[33.14529,57.20101],"type":"Point"}
}