{
  "type": "Feature",
  "properties": {
    "gn:admin1_code":"55",
    "gn:asciiname":"Kochetovskiy",
    "gn:country_code":"RU",
    "gn:dem":144,
    "gn:feature_class":"P",
    "gn:feature_code":"PPL",
    "gn:name":"Kochetovskiy",
    "gn:population":0,
    "gn:timezone":"Asia/Yekaterinburg",
    "iso:country":"RU",
    "name:rus_x_preferred":[
        "\u041a\u043e\u0447\u0435\u0442\u043e\u0432\u0441\u043a\u0438\u0439"
    ],
    "wof:name":"Kochetovskiy",
    "wof:placetype":"locality"
},
  "geometry": {"coordinates":[51.98333,52.11667],"type":"Point"}
}