{
  "type": "Feature",
  "properties": {
    "gn:admin1_code":"33",
    "gn:asciiname":"Nizhnyaya Zotinskaya",
    "gn:country_code":"RU",
    "gn:dem":160,
    "gn:feature_class":"P",
    "gn:feature_code":"PPL",
    "gn:name":"Nizhnyaya Zotinskaya",
    "gn:population":0,
    "gn:timezone":"Europe/Kirov",
    "iso:country":"RU",
    "name:rus_x_preferred":[
        "\u041d\u0438\u0436\u043d\u044f\u044f \u0417\u043e\u0442\u0438\u043d\u0441\u043a\u0430\u044f"
    ],
    "name:und_x_variant":[
        "Nizhnezotinskaya",
        "Nizhnyaya Zotinskaya"
    ],
    "wof:name":"Nizhnyaya Zotinskaya",
    "wof:placetype":"locality"
},
  "geometry": {"coordinates":[48.31283,59.2422],"type":"Point"}
}