{
  "type": "Feature",
  "properties": {
    "gn:admin1_code":"88.0",
    "gn:asciiname":"Fedkovo",
    "gn:country_code":"RU",
    "gn:dem":127,
    "gn:feature_class":"P",
    "gn:feature_code":"PPL",
    "gn:name":"Fedkovo",
    "gn:population":0,
    "gn:timezone":"Europe/Moscow",
    "iso:country":"RU",
    "name:rus_x_preferred":[
        "\u0424\u0435\u0434\u043a\u043e\u0432\u043e"
    ],
    "name:und_x_variant":[
        "\u0424\u0435\u0434\u043a\u043e\u0432\u043e"
    ],
    "wof:name":"Fedkovo",
    "wof:placetype":"locality"
},
  "geometry": {"coordinates":[40.9556,58.32694],"type":"Point"}
}