{
  "type": "Feature",
  "properties": {
    "gn:admin1_code":"63",
    "gn:asciiname":"Argas",
    "gn:country_code":"RU",
    "gn:dem":59,
    "gn:feature_class":"P",
    "gn:feature_code":"PPL",
    "gn:name":"Argas",
    "gn:population":0,
    "gn:timezone":"Asia/Yakutsk",
    "iso:country":"RU",
    "name:ceb_x_preferred":[
        "Argas"
    ],
    "name:deu_x_preferred":[
        "Argas"
    ],
    "name:eng_x_preferred":[
        "Argas"
    ],
    "name:fas_x_preferred":[
        "\u0622\u0631\u06af\u0627\u0633"
    ],
    "name:fra_x_preferred":[
        "Argas"
    ],
    "name:ind_x_preferred":[
        "Caplak unggas"
    ],
    "name:nav_x_preferred":[
        "Naa\u02bcah\u00f3\u00f3hai biya\u02bc"
    ],
    "name:nor_x_preferred":[
        "Argas"
    ],
    "name:por_x_preferred":[
        "Argas"
    ],
    "name:rus_x_preferred":[
        "\u0410\u0440\u0433\u0430\u0441"
    ],
    "name:swe_x_preferred":[
        "Argas"
    ],
    "name:tur_x_preferred":[
        "Argas"
    ],
    "name:war_x_preferred":[
        "Argas"
    ],
    "wof:name":"Argas",
    "wof:placetype":"locality"
},
  "geometry": {"coordinates":[126.61991,63.96366999999999],"type":"Point"}
}