{
  "type": "Feature",
  "properties": {
    "gn:admin1_code":"63",
    "gn:asciiname":"Argas",
    "gn:country_code":"RU",
    "gn:dem":59,
    "gn:feature_class":"P",
    "gn:feature_code":"PPL",
    "gn:name":"Argas",
    "gn:population":0,
    "gn:timezone":"Asia/Yakutsk",
    "iso:country":"RU",
    "name:eng_x_preferred":[
        "Argas"
    ],
    "name:nor_x_preferred":[
        "Argas"
    ],
    "name:rus_x_preferred":[
        "\u0410\u0440\u0433\u0430\u0441"
    ],
    "name:und_x_variant":[
        "\u0410\u0440\u0433\u0430\u0441",
        "Argas"
    ],
    "wof:name":"Argas",
    "wof:placetype":"locality"
},
  "geometry": {"coordinates":[126.61991,63.96366999999999],"type":"Point"}
}