{
  "type": "Feature",
  "properties": {
    "gn:admin1_code":"6.0",
    "gn:asciiname":"Kutozerskaya",
    "gn:country_code":"RU",
    "gn:dem":13,
    "gn:feature_class":"P",
    "gn:feature_code":"PPL",
    "gn:name":"Kutoz\u00ebrskaya",
    "gn:population":0,
    "gn:timezone":"Europe/Moscow",
    "iso:country":"RU",
    "name:rus_x_preferred":[
        "\u041a\u0443\u0442\u043e\u0437\u0451\u0440\u0441\u043a\u0430\u044f"
    ],
    "name:und_x_variant":[
        "Kutoz\u00ebrskaya"
    ],
    "wof:name":"Kutozerskaya",
    "wof:placetype":"locality"
},
  "geometry": {"coordinates":[41.7124,64.1729],"type":"Point"}
}