{
  "type": "Feature",
  "properties": {
    "gn:admin1_code":"56",
    "gn:asciiname":"Derevnya",
    "gn:country_code":"RU",
    "gn:dem":214,
    "gn:feature_class":"P",
    "gn:feature_code":"PPL",
    "gn:name":"Derevnya",
    "gn:population":0,
    "gn:timezone":"Europe/Moscow",
    "iso:country":"RU",
    "name:rus_x_preferred":[
        "\u0414\u0435\u0440\u0435\u0432\u043d\u044f"
    ],
    "wof:name":"Derevnya",
    "wof:placetype":"locality"
},
  "geometry": {"coordinates":[37.24222,52.92528000000001],"type":"Point"}
}