{
  "type": "Feature",
  "properties": {
    "gn:admin1_code":"60",
    "gn:asciiname":"Lamovy Gorki",
    "gn:country_code":"RU",
    "gn:dem":78,
    "gn:feature_class":"P",
    "gn:feature_code":"PPL",
    "gn:name":"Lamovy Gorki",
    "gn:population":0,
    "gn:timezone":"Europe/Moscow",
    "iso:country":"RU",
    "name:rus_x_preferred":[
        "\u041b\u0430\u043c\u043e\u0432\u044b \u0413\u043e\u0440\u043a\u0438"
    ],
    "wof:name":"Lamovy Gorki",
    "wof:placetype":"locality"
},
  "geometry": {"coordinates":[30.347,57.5342],"type":"Point"}
}