{
  "type": "Feature",
  "properties": {
    "gn:admin1_code":"42",
    "gn:asciiname":"Staroye Gorkolovo",
    "gn:country_code":"RU",
    "gn:dem":17,
    "gn:feature_class":"P",
    "gn:feature_code":"PPL",
    "gn:name":"Staroye Gorkolovo",
    "gn:population":0,
    "gn:timezone":"Europe/Moscow",
    "iso:country":"RU",
    "name:eng_x_preferred":[
        "Staroye Gorkolovo"
    ],
    "name:fin_x_preferred":[
        "Harkkola"
    ],
    "name:nor_x_preferred":[
        "Star.Gorkolovo"
    ],
    "name:rus_x_preferred":[
        "\u0421\u0442\u0430\u0440.\u0413\u043e\u0440\u043a\u043e\u043b\u043e\u0432\u043e"
    ],
    "name:rus_x_variant":[
        "\u0421\u0442\u0430\u0440\u043e\u0435 \u0413\u043e\u0440\u043a\u043e\u043b\u043e\u0432\u043e"
    ],
    "name:und_x_variant":[
        "\u0421\u0442\u0430\u0440\u043e\u0435 \u0413\u043e\u0440\u043a\u043e\u043b\u043e\u0432\u043e"
    ],
    "wof:name":"Staroye Gorkolovo",
    "wof:placetype":"locality"
},
  "geometry": {"coordinates":[28.66800000000001,59.79733],"type":"Point"}
}