{
  "type": "Feature",
  "properties": {
    "gn:admin1_code":"05",
    "gn:asciiname":"Kurort Ignashino",
    "gn:country_code":"RU",
    "gn:dem":347,
    "gn:feature_class":"P",
    "gn:feature_code":"PPL",
    "gn:name":"Kurort Ignashino",
    "gn:population":0,
    "gn:timezone":"Asia/Yakutsk",
    "iso:country":"RU",
    "name:eng_x_preferred":[
        "Kurort Ignashino"
    ],
    "name:rus_x_preferred":[
        "\u0418\u0433\u043d\u0430\u0448\u0438\u043d\u043e"
    ],
    "name:rus_x_variant":[
        "\u0418\u0433\u043d\u0430\u0448\u0438\u043d\u043a\u0430",
        "\u041a\u0443\u0440\u043e\u0440\u0442 \u0418\u0433\u043d\u0430\u0448\u0438\u043d\u043e"
    ],
    "name:und_x_variant":[
        "Ignashino"
    ],
    "wof:name":"Kurort Ignashino",
    "wof:placetype":"locality"
},
  "geometry": {"coordinates":[122.44313,53.53043],"type":"Point"}
}