{
  "type": "Feature",
  "properties": {
    "gn:admin1_code":"17",
    "gn:asciiname":"Novokuli",
    "gn:country_code":"RU",
    "gn:dem":313,
    "gn:feature_class":"P",
    "gn:feature_code":"PPL",
    "gn:name":"Novokuli",
    "gn:population":0,
    "gn:timezone":"Europe/Moscow",
    "iso:country":"RU",
    "name:eng_x_preferred":[
        "Novokuli"
    ],
    "name:nor_x_preferred":[
        "Novokuli"
    ],
    "name:rus_x_preferred":[
        "\u041d\u043e\u0432\u043e\u043a\u0443\u043b\u0438"
    ],
    "name:und_x_variant":[
        "Yaryksu-Aukh"
    ],
    "wof:name":"Novokuli",
    "wof:placetype":"locality"
},
  "geometry": {"coordinates":[46.5195,43.1664],"type":"Point"}
}