{
  "type": "Feature",
  "properties": {
    "gn:admin1_code":"59",
    "gn:asciiname":"Krasnyy Pereval",
    "gn:cc2":"RU",
    "gn:country_code":"RU",
    "gn:dem":68,
    "gn:feature_class":"P",
    "gn:feature_code":"PPL",
    "gn:name":"Krasnyy Pereval",
    "gn:population":0,
    "gn:timezone":"Asia/Vladivostok",
    "iso:country":"RU",
    "name:rus_x_preferred":[
        "\u041a\u0440\u0430\u0441\u043d\u044b\u0439 \u041f\u0435\u0440\u0435\u0432\u0430\u043b"
    ],
    "name:und_x_variant":[
        "Nizhniy Krasnyy Pereval",
        "Krasnyy Pereval",
        "\u041a\u0440\u0430\u0441\u043d\u044b\u0439 \u041f\u0435\u0440\u0435\u0432\u0430\u043b"
    ],
    "wof:name":"Krasnyy Pereval",
    "wof:placetype":"locality"
},
  "geometry": {"coordinates":[134.56666999999999,46.55],"type":"Point"}
}