{
  "type": "Feature",
  "properties": {
    "gn:admin1_code":"72",
    "gn:asciiname":"Lipitskiy",
    "gn:country_code":"RU",
    "gn:dem":201,
    "gn:feature_class":"P",
    "gn:feature_code":"PPL",
    "gn:name":"Lipitskiy",
    "gn:population":0,
    "gn:timezone":"Europe/Moscow",
    "iso:country":"RU",
    "name:rus_x_preferred":[
        "\u041b\u0438\u043f\u0438\u0442\u0441\u043a\u0438\u0439"
    ],
    "name:und_x_variant":[
        "Lipovets",
        "Lipitskiy",
        "\u041b\u0438\u043f\u0438\u0442\u0441\u043a\u0438\u0439"
    ],
    "wof:name":"Lipitskiy",
    "wof:placetype":"locality"
},
  "geometry": {"coordinates":[42.35241,52.67712],"type":"Point"}
}