{
  "type": "Feature",
  "properties": {
    "gn:admin1_code":"59",
    "gn:asciiname":"Molodezhnoye",
    "gn:country_code":"RU",
    "gn:dem":787,
    "gn:feature_class":"P",
    "gn:feature_code":"PPL",
    "gn:name":"Molod\u00ebzhnoye",
    "gn:population":0,
    "gn:timezone":"Asia/Vladivostok",
    "iso:country":"RU",
    "name:eng_x_preferred":[
        "Molod\u00ebzhnoye"
    ],
    "name:nor_x_preferred":[
        "Molodezjnoje"
    ],
    "name:rus_x_preferred":[
        "\u041c\u043e\u043b\u043e\u0434\u0435\u0436\u043d\u043e\u0435"
    ],
    "name:rus_x_variant":[
        "\u041c\u043e\u043b\u043e\u0434\u0451\u0436\u043d\u043e\u0435"
    ],
    "wof:name":"Molodezhnoye",
    "wof:placetype":"locality"
},
  "geometry": {"coordinates":[136.48382000000001,45.95842],"type":"Point"}
}