{
  "type": "Feature",
  "properties": {
    "gn:country":"RU",
    "gn:fcode":"PPL",
    "gn:population":10616,
    "iso:country":"RU",
    "name:azb_x_preferred":[
        "\u0627\u0648\u0628\u0648\u062e\u0648\u0648\u0648"
    ],
    "name:bel_x_preferred":[
        "\u041f\u0430\u0441\u0451\u043b\u0430\u043a \u0433\u0430\u0440\u0430\u0434\u0441\u043a\u043e\u0433\u0430 \u0442\u044b\u043f\u0443 \u0410\u0431\u0443\u0445\u0430\u0432\u0430"
    ],
    "name:ceb_x_preferred":[
        "Obukhovo"
    ],
    "name:che_x_preferred":[
        "\u041e\u0431\u0443\u0445\u043e\u0432\u043e"
    ],
    "name:deu_x_preferred":[
        "Obuchowo"
    ],
    "name:eng_x_preferred":[
        "Obukhovo"
    ],
    "name:hye_x_preferred":[
        "\u0555\u0562\u0578\u0582\u056d\u0578\u057e\u0578"
    ],
    "name:ita_x_preferred":[
        "Obuchovo"
    ],
    "name:nld_x_preferred":[
        "Oboechovo"
    ],
    "name:pol_x_preferred":[
        "Obuchowo"
    ],
    "name:rus_x_preferred":[
        "\u041e\u0431\u0443\u0445\u043e\u0432\u043e"
    ],
    "name:swe_x_preferred":[
        "Obuchovo"
    ],
    "name:ukr_x_preferred":[
        "\u041e\u0431\u0443\u0445\u043e\u0432\u0435"
    ],
    "name:zho_x_preferred":[
        "\u5965\u5e03\u970d\u6c83"
    ],
    "qs:name":"Obukhovo",
    "qs:photos_9r":0,
    "qs:photos_sr":0,
    "qs:pop_sr":"6",
    "wd:wordcount":898,
    "wof:name":"Obukhovo",
    "wof:placetype":"locality",
    "wof:population":10616
},
  "geometry": {"coordinates":[38.2725,55.83278],"type":"Point"}
}