{
  "type": "Feature",
  "properties": {
    "gn:admin1_code":"77",
    "gn:asciiname":"Setki",
    "gn:country_code":"RU",
    "gn:dem":266,
    "gn:feature_class":"P",
    "gn:feature_code":"PPL",
    "gn:name":"Setki",
    "gn:population":0,
    "gn:timezone":"Europe/Moscow",
    "iso:country":"RU",
    "name:rus_x_preferred":[
        "\u0421\u0435\u0442\u043a\u0438"
    ],
    "wof:name":"Setki",
    "wof:placetype":"locality"
},
  "geometry": {"coordinates":[34.46455,56.68898000000001],"type":"Point"}
}