{
  "type": "Feature",
  "properties": {
    "gn:admin1_code":"87",
    "gn:asciiname":"Shuga",
    "gn:cc2":"RU",
    "gn:country_code":"RU",
    "gn:dem":-9999,
    "gn:feature_class":"P",
    "gn:feature_code":"PPL",
    "gn:name":"Shuga",
    "gn:population":0,
    "gn:timezone":"Asia/Yekaterinburg",
    "iso:country":"RU",
    "name:ceb_x_preferred":[
        "Shuga"
    ],
    "name:eng_x_preferred":[
        "Shuga"
    ],
    "name:nor_x_preferred":[
        "Sjuga"
    ],
    "name:rus_x_preferred":[
        "\u0428\u0443\u0433\u0430"
    ],
    "name:swe_x_preferred":[
        "Shuga"
    ],
    "name:und_x_variant":[
        "Zimov\u2019ya Shuga",
        "Sukhuy",
        "\u0428\u0443\u0433\u0430",
        "Shuga"
    ],
    "wof:name":"Shuga",
    "wof:placetype":"locality"
},
  "geometry": {"coordinates":[71.56667,66.31667],"type":"Point"}
}