{
  "type": "Feature",
  "properties": {
    "gn:admin1_code":"83.0",
    "gn:asciiname":"Dvoyezery",
    "gn:country_code":"RU",
    "gn:dem":143,
    "gn:feature_class":"P",
    "gn:feature_code":"PPL",
    "gn:name":"Dvoyez\u00ebry",
    "gn:population":0,
    "gn:timezone":"Europe/Moscow",
    "iso:country":"RU",
    "name:eng_x_preferred":[
        "Dvoyez\u00ebry"
    ],
    "name:nor_x_preferred":[
        "Dvojezery"
    ],
    "name:rus_x_preferred":[
        "\u0414\u0432\u043e\u0435\u0437\u0435\u0440\u044b"
    ],
    "name:rus_x_variant":[
        "\u0414\u0432\u043e\u0435\u0437\u0451\u0440\u044b"
    ],
    "wof:name":"Dvoyezery",
    "wof:placetype":"locality"
},
  "geometry": {"coordinates":[41.37404,55.20627],"type":"Point"}
}