{
  "type": "Feature",
  "properties": {
    "gn:admin1_code":"70",
    "gn:asciiname":"Magodynka",
    "gn:country_code":"RU",
    "gn:dem":83,
    "gn:feature_class":"P",
    "gn:feature_code":"PPL",
    "gn:name":"Magodynka",
    "gn:population":0,
    "gn:timezone":"Europe/Moscow",
    "iso:country":"RU",
    "name:rus_x_preferred":[
        "\u041c\u0430\u0433\u043e\u0434\u044b\u043d\u043a\u0430"
    ],
    "wof:name":"Magodynka",
    "wof:placetype":"locality"
},
  "geometry": {"coordinates":[42.32194000000001,45.84361],"type":"Point"}
}