{
  "type": "Feature",
  "properties": {
    "gn:admin1_code":"8",
    "gn:asciiname":"Aytugan",
    "gn:country_code":"RU",
    "gn:dem":141,
    "gn:feature_class":"P",
    "gn:feature_code":"PPL",
    "gn:name":"Aytugan",
    "gn:population":0,
    "gn:timezone":"Asia/Yekaterinburg",
    "iso:country":"RU",
    "name:rus_x_preferred":[
        "\u0410\u0439\u0442\u0443\u0433\u0430\u043d"
    ],
    "wof:name":"Aytugan",
    "wof:placetype":"locality"
},
  "geometry": {"coordinates":[54.6323,53.7745],"type":"Point"}
}