{
  "type": "Feature",
  "properties": {
    "gn:admin1_code":"8",
    "gn:asciiname":"Aytugan",
    "gn:country_code":"RU",
    "gn:dem":141,
    "gn:feature_class":"P",
    "gn:feature_code":"PPL",
    "gn:name":"Aytugan",
    "gn:population":0,
    "gn:timezone":"Asia/Yekaterinburg",
    "iso:country":"RU",
    "name:bak_x_preferred":[
        "\u0410\u0439\u0442\u0443\u0493\u0430\u043d"
    ],
    "name:che_x_preferred":[
        "\u0410\u0439\u0442\u0443\u0433\u0430\u043d"
    ],
    "name:hye_x_preferred":[
        "\u0531\u0575\u057f\u0578\u0582\u0563\u0561\u0576"
    ],
    "name:kat_x_preferred":[
        "\u10d0\u10d8\u10e2\u10e3\u10d2\u10d0\u10dc\u10d8"
    ],
    "name:kaz_x_preferred":[
        "\u0410\u0439\u0442\u0443\u0433\u0430\u043d"
    ],
    "name:kir_x_preferred":[
        "\u0410\u0439\u0442\u0443\u0433\u0430\u043d"
    ],
    "name:rus_x_preferred":[
        "\u0410\u0439\u0442\u0443\u0433\u0430\u043d"
    ],
    "name:tat_x_preferred":[
        "\u0410\u0439\u0442\u0443\u0433\u0430\u043d"
    ],
    "name:ukr_x_preferred":[
        "\u0410\u0439\u0442\u0443\u0433\u0430\u043d"
    ],
    "wof:name":"Aytugan",
    "wof:placetype":"locality"
},
  "geometry": {"coordinates":[54.6323,53.7745],"type":"Point"}
}