{
  "type": "Feature",
  "properties": {
    "gn:admin1_code":"73",
    "gn:asciiname":"Saltyganovo",
    "gn:country_code":"RU",
    "gn:dem":76,
    "gn:feature_class":"P",
    "gn:feature_code":"PPL",
    "gn:name":"Saltyganovo",
    "gn:population":0,
    "gn:timezone":"Europe/Moscow",
    "iso:country":"RU",
    "name:rus_x_preferred":[
        "\u0421\u0430\u043b\u0442\u044b\u0433\u0430\u043d\u043e\u0432\u043e"
    ],
    "wof:name":"Saltyganovo",
    "wof:placetype":"locality"
},
  "geometry": {"coordinates":[49.1387,55.1758],"type":"Point"}
}