{
  "type": "Feature",
  "properties": {
    "gn:admin1_code":"12",
    "gn:asciiname":"Khakkoy",
    "gn:country_code":"RU",
    "gn:dem":634,
    "gn:feature_class":"P",
    "gn:feature_code":"PPL",
    "gn:name":"Khakkoy",
    "gn:population":0,
    "gn:timezone":"Europe/Moscow",
    "iso:country":"RU",
    "name:che_x_preferred":[
        "\u010aogunie"
    ],
    "name:che_x_variant":[
        "Cogunoy",
        "\u1e8aakka",
        "\u0425\u044c\u0430\u043a\u043a\u0430",
        "\u0426\u0406\u043e\u0433\u0443\u043d\u0435",
        "\u0426\u043e\u0433\u0443\u043d\u043e\u0439"
    ],
    "name:rus_x_preferred":[
        "\u0425\u0430\u043a\u043a\u043e\u0439"
    ],
    "name:und_x_variant":[
        "Tsogunoy",
        "Khakkoy",
        "Hakkoj"
    ],
    "wof:name":"Khakkoy",
    "wof:placetype":"locality"
},
  "geometry": {"coordinates":[45.67835,42.87961],"type":"Point"}
}