{
  "type": "Feature",
  "properties": {
    "gn:admin1_code":"29",
    "gn:asciiname":"Chindatskiy",
    "gn:country_code":"RU",
    "gn:dem":229,
    "gn:feature_class":"P",
    "gn:feature_code":"PPL",
    "gn:name":"Chindatskiy",
    "gn:population":0,
    "gn:timezone":"Asia/Novokuznetsk",
    "iso:country":"RU",
    "name:rus_x_preferred":[
        "\u0427\u0438\u043d\u0434\u0430\u0442\u0441\u043a\u0438\u0439"
    ],
    "wof:name":"Chindatskiy",
    "wof:placetype":"locality"
},
  "geometry": {"coordinates":[86.18189,56.12967],"type":"Point"}
}