{
  "type": "Feature",
  "properties": {
    "gn:admin1_code":"33.0",
    "gn:asciiname":"Chuvashi",
    "gn:country_code":"RU",
    "gn:dem":175,
    "gn:feature_class":"P",
    "gn:feature_code":"PPL",
    "gn:name":"Chuvashi",
    "gn:population":0,
    "gn:timezone":"Europe/Kirov",
    "iso:country":"RU",
    "name:eng_x_preferred":[
        "Chuvashi"
    ],
    "name:nor_x_preferred":[
        "Tsjuvasji"
    ],
    "name:rus_x_preferred":[
        "\u0427\u0443\u0432\u0430\u0448\u0438"
    ],
    "wof:name":"Chuvashi",
    "wof:placetype":"locality"
},
  "geometry": {"coordinates":[51.1918,57.5232],"type":"Point"}
}