{
  "type": "Feature",
  "properties": {
    "gn:admin1_code":"65",
    "gn:asciiname":"Prize",
    "gn:country_code":"RU",
    "gn:dem":36,
    "gn:feature_class":"P",
    "gn:feature_code":"PPL",
    "gn:name":"Prize",
    "gn:population":0,
    "gn:timezone":"Europe/Samara",
    "iso:country":"RU",
    "name:rus_x_preferred":[
        "\u041f\u0440\u0438\u0437\u0435"
    ],
    "name:und_x_variant":[
        "\u041f\u0440\u0438\u0437\u0435"
    ],
    "wof:name":"Prize",
    "wof:placetype":"locality"
},
  "geometry": {"coordinates":[51.06957,53.31893],"type":"Point"}
}