{
  "type": "Feature",
  "properties": {
    "gn:admin1_code":"65",
    "gn:asciiname":"Prize",
    "gn:country_code":"RU",
    "gn:dem":36,
    "gn:feature_class":"P",
    "gn:feature_code":"PPL",
    "gn:name":"Prize",
    "gn:population":0,
    "gn:timezone":"Europe/Samara",
    "iso:country":"RU",
    "name:ara_x_preferred":[
        "\u062c\u0627\u0626\u0632\u0629"
    ],
    "name:cat_x_preferred":[
        "Premi"
    ],
    "name:dan_x_preferred":[
        "Pr\u00e6mie"
    ],
    "name:deu_x_preferred":[
        "Preis"
    ],
    "name:ell_x_preferred":[
        "\u0392\u03c1\u03b1\u03b2\u03b5\u03af\u03bf"
    ],
    "name:epo_x_preferred":[
        "Premio"
    ],
    "name:est_x_preferred":[
        "Auhind"
    ],
    "name:fas_x_preferred":[
        "\u062c\u0627\u06cc\u0632\u0647"
    ],
    "name:fry_x_preferred":[
        "Priis"
    ],
    "name:glg_x_preferred":[
        "Premio"
    ],
    "name:hat_x_preferred":[
        "Prim"
    ],
    "name:hye_x_preferred":[
        "\u0544\u0580\u0581\u0561\u0576\u0561\u056f"
    ],
    "name:ita_x_preferred":[
        "Premio"
    ],
    "name:kan_x_preferred":[
        "\u0caa\u0cbe\u0cb0\u0cbf\u0ca4\u0ccb\u0cb7\u0c95"
    ],
    "name:kor_x_preferred":[
        "\uc0c1"
    ],
    "name:nld_x_preferred":[
        "Prijs"
    ],
    "name:nor_x_preferred":[
        "Pris"
    ],
    "name:pan_x_preferred":[
        "\u0a07\u0a28\u0a3e\u0a2e"
    ],
    "name:pol_x_preferred":[
        "Nagroda"
    ],
    "name:rus_x_preferred":[
        "\u041f\u0440\u0438\u0437\u0435"
    ],
    "name:spa_x_preferred":[
        "Premio"
    ],
    "name:swe_x_preferred":[
        "Utm\u00e4rkelse"
    ],
    "name:tel_x_preferred":[
        "\u0c2c\u0c39\u0c41\u0c2e\u0c24\u0c3f"
    ],
    "wof:name":"Prize",
    "wof:placetype":"locality"
},
  "geometry": {"coordinates":[51.06957,53.31893],"type":"Point"}
}