{
  "type": "Feature",
  "properties": {
    "gn:admin1_code":"51",
    "gn:asciiname":"Trekh-Ozery",
    "gn:country_code":"RU",
    "gn:dem":140,
    "gn:feature_class":"P",
    "gn:feature_code":"PPL",
    "gn:name":"Tr\u00ebkh-Oz\u00ebry",
    "gn:population":0,
    "gn:timezone":"Europe/Moscow",
    "iso:country":"RU",
    "name:und_x_variant":[
        "Trekh\u2019ozer\u2019ye",
        "Tr\u00ebkh-Oz\u00ebry"
    ],
    "wof:name":"Trekh-Ozery",
    "wof:placetype":"locality"
},
  "geometry": {"coordinates":[45.5094,55.4121],"type":"Point"}
}