{
  "type": "Feature",
  "properties": {
    "gn:admin1_code":"8",
    "gn:asciiname":"Kanbekovo",
    "gn:country_code":"RU",
    "gn:dem":153,
    "gn:feature_class":"P",
    "gn:feature_code":"PPL",
    "gn:name":"Kanbekovo",
    "gn:population":0,
    "gn:timezone":"Asia/Yekaterinburg",
    "iso:country":"RU",
    "name:rus_x_preferred":[
        "\u041a\u0430\u043d\u0431\u0435\u043a\u043e\u0432\u043e"
    ],
    "name:und_x_variant":[
        "Konybekova",
        "Kanbekovo"
    ],
    "wof:name":"Kanbekovo",
    "wof:placetype":"locality"
},
  "geometry": {"coordinates":[54.5713,53.6596],"type":"Point"}
}