{
  "type": "Feature",
  "properties": {
    "gn:admin1_code":"80.0",
    "gn:asciiname":"Chemashur",
    "gn:cc2":"RU",
    "gn:country_code":"RU",
    "gn:dem":141,
    "gn:feature_class":"P",
    "gn:feature_code":"PPL",
    "gn:name":"Chemashur",
    "gn:population":0,
    "gn:timezone":"Europe/Moscow",
    "iso:country":"RU",
    "name:rus_x_preferred":[
        "\u0427\u0435\u043c\u0430\u0448\u0443\u0440"
    ],
    "name:und_x_variant":[
        "Chermashur",
        "Chemashur"
    ],
    "wof:name":"Chemashur",
    "wof:placetype":"locality"
},
  "geometry": {"coordinates":[53.35,56.11666999999999],"type":"Point"}
}