{
  "type": "Feature",
  "properties": {
    "gn:admin1_code":"33",
    "gn:asciiname":"Novoselovy",
    "gn:country_code":"RU",
    "gn:dem":191,
    "gn:feature_class":"P",
    "gn:feature_code":"PPL",
    "gn:name":"Novos\u00eblovy",
    "gn:population":0,
    "gn:timezone":"Europe/Kirov",
    "iso:country":"RU",
    "name:rus_x_preferred":[
        "\u041d\u043e\u0432\u043e\u0441\u0451\u043b\u043e\u0432\u044b"
    ],
    "name:und_x_variant":[
        "Novos\u00eblovy"
    ],
    "wof:name":"Novoselovy",
    "wof:placetype":"locality"
},
  "geometry": {"coordinates":[48.46057,59.37327],"type":"Point"}
}