{
  "type": "Feature",
  "properties": {
    "gn:admin1_code":"85",
    "gn:asciiname":"Malaya Stupolokhta",
    "gn:country_code":"RU",
    "gn:dem":128,
    "gn:feature_class":"P",
    "gn:feature_code":"PPL",
    "gn:name":"Malaya Stupolokhta",
    "gn:population":0,
    "gn:timezone":"Europe/Moscow",
    "iso:country":"RU",
    "name:rus_x_preferred":[
        "\u041c\u0430\u043b\u0430\u044f \u0421\u0442\u0443\u043f\u043e\u043b\u043e\u0445\u0442\u0430"
    ],
    "name:und_x_variant":[
        "\u041c\u0430\u043b\u0430\u044f \u0421\u0442\u0443\u043f\u043e\u043b\u043e\u0445\u0442\u0430"
    ],
    "wof:name":"Malaya Stupolokhta",
    "wof:placetype":"locality"
},
  "geometry": {"coordinates":[36.989,59.5267],"type":"Point"}
}