{
  "type": "Feature",
  "properties": {
    "gn:admin1_code":"32",
    "gn:asciiname":"Polovinka",
    "gn:country_code":"RU",
    "gn:dem":43,
    "gn:feature_class":"P",
    "gn:feature_code":"PPL",
    "gn:name":"Polovinka",
    "gn:population":0,
    "gn:timezone":"Asia/Yekaterinburg",
    "iso:country":"RU",
    "name:rus_x_preferred":[
        "\u041f\u043e\u043b\u043e\u0432\u0438\u043d\u043a\u0430"
    ],
    "wof:name":"Polovinka",
    "wof:placetype":"locality"
},
  "geometry": {"coordinates":[66.09999999999999,60.03333000000001],"type":"Point"}
}