{
  "type": "Feature",
  "properties": {
    "gn:admin1_code":"62.0",
    "gn:asciiname":"Dobraya Nadezhda",
    "gn:country_code":"RU",
    "gn:dem":149,
    "gn:feature_class":"P",
    "gn:feature_code":"PPL",
    "gn:name":"Dobraya Nadezhda",
    "gn:population":0,
    "gn:timezone":"Europe/Moscow",
    "iso:country":"RU",
    "name:rus_x_preferred":[
        "\u0414\u043e\u0431\u0440\u0430\u044f \u041d\u0430\u0434\u0435\u0436\u0434\u0430"
    ],
    "wof:name":"Dobraya Nadezhda",
    "wof:placetype":"locality"
},
  "geometry": {"coordinates":[40.2226,53.4388],"type":"Point"}
}