{
  "type": "Feature",
  "properties": {
    "gn:admin1_code":"29",
    "gn:asciiname":"Gavan'",
    "gn:country_code":"RU",
    "gn:dem":242,
    "gn:feature_class":"P",
    "gn:feature_code":"PPL",
    "gn:name":"Gavan\u2019",
    "gn:population":0,
    "gn:timezone":"Asia/Novokuznetsk",
    "iso:country":"RU",
    "name:rus_x_preferred":[
        "\u0413\u0430\u0432\u0430\u043d\u044c"
    ],
    "name:und_x_variant":[
        "Gavan\u2019",
        "\u0413\u0430\u0432\u0430\u043d\u044c"
    ],
    "wof:name":"Gavan'",
    "wof:placetype":"locality"
},
  "geometry": {"coordinates":[87.273,53.402],"type":"Point"}
}