{
  "type": "Feature",
  "properties": {
    "gn:admin1_code":"38",
    "gn:asciiname":"Ternovyy",
    "gn:cc2":"RU",
    "gn:country_code":"RU",
    "gn:dem":76,
    "gn:feature_class":"P",
    "gn:feature_code":"PPL",
    "gn:name":"Ternovyy",
    "gn:population":0,
    "gn:timezone":"Europe/Moscow",
    "iso:country":"RU",
    "name:rus_x_preferred":[
        "\u0422\u0435\u0440\u043d\u043e\u0432\u044b\u0439"
    ],
    "name:und_x_variant":[
        "Ternovy",
        "Ternovyy"
    ],
    "wof:name":"Ternovyy",
    "wof:placetype":"locality"
},
  "geometry": {"coordinates":[40.02028,45.46056],"type":"Point"}
}