{
  "type": "Feature",
  "properties": {
    "gn:admin1_code":"88",
    "gn:asciiname":"Khlamovskoye",
    "gn:country_code":"RU",
    "gn:dem":164,
    "gn:feature_class":"P",
    "gn:feature_code":"PPL",
    "gn:name":"Khlamovskoye",
    "gn:population":0,
    "gn:timezone":"Europe/Moscow",
    "iso:country":"RU",
    "name:rus_x_preferred":[
        "\u0425\u043b\u0430\u043c\u043e\u0432\u0441\u043a\u043e\u0435"
    ],
    "wof:name":"Khlamovskoye",
    "wof:placetype":"locality"
},
  "geometry": {"coordinates":[39.49171,57.49502],"type":"Point"}
}