{
  "type": "Feature",
  "properties": {
    "gn:admin1_code":"21",
    "gn:asciiname":"Izotino",
    "gn:country_code":"RU",
    "gn:dem":90,
    "gn:feature_class":"P",
    "gn:feature_code":"PPL",
    "gn:name":"Izotino",
    "gn:population":0,
    "gn:timezone":"Europe/Moscow",
    "iso:country":"RU",
    "name:eng_x_preferred":[
        "Izotino"
    ],
    "name:nor_x_preferred":[
        "Izotino"
    ],
    "name:rus_x_preferred":[
        "\u0418\u0437\u043e\u0442\u0438\u043d\u043e"
    ],
    "wof:name":"Izotino",
    "wof:placetype":"locality"
},
  "geometry": {"coordinates":[41.69758,56.5495],"type":"Point"}
}