{
  "type": "Feature",
  "properties": {
    "gn:admin1_code":"91",
    "gn:asciiname":"Ordzhonikidze",
    "gn:cc2":"RU",
    "gn:country_code":"RU",
    "gn:dem":176,
    "gn:feature_class":"P",
    "gn:feature_code":"PPL",
    "gn:name":"Ordzhonikidze",
    "gn:population":0,
    "gn:timezone":"Asia/Krasnoyarsk",
    "iso:country":"RU",
    "name:eng_x_preferred":[
        "Ordzhonikidze"
    ],
    "name:nor_x_preferred":[
        "Ordzjonikidze"
    ],
    "name:rus_x_preferred":[
        "\u041e\u0440\u0434\u0436\u043e\u043d\u0438\u043a\u0438\u0434\u0437\u0435"
    ],
    "name:und_x_variant":[
        "Potoskuy",
        "Ordzhonikidze"
    ],
    "wof:name":"Ordzhonikidze",
    "wof:placetype":"locality"
},
  "geometry": {"coordinates":[95.45944,58.45833],"type":"Point"}
}