{
  "type": "Feature",
  "properties": {
    "gn:admin1_code":"69.0",
    "gn:asciiname":"Boltutino",
    "gn:country_code":"RU",
    "gn:dem":225,
    "gn:feature_class":"P",
    "gn:feature_code":"PPL",
    "gn:name":"Boltutino",
    "gn:population":0,
    "gn:timezone":"Europe/Moscow",
    "iso:country":"RU",
    "name:eng_x_preferred":[
        "Baltutino"
    ],
    "name:rus_x_preferred":[
        "\u0411\u043e\u043b\u0442\u0443\u0440\u0438\u043d\u043e"
    ],
    "name:rus_x_variant":[
        "\u0411\u043e\u043b\u0442\u0443\u0442\u0438\u043d\u043e"
    ],
    "name:und_x_variant":[
        "Bottutino",
        "Baltutino Pervoye",
        "Baltutino Nomer Pervyy",
        "Bolturino",
        "Boltutino"
    ],
    "wof:name":"Boltutino",
    "wof:placetype":"locality"
},
  "geometry": {"coordinates":[32.81684,54.52896],"type":"Point"}
}