{
  "type": "Feature",
  "properties": {
    "gn:country":"RU",
    "gn:fcode":"PPL",
    "gn:pop":8132,
    "iso:country":"RU",
    "name:eng_x_preferred":[
        "Novogornyy"
    ],
    "name:nor_x_preferred":[
        "Novogornyj"
    ],
    "name:rus_x_preferred":[
        "\u041d\u043e\u0432\u043e\u0433\u043e\u0440\u043d\u044b\u0439"
    ],
    "name:unk_x_variant":[
        "\u041d\u043e\u0432\u043e\u0433\u043e\u0440\u043d\u044b\u0439"
    ],
    "qs:name":"Novogornyy",
    "qs:name_adm0":"Russia",
    "qs:name_adm1":"Chelyabinsk Oblast",
    "qs:photos_9r":0,
    "qs:photos_sr":0,
    "qs:placetype":"Town",
    "qs:pop_sr":"5",
    "wof:name":"Novogornyy",
    "wof:placetype":"locality",
    "wof:population":8132
},
  "geometry": {"coordinates":[60.7919,55.63],"type":"Point"}
}