{
  "type": "Feature",
  "properties": {
    "gn:admin1_code":"16",
    "gn:asciiname":"Volonter",
    "gn:country_code":"RU",
    "gn:dem":123,
    "gn:feature_class":"P",
    "gn:feature_code":"PPL",
    "gn:name":"Volont\u00ebr",
    "gn:population":0,
    "gn:timezone":"Europe/Moscow",
    "iso:country":"RU",
    "name:rus_x_preferred":[
        "\u0412\u043e\u043b\u043e\u043d\u0442\u0451\u0440"
    ],
    "name:und_x_variant":[
        "Volont\u00ebr"
    ],
    "wof:name":"Volonter",
    "wof:placetype":"locality"
},
  "geometry": {"coordinates":[46.78706,55.48593],"type":"Point"}
}