{
  "type": "Feature",
  "properties": {
    "gn:admin1_code":"21.0",
    "gn:asciiname":"Arkhangel",
    "gn:country_code":"RU",
    "gn:dem":145,
    "gn:feature_class":"P",
    "gn:feature_code":"PPL",
    "gn:name":"Arkhangel",
    "gn:population":0,
    "gn:timezone":"Europe/Moscow",
    "iso:country":"RU",
    "name:nor_x_preferred":[
        "Arkhangel"
    ],
    "name:rus_x_preferred":[
        "\u0410\u0440\u0445\u0430\u043d\u0433\u0435\u043b"
    ],
    "wof:name":"Arkhangel",
    "wof:placetype":"locality"
},
  "geometry": {"coordinates":[40.32397,57.1047],"type":"Point"}
}