{
  "type": "Feature",
  "properties": {
    "gn:admin1_code":"60.0",
    "gn:asciiname":"Glazunovo",
    "gn:country_code":"RU",
    "gn:dem":162,
    "gn:feature_class":"P",
    "gn:feature_code":"PPL",
    "gn:name":"Glazunovo",
    "gn:population":0,
    "gn:timezone":"Europe/Moscow",
    "iso:country":"RU",
    "name:eng_x_preferred":[
        "Glazunovo"
    ],
    "name:nor_x_preferred":[
        "Glazunovo"
    ],
    "name:rus_x_preferred":[
        "\u0413\u043b\u0430\u0437\u0443\u043d\u043e\u0432\u043e"
    ],
    "wof:name":"Glazunovo",
    "wof:placetype":"locality"
},
  "geometry": {"coordinates":[30.87245,55.85379],"type":"Point"}
}