{
  "type": "Feature",
  "properties": {
    "gn:admin1_code":"61",
    "gn:asciiname":"Shevchenko",
    "gn:country_code":"RU",
    "gn:dem":48,
    "gn:feature_class":"P",
    "gn:feature_code":"PPL",
    "gn:name":"Shevchenko",
    "gn:population":0,
    "gn:timezone":"Europe/Moscow",
    "iso:country":"RU",
    "name:rus_x_preferred":[
        "\u0428\u0435\u0432\u0447\u0435\u043d\u043a\u043e"
    ],
    "name:slk_x_preferred":[
        "\u0160ev\u010denko"
    ],
    "name:slv_x_preferred":[
        "\u0160ev\u010denko"
    ],
    "wof:name":"Shevchenko",
    "wof:placetype":"locality"
},
  "geometry": {"coordinates":[39.9025,47.66222],"type":"Point"}
}