{
  "type": "Feature",
  "properties": {
    "gn:admin1_code":"4.0",
    "gn:asciiname":"Konstantinovka",
    "gn:country_code":"RU",
    "gn:dem":296,
    "gn:feature_class":"P",
    "gn:feature_code":"PPL",
    "gn:name":"Konstantinovka",
    "gn:population":0,
    "gn:timezone":"Asia/Barnaul",
    "iso:country":"RU",
    "name:rus_x_preferred":[
        "\u041a\u043e\u043d\u0441\u0442\u0430\u043d\u0442\u0438\u043d\u043e\u0432\u043a\u0430"
    ],
    "wof:name":"Konstantinovka",
    "wof:placetype":"locality"
},
  "geometry": {"coordinates":[86.6318,53.0927],"type":"Point"}
}