{
  "type": "Feature",
  "properties": {
    "gn:admin1_code":"86.0",
    "gn:asciiname":"Staroye",
    "gn:country_code":"RU",
    "gn:dem":151,
    "gn:feature_class":"P",
    "gn:feature_code":"PPL",
    "gn:name":"Staroye",
    "gn:population":0,
    "gn:timezone":"Europe/Moscow",
    "iso:country":"RU",
    "name:und_x_variant":[
        "Staroye Selo",
        "Staroye"
    ],
    "wof:name":"Staroye",
    "wof:placetype":"locality"
},
  "geometry": {"coordinates":[39.03538,51.66329],"type":"Point"}
}