{
  "type": "Feature",
  "properties": {
    "gn:admin1_code":"51",
    "gn:asciiname":"Naumovka",
    "gn:country_code":"RU",
    "gn:dem":123,
    "gn:feature_class":"P",
    "gn:feature_code":"PPL",
    "gn:name":"Naumovka",
    "gn:population":0,
    "gn:timezone":"Europe/Moscow",
    "iso:country":"RU",
    "name:eng_x_preferred":[
        "Naumovka"
    ],
    "name:nor_x_preferred":[
        "Naumovka"
    ],
    "name:rus_x_preferred":[
        "\u041d\u0430\u0443\u043c\u043e\u0432\u043a\u0430"
    ],
    "wof:name":"Naumovka",
    "wof:placetype":"locality"
},
  "geometry": {"coordinates":[43.49733,55.6423],"type":"Point"}
}