{
  "type": "Feature",
  "properties": {
    "gn:admin1_code":"67",
    "gn:asciiname":"Krasnyy",
    "gn:country_code":"RU",
    "gn:dem":168,
    "gn:feature_class":"P",
    "gn:feature_code":"PPL",
    "gn:name":"Krasnyy",
    "gn:population":0,
    "gn:timezone":"Europe/Saratov",
    "iso:country":"RU",
    "name:rus_x_preferred":[
        "\u041a\u0440\u0430\u0441\u043d\u044b\u0439"
    ],
    "name:und_x_variant":[
        "Krasnyy Oktyabr\u2019"
    ],
    "wof:name":"Krasnyy",
    "wof:placetype":"locality"
},
  "geometry": {"coordinates":[43.56101,51.44808],"type":"Point"}
}