{
  "type": "Feature",
  "properties": {
    "gn:admin1_code":"11",
    "gn:admin2_code":"2023349",
    "gn:asciiname":"Posol'skoye",
    "gn:country_code":"RU",
    "gn:dem":449,
    "gn:feature_class":"P",
    "gn:feature_code":"PPL",
    "gn:name":"Posol\u2019skoye",
    "gn:population":782,
    "gn:timezone":"Asia/Irkutsk",
    "iso:country":"RU",
    "name:eng_x_preferred":[
        "Posol\u2019skoye"
    ],
    "name:nor_x_preferred":[
        "Posolskoje"
    ],
    "name:rus_x_preferred":[
        "\u041f\u043e\u0441\u043e\u043b\u044c\u0441\u043a\u043e\u0435"
    ],
    "wof:name":"Posol'skoye",
    "wof:placetype":"locality",
    "wof:population":782
},
  "geometry": {"coordinates":[106.17638999999998,52.02111],"type":"Point"}
}