{
  "type": "Feature",
  "properties": {
    "gn:admin1_code":"29",
    "gn:asciiname":"Zhernovo",
    "gn:country_code":"RU",
    "gn:dem":231,
    "gn:feature_class":"P",
    "gn:feature_code":"PPL",
    "gn:name":"Zhernovo",
    "gn:population":0,
    "gn:timezone":"Asia/Novokuznetsk",
    "iso:country":"RU",
    "name:eng_x_preferred":[
        "Zhernovo"
    ],
    "name:nor_x_preferred":[
        "Zjernovo"
    ],
    "name:rus_x_preferred":[
        "\u0416\u0435\u0440\u043d\u043e\u0432\u043e"
    ],
    "name:und_x_variant":[
        "Zhirnovskoye",
        "Zhernovo"
    ],
    "wof:name":"Zhernovo",
    "wof:placetype":"locality"
},
  "geometry": {"coordinates":[87.24938,54.16815],"type":"Point"}
}