{
  "type": "Feature",
  "properties": {
    "gn:admin1_code":"69",
    "gn:asciiname":"Boloto",
    "gn:country_code":"RU",
    "gn:dem":218,
    "gn:feature_class":"P",
    "gn:feature_code":"PPL",
    "gn:name":"Boloto",
    "gn:population":0,
    "gn:timezone":"Europe/Moscow",
    "iso:country":"RU",
    "name:che_x_preferred":[
        "\u0411\u043e\u043b\u043e\u0442\u043e"
    ],
    "name:rus_x_preferred":[
        "\u0411\u043e\u043b\u043e\u0442\u043e"
    ],
    "name:und_x_variant":[
        "\u0411\u043e\u043b\u043e\u0442\u043e"
    ],
    "wof:name":"Boloto",
    "wof:placetype":"locality"
},
  "geometry": {"coordinates":[33.89972,55.10972],"type":"Point"}
}