{
  "type": "Feature",
  "properties": {
    "gn:admin1_code":"57",
    "gn:asciiname":"Pioner",
    "gn:country_code":"RU",
    "gn:dem":290,
    "gn:feature_class":"P",
    "gn:feature_code":"PPL",
    "gn:name":"Pioner",
    "gn:population":0,
    "gn:timezone":"Europe/Moscow",
    "iso:country":"RU",
    "name:bul_x_preferred":[
        "\u041f\u0438\u043e\u043d\u0435\u0440"
    ],
    "name:cat_x_preferred":[
        "Pioner"
    ],
    "name:ceb_x_preferred":[
        "Pioner"
    ],
    "name:deu_x_preferred":[
        "Pioner"
    ],
    "name:eng_x_preferred":[
        "Pioner"
    ],
    "name:kaz_x_preferred":[
        "\u041f\u0438\u043e\u043d\u0435\u0440"
    ],
    "name:nor_x_preferred":[
        "Pioner"
    ],
    "name:rus_x_preferred":[
        "\u041f\u0438\u043e\u043d\u0435\u0440"
    ],
    "name:swe_x_preferred":[
        "Pioner"
    ],
    "name:ukr_x_preferred":[
        "\u041f\u0456\u043e\u043d\u0435\u0440"
    ],
    "wof:name":"Pioner",
    "wof:placetype":"locality"
},
  "geometry": {"coordinates":[46.60328,53.03605],"type":"Point"}
}