{
  "type": "Feature",
  "properties": {
    "gn:admin1_code":"88.0",
    "gn:asciiname":"Dudenevo",
    "gn:country_code":"RU",
    "gn:dem":145,
    "gn:feature_class":"P",
    "gn:feature_code":"PPL",
    "gn:name":"Duden\u00ebvo",
    "gn:population":0,
    "gn:timezone":"Europe/Moscow",
    "iso:country":"RU",
    "name:eng_x_preferred":[
        "Duden\u00ebvo"
    ],
    "name:nor_x_preferred":[
        "Dudenevo"
    ],
    "name:rus_x_preferred":[
        "\u0414\u0443\u0434\u0435\u043d\u0435\u0432\u043e"
    ],
    "name:rus_x_variant":[
        "\u0414\u0443\u0434\u0435\u043d\u0451\u0432\u043e"
    ],
    "wof:name":"Dudenevo",
    "wof:placetype":"locality"
},
  "geometry": {"coordinates":[37.74294,58.30297],"type":"Point"}
}