{
  "type": "Feature",
  "properties": {
    "gn:admin1_code":"60",
    "gn:asciiname":"Lobazy",
    "gn:country_code":"RU",
    "gn:dem":99,
    "gn:feature_class":"P",
    "gn:feature_code":"PPL",
    "gn:name":"Lobazy",
    "gn:population":0,
    "gn:timezone":"Europe/Moscow",
    "iso:country":"RU",
    "name:rus_x_preferred":[
        "\u041b\u0430\u0431\u0430\u0437\u044b"
    ],
    "name:rus_x_variant":[
        "\u041b\u043e\u0431\u0430\u0437\u044b"
    ],
    "name:und_x_variant":[
        "Labazy",
        "Lobazy"
    ],
    "wof:name":"Lobazy",
    "wof:placetype":"locality"
},
  "geometry": {"coordinates":[28.92105,56.98521],"type":"Point"}
}