{
  "type": "Feature",
  "properties": {
    "gn:admin1_code":"69",
    "gn:asciiname":"Yurino",
    "gn:country_code":"RU",
    "gn:dem":229,
    "gn:feature_class":"P",
    "gn:feature_code":"PPL",
    "gn:name":"Yurino",
    "gn:population":0,
    "gn:timezone":"Europe/Moscow",
    "iso:country":"RU",
    "wof:name":"Yurino",
    "wof:placetype":"locality"
},
  "geometry": {"coordinates":[34.38586,55.09553],"type":"Point"}
}