{
  "type": "Feature",
  "properties": {
    "gn:admin1_code":"85",
    "gn:asciiname":"Sysoyevo",
    "gn:country_code":"RU",
    "gn:dem":148,
    "gn:feature_class":"P",
    "gn:feature_code":"PPL",
    "gn:name":"Sysoyevo",
    "gn:population":0,
    "gn:timezone":"Europe/Moscow",
    "iso:country":"RU",
    "name:eng_x_preferred":[
        "Sysoyevo"
    ],
    "name:nor_x_preferred":[
        "Sysojevo"
    ],
    "name:rus_x_preferred":[
        "\u0421\u044b\u0441\u043e\u0435\u0432\u043e"
    ],
    "wof:name":"Sysoyevo",
    "wof:placetype":"locality"
},
  "geometry": {"coordinates":[39.1659,59.4103],"type":"Point"}
}