{
  "type": "Feature",
  "properties": {
    "gn:admin1_code":"28",
    "gn:asciiname":"Vangozero",
    "gn:cc2":"RU",
    "gn:country_code":"RU",
    "gn:dem":75,
    "gn:feature_class":"P",
    "gn:feature_code":"PPL",
    "gn:name":"Vangozero",
    "gn:population":0,
    "gn:timezone":"Europe/Moscow",
    "iso:country":"RU",
    "name:fin_x_preferred":[
        "Venkij\u00e4rvi"
    ],
    "name:und_x_variant":[
        "Vonkaj\u00e4rvi",
        "Vangozero",
        "Marttinainen"
    ],
    "wof:name":"Vangozero",
    "wof:placetype":"locality"
},
  "geometry": {"coordinates":[33.35655,65.56925],"type":"Point"}
}