{
  "type": "Feature",
  "properties": {
    "gn:admin1_code":"47",
    "gn:asciiname":"Individual'nyy",
    "gn:country_code":"RU",
    "gn:dem":118,
    "gn:feature_class":"P",
    "gn:feature_code":"PPL",
    "gn:name":"Individual\u2019nyy",
    "gn:population":0,
    "gn:timezone":"Europe/Moscow",
    "iso:country":"RU",
    "name:rus_x_preferred":[
        "\u0418\u043d\u0434\u0438\u0432\u0438\u0434\u0443\u0430\u043b\u044c\u043d\u044b\u0439"
    ],
    "name:und_x_variant":[
        "Individual\u2019nyy",
        "\u0418\u043d\u0434\u0438\u0432\u0438\u0434\u0443\u0430\u043b\u044c\u043d\u044b\u0439"
    ],
    "wof:name":"Individual'nyy",
    "wof:placetype":"locality"
},
  "geometry": {"coordinates":[39.85,55.66667],"type":"Point"}
}