{
  "type": "Feature",
  "properties": {
    "gn:admin1_code":"69",
    "gn:asciiname":"Deniski",
    "gn:country_code":"RU",
    "gn:dem":227,
    "gn:feature_class":"P",
    "gn:feature_code":"PPL",
    "gn:name":"Deniski",
    "gn:population":0,
    "gn:timezone":"Europe/Moscow",
    "iso:country":"RU",
    "name:azb_x_preferred":[
        "\u062f\u0646\u0642\u0633\u06a9\u06cc"
    ],
    "name:fas_x_preferred":[
        "\u062f\u0646\u06af\u0633\u06a9\u06cc"
    ],
    "name:fra_x_preferred":[
        "Deniski"
    ],
    "name:lit_x_preferred":[
        "Deniskai"
    ],
    "name:pol_x_preferred":[
        "Deniski"
    ],
    "name:rus_x_preferred":[
        "\u0414\u0435\u043d\u0438\u0441\u043a\u0438"
    ],
    "name:ukr_x_preferred":[
        "\u0414\u0435\u043d\u0456\u0441\u043a\u0456"
    ],
    "name:und_x_variant":[
        "\u0414\u0435\u043d\u0438\u0441\u043a\u0438"
    ],
    "wof:name":"Deniski",
    "wof:placetype":"locality"
},
  "geometry": {"coordinates":[33.10472,55.04944],"type":"Point"}
}