{
  "type": "Feature",
  "properties": {
    "gn:admin1_code":"56",
    "gn:asciiname":"Telyakovo",
    "gn:country_code":"RU",
    "gn:dem":181,
    "gn:feature_class":"P",
    "gn:feature_code":"PPL",
    "gn:name":"Telyakovo",
    "gn:population":0,
    "gn:timezone":"Europe/Moscow",
    "iso:country":"RU",
    "name:und_x_variant":[
        "Telekovo",
        "Telyakovo"
    ],
    "wof:name":"Telyakovo",
    "wof:placetype":"locality"
},
  "geometry": {"coordinates":[35.49885,52.98305],"type":"Point"}
}