{
  "type": "Feature",
  "properties": {
    "gn:admin1_code":"52",
    "gn:asciiname":"Klevdino",
    "gn:country_code":"RU",
    "gn:dem":93,
    "gn:feature_class":"P",
    "gn:feature_code":"PPL",
    "gn:name":"Klevdino",
    "gn:population":0,
    "gn:timezone":"Europe/Moscow",
    "iso:country":"RU",
    "name:rus_x_preferred":[
        "\u041a\u043b\u0435\u0432\u0434\u0438\u043d\u043e"
    ],
    "name:und_x_variant":[
        "Klevdina",
        "Klevdino"
    ],
    "wof:name":"Klevdino",
    "wof:placetype":"locality"
},
  "geometry": {"coordinates":[30.76172,57.04887],"type":"Point"}
}