{
  "type": "Feature",
  "properties": {
    "gn:admin1_code":"16",
    "gn:asciiname":"Khozaydankino",
    "gn:country_code":"RU",
    "gn:dem":168,
    "gn:feature_class":"P",
    "gn:feature_code":"PPL",
    "gn:name":"Khozaydankino",
    "gn:population":0,
    "gn:timezone":"Europe/Moscow",
    "iso:country":"RU",
    "name:rus_x_preferred":[
        "\u0425\u043e\u0437\u0430\u043d\u0434\u0430\u0439\u043a\u0438\u043d\u043e"
    ],
    "name:und_x_variant":[
        "Khozandaykino"
    ],
    "wof:name":"Khozaydankino",
    "wof:placetype":"locality"
},
  "geometry": {"coordinates":[47.06292,56.0562],"type":"Point"}
}