{
  "type": "Feature",
  "properties": {
    "gn:admin1_code":"76",
    "gn:asciiname":"Zaninka",
    "gn:country_code":"RU",
    "gn:dem":227,
    "gn:feature_class":"P",
    "gn:feature_code":"PPL",
    "gn:name":"Zaninka",
    "gn:population":0,
    "gn:timezone":"Europe/Moscow",
    "iso:country":"RU",
    "name:und_x_variant":[
        "Maloye Zanino"
    ],
    "wof:name":"Zaninka",
    "wof:placetype":"locality"
},
  "geometry": {"coordinates":[37.07161,54.34071],"type":"Point"}
}