{
  "type": "Feature",
  "properties": {
    "gn:admin1_code":"12.0",
    "gn:asciiname":"Gashtiyev",
    "gn:country_code":"RU",
    "gn:dem":406,
    "gn:feature_class":"P",
    "gn:feature_code":"PPL",
    "gn:name":"Gashtiyev",
    "gn:population":0,
    "gn:timezone":"Europe/Moscow",
    "iso:country":"RU",
    "name:rus_x_preferred":[
        "\u0413\u0430\u0448\u0442\u0438\u0435\u0432"
    ],
    "wof:name":"Gashtiyev",
    "wof:placetype":"locality"
},
  "geometry": {"coordinates":[45.16694,43.48333],"type":"Point"}
}