{
  "type": "Feature",
  "properties": {
    "gn:admin1_code":"24",
    "gn:asciiname":"Kek-Nur",
    "gn:country_code":"RU",
    "gn:dem":35,
    "gn:feature_class":"P",
    "gn:feature_code":"PPL",
    "gn:name":"Kek-Nur",
    "gn:population":0,
    "gn:timezone":"Europe/Moscow",
    "iso:country":"RU",
    "name:rus_x_preferred":[
        "\u041a\u0435\u043a-\u041d\u0443\u0440"
    ],
    "wof:name":"Kek-Nur",
    "wof:placetype":"locality"
},
  "geometry": {"coordinates":[44.8075,46.2914],"type":"Point"}
}