{
  "type": "Feature",
  "properties": {
    "gn:admin1_code":"37",
    "gn:asciiname":"Noskovo",
    "gn:country_code":"RU",
    "gn:dem":166,
    "gn:feature_class":"P",
    "gn:feature_code":"PPL",
    "gn:name":"Noskovo",
    "gn:population":0,
    "gn:timezone":"Europe/Moscow",
    "iso:country":"RU",
    "name:rus_x_preferred":[
        "\u041d\u043e\u0441\u043a\u043e\u0432\u043e"
    ],
    "wof:name":"Noskovo",
    "wof:placetype":"locality"
},
  "geometry": {"coordinates":[42.0262,58.97213000000001],"type":"Point"}
}