{
  "type": "Feature",
  "properties": {
    "gn:admin1_code":"62",
    "gn:asciiname":"Khalymovo",
    "gn:country_code":"RU",
    "gn:dem":159,
    "gn:feature_class":"P",
    "gn:feature_code":"PPL",
    "gn:name":"Khalymovo",
    "gn:population":0,
    "gn:timezone":"Europe/Moscow",
    "iso:country":"RU",
    "name:rus_x_preferred":[
        "\u0425\u0430\u043b\u044b\u043c\u043e\u0432\u043e"
    ],
    "wof:name":"Khalymovo",
    "wof:placetype":"locality"
},
  "geometry": {"coordinates":[41.52286,54.9128],"type":"Point"}
}