{
  "type": "Feature",
  "properties": {
    "gn:admin1_code":"69",
    "gn:asciiname":"Yermaki",
    "gn:country_code":"RU",
    "gn:dem":231,
    "gn:feature_class":"P",
    "gn:feature_code":"PPL",
    "gn:name":"Yermaki",
    "gn:population":0,
    "gn:timezone":"Europe/Moscow",
    "iso:country":"RU",
    "wof:name":"Yermaki",
    "wof:placetype":"locality"
},
  "geometry": {"coordinates":[33.73694,55.75917],"type":"Point"}
}