{
  "type": "Feature",
  "properties": {
    "gn:admin1_code":"55",
    "gn:asciiname":"Yelkhovka",
    "gn:country_code":"RU",
    "gn:dem":107,
    "gn:feature_class":"P",
    "gn:feature_code":"PPL",
    "gn:name":"Yelkhovka",
    "gn:population":0,
    "gn:timezone":"Asia/Yekaterinburg",
    "iso:country":"RU",
    "name:rus_x_preferred":[
        "\u0415\u043b\u0445\u043e\u0432\u043a\u0430"
    ],
    "name:und_x_variant":[
        "Arkhangel\u2019skoye",
        "Yelkhovka",
        "\u0415\u043b\u0445\u043e\u0432\u043a\u0430"
    ],
    "wof:name":"Yelkhovka",
    "wof:placetype":"locality"
},
  "geometry": {"coordinates":[52.3724,52.473],"type":"Point"}
}