{
  "type": "Feature",
  "properties": {
    "gn:admin1_code":"42",
    "gn:admin2_code":"575409",
    "gn:asciiname":"Zubakino",
    "gn:country_code":"RU",
    "gn:dem":160,
    "gn:feature_class":"P",
    "gn:feature_code":"PPL",
    "gn:name":"Zubakino",
    "gn:population":0,
    "gn:timezone":"Europe/Moscow",
    "iso:country":"RU",
    "name:rus_x_preferred":[
        "\u0417\u0443\u0431\u0430\u043a\u0438\u043d\u043e"
    ],
    "wof:name":"Zubakino",
    "wof:placetype":"locality"
},
  "geometry": {"coordinates":[34.00302,59.30506999999999],"type":"Point"}
}