{
  "type": "Feature",
  "properties": {
    "gn:admin1_code":"71.0",
    "gn:asciiname":"Meleyeva",
    "gn:country_code":"RU",
    "gn:dem":66,
    "gn:feature_class":"P",
    "gn:feature_code":"PPL",
    "gn:name":"Meleyeva",
    "gn:population":0,
    "gn:timezone":"Asia/Yekaterinburg",
    "iso:country":"RU",
    "name:rus_x_preferred":[
        "\u041c\u0435\u043b\u0435\u0435\u0432\u0430"
    ],
    "name:und_x_variant":[
        "\u041c\u0435\u043b\u0435\u0435\u0432\u0430",
        "Meleyeva"
    ],
    "wof:name":"Meleyeva",
    "wof:placetype":"locality"
},
  "geometry": {"coordinates":[62.32066999999999,59.48855],"type":"Point"}
}