{
  "type": "Feature",
  "properties": {
    "gn:country":"RU",
    "gn:fcode":"PPL",
    "gn:pop":0,
    "iso:country":"RU",
    "name:dut_x_preferred":[
        "Sakhyurta"
    ],
    "name:eng_x_preferred":[
        "Sakhyurta"
    ],
    "name:nor_x_preferred":[
        "Sakhjurta"
    ],
    "name:rus_x_colloquial":[
        "\u041c\u0420\u0421"
    ],
    "name:rus_x_preferred":[
        "\u0421\u0430\u0445\u044e\u0440\u0442\u0430"
    ],
    "name:rus_x_variant":[
        "\u0421\u0430\u0445\u044e\u0440\u0442\u0430"
    ],
    "name:unk_x_variant":[
        "Satyurty"
    ],
    "qs:name":"Sakhyurta",
    "qs:name_adm0":"Russia",
    "qs:name_adm1":"Irkutsk Oblast",
    "qs:photos":202,
    "qs:photos_1k":41,
    "qs:photos_9k":1,
    "qs:photos_9r":4,
    "qs:photos_all":202,
    "qs:photos_sr":4,
    "qs:placetype":"Town",
    "qs:pop_sr":"0",
    "wd:wordcount":172,
    "wof:name":"Sakhyurta",
    "wof:placetype":"locality",
    "wof:population":0
},
  "geometry": {"coordinates":[106.87972000000001,53.02083],"type":"Point"}
}