{
  "type": "Feature",
  "properties": {
    "gn:country":"RU",
    "gn:fcode":"PPL",
    "gn:population":0,
    "iso:country":"RU",
    "name:azb_x_preferred":[
        "\u0633\u0627\u062e\u06cc\u0648\u0631\u062a\u0627"
    ],
    "name:bel_x_preferred":[
        "\u0421\u0430\u0445\u044e\u0440\u0442\u0430"
    ],
    "name:ceb_x_preferred":[
        "Sakhyurta"
    ],
    "name:che_x_preferred":[
        "\u0421\u0430\u0445\u044e\u0440\u0442\u0430"
    ],
    "name:eng_x_preferred":[
        "Sakhyurta"
    ],
    "name:fra_x_preferred":[
        "Sakhyurta"
    ],
    "name:nld_x_preferred":[
        "Sakhyurta"
    ],
    "name:nno_x_preferred":[
        "Sakhjurta"
    ],
    "name:nob_x_preferred":[
        "Sakhjurta"
    ],
    "name:nor_x_preferred":[
        "Sakhjurta"
    ],
    "name:rus_x_colloquial":[
        "\u041c\u0420\u0421"
    ],
    "name:rus_x_preferred":[
        "\u0421\u0430\u0445\u044e\u0440\u0442\u0430"
    ],
    "name:sqi_x_preferred":[
        "Sahjurta"
    ],
    "name:und_x_variant":[
        "Satyurty"
    ],
    "qs:name":"Sakhyurta",
    "qs:name_adm0":"Russia",
    "qs:name_adm1":"Irkutsk Oblast",
    "qs:photos":202,
    "qs:photos_1k":41,
    "qs:photos_9k":1,
    "qs:photos_9r":4,
    "qs:photos_all":202,
    "qs:photos_sr":4,
    "qs:placetype":"Town",
    "qs:pop_sr":"0",
    "wd:wordcount":172,
    "wof:name":"Sakhyurta",
    "wof:placetype":"locality",
    "wof:population":0
},
  "geometry": {"coordinates":[106.87972000000001,53.02083],"type":"Point"}
}