{
  "type": "Feature",
  "properties": {
    "gn:admin1_code":"05",
    "gn:asciiname":"Sektagli",
    "gn:country_code":"RU",
    "gn:dem":184,
    "gn:feature_class":"P",
    "gn:feature_code":"PPL",
    "gn:name":"Sektagli",
    "gn:population":0,
    "gn:timezone":"Asia/Vladivostok",
    "iso:country":"RU",
    "name:eng_x_preferred":[
        "Sektagli"
    ],
    "name:nor_x_preferred":[
        "Sektagli"
    ],
    "name:rus_x_preferred":[
        "\u0421\u0435\u043a\u0442\u0430\u0433\u043b\u0438"
    ],
    "name:und_x_variant":[
        "Siktagli",
        "\u0421\u0435\u043a\u0442\u0430\u0433\u043b\u0438",
        "Sektagli"
    ],
    "wof:name":"Sektagli",
    "wof:placetype":"locality"
},
  "geometry": {"coordinates":[131.02975000000001,50.43631],"type":"Point"}
}