{
  "type": "Feature",
  "properties": {
    "gn:admin1_code":"86.0",
    "gn:asciiname":"Galkin",
    "gn:country_code":"RU",
    "gn:dem":179,
    "gn:feature_class":"P",
    "gn:feature_code":"PPL",
    "gn:name":"Galkin",
    "gn:population":0,
    "gn:timezone":"Europe/Moscow",
    "iso:country":"RU",
    "name:rus_x_preferred":[
        "\u0413\u0430\u043b\u043a\u0438\u043d"
    ],
    "name:und_x_variant":[
        "\u0413\u0430\u043b\u043a\u0438\u043d"
    ],
    "wof:name":"Galkin",
    "wof:placetype":"locality"
},
  "geometry": {"coordinates":[40.83028,50.58333],"type":"Point"}
}