{
  "type": "Feature",
  "properties": {
    "gn:admin1_code":"67",
    "gn:asciiname":"Mikhaylovskiy Chetvertyy",
    "gn:country_code":"RU",
    "gn:dem":63,
    "gn:feature_class":"P",
    "gn:feature_code":"PPL",
    "gn:name":"Mikhaylovskiy Chetv\u00ebrtyy",
    "gn:population":0,
    "gn:timezone":"Europe/Saratov",
    "iso:country":"RU",
    "name:rus_x_preferred":[
        "\u041c\u0438\u0445\u0430\u0439\u043b\u043e\u0432\u0441\u043a\u0438\u0439 \u0427\u0435\u0442\u0432\u0451\u0440\u0442\u044b\u0439"
    ],
    "name:und_x_variant":[
        "Mikhaylovka Chetv\u00ebrtaya",
        "Mikhaylovskiy Chetv\u00ebrtyy"
    ],
    "wof:name":"Mikhaylovskiy Chetvertyy",
    "wof:placetype":"locality"
},
  "geometry": {"coordinates":[48.5857,51.75899999999999],"type":"Point"}
}