{
  "type": "Feature",
  "properties": {
    "gn:admin1_code":"90.0",
    "gn:asciiname":"Garevka",
    "gn:country_code":"RU",
    "gn:dem":179,
    "gn:feature_class":"P",
    "gn:feature_code":"PPL",
    "gn:name":"Garevka",
    "gn:population":0,
    "gn:timezone":"Asia/Yekaterinburg",
    "iso:country":"RU",
    "name:eng_x_preferred":[
        "Garevka"
    ],
    "name:nor_x_preferred":[
        "Garevka"
    ],
    "name:rus_x_preferred":[
        "\u0413\u0430\u0440\u0435\u0432\u043a\u0430"
    ],
    "wof:name":"Garevka",
    "wof:placetype":"locality"
},
  "geometry": {"coordinates":[57.17417,61.35639000000001],"type":"Point"}
}