{
  "type": "Feature",
  "properties": {
    "gn:admin1_code":"16",
    "gn:asciiname":"Novyye Vysli",
    "gn:country_code":"RU",
    "gn:dem":184,
    "gn:feature_class":"P",
    "gn:feature_code":"PPL",
    "gn:name":"Novyye Vysli",
    "gn:population":0,
    "gn:timezone":"Europe/Moscow",
    "iso:country":"RU",
    "name:rus_x_preferred":[
        "\u041d\u043e\u0432\u044b\u0435 \u0412\u044b\u0441\u043b\u0438"
    ],
    "wof:name":"Novyye Vysli",
    "wof:placetype":"locality"
},
  "geometry": {"coordinates":[47.45955,55.1548],"type":"Point"}
}