{
  "type": "Feature",
  "properties": {
    "gn:admin1_code":"69",
    "gn:asciiname":"Lomanchino",
    "gn:country_code":"RU",
    "gn:dem":219,
    "gn:feature_class":"P",
    "gn:feature_code":"PPL",
    "gn:name":"Lomanchino",
    "gn:population":0,
    "gn:timezone":"Europe/Moscow",
    "iso:country":"RU",
    "name:rus_x_preferred":[
        "\u041b\u043e\u043c\u0430\u043d\u0447\u0438\u043d\u043e"
    ],
    "wof:name":"Lomanchino",
    "wof:placetype":"locality"
},
  "geometry": {"coordinates":[33.87028,54.91944],"type":"Point"}
}