{
  "type": "Feature",
  "properties": {
    "gn:admin1_code":"69",
    "gn:asciiname":"Khokhlovo",
    "gn:country_code":"RU",
    "gn:dem":233,
    "gn:feature_class":"P",
    "gn:feature_code":"PPL",
    "gn:name":"Khokhlovo",
    "gn:population":0,
    "gn:timezone":"Europe/Moscow",
    "iso:country":"RU",
    "name:eng_x_preferred":[
        "Khokhlovo"
    ],
    "name:nor_x_preferred":[
        "Khokhlovo"
    ],
    "name:rus_x_preferred":[
        "\u0425\u043e\u0445\u043b\u043e\u0432\u043e"
    ],
    "wof:name":"Khokhlovo",
    "wof:placetype":"locality"
},
  "geometry": {"coordinates":[31.83772,54.69777],"type":"Point"}
}