{
  "type": "Feature",
  "properties": {
    "gn:admin1_code":"33",
    "gn:asciiname":"Setina-Gora",
    "gn:country_code":"RU",
    "gn:dem":139,
    "gn:feature_class":"P",
    "gn:feature_code":"PPL",
    "gn:name":"Setina-Gora",
    "gn:population":0,
    "gn:timezone":"Europe/Kirov",
    "iso:country":"RU",
    "name:rus_x_preferred":[
        "\u0421\u0435\u0442\u0438\u043d\u0430-\u0413\u043e\u0440\u0430"
    ],
    "name:und_x_variant":[
        "\u0421\u0435\u0442\u0438\u043d\u0430-\u0413\u043e\u0440\u0430"
    ],
    "wof:name":"Setina-Gora",
    "wof:placetype":"locality"
},
  "geometry": {"coordinates":[47.1942,60.2321],"type":"Point"}
}