{
  "type": "Feature",
  "properties": {
    "gn:admin1_code":"76",
    "gn:asciiname":"Zamarino",
    "gn:country_code":"RU",
    "gn:dem":175,
    "gn:feature_class":"P",
    "gn:feature_code":"PPL",
    "gn:name":"Zamarino",
    "gn:population":0,
    "gn:timezone":"Europe/Moscow",
    "iso:country":"RU",
    "name:eng_x_preferred":[
        "Zamarino"
    ],
    "name:nor_x_preferred":[
        "Zamarino"
    ],
    "name:rus_x_preferred":[
        "\u0417\u0430\u043c\u0430\u0440\u0438\u043d\u043e"
    ],
    "wof:name":"Zamarino",
    "wof:placetype":"locality"
},
  "geometry": {"coordinates":[37.18069000000001,54.30345],"type":"Point"}
}