{
  "type": "Feature",
  "properties": {
    "gn:admin1_code":"56.0",
    "gn:asciiname":"Belyy Kolodez' Vtoroy",
    "gn:country_code":"RU",
    "gn:dem":194,
    "gn:feature_class":"P",
    "gn:feature_code":"PPL",
    "gn:name":"Belyy Kolodez\u2019 Vtoroy",
    "gn:population":0,
    "gn:timezone":"Europe/Moscow",
    "iso:country":"RU",
    "name:nor_x_preferred":[
        "Belyj Kolodez Vtoroj"
    ],
    "name:rus_x_preferred":[
        "\u0411\u0435\u043b\u044b\u0439 \u041a\u043e\u043b\u043e\u0434\u0435\u0437\u044c \u0412\u0442\u043e\u0440\u043e\u0439"
    ],
    "name:und_x_variant":[
        "Vtoroy Belyy Kolodez\u2019",
        "Belokolodez\u2019 Vtoroy",
        "Belyy Kolodez\u2019 Vtoroy"
    ],
    "wof:name":"Belyy Kolodez' Vtoroy",
    "wof:placetype":"locality"
},
  "geometry": {"coordinates":[37.07714,52.1257],"type":"Point"}
}