{
  "type": "Feature",
  "properties": {
    "gn:country":"RU",
    "gn:fcode":"PPL",
    "gn:pop":4839,
    "iso:country":"RU",
    "name:eng_x_preferred":[
        "Komsomol'skoye"
    ],
    "name:nor_x_preferred":[
        "Komsomolskoje"
    ],
    "name:rus_x_preferred":[
        "\u041a\u043e\u043c\u0441\u043e\u043c\u043e\u043b\u044c\u0441\u043a\u043e\u0435"
    ],
    "name:unk_x_variant":[
        "Bol'shiye Koshelei"
    ],
    "qs:name":"Komsomol'skoye",
    "qs:name_adm0":"Russia",
    "qs:name_adm1":"Chuvashia Republic",
    "qs:photos_9r":0,
    "qs:photos_sr":0,
    "qs:placetype":"Town",
    "qs:pop_sr":"4",
    "wd:wordcount":206,
    "wof:name":"Komsomol'skoye",
    "wof:placetype":"locality",
    "wof:population":4839
},
  "geometry": {"coordinates":[47.54608,55.25667],"type":"Point"}
}