{
  "type": "Feature",
  "properties": {
    "gn:country":"RU",
    "gn:fcode":"PPL",
    "gn:pop":4839,
    "iso:country":"RU",
    "name:bel_x_preferred":[
        "\u041a\u0430\u043c\u0441\u0430\u043c\u043e\u043b\u044c\u0441\u043a\u0456"
    ],
    "name:cat_x_preferred":[
        "Komsomolski"
    ],
    "name:ceb_x_preferred":[
        "\u041a\u043e\u043c\u0441\u043e\u043c\u043e\u043b\u044c\u0441\u043a\u0438\u0439"
    ],
    "name:deu_x_preferred":[
        "Komsomolski"
    ],
    "name:eng_x_preferred":[
        "Komsomol'skoye"
    ],
    "name:fra_x_preferred":[
        "Komsomolska\u00efa"
    ],
    "name:hun_x_preferred":[
        "Komszomolszkij"
    ],
    "name:hye_x_preferred":[
        "\u053f\u0578\u0574\u057d\u0578\u0574\u0578\u056c\u057d\u056f\u056b"
    ],
    "name:ita_x_preferred":[
        "Komsomol'skij"
    ],
    "name:jpn_x_preferred":[
        "\u30b3\u30e0\u30bd\u30e2\u30fc\u30ea\u30b9\u30ab\u30e4\u99c5"
    ],
    "name:kor_x_preferred":[
        "\ucf64\uc18c\ubab0\uc2a4\uce74\uc57c \uc5ed"
    ],
    "name:nor_x_preferred":[
        "Komsomolskoje"
    ],
    "name:rus_x_preferred":[
        "\u041a\u043e\u043c\u0441\u043e\u043c\u043e\u043b\u044c\u0441\u043a\u043e\u0435"
    ],
    "name:rus_x_variant":[
        "\u041a\u043e\u043c\u0441\u043e\u043c\u043e\u043b\u044c\u0441\u043a\u0438\u0439"
    ],
    "name:spa_x_preferred":[
        "Komsomolski"
    ],
    "name:ukr_x_preferred":[
        "\u041a\u043e\u043c\u0441\u043e\u043c\u043e\u043b\u044c\u0441\u044c\u043a\u0438\u0439"
    ],
    "name:unk_x_variant":[
        "Bol'shiye Koshelei"
    ],
    "name:zho_x_preferred":[
        "\u5171\u9752\u5718\u7ad9"
    ],
    "qs:name":"Komsomol'skoye",
    "qs:name_adm0":"Russia",
    "qs:name_adm1":"Chuvashia Republic",
    "qs:photos_9r":0,
    "qs:photos_sr":0,
    "qs:placetype":"Town",
    "qs:pop_sr":"4",
    "wd:wordcount":206,
    "wof:name":"Komsomol'skoye",
    "wof:placetype":"locality",
    "wof:population":4839
},
  "geometry": {"coordinates":[47.54608,55.25667],"type":"Point"}
}