{
  "type": "Feature",
  "properties": {
    "gn:admin1_code":"20",
    "gn:asciiname":"Kondoy",
    "gn:country_code":"RU",
    "gn:dem":551,
    "gn:feature_class":"P",
    "gn:feature_code":"PPL",
    "gn:name":"Kondoy",
    "gn:population":0,
    "gn:timezone":"Asia/Irkutsk",
    "iso:country":"RU",
    "name:rus_x_preferred":[
        "\u041a\u043e\u043d\u0434\u043e\u0439"
    ],
    "name:und_x_variant":[
        "\u041a\u043e\u043d\u0434\u043e\u0439"
    ],
    "wof:name":"Kondoy",
    "wof:placetype":"locality"
},
  "geometry": {"coordinates":[103.48333,53.48333],"type":"Point"}
}