{
  "type": "Feature",
  "properties": {
    "gn:country":"RU",
    "gn:fcode":"PPL",
    "gn:population":0,
    "iso:country":"RU",
    "name:rus_x_preferred":[
        "\u041a\u0430\u0431\u0430\u043d\u043e\u0432\u043e"
    ],
    "name:und_x_variant":[
        "Kabanova"
    ],
    "qs:name":"Kabanovo",
    "qs:name_adm0":"Russia",
    "qs:name_adm1":"Moscow Oblast",
    "qs:photos_9k":1,
    "qs:photos_9r":1,
    "qs:photos_all":1,
    "qs:photos_sr":0,
    "qs:placetype":"Town",
    "qs:pop_sr":"0",
    "wof:name":"Kabanovo",
    "wof:placetype":"locality",
    "wof:population":0
},
  "geometry": {"coordinates":[38.93511,55.74816],"type":"Point"}
}