{
  "type": "Feature",
  "properties": {
    "gn:admin1_code":"93",
    "gn:asciiname":"Bayka",
    "gn:country_code":"RU",
    "gn:dem":579,
    "gn:feature_class":"P",
    "gn:feature_code":"PPL",
    "gn:name":"Bayka",
    "gn:population":0,
    "gn:timezone":"Asia/Chita",
    "iso:country":"RU",
    "name:eng_x_preferred":[
        "Bayka"
    ],
    "name:nor_x_preferred":[
        "Bajka"
    ],
    "name:rus_x_preferred":[
        "\u0411\u0430\u0439\u043a\u0430"
    ],
    "name:und_x_variant":[
        "Baika",
        "\u0411\u0430\u0439\u043a\u0430",
        "Bayka"
    ],
    "wof:name":"Bayka",
    "wof:placetype":"locality"
},
  "geometry": {"coordinates":[119.29680999999999,51.25533],"type":"Point"}
}