{
  "type": "Feature",
  "properties": {
    "gn:admin1_code":"29",
    "gn:asciiname":"Ust'-Urush",
    "gn:country_code":"RU",
    "gn:dem":413,
    "gn:feature_class":"P",
    "gn:feature_code":"PPL",
    "gn:name":"Ust\u2019-Urush",
    "gn:population":0,
    "gn:timezone":"Asia/Novokuznetsk",
    "iso:country":"RU",
    "name:rus_x_preferred":[
        "\u0423\u0441\u0442\u044c-\u0423\u0440\u0443\u0448"
    ],
    "name:und_x_variant":[
        "Ust\u2019-Urush",
        "\u0423\u0441\u0442\u044c-\u0423\u0440\u0443\u0448"
    ],
    "wof:name":"Ust'-Urush",
    "wof:placetype":"locality"
},
  "geometry": {"coordinates":[87.73009999999999,52.7387],"type":"Point"}
}