{
  "type": "Feature",
  "properties": {
    "gn:admin1_code":"60",
    "gn:asciiname":"Shabunikha",
    "gn:country_code":"RU",
    "gn:dem":110,
    "gn:feature_class":"P",
    "gn:feature_code":"PPL",
    "gn:name":"Shabunikha",
    "gn:population":0,
    "gn:timezone":"Europe/Moscow",
    "iso:country":"RU",
    "name:rus_x_preferred":[
        "\u0428\u0430\u0431\u0443\u043d\u0438\u0445\u0430"
    ],
    "name:und_x_variant":[
        "\u0428\u0430\u0431\u0443\u043d\u0438\u0445\u0430"
    ],
    "wof:name":"Shabunikha",
    "wof:placetype":"locality"
},
  "geometry": {"coordinates":[30.8017,56.5941],"type":"Point"}
}