{
  "type": "Feature",
  "properties": {
    "gn:admin1_code":"67.0",
    "gn:asciiname":"Bol'shaya Dmitriyevka",
    "gn:country_code":"RU",
    "gn:dem":137,
    "gn:feature_class":"P",
    "gn:feature_code":"PPL",
    "gn:name":"Bol\u2019shaya Dmitriyevka",
    "gn:population":0,
    "gn:timezone":"Europe/Saratov",
    "iso:country":"RU",
    "name:rus_x_preferred":[
        "\u0411\u043e\u043b\u044c\u0448\u0430\u044f \u0414\u043c\u0438\u0442\u0440\u0438\u0435\u0432\u043a\u0430"
    ],
    "name:und_x_variant":[
        "Bolshe Dmitrevka",
        "Bol\u2019shaya Dmitriyevka",
        "\u0411\u043e\u043b\u044c\u0448\u0430\u044f \u0414\u043c\u0438\u0442\u0440\u0438\u0435\u0432\u043a\u0430"
    ],
    "wof:name":"Bol'shaya Dmitriyevka",
    "wof:placetype":"locality"
},
  "geometry": {"coordinates":[45.25627,51.34749],"type":"Point"}
}