{
  "type": "Feature",
  "properties": {
    "gn:admin1_code":"73",
    "gn:asciiname":"Surovka",
    "gn:country_code":"RU",
    "gn:dem":105,
    "gn:feature_class":"P",
    "gn:feature_code":"PPL",
    "gn:name":"Surovka",
    "gn:population":0,
    "gn:timezone":"Europe/Moscow",
    "iso:country":"RU",
    "name:rus_x_preferred":[
        "\u0421\u0443\u0440\u043e\u0432\u043a\u0430"
    ],
    "name:und_x_variant":[
        "\u0421\u0443\u0440\u043e\u0432\u043a\u0430"
    ],
    "wof:name":"Surovka",
    "wof:placetype":"locality"
},
  "geometry": {"coordinates":[52.3866,55.6281],"type":"Point"}
}