{
  "type": "Feature",
  "properties": {
    "gn:admin1_code":"41.0",
    "gn:asciiname":"Myasnyankino",
    "gn:country_code":"RU",
    "gn:dem":178,
    "gn:feature_class":"P",
    "gn:feature_code":"PPL",
    "gn:name":"Myasnyankino",
    "gn:population":0,
    "gn:timezone":"Europe/Moscow",
    "iso:country":"RU",
    "name:rus_x_preferred":[
        "\u041c\u044f\u0441\u044f\u043d\u043a\u0438\u043d\u043e"
    ],
    "wof:name":"Myasnyankino",
    "wof:placetype":"locality"
},
  "geometry": {"coordinates":[37.2478,51.7677],"type":"Point"}
}