{
  "type": "Feature",
  "properties": {
    "gn:admin1_code":"38",
    "gn:asciiname":"Sobolevskiy",
    "gn:country_code":"RU",
    "gn:dem":2,
    "gn:feature_class":"P",
    "gn:feature_code":"PPL",
    "gn:name":"Sobolevskiy",
    "gn:population":0,
    "gn:timezone":"Europe/Moscow",
    "iso:country":"RU",
    "name:eng_x_preferred":[
        "Sobolevskiy"
    ],
    "name:nor_x_preferred":[
        "Sobolevskij"
    ],
    "name:rus_x_preferred":[
        "\u0421\u043e\u0431\u043e\u043b\u0435\u0432\u0441\u043a\u0438\u0439"
    ],
    "name:und_x_variant":[
        "\u0421\u043e\u0431\u043e\u043b\u0435\u0432\u0441\u043a\u0438\u0439",
        "Sobolevskiy"
    ],
    "wof:name":"Sobolevskiy",
    "wof:placetype":"locality"
},
  "geometry": {"coordinates":[37.93538,45.14895],"type":"Point"}
}