{
  "type": "Feature",
  "properties": {
    "gn:admin1_code":"8",
    "gn:asciiname":"Nizhniye Termy",
    "gn:country_code":"RU",
    "gn:dem":138,
    "gn:feature_class":"P",
    "gn:feature_code":"PPL",
    "gn:name":"Nizhniye Termy",
    "gn:population":0,
    "gn:timezone":"Asia/Yekaterinburg",
    "iso:country":"RU",
    "name:rus_x_preferred":[
        "\u041d\u0438\u0436\u043d\u0438\u0435 \u0422\u0435\u0440\u043c\u044b"
    ],
    "wof:name":"Nizhniye Termy",
    "wof:placetype":"locality"
},
  "geometry": {"coordinates":[55.26204,54.59342],"type":"Point"}
}