{
  "type": "Feature",
  "properties": {
    "gn:admin1_code":"77",
    "gn:asciiname":"Kishkino",
    "gn:country_code":"RU",
    "gn:dem":151,
    "gn:feature_class":"P",
    "gn:feature_code":"PPL",
    "gn:name":"Kishkino",
    "gn:population":0,
    "gn:timezone":"Europe/Moscow",
    "iso:country":"RU",
    "name:rus_x_preferred":[
        "\u041a\u0438\u0448\u043a\u0438\u043d\u043e"
    ],
    "wof:name":"Kishkino",
    "wof:placetype":"locality"
},
  "geometry": {"coordinates":[37.1887,58.515],"type":"Point"}
}