{
  "type": "Feature",
  "properties": {
    "gn:admin1_code":"42.0",
    "gn:asciiname":"Smolka",
    "gn:country_code":"RU",
    "gn:dem":18,
    "gn:feature_class":"P",
    "gn:feature_code":"PPL",
    "gn:name":"Smolka",
    "gn:population":0,
    "gn:timezone":"Europe/Tallinn",
    "iso:country":"RU",
    "name:fin_x_preferred":[
        "Tervala"
    ],
    "wof:name":"Smolka",
    "wof:placetype":"locality"
},
  "geometry": {"coordinates":[28.13204,59.43686999999999],"type":"Point"}
}