{
  "type": "Feature",
  "properties": {
    "gn:admin1_code":"41.0",
    "gn:asciiname":"Chernikovy Dvory",
    "gn:country_code":"RU",
    "gn:dem":254,
    "gn:feature_class":"P",
    "gn:feature_code":"PPL",
    "gn:name":"Chernikovy Dvory",
    "gn:population":0,
    "gn:timezone":"Europe/Moscow",
    "iso:country":"RU",
    "name:rus_x_preferred":[
        "\u0427\u0435\u0440\u043d\u0438\u043a\u043e\u0432\u044b \u0414\u0432\u043e\u0440\u044b"
    ],
    "wof:name":"Chernikovy Dvory",
    "wof:placetype":"locality"
},
  "geometry": {"coordinates":[37.07861,51.55917],"type":"Point"}
}