{
  "type": "Feature",
  "properties": {
    "gn:admin1_code":"9",
    "gn:asciiname":"Ploskoye",
    "gn:country_code":"RU",
    "gn:dem":131,
    "gn:feature_class":"P",
    "gn:feature_code":"PPL",
    "gn:name":"Ploskoye",
    "gn:population":0,
    "gn:timezone":"Europe/Moscow",
    "iso:country":"RU",
    "name:rus_x_preferred":[
        "\u041f\u043b\u043e\u0441\u043a\u043e\u0435"
    ],
    "name:und_x_variant":[
        "\u041f\u043b\u043e\u0441\u043a\u043e\u0435"
    ],
    "wof:name":"Ploskoye",
    "wof:placetype":"locality"
},
  "geometry": {"coordinates":[37.012,50.7341],"type":"Point"}
}