{
  "type": "Feature",
  "properties": {
    "gn:admin1_code":"85",
    "gn:asciiname":"Luk'yanovo",
    "gn:country_code":"RU",
    "gn:dem":130,
    "gn:feature_class":"P",
    "gn:feature_code":"PPL",
    "gn:name":"Luk\u2019yanovo",
    "gn:population":0,
    "gn:timezone":"Europe/Moscow",
    "iso:country":"RU",
    "name:rus_x_preferred":[
        "\u041b\u0443\u043a\u044c\u044f\u043d\u043e\u0432\u043e"
    ],
    "name:und_x_variant":[
        "Luk\u2019yanovo",
        "\u041b\u0443\u043a\u044c\u044f\u043d\u043e\u0432\u043e"
    ],
    "wof:name":"Luk'yanovo",
    "wof:placetype":"locality"
},
  "geometry": {"coordinates":[38.0082,60.2785],"type":"Point"}
}