{
  "type": "Feature",
  "properties": {
    "gn:admin1_code":"33",
    "gn:asciiname":"Ivaty",
    "gn:country_code":"RU",
    "gn:dem":117,
    "gn:feature_class":"P",
    "gn:feature_code":"PPL",
    "gn:name":"Ivaty",
    "gn:population":0,
    "gn:timezone":"Europe/Kirov",
    "iso:country":"RU",
    "name:rus_x_preferred":[
        "\u0418\u0432\u0430\u0442\u044b"
    ],
    "wof:name":"Ivaty",
    "wof:placetype":"locality"
},
  "geometry": {"coordinates":[47.8422,57.6455],"type":"Point"}
}