{
  "type": "Feature",
  "properties": {
    "gn:admin1_code":"42",
    "gn:asciiname":"Turovo",
    "gn:country_code":"RU",
    "gn:dem":62,
    "gn:feature_class":"P",
    "gn:feature_code":"PPL",
    "gn:name":"Turovo",
    "gn:population":0,
    "gn:timezone":"Europe/Moscow",
    "iso:country":"RU",
    "name:eng_x_preferred":[
        "Turovo"
    ],
    "name:nor_x_preferred":[
        "Turovo"
    ],
    "name:rus_x_preferred":[
        "\u0422\u0443\u0440\u043e\u0432\u043e"
    ],
    "wof:name":"Turovo",
    "wof:placetype":"locality"
},
  "geometry": {"coordinates":[29.93706,58.73995],"type":"Point"}
}