{
  "type": "Feature",
  "properties": {
    "gn:admin1_code":"68.0",
    "gn:asciiname":"Tsus",
    "gn:country_code":"RU",
    "gn:dem":1290,
    "gn:feature_class":"P",
    "gn:feature_code":"PPL",
    "gn:name":"Tsus",
    "gn:population":0,
    "gn:timezone":"Europe/Moscow",
    "iso:country":"RU",
    "wof:name":"Tsus",
    "wof:placetype":"locality"
},
  "geometry": {"coordinates":[44.07667,42.84556],"type":"Point"}
}