{
  "type": "Feature",
  "properties": {
    "gn:admin1_code":"71",
    "gn:asciiname":"Bashkarka",
    "gn:country_code":"RU",
    "gn:dem":207,
    "gn:feature_class":"P",
    "gn:feature_code":"PPL",
    "gn:name":"Bashkarka",
    "gn:population":0,
    "gn:timezone":"Asia/Yekaterinburg",
    "iso:country":"RU",
    "name:eng_x_preferred":[
        "Bashkarka"
    ],
    "name:rus_x_preferred":[
        "\u041d\u043e\u0432.\u0411\u0430\u0448\u043a\u0430\u0440\u043a\u0430"
    ],
    "name:rus_x_variant":[
        "\u0411\u0430\u0448\u043a\u0430\u0440\u043a\u0430"
    ],
    "name:und_x_variant":[
        "Staraya Bashkarka",
        "Staro-Bashkarskoye",
        "\u0411\u0430\u0448\u043a\u0430\u0440\u043a\u0430",
        "Bashkarka"
    ],
    "wof:name":"Bashkarka",
    "wof:placetype":"locality"
},
  "geometry": {"coordinates":[60.8852,57.628],"type":"Point"}
}