{
  "type": "Feature",
  "properties": {
    "gn:admin1_code":"8",
    "gn:asciiname":"Staronadezhdino",
    "gn:country_code":"RU",
    "gn:dem":124,
    "gn:feature_class":"P",
    "gn:feature_code":"PPL",
    "gn:name":"Staronadezhdino",
    "gn:population":0,
    "gn:timezone":"Asia/Yekaterinburg",
    "iso:country":"RU",
    "name:eng_x_preferred":[
        "Staronadezhdino"
    ],
    "name:nor_x_preferred":[
        "Staronadezjdino"
    ],
    "name:rus_x_preferred":[
        "\u0421\u0442\u0430\u0440\u043e\u043d\u0430\u0434\u0435\u0436\u0434\u0438\u043d\u043e"
    ],
    "name:und_x_variant":[
        "Nadezhdino",
        "\u0421\u0442\u0430\u0440\u043e\u043d\u0430\u0434\u0435\u0436\u0434\u0438\u043d\u043e",
        "Staronadezhdino"
    ],
    "wof:name":"Staronadezhdino",
    "wof:placetype":"locality"
},
  "geometry": {"coordinates":[56.45239,55.2178],"type":"Point"}
}