{
  "type": "Feature",
  "properties": {
    "gn:admin1_code":"8",
    "gn:asciiname":"Staronadezhdino",
    "gn:country_code":"RU",
    "gn:dem":124,
    "gn:feature_class":"P",
    "gn:feature_code":"PPL",
    "gn:name":"Staronadezhdino",
    "gn:population":0,
    "gn:timezone":"Asia/Yekaterinburg",
    "iso:country":"RU",
    "name:bak_x_preferred":[
        "\u0418\u04ab\u043a\u0435 \u041d\u0430\u0434\u0435\u0436\u0434\u0438\u043d"
    ],
    "name:che_x_preferred":[
        "\u0421\u0442\u0430\u0440\u043e\u043d\u0430\u0434\u0435\u0436\u0434\u0438\u043d\u043e"
    ],
    "name:eng_x_preferred":[
        "Staronadezhdino"
    ],
    "name:hye_x_preferred":[
        "\u054d\u057f\u0561\u0580\u0578\u0576\u0561\u0564\u0565\u056a\u0564\u056b\u0576\u0578"
    ],
    "name:kaz_x_preferred":[
        "\u0415\u0441\u043a\u0456 \u043d\u0430\u0434\u0435\u0436\u0434\u0438\u043d\u043e"
    ],
    "name:kir_x_preferred":[
        "\u042d\u0441\u043a\u0438 \u043d\u0430\u0434\u0435\u0436\u0434\u0438\u043d\u043e"
    ],
    "name:mhr_x_preferred":[
        "\u0421\u0430\u0440\u043d\u0430\u044f\u0437"
    ],
    "name:nor_x_preferred":[
        "Staronadezjdino"
    ],
    "name:rus_x_preferred":[
        "\u0421\u0442\u0430\u0440\u043e\u043d\u0430\u0434\u0435\u0436\u0434\u0438\u043d\u043e"
    ],
    "name:tat_x_preferred":[
        "\u0418\u0441\u043a\u0435 \u041d\u0430\u0434\u0435\u0436\u0434\u0438\u043d\u043e"
    ],
    "name:und_x_variant":[
        "Nadezhdino"
    ],
    "wof:name":"Staronadezhdino",
    "wof:placetype":"locality"
},
  "geometry": {"coordinates":[56.45239,55.2178],"type":"Point"}
}