{
  "type": "Feature",
  "properties": {
    "gn:admin1_code":"59.0",
    "gn:asciiname":"Kuguki",
    "gn:country_code":"RU",
    "gn:dem":42,
    "gn:feature_class":"P",
    "gn:feature_code":"PPL",
    "gn:name":"Kuguki",
    "gn:population":0,
    "gn:timezone":"Asia/Vladivostok",
    "iso:country":"RU",
    "name:rus_x_preferred":[
        "\u041a\u0443\u0433\u0443\u043a\u0438"
    ],
    "wof:name":"Kuguki",
    "wof:placetype":"locality"
},
  "geometry": {"coordinates":[131.79899,43.75183],"type":"Point"}
}