{
  "type": "Feature",
  "properties": {
    "gn:admin1_code":"10",
    "gn:asciiname":"Mars",
    "gn:country_code":"RU",
    "gn:dem":155,
    "gn:feature_class":"P",
    "gn:feature_code":"PPL",
    "gn:name":"Mars",
    "gn:population":0,
    "gn:timezone":"Europe/Moscow",
    "iso:country":"RU",
    "name:rus_x_preferred":[
        "\u041c\u0430\u0440\u0441"
    ],
    "name:und_x_variant":[
        "\u041c\u0430\u0440\u0441"
    ],
    "wof:name":"Mars",
    "wof:placetype":"locality"
},
  "geometry": {"coordinates":[32.13256,52.96505],"type":"Point"}
}