{
  "type": "Feature",
  "properties": {
    "gn:admin1_code":"38.0",
    "gn:asciiname":"Chvizhepse",
    "gn:country_code":"RU",
    "gn:dem":224,
    "gn:feature_class":"P",
    "gn:feature_code":"PPL",
    "gn:name":"Chvizhepse",
    "gn:population":0,
    "gn:timezone":"Europe/Moscow",
    "iso:country":"RU",
    "name:rus_x_preferred":[
        "\u0427\u0432\u0438\u0436\u0435\u043f\u0441\u0435"
    ],
    "name:und_x_variant":[
        "Chvezhipse",
        "Chvizhepse",
        "\u0427\u0432\u0438\u0436\u0435\u043f\u0441\u0435"
    ],
    "wof:name":"Chvizhepse",
    "wof:placetype":"locality"
},
  "geometry": {"coordinates":[40.08545,43.63253],"type":"Point"}
}