{
  "type": "Feature",
  "properties": {
    "gn:admin1_code":"56",
    "gn:asciiname":"Polzovo",
    "gn:country_code":"RU",
    "gn:dem":203,
    "gn:feature_class":"P",
    "gn:feature_code":"PPL",
    "gn:name":"Polzovo",
    "gn:population":0,
    "gn:timezone":"Europe/Moscow",
    "iso:country":"RU",
    "name:rus_x_preferred":[
        "\u041f\u043e\u043b\u0437\u043e\u0432\u043e"
    ],
    "wof:name":"Polzovo",
    "wof:placetype":"locality"
},
  "geometry": {"coordinates":[36.12112,53.16316],"type":"Point"}
}