{
  "type": "Feature",
  "properties": {
    "gn:admin1_code":"93",
    "gn:asciiname":"Karpovka",
    "gn:country_code":"RU",
    "gn:dem":686,
    "gn:feature_class":"P",
    "gn:feature_code":"PPL",
    "gn:name":"Karpovka",
    "gn:population":0,
    "gn:timezone":"Asia/Chita",
    "iso:country":"RU",
    "name:eng_x_preferred":[
        "Karpovka"
    ],
    "name:nor_x_preferred":[
        "Karpovka"
    ],
    "name:rus_x_preferred":[
        "\u041a\u0430\u0440\u043f\u043e\u0432\u043a\u0430"
    ],
    "name:und_x_variant":[
        "Popovskoye",
        "Karpovo",
        "Popova",
        "Karpovka"
    ],
    "wof:name":"Karpovka",
    "wof:placetype":"locality"
},
  "geometry": {"coordinates":[113.53440000000001,52.20837],"type":"Point"}
}