{
  "type": "Feature",
  "properties": {
    "gn:admin1_code":"17",
    "gn:asciiname":"Tagirkent-Kazmalyar",
    "gn:country_code":"RU",
    "gn:dem":42,
    "gn:feature_class":"P",
    "gn:feature_code":"PPL",
    "gn:name":"Tagirkent-Kazmalyar",
    "gn:population":0,
    "gn:timezone":"Europe/Moscow",
    "iso:country":"RU",
    "name:aze_x_preferred":[
        "Tagirk\u0259nd-Qazmalar"
    ],
    "name:aze_x_variant":[
        "Tahirk\u0259nd-Qazmalar",
        "Tahirkand Qazmalar"
    ],
    "name:eng_x_preferred":[
        "Tagirkent-Kazmalyar"
    ],
    "name:nor_x_preferred":[
        "Tagirkent-Kazmaljar"
    ],
    "name:rus_x_preferred":[
        "\u0422\u0430\u0433\u0438\u0440\u043a\u0435\u043d\u0442-\u041a\u0430\u0437\u043c\u0430\u043b\u044f\u0440"
    ],
    "name:und_x_variant":[
        "Tairkend",
        "Tagirkent-Kazmalyar"
    ],
    "wof:name":"Tagirkent-Kazmalyar",
    "wof:placetype":"locality"
},
  "geometry": {"coordinates":[48.50804,41.81548],"type":"Point"}
}