{
  "type": "Feature",
  "properties": {
    "gn:admin1_code":"77",
    "gn:asciiname":"Koreni",
    "gn:cc2":"RU",
    "gn:country_code":"RU",
    "gn:dem":222,
    "gn:feature_class":"P",
    "gn:feature_code":"PPL",
    "gn:name":"Koreni",
    "gn:population":0,
    "gn:timezone":"Europe/Moscow",
    "iso:country":"RU",
    "name:rus_x_preferred":[
        "\u041a\u043e\u0440\u0435\u043d\u0438"
    ],
    "name:und_x_variant":[
        "Kareni",
        "Koreni",
        "\u041a\u043e\u0440\u0435\u043d\u0438"
    ],
    "wof:name":"Koreni",
    "wof:placetype":"locality"
},
  "geometry": {"coordinates":[31.66667,56.68333000000001],"type":"Point"}
}