{
  "type": "Feature",
  "properties": {
    "gn:admin1_code":"37.0",
    "gn:asciiname":"Bol'shaya Talitsa",
    "gn:country_code":"RU",
    "gn:dem":126,
    "gn:feature_class":"P",
    "gn:feature_code":"PPL",
    "gn:name":"Bol\u2019shaya Talitsa",
    "gn:population":0,
    "gn:timezone":"Europe/Moscow",
    "iso:country":"RU",
    "name:rus_x_preferred":[
        "\u0411\u043e\u043b\u044c\u0448\u0430\u044f \u0422\u0430\u043b\u0438\u0446\u0430"
    ],
    "name:und_x_variant":[
        "Bol\u2019shaya Talitsa"
    ],
    "wof:name":"Bol'shaya Talitsa",
    "wof:placetype":"locality"
},
  "geometry": {"coordinates":[45.57502,58.48054000000001],"type":"Point"}
}