{
  "type": "Feature",
  "properties": {
    "gn:admin1_code":"63",
    "gn:asciiname":"Urochishche Siryalyu",
    "gn:country_code":"RU",
    "gn:dem":630,
    "gn:feature_class":"P",
    "gn:feature_code":"PPL",
    "gn:name":"Urochishche Siryalyu",
    "gn:population":0,
    "gn:timezone":"Asia/Vladivostok",
    "iso:country":"RU",
    "wof:name":"Urochishche Siryalyu",
    "wof:placetype":"locality"
},
  "geometry": {"coordinates":[132.98333,65.90000000000001],"type":"Point"}
}