{
  "type": "Feature",
  "properties": {
    "gn:admin1_code":"80.0",
    "gn:asciiname":"Chernovo",
    "gn:country_code":"RU",
    "gn:dem":131,
    "gn:feature_class":"P",
    "gn:feature_code":"PPL",
    "gn:name":"Chernovo",
    "gn:population":0,
    "gn:timezone":"Europe/Samara",
    "iso:country":"RU",
    "name:eng_x_preferred":[
        "Chernovo"
    ],
    "name:nor_x_preferred":[
        "Tsjernovo"
    ],
    "name:rus_x_preferred":[
        "\u0427\u0435\u0440\u043d\u043e\u0432\u043e"
    ],
    "name:und_x_variant":[
        "Chernova",
        "\u0427\u0435\u0440\u043d\u043e\u0432\u043e",
        "Chernovo"
    ],
    "wof:name":"Chernovo",
    "wof:placetype":"locality"
},
  "geometry": {"coordinates":[53.60938,56.17666],"type":"Point"}
}