{
  "type": "Feature",
  "properties": {
    "gn:admin1_code":"51.0",
    "gn:asciiname":"Gorodki",
    "gn:country_code":"RU",
    "gn:dem":150,
    "gn:feature_class":"P",
    "gn:feature_code":"PPL",
    "gn:name":"Gorodki",
    "gn:population":0,
    "gn:timezone":"Europe/Moscow",
    "iso:country":"RU",
    "name:aze_x_preferred":[
        "Qorodki"
    ],
    "name:ces_x_preferred":[
        "Gorodky"
    ],
    "name:deu_x_preferred":[
        "Gorodki"
    ],
    "name:epo_x_preferred":[
        "Gorodki"
    ],
    "name:fin_x_preferred":[
        "Gorodki"
    ],
    "name:fra_x_preferred":[
        "Gorodki"
    ],
    "name:hye_x_preferred":[
        "\u0533\u0578\u0580\u0578\u0564\u056f\u056b"
    ],
    "name:kir_x_preferred":[
        "\u0413\u043e\u0440\u043e\u0434\u043a\u0438"
    ],
    "name:lav_x_preferred":[
        "Gorodki"
    ],
    "name:lit_x_preferred":[
        "Miestu\u010diai"
    ],
    "name:pol_x_preferred":[
        "Gorodki"
    ],
    "name:rus_x_preferred":[
        "\u0413\u043e\u0440\u043e\u0434\u043a\u0438"
    ],
    "wof:name":"Gorodki",
    "wof:placetype":"locality"
},
  "geometry": {"coordinates":[43.27159,54.96755],"type":"Point"}
}