{
  "type": "Feature",
  "properties": {
    "gn:admin1_code":"41",
    "gn:asciiname":"Suvolochnoye",
    "gn:country_code":"RU",
    "gn:dem":179,
    "gn:feature_class":"P",
    "gn:feature_code":"PPL",
    "gn:name":"Suvolochnoye",
    "gn:population":0,
    "gn:timezone":"Europe/Moscow",
    "iso:country":"RU",
    "name:rus_x_preferred":[
        "\u0421\u0443\u0432\u043e\u043b\u043e\u0447\u043d\u043e\u0435"
    ],
    "name:und_x_variant":[
        "Sulachnaya"
    ],
    "wof:name":"Suvolochnoye",
    "wof:placetype":"locality"
},
  "geometry": {"coordinates":[37.0226,51.3749],"type":"Point"}
}