{
  "type": "Feature",
  "properties": {
    "gn:admin1_code":"72.0",
    "gn:asciiname":"Cheboksary",
    "gn:country_code":"RU",
    "gn:dem":171,
    "gn:feature_class":"P",
    "gn:feature_code":"PPL",
    "gn:name":"Cheboksary",
    "gn:population":0,
    "gn:timezone":"Europe/Moscow",
    "iso:country":"RU",
    "name:rus_x_preferred":[
        "\u0427\u0435\u0431\u043e\u043a\u0441\u0430\u0440\u044b"
    ],
    "name:und_x_variant":[
        "Sukhoverkovo",
        "Cheboksary",
        "\u0427\u0435\u0431\u043e\u043a\u0441\u0430\u0440\u044b"
    ],
    "wof:name":"Cheboksary",
    "wof:placetype":"locality"
},
  "geometry": {"coordinates":[40.9679,52.8728],"type":"Point"}
}