{
  "type": "Feature",
  "properties": {
    "gn:admin1_code":"71",
    "gn:asciiname":"Myagkovo",
    "gn:country_code":"RU",
    "gn:dem":60,
    "gn:feature_class":"P",
    "gn:feature_code":"PPL",
    "gn:name":"Myagkovo",
    "gn:population":0,
    "gn:timezone":"Asia/Yekaterinburg",
    "iso:country":"RU",
    "name:rus_x_preferred":[
        "\u041c\u044f\u0433\u043a\u043e\u0432\u043e"
    ],
    "name:und_x_variant":[
        "Myagkova",
        "Myagkovo"
    ],
    "wof:name":"Myagkovo",
    "wof:placetype":"locality"
},
  "geometry": {"coordinates":[64.74514000000001,58.46211],"type":"Point"}
}