{
  "type": "Feature",
  "properties": {
    "gn:admin1_code":"85",
    "gn:asciiname":"Ionino",
    "gn:country_code":"RU",
    "gn:dem":157,
    "gn:feature_class":"P",
    "gn:feature_code":"PPL",
    "gn:name":"Ionino",
    "gn:population":0,
    "gn:timezone":"Europe/Moscow",
    "iso:country":"RU",
    "name:rus_x_preferred":[
        "\u0418\u043e\u043d\u0438\u043d\u043e"
    ],
    "name:und_x_variant":[
        "\u0418\u043e\u043d\u0438\u043d\u043e"
    ],
    "wof:name":"Ionino",
    "wof:placetype":"locality"
},
  "geometry": {"coordinates":[36.2126,59.93599],"type":"Point"}
}