{
  "type": "Feature",
  "properties": {
    "gn:admin1_code":"40",
    "gn:asciiname":"Stepnoye",
    "gn:country_code":"RU",
    "gn:dem":94,
    "gn:feature_class":"P",
    "gn:feature_code":"PPL",
    "gn:name":"Stepnoye",
    "gn:population":0,
    "gn:timezone":"Asia/Yekaterinburg",
    "iso:country":"RU",
    "name:eng_x_preferred":[
        "Stepnoye"
    ],
    "name:nor_x_preferred":[
        "Stepnoje"
    ],
    "name:rus_x_preferred":[
        "\u0421\u0442\u0435\u043f\u043d\u043e\u0435"
    ],
    "wof:name":"Stepnoye",
    "wof:placetype":"locality"
},
  "geometry": {"coordinates":[64.80333,55.07778],"type":"Point"}
}