{
  "type": "Feature",
  "properties": {
    "gn:admin1_code":"13",
    "gn:asciiname":"Tsentral'nyy",
    "gn:country_code":"RU",
    "gn:dem":399,
    "gn:feature_class":"P",
    "gn:feature_code":"PPL",
    "gn:name":"Tsentral\u2019nyy",
    "gn:population":0,
    "gn:timezone":"Asia/Yekaterinburg",
    "iso:country":"RU",
    "name:eng_x_preferred":[
        "Tsentral'nyy"
    ],
    "name:nor_x_preferred":[
        "Tsentralnyj"
    ],
    "name:rus_x_preferred":[
        "\u0426\u0435\u043d\u0442\u0440\u0430\u043b\u044c\u043d\u044b\u0439"
    ],
    "name:und_x_variant":[
        "Tsentral\u2019nyy"
    ],
    "wof:name":"Tsentral'nyy",
    "wof:placetype":"locality"
},
  "geometry": {"coordinates":[59.39333000000001,55.18167],"type":"Point"}
}