{
  "type": "Feature",
  "properties": {
    "gn:admin1_code":"84.0",
    "gn:asciiname":"Bogatyrev",
    "gn:country_code":"RU",
    "gn:dem":28,
    "gn:feature_class":"P",
    "gn:feature_code":"PPL",
    "gn:name":"Bogatyr\u00ebv",
    "gn:population":0,
    "gn:timezone":"Europe/Volgograd",
    "iso:country":"RU",
    "name:rus_x_preferred":[
        "\u0411\u043e\u0433\u0430\u0442\u044b\u0440\u0451\u0432"
    ],
    "name:und_x_variant":[
        "Bogatyr\u00ebv",
        "\u0411\u043e\u0433\u0430\u0442\u044b\u0440\u0451\u0432"
    ],
    "wof:name":"Bogatyrev",
    "wof:placetype":"locality"
},
  "geometry": {"coordinates":[45.81667,49.81667],"type":"Point"}
}