{
  "type": "Feature",
  "properties": {
    "gn:admin1_code":"10",
    "gn:asciiname":"Vodvinka",
    "gn:country_code":"RU",
    "gn:dem":197,
    "gn:feature_class":"P",
    "gn:feature_code":"PPL",
    "gn:name":"Vodvinka",
    "gn:population":0,
    "gn:timezone":"Europe/Moscow",
    "iso:country":"RU",
    "name:rus_x_preferred":[
        "\u0412\u043e\u0434\u0432\u0438\u043d\u043a\u0430"
    ],
    "name:und_x_variant":[
        "Vodvino",
        "Vodvinka",
        "\u0412\u043e\u0434\u0432\u0438\u043d\u043a\u0430"
    ],
    "wof:name":"Vodvinka",
    "wof:placetype":"locality"
},
  "geometry": {"coordinates":[32.96617,52.8309],"type":"Point"}
}