{
  "type": "Feature",
  "properties": {
    "gn:admin1_code":"85.0",
    "gn:asciiname":"Okhotinskaya",
    "gn:country_code":"RU",
    "gn:dem":165,
    "gn:feature_class":"P",
    "gn:feature_code":"PPL",
    "gn:name":"Okhotinskaya",
    "gn:population":0,
    "gn:timezone":"Europe/Moscow",
    "iso:country":"RU",
    "name:rus_x_preferred":[
        "\u041e\u0445\u043e\u0442\u0438\u043d\u0441\u043a\u0430\u044f"
    ],
    "wof:name":"Okhotinskaya",
    "wof:placetype":"locality"
},
  "geometry": {"coordinates":[41.708,60.7888],"type":"Point"}
}