{
  "type": "Feature",
  "properties": {
    "gn:admin1_code":"73",
    "gn:asciiname":"Ishal'kino",
    "gn:country_code":"RU",
    "gn:dem":128,
    "gn:feature_class":"P",
    "gn:feature_code":"PPL",
    "gn:name":"Ishal\u2019kino",
    "gn:population":0,
    "gn:timezone":"Europe/Moscow",
    "iso:country":"RU",
    "name:rus_x_preferred":[
        "\u0418\u0448\u0430\u043b\u044c\u043a\u0438\u043d\u043e"
    ],
    "name:und_x_variant":[
        "Ishal\u2019kino"
    ],
    "wof:name":"Ishal'kino",
    "wof:placetype":"locality"
},
  "geometry": {"coordinates":[50.74131,55.06087],"type":"Point"}
}