{
  "type": "Feature",
  "properties": {
    "gn:admin1_code":"8",
    "gn:asciiname":"Lentovka",
    "gn:country_code":"RU",
    "gn:dem":163,
    "gn:feature_class":"P",
    "gn:feature_code":"PPL",
    "gn:name":"Lentovka",
    "gn:population":0,
    "gn:timezone":"Asia/Yekaterinburg",
    "iso:country":"RU",
    "name:rus_x_preferred":[
        "\u041b\u0435\u043d\u0442\u043e\u0432\u043a\u0430"
    ],
    "wof:name":"Lentovka",
    "wof:placetype":"locality"
},
  "geometry": {"coordinates":[55.72525,54.488],"type":"Point"}
}