{
  "type": "Feature",
  "properties": {
    "gn:admin1_code":"45.0",
    "gn:asciiname":"Pomashsola-Vonzhepol'",
    "gn:country_code":"RU",
    "gn:dem":152,
    "gn:feature_class":"P",
    "gn:feature_code":"PPL",
    "gn:name":"Pomashsola-Vonzhepol\u2019",
    "gn:population":0,
    "gn:timezone":"Europe/Moscow",
    "iso:country":"RU",
    "name:rus_x_preferred":[
        "\u041f\u043e\u043c\u0430\u0448\u0441\u043e\u043b\u0430-\u0412\u043e\u043d\u0436\u0435\u043f\u043e\u043b\u044c"
    ],
    "name:und_x_variant":[
        "Pomashsola-Vonzhepol\u2019"
    ],
    "wof:name":"Pomashsola-Vonzhepol'",
    "wof:placetype":"locality"
},
  "geometry": {"coordinates":[48.63472,56.35471999999999],"type":"Point"}
}