{
  "type": "Feature",
  "properties": {
    "gn:admin1_code":"53",
    "gn:asciiname":"Novogeorgiyevka",
    "gn:country_code":"RU",
    "gn:dem":117,
    "gn:feature_class":"P",
    "gn:feature_code":"PPL",
    "gn:name":"Novogeorgiyevka",
    "gn:population":0,
    "gn:timezone":"Asia/Novosibirsk",
    "iso:country":"RU",
    "name:eng_x_preferred":[
        "Novogeorgiyevka"
    ],
    "name:nor_x_preferred":[
        "Novogeorgijevka"
    ],
    "name:rus_x_preferred":[
        "\u041d\u043e\u0432\u043e\u0433\u0435\u043e\u0440\u0433\u0438\u0435\u0432\u043a\u0430"
    ],
    "name:und_x_variant":[
        "Novogeorgiyevskiy"
    ],
    "wof:name":"Novogeorgiyevka",
    "wof:placetype":"locality"
},
  "geometry": {"coordinates":[83.96120000000001,55.7726],"type":"Point"}
}