{
  "type": "Feature",
  "properties": {
    "gn:country":"RU",
    "gn:fcode":"PPL",
    "gn:pop":13429,
    "iso:country":"RU",
    "name:ara_x_preferred":[
        "\u0632\u0627\u0648\u0632\u064a\u0648\u0631\u0633\u0643"
    ],
    "name:azb_x_preferred":[
        "\u0632\u0627\u0626\u0648\u0632\u06cc\u0648\u0631\u0633\u06a9"
    ],
    "name:aze_x_preferred":[
        "Zaozyorsk"
    ],
    "name:bel_x_preferred":[
        "\u0417\u0430\u0430\u0437\u0451\u0440\u0441\u043a"
    ],
    "name:bul_x_preferred":[
        "\u0417\u0430\u043e\u0437\u044c\u043e\u0440\u0441\u043a"
    ],
    "name:cat_x_preferred":[
        "Zaozyorsk"
    ],
    "name:ceb_x_preferred":[
        "Zaoz\u00ebrsk"
    ],
    "name:ces_x_preferred":[
        "Zaozjorsk"
    ],
    "name:che_x_preferred":[
        "\u0417\u0430\u043e\u0437\u0451\u0440\u0441\u043a"
    ],
    "name:dan_x_preferred":[
        "Zaozyorsk"
    ],
    "name:deu_x_preferred":[
        "Saosjorsk"
    ],
    "name:ell_x_preferred":[
        "\u0396\u03b1\u03bf\u03b6\u03b9\u03cc\u03c1\u03c3\u03ba"
    ],
    "name:eng_x_preferred":[
        "Zaozyorsk"
    ],
    "name:epo_x_preferred":[
        "Zaozjorsk"
    ],
    "name:fas_x_preferred":[
        "\u0632\u0627\u0626\u0648\u0632\u06cc\u0648\u0631\u0633\u06a9"
    ],
    "name:fin_x_preferred":[
        "Zaozjorsk"
    ],
    "name:fra_x_preferred":[
        "Zaoziorsk"
    ],
    "name:hsb_x_preferred":[
        "Zaozjorsk"
    ],
    "name:hun_x_preferred":[
        "Zaozjorszk"
    ],
    "name:ita_x_preferred":[
        "Zaoz\u00ebrsk"
    ],
    "name:kor_x_preferred":[
        "\uc790\uc624\uc870\ub974\uc2a4\ud06c"
    ],
    "name:lit_x_preferred":[
        "Zaoziorskas"
    ],
    "name:nld_x_preferred":[
        "Zaozjorsk"
    ],
    "name:nno_x_preferred":[
        "Zaoziorsk"
    ],
    "name:nob_x_preferred":[
        "Zaoziorsk"
    ],
    "name:oci_x_preferred":[
        "Zaozyorsk"
    ],
    "name:pol_x_preferred":[
        "Zaoziorsk"
    ],
    "name:por_x_preferred":[
        "Zaozyorsk"
    ],
    "name:rus_x_preferred":[
        "\u0417\u0430\u043e\u0437\u0435\u0440\u0441\u043a"
    ],
    "name:rus_x_variant":[
        "\u0417\u0430\u043e\u0437\u0451\u0440\u0441\u043a"
    ],
    "name:sco_x_preferred":[
        "Zaozyorsk"
    ],
    "name:slk_x_preferred":[
        "Zaozjorsk"
    ],
    "name:srp_x_preferred":[
        "\u0417\u0430\u043e\u0437\u0458\u043e\u0440\u0441\u043a"
    ],
    "name:swe_x_preferred":[
        "Zaoziorsk"
    ],
    "name:tat_x_preferred":[
        "\u0417\u0430\u043e\u0437\u04e9\u0440\u0441\u043a"
    ],
    "name:tgl_x_preferred":[
        "Zaozyorsk"
    ],
    "name:tur_x_preferred":[
        "Zaozyorsk"
    ],
    "name:ukr_x_preferred":[
        "\u0417\u0430\u043e\u0437\u0435\u0440\u0441\u044c\u043a"
    ],
    "name:unk_x_variant":[
        "Murmansk-150"
    ],
    "name:vep_x_preferred":[
        "Zaoz\u00f6rsk"
    ],
    "name:war_x_preferred":[
        "Zaozyorsk"
    ],
    "name:zho_x_preferred":[
        "\u624e\u5967\u7126\u723e\u65af\u514b"
    ],
    "qs:name":"Zaoz\u00ebrsk",
    "qs:photos_9r":0,
    "qs:photos_sr":0,
    "qs:pop_sr":"6",
    "wd:wordcount":582,
    "wof:name":"Zaoz\u00ebrsk",
    "wof:placetype":"locality",
    "wof:population":13429
},
  "geometry": {"coordinates":[32.44761,69.40052],"type":"Point"}
}