{
  "type": "Feature",
  "properties": {
    "gn:admin1_code":"60",
    "gn:asciiname":"Pupkovo",
    "gn:country_code":"RU",
    "gn:dem":85,
    "gn:feature_class":"P",
    "gn:feature_code":"PPL",
    "gn:name":"Pupkovo",
    "gn:population":0,
    "gn:timezone":"Europe/Moscow",
    "iso:country":"RU",
    "name:rus_x_preferred":[
        "\u041f\u0443\u043f\u043a\u043e\u0432\u043e"
    ],
    "wof:name":"Pupkovo",
    "wof:placetype":"locality"
},
  "geometry": {"coordinates":[27.99308,56.92138000000001],"type":"Point"}
}