{
  "type": "Feature",
  "properties": {
    "gn:country":"RU",
    "gn:fcode":"PPL",
    "gn:pop":5514,
    "iso:country":"RU",
    "name:eng_x_preferred":[
        "Turochak"
    ],
    "name:nor_x_preferred":[
        "Turotsjak"
    ],
    "name:rus_x_preferred":[
        "\u0422\u0443\u0440\u043e\u0447\u0430\u043a"
    ],
    "name:unk_x_variant":[
        "Turochan"
    ],
    "qs:name":"Turochak",
    "qs:name_adm0":"Russia",
    "qs:name_adm1":"Altai Republic",
    "qs:photos_9k":1,
    "qs:photos_9r":1,
    "qs:photos_all":1,
    "qs:photos_sr":0,
    "qs:placetype":"Town",
    "qs:pop_sr":"5",
    "wd:wordcount":878,
    "wof:name":"Turochak",
    "wof:placetype":"locality",
    "wof:population":5514
},
  "geometry": {"coordinates":[87.1224,52.2576],"type":"Point"}
}