{
  "type": "Feature",
  "properties": {
    "gn:country":"RU",
    "gn:fcode":"PPL",
    "gn:pop":5514,
    "iso:country":"RU",
    "name:bel_x_preferred":[
        "\u0422\u0443\u0440\u0430\u0447\u0430\u043a\u0441\u043a\u0456 \u0440\u0430\u0451\u043d"
    ],
    "name:che_x_preferred":[
        "\u0422\u0443\u0440\u043e\u0447\u0430\u043a\u0430\u043d \u043a\u04c0\u043e\u0448\u0442"
    ],
    "name:deu_x_preferred":[
        "Turotschakski rajon"
    ],
    "name:eng_x_preferred":[
        "Turochak"
    ],
    "name:eng_x_variant":[
        "Turochaksky District"
    ],
    "name:est_x_preferred":[
        "Turot\u0161aki rajoon"
    ],
    "name:hun_x_preferred":[
        "Turocsaki j\u00e1r\u00e1s"
    ],
    "name:hye_x_preferred":[
        "\u054f\u0578\u0582\u0580\u0578\u0579\u0561\u0576\u057d\u056f\u056b \u0577\u0580\u057b\u0561\u0576"
    ],
    "name:ita_x_preferred":[
        "Turo\u010dakskij rajon"
    ],
    "name:nld_x_preferred":[
        "Toerotsjakskiy rayon"
    ],
    "name:nor_x_preferred":[
        "Turotsjak"
    ],
    "name:pol_x_preferred":[
        "Rejon turoczacki"
    ],
    "name:rus_x_preferred":[
        "\u0422\u0443\u0440\u043e\u0447\u0430\u043a"
    ],
    "name:rus_x_variant":[
        "\u0422\u0443\u0440\u043e\u0447\u0430\u043a\u0441\u043a\u0438\u0439 \u0440\u0430\u0439\u043e\u043d"
    ],
    "name:tur_x_preferred":[
        "Tura\u00e7ak rayonu"
    ],
    "name:ukr_x_preferred":[
        "\u0422\u0443\u0440\u043e\u0447\u0430\u0446\u044c\u043a\u0438\u0439 \u0440\u0430\u0439\u043e\u043d"
    ],
    "name:unk_x_variant":[
        "Turochan"
    ],
    "name:vie_x_preferred":[
        "Turochaksky"
    ],
    "name:zho_x_preferred":[
        "\u5716\u7f85\u6070\u514b\u65af\u57fa\u5340"
    ],
    "qs:name":"Turochak",
    "qs:name_adm0":"Russia",
    "qs:name_adm1":"Altai Republic",
    "qs:photos_9k":1,
    "qs:photos_9r":1,
    "qs:photos_all":1,
    "qs:photos_sr":0,
    "qs:placetype":"Town",
    "qs:pop_sr":"5",
    "wd:wordcount":878,
    "wof:name":"Turochak",
    "wof:placetype":"locality",
    "wof:population":5514
},
  "geometry": {"coordinates":[87.1224,52.2576],"type":"Point"}
}