{
  "type": "Feature",
  "properties": {
    "gn:admin1_code":"71",
    "gn:asciiname":"Kvartsevyy Kar'yer",
    "gn:country_code":"RU",
    "gn:dem":214,
    "gn:feature_class":"P",
    "gn:feature_code":"PPL",
    "gn:name":"Kvartsevyy Kar\u2019yer",
    "gn:population":0,
    "gn:timezone":"Asia/Yekaterinburg",
    "iso:country":"RU",
    "name:rus_x_preferred":[
        "\u041a\u0432\u0430\u0440\u0446\u0435\u0432\u044b\u0439 \u041a\u0430\u0440\u044c\u0435\u0440"
    ],
    "name:und_x_variant":[
        "Kvartsevyy Kar\u2019yer"
    ],
    "wof:name":"Kvartsevyy Kar'yer",
    "wof:placetype":"locality"
},
  "geometry": {"coordinates":[61.31100000000001,56.8599],"type":"Point"}
}