{
  "type": "Feature",
  "properties": {
    "gn:admin1_code":"84",
    "gn:asciiname":"Tarapatino",
    "gn:country_code":"RU",
    "gn:dem":120,
    "gn:feature_class":"P",
    "gn:feature_code":"PPL",
    "gn:name":"Tarapatino",
    "gn:population":0,
    "gn:timezone":"Europe/Volgograd",
    "iso:country":"RU",
    "wof:name":"Tarapatino",
    "wof:placetype":"locality"
},
  "geometry": {"coordinates":[44.54324,50.94726],"type":"Point"}
}