{
  "type": "Feature",
  "properties": {
    "gn:admin1_code":"37",
    "gn:asciiname":"Vtorunka",
    "gn:country_code":"RU",
    "gn:dem":185,
    "gn:feature_class":"P",
    "gn:feature_code":"PPL",
    "gn:name":"Vtorunka",
    "gn:population":0,
    "gn:timezone":"Europe/Moscow",
    "iso:country":"RU",
    "name:rus_x_preferred":[
        "\u0412\u0442\u043e\u0440\u0443\u043d\u043a\u0430"
    ],
    "wof:name":"Vtorunka",
    "wof:placetype":"locality"
},
  "geometry": {"coordinates":[46.3246,59.1394],"type":"Point"}
}