{
  "type": "Feature",
  "properties": {
    "gn:admin1_code":"4.0",
    "gn:asciiname":"Kazansk",
    "gn:country_code":"RU",
    "gn:dem":334,
    "gn:feature_class":"P",
    "gn:feature_code":"PPL",
    "gn:name":"Kazansk",
    "gn:population":0,
    "gn:timezone":"Asia/Barnaul",
    "iso:country":"RU",
    "name:rus_x_preferred":[
        "\u041a\u0430\u0437\u0430\u043dc\u043a"
    ],
    "name:und_x_variant":[
        "\u041a\u0430\u0437\u0430\u043dc\u043a",
        "Kazansk"
    ],
    "wof:name":"Kazansk",
    "wof:placetype":"locality"
},
  "geometry": {"coordinates":[86.6092,53.2232],"type":"Point"}
}