{
  "type": "Feature",
  "properties": {
    "gn:country":"RU",
    "gn:fcode":"PPL",
    "gn:pop":7393,
    "iso:country":"RU",
    "name:rus_x_preferred":[
        "\u041c\u0438\u0440\u043d\u044b\u0439"
    ],
    "qs:name":"Mirnyy",
    "qs:name_adm0":"Russia",
    "qs:name_adm1":"Samara Oblast",
    "qs:photos_9r":0,
    "qs:photos_sr":0,
    "qs:placetype":"Town",
    "qs:pop_sr":"5",
    "wd:wordcount":180,
    "wof:name":"Mirnyy",
    "wof:placetype":"locality",
    "wof:population":7393
},
  "geometry": {"coordinates":[50.27658,53.50642],"type":"Point"}
}