{
  "type": "Feature",
  "properties": {
    "gn:admin1_code":"46",
    "gn:asciiname":"Vodolyay",
    "gn:country_code":"RU",
    "gn:dem":122,
    "gn:feature_class":"P",
    "gn:feature_code":"PPL",
    "gn:name":"Vodolyay",
    "gn:population":0,
    "gn:timezone":"Europe/Moscow",
    "iso:country":"RU",
    "name:rus_x_preferred":[
        "\u0412\u043e\u0434\u043e\u043b\u044f\u0439"
    ],
    "wof:name":"Vodolyay",
    "wof:placetype":"locality"
},
  "geometry": {"coordinates":[42.7503,54.1558],"type":"Point"}
}