{
  "type": "Feature",
  "properties": {
    "gn:admin1_code":"33",
    "gn:asciiname":"Novyye Kokuy",
    "gn:country_code":"RU",
    "gn:dem":160,
    "gn:feature_class":"P",
    "gn:feature_code":"PPL",
    "gn:name":"Novyye Kokuy",
    "gn:population":0,
    "gn:timezone":"Europe/Kirov",
    "iso:country":"RU",
    "name:rus_x_preferred":[
        "\u041d\u043e\u0432\u044b\u0435 \u041a\u043e\u043a\u0443\u0439"
    ],
    "wof:name":"Novyye Kokuy",
    "wof:placetype":"locality"
},
  "geometry": {"coordinates":[50.7201,56.4376],"type":"Point"}
}