{
  "type": "Feature",
  "properties": {
    "gn:admin1_code":"33",
    "gn:asciiname":"Kondrat'yevo",
    "gn:country_code":"RU",
    "gn:dem":124,
    "gn:feature_class":"P",
    "gn:feature_code":"PPL",
    "gn:name":"Kondrat\u2019yevo",
    "gn:population":0,
    "gn:timezone":"Europe/Kirov",
    "iso:country":"RU",
    "name:rus_x_preferred":[
        "\u041a\u043e\u043d\u0434\u0440\u0430\u0442\u044c\u0435\u0432\u043e"
    ],
    "name:und_x_variant":[
        "Kondrat\u2019yevo"
    ],
    "wof:name":"Kondrat'yevo",
    "wof:placetype":"locality"
},
  "geometry": {"coordinates":[46.8691,57.0157],"type":"Point"}
}