{
  "type": "Feature",
  "properties": {
    "gn:admin1_code":"16",
    "gn:asciiname":"Novyye Yakhakasy",
    "gn:country_code":"RU",
    "gn:dem":179,
    "gn:feature_class":"P",
    "gn:feature_code":"PPL",
    "gn:name":"Novyye Yakhakasy",
    "gn:population":0,
    "gn:timezone":"Europe/Moscow",
    "iso:country":"RU",
    "name:rus_x_preferred":[
        "\u041d\u043e\u0432\u044b\u0435 \u042f\u0445\u0430\u043a\u0430\u0441\u044b"
    ],
    "name:und_x_variant":[
        "Novo-Yakha-Kasy",
        "Nov-Yakha-Kasy",
        "Novyye Yakhakasy",
        "\u041d\u043e\u0432\u044b\u0435 \u042f\u0445\u0430\u043a\u0430\u0441\u044b"
    ],
    "wof:name":"Novyye Yakhakasy",
    "wof:placetype":"locality"
},
  "geometry": {"coordinates":[46.98289000000001,55.51503],"type":"Point"}
}