{
  "type": "Feature",
  "properties": {
    "gn:admin1_code":"84",
    "gn:asciiname":"Verbochnyy",
    "gn:country_code":"RU",
    "gn:dem":133,
    "gn:feature_class":"P",
    "gn:feature_code":"PPL",
    "gn:name":"Verbochnyy",
    "gn:population":0,
    "gn:timezone":"Europe/Volgograd",
    "iso:country":"RU",
    "name:rus_x_preferred":[
        "\u0412\u0435\u0440\u0431\u043e\u0447\u043d\u044b\u0439"
    ],
    "wof:name":"Verbochnyy",
    "wof:placetype":"locality"
},
  "geometry": {"coordinates":[42.5543,50.7749],"type":"Point"}
}