{
  "type": "Feature",
  "properties": {
    "gn:admin1_code":"20",
    "gn:asciiname":"Rybinsk",
    "gn:country_code":"RU",
    "gn:dem":230,
    "gn:feature_class":"P",
    "gn:feature_code":"PPL",
    "gn:name":"Rybinsk",
    "gn:population":0,
    "gn:timezone":"Asia/Irkutsk",
    "iso:country":"RU",
    "name:eng_x_preferred":[
        "Rybinskiy"
    ],
    "name:nor_x_preferred":[
        "Rybinsk"
    ],
    "name:rus_x_preferred":[
        "\u0420\u044b\u0431\u0438\u043d\u0441\u043a"
    ],
    "name:und_x_variant":[
        "Rybinskiy",
        "Rybinsk"
    ],
    "wof:name":"Rybinsk",
    "wof:placetype":"locality"
},
  "geometry": {"coordinates":[98.26519999999999,56.0959],"type":"Point"}
}