{
  "type": "Feature",
  "properties": {
    "gn:admin1_code":"32",
    "gn:asciiname":"Itykova S.",
    "gn:country_code":"RU",
    "gn:dem":65,
    "gn:feature_class":"P",
    "gn:feature_code":"PPL",
    "gn:name":"Itykova S.",
    "gn:population":0,
    "gn:timezone":"Asia/Yekaterinburg",
    "iso:country":"RU",
    "name:rus_x_preferred":[
        "\u0418\u0442\u044b\u043a\u043e\u0432\u0430 \u0421."
    ],
    "name:und_x_variant":[
        "\u0418\u0442\u044b\u043a\u043e\u0432\u0430 \u0421."
    ],
    "wof:name":"Itykova S.",
    "wof:placetype":"locality"
},
  "geometry": {"coordinates":[72.36667,61.98333],"type":"Point"}
}