{
  "type": "Feature",
  "properties": {
    "gn:admin1_code":"77",
    "gn:asciiname":"Mishino",
    "gn:country_code":"RU",
    "gn:dem":298,
    "gn:feature_class":"P",
    "gn:feature_code":"PPL",
    "gn:name":"Mishino",
    "gn:population":0,
    "gn:timezone":"Europe/Moscow",
    "iso:country":"RU",
    "wof:name":"Mishino",
    "wof:placetype":"locality"
},
  "geometry": {"coordinates":[32.955,56.62778],"type":"Point"}
}