{
  "type": "Feature",
  "properties": {
    "gn:admin1_code":"6.0",
    "gn:asciiname":"Peganovo",
    "gn:country_code":"RU",
    "gn:dem":134,
    "gn:feature_class":"P",
    "gn:feature_code":"PPL",
    "gn:name":"Peganovo",
    "gn:population":0,
    "gn:timezone":"Europe/Moscow",
    "iso:country":"RU",
    "name:rus_x_preferred":[
        "\u041f\u0435\u0433\u0430\u043d\u043e\u0432\u043e"
    ],
    "wof:name":"Peganovo",
    "wof:placetype":"locality"
},
  "geometry": {"coordinates":[41.8254,60.965],"type":"Point"}
}