{
  "type": "Feature",
  "properties": {
    "gn:admin1_code":"42",
    "gn:asciiname":"Karel'skaya",
    "gn:country_code":"RU",
    "gn:dem":90,
    "gn:feature_class":"P",
    "gn:feature_code":"PPL",
    "gn:name":"Karel\u2019skaya",
    "gn:population":0,
    "gn:timezone":"Europe/Moscow",
    "iso:country":"RU",
    "name:fin_x_preferred":[
        "Karjalankyl\u00e4"
    ],
    "name:rus_x_preferred":[
        "\u041a\u043e\u043d\u0434\u0443\u0448\u0438-\u041a\u0430\u0440\u0435\u043b\u044c\u0441\u043a\u0430\u044f"
    ],
    "name:und_x_variant":[
        "Karel\u2019skaya",
        "Karjala",
        "Kondushi-Karel\u2019skaya"
    ],
    "wof:name":"Karel'skaya",
    "wof:placetype":"locality"
},
  "geometry": {"coordinates":[33.40101,60.86907],"type":"Point"}
}