{
  "type": "Feature",
  "properties": {
    "gn:admin1_code":"52",
    "gn:asciiname":"Zamost'ye",
    "gn:country_code":"RU",
    "gn:dem":58,
    "gn:feature_class":"P",
    "gn:feature_code":"PPL",
    "gn:name":"Zamost\u2019ye",
    "gn:population":0,
    "gn:timezone":"Europe/Moscow",
    "iso:country":"RU",
    "name:eng_x_preferred":[
        "Zamost'ye"
    ],
    "name:nor_x_preferred":[
        "Zamostje"
    ],
    "name:rus_x_preferred":[
        "\u0417\u0430\u043c\u043e\u0441\u0442\u044c\u0435"
    ],
    "name:und_x_variant":[
        "Zamost\u2019ye"
    ],
    "wof:name":"Zamost'ye",
    "wof:placetype":"locality"
},
  "geometry": {"coordinates":[32.93937,58.83299],"type":"Point"}
}