{
  "type": "Feature",
  "properties": {
    "gn:admin1_code":"90.0",
    "gn:asciiname":"Bartym",
    "gn:country_code":"RU",
    "gn:dem":243,
    "gn:feature_class":"P",
    "gn:feature_code":"PPL",
    "gn:name":"Bartym",
    "gn:population":0,
    "gn:timezone":"Asia/Yekaterinburg",
    "iso:country":"RU",
    "name:che_x_preferred":[
        "\u0411\u0430\u0440\u0442\u044b\u043c"
    ],
    "name:eng_x_preferred":[
        "Bartym"
    ],
    "name:nor_x_preferred":[
        "Bartym"
    ],
    "name:rus_x_preferred":[
        "\u0411\u0430\u0440\u0442\u044b\u043c"
    ],
    "wof:name":"Bartym",
    "wof:placetype":"locality"
},
  "geometry": {"coordinates":[56.94054000000001,56.45461],"type":"Point"}
}