{
  "type": "Feature",
  "properties": {
    "gn:admin1_code":"70",
    "gn:asciiname":"Manych",
    "gn:cc2":"RU",
    "gn:country_code":"RU",
    "gn:dem":102,
    "gn:feature_class":"P",
    "gn:feature_code":"PPL",
    "gn:name":"Manych",
    "gn:population":0,
    "gn:timezone":"Europe/Moscow",
    "iso:country":"RU",
    "name:und_x_variant":[
        "Shornika"
    ],
    "wof:name":"Manych",
    "wof:placetype":"locality"
},
  "geometry": {"coordinates":[44.54444,45.23139000000001],"type":"Point"}
}