{
  "type": "Feature",
  "properties": {
    "gn:admin1_code":"76",
    "gn:asciiname":"Stublenka",
    "gn:country_code":"RU",
    "gn:dem":177,
    "gn:feature_class":"P",
    "gn:feature_code":"PPL",
    "gn:name":"Stubl\u00ebnka",
    "gn:population":0,
    "gn:timezone":"Europe/Moscow",
    "iso:country":"RU",
    "name:rus_x_preferred":[
        "\u0421\u0442\u0443\u0431\u043b\u0451\u043d\u043a\u0430"
    ],
    "name:und_x_variant":[
        "Stubl\u00ebnka"
    ],
    "wof:name":"Stublenka",
    "wof:placetype":"locality"
},
  "geometry": {"coordinates":[37.98254,54.11216],"type":"Point"}
}