{
  "type": "Feature",
  "properties": {
    "gn:admin1_code":"85.0",
    "gn:asciiname":"Antsiferikha",
    "gn:country_code":"RU",
    "gn:dem":136,
    "gn:feature_class":"P",
    "gn:feature_code":"PPL",
    "gn:name":"Antsiferikha",
    "gn:population":0,
    "gn:timezone":"Europe/Moscow",
    "iso:country":"RU",
    "name:nor_x_preferred":[
        "Antsiferikha"
    ],
    "name:rus_x_preferred":[
        "\u0410\u043d\u0446\u0438\u0444\u0435\u0440\u0438\u0445\u0430"
    ],
    "wof:name":"Antsiferikha",
    "wof:placetype":"locality"
},
  "geometry": {"coordinates":[42.52553,59.52486],"type":"Point"}
}