{
  "type": "Feature",
  "properties": {
    "gn:admin1_code":"33",
    "gn:asciiname":"Malyy Konyp",
    "gn:country_code":"RU",
    "gn:dem":142,
    "gn:feature_class":"P",
    "gn:feature_code":"PPL",
    "gn:name":"Malyy Konyp",
    "gn:population":0,
    "gn:timezone":"Europe/Kirov",
    "iso:country":"RU",
    "name:eng_x_preferred":[
        "Malyy Konyp"
    ],
    "name:nor_x_preferred":[
        "Mal.Konyp"
    ],
    "name:rus_x_preferred":[
        "\u041c\u0430\u043b.\u041a\u043e\u043d\u044b\u043f"
    ],
    "name:rus_x_variant":[
        "\u041c\u0430\u043b\u044b\u0439 \u041a\u043e\u043d\u044b\u043f"
    ],
    "name:und_x_variant":[
        "Malyy Kanyp"
    ],
    "wof:name":"Malyy Konyp",
    "wof:placetype":"locality"
},
  "geometry": {"coordinates":[50.3619,58.44363000000001],"type":"Point"}
}