{
  "type": "Feature",
  "properties": {
    "gn:admin1_code":"17",
    "gn:admin2_code":"Shamil'skiy Rayon",
    "gn:asciiname":"Mokoda",
    "gn:country_code":"RU",
    "gn:dem":1620,
    "gn:feature_class":"P",
    "gn:feature_code":"PPL",
    "gn:name":"Mokoda",
    "gn:population":0,
    "gn:timezone":"Europe/Moscow",
    "iso:country":"RU",
    "name:rus_x_preferred":[
        "\u041c\u043e\u043a\u043e\u0434\u0430"
    ],
    "name:und_x_variant":[
        "\u041c\u043e\u043a\u043e\u0434\u0430"
    ],
    "wof:name":"Mokoda",
    "wof:placetype":"locality"
},
  "geometry": {"coordinates":[46.66963,42.42385],"type":"Point"}
}