{
  "type": "Feature",
  "properties": {
    "gn:admin1_code":"60",
    "gn:asciiname":"Retskiye",
    "gn:country_code":"RU",
    "gn:dem":61,
    "gn:feature_class":"P",
    "gn:feature_code":"PPL",
    "gn:name":"Retskiye",
    "gn:population":0,
    "gn:timezone":"Europe/Moscow",
    "iso:country":"RU",
    "name:rus_x_preferred":[
        "\u0420\u0435\u0446\u043a\u0438\u0435"
    ],
    "wof:name":"Retskiye",
    "wof:placetype":"locality"
},
  "geometry": {"coordinates":[28.27851,57.34719000000001],"type":"Point"}
}