{
  "type": "Feature",
  "properties": {
    "gn:admin1_code":"57",
    "gn:asciiname":"Voykovo",
    "gn:country_code":"RU",
    "gn:dem":171,
    "gn:feature_class":"P",
    "gn:feature_code":"PPL",
    "gn:name":"Voykovo",
    "gn:population":0,
    "gn:timezone":"Europe/Moscow",
    "iso:country":"RU",
    "name:rus_x_preferred":[
        "\u0412\u043e\u0439\u043a\u043e\u0432\u043e"
    ],
    "name:und_x_variant":[
        "\u0412\u043e\u0439\u043a\u043e\u0432\u043e"
    ],
    "wof:name":"Voykovo",
    "wof:placetype":"locality"
},
  "geometry": {"coordinates":[44.7945,53.608],"type":"Point"}
}