{
  "type": "Feature",
  "properties": {
    "gn:admin1_code":"49",
    "gn:asciiname":"Zhemchuzhnaya",
    "gn:country_code":"RU",
    "gn:dem":78,
    "gn:feature_class":"P",
    "gn:feature_code":"PPL",
    "gn:name":"Zhemchuzhnaya",
    "gn:population":0,
    "gn:timezone":"Europe/Moscow",
    "iso:country":"RU",
    "name:che_x_preferred":[
        "\u0416\u0435\u043c\u0447\u0443\u0436\u043d\u0438"
    ],
    "name:fin_x_preferred":[
        "Helmilampi"
    ],
    "name:rus_x_preferred":[
        "\u0416\u0435\u043c\u0447\u0443\u0436\u043d\u0430\u044f"
    ],
    "wof:name":"Zhemchuzhnaya",
    "wof:placetype":"locality"
},
  "geometry": {"coordinates":[32.20806,66.92333000000001],"type":"Point"}
}