{
  "type": "Feature",
  "properties": {
    "gn:admin1_code":"49",
    "gn:asciiname":"Zhemchuzhnaya",
    "gn:country_code":"RU",
    "gn:dem":78,
    "gn:feature_class":"P",
    "gn:feature_code":"PPL",
    "gn:name":"Zhemchuzhnaya",
    "gn:population":0,
    "gn:timezone":"Europe/Moscow",
    "iso:country":"RU",
    "name:fin_x_preferred":[
        "Helmilampi"
    ],
    "wof:name":"Zhemchuzhnaya",
    "wof:placetype":"locality"
},
  "geometry": {"coordinates":[32.20806,66.92333000000001],"type":"Point"}
}