{
  "type": "Feature",
  "properties": {
    "gn:admin1_code":"41",
    "gn:asciiname":"Zhedenovka",
    "gn:country_code":"RU",
    "gn:dem":197,
    "gn:feature_class":"P",
    "gn:feature_code":"PPL",
    "gn:name":"Zhed\u00ebnovka",
    "gn:population":0,
    "gn:timezone":"Europe/Moscow",
    "iso:country":"RU",
    "name:rus_x_preferred":[
        "\u0416\u0435\u0434\u0451\u043d\u043e\u0432\u043a\u0430"
    ],
    "name:und_x_variant":[
        "Zhadenovka",
        "Zhidenovka",
        "Zhed\u00ebnovka"
    ],
    "wof:name":"Zhedenovka",
    "wof:placetype":"locality"
},
  "geometry": {"coordinates":[34.555,51.8583],"type":"Point"}
}