{
  "type": "Feature",
  "properties": {
    "gn:country":"RU",
    "gn:fcode":"PPL",
    "gn:population":0,
    "iso:country":"RU",
    "name:rus_x_preferred":[
        "\u0413\u043e\u0441\u043a\u043e\u043d\u044e\u0448\u043d\u044f"
    ],
    "qs:name":"Goskonyushnya",
    "qs:name_adm0":"Russia",
    "qs:name_adm1":"Moscow Oblast",
    "qs:photos_9k":1,
    "qs:photos_9r":1,
    "qs:photos_all":1,
    "qs:photos_sr":0,
    "qs:placetype":"Town",
    "qs:pop_sr":"0",
    "wof:name":"Goskonyushnya",
    "wof:placetype":"locality",
    "wof:population":0
},
  "geometry": {"coordinates":[38.36156,55.02336],"type":"Point"}
}