{
  "type": "Feature",
  "properties": {
    "gn:admin1_code":"77",
    "gn:asciiname":"Zhidulino",
    "gn:country_code":"RU",
    "gn:dem":79,
    "gn:feature_class":"P",
    "gn:feature_code":"PPL",
    "gn:name":"Zhidulino",
    "gn:population":0,
    "gn:timezone":"Europe/Moscow",
    "iso:country":"RU",
    "name:rus_x_preferred":[
        "\u0416\u0438\u0434\u0443\u043b\u0438\u043d\u043e"
    ],
    "name:und_x_variant":[
        "\u0416\u0438\u0434\u0443\u043b\u0438\u043d\u043e"
    ],
    "wof:name":"Zhidulino",
    "wof:placetype":"locality"
},
  "geometry": {"coordinates":[31.06725,56.92056],"type":"Point"}
}