{
  "type": "Feature",
  "properties": {
    "gn:admin1_code":"53",
    "gn:asciiname":"Shibkovo",
    "gn:country_code":"RU",
    "gn:dem":167,
    "gn:feature_class":"P",
    "gn:feature_code":"PPL",
    "gn:name":"Shibkovo",
    "gn:population":0,
    "gn:timezone":"Asia/Novosibirsk",
    "iso:country":"RU",
    "name:eng_x_preferred":[
        "Shibkovo"
    ],
    "name:nor_x_preferred":[
        "Sjibkovo"
    ],
    "name:rus_x_preferred":[
        "\u0428\u0438\u0431\u043a\u043e\u0432\u043e"
    ],
    "name:und_x_variant":[
        "Shipkova"
    ],
    "wof:name":"Shibkovo",
    "wof:placetype":"locality"
},
  "geometry": {"coordinates":[83.28570000000001,54.4888],"type":"Point"}
}