{
  "type": "Feature",
  "properties": {
    "gn:admin1_code":"69",
    "gn:asciiname":"Suravtsovo",
    "gn:country_code":"RU",
    "gn:dem":190,
    "gn:feature_class":"P",
    "gn:feature_code":"PPL",
    "gn:name":"Suravtsovo",
    "gn:population":0,
    "gn:timezone":"Europe/Moscow",
    "iso:country":"RU",
    "name:rus_x_preferred":[
        "\u0421\u0443\u0440\u0430\u0432\u0446\u043e\u0432\u043e"
    ],
    "name:und_x_variant":[
        "Surovtsova",
        "Suravtsovo"
    ],
    "wof:name":"Suravtsovo",
    "wof:placetype":"locality"
},
  "geometry": {"coordinates":[32.39745,55.64265],"type":"Point"}
}