{
  "type": "Feature",
  "properties": {
    "gn:admin1_code":"57",
    "gn:asciiname":"Sergiyevo-Polivanovo",
    "gn:country_code":"RU",
    "gn:dem":127,
    "gn:feature_class":"P",
    "gn:feature_code":"PPL",
    "gn:name":"Sergiyevo-Polivanovo",
    "gn:population":0,
    "gn:timezone":"Europe/Moscow",
    "iso:country":"RU",
    "name:eng_x_preferred":[
        "Sergiyevo-Polivanovo"
    ],
    "name:nor_x_preferred":[
        "Sergo-Polivanovo"
    ],
    "name:rus_x_preferred":[
        "\u0421\u0435\u0440\u0433\u043e-\u041f\u043e\u043b\u0438\u0432\u0430\u043d\u043e\u0432\u043e"
    ],
    "name:rus_x_variant":[
        "\u0421\u0435\u0440\u0433\u0438\u0435\u0432\u043e-\u041f\u043e\u043b\u0438\u0432\u0430\u043d\u043e\u0432\u043e"
    ],
    "wof:name":"Sergiyevo-Polivanovo",
    "wof:placetype":"locality"
},
  "geometry": {"coordinates":[42.80676,53.74806],"type":"Point"}
}