{
  "type": "Feature",
  "properties": {
    "gn:admin1_code":"54",
    "gn:asciiname":"Slavinka",
    "gn:country_code":"RU",
    "gn:dem":115,
    "gn:feature_class":"P",
    "gn:feature_code":"PPL",
    "gn:name":"Slavinka",
    "gn:population":0,
    "gn:timezone":"Asia/Omsk",
    "iso:country":"RU",
    "name:eng_x_preferred":[
        "Slavinka"
    ],
    "name:nor_x_preferred":[
        "Slavinka"
    ],
    "name:rus_x_preferred":[
        "\u0421\u043b\u0430\u0432\u0438\u043d\u043a\u0430"
    ],
    "name:und_x_variant":[
        "\u0421\u043b\u0430\u0432\u0438\u043d\u043a\u0430",
        "Slavinka"
    ],
    "wof:name":"Slavinka",
    "wof:placetype":"locality"
},
  "geometry": {"coordinates":[72.36346999999998,55.25341],"type":"Point"}
}