{
  "type": "Feature",
  "properties": {
    "gn:admin1_code":"57",
    "gn:asciiname":"Ust'-Uza",
    "gn:country_code":"RU",
    "gn:dem":155,
    "gn:feature_class":"P",
    "gn:feature_code":"PPL",
    "gn:name":"Ust\u2019-Uza",
    "gn:population":0,
    "gn:timezone":"Europe/Moscow",
    "iso:country":"RU",
    "name:eng_x_preferred":[
        "Ust'-Uza"
    ],
    "name:nor_x_preferred":[
        "Ust-Uza"
    ],
    "name:rus_x_preferred":[
        "\u0423\u0441\u0442\u044c-\u0423\u0437\u0430"
    ],
    "name:und_x_variant":[
        "Ust\u2019-Uza"
    ],
    "wof:name":"Ust'-Uza",
    "wof:placetype":"locality"
},
  "geometry": {"coordinates":[45.30443,52.97085],"type":"Point"}
}