{
  "type": "Feature",
  "properties": {
    "gn:admin1_code":"76",
    "gn:asciiname":"Verkhniye Kalinki",
    "gn:country_code":"RU",
    "gn:dem":201,
    "gn:feature_class":"P",
    "gn:feature_code":"PPL",
    "gn:name":"Verkhniye Kalinki",
    "gn:population":0,
    "gn:timezone":"Europe/Moscow",
    "iso:country":"RU",
    "name:und_x_variant":[
        "Kalink",
        "Verkhniye Kalinki"
    ],
    "wof:name":"Verkhniye Kalinki",
    "wof:placetype":"locality"
},
  "geometry": {"coordinates":[37.65316,53.11498],"type":"Point"}
}