{
  "type": "Feature",
  "properties": {
    "gn:admin1_code":"67.0",
    "gn:asciiname":"Bystrovka Vtoraya",
    "gn:country_code":"RU",
    "gn:dem":230,
    "gn:feature_class":"P",
    "gn:feature_code":"PPL",
    "gn:name":"Bystrovka Vtoraya",
    "gn:population":0,
    "gn:timezone":"Europe/Saratov",
    "iso:country":"RU",
    "name:rus_x_preferred":[
        "\u0411\u044b\u0441\u0442\u0440\u043e\u0432\u043a\u0430 \u0412\u0442\u043e\u0440\u0430\u044f"
    ],
    "name:und_x_variant":[
        "Bystrovka",
        "Bystrovka Vtoraya",
        "\u0411\u044b\u0441\u0442\u0440\u043e\u0432\u043a\u0430 \u0412\u0442\u043e\u0440\u0430\u044f"
    ],
    "wof:name":"Bystrovka Vtoraya",
    "wof:placetype":"locality"
},
  "geometry": {"coordinates":[45.54013,52.43689000000001],"type":"Point"}
}