{
  "type": "Feature",
  "properties": {
    "gn:admin1_code":"55",
    "gn:asciiname":"Spasskoye",
    "gn:country_code":"RU",
    "gn:dem":130,
    "gn:feature_class":"P",
    "gn:feature_code":"PPL",
    "gn:name":"Spasskoye",
    "gn:population":0,
    "gn:timezone":"Asia/Yekaterinburg",
    "iso:country":"RU",
    "name:eng_x_preferred":[
        "Spasskoye"
    ],
    "name:nor_x_preferred":[
        "Spasskoje"
    ],
    "name:rus_x_preferred":[
        "\u0421\u043f\u0430\u0441\u0441\u043a\u043e\u0435"
    ],
    "wof:name":"Spasskoye",
    "wof:placetype":"locality"
},
  "geometry": {"coordinates":[53.2191,52.3277],"type":"Point"}
}