{
  "type": "Feature",
  "properties": {
    "gn:admin1_code":"38.0",
    "gn:asciiname":"Baranikovskiy",
    "gn:country_code":"RU",
    "gn:dem":5,
    "gn:feature_class":"P",
    "gn:feature_code":"PPL",
    "gn:name":"Baranikovskiy",
    "gn:population":0,
    "gn:timezone":"Europe/Moscow",
    "iso:country":"RU",
    "name:eng_x_preferred":[
        "Baranikovskiy"
    ],
    "name:nor_x_preferred":[
        "Baranikovskij"
    ],
    "name:rus_x_preferred":[
        "\u0411\u0430\u0440\u0430\u043d\u0438\u043a\u043e\u0432\u0441\u043a\u0438\u0439"
    ],
    "name:und_x_variant":[
        "\u0411\u0430\u0440\u0430\u043d\u0438\u043a\u043e\u0432\u0441\u043a\u0438\u0439",
        "Baranikovskiy"
    ],
    "wof:name":"Baranikovskiy",
    "wof:placetype":"locality"
},
  "geometry": {"coordinates":[38.02833,45.35022],"type":"Point"}
}