{
  "type": "Feature",
  "properties": {
    "gn:admin1_code":"33.0",
    "gn:asciiname":"Khorobryata",
    "gn:country_code":"RU",
    "gn:dem":150,
    "gn:feature_class":"P",
    "gn:feature_code":"PPL",
    "gn:name":"Khorobryata",
    "gn:population":0,
    "gn:timezone":"Europe/Kirov",
    "iso:country":"RU",
    "name:rus_x_preferred":[
        "\u0425\u043e\u0440\u043e\u0431\u0440\u044f\u0442\u0430"
    ],
    "wof:name":"Khorobryata",
    "wof:placetype":"locality"
},
  "geometry": {"coordinates":[48.33401,58.86653],"type":"Point"}
}