{
  "type": "Feature",
  "properties": {
    "gn:admin1_code":"60",
    "gn:asciiname":"Osnitsa",
    "gn:country_code":"RU",
    "gn:dem":110,
    "gn:feature_class":"P",
    "gn:feature_code":"PPL",
    "gn:name":"Osnitsa",
    "gn:population":21,
    "gn:timezone":"Europe/Moscow",
    "iso:country":"RU",
    "name:rus_x_preferred":[
        "\u041e\u0441\u043d\u0438\u0446\u0430"
    ],
    "name:und_x_variant":[
        "Vos\u2019nitsa",
        "Osnitsa"
    ],
    "wof:name":"Osnitsa",
    "wof:placetype":"locality",
    "wof:population":21
},
  "geometry": {"coordinates":[28.94732,56.9905],"type":"Point"}
}