{
  "type": "Feature",
  "properties": {
    "gn:admin1_code":"88",
    "gn:asciiname":"Chudinovo",
    "gn:country_code":"RU",
    "gn:dem":118,
    "gn:feature_class":"P",
    "gn:feature_code":"PPL",
    "gn:name":"Chudinovo",
    "gn:population":0,
    "gn:timezone":"Europe/Moscow",
    "iso:country":"RU",
    "name:rus_x_preferred":[
        "\u0427\u0443\u0434\u0438\u043d\u043e\u0432\u043e"
    ],
    "name:und_x_variant":[
        "\u0427\u0443\u0434\u0438\u043d\u043e\u0432\u043e"
    ],
    "wof:name":"Chudinovo",
    "wof:placetype":"locality"
},
  "geometry": {"coordinates":[38.5945,57.9944],"type":"Point"}
}