{
  "type": "Feature",
  "properties": {
    "gn:admin1_code":"28",
    "gn:asciiname":"Motovka",
    "gn:country_code":"RU",
    "gn:dem":60,
    "gn:feature_class":"P",
    "gn:feature_code":"PPL",
    "gn:name":"Motovka",
    "gn:population":0,
    "gn:timezone":"Europe/Moscow",
    "iso:country":"RU",
    "name:fin_x_preferred":[
        "Motovka"
    ],
    "name:rus_x_preferred":[
        "\u041c\u043e\u0442\u043e\u0432\u043a\u0430"
    ],
    "name:und_x_variant":[
        "Mutovka"
    ],
    "wof:name":"Motovka",
    "wof:placetype":"locality"
},
  "geometry": {"coordinates":[32.55197,61.35745],"type":"Point"}
}