{
  "type": "Feature",
  "properties": {
    "gn:admin1_code":"4",
    "gn:asciiname":"Gryaznovo",
    "gn:country_code":"RU",
    "gn:dem":135,
    "gn:feature_class":"P",
    "gn:feature_code":"PPL",
    "gn:name":"Gryaznovo",
    "gn:population":0,
    "gn:timezone":"Asia/Barnaul",
    "iso:country":"RU",
    "name:eng_x_preferred":[
        "Gryazhovo"
    ],
    "name:nor_x_preferred":[
        "Grjaznovo"
    ],
    "name:rus_x_preferred":[
        "\u0413\u0440\u044f\u0437\u043d\u043e\u0432\u043e"
    ],
    "name:und_x_variant":[
        "Trezvonova",
        "Trezvonovo",
        "Gryaznovo"
    ],
    "wof:name":"Gryaznovo",
    "wof:placetype":"locality"
},
  "geometry": {"coordinates":[81.2681,53.3827],"type":"Point"}
}