{
  "type": "Feature",
  "properties": {
    "gn:admin1_code":"60",
    "gn:asciiname":"Matyugino",
    "gn:country_code":"RU",
    "gn:dem":56,
    "gn:feature_class":"P",
    "gn:feature_code":"PPL",
    "gn:name":"Matyugino",
    "gn:population":0,
    "gn:timezone":"Europe/Moscow",
    "iso:country":"RU",
    "name:rus_x_preferred":[
        "\u041c\u0430\u0442\u044e\u0433\u0438\u043d\u043e"
    ],
    "wof:name":"Matyugino",
    "wof:placetype":"locality"
},
  "geometry": {"coordinates":[28.23362,57.2925],"type":"Point"}
}