{
  "type": "Feature",
  "properties": {
    "gn:admin1_code":"93",
    "gn:asciiname":"Zelenoye Ozero",
    "gn:country_code":"RU",
    "gn:dem":667,
    "gn:feature_class":"P",
    "gn:feature_code":"PPL",
    "gn:name":"Zel\u00ebnoye Ozero",
    "gn:population":0,
    "gn:timezone":"Asia/Chita",
    "iso:country":"RU",
    "name:eng_x_preferred":[
        "Zel\u00ebnoye Ozero"
    ],
    "name:nor_x_preferred":[
        "Zelenoje-Ozero"
    ],
    "name:rus_x_preferred":[
        "\u0417\u0435\u043b\u0435\u043d\u043e\u0435-\u041e\u0437\u0435\u0440\u043e"
    ],
    "name:und_x_variant":[
        "Zel\u00ebnoye Ozero"
    ],
    "wof:name":"Zelenoye Ozero",
    "wof:placetype":"locality"
},
  "geometry": {"coordinates":[116.59999999999999,53.66667],"type":"Point"}
}