{
  "type": "Feature",
  "properties": {
    "gn:admin1_code":"41.0",
    "gn:asciiname":"Shaposhnikovo",
    "gn:country_code":"RU",
    "gn:dem":178,
    "gn:feature_class":"P",
    "gn:feature_code":"PPL",
    "gn:name":"Shaposhnikovo",
    "gn:population":0,
    "gn:timezone":"Europe/Moscow",
    "iso:country":"RU",
    "name:rus_x_preferred":[
        "\u0428\u0430\u043f\u043e\u0448\u043d\u0438\u043a\u043e\u0432\u043e"
    ],
    "name:und_x_variant":[
        "Shaposhnikov"
    ],
    "wof:name":"Shaposhnikovo",
    "wof:placetype":"locality"
},
  "geometry": {"coordinates":[34.5864,51.5044],"type":"Point"}
}