{
  "type": "Feature",
  "properties": {
    "gn:admin1_code":"47",
    "gn:asciiname":"Annino",
    "gn:country_code":"RU",
    "gn:dem":219,
    "gn:feature_class":"P",
    "gn:feature_code":"PPL",
    "gn:name":"Annino",
    "gn:population":0,
    "gn:timezone":"Europe/Moscow",
    "iso:country":"RU",
    "name:rus_x_preferred":[
        "\u0410\u043d\u043d\u0438\u043d\u043e"
    ],
    "name:und_x_variant":[
        "\u0410\u043d\u043d\u0438\u043d\u043e"
    ],
    "wof:name":"Annino",
    "wof:placetype":"locality"
},
  "geometry": {"coordinates":[36.1676,56.1052],"type":"Point"}
}