{
  "type": "Feature",
  "properties": {
    "gn:admin1_code":"52",
    "gn:asciiname":"Pridanikha",
    "gn:country_code":"RU",
    "gn:dem":179,
    "gn:feature_class":"P",
    "gn:feature_code":"PPL",
    "gn:name":"Pridanikha",
    "gn:population":0,
    "gn:timezone":"Europe/Moscow",
    "iso:country":"RU",
    "name:eng_x_preferred":[
        "Pridanikha"
    ],
    "name:nor_x_preferred":[
        "Pridanikha"
    ],
    "name:rus_x_preferred":[
        "\u041f\u0440\u0438\u0434\u0430\u043d\u0438\u0445\u0430"
    ],
    "wof:name":"Pridanikha",
    "wof:placetype":"locality"
},
  "geometry": {"coordinates":[36.12056,58.52553],"type":"Point"}
}