{
  "type": "Feature",
  "properties": {
    "gn:admin1_code":"33",
    "gn:asciiname":"Semakovy",
    "gn:country_code":"RU",
    "gn:dem":164,
    "gn:feature_class":"P",
    "gn:feature_code":"PPL",
    "gn:name":"Semakovy",
    "gn:population":0,
    "gn:timezone":"Europe/Kirov",
    "iso:country":"RU",
    "name:rus_x_preferred":[
        "\u0421\u0435\u043c\u0430\u043a\u043e\u0432\u044b"
    ],
    "name:und_x_variant":[
        "\u0421\u0435\u043c\u0430\u043a\u043e\u0432\u044b"
    ],
    "wof:name":"Semakovy",
    "wof:placetype":"locality"
},
  "geometry": {"coordinates":[49.16667,58.95],"type":"Point"}
}