{
  "type": "Feature",
  "properties": {
    "gn:admin1_code":"57",
    "gn:asciiname":"Mokraya Polyana",
    "gn:country_code":"RU",
    "gn:dem":268,
    "gn:feature_class":"P",
    "gn:feature_code":"PPL",
    "gn:name":"Mokraya Polyana",
    "gn:population":0,
    "gn:timezone":"Europe/Moscow",
    "iso:country":"RU",
    "name:rus_x_preferred":[
        "\u041c\u043e\u043a\u0440\u0430\u044f \u041f\u043e\u043b\u044f\u043d\u0430"
    ],
    "wof:name":"Mokraya Polyana",
    "wof:placetype":"locality"
},
  "geometry": {"coordinates":[45.97122,53.67449000000001],"type":"Point"}
}