{
  "type": "Feature",
  "properties": {
    "gn:admin1_code":"6",
    "gn:asciiname":"Sinniki",
    "gn:country_code":"RU",
    "gn:dem":128,
    "gn:feature_class":"P",
    "gn:feature_code":"PPL",
    "gn:name":"Sinniki",
    "gn:population":0,
    "gn:timezone":"Europe/Moscow",
    "iso:country":"RU",
    "name:eng_x_preferred":[
        "Sinniki"
    ],
    "name:nor_x_preferred":[
        "Sinniki"
    ],
    "name:rus_x_preferred":[
        "\u0421\u0438\u043d\u043d\u0438\u043a\u0438"
    ],
    "name:und_x_variant":[
        "Sinitskaya",
        "Siniki"
    ],
    "wof:name":"Sinniki",
    "wof:placetype":"locality"
},
  "geometry": {"coordinates":[44.9647,61.45681],"type":"Point"}
}