{
  "type": "Feature",
  "properties": {
    "gn:admin1_code":"34",
    "gn:asciiname":"Raschoy",
    "gn:country_code":"RU",
    "gn:dem":136,
    "gn:feature_class":"P",
    "gn:feature_code":"PPL",
    "gn:name":"Raschoy",
    "gn:population":0,
    "gn:timezone":"Europe/Moscow",
    "iso:country":"RU",
    "name:rus_x_preferred":[
        "\u0420\u0430\u0441\u0447\u043e\u0439"
    ],
    "wof:name":"Raschoy",
    "wof:placetype":"locality"
},
  "geometry": {"coordinates":[49.67064,60.91255],"type":"Point"}
}