{
  "type": "Feature",
  "properties": {
    "gn:admin1_code":"25",
    "gn:asciiname":"Verkhneye Blevkovo",
    "gn:country_code":"RU",
    "gn:dem":223,
    "gn:feature_class":"P",
    "gn:feature_code":"PPL",
    "gn:name":"Verkhneye Blevkovo",
    "gn:population":0,
    "gn:timezone":"Europe/Moscow",
    "iso:country":"RU",
    "name:und_x_variant":[
        "Blevkovo",
        "Verkhneye Blevkovo"
    ],
    "wof:name":"Verkhneye Blevkovo",
    "wof:placetype":"locality"
},
  "geometry": {"coordinates":[33.98188,54.45903000000001],"type":"Point"}
}