{
  "type": "Feature",
  "properties": {
    "gn:admin1_code":"60",
    "gn:asciiname":"Kolesnikovo",
    "gn:country_code":"RU",
    "gn:dem":92,
    "gn:feature_class":"P",
    "gn:feature_code":"PPL",
    "gn:name":"Kolesnikovo",
    "gn:population":0,
    "gn:timezone":"Europe/Moscow",
    "iso:country":"RU",
    "name:rus_x_preferred":[
        "\u041a\u043e\u043b\u0435\u0441\u043d\u0438\u043a\u043e\u0432\u043e"
    ],
    "wof:name":"Kolesnikovo",
    "wof:placetype":"locality"
},
  "geometry": {"coordinates":[28.97183,56.87464],"type":"Point"}
}