{
  "type": "Feature",
  "properties": {
    "gn:admin1_code":"88",
    "gn:asciiname":"Starovo",
    "gn:country_code":"RU",
    "gn:dem":154,
    "gn:feature_class":"P",
    "gn:feature_code":"PPL",
    "gn:name":"Starovo",
    "gn:population":0,
    "gn:timezone":"Europe/Moscow",
    "iso:country":"RU",
    "name:rus_x_preferred":[
        "\u0421\u0442\u0430\u0440\u043e\u0432\u043e"
    ],
    "name:und_x_variant":[
        "\u0421\u0442\u0430\u0440\u043e\u0432\u043e"
    ],
    "wof:name":"Starovo",
    "wof:placetype":"locality"
},
  "geometry": {"coordinates":[37.7357,57.9983],"type":"Point"}
}