{
  "type": "Feature",
  "properties": {
    "gn:country":"RU",
    "gn:fcode":"PPL",
    "gn:pop":10778,
    "iso:country":"RU",
    "name:che_x_preferred":[
        "\u0421\u0443\u043b\u0435\u0431\u043a\u0435\u043d\u0442"
    ],
    "name:deu_x_preferred":[
        "Mairtup"
    ],
    "name:eng_x_preferred":[
        "Mayrtup"
    ],
    "name:nld_x_preferred":[
        "Mayrtup"
    ],
    "name:nor_x_preferred":[
        "Majrtup"
    ],
    "name:rus_x_preferred":[
        "\u041c\u0430\u0439\u0440\u0442\u0443\u043f"
    ],
    "name:unk_x_variant":[
        "Sulebkent"
    ],
    "qs:name":"Mayrtup",
    "qs:name_adm0":"Russia",
    "qs:name_adm1":"Chechnya Republic",
    "qs:photos_9r":0,
    "qs:photos_sr":0,
    "qs:placetype":"Town",
    "qs:pop_sr":"6",
    "wof:name":"Mayrtup",
    "wof:placetype":"locality",
    "wof:population":10778
},
  "geometry": {"coordinates":[46.13214,43.20348],"type":"Point"}
}