{
  "type": "Feature",
  "properties": {
    "gn:admin1_code":"59.0",
    "gn:asciiname":"Orlikha",
    "gn:country_code":"RU",
    "gn:dem":180,
    "gn:feature_class":"P",
    "gn:feature_code":"PPL",
    "gn:name":"Orlikha",
    "gn:population":0,
    "gn:timezone":"Asia/Vladivostok",
    "iso:country":"RU",
    "name:rus_x_preferred":[
        "\u041e\u0440\u043b\u0438\u0445\u0430"
    ],
    "name:und_x_variant":[
        "\u041e\u0440\u043b\u0438\u0445\u0430"
    ],
    "wof:name":"Orlikha",
    "wof:placetype":"locality"
},
  "geometry": {"coordinates":[131.48230000000001,43.778],"type":"Point"}
}