{
  "type": "Feature",
  "properties": {
    "gn:admin1_code":"38",
    "gn:asciiname":"Gunayka Chetvertaya",
    "gn:country_code":"RU",
    "gn:dem":318,
    "gn:feature_class":"P",
    "gn:feature_code":"PPL",
    "gn:name":"Gunayka Chetv\u00ebrtaya",
    "gn:population":0,
    "gn:timezone":"Europe/Moscow",
    "iso:country":"RU",
    "name:eng_x_preferred":[
        "Gunayka Chetvertaya"
    ],
    "name:nor_x_preferred":[
        "Gunajka Tsjetvertaja"
    ],
    "name:rus_x_preferred":[
        "\u0413\u0443\u043d\u0430\u0439\u043a\u0430 \u0427\u0435\u0442\u0432\u0451\u0440\u0442\u0430\u044f"
    ],
    "name:und_x_variant":[
        "Gunayka",
        "Gunaiskoe",
        "Gunayskoye",
        "Gunayka Chetv\u00ebrtaya"
    ],
    "wof:name":"Gunayka Chetvertaya",
    "wof:placetype":"locality"
},
  "geometry": {"coordinates":[39.4373,44.2749],"type":"Point"}
}