{
  "type": "Feature",
  "properties": {
    "gn:admin1_code":"77",
    "gn:asciiname":"Volnitsyno",
    "gn:country_code":"RU",
    "gn:dem":170,
    "gn:feature_class":"P",
    "gn:feature_code":"PPL",
    "gn:name":"Volnitsyno",
    "gn:population":0,
    "gn:timezone":"Europe/Moscow",
    "iso:country":"RU",
    "name:rus_x_preferred":[
        "\u0412\u043e\u043b\u043d\u0438\u0446\u044b\u043d\u043e"
    ],
    "name:und_x_variant":[
        "\u0412\u043e\u043b\u043d\u0438\u0446\u044b\u043d\u043e"
    ],
    "wof:name":"Volnitsyno",
    "wof:placetype":"locality"
},
  "geometry": {"coordinates":[36.7862,58.603],"type":"Point"}
}