{
  "type": "Feature",
  "properties": {
    "gn:admin1_code":"40",
    "gn:asciiname":"Mezhbornoye",
    "gn:country_code":"RU",
    "gn:dem":79,
    "gn:feature_class":"P",
    "gn:feature_code":"PPL",
    "gn:name":"Mezhbornoye",
    "gn:population":0,
    "gn:timezone":"Asia/Yekaterinburg",
    "iso:country":"RU",
    "name:eng_x_preferred":[
        "Mezhbornoye"
    ],
    "name:nor_x_preferred":[
        "Mezjbornoje"
    ],
    "name:rus_x_preferred":[
        "\u041c\u0435\u0436\u0431\u043e\u0440\u043d\u043e\u0435"
    ],
    "name:und_x_variant":[
        "\u041c\u0435\u0436\u0431\u043e\u0440\u043d\u043e\u0435",
        "Mezhbornoye"
    ],
    "wof:name":"Mezhbornoye",
    "wof:placetype":"locality"
},
  "geometry": {"coordinates":[65.09833,54.95278],"type":"Point"}
}