{
  "type": "Feature",
  "properties": {
    "gn:admin1_code":"51.0",
    "gn:asciiname":"Fedorovka",
    "gn:country_code":"RU",
    "gn:dem":193,
    "gn:feature_class":"P",
    "gn:feature_code":"PPL",
    "gn:name":"F\u00ebdorovka",
    "gn:population":0,
    "gn:timezone":"Europe/Moscow",
    "iso:country":"RU",
    "name:rus_x_preferred":[
        "\u0424\u0451\u0434\u043e\u0440\u043e\u0432\u043a\u0430"
    ],
    "name:und_x_variant":[
        "Federovskaya",
        "F\u00ebdorovka",
        "\u0424\u0451\u0434\u043e\u0440\u043e\u0432\u043a\u0430"
    ],
    "wof:name":"Fedorovka",
    "wof:placetype":"locality"
},
  "geometry": {"coordinates":[44.06293,55.11338000000001],"type":"Point"}
}