{
  "type": "Feature",
  "properties": {
    "gn:admin1_code":"6.0",
    "gn:asciiname":"Artel'nyy",
    "gn:country_code":"RU",
    "gn:dem":158,
    "gn:feature_class":"P",
    "gn:feature_code":"PPL",
    "gn:name":"Artel\u2019nyy",
    "gn:population":0,
    "gn:timezone":"Europe/Moscow",
    "iso:country":"RU",
    "name:rus_x_preferred":[
        "(( \u0410\u0440\u0442\u0435\u043b\u044c\u043d\u044b\u0439 ))"
    ],
    "name:und_x_variant":[
        "Artel\u2019ny"
    ],
    "wof:name":"Artel'nyy",
    "wof:placetype":"locality"
},
  "geometry": {"coordinates":[44.18,61.18],"type":"Point"}
}