{
  "type": "Feature",
  "properties": {
    "gn:admin1_code":"53",
    "gn:asciiname":"Verkh-Tarka",
    "gn:country_code":"RU",
    "gn:dem":94,
    "gn:feature_class":"P",
    "gn:feature_code":"PPL",
    "gn:name":"Verkh-Tarka",
    "gn:population":0,
    "gn:timezone":"Asia/Novosibirsk",
    "iso:country":"RU",
    "name:eng_x_preferred":[
        "Verkh-Tarka"
    ],
    "name:rus_x_preferred":[
        "\u0412\u0435\u0440\u0445.-\u0422\u0430\u0440\u043a\u0430"
    ],
    "name:rus_x_variant":[
        "\u0412\u0435\u0440\u0445-\u0422\u0430\u0440\u043a\u0430"
    ],
    "wof:name":"Verkh-Tarka",
    "wof:placetype":"locality"
},
  "geometry": {"coordinates":[77.49868000000002,56.62255],"type":"Point"}
}