{
  "type": "Feature",
  "properties": {
    "gn:admin1_code":"68.0",
    "gn:asciiname":"Kamata",
    "gn:country_code":"RU",
    "gn:dem":1426,
    "gn:feature_class":"P",
    "gn:feature_code":"PPL",
    "gn:name":"Kamata",
    "gn:population":0,
    "gn:timezone":"Europe/Moscow",
    "iso:country":"RU",
    "name:ceb_x_preferred":[
        "Kamata"
    ],
    "name:deu_x_preferred":[
        "Kamata"
    ],
    "name:ita_x_preferred":[
        "Kamata"
    ],
    "name:rus_x_preferred":[
        "\u041a\u0430\u043c\u0430\u0442\u0430"
    ],
    "name:swe_x_preferred":[
        "Kamata"
    ],
    "name:und_x_variant":[
        "Kamat"
    ],
    "wof:name":"Kamata",
    "wof:placetype":"locality"
},
  "geometry": {"coordinates":[43.78829,42.9546],"type":"Point"}
}