{
  "type": "Feature",
  "properties": {
    "gn:admin1_code":"33",
    "gn:asciiname":"Gorelaya Polyana",
    "gn:country_code":"RU",
    "gn:dem":161,
    "gn:feature_class":"P",
    "gn:feature_code":"PPL",
    "gn:name":"Gorelaya Polyana",
    "gn:population":0,
    "gn:timezone":"Europe/Kirov",
    "iso:country":"RU",
    "name:rus_x_preferred":[
        "\u0413\u043e\u0440\u0435\u043b\u0430\u044f \u041f\u043e\u043b\u044f\u043d\u0430"
    ],
    "name:und_x_variant":[
        "Gorelyye Polyany",
        "Gorelaya Polyana",
        "\u0413\u043e\u0440\u0435\u043b\u0430\u044f \u041f\u043e\u043b\u044f\u043d\u0430"
    ],
    "wof:name":"Gorelaya Polyana",
    "wof:placetype":"locality"
},
  "geometry": {"coordinates":[46.83582,57.32548000000001],"type":"Point"}
}