{
  "type": "Feature",
  "properties": {
    "gn:admin1_code":"85",
    "gn:asciiname":"Osyutino",
    "gn:country_code":"RU",
    "gn:dem":175,
    "gn:feature_class":"P",
    "gn:feature_code":"PPL",
    "gn:name":"Osyutino",
    "gn:population":0,
    "gn:timezone":"Europe/Moscow",
    "iso:country":"RU",
    "name:rus_x_preferred":[
        "\u041e\u0441\u044e\u0442\u0438\u043d\u043e"
    ],
    "name:und_x_variant":[
        "\u041e\u0441\u044e\u0442\u0438\u043d\u043e"
    ],
    "wof:name":"Osyutino",
    "wof:placetype":"locality"
},
  "geometry": {"coordinates":[38.62368,59.12311999999999],"type":"Point"}
}