{
  "type": "Feature",
  "properties": {
    "gn:admin1_code":"60",
    "gn:asciiname":"Isaki",
    "gn:country_code":"RU",
    "gn:dem":99,
    "gn:feature_class":"P",
    "gn:feature_code":"PPL",
    "gn:name":"Isaki",
    "gn:population":0,
    "gn:timezone":"Europe/Moscow",
    "iso:country":"RU",
    "name:eng_x_preferred":[
        "Isaki"
    ],
    "name:nor_x_preferred":[
        "Isaki"
    ],
    "name:rus_x_preferred":[
        "\u0418\u0441\u0430\u043a\u0438"
    ],
    "wof:name":"Isaki",
    "wof:placetype":"locality"
},
  "geometry": {"coordinates":[28.60086,56.66146],"type":"Point"}
}