{
  "type": "Feature",
  "properties": {
    "gn:admin1_code":"41",
    "gn:asciiname":"Slobodka-Ivanovka",
    "gn:country_code":"RU",
    "gn:dem":191,
    "gn:feature_class":"P",
    "gn:feature_code":"PPL",
    "gn:name":"Slobodka-Ivanovka",
    "gn:population":0,
    "gn:timezone":"Europe/Moscow",
    "iso:country":"RU",
    "name:rus_x_preferred":[
        "\u0421\u043b\u043e\u0431\u043e\u0434\u043a\u0430-\u0418\u0432\u0430\u043d\u043e\u0432\u043a\u0430"
    ],
    "name:und_x_variant":[
        "Ivanovka",
        "Slobodka Iyanovka",
        "Slobodka-Ivanovka"
    ],
    "wof:name":"Slobodka-Ivanovka",
    "wof:placetype":"locality"
},
  "geometry": {"coordinates":[34.3287,51.5371],"type":"Point"}
}