{
  "type": "Feature",
  "properties": {
    "gn:admin1_code":"68",
    "gn:asciiname":"Salugardon",
    "gn:cc2":"RU",
    "gn:country_code":"RU",
    "gn:dem":616,
    "gn:feature_class":"P",
    "gn:feature_code":"PPL",
    "gn:name":"Salugardon",
    "gn:population":0,
    "gn:timezone":"Europe/Moscow",
    "iso:country":"RU",
    "name:rus_x_preferred":[
        "\u0421\u0430\u043b\u0443\u0433\u0430\u0440\u0434\u043e\u043d"
    ],
    "name:und_x_variant":[
        "Salugordan",
        "Salugardon",
        "\u0421\u0430\u043b\u0443\u0433\u0430\u0440\u0434\u043e\u043d"
    ],
    "wof:name":"Salugardon",
    "wof:placetype":"locality"
},
  "geometry": {"coordinates":[44.24194,43.03667],"type":"Point"}
}