{
  "type": "Feature",
  "properties": {
    "gn:admin1_code":"76.0",
    "gn:asciiname":"Nepryadva",
    "gn:country_code":"RU",
    "gn:dem":227,
    "gn:feature_class":"P",
    "gn:feature_code":"PPL",
    "gn:name":"Nepryadva",
    "gn:population":0,
    "gn:timezone":"Europe/Moscow",
    "iso:country":"RU",
    "name:ceb_x_preferred":[
        "Nepryadva"
    ],
    "name:chv_x_preferred":[
        "\u041d\u0435\u043f\u0440\u044f\u0434\u0432\u0430"
    ],
    "name:rus_x_preferred":[
        "\u041d\u0435\u043f\u0440\u044f\u0434\u0432\u0430"
    ],
    "wof:name":"Nepryadva",
    "wof:placetype":"locality"
},
  "geometry": {"coordinates":[38.0949,53.3204],"type":"Point"}
}