{
  "type": "Feature",
  "properties": {
    "gn:country":"RU",
    "gn:fcode":"PPL",
    "gn:pop":99,
    "iso:country":"RU",
    "name:ces_x_preferred":[
        "Roga\u010dovo"
    ],
    "name:eng_x_preferred":[
        "Rogach\u00ebvo"
    ],
    "name:eng_x_variant":[
        "Rogachevo"
    ],
    "name:hye_x_preferred":[
        "\u054c\u0578\u0563\u0561\u0579\u0575\u0578\u057e\u0578"
    ],
    "name:nno_x_preferred":[
        "Rogatsjovo"
    ],
    "name:nob_x_preferred":[
        "Rogatsjovo"
    ],
    "name:nor_x_preferred":[
        "Rogatsjevo"
    ],
    "name:rus_x_preferred":[
        "\u0420\u043e\u0433\u0430\u0447\u0435\u0432\u043e"
    ],
    "name:rus_x_variant":[
        "\u0420\u043e\u0433\u0430\u0447\u0451\u0432\u043e"
    ],
    "qs:name":"Rogach\u00ebvo",
    "qs:photos_9r":0,
    "qs:photos_sr":0,
    "qs:pop_sr":"1",
    "wof:name":"Rogach\u00ebvo",
    "wof:placetype":"locality",
    "wof:population":99
},
  "geometry": {"coordinates":[52.44753,71.60926000000001],"type":"Point"}
}