{
  "type": "Feature",
  "properties": {
    "gn:admin1_code":"41",
    "gn:asciiname":"Krupets",
    "gn:country_code":"RU",
    "gn:dem":180,
    "gn:feature_class":"P",
    "gn:feature_code":"PPL",
    "gn:name":"Krupets",
    "gn:population":0,
    "gn:timezone":"Europe/Moscow",
    "iso:country":"RU",
    "name:rus_x_preferred":[
        "\u041a\u0440\u0443\u043f\u0435\u0446"
    ],
    "name:und_x_variant":[
        "\u041a\u0440\u0443\u043f\u0435\u0446"
    ],
    "wof:name":"Krupets",
    "wof:placetype":"locality"
},
  "geometry": {"coordinates":[35.05806,52.13972],"type":"Point"}
}