{
  "type": "Feature",
  "properties": {
    "gn:admin1_code":"83",
    "gn:asciiname":"Zavalino",
    "gn:country_code":"RU",
    "gn:dem":138,
    "gn:feature_class":"P",
    "gn:feature_code":"PPL",
    "gn:name":"Zavalino",
    "gn:population":0,
    "gn:timezone":"Europe/Moscow",
    "iso:country":"RU",
    "name:rus_x_preferred":[
        "\u0417\u0430\u0432\u0430\u043b\u0438\u043d\u043e"
    ],
    "wof:name":"Zavalino",
    "wof:placetype":"locality"
},
  "geometry": {"coordinates":[39.46112,56.20571],"type":"Point"}
}