{
  "type": "Feature",
  "properties": {
    "gn:admin1_code":"63",
    "gn:asciiname":"Temirbaga",
    "gn:country_code":"RU",
    "gn:dem":78,
    "gn:feature_class":"P",
    "gn:feature_code":"PPL",
    "gn:name":"Temirbaga",
    "gn:population":0,
    "gn:timezone":"Asia/Yakutsk",
    "iso:country":"RU",
    "wof:name":"Temirbaga",
    "wof:placetype":"locality"
},
  "geometry": {"coordinates":[128.13333,63.55],"type":"Point"}
}