{
  "type": "Feature",
  "properties": {
    "gn:admin1_code":"51",
    "gn:asciiname":"Kuz'minka",
    "gn:country_code":"RU",
    "gn:dem":135,
    "gn:feature_class":"P",
    "gn:feature_code":"PPL",
    "gn:name":"Kuz\u2019minka",
    "gn:population":0,
    "gn:timezone":"Europe/Moscow",
    "iso:country":"RU",
    "name:rus_x_preferred":[
        "\u041a\u0443\u0437\u044c\u043c\u0438\u043d\u043a\u0430"
    ],
    "name:und_x_variant":[
        "Kuz\u2019minka"
    ],
    "wof:name":"Kuz'minka",
    "wof:placetype":"locality"
},
  "geometry": {"coordinates":[46.6038,57.4262],"type":"Point"}
}