{
  "type": "Feature",
  "properties": {
    "gn:admin1_code":"60",
    "gn:asciiname":"Sanevo",
    "gn:country_code":"RU",
    "gn:dem":93,
    "gn:feature_class":"P",
    "gn:feature_code":"PPL",
    "gn:name":"San\u00ebvo",
    "gn:population":0,
    "gn:timezone":"Europe/Moscow",
    "iso:country":"RU",
    "name:rus_x_preferred":[
        "\u0421\u0430\u043d\u0451\u0432\u043e"
    ],
    "name:und_x_variant":[
        "San\u00ebvo"
    ],
    "wof:name":"Sanevo",
    "wof:placetype":"locality"
},
  "geometry": {"coordinates":[29.1771,56.9853],"type":"Point"}
}