{
  "type": "Feature",
  "properties": {
    "gn:admin1_code":"9",
    "gn:asciiname":"Dolgaya Yaruga",
    "gn:country_code":"RU",
    "gn:dem":205,
    "gn:feature_class":"P",
    "gn:feature_code":"PPL",
    "gn:name":"Dolgaya Yaruga",
    "gn:population":0,
    "gn:timezone":"Europe/Moscow",
    "iso:country":"RU",
    "name:rus_x_preferred":[
        "\u0414\u043e\u043b\u0433\u0430\u044f \u042f\u0440\u0443\u0433\u0430"
    ],
    "name:und_x_variant":[
        "\u0414\u043e\u043b\u0433\u0430\u044f \u042f\u0440\u0443\u0433\u0430"
    ],
    "wof:name":"Dolgaya Yaruga",
    "wof:placetype":"locality"
},
  "geometry": {"coordinates":[37.86945,50.89916],"type":"Point"}
}