{
  "type": "Feature",
  "properties": {
    "gn:admin1_code":"55",
    "gn:asciiname":"Nizhnezaglyadino",
    "gn:country_code":"RU",
    "gn:dem":76,
    "gn:feature_class":"P",
    "gn:feature_code":"PPL",
    "gn:name":"Nizhnezaglyadino",
    "gn:population":0,
    "gn:timezone":"Asia/Yekaterinburg",
    "iso:country":"RU",
    "name:rus_x_preferred":[
        "\u041d\u0438\u0436\u043d\u0435\u0437\u0430\u0433\u043b\u044f\u0434\u0438\u043d\u043e"
    ],
    "name:und_x_variant":[
        "Nizhneye Zaglyadino"
    ],
    "wof:name":"Nizhnezaglyadino",
    "wof:placetype":"locality"
},
  "geometry": {"coordinates":[52.64266,53.59169],"type":"Point"}
}