{
  "type": "Feature",
  "properties": {
    "gn:admin1_code":"61",
    "gn:asciiname":"Nizhniye Grachiki",
    "gn:country_code":"RU",
    "gn:dem":57,
    "gn:feature_class":"P",
    "gn:feature_code":"PPL",
    "gn:name":"Nizhniye Grachiki",
    "gn:population":0,
    "gn:timezone":"Europe/Moscow",
    "iso:country":"RU",
    "name:rus_x_preferred":[
        "\u041d\u0438\u0436\u043d\u0438\u0435 \u0413\u0440\u0430\u0447\u0438\u043a\u0438"
    ],
    "name:und_x_variant":[
        "Nizhne-Grachiki",
        "Nizhniye Grachiki"
    ],
    "wof:name":"Nizhniye Grachiki",
    "wof:placetype":"locality"
},
  "geometry": {"coordinates":[39.9345,48.5126],"type":"Point"}
}