{
  "type": "Feature",
  "properties": {
    "gn:admin1_code":"44",
    "gn:asciiname":"Kyurbelyakh",
    "gn:country_code":"RU",
    "gn:dem":779,
    "gn:feature_class":"P",
    "gn:feature_code":"PPL",
    "gn:name":"Kyurbelyakh",
    "gn:population":0,
    "gn:timezone":"Asia/Magadan",
    "iso:country":"RU",
    "wof:name":"Kyurbelyakh",
    "wof:placetype":"locality"
},
  "geometry": {"coordinates":[145.94999999999999,63.05],"type":"Point"}
}