{
  "type": "Feature",
  "properties": {
    "gn:country":"RU",
    "gn:fcode":"PPL",
    "gn:population":2547,
    "iso:country":"RU",
    "name:bel_x_preferred":[
        "\u0423\u0434\u043e\u0440\u0441\u043a\u0456 \u0440\u0430\u0451\u043d"
    ],
    "name:ceb_x_preferred":[
        "Udorskiy Rayon"
    ],
    "name:che_x_preferred":[
        "\u0423\u0434\u043e\u0440\u0430\u043d \u043a\u04c0\u043e\u0448\u0442"
    ],
    "name:che_x_variant":[
        "\u0423\u0434\u043e\u0440\u0438\u0439\u043d \u043a\u04c0\u043e\u0448\u0442"
    ],
    "name:deu_x_preferred":[
        "Udorski rajon"
    ],
    "name:eng_x_preferred":[
        "Koslan"
    ],
    "name:eng_x_variant":[
        "Udorsky District"
    ],
    "name:est_x_preferred":[
        "Udora rajoon"
    ],
    "name:fin_x_preferred":[
        "Udoran piiri"
    ],
    "name:fra_x_preferred":[
        "Ra\u00efon Oudorski"
    ],
    "name:hun_x_preferred":[
        "Udor j\u00e1r\u00e1s"
    ],
    "name:hye_x_preferred":[
        "\u0548\u0582\u0564\u0578\u0580\u057d\u056f\u056b \u0577\u0580\u057b\u0561\u0576"
    ],
    "name:ita_x_preferred":[
        "Udorskij rajon"
    ],
    "name:jpn_x_preferred":[
        "\u30a6\u30c9\u30ea\u30a2"
    ],
    "name:koi_x_preferred":[
        "\u0423\u0434\u043e\u0440\u0430 \u0440\u0430\u0439\u043e\u043d"
    ],
    "name:kom_x_preferred":[
        "\u0423\u0434\u043e\u0440\u0430 \u0440\u0430\u0439\u043e\u043d"
    ],
    "name:myv_x_preferred":[
        "\u0423\u0434\u043e\u0440\u0431\u0443\u0435"
    ],
    "name:nan_x_preferred":[
        "Udorsky Ko\u0101n"
    ],
    "name:nld_x_preferred":[
        "Oedorskiy rayon"
    ],
    "name:nor_x_preferred":[
        "Koslan"
    ],
    "name:rus_x_preferred":[
        "\u041a\u043e\u0441\u043b\u0430\u043d"
    ],
    "name:rus_x_variant":[
        "\u0423\u0434\u043e\u0440\u0441\u043a\u0438\u0439 \u0440\u0430\u0439\u043e\u043d"
    ],
    "name:ukr_x_preferred":[
        "\u0423\u0434\u043e\u0440\u0441\u044c\u043a\u0438\u0439 \u0440\u0430\u0439\u043e\u043d"
    ],
    "name:uzb_x_preferred":[
        "Udora tumani"
    ],
    "name:vie_x_preferred":[
        "Udorsky"
    ],
    "name:war_x_preferred":[
        "Udorsky"
    ],
    "name:zho_x_preferred":[
        "\u70cf\u591a\u723e\u65af\u57fa\u5340"
    ],
    "qs:name":"Koslan",
    "qs:photos_9r":0,
    "qs:photos_sr":0,
    "qs:pop_sr":"4",
    "wd:wordcount":964,
    "wof:name":"Koslan",
    "wof:placetype":"locality",
    "wof:population":2547
},
  "geometry": {"coordinates":[48.89891,63.45642],"type":"Point"}
}