{
  "type": "Feature",
  "properties": {
    "gn:country":"RU",
    "gn:fcode":"PPL",
    "gn:pop":2547,
    "iso:country":"RU",
    "name:eng_x_preferred":[
        "Koslan"
    ],
    "name:nor_x_preferred":[
        "Koslan"
    ],
    "name:rus_x_preferred":[
        "\u041a\u043e\u0441\u043b\u0430\u043d"
    ],
    "name:unk_x_variant":[
        "\u041a\u043e\u0441\u043b\u0430\u043d"
    ],
    "qs:name":"Koslan",
    "qs:photos_9r":0,
    "qs:photos_sr":0,
    "qs:pop_sr":"4",
    "wd:wordcount":964,
    "wof:name":"Koslan",
    "wof:placetype":"locality",
    "wof:population":2547
},
  "geometry": {"coordinates":[48.89891,63.45642],"type":"Point"}
}