{
  "type": "Feature",
  "properties": {
    "gn:admin1_code":"43.0",
    "gn:asciiname":"Demshinka",
    "gn:cc2":"RU",
    "gn:country_code":"RU",
    "gn:dem":134,
    "gn:feature_class":"P",
    "gn:feature_code":"PPL",
    "gn:name":"D\u00ebmshinka",
    "gn:population":0,
    "gn:timezone":"Europe/Moscow",
    "iso:country":"RU",
    "name:eng_x_preferred":[
        "D\u00ebmshinka"
    ],
    "name:nor_x_preferred":[
        "Demsjinka"
    ],
    "name:rus_x_preferred":[
        "\u0414\u0435\u043c\u0448\u0438\u043d\u043a\u0430"
    ],
    "name:rus_x_variant":[
        "D\u00ebmshinka",
        "\u0414\u0451\u043c\u0448\u0438\u043d\u043a\u0430",
        "D\u00ebmshinsk"
    ],
    "name:und_x_variant":[
        "D\u00ebmshinsk",
        "Demshinskoye",
        "D\u00ebmshinka",
        "\u0414\u0451\u043c\u0448\u0438\u043d\u043a\u0430"
    ],
    "wof:name":"Demshinka",
    "wof:placetype":"locality"
},
  "geometry": {"coordinates":[40.32167000000001,52.11306],"type":"Point"}
}