{
  "type": "Feature",
  "properties": {
    "gn:admin1_code":"44",
    "gn:asciiname":"Glukharinyy",
    "gn:country_code":"RU",
    "gn:dem":312,
    "gn:feature_class":"P",
    "gn:feature_code":"PPL",
    "gn:name":"Glukharinyy",
    "gn:population":0,
    "gn:timezone":"Asia/Magadan",
    "iso:country":"RU",
    "name:eng_x_preferred":[
        "Glukharinyy"
    ],
    "name:nor_x_preferred":[
        "Glukharinyj"
    ],
    "name:rus_x_preferred":[
        "\u0413\u043b\u0443\u0445\u0430\u0440\u0438\u043d\u044b\u0439"
    ],
    "name:und_x_variant":[
        "\u0413\u043b\u0443\u0445\u0430\u0440\u0438\u043d\u044b\u0439",
        "Glukharinyy"
    ],
    "wof:name":"Glukharinyy",
    "wof:placetype":"locality"
},
  "geometry": {"coordinates":[153.07961,64.99736],"type":"Point"}
}