{
  "type": "Feature",
  "properties": {
    "gn:admin1_code":"69.0",
    "gn:asciiname":"Dnesino",
    "gn:country_code":"RU",
    "gn:dem":172,
    "gn:feature_class":"P",
    "gn:feature_code":"PPL",
    "gn:name":"Dnesino",
    "gn:population":0,
    "gn:timezone":"Europe/Moscow",
    "iso:country":"RU",
    "name:rus_x_preferred":[
        "\u0414\u043d\u0435\u0441\u0438\u043d\u043e"
    ],
    "name:und_x_variant":[
        "\u0414\u043d\u0435\u0441\u0438\u043d\u043e"
    ],
    "wof:name":"Dnesino",
    "wof:placetype":"locality"
},
  "geometry": {"coordinates":[32.27808,53.91726],"type":"Point"}
}