{
  "type": "Feature",
  "properties": {
    "gn:admin1_code":"33",
    "gn:asciiname":"Khrobosty",
    "gn:country_code":"RU",
    "gn:dem":86,
    "gn:feature_class":"P",
    "gn:feature_code":"PPL",
    "gn:name":"Khrobosty",
    "gn:population":0,
    "gn:timezone":"Europe/Kirov",
    "iso:country":"RU",
    "name:rus_x_preferred":[
        "\u0425\u0440\u043e\u0431\u043e\u0441\u0442\u044b"
    ],
    "wof:name":"Khrobosty",
    "wof:placetype":"locality"
},
  "geometry": {"coordinates":[49.43,57.5507],"type":"Point"}
}