{
  "type": "Feature",
  "properties": {
    "gn:admin1_code":"51.0",
    "gn:asciiname":"Blagodatovka",
    "gn:country_code":"RU",
    "gn:dem":128,
    "gn:feature_class":"P",
    "gn:feature_code":"PPL",
    "gn:name":"Blagodatovka",
    "gn:population":0,
    "gn:timezone":"Europe/Moscow",
    "iso:country":"RU",
    "name:eng_x_preferred":[
        "Blagodatovka"
    ],
    "name:nor_x_preferred":[
        "Blagodatovka"
    ],
    "name:rus_x_preferred":[
        "\u0411\u043b\u0430\u0433\u043e\u0434\u0430\u0442\u043e\u0432\u043a\u0430"
    ],
    "wof:name":"Blagodatovka",
    "wof:placetype":"locality"
},
  "geometry": {"coordinates":[42.7146,55.0118],"type":"Point"}
}