{
  "type": "Feature",
  "properties": {
    "gn:admin1_code":"90.0",
    "gn:asciiname":"Kosoturikha",
    "gn:country_code":"RU",
    "gn:dem":141,
    "gn:feature_class":"P",
    "gn:feature_code":"PPL",
    "gn:name":"Kosoturikha",
    "gn:population":0,
    "gn:timezone":"Asia/Yekaterinburg",
    "iso:country":"RU",
    "name:che_x_preferred":[
        "\u041a\u043e\u0441\u043e\u0442\u0443\u0440\u0438\u0445\u0430"
    ],
    "name:rus_x_preferred":[
        "\u041a\u043e\u0441\u043e\u0442\u0443\u0440\u0438\u0445\u0430"
    ],
    "wof:name":"Kosoturikha",
    "wof:placetype":"locality"
},
  "geometry": {"coordinates":[55.8833,57.8722],"type":"Point"}
}