{
  "type": "Feature",
  "properties": {
    "gn:admin1_code":"51",
    "gn:asciiname":"Kardavil'",
    "gn:country_code":"RU",
    "gn:dem":187,
    "gn:feature_class":"P",
    "gn:feature_code":"PPL",
    "gn:name":"Kardavil\u2019",
    "gn:population":0,
    "gn:timezone":"Europe/Moscow",
    "iso:country":"RU",
    "name:rus_x_preferred":[
        "\u041a\u0430\u0440\u0434\u0430\u0432\u0438\u043b\u044c"
    ],
    "name:und_x_variant":[
        "Kordovil\u2019",
        "Kordovill",
        "Kardavil\u2019"
    ],
    "wof:name":"Kardavil'",
    "wof:placetype":"locality"
},
  "geometry": {"coordinates":[43.85671,55.12372],"type":"Point"}
}