{
  "type": "Feature",
  "properties": {
    "gn:admin1_code":"25",
    "gn:asciiname":"Mamonovo",
    "gn:country_code":"RU",
    "gn:dem":206,
    "gn:feature_class":"P",
    "gn:feature_code":"PPL",
    "gn:name":"Mamonovo",
    "gn:population":0,
    "gn:timezone":"Europe/Moscow",
    "iso:country":"RU",
    "name:ara_x_preferred":[
        "\u0645\u0627\u0645\u0648\u0646\u0648\u0641\u0648"
    ],
    "name:azb_x_preferred":[
        "\u0645\u0627\u0645\u0648\u0646\u0648\u0641\u0648"
    ],
    "name:aze_x_preferred":[
        "Mamonovo"
    ],
    "name:bel_x_preferred":[
        "\u041c\u0430\u043c\u043e\u043d\u0430\u0432\u0430"
    ],
    "name:bul_x_preferred":[
        "\u041c\u0430\u043c\u043e\u043d\u043e\u0432\u043e"
    ],
    "name:ceb_x_preferred":[
        "Mamonovo"
    ],
    "name:che_x_preferred":[
        "\u041c\u0430\u043c\u043e\u043d\u043e\u0432\u043e"
    ],
    "name:chv_x_preferred":[
        "\u041c\u0430\u043c\u043e\u043d\u043e\u0432\u043e"
    ],
    "name:deu_x_preferred":[
        "Mamonowo"
    ],
    "name:epo_x_preferred":[
        "Mamonovo"
    ],
    "name:fas_x_preferred":[
        "\u0645\u0627\u0645\u0648\u0646\u0648\u0641\u0648"
    ],
    "name:fin_x_preferred":[
        "Mamonovo"
    ],
    "name:fra_x_preferred":[
        "Mamonovo"
    ],
    "name:hsb_x_preferred":[
        "Mamonowo"
    ],
    "name:ita_x_preferred":[
        "Mamonovo"
    ],
    "name:jpn_x_preferred":[
        "\u30de\u30e2\u30ce\u30f4\u30a9"
    ],
    "name:kor_x_preferred":[
        "\ub9c8\ubaa8\ub178\ubcf4"
    ],
    "name:lav_x_preferred":[
        "Mamonova"
    ],
    "name:lit_x_preferred":[
        "\u0160ventapil\u0117"
    ],
    "name:nld_x_preferred":[
        "Mamonovo"
    ],
    "name:nno_x_preferred":[
        "Mamonovo"
    ],
    "name:nor_x_preferred":[
        "Mamonovo"
    ],
    "name:pol_x_preferred":[
        "Mamonowo"
    ],
    "name:rus_x_preferred":[
        "\u041c\u0430\u043c\u043e\u043d\u043e\u0432\u043e"
    ],
    "name:srp_x_preferred":[
        "\u041c\u0430\u043c\u043e\u043d\u043e\u0432\u043e"
    ],
    "name:swe_x_preferred":[
        "Mamonovo"
    ],
    "name:tat_x_preferred":[
        "\u041c\u0430\u043c\u043e\u043d\u043e\u0432\u043e"
    ],
    "name:tgk_x_preferred":[
        "\u041c\u0430\u043c\u043e\u043d\u043e\u0432\u043e"
    ],
    "name:tgl_x_preferred":[
        "Mamonovo"
    ],
    "name:tur_x_preferred":[
        "Mamonovo"
    ],
    "name:ukr_x_preferred":[
        "\u041c\u0430\u043c\u043e\u043d\u043e\u0432\u043e"
    ],
    "name:vep_x_preferred":[
        "Mamonovo"
    ],
    "name:war_x_preferred":[
        "Mamonovo"
    ],
    "name:zho_x_preferred":[
        "\u99ac\u83ab\u8afe\u592b"
    ],
    "wof:name":"Mamonovo",
    "wof:placetype":"locality"
},
  "geometry": {"coordinates":[36.61914,54.80416],"type":"Point"}
}