{
  "type": "Feature",
  "properties": {
    "gn:admin1_code":"25",
    "gn:asciiname":"Mamonovo",
    "gn:country_code":"RU",
    "gn:dem":206,
    "gn:feature_class":"P",
    "gn:feature_code":"PPL",
    "gn:name":"Mamonovo",
    "gn:population":0,
    "gn:timezone":"Europe/Moscow",
    "iso:country":"RU",
    "name:nor_x_preferred":[
        "Mamonovo"
    ],
    "name:rus_x_preferred":[
        "\u041c\u0430\u043c\u043e\u043d\u043e\u0432\u043e"
    ],
    "wof:name":"Mamonovo",
    "wof:placetype":"locality"
},
  "geometry": {"coordinates":[36.61914,54.80416],"type":"Point"}
}