{
  "type": "Feature",
  "properties": {
    "gn:admin1_code":"11",
    "gn:asciiname":"Sasanday",
    "gn:cc2":"RU",
    "gn:country_code":"RU",
    "gn:dem":615,
    "gn:feature_class":"P",
    "gn:feature_code":"PPL",
    "gn:name":"Sasanday",
    "gn:population":0,
    "gn:timezone":"Asia/Irkutsk",
    "iso:country":"RU",
    "name:rus_x_preferred":[
        "\u0421\u0430\u0441\u0430\u043d\u0434\u0430\u0439"
    ],
    "name:und_x_variant":[
        "Sagandoy",
        "Sasanday"
    ],
    "wof:name":"Sasanday",
    "wof:placetype":"locality"
},
  "geometry": {"coordinates":[110.59999999999999,54.15],"type":"Point"}
}