{
  "type": "Feature",
  "properties": {
    "gn:admin1_code":"77",
    "gn:asciiname":"Yablonnoye",
    "gn:country_code":"RU",
    "gn:dem":150,
    "gn:feature_class":"P",
    "gn:feature_code":"PPL",
    "gn:name":"Yablonnoye",
    "gn:population":0,
    "gn:timezone":"Europe/Moscow",
    "iso:country":"RU",
    "name:rus_x_preferred":[
        "\u042f\u0431\u043b\u043e\u043d\u043d\u043e\u0435"
    ],
    "name:und_x_variant":[
        "Yablonovo",
        "Yablonnoye"
    ],
    "wof:name":"Yablonnoye",
    "wof:placetype":"locality"
},
  "geometry": {"coordinates":[36.76456,57.96754],"type":"Point"}
}