{
  "type": "Feature",
  "properties": {
    "gn:admin1_code":"77",
    "gn:asciiname":"Dmitrovshchina",
    "gn:country_code":"RU",
    "gn:dem":227,
    "gn:feature_class":"P",
    "gn:feature_code":"PPL",
    "gn:name":"Dmitrovshchina",
    "gn:population":0,
    "gn:timezone":"Europe/Moscow",
    "iso:country":"RU",
    "name:rus_x_preferred":[
        "\u0414\u043c\u0438\u0442\u0440\u043e\u0432\u0449\u0438\u043d\u0430"
    ],
    "wof:name":"Dmitrovshchina",
    "wof:placetype":"locality"
},
  "geometry": {"coordinates":[32.78692,57.31957],"type":"Point"}
}