{
  "type": "Feature",
  "properties": {
    "gn:admin1_code":"60",
    "gn:asciiname":"Rozhnovo",
    "gn:country_code":"RU",
    "gn:dem":155,
    "gn:feature_class":"P",
    "gn:feature_code":"PPL",
    "gn:name":"Rozhnovo",
    "gn:population":0,
    "gn:timezone":"Europe/Moscow",
    "iso:country":"RU",
    "name:rus_x_preferred":[
        "\u0420\u043e\u0436\u043d\u043e\u0432\u043e"
    ],
    "name:und_x_variant":[
        "\u0420\u043e\u0436\u043d\u043e\u0432\u043e"
    ],
    "wof:name":"Rozhnovo",
    "wof:placetype":"locality"
},
  "geometry": {"coordinates":[30.0948,56.4178],"type":"Point"}
}