{
  "type": "Feature",
  "properties": {
    "gn:admin1_code":"47.0",
    "gn:asciiname":"Chegorovo",
    "gn:country_code":"RU",
    "gn:dem":158,
    "gn:feature_class":"P",
    "gn:feature_code":"PPL",
    "gn:name":"Chegorovo",
    "gn:population":0,
    "gn:timezone":"Europe/Moscow",
    "iso:country":"RU",
    "name:rus_x_preferred":[
        "\u0427\u0435\u0433\u043e\u0440\u043e\u0432\u043e"
    ],
    "wof:name":"Chegorovo",
    "wof:placetype":"locality"
},
  "geometry": {"coordinates":[39.1933,55.30492],"type":"Point"}
}