{
  "type": "Feature",
  "properties": {
    "gn:admin1_code":"41.0",
    "gn:asciiname":"Deryugino",
    "gn:country_code":"RU",
    "gn:dem":145,
    "gn:feature_class":"P",
    "gn:feature_code":"PPL",
    "gn:name":"Deryugino",
    "gn:population":0,
    "gn:timezone":"Europe/Moscow",
    "iso:country":"RU",
    "name:rus_x_preferred":[
        "\u0414\u0435\u0440\u044e\u0433\u0438\u043d\u043e"
    ],
    "name:und_x_variant":[
        "\u0414\u0435\u0440\u044e\u0433\u0438\u043d\u043e"
    ],
    "wof:name":"Deryugino",
    "wof:placetype":"locality"
},
  "geometry": {"coordinates":[34.8496,51.532],"type":"Point"}
}