{
  "type": "Feature",
  "properties": {
    "gn:admin1_code":"4",
    "gn:asciiname":"Removskiy",
    "gn:country_code":"RU",
    "gn:dem":240,
    "gn:feature_class":"P",
    "gn:feature_code":"PPL",
    "gn:name":"Removskiy",
    "gn:population":0,
    "gn:timezone":"Asia/Barnaul",
    "iso:country":"RU",
    "name:eng_x_preferred":[
        "Removskiy"
    ],
    "name:nor_x_preferred":[
        "Removskij"
    ],
    "name:rus_x_preferred":[
        "\u0420\u0435\u043c\u043e\u0432\u0441\u043a\u0438\u0439"
    ],
    "wof:name":"Removskiy",
    "wof:placetype":"locality"
},
  "geometry": {"coordinates":[81.22694,51.12806],"type":"Point"}
}