{
  "type": "Feature",
  "properties": {
    "gn:admin1_code":"20",
    "gn:asciiname":"Suvorovskiy",
    "gn:country_code":"RU",
    "gn:dem":327,
    "gn:feature_class":"P",
    "gn:feature_code":"PPL",
    "gn:name":"Suvorovskiy",
    "gn:population":0,
    "gn:timezone":"Asia/Irkutsk",
    "iso:country":"RU",
    "name:rus_x_preferred":[
        "\u0421\u0443\u0432\u043e\u0440\u043e\u0432\u0441\u043a\u0438\u0439"
    ],
    "wof:name":"Suvorovskiy",
    "wof:placetype":"locality"
},
  "geometry": {"coordinates":[103.9425,56.5028],"type":"Point"}
}