{
  "type": "Feature",
  "properties": {
    "gn:admin1_code":"47",
    "gn:asciiname":"Myakinino",
    "gn:country_code":"RU",
    "gn:dem":171,
    "gn:feature_class":"P",
    "gn:feature_code":"PPL",
    "gn:name":"Myakinino",
    "gn:population":0,
    "gn:timezone":"Europe/Moscow",
    "iso:country":"RU",
    "name:rus_x_preferred":[
        "\u041c\u044f\u043a\u0438\u043d\u0438\u043d\u043e"
    ],
    "name:und_x_variant":[
        "\u041c\u044f\u043a\u0438\u043d\u0438\u043d\u043e"
    ],
    "wof:name":"Myakinino",
    "wof:placetype":"locality"
},
  "geometry": {"coordinates":[36.8745,56.3603],"type":"Point"}
}