{
  "type": "Feature",
  "properties": {
    "gn:admin1_code":"33",
    "gn:asciiname":"Malyye Gari",
    "gn:country_code":"RU",
    "gn:dem":115,
    "gn:feature_class":"P",
    "gn:feature_code":"PPL",
    "gn:name":"Malyye Gari",
    "gn:population":0,
    "gn:timezone":"Europe/Kirov",
    "iso:country":"RU",
    "name:rus_x_preferred":[
        "\u041c\u0430\u043b\u044b\u0435 \u0413\u0430\u0440\u0438"
    ],
    "name:und_x_variant":[
        "\u041c\u0430\u043b\u044b\u0435 \u0413\u0430\u0440\u0438"
    ],
    "wof:name":"Malyye Gari",
    "wof:placetype":"locality"
},
  "geometry": {"coordinates":[49.09009,58.51556],"type":"Point"}
}