{
  "type": "Feature",
  "properties": {
    "gn:admin1_code":"17",
    "gn:asciiname":"Tsakhur",
    "gn:country_code":"RU",
    "gn:dem":1848,
    "gn:feature_class":"P",
    "gn:feature_code":"PPL",
    "gn:name":"Tsakhur",
    "gn:population":0,
    "gn:timezone":"Europe/Moscow",
    "iso:country":"RU",
    "name:eng_x_preferred":[
        "Tsakhur"
    ],
    "name:nor_x_preferred":[
        "Tsakhur"
    ],
    "name:rus_x_preferred":[
        "\u0426\u0430\u0445\u0443\u0440"
    ],
    "wof:name":"Tsakhur",
    "wof:placetype":"locality"
},
  "geometry": {"coordinates":[47.13657,41.65222],"type":"Point"}
}