{
  "type": "Feature",
  "properties": {
    "gn:admin1_code":"52",
    "gn:asciiname":"Shumilkino",
    "gn:country_code":"RU",
    "gn:dem":49,
    "gn:feature_class":"P",
    "gn:feature_code":"PPL",
    "gn:name":"Shumilkino",
    "gn:population":0,
    "gn:timezone":"Europe/Moscow",
    "iso:country":"RU",
    "name:rus_x_preferred":[
        "\u0428\u0443\u043c\u0438\u043b\u043a\u0438\u043d\u043e"
    ],
    "name:und_x_variant":[
        "\u0428\u0443\u043c\u0438\u043b\u043a\u0438\u043d\u043e"
    ],
    "wof:name":"Shumilkino",
    "wof:placetype":"locality"
},
  "geometry": {"coordinates":[31.7529,57.6724],"type":"Point"}
}