{
  "type": "Feature",
  "properties": {
    "gn:admin1_code":"85",
    "gn:asciiname":"Zhuregino",
    "gn:country_code":"RU",
    "gn:dem":186,
    "gn:feature_class":"P",
    "gn:feature_code":"PPL",
    "gn:name":"Zhuregino",
    "gn:population":0,
    "gn:timezone":"Europe/Moscow",
    "iso:country":"RU",
    "name:und_x_variant":[
        "Zhurechino",
        "Zhuregino"
    ],
    "wof:name":"Zhuregino",
    "wof:placetype":"locality"
},
  "geometry": {"coordinates":[41.33747,59.66031],"type":"Point"}
}