{
  "type": "Feature",
  "properties": {
    "gn:admin1_code":"33.0",
    "gn:asciiname":"Yefremovtsy",
    "gn:country_code":"RU",
    "gn:dem":175,
    "gn:feature_class":"P",
    "gn:feature_code":"PPL",
    "gn:name":"Yefremovtsy",
    "gn:population":0,
    "gn:timezone":"Europe/Kirov",
    "iso:country":"RU",
    "name:rus_x_preferred":[
        "\u0415\u0444\u0440\u0435\u043c\u043e\u0432\u0446\u044b"
    ],
    "wof:name":"Yefremovtsy",
    "wof:placetype":"locality"
},
  "geometry": {"coordinates":[48.09403,58.96082],"type":"Point"}
}