{
  "type": "Feature",
  "properties": {
    "gn:admin1_code":"23",
    "gn:asciiname":"Krasnooktyabr'skoye",
    "gn:country_code":"RU",
    "gn:dem":8,
    "gn:feature_class":"P",
    "gn:feature_code":"PPL",
    "gn:name":"Krasnooktyabr\u2019skoye",
    "gn:population":0,
    "gn:timezone":"Europe/Kaliningrad",
    "iso:country":"RU",
    "name:rus_x_preferred":[
        "\u041a\u0440\u0430\u0441\u043d\u043e\u043e\u043a\u0442\u044f\u0431\u0440\u044c\u0441\u043a\u043e\u0435"
    ],
    "name:und_x_variant":[
        "Gross Ponnau",
        "Krasnooktjarbrskoe",
        "Krasnooktyabr\u2019skoye",
        "\u041a\u0440\u0430\u0441\u043d\u043e\u043e\u043a\u0442\u044f\u0431\u0440\u044c\u0441\u043a\u043e\u0435"
    ],
    "wof:name":"Krasnooktyabr'skoye",
    "wof:placetype":"locality"
},
  "geometry": {"coordinates":[21.49176,54.68204],"type":"Point"}
}