{
  "type": "Feature",
  "properties": {
    "gn:admin1_code":"16",
    "gn:asciiname":"Shibulaty",
    "gn:country_code":"RU",
    "gn:dem":140,
    "gn:feature_class":"P",
    "gn:feature_code":"PPL",
    "gn:name":"Shibulaty",
    "gn:population":0,
    "gn:timezone":"Europe/Moscow",
    "iso:country":"RU",
    "name:rus_x_preferred":[
        "\u0428\u0438\u0431\u0443\u043b\u0430\u0442\u044b"
    ],
    "name:und_x_variant":[
        "Shibulatovo",
        "Shibulaty",
        "\u0428\u0438\u0431\u0443\u043b\u0430\u0442\u044b"
    ],
    "wof:name":"Shibulaty",
    "wof:placetype":"locality"
},
  "geometry": {"coordinates":[47.70137,55.74865],"type":"Point"}
}