{
  "type": "Feature",
  "properties": {
    "gn:admin1_code":"46",
    "gn:asciiname":"Grabovka",
    "gn:country_code":"RU",
    "gn:dem":138,
    "gn:feature_class":"P",
    "gn:feature_code":"PPL",
    "gn:name":"Grabovka",
    "gn:population":0,
    "gn:timezone":"Europe/Moscow",
    "iso:country":"RU",
    "name:rus_x_preferred":[
        "\u0413\u0440\u0430\u0431\u043e\u0432\u043a\u0430"
    ],
    "wof:name":"Grabovka",
    "wof:placetype":"locality"
},
  "geometry": {"coordinates":[45.1705,54.5394],"type":"Point"}
}