{
  "type": "Feature",
  "properties": {
    "gn:country":"RU",
    "gn:fcode":"PPL",
    "gn:pop":612,
    "iso:country":"RU",
    "name:eng_x_preferred":[
        "Alabino"
    ],
    "name:rus_x_preferred":[
        "\u0410\u043b\u0430\u0431\u0438\u043d\u043e"
    ],
    "name:unk_x_variant":[
        "Alabino"
    ],
    "qs:name":"Aladino",
    "qs:name_adm0":"Russia",
    "qs:name_adm1":"Kaluga Oblast",
    "qs:photos_9r":0,
    "qs:photos_sr":0,
    "qs:placetype":"Town",
    "qs:pop_sr":"2",
    "wof:name":"Aladino",
    "wof:placetype":"locality",
    "wof:population":612
},
  "geometry": {"coordinates":[37.01028,55.52679],"type":"Point"}
}