{
  "type": "Feature",
  "properties": {
    "gn:admin1_code":"38",
    "gn:asciiname":"Krasnaya Moskva",
    "gn:cc2":"RU",
    "gn:country_code":"RU",
    "gn:dem":89,
    "gn:feature_class":"P",
    "gn:feature_code":"PPL",
    "gn:name":"Krasnaya Moskva",
    "gn:population":0,
    "gn:timezone":"Europe/Moscow",
    "iso:country":"RU",
    "name:und_x_variant":[
        "Moskva"
    ],
    "wof:name":"Krasnaya Moskva",
    "wof:placetype":"locality"
},
  "geometry": {"coordinates":[40.42167,45.58528],"type":"Point"}
}