{
  "type": "Feature",
  "properties": {
    "gn:admin1_code":"38",
    "gn:asciiname":"Krasnaya Moskva",
    "gn:cc2":"RU",
    "gn:country_code":"RU",
    "gn:dem":89,
    "gn:feature_class":"P",
    "gn:feature_code":"PPL",
    "gn:name":"Krasnaya Moskva",
    "gn:population":0,
    "gn:timezone":"Europe/Moscow",
    "iso:country":"RU",
    "name:heb_x_preferred":[
        "\u05de\u05d5\u05e1\u05e7\u05d1\u05d4 \u05d0\u05d3\u05d5\u05de\u05d4"
    ],
    "name:hye_x_preferred":[
        "\u053f\u0561\u0580\u0574\u056b\u0580 \u0544\u0578\u057d\u056f\u057e\u0561"
    ],
    "name:rus_x_preferred":[
        "\u041a\u0440\u0430\u0441\u043d\u0430\u044f \u041c\u043e\u0441\u043a\u0432\u0430"
    ],
    "name:und_x_variant":[
        "Moskva"
    ],
    "wof:name":"Krasnaya Moskva",
    "wof:placetype":"locality"
},
  "geometry": {"coordinates":[40.42167,45.58528],"type":"Point"}
}