{
  "type": "Feature",
  "properties": {
    "gn:country":"RU",
    "gn:fcode":"PPL",
    "gn:pop":3593,
    "iso:country":"RU",
    "name:ceb_x_preferred":[
        "Sinyavino"
    ],
    "name:che_x_preferred":[
        "\u0421\u0438\u043d\u044f\u0432\u0438\u043d\u043e"
    ],
    "name:deu_x_preferred":[
        "Sinjawino"
    ],
    "name:eng_x_preferred":[
        "Sinyavino"
    ],
    "name:fin_x_preferred":[
        "Vahriselk\u00e4"
    ],
    "name:fra_x_preferred":[
        "Siniavino"
    ],
    "name:hye_x_preferred":[
        "\u054d\u056b\u0576\u0575\u0561\u057e\u056b\u0576\u0578"
    ],
    "name:ita_x_preferred":[
        "Sinjavino"
    ],
    "name:nld_x_preferred":[
        "Sinjavino"
    ],
    "name:nor_x_preferred":[
        "Sinjavino"
    ],
    "name:pol_x_preferred":[
        "Siniawino"
    ],
    "name:por_x_preferred":[
        "Sini\u00e1vino"
    ],
    "name:rus_x_preferred":[
        "\u0421\u0438\u043d\u044f\u0432\u0438\u043d\u043e"
    ],
    "name:sco_x_preferred":[
        "Sinyavino"
    ],
    "name:srp_x_preferred":[
        "\u0421\u0438\u045a\u0430\u0432\u0438\u043d\u043e"
    ],
    "name:unk_x_variant":[
        "Sinyavino Nomer Pervyy"
    ],
    "name:vie_x_preferred":[
        "Sinyavino"
    ],
    "qs:name":"Sinyavino 2",
    "qs:name_adm0":"Russia",
    "qs:name_adm1":"Leningrad Oblast",
    "qs:photos_9r":0,
    "qs:photos_sr":0,
    "qs:placetype":"Town",
    "qs:pop_sr":"4",
    "wof:name":"Sinyavino 2",
    "wof:placetype":"locality",
    "wof:population":3593
},
  "geometry": {"coordinates":[31.0711,59.90781],"type":"Point"}
}