{
  "type": "Feature",
  "properties": {
    "gn:admin1_code":"25.0",
    "gn:asciiname":"Brusny",
    "gn:country_code":"RU",
    "gn:dem":179,
    "gn:feature_class":"P",
    "gn:feature_code":"PPL",
    "gn:name":"Brusny",
    "gn:population":0,
    "gn:timezone":"Europe/Moscow",
    "iso:country":"RU",
    "name:rus_x_preferred":[
        "\u0411\u0440\u0443\u0441\u043d\u044b"
    ],
    "name:und_x_variant":[
        "Brusna",
        "Brusny"
    ],
    "wof:name":"Brusny",
    "wof:placetype":"locality"
},
  "geometry": {"coordinates":[35.19891,53.69339],"type":"Point"}
}