{
  "type": "Feature",
  "properties": {
    "gn:admin1_code":"33.0",
    "gn:asciiname":"Chernushka",
    "gn:country_code":"RU",
    "gn:dem":83,
    "gn:feature_class":"P",
    "gn:feature_code":"PPL",
    "gn:name":"Chernushka",
    "gn:population":0,
    "gn:timezone":"Europe/Kirov",
    "iso:country":"RU",
    "name:ceb_x_preferred":[
        "Chernushka"
    ],
    "name:eng_x_preferred":[
        "Chernushka"
    ],
    "name:nor_x_preferred":[
        "Tsjernusjka"
    ],
    "name:rus_x_preferred":[
        "\u0427\u0435\u0440\u043d\u0443\u0448\u043a\u0430"
    ],
    "name:swe_x_preferred":[
        "Chernushka"
    ],
    "name:tgl_x_preferred":[
        "Chernushka"
    ],
    "name:und_x_variant":[
        "\u0427\u0435\u0440\u043d\u0443\u0448\u043a\u0430",
        "Chernushka"
    ],
    "wof:name":"Chernushka",
    "wof:placetype":"locality"
},
  "geometry": {"coordinates":[50.79549,56.98345],"type":"Point"}
}