{
  "type": "Feature",
  "properties": {
    "gn:country":"RU",
    "gn:fcode":"ADMD",
    "gn:population":0,
    "iso:country":"RU",
    "name:rus_x_preferred":[
        "\u041d\u043e\u0432\u043e\u0443\u0441\u043c\u0430\u043d\u0441\u043a\u0438\u0439 \u0420\u0430\u0439\u043e\u043d"
    ],
    "qs:name":"Novousmanskiy Rayon",
    "qs:photos_9r":0,
    "qs:photos_sr":0,
    "qs:pop_sr":"0",
    "wof:name":"Novousmanskiy Rayon",
    "wof:placetype":"localadmin",
    "wof:population":0
},
  "geometry": {"coordinates":[39.41667,51.58333],"type":"Point"}
}