{
  "type": "Feature",
  "properties": {
    "gn:admin1_code":"20.0",
    "gn:asciiname":"Grekhnevka",
    "gn:country_code":"RU",
    "gn:dem":443,
    "gn:feature_class":"P",
    "gn:feature_code":"PPL",
    "gn:name":"Grekhnevka",
    "gn:population":0,
    "gn:timezone":"Asia/Irkutsk",
    "iso:country":"RU",
    "name:rus_x_preferred":[
        "\u0413\u0440\u0435\u0445\u043d\u0435\u0432\u043a\u0430"
    ],
    "wof:name":"Grekhnevka",
    "wof:placetype":"locality"
},
  "geometry": {"coordinates":[103.77,52.89972],"type":"Point"}
}