{
  "type": "Feature",
  "properties": {
    "gn:admin1_code":"76",
    "gn:asciiname":"Kakurino",
    "gn:country_code":"RU",
    "gn:dem":208,
    "gn:feature_class":"P",
    "gn:feature_code":"PPL",
    "gn:name":"Kakurino",
    "gn:population":0,
    "gn:timezone":"Europe/Moscow",
    "iso:country":"RU",
    "name:rus_x_preferred":[
        "\u041a\u0430\u043a\u0443\u0440\u0438\u043d\u043e"
    ],
    "wof:name":"Kakurino",
    "wof:placetype":"locality"
},
  "geometry": {"coordinates":[36.09888,53.9134],"type":"Point"}
}