{
  "type": "Feature",
  "properties": {
    "gn:admin1_code":"34",
    "gn:asciiname":"Zagrivochnaya",
    "gn:country_code":"RU",
    "gn:dem":75,
    "gn:feature_class":"P",
    "gn:feature_code":"PPL",
    "gn:name":"Zagrivochnaya",
    "gn:population":0,
    "gn:timezone":"Europe/Moscow",
    "iso:country":"RU",
    "name:eng_x_preferred":[
        "Zagrivochnaya"
    ],
    "name:nor_x_preferred":[
        "Zagrivotsjnaja"
    ],
    "name:rus_x_preferred":[
        "\u0417\u0430\u0433\u0440\u0438\u0432\u043e\u0447\u043d\u0430\u044f"
    ],
    "wof:name":"Zagrivochnaya",
    "wof:placetype":"locality"
},
  "geometry": {"coordinates":[51.94586,65.09018],"type":"Point"}
}