{
  "type": "Feature",
  "properties": {
    "gn:admin1_code":"57",
    "gn:asciiname":"Novaya Studenovka",
    "gn:country_code":"RU",
    "gn:dem":176,
    "gn:feature_class":"P",
    "gn:feature_code":"PPL",
    "gn:name":"Novaya Stud\u00ebnovka",
    "gn:population":0,
    "gn:timezone":"Europe/Moscow",
    "iso:country":"RU",
    "name:eng_x_preferred":[
        "Novaya Stud\u00ebnovka"
    ],
    "name:nor_x_preferred":[
        "Nov. Studenovka"
    ],
    "name:rus_x_preferred":[
        "\u041d\u043e\u0432. \u0421\u0442\u0443\u0434\u0435\u043d\u043e\u0432\u043a\u0430"
    ],
    "name:rus_x_variant":[
        "\u041d\u043e\u0432\u0430\u044f \u0421\u0442\u0443\u0434\u0451\u043d\u043e\u0432\u043a\u0430"
    ],
    "name:und_x_variant":[
        "Novaya Stud\u00ebnovka"
    ],
    "wof:name":"Novaya Studenovka",
    "wof:placetype":"locality"
},
  "geometry": {"coordinates":[44.37178,52.44026],"type":"Point"}
}