{
  "type": "Feature",
  "properties": {
    "gn:admin1_code":"69",
    "gn:asciiname":"Nekrasy",
    "gn:country_code":"RU",
    "gn:dem":183,
    "gn:feature_class":"P",
    "gn:feature_code":"PPL",
    "gn:name":"Nekrasy",
    "gn:population":0,
    "gn:timezone":"Europe/Moscow",
    "iso:country":"RU",
    "name:rus_x_preferred":[
        "\u041d\u0435\u043a\u0440\u0430\u0441\u044b"
    ],
    "name:und_x_variant":[
        "\u041d\u0435\u043a\u0440\u0430\u0441\u044b"
    ],
    "wof:name":"Nekrasy",
    "wof:placetype":"locality"
},
  "geometry": {"coordinates":[33.71632,54.6436],"type":"Point"}
}