{
  "type": "Feature",
  "properties": {
    "gn:admin1_code":"63",
    "gn:asciiname":"Petushki",
    "gn:country_code":"RU",
    "gn:dem":5,
    "gn:feature_class":"P",
    "gn:feature_code":"PPL",
    "gn:name":"Petushki",
    "gn:population":0,
    "gn:timezone":"Asia/Magadan",
    "iso:country":"RU",
    "name:eng_x_preferred":[
        "Petushki"
    ],
    "name:nor_x_preferred":[
        "Petusjki"
    ],
    "name:rus_x_preferred":[
        "\u041f\u0435\u0442\u0443\u0448\u043a\u0438"
    ],
    "name:und_x_variant":[
        "Petushek",
        "Petushok",
        "\u041f\u0435\u0442\u0443\u0448\u043a\u0438",
        "Petushki"
    ],
    "wof:name":"Petushki",
    "wof:placetype":"locality"
},
  "geometry": {"coordinates":[161.54987,68.99231],"type":"Point"}
}