{
  "type": "Feature",
  "properties": {
    "gn:admin1_code":"77",
    "gn:asciiname":"Pervitino",
    "gn:country_code":"RU",
    "gn:dem":151,
    "gn:feature_class":"P",
    "gn:feature_code":"PPL",
    "gn:name":"Pervitino",
    "gn:population":0,
    "gn:timezone":"Europe/Moscow",
    "iso:country":"RU",
    "name:rus_x_preferred":[
        "\u041f\u0435\u0440\u0432\u0438\u0442\u0438\u043d\u043e"
    ],
    "name:und_x_variant":[
        "\u041f\u0435\u0440\u0432\u0438\u0442\u0438\u043d\u043e"
    ],
    "wof:name":"Pervitino",
    "wof:placetype":"locality"
},
  "geometry": {"coordinates":[35.67805999999999,57.12621],"type":"Point"}
}