{
  "type": "Feature",
  "properties": {
    "gn:admin1_code":"44",
    "gn:asciiname":"Glubokiy",
    "gn:cc2":"RU",
    "gn:country_code":"RU",
    "gn:dem":578,
    "gn:feature_class":"P",
    "gn:feature_code":"PPL",
    "gn:name":"Glubokiy",
    "gn:population":0,
    "gn:timezone":"Asia/Magadan",
    "iso:country":"RU",
    "name:rus_x_preferred":[
        "\u0413\u043b\u0443\u0431\u043e\u043a\u0438\u0439"
    ],
    "name:und_x_variant":[
        "Gluboky",
        "Glubokiy",
        "\u0413\u043b\u0443\u0431\u043e\u043a\u0438\u0439"
    ],
    "wof:name":"Glubokiy",
    "wof:placetype":"locality"
},
  "geometry": {"coordinates":[150.21666999999999,62.36666999999999],"type":"Point"}
}