{
  "type": "Feature",
  "properties": {
    "gn:admin1_code":"88",
    "gn:asciiname":"Mil'kovo",
    "gn:country_code":"RU",
    "gn:dem":126,
    "gn:feature_class":"P",
    "gn:feature_code":"PPL",
    "gn:name":"Mil\u2019kovo",
    "gn:population":0,
    "gn:timezone":"Europe/Moscow",
    "iso:country":"RU",
    "name:rus_x_preferred":[
        "\u041c\u0438\u043b\u044c\u043a\u043e\u0432\u043e"
    ],
    "name:und_x_variant":[
        "Mil\u2019kovo",
        "\u041c\u0438\u043b\u044c\u043a\u043e\u0432\u043e"
    ],
    "wof:name":"Mil'kovo",
    "wof:placetype":"locality"
},
  "geometry": {"coordinates":[38.6787,57.8637],"type":"Point"}
}