{
  "type": "Feature",
  "properties": {
    "gn:admin1_code":"60",
    "gn:asciiname":"Nosyrevo",
    "gn:country_code":"RU",
    "gn:dem":94,
    "gn:feature_class":"P",
    "gn:feature_code":"PPL",
    "gn:name":"Nosyrevo",
    "gn:population":0,
    "gn:timezone":"Europe/Moscow",
    "iso:country":"RU",
    "name:rus_x_preferred":[
        "\u041d\u043e\u0441\u044b\u0440\u0435\u0432\u043e"
    ],
    "name:und_x_variant":[
        "\u041d\u043e\u0441\u044b\u0440\u0435\u0432\u043e"
    ],
    "wof:name":"Nosyrevo",
    "wof:placetype":"locality"
},
  "geometry": {"coordinates":[28.40978,58.05311999999999],"type":"Point"}
}