{
  "type": "Feature",
  "properties": {
    "gn:admin1_code":"80",
    "gn:asciiname":"Sredneye Kechevo",
    "gn:country_code":"RU",
    "gn:dem":126,
    "gn:feature_class":"P",
    "gn:feature_code":"PPL",
    "gn:name":"Sredneye Kechevo",
    "gn:population":0,
    "gn:timezone":"Europe/Samara",
    "iso:country":"RU",
    "name:nor_x_preferred":[
        "Sredneje Ketsjevo"
    ],
    "name:rus_x_preferred":[
        "\u0421\u0440\u0435\u0434\u043d\u0435\u0435 \u041a\u0435\u0447\u0435\u0432\u043e"
    ],
    "name:und_x_variant":[
        "Sredne-Kichevo",
        "Sredneye Kichevo",
        "Sredneye Kechevo"
    ],
    "wof:name":"Sredneye Kechevo",
    "wof:placetype":"locality"
},
  "geometry": {"coordinates":[53.21496,56.52652],"type":"Point"}
}