{
  "type": "Feature",
  "properties": {
    "gn:admin1_code":"45",
    "gn:asciiname":"Kumkudyanova",
    "gn:country_code":"RU",
    "gn:dem":132,
    "gn:feature_class":"P",
    "gn:feature_code":"PPL",
    "gn:name":"Kumkudyanova",
    "gn:population":0,
    "gn:timezone":"Europe/Moscow",
    "iso:country":"RU",
    "name:rus_x_preferred":[
        "\u041a\u0443\u043c\u043a\u0443\u0434\u044f\u043d\u043e\u0432\u0430"
    ],
    "name:und_x_variant":[
        "\u041a\u0443\u043c\u043a\u0443\u0434\u044f\u043d\u043e\u0432\u0430"
    ],
    "wof:name":"Kumkudyanova",
    "wof:placetype":"locality"
},
  "geometry": {"coordinates":[49.03333,57.18333000000001],"type":"Point"}
}