{
  "type": "Feature",
  "properties": {
    "gn:admin1_code":"88",
    "gn:asciiname":"Shchelkovo",
    "gn:country_code":"RU",
    "gn:dem":134,
    "gn:feature_class":"P",
    "gn:feature_code":"PPL",
    "gn:name":"Shch\u00eblkovo",
    "gn:population":0,
    "gn:timezone":"Europe/Moscow",
    "iso:country":"RU",
    "name:rus_x_preferred":[
        "\u0429\u0451\u043b\u043a\u043e\u0432\u043e"
    ],
    "name:und_x_variant":[
        "Shch\u00eblkovo",
        "\u0429\u0451\u043b\u043a\u043e\u0432\u043e"
    ],
    "wof:name":"Shchelkovo",
    "wof:placetype":"locality"
},
  "geometry": {"coordinates":[37.8358,57.4545],"type":"Point"}
}