{
  "type": "Feature",
  "properties": {
    "gn:admin1_code":"28",
    "gn:asciiname":"Piyen-Tulola",
    "gn:country_code":"RU",
    "gn:dem":57,
    "gn:feature_class":"P",
    "gn:feature_code":"PPL",
    "gn:name":"Piyen-Tulola",
    "gn:population":0,
    "gn:timezone":"Europe/Moscow",
    "iso:country":"RU",
    "name:fin_x_preferred":[
        "Pien-Tulola"
    ],
    "name:rus_x_preferred":[
        "\u041f\u0438\u0435\u043d-\u0422\u0443\u043b\u043e\u043b\u0430"
    ],
    "wof:name":"Piyen-Tulola",
    "wof:placetype":"locality"
},
  "geometry": {"coordinates":[30.84549,61.69817],"type":"Point"}
}