{
  "type": "Feature",
  "properties": {
    "gn:admin1_code":"47.0",
    "gn:asciiname":"Belorussiya",
    "gn:country_code":"RU",
    "gn:dem":222,
    "gn:feature_class":"P",
    "gn:feature_code":"PPL",
    "gn:name":"Belorussiya",
    "gn:population":0,
    "gn:timezone":"Europe/Moscow",
    "iso:country":"RU",
    "name:nor_x_preferred":[
        "Belorussia"
    ],
    "name:rus_x_preferred":[
        "\u0411\u0435\u043b\u043e\u0440\u0443\u0441\u0441\u0438\u044f"
    ],
    "wof:name":"Belorussiya",
    "wof:placetype":"locality"
},
  "geometry": {"coordinates":[35.56667,55.73333],"type":"Point"}
}