{
  "type": "Feature",
  "properties": {
    "gn:admin1_code":"47",
    "gn:asciiname":"Kuprovo",
    "gn:country_code":"RU",
    "gn:dem":201,
    "gn:feature_class":"P",
    "gn:feature_code":"PPL",
    "gn:name":"Kuprovo",
    "gn:population":0,
    "gn:timezone":"Europe/Moscow",
    "iso:country":"RU",
    "name:rus_x_preferred":[
        "\u041a\u0443\u043f\u0440\u043e\u0432\u043e"
    ],
    "wof:name":"Kuprovo",
    "wof:placetype":"locality"
},
  "geometry": {"coordinates":[35.70833,55.36778],"type":"Point"}
}