{
  "type": "Feature",
  "properties": {
    "gn:admin1_code":"7.0",
    "gn:asciiname":"Anisimovich",
    "gn:country_code":"RU",
    "gn:dem":-24,
    "gn:feature_class":"P",
    "gn:feature_code":"PPL",
    "gn:name":"Anisimovich",
    "gn:population":0,
    "gn:timezone":"Europe/Astrakhan",
    "iso:country":"RU",
    "name:nor_x_preferred":[
        "Anisimovitsj"
    ],
    "name:rus_x_preferred":[
        "\u0410\u043d\u0438\u0441\u0438\u043c\u043e\u0432\u0438\u0447"
    ],
    "wof:name":"Anisimovich",
    "wof:placetype":"locality"
},
  "geometry": {"coordinates":[47.39278,47.1675],"type":"Point"}
}