{
  "type": "Feature",
  "properties": {
    "gn:admin1_code":"16",
    "gn:asciiname":"Magazeynaya",
    "gn:country_code":"RU",
    "gn:dem":152,
    "gn:feature_class":"P",
    "gn:feature_code":"PPL",
    "gn:name":"Magazeynaya",
    "gn:population":0,
    "gn:timezone":"Europe/Moscow",
    "iso:country":"RU",
    "name:rus_x_preferred":[
        "\u041c\u0430\u0433\u0430\u0437\u0435\u0439\u043d\u0430\u044f"
    ],
    "name:und_x_variant":[
        "\u041c\u0430\u0433\u0430\u0437\u0435\u0439\u043d\u0430\u044f"
    ],
    "wof:name":"Magazeynaya",
    "wof:placetype":"locality"
},
  "geometry": {"coordinates":[46.7987,56.1712],"type":"Point"}
}