{
  "type": "Feature",
  "properties": {
    "gn:admin1_code":"90",
    "gn:asciiname":"Pisanoye",
    "gn:country_code":"RU",
    "gn:dem":207,
    "gn:feature_class":"P",
    "gn:feature_code":"PPL",
    "gn:name":"Pisanoye",
    "gn:population":0,
    "gn:timezone":"Asia/Yekaterinburg",
    "iso:country":"RU",
    "name:eng_x_preferred":[
        "Pisanoye"
    ],
    "name:nor_x_preferred":[
        "Pisanoje"
    ],
    "name:rus_x_preferred":[
        "\u041f\u0438\u0441\u0430\u043d\u043e\u0435"
    ],
    "name:und_x_variant":[
        "Pisanaya"
    ],
    "wof:name":"Pisanoye",
    "wof:placetype":"locality"
},
  "geometry": {"coordinates":[57.99612,60.52006],"type":"Point"}
}