{
  "type": "Feature",
  "properties": {
    "gn:admin1_code":"57",
    "gn:asciiname":"Elita",
    "gn:country_code":"RU",
    "gn:dem":246,
    "gn:feature_class":"P",
    "gn:feature_code":"PPL",
    "gn:name":"Elita",
    "gn:population":0,
    "gn:timezone":"Europe/Moscow",
    "iso:country":"RU",
    "name:rus_x_preferred":[
        "\u042d\u043b\u0438\u0442\u0430"
    ],
    "name:uzb_x_preferred":[
        "Elita"
    ],
    "wof:name":"Elita",
    "wof:placetype":"locality"
},
  "geometry": {"coordinates":[44.7873,53.265],"type":"Point"}
}