{
  "type": "Feature",
  "properties": {
    "gn:admin1_code":"80",
    "gn:asciiname":"Loloshur-Vozzhi",
    "gn:country_code":"RU",
    "gn:dem":103,
    "gn:feature_class":"P",
    "gn:feature_code":"PPL",
    "gn:name":"Loloshur-Vozzhi",
    "gn:population":0,
    "gn:timezone":"Europe/Samara",
    "iso:country":"RU",
    "name:eng_x_preferred":[
        "Loloshur-Vozzhi"
    ],
    "name:nor_x_preferred":[
        "Lolosjur Vozzji"
    ],
    "name:rus_x_preferred":[
        "\u041b\u043e\u043b\u043e\u0448\u0443\u0440 \u0412\u043e\u0437\u0436\u0438"
    ],
    "name:rus_x_variant":[
        "\u041b\u043e\u043b\u043e\u0448\u0443\u0440-\u0412\u043e\u0437\u0436\u0438"
    ],
    "name:und_x_variant":[
        "Loloshur-Bozzhi"
    ],
    "wof:name":"Loloshur-Vozzhi",
    "wof:placetype":"locality"
},
  "geometry": {"coordinates":[51.77251,55.99725],"type":"Point"}
}