{
  "type": "Feature",
  "properties": {
    "gn:admin1_code":"88",
    "gn:asciiname":"Andreyevskaya",
    "gn:country_code":"RU",
    "gn:dem":114,
    "gn:feature_class":"P",
    "gn:feature_code":"PPL",
    "gn:name":"Andreyevskaya",
    "gn:population":0,
    "gn:timezone":"Europe/Moscow",
    "iso:country":"RU",
    "name:rus_x_preferred":[
        "\u0410\u043d\u0434\u0440\u0435\u0435\u0432\u0441\u043a\u0430\u044f"
    ],
    "name:und_x_variant":[
        "\u0410\u043d\u0434\u0440\u0435\u0435\u0432\u0441\u043a\u0430\u044f"
    ],
    "wof:name":"Andreyevskaya",
    "wof:placetype":"locality"
},
  "geometry": {"coordinates":[38.3301,57.9135],"type":"Point"}
}