{
  "type": "Feature",
  "properties": {
    "gn:admin1_code":"77",
    "gn:asciiname":"Amshara",
    "gn:country_code":"RU",
    "gn:dem":230,
    "gn:feature_class":"P",
    "gn:feature_code":"PPL",
    "gn:name":"Amshara",
    "gn:population":0,
    "gn:timezone":"Europe/Moscow",
    "iso:country":"RU",
    "name:nor_x_preferred":[
        "Amsjara"
    ],
    "name:rus_x_preferred":[
        "\u0410\u043c\u0448\u0430\u0440\u0430"
    ],
    "wof:name":"Amshara",
    "wof:placetype":"locality"
},
  "geometry": {"coordinates":[33.27639,56.31056],"type":"Point"}
}