{
  "type": "Feature",
  "properties": {
    "gn:admin1_code":"8",
    "gn:asciiname":"Nizhneye Absalyamovo",
    "gn:country_code":"RU",
    "gn:dem":260,
    "gn:feature_class":"P",
    "gn:feature_code":"PPL",
    "gn:name":"Nizhneye Absalyamovo",
    "gn:population":0,
    "gn:timezone":"Asia/Yekaterinburg",
    "iso:country":"RU",
    "name:rus_x_preferred":[
        "\u041d\u0438\u0436\u043d\u0435\u0435 \u0410\u0431\u0441\u0430\u043b\u044f\u043c\u043e\u0432\u043e"
    ],
    "name:und_x_variant":[
        "Apsalyamova",
        "Nizhnyaya Absalyamova",
        "Nizhneye Absalyamovo",
        "\u041d\u0438\u0436\u043d\u0435\u0435 \u0410\u0431\u0441\u0430\u043b\u044f\u043c\u043e\u0432\u043e"
    ],
    "wof:name":"Nizhneye Absalyamovo",
    "wof:placetype":"locality"
},
  "geometry": {"coordinates":[58.18806,55.5925],"type":"Point"}
}