{
  "type": "Feature",
  "properties": {
    "gn:admin1_code":"8",
    "gn:asciiname":"Nizhneye Absalyamovo",
    "gn:country_code":"RU",
    "gn:dem":260,
    "gn:feature_class":"P",
    "gn:feature_code":"PPL",
    "gn:name":"Nizhneye Absalyamovo",
    "gn:population":0,
    "gn:timezone":"Asia/Yekaterinburg",
    "iso:country":"RU",
    "name:bak_x_preferred":[
        "\u0422\u04af\u0431\u04d9\u043d\u0433\u0435 \u04d8\u0431\u0441\u04d9\u043b\u04d9\u043c"
    ],
    "name:che_x_preferred":[
        "\u041d\u0438\u0436\u043d\u0438 \u0410\u0431\u0441\u0430\u043b\u044f\u043c\u043e\u0432\u043e"
    ],
    "name:hye_x_preferred":[
        "\u0546\u056b\u056a\u0576\u0565\u0565 \u0531\u0562\u057d\u0561\u056c\u0575\u0561\u0574\u0578\u057e\u0578"
    ],
    "name:rus_x_preferred":[
        "\u041d\u0438\u0436\u043d\u0435\u0435 \u0410\u0431\u0441\u0430\u043b\u044f\u043c\u043e\u0432\u043e"
    ],
    "name:und_x_variant":[
        "Apsalyamova",
        "Nizhnyaya Absalyamova",
        "Nizhneye Absalyamovo"
    ],
    "wof:name":"Nizhneye Absalyamovo",
    "wof:placetype":"locality"
},
  "geometry": {"coordinates":[58.18806,55.5925],"type":"Point"}
}