{
  "type": "Feature",
  "properties": {
    "gn:admin1_code":"90",
    "gn:asciiname":"Verkhniy Tyush",
    "gn:country_code":"RU",
    "gn:dem":276,
    "gn:feature_class":"P",
    "gn:feature_code":"PPL",
    "gn:name":"Verkhniy Tyush",
    "gn:population":0,
    "gn:timezone":"Asia/Yekaterinburg",
    "iso:country":"RU",
    "name:rus_x_preferred":[
        "\u0412\u0435\u0440\u0445\u043d\u0438\u0439 \u0422\u044e\u0448"
    ],
    "name:und_x_variant":[
        "Verkhniy Tyush Pervyy",
        "Verkhniy Tyush"
    ],
    "wof:name":"Verkhniy Tyush",
    "wof:placetype":"locality"
},
  "geometry": {"coordinates":[57.115,56.6766],"type":"Point"}
}