{
  "type": "Feature",
  "properties": {
    "gn:admin1_code":"25.0",
    "gn:asciiname":"Podvyazki",
    "gn:country_code":"RU",
    "gn:dem":196,
    "gn:feature_class":"P",
    "gn:feature_code":"PPL",
    "gn:name":"Podvyazki",
    "gn:population":0,
    "gn:timezone":"Europe/Moscow",
    "iso:country":"RU",
    "name:rus_x_preferred":[
        "\u041f\u043e\u0434\u0432\u044f\u0437\u043a\u0438"
    ],
    "name:und_x_variant":[
        "\u041f\u043e\u0434\u0432\u044f\u0437\u043a\u0438"
    ],
    "wof:name":"Podvyazki",
    "wof:placetype":"locality"
},
  "geometry": {"coordinates":[35.04,54.53],"type":"Point"}
}