{
  "type": "Feature",
  "properties": {
    "gn:admin1_code":"34",
    "gn:asciiname":"Iosser",
    "gn:country_code":"RU",
    "gn:dem":137,
    "gn:feature_class":"P",
    "gn:feature_code":"PPL",
    "gn:name":"Iosser",
    "gn:population":0,
    "gn:timezone":"Europe/Moscow",
    "iso:country":"RU",
    "name:eng_x_preferred":[
        "Iosser"
    ],
    "name:nor_x_preferred":[
        "Iosser"
    ],
    "name:rus_x_preferred":[
        "\u0418\u043e\u0441\u0441\u0435\u0440"
    ],
    "name:und_x_variant":[
        "Losser",
        "Ioser"
    ],
    "wof:name":"Iosser",
    "wof:placetype":"locality"
},
  "geometry": {"coordinates":[52.18213,62.99588000000001],"type":"Point"}
}