{
  "type": "Feature",
  "properties": {
    "gn:admin1_code":"8",
    "gn:asciiname":"Moskovo",
    "gn:country_code":"RU",
    "gn:dem":416,
    "gn:feature_class":"P",
    "gn:feature_code":"PPL",
    "gn:name":"Moskovo",
    "gn:population":0,
    "gn:timezone":"Asia/Yekaterinburg",
    "iso:country":"RU",
    "name:eng_x_preferred":[
        "Moskova"
    ],
    "name:nor_x_preferred":[
        "Moskovo"
    ],
    "name:rus_x_preferred":[
        "\u041c\u043e\u0441\u043a\u043e\u0432\u043e"
    ],
    "name:und_x_variant":[
        "Moskova"
    ],
    "wof:name":"Moskovo",
    "wof:placetype":"locality"
},
  "geometry": {"coordinates":[59.105,53.9789],"type":"Point"}
}