{
  "type": "Feature",
  "properties": {
    "gn:admin1_code":"80",
    "gn:asciiname":"Kobin'pi",
    "gn:country_code":"RU",
    "gn:dem":202,
    "gn:feature_class":"P",
    "gn:feature_code":"PPL",
    "gn:name":"Kobin\u2019pi",
    "gn:population":0,
    "gn:timezone":"Europe/Samara",
    "iso:country":"RU",
    "name:rus_x_preferred":[
        "\u041a\u043e\u0431\u0438\u043d\u044c\u043f\u0438"
    ],
    "name:und_x_variant":[
        "Kobin\u2019pi",
        "\u041a\u043e\u0431\u0438\u043d\u044c\u043f\u0438"
    ],
    "wof:name":"Kobin'pi",
    "wof:placetype":"locality"
},
  "geometry": {"coordinates":[52.9783,57.8468],"type":"Point"}
}