{
  "type": "Feature",
  "properties": {
    "gn:admin1_code":"85",
    "gn:asciiname":"Makhovo",
    "gn:country_code":"RU",
    "gn:dem":140,
    "gn:feature_class":"P",
    "gn:feature_code":"PPL",
    "gn:name":"Makhovo",
    "gn:population":0,
    "gn:timezone":"Europe/Moscow",
    "iso:country":"RU",
    "name:rus_x_preferred":[
        "\u041c\u0430\u0445\u043e\u0432\u043e"
    ],
    "name:und_x_variant":[
        "\u041c\u0430\u0445\u043e\u0432\u043e"
    ],
    "wof:name":"Makhovo",
    "wof:placetype":"locality"
},
  "geometry": {"coordinates":[35.52504000000001,58.9227],"type":"Point"}
}