{
  "type": "Feature",
  "properties": {
    "gn:admin1_code":"60",
    "gn:asciiname":"Zabel'ye",
    "gn:country_code":"RU",
    "gn:dem":182,
    "gn:feature_class":"P",
    "gn:feature_code":"PPL",
    "gn:name":"Zabel\u2019ye",
    "gn:population":0,
    "gn:timezone":"Europe/Moscow",
    "iso:country":"RU",
    "name:rus_x_preferred":[
        "\u0417\u0430\u0431\u0435\u043b\u044c\u0435"
    ],
    "name:und_x_variant":[
        "Zabel\u2019ye",
        "\u0417\u0430\u0431\u0435\u043b\u044c\u0435"
    ],
    "wof:name":"Zabel'ye",
    "wof:placetype":"locality"
},
  "geometry": {"coordinates":[29.61522,56.35309],"type":"Point"}
}