{
  "type": "Feature",
  "properties": {
    "gn:admin1_code":"54",
    "gn:asciiname":"Sergeyevka",
    "gn:country_code":"RU",
    "gn:dem":114,
    "gn:feature_class":"P",
    "gn:feature_code":"PPL",
    "gn:name":"Sergeyevka",
    "gn:population":0,
    "gn:timezone":"Asia/Omsk",
    "iso:country":"RU",
    "name:rus_x_preferred":[
        "\u0421\u0435\u0440\u0433\u0435\u0435\u0432\u043a\u0430"
    ],
    "name:und_x_variant":[
        "\u0421\u0435\u0440\u0433\u0435\u0435\u0432\u043a\u0430"
    ],
    "wof:name":"Sergeyevka",
    "wof:placetype":"locality"
},
  "geometry": {"coordinates":[74.95,55.55],"type":"Point"}
}