{
  "type": "Feature",
  "properties": {
    "gn:admin1_code":"40",
    "gn:asciiname":"Ptich'ye",
    "gn:country_code":"RU",
    "gn:dem":93,
    "gn:feature_class":"P",
    "gn:feature_code":"PPL",
    "gn:name":"Ptich\u2019ye",
    "gn:population":0,
    "gn:timezone":"Asia/Yekaterinburg",
    "iso:country":"RU",
    "name:eng_x_preferred":[
        "Ptich'ye"
    ],
    "name:nor_x_preferred":[
        "Ptitsje"
    ],
    "name:rus_x_preferred":[
        "\u041f\u0442\u0438\u0447\u044c\u0435"
    ],
    "name:und_x_variant":[
        "\u041f\u0442\u0438\u0447\u044c\u0435",
        "Ptich\u2019ye"
    ],
    "wof:name":"Ptich'ye",
    "wof:placetype":"locality"
},
  "geometry": {"coordinates":[64.52360999999999,54.6825],"type":"Point"}
}