{
  "type": "Feature",
  "properties": {
    "gn:admin1_code":"42",
    "gn:asciiname":"Khantulovo",
    "gn:country_code":"RU",
    "gn:dem":87,
    "gn:feature_class":"P",
    "gn:feature_code":"PPL",
    "gn:name":"Khantulovo",
    "gn:population":0,
    "gn:timezone":"Europe/Moscow",
    "iso:country":"RU",
    "name:fin_x_preferred":[
        "Hanttulanm\u00e4ki"
    ],
    "name:rus_x_preferred":[
        "\u0425\u0430\u043d\u0442\u0443\u043b\u043e\u0432\u043e"
    ],
    "name:und_x_variant":[
        "\u0425\u0430\u043d\u0442\u0443\u043b\u043e\u0432\u043e"
    ],
    "wof:name":"Khantulovo",
    "wof:placetype":"locality"
},
  "geometry": {"coordinates":[30.462,60.3501],"type":"Point"}
}