{
  "type": "Feature",
  "properties": {
    "gn:admin1_code":"85.0",
    "gn:asciiname":"Kromino",
    "gn:country_code":"RU",
    "gn:dem":188,
    "gn:feature_class":"P",
    "gn:feature_code":"PPL",
    "gn:name":"Kromino",
    "gn:population":0,
    "gn:timezone":"Europe/Moscow",
    "iso:country":"RU",
    "name:rus_x_preferred":[
        "\u041a\u0440\u043e\u043c\u0438\u043d\u043e"
    ],
    "name:und_x_variant":[
        "\u041a\u0440\u043e\u043c\u0438\u043d\u043e"
    ],
    "wof:name":"Kromino",
    "wof:placetype":"locality"
},
  "geometry": {"coordinates":[40.33655,58.78589],"type":"Point"}
}