{
  "type": "Feature",
  "properties": {
    "gn:admin1_code":"70",
    "gn:asciiname":"Voskhodskiy",
    "gn:country_code":"RU",
    "gn:dem":426,
    "gn:feature_class":"P",
    "gn:feature_code":"PPL",
    "gn:name":"Voskhodskiy",
    "gn:population":0,
    "gn:timezone":"Europe/Moscow",
    "iso:country":"RU",
    "wof:name":"Voskhodskiy",
    "wof:placetype":"locality"
},
  "geometry": {"coordinates":[41.56667,44.68306],"type":"Point"}
}