{
  "type": "Feature",
  "properties": {
    "gn:admin1_code":"21.0",
    "gn:asciiname":"Bol'shaya Strelka",
    "gn:country_code":"RU",
    "gn:dem":127,
    "gn:feature_class":"P",
    "gn:feature_code":"PPL",
    "gn:name":"Bol\u2019shaya Strelka",
    "gn:population":0,
    "gn:timezone":"Europe/Moscow",
    "iso:country":"RU",
    "name:und_x_variant":[
        "Strelka-Bol\u2019shaya",
        "Bol\u2019shaya Strelka"
    ],
    "wof:name":"Bol'shaya Strelka",
    "wof:placetype":"locality"
},
  "geometry": {"coordinates":[42.73941,56.77103],"type":"Point"}
}