{
  "type": "Feature",
  "properties": {
    "gn:admin1_code":"69.0",
    "gn:asciiname":"Bol'shaya Dubrovka",
    "gn:country_code":"RU",
    "gn:dem":184,
    "gn:feature_class":"P",
    "gn:feature_code":"PPL",
    "gn:name":"Bol\u2019shaya Dubrovka",
    "gn:population":0,
    "gn:timezone":"Europe/Moscow",
    "iso:country":"RU",
    "name:rus_x_preferred":[
        "\u0411\u043e\u043b\u044c\u0448\u0430\u044f \u0414\u0443\u0431\u0440\u043e\u0432\u043a\u0430"
    ],
    "name:und_x_variant":[
        "Bol\u2019shaya Dubrovka",
        "\u0411\u043e\u043b\u044c\u0448\u0430\u044f \u0414\u0443\u0431\u0440\u043e\u0432\u043a\u0430"
    ],
    "wof:name":"Bol'shaya Dubrovka",
    "wof:placetype":"locality"
},
  "geometry": {"coordinates":[31.693,54.95079000000001],"type":"Point"}
}