{
  "type": "Feature",
  "properties": {
    "gn:admin1_code":"93",
    "gn:asciiname":"Kibasovo",
    "gn:country_code":"RU",
    "gn:dem":577,
    "gn:feature_class":"P",
    "gn:feature_code":"PPL",
    "gn:name":"Kibasovo",
    "gn:population":0,
    "gn:timezone":"Asia/Chita",
    "iso:country":"RU",
    "name:eng_x_preferred":[
        "Kibasovo"
    ],
    "name:nor_x_preferred":[
        "Kibasovo 2-je"
    ],
    "name:rus_x_preferred":[
        "\u041a\u0438\u0431\u0430\u0441\u043e\u0432\u043e 2-\u0435"
    ],
    "name:rus_x_variant":[
        "\u041a\u0438\u0431\u0430\u0441\u043e\u0432\u043e"
    ],
    "wof:name":"Kibasovo",
    "wof:placetype":"locality"
},
  "geometry": {"coordinates":[116.13333,51.83333],"type":"Point"}
}