{
  "type": "Feature",
  "properties": {
    "gn:admin1_code":"21.0",
    "gn:asciiname":"Lipnyagi",
    "gn:country_code":"RU",
    "gn:dem":111,
    "gn:feature_class":"P",
    "gn:feature_code":"PPL",
    "gn:name":"Lipnyagi",
    "gn:population":0,
    "gn:timezone":"Europe/Moscow",
    "iso:country":"RU",
    "name:rus_x_preferred":[
        "\u041b\u0438\u043f\u043d\u044f\u0433\u0438"
    ],
    "wof:name":"Lipnyagi",
    "wof:placetype":"locality"
},
  "geometry": {"coordinates":[41.58582,56.92567],"type":"Point"}
}