{
  "type": "Feature",
  "properties": {
    "gn:admin1_code":"90.0",
    "gn:asciiname":"Bol'shoy Yug",
    "gn:country_code":"RU",
    "gn:dem":145,
    "gn:feature_class":"P",
    "gn:feature_code":"PPL",
    "gn:name":"Bol\u2019shoy Yug",
    "gn:population":0,
    "gn:timezone":"Asia/Yekaterinburg",
    "iso:country":"RU",
    "name:rus_x_preferred":[
        "\u0411\u043e\u043b\u044c\u0448\u043e\u0439 \u042e\u0433"
    ],
    "name:und_x_variant":[
        "Bol\u2019shoy Yug",
        "\u0411\u043e\u043b\u044c\u0448\u043e\u0439 \u042e\u0433"
    ],
    "wof:name":"Bol'shoy Yug",
    "wof:placetype":"locality"
},
  "geometry": {"coordinates":[55.94861,56.3964],"type":"Point"}
}