{
  "type": "Feature",
  "properties": {
    "gn:admin1_code":"55",
    "gn:asciiname":"Veselyy Pervyy",
    "gn:country_code":"RU",
    "gn:dem":133,
    "gn:feature_class":"P",
    "gn:feature_code":"PPL",
    "gn:name":"Ves\u00eblyy Pervyy",
    "gn:population":0,
    "gn:timezone":"Asia/Yekaterinburg",
    "iso:country":"RU",
    "name:eng_x_preferred":[
        "Ves\u00eblyy Pervyy"
    ],
    "name:nor_x_preferred":[
        "Veselyj Pervyj"
    ],
    "name:rus_x_preferred":[
        "\u0412\u0435\u0441\u0435\u043b\u044b\u0439 \u041f\u0435\u0440\u0432\u044b\u0439"
    ],
    "name:und_x_variant":[
        "Ves\u00eblyy Pervyy"
    ],
    "wof:name":"Veselyy Pervyy",
    "wof:placetype":"locality"
},
  "geometry": {"coordinates":[55.56804,50.97599],"type":"Point"}
}