{
  "type": "Feature",
  "properties": {
    "gn:admin1_code":"34",
    "gn:asciiname":"Ozhindor",
    "gn:country_code":"RU",
    "gn:dem":126,
    "gn:feature_class":"P",
    "gn:feature_code":"PPL",
    "gn:name":"Ozhindor",
    "gn:population":0,
    "gn:timezone":"Europe/Moscow",
    "iso:country":"RU",
    "name:rus_x_preferred":[
        "\u041e\u0436\u0438\u043d\u0434\u043e\u0440"
    ],
    "wof:name":"Ozhindor",
    "wof:placetype":"locality"
},
  "geometry": {"coordinates":[49.60718,60.34246],"type":"Point"}
}