{
  "type": "Feature",
  "properties": {
    "gn:admin1_code":"85",
    "gn:asciiname":"Rozhnevo",
    "gn:country_code":"RU",
    "gn:dem":121,
    "gn:feature_class":"P",
    "gn:feature_code":"PPL",
    "gn:name":"Rozhn\u00ebvo",
    "gn:population":0,
    "gn:timezone":"Europe/Moscow",
    "iso:country":"RU",
    "name:rus_x_preferred":[
        "\u0420\u043e\u0436\u043d\u0451\u0432\u043e"
    ],
    "name:und_x_variant":[
        "Rozhn\u00ebvo",
        "\u0420\u043e\u0436\u043d\u0451\u0432\u043e"
    ],
    "wof:name":"Rozhnevo",
    "wof:placetype":"locality"
},
  "geometry": {"coordinates":[36.2086,58.9503],"type":"Point"}
}