{
  "type": "Feature",
  "properties": {
    "gn:admin1_code":"91",
    "gn:asciiname":"Payturma",
    "gn:country_code":"RU",
    "gn:dem":29,
    "gn:feature_class":"P",
    "gn:feature_code":"PPL",
    "gn:name":"Payturma",
    "gn:population":0,
    "gn:timezone":"Asia/Krasnoyarsk",
    "iso:country":"RU",
    "name:eng_x_preferred":[
        "Payturma"
    ],
    "name:nor_x_preferred":[
        "Pajturma"
    ],
    "name:rus_x_preferred":[
        "\u041f\u0430\u0439\u0442\u0443\u0440\u043c\u0430"
    ],
    "wof:name":"Payturma",
    "wof:placetype":"locality"
},
  "geometry": {"coordinates":[94.84999999999999,71.62083],"type":"Point"}
}