{
  "type": "Feature",
  "properties": {
    "gn:admin1_code":"76",
    "gn:asciiname":"Sukromna",
    "gn:country_code":"RU",
    "gn:dem":186,
    "gn:feature_class":"P",
    "gn:feature_code":"PPL",
    "gn:name":"Sukromna",
    "gn:population":0,
    "gn:timezone":"Europe/Moscow",
    "iso:country":"RU",
    "name:rus_x_preferred":[
        "\u0421\u0443\u043a\u0440\u043e\u043c\u043d\u0430"
    ],
    "wof:name":"Sukromna",
    "wof:placetype":"locality"
},
  "geometry": {"coordinates":[37.08686,54.45423],"type":"Point"}
}