{
  "type": "Feature",
  "properties": {
    "gn:admin1_code":"25.0",
    "gn:asciiname":"Chernaya Gryaz'",
    "gn:country_code":"RU",
    "gn:dem":210,
    "gn:feature_class":"P",
    "gn:feature_code":"PPL",
    "gn:name":"Ch\u00ebrnaya Gryaz\u2019",
    "gn:population":0,
    "gn:timezone":"Europe/Moscow",
    "iso:country":"RU",
    "name:eng_x_preferred":[
        "Ch\u00ebrnaya Gryaz'"
    ],
    "name:nor_x_preferred":[
        "Tsjernaja Grjaz"
    ],
    "name:rus_x_preferred":[
        "\u0427\u0435\u0440\u043d\u0430\u044f \u0413\u0440\u044f\u0437\u044c"
    ],
    "name:rus_x_variant":[
        "\u0427\u0451\u0440\u043d\u0430\u044f \u0413\u0440\u044f\u0437\u044c"
    ],
    "name:und_x_variant":[
        "Ch\u00ebrnaya Gryaz\u2019",
        "\u0427\u0451\u0440\u043d\u0430\u044f \u0413\u0440\u044f\u0437\u044c"
    ],
    "wof:name":"Chernaya Gryaz'",
    "wof:placetype":"locality"
},
  "geometry": {"coordinates":[35.86575,54.51851],"type":"Point"}
}