{
  "type": "Feature",
  "properties": {
    "gn:admin1_code":"33.0",
    "gn:asciiname":"Bel'nik",
    "gn:country_code":"RU",
    "gn:dem":158,
    "gn:feature_class":"P",
    "gn:feature_code":"PPL",
    "gn:name":"Bel\u2019nik",
    "gn:population":0,
    "gn:timezone":"Europe/Kirov",
    "iso:country":"RU",
    "name:nor_x_preferred":[
        "Belnik"
    ],
    "name:rus_x_preferred":[
        "\u0411\u0435\u043b\u044c\u043d\u0438\u043a"
    ],
    "name:und_x_variant":[
        "Bel\u2019nik"
    ],
    "wof:name":"Bel'nik",
    "wof:placetype":"locality"
},
  "geometry": {"coordinates":[50.18427,58.16879],"type":"Point"}
}