{
  "type": "Feature",
  "properties": {
    "gn:admin1_code":"10",
    "gn:asciiname":"Khalimonki",
    "gn:country_code":"RU",
    "gn:dem":177,
    "gn:feature_class":"P",
    "gn:feature_code":"PPL",
    "gn:name":"Khalimonki",
    "gn:population":0,
    "gn:timezone":"Europe/Moscow",
    "iso:country":"RU",
    "name:rus_x_preferred":[
        "\u0425\u0430\u043b\u0438\u043c\u043e\u043d\u043a\u0438"
    ],
    "name:und_x_variant":[
        "Khahimanki",
        "Khalimonki"
    ],
    "wof:name":"Khalimonki",
    "wof:placetype":"locality"
},
  "geometry": {"coordinates":[32.92847,53.02698],"type":"Point"}
}