{
  "type": "Feature",
  "properties": {
    "gn:admin1_code":"56",
    "gn:asciiname":"Zhidkovo",
    "gn:country_code":"RU",
    "gn:dem":173,
    "gn:feature_class":"P",
    "gn:feature_code":"PPL",
    "gn:name":"Zhidkovo",
    "gn:population":0,
    "gn:timezone":"Europe/Moscow",
    "iso:country":"RU",
    "name:rus_x_preferred":[
        "\u0416\u0438\u0434\u043a\u043e\u0432\u043e"
    ],
    "wof:name":"Zhidkovo",
    "wof:placetype":"locality"
},
  "geometry": {"coordinates":[36.11926,52.80109],"type":"Point"}
}