{
  "type": "Feature",
  "properties": {
    "gn:admin1_code":"77",
    "gn:asciiname":"Kokovkino",
    "gn:country_code":"RU",
    "gn:dem":213,
    "gn:feature_class":"P",
    "gn:feature_code":"PPL",
    "gn:name":"Kokovkino",
    "gn:population":500,
    "gn:timezone":"Europe/Moscow",
    "iso:country":"RU",
    "name:rus_x_preferred":[
        "\u041a\u043e\u043a\u043e\u0432\u043a\u0438\u043d\u043e"
    ],
    "wof:name":"Kokovkino",
    "wof:placetype":"locality",
    "wof:population":500
},
  "geometry": {"coordinates":[32.59477,57.22716],"type":"Point"}
}