{
  "type": "Feature",
  "properties": {
    "gn:admin1_code":"8",
    "gn:asciiname":"Rozhdestvenskiy",
    "gn:country_code":"RU",
    "gn:dem":415,
    "gn:feature_class":"P",
    "gn:feature_code":"PPL",
    "gn:name":"Rozhdestvenskiy",
    "gn:population":0,
    "gn:timezone":"Asia/Yekaterinburg",
    "iso:country":"RU",
    "name:rus_x_preferred":[
        "\u0420\u043e\u0436\u0434\u0435\u0441\u0442\u0432\u0435\u043d\u0441\u043a\u0438\u0439"
    ],
    "name:und_x_variant":[
        "\u0420\u043e\u0436\u0434\u0435\u0441\u0442\u0432\u0435\u043d\u0441\u043a\u0438\u0439"
    ],
    "wof:name":"Rozhdestvenskiy",
    "wof:placetype":"locality"
},
  "geometry": {"coordinates":[59.03333000000001,55.43333000000001],"type":"Point"}
}