{
  "type": "Feature",
  "properties": {
    "gn:admin1_code":"17",
    "gn:asciiname":"Sangimakhi",
    "gn:country_code":"RU",
    "gn:dem":1654,
    "gn:feature_class":"P",
    "gn:feature_code":"PPL",
    "gn:name":"Sangimakhi",
    "gn:population":0,
    "gn:timezone":"Europe/Moscow",
    "iso:country":"RU",
    "name:rus_x_preferred":[
        "\u0421\u0430\u043d\u0433\u0438\u043c\u0430\u0445\u0438"
    ],
    "wof:name":"Sangimakhi",
    "wof:placetype":"locality"
},
  "geometry": {"coordinates":[47.43307,42.33788],"type":"Point"}
}