{
  "type": "Feature",
  "properties": {
    "gn:admin1_code":"6",
    "gn:asciiname":"Nizhnyaya",
    "gn:country_code":"RU",
    "gn:dem":122,
    "gn:feature_class":"P",
    "gn:feature_code":"PPL",
    "gn:name":"Nizhnyaya",
    "gn:population":0,
    "gn:timezone":"Europe/Moscow",
    "iso:country":"RU",
    "name:eng_x_preferred":[
        "Nizhnyaya"
    ],
    "name:nor_x_preferred":[
        "Nizjnjaja"
    ],
    "name:rus_x_preferred":[
        "\u041d\u0438\u0436\u043d\u044f\u044f"
    ],
    "wof:name":"Nizhnyaya",
    "wof:placetype":"locality"
},
  "geometry": {"coordinates":[39.45663,62.05104],"type":"Point"}
}