{
  "type": "Feature",
  "properties": {
    "gn:admin1_code":"52",
    "gn:asciiname":"Otturitsy",
    "gn:country_code":"RU",
    "gn:dem":44,
    "gn:feature_class":"P",
    "gn:feature_code":"PPL",
    "gn:name":"Otturitsy",
    "gn:population":0,
    "gn:timezone":"Europe/Moscow",
    "iso:country":"RU",
    "name:rus_x_preferred":[
        "\u041e\u0442\u0442\u0443\u0440\u0438\u0446\u044b"
    ],
    "name:und_x_variant":[
        "\u041e\u0442\u0442\u0443\u0440\u0438\u0446\u044b"
    ],
    "wof:name":"Otturitsy",
    "wof:placetype":"locality"
},
  "geometry": {"coordinates":[30.46667,58.48333],"type":"Point"}
}