{
  "type": "Feature",
  "properties": {
    "gn:admin1_code":"38.0",
    "gn:asciiname":"Dobrovol'nyy",
    "gn:country_code":"RU",
    "gn:dem":5,
    "gn:feature_class":"P",
    "gn:feature_code":"PPL",
    "gn:name":"Dobrovol\u2019nyy",
    "gn:population":0,
    "gn:timezone":"Europe/Moscow",
    "iso:country":"RU",
    "name:rus_x_preferred":[
        "\u0414\u043e\u0431\u0440\u043e\u0432\u043e\u043b\u044c\u043d\u044b\u0439"
    ],
    "name:und_x_variant":[
        "Dobrovol\u2019ny",
        "Dobrovol\u2019nyy"
    ],
    "wof:name":"Dobrovol'nyy",
    "wof:placetype":"locality"
},
  "geometry": {"coordinates":[38.72303,46.02177],"type":"Point"}
}