{
  "type": "Feature",
  "properties": {
    "gn:admin1_code":"10",
    "gn:asciiname":"Kokotok",
    "gn:country_code":"RU",
    "gn:dem":166,
    "gn:feature_class":"P",
    "gn:feature_code":"PPL",
    "gn:name":"Kokotok",
    "gn:population":0,
    "gn:timezone":"Europe/Moscow",
    "iso:country":"RU",
    "name:rus_x_preferred":[
        "\u041a\u043e\u043a\u043e\u0442\u043e\u043a"
    ],
    "name:und_x_variant":[
        "Kokatok"
    ],
    "wof:name":"Kokotok",
    "wof:placetype":"locality"
},
  "geometry": {"coordinates":[32.28028,52.92579],"type":"Point"}
}