{
  "type": "Feature",
  "properties": {
    "gn:admin1_code":"41.0",
    "gn:asciiname":"Bobrovka",
    "gn:country_code":"RU",
    "gn:dem":209,
    "gn:feature_class":"P",
    "gn:feature_code":"PPL",
    "gn:name":"Bobrovka",
    "gn:population":0,
    "gn:timezone":"Europe/Moscow",
    "iso:country":"RU",
    "name:rus_x_preferred":[
        "\u0411\u043e\u0431\u0440\u043e\u0432\u043a\u0430"
    ],
    "wof:name":"Bobrovka",
    "wof:placetype":"locality"
},
  "geometry": {"coordinates":[36.42864,52.21024],"type":"Point"}
}