{
  "type": "Feature",
  "properties": {
    "gn:admin1_code":"76",
    "gn:asciiname":"Zhdamirovo",
    "gn:country_code":"RU",
    "gn:dem":239,
    "gn:feature_class":"P",
    "gn:feature_code":"PPL",
    "gn:name":"Zhdamirovo",
    "gn:population":0,
    "gn:timezone":"Europe/Moscow",
    "iso:country":"RU",
    "name:und_x_variant":[
        "Zhdamisovo",
        "Zhdamirovo"
    ],
    "wof:name":"Zhdamirovo",
    "wof:placetype":"locality"
},
  "geometry": {"coordinates":[37.31439,54.64558],"type":"Point"}
}