{
  "type": "Feature",
  "properties": {
    "gn:admin1_code":"63",
    "gn:asciiname":"Ilimnir",
    "gn:country_code":"RU",
    "gn:dem":23,
    "gn:feature_class":"P",
    "gn:feature_code":"PPL",
    "gn:name":"Ilimnir",
    "gn:population":0,
    "gn:timezone":"Asia/Magadan",
    "iso:country":"RU",
    "name:che_x_preferred":[
        "\u0418\u043b\u0438\u043c\u043d\u0438\u0440"
    ],
    "name:rus_x_preferred":[
        "\u0418\u043b\u0438\u043c\u043d\u0438\u0440"
    ],
    "name:sah_x_preferred":[
        "\u0418\u043b\u0438\u043c\u043d\u0438\u0438\u0440"
    ],
    "name:und_x_variant":[
        "Ilimniir",
        "Ilimnir",
        "\u0418\u043b\u0438\u043c\u043d\u0438\u0440"
    ],
    "wof:name":"Ilimnir",
    "wof:placetype":"locality"
},
  "geometry": {"coordinates":[152.01044999999999,69.03655000000001],"type":"Point"}
}