{
  "type": "Feature",
  "properties": {
    "gn:admin1_code":"57",
    "gn:asciiname":"Solyanovka",
    "gn:country_code":"RU",
    "gn:dem":274,
    "gn:feature_class":"P",
    "gn:feature_code":"PPL",
    "gn:name":"Solyanovka",
    "gn:population":0,
    "gn:timezone":"Europe/Moscow",
    "iso:country":"RU",
    "name:rus_x_preferred":[
        "\u0421\u043e\u043b\u044f\u043d\u043e\u0432\u043a\u0430"
    ],
    "name:und_x_variant":[
        "\u0421\u043e\u043b\u044f\u043d\u043e\u0432\u043a\u0430"
    ],
    "wof:name":"Solyanovka",
    "wof:placetype":"locality"
},
  "geometry": {"coordinates":[46.291,53.5265],"type":"Point"}
}