{
  "type": "Feature",
  "properties": {
    "gn:admin1_code":"12.0",
    "gn:asciiname":"Dzhelyashki",
    "gn:country_code":"RU",
    "gn:dem":1683,
    "gn:feature_class":"P",
    "gn:feature_code":"PPL",
    "gn:name":"Dzhelyashki",
    "gn:population":0,
    "gn:timezone":"Europe/Moscow",
    "iso:country":"RU",
    "name:rus_x_preferred":[
        "\u0414\u0436\u0435\u043b\u044f\u0448\u043a\u0438"
    ],
    "wof:name":"Dzhelyashki",
    "wof:placetype":"locality"
},
  "geometry": {"coordinates":[45.40389,42.76111],"type":"Point"}
}