{
  "type": "Feature",
  "properties": {
    "gn:admin1_code":"13.0",
    "gn:asciiname":"Ripus",
    "gn:country_code":"RU",
    "gn:dem":302,
    "gn:feature_class":"P",
    "gn:feature_code":"PPL",
    "gn:name":"Ripus",
    "gn:population":0,
    "gn:timezone":"Asia/Yekaterinburg",
    "iso:country":"RU",
    "name:rus_x_preferred":[
        "\u0420\u0438\u043f\u0443\u0441"
    ],
    "wof:name":"Ripus",
    "wof:placetype":"locality"
},
  "geometry": {"coordinates":[60.4308,55.5783],"type":"Point"}
}