{
  "type": "Feature",
  "properties": {
    "gn:admin1_code":"63",
    "gn:asciiname":"Innokent'yevskaya",
    "gn:country_code":"RU",
    "gn:dem":160,
    "gn:feature_class":"P",
    "gn:feature_code":"PPL",
    "gn:name":"Innokent\u2019yevskaya",
    "gn:population":0,
    "gn:timezone":"Asia/Yakutsk",
    "iso:country":"RU",
    "name:rus_x_preferred":[
        "\u0418\u043d\u043d\u043e\u043a\u0435\u043d\u0442\u044c\u0435\u0432\u0441\u043a\u0430\u044f"
    ],
    "name:und_x_variant":[
        "Innokent\u2019yevskoye",
        "Innokent\u2019yevskaya"
    ],
    "wof:name":"Innokent'yevskaya",
    "wof:placetype":"locality"
},
  "geometry": {"coordinates":[117.75,59.85],"type":"Point"}
}