{
  "type": "Feature",
  "properties": {
    "gn:admin1_code":"4",
    "gn:asciiname":"Borisovskiy",
    "gn:country_code":"RU",
    "gn:dem":201,
    "gn:feature_class":"P",
    "gn:feature_code":"PPL",
    "gn:name":"Borisovskiy",
    "gn:population":0,
    "gn:timezone":"Asia/Barnaul",
    "iso:country":"RU",
    "name:eng_x_preferred":[
        "Borisovskiy"
    ],
    "name:nor_x_preferred":[
        "Borisovskij"
    ],
    "name:rus_x_preferred":[
        "\u0411\u043e\u0440\u0438\u0441\u043e\u0432\u0441\u043a\u0438\u0439"
    ],
    "name:und_x_variant":[
        "\u0411\u043e\u0440\u0438\u0441\u043e\u0432\u0441\u043a\u0438\u0439",
        "Borisovskiy"
    ],
    "wof:name":"Borisovskiy",
    "wof:placetype":"locality"
},
  "geometry": {"coordinates":[80.16667,53.56667],"type":"Point"}
}