{
  "type": "Feature",
  "properties": {
    "gn:admin1_code":"4",
    "gn:asciiname":"Filippovskoye",
    "gn:cc2":"RU",
    "gn:country_code":"RU",
    "gn:dem":244,
    "gn:feature_class":"P",
    "gn:feature_code":"PPL",
    "gn:name":"Filippovskoye",
    "gn:population":0,
    "gn:timezone":"Asia/Barnaul",
    "iso:country":"RU",
    "name:eng_x_preferred":[
        "Filippovskoye"
    ],
    "name:nor_x_preferred":[
        "Filippovskij"
    ],
    "name:rus_x_preferred":[
        "\u0424\u0438\u043b\u0438\u043f\u043f\u043e\u0432\u0441\u043a\u0438\u0439"
    ],
    "name:rus_x_variant":[
        "\u0424\u0438\u043b\u0438\u043f\u043f\u043e\u0432\u0441\u043a\u043e\u0435"
    ],
    "name:und_x_variant":[
        "Filippovskiy",
        "Filippovskoye",
        "\u0424\u0438\u043b\u0438\u043f\u043f\u043e\u0432\u0441\u043a\u043e\u0435"
    ],
    "wof:name":"Filippovskoye",
    "wof:placetype":"locality"
},
  "geometry": {"coordinates":[80.66667,53.63333000000001],"type":"Point"}
}