{
  "type": "Feature",
  "properties": {
    "gn:admin1_code":"41.0",
    "gn:asciiname":"Bondarevka",
    "gn:country_code":"RU",
    "gn:dem":148,
    "gn:feature_class":"P",
    "gn:feature_code":"PPL",
    "gn:name":"Bondarevka",
    "gn:population":0,
    "gn:timezone":"Europe/Moscow",
    "iso:country":"RU",
    "name:rus_x_preferred":[
        "\u0411\u043e\u043d\u0434\u0430\u0440\u0435\u0432\u043a\u0430"
    ],
    "wof:name":"Bondarevka",
    "wof:placetype":"locality"
},
  "geometry": {"coordinates":[35.34305999999999,51.19278],"type":"Point"}
}