{
  "type": "Feature",
  "properties": {
    "gn:admin1_code":"16",
    "gn:asciiname":"Kumashi",
    "gn:country_code":"RU",
    "gn:dem":160,
    "gn:feature_class":"P",
    "gn:feature_code":"PPL",
    "gn:name":"Kumashi",
    "gn:population":0,
    "gn:timezone":"Europe/Moscow",
    "iso:country":"RU",
    "name:rus_x_preferred":[
        "\u041a\u0443\u043c\u0430\u0448\u0438"
    ],
    "name:und_x_variant":[
        "\u041a\u0443\u043c\u0430\u0448\u0438"
    ],
    "wof:name":"Kumashi",
    "wof:placetype":"locality"
},
  "geometry": {"coordinates":[47.02015,55.57267],"type":"Point"}
}