{
  "type": "Feature",
  "properties": {
    "gn:admin1_code":"53",
    "gn:asciiname":"Kazantsevo",
    "gn:country_code":"RU",
    "gn:dem":113,
    "gn:feature_class":"P",
    "gn:feature_code":"PPL",
    "gn:name":"Kazantsevo",
    "gn:population":0,
    "gn:timezone":"Asia/Novosibirsk",
    "iso:country":"RU",
    "name:eng_x_preferred":[
        "Kazantsevo"
    ],
    "name:nor_x_preferred":[
        "Kazantsevo"
    ],
    "name:rus_x_preferred":[
        "\u041a\u0430\u0437\u0430\u043d\u0446\u0435\u0432\u043e"
    ],
    "name:und_x_variant":[
        "\u041a\u0430\u0437\u0430\u043d\u0446\u0435\u0432\u043e",
        "Kazantsevo"
    ],
    "wof:name":"Kazantsevo",
    "wof:placetype":"locality"
},
  "geometry": {"coordinates":[77.68256,55.07648],"type":"Point"}
}