{
  "type": "Feature",
  "properties": {
    "gn:admin1_code":"61.0",
    "gn:asciiname":"Chekilev",
    "gn:country_code":"RU",
    "gn:dem":29,
    "gn:feature_class":"P",
    "gn:feature_code":"PPL",
    "gn:name":"Chekil\u00ebv",
    "gn:population":0,
    "gn:timezone":"Europe/Moscow",
    "iso:country":"RU",
    "name:rus_x_preferred":[
        "\u0427\u0435\u043a\u0438\u043b\u0451\u0432"
    ],
    "name:ukr_x_preferred":[
        "Chekylyev"
    ],
    "name:und_x_variant":[
        "Chekil\u00ebv"
    ],
    "wof:name":"Chekilev",
    "wof:placetype":"locality"
},
  "geometry": {"coordinates":[38.39735,47.3612],"type":"Point"}
}