{
  "type": "Feature",
  "properties": {
    "gn:admin1_code":"67",
    "gn:asciiname":"Mizino-Lapshinovka",
    "gn:country_code":"RU",
    "gn:dem":99,
    "gn:feature_class":"P",
    "gn:feature_code":"PPL",
    "gn:name":"Mizino-Lapshinovka",
    "gn:population":0,
    "gn:timezone":"Europe/Saratov",
    "iso:country":"RU",
    "name:eng_x_preferred":[
        "Mizino-Lapshinovka"
    ],
    "name:nor_x_preferred":[
        "Mizino-Lapsjinovka"
    ],
    "name:rus_x_preferred":[
        "\u041c\u0438\u0437\u0438\u043d\u043e-\u041b\u0430\u043f\u0448\u0438\u043d\u043e\u0432\u043a\u0430"
    ],
    "name:und_x_variant":[
        "Mezino-Lapshinovka",
        "Mizino-Lopshinovka",
        "\u041c\u0438\u0437\u0438\u043d\u043e-\u041b\u0430\u043f\u0448\u0438\u043d\u043e\u0432\u043a\u0430",
        "Mizino-Lapshinovka"
    ],
    "wof:name":"Mizino-Lapshinovka",
    "wof:placetype":"locality"
},
  "geometry": {"coordinates":[45.80576,51.84649],"type":"Point"}
}