{
  "type": "Feature",
  "properties": {
    "gn:admin1_code":"91",
    "gn:asciiname":"Vorokovka",
    "gn:country_code":"RU",
    "gn:dem":174,
    "gn:feature_class":"P",
    "gn:feature_code":"PPL",
    "gn:name":"Vorokovka",
    "gn:population":0,
    "gn:timezone":"Asia/Krasnoyarsk",
    "iso:country":"RU",
    "name:eng_x_preferred":[
        "Vorokovka"
    ],
    "name:rus_x_preferred":[
        "\u0412\u043e\u0440\u043e\u043a\u043e\u0432\u043a\u0430"
    ],
    "name:rus_x_variant":[
        "\u0412\u043e\u0440\u043e\u0432\u043a\u0430"
    ],
    "name:und_x_variant":[
        "Varakovka",
        "Varakovskaya",
        "Vorokovka"
    ],
    "wof:name":"Vorokovka",
    "wof:placetype":"locality"
},
  "geometry": {"coordinates":[92.8468,57.5895],"type":"Point"}
}