{
  "type": "Feature",
  "properties": {
    "gn:admin1_code":"64",
    "gn:asciiname":"Shutovo",
    "gn:country_code":"RU",
    "gn:dem":145,
    "gn:feature_class":"P",
    "gn:feature_code":"PPL",
    "gn:name":"Shutovo",
    "gn:population":0,
    "gn:timezone":"Asia/Magadan",
    "iso:country":"RU",
    "name:rus_x_preferred":[
        "\u0428\u0443\u0442\u043e\u0432\u043e"
    ],
    "wof:name":"Shutovo",
    "wof:placetype":"locality"
},
  "geometry": {"coordinates":[156.25416000000001,50.69354000000001],"type":"Point"}
}