{
  "type": "Feature",
  "properties": {
    "gn:admin1_code":"42",
    "gn:asciiname":"Meleksa",
    "gn:country_code":"RU",
    "gn:dem":32,
    "gn:feature_class":"P",
    "gn:feature_code":"PPL",
    "gn:name":"Meleksa",
    "gn:population":0,
    "gn:timezone":"Europe/Moscow",
    "iso:country":"RU",
    "name:eng_x_preferred":[
        "Meleksa"
    ],
    "name:nor_x_preferred":[
        "Meleksa"
    ],
    "name:rus_x_preferred":[
        "\u041c\u0435\u043b\u0435\u043a\u0441\u0430"
    ],
    "name:und_x_variant":[
        "\u041c\u0435\u043b\u0435\u043a\u0441\u0430",
        "Meleksa"
    ],
    "wof:name":"Meleksa",
    "wof:placetype":"locality"
},
  "geometry": {"coordinates":[32.7565,59.91027],"type":"Point"}
}