{
  "type": "Feature",
  "properties": {
    "gn:admin1_code":"84",
    "gn:asciiname":"Krivoy Sukhodol",
    "gn:cc2":"RU",
    "gn:country_code":"RU",
    "gn:dem":128,
    "gn:feature_class":"P",
    "gn:feature_code":"PPL",
    "gn:name":"Krivoy Sukhodol",
    "gn:population":0,
    "gn:timezone":"Europe/Volgograd",
    "iso:country":"RU",
    "name:rus_x_preferred":[
        "\u041a\u0440\u0438\u0432\u043e\u0439 \u0421\u0443\u0445\u043e\u0434\u043e\u043b"
    ],
    "name:und_x_variant":[
        "Khutor Krivoy Sukhodol",
        "Krivosukhodol\u2019skiy",
        "Krivoy Sukhodol"
    ],
    "wof:name":"Krivoy Sukhodol",
    "wof:placetype":"locality"
},
  "geometry": {"coordinates":[42.81667,49.96667],"type":"Point"}
}