{
  "type": "Feature",
  "properties": {
    "gn:admin1_code":"33.0",
    "gn:asciiname":"Bulatovo",
    "gn:country_code":"RU",
    "gn:dem":165,
    "gn:feature_class":"P",
    "gn:feature_code":"PPL",
    "gn:name":"Bulatovo",
    "gn:population":0,
    "gn:timezone":"Europe/Kirov",
    "iso:country":"RU",
    "name:eng_x_preferred":[
        "Bulatovo"
    ],
    "name:nor_x_preferred":[
        "Bulatovo"
    ],
    "name:rus_x_preferred":[
        "\u0411\u0443\u043b\u0430\u0442\u043e\u0432\u043e"
    ],
    "name:und_x_variant":[
        "Bulatovy"
    ],
    "wof:name":"Bulatovo",
    "wof:placetype":"locality"
},
  "geometry": {"coordinates":[53.00727,60.01224000000001],"type":"Point"}
}