{
  "type": "Feature",
  "properties": {
    "gn:country":"RU",
    "gn:fcode":"PPL",
    "gn:population":0,
    "iso:country":"RU",
    "name:aze_x_preferred":[
        "Makarov"
    ],
    "name:bak_x_preferred":[
        "\u041c\u0430\u043a\u0430\u0440\u043e\u0432"
    ],
    "name:che_x_preferred":[
        "\u041c\u0430\u043a\u0430\u0440\u043e\u0432\u043e"
    ],
    "name:eng_x_preferred":[
        "Makarovo"
    ],
    "name:hye_x_preferred":[
        "\u0544\u0561\u056f\u0561\u0580\u0578\u057e\u0578"
    ],
    "name:kaz_x_preferred":[
        "\u041c\u0430\u043a\u0430\u0440"
    ],
    "name:kir_x_preferred":[
        "\u041c\u0430\u043a\u0430\u0440"
    ],
    "name:nor_x_preferred":[
        "Makarovo"
    ],
    "name:rus_x_preferred":[
        "\u041c\u0430\u043a\u0430\u0440\u043e\u0432\u043e"
    ],
    "name:tat_x_preferred":[
        "\u041c\u0430\u043a\u0430\u0440"
    ],
    "name:ukr_x_preferred":[
        "\u041c\u0430\u043a\u0430\u0440\u043e\u0432\u043e"
    ],
    "qs:name":"Makarovo",
    "qs:name_adm0":"Russia",
    "qs:name_adm1":"Yaroslavl Oblast",
    "qs:photos_9r":0,
    "qs:photos_sr":0,
    "qs:placetype":"Town",
    "qs:pop_sr":"0",
    "wof:name":"Makarovo",
    "wof:placetype":"locality",
    "wof:population":0
},
  "geometry": {"coordinates":[39.56351,57.3209],"type":"Point"}
}