{
  "type": "Feature",
  "properties": {
    "gn:admin1_code":"47",
    "gn:asciiname":"Avdeyevskiye Vyselki",
    "gn:country_code":"RU",
    "gn:dem":141,
    "gn:feature_class":"P",
    "gn:feature_code":"PPL",
    "gn:name":"Avdeyevskiye Vyselki",
    "gn:population":0,
    "gn:timezone":"Europe/Moscow",
    "iso:country":"RU",
    "name:nor_x_preferred":[
        "Avdejevskije Vyselki"
    ],
    "name:rus_x_preferred":[
        "\u0410\u0432\u0434\u0435\u0435\u0432\u0441\u043a\u0438\u0435 \u0412\u044b\u0441\u0435\u043b\u043a\u0438"
    ],
    "name:und_x_variant":[
        "Avdeyevskiye",
        "Avdeyevskiye Vyselki"
    ],
    "wof:name":"Avdeyevskiye Vyselki",
    "wof:placetype":"locality"
},
  "geometry": {"coordinates":[38.86762,54.6815],"type":"Point"}
}