{
  "type": "Feature",
  "properties": {
    "gn:admin1_code":"47",
    "gn:asciiname":"Kaletino",
    "gn:country_code":"RU",
    "gn:dem":177,
    "gn:feature_class":"P",
    "gn:feature_code":"PPL",
    "gn:name":"Kaletino",
    "gn:population":0,
    "gn:timezone":"Europe/Moscow",
    "iso:country":"RU",
    "name:rus_x_preferred":[
        "\u041a\u0430\u043b\u0435\u0442\u0438\u043d\u043e"
    ],
    "wof:name":"Kaletino",
    "wof:placetype":"locality"
},
  "geometry": {"coordinates":[37.75065,54.75268000000001],"type":"Point"}
}