{
  "type": "Feature",
  "properties": {
    "gn:admin1_code":"20",
    "gn:asciiname":"Muruy",
    "gn:country_code":"RU",
    "gn:dem":537,
    "gn:feature_class":"P",
    "gn:feature_code":"PPL",
    "gn:name":"Muruy",
    "gn:population":0,
    "gn:timezone":"Asia/Irkutsk",
    "iso:country":"RU",
    "name:eng_x_preferred":[
        "Muruy"
    ],
    "name:nor_x_preferred":[
        "Muruj"
    ],
    "name:rus_x_preferred":[
        "\u041c\u0443\u0440\u0443\u0439"
    ],
    "wof:name":"Muruy",
    "wof:placetype":"locality"
},
  "geometry": {"coordinates":[102.01430000000001,53.3448],"type":"Point"}
}