{
  "type": "Feature",
  "properties": {
    "gn:admin1_code":"21",
    "gn:asciiname":"Khmel'niki",
    "gn:country_code":"RU",
    "gn:dem":151,
    "gn:feature_class":"P",
    "gn:feature_code":"PPL",
    "gn:name":"Khmel\u2019niki",
    "gn:population":0,
    "gn:timezone":"Europe/Moscow",
    "iso:country":"RU",
    "name:rus_x_preferred":[
        "\u0425\u043c\u0435\u043b\u044c\u043d\u0438\u043a\u0438"
    ],
    "name:und_x_variant":[
        "Khmel\u2019niki"
    ],
    "wof:name":"Khmel'niki",
    "wof:placetype":"locality"
},
  "geometry": {"coordinates":[40.11541,56.86313000000001],"type":"Point"}
}