{
  "type": "Feature",
  "properties": {
    "gn:admin1_code":"73.0",
    "gn:asciiname":"Apaykina Gar'",
    "gn:country_code":"RU",
    "gn:dem":143,
    "gn:feature_class":"P",
    "gn:feature_code":"PPL",
    "gn:name":"Apaykina Gar\u2019",
    "gn:population":0,
    "gn:timezone":"Europe/Moscow",
    "iso:country":"RU",
    "name:nor_x_preferred":[
        "Apajkina"
    ],
    "name:rus_x_preferred":[
        "\u0410\u043f\u0430\u0439\u043a\u0438\u043d\u0430 \u0413\u0430\u0440\u044c"
    ],
    "name:und_x_variant":[
        "Apaykina",
        "Apaykina Gar\u2019"
    ],
    "wof:name":"Apaykina Gar'",
    "wof:placetype":"locality"
},
  "geometry": {"coordinates":[50.0607,56.2485],"type":"Point"}
}