{
  "type": "Feature",
  "properties": {
    "gn:admin1_code":"91.0",
    "gn:asciiname":"Shirokiy Log",
    "gn:country_code":"RU",
    "gn:dem":84,
    "gn:feature_class":"P",
    "gn:feature_code":"PPL",
    "gn:name":"Shirokiy Log",
    "gn:population":0,
    "gn:timezone":"Asia/Krasnoyarsk",
    "iso:country":"RU",
    "name:rus_x_preferred":[
        "\u0428\u0438\u0440\u043e\u043a\u0438\u0439 \u041b\u043e\u0433"
    ],
    "name:und_x_variant":[
        "Devyatyy Kilometr",
        "Shirokiy Log"
    ],
    "wof:name":"Shirokiy Log",
    "wof:placetype":"locality"
},
  "geometry": {"coordinates":[92.96120000000001,58.0743],"type":"Point"}
}