{
  "type": "Feature",
  "properties": {
    "gn:admin1_code":"52",
    "gn:asciiname":"Gromovo",
    "gn:country_code":"RU",
    "gn:dem":68,
    "gn:feature_class":"P",
    "gn:feature_code":"PPL",
    "gn:name":"Gromovo",
    "gn:population":0,
    "gn:timezone":"Europe/Moscow",
    "iso:country":"RU",
    "name:che_x_preferred":[
        "\u0413\u0440\u043e\u043c\u043e\u0432\u043e"
    ],
    "name:fas_x_preferred":[
        "\u0641\u0631\u0648\u062f\u06af\u0627\u0647 \u06af\u0631\u0627\u0645\u0648\u0648"
    ],
    "name:fin_x_preferred":[
        "Sakkola"
    ],
    "name:nor_x_preferred":[
        "Gromovo"
    ],
    "name:rus_x_preferred":[
        "\u0413\u0440\u043e\u043c\u043e\u0432\u043e"
    ],
    "name:sco_x_preferred":[
        "Gromovo"
    ],
    "name:swe_x_preferred":[
        "Sakkola"
    ],
    "name:tgk_x_preferred":[
        "\u0424\u0443\u0440\u0443\u0434\u0433\u043e\u04b3\u0438 \u0433\u0440\u043e\u043c\u0443\u0432"
    ],
    "wof:name":"Gromovo",
    "wof:placetype":"locality"
},
  "geometry": {"coordinates":[33.54793,58.51598000000001],"type":"Point"}
}