{
  "type": "Feature",
  "properties": {
    "gn:admin1_code":"53",
    "gn:asciiname":"Novolaptevskiy",
    "gn:country_code":"RU",
    "gn:dem":144,
    "gn:feature_class":"P",
    "gn:feature_code":"PPL",
    "gn:name":"Novolaptevskiy",
    "gn:population":0,
    "gn:timezone":"Asia/Novosibirsk",
    "iso:country":"RU",
    "name:rus_x_preferred":[
        "\u041d\u043e\u0432\u043e\u043b\u0430\u043f\u0442\u0435\u0432\u0441\u043a\u0438\u0439"
    ],
    "name:und_x_variant":[
        "\u041d\u043e\u0432\u043e\u043b\u0430\u043f\u0442\u0435\u0432\u0441\u043a\u0438\u0439"
    ],
    "wof:name":"Novolaptevskiy",
    "wof:placetype":"locality"
},
  "geometry": {"coordinates":[82.28333000000001,55.81667],"type":"Point"}
}