{
  "type": "Feature",
  "properties": {
    "gn:admin1_code":"32",
    "gn:asciiname":"Baz'yany",
    "gn:country_code":"RU",
    "gn:dem":37,
    "gn:feature_class":"P",
    "gn:feature_code":"PPL",
    "gn:name":"Baz\u2019yany",
    "gn:population":0,
    "gn:timezone":"Asia/Yekaterinburg",
    "iso:country":"RU",
    "name:eng_x_preferred":[
        "Baz'yany"
    ],
    "name:nor_x_preferred":[
        "Baziany"
    ],
    "name:rus_x_preferred":[
        "\u0411\u0430\u0437\u044c\u044f\u043d\u044b"
    ],
    "name:und_x_variant":[
        "Baz\u2019yanovskoye",
        "Baz\u2019yany"
    ],
    "wof:name":"Baz'yany",
    "wof:placetype":"locality"
},
  "geometry": {"coordinates":[69.65000000000001,60.86666999999999],"type":"Point"}
}