{
  "type": "Feature",
  "properties": {
    "gn:country":"RU",
    "gn:fcode":"PPLX",
    "gn:pop":0,
    "iso:country":"RU",
    "name:rus_x_preferred":[
        "\u0413\u0440\u0438\u043d\u0451\u0432\u043a\u0430"
    ],
    "qs:name":"Grin\u00ebvka",
    "qs:name_adm0":"Russia",
    "qs:name_adm1":"Belgorod Oblast",
    "qs:photos":9,
    "qs:photos_1k":2,
    "qs:photos_9k":1,
    "qs:photos_9r":1,
    "qs:photos_all":9,
    "qs:photos_sr":1,
    "qs:placetype":"Suburb",
    "qs:pop_sr":"0",
    "wof:name":"Grin\u00ebvka",
    "wof:placetype":"neighbourhood",
    "wof:population":0
},
  "geometry": {"coordinates":[36.56448,50.63492],"type":"Point"}
}