{
  "type": "Feature",
  "properties": {
    "gn:admin1_code":"45",
    "gn:asciiname":"Yamataykino",
    "gn:country_code":"RU",
    "gn:dem":121,
    "gn:feature_class":"P",
    "gn:feature_code":"PPL",
    "gn:name":"Yamataykino",
    "gn:population":0,
    "gn:timezone":"Europe/Moscow",
    "iso:country":"RU",
    "name:rus_x_preferred":[
        "\u042f\u043c\u0430\u0442\u0430\u0439\u043a\u0438\u043d\u043e"
    ],
    "name:und_x_variant":[
        "\u042f\u043c\u0430\u0442\u0430\u0439\u043a\u0438\u043d\u043e"
    ],
    "wof:name":"Yamataykino",
    "wof:placetype":"locality"
},
  "geometry": {"coordinates":[46.3102,56.1717],"type":"Point"}
}