{
  "type": "Feature",
  "properties": {
    "gn:admin1_code":"65",
    "gn:asciiname":"Sukhiye Avrali",
    "gn:country_code":"RU",
    "gn:dem":123,
    "gn:feature_class":"P",
    "gn:feature_code":"PPL",
    "gn:name":"Sukhiye Avrali",
    "gn:population":0,
    "gn:timezone":"Europe/Samara",
    "iso:country":"RU",
    "name:eng_x_preferred":[
        "Sukhiye Avrali"
    ],
    "name:nor_x_preferred":[
        "Sukhije Avrali"
    ],
    "name:rus_x_preferred":[
        "\u0421\u0443\u0445\u0438\u0435 \u0410\u0432\u0440\u0430\u043b\u0438"
    ],
    "name:und_x_variant":[
        "Sukhiye Avraly"
    ],
    "wof:name":"Sukhiye Avrali",
    "wof:placetype":"locality"
},
  "geometry": {"coordinates":[50.06204,53.82366999999999],"type":"Point"}
}