{
  "type": "Feature",
  "properties": {
    "gn:admin1_code":"37.0",
    "gn:asciiname":"Petrushino",
    "gn:country_code":"RU",
    "gn:dem":156,
    "gn:feature_class":"P",
    "gn:feature_code":"PPL",
    "gn:name":"Petrushino",
    "gn:population":0,
    "gn:timezone":"Europe/Moscow",
    "iso:country":"RU",
    "name:che_x_preferred":[
        "\u041f\u0435\u0442\u0440\u0443\u0448\u0438\u043d\u043e"
    ],
    "name:rus_x_preferred":[
        "\u041f\u0435\u0442\u0440\u0443\u0448\u0438\u043d\u043e"
    ],
    "name:und_x_variant":[
        "\u041f\u0435\u0442\u0440\u0443\u0448\u0438\u043d\u043e"
    ],
    "wof:name":"Petrushino",
    "wof:placetype":"locality"
},
  "geometry": {"coordinates":[41.44835,57.61558],"type":"Point"}
}