{
  "type": "Feature",
  "properties": {
    "gn:admin1_code":"7",
    "gn:asciiname":"Pal'min Pervyy",
    "gn:country_code":"RU",
    "gn:dem":-25,
    "gn:feature_class":"P",
    "gn:feature_code":"PPL",
    "gn:name":"Pal\u2019min Pervyy",
    "gn:population":0,
    "gn:timezone":"Europe/Astrakhan",
    "iso:country":"RU",
    "name:rus_x_preferred":[
        "\u041f\u0430\u043b\u044c\u043c\u0438\u043d \u041f\u0435\u0440\u0432\u044b\u0439"
    ],
    "name:und_x_variant":[
        "Gal\u2019min",
        "Pal\u2019min Pervyy",
        "\u041f\u0430\u043b\u044c\u043c\u0438\u043d \u041f\u0435\u0440\u0432\u044b\u0439"
    ],
    "wof:name":"Pal'min Pervyy",
    "wof:placetype":"locality"
},
  "geometry": {"coordinates":[47.73528,46.20139],"type":"Point"}
}