{
  "type": "Feature",
  "properties": {
    "gn:admin1_code":"17.0",
    "gn:asciiname":"Shangoda",
    "gn:country_code":"RU",
    "gn:dem":1514,
    "gn:feature_class":"P",
    "gn:feature_code":"PPL",
    "gn:name":"Shangoda",
    "gn:population":0,
    "gn:timezone":"Europe/Moscow",
    "iso:country":"RU",
    "name:rus_x_preferred":[
        "\u0428\u0430\u043d\u0433\u043e\u0434\u0430"
    ],
    "name:und_x_variant":[
        "\u0428\u0430\u043d\u0433\u043e\u0434\u0430"
    ],
    "wof:name":"Shangoda",
    "wof:placetype":"locality"
},
  "geometry": {"coordinates":[47.00423,42.25161],"type":"Point"}
}