{
  "type": "Feature",
  "properties": {
    "gn:admin1_code":"23",
    "gn:asciiname":"Il'inskoye",
    "gn:country_code":"RU",
    "gn:dem":106,
    "gn:feature_class":"P",
    "gn:feature_code":"PPL",
    "gn:name":"Il\u2019inskoye",
    "gn:population":0,
    "gn:timezone":"Europe/Kaliningrad",
    "iso:country":"RU",
    "name:lit_x_historical":[
        "Ka\u0161\u016bbai"
    ],
    "name:lit_x_preferred":[
        "Ka\u0161\u016bbai"
    ],
    "name:rus_x_preferred":[
        "\u0418\u043b\u044c\u0438\u043d\u0441\u043a\u043e\u0435"
    ],
    "name:und_x_variant":[
        "Kassuben",
        "Il\u2019jinskoe",
        "Il\u2019inskoye"
    ],
    "wof:name":"Il'inskoye",
    "wof:placetype":"locality"
},
  "geometry": {"coordinates":[22.51417,54.5025],"type":"Point"}
}