{
  "type": "Feature",
  "properties": {
    "gn:admin1_code":"10.0",
    "gn:asciiname":"Chekalina Sloboda",
    "gn:country_code":"RU",
    "gn:dem":210,
    "gn:feature_class":"P",
    "gn:feature_code":"PPL",
    "gn:name":"Chekalina Sloboda",
    "gn:population":0,
    "gn:timezone":"Europe/Moscow",
    "iso:country":"RU",
    "name:rus_x_preferred":[
        "\u0427\u0435\u043a\u0430\u043b\u0438\u043d\u0430 \u0421\u043b\u043e\u0431\u043e\u0434\u0430"
    ],
    "name:und_x_variant":[
        "Chekalino",
        "Chekalina Sloboda"
    ],
    "wof:name":"Chekalina Sloboda",
    "wof:placetype":"locality"
},
  "geometry": {"coordinates":[33.47243,53.74713000000001],"type":"Point"}
}