{
  "type": "Feature",
  "properties": {
    "gn:admin1_code":"33",
    "gn:asciiname":"Ryabovo",
    "gn:country_code":"RU",
    "gn:dem":158,
    "gn:feature_class":"P",
    "gn:feature_code":"PPL",
    "gn:name":"Ryabovo",
    "gn:population":0,
    "gn:timezone":"Europe/Kirov",
    "iso:country":"RU",
    "name:rus_x_preferred":[
        "\u0420\u044f\u0431\u043e\u0432\u043e"
    ],
    "name:und_x_variant":[
        "Vakhrushi",
        "Ryabovo",
        "\u0420\u044f\u0431\u043e\u0432\u043e"
    ],
    "wof:name":"Ryabovo",
    "wof:placetype":"locality"
},
  "geometry": {"coordinates":[50.81831,58.1934],"type":"Point"}
}