{
  "type": "Feature",
  "properties": {
    "gn:admin1_code":"84",
    "gn:asciiname":"Mogilinskiy",
    "gn:country_code":"RU",
    "gn:dem":155,
    "gn:feature_class":"P",
    "gn:feature_code":"PPL",
    "gn:name":"Mogilinskiy",
    "gn:population":0,
    "gn:timezone":"Europe/Volgograd",
    "iso:country":"RU",
    "name:rus_x_preferred":[
        "\u041c\u043e\u0433\u0438\u043b\u0438\u043d\u0441\u043a\u0438\u0439"
    ],
    "name:und_x_variant":[
        "\u041c\u043e\u0433\u0438\u043b\u0438\u043d\u0441\u043a\u0438\u0439"
    ],
    "wof:name":"Mogilinskiy",
    "wof:placetype":"locality"
},
  "geometry": {"coordinates":[44.21667,49.88333],"type":"Point"}
}