{
  "type": "Feature",
  "properties": {
    "gn:admin1_code":"47",
    "gn:asciiname":"Aleshino",
    "gn:country_code":"RU",
    "gn:dem":189,
    "gn:feature_class":"P",
    "gn:feature_code":"PPL",
    "gn:name":"Aleshino",
    "gn:population":0,
    "gn:timezone":"Europe/Moscow",
    "iso:country":"RU",
    "name:eng_x_preferred":[
        "Aleshino"
    ],
    "name:nor_x_preferred":[
        "Alesjino"
    ],
    "name:rus_x_preferred":[
        "\u0410\u043b\u0435\u0448\u0438\u043d\u043e"
    ],
    "name:und_x_variant":[
        "\u0410\u043b\u0435\u0448\u0438\u043d\u043e",
        "Aleshino"
    ],
    "wof:name":"Aleshino",
    "wof:placetype":"locality"
},
  "geometry": {"coordinates":[36.03201,55.6747],"type":"Point"}
}