{
  "type": "Feature",
  "properties": {
    "gn:admin1_code":"73",
    "gn:asciiname":"Kon'",
    "gn:country_code":"RU",
    "gn:dem":85,
    "gn:feature_class":"P",
    "gn:feature_code":"PPL",
    "gn:name":"Kon\u2019",
    "gn:population":0,
    "gn:timezone":"Europe/Moscow",
    "iso:country":"RU",
    "name:eng_x_preferred":[
        "Kon'"
    ],
    "name:nor_x_preferred":[
        "Kon"
    ],
    "name:rus_x_preferred":[
        "\u041a\u043e\u043d\u044c"
    ],
    "name:und_x_variant":[
        "Kon\u2019"
    ],
    "wof:name":"Kon'",
    "wof:placetype":"locality"
},
  "geometry": {"coordinates":[49.71606,55.71516999999999],"type":"Point"}
}