{
  "type": "Feature",
  "properties": {
    "gn:admin1_code":"60",
    "gn:asciiname":"Gorai",
    "gn:country_code":"RU",
    "gn:dem":82,
    "gn:feature_class":"P",
    "gn:feature_code":"PPL",
    "gn:name":"Gorai",
    "gn:population":0,
    "gn:timezone":"Europe/Moscow",
    "iso:country":"RU",
    "name:rus_x_preferred":[
        "\u0413\u043e\u0440\u0430\u0438"
    ],
    "name:und_x_variant":[
        "Goray",
        "Gorats",
        "Gorai"
    ],
    "wof:name":"Gorai",
    "wof:placetype":"locality"
},
  "geometry": {"coordinates":[28.51975,57.13158000000001],"type":"Point"}
}