{
  "type": "Feature",
  "properties": {
    "gn:admin1_code":"51",
    "gn:asciiname":"Khomutovo",
    "gn:country_code":"RU",
    "gn:dem":111,
    "gn:feature_class":"P",
    "gn:feature_code":"PPL",
    "gn:name":"Khomutovo",
    "gn:population":0,
    "gn:timezone":"Europe/Moscow",
    "iso:country":"RU",
    "name:eng_x_preferred":[
        "Khomutovo"
    ],
    "name:nor_x_preferred":[
        "Khomutovo"
    ],
    "name:rus_x_preferred":[
        "\u0425\u043e\u043c\u0443\u0442\u043e\u0432\u043e"
    ],
    "name:und_x_variant":[
        "\u0425\u043e\u043c\u0443\u0442\u043e\u0432\u043e",
        "Khomutovo"
    ],
    "wof:name":"Khomutovo",
    "wof:placetype":"locality"
},
  "geometry": {"coordinates":[44.70178,56.7014],"type":"Point"}
}