{
  "type": "Feature",
  "properties": {
    "gn:admin1_code":"28",
    "gn:asciiname":"Malen'ga",
    "gn:country_code":"RU",
    "gn:dem":35,
    "gn:feature_class":"P",
    "gn:feature_code":"PPL",
    "gn:name":"Malen\u2019ga",
    "gn:population":0,
    "gn:timezone":"Europe/Moscow",
    "iso:country":"RU",
    "name:eng_x_preferred":[
        "Malen'ga"
    ],
    "name:nor_x_preferred":[
        "Malenga"
    ],
    "name:rus_x_preferred":[
        "\u041c\u0430\u043b\u0435\u043d\u044c\u0433\u0430"
    ],
    "name:und_x_variant":[
        "Malen\u2019ga",
        "\u041c\u0430\u043b\u0435\u043d\u044c\u0433\u0430"
    ],
    "wof:name":"Malen'ga",
    "wof:placetype":"locality"
},
  "geometry": {"coordinates":[36.44068,63.8408],"type":"Point"}
}