{
  "type": "Feature",
  "properties": {
    "gn:admin1_code":"76",
    "gn:asciiname":"Proshchenoye",
    "gn:country_code":"RU",
    "gn:dem":184,
    "gn:feature_class":"P",
    "gn:feature_code":"PPL",
    "gn:name":"Proshchenoye",
    "gn:population":0,
    "gn:timezone":"Europe/Moscow",
    "iso:country":"RU",
    "name:rus_x_preferred":[
        "\u041f\u0440\u043e\u0449\u0435\u043d\u043e\u0435"
    ],
    "wof:name":"Proshchenoye",
    "wof:placetype":"locality"
},
  "geometry": {"coordinates":[38.793,53.7527],"type":"Point"}
}