{
  "type": "Feature",
  "properties": {
    "gn:admin1_code":"21.0",
    "gn:asciiname":"Burdino",
    "gn:country_code":"RU",
    "gn:dem":115,
    "gn:feature_class":"P",
    "gn:feature_code":"PPL",
    "gn:name":"Burdino",
    "gn:population":0,
    "gn:timezone":"Europe/Moscow",
    "iso:country":"RU",
    "name:che_x_preferred":[
        "\u0411\u0443\u0440\u0434\u0438\u043d\u043e"
    ],
    "name:rus_x_preferred":[
        "\u0411\u0443\u0440\u0434\u0438\u043d\u043e"
    ],
    "wof:name":"Burdino",
    "wof:placetype":"locality"
},
  "geometry": {"coordinates":[42.19013,57.05343000000001],"type":"Point"}
}