{
  "type": "Feature",
  "properties": {
    "gn:admin1_code":"73",
    "gn:asciiname":"Gornyasevo",
    "gn:country_code":"RU",
    "gn:dem":73,
    "gn:feature_class":"P",
    "gn:feature_code":"PPL",
    "gn:name":"Gornyasevo",
    "gn:population":0,
    "gn:timezone":"Europe/Moscow",
    "iso:country":"RU",
    "name:eng_x_preferred":[
        "Gornyasevo"
    ],
    "name:nor_x_preferred":[
        "Tjurnjasevo"
    ],
    "name:rus_x_preferred":[
        "\u0422\u044e\u0440\u043d\u044f\u0441\u0435\u0432\u043e"
    ],
    "name:rus_x_variant":[
        "\u0413\u043e\u0440\u043d\u044f\u0441\u0435\u0432\u043e"
    ],
    "wof:name":"Gornyasevo",
    "wof:placetype":"locality"
},
  "geometry": {"coordinates":[50.58333,54.58333],"type":"Point"}
}