{
  "type": "Feature",
  "properties": {
    "gn:admin1_code":"46",
    "gn:asciiname":"Nizovka",
    "gn:country_code":"RU",
    "gn:dem":127,
    "gn:feature_class":"P",
    "gn:feature_code":"PPL",
    "gn:name":"Nizovka",
    "gn:population":0,
    "gn:timezone":"Europe/Moscow",
    "iso:country":"RU",
    "name:rus_x_preferred":[
        "\u041d\u0438\u0437\u043e\u0432\u043a\u0430"
    ],
    "name:und_x_variant":[
        "\u041d\u0438\u0437\u043e\u0432\u043a\u0430"
    ],
    "wof:name":"Nizovka",
    "wof:placetype":"locality"
},
  "geometry": {"coordinates":[45.74784,54.70453000000001],"type":"Point"}
}