{
  "type": "Feature",
  "properties": {
    "gn:admin1_code":"71",
    "gn:asciiname":"Tarasova",
    "gn:country_code":"RU",
    "gn:dem":69,
    "gn:feature_class":"P",
    "gn:feature_code":"PPL",
    "gn:name":"Tarasova",
    "gn:population":0,
    "gn:timezone":"Asia/Yekaterinburg",
    "iso:country":"RU",
    "name:eng_x_preferred":[
        "Tarasova"
    ],
    "name:nor_x_preferred":[
        "Tarasova"
    ],
    "name:rus_x_preferred":[
        "\u0422\u0430\u0440\u0430\u0441\u043e\u0432\u0430"
    ],
    "wof:name":"Tarasova",
    "wof:placetype":"locality"
},
  "geometry": {"coordinates":[64.07919,57.00635],"type":"Point"}
}