{
  "type": "Feature",
  "properties": {
    "gn:admin1_code":"28",
    "gn:asciiname":"Vendyury",
    "gn:cc2":"RU",
    "gn:country_code":"RU",
    "gn:dem":175,
    "gn:feature_class":"P",
    "gn:feature_code":"PPL",
    "gn:name":"Vendyury",
    "gn:population":0,
    "gn:timezone":"Europe/Moscow",
    "iso:country":"RU",
    "name:eng_x_preferred":[
        "Vendyury"
    ],
    "name:fin_x_preferred":[
        "Ventyr\u00e4"
    ],
    "name:nor_x_preferred":[
        "Vendery"
    ],
    "name:rus_x_preferred":[
        "\u0412\u0435\u043d\u0434\u0435\u0440\u044b"
    ],
    "name:und_x_variant":[
        "Vendery",
        "Vendyury"
    ],
    "wof:name":"Vendyury",
    "wof:placetype":"locality"
},
  "geometry": {"coordinates":[33.2793,62.22524],"type":"Point"}
}