{
  "type": "Feature",
  "properties": {
    "gn:admin1_code":"54",
    "gn:asciiname":"Shiryayevo",
    "gn:country_code":"RU",
    "gn:dem":109,
    "gn:feature_class":"P",
    "gn:feature_code":"PPL",
    "gn:name":"Shiryayevo",
    "gn:population":0,
    "gn:timezone":"Asia/Omsk",
    "iso:country":"RU",
    "name:eng_x_preferred":[
        "Shiryayevo"
    ],
    "name:nor_x_preferred":[
        "Sjirjaevo"
    ],
    "name:rus_x_preferred":[
        "\u0428\u0438\u0440\u044f\u0435\u0432\u043e"
    ],
    "name:und_x_variant":[
        "Shiryayeva",
        "\u0428\u0438\u0440\u044f\u0435\u0432\u043e",
        "Shiryayevo"
    ],
    "wof:name":"Shiryayevo",
    "wof:placetype":"locality"
},
  "geometry": {"coordinates":[71.21968000000003,56.18403000000001],"type":"Point"}
}