{
  "type": "Feature",
  "properties": {
    "gn:admin1_code":"23",
    "gn:asciiname":"Rovnoye",
    "gn:country_code":"RU",
    "gn:dem":29,
    "gn:feature_class":"P",
    "gn:feature_code":"PPL",
    "gn:name":"Rovnoye",
    "gn:population":0,
    "gn:timezone":"Europe/Kaliningrad",
    "iso:country":"RU",
    "name:rus_x_preferred":[
        "\u0420\u043e\u0432\u043d\u043e\u0435"
    ],
    "name:und_x_variant":[
        "Heinrichsdorf",
        "Rovnoye",
        "\u0420\u043e\u0432\u043d\u043e\u0435"
    ],
    "wof:name":"Rovnoye",
    "wof:placetype":"locality"
},
  "geometry": {"coordinates":[20.97641,54.46405],"type":"Point"}
}