{
  "type": "Feature",
  "properties": {
    "gn:admin1_code":"60",
    "gn:asciiname":"Kriukha",
    "gn:country_code":"RU",
    "gn:dem":193,
    "gn:feature_class":"P",
    "gn:feature_code":"PPL",
    "gn:name":"Kriukha",
    "gn:population":0,
    "gn:timezone":"Europe/Moscow",
    "iso:country":"RU",
    "name:eng_x_preferred":[
        "Kriukha"
    ],
    "name:nor_x_preferred":[
        "Kriukha"
    ],
    "name:rus_x_preferred":[
        "\u041a\u0440\u0438\u0443\u0445\u0430"
    ],
    "wof:name":"Kriukha",
    "wof:placetype":"locality"
},
  "geometry": {"coordinates":[29.41576,56.51106],"type":"Point"}
}