{
  "type": "Feature",
  "properties": {
    "gn:admin1_code":"29",
    "gn:asciiname":"Nizhneyashkino",
    "gn:country_code":"RU",
    "gn:dem":190,
    "gn:feature_class":"P",
    "gn:feature_code":"PPL",
    "gn:name":"Nizhneyashkino",
    "gn:population":0,
    "gn:timezone":"Asia/Novokuznetsk",
    "iso:country":"RU",
    "name:eng_x_preferred":[
        "Nizhneyashkino"
    ],
    "name:rus_x_preferred":[
        "\u042f\u0448\u043a\u0438\u043d\u043e"
    ],
    "name:rus_x_variant":[
        "\u041d\u0438\u0436\u043d\u0435\u044f\u0448\u043a\u0438\u043d\u043e"
    ],
    "name:und_x_variant":[
        "Yashkina",
        "\u041d\u0438\u0436\u043d\u0435\u044f\u0448\u043a\u0438\u043d\u043e",
        "Nizhneyashkino"
    ],
    "wof:name":"Nizhneyashkino",
    "wof:placetype":"locality"
},
  "geometry": {"coordinates":[85.4691,55.8288],"type":"Point"}
}