{
  "type": "Feature",
  "properties": {
    "gn:admin1_code":"62.0",
    "gn:asciiname":"Bazhenovo",
    "gn:country_code":"RU",
    "gn:dem":113,
    "gn:feature_class":"P",
    "gn:feature_code":"PPL",
    "gn:name":"Bazhenovo",
    "gn:population":0,
    "gn:timezone":"Europe/Moscow",
    "iso:country":"RU",
    "name:bak_x_preferred":[
        "\u0411\u0430\u0436\u0435\u043d\u043e\u0432"
    ],
    "name:che_x_preferred":[
        "\u0411\u0430\u0436\u0435\u043d\u043e\u0432\u043e"
    ],
    "name:hye_x_preferred":[
        "\u0532\u0561\u056a\u0565\u0576\u0578\u057e\u0578"
    ],
    "name:kaz_x_preferred":[
        "\u0411\u0430\u0436\u0435\u043d"
    ],
    "name:kir_x_preferred":[
        "\u0411\u0430\u0436\u0435\u043d"
    ],
    "name:nor_x_preferred":[
        "Bazjenovo"
    ],
    "name:rus_x_preferred":[
        "\u0411\u0430\u0436\u0435\u043d\u043e\u0432\u043e"
    ],
    "name:tat_x_preferred":[
        "\u0411\u0430\u0436\u0435\u043d\u043e\u0432\u043e"
    ],
    "name:ukr_x_preferred":[
        "\u0411\u0430\u0436\u0435\u043d\u043e\u0432\u043e"
    ],
    "wof:name":"Bazhenovo",
    "wof:placetype":"locality"
},
  "geometry": {"coordinates":[41.31512,54.98682],"type":"Point"}
}