{
  "type": "Feature",
  "properties": {
    "gn:admin1_code":"73",
    "gn:asciiname":"Kim",
    "gn:country_code":"RU",
    "gn:dem":51,
    "gn:feature_class":"P",
    "gn:feature_code":"PPL",
    "gn:name":"Kim",
    "gn:population":0,
    "gn:timezone":"Europe/Moscow",
    "iso:country":"RU",
    "name:aze_x_preferred":[
        "Kim"
    ],
    "name:bel_x_preferred":[
        "\u041a\u0456\u043c"
    ],
    "name:ceb_x_preferred":[
        "Kim"
    ],
    "name:ces_x_preferred":[
        "Kim"
    ],
    "name:dan_x_preferred":[
        "Kim"
    ],
    "name:deu_x_preferred":[
        "Kim"
    ],
    "name:fas_x_preferred":[
        "\u06a9\u06cc\u0645"
    ],
    "name:fin_x_preferred":[
        "Kim"
    ],
    "name:fra_x_preferred":[
        "Kim"
    ],
    "name:heb_x_preferred":[
        "\u05e7\u05d9\u05dd"
    ],
    "name:hun_x_preferred":[
        "Kim"
    ],
    "name:nld_x_preferred":[
        "Kim"
    ],
    "name:nor_x_preferred":[
        "Kim"
    ],
    "name:pol_x_preferred":[
        "Kim"
    ],
    "name:por_x_preferred":[
        "Kim"
    ],
    "name:ron_x_preferred":[
        "Kim"
    ],
    "name:rus_x_preferred":[
        "\u041a\u0438\u043c"
    ],
    "name:sco_x_preferred":[
        "Kim"
    ],
    "name:spa_x_preferred":[
        "Kim"
    ],
    "name:srp_x_preferred":[
        "Kim"
    ],
    "name:swe_x_preferred":[
        "Kim"
    ],
    "name:tur_x_preferred":[
        "Kim"
    ],
    "name:ukr_x_preferred":[
        "\u041a\u0456\u043c"
    ],
    "name:und_x_variant":[
        "\u041a\u0438\u043c"
    ],
    "name:vie_x_preferred":[
        "Kim"
    ],
    "wof:name":"Kim",
    "wof:placetype":"locality"
},
  "geometry": {"coordinates":[49.41667,55.01667],"type":"Point"}
}