{
  "type": "Feature",
  "properties": {
    "gn:admin1_code":"63",
    "gn:asciiname":"Umsan",
    "gn:country_code":"RU",
    "gn:dem":225,
    "gn:feature_class":"P",
    "gn:feature_code":"PPL",
    "gn:name":"Umsan",
    "gn:population":0,
    "gn:timezone":"Asia/Vladivostok",
    "iso:country":"RU",
    "wof:name":"Umsan",
    "wof:placetype":"locality"
},
  "geometry": {"coordinates":[132.18333000000001,67.18333],"type":"Point"}
}