{
  "type": "Feature",
  "properties": {
    "gn:admin1_code":"84",
    "gn:asciiname":"Bol'shaya Glushitsa",
    "gn:country_code":"RU",
    "gn:dem":86,
    "gn:feature_class":"P",
    "gn:feature_code":"PPL",
    "gn:name":"Bol\u2019shaya Glushitsa",
    "gn:population":0,
    "gn:timezone":"Europe/Volgograd",
    "iso:country":"RU",
    "name:rus_x_preferred":[
        "Bol\u2019shaya Glushitsa"
    ],
    "name:rus_x_variant":[
        "\u0411\u043e\u043b\u044c\u0448\u0430\u044f \u0413\u043b\u0443\u0448\u0438\u0446\u0430"
    ],
    "wof:name":"Bol'shaya Glushitsa",
    "wof:placetype":"locality"
},
  "geometry": {"coordinates":[43.5929,50.2402],"type":"Point"}
}