{
  "type": "Feature",
  "properties": {
    "gn:admin1_code":"60",
    "gn:asciiname":"Maloye Golubsko",
    "gn:country_code":"RU",
    "gn:dem":81,
    "gn:feature_class":"P",
    "gn:feature_code":"PPL",
    "gn:name":"Maloye Golubsko",
    "gn:population":0,
    "gn:timezone":"Europe/Moscow",
    "iso:country":"RU",
    "name:rus_x_preferred":[
        "\u041c\u0430\u043b\u043e\u0435 \u0413\u043e\u043b\u0443\u0431\u0441\u043a\u043e"
    ],
    "name:und_x_variant":[
        "Malo-Golubovskoye",
        "Maloye Golubskoye",
        "Maloye Golubsko",
        "\u041c\u0430\u043b\u043e\u0435 \u0413\u043e\u043b\u0443\u0431\u0441\u043a\u043e"
    ],
    "wof:name":"Maloye Golubsko",
    "wof:placetype":"locality"
},
  "geometry": {"coordinates":[28.74164,58.64726999999999],"type":"Point"}
}