{
  "type": "Feature",
  "properties": {
    "gn:admin1_code":"56.0",
    "gn:asciiname":"Bulgakova",
    "gn:country_code":"RU",
    "gn:dem":181,
    "gn:feature_class":"P",
    "gn:feature_code":"PPL",
    "gn:name":"Bulgakova",
    "gn:population":0,
    "gn:timezone":"Europe/Moscow",
    "iso:country":"RU",
    "name:rus_x_preferred":[
        "\u0411\u0443\u043b\u0433\u0430\u043a\u043e\u0432\u0430"
    ],
    "name:und_x_variant":[
        "Bulgakovo",
        "Bulgakova"
    ],
    "wof:name":"Bulgakova",
    "wof:placetype":"locality"
},
  "geometry": {"coordinates":[35.74158,53.39443000000001],"type":"Point"}
}