{
  "type": "Feature",
  "properties": {
    "gn:admin1_code":"90",
    "gn:asciiname":"Gubany",
    "gn:country_code":"RU",
    "gn:dem":133,
    "gn:feature_class":"P",
    "gn:feature_code":"PPL",
    "gn:name":"Gubany",
    "gn:population":0,
    "gn:timezone":"Asia/Yekaterinburg",
    "iso:country":"RU",
    "name:rus_x_preferred":[
        "\u0413\u0443\u0431\u0430\u043d\u044b"
    ],
    "name:und_x_variant":[
        "\u0413\u0443\u0431\u0430\u043d\u044b"
    ],
    "wof:name":"Gubany",
    "wof:placetype":"locality"
},
  "geometry": {"coordinates":[55.5866,56.4741],"type":"Point"}
}