{
  "type": "Feature",
  "properties": {
    "gn:admin1_code":"13",
    "gn:asciiname":"Adishchevo",
    "gn:country_code":"RU",
    "gn:dem":178,
    "gn:feature_class":"P",
    "gn:feature_code":"PPL",
    "gn:name":"Adishchevo",
    "gn:population":0,
    "gn:timezone":"Asia/Yekaterinburg",
    "iso:country":"RU",
    "name:che_x_preferred":[
        "\u0410\u0434\u0438\u0449\u0435\u0432\u043e"
    ],
    "name:eng_x_preferred":[
        "Adishchevo"
    ],
    "name:nor_x_preferred":[
        "Adisjtsjevo"
    ],
    "name:rus_x_preferred":[
        "\u0410\u0434\u0438\u0449\u0435\u0432\u043e"
    ],
    "name:und_x_variant":[
        "\u0410\u0434\u0438\u0449\u0435\u0432\u043e",
        "Adishchevo"
    ],
    "wof:name":"Adishchevo",
    "wof:placetype":"locality"
},
  "geometry": {"coordinates":[61.9561,55.1934],"type":"Point"}
}