{
  "type": "Feature",
  "properties": {
    "gn:admin1_code":"56.0",
    "gn:asciiname":"Arkhipova",
    "gn:country_code":"RU",
    "gn:dem":219,
    "gn:feature_class":"P",
    "gn:feature_code":"PPL",
    "gn:name":"Arkhipova",
    "gn:population":0,
    "gn:timezone":"Europe/Moscow",
    "iso:country":"RU",
    "name:nor_x_preferred":[
        "Arkhipova"
    ],
    "name:rus_x_preferred":[
        "\u0410\u0440\u0445\u0438\u043f\u043e\u0432\u0430"
    ],
    "wof:name":"Arkhipova",
    "wof:placetype":"locality"
},
  "geometry": {"coordinates":[35.96088,53.58976],"type":"Point"}
}