{
  "type": "Feature",
  "properties": {
    "gn:admin1_code":"67",
    "gn:asciiname":"Novoivanovka",
    "gn:country_code":"RU",
    "gn:dem":45,
    "gn:feature_class":"P",
    "gn:feature_code":"PPL",
    "gn:name":"Novoivanovka",
    "gn:population":0,
    "gn:timezone":"Europe/Saratov",
    "iso:country":"RU",
    "name:azb_x_preferred":[
        "\u0646\u0648\u0648\u0648\u06cc\u0648\u0627\u0646\u0648\u0648\u06a9\u0627"
    ],
    "name:aze_x_preferred":[
        "Novoivanovka"
    ],
    "name:ceb_x_preferred":[
        "Novoivanovka"
    ],
    "name:ita_x_preferred":[
        "Novoivanovka"
    ],
    "name:kat_x_preferred":[
        "\u10dc\u10dd\u10d5\u10dd\u10d8\u10d5\u10d0\u10dc\u10dd\u10d5\u10d9\u10d0"
    ],
    "name:msa_x_preferred":[
        "Novoivanovka"
    ],
    "name:rus_x_preferred":[
        "\u041d\u043e\u0432\u043e\u0438\u0432\u0430\u043d\u043e\u0432\u043a\u0430"
    ],
    "name:swe_x_preferred":[
        "Novoivanovka"
    ],
    "wof:name":"Novoivanovka",
    "wof:placetype":"locality"
},
  "geometry": {"coordinates":[49.3895,51.7597],"type":"Point"}
}