{
  "type": "Feature",
  "properties": {
    "gn:admin1_code":"61",
    "gn:asciiname":"Krasnyy Nesvetay",
    "gn:cc2":"RU",
    "gn:country_code":"RU",
    "gn:dem":173,
    "gn:feature_class":"P",
    "gn:feature_code":"PPL",
    "gn:name":"Krasnyy Nesvetay",
    "gn:population":0,
    "gn:timezone":"Europe/Moscow",
    "iso:country":"RU",
    "name:rus_x_preferred":[
        "\u041a\u0440\u0430\u0441\u043d\u044b\u0439 \u041d\u0435\u0441\u0432\u0435\u0442\u0430\u0439"
    ],
    "name:und_x_variant":[
        "Krasny Nesvetay",
        "Krasnyy Nesvetay"
    ],
    "wof:name":"Krasnyy Nesvetay",
    "wof:placetype":"locality"
},
  "geometry": {"coordinates":[39.89833,47.77111],"type":"Point"}
}