{
  "type": "Feature",
  "properties": {
    "gn:admin1_code":"91.0",
    "gn:asciiname":"Novovozdvizhenka",
    "gn:country_code":"RU",
    "gn:dem":269,
    "gn:feature_class":"P",
    "gn:feature_code":"PPL",
    "gn:name":"Novovozdvizhenka",
    "gn:population":0,
    "gn:timezone":"Asia/Krasnoyarsk",
    "iso:country":"RU",
    "name:bak_x_preferred":[
        "\u042f\u04a3\u044b \u0412\u043e\u0437\u0434\u0432\u0438\u0436\u0435\u043d\u043a\u0430"
    ],
    "name:che_x_preferred":[
        "\u041d\u043e\u0432\u043e\u0432\u043e\u0437\u0434\u0432\u0438\u0436\u0435\u043d\u043a\u0430"
    ],
    "name:hye_x_preferred":[
        "\u0546\u0578\u057e\u0578\u057e\u0578\u0566\u0564\u057e\u056b\u056a\u0565\u0576\u056f\u0561"
    ],
    "name:kat_x_preferred":[
        "\u10dc\u10dd\u10d5\u10dd\u10d5\u10dd\u10d6\u10d3\u10d5\u10d8\u10df\u10d4\u10dc\u10d9\u10d0"
    ],
    "name:kaz_x_preferred":[
        "\u0416\u0430\u04a3\u0430 \u0412\u043e\u0437\u0434\u0432\u0438\u0436\u0435\u043d\u043a\u0430"
    ],
    "name:kir_x_preferred":[
        "\u0416\u0430\u04a3\u044b \u0412\u043e\u0437\u0434\u0432\u0438\u0436\u0435\u043d\u043a\u0430"
    ],
    "name:rus_x_preferred":[
        "\u041d\u043e\u0432\u043e\u0432\u043e\u0437\u0434\u0432\u0438\u0436\u0435\u043d\u043a\u0430"
    ],
    "name:tat_x_preferred":[
        "\u041d\u043e\u0432\u043e\u0432\u043e\u0437\u0434\u0432\u0438\u0436\u0435\u043d\u043a\u0430"
    ],
    "name:ukr_x_preferred":[
        "\u041d\u043e\u0432\u043e\u0432\u043e\u0437\u0434\u0432\u0438\u0436\u0435\u043d\u043a\u0430"
    ],
    "wof:name":"Novovozdvizhenka",
    "wof:placetype":"locality"
},
  "geometry": {"coordinates":[96.5622,56.4639],"type":"Point"}
}