{
  "type": "Feature",
  "properties": {
    "gn:asciiname":"Mayskoye",
    "gn:country_code":"RU",
    "gn:dem":1,
    "gn:feature_class":"P",
    "gn:feature_code":"PPL",
    "gn:name":"Mayskoye",
    "gn:population":0,
    "gn:timezone":"Europe/Moscow",
    "iso:country":"RU",
    "name:fin_x_preferred":[
        "Hannukkala"
    ],
    "wof:name":"Mayskoye",
    "wof:placetype":"locality"
},
  "geometry": {"coordinates":[28.63518,60.59194],"type":"Point"}
}