{
  "type": "Feature",
  "properties": {
    "gn:admin1_code":"13",
    "gn:asciiname":"Dolgovka",
    "gn:country_code":"RU",
    "gn:dem":266,
    "gn:feature_class":"P",
    "gn:feature_code":"PPL",
    "gn:name":"Dolgovka",
    "gn:population":0,
    "gn:timezone":"Asia/Yekaterinburg",
    "iso:country":"RU",
    "name:eng_x_preferred":[
        "Dolgovka"
    ],
    "name:nor_x_preferred":[
        "Dolgovka"
    ],
    "name:rus_x_preferred":[
        "\u0414\u043e\u043b\u0433\u043e\u0432\u043a\u0430"
    ],
    "name:und_x_variant":[
        "Dolgovskiy",
        "Dolgovskoye"
    ],
    "wof:name":"Dolgovka",
    "wof:placetype":"locality"
},
  "geometry": {"coordinates":[60.93972,54.79278000000001],"type":"Point"}
}