{
  "type": "Feature",
  "properties": {
    "gn:admin1_code":"41",
    "gn:asciiname":"Belyy Klyuch",
    "gn:country_code":"RU",
    "gn:dem":164,
    "gn:feature_class":"P",
    "gn:feature_code":"PPL",
    "gn:name":"Belyy Klyuch",
    "gn:population":0,
    "gn:timezone":"Europe/Moscow",
    "iso:country":"RU",
    "name:rus_x_preferred":[
        "\u0411\u0435\u043b\u044b\u0439 \u041a\u043b\u044e\u0447"
    ],
    "wof:name":"Belyy Klyuch",
    "wof:placetype":"locality"
},
  "geometry": {"coordinates":[35.1337,51.9979],"type":"Point"}
}