{
  "type": "Feature",
  "properties": {
    "gn:admin1_code":"90",
    "gn:asciiname":"Zavod Mikhaylovskiy",
    "gn:country_code":"RU",
    "gn:dem":138,
    "gn:feature_class":"P",
    "gn:feature_code":"PPL",
    "gn:name":"Zavod Mikhaylovskiy",
    "gn:population":0,
    "gn:timezone":"Asia/Yekaterinburg",
    "iso:country":"RU",
    "name:eng_x_preferred":[
        "Zavod-Mikhaylovskiy"
    ],
    "name:nor_x_preferred":[
        "Zavod Mikhajlovskij"
    ],
    "name:rus_x_preferred":[
        "\u0417\u0430\u0432\u043e\u0434 \u041c\u0438\u0445\u0430\u0439\u043b\u043e\u0432\u0441\u043a\u0438\u0439"
    ],
    "name:und_x_variant":[
        "Mikaylovskiy Zavod",
        "Mikhaylovskiy",
        "Zavod Mikhaylovskiy"
    ],
    "wof:name":"Zavod Mikhaylovskiy",
    "wof:placetype":"locality"
},
  "geometry": {"coordinates":[54.2818,56.5223],"type":"Point"}
}