{
  "type": "Feature",
  "properties": {
    "gn:admin1_code":"85",
    "gn:asciiname":"Kondratovo",
    "gn:country_code":"RU",
    "gn:dem":126,
    "gn:feature_class":"P",
    "gn:feature_code":"PPL",
    "gn:name":"Kondratovo",
    "gn:population":0,
    "gn:timezone":"Europe/Moscow",
    "iso:country":"RU",
    "name:ceb_x_preferred":[
        "Kondratovo"
    ],
    "name:che_x_preferred":[
        "\u041a\u043e\u043d\u0434\u0440\u0430\u0442\u043e\u0432\u043e"
    ],
    "name:deu_x_preferred":[
        "Kondratowo"
    ],
    "name:hye_x_preferred":[
        "\u053f\u0578\u0576\u0564\u0580\u0561\u057f\u0578\u057e\u0578"
    ],
    "name:rus_x_preferred":[
        "\u041a\u043e\u043d\u0434\u0440\u0430\u0442\u043e\u0432\u043e"
    ],
    "name:und_x_variant":[
        "\u041a\u043e\u043d\u0434\u0440\u0430\u0442\u043e\u0432\u043e"
    ],
    "wof:name":"Kondratovo",
    "wof:placetype":"locality"
},
  "geometry": {"coordinates":[38.26214,59.81446999999999],"type":"Point"}
}