{
  "type": "Feature",
  "properties": {
    "gn:admin1_code":"4",
    "gn:asciiname":"Noven'koye",
    "gn:country_code":"RU",
    "gn:dem":239,
    "gn:feature_class":"P",
    "gn:feature_code":"PPL",
    "gn:name":"Noven\u2019koye",
    "gn:population":0,
    "gn:timezone":"Asia/Barnaul",
    "iso:country":"RU",
    "name:eng_x_preferred":[
        "Noven'koye"
    ],
    "name:nor_x_preferred":[
        "Novenkoje"
    ],
    "name:rus_x_preferred":[
        "\u041d\u043e\u0432\u0435\u043d\u044c\u043a\u043e\u0435"
    ],
    "name:und_x_variant":[
        "Noven\u2019koye"
    ],
    "wof:name":"Noven'koye",
    "wof:placetype":"locality"
},
  "geometry": {"coordinates":[81.14889000000002,51.05222],"type":"Point"}
}