{
  "type": "Feature",
  "properties": {
    "gn:admin1_code":"73",
    "gn:asciiname":"Staryy Uzyum",
    "gn:country_code":"RU",
    "gn:dem":131,
    "gn:feature_class":"P",
    "gn:feature_code":"PPL",
    "gn:name":"Staryy Uzyum",
    "gn:population":0,
    "gn:timezone":"Europe/Moscow",
    "iso:country":"RU",
    "name:rus_x_preferred":[
        "\u0421\u0442\u0430\u0440\u044b\u0439 \u0423\u0437\u044e\u043c"
    ],
    "wof:name":"Staryy Uzyum",
    "wof:placetype":"locality"
},
  "geometry": {"coordinates":[49.56151,56.34225],"type":"Point"}
}