{
  "type": "Feature",
  "properties": {
    "gn:admin1_code":"91",
    "gn:asciiname":"Ignatovo",
    "gn:country_code":"RU",
    "gn:dem":171,
    "gn:feature_class":"P",
    "gn:feature_code":"PPL",
    "gn:name":"Ignatovo",
    "gn:population":0,
    "gn:timezone":"Asia/Krasnoyarsk",
    "iso:country":"RU",
    "name:eng_x_preferred":[
        "Ignatovo"
    ],
    "name:nor_x_preferred":[
        "Ignatovo"
    ],
    "name:rus_x_preferred":[
        "\u0418\u0433\u043d\u0430\u0442\u043e\u0432\u043e"
    ],
    "wof:name":"Ignatovo",
    "wof:placetype":"locality"
},
  "geometry": {"coordinates":[92.46339999999999,57.6126],"type":"Point"}
}