{
  "type": "Feature",
  "properties": {
    "gn:admin1_code":"77",
    "gn:asciiname":"Sorokopenino",
    "gn:country_code":"RU",
    "gn:dem":133,
    "gn:feature_class":"P",
    "gn:feature_code":"PPL",
    "gn:name":"Sorokopenino",
    "gn:population":0,
    "gn:timezone":"Europe/Moscow",
    "iso:country":"RU",
    "name:rus_x_preferred":[
        "\u0421\u043e\u0440\u043e\u043a\u043e\u043f\u0435\u043d\u0438\u043d\u043e"
    ],
    "name:und_x_variant":[
        "\u0421\u043e\u0440\u043e\u043a\u043e\u043f\u0435\u043d\u0438\u043d\u043e"
    ],
    "wof:name":"Sorokopenino",
    "wof:placetype":"locality"
},
  "geometry": {"coordinates":[36.8186,56.6716],"type":"Point"}
}