{
  "type": "Feature",
  "properties": {
    "gn:admin1_code":"90.0",
    "gn:asciiname":"Sludka",
    "gn:country_code":"RU",
    "gn:dem":113,
    "gn:feature_class":"P",
    "gn:feature_code":"PPL",
    "gn:name":"Sludka",
    "gn:population":0,
    "gn:timezone":"Asia/Yekaterinburg",
    "iso:country":"RU",
    "name:che_x_preferred":[
        "\u0421\u043b\u0443\u0434\u043a\u0430"
    ],
    "name:chv_x_preferred":[
        "\u0421\u043b\u0443\u0434\u043a\u0430"
    ],
    "name:rus_x_preferred":[
        "\u0421\u043b\u0443\u0434\u043a\u0430"
    ],
    "name:tat_x_preferred":[
        "\u0421\u043b\u0443\u0434\u043a\u0430"
    ],
    "wof:name":"Sludka",
    "wof:placetype":"locality"
},
  "geometry": {"coordinates":[55.5358,58.9866],"type":"Point"}
}