{
  "type": "Feature",
  "properties": {
    "gn:admin1_code":"8",
    "gn:asciiname":"Kyzylyarovo",
    "gn:country_code":"RU",
    "gn:dem":101,
    "gn:feature_class":"P",
    "gn:feature_code":"PPL",
    "gn:name":"Kyzylyarovo",
    "gn:population":0,
    "gn:timezone":"Asia/Yekaterinburg",
    "iso:country":"RU",
    "name:aze_x_preferred":[
        "Q\u0131z\u0131lyar"
    ],
    "name:bak_x_preferred":[
        "\u04a0\u044b\u0499\u044b\u043b\u044a\u044f\u0440"
    ],
    "name:che_x_preferred":[
        "\u041a\u044b\u0437\u044b\u043b\u044f\u0440\u043e\u0432\u043e"
    ],
    "name:hye_x_preferred":[
        "\u053f\u056b\u0566\u056b\u056c\u0575\u0561\u0580\u0578\u057e\u0578"
    ],
    "name:kat_x_preferred":[
        "\u10d9\u10d8\u10d6\u10d8\u10da\u10d8\u10d0\u10e0\u10dd\u10d5\u10dd"
    ],
    "name:kaz_x_preferred":[
        "\u049a\u044b\u0437\u044b\u043b\u044f\u0440"
    ],
    "name:kir_x_preferred":[
        "\u041a\u044b\u0437\u044b\u043b\u044f\u0440"
    ],
    "name:rus_x_preferred":[
        "\u041a\u044b\u0437\u044b\u043b\u044f\u0440\u043e\u0432\u043e"
    ],
    "name:tat_x_preferred":[
        "\u041a\u044b\u0437\u044b\u043b\u044a\u044f\u0440"
    ],
    "name:ukr_x_preferred":[
        "\u041a\u0438\u0437\u0438\u043b\u044f\u0440\u043e\u0432\u043e"
    ],
    "name:und_x_variant":[
        "Kyzylyar"
    ],
    "wof:name":"Kyzylyarovo",
    "wof:placetype":"locality"
},
  "geometry": {"coordinates":[56.60306,54.46496],"type":"Point"}
}