{
  "type": "Feature",
  "properties": {
    "gn:admin1_code":"8",
    "gn:asciiname":"Kyzylyarovo",
    "gn:country_code":"RU",
    "gn:dem":101,
    "gn:feature_class":"P",
    "gn:feature_code":"PPL",
    "gn:name":"Kyzylyarovo",
    "gn:population":0,
    "gn:timezone":"Asia/Yekaterinburg",
    "iso:country":"RU",
    "name:rus_x_preferred":[
        "\u041a\u044b\u0437\u044b\u043b\u044f\u0440\u043e\u0432\u043e"
    ],
    "name:und_x_variant":[
        "\u041a\u044b\u0437\u044b\u043b\u044f\u0440\u043e\u0432\u043e",
        "Kyzylyar"
    ],
    "wof:name":"Kyzylyarovo",
    "wof:placetype":"locality"
},
  "geometry": {"coordinates":[56.60306,54.46496],"type":"Point"}
}