{
  "type": "Feature",
  "properties": {
    "gn:admin1_code":"8",
    "gn:asciiname":"Ibrayevo",
    "gn:country_code":"RU",
    "gn:dem":159,
    "gn:feature_class":"P",
    "gn:feature_code":"PPL",
    "gn:name":"Ibrayevo",
    "gn:population":0,
    "gn:timezone":"Asia/Yekaterinburg",
    "iso:country":"RU",
    "name:rus_x_preferred":[
        "\u0418\u0431\u0440\u0430\u0435\u0432\u043e"
    ],
    "name:und_x_variant":[
        "\u0418\u0431\u0440\u0430\u0435\u0432\u043e"
    ],
    "wof:name":"Ibrayevo",
    "wof:placetype":"locality"
},
  "geometry": {"coordinates":[56.5755,53.66479],"type":"Point"}
}