{
  "type": "Feature",
  "properties": {
    "gn:admin1_code":"8",
    "gn:asciiname":"Ibrayevo",
    "gn:country_code":"RU",
    "gn:dem":159,
    "gn:feature_class":"P",
    "gn:feature_code":"PPL",
    "gn:name":"Ibrayevo",
    "gn:population":0,
    "gn:timezone":"Asia/Yekaterinburg",
    "iso:country":"RU",
    "name:bak_x_preferred":[
        "\u0418\u0431\u0440\u0430\u0439"
    ],
    "name:hye_x_preferred":[
        "\u053b\u0562\u0580\u0561\u0587\u0578"
    ],
    "name:kat_x_preferred":[
        "\u10d8\u10d1\u10e0\u10d0\u10d4\u10d5\u10dd"
    ],
    "name:rus_x_preferred":[
        "\u0418\u0431\u0440\u0430\u0435\u0432\u043e"
    ],
    "name:tat_x_preferred":[
        "\u0418\u0431\u0440\u0430\u0439"
    ],
    "name:ukr_x_preferred":[
        "\u0406\u0431\u0440\u0430\u0454\u0432\u043e"
    ],
    "wof:name":"Ibrayevo",
    "wof:placetype":"locality"
},
  "geometry": {"coordinates":[56.5755,53.66479],"type":"Point"}
}