{
  "type": "Feature",
  "properties": {
    "gn:admin1_code":"28",
    "gn:asciiname":"Suriniyemi",
    "gn:cc2":"RU",
    "gn:country_code":"RU",
    "gn:dem":115,
    "gn:feature_class":"P",
    "gn:feature_code":"PPL",
    "gn:name":"Suriniyemi",
    "gn:population":0,
    "gn:timezone":"Europe/Moscow",
    "iso:country":"RU",
    "name:fin_x_preferred":[
        "Suurniemi"
    ],
    "name:rus_x_preferred":[
        "\u0421\u0443\u0440\u0438\u043d\u0438\u0435\u043c\u0438"
    ],
    "name:und_x_variant":[
        "Suuriniemi",
        "Suriniyemi"
    ],
    "wof:name":"Suriniyemi",
    "wof:placetype":"locality"
},
  "geometry": {"coordinates":[32.36667,62.26667],"type":"Point"}
}