{
  "type": "Feature",
  "properties": {
    "gn:admin1_code":"62",
    "gn:asciiname":"Slobodka",
    "gn:country_code":"RU",
    "gn:dem":168,
    "gn:feature_class":"P",
    "gn:feature_code":"PPL",
    "gn:name":"Slobodka",
    "gn:population":0,
    "gn:timezone":"Europe/Moscow",
    "iso:country":"RU",
    "name:eng_x_preferred":[
        "Slobodka"
    ],
    "name:nor_x_preferred":[
        "Slobodka"
    ],
    "name:rus_x_preferred":[
        "\u0421\u043b\u043e\u0431\u043e\u0434\u043a\u0430"
    ],
    "name:und_x_variant":[
        "\u0421\u043b\u043e\u0431\u043e\u0434\u043a\u0430",
        "Slobodka"
    ],
    "wof:name":"Slobodka",
    "wof:placetype":"locality"
},
  "geometry": {"coordinates":[39.2734,54.1803],"type":"Point"}
}