{
  "type": "Feature",
  "properties": {
    "gn:admin1_code":"46.0",
    "gn:asciiname":"Udobnyy",
    "gn:country_code":"RU",
    "gn:dem":200,
    "gn:feature_class":"P",
    "gn:feature_code":"PPL",
    "gn:name":"Udobnyy",
    "gn:population":0,
    "gn:timezone":"Europe/Moscow",
    "iso:country":"RU",
    "name:rus_x_preferred":[
        "\u0423\u0434\u043e\u0431\u043d\u044b\u0439"
    ],
    "wof:name":"Udobnyy",
    "wof:placetype":"locality"
},
  "geometry": {"coordinates":[44.92714,54.33988000000001],"type":"Point"}
}