{
  "type": "Feature",
  "properties": {
    "gn:admin1_code":"33",
    "gn:asciiname":"Rogozki",
    "gn:country_code":"RU",
    "gn:dem":207,
    "gn:feature_class":"P",
    "gn:feature_code":"PPL",
    "gn:name":"Rogozki",
    "gn:population":0,
    "gn:timezone":"Europe/Kirov",
    "iso:country":"RU",
    "name:rus_x_preferred":[
        "\u0420\u043e\u0433\u043e\u0437\u043a\u0438"
    ],
    "wof:name":"Rogozki",
    "wof:placetype":"locality"
},
  "geometry": {"coordinates":[50.3775,57.97],"type":"Point"}
}