{
  "type": "Feature",
  "properties": {
    "gn:admin1_code":"91",
    "gn:asciiname":"Troitsk",
    "gn:country_code":"RU",
    "gn:dem":362,
    "gn:feature_class":"P",
    "gn:feature_code":"PPL",
    "gn:name":"Troitsk",
    "gn:population":0,
    "gn:timezone":"Asia/Krasnoyarsk",
    "iso:country":"RU",
    "name:ben_x_preferred":[
        "\u09a4\u09cd\u09b0\u09cb\u0987\u09a4\u09b8\u09cd\u0995"
    ],
    "name:hin_x_preferred":[
        "\u0924\u094d\u0930\u094b\u0907\u0924\u094d\u0938\u094d\u0915"
    ],
    "name:ind_x_preferred":[
        "Troitsk"
    ],
    "name:por_x_preferred":[
        "Troitsk"
    ],
    "name:rus_x_preferred":[
        "\u0422\u0440\u043e\u0438\u0446\u043a"
    ],
    "name:swe_x_preferred":[
        "Troitsk"
    ],
    "name:und_x_variant":[
        "Troitskoye"
    ],
    "name:urd_x_preferred":[
        "\u0679\u0631\u0648\u0627\u0626\u0633\u06a9"
    ],
    "wof:name":"Troitsk",
    "wof:placetype":"locality"
},
  "geometry": {"coordinates":[96.1816,55.9561],"type":"Point"}
}