{
  "type": "Feature",
  "properties": {
    "gn:admin1_code":"91",
    "gn:asciiname":"Troitsk",
    "gn:country_code":"RU",
    "gn:dem":362,
    "gn:feature_class":"P",
    "gn:feature_code":"PPL",
    "gn:name":"Troitsk",
    "gn:population":0,
    "gn:timezone":"Asia/Krasnoyarsk",
    "iso:country":"RU",
    "name:rus_x_preferred":[
        "\u0422\u0440\u043e\u0438\u0446\u043a"
    ],
    "name:und_x_variant":[
        "Troitskoye"
    ],
    "wof:name":"Troitsk",
    "wof:placetype":"locality"
},
  "geometry": {"coordinates":[96.1816,55.9561],"type":"Point"}
}