{
  "type": "Feature",
  "properties": {
    "gn:admin1_code":"73",
    "gn:asciiname":"Srednyaya Ushma",
    "gn:country_code":"RU",
    "gn:dem":141,
    "gn:feature_class":"P",
    "gn:feature_code":"PPL",
    "gn:name":"Srednyaya Ushma",
    "gn:population":0,
    "gn:timezone":"Europe/Moscow",
    "iso:country":"RU",
    "name:rus_x_preferred":[
        "\u0421\u0440\u0435\u0434\u043d\u044f\u044f \u0423\u0448\u043c\u0430"
    ],
    "wof:name":"Srednyaya Ushma",
    "wof:placetype":"locality"
},
  "geometry": {"coordinates":[50.1502,56.3198],"type":"Point"}
}