{
  "type": "Feature",
  "properties": {
    "gn:admin1_code":"70.0",
    "gn:asciiname":"Filimonovskaya",
    "gn:country_code":"RU",
    "gn:dem":214,
    "gn:feature_class":"P",
    "gn:feature_code":"PPL",
    "gn:name":"Filimonovskaya",
    "gn:population":0,
    "gn:timezone":"Europe/Moscow",
    "iso:country":"RU",
    "name:rus_x_preferred":[
        "\u0424\u0438\u043b\u0438\u043c\u043e\u043d\u043e\u0432\u0441\u043a\u0430\u044f"
    ],
    "name:und_x_variant":[
        "\u0424\u0438\u043b\u0438\u043c\u043e\u043d\u043e\u0432\u0441\u043a\u0430\u044f"
    ],
    "wof:name":"Filimonovskaya",
    "wof:placetype":"locality"
},
  "geometry": {"coordinates":[41.6579,45.1521],"type":"Point"}
}