{
  "type": "Feature",
  "properties": {
    "gn:admin1_code":"47",
    "gn:asciiname":"Trukhachevo",
    "gn:country_code":"RU",
    "gn:dem":217,
    "gn:feature_class":"P",
    "gn:feature_code":"PPL",
    "gn:name":"Trukhach\u00ebvo",
    "gn:population":0,
    "gn:timezone":"Europe/Moscow",
    "iso:country":"RU",
    "name:und_x_variant":[
        "Trukhach\u00ebva",
        "Trukhach\u00ebvo"
    ],
    "wof:name":"Trukhachevo",
    "wof:placetype":"locality"
},
  "geometry": {"coordinates":[37.65339,54.76886],"type":"Point"}
}