{
  "type": "Feature",
  "properties": {
    "gn:admin1_code":"40",
    "gn:asciiname":"Paderino",
    "gn:country_code":"RU",
    "gn:dem":134,
    "gn:feature_class":"P",
    "gn:feature_code":"PPL",
    "gn:name":"Paderino",
    "gn:population":0,
    "gn:timezone":"Asia/Yekaterinburg",
    "iso:country":"RU",
    "name:eng_x_preferred":[
        "Paderino"
    ],
    "name:nor_x_preferred":[
        "Paderino"
    ],
    "name:rus_x_preferred":[
        "\u041f\u0430\u0434\u0435\u0440\u0438\u043d\u043e"
    ],
    "wof:name":"Paderino",
    "wof:placetype":"locality"
},
  "geometry": {"coordinates":[62.9903,56.5389],"type":"Point"}
}