{
  "type": "Feature",
  "properties": {
    "gn:admin1_code":"84",
    "gn:asciiname":"Cherepashki",
    "gn:country_code":"RU",
    "gn:dem":-2,
    "gn:feature_class":"P",
    "gn:feature_code":"PPL",
    "gn:name":"Cherepashki",
    "gn:population":0,
    "gn:timezone":"Europe/Volgograd",
    "iso:country":"RU",
    "name:rus_x_preferred":[
        "\u0427\u0435\u0440\u0435\u043f\u0430\u0448\u043a\u0438"
    ],
    "wof:name":"Cherepashki",
    "wof:placetype":"locality"
},
  "geometry": {"coordinates":[45.02981,48.55042],"type":"Point"}
}