{
  "type": "Feature",
  "properties": {
    "gn:country":"RU",
    "gn:fcode":"PPL",
    "gn:pop":2243,
    "iso:country":"RU",
    "name:bul_x_preferred":[
        "\u0428\u0443\u0433\u0443\u0440\u043e\u0432\u043e"
    ],
    "name:che_x_preferred":[
        "\u0428\u0443\u0433\u0443\u0440\u043e\u0432\u043e"
    ],
    "name:dut_x_preferred":[
        "Shugurovo"
    ],
    "name:eng_x_preferred":[
        "Shugurovo"
    ],
    "name:nor_x_preferred":[
        "Sjugurovo"
    ],
    "name:rus_x_preferred":[
        "\u0428\u0443\u0433\u0443\u0440\u043e\u0432\u043e"
    ],
    "name:tat_x_preferred":[
        "\u0428\u04e9\u0433\u0435\u0440"
    ],
    "name:unk_x_variant":[
        "\u0428\u0443\u0433\u0443\u0440\u043e\u0432\u043e"
    ],
    "qs:name":"Shugurovo",
    "qs:name_adm0":"Russia",
    "qs:name_adm1":"Tatarstan Republic",
    "qs:photos_9r":0,
    "qs:photos_sr":0,
    "qs:placetype":"Town",
    "qs:pop_sr":"4",
    "wd:wordcount":400,
    "wof:name":"Shugurovo",
    "wof:placetype":"locality",
    "wof:population":2243
},
  "geometry": {"coordinates":[52.13265,54.50828],"type":"Point"}
}