{
  "type": "Feature",
  "properties": {
    "gn:country":"RU",
    "gn:fcode":"PPL",
    "gn:population":2243,
    "iso:country":"RU",
    "name:bul_x_preferred":[
        "\u0428\u0443\u0433\u0443\u0440\u043e\u0432\u043e"
    ],
    "name:cat_x_preferred":[
        "\u015e\u00f6ger"
    ],
    "name:ceb_x_preferred":[
        "Shugurovo"
    ],
    "name:ces_x_preferred":[
        "\u015e\u00f6ger"
    ],
    "name:che_x_preferred":[
        "\u0428\u0443\u0433\u0443\u0440\u043e\u0432\u043e"
    ],
    "name:dan_x_preferred":[
        "\u015e\u00f6ger"
    ],
    "name:deu_x_preferred":[
        "\u015e\u00f6ger"
    ],
    "name:eng_x_preferred":[
        "Shugurovo"
    ],
    "name:eng_x_variant":[
        "\u015e\u00f6ger"
    ],
    "name:fin_x_preferred":[
        "\u015e\u00f6ger"
    ],
    "name:fra_x_preferred":[
        "\u015e\u00f6ger"
    ],
    "name:hun_x_preferred":[
        "\u015e\u00f6ger"
    ],
    "name:ind_x_preferred":[
        "\u015e\u00f6ger"
    ],
    "name:ita_x_preferred":[
        "\u015e\u00f6ger"
    ],
    "name:lat_x_preferred":[
        "\u015e\u00f6ger"
    ],
    "name:nld_x_preferred":[
        "Shugurovo"
    ],
    "name:nld_x_variant":[
        "\u015e\u00f6ger"
    ],
    "name:nno_x_preferred":[
        "Sjugurovo"
    ],
    "name:nob_x_preferred":[
        "Sjugurovo"
    ],
    "name:nor_x_preferred":[
        "Sjugurovo"
    ],
    "name:pol_x_preferred":[
        "\u015e\u00f6ger"
    ],
    "name:por_x_preferred":[
        "\u015e\u00f6ger"
    ],
    "name:ron_x_preferred":[
        "\u015e\u00f6ger"
    ],
    "name:rus_x_preferred":[
        "\u0428\u0443\u0433\u0443\u0440\u043e\u0432\u043e"
    ],
    "name:spa_x_preferred":[
        "\u015e\u00f6ger"
    ],
    "name:sqi_x_preferred":[
        "Sugurovo"
    ],
    "name:swe_x_preferred":[
        "\u015e\u00f6ger"
    ],
    "name:tat_x_preferred":[
        "\u0428\u04e9\u0433\u0435\u0440"
    ],
    "name:vie_x_preferred":[
        "\u015e\u00f6ger"
    ],
    "qs:name":"Shugurovo",
    "qs:name_adm0":"Russia",
    "qs:name_adm1":"Tatarstan Republic",
    "qs:photos_9r":0,
    "qs:photos_sr":0,
    "qs:placetype":"Town",
    "qs:pop_sr":"4",
    "wd:wordcount":400,
    "wof:name":"Shugurovo",
    "wof:placetype":"locality",
    "wof:population":2243
},
  "geometry": {"coordinates":[52.13265,54.50828],"type":"Point"}
}