{
  "type": "Feature",
  "properties": {
    "gn:admin1_code":"33.0",
    "gn:asciiname":"Smetanovshchina",
    "gn:country_code":"RU",
    "gn:dem":142,
    "gn:feature_class":"P",
    "gn:feature_code":"PPL",
    "gn:name":"Smetanovshchina",
    "gn:population":0,
    "gn:timezone":"Europe/Kirov",
    "iso:country":"RU",
    "name:rus_x_preferred":[
        "\u0421\u043c\u0435\u0442\u0430\u043d\u043e\u0432\u0449\u0438\u043d\u0430"
    ],
    "name:und_x_variant":[
        "\u0421\u043c\u0435\u0442\u0430\u043d\u043e\u0432\u0449\u0438\u043d\u0430"
    ],
    "wof:name":"Smetanovshchina",
    "wof:placetype":"locality"
},
  "geometry": {"coordinates":[48.71366,58.24001],"type":"Point"}
}