{
  "type": "Feature",
  "properties": {
    "gn:admin1_code":"85",
    "gn:asciiname":"Zinovkovo",
    "gn:country_code":"RU",
    "gn:dem":135,
    "gn:feature_class":"P",
    "gn:feature_code":"PPL",
    "gn:name":"Zinovkovo",
    "gn:population":0,
    "gn:timezone":"Europe/Moscow",
    "iso:country":"RU",
    "name:rus_x_preferred":[
        "\u0417\u0438\u043d\u043e\u0432\u043a\u043e\u0432\u043e"
    ],
    "wof:name":"Zinovkovo",
    "wof:placetype":"locality"
},
  "geometry": {"coordinates":[46.2325,60.791],"type":"Point"}
}