{
  "type": "Feature",
  "properties": {
    "gn:admin1_code":"86",
    "gn:asciiname":"Tryapichnoye",
    "gn:cc2":"RU",
    "gn:country_code":"RU",
    "gn:dem":106,
    "gn:feature_class":"P",
    "gn:feature_code":"PPL",
    "gn:name":"Tryapichnoye",
    "gn:population":0,
    "gn:timezone":"Europe/Moscow",
    "iso:country":"RU",
    "name:und_x_variant":[
        "Tryapichkin",
        "Tryapichnoye"
    ],
    "wof:name":"Tryapichnoye",
    "wof:placetype":"locality"
},
  "geometry": {"coordinates":[41.14639,51.23056],"type":"Point"}
}