{
  "type": "Feature",
  "properties": {
    "gn:admin1_code":"69",
    "gn:asciiname":"Skachkovo",
    "gn:country_code":"RU",
    "gn:dem":199,
    "gn:feature_class":"P",
    "gn:feature_code":"PPL",
    "gn:name":"Skachkovo",
    "gn:population":0,
    "gn:timezone":"Europe/Moscow",
    "iso:country":"RU",
    "name:eng_x_preferred":[
        "Skachkova"
    ],
    "name:nor_x_preferred":[
        "Skatsjkovo"
    ],
    "name:rus_x_preferred":[
        "\u0421\u043a\u0430\u0447\u043a\u043e\u0432\u043e"
    ],
    "name:rus_x_variant":[
        "\u0421\u043a\u0430\u0447\u043a\u043e\u0432o"
    ],
    "name:und_x_variant":[
        "Skachkova",
        "Skachkovo"
    ],
    "wof:name":"Skachkovo",
    "wof:placetype":"locality"
},
  "geometry": {"coordinates":[32.7457,55.1426],"type":"Point"}
}