{
  "type": "Feature",
  "properties": {
    "gn:admin1_code":"13.0",
    "gn:asciiname":"Belaya Glinka",
    "gn:country_code":"RU",
    "gn:dem":438,
    "gn:feature_class":"P",
    "gn:feature_code":"PPL",
    "gn:name":"Belaya Glinka",
    "gn:population":0,
    "gn:timezone":"Asia/Yekaterinburg",
    "iso:country":"RU",
    "name:nor_x_preferred":[
        "Belaja Glinka"
    ],
    "name:rus_x_preferred":[
        "\u0411\u0435\u043b\u0430\u044f \u0413\u043b\u0438\u043d\u043a\u0430"
    ],
    "wof:name":"Belaya Glinka",
    "wof:placetype":"locality"
},
  "geometry": {"coordinates":[60.05122,53.04923],"type":"Point"}
}