{
  "type": "Feature",
  "properties": {
    "gn:admin1_code":"33",
    "gn:asciiname":"Sobolevo",
    "gn:country_code":"RU",
    "gn:dem":109,
    "gn:feature_class":"P",
    "gn:feature_code":"PPL",
    "gn:name":"Sobol\u00ebvo",
    "gn:population":0,
    "gn:timezone":"Europe/Kirov",
    "iso:country":"RU",
    "name:rus_x_preferred":[
        "\u0421\u043e\u0431\u043e\u043b\u0451\u0432\u043e"
    ],
    "name:und_x_variant":[
        "Sobol\u00ebvo"
    ],
    "wof:name":"Sobolevo",
    "wof:placetype":"locality"
},
  "geometry": {"coordinates":[46.94794,56.95216],"type":"Point"}
}