{
  "type": "Feature",
  "properties": {
    "gn:admin1_code":"90.0",
    "gn:asciiname":"Borovkovo",
    "gn:country_code":"RU",
    "gn:dem":176,
    "gn:feature_class":"P",
    "gn:feature_code":"PPL",
    "gn:name":"Borovkovo",
    "gn:population":0,
    "gn:timezone":"Asia/Yekaterinburg",
    "iso:country":"RU",
    "name:che_x_preferred":[
        "\u0411\u043e\u0440\u043e\u0432\u043a\u043e\u0432\u043e"
    ],
    "name:rus_x_preferred":[
        "\u0411\u043e\u0440\u043e\u0432\u043a\u043e\u0432\u043e"
    ],
    "wof:name":"Borovkovo",
    "wof:placetype":"locality"
},
  "geometry": {"coordinates":[56.5492,58.184],"type":"Point"}
}