{
  "type": "Feature",
  "properties": {
    "gn:admin1_code":"49",
    "gn:asciiname":"Ponchozero",
    "gn:country_code":"RU",
    "gn:dem":52,
    "gn:feature_class":"P",
    "gn:feature_code":"PPL",
    "gn:name":"Ponchozero",
    "gn:population":0,
    "gn:timezone":"Europe/Moscow",
    "iso:country":"RU",
    "name:rus_x_preferred":[
        "\u041f\u043e\u043d\u0447\u043e\u0437\u0435\u0440\u043e"
    ],
    "name:und_x_variant":[
        "\u041f\u043e\u043d\u0447\u043e\u0437\u0435\u0440\u043e"
    ],
    "wof:name":"Ponchozero",
    "wof:placetype":"locality"
},
  "geometry": {"coordinates":[34.29616,66.85151999999999],"type":"Point"}
}