{
  "type": "Feature",
  "properties": {
    "gn:admin1_code":"91",
    "gn:asciiname":"Predgornyy",
    "gn:country_code":"RU",
    "gn:dem":350,
    "gn:feature_class":"P",
    "gn:feature_code":"PPL",
    "gn:name":"Predgornyy",
    "gn:population":0,
    "gn:timezone":"Asia/Krasnoyarsk",
    "iso:country":"RU",
    "name:rus_x_preferred":[
        "\u041f\u0440\u0435\u0434\u0433\u043e\u0440\u043d\u044b\u0439"
    ],
    "wof:name":"Predgornyy",
    "wof:placetype":"locality"
},
  "geometry": {"coordinates":[90.25611000000001,55.64],"type":"Point"}
}