{
  "type": "Feature",
  "properties": {
    "gn:admin1_code":"73",
    "gn:asciiname":"Kadrali",
    "gn:country_code":"RU",
    "gn:dem":106,
    "gn:feature_class":"P",
    "gn:feature_code":"PPL",
    "gn:name":"Kadrali",
    "gn:population":0,
    "gn:timezone":"Europe/Moscow",
    "iso:country":"RU",
    "name:rus_x_preferred":[
        "\u041a\u0430\u0434\u0440\u0430\u043b\u0438"
    ],
    "wof:name":"Kadrali",
    "wof:placetype":"locality"
},
  "geometry": {"coordinates":[52.78674,56.33566],"type":"Point"}
}