{
  "type": "Feature",
  "properties": {
    "gn:admin1_code":"33.0",
    "gn:asciiname":"Smetany",
    "gn:country_code":"RU",
    "gn:dem":147,
    "gn:feature_class":"P",
    "gn:feature_code":"PPL",
    "gn:name":"Smetany",
    "gn:population":0,
    "gn:timezone":"Europe/Kirov",
    "iso:country":"RU",
    "name:rus_x_preferred":[
        "\u0421\u043c\u0435\u0442\u0430\u043d\u044b"
    ],
    "name:und_x_variant":[
        "\u0421\u043c\u0435\u0442\u0430\u043d\u044b"
    ],
    "wof:name":"Smetany",
    "wof:placetype":"locality"
},
  "geometry": {"coordinates":[48.17278,58.24861],"type":"Point"}
}