{
  "type": "Feature",
  "properties": {
    "gn:admin1_code":"61",
    "gn:asciiname":"Mirgorodskiy",
    "gn:country_code":"RU",
    "gn:dem":74,
    "gn:feature_class":"P",
    "gn:feature_code":"PPL",
    "gn:name":"Mirgorodskiy",
    "gn:population":0,
    "gn:timezone":"Europe/Moscow",
    "iso:country":"RU",
    "name:rus_x_preferred":[
        "\u041c\u0438\u0440\u0433\u043e\u0440\u043e\u0434\u0441\u043a\u0438\u0439"
    ],
    "wof:name":"Mirgorodskiy",
    "wof:placetype":"locality"
},
  "geometry": {"coordinates":[40.93266,48.91535],"type":"Point"}
}