{
  "type": "Feature",
  "properties": {
    "gn:admin1_code":"90",
    "gn:asciiname":"Larichi",
    "gn:country_code":"RU",
    "gn:dem":188,
    "gn:feature_class":"P",
    "gn:feature_code":"PPL",
    "gn:name":"Larichi",
    "gn:population":0,
    "gn:timezone":"Asia/Yekaterinburg",
    "iso:country":"RU",
    "name:rus_x_preferred":[
        "\u041b\u0430\u0440\u0438\u0447\u0438"
    ],
    "name:und_x_variant":[
        "\u041b\u0430\u0440\u0438\u0447\u0438"
    ],
    "wof:name":"Larichi",
    "wof:placetype":"locality"
},
  "geometry": {"coordinates":[54.7444,58.54486],"type":"Point"}
}