{
  "type": "Feature",
  "properties": {
    "gn:admin1_code":"60",
    "gn:asciiname":"Apros'yevo",
    "gn:country_code":"RU",
    "gn:dem":74,
    "gn:feature_class":"P",
    "gn:feature_code":"PPL",
    "gn:name":"Apros\u2019yevo",
    "gn:population":0,
    "gn:timezone":"Europe/Moscow",
    "iso:country":"RU",
    "name:rus_x_preferred":[
        "\u0410\u043f\u0440\u043e\u0441\u044c\u0435\u0432\u043e"
    ],
    "name:und_x_variant":[
        "Apros\u2019yevo"
    ],
    "wof:name":"Apros'yevo",
    "wof:placetype":"locality"
},
  "geometry": {"coordinates":[28.56141,57.57625],"type":"Point"}
}