{
  "type": "Feature",
  "properties": {
    "gn:admin1_code":"88",
    "gn:asciiname":"Sukharevo",
    "gn:country_code":"RU",
    "gn:dem":113,
    "gn:feature_class":"P",
    "gn:feature_code":"PPL",
    "gn:name":"Sukhar\u00ebvo",
    "gn:population":0,
    "gn:timezone":"Europe/Moscow",
    "iso:country":"RU",
    "name:rus_x_preferred":[
        "\u0421\u0443\u0445\u0430\u0440\u0451\u0432\u043e"
    ],
    "name:und_x_variant":[
        "Sukhar\u00ebvo"
    ],
    "wof:name":"Sukharevo",
    "wof:placetype":"locality"
},
  "geometry": {"coordinates":[39.92534000000001,57.86644],"type":"Point"}
}