{
  "type": "Feature",
  "properties": {
    "gn:admin1_code":"60",
    "gn:asciiname":"Kosarovo",
    "gn:country_code":"RU",
    "gn:dem":165,
    "gn:feature_class":"P",
    "gn:feature_code":"PPL",
    "gn:name":"Kosarovo",
    "gn:population":0,
    "gn:timezone":"Europe/Moscow",
    "iso:country":"RU",
    "name:rus_x_preferred":[
        "\u041a\u043e\u0441\u0430\u0440\u043e\u0432\u043e"
    ],
    "wof:name":"Kosarovo",
    "wof:placetype":"locality"
},
  "geometry": {"coordinates":[29.129,56.8434],"type":"Point"}
}