{
  "type": "Feature",
  "properties": {
    "gn:admin1_code":"62",
    "gn:asciiname":"Pechernikovskiye Vyselki",
    "gn:country_code":"RU",
    "gn:dem":139,
    "gn:feature_class":"P",
    "gn:feature_code":"PPL",
    "gn:name":"Pechernikovskiye Vyselki",
    "gn:population":0,
    "gn:timezone":"Europe/Moscow",
    "iso:country":"RU",
    "name:eng_x_preferred":[
        "Pechernikovskiye Vyselki"
    ],
    "name:nor_x_preferred":[
        "Petsjernikovskije Vyselki"
    ],
    "name:rus_x_preferred":[
        "\u041f\u0435\u0447\u0435\u0440\u043d\u0438\u043a\u043e\u0432\u0441\u043a\u0438\u0435 \u0412\u044b\u0441\u0435\u043b\u043a\u0438"
    ],
    "name:und_x_variant":[
        "\u041f\u0435\u0447\u0435\u0440\u043d\u0438\u043a\u043e\u0432\u0441\u043a\u0438\u0435 \u0412\u044b\u0441\u0435\u043b\u043a\u0438",
        "Pechernikovskiye Vyselki"
    ],
    "wof:name":"Pechernikovskiye Vyselki",
    "wof:placetype":"locality"
},
  "geometry": {"coordinates":[39.1568,54.1588],"type":"Point"}
}