{
  "type": "Feature",
  "properties": {
    "gn:admin1_code":"46.0",
    "gn:asciiname":"Avdalovo",
    "gn:country_code":"RU",
    "gn:dem":105,
    "gn:feature_class":"P",
    "gn:feature_code":"PPL",
    "gn:name":"Avdalovo",
    "gn:population":0,
    "gn:timezone":"Europe/Moscow",
    "iso:country":"RU",
    "name:nor_x_preferred":[
        "Avdalovo"
    ],
    "name:rus_x_preferred":[
        "\u0410\u0432\u0434\u0430\u043b\u043e\u0432\u043e"
    ],
    "wof:name":"Avdalovo",
    "wof:placetype":"locality"
},
  "geometry": {"coordinates":[42.5864,54.1405],"type":"Point"}
}