{
  "type": "Feature",
  "properties": {
    "gn:admin1_code":"69",
    "gn:asciiname":"Mishutino",
    "gn:country_code":"RU",
    "gn:dem":204,
    "gn:feature_class":"P",
    "gn:feature_code":"PPL",
    "gn:name":"Mishutino",
    "gn:population":0,
    "gn:timezone":"Europe/Moscow",
    "iso:country":"RU",
    "name:rus_x_preferred":[
        "\u041c\u0438\u0448\u0443\u0442\u0438\u043d\u043e"
    ],
    "name:und_x_variant":[
        "\u041c\u0438\u0448\u0443\u0442\u0438\u043d\u043e"
    ],
    "wof:name":"Mishutino",
    "wof:placetype":"locality"
},
  "geometry": {"coordinates":[33.11667,54.78333000000001],"type":"Point"}
}