{
  "type": "Feature",
  "properties": {
    "gn:admin1_code":"37",
    "gn:asciiname":"Nizkus'",
    "gn:country_code":"RU",
    "gn:dem":114,
    "gn:feature_class":"P",
    "gn:feature_code":"PPL",
    "gn:name":"Nizkus\u2019",
    "gn:population":0,
    "gn:timezone":"Europe/Moscow",
    "iso:country":"RU",
    "name:rus_x_preferred":[
        "\u041d\u0438\u0437\u043a\u0443\u0441\u044c"
    ],
    "name:und_x_variant":[
        "Nizkus\u2019"
    ],
    "wof:name":"Nizkus'",
    "wof:placetype":"locality"
},
  "geometry": {"coordinates":[43.02335,58.01069],"type":"Point"}
}