{
  "type": "Feature",
  "properties": {
    "gn:admin1_code":"25",
    "gn:asciiname":"Rechitsy",
    "gn:country_code":"RU",
    "gn:dem":189,
    "gn:feature_class":"P",
    "gn:feature_code":"PPL",
    "gn:name":"Rechitsy",
    "gn:population":0,
    "gn:timezone":"Europe/Moscow",
    "iso:country":"RU",
    "name:rus_x_preferred":[
        "\u0420\u0435\u0447\u0438\u0446\u044b"
    ],
    "wof:name":"Rechitsy",
    "wof:placetype":"locality"
},
  "geometry": {"coordinates":[35.13722,54.49528000000001],"type":"Point"}
}