{
  "type": "Feature",
  "properties": {
    "gn:admin1_code":"37.0",
    "gn:asciiname":"Vasilevo",
    "gn:country_code":"RU",
    "gn:dem":119,
    "gn:feature_class":"P",
    "gn:feature_code":"PPL",
    "gn:name":"Vasil\u00ebvo",
    "gn:population":0,
    "gn:timezone":"Europe/Moscow",
    "iso:country":"RU",
    "name:bel_x_preferred":[
        "\u0412\u0430\u0441\u0456\u043b\u0435\u0432\u0430"
    ],
    "name:ceb_x_preferred":[
        "Vasilevo"
    ],
    "name:heb_x_preferred":[
        "\u05d5\u05e1\u05d9\u05dc\u05d1\u05d5"
    ],
    "name:rus_x_preferred":[
        "\u0412\u0430\u0441\u0438\u043b\u0435\u0432\u043e"
    ],
    "name:srp_x_preferred":[
        "\u0412\u0430\u0441\u0438\u0459\u0435\u0432\u043e"
    ],
    "name:swe_x_preferred":[
        "Vasilevo"
    ],
    "name:ukr_x_preferred":[
        "\u0412\u0430\u0441\u0438\u043b\u0435\u0432\u043e"
    ],
    "wof:name":"Vasilevo",
    "wof:placetype":"locality"
},
  "geometry": {"coordinates":[42.17074,57.59574],"type":"Point"}
}