{
  "type": "Feature",
  "properties": {
    "gn:admin1_code":"4",
    "gn:asciiname":"Bayunovo",
    "gn:country_code":"RU",
    "gn:dem":214,
    "gn:feature_class":"P",
    "gn:feature_code":"PPL",
    "gn:name":"Bayunovo",
    "gn:population":0,
    "gn:timezone":"Asia/Barnaul",
    "iso:country":"RU",
    "name:nor_x_preferred":[
        "Bajunovo"
    ],
    "name:rus_x_preferred":[
        "\u0411\u0430\u044e\u043d\u043e\u0432\u043e"
    ],
    "name:und_x_variant":[
        "Baynovo",
        "Bayunovo"
    ],
    "wof:name":"Bayunovo",
    "wof:placetype":"locality"
},
  "geometry": {"coordinates":[84.30861,53.28417],"type":"Point"}
}