{
  "type": "Feature",
  "properties": {
    "gn:admin1_code":"8",
    "gn:asciiname":"Novosapashevo",
    "gn:country_code":"RU",
    "gn:dem":204,
    "gn:feature_class":"P",
    "gn:feature_code":"PPL",
    "gn:name":"Novosapashevo",
    "gn:population":0,
    "gn:timezone":"Asia/Yekaterinburg",
    "iso:country":"RU",
    "name:rus_x_preferred":[
        "\u041d\u043e\u0432\u043e\u0441\u0430\u043f\u0430\u0448\u0435\u0432\u043e"
    ],
    "name:und_x_variant":[
        "Sapashevo",
        "Novosapashevo"
    ],
    "wof:name":"Novosapashevo",
    "wof:placetype":"locality"
},
  "geometry": {"coordinates":[56.21334,52.83871],"type":"Point"}
}