{
  "type": "Feature",
  "properties": {
    "gn:admin1_code":"8",
    "gn:asciiname":"Saragulovo",
    "gn:country_code":"RU",
    "gn:dem":246,
    "gn:feature_class":"P",
    "gn:feature_code":"PPL",
    "gn:name":"Saragulovo",
    "gn:population":0,
    "gn:timezone":"Asia/Yekaterinburg",
    "iso:country":"RU",
    "name:rus_x_preferred":[
        "\u0421\u0430\u0440\u0430\u0433\u0443\u043b\u043e\u0432\u043e"
    ],
    "name:und_x_variant":[
        "Saragul",
        "Saragulovo"
    ],
    "wof:name":"Saragulovo",
    "wof:placetype":"locality"
},
  "geometry": {"coordinates":[58.5207,55.4978],"type":"Point"}
}