{
  "type": "Feature",
  "properties": {
    "gn:admin1_code":"53",
    "gn:asciiname":"Sharypino",
    "gn:country_code":"RU",
    "gn:dem":133,
    "gn:feature_class":"P",
    "gn:feature_code":"PPL",
    "gn:name":"Sharypino",
    "gn:population":0,
    "gn:timezone":"Asia/Novosibirsk",
    "iso:country":"RU",
    "name:rus_x_preferred":[
        "\u0428\u0430\u0440\u044b\u043f\u0438\u043d\u043e"
    ],
    "name:und_x_variant":[
        "\u0428\u0430\u0440\u044b\u043f\u0438\u043d\u043e"
    ],
    "wof:name":"Sharypino",
    "wof:placetype":"locality"
},
  "geometry": {"coordinates":[79.23333000000002,56.15],"type":"Point"}
}