{
  "type": "Feature",
  "properties": {
    "gn:admin1_code":"77.0",
    "gn:asciiname":"Bit'kovo",
    "gn:country_code":"RU",
    "gn:dem":169,
    "gn:feature_class":"P",
    "gn:feature_code":"PPL",
    "gn:name":"Bit\u2019kovo",
    "gn:population":0,
    "gn:timezone":"Europe/Moscow",
    "iso:country":"RU",
    "name:rus_x_preferred":[
        "\u0411\u0438\u0442\u044c\u043a\u043e\u0432\u043e"
    ],
    "name:und_x_variant":[
        "Bit\u2019kovo",
        "\u0411\u0438\u0442\u044c\u043a\u043e\u0432\u043e"
    ],
    "wof:name":"Bit'kovo",
    "wof:placetype":"locality"
},
  "geometry": {"coordinates":[35.10816,57.13087],"type":"Point"}
}