{
  "type": "Feature",
  "properties": {
    "gn:admin1_code":"57",
    "gn:asciiname":"Marovka",
    "gn:country_code":"RU",
    "gn:dem":160,
    "gn:feature_class":"P",
    "gn:feature_code":"PPL",
    "gn:name":"Marovka",
    "gn:population":0,
    "gn:timezone":"Europe/Moscow",
    "iso:country":"RU",
    "name:rus_x_preferred":[
        "\u041c\u0430\u0440\u043e\u0432\u043a\u0430"
    ],
    "wof:name":"Marovka",
    "wof:placetype":"locality"
},
  "geometry": {"coordinates":[45.12907,53.78077],"type":"Point"}
}