{
  "type": "Feature",
  "properties": {
    "gn:admin1_code":"13",
    "gn:asciiname":"Atkul'",
    "gn:country_code":"RU",
    "gn:dem":185,
    "gn:feature_class":"P",
    "gn:feature_code":"PPL",
    "gn:name":"Atkul\u2019",
    "gn:population":0,
    "gn:timezone":"Asia/Yekaterinburg",
    "iso:country":"RU",
    "name:eng_x_preferred":[
        "Atkul'"
    ],
    "name:nor_x_preferred":[
        "Atkul"
    ],
    "name:rus_x_preferred":[
        "\u0410\u0442\u043a\u0443\u043b\u044c"
    ],
    "name:und_x_variant":[
        "Atkul\u2019skiy",
        "\u0410\u0442\u043a\u0443\u043b\u044c",
        "Atkul\u2019"
    ],
    "wof:name":"Atkul'",
    "wof:placetype":"locality"
},
  "geometry": {"coordinates":[61.893,54.8849],"type":"Point"}
}