{
  "type": "Feature",
  "properties": {
    "gn:admin1_code":"80.0",
    "gn:asciiname":"Korkayag",
    "gn:country_code":"RU",
    "gn:dem":180,
    "gn:feature_class":"P",
    "gn:feature_code":"PPL",
    "gn:name":"Korkayag",
    "gn:population":0,
    "gn:timezone":"Europe/Samara",
    "iso:country":"RU",
    "name:rus_x_preferred":[
        "\u041a\u043e\u0440\u043a\u0430\u044f\u0433"
    ],
    "wof:name":"Korkayag",
    "wof:placetype":"locality"
},
  "geometry": {"coordinates":[53.3742,57.8973],"type":"Point"}
}