{
  "type": "Feature",
  "properties": {
    "gn:admin1_code":"88",
    "gn:asciiname":"Cherelisino",
    "gn:country_code":"RU",
    "gn:dem":129,
    "gn:feature_class":"P",
    "gn:feature_code":"PPL",
    "gn:name":"Cherelisino",
    "gn:population":0,
    "gn:timezone":"Europe/Moscow",
    "iso:country":"RU",
    "name:rus_x_preferred":[
        "\u0427\u0435\u0440\u0435\u043b\u0438\u0441\u0438\u043d\u043e"
    ],
    "wof:name":"Cherelisino",
    "wof:placetype":"locality"
},
  "geometry": {"coordinates":[39.73523,57.51888],"type":"Point"}
}