{
  "type": "Feature",
  "properties": {
    "gn:admin1_code":"20",
    "gn:asciiname":"Zaval'",
    "gn:country_code":"RU",
    "gn:dem":422,
    "gn:feature_class":"P",
    "gn:feature_code":"PPL",
    "gn:name":"Zaval\u2019",
    "gn:population":0,
    "gn:timezone":"Asia/Irkutsk",
    "iso:country":"RU",
    "name:eng_x_preferred":[
        "Zaval'"
    ],
    "name:nor_x_preferred":[
        "Zaval"
    ],
    "name:rus_x_preferred":[
        "\u0417\u0430\u0432\u0430\u043b\u044c"
    ],
    "name:und_x_variant":[
        "Zaval\u2019"
    ],
    "wof:name":"Zaval'",
    "wof:placetype":"locality"
},
  "geometry": {"coordinates":[102.0536,54.6838],"type":"Point"}
}