{
  "type": "Feature",
  "properties": {
    "gn:admin1_code":"63",
    "gn:asciiname":"Khaltang",
    "gn:country_code":"RU",
    "gn:dem":108,
    "gn:feature_class":"P",
    "gn:feature_code":"PPL",
    "gn:name":"Khaltang",
    "gn:population":0,
    "gn:timezone":"Asia/Vladivostok",
    "iso:country":"RU",
    "name:eng_x_preferred":[
        "Khaltang"
    ],
    "name:nor_x_preferred":[
        "Khaltang"
    ],
    "name:rus_x_preferred":[
        "\u0425\u0430\u043b\u0442\u0430\u043d\u0433"
    ],
    "name:und_x_variant":[
        "Khaptay"
    ],
    "wof:name":"Khaltang",
    "wof:placetype":"locality"
},
  "geometry": {"coordinates":[135.05260000000001,68.40262],"type":"Point"}
}