{
  "type": "Feature",
  "properties": {
    "gn:admin1_code":"6",
    "gn:asciiname":"Gorlichevskaya",
    "gn:country_code":"RU",
    "gn:dem":33,
    "gn:feature_class":"P",
    "gn:feature_code":"PPL",
    "gn:name":"Gorlichevskaya",
    "gn:population":0,
    "gn:timezone":"Europe/Moscow",
    "iso:country":"RU",
    "name:rus_x_preferred":[
        "\u0413\u043e\u0440\u043b\u0438\u0447\u0435\u0432\u0441\u043a\u0430\u044f"
    ],
    "name:und_x_variant":[
        "\u0413\u043e\u0440\u043b\u0438\u0447\u0435\u0432\u0441\u043a\u0430\u044f"
    ],
    "wof:name":"Gorlichevskaya",
    "wof:placetype":"locality"
},
  "geometry": {"coordinates":[41.61667,63.91667],"type":"Point"}
}