{
  "type": "Feature",
  "properties": {
    "gn:admin1_code":"24.0",
    "gn:asciiname":"Put' Lenina",
    "gn:country_code":"RU",
    "gn:dem":-8,
    "gn:feature_class":"P",
    "gn:feature_code":"PPL",
    "gn:name":"Put\u2019 Lenina",
    "gn:population":0,
    "gn:timezone":"Europe/Moscow",
    "iso:country":"RU",
    "wof:name":"Put' Lenina",
    "wof:placetype":"locality"
},
  "geometry": {"coordinates":[46.23528,46.62917],"type":"Point"}
}