{
  "type": "Feature",
  "properties": {
    "gn:admin1_code":"37.0",
    "gn:asciiname":"Shablovo",
    "gn:country_code":"RU",
    "gn:dem":157,
    "gn:feature_class":"P",
    "gn:feature_code":"PPL",
    "gn:name":"Shablovo",
    "gn:population":35,
    "gn:timezone":"Europe/Moscow",
    "iso:country":"RU",
    "wof:name":"Shablovo",
    "wof:placetype":"locality",
    "wof:population":35
},
  "geometry": {"coordinates":[44.14573,58.91648000000001],"type":"Point"}
}