{
  "type": "Feature",
  "properties": {
    "gn:admin1_code":"11",
    "gn:asciiname":"Tsaydam",
    "gn:country_code":"RU",
    "gn:dem":824,
    "gn:feature_class":"P",
    "gn:feature_code":"PPL",
    "gn:name":"Tsaydam",
    "gn:population":0,
    "gn:timezone":"Asia/Irkutsk",
    "iso:country":"RU",
    "wof:name":"Tsaydam",
    "wof:placetype":"locality"
},
  "geometry": {"coordinates":[106.84999999999999,50.98333],"type":"Point"}
}