{
  "type": "Feature",
  "properties": {
    "gn:admin1_code":"90.0",
    "gn:asciiname":"Talaya",
    "gn:country_code":"RU",
    "gn:dem":146,
    "gn:feature_class":"P",
    "gn:feature_code":"PPL",
    "gn:name":"Talaya",
    "gn:population":0,
    "gn:timezone":"Asia/Yekaterinburg",
    "iso:country":"RU",
    "name:bel_x_preferred":[
        "\u0422\u0430\u043b\u0430\u044f"
    ],
    "name:che_x_preferred":[
        "\u0422\u0430\u043b\u0430\u044f"
    ],
    "name:deu_x_preferred":[
        "Talaja"
    ],
    "name:hye_x_preferred":[
        "\u054f\u0561\u056c\u0561\u0575\u0561"
    ],
    "name:ita_x_preferred":[
        "Talaja"
    ],
    "name:pol_x_preferred":[
        "Ta\u0142aja"
    ],
    "name:rus_x_preferred":[
        "\u0422\u0430\u043b\u0430\u044f"
    ],
    "wof:name":"Talaya",
    "wof:placetype":"locality"
},
  "geometry": {"coordinates":[56.9036,58.3095],"type":"Point"}
}