{
  "type": "Feature",
  "properties": {
    "gn:admin1_code":"64",
    "gn:asciiname":"Noksi",
    "gn:cc2":"RU",
    "gn:country_code":"RU",
    "gn:dem":-9999,
    "gn:feature_class":"P",
    "gn:feature_code":"PPL",
    "gn:name":"Noksi",
    "gn:population":0,
    "gn:timezone":"Asia/Sakhalin",
    "iso:country":"RU",
    "name:rus_x_preferred":[
        "\u041d\u043e\u043a\u0441\u0438"
    ],
    "name:und_x_variant":[
        "Poksi",
        "Noksi"
    ],
    "wof:name":"Noksi",
    "wof:placetype":"locality"
},
  "geometry": {"coordinates":[141.80000000000001,52.65],"type":"Point"}
}