{
  "type": "Feature",
  "properties": {
    "gn:admin1_code":"6",
    "gn:asciiname":"Trubinskaya",
    "gn:country_code":"RU",
    "gn:dem":70,
    "gn:feature_class":"P",
    "gn:feature_code":"PPL",
    "gn:name":"Trubinskaya",
    "gn:population":0,
    "gn:timezone":"Europe/Moscow",
    "iso:country":"RU",
    "name:eng_x_preferred":[
        "Trubinskaya"
    ],
    "name:nor_x_preferred":[
        "Trubinskaja"
    ],
    "name:rus_x_preferred":[
        "\u0422\u0440\u0443\u0431\u0438\u043d\u0441\u043a\u0430\u044f"
    ],
    "wof:name":"Trubinskaya",
    "wof:placetype":"locality"
},
  "geometry": {"coordinates":[42.29444,61.74],"type":"Point"}
}