{
  "type": "Feature",
  "properties": {
    "gn:admin1_code":"40",
    "gn:asciiname":"Shuravino",
    "gn:country_code":"RU",
    "gn:dem":134,
    "gn:feature_class":"P",
    "gn:feature_code":"PPL",
    "gn:name":"Shuravino",
    "gn:population":0,
    "gn:timezone":"Asia/Yekaterinburg",
    "iso:country":"RU",
    "name:eng_x_preferred":[
        "Shuravino"
    ],
    "name:nor_x_preferred":[
        "Sjuravino"
    ],
    "name:rus_x_preferred":[
        "\u0428\u0443\u0440\u0430\u0432\u0438\u043d\u043e"
    ],
    "wof:name":"Shuravino",
    "wof:placetype":"locality"
},
  "geometry": {"coordinates":[64.51909999999999,56.4495],"type":"Point"}
}