{
  "type": "Feature",
  "properties": {
    "gn:admin1_code":"47",
    "gn:asciiname":"Kuvekino",
    "gn:country_code":"RU",
    "gn:dem":147,
    "gn:feature_class":"P",
    "gn:feature_code":"PPL",
    "gn:name":"Kuvekino",
    "gn:population":0,
    "gn:timezone":"Europe/Moscow",
    "iso:country":"RU",
    "name:rus_x_preferred":[
        "\u041a\u0443\u0432\u0435\u043d\u043a\u0438\u043d\u043e"
    ],
    "name:und_x_variant":[
        "Kuvenkino",
        "\u041a\u0443\u0432\u0435\u043d\u043a\u0438\u043d\u043e",
        "Kuvekino"
    ],
    "wof:name":"Kuvekino",
    "wof:placetype":"locality"
},
  "geometry": {"coordinates":[37.43139,55.49083],"type":"Point"}
}