{
  "type": "Feature",
  "properties": {
    "gn:admin1_code":"21.0",
    "gn:asciiname":"Perfil'yevo",
    "gn:country_code":"RU",
    "gn:dem":125,
    "gn:feature_class":"P",
    "gn:feature_code":"PPL",
    "gn:name":"Perfil\u2019yevo",
    "gn:population":0,
    "gn:timezone":"Europe/Moscow",
    "iso:country":"RU",
    "name:rus_x_preferred":[
        "\u041f\u0435\u0440\u0444\u0438\u043b\u044c\u0435\u0432\u043e"
    ],
    "name:und_x_variant":[
        "Perfil\u2019yevo"
    ],
    "wof:name":"Perfil'yevo",
    "wof:placetype":"locality"
},
  "geometry": {"coordinates":[42.35623,57.44235],"type":"Point"}
}