{
  "type": "Feature",
  "properties": {
    "gn:admin1_code":"16",
    "gn:asciiname":"Olukh-Shumshevashi",
    "gn:country_code":"RU",
    "gn:dem":120,
    "gn:feature_class":"P",
    "gn:feature_code":"PPL",
    "gn:name":"Olukh-Shumshevashi",
    "gn:population":0,
    "gn:timezone":"Europe/Moscow",
    "iso:country":"RU",
    "name:rus_x_preferred":[
        "\u041e\u043b\u0443\u0445-\u0428\u0443\u043c\u0448\u0435\u0432\u0430\u0448\u0438"
    ],
    "name:und_x_variant":[
        "\u041e\u043b\u0443\u0445-\u0428\u0443\u043c\u0448\u0435\u0432\u0430\u0448\u0438"
    ],
    "wof:name":"Olukh-Shumshevashi",
    "wof:placetype":"locality"
},
  "geometry": {"coordinates":[46.55,55.78333000000001],"type":"Point"}
}