{
  "type": "Feature",
  "properties": {
    "gn:admin1_code":"69",
    "gn:asciiname":"Podchesovo",
    "gn:country_code":"RU",
    "gn:dem":196,
    "gn:feature_class":"P",
    "gn:feature_code":"PPL",
    "gn:name":"Podchesovo",
    "gn:population":0,
    "gn:timezone":"Europe/Moscow",
    "iso:country":"RU",
    "name:rus_x_preferred":[
        "\u041f\u043e\u0434\u0447\u0435\u0441\u043e\u0432\u043e"
    ],
    "name:und_x_variant":[
        "\u041f\u043e\u0434\u0447\u0435\u0441\u043e\u0432\u043e"
    ],
    "wof:name":"Podchesovo",
    "wof:placetype":"locality"
},
  "geometry": {"coordinates":[30.96667,55.21666999999999],"type":"Point"}
}