{
  "type": "Feature",
  "properties": {
    "gn:admin1_code":"38.0",
    "gn:asciiname":"Chushka",
    "gn:country_code":"RU",
    "gn:dem":1,
    "gn:feature_class":"P",
    "gn:feature_code":"PPL",
    "gn:name":"Chushka",
    "gn:population":0,
    "gn:timezone":"Europe/Moscow",
    "iso:country":"RU",
    "name:aze_x_preferred":[
        "\u00c7u\u015fka dili"
    ],
    "name:deu_x_preferred":[
        "Tschuschka"
    ],
    "name:eng_x_preferred":[
        "Chushka"
    ],
    "name:nor_x_preferred":[
        "Tsjusjka"
    ],
    "name:rus_x_preferred":[
        "\u0427\u0443\u0448\u043a\u0430"
    ],
    "name:spa_x_preferred":[
        "Punta Chushka"
    ],
    "name:srp_x_preferred":[
        "\u0427\u0443\u0448\u043a\u0430 \u043a\u043e\u0441\u0430"
    ],
    "name:ukr_x_preferred":[
        "\u0427\u0443\u0448\u043a\u0430"
    ],
    "name:und_x_variant":[
        "Kosa Chushka",
        "Chushka-Port",
        "\u0427\u0443\u0448\u043a\u0430",
        "Chushka"
    ],
    "wof:name":"Chushka",
    "wof:placetype":"locality"
},
  "geometry": {"coordinates":[36.66279,45.33127],"type":"Point"}
}