{
  "type": "Feature",
  "properties": {
    "gn:admin1_code":"60",
    "gn:asciiname":"Kukharevo",
    "gn:country_code":"RU",
    "gn:dem":173,
    "gn:feature_class":"P",
    "gn:feature_code":"PPL",
    "gn:name":"Kukhar\u00ebvo",
    "gn:population":0,
    "gn:timezone":"Europe/Moscow",
    "iso:country":"RU",
    "name:rus_x_preferred":[
        "\u041a\u0443\u0445\u0430\u0440\u0451\u0432\u043e"
    ],
    "name:und_x_variant":[
        "Kukhar\u00ebvo",
        "\u041a\u0443\u0445\u0430\u0440\u0451\u0432\u043e"
    ],
    "wof:name":"Kukharevo",
    "wof:placetype":"locality"
},
  "geometry": {"coordinates":[29.9687,56.036],"type":"Point"}
}