{
  "type": "Feature",
  "properties": {
    "gn:admin1_code":"51",
    "gn:asciiname":"Zalivnaya Usad'ba",
    "gn:country_code":"RU",
    "gn:dem":95,
    "gn:feature_class":"P",
    "gn:feature_code":"PPL",
    "gn:name":"Zalivnaya Usad\u2019ba",
    "gn:population":0,
    "gn:timezone":"Europe/Moscow",
    "iso:country":"RU",
    "name:rus_x_preferred":[
        "\u0417\u0430\u043b\u0438\u0432\u043d\u0430\u044f \u0423\u0441\u0430\u0434\u044c\u0431\u0430"
    ],
    "name:und_x_variant":[
        "Zalivnaya Usad\u2019ba"
    ],
    "wof:name":"Zalivnaya Usad'ba",
    "wof:placetype":"locality"
},
  "geometry": {"coordinates":[45.7327,57.4424],"type":"Point"}
}