{
  "type": "Feature",
  "properties": {
    "gn:admin1_code":"9.0",
    "gn:asciiname":"Merkulovka",
    "gn:country_code":"RU",
    "gn:dem":228,
    "gn:feature_class":"P",
    "gn:feature_code":"PPL",
    "gn:name":"Merkulovka",
    "gn:population":0,
    "gn:timezone":"Europe/Moscow",
    "iso:country":"RU",
    "name:rus_x_preferred":[
        "\u041c\u0435\u0440\u043a\u0443\u043b\u043e\u0432\u043a\u0430"
    ],
    "wof:name":"Merkulovka",
    "wof:placetype":"locality"
},
  "geometry": {"coordinates":[37.00973,50.85532],"type":"Point"}
}