{
  "type": "Feature",
  "properties": {
    "gn:admin1_code":"71",
    "gn:asciiname":"Tyamkina",
    "gn:country_code":"RU",
    "gn:dem":110,
    "gn:feature_class":"P",
    "gn:feature_code":"PPL",
    "gn:name":"Tyamkina",
    "gn:population":0,
    "gn:timezone":"Asia/Yekaterinburg",
    "iso:country":"RU",
    "name:rus_x_preferred":[
        "\u0422\u044f\u043c\u043a\u0438\u043d\u0430"
    ],
    "wof:name":"Tyamkina",
    "wof:placetype":"locality"
},
  "geometry": {"coordinates":[64.60906999999999,57.15707],"type":"Point"}
}