{
  "type": "Feature",
  "properties": {
    "gn:admin1_code":"71",
    "gn:asciiname":"Zhuravleva",
    "gn:country_code":"RU",
    "gn:dem":84,
    "gn:feature_class":"P",
    "gn:feature_code":"PPL",
    "gn:name":"Zhuravl\u00ebva",
    "gn:population":0,
    "gn:timezone":"Asia/Yekaterinburg",
    "iso:country":"RU",
    "wof:name":"Zhuravleva",
    "wof:placetype":"locality"
},
  "geometry": {"coordinates":[64.11684,56.89742],"type":"Point"}
}