{
  "type": "Feature",
  "properties": {
    "gn:admin1_code":"33.0",
    "gn:asciiname":"Abramovo",
    "gn:country_code":"RU",
    "gn:dem":115,
    "gn:feature_class":"P",
    "gn:feature_code":"PPL",
    "gn:name":"Abramovo",
    "gn:population":0,
    "gn:timezone":"Europe/Kirov",
    "iso:country":"RU",
    "name:eng_x_preferred":[
        "Abramovo"
    ],
    "name:nor_x_preferred":[
        "Abramovo"
    ],
    "name:rus_x_preferred":[
        "\u0410\u0431\u0440\u0430\u043c\u043e\u0432\u043e"
    ],
    "wof:name":"Abramovo",
    "wof:placetype":"locality"
},
  "geometry": {"coordinates":[47.04457,57.15452],"type":"Point"}
}