{
  "type": "Feature",
  "properties": {
    "gn:admin1_code":"33",
    "gn:asciiname":"Strabykino",
    "gn:country_code":"RU",
    "gn:dem":81,
    "gn:feature_class":"P",
    "gn:feature_code":"PPL",
    "gn:name":"Strabykino",
    "gn:population":0,
    "gn:timezone":"Europe/Kirov",
    "iso:country":"RU",
    "name:rus_x_preferred":[
        "\u0421\u0442\u0440\u0430\u0431\u044b\u043a\u0438\u043d\u043e"
    ],
    "wof:name":"Strabykino",
    "wof:placetype":"locality"
},
  "geometry": {"coordinates":[50.0001,57.0442],"type":"Point"}
}