{
  "type": "Feature",
  "properties": {
    "gn:admin1_code":"77",
    "gn:asciiname":"Prokhorenki",
    "gn:country_code":"RU",
    "gn:dem":173,
    "gn:feature_class":"P",
    "gn:feature_code":"PPL",
    "gn:name":"Prokhorenki",
    "gn:population":0,
    "gn:timezone":"Europe/Moscow",
    "iso:country":"RU",
    "name:rus_x_preferred":[
        "\u041f\u0440\u043e\u0445\u043e\u0440\u0435\u043d\u043a\u0438"
    ],
    "name:und_x_variant":[
        "Prokhoreki",
        "Prokhorenki"
    ],
    "wof:name":"Prokhorenki",
    "wof:placetype":"locality"
},
  "geometry": {"coordinates":[32.19613,55.85816],"type":"Point"}
}