{
  "type": "Feature",
  "properties": {
    "gn:admin1_code":"64",
    "gn:asciiname":"Kurskoye",
    "gn:cc2":"RU",
    "gn:country_code":"RU",
    "gn:dem":58,
    "gn:feature_class":"P",
    "gn:feature_code":"PPL",
    "gn:name":"Kurskoye",
    "gn:population":0,
    "gn:timezone":"Asia/Sakhalin",
    "iso:country":"RU",
    "name:rus_x_preferred":[
        "\u041a\u0443\u0440\u0441\u043a\u043e\u0435"
    ],
    "name:und_x_variant":[
        "Susuya",
        "Krupskoy",
        "Suzuya",
        "Kurskoye",
        "\u041a\u0443\u0440\u0441\u043a\u043e\u0435"
    ],
    "wof:name":"Kurskoye",
    "wof:placetype":"locality"
},
  "geometry": {"coordinates":[142.68333000000001,47.05],"type":"Point"}
}