{
  "type": "Feature",
  "properties": {
    "gn:admin1_code":"23",
    "gn:asciiname":"Kochkino",
    "gn:country_code":"RU",
    "gn:dem":61,
    "gn:feature_class":"P",
    "gn:feature_code":"PPL",
    "gn:name":"Kochkino",
    "gn:population":0,
    "gn:timezone":"Europe/Kaliningrad",
    "iso:country":"RU",
    "name:che_x_preferred":[
        "\u041a\u043e\u0447\u043a\u0438\u043d\u043e"
    ],
    "name:rus_x_preferred":[
        "\u041a\u043e\u0447\u043a\u0438\u043d\u043e"
    ],
    "name:und_x_variant":[
        "\u041a\u043e\u0447\u043a\u0438\u043d\u043e"
    ],
    "wof:name":"Kochkino",
    "wof:placetype":"locality"
},
  "geometry": {"coordinates":[21.48148,54.34925],"type":"Point"}
}