{
  "type": "Feature",
  "properties": {
    "gn:admin1_code":"62",
    "gn:asciiname":"Voronezhskiye Otruba",
    "gn:country_code":"RU",
    "gn:dem":163,
    "gn:feature_class":"P",
    "gn:feature_code":"PPL",
    "gn:name":"Voronezhskiye Otruba",
    "gn:population":0,
    "gn:timezone":"Europe/Moscow",
    "iso:country":"RU",
    "wof:name":"Voronezhskiye Otruba",
    "wof:placetype":"locality"
},
  "geometry": {"coordinates":[40.57083,53.59889],"type":"Point"}
}