{
  "type": "Feature",
  "properties": {
    "gn:admin1_code":"76",
    "gn:asciiname":"Blagoveshchenskiy",
    "gn:country_code":"RU",
    "gn:dem":165,
    "gn:feature_class":"P",
    "gn:feature_code":"PPL",
    "gn:name":"Blagoveshchenskiy",
    "gn:population":0,
    "gn:timezone":"Europe/Moscow",
    "iso:country":"RU",
    "name:rus_x_preferred":[
        "\u0411\u043b\u0430\u0433\u043e\u0432\u0435\u0449\u0435\u043d\u0441\u043a\u0438\u0439"
    ],
    "wof:name":"Blagoveshchenskiy",
    "wof:placetype":"locality"
},
  "geometry": {"coordinates":[38.7679,54.0257],"type":"Point"}
}