{
  "type": "Feature",
  "properties": {
    "gn:admin1_code":"77",
    "gn:asciiname":"Sopot'",
    "gn:country_code":"RU",
    "gn:dem":186,
    "gn:feature_class":"P",
    "gn:feature_code":"PPL",
    "gn:name":"Sopot\u2019",
    "gn:population":0,
    "gn:timezone":"Europe/Moscow",
    "iso:country":"RU",
    "name:rus_x_preferred":[
        "\u0421\u043e\u043f\u043e\u0442\u044c"
    ],
    "name:und_x_variant":[
        "Sopoti",
        "Sopot\u2019"
    ],
    "wof:name":"Sopot'",
    "wof:placetype":"locality"
},
  "geometry": {"coordinates":[32.7026,55.8723],"type":"Point"}
}