{
  "type": "Feature",
  "properties": {
    "gn:country":"RU",
    "gn:fcode":"PPL",
    "gn:population":10360,
    "iso:country":"RU",
    "name:eng_x_preferred":[
        "Serafimovskiy"
    ],
    "name:nor_x_preferred":[
        "Serafimovskij"
    ],
    "name:rus_x_preferred":[
        "\u0421\u0435\u0440\u0430\u0444\u0438\u043c\u043e\u0432\u0441\u043a\u0438\u0439"
    ],
    "name:und_x_variant":[
        "Serafimovka"
    ],
    "qs:name":"Serafimovskiy",
    "qs:photos_9r":0,
    "qs:photos_sr":0,
    "qs:pop_sr":"6",
    "wof:name":"Serafimovskiy",
    "wof:placetype":"locality",
    "wof:population":10360
},
  "geometry": {"coordinates":[53.7964,54.42408],"type":"Point"}
}