{
  "type": "Feature",
  "properties": {
    "gn:admin1_code":"56",
    "gn:asciiname":"Obrutskoye",
    "gn:country_code":"RU",
    "gn:dem":217,
    "gn:feature_class":"P",
    "gn:feature_code":"PPL",
    "gn:name":"Obrutskoye",
    "gn:population":0,
    "gn:timezone":"Europe/Moscow",
    "iso:country":"RU",
    "name:rus_x_preferred":[
        "\u041e\u0431\u0440\u0443\u0446\u043a\u043e\u0435"
    ],
    "name:und_x_variant":[
        "\u041e\u0431\u0440\u0443\u0446\u043a\u043e\u0435"
    ],
    "wof:name":"Obrutskoye",
    "wof:placetype":"locality"
},
  "geometry": {"coordinates":[36.77157,52.63736],"type":"Point"}
}