{
  "type": "Feature",
  "properties": {
    "gn:admin1_code":"73",
    "gn:asciiname":"Studenets",
    "gn:country_code":"RU",
    "gn:dem":79,
    "gn:feature_class":"P",
    "gn:feature_code":"PPL",
    "gn:name":"Studenets",
    "gn:population":0,
    "gn:timezone":"Europe/Moscow",
    "iso:country":"RU",
    "name:rus_x_preferred":[
        "\u0421\u0442\u0443\u0434\u0435\u043d\u0435\u0446"
    ],
    "wof:name":"Studenets",
    "wof:placetype":"locality"
},
  "geometry": {"coordinates":[48.9867,55.7331],"type":"Point"}
}