{
  "type": "Feature",
  "properties": {
    "gn:admin1_code":"42.0",
    "gn:admin2_code":"472350",
    "gn:asciiname":"Buyanitsy",
    "gn:country_code":"RU",
    "gn:dem":152,
    "gn:feature_class":"P",
    "gn:feature_code":"PPL",
    "gn:name":"Buyanitsy",
    "gn:population":0,
    "gn:timezone":"Europe/Moscow",
    "iso:country":"RU",
    "name:nor_x_preferred":[
        "Bujanitsy"
    ],
    "name:rus_x_preferred":[
        "\u0411\u0443\u044f\u043d\u0438\u0446\u044b"
    ],
    "wof:name":"Buyanitsy",
    "wof:placetype":"locality"
},
  "geometry": {"coordinates":[29.20071,59.54844],"type":"Point"}
}