{
  "type": "Feature",
  "properties": {
    "gn:admin1_code":"60",
    "gn:asciiname":"Panikovitsi",
    "gn:country_code":"RU",
    "gn:dem":140,
    "gn:feature_class":"P",
    "gn:feature_code":"PPL",
    "gn:name":"Panikovitsi",
    "gn:population":0,
    "gn:timezone":"Europe/Moscow",
    "iso:country":"RU",
    "name:eng_x_preferred":[
        "Panikovitsi"
    ],
    "name:nor_x_preferred":[
        "Panikovitsji"
    ],
    "name:rus_x_preferred":[
        "\u041f\u0430\u043d\u0438\u043a\u043e\u0432\u0438\u0447\u0438"
    ],
    "name:rus_x_variant":[
        "\u041f\u0430\u043d\u0438\u043a\u043e\u0432\u0438\u0446\u0438"
    ],
    "name:und_x_variant":[
        "Pankjavitsa",
        "Pangevitsa",
        "Panikovitsi",
        "\u041f\u0430\u043d\u0438\u043a\u043e\u0432\u0438\u0446\u0438",
        "Panikovichi"
    ],
    "wof:name":"Panikovitsi",
    "wof:placetype":"locality"
},
  "geometry": {"coordinates":[27.56756,57.68917],"type":"Point"}
}