{
  "type": "Feature",
  "properties": {
    "gn:admin1_code":"63",
    "gn:asciiname":"Myakyari",
    "gn:cc2":"RU",
    "gn:country_code":"RU",
    "gn:dem":173,
    "gn:feature_class":"P",
    "gn:feature_code":"PPL",
    "gn:name":"Myakyari",
    "gn:population":0,
    "gn:timezone":"Asia/Yakutsk",
    "iso:country":"RU",
    "name:rus_x_preferred":[
        "\u041c\u044f\u043a\u044f\u0440\u0438"
    ],
    "name:und_x_variant":[
        "Myakyarim",
        "Myakyari"
    ],
    "wof:name":"Myakyari",
    "wof:placetype":"locality"
},
  "geometry": {"coordinates":[130.65000000000001,62.33333],"type":"Point"}
}