{
  "type": "Feature",
  "properties": {
    "gn:admin1_code":"9",
    "gn:asciiname":"Malinovo",
    "gn:country_code":"RU",
    "gn:dem":197,
    "gn:feature_class":"P",
    "gn:feature_code":"PPL",
    "gn:name":"Malinovo",
    "gn:population":0,
    "gn:timezone":"Europe/Moscow",
    "iso:country":"RU",
    "name:eus_x_preferred":[
        "Malinovo"
    ],
    "name:fra_x_preferred":[
        "Malinovo"
    ],
    "name:lit_x_preferred":[
        "Malinovas"
    ],
    "name:rus_x_preferred":[
        "\u041c\u0430\u043b\u0438\u043d\u043e\u0432\u043e"
    ],
    "wof:name":"Malinovo",
    "wof:placetype":"locality"
},
  "geometry": {"coordinates":[38.4173,50.9658],"type":"Point"}
}