{
  "type": "Feature",
  "properties": {
    "gn:admin1_code":"78",
    "gn:asciiname":"Zinovo",
    "gn:country_code":"RU",
    "gn:dem":66,
    "gn:feature_class":"P",
    "gn:feature_code":"PPL",
    "gn:name":"Zinovo",
    "gn:population":0,
    "gn:timezone":"Asia/Yekaterinburg",
    "iso:country":"RU",
    "name:eng_x_preferred":[
        "Zinovo"
    ],
    "name:nor_x_preferred":[
        "Zinovo"
    ],
    "name:rus_x_preferred":[
        "\u0417\u0438\u043d\u043e\u0432\u043e"
    ],
    "wof:name":"Zinovo",
    "wof:placetype":"locality"
},
  "geometry": {"coordinates":[66.13079999999999,56.64294],"type":"Point"}
}