{
  "type": "Feature",
  "properties": {
    "gn:admin1_code":"65",
    "gn:asciiname":"Malaya Vyazovka",
    "gn:country_code":"RU",
    "gn:dem":112,
    "gn:feature_class":"P",
    "gn:feature_code":"PPL",
    "gn:name":"Malaya Vyazovka",
    "gn:population":0,
    "gn:timezone":"Europe/Samara",
    "iso:country":"RU",
    "name:rus_x_preferred":[
        "\u041c\u0430\u043b\u0430\u044f \u0412\u044f\u0437\u043e\u0432\u043a\u0430"
    ],
    "wof:name":"Malaya Vyazovka",
    "wof:placetype":"locality"
},
  "geometry": {"coordinates":[50.56264,52.63408],"type":"Point"}
}