{
  "type": "Feature",
  "properties": {
    "gn:admin1_code":"86.0",
    "gn:asciiname":"Tamilyanka",
    "gn:country_code":"RU",
    "gn:dem":124,
    "gn:feature_class":"P",
    "gn:feature_code":"PPL",
    "gn:name":"Tamilyanka",
    "gn:population":0,
    "gn:timezone":"Europe/Moscow",
    "iso:country":"RU",
    "name:rus_x_preferred":[
        "\u0422\u0430\u043c\u0438\u043b\u044f\u043d\u043a\u0430"
    ],
    "wof:name":"Tamilyanka",
    "wof:placetype":"locality"
},
  "geometry": {"coordinates":[40.49278,49.64028],"type":"Point"}
}