{
  "type": "Feature",
  "properties": {
    "gn:admin1_code":"81.0",
    "gn:asciiname":"Aksaur",
    "gn:country_code":"RU",
    "gn:dem":164,
    "gn:feature_class":"P",
    "gn:feature_code":"PPL",
    "gn:name":"Aksaur",
    "gn:population":0,
    "gn:timezone":"Europe/Ulyanovsk",
    "iso:country":"RU",
    "name:eng_x_preferred":[
        "Aksaur"
    ],
    "name:nor_x_preferred":[
        "Aksaur"
    ],
    "name:rus_x_preferred":[
        "\u0410\u043a\u0441\u0430\u0443\u0440"
    ],
    "wof:name":"Aksaur",
    "wof:placetype":"locality"
},
  "geometry": {"coordinates":[46.10667,54.06359000000001],"type":"Point"}
}