{
  "type": "Feature",
  "properties": {
    "gn:admin1_code":"65",
    "gn:asciiname":"Russkiy Baytugan",
    "gn:country_code":"RU",
    "gn:dem":119,
    "gn:feature_class":"P",
    "gn:feature_code":"PPL",
    "gn:name":"Russkiy Baytugan",
    "gn:population":0,
    "gn:timezone":"Europe/Samara",
    "iso:country":"RU",
    "name:eng_x_preferred":[
        "Russkiy Baytugan"
    ],
    "name:nor_x_preferred":[
        "Russkij Bajtugan"
    ],
    "name:rus_x_preferred":[
        "\u0420\u0443\u0441\u0441\u043a\u0438\u0439 \u0411\u0430\u0439\u0442\u0443\u0433\u0430\u043d"
    ],
    "name:und_x_variant":[
        "Baytugan Russkiy"
    ],
    "wof:name":"Russkiy Baytugan",
    "wof:placetype":"locality"
},
  "geometry": {"coordinates":[52.26399,54.08914],"type":"Point"}
}