{
  "type": "Feature",
  "properties": {
    "gn:admin1_code":"85.0",
    "gn:asciiname":"Boyarskaya",
    "gn:country_code":"RU",
    "gn:dem":154,
    "gn:feature_class":"P",
    "gn:feature_code":"PPL",
    "gn:name":"Boyarskaya",
    "gn:population":0,
    "gn:timezone":"Europe/Moscow",
    "iso:country":"RU",
    "name:rus_x_preferred":[
        "\u0411\u043e\u044f\u0440\u0441\u043a\u0430\u044f"
    ],
    "name:und_x_variant":[
        "\u0411\u043e\u044f\u0440\u0441\u043a\u0430\u044f"
    ],
    "wof:name":"Boyarskaya",
    "wof:placetype":"locality"
},
  "geometry": {"coordinates":[36.71,59.8018],"type":"Point"}
}