{
  "type": "Feature",
  "properties": {
    "gn:admin1_code":"86.0",
    "gn:asciiname":"Chernavka",
    "gn:country_code":"RU",
    "gn:dem":156,
    "gn:feature_class":"P",
    "gn:feature_code":"PPL",
    "gn:name":"Chernavka",
    "gn:population":0,
    "gn:timezone":"Europe/Moscow",
    "iso:country":"RU",
    "name:eng_x_preferred":[
        "Chernavka"
    ],
    "name:nor_x_preferred":[
        "Tsjernavka"
    ],
    "name:rus_x_preferred":[
        "\u0427\u0435\u0440\u043d\u0430\u0432\u043a\u0430"
    ],
    "name:und_x_variant":[
        "Chernavskiy",
        "\u0427\u0435\u0440\u043d\u0430\u0432\u043a\u0430",
        "Chernavka"
    ],
    "wof:name":"Chernavka",
    "wof:placetype":"locality"
},
  "geometry": {"coordinates":[40.38806,51.69083],"type":"Point"}
}