{
  "type": "Feature",
  "properties": {
    "gn:admin1_code":"63",
    "gn:asciiname":"Orto-Kyuyel'",
    "gn:country_code":"RU",
    "gn:dem":199,
    "gn:feature_class":"P",
    "gn:feature_code":"PPL",
    "gn:name":"Orto-Kyuy\u00ebl\u2019",
    "gn:population":0,
    "gn:timezone":"Asia/Yakutsk",
    "iso:country":"RU",
    "name:eng_x_preferred":[
        "Orto-Kyuy\u00ebl'"
    ],
    "name:nor_x_preferred":[
        "Orto-Kjuel"
    ],
    "name:rus_x_preferred":[
        "\u041e\u0440\u0442\u043e-\u041a\u044e\u0435\u043b\u044c"
    ],
    "name:rus_x_variant":[
        "\u041e\u0440\u0442\u043e-\u041a\u044e\u0451\u043b\u044c"
    ],
    "name:und_x_variant":[
        "Orto-Kyuy\u00ebl\u2019"
    ],
    "wof:name":"Orto-Kyuyel'",
    "wof:placetype":"locality"
},
  "geometry": {"coordinates":[124.06667,63.43333000000001],"type":"Point"}
}