{
  "type": "Feature",
  "properties": {
    "gn:admin1_code":"63",
    "gn:asciiname":"Krestovskiy Lesouchastok",
    "gn:country_code":"RU",
    "gn:dem":185,
    "gn:feature_class":"P",
    "gn:feature_code":"PPL",
    "gn:name":"Krestovskiy Lesouchastok",
    "gn:population":0,
    "gn:timezone":"Asia/Yakutsk",
    "iso:country":"RU",
    "name:rus_x_preferred":[
        "\u041a\u0440\u0435\u0441\u0442\u043e\u0432\u0441\u043a\u0438\u0439 \u041b\u0435\u0441\u043e\u0443\u0447\u0430\u0441\u0442\u043e\u043a"
    ],
    "wof:name":"Krestovskiy Lesouchastok",
    "wof:placetype":"locality"
},
  "geometry": {"coordinates":[113.26694000000001,59.78389],"type":"Point"}
}