{
  "type": "Feature",
  "properties": {
    "gn:admin1_code":"41",
    "gn:asciiname":"Safronovka",
    "gn:country_code":"RU",
    "gn:dem":165,
    "gn:feature_class":"P",
    "gn:feature_code":"PPL",
    "gn:name":"Safronovka",
    "gn:population":0,
    "gn:timezone":"Europe/Moscow",
    "iso:country":"RU",
    "name:rus_x_preferred":[
        "\u0421\u0430\u0444\u0440\u043e\u043d\u043e\u0432\u043a\u0430"
    ],
    "name:und_x_variant":[
        "Safronovo",
        "Safronovka",
        "\u0421\u0430\u0444\u0440\u043e\u043d\u043e\u0432\u043a\u0430"
    ],
    "wof:name":"Safronovka",
    "wof:placetype":"locality"
},
  "geometry": {"coordinates":[34.8143,51.8163],"type":"Point"}
}