{
  "type": "Feature",
  "properties": {
    "iso:country":"RU",
    "name:rus_x_preferred":[
        "\u0412\u043e\u0441\u0442\u043e\u0447\u043d\u043e\u0435 \u0414\u0435\u0433\u0443\u043d\u0438\u043d\u043e"
    ],
    "wof:name":"Vostochnoye Degunino",
    "wof:placetype":"neighbourhood"
},
  "geometry": {"coordinates":[37.56038854363353,55.88207426148558],"type":"Point"}
}