{
  "type": "Feature",
  "properties": {
    "gn:admin1_code":"71",
    "gn:asciiname":"Krasnyy Langur",
    "gn:cc2":"RU",
    "gn:country_code":"RU",
    "gn:dem":108,
    "gn:feature_class":"P",
    "gn:feature_code":"PPL",
    "gn:name":"Krasnyy Langur",
    "gn:population":0,
    "gn:timezone":"Asia/Yekaterinburg",
    "iso:country":"RU",
    "name:eng_x_preferred":[
        "Krasnyy Langur"
    ],
    "name:nor_x_preferred":[
        "Kr.Langur"
    ],
    "name:rus_x_preferred":[
        "\u041a\u0440.\u041b\u0430\u043d\u0433\u0443\u0440"
    ],
    "name:rus_x_variant":[
        "\u041a\u0440\u0430\u0441\u043d\u044b\u0439 \u041b\u0430\u043d\u0433\u0443\u0440"
    ],
    "name:und_x_variant":[
        "Langur",
        "Krasnyy Langur",
        "\u041a\u0440\u0430\u0441\u043d\u044b\u0439 \u041b\u0430\u043d\u0433\u0443\u0440"
    ],
    "wof:name":"Krasnyy Langur",
    "wof:placetype":"locality"
},
  "geometry": {"coordinates":[60.71666999999999,60.11666999999999],"type":"Point"}
}