{
  "type": "Feature",
  "properties": {
    "gn:admin1_code":"55",
    "gn:asciiname":"Razvedka",
    "gn:country_code":"RU",
    "gn:dem":305,
    "gn:feature_class":"P",
    "gn:feature_code":"PPL",
    "gn:name":"Razvedka",
    "gn:population":0,
    "gn:timezone":"Asia/Yekaterinburg",
    "iso:country":"RU",
    "name:eng_x_preferred":[
        "Razvedka"
    ],
    "name:nor_x_preferred":[
        "Razvedka"
    ],
    "name:rus_x_preferred":[
        "\u0420\u0430\u0437\u0432\u0435\u0434\u043a\u0430"
    ],
    "name:und_x_variant":[
        "\u0420\u0430\u0437\u0432\u0435\u0434\u043a\u0430",
        "Razvedka"
    ],
    "wof:name":"Razvedka",
    "wof:placetype":"locality"
},
  "geometry": {"coordinates":[60.80028000000001,50.83972],"type":"Point"}
}