{
  "type": "Feature",
  "properties": {
    "gn:admin1_code":"59.0",
    "gn:asciiname":"Nerpa",
    "gn:country_code":"RU",
    "gn:dem":7,
    "gn:feature_class":"P",
    "gn:feature_code":"PPL",
    "gn:name":"Nerpa",
    "gn:population":0,
    "gn:timezone":"Asia/Vladivostok",
    "iso:country":"RU",
    "name:rus_x_preferred":[
        "\u041d\u0435\u0440\u043f\u0430"
    ],
    "name:und_x_variant":[
        "\u041d\u0435\u0440\u043f\u0430"
    ],
    "wof:name":"Nerpa",
    "wof:placetype":"locality"
},
  "geometry": {"coordinates":[131.43018000000001,42.8666],"type":"Point"}
}