{
  "type": "Feature",
  "properties": {
    "gn:admin1_code":"71",
    "gn:asciiname":"Potaskuyeva",
    "gn:country_code":"RU",
    "gn:dem":76,
    "gn:feature_class":"P",
    "gn:feature_code":"PPL",
    "gn:name":"Potaskuyeva",
    "gn:population":0,
    "gn:timezone":"Asia/Yekaterinburg",
    "iso:country":"RU",
    "name:eng_x_preferred":[
        "Potaskuyeva"
    ],
    "name:nor_x_preferred":[
        "Potaskujeva"
    ],
    "name:rus_x_preferred":[
        "\u041f\u043e\u0442\u0430\u0441\u043a\u0443\u0435\u0432\u0430"
    ],
    "name:und_x_variant":[
        "\u041f\u043e\u0442\u0430\u0441\u043a\u0443\u0435\u0432\u0430",
        "Potaskuyeva"
    ],
    "wof:name":"Potaskuyeva",
    "wof:placetype":"locality"
},
  "geometry": {"coordinates":[64.28236,56.84036],"type":"Point"}
}