{
  "type": "Feature",
  "properties": {
    "gn:admin1_code":"72",
    "gn:asciiname":"Vtoraya Pyatiletka",
    "gn:country_code":"RU",
    "gn:dem":160,
    "gn:feature_class":"P",
    "gn:feature_code":"PPL",
    "gn:name":"Vtoraya Pyatiletka",
    "gn:population":0,
    "gn:timezone":"Europe/Moscow",
    "iso:country":"RU",
    "name:rus_x_preferred":[
        "\u0412\u0442\u043e\u0440\u0430\u044f \u041f\u044f\u0442\u0438\u043b\u0435\u0442\u043a\u0430"
    ],
    "wof:name":"Vtoraya Pyatiletka",
    "wof:placetype":"locality"
},
  "geometry": {"coordinates":[40.4729,52.999],"type":"Point"}
}