{
  "type": "Feature",
  "properties": {
    "gn:admin1_code":"20",
    "gn:asciiname":"Verkhniy Ignay",
    "gn:country_code":"RU",
    "gn:dem":559,
    "gn:feature_class":"P",
    "gn:feature_code":"PPL",
    "gn:name":"Verkhniy Ignay",
    "gn:population":0,
    "gn:timezone":"Asia/Irkutsk",
    "iso:country":"RU",
    "wof:name":"Verkhniy Ignay",
    "wof:placetype":"locality"
},
  "geometry": {"coordinates":[101.41278,53.91694],"type":"Point"}
}