{
  "type": "Feature",
  "properties": {
    "gn:admin1_code":"13",
    "gn:asciiname":"Taktybay",
    "gn:country_code":"RU",
    "gn:dem":311,
    "gn:feature_class":"P",
    "gn:feature_code":"PPL",
    "gn:name":"Taktybay",
    "gn:population":0,
    "gn:timezone":"Asia/Yekaterinburg",
    "iso:country":"RU",
    "name:rus_x_preferred":[
        "\u0422\u0430\u043a\u0442\u044b\u0431\u0430\u0439"
    ],
    "wof:name":"Taktybay",
    "wof:placetype":"locality"
},
  "geometry": {"coordinates":[60.8422,54.9877],"type":"Point"}
}