{
  "type": "Feature",
  "properties": {
    "gn:admin1_code":"88",
    "gn:asciiname":"Semaksino",
    "gn:country_code":"RU",
    "gn:dem":124,
    "gn:feature_class":"P",
    "gn:feature_code":"PPL",
    "gn:name":"Semaksino",
    "gn:population":0,
    "gn:timezone":"Europe/Moscow",
    "iso:country":"RU",
    "name:rus_x_preferred":[
        "\u0421\u0435\u043c\u0430\u043a\u0441\u0438\u043d\u043e"
    ],
    "wof:name":"Semaksino",
    "wof:placetype":"locality"
},
  "geometry": {"coordinates":[38.19300000000001,57.7879],"type":"Point"}
}