{
  "type": "Feature",
  "properties": {
    "gn:admin1_code":"51.0",
    "gn:asciiname":"Dal'nepesochnaya",
    "gn:country_code":"RU",
    "gn:dem":180,
    "gn:feature_class":"P",
    "gn:feature_code":"PPL",
    "gn:name":"Dal\u2019nepesochnaya",
    "gn:population":0,
    "gn:timezone":"Europe/Moscow",
    "iso:country":"RU",
    "name:rus_x_preferred":[
        "\u0414\u0430\u043b\u044c\u043d\u0435\u043f\u0435\u0441\u043e\u0447\u043d\u0430\u044f"
    ],
    "name:und_x_variant":[
        "Dal\u2019ne-Pesochnoye",
        "Dal\u2019nepesochnaya",
        "\u0414\u0430\u043b\u044c\u043d\u0435\u043f\u0435\u0441\u043e\u0447\u043d\u0430\u044f"
    ],
    "wof:name":"Dal'nepesochnaya",
    "wof:placetype":"locality"
},
  "geometry": {"coordinates":[42.7261,55.1363],"type":"Point"}
}