{
  "type": "Feature",
  "properties": {
    "gn:admin1_code":"69",
    "gn:asciiname":"Orekhovo",
    "gn:country_code":"RU",
    "gn:dem":190,
    "gn:feature_class":"P",
    "gn:feature_code":"PPL",
    "gn:name":"Orekhovo",
    "gn:population":0,
    "gn:timezone":"Europe/Moscow",
    "iso:country":"RU",
    "name:ceb_x_preferred":[
        "Orekhovo"
    ],
    "name:fra_x_preferred":[
        "Orekhovo"
    ],
    "name:swe_x_preferred":[
        "Orekhovo"
    ],
    "wof:name":"Orekhovo",
    "wof:placetype":"locality"
},
  "geometry": {"coordinates":[32.22833,55.64417],"type":"Point"}
}