{
  "type": "Feature",
  "properties": {
    "gn:admin1_code":"52",
    "gn:asciiname":"Staraya Zhuravka",
    "gn:country_code":"RU",
    "gn:dem":89,
    "gn:feature_class":"P",
    "gn:feature_code":"PPL",
    "gn:name":"Staraya Zhuravka",
    "gn:population":0,
    "gn:timezone":"Europe/Moscow",
    "iso:country":"RU",
    "name:rus_x_preferred":[
        "\u0421\u0442\u0430\u0440\u0430\u044f \u0416\u0443\u0440\u0430\u0432\u043a\u0430"
    ],
    "wof:name":"Staraya Zhuravka",
    "wof:placetype":"locality"
},
  "geometry": {"coordinates":[30.75,57.48333],"type":"Point"}
}