{
  "type": "Feature",
  "properties": {
    "gn:admin1_code":"65",
    "gn:asciiname":"Kamennodol'sk",
    "gn:country_code":"RU",
    "gn:dem":178,
    "gn:feature_class":"P",
    "gn:feature_code":"PPL",
    "gn:name":"Kamennodol\u2019sk",
    "gn:population":0,
    "gn:timezone":"Europe/Samara",
    "iso:country":"RU",
    "name:rus_x_preferred":[
        "\u041a\u0430\u043c\u0435\u043d\u043d\u043e\u0434\u043e\u043b\u044c\u0441\u043a"
    ],
    "name:und_x_variant":[
        "Kamennodol\u2019sk"
    ],
    "wof:name":"Kamennodol'sk",
    "wof:placetype":"locality"
},
  "geometry": {"coordinates":[51.36600000000001,52.253],"type":"Point"}
}