{
  "type": "Feature",
  "properties": {
    "gn:admin1_code":"42.0",
    "gn:asciiname":"Ankhimovskaya",
    "gn:country_code":"RU",
    "gn:dem":102,
    "gn:feature_class":"P",
    "gn:feature_code":"PPL",
    "gn:name":"Ankhimovskaya",
    "gn:population":0,
    "gn:timezone":"Europe/Moscow",
    "iso:country":"RU",
    "name:nor_x_preferred":[
        "Ankhimovskaja"
    ],
    "name:rus_x_preferred":[
        "\u0410\u043d\u0445\u0438\u043c\u043e\u0432\u0441\u043a\u0430\u044f"
    ],
    "wof:name":"Ankhimovskaya",
    "wof:placetype":"locality"
},
  "geometry": {"coordinates":[34.41667,60.86666999999999],"type":"Point"}
}