{
  "type": "Feature",
  "properties": {
    "gn:admin1_code":"23",
    "gn:asciiname":"Yantarovka",
    "gn:country_code":"RU",
    "gn:dem":45,
    "gn:feature_class":"P",
    "gn:feature_code":"PPL",
    "gn:name":"Yantarovka",
    "gn:population":0,
    "gn:timezone":"Europe/Kaliningrad",
    "iso:country":"RU",
    "name:und_x_variant":[
        "Wangnicken",
        "Yantarovka"
    ],
    "wof:name":"Yantarovka",
    "wof:placetype":"locality"
},
  "geometry": {"coordinates":[20.00433,54.91103],"type":"Point"}
}