{
  "type": "Feature",
  "properties": {
    "gn:admin1_code":"46",
    "gn:asciiname":"Kirikleyevskiy Maydan",
    "gn:country_code":"RU",
    "gn:dem":202,
    "gn:feature_class":"P",
    "gn:feature_code":"PPL",
    "gn:name":"Kirikleyevskiy Maydan",
    "gn:population":0,
    "gn:timezone":"Europe/Moscow",
    "iso:country":"RU",
    "name:rus_x_preferred":[
        "\u041a\u0438\u0440\u0438\u043a\u043b\u0435\u0435\u0432\u0441\u043a\u0438\u0439 \u041c\u0430\u0439\u0434\u0430\u043d"
    ],
    "name:und_x_variant":[
        "Kirikleyskiy Maydan"
    ],
    "wof:name":"Kirikleyevskiy Maydan",
    "wof:placetype":"locality"
},
  "geometry": {"coordinates":[44.12534,53.77277],"type":"Point"}
}