{
  "type": "Feature",
  "properties": {
    "gn:admin1_code":"54",
    "gn:asciiname":"Omskiy",
    "gn:country_code":"RU",
    "gn:dem":127,
    "gn:feature_class":"P",
    "gn:feature_code":"PPL",
    "gn:name":"Omskiy",
    "gn:population":0,
    "gn:timezone":"Asia/Omsk",
    "iso:country":"RU",
    "name:eng_x_preferred":[
        "Omskiy"
    ],
    "name:nor_x_preferred":[
        "Omskij"
    ],
    "name:rus_x_preferred":[
        "\u041e\u043c\u0441\u043a\u0438\u0439"
    ],
    "name:und_x_variant":[
        "\u041e\u043c\u0441\u043a\u0438\u0439",
        "Omskiy"
    ],
    "wof:name":"Omskiy",
    "wof:placetype":"locality"
},
  "geometry": {"coordinates":[73.34690999999999,55.10402],"type":"Point"}
}