{
  "type": "Feature",
  "properties": {
    "gn:admin1_code":"86",
    "gn:asciiname":"Krasnyy Mayak",
    "gn:cc2":"RU",
    "gn:country_code":"RU",
    "gn:dem":167,
    "gn:feature_class":"P",
    "gn:feature_code":"PPL",
    "gn:name":"Krasnyy Mayak",
    "gn:population":0,
    "gn:timezone":"Europe/Moscow",
    "iso:country":"RU",
    "name:rus_x_preferred":[
        "\u041a\u0440\u0430\u0441\u043d\u044b\u0439 \u041c\u0430\u044f\u043a"
    ],
    "name:und_x_variant":[
        "Krasny-Mayak",
        "Krasnyy Mayak"
    ],
    "wof:name":"Krasnyy Mayak",
    "wof:placetype":"locality"
},
  "geometry": {"coordinates":[41.92083,51.43222],"type":"Point"}
}