{
  "type": "Feature",
  "properties": {
    "gn:admin1_code":"87",
    "gn:asciiname":"Ust'-Voykar",
    "gn:country_code":"RU",
    "gn:dem":1,
    "gn:feature_class":"P",
    "gn:feature_code":"PPL",
    "gn:name":"Ust\u2019-Voykar",
    "gn:population":0,
    "gn:timezone":"Asia/Yekaterinburg",
    "iso:country":"RU",
    "name:eng_x_preferred":[
        "Ust'-Voykar"
    ],
    "name:nor_x_preferred":[
        "Ust-Vojkary"
    ],
    "name:rus_x_preferred":[
        "\u0423\u0441\u0442\u044c-\u0412\u043e\u0439\u043a\u0430\u0440\u044b"
    ],
    "name:und_x_variant":[
        "Letnyy Ust\u2019-Voykar",
        "Zimniye Voykarskiye",
        "Ust\u2019-Voykar"
    ],
    "wof:name":"Ust'-Voykar",
    "wof:placetype":"locality"
},
  "geometry": {"coordinates":[64.61062,65.66525],"type":"Point"}
}