{
  "type": "Feature",
  "properties": {
    "gn:admin1_code":"86.0",
    "gn:asciiname":"Belousova Vershina",
    "gn:country_code":"RU",
    "gn:dem":213,
    "gn:feature_class":"P",
    "gn:feature_code":"PPL",
    "gn:name":"Belousova Vershina",
    "gn:population":0,
    "gn:timezone":"Europe/Moscow",
    "iso:country":"RU",
    "name:nor_x_preferred":[
        "Belousova Versjina"
    ],
    "name:rus_x_preferred":[
        "\u0411\u0435\u043b\u043e\u0443\u0441\u043e\u0432\u0430 \u0412\u0435\u0440\u0448\u0438\u043d\u0430"
    ],
    "name:und_x_variant":[
        "Chushkovo",
        "Belousova Vershina"
    ],
    "wof:name":"Belousova Vershina",
    "wof:placetype":"locality"
},
  "geometry": {"coordinates":[39.60056,50.69944],"type":"Point"}
}