{
  "type": "Feature",
  "properties": {
    "gn:admin1_code":"13",
    "gn:asciiname":"Surmenevskiy",
    "gn:country_code":"RU",
    "gn:dem":407,
    "gn:feature_class":"P",
    "gn:feature_code":"PPL",
    "gn:name":"Surmenevskiy",
    "gn:population":0,
    "gn:timezone":"Asia/Yekaterinburg",
    "iso:country":"RU",
    "name:eng_x_preferred":[
        "Surmenevskiy"
    ],
    "name:nor_x_preferred":[
        "Surmenevskij"
    ],
    "name:rus_x_preferred":[
        "\u0421\u0443\u0440\u043c\u0435\u043d\u0435\u0432\u0441\u043a\u0438\u0439"
    ],
    "name:und_x_variant":[
        "Surmenovskiy"
    ],
    "wof:name":"Surmenevskiy",
    "wof:placetype":"locality"
},
  "geometry": {"coordinates":[59.6849,54.0452],"type":"Point"}
}