{
  "type": "Feature",
  "properties": {
    "gn:admin1_code":"79",
    "gn:asciiname":"Chal-Kezhig",
    "gn:country_code":"RU",
    "gn:dem":787,
    "gn:feature_class":"P",
    "gn:feature_code":"PPL",
    "gn:name":"Chal-Kezhig",
    "gn:population":0,
    "gn:timezone":"Asia/Krasnoyarsk",
    "iso:country":"RU",
    "name:eng_x_preferred":[
        "Chal-Kezhig"
    ],
    "name:nor_x_preferred":[
        "Tsjal-Kezjig"
    ],
    "name:rus_x_preferred":[
        "\u0427\u0430\u043b-\u041a\u0435\u0436\u0438\u0433"
    ],
    "wof:name":"Chal-Kezhig",
    "wof:placetype":"locality"
},
  "geometry": {"coordinates":[93.90000000000001,51.33333],"type":"Point"}
}