{
  "type": "Feature",
  "properties": {
    "gn:admin1_code":"13",
    "gn:asciiname":"Deputatskiy",
    "gn:country_code":"RU",
    "gn:dem":281,
    "gn:feature_class":"P",
    "gn:feature_code":"PPL",
    "gn:name":"Deputatskiy",
    "gn:population":0,
    "gn:timezone":"Asia/Yekaterinburg",
    "iso:country":"RU",
    "name:rus_x_preferred":[
        "\u0414\u0435\u043f\u0443\u0442\u0430\u0442\u0441\u043a\u0438\u0439"
    ],
    "name:und_x_variant":[
        "\u0414\u0435\u043f\u0443\u0442\u0430\u0442\u0441\u043a\u0438\u0439"
    ],
    "wof:name":"Deputatskiy",
    "wof:placetype":"locality"
},
  "geometry": {"coordinates":[61.1278,54.8389],"type":"Point"}
}