{
  "type": "Feature",
  "properties": {
    "gn:admin1_code":"6.0",
    "gn:asciiname":"Bubnovskaya",
    "gn:country_code":"RU",
    "gn:dem":126,
    "gn:feature_class":"P",
    "gn:feature_code":"PPL",
    "gn:name":"Bubnovskaya",
    "gn:population":0,
    "gn:timezone":"Europe/Moscow",
    "iso:country":"RU",
    "name:rus_x_preferred":[
        "\u0411\u0443\u0431\u043d\u043e\u0432\u0441\u043a\u0430\u044f"
    ],
    "wof:name":"Bubnovskaya",
    "wof:placetype":"locality"
},
  "geometry": {"coordinates":[45.1759,62.4157],"type":"Point"}
}