{
  "type": "Feature",
  "properties": {
    "gn:admin1_code":"8",
    "gn:asciiname":"Novobel'skoye",
    "gn:country_code":"RU",
    "gn:dem":473,
    "gn:feature_class":"P",
    "gn:feature_code":"PPL",
    "gn:name":"Novobel\u2019skoye",
    "gn:population":0,
    "gn:timezone":"Asia/Yekaterinburg",
    "iso:country":"RU",
    "name:rus_x_preferred":[
        "\u041d\u043e\u0432\u043e\u0431\u0435\u043b\u044c\u0441\u043a\u043e\u0435"
    ],
    "name:und_x_variant":[
        "Novobel\u2019skiy",
        "Novobel\u2019skoye"
    ],
    "wof:name":"Novobel'skoye",
    "wof:placetype":"locality"
},
  "geometry": {"coordinates":[58.1719,53.8554],"type":"Point"}
}