{
  "type": "Feature",
  "properties": {
    "gn:admin1_code":"40",
    "gn:asciiname":"Kargapol'ye",
    "gn:country_code":"RU",
    "gn:dem":105,
    "gn:feature_class":"P",
    "gn:feature_code":"PPL",
    "gn:name":"Kargapol\u2019ye",
    "gn:population":0,
    "gn:timezone":"Asia/Yekaterinburg",
    "iso:country":"RU",
    "name:eng_x_preferred":[
        "Kargapol'ye"
    ],
    "name:nor_x_preferred":[
        "Kargapolje"
    ],
    "name:rus_x_preferred":[
        "\u041a\u0430\u0440\u0433\u0430\u043f\u043e\u043b\u044c\u0435"
    ],
    "name:und_x_variant":[
        "Kargapol\u2019ye"
    ],
    "wof:name":"Kargapol'ye",
    "wof:placetype":"locality"
},
  "geometry": {"coordinates":[64.21694000000001,55.86417],"type":"Point"}
}