{
  "type": "Feature",
  "properties": {
    "gn:admin1_code":"25",
    "gn:asciiname":"Kurbatovo",
    "gn:country_code":"RU",
    "gn:dem":204,
    "gn:feature_class":"P",
    "gn:feature_code":"PPL",
    "gn:name":"Kurbatovo",
    "gn:population":0,
    "gn:timezone":"Europe/Moscow",
    "iso:country":"RU",
    "name:rus_x_preferred":[
        "\u041a\u0443\u0440\u0431\u0430\u0440\u043e\u0432\u043e"
    ],
    "name:und_x_variant":[
        "Kurbarovo",
        "\u041a\u0443\u0440\u0431\u0430\u0440\u043e\u0432\u043e",
        "Kurbatovo"
    ],
    "wof:name":"Kurbatovo",
    "wof:placetype":"locality"
},
  "geometry": {"coordinates":[35.45177,54.34651],"type":"Point"}
}