{
  "type": "Feature",
  "properties": {
    "gn:admin1_code":"60",
    "gn:asciiname":"Shchepets",
    "gn:country_code":"RU",
    "gn:dem":45,
    "gn:feature_class":"P",
    "gn:feature_code":"PPL",
    "gn:name":"Shchepets",
    "gn:population":0,
    "gn:timezone":"Europe/Moscow",
    "iso:country":"RU",
    "name:rus_x_preferred":[
        "\u0429\u0435\u043f\u0435\u0446"
    ],
    "wof:name":"Shchepets",
    "wof:placetype":"locality"
},
  "geometry": {"coordinates":[28.1625,57.6672],"type":"Point"}
}