{
  "type": "Feature",
  "properties": {
    "gn:admin1_code":"88",
    "gn:asciiname":"Nikonovskoye",
    "gn:country_code":"RU",
    "gn:dem":151,
    "gn:feature_class":"P",
    "gn:feature_code":"PPL",
    "gn:name":"Nikonovskoye",
    "gn:population":0,
    "gn:timezone":"Europe/Moscow",
    "iso:country":"RU",
    "name:rus_x_preferred":[
        "\u041d\u0438\u043a\u043e\u043d\u043e\u0432\u0441\u043a\u043e\u0435"
    ],
    "wof:name":"Nikonovskoye",
    "wof:placetype":"locality"
},
  "geometry": {"coordinates":[39.38568,57.5403],"type":"Point"}
}