{
  "type": "Feature",
  "properties": {
    "gn:admin1_code":"55",
    "gn:asciiname":"Novovasil'yevka",
    "gn:country_code":"RU",
    "gn:dem":128,
    "gn:feature_class":"P",
    "gn:feature_code":"PPL",
    "gn:name":"Novovasil\u2019yevka",
    "gn:population":0,
    "gn:timezone":"Asia/Yekaterinburg",
    "iso:country":"RU",
    "name:rus_x_preferred":[
        "\u041d\u043e\u0432\u043e\u0432\u0430\u0441\u0438\u043b\u044c\u0435\u0432\u043a\u0430"
    ],
    "name:und_x_variant":[
        "Novo-Vasil\u2019yevskiy",
        "Novovasil\u2019yevka",
        "\u041d\u043e\u0432\u043e\u0432\u0430\u0441\u0438\u043b\u044c\u0435\u0432\u043a\u0430",
        "Proletarskaya"
    ],
    "wof:name":"Novovasil'yevka",
    "wof:placetype":"locality"
},
  "geometry": {"coordinates":[52.1809,52.10100000000001],"type":"Point"}
}