{
  "type": "Feature",
  "properties": {
    "gn:admin1_code":"60",
    "gn:asciiname":"Stekhny",
    "gn:country_code":"RU",
    "gn:dem":79,
    "gn:feature_class":"P",
    "gn:feature_code":"PPL",
    "gn:name":"Stekhny",
    "gn:population":0,
    "gn:timezone":"Europe/Moscow",
    "iso:country":"RU",
    "name:rus_x_preferred":[
        "\u0421\u0442\u0435\u0445\u043d\u044b"
    ],
    "wof:name":"Stekhny",
    "wof:placetype":"locality"
},
  "geometry": {"coordinates":[28.0271,57.12336],"type":"Point"}
}