{
  "type": "Feature",
  "properties": {
    "gn:admin1_code":"77",
    "gn:asciiname":"Senchukovo",
    "gn:country_code":"RU",
    "gn:dem":171,
    "gn:feature_class":"P",
    "gn:feature_code":"PPL",
    "gn:name":"Senchukovo",
    "gn:population":0,
    "gn:timezone":"Europe/Moscow",
    "iso:country":"RU",
    "name:rus_x_preferred":[
        "\u0421\u0435\u043d\u0447\u0443\u043a\u043e\u0432\u043e"
    ],
    "wof:name":"Senchukovo",
    "wof:placetype":"locality"
},
  "geometry": {"coordinates":[34.76237,56.67126999999999],"type":"Point"}
}