{
  "type": "Feature",
  "properties": {
    "gn:admin1_code":"63",
    "gn:asciiname":"Argakhtakh",
    "gn:country_code":"RU",
    "gn:dem":22,
    "gn:feature_class":"P",
    "gn:feature_code":"PPL",
    "gn:name":"Argakhtakh",
    "gn:population":0,
    "gn:timezone":"Asia/Magadan",
    "iso:country":"RU",
    "name:che_x_preferred":[
        "\u0410\u0440\u0433\u0430\u0445\u0442\u0430\u0445"
    ],
    "name:eng_x_preferred":[
        "Argakhtakh"
    ],
    "name:nor_x_preferred":[
        "Argakhtakh"
    ],
    "name:rus_x_preferred":[
        "\u0410\u0440\u0433\u0430\u0445\u0442\u0430\u0445"
    ],
    "name:und_x_variant":[
        "Zimov\u2019ye Argakhtakh",
        "Orlovo",
        "Yurta-Argakhtakh"
    ],
    "wof:name":"Argakhtakh",
    "wof:placetype":"locality"
},
  "geometry": {"coordinates":[153.37846999999999,68.44434],"type":"Point"}
}