{
  "type": "Feature",
  "properties": {
    "gn:admin1_code":"88",
    "gn:asciiname":"Borisovka",
    "gn:country_code":"RU",
    "gn:dem":166,
    "gn:feature_class":"P",
    "gn:feature_code":"PPL",
    "gn:name":"Borisovka",
    "gn:population":0,
    "gn:timezone":"Europe/Moscow",
    "iso:country":"RU",
    "name:lav_x_preferred":[
        "Borisovka"
    ],
    "name:rus_x_preferred":[
        "\u0411\u043e\u0440\u0438\u0441\u043e\u0432\u043a\u0430"
    ],
    "wof:name":"Borisovka",
    "wof:placetype":"locality"
},
  "geometry": {"coordinates":[37.5383,58.2284],"type":"Point"}
}