{
  "type": "Feature",
  "properties": {
    "gn:admin1_code":"55",
    "gn:asciiname":"Ruzheyevka",
    "gn:country_code":"RU",
    "gn:dem":187,
    "gn:feature_class":"P",
    "gn:feature_code":"PPL",
    "gn:name":"Ruzheyevka",
    "gn:population":0,
    "gn:timezone":"Asia/Yekaterinburg",
    "iso:country":"RU",
    "name:rus_x_preferred":[
        "\u0420\u0443\u0436\u0435\u0435\u0432\u043a\u0430"
    ],
    "wof:name":"Ruzheyevka",
    "wof:placetype":"locality"
},
  "geometry": {"coordinates":[52.7478,54.2904],"type":"Point"}
}