{
  "type": "Feature",
  "properties": {
    "gn:admin1_code":"8",
    "gn:asciiname":"Novoyaushevo",
    "gn:country_code":"RU",
    "gn:dem":204,
    "gn:feature_class":"P",
    "gn:feature_code":"PPL",
    "gn:name":"Novoyaushevo",
    "gn:population":0,
    "gn:timezone":"Asia/Yekaterinburg",
    "iso:country":"RU",
    "name:rus_x_preferred":[
        "\u041d\u043e\u0432\u043e\u044f\u0443\u0448\u0435\u0432\u043e"
    ],
    "wof:name":"Novoyaushevo",
    "wof:placetype":"locality"
},
  "geometry": {"coordinates":[58.375,55.71611],"type":"Point"}
}