{
  "type": "Feature",
  "properties": {
    "gn:admin1_code":"51",
    "gn:asciiname":"Duplyaki",
    "gn:country_code":"RU",
    "gn:dem":159,
    "gn:feature_class":"P",
    "gn:feature_code":"PPL",
    "gn:name":"Duplyaki",
    "gn:population":0,
    "gn:timezone":"Europe/Moscow",
    "iso:country":"RU",
    "name:rus_x_preferred":[
        "\u0414\u0443\u043f\u043b\u044f\u043a\u0438"
    ],
    "wof:name":"Duplyaki",
    "wof:placetype":"locality"
},
  "geometry": {"coordinates":[47.1118,57.6646],"type":"Point"}
}