{
  "type": "Feature",
  "properties": {
    "gn:admin1_code":"73",
    "gn:asciiname":"Tashkirmen'",
    "gn:country_code":"RU",
    "gn:dem":68,
    "gn:feature_class":"P",
    "gn:feature_code":"PPL",
    "gn:name":"Tashkirmen\u2019",
    "gn:population":0,
    "gn:timezone":"Europe/Moscow",
    "iso:country":"RU",
    "name:eng_x_preferred":[
        "Tashkirmen'"
    ],
    "name:nor_x_preferred":[
        "Tasjkirmen"
    ],
    "name:rus_x_preferred":[
        "\u0422\u0430\u0448\u043a\u0438\u0440\u043c\u0435\u043d\u044c"
    ],
    "name:und_x_variant":[
        "Yuski Takirmeny",
        "Tashkirmen\u2019"
    ],
    "wof:name":"Tashkirmen'",
    "wof:placetype":"locality"
},
  "geometry": {"coordinates":[49.3862,55.3191],"type":"Point"}
}