{
  "type": "Feature",
  "properties": {
    "gn:admin1_code":"67",
    "gn:asciiname":"Novaya Alekseyevka",
    "gn:country_code":"RU",
    "gn:dem":46,
    "gn:feature_class":"P",
    "gn:feature_code":"PPL",
    "gn:name":"Novaya Alekseyevka",
    "gn:population":0,
    "gn:timezone":"Europe/Saratov",
    "iso:country":"RU",
    "name:eng_x_preferred":[
        "Novaya Alekseyevka"
    ],
    "name:nor_x_preferred":[
        "Nov.Alekejevka"
    ],
    "name:rus_x_preferred":[
        "\u041d\u043e\u0432.\u0410\u043b\u0435\u043a\u0435\u0435\u0432\u043a\u0430"
    ],
    "name:und_x_variant":[
        "Novoalekseyevka",
        "Novaya Alekseyevka"
    ],
    "wof:name":"Novaya Alekseyevka",
    "wof:placetype":"locality"
},
  "geometry": {"coordinates":[46.80833,51.95806],"type":"Point"}
}