{
  "type": "Feature",
  "properties": {
    "gn:admin1_code":"56",
    "gn:asciiname":"Koty",
    "gn:country_code":"RU",
    "gn:dem":249,
    "gn:feature_class":"P",
    "gn:feature_code":"PPL",
    "gn:name":"Koty",
    "gn:population":0,
    "gn:timezone":"Europe/Moscow",
    "iso:country":"RU",
    "name:rus_x_preferred":[
        "\u041a\u043e\u0442\u044b"
    ],
    "name:und_x_variant":[
        "\u041a\u043e\u0442\u044b"
    ],
    "wof:name":"Koty",
    "wof:placetype":"locality"
},
  "geometry": {"coordinates":[37.5027,53.18992],"type":"Point"}
}