{
  "type": "Feature",
  "properties": {
    "gn:admin1_code":"25",
    "gn:asciiname":"Akulovo",
    "gn:country_code":"RU",
    "gn:dem":188,
    "gn:feature_class":"P",
    "gn:feature_code":"PPL",
    "gn:name":"Akulovo",
    "gn:population":0,
    "gn:timezone":"Europe/Moscow",
    "iso:country":"RU",
    "name:nor_x_preferred":[
        "Akulovo"
    ],
    "name:rus_x_preferred":[
        "\u0410\u043a\u0443\u043b\u043e\u0432\u043e"
    ],
    "wof:name":"Akulovo",
    "wof:placetype":"locality"
},
  "geometry": {"coordinates":[36.44278,55.17083],"type":"Point"}
}