{
  "type": "Feature",
  "properties": {
    "gn:admin1_code":"47",
    "gn:asciiname":"Ivan'shevo",
    "gn:country_code":"RU",
    "gn:dem":188,
    "gn:feature_class":"P",
    "gn:feature_code":"PPL",
    "gn:name":"Ivan\u2019shevo",
    "gn:population":0,
    "gn:timezone":"Europe/Moscow",
    "iso:country":"RU",
    "name:rus_x_preferred":[
        "\u0418\u0432\u0430\u043d\u044c\u0448\u0435\u0432\u043e"
    ],
    "name:und_x_variant":[
        "Ivan\u2019shevo"
    ],
    "wof:name":"Ivan'shevo",
    "wof:placetype":"locality"
},
  "geometry": {"coordinates":[38.66633,54.70653000000001],"type":"Point"}
}