{
  "type": "Feature",
  "properties": {
    "gn:admin1_code":"53",
    "gn:asciiname":"Kos'minka",
    "gn:country_code":"RU",
    "gn:dem":130,
    "gn:feature_class":"P",
    "gn:feature_code":"PPL",
    "gn:name":"Kos\u2019minka",
    "gn:population":0,
    "gn:timezone":"Asia/Novosibirsk",
    "iso:country":"RU",
    "name:rus_x_preferred":[
        "\u041a\u043e\u0441\u044c\u043c\u0438\u043d\u043a\u0430"
    ],
    "name:und_x_variant":[
        "Kos\u2019minka",
        "\u041a\u043e\u0441\u044c\u043c\u0438\u043d\u043a\u0430"
    ],
    "wof:name":"Kos'minka",
    "wof:placetype":"locality"
},
  "geometry": {"coordinates":[79.23333000000002,56.45],"type":"Point"}
}