{
  "type": "Feature",
  "properties": {
    "gn:admin1_code":"13",
    "gn:asciiname":"Krakhalevka",
    "gn:country_code":"RU",
    "gn:dem":192,
    "gn:feature_class":"P",
    "gn:feature_code":"PPL",
    "gn:name":"Krakhalevka",
    "gn:population":0,
    "gn:timezone":"Asia/Yekaterinburg",
    "iso:country":"RU",
    "name:rus_x_preferred":[
        "\u041a\u0440\u0430\u0445\u0430\u043b\u0435\u0432\u043a\u0430"
    ],
    "name:und_x_variant":[
        "Krokhalevka"
    ],
    "wof:name":"Krakhalevka",
    "wof:placetype":"locality"
},
  "geometry": {"coordinates":[61.1562,54.097],"type":"Point"}
}