{
  "type": "Feature",
  "properties": {
    "gn:admin1_code":"37",
    "gn:asciiname":"Blinovshchina",
    "gn:country_code":"RU",
    "gn:dem":164,
    "gn:feature_class":"P",
    "gn:feature_code":"PPL",
    "gn:name":"Blinovshchina",
    "gn:population":0,
    "gn:timezone":"Europe/Moscow",
    "iso:country":"RU",
    "name:eng_x_preferred":[
        "Blinovshchina"
    ],
    "name:nor_x_preferred":[
        "Blinovsjtsjina"
    ],
    "name:rus_x_preferred":[
        "\u0411\u043b\u0438\u043d\u043e\u0432\u0449\u0438\u043d\u0430"
    ],
    "name:und_x_variant":[
        "\u0411\u043b\u0438\u043d\u043e\u0432\u0449\u0438\u043d\u0430",
        "Blinovshchina"
    ],
    "wof:name":"Blinovshchina",
    "wof:placetype":"locality"
},
  "geometry": {"coordinates":[47.26333,58.9622],"type":"Point"}
}