{
  "type": "Feature",
  "properties": {
    "gn:admin1_code":"16",
    "gn:asciiname":"Asanovo",
    "gn:country_code":"RU",
    "gn:dem":146,
    "gn:feature_class":"P",
    "gn:feature_code":"PPL",
    "gn:name":"Asanovo",
    "gn:population":0,
    "gn:timezone":"Europe/Moscow",
    "iso:country":"RU",
    "name:rus_x_preferred":[
        "\u0410\u0441\u0430\u043d\u043e\u0432\u043e"
    ],
    "wof:name":"Asanovo",
    "wof:placetype":"locality"
},
  "geometry": {"coordinates":[47.3464,54.7629],"type":"Point"}
}