{
  "type": "Feature",
  "properties": {
    "gn:admin1_code":"80",
    "gn:asciiname":"Nizhniy Tyloy",
    "gn:country_code":"RU",
    "gn:dem":201,
    "gn:feature_class":"P",
    "gn:feature_code":"PPL",
    "gn:name":"Nizhniy Tyloy",
    "gn:population":0,
    "gn:timezone":"Europe/Samara",
    "iso:country":"RU",
    "name:rus_x_preferred":[
        "\u041d\u0438\u0436\u043d\u0438\u0439 \u0422\u044b\u043b\u043e\u0439"
    ],
    "name:und_x_variant":[
        "\u041d\u0438\u0436\u043d\u0438\u0439 \u0422\u044b\u043b\u043e\u0439"
    ],
    "wof:name":"Nizhniy Tyloy",
    "wof:placetype":"locality"
},
  "geometry": {"coordinates":[53.5351,57.3819],"type":"Point"}
}