{
  "type": "Feature",
  "properties": {
    "gn:admin1_code":"33",
    "gn:asciiname":"Klyuch",
    "gn:country_code":"RU",
    "gn:dem":144,
    "gn:feature_class":"P",
    "gn:feature_code":"PPL",
    "gn:name":"Klyuch",
    "gn:population":0,
    "gn:timezone":"Europe/Kirov",
    "iso:country":"RU",
    "name:bul_x_preferred":[
        "\u041a\u043b\u044e\u0447"
    ],
    "name:fra_x_preferred":[
        "Klyuch"
    ],
    "name:kat_x_preferred":[
        "\u10d9\u10da\u10d8\u10e3\u10e9\u10d8"
    ],
    "name:kaz_x_preferred":[
        "\u041a\u043b\u044e\u0447"
    ],
    "name:lat_x_preferred":[
        "Clidium"
    ],
    "name:mkd_x_preferred":[
        "\u041a\u043b\u0443\u0447"
    ],
    "name:msa_x_preferred":[
        "Klyuch"
    ],
    "name:ron_x_preferred":[
        "Kliuci"
    ],
    "name:rus_x_preferred":[
        "\u041a\u043b\u044e\u0447"
    ],
    "name:spa_x_preferred":[
        "Klyuch"
    ],
    "name:ukr_x_preferred":[
        "\u041a\u043b\u044e\u0447"
    ],
    "wof:name":"Klyuch",
    "wof:placetype":"locality"
},
  "geometry": {"coordinates":[50.2464,57.9939],"type":"Point"}
}