{
  "type": "Feature",
  "properties": {
    "gn:admin1_code":"8",
    "gn:asciiname":"Sultanay",
    "gn:country_code":"RU",
    "gn:dem":234,
    "gn:feature_class":"P",
    "gn:feature_code":"PPL",
    "gn:name":"Sultanay",
    "gn:population":0,
    "gn:timezone":"Asia/Yekaterinburg",
    "iso:country":"RU",
    "name:aze_x_preferred":[
        "Sultanay"
    ],
    "name:bak_x_preferred":[
        "\u0421\u043e\u043b\u0442\u0430\u043d\u0430\u0439"
    ],
    "name:eng_x_preferred":[
        "Sultanay"
    ],
    "name:hye_x_preferred":[
        "\u054d\u0578\u0582\u056c\u057f\u0561\u0576\u0561\u0575"
    ],
    "name:kat_x_preferred":[
        "\u10e1\u10e3\u10da\u10e2\u10d0\u10dc\u10d0\u10d8"
    ],
    "name:nor_x_preferred":[
        "Sultanaj"
    ],
    "name:rus_x_preferred":[
        "\u0421\u0443\u043b\u0442\u0430\u043d\u0430\u0439"
    ],
    "wof:name":"Sultanay",
    "wof:placetype":"locality"
},
  "geometry": {"coordinates":[56.48091,56.02779],"type":"Point"}
}