{
  "type": "Feature",
  "properties": {
    "gn:admin1_code":"8",
    "gn:asciiname":"Sultanay",
    "gn:country_code":"RU",
    "gn:dem":234,
    "gn:feature_class":"P",
    "gn:feature_code":"PPL",
    "gn:name":"Sultanay",
    "gn:population":0,
    "gn:timezone":"Asia/Yekaterinburg",
    "iso:country":"RU",
    "name:eng_x_preferred":[
        "Sultanay"
    ],
    "name:nor_x_preferred":[
        "Sultanaj"
    ],
    "name:rus_x_preferred":[
        "\u0421\u0443\u043b\u0442\u0430\u043d\u0430\u0439"
    ],
    "wof:name":"Sultanay",
    "wof:placetype":"locality"
},
  "geometry": {"coordinates":[56.48091,56.02779],"type":"Point"}
}