{
  "type": "Feature",
  "properties": {
    "gn:admin1_code":"69",
    "gn:asciiname":"Ivishenka",
    "gn:country_code":"RU",
    "gn:dem":224,
    "gn:feature_class":"P",
    "gn:feature_code":"PPL",
    "gn:name":"Ivishenka",
    "gn:population":0,
    "gn:timezone":"Europe/Moscow",
    "iso:country":"RU",
    "name:rus_x_preferred":[
        "\u0418\u0432\u0438\u0448\u0435\u043d\u043a\u0430"
    ],
    "name:und_x_variant":[
        "\u0418\u0432\u0438\u0448\u0435\u043d\u043a\u0430"
    ],
    "wof:name":"Ivishenka",
    "wof:placetype":"locality"
},
  "geometry": {"coordinates":[32.63528,55.12806],"type":"Point"}
}