{
  "type": "Feature",
  "properties": {
    "gn:admin1_code":"73",
    "gn:asciiname":"Yamurzino",
    "gn:country_code":"RU",
    "gn:dem":79,
    "gn:feature_class":"P",
    "gn:feature_code":"PPL",
    "gn:name":"Yamurzino",
    "gn:population":0,
    "gn:timezone":"Europe/Moscow",
    "iso:country":"RU",
    "name:und_x_variant":[
        "Amurzino",
        "Yamurzino"
    ],
    "wof:name":"Yamurzino",
    "wof:placetype":"locality"
},
  "geometry": {"coordinates":[53.01176,56.00892],"type":"Point"}
}