{
  "type": "Feature",
  "properties": {
    "gn:admin1_code":"69.0",
    "gn:asciiname":"Bryukhachikha",
    "gn:country_code":"RU",
    "gn:dem":214,
    "gn:feature_class":"P",
    "gn:feature_code":"PPL",
    "gn:name":"Bryukhachikha",
    "gn:population":0,
    "gn:timezone":"Europe/Moscow",
    "iso:country":"RU",
    "name:rus_x_preferred":[
        "\u0411\u0440\u044e\u0445\u0430\u0447\u0438\u0445\u0430"
    ],
    "name:und_x_variant":[
        "Brekhachikha",
        "Bryukhachikha",
        "\u0411\u0440\u044e\u0445\u0430\u0447\u0438\u0445\u0430"
    ],
    "wof:name":"Bryukhachikha",
    "wof:placetype":"locality"
},
  "geometry": {"coordinates":[34.06427,55.53716],"type":"Point"}
}