{
  "type": "Feature",
  "properties": {
    "gn:admin1_code":"84",
    "gn:asciiname":"Kulichki",
    "gn:country_code":"RU",
    "gn:dem":145,
    "gn:feature_class":"P",
    "gn:feature_code":"PPL",
    "gn:name":"Kulichki",
    "gn:population":0,
    "gn:timezone":"Europe/Volgograd",
    "iso:country":"RU",
    "name:eng_x_preferred":[
        "Kulichki"
    ],
    "name:nor_x_preferred":[
        "Kulitsjki"
    ],
    "name:rus_x_preferred":[
        "\u041a\u0443\u043b\u0438\u0447\u043a\u0438"
    ],
    "name:und_x_variant":[
        "Kulichevskiy",
        "Kulikovskiy",
        "\u041a\u0443\u043b\u0438\u0447\u043a\u0438",
        "Kulichki"
    ],
    "wof:name":"Kulichki",
    "wof:placetype":"locality"
},
  "geometry": {"coordinates":[41.7674,50.1206],"type":"Point"}
}