{
  "type": "Feature",
  "properties": {
    "gn:admin1_code":"77",
    "gn:asciiname":"Shelbodino",
    "gn:country_code":"RU",
    "gn:dem":156,
    "gn:feature_class":"P",
    "gn:feature_code":"PPL",
    "gn:name":"Shelbodino",
    "gn:population":0,
    "gn:timezone":"Europe/Moscow",
    "iso:country":"RU",
    "name:rus_x_preferred":[
        "\u0428\u0435\u043b\u0431\u043e\u0434\u0438\u043d\u043e"
    ],
    "wof:name":"Shelbodino",
    "wof:placetype":"locality"
},
  "geometry": {"coordinates":[36.6397,57.4613],"type":"Point"}
}