{
  "type": "Feature",
  "properties": {
    "gn:admin1_code":"28",
    "gn:asciiname":"Kukoynavolok",
    "gn:country_code":"RU",
    "gn:dem":76,
    "gn:feature_class":"P",
    "gn:feature_code":"PPL",
    "gn:name":"Kukoynavolok",
    "gn:population":0,
    "gn:timezone":"Europe/Moscow",
    "iso:country":"RU",
    "name:fin_x_preferred":[
        "Kukonniemi"
    ],
    "name:rus_x_preferred":[
        "\u041a\u0443\u043a\u043e\u0439\u043d\u0430\u0432\u043e\u043b\u043e\u043a"
    ],
    "name:und_x_variant":[
        "\u041a\u0443\u043a\u043e\u0439\u043d\u0430\u0432\u043e\u043b\u043e\u043a"
    ],
    "wof:name":"Kukoynavolok",
    "wof:placetype":"locality"
},
  "geometry": {"coordinates":[33.73333,61.05],"type":"Point"}
}