{
  "type": "Feature",
  "properties": {
    "gn:admin1_code":"4",
    "gn:asciiname":"Glushinka",
    "gn:country_code":"RU",
    "gn:dem":184,
    "gn:feature_class":"P",
    "gn:feature_code":"PPL",
    "gn:name":"Glushinka",
    "gn:population":0,
    "gn:timezone":"Asia/Barnaul",
    "iso:country":"RU",
    "name:eng_x_preferred":[
        "Glushinka"
    ],
    "name:nor_x_preferred":[
        "Glusjinka"
    ],
    "name:rus_x_preferred":[
        "\u0413\u043b\u0443\u0448\u0438\u043d\u043a\u0430"
    ],
    "name:und_x_variant":[
        "Glushinskoye",
        "Glushenka",
        "\u0413\u043b\u0443\u0448\u0438\u043d\u043a\u0430",
        "Glushinka"
    ],
    "wof:name":"Glushinka",
    "wof:placetype":"locality"
},
  "geometry": {"coordinates":[84.5025,53.45639],"type":"Point"}
}