{
  "type": "Feature",
  "properties": {
    "gn:admin1_code":"6",
    "gn:asciiname":"Uzkoye",
    "gn:country_code":"RU",
    "gn:dem":128,
    "gn:feature_class":"P",
    "gn:feature_code":"PPL",
    "gn:name":"Uzkoye",
    "gn:population":0,
    "gn:timezone":"Europe/Moscow",
    "iso:country":"RU",
    "name:bul_x_preferred":[
        "\u0423\u0437\u043a\u043e\u0435"
    ],
    "name:dan_x_preferred":[
        "Uzkoje"
    ],
    "name:fra_x_preferred":[
        "Ch\u00e2teau d'Ouzko\u00efe"
    ],
    "name:ita_x_preferred":[
        "Uzkoe"
    ],
    "name:rus_x_preferred":[
        "\u0423\u0437\u043a\u043e\u0435"
    ],
    "wof:name":"Uzkoye",
    "wof:placetype":"locality"
},
  "geometry": {"coordinates":[38.88333,62.53333000000001],"type":"Point"}
}