{
  "type": "Feature",
  "properties": {
    "gn:admin1_code":"52.0",
    "gn:asciiname":"Dorokhnovo",
    "gn:country_code":"RU",
    "gn:dem":64,
    "gn:feature_class":"P",
    "gn:feature_code":"PPL",
    "gn:name":"Dorokhnovo",
    "gn:population":0,
    "gn:timezone":"Europe/Moscow",
    "iso:country":"RU",
    "name:rus_x_preferred":[
        "\u0414\u043e\u0440\u043e\u0445\u043d\u043e\u0432\u043e"
    ],
    "name:und_x_variant":[
        "Dorokhnova",
        "Dorokhnovo"
    ],
    "wof:name":"Dorokhnovo",
    "wof:placetype":"locality"
},
  "geometry": {"coordinates":[31.08114,57.72784],"type":"Point"}
}