{
  "type": "Feature",
  "properties": {
    "gn:admin1_code":"37",
    "gn:asciiname":"Romantsevo",
    "gn:country_code":"RU",
    "gn:dem":165,
    "gn:feature_class":"P",
    "gn:feature_code":"PPL",
    "gn:name":"Romants\u00ebvo",
    "gn:population":0,
    "gn:timezone":"Europe/Moscow",
    "iso:country":"RU",
    "name:eng_x_preferred":[
        "Romantsevo"
    ],
    "name:nor_x_preferred":[
        "Romantsevo"
    ],
    "name:rus_x_preferred":[
        "\u0420\u043e\u043c\u0430\u043d\u0446\u0435\u0432\u043e"
    ],
    "name:und_x_variant":[
        "Romants\u00ebvo"
    ],
    "wof:name":"Romantsevo",
    "wof:placetype":"locality"
},
  "geometry": {"coordinates":[41.68722,58.67944],"type":"Point"}
}