{
  "type": "Feature",
  "properties": {
    "gn:admin1_code":"6",
    "gn:asciiname":"Il'inskaya Sloboda",
    "gn:country_code":"RU",
    "gn:dem":148,
    "gn:feature_class":"P",
    "gn:feature_code":"PPL",
    "gn:name":"Il\u2019inskaya Sloboda",
    "gn:population":0,
    "gn:timezone":"Europe/Moscow",
    "iso:country":"RU",
    "name:rus_x_preferred":[
        "\u0418\u043b\u044c\u0438\u043d\u0441\u043a\u0430\u044f \u0421\u043b\u043e\u0431\u043e\u0434\u0430"
    ],
    "name:und_x_variant":[
        "Il\u2019inskaya Slobodka",
        "Il\u2019inskaya Sloboda"
    ],
    "wof:name":"Il'inskaya Sloboda",
    "wof:placetype":"locality"
},
  "geometry": {"coordinates":[38.1161,61.4043],"type":"Point"}
}