{
  "type": "Feature",
  "properties": {
    "gn:country":"RU",
    "gn:fcode":"ADMD",
    "gn:population":0,
    "iso:country":"RU",
    "name:rus_x_preferred":[
        "\u0424\u0430\u043b\u0435\u043d\u0441\u043a\u0438\u0439 \u0440\u0430\u0439\u043e\u043d"
    ],
    "name:und_x_variant":[
        "Falenski\u012d Ra\u012don"
    ],
    "qs:name":"Fal\u00ebnskiy Rayon",
    "qs:photos_9r":0,
    "qs:photos_sr":0,
    "qs:pop_sr":"0",
    "wof:name":"Fal\u00ebnskiy Rayon",
    "wof:placetype":"localadmin",
    "wof:population":0
},
  "geometry": {"coordinates":[51.58333,58.33333],"type":"Point"}
}