{
  "type": "Feature",
  "properties": {
    "gn:country":"RU",
    "gn:fcode":"PPLX",
    "gn:population":0,
    "iso:country":"RU",
    "name:bul_x_preferred":[
        "\u0411\u0435\u0441\u043a\u0443\u0434\u043d\u0438\u043a\u043e\u0432\u0441\u043a\u0438 \u0440\u0430\u0439\u043e\u043d"
    ],
    "name:eng_x_preferred":[
        "Beskudnikovsky District"
    ],
    "name:fra_x_preferred":[
        "Beskoudnikovski"
    ],
    "name:ita_x_preferred":[
        "Beskudinkovskij"
    ],
    "name:nld_x_preferred":[
        "Beskoednikovskiy rayon"
    ],
    "name:nor_x_preferred":[
        "Beskudnikovo"
    ],
    "name:por_x_preferred":[
        "Beskudnikovsky"
    ],
    "name:rus_x_preferred":[
        "\u0411\u0435\u0441\u043a\u0443\u0434\u043d\u0438\u043a\u043e\u0432\u0441\u043a\u0438\u0439"
    ],
    "name:rus_x_variant":[
        "\u0411\u0435\u0441\u043a\u0443\u0434\u043d\u0438\u043a\u043e\u0432\u0441\u043a\u0438\u0439 \u0440\u0430\u0439\u043e\u043d"
    ],
    "name:sco_x_preferred":[
        "Beskudnikovsky Destrict"
    ],
    "name:ukr_x_preferred":[
        "\u0411\u0435\u0441\u043a\u0443\u0434\u043d\u0438\u043a\u043e\u0432\u0441\u044c\u043a\u0438\u0439"
    ],
    "name:zho_x_preferred":[
        "\u5225\u65af\u5eab\u5fb7\u5c3c\u79d1\u592b\u5340"
    ],
    "wof:name":"Beskudnikovsky",
    "wof:placetype":"neighbourhood",
    "wof:population":0
},
  "geometry": {"coordinates":[37.55260655729615,55.86820680600853],"type":"Point"}
}