{
  "type": "Feature",
  "properties": {
    "gn:country":"RU",
    "gn:fcode":"PPLX",
    "gn:pop":0,
    "iso:country":"RU",
    "name:eng_x_preferred":[
        "Beskudnikovsky District"
    ],
    "name:nor_x_preferred":[
        "Beskudnikovo"
    ],
    "name:rus_x_preferred":[
        "\u0411\u0435\u0441\u043a\u0443\u0434\u043d\u0438\u043a\u043e\u0432\u0441\u043a\u0438\u0439"
    ],
    "wof:name":"Beskudnikovsky",
    "wof:placetype":"neighbourhood",
    "wof:population":0
},
  "geometry": {"coordinates":[37.55260655729615,55.86820680600853],"type":"Point"}
}