{
  "type": "Feature",
  "properties": {
    "gn:country":"RU",
    "gn:fcode":"PPLX",
    "gn:population":0,
    "iso:country":"RU",
    "name:azb_x_preferred":[
        "\u0628\u0632\u06a9\u0648\u062f\u0646\u06cc\u06a9\u0648\u0648\u0627\u06cc\u0633\u06a9\u0627\u06cc"
    ],
    "name:bul_x_preferred":[
        "\u0411\u0435\u0441\u043a\u0443\u0434\u043d\u0438\u043a\u043e\u0432\u0441\u043a\u0438 \u0440\u0430\u0439\u043e\u043d"
    ],
    "name:ceb_x_preferred":[
        "Beskudnikovo"
    ],
    "name:eng_x_preferred":[
        "Beskudnikovsky District"
    ],
    "name:fra_x_preferred":[
        "Beskoudnikovski"
    ],
    "name:heb_x_preferred":[
        "\u05d1\u05e1\u05e7\u05d5\u05d3\u05e0\u05d9\u05e7\u05d5\u05d1\u05e1\u05e7\u05d9 \u05e8\u05d0\u05d9\u05d5\u05df"
    ],
    "name:ita_x_preferred":[
        "Beskudinkovskij"
    ],
    "name:nan_x_preferred":[
        "Beskudnikovsky Ko\u0101n"
    ],
    "name:nld_x_preferred":[
        "Beskoednikovskiy rayon"
    ],
    "name:nor_x_preferred":[
        "Beskudnikovo"
    ],
    "name:por_x_preferred":[
        "Beskudnikovsky"
    ],
    "name:rus_x_preferred":[
        "\u0411\u0435\u0441\u043a\u0443\u0434\u043d\u0438\u043a\u043e\u0432\u0441\u043a\u0438\u0439"
    ],
    "name:rus_x_variant":[
        "\u0411\u0435\u0441\u043a\u0443\u0434\u043d\u0438\u043a\u043e\u0432\u0441\u043a\u0438\u0439 \u0440\u0430\u0439\u043e\u043d"
    ],
    "name:sco_x_preferred":[
        "Beskudnikovsky Destrict"
    ],
    "name:ukr_x_preferred":[
        "\u0411\u0435\u0441\u043a\u0443\u0434\u043d\u0438\u043a\u043e\u0432\u0441\u044c\u043a\u0438\u0439"
    ],
    "name:zho_x_preferred":[
        "\u5225\u65af\u5eab\u5fb7\u5c3c\u79d1\u592b\u5340"
    ],
    "wof:name":"Beskudnikovsky",
    "wof:placetype":"neighbourhood",
    "wof:population":0
},
  "geometry": {"coordinates":[37.552607,55.868207],"type":"Point"}
}