{
  "type": "Feature",
  "properties": {
    "gn:admin1_code":"65",
    "gn:asciiname":"Yumratka",
    "gn:country_code":"RU",
    "gn:dem":73,
    "gn:feature_class":"P",
    "gn:feature_code":"PPL",
    "gn:name":"Yumratka",
    "gn:population":0,
    "gn:timezone":"Europe/Samara",
    "iso:country":"RU",
    "name:rus_x_preferred":[
        "\u042e\u043c\u0440\u0430\u0442\u043a\u0430"
    ],
    "name:und_x_variant":[
        "\u042e\u043c\u0440\u0430\u0442\u043a\u0430"
    ],
    "wof:name":"Yumratka",
    "wof:placetype":"locality"
},
  "geometry": {"coordinates":[50.3364,54.4259],"type":"Point"}
}