{
  "type": "Feature",
  "properties": {
    "gn:admin1_code":"90.0",
    "gn:asciiname":"Busyryata",
    "gn:country_code":"RU",
    "gn:dem":136,
    "gn:feature_class":"P",
    "gn:feature_code":"PPL",
    "gn:name":"Busyryata",
    "gn:population":0,
    "gn:timezone":"Asia/Yekaterinburg",
    "iso:country":"RU",
    "name:rus_x_preferred":[
        "\u0411\u0443\u0441\u044b\u0440\u044f\u0442\u0430"
    ],
    "wof:name":"Busyryata",
    "wof:placetype":"locality"
},
  "geometry": {"coordinates":[55.94889000000001,58.13833],"type":"Point"}
}