{
  "type": "Feature",
  "properties": {
    "gn:admin1_code":"28",
    "gn:asciiname":"Kulemino",
    "gn:country_code":"RU",
    "gn:dem":128,
    "gn:feature_class":"P",
    "gn:feature_code":"PPL",
    "gn:name":"Kul\u00ebmino",
    "gn:population":0,
    "gn:timezone":"Europe/Moscow",
    "iso:country":"RU",
    "name:rus_x_preferred":[
        "\u041a\u0443\u043b\u0451\u043c\u0438\u043d\u043e"
    ],
    "name:und_x_variant":[
        "Kul\u00ebmino",
        "\u041a\u0443\u043b\u0451\u043c\u0438\u043d\u043e"
    ],
    "wof:name":"Kulemino",
    "wof:placetype":"locality"
},
  "geometry": {"coordinates":[34.65,63.88333000000001],"type":"Point"}
}