{
  "type": "Feature",
  "properties": {
    "gn:admin1_code":"42",
    "gn:asciiname":"Os'mino Gora",
    "gn:country_code":"RU",
    "gn:dem":52,
    "gn:feature_class":"P",
    "gn:feature_code":"PPL",
    "gn:name":"Os\u2019mino Gora",
    "gn:population":0,
    "gn:timezone":"Europe/Moscow",
    "iso:country":"RU",
    "name:rus_x_preferred":[
        "\u041e\u0441\u044c\u043c\u0438\u043d\u043e \u0413\u043e\u0440\u0430"
    ],
    "name:und_x_variant":[
        "Os\u2019mino Gora"
    ],
    "wof:name":"Os'mino Gora",
    "wof:placetype":"locality"
},
  "geometry": {"coordinates":[29.08333,59.01667],"type":"Point"}
}