{
  "type": "Feature",
  "properties": {
    "gn:admin1_code":"38.0",
    "gn:asciiname":"Glebovskoye",
    "gn:country_code":"RU",
    "gn:dem":52,
    "gn:feature_class":"P",
    "gn:feature_code":"PPL",
    "gn:name":"Glebovskoye",
    "gn:population":0,
    "gn:timezone":"Europe/Moscow",
    "iso:country":"RU",
    "name:rus_x_preferred":[
        "\u0413\u043b\u0435\u0431\u043e\u0432\u0441\u043a\u043e\u0435"
    ],
    "name:und_x_variant":[
        "Glebovka",
        "Glebovskoye",
        "\u0413\u043b\u0435\u0431\u043e\u0432\u0441\u043a\u043e\u0435"
    ],
    "wof:name":"Glebovskoye",
    "wof:placetype":"locality"
},
  "geometry": {"coordinates":[37.64284,44.70972],"type":"Point"}
}