{
  "type": "Feature",
  "properties": {
    "gn:admin1_code":"56",
    "gn:asciiname":"Nizhnyaya Kirillovka",
    "gn:country_code":"RU",
    "gn:dem":145,
    "gn:feature_class":"P",
    "gn:feature_code":"PPL",
    "gn:name":"Nizhnyaya Kirillovka",
    "gn:population":0,
    "gn:timezone":"Europe/Moscow",
    "iso:country":"RU",
    "name:rus_x_preferred":[
        "\u041d\u0438\u0436\u043d\u044f\u044f \u041a\u0438\u0440\u0438\u043b\u043b\u043e\u0432\u043a\u0430"
    ],
    "wof:name":"Nizhnyaya Kirillovka",
    "wof:placetype":"locality"
},
  "geometry": {"coordinates":[37.72417,52.19917],"type":"Point"}
}