{
  "type": "Feature",
  "properties": {
    "gn:admin1_code":"10",
    "gn:asciiname":"Krasnyy Klin",
    "gn:country_code":"RU",
    "gn:dem":179,
    "gn:feature_class":"P",
    "gn:feature_code":"PPL",
    "gn:name":"Krasnyy Klin",
    "gn:population":0,
    "gn:timezone":"Europe/Moscow",
    "iso:country":"RU",
    "name:rus_x_preferred":[
        "\u041a\u0440\u0430\u0441\u043d\u044b\u0439 \u041a\u043b\u0438\u043d"
    ],
    "name:und_x_variant":[
        "Krasny Klin",
        "Krasnyy Klin"
    ],
    "wof:name":"Krasnyy Klin",
    "wof:placetype":"locality"
},
  "geometry": {"coordinates":[32.4218,52.55031999999999],"type":"Point"}
}