{
  "type": "Feature",
  "properties": {
    "gn:admin1_code":"51",
    "gn:asciiname":"Ryabkovo",
    "gn:country_code":"RU",
    "gn:dem":117,
    "gn:feature_class":"P",
    "gn:feature_code":"PPL",
    "gn:name":"Ryabkovo",
    "gn:population":0,
    "gn:timezone":"Europe/Moscow",
    "iso:country":"RU",
    "name:rus_x_preferred":[
        "\u0420\u044f\u0431\u043a\u043e\u0432\u043e"
    ],
    "name:und_x_variant":[
        "\u0420\u044f\u0431\u043a\u043e\u0432\u043e"
    ],
    "wof:name":"Ryabkovo",
    "wof:placetype":"locality"
},
  "geometry": {"coordinates":[46.524,57.7361],"type":"Point"}
}