{
  "type": "Feature",
  "properties": {
    "gn:admin1_code":"11",
    "gn:asciiname":"Shuluta",
    "gn:country_code":"RU",
    "gn:dem":827,
    "gn:feature_class":"P",
    "gn:feature_code":"PPL",
    "gn:name":"Shuluta",
    "gn:population":0,
    "gn:timezone":"Asia/Irkutsk",
    "iso:country":"RU",
    "name:rus_x_preferred":[
        "\u0428\u0443\u043b\u0443\u0442\u0430"
    ],
    "name:und_x_variant":[
        "\u0428\u0443\u043b\u0443\u0442\u0430"
    ],
    "wof:name":"Shuluta",
    "wof:placetype":"locality"
},
  "geometry": {"coordinates":[109.91667,51.88333],"type":"Point"}
}