{
  "type": "Feature",
  "properties": {
    "gn:admin1_code":"45",
    "gn:asciiname":"Sarapayevo",
    "gn:country_code":"RU",
    "gn:dem":136,
    "gn:feature_class":"P",
    "gn:feature_code":"PPL",
    "gn:name":"Sarapayevo",
    "gn:population":0,
    "gn:timezone":"Europe/Moscow",
    "iso:country":"RU",
    "name:rus_x_preferred":[
        "\u0421\u0430\u0440\u0430\u043f\u0430\u0435\u0432\u043e"
    ],
    "wof:name":"Sarapayevo",
    "wof:placetype":"locality"
},
  "geometry": {"coordinates":[46.387,56.198],"type":"Point"}
}