{
  "type": "Feature",
  "properties": {
    "gn:admin1_code":"77",
    "gn:asciiname":"Vedernitsa",
    "gn:country_code":"RU",
    "gn:dem":153,
    "gn:feature_class":"P",
    "gn:feature_code":"PPL",
    "gn:name":"Vedernitsa",
    "gn:population":0,
    "gn:timezone":"Europe/Moscow",
    "iso:country":"RU",
    "name:rus_x_preferred":[
        "\u0412\u0435\u0434\u0435\u0440\u043d\u0438\u0446\u0430"
    ],
    "wof:name":"Vedernitsa",
    "wof:placetype":"locality"
},
  "geometry": {"coordinates":[36.9299,58.0828],"type":"Point"}
}