{
  "type": "Feature",
  "properties": {
    "gn:admin1_code":"28",
    "gn:asciiname":"Voloma",
    "gn:country_code":"RU",
    "gn:dem":232,
    "gn:feature_class":"P",
    "gn:feature_code":"PPL",
    "gn:name":"Voloma",
    "gn:population":0,
    "gn:timezone":"Europe/Moscow",
    "iso:country":"RU",
    "name:eng_x_preferred":[
        "Voloma"
    ],
    "name:nor_x_preferred":[
        "Voloma"
    ],
    "name:rus_x_preferred":[
        "\u0412\u043e\u043b\u043e\u043c\u0430"
    ],
    "wof:name":"Voloma",
    "wof:placetype":"locality"
},
  "geometry": {"coordinates":[32.03777,63.65104],"type":"Point"}
}