{
  "type": "Feature",
  "properties": {
    "gn:admin1_code":"77",
    "gn:asciiname":"Spass",
    "gn:country_code":"RU",
    "gn:dem":158,
    "gn:feature_class":"P",
    "gn:feature_code":"PPL",
    "gn:name":"Spass",
    "gn:population":0,
    "gn:timezone":"Europe/Moscow",
    "iso:country":"RU",
    "name:nor_x_preferred":[
        "Spass"
    ],
    "name:rus_x_preferred":[
        "\u0421\u043f\u0430\u0441\u0441"
    ],
    "name:und_x_variant":[
        "Spas"
    ],
    "wof:name":"Spass",
    "wof:placetype":"locality"
},
  "geometry": {"coordinates":[35.13063,56.9915],"type":"Point"}
}