{
  "type": "Feature",
  "properties": {
    "gn:admin1_code":"73.0",
    "gn:asciiname":"Churu-Baryshevo",
    "gn:country_code":"RU",
    "gn:dem":68,
    "gn:feature_class":"P",
    "gn:feature_code":"PPL",
    "gn:name":"Churu-Baryshevo",
    "gn:population":0,
    "gn:timezone":"Europe/Moscow",
    "iso:country":"RU",
    "name:eng_x_preferred":[
        "Churu-Baryshevo"
    ],
    "name:nor_x_preferred":[
        "Tsjuru-Barysjevo"
    ],
    "name:rus_x_preferred":[
        "\u0427\u0443\u0440\u0443-\u0411\u0430\u0440\u044b\u0448\u0435\u0432\u043e"
    ],
    "name:und_x_variant":[
        "Nury Baryshevo",
        "\u0427\u0443\u0440\u0443-\u0411\u0430\u0440\u044b\u0448\u0435\u0432\u043e",
        "Churu-Baryshevo"
    ],
    "wof:name":"Churu-Baryshevo",
    "wof:placetype":"locality"
},
  "geometry": {"coordinates":[48.58375,55.22727],"type":"Point"}
}