{
  "type": "Feature",
  "properties": {
    "gn:admin1_code":"51.0",
    "gn:asciiname":"Bol'shiye Kilimary",
    "gn:country_code":"RU",
    "gn:dem":136,
    "gn:feature_class":"P",
    "gn:feature_code":"PPL",
    "gn:name":"Bol\u2019shiye Kilimary",
    "gn:population":0,
    "gn:timezone":"Europe/Moscow",
    "iso:country":"RU",
    "name:rus_x_preferred":[
        "\u0411\u043e\u043b\u044c\u0448\u0438\u0435 \u041a\u0438\u043b\u0438\u043c\u0430\u0440\u044b"
    ],
    "name:und_x_variant":[
        "Bol\u2019shiye Kilemary",
        "Bol\u2019shiye Kilimary",
        "\u0411\u043e\u043b\u044c\u0448\u0438\u0435 \u041a\u0438\u043b\u0438\u043c\u0430\u0440\u044b",
        "Bol\u2019shiye Killimary"
    ],
    "wof:name":"Bol'shiye Kilimary",
    "wof:placetype":"locality"
},
  "geometry": {"coordinates":[46.40116,57.06311],"type":"Point"}
}