{
  "type": "Feature",
  "properties": {
    "gn:admin1_code":"77",
    "gn:asciiname":"Rucheyek",
    "gn:country_code":"RU",
    "gn:dem":187,
    "gn:feature_class":"P",
    "gn:feature_code":"PPL",
    "gn:name":"Ruchey\u00ebk",
    "gn:population":0,
    "gn:timezone":"Europe/Moscow",
    "iso:country":"RU",
    "name:rus_x_preferred":[
        "\u0420\u0443\u0447\u0435\u0451\u043a"
    ],
    "name:und_x_variant":[
        "Ruchey\u00ebk",
        "\u0420\u0443\u0447\u0435\u0451\u043a"
    ],
    "wof:name":"Rucheyek",
    "wof:placetype":"locality"
},
  "geometry": {"coordinates":[32.73722,55.96111],"type":"Point"}
}