{
  "type": "Feature",
  "properties": {
    "gn:admin1_code":"8",
    "gn:asciiname":"Penza",
    "gn:country_code":"RU",
    "gn:dem":112,
    "gn:feature_class":"P",
    "gn:feature_code":"PPL",
    "gn:name":"Penza",
    "gn:population":0,
    "gn:timezone":"Asia/Yekaterinburg",
    "iso:country":"RU",
    "name:rus_x_preferred":[
        "\u041f\u0435\u043d\u0437\u0430"
    ],
    "name:und_x_variant":[
        "\u041f\u0435\u043d\u0437\u0430"
    ],
    "wof:name":"Penza",
    "wof:placetype":"locality"
},
  "geometry": {"coordinates":[55.31632,54.44414],"type":"Point"}
}