{
  "type": "Feature",
  "properties": {
    "gn:admin1_code":"37",
    "gn:asciiname":"Marinenki",
    "gn:country_code":"RU",
    "gn:dem":169,
    "gn:feature_class":"P",
    "gn:feature_code":"PPL",
    "gn:name":"Marinenki",
    "gn:population":0,
    "gn:timezone":"Europe/Moscow",
    "iso:country":"RU",
    "name:rus_x_preferred":[
        "\u041c\u0430\u0440\u0438\u043d\u0435\u043d\u043a\u0438"
    ],
    "wof:name":"Marinenki",
    "wof:placetype":"locality"
},
  "geometry": {"coordinates":[46.6439,59.0758],"type":"Point"}
}