{
  "type": "Feature",
  "properties": {
    "gn:admin1_code":"25",
    "gn:asciiname":"Kositsk",
    "gn:country_code":"RU",
    "gn:dem":195,
    "gn:feature_class":"P",
    "gn:feature_code":"PPL",
    "gn:name":"Kositsk",
    "gn:population":0,
    "gn:timezone":"Europe/Moscow",
    "iso:country":"RU",
    "name:rus_x_preferred":[
        "\u041a\u043e\u0441\u0438\u0446\u043a"
    ],
    "wof:name":"Kositsk",
    "wof:placetype":"locality"
},
  "geometry": {"coordinates":[35.65755,55.08241],"type":"Point"}
}