{
  "type": "Feature",
  "properties": {
    "gn:admin1_code":"17",
    "gn:asciiname":"L'vovskiy Nomer Chetyrnadtsat'",
    "gn:country_code":"RU",
    "gn:dem":-22,
    "gn:feature_class":"P",
    "gn:feature_code":"PPL",
    "gn:name":"L\u2019vovskiy Nomer Chetyrnadtsat\u2019",
    "gn:population":0,
    "gn:timezone":"Europe/Moscow",
    "iso:country":"RU",
    "name:rus_x_preferred":[
        "\u041b\u044c\u0432\u043e\u0432\u0441\u043a\u0438\u0439 \u041d\u043e\u043c\u0435\u0440 \u0427\u0435\u0442\u044b\u0440\u043d\u0430\u0434\u0446\u0430\u0442\u044c"
    ],
    "name:und_x_variant":[
        "L\u2019vovskiy Chetyrnadtsatyy",
        "L\u2019vovskiy Nomer Chetyrnadtsat\u2019"
    ],
    "wof:name":"L'vovskiy Nomer Chetyrnadtsat'",
    "wof:placetype":"locality"
},
  "geometry": {"coordinates":[47.3215,43.48179],"type":"Point"}
}