{
  "type": "Feature",
  "properties": {
    "gn:admin1_code":"20",
    "gn:asciiname":"Alekhino",
    "gn:country_code":"RU",
    "gn:dem":563,
    "gn:feature_class":"P",
    "gn:feature_code":"PPL",
    "gn:name":"Al\u00ebkhino",
    "gn:population":0,
    "gn:timezone":"Asia/Irkutsk",
    "iso:country":"RU",
    "name:eng_x_preferred":[
        "Alekhino"
    ],
    "name:nor_x_preferred":[
        "Alekhino"
    ],
    "name:rus_x_preferred":[
        "\u0410\u043b\u0451\u0445\u0438\u043d\u043e"
    ],
    "name:und_x_variant":[
        "Al\u00ebkhina",
        "Al\u00ebkhino"
    ],
    "wof:name":"Alekhino",
    "wof:placetype":"locality"
},
  "geometry": {"coordinates":[103.1343,53.0741],"type":"Point"}
}