{
  "type": "Feature",
  "properties": {
    "gn:admin1_code":"60",
    "gn:asciiname":"Naumovshchina",
    "gn:country_code":"RU",
    "gn:dem":91,
    "gn:feature_class":"P",
    "gn:feature_code":"PPL",
    "gn:name":"Naumovshchina",
    "gn:population":0,
    "gn:timezone":"Europe/Moscow",
    "iso:country":"RU",
    "name:eng_x_preferred":[
        "Naumovshchina"
    ],
    "name:nor_x_preferred":[
        "Naumovsjtsjina"
    ],
    "name:rus_x_preferred":[
        "\u041d\u0430\u0443\u043c\u043e\u0432\u0449\u0438\u043d\u0430"
    ],
    "wof:name":"Naumovshchina",
    "wof:placetype":"locality"
},
  "geometry": {"coordinates":[28.34316,58.36781],"type":"Point"}
}