{
  "type": "Feature",
  "properties": {
    "gn:admin1_code":"40",
    "gn:asciiname":"Borovichi",
    "gn:country_code":"RU",
    "gn:dem":170,
    "gn:feature_class":"P",
    "gn:feature_code":"PPL",
    "gn:name":"Borovichi",
    "gn:population":0,
    "gn:timezone":"Asia/Yekaterinburg",
    "iso:country":"RU",
    "name:eng_x_preferred":[
        "Borovichi"
    ],
    "name:nor_x_preferred":[
        "Borovoje"
    ],
    "name:rus_x_preferred":[
        "\u0411\u043e\u0440\u043e\u0432\u043e\u0435"
    ],
    "name:rus_x_variant":[
        "\u0411\u043e\u0440\u043e\u0432\u0438\u0447\u0438"
    ],
    "name:und_x_variant":[
        "Borovoye",
        "Borovichi",
        "\u0411\u043e\u0440\u043e\u0432\u0438\u0447\u0438"
    ],
    "wof:name":"Borovichi",
    "wof:placetype":"locality"
},
  "geometry": {"coordinates":[62.5738,55.0622],"type":"Point"}
}