{
  "type": "Feature",
  "properties": {
    "gn:admin1_code":"40",
    "gn:asciiname":"Borovichi",
    "gn:country_code":"RU",
    "gn:dem":170,
    "gn:feature_class":"P",
    "gn:feature_code":"PPL",
    "gn:name":"Borovichi",
    "gn:population":0,
    "gn:timezone":"Asia/Yekaterinburg",
    "iso:country":"RU",
    "name:ara_x_preferred":[
        "\u0628\u0648\u0631\u0648\u0641\u064a\u062a\u0634\u064a"
    ],
    "name:azb_x_preferred":[
        "\u0628\u0648\u0631\u0648\u0648\u06cc\u0686\u06cc"
    ],
    "name:aze_x_preferred":[
        "Borovi\u00e7i"
    ],
    "name:bel_x_preferred":[
        "\u0411\u0430\u0440\u0430\u0432\u0456\u0447\u044b"
    ],
    "name:bul_x_preferred":[
        "\u0411\u043e\u0440\u043e\u0432\u0438\u0447\u0438"
    ],
    "name:ceb_x_preferred":[
        "Borovichi"
    ],
    "name:ces_x_preferred":[
        "Borovi\u010di"
    ],
    "name:deu_x_preferred":[
        "Borowitschi"
    ],
    "name:eng_x_preferred":[
        "Borovichi"
    ],
    "name:epo_x_preferred":[
        "Borovi\u0109i"
    ],
    "name:est_x_preferred":[
        "Borovit\u0161i"
    ],
    "name:fas_x_preferred":[
        "\u0628\u0648\u0631\u0648\u0648\u06cc\u0686\u06cc"
    ],
    "name:fin_x_preferred":[
        "Borovit\u0161i"
    ],
    "name:fra_x_preferred":[
        "Borovitchi"
    ],
    "name:haw_x_preferred":[
        "W\u016blowini"
    ],
    "name:hsb_x_preferred":[
        "Borowi\u010di"
    ],
    "name:ita_x_preferred":[
        "Borovi\u010di"
    ],
    "name:jpn_x_preferred":[
        "\u30dc\u30ed\u30f4\u30a3\u30c1"
    ],
    "name:kor_x_preferred":[
        "\ubcf4\ub85c\ube44\uce58"
    ],
    "name:lav_x_preferred":[
        "Borovi\u010di"
    ],
    "name:lit_x_preferred":[
        "Borovi\u010diai"
    ],
    "name:mkd_x_preferred":[
        "\u0411\u043e\u0440\u043e\u0432\u0438\u0447\u0438"
    ],
    "name:nld_x_preferred":[
        "Borovitsji"
    ],
    "name:nno_x_preferred":[
        "Borovitsji"
    ],
    "name:nor_x_preferred":[
        "Borovoje"
    ],
    "name:nor_x_variant":[
        "Borovitsji"
    ],
    "name:pnb_x_preferred":[
        "\u0628\u0648\u0631\u0648\u0648\u06cc\u0686\u06cc"
    ],
    "name:pol_x_preferred":[
        "Borowicze"
    ],
    "name:por_x_preferred":[
        "Borovich\u00ed"
    ],
    "name:ron_x_preferred":[
        "Borovici"
    ],
    "name:rus_x_preferred":[
        "\u0411\u043e\u0440\u043e\u0432\u043e\u0435"
    ],
    "name:rus_x_variant":[
        "\u0411\u043e\u0440\u043e\u0432\u0438\u0447\u0438"
    ],
    "name:spa_x_preferred":[
        "Borovich\u00ed"
    ],
    "name:srp_x_preferred":[
        "\u0411\u043e\u0440\u043e\u0432\u0438\u0447\u0438"
    ],
    "name:swe_x_preferred":[
        "Borovitji"
    ],
    "name:tat_x_preferred":[
        "\u0411\u043e\u0440\u043e\u0432\u0438\u0447\u0438"
    ],
    "name:tgl_x_preferred":[
        "Borovichi"
    ],
    "name:ukr_x_preferred":[
        "\u0411\u043e\u0440\u043e\u0432\u0438\u0447\u0456"
    ],
    "name:und_x_variant":[
        "Borovoye"
    ],
    "name:vep_x_preferred":[
        "Borovi\u010di"
    ],
    "name:vie_x_preferred":[
        "Borovichi"
    ],
    "name:war_x_preferred":[
        "Borovichi"
    ],
    "name:zho_x_preferred":[
        "\u535a\u7f85\u7dad\u5947"
    ],
    "wof:name":"Borovichi",
    "wof:placetype":"locality"
},
  "geometry": {"coordinates":[62.5738,55.0622],"type":"Point"}
}