{
  "type": "Feature",
  "properties": {
    "gn:admin1_code":"86",
    "gn:asciiname":"Sud'yevka-Nikolayevka",
    "gn:country_code":"RU",
    "gn:dem":90,
    "gn:feature_class":"P",
    "gn:feature_code":"PPL",
    "gn:name":"Sud\u2019yevka-Nikolayevka",
    "gn:population":0,
    "gn:timezone":"Europe/Moscow",
    "iso:country":"RU",
    "name:rus_x_preferred":[
        "\u0421\u0443\u0434\u044c\u0435\u0432\u043a\u0430-\u041d\u0438\u043a\u043e\u043b\u0430\u0435\u0432\u043a\u0430"
    ],
    "name:und_x_variant":[
        "Nikolayevka",
        "Sud-Nikolayevka",
        "Sud\u2019yevka-Nikolayevka",
        "\u0421\u0443\u0434\u044c\u0435\u0432\u043a\u0430-\u041d\u0438\u043a\u043e\u043b\u0430\u0435\u0432\u043a\u0430"
    ],
    "wof:name":"Sud'yevka-Nikolayevka",
    "wof:placetype":"locality"
},
  "geometry": {"coordinates":[39.61115,50.35633],"type":"Point"}
}