{
  "type": "Feature",
  "properties": {
    "gn:admin1_code":"33",
    "gn:asciiname":"Volokovyye",
    "gn:country_code":"RU",
    "gn:dem":179,
    "gn:feature_class":"P",
    "gn:feature_code":"PPL",
    "gn:name":"Volokovyye",
    "gn:population":0,
    "gn:timezone":"Europe/Kirov",
    "iso:country":"RU",
    "name:eng_x_preferred":[
        "Volokovyye"
    ],
    "name:nor_x_preferred":[
        "Volokovye"
    ],
    "name:rus_x_preferred":[
        "\u0412\u043e\u043b\u043e\u043a\u043e\u0432\u044b\u0435"
    ],
    "name:und_x_variant":[
        "Volkovskaya",
        "Volokovyye"
    ],
    "wof:name":"Volokovyye",
    "wof:placetype":"locality"
},
  "geometry": {"coordinates":[52.3518,59.08998],"type":"Point"}
}