{
  "type": "Feature",
  "properties": {
    "gn:admin1_code":"45.0",
    "gn:asciiname":"Kozhlanger",
    "gn:country_code":"RU",
    "gn:dem":82,
    "gn:feature_class":"P",
    "gn:feature_code":"PPL",
    "gn:name":"Kozhlanger",
    "gn:population":0,
    "gn:timezone":"Europe/Moscow",
    "iso:country":"RU",
    "name:rus_x_preferred":[
        "\u041a\u043e\u0436\u043b\u0430\u043d\u0433\u0435\u0440"
    ],
    "wof:name":"Kozhlanger",
    "wof:placetype":"locality"
},
  "geometry": {"coordinates":[48.35667,56.20444000000001],"type":"Point"}
}