{
  "type": "Feature",
  "properties": {
    "gn:admin1_code":"51.0",
    "gn:asciiname":"Bab'ye",
    "gn:country_code":"RU",
    "gn:dem":89,
    "gn:feature_class":"P",
    "gn:feature_code":"PPL",
    "gn:name":"Bab\u2019ye",
    "gn:population":0,
    "gn:timezone":"Europe/Moscow",
    "iso:country":"RU",
    "name:nor_x_preferred":[
        "Babje"
    ],
    "name:rus_x_preferred":[
        "\u0411\u0430\u0431\u044c\u0435"
    ],
    "name:und_x_variant":[
        "Bol\u2019shoye Bab\u2019ye",
        "Bab\u2019ye"
    ],
    "wof:name":"Bab'ye",
    "wof:placetype":"locality"
},
  "geometry": {"coordinates":[43.36126,57.07344000000001],"type":"Point"}
}