{
  "type": "Feature",
  "properties": {
    "gn:admin1_code":"9",
    "gn:asciiname":"Russkaya Berezovka",
    "gn:country_code":"RU",
    "gn:dem":171,
    "gn:feature_class":"P",
    "gn:feature_code":"PPL",
    "gn:name":"Russkaya Ber\u00ebzovka",
    "gn:population":0,
    "gn:timezone":"Europe/Moscow",
    "iso:country":"RU",
    "name:rus_x_preferred":[
        "\u0420\u0443\u0441\u0441\u043a\u0430\u044f \u0411\u0435\u0440\u0451\u0437\u043e\u0432\u043a\u0430"
    ],
    "name:und_x_variant":[
        "Russkaya Ber\u00ebzovka",
        "\u0420\u0443\u0441\u0441\u043a\u0430\u044f \u0411\u0435\u0440\u0451\u0437\u043e\u0432\u043a\u0430"
    ],
    "wof:name":"Russkaya Berezovka",
    "wof:placetype":"locality"
},
  "geometry": {"coordinates":[35.7393,50.6723],"type":"Point"}
}