{
  "type": "Feature",
  "properties": {
    "gn:admin1_code":"43",
    "gn:asciiname":"Donskoye Vtoroye",
    "gn:country_code":"RU",
    "gn:dem":119,
    "gn:feature_class":"P",
    "gn:feature_code":"PPL",
    "gn:name":"Donskoye Vtoroye",
    "gn:population":0,
    "gn:timezone":"Europe/Moscow",
    "iso:country":"RU",
    "name:rus_x_preferred":[
        "\u0414\u043e\u043d\u0441\u043a\u043e\u0435 \u0412\u0442\u043e\u0440\u043e\u0435"
    ],
    "name:und_x_variant":[
        "\u0414\u043e\u043d\u0441\u043a\u043e\u0435 \u0412\u0442\u043e\u0440\u043e\u0435",
        "Vtoroye Donskoye"
    ],
    "wof:name":"Donskoye Vtoroye",
    "wof:placetype":"locality"
},
  "geometry": {"coordinates":[38.97,52.7865],"type":"Point"}
}