{
  "type": "Feature",
  "properties": {
    "gn:admin1_code":"77",
    "gn:asciiname":"Toporovo",
    "gn:country_code":"RU",
    "gn:dem":206,
    "gn:feature_class":"P",
    "gn:feature_code":"PPL",
    "gn:name":"Toporovo",
    "gn:population":0,
    "gn:timezone":"Europe/Moscow",
    "iso:country":"RU",
    "name:rus_x_preferred":[
        "\u0422\u043e\u043f\u043e\u0440\u043e\u0432\u043e"
    ],
    "wof:name":"Toporovo",
    "wof:placetype":"locality"
},
  "geometry": {"coordinates":[36.71237,58.38709],"type":"Point"}
}