{
  "type": "Feature",
  "properties": {
    "gn:admin1_code":"88",
    "gn:asciiname":"Savel'yevo",
    "gn:country_code":"RU",
    "gn:dem":127,
    "gn:feature_class":"P",
    "gn:feature_code":"PPL",
    "gn:name":"Savel\u2019yevo",
    "gn:population":0,
    "gn:timezone":"Europe/Moscow",
    "iso:country":"RU",
    "name:rus_x_preferred":[
        "\u0421\u0430\u0432\u0435\u043b\u044c\u0435\u0432\u043e"
    ],
    "name:und_x_variant":[
        "Savel\u2019yevo"
    ],
    "wof:name":"Savel'yevo",
    "wof:placetype":"locality"
},
  "geometry": {"coordinates":[38.3271,57.6376],"type":"Point"}
}