{
  "type": "Feature",
  "properties": {
    "gn:admin1_code":"38",
    "gn:asciiname":"Novovladimirovskaya",
    "gn:country_code":"RU",
    "gn:dem":54,
    "gn:feature_class":"P",
    "gn:feature_code":"PPL",
    "gn:name":"Novovladimirovskaya",
    "gn:population":0,
    "gn:timezone":"Europe/Moscow",
    "iso:country":"RU",
    "name:rus_x_preferred":[
        "\u041d\u043e\u0432\u043e\u0432\u043b\u0430\u0434\u0438\u043c\u0438\u0440\u043e\u0432\u0441\u043a\u0430\u044f"
    ],
    "name:und_x_variant":[
        "Novovladimirovskiye",
        "Novovladimirovskaya"
    ],
    "wof:name":"Novovladimirovskaya",
    "wof:placetype":"locality"
},
  "geometry": {"coordinates":[40.0935,45.5469],"type":"Point"}
}