{
  "type": "Feature",
  "properties": {
    "gn:admin1_code":"6",
    "gn:asciiname":"Krivoye",
    "gn:country_code":"RU",
    "gn:dem":3,
    "gn:feature_class":"P",
    "gn:feature_code":"PPL",
    "gn:name":"Krivoye",
    "gn:population":0,
    "gn:timezone":"Europe/Moscow",
    "iso:country":"RU",
    "name:rus_x_preferred":[
        "\u041a\u0440\u0438\u0432\u043e\u0435"
    ],
    "name:und_x_variant":[
        "\u041a\u0440\u0438\u0432\u043e\u0435"
    ],
    "wof:name":"Krivoye",
    "wof:placetype":"locality"
},
  "geometry": {"coordinates":[41.61778,63.90416],"type":"Point"}
}