{
  "type": "Feature",
  "properties": {
    "gn:admin1_code":"20",
    "gn:asciiname":"Korshunovskiy",
    "gn:country_code":"RU",
    "gn:dem":512,
    "gn:feature_class":"P",
    "gn:feature_code":"PPL",
    "gn:name":"Korshunovskiy",
    "gn:population":0,
    "gn:timezone":"Asia/Irkutsk",
    "iso:country":"RU",
    "name:rus_x_preferred":[
        "\u041a\u043e\u0440\u0448\u0443\u043d\u043e\u0432\u0441\u043a\u0438\u0439"
    ],
    "wof:name":"Korshunovskiy",
    "wof:placetype":"locality"
},
  "geometry": {"coordinates":[104.19410000000001,56.4898],"type":"Point"}
}