{
  "type": "Feature",
  "properties": {
    "gn:admin1_code":"25.0",
    "gn:asciiname":"Bukrino",
    "gn:country_code":"RU",
    "gn:dem":171,
    "gn:feature_class":"P",
    "gn:feature_code":"PPL",
    "gn:name":"Bukrino",
    "gn:population":0,
    "gn:timezone":"Europe/Moscow",
    "iso:country":"RU",
    "name:nor_x_preferred":[
        "Bukrino"
    ],
    "name:rus_x_preferred":[
        "\u0411\u0443\u043a\u0440\u0438\u043d\u043e"
    ],
    "wof:name":"Bukrino",
    "wof:placetype":"locality"
},
  "geometry": {"coordinates":[36.22316,54.79437],"type":"Point"}
}