{
  "type": "Feature",
  "properties": {
    "gn:admin1_code":"86",
    "gn:asciiname":"Studenovka",
    "gn:country_code":"RU",
    "gn:dem":158,
    "gn:feature_class":"P",
    "gn:feature_code":"PPL",
    "gn:name":"Stud\u00ebnovka",
    "gn:population":0,
    "gn:timezone":"Europe/Moscow",
    "iso:country":"RU",
    "name:rus_x_preferred":[
        "\u0421\u0442\u0443\u0434\u0451\u043d\u043e\u0432\u043a\u0430"
    ],
    "name:und_x_variant":[
        "Stud\u00ebnoye",
        "Stud\u00ebnovka"
    ],
    "wof:name":"Studenovka",
    "wof:placetype":"locality"
},
  "geometry": {"coordinates":[38.9613,51.7707],"type":"Point"}
}