{
  "type": "Feature",
  "properties": {
    "gn:admin1_code":"80",
    "gn:asciiname":"Sundoshur",
    "gn:country_code":"RU",
    "gn:dem":179,
    "gn:feature_class":"P",
    "gn:feature_code":"PPL",
    "gn:name":"Sundoshur",
    "gn:population":0,
    "gn:timezone":"Europe/Samara",
    "iso:country":"RU",
    "name:rus_x_preferred":[
        "\u0421\u0443\u043d\u0434\u043e\u0448\u0443\u0440"
    ],
    "wof:name":"Sundoshur",
    "wof:placetype":"locality"
},
  "geometry": {"coordinates":[53.003,57.5188],"type":"Point"}
}