{
  "type": "Feature",
  "properties": {
    "gn:admin1_code":"45",
    "gn:asciiname":"Yel'nikovo",
    "gn:country_code":"RU",
    "gn:dem":113,
    "gn:feature_class":"P",
    "gn:feature_code":"PPL",
    "gn:name":"Yel\u2019nikovo",
    "gn:population":0,
    "gn:timezone":"Europe/Moscow",
    "iso:country":"RU",
    "name:rus_x_preferred":[
        "\u0415\u043b\u044c\u043d\u0438\u043a\u043e\u0432\u043e"
    ],
    "name:und_x_variant":[
        "Yel\u2019nikovo",
        "\u0415\u043b\u044c\u043d\u0438\u043a\u043e\u0432\u043e"
    ],
    "wof:name":"Yel'nikovo",
    "wof:placetype":"locality"
},
  "geometry": {"coordinates":[46.6514,56.1917],"type":"Point"}
}