{
  "type": "Feature",
  "properties": {
    "gn:admin1_code":"63",
    "gn:asciiname":"Bulun",
    "gn:country_code":"RU",
    "gn:dem":155,
    "gn:feature_class":"P",
    "gn:feature_code":"PPL",
    "gn:name":"Bulun",
    "gn:population":0,
    "gn:timezone":"Asia/Yakutsk",
    "iso:country":"RU",
    "name:eng_x_preferred":[
        "Bulun"
    ],
    "name:nor_x_preferred":[
        "Bulun"
    ],
    "name:rus_x_preferred":[
        "\u0411\u0443\u043b\u0443\u043d"
    ],
    "wof:name":"Bulun",
    "wof:placetype":"locality"
},
  "geometry": {"coordinates":[131.60326000000001,60.68968],"type":"Point"}
}