{
  "type": "Feature",
  "properties": {
    "gn:admin1_code":"84",
    "gn:asciiname":"Koldair",
    "gn:country_code":"RU",
    "gn:dem":41,
    "gn:feature_class":"P",
    "gn:feature_code":"PPL",
    "gn:name":"Koldair",
    "gn:population":0,
    "gn:timezone":"Europe/Volgograd",
    "iso:country":"RU",
    "name:rus_x_preferred":[
        "\u041a\u043e\u043b\u0434\u0430\u0438\u0440"
    ],
    "name:und_x_variant":[
        "\u041a\u043e\u043b\u0434\u0430\u0438\u0440"
    ],
    "wof:name":"Koldair",
    "wof:placetype":"locality"
},
  "geometry": {"coordinates":[43.78333,49.25],"type":"Point"}
}