{
  "type": "Feature",
  "properties": {
    "gn:admin1_code":"52",
    "gn:asciiname":"Oboronevo",
    "gn:country_code":"RU",
    "gn:dem":199,
    "gn:feature_class":"P",
    "gn:feature_code":"PPL",
    "gn:name":"Oboronevo",
    "gn:population":0,
    "gn:timezone":"Europe/Moscow",
    "iso:country":"RU",
    "name:rus_x_preferred":[
        "\u041e\u0431\u043e\u0440\u043e\u043d\u0435\u0432\u043e"
    ],
    "name:rus_x_variant":[
        "\u041e\u0431\u043e\u0440\u043d\u0435\u0432\u043e"
    ],
    "name:und_x_variant":[
        "\u041e\u0431\u043e\u0440\u043e\u043d\u0435\u0432\u043e",
        "Obornevo",
        "\u041e\u0431\u043e\u0440\u043d\u0435\u0432\u043e"
    ],
    "wof:name":"Oboronevo",
    "wof:placetype":"locality"
},
  "geometry": {"coordinates":[35.47345,58.63686],"type":"Point"}
}