{
  "type": "Feature",
  "properties": {
    "gn:admin1_code":"69",
    "gn:asciiname":"Martynovo",
    "gn:country_code":"RU",
    "gn:dem":191,
    "gn:feature_class":"P",
    "gn:feature_code":"PPL",
    "gn:name":"Martynovo",
    "gn:population":0,
    "gn:timezone":"Europe/Moscow",
    "iso:country":"RU",
    "name:bak_x_preferred":[
        "\u041c\u0430\u0440\u0442\u044b\u043d\u043e\u0432"
    ],
    "name:che_x_preferred":[
        "\u041c\u0430\u0440\u0442\u044b\u043d\u043e\u0432\u043e"
    ],
    "name:hye_x_preferred":[
        "\u0544\u0561\u0580\u057f\u056b\u0576\u0578\u057e\u0578"
    ],
    "name:kaz_x_preferred":[
        "\u041c\u0430\u0440\u0442\u044b\u043d"
    ],
    "name:kir_x_preferred":[
        "\u041c\u0430\u0440\u0442\u044b\u043d"
    ],
    "name:rus_x_preferred":[
        "\u041c\u0430\u0440\u0442\u044b\u043d\u043e\u0432\u043e"
    ],
    "name:tat_x_preferred":[
        "\u041c\u0430\u0440\u0442\u044b\u043d\u043e\u0432\u043e"
    ],
    "name:ukr_x_preferred":[
        "\u041c\u0430\u0440\u0442\u0438\u043d\u043e\u0432\u043e"
    ],
    "name:und_x_variant":[
        "\u041c\u0430\u0440\u0442\u044b\u043d\u043e\u0432\u043e"
    ],
    "wof:name":"Martynovo",
    "wof:placetype":"locality"
},
  "geometry": {"coordinates":[33.01667,55.51667],"type":"Point"}
}