{
  "type": "Feature",
  "properties": {
    "gn:admin1_code":"20.0",
    "gn:asciiname":"Tochil'nyy",
    "gn:country_code":"RU",
    "gn:dem":384,
    "gn:feature_class":"P",
    "gn:feature_code":"PPL",
    "gn:name":"Tochil\u2019nyy",
    "gn:population":0,
    "gn:timezone":"Asia/Irkutsk",
    "iso:country":"RU",
    "name:rus_x_preferred":[
        "\u0422\u043e\u0447\u0438\u043b\u044c\u043d\u044b\u0439"
    ],
    "name:und_x_variant":[
        "Tochil\u2019nyy"
    ],
    "wof:name":"Tochil'nyy",
    "wof:placetype":"locality"
},
  "geometry": {"coordinates":[97.425,56.0813],"type":"Point"}
}