{
  "type": "Feature",
  "properties": {
    "gn:admin1_code":"71",
    "gn:asciiname":"Kolchedan",
    "gn:country_code":"RU",
    "gn:dem":139,
    "gn:feature_class":"P",
    "gn:feature_code":"PPL",
    "gn:name":"Kolchedan",
    "gn:population":0,
    "gn:timezone":"Asia/Yekaterinburg",
    "iso:country":"RU",
    "name:eng_x_preferred":[
        "Kolchedan"
    ],
    "name:nor_x_preferred":[
        "Koltsjedan"
    ],
    "name:rus_x_preferred":[
        "\u041a\u043e\u043b\u0447\u0435\u0434\u0430\u043d"
    ],
    "wof:name":"Kolchedan",
    "wof:placetype":"locality"
},
  "geometry": {"coordinates":[62.1944,56.369],"type":"Point"}
}