{
  "type": "Feature",
  "properties": {
    "gn:admin1_code":"56",
    "gn:asciiname":"Uspenskiy",
    "gn:country_code":"RU",
    "gn:dem":202,
    "gn:feature_class":"P",
    "gn:feature_code":"PPL",
    "gn:name":"Uspenskiy",
    "gn:population":0,
    "gn:timezone":"Europe/Moscow",
    "iso:country":"RU",
    "wof:name":"Uspenskiy",
    "wof:placetype":"locality"
},
  "geometry": {"coordinates":[34.92,52.80889000000001],"type":"Point"}
}