{
  "type": "Feature",
  "properties": {
    "gn:admin1_code":"46",
    "gn:asciiname":"Nerley",
    "gn:country_code":"RU",
    "gn:dem":195,
    "gn:feature_class":"P",
    "gn:feature_code":"PPL",
    "gn:name":"Nerley",
    "gn:population":0,
    "gn:timezone":"Europe/Moscow",
    "iso:country":"RU",
    "name:rus_x_preferred":[
        "\u041d\u0435\u0440\u043b\u0435\u0439"
    ],
    "name:und_x_variant":[
        "\u041d\u0435\u0440\u043b\u0435\u0439"
    ],
    "wof:name":"Nerley",
    "wof:placetype":"locality"
},
  "geometry": {"coordinates":[45.70065,54.07705],"type":"Point"}
}