{
  "type": "Feature",
  "properties": {
    "gn:admin1_code":"55",
    "gn:asciiname":"Starokul'sharipovo",
    "gn:country_code":"RU",
    "gn:dem":177,
    "gn:feature_class":"P",
    "gn:feature_code":"PPL",
    "gn:name":"Starokul\u2019sharipovo",
    "gn:population":0,
    "gn:timezone":"Asia/Yekaterinburg",
    "iso:country":"RU",
    "name:eng_x_preferred":[
        "Starokul'sharipovo"
    ],
    "name:nor_x_preferred":[
        "Starokulsjaripovo"
    ],
    "name:rus_x_preferred":[
        "\u0421\u0442\u0430\u0440\u043e\u043a\u0443\u043b\u044c\u0448\u0430\u0440\u0438\u043f\u043e\u0432\u043e"
    ],
    "name:und_x_variant":[
        "Staroye Kul\u2019sharypovo",
        "Starokul\u2019sharipovo"
    ],
    "wof:name":"Starokul'sharipovo",
    "wof:placetype":"locality"
},
  "geometry": {"coordinates":[53.05,53.48333],"type":"Point"}
}