{
  "type": "Feature",
  "properties": {
    "gn:admin1_code":"85",
    "gn:asciiname":"Telibanovo",
    "gn:country_code":"RU",
    "gn:dem":163,
    "gn:feature_class":"P",
    "gn:feature_code":"PPL",
    "gn:name":"Telibanovo",
    "gn:population":0,
    "gn:timezone":"Europe/Moscow",
    "iso:country":"RU",
    "name:rus_x_preferred":[
        "\u0422\u0435\u043b\u0438\u0431\u0430\u043d\u043e\u0432\u043e"
    ],
    "wof:name":"Telibanovo",
    "wof:placetype":"locality"
},
  "geometry": {"coordinates":[38.7804,59.4321],"type":"Point"}
}