{
  "type": "Feature",
  "properties": {
    "gn:admin1_code":"38.0",
    "gn:asciiname":"Krasnoselovka",
    "gn:country_code":"RU",
    "gn:dem":63,
    "gn:feature_class":"P",
    "gn:feature_code":"PPL",
    "gn:name":"Krasnoselovka",
    "gn:population":0,
    "gn:timezone":"Europe/Moscow",
    "iso:country":"RU",
    "name:rus_x_preferred":[
        "\u041a\u0440\u0430\u0441\u043d\u043e\u0441\u0435\u043b\u043e\u0432\u043a\u0430"
    ],
    "wof:name":"Krasnoselovka",
    "wof:placetype":"locality"
},
  "geometry": {"coordinates":[40.03556,45.10056],"type":"Point"}
}