{
  "type": "Feature",
  "properties": {
    "gn:admin1_code":"77",
    "gn:asciiname":"Sandyrevo",
    "gn:country_code":"RU",
    "gn:dem":129,
    "gn:feature_class":"P",
    "gn:feature_code":"PPL",
    "gn:name":"Sandyrevo",
    "gn:population":0,
    "gn:timezone":"Europe/Moscow",
    "iso:country":"RU",
    "name:rus_x_preferred":[
        "\u0421\u0430\u043d\u0434\u044b\u0440\u0435\u0432\u043e"
    ],
    "wof:name":"Sandyrevo",
    "wof:placetype":"locality"
},
  "geometry": {"coordinates":[37.9206,57.0367],"type":"Point"}
}