{
  "type": "Feature",
  "properties": {
    "gn:admin1_code":"52",
    "gn:asciiname":"Kachanovo",
    "gn:country_code":"RU",
    "gn:dem":81,
    "gn:feature_class":"P",
    "gn:feature_code":"PPL",
    "gn:name":"Kachanovo",
    "gn:population":0,
    "gn:timezone":"Europe/Moscow",
    "iso:country":"RU",
    "name:rus_x_preferred":[
        "\u041a\u0430\u0447\u0430\u043d\u043e\u0432\u043e"
    ],
    "name:und_x_variant":[
        "\u041a\u0430\u0447\u0430\u043d\u043e\u0432\u043e"
    ],
    "wof:name":"Kachanovo",
    "wof:placetype":"locality"
},
  "geometry": {"coordinates":[30.76667,56.95],"type":"Point"}
}