{
  "type": "Feature",
  "properties": {
    "gn:admin1_code":"80",
    "gn:asciiname":"Logovo",
    "gn:country_code":"RU",
    "gn:dem":217,
    "gn:feature_class":"P",
    "gn:feature_code":"PPL",
    "gn:name":"Logovo",
    "gn:population":0,
    "gn:timezone":"Europe/Samara",
    "iso:country":"RU",
    "name:rus_x_preferred":[
        "\u041b\u043e\u0433\u043e\u0432\u043e"
    ],
    "name:und_x_variant":[
        "\u041b\u043e\u0433\u043e\u0432\u043e"
    ],
    "wof:name":"Logovo",
    "wof:placetype":"locality"
},
  "geometry": {"coordinates":[52.23333,57.65],"type":"Point"}
}