{
  "type": "Feature",
  "properties": {
    "gn:admin1_code":"90.0",
    "gn:asciiname":"Konovalovo",
    "gn:country_code":"RU",
    "gn:dem":137,
    "gn:feature_class":"P",
    "gn:feature_code":"PPL",
    "gn:name":"Konovalovo",
    "gn:population":0,
    "gn:timezone":"Asia/Yekaterinburg",
    "iso:country":"RU",
    "name:rus_x_preferred":[
        "\u041a\u043e\u043d\u043e\u0432\u0430\u043b\u043e\u0432\u043e"
    ],
    "wof:name":"Konovalovo",
    "wof:placetype":"locality"
},
  "geometry": {"coordinates":[55.2419,58.6123],"type":"Point"}
}