{
  "type": "Feature",
  "properties": {
    "gn:admin1_code":"88",
    "gn:asciiname":"Byshnevo",
    "gn:country_code":"RU",
    "gn:dem":140,
    "gn:feature_class":"P",
    "gn:feature_code":"PPL",
    "gn:name":"Byshn\u00ebvo",
    "gn:population":0,
    "gn:timezone":"Europe/Moscow",
    "iso:country":"RU",
    "name:rus_x_preferred":[
        "\u0411\u044b\u0448\u043d\u0451\u0432\u043e"
    ],
    "name:und_x_variant":[
        "Byshn\u00ebvo",
        "\u0411\u044b\u0448\u043d\u0451\u0432\u043e"
    ],
    "wof:name":"Byshnevo",
    "wof:placetype":"locality"
},
  "geometry": {"coordinates":[37.7347,57.7956],"type":"Point"}
}