{
  "type": "Feature",
  "properties": {
    "gn:admin1_code":"93",
    "gn:asciiname":"Sharakhayeva",
    "gn:country_code":"RU",
    "gn:dem":730,
    "gn:feature_class":"P",
    "gn:feature_code":"PPL",
    "gn:name":"Sharakhayeva",
    "gn:population":0,
    "gn:timezone":"Asia/Chita",
    "iso:country":"RU",
    "name:rus_x_preferred":[
        "\u0428\u0430\u0440\u0430\u0445\u0430\u0435\u0432\u0430"
    ],
    "name:und_x_variant":[
        "\u0428\u0430\u0440\u0430\u0445\u0430\u0435\u0432\u0430"
    ],
    "wof:name":"Sharakhayeva",
    "wof:placetype":"locality"
},
  "geometry": {"coordinates":[117.01667,54.93333000000001],"type":"Point"}
}