{
  "type": "Feature",
  "properties": {
    "gn:admin1_code":"8.0",
    "gn:asciiname":"Changakul'",
    "gn:country_code":"RU",
    "gn:dem":170,
    "gn:feature_class":"P",
    "gn:feature_code":"PPL",
    "gn:name":"Changakul\u2019",
    "gn:population":0,
    "gn:timezone":"Asia/Yekaterinburg",
    "iso:country":"RU",
    "name:rus_x_preferred":[
        "\u0427\u0430\u043d\u0433\u0430\u043a\u0443\u043b\u044c"
    ],
    "name:und_x_variant":[
        "Changakul\u2019",
        "\u0427\u0430\u043d\u0433\u0430\u043a\u0443\u043b\u044c"
    ],
    "wof:name":"Changakul'",
    "wof:placetype":"locality"
},
  "geometry": {"coordinates":[54.5752,56.389],"type":"Point"}
}