{
  "type": "Feature",
  "properties": {
    "gn:admin1_code":"28",
    "gn:asciiname":"Purdega",
    "gn:country_code":"RU",
    "gn:dem":130,
    "gn:feature_class":"P",
    "gn:feature_code":"PPL",
    "gn:name":"Purdega",
    "gn:population":0,
    "gn:timezone":"Europe/Moscow",
    "iso:country":"RU",
    "name:fin_x_preferred":[
        "Purku"
    ],
    "name:rus_x_preferred":[
        "\u041f\u0443\u0440\u0434\u0435\u0433\u0430"
    ],
    "wof:name":"Purdega",
    "wof:placetype":"locality"
},
  "geometry": {"coordinates":[34.80605,62.45812],"type":"Point"}
}