{
  "type": "Feature",
  "properties": {
    "gn:admin1_code":"52",
    "gn:asciiname":"Radoni",
    "gn:country_code":"RU",
    "gn:dem":68,
    "gn:feature_class":"P",
    "gn:feature_code":"PPL",
    "gn:name":"Radoni",
    "gn:population":0,
    "gn:timezone":"Europe/Moscow",
    "iso:country":"RU",
    "name:rus_x_preferred":[
        "\u0420\u0430\u0434\u043e\u043d\u0438"
    ],
    "wof:name":"Radoni",
    "wof:placetype":"locality"
},
  "geometry": {"coordinates":[30.9996,58.8083],"type":"Point"}
}