{
  "type": "Feature",
  "properties": {
    "gn:country":"RU",
    "gn:fcode":"PPL",
    "gn:population":4070,
    "iso:country":"RU",
    "name:nor_x_preferred":[
        "Aknada"
    ],
    "name:rus_x_preferred":[
        "\u0410\u043a\u043d\u0430\u0434\u0430"
    ],
    "name:und_x_variant":[
        "Aknoda"
    ],
    "qs:name":"Aknada",
    "qs:photos_9r":0,
    "qs:photos_sr":0,
    "qs:pop_sr":"4",
    "wof:name":"Aknada",
    "wof:placetype":"locality",
    "wof:population":4070
},
  "geometry": {"coordinates":[46.17228,42.40155],"type":"Point"}
}