{
  "type": "Feature",
  "properties": {
    "gn:admin1_code":"77.0",
    "gn:asciiname":"Astakhovo",
    "gn:cc2":"RU",
    "gn:country_code":"RU",
    "gn:dem":192,
    "gn:feature_class":"P",
    "gn:feature_code":"PPL",
    "gn:name":"Astakhovo",
    "gn:population":0,
    "gn:timezone":"Europe/Moscow",
    "iso:country":"RU",
    "name:nor_x_preferred":[
        "Astakhovo"
    ],
    "name:rus_x_preferred":[
        "\u0410\u0441\u0442\u0430\u0445\u043e\u0432\u043e"
    ],
    "name:und_x_variant":[
        "Astakhova"
    ],
    "wof:name":"Astakhovo",
    "wof:placetype":"locality"
},
  "geometry": {"coordinates":[31.65,56.65],"type":"Point"}
}