{
  "type": "Feature",
  "properties": {
    "gn:admin1_code":"16.0",
    "gn:asciiname":"Anish-Bos'",
    "gn:country_code":"RU",
    "gn:dem":170,
    "gn:feature_class":"P",
    "gn:feature_code":"PPL",
    "gn:name":"Anish-Bos\u2019",
    "gn:population":0,
    "gn:timezone":"Europe/Moscow",
    "iso:country":"RU",
    "name:rus_x_preferred":[
        "\u0410\u043d\u0438\u0448-\u0411\u043e\u0441\u044c"
    ],
    "name:und_x_variant":[
        "Anish-Bos\u2019"
    ],
    "wof:name":"Anish-Bos'",
    "wof:placetype":"locality"
},
  "geometry": {"coordinates":[47.58333,55.86666999999999],"type":"Point"}
}