{
  "type": "Feature",
  "properties": {
    "gn:admin1_code":"38.0",
    "gn:asciiname":"Krasnaya Skala",
    "gn:country_code":"RU",
    "gn:dem":74,
    "gn:feature_class":"P",
    "gn:feature_code":"PPL",
    "gn:name":"Krasnaya Skala",
    "gn:population":0,
    "gn:timezone":"Europe/Moscow",
    "iso:country":"RU",
    "name:rus_x_preferred":[
        "\u041a\u0440\u0430\u0441\u043d\u0430\u044f \u0421\u043a\u0430\u043b\u0430"
    ],
    "name:und_x_variant":[
        "Vtoraya Pyatiletki",
        "Krasnaya Skala"
    ],
    "wof:name":"Krasnaya Skala",
    "wof:placetype":"locality"
},
  "geometry": {"coordinates":[37.38544,45.02316],"type":"Point"}
}