{
  "type": "Feature",
  "properties": {
    "gn:admin1_code":"85.0",
    "gn:asciiname":"Myshino",
    "gn:country_code":"RU",
    "gn:dem":179,
    "gn:feature_class":"P",
    "gn:feature_code":"PPL",
    "gn:name":"Myshino",
    "gn:population":0,
    "gn:timezone":"Europe/Moscow",
    "iso:country":"RU",
    "name:rus_x_preferred":[
        "\u041c\u044b\u0448\u0438\u043d\u043e"
    ],
    "wof:name":"Myshino",
    "wof:placetype":"locality"
},
  "geometry": {"coordinates":[39.3795,60.3909],"type":"Point"}
}