{
  "type": "Feature",
  "properties": {
    "gn:admin1_code":"7",
    "gn:asciiname":"Vyatskoye",
    "gn:country_code":"RU",
    "gn:dem":-26,
    "gn:feature_class":"P",
    "gn:feature_code":"PPL",
    "gn:name":"Vyatskoye",
    "gn:population":0,
    "gn:timezone":"Europe/Astrakhan",
    "iso:country":"RU",
    "name:rus_x_preferred":[
        "\u0412\u044f\u0442\u0441\u043a\u043e\u0435"
    ],
    "wof:name":"Vyatskoye",
    "wof:placetype":"locality"
},
  "geometry": {"coordinates":[48.15266,46.64454],"type":"Point"}
}