{
  "type": "Feature",
  "properties": {
    "gn:admin1_code":"54",
    "gn:asciiname":"Bichili",
    "gn:country_code":"RU",
    "gn:dem":53,
    "gn:feature_class":"P",
    "gn:feature_code":"PPL",
    "gn:name":"Bichili",
    "gn:population":0,
    "gn:timezone":"Asia/Omsk",
    "iso:country":"RU",
    "name:rus_x_preferred":[
        "\u0411\u0438\u0447\u0438\u043b\u0438"
    ],
    "name:und_x_variant":[
        "\u0411\u0438\u0447\u0438\u043b\u0438"
    ],
    "wof:name":"Bichili",
    "wof:placetype":"locality"
},
  "geometry": {"coordinates":[72.61669999999999,57.576],"type":"Point"}
}