{
  "type": "Feature",
  "properties": {
    "gn:admin1_code":"67",
    "gn:asciiname":"Maresevo",
    "gn:country_code":"RU",
    "gn:dem":210,
    "gn:feature_class":"P",
    "gn:feature_code":"PPL",
    "gn:name":"Maresevo",
    "gn:population":0,
    "gn:timezone":"Europe/Saratov",
    "iso:country":"RU",
    "name:rus_x_preferred":[
        "\u041c\u0430\u0440\u0435\u0441\u0435\u0432\u043e"
    ],
    "name:und_x_variant":[
        "\u041c\u0430\u0440\u0435\u0441\u0435\u0432\u043e"
    ],
    "wof:name":"Maresevo",
    "wof:placetype":"locality"
},
  "geometry": {"coordinates":[45.33333,52.06667],"type":"Point"}
}