{
  "type": "Feature",
  "properties": {
    "gn:admin1_code":"69",
    "gn:asciiname":"Polufeyevka",
    "gn:country_code":"RU",
    "gn:dem":212,
    "gn:feature_class":"P",
    "gn:feature_code":"PPL",
    "gn:name":"Polufeyevka",
    "gn:population":0,
    "gn:timezone":"Europe/Moscow",
    "iso:country":"RU",
    "name:rus_x_preferred":[
        "\u041f\u043e\u043b\u0443\u0444\u0435\u0435\u0432\u043a\u0430"
    ],
    "wof:name":"Polufeyevka",
    "wof:placetype":"locality"
},
  "geometry": {"coordinates":[32.85783,54.22316],"type":"Point"}
}