{
  "type": "Feature",
  "properties": {
    "gn:admin1_code":"77",
    "gn:asciiname":"Osinovka",
    "gn:country_code":"RU",
    "gn:dem":248,
    "gn:feature_class":"P",
    "gn:feature_code":"PPL",
    "gn:name":"Osinovka",
    "gn:population":0,
    "gn:timezone":"Europe/Moscow",
    "iso:country":"RU",
    "name:ceb_x_preferred":[
        "Osinovka"
    ],
    "name:lav_x_preferred":[
        "Osinovka"
    ],
    "name:rus_x_preferred":[
        "\u041e\u0441\u0438\u043d\u043e\u0432\u043a\u0430"
    ],
    "name:swe_x_preferred":[
        "Osinovka"
    ],
    "wof:name":"Osinovka",
    "wof:placetype":"locality"
},
  "geometry": {"coordinates":[32.64194000000001,56.41944],"type":"Point"}
}