{
  "type": "Feature",
  "properties": {
    "gn:admin1_code":"52",
    "gn:asciiname":"Maloye Sheludkovo",
    "gn:country_code":"RU",
    "gn:dem":73,
    "gn:feature_class":"P",
    "gn:feature_code":"PPL",
    "gn:name":"Maloye Sheludkovo",
    "gn:population":0,
    "gn:timezone":"Europe/Moscow",
    "iso:country":"RU",
    "name:rus_x_preferred":[
        "\u041c\u0430\u043b\u043e\u0435 \u0428\u0435\u043b\u0443\u0434\u043a\u043e\u0432\u043e"
    ],
    "wof:name":"Maloye Sheludkovo",
    "wof:placetype":"locality"
},
  "geometry": {"coordinates":[31.10012,57.6459],"type":"Point"}
}