{
  "type": "Feature",
  "properties": {
    "gn:admin1_code":"77",
    "gn:asciiname":"Soronino",
    "gn:country_code":"RU",
    "gn:dem":148,
    "gn:feature_class":"P",
    "gn:feature_code":"PPL",
    "gn:name":"Soronino",
    "gn:population":0,
    "gn:timezone":"Europe/Moscow",
    "iso:country":"RU",
    "name:rus_x_preferred":[
        "\u0421\u043e\u0440\u043e\u043d\u0438\u043d\u043e"
    ],
    "wof:name":"Soronino",
    "wof:placetype":"locality"
},
  "geometry": {"coordinates":[37.1347,57.4015],"type":"Point"}
}