{
  "type": "Feature",
  "properties": {
    "gn:admin1_code":"25",
    "gn:asciiname":"Korovino",
    "gn:country_code":"RU",
    "gn:dem":180,
    "gn:feature_class":"P",
    "gn:feature_code":"PPL",
    "gn:name":"Korovino",
    "gn:population":0,
    "gn:timezone":"Europe/Moscow",
    "iso:country":"RU",
    "name:rus_x_preferred":[
        "\u041a\u043e\u0440\u043e\u0432\u0438\u043d\u0430"
    ],
    "name:und_x_variant":[
        "Korovina",
        "Korovino",
        "\u041a\u043e\u0440\u043e\u0432\u0438\u043d\u0430"
    ],
    "wof:name":"Korovino",
    "wof:placetype":"locality"
},
  "geometry": {"coordinates":[35.385,54.29306],"type":"Point"}
}