{
  "type": "Feature",
  "properties": {
    "gn:admin1_code":"40",
    "gn:asciiname":"Banshchikovo",
    "gn:country_code":"RU",
    "gn:dem":152,
    "gn:feature_class":"P",
    "gn:feature_code":"PPL",
    "gn:name":"Banshchikovo",
    "gn:population":0,
    "gn:timezone":"Asia/Yekaterinburg",
    "iso:country":"RU",
    "name:nor_x_preferred":[
        "Bansjtsjikovo"
    ],
    "name:rus_x_preferred":[
        "\u0411\u0430\u043d\u0449\u0438\u043a\u043e\u0432\u043e"
    ],
    "name:und_x_variant":[
        "Ban\u2019shchikova",
        "Banshchikovo"
    ],
    "wof:name":"Banshchikovo",
    "wof:placetype":"locality"
},
  "geometry": {"coordinates":[65.38722,54.71111],"type":"Point"}
}