{
  "type": "Feature",
  "properties": {
    "gn:admin1_code":"85",
    "gn:asciiname":"Lodygino",
    "gn:country_code":"RU",
    "gn:dem":169,
    "gn:feature_class":"P",
    "gn:feature_code":"PPL",
    "gn:name":"Lodygino",
    "gn:population":0,
    "gn:timezone":"Europe/Moscow",
    "iso:country":"RU",
    "name:rus_x_preferred":[
        "\u041b\u043e\u0434\u044b\u0433\u0438\u043d\u043e"
    ],
    "name:und_x_variant":[
        "\u041b\u043e\u0434\u044b\u0433\u0438\u043d\u043e"
    ],
    "wof:name":"Lodygino",
    "wof:placetype":"locality"
},
  "geometry": {"coordinates":[42.30045,59.97494],"type":"Point"}
}