{
  "type": "Feature",
  "properties": {
    "gn:country":"RU",
    "gn:fcode":"PPL",
    "gn:population":0,
    "iso:country":"RU",
    "name:eng_x_preferred":[
        "Karamyshevo"
    ],
    "name:nor_x_preferred":[
        "Karamysjevo"
    ],
    "name:rus_x_preferred":[
        "\u041a\u0430\u0440\u0430\u043c\u044b\u0448\u0435\u0432\u043e"
    ],
    "name:sco_x_preferred":[
        "Karamyshevo"
    ],
    "name:zho_x_preferred":[
        "Oktyabr'skij"
    ],
    "qs:name":"Karamyshevo",
    "qs:name_adm0":"Russia",
    "qs:name_adm1":"Tula Oblast",
    "qs:photos_9r":0,
    "qs:photos_sr":0,
    "qs:placetype":"Town",
    "qs:pop_sr":"0",
    "wd:wordcount":239,
    "wof:name":"Karamyshevo",
    "wof:placetype":"locality",
    "wof:population":0
},
  "geometry": {"coordinates":[37.45864,53.90604],"type":"Point"}
}