{
  "type": "Feature",
  "properties": {
    "gn:admin1_code":"91",
    "gn:asciiname":"Ust'-Port",
    "gn:country_code":"RU",
    "gn:dem":16,
    "gn:feature_class":"P",
    "gn:feature_code":"PPL",
    "gn:name":"Ust\u2019-Port",
    "gn:population":0,
    "gn:timezone":"Asia/Krasnoyarsk",
    "iso:country":"RU",
    "name:eng_x_preferred":[
        "Ust'-Port"
    ],
    "name:nor_x_preferred":[
        "Ust-Port"
    ],
    "name:rus_x_preferred":[
        "\u0423\u0441\u0442\u044c-\u041f\u043e\u0440\u0442"
    ],
    "name:und_x_variant":[
        "Ust Yenisei Port",
        "Ust Eniseiski Port",
        "Ust\u2019-Yeniseyskiy-Port",
        "Ust\u2019-Veniseyskiy Port",
        "Ust\u2019-Port"
    ],
    "wof:name":"Ust'-Port",
    "wof:placetype":"locality"
},
  "geometry": {"coordinates":[84.40765,69.66370000000001],"type":"Point"}
}