{
  "type": "Feature",
  "properties": {
    "gn:admin1_code":"33.0",
    "gn:asciiname":"Shvetsovo",
    "gn:country_code":"RU",
    "gn:dem":127,
    "gn:feature_class":"P",
    "gn:feature_code":"PPL",
    "gn:name":"Shvetsovo",
    "gn:population":0,
    "gn:timezone":"Europe/Kirov",
    "iso:country":"RU",
    "name:rus_x_preferred":[
        "\u0428\u0432\u0435\u0446\u043e\u0432\u043e"
    ],
    "name:und_x_variant":[
        "\u0428\u0432\u0435\u0446\u043e\u0432\u043e"
    ],
    "wof:name":"Shvetsovo",
    "wof:placetype":"locality"
},
  "geometry": {"coordinates":[48.0096,57.34854],"type":"Point"}
}