{
  "type": "Feature",
  "properties": {
    "gn:admin1_code":"69",
    "gn:asciiname":"Kushlyanshchina",
    "gn:country_code":"RU",
    "gn:dem":219,
    "gn:feature_class":"P",
    "gn:feature_code":"PPL",
    "gn:name":"Kushlyanshchina",
    "gn:population":0,
    "gn:timezone":"Europe/Moscow",
    "iso:country":"RU",
    "name:rus_x_preferred":[
        "\u041a\u0443\u0448\u043b\u044f\u043d\u0449\u0438\u043d\u0430"
    ],
    "name:und_x_variant":[
        "Bol\u2019shaya Kushlyanshchina",
        "Kushlyanshchina"
    ],
    "wof:name":"Kushlyanshchina",
    "wof:placetype":"locality"
},
  "geometry": {"coordinates":[31.9103,54.6698],"type":"Point"}
}