{
  "type": "Feature",
  "properties": {
    "gn:admin1_code":"91",
    "gn:asciiname":"Kan-Okler",
    "gn:country_code":"RU",
    "gn:dem":377,
    "gn:feature_class":"P",
    "gn:feature_code":"PPL",
    "gn:name":"Kan-Okler",
    "gn:population":0,
    "gn:timezone":"Asia/Krasnoyarsk",
    "iso:country":"RU",
    "name:eng_x_preferred":[
        "Kan-Okler"
    ],
    "name:nor_x_preferred":[
        "Kan-Okler"
    ],
    "name:rus_x_preferred":[
        "\u041a\u0430\u043d-\u041e\u043a\u043b\u0435\u0440"
    ],
    "wof:name":"Kan-Okler",
    "wof:placetype":"locality"
},
  "geometry": {"coordinates":[95.11190000000001,55.0377],"type":"Point"}
}