{
  "type": "Feature",
  "properties": {
    "gn:admin1_code":"05",
    "gn:asciiname":"Tymersol'",
    "gn:country_code":"RU",
    "gn:dem":348,
    "gn:feature_class":"P",
    "gn:feature_code":"PPL",
    "gn:name":"Tymersol\u2019",
    "gn:population":0,
    "gn:timezone":"Asia/Yakutsk",
    "iso:country":"RU",
    "name:und_x_variant":[
        "Tymarsol\u2019",
        "Tymersol\u2019"
    ],
    "wof:name":"Tymersol'",
    "wof:placetype":"locality"
},
  "geometry": {"coordinates":[126.12564999999999,53.38239],"type":"Point"}
}