{
  "type": "Feature",
  "properties": {
    "gn:country":"RU",
    "gn:fcode":"PPLX",
    "gn:population":0,
    "iso:country":"RU",
    "name:ceb_x_preferred":[
        "\u042f\u0440\u043e\u0441\u043b\u0430\u0432\u0441\u043a\u0438\u0439"
    ],
    "name:deu_x_preferred":[
        "Jaroslawski"
    ],
    "name:rus_x_preferred":[
        "\u042f\u0440\u043e\u0441\u043b\u0430\u0301\u0432\u0441\u043a\u0438\u0439"
    ],
    "name:rus_x_variant":[
        "\u042f\u0440\u043e\u0441\u043b\u0430\u0432\u0441\u043a\u0438\u0439"
    ],
    "name:sco_x_preferred":[
        "Yaroslavsky"
    ],
    "name:ukr_x_preferred":[
        "\u042f\u0440\u043e\u0441\u043b\u0430\u0432\u0441\u044c\u043a\u0438\u0439"
    ],
    "name:und_x_variant":[
        "Malyye Mytishchi"
    ],
    "wof:name":"Yaroslavsky",
    "wof:placetype":"neighbourhood",
    "wof:population":0
},
  "geometry": {"coordinates":[37.69771771429343,55.86602351462101],"type":"Point"}
}