{
  "type": "Feature",
  "properties": {
    "gn:admin1_code":"40",
    "gn:asciiname":"P'yankovo",
    "gn:country_code":"RU",
    "gn:dem":136,
    "gn:feature_class":"P",
    "gn:feature_code":"PPL",
    "gn:name":"P\u2019yankovo",
    "gn:population":0,
    "gn:timezone":"Asia/Yekaterinburg",
    "iso:country":"RU",
    "name:rus_x_preferred":[
        "\u041f\u044c\u044f\u043d\u043a\u043e\u0432\u043e"
    ],
    "name:und_x_variant":[
        "P\u2019yankova",
        "P\u2019yankovo",
        "\u041f\u044c\u044f\u043d\u043a\u043e\u0432\u043e"
    ],
    "wof:name":"P'yankovo",
    "wof:placetype":"locality"
},
  "geometry": {"coordinates":[67.57083,55.13806],"type":"Point"}
}