{
  "type": "Feature",
  "properties": {
    "gn:admin1_code":"77",
    "gn:asciiname":"Parzha",
    "gn:country_code":"RU",
    "gn:dem":141,
    "gn:feature_class":"P",
    "gn:feature_code":"PPL",
    "gn:name":"Parzha",
    "gn:population":0,
    "gn:timezone":"Europe/Moscow",
    "iso:country":"RU",
    "name:rus_x_preferred":[
        "\u041f\u0430\u0440\u0436\u0430"
    ],
    "wof:name":"Parzha",
    "wof:placetype":"locality"
},
  "geometry": {"coordinates":[35.78209000000001,57.87272],"type":"Point"}
}