{
  "type": "Feature",
  "properties": {
    "gn:admin1_code":"77",
    "gn:asciiname":"Andrianovo",
    "gn:country_code":"RU",
    "gn:dem":214,
    "gn:feature_class":"P",
    "gn:feature_code":"PPL",
    "gn:name":"Andrianovo",
    "gn:population":0,
    "gn:timezone":"Europe/Moscow",
    "iso:country":"RU",
    "name:nor_x_preferred":[
        "Andrianovo"
    ],
    "name:rus_x_preferred":[
        "\u0410\u043d\u0434\u0440\u0438\u0430\u043d\u043e\u0432\u043e"
    ],
    "wof:name":"Andrianovo",
    "wof:placetype":"locality"
},
  "geometry": {"coordinates":[32.30446,56.29055],"type":"Point"}
}