{
  "type": "Feature",
  "properties": {
    "gn:admin1_code":"52",
    "gn:asciiname":"Mantsy",
    "gn:country_code":"RU",
    "gn:dem":240,
    "gn:feature_class":"P",
    "gn:feature_code":"PPL",
    "gn:name":"Mantsy",
    "gn:population":0,
    "gn:timezone":"Europe/Moscow",
    "iso:country":"RU",
    "name:eng_x_preferred":[
        "Mantsy"
    ],
    "name:nor_x_preferred":[
        "Mantsy"
    ],
    "name:rus_x_preferred":[
        "\u041c\u0430\u043d\u0446\u044b"
    ],
    "wof:name":"Mantsy",
    "wof:placetype":"locality"
},
  "geometry": {"coordinates":[32.3048,57.2595],"type":"Point"}
}