{
  "type": "Feature",
  "properties": {
    "gn:admin1_code":"80",
    "gn:asciiname":"Ayduan-Chab'ya",
    "gn:country_code":"RU",
    "gn:dem":176,
    "gn:feature_class":"P",
    "gn:feature_code":"PPL",
    "gn:name":"Ayduan-Chab\u2019ya",
    "gn:population":0,
    "gn:timezone":"Europe/Samara",
    "iso:country":"RU",
    "name:nor_x_preferred":[
        "Ajduan-Tsjabja"
    ],
    "name:rus_x_preferred":[
        "\u0410\u0439\u0434\u0443\u0430\u043d-\u0427\u0430\u0431\u044c\u044f"
    ],
    "name:und_x_variant":[
        "Ayduan-Chab\u2019ya"
    ],
    "wof:name":"Ayduan-Chab'ya",
    "wof:placetype":"locality"
},
  "geometry": {"coordinates":[51.6706,56.20758000000001],"type":"Point"}
}