{
  "type": "Feature",
  "properties": {
    "gn:admin1_code":"71",
    "gn:asciiname":"Krutikhinskoye",
    "gn:country_code":"RU",
    "gn:dem":104,
    "gn:feature_class":"P",
    "gn:feature_code":"PPL",
    "gn:name":"Krutikhinskoye",
    "gn:population":0,
    "gn:timezone":"Asia/Yekaterinburg",
    "iso:country":"RU",
    "name:eng_x_preferred":[
        "Krutikhinskoye"
    ],
    "name:nor_x_preferred":[
        "Krutikhinskoje"
    ],
    "name:rus_x_preferred":[
        "\u041a\u0440\u0443\u0442\u0438\u0445\u0438\u043d\u0441\u043a\u043e\u0435"
    ],
    "name:und_x_variant":[
        "\u041a\u0440\u0443\u0442\u0438\u0445\u0438\u043d\u0441\u043a\u043e\u0435",
        "Krutikhinskoye"
    ],
    "wof:name":"Krutikhinskoye",
    "wof:placetype":"locality"
},
  "geometry": {"coordinates":[62.7571,57.34859],"type":"Point"}
}