{
  "type": "Feature",
  "properties": {
    "gn:admin1_code":"45",
    "gn:asciiname":"Russkiy Kukmor",
    "gn:country_code":"RU",
    "gn:dem":104,
    "gn:feature_class":"P",
    "gn:feature_code":"PPL",
    "gn:name":"Russkiy Kukmor",
    "gn:population":0,
    "gn:timezone":"Europe/Moscow",
    "iso:country":"RU",
    "name:eng_x_preferred":[
        "Russkiy Kukmor"
    ],
    "name:nor_x_preferred":[
        "Russkij Kukmor"
    ],
    "name:rus_x_preferred":[
        "\u0420\u0443\u0441\u0441\u043a\u0438\u0439 \u041a\u0443\u043a\u043c\u043e\u0440"
    ],
    "name:und_x_variant":[
        "Kukumor Russkiy"
    ],
    "wof:name":"Russkiy Kukmor",
    "wof:placetype":"locality"
},
  "geometry": {"coordinates":[48.14139,56.67167],"type":"Point"}
}