{
  "type": "Feature",
  "properties": {
    "gn:admin1_code":"42.0",
    "gn:asciiname":"Ryzhiki",
    "gn:country_code":"RU",
    "gn:dem":31,
    "gn:feature_class":"P",
    "gn:feature_code":"PPL",
    "gn:name":"Ryzhiki",
    "gn:population":0,
    "gn:timezone":"Europe/Moscow",
    "iso:country":"RU",
    "name:fin_x_preferred":[
        "Riisikkala"
    ],
    "wof:name":"Ryzhiki",
    "wof:placetype":"locality"
},
  "geometry": {"coordinates":[30.65529,59.90728000000001],"type":"Point"}
}