{
  "type": "Feature",
  "properties": {
    "gn:admin1_code":"37",
    "gn:asciiname":"Tchanikovo",
    "gn:country_code":"RU",
    "gn:dem":158,
    "gn:feature_class":"P",
    "gn:feature_code":"PPL",
    "gn:name":"Tchanikovo",
    "gn:population":0,
    "gn:timezone":"Europe/Moscow",
    "iso:country":"RU",
    "name:rus_x_preferred":[
        "\u0422\u0447\u0430\u043d\u0438\u043a\u043e\u0432\u043e"
    ],
    "name:und_x_variant":[
        "\u0422\u0447\u0430\u043d\u0438\u043a\u043e\u0432\u043e",
        "Tchannikovo"
    ],
    "wof:name":"Tchanikovo",
    "wof:placetype":"locality"
},
  "geometry": {"coordinates":[43.25235,58.35777],"type":"Point"}
}