{
  "type": "Feature",
  "properties": {
    "gn:admin1_code":"25",
    "gn:asciiname":"Kartsevo",
    "gn:country_code":"RU",
    "gn:dem":191,
    "gn:feature_class":"P",
    "gn:feature_code":"PPL",
    "gn:name":"Kartsevo",
    "gn:population":0,
    "gn:timezone":"Europe/Moscow",
    "iso:country":"RU",
    "name:rus_x_preferred":[
        "\u041a\u0430\u0440\u0446\u0435\u0432\u043e"
    ],
    "name:und_x_variant":[
        "\u041a\u0430\u0440\u0446\u0435\u0432\u043e"
    ],
    "wof:name":"Kartsevo",
    "wof:placetype":"locality"
},
  "geometry": {"coordinates":[35.38241,54.26297],"type":"Point"}
}