{
  "type": "Feature",
  "properties": {
    "gn:admin1_code":"8",
    "gn:asciiname":"Kakhnovka",
    "gn:country_code":"RU",
    "gn:dem":143,
    "gn:feature_class":"P",
    "gn:feature_code":"PPL",
    "gn:name":"Kakhnovka",
    "gn:population":0,
    "gn:timezone":"Asia/Yekaterinburg",
    "iso:country":"RU",
    "name:rus_x_preferred":[
        "\u041a\u0430\u0445\u043d\u043e\u0432\u043a\u0430"
    ],
    "name:und_x_variant":[
        "Kazenovka",
        "Kakhnovka",
        "\u041a\u0430\u0445\u043d\u043e\u0432\u043a\u0430"
    ],
    "wof:name":"Kakhnovka",
    "wof:placetype":"locality"
},
  "geometry": {"coordinates":[55.38333000000001,54.78333000000001],"type":"Point"}
}