{
  "type": "Feature",
  "properties": {
    "gn:admin1_code":"77",
    "gn:asciiname":"Zadovo",
    "gn:country_code":"RU",
    "gn:dem":127,
    "gn:feature_class":"P",
    "gn:feature_code":"PPL",
    "gn:name":"Zadovo",
    "gn:population":0,
    "gn:timezone":"Europe/Moscow",
    "iso:country":"RU",
    "name:rus_x_preferred":[
        "\u0417\u0430\u0434\u043e\u0432\u043e"
    ],
    "wof:name":"Zadovo",
    "wof:placetype":"locality"
},
  "geometry": {"coordinates":[37.7057,57.2704],"type":"Point"}
}