{
  "type": "Feature",
  "properties": {
    "gn:country":"RU",
    "gn:fcode":"PPL",
    "gn:population":1539,
    "iso:country":"RU",
    "name:eng_x_preferred":[
        "Ch\u00ebrnaya Kholunitsa"
    ],
    "name:nor_x_preferred":[
        "Tsjernaja Kholunitsa"
    ],
    "name:rus_x_preferred":[
        "\u0427\u0435\u0440\u043d\u0430\u044f \u0425\u043e\u043b\u0443\u043d\u0438\u0446\u0430"
    ],
    "name:rus_x_variant":[
        "\u0427\u0451\u0440\u043d\u0430\u044f \u0425\u043e\u043b\u0443\u043d\u0438\u0446\u0430"
    ],
    "qs_pg:aaroncc":"RU",
    "qs_pg:gn_country":"RU",
    "qs_pg:gn_fcode":"PPL",
    "qs_pg:gn_pop":1539,
    "qs_pg:name":"Ch\u00ebrnaya Kholunitsa",
    "qs_pg:photos_9r":0,
    "qs_pg:photos_sr":0,
    "qs_pg:pop_sr":3,
    "qs_pg:qs_pg_placetype":"locality",
    "wof:name":"Ch\u00ebrnaya Kholunitsa",
    "wof:placetype":"locality",
    "wof:population":1539
},
  "geometry": {"coordinates":[51.71545,58.85114],"type":"Point"}
}