{
  "type": "Feature",
  "properties": {
    "gn:admin1_code":"16.0",
    "gn:asciiname":"Azim-Sirma",
    "gn:country_code":"RU",
    "gn:dem":153,
    "gn:feature_class":"P",
    "gn:feature_code":"PPL",
    "gn:name":"Azim-Sirma",
    "gn:population":0,
    "gn:timezone":"Europe/Moscow",
    "iso:country":"RU",
    "name:che_x_preferred":[
        "\u0410\u0437\u0438\u043c-\u0421\u0438\u0440\u043c\u0430"
    ],
    "name:chv_x_preferred":[
        "\u0410\u00e7\u0103\u043c \u00c7\u044b\u0440\u043c\u0438"
    ],
    "name:fra_x_preferred":[
        "Azim Sirma"
    ],
    "name:ita_x_preferred":[
        "Azim Sirma"
    ],
    "name:nor_x_preferred":[
        "Azim-Sirma"
    ],
    "name:oci_x_preferred":[
        "Azim Sirma"
    ],
    "name:por_x_preferred":[
        "Azim Sirma"
    ],
    "name:rus_x_preferred":[
        "\u0410\u0437\u0438\u043c-\u0421\u0438\u0440\u043c\u0430"
    ],
    "name:tat_x_preferred":[
        "\u04d8\u0497\u0435\u043c \u0421\u044b\u0440\u043c\u0430"
    ],
    "wof:name":"Azim-Sirma",
    "wof:placetype":"locality"
},
  "geometry": {"coordinates":[46.74488,55.61583],"type":"Point"}
}