{
  "type": "Feature",
  "properties": {
    "gn:admin1_code":"42",
    "gn:asciiname":"Ol'khovo",
    "gn:country_code":"RU",
    "gn:dem":154,
    "gn:feature_class":"P",
    "gn:feature_code":"PPL",
    "gn:name":"Ol\u2019khovo",
    "gn:population":0,
    "gn:timezone":"Europe/Moscow",
    "iso:country":"RU",
    "name:fin_x_preferred":[
        "Olkkuva"
    ],
    "name:nor_x_preferred":[
        "Olkhovo"
    ],
    "name:rus_x_preferred":[
        "\u041e\u043b\u044c\u0445\u043e\u0432\u043e"
    ],
    "name:und_x_variant":[
        "Ol\u2019khovo"
    ],
    "wof:name":"Ol'khovo",
    "wof:placetype":"locality"
},
  "geometry": {"coordinates":[29.39107000000001,59.54433],"type":"Point"}
}