{
  "type": "Feature",
  "properties": {
    "gn:admin1_code":"8",
    "gn:asciiname":"Novosinitsyno",
    "gn:cc2":"RU",
    "gn:country_code":"RU",
    "gn:dem":194,
    "gn:feature_class":"P",
    "gn:feature_code":"PPL",
    "gn:name":"Novosinitsyno",
    "gn:population":0,
    "gn:timezone":"Asia/Yekaterinburg",
    "iso:country":"RU",
    "name:rus_x_preferred":[
        "\u041d\u043e\u0432\u043e\u0441\u0438\u043d\u0438\u0446\u044b\u043d\u043e"
    ],
    "name:und_x_variant":[
        "Nadlesnyy",
        "Novosinitsyno",
        "\u041d\u043e\u0432\u043e\u0441\u0438\u043d\u0438\u0446\u044b\u043d\u043e"
    ],
    "wof:name":"Novosinitsyno",
    "wof:placetype":"locality"
},
  "geometry": {"coordinates":[54.88333000000001,54.71666999999999],"type":"Point"}
}