{
  "type": "Feature",
  "properties": {
    "gn:admin1_code":"43",
    "gn:asciiname":"Zamartyn'ye",
    "gn:country_code":"RU",
    "gn:dem":135,
    "gn:feature_class":"P",
    "gn:feature_code":"PPL",
    "gn:name":"Zamartyn\u2019ye",
    "gn:population":0,
    "gn:timezone":"Europe/Moscow",
    "iso:country":"RU",
    "name:eng_x_preferred":[
        "Zamartyn'ye"
    ],
    "name:nor_x_preferred":[
        "Zamartynje"
    ],
    "name:rus_x_preferred":[
        "\u0417\u0430\u043c\u0430\u0440\u0442\u044b\u043d\u044c\u0435"
    ],
    "name:und_x_variant":[
        "\u0417\u0430\u043c\u0430\u0440\u0442\u044b\u043d\u044c\u0435",
        "Zamartyn\u2019ye"
    ],
    "wof:name":"Zamartyn'ye",
    "wof:placetype":"locality"
},
  "geometry": {"coordinates":[39.68884,52.86554],"type":"Point"}
}