{
  "type": "Feature",
  "properties": {
    "gn:admin1_code":"47",
    "gn:asciiname":"Gusenki",
    "gn:country_code":"RU",
    "gn:dem":129,
    "gn:feature_class":"P",
    "gn:feature_code":"PPL",
    "gn:name":"Gusenki",
    "gn:population":0,
    "gn:timezone":"Europe/Moscow",
    "iso:country":"RU",
    "name:rus_x_preferred":[
        "\u0413\u0443\u0441\u0435\u043d\u043a\u0438"
    ],
    "name:und_x_variant":[
        "\u0413\u0443\u0441\u0435\u043d\u043a\u0438"
    ],
    "wof:name":"Gusenki",
    "wof:placetype":"locality"
},
  "geometry": {"coordinates":[37.46667,56.63333000000001],"type":"Point"}
}