{
  "type": "Feature",
  "properties": {
    "gn:admin1_code":"8",
    "gn:asciiname":"Novomusino",
    "gn:country_code":"RU",
    "gn:dem":122,
    "gn:feature_class":"P",
    "gn:feature_code":"PPL",
    "gn:name":"Novomusino",
    "gn:population":0,
    "gn:timezone":"Asia/Yekaterinburg",
    "iso:country":"RU",
    "name:rus_x_preferred":[
        "\u041d\u043e\u0432\u043e\u043c\u0443\u0441\u0438\u043d\u043e"
    ],
    "name:und_x_variant":[
        "\u041d\u043e\u0432\u043e\u043c\u0443\u0441\u0438\u043d\u043e"
    ],
    "wof:name":"Novomusino",
    "wof:placetype":"locality"
},
  "geometry": {"coordinates":[55.9036,54.3565],"type":"Point"}
}