{
  "type": "Feature",
  "properties": {
    "gn:admin1_code":"56",
    "gn:asciiname":"Maloye Yur'yevo",
    "gn:country_code":"RU",
    "gn:dem":202,
    "gn:feature_class":"P",
    "gn:feature_code":"PPL",
    "gn:name":"Maloye Yur\u2019yevo",
    "gn:population":0,
    "gn:timezone":"Europe/Moscow",
    "iso:country":"RU",
    "name:rus_x_preferred":[
        "\u041c\u0430\u043b\u043e\u0435 \u042e\u0440\u044c\u0435\u0432\u043e"
    ],
    "name:und_x_variant":[
        "Maloye Yur\u2019yevo"
    ],
    "wof:name":"Maloye Yur'yevo",
    "wof:placetype":"locality"
},
  "geometry": {"coordinates":[35.25222,53.15397],"type":"Point"}
}