{
  "type": "Feature",
  "properties": {
    "gn:admin1_code":"53.0",
    "gn:asciiname":"Ninochkin",
    "gn:country_code":"RU",
    "gn:dem":113,
    "gn:feature_class":"P",
    "gn:feature_code":"PPL",
    "gn:name":"Ninochkin",
    "gn:population":0,
    "gn:timezone":"Asia/Novosibirsk",
    "iso:country":"RU",
    "name:rus_x_preferred":[
        "\u041d\u0438\u043d\u043e\u0447\u043a\u0438\u043d"
    ],
    "wof:name":"Ninochkin",
    "wof:placetype":"locality"
},
  "geometry": {"coordinates":[77.43611,54.22857],"type":"Point"}
}