{
  "type": "Feature",
  "properties": {
    "gn:admin1_code":"76",
    "gn:asciiname":"Samozvanovka",
    "gn:country_code":"RU",
    "gn:dem":236,
    "gn:feature_class":"P",
    "gn:feature_code":"PPL",
    "gn:name":"Samozvanovka",
    "gn:population":0,
    "gn:timezone":"Europe/Moscow",
    "iso:country":"RU",
    "name:rus_x_preferred":[
        "\u0421\u0430\u043c\u043e\u0437\u0432\u0430\u043d\u043e\u0432\u043a\u0430"
    ],
    "wof:name":"Samozvanovka",
    "wof:placetype":"locality"
},
  "geometry": {"coordinates":[37.205,53.6175],"type":"Point"}
}