{
  "type": "Feature",
  "properties": {
    "gn:admin1_code":"54",
    "gn:asciiname":"Utich'ye",
    "gn:country_code":"RU",
    "gn:dem":125,
    "gn:feature_class":"P",
    "gn:feature_code":"PPL",
    "gn:name":"Utich\u2019ye",
    "gn:population":0,
    "gn:timezone":"Asia/Omsk",
    "iso:country":"RU",
    "name:eng_x_preferred":[
        "Utich'ye"
    ],
    "name:nor_x_preferred":[
        "Utitsje"
    ],
    "name:rus_x_preferred":[
        "\u0423\u0442\u0438\u0447\u044c\u0435"
    ],
    "name:und_x_variant":[
        "Utich\u2019ye",
        "\u0423\u0442\u0438\u0447\u044c\u0435"
    ],
    "wof:name":"Utich'ye",
    "wof:placetype":"locality"
},
  "geometry": {"coordinates":[71.64,55.31753000000001],"type":"Point"}
}