{
  "type": "Feature",
  "properties": {
    "gn:admin1_code":"62.0",
    "gn:asciiname":"Bol'shoye Khrenovo",
    "gn:country_code":"RU",
    "gn:dem":137,
    "gn:feature_class":"P",
    "gn:feature_code":"PPL",
    "gn:name":"Bol\u2019shoye Khrenovo",
    "gn:population":0,
    "gn:timezone":"Europe/Moscow",
    "iso:country":"RU",
    "name:rus_x_preferred":[
        "\u0411\u043e\u043b\u044c\u0448\u043e\u0435 \u0425\u0440\u0435\u043d\u043e\u0432\u043e"
    ],
    "name:und_x_variant":[
        "Khrenovo",
        "Bol\u2019shoye Khrenovo"
    ],
    "wof:name":"Bol'shoye Khrenovo",
    "wof:placetype":"locality"
},
  "geometry": {"coordinates":[41.75,54.35],"type":"Point"}
}