{
  "type": "Feature",
  "properties": {
    "gn:admin1_code":"62",
    "gn:asciiname":"Krasava",
    "gn:country_code":"RU",
    "gn:dem":143,
    "gn:feature_class":"P",
    "gn:feature_code":"PPL",
    "gn:name":"Krasava",
    "gn:population":0,
    "gn:timezone":"Europe/Moscow",
    "iso:country":"RU",
    "name:ceb_x_preferred":[
        "Krasava"
    ],
    "name:fra_x_preferred":[
        "Krasava"
    ],
    "name:msa_x_preferred":[
        "Krasava"
    ],
    "name:nld_x_preferred":[
        "Krasava"
    ],
    "name:por_x_preferred":[
        "Krasava"
    ],
    "name:rus_x_preferred":[
        "\u041a\u0440\u0430\u0441\u0430\u0432\u0430"
    ],
    "name:slv_x_preferred":[
        "Krasava"
    ],
    "name:srp_x_preferred":[
        "\u041a\u0440\u0430\u0441\u0430\u0432\u0430"
    ],
    "wof:name":"Krasava",
    "wof:placetype":"locality"
},
  "geometry": {"coordinates":[40.5351,54.0892],"type":"Point"}
}