{
  "type": "Feature",
  "properties": {
    "gn:admin1_code":"29",
    "gn:asciiname":"Verkhnyaya Tala",
    "gn:country_code":"RU",
    "gn:dem":377,
    "gn:feature_class":"P",
    "gn:feature_code":"PPL",
    "gn:name":"Verkhnyaya Tala",
    "gn:population":0,
    "gn:timezone":"Asia/Novokuznetsk",
    "iso:country":"RU",
    "wof:name":"Verkhnyaya Tala",
    "wof:placetype":"locality"
},
  "geometry": {"coordinates":[87.13333,53.21666999999999],"type":"Point"}
}