{
  "type": "Feature",
  "properties": {
    "gn:admin1_code":"10.0",
    "gn:asciiname":"Alad'ino",
    "gn:country_code":"RU",
    "gn:dem":186,
    "gn:feature_class":"P",
    "gn:feature_code":"PPL",
    "gn:name":"Alad\u2019ino",
    "gn:population":251,
    "gn:timezone":"Europe/Moscow",
    "iso:country":"RU",
    "name:nor_x_preferred":[
        "Aladino"
    ],
    "name:rus_x_preferred":[
        "\u0410\u043b\u0430\u0434\u044c\u0438\u043d\u043e"
    ],
    "name:und_x_variant":[
        "Alad\u2019ino"
    ],
    "wof:name":"Alad'ino",
    "wof:placetype":"locality",
    "wof:population":251
},
  "geometry": {"coordinates":[33.69882,52.61179],"type":"Point"}
}