{
  "type": "Feature",
  "properties": {
    "gn:admin1_code":"42",
    "gn:admin2_code":"6695196",
    "gn:asciiname":"Kommunary",
    "gn:country_code":"RU",
    "gn:dem":27,
    "gn:feature_class":"P",
    "gn:feature_code":"PPL",
    "gn:name":"Kommunary",
    "gn:population":0,
    "gn:timezone":"Europe/Moscow",
    "iso:country":"RU",
    "name:eng_x_preferred":[
        "Kommunary"
    ],
    "name:fin_x_preferred":[
        "Myllypelto"
    ],
    "name:nor_x_preferred":[
        "Kommunary"
    ],
    "name:rus_x_historical":[
        "\u041c\u044e\u043b\u043b\u0435\u043f\u0435\u043b\u044c\u0442\u043e"
    ],
    "name:rus_x_preferred":[
        "\u041a\u043e\u043c\u043c\u0443\u043d\u0430\u0440\u044b"
    ],
    "name:rus_x_variant":[
        "\u041c\u044e\u043b\u043b\u0435\u043f\u0435\u043b\u044c\u0442\u043e"
    ],
    "name:und_x_variant":[
        "Myullyu-Pelto",
        "Kommunary"
    ],
    "wof:name":"Kommunary",
    "wof:placetype":"locality"
},
  "geometry": {"coordinates":[30.07251,60.90638000000001],"type":"Point"}
}