{
  "type": "Feature",
  "properties": {
    "gn:admin1_code":"77",
    "gn:asciiname":"Lavrovo",
    "gn:country_code":"RU",
    "gn:dem":243,
    "gn:feature_class":"P",
    "gn:feature_code":"PPL",
    "gn:name":"Lavrovo",
    "gn:population":0,
    "gn:timezone":"Europe/Moscow",
    "iso:country":"RU",
    "name:rus_x_preferred":[
        "\u041b\u0430\u0432\u0440\u043e\u0432\u043e"
    ],
    "wof:name":"Lavrovo",
    "wof:placetype":"locality"
},
  "geometry": {"coordinates":[34.26053,57.28189],"type":"Point"}
}