{
  "type": "Feature",
  "properties": {
    "gn:admin1_code":"60",
    "gn:asciiname":"Ivashkovo",
    "gn:country_code":"RU",
    "gn:dem":61,
    "gn:feature_class":"P",
    "gn:feature_code":"PPL",
    "gn:name":"Ivashkovo",
    "gn:population":0,
    "gn:timezone":"Europe/Moscow",
    "iso:country":"RU",
    "name:rus_x_preferred":[
        "\u0418\u0432\u0430\u0448\u043a\u043e\u0432\u043e"
    ],
    "name:und_x_variant":[
        "\u0418\u0432\u0430\u0448\u043a\u043e\u0432\u043e"
    ],
    "wof:name":"Ivashkovo",
    "wof:placetype":"locality"
},
  "geometry": {"coordinates":[30.0772,57.9444],"type":"Point"}
}