{
  "type": "Feature",
  "properties": {
    "gn:admin1_code":"21",
    "gn:asciiname":"Kosachevo",
    "gn:country_code":"RU",
    "gn:dem":112,
    "gn:feature_class":"P",
    "gn:feature_code":"PPL",
    "gn:name":"Kosach\u00ebvo",
    "gn:population":0,
    "gn:timezone":"Europe/Moscow",
    "iso:country":"RU",
    "name:rus_x_preferred":[
        "\u041a\u043e\u0441\u0430\u0447\u0451\u0432\u043e"
    ],
    "name:und_x_variant":[
        "Kosachovo",
        "Kosach\u00ebvo",
        "\u041a\u043e\u0441\u0430\u0447\u0451\u0432\u043e"
    ],
    "wof:name":"Kosachevo",
    "wof:placetype":"locality"
},
  "geometry": {"coordinates":[41.94139000000001,57.30768000000001],"type":"Point"}
}