{
  "type": "Feature",
  "properties": {
    "gn:admin1_code":"83",
    "gn:asciiname":"Narmuchi",
    "gn:country_code":"RU",
    "gn:dem":130,
    "gn:feature_class":"P",
    "gn:feature_code":"PPL",
    "gn:name":"Narmuchi",
    "gn:population":0,
    "gn:timezone":"Europe/Moscow",
    "iso:country":"RU",
    "name:rus_x_preferred":[
        "\u041d\u0430\u0440\u043c\u0443\u0447\u0438"
    ],
    "name:und_x_variant":[
        "\u041d\u0430\u0440\u043c\u0443\u0447\u0438"
    ],
    "wof:name":"Narmuchi",
    "wof:placetype":"locality"
},
  "geometry": {"coordinates":[40.49342,55.57279000000001],"type":"Point"}
}