{
  "type": "Feature",
  "properties": {
    "gn:admin1_code":"62",
    "gn:asciiname":"Kashirovo",
    "gn:country_code":"RU",
    "gn:dem":123,
    "gn:feature_class":"P",
    "gn:feature_code":"PPL",
    "gn:name":"Kashirovo",
    "gn:population":0,
    "gn:timezone":"Europe/Moscow",
    "iso:country":"RU",
    "name:rus_x_preferred":[
        "\u041a\u0430\u0448\u0438\u0440\u043e\u0432\u043e"
    ],
    "name:und_x_variant":[
        "Kazykino",
        "Kashirovo",
        "\u041a\u0430\u0448\u0438\u0440\u043e\u0432\u043e"
    ],
    "wof:name":"Kashirovo",
    "wof:placetype":"locality"
},
  "geometry": {"coordinates":[39.8629,55.19248],"type":"Point"}
}