{
  "type": "Feature",
  "properties": {
    "gn:admin1_code":"7.0",
    "gn:asciiname":"Tatal",
    "gn:country_code":"RU",
    "gn:dem":-13,
    "gn:feature_class":"P",
    "gn:feature_code":"PPL",
    "gn:name":"Tatal",
    "gn:population":0,
    "gn:timezone":"Europe/Astrakhan",
    "iso:country":"RU",
    "name:rus_x_preferred":[
        "\u0422\u0430\u0442\u0430\u043b"
    ],
    "wof:name":"Tatal",
    "wof:placetype":"locality"
},
  "geometry": {"coordinates":[47.6761,47.4365],"type":"Point"}
}