{
  "type": "Feature",
  "properties": {
    "gn:admin1_code":"25",
    "gn:asciiname":"Vtoraya Isayevka",
    "gn:cc2":"RU",
    "gn:country_code":"RU",
    "gn:dem":201,
    "gn:feature_class":"P",
    "gn:feature_code":"PPL",
    "gn:name":"Vtoraya Isayevka",
    "gn:population":0,
    "gn:timezone":"Europe/Moscow",
    "iso:country":"RU",
    "name:und_x_variant":[
        "Isayeva",
        "Vtoraya Isayeva",
        "Vtoraya Isayevka"
    ],
    "wof:name":"Vtoraya Isayevka",
    "wof:placetype":"locality"
},
  "geometry": {"coordinates":[33.6275,54.12444],"type":"Point"}
}