{
  "type": "Feature",
  "properties": {
    "gn:admin1_code":"43",
    "gn:asciiname":"Novaya Gnilusha",
    "gn:cc2":"RU",
    "gn:country_code":"RU",
    "gn:dem":193,
    "gn:feature_class":"P",
    "gn:feature_code":"PPL",
    "gn:name":"Novaya Gnilusha",
    "gn:population":0,
    "gn:timezone":"Europe/Moscow",
    "iso:country":"RU",
    "name:rus_x_preferred":[
        "\u041d\u043e\u0432\u0430\u044f \u0413\u043d\u0438\u043b\u0443\u0448\u0430"
    ],
    "name:und_x_variant":[
        "Novo-Gnilusha",
        "Novaya Gnilusha",
        "\u041d\u043e\u0432\u0430\u044f \u0413\u043d\u0438\u043b\u0443\u0448\u0430"
    ],
    "wof:name":"Novaya Gnilusha",
    "wof:placetype":"locality"
},
  "geometry": {"coordinates":[39.08333,52.35],"type":"Point"}
}