{
  "type": "Feature",
  "properties": {
    "gn:admin1_code":"16",
    "gn:asciiname":"Polevyye Ineli",
    "gn:country_code":"RU",
    "gn:dem":141,
    "gn:feature_class":"P",
    "gn:feature_code":"PPL",
    "gn:name":"Polevyye Ineli",
    "gn:population":0,
    "gn:timezone":"Europe/Moscow",
    "iso:country":"RU",
    "name:rus_x_preferred":[
        "\u041f\u043e\u043b\u0435\u0432\u044b\u0435 \u0418\u043d\u0435\u043b\u0438"
    ],
    "wof:name":"Polevyye Ineli",
    "wof:placetype":"locality"
},
  "geometry": {"coordinates":[47.67091,55.17895],"type":"Point"}
}