{
  "type": "Feature",
  "properties": {
    "gn:admin1_code":"13",
    "gn:asciiname":"Irkuskan",
    "gn:country_code":"RU",
    "gn:dem":729,
    "gn:feature_class":"P",
    "gn:feature_code":"PPL",
    "gn:name":"Irkuskan",
    "gn:population":0,
    "gn:timezone":"Asia/Yekaterinburg",
    "iso:country":"RU",
    "name:rus_x_preferred":[
        "\u0418\u0440\u043a\u0443\u0441\u043a\u0430\u043d"
    ],
    "name:und_x_variant":[
        "\u0418\u0440\u043a\u0443\u0441\u043a\u0430\u043d"
    ],
    "wof:name":"Irkuskan",
    "wof:placetype":"locality"
},
  "geometry": {"coordinates":[58.85471999999999,54.92611],"type":"Point"}
}