{
  "type": "Feature",
  "properties": {
    "gn:admin1_code":"79",
    "gn:asciiname":"Kara Khem",
    "gn:cc2":"RU",
    "gn:country_code":"RU",
    "gn:dem":1228,
    "gn:feature_class":"P",
    "gn:feature_code":"PPL",
    "gn:name":"Kara Khem",
    "gn:population":0,
    "gn:timezone":"Asia/Krasnoyarsk",
    "iso:country":"RU",
    "name:rus_x_preferred":[
        "\u041a\u0430\u0440\u0430 \u0425\u0435\u043c"
    ],
    "name:und_x_variant":[
        "Kara Kem",
        "Kara Khem",
        "\u041a\u0430\u0440\u0430 \u0425\u0435\u043c"
    ],
    "wof:name":"Kara Khem",
    "wof:placetype":"locality"
},
  "geometry": {"coordinates":[95.95,51.85],"type":"Point"}
}