{
  "type": "Feature",
  "properties": {
    "gn:admin1_code":"4",
    "gn:asciiname":"Kamyshenka",
    "gn:country_code":"RU",
    "gn:dem":389,
    "gn:feature_class":"P",
    "gn:feature_code":"PPL",
    "gn:name":"Kamyshenka",
    "gn:population":0,
    "gn:timezone":"Asia/Barnaul",
    "iso:country":"RU",
    "name:rus_x_preferred":[
        "\u041a\u0430\u043c\u044b\u0448\u0435\u043d\u043a\u0430"
    ],
    "name:und_x_variant":[
        "\u041a\u0430\u043c\u044b\u0448\u0435\u043d\u043a\u0430"
    ],
    "wof:name":"Kamyshenka",
    "wof:placetype":"locality"
},
  "geometry": {"coordinates":[86.11667,52.85],"type":"Point"}
}