{
  "type": "Feature",
  "properties": {
    "gn:admin1_code":"69.0",
    "gn:asciiname":"Putyatino",
    "gn:country_code":"RU",
    "gn:dem":207,
    "gn:feature_class":"P",
    "gn:feature_code":"PPL",
    "gn:name":"Putyatino",
    "gn:population":0,
    "gn:timezone":"Europe/Moscow",
    "iso:country":"RU",
    "name:rus_x_preferred":[
        "\u041f\u0443\u0442\u044f\u0442\u0438\u043d\u043e"
    ],
    "name:und_x_variant":[
        "Bol\u2019shoye Putyatino",
        "Putyatino"
    ],
    "wof:name":"Putyatino",
    "wof:placetype":"locality"
},
  "geometry": {"coordinates":[32.62676,54.46896],"type":"Point"}
}