{
  "type": "Feature",
  "properties": {
    "gn:admin1_code":"60",
    "gn:asciiname":"Novodeti",
    "gn:country_code":"RU",
    "gn:dem":57,
    "gn:feature_class":"P",
    "gn:feature_code":"PPL",
    "gn:name":"Novodeti",
    "gn:population":0,
    "gn:timezone":"Europe/Moscow",
    "iso:country":"RU",
    "name:rus_x_preferred":[
        "\u041d\u043e\u0432\u043e\u0434\u0435\u0442\u0438"
    ],
    "name:und_x_variant":[
        "\u041d\u043e\u0432\u043e\u0434\u0435\u0442\u0438"
    ],
    "wof:name":"Novodeti",
    "wof:placetype":"locality"
},
  "geometry": {"coordinates":[30.045,57.9455],"type":"Point"}
}