{
  "type": "Feature",
  "properties": {
    "gn:admin1_code":"90",
    "gn:asciiname":"Piskuny",
    "gn:country_code":"RU",
    "gn:dem":184,
    "gn:feature_class":"P",
    "gn:feature_code":"PPL",
    "gn:name":"Piskuny",
    "gn:population":0,
    "gn:timezone":"Asia/Yekaterinburg",
    "iso:country":"RU",
    "name:rus_x_preferred":[
        "\u041f\u0438\u0441\u043a\u0443\u043d\u044b"
    ],
    "wof:name":"Piskuny",
    "wof:placetype":"locality"
},
  "geometry": {"coordinates":[56.75,57.23333],"type":"Point"}
}