{
  "type": "Feature",
  "properties": {
    "gn:admin1_code":"33.0",
    "gn:asciiname":"Pakhar'",
    "gn:country_code":"RU",
    "gn:dem":147,
    "gn:feature_class":"P",
    "gn:feature_code":"PPL",
    "gn:name":"Pakhar\u2019",
    "gn:population":0,
    "gn:timezone":"Europe/Kirov",
    "iso:country":"RU",
    "name:rus_x_preferred":[
        "\u041f\u0430\u0445\u0430\u0440\u044c"
    ],
    "name:und_x_variant":[
        "Pakhar\u2019",
        "\u041f\u0430\u0445\u0430\u0440\u044c"
    ],
    "wof:name":"Pakhar'",
    "wof:placetype":"locality"
},
  "geometry": {"coordinates":[49.10897,59.31104000000001],"type":"Point"}
}