{
  "type": "Feature",
  "properties": {
    "gn:admin1_code":"71",
    "gn:asciiname":"Klyuchevoy",
    "gn:country_code":"RU",
    "gn:dem":124,
    "gn:feature_class":"P",
    "gn:feature_code":"PPL",
    "gn:name":"Klyuchevoy",
    "gn:population":0,
    "gn:timezone":"Asia/Yekaterinburg",
    "iso:country":"RU",
    "name:eng_x_preferred":[
        "Klyuchevoy"
    ],
    "name:nor_x_preferred":[
        "Kljutsjevoj"
    ],
    "name:rus_x_preferred":[
        "\u041a\u043b\u044e\u0447\u0435\u0432\u043e\u0439"
    ],
    "name:und_x_variant":[
        "Zamarayka",
        "Klyuchevoy"
    ],
    "wof:name":"Klyuchevoy",
    "wof:placetype":"locality"
},
  "geometry": {"coordinates":[60.39358000000001,59.64263],"type":"Point"}
}