{
  "type": "Feature",
  "properties": {
    "gn:admin1_code":"53",
    "gn:asciiname":"Kolonbek",
    "gn:country_code":"RU",
    "gn:dem":120,
    "gn:feature_class":"P",
    "gn:feature_code":"PPL",
    "gn:name":"Kolonbek",
    "gn:population":0,
    "gn:timezone":"Asia/Novosibirsk",
    "iso:country":"RU",
    "name:rus_x_preferred":[
        "\u041a\u043e\u043b\u043e\u043d\u0431\u0435\u043a"
    ],
    "name:und_x_variant":[
        "\u041a\u043e\u043b\u043e\u043d\u0431\u0435\u043a"
    ],
    "wof:name":"Kolonbek",
    "wof:placetype":"locality"
},
  "geometry": {"coordinates":[76.16667,56.35],"type":"Point"}
}