{
  "type": "Feature",
  "properties": {
    "gn:admin1_code":"59",
    "gn:asciiname":"Rozhdestvenka",
    "gn:country_code":"RU",
    "gn:dem":87,
    "gn:feature_class":"P",
    "gn:feature_code":"PPL",
    "gn:name":"Rozhdestvenka",
    "gn:population":0,
    "gn:timezone":"Asia/Vladivostok",
    "iso:country":"RU",
    "name:eng_x_preferred":[
        "Rozhdestvenka"
    ],
    "name:kaz_x_preferred":[
        "\u0420\u043e\u0436\u0434\u0435\u0441\u0442\u0432\u0435\u043d\u043a\u0430"
    ],
    "name:nor_x_preferred":[
        "Rozjdestvenka"
    ],
    "name:rus_x_preferred":[
        "\u0420\u043e\u0436\u0434\u0435\u0441\u0442\u0432\u0435\u043d\u043a\u0430"
    ],
    "name:ukr_x_preferred":[
        "\u0420\u043e\u0436\u0434\u0435\u0441\u0442\u0432\u0435\u043d\u043a\u0430"
    ],
    "wof:name":"Rozhdestvenka",
    "wof:placetype":"locality"
},
  "geometry": {"coordinates":[133.76714999999999,45.79828],"type":"Point"}
}