{
  "type": "Feature",
  "properties": {
    "gn:admin1_code":"84",
    "gn:asciiname":"Kuznechikov",
    "gn:country_code":"RU",
    "gn:dem":61,
    "gn:feature_class":"P",
    "gn:feature_code":"PPL",
    "gn:name":"Kuznechikov",
    "gn:population":0,
    "gn:timezone":"Europe/Volgograd",
    "iso:country":"RU",
    "name:rus_x_preferred":[
        "\u041a\u0443\u0437\u043d\u0435\u0447\u0438\u043a\u043e\u0432"
    ],
    "name:und_x_variant":[
        "Kuznechiki"
    ],
    "wof:name":"Kuznechikov",
    "wof:placetype":"locality"
},
  "geometry": {"coordinates":[42.4948,49.5774],"type":"Point"}
}