{
  "type": "Feature",
  "properties": {
    "gn:admin1_code":"90",
    "gn:asciiname":"Fadeyeva",
    "gn:country_code":"RU",
    "gn:dem":147,
    "gn:feature_class":"P",
    "gn:feature_code":"PPL",
    "gn:name":"Fadeyeva",
    "gn:population":0,
    "gn:timezone":"Asia/Yekaterinburg",
    "iso:country":"RU",
    "name:rus_x_preferred":[
        "\u0424\u0430\u0434\u0435\u0435\u0432\u0430"
    ],
    "name:und_x_variant":[
        "\u0424\u0430\u0434\u0435\u0435\u0432\u0430"
    ],
    "wof:name":"Fadeyeva",
    "wof:placetype":"locality"
},
  "geometry": {"coordinates":[54.7559,59.2498],"type":"Point"}
}