{
  "type": "Feature",
  "properties": {
    "gn:admin1_code":"65.0",
    "gn:asciiname":"Yelkhovoye Ozero",
    "gn:country_code":"RU",
    "gn:dem":57,
    "gn:feature_class":"P",
    "gn:feature_code":"PPL",
    "gn:name":"Yelkhovoye Ozero",
    "gn:population":0,
    "gn:timezone":"Europe/Samara",
    "iso:country":"RU",
    "name:rus_x_preferred":[
        "\u0415\u043b\u0445\u043e\u0432\u043e\u0435 \u041e\u0437\u0435\u0440\u043e"
    ],
    "wof:name":"Yelkhovoye Ozero",
    "wof:placetype":"locality"
},
  "geometry": {"coordinates":[50.36756,53.99408],"type":"Point"}
}