{
  "type": "Feature",
  "properties": {
    "gn:admin1_code":"41.0",
    "gn:asciiname":"Nizhniy Voronok",
    "gn:country_code":"RU",
    "gn:dem":170,
    "gn:feature_class":"P",
    "gn:feature_code":"PPL",
    "gn:name":"Nizhniy Voronok",
    "gn:population":0,
    "gn:timezone":"Europe/Moscow",
    "iso:country":"RU",
    "name:rus_x_preferred":[
        "\u041d\u0438\u0436\u043d\u0438\u0439 \u0412\u043e\u0440\u043e\u043d\u043e\u043a"
    ],
    "name:und_x_variant":[
        "\u041d\u0438\u0436\u043d\u0438\u0439 \u0412\u043e\u0440\u043e\u043d\u043e\u043a"
    ],
    "wof:name":"Nizhniy Voronok",
    "wof:placetype":"locality"
},
  "geometry": {"coordinates":[34.7062,51.7227],"type":"Point"}
}