{
  "type": "Feature",
  "properties": {
    "gn:admin1_code":"60",
    "gn:asciiname":"Pashkovo",
    "gn:country_code":"RU",
    "gn:dem":105,
    "gn:feature_class":"P",
    "gn:feature_code":"PPL",
    "gn:name":"Pashkovo",
    "gn:population":0,
    "gn:timezone":"Europe/Moscow",
    "iso:country":"RU",
    "name:rus_x_preferred":[
        "\u041f\u0430\u0448\u043a\u043e\u0432\u043e"
    ],
    "wof:name":"Pashkovo",
    "wof:placetype":"locality"
},
  "geometry": {"coordinates":[29.7312,56.9885],"type":"Point"}
}