{
  "type": "Feature",
  "properties": {
    "gn:admin1_code":"51",
    "gn:asciiname":"Kuzhener",
    "gn:country_code":"RU",
    "gn:dem":146,
    "gn:feature_class":"P",
    "gn:feature_code":"PPL",
    "gn:name":"Kuzhener",
    "gn:population":0,
    "gn:timezone":"Europe/Moscow",
    "iso:country":"RU",
    "name:rus_x_preferred":[
        "\u041a\u0443\u0436\u0435\u043d\u0435\u0440"
    ],
    "wof:name":"Kuzhener",
    "wof:placetype":"locality"
},
  "geometry": {"coordinates":[46.915,57.7369],"type":"Point"}
}