{
  "type": "Feature",
  "properties": {
    "gn:admin1_code":"8",
    "gn:asciiname":"Tansaitovo",
    "gn:country_code":"RU",
    "gn:dem":157,
    "gn:feature_class":"P",
    "gn:feature_code":"PPL",
    "gn:name":"Tansaitovo",
    "gn:population":0,
    "gn:timezone":"Asia/Yekaterinburg",
    "iso:country":"RU",
    "name:rus_x_preferred":[
        "\u0422\u0430\u043d\u0441\u0430\u0438\u0442\u043e\u0432\u043e"
    ],
    "name:und_x_variant":[
        "\u0422\u0430\u043d\u0441\u0430\u0438\u0442\u043e\u0432\u043e",
        "Tanseitovo"
    ],
    "wof:name":"Tansaitovo",
    "wof:placetype":"locality"
},
  "geometry": {"coordinates":[55.63316,54.28957],"type":"Point"}
}