{
  "type": "Feature",
  "properties": {
    "gn:admin1_code":"25",
    "gn:asciiname":"Klevenevo",
    "gn:country_code":"RU",
    "gn:dem":217,
    "gn:feature_class":"P",
    "gn:feature_code":"PPL",
    "gn:name":"Klevenevo",
    "gn:population":0,
    "gn:timezone":"Europe/Moscow",
    "iso:country":"RU",
    "name:rus_x_preferred":[
        "\u041a\u043b\u0435\u0432\u0435\u043d\u044c\u0435\u0432\u043e"
    ],
    "name:und_x_variant":[
        "Kleven\u2019yevo",
        "Klevenevo"
    ],
    "wof:name":"Klevenevo",
    "wof:placetype":"locality"
},
  "geometry": {"coordinates":[35.12231,54.18143000000001],"type":"Point"}
}