{
  "type": "Feature",
  "properties": {
    "gn:admin1_code":"25.0",
    "gn:asciiname":"Ovrazhek",
    "gn:country_code":"RU",
    "gn:dem":213,
    "gn:feature_class":"P",
    "gn:feature_code":"PPL",
    "gn:name":"Ovrazhek",
    "gn:population":0,
    "gn:timezone":"Europe/Moscow",
    "iso:country":"RU",
    "name:rus_x_preferred":[
        "\u041e\u0432\u0440\u0430\u0436\u0435\u043a"
    ],
    "name:und_x_variant":[
        "\u041e\u0432\u0440\u0430\u0436\u0435\u043a"
    ],
    "wof:name":"Ovrazhek",
    "wof:placetype":"locality"
},
  "geometry": {"coordinates":[34.51593,54.16316],"type":"Point"}
}