{
  "type": "Feature",
  "properties": {
    "gn:admin1_code":"8",
    "gn:asciiname":"Idrisovo",
    "gn:country_code":"RU",
    "gn:dem":370,
    "gn:feature_class":"P",
    "gn:feature_code":"PPL",
    "gn:name":"Idrisovo",
    "gn:population":0,
    "gn:timezone":"Asia/Yekaterinburg",
    "iso:country":"RU",
    "name:eng_x_preferred":[
        "Idrisovo"
    ],
    "name:nor_x_preferred":[
        "Idrisovo"
    ],
    "name:rus_x_preferred":[
        "\u0418\u0434\u0440\u0438\u0441\u043e\u0432\u043e"
    ],
    "name:und_x_variant":[
        "Idrisova",
        "\u0418\u0434\u0440\u0438\u0441\u043e\u0432\u043e",
        "Idrisovo"
    ],
    "wof:name":"Idrisovo",
    "wof:placetype":"locality"
},
  "geometry": {"coordinates":[58.8627,55.3726],"type":"Point"}
}