{
  "type": "Feature",
  "properties": {
    "gn:admin1_code":"8",
    "gn:asciiname":"Idrisovo",
    "gn:country_code":"RU",
    "gn:dem":370,
    "gn:feature_class":"P",
    "gn:feature_code":"PPL",
    "gn:name":"Idrisovo",
    "gn:population":0,
    "gn:timezone":"Asia/Yekaterinburg",
    "iso:country":"RU",
    "name:bak_x_preferred":[
        "\u0418\u0499\u0440\u0438\u0441"
    ],
    "name:che_x_preferred":[
        "\u0418\u0434\u0440\u0438\u0441\u043e\u0432\u043e"
    ],
    "name:eng_x_preferred":[
        "Idrisovo"
    ],
    "name:hye_x_preferred":[
        "\u053b\u0564\u0580\u056b\u057d\u0578\u057e\u0578"
    ],
    "name:kat_x_preferred":[
        "\u10d8\u10d3\u10e0\u10d8\u10e1\u10dd\u10d5\u10dd"
    ],
    "name:kaz_x_preferred":[
        "\u0418\u0434\u0440\u0438\u0441"
    ],
    "name:kir_x_preferred":[
        "\u0418\u0434\u0440\u0438\u0441"
    ],
    "name:nor_x_preferred":[
        "Idrisovo"
    ],
    "name:rus_x_preferred":[
        "\u0418\u0434\u0440\u0438\u0441\u043e\u0432\u043e"
    ],
    "name:tat_x_preferred":[
        "\u0418\u0434\u0440\u0438\u0441"
    ],
    "name:ukr_x_preferred":[
        "\u0406\u0434\u0440\u0456\u0441\u043e\u0432\u043e"
    ],
    "name:und_x_variant":[
        "Idrisova",
        "\u0418\u0434\u0440\u0438\u0441\u043e\u0432\u043e",
        "Idrisovo"
    ],
    "wof:name":"Idrisovo",
    "wof:placetype":"locality"
},
  "geometry": {"coordinates":[58.8627,55.3726],"type":"Point"}
}