{
  "type": "Feature",
  "properties": {
    "gn:admin1_code":"75",
    "gn:asciiname":"Verkhniye Sokoly",
    "gn:country_code":"RU",
    "gn:dem":186,
    "gn:feature_class":"P",
    "gn:feature_code":"PPL",
    "gn:name":"Verkhniye Sokoly",
    "gn:population":0,
    "gn:timezone":"Asia/Tomsk",
    "iso:country":"RU",
    "name:und_x_variant":[
        "Sokoly",
        "Verkhniye Sokoly"
    ],
    "wof:name":"Verkhniye Sokoly",
    "wof:placetype":"locality"
},
  "geometry": {"coordinates":[85.7283,56.89941999999999],"type":"Point"}
}