{
  "type": "Feature",
  "properties": {
    "gn:admin1_code":"65.0",
    "gn:asciiname":"Avtozavodskiy Rayon",
    "gn:country_code":"RU",
    "gn:dem":104,
    "gn:feature_class":"P",
    "gn:feature_code":"PPL",
    "gn:name":"Avtozavodskiy Rayon",
    "gn:population":0,
    "gn:timezone":"Europe/Samara",
    "iso:country":"RU",
    "name:nor_x_preferred":[
        "Avtozavodskij Rajon"
    ],
    "name:rus_x_preferred":[
        "\u0410\u0432\u0442\u043e\u0437\u0430\u0432\u043e\u0434\u0441\u043a\u0438\u0439 \u0420\u0430\u0439\u043e\u043d"
    ],
    "wof:name":"Avtozavodskiy Rayon",
    "wof:placetype":"locality"
},
  "geometry": {"coordinates":[49.43333,53.51667],"type":"Point"}
}