{
  "type": "Feature",
  "properties": {
    "gn:country":"RU",
    "gn:fcode":"PPL",
    "gn:pop":3209,
    "iso:country":"RU",
    "name:eng_x_preferred":[
        "Bavleny"
    ],
    "name:rus_x_preferred":[
        "\u0411\u0430\u0432\u043b\u0435\u043d\u044b"
    ],
    "name:unk_x_variant":[
        "Bavieni"
    ],
    "qs:name":"Bavleny",
    "qs:name_adm0":"Russia",
    "qs:name_adm1":"Vladimir Oblast",
    "qs:photos_9k":1,
    "qs:photos_9r":1,
    "qs:photos_all":3,
    "qs:photos_sr":0,
    "qs:placetype":"Town",
    "qs:pop_sr":"4",
    "wof:name":"Bavleny",
    "wof:placetype":"locality",
    "wof:population":3209
},
  "geometry": {"coordinates":[39.56504,56.39448],"type":"Point"}
}