{
  "type": "Feature",
  "properties": {
    "gn:admin1_code":"73",
    "gn:asciiname":"Burtasy",
    "gn:country_code":"RU",
    "gn:dem":81,
    "gn:feature_class":"P",
    "gn:feature_code":"PPL",
    "gn:name":"Burtasy",
    "gn:population":0,
    "gn:timezone":"Europe/Moscow",
    "iso:country":"RU",
    "name:rus_x_preferred":[
        "\u0411\u0443\u0440\u0442\u0430\u0441\u044b"
    ],
    "name:und_x_variant":[
        "Russkiye Burtasy",
        "Burtasy"
    ],
    "wof:name":"Burtasy",
    "wof:placetype":"locality"
},
  "geometry": {"coordinates":[49.04185,55.39122],"type":"Point"}
}