{
  "type": "Feature",
  "properties": {
    "gn:admin1_code":"92",
    "gn:asciiname":"Razdol'nyy",
    "gn:country_code":"RU",
    "gn:dem":46,
    "gn:feature_class":"P",
    "gn:feature_code":"PPL",
    "gn:name":"Razdol\u2019nyy",
    "gn:population":0,
    "gn:timezone":"Asia/Kamchatka",
    "iso:country":"RU",
    "name:eng_x_preferred":[
        "Razdol'nyy"
    ],
    "name:nor_x_preferred":[
        "Razdolnyj"
    ],
    "name:rus_x_preferred":[
        "\u0420\u0430\u0437\u0434\u043e\u043b\u044c\u043d\u044b\u0439"
    ],
    "name:und_x_variant":[
        "Razdol\u2019nyy"
    ],
    "wof:name":"Razdol'nyy",
    "wof:placetype":"locality"
},
  "geometry": {"coordinates":[158.2884,53.27123],"type":"Point"}
}