{
  "type": "Feature",
  "properties": {
    "gn:admin1_code":"80",
    "gn:asciiname":"Yuski",
    "gn:country_code":"RU",
    "gn:dem":244,
    "gn:feature_class":"P",
    "gn:feature_code":"PPL",
    "gn:name":"Yuski",
    "gn:population":0,
    "gn:timezone":"Europe/Samara",
    "iso:country":"RU",
    "name:eng_x_preferred":[
        "Yuski"
    ],
    "name:nor_x_preferred":[
        "Juski"
    ],
    "name:rus_x_preferred":[
        "\u042e\u0441\u043a\u0438"
    ],
    "wof:name":"Yuski",
    "wof:placetype":"locality"
},
  "geometry": {"coordinates":[53.7752,57.9308],"type":"Point"}
}