{
  "type": "Feature",
  "properties": {
    "gn:admin1_code":"41",
    "gn:asciiname":"Lenina",
    "gn:country_code":"RU",
    "gn:dem":212,
    "gn:feature_class":"P",
    "gn:feature_code":"PPL",
    "gn:name":"Lenina",
    "gn:population":0,
    "gn:timezone":"Europe/Moscow",
    "iso:country":"RU",
    "name:cat_x_preferred":[
        "L\u00e9nina"
    ],
    "name:ceb_x_preferred":[
        "Lenina"
    ],
    "name:deu_x_preferred":[
        "Lenina"
    ],
    "name:hye_x_preferred":[
        "\u053c\u0565\u0576\u056b\u0576\u056b"
    ],
    "name:rus_x_preferred":[
        "\u043f\u0438\u043a \u041b\u0435\u043d\u0438\u043d\u0430"
    ],
    "name:rus_x_variant":[
        "\u041b\u0435\u043d\u0438\u043d\u0430"
    ],
    "name:spa_x_preferred":[
        "L\u00e9nina"
    ],
    "name:swe_x_preferred":[
        "Pik Lenina"
    ],
    "name:tur_x_preferred":[
        "Lenina"
    ],
    "name:ukr_x_preferred":[
        "\u041b\u0435\u043d\u0456\u043d\u0430"
    ],
    "name:und_x_variant":[
        "Leninskiy"
    ],
    "name:urd_x_preferred":[
        "\u0644\u06cc\u0646\u06cc\u0646\u0627"
    ],
    "name:vie_x_preferred":[
        "N\u00fai Lenina"
    ],
    "name:zho_cn_x_preferred":[
        "\u5217\u5b81\u5a1c\u5c71"
    ],
    "name:zho_tw_x_preferred":[
        "\u5217\u5be7\u5cf0"
    ],
    "wof:name":"Lenina",
    "wof:placetype":"locality"
},
  "geometry": {"coordinates":[35.8692,52.0289],"type":"Point"}
}