{
  "type": "Feature",
  "properties": {
    "gn:admin1_code":"60",
    "gn:asciiname":"Popova Gora",
    "gn:country_code":"RU",
    "gn:dem":146,
    "gn:feature_class":"P",
    "gn:feature_code":"PPL",
    "gn:name":"Popova Gora",
    "gn:population":0,
    "gn:timezone":"Europe/Moscow",
    "iso:country":"RU",
    "name:rus_x_preferred":[
        "\u041f\u043e\u043f\u043e\u0432\u0430 \u0413\u043e\u0440\u0430"
    ],
    "wof:name":"Popova Gora",
    "wof:placetype":"locality"
},
  "geometry": {"coordinates":[28.96429,56.79182],"type":"Point"}
}