{
  "type": "Feature",
  "properties": {
    "gn:admin1_code":"59.0",
    "gn:asciiname":"Ebergard",
    "gn:country_code":"RU",
    "gn:dem":62,
    "gn:feature_class":"P",
    "gn:feature_code":"PPL",
    "gn:name":"Ebergard",
    "gn:population":0,
    "gn:timezone":"Asia/Vladivostok",
    "iso:country":"RU",
    "name:nor_x_preferred":[
        "Ebergard"
    ],
    "name:rus_x_preferred":[
        "\u042d\u0431\u0435\u0440\u0433\u0430\u0440\u0434"
    ],
    "wof:name":"Ebergard",
    "wof:placetype":"locality"
},
  "geometry": {"coordinates":[133.78183000000001,46.03817],"type":"Point"}
}