{
  "type": "Feature",
  "properties": {
    "gn:admin1_code":"47",
    "gn:asciiname":"Khrushchevo",
    "gn:country_code":"RU",
    "gn:dem":147,
    "gn:feature_class":"P",
    "gn:feature_code":"PPL",
    "gn:name":"Khrushch\u00ebvo",
    "gn:population":0,
    "gn:timezone":"Europe/Moscow",
    "iso:country":"RU",
    "name:rus_x_preferred":[
        "\u0425\u0440\u0443\u0449\u0451\u0432\u043e"
    ],
    "name:und_x_variant":[
        "Khrushch\u00ebvo",
        "\u0425\u0440\u0443\u0449\u0451\u0432\u043e"
    ],
    "wof:name":"Khrushchevo",
    "wof:placetype":"locality"
},
  "geometry": {"coordinates":[36.41667,55.61666999999999],"type":"Point"}
}