{
  "type": "Feature",
  "properties": {
    "gn:admin1_code":"76",
    "gn:asciiname":"Vladimirovka",
    "gn:country_code":"RU",
    "gn:dem":248,
    "gn:feature_class":"P",
    "gn:feature_code":"PPL",
    "gn:name":"Vladimirovka",
    "gn:population":0,
    "gn:timezone":"Europe/Moscow",
    "iso:country":"RU",
    "name:aze_x_preferred":[
        "Vladimirovka"
    ],
    "name:bel_x_preferred":[
        "\u0423\u043b\u0430\u0434\u0437\u0456\u043c\u0456\u0440\u0430\u045e\u043a\u0430"
    ],
    "name:ceb_x_preferred":[
        "\u0412\u043b\u0430\u0434\u0438\u043c\u0438\u0440\u043e\u0432\u043a\u0430"
    ],
    "name:deu_x_preferred":[
        "Wladimirowka"
    ],
    "name:jpn_x_preferred":[
        "\u30f4\u30a9\u30ed\u30c7\u30a3\u30fc\u30e0\u30a3\u30ea\u30a6\u30ab"
    ],
    "name:kaz_x_preferred":[
        "\u0412\u043b\u0430\u0434\u0438\u043c\u0438\u0440\u043e\u0432\u043a\u0430"
    ],
    "name:rus_x_preferred":[
        "\u0412\u043b\u0430\u0434\u0438\u043c\u0438\u0440\u043e\u0432\u043a\u0430"
    ],
    "name:sco_x_preferred":[
        "Vladimirovka"
    ],
    "name:swe_x_preferred":[
        "Vladimirovka"
    ],
    "name:ukr_x_preferred":[
        "\u0412\u043e\u043b\u043e\u0434\u0438\u043c\u0438\u0440\u0456\u0432\u043a\u0430"
    ],
    "wof:name":"Vladimirovka",
    "wof:placetype":"locality"
},
  "geometry": {"coordinates":[37.8868,53.89471],"type":"Point"}
}