{
  "type": "Feature",
  "properties": {
    "gn:admin1_code":"8",
    "gn:asciiname":"Sharipkulovo",
    "gn:country_code":"RU",
    "gn:dem":150,
    "gn:feature_class":"P",
    "gn:feature_code":"PPL",
    "gn:name":"Sharipkulovo",
    "gn:population":0,
    "gn:timezone":"Asia/Yekaterinburg",
    "iso:country":"RU",
    "name:rus_x_preferred":[
        "\u0428\u0430\u0440\u0438\u043f\u043a\u0443\u043b\u043e\u0432\u043e"
    ],
    "wof:name":"Sharipkulovo",
    "wof:placetype":"locality"
},
  "geometry": {"coordinates":[56.2826,54.3628],"type":"Point"}
}