{
  "type": "Feature",
  "properties": {
    "gn:admin1_code":"8",
    "gn:asciiname":"Simskiy",
    "gn:country_code":"RU",
    "gn:dem":92,
    "gn:feature_class":"P",
    "gn:feature_code":"PPL",
    "gn:name":"Simskiy",
    "gn:population":0,
    "gn:timezone":"Asia/Yekaterinburg",
    "iso:country":"RU",
    "name:rus_x_preferred":[
        "\u0421\u0438\u043c\u0441\u043a\u0438\u0439"
    ],
    "wof:name":"Simskiy",
    "wof:placetype":"locality"
},
  "geometry": {"coordinates":[56.4457,54.4871],"type":"Point"}
}