{
  "type": "Feature",
  "properties": {
    "gn:admin1_code":"73",
    "gn:asciiname":"Sabay",
    "gn:country_code":"RU",
    "gn:dem":121,
    "gn:feature_class":"P",
    "gn:feature_code":"PPL",
    "gn:name":"Sabay",
    "gn:population":0,
    "gn:timezone":"Europe/Moscow",
    "iso:country":"RU",
    "name:rus_x_preferred":[
        "\u0421\u0430\u0431\u0430\u0439"
    ],
    "wof:name":"Sabay",
    "wof:placetype":"locality"
},
  "geometry": {"coordinates":[50.3021,55.994],"type":"Point"}
}