{
  "type": "Feature",
  "properties": {
    "gn:admin1_code":"93",
    "gn:asciiname":"Arkiya",
    "gn:country_code":"RU",
    "gn:dem":693,
    "gn:feature_class":"P",
    "gn:feature_code":"PPL",
    "gn:name":"Arkiya",
    "gn:population":0,
    "gn:timezone":"Asia/Chita",
    "iso:country":"RU",
    "name:nor_x_preferred":[
        "Arkia"
    ],
    "name:rus_x_preferred":[
        "\u0410\u0440\u043a\u0438\u044f"
    ],
    "wof:name":"Arkiya",
    "wof:placetype":"locality"
},
  "geometry": {"coordinates":[119.73333,51.61667],"type":"Point"}
}