{
  "type": "Feature",
  "properties": {
    "gn:admin1_code":"90",
    "gn:asciiname":"Shitoyevo",
    "gn:country_code":"RU",
    "gn:dem":193,
    "gn:feature_class":"P",
    "gn:feature_code":"PPL",
    "gn:name":"Shitoyevo",
    "gn:population":0,
    "gn:timezone":"Asia/Yekaterinburg",
    "iso:country":"RU",
    "name:rus_x_preferred":[
        "\u0428\u0438\u0442\u043e\u0435\u0432\u043e"
    ],
    "wof:name":"Shitoyevo",
    "wof:placetype":"locality"
},
  "geometry": {"coordinates":[54.50186,58.42729],"type":"Point"}
}