{
  "type": "Feature",
  "properties": {
    "gn:admin1_code":"47",
    "gn:asciiname":"Proskurnikovo",
    "gn:country_code":"RU",
    "gn:dem":162,
    "gn:feature_class":"P",
    "gn:feature_code":"PPL",
    "gn:name":"Proskurnikovo",
    "gn:population":0,
    "gn:timezone":"Europe/Moscow",
    "iso:country":"RU",
    "name:rus_x_preferred":[
        "\u041f\u0440\u043e\u0441\u043a\u0443\u0440\u043d\u0438\u043a\u043e\u0432\u043e"
    ],
    "name:und_x_variant":[
        "Proyekurnikovo",
        "Proskurnikovo"
    ],
    "wof:name":"Proskurnikovo",
    "wof:placetype":"locality"
},
  "geometry": {"coordinates":[37.96744,55.18289],"type":"Point"}
}