{
  "type": "Feature",
  "properties": {
    "gn:admin1_code":"85.0",
    "gn:asciiname":"Opurinskaya",
    "gn:country_code":"RU",
    "gn:dem":153,
    "gn:feature_class":"P",
    "gn:feature_code":"PPL",
    "gn:name":"Opurinskaya",
    "gn:population":0,
    "gn:timezone":"Europe/Moscow",
    "iso:country":"RU",
    "name:rus_x_preferred":[
        "\u041e\u043f\u0443\u0440\u0438\u043d\u0441\u043a\u0430\u044f"
    ],
    "wof:name":"Opurinskaya",
    "wof:placetype":"locality"
},
  "geometry": {"coordinates":[39.6258,60.184],"type":"Point"}
}