{
  "type": "Feature",
  "properties": {
    "gn:admin1_code":"70.0",
    "gn:asciiname":"Dvortsovskiy",
    "gn:country_code":"RU",
    "gn:dem":404,
    "gn:feature_class":"P",
    "gn:feature_code":"PPL",
    "gn:name":"Dvortsovskiy",
    "gn:population":0,
    "gn:timezone":"Europe/Moscow",
    "iso:country":"RU",
    "wof:name":"Dvortsovskiy",
    "wof:placetype":"locality"
},
  "geometry": {"coordinates":[42.80389,44.51667],"type":"Point"}
}