{
  "type": "Feature",
  "properties": {
    "gn:admin1_code":"73.0",
    "gn:asciiname":"Dimitarlau",
    "gn:country_code":"RU",
    "gn:dem":148,
    "gn:feature_class":"P",
    "gn:feature_code":"PPL",
    "gn:name":"Dimitarlau",
    "gn:population":0,
    "gn:timezone":"Europe/Moscow",
    "iso:country":"RU",
    "name:rus_x_preferred":[
        "\u0414\u0438\u043c\u0438\u0442\u0430\u0440\u043b\u0430\u0443"
    ],
    "name:und_x_variant":[
        "Dmitarlovo",
        "Dimitarlau",
        "\u0414\u0438\u043c\u0438\u0442\u0430\u0440\u043b\u0430\u0443"
    ],
    "wof:name":"Dimitarlau",
    "wof:placetype":"locality"
},
  "geometry": {"coordinates":[52.5423,55.2886],"type":"Point"}
}