{
  "type": "Feature",
  "properties": {
    "gn:admin1_code":"43.0",
    "gn:asciiname":"Gagarinskiy",
    "gn:cc2":"RU",
    "gn:country_code":"RU",
    "gn:dem":164,
    "gn:feature_class":"P",
    "gn:feature_code":"PPL",
    "gn:name":"Gagarinskiy",
    "gn:population":0,
    "gn:timezone":"Europe/Moscow",
    "iso:country":"RU",
    "name:rus_x_preferred":[
        "\u0413\u0430\u0433\u0430\u0440\u0438\u043d\u0441\u043a\u0438\u0439"
    ],
    "name:und_x_variant":[
        "Zhelyabovo",
        "Gagarinskiy",
        "\u0413\u0430\u0433\u0430\u0440\u0438\u043d\u0441\u043a\u0438\u0439"
    ],
    "wof:name":"Gagarinskiy",
    "wof:placetype":"locality"
},
  "geometry": {"coordinates":[39.70278,53.34556],"type":"Point"}
}