{
  "type": "Feature",
  "properties": {
    "gn:admin1_code":"6",
    "gn:asciiname":"Nasonovskaya",
    "gn:country_code":"RU",
    "gn:dem":79,
    "gn:feature_class":"P",
    "gn:feature_code":"PPL",
    "gn:name":"Nasonovskaya",
    "gn:population":0,
    "gn:timezone":"Europe/Moscow",
    "iso:country":"RU",
    "name:rus_x_preferred":[
        "\u041d\u0430\u0441\u043e\u043d\u043e\u0432\u0441\u043a\u0430\u044f"
    ],
    "name:und_x_variant":[
        "\u041d\u0430\u0441\u043e\u043d\u043e\u0432\u0441\u043a\u0430\u044f"
    ],
    "wof:name":"Nasonovskaya",
    "wof:placetype":"locality"
},
  "geometry": {"coordinates":[46.68191,61.64608000000001],"type":"Point"}
}