{
  "type": "Feature",
  "properties": {
    "gn:admin1_code":"86.0",
    "gn:asciiname":"Gnilusha",
    "gn:country_code":"RU",
    "gn:dem":118,
    "gn:feature_class":"P",
    "gn:feature_code":"PPL",
    "gn:name":"Gnilusha",
    "gn:population":0,
    "gn:timezone":"Europe/Moscow",
    "iso:country":"RU",
    "name:rus_x_preferred":[
        "\u0413\u043d\u0438\u043b\u0443\u0448\u0430"
    ],
    "name:und_x_variant":[
        "\u0413\u043d\u0438\u043b\u0443\u0448\u0430"
    ],
    "wof:name":"Gnilusha",
    "wof:placetype":"locality"
},
  "geometry": {"coordinates":[40.5067,51.8938],"type":"Point"}
}