{
  "type": "Feature",
  "properties": {
    "gn:admin1_code":"69",
    "gn:asciiname":"Skotarzh",
    "gn:country_code":"RU",
    "gn:dem":181,
    "gn:feature_class":"P",
    "gn:feature_code":"PPL",
    "gn:name":"Skotarzh",
    "gn:population":0,
    "gn:timezone":"Europe/Moscow",
    "iso:country":"RU",
    "name:eng_x_preferred":[
        "Skotarzh"
    ],
    "name:nor_x_preferred":[
        "Skotarzj"
    ],
    "name:rus_x_preferred":[
        "\u0421\u043a\u043e\u0442\u0430\u0440\u0436"
    ],
    "name:und_x_variant":[
        "\u0421\u043a\u043e\u0442\u0430\u0440\u0436",
        "Skotarzh"
    ],
    "wof:name":"Skotarzh",
    "wof:placetype":"locality"
},
  "geometry": {"coordinates":[32.86222,53.61694],"type":"Point"}
}