{
  "type": "Feature",
  "properties": {
    "gn:admin1_code":"45.0",
    "gn:asciiname":"Saltak",
    "gn:country_code":"RU",
    "gn:dem":138,
    "gn:feature_class":"P",
    "gn:feature_code":"PPL",
    "gn:name":"Saltak",
    "gn:population":0,
    "gn:timezone":"Europe/Moscow",
    "iso:country":"RU",
    "name:rus_x_preferred":[
        "\u0421\u0430\u043b\u0442\u0430\u043a"
    ],
    "name:und_x_variant":[
        "\u0421\u0430\u043b\u0442\u0430\u043a"
    ],
    "wof:name":"Saltak",
    "wof:placetype":"locality"
},
  "geometry": {"coordinates":[48.99,57.06],"type":"Point"}
}