{
  "type": "Feature",
  "properties": {
    "gn:admin1_code":"61",
    "gn:asciiname":"Novo-Dmitriyevskiy",
    "gn:country_code":"RU",
    "gn:dem":103,
    "gn:feature_class":"P",
    "gn:feature_code":"PPL",
    "gn:name":"Novo-Dmitriyevskiy",
    "gn:population":0,
    "gn:timezone":"Europe/Moscow",
    "iso:country":"RU",
    "name:rus_x_preferred":[
        "\u041d\u043e\u0432\u043e-\u0414\u043c\u0438\u0442\u0440\u0438\u0435\u0432\u0441\u043a\u0438\u0439"
    ],
    "name:und_x_variant":[
        "\u041d\u043e\u0432\u043e-\u0414\u043c\u0438\u0442\u0440\u0438\u0435\u0432\u0441\u043a\u0438\u0439"
    ],
    "wof:name":"Novo-Dmitriyevskiy",
    "wof:placetype":"locality"
},
  "geometry": {"coordinates":[39.35,47.68333],"type":"Point"}
}