{
  "type": "Feature",
  "properties": {
    "gn:admin1_code":"47",
    "gn:asciiname":"Saryb'yevo",
    "gn:country_code":"RU",
    "gn:dem":160,
    "gn:feature_class":"P",
    "gn:feature_code":"PPL",
    "gn:name":"Saryb\u2019yevo",
    "gn:population":0,
    "gn:timezone":"Europe/Moscow",
    "iso:country":"RU",
    "name:rus_x_preferred":[
        "\u0421\u0430\u0440\u044b\u0431\u044c\u0435\u0432\u043e"
    ],
    "name:und_x_variant":[
        "Saribyevo",
        "Saryb\u2019yevo",
        "\u0421\u0430\u0440\u044b\u0431\u044c\u0435\u0432\u043e"
    ],
    "wof:name":"Saryb'yevo",
    "wof:placetype":"locality"
},
  "geometry": {"coordinates":[38.96345,54.89648],"type":"Point"}
}