{
  "type": "Feature",
  "properties": {
    "gn:admin1_code":"33",
    "gn:asciiname":"Yelizarovo",
    "gn:country_code":"RU",
    "gn:dem":111,
    "gn:feature_class":"P",
    "gn:feature_code":"PPL",
    "gn:name":"Yelizarovo",
    "gn:population":0,
    "gn:timezone":"Europe/Kirov",
    "iso:country":"RU",
    "name:rus_x_preferred":[
        "\u0415\u043b\u0438\u0437\u0430\u0440\u043e\u0432\u043e"
    ],
    "wof:name":"Yelizarovo",
    "wof:placetype":"locality"
},
  "geometry": {"coordinates":[47.5066,60.2085],"type":"Point"}
}