{
  "type": "Feature",
  "properties": {
    "gn:admin1_code":"20",
    "gn:asciiname":"Tyekan",
    "gn:country_code":"RU",
    "gn:dem":467,
    "gn:feature_class":"P",
    "gn:feature_code":"PPL",
    "gn:name":"Tyekan",
    "gn:population":0,
    "gn:timezone":"Asia/Irkutsk",
    "iso:country":"RU",
    "name:eng_x_preferred":[
        "Tyekan"
    ],
    "name:nor_x_preferred":[
        "Tyekan"
    ],
    "name:rus_x_preferred":[
        "\u0422\u044b\u044d\u043a\u0430\u043d"
    ],
    "wof:name":"Tyekan",
    "wof:placetype":"locality"
},
  "geometry": {"coordinates":[107.73196000000002,55.31565],"type":"Point"}
}