{
  "type": "Feature",
  "properties": {
    "gn:admin1_code":"60",
    "gn:asciiname":"Priborok",
    "gn:country_code":"RU",
    "gn:dem":48,
    "gn:feature_class":"P",
    "gn:feature_code":"PPL",
    "gn:name":"Priborok",
    "gn:population":0,
    "gn:timezone":"Europe/Moscow",
    "iso:country":"RU",
    "name:rus_x_preferred":[
        "\u041f\u0440\u0438\u0431\u043e\u0440\u043e\u043a"
    ],
    "wof:name":"Priborok",
    "wof:placetype":"locality"
},
  "geometry": {"coordinates":[28.467,57.7397],"type":"Point"}
}