{
  "type": "Feature",
  "properties": {
    "gn:admin1_code":"87",
    "gn:asciiname":"Novyy Kiyevat",
    "gn:country_code":"RU",
    "gn:dem":9,
    "gn:feature_class":"P",
    "gn:feature_code":"PPL",
    "gn:name":"Novyy Kiyevat",
    "gn:population":0,
    "gn:timezone":"Asia/Yekaterinburg",
    "iso:country":"RU",
    "name:eng_x_preferred":[
        "Novyy Kiyevat"
    ],
    "name:nor_x_preferred":[
        "Nov.Kijevat"
    ],
    "name:rus_x_preferred":[
        "\u041d\u043e\u0432.\u041a\u0438\u0435\u0432\u0430\u0442"
    ],
    "name:rus_x_variant":[
        "\u041d\u043e\u0432\u044b\u0439 \u041a\u0438\u0435\u0432\u0430\u0442"
    ],
    "name:und_x_variant":[
        "Yurty Zimnyy Kevvatskiv",
        "Novyy Kiyevat",
        "\u041d\u043e\u0432\u044b\u0439 \u041a\u0438\u0435\u0432\u0430\u0442"
    ],
    "wof:name":"Novyy Kiyevat",
    "wof:placetype":"locality"
},
  "geometry": {"coordinates":[64.81284000000001,65.23278000000001],"type":"Point"}
}