{
  "type": "Feature",
  "properties": {
    "gn:admin1_code":"12.0",
    "gn:asciiname":"Shelkozavodskaya",
    "gn:country_code":"RU",
    "gn:dem":18,
    "gn:feature_class":"P",
    "gn:feature_code":"PPL",
    "gn:name":"Shelkozavodskaya",
    "gn:population":0,
    "gn:timezone":"Europe/Moscow",
    "iso:country":"RU",
    "name:che_x_preferred":[
        "\u015eelkozavodski"
    ],
    "name:che_x_variant":[
        "\u0428\u0435\u043b\u043a\u043e\u0437\u0430\u0432\u043e\u0434\u0441\u043a\u0438"
    ],
    "name:rus_x_preferred":[
        "\u0428\u0435\u043b\u043a\u043e\u0437\u0430\u0432\u043e\u0434\u0441\u043a\u0430\u044f"
    ],
    "name:rus_x_variant":[
        "\u0160elkozavodskaja"
    ],
    "name:und_x_variant":[
        "Shelkozavodskoye",
        "Shelkozavodskaya"
    ],
    "wof:name":"Shelkozavodskaya",
    "wof:placetype":"locality"
},
  "geometry": {"coordinates":[46.30705,43.49059000000001],"type":"Point"}
}