{
  "type": "Feature",
  "properties": {
    "gn:admin1_code":"40",
    "gn:asciiname":"Dukhovka",
    "gn:country_code":"RU",
    "gn:dem":66,
    "gn:feature_class":"P",
    "gn:feature_code":"PPL",
    "gn:name":"Dukhovka",
    "gn:population":0,
    "gn:timezone":"Asia/Yekaterinburg",
    "iso:country":"RU",
    "name:eng_x_preferred":[
        "Dukhovka"
    ],
    "name:nor_x_preferred":[
        "Dukhovka"
    ],
    "name:rus_x_preferred":[
        "\u0414\u0443\u0445\u043e\u0432\u043a\u0430"
    ],
    "name:und_x_variant":[
        "Bol\u2019shaya Dukhovka",
        "\u0414\u0443\u0445\u043e\u0432\u043a\u0430",
        "Dukhovka"
    ],
    "wof:name":"Dukhovka",
    "wof:placetype":"locality"
},
  "geometry": {"coordinates":[65.0808,56.3934],"type":"Point"}
}