{
  "type": "Feature",
  "properties": {
    "gn:admin1_code":"9.0",
    "gn:asciiname":"Rakovo",
    "gn:country_code":"RU",
    "gn:dem":148,
    "gn:feature_class":"P",
    "gn:feature_code":"PPL",
    "gn:name":"Rakovo",
    "gn:population":0,
    "gn:timezone":"Europe/Moscow",
    "iso:country":"RU",
    "name:bul_x_preferred":[
        "\u0420\u0430\u043a\u043e\u0432\u043e"
    ],
    "name:ceb_x_preferred":[
        "Rakovo"
    ],
    "name:deu_x_preferred":[
        "Rakowe"
    ],
    "name:epo_x_preferred":[
        "Rakovo"
    ],
    "name:fra_x_preferred":[
        "Rakovo"
    ],
    "name:ron_x_preferred":[
        "Rakovo"
    ],
    "name:rus_x_preferred":[
        "\u0420\u0430\u043a\u043e\u0432\u043e"
    ],
    "name:srp_x_preferred":[
        "\u0420\u0430\u043a\u043e\u0432\u043e"
    ],
    "name:swe_x_preferred":[
        "Rakovo"
    ],
    "name:ukr_x_preferred":[
        "\u0420\u0430\u043a\u043e\u0432\u0435"
    ],
    "wof:name":"Rakovo",
    "wof:placetype":"locality"
},
  "geometry": {"coordinates":[36.44463,50.68322],"type":"Point"}
}