{
  "type": "Feature",
  "properties": {
    "gn:admin1_code":"63",
    "gn:asciiname":"Kerak",
    "gn:country_code":"RU",
    "gn:dem":1134,
    "gn:feature_class":"P",
    "gn:feature_code":"PPL",
    "gn:name":"Kerak",
    "gn:population":0,
    "gn:timezone":"Asia/Yakutsk",
    "iso:country":"RU",
    "name:rus_x_preferred":[
        "\u041a\u0435\u0440\u0430\u043a"
    ],
    "wof:name":"Kerak",
    "wof:placetype":"locality"
},
  "geometry": {"coordinates":[125.40000000000001,57.93333000000001],"type":"Point"}
}