{
  "type": "Feature",
  "properties": {
    "gn:admin1_code":"56",
    "gn:asciiname":"Lebedinskiy",
    "gn:country_code":"RU",
    "gn:dem":214,
    "gn:feature_class":"P",
    "gn:feature_code":"PPL",
    "gn:name":"Lebedinskiy",
    "gn:population":0,
    "gn:timezone":"Europe/Moscow",
    "iso:country":"RU",
    "name:rus_x_preferred":[
        "\u041b\u0435\u0431\u0435\u0434\u0438\u043d\u0441\u043a\u0438\u0439"
    ],
    "wof:name":"Lebedinskiy",
    "wof:placetype":"locality"
},
  "geometry": {"coordinates":[35.1521,52.339],"type":"Point"}
}