{
  "type": "Feature",
  "properties": {
    "gn:admin1_code":"37",
    "gn:asciiname":"Zeblyaki",
    "gn:country_code":"RU",
    "gn:dem":128,
    "gn:feature_class":"P",
    "gn:feature_code":"PPL",
    "gn:name":"Zeblyaki",
    "gn:population":0,
    "gn:timezone":"Europe/Moscow",
    "iso:country":"RU",
    "name:eng_x_preferred":[
        "Zeblyaki"
    ],
    "name:nor_x_preferred":[
        "Zebljaki"
    ],
    "name:rus_x_preferred":[
        "\u0417\u0435\u0431\u043b\u044f\u043a\u0438"
    ],
    "wof:name":"Zeblyaki",
    "wof:placetype":"locality"
},
  "geometry": {"coordinates":[45.64999,58.42243000000001],"type":"Point"}
}