{
  "type": "Feature",
  "properties": {
    "gn:admin1_code":"25.0",
    "gn:asciiname":"Abiley",
    "gn:country_code":"RU",
    "gn:dem":206,
    "gn:feature_class":"P",
    "gn:feature_code":"PPL",
    "gn:name":"Abiley",
    "gn:population":0,
    "gn:timezone":"Europe/Moscow",
    "iso:country":"RU",
    "name:nor_x_preferred":[
        "Abilej"
    ],
    "name:rus_x_preferred":[
        "\u0410\u0431\u0438\u043b\u0435\u0439"
    ],
    "wof:name":"Abiley",
    "wof:placetype":"locality"
},
  "geometry": {"coordinates":[36.38365,54.77634000000001],"type":"Point"}
}