{
  "type": "Feature",
  "properties": {
    "gn:admin1_code":"63",
    "gn:asciiname":"Khocho",
    "gn:country_code":"RU",
    "gn:dem":131,
    "gn:feature_class":"P",
    "gn:feature_code":"PPL",
    "gn:name":"Khocho",
    "gn:population":0,
    "gn:timezone":"Asia/Yakutsk",
    "iso:country":"RU",
    "name:rus_x_preferred":[
        "\u0425\u043e\u0447\u043e"
    ],
    "name:und_x_variant":[
        "\u0425\u043e\u0447\u043e"
    ],
    "wof:name":"Khocho",
    "wof:placetype":"locality"
},
  "geometry": {"coordinates":[134.27365,62.21816],"type":"Point"}
}