{
  "type": "Feature",
  "properties": {
    "gn:admin1_code":"85",
    "gn:asciiname":"Rodishkino",
    "gn:country_code":"RU",
    "gn:dem":120,
    "gn:feature_class":"P",
    "gn:feature_code":"PPL",
    "gn:name":"Rodishkino",
    "gn:population":0,
    "gn:timezone":"Europe/Moscow",
    "iso:country":"RU",
    "name:rus_x_preferred":[
        "\u0420\u043e\u0434\u0438\u0448\u043a\u0438\u043d\u043e"
    ],
    "wof:name":"Rodishkino",
    "wof:placetype":"locality"
},
  "geometry": {"coordinates":[36.7639,58.7622],"type":"Point"}
}