{
  "type": "Feature",
  "properties": {
    "gn:admin1_code":"40",
    "gn:asciiname":"Imeni Budennogo",
    "gn:country_code":"RU",
    "gn:dem":130,
    "gn:feature_class":"P",
    "gn:feature_code":"PPL",
    "gn:name":"Imeni Bud\u00ebnnogo",
    "gn:population":0,
    "gn:timezone":"Asia/Yekaterinburg",
    "iso:country":"RU",
    "name:rus_x_preferred":[
        "\u0418\u043c\u0435\u043d\u0438 \u0411\u0443\u0434\u0451\u043d\u043d\u043e\u0433\u043e"
    ],
    "name:und_x_variant":[
        "Imeni Bud\u00ebnnogo"
    ],
    "wof:name":"Imeni Budennogo",
    "wof:placetype":"locality"
},
  "geometry": {"coordinates":[67.00694,55.2925],"type":"Point"}
}