{
  "type": "Feature",
  "properties": {
    "gn:admin1_code":"91.0",
    "gn:asciiname":"Rozhdestvenka",
    "gn:country_code":"RU",
    "gn:dem":241,
    "gn:feature_class":"P",
    "gn:feature_code":"PPL",
    "gn:name":"Rozhdestvenka",
    "gn:population":0,
    "gn:timezone":"Asia/Krasnoyarsk",
    "iso:country":"RU",
    "name:kaz_x_preferred":[
        "\u0420\u043e\u0436\u0434\u0435\u0441\u0442\u0432\u0435\u043d\u043a\u0430"
    ],
    "name:rus_x_preferred":[
        "\u0420\u043e\u0436\u0434\u0435\u0441\u0442\u0432\u0435\u043d\u043a\u0430"
    ],
    "name:ukr_x_preferred":[
        "\u0420\u043e\u0436\u0434\u0435\u0441\u0442\u0432\u0435\u043d\u043a\u0430"
    ],
    "wof:name":"Rozhdestvenka",
    "wof:placetype":"locality"
},
  "geometry": {"coordinates":[96.7911,56.2713],"type":"Point"}
}