{
  "type": "Feature",
  "properties": {
    "gn:admin1_code":"85",
    "gn:asciiname":"Shiri",
    "gn:country_code":"RU",
    "gn:dem":180,
    "gn:feature_class":"P",
    "gn:feature_code":"PPL",
    "gn:name":"Shiri",
    "gn:population":0,
    "gn:timezone":"Europe/Moscow",
    "iso:country":"RU",
    "name:ceb_x_preferred":[
        "Shiri"
    ],
    "name:deu_x_preferred":[
        "Shiri"
    ],
    "name:eng_x_preferred":[
        "Shiri"
    ],
    "name:nor_x_preferred":[
        "Sjiri"
    ],
    "name:rus_x_preferred":[
        "\u0428\u0438\u0440\u0438"
    ],
    "name:swe_x_preferred":[
        "Shiri"
    ],
    "name:und_x_variant":[
        "\u0428\u0438\u0440\u0438",
        "Shiri"
    ],
    "wof:name":"Shiri",
    "wof:placetype":"locality"
},
  "geometry": {"coordinates":[45.5426,59.28569],"type":"Point"}
}