{
  "type": "Feature",
  "properties": {
    "gn:admin1_code":"77",
    "gn:asciiname":"Kolentsevo",
    "gn:country_code":"RU",
    "gn:dem":125,
    "gn:feature_class":"P",
    "gn:feature_code":"PPL",
    "gn:name":"Kolentsevo",
    "gn:population":0,
    "gn:timezone":"Europe/Moscow",
    "iso:country":"RU",
    "name:rus_x_preferred":[
        "\u041a\u043e\u043b\u0435\u043d\u0446\u0435\u0432\u043e"
    ],
    "name:und_x_variant":[
        "\u041a\u043e\u043b\u0435\u043d\u0446\u0435\u0432\u043e"
    ],
    "wof:name":"Kolentsevo",
    "wof:placetype":"locality"
},
  "geometry": {"coordinates":[37.1125,57.2001],"type":"Point"}
}