{
  "type": "Feature",
  "properties": {
    "gn:admin1_code":"54",
    "gn:asciiname":"Yuzhno-Podol'sk",
    "gn:country_code":"RU",
    "gn:dem":107,
    "gn:feature_class":"P",
    "gn:feature_code":"PPL",
    "gn:name":"Yuzhno-Podol\u2019sk",
    "gn:population":0,
    "gn:timezone":"Asia/Omsk",
    "iso:country":"RU",
    "name:eng_x_preferred":[
        "Yuzhno-Podol'skoye"
    ],
    "name:nor_x_preferred":[
        "Juzjno-Podolsk"
    ],
    "name:rus_x_preferred":[
        "\u042e\u0436\u043d\u043e-\u041f\u043e\u0434\u043e\u043b\u044c\u0441\u043a"
    ],
    "name:und_x_variant":[
        "Yuzhno-Podol\u2019skoye",
        "Yuzhno-Podol\u2019sk"
    ],
    "wof:name":"Yuzhno-Podol'sk",
    "wof:placetype":"locality"
},
  "geometry": {"coordinates":[75.05731,54.41562],"type":"Point"}
}