{
  "type": "Feature",
  "properties": {
    "gn:admin1_code":"85",
    "gn:asciiname":"Usadishchi",
    "gn:country_code":"RU",
    "gn:dem":158,
    "gn:feature_class":"P",
    "gn:feature_code":"PPL",
    "gn:name":"Usadishchi",
    "gn:population":0,
    "gn:timezone":"Europe/Moscow",
    "iso:country":"RU",
    "name:rus_x_preferred":[
        "\u0423\u0441\u0430\u0434\u0438\u0449\u0438"
    ],
    "name:und_x_variant":[
        "\u0423\u0441\u0430\u0434\u0438\u0449\u0438"
    ],
    "wof:name":"Usadishchi",
    "wof:placetype":"locality"
},
  "geometry": {"coordinates":[35.20791,58.84983],"type":"Point"}
}