{
  "type": "Feature",
  "properties": {
    "gn:admin1_code":"60",
    "gn:asciiname":"Talets",
    "gn:country_code":"RU",
    "gn:dem":73,
    "gn:feature_class":"P",
    "gn:feature_code":"PPL",
    "gn:name":"Talets",
    "gn:population":0,
    "gn:timezone":"Europe/Moscow",
    "iso:country":"RU",
    "name:eng_x_preferred":[
        "Talets"
    ],
    "name:nor_x_preferred":[
        "Talets"
    ],
    "name:rus_x_preferred":[
        "\u0422\u0430\u043b\u0435\u0446"
    ],
    "wof:name":"Talets",
    "wof:placetype":"locality"
},
  "geometry": {"coordinates":[29.07193,57.83218000000001],"type":"Point"}
}