{
  "type": "Feature",
  "properties": {
    "gn:admin1_code":"4",
    "gn:asciiname":"Lugovoye",
    "gn:country_code":"RU",
    "gn:dem":151,
    "gn:feature_class":"P",
    "gn:feature_code":"PPL",
    "gn:name":"Lugovoye",
    "gn:population":0,
    "gn:timezone":"Asia/Barnaul",
    "iso:country":"RU",
    "name:eng_x_preferred":[
        "Lugovoye"
    ],
    "name:nor_x_preferred":[
        "Lugovoje"
    ],
    "name:rus_x_preferred":[
        "\u041b\u0443\u0433\u043e\u0432\u043e\u0435"
    ],
    "wof:name":"Lugovoye",
    "wof:placetype":"locality"
},
  "geometry": {"coordinates":[81.62269999999999,53.5127],"type":"Point"}
}