{
  "type": "Feature",
  "properties": {
    "gn:admin1_code":"88.0",
    "gn:asciiname":"Pavlovskoye",
    "gn:country_code":"RU",
    "gn:dem":168,
    "gn:feature_class":"P",
    "gn:feature_code":"PPL",
    "gn:name":"Pavlovskoye",
    "gn:population":0,
    "gn:timezone":"Europe/Moscow",
    "iso:country":"RU",
    "name:und_x_variant":[
        "Pavlovskaya",
        "Pavlovskoye"
    ],
    "wof:name":"Pavlovskoye",
    "wof:placetype":"locality"
},
  "geometry": {"coordinates":[40.13726,57.82434],"type":"Point"}
}