{
  "type": "Feature",
  "properties": {
    "gn:admin1_code":"24",
    "gn:asciiname":"Muzanga",
    "gn:country_code":"RU",
    "gn:dem":3,
    "gn:feature_class":"P",
    "gn:feature_code":"PPL",
    "gn:name":"Muzanga",
    "gn:population":0,
    "gn:timezone":"Europe/Moscow",
    "iso:country":"RU",
    "name:rus_x_preferred":[
        "\u041c\u0443\u0437\u0430\u043d\u0433\u0430"
    ],
    "name:und_x_variant":[
        "\u041c\u0443\u0437\u0430\u043d\u0433\u0430"
    ],
    "wof:name":"Muzanga",
    "wof:placetype":"locality"
},
  "geometry": {"coordinates":[45.13333,47.68333],"type":"Point"}
}