{
  "type": "Feature",
  "properties": {
    "gn:admin1_code":"90.0",
    "gn:asciiname":"Staraya Selishcha",
    "gn:country_code":"RU",
    "gn:dem":128,
    "gn:feature_class":"P",
    "gn:feature_code":"PPL",
    "gn:name":"Staraya Selishcha",
    "gn:population":0,
    "gn:timezone":"Asia/Yekaterinburg",
    "iso:country":"RU",
    "name:rus_x_preferred":[
        "\u0421\u0442\u0430\u0440\u0430\u044f \u0421\u0435\u043b\u0438\u0449\u0430"
    ],
    "name:und_x_variant":[
        "\u0421\u0442\u0430\u0440\u0430\u044f \u0421\u0435\u043b\u0438\u0449\u0430"
    ],
    "wof:name":"Staraya Selishcha",
    "wof:placetype":"locality"
},
  "geometry": {"coordinates":[55.1286,57.6479],"type":"Point"}
}