{
  "type": "Feature",
  "properties": {
    "gn:admin1_code":"16",
    "gn:asciiname":"Yamashi",
    "gn:country_code":"RU",
    "gn:dem":122,
    "gn:feature_class":"P",
    "gn:feature_code":"PPL",
    "gn:name":"Yamashi",
    "gn:population":0,
    "gn:timezone":"Europe/Moscow",
    "iso:country":"RU",
    "name:rus_x_preferred":[
        "\u042f\u043c\u0430\u0448\u0438"
    ],
    "wof:name":"Yamashi",
    "wof:placetype":"locality"
},
  "geometry": {"coordinates":[46.12101,55.73872],"type":"Point"}
}