{
  "type": "Feature",
  "properties": {
    "gn:admin1_code":"10",
    "gn:asciiname":"Uruch'ye",
    "gn:country_code":"RU",
    "gn:dem":146,
    "gn:feature_class":"P",
    "gn:feature_code":"PPL",
    "gn:name":"Uruch\u2019ye",
    "gn:population":0,
    "gn:timezone":"Europe/Moscow",
    "iso:country":"RU",
    "name:eng_x_preferred":[
        "Uruch'ye"
    ],
    "name:nor_x_preferred":[
        "Urutsje"
    ],
    "name:rus_x_preferred":[
        "\u0423\u0440\u0443\u0447\u044c\u0435"
    ],
    "name:und_x_variant":[
        "Uruch\u2019ye"
    ],
    "wof:name":"Uruch'ye",
    "wof:placetype":"locality"
},
  "geometry": {"coordinates":[33.96315999999999,52.91605],"type":"Point"}
}