{
  "type": "Feature",
  "properties": {
    "gn:admin1_code":"25",
    "gn:asciiname":"Koltenki",
    "gn:country_code":"RU",
    "gn:dem":215,
    "gn:feature_class":"P",
    "gn:feature_code":"PPL",
    "gn:name":"Kolt\u00ebnki",
    "gn:population":0,
    "gn:timezone":"Europe/Moscow",
    "iso:country":"RU",
    "name:rus_x_preferred":[
        "\u041a\u043e\u043b\u0442\u0451\u043d\u043a\u0438"
    ],
    "name:und_x_variant":[
        "Kolt\u00ebnki"
    ],
    "wof:name":"Koltenki",
    "wof:placetype":"locality"
},
  "geometry": {"coordinates":[35.5169,54.40976],"type":"Point"}
}