{
  "type": "Feature",
  "properties": {
    "gn:admin1_code":"52",
    "gn:asciiname":"Shchekotets",
    "gn:country_code":"RU",
    "gn:dem":23,
    "gn:feature_class":"P",
    "gn:feature_code":"PPL",
    "gn:name":"Shchekotets",
    "gn:population":0,
    "gn:timezone":"Europe/Moscow",
    "iso:country":"RU",
    "name:rus_x_preferred":[
        "\u0429\u0435\u043a\u043e\u0442\u0435\u0446"
    ],
    "name:und_x_variant":[
        "\u0429\u0435\u043a\u043e\u0442\u0435\u0446"
    ],
    "wof:name":"Shchekotets",
    "wof:placetype":"locality"
},
  "geometry": {"coordinates":[31.65776,58.02632],"type":"Point"}
}