{
  "type": "Feature",
  "properties": {
    "gn:admin1_code":"71",
    "gn:asciiname":"Srednyaya Poldnevaya",
    "gn:country_code":"RU",
    "gn:dem":146,
    "gn:feature_class":"P",
    "gn:feature_code":"PPL",
    "gn:name":"Srednyaya Poldnevaya",
    "gn:population":0,
    "gn:timezone":"Asia/Yekaterinburg",
    "iso:country":"RU",
    "name:rus_x_preferred":[
        "\u0421\u0440\u0435\u0434\u043d\u044f\u044f \u041f\u043e\u043b\u0434\u043d\u0435\u0432\u0430\u044f"
    ],
    "wof:name":"Srednyaya Poldnevaya",
    "wof:placetype":"locality"
},
  "geometry": {"coordinates":[62.26667,56.65],"type":"Point"}
}