{
  "type": "Feature",
  "properties": {
    "gn:admin1_code":"51",
    "gn:asciiname":"Butaki",
    "gn:country_code":"RU",
    "gn:dem":121,
    "gn:feature_class":"P",
    "gn:feature_code":"PPL",
    "gn:name":"Butaki",
    "gn:population":0,
    "gn:timezone":"Europe/Moscow",
    "iso:country":"RU",
    "name:rus_x_preferred":[
        "\u0411\u0443\u0442\u0430\u043a\u0438"
    ],
    "name:und_x_variant":[
        "\u0411\u0443\u0442\u0430\u043a\u0438"
    ],
    "wof:name":"Butaki",
    "wof:placetype":"locality"
},
  "geometry": {"coordinates":[44.33571,56.93899999999999],"type":"Point"}
}