{
  "type": "Feature",
  "properties": {
    "gn:admin1_code":"21",
    "gn:asciiname":"Shchurikha",
    "gn:country_code":"RU",
    "gn:dem":131,
    "gn:feature_class":"P",
    "gn:feature_code":"PPL",
    "gn:name":"Shchurikha",
    "gn:population":0,
    "gn:timezone":"Europe/Moscow",
    "iso:country":"RU",
    "name:rus_x_preferred":[
        "\u0429\u0443\u0440\u0438\u0445\u0430"
    ],
    "wof:name":"Shchurikha",
    "wof:placetype":"locality"
},
  "geometry": {"coordinates":[40.09754,56.97819000000001],"type":"Point"}
}