{
  "type": "Feature",
  "properties": {
    "gn:admin1_code":"93",
    "gn:asciiname":"Torgokon",
    "gn:country_code":"RU",
    "gn:dem":740,
    "gn:feature_class":"P",
    "gn:feature_code":"PPL",
    "gn:name":"Torgokon",
    "gn:population":0,
    "gn:timezone":"Asia/Chita",
    "iso:country":"RU",
    "wof:name":"Torgokon",
    "wof:placetype":"locality"
},
  "geometry": {"coordinates":[115.53333000000001,52.21667],"type":"Point"}
}