{
  "type": "Feature",
  "properties": {
    "gn:admin1_code":"22",
    "gn:asciiname":"Sunzhenskiy",
    "gn:country_code":"RU",
    "gn:dem":238,
    "gn:feature_class":"P",
    "gn:feature_code":"PPL",
    "gn:name":"Sunzhenskiy",
    "gn:population":0,
    "gn:timezone":"Europe/Moscow",
    "iso:country":"RU",
    "name:rus_x_preferred":[
        "\u0421\u0443\u043d\u0436\u0435\u043d\u0441\u043a\u0438\u0439"
    ],
    "name:und_x_variant":[
        "\u0421\u0443\u043d\u0436\u0435\u043d\u0441\u043a\u0438\u0439"
    ],
    "wof:name":"Sunzhenskiy",
    "wof:placetype":"locality"
},
  "geometry": {"coordinates":[44.03139,43.93361],"type":"Point"}
}