{
  "type": "Feature",
  "properties": {
    "gn:admin1_code":"60",
    "gn:asciiname":"Sidorovskiye",
    "gn:country_code":"RU",
    "gn:dem":54,
    "gn:feature_class":"P",
    "gn:feature_code":"PPL",
    "gn:name":"Sidorovskiye",
    "gn:population":0,
    "gn:timezone":"Europe/Moscow",
    "iso:country":"RU",
    "name:rus_x_preferred":[
        "\u0421\u0438\u0434\u043e\u0440\u043e\u0432\u0441\u043a\u0438\u0435"
    ],
    "wof:name":"Sidorovskiye",
    "wof:placetype":"locality"
},
  "geometry": {"coordinates":[28.17123,57.35111],"type":"Point"}
}