{
  "type": "Feature",
  "properties": {
    "gn:admin1_code":"47",
    "gn:asciiname":"Merchalovo",
    "gn:country_code":"RU",
    "gn:dem":200,
    "gn:feature_class":"P",
    "gn:feature_code":"PPL",
    "gn:name":"Merchalovo",
    "gn:population":0,
    "gn:timezone":"Europe/Moscow",
    "iso:country":"RU",
    "name:rus_x_preferred":[
        "\u041c\u0435\u0440\u0447\u0430\u043b\u043e\u0432\u043e"
    ],
    "name:und_x_variant":[
        "\u041c\u0435\u0440\u0447\u0430\u043b\u043e\u0432\u043e"
    ],
    "wof:name":"Merchalovo",
    "wof:placetype":"locality"
},
  "geometry": {"coordinates":[36.13944,55.39306],"type":"Point"}
}