{
  "type": "Feature",
  "properties": {
    "gn:admin1_code":"84",
    "gn:asciiname":"Staryy Pronin",
    "gn:country_code":"RU",
    "gn:dem":88,
    "gn:feature_class":"P",
    "gn:feature_code":"PPL",
    "gn:name":"Staryy Pronin",
    "gn:population":0,
    "gn:timezone":"Europe/Volgograd",
    "iso:country":"RU",
    "name:rus_x_preferred":[
        "\u0421\u0442\u0430\u0440\u044b\u0439 \u041f\u0440\u043e\u043d\u0438\u043d"
    ],
    "name:und_x_variant":[
        "\u0421\u0442\u0430\u0440\u044b\u0439 \u041f\u0440\u043e\u043d\u0438\u043d"
    ],
    "wof:name":"Staryy Pronin",
    "wof:placetype":"locality"
},
  "geometry": {"coordinates":[42.16667,49.18333],"type":"Point"}
}