{
  "type": "Feature",
  "properties": {
    "gn:admin1_code":"60",
    "gn:asciiname":"Susany",
    "gn:country_code":"RU",
    "gn:dem":88,
    "gn:feature_class":"P",
    "gn:feature_code":"PPL",
    "gn:name":"Susany",
    "gn:population":0,
    "gn:timezone":"Europe/Moscow",
    "iso:country":"RU",
    "name:rus_x_preferred":[
        "\u0421\u0443\u0441\u0430\u043d\u044b"
    ],
    "wof:name":"Susany",
    "wof:placetype":"locality"
},
  "geometry": {"coordinates":[28.37207,56.95635],"type":"Point"}
}