{
  "type": "Feature",
  "properties": {
    "gn:admin1_code":"61",
    "gn:asciiname":"Yelizavetinskaya",
    "gn:country_code":"RU",
    "gn:dem":1,
    "gn:feature_class":"P",
    "gn:feature_code":"PPL",
    "gn:name":"Yelizavetinskaya",
    "gn:population":0,
    "gn:timezone":"Europe/Moscow",
    "iso:country":"RU",
    "name:eng_x_preferred":[
        "Yelizavetinskaya"
    ],
    "name:nor_x_preferred":[
        "Jelizavetinskaja"
    ],
    "name:rus_x_preferred":[
        "\u0415\u043b\u0438\u0437\u0430\u0432\u0435\u0442\u0438\u043d\u0441\u043a\u0430\u044f"
    ],
    "name:und_x_variant":[
        "Yelizavetovskaya",
        "Yelizavetovka",
        "Yelizavetinskaya"
    ],
    "wof:name":"Yelizavetinskaya",
    "wof:placetype":"locality"
},
  "geometry": {"coordinates":[39.47454000000001,47.13457],"type":"Point"}
}