{
  "type": "Feature",
  "properties": {
    "gn:admin1_code":"34",
    "gn:asciiname":"Yevdino",
    "gn:country_code":"RU",
    "gn:dem":115,
    "gn:feature_class":"P",
    "gn:feature_code":"PPL",
    "gn:name":"Yevdino",
    "gn:population":0,
    "gn:timezone":"Europe/Moscow",
    "iso:country":"RU",
    "name:eng_x_preferred":[
        "Yevdino"
    ],
    "name:nor_x_preferred":[
        "Jevdino"
    ],
    "name:rus_x_preferred":[
        "\u0415\u0432\u0434\u0438\u043d\u043e"
    ],
    "name:und_x_variant":[
        "Yelvino"
    ],
    "wof:name":"Yevdino",
    "wof:placetype":"locality"
},
  "geometry": {"coordinates":[50.88028,63.04885],"type":"Point"}
}