{
  "type": "Feature",
  "properties": {
    "gn:admin1_code":"10.0",
    "gn:asciiname":"Bazhenov",
    "gn:country_code":"RU",
    "gn:dem":199,
    "gn:feature_class":"P",
    "gn:feature_code":"PPL",
    "gn:name":"Bazhenov",
    "gn:population":0,
    "gn:timezone":"Europe/Moscow",
    "iso:country":"RU",
    "name:deu_x_preferred":[
        "Baschenow"
    ],
    "name:fra_x_preferred":[
        "Bajenov"
    ],
    "name:nor_x_preferred":[
        "Bazjenov"
    ],
    "name:rus_x_preferred":[
        "\u0411\u0430\u0436\u0435\u043d\u043e\u0432"
    ],
    "name:ukr_x_preferred":[
        "\u0411\u0430\u0436\u0435\u043d\u043e\u0432"
    ],
    "wof:name":"Bazhenov",
    "wof:placetype":"locality"
},
  "geometry": {"coordinates":[33.78528,53.89333000000001],"type":"Point"}
}