{
  "type": "Feature",
  "properties": {
    "gn:admin1_code":"8",
    "gn:asciiname":"Ay",
    "gn:country_code":"RU",
    "gn:dem":208,
    "gn:feature_class":"P",
    "gn:feature_code":"PPL",
    "gn:name":"Ay",
    "gn:population":0,
    "gn:timezone":"Asia/Yekaterinburg",
    "iso:country":"RU",
    "name:nor_x_preferred":[
        "Aj"
    ],
    "name:rus_x_preferred":[
        "\u0410\u0439"
    ],
    "wof:name":"Ay",
    "wof:placetype":"locality"
},
  "geometry": {"coordinates":[58.1844,55.9668],"type":"Point"}
}