{
  "type": "Feature",
  "properties": {
    "gn:admin1_code":"8",
    "gn:asciiname":"Ay",
    "gn:country_code":"RU",
    "gn:dem":208,
    "gn:feature_class":"P",
    "gn:feature_code":"PPL",
    "gn:name":"Ay",
    "gn:population":0,
    "gn:timezone":"Asia/Yekaterinburg",
    "iso:country":"RU",
    "name:ara_x_preferred":[
        "\u0622\u064a"
    ],
    "name:aze_x_preferred":[
        "II Eye"
    ],
    "name:bul_x_preferred":[
        "\u0410\u0439"
    ],
    "name:ces_x_preferred":[
        "Aj"
    ],
    "name:dan_x_preferred":[
        "Kheperkheprure Ay"
    ],
    "name:deu_x_preferred":[
        "Eje"
    ],
    "name:fas_x_preferred":[
        "\u0622\u06cc\u06cc"
    ],
    "name:heb_x_preferred":[
        "\u05d0\u05d9\u05d9"
    ],
    "name:kat_x_preferred":[
        "\u10d4\u10d8\u10d4"
    ],
    "name:kor_x_preferred":[
        "\uc544\uc774"
    ],
    "name:lit_x_preferred":[
        "Ajas"
    ],
    "name:nld_x_preferred":[
        "Eje"
    ],
    "name:nor_x_preferred":[
        "Aj"
    ],
    "name:nor_x_variant":[
        "Kheperkheprure Ai"
    ],
    "name:pol_x_preferred":[
        "Aj"
    ],
    "name:por_x_preferred":[
        "A\u00ed"
    ],
    "name:ron_x_preferred":[
        "Ay"
    ],
    "name:rus_x_preferred":[
        "\u0410\u0439"
    ],
    "name:rus_x_variant":[
        "\u042d\u0439\u0435"
    ],
    "name:sin_x_preferred":[
        "\u0d86\u0dba\u0dd2"
    ],
    "name:slk_x_preferred":[
        "Aje"
    ],
    "name:slv_x_preferred":[
        "Aj"
    ],
    "name:srp_x_preferred":[
        "\u0410\u0458"
    ],
    "name:swe_x_preferred":[
        "Ay"
    ],
    "name:tgl_x_preferred":[
        "Ay"
    ],
    "name:tha_x_preferred":[
        "\u0e1f\u0e32\u0e42\u0e23\u0e2b\u0e4c\u0e40\u0e04\u0e40\u0e1b\u0e2d\u0e23\u0e4c\u0e40\u0e04\u0e40\u0e1b\u0e2d\u0e23\u0e4c\u0e23\u0e39\u0e40\u0e23 \u0e44\u0e2d\u0e22\u0e4c"
    ],
    "name:tur_x_preferred":[
        "Ay"
    ],
    "name:ukr_x_preferred":[
        "\u0410\u0439"
    ],
    "name:vie_x_preferred":[
        "Ay"
    ],
    "wof:name":"Ay",
    "wof:placetype":"locality"
},
  "geometry": {"coordinates":[58.1844,55.9668],"type":"Point"}
}