{
  "type": "Feature",
  "properties": {
    "gn:admin1_code":"57",
    "gn:asciiname":"Yavleyka",
    "gn:country_code":"RU",
    "gn:dem":244,
    "gn:feature_class":"P",
    "gn:feature_code":"PPL",
    "gn:name":"Yavleyka",
    "gn:population":0,
    "gn:timezone":"Europe/Moscow",
    "iso:country":"RU",
    "name:rus_x_preferred":[
        "\u042f\u0432\u043b\u0435\u0439\u043a\u0430"
    ],
    "name:und_x_variant":[
        "\u042f\u0432\u043b\u0435\u0439\u043a\u0430"
    ],
    "wof:name":"Yavleyka",
    "wof:placetype":"locality"
},
  "geometry": {"coordinates":[46.80662,53.26923000000001],"type":"Point"}
}