{
  "type": "Feature",
  "properties": {
    "gn:admin1_code":"8",
    "gn:asciiname":"Pichugino",
    "gn:country_code":"RU",
    "gn:dem":290,
    "gn:feature_class":"P",
    "gn:feature_code":"PPL",
    "gn:name":"Pichugino",
    "gn:population":0,
    "gn:timezone":"Asia/Yekaterinburg",
    "iso:country":"RU",
    "name:rus_x_preferred":[
        "\u041f\u0438\u0447\u0443\u0433\u0438\u043d\u043e"
    ],
    "wof:name":"Pichugino",
    "wof:placetype":"locality"
},
  "geometry": {"coordinates":[57.96475,55.60141],"type":"Point"}
}