{
  "type": "Feature",
  "properties": {
    "gn:admin1_code":"85.0",
    "gn:asciiname":"Talinskoye",
    "gn:country_code":"RU",
    "gn:dem":155,
    "gn:feature_class":"P",
    "gn:feature_code":"PPL",
    "gn:name":"Talinskoye",
    "gn:population":0,
    "gn:timezone":"Europe/Moscow",
    "iso:country":"RU",
    "name:rus_x_preferred":[
        "\u0422\u0430\u043b\u0438\u043d\u0441\u043a\u043e\u0435"
    ],
    "name:und_x_variant":[
        "\u0422\u0430\u043b\u0438\u043d\u0441\u043a\u043e\u0435",
        "Galinskaya"
    ],
    "wof:name":"Talinskoye",
    "wof:placetype":"locality"
},
  "geometry": {"coordinates":[38.13385,59.66544],"type":"Point"}
}