{
  "type": "Feature",
  "properties": {
    "gn:admin1_code":"62",
    "gn:asciiname":"Ivashkovo",
    "gn:country_code":"RU",
    "gn:dem":124,
    "gn:feature_class":"P",
    "gn:feature_code":"PPL",
    "gn:name":"Ivashkovo",
    "gn:population":0,
    "gn:timezone":"Europe/Moscow",
    "iso:country":"RU",
    "name:rus_x_preferred":[
        "\u0418\u0432\u0430\u0448\u043a\u043e\u0432\u043e"
    ],
    "wof:name":"Ivashkovo",
    "wof:placetype":"locality"
},
  "geometry": {"coordinates":[40.0521,54.4481],"type":"Point"}
}