{
  "type": "Feature",
  "properties": {
    "gn:admin1_code":"33",
    "gn:asciiname":"Serdovinskaya",
    "gn:country_code":"RU",
    "gn:dem":110,
    "gn:feature_class":"P",
    "gn:feature_code":"PPL",
    "gn:name":"Serdovinskaya",
    "gn:population":0,
    "gn:timezone":"Europe/Kirov",
    "iso:country":"RU",
    "name:rus_x_preferred":[
        "\u0421\u0435\u0440\u0434\u043e\u0432\u0438\u043d\u0441\u043a\u0430\u044f"
    ],
    "name:und_x_variant":[
        "\u0421\u0435\u0440\u0434\u043e\u0432\u0438\u043d\u0441\u043a\u0430\u044f"
    ],
    "wof:name":"Serdovinskaya",
    "wof:placetype":"locality"
},
  "geometry": {"coordinates":[50.21667,57.83333],"type":"Point"}
}