{
  "type": "Feature",
  "properties": {
    "gn:admin1_code":"77",
    "gn:asciiname":"Klechki",
    "gn:country_code":"RU",
    "gn:dem":250,
    "gn:feature_class":"P",
    "gn:feature_code":"PPL",
    "gn:name":"Klechki",
    "gn:population":0,
    "gn:timezone":"Europe/Moscow",
    "iso:country":"RU",
    "name:rus_x_preferred":[
        "\u041a\u043b\u0435\u0447\u043a\u0438"
    ],
    "name:und_x_variant":[
        "\u041a\u043b\u0435\u0447\u043a\u0438"
    ],
    "wof:name":"Klechki",
    "wof:placetype":"locality"
},
  "geometry": {"coordinates":[33.53333,56.18333000000001],"type":"Point"}
}