{
  "type": "Feature",
  "properties": {
    "gn:admin1_code":"13",
    "gn:asciiname":"Verkhniy Iremel'",
    "gn:country_code":"RU",
    "gn:dem":444,
    "gn:feature_class":"P",
    "gn:feature_code":"PPL",
    "gn:name":"Verkhniy Iremel\u2019",
    "gn:population":0,
    "gn:timezone":"Asia/Yekaterinburg",
    "iso:country":"RU",
    "name:rus_x_preferred":[
        "\u0412\u0435\u0440\u0445\u043d\u0438\u0439 \u0418\u0440\u0435\u043c\u0435\u043b\u044c"
    ],
    "name:und_x_variant":[
        "Verkhne-Iremel\u2019sk",
        "Verkhniy Iremel\u2019"
    ],
    "wof:name":"Verkhniy Iremel'",
    "wof:placetype":"locality"
},
  "geometry": {"coordinates":[59.7401,54.8859],"type":"Point"}
}