{
  "type": "Feature",
  "properties": {
    "gn:admin1_code":"64",
    "gn:asciiname":"Rybaki",
    "gn:country_code":"RU",
    "gn:dem":41,
    "gn:feature_class":"P",
    "gn:feature_code":"PPL",
    "gn:name":"Rybaki",
    "gn:population":0,
    "gn:timezone":"Asia/Magadan",
    "iso:country":"RU",
    "name:eng_x_preferred":[
        "Rybaki"
    ],
    "name:fra_x_preferred":[
        "Rybaki"
    ],
    "name:lit_x_preferred":[
        "Ribakai"
    ],
    "name:nor_x_preferred":[
        "Rybaki"
    ],
    "name:pol_x_preferred":[
        "Rybaki"
    ],
    "name:rus_x_preferred":[
        "\u0420\u044b\u0431\u0430\u043a\u0438"
    ],
    "name:ukr_x_preferred":[
        "\u0420\u0438\u0431\u0430\u043a\u0456"
    ],
    "name:und_x_variant":[
        "Arimoe",
        "Arimoi",
        "Arimoye"
    ],
    "wof:name":"Rybaki",
    "wof:placetype":"locality"
},
  "geometry": {"coordinates":[147.84637000000001,45.20785],"type":"Point"}
}