{
  "type": "Feature",
  "properties": {
    "gn:admin1_code":"8",
    "gn:asciiname":"Kuyurgazy",
    "gn:country_code":"RU",
    "gn:dem":140,
    "gn:feature_class":"P",
    "gn:feature_code":"PPL",
    "gn:name":"Kuyurgazy",
    "gn:population":0,
    "gn:timezone":"Asia/Yekaterinburg",
    "iso:country":"RU",
    "name:rus_x_preferred":[
        "\u041a\u0443\u044e\u0440\u0433\u0430\u0437\u044b"
    ],
    "wof:name":"Kuyurgazy",
    "wof:placetype":"locality"
},
  "geometry": {"coordinates":[55.5603,52.496],"type":"Point"}
}