{
  "type": "Feature",
  "properties": {
    "gn:admin1_code":"54",
    "gn:asciiname":"Kuygaly",
    "gn:country_code":"RU",
    "gn:dem":103,
    "gn:feature_class":"P",
    "gn:feature_code":"PPL",
    "gn:name":"Kuygaly",
    "gn:population":0,
    "gn:timezone":"Asia/Omsk",
    "iso:country":"RU",
    "name:eng_x_preferred":[
        "Kuygaly"
    ],
    "name:nor_x_preferred":[
        "Kujgaly"
    ],
    "name:rus_x_preferred":[
        "\u041a\u0443\u0439\u0433\u0430\u043b\u044b"
    ],
    "wof:name":"Kuygaly",
    "wof:placetype":"locality"
},
  "geometry": {"coordinates":[74.16115000000001,56.22065],"type":"Point"}
}