{
  "type": "Feature",
  "properties": {
    "gn:admin1_code":"69.0",
    "gn:asciiname":"Durmanovka",
    "gn:country_code":"RU",
    "gn:dem":203,
    "gn:feature_class":"P",
    "gn:feature_code":"PPL",
    "gn:name":"Durmanovka",
    "gn:population":0,
    "gn:timezone":"Europe/Moscow",
    "iso:country":"RU",
    "name:rus_x_preferred":[
        "\u0414\u0443\u0440\u043c\u0430\u043d\u043e\u0432\u043a\u0430"
    ],
    "name:und_x_variant":[
        "\u0414\u0443\u0440\u043c\u0430\u043d\u043e\u0432\u043a\u0430"
    ],
    "wof:name":"Durmanovka",
    "wof:placetype":"locality"
},
  "geometry": {"coordinates":[33.25194,54.04583],"type":"Point"}
}