{
  "type": "Feature",
  "properties": {
    "gn:admin1_code":"42",
    "gn:asciiname":"Pan'shino",
    "gn:country_code":"RU",
    "gn:dem":109,
    "gn:feature_class":"P",
    "gn:feature_code":"PPL",
    "gn:name":"Pan\u2019shino",
    "gn:population":0,
    "gn:timezone":"Europe/Moscow",
    "iso:country":"RU",
    "name:rus_x_preferred":[
        "\u041f\u0430\u043d\u044c\u0448\u0438\u043d\u043e"
    ],
    "name:und_x_variant":[
        "Pan\u2019shino",
        "\u041f\u0430\u043d\u044c\u0448\u0438\u043d\u043e"
    ],
    "wof:name":"Pan'shino",
    "wof:placetype":"locality"
},
  "geometry": {"coordinates":[34.285,59.78083],"type":"Point"}
}