{
  "type": "Feature",
  "properties": {
    "gn:admin1_code":"63",
    "gn:asciiname":"Symakh",
    "gn:country_code":"RU",
    "gn:dem":159,
    "gn:feature_class":"P",
    "gn:feature_code":"PPL",
    "gn:name":"Symakh",
    "gn:population":0,
    "gn:timezone":"Asia/Yakutsk",
    "iso:country":"RU",
    "name:che_x_preferred":[
        "\u0421\u044b\u043c\u0430\u0445"
    ],
    "name:eng_x_preferred":[
        "Symakh"
    ],
    "name:hye_x_preferred":[
        "\u054d\u056b\u0574\u0561\u056d"
    ],
    "name:nor_x_preferred":[
        "Symakh"
    ],
    "name:rus_x_preferred":[
        "\u0421\u044b\u043c\u0430\u0445"
    ],
    "name:sah_x_preferred":[
        "\u0421\u044b\u044b\u043c\u0430\u0445"
    ],
    "name:und_x_variant":[
        "Syymakh"
    ],
    "wof:name":"Symakh",
    "wof:placetype":"locality"
},
  "geometry": {"coordinates":[130.95937000000001,61.92503000000001],"type":"Point"}
}