{
  "type": "Feature",
  "properties": {
    "gn:admin1_code":"51.0",
    "gn:asciiname":"Bol'shiye Lomy",
    "gn:country_code":"RU",
    "gn:dem":135,
    "gn:feature_class":"P",
    "gn:feature_code":"PPL",
    "gn:name":"Bol\u2019shiye Lomy",
    "gn:population":0,
    "gn:timezone":"Europe/Moscow",
    "iso:country":"RU",
    "name:rus_x_preferred":[
        "\u0411\u043e\u043b\u044c\u0448\u0438\u0435 \u041b\u043e\u043c\u044b"
    ],
    "name:und_x_variant":[
        "Bol\u2019shiye Lomy"
    ],
    "wof:name":"Bol'shiye Lomy",
    "wof:placetype":"locality"
},
  "geometry": {"coordinates":[46.26089,57.69013],"type":"Point"}
}