{
  "type": "Feature",
  "properties": {
    "gn:admin1_code":"47",
    "gn:asciiname":"Kiselevo",
    "gn:cc2":"RU",
    "gn:country_code":"RU",
    "gn:dem":264,
    "gn:feature_class":"P",
    "gn:feature_code":"PPL",
    "gn:name":"Kisel\u00ebvo",
    "gn:population":0,
    "gn:timezone":"Europe/Moscow",
    "iso:country":"RU",
    "name:eng_x_preferred":[
        "Kisel\u00ebvo"
    ],
    "name:nor_x_preferred":[
        "Kiselevo"
    ],
    "name:rus_x_preferred":[
        "\u041a\u0438\u0441\u0435\u043b\u0435\u0432\u043e"
    ],
    "name:rus_x_variant":[
        "\u041a\u0438\u0441\u0435\u043b\u0451\u0432\u043e"
    ],
    "name:und_x_variant":[
        "Kiseleva",
        "Kisel\u00ebvo",
        "\u041a\u0438\u0441\u0435\u043b\u0451\u0432\u043e"
    ],
    "wof:name":"Kiselevo",
    "wof:placetype":"locality"
},
  "geometry": {"coordinates":[35.46083,55.42028000000001],"type":"Point"}
}