{
  "type": "Feature",
  "properties": {
    "gn:admin1_code":"47.0",
    "gn:admin2_code":"472430",
    "gn:asciiname":"Maslennikovo",
    "gn:country_code":"RU",
    "gn:dem":153,
    "gn:feature_class":"P",
    "gn:feature_code":"PPL",
    "gn:name":"Maslennikovo",
    "gn:population":0,
    "gn:timezone":"Europe/Moscow",
    "iso:country":"RU",
    "name:rus_x_preferred":[
        "\u041c\u0430\u0441\u043b\u0435\u043d\u043d\u0438\u043a\u043e\u0432\u043e"
    ],
    "wof:name":"Maslennikovo",
    "wof:placetype":"locality"
},
  "geometry": {"coordinates":[35.91196,56.11945],"type":"Point"}
}