{
  "type": "Feature",
  "properties": {
    "gn:admin1_code":"83",
    "gn:asciiname":"Turygino",
    "gn:country_code":"RU",
    "gn:dem":165,
    "gn:feature_class":"P",
    "gn:feature_code":"PPL",
    "gn:name":"Turygino",
    "gn:population":0,
    "gn:timezone":"Europe/Moscow",
    "iso:country":"RU",
    "name:rus_x_preferred":[
        "\u0422\u0443\u0440\u044b\u0433\u0438\u043d\u043e"
    ],
    "wof:name":"Turygino",
    "wof:placetype":"locality"
},
  "geometry": {"coordinates":[39.81162,56.33062],"type":"Point"}
}