{
  "type": "Feature",
  "properties": {
    "gn:admin1_code":"71",
    "gn:asciiname":"Chechulina",
    "gn:country_code":"RU",
    "gn:dem":194,
    "gn:feature_class":"P",
    "gn:feature_code":"PPL",
    "gn:name":"Chechulina",
    "gn:population":0,
    "gn:timezone":"Asia/Yekaterinburg",
    "iso:country":"RU",
    "name:eng_x_preferred":[
        "Chechulina"
    ],
    "name:nor_x_preferred":[
        "Tsjetsjulina"
    ],
    "name:rus_x_preferred":[
        "\u0427\u0435\u0447\u0443\u043b\u0438\u043d\u0430"
    ],
    "name:und_x_variant":[
        "Chechulino",
        "\u0427\u0435\u0447\u0443\u043b\u0438\u043d\u0430",
        "Chechulina"
    ],
    "wof:name":"Chechulina",
    "wof:placetype":"locality"
},
  "geometry": {"coordinates":[61.7354,56.6132],"type":"Point"}
}