{
  "type": "Feature",
  "properties": {
    "gn:admin1_code":"73.0",
    "gn:asciiname":"Chikanas",
    "gn:country_code":"RU",
    "gn:dem":145,
    "gn:feature_class":"P",
    "gn:feature_code":"PPL",
    "gn:name":"Chikanas",
    "gn:population":0,
    "gn:timezone":"Europe/Moscow",
    "iso:country":"RU",
    "name:rus_x_preferred":[
        "\u0427\u0438\u043a\u0430\u043d\u0430\u0441"
    ],
    "name:und_x_variant":[
        "\u0427\u0438\u043a\u0430\u043d\u0430\u0441"
    ],
    "wof:name":"Chikanas",
    "wof:placetype":"locality"
},
  "geometry": {"coordinates":[49.79314,56.20279],"type":"Point"}
}