{
  "type": "Feature",
  "properties": {
    "gn:admin1_code":"77",
    "gn:asciiname":"Staryy Borok",
    "gn:country_code":"RU",
    "gn:dem":164,
    "gn:feature_class":"P",
    "gn:feature_code":"PPL",
    "gn:name":"Staryy Borok",
    "gn:population":0,
    "gn:timezone":"Europe/Moscow",
    "iso:country":"RU",
    "name:rus_x_preferred":[
        "\u0421\u0442\u0430\u0440\u044b\u0439 \u0411\u043e\u0440\u043e\u043a"
    ],
    "wof:name":"Staryy Borok",
    "wof:placetype":"locality"
},
  "geometry": {"coordinates":[36.8366,57.8553],"type":"Point"}
}