{
  "type": "Feature",
  "properties": {
    "gn:admin1_code":"20",
    "gn:asciiname":"Barda",
    "gn:country_code":"RU",
    "gn:dem":527,
    "gn:feature_class":"P",
    "gn:feature_code":"PPL",
    "gn:name":"Barda",
    "gn:population":0,
    "gn:timezone":"Asia/Irkutsk",
    "iso:country":"RU",
    "name:eng_x_preferred":[
        "Barda"
    ],
    "name:nor_x_preferred":[
        "Barda"
    ],
    "name:rus_x_preferred":[
        "\u0411\u0430\u0440\u0434\u0430"
    ],
    "name:und_x_variant":[
        "Bard",
        "Barda",
        "\u0411\u0430\u0440\u0434\u0430"
    ],
    "wof:name":"Barda",
    "wof:placetype":"locality"
},
  "geometry": {"coordinates":[104.4098,52.8314],"type":"Point"}
}