{
  "type": "Feature",
  "properties": {
    "gn:admin1_code":"37",
    "gn:asciiname":"Malyy Zavryag",
    "gn:country_code":"RU",
    "gn:dem":177,
    "gn:feature_class":"P",
    "gn:feature_code":"PPL",
    "gn:name":"Malyy Zavryag",
    "gn:population":0,
    "gn:timezone":"Europe/Moscow",
    "iso:country":"RU",
    "name:rus_x_preferred":[
        "\u041c\u0430\u043b\u044b\u0439 \u0417\u0430\u0432\u0440\u044f\u0433"
    ],
    "name:und_x_variant":[
        "Malyy Zavryug"
    ],
    "wof:name":"Malyy Zavryag",
    "wof:placetype":"locality"
},
  "geometry": {"coordinates":[46.2226,59.1157],"type":"Point"}
}