{
  "type": "Feature",
  "properties": {
    "gn:admin1_code":"13",
    "gn:asciiname":"Mayachnoye",
    "gn:country_code":"RU",
    "gn:dem":186,
    "gn:feature_class":"P",
    "gn:feature_code":"PPL",
    "gn:name":"Mayachnoye",
    "gn:population":0,
    "gn:timezone":"Asia/Yekaterinburg",
    "iso:country":"RU",
    "name:eng_x_preferred":[
        "Mayachnoye"
    ],
    "name:nor_x_preferred":[
        "Majatsjnoje"
    ],
    "name:rus_x_preferred":[
        "\u041c\u0430\u044f\u0447\u043d\u043e\u0435"
    ],
    "wof:name":"Mayachnoye",
    "wof:placetype":"locality"
},
  "geometry": {"coordinates":[62.7747,54.2649],"type":"Point"}
}