{
  "type": "Feature",
  "properties": {
    "gn:admin1_code":"33",
    "gn:asciiname":"Kozulevshchina",
    "gn:country_code":"RU",
    "gn:dem":214,
    "gn:feature_class":"P",
    "gn:feature_code":"PPL",
    "gn:name":"Kozulevshchina",
    "gn:population":0,
    "gn:timezone":"Europe/Kirov",
    "iso:country":"RU",
    "name:rus_x_preferred":[
        "\u041a\u043e\u0437\u0443\u043b\u0435\u0432\u0449\u0438\u043d\u0430"
    ],
    "wof:name":"Kozulevshchina",
    "wof:placetype":"locality"
},
  "geometry": {"coordinates":[48.58111,59.09721999999999],"type":"Point"}
}