{
  "type": "Feature",
  "properties": {
    "gn:admin1_code":"47.0",
    "gn:admin2_code":"579462",
    "gn:asciiname":"Pavlino",
    "gn:country_code":"RU",
    "gn:dem":122,
    "gn:feature_class":"P",
    "gn:feature_code":"PPL",
    "gn:name":"Pavlino",
    "gn:population":96,
    "gn:timezone":"Europe/Moscow",
    "iso:country":"RU",
    "name:rus_x_preferred":[
        "\u041f\u0430\u0432\u043b\u0438\u043d\u043e"
    ],
    "name:und_x_variant":[
        "\u041f\u0430\u0432\u043b\u0438\u043d\u043e"
    ],
    "wof:name":"Pavlino",
    "wof:placetype":"locality",
    "wof:population":96
},
  "geometry": {"coordinates":[37.95,55.72],"type":"Point"}
}