{
  "type": "Feature",
  "properties": {
    "gn:admin1_code":"8",
    "gn:asciiname":"Ponosova",
    "gn:country_code":"RU",
    "gn:dem":227,
    "gn:feature_class":"P",
    "gn:feature_code":"PPL",
    "gn:name":"Ponosova",
    "gn:population":0,
    "gn:timezone":"Asia/Yekaterinburg",
    "iso:country":"RU",
    "name:che_x_preferred":[
        "\u041f\u043e\u043d\u043e\u0441\u043e\u0432\u0430"
    ],
    "name:rus_x_preferred":[
        "\u041f\u043e\u043d\u043e\u0441\u043e\u0432\u0430"
    ],
    "wof:name":"Ponosova",
    "wof:placetype":"locality"
},
  "geometry": {"coordinates":[55.01667,54.61666999999999],"type":"Point"}
}