{
  "type": "Feature",
  "properties": {
    "gn:admin1_code":"62",
    "gn:asciiname":"Petroslobodka",
    "gn:country_code":"RU",
    "gn:dem":99,
    "gn:feature_class":"P",
    "gn:feature_code":"PPL",
    "gn:name":"Petroslobodka",
    "gn:population":0,
    "gn:timezone":"Europe/Moscow",
    "iso:country":"RU",
    "name:rus_x_preferred":[
        "\u041f\u0435\u0442\u0440\u043e\u0441\u043b\u043e\u0431\u043e\u0434\u043a\u0430"
    ],
    "wof:name":"Petroslobodka",
    "wof:placetype":"locality"
},
  "geometry": {"coordinates":[42.4704,54.4097],"type":"Point"}
}