{
  "type": "Feature",
  "properties": {
    "gn:admin1_code":"4",
    "gn:asciiname":"Dolino",
    "gn:country_code":"RU",
    "gn:dem":231,
    "gn:feature_class":"P",
    "gn:feature_code":"PPL",
    "gn:name":"Dolino",
    "gn:population":0,
    "gn:timezone":"Asia/Barnaul",
    "iso:country":"RU",
    "name:eng_x_preferred":[
        "Dolino"
    ],
    "name:nor_x_preferred":[
        "Dolino"
    ],
    "name:rus_x_preferred":[
        "\u0414\u043e\u043b\u0438\u043d\u043e"
    ],
    "wof:name":"Dolino",
    "wof:placetype":"locality"
},
  "geometry": {"coordinates":[80.911,51.4876],"type":"Point"}
}