{
  "type": "Feature",
  "properties": {
    "gn:admin1_code":"24",
    "gn:asciiname":"Shorvin Kets",
    "gn:country_code":"RU",
    "gn:dem":-5,
    "gn:feature_class":"P",
    "gn:feature_code":"PPL",
    "gn:name":"Shorvin Kets",
    "gn:population":0,
    "gn:timezone":"Europe/Moscow",
    "iso:country":"RU",
    "name:rus_x_preferred":[
        "\u0428\u043e\u0440\u0432\u0438\u043d \u041a\u0435\u0446"
    ],
    "wof:name":"Shorvin Kets",
    "wof:placetype":"locality"
},
  "geometry": {"coordinates":[45.4972,46.986],"type":"Point"}
}