{
  "type": "Feature",
  "properties": {
    "gn:admin1_code":"25",
    "gn:asciiname":"Myzgi",
    "gn:country_code":"RU",
    "gn:dem":202,
    "gn:feature_class":"P",
    "gn:feature_code":"PPL",
    "gn:name":"Myzgi",
    "gn:population":0,
    "gn:timezone":"Europe/Moscow",
    "iso:country":"RU",
    "name:nor_x_preferred":[
        "Myzgi"
    ],
    "name:rus_x_preferred":[
        "\u041c\u044b\u0437\u0433\u0438"
    ],
    "wof:name":"Myzgi",
    "wof:placetype":"locality"
},
  "geometry": {"coordinates":[36.25789,54.74173],"type":"Point"}
}