{
  "type": "Feature",
  "properties": {
    "gn:admin1_code":"34",
    "gn:asciiname":"Kyddzyavidz'",
    "gn:country_code":"RU",
    "gn:dem":133,
    "gn:feature_class":"P",
    "gn:feature_code":"PPL",
    "gn:name":"Kyddzyavidz\u2019",
    "gn:population":0,
    "gn:timezone":"Europe/Moscow",
    "iso:country":"RU",
    "name:eng_x_preferred":[
        "Kyddzyavidz'"
    ],
    "name:nor_x_preferred":[
        "Kyddziavidz"
    ],
    "name:rus_x_preferred":[
        "\u041a\u044b\u0434\u0434\u0437\u044f\u0432\u0438\u0434\u0437\u044c"
    ],
    "name:und_x_variant":[
        "Kyddzavidz\u2019",
        "Kyddzyavidz\u2019"
    ],
    "wof:name":"Kyddzyavidz'",
    "wof:placetype":"locality"
},
  "geometry": {"coordinates":[49.59705,60.49276999999999],"type":"Point"}
}