{
  "type": "Feature",
  "properties": {
    "gn:admin1_code":"9.0",
    "gn:asciiname":"Druzhnyy",
    "gn:country_code":"RU",
    "gn:dem":137,
    "gn:feature_class":"P",
    "gn:feature_code":"PPL",
    "gn:name":"Druzhnyy",
    "gn:population":0,
    "gn:timezone":"Europe/Moscow",
    "iso:country":"RU",
    "name:rus_x_preferred":[
        "\u0414\u0440\u0443\u0436\u043d\u044b\u0439"
    ],
    "wof:name":"Druzhnyy",
    "wof:placetype":"locality"
},
  "geometry": {"coordinates":[36.61718,50.76056],"type":"Point"}
}