{
  "type": "Feature",
  "properties": {
    "gn:admin1_code":"80.0",
    "gn:asciiname":"Chepyk",
    "gn:country_code":"RU",
    "gn:dem":183,
    "gn:feature_class":"P",
    "gn:feature_code":"PPL",
    "gn:name":"Chepyk",
    "gn:population":0,
    "gn:timezone":"Europe/Samara",
    "iso:country":"RU",
    "name:eng_x_preferred":[
        "Chepyk"
    ],
    "name:nor_x_preferred":[
        "Tsjepyk"
    ],
    "name:rus_x_preferred":[
        "\u0427\u0435\u043f\u044b\u043a"
    ],
    "name:und_x_variant":[
        "\u0427\u0435\u043f\u044b\u043a",
        "Chepyk"
    ],
    "wof:name":"Chepyk",
    "wof:placetype":"locality"
},
  "geometry": {"coordinates":[53.6524,57.7339],"type":"Point"}
}