{
  "type": "Feature",
  "properties": {
    "gn:admin1_code":"77",
    "gn:asciiname":"Goroshkovo",
    "gn:country_code":"RU",
    "gn:dem":142,
    "gn:feature_class":"P",
    "gn:feature_code":"PPL",
    "gn:name":"Goroshkovo",
    "gn:population":0,
    "gn:timezone":"Europe/Moscow",
    "iso:country":"RU",
    "name:rus_x_preferred":[
        "\u0413\u043e\u0440\u043e\u0448\u043a\u043e\u0432\u043e"
    ],
    "name:und_x_variant":[
        "\u0413\u043e\u0440\u043e\u0448\u043a\u043e\u0432\u043e"
    ],
    "wof:name":"Goroshkovo",
    "wof:placetype":"locality"
},
  "geometry": {"coordinates":[36.1128,58.2457],"type":"Point"}
}