{
  "type": "Feature",
  "properties": {
    "gn:admin1_code":"10",
    "gn:asciiname":"Khoten",
    "gn:country_code":"RU",
    "gn:dem":199,
    "gn:feature_class":"P",
    "gn:feature_code":"PPL",
    "gn:name":"Khoten",
    "gn:population":0,
    "gn:timezone":"Europe/Moscow",
    "iso:country":"RU",
    "name:rus_x_preferred":[
        "\u0425\u043e\u0442\u0435\u043d"
    ],
    "wof:name":"Khoten",
    "wof:placetype":"locality"
},
  "geometry": {"coordinates":[33.0825,53.62300000000001],"type":"Point"}
}