{
  "type": "Feature",
  "properties": {
    "gn:admin1_code":"72",
    "gn:asciiname":"Kipets",
    "gn:country_code":"RU",
    "gn:dem":124,
    "gn:feature_class":"P",
    "gn:feature_code":"PPL",
    "gn:name":"Kipets",
    "gn:population":0,
    "gn:timezone":"Europe/Moscow",
    "iso:country":"RU",
    "name:rus_x_preferred":[
        "\u041a\u0438\u043f\u0435\u0446"
    ],
    "wof:name":"Kipets",
    "wof:placetype":"locality"
},
  "geometry": {"coordinates":[42.64027,52.43105],"type":"Point"}
}