{
  "type": "Feature",
  "properties": {
    "gn:admin1_code":"85",
    "gn:asciiname":"Maksimovo",
    "gn:country_code":"RU",
    "gn:dem":142,
    "gn:feature_class":"P",
    "gn:feature_code":"PPL",
    "gn:name":"Maksimovo",
    "gn:population":0,
    "gn:timezone":"Europe/Moscow",
    "iso:country":"RU",
    "name:rus_x_preferred":[
        "\u041c\u0430\u043a\u0441\u0438\u043c\u043e\u0432\u043e"
    ],
    "wof:name":"Maksimovo",
    "wof:placetype":"locality"
},
  "geometry": {"coordinates":[36.9294,60.2737],"type":"Point"}
}