{
  "type": "Feature",
  "properties": {
    "gn:admin1_code":"38.0",
    "gn:asciiname":"Bol'shaya Kozinka",
    "gn:country_code":"RU",
    "gn:dem":39,
    "gn:feature_class":"P",
    "gn:feature_code":"PPL",
    "gn:name":"Bol\u2019shaya Kozinka",
    "gn:population":0,
    "gn:timezone":"Europe/Moscow",
    "iso:country":"RU",
    "name:rus_x_preferred":[
        "\u0411\u043e\u043b\u044c\u0448\u0430\u044f \u041a\u043e\u0437\u0438\u043d\u043a\u0430"
    ],
    "name:und_x_variant":[
        "Bol\u2019shaya Kozinka"
    ],
    "wof:name":"Bol'shaya Kozinka",
    "wof:placetype":"locality"
},
  "geometry": {"coordinates":[39.44583,46.67417],"type":"Point"}
}