{
  "type": "Feature",
  "properties": {
    "gn:admin1_code":"33.0",
    "gn:asciiname":"Sabel'tsy",
    "gn:country_code":"RU",
    "gn:dem":170,
    "gn:feature_class":"P",
    "gn:feature_code":"PPL",
    "gn:name":"Sabel\u2019tsy",
    "gn:population":0,
    "gn:timezone":"Europe/Kirov",
    "iso:country":"RU",
    "name:rus_x_preferred":[
        "\u0421\u0430\u0431\u0435\u043b\u044c\u0446\u044b"
    ],
    "name:und_x_variant":[
        "Sabel\u2019tsy"
    ],
    "wof:name":"Sabel'tsy",
    "wof:placetype":"locality"
},
  "geometry": {"coordinates":[50.99278,59.305],"type":"Point"}
}