{
  "type": "Feature",
  "properties": {
    "gn:admin1_code":"63",
    "gn:asciiname":"Tereshkino",
    "gn:country_code":"RU",
    "gn:dem":241,
    "gn:feature_class":"P",
    "gn:feature_code":"PPL",
    "gn:name":"Ter\u00ebshkino",
    "gn:population":0,
    "gn:timezone":"Asia/Yakutsk",
    "iso:country":"RU",
    "name:und_x_variant":[
        "Ter\u00ebshkina",
        "Ter\u00ebshkino"
    ],
    "wof:name":"Tereshkino",
    "wof:placetype":"locality"
},
  "geometry": {"coordinates":[114.4864,60.55855],"type":"Point"}
}