{
  "type": "Feature",
  "properties": {
    "gn:admin1_code":"32",
    "gn:asciiname":"Novyy Nazym",
    "gn:country_code":"RU",
    "gn:dem":29,
    "gn:feature_class":"P",
    "gn:feature_code":"PPL",
    "gn:name":"Novyy Nazym",
    "gn:population":0,
    "gn:timezone":"Asia/Yekaterinburg",
    "iso:country":"RU",
    "name:eng_x_preferred":[
        "Novyy Nazym"
    ],
    "name:nor_x_preferred":[
        "Nov.Nazym"
    ],
    "name:rus_x_preferred":[
        "\u041d\u043e\u0432.\u041d\u0430\u0437\u044b\u043c"
    ],
    "name:rus_x_variant":[
        "\u041d\u043e\u0432\u044b\u0439 \u041d\u0430\u0437\u044b\u043c"
    ],
    "wof:name":"Novyy Nazym",
    "wof:placetype":"locality"
},
  "geometry": {"coordinates":[68.78333000000001,61.58333],"type":"Point"}
}