{
  "type": "Feature",
  "properties": {
    "gn:admin1_code":"24",
    "gn:asciiname":"Ural'skiy",
    "gn:country_code":"RU",
    "gn:dem":52,
    "gn:feature_class":"P",
    "gn:feature_code":"PPL",
    "gn:name":"Ural\u2019skiy",
    "gn:population":0,
    "gn:timezone":"Europe/Moscow",
    "iso:country":"RU",
    "name:und_x_variant":[
        "Tsentral\u2019naya Usad\u2019ba Sovkhoza Nomer Sto Dvenadtsatogo",
        "Ural\u2019skiy"
    ],
    "wof:name":"Ural'skiy",
    "wof:placetype":"locality"
},
  "geometry": {"coordinates":[41.89639,46.08444],"type":"Point"}
}