{
  "type": "Feature",
  "properties": {
    "gn:admin1_code":"77.0",
    "gn:asciiname":"Aksent'va",
    "gn:country_code":"RU",
    "gn:dem":184,
    "gn:feature_class":"P",
    "gn:feature_code":"PPL",
    "gn:name":"Aksent\u2019va",
    "gn:population":0,
    "gn:timezone":"Europe/Moscow",
    "iso:country":"RU",
    "name:nor_x_preferred":[
        "Aksentva"
    ],
    "name:rus_x_preferred":[
        "\u0410\u043a\u0441\u0435\u043d\u0442\u044c\u0432\u0430"
    ],
    "name:und_x_variant":[
        "Aksent\u2019yevo",
        "Aksent\u2019va"
    ],
    "wof:name":"Aksent'va",
    "wof:placetype":"locality"
},
  "geometry": {"coordinates":[31.63582,55.82916],"type":"Point"}
}