{
  "type": "Feature",
  "properties": {
    "gn:admin1_code":"20",
    "gn:asciiname":"Mal'tinka",
    "gn:country_code":"RU",
    "gn:dem":465,
    "gn:feature_class":"P",
    "gn:feature_code":"PPL",
    "gn:name":"Mal\u2019tinka",
    "gn:population":0,
    "gn:timezone":"Asia/Irkutsk",
    "iso:country":"RU",
    "name:rus_x_preferred":[
        "\u041c\u0430\u043b\u044c\u0442\u0438\u043d\u043a\u0430"
    ],
    "name:und_x_variant":[
        "Mal\u2019tinka"
    ],
    "wof:name":"Mal'tinka",
    "wof:placetype":"locality"
},
  "geometry": {"coordinates":[99.2269,54.8582],"type":"Point"}
}