{
  "type": "Feature",
  "properties": {
    "gn:admin1_code":"47",
    "gn:asciiname":"Levashovo",
    "gn:country_code":"RU",
    "gn:dem":138,
    "gn:feature_class":"P",
    "gn:feature_code":"PPL",
    "gn:name":"Levashovo",
    "gn:population":0,
    "gn:timezone":"Europe/Moscow",
    "iso:country":"RU",
    "name:rus_x_preferred":[
        "\u041b\u0435\u0432\u0430\u0448\u043e\u0432\u043e"
    ],
    "wof:name":"Levashovo",
    "wof:placetype":"locality"
},
  "geometry": {"coordinates":[37.50795,54.93334],"type":"Point"}
}