{
  "type": "Feature",
  "properties": {
    "gn:admin1_code":"91.0",
    "gn:asciiname":"Verkhnyaya Yelovaya",
    "gn:country_code":"RU",
    "gn:dem":401,
    "gn:feature_class":"P",
    "gn:feature_code":"PPL",
    "gn:name":"Verkhnyaya Yelovaya",
    "gn:population":0,
    "gn:timezone":"Asia/Krasnoyarsk",
    "iso:country":"RU",
    "name:rus_x_preferred":[
        "\u0412\u0435\u0440\u0445\u043d\u044f\u044f \u0415\u043b\u043e\u0432\u0430\u044f"
    ],
    "wof:name":"Verkhnyaya Yelovaya",
    "wof:placetype":"locality"
},
  "geometry": {"coordinates":[92.39019999999999,56.12],"type":"Point"}
}