{
  "type": "Feature",
  "properties": {
    "gn:admin1_code":"60",
    "gn:asciiname":"Borzovo",
    "gn:country_code":"RU",
    "gn:dem":62,
    "gn:feature_class":"P",
    "gn:feature_code":"PPL",
    "gn:name":"Borzovo",
    "gn:population":0,
    "gn:timezone":"Europe/Moscow",
    "iso:country":"RU",
    "name:rus_x_preferred":[
        "\u0411\u043e\u0440\u0437\u043e\u0432\u043e"
    ],
    "wof:name":"Borzovo",
    "wof:placetype":"locality"
},
  "geometry": {"coordinates":[28.17655,57.21654],"type":"Point"}
}