{
  "type": "Feature",
  "properties": {
    "gn:admin1_code":"47",
    "gn:asciiname":"Petelino",
    "gn:country_code":"RU",
    "gn:dem":201,
    "gn:feature_class":"P",
    "gn:feature_code":"PPL",
    "gn:name":"Petelino",
    "gn:population":0,
    "gn:timezone":"Europe/Moscow",
    "iso:country":"RU",
    "name:rus_x_preferred":[
        "\u041f\u0435\u0442\u0435\u043b\u0438\u043d\u043e"
    ],
    "wof:name":"Petelino",
    "wof:placetype":"locality"
},
  "geometry": {"coordinates":[36.86029,55.59857],"type":"Point"}
}