{
  "type": "Feature",
  "properties": {
    "gn:admin1_code":"77",
    "gn:asciiname":"Ostrechikha",
    "gn:country_code":"RU",
    "gn:dem":209,
    "gn:feature_class":"P",
    "gn:feature_code":"PPL",
    "gn:name":"Ostrechikha",
    "gn:population":0,
    "gn:timezone":"Europe/Moscow",
    "iso:country":"RU",
    "name:rus_x_preferred":[
        "\u041e\u0441\u0442\u0440\u0435\u0447\u0438\u0445\u0430"
    ],
    "name:und_x_variant":[
        "Ostrelikha",
        "Ostrechikha"
    ],
    "wof:name":"Ostrechikha",
    "wof:placetype":"locality"
},
  "geometry": {"coordinates":[36.62501,58.41318],"type":"Point"}
}