{
  "type": "Feature",
  "properties": {
    "gn:admin1_code":"72",
    "gn:asciiname":"Priyut",
    "gn:country_code":"RU",
    "gn:dem":157,
    "gn:feature_class":"P",
    "gn:feature_code":"PPL",
    "gn:name":"Priyut",
    "gn:population":0,
    "gn:timezone":"Europe/Moscow",
    "iso:country":"RU",
    "name:rus_x_preferred":[
        "\u041f\u0440\u0438\u044e\u0442"
    ],
    "wof:name":"Priyut",
    "wof:placetype":"locality"
},
  "geometry": {"coordinates":[40.7395,52.3017],"type":"Point"}
}