{
  "type": "Feature",
  "properties": {
    "gn:admin1_code":"44",
    "gn:asciiname":"Khevkandya",
    "gn:country_code":"RU",
    "gn:dem":728,
    "gn:feature_class":"P",
    "gn:feature_code":"PPL",
    "gn:name":"Khevkandya",
    "gn:population":0,
    "gn:timezone":"Asia/Magadan",
    "iso:country":"RU",
    "name:rus_x_preferred":[
        "\u0425\u0435\u0432\u043a\u0430\u043d\u0434\u044f"
    ],
    "wof:name":"Khevkandya",
    "wof:placetype":"locality"
},
  "geometry": {"coordinates":[147.98033000000001,63.16167],"type":"Point"}
}