{
  "type": "Feature",
  "properties": {
    "gn:admin1_code":"10.0",
    "gn:asciiname":"Buda-Koretskaya",
    "gn:country_code":"RU",
    "gn:dem":184,
    "gn:feature_class":"P",
    "gn:feature_code":"PPL",
    "gn:name":"Buda-Koretskaya",
    "gn:population":0,
    "gn:timezone":"Europe/Moscow",
    "iso:country":"RU",
    "name:rus_x_preferred":[
        "\u0411\u0443\u0434\u0430-\u041a\u043e\u0440\u0435\u0446\u043a\u0430\u044f"
    ],
    "name:und_x_variant":[
        "\u0411\u0443\u0434\u0430-\u041a\u043e\u0440\u0435\u0446\u043a\u0430\u044f"
    ],
    "wof:name":"Buda-Koretskaya",
    "wof:placetype":"locality"
},
  "geometry": {"coordinates":[32.79875,52.42843],"type":"Point"}
}