{
  "type": "Feature",
  "properties": {
    "gn:admin1_code":"47",
    "gn:asciiname":"Smol'nikovo",
    "gn:country_code":"RU",
    "gn:dem":164,
    "gn:feature_class":"P",
    "gn:feature_code":"PPL",
    "gn:name":"Smol\u2019nikovo",
    "gn:population":0,
    "gn:timezone":"Europe/Moscow",
    "iso:country":"RU",
    "name:rus_x_preferred":[
        "\u0421\u043c\u043e\u043b\u044c\u043d\u0438\u043a\u043e\u0432\u043e"
    ],
    "name:und_x_variant":[
        "Smol\u2019nikovo",
        "\u0421\u043c\u043e\u043b\u044c\u043d\u0438\u043a\u043e\u0432\u043e"
    ],
    "wof:name":"Smol'nikovo",
    "wof:placetype":"locality"
},
  "geometry": {"coordinates":[36.1507,56.1764],"type":"Point"}
}