{
  "type": "Feature",
  "properties": {
    "gn:admin1_code":"55",
    "gn:asciiname":"Leninskiy Luch",
    "gn:country_code":"RU",
    "gn:dem":91,
    "gn:feature_class":"P",
    "gn:feature_code":"PPL",
    "gn:name":"Leninskiy Luch",
    "gn:population":0,
    "gn:timezone":"Asia/Yekaterinburg",
    "iso:country":"RU",
    "name:rus_x_preferred":[
        "\u041b\u0435\u043d\u0438\u043d\u0441\u043a\u0438\u0439 \u041b\u0443\u0447"
    ],
    "wof:name":"Leninskiy Luch",
    "wof:placetype":"locality"
},
  "geometry": {"coordinates":[55.04117,51.83437],"type":"Point"}
}