{
  "type": "Feature",
  "properties": {
    "gn:admin1_code":"10",
    "gn:asciiname":"Orliya",
    "gn:country_code":"RU",
    "gn:dem":192,
    "gn:feature_class":"P",
    "gn:feature_code":"PPL",
    "gn:name":"Orliya",
    "gn:population":0,
    "gn:timezone":"Europe/Moscow",
    "iso:country":"RU",
    "name:rus_x_preferred":[
        "\u041e\u0440\u043b\u0438\u044f"
    ],
    "wof:name":"Orliya",
    "wof:placetype":"locality"
},
  "geometry": {"coordinates":[34.2445,52.1421],"type":"Point"}
}