{
  "type": "Feature",
  "properties": {
    "gn:admin1_code":"4",
    "gn:asciiname":"Kranokholmskiy",
    "gn:country_code":"RU",
    "gn:dem":198,
    "gn:feature_class":"P",
    "gn:feature_code":"PPL",
    "gn:name":"Kranokholmskiy",
    "gn:population":0,
    "gn:timezone":"Asia/Barnaul",
    "iso:country":"RU",
    "name:rus_x_preferred":[
        "\u041a\u0440\u0430\u043d\u043e\u0445\u043e\u043b\u043c\u0441\u043a\u0438\u0439"
    ],
    "name:und_x_variant":[
        "\u041a\u0440\u0430\u043d\u043e\u0445\u043e\u043b\u043c\u0441\u043a\u0438\u0439"
    ],
    "wof:name":"Kranokholmskiy",
    "wof:placetype":"locality"
},
  "geometry": {"coordinates":[81.46666999999999,52.86666999999999],"type":"Point"}
}