{
  "type": "Feature",
  "properties": {
    "gn:admin1_code":"33",
    "gn:asciiname":"Ploskaya",
    "gn:country_code":"RU",
    "gn:dem":132,
    "gn:feature_class":"P",
    "gn:feature_code":"PPL",
    "gn:name":"Ploskaya",
    "gn:population":0,
    "gn:timezone":"Europe/Kirov",
    "iso:country":"RU",
    "name:rus_x_preferred":[
        "\u041f\u043b\u043e\u0441\u043a\u0430\u044f"
    ],
    "wof:name":"Ploskaya",
    "wof:placetype":"locality"
},
  "geometry": {"coordinates":[49.6234,57.7365],"type":"Point"}
}