{
  "type": "Feature",
  "properties": {
    "gn:admin1_code":"37",
    "gn:asciiname":"Khrenovo",
    "gn:country_code":"RU",
    "gn:dem":123,
    "gn:feature_class":"P",
    "gn:feature_code":"PPL",
    "gn:name":"Khrenovo",
    "gn:population":0,
    "gn:timezone":"Europe/Moscow",
    "iso:country":"RU",
    "name:rus_x_preferred":[
        "\u0425\u0440\u0435\u043d\u043e\u0432\u043e"
    ],
    "wof:name":"Khrenovo",
    "wof:placetype":"locality"
},
  "geometry": {"coordinates":[45.5346,58.1439],"type":"Point"}
}