{
  "type": "Feature",
  "properties": {
    "gn:admin1_code":"90",
    "gn:asciiname":"Verkhnyaya Rechka",
    "gn:country_code":"RU",
    "gn:dem":107,
    "gn:feature_class":"P",
    "gn:feature_code":"PPL",
    "gn:name":"Verkhnyaya Rechka",
    "gn:population":0,
    "gn:timezone":"Asia/Yekaterinburg",
    "iso:country":"RU",
    "name:rus_x_preferred":[
        "\u0412\u0435\u0440\u0445\u043d\u044f\u044f \u0420\u0435\u0447\u043a\u0430"
    ],
    "wof:name":"Verkhnyaya Rechka",
    "wof:placetype":"locality"
},
  "geometry": {"coordinates":[56.6275,58.0919],"type":"Point"}
}