{
  "type": "Feature",
  "properties": {
    "gn:admin1_code":"7.0",
    "gn:asciiname":"Babikov",
    "gn:country_code":"RU",
    "gn:dem":-29,
    "gn:feature_class":"P",
    "gn:feature_code":"PPL",
    "gn:name":"Babikov",
    "gn:population":0,
    "gn:timezone":"Europe/Astrakhan",
    "iso:country":"RU",
    "name:nor_x_preferred":[
        "Babikov"
    ],
    "name:rus_x_preferred":[
        "\u0411\u0430\u0431\u0438\u043a\u043e\u0432"
    ],
    "name:und_x_variant":[
        "Bibikov",
        "Babikov"
    ],
    "wof:name":"Babikov",
    "wof:placetype":"locality"
},
  "geometry": {"coordinates":[48.58333,46.06667],"type":"Point"}
}