{
  "type": "Feature",
  "properties": {
    "gn:admin1_code":"71",
    "gn:asciiname":"Pisanets",
    "gn:country_code":"RU",
    "gn:dem":135,
    "gn:feature_class":"P",
    "gn:feature_code":"PPL",
    "gn:name":"Pisanets",
    "gn:population":0,
    "gn:timezone":"Asia/Yekaterinburg",
    "iso:country":"RU",
    "name:eng_x_preferred":[
        "Pisanets"
    ],
    "name:nor_x_preferred":[
        "Pisanets"
    ],
    "name:rus_x_preferred":[
        "\u041f\u0438\u0441\u0430\u043d\u0435\u0446"
    ],
    "name:und_x_variant":[
        "Pisanskoye",
        "\u041f\u0438\u0441\u0430\u043d\u0435\u0446",
        "Pisanets"
    ],
    "wof:name":"Pisanets",
    "wof:placetype":"locality"
},
  "geometry": {"coordinates":[62.14674,57.36171],"type":"Point"}
}