{
  "type": "Feature",
  "properties": {
    "gn:admin1_code":"33",
    "gn:asciiname":"Pavlushinskaya",
    "gn:country_code":"RU",
    "gn:dem":102,
    "gn:feature_class":"P",
    "gn:feature_code":"PPL",
    "gn:name":"Pavlushinskaya",
    "gn:population":0,
    "gn:timezone":"Europe/Kirov",
    "iso:country":"RU",
    "name:rus_x_preferred":[
        "\u041f\u0430\u0432\u043b\u0443\u0448\u0438\u043d\u0441\u043a\u0430\u044f"
    ],
    "name:und_x_variant":[
        "Pavshinskaya",
        "Povshinskaya",
        "Pavlushinskaya"
    ],
    "wof:name":"Pavlushinskaya",
    "wof:placetype":"locality"
},
  "geometry": {"coordinates":[48.3007,60.4027],"type":"Point"}
}