{
  "type": "Feature",
  "properties": {
    "gn:admin1_code":"16",
    "gn:asciiname":"Sidukkasy",
    "gn:country_code":"RU",
    "gn:dem":168,
    "gn:feature_class":"P",
    "gn:feature_code":"PPL",
    "gn:name":"Sidukkasy",
    "gn:population":0,
    "gn:timezone":"Europe/Moscow",
    "iso:country":"RU",
    "name:rus_x_preferred":[
        "\u0421\u0438\u0434\u0443\u043a\u043a\u0430\u0441\u044b"
    ],
    "wof:name":"Sidukkasy",
    "wof:placetype":"locality"
},
  "geometry": {"coordinates":[46.7763,56.0452],"type":"Point"}
}