{
  "type": "Feature",
  "properties": {
    "gn:admin1_code":"67",
    "gn:asciiname":"Macha",
    "gn:country_code":"RU",
    "gn:dem":144,
    "gn:feature_class":"P",
    "gn:feature_code":"PPL",
    "gn:name":"Macha",
    "gn:population":0,
    "gn:timezone":"Europe/Saratov",
    "iso:country":"RU",
    "name:bel_x_preferred":[
        "\u041c\u0430\u0445\u0430"
    ],
    "name:cat_x_preferred":[
        "Macha"
    ],
    "name:ces_x_preferred":[
        "Macha"
    ],
    "name:cym_x_preferred":[
        "Macha"
    ],
    "name:deu_x_preferred":[
        "Macha"
    ],
    "name:fin_x_preferred":[
        "Macha"
    ],
    "name:fra_x_preferred":[
        "Macha"
    ],
    "name:ind_x_preferred":[
        "Macha"
    ],
    "name:ita_x_preferred":[
        "Macha"
    ],
    "name:jpn_x_preferred":[
        "\u30de\u30c3\u30cf"
    ],
    "name:kor_x_preferred":[
        "\ub9c8\ud558"
    ],
    "name:nld_x_preferred":[
        "Macha"
    ],
    "name:pol_x_preferred":[
        "Macha"
    ],
    "name:por_x_preferred":[
        "Macha"
    ],
    "name:ron_x_preferred":[
        "Macha"
    ],
    "name:rus_x_preferred":[
        "\u041c\u0430\u0447\u0430"
    ],
    "name:rus_x_variant":[
        "\u041c\u0430\u0445\u0430"
    ],
    "name:sco_x_preferred":[
        "Macha"
    ],
    "name:swe_x_preferred":[
        "Macha"
    ],
    "name:ukr_x_preferred":[
        "\u041c\u0430\u0445\u0430"
    ],
    "wof:name":"Macha",
    "wof:placetype":"locality"
},
  "geometry": {"coordinates":[43.15,51.58333],"type":"Point"}
}