{
  "type": "Feature",
  "properties": {
    "gn:admin1_code":"67",
    "gn:asciiname":"Macha",
    "gn:country_code":"RU",
    "gn:dem":144,
    "gn:feature_class":"P",
    "gn:feature_code":"PPL",
    "gn:name":"Macha",
    "gn:population":0,
    "gn:timezone":"Europe/Saratov",
    "iso:country":"RU",
    "name:rus_x_preferred":[
        "\u041c\u0430\u0447\u0430"
    ],
    "name:und_x_variant":[
        "\u041c\u0430\u0447\u0430"
    ],
    "wof:name":"Macha",
    "wof:placetype":"locality"
},
  "geometry": {"coordinates":[43.15,51.58333],"type":"Point"}
}