{
  "type": "Feature",
  "properties": {
    "gn:admin1_code":"80",
    "gn:asciiname":"Zarechnyy Vishur",
    "gn:country_code":"RU",
    "gn:dem":124,
    "gn:feature_class":"P",
    "gn:feature_code":"PPL",
    "gn:name":"Zarechnyy Vishur",
    "gn:population":0,
    "gn:timezone":"Europe/Samara",
    "iso:country":"RU",
    "name:eng_x_preferred":[
        "Zarechnyy Vishur"
    ],
    "name:nor_x_preferred":[
        "Zaretsjnyj Visjur"
    ],
    "name:rus_x_preferred":[
        "\u0417\u0430\u0440\u0435\u0447\u043d\u044b\u0439 \u0412\u0438\u0448\u0443\u0440"
    ],
    "wof:name":"Zarechnyy Vishur",
    "wof:placetype":"locality"
},
  "geometry": {"coordinates":[53.58071,57.1946],"type":"Point"}
}