{
  "type": "Feature",
  "properties": {
    "gn:admin1_code":"62",
    "gn:asciiname":"Dymovo-Gosudarstvennoye",
    "gn:country_code":"RU",
    "gn:dem":112,
    "gn:feature_class":"P",
    "gn:feature_code":"PPL",
    "gn:name":"Dymovo-Gosudarstvennoye",
    "gn:population":0,
    "gn:timezone":"Europe/Moscow",
    "iso:country":"RU",
    "name:rus_x_preferred":[
        "\u0414\u044b\u043c\u043e\u0432\u043e-\u0413\u043e\u0441\u0443\u0434\u0430\u0440\u0441\u0442\u0432\u0435\u043d\u043d\u043e\u0435"
    ],
    "wof:name":"Dymovo-Gosudarstvennoye",
    "wof:placetype":"locality"
},
  "geometry": {"coordinates":[39.7955,53.6413],"type":"Point"}
}