{
  "type": "Feature",
  "properties": {
    "gn:admin1_code":"79",
    "gn:asciiname":"Tunuk",
    "gn:country_code":"RU",
    "gn:dem":944,
    "gn:feature_class":"P",
    "gn:feature_code":"PPL",
    "gn:name":"Tunuk",
    "gn:population":0,
    "gn:timezone":"Asia/Krasnoyarsk",
    "iso:country":"RU",
    "wof:name":"Tunuk",
    "wof:placetype":"locality"
},
  "geometry": {"coordinates":[93.43333,51.95],"type":"Point"}
}