{
  "type": "Feature",
  "properties": {
    "gn:admin1_code":"52",
    "gn:asciiname":"Gaynovo",
    "gn:country_code":"RU",
    "gn:dem":46,
    "gn:feature_class":"P",
    "gn:feature_code":"PPL",
    "gn:name":"Gaynovo",
    "gn:population":0,
    "gn:timezone":"Europe/Moscow",
    "iso:country":"RU",
    "name:rus_x_preferred":[
        "\u0413\u0430\u0439\u043d\u043e\u0432\u043e"
    ],
    "wof:name":"Gaynovo",
    "wof:placetype":"locality"
},
  "geometry": {"coordinates":[31.1478,57.7956],"type":"Point"}
}