{
  "type": "Feature",
  "properties": {
    "gn:admin1_code":"85",
    "gn:asciiname":"Nokshino",
    "gn:country_code":"RU",
    "gn:dem":62,
    "gn:feature_class":"P",
    "gn:feature_code":"PPL",
    "gn:name":"Nokshino",
    "gn:population":0,
    "gn:timezone":"Europe/Moscow",
    "iso:country":"RU",
    "name:rus_x_preferred":[
        "\u041d\u043e\u043a\u0448\u0438\u043d\u043e"
    ],
    "wof:name":"Nokshino",
    "wof:placetype":"locality"
},
  "geometry": {"coordinates":[46.3922,60.7962],"type":"Point"}
}