{
  "type": "Feature",
  "properties": {
    "gn:admin1_code":"52",
    "gn:asciiname":"Moshkovo",
    "gn:country_code":"RU",
    "gn:dem":156,
    "gn:feature_class":"P",
    "gn:feature_code":"PPL",
    "gn:name":"Moshkovo",
    "gn:population":0,
    "gn:timezone":"Europe/Moscow",
    "iso:country":"RU",
    "name:rus_x_preferred":[
        "\u041c\u043e\u0448\u043a\u043e\u0432\u043e"
    ],
    "name:und_x_variant":[
        "\u041c\u043e\u0448\u043a\u043e\u0432\u043e"
    ],
    "wof:name":"Moshkovo",
    "wof:placetype":"locality"
},
  "geometry": {"coordinates":[34.35,58.18333000000001],"type":"Point"}
}