{
  "type": "Feature",
  "properties": {
    "gn:admin1_code":"42",
    "gn:asciiname":"Novoselok",
    "gn:country_code":"RU",
    "gn:dem":46,
    "gn:feature_class":"P",
    "gn:feature_code":"PPL",
    "gn:name":"Novos\u00eblok",
    "gn:population":0,
    "gn:timezone":"Europe/Moscow",
    "iso:country":"RU",
    "name:rus_x_preferred":[
        "\u041d\u043e\u0432\u043e\u0441\u0451\u043b\u043e\u043a"
    ],
    "name:und_x_variant":[
        "Novos\u00eblok"
    ],
    "wof:name":"Novoselok",
    "wof:placetype":"locality"
},
  "geometry": {"coordinates":[32.03333,59.73333],"type":"Point"}
}