{
  "type": "Feature",
  "properties": {
    "gn:admin1_code":"77",
    "gn:asciiname":"Korchelovo",
    "gn:country_code":"RU",
    "gn:dem":242,
    "gn:feature_class":"P",
    "gn:feature_code":"PPL",
    "gn:name":"Korchelovo",
    "gn:population":0,
    "gn:timezone":"Europe/Moscow",
    "iso:country":"RU",
    "name:rus_x_preferred":[
        "\u041a\u043e\u0440\u0447\u0435\u043b\u043e\u0432\u043e"
    ],
    "name:und_x_variant":[
        "\u041a\u043e\u0440\u0447\u0435\u043b\u043e\u0432\u043e"
    ],
    "wof:name":"Korchelovo",
    "wof:placetype":"locality"
},
  "geometry": {"coordinates":[33.90267,56.85735],"type":"Point"}
}