{
  "type": "Feature",
  "properties": {
    "gn:admin1_code":"73",
    "gn:asciiname":"Krym-Saray",
    "gn:country_code":"RU",
    "gn:dem":150,
    "gn:feature_class":"P",
    "gn:feature_code":"PPL",
    "gn:name":"Krym-Saray",
    "gn:population":0,
    "gn:timezone":"Europe/Moscow",
    "iso:country":"RU",
    "name:eng_x_preferred":[
        "Krym-Saray"
    ],
    "name:nor_x_preferred":[
        "Krym-Saraj"
    ],
    "name:rus_x_preferred":[
        "\u041a\u0440\u044b\u043c-\u0421\u0430\u0440\u0430\u0439"
    ],
    "wof:name":"Krym-Saray",
    "wof:placetype":"locality"
},
  "geometry": {"coordinates":[53.11221,54.53566],"type":"Point"}
}