{
  "type": "Feature",
  "properties": {
    "gn:admin1_code":"62",
    "gn:asciiname":"Bol'shoye Aleshino",
    "gn:country_code":"RU",
    "gn:dem":147,
    "gn:feature_class":"P",
    "gn:feature_code":"PPL",
    "gn:name":"Bol\u2019shoye Al\u00ebshino",
    "gn:population":0,
    "gn:timezone":"Europe/Moscow",
    "iso:country":"RU",
    "name:rus_x_preferred":[
        "\u0411\u043e\u043b\u044c\u0448\u043e\u0435 \u0410\u043b\u0451\u0448\u0438\u043d\u043e"
    ],
    "name:und_x_variant":[
        "Bol\u2019shoye Al\u00ebshino"
    ],
    "wof:name":"Bol'shoye Aleshino",
    "wof:placetype":"locality"
},
  "geometry": {"coordinates":[39.0381,54.603],"type":"Point"}
}