{
  "type": "Feature",
  "properties": {
    "gn:admin1_code":"77",
    "gn:asciiname":"Vysokoye",
    "gn:country_code":"RU",
    "gn:dem":244,
    "gn:feature_class":"P",
    "gn:feature_code":"PPL",
    "gn:name":"Vysokoye",
    "gn:population":0,
    "gn:timezone":"Europe/Moscow",
    "iso:country":"RU",
    "wof:name":"Vysokoye",
    "wof:placetype":"locality"
},
  "geometry": {"coordinates":[34.52753,56.8213],"type":"Point"}
}