{
  "type": "Feature",
  "properties": {
    "gn:admin1_code":"8",
    "gn:asciiname":"Kayupovo",
    "gn:country_code":"RU",
    "gn:dem":289,
    "gn:feature_class":"P",
    "gn:feature_code":"PPL",
    "gn:name":"Kayupovo",
    "gn:population":0,
    "gn:timezone":"Asia/Yekaterinburg",
    "iso:country":"RU",
    "name:bak_x_preferred":[
        "\u04a0\u04d9\u0439\u04af\u043f"
    ],
    "name:che_x_preferred":[
        "\u041a\u0430\u044e\u043f\u043e\u0432\u043e"
    ],
    "name:hye_x_preferred":[
        "\u053f\u0561\u0575\u0578\u0582\u057a\u0578\u057e\u0578"
    ],
    "name:kat_x_preferred":[
        "\u10d9\u10d0\u10d8\u10e3\u10de\u10dd\u10d5\u10dd"
    ],
    "name:kaz_x_preferred":[
        "\u041a\u0430\u044e\u043f"
    ],
    "name:kir_x_preferred":[
        "\u041a\u0430\u044e\u043f"
    ],
    "name:rus_x_preferred":[
        "\u041a\u0430\u044e\u043f\u043e\u0432\u043e"
    ],
    "name:tat_x_preferred":[
        "\u041a\u0430\u0435\u043f"
    ],
    "name:und_x_variant":[
        "Kaipovo",
        "Kaipova",
        "Kampovo",
        "Kayupovo",
        "\u041a\u0430\u044e\u043f\u043e\u0432\u043e"
    ],
    "wof:name":"Kayupovo",
    "wof:placetype":"locality"
},
  "geometry": {"coordinates":[59.24278,56.05889000000001],"type":"Point"}
}