{
  "type": "Feature",
  "properties": {
    "gn:admin1_code":"43",
    "gn:asciiname":"Cherkasskaya",
    "gn:country_code":"RU",
    "gn:dem":129,
    "gn:feature_class":"P",
    "gn:feature_code":"PPL",
    "gn:name":"Cherkasskaya",
    "gn:population":0,
    "gn:timezone":"Europe/Moscow",
    "iso:country":"RU",
    "name:rus_x_preferred":[
        "\u0427\u0435\u0440\u043a\u0430\u0441\u0441\u043a\u0430\u044f"
    ],
    "wof:name":"Cherkasskaya",
    "wof:placetype":"locality"
},
  "geometry": {"coordinates":[38.0437,52.4684],"type":"Point"}
}