{
  "type": "Feature",
  "properties": {
    "gn:admin1_code":"13",
    "gn:asciiname":"Tridtsat' Vtoroy Kilometr",
    "gn:country_code":"RU",
    "gn:dem":426,
    "gn:feature_class":"P",
    "gn:feature_code":"PPL",
    "gn:name":"Tridtsat\u2019 Vtoroy Kilometr",
    "gn:population":0,
    "gn:timezone":"Asia/Yekaterinburg",
    "iso:country":"RU",
    "name:rus_x_preferred":[
        "\u0422\u0440\u0438\u0434\u0446\u0430\u0442\u044c \u0412\u0442\u043e\u0440\u043e\u0439 \u041a\u0438\u043b\u043e\u043c\u0435\u0442\u0440"
    ],
    "name:und_x_variant":[
        "Tridtsat\u2019 Vtoroy Kilometr"
    ],
    "wof:name":"Tridtsat' Vtoroy Kilometr",
    "wof:placetype":"locality"
},
  "geometry": {"coordinates":[58.9203,55.0383],"type":"Point"}
}