{
  "type": "Feature",
  "properties": {
    "gn:admin1_code":"60",
    "gn:asciiname":"Fishovo",
    "gn:country_code":"RU",
    "gn:dem":56,
    "gn:feature_class":"P",
    "gn:feature_code":"PPL",
    "gn:name":"Fishovo",
    "gn:population":0,
    "gn:timezone":"Europe/Moscow",
    "iso:country":"RU",
    "name:rus_x_preferred":[
        "\u0424\u0438\u0448\u043e\u0432\u043e"
    ],
    "wof:name":"Fishovo",
    "wof:placetype":"locality"
},
  "geometry": {"coordinates":[28.0081,57.6196],"type":"Point"}
}