{
  "type": "Feature",
  "properties": {
    "gn:admin1_code":"67",
    "gn:asciiname":"Vostochnyy",
    "gn:country_code":"RU",
    "gn:dem":88,
    "gn:feature_class":"P",
    "gn:feature_code":"PPL",
    "gn:name":"Vostochnyy",
    "gn:population":0,
    "gn:timezone":"Europe/Saratov",
    "iso:country":"RU",
    "name:eng_x_preferred":[
        "Vostochnyy"
    ],
    "name:nor_x_preferred":[
        "Vostotsjnyj"
    ],
    "name:rus_x_preferred":[
        "\u0412\u043e\u0441\u0442\u043e\u0447\u043d\u044b\u0439"
    ],
    "wof:name":"Vostochnyy",
    "wof:placetype":"locality"
},
  "geometry": {"coordinates":[50.03524,51.33691],"type":"Point"}
}