{
  "type": "Feature",
  "properties": {
    "gn:admin1_code":"70",
    "gn:asciiname":"Veselyy",
    "gn:country_code":"RU",
    "gn:dem":394,
    "gn:feature_class":"P",
    "gn:feature_code":"PPL",
    "gn:name":"Ves\u00eblyy",
    "gn:population":0,
    "gn:timezone":"Europe/Moscow",
    "iso:country":"RU",
    "name:eng_x_preferred":[
        "Ves\u00eblyy"
    ],
    "name:nor_x_preferred":[
        "Veselyj"
    ],
    "name:rus_x_preferred":[
        "\u0412\u0435\u0441\u0435\u043b\u044b\u0439"
    ],
    "name:rus_x_variant":[
        "\u0412\u0435\u0441\u0451\u043b\u044b\u0439"
    ],
    "name:und_x_variant":[
        "Imeni Stalina",
        "Ves\u00eblyy",
        "\u0412\u0435\u0441\u0451\u043b\u044b\u0439"
    ],
    "wof:name":"Veselyy",
    "wof:placetype":"locality"
},
  "geometry": {"coordinates":[42.1947,44.8031],"type":"Point"}
}