{
  "type": "Feature",
  "properties": {
    "gn:admin1_code":"80",
    "gn:asciiname":"Osen'chugi",
    "gn:country_code":"RU",
    "gn:dem":257,
    "gn:feature_class":"P",
    "gn:feature_code":"PPL",
    "gn:name":"Osen\u2019chugi",
    "gn:population":0,
    "gn:timezone":"Europe/Samara",
    "iso:country":"RU",
    "name:rus_x_preferred":[
        "\u041e\u0441\u0435\u043d\u044c\u0447\u0443\u0433\u0438"
    ],
    "name:und_x_variant":[
        "Osen\u2019chugi",
        "\u041e\u0441\u0435\u043d\u044c\u0447\u0443\u0433\u0438"
    ],
    "wof:name":"Osen'chugi",
    "wof:placetype":"locality"
},
  "geometry": {"coordinates":[53.9402,58.0952],"type":"Point"}
}