{
  "type": "Feature",
  "properties": {
    "gn:admin1_code":"53",
    "gn:asciiname":"Yasnaya Polyana",
    "gn:country_code":"RU",
    "gn:dem":109,
    "gn:feature_class":"P",
    "gn:feature_code":"PPL",
    "gn:name":"Yasnaya Polyana",
    "gn:population":0,
    "gn:timezone":"Asia/Novosibirsk",
    "iso:country":"RU",
    "wof:name":"Yasnaya Polyana",
    "wof:placetype":"locality"
},
  "geometry": {"coordinates":[75.71666999999999,55.43333000000001],"type":"Point"}
}