{
  "type": "Feature",
  "properties": {
    "gn:admin1_code":"42",
    "gn:asciiname":"Rabochiy Poselok Nomer Pyatyy",
    "gn:country_code":"RU",
    "gn:dem":62,
    "gn:feature_class":"P",
    "gn:feature_code":"PPL",
    "gn:name":"Rabochiy Pos\u00eblok Nomer Pyatyy",
    "gn:population":0,
    "gn:timezone":"Europe/Moscow",
    "iso:country":"RU",
    "wof:name":"Rabochiy Poselok Nomer Pyatyy",
    "wof:placetype":"locality"
},
  "geometry": {"coordinates":[31.61667000000001,59.71666999999999],"type":"Point"}
}