{
  "type": "Feature",
  "properties": {
    "gn:admin1_code":"89",
    "gn:asciiname":"Mar'ino",
    "gn:country_code":"RU",
    "gn:dem":188,
    "gn:feature_class":"P",
    "gn:feature_code":"PPL",
    "gn:name":"Mar\u2019ino",
    "gn:population":0,
    "gn:timezone":"Asia/Vladivostok",
    "iso:country":"RU",
    "name:rus_x_preferred":[
        "\u041c\u0430\u0440\u044c\u0438\u043d\u043e"
    ],
    "name:und_x_variant":[
        "Mar\u2019inskiy",
        "Mar\u2019ino",
        "\u041c\u0430\u0440\u044c\u0438\u043d\u043e"
    ],
    "wof:name":"Mar'ino",
    "wof:placetype":"locality"
},
  "geometry": {"coordinates":[130.63333,48.51667],"type":"Point"}
}