{
  "type": "Feature",
  "properties": {
    "gn:admin1_code":"85",
    "gn:asciiname":"Rodino",
    "gn:country_code":"RU",
    "gn:dem":139,
    "gn:feature_class":"P",
    "gn:feature_code":"PPL",
    "gn:name":"Rodino",
    "gn:population":0,
    "gn:timezone":"Europe/Moscow",
    "iso:country":"RU",
    "name:rus_x_preferred":[
        "\u0420\u043e\u0434\u0438\u043d\u043e"
    ],
    "name:und_x_variant":[
        "\u0420\u043e\u0434\u0438\u043d\u043e"
    ],
    "wof:name":"Rodino",
    "wof:placetype":"locality"
},
  "geometry": {"coordinates":[38.50493,59.96657],"type":"Point"}
}