{
  "type": "Feature",
  "properties": {
    "gn:admin1_code":"6",
    "gn:asciiname":"Topsa",
    "gn:country_code":"RU",
    "gn:dem":77,
    "gn:feature_class":"P",
    "gn:feature_code":"PPL",
    "gn:name":"Topsa",
    "gn:population":0,
    "gn:timezone":"Europe/Moscow",
    "iso:country":"RU",
    "name:che_x_preferred":[
        "\u0422\u043e\u043f\u0441\u0430"
    ],
    "name:hye_x_preferred":[
        "\u054f\u0578\u057a\u057d\u0561"
    ],
    "name:rus_x_preferred":[
        "\u0422\u043e\u043f\u0441\u0430"
    ],
    "name:tgk_x_preferred":[
        "\u0422\u043e\u043f\u0441\u0430"
    ],
    "wof:name":"Topsa",
    "wof:placetype":"locality"
},
  "geometry": {"coordinates":[46.66727,61.6341],"type":"Point"}
}