{
  "type": "Feature",
  "properties": {
    "gn:admin1_code":"54",
    "gn:asciiname":"Kharlamovo",
    "gn:country_code":"RU",
    "gn:dem":89,
    "gn:feature_class":"P",
    "gn:feature_code":"PPL",
    "gn:name":"Kharlamovo",
    "gn:population":0,
    "gn:timezone":"Asia/Omsk",
    "iso:country":"RU",
    "name:eng_x_preferred":[
        "Kharlamovo"
    ],
    "name:nor_x_preferred":[
        "Kharlamovo"
    ],
    "name:rus_x_preferred":[
        "\u0425\u0430\u0440\u043b\u0430\u043c\u043e\u0432\u043e"
    ],
    "name:und_x_variant":[
        "Imeni Kharlamova",
        "Kharlamovo"
    ],
    "wof:name":"Kharlamovo",
    "wof:placetype":"locality"
},
  "geometry": {"coordinates":[73.62447,54.68922],"type":"Point"}
}