{
  "type": "Feature",
  "properties": {
    "gn:admin1_code":"61",
    "gn:asciiname":"Podgorenskaya",
    "gn:country_code":"RU",
    "gn:dem":40,
    "gn:feature_class":"P",
    "gn:feature_code":"PPL",
    "gn:name":"Podgorenskaya",
    "gn:population":0,
    "gn:timezone":"Europe/Moscow",
    "iso:country":"RU",
    "name:rus_x_preferred":[
        "\u041f\u043e\u0434\u0433\u043e\u0440\u0435\u043d\u0441\u043a\u0430\u044f"
    ],
    "name:und_x_variant":[
        "Podgornyy",
        "Podgorenskaya"
    ],
    "wof:name":"Podgorenskaya",
    "wof:placetype":"locality"
},
  "geometry": {"coordinates":[42.3803,47.5627],"type":"Point"}
}