{
  "type": "Feature",
  "properties": {
    "gn:admin1_code":"33",
    "gn:asciiname":"Baranovshchina",
    "gn:country_code":"RU",
    "gn:dem":149,
    "gn:feature_class":"P",
    "gn:feature_code":"PPL",
    "gn:name":"Baranovshchina",
    "gn:population":0,
    "gn:timezone":"Europe/Kirov",
    "iso:country":"RU",
    "name:eng_x_preferred":[
        "Baranovshchina"
    ],
    "name:nor_x_preferred":[
        "Baranovsjtsjina"
    ],
    "name:rus_x_preferred":[
        "\u0411\u0430\u0440\u0430\u043d\u043e\u0432\u0449\u0438\u043d\u0430"
    ],
    "name:und_x_variant":[
        "\u0411\u0430\u0440\u0430\u043d\u043e\u0432\u0449\u0438\u043d\u0430",
        "Baranovshchina"
    ],
    "wof:name":"Baranovshchina",
    "wof:placetype":"locality"
},
  "geometry": {"coordinates":[49.56079,58.20323000000001],"type":"Point"}
}