{
  "type": "Feature",
  "properties": {
    "gn:admin1_code":"33",
    "gn:asciiname":"Zamyatino",
    "gn:country_code":"RU",
    "gn:dem":101,
    "gn:feature_class":"P",
    "gn:feature_code":"PPL",
    "gn:name":"Zamyatino",
    "gn:population":0,
    "gn:timezone":"Europe/Kirov",
    "iso:country":"RU",
    "name:rus_x_preferred":[
        "\u0417\u0430\u043c\u044f\u0442\u0438\u043d\u043e"
    ],
    "wof:name":"Zamyatino",
    "wof:placetype":"locality"
},
  "geometry": {"coordinates":[47.18837,56.95439],"type":"Point"}
}