{
  "type": "Feature",
  "properties": {
    "gn:admin1_code":"13.0",
    "gn:asciiname":"Babarykinskiy",
    "gn:country_code":"RU",
    "gn:dem":440,
    "gn:feature_class":"P",
    "gn:feature_code":"PPL",
    "gn:name":"Babarykinskiy",
    "gn:population":0,
    "gn:timezone":"Asia/Yekaterinburg",
    "iso:country":"RU",
    "name:eng_x_preferred":[
        "Babarykinskiy"
    ],
    "name:nor_x_preferred":[
        "Babarykinskij"
    ],
    "name:rus_x_preferred":[
        "\u0411\u0430\u0431\u0430\u0440\u044b\u043a\u0438\u043d\u0441\u043a\u0438\u0439"
    ],
    "name:und_x_variant":[
        "Babaryk",
        "\u0411\u0430\u0431\u0430\u0440\u044b\u043a\u0438\u043d\u0441\u043a\u0438\u0439",
        "Babarykinskiy"
    ],
    "wof:name":"Babarykinskiy",
    "wof:placetype":"locality"
},
  "geometry": {"coordinates":[59.3086,53.5447],"type":"Point"}
}