{
  "type": "Feature",
  "properties": {
    "gn:admin1_code":"84.0",
    "gn:asciiname":"Blizhnepodgorskiy",
    "gn:country_code":"RU",
    "gn:dem":38,
    "gn:feature_class":"P",
    "gn:feature_code":"PPL",
    "gn:name":"Blizhnepodgorskiy",
    "gn:population":0,
    "gn:timezone":"Europe/Volgograd",
    "iso:country":"RU",
    "name:eng_x_preferred":[
        "Blizhnepodgorskiy"
    ],
    "name:nor_x_preferred":[
        "Blizjnepodgorskij"
    ],
    "name:rus_x_preferred":[
        "\u0411\u043b\u0438\u0436\u043d\u0435\u043f\u043e\u0434\u0433\u043e\u0440\u0441\u043a\u0438\u0439"
    ],
    "name:und_x_variant":[
        "Blizhnemel\u2019nichnyy",
        "\u0411\u043b\u0438\u0436\u043d\u0435\u043f\u043e\u0434\u0433\u043e\u0440\u0441\u043a\u0438\u0439",
        "Blizhnepodgorskiy"
    ],
    "wof:name":"Blizhnepodgorskiy",
    "wof:placetype":"locality"
},
  "geometry": {"coordinates":[43.07028,48.41886],"type":"Point"}
}