{
  "type": "Feature",
  "properties": {
    "gn:country":"RU",
    "gn:fcode":"PPL",
    "gn:pop":0,
    "iso:country":"RU",
    "name:bel_x_preferred":[
        "\u0406\u0432\u0430\u043d\u043e\u045e\u0441\u043a\u0456"
    ],
    "name:ceb_x_preferred":[
        "\u0418\u0432\u0430\u043d\u043e\u0432\u0441\u043a\u0438\u0439"
    ],
    "name:che_x_preferred":[
        "\u0418\u0432\u0430\u043d\u043e\u0432\u0441\u043a\u0438\u0439"
    ],
    "name:deu_x_preferred":[
        "Iwanowski"
    ],
    "name:eng_x_preferred":[
        "Ivanovsky"
    ],
    "name:fra_x_preferred":[
        "Ivanovsky"
    ],
    "name:hye_x_preferred":[
        "\u053b\u057e\u0561\u0576\u0578\u057e\u057d\u056f\u056b"
    ],
    "name:ita_x_preferred":[
        "Ivanovskij"
    ],
    "name:kat_x_preferred":[
        "\u10d8\u10d5\u10d0\u10dc\u10dd\u10d5\u10e1\u10d9\u10d8"
    ],
    "name:nld_x_preferred":[
        "Ivanovsky"
    ],
    "name:rus_x_preferred":[
        "\u0418\u0432\u0430\u043d\u043e\u0432\u0441\u043a\u043e\u0435"
    ],
    "name:rus_x_variant":[
        "\u0418\u0432\u0430\u043d\u043e\u0432\u0441\u043a\u0438\u0439"
    ],
    "name:srp_x_preferred":[
        "\u0418\u0432\u0430\u043d\u043e\u0432\u0441\u043a\u0438"
    ],
    "name:ukr_x_preferred":[
        "\u0406\u0432\u0430\u043d\u043e\u0432\u0441\u044c\u043a\u0438\u0439"
    ],
    "name:unk_x_variant":[
        "\u0418\u0432\u0430\u043d\u043e\u0432\u0441\u043a\u043e\u0435"
    ],
    "qs:name":"Ivanovskoye",
    "qs:name_adm0":"Russia",
    "qs:name_adm1":"Moscow Oblast",
    "qs:photos_9r":0,
    "qs:photos_sr":0,
    "qs:placetype":"Town",
    "qs:pop_sr":"0",
    "wd:wordcount":88,
    "wof:name":"Ivanovskoye",
    "wof:placetype":"locality",
    "wof:population":0
},
  "geometry": {"coordinates":[36.7216,56.106],"type":"Point"}
}