{
  "type": "Feature",
  "properties": {
    "gn:country":"RU",
    "gn:fcode":"PPL",
    "gn:pop":0,
    "iso:country":"RU",
    "name:rus_x_preferred":[
        "\u0418\u0432\u0430\u043d\u043e\u0432\u0441\u043a\u043e\u0435"
    ],
    "name:unk_x_variant":[
        "\u0418\u0432\u0430\u043d\u043e\u0432\u0441\u043a\u043e\u0435"
    ],
    "qs:name":"Ivanovskoye",
    "qs:name_adm0":"Russia",
    "qs:name_adm1":"Moscow Oblast",
    "qs:photos_9r":0,
    "qs:photos_sr":0,
    "qs:placetype":"Town",
    "qs:pop_sr":"0",
    "wd:wordcount":88,
    "wof:name":"Ivanovskoye",
    "wof:placetype":"locality",
    "wof:population":0
},
  "geometry": {"coordinates":[36.7216,56.106],"type":"Point"}
}