{
  "type": "Feature",
  "properties": {
    "gn:admin1_code":"56",
    "gn:asciiname":"Korovnik",
    "gn:country_code":"RU",
    "gn:dem":223,
    "gn:feature_class":"P",
    "gn:feature_code":"PPL",
    "gn:name":"Korovnik",
    "gn:population":0,
    "gn:timezone":"Europe/Moscow",
    "iso:country":"RU",
    "name:rus_x_preferred":[
        "\u041a\u043e\u0440\u043e\u0432\u043d\u0438\u043a"
    ],
    "name:und_x_variant":[
        "\u041a\u043e\u0440\u043e\u0432\u043d\u0438\u043a"
    ],
    "wof:name":"Korovnik",
    "wof:placetype":"locality"
},
  "geometry": {"coordinates":[36.7738,52.7871],"type":"Point"}
}