{
  "type": "Feature",
  "properties": {
    "gn:admin1_code":"10",
    "gn:asciiname":"Troyebortnoye",
    "gn:country_code":"RU",
    "gn:dem":197,
    "gn:feature_class":"P",
    "gn:feature_code":"PPL",
    "gn:name":"Troyebortnoye",
    "gn:population":0,
    "gn:timezone":"Europe/Moscow",
    "iso:country":"RU",
    "name:rus_x_preferred":[
        "\u0422\u0440\u043e\u0435\u0431\u043e\u0440\u0442\u043d\u043e\u0435"
    ],
    "wof:name":"Troyebortnoye",
    "wof:placetype":"locality"
},
  "geometry": {"coordinates":[34.3946,51.8883],"type":"Point"}
}