{
  "type": "Feature",
  "properties": {
    "gn:admin1_code":"52.0",
    "gn:asciiname":"Gladovo",
    "gn:country_code":"RU",
    "gn:dem":214,
    "gn:feature_class":"P",
    "gn:feature_code":"PPL",
    "gn:name":"Gladovo",
    "gn:population":0,
    "gn:timezone":"Europe/Moscow",
    "iso:country":"RU",
    "name:rus_x_preferred":[
        "\u0413\u043b\u0430\u0434\u043e\u0432\u043e"
    ],
    "name:und_x_variant":[
        "\u0413\u043b\u0430\u0434\u043e\u0432\u043e"
    ],
    "wof:name":"Gladovo",
    "wof:placetype":"locality"
},
  "geometry": {"coordinates":[33.83333,58.91667],"type":"Point"}
}