{
  "type": "Feature",
  "properties": {
    "gn:admin1_code":"90.0",
    "gn:asciiname":"Erna",
    "gn:country_code":"RU",
    "gn:dem":181,
    "gn:feature_class":"P",
    "gn:feature_code":"PPL",
    "gn:name":"Erna",
    "gn:population":0,
    "gn:timezone":"Asia/Yekaterinburg",
    "iso:country":"RU",
    "name:ceb_x_preferred":[
        "Erna"
    ],
    "name:deu_x_preferred":[
        "Erna"
    ],
    "name:eng_x_preferred":[
        "Erna"
    ],
    "name:nor_x_preferred":[
        "Erna"
    ],
    "name:por_x_preferred":[
        "Erna"
    ],
    "name:rus_x_preferred":[
        "\u042d\u0440\u043d\u0430"
    ],
    "name:swe_x_preferred":[
        "Erna"
    ],
    "wof:name":"Erna",
    "wof:placetype":"locality"
},
  "geometry": {"coordinates":[55.3678,59.3506],"type":"Point"}
}