{
  "type": "Feature",
  "properties": {
    "gn:admin1_code":"53",
    "gn:asciiname":"Yevgen'yevka",
    "gn:country_code":"RU",
    "gn:dem":109,
    "gn:feature_class":"P",
    "gn:feature_code":"PPL",
    "gn:name":"Yevgen\u2019yevka",
    "gn:population":0,
    "gn:timezone":"Asia/Novosibirsk",
    "iso:country":"RU",
    "name:eng_x_preferred":[
        "Yevgen'yevka"
    ],
    "name:nor_x_preferred":[
        "Jevgenjevka"
    ],
    "name:rus_x_preferred":[
        "\u0415\u0432\u0433\u0435\u043d\u044c\u0435\u0432\u043a\u0430"
    ],
    "name:und_x_variant":[
        "Yevgen\u2019yevka"
    ],
    "wof:name":"Yevgen'yevka",
    "wof:placetype":"locality"
},
  "geometry": {"coordinates":[75.69164000000001,55.08418],"type":"Point"}
}