{
  "type": "Feature",
  "properties": {
    "gn:admin1_code":"88",
    "gn:asciiname":"Praskov'ino",
    "gn:country_code":"RU",
    "gn:dem":129,
    "gn:feature_class":"P",
    "gn:feature_code":"PPL",
    "gn:name":"Praskov\u2019ino",
    "gn:population":0,
    "gn:timezone":"Europe/Moscow",
    "iso:country":"RU",
    "name:rus_x_preferred":[
        "\u041f\u0440\u0430\u0441\u043a\u043e\u0432\u044c\u0438\u043d\u043e"
    ],
    "name:und_x_variant":[
        "Praskov\u2019ino"
    ],
    "wof:name":"Praskov'ino",
    "wof:placetype":"locality"
},
  "geometry": {"coordinates":[39.65967,57.4706],"type":"Point"}
}