{
  "type": "Feature",
  "properties": {
    "gn:admin1_code":"24.0",
    "gn:asciiname":"Shurn-Tsalym",
    "gn:country_code":"RU",
    "gn:dem":-2,
    "gn:feature_class":"P",
    "gn:feature_code":"PPL",
    "gn:name":"Shurn-Tsalym",
    "gn:population":0,
    "gn:timezone":"Europe/Moscow",
    "iso:country":"RU",
    "wof:name":"Shurn-Tsalym",
    "wof:placetype":"locality"
},
  "geometry": {"coordinates":[44.97194,47.24611],"type":"Point"}
}