{
  "type": "Feature",
  "properties": {
    "gn:admin1_code":"54",
    "gn:asciiname":"Kyzyl-Agash",
    "gn:country_code":"RU",
    "gn:dem":84,
    "gn:feature_class":"P",
    "gn:feature_code":"PPL",
    "gn:name":"Kyzyl-Agash",
    "gn:population":0,
    "gn:timezone":"Asia/Omsk",
    "iso:country":"RU",
    "name:eng_x_preferred":[
        "Kyzyl-Agash"
    ],
    "name:nor_x_preferred":[
        "Kzyl-Agasj"
    ],
    "name:rus_x_preferred":[
        "\u041a\u0437\u044b\u043b-\u0410\u0433\u0430\u0448"
    ],
    "wof:name":"Kyzyl-Agash",
    "wof:placetype":"locality"
},
  "geometry": {"coordinates":[71.84798000000001,54.71215],"type":"Point"}
}