{
  "type": "Feature",
  "properties": {
    "gn:admin1_code":"23",
    "gn:asciiname":"Muromskoye",
    "gn:country_code":"RU",
    "gn:dem":20,
    "gn:feature_class":"P",
    "gn:feature_code":"PPL",
    "gn:name":"Muromskoye",
    "gn:population":0,
    "gn:timezone":"Europe/Kaliningrad",
    "iso:country":"RU",
    "name:eng_x_preferred":[
        "Muromskoye"
    ],
    "name:nor_x_preferred":[
        "Muromskoje"
    ],
    "name:rus_x_preferred":[
        "\u041c\u0443\u0440\u043e\u043c\u0441\u043a\u043e\u0435"
    ],
    "name:und_x_variant":[
        "Lyaptau",
        "Laptau",
        "\u041c\u0443\u0440\u043e\u043c\u0441\u043a\u043e\u0435",
        "Muromskoye"
    ],
    "wof:name":"Muromskoye",
    "wof:placetype":"locality"
},
  "geometry": {"coordinates":[20.49148,54.89719],"type":"Point"}
}