{
  "type": "Feature",
  "properties": {
    "gn:admin1_code":"85",
    "gn:asciiname":"Podalets",
    "gn:country_code":"RU",
    "gn:dem":127,
    "gn:feature_class":"P",
    "gn:feature_code":"PPL",
    "gn:name":"Podalets",
    "gn:population":0,
    "gn:timezone":"Europe/Moscow",
    "iso:country":"RU",
    "name:rus_x_preferred":[
        "\u041f\u043e\u0434\u0430\u043b\u0435\u0446"
    ],
    "wof:name":"Podalets",
    "wof:placetype":"locality"
},
  "geometry": {"coordinates":[39.27888,59.66239],"type":"Point"}
}