{
  "type": "Feature",
  "properties": {
    "gn:admin1_code":"33",
    "gn:asciiname":"Zabegayevo",
    "gn:country_code":"RU",
    "gn:dem":176,
    "gn:feature_class":"P",
    "gn:feature_code":"PPL",
    "gn:name":"Zabegayevo",
    "gn:population":0,
    "gn:timezone":"Europe/Kirov",
    "iso:country":"RU",
    "name:eng_x_preferred":[
        "Zabegayevo"
    ],
    "name:nor_x_preferred":[
        "Zabegajevo"
    ],
    "name:rus_x_preferred":[
        "\u0417\u0430\u0431\u0435\u0433\u0430\u0435\u0432\u043e"
    ],
    "wof:name":"Zabegayevo",
    "wof:placetype":"locality"
},
  "geometry": {"coordinates":[49.70496,58.95895],"type":"Point"}
}