{
  "type": "Feature",
  "properties": {
    "gn:admin1_code":"60",
    "gn:asciiname":"Usovo",
    "gn:country_code":"RU",
    "gn:dem":124,
    "gn:feature_class":"P",
    "gn:feature_code":"PPL",
    "gn:name":"Usovo",
    "gn:population":0,
    "gn:timezone":"Europe/Moscow",
    "iso:country":"RU",
    "name:rus_x_preferred":[
        "\u0423\u0441\u043e\u0432\u043e \u041e\u0432\u0438\u043d\u043a\u0438"
    ],
    "name:rus_x_variant":[
        "\u0423\u0441\u043e\u0432\u043e"
    ],
    "name:und_x_variant":[
        "Usovo Ovinki",
        "Usovo"
    ],
    "wof:name":"Usovo",
    "wof:placetype":"locality"
},
  "geometry": {"coordinates":[28.2178,56.3686],"type":"Point"}
}