{
  "type": "Feature",
  "properties": {
    "gn:admin1_code":"80",
    "gn:asciiname":"Staryye Zyattsy",
    "gn:country_code":"RU",
    "gn:dem":163,
    "gn:feature_class":"P",
    "gn:feature_code":"PPL",
    "gn:name":"Staryye Zyattsy",
    "gn:population":0,
    "gn:timezone":"Europe/Samara",
    "iso:country":"RU",
    "name:rus_x_preferred":[
        "\u0421\u0442\u0430\u0440\u044b\u0435 \u0417\u044f\u0442\u0446\u044b"
    ],
    "wof:name":"Staryye Zyattsy",
    "wof:placetype":"locality"
},
  "geometry": {"coordinates":[52.6496,57.3463],"type":"Point"}
}