{
  "type": "Feature",
  "properties": {
    "gn:admin1_code":"29",
    "gn:asciiname":"Verkhnyaya Mitikha",
    "gn:cc2":"RU",
    "gn:country_code":"RU",
    "gn:dem":206,
    "gn:feature_class":"P",
    "gn:feature_code":"PPL",
    "gn:name":"Verkhnyaya Mitikha",
    "gn:population":0,
    "gn:timezone":"Asia/Novokuznetsk",
    "iso:country":"RU",
    "name:und_x_variant":[
        "Verkhnyaya Mit\u2019kina",
        "Verkhnyaya Mitikha"
    ],
    "wof:name":"Verkhnyaya Mitikha",
    "wof:placetype":"locality"
},
  "geometry": {"coordinates":[84.93333,55.28333000000001],"type":"Point"}
}