{
  "type": "Feature",
  "properties": {
    "gn:admin1_code":"51",
    "gn:asciiname":"Pomra",
    "gn:country_code":"RU",
    "gn:dem":135,
    "gn:feature_class":"P",
    "gn:feature_code":"PPL",
    "gn:name":"Pomra",
    "gn:population":0,
    "gn:timezone":"Europe/Moscow",
    "iso:country":"RU",
    "name:rus_x_preferred":[
        "\u041f\u043e\u043c\u0440\u0430"
    ],
    "name:und_x_variant":[
        "\u041f\u043e\u043c\u0440\u0430"
    ],
    "wof:name":"Pomra",
    "wof:placetype":"locality"
},
  "geometry": {"coordinates":[44.31963,55.77681],"type":"Point"}
}