{
  "type": "Feature",
  "properties": {
    "gn:admin1_code":"77.0",
    "gn:asciiname":"Borodino",
    "gn:country_code":"RU",
    "gn:dem":222,
    "gn:feature_class":"P",
    "gn:feature_code":"PPL",
    "gn:name":"Borodino",
    "gn:population":0,
    "gn:timezone":"Europe/Moscow",
    "iso:country":"RU",
    "name:rus_x_preferred":[
        "\u0411\u043e\u0440\u043e\u0434\u0438\u043d\u043e"
    ],
    "name:und_x_variant":[
        "Ganino-Udel\u2019noye",
        "Borodino"
    ],
    "wof:name":"Borodino",
    "wof:placetype":"locality"
},
  "geometry": {"coordinates":[32.70003,56.64248000000001],"type":"Point"}
}