{
  "type": "Feature",
  "properties": {
    "gn:admin1_code":"80.0",
    "gn:asciiname":"Zyaniyevo",
    "gn:country_code":"RU",
    "gn:dem":234,
    "gn:feature_class":"P",
    "gn:feature_code":"PPL",
    "gn:name":"Zyaniyevo",
    "gn:population":0,
    "gn:timezone":"Europe/Samara",
    "iso:country":"RU",
    "name:rus_x_preferred":[
        "\u0417\u044f\u043d\u0438\u0435\u0432\u043e"
    ],
    "wof:name":"Zyaniyevo",
    "wof:placetype":"locality"
},
  "geometry": {"coordinates":[53.1901,58.0419],"type":"Point"}
}