{
  "type": "Feature",
  "properties": {
    "gn:admin1_code":"61",
    "gn:asciiname":"Odintsovka",
    "gn:country_code":"RU",
    "gn:dem":58,
    "gn:feature_class":"P",
    "gn:feature_code":"PPL",
    "gn:name":"Odintsovka",
    "gn:population":0,
    "gn:timezone":"Europe/Moscow",
    "iso:country":"RU",
    "name:rus_x_preferred":[
        "\u041e\u0434\u0438\u043d\u0446\u043e\u0432\u043a\u0430"
    ],
    "name:und_x_variant":[
        "Odinsovka",
        "Odintsovka",
        "\u041e\u0434\u0438\u043d\u0446\u043e\u0432\u043a\u0430"
    ],
    "wof:name":"Odintsovka",
    "wof:placetype":"locality"
},
  "geometry": {"coordinates":[41.16942,46.70218],"type":"Point"}
}