{
  "type": "Feature",
  "properties": {
    "gn:admin1_code":"16.0",
    "gn:asciiname":"Chelkasy",
    "gn:country_code":"RU",
    "gn:dem":99,
    "gn:feature_class":"P",
    "gn:feature_code":"PPL",
    "gn:name":"Chelkasy",
    "gn:population":0,
    "gn:timezone":"Europe/Moscow",
    "iso:country":"RU",
    "name:rus_x_preferred":[
        "\u0427\u0435\u043b\u043a\u0430\u0441\u044b"
    ],
    "name:und_x_variant":[
        "\u0427\u0435\u043b\u043a\u0430\u0441\u044b"
    ],
    "wof:name":"Chelkasy",
    "wof:placetype":"locality"
},
  "geometry": {"coordinates":[46.95063,55.74135],"type":"Point"}
}