{
  "type": "Feature",
  "properties": {
    "gn:admin1_code":"90.0",
    "gn:asciiname":"Demino",
    "gn:country_code":"RU",
    "gn:dem":184,
    "gn:feature_class":"P",
    "gn:feature_code":"PPL",
    "gn:name":"D\u00ebmino",
    "gn:population":0,
    "gn:timezone":"Asia/Yekaterinburg",
    "iso:country":"RU",
    "name:che_x_preferred":[
        "\u0414\u0435\u043c\u0438\u043d\u043e"
    ],
    "name:koi_x_preferred":[
        "\u0414\u0451\u043c\u0430"
    ],
    "name:rus_x_preferred":[
        "\u0414\u0451\u043c\u0438\u043d\u043e"
    ],
    "name:rus_x_variant":[
        "\u0414\u0435\u043c\u0438\u043d\u043e"
    ],
    "name:und_x_variant":[
        "D\u00ebmina",
        "D\u00ebmino"
    ],
    "wof:name":"Demino",
    "wof:placetype":"locality"
},
  "geometry": {"coordinates":[54.3362,59.6272],"type":"Point"}
}