{
  "type": "Feature",
  "properties": {
    "gn:admin1_code":"70.0",
    "gn:asciiname":"Budennogo",
    "gn:country_code":"RU",
    "gn:dem":6,
    "gn:feature_class":"P",
    "gn:feature_code":"PPL",
    "gn:name":"Budennogo",
    "gn:population":0,
    "gn:timezone":"Europe/Moscow",
    "iso:country":"RU",
    "name:rus_x_preferred":[
        "\u0411\u0443\u0434\u0435\u043d\u043d\u043e\u0433\u043e"
    ],
    "name:und_x_variant":[
        "\u0411\u0443\u0434\u0435\u043d\u043d\u043e\u0433\u043e"
    ],
    "wof:name":"Budennogo",
    "wof:placetype":"locality"
},
  "geometry": {"coordinates":[45.56806,45.09972],"type":"Point"}
}