{
  "type": "Feature",
  "properties": {
    "gn:admin1_code":"62",
    "gn:asciiname":"Polovnevo",
    "gn:country_code":"RU",
    "gn:dem":176,
    "gn:feature_class":"P",
    "gn:feature_code":"PPL",
    "gn:name":"Polovnevo",
    "gn:population":0,
    "gn:timezone":"Europe/Moscow",
    "iso:country":"RU",
    "name:rus_x_preferred":[
        "\u041f\u043e\u043b\u043e\u0432\u043d\u0435\u0432\u043e"
    ],
    "wof:name":"Polovnevo",
    "wof:placetype":"locality"
},
  "geometry": {"coordinates":[39.0662,54.00185],"type":"Point"}
}