{
  "type": "Feature",
  "properties": {
    "gn:admin1_code":"85.0",
    "gn:asciiname":"Artem'yevskaya",
    "gn:country_code":"RU",
    "gn:dem":120,
    "gn:feature_class":"P",
    "gn:feature_code":"PPL",
    "gn:name":"Artem\u2019yevskaya",
    "gn:population":0,
    "gn:timezone":"Europe/Moscow",
    "iso:country":"RU",
    "name:eng_x_preferred":[
        "Artem'yevskaya"
    ],
    "name:nor_x_preferred":[
        "Artemjevskaja"
    ],
    "name:rus_x_preferred":[
        "\u0410\u0440\u0442\u0435\u043c\u044c\u0435\u0432\u0441\u043a\u0430\u044f"
    ],
    "name:rus_x_variant":[
        "Artem\u2019yevskaya"
    ],
    "wof:name":"Artem'yevskaya",
    "wof:placetype":"locality"
},
  "geometry": {"coordinates":[41.6201,60.7478],"type":"Point"}
}