{
  "type": "Feature",
  "properties": {
    "gn:admin1_code":"25",
    "gn:asciiname":"Ugra",
    "gn:country_code":"RU",
    "gn:dem":141,
    "gn:feature_class":"P",
    "gn:feature_code":"PPL",
    "gn:name":"Ugra",
    "gn:population":0,
    "gn:timezone":"Europe/Moscow",
    "iso:country":"RU",
    "name:bel_x_preferred":[
        "\u0423\u0433\u0440\u0430"
    ],
    "name:ceb_x_preferred":[
        "Ugra"
    ],
    "name:deu_x_preferred":[
        "Ugra"
    ],
    "name:hrv_x_preferred":[
        "Ugra"
    ],
    "name:hun_x_preferred":[
        "Ugra"
    ],
    "name:ita_x_preferred":[
        "Ugra"
    ],
    "name:lav_x_preferred":[
        "Ugra"
    ],
    "name:rus_x_preferred":[
        "\u0423\u0433\u0440\u0430"
    ],
    "name:srp_x_preferred":[
        "\u0423\u0433\u0440\u0430"
    ],
    "wof:name":"Ugra",
    "wof:placetype":"locality"
},
  "geometry": {"coordinates":[36.0906,54.50541],"type":"Point"}
}