{
  "type": "Feature",
  "properties": {
    "gn:admin1_code":"55",
    "gn:asciiname":"Kandurovka",
    "gn:country_code":"RU",
    "gn:dem":170,
    "gn:feature_class":"P",
    "gn:feature_code":"PPL",
    "gn:name":"Kandurovka",
    "gn:population":0,
    "gn:timezone":"Asia/Yekaterinburg",
    "iso:country":"RU",
    "name:eng_x_preferred":[
        "Kandurovka"
    ],
    "name:nor_x_preferred":[
        "Kondurovka"
    ],
    "name:rus_x_preferred":[
        "\u041a\u043e\u043d\u0434\u0443\u0440\u043e\u0432\u043a\u0430"
    ],
    "name:rus_x_variant":[
        "\u041a\u0430\u043d\u0434\u0443\u0440\u043e\u0432\u043a\u0430"
    ],
    "name:und_x_variant":[
        "Rondurovski"
    ],
    "wof:name":"Kandurovka",
    "wof:placetype":"locality"
},
  "geometry": {"coordinates":[56.69017,51.52678],"type":"Point"}
}