{
  "type": "Feature",
  "properties": {
    "gn:admin1_code":"51",
    "gn:asciiname":"Semet'",
    "gn:country_code":"RU",
    "gn:dem":99,
    "gn:feature_class":"P",
    "gn:feature_code":"PPL",
    "gn:name":"Semet\u2019",
    "gn:population":0,
    "gn:timezone":"Europe/Moscow",
    "iso:country":"RU",
    "name:rus_x_preferred":[
        "\u0421\u0435\u043c\u0435\u0442\u044c"
    ],
    "name:und_x_variant":[
        "Semet\u2019"
    ],
    "wof:name":"Semet'",
    "wof:placetype":"locality"
},
  "geometry": {"coordinates":[44.06121,56.0767],"type":"Point"}
}