{
  "type": "Feature",
  "properties": {
    "gn:admin1_code":"4",
    "gn:asciiname":"Krasnoye Razdol'ye",
    "gn:country_code":"RU",
    "gn:dem":350,
    "gn:feature_class":"P",
    "gn:feature_code":"PPL",
    "gn:name":"Krasnoye Razdol\u2019ye",
    "gn:population":0,
    "gn:timezone":"Asia/Barnaul",
    "iso:country":"RU",
    "name:eng_x_preferred":[
        "Krasnoye Razdol'ye"
    ],
    "name:nor_x_preferred":[
        "Krasnoje-Razdolje"
    ],
    "name:rus_x_preferred":[
        "\u041a\u0440\u0430\u0441\u043d\u043e\u0435-\u0420\u0430\u0437\u0434\u043e\u043b\u044c\u0435"
    ],
    "name:rus_x_variant":[
        "\u041a\u0440\u0430\u0441\u043d\u043e\u0435 \u0420\u0430\u0437\u0434\u043e\u043b\u044c\u0435"
    ],
    "name:und_x_variant":[
        "Krasnoye Razdol\u2019ye",
        "\u041a\u0440\u0430\u0441\u043d\u043e\u0435 \u0420\u0430\u0437\u0434\u043e\u043b\u044c\u0435"
    ],
    "wof:name":"Krasnoye Razdol'ye",
    "wof:placetype":"locality"
},
  "geometry": {"coordinates":[82.33417,50.91028],"type":"Point"}
}