{
  "type": "Feature",
  "properties": {
    "gn:admin1_code":"90.0",
    "gn:asciiname":"Chasovnya",
    "gn:country_code":"RU",
    "gn:dem":155,
    "gn:feature_class":"P",
    "gn:feature_code":"PPL",
    "gn:name":"Chasovnya",
    "gn:population":0,
    "gn:timezone":"Asia/Yekaterinburg",
    "iso:country":"RU",
    "name:rus_x_preferred":[
        "\u0427\u0430\u0441\u043e\u0432\u043d\u044f"
    ],
    "wof:name":"Chasovnya",
    "wof:placetype":"locality"
},
  "geometry": {"coordinates":[55.8002,58.2614],"type":"Point"}
}