{
  "type": "Feature",
  "properties": {
    "gn:admin1_code":"8",
    "gn:asciiname":"Ibragimovo",
    "gn:country_code":"RU",
    "gn:dem":238,
    "gn:feature_class":"P",
    "gn:feature_code":"PPL",
    "gn:name":"Ibragimovo",
    "gn:population":0,
    "gn:timezone":"Asia/Yekaterinburg",
    "iso:country":"RU",
    "name:bak_x_preferred":[
        "\u0418\u0431\u0440\u0430\u04bb\u0438\u043c"
    ],
    "name:che_x_preferred":[
        "\u0418\u0431\u0440\u0430\u0433\u0438\u043c\u043e\u0432\u043e"
    ],
    "name:hye_x_preferred":[
        "\u053b\u0562\u0580\u0561\u0563\u056b\u0574\u0578\u057e\u0578"
    ],
    "name:kaz_x_preferred":[
        "\u0418\u0431\u0440\u0430\u0433\u0438\u043c"
    ],
    "name:kir_x_preferred":[
        "\u0418\u0431\u0440\u0430\u0433\u0438\u043c"
    ],
    "name:rus_x_preferred":[
        "\u0418\u0431\u0440\u0430\u0433\u0438\u043c\u043e\u0432\u043e"
    ],
    "name:tat_x_preferred":[
        "\u0418\u0431\u0440\u0430\u04bb\u0438\u043c"
    ],
    "name:ukr_x_preferred":[
        "\u0406\u0431\u0440\u0430\u0433\u0456\u043c\u043e\u0432\u043e"
    ],
    "name:und_x_variant":[
        "\u0418\u0431\u0440\u0430\u0433\u0438\u043c\u043e\u0432\u043e"
    ],
    "wof:name":"Ibragimovo",
    "wof:placetype":"locality"
},
  "geometry": {"coordinates":[56.68736,52.67531999999999],"type":"Point"}
}