{
  "type": "Feature",
  "properties": {
    "gn:admin1_code":"69",
    "gn:asciiname":"Frolovskiy",
    "gn:country_code":"RU",
    "gn:dem":175,
    "gn:feature_class":"P",
    "gn:feature_code":"PPL",
    "gn:name":"Frolovskiy",
    "gn:population":0,
    "gn:timezone":"Europe/Moscow",
    "iso:country":"RU",
    "name:rus_x_preferred":[
        "\u0424\u0440\u043e\u043b\u043e\u0432\u0441\u043a\u0438\u0439"
    ],
    "name:und_x_variant":[
        "\u0424\u0440\u043e\u043b\u043e\u0432\u0441\u043a\u0438\u0439"
    ],
    "wof:name":"Frolovskiy",
    "wof:placetype":"locality"
},
  "geometry": {"coordinates":[32.61833,53.49694],"type":"Point"}
}