{
  "type": "Feature",
  "properties": {
    "gn:admin1_code":"88",
    "gn:asciiname":"Daratniki",
    "gn:country_code":"RU",
    "gn:dem":131,
    "gn:feature_class":"P",
    "gn:feature_code":"PPL",
    "gn:name":"Daratniki",
    "gn:population":0,
    "gn:timezone":"Europe/Moscow",
    "iso:country":"RU",
    "name:rus_x_preferred":[
        "\u0414\u0430\u0440\u0430\u0442\u043d\u0438\u043a\u0438"
    ],
    "wof:name":"Daratniki",
    "wof:placetype":"locality"
},
  "geometry": {"coordinates":[38.2831,57.0489],"type":"Point"}
}