{
  "type": "Feature",
  "properties": {
    "gn:admin1_code":"6.0",
    "gn:asciiname":"Gar'",
    "gn:country_code":"RU",
    "gn:dem":120,
    "gn:feature_class":"P",
    "gn:feature_code":"PPL",
    "gn:name":"Gar\u2019",
    "gn:population":0,
    "gn:timezone":"Europe/Moscow",
    "iso:country":"RU",
    "name:rus_x_preferred":[
        "\u0413\u0430\u0440\u044c"
    ],
    "name:und_x_variant":[
        "Gar\u2019"
    ],
    "wof:name":"Gar'",
    "wof:placetype":"locality"
},
  "geometry": {"coordinates":[38.79892,61.92081999999999],"type":"Point"}
}