{
  "type": "Feature",
  "properties": {
    "gn:admin1_code":"60",
    "gn:asciiname":"Mayevo",
    "gn:country_code":"RU",
    "gn:dem":217,
    "gn:feature_class":"P",
    "gn:feature_code":"PPL",
    "gn:name":"Mayevo",
    "gn:population":0,
    "gn:timezone":"Europe/Moscow",
    "iso:country":"RU",
    "name:eng_x_preferred":[
        "Mayevo"
    ],
    "name:nor_x_preferred":[
        "Majevo"
    ],
    "name:rus_x_preferred":[
        "\u041c\u0430\u0435\u0432\u043e"
    ],
    "name:und_x_variant":[
        "\u041c\u0430\u0435\u0432\u043e",
        "Mayevo"
    ],
    "wof:name":"Mayevo",
    "wof:placetype":"locality"
},
  "geometry": {"coordinates":[29.7953,56.36035],"type":"Point"}
}