{
  "type": "Feature",
  "properties": {
    "gn:admin1_code":"8",
    "gn:asciiname":"Kugarchi",
    "gn:country_code":"RU",
    "gn:dem":230,
    "gn:feature_class":"P",
    "gn:feature_code":"PPL",
    "gn:name":"Kugarchi",
    "gn:population":0,
    "gn:timezone":"Asia/Yekaterinburg",
    "iso:country":"RU",
    "name:eng_x_preferred":[
        "Kugarchi"
    ],
    "name:nor_x_preferred":[
        "Kugartsji"
    ],
    "name:rus_x_preferred":[
        "\u041a\u0443\u0433\u0430\u0440\u0447\u0438"
    ],
    "name:und_x_variant":[
        "\u041a\u0443\u0433\u0430\u0440\u0447\u0438",
        "Kugarchi"
    ],
    "wof:name":"Kugarchi",
    "wof:placetype":"locality"
},
  "geometry": {"coordinates":[56.57903,52.43726],"type":"Point"}
}