{
  "type": "Feature",
  "properties": {
    "gn:admin1_code":"55",
    "gn:asciiname":"Kokosheyevka",
    "gn:country_code":"RU",
    "gn:dem":122,
    "gn:feature_class":"P",
    "gn:feature_code":"PPL",
    "gn:name":"Kokosheyevka",
    "gn:population":0,
    "gn:timezone":"Asia/Yekaterinburg",
    "iso:country":"RU",
    "name:eng_x_preferred":[
        "Kokosheyevka"
    ],
    "name:nor_x_preferred":[
        "Kokosjejevka"
    ],
    "name:rus_x_preferred":[
        "\u041a\u043e\u043a\u043e\u0448\u0435\u0435\u0432\u043a\u0430"
    ],
    "wof:name":"Kokosheyevka",
    "wof:placetype":"locality"
},
  "geometry": {"coordinates":[52.3656,53.482],"type":"Point"}
}