{
  "type": "Feature",
  "properties": {
    "gn:admin1_code":"42",
    "gn:asciiname":"Kelkolovo",
    "gn:country_code":"RU",
    "gn:dem":42,
    "gn:feature_class":"P",
    "gn:feature_code":"PPL",
    "gn:name":"Kelkolovo",
    "gn:population":0,
    "gn:timezone":"Europe/Moscow",
    "iso:country":"RU",
    "name:fin_x_preferred":[
        "Kelkkula"
    ],
    "name:rus_x_preferred":[
        "\u041a\u0435\u043b\u043a\u043e\u043b\u043e\u0432\u043e"
    ],
    "wof:name":"Kelkolovo",
    "wof:placetype":"locality"
},
  "geometry": {"coordinates":[31.01667,59.78333000000001],"type":"Point"}
}