{
  "type": "Feature",
  "properties": {
    "gn:admin1_code":"86.0",
    "gn:asciiname":"Dedovka",
    "gn:country_code":"RU",
    "gn:dem":73,
    "gn:feature_class":"P",
    "gn:feature_code":"PPL",
    "gn:name":"Dedovka",
    "gn:population":0,
    "gn:timezone":"Europe/Moscow",
    "iso:country":"RU",
    "name:rus_x_preferred":[
        "\u0414\u0435\u0434\u043e\u0432\u043a\u0430"
    ],
    "wof:name":"Dedovka",
    "wof:placetype":"locality"
},
  "geometry": {"coordinates":[40.945,49.88861],"type":"Point"}
}