{
  "type": "Feature",
  "properties": {
    "gn:admin1_code":"53",
    "gn:asciiname":"Vorob'yevo",
    "gn:country_code":"RU",
    "gn:dem":95,
    "gn:feature_class":"P",
    "gn:feature_code":"PPL",
    "gn:name":"Vorob\u2019y\u00ebvo",
    "gn:population":0,
    "gn:timezone":"Asia/Novosibirsk",
    "iso:country":"RU",
    "name:rus_x_preferred":[
        "\u0412\u043e\u0440\u043e\u0431\u044c\u00eb\u0432\u043e"
    ],
    "name:und_x_variant":[
        "Vorob\u2019y\u00ebvo"
    ],
    "wof:name":"Vorob'yevo",
    "wof:placetype":"locality"
},
  "geometry": {"coordinates":[82.5703,55.3087],"type":"Point"}
}