{
  "type": "Feature",
  "properties": {
    "gn:admin1_code":"41.0",
    "gn:asciiname":"Bogatyr'",
    "gn:country_code":"RU",
    "gn:dem":149,
    "gn:feature_class":"P",
    "gn:feature_code":"PPL",
    "gn:name":"Bogatyr\u2019",
    "gn:population":0,
    "gn:timezone":"Europe/Moscow",
    "iso:country":"RU",
    "name:rus_x_preferred":[
        "\u0411\u043e\u0433\u0430\u0442\u044b\u0440\u044c"
    ],
    "name:und_x_variant":[
        "Bogatyr\u2019",
        "\u0411\u043e\u0433\u0430\u0442\u044b\u0440\u044c"
    ],
    "wof:name":"Bogatyr'",
    "wof:placetype":"locality"
},
  "geometry": {"coordinates":[35.0438,51.8633],"type":"Point"}
}