{
  "type": "Feature",
  "properties": {
    "gn:admin1_code":"77",
    "gn:asciiname":"Lyubini",
    "gn:country_code":"RU",
    "gn:dem":137,
    "gn:feature_class":"P",
    "gn:feature_code":"PPL",
    "gn:name":"Lyubini",
    "gn:population":0,
    "gn:timezone":"Europe/Moscow",
    "iso:country":"RU",
    "name:rus_x_preferred":[
        "\u041b\u044e\u0431\u0438\u043d\u0438"
    ],
    "name:und_x_variant":[
        "Lyubino",
        "Lyubini",
        "\u041b\u044e\u0431\u0438\u043d\u0438"
    ],
    "wof:name":"Lyubini",
    "wof:placetype":"locality"
},
  "geometry": {"coordinates":[36.38698,57.98263000000001],"type":"Point"}
}