{
  "type": "Feature",
  "properties": {
    "gn:admin1_code":"37",
    "gn:asciiname":"Marfino",
    "gn:country_code":"RU",
    "gn:dem":158,
    "gn:feature_class":"P",
    "gn:feature_code":"PPL",
    "gn:name":"Marfino",
    "gn:population":0,
    "gn:timezone":"Europe/Moscow",
    "iso:country":"RU",
    "name:rus_x_preferred":[
        "\u041c\u0430\u0440\u0444\u0438\u043d\u043e"
    ],
    "wof:name":"Marfino",
    "wof:placetype":"locality"
},
  "geometry": {"coordinates":[42.9655,58.7559],"type":"Point"}
}