{
  "type": "Feature",
  "properties": {
    "gn:admin1_code":"80",
    "gn:asciiname":"Staryye Kaksi",
    "gn:country_code":"RU",
    "gn:dem":144,
    "gn:feature_class":"P",
    "gn:feature_code":"PPL",
    "gn:name":"Staryye Kaksi",
    "gn:population":0,
    "gn:timezone":"Europe/Samara",
    "iso:country":"RU",
    "name:rus_x_preferred":[
        "\u0421\u0442\u0430\u0440\u044b\u0435 \u041a\u0430\u043a\u0441\u0438"
    ],
    "wof:name":"Staryye Kaksi",
    "wof:placetype":"locality"
},
  "geometry": {"coordinates":[51.38083,57.00659],"type":"Point"}
}