{
  "type": "Feature",
  "properties": {
    "gn:admin1_code":"85",
    "gn:asciiname":"Yugozero-Varino",
    "gn:country_code":"RU",
    "gn:dem":196,
    "gn:feature_class":"P",
    "gn:feature_code":"PPL",
    "gn:name":"Yugozero-Varino",
    "gn:population":0,
    "gn:timezone":"Europe/Moscow",
    "iso:country":"RU",
    "name:und_x_variant":[
        "Varino",
        "Varina",
        "Yugozero-Varino"
    ],
    "wof:name":"Yugozero-Varino",
    "wof:placetype":"locality"
},
  "geometry": {"coordinates":[37.24879,61.24795],"type":"Point"}
}