{
  "type": "Feature",
  "properties": {
    "gn:admin1_code":"71",
    "gn:asciiname":"Pashnya",
    "gn:country_code":"RU",
    "gn:dem":65,
    "gn:feature_class":"P",
    "gn:feature_code":"PPL",
    "gn:name":"Pashnya",
    "gn:population":0,
    "gn:timezone":"Asia/Yekaterinburg",
    "iso:country":"RU",
    "name:che_x_preferred":[
        "\u041f\u0430\u0448\u043d\u044f"
    ],
    "name:rus_x_preferred":[
        "\u041f\u0430\u0448\u043d\u044f"
    ],
    "wof:name":"Pashnya",
    "wof:placetype":"locality"
},
  "geometry": {"coordinates":[63.44161999999999,59.24849],"type":"Point"}
}