{
  "type": "Feature",
  "properties": {
    "gn:admin1_code":"77",
    "gn:asciiname":"Pominovo",
    "gn:country_code":"RU",
    "gn:dem":201,
    "gn:feature_class":"P",
    "gn:feature_code":"PPL",
    "gn:name":"Pominovo",
    "gn:population":0,
    "gn:timezone":"Europe/Moscow",
    "iso:country":"RU",
    "name:rus_x_preferred":[
        "\u041f\u043e\u043c\u0438\u043d\u043e\u0432\u043e"
    ],
    "wof:name":"Pominovo",
    "wof:placetype":"locality"
},
  "geometry": {"coordinates":[36.0125,56.7309],"type":"Point"}
}