{
  "type": "Feature",
  "properties": {
    "gn:admin1_code":"76",
    "gn:asciiname":"Ulanovskiy",
    "gn:country_code":"RU",
    "gn:dem":242,
    "gn:feature_class":"P",
    "gn:feature_code":"PPL",
    "gn:name":"Ulanovskiy",
    "gn:population":0,
    "gn:timezone":"Europe/Moscow",
    "iso:country":"RU",
    "name:eng_x_preferred":[
        "Ulanovka"
    ],
    "name:nor_x_preferred":[
        "Ulanovskij"
    ],
    "name:rus_x_preferred":[
        "\u0423\u043b\u0430\u043d\u043e\u0432\u0441\u043a\u0438\u0439"
    ],
    "wof:name":"Ulanovskiy",
    "wof:placetype":"locality"
},
  "geometry": {"coordinates":[37.85433,54.06372],"type":"Point"}
}