{
  "type": "Feature",
  "properties": {
    "gn:admin1_code":"16",
    "gn:asciiname":"Nizhniye Khachiki",
    "gn:country_code":"RU",
    "gn:dem":145,
    "gn:feature_class":"P",
    "gn:feature_code":"PPL",
    "gn:name":"Nizhniye Khachiki",
    "gn:population":0,
    "gn:timezone":"Europe/Moscow",
    "iso:country":"RU",
    "name:rus_x_preferred":[
        "\u041d\u0438\u0436\u043d\u0438\u0435 \u0425\u0430\u0447\u0438\u043a\u0438"
    ],
    "name:und_x_variant":[
        "\u041d\u0438\u0436\u043d\u0438\u0435 \u0425\u0430\u0447\u0438\u043a\u0438",
        "Nizhniye Khacheki"
    ],
    "wof:name":"Nizhniye Khachiki",
    "wof:placetype":"locality"
},
  "geometry": {"coordinates":[46.7783,56.074],"type":"Point"}
}