{
  "type": "Feature",
  "properties": {
    "gn:admin1_code":"51",
    "gn:asciiname":"Gorbanovo",
    "gn:country_code":"RU",
    "gn:dem":102,
    "gn:feature_class":"P",
    "gn:feature_code":"PPL",
    "gn:name":"Gorbanovo",
    "gn:population":0,
    "gn:timezone":"Europe/Moscow",
    "iso:country":"RU",
    "name:rus_x_preferred":[
        "\u0413\u043e\u0440\u0431\u0430\u043d\u043e\u0432\u043e"
    ],
    "wof:name":"Gorbanovo",
    "wof:placetype":"locality"
},
  "geometry": {"coordinates":[42.9695,55.9214],"type":"Point"}
}