{
  "type": "Feature",
  "properties": {
    "gn:admin1_code":"45.0",
    "gn:asciiname":"Maskarodo",
    "gn:country_code":"RU",
    "gn:dem":147,
    "gn:feature_class":"P",
    "gn:feature_code":"PPL",
    "gn:name":"Maskarodo",
    "gn:population":0,
    "gn:timezone":"Europe/Moscow",
    "iso:country":"RU",
    "name:rus_x_preferred":[
        "\u041c\u0430\u0441\u043a\u0430\u0440\u043e\u0434\u043e"
    ],
    "name:und_x_variant":[
        "\u041c\u0430\u0441\u043a\u0430\u0440\u043e\u0434\u043e"
    ],
    "wof:name":"Maskarodo",
    "wof:placetype":"locality"
},
  "geometry": {"coordinates":[48.665,56.74889],"type":"Point"}
}