{
  "type": "Feature",
  "properties": {
    "gn:admin1_code":"71",
    "gn:asciiname":"Pozdnyakovka",
    "gn:country_code":"RU",
    "gn:dem":199,
    "gn:feature_class":"P",
    "gn:feature_code":"PPL",
    "gn:name":"Pozdnyakovka",
    "gn:population":0,
    "gn:timezone":"Asia/Yekaterinburg",
    "iso:country":"RU",
    "name:eng_x_preferred":[
        "Pozdnyakovka"
    ],
    "name:nor_x_preferred":[
        "Pozdnjakovka"
    ],
    "name:rus_x_preferred":[
        "\u041f\u043e\u0437\u0434\u043d\u044f\u043a\u043e\u0432\u043a\u0430"
    ],
    "wof:name":"Pozdnyakovka",
    "wof:placetype":"locality"
},
  "geometry": {"coordinates":[60.0211,59.1253],"type":"Point"}
}