{
  "type": "Feature",
  "properties": {
    "gn:admin1_code":"91",
    "gn:asciiname":"Lebed'",
    "gn:country_code":"RU",
    "gn:dem":46,
    "gn:feature_class":"P",
    "gn:feature_code":"PPL",
    "gn:name":"Lebed\u2019",
    "gn:population":0,
    "gn:timezone":"Asia/Krasnoyarsk",
    "iso:country":"RU",
    "name:eng_x_preferred":[
        "Lebed'"
    ],
    "name:nor_x_preferred":[
        "Lebed"
    ],
    "name:rus_x_preferred":[
        "\u041b\u0435\u0431\u0435\u0434\u044c"
    ],
    "name:und_x_variant":[
        "Lebed\u2019"
    ],
    "wof:name":"Lebed'",
    "wof:placetype":"locality"
},
  "geometry": {"coordinates":[89.18639,62.09444000000001],"type":"Point"}
}