{
  "type": "Feature",
  "properties": {
    "gn:country":"RU",
    "gn:fcode":"PPL",
    "gn:pop":0,
    "iso:country":"RU",
    "name:eng_x_preferred":[
        "Nizhegorodskaya"
    ],
    "name:nor_x_preferred":[
        "Nizjegorodskaja"
    ],
    "name:rus_x_preferred":[
        "\u041d\u0438\u0436\u0435\u0433\u043e\u0440\u043e\u0434\u0441\u043a\u0430\u044f"
    ],
    "name:unk_x_variant":[
        "\u041d\u0438\u0436\u0435\u0433\u043e\u0440\u043e\u0434\u0441\u043a\u0430\u044f"
    ],
    "qs:name":"Nizhegorodskaya",
    "qs:name_adm0":"Russia",
    "qs:name_adm1":"Krasnodar Krai",
    "qs:photos_9k":1,
    "qs:photos_9r":1,
    "qs:photos_all":2,
    "qs:photos_sr":0,
    "qs:placetype":"Town",
    "qs:pop_sr":"0",
    "wd:wordcount":66,
    "wof:name":"Nizhegorodskaya",
    "wof:placetype":"locality",
    "wof:population":0
},
  "geometry": {"coordinates":[39.9234,44.2692],"type":"Point"}
}