{
  "type": "Feature",
  "properties": {
    "gn:admin1_code":"85",
    "gn:asciiname":"Mineyka",
    "gn:country_code":"RU",
    "gn:dem":143,
    "gn:feature_class":"P",
    "gn:feature_code":"PPL",
    "gn:name":"Mineyka",
    "gn:population":0,
    "gn:timezone":"Europe/Moscow",
    "iso:country":"RU",
    "name:rus_x_preferred":[
        "\u041c\u0438\u043d\u0435\u0439\u043a\u0430"
    ],
    "name:und_x_variant":[
        "\u041c\u0438\u043d\u0435\u0439\u043a\u0430"
    ],
    "wof:name":"Mineyka",
    "wof:placetype":"locality"
},
  "geometry": {"coordinates":[39.31533,59.30009],"type":"Point"}
}