{
  "type": "Feature",
  "properties": {
    "gn:admin1_code":"29",
    "gn:asciiname":"Verkh-Kochura",
    "gn:country_code":"RU",
    "gn:dem":502,
    "gn:feature_class":"P",
    "gn:feature_code":"PPL",
    "gn:name":"Verkh-Kochura",
    "gn:population":0,
    "gn:timezone":"Asia/Novokuznetsk",
    "iso:country":"RU",
    "name:rus_x_preferred":[
        "\u0412\u0435\u0440\u0445-\u041a\u043e\u0447\u0443\u0440\u0430"
    ],
    "name:und_x_variant":[
        "Ulus Verkhnyaya Kochura",
        "Verkh-Kochura",
        "\u0412\u0435\u0440\u0445-\u041a\u043e\u0447\u0443\u0440\u0430",
        "Verkhnyaya Kochura"
    ],
    "wof:name":"Verkh-Kochura",
    "wof:placetype":"locality"
},
  "geometry": {"coordinates":[87.9686,52.6562],"type":"Point"}
}