{
  "type": "Feature",
  "properties": {
    "gn:admin1_code":"52",
    "gn:asciiname":"Uloma",
    "gn:country_code":"RU",
    "gn:dem":167,
    "gn:feature_class":"P",
    "gn:feature_code":"PPL",
    "gn:name":"Uloma",
    "gn:population":0,
    "gn:timezone":"Europe/Moscow",
    "iso:country":"RU",
    "name:rus_x_preferred":[
        "\u0423\u043b\u043e\u043c\u0430"
    ],
    "name:und_x_variant":[
        "Ulama",
        "Uloma"
    ],
    "wof:name":"Uloma",
    "wof:placetype":"locality"
},
  "geometry": {"coordinates":[35.37351,58.45557],"type":"Point"}
}