{
  "type": "Feature",
  "properties": {
    "gn:admin1_code":"43",
    "gn:asciiname":"Metelkino",
    "gn:country_code":"RU",
    "gn:dem":213,
    "gn:feature_class":"P",
    "gn:feature_code":"PPL",
    "gn:name":"Metelkino",
    "gn:population":0,
    "gn:timezone":"Europe/Moscow",
    "iso:country":"RU",
    "name:rus_x_preferred":[
        "\u041c\u0435\u0442\u0435\u043b\u043a\u0438\u043d\u043e"
    ],
    "name:und_x_variant":[
        "\u041c\u0435\u0442\u0435\u043b\u043a\u0438\u043d\u043e"
    ],
    "wof:name":"Metelkino",
    "wof:placetype":"locality"
},
  "geometry": {"coordinates":[38.5342,52.8411],"type":"Point"}
}