{
  "type": "Feature",
  "properties": {
    "gn:admin1_code":"45.0",
    "gn:asciiname":"Uktash",
    "gn:country_code":"RU",
    "gn:dem":181,
    "gn:feature_class":"P",
    "gn:feature_code":"PPL",
    "gn:name":"Uktash",
    "gn:population":0,
    "gn:timezone":"Europe/Moscow",
    "iso:country":"RU",
    "name:rus_x_preferred":[
        "\u0423\u043a\u0442\u0430\u0448"
    ],
    "wof:name":"Uktash",
    "wof:placetype":"locality"
},
  "geometry": {"coordinates":[48.86694,57.03056],"type":"Point"}
}