{
  "type": "Feature",
  "properties": {
    "gn:admin1_code":"47",
    "gn:asciiname":"Stepantsevo",
    "gn:country_code":"RU",
    "gn:dem":134,
    "gn:feature_class":"P",
    "gn:feature_code":"PPL",
    "gn:name":"Stepantsevo",
    "gn:population":0,
    "gn:timezone":"Europe/Moscow",
    "iso:country":"RU",
    "name:eng_x_preferred":[
        "Stepantsevo"
    ],
    "name:nor_x_preferred":[
        "Stepantsevo"
    ],
    "name:rus_x_preferred":[
        "\u0421\u0442\u0435\u043f\u0430\u043d\u0446\u0435\u0432\u043e"
    ],
    "name:und_x_variant":[
        "\u0421\u0442\u0435\u043f\u0430\u043d\u0446\u0435\u0432\u043e"
    ],
    "wof:name":"Stepantsevo",
    "wof:placetype":"locality"
},
  "geometry": {"coordinates":[36.17192,56.37634],"type":"Point"}
}