{
  "type": "Feature",
  "properties": {
    "gn:admin1_code":"65",
    "gn:asciiname":"Neprik",
    "gn:country_code":"RU",
    "gn:dem":156,
    "gn:feature_class":"P",
    "gn:feature_code":"PPL",
    "gn:name":"Neprik",
    "gn:population":0,
    "gn:timezone":"Europe/Samara",
    "iso:country":"RU",
    "name:eng_x_preferred":[
        "Neprik"
    ],
    "name:nor_x_preferred":[
        "Neprik"
    ],
    "name:rus_x_preferred":[
        "\u041d\u0435\u043f\u0440\u0438\u043a"
    ],
    "wof:name":"Neprik",
    "wof:placetype":"locality"
},
  "geometry": {"coordinates":[51.84657,53.12236],"type":"Point"}
}