{
  "type": "Feature",
  "properties": {
    "gn:admin1_code":"69",
    "gn:asciiname":"Savostino",
    "gn:country_code":"RU",
    "gn:dem":260,
    "gn:feature_class":"P",
    "gn:feature_code":"PPL",
    "gn:name":"Savostino",
    "gn:population":0,
    "gn:timezone":"Europe/Moscow",
    "iso:country":"RU",
    "name:rus_x_preferred":[
        "\u0421\u0430\u0432\u043e\u0441\u0442\u0438\u043d\u043e"
    ],
    "name:und_x_variant":[
        "\u0421\u0430\u0432\u043e\u0441\u0442\u0438\u043d\u043e"
    ],
    "wof:name":"Savostino",
    "wof:placetype":"locality"
},
  "geometry": {"coordinates":[33.25484,54.71915],"type":"Point"}
}