{
  "type": "Feature",
  "properties": {
    "gn:admin1_code":"60",
    "gn:asciiname":"Kashevarovo",
    "gn:country_code":"RU",
    "gn:dem":46,
    "gn:feature_class":"P",
    "gn:feature_code":"PPL",
    "gn:name":"Kashevarovo",
    "gn:population":0,
    "gn:timezone":"Europe/Moscow",
    "iso:country":"RU",
    "name:rus_x_preferred":[
        "\u041a\u0430\u0448\u0435\u0432\u0430\u0440\u043e\u0432\u043e"
    ],
    "wof:name":"Kashevarovo",
    "wof:placetype":"locality"
},
  "geometry": {"coordinates":[28.4913,57.7412],"type":"Point"}
}