{
  "type": "Feature",
  "properties": {
    "gn:country":"RU",
    "gn:fcode":"PPL",
    "gn:population":0,
    "iso:country":"RU",
    "name:eng_x_preferred":[
        "Ozeretskoye"
    ],
    "name:nor_x_preferred":[
        "Ozeretskoje"
    ],
    "name:rus_x_preferred":[
        "\u041e\u0437\u0435\u0440\u0435\u0446\u043a\u043e\u0435"
    ],
    "name:rus_x_variant":[
        "\u041e\u0437\u0435\u0440\u0435\u0442\u0441\u043a\u043e\u0435"
    ],
    "qs:name":"Ozerskoe",
    "qs:name_adm0":"Russia",
    "qs:name_adm1":"Moscow Oblast",
    "qs:photos_9r":0,
    "qs:photos_sr":0,
    "qs:placetype":"Town",
    "qs:pop_sr":"0",
    "wof:name":"Ozerskoe",
    "wof:placetype":"locality",
    "wof:population":0
},
  "geometry": {"coordinates":[37.38333,56.06667],"type":"Point"}
}