{
  "type": "Feature",
  "properties": {
    "gn:admin1_code":"8.0",
    "gn:asciiname":"Fedotovka",
    "gn:country_code":"RU",
    "gn:dem":175,
    "gn:feature_class":"P",
    "gn:feature_code":"PPL",
    "gn:name":"Fedotovka",
    "gn:population":0,
    "gn:timezone":"Asia/Yekaterinburg",
    "iso:country":"RU",
    "name:rus_x_preferred":[
        "\u0424\u0435\u0434\u043e\u0442\u043e\u0432\u043a\u0430"
    ],
    "wof:name":"Fedotovka",
    "wof:placetype":"locality"
},
  "geometry": {"coordinates":[55.4701,53.1291],"type":"Point"}
}