{
  "type": "Feature",
  "properties": {
    "gn:admin1_code":"6",
    "gn:asciiname":"Zavrazh'ya",
    "gn:country_code":"RU",
    "gn:dem":97,
    "gn:feature_class":"P",
    "gn:feature_code":"PPL",
    "gn:name":"Zavrazh\u2019ya",
    "gn:population":0,
    "gn:timezone":"Europe/Moscow",
    "iso:country":"RU",
    "name:und_x_variant":[
        "Zavrazh\u2019ye",
        "Zavrazh\u2019ya"
    ],
    "wof:name":"Zavrazh'ya",
    "wof:placetype":"locality"
},
  "geometry": {"coordinates":[46.65,61.15],"type":"Point"}
}