{
  "type": "Feature",
  "properties": {
    "gn:admin1_code":"33",
    "gn:asciiname":"Renevskaya",
    "gn:country_code":"RU",
    "gn:dem":195,
    "gn:feature_class":"P",
    "gn:feature_code":"PPL",
    "gn:name":"Renevskaya",
    "gn:population":0,
    "gn:timezone":"Europe/Kirov",
    "iso:country":"RU",
    "name:rus_x_preferred":[
        "\u0420\u0435\u043d\u0435\u0432\u0441\u043a\u0430\u044f"
    ],
    "wof:name":"Renevskaya",
    "wof:placetype":"locality"
},
  "geometry": {"coordinates":[52.41667,58.81667],"type":"Point"}
}