{
  "type": "Feature",
  "properties": {
    "iso:country":"RU",
    "name:rus_x_preferred":[
        "\u0421\u0430\u043f\u0451\u0440\u043d\u044b\u0439"
    ],
    "wof:name":"Sapyorny",
    "wof:placetype":"neighbourhood"
},
  "geometry": {"coordinates":[30.68504522941743,59.77714636196961],"type":"Point"}
}