{
  "type": "Feature",
  "properties": {
    "gn:admin1_code":"60",
    "gn:asciiname":"Gnil'no",
    "gn:country_code":"RU",
    "gn:dem":64,
    "gn:feature_class":"P",
    "gn:feature_code":"PPL",
    "gn:name":"Gnil\u2019no",
    "gn:population":0,
    "gn:timezone":"Europe/Moscow",
    "iso:country":"RU",
    "name:rus_x_preferred":[
        "\u0413\u043d\u0438\u043b\u044c\u043d\u043e"
    ],
    "name:und_x_variant":[
        "Gnil\u2019no"
    ],
    "wof:name":"Gnil'no",
    "wof:placetype":"locality"
},
  "geometry": {"coordinates":[28.6706,57.8253],"type":"Point"}
}