{
  "type": "Feature",
  "properties": {
    "gn:admin1_code":"69",
    "gn:asciiname":"Shchedra",
    "gn:country_code":"RU",
    "gn:dem":210,
    "gn:feature_class":"P",
    "gn:feature_code":"PPL",
    "gn:name":"Shchedra",
    "gn:population":0,
    "gn:timezone":"Europe/Moscow",
    "iso:country":"RU",
    "name:rus_x_preferred":[
        "\u0429\u0435\u0434\u0440\u0430"
    ],
    "wof:name":"Shchedra",
    "wof:placetype":"locality"
},
  "geometry": {"coordinates":[33.13333,53.86666999999999],"type":"Point"}
}