{
  "type": "Feature",
  "properties": {
    "gn:admin1_code":"29",
    "gn:asciiname":"Zeledeyevo",
    "gn:country_code":"RU",
    "gn:dem":99,
    "gn:feature_class":"P",
    "gn:feature_code":"PPL",
    "gn:name":"Zeledeyevo",
    "gn:population":0,
    "gn:timezone":"Asia/Novokuznetsk",
    "iso:country":"RU",
    "name:eng_x_preferred":[
        "Zaledeyevo"
    ],
    "name:nor_x_preferred":[
        "Zeledejevo"
    ],
    "name:rus_x_preferred":[
        "\u0417\u0435\u043b\u0435\u0434\u0435\u0435\u0432\u043e"
    ],
    "name:und_x_variant":[
        "Zeledeyevskoye",
        "Zaledeyevo",
        "Zeledeyevo"
    ],
    "wof:name":"Zeledeyevo",
    "wof:placetype":"locality"
},
  "geometry": {"coordinates":[84.87535,56.04093],"type":"Point"}
}