{
  "type": "Feature",
  "properties": {
    "gn:admin1_code":"37",
    "gn:asciiname":"Maslovo",
    "gn:country_code":"RU",
    "gn:dem":175,
    "gn:feature_class":"P",
    "gn:feature_code":"PPL",
    "gn:name":"Maslovo",
    "gn:population":0,
    "gn:timezone":"Europe/Moscow",
    "iso:country":"RU",
    "name:rus_x_preferred":[
        "\u041c\u0430\u0441\u043b\u043e\u0432\u043e"
    ],
    "name:und_x_variant":[
        "\u041c\u0430\u0441\u043b\u043e\u0432\u043e"
    ],
    "wof:name":"Maslovo",
    "wof:placetype":"locality"
},
  "geometry": {"coordinates":[43.3552,58.7363],"type":"Point"}
}