{
  "type": "Feature",
  "properties": {
    "gn:admin1_code":"63",
    "gn:asciiname":"Kulbik",
    "gn:country_code":"RU",
    "gn:dem":184,
    "gn:feature_class":"P",
    "gn:feature_code":"PPL",
    "gn:name":"Kulbik",
    "gn:population":0,
    "gn:timezone":"Asia/Vladivostok",
    "iso:country":"RU",
    "name:rus_x_preferred":[
        "\u041a\u0443\u043b\u0431\u0438\u043a"
    ],
    "name:und_x_variant":[
        "Kiloik",
        "Kilbik",
        "Kulbik",
        "\u041a\u0443\u043b\u0431\u0438\u043a"
    ],
    "wof:name":"Kulbik",
    "wof:placetype":"locality"
},
  "geometry": {"coordinates":[135.09891999999999,60.49057],"type":"Point"}
}