{
  "type": "Feature",
  "properties": {
    "gn:admin1_code":"34",
    "gn:asciiname":"Mokhcha",
    "gn:country_code":"RU",
    "gn:dem":38,
    "gn:feature_class":"P",
    "gn:feature_code":"PPL",
    "gn:name":"Mokhcha",
    "gn:population":0,
    "gn:timezone":"Europe/Moscow",
    "iso:country":"RU",
    "name:eng_x_preferred":[
        "Mokhcha"
    ],
    "name:nor_x_preferred":[
        "Mokhtsja"
    ],
    "name:rus_x_preferred":[
        "\u041c\u043e\u0445\u0447\u0430"
    ],
    "wof:name":"Mokhcha",
    "wof:placetype":"locality"
},
  "geometry": {"coordinates":[53.82711,65.00095],"type":"Point"}
}