{
  "type": "Feature",
  "properties": {
    "gn:admin1_code":"6",
    "gn:asciiname":"Kolodino",
    "gn:country_code":"RU",
    "gn:dem":100,
    "gn:feature_class":"P",
    "gn:feature_code":"PPL",
    "gn:name":"Kolodino",
    "gn:population":0,
    "gn:timezone":"Europe/Moscow",
    "iso:country":"RU",
    "name:rus_x_preferred":[
        "\u041a\u043e\u043b\u043e\u0434\u0438\u043d\u043e"
    ],
    "wof:name":"Kolodino",
    "wof:placetype":"locality"
},
  "geometry": {"coordinates":[48.3058,61.12951],"type":"Point"}
}