{
  "type": "Feature",
  "properties": {
    "gn:admin1_code":"25",
    "gn:asciiname":"Kurgan",
    "gn:country_code":"RU",
    "gn:dem":187,
    "gn:feature_class":"P",
    "gn:feature_code":"PPL",
    "gn:name":"Kurgan",
    "gn:population":0,
    "gn:timezone":"Europe/Moscow",
    "iso:country":"RU",
    "name:rus_x_preferred":[
        "\u041a\u0443\u0440\u0433\u0430\u043d"
    ],
    "name:und_x_variant":[
        "\u041a\u0443\u0440\u0433\u0430\u043d"
    ],
    "wof:name":"Kurgan",
    "wof:placetype":"locality"
},
  "geometry": {"coordinates":[35.03037,53.41309],"type":"Point"}
}