{
  "type": "Feature",
  "properties": {
    "gn:admin1_code":"25",
    "gn:asciiname":"Kurgan",
    "gn:country_code":"RU",
    "gn:dem":187,
    "gn:feature_class":"P",
    "gn:feature_code":"PPL",
    "gn:name":"Kurgan",
    "gn:population":0,
    "gn:timezone":"Europe/Moscow",
    "iso:country":"RU",
    "name:ara_x_preferred":[
        "\u0643\u0648\u0631\u063a\u0627\u0646"
    ],
    "name:aze_x_preferred":[
        "Kurqan"
    ],
    "name:bel_x_preferred":[
        "\u041a\u0443\u0440\u0433\u0430\u043d"
    ],
    "name:bul_x_preferred":[
        "\u041a\u0443\u0440\u0433\u0430\u043d"
    ],
    "name:cat_x_preferred":[
        "Kurgan"
    ],
    "name:che_x_preferred":[
        "\u0411\u0430\u0440\u0437"
    ],
    "name:dan_x_preferred":[
        "Kurgan"
    ],
    "name:deu_x_preferred":[
        "Kurgan"
    ],
    "name:epo_x_preferred":[
        "Kurgano"
    ],
    "name:est_x_preferred":[
        "Kurgaan"
    ],
    "name:fas_x_preferred":[
        "\u06a9\u0648\u0631\u06af\u0627\u0646"
    ],
    "name:fra_x_preferred":[
        "Kourgane"
    ],
    "name:fry_x_preferred":[
        "Koergan"
    ],
    "name:hun_x_preferred":[
        "Kurg\u00e1n"
    ],
    "name:hye_x_preferred":[
        "\u0534\u0561\u0574\u0562\u0561\u0580\u0561\u0576\u0561\u0562\u056c\u0578\u0582\u0580"
    ],
    "name:ita_x_preferred":[
        "Kurgan scita"
    ],
    "name:jpn_x_preferred":[
        "\u30af\u30eb\u30ac\u30f3"
    ],
    "name:kat_x_preferred":[
        "\u10e7\u10dd\u10e0\u10e6\u10d0\u10dc\u10d8"
    ],
    "name:kaz_x_preferred":[
        "\u049a\u043e\u0440\u0493\u0430\u043d"
    ],
    "name:lit_x_preferred":[
        "Kurganas"
    ],
    "name:nld_x_preferred":[
        "Koergan"
    ],
    "name:pol_x_preferred":[
        "Kurhan"
    ],
    "name:rus_x_preferred":[
        "\u041a\u0443\u0440\u0433\u0430\u043d"
    ],
    "name:sco_x_preferred":[
        "Kurgan"
    ],
    "name:spa_x_preferred":[
        "Kurg\u00e1n"
    ],
    "name:srp_x_preferred":[
        "\u041a\u0443\u0440\u0433\u0430\u043d"
    ],
    "name:swe_x_preferred":[
        "Kurganer"
    ],
    "name:tur_x_preferred":[
        "Kurgan"
    ],
    "name:ukr_x_preferred":[
        "\u041a\u0443\u0440\u0433\u0430\u043d"
    ],
    "name:und_x_variant":[
        "\u041a\u0443\u0440\u0433\u0430\u043d"
    ],
    "name:uzb_x_preferred":[
        "Mozorqo\u02bbrg\u02bbon"
    ],
    "name:vie_x_preferred":[
        "Kurgan"
    ],
    "wof:name":"Kurgan",
    "wof:placetype":"locality"
},
  "geometry": {"coordinates":[35.03037,53.41309],"type":"Point"}
}