{
  "type": "Feature",
  "properties": {
    "gn:admin1_code":"6.0",
    "gn:asciiname":"Butorinskaya",
    "gn:country_code":"RU",
    "gn:dem":81,
    "gn:feature_class":"P",
    "gn:feature_code":"PPL",
    "gn:name":"Butorinskaya",
    "gn:population":0,
    "gn:timezone":"Europe/Moscow",
    "iso:country":"RU",
    "name:eng_x_preferred":[
        "Butorinskaya"
    ],
    "name:nor_x_preferred":[
        "Butorinskaja"
    ],
    "name:rus_x_preferred":[
        "\u0411\u0443\u0442\u043e\u0440\u0438\u043d\u0441\u043a\u0430\u044f"
    ],
    "wof:name":"Butorinskaya",
    "wof:placetype":"locality"
},
  "geometry": {"coordinates":[42.37966,60.97988],"type":"Point"}
}