{
  "type": "Feature",
  "properties": {
    "gn:admin1_code":"51",
    "gn:asciiname":"Orekhovets",
    "gn:country_code":"RU",
    "gn:dem":167,
    "gn:feature_class":"P",
    "gn:feature_code":"PPL",
    "gn:name":"Orekhovets",
    "gn:population":0,
    "gn:timezone":"Europe/Moscow",
    "iso:country":"RU",
    "name:eng_x_preferred":[
        "Orekhovets"
    ],
    "name:nor_x_preferred":[
        "Orekhovets"
    ],
    "name:rus_x_preferred":[
        "\u041e\u0440\u0435\u0445\u043e\u0432\u0435\u0446"
    ],
    "wof:name":"Orekhovets",
    "wof:placetype":"locality"
},
  "geometry": {"coordinates":[43.62636,55.23114],"type":"Point"}
}