{
  "type": "Feature",
  "properties": {
    "gn:admin1_code":"77.0",
    "gn:asciiname":"Dornikovo",
    "gn:country_code":"RU",
    "gn:dem":260,
    "gn:feature_class":"P",
    "gn:feature_code":"PPL",
    "gn:name":"Dornikovo",
    "gn:population":0,
    "gn:timezone":"Europe/Moscow",
    "iso:country":"RU",
    "name:rus_x_preferred":[
        "\u0414\u043e\u0440\u043d\u0438\u043a\u043e\u0432\u043e"
    ],
    "wof:name":"Dornikovo",
    "wof:placetype":"locality"
},
  "geometry": {"coordinates":[34.15243,57.25304000000001],"type":"Point"}
}