{
  "type": "Feature",
  "properties": {
    "gn:admin1_code":"20.0",
    "gn:asciiname":"Letnyaya",
    "gn:country_code":"RU",
    "gn:dem":457,
    "gn:feature_class":"P",
    "gn:feature_code":"PPL",
    "gn:name":"Letnyaya",
    "gn:population":0,
    "gn:timezone":"Asia/Irkutsk",
    "iso:country":"RU",
    "name:rus_x_preferred":[
        "\u041b\u0435\u0442\u043d\u044f\u044f"
    ],
    "name:und_x_variant":[
        "\u041b\u0435\u0442\u043d\u044f\u044f"
    ],
    "wof:name":"Letnyaya",
    "wof:placetype":"locality"
},
  "geometry": {"coordinates":[104.06999999999999,52.15],"type":"Point"}
}