{
  "type": "Feature",
  "properties": {
    "gn:admin1_code":"7",
    "gn:asciiname":"Kuray",
    "gn:country_code":"RU",
    "gn:dem":-19,
    "gn:feature_class":"P",
    "gn:feature_code":"PPL",
    "gn:name":"Kuray",
    "gn:population":0,
    "gn:timezone":"Europe/Astrakhan",
    "iso:country":"RU",
    "name:ceb_x_preferred":[
        "Kuray"
    ],
    "name:che_x_preferred":[
        "\u041a\u0443\u0440\u0430\u0439"
    ],
    "name:nld_x_preferred":[
        "Koeraj"
    ],
    "name:rus_x_preferred":[
        "\u041a\u0443\u0440\u0430\u0439"
    ],
    "name:tat_x_preferred":[
        "\u041a\u0443\u0440\u0430\u0439"
    ],
    "name:ukr_x_preferred":[
        "\u041a\u0443\u0440\u0430\u0439"
    ],
    "wof:name":"Kuray",
    "wof:placetype":"locality"
},
  "geometry": {"coordinates":[46.9697,46.5361],"type":"Point"}
}