{
  "type": "Feature",
  "properties": {
    "gn:admin1_code":"77",
    "gn:asciiname":"Bychkovo",
    "gn:country_code":"RU",
    "gn:dem":169,
    "gn:feature_class":"P",
    "gn:feature_code":"PPL",
    "gn:name":"Bychkovo",
    "gn:population":0,
    "gn:timezone":"Europe/Moscow",
    "iso:country":"RU",
    "name:rus_x_preferred":[
        "\u0411\u044b\u0447\u043a\u043e\u0432\u043e"
    ],
    "wof:name":"Bychkovo",
    "wof:placetype":"locality"
},
  "geometry": {"coordinates":[37.3398,57.6126],"type":"Point"}
}