{
  "type": "Feature",
  "properties": {
    "gn:admin1_code":"62.0",
    "gn:asciiname":"Barskoye",
    "gn:country_code":"RU",
    "gn:dem":114,
    "gn:feature_class":"P",
    "gn:feature_code":"PPL",
    "gn:name":"Barskoye",
    "gn:population":0,
    "gn:timezone":"Europe/Moscow",
    "iso:country":"RU",
    "name:nor_x_preferred":[
        "Barskoje"
    ],
    "name:rus_x_preferred":[
        "\u0411\u0430\u0440\u0441\u043a\u043e\u0435"
    ],
    "wof:name":"Barskoye",
    "wof:placetype":"locality"
},
  "geometry": {"coordinates":[40.12302,55.21762],"type":"Point"}
}