{
  "type": "Feature",
  "properties": {
    "gn:admin1_code":"76",
    "gn:asciiname":"Babkin",
    "gn:country_code":"RU",
    "gn:dem":256,
    "gn:feature_class":"P",
    "gn:feature_code":"PPL",
    "gn:name":"Babkin",
    "gn:population":0,
    "gn:timezone":"Europe/Moscow",
    "iso:country":"RU",
    "name:nor_x_preferred":[
        "Babkin"
    ],
    "name:rus_x_preferred":[
        "\u0411\u0430\u0431\u043a\u0438\u043d"
    ],
    "wof:name":"Babkin",
    "wof:placetype":"locality"
},
  "geometry": {"coordinates":[37.65667,53.20361],"type":"Point"}
}