{
  "type": "Feature",
  "properties": {
    "gn:admin1_code":"44",
    "gn:asciiname":"Bogulino",
    "gn:country_code":"RU",
    "gn:dem":66,
    "gn:feature_class":"P",
    "gn:feature_code":"PPL",
    "gn:name":"Bogulino",
    "gn:population":0,
    "gn:timezone":"Asia/Magadan",
    "iso:country":"RU",
    "name:rus_x_preferred":[
        "\u0411\u043e\u0433\u0443\u043b\u0438\u043d\u043e"
    ],
    "wof:name":"Bogulino",
    "wof:placetype":"locality"
},
  "geometry": {"coordinates":[160.23333,62.15],"type":"Point"}
}