{
  "type": "Feature",
  "properties": {
    "gn:admin1_code":"64",
    "gn:asciiname":"Rybatskoye",
    "gn:country_code":"RU",
    "gn:dem":2,
    "gn:feature_class":"P",
    "gn:feature_code":"PPL",
    "gn:name":"Rybatskoye",
    "gn:population":0,
    "gn:timezone":"Asia/Sakhalin",
    "iso:country":"RU",
    "name:eng_x_preferred":[
        "Rybatskoye"
    ],
    "name:rus_x_preferred":[
        "\u0420\u044b\u0431\u0430\u0446\u043a\u043e\u0435"
    ],
    "name:rus_x_variant":[
        "\u0420\u044b\u0431\u0430\u0442\u0441\u043a\u043e\u0435"
    ],
    "name:und_x_variant":[
        "Kawaguti",
        "Kawaguchi"
    ],
    "wof:name":"Rybatskoye",
    "wof:placetype":"locality"
},
  "geometry": {"coordinates":[142.52215000000001,46.7004],"type":"Point"}
}