{
  "type": "Feature",
  "properties": {
    "iso:country":"RU",
    "name:rus_x_preferred":[
        "\u0414\u0435\u0442\u0441\u043a\u043e\u0441\u0435\u043b\u044c\u0441\u043a\u0438\u0439"
    ],
    "wof:name":"Detskoselskiy",
    "wof:placetype":"neighbourhood"
},
  "geometry": {"coordinates":[30.4672640529459,59.73108779047881],"type":"Point"}
}