{
  "type": "Feature",
  "properties": {
    "gn:admin1_code":"25.0",
    "gn:asciiname":"Ageyevka",
    "gn:country_code":"RU",
    "gn:dem":206,
    "gn:feature_class":"P",
    "gn:feature_code":"PPL",
    "gn:name":"Ageyevka",
    "gn:population":0,
    "gn:timezone":"Europe/Moscow",
    "iso:country":"RU",
    "name:nor_x_preferred":[
        "Agejevka"
    ],
    "name:rus_x_preferred":[
        "\u0410\u0433\u0435\u0435\u0432\u043a\u0430"
    ],
    "name:und_x_variant":[
        "Ageyevo",
        "Ageyevka"
    ],
    "wof:name":"Ageyevka",
    "wof:placetype":"locality"
},
  "geometry": {"coordinates":[35.24372,53.30666],"type":"Point"}
}