{
  "type": "Feature",
  "properties": {
    "gn:admin1_code":"71",
    "gn:asciiname":"Yurty",
    "gn:country_code":"RU",
    "gn:dem":180,
    "gn:feature_class":"P",
    "gn:feature_code":"PPL",
    "gn:name":"Yurty",
    "gn:population":0,
    "gn:timezone":"Asia/Yekaterinburg",
    "iso:country":"RU",
    "name:eng_x_preferred":[
        "Yurty"
    ],
    "name:nor_x_preferred":[
        "Jurty"
    ],
    "name:rus_x_preferred":[
        "\u042e\u0440\u0442\u044b"
    ],
    "wof:name":"Yurty",
    "wof:placetype":"locality"
},
  "geometry": {"coordinates":[59.6546,59.1559],"type":"Point"}
}