{
  "type": "Feature",
  "properties": {
    "gn:admin1_code":"11",
    "gn:asciiname":"Yekhe-Gorkhon",
    "gn:country_code":"RU",
    "gn:dem":840,
    "gn:feature_class":"P",
    "gn:feature_code":"PPL",
    "gn:name":"Yekhe-Gorkhon",
    "gn:population":0,
    "gn:timezone":"Asia/Irkutsk",
    "iso:country":"RU",
    "name:rus_x_preferred":[
        "\u0415\u0445\u044d-\u0413\u043e\u0440\u0445\u043e\u043d"
    ],
    "wof:name":"Yekhe-Gorkhon",
    "wof:placetype":"locality"
},
  "geometry": {"coordinates":[109.42888000000001,51.791],"type":"Point"}
}