{
  "type": "Feature",
  "properties": {
    "gn:admin1_code":"55",
    "gn:asciiname":"Novaya Rakityanka",
    "gn:country_code":"RU",
    "gn:dem":322,
    "gn:feature_class":"P",
    "gn:feature_code":"PPL",
    "gn:name":"Novaya Rakityanka",
    "gn:population":0,
    "gn:timezone":"Asia/Yekaterinburg",
    "iso:country":"RU",
    "name:rus_x_preferred":[
        "\u041d\u043e\u0432\u0430\u044f \u0420\u0430\u043a\u0438\u0442\u044f\u043d\u043a\u0430"
    ],
    "name:und_x_variant":[
        "Novoya Rakityanka",
        "Novaya Rakityanka",
        "\u041d\u043e\u0432\u0430\u044f \u0420\u0430\u043a\u0438\u0442\u044f\u043d\u043a\u0430"
    ],
    "wof:name":"Novaya Rakityanka",
    "wof:placetype":"locality"
},
  "geometry": {"coordinates":[57.6564,51.5224],"type":"Point"}
}