{
  "type": "Feature",
  "properties": {
    "gn:admin1_code":"67",
    "gn:asciiname":"Lopata",
    "gn:cc2":"RU",
    "gn:country_code":"RU",
    "gn:dem":44,
    "gn:feature_class":"P",
    "gn:feature_code":"PPL",
    "gn:name":"Lopata",
    "gn:population":0,
    "gn:timezone":"Europe/Saratov",
    "iso:country":"RU",
    "name:bos_x_preferred":[
        "Lopata"
    ],
    "name:bul_x_preferred":[
        "\u041b\u043e\u043f\u0430\u0442\u0430"
    ],
    "name:ceb_x_preferred":[
        "Lopata"
    ],
    "name:ita_x_preferred":[
        "Lopata"
    ],
    "name:nld_x_preferred":[
        "Lopata"
    ],
    "name:pol_x_preferred":[
        "Lopata"
    ],
    "name:ron_x_preferred":[
        "Lopata"
    ],
    "name:rus_x_preferred":[
        "\u041b\u043e\u043f\u0430\u0442\u0430"
    ],
    "name:slv_x_preferred":[
        "Lopata"
    ],
    "name:ukr_x_preferred":[
        "\u041b\u043e\u043f\u0430\u0442\u0430"
    ],
    "name:und_x_variant":[
        "Lopama",
        "Lopata",
        "\u041b\u043e\u043f\u0430\u0442\u0430"
    ],
    "wof:name":"Lopata",
    "wof:placetype":"locality"
},
  "geometry": {"coordinates":[46.48333,52.11667],"type":"Point"}
}