{
  "type": "Feature",
  "properties": {
    "gn:admin1_code":"69.0",
    "gn:asciiname":"Dudino",
    "gn:country_code":"RU",
    "gn:dem":213,
    "gn:feature_class":"P",
    "gn:feature_code":"PPL",
    "gn:name":"Dudino",
    "gn:population":0,
    "gn:timezone":"Europe/Moscow",
    "iso:country":"RU",
    "name:rus_x_preferred":[
        "\u0414\u0443\u0434\u0438\u043d\u043e"
    ],
    "wof:name":"Dudino",
    "wof:placetype":"locality"
},
  "geometry": {"coordinates":[32.08333,54.61666999999999],"type":"Point"}
}