{
  "type": "Feature",
  "properties": {
    "gn:admin1_code":"16",
    "gn:asciiname":"Kalugino",
    "gn:country_code":"RU",
    "gn:dem":118,
    "gn:feature_class":"P",
    "gn:feature_code":"PPL",
    "gn:name":"Kalugino",
    "gn:population":0,
    "gn:timezone":"Europe/Moscow",
    "iso:country":"RU",
    "name:rus_x_preferred":[
        "\u041a\u0430\u043b\u0443\u0433\u0438\u043d\u043e"
    ],
    "wof:name":"Kalugino",
    "wof:placetype":"locality"
},
  "geometry": {"coordinates":[47.86024000000001,55.83635],"type":"Point"}
}