{
  "type": "Feature",
  "properties": {
    "gn:admin1_code":"45.0",
    "gn:asciiname":"Zavodskoy",
    "gn:country_code":"RU",
    "gn:dem":114,
    "gn:feature_class":"P",
    "gn:feature_code":"PPL",
    "gn:name":"Zavodskoy",
    "gn:population":0,
    "gn:timezone":"Europe/Moscow",
    "iso:country":"RU",
    "name:rus_x_preferred":[
        "\u0417\u0430\u0432\u043e\u0434\u0441\u043a\u043e\u0439"
    ],
    "wof:name":"Zavodskoy",
    "wof:placetype":"locality"
},
  "geometry": {"coordinates":[49.67854000000001,56.77875],"type":"Point"}
}