{
  "type": "Feature",
  "properties": {
    "gn:admin1_code":"60",
    "gn:asciiname":"Shkurly",
    "gn:country_code":"RU",
    "gn:dem":76,
    "gn:feature_class":"P",
    "gn:feature_code":"PPL",
    "gn:name":"Shkurly",
    "gn:population":0,
    "gn:timezone":"Europe/Moscow",
    "iso:country":"RU",
    "name:rus_x_preferred":[
        "\u0428\u043a\u0443\u0440\u043b\u044b"
    ],
    "wof:name":"Shkurly",
    "wof:placetype":"locality"
},
  "geometry": {"coordinates":[28.07036,57.00021],"type":"Point"}
}