{
  "type": "Feature",
  "properties": {
    "gn:admin1_code":"73",
    "gn:asciiname":"Tarkhan",
    "gn:country_code":"RU",
    "gn:dem":84,
    "gn:feature_class":"P",
    "gn:feature_code":"PPL",
    "gn:name":"Tarkhan",
    "gn:population":0,
    "gn:timezone":"Europe/Moscow",
    "iso:country":"RU",
    "name:rus_x_preferred":[
        "\u0422\u0430\u0440\u0445\u0430\u043d"
    ],
    "wof:name":"Tarkhan",
    "wof:placetype":"locality"
},
  "geometry": {"coordinates":[50.3856,56.5104],"type":"Point"}
}