{
  "type": "Feature",
  "properties": {
    "gn:admin1_code":"37",
    "gn:asciiname":"Yakutino",
    "gn:country_code":"RU",
    "gn:dem":136,
    "gn:feature_class":"P",
    "gn:feature_code":"PPL",
    "gn:name":"Yakutino",
    "gn:population":0,
    "gn:timezone":"Europe/Moscow",
    "iso:country":"RU",
    "name:rus_x_preferred":[
        "\u042f\u043a\u0443\u0442\u0438\u043d\u043e"
    ],
    "name:und_x_variant":[
        "\u042f\u043a\u0443\u0442\u0438\u043d\u043e"
    ],
    "wof:name":"Yakutino",
    "wof:placetype":"locality"
},
  "geometry": {"coordinates":[45.831,58.1658],"type":"Point"}
}