{
  "type": "Feature",
  "properties": {
    "gn:admin1_code":"6.0",
    "gn:asciiname":"Burtsevskaya",
    "gn:country_code":"RU",
    "gn:dem":44,
    "gn:feature_class":"P",
    "gn:feature_code":"PPL",
    "gn:name":"Burtsevskaya",
    "gn:population":0,
    "gn:timezone":"Europe/Moscow",
    "iso:country":"RU",
    "name:eng_x_preferred":[
        "Burtsevskaya"
    ],
    "name:nor_x_preferred":[
        "Burtsevskaja"
    ],
    "name:rus_x_preferred":[
        "\u0411\u0443\u0440\u0446\u0435\u0432\u0441\u043a\u0430\u044f"
    ],
    "name:und_x_variant":[
        "\u0411\u0443\u0440\u0446\u0435\u0432\u0441\u043a\u0430\u044f",
        "Burtsevskaya"
    ],
    "wof:name":"Burtsevskaya",
    "wof:placetype":"locality"
},
  "geometry": {"coordinates":[44.2788,62.3577],"type":"Point"}
}