{
  "type": "Feature",
  "properties": {
    "gn:admin1_code":"77",
    "gn:asciiname":"Podgor'ye",
    "gn:country_code":"RU",
    "gn:dem":232,
    "gn:feature_class":"P",
    "gn:feature_code":"PPL",
    "gn:name":"Podgor\u2019ye",
    "gn:population":0,
    "gn:timezone":"Europe/Moscow",
    "iso:country":"RU",
    "name:rus_x_preferred":[
        "\u041f\u043e\u0434\u0433\u043e\u0440\u044c\u0435"
    ],
    "name:und_x_variant":[
        "Podgor\u2019ye"
    ],
    "wof:name":"Podgor'ye",
    "wof:placetype":"locality"
},
  "geometry": {"coordinates":[32.74232,57.28474],"type":"Point"}
}