{
  "type": "Feature",
  "properties": {
    "gn:admin1_code":"88",
    "gn:asciiname":"Tarkhovo",
    "gn:country_code":"RU",
    "gn:dem":166,
    "gn:feature_class":"P",
    "gn:feature_code":"PPL",
    "gn:name":"Tarkhovo",
    "gn:population":0,
    "gn:timezone":"Europe/Moscow",
    "iso:country":"RU",
    "name:rus_x_preferred":[
        "\u0422\u0430\u0440\u0445\u043e\u0432\u043e"
    ],
    "wof:name":"Tarkhovo",
    "wof:placetype":"locality"
},
  "geometry": {"coordinates":[39.0285,57.1438],"type":"Point"}
}