{
  "type": "Feature",
  "properties": {
    "gn:admin1_code":"21",
    "gn:asciiname":"Lysnovo",
    "gn:country_code":"RU",
    "gn:dem":130,
    "gn:feature_class":"P",
    "gn:feature_code":"PPL",
    "gn:name":"Lysnovo",
    "gn:population":0,
    "gn:timezone":"Europe/Moscow",
    "iso:country":"RU",
    "name:rus_x_preferred":[
        "\u041b\u044b\u0441\u043d\u043e\u0432\u043e"
    ],
    "wof:name":"Lysnovo",
    "wof:placetype":"locality"
},
  "geometry": {"coordinates":[40.92047,56.88943],"type":"Point"}
}