{
  "type": "Feature",
  "properties": {
    "gn:admin1_code":"57.0",
    "gn:asciiname":"Chertaley",
    "gn:country_code":"RU",
    "gn:dem":235,
    "gn:feature_class":"P",
    "gn:feature_code":"PPL",
    "gn:name":"Chertaley",
    "gn:population":0,
    "gn:timezone":"Europe/Moscow",
    "iso:country":"RU",
    "name:rus_x_preferred":[
        "\u0427\u0435\u0440\u0442\u0430\u043b\u0435\u0439"
    ],
    "wof:name":"Chertaley",
    "wof:placetype":"locality"
},
  "geometry": {"coordinates":[46.74892,52.698],"type":"Point"}
}