{
  "type": "Feature",
  "properties": {
    "gn:admin1_code":"42",
    "gn:asciiname":"Mekhbaza",
    "gn:country_code":"RU",
    "gn:dem":81,
    "gn:feature_class":"P",
    "gn:feature_code":"PPL",
    "gn:name":"Mekhbaza",
    "gn:population":0,
    "gn:timezone":"Europe/Moscow",
    "iso:country":"RU",
    "name:eng_x_preferred":[
        "Mekhbaza"
    ],
    "name:nor_x_preferred":[
        "Mekhbaza"
    ],
    "name:rus_x_preferred":[
        "\u041c\u0435\u0445\u0431\u0430\u0437\u0430"
    ],
    "name:und_x_variant":[
        "\u041c\u0435\u0445\u0431\u0430\u0437\u0430",
        "Mekhbaza"
    ],
    "wof:name":"Mekhbaza",
    "wof:placetype":"locality"
},
  "geometry": {"coordinates":[33.88516,60.00156],"type":"Point"}
}