{
  "type": "Feature",
  "properties": {
    "gn:admin1_code":"13",
    "gn:asciiname":"Novoakhunovo",
    "gn:country_code":"RU",
    "gn:dem":413,
    "gn:feature_class":"P",
    "gn:feature_code":"PPL",
    "gn:name":"Novoakhunovo",
    "gn:population":0,
    "gn:timezone":"Asia/Yekaterinburg",
    "iso:country":"RU",
    "name:eng_x_preferred":[
        "Novoakhunovo"
    ],
    "name:nor_x_preferred":[
        "Novoakhunovo"
    ],
    "name:rus_x_preferred":[
        "\u041d\u043e\u0432\u043e\u0430\u0445\u0443\u043d\u043e\u0432\u043e"
    ],
    "wof:name":"Novoakhunovo",
    "wof:placetype":"locality"
},
  "geometry": {"coordinates":[59.26444,53.95083],"type":"Point"}
}