{
  "type": "Feature",
  "properties": {
    "gn:admin1_code":"25",
    "gn:asciiname":"Peski",
    "gn:country_code":"RU",
    "gn:dem":175,
    "gn:feature_class":"P",
    "gn:feature_code":"PPL",
    "gn:name":"Peski",
    "gn:population":0,
    "gn:timezone":"Europe/Moscow",
    "iso:country":"RU",
    "name:bel_x_preferred":[
        "\u041f\u044f\u0441\u043a\u0456"
    ],
    "name:est_x_preferred":[
        "Peski"
    ],
    "name:fin_x_preferred":[
        "Peski"
    ],
    "name:hye_x_preferred":[
        "\u054a\u0565\u057d\u056f\u056b"
    ],
    "name:rus_x_preferred":[
        "\u041f\u0435\u0441\u043a\u0438"
    ],
    "wof:name":"Peski",
    "wof:placetype":"locality"
},
  "geometry": {"coordinates":[36.622,54.41748000000001],"type":"Point"}
}