{
  "type": "Feature",
  "properties": {
    "gn:admin1_code":"76",
    "gn:asciiname":"Yasnopol'ye",
    "gn:country_code":"RU",
    "gn:dem":265,
    "gn:feature_class":"P",
    "gn:feature_code":"PPL",
    "gn:name":"Yasnopol\u2019ye",
    "gn:population":0,
    "gn:timezone":"Europe/Moscow",
    "iso:country":"RU",
    "wof:name":"Yasnopol'ye",
    "wof:placetype":"locality"
},
  "geometry": {"coordinates":[37.58222,53.44556],"type":"Point"}
}