{
  "type": "Feature",
  "properties": {
    "gn:admin1_code":"83.0",
    "gn:asciiname":"Trukhachevo",
    "gn:country_code":"RU",
    "gn:dem":110,
    "gn:feature_class":"P",
    "gn:feature_code":"PPL",
    "gn:name":"Trukhach\u00ebvo",
    "gn:population":0,
    "gn:timezone":"Europe/Moscow",
    "iso:country":"RU",
    "name:rus_x_preferred":[
        "\u0422\u0440\u0443\u0445\u0430\u0447\u0451\u0432\u043e"
    ],
    "name:und_x_variant":[
        "Trukhach\u00ebvo"
    ],
    "wof:name":"Trukhachevo",
    "wof:placetype":"locality"
},
  "geometry": {"coordinates":[40.78569,56.10028000000001],"type":"Point"}
}