{
  "type": "Feature",
  "properties": {
    "gn:admin1_code":"61",
    "gn:asciiname":"Antipovskiy",
    "gn:country_code":"RU",
    "gn:dem":107,
    "gn:feature_class":"P",
    "gn:feature_code":"PPL",
    "gn:name":"Antipovskiy",
    "gn:population":0,
    "gn:timezone":"Europe/Moscow",
    "iso:country":"RU",
    "name:nor_x_preferred":[
        "Antipovskij"
    ],
    "name:rus_x_preferred":[
        "\u0410\u043d\u0442\u0438\u043f\u043e\u0432\u0441\u043a\u0438\u0439"
    ],
    "name:und_x_variant":[
        "Khutor Antipovskiy",
        "Verkhniy Antipovskiy",
        "Antikovskiy",
        "Verkhne-Antipovskiy",
        "Antipovskiy"
    ],
    "wof:name":"Antipovskiy",
    "wof:placetype":"locality"
},
  "geometry": {"coordinates":[41.55021,49.72318],"type":"Point"}
}