{
  "type": "Feature",
  "properties": {
    "gn:admin1_code":"85",
    "gn:asciiname":"Sinitsyno",
    "gn:country_code":"RU",
    "gn:dem":157,
    "gn:feature_class":"P",
    "gn:feature_code":"PPL",
    "gn:name":"Sinitsyno",
    "gn:population":0,
    "gn:timezone":"Europe/Moscow",
    "iso:country":"RU",
    "name:rus_x_preferred":[
        "\u0421\u0438\u043d\u0438\u0446\u044b\u043d\u043e"
    ],
    "name:und_x_variant":[
        "\u0421\u0438\u043d\u0438\u0446\u044b\u043d\u043e"
    ],
    "wof:name":"Sinitsyno",
    "wof:placetype":"locality"
},
  "geometry": {"coordinates":[42.57727,59.44999],"type":"Point"}
}