{
  "type": "Feature",
  "properties": {
    "gn:admin1_code":"60",
    "gn:asciiname":"Panikli",
    "gn:country_code":"RU",
    "gn:dem":179,
    "gn:feature_class":"P",
    "gn:feature_code":"PPL",
    "gn:name":"Panikli",
    "gn:population":0,
    "gn:timezone":"Europe/Moscow",
    "iso:country":"RU",
    "name:rus_x_preferred":[
        "\u041f\u0430\u043d\u0438\u043a\u043b\u0438"
    ],
    "name:und_x_variant":[
        "\u041f\u0430\u043d\u0438\u043a\u043b\u0438"
    ],
    "wof:name":"Panikli",
    "wof:placetype":"locality"
},
  "geometry": {"coordinates":[31.13333,56.03333000000001],"type":"Point"}
}