{
  "type": "Feature",
  "properties": {
    "gn:admin1_code":"43",
    "gn:asciiname":"Khitrovo",
    "gn:country_code":"RU",
    "gn:dem":218,
    "gn:feature_class":"P",
    "gn:feature_code":"PPL",
    "gn:name":"Khitrovo",
    "gn:population":0,
    "gn:timezone":"Europe/Moscow",
    "iso:country":"RU",
    "name:rus_x_preferred":[
        "\u0425\u0438\u0442\u0440\u043e\u0432\u043e"
    ],
    "wof:name":"Khitrovo",
    "wof:placetype":"locality"
},
  "geometry": {"coordinates":[38.60274,52.46394],"type":"Point"}
}