{
  "type": "Feature",
  "properties": {
    "gn:admin1_code":"60",
    "gn:asciiname":"Lopatkino",
    "gn:country_code":"RU",
    "gn:dem":154,
    "gn:feature_class":"P",
    "gn:feature_code":"PPL",
    "gn:name":"Lopatkino",
    "gn:population":0,
    "gn:timezone":"Europe/Moscow",
    "iso:country":"RU",
    "name:rus_x_preferred":[
        "\u041b\u043e\u043f\u0430\u0442\u043a\u0438\u043d\u043e"
    ],
    "wof:name":"Lopatkino",
    "wof:placetype":"locality"
},
  "geometry": {"coordinates":[30.6343,56.0274],"type":"Point"}
}