{
  "type": "Feature",
  "properties": {
    "gn:admin1_code":"52",
    "gn:asciiname":"Gorshkovitsy",
    "gn:country_code":"RU",
    "gn:dem":74,
    "gn:feature_class":"P",
    "gn:feature_code":"PPL",
    "gn:name":"Gorshkovitsy",
    "gn:population":0,
    "gn:timezone":"Europe/Moscow",
    "iso:country":"RU",
    "name:rus_x_preferred":[
        "\u0413\u043e\u0440\u0448\u043a\u043e\u0432\u0438\u0446\u044b"
    ],
    "name:und_x_variant":[
        "Gorshovitsy",
        "Gorshkovitsy"
    ],
    "wof:name":"Gorshkovitsy",
    "wof:placetype":"locality"
},
  "geometry": {"coordinates":[32.55021,57.75100000000001],"type":"Point"}
}