{
  "type": "Feature",
  "properties": {
    "gn:admin1_code":"13",
    "gn:asciiname":"Itkul'",
    "gn:country_code":"RU",
    "gn:dem":442,
    "gn:feature_class":"P",
    "gn:feature_code":"PPL",
    "gn:name":"Itkul\u2019",
    "gn:population":0,
    "gn:timezone":"Asia/Yekaterinburg",
    "iso:country":"RU",
    "name:rus_x_preferred":[
        "\u0418\u0442\u043a\u0443\u043b\u044c"
    ],
    "name:und_x_variant":[
        "Itkul\u2019",
        "\u0418\u0442\u043a\u0443\u043b\u044c"
    ],
    "wof:name":"Itkul'",
    "wof:placetype":"locality"
},
  "geometry": {"coordinates":[60.3307,56.049],"type":"Point"}
}