{
  "type": "Feature",
  "properties": {
    "gn:admin1_code":"85",
    "gn:asciiname":"Filimonovo",
    "gn:country_code":"RU",
    "gn:dem":145,
    "gn:feature_class":"P",
    "gn:feature_code":"PPL",
    "gn:name":"Filimonovo",
    "gn:population":0,
    "gn:timezone":"Europe/Moscow",
    "iso:country":"RU",
    "name:rus_x_preferred":[
        "\u0424\u0438\u043b\u0438\u043c\u043e\u043d\u043e\u0432\u043e"
    ],
    "name:und_x_variant":[
        "\u0424\u0438\u043b\u0438\u043c\u043e\u043d\u043e\u0432\u043e"
    ],
    "wof:name":"Filimonovo",
    "wof:placetype":"locality"
},
  "geometry": {"coordinates":[38.1988,58.9335],"type":"Point"}
}