{
  "type": "Feature",
  "properties": {
    "gn:admin1_code":"52",
    "gn:asciiname":"Zadnyaya",
    "gn:country_code":"RU",
    "gn:dem":57,
    "gn:feature_class":"P",
    "gn:feature_code":"PPL",
    "gn:name":"Zadnyaya",
    "gn:population":0,
    "gn:timezone":"Europe/Moscow",
    "iso:country":"RU",
    "name:eng_x_preferred":[
        "Zadnyaya"
    ],
    "name:nor_x_preferred":[
        "Zadnjaja"
    ],
    "name:rus_x_preferred":[
        "\u0417\u0430\u0434\u043d\u044f\u044f"
    ],
    "name:und_x_variant":[
        "Voskhod",
        "Zadnyaya"
    ],
    "wof:name":"Zadnyaya",
    "wof:placetype":"locality"
},
  "geometry": {"coordinates":[32.6007,57.9557],"type":"Point"}
}