{
  "type": "Feature",
  "properties": {
    "gn:admin1_code":"37",
    "gn:asciiname":"Slepnikha",
    "gn:country_code":"RU",
    "gn:dem":133,
    "gn:feature_class":"P",
    "gn:feature_code":"PPL",
    "gn:name":"Slepnikha",
    "gn:population":0,
    "gn:timezone":"Europe/Moscow",
    "iso:country":"RU",
    "name:rus_x_preferred":[
        "\u0421\u043b\u0435\u0440\u043d\u0438\u0445\u0430"
    ],
    "name:und_x_variant":[
        "\u0421\u043b\u0435\u0440\u043d\u0438\u0445\u0430"
    ],
    "wof:name":"Slepnikha",
    "wof:placetype":"locality"
},
  "geometry": {"coordinates":[45.7835,58.20399999999999],"type":"Point"}
}