{
  "type": "Feature",
  "properties": {
    "gn:admin1_code":"83.0",
    "gn:asciiname":"Melkishevo",
    "gn:country_code":"RU",
    "gn:dem":89,
    "gn:feature_class":"P",
    "gn:feature_code":"PPL",
    "gn:name":"Melkishevo",
    "gn:population":0,
    "gn:timezone":"Europe/Moscow",
    "iso:country":"RU",
    "name:nor_x_preferred":[
        "Melkisjevo"
    ],
    "name:rus_x_preferred":[
        "\u041c\u0435\u043b\u043a\u0438\u0448\u0435\u0432\u043e"
    ],
    "wof:name":"Melkishevo",
    "wof:placetype":"locality"
},
  "geometry": {"coordinates":[42.50229,56.07601],"type":"Point"}
}