{
  "type": "Feature",
  "properties": {
    "gn:admin1_code":"77.0",
    "gn:asciiname":"Fedortsevo",
    "gn:country_code":"RU",
    "gn:dem":137,
    "gn:feature_class":"P",
    "gn:feature_code":"PPL",
    "gn:name":"F\u00ebdortsevo",
    "gn:population":0,
    "gn:timezone":"Europe/Moscow",
    "iso:country":"RU",
    "name:eng_x_preferred":[
        "F\u00ebdortsevo"
    ],
    "name:nor_x_preferred":[
        "Fedortsevo"
    ],
    "name:rus_x_preferred":[
        "\u0424\u0435\u0434\u043e\u0440\u0446\u0435\u0432\u043e"
    ],
    "name:rus_x_variant":[
        "\u0424\u0451\u0434\u043e\u0440\u0446\u0435\u0432\u043e"
    ],
    "name:und_x_variant":[
        "F\u00ebdortsovo",
        "F\u00ebdortsevo",
        "\u0424\u0451\u0434\u043e\u0440\u0446\u0435\u0432\u043e"
    ],
    "wof:name":"Fedortsevo",
    "wof:placetype":"locality"
},
  "geometry": {"coordinates":[36.23274,57.93908],"type":"Point"}
}