{
  "type": "Feature",
  "properties": {
    "gn:admin1_code":"81",
    "gn:asciiname":"Sof'ino",
    "gn:country_code":"RU",
    "gn:dem":171,
    "gn:feature_class":"P",
    "gn:feature_code":"PPL",
    "gn:name":"Sof\u2019ino",
    "gn:population":0,
    "gn:timezone":"Europe/Ulyanovsk",
    "iso:country":"RU",
    "name:eng_x_preferred":[
        "Sof'ino"
    ],
    "name:nor_x_preferred":[
        "Sofino"
    ],
    "name:rus_x_preferred":[
        "\u0421\u043e\u0444\u044c\u0438\u043d\u043e"
    ],
    "name:und_x_variant":[
        "Sof\u2019ino"
    ],
    "wof:name":"Sof'ino",
    "wof:placetype":"locality"
},
  "geometry": {"coordinates":[48.04083,52.93306],"type":"Point"}
}