{
  "type": "Feature",
  "properties": {
    "gn:admin1_code":"85",
    "gn:asciiname":"Skomorokhovo",
    "gn:country_code":"RU",
    "gn:dem":155,
    "gn:feature_class":"P",
    "gn:feature_code":"PPL",
    "gn:name":"Skomorokhovo",
    "gn:population":0,
    "gn:timezone":"Europe/Moscow",
    "iso:country":"RU",
    "name:rus_x_preferred":[
        "\u0421\u043a\u043e\u043c\u043e\u0440\u043e\u0445\u043e\u0432\u043e"
    ],
    "name:und_x_variant":[
        "\u0421\u043a\u043e\u043c\u043e\u0440\u043e\u0445\u043e\u0432\u043e"
    ],
    "wof:name":"Skomorokhovo",
    "wof:placetype":"locality"
},
  "geometry": {"coordinates":[41.23192,59.58851],"type":"Point"}
}