{
  "type": "Feature",
  "properties": {
    "gn:admin1_code":"77",
    "gn:asciiname":"Teben'ki",
    "gn:country_code":"RU",
    "gn:dem":163,
    "gn:feature_class":"P",
    "gn:feature_code":"PPL",
    "gn:name":"Teben\u2019ki",
    "gn:population":0,
    "gn:timezone":"Europe/Moscow",
    "iso:country":"RU",
    "name:rus_x_preferred":[
        "\u0422\u0435\u0431\u0435\u043d\u044c\u043a\u0438"
    ],
    "name:und_x_variant":[
        "Teben\u2019ki"
    ],
    "wof:name":"Teben'ki",
    "wof:placetype":"locality"
},
  "geometry": {"coordinates":[37.1233,58.4685],"type":"Point"}
}