{
  "type": "Feature",
  "properties": {
    "gn:admin1_code":"34",
    "gn:asciiname":"Nyuchpas",
    "gn:country_code":"RU",
    "gn:dem":148,
    "gn:feature_class":"P",
    "gn:feature_code":"PPL",
    "gn:name":"Nyuchpas",
    "gn:population":0,
    "gn:timezone":"Europe/Moscow",
    "iso:country":"RU",
    "name:eng_x_preferred":[
        "Nyuchpas"
    ],
    "name:nor_x_preferred":[
        "Njutsjpas"
    ],
    "name:rus_x_preferred":[
        "\u041d\u044e\u0447\u043f\u0430\u0441"
    ],
    "wof:name":"Nyuchpas",
    "wof:placetype":"locality"
},
  "geometry": {"coordinates":[51.47972,60.67886],"type":"Point"}
}