{
  "type": "Feature",
  "properties": {
    "gn:admin1_code":"29.0",
    "gn:asciiname":"Novosafonovskiy",
    "gn:country_code":"RU",
    "gn:dem":391,
    "gn:feature_class":"P",
    "gn:feature_code":"PPL",
    "gn:name":"Novosafonovskiy",
    "gn:population":0,
    "gn:timezone":"Asia/Novokuznetsk",
    "iso:country":"RU",
    "name:rus_x_preferred":[
        "\u041d\u043e\u0432\u043e\u0441\u0430\u0444\u043e\u043d\u043e\u0432\u0441\u043a\u0438\u0439"
    ],
    "wof:name":"Novosafonovskiy",
    "wof:placetype":"locality"
},
  "geometry": {"coordinates":[86.5996,53.8432],"type":"Point"}
}