{
  "type": "Feature",
  "properties": {
    "gn:admin1_code":"33",
    "gn:asciiname":"Bykova Gorka",
    "gn:country_code":"RU",
    "gn:dem":204,
    "gn:feature_class":"P",
    "gn:feature_code":"PPL",
    "gn:name":"Bykova Gorka",
    "gn:population":0,
    "gn:timezone":"Europe/Kirov",
    "iso:country":"RU",
    "name:rus_x_preferred":[
        "\u0411\u044b\u043a\u043e\u0432\u0430 \u0413\u043e\u0440\u043a\u0430"
    ],
    "name:und_x_variant":[
        "Vas\u2019kovo",
        "Bykova Gorka"
    ],
    "wof:name":"Bykova Gorka",
    "wof:placetype":"locality"
},
  "geometry": {"coordinates":[50.67611,58.97194],"type":"Point"}
}