{
  "type": "Feature",
  "properties": {
    "gn:admin1_code":"33.0",
    "gn:asciiname":"Zabaydug",
    "gn:country_code":"RU",
    "gn:dem":181,
    "gn:feature_class":"P",
    "gn:feature_code":"PPL",
    "gn:name":"Zabaydug",
    "gn:population":0,
    "gn:timezone":"Europe/Kirov",
    "iso:country":"RU",
    "name:rus_x_preferred":[
        "\u0417\u0430\u0431\u0430\u0439\u0434\u0443\u0433"
    ],
    "wof:name":"Zabaydug",
    "wof:placetype":"locality"
},
  "geometry": {"coordinates":[48.76303,58.75678000000001],"type":"Point"}
}