{
  "type": "Feature",
  "properties": {
    "gn:admin1_code":"51",
    "gn:asciiname":"Lapshikha",
    "gn:country_code":"RU",
    "gn:dem":139,
    "gn:feature_class":"P",
    "gn:feature_code":"PPL",
    "gn:name":"Lapshikha",
    "gn:population":0,
    "gn:timezone":"Europe/Moscow",
    "iso:country":"RU",
    "name:rus_x_preferred":[
        "\u041b\u0430\u043f\u0448\u0438\u0445\u0430"
    ],
    "wof:name":"Lapshikha",
    "wof:placetype":"locality"
},
  "geometry": {"coordinates":[44.00209,55.88407],"type":"Point"}
}