{
  "type": "Feature",
  "properties": {
    "gn:admin1_code":"54",
    "gn:asciiname":"Mel'nichnoye",
    "gn:country_code":"RU",
    "gn:dem":87,
    "gn:feature_class":"P",
    "gn:feature_code":"PPL",
    "gn:name":"Mel\u2019nichnoye",
    "gn:population":0,
    "gn:timezone":"Asia/Omsk",
    "iso:country":"RU",
    "name:eng_x_preferred":[
        "Mel'nichnoye"
    ],
    "name:nor_x_preferred":[
        "Melnitsjnoje"
    ],
    "name:rus_x_preferred":[
        "\u041c\u0435\u043b\u044c\u043d\u0438\u0447\u043d\u043e\u0435"
    ],
    "name:und_x_variant":[
        "Mel\u2019nichnyy",
        "Mel\u2019nichnaya",
        "Mel\u2019nichnoye"
    ],
    "wof:name":"Mel'nichnoye",
    "wof:placetype":"locality"
},
  "geometry": {"coordinates":[73.04089,55.02388000000001],"type":"Point"}
}