{
  "type": "Feature",
  "properties": {
    "gn:admin1_code":"17.0",
    "gn:asciiname":"Dzhilikhur",
    "gn:country_code":"RU",
    "gn:dem":1927,
    "gn:feature_class":"P",
    "gn:feature_code":"PPL",
    "gn:name":"Dzhilikhur",
    "gn:population":0,
    "gn:timezone":"Europe/Moscow",
    "iso:country":"RU",
    "name:rus_x_preferred":[
        "\u0414\u0436\u0438\u043b\u0438\u0445\u0443\u0440"
    ],
    "wof:name":"Dzhilikhur",
    "wof:placetype":"locality"
},
  "geometry": {"coordinates":[47.26752000000001,41.65748],"type":"Point"}
}