{
  "type": "Feature",
  "properties": {
    "gn:admin1_code":"90.0",
    "gn:asciiname":"Verkhnyaya Tulva",
    "gn:country_code":"RU",
    "gn:dem":208,
    "gn:feature_class":"P",
    "gn:feature_code":"PPL",
    "gn:name":"Verkhnyaya Tulva",
    "gn:population":0,
    "gn:timezone":"Asia/Yekaterinburg",
    "iso:country":"RU",
    "name:rus_x_preferred":[
        "\u0412\u0435\u0440\u0445\u043d\u044f\u044f \u0422\u0443\u043b\u0432\u0430"
    ],
    "wof:name":"Verkhnyaya Tulva",
    "wof:placetype":"locality"
},
  "geometry": {"coordinates":[56.20927,56.80282],"type":"Point"}
}