{
  "type": "Feature",
  "properties": {
    "gn:admin1_code":"69",
    "gn:asciiname":"Kuvshinovo",
    "gn:country_code":"RU",
    "gn:dem":232,
    "gn:feature_class":"P",
    "gn:feature_code":"PPL",
    "gn:name":"Kuvshinovo",
    "gn:population":0,
    "gn:timezone":"Europe/Moscow",
    "iso:country":"RU",
    "name:rus_x_preferred":[
        "\u041a\u0443\u0432\u0448\u0438\u043d\u043e\u0432\u043e"
    ],
    "name:und_x_variant":[
        "Kuvshinove",
        "Kuvshinovo"
    ],
    "wof:name":"Kuvshinovo",
    "wof:placetype":"locality"
},
  "geometry": {"coordinates":[31.96376,54.8682],"type":"Point"}
}