{
  "type": "Feature",
  "properties": {
    "gn:admin1_code":"10",
    "gn:asciiname":"Drugovshchina",
    "gn:country_code":"RU",
    "gn:dem":176,
    "gn:feature_class":"P",
    "gn:feature_code":"PPL",
    "gn:name":"Drugovshchina",
    "gn:population":0,
    "gn:timezone":"Europe/Moscow",
    "iso:country":"RU",
    "name:rus_x_preferred":[
        "\u0414\u0440\u0443\u0433\u043e\u0432\u0449\u0438\u043d\u0430"
    ],
    "wof:name":"Drugovshchina",
    "wof:placetype":"locality"
},
  "geometry": {"coordinates":[32.7648,52.5468],"type":"Point"}
}