{
  "type": "Feature",
  "properties": {
    "gn:admin1_code":"76",
    "gn:asciiname":"Zybinka",
    "gn:country_code":"RU",
    "gn:dem":275,
    "gn:feature_class":"P",
    "gn:feature_code":"PPL",
    "gn:name":"Zybinka",
    "gn:population":0,
    "gn:timezone":"Europe/Moscow",
    "iso:country":"RU",
    "wof:name":"Zybinka",
    "wof:placetype":"locality"
},
  "geometry": {"coordinates":[37.52694,53.40416999999999],"type":"Point"}
}