{
  "type": "Feature",
  "properties": {
    "gn:admin1_code":"73",
    "gn:asciiname":"Karmaly",
    "gn:country_code":"RU",
    "gn:dem":55,
    "gn:feature_class":"P",
    "gn:feature_code":"PPL",
    "gn:name":"Karmaly",
    "gn:population":0,
    "gn:timezone":"Europe/Moscow",
    "iso:country":"RU",
    "name:eng_x_preferred":[
        "Karmaly"
    ],
    "name:nor_x_preferred":[
        "Karmaly"
    ],
    "name:rus_x_preferred":[
        "\u041a\u0430\u0440\u043c\u0430\u043b\u044b"
    ],
    "name:und_x_variant":[
        "\u041a\u0430\u0440\u043c\u0430\u043b\u044b",
        "Karmaly"
    ],
    "wof:name":"Karmaly",
    "wof:placetype":"locality"
},
  "geometry": {"coordinates":[51.17321,55.30376999999999],"type":"Point"}
}