{
  "type": "Feature",
  "properties": {
    "gn:admin1_code":"05",
    "gn:asciiname":"Mongoli",
    "gn:country_code":"RU",
    "gn:dem":574,
    "gn:feature_class":"P",
    "gn:feature_code":"PPL",
    "gn:name":"Mongoli",
    "gn:population":0,
    "gn:timezone":"Asia/Yakutsk",
    "iso:country":"RU",
    "name:rus_x_preferred":[
        "\u041c\u043e\u043d\u0433\u043e\u043b\u0438"
    ],
    "name:und_x_variant":[
        "\u041c\u043e\u043d\u0433\u043e\u043b\u0438"
    ],
    "wof:name":"Mongoli",
    "wof:placetype":"locality"
},
  "geometry": {"coordinates":[123.39375,54.3842],"type":"Point"}
}