{
  "type": "Feature",
  "properties": {
    "gn:admin1_code":"32",
    "gn:asciiname":"Katesovo Yugan",
    "gn:country_code":"RU",
    "gn:dem":58,
    "gn:feature_class":"P",
    "gn:feature_code":"PPL",
    "gn:name":"Katesovo Yugan",
    "gn:population":0,
    "gn:timezone":"Asia/Yekaterinburg",
    "iso:country":"RU",
    "name:rus_x_preferred":[
        "\u041a\u0430\u0442\u0435\u0441\u043e\u0432\u043e \u042e\u0433\u0430\u043d"
    ],
    "name:und_x_variant":[
        "\u041a\u0430\u0442\u0435\u0441\u043e\u0432\u043e \u042e\u0433\u0430\u043d"
    ],
    "wof:name":"Katesovo Yugan",
    "wof:placetype":"locality"
},
  "geometry": {"coordinates":[74.3404,60.9905],"type":"Point"}
}