{
  "type": "Feature",
  "properties": {
    "gn:admin1_code":"9",
    "gn:asciiname":"Klinovets",
    "gn:country_code":"RU",
    "gn:dem":219,
    "gn:feature_class":"P",
    "gn:feature_code":"PPL",
    "gn:name":"Klinovets",
    "gn:population":0,
    "gn:timezone":"Europe/Moscow",
    "iso:country":"RU",
    "name:rus_x_preferred":[
        "\u041a\u043b\u0438\u043d\u043e\u0432\u0435\u0446"
    ],
    "name:und_x_variant":[
        "Klenovets",
        "Klinovets",
        "Klinovets Pervyy"
    ],
    "wof:name":"Klinovets",
    "wof:placetype":"locality"
},
  "geometry": {"coordinates":[37.28478,50.78745],"type":"Point"}
}