{
  "type": "Feature",
  "properties": {
    "gn:admin1_code":"64.0",
    "gn:asciiname":"Bambuchek",
    "gn:country_code":"RU",
    "gn:dem":107,
    "gn:feature_class":"P",
    "gn:feature_code":"PPL",
    "gn:name":"Bambuchek",
    "gn:population":0,
    "gn:timezone":"Asia/Sakhalin",
    "iso:country":"RU",
    "wof:name":"Bambuchek",
    "wof:placetype":"locality"
},
  "geometry": {"coordinates":[142.27666000000005,46.93867],"type":"Point"}
}