{
  "type": "Feature",
  "properties": {
    "gn:admin1_code":"50",
    "gn:asciiname":"Karatayka",
    "gn:cc2":"RU",
    "gn:country_code":"RU",
    "gn:dem":11,
    "gn:feature_class":"P",
    "gn:feature_code":"PPL",
    "gn:name":"Karatayka",
    "gn:population":0,
    "gn:timezone":"Europe/Moscow",
    "iso:country":"RU",
    "name:eng_x_preferred":[
        "Karatayka"
    ],
    "name:nor_x_preferred":[
        "Karatajka"
    ],
    "name:rus_x_preferred":[
        "\u041a\u0430\u0440\u0430\u0442\u0430\u0439\u043a\u0430"
    ],
    "name:und_x_variant":[
        "Korotaykha",
        "Korotaikha",
        "\u041a\u0430\u0440\u0430\u0442\u0430\u0439\u043a\u0430",
        "Karatayka"
    ],
    "wof:name":"Karatayka",
    "wof:placetype":"locality"
},
  "geometry": {"coordinates":[61.21666999999999,68.81667],"type":"Point"}
}