{
  "type": "Feature",
  "properties": {
    "gn:admin1_code":"6",
    "gn:asciiname":"Osinovo-Baranovo",
    "gn:cc2":"RU",
    "gn:country_code":"RU",
    "gn:dem":152,
    "gn:feature_class":"P",
    "gn:feature_code":"PPL",
    "gn:name":"Osinovo-Baranovo",
    "gn:population":0,
    "gn:timezone":"Europe/Moscow",
    "iso:country":"RU",
    "name:und_x_variant":[
        "Osipovo-Baranovo"
    ],
    "wof:name":"Osinovo-Baranovo",
    "wof:placetype":"locality"
},
  "geometry": {"coordinates":[44.43333,61.43333000000001],"type":"Point"}
}