{
  "type": "Feature",
  "properties": {
    "gn:admin1_code":"10.0",
    "gn:asciiname":"Aleshinka",
    "gn:country_code":"RU",
    "gn:dem":229,
    "gn:feature_class":"P",
    "gn:feature_code":"PPL",
    "gn:name":"Al\u00ebshinka",
    "gn:population":0,
    "gn:timezone":"Europe/Moscow",
    "iso:country":"RU",
    "name:und_x_variant":[
        "\u0410\u043b\u0451\u0448\u0438\u043d\u043a\u0430",
        "Al\u00ebshinka"
    ],
    "wof:name":"Aleshinka",
    "wof:placetype":"locality"
},
  "geometry": {"coordinates":[33.2754,53.6322],"type":"Point"}
}