{
  "type": "Feature",
  "properties": {
    "gn:admin1_code":"12.0",
    "gn:asciiname":"Khindoy",
    "gn:country_code":"RU",
    "gn:dem":1967,
    "gn:feature_class":"P",
    "gn:feature_code":"PPL",
    "gn:name":"Khindoy",
    "gn:population":0,
    "gn:timezone":"Europe/Moscow",
    "iso:country":"RU",
    "name:che_x_preferred":[
        "Hinda"
    ],
    "name:che_x_variant":[
        "\u0425\u0406\u0438\u043d\u0434\u0430"
    ],
    "name:rus_x_preferred":[
        "\u0425\u0438\u043d\u0434\u043e\u0439"
    ],
    "name:und_x_variant":[
        "Hindoj"
    ],
    "wof:name":"Khindoy",
    "wof:placetype":"locality"
},
  "geometry": {"coordinates":[45.97333,42.70611],"type":"Point"}
}