{
  "type": "Feature",
  "properties": {
    "gn:admin1_code":"70",
    "gn:asciiname":"Varenikovskoye",
    "gn:country_code":"RU",
    "gn:dem":139,
    "gn:feature_class":"P",
    "gn:feature_code":"PPL",
    "gn:name":"Varenikovskoye",
    "gn:population":0,
    "gn:timezone":"Europe/Moscow",
    "iso:country":"RU",
    "name:eng_x_preferred":[
        "Varenikovskoye"
    ],
    "name:nor_x_preferred":[
        "Varenikovskoje"
    ],
    "name:rus_x_preferred":[
        "\u0412\u0430\u0440\u0435\u043d\u0438\u043a\u043e\u0432\u0441\u043a\u043e\u0435"
    ],
    "wof:name":"Varenikovskoye",
    "wof:placetype":"locality"
},
  "geometry": {"coordinates":[44.31667,44.46667],"type":"Point"}
}