{
  "type": "Feature",
  "properties": {
    "gn:admin1_code":"62.0",
    "gn:asciiname":"Bestuzhevo",
    "gn:country_code":"RU",
    "gn:dem":121,
    "gn:feature_class":"P",
    "gn:feature_code":"PPL",
    "gn:name":"Bestuzhevo",
    "gn:population":0,
    "gn:timezone":"Europe/Moscow",
    "iso:country":"RU",
    "name:eng_x_preferred":[
        "Bestuzhevo"
    ],
    "name:nor_x_preferred":[
        "Bestuzjevo"
    ],
    "name:rus_x_preferred":[
        "\u0411\u0435\u0441\u0442\u0443\u0436\u0435\u0432\u043e"
    ],
    "name:und_x_variant":[
        "\u0411\u0435\u0441\u0442\u0443\u0436\u0435\u0432\u043e",
        "Bestuzhevo"
    ],
    "wof:name":"Bestuzhevo",
    "wof:placetype":"locality"
},
  "geometry": {"coordinates":[39.8753,54.0322],"type":"Point"}
}