{
  "type": "Feature",
  "properties": {
    "gn:admin1_code":"77.0",
    "gn:asciiname":"Arkhangel'skoye",
    "gn:country_code":"RU",
    "gn:dem":163,
    "gn:feature_class":"P",
    "gn:feature_code":"PPL",
    "gn:name":"Arkhangel\u2019skoye",
    "gn:population":0,
    "gn:timezone":"Europe/Moscow",
    "iso:country":"RU",
    "wof:name":"Arkhangel'skoye",
    "wof:placetype":"locality"
},
  "geometry": {"coordinates":[35.23909000000001,56.60663],"type":"Point"}
}