{
  "type": "Feature",
  "properties": {
    "gn:admin1_code":"47.0",
    "gn:asciiname":"Korolyov",
    "gn:country_code":"RU",
    "gn:dem":166,
    "gn:feature_class":"P",
    "gn:feature_code":"PPL",
    "gn:name":"Korolyov",
    "gn:population":183402,
    "gn:timezone":"Europe/Moscow",
    "iso:country":"RU",
    "wof:name":"Korolyov",
    "wof:placetype":"locality",
    "wof:population":183402
},
  "geometry": {"coordinates":[37.81786,55.91732],"type":"Point"}
}