{
  "type": "Feature",
  "properties": {
    "gn:admin1_code":"47.0",
    "gn:asciiname":"Korolyov",
    "gn:country_code":"RU",
    "gn:dem":166,
    "gn:feature_class":"P",
    "gn:feature_code":"PPL",
    "gn:name":"Korolyov",
    "gn:population":183402,
    "gn:timezone":"Europe/Moscow",
    "iso:country":"RU",
    "name:bel_x_preferred":[
        "\u041a\u0430\u0440\u0430\u043b\u0451\u045e"
    ],
    "name:bul_x_preferred":[
        "\u041a\u043e\u0440\u043e\u043b\u044c\u043e\u0432"
    ],
    "name:ces_x_preferred":[
        "Koroljov"
    ],
    "name:deu_x_preferred":[
        "Koroljow"
    ],
    "name:epo_x_preferred":[
        "Koroljov"
    ],
    "name:fin_x_preferred":[
        "Koroljov"
    ],
    "name:fra_x_preferred":[
        "Korolev"
    ],
    "name:hrv_x_preferred":[
        "Koroljov"
    ],
    "name:hun_x_preferred":[
        "Koroljov"
    ],
    "name:ita_x_preferred":[
        "Korol\u00ebv"
    ],
    "name:jpn_x_preferred":[
        "\u30b3\u30ed\u30ea\u30e7\u30d5"
    ],
    "name:nld_x_preferred":[
        "Koroljov"
    ],
    "name:nor_x_preferred":[
        "Koroljov"
    ],
    "name:pol_x_preferred":[
        "Korolev"
    ],
    "name:por_x_preferred":[
        "Korolev"
    ],
    "name:ron_x_preferred":[
        "Koroliov"
    ],
    "name:rus_x_preferred":[
        "\u041a\u043e\u0440\u043e\u043b\u0451\u0432"
    ],
    "name:sco_x_preferred":[
        "Korolyov"
    ],
    "name:slv_x_preferred":[
        "Koroljov"
    ],
    "name:spa_x_preferred":[
        "Koroliov"
    ],
    "name:swe_x_preferred":[
        "Koroljov"
    ],
    "name:ukr_x_preferred":[
        "\u041a\u043e\u0440\u043e\u043b\u044c\u043e\u0432"
    ],
    "name:vie_x_preferred":[
        "Korolyov"
    ],
    "wof:name":"Korolyov",
    "wof:placetype":"locality",
    "wof:population":183402
},
  "geometry": {"coordinates":[37.81786,55.91732],"type":"Point"}
}