{
  "type": "Feature",
  "properties": {
    "gn:admin1_code":"90",
    "gn:asciiname":"Oralovo",
    "gn:country_code":"RU",
    "gn:dem":182,
    "gn:feature_class":"P",
    "gn:feature_code":"PPL",
    "gn:name":"Oralovo",
    "gn:population":0,
    "gn:timezone":"Asia/Yekaterinburg",
    "iso:country":"RU",
    "name:che_x_preferred":[
        "\u041e\u0440\u0430\u043b\u043e\u0432\u043e"
    ],
    "name:eng_x_preferred":[
        "Oralovo"
    ],
    "name:nor_x_preferred":[
        "Oralovo"
    ],
    "name:rus_x_preferred":[
        "\u041e\u0440\u0430\u043b\u043e\u0432\u043e"
    ],
    "name:und_x_variant":[
        "\u041e\u0440\u0430\u043b\u043e\u0432\u043e"
    ],
    "wof:name":"Oralovo",
    "wof:placetype":"locality"
},
  "geometry": {"coordinates":[56.87898000000001,60.49215],"type":"Point"}
}