{
  "type": "Feature",
  "properties": {
    "gn:admin1_code":"55",
    "gn:asciiname":"Tukay",
    "gn:country_code":"RU",
    "gn:dem":196,
    "gn:feature_class":"P",
    "gn:feature_code":"PPL",
    "gn:name":"Tukay",
    "gn:population":0,
    "gn:timezone":"Asia/Yekaterinburg",
    "iso:country":"RU",
    "name:chv_x_preferred":[
        "\u0422\u0443\u043a\u0430\u0439"
    ],
    "name:eng_x_preferred":[
        "Tukay"
    ],
    "name:hye_x_preferred":[
        "\u054f\u0578\u0582\u056f\u0561\u0575"
    ],
    "name:nor_x_preferred":[
        "Tukaj"
    ],
    "name:rus_x_preferred":[
        "\u0422\u0443\u043a\u0430\u0439"
    ],
    "name:tat_x_preferred":[
        "\u0422\u0443\u043a\u0430\u0439"
    ],
    "name:ukr_x_preferred":[
        "\u0422\u0443\u043a\u0430\u0439"
    ],
    "wof:name":"Tukay",
    "wof:placetype":"locality"
},
  "geometry": {"coordinates":[58.77288000000001,51.15655],"type":"Point"}
}