{
  "type": "Feature",
  "properties": {
    "gn:admin1_code":"73",
    "gn:asciiname":"Nuriner",
    "gn:country_code":"RU",
    "gn:dem":79,
    "gn:feature_class":"P",
    "gn:feature_code":"PPL",
    "gn:name":"Nuriner",
    "gn:population":0,
    "gn:timezone":"Europe/Volgograd",
    "iso:country":"RU",
    "name:eng_x_preferred":[
        "Nuriner"
    ],
    "name:nor_x_preferred":[
        "Nuriner"
    ],
    "name:rus_x_preferred":[
        "\u041d\u0443\u0440\u0438\u043d\u0435\u0440"
    ],
    "name:und_x_variant":[
        "\u041d\u0443\u0440\u0438\u043d\u0435\u0440",
        "Nuriner"
    ],
    "wof:name":"Nuriner",
    "wof:placetype":"locality"
},
  "geometry": {"coordinates":[50.4664,56.5326],"type":"Point"}
}