{
  "type": "Feature",
  "properties": {
    "gn:admin1_code":"73",
    "gn:asciiname":"Smak-Korsa",
    "gn:country_code":"RU",
    "gn:dem":144,
    "gn:feature_class":"P",
    "gn:feature_code":"PPL",
    "gn:name":"Smak-Korsa",
    "gn:population":0,
    "gn:timezone":"Europe/Moscow",
    "iso:country":"RU",
    "name:rus_x_preferred":[
        "\u0421\u043c\u0430\u043a-\u041a\u043e\u0440\u0441\u0430"
    ],
    "wof:name":"Smak-Korsa",
    "wof:placetype":"locality"
},
  "geometry": {"coordinates":[50.1017,56.107],"type":"Point"}
}