{
  "type": "Feature",
  "properties": {
    "gn:admin1_code":"91",
    "gn:asciiname":"Bol'shiye Klyuchi",
    "gn:country_code":"RU",
    "gn:dem":354,
    "gn:feature_class":"P",
    "gn:feature_code":"PPL",
    "gn:name":"Bol\u2019shiye Klyuchi",
    "gn:population":0,
    "gn:timezone":"Asia/Krasnoyarsk",
    "iso:country":"RU",
    "name:eng_x_preferred":[
        "Bol'shiye Klyuchi"
    ],
    "name:nor_x_preferred":[
        "Bolsjije Kljutsji"
    ],
    "name:rus_x_preferred":[
        "\u0411\u043e\u043b\u044c\u0448\u0438\u0435 \u041a\u043b\u044e\u0447\u0438"
    ],
    "name:und_x_variant":[
        "Bol\u2019shiye Klyuchi"
    ],
    "wof:name":"Bol'shiye Klyuchi",
    "wof:placetype":"locality"
},
  "geometry": {"coordinates":[95.1771,55.9487],"type":"Point"}
}