{
  "type": "Feature",
  "properties": {
    "gn:admin1_code":"4",
    "gn:asciiname":"Usovo",
    "gn:country_code":"RU",
    "gn:dem":132,
    "gn:feature_class":"P",
    "gn:feature_code":"PPL",
    "gn:name":"Usovo",
    "gn:population":0,
    "gn:timezone":"Asia/Barnaul",
    "iso:country":"RU",
    "name:rus_x_preferred":[
        "\u0423\u0441\u043e\u0432\u043e"
    ],
    "name:und_x_variant":[
        "Usova",
        "Usovo"
    ],
    "wof:name":"Usovo",
    "wof:placetype":"locality"
},
  "geometry": {"coordinates":[83.22399999999998,53.6299],"type":"Point"}
}