{
  "type": "Feature",
  "properties": {
    "gn:admin1_code":"51.0",
    "gn:asciiname":"Malyye Pany",
    "gn:country_code":"RU",
    "gn:dem":173,
    "gn:feature_class":"P",
    "gn:feature_code":"PPL",
    "gn:name":"Malyye Pany",
    "gn:population":0,
    "gn:timezone":"Europe/Moscow",
    "iso:country":"RU",
    "name:rus_x_preferred":[
        "\u041c\u0430\u043b\u044b\u0435 \u041f\u0430\u043d\u044b"
    ],
    "name:und_x_variant":[
        "\u041c\u0430\u043b\u044b\u0435 \u041f\u0430\u043d\u044b"
    ],
    "wof:name":"Malyye Pany",
    "wof:placetype":"locality"
},
  "geometry": {"coordinates":[43.27535,55.1448],"type":"Point"}
}