{
  "type": "Feature",
  "properties": {
    "gn:admin1_code":"8",
    "gn:asciiname":"Verkhnemancharovo",
    "gn:country_code":"RU",
    "gn:dem":141,
    "gn:feature_class":"P",
    "gn:feature_code":"PPL",
    "gn:name":"Verkhnemancharovo",
    "gn:population":0,
    "gn:timezone":"Asia/Yekaterinburg",
    "iso:country":"RU",
    "name:eng_x_preferred":[
        "Verkhnemancharovo"
    ],
    "name:nor_x_preferred":[
        "Verkhnemantsjarovo"
    ],
    "name:rus_x_preferred":[
        "\u0412\u0435\u0440\u0445\u043d\u0435\u043c\u0430\u043d\u0447\u0430\u0440\u043e\u0432\u043e"
    ],
    "name:und_x_variant":[
        "Verkhnyaya Mancharova",
        "Verkhneye Mancharovo",
        "Verkhnyaya Moncharova",
        "Verkhnemancharovo"
    ],
    "wof:name":"Verkhnemancharovo",
    "wof:placetype":"locality"
},
  "geometry": {"coordinates":[54.54888,55.3644],"type":"Point"}
}