{
  "type": "Feature",
  "properties": {
    "gn:admin1_code":"65",
    "gn:asciiname":"Kazachiy",
    "gn:country_code":"RU",
    "gn:dem":70,
    "gn:feature_class":"P",
    "gn:feature_code":"PPL",
    "gn:name":"Kazachiy",
    "gn:population":0,
    "gn:timezone":"Europe/Samara",
    "iso:country":"RU",
    "name:rus_x_preferred":[
        "\u041a\u0430\u0437\u0430\u0447\u0438\u0439"
    ],
    "wof:name":"Kazachiy",
    "wof:placetype":"locality"
},
  "geometry": {"coordinates":[50.4191,54.0002],"type":"Point"}
}