{
  "type": "Feature",
  "properties": {
    "gn:admin1_code":"72",
    "gn:asciiname":"Shinovka",
    "gn:country_code":"RU",
    "gn:dem":128,
    "gn:feature_class":"P",
    "gn:feature_code":"PPL",
    "gn:name":"Shinovka",
    "gn:population":0,
    "gn:timezone":"Europe/Moscow",
    "iso:country":"RU",
    "name:rus_x_preferred":[
        "\u0428\u0438\u043d\u043e\u0432\u043a\u0430"
    ],
    "name:und_x_variant":[
        "\u0428\u0438\u043d\u043e\u0432\u043a\u0430"
    ],
    "wof:name":"Shinovka",
    "wof:placetype":"locality"
},
  "geometry": {"coordinates":[42.67228,52.64478],"type":"Point"}
}