{
  "type": "Feature",
  "properties": {
    "gn:admin1_code":"51.0",
    "gn:asciiname":"Chernoye",
    "gn:country_code":"RU",
    "gn:dem":138,
    "gn:feature_class":"P",
    "gn:feature_code":"PPL",
    "gn:name":"Ch\u00ebrnoye",
    "gn:population":0,
    "gn:timezone":"Europe/Moscow",
    "iso:country":"RU",
    "name:eng_x_preferred":[
        "Chernoye"
    ],
    "name:nor_x_preferred":[
        "Tsjernoje"
    ],
    "name:rus_x_preferred":[
        "\u0427\u0451\u0440\u043d\u043e\u0435"
    ],
    "name:und_x_variant":[
        "Chernov",
        "\u0427\u0451\u0440\u043d\u043e\u0435",
        "Ch\u00ebrnoye"
    ],
    "wof:name":"Chernoye",
    "wof:placetype":"locality"
},
  "geometry": {"coordinates":[46.40107,57.53648000000001],"type":"Point"}
}