{
  "type": "Feature",
  "properties": {
    "gn:admin1_code":"38",
    "gn:asciiname":"Armyanskiy",
    "gn:country_code":"RU",
    "gn:dem":306,
    "gn:feature_class":"P",
    "gn:feature_code":"PPL",
    "gn:name":"Armyanskiy",
    "gn:population":0,
    "gn:timezone":"Europe/Moscow",
    "iso:country":"RU",
    "name:nor_x_preferred":[
        "Armjanskij"
    ],
    "name:rus_x_preferred":[
        "\u0410\u0440\u043c\u044f\u043d\u0441\u043a\u0438\u0439"
    ],
    "wof:name":"Armyanskiy",
    "wof:placetype":"locality"
},
  "geometry": {"coordinates":[39.8227,44.2424],"type":"Point"}
}