{
  "type": "Feature",
  "properties": {
    "gn:admin1_code":"88",
    "gn:asciiname":"Mit'kovo",
    "gn:country_code":"RU",
    "gn:dem":173,
    "gn:feature_class":"P",
    "gn:feature_code":"PPL",
    "gn:name":"Mit\u2019kovo",
    "gn:population":0,
    "gn:timezone":"Europe/Moscow",
    "iso:country":"RU",
    "name:rus_x_preferred":[
        "\u041c\u0438\u0442\u044c\u043a\u043e\u0432\u043e"
    ],
    "name:und_x_variant":[
        "Mit\u2019kovo"
    ],
    "wof:name":"Mit'kovo",
    "wof:placetype":"locality"
},
  "geometry": {"coordinates":[39.40066,57.48417],"type":"Point"}
}