{
  "type": "Feature",
  "properties": {
    "gn:admin1_code":"17",
    "gn:asciiname":"Patimat-Otar",
    "gn:country_code":"RU",
    "gn:dem":8,
    "gn:feature_class":"P",
    "gn:feature_code":"PPL",
    "gn:name":"Patimat-Otar",
    "gn:population":0,
    "gn:timezone":"Europe/Moscow",
    "iso:country":"RU",
    "name:rus_x_preferred":[
        "\u041f\u0430\u0442\u0438\u043c\u0430\u0442-\u041e\u0442\u0430\u0440"
    ],
    "name:und_x_variant":[
        "\u041f\u0430\u0442\u0438\u043c\u0430\u0442-\u041e\u0442\u0430\u0440"
    ],
    "wof:name":"Patimat-Otar",
    "wof:placetype":"locality"
},
  "geometry": {"coordinates":[46.50722,43.57111],"type":"Point"}
}