{
  "type": "Feature",
  "properties": {
    "gn:admin1_code":"62",
    "gn:asciiname":"Melenino",
    "gn:country_code":"RU",
    "gn:dem":109,
    "gn:feature_class":"P",
    "gn:feature_code":"PPL",
    "gn:name":"Melenino",
    "gn:population":0,
    "gn:timezone":"Europe/Moscow",
    "iso:country":"RU",
    "name:rus_x_preferred":[
        "\u041c\u0435\u043b\u0435\u043d\u0438\u043d\u043e"
    ],
    "wof:name":"Melenino",
    "wof:placetype":"locality"
},
  "geometry": {"coordinates":[40.8564,55.01279],"type":"Point"}
}