{
  "type": "Feature",
  "properties": {
    "gn:admin1_code":"34",
    "gn:asciiname":"Sel'yb",
    "gn:country_code":"RU",
    "gn:dem":107,
    "gn:feature_class":"P",
    "gn:feature_code":"PPL",
    "gn:name":"S\u00ebl\u2019yb",
    "gn:population":0,
    "gn:timezone":"Europe/Moscow",
    "iso:country":"RU",
    "name:eng_x_preferred":[
        "S\u00ebl'yb"
    ],
    "name:nor_x_preferred":[
        "Selyb"
    ],
    "name:rus_x_preferred":[
        "\u0421\u0435\u043b\u044c\u044b\u0431"
    ],
    "name:rus_x_variant":[
        "\u0421\u0451\u043b\u044c\u044b\u0431"
    ],
    "name:und_x_variant":[
        "Selib",
        "S\u00ebl\u2019yb",
        "\u0421\u0451\u043b\u044c\u044b\u0431"
    ],
    "wof:name":"Sel'yb",
    "wof:placetype":"locality"
},
  "geometry": {"coordinates":[48.57674,63.69271],"type":"Point"}
}