{
  "type": "Feature",
  "properties": {
    "gn:admin1_code":"68",
    "gn:asciiname":"Khidikus",
    "gn:cc2":"RU",
    "gn:country_code":"RU",
    "gn:dem":1289,
    "gn:feature_class":"P",
    "gn:feature_code":"PPL",
    "gn:name":"Khidikus",
    "gn:population":0,
    "gn:timezone":"Europe/Moscow",
    "iso:country":"RU",
    "name:rus_x_preferred":[
        "\u0425\u0438\u0434\u0438\u043a\u0443\u0441"
    ],
    "name:und_x_variant":[
        "Khidakus",
        "Khidikus",
        "\u0425\u0438\u0434\u0438\u043a\u0443\u0441"
    ],
    "wof:name":"Khidikus",
    "wof:placetype":"locality"
},
  "geometry": {"coordinates":[44.27361,42.82083],"type":"Point"}
}