{
  "type": "Feature",
  "properties": {
    "gn:admin1_code":"7.0",
    "gn:asciiname":"Aysapay",
    "gn:country_code":"RU",
    "gn:dem":-23,
    "gn:feature_class":"P",
    "gn:feature_code":"PPL",
    "gn:name":"Aysapay",
    "gn:population":0,
    "gn:timezone":"Europe/Astrakhan",
    "iso:country":"RU",
    "name:che_x_preferred":[
        "\u0410\u0439\u0441\u0430\u043f\u0430\u0439"
    ],
    "name:nor_x_preferred":[
        "Aj Saraj"
    ],
    "name:rus_x_preferred":[
        "\u0410\u0439\u0441\u0430\u043f\u0430\u0439"
    ],
    "name:tat_x_preferred":[
        "\u0410\u0439\u0441\u0430\u043f\u0430\u0439"
    ],
    "name:tgk_x_preferred":[
        "\u0410\u0439\u0441\u0430\u043f\u0430\u0439"
    ],
    "name:und_x_variant":[
        "Aysapay"
    ],
    "wof:name":"Aysapay",
    "wof:placetype":"locality"
},
  "geometry": {"coordinates":[47.98744,46.76567],"type":"Point"}
}