{
  "type": "Feature",
  "properties": {
    "gn:admin1_code":"77",
    "gn:asciiname":"Lyapunikha",
    "gn:country_code":"RU",
    "gn:dem":158,
    "gn:feature_class":"P",
    "gn:feature_code":"PPL",
    "gn:name":"Lyapunikha",
    "gn:population":0,
    "gn:timezone":"Europe/Moscow",
    "iso:country":"RU",
    "name:rus_x_preferred":[
        "\u041b\u044f\u043f\u0443\u043d\u0438\u0445\u0430"
    ],
    "wof:name":"Lyapunikha",
    "wof:placetype":"locality"
},
  "geometry": {"coordinates":[34.87617,57.56807],"type":"Point"}
}