{
  "type": "Feature",
  "properties": {
    "gn:admin1_code":"47",
    "gn:asciiname":"Levinskaya",
    "gn:country_code":"RU",
    "gn:dem":132,
    "gn:feature_class":"P",
    "gn:feature_code":"PPL",
    "gn:name":"Levinskaya",
    "gn:population":0,
    "gn:timezone":"Europe/Moscow",
    "iso:country":"RU",
    "name:rus_x_preferred":[
        "\u041b\u0435\u0432\u0438\u043d\u0441\u043a\u0430\u044f"
    ],
    "name:und_x_variant":[
        "\u041b\u0435\u0432\u0438\u043d\u0441\u043a\u0430\u044f"
    ],
    "wof:name":"Levinskaya",
    "wof:placetype":"locality"
},
  "geometry": {"coordinates":[38.98333,55.43333000000001],"type":"Point"}
}