{
  "type": "Feature",
  "properties": {
    "gn:admin1_code":"42",
    "gn:asciiname":"Solov'yevo",
    "gn:country_code":"RU",
    "gn:dem":25,
    "gn:feature_class":"P",
    "gn:feature_code":"PPL",
    "gn:name":"Solov\u2019y\u00ebvo",
    "gn:population":0,
    "gn:timezone":"Europe/Moscow",
    "iso:country":"RU",
    "name:fin_x_preferred":[
        "Lohijoki"
    ],
    "name:rus_x_preferred":[
        "\u0421\u043e\u043b\u043e\u0432\u044c\u0451\u0432\u043e"
    ],
    "name:und_x_variant":[
        "Lokhiyoki",
        "Solov\u2019y\u00ebvo",
        "\u0421\u043e\u043b\u043e\u0432\u044c\u0451\u0432\u043e"
    ],
    "wof:name":"Solov'yevo",
    "wof:placetype":"locality"
},
  "geometry": {"coordinates":[30.47916,60.70226],"type":"Point"}
}