{
  "type": "Feature",
  "properties": {
    "gn:admin1_code":"37.0",
    "gn:asciiname":"Anan'ino",
    "gn:country_code":"RU",
    "gn:dem":164,
    "gn:feature_class":"P",
    "gn:feature_code":"PPL",
    "gn:name":"Anan\u2019ino",
    "gn:population":0,
    "gn:timezone":"Europe/Moscow",
    "iso:country":"RU",
    "name:und_x_variant":[
        "Akan\u2019ino",
        "Anan\u2019ino"
    ],
    "wof:name":"Anan'ino",
    "wof:placetype":"locality"
},
  "geometry": {"coordinates":[42.33734000000001,57.98203],"type":"Point"}
}