{
  "type": "Feature",
  "properties": {
    "gn:admin1_code":"45",
    "gn:asciiname":"Kozloyal-Syuba",
    "gn:country_code":"RU",
    "gn:dem":123,
    "gn:feature_class":"P",
    "gn:feature_code":"PPL",
    "gn:name":"Kozloyal-Syuba",
    "gn:population":0,
    "gn:timezone":"Europe/Moscow",
    "iso:country":"RU",
    "name:rus_x_preferred":[
        "\u041a\u043e\u0437\u043b\u043e\u044f\u043b-\u0421\u044e\u0431\u0430"
    ],
    "wof:name":"Kozloyal-Syuba",
    "wof:placetype":"locality"
},
  "geometry": {"coordinates":[49.6363,57.0622],"type":"Point"}
}