{
  "type": "Feature",
  "properties": {
    "gn:admin1_code":"80",
    "gn:asciiname":"Kokman",
    "gn:country_code":"RU",
    "gn:dem":154,
    "gn:feature_class":"P",
    "gn:feature_code":"PPL",
    "gn:name":"Kokman",
    "gn:population":0,
    "gn:timezone":"Europe/Samara",
    "iso:country":"RU",
    "name:eng_x_preferred":[
        "Kokman"
    ],
    "name:nor_x_preferred":[
        "Kokman"
    ],
    "name:rus_x_preferred":[
        "\u041a\u043e\u043a\u043c\u0430\u043d"
    ],
    "name:und_x_variant":[
        "Kokmanskiy"
    ],
    "wof:name":"Kokman",
    "wof:placetype":"locality"
},
  "geometry": {"coordinates":[52.3743,57.5728],"type":"Point"}
}