{
  "type": "Feature",
  "properties": {
    "gn:admin1_code":"87",
    "gn:asciiname":"Chasel'ka",
    "gn:country_code":"RU",
    "gn:dem":18,
    "gn:feature_class":"P",
    "gn:feature_code":"PPL",
    "gn:name":"Chasel\u2019ka",
    "gn:population":0,
    "gn:timezone":"Asia/Yekaterinburg",
    "iso:country":"RU",
    "name:eng_x_preferred":[
        "Chasel'ka"
    ],
    "name:nor_x_preferred":[
        "Tsjaselka"
    ],
    "name:rus_x_preferred":[
        "\u0427\u0430\u0441\u0435\u043b\u044c\u043a\u0430"
    ],
    "name:und_x_variant":[
        "Faktoriya Chasel\u2019ka",
        "Chasyl\u2019ka",
        "\u0427\u0430\u0441\u0435\u043b\u044c\u043a\u0430",
        "Chasel\u2019ka"
    ],
    "wof:name":"Chasel'ka",
    "wof:placetype":"locality"
},
  "geometry": {"coordinates":[81.45546999999998,65.09397],"type":"Point"}
}