{
  "type": "Feature",
  "properties": {
    "gn:admin1_code":"29",
    "gn:asciiname":"Sklad Tretiy",
    "gn:country_code":"RU",
    "gn:dem":254,
    "gn:feature_class":"P",
    "gn:feature_code":"PPL",
    "gn:name":"Sklad Tretiy",
    "gn:population":0,
    "gn:timezone":"Asia/Novokuznetsk",
    "iso:country":"RU",
    "name:rus_x_preferred":[
        "\u0421\u043a\u043b\u0430\u0434 \u0422\u0440\u0435\u0442\u0438\u0439"
    ],
    "wof:name":"Sklad Tretiy",
    "wof:placetype":"locality"
},
  "geometry": {"coordinates":[86.0513,56.02],"type":"Point"}
}