{
  "type": "Feature",
  "properties": {
    "gn:admin1_code":"86",
    "gn:asciiname":"Malyye Gorki",
    "gn:country_code":"RU",
    "gn:dem":112,
    "gn:feature_class":"P",
    "gn:feature_code":"PPL",
    "gn:name":"Malyye Gorki",
    "gn:population":0,
    "gn:timezone":"Europe/Moscow",
    "iso:country":"RU",
    "name:eng_x_preferred":[
        "Malyye Gorki"
    ],
    "name:nor_x_preferred":[
        "Gorki"
    ],
    "name:rus_x_preferred":[
        "\u0413\u043e\u0440\u043a\u0438"
    ],
    "name:rus_x_variant":[
        "\u041c\u0430\u043b\u044b\u0435 \u0413\u043e\u0440\u043a\u0438"
    ],
    "name:und_x_variant":[
        "Gorki",
        "Malyye Gorki"
    ],
    "wof:name":"Malyye Gorki",
    "wof:placetype":"locality"
},
  "geometry": {"coordinates":[39.60131,51.6908],"type":"Point"}
}