{
  "type": "Feature",
  "properties": {
    "gn:country":"RU",
    "gn:fcode":"PPL",
    "gn:population":5103,
    "iso:country":"RU",
    "name:eng_x_preferred":[
        "Polovinnoye"
    ],
    "name:nor_x_preferred":[
        "Polovinnoje"
    ],
    "name:rus_x_preferred":[
        "\u041f\u043e\u043b\u043e\u0432\u0438\u043d\u043d\u043e\u0435"
    ],
    "qs_pg:aaroncc":"RU",
    "qs_pg:gn_country":"RU",
    "qs_pg:gn_fcode":"PPL",
    "qs_pg:gn_pop":5103,
    "qs_pg:name":"Golovnoye",
    "qs_pg:name_adm0":"Russia",
    "qs_pg:name_adm1":"Kurgan Oblast",
    "qs_pg:photos_9r":0,
    "qs_pg:photos_sr":0,
    "qs_pg:pop_sr":5,
    "qs_pg:qs_pg_placetype":"locality",
    "qs_pg:qs_pg_placetype_gp":"Town",
    "qs_pg:woe_adm0":23424936,
    "woe:adm0_id":23424936,
    "woe:name_adm0":"Russia",
    "woe:name_adm1":"Kurgan Oblast",
    "woe:placetype":"Town",
    "wof:name":"Golovnoye",
    "wof:placetype":"locality",
    "wof:population":5103
},
  "geometry": {"coordinates":[65.98639,54.79139],"type":"Point"}
}