{
  "type": "Feature",
  "properties": {
    "gn:admin1_code":"4",
    "gn:asciiname":"Bol'shoy Kaltay",
    "gn:country_code":"RU",
    "gn:dem":208,
    "gn:feature_class":"P",
    "gn:feature_code":"PPL",
    "gn:name":"Bol\u2019shoy Kaltay",
    "gn:population":0,
    "gn:timezone":"Asia/Barnaul",
    "iso:country":"RU",
    "name:rus_x_preferred":[
        "\u0411\u043e\u043b\u044c\u0448\u043e\u0439 \u041a\u0430\u043b\u0442\u0430\u0439"
    ],
    "name:und_x_variant":[
        "Kaltay",
        "Bol\u2019shoy Kaltay",
        "\u0411\u043e\u043b\u044c\u0448\u043e\u0439 \u041a\u0430\u043b\u0442\u0430\u0439"
    ],
    "wof:name":"Bol'shoy Kaltay",
    "wof:placetype":"locality"
},
  "geometry": {"coordinates":[84.25389,54.13],"type":"Point"}
}