{
  "type": "Feature",
  "properties": {
    "gn:admin1_code":"90.0",
    "gn:asciiname":"Mokrushino",
    "gn:country_code":"RU",
    "gn:dem":157,
    "gn:feature_class":"P",
    "gn:feature_code":"PPL",
    "gn:name":"Mokrushino",
    "gn:population":0,
    "gn:timezone":"Asia/Yekaterinburg",
    "iso:country":"RU",
    "name:rus_x_preferred":[
        "\u041c\u043e\u043a\u0440\u0443\u0448\u0438\u043d\u043e"
    ],
    "wof:name":"Mokrushino",
    "wof:placetype":"locality"
},
  "geometry": {"coordinates":[54.8782,58.9762],"type":"Point"}
}