{
  "type": "Feature",
  "properties": {
    "gn:admin1_code":"44",
    "gn:asciiname":"Verkhniy Paren'",
    "gn:country_code":"RU",
    "gn:dem":44,
    "gn:feature_class":"P",
    "gn:feature_code":"PPL",
    "gn:name":"Verkhniy Paren\u2019",
    "gn:population":0,
    "gn:timezone":"Asia/Magadan",
    "iso:country":"RU",
    "name:eng_x_preferred":[
        "Verkhniy Paren'"
    ],
    "name:nor_x_preferred":[
        "Verkh.Paren"
    ],
    "name:rus_x_preferred":[
        "\u0412\u0435\u0440\u0445.\u041f\u0430\u0440\u0435\u043d\u044c"
    ],
    "name:und_x_variant":[
        "Verkhniy Paren\u2019"
    ],
    "wof:name":"Verkhniy Paren'",
    "wof:placetype":"locality"
},
  "geometry": {"coordinates":[162.38415000000001,62.65286],"type":"Point"}
}