{
  "type": "Feature",
  "properties": {
    "gn:country":"RU",
    "gn:fcode":"PPL",
    "gn:pop":0,
    "iso:country":"RU",
    "name:eng_x_preferred":[
        "Pekhlets"
    ],
    "name:nor_x_preferred":[
        "Pekhlets"
    ],
    "name:rus_x_preferred":[
        "\u041f\u0435\u0445\u043b\u0435\u0446"
    ],
    "name:unk_x_variant":[
        "Pekhlgi"
    ],
    "qs:name":"Pekhlets",
    "qs:name_adm0":"Russia",
    "qs:name_adm1":"Ryazan Oblast",
    "qs:photos_9r":0,
    "qs:photos_sr":0,
    "qs:placetype":"Town",
    "qs:pop_sr":"0",
    "wof:name":"Pekhlets",
    "wof:placetype":"locality",
    "wof:population":0
},
  "geometry": {"coordinates":[40.112,53.9447],"type":"Point"}
}