{
  "type": "Feature",
  "properties": {
    "gn:admin1_code":"20",
    "gn:asciiname":"Turuka",
    "gn:country_code":"RU",
    "gn:dem":291,
    "gn:feature_class":"P",
    "gn:feature_code":"PPL",
    "gn:name":"Turuka",
    "gn:population":0,
    "gn:timezone":"Asia/Irkutsk",
    "iso:country":"RU",
    "name:eng_x_preferred":[
        "Turuka"
    ],
    "name:nor_x_preferred":[
        "Turuka"
    ],
    "name:rus_x_preferred":[
        "\u0422\u0443\u0440\u0443\u043a\u0430"
    ],
    "wof:name":"Turuka",
    "wof:placetype":"locality"
},
  "geometry": {"coordinates":[105.7709,56.6792],"type":"Point"}
}