{
  "type": "Feature",
  "properties": {
    "gn:admin1_code":"91",
    "gn:asciiname":"Shila",
    "gn:country_code":"RU",
    "gn:dem":205,
    "gn:feature_class":"P",
    "gn:feature_code":"PPL",
    "gn:name":"Shila",
    "gn:population":0,
    "gn:timezone":"Asia/Krasnoyarsk",
    "iso:country":"RU",
    "name:eng_x_preferred":[
        "Shila"
    ],
    "name:nor_x_preferred":[
        "Sjila"
    ],
    "name:rus_x_preferred":[
        "\u0428\u0438\u043b\u0430"
    ],
    "name:und_x_variant":[
        "Shilinskaya",
        "Shilinskoye",
        "Shila"
    ],
    "wof:name":"Shila",
    "wof:placetype":"locality"
},
  "geometry": {"coordinates":[93.05139,56.55056],"type":"Point"}
}