{
  "type": "Feature",
  "properties": {
    "gn:admin1_code":"16",
    "gn:asciiname":"Polaykasy",
    "gn:country_code":"RU",
    "gn:dem":125,
    "gn:feature_class":"P",
    "gn:feature_code":"PPL",
    "gn:name":"Polaykasy",
    "gn:population":0,
    "gn:timezone":"Europe/Moscow",
    "iso:country":"RU",
    "name:rus_x_preferred":[
        "\u041f\u043e\u043b\u0430\u0439\u043a\u0430\u0441\u044b"
    ],
    "name:und_x_variant":[
        "\u041f\u043e\u043b\u0430\u0439\u043a\u0430\u0441\u044b"
    ],
    "wof:name":"Polaykasy",
    "wof:placetype":"locality"
},
  "geometry": {"coordinates":[47.1395,55.86316],"type":"Point"}
}