{
  "type": "Feature",
  "properties": {
    "gn:admin1_code":"55",
    "gn:asciiname":"Yagodnyy",
    "gn:country_code":"RU",
    "gn:dem":212,
    "gn:feature_class":"P",
    "gn:feature_code":"PPL",
    "gn:name":"Yagodnyy",
    "gn:population":0,
    "gn:timezone":"Asia/Yekaterinburg",
    "iso:country":"RU",
    "name:rus_x_preferred":[
        "\u042f\u0433\u043e\u0434\u043d\u044b\u0439"
    ],
    "wof:name":"Yagodnyy",
    "wof:placetype":"locality"
},
  "geometry": {"coordinates":[55.7771,52.3196],"type":"Point"}
}