{
  "type": "Feature",
  "properties": {
    "gn:admin1_code":"73.0",
    "gn:asciiname":"Alat",
    "gn:country_code":"RU",
    "gn:dem":109,
    "gn:feature_class":"P",
    "gn:feature_code":"PPL",
    "gn:name":"Alat",
    "gn:population":0,
    "gn:timezone":"Europe/Moscow",
    "iso:country":"RU",
    "name:eng_x_preferred":[
        "Alat"
    ],
    "name:nor_x_preferred":[
        "Alat"
    ],
    "name:rus_x_preferred":[
        "\u0410\u043b\u0430\u0442"
    ],
    "name:und_x_variant":[
        "Alaty"
    ],
    "wof:name":"Alat",
    "wof:placetype":"locality"
},
  "geometry": {"coordinates":[49.21028,56.19389],"type":"Point"}
}