{
  "type": "Feature",
  "properties": {
    "gn:admin1_code":"93",
    "gn:asciiname":"Ust'-Urov",
    "gn:country_code":"RU",
    "gn:dem":484,
    "gn:feature_class":"P",
    "gn:feature_code":"PPL",
    "gn:name":"Ust\u2019-Urov",
    "gn:population":0,
    "gn:timezone":"Asia/Chita",
    "iso:country":"RU",
    "wof:name":"Ust'-Urov",
    "wof:placetype":"locality"
},
  "geometry": {"coordinates":[120.71666999999999,52.25],"type":"Point"}
}