{
  "type": "Feature",
  "properties": {
    "gn:admin1_code":"23",
    "gn:asciiname":"Karpinskoye",
    "gn:cc2":"RU",
    "gn:country_code":"RU",
    "gn:dem":125,
    "gn:feature_class":"P",
    "gn:feature_code":"PPL",
    "gn:name":"Karpinskoye",
    "gn:population":0,
    "gn:timezone":"Europe/Kaliningrad",
    "iso:country":"RU",
    "name:rus_x_preferred":[
        "\u041a\u0430\u0440\u043f\u0438\u043d\u0441\u043a\u043e\u0435"
    ],
    "name:und_x_variant":[
        "Pavlovka",
        "Karpinskoye",
        "\u041a\u0430\u0440\u043f\u0438\u043d\u0441\u043a\u043e\u0435"
    ],
    "wof:name":"Karpinskoye",
    "wof:placetype":"locality"
},
  "geometry": {"coordinates":[22.45444,54.44556],"type":"Point"}
}