{
  "type": "Feature",
  "properties": {
    "gn:admin1_code":"8",
    "gn:asciiname":"Alkino Shestoye",
    "gn:country_code":"RU",
    "gn:dem":123,
    "gn:feature_class":"P",
    "gn:feature_code":"PPL",
    "gn:name":"Alkino Shestoye",
    "gn:population":0,
    "gn:timezone":"Asia/Yekaterinburg",
    "iso:country":"RU",
    "name:rus_x_preferred":[
        "\u0410\u043b\u043a\u0438\u043d\u043e \u0428\u0435\u0441\u0442\u043e\u0435"
    ],
    "wof:name":"Alkino Shestoye",
    "wof:placetype":"locality"
},
  "geometry": {"coordinates":[54.658,54.7484],"type":"Point"}
}