{
  "type": "Feature",
  "properties": {
    "gn:gn_country":"RU",
    "gn:gn_fcode":"PPL",
    "gn:gn_pop":6474,
    "gn:population":6474,
    "iso:country":"RU",
    "name:eng_x_preferred":[
        "Sokol'skoye"
    ],
    "name:nor_x_preferred":[
        "Sokolskoje"
    ],
    "name:rus_x_preferred":[
        "\u0421\u043e\u043a\u043e\u043b\u044c\u0441\u043a\u043e\u0435"
    ],
    "name:unk_x_variant":[
        "\u0421\u043e\u043a\u043e\u043b\u044c\u0441\u043a\u043e\u0435"
    ],
    "qs_pg:aaroncc":"RU",
    "qs_pg:gn_country":"RU",
    "qs_pg:gn_fcode":"PPL",
    "qs_pg:gn_pop":6474,
    "qs_pg:name":"Sokol\u2019skoye",
    "qs_pg:photos_9r":0,
    "qs_pg:photos_sr":0,
    "qs_pg:pop_sr":5,
    "qs_pg:qs_pg_placetype":"locality",
    "wof:name":"Sokol\u2019skoye",
    "wof:placetype":"locality",
    "wof:population":6474
},
  "geometry": {"coordinates":[43.15894,57.14122],"type":"Point"}
}