{
  "type": "Feature",
  "properties": {
    "gn:admin1_code":"79",
    "gn:asciiname":"Chazylar",
    "gn:country_code":"RU",
    "gn:dem":1041,
    "gn:feature_class":"P",
    "gn:feature_code":"PPL",
    "gn:name":"Chazylar",
    "gn:population":0,
    "gn:timezone":"Asia/Krasnoyarsk",
    "iso:country":"RU",
    "name:rus_x_preferred":[
        "\u0427\u0430\u0437\u044b\u043b\u0430\u0440"
    ],
    "name:und_x_variant":[
        "\u0427\u0430\u0437\u044b\u043b\u0430\u0440"
    ],
    "wof:name":"Chazylar",
    "wof:placetype":"locality"
},
  "geometry": {"coordinates":[97.41611,52.75778],"type":"Point"}
}