{
  "type": "Feature",
  "properties": {
    "gn:admin1_code":"28",
    "gn:asciiname":"Luzhma-Guba",
    "gn:country_code":"RU",
    "gn:dem":203,
    "gn:feature_class":"P",
    "gn:feature_code":"PPL",
    "gn:name":"Luzhma-Guba",
    "gn:population":0,
    "gn:timezone":"Europe/Moscow",
    "iso:country":"RU",
    "name:fin_x_preferred":[
        "Lusma"
    ],
    "name:rus_x_preferred":[
        "\u041b\u0443\u0436\u043c\u0430-\u0413\u0443\u0431\u0430"
    ],
    "wof:name":"Luzhma-Guba",
    "wof:placetype":"locality"
},
  "geometry": {"coordinates":[30.36151,64.45034],"type":"Point"}
}