{
  "type": "Feature",
  "properties": {
    "gn:admin1_code":"77",
    "gn:asciiname":"Isakovskoye",
    "gn:country_code":"RU",
    "gn:dem":205,
    "gn:feature_class":"P",
    "gn:feature_code":"PPL",
    "gn:name":"Isakovskoye",
    "gn:population":0,
    "gn:timezone":"Europe/Moscow",
    "iso:country":"RU",
    "name:rus_x_preferred":[
        "\u0418\u0441\u0430\u043a\u043e\u0432\u0441\u043a\u043e\u0435"
    ],
    "wof:name":"Isakovskoye",
    "wof:placetype":"locality"
},
  "geometry": {"coordinates":[32.02194,56.37139000000001],"type":"Point"}
}