{
  "type": "Feature",
  "properties": {
    "gn:admin1_code":"62",
    "gn:asciiname":"Dubasovo",
    "gn:country_code":"RU",
    "gn:dem":208,
    "gn:feature_class":"P",
    "gn:feature_code":"PPL",
    "gn:name":"Dubasovo",
    "gn:population":0,
    "gn:timezone":"Europe/Moscow",
    "iso:country":"RU",
    "name:rus_x_preferred":[
        "\u0414\u0443\u0431\u0430\u0441\u043e\u0432\u043e"
    ],
    "name:und_x_variant":[
        "Dubasovskiy",
        "Dubasovo",
        "\u0414\u0443\u0431\u0430\u0441\u043e\u0432\u043e"
    ],
    "wof:name":"Dubasovo",
    "wof:placetype":"locality"
},
  "geometry": {"coordinates":[39.37653,53.53129000000001],"type":"Point"}
}