{
  "type": "Feature",
  "properties": {
    "gn:admin1_code":"88",
    "gn:asciiname":"Kabotovo",
    "gn:country_code":"RU",
    "gn:dem":116,
    "gn:feature_class":"P",
    "gn:feature_code":"PPL",
    "gn:name":"Kabotovo",
    "gn:population":0,
    "gn:timezone":"Europe/Moscow",
    "iso:country":"RU",
    "name:rus_x_preferred":[
        "\u041a\u0430\u0431\u043e\u0442\u043e\u0432\u043e"
    ],
    "name:und_x_variant":[
        "\u041a\u0430\u0431\u043e\u0442\u043e\u0432\u043e"
    ],
    "wof:name":"Kabotovo",
    "wof:placetype":"locality"
},
  "geometry": {"coordinates":[38.65408,58.00453],"type":"Point"}
}