{
  "type": "Feature",
  "properties": {
    "gn:admin1_code":"51",
    "gn:asciiname":"Panovo-Leont'yevo",
    "gn:country_code":"RU",
    "gn:dem":114,
    "gn:feature_class":"P",
    "gn:feature_code":"PPL",
    "gn:name":"Panovo-Leont\u2019yevo",
    "gn:population":0,
    "gn:timezone":"Europe/Moscow",
    "iso:country":"RU",
    "name:rus_x_preferred":[
        "\u041f\u0430\u043d\u043e\u0432\u043e-\u041b\u0435\u043e\u043d\u0442\u044c\u0435\u0432\u043e"
    ],
    "name:und_x_variant":[
        "Panovo",
        "Panovo-Leont\u2019yevo",
        "\u041f\u0430\u043d\u043e\u0432\u043e-\u041b\u0435\u043e\u043d\u0442\u044c\u0435\u0432\u043e"
    ],
    "wof:name":"Panovo-Leont'yevo",
    "wof:placetype":"locality"
},
  "geometry": {"coordinates":[44.92843,55.34712],"type":"Point"}
}