{
  "type": "Feature",
  "properties": {
    "iso:country":"RU",
    "name:rus_x_preferred":[
        "\u041f\u0435\u0441\u043e\u0447\u043d\u044b\u0439"
    ],
    "wof:name":"Pesochny",
    "wof:placetype":"neighbourhood"
},
  "geometry": {"coordinates":[30.1645596845715,60.12273224978288],"type":"Point"}
}