{
  "type": "Feature",
  "properties": {
    "gn:admin1_code":"13",
    "gn:asciiname":"Tominskiy",
    "gn:country_code":"RU",
    "gn:dem":349,
    "gn:feature_class":"P",
    "gn:feature_code":"PPL",
    "gn:name":"Tominskiy",
    "gn:population":0,
    "gn:timezone":"Asia/Yekaterinburg",
    "iso:country":"RU",
    "name:eng_x_preferred":[
        "Tominskiy"
    ],
    "name:nor_x_preferred":[
        "Tominskoje"
    ],
    "name:rus_x_preferred":[
        "\u0422\u043e\u043c\u0438\u043d\u0441\u043a\u043e\u0435"
    ],
    "name:rus_x_variant":[
        "\u0422\u043e\u043c\u0438\u043d\u0441\u043a\u0438\u0439"
    ],
    "wof:name":"Tominskiy",
    "wof:placetype":"locality"
},
  "geometry": {"coordinates":[60.25361,53.93611],"type":"Point"}
}