{
  "type": "Feature",
  "properties": {
    "gn:admin1_code":"37",
    "gn:asciiname":"Komarovo",
    "gn:country_code":"RU",
    "gn:dem":172,
    "gn:feature_class":"P",
    "gn:feature_code":"PPL",
    "gn:name":"Komarovo",
    "gn:population":0,
    "gn:timezone":"Europe/Moscow",
    "iso:country":"RU",
    "name:eng_x_preferred":[
        "Komarovo"
    ],
    "name:nor_x_preferred":[
        "Komarovo"
    ],
    "name:rus_x_preferred":[
        "\u041a\u043e\u043c\u0430\u0440\u043e\u0432\u043e"
    ],
    "name:und_x_variant":[
        "\u041a\u043e\u043c\u0430\u0440\u043e\u0432\u043e",
        "Komarovo"
    ],
    "wof:name":"Komarovo",
    "wof:placetype":"locality"
},
  "geometry": {"coordinates":[46.67387,59.10743000000001],"type":"Point"}
}