{
  "type": "Feature",
  "properties": {
    "gn:admin1_code":"54",
    "gn:asciiname":"Agafonovka",
    "gn:country_code":"RU",
    "gn:dem":126,
    "gn:feature_class":"P",
    "gn:feature_code":"PPL",
    "gn:name":"Agafonovka",
    "gn:population":0,
    "gn:timezone":"Asia/Omsk",
    "iso:country":"RU",
    "name:eng_x_preferred":[
        "Agafonovka"
    ],
    "name:nor_x_preferred":[
        "Agafonovka"
    ],
    "name:rus_x_preferred":[
        "\u0410\u0433\u0430\u0444\u043e\u043d\u043e\u0432\u043a\u0430"
    ],
    "wof:name":"Agafonovka",
    "wof:placetype":"locality"
},
  "geometry": {"coordinates":[73.86126999999998,55.52413000000001],"type":"Point"}
}