{
  "type": "Feature",
  "properties": {
    "gn:admin1_code":"60",
    "gn:asciiname":"Khvoshchinka",
    "gn:country_code":"RU",
    "gn:dem":115,
    "gn:feature_class":"P",
    "gn:feature_code":"PPL",
    "gn:name":"Khvoshchinka",
    "gn:population":0,
    "gn:timezone":"Europe/Moscow",
    "iso:country":"RU",
    "name:rus_x_preferred":[
        "\u0425\u0432\u043e\u0449\u0438\u043d\u043a\u0430"
    ],
    "wof:name":"Khvoshchinka",
    "wof:placetype":"locality"
},
  "geometry": {"coordinates":[28.4716,56.3967],"type":"Point"}
}