{
  "type": "Feature",
  "properties": {
    "gn:admin1_code":"51.0",
    "gn:asciiname":"Blyudo",
    "gn:country_code":"RU",
    "gn:dem":153,
    "gn:feature_class":"P",
    "gn:feature_code":"PPL",
    "gn:name":"Blyudo",
    "gn:population":0,
    "gn:timezone":"Europe/Moscow",
    "iso:country":"RU",
    "name:rus_x_preferred":[
        "\u0411\u043b\u044e\u0434\u043e"
    ],
    "name:und_x_variant":[
        "\u0411\u043b\u044e\u0434\u043e"
    ],
    "wof:name":"Blyudo",
    "wof:placetype":"locality"
},
  "geometry": {"coordinates":[42.8481,55.1649],"type":"Point"}
}