{
  "type": "Feature",
  "properties": {
    "gn:admin1_code":"85",
    "gn:asciiname":"Mitinskaya",
    "gn:country_code":"RU",
    "gn:dem":142,
    "gn:feature_class":"P",
    "gn:feature_code":"PPL",
    "gn:name":"Mitinskaya",
    "gn:population":0,
    "gn:timezone":"Europe/Moscow",
    "iso:country":"RU",
    "name:rus_x_preferred":[
        "\u041c\u0438\u0442\u0438\u043d\u0441\u043a\u0430\u044f"
    ],
    "name:und_x_variant":[
        "\u041c\u0438\u0442\u0438\u043d\u0441\u043a\u0430\u044f"
    ],
    "wof:name":"Mitinskaya",
    "wof:placetype":"locality"
},
  "geometry": {"coordinates":[39.8062,60.1239],"type":"Point"}
}