{
  "type": "Feature",
  "properties": {
    "gn:admin1_code":"62",
    "gn:asciiname":"Slivkovo",
    "gn:country_code":"RU",
    "gn:dem":131,
    "gn:feature_class":"P",
    "gn:feature_code":"PPL",
    "gn:name":"Slivkovo",
    "gn:population":0,
    "gn:timezone":"Europe/Moscow",
    "iso:country":"RU",
    "name:rus_x_preferred":[
        "\u0421\u043b\u0438\u0432\u043a\u043e\u0432\u043e"
    ],
    "wof:name":"Slivkovo",
    "wof:placetype":"locality"
},
  "geometry": {"coordinates":[39.1584,54.5954],"type":"Point"}
}