{
  "type": "Feature",
  "properties": {
    "gn:admin1_code":"33.0",
    "gn:asciiname":"Svinogor",
    "gn:country_code":"RU",
    "gn:dem":153,
    "gn:feature_class":"P",
    "gn:feature_code":"PPL",
    "gn:name":"Svinogor",
    "gn:population":0,
    "gn:timezone":"Europe/Kirov",
    "iso:country":"RU",
    "name:rus_x_preferred":[
        "\u0421\u0432\u0438\u043d\u043e\u0433\u043e\u0440"
    ],
    "wof:name":"Svinogor",
    "wof:placetype":"locality"
},
  "geometry": {"coordinates":[50.51218,58.35711],"type":"Point"}
}