{
  "type": "Feature",
  "properties": {
    "gn:admin1_code":"85",
    "gn:asciiname":"Kury",
    "gn:country_code":"RU",
    "gn:dem":130,
    "gn:feature_class":"P",
    "gn:feature_code":"PPL",
    "gn:name":"Kury",
    "gn:population":0,
    "gn:timezone":"Europe/Moscow",
    "iso:country":"RU",
    "name:rus_x_preferred":[
        "\u041a\u0443\u0440\u044b"
    ],
    "name:und_x_variant":[
        "Kuri",
        "Kury",
        "\u041a\u0443\u0440\u044b"
    ],
    "wof:name":"Kury",
    "wof:placetype":"locality"
},
  "geometry": {"coordinates":[36.66799,60.95998],"type":"Point"}
}