{
  "type": "Feature",
  "properties": {
    "gn:admin1_code":"4",
    "gn:asciiname":"Krasnoryazhskiy",
    "gn:country_code":"RU",
    "gn:dem":192,
    "gn:feature_class":"P",
    "gn:feature_code":"PPL",
    "gn:name":"Krasnoryazhskiy",
    "gn:population":0,
    "gn:timezone":"Asia/Barnaul",
    "iso:country":"RU",
    "name:eng_x_preferred":[
        "Krasnoryazhskiy"
    ],
    "name:nor_x_preferred":[
        "Krasnorjazjskij"
    ],
    "name:rus_x_preferred":[
        "\u041a\u0440\u0430\u0441\u043d\u043e\u0440\u044f\u0436\u0441\u043a\u0438\u0439"
    ],
    "wof:name":"Krasnoryazhskiy",
    "wof:placetype":"locality"
},
  "geometry": {"coordinates":[80.98333000000002,53.91667],"type":"Point"}
}