{
  "type": "Feature",
  "properties": {
    "gn:admin1_code":"55",
    "gn:asciiname":"Nizhnyaya Gusikha",
    "gn:country_code":"RU",
    "gn:dem":214,
    "gn:feature_class":"P",
    "gn:feature_code":"PPL",
    "gn:name":"Nizhnyaya Gusikha",
    "gn:population":0,
    "gn:timezone":"Asia/Yekaterinburg",
    "iso:country":"RU",
    "name:rus_x_preferred":[
        "\u041d\u0438\u0436\u043d\u044f\u044f \u0413\u0443\u0441\u0438\u0445\u0430"
    ],
    "wof:name":"Nizhnyaya Gusikha",
    "wof:placetype":"locality"
},
  "geometry": {"coordinates":[54.43333000000001,52.23333],"type":"Point"}
}