{
  "type": "Feature",
  "properties": {
    "gn:admin1_code":"54",
    "gn:asciiname":"Kaygarly",
    "gn:country_code":"RU",
    "gn:dem":45,
    "gn:feature_class":"P",
    "gn:feature_code":"PPL",
    "gn:name":"Kaygarly",
    "gn:population":0,
    "gn:timezone":"Asia/Omsk",
    "iso:country":"RU",
    "name:eng_x_preferred":[
        "Kaygarly"
    ],
    "name:nor_x_preferred":[
        "Kajgarly"
    ],
    "name:rus_x_preferred":[
        "\u041a\u0430\u0439\u0433\u0430\u0440\u043b\u044b"
    ],
    "wof:name":"Kaygarly",
    "wof:placetype":"locality"
},
  "geometry": {"coordinates":[72.905,57.4551],"type":"Point"}
}