{
  "type": "Feature",
  "properties": {
    "gn:admin1_code":"46",
    "gn:asciiname":"Morga",
    "gn:country_code":"RU",
    "gn:dem":178,
    "gn:feature_class":"P",
    "gn:feature_code":"PPL",
    "gn:name":"Morga",
    "gn:population":0,
    "gn:timezone":"Europe/Moscow",
    "iso:country":"RU",
    "name:ara_x_preferred":[
        "\u0645\u0648\u0631\u063a\u0627"
    ],
    "name:arg_x_preferred":[
        "Morga"
    ],
    "name:ast_x_preferred":[
        "Morga"
    ],
    "name:cat_x_preferred":[
        "Morga"
    ],
    "name:ceb_x_preferred":[
        "Morga"
    ],
    "name:eng_x_preferred":[
        "Morga"
    ],
    "name:eus_x_preferred":[
        "Morga"
    ],
    "name:fra_x_preferred":[
        "Morga"
    ],
    "name:glg_x_preferred":[
        "Morga"
    ],
    "name:hun_x_preferred":[
        "Morga"
    ],
    "name:ita_x_preferred":[
        "Morga"
    ],
    "name:msa_x_preferred":[
        "Morga"
    ],
    "name:nld_x_preferred":[
        "Morga"
    ],
    "name:nor_x_preferred":[
        "Morga"
    ],
    "name:oci_x_preferred":[
        "Morga"
    ],
    "name:pol_x_preferred":[
        "Morga"
    ],
    "name:por_x_preferred":[
        "Morga"
    ],
    "name:rus_x_preferred":[
        "\u041c\u043e\u0440\u0433\u0430"
    ],
    "name:sco_x_preferred":[
        "Morga"
    ],
    "name:spa_x_preferred":[
        "Morga"
    ],
    "name:sqi_x_preferred":[
        "Morga"
    ],
    "name:swe_x_preferred":[
        "Morga"
    ],
    "name:ukr_x_preferred":[
        "\u041c\u043e\u0440\u0433\u0430"
    ],
    "name:uzb_x_preferred":[
        "Morga"
    ],
    "name:war_x_preferred":[
        "Morga"
    ],
    "name:zho_x_preferred":[
        "\u83ab\u5c14\u52a0"
    ],
    "wof:name":"Morga",
    "wof:placetype":"locality"
},
  "geometry": {"coordinates":[46.4466,54.40396],"type":"Point"}
}