{
  "type": "Feature",
  "properties": {
    "gn:admin1_code":"46",
    "gn:asciiname":"Morga",
    "gn:country_code":"RU",
    "gn:dem":178,
    "gn:feature_class":"P",
    "gn:feature_code":"PPL",
    "gn:name":"Morga",
    "gn:population":0,
    "gn:timezone":"Europe/Moscow",
    "iso:country":"RU",
    "name:eng_x_preferred":[
        "Morga"
    ],
    "name:nor_x_preferred":[
        "Morga"
    ],
    "name:rus_x_preferred":[
        "\u041c\u043e\u0440\u0433\u0430"
    ],
    "name:und_x_variant":[
        "\u041c\u043e\u0440\u0433\u0430",
        "Morga"
    ],
    "wof:name":"Morga",
    "wof:placetype":"locality"
},
  "geometry": {"coordinates":[46.4466,54.40396],"type":"Point"}
}