{
  "type": "Feature",
  "properties": {
    "gn:admin1_code":"60",
    "gn:asciiname":"Laneva Gora",
    "gn:country_code":"RU",
    "gn:dem":52,
    "gn:feature_class":"P",
    "gn:feature_code":"PPL",
    "gn:name":"Laneva Gora",
    "gn:population":0,
    "gn:timezone":"Europe/Moscow",
    "iso:country":"RU",
    "name:rus_x_preferred":[
        "\u041b\u0430\u043d\u0435\u0432\u0430 \u0413\u043e\u0440\u0430"
    ],
    "wof:name":"Laneva Gora",
    "wof:placetype":"locality"
},
  "geometry": {"coordinates":[28.53896,57.64674],"type":"Point"}
}