{
  "type": "Feature",
  "properties": {
    "gn:admin1_code":"90",
    "gn:asciiname":"Sopino",
    "gn:country_code":"RU",
    "gn:dem":142,
    "gn:feature_class":"P",
    "gn:feature_code":"PPL",
    "gn:name":"Sopino",
    "gn:population":0,
    "gn:timezone":"Asia/Yekaterinburg",
    "iso:country":"RU",
    "name:rus_x_preferred":[
        "\u0421\u043e\u043f\u0438\u043d\u043e"
    ],
    "name:und_x_variant":[
        "Sopina",
        "Sopino"
    ],
    "wof:name":"Sopino",
    "wof:placetype":"locality"
},
  "geometry": {"coordinates":[55.0903,58.7082],"type":"Point"}
}