{
  "type": "Feature",
  "properties": {
    "gn:admin1_code":"43",
    "gn:asciiname":"Popovskiye Dvoriki",
    "gn:country_code":"RU",
    "gn:dem":149,
    "gn:feature_class":"P",
    "gn:feature_code":"PPL",
    "gn:name":"Popovskiye Dvoriki",
    "gn:population":0,
    "gn:timezone":"Europe/Moscow",
    "iso:country":"RU",
    "name:rus_x_preferred":[
        "\u041f\u043e\u043f\u043e\u0432\u0441\u043a\u0438\u0435 \u0414\u0432\u043e\u0440\u0438\u043a\u0438"
    ],
    "wof:name":"Popovskiye Dvoriki",
    "wof:placetype":"locality"
},
  "geometry": {"coordinates":[40.25,52.01667],"type":"Point"}
}