{
  "type": "Feature",
  "properties": {
    "gn:admin1_code":"86.0",
    "gn:asciiname":"Zelenaya Polyana",
    "gn:country_code":"RU",
    "gn:dem":168,
    "gn:feature_class":"P",
    "gn:feature_code":"PPL",
    "gn:name":"Zelenaya Polyana",
    "gn:population":0,
    "gn:timezone":"Europe/Moscow",
    "iso:country":"RU",
    "wof:name":"Zelenaya Polyana",
    "wof:placetype":"locality"
},
  "geometry": {"coordinates":[38.50556,51.44611],"type":"Point"}
}