{
  "type": "Feature",
  "properties": {
    "gn:admin1_code":"90",
    "gn:asciiname":"Spirino",
    "gn:country_code":"RU",
    "gn:dem":158,
    "gn:feature_class":"P",
    "gn:feature_code":"PPL",
    "gn:name":"Spirino",
    "gn:population":0,
    "gn:timezone":"Asia/Yekaterinburg",
    "iso:country":"RU",
    "name:rus_x_preferred":[
        "\u0421\u043f\u0438\u0440\u0438\u043d\u043e"
    ],
    "name:und_x_variant":[
        "Spirina",
        "Spirino"
    ],
    "wof:name":"Spirino",
    "wof:placetype":"locality"
},
  "geometry": {"coordinates":[55.0372,58.9498],"type":"Point"}
}