{
  "type": "Feature",
  "properties": {
    "gn:admin1_code":"30",
    "gn:asciiname":"Bakirka",
    "gn:country_code":"RU",
    "gn:dem":12,
    "gn:feature_class":"P",
    "gn:feature_code":"PPL",
    "gn:name":"Bakirka",
    "gn:population":0,
    "gn:timezone":"Asia/Vladivostok",
    "iso:country":"RU",
    "name:eng_x_preferred":[
        "Bakirka"
    ],
    "name:nor_x_preferred":[
        "Bakirka"
    ],
    "name:rus_x_preferred":[
        "\u0411\u0430\u043a\u0438\u0440\u043a\u0430"
    ],
    "wof:name":"Bakirka",
    "wof:placetype":"locality"
},
  "geometry": {"coordinates":[143.28333000000001,59.48333],"type":"Point"}
}