{
  "type": "Feature",
  "properties": {
    "gn:admin1_code":"6",
    "gn:asciiname":"Klement'evskaya",
    "gn:country_code":"RU",
    "gn:dem":60,
    "gn:feature_class":"P",
    "gn:feature_code":"PPL",
    "gn:name":"Klement\u2019evskaya",
    "gn:population":0,
    "gn:timezone":"Europe/Moscow",
    "iso:country":"RU",
    "name:rus_x_preferred":[
        "\u041a\u043b\u0435\u043c\u0435\u043d\u0442\u044c\u0435\u0432\u0441\u043a\u0430\u044f"
    ],
    "name:und_x_variant":[
        "Yushmanovskaya",
        "Klement\u2019evskaya"
    ],
    "wof:name":"Klement'evskaya",
    "wof:placetype":"locality"
},
  "geometry": {"coordinates":[42.26722,61.76472],"type":"Point"}
}