{
  "type": "Feature",
  "properties": {
    "gn:admin1_code":"7",
    "gn:asciiname":"Svitovka",
    "gn:country_code":"RU",
    "gn:dem":-24,
    "gn:feature_class":"P",
    "gn:feature_code":"PPL",
    "gn:name":"Svitovka",
    "gn:population":0,
    "gn:timezone":"Europe/Astrakhan",
    "iso:country":"RU",
    "name:eng_x_preferred":[
        "Svitovka"
    ],
    "name:nor_x_preferred":[
        "Seitovka"
    ],
    "name:rus_x_preferred":[
        "\u0421\u0435\u0438\u0442\u043e\u0432\u043a\u0430"
    ],
    "wof:name":"Svitovka",
    "wof:placetype":"locality"
},
  "geometry": {"coordinates":[48.08333,46.75],"type":"Point"}
}