{
  "type": "Feature",
  "properties": {
    "gn:admin1_code":"77",
    "gn:asciiname":"Dobritsa",
    "gn:country_code":"RU",
    "gn:dem":156,
    "gn:feature_class":"P",
    "gn:feature_code":"PPL",
    "gn:name":"Dobritsa",
    "gn:population":0,
    "gn:timezone":"Europe/Moscow",
    "iso:country":"RU",
    "name:rus_x_preferred":[
        "\u0414\u043e\u0431\u0440\u0438\u0446\u0430"
    ],
    "wof:name":"Dobritsa",
    "wof:placetype":"locality"
},
  "geometry": {"coordinates":[37.3973,58.4128],"type":"Point"}
}