{
  "type": "Feature",
  "properties": {
    "gn:admin1_code":"8",
    "gn:asciiname":"Koyanovo",
    "gn:country_code":"RU",
    "gn:dem":79,
    "gn:feature_class":"P",
    "gn:feature_code":"PPL",
    "gn:name":"Koyanovo",
    "gn:population":0,
    "gn:timezone":"Asia/Yekaterinburg",
    "iso:country":"RU",
    "name:bak_x_preferred":[
        "\u04a0\u0443\u044f\u043d"
    ],
    "name:che_x_preferred":[
        "\u041a\u043e\u044f\u043d\u043e\u0432\u043e"
    ],
    "name:rus_x_preferred":[
        "\u041a\u043e\u044f\u043d\u043e\u0432\u043e"
    ],
    "name:tat_x_preferred":[
        "\u041a\u0443\u044f\u043d"
    ],
    "name:und_x_variant":[
        "\u041a\u043e\u044f\u043d\u043e\u0432\u043e"
    ],
    "wof:name":"Koyanovo",
    "wof:placetype":"locality"
},
  "geometry": {"coordinates":[55.34056,55.27889],"type":"Point"}
}