{
  "type": "Feature",
  "properties": {
    "gn:admin1_code":"37",
    "gn:asciiname":"Turdiyevo",
    "gn:country_code":"RU",
    "gn:dem":165,
    "gn:feature_class":"P",
    "gn:feature_code":"PPL",
    "gn:name":"Turdiyevo",
    "gn:population":0,
    "gn:timezone":"Europe/Moscow",
    "iso:country":"RU",
    "name:rus_x_preferred":[
        "\u0422\u0443\u0440\u0434\u0438\u0435\u0432\u043e"
    ],
    "name:und_x_variant":[
        "\u0422\u0443\u0440\u0434\u0438\u0435\u0432\u043e",
        "Turgiyevo"
    ],
    "wof:name":"Turdiyevo",
    "wof:placetype":"locality"
},
  "geometry": {"coordinates":[42.5839,58.8853],"type":"Point"}
}