{
  "type": "Feature",
  "properties": {
    "gn:admin1_code":"6",
    "gn:asciiname":"Vandysh",
    "gn:country_code":"RU",
    "gn:dem":77,
    "gn:feature_class":"P",
    "gn:feature_code":"PPL",
    "gn:name":"Vandysh",
    "gn:population":0,
    "gn:timezone":"Europe/Moscow",
    "iso:country":"RU",
    "name:rus_x_preferred":[
        "\u0412\u0430\u043d\u0434\u044b\u0448"
    ],
    "name:und_x_variant":[
        "\u0412\u0430\u043d\u0434\u044b\u0448"
    ],
    "wof:name":"Vandysh",
    "wof:placetype":"locality"
},
  "geometry": {"coordinates":[48.324,61.7234],"type":"Point"}
}