{
  "type": "Feature",
  "properties": {
    "gn:admin1_code":"32",
    "gn:asciiname":"Bobrovskiy",
    "gn:country_code":"RU",
    "gn:dem":46,
    "gn:feature_class":"P",
    "gn:feature_code":"PPL",
    "gn:name":"Bobrovskiy",
    "gn:population":0,
    "gn:timezone":"Asia/Yekaterinburg",
    "iso:country":"RU",
    "name:eng_x_preferred":[
        "Bobrovskiy"
    ],
    "name:nor_x_preferred":[
        "Bobrovskij"
    ],
    "name:rus_x_preferred":[
        "\u0411\u043e\u0431\u0440\u043e\u0432\u0441\u043a\u0438\u0439"
    ],
    "wof:name":"Bobrovskiy",
    "wof:placetype":"locality"
},
  "geometry": {"coordinates":[69.925,59.97167],"type":"Point"}
}