{
  "type": "Feature",
  "properties": {
    "gn:country":"RU",
    "gn:fcode":"PPL",
    "gn:pop":4326,
    "iso:country":"RU",
    "name:eng_x_preferred":[
        "Karagaylinskiy"
    ],
    "name:rus_x_preferred":[
        "\u041a\u0430\u0440\u0430\u0433\u0430\u0439\u043b\u0438\u043d\u0441\u043a\u0438\u0439"
    ],
    "name:rus_x_variant":[
        "\u041a\u0430\u0440\u0430\u0433\u0430\u0439\u043b\u0430"
    ],
    "name:unk_x_variant":[
        "Nizhniye Karagayli"
    ],
    "qs:name":"Karagayla",
    "qs:photos_9r":0,
    "qs:photos_sr":0,
    "qs:pop_sr":"4",
    "wof:name":"Karagayla",
    "wof:placetype":"locality",
    "wof:population":4326
},
  "geometry": {"coordinates":[86.5521,54.172],"type":"Point"}
}