{
  "type": "Feature",
  "properties": {
    "gn:admin1_code":"10",
    "gn:asciiname":"Krutitsa",
    "gn:country_code":"RU",
    "gn:dem":163,
    "gn:feature_class":"P",
    "gn:feature_code":"PPL",
    "gn:name":"Krutitsa",
    "gn:population":0,
    "gn:timezone":"Europe/Moscow",
    "iso:country":"RU",
    "name:rus_x_preferred":[
        "\u041a\u0440\u0443\u0442\u0438\u0446\u0430"
    ],
    "wof:name":"Krutitsa",
    "wof:placetype":"locality"
},
  "geometry": {"coordinates":[33.68389000000001,53.77444000000001],"type":"Point"}
}