{
  "type": "Feature",
  "properties": {
    "gn:admin1_code":"33.0",
    "gn:asciiname":"Zonovy",
    "gn:country_code":"RU",
    "gn:dem":140,
    "gn:feature_class":"P",
    "gn:feature_code":"PPL",
    "gn:name":"Zonovy",
    "gn:population":0,
    "gn:timezone":"Europe/Kirov",
    "iso:country":"RU",
    "name:rus_x_preferred":[
        "\u0417\u043e\u043d\u043e\u0432\u044b"
    ],
    "wof:name":"Zonovy",
    "wof:placetype":"locality"
},
  "geometry": {"coordinates":[48.94549,58.70691],"type":"Point"}
}