{
  "type": "Feature",
  "properties": {
    "gn:admin1_code":"86",
    "gn:asciiname":"Kuchugury",
    "gn:country_code":"RU",
    "gn:dem":171,
    "gn:feature_class":"P",
    "gn:feature_code":"PPL",
    "gn:name":"Kuchugury",
    "gn:population":0,
    "gn:timezone":"Europe/Moscow",
    "iso:country":"RU",
    "name:eng_x_preferred":[
        "Kuchugury"
    ],
    "name:nor_x_preferred":[
        "Kutsjugury"
    ],
    "name:rus_x_preferred":[
        "\u041a\u0443\u0447\u0443\u0433\u0443\u0440\u044b"
    ],
    "name:und_x_variant":[
        "\u041a\u0443\u0447\u0443\u0433\u0443\u0440\u044b",
        "Kuchugury"
    ],
    "wof:name":"Kuchugury",
    "wof:placetype":"locality"
},
  "geometry": {"coordinates":[38.2845,51.6037],"type":"Point"}
}