{
  "type": "Feature",
  "properties": {
    "gn:admin1_code":"8.0",
    "gn:asciiname":"Desyatkino",
    "gn:country_code":"RU",
    "gn:dem":99,
    "gn:feature_class":"P",
    "gn:feature_code":"PPL",
    "gn:name":"Desyatkino",
    "gn:population":0,
    "gn:timezone":"Asia/Yekaterinburg",
    "iso:country":"RU",
    "name:rus_x_preferred":[
        "\u0414\u0435\u0441\u044f\u0442\u043a\u0438\u043d\u043e"
    ],
    "name:und_x_variant":[
        "\u0414\u0435\u0441\u044f\u0442\u043a\u0438\u043d\u043e"
    ],
    "wof:name":"Desyatkino",
    "wof:placetype":"locality"
},
  "geometry": {"coordinates":[55.74368000000001,55.41376],"type":"Point"}
}