{
  "type": "Feature",
  "properties": {
    "gn:admin1_code":"53",
    "gn:asciiname":"Put' Il'icha",
    "gn:country_code":"RU",
    "gn:dem":150,
    "gn:feature_class":"P",
    "gn:feature_code":"PPL",
    "gn:name":"Put\u2019 Il\u2019icha",
    "gn:population":0,
    "gn:timezone":"Asia/Novosibirsk",
    "iso:country":"RU",
    "name:rus_x_preferred":[
        "\u041f\u0443\u0442\u044c \u0418\u043b\u044c\u0438\u0447\u0430"
    ],
    "name:und_x_variant":[
        "Put\u2019 Il\u2019icha",
        "\u041f\u0443\u0442\u044c \u0418\u043b\u044c\u0438\u0447\u0430"
    ],
    "wof:name":"Put' Il'icha",
    "wof:placetype":"locality"
},
  "geometry": {"coordinates":[82.59999999999999,54.83333],"type":"Point"}
}