{
  "type": "Feature",
  "properties": {
    "gn:admin1_code":"64",
    "gn:asciiname":"Travyanaya",
    "gn:country_code":"RU",
    "gn:dem":11,
    "gn:feature_class":"P",
    "gn:feature_code":"PPL",
    "gn:name":"Travyanaya",
    "gn:population":0,
    "gn:timezone":"Asia/Sakhalin",
    "iso:country":"RU",
    "name:und_x_variant":[
        "Shiraishizawa",
        "Shiraishisawa",
        "Travyanaya"
    ],
    "wof:name":"Travyanaya",
    "wof:placetype":"locality"
},
  "geometry": {"coordinates":[142.52992,48.15631],"type":"Point"}
}