{
  "type": "Feature",
  "properties": {
    "gn:admin1_code":"64",
    "gn:asciiname":"Otlivnyy",
    "gn:country_code":"RU",
    "gn:dem":9,
    "gn:feature_class":"P",
    "gn:feature_code":"PPL",
    "gn:name":"Otlivnyy",
    "gn:population":0,
    "gn:timezone":"Asia/Tokyo",
    "iso:country":"RU",
    "name:rus_x_preferred":[
        "\u041e\u0442\u043b\u0438\u0432\u043d\u044b\u0439"
    ],
    "name:und_x_variant":[
        "Guya",
        "Otlivnyy"
    ],
    "wof:name":"Otlivnyy",
    "wof:placetype":"locality"
},
  "geometry": {"coordinates":[147.55000000000001,44.81667],"type":"Point"}
}