{
  "type": "Feature",
  "properties": {
    "gn:admin1_code":"9",
    "gn:asciiname":"Novyy Put'",
    "gn:country_code":"RU",
    "gn:dem":222,
    "gn:feature_class":"P",
    "gn:feature_code":"PPL",
    "gn:name":"Novyy Put\u2019",
    "gn:population":0,
    "gn:timezone":"Europe/Moscow",
    "iso:country":"RU",
    "name:rus_x_preferred":[
        "\u041d\u043e\u0432\u044b\u0439 \u041f\u0443\u0442\u044c"
    ],
    "name:und_x_variant":[
        "Novyy Put\u2019"
    ],
    "wof:name":"Novyy Put'",
    "wof:placetype":"locality"
},
  "geometry": {"coordinates":[38.4932,50.9702],"type":"Point"}
}