{
  "type": "Feature",
  "properties": {
    "gn:admin1_code":"8",
    "gn:asciiname":"Nizhniy Sardyk",
    "gn:country_code":"RU",
    "gn:dem":138,
    "gn:feature_class":"P",
    "gn:feature_code":"PPL",
    "gn:name":"Nizhniy Sardyk",
    "gn:population":0,
    "gn:timezone":"Asia/Yekaterinburg",
    "iso:country":"RU",
    "name:rus_x_preferred":[
        "\u041d\u0438\u0436\u043d\u0438\u0439 \u0421\u0430\u0440\u0434\u044b\u043a"
    ],
    "wof:name":"Nizhniy Sardyk",
    "wof:placetype":"locality"
},
  "geometry": {"coordinates":[53.96785,54.61476],"type":"Point"}
}