{
  "type": "Feature",
  "properties": {
    "gn:admin1_code":"69",
    "gn:asciiname":"Konstantinovo",
    "gn:country_code":"RU",
    "gn:dem":236,
    "gn:feature_class":"P",
    "gn:feature_code":"PPL",
    "gn:name":"Konstantinovo",
    "gn:population":0,
    "gn:timezone":"Europe/Moscow",
    "iso:country":"RU",
    "name:bel_x_preferred":[
        "\u041a\u0430\u043d\u0441\u0442\u0430\u043d\u0446\u0456\u043d\u0430\u0432\u0430"
    ],
    "name:bul_x_preferred":[
        "\u041a\u043e\u043d\u0441\u0442\u0430\u043d\u0442\u0438\u043d\u043e\u0432\u043e"
    ],
    "name:ceb_x_preferred":[
        "Konstantinovo"
    ],
    "name:est_x_preferred":[
        "Konstantinovo"
    ],
    "name:fra_x_preferred":[
        "Konstantinovo"
    ],
    "name:ron_x_preferred":[
        "Konstantinovo"
    ],
    "name:rus_x_preferred":[
        "\u041a\u043e\u043d\u0441\u0442\u0430\u043d\u0442\u0438\u043d\u043e\u0432\u043e"
    ],
    "name:swe_x_preferred":[
        "Konstantinovo"
    ],
    "name:ukr_x_preferred":[
        "\u041a\u043e\u043d\u0441\u0442\u0430\u043d\u0442\u0438\u043d\u043e\u0432\u043e"
    ],
    "name:und_x_variant":[
        "\u041a\u043e\u043d\u0441\u0442\u0430\u043d\u0442\u0438\u043d\u043e\u0432\u043e"
    ],
    "wof:name":"Konstantinovo",
    "wof:placetype":"locality"
},
  "geometry": {"coordinates":[33.82861,55.46167],"type":"Point"}
}