{
  "type": "Feature",
  "properties": {
    "gn:admin1_code":"80.0",
    "gn:asciiname":"Kolbenki",
    "gn:country_code":"RU",
    "gn:dem":217,
    "gn:feature_class":"P",
    "gn:feature_code":"PPL",
    "gn:name":"Kolbenki",
    "gn:population":0,
    "gn:timezone":"Europe/Samara",
    "iso:country":"RU",
    "name:rus_x_preferred":[
        "\u041a\u043e\u043b\u0431\u0435\u043d\u043a\u0438"
    ],
    "wof:name":"Kolbenki",
    "wof:placetype":"locality"
},
  "geometry": {"coordinates":[52.2235,57.7797],"type":"Point"}
}