{
  "type": "Feature",
  "properties": {
    "gn:admin1_code":"77",
    "gn:asciiname":"Ozhibokovo",
    "gn:country_code":"RU",
    "gn:dem":165,
    "gn:feature_class":"P",
    "gn:feature_code":"PPL",
    "gn:name":"Ozhibokovo",
    "gn:population":0,
    "gn:timezone":"Europe/Moscow",
    "iso:country":"RU",
    "name:rus_x_preferred":[
        "\u041e\u0436\u0438\u0431\u043e\u043a\u043e\u0432\u043e"
    ],
    "name:und_x_variant":[
        "Ozhibakovo",
        "Ozhibokovo"
    ],
    "wof:name":"Ozhibokovo",
    "wof:placetype":"locality"
},
  "geometry": {"coordinates":[34.58493,56.18386],"type":"Point"}
}