{
  "type": "Feature",
  "properties": {
    "gn:admin1_code":"25.0",
    "gn:asciiname":"Gremyachevka",
    "gn:country_code":"RU",
    "gn:dem":197,
    "gn:feature_class":"P",
    "gn:feature_code":"PPL",
    "gn:name":"Gremyach\u00ebvka",
    "gn:population":0,
    "gn:timezone":"Europe/Moscow",
    "iso:country":"RU",
    "name:rus_x_preferred":[
        "\u0413\u0440\u0435\u043c\u044f\u0447\u0451\u0432\u043a\u0430"
    ],
    "name:und_x_variant":[
        "Gremyach\u00ebvka",
        "\u0413\u0440\u0435\u043c\u044f\u0447\u0451\u0432\u043a\u0430"
    ],
    "wof:name":"Gremyachevka",
    "wof:placetype":"locality"
},
  "geometry": {"coordinates":[34.9383,54.02818000000001],"type":"Point"}
}