{
  "type": "Feature",
  "properties": {
    "iso:country":"RU",
    "ne:ADM0CAP":0.0,
    "ne:ADM0NAME":"Russia",
    "ne:ADM0_A3":"RUS",
    "ne:ADM1NAME":"Chita",
    "ne:ADMIN1_COD":0,
    "ne:CAPALT":0,
    "ne:CHANGED":0,
    "ne:CHECKME":0,
    "ne:COMPARE":0,
    "ne:DIFFASCII":0,
    "ne:ELEVATION":0.0,
    "ne:FEATURECLA":"Populated place",
    "ne:GEONAMEID":-1,
    "ne:GEONAMESNO":"No GeoNames match due to small population, not in GeoNames, or poor NEV placement.",
    "ne:GN_POP":0,
    "ne:GTOPO30":0.0,
    "ne:ISO_A2":"RU",
    "ne:LABELRANK":2,
    "ne:LATITUDE":50.530597,
    "ne:LONGITUDE":116.300642,
    "ne:LS_MATCH":1,
    "ne:LS_NAME":"Sherlovaya Gora",
    "ne:MAX_AREAKM":1.0,
    "ne:MAX_AREAMI":0.0,
    "ne:MAX_BBXMAX":116.308333,
    "ne:MAX_BBXMIN":116.291667,
    "ne:MAX_BBYMAX":50.533333,
    "ne:MAX_BBYMIN":50.525,
    "ne:MAX_NATSCA":10.0,
    "ne:MAX_PERKM":5.0,
    "ne:MAX_PERMI":3.0,
    "ne:MAX_POP10":411,
    "ne:MAX_POP20":0,
    "ne:MAX_POP300":0,
    "ne:MAX_POP310":0,
    "ne:MAX_POP50":0,
    "ne:MEAN_BBXC":116.3,
    "ne:MEAN_BBYC":50.529167,
    "ne:MEGACITY":0,
    "ne:MIN_AREAKM":1.0,
    "ne:MIN_AREAMI":0.0,
    "ne:MIN_BBXMAX":116.308333,
    "ne:MIN_BBXMIN":116.291667,
    "ne:MIN_BBYMAX":50.533333,
    "ne:MIN_BBYMIN":50.525,
    "ne:MIN_PERKM":5.0,
    "ne:MIN_PERMI":3.0,
    "ne:NAME":"Sherlovaya Gora",
    "ne:NAMEASCII":"Sherlovaya Gora",
    "ne:NAMEDIFF":0,
    "ne:NATSCALE":10,
    "ne:POP1950":0,
    "ne:POP1955":0,
    "ne:POP1960":0,
    "ne:POP1965":0,
    "ne:POP1970":0,
    "ne:POP1975":0,
    "ne:POP1980":0,
    "ne:POP1985":0,
    "ne:POP1990":0,
    "ne:POP1995":0,
    "ne:POP2000":0,
    "ne:POP2005":0,
    "ne:POP2010":0,
    "ne:POP2015":0,
    "ne:POP2020":0,
    "ne:POP2025":0,
    "ne:POP2050":0,
    "ne:POP_MAX":411,
    "ne:POP_MIN":411,
    "ne:POP_OTHER":411,
    "ne:RANK_MAX":2,
    "ne:RANK_MIN":2,
    "ne:SCALERANK":8,
    "ne:SOV0NAME":"Russia",
    "ne:SOV_A3":"RUS",
    "ne:UN_FID":0,
    "ne:UN_LAT":0.0,
    "ne:UN_LONG":0.0,
    "ne:WORLDCITY":0,
    "ne:min_zoom":7.0,
    "wof:name":"Sherlovaya Gora",
    "wof:placetype":"locality"
},
  "geometry": {"coordinates":[116.30064245510528,50.53059653635142],"type":"Point"}
}