{
  "type": "Feature",
  "properties": {
    "gn:country":"RU",
    "gn:fcode":"PPL",
    "gn:population":0,
    "iso:country":"RU",
    "name:che_x_preferred":[
        "\u041d\u0438\u043a\u0438\u0442\u0441\u043a\u043e\u0435"
    ],
    "name:eng_x_preferred":[
        "Nikitskoye"
    ],
    "name:eng_x_variant":[
        "Nikitskoe estate"
    ],
    "name:nor_x_preferred":[
        "Nikitskoje"
    ],
    "name:rus_x_preferred":[
        "\u041d\u0438\u043a\u0438\u0442\u0441\u043a\u043e\u0435"
    ],
    "qs:name":"Nikitskoye",
    "qs:name_adm0":"Russia",
    "qs:name_adm1":"Moscow Oblast",
    "qs:photos_9r":0,
    "qs:photos_sr":0,
    "qs:placetype":"Town",
    "qs:pop_sr":"0",
    "wof:name":"Nikitskoye",
    "wof:placetype":"locality",
    "wof:population":0
},
  "geometry": {"coordinates":[38.46518,55.30232],"type":"Point"}
}