{
  "type": "Feature",
  "properties": {
    "gn:admin1_code":"28",
    "gn:asciiname":"Vyatikkya",
    "gn:country_code":"RU",
    "gn:dem":12,
    "gn:feature_class":"P",
    "gn:feature_code":"PPL",
    "gn:name":"Vyatikkya",
    "gn:population":0,
    "gn:timezone":"Europe/Moscow",
    "iso:country":"RU",
    "name:fin_x_preferred":[
        "V\u00e4tikk\u00e4"
    ],
    "wof:name":"Vyatikkya",
    "wof:placetype":"locality"
},
  "geometry": {"coordinates":[30.05718,61.29293000000001],"type":"Point"}
}