{
  "type": "Feature",
  "properties": {
    "gn:admin1_code":"42",
    "gn:asciiname":"Tipanovo",
    "gn:cc2":"RU",
    "gn:country_code":"RU",
    "gn:dem":32,
    "gn:feature_class":"P",
    "gn:feature_code":"PPL",
    "gn:name":"Tipanovo",
    "gn:population":0,
    "gn:timezone":"Europe/Moscow",
    "iso:country":"RU",
    "name:fin_x_preferred":[
        "Vilakkala"
    ],
    "name:und_x_variant":[
        "Vilakkalo",
        "Tipanovo"
    ],
    "wof:name":"Tipanovo",
    "wof:placetype":"locality"
},
  "geometry": {"coordinates":[30.40226,60.65871],"type":"Point"}
}