{
  "type": "Feature",
  "properties": {
    "gn:admin1_code":"91.0",
    "gn:asciiname":"Imisskaya Baza",
    "gn:country_code":"RU",
    "gn:dem":330,
    "gn:feature_class":"P",
    "gn:feature_code":"PPL",
    "gn:name":"Imisskaya Baza",
    "gn:population":0,
    "gn:timezone":"Asia/Krasnoyarsk",
    "iso:country":"RU",
    "name:rus_x_preferred":[
        "\u0418\u043c\u0438\u0441\u0441\u043a\u0430\u044f \u0411\u0430\u0437\u0430"
    ],
    "wof:name":"Imisskaya Baza",
    "wof:placetype":"locality"
},
  "geometry": {"coordinates":[93.1935,53.9393],"type":"Point"}
}