{
  "type": "Feature",
  "properties": {
    "gn:admin1_code":"60",
    "gn:asciiname":"Poshchupino",
    "gn:country_code":"RU",
    "gn:dem":64,
    "gn:feature_class":"P",
    "gn:feature_code":"PPL",
    "gn:name":"Poshchupino",
    "gn:population":0,
    "gn:timezone":"Europe/Moscow",
    "iso:country":"RU",
    "name:rus_x_preferred":[
        "\u041f\u043e\u0449\u0443\u043f\u0438\u043d\u043e"
    ],
    "wof:name":"Poshchupino",
    "wof:placetype":"locality"
},
  "geometry": {"coordinates":[28.02732,57.28777],"type":"Point"}
}