{
  "type": "Feature",
  "properties": {
    "gn:admin1_code":"52",
    "gn:asciiname":"Shapkino",
    "gn:country_code":"RU",
    "gn:dem":42,
    "gn:feature_class":"P",
    "gn:feature_code":"PPL",
    "gn:name":"Shapkino",
    "gn:population":0,
    "gn:timezone":"Europe/Moscow",
    "iso:country":"RU",
    "name:rus_x_preferred":[
        "\u0428\u0430\u043f\u043a\u0438\u043d\u043e"
    ],
    "name:und_x_variant":[
        "\u0428\u0430\u043f\u043a\u0438\u043d\u043e"
    ],
    "wof:name":"Shapkino",
    "wof:placetype":"locality"
},
  "geometry": {"coordinates":[31.45315,57.83618000000001],"type":"Point"}
}