{
  "type": "Feature",
  "properties": {
    "gn:admin1_code":"10",
    "gn:asciiname":"Terebikovo",
    "gn:cc2":"RU",
    "gn:country_code":"RU",
    "gn:dem":171,
    "gn:feature_class":"P",
    "gn:feature_code":"PPL",
    "gn:name":"Terebikovo",
    "gn:population":0,
    "gn:timezone":"Europe/Moscow",
    "iso:country":"RU",
    "name:rus_x_preferred":[
        "\u0422\u0435\u0440\u0435\u0431\u0438\u043a\u043e\u0432\u043e"
    ],
    "name:und_x_variant":[
        "Terebikova",
        "Terebikovo"
    ],
    "wof:name":"Terebikovo",
    "wof:placetype":"locality"
},
  "geometry": {"coordinates":[34.2725,52.3625],"type":"Point"}
}