{
  "type": "Feature",
  "properties": {
    "gn:admin1_code":"4",
    "gn:asciiname":"Tretiy Internatsional",
    "gn:country_code":"RU",
    "gn:dem":214,
    "gn:feature_class":"P",
    "gn:feature_code":"PPL",
    "gn:name":"Tretiy Internatsional",
    "gn:population":0,
    "gn:timezone":"Asia/Barnaul",
    "iso:country":"RU",
    "name:rus_x_preferred":[
        "\u0422\u0440\u0435\u0442\u0438\u0439 \u0418\u043d\u0442\u0435\u0440\u043d\u0430\u0446\u0438\u043e\u043d\u0430\u043b"
    ],
    "wof:name":"Tretiy Internatsional",
    "wof:placetype":"locality"
},
  "geometry": {"coordinates":[81.5959,53.8818],"type":"Point"}
}