{
  "type": "Feature",
  "properties": {
    "gn:admin1_code":"5.0",
    "gn:asciiname":"Belousovka",
    "gn:country_code":"RU",
    "gn:dem":148,
    "gn:feature_class":"P",
    "gn:feature_code":"PPL",
    "gn:name":"Belousovka",
    "gn:population":0,
    "gn:timezone":"Asia/Yakutsk",
    "iso:country":"RU",
    "name:che_x_preferred":[
        "\u0411\u0435\u043b\u043e\u0443\u0441\u043e\u0432\u043a\u0430"
    ],
    "name:rus_x_preferred":[
        "\u0411\u0435\u043b\u043e\u0443\u0441\u043e\u0432\u043a\u0430"
    ],
    "wof:name":"Belousovka",
    "wof:placetype":"locality"
},
  "geometry": {"coordinates":[128.10366999999999,50.98966],"type":"Point"}
}