{
  "type": "Feature",
  "properties": {
    "gn:admin1_code":"60.0",
    "gn:asciiname":"Berdyshi",
    "gn:country_code":"RU",
    "gn:dem":74,
    "gn:feature_class":"P",
    "gn:feature_code":"PPL",
    "gn:name":"Berdyshi",
    "gn:population":0,
    "gn:timezone":"Europe/Moscow",
    "iso:country":"RU",
    "name:nor_x_preferred":[
        "Berdysji"
    ],
    "name:rus_x_preferred":[
        "\u0411\u0435\u0440\u0434\u044b\u0448\u0438"
    ],
    "wof:name":"Berdyshi",
    "wof:placetype":"locality"
},
  "geometry": {"coordinates":[28.12056,57.00338000000001],"type":"Point"}
}