{
  "type": "Feature",
  "properties": {
    "gn:admin1_code":"44",
    "gn:asciiname":"Topkiy",
    "gn:cc2":"RU",
    "gn:country_code":"RU",
    "gn:dem":1064,
    "gn:feature_class":"P",
    "gn:feature_code":"PPL",
    "gn:name":"Topkiy",
    "gn:population":0,
    "gn:timezone":"Asia/Magadan",
    "iso:country":"RU",
    "name:und_x_variant":[
        "Topkii",
        "Topikiy",
        "Topkiy"
    ],
    "wof:name":"Topkiy",
    "wof:placetype":"locality"
},
  "geometry": {"coordinates":[147.51667,62.91667],"type":"Point"}
}