{
  "type": "Feature",
  "properties": {
    "gn:admin1_code":"90",
    "gn:asciiname":"Novaya Ivanovka",
    "gn:country_code":"RU",
    "gn:dem":121,
    "gn:feature_class":"P",
    "gn:feature_code":"PPL",
    "gn:name":"Novaya Ivanovka",
    "gn:population":0,
    "gn:timezone":"Asia/Yekaterinburg",
    "iso:country":"RU",
    "name:rus_x_preferred":[
        "\u041d\u043e\u0432\u0430\u044f \u0418\u0432\u0430\u043d\u043e\u0432\u043a\u0430"
    ],
    "wof:name":"Novaya Ivanovka",
    "wof:placetype":"locality"
},
  "geometry": {"coordinates":[55.8405,58.115],"type":"Point"}
}