{
  "type": "Feature",
  "properties": {
    "gn:admin1_code":"47",
    "gn:asciiname":"Valuchiki",
    "gn:country_code":"RU",
    "gn:dem":153,
    "gn:feature_class":"P",
    "gn:feature_code":"PPL",
    "gn:name":"Valuchiki",
    "gn:population":0,
    "gn:timezone":"Europe/Moscow",
    "iso:country":"RU",
    "name:rus_x_preferred":[
        "\u0412\u0430\u043b\u0443\u0447\u0438\u043a\u0438"
    ],
    "wof:name":"Valuchiki",
    "wof:placetype":"locality"
},
  "geometry": {"coordinates":[36.1124,56.1606],"type":"Point"}
}