{
  "type": "Feature",
  "properties": {
    "gn:admin1_code":"67",
    "gn:asciiname":"Kukino",
    "gn:cc2":"RU",
    "gn:country_code":"RU",
    "gn:dem":66,
    "gn:feature_class":"P",
    "gn:feature_code":"PPL",
    "gn:name":"Kukino",
    "gn:population":0,
    "gn:timezone":"Europe/Saratov",
    "iso:country":"RU",
    "name:rus_x_preferred":[
        "\u041a\u0443\u043a\u0438\u043d\u043e"
    ],
    "name:und_x_variant":[
        "Put\u2019 Novoy Zhizn",
        "Kukino",
        "\u041a\u0443\u043a\u0438\u043d\u043e"
    ],
    "wof:name":"Kukino",
    "wof:placetype":"locality"
},
  "geometry": {"coordinates":[47.25,50.61667],"type":"Point"}
}