{
  "type": "Feature",
  "properties": {
    "gn:admin1_code":"9.0",
    "gn:asciiname":"Golofeyevka",
    "gn:country_code":"RU",
    "gn:dem":112,
    "gn:feature_class":"P",
    "gn:feature_code":"PPL",
    "gn:name":"Golofeyevka",
    "gn:population":0,
    "gn:timezone":"Europe/Moscow",
    "iso:country":"RU",
    "name:rus_x_preferred":[
        "\u0413\u043e\u043b\u043e\u0444\u0435\u0435\u0432\u043a\u0430"
    ],
    "wof:name":"Golofeyevka",
    "wof:placetype":"locality"
},
  "geometry": {"coordinates":[37.9344,50.3726],"type":"Point"}
}