{
  "type": "Feature",
  "properties": {
    "gn:admin1_code":"37",
    "gn:asciiname":"Khlyabishino",
    "gn:country_code":"RU",
    "gn:dem":137,
    "gn:feature_class":"P",
    "gn:feature_code":"PPL",
    "gn:name":"Khlyabishino",
    "gn:population":0,
    "gn:timezone":"Europe/Moscow",
    "iso:country":"RU",
    "name:rus_x_preferred":[
        "\u0425\u043b\u044f\u0431\u0438\u0448\u0438\u043d\u043e"
    ],
    "name:und_x_variant":[
        "\u0425\u043b\u044f\u0431\u0438\u0448\u0438\u043d\u043e"
    ],
    "wof:name":"Khlyabishino",
    "wof:placetype":"locality"
},
  "geometry": {"coordinates":[44.29468,58.11429],"type":"Point"}
}