{
  "type": "Feature",
  "properties": {
    "gn:admin1_code":"13",
    "gn:asciiname":"Annenskoye",
    "gn:country_code":"RU",
    "gn:dem":325,
    "gn:feature_class":"P",
    "gn:feature_code":"PPL",
    "gn:name":"Annenskoye",
    "gn:population":0,
    "gn:timezone":"Asia/Yekaterinburg",
    "iso:country":"RU",
    "name:eng_x_preferred":[
        "Annenskoye"
    ],
    "name:nor_x_preferred":[
        "Annenskoje"
    ],
    "name:rus_x_preferred":[
        "\u0410\u043d\u043d\u0435\u043d\u0441\u043a\u043e\u0435"
    ],
    "name:und_x_variant":[
        "Annenskiy",
        "\u0410\u043d\u043d\u0435\u043d\u0441\u043a\u043e\u0435",
        "Annenskoye"
    ],
    "wof:name":"Annenskoye",
    "wof:placetype":"locality"
},
  "geometry": {"coordinates":[60.37791,53.12029],"type":"Point"}
}