{
  "type": "Feature",
  "properties": {
    "gn:admin1_code":"23",
    "gn:asciiname":"Mezhrech'ye",
    "gn:country_code":"RU",
    "gn:dem":112,
    "gn:feature_class":"P",
    "gn:feature_code":"PPL",
    "gn:name":"Mezhrech\u2019ye",
    "gn:population":0,
    "gn:timezone":"Europe/Kaliningrad",
    "iso:country":"RU",
    "name:rus_x_preferred":[
        "\u041c\u0435\u0436\u0440\u0435\u0447\u044c\u0435"
    ],
    "name:und_x_variant":[
        "Mezhdurech\u2019ye",
        "Mezhrech\u2019ye",
        "\u041c\u0435\u0436\u0440\u0435\u0447\u044c\u0435"
    ],
    "wof:name":"Mezhrech'ye",
    "wof:placetype":"locality"
},
  "geometry": {"coordinates":[21.99043,54.3712],"type":"Point"}
}