{
  "type": "Feature",
  "properties": {
    "gn:admin1_code":"28",
    "gn:asciiname":"Nemozero",
    "gn:country_code":"RU",
    "gn:dem":172,
    "gn:feature_class":"P",
    "gn:feature_code":"PPL",
    "gn:name":"Nemozero",
    "gn:population":0,
    "gn:timezone":"Europe/Moscow",
    "iso:country":"RU",
    "name:rus_x_preferred":[
        "\u041d\u0435\u043c\u043e\u0437\u0435\u0440\u043e"
    ],
    "name:und_x_variant":[
        "Hemj\u00e4rvi",
        "Nemozero"
    ],
    "wof:name":"Nemozero",
    "wof:placetype":"locality"
},
  "geometry": {"coordinates":[36.44309000000001,62.56708],"type":"Point"}
}