{
  "type": "Feature",
  "properties": {
    "gn:admin1_code":"52",
    "gn:asciiname":"Lapustino",
    "gn:country_code":"RU",
    "gn:dem":178,
    "gn:feature_class":"P",
    "gn:feature_code":"PPL",
    "gn:name":"Lapustino",
    "gn:population":0,
    "gn:timezone":"Europe/Moscow",
    "iso:country":"RU",
    "name:eng_x_preferred":[
        "Lapustino"
    ],
    "name:nor_x_preferred":[
        "Lapustino"
    ],
    "name:rus_x_preferred":[
        "\u041b\u0430\u043f\u0443\u0441\u0442\u0438\u043d\u043e"
    ],
    "name:und_x_variant":[
        "\u041b\u0430\u043f\u0443\u0441\u0442\u0438\u043d\u043e",
        "Lapustino"
    ],
    "wof:name":"Lapustino",
    "wof:placetype":"locality"
},
  "geometry": {"coordinates":[32.87733,58.42464],"type":"Point"}
}