{
  "type": "Feature",
  "properties": {
    "gn:admin1_code":"90",
    "gn:asciiname":"Vaksa",
    "gn:country_code":"RU",
    "gn:dem":171,
    "gn:feature_class":"P",
    "gn:feature_code":"PPL",
    "gn:name":"Vaksa",
    "gn:population":0,
    "gn:timezone":"Asia/Yekaterinburg",
    "iso:country":"RU",
    "name:rus_x_preferred":[
        "\u0412\u0430\u043a\u0441\u0430"
    ],
    "wof:name":"Vaksa",
    "wof:placetype":"locality"
},
  "geometry": {"coordinates":[57.425,57.894],"type":"Point"}
}