{
  "type": "Feature",
  "properties": {
    "gn:admin1_code":"29",
    "gn:asciiname":"Zolotovinka",
    "gn:country_code":"RU",
    "gn:dem":341,
    "gn:feature_class":"P",
    "gn:feature_code":"PPL",
    "gn:name":"Zolotovinka",
    "gn:population":0,
    "gn:timezone":"Asia/Novokuznetsk",
    "iso:country":"RU",
    "name:rus_x_preferred":[
        "\u0417\u043e\u043b\u043e\u0442\u043e\u0432\u0438\u043d\u043a\u0430"
    ],
    "wof:name":"Zolotovinka",
    "wof:placetype":"locality"
},
  "geometry": {"coordinates":[85.3946,54.3697],"type":"Point"}
}