{
  "type": "Feature",
  "properties": {
    "gn:admin1_code":"43",
    "gn:asciiname":"Kazeyevo",
    "gn:country_code":"RU",
    "gn:dem":191,
    "gn:feature_class":"P",
    "gn:feature_code":"PPL",
    "gn:name":"Kazeyevo",
    "gn:population":0,
    "gn:timezone":"Europe/Moscow",
    "iso:country":"RU",
    "name:rus_x_preferred":[
        "\u041a\u0430\u0437\u0435\u0435\u0432\u043e"
    ],
    "name:und_x_variant":[
        "\u041a\u0430\u0437\u0435\u0435\u0432\u043e"
    ],
    "wof:name":"Kazeyevo",
    "wof:placetype":"locality"
},
  "geometry": {"coordinates":[38.26300000000001,52.57592],"type":"Point"}
}