{
  "type": "Feature",
  "properties": {
    "gn:admin1_code":"77",
    "gn:asciiname":"Krasnaya Znamya",
    "gn:country_code":"RU",
    "gn:dem":150,
    "gn:feature_class":"P",
    "gn:feature_code":"PPL",
    "gn:name":"Krasnaya Znamya",
    "gn:population":0,
    "gn:timezone":"Europe/Moscow",
    "iso:country":"RU",
    "name:rus_x_preferred":[
        "\u041a\u0440\u0430\u0441\u043d\u0430\u044f \u0417\u043d\u0430\u043c\u044f"
    ],
    "name:und_x_variant":[
        "\u041a\u0440\u0430\u0441\u043d\u0430\u044f \u0417\u043d\u0430\u043c\u044f"
    ],
    "wof:name":"Krasnaya Znamya",
    "wof:placetype":"locality"
},
  "geometry": {"coordinates":[36.9783,57.4671],"type":"Point"}
}