{
  "type": "Feature",
  "properties": {
    "gn:admin1_code":"24.0",
    "gn:asciiname":"Akhnud",
    "gn:country_code":"RU",
    "gn:dem":65,
    "gn:feature_class":"P",
    "gn:feature_code":"PPL",
    "gn:name":"Akhnud",
    "gn:population":0,
    "gn:timezone":"Europe/Moscow",
    "iso:country":"RU",
    "name:eng_x_preferred":[
        "Akhnud"
    ],
    "name:nor_x_preferred":[
        "Akhnud"
    ],
    "name:rus_x_preferred":[
        "\u0410\u0445\u043d\u0443\u0434"
    ],
    "name:und_x_variant":[
        "Ikituktun Vtoroy",
        "Lapino",
        "Vtoroy Ikituktun",
        "Lapin"
    ],
    "wof:name":"Akhnud",
    "wof:placetype":"locality"
},
  "geometry": {"coordinates":[42.06361,46.21639],"type":"Point"}
}