{
  "type": "Feature",
  "properties": {
    "gn:admin1_code":"88",
    "gn:asciiname":"Biserovo",
    "gn:country_code":"RU",
    "gn:dem":127,
    "gn:feature_class":"P",
    "gn:feature_code":"PPL",
    "gn:name":"Biserovo",
    "gn:population":0,
    "gn:timezone":"Europe/Moscow",
    "iso:country":"RU",
    "name:rus_x_preferred":[
        "\u0411\u0438\u0441\u0435\u0440\u043e\u0432\u043e"
    ],
    "wof:name":"Biserovo",
    "wof:placetype":"locality"
},
  "geometry": {"coordinates":[39.99148,57.76011],"type":"Point"}
}