{
  "type": "Feature",
  "properties": {
    "gn:admin1_code":"29",
    "gn:asciiname":"Bungur",
    "gn:country_code":"RU",
    "gn:dem":241,
    "gn:feature_class":"P",
    "gn:feature_code":"PPL",
    "gn:name":"Bungur",
    "gn:population":0,
    "gn:timezone":"Asia/Novokuznetsk",
    "iso:country":"RU",
    "name:eng_x_preferred":[
        "Bungur"
    ],
    "name:nor_x_preferred":[
        "Bungur"
    ],
    "name:rus_x_preferred":[
        "\u0411\u0443\u043d\u0433\u0443\u0440"
    ],
    "name:und_x_variant":[
        "Bungurskaya",
        "\u0411\u0443\u043d\u0433\u0443\u0440",
        "Bungur"
    ],
    "wof:name":"Bungur",
    "wof:placetype":"locality"
},
  "geometry": {"coordinates":[87.03959999999999,53.7499],"type":"Point"}
}