{
  "type": "Feature",
  "properties": {
    "gn:admin1_code":"86",
    "gn:asciiname":"Khlopotnoye",
    "gn:country_code":"RU",
    "gn:dem":159,
    "gn:feature_class":"P",
    "gn:feature_code":"PPL",
    "gn:name":"Khlopotnoye",
    "gn:population":0,
    "gn:timezone":"Europe/Moscow",
    "iso:country":"RU",
    "name:rus_x_preferred":[
        "\u0425\u043b\u043e\u043f\u043e\u0442\u043d\u043e\u0435"
    ],
    "name:und_x_variant":[
        "Sanbikino",
        "Khlopotnoy",
        "Khlopotnoye"
    ],
    "wof:name":"Khlopotnoye",
    "wof:placetype":"locality"
},
  "geometry": {"coordinates":[39.7822,51.76344],"type":"Point"}
}