{
  "type": "Feature",
  "properties": {
    "gn:admin1_code":"41",
    "gn:asciiname":"Klennaya",
    "gn:country_code":"RU",
    "gn:dem":158,
    "gn:feature_class":"P",
    "gn:feature_code":"PPL",
    "gn:name":"Kl\u00ebnnaya",
    "gn:population":0,
    "gn:timezone":"Europe/Moscow",
    "iso:country":"RU",
    "name:rus_x_preferred":[
        "\u041a\u043b\u0451\u043d\u043d\u0430\u044f"
    ],
    "name:und_x_variant":[
        "Kl\u00ebnaya",
        "Kl\u00ebnnaya"
    ],
    "wof:name":"Klennaya",
    "wof:placetype":"locality"
},
  "geometry": {"coordinates":[34.6903,51.6843],"type":"Point"}
}