{
  "type": "Feature",
  "properties": {
    "gn:admin1_code":"33",
    "gn:asciiname":"Romashonki",
    "gn:country_code":"RU",
    "gn:dem":156,
    "gn:feature_class":"P",
    "gn:feature_code":"PPL",
    "gn:name":"Romashonki",
    "gn:population":0,
    "gn:timezone":"Europe/Kirov",
    "iso:country":"RU",
    "name:rus_x_preferred":[
        "\u0420\u043e\u043c\u0430\u0448\u043e\u043d\u043a\u0438"
    ],
    "name:und_x_variant":[
        "Romashenki",
        "Romashonki"
    ],
    "wof:name":"Romashonki",
    "wof:placetype":"locality"
},
  "geometry": {"coordinates":[49.05831,57.40839],"type":"Point"}
}