{
  "type": "Feature",
  "properties": {
    "gn:admin1_code":"62",
    "gn:asciiname":"Nyukhovets",
    "gn:country_code":"RU",
    "gn:dem":188,
    "gn:feature_class":"P",
    "gn:feature_code":"PPL",
    "gn:name":"Nyukhovets",
    "gn:population":0,
    "gn:timezone":"Europe/Moscow",
    "iso:country":"RU",
    "name:rus_x_preferred":[
        "\u041d\u044e\u0445\u043e\u0432\u0435\u0446"
    ],
    "wof:name":"Nyukhovets",
    "wof:placetype":"locality"
},
  "geometry": {"coordinates":[39.09014000000001,53.93013000000001],"type":"Point"}
}