{
  "type": "Feature",
  "properties": {
    "gn:admin1_code":"80.0",
    "gn:asciiname":"Kucher-Kopki",
    "gn:country_code":"RU",
    "gn:dem":141,
    "gn:feature_class":"P",
    "gn:feature_code":"PPL",
    "gn:name":"Kucher-Kopki",
    "gn:population":0,
    "gn:timezone":"Europe/Samara",
    "iso:country":"RU",
    "name:rus_x_preferred":[
        "\u041a\u0443\u0447\u0435\u0440-\u041a\u043e\u043f\u043a\u0438"
    ],
    "wof:name":"Kucher-Kopki",
    "wof:placetype":"locality"
},
  "geometry": {"coordinates":[51.8177,57.3592],"type":"Point"}
}