{
  "type": "Feature",
  "properties": {
    "gn:admin1_code":"59",
    "gn:asciiname":"Ignat'yevka",
    "gn:country_code":"RU",
    "gn:dem":77,
    "gn:feature_class":"P",
    "gn:feature_code":"PPL",
    "gn:name":"Ignat\u2019yevka",
    "gn:population":0,
    "gn:timezone":"Asia/Vladivostok",
    "iso:country":"RU",
    "name:eng_x_preferred":[
        "Ignat'yevka"
    ],
    "name:nor_x_preferred":[
        "Ignatjevka"
    ],
    "name:rus_x_preferred":[
        "\u0418\u0433\u043d\u0430\u0442\u044c\u0435\u0432\u043a\u0430"
    ],
    "name:und_x_variant":[
        "Ignatovka",
        "Ignat\u2019yevka"
    ],
    "wof:name":"Ignat'yevka",
    "wof:placetype":"locality"
},
  "geometry": {"coordinates":[134.13583,46.4072],"type":"Point"}
}