{
  "type": "Feature",
  "properties": {
    "gn:admin1_code":"17.0",
    "gn:asciiname":"Gamiyakh",
    "gn:country_code":"RU",
    "gn:dem":222,
    "gn:feature_class":"P",
    "gn:feature_code":"PPL",
    "gn:name":"Gamiyakh",
    "gn:population":0,
    "gn:timezone":"Europe/Moscow",
    "iso:country":"RU",
    "name:rus_x_preferred":[
        "\u0413\u0430\u043c\u0438\u044f\u0445"
    ],
    "name:und_x_variant":[
        "Minay-Tugay",
        "Gamiakh",
        "Gamiyakh"
    ],
    "wof:name":"Gamiyakh",
    "wof:placetype":"locality"
},
  "geometry": {"coordinates":[46.48795,43.20773],"type":"Point"}
}