{
  "type": "Feature",
  "properties": {
    "gn:admin1_code":"88",
    "gn:asciiname":"Iskrobol",
    "gn:country_code":"RU",
    "gn:dem":88,
    "gn:feature_class":"P",
    "gn:feature_code":"PPL",
    "gn:name":"Iskrobol",
    "gn:population":0,
    "gn:timezone":"Europe/Moscow",
    "iso:country":"RU",
    "name:eng_x_preferred":[
        "Iskrobol"
    ],
    "name:nor_x_preferred":[
        "Iskrobol"
    ],
    "name:rus_x_preferred":[
        "\u0418\u0441\u043a\u0440\u043e\u0431\u043e\u043b"
    ],
    "name:und_x_variant":[
        "\u0418\u0441\u043a\u0440\u043e\u0431\u043e\u043b",
        "Iskrobol"
    ],
    "wof:name":"Iskrobol",
    "wof:placetype":"locality"
},
  "geometry": {"coordinates":[40.45425,57.79898000000001],"type":"Point"}
}