{
  "type": "Feature",
  "properties": {
    "gn:admin1_code":"91",
    "gn:asciiname":"Asansk",
    "gn:country_code":"RU",
    "gn:dem":226,
    "gn:feature_class":"P",
    "gn:feature_code":"PPL",
    "gn:name":"Asansk",
    "gn:population":0,
    "gn:timezone":"Asia/Krasnoyarsk",
    "iso:country":"RU",
    "name:eng_x_preferred":[
        "Asansk"
    ],
    "name:nor_x_preferred":[
        "Asansk"
    ],
    "name:rus_x_preferred":[
        "\u0410\u0441\u0430\u043d\u0441\u043a"
    ],
    "name:und_x_variant":[
        "Asanskoye",
        "Asanskaya"
    ],
    "wof:name":"Asansk",
    "wof:placetype":"locality"
},
  "geometry": {"coordinates":[95.562,57.0398],"type":"Point"}
}