{
  "type": "Feature",
  "properties": {
    "gn:admin1_code":"38",
    "gn:asciiname":"Supsekh",
    "gn:country_code":"RU",
    "gn:dem":83,
    "gn:feature_class":"P",
    "gn:feature_code":"PPL",
    "gn:name":"Supsekh",
    "gn:population":0,
    "gn:timezone":"Europe/Moscow",
    "iso:country":"RU",
    "name:rus_x_preferred":[
        "\u0421\u0443\u043f\u0441\u0435\u0445"
    ],
    "wof:name":"Supsekh",
    "wof:placetype":"locality"
},
  "geometry": {"coordinates":[37.36629,44.86285],"type":"Point"}
}