{
  "type": "Feature",
  "properties": {
    "gn:admin1_code":"3",
    "gn:asciiname":"Lysanova",
    "gn:country_code":"RU",
    "gn:dem":1032,
    "gn:feature_class":"P",
    "gn:feature_code":"PPL",
    "gn:name":"Lysanova",
    "gn:population":0,
    "gn:timezone":"Asia/Omsk",
    "iso:country":"RU",
    "name:rus_x_preferred":[
        "\u041b\u044b\u0441\u0430\u043d\u043e\u0432\u0430"
    ],
    "name:und_x_variant":[
        "\u041b\u044b\u0441\u0430\u043d\u043e\u0432\u0430"
    ],
    "wof:name":"Lysanova",
    "wof:placetype":"locality"
},
  "geometry": {"coordinates":[85.88333,50.28333],"type":"Point"}
}