{
  "type": "Feature",
  "properties": {
    "gn:admin1_code":"77",
    "gn:asciiname":"Bavykino",
    "gn:country_code":"RU",
    "gn:dem":226,
    "gn:feature_class":"P",
    "gn:feature_code":"PPL",
    "gn:name":"Bavykino",
    "gn:population":0,
    "gn:timezone":"Europe/Moscow",
    "iso:country":"RU",
    "name:nor_x_preferred":[
        "Bavykino"
    ],
    "name:rus_x_preferred":[
        "\u0411\u0430\u0432\u044b\u043a\u0438\u043d\u043e"
    ],
    "wof:name":"Bavykino",
    "wof:placetype":"locality"
},
  "geometry": {"coordinates":[34.46818,57.22588],"type":"Point"}
}