{
  "type": "Feature",
  "properties": {
    "gn:admin1_code":"81",
    "gn:asciiname":"Yazykovo",
    "gn:country_code":"RU",
    "gn:dem":97,
    "gn:feature_class":"P",
    "gn:feature_code":"PPL",
    "gn:name":"Yazykovo",
    "gn:population":0,
    "gn:timezone":"Europe/Ulyanovsk",
    "iso:country":"RU",
    "name:rus_x_preferred":[
        "\u042f\u0437\u044b\u043a\u043e\u0432\u043e"
    ],
    "wof:name":"Yazykovo",
    "wof:placetype":"locality"
},
  "geometry": {"coordinates":[48.4612,53.6757],"type":"Point"}
}