{
  "type": "Feature",
  "properties": {
    "gn:admin1_code":"52",
    "gn:asciiname":"Merlyugino",
    "gn:country_code":"RU",
    "gn:dem":140,
    "gn:feature_class":"P",
    "gn:feature_code":"PPL",
    "gn:name":"Merlyugino",
    "gn:population":0,
    "gn:timezone":"Europe/Moscow",
    "iso:country":"RU",
    "name:rus_x_preferred":[
        "\u041c\u0435\u0440\u043b\u044e\u0433\u0438\u043d\u043e"
    ],
    "name:und_x_variant":[
        "\u041c\u0435\u0440\u043b\u044e\u0433\u0438\u043d\u043e"
    ],
    "wof:name":"Merlyugino",
    "wof:placetype":"locality"
},
  "geometry": {"coordinates":[34.15158,58.37589000000001],"type":"Point"}
}