{
  "type": "Feature",
  "properties": {
    "gn:admin1_code":"77",
    "gn:asciiname":"Zaykovo",
    "gn:country_code":"RU",
    "gn:dem":179,
    "gn:feature_class":"P",
    "gn:feature_code":"PPL",
    "gn:name":"Zaykovo",
    "gn:population":0,
    "gn:timezone":"Europe/Moscow",
    "iso:country":"RU",
    "name:che_x_preferred":[
        "\u0417\u0430\u0439\u043a\u043e\u0432\u043e"
    ],
    "name:rus_x_preferred":[
        "\u0417\u0430\u0439\u043a\u043e\u0432\u043e"
    ],
    "wof:name":"Zaykovo",
    "wof:placetype":"locality"
},
  "geometry": {"coordinates":[32.4467,55.7329],"type":"Point"}
}