{
  "type": "Feature",
  "properties": {
    "gn:admin1_code":"33.0",
    "gn:asciiname":"Sudnitsyny",
    "gn:country_code":"RU",
    "gn:dem":106,
    "gn:feature_class":"P",
    "gn:feature_code":"PPL",
    "gn:name":"Sudnitsyny",
    "gn:population":0,
    "gn:timezone":"Europe/Kirov",
    "iso:country":"RU",
    "name:rus_x_preferred":[
        "\u0421\u0443\u0434\u043d\u0438\u0446\u044b\u043d\u044b"
    ],
    "name:und_x_variant":[
        "\u0421\u0443\u0434\u043d\u0438\u0446\u044b\u043d\u044b"
    ],
    "wof:name":"Sudnitsyny",
    "wof:placetype":"locality"
},
  "geometry": {"coordinates":[48.28813,57.94749],"type":"Point"}
}