{
  "type": "Feature",
  "properties": {
    "gn:admin1_code":"61",
    "gn:asciiname":"Pavlov",
    "gn:country_code":"RU",
    "gn:dem":13,
    "gn:feature_class":"P",
    "gn:feature_code":"PPL",
    "gn:name":"Pavlov",
    "gn:population":0,
    "gn:timezone":"Europe/Moscow",
    "iso:country":"RU",
    "name:eng_x_preferred":[
        "Pavlov"
    ],
    "name:nor_x_preferred":[
        "Pavlov"
    ],
    "name:rus_x_preferred":[
        "\u041f\u0430\u0432\u043b\u043e\u0432"
    ],
    "name:und_x_variant":[
        "Pavlovskiy",
        "\u041f\u0430\u0432\u043b\u043e\u0432",
        "Pavlov"
    ],
    "wof:name":"Pavlov",
    "wof:placetype":"locality"
},
  "geometry": {"coordinates":[41.14265,47.31565],"type":"Point"}
}