{
  "type": "Feature",
  "properties": {
    "gn:admin1_code":"54",
    "gn:asciiname":"Lyubino-Moskali",
    "gn:cc2":"RU",
    "gn:country_code":"RU",
    "gn:dem":81,
    "gn:feature_class":"P",
    "gn:feature_code":"PPL",
    "gn:name":"Lyubino-Moskali",
    "gn:population":0,
    "gn:timezone":"Asia/Omsk",
    "iso:country":"RU",
    "name:rus_x_preferred":[
        "\u041b\u044e\u0431\u0438\u043d\u043e-\u041c\u043e\u0441\u043a\u0430\u043b\u0438"
    ],
    "name:und_x_variant":[
        "Lyubino-Russkoye",
        "Lyubino-Moskali"
    ],
    "wof:name":"Lyubino-Moskali",
    "wof:placetype":"locality"
},
  "geometry": {"coordinates":[72.93333,55.21666999999999],"type":"Point"}
}