{
  "type": "Feature",
  "properties": {
    "gn:admin1_code":"71",
    "gn:asciiname":"Novoalekseyevskoye",
    "gn:country_code":"RU",
    "gn:dem":314,
    "gn:feature_class":"P",
    "gn:feature_code":"PPL",
    "gn:name":"Novoalekseyevskoye",
    "gn:population":0,
    "gn:timezone":"Asia/Yekaterinburg",
    "iso:country":"RU",
    "name:rus_x_preferred":[
        "\u041d\u043e\u0432\u043e\u0430\u043b\u0435\u043a\u0441\u0435\u0435\u0432\u0441\u043a\u043e\u0435"
    ],
    "wof:name":"Novoalekseyevskoye",
    "wof:placetype":"locality"
},
  "geometry": {"coordinates":[60.1341,56.8515],"type":"Point"}
}