{
  "type": "Feature",
  "properties": {
    "gn:admin1_code":"28",
    "gn:asciiname":"Matyuki",
    "gn:country_code":"RU",
    "gn:dem":54,
    "gn:feature_class":"P",
    "gn:feature_code":"PPL",
    "gn:name":"Matyuki",
    "gn:population":0,
    "gn:timezone":"Europe/Moscow",
    "iso:country":"RU",
    "name:fin_x_preferred":[
        "Matunkyl\u00e4"
    ],
    "name:rus_x_preferred":[
        "\u041c\u0430\u0442\u044e\u043a\u0438"
    ],
    "name:und_x_variant":[
        "\u041c\u0430\u0442\u044e\u043a\u0438"
    ],
    "wof:name":"Matyuki",
    "wof:placetype":"locality"
},
  "geometry": {"coordinates":[34.00835,62.5214],"type":"Point"}
}