{
  "type": "Feature",
  "properties": {
    "gn:admin1_code":"6",
    "gn:asciiname":"Nyonoksa",
    "gn:country_code":"RU",
    "gn:dem":9,
    "gn:feature_class":"P",
    "gn:feature_code":"PPL",
    "gn:name":"Nyonoksa",
    "gn:population":468,
    "gn:timezone":"Europe/Moscow",
    "iso:country":"RU",
    "name:deu_x_preferred":[
        "Njonoksa"
    ],
    "name:eng_x_preferred":[
        "Nenoksa"
    ],
    "name:hye_x_preferred":[
        "\u0546\u0575\u0578\u0576\u0578\u056f\u057d\u0561"
    ],
    "name:nor_x_preferred":[
        "Nenoksa"
    ],
    "name:rus_x_preferred":[
        "\u041d\u0451\u043d\u043e\u043a\u0441\u0430"
    ],
    "name:swe_x_preferred":[
        "Njonoksa"
    ],
    "name:und_x_variant":[
        "N\u00ebnoksa"
    ],
    "wof:name":"Nyonoksa",
    "wof:placetype":"locality",
    "wof:population":468
},
  "geometry": {"coordinates":[39.1835,64.622],"type":"Point"}
}