{
  "type": "Feature",
  "properties": {
    "gn:admin1_code":"77",
    "gn:asciiname":"Kudnevo",
    "gn:country_code":"RU",
    "gn:dem":157,
    "gn:feature_class":"P",
    "gn:feature_code":"PPL",
    "gn:name":"Kudnevo",
    "gn:population":0,
    "gn:timezone":"Europe/Moscow",
    "iso:country":"RU",
    "name:rus_x_preferred":[
        "\u041a\u0443\u0434\u043d\u0435\u0432\u043e"
    ],
    "wof:name":"Kudnevo",
    "wof:placetype":"locality"
},
  "geometry": {"coordinates":[37.0552,58.1569],"type":"Point"}
}