{
  "type": "Feature",
  "properties": {
    "gn:admin1_code":"73",
    "gn:asciiname":"Verkhniye Lashchi",
    "gn:country_code":"RU",
    "gn:dem":134,
    "gn:feature_class":"P",
    "gn:feature_code":"PPL",
    "gn:name":"Verkhniye Lashchi",
    "gn:population":0,
    "gn:timezone":"Europe/Moscow",
    "iso:country":"RU",
    "name:und_x_variant":[
        "Verkhniye Loshchi",
        "Verkhniy Lashchi",
        "Verkhniye Lashchi"
    ],
    "wof:name":"Verkhniye Lashchi",
    "wof:placetype":"locality"
},
  "geometry": {"coordinates":[48.0545,55.03159],"type":"Point"}
}