{
  "type": "Feature",
  "properties": {
    "gn:admin1_code":"90.0",
    "gn:asciiname":"Baturyata",
    "gn:country_code":"RU",
    "gn:dem":186,
    "gn:feature_class":"P",
    "gn:feature_code":"PPL",
    "gn:name":"Baturyata",
    "gn:population":0,
    "gn:timezone":"Asia/Yekaterinburg",
    "iso:country":"RU",
    "name:nor_x_preferred":[
        "Baturjata"
    ],
    "name:rus_x_preferred":[
        "\u0411\u0430\u0442\u0443\u0440\u044f\u0442\u0430"
    ],
    "wof:name":"Baturyata",
    "wof:placetype":"locality"
},
  "geometry": {"coordinates":[57.672,57.6763],"type":"Point"}
}