{
  "type": "Feature",
  "properties": {
    "gn:admin1_code":"85",
    "gn:asciiname":"Zadunay",
    "gn:country_code":"RU",
    "gn:dem":149,
    "gn:feature_class":"P",
    "gn:feature_code":"PPL",
    "gn:name":"Zadunay",
    "gn:population":0,
    "gn:timezone":"Europe/Moscow",
    "iso:country":"RU",
    "name:rus_x_preferred":[
        "\u0417\u0430\u0434\u0443\u043d\u0430\u0439"
    ],
    "wof:name":"Zadunay",
    "wof:placetype":"locality"
},
  "geometry": {"coordinates":[38.1415,59.6718],"type":"Point"}
}