{
  "type": "Feature",
  "properties": {
    "gn:admin1_code":"40",
    "gn:asciiname":"Bezbozhnaya",
    "gn:country_code":"RU",
    "gn:dem":78,
    "gn:feature_class":"P",
    "gn:feature_code":"PPL",
    "gn:name":"Bezbozhnaya",
    "gn:population":0,
    "gn:timezone":"Asia/Yekaterinburg",
    "iso:country":"RU",
    "name:rus_x_preferred":[
        "\u0411\u0435\u0437\u0431\u043e\u0436\u043d\u0430\u044f"
    ],
    "wof:name":"Bezbozhnaya",
    "wof:placetype":"locality"
},
  "geometry": {"coordinates":[63.1545,56.1902],"type":"Point"}
}