{
  "type": "Feature",
  "properties": {
    "gn:admin1_code":"77",
    "gn:asciiname":"Khrebtovo",
    "gn:country_code":"RU",
    "gn:dem":163,
    "gn:feature_class":"P",
    "gn:feature_code":"PPL",
    "gn:name":"Khrebtovo",
    "gn:population":0,
    "gn:timezone":"Europe/Moscow",
    "iso:country":"RU",
    "name:rus_x_preferred":[
        "\u0425\u0440\u0435\u0431\u0442\u043e\u0432\u043e"
    ],
    "wof:name":"Khrebtovo",
    "wof:placetype":"locality"
},
  "geometry": {"coordinates":[35.28667,57.66111],"type":"Point"}
}