{
  "type": "Feature",
  "properties": {
    "gn:admin1_code":"76",
    "gn:asciiname":"Verkhnyaya Izroga",
    "gn:country_code":"RU",
    "gn:dem":173,
    "gn:feature_class":"P",
    "gn:feature_code":"PPL",
    "gn:name":"Verkhnyaya Izroga",
    "gn:population":0,
    "gn:timezone":"Europe/Moscow",
    "iso:country":"RU",
    "name:und_x_variant":[
        "Izrog",
        "Verkhniy Izrog",
        "Verkhnyaya Izroga"
    ],
    "wof:name":"Verkhnyaya Izroga",
    "wof:placetype":"locality"
},
  "geometry": {"coordinates":[37.89631,53.25813],"type":"Point"}
}