{
  "type": "Feature",
  "properties": {
    "gn:admin1_code":"60",
    "gn:asciiname":"Ovinets",
    "gn:country_code":"RU",
    "gn:dem":73,
    "gn:feature_class":"P",
    "gn:feature_code":"PPL",
    "gn:name":"Ovinets",
    "gn:population":0,
    "gn:timezone":"Europe/Moscow",
    "iso:country":"RU",
    "name:rus_x_preferred":[
        "\u041e\u0432\u0438\u043d\u0435\u0446"
    ],
    "name:und_x_variant":[
        "\u041e\u0432\u0438\u043d\u0435\u0446"
    ],
    "wof:name":"Ovinets",
    "wof:placetype":"locality"
},
  "geometry": {"coordinates":[29.18503,58.46441],"type":"Point"}
}