{
  "type": "Feature",
  "properties": {
    "gn:admin1_code":"77",
    "gn:asciiname":"Kurkino",
    "gn:country_code":"RU",
    "gn:dem":163,
    "gn:feature_class":"P",
    "gn:feature_code":"PPL",
    "gn:name":"Kurkino",
    "gn:population":0,
    "gn:timezone":"Europe/Moscow",
    "iso:country":"RU",
    "name:ceb_x_preferred":[
        "Kurkino"
    ],
    "name:deu_x_preferred":[
        "Kurkino"
    ],
    "name:nor_x_preferred":[
        "Kurkino"
    ],
    "name:rus_x_preferred":[
        "\u041a\u0443\u0440\u043a\u0438\u043d\u043e"
    ],
    "name:und_x_variant":[
        "Bol\u2019shoye Kurkino"
    ],
    "wof:name":"Kurkino",
    "wof:placetype":"locality"
},
  "geometry": {"coordinates":[35.95282,56.69991],"type":"Point"}
}