{
  "type": "Feature",
  "properties": {
    "gn:admin1_code":"85.0",
    "gn:asciiname":"Chuykovo",
    "gn:country_code":"RU",
    "gn:dem":149,
    "gn:feature_class":"P",
    "gn:feature_code":"PPL",
    "gn:name":"Chuykovo",
    "gn:population":0,
    "gn:timezone":"Europe/Moscow",
    "iso:country":"RU",
    "name:rus_x_preferred":[
        "\u0427\u0443\u0439\u043a\u043e\u0432\u043e"
    ],
    "name:und_x_variant":[
        "Chuykino",
        "Chuykovo",
        "\u0427\u0443\u0439\u043a\u043e\u0432\u043e"
    ],
    "wof:name":"Chuykovo",
    "wof:placetype":"locality"
},
  "geometry": {"coordinates":[38.14326,59.78221],"type":"Point"}
}