{
  "type": "Feature",
  "properties": {
    "gn:admin1_code":"42",
    "gn:asciiname":"Tetoy Gora-Karka",
    "gn:cc2":"RU",
    "gn:country_code":"RU",
    "gn:dem":207,
    "gn:feature_class":"P",
    "gn:feature_code":"PPL",
    "gn:name":"Tetoy Gora-Karka",
    "gn:population":0,
    "gn:timezone":"Europe/Moscow",
    "iso:country":"RU",
    "name:und_x_variant":[
        "Karka",
        "Tetoy Gora-Karka"
    ],
    "wof:name":"Tetoy Gora-Karka",
    "wof:placetype":"locality"
},
  "geometry": {"coordinates":[35.23333,60.86666999999999],"type":"Point"}
}