{
  "type": "Feature",
  "properties": {
    "gn:admin1_code":"60",
    "gn:asciiname":"Beredniki",
    "gn:country_code":"RU",
    "gn:dem":68,
    "gn:feature_class":"P",
    "gn:feature_code":"PPL",
    "gn:name":"Beredniki",
    "gn:population":0,
    "gn:timezone":"Europe/Moscow",
    "iso:country":"RU",
    "name:rus_x_preferred":[
        "\u0411\u0435\u0440\u0435\u0434\u043d\u0438\u043a\u0438"
    ],
    "wof:name":"Beredniki",
    "wof:placetype":"locality"
},
  "geometry": {"coordinates":[28.45032,57.30704],"type":"Point"}
}