{
  "type": "Feature",
  "properties": {
    "gn:admin1_code":"28",
    "gn:asciiname":"Sikavara",
    "gn:cc2":"RU",
    "gn:country_code":"RU",
    "gn:dem":173,
    "gn:feature_class":"P",
    "gn:feature_code":"PPL",
    "gn:name":"Sikavara",
    "gn:population":0,
    "gn:timezone":"Europe/Moscow",
    "iso:country":"RU",
    "name:fin_x_preferred":[
        "Siikavaara"
    ],
    "name:rus_x_preferred":[
        "\u0421\u0438\u043a\u0430\u0432\u0430\u0440\u0430"
    ],
    "wof:name":"Sikavara",
    "wof:placetype":"locality"
},
  "geometry": {"coordinates":[31.55205,62.66003000000001],"type":"Point"}
}