{
  "type": "Feature",
  "properties": {
    "gn:admin1_code":"38",
    "gn:asciiname":"Urozhaynyy",
    "gn:country_code":"RU",
    "gn:dem":81,
    "gn:feature_class":"P",
    "gn:feature_code":"PPL",
    "gn:name":"Urozhaynyy",
    "gn:population":0,
    "gn:timezone":"Europe/Moscow",
    "iso:country":"RU",
    "name:rus_x_preferred":[
        "\u0423\u0440\u043e\u0436\u0430\u0439\u043d\u044b\u0439"
    ],
    "wof:name":"Urozhaynyy",
    "wof:placetype":"locality"
},
  "geometry": {"coordinates":[40.2802,45.9232],"type":"Point"}
}