{
  "type": "Feature",
  "properties": {
    "gn:admin1_code":"13",
    "gn:asciiname":"Klyuchi",
    "gn:country_code":"RU",
    "gn:dem":211,
    "gn:feature_class":"P",
    "gn:feature_code":"PPL",
    "gn:name":"Klyuchi",
    "gn:population":0,
    "gn:timezone":"Asia/Yekaterinburg",
    "iso:country":"RU",
    "name:rus_x_preferred":[
        "\u041a\u043b\u044e\u0447\u0438"
    ],
    "name:und_x_variant":[
        "\u041a\u043b\u044e\u0447\u0438"
    ],
    "wof:name":"Klyuchi",
    "wof:placetype":"locality"
},
  "geometry": {"coordinates":[61.25,54.41667],"type":"Point"}
}