{
  "type": "Feature",
  "properties": {
    "gn:admin1_code":"88",
    "gn:asciiname":"Bol'shoye Andreykovo",
    "gn:country_code":"RU",
    "gn:dem":114,
    "gn:feature_class":"P",
    "gn:feature_code":"PPL",
    "gn:name":"Bol\u2019shoye Andreykovo",
    "gn:population":0,
    "gn:timezone":"Europe/Moscow",
    "iso:country":"RU",
    "name:rus_x_preferred":[
        "\u0411\u043e\u043b\u044c\u0448\u043e\u0435 \u0410\u043d\u0434\u0440\u0435\u0439\u043a\u043e\u0432\u043e"
    ],
    "name:und_x_variant":[
        "Bol\u2019shoye Andreykovo",
        "\u0411\u043e\u043b\u044c\u0448\u043e\u0435 \u0410\u043d\u0434\u0440\u0435\u0439\u043a\u043e\u0432\u043e"
    ],
    "wof:name":"Bol'shoye Andreykovo",
    "wof:placetype":"locality"
},
  "geometry": {"coordinates":[38.63314,58.07123000000001],"type":"Point"}
}