{
  "type": "Feature",
  "properties": {
    "gn:admin1_code":"4",
    "gn:asciiname":"Kungurovo",
    "gn:country_code":"RU",
    "gn:dem":128,
    "gn:feature_class":"P",
    "gn:feature_code":"PPL",
    "gn:name":"Kungurovo",
    "gn:population":0,
    "gn:timezone":"Asia/Barnaul",
    "iso:country":"RU",
    "name:rus_x_preferred":[
        "\u041a\u0443\u043d\u0433\u0443\u0440\u043e\u0432\u043e"
    ],
    "name:und_x_variant":[
        "Kungurova",
        "Kungurovo",
        "\u041a\u0443\u043d\u0433\u0443\u0440\u043e\u0432\u043e"
    ],
    "wof:name":"Kungurovo",
    "wof:placetype":"locality"
},
  "geometry": {"coordinates":[83.4256,53.49],"type":"Point"}
}