{
  "type": "Feature",
  "properties": {
    "gn:admin1_code":"47",
    "gn:asciiname":"Kuznetsovo",
    "gn:country_code":"RU",
    "gn:dem":191,
    "gn:feature_class":"P",
    "gn:feature_code":"PPL",
    "gn:name":"Kuznetsovo",
    "gn:population":0,
    "gn:timezone":"Europe/Moscow",
    "iso:country":"RU",
    "name:und_x_variant":[
        "Ryzhkovo",
        "Kuznetsovo"
    ],
    "wof:name":"Kuznetsovo",
    "wof:placetype":"locality"
},
  "geometry": {"coordinates":[36.94337,55.45732],"type":"Point"}
}