{
  "type": "Feature",
  "properties": {
    "gn:admin1_code":"76",
    "gn:asciiname":"Sorochinka",
    "gn:country_code":"RU",
    "gn:dem":210,
    "gn:feature_class":"P",
    "gn:feature_code":"PPL",
    "gn:name":"Sorochinka",
    "gn:population":0,
    "gn:timezone":"Europe/Moscow",
    "iso:country":"RU",
    "name:eng_x_preferred":[
        "Sorochinka"
    ],
    "name:nor_x_preferred":[
        "Sorotsjinka"
    ],
    "name:rus_x_preferred":[
        "\u0421\u043e\u0440\u043e\u0447\u0438\u043d\u043a\u0430"
    ],
    "name:und_x_variant":[
        "Sorochenka",
        "\u0421\u043e\u0440\u043e\u0447\u0438\u043d\u043a\u0430",
        "Sorochinka"
    ],
    "wof:name":"Sorochinka",
    "wof:placetype":"locality"
},
  "geometry": {"coordinates":[37.44815,53.67404000000001],"type":"Point"}
}