{
  "type": "Feature",
  "properties": {
    "gn:admin1_code":"63",
    "gn:asciiname":"Bikche",
    "gn:country_code":"RU",
    "gn:dem":121,
    "gn:feature_class":"P",
    "gn:feature_code":"PPL",
    "gn:name":"Bikche",
    "gn:population":0,
    "gn:timezone":"Asia/Yakutsk",
    "iso:country":"RU",
    "name:rus_x_preferred":[
        "\u0411\u0438\u043a\u0447\u0435"
    ],
    "wof:name":"Bikche",
    "wof:placetype":"locality"
},
  "geometry": {"coordinates":[124.98333,65.86667],"type":"Point"}
}