{
  "type": "Feature",
  "properties": {
    "gn:admin1_code":"60",
    "gn:asciiname":"Sanino",
    "gn:country_code":"RU",
    "gn:dem":67,
    "gn:feature_class":"P",
    "gn:feature_code":"PPL",
    "gn:name":"Sanino",
    "gn:population":0,
    "gn:timezone":"Europe/Moscow",
    "iso:country":"RU",
    "name:rus_x_preferred":[
        "\u0421\u0430\u043d\u0438\u043d\u043e"
    ],
    "wof:name":"Sanino",
    "wof:placetype":"locality"
},
  "geometry": {"coordinates":[28.11688,57.20843000000001],"type":"Point"}
}