{
  "type": "Feature",
  "properties": {
    "gn:admin1_code":"60",
    "gn:asciiname":"Poddubka",
    "gn:country_code":"RU",
    "gn:dem":80,
    "gn:feature_class":"P",
    "gn:feature_code":"PPL",
    "gn:name":"Poddubka",
    "gn:population":0,
    "gn:timezone":"Europe/Moscow",
    "iso:country":"RU",
    "name:rus_x_preferred":[
        "\u041f\u043e\u0434\u0434\u0443\u0431\u043a\u0430"
    ],
    "wof:name":"Poddubka",
    "wof:placetype":"locality"
},
  "geometry": {"coordinates":[28.56628,57.04239000000001],"type":"Point"}
}