{
  "type": "Feature",
  "properties": {
    "gn:admin1_code":"72.0",
    "gn:asciiname":"Poselok Sel'skokhozyaystvennogo Professional'no-Tekhnicheskogo Uchilishcha Nomer Desyat'",
    "gn:country_code":"RU",
    "gn:dem":152,
    "gn:feature_class":"P",
    "gn:feature_code":"PPL",
    "gn:name":"Pos\u00eblok Sel\u2019skokhozyaystvennogo Professional\u2019no-Tekhnicheskogo Uchilishcha Nomer Desyat\u2019",
    "gn:population":0,
    "gn:timezone":"Europe/Moscow",
    "iso:country":"RU",
    "wof:name":"Poselok Sel'skokhozyaystvennogo Professional'no-Tekhnicheskogo Uchilishcha Nomer Desyat'",
    "wof:placetype":"locality"
},
  "geometry": {"coordinates":[41.55425,52.69917],"type":"Point"}
}