{
  "type": "Feature",
  "properties": {
    "gn:admin1_code":"9",
    "gn:asciiname":"Ternovoye",
    "gn:country_code":"RU",
    "gn:dem":142,
    "gn:feature_class":"P",
    "gn:feature_code":"PPL",
    "gn:name":"Ternovoye",
    "gn:population":0,
    "gn:timezone":"Europe/Moscow",
    "iso:country":"RU",
    "name:rus_x_preferred":[
        "\u0422\u0435\u0440\u043d\u043e\u0432\u043e\u0435"
    ],
    "name:und_x_variant":[
        "Ternovaya",
        "Ternovoye"
    ],
    "wof:name":"Ternovoye",
    "wof:placetype":"locality"
},
  "geometry": {"coordinates":[38.1296,51.1814],"type":"Point"}
}