{
  "type": "Feature",
  "properties": {
    "gn:admin1_code":"59.0",
    "gn:asciiname":"Pervomayskiy Pervyy",
    "gn:country_code":"RU",
    "gn:dem":64,
    "gn:feature_class":"P",
    "gn:feature_code":"PPL",
    "gn:name":"Pervomayskiy Pervyy",
    "gn:population":0,
    "gn:timezone":"Asia/Vladivostok",
    "iso:country":"RU",
    "name:rus_x_preferred":[
        "\u041f\u0435\u0440\u0432\u043e\u043c\u0430\u0439\u0441\u043a\u0438\u0439 \u041f\u0435\u0440\u0432\u044b\u0439"
    ],
    "wof:name":"Pervomayskiy Pervyy",
    "wof:placetype":"locality"
},
  "geometry": {"coordinates":[131.91083,44.00258],"type":"Point"}
}