{
  "type": "Feature",
  "properties": {
    "gn:admin1_code":"60",
    "gn:asciiname":"Lipnya",
    "gn:country_code":"RU",
    "gn:dem":69,
    "gn:feature_class":"P",
    "gn:feature_code":"PPL",
    "gn:name":"Lipnya",
    "gn:population":0,
    "gn:timezone":"Europe/Moscow",
    "iso:country":"RU",
    "name:rus_x_preferred":[
        "\u041b\u0438\u043f\u043d\u044f"
    ],
    "name:und_x_variant":[
        "\u041b\u0438\u043f\u043d\u044f"
    ],
    "wof:name":"Lipnya",
    "wof:placetype":"locality"
},
  "geometry": {"coordinates":[30.01031,57.62876],"type":"Point"}
}