{
  "type": "Feature",
  "properties": {
    "gn:admin1_code":"37",
    "gn:asciiname":"Malaya Strelka",
    "gn:country_code":"RU",
    "gn:dem":153,
    "gn:feature_class":"P",
    "gn:feature_code":"PPL",
    "gn:name":"Malaya Strelka",
    "gn:population":0,
    "gn:timezone":"Europe/Moscow",
    "iso:country":"RU",
    "name:rus_x_preferred":[
        "\u041c\u0430\u043b\u0430\u044f \u0421\u0442\u0440\u0435\u043b\u043a\u0430"
    ],
    "name:und_x_variant":[
        "\u041c\u0430\u043b\u0430\u044f \u0421\u0442\u0440\u0435\u043b\u043a\u0430"
    ],
    "wof:name":"Malaya Strelka",
    "wof:placetype":"locality"
},
  "geometry": {"coordinates":[46.7768,58.7631],"type":"Point"}
}