{
  "type": "Feature",
  "properties": {
    "gn:admin1_code":"17",
    "gn:asciiname":"Novaya Barsha",
    "gn:country_code":"RU",
    "gn:dem":294,
    "gn:feature_class":"P",
    "gn:feature_code":"PPL",
    "gn:name":"Novaya Barsha",
    "gn:population":0,
    "gn:timezone":"Europe/Moscow",
    "iso:country":"RU",
    "name:rus_x_preferred":[
        "\u041d\u043e\u0432\u0430\u044f \u0411\u0430\u0440\u0448\u0430"
    ],
    "wof:name":"Novaya Barsha",
    "wof:placetype":"locality"
},
  "geometry": {"coordinates":[47.83600000000001,42.18284],"type":"Point"}
}