{
  "type": "Feature",
  "properties": {
    "gn:admin1_code":"29",
    "gn:asciiname":"Lebedi",
    "gn:country_code":"RU",
    "gn:dem":187,
    "gn:feature_class":"P",
    "gn:feature_code":"PPL",
    "gn:name":"Lebedi",
    "gn:population":0,
    "gn:timezone":"Asia/Novokuznetsk",
    "iso:country":"RU",
    "name:eng_x_preferred":[
        "Lebedi"
    ],
    "name:nor_x_preferred":[
        "Lebedi"
    ],
    "name:rus_x_preferred":[
        "\u041b\u0435\u0431\u0435\u0434\u0438"
    ],
    "name:und_x_variant":[
        "Lebedevskoye",
        "\u041b\u0435\u0431\u0435\u0434\u0438",
        "Lebedi"
    ],
    "wof:name":"Lebedi",
    "wof:placetype":"locality"
},
  "geometry": {"coordinates":[85.5834,55.0413],"type":"Point"}
}