{
  "type": "Feature",
  "properties": {
    "gn:admin1_code":"81.0",
    "gn:asciiname":"Belozer'ye",
    "gn:country_code":"RU",
    "gn:dem":118,
    "gn:feature_class":"P",
    "gn:feature_code":"PPL",
    "gn:name":"Belozer\u2019ye",
    "gn:population":0,
    "gn:timezone":"Europe/Ulyanovsk",
    "iso:country":"RU",
    "name:eng_x_preferred":[
        "Beloz\u00ebr'ye"
    ],
    "name:rus_x_preferred":[
        "\u0411\u0435\u043b\u043e\u0437\u0435\u0440\u044c\u0435"
    ],
    "name:und_x_variant":[
        "Belozer\u2019ye"
    ],
    "wof:name":"Belozer'ye",
    "wof:placetype":"locality"
},
  "geometry": {"coordinates":[47.1851,54.3311],"type":"Point"}
}