{
  "type": "Feature",
  "properties": {
    "gn:admin1_code":"90",
    "gn:asciiname":"Savina",
    "gn:country_code":"RU",
    "gn:dem":148,
    "gn:feature_class":"P",
    "gn:feature_code":"PPL",
    "gn:name":"Savina",
    "gn:population":0,
    "gn:timezone":"Asia/Yekaterinburg",
    "iso:country":"RU",
    "name:bos_x_preferred":[
        "Savina"
    ],
    "name:cat_x_preferred":[
        "Savina"
    ],
    "name:ceb_x_preferred":[
        "Savina"
    ],
    "name:deu_x_preferred":[
        "Savina"
    ],
    "name:eng_x_preferred":[
        "Savina"
    ],
    "name:fra_x_preferred":[
        "Savina"
    ],
    "name:nld_x_preferred":[
        "Savina"
    ],
    "name:nor_x_preferred":[
        "Savina"
    ],
    "name:rus_x_preferred":[
        "\u0421\u0430\u0432\u0438\u043d\u0430"
    ],
    "name:slv_x_preferred":[
        "Savina"
    ],
    "name:swe_x_preferred":[
        "Savina"
    ],
    "name:und_x_variant":[
        "Savino"
    ],
    "wof:name":"Savina",
    "wof:placetype":"locality"
},
  "geometry": {"coordinates":[56.21728,60.51071],"type":"Point"}
}