{
  "type": "Feature",
  "properties": {
    "gn:admin1_code":"28",
    "gn:asciiname":"Verkhneye Myagrozero",
    "gn:country_code":"RU",
    "gn:dem":52,
    "gn:feature_class":"P",
    "gn:feature_code":"PPL",
    "gn:name":"Verkhneye Myagrozero",
    "gn:population":0,
    "gn:timezone":"Europe/Moscow",
    "iso:country":"RU",
    "name:fin_x_preferred":[
        "Yl\u00e4-M\u00e4kr\u00e4j\u00e4rvi"
    ],
    "name:und_x_variant":[
        "Kurnikino",
        "Verkhneye Myagrozero"
    ],
    "wof:name":"Verkhneye Myagrozero",
    "wof:placetype":"locality"
},
  "geometry": {"coordinates":[34.81727,62.49413000000001],"type":"Point"}
}