{
  "type": "Feature",
  "properties": {
    "gn:admin1_code":"6",
    "gn:asciiname":"Pleshkovskaya",
    "gn:country_code":"RU",
    "gn:dem":75,
    "gn:feature_class":"P",
    "gn:feature_code":"PPL",
    "gn:name":"Pleshkovskaya",
    "gn:population":0,
    "gn:timezone":"Europe/Moscow",
    "iso:country":"RU",
    "name:rus_x_preferred":[
        "\u041f\u043b\u0435\u0448\u043a\u043e\u0432\u0441\u043a\u0430\u044f"
    ],
    "name:und_x_variant":[
        "\u041f\u043b\u0435\u0448\u043a\u043e\u0432\u0441\u043a\u0430\u044f"
    ],
    "wof:name":"Pleshkovskaya",
    "wof:placetype":"locality"
},
  "geometry": {"coordinates":[39.91667,62.73333],"type":"Point"}
}