{
  "type": "Feature",
  "properties": {
    "gn:admin1_code":"41",
    "gn:asciiname":"Nizhniy Mordok",
    "gn:country_code":"RU",
    "gn:dem":142,
    "gn:feature_class":"P",
    "gn:feature_code":"PPL",
    "gn:name":"Nizhniy Mordok",
    "gn:population":0,
    "gn:timezone":"Europe/Moscow",
    "iso:country":"RU",
    "name:rus_x_preferred":[
        "\u041d\u0438\u0436\u043d\u0438\u0439 \u041c\u043e\u0440\u0434\u043e\u043a"
    ],
    "wof:name":"Nizhniy Mordok",
    "wof:placetype":"locality"
},
  "geometry": {"coordinates":[34.7125,51.3815],"type":"Point"}
}