{
  "type": "Feature",
  "properties": {
    "gn:admin1_code":"34",
    "gn:asciiname":"Michabichevnik",
    "gn:country_code":"RU",
    "gn:dem":83,
    "gn:feature_class":"P",
    "gn:feature_code":"PPL",
    "gn:name":"Michabichevnik",
    "gn:population":0,
    "gn:timezone":"Europe/Moscow",
    "iso:country":"RU",
    "name:rus_x_preferred":[
        "\u041c\u0438\u0447\u0430\u0431\u0438\u0447\u0435\u0432\u043d\u0438\u043a"
    ],
    "name:und_x_variant":[
        "\u041c\u0438\u0447\u0430\u0431\u0438\u0447\u0435\u0432\u043d\u0438\u043a"
    ],
    "wof:name":"Michabichevnik",
    "wof:placetype":"locality"
},
  "geometry": {"coordinates":[58.03262,64.19632],"type":"Point"}
}