{
  "type": "Feature",
  "properties": {
    "gn:admin1_code":"60",
    "gn:asciiname":"Ivanishchevo",
    "gn:country_code":"RU",
    "gn:dem":183,
    "gn:feature_class":"P",
    "gn:feature_code":"PPL",
    "gn:name":"Ivanishchevo",
    "gn:population":0,
    "gn:timezone":"Europe/Moscow",
    "iso:country":"RU",
    "name:rus_x_preferred":[
        "\u0418\u0432\u0430\u043d\u0438\u0449\u0435\u0432\u043e"
    ],
    "wof:name":"Ivanishchevo",
    "wof:placetype":"locality"
},
  "geometry": {"coordinates":[29.6173,56.3891],"type":"Point"}
}