{
  "type": "Feature",
  "properties": {
    "gn:admin1_code":"31",
    "gn:asciiname":"Nizhniy Kyzylsuk",
    "gn:country_code":"RU",
    "gn:dem":611,
    "gn:feature_class":"P",
    "gn:feature_code":"PPL",
    "gn:name":"Nizhniy Kyzylsuk",
    "gn:population":0,
    "gn:timezone":"Asia/Krasnoyarsk",
    "iso:country":"RU",
    "name:rus_x_preferred":[
        "\u041d\u0438\u0436\u043d\u0438\u0439 \u041a\u044b\u0437\u044b\u043b\u0441\u0443\u043a"
    ],
    "wof:name":"Nizhniy Kyzylsuk",
    "wof:placetype":"locality"
},
  "geometry": {"coordinates":[89.53333000000001,52.78333000000001],"type":"Point"}
}