{
  "type": "Feature",
  "properties": {
    "gn:admin1_code":"20",
    "gn:asciiname":"Sharaty",
    "gn:country_code":"RU",
    "gn:dem":417,
    "gn:feature_class":"P",
    "gn:feature_code":"PPL",
    "gn:name":"Sharaty",
    "gn:population":0,
    "gn:timezone":"Asia/Irkutsk",
    "iso:country":"RU",
    "name:eng_x_preferred":[
        "Sharaty"
    ],
    "name:nor_x_preferred":[
        "Sjaraty"
    ],
    "name:rus_x_preferred":[
        "\u0428\u0430\u0440\u0430\u0442\u044b"
    ],
    "name:und_x_variant":[
        "Nizhniye Tanguty"
    ],
    "wof:name":"Sharaty",
    "wof:placetype":"locality"
},
  "geometry": {"coordinates":[102.57340000000001,53.8269],"type":"Point"}
}