{
  "type": "Feature",
  "properties": {
    "gn:admin1_code":"60",
    "gn:asciiname":"Voronich",
    "gn:country_code":"RU",
    "gn:dem":85,
    "gn:feature_class":"P",
    "gn:feature_code":"PPL",
    "gn:name":"Voronich",
    "gn:population":0,
    "gn:timezone":"Europe/Moscow",
    "iso:country":"RU",
    "name:rus_x_preferred":[
        "\u0412\u043e\u0440\u043e\u043d\u0438\u0447"
    ],
    "name:und_x_variant":[
        "\u0412\u043e\u0440\u043e\u043d\u0438\u0447"
    ],
    "wof:name":"Voronich",
    "wof:placetype":"locality"
},
  "geometry": {"coordinates":[28.87813,57.05338],"type":"Point"}
}