{
  "type": "Feature",
  "properties": {
    "gn:admin1_code":"3",
    "gn:asciiname":"Verkhniy Sartakol",
    "gn:country_code":"RU",
    "gn:dem":651,
    "gn:feature_class":"P",
    "gn:feature_code":"PPL",
    "gn:name":"Verkhniy Sartakol",
    "gn:population":0,
    "gn:timezone":"Asia/Omsk",
    "iso:country":"RU",
    "wof:name":"Verkhniy Sartakol",
    "wof:placetype":"locality"
},
  "geometry": {"coordinates":[86.90000000000001,51.93333],"type":"Point"}
}