{
  "type": "Feature",
  "properties": {
    "gn:admin1_code":"47",
    "gn:asciiname":"Iglovo",
    "gn:country_code":"RU",
    "gn:dem":217,
    "gn:feature_class":"P",
    "gn:feature_code":"PPL",
    "gn:name":"Iglovo",
    "gn:population":0,
    "gn:timezone":"Europe/Moscow",
    "iso:country":"RU",
    "name:rus_x_preferred":[
        "\u0418\u0433\u043b\u043e\u0432\u043e"
    ],
    "name:und_x_variant":[
        "\u0418\u0433\u043b\u043e\u0432\u043e"
    ],
    "wof:name":"Iglovo",
    "wof:placetype":"locality"
},
  "geometry": {"coordinates":[36.6657,55.78517],"type":"Point"}
}