{
  "type": "Feature",
  "properties": {
    "gn:admin1_code":"40",
    "gn:asciiname":"Kosachevo",
    "gn:country_code":"RU",
    "gn:dem":133,
    "gn:feature_class":"P",
    "gn:feature_code":"PPL",
    "gn:name":"Kosach\u00ebvo",
    "gn:population":0,
    "gn:timezone":"Asia/Yekaterinburg",
    "iso:country":"RU",
    "name:eng_x_preferred":[
        "Kosach\u00ebvo"
    ],
    "name:nor_x_preferred":[
        "Kosatsjevo"
    ],
    "name:rus_x_preferred":[
        "\u041a\u043e\u0441\u0430\u0447\u0435\u0432\u043e"
    ],
    "name:rus_x_variant":[
        "\u041a\u043e\u0441\u0430\u0447\u0451\u0432\u043e"
    ],
    "wof:name":"Kosachevo",
    "wof:placetype":"locality"
},
  "geometry": {"coordinates":[68.49194,55.20916999999999],"type":"Point"}
}