{
  "type": "Feature",
  "properties": {
    "gn:admin1_code":"17.0",
    "gn:asciiname":"Sarsak",
    "gn:country_code":"RU",
    "gn:dem":1048,
    "gn:feature_class":"P",
    "gn:feature_code":"PPL",
    "gn:name":"Sarsak",
    "gn:population":0,
    "gn:timezone":"Europe/Moscow",
    "iso:country":"RU",
    "wof:name":"Sarsak",
    "wof:placetype":"locality"
},
  "geometry": {"coordinates":[47.29028,42.62806],"type":"Point"}
}