{
  "type": "Feature",
  "properties": {
    "gn:admin1_code":"41",
    "gn:asciiname":"Novaya Golovinka",
    "gn:country_code":"RU",
    "gn:dem":198,
    "gn:feature_class":"P",
    "gn:feature_code":"PPL",
    "gn:name":"Novaya Golovinka",
    "gn:population":0,
    "gn:timezone":"Europe/Moscow",
    "iso:country":"RU",
    "name:rus_x_preferred":[
        "\u041d\u043e\u0432\u0430\u044f \u0413\u043e\u043b\u043e\u0432\u0438\u043d\u043a\u0430"
    ],
    "wof:name":"Novaya Golovinka",
    "wof:placetype":"locality"
},
  "geometry": {"coordinates":[35.7991,52.2597],"type":"Point"}
}