{
  "type": "Feature",
  "properties": {
    "gn:admin1_code":"4.0",
    "gn:asciiname":"Zarya",
    "gn:country_code":"RU",
    "gn:dem":238,
    "gn:feature_class":"P",
    "gn:feature_code":"PPL",
    "gn:name":"Zarya",
    "gn:population":1700,
    "gn:timezone":"Asia/Barnaul",
    "iso:country":"RU",
    "wof:name":"Zarya",
    "wof:placetype":"locality",
    "wof:population":1700
},
  "geometry": {"coordinates":[85.17570000000001,52.59696],"type":"Point"}
}