{
  "type": "Feature",
  "properties": {
    "gn:admin1_code":"61",
    "gn:asciiname":"Sharpayevka",
    "gn:country_code":"RU",
    "gn:dem":47,
    "gn:feature_class":"P",
    "gn:feature_code":"PPL",
    "gn:name":"Sharpayevka",
    "gn:population":0,
    "gn:timezone":"Europe/Moscow",
    "iso:country":"RU",
    "name:eng_x_preferred":[
        "Sharpayevka"
    ],
    "name:nor_x_preferred":[
        "Sjarpajevka"
    ],
    "name:rus_x_preferred":[
        "\u0428\u0430\u0440\u043f\u0430\u0435\u0432\u043a\u0430"
    ],
    "name:und_x_variant":[
        "Sharpayevskaya",
        "\u0428\u0430\u0440\u043f\u0430\u0435\u0432\u043a\u0430",
        "Sharpayevka"
    ],
    "wof:name":"Sharpayevka",
    "wof:placetype":"locality"
},
  "geometry": {"coordinates":[40.98639,48.58823],"type":"Point"}
}