{
  "type": "Feature",
  "properties": {
    "gn:admin1_code":"77.0",
    "gn:asciiname":"Dudentsy",
    "gn:country_code":"RU",
    "gn:dem":177,
    "gn:feature_class":"P",
    "gn:feature_code":"PPL",
    "gn:name":"Dudentsy",
    "gn:population":0,
    "gn:timezone":"Europe/Moscow",
    "iso:country":"RU",
    "name:nor_x_preferred":[
        "Dudentsy"
    ],
    "name:rus_x_preferred":[
        "\u0414\u0443\u0434\u0435\u043d\u0446\u044b"
    ],
    "name:und_x_variant":[
        "Dudnitsa",
        "Dudentsy"
    ],
    "wof:name":"Dudentsy",
    "wof:placetype":"locality"
},
  "geometry": {"coordinates":[35.82732,56.57603],"type":"Point"}
}