{
  "type": "Feature",
  "properties": {
    "gn:admin1_code":"51.0",
    "gn:asciiname":"Fedena",
    "gn:country_code":"RU",
    "gn:dem":104,
    "gn:feature_class":"P",
    "gn:feature_code":"PPL",
    "gn:name":"Fedena",
    "gn:population":0,
    "gn:timezone":"Europe/Moscow",
    "iso:country":"RU",
    "name:nor_x_preferred":[
        "Fedena"
    ],
    "name:rus_x_preferred":[
        "\u0424\u0435\u0434\u0435\u043d\u0430"
    ],
    "wof:name":"Fedena",
    "wof:placetype":"locality"
},
  "geometry": {"coordinates":[42.90164,56.68148000000001],"type":"Point"}
}