{
  "type": "Feature",
  "properties": {
    "gn:admin1_code":"16",
    "gn:asciiname":"Kaderkino",
    "gn:country_code":"RU",
    "gn:dem":155,
    "gn:feature_class":"P",
    "gn:feature_code":"PPL",
    "gn:name":"Kaderkino",
    "gn:population":0,
    "gn:timezone":"Europe/Moscow",
    "iso:country":"RU",
    "name:rus_x_preferred":[
        "\u041a\u0430\u0434\u0435\u0440\u043a\u0438\u043d\u043e"
    ],
    "name:und_x_variant":[
        "\u041a\u0430\u0434\u0435\u0440\u043a\u0438\u043d\u043e"
    ],
    "wof:name":"Kaderkino",
    "wof:placetype":"locality"
},
  "geometry": {"coordinates":[46.64061,55.64531],"type":"Point"}
}