{
  "type": "Feature",
  "properties": {
    "gn:admin1_code":"56",
    "gn:asciiname":"Shashkino",
    "gn:country_code":"RU",
    "gn:dem":149,
    "gn:feature_class":"P",
    "gn:feature_code":"PPL",
    "gn:name":"Shashkino",
    "gn:population":0,
    "gn:timezone":"Europe/Moscow",
    "iso:country":"RU",
    "name:eng_x_preferred":[
        "Shashkino"
    ],
    "name:nor_x_preferred":[
        "Sjasjkino"
    ],
    "name:rus_x_preferred":[
        "\u0428\u0430\u0448\u043a\u0438\u043d\u043e"
    ],
    "wof:name":"Shashkino",
    "wof:placetype":"locality"
},
  "geometry": {"coordinates":[36.42444,53.42083],"type":"Point"}
}