{
  "type": "Feature",
  "properties": {
    "gn:admin1_code":"51",
    "gn:asciiname":"Malaya Mikrikha",
    "gn:country_code":"RU",
    "gn:dem":147,
    "gn:feature_class":"P",
    "gn:feature_code":"PPL",
    "gn:name":"Malaya Mikrikha",
    "gn:population":0,
    "gn:timezone":"Europe/Moscow",
    "iso:country":"RU",
    "name:rus_x_preferred":[
        "\u041c\u0430\u043b\u0430\u044f \u041c\u0438\u043a\u0440\u0438\u0445\u0430"
    ],
    "wof:name":"Malaya Mikrikha",
    "wof:placetype":"locality"
},
  "geometry": {"coordinates":[45.8422,57.8849],"type":"Point"}
}