{
  "type": "Feature",
  "properties": {
    "gn:admin1_code":"25",
    "gn:asciiname":"Sereno-Zavod",
    "gn:country_code":"RU",
    "gn:dem":143,
    "gn:feature_class":"P",
    "gn:feature_code":"PPL",
    "gn:name":"Sereno-Zavod",
    "gn:population":0,
    "gn:timezone":"Europe/Moscow",
    "iso:country":"RU",
    "name:rus_x_preferred":[
        "\u0421\u0435\u0440\u0435\u043d\u043e-\u0417\u0430\u0432\u043e\u0434"
    ],
    "name:und_x_variant":[
        "Stereno-Zavod",
        "Sereno-Zavod",
        "\u0421\u0435\u0440\u0435\u043d\u043e-\u0417\u0430\u0432\u043e\u0434"
    ],
    "wof:name":"Sereno-Zavod",
    "wof:placetype":"locality"
},
  "geometry": {"coordinates":[35.844,54.14353000000001],"type":"Point"}
}