{
  "type": "Feature",
  "properties": {
    "gn:admin1_code":"69.0",
    "gn:asciiname":"Uchastok Desyatyy",
    "gn:country_code":"RU",
    "gn:dem":198,
    "gn:feature_class":"P",
    "gn:feature_code":"PPL",
    "gn:name":"Uchastok Desyatyy",
    "gn:population":0,
    "gn:timezone":"Europe/Moscow",
    "iso:country":"RU",
    "wof:name":"Uchastok Desyatyy",
    "wof:placetype":"locality"
},
  "geometry": {"coordinates":[34.03507,54.7518],"type":"Point"}
}