{
  "type": "Feature",
  "properties": {
    "gn:country":"RU",
    "gn:fcode":"PPL",
    "gn:pop":700,
    "iso:country":"RU",
    "name:rus_x_preferred":[
        "\u041f\u0430\u043d\u0441\u043a\u043e\u0435"
    ],
    "name:unk_x_variant":[
        "Panskoye"
    ],
    "qs:name":"Spasskoye",
    "qs:name_adm0":"Russia",
    "qs:name_adm1":"Kaluga Oblast",
    "qs:photos_9r":0,
    "qs:photos_sr":0,
    "qs:placetype":"Town",
    "qs:pop_sr":"2",
    "wd:wordcount":10,
    "wof:name":"Spasskoye",
    "wof:placetype":"locality",
    "wof:population":700
},
  "geometry": {"coordinates":[36.39191,55.0314],"type":"Point"}
}