{
  "type": "Feature",
  "properties": {
    "gn:admin1_code":"33.0",
    "gn:asciiname":"Tikhonenki",
    "gn:country_code":"RU",
    "gn:dem":129,
    "gn:feature_class":"P",
    "gn:feature_code":"PPL",
    "gn:name":"Tikhonenki",
    "gn:population":0,
    "gn:timezone":"Europe/Kirov",
    "iso:country":"RU",
    "name:rus_x_preferred":[
        "\u0422\u0438\u0445\u043e\u043d\u0435\u043d\u043a\u0438"
    ],
    "wof:name":"Tikhonenki",
    "wof:placetype":"locality"
},
  "geometry": {"coordinates":[48.71018,58.30597],"type":"Point"}
}