{
  "type": "Feature",
  "properties": {
    "gn:admin1_code":"52.0",
    "gn:asciiname":"Burtseva Gora",
    "gn:country_code":"RU",
    "gn:dem":72,
    "gn:feature_class":"P",
    "gn:feature_code":"PPL",
    "gn:name":"Burtseva Gora",
    "gn:population":0,
    "gn:timezone":"Europe/Moscow",
    "iso:country":"RU",
    "name:rus_x_preferred":[
        "\u0411\u0443\u0440\u0446\u0435\u0432\u0430 \u0413\u043e\u0440\u0430"
    ],
    "name:und_x_variant":[
        "\u0411\u0443\u0440\u0446\u0435\u0432\u0430 \u0413\u043e\u0440\u0430"
    ],
    "wof:name":"Burtseva Gora",
    "wof:placetype":"locality"
},
  "geometry": {"coordinates":[32.49579,58.63123],"type":"Point"}
}