{
  "type": "Feature",
  "properties": {
    "gn:admin1_code":"8",
    "gn:asciiname":"Tugayevo",
    "gn:country_code":"RU",
    "gn:dem":223,
    "gn:feature_class":"P",
    "gn:feature_code":"PPL",
    "gn:name":"Tugayevo",
    "gn:population":0,
    "gn:timezone":"Asia/Yekaterinburg",
    "iso:country":"RU",
    "name:bak_x_preferred":[
        "\u0422\u0443\u0493\u0430\u0439"
    ],
    "name:che_x_preferred":[
        "\u0422\u0443\u0433\u0430\u0435\u0432\u043e"
    ],
    "name:hye_x_preferred":[
        "\u054f\u0578\u0582\u0563\u0561\u0587\u0578"
    ],
    "name:kaz_x_preferred":[
        "\u0422\u0443\u0433\u0430"
    ],
    "name:rus_x_preferred":[
        "\u0422\u0443\u0433\u0430\u0435\u0432\u043e"
    ],
    "name:tat_x_preferred":[
        "\u0422\u0443\u0433\u0430\u0439"
    ],
    "wof:name":"Tugayevo",
    "wof:placetype":"locality"
},
  "geometry": {"coordinates":[54.36666999999999,54.86666999999999],"type":"Point"}
}