{
  "type": "Feature",
  "properties": {
    "gn:admin1_code":"65",
    "gn:asciiname":"Trukhmyanka",
    "gn:country_code":"RU",
    "gn:dem":36,
    "gn:feature_class":"P",
    "gn:feature_code":"PPL",
    "gn:name":"Trukhmyanka",
    "gn:population":0,
    "gn:timezone":"Europe/Samara",
    "iso:country":"RU",
    "name:rus_x_preferred":[
        "\u0422\u0440\u0443\u0445\u043c\u044f\u043d\u043a\u0430"
    ],
    "name:und_x_variant":[
        "Trukhlyanka",
        "Trukhmyanka"
    ],
    "wof:name":"Trukhmyanka",
    "wof:placetype":"locality"
},
  "geometry": {"coordinates":[50.444,53.57883],"type":"Point"}
}