{
  "type": "Feature",
  "properties": {
    "gn:admin1_code":"85",
    "gn:asciiname":"Shilovo",
    "gn:country_code":"RU",
    "gn:dem":153,
    "gn:feature_class":"P",
    "gn:feature_code":"PPL",
    "gn:name":"Shilovo",
    "gn:population":0,
    "gn:timezone":"Europe/Moscow",
    "iso:country":"RU",
    "name:rus_x_preferred":[
        "\u0428\u0438\u043b\u043e\u0432\u043e"
    ],
    "name:und_x_variant":[
        "\u0428\u0438\u043b\u043e\u0432\u043e"
    ],
    "wof:name":"Shilovo",
    "wof:placetype":"locality"
},
  "geometry": {"coordinates":[40.90615,58.74955],"type":"Point"}
}