{
  "type": "Feature",
  "properties": {
    "gn:admin1_code":"83.0",
    "gn:asciiname":"Maslenka",
    "gn:country_code":"RU",
    "gn:dem":152,
    "gn:feature_class":"P",
    "gn:feature_code":"PPL",
    "gn:name":"Maslenka",
    "gn:population":0,
    "gn:timezone":"Europe/Moscow",
    "iso:country":"RU",
    "name:rus_x_preferred":[
        "\u041c\u0430\u0441\u043b\u0435\u043d\u043a\u0430"
    ],
    "wof:name":"Maslenka",
    "wof:placetype":"locality"
},
  "geometry": {"coordinates":[40.3174,56.19863],"type":"Point"}
}