{
  "type": "Feature",
  "properties": {
    "gn:admin1_code":"52",
    "gn:asciiname":"Klinkovo",
    "gn:country_code":"RU",
    "gn:dem":37,
    "gn:feature_class":"P",
    "gn:feature_code":"PPL",
    "gn:name":"Klinkovo",
    "gn:population":0,
    "gn:timezone":"Europe/Moscow",
    "iso:country":"RU",
    "name:rus_x_preferred":[
        "\u041a\u043b\u0438\u043d\u043a\u043e\u0432\u043e"
    ],
    "wof:name":"Klinkovo",
    "wof:placetype":"locality"
},
  "geometry": {"coordinates":[31.3863,57.8368],"type":"Point"}
}