{
  "type": "Feature",
  "properties": {
    "gn:admin1_code":"6.0",
    "gn:asciiname":"Denisovskaya",
    "gn:country_code":"RU",
    "gn:dem":29,
    "gn:feature_class":"P",
    "gn:feature_code":"PPL",
    "gn:name":"Denisovskaya",
    "gn:population":0,
    "gn:timezone":"Europe/Moscow",
    "iso:country":"RU",
    "name:rus_x_preferred":[
        "\u0414\u0435\u043d\u0438\u0441\u043e\u0432\u0441\u043a\u0430\u044f"
    ],
    "name:und_x_variant":[
        "\u0414\u0435\u043d\u0438\u0441\u043e\u0432\u0441\u043a\u0430\u044f"
    ],
    "wof:name":"Denisovskaya",
    "wof:placetype":"locality"
},
  "geometry": {"coordinates":[42.13333,63.05],"type":"Point"}
}