{
  "type": "Feature",
  "properties": {
    "gn:admin1_code":"77",
    "gn:asciiname":"Kuznetsovo",
    "gn:country_code":"RU",
    "gn:dem":251,
    "gn:feature_class":"P",
    "gn:feature_code":"PPL",
    "gn:name":"Kuznetsovo",
    "gn:population":0,
    "gn:timezone":"Europe/Moscow",
    "iso:country":"RU",
    "name:rus_x_preferred":[
        "\u041a\u0443\u0437\u043d\u0435\u0442\u0441\u043e\u0432\u043e"
    ],
    "name:und_x_variant":[
        "\u041a\u0443\u0437\u043d\u0435\u0442\u0441\u043e\u0432\u043e"
    ],
    "wof:name":"Kuznetsovo",
    "wof:placetype":"locality"
},
  "geometry": {"coordinates":[31.97469,56.88401999999999],"type":"Point"}
}