{
  "type": "Feature",
  "properties": {
    "gn:admin1_code":"60",
    "gn:asciiname":"Zhevlachevo",
    "gn:country_code":"RU",
    "gn:dem":163,
    "gn:feature_class":"P",
    "gn:feature_code":"PPL",
    "gn:name":"Zhevlach\u00ebvo",
    "gn:population":0,
    "gn:timezone":"Europe/Moscow",
    "iso:country":"RU",
    "name:rus_x_preferred":[
        "\u0416\u0435\u0432\u043b\u0430\u0447\u0451\u0432\u043e"
    ],
    "name:und_x_variant":[
        "Zhevlach\u00ebvo"
    ],
    "wof:name":"Zhevlachevo",
    "wof:placetype":"locality"
},
  "geometry": {"coordinates":[29.9126,56.0972],"type":"Point"}
}