{
  "type": "Feature",
  "properties": {
    "gn:admin1_code":"85.0",
    "gn:asciiname":"Kholmok",
    "gn:country_code":"RU",
    "gn:dem":170,
    "gn:feature_class":"P",
    "gn:feature_code":"PPL",
    "gn:name":"Kholmok",
    "gn:population":0,
    "gn:timezone":"Europe/Moscow",
    "iso:country":"RU",
    "name:rus_x_preferred":[
        "\u0425\u043e\u043b\u043c\u043e\u043a"
    ],
    "wof:name":"Kholmok",
    "wof:placetype":"locality"
},
  "geometry": {"coordinates":[37.8302,60.4312],"type":"Point"}
}