{
  "type": "Feature",
  "properties": {
    "gn:admin1_code":"29",
    "gn:asciiname":"Terekhino",
    "gn:country_code":"RU",
    "gn:dem":179,
    "gn:feature_class":"P",
    "gn:feature_code":"PPL",
    "gn:name":"Ter\u00ebkhino",
    "gn:population":0,
    "gn:timezone":"Asia/Novokuznetsk",
    "iso:country":"RU",
    "name:eng_x_preferred":[
        "Ter\u00ebkhino"
    ],
    "name:nor_x_preferred":[
        "Terekhino"
    ],
    "name:rus_x_preferred":[
        "\u0422\u0435\u0440\u0435\u0445\u0438\u043d\u043e"
    ],
    "name:rus_x_variant":[
        "\u0422\u0435\u0440\u0451\u0445\u0438\u043d\u043e"
    ],
    "name:und_x_variant":[
        "Ter\u00ebkhina",
        "Ter\u00ebkhino"
    ],
    "wof:name":"Terekhino",
    "wof:placetype":"locality"
},
  "geometry": {"coordinates":[85.4958,55.3474],"type":"Point"}
}