{
  "type": "Feature",
  "properties": {
    "gn:admin1_code":"9",
    "gn:asciiname":"Bokov",
    "gn:country_code":"RU",
    "gn:dem":210,
    "gn:feature_class":"P",
    "gn:feature_code":"PPL",
    "gn:name":"Bokov",
    "gn:population":0,
    "gn:timezone":"Europe/Moscow",
    "iso:country":"RU",
    "name:rus_x_preferred":[
        "\u0411\u043e\u043a\u043e\u0432"
    ],
    "wof:name":"Bokov",
    "wof:placetype":"locality"
},
  "geometry": {"coordinates":[38.2758,50.9242],"type":"Point"}
}