{
  "type": "Feature",
  "properties": {
    "gn:admin1_code":"33",
    "gn:asciiname":"Verkhniye Iziverki",
    "gn:country_code":"RU",
    "gn:dem":101,
    "gn:feature_class":"P",
    "gn:feature_code":"PPL",
    "gn:name":"Verkhniye Iziverki",
    "gn:population":0,
    "gn:timezone":"Europe/Kirov",
    "iso:country":"RU",
    "name:und_x_variant":[
        "Verkhniye Izeverki",
        "Verkhniye Iziverki"
    ],
    "wof:name":"Verkhniye Iziverki",
    "wof:placetype":"locality"
},
  "geometry": {"coordinates":[51.01562,56.28927],"type":"Point"}
}