{
  "type": "Feature",
  "properties": {
    "gn:admin1_code":"33",
    "gn:asciiname":"Sibirskiy",
    "gn:country_code":"RU",
    "gn:dem":171,
    "gn:feature_class":"P",
    "gn:feature_code":"PPL",
    "gn:name":"Sibirskiy",
    "gn:population":0,
    "gn:timezone":"Europe/Kirov",
    "iso:country":"RU",
    "name:rus_x_preferred":[
        "\u0421\u0438\u0431\u0438\u0440\u0441\u043a\u0438\u0439"
    ],
    "name:und_x_variant":[
        "\u0421\u0438\u0431\u0438\u0440\u0441\u043a\u0438\u0439"
    ],
    "wof:name":"Sibirskiy",
    "wof:placetype":"locality"
},
  "geometry": {"coordinates":[50.88333,59.78333000000001],"type":"Point"}
}