{
  "type": "Feature",
  "properties": {
    "gn:admin1_code":"43",
    "gn:asciiname":"Staryy Kopyl",
    "gn:country_code":"RU",
    "gn:dem":189,
    "gn:feature_class":"P",
    "gn:feature_code":"PPL",
    "gn:name":"Staryy Kopyl",
    "gn:population":0,
    "gn:timezone":"Europe/Moscow",
    "iso:country":"RU",
    "name:rus_x_preferred":[
        "\u0421\u0442\u0430\u0440\u044b\u0439 \u041a\u043e\u043f\u044b\u043b"
    ],
    "name:und_x_variant":[
        "Stary Kopyl",
        "Staryy Kopyl",
        "\u0421\u0442\u0430\u0440\u044b\u0439 \u041a\u043e\u043f\u044b\u043b"
    ],
    "wof:name":"Staryy Kopyl",
    "wof:placetype":"locality"
},
  "geometry": {"coordinates":[38.90874,53.03473],"type":"Point"}
}