{
  "type": "Feature",
  "properties": {
    "gn:admin1_code":"25",
    "gn:asciiname":"Verkhneye Gul'tsovo",
    "gn:country_code":"RU",
    "gn:dem":205,
    "gn:feature_class":"P",
    "gn:feature_code":"PPL",
    "gn:name":"Verkhneye Gul\u2019tsovo",
    "gn:population":0,
    "gn:timezone":"Europe/Moscow",
    "iso:country":"RU",
    "name:eng_x_preferred":[
        "Gul'tsovo"
    ],
    "name:nor_x_preferred":[
        "Gultsevo"
    ],
    "name:rus_x_preferred":[
        "\u0413\u0443\u043b\u044c\u0446\u0435\u0432\u043e"
    ],
    "name:rus_x_variant":[
        "\u0413\u0443\u043b\u044c\u0446\u043e\u0432\u043e"
    ],
    "name:und_x_variant":[
        "Gul\u2019tsova",
        "Gul\u2019tsovo",
        "Verkhneye Gul\u2019tsovo",
        "\u0413\u0443\u043b\u044c\u0446\u043e\u0432\u043e"
    ],
    "wof:name":"Verkhneye Gul'tsovo",
    "wof:placetype":"locality"
},
  "geometry": {"coordinates":[35.0321,54.05588],"type":"Point"}
}