{
  "type": "Feature",
  "properties": {
    "gn:admin1_code":"73",
    "gn:asciiname":"Nyr'ya",
    "gn:country_code":"RU",
    "gn:dem":110,
    "gn:feature_class":"P",
    "gn:feature_code":"PPL",
    "gn:name":"Nyr\u2019ya",
    "gn:population":0,
    "gn:timezone":"Europe/Moscow",
    "iso:country":"RU",
    "name:rus_x_preferred":[
        "\u041d\u044b\u0440\u044c\u044f"
    ],
    "name:und_x_variant":[
        "Nyr\u2019ya"
    ],
    "wof:name":"Nyr'ya",
    "wof:placetype":"locality"
},
  "geometry": {"coordinates":[50.5831,56.1991],"type":"Point"}
}