{
  "type": "Feature",
  "properties": {
    "gn:admin1_code":"21",
    "gn:asciiname":"Knutikha",
    "gn:country_code":"RU",
    "gn:dem":111,
    "gn:feature_class":"P",
    "gn:feature_code":"PPL",
    "gn:name":"Knutikha",
    "gn:population":0,
    "gn:timezone":"Europe/Moscow",
    "iso:country":"RU",
    "name:rus_x_preferred":[
        "\u041a\u043d\u0443\u0442\u0438\u0445\u0430"
    ],
    "name:und_x_variant":[
        "\u041a\u043d\u0443\u0442\u0438\u0445\u0430"
    ],
    "wof:name":"Knutikha",
    "wof:placetype":"locality"
},
  "geometry": {"coordinates":[41.09463,56.77831],"type":"Point"}
}