{
  "type": "Feature",
  "properties": {
    "gn:admin1_code":"33",
    "gn:asciiname":"Chikishi",
    "gn:country_code":"RU",
    "gn:dem":173,
    "gn:feature_class":"P",
    "gn:feature_code":"PPL",
    "gn:name":"Chikishi",
    "gn:population":0,
    "gn:timezone":"Europe/Kirov",
    "iso:country":"RU",
    "name:rus_x_preferred":[
        "\u0427\u0438\u043a\u0438\u0448\u0438"
    ],
    "name:und_x_variant":[
        "\u0427\u0438\u043a\u0438\u0448\u0438"
    ],
    "wof:name":"Chikishi",
    "wof:placetype":"locality"
},
  "geometry": {"coordinates":[49.01514,58.06976],"type":"Point"}
}