{
  "type": "Feature",
  "properties": {
    "gn:admin1_code":"77",
    "gn:asciiname":"Malyye Kolodezi",
    "gn:country_code":"RU",
    "gn:dem":176,
    "gn:feature_class":"P",
    "gn:feature_code":"PPL",
    "gn:name":"Malyye Kolodezi",
    "gn:population":0,
    "gn:timezone":"Europe/Moscow",
    "iso:country":"RU",
    "name:rus_x_preferred":[
        "\u041c\u0430\u043b\u044b\u0435 \u041a\u043e\u043b\u043e\u0434\u0435\u0437\u0438"
    ],
    "wof:name":"Malyye Kolodezi",
    "wof:placetype":"locality"
},
  "geometry": {"coordinates":[35.08333,57.06667],"type":"Point"}
}