{
  "type": "Feature",
  "properties": {
    "gn:admin1_code":"88.0",
    "gn:asciiname":"Bol'shiye Mkhi",
    "gn:country_code":"RU",
    "gn:dem":153,
    "gn:feature_class":"P",
    "gn:feature_code":"PPL",
    "gn:name":"Bol\u2019shiye Mkhi",
    "gn:population":0,
    "gn:timezone":"Europe/Moscow",
    "iso:country":"RU",
    "name:eng_x_preferred":[
        "Bol'shiye Mkhi"
    ],
    "name:nor_x_preferred":[
        "Bolsjije Mkhi"
    ],
    "name:rus_x_preferred":[
        "\u0411\u043e\u043b\u044c\u0448\u0438\u0435 \u041c\u0445\u0438"
    ],
    "name:und_x_variant":[
        "\u0411\u043e\u043b\u044c\u0448\u0438\u0435 \u041c\u0445\u0438",
        "Bol\u2019shiye Mkhi"
    ],
    "wof:name":"Bol'shiye Mkhi",
    "wof:placetype":"locality"
},
  "geometry": {"coordinates":[38.97144,58.18167],"type":"Point"}
}