{
  "type": "Feature",
  "properties": {
    "gn:admin1_code":"41",
    "gn:asciiname":"Luboshevo",
    "gn:country_code":"RU",
    "gn:dem":187,
    "gn:feature_class":"P",
    "gn:feature_code":"PPL",
    "gn:name":"Luboshevo",
    "gn:population":0,
    "gn:timezone":"Europe/Moscow",
    "iso:country":"RU",
    "name:rus_x_preferred":[
        "\u041b\u0443\u0431\u043e\u0448\u0435\u0432\u043e"
    ],
    "wof:name":"Luboshevo",
    "wof:placetype":"locality"
},
  "geometry": {"coordinates":[35.1602,52.32100000000001],"type":"Point"}
}