{
  "type": "Feature",
  "properties": {
    "gn:country":"RU",
    "gn:fcode":"PPL",
    "gn:pop":10541,
    "iso:country":"RU",
    "name:arm_x_preferred":[
        "\u0544\u0578\u0577\u056f\u0578\u057e\u0578"
    ],
    "name:che_x_preferred":[
        "\u041c\u043e\u0448\u043a\u043e\u0432\u043e"
    ],
    "name:dut_x_preferred":[
        "Mosjkovo"
    ],
    "name:eng_x_preferred":[
        "Moshkovo"
    ],
    "name:ger_x_preferred":[
        "Moschkowo"
    ],
    "name:hsb_x_preferred":[
        "Mo\u0161kowo"
    ],
    "name:ita_x_preferred":[
        "Mo\u0161kovo"
    ],
    "name:rus_x_preferred":[
        "\u041c\u043e\u0448\u043a\u043e\u0432\u043e"
    ],
    "name:unk_x_variant":[
        "Moschkowo"
    ],
    "qs:name":"Moshkovo",
    "qs:name_adm0":"Russia",
    "qs:name_adm1":"Novosibirsk Oblast",
    "qs:photos_9k":1,
    "qs:photos_9r":1,
    "qs:photos_all":1,
    "qs:photos_sr":0,
    "qs:placetype":"Town",
    "qs:pop_sr":"6",
    "wd:wordcount":151,
    "wof:name":"Moshkovo",
    "wof:placetype":"locality",
    "wof:population":10541
},
  "geometry": {"coordinates":[83.6104,55.3053],"type":"Point"}
}