{
  "type": "Feature",
  "properties": {
    "gn:admin1_code":"37",
    "gn:asciiname":"Anikovo",
    "gn:country_code":"RU",
    "gn:dem":168,
    "gn:feature_class":"P",
    "gn:feature_code":"PPL",
    "gn:name":"Anikovo",
    "gn:population":0,
    "gn:timezone":"Europe/Moscow",
    "iso:country":"RU",
    "name:rus_x_preferred":[
        "\u0410\u043d\u0438\u043a\u043e\u0432\u043e"
    ],
    "wof:name":"Anikovo",
    "wof:placetype":"locality"
},
  "geometry": {"coordinates":[42.5918,58.8716],"type":"Point"}
}