{
  "type": "Feature",
  "properties": {
    "gn:admin1_code":"69",
    "gn:asciiname":"Krivtsy",
    "gn:country_code":"RU",
    "gn:dem":228,
    "gn:feature_class":"P",
    "gn:feature_code":"PPL",
    "gn:name":"Krivtsy",
    "gn:population":0,
    "gn:timezone":"Europe/Moscow",
    "iso:country":"RU",
    "name:che_x_preferred":[
        "\u041a\u0440\u0438\u0432\u0446\u044b"
    ],
    "name:rus_x_preferred":[
        "\u041a\u0440\u0438\u0432\u0446\u044b"
    ],
    "name:und_x_variant":[
        "\u041a\u0440\u0438\u0432\u0446\u044b"
    ],
    "wof:name":"Krivtsy",
    "wof:placetype":"locality"
},
  "geometry": {"coordinates":[32.52139,55.32],"type":"Point"}
}