{
  "type": "Feature",
  "properties": {
    "gn:admin1_code":"24",
    "gn:asciiname":"Kirovskiy",
    "gn:country_code":"RU",
    "gn:dem":47,
    "gn:feature_class":"P",
    "gn:feature_code":"PPL",
    "gn:name":"Kirovskiy",
    "gn:population":0,
    "gn:timezone":"Europe/Moscow",
    "iso:country":"RU",
    "name:eng_x_preferred":[
        "Kirovskiy"
    ],
    "name:nor_x_preferred":[
        "Kirovskij"
    ],
    "name:rus_x_preferred":[
        "\u041a\u0438\u0440\u043e\u0432\u0441\u043a\u0438\u0439"
    ],
    "name:und_x_variant":[
        "Zharkov",
        "Kochubeyevo-Zharkov",
        "\u041a\u0438\u0440\u043e\u0432\u0441\u043a\u0438\u0439",
        "Kirovskiy"
    ],
    "wof:name":"Kirovskiy",
    "wof:placetype":"locality"
},
  "geometry": {"coordinates":[44.5059,47.6465],"type":"Point"}
}