{
  "type": "Feature",
  "properties": {
    "gn:admin1_code":"53",
    "gn:asciiname":"Ivankino",
    "gn:cc2":"RU",
    "gn:country_code":"RU",
    "gn:dem":129,
    "gn:feature_class":"P",
    "gn:feature_code":"PPL",
    "gn:name":"Ivankino",
    "gn:population":0,
    "gn:timezone":"Asia/Novosibirsk",
    "iso:country":"RU",
    "name:eng_x_preferred":[
        "Ivankino"
    ],
    "name:nor_x_preferred":[
        "Ivankino"
    ],
    "name:rus_x_preferred":[
        "\u0418\u0432\u0430\u043d\u043a\u0438\u043d\u043e"
    ],
    "name:und_x_variant":[
        "Ivankinskiy"
    ],
    "wof:name":"Ivankino",
    "wof:placetype":"locality"
},
  "geometry": {"coordinates":[79.90944,54.88861],"type":"Point"}
}