{
  "type": "Feature",
  "properties": {
    "gn:admin1_code":"37.0",
    "gn:asciiname":"Chelpanovo",
    "gn:country_code":"RU",
    "gn:dem":133,
    "gn:feature_class":"P",
    "gn:feature_code":"PPL",
    "gn:name":"Chelpanovo",
    "gn:population":0,
    "gn:timezone":"Europe/Moscow",
    "iso:country":"RU",
    "name:eng_x_preferred":[
        "Chelpanovo"
    ],
    "name:nor_x_preferred":[
        "Tsjelpanovo"
    ],
    "name:rus_x_preferred":[
        "\u0427\u0435\u043b\u043f\u0430\u043d\u043e\u0432\u043e"
    ],
    "wof:name":"Chelpanovo",
    "wof:placetype":"locality"
},
  "geometry": {"coordinates":[40.7007,57.57764],"type":"Point"}
}