{
  "type": "Feature",
  "properties": {
    "gn:admin1_code":"54",
    "gn:asciiname":"Borisovskoye",
    "gn:country_code":"RU",
    "gn:dem":109,
    "gn:feature_class":"P",
    "gn:feature_code":"PPL",
    "gn:name":"Borisovskoye",
    "gn:population":0,
    "gn:timezone":"Asia/Omsk",
    "iso:country":"RU",
    "name:eng_x_preferred":[
        "Borisovskoye"
    ],
    "name:nor_x_preferred":[
        "Borisovskoje"
    ],
    "name:rus_x_preferred":[
        "\u0411\u043e\u0440\u0438\u0441\u043e\u0432\u0441\u043a\u043e\u0435"
    ],
    "name:und_x_variant":[
        "Borisovskiy"
    ],
    "wof:name":"Borisovskoye",
    "wof:placetype":"locality"
},
  "geometry": {"coordinates":[72.58551,54.62446],"type":"Point"}
}