{
  "type": "Feature",
  "properties": {
    "iso:country":"RU",
    "name:rus_x_preferred":[
        "\u0412\u043d\u0443\u043a\u043e\u0432\u043e"
    ],
    "wof:name":"Vnukovo",
    "wof:placetype":"neighbourhood"
},
  "geometry": {"coordinates":[37.28903468548271,55.60721729402116],"type":"Point"}
}