{
  "type": "Feature",
  "properties": {
    "gn:admin1_code":"88",
    "gn:asciiname":"Dubovitsy",
    "gn:country_code":"RU",
    "gn:dem":96,
    "gn:feature_class":"P",
    "gn:feature_code":"PPL",
    "gn:name":"Dubovitsy",
    "gn:population":0,
    "gn:timezone":"Europe/Moscow",
    "iso:country":"RU",
    "name:rus_x_preferred":[
        "\u0414\u0443\u0431\u043e\u0432\u0438\u0446\u044b"
    ],
    "name:und_x_variant":[
        "Dubovitsa",
        "Dubovitsy"
    ],
    "wof:name":"Dubovitsy",
    "wof:placetype":"locality"
},
  "geometry": {"coordinates":[39.57375,57.62419000000001],"type":"Point"}
}