{
  "type": "Feature",
  "properties": {
    "gn:admin1_code":"61.0",
    "gn:asciiname":"Leninskiy",
    "gn:country_code":"RU",
    "gn:dem":122,
    "gn:feature_class":"P",
    "gn:feature_code":"PPL",
    "gn:name":"Leninskiy",
    "gn:population":0,
    "gn:timezone":"Europe/Moscow",
    "iso:country":"RU",
    "name:rus_x_preferred":[
        "\u041b\u0435\u043d\u0438\u043d\u0441\u043a\u0438\u0439"
    ],
    "name:ukr_x_preferred":[
        "Lenins\u2019kyy"
    ],
    "name:und_x_variant":[
        "Mar\u2019yevka"
    ],
    "wof:name":"Leninskiy",
    "wof:placetype":"locality"
},
  "geometry": {"coordinates":[38.83389,47.75139],"type":"Point"}
}