{
  "type": "Feature",
  "properties": {
    "gn:admin1_code":"59.0",
    "gn:asciiname":"Filaretovka",
    "gn:country_code":"RU",
    "gn:dem":70,
    "gn:feature_class":"P",
    "gn:feature_code":"PPL",
    "gn:name":"Filaretovka",
    "gn:population":0,
    "gn:timezone":"Asia/Vladivostok",
    "iso:country":"RU",
    "name:nor_x_preferred":[
        "Filaretovka"
    ],
    "name:rus_x_preferred":[
        "\u0424\u0438\u043b\u0430\u0440\u0435\u0442\u043e\u0432\u043a\u0430"
    ],
    "wof:name":"Filaretovka",
    "wof:placetype":"locality"
},
  "geometry": {"coordinates":[133.51868000000002,45.55607],"type":"Point"}
}