{
  "type": "Feature",
  "properties": {
    "gn:admin1_code":"60",
    "gn:asciiname":"Kitovo",
    "gn:country_code":"RU",
    "gn:dem":192,
    "gn:feature_class":"P",
    "gn:feature_code":"PPL",
    "gn:name":"Kitovo",
    "gn:population":0,
    "gn:timezone":"Europe/Moscow",
    "iso:country":"RU",
    "name:rus_x_preferred":[
        "\u041a\u0438\u0442\u043e\u0432\u043e"
    ],
    "wof:name":"Kitovo",
    "wof:placetype":"locality"
},
  "geometry": {"coordinates":[29.9093,56.8372],"type":"Point"}
}