{
  "type": "Feature",
  "properties": {
    "gn:admin1_code":"85.0",
    "gn:asciiname":"Krapivinskaya",
    "gn:country_code":"RU",
    "gn:dem":162,
    "gn:feature_class":"P",
    "gn:feature_code":"PPL",
    "gn:name":"Krapivinskaya",
    "gn:population":0,
    "gn:timezone":"Europe/Moscow",
    "iso:country":"RU",
    "name:rus_x_preferred":[
        "\u041a\u0440\u0430\u043f\u0438\u0432\u0438\u043d\u0441\u043a\u0430\u044f"
    ],
    "wof:name":"Krapivinskaya",
    "wof:placetype":"locality"
},
  "geometry": {"coordinates":[38.48,60.1368],"type":"Point"}
}