{
  "type": "Feature",
  "properties": {
    "gn:admin1_code":"42",
    "gn:asciiname":"Yustila",
    "gn:cc2":"RU",
    "gn:country_code":"RU",
    "gn:dem":24,
    "gn:feature_class":"P",
    "gn:feature_code":"PPL",
    "gn:name":"Yustila",
    "gn:population":0,
    "gn:timezone":"Europe/Moscow",
    "iso:country":"RU",
    "name:fin_x_preferred":[
        "Juustila"
    ],
    "name:und_x_variant":[
        "Yuustila",
        "Yustila"
    ],
    "wof:name":"Yustila",
    "wof:placetype":"locality"
},
  "geometry": {"coordinates":[28.73508,60.81019000000001],"type":"Point"}
}