{
  "type": "Feature",
  "properties": {
    "gn:admin1_code":"42",
    "gn:asciiname":"Zagub'ye",
    "gn:country_code":"RU",
    "gn:dem":13,
    "gn:feature_class":"P",
    "gn:feature_code":"PPL",
    "gn:name":"Zagub\u2019ye",
    "gn:population":0,
    "gn:timezone":"Europe/Moscow",
    "iso:country":"RU",
    "name:eng_x_preferred":[
        "Zagub'ye"
    ],
    "name:nor_x_preferred":[
        "Zagubje"
    ],
    "name:rus_x_preferred":[
        "\u0417\u0430\u0433\u0443\u0431\u044c\u0435"
    ],
    "name:und_x_variant":[
        "Zagub\u2019ye"
    ],
    "wof:name":"Zagub'ye",
    "wof:placetype":"locality"
},
  "geometry": {"coordinates":[32.7609,60.42977],"type":"Point"}
}