{
  "type": "Feature",
  "properties": {
    "gn:admin1_code":"83",
    "gn:asciiname":"Rodmevo",
    "gn:country_code":"RU",
    "gn:dem":142,
    "gn:feature_class":"P",
    "gn:feature_code":"PPL",
    "gn:name":"Rodm\u00ebvo",
    "gn:population":0,
    "gn:timezone":"Europe/Moscow",
    "iso:country":"RU",
    "name:rus_x_preferred":[
        "\u0420\u043e\u0434\u043c\u0451\u0432\u043e"
    ],
    "name:und_x_variant":[
        "Rodm\u00ebvo",
        "\u0420\u043e\u0434\u043c\u0451\u0432\u043e"
    ],
    "wof:name":"Rodmevo",
    "wof:placetype":"locality"
},
  "geometry": {"coordinates":[40.85,55.58333],"type":"Point"}
}