{
  "type": "Feature",
  "properties": {
    "gn:admin1_code":"60",
    "gn:asciiname":"Shchir",
    "gn:country_code":"RU",
    "gn:dem":145,
    "gn:feature_class":"P",
    "gn:feature_code":"PPL",
    "gn:name":"Shchir",
    "gn:population":0,
    "gn:timezone":"Europe/Moscow",
    "iso:country":"RU",
    "name:rus_x_preferred":[
        "\u0429\u0438\u0440"
    ],
    "name:und_x_variant":[
        "\u0429\u0438\u0440"
    ],
    "wof:name":"Shchir",
    "wof:placetype":"locality"
},
  "geometry": {"coordinates":[29.05016,58.32384],"type":"Point"}
}