{
  "type": "Feature",
  "properties": {
    "gn:admin1_code":"47.0",
    "gn:admin2_code":"536086",
    "gn:asciiname":"Aparinki",
    "gn:country_code":"RU",
    "gn:dem":164,
    "gn:feature_class":"P",
    "gn:feature_code":"PPL",
    "gn:name":"Aparinki",
    "gn:population":0,
    "gn:timezone":"Europe/Moscow",
    "iso:country":"RU",
    "name:nor_x_preferred":[
        "Aparinki"
    ],
    "name:rus_x_preferred":[
        "\u0410\u043f\u0430\u0440\u0438\u043d\u043a\u0438"
    ],
    "wof:name":"Aparinki",
    "wof:placetype":"locality"
},
  "geometry": {"coordinates":[37.75833,55.57028],"type":"Point"}
}