{
  "type": "Feature",
  "properties": {
    "gn:admin1_code":"56",
    "gn:asciiname":"Kusty",
    "gn:country_code":"RU",
    "gn:dem":224,
    "gn:feature_class":"P",
    "gn:feature_code":"PPL",
    "gn:name":"Kusty",
    "gn:population":0,
    "gn:timezone":"Europe/Moscow",
    "iso:country":"RU",
    "name:rus_x_preferred":[
        "\u041a\u0443\u0441\u0442\u044b"
    ],
    "name:und_x_variant":[
        "\u041a\u0443\u0441\u0442\u044b"
    ],
    "wof:name":"Kusty",
    "wof:placetype":"locality"
},
  "geometry": {"coordinates":[36.15452,52.75051],"type":"Point"}
}