{
  "type": "Feature",
  "properties": {
    "gn:country":"RU",
    "gn:fcode":"PPL",
    "gn:population":6347,
    "iso:country":"RU",
    "name:bel_x_preferred":[
        "\u041e\u043b\u0430"
    ],
    "name:bul_x_preferred":[
        "\u041e\u043b\u0430"
    ],
    "name:ceb_x_preferred":[
        "Ola"
    ],
    "name:che_x_preferred":[
        "\u041e\u043b\u0430"
    ],
    "name:deu_x_preferred":[
        "Ola"
    ],
    "name:eng_x_preferred":[
        "Ola"
    ],
    "name:fin_x_preferred":[
        "Ola"
    ],
    "name:fra_x_preferred":[
        "Ola"
    ],
    "name:hye_x_preferred":[
        "\u0555\u056c\u0561"
    ],
    "name:ita_x_preferred":[
        "Ola"
    ],
    "name:nld_x_preferred":[
        "Ola"
    ],
    "name:nor_x_preferred":[
        "Ola"
    ],
    "name:pol_x_preferred":[
        "O\u0142a"
    ],
    "name:rus_x_preferred":[
        "\u041e\u043b\u0430"
    ],
    "name:spa_x_preferred":[
        "Ol\u00e1"
    ],
    "name:swe_x_preferred":[
        "Ola"
    ],
    "name:tgl_x_preferred":[
        "Ola"
    ],
    "name:ukr_x_preferred":[
        "\u041e\u043b\u0430"
    ],
    "name:zho_x_preferred":[
        "\u5967\u62c9"
    ],
    "qs:name":"Ola",
    "qs:photos_9r":0,
    "qs:photos_sr":0,
    "qs:pop_sr":"5",
    "wd:wordcount":311,
    "wof:name":"Ola",
    "wof:placetype":"locality",
    "wof:population":6347
},
  "geometry": {"coordinates":[151.29819000000001,59.57823],"type":"Point"}
}