{
  "type": "Feature",
  "properties": {
    "gn:admin1_code":"60",
    "gn:asciiname":"Zeyby",
    "gn:country_code":"RU",
    "gn:dem":91,
    "gn:feature_class":"P",
    "gn:feature_code":"PPL",
    "gn:name":"Zeyby",
    "gn:population":0,
    "gn:timezone":"Europe/Moscow",
    "iso:country":"RU",
    "name:rus_x_preferred":[
        "\u0417\u0435\u0439\u0431\u044b"
    ],
    "wof:name":"Zeyby",
    "wof:placetype":"locality"
},
  "geometry": {"coordinates":[28.02301,56.94694000000001],"type":"Point"}
}