{
  "type": "Feature",
  "properties": {
    "gn:admin1_code":"73",
    "gn:admin2_code":"536160",
    "gn:asciiname":"Gorkino",
    "gn:country_code":"RU",
    "gn:dem":220,
    "gn:feature_class":"P",
    "gn:feature_code":"PPL",
    "gn:name":"Gorkino",
    "gn:population":0,
    "gn:timezone":"Europe/Moscow",
    "iso:country":"RU",
    "name:rus_x_preferred":[
        "\u0413\u043e\u0440\u043a\u0438\u043d\u043e"
    ],
    "wof:name":"Gorkino",
    "wof:placetype":"locality"
},
  "geometry": {"coordinates":[52.4087,54.64906],"type":"Point"}
}