{
  "type": "Feature",
  "properties": {
    "gn:admin1_code":"65",
    "gn:asciiname":"Vodnyy",
    "gn:country_code":"RU",
    "gn:dem":154,
    "gn:feature_class":"P",
    "gn:feature_code":"PPL",
    "gn:name":"Vodnyy",
    "gn:population":0,
    "gn:timezone":"Europe/Samara",
    "iso:country":"RU",
    "name:rus_x_preferred":[
        "\u0412\u043e\u0434\u043d\u044b\u0439"
    ],
    "name:und_x_variant":[
        "Vodny",
        "Vodnyy"
    ],
    "wof:name":"Vodnyy",
    "wof:placetype":"locality"
},
  "geometry": {"coordinates":[50.52657,53.46084000000001],"type":"Point"}
}