{
  "type": "Feature",
  "properties": {
    "gn:admin1_code":"8",
    "gn:asciiname":"Staroatnagulovo",
    "gn:country_code":"RU",
    "gn:dem":156,
    "gn:feature_class":"P",
    "gn:feature_code":"PPL",
    "gn:name":"Staroatnagulovo",
    "gn:population":0,
    "gn:timezone":"Asia/Yekaterinburg",
    "iso:country":"RU",
    "name:rus_x_preferred":[
        "\u0421\u0442\u0430\u0440\u043e\u0430\u0442\u043d\u0430\u0433\u0443\u043b\u043e\u0432\u043e"
    ],
    "name:und_x_variant":[
        "Staroye Atnagulovo",
        "Staroatnagulovo"
    ],
    "wof:name":"Staroatnagulovo",
    "wof:placetype":"locality"
},
  "geometry": {"coordinates":[55.96454,55.69519],"type":"Point"}
}