{
  "type": "Feature",
  "properties": {
    "gn:admin1_code":"34",
    "gn:asciiname":"Kunib",
    "gn:country_code":"RU",
    "gn:dem":107,
    "gn:feature_class":"P",
    "gn:feature_code":"PPL",
    "gn:name":"Kunib",
    "gn:population":0,
    "gn:timezone":"Europe/Moscow",
    "iso:country":"RU",
    "name:rus_x_preferred":[
        "\u041a\u0443\u043d\u0438\u0431"
    ],
    "wof:name":"Kunib",
    "wof:placetype":"locality"
},
  "geometry": {"coordinates":[50.25916,61.12201999999999],"type":"Point"}
}