{
  "type": "Feature",
  "properties": {
    "gn:admin1_code":"77",
    "gn:asciiname":"Mashutino",
    "gn:country_code":"RU",
    "gn:dem":282,
    "gn:feature_class":"P",
    "gn:feature_code":"PPL",
    "gn:name":"Mashutino",
    "gn:population":0,
    "gn:timezone":"Europe/Moscow",
    "iso:country":"RU",
    "wof:name":"Mashutino",
    "wof:placetype":"locality"
},
  "geometry": {"coordinates":[33.34862,56.44355],"type":"Point"}
}