{
  "type": "Feature",
  "properties": {
    "gn:admin1_code":"8",
    "gn:asciiname":"Rayevskiy",
    "gn:country_code":"RU",
    "gn:dem":137,
    "gn:feature_class":"P",
    "gn:feature_code":"PPL",
    "gn:name":"Rayevskiy",
    "gn:population":0,
    "gn:timezone":"Asia/Yekaterinburg",
    "iso:country":"RU",
    "name:rus_x_preferred":[
        "\u0420\u0430\u0435\u0432\u0441\u043a\u0438\u0439"
    ],
    "name:und_x_variant":[
        "\u0420\u0430\u0435\u0432\u0441\u043a\u0438\u0439"
    ],
    "wof:name":"Rayevskiy",
    "wof:placetype":"locality"
},
  "geometry": {"coordinates":[55.78333000000001,53.46666999999999],"type":"Point"}
}