{
  "type": "Feature",
  "properties": {
    "gn:admin1_code":"8",
    "gn:asciiname":"Rayevskiy",
    "gn:country_code":"RU",
    "gn:dem":137,
    "gn:feature_class":"P",
    "gn:feature_code":"PPL",
    "gn:name":"Rayevskiy",
    "gn:population":0,
    "gn:timezone":"Asia/Yekaterinburg",
    "iso:country":"RU",
    "name:ben_x_preferred":[
        "\u09b0\u09be\u09df\u09c7\u09ad\u09b8\u09cd\u0995\u09bf"
    ],
    "name:ell_x_preferred":[
        "\u03a1\u03b1\u03b3\u03b9\u03ad\u03c6\u03c3\u03ba\u03b9"
    ],
    "name:fas_x_preferred":[
        "\u0631\u0627\u06cc\u0641\u0633\u06a9\u06cc"
    ],
    "name:fra_x_preferred":[
        "Raevo"
    ],
    "name:heb_x_preferred":[
        "\u05e8\u05d9\u05d9\u05d1\u05e1\u05e7\u05d9\u05d9"
    ],
    "name:hin_x_preferred":[
        "\u0930\u093e\u092f\u0947\u0935\u094d\u0938\u094d\u0915\u0940\u092f"
    ],
    "name:ind_x_preferred":[
        "Rayevskiy"
    ],
    "name:ita_x_preferred":[
        "Rayevskiy"
    ],
    "name:jpn_x_preferred":[
        "\u30ec\u30a4\u30a8\u30d5\u30b9\u30ad\u30fc"
    ],
    "name:kor_x_preferred":[
        "\ub77c\uc608\ud504\uc2a4\ud0a4"
    ],
    "name:rus_x_preferred":[
        "\u0420\u0430\u0435\u0432\u0441\u043a\u0438\u0439"
    ],
    "name:spa_x_preferred":[
        "Rayevskiy"
    ],
    "name:swe_x_preferred":[
        "Rajevskij"
    ],
    "name:tur_x_preferred":[
        "Rayevskiy"
    ],
    "name:urd_x_preferred":[
        "\u0631\u06cc\u0648\u06cc\u0633\u06a9\u0627\u0626\u06d2"
    ],
    "name:vie_x_preferred":[
        "Rayevskiy"
    ],
    "name:zho_cn_x_preferred":[
        "\u96f7\u8036\u592b\u65af\u57fa"
    ],
    "name:zho_tw_x_preferred":[
        "\u96f7\u8036\u592b\u65af\u57fa"
    ],
    "wof:name":"Rayevskiy",
    "wof:placetype":"locality"
},
  "geometry": {"coordinates":[55.78333,53.46667],"type":"Point"}
}