{
  "type": "Feature",
  "properties": {
    "gn:admin1_code":"78",
    "gn:asciiname":"Keum",
    "gn:country_code":"RU",
    "gn:dem":67,
    "gn:feature_class":"P",
    "gn:feature_code":"PPL",
    "gn:name":"Keum",
    "gn:population":0,
    "gn:timezone":"Asia/Yekaterinburg",
    "iso:country":"RU",
    "name:rus_x_preferred":[
        "\u041a\u0435\u0443\u043c"
    ],
    "wof:name":"Keum",
    "wof:placetype":"locality"
},
  "geometry": {"coordinates":[71.18600000000001,59.6245],"type":"Point"}
}