{
  "type": "Feature",
  "properties": {
    "gn:admin1_code":"52",
    "gn:asciiname":"Zhelonka",
    "gn:country_code":"RU",
    "gn:dem":185,
    "gn:feature_class":"P",
    "gn:feature_code":"PPL",
    "gn:name":"Zhelonka",
    "gn:population":0,
    "gn:timezone":"Europe/Moscow",
    "iso:country":"RU",
    "name:rus_x_preferred":[
        "\u0416\u0435\u043b\u043e\u043d\u043a\u0430"
    ],
    "wof:name":"Zhelonka",
    "wof:placetype":"locality"
},
  "geometry": {"coordinates":[31.95833,57.12056],"type":"Point"}
}