{
  "type": "Feature",
  "properties": {
    "gn:admin1_code":"79",
    "gn:asciiname":"Avyygan",
    "gn:country_code":"RU",
    "gn:dem":938,
    "gn:feature_class":"P",
    "gn:feature_code":"PPL",
    "gn:name":"Avyygan",
    "gn:population":0,
    "gn:timezone":"Asia/Krasnoyarsk",
    "iso:country":"RU",
    "name:eng_x_preferred":[
        "Avyygan"
    ],
    "name:nor_x_preferred":[
        "Avyjgan"
    ],
    "name:rus_x_preferred":[
        "\u0410\u0432\u044b\u0439\u0433\u0430\u043d"
    ],
    "name:und_x_variant":[
        "\u0410\u0432\u044b\u0439\u0433\u0430\u043d",
        "Avyygan"
    ],
    "wof:name":"Avyygan",
    "wof:placetype":"locality"
},
  "geometry": {"coordinates":[95.55,51.35],"type":"Point"}
}