{
  "type": "Feature",
  "properties": {
    "gn:admin1_code":"34",
    "gn:asciiname":"Klimovsk",
    "gn:country_code":"RU",
    "gn:dem":126,
    "gn:feature_class":"P",
    "gn:feature_code":"PPL",
    "gn:name":"Klimovsk",
    "gn:population":0,
    "gn:timezone":"Europe/Moscow",
    "iso:country":"RU",
    "name:ara_x_preferred":[
        "\u0643\u0644\u064a\u0645\u0648\u0641\u0633\u0643"
    ],
    "name:azb_x_preferred":[
        "\u06a9\u0644\u06cc\u0645\u0648\u0641\u0633\u06a9"
    ],
    "name:bel_x_preferred":[
        "\u041a\u043b\u0456\u043c\u0430\u045e\u0441\u043a"
    ],
    "name:bul_x_preferred":[
        "\u041a\u043b\u0438\u043c\u043e\u0432\u0441\u043a"
    ],
    "name:ceb_x_preferred":[
        "Klimovsk"
    ],
    "name:ces_x_preferred":[
        "Klimovsk"
    ],
    "name:che_x_preferred":[
        "\u041a\u043b\u0438\u043c\u043e\u0432\u0441\u043a"
    ],
    "name:deu_x_preferred":[
        "Klimowsk"
    ],
    "name:eng_x_preferred":[
        "Klimovsk"
    ],
    "name:epo_x_preferred":[
        "Klimovsk"
    ],
    "name:est_x_preferred":[
        "Klimovsk"
    ],
    "name:fas_x_preferred":[
        "\u06a9\u0644\u06cc\u0645\u0648\u0641\u0633\u06a9"
    ],
    "name:fin_x_preferred":[
        "Klimovsk"
    ],
    "name:fra_x_preferred":[
        "Klimovsk"
    ],
    "name:hsb_x_preferred":[
        "Klimowsk"
    ],
    "name:ita_x_preferred":[
        "Klimovsk"
    ],
    "name:jpn_x_preferred":[
        "\u30af\u30ea\u30e2\u30d5\u30b9\u30af"
    ],
    "name:kor_x_preferred":[
        "\ud074\ub9ac\ubab9\uc2a4\ud06c"
    ],
    "name:lav_x_preferred":[
        "K\u013cimovska"
    ],
    "name:lit_x_preferred":[
        "Klimovskas"
    ],
    "name:nno_x_preferred":[
        "Klimovsk"
    ],
    "name:nor_x_preferred":[
        "Klimovsk"
    ],
    "name:pnb_x_preferred":[
        "\u06a9\u0644\u06cc\u0645\u0648\u0648\u0633\u06a9"
    ],
    "name:pol_x_preferred":[
        "Klimowsk"
    ],
    "name:por_x_preferred":[
        "Klimovsk"
    ],
    "name:ron_x_preferred":[
        "Klimovsk"
    ],
    "name:rus_x_preferred":[
        "\u041a\u043b\u0438\u043c\u043e\u0432\u0441\u043a"
    ],
    "name:sah_x_preferred":[
        "\u041a\u043b\u0438\u043c\u043e\u0432\u0441\u043a\u0430\u0439"
    ],
    "name:srp_x_preferred":[
        "\u041a\u043b\u0438\u043c\u043e\u0432\u0441\u043a"
    ],
    "name:tat_x_preferred":[
        "\u041a\u043b\u0438\u043c\u043e\u0432\u0441\u043a"
    ],
    "name:tgk_x_preferred":[
        "\u041a\u043b\u0438\u043c\u043e\u0432\u0441\u043a"
    ],
    "name:tgl_x_preferred":[
        "Klimovsk"
    ],
    "name:tur_x_preferred":[
        "Klimovsk"
    ],
    "name:ukr_x_preferred":[
        "\u041a\u043b\u0438\u043c\u043e\u0432\u0441\u044c\u043a"
    ],
    "name:und_x_variant":[
        "Klimov",
        "\u041a\u043b\u0438\u043c\u043e\u0432\u0441\u043a",
        "Klimovsk"
    ],
    "name:vie_x_preferred":[
        "Klimovsk"
    ],
    "name:war_x_preferred":[
        "Klimovsk"
    ],
    "name:xal_x_preferred":[
        "\u041a\u043b\u0438\u043c\u043e\u0432\u0441\u043a \u0431\u0430\u043b\u04bb\u0441\u043d"
    ],
    "name:zho_x_preferred":[
        "\u514b\u5229\u83ab\u592b\u65af\u514b"
    ],
    "wof:name":"Klimovsk",
    "wof:placetype":"locality"
},
  "geometry": {"coordinates":[53.64803000000001,61.28632],"type":"Point"}
}