{
  "type": "Feature",
  "properties": {
    "gn:admin1_code":"34",
    "gn:asciiname":"Klimovsk",
    "gn:country_code":"RU",
    "gn:dem":126,
    "gn:feature_class":"P",
    "gn:feature_code":"PPL",
    "gn:name":"Klimovsk",
    "gn:population":0,
    "gn:timezone":"Europe/Moscow",
    "iso:country":"RU",
    "name:eng_x_preferred":[
        "Klimovsk"
    ],
    "name:nor_x_preferred":[
        "Klimovsk"
    ],
    "name:rus_x_preferred":[
        "\u041a\u043b\u0438\u043c\u043e\u0432\u0441\u043a"
    ],
    "name:und_x_variant":[
        "Klimov",
        "\u041a\u043b\u0438\u043c\u043e\u0432\u0441\u043a",
        "Klimovsk"
    ],
    "wof:name":"Klimovsk",
    "wof:placetype":"locality"
},
  "geometry": {"coordinates":[53.64803000000001,61.28632],"type":"Point"}
}