{
  "type": "Feature",
  "properties": {
    "gn:admin1_code":"6.0",
    "gn:asciiname":"Belogorskiy",
    "gn:country_code":"RU",
    "gn:dem":47,
    "gn:feature_class":"P",
    "gn:feature_code":"PPL",
    "gn:name":"Belogorskiy",
    "gn:population":713,
    "gn:timezone":"Europe/Moscow",
    "iso:country":"RU",
    "name:nor_x_preferred":[
        "Belogorskij"
    ],
    "name:rus_x_preferred":[
        "\u0411\u0435\u043b\u043e\u0433\u043e\u0440\u0441\u043a\u0438\u0439"
    ],
    "name:und_x_variant":[
        "Belogorskiy"
    ],
    "wof:name":"Belogorskiy",
    "wof:placetype":"locality",
    "wof:population":713
},
  "geometry": {"coordinates":[42.3433,64.18940000000001],"type":"Point"}
}