{
  "type": "Feature",
  "properties": {
    "gn:admin1_code":"4",
    "gn:asciiname":"Malaya Chebichen'",
    "gn:country_code":"RU",
    "gn:dem":173,
    "gn:feature_class":"P",
    "gn:feature_code":"PPL",
    "gn:name":"Malaya Chebichen\u2019",
    "gn:population":0,
    "gn:timezone":"Asia/Barnaul",
    "iso:country":"RU",
    "name:rus_x_preferred":[
        "\u041c\u0430\u043b\u0430\u044f \u0427\u0435\u0431\u0438\u0447\u0435\u043d\u044c"
    ],
    "name:und_x_variant":[
        "Malaya Chebichen\u2019",
        "\u041c\u0430\u043b\u0430\u044f \u0427\u0435\u0431\u0438\u0447\u0435\u043d\u044c"
    ],
    "wof:name":"Malaya Chebichen'",
    "wof:placetype":"locality"
},
  "geometry": {"coordinates":[84.93333,52.33333],"type":"Point"}
}