{
  "type": "Feature",
  "properties": {
    "gn:admin1_code":"33",
    "gn:asciiname":"Rodina",
    "gn:country_code":"RU",
    "gn:dem":143,
    "gn:feature_class":"P",
    "gn:feature_code":"PPL",
    "gn:name":"Rodina",
    "gn:population":0,
    "gn:timezone":"Europe/Kirov",
    "iso:country":"RU",
    "name:eng_x_preferred":[
        "Rodina"
    ],
    "name:nor_x_preferred":[
        "Rodina"
    ],
    "name:rus_x_preferred":[
        "\u0420\u043e\u0434\u0438\u043d\u0430"
    ],
    "name:und_x_variant":[
        "Slepovtsy",
        "Stepovtsy",
        "\u0420\u043e\u0434\u0438\u043d\u0430",
        "Rodina"
    ],
    "wof:name":"Rodina",
    "wof:placetype":"locality"
},
  "geometry": {"coordinates":[51.4449,57.6217],"type":"Point"}
}