{
  "type": "Feature",
  "properties": {
    "gn:admin1_code":"54",
    "gn:asciiname":"Reshetino",
    "gn:country_code":"RU",
    "gn:dem":84,
    "gn:feature_class":"P",
    "gn:feature_code":"PPL",
    "gn:name":"Reshetino",
    "gn:population":0,
    "gn:timezone":"Asia/Omsk",
    "iso:country":"RU",
    "name:eng_x_preferred":[
        "Reshetino"
    ],
    "name:nor_x_preferred":[
        "Resjetino"
    ],
    "name:rus_x_preferred":[
        "\u0420\u0435\u0448\u0435\u0442\u0438\u043d\u043e"
    ],
    "name:und_x_variant":[
        "Reshetina"
    ],
    "wof:name":"Reshetino",
    "wof:placetype":"locality"
},
  "geometry": {"coordinates":[72.44353000000002,56.9231],"type":"Point"}
}