{
  "type": "Feature",
  "properties": {
    "gn:admin1_code":"69",
    "gn:asciiname":"Mityayevo",
    "gn:country_code":"RU",
    "gn:dem":234,
    "gn:feature_class":"P",
    "gn:feature_code":"PPL",
    "gn:name":"Mityayevo",
    "gn:population":0,
    "gn:timezone":"Europe/Moscow",
    "iso:country":"RU",
    "name:rus_x_preferred":[
        "\u041c\u0438\u0442\u044f\u0435\u0432\u043e"
    ],
    "wof:name":"Mityayevo",
    "wof:placetype":"locality"
},
  "geometry": {"coordinates":[32.3681,55.2788],"type":"Point"}
}