{
  "type": "Feature",
  "properties": {
    "gn:admin1_code":"71",
    "gn:asciiname":"Staraya Lyalya",
    "gn:country_code":"RU",
    "gn:dem":160,
    "gn:feature_class":"P",
    "gn:feature_code":"PPL",
    "gn:name":"Staraya Lyalya",
    "gn:population":0,
    "gn:timezone":"Asia/Yekaterinburg",
    "iso:country":"RU",
    "name:rus_x_preferred":[
        "\u0421\u0442\u0430\u0440\u0430\u044f \u041b\u044f\u043b\u044f"
    ],
    "name:und_x_variant":[
        "Lyalya",
        "Staraya Lyalya"
    ],
    "wof:name":"Staraya Lyalya",
    "wof:placetype":"locality"
},
  "geometry": {"coordinates":[59.8685,59.0735],"type":"Point"}
}