{
  "type": "Feature",
  "properties": {
    "gn:admin1_code":"63",
    "gn:asciiname":"Yansk",
    "gn:country_code":"RU",
    "gn:dem":97,
    "gn:feature_class":"P",
    "gn:feature_code":"PPL",
    "gn:name":"Yansk",
    "gn:population":0,
    "gn:timezone":"Asia/Vladivostok",
    "iso:country":"RU",
    "name:eng_x_preferred":[
        "Yansk"
    ],
    "name:nor_x_preferred":[
        "Janskij"
    ],
    "name:rus_x_preferred":[
        "\u042f\u043d\u0441\u043a\u0438\u0439"
    ],
    "name:und_x_variant":[
        "Kugun",
        "Yanskiy"
    ],
    "wof:name":"Yansk",
    "wof:placetype":"locality"
},
  "geometry": {"coordinates":[134.8107,68.45237],"type":"Point"}
}