{
  "type": "Feature",
  "properties": {
    "gn:admin1_code":"77",
    "gn:asciiname":"Kuzovino",
    "gn:country_code":"RU",
    "gn:dem":201,
    "gn:feature_class":"P",
    "gn:feature_code":"PPL",
    "gn:name":"Kuzovino",
    "gn:population":0,
    "gn:timezone":"Europe/Moscow",
    "iso:country":"RU",
    "name:eng_x_preferred":[
        "Kuzovino"
    ],
    "name:nor_x_preferred":[
        "Kuzovino"
    ],
    "name:rus_x_preferred":[
        "\u041a\u0443\u0437\u043e\u0432\u0438\u043d\u043e"
    ],
    "wof:name":"Kuzovino",
    "wof:placetype":"locality"
},
  "geometry": {"coordinates":[35.51421,57.18397],"type":"Point"}
}