{
  "type": "Feature",
  "properties": {
    "gn:admin1_code":"20",
    "gn:asciiname":"Lytkino",
    "gn:cc2":"RU",
    "gn:country_code":"RU",
    "gn:dem":609,
    "gn:feature_class":"P",
    "gn:feature_code":"PPL",
    "gn:name":"Lytkino",
    "gn:population":0,
    "gn:timezone":"Asia/Irkutsk",
    "iso:country":"RU",
    "name:rus_x_preferred":[
        "\u041b\u044b\u0442\u043a\u0438\u043d\u043e"
    ],
    "name:und_x_variant":[
        "Lytkinskiy",
        "Lytkina",
        "Lytkinski",
        "Lytkino"
    ],
    "wof:name":"Lytkino",
    "wof:placetype":"locality"
},
  "geometry": {"coordinates":[103.23333,52.33333],"type":"Point"}
}