{
  "type": "Feature",
  "properties": {
    "gn:admin1_code":"47.0",
    "gn:asciiname":"Alad'ino",
    "gn:country_code":"RU",
    "gn:dem":202,
    "gn:feature_class":"P",
    "gn:feature_code":"PPL",
    "gn:name":"Alad\u2019ino",
    "gn:population":0,
    "gn:timezone":"Europe/Moscow",
    "iso:country":"RU",
    "name:nor_x_preferred":[
        "Aladino"
    ],
    "name:rus_x_preferred":[
        "\u0410\u043b\u0430\u0434\u044c\u0438\u043d\u043e"
    ],
    "name:und_x_variant":[
        "A ad\u2019ino",
        "Alad\u2019ino"
    ],
    "wof:name":"Alad'ino",
    "wof:placetype":"locality"
},
  "geometry": {"coordinates":[38.20759,54.81377],"type":"Point"}
}