{
  "type": "Feature",
  "properties": {
    "gn:admin1_code":"85",
    "gn:asciiname":"Gribtsovo",
    "gn:country_code":"RU",
    "gn:dem":185,
    "gn:feature_class":"P",
    "gn:feature_code":"PPL",
    "gn:name":"Gribtsovo",
    "gn:population":0,
    "gn:timezone":"Europe/Moscow",
    "iso:country":"RU",
    "name:rus_x_preferred":[
        "\u0413\u0440\u0438\u0431\u0446\u043e\u0432\u043e"
    ],
    "wof:name":"Gribtsovo",
    "wof:placetype":"locality"
},
  "geometry": {"coordinates":[39.70715,59.10811999999999],"type":"Point"}
}