{
  "type": "Feature",
  "properties": {
    "gn:admin1_code":"34",
    "gn:asciiname":"Kydz'shor",
    "gn:country_code":"RU",
    "gn:dem":146,
    "gn:feature_class":"P",
    "gn:feature_code":"PPL",
    "gn:name":"Kydz\u2019shor",
    "gn:population":0,
    "gn:timezone":"Europe/Moscow",
    "iso:country":"RU",
    "name:eng_x_preferred":[
        "Kydz'shor"
    ],
    "name:nor_x_preferred":[
        "Kydzsjor"
    ],
    "name:rus_x_preferred":[
        "\u041a\u044b\u0434\u0437\u044c\u0448\u043e\u0440"
    ],
    "name:und_x_variant":[
        "Kydz\u2019shor"
    ],
    "wof:name":"Kydz'shor",
    "wof:placetype":"locality"
},
  "geometry": {"coordinates":[50.2393,60.73618],"type":"Point"}
}