{
  "type": "Feature",
  "properties": {
    "gn:admin1_code":"85",
    "gn:asciiname":"Kostinskoye",
    "gn:country_code":"RU",
    "gn:dem":133,
    "gn:feature_class":"P",
    "gn:feature_code":"PPL",
    "gn:name":"Kostinskoye",
    "gn:population":0,
    "gn:timezone":"Europe/Moscow",
    "iso:country":"RU",
    "name:rus_x_preferred":[
        "\u041a\u043e\u0441\u0442\u0438\u043d\u0441\u043a\u043e\u0435"
    ],
    "wof:name":"Kostinskoye",
    "wof:placetype":"locality"
},
  "geometry": {"coordinates":[38.49009,59.19179000000001],"type":"Point"}
}