{
  "type": "Feature",
  "properties": {
    "gn:admin1_code":"84",
    "gn:asciiname":"Zhuravka",
    "gn:country_code":"RU",
    "gn:dem":143,
    "gn:feature_class":"P",
    "gn:feature_code":"PPL",
    "gn:name":"Zhuravka",
    "gn:population":0,
    "gn:timezone":"Europe/Volgograd",
    "iso:country":"RU",
    "name:rus_x_preferred":[
        "\u0416\u0443\u0440\u0430\u0432\u043a\u0430"
    ],
    "wof:name":"Zhuravka",
    "wof:placetype":"locality"
},
  "geometry": {"coordinates":[43.1453,50.5253],"type":"Point"}
}