{
  "type": "Feature",
  "properties": {
    "gn:admin1_code":"31",
    "gn:asciiname":"Sovetskaya Khakasiya",
    "gn:cc2":"RU",
    "gn:country_code":"RU",
    "gn:dem":270,
    "gn:feature_class":"P",
    "gn:feature_code":"PPL",
    "gn:name":"Sovetskaya Khakasiya",
    "gn:population":0,
    "gn:timezone":"Asia/Krasnoyarsk",
    "iso:country":"RU",
    "name:eng_x_preferred":[
        "Sovetskaya Khakasiya"
    ],
    "name:nor_x_preferred":[
        "Sovetskaja Khakasia"
    ],
    "name:rus_x_preferred":[
        "\u0421\u043e\u0432\u0435\u0442\u0441\u043a\u0430\u044f \u0425\u0430\u043a\u0430\u0441\u0438\u044f"
    ],
    "name:und_x_variant":[
        "Kakashkin",
        "Sovetskaya Khakassiya",
        "Khakassiya"
    ],
    "wof:name":"Sovetskaya Khakasiya",
    "wof:placetype":"locality"
},
  "geometry": {"coordinates":[91.43333,54.11111],"type":"Point"}
}