{
  "type": "Feature",
  "properties": {
    "gn:admin1_code":"45",
    "gn:asciiname":"Malaya Kul'sha",
    "gn:country_code":"RU",
    "gn:dem":122,
    "gn:feature_class":"P",
    "gn:feature_code":"PPL",
    "gn:name":"Malaya Kul\u2019sha",
    "gn:population":0,
    "gn:timezone":"Europe/Moscow",
    "iso:country":"RU",
    "name:rus_x_preferred":[
        "\u041c\u0430\u043b\u0430\u044f \u041a\u0443\u043b\u044c\u0448\u0430"
    ],
    "name:und_x_variant":[
        "Malaya Kul\u2019sha"
    ],
    "wof:name":"Malaya Kul'sha",
    "wof:placetype":"locality"
},
  "geometry": {"coordinates":[49.1215,57.2477],"type":"Point"}
}