{
  "type": "Feature",
  "properties": {
    "gn:admin1_code":"84",
    "gn:asciiname":"Imeni Zhdanova",
    "gn:country_code":"RU",
    "gn:dem":31,
    "gn:feature_class":"P",
    "gn:feature_code":"PPL",
    "gn:name":"Imeni Zhdanova",
    "gn:population":0,
    "gn:timezone":"Europe/Volgograd",
    "iso:country":"RU",
    "name:rus_x_preferred":[
        "\u0418\u043c\u0435\u043d\u0438 \u0416\u0434\u0430\u043d\u043e\u0432\u0430"
    ],
    "name:und_x_variant":[
        "\u0418\u043c\u0435\u043d\u0438 \u0416\u0434\u0430\u043d\u043e\u0432\u0430"
    ],
    "wof:name":"Imeni Zhdanova",
    "wof:placetype":"locality"
},
  "geometry": {"coordinates":[45.76402,50.10359],"type":"Point"}
}