{
  "type": "Feature",
  "properties": {
    "gn:admin1_code":"25",
    "gn:asciiname":"Mladensk",
    "gn:country_code":"RU",
    "gn:dem":208,
    "gn:feature_class":"P",
    "gn:feature_code":"PPL",
    "gn:name":"Mladensk",
    "gn:population":0,
    "gn:timezone":"Europe/Moscow",
    "iso:country":"RU",
    "name:eng_x_preferred":[
        "Mladensk"
    ],
    "name:nor_x_preferred":[
        "Mladensk"
    ],
    "name:rus_x_preferred":[
        "\u041c\u043b\u0430\u0434\u0435\u043d\u0441\u043a"
    ],
    "name:und_x_variant":[
        "\u041c\u043b\u0430\u0434\u0435\u043d\u0441\u043a",
        "Mladensk"
    ],
    "wof:name":"Mladensk",
    "wof:placetype":"locality"
},
  "geometry": {"coordinates":[34.81976,53.60822],"type":"Point"}
}