{
  "type": "Feature",
  "properties": {
    "gn:admin1_code":"12.0",
    "gn:asciiname":"Chishki",
    "gn:country_code":"RU",
    "gn:dem":404,
    "gn:feature_class":"P",
    "gn:feature_code":"PPL",
    "gn:name":"Chishki",
    "gn:population":0,
    "gn:timezone":"Europe/Moscow",
    "iso:country":"RU",
    "name:che_x_preferred":[
        "Pionerskoe"
    ],
    "name:che_x_variant":[
        "\u010a\u0327i\u015fka",
        "\u041f\u0438\u043e\u043d\u0435\u0440\u0441\u043a\u043e\u0435",
        "\u0427\u0406\u0438\u0448\u043a\u0430"
    ],
    "name:rus_x_preferred":[
        "\u0427\u0438\u0448\u043a\u0438"
    ],
    "name:rus_x_variant":[
        "\u010ci\u0161ki"
    ],
    "name:und_x_variant":[
        "Pionerskoye",
        "Chishki"
    ],
    "wof:name":"Chishki",
    "wof:placetype":"locality"
},
  "geometry": {"coordinates":[45.70676,43.01108],"type":"Point"}
}