{
  "type": "Feature",
  "properties": {
    "gn:admin1_code":"81",
    "gn:asciiname":"Pomayevo",
    "gn:country_code":"RU",
    "gn:dem":173,
    "gn:feature_class":"P",
    "gn:feature_code":"PPL",
    "gn:name":"Pomayevo",
    "gn:population":0,
    "gn:timezone":"Europe/Ulyanovsk",
    "iso:country":"RU",
    "name:rus_x_preferred":[
        "\u041f\u043e\u043c\u0430\u0435\u0432\u043e"
    ],
    "name:und_x_variant":[
        "\u041f\u043e\u043c\u0430\u0435\u0432\u043e"
    ],
    "wof:name":"Pomayevo",
    "wof:placetype":"locality"
},
  "geometry": {"coordinates":[47.2027,54.6191],"type":"Point"}
}