{
  "type": "Feature",
  "properties": {
    "gn:admin1_code":"88.0",
    "gn:asciiname":"Fedurino",
    "gn:country_code":"RU",
    "gn:dem":120,
    "gn:feature_class":"P",
    "gn:feature_code":"PPL",
    "gn:name":"Fedurino",
    "gn:population":0,
    "gn:timezone":"Europe/Moscow",
    "iso:country":"RU",
    "name:eng_x_preferred":[
        "Fedurino"
    ],
    "name:nor_x_preferred":[
        "Fedurino"
    ],
    "name:rus_x_preferred":[
        "\u0424\u0435\u0434\u0443\u0440\u0438\u043d\u043e"
    ],
    "name:und_x_variant":[
        "Feduriko",
        "\u0424\u0435\u0434\u0443\u0440\u0438\u043d\u043e",
        "Fedurino"
    ],
    "wof:name":"Fedurino",
    "wof:placetype":"locality"
},
  "geometry": {"coordinates":[40.45021,58.04501],"type":"Point"}
}