{
  "type": "Feature",
  "properties": {
    "gn:admin1_code":"05",
    "gn:asciiname":"Budunda",
    "gn:country_code":"RU",
    "gn:dem":128,
    "gn:feature_class":"P",
    "gn:feature_code":"PPL",
    "gn:name":"Budunda",
    "gn:population":0,
    "gn:timezone":"Asia/Yakutsk",
    "iso:country":"RU",
    "name:rus_x_preferred":[
        "\u0411\u0443\u0434\u0443\u043d\u0434\u0430"
    ],
    "wof:name":"Budunda",
    "wof:placetype":"locality"
},
  "geometry": {"coordinates":[127.75,50.33333],"type":"Point"}
}