{
  "type": "Feature",
  "properties": {
    "gn:admin1_code":"90.0",
    "gn:asciiname":"Petukhi",
    "gn:country_code":"RU",
    "gn:dem":168,
    "gn:feature_class":"P",
    "gn:feature_code":"PPL",
    "gn:name":"Petukhi",
    "gn:population":0,
    "gn:timezone":"Asia/Yekaterinburg",
    "iso:country":"RU",
    "name:rus_x_preferred":[
        "\u041f\u0435\u0442\u0443\u0445\u0438"
    ],
    "wof:name":"Petukhi",
    "wof:placetype":"locality"
},
  "geometry": {"coordinates":[55.0011,58.1318],"type":"Point"}
}