{
  "type": "Feature",
  "properties": {
    "gn:admin1_code":"13.0",
    "gn:asciiname":"Chernootrog",
    "gn:country_code":"RU",
    "gn:dem":325,
    "gn:feature_class":"P",
    "gn:feature_code":"PPL",
    "gn:name":"Chernootrog",
    "gn:population":0,
    "gn:timezone":"Asia/Yekaterinburg",
    "iso:country":"RU",
    "name:eng_x_preferred":[
        "Chernootrog"
    ],
    "name:nor_x_preferred":[
        "Tsjernootrog"
    ],
    "name:rus_x_preferred":[
        "\u0427\u0435\u0440\u043d\u043e\u043e\u0442\u0440\u043e\u0433"
    ],
    "name:und_x_variant":[
        "Chernootrozhskiy"
    ],
    "wof:name":"Chernootrog",
    "wof:placetype":"locality"
},
  "geometry": {"coordinates":[59.1375,53.16],"type":"Point"}
}