{
  "type": "Feature",
  "properties": {
    "gn:admin1_code":"84.0",
    "gn:asciiname":"Bobrovskiy Vtoroy",
    "gn:country_code":"RU",
    "gn:dem":69,
    "gn:feature_class":"P",
    "gn:feature_code":"PPL",
    "gn:name":"Bobrovskiy Vtoroy",
    "gn:population":0,
    "gn:timezone":"Europe/Volgograd",
    "iso:country":"RU",
    "name:rus_x_preferred":[
        "\u0411\u043e\u0431\u0440\u043e\u0432\u0441\u043a\u0438\u0439 \u0412\u0442\u043e\u0440\u043e\u0439"
    ],
    "name:und_x_variant":[
        "Bobrovskiy",
        "Bobrovskiy Vtoroy"
    ],
    "wof:name":"Bobrovskiy Vtoroy",
    "wof:placetype":"locality"
},
  "geometry": {"coordinates":[42.7547,49.4882],"type":"Point"}
}