{
  "type": "Feature",
  "properties": {
    "gn:admin1_code":"63",
    "gn:asciiname":"Russkoye Ust'ye",
    "gn:country_code":"RU",
    "gn:dem":25,
    "gn:feature_class":"P",
    "gn:feature_code":"PPL",
    "gn:name":"Russkoye Ust\u2019ye",
    "gn:population":0,
    "gn:timezone":"Asia/Magadan",
    "iso:country":"RU",
    "name:rus_x_preferred":[
        "\u0420\u0443\u0441\u0441\u043a\u043e\u0435 \u0423\u0441\u0442\u044c\u0435"
    ],
    "name:und_x_variant":[
        "Russkoe Uste",
        "Russkoye Ust\u2019ye",
        "\u0420\u0443\u0441\u0441\u043a\u043e\u0435 \u0423\u0441\u0442\u044c\u0435"
    ],
    "wof:name":"Russkoye Ust'ye",
    "wof:placetype":"locality"
},
  "geometry": {"coordinates":[149.06662,71.00408],"type":"Point"}
}