{
  "type": "Feature",
  "properties": {
    "gn:admin1_code":"93",
    "gn:asciiname":"Zapisina",
    "gn:country_code":"RU",
    "gn:dem":507,
    "gn:feature_class":"P",
    "gn:feature_code":"PPL",
    "gn:name":"Zapisina",
    "gn:population":0,
    "gn:timezone":"Asia/Chita",
    "iso:country":"RU",
    "name:eng_x_preferred":[
        "Zapisina"
    ],
    "name:nor_x_preferred":[
        "Zapisina"
    ],
    "name:rus_x_preferred":[
        "\u0417\u0430\u043f\u0438\u0441\u0438\u043d\u0430"
    ],
    "name:und_x_variant":[
        "Ilya",
        "Zapisino",
        "Il\u2019ya-Zapisina",
        "Zapisyano"
    ],
    "wof:name":"Zapisina",
    "wof:placetype":"locality"
},
  "geometry": {"coordinates":[120.25303999999998,51.75048],"type":"Point"}
}