{
  "type": "Feature",
  "properties": {
    "gn:admin1_code":"16",
    "gn:asciiname":"Nizhniye Irzei",
    "gn:country_code":"RU",
    "gn:dem":153,
    "gn:feature_class":"P",
    "gn:feature_code":"PPL",
    "gn:name":"Nizhniye Irzei",
    "gn:population":0,
    "gn:timezone":"Europe/Moscow",
    "iso:country":"RU",
    "name:rus_x_preferred":[
        "\u041d\u0438\u0436\u043d\u0438\u0435 \u0418\u0440\u0437\u0435\u0438"
    ],
    "name:und_x_variant":[
        "\u041d\u0438\u0436\u043d\u0438\u0435 \u0418\u0440\u0437\u0435\u0438"
    ],
    "wof:name":"Nizhniye Irzei",
    "wof:placetype":"locality"
},
  "geometry": {"coordinates":[46.5365,56.0773],"type":"Point"}
}