{
  "type": "Feature",
  "properties": {
    "gn:admin1_code":"73.0",
    "gn:asciiname":"Borok",
    "gn:country_code":"RU",
    "gn:dem":60,
    "gn:feature_class":"P",
    "gn:feature_code":"PPL",
    "gn:name":"Borok",
    "gn:population":0,
    "gn:timezone":"Europe/Moscow",
    "iso:country":"RU",
    "name:eng_x_preferred":[
        "Borok"
    ],
    "name:nor_x_preferred":[
        "Borok"
    ],
    "name:rus_x_preferred":[
        "\u0411\u043e\u0440\u043e\u043a"
    ],
    "wof:name":"Borok",
    "wof:placetype":"locality"
},
  "geometry": {"coordinates":[51.67913,55.54695],"type":"Point"}
}