{
  "type": "Feature",
  "properties": {
    "gn:admin1_code":"84.0",
    "gn:asciiname":"Bol'shoy Oreshkin",
    "gn:country_code":"RU",
    "gn:dem":83,
    "gn:feature_class":"P",
    "gn:feature_code":"PPL",
    "gn:name":"Bol\u2019shoy Oreshkin",
    "gn:population":0,
    "gn:timezone":"Europe/Volgograd",
    "iso:country":"RU",
    "name:rus_x_preferred":[
        "Bol\u2019shoy Oreshkin"
    ],
    "name:rus_x_variant":[
        "\u0411\u043e\u043b\u044c\u0448\u043e\u0439 \u041e\u0440\u0435\u0448\u043a\u0438\u043d"
    ],
    "wof:name":"Bol'shoy Oreshkin",
    "wof:placetype":"locality"
},
  "geometry": {"coordinates":[43.3829,50.1497],"type":"Point"}
}