{
  "type": "Feature",
  "properties": {
    "gn:admin1_code":"47",
    "gn:asciiname":"Ivanovo",
    "gn:country_code":"RU",
    "gn:dem":203,
    "gn:feature_class":"P",
    "gn:feature_code":"PPL",
    "gn:name":"Ivanovo",
    "gn:population":0,
    "gn:timezone":"Europe/Moscow",
    "iso:country":"RU",
    "name:eng_x_preferred":[
        "Ivanovo"
    ],
    "name:nor_x_preferred":[
        "Ivanovo"
    ],
    "name:rus_x_preferred":[
        "\u0418\u0432\u0430\u043d\u043e\u0432\u043e"
    ],
    "name:und_x_variant":[
        "\u0418\u0432\u0430\u043d\u043e\u0432\u043e",
        "Ivanovo"
    ],
    "wof:name":"Ivanovo",
    "wof:placetype":"locality"
},
  "geometry": {"coordinates":[36.11434000000001,55.80836],"type":"Point"}
}