{
  "type": "Feature",
  "properties": {
    "gn:admin1_code":"76",
    "gn:asciiname":"Krasnokol'ye",
    "gn:country_code":"RU",
    "gn:dem":220,
    "gn:feature_class":"P",
    "gn:feature_code":"PPL",
    "gn:name":"Krasnokol\u2019ye",
    "gn:population":0,
    "gn:timezone":"Europe/Moscow",
    "iso:country":"RU",
    "name:rus_x_preferred":[
        "\u041a\u0440\u0430\u0441\u043d\u043e\u043a\u043e\u043b\u044c\u0435"
    ],
    "name:und_x_variant":[
        "Krasnokol\u2019ye",
        "\u041a\u0440\u0430\u0441\u043d\u043e\u043a\u043e\u043b\u044c\u0435"
    ],
    "wof:name":"Krasnokol'ye",
    "wof:placetype":"locality"
},
  "geometry": {"coordinates":[36.57649,53.89024000000001],"type":"Point"}
}