{
  "type": "Feature",
  "properties": {
    "gn:admin1_code":"62",
    "gn:asciiname":"Staro-Plastikovo",
    "gn:country_code":"RU",
    "gn:dem":156,
    "gn:feature_class":"P",
    "gn:feature_code":"PPL",
    "gn:name":"Staro-Plastikovo",
    "gn:population":0,
    "gn:timezone":"Europe/Moscow",
    "iso:country":"RU",
    "name:eng_x_preferred":[
        "Staro-Plastikovo"
    ],
    "name:nor_x_preferred":[
        "Ostro-Plastikovo"
    ],
    "name:rus_x_preferred":[
        "\u041e\u0441\u0442\u0440\u043e-\u041f\u043b\u0430\u0441\u0442\u0438\u043a\u043e\u0432\u043e"
    ],
    "name:rus_x_variant":[
        "\u0421\u0442\u0430\u0440\u043e-\u041f\u043b\u0430\u0441\u0442\u0438\u043a\u043e\u0432\u043e"
    ],
    "name:und_x_variant":[
        "\u0421\u0442\u0430\u0440\u043e-\u041f\u043b\u0430\u0441\u0442\u0438\u043a\u043e\u0432\u043e"
    ],
    "wof:name":"Staro-Plastikovo",
    "wof:placetype":"locality"
},
  "geometry": {"coordinates":[41.31667,54.18333000000001],"type":"Point"}
}