{
  "type": "Feature",
  "properties": {
    "gn:admin1_code":"44",
    "gn:asciiname":"Kegali",
    "gn:country_code":"RU",
    "gn:dem":412,
    "gn:feature_class":"P",
    "gn:feature_code":"PPL",
    "gn:name":"Kegali",
    "gn:population":0,
    "gn:timezone":"Asia/Magadan",
    "iso:country":"RU",
    "name:rus_x_preferred":[
        "\u041a\u0435\u0433\u0430\u043b\u0438"
    ],
    "name:und_x_variant":[
        "\u041a\u0435\u0433\u0430\u043b\u0438"
    ],
    "wof:name":"Kegali",
    "wof:placetype":"locality"
},
  "geometry": {"coordinates":[161.96733,64.36270999999999],"type":"Point"}
}