{
  "type": "Feature",
  "properties": {
    "gn:admin1_code":"67.0",
    "gn:asciiname":"Belyy Klyuch",
    "gn:country_code":"RU",
    "gn:dem":223,
    "gn:feature_class":"P",
    "gn:feature_code":"PPL",
    "gn:name":"Belyy Klyuch",
    "gn:population":0,
    "gn:timezone":"Europe/Saratov",
    "iso:country":"RU",
    "name:nor_x_preferred":[
        "Belyj Kljutsj"
    ],
    "name:rus_x_preferred":[
        "\u0411\u0435\u043b\u044b\u0439 \u041a\u043b\u044e\u0447"
    ],
    "wof:name":"Belyy Klyuch",
    "wof:placetype":"locality"
},
  "geometry": {"coordinates":[46.38008,52.56329],"type":"Point"}
}