{
  "type": "Feature",
  "properties": {
    "gn:admin1_code":"20",
    "gn:asciiname":"Kaduychik",
    "gn:country_code":"RU",
    "gn:dem":574,
    "gn:feature_class":"P",
    "gn:feature_code":"PPL",
    "gn:name":"Kaduychik",
    "gn:population":0,
    "gn:timezone":"Asia/Irkutsk",
    "iso:country":"RU",
    "name:rus_x_preferred":[
        "\u041a\u0430\u0434\u0443\u0439\u0447\u0438\u043a"
    ],
    "wof:name":"Kaduychik",
    "wof:placetype":"locality"
},
  "geometry": {"coordinates":[99.53360000000001,54.7497],"type":"Point"}
}