{
  "type": "Feature",
  "properties": {
    "gn:admin1_code":"73",
    "gn:asciiname":"Leshev-Tamak",
    "gn:country_code":"RU",
    "gn:dem":160,
    "gn:feature_class":"P",
    "gn:feature_code":"PPL",
    "gn:name":"Leshev-Tamak",
    "gn:population":0,
    "gn:timezone":"Europe/Moscow",
    "iso:country":"RU",
    "name:eng_x_preferred":[
        "Leshev-Tamak"
    ],
    "name:nor_x_preferred":[
        "Lesjev-Tamak"
    ],
    "name:rus_x_preferred":[
        "\u041b\u0435\u0448\u0435\u0432-\u0422\u0430\u043c\u0430\u043a"
    ],
    "name:und_x_variant":[
        "Leshchev Tamak",
        "\u041b\u0435\u0448\u0435\u0432-\u0422\u0430\u043c\u0430\u043a",
        "Leshev-Tamak"
    ],
    "wof:name":"Leshev-Tamak",
    "wof:placetype":"locality"
},
  "geometry": {"coordinates":[52.62886999999999,55.11571],"type":"Point"}
}