{
  "type": "Feature",
  "properties": {
    "gn:admin1_code":"28",
    "gn:asciiname":"Kuzhon",
    "gn:country_code":"RU",
    "gn:dem":76,
    "gn:feature_class":"P",
    "gn:feature_code":"PPL",
    "gn:name":"Kuzhon",
    "gn:population":0,
    "gn:timezone":"Europe/Moscow",
    "iso:country":"RU",
    "name:fin_x_preferred":[
        "Kutsoinm\u00e4ki"
    ],
    "name:rus_x_preferred":[
        "\u041a\u0443\u0436\u043e\u043d"
    ],
    "name:und_x_variant":[
        "\u041a\u0443\u0436\u043e\u043d"
    ],
    "wof:name":"Kuzhon",
    "wof:placetype":"locality"
},
  "geometry": {"coordinates":[32.51667,61.43333000000001],"type":"Point"}
}