{
  "type": "Feature",
  "properties": {
    "gn:admin1_code":"63",
    "gn:asciiname":"Usun-Chemis",
    "gn:country_code":"RU",
    "gn:dem":383,
    "gn:feature_class":"P",
    "gn:feature_code":"PPL",
    "gn:name":"Usun-Chemis",
    "gn:population":0,
    "gn:timezone":"Asia/Yakutsk",
    "iso:country":"RU",
    "wof:name":"Usun-Chemis",
    "wof:placetype":"locality"
},
  "geometry": {"coordinates":[120.58333,58.53333000000001],"type":"Point"}
}