{
  "type": "Feature",
  "properties": {
    "gn:admin1_code":"88",
    "gn:asciiname":"Sermino",
    "gn:country_code":"RU",
    "gn:dem":138,
    "gn:feature_class":"P",
    "gn:feature_code":"PPL",
    "gn:name":"Sermino",
    "gn:population":0,
    "gn:timezone":"Europe/Moscow",
    "iso:country":"RU",
    "name:rus_x_preferred":[
        "\u0421\u0435\u0440\u043c\u0438\u043d\u043e"
    ],
    "wof:name":"Sermino",
    "wof:placetype":"locality"
},
  "geometry": {"coordinates":[40.13333,57.25],"type":"Point"}
}