{
  "type": "Feature",
  "properties": {
    "gn:admin1_code":"33.0",
    "gn:asciiname":"Bol'shoy Krasnoyar",
    "gn:country_code":"RU",
    "gn:dem":88,
    "gn:feature_class":"P",
    "gn:feature_code":"PPL",
    "gn:name":"Bol\u2019shoy Krasnoyar",
    "gn:population":0,
    "gn:timezone":"Europe/Kirov",
    "iso:country":"RU",
    "name:rus_x_preferred":[
        "\u0411\u043e\u043b\u044c\u0448\u043e\u0439 \u041a\u0440\u0430\u0441\u043d\u043e\u044f\u0440"
    ],
    "name:und_x_variant":[
        "Bol\u2019shoy Krasnoyar"
    ],
    "wof:name":"Bol'shoy Krasnoyar",
    "wof:placetype":"locality"
},
  "geometry": {"coordinates":[47.1512,57.04857],"type":"Point"}
}