{
  "type": "Feature",
  "properties": {
    "gn:admin1_code":"71",
    "gn:asciiname":"Tangupskaya",
    "gn:country_code":"RU",
    "gn:dem":65,
    "gn:feature_class":"P",
    "gn:feature_code":"PPL",
    "gn:name":"Tangupskaya",
    "gn:population":0,
    "gn:timezone":"Asia/Yekaterinburg",
    "iso:country":"RU",
    "name:rus_x_preferred":[
        "\u0422\u0430\u043d\u0433\u0443\u043f\u0441\u043a\u0430\u044f"
    ],
    "name:und_x_variant":[
        "Tongubsk",
        "Novos\u00eblovo",
        "Tangupskaya"
    ],
    "wof:name":"Tangupskaya",
    "wof:placetype":"locality"
},
  "geometry": {"coordinates":[63.95405,58.91105],"type":"Point"}
}