{
  "type": "Feature",
  "properties": {
    "gn:admin1_code":"53",
    "gn:asciiname":"Rybnyy",
    "gn:country_code":"RU",
    "gn:dem":115,
    "gn:feature_class":"P",
    "gn:feature_code":"PPL",
    "gn:name":"Rybnyy",
    "gn:population":0,
    "gn:timezone":"Asia/Novosibirsk",
    "iso:country":"RU",
    "name:eng_x_preferred":[
        "Rybnyy"
    ],
    "name:nor_x_preferred":[
        "Rybnyj"
    ],
    "name:rus_x_preferred":[
        "\u0420\u044b\u0431\u043d\u044b\u0439"
    ],
    "name:und_x_variant":[
        "\u0420\u044b\u0431\u043d\u044b\u0439",
        "Rybnyy"
    ],
    "wof:name":"Rybnyy",
    "wof:placetype":"locality"
},
  "geometry": {"coordinates":[78.91960999999998,54.33633],"type":"Point"}
}