{
  "type": "Feature",
  "properties": {
    "gn:admin1_code":"55",
    "gn:asciiname":"Gostepriimnaya",
    "gn:country_code":"RU",
    "gn:dem":313,
    "gn:feature_class":"P",
    "gn:feature_code":"PPL",
    "gn:name":"Gostepriimnaya",
    "gn:population":0,
    "gn:timezone":"Asia/Yekaterinburg",
    "iso:country":"RU",
    "name:eng_x_preferred":[
        "Gostepriimnaya"
    ],
    "name:nor_x_preferred":[
        "Gostepriimnyj"
    ],
    "name:rus_x_preferred":[
        "\u0413\u043e\u0441\u0442\u0435\u043f\u0440\u0438\u0438\u043c\u043d\u044b\u0439"
    ],
    "name:rus_x_variant":[
        "\u0413\u043e\u0441\u0442\u0435\u043f\u0440\u0438\u0438\u043c\u043d\u0430\u044f"
    ],
    "name:und_x_variant":[
        "\u0413\u043e\u0441\u0442\u0435\u043f\u0440\u0438\u0438\u043c\u043d\u0430\u044f"
    ],
    "wof:name":"Gostepriimnaya",
    "wof:placetype":"locality"
},
  "geometry": {"coordinates":[60.46333000000001,50.84917],"type":"Point"}
}