{
  "type": "Feature",
  "properties": {
    "gn:admin1_code":"77",
    "gn:asciiname":"Ryukhovo",
    "gn:cc2":"RU",
    "gn:country_code":"RU",
    "gn:dem":134,
    "gn:feature_class":"P",
    "gn:feature_code":"PPL",
    "gn:name":"Ryukhovo",
    "gn:population":0,
    "gn:timezone":"Europe/Moscow",
    "iso:country":"RU",
    "name:rus_x_preferred":[
        "\u0420\u044e\u0445\u043e\u0432\u043e"
    ],
    "name:und_x_variant":[
        "Ryukhova",
        "Ryukhovo",
        "\u0420\u044e\u0445\u043e\u0432\u043e"
    ],
    "wof:name":"Ryukhovo",
    "wof:placetype":"locality"
},
  "geometry": {"coordinates":[36.46667,58.01667],"type":"Point"}
}