{
  "type": "Feature",
  "properties": {
    "gn:admin1_code":"91",
    "gn:asciiname":"Roshchino",
    "gn:country_code":"RU",
    "gn:dem":243,
    "gn:feature_class":"P",
    "gn:feature_code":"PPL",
    "gn:name":"Roshchino",
    "gn:population":0,
    "gn:timezone":"Asia/Krasnoyarsk",
    "iso:country":"RU",
    "name:rus_x_preferred":[
        "\u0420\u043e\u0449\u0438\u043d\u043e"
    ],
    "wof:name":"Roshchino",
    "wof:placetype":"locality"
},
  "geometry": {"coordinates":[90.65000000000001,55.95],"type":"Point"}
}