{
  "type": "Feature",
  "properties": {
    "gn:admin1_code":"33",
    "gn:asciiname":"Bol'shoye Lipovo",
    "gn:country_code":"RU",
    "gn:dem":154,
    "gn:feature_class":"P",
    "gn:feature_code":"PPL",
    "gn:name":"Bol\u2019shoye Lipovo",
    "gn:population":0,
    "gn:timezone":"Europe/Kirov",
    "iso:country":"RU",
    "name:rus_x_preferred":[
        "\u0411\u043e\u043b\u044c\u0448\u043e\u0435 \u041b\u0438\u043f\u043e\u0432\u043e"
    ],
    "name:und_x_variant":[
        "Bol\u2019shoye Lipovo",
        "\u0411\u043e\u043b\u044c\u0448\u043e\u0435 \u041b\u0438\u043f\u043e\u0432\u043e"
    ],
    "wof:name":"Bol'shoye Lipovo",
    "wof:placetype":"locality"
},
  "geometry": {"coordinates":[46.9605,58.53915],"type":"Point"}
}