{
  "type": "Feature",
  "properties": {
    "gn:admin1_code":"33.0",
    "gn:asciiname":"Boroviki",
    "gn:country_code":"RU",
    "gn:dem":181,
    "gn:feature_class":"P",
    "gn:feature_code":"PPL",
    "gn:name":"Boroviki",
    "gn:population":0,
    "gn:timezone":"Europe/Kirov",
    "iso:country":"RU",
    "name:rus_x_preferred":[
        "\u0411\u043e\u0440\u043e\u0432\u0438\u043a\u0438"
    ],
    "name:und_x_variant":[
        "\u0411\u043e\u0440\u043e\u0432\u0438\u043a\u0438"
    ],
    "wof:name":"Boroviki",
    "wof:placetype":"locality"
},
  "geometry": {"coordinates":[48.35,58.85],"type":"Point"}
}