{
  "type": "Feature",
  "properties": {
    "gn:admin1_code":"33",
    "gn:asciiname":"Russkoye Timkino",
    "gn:country_code":"RU",
    "gn:dem":159,
    "gn:feature_class":"P",
    "gn:feature_code":"PPL",
    "gn:name":"Russkoye Timkino",
    "gn:population":0,
    "gn:timezone":"Europe/Kirov",
    "iso:country":"RU",
    "name:rus_x_preferred":[
        "\u0420\u0443\u0441\u0441\u043a\u043e\u0435 \u0422\u0438\u043c\u043a\u0438\u043d\u043e"
    ],
    "wof:name":"Russkoye Timkino",
    "wof:placetype":"locality"
},
  "geometry": {"coordinates":[50.09029,57.12399],"type":"Point"}
}