{
  "type": "Feature",
  "properties": {
    "gn:admin1_code":"85",
    "gn:asciiname":"Solovtsovo",
    "gn:country_code":"RU",
    "gn:dem":111,
    "gn:feature_class":"P",
    "gn:feature_code":"PPL",
    "gn:name":"Solovtsovo",
    "gn:population":0,
    "gn:timezone":"Europe/Moscow",
    "iso:country":"RU",
    "name:rus_x_preferred":[
        "\u0421\u043e\u043b\u043e\u0432\u0446\u043e\u0432\u043e"
    ],
    "wof:name":"Solovtsovo",
    "wof:placetype":"locality"
},
  "geometry": {"coordinates":[36.363,58.8578],"type":"Point"}
}