{
  "type": "Feature",
  "properties": {
    "gn:admin1_code":"28",
    "gn:asciiname":"Vitcheozero",
    "gn:country_code":"RU",
    "gn:dem":135,
    "gn:feature_class":"P",
    "gn:feature_code":"PPL",
    "gn:name":"Vitcheozero",
    "gn:population":0,
    "gn:timezone":"Europe/Moscow",
    "iso:country":"RU",
    "name:fin_x_preferred":[
        "Vitsaj\u00e4rvi"
    ],
    "wof:name":"Vitcheozero",
    "wof:placetype":"locality"
},
  "geometry": {"coordinates":[33.16667,63.55],"type":"Point"}
}