{
  "type": "Feature",
  "properties": {
    "gn:admin1_code":"72.0",
    "gn:asciiname":"Belomestnaya Kriusha",
    "gn:country_code":"RU",
    "gn:dem":153,
    "gn:feature_class":"P",
    "gn:feature_code":"PPL",
    "gn:name":"Belomestnaya Kriusha",
    "gn:population":0,
    "gn:timezone":"Europe/Moscow",
    "iso:country":"RU",
    "name:eng_x_preferred":[
        "Belomestnaya Kriusha"
    ],
    "name:rus_x_preferred":[
        "\u0411\u0435\u043b\u043e\u043c\u0435\u0441\u0442\u043d\u0430\u044f-\u041a\u0440\u0438\u0443\u0448\u0430"
    ],
    "name:rus_x_variant":[
        "\u0411\u0435\u043b\u043e\u043c\u0435\u0441\u0442\u043d\u0430\u044f \u041a\u0440\u0438\u0443\u0448\u0430"
    ],
    "wof:name":"Belomestnaya Kriusha",
    "wof:placetype":"locality"
},
  "geometry": {"coordinates":[41.14569,52.7886],"type":"Point"}
}