{
  "type": "Feature",
  "properties": {
    "gn:admin1_code":"65",
    "gn:asciiname":"Kochkinovka",
    "gn:country_code":"RU",
    "gn:dem":67,
    "gn:feature_class":"P",
    "gn:feature_code":"PPL",
    "gn:name":"Kochkinovka",
    "gn:population":0,
    "gn:timezone":"Europe/Samara",
    "iso:country":"RU",
    "name:rus_x_preferred":[
        "\u041a\u043e\u0447\u043a\u0438\u043d\u043e\u0432\u043a\u0430"
    ],
    "name:und_x_variant":[
        "Kochkinovo",
        "Kochkino",
        "Kochkinovka",
        "\u041a\u043e\u0447\u043a\u0438\u043d\u043e\u0432\u043a\u0430"
    ],
    "wof:name":"Kochkinovka",
    "wof:placetype":"locality"
},
  "geometry": {"coordinates":[50.84509,52.13189000000001],"type":"Point"}
}