{
  "type": "Feature",
  "properties": {
    "gn:admin1_code":"77",
    "gn:asciiname":"Melechkino",
    "gn:country_code":"RU",
    "gn:dem":141,
    "gn:feature_class":"P",
    "gn:feature_code":"PPL",
    "gn:name":"Melechkino",
    "gn:population":0,
    "gn:timezone":"Europe/Moscow",
    "iso:country":"RU",
    "name:nor_x_preferred":[
        "Meletsjkino"
    ],
    "name:rus_x_preferred":[
        "\u041c\u0435\u043b\u0435\u0447\u043a\u0438\u043d\u043e"
    ],
    "name:und_x_variant":[
        "Melichkino",
        "Melechkino"
    ],
    "wof:name":"Melechkino",
    "wof:placetype":"locality"
},
  "geometry": {"coordinates":[35.94893,56.508],"type":"Point"}
}