{
  "type": "Feature",
  "properties": {
    "gn:admin1_code":"76.0",
    "gn:asciiname":"Beloye",
    "gn:country_code":"RU",
    "gn:dem":153,
    "gn:feature_class":"P",
    "gn:feature_code":"PPL",
    "gn:name":"Beloye",
    "gn:population":0,
    "gn:timezone":"Europe/Moscow",
    "iso:country":"RU",
    "name:nor_x_preferred":[
        "Beloje"
    ],
    "name:rus_x_preferred":[
        "\u0411\u0435\u043b\u043e\u0435"
    ],
    "wof:name":"Beloye",
    "wof:placetype":"locality"
},
  "geometry": {"coordinates":[36.3546,54.05074000000001],"type":"Point"}
}