{
  "type": "Feature",
  "properties": {
    "gn:admin1_code":"33",
    "gn:asciiname":"Oshlan'",
    "gn:country_code":"RU",
    "gn:dem":148,
    "gn:feature_class":"P",
    "gn:feature_code":"PPL",
    "gn:name":"Oshlan\u2019",
    "gn:population":0,
    "gn:timezone":"Europe/Kirov",
    "iso:country":"RU",
    "name:eng_x_preferred":[
        "Oshlan'"
    ],
    "name:nor_x_preferred":[
        "Osjlan"
    ],
    "name:rus_x_preferred":[
        "\u041e\u0448\u043b\u0430\u043d\u044c"
    ],
    "name:und_x_variant":[
        "Oshalan\u2019",
        "\u041e\u0448\u043b\u0430\u043d\u044c",
        "Oshlan\u2019"
    ],
    "wof:name":"Oshlan'",
    "wof:placetype":"locality"
},
  "geometry": {"coordinates":[50.51061,57.96331],"type":"Point"}
}