{
  "type": "Feature",
  "properties": {
    "gn:admin1_code":"37",
    "gn:asciiname":"Ray",
    "gn:country_code":"RU",
    "gn:dem":159,
    "gn:feature_class":"P",
    "gn:feature_code":"PPL",
    "gn:name":"Ray",
    "gn:population":0,
    "gn:timezone":"Europe/Moscow",
    "iso:country":"RU",
    "name:rus_x_preferred":[
        "\u0420\u0430\u0439"
    ],
    "name:und_x_variant":[
        "\u0420\u0430\u0439"
    ],
    "wof:name":"Ray",
    "wof:placetype":"locality"
},
  "geometry": {"coordinates":[46.79496,59.03728],"type":"Point"}
}