{
  "type": "Feature",
  "properties": {
    "gn:admin1_code":"91",
    "gn:asciiname":"Linevo",
    "gn:country_code":"RU",
    "gn:dem":381,
    "gn:feature_class":"P",
    "gn:feature_code":"PPL",
    "gn:name":"Lin\u00ebvo",
    "gn:population":0,
    "gn:timezone":"Asia/Krasnoyarsk",
    "iso:country":"RU",
    "name:eng_x_preferred":[
        "Linevo"
    ],
    "name:nor_x_preferred":[
        "Linevo"
    ],
    "name:rus_x_preferred":[
        "\u041b\u0438\u043d\u0435\u0432\u043e"
    ],
    "name:rus_x_variant":[
        "\u041b\u0438\u043d\u0451\u0432\u043e"
    ],
    "name:und_x_variant":[
        "Linevskaya",
        "Lin\u00ebvo"
    ],
    "wof:name":"Linevo",
    "wof:placetype":"locality"
},
  "geometry": {"coordinates":[89.08389,55.38222],"type":"Point"}
}