{
  "type": "Feature",
  "properties": {
    "gn:admin1_code":"4",
    "gn:asciiname":"Korobeynikovo",
    "gn:country_code":"RU",
    "gn:dem":230,
    "gn:feature_class":"P",
    "gn:feature_code":"PPL",
    "gn:name":"Korobeynikovo",
    "gn:population":0,
    "gn:timezone":"Asia/Barnaul",
    "iso:country":"RU",
    "name:eng_x_preferred":[
        "Korobeynikovo"
    ],
    "name:nor_x_preferred":[
        "Korobejnikovo"
    ],
    "name:rus_x_preferred":[
        "\u041a\u043e\u0440\u043e\u0431\u0435\u0439\u043d\u0438\u043a\u043e\u0432\u043e"
    ],
    "name:und_x_variant":[
        "Korobeynikovskoye",
        "Korobeynikovo"
    ],
    "wof:name":"Korobeynikovo",
    "wof:placetype":"locality"
},
  "geometry": {"coordinates":[81.6955,52.4112],"type":"Point"}
}