{
  "type": "Feature",
  "properties": {
    "gn:admin1_code":"60",
    "gn:asciiname":"Samrinikha",
    "gn:country_code":"RU",
    "gn:dem":181,
    "gn:feature_class":"P",
    "gn:feature_code":"PPL",
    "gn:name":"Samrinikha",
    "gn:population":0,
    "gn:timezone":"Europe/Moscow",
    "iso:country":"RU",
    "name:rus_x_preferred":[
        "\u0421\u0430\u043c\u0440\u0438\u043d\u0438\u0445\u0430"
    ],
    "wof:name":"Samrinikha",
    "wof:placetype":"locality"
},
  "geometry": {"coordinates":[29.6384,56.2396],"type":"Point"}
}