{
  "type": "Feature",
  "properties": {
    "gn:admin1_code":"16",
    "gn:asciiname":"Shorkasy",
    "gn:country_code":"RU",
    "gn:dem":115,
    "gn:feature_class":"P",
    "gn:feature_code":"PPL",
    "gn:name":"Shorkasy",
    "gn:population":0,
    "gn:timezone":"Europe/Moscow",
    "iso:country":"RU",
    "name:rus_x_preferred":[
        "\u0428\u043e\u0440\u043a\u0430\u0441\u044b"
    ],
    "wof:name":"Shorkasy",
    "wof:placetype":"locality"
},
  "geometry": {"coordinates":[47.03291,55.94226],"type":"Point"}
}