{
  "type": "Feature",
  "properties": {
    "gn:admin1_code":"8",
    "gn:asciiname":"Kaymashbash",
    "gn:country_code":"RU",
    "gn:dem":135,
    "gn:feature_class":"P",
    "gn:feature_code":"PPL",
    "gn:name":"Kaymashbash",
    "gn:population":0,
    "gn:timezone":"Asia/Yekaterinburg",
    "iso:country":"RU",
    "name:eng_x_preferred":[
        "Kaymashbash"
    ],
    "name:nor_x_preferred":[
        "Kajmasjabasj"
    ],
    "name:rus_x_preferred":[
        "\u041a\u0430\u0439\u043c\u0430\u0448\u0430\u0431\u0430\u0448"
    ],
    "name:rus_x_variant":[
        "\u041a\u0430\u0439\u043c\u0430\u0448\u0431\u0430\u0448"
    ],
    "name:und_x_variant":[
        "Kaymasha",
        "Kaymash",
        "Kaymashbash",
        "\u041a\u0430\u0439\u043c\u0430\u0448\u0431\u0430\u0448"
    ],
    "wof:name":"Kaymashbash",
    "wof:placetype":"locality"
},
  "geometry": {"coordinates":[55.07064,56.18798],"type":"Point"}
}