{
  "type": "Feature",
  "properties": {
    "gn:admin1_code":"67",
    "gn:asciiname":"Novaya Slobodka",
    "gn:country_code":"RU",
    "gn:dem":88,
    "gn:feature_class":"P",
    "gn:feature_code":"PPL",
    "gn:name":"Novaya Slobodka",
    "gn:population":0,
    "gn:timezone":"Europe/Saratov",
    "iso:country":"RU",
    "name:rus_x_preferred":[
        "\u041d\u043e\u0432\u0430\u044f \u0421\u043b\u043e\u0431\u043e\u0434\u043a\u0430"
    ],
    "name:und_x_variant":[
        "\u041d\u043e\u0432\u0430\u044f \u0421\u043b\u043e\u0431\u043e\u0434\u043a\u0430"
    ],
    "wof:name":"Novaya Slobodka",
    "wof:placetype":"locality"
},
  "geometry": {"coordinates":[48.3113,51.2523],"type":"Point"}
}