{
  "type": "Feature",
  "properties": {
    "gn:admin1_code":"8",
    "gn:asciiname":"Verkhneye Dudkino",
    "gn:country_code":"RU",
    "gn:dem":92,
    "gn:feature_class":"P",
    "gn:feature_code":"PPL",
    "gn:name":"Verkhneye Dudkino",
    "gn:population":0,
    "gn:timezone":"Asia/Yekaterinburg",
    "iso:country":"RU",
    "name:rus_x_preferred":[
        "\u0412\u0435\u0440\u0445\u043d\u0435\u0435 \u0414\u0443\u0434\u043a\u0438\u043d\u043e"
    ],
    "name:und_x_variant":[
        "\u0412\u0435\u0440\u0445\u043d\u0435\u0435 \u0414\u0443\u0434\u043a\u0438\u043d\u043e"
    ],
    "wof:name":"Verkhneye Dudkino",
    "wof:placetype":"locality"
},
  "geometry": {"coordinates":[56.0453,54.74191999999999],"type":"Point"}
}