{
  "type": "Feature",
  "properties": {
    "gn:admin1_code":"65",
    "gn:asciiname":"Novokrotkovo",
    "gn:country_code":"RU",
    "gn:dem":147,
    "gn:feature_class":"P",
    "gn:feature_code":"PPL",
    "gn:name":"Novokrotkovo",
    "gn:population":0,
    "gn:timezone":"Europe/Samara",
    "iso:country":"RU",
    "name:rus_x_preferred":[
        "\u041d\u043e\u0432\u043e\u043a\u0440\u043e\u0442\u043a\u043e\u0432\u043e"
    ],
    "name:und_x_variant":[
        "\u041d\u043e\u0432\u043e\u043a\u0440\u043e\u0442\u043a\u043e\u0432\u043e"
    ],
    "wof:name":"Novokrotkovo",
    "wof:placetype":"locality"
},
  "geometry": {"coordinates":[52.1407,53.8757],"type":"Point"}
}