{
  "type": "Feature",
  "properties": {
    "gn:admin1_code":"41",
    "gn:asciiname":"Linets",
    "gn:country_code":"RU",
    "gn:dem":188,
    "gn:feature_class":"P",
    "gn:feature_code":"PPL",
    "gn:name":"Linets",
    "gn:population":0,
    "gn:timezone":"Europe/Moscow",
    "iso:country":"RU",
    "name:eng_x_preferred":[
        "Linets"
    ],
    "name:nor_x_preferred":[
        "Linets"
    ],
    "name:rus_x_preferred":[
        "\u041b\u0438\u043d\u0435\u0446"
    ],
    "name:und_x_variant":[
        "Linets Lipets",
        "Lipez",
        "Lipets"
    ],
    "wof:name":"Linets",
    "wof:placetype":"locality"
},
  "geometry": {"coordinates":[35.5318,52.0856],"type":"Point"}
}