{
  "type": "Feature",
  "properties": {
    "gn:admin1_code":"42",
    "gn:asciiname":"Voloskovo",
    "gn:cc2":"RU",
    "gn:country_code":"RU",
    "gn:dem":55,
    "gn:feature_class":"P",
    "gn:feature_code":"PPL",
    "gn:name":"Voloskovo",
    "gn:population":0,
    "gn:timezone":"Europe/Moscow",
    "iso:country":"RU",
    "name:und_x_variant":[
        "Volosovo",
        "Voloskovo"
    ],
    "wof:name":"Voloskovo",
    "wof:placetype":"locality"
},
  "geometry": {"coordinates":[30.75,58.93333000000001],"type":"Point"}
}