{
  "type": "Feature",
  "properties": {
    "gn:admin1_code":"77",
    "gn:asciiname":"Malaya Motolosha",
    "gn:country_code":"RU",
    "gn:dem":146,
    "gn:feature_class":"P",
    "gn:feature_code":"PPL",
    "gn:name":"Malaya Motolosha",
    "gn:population":0,
    "gn:timezone":"Europe/Moscow",
    "iso:country":"RU",
    "name:rus_x_preferred":[
        "\u041c\u0430\u043b\u0430\u044f \u041c\u043e\u0442\u043e\u043b\u043e\u0448\u0430"
    ],
    "wof:name":"Malaya Motolosha",
    "wof:placetype":"locality"
},
  "geometry": {"coordinates":[36.6329,58.1441],"type":"Point"}
}