{
  "type": "Feature",
  "properties": {
    "gn:admin1_code":"84",
    "gn:asciiname":"Samarkin",
    "gn:country_code":"RU",
    "gn:dem":25,
    "gn:feature_class":"P",
    "gn:feature_code":"PPL",
    "gn:name":"Samarkin",
    "gn:population":0,
    "gn:timezone":"Europe/Volgograd",
    "iso:country":"RU",
    "name:rus_x_preferred":[
        "\u0421\u0430\u043c\u0430\u0440\u043a\u0438\u043d"
    ],
    "wof:name":"Samarkin",
    "wof:placetype":"locality"
},
  "geometry": {"coordinates":[46.66662,49.52416],"type":"Point"}
}