{
  "type": "Feature",
  "properties": {
    "gn:admin1_code":"37",
    "gn:asciiname":"Gora",
    "gn:country_code":"RU",
    "gn:dem":141,
    "gn:feature_class":"P",
    "gn:feature_code":"PPL",
    "gn:name":"Gora",
    "gn:population":0,
    "gn:timezone":"Europe/Moscow",
    "iso:country":"RU",
    "name:rus_x_preferred":[
        "\u0413\u043e\u0440\u0430"
    ],
    "name:und_x_variant":[
        "\u0413\u043e\u0440\u0430"
    ],
    "wof:name":"Gora",
    "wof:placetype":"locality"
},
  "geometry": {"coordinates":[42.0114,58.4632],"type":"Point"}
}