{
  "type": "Feature",
  "properties": {
    "gn:admin1_code":"45.0",
    "gn:asciiname":"Yoshkarener",
    "gn:country_code":"RU",
    "gn:dem":123,
    "gn:feature_class":"P",
    "gn:feature_code":"PPL",
    "gn:name":"Yoshkarener",
    "gn:population":0,
    "gn:timezone":"Europe/Moscow",
    "iso:country":"RU",
    "name:rus_x_preferred":[
        "\u0419\u043e\u0448\u043a\u0430\u0440\u0435\u043d\u0435\u0440"
    ],
    "wof:name":"Yoshkarener",
    "wof:placetype":"locality"
},
  "geometry": {"coordinates":[48.37694000000001,56.87444],"type":"Point"}
}