{
  "type": "Feature",
  "properties": {
    "gn:admin1_code":"65",
    "gn:asciiname":"Platforma Tysyacha Sto Shest'desyat Devyatyy Kilometr",
    "gn:country_code":"RU",
    "gn:dem":43,
    "gn:feature_class":"P",
    "gn:feature_code":"PPL",
    "gn:name":"Platforma Tysyacha Sto Shest\u2019desyat Devyatyy Kilometr",
    "gn:population":0,
    "gn:timezone":"Europe/Samara",
    "iso:country":"RU",
    "name:rus_x_preferred":[
        "\u041f\u043b\u0430\u0442\u0444\u043e\u0440\u043c\u0430 \u0422\u044b\u0441\u044f\u0447\u0430 \u0421\u0442\u043e \u0428\u0435\u0441\u0442\u044c\u0434\u0435\u0441\u044f\u0442 \u0414\u0435\u0432\u044f\u0442\u044b\u0439 \u041a\u0438\u043b\u043e\u043c\u0435\u0442\u0440"
    ],
    "name:und_x_variant":[
        "Platforma Tysyacha Sto Shest\u2019desyat Devyatyy Kilometr",
        "\u041f\u043b\u0430\u0442\u0444\u043e\u0440\u043c\u0430 \u0422\u044b\u0441\u044f\u0447\u0430 \u0421\u0442\u043e \u0428\u0435\u0441\u0442\u044c\u0434\u0435\u0441\u044f\u0442 \u0414\u0435\u0432\u044f\u0442\u044b\u0439 \u041a\u0438\u043b\u043e\u043c\u0435\u0442\u0440"
    ],
    "wof:name":"Platforma Tysyacha Sto Shest'desyat Devyatyy Kilometr",
    "wof:placetype":"locality"
},
  "geometry": {"coordinates":[51.0757,53.2726],"type":"Point"}
}