{
  "type": "Feature",
  "properties": {
    "gn:country":"RU",
    "gn:fcode":"PPL",
    "gn:population":3400,
    "iso:country":"RU",
    "name:bak_x_preferred":[
        "\u0411\u04d9\u0493\u0435\u0440\u04d9\u043a\u0442\u0430\u043c\u0430\u04a1"
    ],
    "name:ceb_x_preferred":[
        "Ust'-Bagaryak"
    ],
    "name:che_x_preferred":[
        "\u0423\u0441\u0442\u044c-\u0411\u0430\u0433\u0430\u0440\u044f\u043a"
    ],
    "name:eng_x_preferred":[
        "Ust'-Bagaryak"
    ],
    "name:eng_x_variant":[
        "B\u00e4g\u00e4r\u00e4ktamaq"
    ],
    "name:nld_x_preferred":[
        "Ust'-Bagaryak"
    ],
    "name:nno_x_preferred":[
        "Ust-Bagarjak"
    ],
    "name:nob_x_preferred":[
        "Ust-Bagarjak"
    ],
    "name:nor_x_preferred":[
        "Ust-Bagarjak"
    ],
    "name:rus_x_preferred":[
        "\u0423\u0441\u0442\u044c-\u0411\u0430\u0433\u0430\u0440\u044f\u043a"
    ],
    "name:tat_x_preferred":[
        "\u0411\u04d9\u0433\u04d9\u0440\u04d9\u043a\u0442\u0430\u043c\u0430\u043a"
    ],
    "name:ukr_x_preferred":[
        "\u0423\u0441\u0442\u044c-\u0411\u0430\u0433\u0430\u0440\u044f\u043a"
    ],
    "name:und_x_variant":[
        "Nizhnyaya"
    ],
    "qs_pg:aaroncc":"RU",
    "qs_pg:gn_country":"RU",
    "qs_pg:gn_fcode":"PPL",
    "qs_pg:gn_pop":3400,
    "qs_pg:name":"Ust\u2019-Bagaryak",
    "qs_pg:photos_9r":0,
    "qs_pg:photos_sr":0,
    "qs_pg:pop_sr":4,
    "qs_pg:qs_pg_placetype":"locality",
    "wof:name":"Ust\u2019-Bagaryak",
    "wof:placetype":"locality",
    "wof:population":3400
},
  "geometry": {"coordinates":[61.84722,56.13278],"type":"Point"}
}