{
  "type": "Feature",
  "properties": {
    "gn:admin1_code":"16.0",
    "gn:asciiname":"Attikovo",
    "gn:country_code":"RU",
    "gn:dem":127,
    "gn:feature_class":"P",
    "gn:feature_code":"PPL",
    "gn:name":"Attikovo",
    "gn:population":0,
    "gn:timezone":"Europe/Moscow",
    "iso:country":"RU",
    "name:nor_x_preferred":[
        "Attikovo"
    ],
    "name:rus_x_preferred":[
        "\u0410\u0442\u0442\u0438\u043a\u043e\u0432\u043e"
    ],
    "name:und_x_variant":[
        "Atikovo",
        "Attikovo"
    ],
    "wof:name":"Attikovo",
    "wof:placetype":"locality"
},
  "geometry": {"coordinates":[48.12678,55.77696],"type":"Point"}
}