{
  "type": "Feature",
  "properties": {
    "gn:admin1_code":"55",
    "gn:asciiname":"Kipchag",
    "gn:country_code":"RU",
    "gn:dem":116,
    "gn:feature_class":"P",
    "gn:feature_code":"PPL",
    "gn:name":"Kipchag",
    "gn:population":0,
    "gn:timezone":"Asia/Yekaterinburg",
    "iso:country":"RU",
    "name:eng_x_preferred":[
        "Kipchak"
    ],
    "name:nor_x_preferred":[
        "Kiptsjag"
    ],
    "name:rus_x_preferred":[
        "\u041a\u0438\u043f\u0447\u0430\u0433"
    ],
    "name:und_x_variant":[
        "\u041a\u0438\u043f\u0447\u0430\u0433",
        "Kipchag",
        "Kipchak"
    ],
    "wof:name":"Kipchag",
    "wof:placetype":"locality"
},
  "geometry": {"coordinates":[52.685,53.94489],"type":"Point"}
}