{
  "type": "Feature",
  "properties": {
    "gn:admin1_code":"90",
    "gn:asciiname":"Shumilovka",
    "gn:country_code":"RU",
    "gn:dem":188,
    "gn:feature_class":"P",
    "gn:feature_code":"PPL",
    "gn:name":"Shumilovka",
    "gn:population":0,
    "gn:timezone":"Asia/Yekaterinburg",
    "iso:country":"RU",
    "name:che_x_preferred":[
        "\u0428\u0443\u043c\u0438\u043b\u043e\u0432\u043a\u0430"
    ],
    "name:rus_x_preferred":[
        "\u0428\u0443\u043c\u0438\u043b\u043e\u0432\u043a\u0430"
    ],
    "name:und_x_variant":[
        "\u0428\u0443\u043c\u0438\u043b\u043e\u0432\u043a\u0430"
    ],
    "wof:name":"Shumilovka",
    "wof:placetype":"locality"
},
  "geometry": {"coordinates":[56.4812,57.5064],"type":"Point"}
}