{
  "type": "Feature",
  "properties": {
    "gn:admin1_code":"71",
    "gn:asciiname":"Kalinovskoye",
    "gn:country_code":"RU",
    "gn:dem":92,
    "gn:feature_class":"P",
    "gn:feature_code":"PPL",
    "gn:name":"Kalinovskoye",
    "gn:population":0,
    "gn:timezone":"Asia/Yekaterinburg",
    "iso:country":"RU",
    "name:rus_x_preferred":[
        "\u041a\u0430\u043b\u0438\u043d\u043e\u0432\u0441\u043a\u043e\u0435"
    ],
    "name:und_x_variant":[
        "Bol\u2019shoye Kalinovskoye",
        "Kalinovskoye"
    ],
    "wof:name":"Kalinovskoye",
    "wof:placetype":"locality"
},
  "geometry": {"coordinates":[62.4809,56.8197],"type":"Point"}
}