{
  "type": "Feature",
  "properties": {
    "gn:admin1_code":"17",
    "gn:admin2_code":"Tsuntinskiy Rayon",
    "gn:asciiname":"Kimyatli",
    "gn:country_code":"RU",
    "gn:dem":1924,
    "gn:feature_class":"P",
    "gn:feature_code":"PPL",
    "gn:name":"Kimyatli",
    "gn:population":0,
    "gn:timezone":"Europe/Moscow",
    "iso:country":"RU",
    "name:rus_x_preferred":[
        "\u041a\u0438\u043c\u044f\u0442\u043b\u0438"
    ],
    "name:und_x_variant":[
        "Kematl\u2019",
        "Kamatl\u2019",
        "Kimyatli",
        "\u041a\u0438\u043c\u044f\u0442\u043b\u0438"
    ],
    "wof:name":"Kimyatli",
    "wof:placetype":"locality"
},
  "geometry": {"coordinates":[45.82303,42.2488],"type":"Point"}
}