{
  "type": "Feature",
  "properties": {
    "gn:admin1_code":"62",
    "gn:asciiname":"Maksy",
    "gn:country_code":"RU",
    "gn:dem":126,
    "gn:feature_class":"P",
    "gn:feature_code":"PPL",
    "gn:name":"Maksy",
    "gn:population":0,
    "gn:timezone":"Europe/Moscow",
    "iso:country":"RU",
    "name:eng_x_preferred":[
        "Maksy"
    ],
    "name:nor_x_preferred":[
        "Maksy"
    ],
    "name:rus_x_preferred":[
        "\u041c\u0430\u043a\u0441\u044b"
    ],
    "wof:name":"Maksy",
    "wof:placetype":"locality"
},
  "geometry": {"coordinates":[41.283,53.70241],"type":"Point"}
}