{
  "type": "Feature",
  "properties": {
    "gn:admin1_code":"28",
    "gn:asciiname":"Kaynula",
    "gn:country_code":"RU",
    "gn:dem":162,
    "gn:feature_class":"P",
    "gn:feature_code":"PPL",
    "gn:name":"Kaynula",
    "gn:population":0,
    "gn:timezone":"Europe/Moscow",
    "iso:country":"RU",
    "name:rus_x_preferred":[
        "\u041a\u0430\u0439\u043d\u0443\u043b\u0430"
    ],
    "wof:name":"Kaynula",
    "wof:placetype":"locality"
},
  "geometry": {"coordinates":[31.50827,62.71029],"type":"Point"}
}