{
  "type": "Feature",
  "properties": {
    "gn:admin1_code":"33.0",
    "gn:asciiname":"Osipyata",
    "gn:country_code":"RU",
    "gn:dem":227,
    "gn:feature_class":"P",
    "gn:feature_code":"PPL",
    "gn:name":"Osipyata",
    "gn:population":0,
    "gn:timezone":"Europe/Kirov",
    "iso:country":"RU",
    "name:rus_x_preferred":[
        "\u041e\u0441\u0438\u043f\u044f\u0442\u0430"
    ],
    "name:und_x_variant":[
        "\u041e\u0441\u0438\u043f\u044f\u0442\u0430"
    ],
    "wof:name":"Osipyata",
    "wof:placetype":"locality"
},
  "geometry": {"coordinates":[50.97774,59.44158],"type":"Point"}
}