{
  "type": "Feature",
  "properties": {
    "gn:admin1_code":"88",
    "gn:asciiname":"Shchurovo",
    "gn:country_code":"RU",
    "gn:dem":175,
    "gn:feature_class":"P",
    "gn:feature_code":"PPL",
    "gn:name":"Shchurovo",
    "gn:population":0,
    "gn:timezone":"Europe/Moscow",
    "iso:country":"RU",
    "name:eng_x_preferred":[
        "Shchurovo"
    ],
    "name:nor_x_preferred":[
        "Sjtsjurovo"
    ],
    "name:rus_x_preferred":[
        "\u0429\u0443\u0440\u043e\u0432\u043e"
    ],
    "name:und_x_variant":[
        "Shurovo",
        "\u0429\u0443\u0440\u043e\u0432\u043e",
        "Shchurovo"
    ],
    "wof:name":"Shchurovo",
    "wof:placetype":"locality"
},
  "geometry": {"coordinates":[38.8146,57.16814],"type":"Point"}
}