{
  "type": "Feature",
  "properties": {
    "gn:admin1_code":"25",
    "gn:asciiname":"Polyudovo",
    "gn:country_code":"RU",
    "gn:dem":205,
    "gn:feature_class":"P",
    "gn:feature_code":"PPL",
    "gn:name":"Polyudovo",
    "gn:population":0,
    "gn:timezone":"Europe/Moscow",
    "iso:country":"RU",
    "name:eng_x_preferred":[
        "Polyudovo"
    ],
    "name:nor_x_preferred":[
        "Poljudovo"
    ],
    "name:rus_x_preferred":[
        "\u041f\u043e\u043b\u044e\u0434\u043e\u0432\u043e"
    ],
    "name:und_x_variant":[
        "\u041f\u043e\u043b\u044e\u0434\u043e\u0432\u043e",
        "Polyudovo"
    ],
    "wof:name":"Polyudovo",
    "wof:placetype":"locality"
},
  "geometry": {"coordinates":[35.00109,53.76259],"type":"Point"}
}