{
  "type": "Feature",
  "properties": {
    "gn:admin1_code":"84",
    "gn:asciiname":"Pronosnyy",
    "gn:country_code":"RU",
    "gn:dem":64,
    "gn:feature_class":"P",
    "gn:feature_code":"PPL",
    "gn:name":"Pronosnyy",
    "gn:population":0,
    "gn:timezone":"Europe/Volgograd",
    "iso:country":"RU",
    "name:rus_x_preferred":[
        "\u041f\u0440\u043e\u043d\u043e\u0441\u043d\u044b\u0439"
    ],
    "name:und_x_variant":[
        "Prokosnyy",
        "Pronosnyy",
        "\u041f\u0440\u043e\u043d\u043e\u0441\u043d\u044b\u0439"
    ],
    "wof:name":"Pronosnyy",
    "wof:placetype":"locality"
},
  "geometry": {"coordinates":[42.4549,50.0604],"type":"Point"}
}