{
  "type": "Feature",
  "properties": {
    "gn:admin1_code":"40",
    "gn:asciiname":"Orlovo",
    "gn:country_code":"RU",
    "gn:dem":132,
    "gn:feature_class":"P",
    "gn:feature_code":"PPL",
    "gn:name":"Orlovo",
    "gn:population":0,
    "gn:timezone":"Asia/Yekaterinburg",
    "iso:country":"RU",
    "name:rus_x_preferred":[
        "\u041e\u0440\u043b\u043e\u0432\u043e"
    ],
    "name:und_x_variant":[
        "\u041e\u0440\u043b\u043e\u0432\u043e"
    ],
    "wof:name":"Orlovo",
    "wof:placetype":"locality"
},
  "geometry": {"coordinates":[68.33778000000001,55.21694],"type":"Point"}
}