{
  "type": "Feature",
  "properties": {
    "gn:admin1_code":"40",
    "gn:asciiname":"Baskazyk",
    "gn:country_code":"RU",
    "gn:dem":142,
    "gn:feature_class":"P",
    "gn:feature_code":"PPL",
    "gn:name":"Baskazyk",
    "gn:population":0,
    "gn:timezone":"Asia/Yekaterinburg",
    "iso:country":"RU",
    "name:nor_x_preferred":[
        "Baskazyk"
    ],
    "name:rus_x_preferred":[
        "\u0411\u0430\u0441\u043a\u0430\u0437\u044b\u043a"
    ],
    "wof:name":"Baskazyk",
    "wof:placetype":"locality"
},
  "geometry": {"coordinates":[62.5465,55.8092],"type":"Point"}
}