{
  "type": "Feature",
  "properties": {
    "gn:admin1_code":"59",
    "gn:asciiname":"Tsukanovo",
    "gn:country_code":"RU",
    "gn:dem":35,
    "gn:feature_class":"P",
    "gn:feature_code":"PPL",
    "gn:name":"Tsukanovo",
    "gn:population":0,
    "gn:timezone":"Asia/Vladivostok",
    "iso:country":"RU",
    "name:rus_x_preferred":[
        "\u0426\u0443\u043a\u0430\u043d\u043e\u0432\u043e"
    ],
    "name:und_x_variant":[
        "Nizhneye Yanchikhe",
        "Nizhne-Yanchikhe",
        "Tsukanovo"
    ],
    "wof:name":"Tsukanovo",
    "wof:placetype":"locality"
},
  "geometry": {"coordinates":[130.78241,42.75871],"type":"Point"}
}