{
  "type": "Feature",
  "properties": {
    "gn:admin1_code":"76",
    "gn:asciiname":"Karlino",
    "gn:country_code":"RU",
    "gn:dem":208,
    "gn:feature_class":"P",
    "gn:feature_code":"PPL",
    "gn:name":"Karlino",
    "gn:population":0,
    "gn:timezone":"Europe/Moscow",
    "iso:country":"RU",
    "name:ceb_x_preferred":[
        "Karlino"
    ],
    "name:ces_x_preferred":[
        "Karlino"
    ],
    "name:csb_x_preferred":[
        "Karlino"
    ],
    "name:deu_x_preferred":[
        "Karlino"
    ],
    "name:epo_x_preferred":[
        "Karlino"
    ],
    "name:est_x_preferred":[
        "Karlino"
    ],
    "name:fra_x_preferred":[
        "Karlino"
    ],
    "name:jav_x_preferred":[
        "Karlino"
    ],
    "name:kaz_x_preferred":[
        "\u041a\u0430\u0440\u043b\u0438\u043d\u043e"
    ],
    "name:lav_x_preferred":[
        "Karlino"
    ],
    "name:msa_x_preferred":[
        "Karlino"
    ],
    "name:nld_x_preferred":[
        "Karlino"
    ],
    "name:pol_x_preferred":[
        "Karlino"
    ],
    "name:por_x_preferred":[
        "Karlino"
    ],
    "name:ron_x_preferred":[
        "Karlino"
    ],
    "name:rus_x_preferred":[
        "\u041a\u0430\u0440\u043b\u0438\u043d\u043e"
    ],
    "name:slk_x_preferred":[
        "Karlino"
    ],
    "name:srp_x_preferred":[
        "\u041a\u0430\u0440\u043b\u0438\u043d\u043e"
    ],
    "name:swe_x_preferred":[
        "Karlino"
    ],
    "name:ukr_x_preferred":[
        "\u041a\u0430\u0440\u043b\u0456\u043d\u043e"
    ],
    "name:und_x_variant":[
        "\u041a\u0430\u0440\u043b\u0438\u043d\u043e"
    ],
    "name:vie_x_preferred":[
        "Karlino"
    ],
    "name:zho_x_preferred":[
        "\u5361\u723e\u5229\u8afe"
    ],
    "wof:name":"Karlino",
    "wof:placetype":"locality"
},
  "geometry": {"coordinates":[38.36046,53.70151],"type":"Point"}
}