{
  "type": "Feature",
  "properties": {
    "gn:admin1_code":"90.0",
    "gn:asciiname":"Yezhi",
    "gn:country_code":"RU",
    "gn:dem":113,
    "gn:feature_class":"P",
    "gn:feature_code":"PPL",
    "gn:name":"Yezhi",
    "gn:population":0,
    "gn:timezone":"Asia/Yekaterinburg",
    "iso:country":"RU",
    "name:che_x_preferred":[
        "\u0415\u0436\u0438"
    ],
    "name:rus_x_preferred":[
        "\u0415\u0436\u0438"
    ],
    "wof:name":"Yezhi",
    "wof:placetype":"locality"
},
  "geometry": {"coordinates":[55.8515,57.9265],"type":"Point"}
}