{
  "type": "Feature",
  "properties": {
    "gn:admin1_code":"76",
    "gn:asciiname":"Kondrovo",
    "gn:country_code":"RU",
    "gn:dem":239,
    "gn:feature_class":"P",
    "gn:feature_code":"PPL",
    "gn:name":"Kondrovo",
    "gn:population":0,
    "gn:timezone":"Europe/Moscow",
    "iso:country":"RU",
    "name:rus_x_preferred":[
        "\u041a\u043e\u043d\u0434\u0440\u043e\u0432\u043e"
    ],
    "name:und_x_variant":[
        "\u041a\u043e\u043d\u0434\u0440\u043e\u0432\u043e"
    ],
    "wof:name":"Kondrovo",
    "wof:placetype":"locality"
},
  "geometry": {"coordinates":[38.14375,53.93247],"type":"Point"}
}