{
  "type": "Feature",
  "properties": {
    "gn:admin1_code":"56",
    "gn:asciiname":"Chekhovskiy",
    "gn:country_code":"RU",
    "gn:dem":215,
    "gn:feature_class":"P",
    "gn:feature_code":"PPL",
    "gn:name":"Chekhovskiy",
    "gn:population":0,
    "gn:timezone":"Europe/Moscow",
    "iso:country":"RU",
    "name:rus_x_preferred":[
        "\u0427\u0435\u0445\u043e\u0432\u0441\u043a\u0438\u0439"
    ],
    "name:und_x_variant":[
        "\u0427\u0435\u0445\u043e\u0432\u0441\u043a\u0438\u0439"
    ],
    "wof:name":"Chekhovskiy",
    "wof:placetype":"locality"
},
  "geometry": {"coordinates":[35.68671,53.22356],"type":"Point"}
}