{
  "type": "Feature",
  "properties": {
    "gn:admin1_code":"61",
    "gn:asciiname":"Ravnopol'",
    "gn:country_code":"RU",
    "gn:dem":135,
    "gn:feature_class":"P",
    "gn:feature_code":"PPL",
    "gn:name":"Ravnopol\u2019",
    "gn:population":0,
    "gn:timezone":"Europe/Moscow",
    "iso:country":"RU",
    "name:rus_x_preferred":[
        "\u0420\u0430\u0432\u043d\u043e\u043f\u043e\u043b\u044c"
    ],
    "name:und_x_variant":[
        "Ravnopol\u2019"
    ],
    "wof:name":"Ravnopol'",
    "wof:placetype":"locality"
},
  "geometry": {"coordinates":[39.07611,47.75861],"type":"Point"}
}