{
  "type": "Feature",
  "properties": {
    "gn:admin1_code":"54",
    "gn:asciiname":"Sbornoye",
    "gn:cc2":"RU",
    "gn:country_code":"RU",
    "gn:dem":127,
    "gn:feature_class":"P",
    "gn:feature_code":"PPL",
    "gn:name":"Sbornoye",
    "gn:population":0,
    "gn:timezone":"Asia/Omsk",
    "iso:country":"RU",
    "name:rus_x_preferred":[
        "\u0421\u0431\u043e\u0440\u043d\u043e\u0435"
    ],
    "name:und_x_variant":[
        "Sbornyy",
        "Sbornoye"
    ],
    "wof:name":"Sbornoye",
    "wof:placetype":"locality"
},
  "geometry": {"coordinates":[74.55,57.28333000000001],"type":"Point"}
}