{
  "type": "Feature",
  "properties": {
    "gn:admin1_code":"77",
    "gn:asciiname":"Sady",
    "gn:country_code":"RU",
    "gn:dem":266,
    "gn:feature_class":"P",
    "gn:feature_code":"PPL",
    "gn:name":"Sady",
    "gn:population":0,
    "gn:timezone":"Europe/Moscow",
    "iso:country":"RU",
    "name:ces_x_preferred":[
        "Sady"
    ],
    "name:deu_x_preferred":[
        "Sady"
    ],
    "name:fra_x_preferred":[
        "Sady"
    ],
    "name:ita_x_preferred":[
        "Sady"
    ],
    "name:pol_x_preferred":[
        "Sady"
    ],
    "name:rus_x_preferred":[
        "\u0421\u0430\u0434\u044b"
    ],
    "name:slk_x_preferred":[
        "Sady"
    ],
    "name:ukr_x_preferred":[
        "\u0421\u0430\u0434\u0438"
    ],
    "name:und_x_variant":[
        "\u0421\u0430\u0434\u044b"
    ],
    "wof:name":"Sady",
    "wof:placetype":"locality"
},
  "geometry": {"coordinates":[33.62019,56.25098000000001],"type":"Point"}
}