{
  "type": "Feature",
  "properties": {
    "gn:admin1_code":"76",
    "gn:asciiname":"Lomovskiy",
    "gn:country_code":"RU",
    "gn:dem":225,
    "gn:feature_class":"P",
    "gn:feature_code":"PPL",
    "gn:name":"Lomovskiy",
    "gn:population":0,
    "gn:timezone":"Europe/Moscow",
    "iso:country":"RU",
    "name:rus_x_preferred":[
        "\u041b\u043e\u043c\u043e\u0432\u0441\u043a\u0438\u0439"
    ],
    "name:und_x_variant":[
        "\u041b\u043e\u043c\u043e\u0432\u0441\u043a\u0438\u0439"
    ],
    "wof:name":"Lomovskiy",
    "wof:placetype":"locality"
},
  "geometry": {"coordinates":[37.74252,53.62286],"type":"Point"}
}