{
  "type": "Feature",
  "properties": {
    "gn:admin1_code":"61",
    "gn:asciiname":"Ol'khovskiy",
    "gn:country_code":"RU",
    "gn:dem":14,
    "gn:feature_class":"P",
    "gn:feature_code":"PPL",
    "gn:name":"Ol\u2019khovskiy",
    "gn:population":0,
    "gn:timezone":"Europe/Moscow",
    "iso:country":"RU",
    "name:eng_x_preferred":[
        "Ol'khovskiy"
    ],
    "name:nor_x_preferred":[
        "Olkhovskij"
    ],
    "name:rus_x_preferred":[
        "\u041e\u043b\u044c\u0445\u043e\u0432\u0441\u043a\u0438\u0439"
    ],
    "name:und_x_variant":[
        "Ol\u2019khovka",
        "\u041e\u043b\u044c\u0445\u043e\u0432\u0441\u043a\u0438\u0439",
        "Ol\u2019khovskiy"
    ],
    "wof:name":"Ol'khovskiy",
    "wof:placetype":"locality"
},
  "geometry": {"coordinates":[40.70494,47.64071],"type":"Point"}
}