{
  "type": "Feature",
  "properties": {
    "gn:admin1_code":"17.0",
    "gn:asciiname":"Akhayotar",
    "gn:country_code":"RU",
    "gn:dem":-7,
    "gn:feature_class":"P",
    "gn:feature_code":"PPL",
    "gn:name":"Akhayotar",
    "gn:population":0,
    "gn:timezone":"Europe/Moscow",
    "iso:country":"RU",
    "name:nor_x_preferred":[
        "Akhajotar"
    ],
    "name:rus_x_preferred":[
        "\u0410\u0445\u0430\u0439\u043e\u0442\u0430\u0440"
    ],
    "wof:name":"Akhayotar",
    "wof:placetype":"locality"
},
  "geometry": {"coordinates":[46.81724000000001,43.65044],"type":"Point"}
}