{
  "type": "Feature",
  "properties": {
    "gn:admin1_code":"83",
    "gn:asciiname":"Poleskovo",
    "gn:country_code":"RU",
    "gn:dem":81,
    "gn:feature_class":"P",
    "gn:feature_code":"PPL",
    "gn:name":"Poleskovo",
    "gn:population":0,
    "gn:timezone":"Europe/Moscow",
    "iso:country":"RU",
    "name:rus_x_preferred":[
        "\u041f\u043e\u043b\u0435\u0441\u043a\u043e\u0432\u043e"
    ],
    "name:und_x_variant":[
        "Pleskovo",
        "Poleskovo",
        "\u041f\u043e\u043b\u0435\u0441\u043a\u043e\u0432\u043e"
    ],
    "wof:name":"Poleskovo",
    "wof:placetype":"locality"
},
  "geometry": {"coordinates":[42.4535,55.8589],"type":"Point"}
}