{
  "type": "Feature",
  "properties": {
    "gn:admin1_code":"33.0",
    "gn:asciiname":"Ovsyanniki",
    "gn:country_code":"RU",
    "gn:dem":165,
    "gn:feature_class":"P",
    "gn:feature_code":"PPL",
    "gn:name":"Ovsyanniki",
    "gn:population":0,
    "gn:timezone":"Europe/Kirov",
    "iso:country":"RU",
    "name:rus_x_preferred":[
        "\u041e\u0432\u0441\u044f\u043d\u043d\u0438\u043a\u0438"
    ],
    "name:und_x_variant":[
        "\u041e\u0432\u0441\u044f\u043d\u043d\u0438\u043a\u0438"
    ],
    "wof:name":"Ovsyanniki",
    "wof:placetype":"locality"
},
  "geometry": {"coordinates":[50.79194,58.26111],"type":"Point"}
}