{
  "type": "Feature",
  "properties": {
    "gn:admin1_code":"77",
    "gn:asciiname":"Obukhovo",
    "gn:country_code":"RU",
    "gn:dem":193,
    "gn:feature_class":"P",
    "gn:feature_code":"PPL",
    "gn:name":"Obukhovo",
    "gn:population":0,
    "gn:timezone":"Europe/Moscow",
    "iso:country":"RU",
    "name:rus_x_preferred":[
        "\u041e\u0431\u0443\u0445\u043e\u0432\u043e"
    ],
    "name:und_x_variant":[
        "\u041e\u0431\u0443\u0445\u043e\u0432\u043e"
    ],
    "wof:name":"Obukhovo",
    "wof:placetype":"locality"
},
  "geometry": {"coordinates":[34.69022,56.96554],"type":"Point"}
}