{
  "type": "Feature",
  "properties": {
    "gn:admin1_code":"85",
    "gn:asciiname":"Srodino",
    "gn:country_code":"RU",
    "gn:dem":188,
    "gn:feature_class":"P",
    "gn:feature_code":"PPL",
    "gn:name":"Srodino",
    "gn:population":0,
    "gn:timezone":"Europe/Moscow",
    "iso:country":"RU",
    "name:eng_x_preferred":[
        "Srodino"
    ],
    "name:nor_x_preferred":[
        "Srodino"
    ],
    "name:rus_x_preferred":[
        "\u0421\u0440\u043e\u0434\u0438\u043d\u043e"
    ],
    "name:und_x_variant":[
        "Sredino"
    ],
    "wof:name":"Srodino",
    "wof:placetype":"locality"
},
  "geometry": {"coordinates":[42.34322,60.01253000000001],"type":"Point"}
}