{
  "type": "Feature",
  "properties": {
    "gn:country":"RU",
    "gn:fcode":"PPL",
    "gn:pop":0,
    "iso:country":"RU",
    "name:rus_x_preferred":[
        "\u0421\u043a\u0438\u0440\u0438\u043d\u043e"
    ],
    "name:unk_x_variant":[
        "\u0421\u043a\u0438\u0440\u0438\u043d\u043e"
    ],
    "qs:name":"Skirino",
    "qs:name_adm0":"Russia",
    "qs:name_adm1":"Novgorod Oblast",
    "qs:photos_9k":1,
    "qs:photos_9r":1,
    "qs:photos_all":1,
    "qs:photos_sr":0,
    "qs:placetype":"Town",
    "qs:pop_sr":"0",
    "wof:name":"Skirino",
    "wof:placetype":"locality",
    "wof:population":0
},
  "geometry": {"coordinates":[30.46144,58.15617],"type":"Point"}
}