{
  "type": "Feature",
  "properties": {
    "gn:admin1_code":"55",
    "gn:asciiname":"Shirokaya Zhizn'",
    "gn:country_code":"RU",
    "gn:dem":90,
    "gn:feature_class":"P",
    "gn:feature_code":"PPL",
    "gn:name":"Shirokaya Zhizn\u2019",
    "gn:population":0,
    "gn:timezone":"Asia/Yekaterinburg",
    "iso:country":"RU",
    "name:rus_x_preferred":[
        "\u0428\u0438\u0440\u043e\u043a\u0430\u044f \u0416\u0438\u0437\u043d\u044c"
    ],
    "name:und_x_variant":[
        "Shirokaya Zhizn\u2019",
        "Lukinka"
    ],
    "wof:name":"Shirokaya Zhizn'",
    "wof:placetype":"locality"
},
  "geometry": {"coordinates":[52.4716,53.4097],"type":"Point"}
}