{
  "type": "Feature",
  "properties": {
    "gn:admin1_code":"27",
    "gn:asciiname":"Psysh",
    "gn:country_code":"RU",
    "gn:dem":1579,
    "gn:feature_class":"P",
    "gn:feature_code":"PPL",
    "gn:name":"Psysh",
    "gn:population":0,
    "gn:timezone":"Europe/Moscow",
    "iso:country":"RU",
    "wof:name":"Psysh",
    "wof:placetype":"locality"
},
  "geometry": {"coordinates":[41.23333,43.51667],"type":"Point"}
}