{
  "type": "Feature",
  "properties": {
    "gn:admin1_code":"67.0",
    "gn:asciiname":"Finogeyevka",
    "gn:country_code":"RU",
    "gn:dem":128,
    "gn:feature_class":"P",
    "gn:feature_code":"PPL",
    "gn:name":"Finogeyevka",
    "gn:population":0,
    "gn:timezone":"Europe/Saratov",
    "iso:country":"RU",
    "name:rus_x_preferred":[
        "\u0424\u0438\u043d\u043e\u0433\u0435\u0435\u0432\u043a\u0430"
    ],
    "wof:name":"Finogeyevka",
    "wof:placetype":"locality"
},
  "geometry": {"coordinates":[42.99556,51.83389],"type":"Point"}
}