{
  "type": "Feature",
  "properties": {
    "gn:admin1_code":"40",
    "gn:asciiname":"Krasnaya Niva",
    "gn:country_code":"RU",
    "gn:dem":131,
    "gn:feature_class":"P",
    "gn:feature_code":"PPL",
    "gn:name":"Krasnaya Niva",
    "gn:population":0,
    "gn:timezone":"Asia/Yekaterinburg",
    "iso:country":"RU",
    "name:rus_x_preferred":[
        "\u041a\u0440\u0430\u0441\u043d\u0430\u044f \u041d\u0438\u0432\u0430"
    ],
    "wof:name":"Krasnaya Niva",
    "wof:placetype":"locality"
},
  "geometry": {"coordinates":[63.6466,56.021],"type":"Point"}
}