{
  "type": "Feature",
  "properties": {
    "gn:admin1_code":"28",
    "gn:asciiname":"Lekhtovaara",
    "gn:cc2":"RU",
    "gn:country_code":"RU",
    "gn:dem":242,
    "gn:feature_class":"P",
    "gn:feature_code":"PPL",
    "gn:name":"Lekhtovaara",
    "gn:population":0,
    "gn:timezone":"Europe/Moscow",
    "iso:country":"RU",
    "name:fin_x_preferred":[
        "Lehtovaara"
    ],
    "name:rus_x_preferred":[
        "\u041b\u0435\u0445\u0442\u043e\u0432\u0430\u0430\u0440\u0430"
    ],
    "wof:name":"Lekhtovaara",
    "wof:placetype":"locality"
},
  "geometry": {"coordinates":[30.03333,65.58333],"type":"Point"}
}