{
  "type": "Feature",
  "properties": {
    "gn:admin1_code":"67",
    "gn:asciiname":"Krasnoarmeyskoye",
    "gn:country_code":"RU",
    "gn:dem":24,
    "gn:feature_class":"P",
    "gn:feature_code":"PPL",
    "gn:name":"Krasnoarmeyskoye",
    "gn:population":0,
    "gn:timezone":"Europe/Saratov",
    "iso:country":"RU",
    "name:eng_x_preferred":[
        "Krasnoarmeyskoye"
    ],
    "name:nor_x_preferred":[
        "Krasnoarmejskoje"
    ],
    "name:rus_x_preferred":[
        "\u041a\u0440\u0430\u0441\u043d\u043e\u0430\u0440\u043c\u0435\u0439\u0441\u043a\u043e\u0435"
    ],
    "name:und_x_variant":[
        "Brabander"
    ],
    "wof:name":"Krasnoarmeyskoye",
    "wof:placetype":"locality"
},
  "geometry": {"coordinates":[45.91722,51.20389],"type":"Point"}
}