{
  "type": "Feature",
  "properties": {
    "gn:admin1_code":"51",
    "gn:asciiname":"L'vovka",
    "gn:country_code":"RU",
    "gn:dem":192,
    "gn:feature_class":"P",
    "gn:feature_code":"PPL",
    "gn:name":"L\u2019vovka",
    "gn:population":0,
    "gn:timezone":"Europe/Moscow",
    "iso:country":"RU",
    "name:rus_x_preferred":[
        "\u041b\u044c\u0432\u043e\u0432\u043a\u0430"
    ],
    "name:und_x_variant":[
        "L\u2019vovka",
        "\u041b\u044c\u0432\u043e\u0432\u043a\u0430"
    ],
    "wof:name":"L'vovka",
    "wof:placetype":"locality"
},
  "geometry": {"coordinates":[45.3148,54.9334],"type":"Point"}
}