{
  "type": "Feature",
  "properties": {
    "gn:admin1_code":"63",
    "gn:asciiname":"Yuzhnyy Khatyngnakh",
    "gn:country_code":"RU",
    "gn:dem":40,
    "gn:feature_class":"P",
    "gn:feature_code":"PPL",
    "gn:name":"Yuzhnyy Khatyngnakh",
    "gn:population":0,
    "gn:timezone":"Asia/Magadan",
    "iso:country":"RU",
    "wof:name":"Yuzhnyy Khatyngnakh",
    "wof:placetype":"locality"
},
  "geometry": {"coordinates":[152.44999999999999,67.41667],"type":"Point"}
}