{
  "type": "Feature",
  "properties": {
    "gn:admin1_code":"51",
    "gn:asciiname":"Kotel'nitsy",
    "gn:country_code":"RU",
    "gn:dem":106,
    "gn:feature_class":"P",
    "gn:feature_code":"PPL",
    "gn:name":"Kotel\u2019nitsy",
    "gn:population":0,
    "gn:timezone":"Europe/Moscow",
    "iso:country":"RU",
    "name:nor_x_preferred":[
        "Kotelnitsy"
    ],
    "name:rus_x_preferred":[
        "\u041a\u043e\u0442\u0435\u043b\u044c\u043d\u0438\u0446\u044b"
    ],
    "name:und_x_variant":[
        "Kotel\u2019nitsy"
    ],
    "wof:name":"Kotel'nitsy",
    "wof:placetype":"locality"
},
  "geometry": {"coordinates":[43.21247,56.80976999999999],"type":"Point"}
}