{
  "type": "Feature",
  "properties": {
    "gn:admin1_code":"10.0",
    "gn:asciiname":"Chishchenoye",
    "gn:country_code":"RU",
    "gn:dem":245,
    "gn:feature_class":"P",
    "gn:feature_code":"PPL",
    "gn:name":"Chishchenoye",
    "gn:population":0,
    "gn:timezone":"Europe/Moscow",
    "iso:country":"RU",
    "name:rus_x_preferred":[
        "\u0427\u0438\u0449\u0435\u043d\u043e\u0435"
    ],
    "wof:name":"Chishchenoye",
    "wof:placetype":"locality"
},
  "geometry": {"coordinates":[34.90818,52.69065],"type":"Point"}
}