{
  "type": "Feature",
  "properties": {
    "gn:admin1_code":"68.0",
    "gn:asciiname":"Dagom",
    "gn:country_code":"RU",
    "gn:dem":1489,
    "gn:feature_class":"P",
    "gn:feature_code":"PPL",
    "gn:name":"Dagom",
    "gn:population":0,
    "gn:timezone":"Europe/Moscow",
    "iso:country":"RU",
    "name:rus_x_preferred":[
        "\u0414\u0430\u0433\u043e\u043c"
    ],
    "name:und_x_variant":[
        "\u0414\u0430\u0433\u043e\u043c"
    ],
    "wof:name":"Dagom",
    "wof:placetype":"locality"
},
  "geometry": {"coordinates":[44.18476,42.86101],"type":"Point"}
}