{
  "type": "Feature",
  "properties": {
    "gn:admin1_code":"47",
    "gn:asciiname":"Maurino",
    "gn:country_code":"RU",
    "gn:dem":169,
    "gn:feature_class":"P",
    "gn:feature_code":"PPL",
    "gn:name":"Maurino",
    "gn:population":0,
    "gn:timezone":"Europe/Moscow",
    "iso:country":"RU",
    "name:rus_x_preferred":[
        "\u041c\u0430\u0443\u0440\u0438\u043d\u043e"
    ],
    "wof:name":"Maurino",
    "wof:placetype":"locality"
},
  "geometry": {"coordinates":[36.56513,55.45353000000001],"type":"Point"}
}