{
  "type": "Feature",
  "properties": {
    "gn:admin1_code":"72",
    "gn:asciiname":"Kalinin",
    "gn:country_code":"RU",
    "gn:dem":174,
    "gn:feature_class":"P",
    "gn:feature_code":"PPL",
    "gn:name":"Kalinin",
    "gn:population":0,
    "gn:timezone":"Europe/Moscow",
    "iso:country":"RU",
    "name:rus_x_preferred":[
        "\u041a\u0430\u043b\u0438\u043d\u0438\u043d"
    ],
    "name:und_x_variant":[
        "\u041a\u0430\u043b\u0438\u043d\u0438\u043d"
    ],
    "wof:name":"Kalinin",
    "wof:placetype":"locality"
},
  "geometry": {"coordinates":[40.98139000000001,52.835],"type":"Point"}
}