{
  "type": "Feature",
  "properties": {
    "gn:admin1_code":"91",
    "gn:asciiname":"Galanino",
    "gn:country_code":"RU",
    "gn:dem":93,
    "gn:feature_class":"P",
    "gn:feature_code":"PPL",
    "gn:name":"Galanino",
    "gn:population":0,
    "gn:timezone":"Asia/Krasnoyarsk",
    "iso:country":"RU",
    "name:eng_x_preferred":[
        "Galanino"
    ],
    "name:nor_x_preferred":[
        "Galanino"
    ],
    "name:rus_x_preferred":[
        "\u0413\u0430\u043b\u0430\u043d\u0438\u043d\u043e"
    ],
    "wof:name":"Galanino",
    "wof:placetype":"locality"
},
  "geometry": {"coordinates":[93.2747,57.6203],"type":"Point"}
}