{
  "type": "Feature",
  "properties": {
    "gn:admin1_code":"43",
    "gn:asciiname":"Pishchulino",
    "gn:country_code":"RU",
    "gn:dem":200,
    "gn:feature_class":"P",
    "gn:feature_code":"PPL",
    "gn:name":"Pishchulino",
    "gn:population":0,
    "gn:timezone":"Europe/Moscow",
    "iso:country":"RU",
    "name:rus_x_preferred":[
        "\u041f\u0438\u0449\u0443\u043b\u0438\u043d\u043e"
    ],
    "name:und_x_variant":[
        "\u041f\u0438\u0449\u0443\u043b\u0438\u043d\u043e"
    ],
    "wof:name":"Pishchulino",
    "wof:placetype":"locality"
},
  "geometry": {"coordinates":[38.45951,52.68268000000001],"type":"Point"}
}