{
  "type": "Feature",
  "properties": {
    "gn:admin1_code":"67.0",
    "gn:asciiname":"Ravninnyy",
    "gn:country_code":"RU",
    "gn:dem":219,
    "gn:feature_class":"P",
    "gn:feature_code":"PPL",
    "gn:name":"Ravninnyy",
    "gn:population":0,
    "gn:timezone":"Europe/Saratov",
    "iso:country":"RU",
    "name:rus_x_preferred":[
        "\u0420\u0430\u0432\u043d\u0438\u043d\u043d\u044b\u0439"
    ],
    "wof:name":"Ravninnyy",
    "wof:placetype":"locality"
},
  "geometry": {"coordinates":[46.38111,52.41528],"type":"Point"}
}