{
  "type": "Feature",
  "properties": {
    "gn:admin1_code":"77",
    "gn:asciiname":"Otrokovichi",
    "gn:country_code":"RU",
    "gn:dem":135,
    "gn:feature_class":"P",
    "gn:feature_code":"PPL",
    "gn:name":"Otrokovichi",
    "gn:population":0,
    "gn:timezone":"Europe/Moscow",
    "iso:country":"RU",
    "name:rus_x_preferred":[
        "\u041e\u0442\u0440\u043e\u043a\u043e\u0432\u0438\u0447\u0438"
    ],
    "name:und_x_variant":[
        "\u041e\u0442\u0440\u043e\u043a\u043e\u0432\u0438\u0447\u0438"
    ],
    "wof:name":"Otrokovichi",
    "wof:placetype":"locality"
},
  "geometry": {"coordinates":[36.33175,56.75813],"type":"Point"}
}