{
  "type": "Feature",
  "properties": {
    "iso:country":"RU",
    "name:eng_x_variant":[
        "Mozhajskij"
    ],
    "name:rus_x_preferred":[
        "\u041c\u043e\u0436\u0430\u0439\u0441\u043a\u0438\u0439"
    ],
    "name:rus_x_variant":[
        "\u0414\u0443\u0434\u0435\u0440\u0433\u043e\u0301\u0444"
    ],
    "wof:name":"Duderhof",
    "wof:placetype":"neighbourhood"
},
  "geometry": {"coordinates":[30.12022179459068,59.70047186988149],"type":"Point"}
}