{
  "type": "Feature",
  "properties": {
    "gn:admin1_code":"51",
    "gn:asciiname":"Suvadskiy",
    "gn:country_code":"RU",
    "gn:dem":124,
    "gn:feature_class":"P",
    "gn:feature_code":"PPL",
    "gn:name":"Suvadskiy",
    "gn:population":0,
    "gn:timezone":"Europe/Moscow",
    "iso:country":"RU",
    "name:rus_x_preferred":[
        "\u0421\u0443\u0432\u0430\u0434\u0441\u043a\u0438\u0439"
    ],
    "wof:name":"Suvadskiy",
    "wof:placetype":"locality"
},
  "geometry": {"coordinates":[42.0915,55.19],"type":"Point"}
}