{
  "type": "Feature",
  "properties": {
    "gn:admin1_code":"20",
    "gn:asciiname":"Bazhey",
    "gn:country_code":"RU",
    "gn:dem":452,
    "gn:feature_class":"P",
    "gn:feature_code":"PPL",
    "gn:name":"Bazhey",
    "gn:population":0,
    "gn:timezone":"Asia/Irkutsk",
    "iso:country":"RU",
    "name:nor_x_preferred":[
        "Bazjej"
    ],
    "name:rus_x_preferred":[
        "\u0411\u0430\u0436\u0435\u0439"
    ],
    "name:und_x_variant":[
        "Vazhey",
        "Bazhey"
    ],
    "wof:name":"Bazhey",
    "wof:placetype":"locality"
},
  "geometry": {"coordinates":[102.63916999999999,52.97389],"type":"Point"}
}