{
  "type": "Feature",
  "properties": {
    "gn:admin1_code":"47",
    "gn:asciiname":"Ivantsevo",
    "gn:country_code":"RU",
    "gn:dem":147,
    "gn:feature_class":"P",
    "gn:feature_code":"PPL",
    "gn:name":"Ivants\u00ebvo",
    "gn:population":0,
    "gn:timezone":"Europe/Moscow",
    "iso:country":"RU",
    "name:rus_x_preferred":[
        "\u0418\u0432\u0430\u043d\u0446\u0451\u0432\u043e"
    ],
    "name:und_x_variant":[
        "Ivants\u00ebvo",
        "\u0418\u0432\u0430\u043d\u0446\u0451\u0432\u043e"
    ],
    "wof:name":"Ivantsevo",
    "wof:placetype":"locality"
},
  "geometry": {"coordinates":[39.26267,55.53242],"type":"Point"}
}