{
  "type": "Feature",
  "properties": {
    "gn:admin1_code":"21",
    "gn:asciiname":"Redtsyno",
    "gn:country_code":"RU",
    "gn:dem":126,
    "gn:feature_class":"P",
    "gn:feature_code":"PPL",
    "gn:name":"Redtsyno",
    "gn:population":0,
    "gn:timezone":"Europe/Moscow",
    "iso:country":"RU",
    "name:rus_x_preferred":[
        "\u0420\u0435\u0434\u0446\u044b\u043d\u043e"
    ],
    "name:und_x_variant":[
        "Redtsino",
        "Redtsyno"
    ],
    "wof:name":"Redtsyno",
    "wof:placetype":"locality"
},
  "geometry": {"coordinates":[39.90602,56.85946],"type":"Point"}
}