{
  "type": "Feature",
  "properties": {
    "gn:admin1_code":"80.0",
    "gn:asciiname":"Kotomka",
    "gn:country_code":"RU",
    "gn:dem":238,
    "gn:feature_class":"P",
    "gn:feature_code":"PPL",
    "gn:name":"Kotomka",
    "gn:population":0,
    "gn:timezone":"Europe/Samara",
    "iso:country":"RU",
    "name:rus_x_preferred":[
        "\u041a\u043e\u0442\u043e\u043c\u043a\u0430"
    ],
    "wof:name":"Kotomka",
    "wof:placetype":"locality"
},
  "geometry": {"coordinates":[52.5022,57.7236],"type":"Point"}
}