{
  "type": "Feature",
  "properties": {
    "gn:admin1_code":"47",
    "gn:asciiname":"Popovskoye",
    "gn:country_code":"RU",
    "gn:dem":165,
    "gn:feature_class":"P",
    "gn:feature_code":"PPL",
    "gn:name":"Popovskoye",
    "gn:population":12,
    "gn:timezone":"Europe/Moscow",
    "iso:country":"RU",
    "name:rus_x_preferred":[
        "\u041f\u043e\u043f\u043e\u0432\u0441\u043a\u043e\u0435"
    ],
    "name:und_x_variant":[
        "\u041f\u043e\u043f\u043e\u0432\u0441\u043a\u043e\u0435"
    ],
    "wof:name":"Popovskoye",
    "wof:placetype":"locality",
    "wof:population":12
},
  "geometry": {"coordinates":[37.15,56.41667],"type":"Point"}
}