{
  "type": "Feature",
  "properties": {
    "gn:admin1_code":"90",
    "gn:asciiname":"Kekur",
    "gn:country_code":"RU",
    "gn:dem":168,
    "gn:feature_class":"P",
    "gn:feature_code":"PPL",
    "gn:name":"Kekur",
    "gn:population":0,
    "gn:timezone":"Asia/Yekaterinburg",
    "iso:country":"RU",
    "name:rus_x_preferred":[
        "\u041a\u0435\u043a\u0443\u0440"
    ],
    "wof:name":"Kekur",
    "wof:placetype":"locality"
},
  "geometry": {"coordinates":[55.8984,59.5832],"type":"Point"}
}