{
  "type": "Feature",
  "properties": {
    "gn:admin1_code":"51.0",
    "gn:asciiname":"Novaya Puner'",
    "gn:country_code":"RU",
    "gn:dem":132,
    "gn:feature_class":"P",
    "gn:feature_code":"PPL",
    "gn:name":"Novaya Puner\u2019",
    "gn:population":0,
    "gn:timezone":"Europe/Moscow",
    "iso:country":"RU",
    "name:rus_x_preferred":[
        "\u041d\u043e\u0432\u0430\u044f \u041f\u0443\u043d\u0435\u0440\u044c"
    ],
    "name:und_x_variant":[
        "Novaya Puner\u2019"
    ],
    "wof:name":"Novaya Puner'",
    "wof:placetype":"locality"
},
  "geometry": {"coordinates":[44.01215,56.07235],"type":"Point"}
}