{
  "type": "Feature",
  "properties": {
    "gn:admin1_code":"28",
    "gn:asciiname":"Rastilakshi",
    "gn:cc2":"RU",
    "gn:country_code":"RU",
    "gn:dem":189,
    "gn:feature_class":"P",
    "gn:feature_code":"PPL",
    "gn:name":"Rastilakshi",
    "gn:population":0,
    "gn:timezone":"Europe/Moscow",
    "iso:country":"RU",
    "name:fin_x_preferred":[
        "Rastilahti"
    ],
    "name:rus_x_preferred":[
        "\u0420\u0430\u0441\u0442\u0438\u043b\u0430\u043a\u0448\u0438"
    ],
    "name:und_x_variant":[
        "Pos\u00eblok Rastilakshi",
        "Rastilakshi",
        "\u0420\u0430\u0441\u0442\u0438\u043b\u0430\u043a\u0448\u0438"
    ],
    "wof:name":"Rastilakshi",
    "wof:placetype":"locality"
},
  "geometry": {"coordinates":[31.16667,63.98333],"type":"Point"}
}