{
  "type": "Feature",
  "properties": {
    "gn:admin1_code":"32",
    "gn:asciiname":"Tap",
    "gn:country_code":"RU",
    "gn:dem":46,
    "gn:feature_class":"P",
    "gn:feature_code":"PPL",
    "gn:name":"Tap",
    "gn:population":0,
    "gn:timezone":"Asia/Yekaterinburg",
    "iso:country":"RU",
    "name:und_x_variant":[
        "Bol\u2019shoy Tap",
        "Tap"
    ],
    "wof:name":"Tap",
    "wof:placetype":"locality"
},
  "geometry": {"coordinates":[65.76489000000001,59.94848],"type":"Point"}
}