{
  "type": "Feature",
  "properties": {
    "gn:admin1_code":"32",
    "gn:asciiname":"Tap",
    "gn:country_code":"RU",
    "gn:dem":46,
    "gn:feature_class":"P",
    "gn:feature_code":"PPL",
    "gn:name":"Tap",
    "gn:population":0,
    "gn:timezone":"Asia/Yekaterinburg",
    "iso:country":"RU",
    "name:aze_x_preferred":[
        "Tap"
    ],
    "name:cat_x_preferred":[
        "Tap"
    ],
    "name:ceb_x_preferred":[
        "Tap"
    ],
    "name:dan_x_preferred":[
        "Tap"
    ],
    "name:deu_x_preferred":[
        "Tap"
    ],
    "name:kat_x_preferred":[
        "\u10d7\u10d0\u10e4\u10d8"
    ],
    "name:nld_x_preferred":[
        "Tap"
    ],
    "name:pol_x_preferred":[
        "Tap"
    ],
    "name:por_x_preferred":[
        "Tap"
    ],
    "name:swe_x_preferred":[
        "Tap"
    ],
    "name:und_x_variant":[
        "Bol\u2019shoy Tap",
        "Tap"
    ],
    "wof:name":"Tap",
    "wof:placetype":"locality"
},
  "geometry": {"coordinates":[65.76489000000001,59.94848],"type":"Point"}
}