{
  "type": "Feature",
  "properties": {
    "gn:admin1_code":"85",
    "gn:asciiname":"Nizhnekubenskiy",
    "gn:country_code":"RU",
    "gn:dem":166,
    "gn:feature_class":"P",
    "gn:feature_code":"PPL",
    "gn:name":"Nizhnekubenskiy",
    "gn:population":0,
    "gn:timezone":"Europe/Moscow",
    "iso:country":"RU",
    "name:rus_x_preferred":[
        "\u041d\u0438\u0436\u043d\u0435\u043a\u0443\u0431\u0435\u043d\u0441\u043a\u0438\u0439"
    ],
    "wof:name":"Nizhnekubenskiy",
    "wof:placetype":"locality"
},
  "geometry": {"coordinates":[39.9484,59.9725],"type":"Point"}
}