{
  "type": "Feature",
  "properties": {
    "gn:admin1_code":"17.0",
    "gn:asciiname":"Churtakh",
    "gn:country_code":"RU",
    "gn:dem":1996,
    "gn:feature_class":"P",
    "gn:feature_code":"PPL",
    "gn:name":"Churtakh",
    "gn:population":0,
    "gn:timezone":"Europe/Moscow",
    "iso:country":"RU",
    "name:rus_x_preferred":[
        "\u0427\u0443\u0440\u0442\u0430\u0445"
    ],
    "name:und_x_variant":[
        "\u0427\u0443\u0440\u0442\u0430\u0445"
    ],
    "wof:name":"Churtakh",
    "wof:placetype":"locality"
},
  "geometry": {"coordinates":[47.08687000000001,42.11257],"type":"Point"}
}