{
  "type": "Feature",
  "properties": {
    "gn:admin1_code":"49",
    "gn:asciiname":"Slyudyanka",
    "gn:country_code":"RU",
    "gn:dem":135,
    "gn:feature_class":"P",
    "gn:feature_code":"PPL",
    "gn:name":"Slyudyanka",
    "gn:population":0,
    "gn:timezone":"Europe/Moscow",
    "iso:country":"RU",
    "name:rus_x_preferred":[
        "\u0421\u043b\u044e\u0434\u044f\u043d\u043a\u0430"
    ],
    "name:und_x_variant":[
        "Slyudorazrabotki",
        "Slyudyanka",
        "\u0421\u043b\u044e\u0434\u044f\u043d\u043a\u0430"
    ],
    "wof:name":"Slyudyanka",
    "wof:placetype":"locality"
},
  "geometry": {"coordinates":[38.05211,66.7034],"type":"Point"}
}