{
  "type": "Feature",
  "properties": {
    "gn:admin1_code":"41.0",
    "gn:asciiname":"Kauchuk",
    "gn:country_code":"RU",
    "gn:dem":209,
    "gn:feature_class":"P",
    "gn:feature_code":"PPL",
    "gn:name":"Kauchuk",
    "gn:population":0,
    "gn:timezone":"Europe/Moscow",
    "iso:country":"RU",
    "name:msa_x_preferred":[
        "Kauchuk"
    ],
    "name:rus_x_preferred":[
        "\u041a\u0430\u0443\u0447\u0443\u043a"
    ],
    "name:und_x_variant":[
        "\u041a\u0430\u0443\u0447\u0443\u043a"
    ],
    "wof:name":"Kauchuk",
    "wof:placetype":"locality"
},
  "geometry": {"coordinates":[35.19722,51.46639],"type":"Point"}
}