{
  "type": "Feature",
  "properties": {
    "gn:admin1_code":"25",
    "gn:asciiname":"Tarnyy",
    "gn:cc2":"RU",
    "gn:country_code":"RU",
    "gn:dem":214,
    "gn:feature_class":"P",
    "gn:feature_code":"PPL",
    "gn:name":"Tarnyy",
    "gn:population":0,
    "gn:timezone":"Europe/Moscow",
    "iso:country":"RU",
    "name:und_x_variant":[
        "Tarny",
        "Tarnyy"
    ],
    "wof:name":"Tarnyy",
    "wof:placetype":"locality"
},
  "geometry": {"coordinates":[35.36194000000001,53.42194],"type":"Point"}
}