{
  "type": "Feature",
  "properties": {
    "gn:admin1_code":"69",
    "gn:asciiname":"Karacharovo",
    "gn:country_code":"RU",
    "gn:dem":229,
    "gn:feature_class":"P",
    "gn:feature_code":"PPL",
    "gn:name":"Karacharovo",
    "gn:population":0,
    "gn:timezone":"Europe/Moscow",
    "iso:country":"RU",
    "name:rus_x_preferred":[
        "\u041a\u0430\u0440\u0430\u0447\u0430\u0440\u043e\u0432\u043e"
    ],
    "wof:name":"Karacharovo",
    "wof:placetype":"locality"
},
  "geometry": {"coordinates":[33.49082,55.02634000000001],"type":"Point"}
}