{
  "type": "Feature",
  "properties": {
    "gn:admin1_code":"33",
    "gn:asciiname":"Annenskaya",
    "gn:country_code":"RU",
    "gn:dem":97,
    "gn:feature_class":"P",
    "gn:feature_code":"PPL",
    "gn:name":"Annenskaya",
    "gn:population":0,
    "gn:timezone":"Europe/Kirov",
    "iso:country":"RU",
    "name:nor_x_preferred":[
        "Annenskaja"
    ],
    "name:rus_x_preferred":[
        "\u0410\u043d\u043d\u0435\u043d\u0441\u043a\u0430\u044f"
    ],
    "wof:name":"Annenskaya",
    "wof:placetype":"locality"
},
  "geometry": {"coordinates":[47.13299,56.97563],"type":"Point"}
}