{
  "type": "Feature",
  "properties": {
    "gn:admin1_code":"33.0",
    "gn:asciiname":"Ozhegovy",
    "gn:country_code":"RU",
    "gn:dem":179,
    "gn:feature_class":"P",
    "gn:feature_code":"PPL",
    "gn:name":"Ozhegovy",
    "gn:population":0,
    "gn:timezone":"Europe/Kirov",
    "iso:country":"RU",
    "name:rus_x_preferred":[
        "\u041e\u0436\u0435\u0433\u043e\u0432\u044b"
    ],
    "name:und_x_variant":[
        "\u041e\u0436\u0435\u0433\u043e\u0432\u044b"
    ],
    "wof:name":"Ozhegovy",
    "wof:placetype":"locality"
},
  "geometry": {"coordinates":[48.02696,58.9216],"type":"Point"}
}