{
  "type": "Feature",
  "properties": {
    "gn:admin1_code":"77",
    "gn:asciiname":"Khlebniki",
    "gn:country_code":"RU",
    "gn:dem":303,
    "gn:feature_class":"P",
    "gn:feature_code":"PPL",
    "gn:name":"Khlebniki",
    "gn:population":0,
    "gn:timezone":"Europe/Moscow",
    "iso:country":"RU",
    "name:rus_x_preferred":[
        "\u0425\u043b\u0435\u0431\u043d\u0438\u043a\u0438"
    ],
    "name:und_x_variant":[
        "\u0425\u043b\u0435\u0431\u043d\u0438\u043a\u0438"
    ],
    "wof:name":"Khlebniki",
    "wof:placetype":"locality"
},
  "geometry": {"coordinates":[33.58238,56.27293],"type":"Point"}
}