{
  "type": "Feature",
  "properties": {
    "gn:admin1_code":"69",
    "gn:asciiname":"Devyatkino",
    "gn:country_code":"RU",
    "gn:dem":214,
    "gn:feature_class":"P",
    "gn:feature_code":"PPL",
    "gn:name":"Devyatkino",
    "gn:population":0,
    "gn:timezone":"Europe/Moscow",
    "iso:country":"RU",
    "name:rus_x_preferred":[
        "\u0414\u0435\u0432\u044f\u0442\u043a\u0438\u043d\u043e"
    ],
    "name:und_x_variant":[
        "\u0414\u0435\u0432\u044f\u0442\u043a\u0438\u043d\u043e"
    ],
    "wof:name":"Devyatkino",
    "wof:placetype":"locality"
},
  "geometry": {"coordinates":[34.80407,55.25312],"type":"Point"}
}