{
  "type": "Feature",
  "properties": {
    "gn:admin1_code":"37.0",
    "gn:asciiname":"Yuzhaki",
    "gn:country_code":"RU",
    "gn:dem":164,
    "gn:feature_class":"P",
    "gn:feature_code":"PPL",
    "gn:name":"Yuzhaki",
    "gn:population":0,
    "gn:timezone":"Europe/Moscow",
    "iso:country":"RU",
    "name:rus_x_preferred":[
        "\u042e\u0436\u0430\u043a\u0438"
    ],
    "name:und_x_variant":[
        "Bol\u2019shoye Yuzhakovo"
    ],
    "wof:name":"Yuzhaki",
    "wof:placetype":"locality"
},
  "geometry": {"coordinates":[47.23181,58.82532],"type":"Point"}
}