{
  "type": "Feature",
  "properties": {
    "gn:admin1_code":"25",
    "gn:asciiname":"Pyshkovo",
    "gn:country_code":"RU",
    "gn:dem":191,
    "gn:feature_class":"P",
    "gn:feature_code":"PPL",
    "gn:name":"Pyshkovo",
    "gn:population":0,
    "gn:timezone":"Europe/Moscow",
    "iso:country":"RU",
    "name:nor_x_preferred":[
        "Pysjkovo"
    ],
    "name:rus_x_preferred":[
        "\u041f\u044b\u0448\u043a\u043e\u0432\u043e"
    ],
    "wof:name":"Pyshkovo",
    "wof:placetype":"locality"
},
  "geometry": {"coordinates":[36.68871,54.48622],"type":"Point"}
}