{
  "type": "Feature",
  "properties": {
    "gn:admin1_code":"62",
    "gn:asciiname":"Poselok Otkormkhoza",
    "gn:country_code":"RU",
    "gn:dem":97,
    "gn:feature_class":"P",
    "gn:feature_code":"PPL",
    "gn:name":"Pos\u00eblok Otkormkhoza",
    "gn:population":0,
    "gn:timezone":"Europe/Moscow",
    "iso:country":"RU",
    "name:rus_x_preferred":[
        "\u041f\u043e\u0441\u00eb\u043b\u043e\u043a \u041e\u0442\u043a\u043e\u0440\u043c\u0445\u043e\u0437\u0430"
    ],
    "name:und_x_variant":[
        "Pos\u00eblok Otkormkhoza"
    ],
    "wof:name":"Poselok Otkormkhoza",
    "wof:placetype":"locality"
},
  "geometry": {"coordinates":[40.2576,54.3058],"type":"Point"}
}