{
  "type": "Feature",
  "properties": {
    "gn:admin1_code":"85",
    "gn:asciiname":"Petryayeva Gorka",
    "gn:country_code":"RU",
    "gn:dem":155,
    "gn:feature_class":"P",
    "gn:feature_code":"PPL",
    "gn:name":"Petryayeva Gorka",
    "gn:population":0,
    "gn:timezone":"Europe/Moscow",
    "iso:country":"RU",
    "name:rus_x_preferred":[
        "\u041f\u0435\u0442\u0440\u044f\u0435\u0432\u0430 \u0413\u043e\u0440\u043a\u0430"
    ],
    "name:und_x_variant":[
        "Gorka",
        "Petryayeva Gorka"
    ],
    "wof:name":"Petryayeva Gorka",
    "wof:placetype":"locality"
},
  "geometry": {"coordinates":[37.24724000000001,59.91603000000001],"type":"Point"}
}