{
  "type": "Feature",
  "properties": {
    "gn:admin1_code":"56",
    "gn:asciiname":"Vyshnyaya Zamarayka Vtoraya",
    "gn:country_code":"RU",
    "gn:dem":206,
    "gn:feature_class":"P",
    "gn:feature_code":"PPL",
    "gn:name":"Vyshnyaya Zamarayka Vtoraya",
    "gn:population":0,
    "gn:timezone":"Europe/Moscow",
    "iso:country":"RU",
    "name:und_x_variant":[
        "Zamarayka",
        "Zamaraika",
        "Vyshnyaya Zamarayka Vtoraya"
    ],
    "wof:name":"Vyshnyaya Zamarayka Vtoraya",
    "wof:placetype":"locality"
},
  "geometry": {"coordinates":[37.2607,52.06676],"type":"Point"}
}