{
  "type": "Feature",
  "properties": {
    "gn:admin1_code":"64",
    "gn:asciiname":"Polovinka",
    "gn:country_code":"RU",
    "gn:dem":51,
    "gn:feature_class":"P",
    "gn:feature_code":"PPL",
    "gn:name":"Polovinka",
    "gn:population":0,
    "gn:timezone":"Asia/Sakhalin",
    "iso:country":"RU",
    "name:eng_x_preferred":[
        "Polovinka"
    ],
    "name:nor_x_preferred":[
        "Polovinka"
    ],
    "name:rus_x_preferred":[
        "\u041f\u043e\u043b\u043e\u0432\u0438\u043d\u043a\u0430"
    ],
    "wof:name":"Polovinka",
    "wof:placetype":"locality"
},
  "geometry": {"coordinates":[142.19999999999999,50.95],"type":"Point"}
}