{
  "type": "Feature",
  "properties": {
    "gn:admin1_code":"72",
    "gn:asciiname":"Tyumenevskiy Pervyy",
    "gn:country_code":"RU",
    "gn:dem":172,
    "gn:feature_class":"P",
    "gn:feature_code":"PPL",
    "gn:name":"Tyumenevskiy Pervyy",
    "gn:population":0,
    "gn:timezone":"Europe/Moscow",
    "iso:country":"RU",
    "name:und_x_variant":[
        "Tyumenevskiye Vyselki",
        "Tyumenevskiy Pervyy"
    ],
    "wof:name":"Tyumenevskiy Pervyy",
    "wof:placetype":"locality"
},
  "geometry": {"coordinates":[41.05395,52.38576],"type":"Point"}
}