{
  "type": "Feature",
  "properties": {
    "gn:admin1_code":"65",
    "gn:asciiname":"Kokhany",
    "gn:country_code":"RU",
    "gn:dem":101,
    "gn:feature_class":"P",
    "gn:feature_code":"PPL",
    "gn:name":"Kokhany",
    "gn:population":0,
    "gn:timezone":"Europe/Samara",
    "iso:country":"RU",
    "name:eng_x_preferred":[
        "Kokhany"
    ],
    "name:nor_x_preferred":[
        "Kokhany"
    ],
    "name:rus_x_preferred":[
        "\u041a\u043e\u0445\u0430\u043d\u044b"
    ],
    "name:und_x_variant":[
        "\u041a\u043e\u0445\u0430\u043d\u044b",
        "Kokhany"
    ],
    "wof:name":"Kokhany",
    "wof:placetype":"locality"
},
  "geometry": {"coordinates":[51.68515,53.3115],"type":"Point"}
}