{
  "type": "Feature",
  "properties": {
    "gn:admin1_code":"51.0",
    "gn:asciiname":"Chashchikha",
    "gn:country_code":"RU",
    "gn:dem":140,
    "gn:feature_class":"P",
    "gn:feature_code":"PPL",
    "gn:name":"Chashchikha",
    "gn:population":0,
    "gn:timezone":"Europe/Moscow",
    "iso:country":"RU",
    "name:eng_x_preferred":[
        "Chashchikha"
    ],
    "name:nor_x_preferred":[
        "Tsjasjtsjikha"
    ],
    "name:rus_x_preferred":[
        "\u0427\u0430\u0449\u0438\u0445\u0430"
    ],
    "wof:name":"Chashchikha",
    "wof:placetype":"locality"
},
  "geometry": {"coordinates":[45.15187,57.10623],"type":"Point"}
}