{
  "type": "Feature",
  "properties": {
    "gn:admin1_code":"80.0",
    "gn:asciiname":"Staryye Marasany",
    "gn:country_code":"RU",
    "gn:dem":153,
    "gn:feature_class":"P",
    "gn:feature_code":"PPL",
    "gn:name":"Staryye Marasany",
    "gn:population":0,
    "gn:timezone":"Europe/Samara",
    "iso:country":"RU",
    "wof:name":"Staryye Marasany",
    "wof:placetype":"locality"
},
  "geometry": {"coordinates":[53.40136,56.92142],"type":"Point"}
}