{
  "type": "Feature",
  "properties": {
    "gn:admin1_code":"77",
    "gn:asciiname":"Korotnya",
    "gn:country_code":"RU",
    "gn:dem":267,
    "gn:feature_class":"P",
    "gn:feature_code":"PPL",
    "gn:name":"Korotnya",
    "gn:population":0,
    "gn:timezone":"Europe/Moscow",
    "iso:country":"RU",
    "name:rus_x_preferred":[
        "\u041a\u043e\u0440\u043e\u0442\u043d\u044f"
    ],
    "name:und_x_variant":[
        "\u041a\u043e\u0440\u043e\u0442\u043d\u044f"
    ],
    "wof:name":"Korotnya",
    "wof:placetype":"locality"
},
  "geometry": {"coordinates":[33.39896,56.10972],"type":"Point"}
}