{
  "type": "Feature",
  "properties": {
    "gn:admin1_code":"1",
    "gn:asciiname":"Tauykhabl'",
    "gn:country_code":"RU",
    "gn:dem":44,
    "gn:feature_class":"P",
    "gn:feature_code":"PPL",
    "gn:name":"Tauykhabl\u2019",
    "gn:population":0,
    "gn:timezone":"Europe/Moscow",
    "iso:country":"RU",
    "name:und_x_variant":[
        "Taukykhabl\u2019",
        "Tauykhabl\u2019"
    ],
    "wof:name":"Tauykhabl'",
    "wof:placetype":"locality"
},
  "geometry": {"coordinates":[39.36874,44.96435],"type":"Point"}
}