{
  "type": "Feature",
  "properties": {
    "gn:admin1_code":"71",
    "gn:asciiname":"Severnaya Chernushka",
    "gn:country_code":"RU",
    "gn:dem":99,
    "gn:feature_class":"P",
    "gn:feature_code":"PPL",
    "gn:name":"Severnaya Chernushka",
    "gn:population":0,
    "gn:timezone":"Asia/Yekaterinburg",
    "iso:country":"RU",
    "name:eng_x_preferred":[
        "Severnaya Chernushka"
    ],
    "name:nor_x_preferred":[
        "Sev.Tsjernusjka"
    ],
    "name:rus_x_preferred":[
        "\u0421\u0435\u0432.\u0427\u0435\u0440\u043d\u0443\u0448\u043a\u0430"
    ],
    "name:rus_x_variant":[
        "\u0421\u0435\u0432\u0435\u0440\u043d\u0430\u044f \u0427\u0435\u0440\u043d\u0443\u0448\u043a\u0430"
    ],
    "name:und_x_variant":[
        "Chernushka"
    ],
    "wof:name":"Severnaya Chernushka",
    "wof:placetype":"locality"
},
  "geometry": {"coordinates":[64.69673,58.10219],"type":"Point"}
}