{
  "type": "Feature",
  "properties": {
    "gn:admin1_code":"41",
    "gn:asciiname":"Pokrovskiy",
    "gn:country_code":"RU",
    "gn:dem":149,
    "gn:feature_class":"P",
    "gn:feature_code":"PPL",
    "gn:name":"Pokrovskiy",
    "gn:population":0,
    "gn:timezone":"Europe/Moscow",
    "iso:country":"RU",
    "name:rus_x_preferred":[
        "\u041f\u043e\u043a\u0440\u043e\u0432\u0441\u043a\u0438\u0439"
    ],
    "wof:name":"Pokrovskiy",
    "wof:placetype":"locality"
},
  "geometry": {"coordinates":[35.0117,51.2848],"type":"Point"}
}