{
  "type": "Feature",
  "properties": {
    "gn:admin1_code":"45.0",
    "gn:asciiname":"Miklino",
    "gn:country_code":"RU",
    "gn:dem":132,
    "gn:feature_class":"P",
    "gn:feature_code":"PPL",
    "gn:name":"Miklino",
    "gn:population":0,
    "gn:timezone":"Europe/Moscow",
    "iso:country":"RU",
    "name:rus_x_preferred":[
        "\u041c\u0438\u043a\u043b\u0438\u043d\u043e"
    ],
    "name:und_x_variant":[
        "\u041c\u0438\u043a\u043b\u0438\u043d\u043e"
    ],
    "wof:name":"Miklino",
    "wof:placetype":"locality"
},
  "geometry": {"coordinates":[49.28472,56.3475],"type":"Point"}
}