{
  "type": "Feature",
  "properties": {
    "gn:admin1_code":"76.0",
    "gn:asciiname":"Davydovskoye",
    "gn:country_code":"RU",
    "gn:dem":193,
    "gn:feature_class":"P",
    "gn:feature_code":"PPL",
    "gn:name":"Davydovskoye",
    "gn:population":0,
    "gn:timezone":"Europe/Moscow",
    "iso:country":"RU",
    "name:rus_x_preferred":[
        "\u0414\u0430\u0432\u044b\u0434\u043e\u0432\u0441\u043a\u043e\u0435"
    ],
    "wof:name":"Davydovskoye",
    "wof:placetype":"locality"
},
  "geometry": {"coordinates":[37.55774,54.52309],"type":"Point"}
}