{
  "type": "Feature",
  "properties": {
    "gn:admin1_code":"72.0",
    "gn:asciiname":"Engurazovo",
    "gn:country_code":"RU",
    "gn:dem":176,
    "gn:feature_class":"P",
    "gn:feature_code":"PPL",
    "gn:name":"Engurazovo",
    "gn:population":0,
    "gn:timezone":"Europe/Moscow",
    "iso:country":"RU",
    "name:rus_x_preferred":[
        "\u042d\u043d\u0433\u0443\u0440\u0430\u0437\u043e\u0432\u043e"
    ],
    "name:und_x_variant":[
        "\u042d\u043d\u0433\u0443\u0440\u0430\u0437\u043e\u0432\u043e"
    ],
    "wof:name":"Engurazovo",
    "wof:placetype":"locality"
},
  "geometry": {"coordinates":[41.96305,51.84036],"type":"Point"}
}