{
  "type": "Feature",
  "properties": {
    "gn:admin1_code":"05",
    "gn:asciiname":"Kalinovka",
    "gn:country_code":"RU",
    "gn:dem":130,
    "gn:feature_class":"P",
    "gn:feature_code":"PPL",
    "gn:name":"Kalinovka",
    "gn:population":0,
    "gn:timezone":"Asia/Yakutsk",
    "iso:country":"RU",
    "name:bel_x_preferred":[
        "\u041a\u0430\u043b\u0456\u043d\u0430\u045e\u043a\u0430"
    ],
    "name:ceb_x_preferred":[
        "Kalinovka"
    ],
    "name:fra_x_preferred":[
        "Kalinovka"
    ],
    "name:kaz_x_preferred":[
        "\u041a\u0430\u043b\u0438\u043d\u043e\u0432\u043a\u0430"
    ],
    "name:lit_x_preferred":[
        "Kalinovka"
    ],
    "name:rus_x_preferred":[
        "\u041a\u0430\u043b\u0438\u043d\u043e\u0432\u043a\u0430"
    ],
    "name:sco_x_preferred":[
        "Kalinovka"
    ],
    "name:spa_x_preferred":[
        "Kalinovka"
    ],
    "name:swe_x_preferred":[
        "Kalinovka"
    ],
    "name:ukr_x_preferred":[
        "\u041a\u0430\u043b\u0438\u043d\u043e\u0432\u043a\u0430"
    ],
    "name:und_x_variant":[
        "\u041a\u0430\u043b\u0438\u043d\u043e\u0432\u043a\u0430"
    ],
    "wof:name":"Kalinovka",
    "wof:placetype":"locality"
},
  "geometry": {"coordinates":[130.44999999999999,49.21667],"type":"Point"}
}