{
  "type": "Feature",
  "properties": {
    "gn:admin1_code":"37",
    "gn:asciiname":"Ugol'skoye",
    "gn:country_code":"RU",
    "gn:dem":110,
    "gn:feature_class":"P",
    "gn:feature_code":"PPL",
    "gn:name":"Ugol\u2019skoye",
    "gn:population":0,
    "gn:timezone":"Europe/Moscow",
    "iso:country":"RU",
    "name:und_x_variant":[
        "Ugol\u2019skaya",
        "Ugol\u2019skoye"
    ],
    "wof:name":"Ugol'skoye",
    "wof:placetype":"locality"
},
  "geometry": {"coordinates":[41.47648,58.5111],"type":"Point"}
}