{
  "type": "Feature",
  "properties": {
    "gn:admin1_code":"47",
    "gn:asciiname":"Podberezniki",
    "gn:country_code":"RU",
    "gn:dem":152,
    "gn:feature_class":"P",
    "gn:feature_code":"PPL",
    "gn:name":"Podberezniki",
    "gn:population":0,
    "gn:timezone":"Europe/Moscow",
    "iso:country":"RU",
    "name:rus_x_preferred":[
        "\u041f\u043e\u0434\u0431\u0435\u0440\u0435\u0437\u043d\u0438\u043a\u0438"
    ],
    "wof:name":"Podberezniki",
    "wof:placetype":"locality"
},
  "geometry": {"coordinates":[38.48794,55.13036999999999],"type":"Point"}
}