{
  "type": "Feature",
  "properties": {
    "gn:admin1_code":"37.0",
    "gn:asciiname":"Barinovo",
    "gn:country_code":"RU",
    "gn:dem":151,
    "gn:feature_class":"P",
    "gn:feature_code":"PPL",
    "gn:name":"Barinovo",
    "gn:population":0,
    "gn:timezone":"Europe/Moscow",
    "iso:country":"RU",
    "name:nor_x_preferred":[
        "Barinovo"
    ],
    "name:rus_x_preferred":[
        "\u0411\u0430\u0440\u0438\u043d\u043e\u0432\u043e"
    ],
    "wof:name":"Barinovo",
    "wof:placetype":"locality"
},
  "geometry": {"coordinates":[42.99649,58.76824000000001],"type":"Point"}
}