{
  "type": "Feature",
  "properties": {
    "gn:admin1_code":"13",
    "gn:asciiname":"Staraya Arsha",
    "gn:country_code":"RU",
    "gn:dem":343,
    "gn:feature_class":"P",
    "gn:feature_code":"PPL",
    "gn:name":"Staraya Arsha",
    "gn:population":0,
    "gn:timezone":"Asia/Yekaterinburg",
    "iso:country":"RU",
    "name:rus_x_preferred":[
        "\u0421\u0442\u0430\u0440\u0430\u044f \u0410\u0440\u0448\u0430"
    ],
    "name:und_x_variant":[
        "\u0421\u0442\u0430\u0440\u0430\u044f \u0410\u0440\u0448\u0430"
    ],
    "wof:name":"Staraya Arsha",
    "wof:placetype":"locality"
},
  "geometry": {"coordinates":[59.34389,55.38111],"type":"Point"}
}