{
  "type": "Feature",
  "properties": {
    "gn:admin1_code":"6.0",
    "gn:asciiname":"Bukobory",
    "gn:country_code":"RU",
    "gn:dem":21,
    "gn:feature_class":"P",
    "gn:feature_code":"PPL",
    "gn:name":"Bukobory",
    "gn:population":0,
    "gn:timezone":"Europe/Moscow",
    "iso:country":"RU",
    "name:eng_x_preferred":[
        "Bukobory"
    ],
    "name:nor_x_preferred":[
        "Bukobory"
    ],
    "name:rus_x_preferred":[
        "\u0411\u0443\u043a\u043e\u0431\u043e\u0440\u044b"
    ],
    "wof:name":"Bukobory",
    "wof:placetype":"locality"
},
  "geometry": {"coordinates":[38.88951,63.57971],"type":"Point"}
}