{
  "type": "Feature",
  "properties": {
    "gn:admin1_code":"69",
    "gn:asciiname":"Krasnoye Znamya",
    "gn:country_code":"RU",
    "gn:dem":182,
    "gn:feature_class":"P",
    "gn:feature_code":"PPL",
    "gn:name":"Krasnoye Znamya",
    "gn:population":0,
    "gn:timezone":"Europe/Moscow",
    "iso:country":"RU",
    "name:eng_x_preferred":[
        "Krasnoye Znamya"
    ],
    "name:nor_x_preferred":[
        "Krasnoje-Znamja"
    ],
    "name:rus_x_preferred":[
        "\u041a\u0440\u0430\u0441\u043d\u043e\u0435-\u0417\u043d\u0430\u043c\u044f"
    ],
    "name:rus_x_variant":[
        "\u041a\u0440\u0430\u0441\u043d\u043e\u0435 \u0417\u043d\u0430\u043c\u044f"
    ],
    "wof:name":"Krasnoye Znamya",
    "wof:placetype":"locality"
},
  "geometry": {"coordinates":[32.53551,54.12286999999999],"type":"Point"}
}