{
  "type": "Feature",
  "properties": {
    "gn:admin1_code":"20",
    "gn:asciiname":"Zakhal",
    "gn:country_code":"RU",
    "gn:dem":529,
    "gn:feature_class":"P",
    "gn:feature_code":"PPL",
    "gn:name":"Zakhal",
    "gn:population":0,
    "gn:timezone":"Asia/Irkutsk",
    "iso:country":"RU",
    "name:eng_x_preferred":[
        "Zakhal"
    ],
    "name:nor_x_preferred":[
        "Zakhal"
    ],
    "name:rus_x_preferred":[
        "\u0417\u0430\u0445\u0430\u043b"
    ],
    "wof:name":"Zakhal",
    "wof:placetype":"locality"
},
  "geometry": {"coordinates":[104.73375,52.60227],"type":"Point"}
}