{
  "type": "Feature",
  "properties": {
    "gn:admin1_code":"9.0",
    "gn:asciiname":"Gubkin",
    "gn:country_code":"RU",
    "gn:dem":178,
    "gn:feature_class":"P",
    "gn:feature_code":"PPL",
    "gn:name":"Gubkin",
    "gn:population":0,
    "gn:timezone":"Europe/Moscow",
    "iso:country":"RU",
    "name:rus_x_preferred":[
        "\u0413\u0443\u0431\u043a\u0438\u043d"
    ],
    "name:und_x_variant":[
        "\u0413\u0443\u0431\u043a\u0438\u043d"
    ],
    "wof:name":"Gubkin",
    "wof:placetype":"locality"
},
  "geometry": {"coordinates":[36.54667,51.09056],"type":"Point"}
}