{
  "type": "Feature",
  "properties": {
    "gn:admin1_code":"9.0",
    "gn:asciiname":"Gubkin",
    "gn:country_code":"RU",
    "gn:dem":178,
    "gn:feature_class":"P",
    "gn:feature_code":"PPL",
    "gn:name":"Gubkin",
    "gn:population":0,
    "gn:timezone":"Europe/Moscow",
    "iso:country":"RU",
    "name:ara_x_preferred":[
        "\u063a\u0648\u0628\u0643\u064a\u0646"
    ],
    "name:azb_x_preferred":[
        "\u0642\u0648\u0628\u06a9\u06cc\u0646"
    ],
    "name:aze_x_preferred":[
        "Qubkin"
    ],
    "name:bel_x_preferred":[
        "\u0413\u0443\u0431\u043a\u0456\u043d"
    ],
    "name:bul_x_preferred":[
        "\u0413\u0443\u0431\u043a\u0438\u043d"
    ],
    "name:cat_x_preferred":[
        "Gubkin"
    ],
    "name:ceb_x_preferred":[
        "Gubkin"
    ],
    "name:ces_x_preferred":[
        "Gubkin"
    ],
    "name:deu_x_preferred":[
        "Gubkin"
    ],
    "name:epo_x_preferred":[
        "Gubkin"
    ],
    "name:est_x_preferred":[
        "Gubkin"
    ],
    "name:fas_x_preferred":[
        "\u06af\u0648\u0628\u06a9\u06cc\u0646"
    ],
    "name:fin_x_preferred":[
        "Gubkin"
    ],
    "name:fra_x_preferred":[
        "Goubkine"
    ],
    "name:hrv_x_preferred":[
        "Gubkin"
    ],
    "name:hsb_x_preferred":[
        "Gubkin"
    ],
    "name:ita_x_preferred":[
        "Gubkin"
    ],
    "name:lit_x_preferred":[
        "Gubkinas"
    ],
    "name:nno_x_preferred":[
        "Gubkin"
    ],
    "name:nor_x_preferred":[
        "Gubkin"
    ],
    "name:pnb_x_preferred":[
        "\u06af\u0648\u0628\u0646\u06a9"
    ],
    "name:pol_x_preferred":[
        "Gubkin"
    ],
    "name:ron_x_preferred":[
        "Gubkin"
    ],
    "name:rus_x_preferred":[
        "\u0413\u0443\u0431\u043a\u0438\u043d"
    ],
    "name:srp_x_preferred":[
        "\u0413\u0443\u043f\u043a\u0438\u043d"
    ],
    "name:swe_x_preferred":[
        "Gubkin"
    ],
    "name:tat_x_preferred":[
        "\u0413\u0443\u0431\u043a\u0438\u043d"
    ],
    "name:tgk_x_preferred":[
        "\u0413\u0443\u0431\u043a\u0438\u043d"
    ],
    "name:tgl_x_preferred":[
        "Gubkin"
    ],
    "name:tur_x_preferred":[
        "Gubkin"
    ],
    "name:ukr_x_preferred":[
        "\u0413\u0443\u0431\u043a\u0456\u043d"
    ],
    "name:und_x_variant":[
        "\u0413\u0443\u0431\u043a\u0438\u043d"
    ],
    "name:vep_x_preferred":[
        "Gubkin"
    ],
    "name:vie_x_preferred":[
        "Gubkin"
    ],
    "name:war_x_preferred":[
        "Gubkin"
    ],
    "name:zho_x_preferred":[
        "\u53e4\u5e03\u91d1"
    ],
    "wof:name":"Gubkin",
    "wof:placetype":"locality"
},
  "geometry": {"coordinates":[36.54667,51.09056],"type":"Point"}
}