{
  "type": "Feature",
  "properties": {
    "gn:admin1_code":"21",
    "gn:asciiname":"Krenevo",
    "gn:country_code":"RU",
    "gn:dem":136,
    "gn:feature_class":"P",
    "gn:feature_code":"PPL",
    "gn:name":"Kren\u00ebvo",
    "gn:population":0,
    "gn:timezone":"Europe/Moscow",
    "iso:country":"RU",
    "name:rus_x_preferred":[
        "\u041a\u0440\u0435\u043d\u0451\u0432\u043e"
    ],
    "name:und_x_variant":[
        "Kreneva",
        "Kren\u00ebvo"
    ],
    "wof:name":"Krenevo",
    "wof:placetype":"locality"
},
  "geometry": {"coordinates":[41.39076,57.41577],"type":"Point"}
}