{
  "type": "Feature",
  "properties": {
    "gn:admin1_code":"77",
    "gn:asciiname":"Polibino",
    "gn:country_code":"RU",
    "gn:dem":214,
    "gn:feature_class":"P",
    "gn:feature_code":"PPL",
    "gn:name":"Polibino",
    "gn:population":0,
    "gn:timezone":"Europe/Moscow",
    "iso:country":"RU",
    "name:rus_x_preferred":[
        "\u041f\u043e\u043b\u0438\u0431\u0438\u043d\u043e"
    ],
    "name:und_x_variant":[
        "\u041f\u043e\u043b\u0438\u0431\u0438\u043d\u043e"
    ],
    "wof:name":"Polibino",
    "wof:placetype":"locality"
},
  "geometry": {"coordinates":[31.4362,56.48863000000001],"type":"Point"}
}