{
  "type": "Feature",
  "properties": {
    "gn:country":"RU",
    "gn:fcode":"PPL",
    "gn:pop":1253,
    "iso:country":"RU",
    "name:eng_x_preferred":[
        "Bernovo"
    ],
    "name:nor_x_preferred":[
        "Bernovo"
    ],
    "name:rus_x_preferred":[
        "\u0411\u0435\u0440\u043d\u043e\u0432\u043e"
    ],
    "name:unk_x_variant":[
        "\u0411\u0435\u0440\u043d\u043e\u0432\u043e"
    ],
    "qs:name":"Bernovo",
    "qs:name_adm0":"Russia",
    "qs:name_adm1":"Tver Oblast",
    "qs:photos_9k":1,
    "qs:photos_9r":2,
    "qs:photos_all":32,
    "qs:photos_sr":0,
    "qs:placetype":"Town",
    "qs:pop_sr":"3",
    "wd:wordcount":1923,
    "wof:name":"Bernovo",
    "wof:placetype":"locality",
    "wof:population":1253
},
  "geometry": {"coordinates":[34.70357,56.68633],"type":"Point"}
}