{
  "type": "Feature",
  "properties": {
    "gn:country":"RU",
    "gn:fcode":"PPL",
    "gn:population":1253,
    "iso:country":"RU",
    "name:bel_x_preferred":[
        "\u0421\u0442\u0430\u0440\u044b\u0446\u043a\u0456 \u0440\u0430\u0451\u043d"
    ],
    "name:ceb_x_preferred":[
        "Staritskiy Rayon"
    ],
    "name:che_x_preferred":[
        "\u0421\u0442\u0430\u0440\u0438\u0446\u0430\u043d \u043a\u04c0\u043e\u0448\u0442"
    ],
    "name:chv_x_preferred":[
        "\u0421\u0442\u0430\u0440\u0438\u0446\u0430 \u0440\u0430\u0439\u043e\u043d\u0115"
    ],
    "name:deu_x_preferred":[
        "Starizki rajon"
    ],
    "name:eng_x_preferred":[
        "Bernovo"
    ],
    "name:eng_x_variant":[
        "Staritsky District"
    ],
    "name:est_x_preferred":[
        "Staritsa rajoon"
    ],
    "name:fin_x_preferred":[
        "Staritsan piiri"
    ],
    "name:hun_x_preferred":[
        "Sztaricai j\u00e1r\u00e1s"
    ],
    "name:hye_x_preferred":[
        "\u054d\u057f\u0561\u0580\u056b\u0581\u056f\u056b \u0577\u0580\u057b\u0561\u0576"
    ],
    "name:ita_x_preferred":[
        "Starickij rajon"
    ],
    "name:jpn_x_preferred":[
        "\u30b9\u30bf\u30fc\u30ea\u30c4\u30ad\u30fc\u5730\u533a"
    ],
    "name:nan_x_preferred":[
        "Staritsky Ko\u0101n"
    ],
    "name:nld_x_preferred":[
        "Staritskiy rayon"
    ],
    "name:nor_x_preferred":[
        "Bernovo"
    ],
    "name:rus_x_preferred":[
        "\u0411\u0435\u0440\u043d\u043e\u0432\u043e"
    ],
    "name:rus_x_variant":[
        "\u0421\u0442\u0430\u0440\u0438\u0446\u043a\u0438\u0439 \u0440\u0430\u0439\u043e\u043d"
    ],
    "name:srp_x_preferred":[
        "\u0421\u0442\u0430\u0440\u0438\u0447\u043a\u0438 \u0440\u0435\u0458\u043e\u043d"
    ],
    "name:tat_x_preferred":[
        "\u0421\u0442\u0430\u0440\u0438\u0446\u0430 \u0440\u0430\u0439\u043e\u043d\u044b"
    ],
    "name:ukr_x_preferred":[
        "\u0421\u0442\u0430\u0440\u0438\u0446\u044c\u043a\u0438\u0439 \u0440\u0430\u0439\u043e\u043d"
    ],
    "name:vie_x_preferred":[
        "Staritsky"
    ],
    "name:zho_x_preferred":[
        "\u65af\u5854\u91cc\u8328\u57fa\u5340"
    ],
    "qs:name":"Bernovo",
    "qs:name_adm0":"Russia",
    "qs:name_adm1":"Tver Oblast",
    "qs:photos_9k":1,
    "qs:photos_9r":2,
    "qs:photos_all":32,
    "qs:photos_sr":0,
    "qs:placetype":"Town",
    "qs:pop_sr":"3",
    "wd:wordcount":1923,
    "wof:name":"Bernovo",
    "wof:placetype":"locality",
    "wof:population":1253
},
  "geometry": {"coordinates":[34.70357,56.68633],"type":"Point"}
}