{
  "type": "Feature",
  "properties": {
    "gn:admin1_code":"88",
    "gn:asciiname":"Shchekotovo",
    "gn:country_code":"RU",
    "gn:dem":161,
    "gn:feature_class":"P",
    "gn:feature_code":"PPL",
    "gn:name":"Shch\u00ebkotovo",
    "gn:population":0,
    "gn:timezone":"Europe/Moscow",
    "iso:country":"RU",
    "name:rus_x_preferred":[
        "\u0429\u0451\u043a\u043e\u0442\u043e\u0432\u043e"
    ],
    "name:und_x_variant":[
        "Shch\u00ebkotovo"
    ],
    "wof:name":"Shchekotovo",
    "wof:placetype":"locality"
},
  "geometry": {"coordinates":[39.58165,57.47234],"type":"Point"}
}