{
  "type": "Feature",
  "properties": {
    "gn:admin1_code":"52",
    "gn:asciiname":"Malyye Berezitsy",
    "gn:country_code":"RU",
    "gn:dem":55,
    "gn:feature_class":"P",
    "gn:feature_code":"PPL",
    "gn:name":"Malyye Berezitsy",
    "gn:population":0,
    "gn:timezone":"Europe/Moscow",
    "iso:country":"RU",
    "name:rus_x_preferred":[
        "\u041c\u0430\u043b\u044b\u0435 \u0411\u0435\u0440\u0435\u0437\u0438\u0446\u044b"
    ],
    "wof:name":"Malyye Berezitsy",
    "wof:placetype":"locality"
},
  "geometry": {"coordinates":[30.01732,58.28207],"type":"Point"}
}