{
  "type": "Feature",
  "properties": {
    "gn:admin1_code":"52",
    "gn:asciiname":"Vidzha",
    "gn:country_code":"RU",
    "gn:dem":78,
    "gn:feature_class":"P",
    "gn:feature_code":"PPL",
    "gn:name":"Vidzha",
    "gn:population":0,
    "gn:timezone":"Europe/Moscow",
    "iso:country":"RU",
    "name:rus_x_preferred":[
        "\u0412\u0438\u0434\u0436\u0430"
    ],
    "wof:name":"Vidzha",
    "wof:placetype":"locality"
},
  "geometry": {"coordinates":[30.9323,57.637],"type":"Point"}
}