{
  "type": "Feature",
  "properties": {
    "gn:admin1_code":"6",
    "gn:asciiname":"Zherd'",
    "gn:country_code":"RU",
    "gn:dem":28,
    "gn:feature_class":"P",
    "gn:feature_code":"PPL",
    "gn:name":"Zherd\u2019",
    "gn:population":0,
    "gn:timezone":"Europe/Moscow",
    "iso:country":"RU",
    "name:eng_x_preferred":[
        "Zherd'"
    ],
    "name:nor_x_preferred":[
        "Zjerd"
    ],
    "name:rus_x_preferred":[
        "\u0416\u0435\u0440\u0434\u044c"
    ],
    "name:und_x_variant":[
        "Zherd\u2019"
    ],
    "wof:name":"Zherd'",
    "wof:placetype":"locality"
},
  "geometry": {"coordinates":[44.6941,65.5688],"type":"Point"}
}