{
  "type": "Feature",
  "properties": {
    "iso:country":"RU",
    "name:rus_x_preferred":[
        "\u041d\u0430\u0440\u0432\u0441\u043a\u0438\u0439"
    ],
    "wof:name":"Narvsky",
    "wof:placetype":"neighbourhood"
},
  "geometry": {"coordinates":[30.26458908524694,59.89124023066825],"type":"Point"}
}