{
  "type": "Feature",
  "properties": {
    "gn:admin1_code":"37",
    "gn:asciiname":"Kozhukhovo",
    "gn:country_code":"RU",
    "gn:dem":148,
    "gn:feature_class":"P",
    "gn:feature_code":"PPL",
    "gn:name":"Kozhukhovo",
    "gn:population":0,
    "gn:timezone":"Europe/Moscow",
    "iso:country":"RU",
    "name:und_x_variant":[
        "Kozhukhova",
        "Kozhukhovo"
    ],
    "wof:name":"Kozhukhovo",
    "wof:placetype":"locality"
},
  "geometry": {"coordinates":[41.9441,58.41928000000001],"type":"Point"}
}