{
  "type": "Feature",
  "properties": {
    "gn:admin1_code":"85",
    "gn:asciiname":"Remenevo",
    "gn:country_code":"RU",
    "gn:dem":146,
    "gn:feature_class":"P",
    "gn:feature_code":"PPL",
    "gn:name":"Remenevo",
    "gn:population":0,
    "gn:timezone":"Europe/Moscow",
    "iso:country":"RU",
    "name:rus_x_preferred":[
        "\u0420\u0435\u043c\u0435\u043d\u0435\u0432\u043e"
    ],
    "name:und_x_variant":[
        "\u0420\u0435\u043c\u0435\u043d\u0435\u0432\u043e"
    ],
    "wof:name":"Remenevo",
    "wof:placetype":"locality"
},
  "geometry": {"coordinates":[35.6027,58.92515],"type":"Point"}
}