{
  "type": "Feature",
  "properties": {
    "gn:admin1_code":"52",
    "gn:asciiname":"Okulovo",
    "gn:country_code":"RU",
    "gn:dem":47,
    "gn:feature_class":"P",
    "gn:feature_code":"PPL",
    "gn:name":"Okulovo",
    "gn:population":0,
    "gn:timezone":"Europe/Moscow",
    "iso:country":"RU",
    "name:rus_x_preferred":[
        "\u041e\u043a\u0443\u043b\u043e\u0432\u043e"
    ],
    "wof:name":"Okulovo",
    "wof:placetype":"locality"
},
  "geometry": {"coordinates":[32.81107,58.77962],"type":"Point"}
}