{
  "type": "Feature",
  "properties": {
    "gn:admin1_code":"49",
    "gn:asciiname":"Iokangskiy",
    "gn:country_code":"RU",
    "gn:dem":217,
    "gn:feature_class":"P",
    "gn:feature_code":"PPL",
    "gn:name":"Iokangskiy",
    "gn:population":0,
    "gn:timezone":"Europe/Moscow",
    "iso:country":"RU",
    "name:rus_x_preferred":[
        "\u0418\u043e\u043a\u0430\u043d\u0433\u0441\u043a\u0438\u0439"
    ],
    "name:und_x_variant":[
        "Zimnik Iokan\u2019ge",
        "Iokangskiy Zimniy Pogost",
        "Zimnyaya Yokan\u2019ga",
        "Zimnyaya Iokan\u2019skiy Pogost",
        "Iokangskiy"
    ],
    "wof:name":"Iokangskiy",
    "wof:placetype":"locality"
},
  "geometry": {"coordinates":[38.78648,67.32952],"type":"Point"}
}