{
  "type": "Feature",
  "properties": {
    "gn:admin1_code":"20",
    "gn:asciiname":"Rassvet",
    "gn:country_code":"RU",
    "gn:dem":483,
    "gn:feature_class":"P",
    "gn:feature_code":"PPL",
    "gn:name":"Rassvet",
    "gn:population":0,
    "gn:timezone":"Asia/Irkutsk",
    "iso:country":"RU",
    "name:eng_x_preferred":[
        "Rassvet"
    ],
    "name:nor_x_preferred":[
        "Rassvet"
    ],
    "name:rus_x_preferred":[
        "\u0420\u0430\u0441\u0441\u0432\u0435\u0442"
    ],
    "name:und_x_variant":[
        "\u0420\u0430\u0441\u0441\u0432\u0435\u0442"
    ],
    "wof:name":"Rassvet",
    "wof:placetype":"locality"
},
  "geometry": {"coordinates":[103.4418,53.563],"type":"Point"}
}