{
  "type": "Feature",
  "properties": {
    "gn:admin1_code":"10",
    "gn:asciiname":"V'yunki",
    "gn:country_code":"RU",
    "gn:dem":156,
    "gn:feature_class":"P",
    "gn:feature_code":"PPL",
    "gn:name":"V\u2019yunki",
    "gn:population":0,
    "gn:timezone":"Europe/Moscow",
    "iso:country":"RU",
    "name:rus_x_preferred":[
        "\u0412\u044c\u044e\u043d\u043a\u0438"
    ],
    "name:und_x_variant":[
        "V\u2019yunki",
        "\u0412\u044c\u044e\u043d\u043a\u0438"
    ],
    "wof:name":"V'yunki",
    "wof:placetype":"locality"
},
  "geometry": {"coordinates":[32.2599,52.7855],"type":"Point"}
}