{
  "type": "Feature",
  "properties": {
    "gn:admin1_code":"85",
    "gn:asciiname":"Kharchevnya",
    "gn:country_code":"RU",
    "gn:dem":178,
    "gn:feature_class":"P",
    "gn:feature_code":"PPL",
    "gn:name":"Kharchevnya",
    "gn:population":0,
    "gn:timezone":"Europe/Moscow",
    "iso:country":"RU",
    "name:rus_x_preferred":[
        "\u0425\u0430\u0440\u0447\u0435\u0432\u043d\u044f"
    ],
    "name:und_x_variant":[
        "\u0425\u0430\u0440\u0447\u0435\u0432\u043d\u044f"
    ],
    "wof:name":"Kharchevnya",
    "wof:placetype":"locality"
},
  "geometry": {"coordinates":[35.9482,59.9066],"type":"Point"}
}