{
  "type": "Feature",
  "properties": {
    "gn:admin1_code":"16",
    "gn:asciiname":"Nizhniye Shiushi",
    "gn:country_code":"RU",
    "gn:dem":142,
    "gn:feature_class":"P",
    "gn:feature_code":"PPL",
    "gn:name":"Nizhniye Shiushi",
    "gn:population":0,
    "gn:timezone":"Europe/Moscow",
    "iso:country":"RU",
    "name:rus_x_preferred":[
        "\u041d\u0438\u0436\u043d\u0438\u0435 \u0428\u0438\u0443\u0448\u0438"
    ],
    "wof:name":"Nizhniye Shiushi",
    "wof:placetype":"locality"
},
  "geometry": {"coordinates":[46.8333,55.8296],"type":"Point"}
}