{
  "type": "Feature",
  "properties": {
    "gn:admin1_code":"32",
    "gn:asciiname":"Sey-Kurt",
    "gn:country_code":"RU",
    "gn:dem":6,
    "gn:feature_class":"P",
    "gn:feature_code":"PPL",
    "gn:name":"Sey-Kurt",
    "gn:population":0,
    "gn:timezone":"Asia/Yekaterinburg",
    "iso:country":"RU",
    "name:rus_x_preferred":[
        "\u0421\u0435\u0439-\u041a\u0443\u0440\u0442"
    ],
    "name:und_x_variant":[
        "\u0421\u0435\u0439-\u041a\u0443\u0440\u0442"
    ],
    "wof:name":"Sey-Kurt",
    "wof:placetype":"locality"
},
  "geometry": {"coordinates":[64.86667,63.08333],"type":"Point"}
}