{
  "type": "Feature",
  "properties": {
    "gn:admin1_code":"71",
    "gn:asciiname":"Baskoy",
    "gn:country_code":"RU",
    "gn:dem":168,
    "gn:feature_class":"P",
    "gn:feature_code":"PPL",
    "gn:name":"Baskoy",
    "gn:population":0,
    "gn:timezone":"Asia/Yekaterinburg",
    "iso:country":"RU",
    "name:nor_x_preferred":[
        "Baskoj"
    ],
    "name:rus_x_preferred":[
        "\u0411\u0430\u0441\u043a\u043e\u0439"
    ],
    "wof:name":"Baskoy",
    "wof:placetype":"locality"
},
  "geometry": {"coordinates":[60.76667,58.45],"type":"Point"}
}