{
  "type": "Feature",
  "properties": {
    "gn:admin1_code":"85",
    "gn:asciiname":"Barskoye Pole",
    "gn:country_code":"RU",
    "gn:dem":185,
    "gn:feature_class":"P",
    "gn:feature_code":"PPL",
    "gn:name":"Barskoye Pole",
    "gn:population":0,
    "gn:timezone":"Europe/Moscow",
    "iso:country":"RU",
    "name:rus_x_preferred":[
        "\u0411\u0430\u0440\u0441\u043a\u043e\u0435 \u041f\u043e\u043b\u0435"
    ],
    "name:und_x_variant":[
        "\u0411\u0430\u0440\u0441\u043a\u043e\u0435 \u041f\u043e\u043b\u0435"
    ],
    "wof:name":"Barskoye Pole",
    "wof:placetype":"locality"
},
  "geometry": {"coordinates":[38.39791,58.96161],"type":"Point"}
}