{
  "type": "Feature",
  "properties": {
    "gn:admin1_code":"60",
    "gn:asciiname":"Anashkino",
    "gn:country_code":"RU",
    "gn:dem":97,
    "gn:feature_class":"P",
    "gn:feature_code":"PPL",
    "gn:name":"Anashkino",
    "gn:population":0,
    "gn:timezone":"Europe/Moscow",
    "iso:country":"RU",
    "name:rus_x_preferred":[
        "\u0410\u043d\u0430\u0448\u043a\u0438\u043d\u043e"
    ],
    "wof:name":"Anashkino",
    "wof:placetype":"locality"
},
  "geometry": {"coordinates":[28.97502,57.31154],"type":"Point"}
}