{
  "type": "Feature",
  "properties": {
    "gn:admin1_code":"1.0",
    "gn:asciiname":"Aresh",
    "gn:country_code":"RU",
    "gn:dem":1027,
    "gn:feature_class":"P",
    "gn:feature_code":"PPL",
    "gn:name":"Aresh",
    "gn:population":0,
    "gn:timezone":"Europe/Moscow",
    "iso:country":"RU",
    "name:ceb_x_preferred":[
        "Aresh"
    ],
    "name:fra_x_preferred":[
        "Aresh"
    ],
    "name:mai_x_preferred":[
        "\u0905\u0930\u0947\u0936"
    ],
    "name:msa_x_preferred":[
        "Aresh"
    ],
    "name:nep_x_preferred":[
        "\u0905\u0930\u0947\u0936"
    ],
    "name:new_x_preferred":[
        "\u0905\u0930\u0947\u0936"
    ],
    "name:pol_x_preferred":[
        "Aresh"
    ],
    "wof:name":"Aresh",
    "wof:placetype":"locality"
},
  "geometry": {"coordinates":[40.14404,43.95724000000001],"type":"Point"}
}