{
  "type": "Feature",
  "properties": {
    "gn:admin1_code":"77",
    "gn:asciiname":"Rogodino",
    "gn:country_code":"RU",
    "gn:dem":141,
    "gn:feature_class":"P",
    "gn:feature_code":"PPL",
    "gn:name":"Rogodino",
    "gn:population":0,
    "gn:timezone":"Europe/Moscow",
    "iso:country":"RU",
    "name:nor_x_preferred":[
        "Rogodino"
    ],
    "name:rus_x_preferred":[
        "\u0420\u043e\u0433\u043e\u0434\u0438\u043d\u043e"
    ],
    "name:und_x_variant":[
        "Ragodino",
        "Rogodino"
    ],
    "wof:name":"Rogodino",
    "wof:placetype":"locality"
},
  "geometry": {"coordinates":[35.66115999999999,56.95649],"type":"Point"}
}