{
  "type": "Feature",
  "properties": {
    "gn:admin1_code":"80.0",
    "gn:asciiname":"Bakhtiyevo",
    "gn:country_code":"RU",
    "gn:dem":220,
    "gn:feature_class":"P",
    "gn:feature_code":"PPL",
    "gn:name":"Bakhtiyevo",
    "gn:population":0,
    "gn:timezone":"Europe/Samara",
    "iso:country":"RU",
    "name:nor_x_preferred":[
        "Bakhtijevo"
    ],
    "name:rus_x_preferred":[
        "\u0411\u0430\u0445\u0442\u0438\u0435\u0432\u043e"
    ],
    "name:und_x_variant":[
        "Bakhteyevo",
        "Bakhtn\u00ebvo",
        "Bakhtiyevo"
    ],
    "wof:name":"Bakhtiyevo",
    "wof:placetype":"locality"
},
  "geometry": {"coordinates":[52.9411,57.8672],"type":"Point"}
}