{
  "type": "Feature",
  "properties": {
    "gn:admin1_code":"54",
    "gn:asciiname":"Urusovo",
    "gn:country_code":"RU",
    "gn:dem":91,
    "gn:feature_class":"P",
    "gn:feature_code":"PPL",
    "gn:name":"Urusovo",
    "gn:population":0,
    "gn:timezone":"Asia/Omsk",
    "iso:country":"RU",
    "name:eng_x_preferred":[
        "Urusovo"
    ],
    "name:nor_x_preferred":[
        "Urusovo"
    ],
    "name:rus_x_preferred":[
        "\u0423\u0440\u0443\u0441\u043e\u0432\u043e"
    ],
    "name:und_x_variant":[
        "\u0423\u0440\u0443\u0441\u043e\u0432\u043e"
    ],
    "wof:name":"Urusovo",
    "wof:placetype":"locality"
},
  "geometry": {"coordinates":[73.29353,55.65686],"type":"Point"}
}