{
  "type": "Feature",
  "properties": {
    "gn:admin1_code":"63",
    "gn:asciiname":"Kysyl-Khaya",
    "gn:country_code":"RU",
    "gn:dem":191,
    "gn:feature_class":"P",
    "gn:feature_code":"PPL",
    "gn:name":"Kysyl-Khaya",
    "gn:population":0,
    "gn:timezone":"Asia/Vladivostok",
    "iso:country":"RU",
    "wof:name":"Kysyl-Khaya",
    "wof:placetype":"locality"
},
  "geometry": {"coordinates":[135.84953999999999,67.0984],"type":"Point"}
}