{
  "type": "Feature",
  "properties": {
    "gn:admin1_code":"90",
    "gn:asciiname":"Kylasovo",
    "gn:country_code":"RU",
    "gn:dem":135,
    "gn:feature_class":"P",
    "gn:feature_code":"PPL",
    "gn:name":"Kylasovo",
    "gn:population":0,
    "gn:timezone":"Asia/Yekaterinburg",
    "iso:country":"RU",
    "name:eng_x_preferred":[
        "Kylasovo"
    ],
    "name:nor_x_preferred":[
        "Kylasovo"
    ],
    "name:rus_x_preferred":[
        "\u041a\u044b\u043b\u0430\u0441\u043e\u0432\u043e"
    ],
    "wof:name":"Kylasovo",
    "wof:placetype":"locality"
},
  "geometry": {"coordinates":[56.1071,58.8881],"type":"Point"}
}