{
  "type": "Feature",
  "properties": {
    "gn:admin1_code":"40",
    "gn:asciiname":"Grenadery",
    "gn:country_code":"RU",
    "gn:dem":141,
    "gn:feature_class":"P",
    "gn:feature_code":"PPL",
    "gn:name":"Grenadery",
    "gn:population":0,
    "gn:timezone":"Asia/Yekaterinburg",
    "iso:country":"RU",
    "name:eng_x_preferred":[
        "Grenadery"
    ],
    "name:nor_x_preferred":[
        "Grenadery"
    ],
    "name:rus_x_preferred":[
        "\u0413\u0440\u0435\u043d\u0430\u0434\u0435\u0440\u044b"
    ],
    "wof:name":"Grenadery",
    "wof:placetype":"locality"
},
  "geometry": {"coordinates":[67.12472,55.09028000000001],"type":"Point"}
}