{
  "type": "Feature",
  "properties": {
    "gn:admin1_code":"59",
    "gn:asciiname":"Nizhnemikhaylovka",
    "gn:country_code":"RU",
    "gn:dem":88,
    "gn:feature_class":"P",
    "gn:feature_code":"PPL",
    "gn:name":"Nizhnemikhaylovka",
    "gn:population":0,
    "gn:timezone":"Asia/Vladivostok",
    "iso:country":"RU",
    "name:eng_x_preferred":[
        "Nizhnemikhaylovka"
    ],
    "name:nor_x_preferred":[
        "Nizjnemikhajlovka"
    ],
    "name:rus_x_preferred":[
        "\u041d\u0438\u0436\u043d\u0435\u043c\u0438\u0445\u0430\u0439\u043b\u043e\u0432\u043a\u0430"
    ],
    "name:und_x_variant":[
        "Nizhne-Mikhaylovskaya",
        "Nizhne-Mikhaylovskiy",
        "Novomikhaylovskoye",
        "Nizhne-Mikhaylovskoye",
        "Novo-Mikhaylov"
    ],
    "wof:name":"Nizhnemikhaylovka",
    "wof:placetype":"locality"
},
  "geometry": {"coordinates":[133.91468999999998,46.44436],"type":"Point"}
}