{
  "type": "Feature",
  "properties": {
    "gn:admin1_code":"17.0",
    "gn:asciiname":"Chagarotar",
    "gn:country_code":"RU",
    "gn:dem":18,
    "gn:feature_class":"P",
    "gn:feature_code":"PPL",
    "gn:name":"Chagarotar",
    "gn:population":0,
    "gn:timezone":"Europe/Moscow",
    "iso:country":"RU",
    "name:rus_x_preferred":[
        "\u0427\u0430\u0433\u0430\u0440\u043e\u0442\u0430\u0440"
    ],
    "name:und_x_variant":[
        "Chogar-Otar",
        "Chagarotar"
    ],
    "wof:name":"Chagarotar",
    "wof:placetype":"locality"
},
  "geometry": {"coordinates":[46.53704000000001,43.46901],"type":"Point"}
}