{
  "type": "Feature",
  "properties": {
    "gn:admin1_code":"10",
    "gn:asciiname":"Krutoberezka",
    "gn:country_code":"RU",
    "gn:dem":169,
    "gn:feature_class":"P",
    "gn:feature_code":"PPL",
    "gn:name":"Krutoberezka",
    "gn:population":0,
    "gn:timezone":"Europe/Moscow",
    "iso:country":"RU",
    "name:rus_x_preferred":[
        "\u041a\u0440\u0443\u0442\u043e\u0431\u0435\u0440\u0435\u0437\u043a\u0430"
    ],
    "name:und_x_variant":[
        "Krutoberezhka"
    ],
    "wof:name":"Krutoberezka",
    "wof:placetype":"locality"
},
  "geometry": {"coordinates":[31.9962,52.5739],"type":"Point"}
}