{
  "type": "Feature",
  "properties": {
    "gn:admin1_code":"77",
    "gn:asciiname":"Kononkovo",
    "gn:country_code":"RU",
    "gn:dem":165,
    "gn:feature_class":"P",
    "gn:feature_code":"PPL",
    "gn:name":"Kononkovo",
    "gn:population":0,
    "gn:timezone":"Europe/Moscow",
    "iso:country":"RU",
    "name:rus_x_preferred":[
        "\u041a\u043e\u043d\u043e\u043d\u043a\u043e\u0432\u043e"
    ],
    "name:und_x_variant":[
        "\u041a\u043e\u043d\u043e\u043d\u043a\u043e\u0432\u043e"
    ],
    "wof:name":"Kononkovo",
    "wof:placetype":"locality"
},
  "geometry": {"coordinates":[34.39049,58.02911],"type":"Point"}
}