{
  "type": "Feature",
  "properties": {
    "gn:admin1_code":"20",
    "gn:asciiname":"Kharat",
    "gn:country_code":"RU",
    "gn:dem":548,
    "gn:feature_class":"P",
    "gn:feature_code":"PPL",
    "gn:name":"Kharat",
    "gn:population":0,
    "gn:timezone":"Asia/Irkutsk",
    "iso:country":"RU",
    "name:eng_x_preferred":[
        "Kharat"
    ],
    "name:nor_x_preferred":[
        "Kharat"
    ],
    "name:rus_x_preferred":[
        "\u0425\u0430\u0440\u0430\u0442"
    ],
    "wof:name":"Kharat",
    "wof:placetype":"locality"
},
  "geometry": {"coordinates":[105.0624,52.754],"type":"Point"}
}