{
  "type": "Feature",
  "properties": {
    "gn:admin1_code":"59.0",
    "gn:asciiname":"Lesnoye",
    "gn:country_code":"RU",
    "gn:dem":111,
    "gn:feature_class":"P",
    "gn:feature_code":"PPL",
    "gn:name":"Lesnoye",
    "gn:population":0,
    "gn:timezone":"Asia/Vladivostok",
    "iso:country":"RU",
    "name:nor_x_preferred":[
        "Lesnoje"
    ],
    "name:rus_x_preferred":[
        "\u041b\u0435\u0441\u043d\u043e\u0435"
    ],
    "wof:name":"Lesnoye",
    "wof:placetype":"locality"
},
  "geometry": {"coordinates":[133.55285000000001,45.46838],"type":"Point"}
}