{
  "type": "Feature",
  "properties": {
    "gn:admin1_code":"13.0",
    "gn:asciiname":"Solnechnyy",
    "gn:country_code":"RU",
    "gn:dem":326,
    "gn:feature_class":"P",
    "gn:feature_code":"PPL",
    "gn:name":"Solnechnyy",
    "gn:population":0,
    "gn:timezone":"Asia/Yekaterinburg",
    "iso:country":"RU",
    "name:rus_x_preferred":[
        "\u0421\u043e\u043b\u043d\u0435\u0447\u043d\u044b\u0439"
    ],
    "name:und_x_variant":[
        "\u0421\u043e\u043b\u043d\u0435\u0447\u043d\u044b\u0439"
    ],
    "wof:name":"Solnechnyy",
    "wof:placetype":"locality"
},
  "geometry": {"coordinates":[60.60007,53.04121],"type":"Point"}
}