{
  "type": "Feature",
  "properties": {
    "gn:admin1_code":"77.0",
    "gn:asciiname":"Bol'shoye Ryabtsevo",
    "gn:country_code":"RU",
    "gn:dem":215,
    "gn:feature_class":"P",
    "gn:feature_code":"PPL",
    "gn:name":"Bol\u2019shoye Ryabtsevo",
    "gn:population":0,
    "gn:timezone":"Europe/Moscow",
    "iso:country":"RU",
    "name:rus_x_preferred":[
        "\u0411\u043e\u043b\u044c\u0448\u043e\u0435 \u0420\u044f\u0431\u0446\u0435\u0432\u043e"
    ],
    "name:und_x_variant":[
        "Bol\u2019shoye Ryabtsevo"
    ],
    "wof:name":"Bol'shoye Ryabtsevo",
    "wof:placetype":"locality"
},
  "geometry": {"coordinates":[33.67963,56.72098],"type":"Point"}
}