{
  "type": "Feature",
  "properties": {
    "gn:admin1_code":"93",
    "gn:asciiname":"Dzhelonda",
    "gn:country_code":"RU",
    "gn:dem":480,
    "gn:feature_class":"P",
    "gn:feature_code":"PPL",
    "gn:name":"Dzhelonda",
    "gn:population":0,
    "gn:timezone":"Asia/Chita",
    "iso:country":"RU",
    "name:eng_x_preferred":[
        "Dzhelonda"
    ],
    "name:nor_x_preferred":[
        "Dzjelonda"
    ],
    "name:rus_x_preferred":[
        "\u0414\u0436\u0435\u043b\u043e\u043d\u0434\u0430"
    ],
    "name:und_x_variant":[
        "Dzholonda",
        "\u0414\u0436\u0435\u043b\u043e\u043d\u0434\u0430",
        "Dzhelonda"
    ],
    "wof:name":"Dzhelonda",
    "wof:placetype":"locality"
},
  "geometry": {"coordinates":[118.3754,53.26997],"type":"Point"}
}