{
  "type": "Feature",
  "properties": {
    "gn:admin1_code":"85",
    "gn:asciiname":"Kyrgoda",
    "gn:country_code":"RU",
    "gn:dem":223,
    "gn:feature_class":"P",
    "gn:feature_code":"PPL",
    "gn:name":"Kyrgoda",
    "gn:population":0,
    "gn:timezone":"Europe/Moscow",
    "iso:country":"RU",
    "name:eng_x_preferred":[
        "Kyrgoda"
    ],
    "name:nor_x_preferred":[
        "Kyrgoda"
    ],
    "name:rus_x_preferred":[
        "\u041a\u044b\u0440\u0433\u043e\u0434\u0430"
    ],
    "wof:name":"Kyrgoda",
    "wof:placetype":"locality"
},
  "geometry": {"coordinates":[37.06667,59.76667],"type":"Point"}
}