{
  "type": "Feature",
  "properties": {
    "gn:admin1_code":"37",
    "gn:asciiname":"Sazhino",
    "gn:country_code":"RU",
    "gn:dem":149,
    "gn:feature_class":"P",
    "gn:feature_code":"PPL",
    "gn:name":"Sazhino",
    "gn:population":0,
    "gn:timezone":"Europe/Moscow",
    "iso:country":"RU",
    "name:che_x_preferred":[
        "\u0421\u0430\u0436\u0438\u043d\u043e"
    ],
    "name:rus_x_preferred":[
        "\u0421\u0430\u0436\u0438\u043d\u043e"
    ],
    "wof:name":"Sazhino",
    "wof:placetype":"locality"
},
  "geometry": {"coordinates":[41.36128,57.59249000000001],"type":"Point"}
}