{
  "type": "Feature",
  "properties": {
    "gn:admin1_code":"4.0",
    "gn:asciiname":"Borovlyanskiy",
    "gn:country_code":"RU",
    "gn:dem":238,
    "gn:feature_class":"P",
    "gn:feature_code":"PPL",
    "gn:name":"Borovlyanskiy",
    "gn:population":0,
    "gn:timezone":"Asia/Barnaul",
    "iso:country":"RU",
    "name:rus_x_preferred":[
        "\u0411\u043e\u0440\u043e\u0432\u043b\u044f\u043d\u0441\u043a\u0438\u0439"
    ],
    "wof:name":"Borovlyanskiy",
    "wof:placetype":"locality"
},
  "geometry": {"coordinates":[84.6936,52.862],"type":"Point"}
}