{
  "type": "Feature",
  "properties": {
    "gn:admin1_code":"63",
    "gn:asciiname":"Ozhogin",
    "gn:country_code":"RU",
    "gn:dem":124,
    "gn:feature_class":"P",
    "gn:feature_code":"PPL",
    "gn:name":"Ozhogin",
    "gn:population":0,
    "gn:timezone":"Asia/Magadan",
    "iso:country":"RU",
    "name:rus_x_preferred":[
        "\u041e\u0436\u043e\u0433\u0438\u043d"
    ],
    "name:und_x_variant":[
        "\u041e\u0436\u043e\u0433\u0438\u043d"
    ],
    "wof:name":"Ozhogin",
    "wof:placetype":"locality"
},
  "geometry": {"coordinates":[146.38333,69.38333],"type":"Point"}
}