{
  "type": "Feature",
  "properties": {
    "gn:admin1_code":"91",
    "gn:asciiname":"Ishimka",
    "gn:country_code":"RU",
    "gn:dem":188,
    "gn:feature_class":"P",
    "gn:feature_code":"PPL",
    "gn:name":"Ishimka",
    "gn:population":0,
    "gn:timezone":"Asia/Krasnoyarsk",
    "iso:country":"RU",
    "name:eng_x_preferred":[
        "Ishimka"
    ],
    "name:nor_x_preferred":[
        "Isjimka"
    ],
    "name:rus_x_preferred":[
        "\u0418\u0448\u0438\u043c\u043a\u0430"
    ],
    "wof:name":"Ishimka",
    "wof:placetype":"locality"
},
  "geometry": {"coordinates":[90.5059,56.7738],"type":"Point"}
}