{
  "type": "Feature",
  "properties": {
    "gn:country":"RU",
    "gn:fcode":"ADM3",
    "gn:population":0,
    "iso:country":"RU",
    "name:rus_x_preferred":[
        "\u041a\u0443\u0440\u0447\u0430\u0442\u043e\u0432\u0441\u043a\u0438\u0439 \u0440\u0430\u0439\u043e\u043d"
    ],
    "name:und_x_variant":[
        "Kurchatovsky"
    ],
    "qs:name":"Kurchatovskiy Rayon",
    "qs:photos_9r":0,
    "qs:photos_sr":0,
    "qs:pop_sr":"0",
    "wof:name":"Kurchatovskiy Rayon",
    "wof:placetype":"localadmin",
    "wof:population":0
},
  "geometry": {"coordinates":[35.66667,51.65],"type":"Point"}
}