{
  "type": "Feature",
  "properties": {
    "gn:admin1_code":"92",
    "gn:asciiname":"Verkhne-Kamchatsk",
    "gn:country_code":"RU",
    "gn:dem":166,
    "gn:feature_class":"P",
    "gn:feature_code":"PPL",
    "gn:name":"Verkhne-Kamchatsk",
    "gn:population":0,
    "gn:timezone":"Asia/Kamchatka",
    "iso:country":"RU",
    "name:und_x_variant":[
        "Upper-Kamchalka",
        "Vevkhne-Kamchatsk",
        "Verkhne-Kamchatsk"
    ],
    "wof:name":"Verkhne-Kamchatsk",
    "wof:placetype":"locality"
},
  "geometry": {"coordinates":[158.46754000000001,54.62906],"type":"Point"}
}