{
  "type": "Feature",
  "properties": {
    "gn:admin1_code":"60",
    "gn:asciiname":"Rovnoye",
    "gn:country_code":"RU",
    "gn:dem":171,
    "gn:feature_class":"P",
    "gn:feature_code":"PPL",
    "gn:name":"Rovnoye",
    "gn:population":0,
    "gn:timezone":"Europe/Moscow",
    "iso:country":"RU",
    "name:rus_x_preferred":[
        "\u0420\u043e\u0432\u043d\u043e\u0435"
    ],
    "name:und_x_variant":[
        "\u0420\u043e\u0432\u043d\u043e\u0435"
    ],
    "wof:name":"Rovnoye",
    "wof:placetype":"locality"
},
  "geometry": {"coordinates":[29.4333,56.168],"type":"Point"}
}