{
  "type": "Feature",
  "properties": {
    "gn:admin1_code":"41.0",
    "gn:asciiname":"Borki",
    "gn:country_code":"RU",
    "gn:dem":139,
    "gn:feature_class":"P",
    "gn:feature_code":"PPL",
    "gn:name":"Borki",
    "gn:population":0,
    "gn:timezone":"Europe/Moscow",
    "iso:country":"RU",
    "name:eng_x_preferred":[
        "Borki"
    ],
    "name:nor_x_preferred":[
        "Borki"
    ],
    "name:rus_x_preferred":[
        "\u0411\u043e\u0440\u043a\u0438"
    ],
    "name:und_x_variant":[
        "\u0411\u043e\u0440\u043a\u0438",
        "Borki"
    ],
    "wof:name":"Borki",
    "wof:placetype":"locality"
},
  "geometry": {"coordinates":[35.4164,51.0984],"type":"Point"}
}