{
  "type": "Feature",
  "properties": {
    "gn:admin1_code":"60.0",
    "gn:asciiname":"Bol'shaya Guba",
    "gn:country_code":"RU",
    "gn:dem":54,
    "gn:feature_class":"P",
    "gn:feature_code":"PPL",
    "gn:name":"Bol\u2019shaya Guba",
    "gn:population":0,
    "gn:timezone":"Europe/Moscow",
    "iso:country":"RU",
    "name:rus_x_preferred":[
        "\u0411\u043e\u043b\u044c\u0448\u0430\u044f \u0413\u0443\u0431\u0430"
    ],
    "name:und_x_variant":[
        "Bol\u2019shaya Guba"
    ],
    "wof:name":"Bol'shaya Guba",
    "wof:placetype":"locality"
},
  "geometry": {"coordinates":[28.21082,57.33199000000001],"type":"Point"}
}