{
  "type": "Feature",
  "properties": {
    "gn:admin1_code":"67",
    "gn:asciiname":"Zernovoy",
    "gn:country_code":"RU",
    "gn:dem":61,
    "gn:feature_class":"P",
    "gn:feature_code":"PPL",
    "gn:name":"Zernovoy",
    "gn:population":0,
    "gn:timezone":"Europe/Saratov",
    "iso:country":"RU",
    "name:eng_x_preferred":[
        "Zernovoy"
    ],
    "name:nor_x_preferred":[
        "Zernovoj"
    ],
    "name:rus_x_preferred":[
        "\u0417\u0435\u0440\u043d\u043e\u0432\u043e\u0439"
    ],
    "wof:name":"Zernovoy",
    "wof:placetype":"locality"
},
  "geometry": {"coordinates":[48.2714,51.0338],"type":"Point"}
}