{
  "type": "Feature",
  "properties": {
    "gn:admin1_code":"34",
    "gn:asciiname":"Malaya Pera",
    "gn:country_code":"RU",
    "gn:dem":191,
    "gn:feature_class":"P",
    "gn:feature_code":"PPL",
    "gn:name":"Malaya Pera",
    "gn:population":0,
    "gn:timezone":"Europe/Moscow",
    "iso:country":"RU",
    "name:eng_x_preferred":[
        "Malaya Pera"
    ],
    "name:nor_x_preferred":[
        "Malaja Pera"
    ],
    "name:rus_x_preferred":[
        "\u041c\u0430\u043b\u0430\u044f \u041f\u0435\u0440\u0430"
    ],
    "wof:name":"Malaya Pera",
    "wof:placetype":"locality"
},
  "geometry": {"coordinates":[54.83257,64.18162],"type":"Point"}
}