{
  "type": "Feature",
  "properties": {
    "gn:admin1_code":"88",
    "gn:asciiname":"Yudakovo",
    "gn:country_code":"RU",
    "gn:dem":139,
    "gn:feature_class":"P",
    "gn:feature_code":"PPL",
    "gn:name":"Yudakovo",
    "gn:population":0,
    "gn:timezone":"Europe/Moscow",
    "iso:country":"RU",
    "name:rus_x_preferred":[
        "\u042e\u0434\u0430\u043a\u043e\u0432\u043e"
    ],
    "name:und_x_variant":[
        "Yudokovo",
        "Yudakovo"
    ],
    "wof:name":"Yudakovo",
    "wof:placetype":"locality"
},
  "geometry": {"coordinates":[39.21001,57.87907],"type":"Point"}
}