{
  "type": "Feature",
  "properties": {
    "gn:admin1_code":"90",
    "gn:asciiname":"Lipova",
    "gn:cc2":"RU",
    "gn:country_code":"RU",
    "gn:dem":176,
    "gn:feature_class":"P",
    "gn:feature_code":"PPL",
    "gn:name":"Lipova",
    "gn:population":0,
    "gn:timezone":"Asia/Yekaterinburg",
    "iso:country":"RU",
    "name:eng_x_preferred":[
        "Lipova"
    ],
    "name:nor_x_preferred":[
        "Lipova"
    ],
    "name:rus_x_preferred":[
        "\u041b\u0438\u043f\u043e\u0432\u0430"
    ],
    "name:und_x_variant":[
        "Lipovka",
        "Lipovo",
        "Lipova",
        "\u041b\u0438\u043f\u043e\u0432\u0430"
    ],
    "wof:name":"Lipova",
    "wof:placetype":"locality"
},
  "geometry": {"coordinates":[53.77667,59.5375],"type":"Point"}
}