{
  "type": "Feature",
  "properties": {
    "gn:admin1_code":"41.0",
    "gn:asciiname":"Provotorova",
    "gn:country_code":"RU",
    "gn:dem":193,
    "gn:feature_class":"P",
    "gn:feature_code":"PPL",
    "gn:name":"Provotorova",
    "gn:population":0,
    "gn:timezone":"Europe/Moscow",
    "iso:country":"RU",
    "name:rus_x_preferred":[
        "\u041f\u0440\u043e\u0432\u043e\u0442\u043e\u0440\u043e\u0432\u0430"
    ],
    "name:und_x_variant":[
        "Pravotorova",
        "Provotorova",
        "\u041f\u0440\u043e\u0432\u043e\u0442\u043e\u0440\u043e\u0432\u0430"
    ],
    "wof:name":"Provotorova",
    "wof:placetype":"locality"
},
  "geometry": {"coordinates":[35.7266,51.8223],"type":"Point"}
}