{
  "type": "Feature",
  "properties": {
    "gn:admin1_code":"62",
    "gn:asciiname":"Bat'ki",
    "gn:country_code":"RU",
    "gn:dem":107,
    "gn:feature_class":"P",
    "gn:feature_code":"PPL",
    "gn:name":"Bat\u2019ki",
    "gn:population":0,
    "gn:timezone":"Europe/Moscow",
    "iso:country":"RU",
    "name:rus_x_preferred":[
        "\u0411\u0430\u0442\u044c\u043a\u0438"
    ],
    "name:und_x_variant":[
        "Bat\u2019ki"
    ],
    "wof:name":"Bat'ki",
    "wof:placetype":"locality"
},
  "geometry": {"coordinates":[42.0531,54.2664],"type":"Point"}
}