{
  "type": "Feature",
  "properties": {
    "gn:admin1_code":"90.0",
    "gn:asciiname":"Poserdtsy",
    "gn:country_code":"RU",
    "gn:dem":195,
    "gn:feature_class":"P",
    "gn:feature_code":"PPL",
    "gn:name":"Poserdtsy",
    "gn:population":0,
    "gn:timezone":"Asia/Yekaterinburg",
    "iso:country":"RU",
    "name:rus_x_preferred":[
        "\u041f\u043e\u0441\u0435\u0440\u0434\u0446\u044b"
    ],
    "wof:name":"Poserdtsy",
    "wof:placetype":"locality"
},
  "geometry": {"coordinates":[55.3412,58.3792],"type":"Point"}
}