{
  "type": "Feature",
  "properties": {
    "gn:admin1_code":"28.0",
    "gn:asciiname":"Kintsinniemi",
    "gn:country_code":"RU",
    "gn:dem":67,
    "gn:feature_class":"P",
    "gn:feature_code":"PPL",
    "gn:name":"Kintsinniemi",
    "gn:population":0,
    "gn:timezone":"Europe/Moscow",
    "iso:country":"RU",
    "wof:name":"Kintsinniemi",
    "wof:placetype":"locality"
},
  "geometry": {"coordinates":[31.00402,62.0604],"type":"Point"}
}