{
  "type": "Feature",
  "properties": {
    "gn:admin1_code":"41.0",
    "gn:asciiname":"Gluboye",
    "gn:country_code":"RU",
    "gn:dem":193,
    "gn:feature_class":"P",
    "gn:feature_code":"PPL",
    "gn:name":"Gluboye",
    "gn:population":0,
    "gn:timezone":"Europe/Moscow",
    "iso:country":"RU",
    "name:rus_x_preferred":[
        "\u0413\u043b\u0443\u0431\u043e\u0435"
    ],
    "wof:name":"Gluboye",
    "wof:placetype":"locality"
},
  "geometry": {"coordinates":[34.7569,52.0585],"type":"Point"}
}