{
  "type": "Feature",
  "properties": {
    "gn:admin1_code":"4",
    "gn:asciiname":"Bespalovo",
    "gn:country_code":"RU",
    "gn:dem":146,
    "gn:feature_class":"P",
    "gn:feature_code":"PPL",
    "gn:name":"Bespalovo",
    "gn:population":0,
    "gn:timezone":"Asia/Barnaul",
    "iso:country":"RU",
    "name:eng_x_preferred":[
        "Bespalovo"
    ],
    "name:nor_x_preferred":[
        "Bespalovo"
    ],
    "name:rus_x_preferred":[
        "\u0411\u0435\u0441\u043f\u0430\u043b\u043e\u0432\u043e"
    ],
    "name:und_x_variant":[
        "Bespalova",
        "\u0411\u0435\u0441\u043f\u0430\u043b\u043e\u0432\u043e",
        "Bespalovo"
    ],
    "wof:name":"Bespalovo",
    "wof:placetype":"locality"
},
  "geometry": {"coordinates":[83.6897,52.313],"type":"Point"}
}