{
  "type": "Feature",
  "properties": {
    "gn:admin1_code":"69.0",
    "gn:asciiname":"Vyaz'ma-Bryanskaya",
    "gn:country_code":"RU",
    "gn:dem":246,
    "gn:feature_class":"P",
    "gn:feature_code":"PPL",
    "gn:name":"Vyaz\u2019ma-Bryanskaya",
    "gn:population":0,
    "gn:timezone":"Europe/Moscow",
    "iso:country":"RU",
    "wof:name":"Vyaz'ma-Bryanskaya",
    "wof:placetype":"locality"
},
  "geometry": {"coordinates":[34.3691,55.16441],"type":"Point"}
}