{
  "type": "Feature",
  "properties": {
    "gn:admin1_code":"73",
    "gn:asciiname":"Kubyakova",
    "gn:country_code":"RU",
    "gn:dem":150,
    "gn:feature_class":"P",
    "gn:feature_code":"PPL",
    "gn:name":"Kubyakova",
    "gn:population":0,
    "gn:timezone":"Europe/Moscow",
    "iso:country":"RU",
    "name:rus_x_preferred":[
        "\u041a\u0443\u0431\u044f\u043a\u043e\u0432\u0430"
    ],
    "name:und_x_variant":[
        "Kubyakovo",
        "Kubyakova",
        "\u041a\u0443\u0431\u044f\u043a\u043e\u0432\u0430"
    ],
    "wof:name":"Kubyakova",
    "wof:placetype":"locality"
},
  "geometry": {"coordinates":[53.56667,55.33333],"type":"Point"}
}