{
  "type": "Feature",
  "properties": {
    "gn:admin1_code":"85",
    "gn:asciiname":"Ochenikovo",
    "gn:country_code":"RU",
    "gn:dem":113,
    "gn:feature_class":"P",
    "gn:feature_code":"PPL",
    "gn:name":"Ochenikovo",
    "gn:population":0,
    "gn:timezone":"Europe/Moscow",
    "iso:country":"RU",
    "name:rus_x_preferred":[
        "\u041e\u0447\u0435\u043d\u0438\u043a\u043e\u0432\u043e"
    ],
    "name:und_x_variant":[
        "\u041e\u0447\u0435\u043d\u0438\u043a\u043e\u0432\u043e"
    ],
    "wof:name":"Ochenikovo",
    "wof:placetype":"locality"
},
  "geometry": {"coordinates":[38.34704,59.02291],"type":"Point"}
}