{
  "type": "Feature",
  "properties": {
    "gn:admin1_code":"60",
    "gn:asciiname":"Lashkovo",
    "gn:country_code":"RU",
    "gn:dem":156,
    "gn:feature_class":"P",
    "gn:feature_code":"PPL",
    "gn:name":"Lashkovo",
    "gn:population":0,
    "gn:timezone":"Europe/Moscow",
    "iso:country":"RU",
    "name:rus_x_preferred":[
        "\u041b\u0430\u0448\u043a\u043e\u0432\u043e"
    ],
    "wof:name":"Lashkovo",
    "wof:placetype":"locality"
},
  "geometry": {"coordinates":[29.2074,56.0255],"type":"Point"}
}