{
  "type": "Feature",
  "properties": {
    "gn:admin1_code":"52",
    "gn:asciiname":"Khvoroshchino",
    "gn:country_code":"RU",
    "gn:dem":81,
    "gn:feature_class":"P",
    "gn:feature_code":"PPL",
    "gn:name":"Khvoroshchino",
    "gn:population":0,
    "gn:timezone":"Europe/Moscow",
    "iso:country":"RU",
    "name:rus_x_preferred":[
        "\u0425\u0432\u043e\u0440\u043e\u0449\u0438\u043d\u043e"
    ],
    "wof:name":"Khvoroshchino",
    "wof:placetype":"locality"
},
  "geometry": {"coordinates":[31.03333,57.11666999999999],"type":"Point"}
}