{
  "type": "Feature",
  "properties": {
    "gn:admin1_code":"56",
    "gn:asciiname":"Spartak",
    "gn:country_code":"RU",
    "gn:dem":216,
    "gn:feature_class":"P",
    "gn:feature_code":"PPL",
    "gn:name":"Spartak",
    "gn:population":0,
    "gn:timezone":"Europe/Moscow",
    "iso:country":"RU",
    "name:rus_x_preferred":[
        "\u0421\u043f\u0430\u0440\u0442\u0430\u043a"
    ],
    "name:und_x_variant":[
        "\u0421\u043f\u0430\u0440\u0442\u0430\u043a"
    ],
    "wof:name":"Spartak",
    "wof:placetype":"locality"
},
  "geometry": {"coordinates":[35.98334000000001,53.4449],"type":"Point"}
}