{
  "type": "Feature",
  "properties": {
    "gn:admin1_code":"91",
    "gn:asciiname":"Kukdusuk",
    "gn:cc2":"RU",
    "gn:country_code":"RU",
    "gn:dem":774,
    "gn:feature_class":"P",
    "gn:feature_code":"PPL",
    "gn:name":"Kukdusuk",
    "gn:population":0,
    "gn:timezone":"Asia/Krasnoyarsk",
    "iso:country":"RU",
    "name:rus_x_preferred":[
        "\u041a\u0443\u043a\u0434\u0443\u0441\u0443\u043a"
    ],
    "name:und_x_variant":[
        "Kundusuk",
        "Kukdusuk"
    ],
    "wof:name":"Kukdusuk",
    "wof:placetype":"locality"
},
  "geometry": {"coordinates":[94.51667,53.15],"type":"Point"}
}