{
  "type": "Feature",
  "properties": {
    "gn:admin1_code":"67",
    "gn:asciiname":"Muravli",
    "gn:cc2":"RU",
    "gn:country_code":"RU",
    "gn:dem":45,
    "gn:feature_class":"P",
    "gn:feature_code":"PPL",
    "gn:name":"Muravli",
    "gn:population":0,
    "gn:timezone":"Europe/Saratov",
    "iso:country":"RU",
    "name:rus_x_preferred":[
        "\u041c\u0443\u0440\u0430\u0432\u043b\u0438"
    ],
    "name:und_x_variant":[
        "Novyye Muravli",
        "Muravli"
    ],
    "wof:name":"Muravli",
    "wof:placetype":"locality"
},
  "geometry": {"coordinates":[49.98333,51.56667],"type":"Point"}
}