{
  "type": "Feature",
  "properties": {
    "gn:admin1_code":"71",
    "gn:asciiname":"Skorodum",
    "gn:country_code":"RU",
    "gn:dem":90,
    "gn:feature_class":"P",
    "gn:feature_code":"PPL",
    "gn:name":"Skorodum",
    "gn:population":0,
    "gn:timezone":"Asia/Yekaterinburg",
    "iso:country":"RU",
    "name:rus_x_preferred":[
        "\u0421\u043a\u043e\u0440\u043e\u0434\u0443\u043c"
    ],
    "wof:name":"Skorodum",
    "wof:placetype":"locality"
},
  "geometry": {"coordinates":[64.98333000000001,57.08333],"type":"Point"}
}