{
  "type": "Feature",
  "properties": {
    "gn:country":"RU",
    "gn:fcode":"PPLX",
    "gn:pop":0,
    "iso:country":"RU",
    "name:rus_x_preferred":[
        "\u0427\u043a\u0430\u043b\u043e\u0432\u0441\u043a\u0438\u0439"
    ],
    "name:unk_x_variant":[
        "Chkalovskaya"
    ],
    "qs:name":"Chkalovskij",
    "qs:name_adm0":"Russia",
    "qs:name_adm1":"Moscow Oblast",
    "qs:photos_9r":0,
    "qs:photos_sr":0,
    "qs:placetype":"Town",
    "qs:pop_sr":"0",
    "wof:name":"Chkalovskij",
    "wof:placetype":"neighbourhood",
    "wof:population":0
},
  "geometry": {"coordinates":[38.07763,55.89534],"type":"Point"}
}