{
  "type": "Feature",
  "properties": {
    "gn:admin1_code":"37",
    "gn:asciiname":"Kanayevo",
    "gn:country_code":"RU",
    "gn:dem":170,
    "gn:feature_class":"P",
    "gn:feature_code":"PPL",
    "gn:name":"Kanayevo",
    "gn:population":0,
    "gn:timezone":"Europe/Moscow",
    "iso:country":"RU",
    "name:rus_x_preferred":[
        "\u041a\u0430\u043d\u0430\u0435\u0432\u043e"
    ],
    "name:und_x_variant":[
        "\u041a\u0430\u043d\u0430\u0435\u0432\u043e"
    ],
    "wof:name":"Kanayevo",
    "wof:placetype":"locality"
},
  "geometry": {"coordinates":[46.5598,58.9376],"type":"Point"}
}