{
  "type": "Feature",
  "properties": {
    "gn:admin1_code":"51",
    "gn:asciiname":"Sermyagino",
    "gn:country_code":"RU",
    "gn:dem":139,
    "gn:feature_class":"P",
    "gn:feature_code":"PPL",
    "gn:name":"Sermyagino",
    "gn:population":0,
    "gn:timezone":"Europe/Moscow",
    "iso:country":"RU",
    "name:rus_x_preferred":[
        "\u0421\u0435\u0440\u043c\u044f\u0433\u0438\u043d\u043e"
    ],
    "wof:name":"Sermyagino",
    "wof:placetype":"locality"
},
  "geometry": {"coordinates":[44.03,57.2706],"type":"Point"}
}