{
  "type": "Feature",
  "properties": {
    "gn:admin1_code":"52",
    "gn:asciiname":"Zagorodnaya",
    "gn:country_code":"RU",
    "gn:dem":24,
    "gn:feature_class":"P",
    "gn:feature_code":"PPL",
    "gn:name":"Zagorodnaya",
    "gn:population":0,
    "gn:timezone":"Europe/Moscow",
    "iso:country":"RU",
    "name:rus_x_preferred":[
        "\u0417\u0430\u0433\u043e\u0440\u043e\u0434\u043d\u0430\u044f"
    ],
    "name:und_x_variant":[
        "\u0417\u0430\u0433\u043e\u0440\u043e\u0434\u043d\u0430\u044f"
    ],
    "wof:name":"Zagorodnaya",
    "wof:placetype":"locality"
},
  "geometry": {"coordinates":[31.3196,57.9853],"type":"Point"}
}