{
  "type": "Feature",
  "properties": {
    "gn:admin1_code":"65.0",
    "gn:asciiname":"Dubrovskiy",
    "gn:country_code":"RU",
    "gn:dem":111,
    "gn:feature_class":"P",
    "gn:feature_code":"PPL",
    "gn:name":"Dubrovskiy",
    "gn:population":0,
    "gn:timezone":"Europe/Samara",
    "iso:country":"RU",
    "name:rus_x_preferred":[
        "\u0414\u0443\u0431\u0440\u043e\u0432\u0441\u043a\u0438\u0439"
    ],
    "wof:name":"Dubrovskiy",
    "wof:placetype":"locality"
},
  "geometry": {"coordinates":[50.18333,53.88333000000001],"type":"Point"}
}