{
  "type": "Feature",
  "properties": {
    "gn:admin1_code":"53",
    "gn:asciiname":"Tulinskiy",
    "gn:country_code":"RU",
    "gn:dem":144,
    "gn:feature_class":"P",
    "gn:feature_code":"PPL",
    "gn:name":"Tulinskiy",
    "gn:population":0,
    "gn:timezone":"Asia/Novosibirsk",
    "iso:country":"RU",
    "name:eng_x_preferred":[
        "Tulinskiy"
    ],
    "name:nor_x_preferred":[
        "Tulinskij"
    ],
    "name:rus_x_preferred":[
        "\u0422\u0443\u043b\u0438\u043d\u0441\u043a\u0438\u0439"
    ],
    "wof:name":"Tulinskiy",
    "wof:placetype":"locality"
},
  "geometry": {"coordinates":[82.8323,54.9126],"type":"Point"}
}