{
  "type": "Feature",
  "properties": {
    "gn:admin1_code":"69",
    "gn:asciiname":"Vlasova Sloboda",
    "gn:country_code":"RU",
    "gn:dem":193,
    "gn:feature_class":"P",
    "gn:feature_code":"PPL",
    "gn:name":"Vlasova Sloboda",
    "gn:population":0,
    "gn:timezone":"Europe/Moscow",
    "iso:country":"RU",
    "wof:name":"Vlasova Sloboda",
    "wof:placetype":"locality"
},
  "geometry": {"coordinates":[31.56086,54.69989],"type":"Point"}
}