{
  "type": "Feature",
  "properties": {
    "gn:admin1_code":"71",
    "gn:asciiname":"Tolmacheva",
    "gn:country_code":"RU",
    "gn:dem":68,
    "gn:feature_class":"P",
    "gn:feature_code":"PPL",
    "gn:name":"Tolmach\u00ebva",
    "gn:population":0,
    "gn:timezone":"Asia/Yekaterinburg",
    "iso:country":"RU",
    "wof:name":"Tolmacheva",
    "wof:placetype":"locality"
},
  "geometry": {"coordinates":[61.46666999999999,59.18333000000001],"type":"Point"}
}