{
  "type": "Feature",
  "properties": {
    "gn:admin1_code":"78",
    "gn:asciiname":"Revda",
    "gn:country_code":"RU",
    "gn:dem":56,
    "gn:feature_class":"P",
    "gn:feature_code":"PPL",
    "gn:name":"Revda",
    "gn:population":0,
    "gn:timezone":"Asia/Yekaterinburg",
    "iso:country":"RU",
    "name:eng_x_preferred":[
        "Revda"
    ],
    "name:nor_x_preferred":[
        "Revda"
    ],
    "name:rus_x_preferred":[
        "\u0420\u0435\u0432\u0434\u0430"
    ],
    "name:und_x_variant":[
        "\u0420\u0435\u0432\u0434\u0430",
        "Revda"
    ],
    "wof:name":"Revda",
    "wof:placetype":"locality"
},
  "geometry": {"coordinates":[66.61136999999999,56.87813000000001],"type":"Point"}
}