{
  "type": "Feature",
  "properties": {
    "gn:admin1_code":"78",
    "gn:asciiname":"Revda",
    "gn:country_code":"RU",
    "gn:dem":56,
    "gn:feature_class":"P",
    "gn:feature_code":"PPL",
    "gn:name":"Revda",
    "gn:population":0,
    "gn:timezone":"Asia/Yekaterinburg",
    "iso:country":"RU",
    "name:bel_x_preferred":[
        "\u0420\u044d\u045e\u0434\u0430"
    ],
    "name:ceb_x_preferred":[
        "Revda"
    ],
    "name:ces_x_preferred":[
        "Revda"
    ],
    "name:deu_x_preferred":[
        "Rewda"
    ],
    "name:eng_x_preferred":[
        "Revda"
    ],
    "name:ita_x_preferred":[
        "Revda"
    ],
    "name:lit_x_preferred":[
        "Revda"
    ],
    "name:nld_x_preferred":[
        "Revda"
    ],
    "name:nor_x_preferred":[
        "Revda"
    ],
    "name:rus_x_preferred":[
        "\u0420\u0435\u0432\u0434\u0430"
    ],
    "name:swe_x_preferred":[
        "Revda"
    ],
    "wof:name":"Revda",
    "wof:placetype":"locality"
},
  "geometry": {"coordinates":[66.61136999999999,56.87813000000001],"type":"Point"}
}