{
  "type": "Feature",
  "properties": {
    "gn:admin1_code":"4.0",
    "gn:asciiname":"Akat'yevo",
    "gn:country_code":"RU",
    "gn:dem":223,
    "gn:feature_class":"P",
    "gn:feature_code":"PPL",
    "gn:name":"Akat\u2019yevo",
    "gn:population":0,
    "gn:timezone":"Asia/Barnaul",
    "iso:country":"RU",
    "name:rus_x_preferred":[
        "\u0410\u043a\u0430\u0442\u044c\u0435\u0432\u043e"
    ],
    "name:und_x_variant":[
        "Akat\u2019yevo"
    ],
    "wof:name":"Akat'yevo",
    "wof:placetype":"locality"
},
  "geometry": {"coordinates":[86.4609,52.7731],"type":"Point"}
}