{
  "type": "Feature",
  "properties": {
    "gn:admin1_code":"73",
    "gn:asciiname":"Dva Polya Artash",
    "gn:country_code":"RU",
    "gn:dem":126,
    "gn:feature_class":"P",
    "gn:feature_code":"PPL",
    "gn:name":"Dva Polya Artash",
    "gn:population":0,
    "gn:timezone":"Europe/Moscow",
    "iso:country":"RU",
    "name:rus_x_preferred":[
        "\u0414\u0432\u0430 \u041f\u043e\u043b\u044f \u0410\u0440\u0442\u0430\u0448"
    ],
    "name:und_x_variant":[
        "\u0414\u0432\u0430 \u041f\u043e\u043b\u044f \u0410\u0440\u0442\u0430\u0448"
    ],
    "wof:name":"Dva Polya Artash",
    "wof:placetype":"locality"
},
  "geometry": {"coordinates":[50.6566,55.9444],"type":"Point"}
}