{
  "type": "Feature",
  "properties": {
    "gn:admin1_code":"33.0",
    "gn:asciiname":"Kostino",
    "gn:country_code":"RU",
    "gn:dem":144,
    "gn:feature_class":"P",
    "gn:feature_code":"PPL",
    "gn:name":"Kostino",
    "gn:population":0,
    "gn:timezone":"Europe/Kirov",
    "iso:country":"RU",
    "name:rus_x_preferred":[
        "\u041a\u043e\u0441\u0442\u0438\u043d\u043e"
    ],
    "name:und_x_variant":[
        "Kostiny",
        "Kostino",
        "\u041a\u043e\u0441\u0442\u0438\u043d\u043e"
    ],
    "wof:name":"Kostino",
    "wof:placetype":"locality"
},
  "geometry": {"coordinates":[49.47518,58.61374],"type":"Point"}
}