{
  "type": "Feature",
  "properties": {
    "gn:admin1_code":"85",
    "gn:asciiname":"Ryazanka",
    "gn:country_code":"RU",
    "gn:dem":142,
    "gn:feature_class":"P",
    "gn:feature_code":"PPL",
    "gn:name":"Ryazanka",
    "gn:population":0,
    "gn:timezone":"Europe/Moscow",
    "iso:country":"RU",
    "name:eng_x_preferred":[
        "Ryazanka"
    ],
    "name:nor_x_preferred":[
        "Rjazanka"
    ],
    "name:rus_x_preferred":[
        "\u0420\u044f\u0437\u0430\u043d\u043a\u0430"
    ],
    "name:und_x_variant":[
        "\u0420\u044f\u0437\u0430\u043d\u043a\u0430",
        "Ryazanka"
    ],
    "wof:name":"Ryazanka",
    "wof:placetype":"locality"
},
  "geometry": {"coordinates":[42.51905,59.91205],"type":"Point"}
}