{
  "type": "Feature",
  "properties": {
    "gn:admin1_code":"88",
    "gn:asciiname":"Kozlitsy",
    "gn:country_code":"RU",
    "gn:dem":185,
    "gn:feature_class":"P",
    "gn:feature_code":"PPL",
    "gn:name":"Kozlitsy",
    "gn:population":0,
    "gn:timezone":"Europe/Moscow",
    "iso:country":"RU",
    "name:rus_x_preferred":[
        "\u041a\u043e\u0437\u043b\u0438\u0446\u044b"
    ],
    "name:und_x_variant":[
        "\u041a\u043e\u0437\u043b\u0438\u0446\u044b"
    ],
    "wof:name":"Kozlitsy",
    "wof:placetype":"locality"
},
  "geometry": {"coordinates":[38.6494,57.3392],"type":"Point"}
}