{
  "type": "Feature",
  "properties": {
    "gn:admin1_code":"62",
    "gn:asciiname":"Petrovichi",
    "gn:country_code":"RU",
    "gn:dem":112,
    "gn:feature_class":"P",
    "gn:feature_code":"PPL",
    "gn:name":"Petrovichi",
    "gn:population":0,
    "gn:timezone":"Europe/Moscow",
    "iso:country":"RU",
    "name:rus_x_preferred":[
        "\u041f\u0435\u0442\u0440\u043e\u0432\u0438\u0447\u0438"
    ],
    "name:und_x_variant":[
        "\u041f\u0435\u0442\u0440\u043e\u0432\u0438\u0447\u0438"
    ],
    "wof:name":"Petrovichi",
    "wof:placetype":"locality"
},
  "geometry": {"coordinates":[40.2242,54.5045],"type":"Point"}
}