{
  "type": "Feature",
  "properties": {
    "gn:admin1_code":"54",
    "gn:asciiname":"Molodezhnoye",
    "gn:country_code":"RU",
    "gn:dem":95,
    "gn:feature_class":"P",
    "gn:feature_code":"PPL",
    "gn:name":"Molod\u00ebzhnoye",
    "gn:population":0,
    "gn:timezone":"Asia/Omsk",
    "iso:country":"RU",
    "name:rus_x_preferred":[
        "\u041c\u043e\u043b\u043e\u0434\u0451\u0436\u043d\u043e\u0435"
    ],
    "name:und_x_variant":[
        "Molod\u00ebzhnoye",
        "\u041c\u043e\u043b\u043e\u0434\u0451\u0436\u043d\u043e\u0435"
    ],
    "wof:name":"Molodezhnoye",
    "wof:placetype":"locality"
},
  "geometry": {"coordinates":[74.39490000000001,54.0498],"type":"Point"}
}