{
  "type": "Feature",
  "properties": {
    "gn:admin1_code":"53",
    "gn:asciiname":"Starogornostalevo",
    "gn:country_code":"RU",
    "gn:dem":114,
    "gn:feature_class":"P",
    "gn:feature_code":"PPL",
    "gn:name":"Starogornostalevo",
    "gn:population":0,
    "gn:timezone":"Asia/Novosibirsk",
    "iso:country":"RU",
    "name:eng_x_preferred":[
        "Starogornostalevo"
    ],
    "name:nor_x_preferred":[
        "Starogornostalevo"
    ],
    "name:rus_x_preferred":[
        "\u0421\u0442\u0430\u0440\u043e\u0433\u043e\u0440\u043d\u043e\u0441\u0442\u0430\u043b\u0435\u0432\u043e"
    ],
    "name:und_x_variant":[
        "Gornostaleva",
        "Starogornostali",
        "Uval\u2019naya",
        "\u0421\u0442\u0430\u0440\u043e\u0433\u043e\u0440\u043d\u043e\u0441\u0442\u0430\u043b\u0435\u0432\u043e",
        "Starogornostalevo"
    ],
    "wof:name":"Starogornostalevo",
    "wof:placetype":"locality"
},
  "geometry": {"coordinates":[79.23727,54.68101],"type":"Point"}
}