{
  "type": "Feature",
  "properties": {
    "gn:admin1_code":"86.0",
    "gn:asciiname":"Kashcheyev",
    "gn:country_code":"RU",
    "gn:dem":181,
    "gn:feature_class":"P",
    "gn:feature_code":"PPL",
    "gn:name":"Kashcheyev",
    "gn:population":0,
    "gn:timezone":"Europe/Moscow",
    "iso:country":"RU",
    "name:rus_x_preferred":[
        "\u041a\u0430\u0449\u0435\u0435\u0432"
    ],
    "wof:name":"Kashcheyev",
    "wof:placetype":"locality"
},
  "geometry": {"coordinates":[39.60389,49.71806],"type":"Point"}
}