{
  "type": "Feature",
  "properties": {
    "gn:country":"RU",
    "gn:fcode":"PPL",
    "gn:population":0,
    "iso:country":"RU",
    "name:rus_x_preferred":[
        "\u041b\u0438\u043a\u0438\u043d\u043e"
    ],
    "qs:name":"Likino",
    "qs:name_adm0":"Russia",
    "qs:name_adm1":"Moscow Oblast",
    "qs:photos_9r":0,
    "qs:photos_sr":0,
    "qs:placetype":"Town",
    "qs:pop_sr":"0",
    "wof:name":"Likino",
    "wof:placetype":"locality",
    "wof:population":0
},
  "geometry": {"coordinates":[37.13274,55.62538],"type":"Point"}
}