{
  "type": "Feature",
  "properties": {
    "gn:admin1_code":"37",
    "gn:asciiname":"Baklanovo",
    "gn:country_code":"RU",
    "gn:dem":151,
    "gn:feature_class":"P",
    "gn:feature_code":"PPL",
    "gn:name":"Baklanovo",
    "gn:population":0,
    "gn:timezone":"Europe/Moscow",
    "iso:country":"RU",
    "name:rus_x_preferred":[
        "\u0411\u0430\u043a\u043b\u0430\u043d\u043e\u0432\u043e"
    ],
    "name:und_x_variant":[
        "\u0411\u0430\u043a\u043b\u0430\u043d\u043e\u0432\u043e"
    ],
    "wof:name":"Baklanovo",
    "wof:placetype":"locality"
},
  "geometry": {"coordinates":[42.2518,58.5036],"type":"Point"}
}