{
  "type": "Feature",
  "properties": {
    "gn:admin1_code":"05",
    "gn:asciiname":"Pyatidesyatyy Kilometr",
    "gn:country_code":"RU",
    "gn:dem":313,
    "gn:feature_class":"P",
    "gn:feature_code":"PPL",
    "gn:name":"Pyatidesyatyy Kilometr",
    "gn:population":0,
    "gn:timezone":"Asia/Yakutsk",
    "iso:country":"RU",
    "name:rus_x_preferred":[
        "\u041f\u044f\u0442\u0438\u0434\u0435\u0441\u044f\u0442\u044b\u0439 \u041a\u0438\u043b\u043e\u043c\u0435\u0442\u0440"
    ],
    "wof:name":"Pyatidesyatyy Kilometr",
    "wof:placetype":"locality"
},
  "geometry": {"coordinates":[127.25,52.65],"type":"Point"}
}