{
  "type": "Feature",
  "properties": {
    "gn:admin1_code":"76",
    "gn:asciiname":"Rumyantsevo",
    "gn:country_code":"RU",
    "gn:dem":215,
    "gn:feature_class":"P",
    "gn:feature_code":"PPL",
    "gn:name":"Rumyantsevo",
    "gn:population":0,
    "gn:timezone":"Europe/Moscow",
    "iso:country":"RU",
    "name:rus_x_preferred":[
        "\u0420\u0443\u043c\u044f\u043d\u0446\u0435\u0432\u043e"
    ],
    "name:und_x_variant":[
        "\u0420\u0443\u043c\u044f\u043d\u0446\u0435\u0432\u043e"
    ],
    "wof:name":"Rumyantsevo",
    "wof:placetype":"locality"
},
  "geometry": {"coordinates":[38.62785,53.98522],"type":"Point"}
}