{
  "type": "Feature",
  "properties": {
    "gn:admin1_code":"63",
    "gn:asciiname":"At-Daban",
    "gn:country_code":"RU",
    "gn:dem":129,
    "gn:feature_class":"P",
    "gn:feature_code":"PPL",
    "gn:name":"At-Daban",
    "gn:population":0,
    "gn:timezone":"Asia/Yakutsk",
    "iso:country":"RU",
    "name:eng_x_preferred":[
        "At-Daban"
    ],
    "name:nor_x_preferred":[
        "At-Daban"
    ],
    "name:rus_x_preferred":[
        "\u0410\u0442-\u0414\u0430\u0431\u0430\u043d"
    ],
    "wof:name":"At-Daban",
    "wof:placetype":"locality"
},
  "geometry": {"coordinates":[126.50355999999999,61.11561],"type":"Point"}
}