{
  "type": "Feature",
  "properties": {
    "gn:admin1_code":"81.0",
    "gn:asciiname":"Chaadayevka",
    "gn:country_code":"RU",
    "gn:dem":217,
    "gn:feature_class":"P",
    "gn:feature_code":"PPL",
    "gn:name":"Chaadayevka",
    "gn:population":0,
    "gn:timezone":"Europe/Ulyanovsk",
    "iso:country":"RU",
    "name:rus_x_preferred":[
        "\u0427\u0430\u0430\u0434\u0430\u0435\u0432\u043a\u0430"
    ],
    "name:und_x_variant":[
        "\u0427\u0430\u0430\u0434\u0430\u0435\u0432\u043a\u0430"
    ],
    "wof:name":"Chaadayevka",
    "wof:placetype":"locality"
},
  "geometry": {"coordinates":[46.50985,53.57225],"type":"Point"}
}