{
  "type": "Feature",
  "properties": {
    "gn:admin1_code":"40",
    "gn:asciiname":"Chistoye",
    "gn:country_code":"RU",
    "gn:dem":176,
    "gn:feature_class":"P",
    "gn:feature_code":"PPL",
    "gn:name":"Chistoye",
    "gn:population":0,
    "gn:timezone":"Asia/Yekaterinburg",
    "iso:country":"RU",
    "name:eng_x_preferred":[
        "Chistoye"
    ],
    "name:nor_x_preferred":[
        "Tsjistoje"
    ],
    "name:rus_x_preferred":[
        "\u0427\u0438\u0441\u0442\u043e\u0435"
    ],
    "wof:name":"Chistoye",
    "wof:placetype":"locality"
},
  "geometry": {"coordinates":[62.4904,55.1568],"type":"Point"}
}