{
  "type": "Feature",
  "properties": {
    "gn:admin1_code":"10",
    "gn:asciiname":"Chaykino",
    "gn:country_code":"RU",
    "gn:dem":148,
    "gn:feature_class":"P",
    "gn:feature_code":"PPL",
    "gn:name":"Chaykino",
    "gn:population":0,
    "gn:timezone":"Europe/Moscow",
    "iso:country":"RU",
    "name:bak_x_preferred":[
        "\u0427\u0430\u0439\u043a\u0438\u043d"
    ],
    "name:che_x_preferred":[
        "\u0427\u0430\u0439\u043a\u0438\u043d\u043e"
    ],
    "name:hye_x_preferred":[
        "\u0549\u0561\u0575\u056f\u056b\u0576\u0578"
    ],
    "name:kat_x_preferred":[
        "\u10e9\u10d0\u10d8\u10d9\u10d8\u10dc\u10dd"
    ],
    "name:kaz_x_preferred":[
        "\u0427\u0430\u0439\u043a\u0438\u043d\u043e"
    ],
    "name:kir_x_preferred":[
        "\u0427\u0430\u0439\u043a\u0438\u043d\u043e"
    ],
    "name:rus_x_preferred":[
        "\u0427\u0430\u0439\u043a\u0438\u043d\u043e"
    ],
    "name:tat_x_preferred":[
        "\u0427\u0430\u0439\u043a\u0438\u043d \u0443\u0442\u0430\u0440\u044b"
    ],
    "name:ukr_x_preferred":[
        "\u0427\u0430\u0439\u043a\u0456\u043d\u043e"
    ],
    "wof:name":"Chaykino",
    "wof:placetype":"locality"
},
  "geometry": {"coordinates":[33.2139,52.5426],"type":"Point"}
}