{
  "type": "Feature",
  "properties": {
    "gn:admin1_code":"71",
    "gn:asciiname":"Volchevka",
    "gn:country_code":"RU",
    "gn:dem":212,
    "gn:feature_class":"P",
    "gn:feature_code":"PPL",
    "gn:name":"Volch\u00ebvka",
    "gn:population":0,
    "gn:timezone":"Asia/Yekaterinburg",
    "iso:country":"RU",
    "name:eng_x_preferred":[
        "Volch\u00ebvka"
    ],
    "name:nor_x_preferred":[
        "Voltsjevka"
    ],
    "name:rus_x_preferred":[
        "\u0412\u043e\u043b\u0447\u0435\u0432\u043a\u0430"
    ],
    "name:rus_x_variant":[
        "\u0412\u043e\u043b\u0447\u00eb\u0432\u043a\u0430"
    ],
    "name:und_x_variant":[
        "Bolchevka",
        "Volch\u00ebvka"
    ],
    "wof:name":"Volchevka",
    "wof:placetype":"locality"
},
  "geometry": {"coordinates":[59.7383,57.9535],"type":"Point"}
}