{
  "type": "Feature",
  "properties": {
    "gn:admin1_code":"83",
    "gn:asciiname":"Palishchi",
    "gn:country_code":"RU",
    "gn:dem":120,
    "gn:feature_class":"P",
    "gn:feature_code":"PPL",
    "gn:name":"Palishchi",
    "gn:population":0,
    "gn:timezone":"Europe/Moscow",
    "iso:country":"RU",
    "name:rus_x_preferred":[
        "\u041f\u0430\u043b\u0438\u0449\u0438"
    ],
    "wof:name":"Palishchi",
    "wof:placetype":"locality"
},
  "geometry": {"coordinates":[40.3205,55.42583000000001],"type":"Point"}
}