{
  "type": "Feature",
  "properties": {
    "gn:admin1_code":"63",
    "gn:asciiname":"Maralakh",
    "gn:country_code":"RU",
    "gn:dem":172,
    "gn:feature_class":"P",
    "gn:feature_code":"PPL",
    "gn:name":"Maralakh",
    "gn:population":0,
    "gn:timezone":"Asia/Yakutsk",
    "iso:country":"RU",
    "name:eng_x_preferred":[
        "Maralakh"
    ],
    "name:nor_x_preferred":[
        "Maralakh"
    ],
    "name:rus_x_preferred":[
        "\u041c\u0430\u0440\u0430\u043b\u0430\u0445"
    ],
    "wof:name":"Maralakh",
    "wof:placetype":"locality"
},
  "geometry": {"coordinates":[131.40707,60.46697],"type":"Point"}
}