{
  "type": "Feature",
  "properties": {
    "gn:admin1_code":"28",
    "gn:asciiname":"Rubchayla",
    "gn:country_code":"RU",
    "gn:dem":83,
    "gn:feature_class":"P",
    "gn:feature_code":"PPL",
    "gn:name":"Rubchayla",
    "gn:population":0,
    "gn:timezone":"Europe/Moscow",
    "iso:country":"RU",
    "name:rus_x_preferred":[
        "\u0420\u0443\u0431\u0447\u0430\u0439\u043b\u0430"
    ],
    "name:und_x_variant":[
        "Rubchaila",
        "Rubchayla",
        "\u0420\u0443\u0431\u0447\u0430\u0439\u043b\u0430"
    ],
    "wof:name":"Rubchayla",
    "wof:placetype":"locality"
},
  "geometry": {"coordinates":[33.15598,61.80059],"type":"Point"}
}