{
  "type": "Feature",
  "properties": {
    "gn:admin1_code":"77.0",
    "gn:asciiname":"Anankino",
    "gn:country_code":"RU",
    "gn:dem":164,
    "gn:feature_class":"P",
    "gn:feature_code":"PPL",
    "gn:name":"Anankino",
    "gn:population":0,
    "gn:timezone":"Europe/Moscow",
    "iso:country":"RU",
    "name:eng_x_preferred":[
        "Anankino"
    ],
    "name:nor_x_preferred":[
        "Anankino"
    ],
    "name:rus_x_preferred":[
        "\u0410\u043d\u0430\u043d\u043a\u0438\u043d\u043e"
    ],
    "name:und_x_variant":[
        "\u0410\u043d\u0430\u043d\u043a\u0438\u043d\u043e",
        "Anankino"
    ],
    "wof:name":"Anankino",
    "wof:placetype":"locality"
},
  "geometry": {"coordinates":[35.68177,57.31809000000001],"type":"Point"}
}