{
  "type": "Feature",
  "properties": {
    "gn:admin1_code":"69.0",
    "gn:asciiname":"Bessonovo",
    "gn:country_code":"RU",
    "gn:dem":228,
    "gn:feature_class":"P",
    "gn:feature_code":"PPL",
    "gn:name":"Bessonovo",
    "gn:population":0,
    "gn:timezone":"Europe/Moscow",
    "iso:country":"RU",
    "name:nor_x_preferred":[
        "Bessonovo"
    ],
    "name:rus_x_preferred":[
        "\u0411\u0435\u0441\u0441\u043e\u043d\u043e\u0432\u043e"
    ],
    "wof:name":"Bessonovo",
    "wof:placetype":"locality"
},
  "geometry": {"coordinates":[33.78419,55.089],"type":"Point"}
}