{
  "type": "Feature",
  "properties": {
    "gn:admin1_code":"46",
    "gn:asciiname":"Saygushi",
    "gn:country_code":"RU",
    "gn:dem":196,
    "gn:feature_class":"P",
    "gn:feature_code":"PPL",
    "gn:name":"Saygushi",
    "gn:population":0,
    "gn:timezone":"Europe/Moscow",
    "iso:country":"RU",
    "name:rus_x_preferred":[
        "\u0421\u0430\u0439\u0433\u0443\u0448\u0438"
    ],
    "wof:name":"Saygushi",
    "wof:placetype":"locality"
},
  "geometry": {"coordinates":[45.8093,54.4159],"type":"Point"}
}