{
  "type": "Feature",
  "properties": {
    "gn:admin1_code":"85",
    "gn:asciiname":"Talitsa",
    "gn:country_code":"RU",
    "gn:dem":200,
    "gn:feature_class":"P",
    "gn:feature_code":"PPL",
    "gn:name":"Talitsa",
    "gn:population":0,
    "gn:timezone":"Europe/Moscow",
    "iso:country":"RU",
    "name:bel_x_preferred":[
        "\u0422\u0430\u043b\u0456\u0446\u0430"
    ],
    "name:ceb_x_preferred":[
        "Talitsa"
    ],
    "name:eng_x_preferred":[
        "Talitsa"
    ],
    "name:nld_x_preferred":[
        "Talitsa"
    ],
    "name:nor_x_preferred":[
        "Talitsa"
    ],
    "name:rus_x_preferred":[
        "\u0422\u0430\u043b\u0438\u0446\u0430"
    ],
    "name:swe_x_preferred":[
        "Talitsa"
    ],
    "name:ukr_x_preferred":[
        "\u0422\u0430\u043b\u0438\u0446\u044f"
    ],
    "wof:name":"Talitsa",
    "wof:placetype":"locality"
},
  "geometry": {"coordinates":[43.73609,59.65943000000001],"type":"Point"}
}