{
  "type": "Feature",
  "properties": {
    "gn:admin1_code":"86",
    "gn:asciiname":"Slavyanka",
    "gn:country_code":"RU",
    "gn:dem":85,
    "gn:feature_class":"P",
    "gn:feature_code":"PPL",
    "gn:name":"Slavyanka",
    "gn:population":0,
    "gn:timezone":"Europe/Moscow",
    "iso:country":"RU",
    "name:rus_x_preferred":[
        "\u0421\u043b\u0430\u0432\u044f\u043d\u043a\u0430"
    ],
    "name:und_x_variant":[
        "\u0421\u043b\u0430\u0432\u044f\u043d\u043a\u0430"
    ],
    "wof:name":"Slavyanka",
    "wof:placetype":"locality"
},
  "geometry": {"coordinates":[39.79252,50.17434],"type":"Point"}
}