{
  "type": "Feature",
  "properties": {
    "gn:admin1_code":"40",
    "gn:asciiname":"Lenskaya",
    "gn:country_code":"RU",
    "gn:dem":73,
    "gn:feature_class":"P",
    "gn:feature_code":"PPL",
    "gn:name":"Lenskaya",
    "gn:population":0,
    "gn:timezone":"Asia/Yekaterinburg",
    "iso:country":"RU",
    "name:rus_x_preferred":[
        "\u041b\u0435\u043d\u0441\u043a\u0430\u044f"
    ],
    "wof:name":"Lenskaya",
    "wof:placetype":"locality"
},
  "geometry": {"coordinates":[64.5187,56.1877],"type":"Point"}
}