{
  "type": "Feature",
  "properties": {
    "gn:admin1_code":"73",
    "gn:asciiname":"Verkhnyaya Yum'ya",
    "gn:country_code":"RU",
    "gn:dem":165,
    "gn:feature_class":"P",
    "gn:feature_code":"PPL",
    "gn:name":"Verkhnyaya Yum\u2019ya",
    "gn:population":0,
    "gn:timezone":"Europe/Moscow",
    "iso:country":"RU",
    "name:rus_x_preferred":[
        "\u0412\u0435\u0440\u0445\u043d\u044f\u044f \u042e\u043c\u044c\u044f"
    ],
    "name:und_x_variant":[
        "Verkhnyaya Yum\u2019ya"
    ],
    "wof:name":"Verkhnyaya Yum'ya",
    "wof:placetype":"locality"
},
  "geometry": {"coordinates":[50.6882,56.15600000000001],"type":"Point"}
}