{
  "type": "Feature",
  "properties": {
    "gn:admin1_code":"9",
    "gn:asciiname":"Zhil'tsovo",
    "gn:country_code":"RU",
    "gn:dem":232,
    "gn:feature_class":"P",
    "gn:feature_code":"PPL",
    "gn:name":"Zhil\u2019tsovo",
    "gn:population":0,
    "gn:timezone":"Europe/Moscow",
    "iso:country":"RU",
    "name:rus_x_preferred":[
        "\u0416\u0438\u043b\u044c\u0446\u043e\u0432\u043e"
    ],
    "name:und_x_variant":[
        "Zhil\u2019tsovo",
        "Zhil\u2019tsov"
    ],
    "wof:name":"Zhil'tsovo",
    "wof:placetype":"locality"
},
  "geometry": {"coordinates":[37.14308,51.0595],"type":"Point"}
}