{
  "type": "Feature",
  "properties": {
    "gn:admin1_code":"85",
    "gn:asciiname":"Bol'shoye Lyskarevo",
    "gn:country_code":"RU",
    "gn:dem":116,
    "gn:feature_class":"P",
    "gn:feature_code":"PPL",
    "gn:name":"Bol\u2019shoye Lyskar\u00ebvo",
    "gn:population":0,
    "gn:timezone":"Europe/Moscow",
    "iso:country":"RU",
    "name:rus_x_preferred":[
        "\u0411\u043e\u043b\u044c\u0448\u043e\u0435 \u041b\u044b\u0441\u043a\u0430\u0440\u0451\u0432\u043e"
    ],
    "name:und_x_variant":[
        "Bol\u2019shoye Lyskar\u00ebvo",
        "\u0411\u043e\u043b\u044c\u0448\u043e\u0435 \u041b\u044b\u0441\u043a\u0430\u0440\u0451\u0432\u043e"
    ],
    "wof:name":"Bol'shoye Lyskarevo",
    "wof:placetype":"locality"
},
  "geometry": {"coordinates":[39.27562,59.78796],"type":"Point"}
}