{
  "type": "Feature",
  "properties": {
    "gn:admin1_code":"88",
    "gn:asciiname":"Nikola-Gora",
    "gn:country_code":"RU",
    "gn:dem":165,
    "gn:feature_class":"P",
    "gn:feature_code":"PPL",
    "gn:name":"Nikola-Gora",
    "gn:population":0,
    "gn:timezone":"Europe/Moscow",
    "iso:country":"RU",
    "name:eng_x_preferred":[
        "Nikolo-Gora"
    ],
    "name:nor_x_preferred":[
        "Nikola-Gora"
    ],
    "name:rus_x_preferred":[
        "\u041d\u0438\u043a\u043e\u043b\u0430-\u0413\u043e\u0440\u0430"
    ],
    "wof:name":"Nikola-Gora",
    "wof:placetype":"locality"
},
  "geometry": {"coordinates":[40.12198,58.43142],"type":"Point"}
}