{
  "type": "Feature",
  "properties": {
    "gn:admin1_code":"75",
    "gn:asciiname":"Platonovka",
    "gn:cc2":"RU",
    "gn:country_code":"RU",
    "gn:dem":150,
    "gn:feature_class":"P",
    "gn:feature_code":"PPL",
    "gn:name":"Platonovka",
    "gn:population":0,
    "gn:timezone":"Asia/Tomsk",
    "iso:country":"RU",
    "name:und_x_variant":[
        "Platonevka"
    ],
    "wof:name":"Platonovka",
    "wof:placetype":"locality"
},
  "geometry": {"coordinates":[86.60417,56.62806],"type":"Point"}
}