{
  "type": "Feature",
  "properties": {
    "gn:admin1_code":"56",
    "gn:asciiname":"Masalovka",
    "gn:country_code":"RU",
    "gn:dem":228,
    "gn:feature_class":"P",
    "gn:feature_code":"PPL",
    "gn:name":"Masalovka",
    "gn:population":0,
    "gn:timezone":"Europe/Moscow",
    "iso:country":"RU",
    "name:rus_x_preferred":[
        "\u041c\u0430\u0441\u0430\u043b\u043e\u0432\u043a\u0430"
    ],
    "name:und_x_variant":[
        "\u041c\u0430\u0441\u0430\u043b\u043e\u0432\u043a\u0430"
    ],
    "wof:name":"Masalovka",
    "wof:placetype":"locality"
},
  "geometry": {"coordinates":[36.47176,52.79516],"type":"Point"}
}