{
  "type": "Feature",
  "properties": {
    "gn:admin1_code":"62",
    "gn:asciiname":"Kornevskoy",
    "gn:country_code":"RU",
    "gn:dem":172,
    "gn:feature_class":"P",
    "gn:feature_code":"PPL",
    "gn:name":"Kornevskoy",
    "gn:population":0,
    "gn:timezone":"Europe/Moscow",
    "iso:country":"RU",
    "name:rus_x_preferred":[
        "\u041a\u043e\u0440\u043d\u0435\u0432\u0441\u043a\u043e\u0439"
    ],
    "wof:name":"Kornevskoy",
    "wof:placetype":"locality"
},
  "geometry": {"coordinates":[39.39379,53.67406999999999],"type":"Point"}
}