{
  "type": "Feature",
  "properties": {
    "gn:admin1_code":"8",
    "gn:asciiname":"Starobazanovo",
    "gn:country_code":"RU",
    "gn:dem":80,
    "gn:feature_class":"P",
    "gn:feature_code":"PPL",
    "gn:name":"Starobazanovo",
    "gn:population":0,
    "gn:timezone":"Asia/Yekaterinburg",
    "iso:country":"RU",
    "name:bak_x_preferred":[
        "\u0418\u04ab\u043a\u0435 \u0411\u0430\u0499\u0430\u043d"
    ],
    "name:che_x_preferred":[
        "\u0421\u0442\u0430\u0440\u043e\u0431\u0430\u0437\u0430\u043d\u043e\u0432\u043e"
    ],
    "name:eng_x_preferred":[
        "Starobazanovo"
    ],
    "name:hye_x_preferred":[
        "\u054d\u057f\u0561\u0580\u0578\u0562\u0561\u0566\u0561\u0576\u0578\u057e\u0578"
    ],
    "name:kaz_x_preferred":[
        "\u0415\u0441\u043a\u0456 \u0411\u0430\u0437\u0430\u043d"
    ],
    "name:kir_x_preferred":[
        "\u042d\u0441\u043a\u0438 \u0411\u0430\u0437\u0430\u043d"
    ],
    "name:nor_x_preferred":[
        "Starobazanovo"
    ],
    "name:rus_x_preferred":[
        "\u0421\u0442\u0430\u0440\u043e\u0431\u0430\u0437\u0430\u043d\u043e\u0432\u043e"
    ],
    "name:tat_x_preferred":[
        "\u0418\u0441\u043a\u0435 \u0411\u0430\u0437\u0430\u043d"
    ],
    "wof:name":"Starobazanovo",
    "wof:placetype":"locality"
},
  "geometry": {"coordinates":[55.3175,55.29861],"type":"Point"}
}