{
  "type": "Feature",
  "properties": {
    "gn:admin1_code":"8",
    "gn:asciiname":"Starobazanovo",
    "gn:country_code":"RU",
    "gn:dem":80,
    "gn:feature_class":"P",
    "gn:feature_code":"PPL",
    "gn:name":"Starobazanovo",
    "gn:population":0,
    "gn:timezone":"Asia/Yekaterinburg",
    "iso:country":"RU",
    "name:eng_x_preferred":[
        "Starobazanovo"
    ],
    "name:nor_x_preferred":[
        "Starobazanovo"
    ],
    "name:rus_x_preferred":[
        "\u0421\u0442\u0430\u0440\u043e\u0431\u0430\u0437\u0430\u043d\u043e\u0432\u043e"
    ],
    "name:und_x_variant":[
        "\u0421\u0442\u0430\u0440\u043e\u0431\u0430\u0437\u0430\u043d\u043e\u0432\u043e",
        "Starobazanovo"
    ],
    "wof:name":"Starobazanovo",
    "wof:placetype":"locality"
},
  "geometry": {"coordinates":[55.3175,55.29861],"type":"Point"}
}