{
  "type": "Feature",
  "properties": {
    "gn:country":"RU",
    "gn:fcode":"PPL",
    "gn:pop":676,
    "iso:country":"RU",
    "name:eng_x_preferred":[
        "Syapsya"
    ],
    "name:fin_x_preferred":[
        "S\u00e4ps\u00e4"
    ],
    "name:krl_x_preferred":[
        "S\u00e4psy"
    ],
    "name:rus_x_preferred":[
        "\u0421\u044f\u043f\u0441\u044f"
    ],
    "qs:name":"Syapsya",
    "qs:name_adm0":"Russia",
    "qs:name_adm1":"Karelia Republic",
    "qs:photos_9r":0,
    "qs:photos_sr":0,
    "qs:placetype":"Town",
    "qs:pop_sr":"2",
    "wof:name":"Syapsya",
    "wof:placetype":"locality",
    "wof:population":676
},
  "geometry": {"coordinates":[33.38676,61.92215],"type":"Point"}
}