{
  "type": "Feature",
  "properties": {
    "gn:admin1_code":"69",
    "gn:asciiname":"Zhary",
    "gn:country_code":"RU",
    "gn:dem":184,
    "gn:feature_class":"P",
    "gn:feature_code":"PPL",
    "gn:name":"Zhary",
    "gn:population":0,
    "gn:timezone":"Europe/Moscow",
    "iso:country":"RU",
    "name:rus_x_preferred":[
        "\u0416\u0430\u0440\u044b"
    ],
    "wof:name":"Zhary",
    "wof:placetype":"locality"
},
  "geometry": {"coordinates":[32.66368,54.34165],"type":"Point"}
}