{
  "type": "Feature",
  "properties": {
    "gn:admin1_code":"69",
    "gn:asciiname":"Zevakino",
    "gn:country_code":"RU",
    "gn:dem":234,
    "gn:feature_class":"P",
    "gn:feature_code":"PPL",
    "gn:name":"Zevakino",
    "gn:population":0,
    "gn:timezone":"Europe/Moscow",
    "iso:country":"RU",
    "name:rus_x_preferred":[
        "\u0417\u0435\u0432\u0430\u043a\u0438\u043d\u043e"
    ],
    "name:und_x_variant":[
        "Zeva Zevokino",
        "Zevakino"
    ],
    "wof:name":"Zevakino",
    "wof:placetype":"locality"
},
  "geometry": {"coordinates":[32.27785,54.85345],"type":"Point"}
}