{
  "type": "Feature",
  "properties": {
    "gn:admin1_code":"91",
    "gn:asciiname":"Gladkoye",
    "gn:country_code":"RU",
    "gn:dem":327,
    "gn:feature_class":"P",
    "gn:feature_code":"PPL",
    "gn:name":"Gladkoye",
    "gn:population":0,
    "gn:timezone":"Asia/Krasnoyarsk",
    "iso:country":"RU",
    "name:eng_x_preferred":[
        "Gladkoye"
    ],
    "name:nor_x_preferred":[
        "Gladkoje"
    ],
    "name:rus_x_preferred":[
        "\u0413\u043b\u0430\u0434\u043a\u043e\u0435"
    ],
    "name:und_x_variant":[
        "Gladkaya"
    ],
    "wof:name":"Gladkoye",
    "wof:placetype":"locality"
},
  "geometry": {"coordinates":[92.42639,56.35611],"type":"Point"}
}