{
  "type": "Feature",
  "properties": {
    "gn:admin1_code":"42",
    "gn:asciiname":"Lavniya",
    "gn:country_code":"RU",
    "gn:dem":17,
    "gn:feature_class":"P",
    "gn:feature_code":"PPL",
    "gn:name":"Lavniya",
    "gn:population":0,
    "gn:timezone":"Europe/Moscow",
    "iso:country":"RU",
    "name:rus_x_preferred":[
        "\u041b\u0430\u0432\u043d\u0438\u044f"
    ],
    "name:und_x_variant":[
        "L\u00e1vnia",
        "Lavinya",
        "Lavnin",
        "Lavniya"
    ],
    "wof:name":"Lavniya",
    "wof:placetype":"locality"
},
  "geometry": {"coordinates":[31.97996,60.08425],"type":"Point"}
}