{
  "type": "Feature",
  "properties": {
    "gn:admin1_code":"62",
    "gn:asciiname":"Poselok Otdeleniya Proletarskoye Selskokhozyaystvennogo Predpriyatiya Imeni Il'icha",
    "gn:country_code":"RU",
    "gn:dem":185,
    "gn:feature_class":"P",
    "gn:feature_code":"PPL",
    "gn:name":"Pos\u00eblok Otdeleniya Proletarskoye Selskokhozyaystvennogo Predpriyatiya Imeni Il\u2019icha",
    "gn:population":0,
    "gn:timezone":"Europe/Moscow",
    "iso:country":"RU",
    "name:rus_x_preferred":[
        "\u041f\u043e\u0441\u0451\u043b\u043e\u043a \u041e\u0442\u0434\u0435\u043b\u0435\u043d\u0438\u044f \u041f\u0440\u043e\u043b\u0435\u0442\u0430\u0440\u0441\u043a\u043e\u0435 \u0421\u0435\u043b\u044c\u0441\u043a\u043e\u0445\u043e\u0437\u044f\u0439\u0441\u0442\u0432\u0435\u043d\u043d\u043e\u0433\u043e \u041f\u0440\u0435\u0434\u043f\u0440\u0438\u044f\u0442\u0438\u044f \u0418\u043c\u0435\u043d\u0438 \u0418\u043b\u044c\u0438\u0447\u0430"
    ],
    "name:und_x_variant":[
        "Pos\u00eblok Otdeleniya Proletarskoye Selskokhozyaystvennogo Predpriyatiya Imeni Il\u2019icha",
        "Proletarskoye"
    ],
    "wof:name":"Poselok Otdeleniya Proletarskoye Selskokhozyaystvennogo Predpriyatiya Imeni Il'icha",
    "wof:placetype":"locality"
},
  "geometry": {"coordinates":[39.1601,54.0482],"type":"Point"}
}