{
  "type": "Feature",
  "properties": {
    "gn:admin1_code":"90.0",
    "gn:asciiname":"Lesouchastok",
    "gn:country_code":"RU",
    "gn:dem":180,
    "gn:feature_class":"P",
    "gn:feature_code":"PPL",
    "gn:name":"Lesouchastok",
    "gn:population":0,
    "gn:timezone":"Asia/Yekaterinburg",
    "iso:country":"RU",
    "name:rus_x_preferred":[
        "\u041b\u0435\u0441\u043e\u0443\u0447\u0430\u0441\u0442\u043e\u043a"
    ],
    "wof:name":"Lesouchastok",
    "wof:placetype":"locality"
},
  "geometry": {"coordinates":[55.6894,56.6498],"type":"Point"}
}