{
  "type": "Feature",
  "properties": {
    "gn:admin1_code":"52",
    "gn:asciiname":"Mezhenino",
    "gn:country_code":"RU",
    "gn:dem":46,
    "gn:feature_class":"P",
    "gn:feature_code":"PPL",
    "gn:name":"Mezhenino",
    "gn:population":0,
    "gn:timezone":"Europe/Moscow",
    "iso:country":"RU",
    "name:rus_x_preferred":[
        "\u041c\u0435\u0436\u0435\u043d\u0438\u043d\u043e"
    ],
    "name:und_x_variant":[
        "\u041c\u0435\u0436\u0435\u043d\u0438\u043d\u043e"
    ],
    "wof:name":"Mezhenino",
    "wof:placetype":"locality"
},
  "geometry": {"coordinates":[32.36667,58.66667],"type":"Point"}
}