{
  "type": "Feature",
  "properties": {
    "gn:admin1_code":"17.0",
    "gn:asciiname":"Yukhari-Yarak",
    "gn:country_code":"RU",
    "gn:dem":1417,
    "gn:feature_class":"P",
    "gn:feature_code":"PPL",
    "gn:name":"Yukhari-Yarak",
    "gn:population":0,
    "gn:timezone":"Europe/Moscow",
    "iso:country":"RU",
    "name:rus_x_preferred":[
        "\u042e\u0445\u0430\u0440\u0438-\u042f\u0440\u0430\u043a"
    ],
    "wof:name":"Yukhari-Yarak",
    "wof:placetype":"locality"
},
  "geometry": {"coordinates":[47.94825,41.83714000000001],"type":"Point"}
}