{
  "type": "Feature",
  "properties": {
    "gn:admin1_code":"7",
    "gn:asciiname":"Seitovka",
    "gn:country_code":"RU",
    "gn:dem":-25,
    "gn:feature_class":"P",
    "gn:feature_code":"PPL",
    "gn:name":"Seitovka",
    "gn:population":0,
    "gn:timezone":"Europe/Astrakhan",
    "iso:country":"RU",
    "name:rus_x_preferred":[
        "\u0421\u0435\u0438\u0442\u043e\u0432\u043a\u0430"
    ],
    "name:und_x_variant":[
        "Seytovka",
        "Seitovka"
    ],
    "wof:name":"Seitovka",
    "wof:placetype":"locality"
},
  "geometry": {"coordinates":[48.06031,46.72521],"type":"Point"}
}