{
  "type": "Feature",
  "properties": {
    "gn:admin1_code":"62",
    "gn:asciiname":"Vilki",
    "gn:country_code":"RU",
    "gn:dem":127,
    "gn:feature_class":"P",
    "gn:feature_code":"PPL",
    "gn:name":"Vilki",
    "gn:population":0,
    "gn:timezone":"Europe/Moscow",
    "iso:country":"RU",
    "name:rus_x_preferred":[
        "\u0412\u0438\u043b\u043a\u0438"
    ],
    "wof:name":"Vilki",
    "wof:placetype":"locality"
},
  "geometry": {"coordinates":[39.1809,54.2971],"type":"Point"}
}