{
  "type": "Feature",
  "properties": {
    "gn:admin1_code":"69.0",
    "gn:asciiname":"Bobny",
    "gn:country_code":"RU",
    "gn:dem":168,
    "gn:feature_class":"P",
    "gn:feature_code":"PPL",
    "gn:name":"Bobny",
    "gn:population":0,
    "gn:timezone":"Europe/Moscow",
    "iso:country":"RU",
    "name:rus_x_preferred":[
        "\u0411\u043e\u0431\u043d\u044b"
    ],
    "name:und_x_variant":[
        "Babny",
        "Bobny"
    ],
    "wof:name":"Bobny",
    "wof:placetype":"locality"
},
  "geometry": {"coordinates":[31.5627,55.11772],"type":"Point"}
}