{
  "type": "Feature",
  "properties": {
    "gn:admin1_code":"64",
    "gn:asciiname":"Kekkyowan",
    "gn:country_code":"RU",
    "gn:dem":10,
    "gn:feature_class":"P",
    "gn:feature_code":"PPL",
    "gn:name":"Kekkyowan",
    "gn:population":0,
    "gn:timezone":"Asia/Magadan",
    "iso:country":"RU",
    "name:jpn_x_preferred":[
        "\u30b1\u30c3\u30ad\u30e7\u30ef\u30f3"
    ],
    "name:jpn_x_variant":[
        "\u3051\u3063\u304d\u3087\u308f\u3093"
    ],
    "wof:name":"Kekkyowan",
    "wof:placetype":"locality"
},
  "geometry": {"coordinates":[146.77116000000001,43.7686],"type":"Point"}
}