{
  "type": "Feature",
  "properties": {
    "gn:admin1_code":"16",
    "gn:asciiname":"Kozhar-Yandoba",
    "gn:country_code":"RU",
    "gn:dem":114,
    "gn:feature_class":"P",
    "gn:feature_code":"PPL",
    "gn:name":"Kozhar-Yandoba",
    "gn:population":0,
    "gn:timezone":"Europe/Moscow",
    "iso:country":"RU",
    "name:rus_x_preferred":[
        "\u041a\u043e\u0436\u0430\u0440-\u042f\u043d\u0434\u043e\u0431\u0430"
    ],
    "name:und_x_variant":[
        "Kozhary",
        "Kozhar-Yandoba",
        "\u041a\u043e\u0436\u0430\u0440-\u042f\u043d\u0434\u043e\u0431\u0430"
    ],
    "wof:name":"Kozhar-Yandoba",
    "wof:placetype":"locality"
},
  "geometry": {"coordinates":[47.02677,55.694],"type":"Point"}
}