{
  "type": "Feature",
  "properties": {
    "gn:admin1_code":"57",
    "gn:asciiname":"Malyy Koloyar",
    "gn:cc2":"RU",
    "gn:country_code":"RU",
    "gn:dem":138,
    "gn:feature_class":"P",
    "gn:feature_code":"PPL",
    "gn:name":"Malyy Koloyar",
    "gn:population":0,
    "gn:timezone":"Europe/Moscow",
    "iso:country":"RU",
    "name:rus_x_preferred":[
        "\u041c\u0430\u043b\u044b\u0439 \u041a\u043e\u043b\u043e\u044f\u0440"
    ],
    "name:und_x_variant":[
        "Maly Koloyar",
        "Malyy Koloyar",
        "\u041c\u0430\u043b\u044b\u0439 \u041a\u043e\u043b\u043e\u044f\u0440"
    ],
    "wof:name":"Malyy Koloyar",
    "wof:placetype":"locality"
},
  "geometry": {"coordinates":[45.06667,53.36666999999999],"type":"Point"}
}