{
  "type": "Feature",
  "properties": {
    "gn:admin1_code":"33.0",
    "gn:asciiname":"Tormazy",
    "gn:country_code":"RU",
    "gn:dem":133,
    "gn:feature_class":"P",
    "gn:feature_code":"PPL",
    "gn:name":"Tormazy",
    "gn:population":0,
    "gn:timezone":"Europe/Kirov",
    "iso:country":"RU",
    "name:rus_x_preferred":[
        "\u0422\u043e\u0440\u043c\u0430\u0437\u044b"
    ],
    "wof:name":"Tormazy",
    "wof:placetype":"locality"
},
  "geometry": {"coordinates":[48.22237,57.77186],"type":"Point"}
}