{
  "type": "Feature",
  "properties": {
    "gn:admin1_code":"69",
    "gn:asciiname":"Vishnevka",
    "gn:country_code":"RU",
    "gn:dem":198,
    "gn:feature_class":"P",
    "gn:feature_code":"PPL",
    "gn:name":"Vishn\u00ebvka",
    "gn:population":0,
    "gn:timezone":"Europe/Moscow",
    "iso:country":"RU",
    "name:rus_x_preferred":[
        "\u0412\u0438\u0448\u043d\u0451\u0432\u043a\u0430"
    ],
    "name:und_x_variant":[
        "Vishn\u00ebvka"
    ],
    "wof:name":"Vishnevka",
    "wof:placetype":"locality"
},
  "geometry": {"coordinates":[32.4221,55.5666],"type":"Point"}
}