{
  "type": "Feature",
  "properties": {
    "gn:admin1_code":"7.0",
    "gn:asciiname":"Aulet",
    "gn:country_code":"RU",
    "gn:dem":27,
    "gn:feature_class":"P",
    "gn:feature_code":"PPL",
    "gn:name":"Aulet",
    "gn:population":0,
    "gn:timezone":"Europe/Astrakhan",
    "iso:country":"RU",
    "name:nor_x_preferred":[
        "Aulet"
    ],
    "name:rus_x_preferred":[
        "\u0410\u0443\u043b\u0435\u0442"
    ],
    "wof:name":"Aulet",
    "wof:placetype":"locality"
},
  "geometry": {"coordinates":[46.64133,48.34936],"type":"Point"}
}