{
  "type": "Feature",
  "properties": {
    "gn:admin1_code":"76",
    "gn:asciiname":"Soklakovo",
    "gn:country_code":"RU",
    "gn:dem":210,
    "gn:feature_class":"P",
    "gn:feature_code":"PPL",
    "gn:name":"Soklakovo",
    "gn:population":0,
    "gn:timezone":"Europe/Moscow",
    "iso:country":"RU",
    "name:eng_x_preferred":[
        "Soklakovo"
    ],
    "name:nor_x_preferred":[
        "Soklakovo"
    ],
    "name:rus_x_preferred":[
        "\u0421\u043e\u043a\u043b\u0430\u043a\u043e\u0432\u043e"
    ],
    "name:und_x_variant":[
        "\u0421\u043e\u043a\u043b\u0430\u043a\u043e\u0432\u043e",
        "Soklakovo"
    ],
    "wof:name":"Soklakovo",
    "wof:placetype":"locality"
},
  "geometry": {"coordinates":[37.68278,53.14361],"type":"Point"}
}