{
  "type": "Feature",
  "properties": {
    "gn:admin1_code":"5.0",
    "gn:asciiname":"Ust'-Kivda",
    "gn:country_code":"RU",
    "gn:dem":109,
    "gn:feature_class":"P",
    "gn:feature_code":"PPL",
    "gn:name":"Ust\u2019-Kivda",
    "gn:population":0,
    "gn:timezone":"Asia/Yakutsk",
    "iso:country":"RU",
    "name:rus_x_preferred":[
        "\u0423\u0441\u0442\u044c-\u041a\u0438\u0432\u0434\u0430"
    ],
    "name:und_x_variant":[
        "Ust\u2019-Kivda"
    ],
    "wof:name":"Ust'-Kivda",
    "wof:placetype":"locality"
},
  "geometry": {"coordinates":[129.69565,49.67807],"type":"Point"}
}