{
  "type": "Feature",
  "properties": {
    "gn:admin1_code":"62",
    "gn:asciiname":"Luzhki",
    "gn:country_code":"RU",
    "gn:dem":107,
    "gn:feature_class":"P",
    "gn:feature_code":"PPL",
    "gn:name":"Luzhki",
    "gn:population":0,
    "gn:timezone":"Europe/Moscow",
    "iso:country":"RU",
    "name:rus_x_preferred":[
        "\u041b\u0443\u0436\u043a\u0438"
    ],
    "name:und_x_variant":[
        "\u041b\u0443\u0436\u043a\u0438"
    ],
    "wof:name":"Luzhki",
    "wof:placetype":"locality"
},
  "geometry": {"coordinates":[39.33759000000001,54.66794],"type":"Point"}
}