{
  "type": "Feature",
  "properties": {
    "gn:admin1_code":"60",
    "gn:asciiname":"Knyazevo",
    "gn:country_code":"RU",
    "gn:dem":41,
    "gn:feature_class":"P",
    "gn:feature_code":"PPL",
    "gn:name":"Knyazevo",
    "gn:population":0,
    "gn:timezone":"Europe/Moscow",
    "iso:country":"RU",
    "name:rus_x_preferred":[
        "\u041a\u043d\u044f\u0437\u0435\u0432\u043e"
    ],
    "wof:name":"Knyazevo",
    "wof:placetype":"locality"
},
  "geometry": {"coordinates":[28.3831,57.6751],"type":"Point"}
}