{
  "type": "Feature",
  "properties": {
    "gn:admin1_code":"40",
    "gn:asciiname":"Krasnyy Dol",
    "gn:country_code":"RU",
    "gn:dem":148,
    "gn:feature_class":"P",
    "gn:feature_code":"PPL",
    "gn:name":"Krasnyy Dol",
    "gn:population":0,
    "gn:timezone":"Asia/Yekaterinburg",
    "iso:country":"RU",
    "name:rus_x_preferred":[
        "\u041a\u0440\u0430\u0441\u043d\u044b\u0439 \u0414\u043e\u043b"
    ],
    "wof:name":"Krasnyy Dol",
    "wof:placetype":"locality"
},
  "geometry": {"coordinates":[63.92278,55.49166999999999],"type":"Point"}
}