{
  "type": "Feature",
  "properties": {
    "gn:admin1_code":"44",
    "gn:asciiname":"Eriki",
    "gn:country_code":"RU",
    "gn:dem":563,
    "gn:feature_class":"P",
    "gn:feature_code":"PPL",
    "gn:name":"Eriki",
    "gn:population":0,
    "gn:timezone":"Asia/Magadan",
    "iso:country":"RU",
    "name:rus_x_preferred":[
        "\u042d\u0440\u0438\u043a\u0438"
    ],
    "name:und_x_variant":[
        "\u042d\u0440\u0438\u043a\u0438"
    ],
    "wof:name":"Eriki",
    "wof:placetype":"locality"
},
  "geometry": {"coordinates":[148.91666999999995,61.46666999999999],"type":"Point"}
}