{
  "type": "Feature",
  "properties": {
    "gn:admin1_code":"28.0",
    "gn:asciiname":"Uusi-Jerusalem",
    "gn:country_code":"RU",
    "gn:dem":24,
    "gn:feature_class":"P",
    "gn:feature_code":"PPL",
    "gn:name":"Uusi-Jerusalem",
    "gn:population":0,
    "gn:timezone":"Europe/Moscow",
    "iso:country":"RU",
    "wof:name":"Uusi-Jerusalem",
    "wof:placetype":"locality"
},
  "geometry": {"coordinates":[30.8927,61.37164],"type":"Point"}
}