{
  "type": "Feature",
  "properties": {
    "gn:admin1_code":"61.0",
    "gn:asciiname":"Otradnyy",
    "gn:country_code":"RU",
    "gn:dem":70,
    "gn:feature_class":"P",
    "gn:feature_code":"PPL",
    "gn:name":"Otradnyy",
    "gn:population":0,
    "gn:timezone":"Europe/Moscow",
    "iso:country":"RU",
    "name:ben_x_preferred":[
        "\u0993\u09a4\u09cd\u09b0\u09be\u09a6\u09a8\u09bf"
    ],
    "name:ell_x_preferred":[
        "\u039f\u03c4\u03c1\u03b1\u03bd\u03c4\u03c1\u03af\u03b9"
    ],
    "name:heb_x_preferred":[
        "\u05d0\u05d5\u05d8\u05e8\u05d0\u05d3\u05e0\u05d9"
    ],
    "name:hin_x_preferred":[
        "\u0913\u0924\u094d\u0930\u093e\u0926\u094d\u0928\u0940"
    ],
    "name:hun_x_preferred":[
        "Otradny"
    ],
    "name:ind_x_preferred":[
        "Otradnyy"
    ],
    "name:jpn_x_preferred":[
        "\u30aa\u30c8\u30e9\u30c9\u30cb"
    ],
    "name:kor_x_preferred":[
        "\uc624\ud2b8\ub77c\ub4dc\ub2c8"
    ],
    "name:por_x_preferred":[
        "Otradny"
    ],
    "name:urd_x_preferred":[
        "\u0627\u0648\u0679\u0631\u0627\u0688\u0646\u06cc"
    ],
    "name:vie_x_preferred":[
        "Otradnyy"
    ],
    "wof:name":"Otradnyy",
    "wof:placetype":"locality"
},
  "geometry": {"coordinates":[41.57139,48.75389],"type":"Point"}
}