{
  "type": "Feature",
  "properties": {
    "gn:admin1_code":"69",
    "gn:asciiname":"Novyye Kurdyuki",
    "gn:country_code":"RU",
    "gn:dem":209,
    "gn:feature_class":"P",
    "gn:feature_code":"PPL",
    "gn:name":"Novyye Kurdyuki",
    "gn:population":0,
    "gn:timezone":"Europe/Moscow",
    "iso:country":"RU",
    "wof:name":"Novyye Kurdyuki",
    "wof:placetype":"locality"
},
  "geometry": {"coordinates":[34.97528,55.87726],"type":"Point"}
}