{
  "type": "Feature",
  "properties": {
    "gn:admin1_code":"32",
    "gn:asciiname":"Tutleym",
    "gn:cc2":"RU",
    "gn:country_code":"RU",
    "gn:dem":12,
    "gn:feature_class":"P",
    "gn:feature_code":"PPL",
    "gn:name":"Tutleym",
    "gn:population":0,
    "gn:timezone":"Asia/Yekaterinburg",
    "iso:country":"RU",
    "name:eng_x_preferred":[
        "Tutleym"
    ],
    "name:nor_x_preferred":[
        "Tutlejm"
    ],
    "name:rus_x_preferred":[
        "\u0422\u0443\u0442\u043b\u0435\u0439\u043c"
    ],
    "name:und_x_variant":[
        "Tutleim",
        "Tutleumskiye Yurty",
        "Tuplenskiye",
        "Tutleumskiye",
        "Tutleym"
    ],
    "wof:name":"Tutleym",
    "wof:placetype":"locality"
},
  "geometry": {"coordinates":[64.62278000000001,63.97417],"type":"Point"}
}