{
  "type": "Feature",
  "properties": {
    "gn:admin1_code":"23",
    "gn:asciiname":"Otradnoye",
    "gn:country_code":"RU",
    "gn:dem":120,
    "gn:feature_class":"P",
    "gn:feature_code":"PPL",
    "gn:name":"Otradnoye",
    "gn:population":0,
    "gn:timezone":"Europe/Kaliningrad",
    "iso:country":"RU",
    "name:rus_x_preferred":[
        "\u041e\u0442\u0440\u0430\u0434\u043d\u043e\u0435"
    ],
    "name:und_x_variant":[
        "Kunigelen",
        "Otradnoe",
        "Kunigehlen",
        "Stroppau",
        "Otradnoye",
        "\u041e\u0442\u0440\u0430\u0434\u043d\u043e\u0435"
    ],
    "wof:name":"Otradnoye",
    "wof:placetype":"locality"
},
  "geometry": {"coordinates":[21.8961,54.37633],"type":"Point"}
}