{
  "type": "Feature",
  "properties": {
    "gn:admin1_code":"72.0",
    "gn:asciiname":"Baylovka Vtoraya",
    "gn:country_code":"RU",
    "gn:dem":116,
    "gn:feature_class":"P",
    "gn:feature_code":"PPL",
    "gn:name":"Baylovka Vtoraya",
    "gn:population":0,
    "gn:timezone":"Europe/Moscow",
    "iso:country":"RU",
    "name:nor_x_preferred":[
        "Bajlovka Vtoraja"
    ],
    "name:rus_x_preferred":[
        "\u0411\u0430\u0439\u043b\u043e\u0432\u043a\u0430 \u0412\u0442\u043e\u0440\u0430\u044f"
    ],
    "name:und_x_variant":[
        "Bainovka",
        "Baylovka Vtoraya"
    ],
    "wof:name":"Baylovka Vtoraya",
    "wof:placetype":"locality"
},
  "geometry": {"coordinates":[42.06922,53.28101],"type":"Point"}
}