{
  "type": "Feature",
  "properties": {
    "gn:admin1_code":"20",
    "gn:asciiname":"Chistopolyanskiy",
    "gn:country_code":"RU",
    "gn:dem":473,
    "gn:feature_class":"P",
    "gn:feature_code":"PPL",
    "gn:name":"Chistopolyanskiy",
    "gn:population":0,
    "gn:timezone":"Asia/Irkutsk",
    "iso:country":"RU",
    "name:rus_x_preferred":[
        "\u0427\u0438\u0441\u0442\u043e\u043f\u043e\u043b\u044f\u043d\u0441\u043a\u0438\u0439"
    ],
    "name:und_x_variant":[
        "Chistaya Polyana",
        "Chistopolyanskiy",
        "Vidim"
    ],
    "wof:name":"Chistopolyanskiy",
    "wof:placetype":"locality"
},
  "geometry": {"coordinates":[103.1176,56.3854],"type":"Point"}
}