{
  "type": "Feature",
  "properties": {
    "gn:admin1_code":"90.0",
    "gn:asciiname":"Baraki",
    "gn:country_code":"RU",
    "gn:dem":335,
    "gn:feature_class":"P",
    "gn:feature_code":"PPL",
    "gn:name":"Baraki",
    "gn:population":0,
    "gn:timezone":"Asia/Yekaterinburg",
    "iso:country":"RU",
    "name:ceb_x_preferred":[
        "Baraki"
    ],
    "name:deu_x_preferred":[
        "Baraki"
    ],
    "name:fra_x_preferred":[
        "Baraki"
    ],
    "name:msa_x_preferred":[
        "Baraki"
    ],
    "name:nor_x_preferred":[
        "Baraki"
    ],
    "name:pol_x_preferred":[
        "Baraki"
    ],
    "name:ron_x_preferred":[
        "Baraki"
    ],
    "name:rus_x_preferred":[
        "\u0411\u0430\u0440\u0430\u043a\u0438"
    ],
    "name:swe_x_preferred":[
        "Baraki"
    ],
    "name:ukr_x_preferred":[
        "\u0411\u0430\u0440\u0430\u043a\u0456"
    ],
    "name:wol_x_preferred":[
        "Baraki"
    ],
    "wof:name":"Baraki",
    "wof:placetype":"locality"
},
  "geometry": {"coordinates":[58.43333000000001,57.73333],"type":"Point"}
}