{
  "type": "Feature",
  "properties": {
    "gn:admin1_code":"11",
    "gn:asciiname":"Kargino",
    "gn:country_code":"RU",
    "gn:dem":464,
    "gn:feature_class":"P",
    "gn:feature_code":"PPL",
    "gn:name":"Kargino",
    "gn:population":0,
    "gn:timezone":"Asia/Irkutsk",
    "iso:country":"RU",
    "name:eng_x_preferred":[
        "Kargino"
    ],
    "name:nor_x_preferred":[
        "Kargino"
    ],
    "name:rus_x_preferred":[
        "\u041a\u0430\u0440\u0433\u0438\u043d\u043e"
    ],
    "name:und_x_variant":[
        "\u041a\u0430\u0440\u0433\u0438\u043d\u043e",
        "Kargino"
    ],
    "wof:name":"Kargino",
    "wof:placetype":"locality"
},
  "geometry": {"coordinates":[106.59332999999999,52.08222],"type":"Point"}
}