{
  "type": "Feature",
  "properties": {
    "gn:admin1_code":"13",
    "gn:admin2_code":"498416",
    "gn:asciiname":"Zyuratkul'",
    "gn:country_code":"RU",
    "gn:dem":728,
    "gn:feature_class":"P",
    "gn:feature_code":"PPL",
    "gn:name":"Zyuratkul\u2019",
    "gn:population":86,
    "gn:timezone":"Asia/Yekaterinburg",
    "iso:country":"RU",
    "name:eng_x_preferred":[
        "Zyuratkul'"
    ],
    "name:nor_x_preferred":[
        "Ziuratkul"
    ],
    "name:rus_x_preferred":[
        "\u0417\u044e\u0440\u0430\u0442\u043a\u0443\u043b\u044c"
    ],
    "name:und_x_variant":[
        "Zyuratkul\u2019"
    ],
    "wof:name":"Zyuratkul'",
    "wof:placetype":"locality",
    "wof:population":86
},
  "geometry": {"coordinates":[59.2314,54.9259],"type":"Point"}
}