{
  "type": "Feature",
  "properties": {
    "gn:admin1_code":"37.0",
    "gn:asciiname":"Nikiforovo",
    "gn:country_code":"RU",
    "gn:dem":160,
    "gn:feature_class":"P",
    "gn:feature_code":"PPL",
    "gn:name":"Nikiforovo",
    "gn:population":0,
    "gn:timezone":"Europe/Moscow",
    "iso:country":"RU",
    "name:che_x_preferred":[
        "\u041d\u0438\u043a\u0438\u0444\u043e\u0440\u043e\u0432\u043e"
    ],
    "name:rus_x_preferred":[
        "\u041d\u0438\u043a\u0438\u0444\u043e\u0440\u043e\u0432\u043e"
    ],
    "wof:name":"Nikiforovo",
    "wof:placetype":"locality"
},
  "geometry": {"coordinates":[41.56446,57.57475],"type":"Point"}
}