{
  "type": "Feature",
  "properties": {
    "gn:admin1_code":"33.0",
    "gn:asciiname":"Makoldino",
    "gn:country_code":"RU",
    "gn:dem":121,
    "gn:feature_class":"P",
    "gn:feature_code":"PPL",
    "gn:name":"Makoldino",
    "gn:population":0,
    "gn:timezone":"Europe/Kirov",
    "iso:country":"RU",
    "name:rus_x_preferred":[
        "\u041c\u0430\u043a\u043e\u043b\u0434\u0438\u043d\u043e"
    ],
    "name:und_x_variant":[
        "\u041c\u0430\u043a\u043e\u043b\u0434\u0438\u043d\u043e"
    ],
    "wof:name":"Makoldino",
    "wof:placetype":"locality"
},
  "geometry": {"coordinates":[48.35062,58.48308000000001],"type":"Point"}
}