{
  "type": "Feature",
  "properties": {
    "gn:admin1_code":"42.0",
    "gn:asciiname":"Muta-Kyulya",
    "gn:country_code":"RU",
    "gn:dem":94,
    "gn:feature_class":"P",
    "gn:feature_code":"PPL",
    "gn:name":"Muta-Kyulya",
    "gn:population":0,
    "gn:timezone":"Europe/Moscow",
    "iso:country":"RU",
    "name:fin_x_preferred":[
        "Mutakyl\u00e4"
    ],
    "wof:name":"Muta-Kyulya",
    "wof:placetype":"locality"
},
  "geometry": {"coordinates":[29.96501,59.64474000000001],"type":"Point"}
}