{
  "type": "Feature",
  "properties": {
    "gn:admin1_code":"41",
    "gn:asciiname":"Polsela Goryainovo",
    "gn:country_code":"RU",
    "gn:dem":226,
    "gn:feature_class":"P",
    "gn:feature_code":"PPL",
    "gn:name":"Polsela Goryainovo",
    "gn:population":0,
    "gn:timezone":"Europe/Moscow",
    "iso:country":"RU",
    "name:rus_x_preferred":[
        "\u041f\u043e\u043b\u0441\u0435\u043b\u0430 \u0413\u043e\u0440\u044f\u0438\u043d\u043e\u0432\u043e"
    ],
    "name:und_x_variant":[
        "\u041f\u043e\u043b\u0441\u0435\u043b\u0430 \u0413\u043e\u0440\u044f\u0438\u043d\u043e\u0432\u043e"
    ],
    "wof:name":"Polsela Goryainovo",
    "wof:placetype":"locality"
},
  "geometry": {"coordinates":[36.4325,52.26667],"type":"Point"}
}