{
  "type": "Feature",
  "properties": {
    "gn:admin1_code":"6.0",
    "gn:asciiname":"Verkhov'ye",
    "gn:country_code":"RU",
    "gn:dem":101,
    "gn:feature_class":"P",
    "gn:feature_code":"PPL",
    "gn:name":"Verkhov\u2019ye",
    "gn:population":0,
    "gn:timezone":"Europe/Moscow",
    "iso:country":"RU",
    "name:rus_x_preferred":[
        "\u0412\u0435\u0440\u0445\u043e\u0432\u044c\u0435"
    ],
    "name:und_x_variant":[
        "Verkhov\u2019ye"
    ],
    "wof:name":"Verkhov'ye",
    "wof:placetype":"locality"
},
  "geometry": {"coordinates":[40.9211,61.9027],"type":"Point"}
}