{
  "type": "Feature",
  "properties": {
    "gn:admin1_code":"88.0",
    "gn:asciiname":"Dvoryankino",
    "gn:country_code":"RU",
    "gn:dem":99,
    "gn:feature_class":"P",
    "gn:feature_code":"PPL",
    "gn:name":"Dvoryankino",
    "gn:population":0,
    "gn:timezone":"Europe/Moscow",
    "iso:country":"RU",
    "name:rus_x_preferred":[
        "\u0414\u0432\u043e\u0440\u044f\u043d\u043a\u0438\u043d\u043e"
    ],
    "wof:name":"Dvoryankino",
    "wof:placetype":"locality"
},
  "geometry": {"coordinates":[40.78874,58.36006],"type":"Point"}
}