{
  "type": "Feature",
  "properties": {
    "gn:admin1_code":"10",
    "gn:asciiname":"Pupkovo",
    "gn:country_code":"RU",
    "gn:dem":177,
    "gn:feature_class":"P",
    "gn:feature_code":"PPL",
    "gn:name":"Pupkovo",
    "gn:population":0,
    "gn:timezone":"Europe/Moscow",
    "iso:country":"RU",
    "name:eng_x_preferred":[
        "Pupkovo"
    ],
    "name:nor_x_preferred":[
        "Pupkovo"
    ],
    "name:rus_x_preferred":[
        "\u041f\u0443\u043f\u043a\u043e\u0432\u043e"
    ],
    "name:und_x_variant":[
        "\u041f\u0443\u043f\u043a\u043e\u0432\u043e",
        "Pupkovo"
    ],
    "wof:name":"Pupkovo",
    "wof:placetype":"locality"
},
  "geometry": {"coordinates":[34.45121,53.51333],"type":"Point"}
}