{
  "type": "Feature",
  "properties": {
    "gn:admin1_code":"05",
    "gn:asciiname":"Nekrasovka",
    "gn:country_code":"RU",
    "gn:dem":162,
    "gn:feature_class":"P",
    "gn:feature_code":"PPL",
    "gn:name":"Nekrasovka",
    "gn:population":0,
    "gn:timezone":"Asia/Yakutsk",
    "iso:country":"RU",
    "name:eng_x_preferred":[
        "Nekrasovskoye"
    ],
    "name:rus_x_preferred":[
        "\u041d\u0435\u043a\u0440\u0430\u0441\u043e\u0432\u0441\u043a\u0438\u0439"
    ],
    "name:rus_x_variant":[
        "\u041d\u0435\u043a\u0440\u0430\u0441\u043e\u0432\u043a\u0430"
    ],
    "name:und_x_variant":[
        "Nekrasovskiy",
        "\u041d\u0435\u043a\u0440\u0430\u0441\u043e\u0432\u043a\u0430",
        "Nekrasovskoye",
        "Nekrasovka"
    ],
    "wof:name":"Nekrasovka",
    "wof:placetype":"locality"
},
  "geometry": {"coordinates":[128.09191999999999,50.34429],"type":"Point"}
}