{
  "type": "Feature",
  "properties": {
    "gn:admin1_code":"88",
    "gn:asciiname":"Oshalayevo",
    "gn:country_code":"RU",
    "gn:dem":125,
    "gn:feature_class":"P",
    "gn:feature_code":"PPL",
    "gn:name":"Oshalayevo",
    "gn:population":0,
    "gn:timezone":"Europe/Moscow",
    "iso:country":"RU",
    "name:rus_x_preferred":[
        "\u041e\u0448\u0430\u043b\u0430\u0435\u0432\u043e"
    ],
    "name:und_x_variant":[
        "\u041e\u0448\u0430\u043b\u0430\u0435\u0432\u043e"
    ],
    "wof:name":"Oshalayevo",
    "wof:placetype":"locality"
},
  "geometry": {"coordinates":[37.9968,57.3773],"type":"Point"}
}