{
  "type": "Feature",
  "properties": {
    "gn:admin1_code":"84",
    "gn:asciiname":"Il'icha",
    "gn:country_code":"RU",
    "gn:dem":21,
    "gn:feature_class":"P",
    "gn:feature_code":"PPL",
    "gn:name":"Il\u2019icha",
    "gn:population":0,
    "gn:timezone":"Europe/Volgograd",
    "iso:country":"RU",
    "name:rus_x_preferred":[
        "\u0418\u043b\u044c\u0438\u0447\u0430"
    ],
    "name:und_x_variant":[
        "Borisov",
        "Put\u2019 Il\u2019icha",
        "Imeni Il\u2019icha",
        "Il\u2019icha"
    ],
    "wof:name":"Il'icha",
    "wof:placetype":"locality"
},
  "geometry": {"coordinates":[45.85611,48.92722],"type":"Point"}
}