{
  "type": "Feature",
  "properties": {
    "gn:country":"RU",
    "gn:fcode":"PPL",
    "gn:population":2363,
    "iso:country":"RU",
    "name:ara_x_preferred":[
        "\u0641\u0627\u0633\u064a\u0644\u064a\u064a\u0641\u0633\u0643\u064a\u064a \u0645\u0648\u0643"
    ],
    "name:che_x_preferred":[
        "\u0412\u0430\u0441\u0438\u043b\u044c\u0435\u0432\u0441\u043a\u0438\u0439 \u041c\u043e\u0445"
    ],
    "name:eng_x_preferred":[
        "Vasil'yevskiy Mokh"
    ],
    "name:eng_x_variant":[
        "Vasilyevsky Mokh"
    ],
    "name:nor_x_preferred":[
        "Vasiljevskij Mokh"
    ],
    "name:pol_x_preferred":[
        "Wasiljewskij Moch"
    ],
    "name:rus_x_preferred":[
        "\u0412\u0430\u0441\u0438\u043b\u044c\u0435\u0432\u0441\u043a\u0438\u0439 \u041c\u043e\u0445"
    ],
    "name:srp_x_preferred":[
        "\u0412\u0430\u0441\u0438\u0459\u0435\u0432\u0441\u043a\u0438 \u041c\u043e\u0445"
    ],
    "name:und_x_variant":[
        "Tsentral\u2019nyy"
    ],
    "qs:name":"Vasil'yevskiy Mokh",
    "qs:name_adm0":"Russia",
    "qs:name_adm1":"Tver Oblast",
    "qs:photos_9r":0,
    "qs:photos_sr":0,
    "qs:placetype":"Town",
    "qs:pop_sr":"4",
    "wof:name":"Vasil'yevskiy Mokh",
    "wof:placetype":"locality",
    "wof:population":2363
},
  "geometry": {"coordinates":[35.91897,57.01316],"type":"Point"}
}