{
  "type": "Feature",
  "properties": {
    "gn:country":"RU",
    "gn:fcode":"PPL",
    "gn:population":2363,
    "iso:country":"RU",
    "name:ara_x_preferred":[
        "\u0641\u0627\u0633\u064a\u0644\u064a\u064a\u0641\u0633\u0643\u064a\u064a \u0645\u0648\u0643"
    ],
    "name:azb_x_preferred":[
        "\u0648\u0627\u0633\u06cc\u0644\u06cc\u0648\u0627\u06cc\u0633\u06a9\u0627\u06cc \u0645\u0648\u062e"
    ],
    "name:bel_x_preferred":[
        "\u0412\u0430\u0441\u0456\u043b\u044c\u0435\u045e\u0441\u043a\u0456 \u041c\u043e\u0445"
    ],
    "name:ceb_x_preferred":[
        "Vasil'yevskiy Mokh"
    ],
    "name:che_x_preferred":[
        "\u0412\u0430\u0441\u0438\u043b\u044c\u0435\u0432\u0441\u043a\u0438\u0439 \u041c\u043e\u0445"
    ],
    "name:crh_x_preferred":[
        "Vasilyevskiy Moh"
    ],
    "name:eng_x_preferred":[
        "Vasil'yevskiy Mokh"
    ],
    "name:eng_x_variant":[
        "Vasilyevsky Mokh"
    ],
    "name:nld_x_preferred":[
        "Vasil'yevskiy Mokh"
    ],
    "name:nor_x_preferred":[
        "Vasiljevskij Mokh"
    ],
    "name:pol_x_preferred":[
        "Wasiljewskij Moch"
    ],
    "name:rus_x_preferred":[
        "\u0412\u0430\u0441\u0438\u043b\u044c\u0435\u0432\u0441\u043a\u0438\u0439 \u041c\u043e\u0445"
    ],
    "name:spa_x_preferred":[
        "Vas\u00edlyevski Moj"
    ],
    "name:srp_x_preferred":[
        "\u0412\u0430\u0441\u0438\u0459\u0435\u0432\u0441\u043a\u0438 \u041c\u043e\u0445"
    ],
    "name:ukr_x_preferred":[
        "\u0412\u0430\u0441\u0438\u043b\u0456\u0432\u0441\u044c\u043a\u0438\u0439 \u041c\u043e\u0445"
    ],
    "name:und_x_variant":[
        "Tsentral\u2019nyy"
    ],
    "name:zho_x_preferred":[
        "\u74e6\u897f\u91cc\u8036\u592b\u65af\u57fa\u83ab\u8d6b"
    ],
    "qs:name":"Vasil'yevskiy Mokh",
    "qs:name_adm0":"Russia",
    "qs:name_adm1":"Tver Oblast",
    "qs:photos_9r":0,
    "qs:photos_sr":0,
    "qs:placetype":"Town",
    "qs:pop_sr":"4",
    "wof:name":"Vasil'yevskiy Mokh",
    "wof:placetype":"locality",
    "wof:population":2363
},
  "geometry": {"coordinates":[35.91897,57.01316],"type":"Point"}
}