{
  "type": "Feature",
  "properties": {
    "gn:admin1_code":"25",
    "gn:asciiname":"Mityukovo",
    "gn:country_code":"RU",
    "gn:dem":187,
    "gn:feature_class":"P",
    "gn:feature_code":"PPL",
    "gn:name":"Mityukovo",
    "gn:population":0,
    "gn:timezone":"Europe/Moscow",
    "iso:country":"RU",
    "name:nor_x_preferred":[
        "Mitjukovo"
    ],
    "name:rus_x_preferred":[
        "\u041c\u0438\u0442\u044e\u043a\u043e\u0432\u043e"
    ],
    "wof:name":"Mityukovo",
    "wof:placetype":"locality"
},
  "geometry": {"coordinates":[36.52347,54.49858],"type":"Point"}
}