{
  "type": "Feature",
  "properties": {
    "gn:admin1_code":"79",
    "gn:asciiname":"Urbyun",
    "gn:country_code":"RU",
    "gn:dem":520,
    "gn:feature_class":"P",
    "gn:feature_code":"PPL",
    "gn:name":"Urbyun",
    "gn:population":0,
    "gn:timezone":"Asia/Krasnoyarsk",
    "iso:country":"RU",
    "wof:name":"Urbyun",
    "wof:placetype":"locality"
},
  "geometry": {"coordinates":[92.40000000000001,51.63333],"type":"Point"}
}