{
  "type": "Feature",
  "properties": {
    "gn:admin1_code":"85",
    "gn:asciiname":"Stupino",
    "gn:country_code":"RU",
    "gn:dem":116,
    "gn:feature_class":"P",
    "gn:feature_code":"PPL",
    "gn:name":"Stupino",
    "gn:population":0,
    "gn:timezone":"Europe/Moscow",
    "iso:country":"RU",
    "name:rus_x_preferred":[
        "\u0421\u0442\u0443\u043f\u0438\u043d\u043e"
    ],
    "wof:name":"Stupino",
    "wof:placetype":"locality"
},
  "geometry": {"coordinates":[37.7713,58.7298],"type":"Point"}
}