{
  "type": "Feature",
  "properties": {
    "gn:admin1_code":"45",
    "gn:asciiname":"Muza",
    "gn:country_code":"RU",
    "gn:dem":87,
    "gn:feature_class":"P",
    "gn:feature_code":"PPL",
    "gn:name":"Muza",
    "gn:population":0,
    "gn:timezone":"Europe/Moscow",
    "iso:country":"RU",
    "name:ceb_x_preferred":[
        "Muza"
    ],
    "name:deu_x_preferred":[
        "Muza"
    ],
    "name:fra_x_preferred":[
        "Muza"
    ],
    "name:pol_x_preferred":[
        "Muza"
    ],
    "name:rus_x_preferred":[
        "\u041c\u0443\u0437\u0430"
    ],
    "name:spa_x_preferred":[
        "Muza"
    ],
    "name:swe_x_preferred":[
        "Muza"
    ],
    "wof:name":"Muza",
    "wof:placetype":"locality"
},
  "geometry": {"coordinates":[45.88354,56.51982],"type":"Point"}
}