{
  "type": "Feature",
  "properties": {
    "gn:admin1_code":"41",
    "gn:asciiname":"Lyubitskoye",
    "gn:country_code":"RU",
    "gn:dem":152,
    "gn:feature_class":"P",
    "gn:feature_code":"PPL",
    "gn:name":"Lyubitskoye",
    "gn:population":0,
    "gn:timezone":"Europe/Moscow",
    "iso:country":"RU",
    "name:rus_x_preferred":[
        "\u041b\u044e\u0431\u0438\u0446\u043a\u043e\u0435"
    ],
    "name:und_x_variant":[
        "Lyubitskaya",
        "Lyubitskoye"
    ],
    "wof:name":"Lyubitskoye",
    "wof:placetype":"locality"
},
  "geometry": {"coordinates":[35.57389000000001,51.57861],"type":"Point"}
}