{
  "type": "Feature",
  "properties": {
    "gn:admin1_code":"33.0",
    "gn:asciiname":"Temnyakovshchina",
    "gn:country_code":"RU",
    "gn:dem":161,
    "gn:feature_class":"P",
    "gn:feature_code":"PPL",
    "gn:name":"Temnyakovshchina",
    "gn:population":0,
    "gn:timezone":"Europe/Kirov",
    "iso:country":"RU",
    "name:rus_x_preferred":[
        "\u0422\u0435\u043c\u043d\u044f\u043a\u043e\u0432\u0449\u0438\u043d\u0430"
    ],
    "wof:name":"Temnyakovshchina",
    "wof:placetype":"locality"
},
  "geometry": {"coordinates":[48.64803,58.66212],"type":"Point"}
}