{
  "type": "Feature",
  "properties": {
    "gn:admin1_code":"20",
    "gn:asciiname":"Solyanka",
    "gn:country_code":"RU",
    "gn:dem":478,
    "gn:feature_class":"P",
    "gn:feature_code":"PPL",
    "gn:name":"Solyanka",
    "gn:population":0,
    "gn:timezone":"Asia/Irkutsk",
    "iso:country":"RU",
    "name:eng_x_preferred":[
        "Solyanka"
    ],
    "name:nor_x_preferred":[
        "Soljanka"
    ],
    "name:rus_x_preferred":[
        "\u0421\u043e\u043b\u044f\u043d\u043a\u0430"
    ],
    "name:und_x_variant":[
        "Solyanskiy",
        "Solyarskiy",
        "Solyarski",
        "Solyanka",
        "\u0421\u043e\u043b\u044f\u043d\u043a\u0430"
    ],
    "wof:name":"Solyanka",
    "wof:placetype":"locality"
},
  "geometry": {"coordinates":[104.61888999999999,52.67222],"type":"Point"}
}