{
  "type": "Feature",
  "properties": {
    "gn:admin1_code":"40",
    "gn:asciiname":"Nechunayeva",
    "gn:country_code":"RU",
    "gn:dem":70,
    "gn:feature_class":"P",
    "gn:feature_code":"PPL",
    "gn:name":"Nechunayeva",
    "gn:population":0,
    "gn:timezone":"Asia/Yekaterinburg",
    "iso:country":"RU",
    "name:eng_x_preferred":[
        "Nechunayeva"
    ],
    "name:rus_x_preferred":[
        "\u041d\u0435\u0447\u0443\u043d\u0430\u0435\u0432\u043e"
    ],
    "name:rus_x_variant":[
        "\u041d\u0435\u0447\u0443\u043d\u0430\u0435\u0432\u0430"
    ],
    "name:und_x_variant":[
        "\u041d\u0435\u0447\u0443\u043d\u0430\u0435\u0432\u0430",
        "Nechunayeva"
    ],
    "wof:name":"Nechunayeva",
    "wof:placetype":"locality"
},
  "geometry": {"coordinates":[64.322,56.0502],"type":"Point"}
}