{
  "type": "Feature",
  "properties": {
    "gn:admin1_code":"64",
    "gn:asciiname":"Yasenki",
    "gn:country_code":"RU",
    "gn:dem":245,
    "gn:feature_class":"P",
    "gn:feature_code":"PPL",
    "gn:name":"Yasenki",
    "gn:population":0,
    "gn:timezone":"Asia/Sakhalin",
    "iso:country":"RU",
    "wof:name":"Yasenki",
    "wof:placetype":"locality"
},
  "geometry": {"coordinates":[142.13333,50.55],"type":"Point"}
}