{
  "type": "Feature",
  "properties": {
    "gn:admin1_code":"47",
    "gn:asciiname":"Sukharevo",
    "gn:country_code":"RU",
    "gn:dem":184,
    "gn:feature_class":"P",
    "gn:feature_code":"PPL",
    "gn:name":"Sukharevo",
    "gn:population":452,
    "gn:timezone":"Europe/Moscow",
    "iso:country":"RU",
    "name:rus_x_preferred":[
        "\u0421\u0443\u0445\u0430\u0440\u0435\u0432\u043e"
    ],
    "wof:name":"Sukharevo",
    "wof:placetype":"locality",
    "wof:population":452
},
  "geometry": {"coordinates":[37.51445,56.08133],"type":"Point"}
}