{
  "type": "Feature",
  "properties": {
    "gn:admin1_code":"45.0",
    "gn:asciiname":"Pibakhtino",
    "gn:country_code":"RU",
    "gn:dem":191,
    "gn:feature_class":"P",
    "gn:feature_code":"PPL",
    "gn:name":"Pibakhtino",
    "gn:population":0,
    "gn:timezone":"Europe/Moscow",
    "iso:country":"RU",
    "name:rus_x_preferred":[
        "\u041f\u0438\u0431\u0430\u0445\u0442\u0438\u043d\u043e"
    ],
    "name:und_x_variant":[
        "\u041f\u0438\u0431\u0430\u0445\u0442\u0438\u043d\u043e"
    ],
    "wof:name":"Pibakhtino",
    "wof:placetype":"locality"
},
  "geometry": {"coordinates":[48.70972,56.85694],"type":"Point"}
}