{
  "type": "Feature",
  "properties": {
    "gn:admin1_code":"75",
    "gn:asciiname":"Lomovka Pervaya",
    "gn:cc2":"RU",
    "gn:country_code":"RU",
    "gn:dem":73,
    "gn:feature_class":"P",
    "gn:feature_code":"PPL",
    "gn:name":"Lomovka Pervaya",
    "gn:population":0,
    "gn:timezone":"Asia/Tomsk",
    "iso:country":"RU",
    "name:rus_x_preferred":[
        "\u041b\u043e\u043c\u043e\u0432\u043a\u0430 \u041f\u0435\u0440\u0432\u0430\u044f"
    ],
    "name:und_x_variant":[
        "Lomovskoy",
        "Lomovka Pervaya"
    ],
    "wof:name":"Lomovka Pervaya",
    "wof:placetype":"locality"
},
  "geometry": {"coordinates":[82.68333,58.53333000000001],"type":"Point"}
}