{
  "type": "Feature",
  "properties": {
    "gn:admin1_code":"56",
    "gn:asciiname":"Sennoy",
    "gn:country_code":"RU",
    "gn:dem":245,
    "gn:feature_class":"P",
    "gn:feature_code":"PPL",
    "gn:name":"Sennoy",
    "gn:population":0,
    "gn:timezone":"Europe/Moscow",
    "iso:country":"RU",
    "name:ceb_x_preferred":[
        "Sennoy"
    ],
    "name:rus_x_preferred":[
        "\u0421\u0435\u043d\u043d\u043e\u0439"
    ],
    "name:und_x_variant":[
        "\u0421\u0435\u043d\u043d\u043e\u0439"
    ],
    "wof:name":"Sennoy",
    "wof:placetype":"locality"
},
  "geometry": {"coordinates":[37.58333,52.95],"type":"Point"}
}