{
  "type": "Feature",
  "properties": {
    "gn:admin1_code":"86.0",
    "gn:asciiname":"Serobabin",
    "gn:country_code":"RU",
    "gn:dem":171,
    "gn:feature_class":"P",
    "gn:feature_code":"PPL",
    "gn:name":"Serobabin",
    "gn:population":0,
    "gn:timezone":"Europe/Moscow",
    "iso:country":"RU",
    "wof:name":"Serobabin",
    "wof:placetype":"locality"
},
  "geometry": {"coordinates":[39.8025,49.9525],"type":"Point"}
}