{
  "type": "Feature",
  "properties": {
    "gn:admin1_code":"53",
    "gn:asciiname":"Ust'-Kamenka",
    "gn:country_code":"RU",
    "gn:dem":198,
    "gn:feature_class":"P",
    "gn:feature_code":"PPL",
    "gn:name":"Ust\u2019-Kamenka",
    "gn:population":0,
    "gn:timezone":"Asia/Novosibirsk",
    "iso:country":"RU",
    "name:eng_x_preferred":[
        "Ust'-Kamenka"
    ],
    "name:nor_x_preferred":[
        "Ust-Kamenka"
    ],
    "name:rus_x_preferred":[
        "\u0423\u0441\u0442\u044c-\u041a\u0430\u043c\u0435\u043d\u043a\u0430"
    ],
    "name:und_x_variant":[
        "Ust\u2019-Kamenskiy",
        "Ust\u2019-Kamenka"
    ],
    "wof:name":"Ust'-Kamenka",
    "wof:placetype":"locality"
},
  "geometry": {"coordinates":[83.8463,54.995],"type":"Point"}
}