{
  "type": "Feature",
  "properties": {
    "gn:admin1_code":"86",
    "gn:asciiname":"Somovo",
    "gn:country_code":"RU",
    "gn:dem":209,
    "gn:feature_class":"P",
    "gn:feature_code":"PPL",
    "gn:name":"Somovo",
    "gn:population":0,
    "gn:timezone":"Europe/Moscow",
    "iso:country":"RU",
    "name:rus_x_preferred":[
        "\u0421\u043e\u043c\u043e\u0432\u043e"
    ],
    "wof:name":"Somovo",
    "wof:placetype":"locality"
},
  "geometry": {"coordinates":[38.8002,51.93899999999999],"type":"Point"}
}