{
  "type": "Feature",
  "properties": {
    "gn:admin1_code":"38",
    "gn:asciiname":"Tsygankov Aul",
    "gn:country_code":"RU",
    "gn:dem":186,
    "gn:feature_class":"P",
    "gn:feature_code":"PPL",
    "gn:name":"Tsygankov Aul",
    "gn:population":0,
    "gn:timezone":"Europe/Moscow",
    "iso:country":"RU",
    "name:rus_x_preferred":[
        "\u0426\u044b\u0433\u0430\u043d\u043a\u043e\u0432 \u0410\u0443\u043b"
    ],
    "wof:name":"Tsygankov Aul",
    "wof:placetype":"locality"
},
  "geometry": {"coordinates":[38.4496,44.4808],"type":"Point"}
}