{
  "type": "Feature",
  "properties": {
    "gn:admin1_code":"88",
    "gn:asciiname":"Militino",
    "gn:country_code":"RU",
    "gn:dem":102,
    "gn:feature_class":"P",
    "gn:feature_code":"PPL",
    "gn:name":"Militino",
    "gn:population":0,
    "gn:timezone":"Europe/Moscow",
    "iso:country":"RU",
    "name:rus_x_preferred":[
        "\u041c\u0438\u043b\u0438\u0442\u0438\u043d\u043e"
    ],
    "wof:name":"Militino",
    "wof:placetype":"locality"
},
  "geometry": {"coordinates":[39.78508,57.30591999999999],"type":"Point"}
}