{
  "type": "Feature",
  "properties": {
    "gn:admin1_code":"84.0",
    "gn:asciiname":"Dikaya Balka",
    "gn:cc2":"RU",
    "gn:country_code":"RU",
    "gn:dem":67,
    "gn:feature_class":"P",
    "gn:feature_code":"PPL",
    "gn:name":"Dikaya Balka",
    "gn:population":0,
    "gn:timezone":"Europe/Volgograd",
    "iso:country":"RU",
    "name:rus_x_preferred":[
        "\u0414\u0438\u043a\u0430\u044f \u0411\u0430\u043b\u043a\u0430"
    ],
    "name:und_x_variant":[
        "Dikova Balka",
        "Dikaya Balka",
        "\u0414\u0438\u043a\u0430\u044f \u0411\u0430\u043b\u043a\u0430"
    ],
    "wof:name":"Dikaya Balka",
    "wof:placetype":"locality"
},
  "geometry": {"coordinates":[44.65,49.06667],"type":"Point"}
}