{
  "type": "Feature",
  "properties": {
    "gn:admin1_code":"20",
    "gn:asciiname":"Shunta",
    "gn:country_code":"RU",
    "gn:dem":454,
    "gn:feature_class":"P",
    "gn:feature_code":"PPL",
    "gn:name":"Shunta",
    "gn:population":0,
    "gn:timezone":"Asia/Irkutsk",
    "iso:country":"RU",
    "name:rus_x_preferred":[
        "\u0428\u0443\u043d\u0442\u0430"
    ],
    "wof:name":"Shunta",
    "wof:placetype":"locality"
},
  "geometry": {"coordinates":[103.82089999999999,53.1587],"type":"Point"}
}