{
  "type": "Feature",
  "properties": {
    "gn:admin1_code":"41",
    "gn:asciiname":"Rakitinka",
    "gn:country_code":"RU",
    "gn:dem":220,
    "gn:feature_class":"P",
    "gn:feature_code":"PPL",
    "gn:name":"Rakitinka",
    "gn:population":0,
    "gn:timezone":"Europe/Moscow",
    "iso:country":"RU",
    "name:rus_x_preferred":[
        "\u0420\u0430\u043a\u0438\u0442\u0438\u043d\u043a\u0430"
    ],
    "name:und_x_variant":[
        "Bol\u2019shaya Psinka",
        "Rakitinka"
    ],
    "wof:name":"Rakitinka",
    "wof:placetype":"locality"
},
  "geometry": {"coordinates":[36.50004000000001,51.15293],"type":"Point"}
}