{
  "type": "Feature",
  "properties": {
    "gn:admin1_code":"93",
    "gn:asciiname":"Verkhniye Kumaki",
    "gn:country_code":"RU",
    "gn:dem":486,
    "gn:feature_class":"P",
    "gn:feature_code":"PPL",
    "gn:name":"Verkhniye Kumaki",
    "gn:population":0,
    "gn:timezone":"Asia/Chita",
    "iso:country":"RU",
    "name:eng_x_preferred":[
        "Verkhniye Kumaki"
    ],
    "name:nor_x_preferred":[
        "Lev.Kumaki"
    ],
    "name:rus_x_preferred":[
        "\u041b\u0435\u0432.\u041a\u0443\u043c\u0430\u043a\u0438"
    ],
    "name:und_x_variant":[
        "Kumaki",
        "Verkhnyaya Kumaki"
    ],
    "wof:name":"Verkhniye Kumaki",
    "wof:placetype":"locality"
},
  "geometry": {"coordinates":[116.34999999999999,52.08333],"type":"Point"}
}