{
  "type": "Feature",
  "properties": {
    "gn:admin1_code":"67.0",
    "gn:asciiname":"Aleksandrovka Vtoraya",
    "gn:country_code":"RU",
    "gn:dem":164,
    "gn:feature_class":"P",
    "gn:feature_code":"PPL",
    "gn:name":"Aleksandrovka Vtoraya",
    "gn:population":0,
    "gn:timezone":"Europe/Saratov",
    "iso:country":"RU",
    "name:nor_x_preferred":[
        "Aleksandrovka Vtoraja"
    ],
    "name:rus_x_preferred":[
        "\u0410\u043b\u0435\u043a\u0441\u0430\u043d\u0434\u0440\u043e\u0432\u043a\u0430 \u0412\u0442\u043e\u0440\u0430\u044f"
    ],
    "name:und_x_variant":[
        "Staraya Aleksandrovka",
        "Vtoraya Aleksandrovka",
        "Staro-Aleksandrovka",
        "Aleksandrovka Vtoraya"
    ],
    "wof:name":"Aleksandrovka Vtoraya",
    "wof:placetype":"locality"
},
  "geometry": {"coordinates":[44.62219,51.59213],"type":"Point"}
}