{
  "type": "Feature",
  "properties": {
    "gn:admin1_code":"81",
    "gn:asciiname":"Kamyshovka",
    "gn:country_code":"RU",
    "gn:dem":77,
    "gn:feature_class":"P",
    "gn:feature_code":"PPL",
    "gn:name":"Kamyshovka",
    "gn:population":0,
    "gn:timezone":"Europe/Ulyanovsk",
    "iso:country":"RU",
    "name:nor_x_preferred":[
        "Kamysjovka"
    ],
    "name:rus_x_preferred":[
        "\u041a\u0430\u043c\u044b\u0448\u043e\u0432\u043a\u0430"
    ],
    "name:und_x_variant":[
        "Kamyshevka",
        "Kamyshovka"
    ],
    "wof:name":"Kamyshovka",
    "wof:placetype":"locality"
},
  "geometry": {"coordinates":[48.95966,54.2431],"type":"Point"}
}