{
  "type": "Feature",
  "properties": {
    "gn:admin1_code":"61",
    "gn:asciiname":"Yergeni",
    "gn:country_code":"RU",
    "gn:dem":78,
    "gn:feature_class":"P",
    "gn:feature_code":"PPL",
    "gn:name":"Yergeni",
    "gn:population":0,
    "gn:timezone":"Europe/Moscow",
    "iso:country":"RU",
    "name:rus_x_preferred":[
        "\u0415\u0440\u0433\u0435\u043d\u0438"
    ],
    "wof:name":"Yergeni",
    "wof:placetype":"locality"
},
  "geometry": {"coordinates":[43.143,47.1935],"type":"Point"}
}