{
  "type": "Feature",
  "properties": {
    "gn:admin1_code":"85.0",
    "gn:asciiname":"Rogachikha",
    "gn:country_code":"RU",
    "gn:dem":120,
    "gn:feature_class":"P",
    "gn:feature_code":"PPL",
    "gn:name":"Rogachikha",
    "gn:population":0,
    "gn:timezone":"Europe/Moscow",
    "iso:country":"RU",
    "name:rus_x_preferred":[
        "\u0420\u043e\u0433\u0430\u0447\u0438\u0445\u0430"
    ],
    "wof:name":"Rogachikha",
    "wof:placetype":"locality"
},
  "geometry": {"coordinates":[41.9969,60.71],"type":"Point"}
}