{
  "type": "Feature",
  "properties": {
    "gn:admin1_code":"93",
    "gn:asciiname":"Bogachi",
    "gn:country_code":"RU",
    "gn:dem":533,
    "gn:feature_class":"P",
    "gn:feature_code":"PPL",
    "gn:name":"Bogachi",
    "gn:population":0,
    "gn:timezone":"Asia/Chita",
    "iso:country":"RU",
    "name:rus_x_preferred":[
        "\u0411\u043e\u0433\u0430\u0447\u0438"
    ],
    "wof:name":"Bogachi",
    "wof:placetype":"locality"
},
  "geometry": {"coordinates":[118.31667,49.75],"type":"Point"}
}