{
  "type": "Feature",
  "properties": {
    "gn:admin1_code":"8.0",
    "gn:asciiname":"Berseneva",
    "gn:country_code":"RU",
    "gn:dem":292,
    "gn:feature_class":"P",
    "gn:feature_code":"PPL",
    "gn:name":"Berseneva",
    "gn:population":0,
    "gn:timezone":"Asia/Yekaterinburg",
    "iso:country":"RU",
    "name:nor_x_preferred":[
        "Berseneva"
    ],
    "name:rus_x_preferred":[
        "\u0411\u0435\u0440\u0441\u0435\u043d\u0435\u0432\u0430"
    ],
    "wof:name":"Berseneva",
    "wof:placetype":"locality"
},
  "geometry": {"coordinates":[58.71666999999999,56.06667],"type":"Point"}
}