{
  "type": "Feature",
  "properties": {
    "gn:admin1_code":"90",
    "gn:asciiname":"Laki",
    "gn:country_code":"RU",
    "gn:dem":194,
    "gn:feature_class":"P",
    "gn:feature_code":"PPL",
    "gn:name":"Laki",
    "gn:population":0,
    "gn:timezone":"Asia/Yekaterinburg",
    "iso:country":"RU",
    "name:rus_x_preferred":[
        "\u041b\u0430\u043a\u0438"
    ],
    "name:und_x_variant":[
        "\u041b\u0430\u043a\u0438"
    ],
    "wof:name":"Laki",
    "wof:placetype":"locality"
},
  "geometry": {"coordinates":[57.63333000000001,58.33333],"type":"Point"}
}