{
  "type": "Feature",
  "properties": {
    "gn:admin1_code":"90",
    "gn:asciiname":"Laki",
    "gn:country_code":"RU",
    "gn:dem":194,
    "gn:feature_class":"P",
    "gn:feature_code":"PPL",
    "gn:name":"Laki",
    "gn:population":0,
    "gn:timezone":"Asia/Yekaterinburg",
    "iso:country":"RU",
    "name:afr_x_preferred":[
        "Laki"
    ],
    "name:ara_x_preferred":[
        "\u0644\u0627\u0643\u064a"
    ],
    "name:ast_x_preferred":[
        "Laki"
    ],
    "name:bel_x_preferred":[
        "\u041b\u0430\u043a\u0456"
    ],
    "name:cat_x_preferred":[
        "Laki"
    ],
    "name:ceb_x_preferred":[
        "Laki"
    ],
    "name:ces_x_preferred":[
        "Laki"
    ],
    "name:dan_x_preferred":[
        "Laki"
    ],
    "name:deu_x_preferred":[
        "Laki-Krater"
    ],
    "name:ell_x_preferred":[
        "\u039b\u03ac\u03ba\u03b9"
    ],
    "name:epo_x_preferred":[
        "Lakag\u00edgar"
    ],
    "name:est_x_preferred":[
        "Laki"
    ],
    "name:eus_x_preferred":[
        "Laki"
    ],
    "name:fas_x_preferred":[
        "\u0644\u06a9\u06cc"
    ],
    "name:fin_x_preferred":[
        "Lakagigar"
    ],
    "name:fra_x_preferred":[
        "Lakag\u00edgar"
    ],
    "name:hrv_x_preferred":[
        "Laki"
    ],
    "name:ind_x_preferred":[
        "Lakag\u00edgar"
    ],
    "name:isl_x_preferred":[
        "Lakag\u00edgar"
    ],
    "name:ita_x_preferred":[
        "Laki"
    ],
    "name:jpn_x_preferred":[
        "\u30e9\u30ad\u706b\u5c71"
    ],
    "name:kat_x_preferred":[
        "\u10da\u10d0\u10d9\u10d8"
    ],
    "name:kor_x_preferred":[
        "\ub77c\ud0a4\uc0b0"
    ],
    "name:lit_x_preferred":[
        "Lakis"
    ],
    "name:mkd_x_preferred":[
        "\u041b\u0430\u043a\u0438"
    ],
    "name:nld_x_preferred":[
        "Laki"
    ],
    "name:nno_x_preferred":[
        "Laki"
    ],
    "name:nor_x_preferred":[
        "Laki"
    ],
    "name:pnb_x_preferred":[
        "\u0644\u0627\u06a9\u06cc"
    ],
    "name:pol_x_preferred":[
        "Laki"
    ],
    "name:por_x_preferred":[
        "Laki"
    ],
    "name:rus_x_preferred":[
        "\u041b\u0430\u043a\u0438"
    ],
    "name:spa_x_preferred":[
        "Laki"
    ],
    "name:sqi_x_preferred":[
        "Krateri Laki"
    ],
    "name:srp_x_preferred":[
        "\u041a\u0440\u0430\u0442\u0435\u0440 \u041b\u0430\u043a\u0438"
    ],
    "name:swe_x_preferred":[
        "Laki"
    ],
    "name:tam_x_preferred":[
        "\u0bb2\u0bbe\u0b95\u0bcd\u0b95\u0bbf"
    ],
    "name:tha_x_preferred":[
        "\u0e20\u0e39\u0e40\u0e02\u0e32\u0e44\u0e1f\u0e25\u0e32\u0e44\u0e04"
    ],
    "name:ukr_x_preferred":[
        "\u041b\u0430\u043a\u0456"
    ],
    "name:und_x_variant":[
        "\u041b\u0430\u043a\u0438"
    ],
    "name:wuu_x_preferred":[
        "\u62c9\u57fa\u706b\u5c71"
    ],
    "name:xmf_x_preferred":[
        "\u10da\u10d0\u10d9\u10d8"
    ],
    "name:zho_x_preferred":[
        "\u62c9\u57fa\u706b\u5c71"
    ],
    "wof:name":"Laki",
    "wof:placetype":"locality"
},
  "geometry": {"coordinates":[57.63333000000001,58.33333],"type":"Point"}
}