{
  "type": "Feature",
  "properties": {
    "gn:admin1_code":"47",
    "gn:asciiname":"Kareyevo",
    "gn:country_code":"RU",
    "gn:dem":125,
    "gn:feature_class":"P",
    "gn:feature_code":"PPL",
    "gn:name":"Kareyevo",
    "gn:population":0,
    "gn:timezone":"Europe/Moscow",
    "iso:country":"RU",
    "name:rus_x_preferred":[
        "\u041a\u0430\u0440\u0435\u0435\u0432\u043e"
    ],
    "name:und_x_variant":[
        "\u041a\u0430\u0440\u0435\u0435\u0432\u043e"
    ],
    "wof:name":"Kareyevo",
    "wof:placetype":"locality"
},
  "geometry": {"coordinates":[39.33557,54.82185],"type":"Point"}
}