{
  "type": "Feature",
  "properties": {
    "gn:admin1_code":"69",
    "gn:asciiname":"Boriskovo",
    "gn:country_code":"RU",
    "gn:dem":219,
    "gn:feature_class":"P",
    "gn:feature_code":"PPL",
    "gn:name":"Boriskovo",
    "gn:population":0,
    "gn:timezone":"Europe/Moscow",
    "iso:country":"RU",
    "name:rus_x_preferred":[
        "\u0411\u043e\u0440\u0438\u0441\u043a\u043e\u0432\u043e"
    ],
    "name:und_x_variant":[
        "\u0411\u043e\u0440\u0438\u0441\u043a\u043e\u0432\u043e"
    ],
    "wof:name":"Boriskovo",
    "wof:placetype":"locality"
},
  "geometry": {"coordinates":[33.16194,54.99389],"type":"Point"}
}