{
  "type": "Feature",
  "properties": {
    "gn:admin1_code":"10",
    "gn:asciiname":"Zernovo",
    "gn:country_code":"RU",
    "gn:dem":194,
    "gn:feature_class":"P",
    "gn:feature_code":"PPL",
    "gn:name":"Zernovo",
    "gn:population":0,
    "gn:timezone":"Europe/Moscow",
    "iso:country":"RU",
    "name:eng_x_preferred":[
        "Zernovo"
    ],
    "name:nor_x_preferred":[
        "Zernovo"
    ],
    "name:rus_x_preferred":[
        "\u0417\u0435\u0440\u043d\u043e\u0432\u043e"
    ],
    "wof:name":"Zernovo",
    "wof:placetype":"locality"
},
  "geometry": {"coordinates":[34.0916,52.1925],"type":"Point"}
}