{
  "type": "Feature",
  "properties": {
    "gn:admin1_code":"25",
    "gn:asciiname":"Svitino",
    "gn:country_code":"RU",
    "gn:dem":166,
    "gn:feature_class":"P",
    "gn:feature_code":"PPL",
    "gn:name":"Svitino",
    "gn:population":0,
    "gn:timezone":"Europe/Moscow",
    "iso:country":"RU",
    "name:und_x_variant":[
        "Svetino",
        "Svitino"
    ],
    "wof:name":"Svitino",
    "wof:placetype":"locality"
},
  "geometry": {"coordinates":[35.80778,54.90722],"type":"Point"}
}