{
  "type": "Feature",
  "properties": {
    "gn:country":"RU",
    "gn:fcode":"PPL",
    "gn:pop":0,
    "iso:country":"RU",
    "name:rus_x_preferred":[
        "\u0421\u043e\u043b\u0451\u043d\u043e\u0435 \u041e\u0437\u0435\u0440\u043e"
    ],
    "name:unk_x_variant":[
        "Sol\u00ebnoye Ozero"
    ],
    "qs:name":"Solenoye Ozero",
    "qs:name_adm0":"Russia",
    "qs:name_adm1":"Stavropol Krai",
    "qs:photos_9k":1,
    "qs:photos_9r":1,
    "qs:photos_all":1,
    "qs:photos_sr":0,
    "qs:placetype":"Town",
    "qs:pop_sr":"0",
    "wof:name":"Solenoye Ozero",
    "wof:placetype":"locality",
    "wof:population":0
},
  "geometry": {"coordinates":[42.84778,45.26889],"type":"Point"}
}