{
  "type": "Feature",
  "properties": {
    "gn:admin1_code":"61.0",
    "gn:asciiname":"Prikhod'kin",
    "gn:country_code":"RU",
    "gn:dem":67,
    "gn:feature_class":"P",
    "gn:feature_code":"PPL",
    "gn:name":"Prikhod\u2019kin",
    "gn:population":0,
    "gn:timezone":"Europe/Moscow",
    "iso:country":"RU",
    "wof:name":"Prikhod'kin",
    "wof:placetype":"locality"
},
  "geometry": {"coordinates":[41.50278,48.73306],"type":"Point"}
}