{
  "type": "Feature",
  "properties": {
    "gn:admin1_code":"44",
    "gn:asciiname":"Krestik",
    "gn:country_code":"RU",
    "gn:dem":369,
    "gn:feature_class":"P",
    "gn:feature_code":"PPL",
    "gn:name":"Krestik",
    "gn:population":0,
    "gn:timezone":"Asia/Magadan",
    "iso:country":"RU",
    "name:rus_x_preferred":[
        "\u041a\u0440\u0435\u0441\u0442\u0438\u043a"
    ],
    "wof:name":"Krestik",
    "wof:placetype":"locality"
},
  "geometry": {"coordinates":[161.03333000000001,64.21666999999999],"type":"Point"}
}