{
  "type": "Feature",
  "properties": {
    "gn:country":"RU",
    "gn:fcode":"PPL",
    "gn:pop":4110,
    "iso:country":"RU",
    "name:che_x_preferred":[
        "\u041f\u0440\u0438\u0432\u043e\u043b\u0436\u0441\u043a\u0438\u0439"
    ],
    "name:eng_x_preferred":[
        "Privolzhskiy"
    ],
    "name:hun_x_preferred":[
        "Privolzsszkij"
    ],
    "name:hye_x_preferred":[
        "\u054a\u0580\u056b\u057e\u0578\u056c\u056a\u057d\u056f\u056b\u0575"
    ],
    "name:mhr_x_preferred":[
        "\u041f\u0440\u0438\u0432\u043e\u043b\u0436\u0441\u043a\u0438\u0439"
    ],
    "name:nor_x_preferred":[
        "Privolzjskij"
    ],
    "name:pol_x_preferred":[
        "Priwo\u0142\u017cskij"
    ],
    "name:rus_x_preferred":[
        "\u041f\u0440\u0438\u0432\u043e\u043b\u0436\u0441\u043a\u0438\u0439"
    ],
    "name:tat_x_preferred":[
        "\u041f\u0440\u0438\u0432\u043e\u043b\u0436\u0441\u043a\u0438\u0439"
    ],
    "name:unk_x_variant":[
        "\u041f\u0440\u0438\u0432\u043e\u043b\u0436\u0441\u043a\u0438\u0439"
    ],
    "qs:name":"Privolzhskiy",
    "qs:photos_9r":0,
    "qs:photos_sr":0,
    "qs:pop_sr":"4",
    "wd:wordcount":47,
    "wof:name":"Privolzhskiy",
    "wof:placetype":"locality",
    "wof:population":4110
},
  "geometry": {"coordinates":[48.41512,55.96135],"type":"Point"}
}