{
  "type": "Feature",
  "properties": {
    "gn:admin1_code":"33",
    "gn:asciiname":"Arkul'skiy",
    "gn:country_code":"RU",
    "gn:dem":77,
    "gn:feature_class":"P",
    "gn:feature_code":"PPL",
    "gn:name":"Arkul\u2019skiy",
    "gn:population":0,
    "gn:timezone":"Europe/Kirov",
    "iso:country":"RU",
    "name:nor_x_preferred":[
        "Arkulskij"
    ],
    "name:rus_x_preferred":[
        "\u0410\u0440\u043a\u0443\u043b\u044c\u0441\u043a\u0438\u0439"
    ],
    "name:und_x_variant":[
        "Arkul\u2019skiy"
    ],
    "wof:name":"Arkul'skiy",
    "wof:placetype":"locality"
},
  "geometry": {"coordinates":[50.78067,56.97783],"type":"Point"}
}