{
  "type": "Feature",
  "properties": {
    "gn:admin1_code":"6",
    "gn:asciiname":"Tysyacha Sto Vosem'desyat Kilometr",
    "gn:country_code":"RU",
    "gn:dem":94,
    "gn:feature_class":"P",
    "gn:feature_code":"PPL",
    "gn:name":"Tysyacha Sto Vosem\u2019desyat Kilometr",
    "gn:population":0,
    "gn:timezone":"Europe/Moscow",
    "iso:country":"RU",
    "name:rus_x_preferred":[
        "\u0422\u044b\u0441\u044f\u0447\u0430 \u0421\u0442\u043e Bo\u0441e\u043c\u044c\u0434\u0435\u0441\u044f\u0442 \u041a\u0438\u043b\u043e\u043c\u0435\u0442\u0440"
    ],
    "name:und_x_variant":[
        "Tysyacha Sto Vosem\u2019desyat Kilometr"
    ],
    "wof:name":"Tysyacha Sto Vosem'desyat Kilometr",
    "wof:placetype":"locality"
},
  "geometry": {"coordinates":[48.2303,61.5732],"type":"Point"}
}