{
  "type": "Feature",
  "properties": {
    "gn:admin1_code":"10",
    "gn:asciiname":"Strativa",
    "gn:country_code":"RU",
    "gn:dem":164,
    "gn:feature_class":"P",
    "gn:feature_code":"PPL",
    "gn:name":"Strativa",
    "gn:population":0,
    "gn:timezone":"Europe/Moscow",
    "iso:country":"RU",
    "name:rus_x_preferred":[
        "\u0421\u0442\u0440\u0430\u0442\u0438\u0432\u0430"
    ],
    "name:und_x_variant":[
        "\u0421\u0442\u0440\u0430\u0442\u0438\u0432\u0430"
    ],
    "wof:name":"Strativa",
    "wof:placetype":"locality"
},
  "geometry": {"coordinates":[32.6521,52.33055],"type":"Point"}
}