{
  "type": "Feature",
  "properties": {
    "gn:admin1_code":"86",
    "gn:asciiname":"Pervomayskoye",
    "gn:country_code":"RU",
    "gn:dem":205,
    "gn:feature_class":"P",
    "gn:feature_code":"PPL",
    "gn:name":"Pervomayskoye",
    "gn:population":0,
    "gn:timezone":"Europe/Moscow",
    "iso:country":"RU",
    "name:eng_x_preferred":[
        "Pervomayskoye"
    ],
    "name:nor_x_preferred":[
        "Pervomajskoje"
    ],
    "name:rus_x_preferred":[
        "\u041f\u0435\u0440\u0432\u043e\u043c\u0430\u0439\u0441\u043a\u043e\u0435"
    ],
    "name:und_x_variant":[
        "Deresovatka",
        "Pervomaysk",
        "Derezovatka",
        "Derezovataya"
    ],
    "wof:name":"Pervomayskoye",
    "wof:placetype":"locality"
},
  "geometry": {"coordinates":[39.95453,49.96557],"type":"Point"}
}