{
  "type": "Feature",
  "properties": {
    "gn:admin1_code":"85.0",
    "gn:asciiname":"Kozino",
    "gn:country_code":"RU",
    "gn:dem":181,
    "gn:feature_class":"P",
    "gn:feature_code":"PPL",
    "gn:name":"Kozino",
    "gn:population":0,
    "gn:timezone":"Europe/Moscow",
    "iso:country":"RU",
    "name:rus_x_preferred":[
        "\u041a\u043e\u0437\u0438\u043d\u043e"
    ],
    "name:und_x_variant":[
        "\u041a\u043e\u0437\u0438\u043d\u043e"
    ],
    "wof:name":"Kozino",
    "wof:placetype":"locality"
},
  "geometry": {"coordinates":[40.70667,58.71194000000001],"type":"Point"}
}