{
  "type": "Feature",
  "properties": {
    "gn:admin1_code":"41",
    "gn:asciiname":"Krasnaya Narezka",
    "gn:country_code":"RU",
    "gn:dem":226,
    "gn:feature_class":"P",
    "gn:feature_code":"PPL",
    "gn:name":"Krasnaya Narezka",
    "gn:population":0,
    "gn:timezone":"Europe/Moscow",
    "iso:country":"RU",
    "name:rus_x_preferred":[
        "\u041a\u0440\u0430\u0441\u043d\u0430\u044f \u041d\u0430\u0440\u0435\u0437\u043a\u0430"
    ],
    "wof:name":"Krasnaya Narezka",
    "wof:placetype":"locality"
},
  "geometry": {"coordinates":[37.2392,51.3897],"type":"Point"}
}