{
  "type": "Feature",
  "properties": {
    "gn:admin1_code":"76",
    "gn:asciiname":"Osanovo",
    "gn:country_code":"RU",
    "gn:dem":191,
    "gn:feature_class":"P",
    "gn:feature_code":"PPL",
    "gn:name":"Osanovo",
    "gn:population":0,
    "gn:timezone":"Europe/Moscow",
    "iso:country":"RU",
    "name:rus_x_preferred":[
        "\u041e\u0441\u0430\u043d\u043e\u0432\u043e"
    ],
    "wof:name":"Osanovo",
    "wof:placetype":"locality"
},
  "geometry": {"coordinates":[38.67737,54.19548],"type":"Point"}
}