{
  "type": "Feature",
  "properties": {
    "gn:admin1_code":"41",
    "gn:asciiname":"Lobovy Dvory",
    "gn:country_code":"RU",
    "gn:dem":235,
    "gn:feature_class":"P",
    "gn:feature_code":"PPL",
    "gn:name":"Lobovy Dvory",
    "gn:population":0,
    "gn:timezone":"Europe/Moscow",
    "iso:country":"RU",
    "name:rus_x_preferred":[
        "\u041b\u043e\u0431\u043e\u0432\u044b \u0414\u0432\u043e\u0440\u044b"
    ],
    "name:und_x_variant":[
        "Lobovskiye Dvory",
        "Lobovy Dvory"
    ],
    "wof:name":"Lobovy Dvory",
    "wof:placetype":"locality"
},
  "geometry": {"coordinates":[37.2367,51.456],"type":"Point"}
}