{
  "type": "Feature",
  "properties": {
    "gn:admin1_code":"60",
    "gn:asciiname":"Kyurovshchina",
    "gn:country_code":"RU",
    "gn:dem":73,
    "gn:feature_class":"P",
    "gn:feature_code":"PPL",
    "gn:name":"Kyurovshchina",
    "gn:population":0,
    "gn:timezone":"Europe/Moscow",
    "iso:country":"RU",
    "name:rus_x_preferred":[
        "\u041a\u044e\u0440\u043e\u0432\u0449\u0438\u043d\u0430"
    ],
    "name:und_x_variant":[
        "\u041a\u044e\u0440\u043e\u0432\u0449\u0438\u043d\u0430"
    ],
    "wof:name":"Kyurovshchina",
    "wof:placetype":"locality"
},
  "geometry": {"coordinates":[28.1167,58.832],"type":"Point"}
}