{
  "type": "Feature",
  "properties": {
    "gn:admin1_code":"70",
    "gn:asciiname":"Gribnoy",
    "gn:country_code":"RU",
    "gn:dem":327,
    "gn:feature_class":"P",
    "gn:feature_code":"PPL",
    "gn:name":"Gribnoy",
    "gn:population":0,
    "gn:timezone":"Europe/Moscow",
    "iso:country":"RU",
    "name:rus_x_preferred":[
        "\u0413\u0440\u0438\u0431\u043d\u043e\u0439"
    ],
    "name:und_x_variant":[
        "\u0413\u0440\u0438\u0431\u043d\u043e\u0439"
    ],
    "wof:name":"Gribnoy",
    "wof:placetype":"locality"
},
  "geometry": {"coordinates":[43.54278,44.04583],"type":"Point"}
}