{
  "type": "Feature",
  "properties": {
    "gn:admin1_code":"77",
    "gn:asciiname":"Gornyaya",
    "gn:country_code":"RU",
    "gn:dem":210,
    "gn:feature_class":"P",
    "gn:feature_code":"PPL",
    "gn:name":"Gornyaya",
    "gn:population":0,
    "gn:timezone":"Europe/Moscow",
    "iso:country":"RU",
    "name:rus_x_preferred":[
        "\u0413\u043e\u0440\u043d\u044f\u044f"
    ],
    "name:und_x_variant":[
        "Gornaya",
        "Gornyaya",
        "Gora"
    ],
    "wof:name":"Gornyaya",
    "wof:placetype":"locality"
},
  "geometry": {"coordinates":[31.7891,56.73828],"type":"Point"}
}