{
  "type": "Feature",
  "properties": {
    "gn:admin1_code":"61",
    "gn:asciiname":"Volna Revolyutsii",
    "gn:country_code":"RU",
    "gn:dem":122,
    "gn:feature_class":"P",
    "gn:feature_code":"PPL",
    "gn:name":"Volna Revolyutsii",
    "gn:population":0,
    "gn:timezone":"Europe/Moscow",
    "iso:country":"RU",
    "wof:name":"Volna Revolyutsii",
    "wof:placetype":"locality"
},
  "geometry": {"coordinates":[39.17028,47.83083],"type":"Point"}
}