{
  "type": "Feature",
  "properties": {
    "gn:admin1_code":"85",
    "gn:asciiname":"Kolokolets",
    "gn:country_code":"RU",
    "gn:dem":112,
    "gn:feature_class":"P",
    "gn:feature_code":"PPL",
    "gn:name":"Kolokolets",
    "gn:population":0,
    "gn:timezone":"Europe/Moscow",
    "iso:country":"RU",
    "name:rus_x_preferred":[
        "\u041a\u043e\u043b\u043e\u043a\u043e\u043b\u0435\u0446"
    ],
    "wof:name":"Kolokolets",
    "wof:placetype":"locality"
},
  "geometry": {"coordinates":[36.9126,58.9443],"type":"Point"}
}