{
  "type": "Feature",
  "properties": {
    "gn:admin1_code":"77",
    "gn:asciiname":"Sosnitsa",
    "gn:country_code":"RU",
    "gn:dem":211,
    "gn:feature_class":"P",
    "gn:feature_code":"PPL",
    "gn:name":"Sosnitsa",
    "gn:population":0,
    "gn:timezone":"Europe/Moscow",
    "iso:country":"RU",
    "name:rus_x_preferred":[
        "\u0421\u043e\u0441\u043d\u0438\u0446\u0430"
    ],
    "name:und_x_variant":[
        "Sosnitsy",
        "Sosnitsa",
        "\u0421\u043e\u0441\u043d\u0438\u0446\u0430"
    ],
    "wof:name":"Sosnitsa",
    "wof:placetype":"locality"
},
  "geometry": {"coordinates":[33.0122,57.40046],"type":"Point"}
}