{
  "type": "Feature",
  "properties": {
    "gn:admin1_code":"72",
    "gn:asciiname":"Inokovka",
    "gn:country_code":"RU",
    "gn:dem":127,
    "gn:feature_class":"P",
    "gn:feature_code":"PPL",
    "gn:name":"Inokovka",
    "gn:population":0,
    "gn:timezone":"Europe/Moscow",
    "iso:country":"RU",
    "name:eng_x_preferred":[
        "Inokovka"
    ],
    "name:nor_x_preferred":[
        "Inokovka"
    ],
    "name:rus_x_preferred":[
        "\u0418\u043d\u043e\u043a\u043e\u0432\u043a\u0430"
    ],
    "name:und_x_variant":[
        "\u0418\u043d\u043e\u043a\u043e\u0432\u043a\u0430",
        "Inokovka"
    ],
    "wof:name":"Inokovka",
    "wof:placetype":"locality"
},
  "geometry": {"coordinates":[42.56667,52.55],"type":"Point"}
}