{
  "type": "Feature",
  "properties": {
    "gn:admin1_code":"60",
    "gn:asciiname":"Privorot",
    "gn:country_code":"RU",
    "gn:dem":73,
    "gn:feature_class":"P",
    "gn:feature_code":"PPL",
    "gn:name":"Privorot",
    "gn:population":0,
    "gn:timezone":"Europe/Moscow",
    "iso:country":"RU",
    "name:rus_x_preferred":[
        "\u041f\u0440\u0438\u0432\u043e\u0440\u043e\u0442"
    ],
    "wof:name":"Privorot",
    "wof:placetype":"locality"
},
  "geometry": {"coordinates":[28.8219,56.99858],"type":"Point"}
}