{
  "type": "Feature",
  "properties": {
    "gn:admin1_code":"90.0",
    "gn:asciiname":"Vereinskiy",
    "gn:country_code":"RU",
    "gn:dem":193,
    "gn:feature_class":"P",
    "gn:feature_code":"PPL",
    "gn:name":"Vereinskiy",
    "gn:population":0,
    "gn:timezone":"Asia/Yekaterinburg",
    "iso:country":"RU",
    "name:rus_x_preferred":[
        "\u0412\u0435\u0440\u0435\u0438\u043d\u0441\u043a\u0438\u0439"
    ],
    "wof:name":"Vereinskiy",
    "wof:placetype":"locality"
},
  "geometry": {"coordinates":[57.5751,58.1987],"type":"Point"}
}