{
  "type": "Feature",
  "properties": {
    "gn:admin1_code":"38.0",
    "gn:asciiname":"Godovnikov",
    "gn:country_code":"RU",
    "gn:dem":242,
    "gn:feature_class":"P",
    "gn:feature_code":"PPL",
    "gn:name":"Godovnikov",
    "gn:population":0,
    "gn:timezone":"Europe/Moscow",
    "iso:country":"RU",
    "name:rus_x_preferred":[
        "\u0413\u043e\u0434\u043e\u0432\u043d\u0438\u043a\u043e\u0432"
    ],
    "wof:name":"Godovnikov",
    "wof:placetype":"locality"
},
  "geometry": {"coordinates":[39.8008,44.3506],"type":"Point"}
}