{
  "type": "Feature",
  "properties": {
    "gn:admin1_code":"56",
    "gn:asciiname":"Red'kino",
    "gn:country_code":"RU",
    "gn:dem":185,
    "gn:feature_class":"P",
    "gn:feature_code":"PPL",
    "gn:name":"Red\u2019kino",
    "gn:population":0,
    "gn:timezone":"Europe/Moscow",
    "iso:country":"RU",
    "name:rus_x_preferred":[
        "\u0420\u0435\u0434\u044c\u043a\u0438\u043d\u043e"
    ],
    "name:und_x_variant":[
        "Red\u2019kino"
    ],
    "wof:name":"Red'kino",
    "wof:placetype":"locality"
},
  "geometry": {"coordinates":[35.94337,53.12561],"type":"Point"}
}