{
  "type": "Feature",
  "properties": {
    "gn:admin1_code":"9",
    "gn:asciiname":"Krasnyy Khutor",
    "gn:country_code":"RU",
    "gn:dem":145,
    "gn:feature_class":"P",
    "gn:feature_code":"PPL",
    "gn:name":"Krasnyy Khutor",
    "gn:population":0,
    "gn:timezone":"Europe/Moscow",
    "iso:country":"RU",
    "name:rus_x_preferred":[
        "\u041a\u0440\u0430\u0441\u043d\u044b\u0439 \u0425\u0443\u0442\u043e\u0440"
    ],
    "name:und_x_variant":[
        "Khutor Krasnyy",
        "Krasnyy Khutor"
    ],
    "wof:name":"Krasnyy Khutor",
    "wof:placetype":"locality"
},
  "geometry": {"coordinates":[36.25087,50.37049],"type":"Point"}
}