{
  "type": "Feature",
  "properties": {
    "gn:admin1_code":"42",
    "gn:asciiname":"Filevo",
    "gn:country_code":"RU",
    "gn:dem":67,
    "gn:feature_class":"P",
    "gn:feature_code":"PPL",
    "gn:name":"Fil\u00ebvo",
    "gn:population":0,
    "gn:timezone":"Europe/Moscow",
    "iso:country":"RU",
    "name:rus_x_preferred":[
        "Fil\u00ebvo"
    ],
    "name:rus_x_variant":[
        "\u0424\u0438\u043b\u0451\u0432\u043e"
    ],
    "wof:name":"Filevo",
    "wof:placetype":"locality"
},
  "geometry": {"coordinates":[28.6366,58.9181],"type":"Point"}
}