{
  "type": "Feature",
  "properties": {
    "gn:admin1_code":"69",
    "gn:asciiname":"Kolodezi",
    "gn:country_code":"RU",
    "gn:dem":192,
    "gn:feature_class":"P",
    "gn:feature_code":"PPL",
    "gn:name":"Kolodezi",
    "gn:population":0,
    "gn:timezone":"Europe/Moscow",
    "iso:country":"RU",
    "name:rus_x_preferred":[
        "\u041a\u043e\u043b\u043e\u0434\u0435\u0437\u0438"
    ],
    "wof:name":"Kolodezi",
    "wof:placetype":"locality"
},
  "geometry": {"coordinates":[33.37427,54.11617],"type":"Point"}
}