{
  "type": "Feature",
  "properties": {
    "gn:admin1_code":"4",
    "gn:asciiname":"Kursk",
    "gn:country_code":"RU",
    "gn:dem":135,
    "gn:feature_class":"P",
    "gn:feature_code":"PPL",
    "gn:name":"Kursk",
    "gn:population":0,
    "gn:timezone":"Asia/Barnaul",
    "iso:country":"RU",
    "name:eng_x_preferred":[
        "Kurskiy"
    ],
    "name:nor_x_preferred":[
        "Kursk"
    ],
    "name:rus_x_preferred":[
        "\u041a\u0443\u0440\u0441\u043a"
    ],
    "name:und_x_variant":[
        "\u041a\u0443\u0440\u0441\u043a",
        "Kursk",
        "Kurskiy"
    ],
    "wof:name":"Kursk",
    "wof:placetype":"locality"
},
  "geometry": {"coordinates":[78.9233,52.4439],"type":"Point"}
}