{
  "type": "Feature",
  "properties": {
    "gn:admin1_code":"56",
    "gn:asciiname":"Groshev",
    "gn:country_code":"RU",
    "gn:dem":159,
    "gn:feature_class":"P",
    "gn:feature_code":"PPL",
    "gn:name":"Grosh\u00ebv",
    "gn:population":0,
    "gn:timezone":"Europe/Moscow",
    "iso:country":"RU",
    "name:rus_x_preferred":[
        "\u0413\u0440\u043e\u0448\u0451\u0432"
    ],
    "name:und_x_variant":[
        "Grosh\u00ebv"
    ],
    "wof:name":"Groshev",
    "wof:placetype":"locality"
},
  "geometry": {"coordinates":[36.74833,53.15833000000001],"type":"Point"}
}