{
  "type": "Feature",
  "properties": {
    "gn:admin1_code":"77",
    "gn:asciiname":"Podsadikha",
    "gn:country_code":"RU",
    "gn:dem":219,
    "gn:feature_class":"P",
    "gn:feature_code":"PPL",
    "gn:name":"Podsadikha",
    "gn:population":0,
    "gn:timezone":"Europe/Moscow",
    "iso:country":"RU",
    "name:rus_x_preferred":[
        "\u041f\u043e\u0434\u0441\u0430\u0434\u0438\u0445\u0430"
    ],
    "wof:name":"Podsadikha",
    "wof:placetype":"locality"
},
  "geometry": {"coordinates":[34.48333,57.28333000000001],"type":"Point"}
}