{
  "type": "Feature",
  "properties": {
    "iso:country":"RU",
    "name:ceb_x_preferred":[
        "Kosino"
    ],
    "name:fra_x_preferred":[
        "Kosino"
    ],
    "name:nld_x_preferred":[
        "Kosino"
    ],
    "name:rus_x_preferred":[
        "\u041a\u043e\u0441\u0438\u043d\u043e"
    ],
    "name:swe_x_preferred":[
        "Kosino"
    ],
    "wof:name":"Kosino",
    "wof:placetype":"neighbourhood"
},
  "geometry": {"coordinates":[37.85802091079499,55.71740050551043],"type":"Point"}
}