{
  "type": "Feature",
  "properties": {
    "gn:admin1_code":"20",
    "gn:asciiname":"Andryushino",
    "gn:country_code":"RU",
    "gn:dem":457,
    "gn:feature_class":"P",
    "gn:feature_code":"PPL",
    "gn:name":"Andryushino",
    "gn:population":0,
    "gn:timezone":"Asia/Irkutsk",
    "iso:country":"RU",
    "name:eng_x_preferred":[
        "Andryushino"
    ],
    "name:nor_x_preferred":[
        "Andrjusjino"
    ],
    "name:rus_x_preferred":[
        "\u0410\u043d\u0434\u0440\u044e\u0448\u0438\u043d\u043e"
    ],
    "name:und_x_variant":[
        "Andryushinskaya",
        "\u0410\u043d\u0434\u0440\u044e\u0448\u0438\u043d\u043e",
        "Andryushino"
    ],
    "wof:name":"Andryushino",
    "wof:placetype":"locality"
},
  "geometry": {"coordinates":[101.63687,54.36326],"type":"Point"}
}