{
  "type": "Feature",
  "properties": {
    "gn:admin1_code":"49",
    "gn:asciiname":"Svyatonosskiy Mayak",
    "gn:country_code":"RU",
    "gn:dem":-9999,
    "gn:feature_class":"P",
    "gn:feature_code":"PPL",
    "gn:name":"Svyatonosskiy Mayak",
    "gn:population":0,
    "gn:timezone":"Europe/Moscow",
    "iso:country":"RU",
    "wof:name":"Svyatonosskiy Mayak",
    "wof:placetype":"locality"
},
  "geometry": {"coordinates":[39.7495,68.14995999999999],"type":"Point"}
}