{
  "type": "Feature",
  "properties": {
    "gn:admin1_code":"90.0",
    "gn:asciiname":"Bondyug",
    "gn:country_code":"RU",
    "gn:dem":132,
    "gn:feature_class":"P",
    "gn:feature_code":"PPL",
    "gn:name":"Bondyug",
    "gn:population":0,
    "gn:timezone":"Asia/Yekaterinburg",
    "iso:country":"RU",
    "name:eng_x_preferred":[
        "Bondyug"
    ],
    "name:nor_x_preferred":[
        "Bondjug"
    ],
    "name:rus_x_preferred":[
        "\u0411\u043e\u043d\u0434\u044e\u0433"
    ],
    "name:und_x_variant":[
        "Bondyushk",
        "Bondyug",
        "\u0411\u043e\u043d\u0434\u044e\u0433"
    ],
    "wof:name":"Bondyug",
    "wof:placetype":"locality"
},
  "geometry": {"coordinates":[55.93116,60.48696],"type":"Point"}
}