{
  "type": "Feature",
  "properties": {
    "gn:admin1_code":"64",
    "gn:asciiname":"Khiva",
    "gn:country_code":"RU",
    "gn:dem":20,
    "gn:feature_class":"P",
    "gn:feature_code":"PPL",
    "gn:name":"Khiva",
    "gn:population":0,
    "gn:timezone":"Asia/Magadan",
    "iso:country":"RU",
    "name:rus_x_preferred":[
        "\u0425\u0438\u0432\u0430"
    ],
    "name:und_x_variant":[
        "\u0425\u0438\u0432\u0430"
    ],
    "wof:name":"Khiva",
    "wof:placetype":"locality"
},
  "geometry": {"coordinates":[150.30082999999999,46.06972],"type":"Point"}
}