{
  "type": "Feature",
  "properties": {
    "gn:admin1_code":"64",
    "gn:asciiname":"Khiva",
    "gn:country_code":"RU",
    "gn:dem":20,
    "gn:feature_class":"P",
    "gn:feature_code":"PPL",
    "gn:name":"Khiva",
    "gn:population":0,
    "gn:timezone":"Asia/Magadan",
    "iso:country":"RU",
    "name:ara_x_preferred":[
        "\u062e\u064a\u0648\u0629"
    ],
    "name:azb_x_preferred":[
        "\u062e\u06cc\u0648\u0647"
    ],
    "name:aze_x_preferred":[
        "Xiv\u0259"
    ],
    "name:bak_x_preferred":[
        "\u0425\u0438\u0443\u0430"
    ],
    "name:bel_x_preferred":[
        "\u0425\u0456\u0432\u0430"
    ],
    "name:bul_x_preferred":[
        "\u0425\u0438\u0432\u0430"
    ],
    "name:cat_x_preferred":[
        "Khiv\u00e0"
    ],
    "name:ceb_x_preferred":[
        "Khiwa"
    ],
    "name:ces_x_preferred":[
        "Chiva"
    ],
    "name:che_x_preferred":[
        "\u0425\u0438\u0432\u0430"
    ],
    "name:dan_x_preferred":[
        "Khiva"
    ],
    "name:deu_x_preferred":[
        "Xiva"
    ],
    "name:ell_x_preferred":[
        "\u03a7\u03af\u03b2\u03b1"
    ],
    "name:epo_x_preferred":[
        "\u0124iva"
    ],
    "name:est_x_preferred":[
        "Hiiva"
    ],
    "name:eus_x_preferred":[
        "Khiva"
    ],
    "name:fas_x_preferred":[
        "\u062e\u06cc\u0648\u0647"
    ],
    "name:fin_x_preferred":[
        "Hiva"
    ],
    "name:fra_x_preferred":[
        "Khiva"
    ],
    "name:hin_x_preferred":[
        "\u0916\u093c\u0940\u0935\u093e"
    ],
    "name:hsb_x_preferred":[
        "Xiva"
    ],
    "name:hun_x_preferred":[
        "Xiva"
    ],
    "name:hye_x_preferred":[
        "\u053d\u056b\u057e\u0561"
    ],
    "name:hyw_x_preferred":[
        "\u053d\u056b\u057e\u0561"
    ],
    "name:ita_x_preferred":[
        "Khiva"
    ],
    "name:jpn_x_preferred":[
        "\u30d2\u30f4\u30a1"
    ],
    "name:kat_x_preferred":[
        "\u10ee\u10d8\u10d5\u10d0"
    ],
    "name:kaz_x_preferred":[
        "\u0425\u0438\u0443\u0430"
    ],
    "name:kik_x_preferred":[
        "Khiva"
    ],
    "name:kir_x_preferred":[
        "\u0425\u0438\u0432\u0430"
    ],
    "name:lav_x_preferred":[
        "Hiva"
    ],
    "name:lit_x_preferred":[
        "Chiva"
    ],
    "name:mhr_x_preferred":[
        "\u0425\u0438\u0432\u0430"
    ],
    "name:msa_x_preferred":[
        "Khiva"
    ],
    "name:nld_x_preferred":[
        "Xiva"
    ],
    "name:nor_x_preferred":[
        "Khiva"
    ],
    "name:pan_x_preferred":[
        "\u0a16\u0a3c\u0a40\u0a35\u0a3e"
    ],
    "name:pnb_x_preferred":[
        "\u062e\u06cc\u0648\u0627"
    ],
    "name:pol_x_preferred":[
        "Chiwa"
    ],
    "name:por_x_preferred":[
        "Khiva"
    ],
    "name:rus_x_preferred":[
        "\u0425\u0438\u0432\u0430"
    ],
    "name:sco_x_preferred":[
        "Khiva"
    ],
    "name:slk_x_preferred":[
        "Chiva"
    ],
    "name:slv_x_preferred":[
        "Hiva"
    ],
    "name:spa_x_preferred":[
        "Jiva"
    ],
    "name:srp_x_preferred":[
        "\u0425\u0438\u0432\u0430"
    ],
    "name:swe_x_preferred":[
        "Chiva"
    ],
    "name:tat_x_preferred":[
        "\u0425\u0438\u0432\u04d9"
    ],
    "name:tuk_x_preferred":[
        "Hywa"
    ],
    "name:tur_x_preferred":[
        "Hive"
    ],
    "name:ukr_x_preferred":[
        "\u0425\u0456\u0432\u0430"
    ],
    "name:und_x_variant":[
        "\u0425\u0438\u0432\u0430"
    ],
    "name:urd_x_preferred":[
        "\u062e\u06cc\u0648\u0627"
    ],
    "name:uzb_x_preferred":[
        "Xiva"
    ],
    "name:vie_x_preferred":[
        "Khiva"
    ],
    "name:zho_x_preferred":[
        "\u5e0c\u74e6"
    ],
    "wof:name":"Khiva",
    "wof:placetype":"locality"
},
  "geometry": {"coordinates":[150.30082999999999,46.06972],"type":"Point"}
}