{
  "type": "Feature",
  "properties": {
    "gn:admin1_code":"23",
    "gn:asciiname":"Volochayevskoye",
    "gn:country_code":"RU",
    "gn:dem":3,
    "gn:feature_class":"P",
    "gn:feature_code":"PPL",
    "gn:name":"Volochayevskoye",
    "gn:population":1582,
    "gn:timezone":"Europe/Kaliningrad",
    "iso:country":"RU",
    "name:rus_x_preferred":[
        "\u0412\u043e\u043b\u043e\u0447\u0430\u0435\u0432\u0441\u043a\u043e\u0435"
    ],
    "name:und_x_variant":[
        "Marshenen",
        "Marschenen",
        "Volochayevskoye"
    ],
    "wof:name":"Volochayevskoye",
    "wof:placetype":"locality",
    "wof:population":1582
},
  "geometry": {"coordinates":[20.21966,54.70034],"type":"Point"}
}