{
  "type": "Feature",
  "properties": {
    "gn:admin1_code":"84",
    "gn:asciiname":"Serino",
    "gn:country_code":"RU",
    "gn:dem":176,
    "gn:feature_class":"P",
    "gn:feature_code":"PPL",
    "gn:name":"Serino",
    "gn:population":0,
    "gn:timezone":"Europe/Volgograd",
    "iso:country":"RU",
    "name:azb_x_preferred":[
        "\u0633\u0631\u06cc\u0646\u0648"
    ],
    "name:bul_x_preferred":[
        "\u0421\u0435\u0440\u0438\u043d\u043e"
    ],
    "name:ceb_x_preferred":[
        "Serino"
    ],
    "name:deu_x_preferred":[
        "Serino"
    ],
    "name:epo_x_preferred":[
        "Serino"
    ],
    "name:est_x_preferred":[
        "Serino"
    ],
    "name:eus_x_preferred":[
        "Serino"
    ],
    "name:fas_x_preferred":[
        "\u0633\u0631\u06cc\u0646\u0648"
    ],
    "name:fra_x_preferred":[
        "Serino"
    ],
    "name:hun_x_preferred":[
        "Serino"
    ],
    "name:hye_x_preferred":[
        "\u054d\u0565\u0580\u056b\u0576\u0578"
    ],
    "name:ina_x_preferred":[
        "Serino"
    ],
    "name:ita_x_preferred":[
        "Serino"
    ],
    "name:jpn_x_preferred":[
        "\u30bb\u30ea\u30fc\u30ce"
    ],
    "name:kaz_x_preferred":[
        "\u0421\u0435\u0440\u0438\u043d\u043e"
    ],
    "name:kor_x_preferred":[
        "\uc138\ub9ac\ub178"
    ],
    "name:lat_x_preferred":[
        "Serinum"
    ],
    "name:lmo_x_preferred":[
        "Serino"
    ],
    "name:mkd_x_preferred":[
        "\u0421\u0435\u0440\u0438\u043d\u043e"
    ],
    "name:msa_x_preferred":[
        "Serino"
    ],
    "name:nap_x_preferred":[
        "Serino"
    ],
    "name:nld_x_preferred":[
        "Serino"
    ],
    "name:pms_x_preferred":[
        "Serino"
    ],
    "name:pol_x_preferred":[
        "Serino"
    ],
    "name:por_x_preferred":[
        "Serino"
    ],
    "name:ron_x_preferred":[
        "Serino"
    ],
    "name:rus_x_preferred":[
        "\u0421\u0435\u0440\u0438\u043d\u043e"
    ],
    "name:scn_x_preferred":[
        "Serinu"
    ],
    "name:spa_x_preferred":[
        "Serino"
    ],
    "name:srp_x_preferred":[
        "\u0421\u0435\u0440\u0438\u043d\u043e"
    ],
    "name:swe_x_preferred":[
        "Serino"
    ],
    "name:szl_x_preferred":[
        "Serino"
    ],
    "name:tgl_x_preferred":[
        "Serino"
    ],
    "name:tur_x_preferred":[
        "Serino"
    ],
    "name:ukr_x_preferred":[
        "\u0421\u0435\u0440\u0438\u043d\u043e"
    ],
    "name:und_x_variant":[
        "\u0421\u0435\u0440\u0438\u043d\u043e"
    ],
    "name:uzb_x_preferred":[
        "Serino"
    ],
    "name:vec_x_preferred":[
        "Serino"
    ],
    "name:vie_x_preferred":[
        "Serino"
    ],
    "name:vol_x_preferred":[
        "Serino"
    ],
    "name:war_x_preferred":[
        "Serino"
    ],
    "name:zho_x_preferred":[
        "\u585e\u91cc\u8bfa"
    ],
    "wof:name":"Serino",
    "wof:placetype":"locality"
},
  "geometry": {"coordinates":[44.76667,50.33333],"type":"Point"}
}