{
  "type": "Feature",
  "properties": {
    "gn:admin1_code":"84",
    "gn:asciiname":"Serino",
    "gn:country_code":"RU",
    "gn:dem":176,
    "gn:feature_class":"P",
    "gn:feature_code":"PPL",
    "gn:name":"Serino",
    "gn:population":0,
    "gn:timezone":"Europe/Volgograd",
    "iso:country":"RU",
    "name:rus_x_preferred":[
        "\u0421\u0435\u0440\u0438\u043d\u043e"
    ],
    "name:und_x_variant":[
        "\u0421\u0435\u0440\u0438\u043d\u043e"
    ],
    "wof:name":"Serino",
    "wof:placetype":"locality"
},
  "geometry": {"coordinates":[44.76667,50.33333],"type":"Point"}
}