{
  "type": "Feature",
  "properties": {
    "gn:admin1_code":"8.0",
    "gn:asciiname":"Garibashevo",
    "gn:country_code":"RU",
    "gn:dem":144,
    "gn:feature_class":"P",
    "gn:feature_code":"PPL",
    "gn:name":"Garibashevo",
    "gn:population":0,
    "gn:timezone":"Asia/Yekaterinburg",
    "iso:country":"RU",
    "name:eng_x_preferred":[
        "Garibashevo"
    ],
    "name:nor_x_preferred":[
        "Garibasjevo"
    ],
    "name:rus_x_preferred":[
        "\u0413\u0430\u0440\u0438\u0431\u0430\u0448\u0435\u0432\u043e"
    ],
    "name:und_x_variant":[
        "Gareybashsevo"
    ],
    "wof:name":"Garibashevo",
    "wof:placetype":"locality"
},
  "geometry": {"coordinates":[55.5715,56.1708],"type":"Point"}
}