{
  "type": "Feature",
  "properties": {
    "gn:country":"RU",
    "gn:fcode":"PPL",
    "gn:population":6651,
    "iso:country":"RU",
    "name:eng_x_preferred":[
        "Tashla"
    ],
    "name:nor_x_preferred":[
        "Tasjla"
    ],
    "name:rus_x_preferred":[
        "\u0422\u0430\u0448\u043b\u0430"
    ],
    "name:und_x_variant":[
        "Tasala"
    ],
    "qs:name":"Tashla",
    "qs:name_adm0":"Russia",
    "qs:name_adm1":"Orenburg Oblast",
    "qs:photos_9r":0,
    "qs:photos_sr":0,
    "qs:placetype":"Town",
    "qs:pop_sr":"5",
    "wd:wordcount":102,
    "wof:name":"Tashla",
    "wof:placetype":"locality",
    "wof:population":6651
},
  "geometry": {"coordinates":[52.7427,51.77157],"type":"Point"}
}