{
  "type": "Feature",
  "properties": {
    "gn:admin1_code":"60",
    "gn:asciiname":"Agafonkovo",
    "gn:country_code":"RU",
    "gn:dem":165,
    "gn:feature_class":"P",
    "gn:feature_code":"PPL",
    "gn:name":"Agafonkovo",
    "gn:population":0,
    "gn:timezone":"Europe/Moscow",
    "iso:country":"RU",
    "name:rus_x_preferred":[
        "\u0410\u0433\u0430\u0444\u043e\u043d\u043a\u043e\u0432\u043e"
    ],
    "wof:name":"Agafonkovo",
    "wof:placetype":"locality"
},
  "geometry": {"coordinates":[29.0585,56.5747],"type":"Point"}
}