{
  "type": "Feature",
  "properties": {
    "gn:admin1_code":"71",
    "gn:asciiname":"Simanova",
    "gn:country_code":"RU",
    "gn:dem":68,
    "gn:feature_class":"P",
    "gn:feature_code":"PPL",
    "gn:name":"Simanova",
    "gn:population":0,
    "gn:timezone":"Asia/Yekaterinburg",
    "iso:country":"RU",
    "name:che_x_preferred":[
        "\u0421\u0438\u043c\u0430\u043d\u043e\u0432\u0430"
    ],
    "name:eng_x_preferred":[
        "Simonova"
    ],
    "name:nor_x_preferred":[
        "Simanova"
    ],
    "name:rus_x_preferred":[
        "\u0421\u0438\u043c\u0430\u043d\u043e\u0432\u0430"
    ],
    "wof:name":"Simanova",
    "wof:placetype":"locality"
},
  "geometry": {"coordinates":[62.77588000000001,57.62582],"type":"Point"}
}