{
  "type": "Feature",
  "properties": {
    "gn:admin1_code":"25",
    "gn:asciiname":"Sikerki",
    "gn:country_code":"RU",
    "gn:dem":209,
    "gn:feature_class":"P",
    "gn:feature_code":"PPL",
    "gn:name":"Sikerki",
    "gn:population":0,
    "gn:timezone":"Europe/Moscow",
    "iso:country":"RU",
    "name:rus_x_preferred":[
        "\u0421\u0438\u043a\u0435\u0440\u043a\u0438"
    ],
    "wof:name":"Sikerki",
    "wof:placetype":"locality"
},
  "geometry": {"coordinates":[35.78277,54.22499000000001],"type":"Point"}
}