{
  "type": "Feature",
  "properties": {
    "gn:admin1_code":"60",
    "gn:asciiname":"Konyushkino",
    "gn:country_code":"RU",
    "gn:dem":52,
    "gn:feature_class":"P",
    "gn:feature_code":"PPL",
    "gn:name":"Konyushkino",
    "gn:population":0,
    "gn:timezone":"Europe/Moscow",
    "iso:country":"RU",
    "name:rus_x_preferred":[
        "\u041a\u043e\u043d\u044e\u0448\u043a\u0438\u043d\u043e"
    ],
    "wof:name":"Konyushkino",
    "wof:placetype":"locality"
},
  "geometry": {"coordinates":[28.2376,57.9632],"type":"Point"}
}