{
  "type": "Feature",
  "properties": {
    "gn:admin1_code":"69",
    "gn:asciiname":"Trisvyat'ye",
    "gn:country_code":"RU",
    "gn:dem":225,
    "gn:feature_class":"P",
    "gn:feature_code":"PPL",
    "gn:name":"Trisvyat\u2019ye",
    "gn:population":0,
    "gn:timezone":"Europe/Moscow",
    "iso:country":"RU",
    "name:rus_x_preferred":[
        "\u0422\u0440\u0438\u0441\u0432\u044f\u0442\u044c\u0435"
    ],
    "name:und_x_variant":[
        "Tresvyat\u2019ye",
        "Trisvyat\u2019ye"
    ],
    "wof:name":"Trisvyat'ye",
    "wof:placetype":"locality"
},
  "geometry": {"coordinates":[32.47398,54.92977],"type":"Point"}
}