{
  "type": "Feature",
  "properties": {
    "gn:admin1_code":"31",
    "gn:asciiname":"Podkamen'",
    "gn:country_code":"RU",
    "gn:dem":441,
    "gn:feature_class":"P",
    "gn:feature_code":"PPL",
    "gn:name":"Podkamen\u2019",
    "gn:population":0,
    "gn:timezone":"Asia/Krasnoyarsk",
    "iso:country":"RU",
    "name:eng_x_preferred":[
        "Podkamen'"
    ],
    "name:nor_x_preferred":[
        "Podkamen"
    ],
    "name:rus_x_preferred":[
        "\u041f\u043e\u0434\u043a\u0430\u043c\u0435\u043d\u044c"
    ],
    "name:und_x_variant":[
        "Ulus Podkamennyy",
        "Podkamennyy",
        "Podkamen\u2019"
    ],
    "wof:name":"Podkamen'",
    "wof:placetype":"locality"
},
  "geometry": {"coordinates":[89.44833,54.82167],"type":"Point"}
}