{
  "type": "Feature",
  "properties": {
    "gn:admin1_code":"33",
    "gn:asciiname":"Repaki",
    "gn:country_code":"RU",
    "gn:dem":135,
    "gn:feature_class":"P",
    "gn:feature_code":"PPL",
    "gn:name":"Repaki",
    "gn:population":0,
    "gn:timezone":"Europe/Kirov",
    "iso:country":"RU",
    "name:rus_x_preferred":[
        "\u0420\u0435\u043f\u0430\u043a\u0438"
    ],
    "wof:name":"Repaki",
    "wof:placetype":"locality"
},
  "geometry": {"coordinates":[46.8576,57.3774],"type":"Point"}
}