{
  "type": "Feature",
  "properties": {
    "gn:admin1_code":"61.0",
    "gn:asciiname":"Brata",
    "gn:cc2":"RU",
    "gn:country_code":"RU",
    "gn:dem":119,
    "gn:feature_class":"P",
    "gn:feature_code":"PPL",
    "gn:name":"Brata",
    "gn:population":0,
    "gn:timezone":"Europe/Moscow",
    "iso:country":"RU",
    "name:rus_x_preferred":[
        "\u0411\u0440\u0430\u0442\u0430"
    ],
    "name:und_x_variant":[
        "Bratinskiye",
        "Brata",
        "\u0411\u0440\u0430\u0442\u0430"
    ],
    "wof:name":"Brata",
    "wof:placetype":"locality"
},
  "geometry": {"coordinates":[43.70444000000001,46.3375],"type":"Point"}
}