{
  "type": "Feature",
  "properties": {
    "gn:admin1_code":"41",
    "gn:asciiname":"Basovo",
    "gn:country_code":"RU",
    "gn:dem":219,
    "gn:feature_class":"P",
    "gn:feature_code":"PPL",
    "gn:name":"Basovo",
    "gn:population":0,
    "gn:timezone":"Europe/Moscow",
    "iso:country":"RU",
    "name:rus_x_preferred":[
        "\u0411\u0430\u0441\u043e\u0432\u043e"
    ],
    "name:und_x_variant":[
        "\u0411\u0430\u0441\u043e\u0432\u043e"
    ],
    "wof:name":"Basovo",
    "wof:placetype":"locality"
},
  "geometry": {"coordinates":[36.5016,52.0622],"type":"Point"}
}