{
  "type": "Feature",
  "properties": {
    "gn:admin1_code":"28",
    "gn:asciiname":"Myuzilamba",
    "gn:country_code":"RU",
    "gn:dem":107,
    "gn:feature_class":"P",
    "gn:feature_code":"PPL",
    "gn:name":"Myuzilamba",
    "gn:population":0,
    "gn:timezone":"Europe/Moscow",
    "iso:country":"RU",
    "name:fin_x_preferred":[
        "Mesilampi"
    ],
    "name:rus_x_preferred":[
        "\u041c\u044e\u0437\u0438\u043b\u0430\u043c\u0431\u0430"
    ],
    "name:und_x_variant":[
        "\u041c\u044e\u0437\u0438\u043b\u0430\u043c\u0431\u0430"
    ],
    "wof:name":"Myuzilamba",
    "wof:placetype":"locality"
},
  "geometry": {"coordinates":[32.67437,61.82131],"type":"Point"}
}