{
  "type": "Feature",
  "properties": {
    "gn:admin1_code":"60",
    "gn:asciiname":"L'zi",
    "gn:country_code":"RU",
    "gn:dem":60,
    "gn:feature_class":"P",
    "gn:feature_code":"PPL",
    "gn:name":"L\u2019zi",
    "gn:population":0,
    "gn:timezone":"Europe/Moscow",
    "iso:country":"RU",
    "name:eng_x_preferred":[
        "L'zi"
    ],
    "name:nor_x_preferred":[
        "Lzi"
    ],
    "name:rus_x_preferred":[
        "\u041b\u044c\u0437\u0438"
    ],
    "name:und_x_variant":[
        "\u041b\u044c\u0437\u0438",
        "L\u2019zi"
    ],
    "wof:name":"L'zi",
    "wof:placetype":"locality"
},
  "geometry": {"coordinates":[29.58991,58.31735],"type":"Point"}
}