{
  "type": "Feature",
  "properties": {
    "gn:admin1_code":"52",
    "gn:asciiname":"Podolzhino",
    "gn:country_code":"RU",
    "gn:dem":35,
    "gn:feature_class":"P",
    "gn:feature_code":"PPL",
    "gn:name":"Podolzhino",
    "gn:population":0,
    "gn:timezone":"Europe/Moscow",
    "iso:country":"RU",
    "name:rus_x_preferred":[
        "\u041f\u043e\u0434\u043e\u043b\u0436\u0438\u043d\u043e"
    ],
    "wof:name":"Podolzhino",
    "wof:placetype":"locality"
},
  "geometry": {"coordinates":[31.4925,57.6557],"type":"Point"}
}