{
  "type": "Feature",
  "properties": {
    "gn:admin1_code":"21.0",
    "gn:asciiname":"Anan'kino",
    "gn:country_code":"RU",
    "gn:dem":131,
    "gn:feature_class":"P",
    "gn:feature_code":"PPL",
    "gn:name":"Anan\u2019kino",
    "gn:population":0,
    "gn:timezone":"Europe/Moscow",
    "iso:country":"RU",
    "name:nor_x_preferred":[
        "Anankino"
    ],
    "name:rus_x_preferred":[
        "\u0410\u043d\u0430\u043d\u044c\u043a\u0438\u043d\u043e"
    ],
    "name:und_x_variant":[
        "Anan\u2019kino"
    ],
    "wof:name":"Anan'kino",
    "wof:placetype":"locality"
},
  "geometry": {"coordinates":[40.26667,57.23333],"type":"Point"}
}