{
  "type": "Feature",
  "properties": {
    "gn:admin1_code":"33.0",
    "gn:asciiname":"Esaulovy",
    "gn:country_code":"RU",
    "gn:dem":112,
    "gn:feature_class":"P",
    "gn:feature_code":"PPL",
    "gn:name":"Esaulovy",
    "gn:population":0,
    "gn:timezone":"Europe/Kirov",
    "iso:country":"RU",
    "name:rus_x_preferred":[
        "\u042d\u0441\u0430\u0443\u043b\u043e\u0432\u044b"
    ],
    "name:und_x_variant":[
        "Yesaulovy",
        "Esaulovy"
    ],
    "wof:name":"Esaulovy",
    "wof:placetype":"locality"
},
  "geometry": {"coordinates":[49.41713,58.6238],"type":"Point"}
}