{
  "type": "Feature",
  "properties": {
    "gn:admin1_code":"65.0",
    "gn:asciiname":"Filippovka",
    "gn:country_code":"RU",
    "gn:dem":70,
    "gn:feature_class":"P",
    "gn:feature_code":"PPL",
    "gn:name":"Filippovka",
    "gn:population":0,
    "gn:timezone":"Europe/Samara",
    "iso:country":"RU",
    "name:rus_x_preferred":[
        "\u0424\u0438\u043b\u0438\u043f\u043f\u043e\u0432\u043a\u0430"
    ],
    "name:und_x_variant":[
        "Filipovka",
        "Filippovka"
    ],
    "wof:name":"Filippovka",
    "wof:placetype":"locality"
},
  "geometry": {"coordinates":[50.98211,53.19974000000001],"type":"Point"}
}