{
  "type": "Feature",
  "properties": {
    "gn:admin1_code":"61.0",
    "gn:asciiname":"Bogomolov",
    "gn:country_code":"RU",
    "gn:dem":134,
    "gn:feature_class":"P",
    "gn:feature_code":"PPL",
    "gn:name":"Bogomolov",
    "gn:population":0,
    "gn:timezone":"Europe/Moscow",
    "iso:country":"RU",
    "name:bel_x_preferred":[
        "\u0411\u0430\u0433\u0430\u043c\u043e\u043b\u0430\u045e"
    ],
    "name:ces_x_preferred":[
        "Bogomolov"
    ],
    "name:deu_x_preferred":[
        "Bogomolow"
    ],
    "name:fra_x_preferred":[
        "Bogomolov"
    ],
    "name:lav_x_preferred":[
        "Bogomolovs"
    ],
    "name:pol_x_preferred":[
        "Bogomo\u0142ow"
    ],
    "name:rus_x_preferred":[
        "\u0411\u043e\u0433\u043e\u043c\u043e\u043b\u043e\u0432"
    ],
    "name:ukr_x_preferred":[
        "\u0411\u043e\u0433\u043e\u043c\u043e\u043b\u043e\u0432"
    ],
    "wof:name":"Bogomolov",
    "wof:placetype":"locality"
},
  "geometry": {"coordinates":[41.03667,49.70694],"type":"Point"}
}