{
  "type": "Feature",
  "properties": {
    "gn:admin1_code":"60",
    "gn:asciiname":"Yeliseyevo",
    "gn:country_code":"RU",
    "gn:dem":153,
    "gn:feature_class":"P",
    "gn:feature_code":"PPL",
    "gn:name":"Yeliseyevo",
    "gn:population":0,
    "gn:timezone":"Europe/Moscow",
    "iso:country":"RU",
    "name:rus_x_preferred":[
        "\u0415\u043b\u0438\u0441\u0435\u0435\u0432\u043e"
    ],
    "wof:name":"Yeliseyevo",
    "wof:placetype":"locality"
},
  "geometry": {"coordinates":[29.9821,56.3622],"type":"Point"}
}