{
  "type": "Feature",
  "properties": {
    "gn:admin1_code":"44",
    "gn:asciiname":"Kedrovyy",
    "gn:country_code":"RU",
    "gn:dem":732,
    "gn:feature_class":"P",
    "gn:feature_code":"PPL",
    "gn:name":"Kedrovyy",
    "gn:population":0,
    "gn:timezone":"Asia/Magadan",
    "iso:country":"RU",
    "name:eng_x_preferred":[
        "Kedrovyy"
    ],
    "name:nor_x_preferred":[
        "Kedrovyj"
    ],
    "name:rus_x_preferred":[
        "\u041a\u0435\u0434\u0440\u043e\u0432\u044b\u0439"
    ],
    "name:und_x_variant":[
        "Arkagalinskaya"
    ],
    "wof:name":"Kedrovyy",
    "wof:placetype":"locality"
},
  "geometry": {"coordinates":[147.06049999999999,63.01194],"type":"Point"}
}