{
  "type": "Feature",
  "properties": {
    "gn:admin1_code":"3",
    "gn:asciiname":"Kummunarskiy",
    "gn:country_code":"RU",
    "gn:dem":410,
    "gn:feature_class":"P",
    "gn:feature_code":"PPL",
    "gn:name":"Kummunarskiy",
    "gn:population":0,
    "gn:timezone":"Asia/Omsk",
    "iso:country":"RU",
    "name:rus_x_preferred":[
        "\u041a\u0443\u043c\u043c\u0443\u043d\u0430\u0440\u0441\u043a\u0438\u0439"
    ],
    "name:und_x_variant":[
        "\u041a\u0443\u043c\u043c\u0443\u043d\u0430\u0440\u0441\u043a\u0438\u0439"
    ],
    "wof:name":"Kummunarskiy",
    "wof:placetype":"locality"
},
  "geometry": {"coordinates":[86.53333000000001,51.95],"type":"Point"}
}