{
  "type": "Feature",
  "properties": {
    "gn:admin1_code":"60",
    "gn:asciiname":"Burovets",
    "gn:country_code":"RU",
    "gn:dem":221,
    "gn:feature_class":"P",
    "gn:feature_code":"PPL",
    "gn:name":"Burovets",
    "gn:population":0,
    "gn:timezone":"Europe/Moscow",
    "iso:country":"RU",
    "name:rus_x_preferred":[
        "\u0411\u0443\u0440\u043e\u0432\u0435\u0446"
    ],
    "name:und_x_variant":[
        "\u0411\u0443\u0440\u043e\u0432\u0435\u0446"
    ],
    "wof:name":"Burovets",
    "wof:placetype":"locality"
},
  "geometry": {"coordinates":[29.7436,56.4815],"type":"Point"}
}