{
  "type": "Feature",
  "properties": {
    "gn:admin1_code":"77",
    "gn:asciiname":"Kalitsino",
    "gn:country_code":"RU",
    "gn:dem":169,
    "gn:feature_class":"P",
    "gn:feature_code":"PPL",
    "gn:name":"Kalitsino",
    "gn:population":0,
    "gn:timezone":"Europe/Moscow",
    "iso:country":"RU",
    "name:nor_x_preferred":[
        "Kalitsino"
    ],
    "name:rus_x_preferred":[
        "\u041a\u0430\u043b\u0438\u0446\u0438\u043d\u043e"
    ],
    "name:und_x_variant":[
        "Kalach\u00ebvo",
        "Kalitsino"
    ],
    "wof:name":"Kalitsino",
    "wof:placetype":"locality"
},
  "geometry": {"coordinates":[35.31661,56.2932],"type":"Point"}
}