{
  "type": "Feature",
  "properties": {
    "gn:country":"RU",
    "gn:fcode":"PPL",
    "gn:pop":0,
    "iso:country":"RU",
    "name:rus_x_preferred":[
        "\u0428\u0438\u0440\u043e\u043a\u0430\u044f"
    ],
    "name:unk_x_variant":[
        "Bab\u2019ye"
    ],
    "qs:name":"Shirokaya",
    "qs:name_adm0":"Russia",
    "qs:name_adm1":"Tver Oblast",
    "qs:photos_9r":0,
    "qs:photos_sr":0,
    "qs:placetype":"Town",
    "qs:pop_sr":"0",
    "wof:name":"Shirokaya",
    "wof:placetype":"locality",
    "wof:population":0
},
  "geometry": {"coordinates":[35.74494,57.26094],"type":"Point"}
}