{
  "type": "Feature",
  "properties": {
    "gn:admin1_code":"20",
    "gn:asciiname":"Poltava",
    "gn:country_code":"RU",
    "gn:dem":460,
    "gn:feature_class":"P",
    "gn:feature_code":"PPL",
    "gn:name":"Poltava",
    "gn:population":0,
    "gn:timezone":"Asia/Irkutsk",
    "iso:country":"RU",
    "name:rus_x_preferred":[
        "\u041f\u043e\u043b\u0442\u0430\u0432\u0430"
    ],
    "name:und_x_variant":[
        "Poltavskiy",
        "Poltava",
        "\u041f\u043e\u043b\u0442\u0430\u0432\u0430"
    ],
    "wof:name":"Poltava",
    "wof:placetype":"locality"
},
  "geometry": {"coordinates":[101.4144,54.0951],"type":"Point"}
}