{
  "type": "Feature",
  "properties": {
    "gn:admin1_code":"16",
    "gn:asciiname":"Nizhniye Khyrkasy",
    "gn:country_code":"RU",
    "gn:dem":78,
    "gn:feature_class":"P",
    "gn:feature_code":"PPL",
    "gn:name":"Nizhniye Khyrkasy",
    "gn:population":0,
    "gn:timezone":"Europe/Moscow",
    "iso:country":"RU",
    "name:rus_x_preferred":[
        "\u041d\u0438\u0436\u043d\u0438\u0435 \u0425\u044b\u0440\u043a\u0430\u0441\u044b"
    ],
    "wof:name":"Nizhniye Khyrkasy",
    "wof:placetype":"locality"
},
  "geometry": {"coordinates":[47.3116,55.8664],"type":"Point"}
}