{
  "type": "Feature",
  "properties": {
    "gn:admin1_code":"10.0",
    "gn:asciiname":"Filosofov Zavod",
    "gn:country_code":"RU",
    "gn:dem":168,
    "gn:feature_class":"P",
    "gn:feature_code":"PPL",
    "gn:name":"Filosofov Zavod",
    "gn:population":0,
    "gn:timezone":"Europe/Moscow",
    "iso:country":"RU",
    "name:rus_x_preferred":[
        "\u0424\u0438\u043b\u043e\u0441\u043e\u0444\u043e\u0432 \u0417\u0430\u0432\u043e\u0434"
    ],
    "name:und_x_variant":[
        "Filosofskiy Zavod",
        "Filosofov Zavod"
    ],
    "wof:name":"Filosofov Zavod",
    "wof:placetype":"locality"
},
  "geometry": {"coordinates":[34.78942,53.19759000000001],"type":"Point"}
}