{
  "type": "Feature",
  "properties": {
    "gn:admin1_code":"75",
    "gn:asciiname":"Yagodnoye",
    "gn:country_code":"RU",
    "gn:dem":122,
    "gn:feature_class":"P",
    "gn:feature_code":"PPL",
    "gn:name":"Yagodnoye",
    "gn:population":0,
    "gn:timezone":"Asia/Tomsk",
    "iso:country":"RU",
    "name:eng_x_preferred":[
        "Yagodnoye"
    ],
    "name:nor_x_preferred":[
        "Jagodnoje"
    ],
    "name:rus_x_preferred":[
        "\u042f\u0433\u043e\u0434\u043d\u043e\u0435"
    ],
    "name:und_x_variant":[
        "Yagodnoya"
    ],
    "wof:name":"Yagodnoye",
    "wof:placetype":"locality"
},
  "geometry": {"coordinates":[86.0814,56.8053],"type":"Point"}
}