{
  "type": "Feature",
  "properties": {
    "gn:admin1_code":"88.0",
    "gn:asciiname":"Bol'shoye Dubinino",
    "gn:country_code":"RU",
    "gn:dem":133,
    "gn:feature_class":"P",
    "gn:feature_code":"PPL",
    "gn:name":"Bol\u2019shoye Dubinino",
    "gn:population":0,
    "gn:timezone":"Europe/Moscow",
    "iso:country":"RU",
    "name:rus_x_preferred":[
        "\u0411\u043e\u043b\u044c\u0448\u043e\u0435 \u0414\u0443\u0431\u0438\u043d\u0438\u043d\u043e"
    ],
    "name:und_x_variant":[
        "Dubino",
        "Bol\u2019shoye Dubino",
        "Bol\u2019shoye Dubinino"
    ],
    "wof:name":"Bol'shoye Dubinino",
    "wof:placetype":"locality"
},
  "geometry": {"coordinates":[38.08062,57.98257],"type":"Point"}
}