{
  "type": "Feature",
  "properties": {
    "gn:admin1_code":"52",
    "gn:asciiname":"Terebutitsy",
    "gn:country_code":"RU",
    "gn:dem":27,
    "gn:feature_class":"P",
    "gn:feature_code":"PPL",
    "gn:name":"Terebutitsy",
    "gn:population":0,
    "gn:timezone":"Europe/Moscow",
    "iso:country":"RU",
    "name:eng_x_preferred":[
        "Terebutitsy"
    ],
    "name:nor_x_preferred":[
        "Terebutitsy"
    ],
    "name:rus_x_preferred":[
        "\u0422\u0435\u0440\u0435\u0431\u0443\u0442\u0438\u0446\u044b"
    ],
    "wof:name":"Terebutitsy",
    "wof:placetype":"locality"
},
  "geometry": {"coordinates":[30.68871,58.25285],"type":"Point"}
}