{
  "type": "Feature",
  "properties": {
    "gn:admin1_code":"92",
    "gn:asciiname":"Rekinniki",
    "gn:cc2":"RU",
    "gn:country_code":"RU",
    "gn:dem":75,
    "gn:feature_class":"P",
    "gn:feature_code":"PPL",
    "gn:name":"Rekinniki",
    "gn:population":0,
    "gn:timezone":"Asia/Kamchatka",
    "iso:country":"RU",
    "name:rus_x_preferred":[
        "\u0420\u0435\u043a\u0438\u043d\u043d\u0438\u043a\u0438"
    ],
    "name:und_x_variant":[
        "Rekiniki",
        "Rekinniki"
    ],
    "wof:name":"Rekinniki",
    "wof:placetype":"locality"
},
  "geometry": {"coordinates":[163.83333000000005,60.63333000000001],"type":"Point"}
}