{
  "type": "Feature",
  "properties": {
    "gn:admin1_code":"55.0",
    "gn:asciiname":"Burtinskiy",
    "gn:country_code":"RU",
    "gn:dem":134,
    "gn:feature_class":"P",
    "gn:feature_code":"PPL",
    "gn:name":"Burtinskiy",
    "gn:population":0,
    "gn:timezone":"Asia/Yekaterinburg",
    "iso:country":"RU",
    "name:eng_x_preferred":[
        "Burtinskiy"
    ],
    "name:nor_x_preferred":[
        "Burtinskij"
    ],
    "name:rus_x_preferred":[
        "\u0411\u0443\u0440\u0442\u0438\u043d\u0441\u043a\u0438\u0439"
    ],
    "wof:name":"Burtinskiy",
    "wof:placetype":"locality"
},
  "geometry": {"coordinates":[55.99326,51.36962],"type":"Point"}
}