{
  "type": "Feature",
  "properties": {
    "gn:admin1_code":"57",
    "gn:asciiname":"Stepnaya",
    "gn:cc2":"RU",
    "gn:country_code":"RU",
    "gn:dem":128,
    "gn:feature_class":"P",
    "gn:feature_code":"PPL",
    "gn:name":"Stepnaya",
    "gn:population":0,
    "gn:timezone":"Europe/Moscow",
    "iso:country":"RU",
    "name:rus_x_preferred":[
        "\u0421\u0442\u0435\u043f\u043d\u0430\u044f"
    ],
    "name:und_x_variant":[
        "Gryazevka",
        "Stepnaya",
        "\u0421\u0442\u0435\u043f\u043d\u0430\u044f"
    ],
    "wof:name":"Stepnaya",
    "wof:placetype":"locality"
},
  "geometry": {"coordinates":[45.23333,53.58333],"type":"Point"}
}