{
  "type": "Feature",
  "properties": {
    "gn:admin1_code":"6",
    "gn:asciiname":"Artyukovskaya",
    "gn:country_code":"RU",
    "gn:dem":74,
    "gn:feature_class":"P",
    "gn:feature_code":"PPL",
    "gn:name":"Artyukovskaya",
    "gn:population":0,
    "gn:timezone":"Europe/Moscow",
    "iso:country":"RU",
    "name:nor_x_preferred":[
        "Artjukovskaja"
    ],
    "name:rus_x_preferred":[
        "\u0410\u0440\u0442\u044e\u043a\u043e\u0432\u0441\u043a\u0430\u044f"
    ],
    "wof:name":"Artyukovskaya",
    "wof:placetype":"locality"
},
  "geometry": {"coordinates":[46.22944,61.4325],"type":"Point"}
}