{
  "type": "Feature",
  "properties": {
    "gn:admin1_code":"33.0",
    "gn:asciiname":"Shalaginovy",
    "gn:country_code":"RU",
    "gn:dem":103,
    "gn:feature_class":"P",
    "gn:feature_code":"PPL",
    "gn:name":"Shalaginovy",
    "gn:population":0,
    "gn:timezone":"Europe/Kirov",
    "iso:country":"RU",
    "name:rus_x_preferred":[
        "\u0428\u0430\u043b\u0430\u0433\u0438\u043d\u043e\u0432\u044b"
    ],
    "name:und_x_variant":[
        "\u0428\u0430\u043b\u0430\u0433\u0438\u043d\u043e\u0432\u044b"
    ],
    "wof:name":"Shalaginovy",
    "wof:placetype":"locality"
},
  "geometry": {"coordinates":[48.58566,58.47219000000001],"type":"Point"}
}