{
  "type": "Feature",
  "properties": {
    "gn:admin1_code":"60",
    "gn:asciiname":"Molodi",
    "gn:country_code":"RU",
    "gn:dem":143,
    "gn:feature_class":"P",
    "gn:feature_code":"PPL",
    "gn:name":"Molodi",
    "gn:population":0,
    "gn:timezone":"Europe/Moscow",
    "iso:country":"RU",
    "name:rus_x_preferred":[
        "\u041c\u043e\u043b\u043e\u0434\u0438"
    ],
    "wof:name":"Molodi",
    "wof:placetype":"locality"
},
  "geometry": {"coordinates":[29.9916,56.3325],"type":"Point"}
}