{
  "type": "Feature",
  "properties": {
    "gn:admin1_code":"37",
    "gn:asciiname":"Rishchevo",
    "gn:country_code":"RU",
    "gn:dem":133,
    "gn:feature_class":"P",
    "gn:feature_code":"PPL",
    "gn:name":"Rishchevo",
    "gn:population":0,
    "gn:timezone":"Europe/Moscow",
    "iso:country":"RU",
    "name:rus_x_preferred":[
        "\u0420\u0438\u0449\u0435\u0432\u043e"
    ],
    "name:und_x_variant":[
        "\u0420\u0438\u0449\u0435\u0432\u043e"
    ],
    "wof:name":"Rishchevo",
    "wof:placetype":"locality"
},
  "geometry": {"coordinates":[43.5516,58.5349],"type":"Point"}
}