{
  "type": "Feature",
  "properties": {
    "gn:admin1_code":"33.0",
    "gn:asciiname":"Belaya",
    "gn:country_code":"RU",
    "gn:dem":155,
    "gn:feature_class":"P",
    "gn:feature_code":"PPL",
    "gn:name":"Belaya",
    "gn:population":0,
    "gn:timezone":"Europe/Kirov",
    "iso:country":"RU",
    "name:eng_x_preferred":[
        "Belaya"
    ],
    "name:nor_x_preferred":[
        "Belaja"
    ],
    "name:rus_x_preferred":[
        "\u0411\u0435\u043b\u0430\u044f"
    ],
    "name:und_x_variant":[
        "\u0411\u0435\u043b\u0430\u044f",
        "Belaya"
    ],
    "wof:name":"Belaya",
    "wof:placetype":"locality"
},
  "geometry": {"coordinates":[51.6831,57.9813],"type":"Point"}
}