{
  "type": "Feature",
  "properties": {
    "gn:admin1_code":"85",
    "gn:asciiname":"Lukinskoye",
    "gn:country_code":"RU",
    "gn:dem":135,
    "gn:feature_class":"P",
    "gn:feature_code":"PPL",
    "gn:name":"Lukinskoye",
    "gn:population":0,
    "gn:timezone":"Europe/Moscow",
    "iso:country":"RU",
    "name:rus_x_preferred":[
        "\u041b\u0443\u043a\u0438\u043d\u0441\u043a\u043e\u0435"
    ],
    "wof:name":"Lukinskoye",
    "wof:placetype":"locality"
},
  "geometry": {"coordinates":[38.5065,59.9564],"type":"Point"}
}