{
  "type": "Feature",
  "properties": {
    "gn:admin1_code":"54",
    "gn:asciiname":"Obalykul'",
    "gn:country_code":"RU",
    "gn:dem":127,
    "gn:feature_class":"P",
    "gn:feature_code":"PPL",
    "gn:name":"Obalykul\u2019",
    "gn:population":0,
    "gn:timezone":"Asia/Omsk",
    "iso:country":"RU",
    "name:rus_x_preferred":[
        "\u041e\u0431\u0430\u043b\u044b\u043a\u0443\u043b\u044c"
    ],
    "name:und_x_variant":[
        "Obalykul\u2019",
        "\u041e\u0431\u0430\u043b\u044b\u043a\u0443\u043b\u044c"
    ],
    "wof:name":"Obalykul'",
    "wof:placetype":"locality"
},
  "geometry": {"coordinates":[73.48333000000002,53.75],"type":"Point"}
}