{
  "type": "Feature",
  "properties": {
    "gn:admin1_code":"37",
    "gn:asciiname":"Mulino",
    "gn:country_code":"RU",
    "gn:dem":142,
    "gn:feature_class":"P",
    "gn:feature_code":"PPL",
    "gn:name":"Mulino",
    "gn:population":0,
    "gn:timezone":"Europe/Moscow",
    "iso:country":"RU",
    "name:rus_x_preferred":[
        "\u041c\u0443\u043b\u0438\u043d\u043e"
    ],
    "name:und_x_variant":[
        "\u041c\u0443\u043b\u0438\u043d\u043e"
    ],
    "wof:name":"Mulino",
    "wof:placetype":"locality"
},
  "geometry": {"coordinates":[43.6754,58.0327],"type":"Point"}
}