{
  "type": "Feature",
  "properties": {
    "gn:admin1_code":"84.0",
    "gn:asciiname":"Makarovskiy",
    "gn:country_code":"RU",
    "gn:dem":130,
    "gn:feature_class":"P",
    "gn:feature_code":"PPL",
    "gn:name":"Makarovskiy",
    "gn:population":0,
    "gn:timezone":"Europe/Volgograd",
    "iso:country":"RU",
    "name:rus_x_preferred":[
        "\u041c\u0430\u043a\u0430\u0440\u043e\u0432\u0441\u043a\u0438\u0439"
    ],
    "wof:name":"Makarovskiy",
    "wof:placetype":"locality"
},
  "geometry": {"coordinates":[41.7319,50.6568],"type":"Point"}
}