{
  "type": "Feature",
  "properties": {
    "gn:admin1_code":"88",
    "gn:asciiname":"Maloye Dubinino",
    "gn:country_code":"RU",
    "gn:dem":128,
    "gn:feature_class":"P",
    "gn:feature_code":"PPL",
    "gn:name":"Maloye Dubinino",
    "gn:population":0,
    "gn:timezone":"Europe/Moscow",
    "iso:country":"RU",
    "name:rus_x_preferred":[
        "\u041c\u0430\u043b\u043e\u0435 \u0414\u0443\u0431\u0438\u043d\u0438\u043d\u043e"
    ],
    "name:und_x_variant":[
        "Maloye Dubino",
        "Maloye Dubinino"
    ],
    "wof:name":"Maloye Dubinino",
    "wof:placetype":"locality"
},
  "geometry": {"coordinates":[38.08821,57.9798],"type":"Point"}
}