{
  "type": "Feature",
  "properties": {
    "gn:admin1_code":"60",
    "gn:asciiname":"Bondarevo",
    "gn:country_code":"RU",
    "gn:dem":144,
    "gn:feature_class":"P",
    "gn:feature_code":"PPL",
    "gn:name":"Bondar\u00ebvo",
    "gn:population":0,
    "gn:timezone":"Europe/Moscow",
    "iso:country":"RU",
    "name:rus_x_preferred":[
        "\u0411\u043e\u043d\u0434\u0430\u0440\u0451\u0432\u043e"
    ],
    "name:und_x_variant":[
        "Bondar\u00ebvo"
    ],
    "wof:name":"Bondarevo",
    "wof:placetype":"locality"
},
  "geometry": {"coordinates":[28.33372,56.33441],"type":"Point"}
}