{
  "type": "Feature",
  "properties": {
    "gn:admin1_code":"17",
    "gn:asciiname":"Rybalko",
    "gn:country_code":"RU",
    "gn:dem":-3,
    "gn:feature_class":"P",
    "gn:feature_code":"PPL",
    "gn:name":"Rybalko",
    "gn:population":0,
    "gn:timezone":"Europe/Moscow",
    "iso:country":"RU",
    "name:rus_x_preferred":[
        "\u0420\u044b\u0431\u0430\u043b\u043a\u043e"
    ],
    "wof:name":"Rybalko",
    "wof:placetype":"locality"
},
  "geometry": {"coordinates":[46.65519000000001,43.78321],"type":"Point"}
}