{
  "type": "Feature",
  "properties": {
    "gn:admin1_code":"71",
    "gn:asciiname":"Kirpichnyy",
    "gn:country_code":"RU",
    "gn:dem":262,
    "gn:feature_class":"P",
    "gn:feature_code":"PPL",
    "gn:name":"Kirpichnyy",
    "gn:population":0,
    "gn:timezone":"Asia/Yekaterinburg",
    "iso:country":"RU",
    "name:rus_x_preferred":[
        "\u041a\u0438\u0440\u043f\u0438\u0447\u043d\u044b\u0439"
    ],
    "wof:name":"Kirpichnyy",
    "wof:placetype":"locality"
},
  "geometry": {"coordinates":[60.4388,56.9601],"type":"Point"}
}