{
  "type": "Feature",
  "properties": {
    "gn:admin1_code":"53",
    "gn:asciiname":"Troitskiy",
    "gn:country_code":"RU",
    "gn:dem":155,
    "gn:feature_class":"P",
    "gn:feature_code":"PPL",
    "gn:name":"Troitskiy",
    "gn:population":0,
    "gn:timezone":"Asia/Novosibirsk",
    "iso:country":"RU",
    "name:und_x_variant":[
        "Krasno-Oktyabr\u2019skiy",
        "Troitskiy"
    ],
    "wof:name":"Troitskiy",
    "wof:placetype":"locality"
},
  "geometry": {"coordinates":[80.84130999999999,54.68534],"type":"Point"}
}