{
  "type": "Feature",
  "properties": {
    "gn:admin1_code":"6",
    "gn:asciiname":"Churkovskaya",
    "gn:cc2":"RU",
    "gn:country_code":"RU",
    "gn:dem":40,
    "gn:feature_class":"P",
    "gn:feature_code":"PPL",
    "gn:name":"Churkovskaya",
    "gn:population":0,
    "gn:timezone":"Europe/Moscow",
    "iso:country":"RU",
    "name:rus_x_preferred":[
        "\u0427\u0443\u0440\u043a\u043e\u0432\u0441\u043a\u0430\u044f"
    ],
    "name:und_x_variant":[
        "Sloboda-Churkovskaya",
        "Churkovskaya",
        "\u0427\u0443\u0440\u043a\u043e\u0432\u0441\u043a\u0430\u044f"
    ],
    "wof:name":"Churkovskaya",
    "wof:placetype":"locality"
},
  "geometry": {"coordinates":[42.52889,61.48111],"type":"Point"}
}