{
  "type": "Feature",
  "properties": {
    "gn:admin1_code":"85",
    "gn:asciiname":"Podol'noye",
    "gn:country_code":"RU",
    "gn:dem":118,
    "gn:feature_class":"P",
    "gn:feature_code":"PPL",
    "gn:name":"Podol\u2019noye",
    "gn:population":0,
    "gn:timezone":"Europe/Moscow",
    "iso:country":"RU",
    "name:rus_x_preferred":[
        "\u041f\u043e\u0434\u043e\u043b\u044c\u043d\u043e\u0435"
    ],
    "name:und_x_variant":[
        "Podol\u2019noye",
        "\u041f\u043e\u0434\u043e\u043b\u044c\u043d\u043e\u0435"
    ],
    "wof:name":"Podol'noye",
    "wof:placetype":"locality"
},
  "geometry": {"coordinates":[39.2878,59.83798],"type":"Point"}
}