{
  "type": "Feature",
  "properties": {
    "gn:admin1_code":"93",
    "gn:asciiname":"Beregovoy",
    "gn:country_code":"RU",
    "gn:dem":674,
    "gn:feature_class":"P",
    "gn:feature_code":"PPL",
    "gn:name":"Beregovoy",
    "gn:population":0,
    "gn:timezone":"Asia/Chita",
    "iso:country":"RU",
    "name:ceb_x_preferred":[
        "Beregovoy"
    ],
    "name:fra_x_preferred":[
        "Famille B\u00e9r\u00e9govoy"
    ],
    "name:hye_x_preferred":[
        "\u0532\u0565\u0580\u0565\u0563\u0578\u057e\u0578"
    ],
    "name:ita_x_preferred":[
        "Beregovoj"
    ],
    "name:nor_x_preferred":[
        "Beregovoj"
    ],
    "name:rus_x_preferred":[
        "\u0411\u0435\u0440\u0435\u0433\u043e\u0432\u043e\u0439"
    ],
    "name:spa_x_preferred":[
        "Beregov\u00f3i"
    ],
    "name:ukr_x_preferred":[
        "\u0411\u0435\u0440\u0435\u0433\u043e\u0432\u0438\u0439"
    ],
    "wof:name":"Beregovoy",
    "wof:placetype":"locality"
},
  "geometry": {"coordinates":[113.48911,52.1959],"type":"Point"}
}