{
  "type": "Feature",
  "properties": {
    "gn:admin1_code":"21",
    "gn:asciiname":"Uvod'",
    "gn:country_code":"RU",
    "gn:dem":134,
    "gn:feature_class":"P",
    "gn:feature_code":"PPL",
    "gn:name":"Uvod\u2019",
    "gn:population":0,
    "gn:timezone":"Europe/Moscow",
    "iso:country":"RU",
    "name:und_x_variant":[
        "Uvod\u2019stroy",
        "Uvod\u2019"
    ],
    "wof:name":"Uvod'",
    "wof:placetype":"locality"
},
  "geometry": {"coordinates":[40.8766,57.05931],"type":"Point"}
}