{
  "type": "Feature",
  "properties": {
    "gn:admin1_code":"47",
    "gn:asciiname":"Trasna",
    "gn:country_code":"RU",
    "gn:dem":166,
    "gn:feature_class":"P",
    "gn:feature_code":"PPL",
    "gn:name":"Trasna",
    "gn:population":0,
    "gn:timezone":"Europe/Moscow",
    "iso:country":"RU",
    "name:und_x_variant":[
        "Trosna",
        "Trasna"
    ],
    "wof:name":"Trasna",
    "wof:placetype":"locality"
},
  "geometry": {"coordinates":[38.69306,54.75216999999999],"type":"Point"}
}