{
  "type": "Feature",
  "properties": {
    "gn:admin1_code":"61.0",
    "gn:asciiname":"Gayevka",
    "gn:country_code":"RU",
    "gn:dem":14,
    "gn:feature_class":"P",
    "gn:feature_code":"PPL",
    "gn:name":"Gayevka",
    "gn:population":0,
    "gn:timezone":"Europe/Moscow",
    "iso:country":"RU",
    "name:eng_x_preferred":[
        "Gayevka"
    ],
    "name:nor_x_preferred":[
        "Gajevka"
    ],
    "name:rus_x_preferred":[
        "\u0413\u0430\u0435\u0432\u043a\u0430"
    ],
    "name:und_x_variant":[
        "Goyevka",
        "Gayevka-Kaymakchi"
    ],
    "wof:name":"Gayevka",
    "wof:placetype":"locality"
},
  "geometry": {"coordinates":[38.6569,47.23815],"type":"Point"}
}