{
  "type": "Feature",
  "properties": {
    "gn:admin1_code":"12.0",
    "gn:asciiname":"Gendergen",
    "gn:country_code":"RU",
    "gn:dem":721,
    "gn:feature_class":"P",
    "gn:feature_code":"PPL",
    "gn:name":"Gendergen",
    "gn:population":0,
    "gn:timezone":"Europe/Moscow",
    "iso:country":"RU",
    "name:che_x_preferred":[
        "Verxnii Siux"
    ],
    "name:che_x_variant":[
        "Gendargana",
        "\u0412\u0435\u0440\u0445\u043d\u0438\u0439 \u0421\u0438\u0443\u0445",
        "\u0413\u0435\u043d\u0434\u0430\u0440\u0433\u0430\u043d\u0430"
    ],
    "name:rus_x_preferred":[
        "\u0413\u0435\u043d\u0434\u0435\u0440\u0433\u0435\u043d"
    ],
    "name:und_x_variant":[
        "Verkhniy Siukh",
        "Nizhniy Siukh",
        "Gendergen"
    ],
    "wof:name":"Gendergen",
    "wof:placetype":"locality"
},
  "geometry": {"coordinates":[46.33442,43.02467],"type":"Point"}
}