{
  "type": "Feature",
  "properties": {
    "gn:admin1_code":"85",
    "gn:asciiname":"Uskovo",
    "gn:country_code":"RU",
    "gn:dem":140,
    "gn:feature_class":"P",
    "gn:feature_code":"PPL",
    "gn:name":"Uskovo",
    "gn:population":0,
    "gn:timezone":"Europe/Moscow",
    "iso:country":"RU",
    "name:rus_x_preferred":[
        "\u0423\u0441\u043a\u043e\u0432\u043e"
    ],
    "name:und_x_variant":[
        "\u0423\u0441\u043a\u043e\u0432\u043e"
    ],
    "wof:name":"Uskovo",
    "wof:placetype":"locality"
},
  "geometry": {"coordinates":[38.5272,59.9628],"type":"Point"}
}