{
  "type": "Feature",
  "properties": {
    "gn:admin1_code":"93",
    "gn:asciiname":"Utesnaya",
    "gn:country_code":"RU",
    "gn:dem":351,
    "gn:feature_class":"P",
    "gn:feature_code":"PPL",
    "gn:name":"Ut\u00ebsnaya",
    "gn:population":0,
    "gn:timezone":"Asia/Chita",
    "iso:country":"RU",
    "wof:name":"Utesnaya",
    "wof:placetype":"locality"
},
  "geometry": {"coordinates":[121.25067,53.50798],"type":"Point"}
}