{
  "type": "Feature",
  "properties": {
    "gn:admin1_code":"8",
    "gn:asciiname":"Starobashirovo",
    "gn:cc2":"RU",
    "gn:country_code":"RU",
    "gn:dem":89,
    "gn:feature_class":"P",
    "gn:feature_code":"PPL",
    "gn:name":"Starobashirovo",
    "gn:population":0,
    "gn:timezone":"Asia/Yekaterinburg",
    "iso:country":"RU",
    "name:bak_x_preferred":[
        "\u0418\u04ab\u043a\u0435 \u0411\u04d9\u0448\u0438\u0440"
    ],
    "name:che_x_preferred":[
        "\u0421\u0442\u0430\u0440\u043e\u0431\u0430\u0448\u0438\u0440\u043e\u0432\u043e"
    ],
    "name:chv_x_preferred":[
        "\u0421\u0442\u0430\u0440\u043e\u0431\u0430\u0448\u0438\u0440\u043e\u0432\u043e"
    ],
    "name:eng_x_preferred":[
        "Starobashirovo"
    ],
    "name:hye_x_preferred":[
        "\u054d\u057f\u0561\u0580\u0578\u0562\u0561\u0577\u056b\u0580\u0578\u057e\u0578"
    ],
    "name:kaz_x_preferred":[
        "\u0415\u0441\u043a\u0456 \u0431\u0430\u0448\u0438\u0440"
    ],
    "name:nor_x_preferred":[
        "Starobasjirovo"
    ],
    "name:rus_x_preferred":[
        "\u0421\u0442\u0430\u0440\u043e\u0431\u0430\u0448\u0438\u0440\u043e\u0432\u043e"
    ],
    "name:tat_x_preferred":[
        "\u0418\u0441\u043a\u0435 \u0411\u04d9\u0448\u0438\u0440"
    ],
    "name:und_x_variant":[
        "Staraya Bashirova",
        "\u0421\u0442\u0430\u0440\u043e\u0431\u0430\u0448\u0438\u0440\u043e\u0432\u043e",
        "Starobashirovo"
    ],
    "wof:name":"Starobashirovo",
    "wof:placetype":"locality"
},
  "geometry": {"coordinates":[55.05778000000001,55.09444000000001],"type":"Point"}
}