{
  "type": "Feature",
  "properties": {
    "gn:admin1_code":"86.0",
    "gn:asciiname":"Salovka",
    "gn:country_code":"RU",
    "gn:dem":88,
    "gn:feature_class":"P",
    "gn:feature_code":"PPL",
    "gn:name":"Salovka",
    "gn:population":0,
    "gn:timezone":"Europe/Moscow",
    "iso:country":"RU",
    "name:rus_x_preferred":[
        "\u0421\u0430\u043b\u043e\u0432\u043a\u0430"
    ],
    "wof:name":"Salovka",
    "wof:placetype":"locality"
},
  "geometry": {"coordinates":[39.29971,50.30584],"type":"Point"}
}