{
  "type": "Feature",
  "properties": {
    "gn:admin1_code":"43",
    "gn:asciiname":"Kulikovka Pervaya",
    "gn:country_code":"RU",
    "gn:dem":118,
    "gn:feature_class":"P",
    "gn:feature_code":"PPL",
    "gn:name":"Kulikovka Pervaya",
    "gn:population":0,
    "gn:timezone":"Europe/Moscow",
    "iso:country":"RU",
    "name:rus_x_preferred":[
        "\u041a\u0443\u043b\u0438\u043a\u043e\u0432\u043a\u0430 \u041f\u0435\u0440\u0432\u0430\u044f"
    ],
    "name:und_x_variant":[
        "\u041a\u0443\u043b\u0438\u043a\u043e\u0432\u043a\u0430 \u041f\u0435\u0440\u0432\u0430\u044f"
    ],
    "wof:name":"Kulikovka Pervaya",
    "wof:placetype":"locality"
},
  "geometry": {"coordinates":[39.01817,52.87911],"type":"Point"}
}