{
  "type": "Feature",
  "properties": {
    "gn:admin1_code":"47",
    "gn:asciiname":"Modenovo",
    "gn:country_code":"RU",
    "gn:dem":196,
    "gn:feature_class":"P",
    "gn:feature_code":"PPL",
    "gn:name":"Modenovo",
    "gn:population":0,
    "gn:timezone":"Europe/Moscow",
    "iso:country":"RU",
    "name:rus_x_preferred":[
        "\u041c\u043e\u0434\u0435\u043d\u043e\u0432\u043e"
    ],
    "wof:name":"Modenovo",
    "wof:placetype":"locality"
},
  "geometry": {"coordinates":[36.25,55.51667],"type":"Point"}
}