{
  "type": "Feature",
  "properties": {
    "gn:admin1_code":"83",
    "gn:asciiname":"Pavlovskoye",
    "gn:country_code":"RU",
    "gn:dem":142,
    "gn:feature_class":"P",
    "gn:feature_code":"PPL",
    "gn:name":"Pavlovskoye",
    "gn:population":0,
    "gn:timezone":"Europe/Moscow",
    "iso:country":"RU",
    "name:eng_x_preferred":[
        "Pavlovskoye"
    ],
    "name:nor_x_preferred":[
        "Pavlovskoje"
    ],
    "name:rus_x_preferred":[
        "\u041f\u0430\u0432\u043b\u043e\u0432\u0441\u043a\u043e\u0435"
    ],
    "wof:name":"Pavlovskoye",
    "wof:placetype":"locality"
},
  "geometry": {"coordinates":[40.47097,56.32458000000001],"type":"Point"}
}