{
  "type": "Feature",
  "properties": {
    "gn:admin1_code":"34",
    "gn:asciiname":"Sivomaskinskiy",
    "gn:cc2":"RU",
    "gn:country_code":"RU",
    "gn:dem":77,
    "gn:feature_class":"P",
    "gn:feature_code":"PPL",
    "gn:name":"Sivomaskinskiy",
    "gn:population":0,
    "gn:timezone":"Europe/Moscow",
    "iso:country":"RU",
    "name:eng_x_preferred":[
        "Sivomaskinskiy"
    ],
    "name:nor_x_preferred":[
        "Sivomaskinskij"
    ],
    "name:rus_x_preferred":[
        "\u0421\u0438\u0432\u043e\u043c\u0430\u0441\u043a\u0438\u043d\u0441\u043a\u0438\u0439"
    ],
    "name:und_x_variant":[
        "Sivaya Maska",
        "Sivomaskinskiy",
        "\u0421\u0438\u0432\u043e\u043c\u0430\u0441\u043a\u0438\u043d\u0441\u043a\u0438\u0439"
    ],
    "wof:name":"Sivomaskinskiy",
    "wof:placetype":"locality"
},
  "geometry": {"coordinates":[62.58333,66.66667],"type":"Point"}
}