{
  "type": "Feature",
  "properties": {
    "gn:admin1_code":"77",
    "gn:asciiname":"Nashchekino",
    "gn:cc2":"RU",
    "gn:country_code":"RU",
    "gn:dem":212,
    "gn:feature_class":"P",
    "gn:feature_code":"PPL",
    "gn:name":"Nashch\u00ebkino",
    "gn:population":0,
    "gn:timezone":"Europe/Moscow",
    "iso:country":"RU",
    "name:rus_x_preferred":[
        "\u041d\u0430\u0449\u0451\u043a\u0438\u043d\u043e"
    ],
    "name:und_x_variant":[
        "Remennitsa",
        "Nashch\u00ebkino",
        "\u041d\u0430\u0449\u0451\u043a\u0438\u043d\u043e"
    ],
    "wof:name":"Nashchekino",
    "wof:placetype":"locality"
},
  "geometry": {"coordinates":[34.53333,57.03333000000001],"type":"Point"}
}