{
  "type": "Feature",
  "properties": {
    "gn:admin1_code":"62",
    "gn:asciiname":"Kopi",
    "gn:country_code":"RU",
    "gn:dem":170,
    "gn:feature_class":"P",
    "gn:feature_code":"PPL",
    "gn:name":"Kopi",
    "gn:population":0,
    "gn:timezone":"Europe/Moscow",
    "iso:country":"RU",
    "name:rus_x_preferred":[
        "\u041a\u043e\u043f\u0438"
    ],
    "name:und_x_variant":[
        "\u041a\u043e\u043f\u0438"
    ],
    "wof:name":"Kopi",
    "wof:placetype":"locality"
},
  "geometry": {"coordinates":[39.3007,53.69600000000001],"type":"Point"}
}