{
  "type": "Feature",
  "properties": {
    "gn:admin1_code":"42",
    "gn:admin2_code":"483008",
    "gn:asciiname":"Koptyayevo",
    "gn:country_code":"RU",
    "gn:dem":128,
    "gn:feature_class":"P",
    "gn:feature_code":"PPL",
    "gn:name":"Koptyayevo",
    "gn:population":0,
    "gn:timezone":"Europe/Moscow",
    "iso:country":"RU",
    "name:rus_x_preferred":[
        "\u041a\u043e\u043f\u0442\u044f\u0435\u0432\u043e"
    ],
    "name:und_x_variant":[
        "Kopt\u00e4jevo",
        "Koptyayevo"
    ],
    "wof:name":"Koptyayevo",
    "wof:placetype":"locality"
},
  "geometry": {"coordinates":[34.53193,60.05954000000001],"type":"Point"}
}