{
  "type": "Feature",
  "properties": {
    "gn:admin1_code":"41",
    "gn:asciiname":"Kitayevka",
    "gn:country_code":"RU",
    "gn:dem":188,
    "gn:feature_class":"P",
    "gn:feature_code":"PPL",
    "gn:name":"Kitayevka",
    "gn:population":0,
    "gn:timezone":"Europe/Moscow",
    "iso:country":"RU",
    "name:rus_x_preferred":[
        "\u041a\u0438\u0442\u0430\u0435\u0432\u043a\u0430"
    ],
    "wof:name":"Kitayevka",
    "wof:placetype":"locality"
},
  "geometry": {"coordinates":[36.33333,51.48333],"type":"Point"}
}