{
  "type": "Feature",
  "properties": {
    "gn:admin1_code":"6",
    "gn:asciiname":"Medvezh'ye",
    "gn:country_code":"RU",
    "gn:dem":128,
    "gn:feature_class":"P",
    "gn:feature_code":"PPL",
    "gn:name":"Medvezh\u2019ye",
    "gn:population":0,
    "gn:timezone":"Europe/Moscow",
    "iso:country":"RU",
    "name:rus_x_preferred":[
        "\u041c\u0435\u0434\u0432\u0435\u0436\u044c\u0435"
    ],
    "name:und_x_variant":[
        "Medvezh\u2019ye"
    ],
    "wof:name":"Medvezh'ye",
    "wof:placetype":"locality"
},
  "geometry": {"coordinates":[44.96611,61.45583000000001],"type":"Point"}
}