{
  "type": "Feature",
  "properties": {
    "gn:admin1_code":"20",
    "gn:asciiname":"Nikolayevskiy",
    "gn:country_code":"RU",
    "gn:dem":498,
    "gn:feature_class":"P",
    "gn:feature_code":"PPL",
    "gn:name":"Nikolayevskiy",
    "gn:population":0,
    "gn:timezone":"Asia/Irkutsk",
    "iso:country":"RU",
    "name:eng_x_preferred":[
        "Nikolayevskiy"
    ],
    "name:nor_x_preferred":[
        "Nikolajevskij"
    ],
    "name:rus_x_preferred":[
        "\u041d\u0438\u043a\u043e\u043b\u0430\u0435\u0432\u0441\u043a\u0438\u0439"
    ],
    "wof:name":"Nikolayevskiy",
    "wof:placetype":"locality"
},
  "geometry": {"coordinates":[102.14,53.63222],"type":"Point"}
}