{
  "type": "Feature",
  "properties": {
    "gn:admin1_code":"81.0",
    "gn:asciiname":"Agarevka",
    "gn:country_code":"RU",
    "gn:dem":154,
    "gn:feature_class":"P",
    "gn:feature_code":"PPL",
    "gn:name":"Agar\u00ebvka",
    "gn:population":0,
    "gn:timezone":"Europe/Ulyanovsk",
    "iso:country":"RU",
    "name:nor_x_preferred":[
        "Agarjovka"
    ],
    "name:rus_x_preferred":[
        "\u0410\u0433\u0430\u0440\u0451\u0432\u043a\u0430"
    ],
    "name:und_x_variant":[
        "Ogarevka",
        "Agar\u00ebvka"
    ],
    "wof:name":"Agarevka",
    "wof:placetype":"locality"
},
  "geometry": {"coordinates":[47.43333,53.06667],"type":"Point"}
}