{
  "type": "Feature",
  "properties": {
    "gn:admin1_code":"75",
    "gn:asciiname":"Arapkino",
    "gn:country_code":"RU",
    "gn:dem":80,
    "gn:feature_class":"P",
    "gn:feature_code":"PPL",
    "gn:name":"Arapkino",
    "gn:population":0,
    "gn:timezone":"Asia/Tomsk",
    "iso:country":"RU",
    "name:nor_x_preferred":[
        "Arapkino"
    ],
    "name:rus_x_preferred":[
        "\u0410\u0440\u0430\u043f\u043a\u0438\u043d\u043e"
    ],
    "wof:name":"Arapkino",
    "wof:placetype":"locality"
},
  "geometry": {"coordinates":[84.98333000000002,57.81667],"type":"Point"}
}