{
  "type": "Feature",
  "properties": {
    "gn:admin1_code":"91",
    "gn:asciiname":"Vereshchagino",
    "gn:country_code":"RU",
    "gn:dem":43,
    "gn:feature_class":"P",
    "gn:feature_code":"PPL",
    "gn:name":"Vereshchagino",
    "gn:population":0,
    "gn:timezone":"Asia/Krasnoyarsk",
    "iso:country":"RU",
    "name:eng_x_preferred":[
        "Vereshchagino"
    ],
    "name:nor_x_preferred":[
        "Veresjtsjagino"
    ],
    "name:rus_x_preferred":[
        "\u0412\u0435\u0440\u0435\u0449\u0430\u0433\u0438\u043d\u043e"
    ],
    "name:tgl_x_preferred":[
        "Vereshchagino"
    ],
    "name:udm_x_preferred":[
        "\u0412\u0435\u0440\u0435\u0449\u0430\u0433\u0438\u043d\u043e"
    ],
    "name:und_x_variant":[
        "Yamskaya"
    ],
    "wof:name":"Vereshchagino",
    "wof:placetype":"locality"
},
  "geometry": {"coordinates":[87.57536,64.2424],"type":"Point"}
}