{
  "type": "Feature",
  "properties": {
    "gn:admin1_code":"42",
    "gn:asciiname":"Valyanitsa",
    "gn:country_code":"RU",
    "gn:dem":92,
    "gn:feature_class":"P",
    "gn:feature_code":"PPL",
    "gn:name":"Valyanitsa",
    "gn:population":0,
    "gn:timezone":"Europe/Moscow",
    "iso:country":"RU",
    "name:fin_x_preferred":[
        "Voloitsa"
    ],
    "name:rus_x_preferred":[
        "\u0412\u043e\u043b\u043e\u043d\u0438\u0446\u044b"
    ],
    "wof:name":"Valyanitsa",
    "wof:placetype":"locality"
},
  "geometry": {"coordinates":[28.48722,59.78902],"type":"Point"}
}