{
  "type": "Feature",
  "properties": {
    "gn:country":"RU",
    "gn:fcode":"PPL",
    "gn:pop":983,
    "iso:country":"RU",
    "name:ara_x_preferred":[
        "\u0632\u0627\u0634\u064a\u064a\u0643"
    ],
    "name:arm_x_preferred":[
        "\u0536\u0561\u0577\u0565\u0565\u056f"
    ],
    "name:che_x_preferred":[
        "\u0417\u0430\u0448\u0435\u0435\u043a"
    ],
    "name:eng_x_preferred":[
        "Zasheyek"
    ],
    "name:fin_x_preferred":[
        "Nivanniska"
    ],
    "name:nor_x_preferred":[
        "Zasjejek"
    ],
    "name:rus_x_preferred":[
        "\u0417\u0430\u0448\u0435\u0435\u043a"
    ],
    "name:unk_x_variant":[
        "Pos\u00eblok Zasheyek"
    ],
    "qs:name":"Zasheyek",
    "qs:name_adm0":"Russia",
    "qs:name_adm1":"Murmansk Oblast",
    "qs:photos_9k":1,
    "qs:photos_9r":1,
    "qs:photos_all":6,
    "qs:photos_sr":0,
    "qs:placetype":"Town",
    "qs:pop_sr":"2",
    "wd:wordcount":46,
    "wof:name":"Zasheyek",
    "wof:placetype":"locality",
    "wof:population":983
},
  "geometry": {"coordinates":[32.54803,67.40406],"type":"Point"}
}