{
  "type": "Feature",
  "properties": {
    "gn:admin1_code":"69.0",
    "gn:asciiname":"Lakhovo",
    "gn:country_code":"RU",
    "gn:dem":180,
    "gn:feature_class":"P",
    "gn:feature_code":"PPL",
    "gn:name":"Lakhovo",
    "gn:population":0,
    "gn:timezone":"Europe/Moscow",
    "iso:country":"RU",
    "name:rus_x_preferred":[
        "\u041b\u0430\u0445\u043e\u0432\u043e"
    ],
    "name:und_x_variant":[
        "Bol\u2019shoye Lakhovo",
        "Lakhovo"
    ],
    "wof:name":"Lakhovo",
    "wof:placetype":"locality"
},
  "geometry": {"coordinates":[34.43278,54.83889],"type":"Point"}
}