{
  "type": "Feature",
  "properties": {
    "gn:admin1_code":"75",
    "gn:asciiname":"Ust'-Syraya",
    "gn:country_code":"RU",
    "gn:dem":125,
    "gn:feature_class":"P",
    "gn:feature_code":"PPL",
    "gn:name":"Ust\u2019-Syraya",
    "gn:population":0,
    "gn:timezone":"Asia/Tomsk",
    "iso:country":"RU",
    "name:und_x_variant":[
        "Ust\u2019-Syroy",
        "Ust\u2019-Syraya"
    ],
    "wof:name":"Ust'-Syraya",
    "wof:placetype":"locality"
},
  "geometry": {"coordinates":[88.15000000000001,57.05],"type":"Point"}
}