{
  "type": "Feature",
  "properties": {
    "gn:admin1_code":"60",
    "gn:asciiname":"Romonyaty",
    "gn:country_code":"RU",
    "gn:dem":67,
    "gn:feature_class":"P",
    "gn:feature_code":"PPL",
    "gn:name":"Romonyaty",
    "gn:population":0,
    "gn:timezone":"Europe/Moscow",
    "iso:country":"RU",
    "name:rus_x_preferred":[
        "\u0420\u043e\u043c\u043e\u043d\u044f\u0442\u044b"
    ],
    "wof:name":"Romonyaty",
    "wof:placetype":"locality"
},
  "geometry": {"coordinates":[28.42762,57.19233000000001],"type":"Point"}
}