{
  "type": "Feature",
  "properties": {
    "gn:admin1_code":"90",
    "gn:asciiname":"Nyuzim",
    "gn:country_code":"RU",
    "gn:dem":165,
    "gn:feature_class":"P",
    "gn:feature_code":"PPL",
    "gn:name":"Nyuzim",
    "gn:population":0,
    "gn:timezone":"Asia/Yekaterinburg",
    "iso:country":"RU",
    "name:eng_x_preferred":[
        "Nyuzim"
    ],
    "name:nor_x_preferred":[
        "Njuzim"
    ],
    "name:rus_x_preferred":[
        "\u041d\u044e\u0437\u0438\u043c"
    ],
    "name:und_x_variant":[
        "Nuyzim"
    ],
    "wof:name":"Nyuzim",
    "wof:placetype":"locality"
},
  "geometry": {"coordinates":[57.49226,61.38665],"type":"Point"}
}