{
  "type": "Feature",
  "properties": {
    "gn:admin1_code":"53",
    "gn:asciiname":"Firsovskiy",
    "gn:country_code":"RU",
    "gn:dem":343,
    "gn:feature_class":"P",
    "gn:feature_code":"PPL",
    "gn:name":"Firsovskiy",
    "gn:population":0,
    "gn:timezone":"Asia/Novosibirsk",
    "iso:country":"RU",
    "name:rus_x_preferred":[
        "\u0424\u0438\u0440\u0441\u043e\u0432\u0441\u043a\u0438\u0439"
    ],
    "wof:name":"Firsovskiy",
    "wof:placetype":"locality"
},
  "geometry": {"coordinates":[84.06667,54.78333000000001],"type":"Point"}
}