{
  "type": "Feature",
  "properties": {
    "gn:admin1_code":"62",
    "gn:asciiname":"Turmadeyevo",
    "gn:country_code":"RU",
    "gn:dem":105,
    "gn:feature_class":"P",
    "gn:feature_code":"PPL",
    "gn:name":"Turmadeyevo",
    "gn:population":0,
    "gn:timezone":"Europe/Moscow",
    "iso:country":"RU",
    "name:rus_x_preferred":[
        "\u0422\u0443\u0440\u043c\u0430\u0434\u0435\u0435\u0432\u043e"
    ],
    "wof:name":"Turmadeyevo",
    "wof:placetype":"locality"
},
  "geometry": {"coordinates":[42.3658,54.7166],"type":"Point"}
}