{
  "type": "Feature",
  "properties": {
    "gn:admin1_code":"80",
    "gn:asciiname":"Tuga",
    "gn:country_code":"RU",
    "gn:dem":181,
    "gn:feature_class":"P",
    "gn:feature_code":"PPL",
    "gn:name":"Tuga",
    "gn:population":0,
    "gn:timezone":"Europe/Samara",
    "iso:country":"RU",
    "name:rus_x_preferred":[
        "\u0422\u0443\u0433\u0430"
    ],
    "wof:name":"Tuga",
    "wof:placetype":"locality"
},
  "geometry": {"coordinates":[53.3039,57.7343],"type":"Point"}
}