{
  "type": "Feature",
  "properties": {
    "gn:admin1_code":"69",
    "gn:asciiname":"Dobroye",
    "gn:country_code":"RU",
    "gn:dem":252,
    "gn:feature_class":"P",
    "gn:feature_code":"PPL",
    "gn:name":"Dobroye",
    "gn:population":0,
    "gn:timezone":"Europe/Moscow",
    "iso:country":"RU",
    "name:rus_x_preferred":[
        "\u0414\u043e\u0431\u0440\u043e\u0435"
    ],
    "name:und_x_variant":[
        "\u0414\u043e\u0431\u0440\u043e\u0435"
    ],
    "wof:name":"Dobroye",
    "wof:placetype":"locality"
},
  "geometry": {"coordinates":[33.58917,54.47694],"type":"Point"}
}