{
  "type": "Feature",
  "properties": {
    "gn:admin1_code":"33.0",
    "gn:asciiname":"Russkaya Shuyma",
    "gn:country_code":"RU",
    "gn:dem":132,
    "gn:feature_class":"P",
    "gn:feature_code":"PPL",
    "gn:name":"Russkaya Shuyma",
    "gn:population":0,
    "gn:timezone":"Europe/Kirov",
    "iso:country":"RU",
    "name:eng_x_preferred":[
        "Bol'shaya Shuyma"
    ],
    "name:nor_x_preferred":[
        "Russkaja Sjujma"
    ],
    "name:rus_x_preferred":[
        "\u0420\u0443\u0441\u0441\u043a\u0430\u044f \u0428\u0443\u0439\u043c\u0430"
    ],
    "name:und_x_variant":[
        "\u0420\u0443\u0441\u0441\u043a\u0430\u044f \u0428\u0443\u0439\u043c\u0430",
        "Bol\u2019shaya Shuyma",
        "Russkaya Shuyma"
    ],
    "wof:name":"Russkaya Shuyma",
    "wof:placetype":"locality"
},
  "geometry": {"coordinates":[48.342,57.3313],"type":"Point"}
}