{
  "type": "Feature",
  "properties": {
    "gn:admin1_code":"11",
    "gn:asciiname":"Angarakan",
    "gn:country_code":"RU",
    "gn:dem":462,
    "gn:feature_class":"P",
    "gn:feature_code":"PPL",
    "gn:name":"Angarakan",
    "gn:population":0,
    "gn:timezone":"Asia/Irkutsk",
    "iso:country":"RU",
    "name:eng_x_preferred":[
        "Angarakan"
    ],
    "name:nor_x_preferred":[
        "Angarakan"
    ],
    "name:rus_x_preferred":[
        "\u0410\u043d\u0433\u0430\u0440\u0430\u043a\u0430\u043d"
    ],
    "wof:name":"Angarakan",
    "wof:placetype":"locality"
},
  "geometry": {"coordinates":[110.10366999999999,55.82709000000001],"type":"Point"}
}