{
  "type": "Feature",
  "properties": {
    "gn:admin1_code":"78",
    "gn:asciiname":"Nizhnepinigino",
    "gn:country_code":"RU",
    "gn:dem":110,
    "gn:feature_class":"P",
    "gn:feature_code":"PPL",
    "gn:name":"Nizhnepinigino",
    "gn:population":0,
    "gn:timezone":"Asia/Yekaterinburg",
    "iso:country":"RU",
    "name:eng_x_preferred":[
        "Nizhnepinigino"
    ],
    "name:nor_x_preferred":[
        "Nizjnepinigino"
    ],
    "name:rus_x_preferred":[
        "\u041d\u0438\u0436\u043d\u0435\u043f\u0438\u043d\u0438\u0433\u0438\u043d\u043e"
    ],
    "name:und_x_variant":[
        "\u041d\u0438\u0436\u043d\u0435\u043f\u0438\u043d\u0438\u0433\u0438\u043d\u043e",
        "Nizhnepinigino"
    ],
    "wof:name":"Nizhnepinigino",
    "wof:placetype":"locality"
},
  "geometry": {"coordinates":[69.9562,56.5082],"type":"Point"}
}