{
  "type": "Feature",
  "properties": {
    "gn:admin1_code":"42",
    "gn:asciiname":"Ozera-Selivanovskaya",
    "gn:cc2":"RU",
    "gn:country_code":"RU",
    "gn:dem":111,
    "gn:feature_class":"P",
    "gn:feature_code":"PPL",
    "gn:name":"Oz\u00ebra-Selivanovskaya",
    "gn:population":0,
    "gn:timezone":"Europe/Moscow",
    "iso:country":"RU",
    "name:und_x_variant":[
        "Selivanovskaya"
    ],
    "wof:name":"Ozera-Selivanovskaya",
    "wof:placetype":"locality"
},
  "geometry": {"coordinates":[34.84139,60.46444],"type":"Point"}
}