{
  "type": "Feature",
  "properties": {
    "gn:admin1_code":"90",
    "gn:asciiname":"Ponomarevka",
    "gn:country_code":"RU",
    "gn:dem":117,
    "gn:feature_class":"P",
    "gn:feature_code":"PPL",
    "gn:name":"Ponomar\u00ebvka",
    "gn:population":0,
    "gn:timezone":"Asia/Yekaterinburg",
    "iso:country":"RU",
    "name:rus_x_preferred":[
        "Ponomar\u00ebvka"
    ],
    "name:rus_x_variant":[
        "\u041f\u043e\u043d\u043e\u043c\u0430\u0440\u00eb\u0432\u043a\u0430"
    ],
    "wof:name":"Ponomarevka",
    "wof:placetype":"locality"
},
  "geometry": {"coordinates":[56.798,57.4653],"type":"Point"}
}