{
  "type": "Feature",
  "properties": {
    "gn:admin1_code":"90.0",
    "gn:asciiname":"Dubovaya",
    "gn:country_code":"RU",
    "gn:dem":154,
    "gn:feature_class":"P",
    "gn:feature_code":"PPL",
    "gn:name":"Dubovaya",
    "gn:population":0,
    "gn:timezone":"Asia/Yekaterinburg",
    "iso:country":"RU",
    "name:rus_x_preferred":[
        "\u0414\u0443\u0431\u043e\u0432\u0430\u044f"
    ],
    "name:und_x_variant":[
        "\u0414\u0443\u0431\u043e\u0432\u0430\u044f"
    ],
    "wof:name":"Dubovaya",
    "wof:placetype":"locality"
},
  "geometry": {"coordinates":[54.1493,56.6414],"type":"Point"}
}