{
  "type": "Feature",
  "properties": {
    "gn:country":"RU",
    "gn:fcode":"PPL",
    "gn:pop":0,
    "iso:country":"RU",
    "name:rus_x_preferred":[
        "\u041b\u0435\u043e\u043d\u0438\u0445\u0430"
    ],
    "qs:name":"Leonikha",
    "qs:name_adm0":"Russia",
    "qs:name_adm1":"Moscow Oblast",
    "qs:photos_9r":0,
    "qs:photos_sr":0,
    "qs:placetype":"Town",
    "qs:pop_sr":"0",
    "wof:name":"Leonikha",
    "wof:placetype":"locality",
    "wof:population":0
},
  "geometry": {"coordinates":[38.09315,55.88602],"type":"Point"}
}