{
  "type": "Feature",
  "properties": {
    "gn:admin1_code":"77",
    "gn:asciiname":"Smotrovo",
    "gn:country_code":"RU",
    "gn:dem":215,
    "gn:feature_class":"P",
    "gn:feature_code":"PPL",
    "gn:name":"Smotrovo",
    "gn:population":0,
    "gn:timezone":"Europe/Moscow",
    "iso:country":"RU",
    "name:rus_x_preferred":[
        "\u0421\u043c\u043e\u0442\u0440\u043e\u0432\u043e"
    ],
    "name:und_x_variant":[
        "\u0421\u043c\u043e\u0442\u0440\u043e\u0432\u043e"
    ],
    "wof:name":"Smotrovo",
    "wof:placetype":"locality"
},
  "geometry": {"coordinates":[34.24105,57.41307],"type":"Point"}
}