{
  "type": "Feature",
  "properties": {
    "gn:admin1_code":"32",
    "gn:asciiname":"Punga",
    "gn:country_code":"RU",
    "gn:dem":25,
    "gn:feature_class":"P",
    "gn:feature_code":"PPL",
    "gn:name":"Punga",
    "gn:population":0,
    "gn:timezone":"Asia/Yekaterinburg",
    "iso:country":"RU",
    "name:ceb_x_preferred":[
        "Punga"
    ],
    "name:deu_x_preferred":[
        "Punga"
    ],
    "name:eng_x_preferred":[
        "Punga"
    ],
    "name:nor_x_preferred":[
        "Punga"
    ],
    "name:rus_x_preferred":[
        "\u041f\u0443\u043d\u0433\u0430"
    ],
    "name:swe_x_preferred":[
        "Punga"
    ],
    "wof:name":"Punga",
    "wof:placetype":"locality"
},
  "geometry": {"coordinates":[64.35194,62.76221999999999],"type":"Point"}
}