{
  "type": "Feature",
  "properties": {
    "gn:admin1_code":"38",
    "gn:asciiname":"Kul'sha",
    "gn:country_code":"RU",
    "gn:dem":53,
    "gn:feature_class":"P",
    "gn:feature_code":"PPL",
    "gn:name":"Kul\u2019sha",
    "gn:population":0,
    "gn:timezone":"Europe/Moscow",
    "iso:country":"RU",
    "name:rus_x_preferred":[
        "\u041a\u0443\u043b\u044c\u0448\u0430"
    ],
    "name:und_x_variant":[
        "Kul\u2019sha"
    ],
    "wof:name":"Kul'sha",
    "wof:placetype":"locality"
},
  "geometry": {"coordinates":[39.98333,46.43333],"type":"Point"}
}