{
  "type": "Feature",
  "properties": {
    "gn:admin1_code":"57",
    "gn:asciiname":"Lyacha",
    "gn:country_code":"RU",
    "gn:dem":144,
    "gn:feature_class":"P",
    "gn:feature_code":"PPL",
    "gn:name":"Lyacha",
    "gn:population":0,
    "gn:timezone":"Europe/Moscow",
    "iso:country":"RU",
    "name:rus_x_preferred":[
        "\u041b\u044f\u0447\u0430"
    ],
    "name:und_x_variant":[
        "\u041b\u044f\u0447\u0430"
    ],
    "wof:name":"Lyacha",
    "wof:placetype":"locality"
},
  "geometry": {"coordinates":[43.69958,53.68606],"type":"Point"}
}