{
  "type": "Feature",
  "properties": {
    "gn:admin1_code":"77",
    "gn:asciiname":"Veski Porechskiye",
    "gn:country_code":"RU",
    "gn:dem":126,
    "gn:feature_class":"P",
    "gn:feature_code":"PPL",
    "gn:name":"Veski Porechskiye",
    "gn:population":0,
    "gn:timezone":"Europe/Moscow",
    "iso:country":"RU",
    "name:rus_x_preferred":[
        "\u0412\u0435\u0441\u043a\u0438 \u041f\u043e\u0440\u0435\u0447\u0441\u043a\u0438\u0435"
    ],
    "wof:name":"Veski Porechskiye",
    "wof:placetype":"locality"
},
  "geometry": {"coordinates":[37.98,57.0835],"type":"Point"}
}