{
  "type": "Feature",
  "properties": {
    "gn:country":"RU",
    "gn:fcode":"PPL",
    "gn:population":597,
    "iso:country":"RU",
    "name:rus_x_preferred":[
        "\u0417\u0430\u043d\u043e\u0433\u0438"
    ],
    "qs:name":"Zanogi",
    "qs:photos_9r":0,
    "qs:photos_sr":0,
    "qs:pop_sr":"2",
    "wof:name":"Zanogi",
    "wof:placetype":"locality",
    "wof:population":597
},
  "geometry": {"coordinates":[28.96211,56.52688],"type":"Point"}
}