{
  "type": "Feature",
  "properties": {
    "gn:admin1_code":"8",
    "gn:asciiname":"Khusainovo",
    "gn:country_code":"RU",
    "gn:dem":122,
    "gn:feature_class":"P",
    "gn:feature_code":"PPL",
    "gn:name":"Khusainovo",
    "gn:population":0,
    "gn:timezone":"Asia/Yekaterinburg",
    "iso:country":"RU",
    "name:rus_x_preferred":[
        "\u0425\u0443\u0441\u0430\u0438\u043d\u043e\u0432\u043e"
    ],
    "name:und_x_variant":[
        "Starokhusainovo",
        "Khusainovo",
        "\u0425\u0443\u0441\u0430\u0438\u043d\u043e\u0432\u043e"
    ],
    "wof:name":"Khusainovo",
    "wof:placetype":"locality"
},
  "geometry": {"coordinates":[55.55914,54.10858],"type":"Point"}
}