{
  "type": "Feature",
  "properties": {
    "gn:admin1_code":"8",
    "gn:asciiname":"Khusainovo",
    "gn:country_code":"RU",
    "gn:dem":122,
    "gn:feature_class":"P",
    "gn:feature_code":"PPL",
    "gn:name":"Khusainovo",
    "gn:population":0,
    "gn:timezone":"Asia/Yekaterinburg",
    "iso:country":"RU",
    "name:aze_x_preferred":[
        "H\u00fcseyn"
    ],
    "name:bak_x_preferred":[
        "\u0425\u04e9\u0441\u04d9\u0439\u0435\u043d"
    ],
    "name:che_x_preferred":[
        "\u0425\u0443\u0441\u0430\u0438\u043d\u043e\u0432\u043e"
    ],
    "name:hye_x_preferred":[
        "\u053d\u0578\u0582\u057d\u0561\u056b\u0576\u0578\u057e\u0578"
    ],
    "name:kat_x_preferred":[
        "\u10f0\u10e3\u10e1\u10d0\u10d8\u10dc\u10dd\u10d5\u10dd"
    ],
    "name:kaz_x_preferred":[
        "\u0425\u0443\u0441\u0430\u0439\u044b\u043d"
    ],
    "name:kir_x_preferred":[
        "\u0425\u0443\u0441\u0430\u0439\u044b\u043d"
    ],
    "name:rus_x_preferred":[
        "\u0425\u0443\u0441\u0430\u0438\u043d\u043e\u0432\u043e"
    ],
    "name:tat_x_preferred":[
        "\u0425\u04e9\u0441\u04d9\u0435\u043d"
    ],
    "name:ukr_x_preferred":[
        "\u0425\u0443\u0441\u0430\u0457\u043d\u043e\u0432\u043e"
    ],
    "name:und_x_variant":[
        "Starokhusainovo",
        "Khusainovo"
    ],
    "wof:name":"Khusainovo",
    "wof:placetype":"locality"
},
  "geometry": {"coordinates":[55.55914,54.10858],"type":"Point"}
}