{
  "type": "Feature",
  "properties": {
    "gn:admin1_code":"4",
    "gn:asciiname":"Staraya Azhinka",
    "gn:country_code":"RU",
    "gn:dem":265,
    "gn:feature_class":"P",
    "gn:feature_code":"PPL",
    "gn:name":"Staraya Azhinka",
    "gn:population":0,
    "gn:timezone":"Asia/Barnaul",
    "iso:country":"RU",
    "name:eng_x_preferred":[
        "Staraya Azhinka"
    ],
    "name:nor_x_preferred":[
        "Star.Azjinka"
    ],
    "name:rus_x_preferred":[
        "\u0421\u0442\u0430\u0440.\u0410\u0436\u0438\u043d\u043a\u0430"
    ],
    "name:rus_x_variant":[
        "\u0421\u0442\u0430\u0440\u0430\u044f \u0410\u0436\u0438\u043d\u043a\u0430"
    ],
    "wof:name":"Staraya Azhinka",
    "wof:placetype":"locality"
},
  "geometry": {"coordinates":[86.3905,52.6388],"type":"Point"}
}