{
  "type": "Feature",
  "properties": {
    "gn:admin1_code":"20.0",
    "gn:asciiname":"Kirkhay",
    "gn:country_code":"RU",
    "gn:dem":575,
    "gn:feature_class":"P",
    "gn:feature_code":"PPL",
    "gn:name":"Kirkhay",
    "gn:population":0,
    "gn:timezone":"Asia/Irkutsk",
    "iso:country":"RU",
    "name:rus_x_preferred":[
        "\u041a\u0438\u0440\u0445\u0430\u0439"
    ],
    "wof:name":"Kirkhay",
    "wof:placetype":"locality"
},
  "geometry": {"coordinates":[102.14749999999999,53.3401],"type":"Point"}
}