{
  "type": "Feature",
  "properties": {
    "gn:admin1_code":"73",
    "gn:asciiname":"Kolkomerka",
    "gn:country_code":"RU",
    "gn:dem":91,
    "gn:feature_class":"P",
    "gn:feature_code":"PPL",
    "gn:name":"Kolkomerka",
    "gn:population":0,
    "gn:timezone":"Europe/Moscow",
    "iso:country":"RU",
    "name:rus_x_preferred":[
        "\u041a\u043e\u043b\u043a\u043e\u043c\u0435\u0440\u043a\u0430"
    ],
    "wof:name":"Kolkomerka",
    "wof:placetype":"locality"
},
  "geometry": {"coordinates":[49.98855,55.71306],"type":"Point"}
}