{
  "type": "Feature",
  "properties": {
    "gn:admin1_code":"76.0",
    "gn:asciiname":"Svinskaya",
    "gn:country_code":"RU",
    "gn:dem":181,
    "gn:feature_class":"P",
    "gn:feature_code":"PPL",
    "gn:name":"Svinskaya",
    "gn:population":0,
    "gn:timezone":"Europe/Moscow",
    "iso:country":"RU",
    "name:und_x_variant":[
        "Pos\u00eblok Svinskaya",
        "Svinskaya"
    ],
    "wof:name":"Svinskaya",
    "wof:placetype":"locality"
},
  "geometry": {"coordinates":[37.36912,54.83004],"type":"Point"}
}