{
  "type": "Feature",
  "properties": {
    "gn:admin1_code":"33.0",
    "gn:asciiname":"Solodily",
    "gn:country_code":"RU",
    "gn:dem":177,
    "gn:feature_class":"P",
    "gn:feature_code":"PPL",
    "gn:name":"Solodily",
    "gn:population":0,
    "gn:timezone":"Europe/Kirov",
    "iso:country":"RU",
    "name:rus_x_preferred":[
        "\u0421\u043e\u043b\u043e\u0434\u0438\u043b\u044b"
    ],
    "name:und_x_variant":[
        "\u0421\u043e\u043b\u043e\u0434\u0438\u043b\u044b"
    ],
    "wof:name":"Solodily",
    "wof:placetype":"locality"
},
  "geometry": {"coordinates":[50.61338,58.20506999999999],"type":"Point"}
}