{
  "type": "Feature",
  "properties": {
    "gn:admin1_code":"33",
    "gn:asciiname":"Serdezh",
    "gn:country_code":"RU",
    "gn:dem":133,
    "gn:feature_class":"P",
    "gn:feature_code":"PPL",
    "gn:name":"Serdezh",
    "gn:population":0,
    "gn:timezone":"Europe/Kirov",
    "iso:country":"RU",
    "name:eng_x_preferred":[
        "Serdezh"
    ],
    "name:nor_x_preferred":[
        "Serdezj"
    ],
    "name:rus_x_preferred":[
        "\u0421\u0435\u0440\u0434\u0435\u0436"
    ],
    "name:und_x_variant":[
        "Serdesh"
    ],
    "wof:name":"Serdezh",
    "wof:placetype":"locality"
},
  "geometry": {"coordinates":[48.2886,57.2804],"type":"Point"}
}