{
  "type": "Feature",
  "properties": {
    "gn:admin1_code":"60",
    "gn:asciiname":"Lipovets",
    "gn:country_code":"RU",
    "gn:dem":194,
    "gn:feature_class":"P",
    "gn:feature_code":"PPL",
    "gn:name":"Lipovets",
    "gn:population":0,
    "gn:timezone":"Europe/Moscow",
    "iso:country":"RU",
    "name:rus_x_preferred":[
        "\u041b\u0438\u043f\u043e\u0432\u0435\u0446"
    ],
    "wof:name":"Lipovets",
    "wof:placetype":"locality"
},
  "geometry": {"coordinates":[29.1125,56.7732],"type":"Point"}
}