{
  "type": "Feature",
  "properties": {
    "gn:admin1_code":"28",
    "gn:asciiname":"Sunskiy",
    "gn:country_code":"RU",
    "gn:dem":30,
    "gn:feature_class":"P",
    "gn:feature_code":"PPL",
    "gn:name":"Sunskiy",
    "gn:population":0,
    "gn:timezone":"Europe/Moscow",
    "iso:country":"RU",
    "name:fin_x_preferred":[
        "Suunu"
    ],
    "name:und_x_variant":[
        "\u0421\u0443\u043d\u0441\u043a\u0438\u0439"
    ],
    "wof:name":"Sunskiy",
    "wof:placetype":"locality"
},
  "geometry": {"coordinates":[34.24679,62.10742],"type":"Point"}
}