{
  "type": "Feature",
  "properties": {
    "gn:admin1_code":"75",
    "gn:asciiname":"Karbyshevo",
    "gn:country_code":"RU",
    "gn:dem":130,
    "gn:feature_class":"P",
    "gn:feature_code":"PPL",
    "gn:name":"Karbyshevo",
    "gn:population":0,
    "gn:timezone":"Asia/Tomsk",
    "iso:country":"RU",
    "name:eng_x_preferred":[
        "Karbysheva"
    ],
    "name:nor_x_preferred":[
        "Karbysjevo"
    ],
    "name:rus_x_preferred":[
        "\u041a\u0430\u0440\u0431\u044b\u0448\u0435\u0432\u043e"
    ],
    "name:und_x_variant":[
        "Karbyshevo"
    ],
    "wof:name":"Karbyshevo",
    "wof:placetype":"locality"
},
  "geometry": {"coordinates":[84.44917,56.48721999999999],"type":"Point"}
}