{
  "type": "Feature",
  "properties": {
    "gn:admin1_code":"81.0",
    "gn:asciiname":"Patrikeyevo",
    "gn:country_code":"RU",
    "gn:dem":291,
    "gn:feature_class":"P",
    "gn:feature_code":"PPL",
    "gn:name":"Patrikeyevo",
    "gn:population":0,
    "gn:timezone":"Europe/Ulyanovsk",
    "iso:country":"RU",
    "name:rus_x_preferred":[
        "\u041f\u0430\u0442\u0440\u0438\u043a\u0435\u0435\u0432\u043e"
    ],
    "wof:name":"Patrikeyevo",
    "wof:placetype":"locality"
},
  "geometry": {"coordinates":[46.8296,53.6736],"type":"Point"}
}