{
  "type": "Feature",
  "properties": {
    "gn:admin1_code":"60",
    "gn:asciiname":"Akhmylovo",
    "gn:country_code":"RU",
    "gn:dem":91,
    "gn:feature_class":"P",
    "gn:feature_code":"PPL",
    "gn:name":"Akhmylovo",
    "gn:population":0,
    "gn:timezone":"Europe/Moscow",
    "iso:country":"RU",
    "name:rus_x_preferred":[
        "\u0410\u0445\u043c\u044b\u043b\u043e\u0432\u043e"
    ],
    "wof:name":"Akhmylovo",
    "wof:placetype":"locality"
},
  "geometry": {"coordinates":[28.53896,56.7689],"type":"Point"}
}