{
  "type": "Feature",
  "properties": {
    "gn:admin1_code":"65",
    "gn:asciiname":"Novoye Yakushkino",
    "gn:country_code":"RU",
    "gn:dem":109,
    "gn:feature_class":"P",
    "gn:feature_code":"PPL",
    "gn:name":"Novoye Yakushkino",
    "gn:population":0,
    "gn:timezone":"Europe/Samara",
    "iso:country":"RU",
    "name:eng_x_preferred":[
        "Novoye Yakushkino"
    ],
    "name:nor_x_preferred":[
        "Novoje Jakusjkino"
    ],
    "name:rus_x_preferred":[
        "\u041d\u043e\u0432\u043e\u0435 \u042f\u043a\u0443\u0448\u043a\u0438\u043d\u043e"
    ],
    "name:und_x_variant":[
        "\u041d\u043e\u0432\u043e\u0435 \u042f\u043a\u0443\u0448\u043a\u0438\u043d\u043e",
        "Novoye Yakushkino"
    ],
    "wof:name":"Novoye Yakushkino",
    "wof:placetype":"locality"
},
  "geometry": {"coordinates":[51.51756,53.94532],"type":"Point"}
}