{
  "type": "Feature",
  "properties": {
    "gn:admin1_code":"71",
    "gn:asciiname":"Molokova",
    "gn:country_code":"RU",
    "gn:dem":74,
    "gn:feature_class":"P",
    "gn:feature_code":"PPL",
    "gn:name":"Molokova",
    "gn:population":0,
    "gn:timezone":"Asia/Yekaterinburg",
    "iso:country":"RU",
    "name:eng_x_preferred":[
        "Molokova"
    ],
    "name:nor_x_preferred":[
        "Molokovo"
    ],
    "name:rus_x_preferred":[
        "\u041c\u043e\u043b\u043e\u043a\u043e\u0432\u043e"
    ],
    "name:rus_x_variant":[
        "\u041c\u043e\u043b\u043e\u043a\u043e\u0432\u0430"
    ],
    "name:und_x_variant":[
        "Molokovo",
        "Molokova",
        "\u041c\u043e\u043b\u043e\u043a\u043e\u0432\u0430"
    ],
    "wof:name":"Molokova",
    "wof:placetype":"locality"
},
  "geometry": {"coordinates":[62.66972,57.50474000000001],"type":"Point"}
}