{
  "type": "Feature",
  "properties": {
    "gn:admin1_code":"77.0",
    "gn:asciiname":"Borshchevo",
    "gn:country_code":"RU",
    "gn:dem":126,
    "gn:feature_class":"P",
    "gn:feature_code":"PPL",
    "gn:name":"Borshch\u00ebvo",
    "gn:population":0,
    "gn:timezone":"Europe/Moscow",
    "iso:country":"RU",
    "name:rus_x_preferred":[
        "\u0411\u043e\u0440\u0449\u0451\u0432\u043e"
    ],
    "name:und_x_variant":[
        "Borshch\u00ebvo"
    ],
    "wof:name":"Borshchevo",
    "wof:placetype":"locality"
},
  "geometry": {"coordinates":[37.36667,57.31667],"type":"Point"}
}