{
  "type": "Feature",
  "properties": {
    "gn:admin1_code":"8.0",
    "gn:asciiname":"Bekeshevo",
    "gn:country_code":"RU",
    "gn:dem":213,
    "gn:feature_class":"P",
    "gn:feature_code":"PPL",
    "gn:name":"Bekeshevo",
    "gn:population":0,
    "gn:timezone":"Asia/Yekaterinburg",
    "iso:country":"RU",
    "name:eng_x_preferred":[
        "Bekeshevo"
    ],
    "name:nor_x_preferred":[
        "Bekesjevo"
    ],
    "name:rus_x_preferred":[
        "\u0411\u0435\u043a\u0435\u0448\u0435\u0432\u043e"
    ],
    "name:und_x_variant":[
        "\u0411\u0435\u043a\u0435\u0448\u0435\u0432\u043e",
        "Bekeshevo"
    ],
    "wof:name":"Bekeshevo",
    "wof:placetype":"locality"
},
  "geometry": {"coordinates":[56.53694,52.58478],"type":"Point"}
}