{
  "type": "Feature",
  "properties": {
    "gn:admin1_code":"38",
    "gn:asciiname":"Solodkovskiy",
    "gn:country_code":"RU",
    "gn:dem":1,
    "gn:feature_class":"P",
    "gn:feature_code":"PPL",
    "gn:name":"Solodkovskiy",
    "gn:population":0,
    "gn:timezone":"Europe/Moscow",
    "iso:country":"RU",
    "name:rus_x_preferred":[
        "\u0421\u043e\u043b\u043e\u0434\u043a\u043e\u0432\u0441\u043a\u0438\u0439"
    ],
    "wof:name":"Solodkovskiy",
    "wof:placetype":"locality"
},
  "geometry": {"coordinates":[38.03371,45.56989],"type":"Point"}
}