{
  "type": "Feature",
  "properties": {
    "gn:admin1_code":"61",
    "gn:asciiname":"Pimenovo",
    "gn:country_code":"RU",
    "gn:dem":50,
    "gn:feature_class":"P",
    "gn:feature_code":"PPL",
    "gn:name":"Pimenovo",
    "gn:population":0,
    "gn:timezone":"Europe/Moscow",
    "iso:country":"RU",
    "name:rus_x_preferred":[
        "\u041f\u0438\u043c\u0435\u043d\u043e\u0432\u043e"
    ],
    "name:und_x_variant":[
        "Pimenov",
        "Pimenova",
        "Pimenovo"
    ],
    "wof:name":"Pimenovo",
    "wof:placetype":"locality"
},
  "geometry": {"coordinates":[38.75683,47.41299],"type":"Point"}
}