{
  "type": "Feature",
  "properties": {
    "gn:admin1_code":"90",
    "gn:asciiname":"Shumkovo",
    "gn:country_code":"RU",
    "gn:dem":130,
    "gn:feature_class":"P",
    "gn:feature_code":"PPL",
    "gn:name":"Shumkovo",
    "gn:population":0,
    "gn:timezone":"Asia/Yekaterinburg",
    "iso:country":"RU",
    "name:rus_x_preferred":[
        "\u0428\u0443\u043c\u043a\u043e\u0432\u043e"
    ],
    "name:und_x_variant":[
        "Shumkova",
        "Shumkovo",
        "\u0428\u0443\u043c\u043a\u043e\u0432\u043e"
    ],
    "wof:name":"Shumkovo",
    "wof:placetype":"locality"
},
  "geometry": {"coordinates":[57.1502,59.167],"type":"Point"}
}