{
  "type": "Feature",
  "properties": {
    "gn:admin1_code":"77",
    "gn:asciiname":"Nikulino",
    "gn:country_code":"RU",
    "gn:dem":143,
    "gn:feature_class":"P",
    "gn:feature_code":"PPL",
    "gn:name":"Nikulino",
    "gn:population":0,
    "gn:timezone":"Europe/Moscow",
    "iso:country":"RU",
    "name:eng_x_preferred":[
        "Nikulino"
    ],
    "name:nor_x_preferred":[
        "Nikulino"
    ],
    "name:rus_x_preferred":[
        "\u041d\u0438\u043a\u0443\u043b\u0438\u043d\u043e"
    ],
    "wof:name":"Nikulino",
    "wof:placetype":"locality"
},
  "geometry": {"coordinates":[35.83163,56.80747],"type":"Point"}
}