{
  "type": "Feature",
  "properties": {
    "gn:admin1_code":"29",
    "gn:asciiname":"Kalzagay",
    "gn:country_code":"RU",
    "gn:dem":406,
    "gn:feature_class":"P",
    "gn:feature_code":"PPL",
    "gn:name":"Kalzagay",
    "gn:population":0,
    "gn:timezone":"Asia/Novokuznetsk",
    "iso:country":"RU",
    "name:rus_x_preferred":[
        "\u041a\u0430\u043b\u0437\u0430\u0433\u0430\u0439"
    ],
    "wof:name":"Kalzagay",
    "wof:placetype":"locality"
},
  "geometry": {"coordinates":[86.5343,54.0085],"type":"Point"}
}