{
  "type": "Feature",
  "properties": {
    "gn:admin1_code":"51.0",
    "gn:asciiname":"Arefino",
    "gn:country_code":"RU",
    "gn:dem":93,
    "gn:feature_class":"P",
    "gn:feature_code":"PPL",
    "gn:name":"Arefino",
    "gn:population":0,
    "gn:timezone":"Europe/Moscow",
    "iso:country":"RU",
    "name:und_x_variant":[
        "\u0410\u0440\u0435\u0444\u0438\u043d\u043e",
        "Arefino"
    ],
    "wof:name":"Arefino",
    "wof:placetype":"locality"
},
  "geometry": {"coordinates":[43.8229,56.4852],"type":"Point"}
}