{
  "type": "Feature",
  "properties": {
    "gn:admin1_code":"10",
    "gn:asciiname":"Gatka",
    "gn:country_code":"RU",
    "gn:dem":137,
    "gn:feature_class":"P",
    "gn:feature_code":"PPL",
    "gn:name":"Gatka",
    "gn:population":2,
    "gn:timezone":"Europe/Moscow",
    "iso:country":"RU",
    "name:ces_x_preferred":[
        "Gatka"
    ],
    "name:dan_x_preferred":[
        "Gatka"
    ],
    "name:eng_x_preferred":[
        "Gatka"
    ],
    "name:fra_x_preferred":[
        "Gatka"
    ],
    "name:hin_x_preferred":[
        "\u0917\u091f\u0915\u093e"
    ],
    "name:ita_x_preferred":[
        "Gatka"
    ],
    "name:jpn_x_preferred":[
        "\u30ac\u30c3\u30ab"
    ],
    "name:mal_x_preferred":[
        "\u0d17\u0d24\u0d4d\u0d15"
    ],
    "name:pan_x_preferred":[
        "\u0a17\u0a71\u0a24\u0a15\u0a3e"
    ],
    "name:por_x_preferred":[
        "Gatka"
    ],
    "name:rus_x_preferred":[
        "\u0413\u0430\u0442\u043a\u0430"
    ],
    "name:spa_x_preferred":[
        "Gatka"
    ],
    "name:ukr_x_preferred":[
        "\u0413\u0430\u0442\u043a\u0430"
    ],
    "name:urd_x_preferred":[
        "\u06af\u062a\u06a9\u0627"
    ],
    "wof:name":"Gatka",
    "wof:placetype":"locality",
    "wof:population":2
},
  "geometry": {"coordinates":[31.7781,52.5935],"type":"Point"}
}