{
  "type": "Feature",
  "properties": {
    "gn:admin1_code":"10",
    "gn:asciiname":"Gatka",
    "gn:country_code":"RU",
    "gn:dem":137,
    "gn:feature_class":"P",
    "gn:feature_code":"PPL",
    "gn:name":"Gatka",
    "gn:population":2,
    "gn:timezone":"Europe/Moscow",
    "iso:country":"RU",
    "name:eng_x_preferred":[
        "Gatka"
    ],
    "name:rus_x_preferred":[
        "\u0413\u0430\u0442\u043a\u0430"
    ],
    "wof:name":"Gatka",
    "wof:placetype":"locality",
    "wof:population":2
},
  "geometry": {"coordinates":[31.7781,52.5935],"type":"Point"}
}