{
  "type": "Feature",
  "properties": {
    "iso:country":"RU",
    "name:bel_x_preferred":[
        "\u0423\u0441\u0445\u043e\u0434\u043d\u044f\u044f \u0430\u0434\u043c\u0456\u043d\u0456\u0441\u0442\u0440\u0430\u0446\u044b\u0439\u043d\u0430\u044f \u0430\u043a\u0440\u0443\u0433\u0430"
    ],
    "name:bul_x_preferred":[
        "\u0418\u0437\u0442\u043e\u0447\u0435\u043d \u0430\u0434\u043c\u0438\u043d\u0438\u0441\u0442\u0440\u0430\u0442\u0438\u0432\u0435\u043d \u043e\u043a\u0440\u044a\u0433"
    ],
    "name:ceb_x_preferred":[
        "Eastern Administrative Okrug"
    ],
    "name:deu_x_preferred":[
        "\u00d6stlicher Verwaltungsbezirk"
    ],
    "name:eng_x_variant":[
        "Vostochny administrativny okrug"
    ],
    "name:epo_x_preferred":[
        "Orienta administra arondismento"
    ],
    "name:eus_x_preferred":[
        "Ekialdeko barrutia"
    ],
    "name:fra_x_preferred":[
        "District administratif est"
    ],
    "name:heb_x_preferred":[
        "\u05d4\u05de\u05d7\u05d5\u05d6 \u05d4\u05d0\u05d3\u05de\u05d9\u05e0\u05d9\u05e1\u05d8\u05e8\u05d8\u05d9\u05d1\u05d9 \u05d4\u05de\u05d6\u05e8\u05d7\u05d9"
    ],
    "name:kor_x_preferred":[
        "\ubcf4\uc2a4\ud1a0\uce58\ub2c8 \uad6c"
    ],
    "name:lat_x_preferred":[
        "Circulus administrativus orientalis"
    ],
    "name:pol_x_preferred":[
        "Wschodni okr\u0119g administracyjny Moskwy"
    ],
    "name:rus_x_preferred":[
        "\u0412\u043e\u0441\u0442\u043e\u0447\u043d\u044b\u0439 \u0430\u0434\u043c\u0438\u043d\u0438\u0441\u0442\u0440\u0430\u0442\u0438\u0432\u043d\u044b\u0439 \u043e\u043a\u0440\u0443\u0433"
    ],
    "name:sco_x_preferred":[
        "Eastren Admeenistrative Okrug"
    ],
    "name:spa_x_preferred":[
        "Distrito Administrativo Oriental"
    ],
    "name:tat_x_preferred":[
        "\u041a\u04e9\u043d\u0447\u044b\u0433\u044b\u0448 \u0430\u0434\u043c\u0438\u043d\u0438\u0441\u0442\u0440\u0430\u0442\u0438\u0432 \u043e\u043a\u0440\u0443\u0433"
    ],
    "name:tur_x_preferred":[
        "Do\u011fu \u0130dari Okrugu"
    ],
    "name:ukr_x_preferred":[
        "\u0421\u0445\u0456\u0434\u043d\u0438\u0439 \u0430\u0434\u043c\u0456\u043d\u0456\u0441\u0442\u0440\u0430\u0442\u0438\u0432\u043d\u0438\u0439 \u043e\u043a\u0440\u0443\u0433"
    ],
    "name:zho_x_preferred":[
        "\u4e1c\u884c\u653f\u533a"
    ],
    "wof:name":"Eastern Administrative Okrug",
    "wof:placetype":"neighbourhood"
},
  "geometry": {"coordinates":[37.75470932011737,55.79023873270566],"type":"Point"}
}