{
  "type": "Feature",
  "properties": {
    "iso:country":"RU",
    "name:eng_x_variant":[
        "Vostochny administrativny okrug"
    ],
    "name:rus_x_preferred":[
        "\u0412\u043e\u0441\u0442\u043e\u0447\u043d\u044b\u0439 \u0430\u0434\u043c\u0438\u043d\u0438\u0441\u0442\u0440\u0430\u0442\u0438\u0432\u043d\u044b\u0439 \u043e\u043a\u0440\u0443\u0433"
    ],
    "wof:name":"Eastern Administrative Okrug",
    "wof:placetype":"neighbourhood"
},
  "geometry": {"coordinates":[37.75470932011737,55.79023873270566],"type":"Point"}
}