{
  "type": "Feature",
  "properties": {
    "gn:admin1_code":"77",
    "gn:asciiname":"Shateyevo",
    "gn:country_code":"RU",
    "gn:dem":171,
    "gn:feature_class":"P",
    "gn:feature_code":"PPL",
    "gn:name":"Shateyevo",
    "gn:population":0,
    "gn:timezone":"Europe/Moscow",
    "iso:country":"RU",
    "name:rus_x_preferred":[
        "\u0428\u0430\u0442\u0435\u0435\u0432\u043e"
    ],
    "name:und_x_variant":[
        "Shateyeva",
        "Shateyevo",
        "\u0428\u0430\u0442\u0435\u0435\u0432\u043e"
    ],
    "wof:name":"Shateyevo",
    "wof:placetype":"locality"
},
  "geometry": {"coordinates":[35.22574,58.17016],"type":"Point"}
}