{
  "type": "Feature",
  "properties": {
    "gn:country":"RU",
    "gn:fcode":"PPL",
    "gn:population":0,
    "iso:country":"RU",
    "name:eng_x_preferred":[
        "Krotovo"
    ],
    "name:fin_x_preferred":[
        "Toivola"
    ],
    "name:nor_x_preferred":[
        "Krotovo"
    ],
    "name:rus_x_preferred":[
        "\u041a\u0440\u043e\u0442\u043e\u0432\u043e"
    ],
    "name:und_x_variant":[
        "Toyvola"
    ],
    "qs:name":"Krotovo",
    "qs:name_adm0":"Russia",
    "qs:name_adm1":"Leningrad Oblast",
    "qs:photos_9r":0,
    "qs:photos_sr":0,
    "qs:placetype":"Town",
    "qs:pop_sr":"0",
    "wof:name":"Krotovo",
    "wof:placetype":"locality",
    "wof:population":0
},
  "geometry": {"coordinates":[29.9961,60.89979],"type":"Point"}
}