{
  "type": "Feature",
  "properties": {
    "gn:admin1_code":"91",
    "gn:asciiname":"Tolstyy Mys",
    "gn:country_code":"RU",
    "gn:dem":330,
    "gn:feature_class":"P",
    "gn:feature_code":"PPL",
    "gn:name":"Tolstyy Mys",
    "gn:population":0,
    "gn:timezone":"Asia/Krasnoyarsk",
    "iso:country":"RU",
    "name:eng_x_preferred":[
        "Tolstyy Mys"
    ],
    "name:nor_x_preferred":[
        "Tolstyj-Mys"
    ],
    "name:rus_x_preferred":[
        "\u0422\u043e\u043b\u0441\u0442\u044b\u0439-\u041c\u044b\u0441"
    ],
    "name:und_x_variant":[
        "Tolsty Mys"
    ],
    "wof:name":"Tolstyy Mys",
    "wof:placetype":"locality"
},
  "geometry": {"coordinates":[90.76291999999999,54.96992],"type":"Point"}
}