{
  "type": "Feature",
  "properties": {
    "gn:admin1_code":"33.0",
    "gn:asciiname":"Gorbunovshchina",
    "gn:country_code":"RU",
    "gn:dem":117,
    "gn:feature_class":"P",
    "gn:feature_code":"PPL",
    "gn:name":"Gorbunovshchina",
    "gn:population":0,
    "gn:timezone":"Europe/Kirov",
    "iso:country":"RU",
    "name:rus_x_preferred":[
        "\u0413\u043e\u0440\u0431\u0443\u043d\u043e\u0432\u0449\u0438\u043d\u0430"
    ],
    "wof:name":"Gorbunovshchina",
    "wof:placetype":"locality"
},
  "geometry": {"coordinates":[48.46238,57.89221],"type":"Point"}
}