{
  "type": "Feature",
  "properties": {
    "gn:admin1_code":"37",
    "gn:asciiname":"Fednevo",
    "gn:country_code":"RU",
    "gn:dem":160,
    "gn:feature_class":"P",
    "gn:feature_code":"PPL",
    "gn:name":"Fednevo",
    "gn:population":0,
    "gn:timezone":"Europe/Moscow",
    "iso:country":"RU",
    "name:rus_x_preferred":[
        "\u0424\u0435\u0434\u043d\u0435\u0432\u043e"
    ],
    "name:und_x_variant":[
        "\u0424\u0435\u0434\u043d\u0435\u0432\u043e"
    ],
    "wof:name":"Fednevo",
    "wof:placetype":"locality"
},
  "geometry": {"coordinates":[42.2572,58.6517],"type":"Point"}
}