{
  "type": "Feature",
  "properties": {
    "gn:admin1_code":"86",
    "gn:asciiname":"Verilovka",
    "gn:country_code":"RU",
    "gn:dem":102,
    "gn:feature_class":"P",
    "gn:feature_code":"PPL",
    "gn:name":"Verilovka",
    "gn:population":0,
    "gn:timezone":"Europe/Moscow",
    "iso:country":"RU",
    "name:und_x_variant":[
        "Shatilovo",
        "Verilovka"
    ],
    "wof:name":"Verilovka",
    "wof:placetype":"locality"
},
  "geometry": {"coordinates":[39.11092,51.95917],"type":"Point"}
}