{
  "type": "Feature",
  "properties": {
    "gn:admin1_code":"57.0",
    "gn:asciiname":"Arishka",
    "gn:country_code":"RU",
    "gn:dem":134,
    "gn:feature_class":"P",
    "gn:feature_code":"PPL",
    "gn:name":"Arishka",
    "gn:population":0,
    "gn:timezone":"Europe/Moscow",
    "iso:country":"RU",
    "name:eng_x_preferred":[
        "Arishka"
    ],
    "name:nor_x_preferred":[
        "Arisjka"
    ],
    "name:rus_x_preferred":[
        "\u0410\u0440\u0438\u0448\u043a\u0430"
    ],
    "wof:name":"Arishka",
    "wof:placetype":"locality"
},
  "geometry": {"coordinates":[45.5551,53.63373000000001],"type":"Point"}
}