{
  "type": "Feature",
  "properties": {
    "gn:admin1_code":"8",
    "gn:asciiname":"Vyazovka",
    "gn:country_code":"RU",
    "gn:dem":390,
    "gn:feature_class":"P",
    "gn:feature_code":"PPL",
    "gn:name":"Vyazovka",
    "gn:population":0,
    "gn:timezone":"Asia/Yekaterinburg",
    "iso:country":"RU",
    "name:rus_x_preferred":[
        "\u0412\u044f\u0437\u043e\u0432\u043a\u0430"
    ],
    "name:und_x_variant":[
        "Verkhnyaya Vyazovka",
        "Vyazovka"
    ],
    "wof:name":"Vyazovka",
    "wof:placetype":"locality"
},
  "geometry": {"coordinates":[58.93056,55.41139],"type":"Point"}
}