{
  "type": "Feature",
  "properties": {
    "gn:admin1_code":"41",
    "gn:asciiname":"Marfinka",
    "gn:country_code":"RU",
    "gn:dem":205,
    "gn:feature_class":"P",
    "gn:feature_code":"PPL",
    "gn:name":"Marfinka",
    "gn:population":0,
    "gn:timezone":"Europe/Moscow",
    "iso:country":"RU",
    "name:rus_x_preferred":[
        "\u041c\u0430\u0440\u0444\u0438\u043d\u043a\u0430"
    ],
    "wof:name":"Marfinka",
    "wof:placetype":"locality"
},
  "geometry": {"coordinates":[36.59028,52.19472],"type":"Point"}
}