{
  "type": "Feature",
  "properties": {
    "gn:admin1_code":"88",
    "gn:asciiname":"Lekino",
    "gn:country_code":"RU",
    "gn:dem":161,
    "gn:feature_class":"P",
    "gn:feature_code":"PPL",
    "gn:name":"Lekino",
    "gn:population":0,
    "gn:timezone":"Europe/Moscow",
    "iso:country":"RU",
    "name:ita_x_preferred":[
        "Lekino"
    ],
    "name:kat_x_preferred":[
        "\u10da\u10d4\u10e5\u10d8\u10dc\u10dd"
    ],
    "name:msa_x_preferred":[
        "Lekino"
    ],
    "name:rus_x_preferred":[
        "\u041b\u0435\u043a\u0438\u043d\u043e"
    ],
    "name:und_x_variant":[
        "\u041b\u0435\u043a\u0438\u043d\u043e"
    ],
    "wof:name":"Lekino",
    "wof:placetype":"locality"
},
  "geometry": {"coordinates":[38.7622,57.2908],"type":"Point"}
}