{
  "type": "Feature",
  "properties": {
    "gn:admin1_code":"90",
    "gn:asciiname":"Mysly",
    "gn:country_code":"RU",
    "gn:dem":114,
    "gn:feature_class":"P",
    "gn:feature_code":"PPL",
    "gn:name":"Mysly",
    "gn:population":0,
    "gn:timezone":"Asia/Yekaterinburg",
    "iso:country":"RU",
    "name:rus_x_preferred":[
        "\u041c\u044b\u0441\u043b\u044b"
    ],
    "name:und_x_variant":[
        "Mysty",
        "Mysly",
        "\u041c\u044b\u0441\u043b\u044b"
    ],
    "wof:name":"Mysly",
    "wof:placetype":"locality"
},
  "geometry": {"coordinates":[56.3659,59.4974],"type":"Point"}
}