{
  "type": "Feature",
  "properties": {
    "gn:admin1_code":"60",
    "gn:asciiname":"Ferkovo",
    "gn:country_code":"RU",
    "gn:dem":105,
    "gn:feature_class":"P",
    "gn:feature_code":"PPL",
    "gn:name":"Ferkovo",
    "gn:population":0,
    "gn:timezone":"Europe/Moscow",
    "iso:country":"RU",
    "name:rus_x_preferred":[
        "\u0424\u0435\u0440\u043a\u043e\u0432\u043e"
    ],
    "wof:name":"Ferkovo",
    "wof:placetype":"locality"
},
  "geometry": {"coordinates":[28.95656,57.27918],"type":"Point"}
}