{
  "type": "Feature",
  "properties": {
    "gn:admin1_code":"30",
    "gn:asciiname":"Tugur",
    "gn:country_code":"RU",
    "gn:dem":32,
    "gn:feature_class":"P",
    "gn:feature_code":"PPL",
    "gn:name":"Tugur",
    "gn:population":0,
    "gn:timezone":"Asia/Vladivostok",
    "iso:country":"RU",
    "name:eng_x_preferred":[
        "Tugur"
    ],
    "name:nor_x_preferred":[
        "Tugur"
    ],
    "name:rus_x_preferred":[
        "\u0422\u0443\u0433\u0443\u0440"
    ],
    "wof:name":"Tugur",
    "wof:placetype":"locality"
},
  "geometry": {"coordinates":[136.82793000000001,53.77284],"type":"Point"}
}