{
  "type": "Feature",
  "properties": {
    "gn:admin1_code":"17",
    "gn:asciiname":"Tsudakhar",
    "gn:country_code":"RU",
    "gn:dem":1047,
    "gn:feature_class":"P",
    "gn:feature_code":"PPL",
    "gn:name":"Tsudakhar",
    "gn:population":0,
    "gn:timezone":"Europe/Moscow",
    "iso:country":"RU",
    "name:eng_x_preferred":[
        "Tsudakhar"
    ],
    "name:nor_x_preferred":[
        "Tsudakhar"
    ],
    "name:rus_x_preferred":[
        "\u0426\u0443\u0434\u0430\u0445\u0430\u0440"
    ],
    "wof:name":"Tsudakhar",
    "wof:placetype":"locality"
},
  "geometry": {"coordinates":[47.16056,42.3425],"type":"Point"}
}