{
  "type": "Feature",
  "properties": {
    "gn:admin1_code":"77",
    "gn:asciiname":"Kazitsyno",
    "gn:country_code":"RU",
    "gn:dem":161,
    "gn:feature_class":"P",
    "gn:feature_code":"PPL",
    "gn:name":"Kazitsyno",
    "gn:population":0,
    "gn:timezone":"Europe/Moscow",
    "iso:country":"RU",
    "name:rus_x_preferred":[
        "\u041a\u0430\u0437\u0438\u0446\u044b\u043d\u043e"
    ],
    "name:und_x_variant":[
        "\u041a\u0430\u0437\u0438\u0446\u044b\u043d\u043e"
    ],
    "wof:name":"Kazitsyno",
    "wof:placetype":"locality"
},
  "geometry": {"coordinates":[34.65033,57.19009000000001],"type":"Point"}
}