{
  "type": "Feature",
  "properties": {
    "gn:admin1_code":"81",
    "gn:asciiname":"Latyshskiy",
    "gn:country_code":"RU",
    "gn:dem":251,
    "gn:feature_class":"P",
    "gn:feature_code":"PPL",
    "gn:name":"Latyshskiy",
    "gn:population":0,
    "gn:timezone":"Europe/Ulyanovsk",
    "iso:country":"RU",
    "name:rus_x_preferred":[
        "\u041b\u0430\u0442\u044b\u0448\u0441\u043a\u0438\u0439"
    ],
    "name:und_x_variant":[
        "\u041b\u0430\u0442\u044b\u0448\u0441\u043a\u0438\u0439"
    ],
    "wof:name":"Latyshskiy",
    "wof:placetype":"locality"
},
  "geometry": {"coordinates":[47.7901,53.5568],"type":"Point"}
}