{
  "type": "Feature",
  "properties": {
    "gn:admin1_code":"67",
    "gn:asciiname":"Mezhdurech'ye",
    "gn:country_code":"RU",
    "gn:dem":65,
    "gn:feature_class":"P",
    "gn:feature_code":"PPL",
    "gn:name":"Mezhdurech\u2019ye",
    "gn:population":0,
    "gn:timezone":"Europe/Saratov",
    "iso:country":"RU",
    "name:eng_x_preferred":[
        "Pos\u00eblok"
    ],
    "name:nor_x_preferred":[
        "Poselok"
    ],
    "name:rus_x_preferred":[
        "\u041f\u043e\u0441\u0435\u043b\u043e\u043a"
    ],
    "name:rus_x_variant":[
        "\u041c\u0435\u0436\u0434\u0443\u0440\u0435\u0447\u044c\u0435",
        "\u041f\u043e\u0441\u0451\u043b\u043e\u043a"
    ],
    "name:und_x_variant":[
        "Pos\u00eblok",
        "Mezhdurech\u2019ye"
    ],
    "wof:name":"Mezhdurech'ye",
    "wof:placetype":"locality"
},
  "geometry": {"coordinates":[47.51014,52.50788000000001],"type":"Point"}
}