{
  "type": "Feature",
  "properties": {
    "gn:country":"RU",
    "gn:fcode":"PPL",
    "gn:population":0,
    "iso:country":"RU",
    "name:aze_x_preferred":[
        "M\u0131\u015fatkan"
    ],
    "name:bak_x_preferred":[
        "\u0412\u0430\u043b\u0435\u043d\u0442\u0438\u043d\u043e\u0432\u043a\u0430"
    ],
    "name:che_x_preferred":[
        "\u0412\u0430\u043b\u0435\u043d\u0442\u0438\u043d\u043e\u0432\u043a\u0430"
    ],
    "name:eng_x_preferred":[
        "Valentinovka"
    ],
    "name:hye_x_preferred":[
        "\u054e\u0561\u056c\u0565\u0576\u057f\u056b\u0576\u0578\u057e\u056f\u0561"
    ],
    "name:kat_x_preferred":[
        "\u10d5\u10d0\u10da\u10d4\u10dc\u10e2\u10d8\u10dc\u10dd\u10d5\u10d9\u10d0"
    ],
    "name:kaz_x_preferred":[
        "\u0412\u0430\u043b\u0435\u043d\u0442\u0438\u043d\u043e\u0432\u043a\u0430"
    ],
    "name:kir_x_preferred":[
        "\u0412\u0430\u043b\u0435\u043d\u0442\u0438\u043d\u043e\u0432\u043a\u0430"
    ],
    "name:nor_x_preferred":[
        "Valentinovka"
    ],
    "name:rus_x_preferred":[
        "\u0412\u0430\u043b\u0435\u043d\u0442\u0438\u043d\u043e\u0432\u043a\u0430"
    ],
    "name:tat_x_preferred":[
        "\u0412\u0430\u043b\u0435\u043d\u0442\u0438\u043d\u043e\u0432\u043a\u0430"
    ],
    "name:ukr_x_preferred":[
        "\u0412\u0430\u043b\u0435\u043d\u0442\u0438\u043d\u043e\u0432\u043a\u0430"
    ],
    "qs:name":"Valentinovka",
    "qs:name_adm0":"Russia",
    "qs:name_adm1":"Bashkortostan Republic",
    "qs:photos_9r":0,
    "qs:photos_sr":0,
    "qs:placetype":"Town",
    "qs:pop_sr":"0",
    "wof:name":"Valentinovka",
    "wof:placetype":"locality",
    "wof:population":0
},
  "geometry": {"coordinates":[56.8823,54.5425],"type":"Point"}
}