{
  "type": "Feature",
  "properties": {
    "gn:admin1_code":"21.0",
    "gn:asciiname":"Pezukha",
    "gn:country_code":"RU",
    "gn:dem":102,
    "gn:feature_class":"P",
    "gn:feature_code":"PPL",
    "gn:name":"Pezukha",
    "gn:population":0,
    "gn:timezone":"Europe/Moscow",
    "iso:country":"RU",
    "name:rus_x_preferred":[
        "\u041f\u0435\u0437\u0443\u0445\u0430"
    ],
    "name:und_x_variant":[
        "\u041f\u0435\u0437\u0443\u0445\u0430"
    ],
    "wof:name":"Pezukha",
    "wof:placetype":"locality"
},
  "geometry": {"coordinates":[41.91278,57.29417],"type":"Point"}
}