{
  "type": "Feature",
  "properties": {
    "gn:admin1_code":"37",
    "gn:asciiname":"Vysokovo",
    "gn:country_code":"RU",
    "gn:dem":159,
    "gn:feature_class":"P",
    "gn:feature_code":"PPL",
    "gn:name":"Vysokovo",
    "gn:population":0,
    "gn:timezone":"Europe/Moscow",
    "iso:country":"RU",
    "name:und_x_variant":[
        "Vysokoye",
        "Vysokovo"
    ],
    "wof:name":"Vysokovo",
    "wof:placetype":"locality"
},
  "geometry": {"coordinates":[41.58496,58.29054],"type":"Point"}
}