{
  "type": "Feature",
  "properties": {
    "gn:admin1_code":"55.0",
    "gn:asciiname":"Berkutkin",
    "gn:country_code":"RU",
    "gn:dem":297,
    "gn:feature_class":"P",
    "gn:feature_code":"PPL",
    "gn:name":"Berkutkin",
    "gn:population":0,
    "gn:timezone":"Asia/Yekaterinburg",
    "iso:country":"RU",
    "name:nor_x_preferred":[
        "Berkutkin"
    ],
    "name:rus_x_preferred":[
        "\u0411\u0435\u0440\u043a\u0443\u0442\u043a\u0438\u043d"
    ],
    "name:und_x_variant":[
        "Berkut"
    ],
    "wof:name":"Berkutkin",
    "wof:placetype":"locality"
},
  "geometry": {"coordinates":[59.61666999999999,51.86667],"type":"Point"}
}