{
  "type": "Feature",
  "properties": {
    "gn:admin1_code":"9",
    "gn:asciiname":"Tavricheskiy",
    "gn:cc2":"RU",
    "gn:country_code":"RU",
    "gn:dem":206,
    "gn:feature_class":"P",
    "gn:feature_code":"PPL",
    "gn:name":"Tavricheskiy",
    "gn:population":0,
    "gn:timezone":"Europe/Moscow",
    "iso:country":"RU",
    "name:und_x_variant":[
        "Tavrichanskiy",
        "Tavricheskiy"
    ],
    "wof:name":"Tavricheskiy",
    "wof:placetype":"locality"
},
  "geometry": {"coordinates":[37.97444,50.50972],"type":"Point"}
}