{
  "type": "Feature",
  "properties": {
    "gn:admin1_code":"21.0",
    "gn:asciiname":"Pyr'yevo",
    "gn:country_code":"RU",
    "gn:dem":121,
    "gn:feature_class":"P",
    "gn:feature_code":"PPL",
    "gn:name":"Pyr\u2019yevo",
    "gn:population":0,
    "gn:timezone":"Europe/Moscow",
    "iso:country":"RU",
    "name:rus_x_preferred":[
        "\u041f\u044b\u0440\u044c\u0435\u0432\u043e"
    ],
    "name:und_x_variant":[
        "Pyr\u2019yevo",
        "\u041f\u044b\u0440\u044c\u0435\u0432\u043e"
    ],
    "wof:name":"Pyr'yevo",
    "wof:placetype":"locality"
},
  "geometry": {"coordinates":[42.4134,57.29414000000001],"type":"Point"}
}