{
  "type": "Feature",
  "properties": {
    "gn:admin1_code":"80",
    "gn:asciiname":"Lezya",
    "gn:country_code":"RU",
    "gn:dem":166,
    "gn:feature_class":"P",
    "gn:feature_code":"PPL",
    "gn:name":"Lezya",
    "gn:population":0,
    "gn:timezone":"Europe/Samara",
    "iso:country":"RU",
    "name:rus_x_preferred":[
        "\u041b\u0435\u0437\u044f"
    ],
    "name:und_x_variant":[
        "Lezino",
        "Lezya"
    ],
    "wof:name":"Lezya",
    "wof:placetype":"locality"
},
  "geometry": {"coordinates":[52.2748,58.1469],"type":"Point"}
}