{
  "type": "Feature",
  "properties": {
    "gn:admin1_code":"47",
    "gn:asciiname":"Kochkarevo",
    "gn:country_code":"RU",
    "gn:dem":181,
    "gn:feature_class":"P",
    "gn:feature_code":"PPL",
    "gn:name":"Kochkar\u00ebvo",
    "gn:population":0,
    "gn:timezone":"Europe/Moscow",
    "iso:country":"RU",
    "name:rus_x_preferred":[
        "\u041a\u043e\u0447\u043a\u0430\u0440\u0451\u0432\u043e"
    ],
    "name:und_x_variant":[
        "Kochkar\u00ebvo"
    ],
    "wof:name":"Kochkarevo",
    "wof:placetype":"locality"
},
  "geometry": {"coordinates":[38.20846,55.0472],"type":"Point"}
}