{
  "type": "Feature",
  "properties": {
    "gn:admin1_code":"7",
    "gn:asciiname":"Orlov",
    "gn:country_code":"RU",
    "gn:dem":16,
    "gn:feature_class":"P",
    "gn:feature_code":"PPL",
    "gn:name":"Orlov",
    "gn:population":0,
    "gn:timezone":"Europe/Astrakhan",
    "iso:country":"RU",
    "name:rus_x_preferred":[
        "\u041e\u0440\u043b\u043e\u0432"
    ],
    "name:und_x_variant":[
        "\u041e\u0440\u043b\u043e\u0432"
    ],
    "wof:name":"Orlov",
    "wof:placetype":"locality"
},
  "geometry": {"coordinates":[46.11361,48.49972],"type":"Point"}
}