{
  "type": "Feature",
  "properties": {
    "gn:admin1_code":"69",
    "gn:asciiname":"Yelizavetino",
    "gn:cc2":"RU",
    "gn:country_code":"RU",
    "gn:dem":194,
    "gn:feature_class":"P",
    "gn:feature_code":"PPL",
    "gn:name":"Yelizavetino",
    "gn:population":0,
    "gn:timezone":"Europe/Moscow",
    "iso:country":"RU",
    "name:und_x_variant":[
        "Shtapovka",
        "Shtalovka",
        "Yelizavetino"
    ],
    "wof:name":"Yelizavetino",
    "wof:placetype":"locality"
},
  "geometry": {"coordinates":[35.08444,55.13222],"type":"Point"}
}