{
  "type": "Feature",
  "properties": {
    "gn:admin1_code":"40",
    "gn:asciiname":"Krasnyy Mayak",
    "gn:country_code":"RU",
    "gn:dem":136,
    "gn:feature_class":"P",
    "gn:feature_code":"PPL",
    "gn:name":"Krasnyy Mayak",
    "gn:population":0,
    "gn:timezone":"Asia/Yekaterinburg",
    "iso:country":"RU",
    "name:rus_x_preferred":[
        "\u041a\u0440\u0430\u0441\u043d\u044b\u0439 \u041c\u0430\u044f\u043a"
    ],
    "name:und_x_variant":[
        "\u041a\u0440\u0430\u0441\u043d\u044b\u0439 \u041c\u0430\u044f\u043a"
    ],
    "wof:name":"Krasnyy Mayak",
    "wof:placetype":"locality"
},
  "geometry": {"coordinates":[67.44528000000001,55.27806],"type":"Point"}
}