{
  "type": "Feature",
  "properties": {
    "gn:admin1_code":"61.0",
    "gn:asciiname":"Annovka",
    "gn:country_code":"RU",
    "gn:dem":42,
    "gn:feature_class":"P",
    "gn:feature_code":"PPL",
    "gn:name":"Annovka",
    "gn:population":0,
    "gn:timezone":"Europe/Moscow",
    "iso:country":"RU",
    "name:che_x_preferred":[
        "\u0410\u043d\u043d\u043e\u0432\u043a\u0430"
    ],
    "name:nor_x_preferred":[
        "Annovka"
    ],
    "name:rus_x_preferred":[
        "\u0410\u043d\u043d\u043e\u0432\u043a\u0430"
    ],
    "name:tgk_x_preferred":[
        "\u0410\u043d\u043e\u0432\u043a\u0430"
    ],
    "wof:name":"Annovka",
    "wof:placetype":"locality"
},
  "geometry": {"coordinates":[41.04268,48.54252],"type":"Point"}
}