{
  "type": "Feature",
  "properties": {
    "gn:admin1_code":"85",
    "gn:asciiname":"Velikiy Dvor",
    "gn:country_code":"RU",
    "gn:dem":143,
    "gn:feature_class":"P",
    "gn:feature_code":"PPL",
    "gn:name":"Velikiy Dvor",
    "gn:population":0,
    "gn:timezone":"Europe/Moscow",
    "iso:country":"RU",
    "name:eng_x_preferred":[
        "Velikiy Dvor"
    ],
    "name:nor_x_preferred":[
        "Velikij Dvor"
    ],
    "name:rus_x_preferred":[
        "\u0412\u0435\u043b\u0438\u043a\u0438\u0439 \u0414\u0432\u043e\u0440"
    ],
    "wof:name":"Velikiy Dvor",
    "wof:placetype":"locality"
},
  "geometry": {"coordinates":[40.05976,59.63788],"type":"Point"}
}