{
  "type": "Feature",
  "properties": {
    "gn:admin1_code":"91",
    "gn:asciiname":"Koloma",
    "gn:country_code":"RU",
    "gn:dem":791,
    "gn:feature_class":"P",
    "gn:feature_code":"PPL",
    "gn:name":"Koloma",
    "gn:population":0,
    "gn:timezone":"Asia/Krasnoyarsk",
    "iso:country":"RU",
    "name:rus_x_preferred":[
        "\u041a\u043e\u043b\u043e\u043c\u0430"
    ],
    "wof:name":"Koloma",
    "wof:placetype":"locality"
},
  "geometry": {"coordinates":[94.71666999999999,70.25],"type":"Point"}
}