{
  "type": "Feature",
  "properties": {
    "gn:admin1_code":"47",
    "gn:asciiname":"Fedorovka",
    "gn:country_code":"RU",
    "gn:dem":192,
    "gn:feature_class":"P",
    "gn:feature_code":"PPL",
    "gn:name":"\u0424\u0435\u0434\u043e\u0440\u043e\u0432\u043a\u0430",
    "gn:population":0,
    "gn:timezone":"Europe/Moscow",
    "iso:country":"RU",
    "name:rus_x_preferred":[
        "\u0424\u0435\u0434\u043e\u0440\u043e\u0432\u043a\u0430"
    ],
    "name:rus_x_variant":[
        "\u0424\u0451\u0434\u043e\u0440\u043e\u0432\u043a\u0430"
    ],
    "name:und_x_variant":[
        "\u0424\u0435\u0434\u043e\u0440\u043e\u0432\u043a\u0430",
        "F\u00ebdorovka",
        "\u0424\u0451\u0434\u043e\u0440\u043e\u0432\u043a\u0430"
    ],
    "wof:name":"Fedorovka",
    "wof:placetype":"locality"
},
  "geometry": {"coordinates":[37.2348,55.9007],"type":"Point"}
}