{
  "type": "Feature",
  "properties": {
    "gn:admin1_code":"61",
    "gn:asciiname":"Spornyy",
    "gn:cc2":"RU",
    "gn:country_code":"RU",
    "gn:dem":7,
    "gn:feature_class":"P",
    "gn:feature_code":"PPL",
    "gn:name":"Spornyy",
    "gn:population":0,
    "gn:timezone":"Europe/Moscow",
    "iso:country":"RU",
    "name:rus_x_preferred":[
        "\u0421\u043f\u043e\u0440\u043d\u044b\u0439"
    ],
    "name:und_x_variant":[
        "Sporny",
        "Spornyy"
    ],
    "wof:name":"Spornyy",
    "wof:placetype":"locality"
},
  "geometry": {"coordinates":[40.76389,47.12417],"type":"Point"}
}