{
  "type": "Feature",
  "properties": {
    "gn:admin1_code":"28.0",
    "gn:asciiname":"Metsaekylae",
    "gn:country_code":"RU",
    "gn:dem":11,
    "gn:feature_class":"P",
    "gn:feature_code":"PPL",
    "gn:name":"Mets\u00e4kyl\u00e4",
    "gn:population":0,
    "gn:timezone":"Europe/Moscow",
    "iso:country":"RU",
    "wof:name":"Metsaekylae",
    "wof:placetype":"locality"
},
  "geometry": {"coordinates":[31.15551,61.6832],"type":"Point"}
}