{
  "type": "Feature",
  "properties": {
    "gn:admin1_code":"85",
    "gn:asciiname":"Koltyrikha",
    "gn:country_code":"RU",
    "gn:dem":148,
    "gn:feature_class":"P",
    "gn:feature_code":"PPL",
    "gn:name":"Koltyrikha",
    "gn:population":0,
    "gn:timezone":"Europe/Moscow",
    "iso:country":"RU",
    "name:eng_x_preferred":[
        "Koltyrikha"
    ],
    "name:nor_x_preferred":[
        "Koltyrikha"
    ],
    "name:rus_x_preferred":[
        "\u041a\u043e\u043b\u0442\u044b\u0440\u0438\u0445\u0430"
    ],
    "name:und_x_variant":[
        "\u041a\u043e\u043b\u0442\u044b\u0440\u0438\u0445\u0430",
        "Koltyrikha"
    ],
    "wof:name":"Koltyrikha",
    "wof:placetype":"locality"
},
  "geometry": {"coordinates":[41.67473,60.12125],"type":"Point"}
}