{
  "type": "Feature",
  "properties": {
    "gn:admin1_code":"76",
    "gn:asciiname":"Plekhanovo",
    "gn:country_code":"RU",
    "gn:dem":228,
    "gn:feature_class":"P",
    "gn:feature_code":"PPL",
    "gn:name":"Plekhanovo",
    "gn:population":0,
    "gn:timezone":"Europe/Moscow",
    "iso:country":"RU",
    "name:nor_x_preferred":[
        "Plekhanovo"
    ],
    "name:rus_x_preferred":[
        "\u041f\u043b\u0435\u0445\u0430\u043d\u043e\u0432\u043e"
    ],
    "wof:name":"Plekhanovo",
    "wof:placetype":"locality"
},
  "geometry": {"coordinates":[37.71713,54.01506],"type":"Point"}
}