{
  "type": "Feature",
  "properties": {
    "gn:admin1_code":"33.0",
    "gn:asciiname":"Deyanovo Pervoye",
    "gn:country_code":"RU",
    "gn:dem":113,
    "gn:feature_class":"P",
    "gn:feature_code":"PPL",
    "gn:name":"Deyanovo Pervoye",
    "gn:population":0,
    "gn:timezone":"Europe/Kirov",
    "iso:country":"RU",
    "name:rus_x_preferred":[
        "\u0414\u0435\u044f\u043d\u043e\u0432\u043e \u041f\u0435\u0440\u0432\u043e\u0435"
    ],
    "name:und_x_variant":[
        "\u0414\u0435\u044f\u043d\u043e\u0432\u043e \u041f\u0435\u0440\u0432\u043e\u0435"
    ],
    "wof:name":"Deyanovo Pervoye",
    "wof:placetype":"locality"
},
  "geometry": {"coordinates":[48.58333,57.68333000000001],"type":"Point"}
}