{
  "type": "Feature",
  "properties": {
    "gn:admin1_code":"34",
    "gn:asciiname":"Letma",
    "gn:country_code":"RU",
    "gn:dem":181,
    "gn:feature_class":"P",
    "gn:feature_code":"PPL",
    "gn:name":"L\u00ebtma",
    "gn:population":0,
    "gn:timezone":"Europe/Moscow",
    "iso:country":"RU",
    "name:eng_x_preferred":[
        "L\u00ebtma"
    ],
    "name:nor_x_preferred":[
        "Letma"
    ],
    "name:rus_x_preferred":[
        "\u041b\u0435\u0442\u043c\u0430"
    ],
    "name:rus_x_variant":[
        "\u041b\u0451\u0442\u043c\u0430"
    ],
    "wof:name":"Letma",
    "wof:placetype":"locality"
},
  "geometry": {"coordinates":[50.81125,60.50332],"type":"Point"}
}