{
  "type": "Feature",
  "properties": {
    "gn:admin1_code":"21",
    "gn:asciiname":"Inarkhovo",
    "gn:country_code":"RU",
    "gn:dem":149,
    "gn:feature_class":"P",
    "gn:feature_code":"PPL",
    "gn:name":"Inarkhovo",
    "gn:population":0,
    "gn:timezone":"Europe/Moscow",
    "iso:country":"RU",
    "name:rus_x_preferred":[
        "\u0418\u043d\u0430\u0440\u0445\u043e\u0432\u043e"
    ],
    "wof:name":"Inarkhovo",
    "wof:placetype":"locality"
},
  "geometry": {"coordinates":[39.55766,56.89368],"type":"Point"}
}