{
  "type": "Feature",
  "properties": {
    "gn:admin1_code":"90.0",
    "gn:asciiname":"Bayandina",
    "gn:country_code":"RU",
    "gn:dem":130,
    "gn:feature_class":"P",
    "gn:feature_code":"PPL",
    "gn:name":"Bayandina",
    "gn:population":0,
    "gn:timezone":"Asia/Yekaterinburg",
    "iso:country":"RU",
    "name:rus_x_preferred":[
        "\u0411\u0430\u044f\u043d\u0434\u0438\u043d\u0430"
    ],
    "wof:name":"Bayandina",
    "wof:placetype":"locality"
},
  "geometry": {"coordinates":[56.2835,59.9656],"type":"Point"}
}