{
  "type": "Feature",
  "properties": {
    "gn:admin1_code":"85",
    "gn:asciiname":"Kremen'ye",
    "gn:country_code":"RU",
    "gn:dem":79,
    "gn:feature_class":"P",
    "gn:feature_code":"PPL",
    "gn:name":"Kremen\u2019ye",
    "gn:population":0,
    "gn:timezone":"Europe/Moscow",
    "iso:country":"RU",
    "name:rus_x_preferred":[
        "\u041a\u0440\u0435\u043c\u0435\u043d\u044c\u0435"
    ],
    "name:und_x_variant":[
        "Kremen\u2019ye"
    ],
    "wof:name":"Kremen'ye",
    "wof:placetype":"locality"
},
  "geometry": {"coordinates":[46.2064,60.6432],"type":"Point"}
}