{
  "type": "Feature",
  "properties": {
    "gn:admin1_code":"77",
    "gn:asciiname":"Lyuboditsy",
    "gn:country_code":"RU",
    "gn:dem":142,
    "gn:feature_class":"P",
    "gn:feature_code":"PPL",
    "gn:name":"Lyuboditsy",
    "gn:population":0,
    "gn:timezone":"Europe/Moscow",
    "iso:country":"RU",
    "name:rus_x_preferred":[
        "\u041b\u044e\u0431\u043e\u0434\u0438\u0446\u044b"
    ],
    "wof:name":"Lyuboditsy",
    "wof:placetype":"locality"
},
  "geometry": {"coordinates":[36.68778,57.69472],"type":"Point"}
}