{
  "type": "Feature",
  "properties": {
    "gn:admin1_code":"16",
    "gn:asciiname":"Nizhneye Atykovo",
    "gn:country_code":"RU",
    "gn:dem":121,
    "gn:feature_class":"P",
    "gn:feature_code":"PPL",
    "gn:name":"Nizhneye Atykovo",
    "gn:population":0,
    "gn:timezone":"Europe/Moscow",
    "iso:country":"RU",
    "name:rus_x_preferred":[
        "\u041d\u0438\u0436\u043d\u0435\u0435 \u0410\u0442\u044b\u043a\u043e\u0432\u043e"
    ],
    "wof:name":"Nizhneye Atykovo",
    "wof:placetype":"locality"
},
  "geometry": {"coordinates":[47.38399999999999,55.0679],"type":"Point"}
}