{
  "type": "Feature",
  "properties": {
    "gn:admin1_code":"10",
    "gn:asciiname":"Pugachovka",
    "gn:country_code":"RU",
    "gn:dem":175,
    "gn:feature_class":"P",
    "gn:feature_code":"PPL",
    "gn:name":"Pugachovka",
    "gn:population":0,
    "gn:timezone":"Europe/Moscow",
    "iso:country":"RU",
    "name:rus_x_preferred":[
        "\u041f\u0443\u0433\u0430\u0447\u043e\u0432\u043a\u0430"
    ],
    "wof:name":"Pugachovka",
    "wof:placetype":"locality"
},
  "geometry": {"coordinates":[32.84508,53.11212],"type":"Point"}
}