{
  "type": "Feature",
  "properties": {
    "gn:admin1_code":"54",
    "gn:asciiname":"Belyayevka",
    "gn:country_code":"RU",
    "gn:dem":113,
    "gn:feature_class":"P",
    "gn:feature_code":"PPL",
    "gn:name":"Belyayevka",
    "gn:population":0,
    "gn:timezone":"Asia/Omsk",
    "iso:country":"RU",
    "name:rus_x_preferred":[
        "\u0411\u0435\u043b\u044f\u0435\u0432\u043a\u0430"
    ],
    "name:und_x_variant":[
        "\u0411\u0435\u043b\u044f\u0435\u0432\u043a\u0430"
    ],
    "wof:name":"Belyayevka",
    "wof:placetype":"locality"
},
  "geometry": {"coordinates":[72.71259999999999,55.2366],"type":"Point"}
}