{
  "type": "Feature",
  "properties": {
    "gn:admin1_code":"30",
    "gn:asciiname":"Malyy Amurchik",
    "gn:cc2":"RU",
    "gn:country_code":"RU",
    "gn:dem":104,
    "gn:feature_class":"P",
    "gn:feature_code":"PPL",
    "gn:name":"Malyy Amurchik",
    "gn:population":0,
    "gn:timezone":"Asia/Vladivostok",
    "iso:country":"RU",
    "name:rus_x_preferred":[
        "\u041c\u0430\u043b\u044b\u0439 \u0410\u043c\u0443\u0440\u0447\u0438\u043a"
    ],
    "name:und_x_variant":[
        "Tarakanovka",
        "Malyy Amurchik",
        "\u041c\u0430\u043b\u044b\u0439 \u0410\u043c\u0443\u0440\u0447\u0438\u043a"
    ],
    "wof:name":"Malyy Amurchik",
    "wof:placetype":"locality"
},
  "geometry": {"coordinates":[140.80000000000001,53.03333000000001],"type":"Point"}
}