{
  "type": "Feature",
  "properties": {
    "gn:admin1_code":"46",
    "gn:asciiname":"Tumola",
    "gn:country_code":"RU",
    "gn:dem":167,
    "gn:feature_class":"P",
    "gn:feature_code":"PPL",
    "gn:name":"Tumola",
    "gn:population":0,
    "gn:timezone":"Europe/Moscow",
    "iso:country":"RU",
    "name:rus_x_preferred":[
        "\u0422\u0443\u043c\u043e\u043b\u0430"
    ],
    "name:und_x_variant":[
        "\u0422\u0443\u043c\u043e\u043b\u0430"
    ],
    "wof:name":"Tumola",
    "wof:placetype":"locality"
},
  "geometry": {"coordinates":[44.4606,53.8677],"type":"Point"}
}