{
  "type": "Feature",
  "properties": {
    "gn:admin1_code":"28",
    "gn:asciiname":"Kolmachevo",
    "gn:country_code":"RU",
    "gn:dem":74,
    "gn:feature_class":"P",
    "gn:feature_code":"PPL",
    "gn:name":"Kolmach\u00ebvo",
    "gn:population":0,
    "gn:timezone":"Europe/Moscow",
    "iso:country":"RU",
    "name:fin_x_preferred":[
        "Kolmatsu"
    ],
    "name:rus_x_preferred":[
        "\u041a\u043e\u043b\u043c\u0430\u0447\u0451\u0432\u043e"
    ],
    "name:und_x_variant":[
        "Kolmach\u00ebvo",
        "\u041a\u043e\u043b\u043c\u0430\u0447\u0451\u0432\u043e"
    ],
    "wof:name":"Kolmachevo",
    "wof:placetype":"locality"
},
  "geometry": {"coordinates":[35.39892000000001,62.27348000000001],"type":"Point"}
}