{
  "type": "Feature",
  "properties": {
    "gn:admin1_code":"73",
    "gn:asciiname":"Ostankovo",
    "gn:country_code":"RU",
    "gn:dem":89,
    "gn:feature_class":"P",
    "gn:feature_code":"PPL",
    "gn:name":"Ostankovo",
    "gn:population":0,
    "gn:timezone":"Europe/Moscow",
    "iso:country":"RU",
    "name:rus_x_preferred":[
        "\u041e\u0441\u0442\u0430\u043d\u043a\u043e\u0432\u043e"
    ],
    "wof:name":"Ostankovo",
    "wof:placetype":"locality"
},
  "geometry": {"coordinates":[52.6891,55.50514],"type":"Point"}
}