{
  "type": "Feature",
  "properties": {
    "gn:admin1_code":"38.0",
    "gn:asciiname":"Beysugskiye",
    "gn:country_code":"RU",
    "gn:dem":4,
    "gn:feature_class":"P",
    "gn:feature_code":"PPL",
    "gn:name":"Beysugskiye",
    "gn:population":0,
    "gn:timezone":"Europe/Moscow",
    "iso:country":"RU",
    "name:nor_x_preferred":[
        "Bejsugskije"
    ],
    "name:rus_x_preferred":[
        "\u0411\u0435\u0439\u0441\u0443\u0433\u0441\u043a\u0438\u0435"
    ],
    "name:und_x_variant":[
        "Khutora Beysugskiye",
        "Beysug",
        "Beysugskiye"
    ],
    "wof:name":"Beysugskiye",
    "wof:placetype":"locality"
},
  "geometry": {"coordinates":[38.70879,45.92753],"type":"Point"}
}