{
  "type": "Feature",
  "properties": {
    "gn:admin1_code":"47.0",
    "gn:asciiname":"Chigasovo",
    "gn:country_code":"RU",
    "gn:dem":194,
    "gn:feature_class":"P",
    "gn:feature_code":"PPL",
    "gn:name":"Chigasovo",
    "gn:population":0,
    "gn:timezone":"Europe/Moscow",
    "iso:country":"RU",
    "name:rus_x_preferred":[
        "\u0427\u0438\u0433\u0430\u0441\u043e\u0432\u043e"
    ],
    "wof:name":"Chigasovo",
    "wof:placetype":"locality"
},
  "geometry": {"coordinates":[36.95514,55.68733],"type":"Point"}
}