{
  "type": "Feature",
  "properties": {
    "gn:admin1_code":"63",
    "gn:asciiname":"Sitte",
    "gn:country_code":"RU",
    "gn:dem":45,
    "gn:feature_class":"P",
    "gn:feature_code":"PPL",
    "gn:name":"Sitte",
    "gn:population":0,
    "gn:timezone":"Asia/Yakutsk",
    "iso:country":"RU",
    "name:deu_x_preferred":[
        "Sitte"
    ],
    "name:nds_x_preferred":[
        "Sitte"
    ],
    "name:rus_x_preferred":[
        "\u0421\u0438\u0442\u0442\u0435"
    ],
    "name:rus_x_variant":[
        "\u0417\u0438\u0442\u0442\u0435"
    ],
    "wof:name":"Sitte",
    "wof:placetype":"locality"
},
  "geometry": {"coordinates":[127.01778,63.93389000000001],"type":"Point"}
}