{
  "type": "Feature",
  "properties": {
    "gn:admin1_code":"38.0",
    "gn:asciiname":"Sergeyevskiy",
    "gn:cc2":"RU",
    "gn:country_code":"RU",
    "gn:dem":81,
    "gn:feature_class":"P",
    "gn:feature_code":"PPL",
    "gn:name":"Sergeyevskiy",
    "gn:population":0,
    "gn:timezone":"Europe/Moscow",
    "iso:country":"RU",
    "name:rus_x_preferred":[
        "\u0421\u0435\u0440\u0433\u0435\u0435\u0432\u0441\u043a\u0438\u0439"
    ],
    "name:und_x_variant":[
        "Sergeyerskiy",
        "Sergeyevskiy",
        "\u0421\u0435\u0440\u0433\u0435\u0435\u0432\u0441\u043a\u0438\u0439"
    ],
    "wof:name":"Sergeyevskiy",
    "wof:placetype":"locality"
},
  "geometry": {"coordinates":[40.40389,45.24],"type":"Point"}
}