{
  "type": "Feature",
  "properties": {
    "gn:admin1_code":"43",
    "gn:asciiname":"Verkhnyaya Matrenka",
    "gn:country_code":"RU",
    "gn:dem":157,
    "gn:feature_class":"P",
    "gn:feature_code":"PPL",
    "gn:name":"Verkhnyaya Matr\u00ebnka",
    "gn:population":0,
    "gn:timezone":"Europe/Moscow",
    "iso:country":"RU",
    "name:rus_x_preferred":[
        "Verkhnyaya Matr\u00ebnka"
    ],
    "name:rus_x_variant":[
        "\u0412\u0435\u0440\u0445\u043d\u044f\u044f \u041c\u0430\u0442\u0440\u0451\u043d\u043a\u0430"
    ],
    "wof:name":"Verkhnyaya Matrenka",
    "wof:placetype":"locality"
},
  "geometry": {"coordinates":[40.18222,52.05444],"type":"Point"}
}