{
  "type": "Feature",
  "properties": {
    "gn:admin1_code":"54",
    "gn:asciiname":"Polyaki",
    "gn:country_code":"RU",
    "gn:dem":64,
    "gn:feature_class":"P",
    "gn:feature_code":"PPL",
    "gn:name":"Polyaki",
    "gn:population":0,
    "gn:timezone":"Asia/Omsk",
    "iso:country":"RU",
    "name:rus_x_preferred":[
        "\u041f\u043e\u043b\u044f\u043a\u0438"
    ],
    "wof:name":"Polyaki",
    "wof:placetype":"locality"
},
  "geometry": {"coordinates":[73.6215,57.1131],"type":"Point"}
}