{
  "type": "Feature",
  "properties": {
    "gn:admin1_code":"30",
    "gn:asciiname":"Seleya",
    "gn:cc2":"RU",
    "gn:country_code":"RU",
    "gn:dem":664,
    "gn:feature_class":"P",
    "gn:feature_code":"PPL",
    "gn:name":"Seleya",
    "gn:population":0,
    "gn:timezone":"Asia/Vladivostok",
    "iso:country":"RU",
    "name:rus_x_preferred":[
        "\u0421\u0435\u043b\u0435\u044f"
    ],
    "name:und_x_variant":[
        "Selen",
        "Seleya",
        "\u0421\u0435\u043b\u0435\u044f"
    ],
    "wof:name":"Seleya",
    "wof:placetype":"locality"
},
  "geometry": {"coordinates":[134.13333,58.68333000000001],"type":"Point"}
}