{
  "type": "Feature",
  "properties": {
    "gn:admin1_code":"55",
    "gn:asciiname":"Petro-Khersonets",
    "gn:country_code":"RU",
    "gn:dem":123,
    "gn:feature_class":"P",
    "gn:feature_code":"PPL",
    "gn:name":"Petro-Khersonets",
    "gn:population":0,
    "gn:timezone":"Asia/Yekaterinburg",
    "iso:country":"RU",
    "name:eng_x_preferred":[
        "Petro-Khersonets"
    ],
    "name:nor_x_preferred":[
        "Petro-Khersonets"
    ],
    "name:rus_x_preferred":[
        "\u041f\u0435\u0442\u0440\u043e-\u0425\u0435\u0440\u0441\u043e\u043d\u0435\u0446"
    ],
    "name:und_x_variant":[
        "\u041f\u0435\u0442\u0440\u043e-\u0425\u0435\u0440\u0441\u043e\u043d\u0435\u0446",
        "Petro-Khersonets"
    ],
    "wof:name":"Petro-Khersonets",
    "wof:placetype":"locality"
},
  "geometry": {"coordinates":[53.03333000000001,53.01667],"type":"Point"}
}