{
  "type": "Feature",
  "properties": {
    "gn:admin1_code":"67.0",
    "gn:asciiname":"Dukhovoye",
    "gn:country_code":"RU",
    "gn:dem":132,
    "gn:feature_class":"P",
    "gn:feature_code":"PPL",
    "gn:name":"Dukhovoye",
    "gn:population":0,
    "gn:timezone":"Europe/Saratov",
    "iso:country":"RU",
    "name:rus_x_preferred":[
        "\u0414\u0443\u0445\u043e\u0432\u043e\u0435"
    ],
    "name:und_x_variant":[
        "Dukhovoy"
    ],
    "wof:name":"Dukhovoye",
    "wof:placetype":"locality"
},
  "geometry": {"coordinates":[43.36083,51.99236],"type":"Point"}
}