{
  "type": "Feature",
  "properties": {
    "gn:admin1_code":"62",
    "gn:asciiname":"Sidorovo",
    "gn:country_code":"RU",
    "gn:dem":129,
    "gn:feature_class":"P",
    "gn:feature_code":"PPL",
    "gn:name":"Sidorovo",
    "gn:population":0,
    "gn:timezone":"Europe/Moscow",
    "iso:country":"RU",
    "name:rus_x_preferred":[
        "\u0421\u0438\u0434\u043e\u0440\u043e\u0432\u043e"
    ],
    "name:und_x_variant":[
        "\u0421\u0438\u0434\u043e\u0440\u043e\u0432\u043e"
    ],
    "wof:name":"Sidorovo",
    "wof:placetype":"locality"
},
  "geometry": {"coordinates":[41.27598,54.86163000000001],"type":"Point"}
}