{
  "type": "Feature",
  "properties": {
    "gn:admin1_code":"72.0",
    "gn:asciiname":"Goloday Dmitriyevka",
    "gn:country_code":"RU",
    "gn:dem":158,
    "gn:feature_class":"P",
    "gn:feature_code":"PPL",
    "gn:name":"Goloday Dmitriyevka",
    "gn:population":0,
    "gn:timezone":"Europe/Moscow",
    "iso:country":"RU",
    "name:rus_x_preferred":[
        "\u0413\u043e\u043b\u043e\u0434\u0430\u0439 \u0414\u043c\u0438\u0442\u0440\u0438\u0435\u0432\u043a\u0430"
    ],
    "name:und_x_variant":[
        "\u0413\u043e\u043b\u043e\u0434\u0430\u0439 \u0414\u043c\u0438\u0442\u0440\u0438\u0435\u0432\u043a\u0430"
    ],
    "wof:name":"Goloday Dmitriyevka",
    "wof:placetype":"locality"
},
  "geometry": {"coordinates":[40.84306,52.31972],"type":"Point"}
}