{
  "type": "Feature",
  "properties": {
    "gn:admin1_code":"81.0",
    "gn:asciiname":"Pyatisotennyy",
    "gn:country_code":"RU",
    "gn:dem":90,
    "gn:feature_class":"P",
    "gn:feature_code":"PPL",
    "gn:name":"Pyatisotennyy",
    "gn:population":0,
    "gn:timezone":"Europe/Ulyanovsk",
    "iso:country":"RU",
    "name:und_x_variant":[
        "Otdeleniye Nomer Tri Uchebnogo Khozyaystva Sel\u2019skokhozyaystvennogo Instituta",
        "Pyatisotennyy"
    ],
    "wof:name":"Pyatisotennyy",
    "wof:placetype":"locality"
},
  "geometry": {"coordinates":[48.81936,54.22315],"type":"Point"}
}