{
  "type": "Feature",
  "properties": {
    "gn:admin1_code":"53",
    "gn:asciiname":"Ust'-Urgul'ka",
    "gn:country_code":"RU",
    "gn:dem":114,
    "gn:feature_class":"P",
    "gn:feature_code":"PPL",
    "gn:name":"Ust\u2019-Urgul\u2019ka",
    "gn:population":0,
    "gn:timezone":"Asia/Novosibirsk",
    "iso:country":"RU",
    "name:eng_x_preferred":[
        "Ust'-Urgul'ka"
    ],
    "name:nor_x_preferred":[
        "Ust-Urgulka"
    ],
    "name:rus_x_preferred":[
        "\u0423\u0441\u0442\u044c-\u0423\u0440\u0433\u0443\u043b\u044c\u043a\u0430"
    ],
    "name:und_x_variant":[
        "Ust\u2019-Urgul\u2019ka"
    ],
    "wof:name":"Ust'-Urgul'ka",
    "wof:placetype":"locality"
},
  "geometry": {"coordinates":[77.79052,56.33145],"type":"Point"}
}