{
  "type": "Feature",
  "properties": {
    "gn:admin1_code":"43",
    "gn:asciiname":"Lozy",
    "gn:country_code":"RU",
    "gn:dem":138,
    "gn:feature_class":"P",
    "gn:feature_code":"PPL",
    "gn:name":"Lozy",
    "gn:population":0,
    "gn:timezone":"Europe/Moscow",
    "iso:country":"RU",
    "name:rus_x_preferred":[
        "\u041b\u043e\u0437\u044b"
    ],
    "name:und_x_variant":[
        "\u041b\u043e\u0437\u044b"
    ],
    "wof:name":"Lozy",
    "wof:placetype":"locality"
},
  "geometry": {"coordinates":[39.19165,52.43616],"type":"Point"}
}