{
  "type": "Feature",
  "properties": {
    "gn:admin1_code":"8",
    "gn:asciiname":"Kushkulevo",
    "gn:country_code":"RU",
    "gn:dem":169,
    "gn:feature_class":"P",
    "gn:feature_code":"PPL",
    "gn:name":"Kushkulevo",
    "gn:population":0,
    "gn:timezone":"Asia/Yekaterinburg",
    "iso:country":"RU",
    "name:rus_x_preferred":[
        "\u041a\u0443\u0448\u043a\u0443\u043b\u0435\u0432\u043e"
    ],
    "name:und_x_variant":[
        "Kushkul\u2019",
        "Kushkulevo"
    ],
    "wof:name":"Kushkulevo",
    "wof:placetype":"locality"
},
  "geometry": {"coordinates":[56.60025,54.97695],"type":"Point"}
}