{
  "type": "Feature",
  "properties": {
    "gn:admin1_code":"84",
    "gn:asciiname":"Uspenka",
    "gn:country_code":"RU",
    "gn:dem":133,
    "gn:feature_class":"P",
    "gn:feature_code":"PPL",
    "gn:name":"Uspenka",
    "gn:population":0,
    "gn:timezone":"Europe/Volgograd",
    "iso:country":"RU",
    "name:eng_x_preferred":[
        "Uspenka"
    ],
    "name:nor_x_preferred":[
        "Uspenskij"
    ],
    "name:rus_x_preferred":[
        "\u0423\u0441\u043f\u0435\u043d\u0441\u043a\u0438\u0439"
    ],
    "name:rus_x_variant":[
        "\u0423\u0441\u043f\u0435\u043d\u043a\u0430"
    ],
    "name:und_x_variant":[
        "Uspenskaya",
        "Uspenskiy",
        "Uspenka"
    ],
    "wof:name":"Uspenka",
    "wof:placetype":"locality"
},
  "geometry": {"coordinates":[41.4779,50.6307],"type":"Point"}
}