{
  "type": "Feature",
  "properties": {
    "gn:admin1_code":"52",
    "gn:asciiname":"Staryye Ladomiri",
    "gn:country_code":"RU",
    "gn:dem":64,
    "gn:feature_class":"P",
    "gn:feature_code":"PPL",
    "gn:name":"Staryye Ladomiri",
    "gn:population":0,
    "gn:timezone":"Europe/Moscow",
    "iso:country":"RU",
    "name:rus_x_preferred":[
        "\u0421\u0442\u0430\u0440\u044b\u0435 \u041b\u0430\u0434\u043e\u043c\u0438\u0440\u0438"
    ],
    "name:und_x_variant":[
        "Staryye Ladomery",
        "Staryye Ladomiry",
        "Staryye Ladomiri"
    ],
    "wof:name":"Staryye Ladomiri",
    "wof:placetype":"locality"
},
  "geometry": {"coordinates":[32.33619,57.57601999999999],"type":"Point"}
}