{
  "type": "Feature",
  "properties": {
    "gn:admin1_code":"76",
    "gn:asciiname":"Kukuy",
    "gn:country_code":"RU",
    "gn:dem":201,
    "gn:feature_class":"P",
    "gn:feature_code":"PPL",
    "gn:name":"Kukuy",
    "gn:population":0,
    "gn:timezone":"Europe/Moscow",
    "iso:country":"RU",
    "name:rus_x_preferred":[
        "\u041a\u0443\u043a\u0443\u0439"
    ],
    "wof:name":"Kukuy",
    "wof:placetype":"locality"
},
  "geometry": {"coordinates":[38.4974,54.121],"type":"Point"}
}