{
  "type": "Feature",
  "properties": {
    "gn:admin1_code":"41",
    "gn:asciiname":"Abramovskiy",
    "gn:country_code":"RU",
    "gn:dem":234,
    "gn:feature_class":"P",
    "gn:feature_code":"PPL",
    "gn:name":"Abramovskiy",
    "gn:population":0,
    "gn:timezone":"Europe/Moscow",
    "iso:country":"RU",
    "name:rus_x_preferred":[
        "\u0410\u0431\u0440\u0430\u043c\u043e\u0432\u0441\u043a\u0438\u0439"
    ],
    "wof:name":"Abramovskiy",
    "wof:placetype":"locality"
},
  "geometry": {"coordinates":[35.8313,51.9164],"type":"Point"}
}