{
  "type": "Feature",
  "properties": {
    "gn:admin1_code":"76.0",
    "gn:asciiname":"Andrianovka",
    "gn:country_code":"RU",
    "gn:dem":230,
    "gn:feature_class":"P",
    "gn:feature_code":"PPL",
    "gn:name":"Andrianovka",
    "gn:population":0,
    "gn:timezone":"Europe/Moscow",
    "iso:country":"RU",
    "name:bak_x_preferred":[
        "\u0410\u043d\u0434\u0440\u0438\u0430\u043d\u043e\u0432\u043a\u0430"
    ],
    "name:che_x_preferred":[
        "\u0410\u043d\u0434\u0440\u0438\u0430\u043d\u043e\u0432\u043a\u0430"
    ],
    "name:chv_x_preferred":[
        "\u0410\u043d\u0434\u0440\u0438\u0430\u043d\u043e\u0432\u043a\u0430"
    ],
    "name:hye_x_preferred":[
        "\u0531\u0576\u0564\u0580\u056b\u0561\u0576\u0578\u057e\u056f\u0561"
    ],
    "name:kat_x_preferred":[
        "\u10d0\u10dc\u10d3\u10e0\u10d8\u10d0\u10dc\u10dd\u10d5\u10d9\u10d0"
    ],
    "name:kaz_x_preferred":[
        "\u0410\u043d\u0434\u0440\u0438\u0430\u043d\u043e\u0432\u043a\u0430"
    ],
    "name:kir_x_preferred":[
        "\u0410\u043d\u0434\u0440\u0438\u0430\u043d\u043e\u0432\u043a\u0430"
    ],
    "name:nor_x_preferred":[
        "Andrianovka"
    ],
    "name:rus_x_preferred":[
        "\u0410\u043d\u0434\u0440\u0438\u0430\u043d\u043e\u0432\u043a\u0430"
    ],
    "name:tat_x_preferred":[
        "\u0410\u043d\u0434\u0440\u0438\u0430\u043d\u043e\u0432\u043a\u0430"
    ],
    "name:ukr_x_preferred":[
        "\u0410\u043d\u0434\u0440\u0456\u0430\u043d\u043e\u0432\u043a\u0430"
    ],
    "wof:name":"Andrianovka",
    "wof:placetype":"locality"
},
  "geometry": {"coordinates":[37.79934,53.58629000000001],"type":"Point"}
}