{
  "type": "Feature",
  "properties": {
    "gn:admin1_code":"9",
    "gn:asciiname":"Soldatskoye",
    "gn:country_code":"RU",
    "gn:dem":171,
    "gn:feature_class":"P",
    "gn:feature_code":"PPL",
    "gn:name":"Soldatskoye",
    "gn:population":0,
    "gn:timezone":"Europe/Moscow",
    "iso:country":"RU",
    "name:eng_x_preferred":[
        "Soldatskoye"
    ],
    "name:nor_x_preferred":[
        "Soldatskoje"
    ],
    "name:rus_x_preferred":[
        "\u0421\u043e\u043b\u0434\u0430\u0442\u0441\u043a\u043e\u0435"
    ],
    "name:und_x_variant":[
        "Pokrovskoye"
    ],
    "wof:name":"Soldatskoye",
    "wof:placetype":"locality"
},
  "geometry": {"coordinates":[35.78306,50.71944000000001],"type":"Point"}
}