{
  "type": "Feature",
  "properties": {
    "gn:admin1_code":"90",
    "gn:asciiname":"Mosino",
    "gn:country_code":"RU",
    "gn:dem":157,
    "gn:feature_class":"P",
    "gn:feature_code":"PPL",
    "gn:name":"Mosino",
    "gn:population":0,
    "gn:timezone":"Asia/Yekaterinburg",
    "iso:country":"RU",
    "name:rus_x_preferred":[
        "\u041c\u043e\u0441\u0438\u043d\u043e"
    ],
    "name:und_x_variant":[
        "Mosina",
        "Mosino"
    ],
    "wof:name":"Mosino",
    "wof:placetype":"locality"
},
  "geometry": {"coordinates":[54.58725,58.09816],"type":"Point"}
}