{
  "type": "Feature",
  "properties": {
    "gn:admin1_code":"91",
    "gn:asciiname":"Vorogovo",
    "gn:country_code":"RU",
    "gn:dem":35,
    "gn:feature_class":"P",
    "gn:feature_code":"PPL",
    "gn:name":"Vorogovo",
    "gn:population":0,
    "gn:timezone":"Asia/Krasnoyarsk",
    "iso:country":"RU",
    "name:eng_x_preferred":[
        "Vorogovo"
    ],
    "name:nor_x_preferred":[
        "Vorogovo"
    ],
    "name:rus_x_preferred":[
        "\u0412\u043e\u0440\u043e\u0433\u043e\u0432\u043e"
    ],
    "name:und_x_variant":[
        "Vorokovo",
        "Vorogovo"
    ],
    "wof:name":"Vorogovo",
    "wof:placetype":"locality"
},
  "geometry": {"coordinates":[89.61799999999999,61.02743],"type":"Point"}
}