{
  "type": "Feature",
  "properties": {
    "gn:admin1_code":"85",
    "gn:asciiname":"Kolbino",
    "gn:country_code":"RU",
    "gn:dem":155,
    "gn:feature_class":"P",
    "gn:feature_code":"PPL",
    "gn:name":"Kolbino",
    "gn:population":0,
    "gn:timezone":"Europe/Moscow",
    "iso:country":"RU",
    "name:rus_x_preferred":[
        "\u041a\u043e\u043b\u0431\u0438\u043d\u043e"
    ],
    "name:und_x_variant":[
        "\u041a\u043e\u043b\u0431\u0438\u043d\u043e"
    ],
    "wof:name":"Kolbino",
    "wof:placetype":"locality"
},
  "geometry": {"coordinates":[39.69673,59.3699],"type":"Point"}
}