{
  "type": "Feature",
  "properties": {
    "gn:admin1_code":"29",
    "gn:asciiname":"Rudzitovka",
    "gn:country_code":"RU",
    "gn:dem":301,
    "gn:feature_class":"P",
    "gn:feature_code":"PPL",
    "gn:name":"Rudzitovka",
    "gn:population":0,
    "gn:timezone":"Asia/Novokuznetsk",
    "iso:country":"RU",
    "name:rus_x_preferred":[
        "\u0420\u0443\u0434\u0437\u0438\u0442\u043e\u0432\u043a\u0430"
    ],
    "wof:name":"Rudzitovka",
    "wof:placetype":"locality"
},
  "geometry": {"coordinates":[88.99167,56.20889],"type":"Point"}
}