{
  "type": "Feature",
  "properties": {
    "gn:admin1_code":"63",
    "gn:asciiname":"Kumakh-Bulung",
    "gn:country_code":"RU",
    "gn:dem":111,
    "gn:feature_class":"P",
    "gn:feature_code":"PPL",
    "gn:name":"Kumakh-Bulung",
    "gn:population":0,
    "gn:timezone":"Asia/Vladivostok",
    "iso:country":"RU",
    "name:rus_x_preferred":[
        "\u041a\u0443\u043c\u0430\u0445-\u0411\u0443\u043b\u0443\u043d\u0433"
    ],
    "wof:name":"Kumakh-Bulung",
    "wof:placetype":"locality"
},
  "geometry": {"coordinates":[135.19106000000002,62.58413],"type":"Point"}
}