{
  "type": "Feature",
  "properties": {
    "gn:admin1_code":"84.0",
    "gn:asciiname":"Biryukov",
    "gn:country_code":"RU",
    "gn:dem":37,
    "gn:feature_class":"P",
    "gn:feature_code":"PPL",
    "gn:name":"Biryukov",
    "gn:population":0,
    "gn:timezone":"Europe/Volgograd",
    "iso:country":"RU",
    "name:rus_x_preferred":[
        "\u0411\u0438\u0440\u044e\u043a\u043e\u0432"
    ],
    "name:und_x_variant":[
        "\u0411\u0438\u0440\u044e\u043a\u043e\u0432"
    ],
    "wof:name":"Biryukov",
    "wof:placetype":"locality"
},
  "geometry": {"coordinates":[43.31667,47.98333],"type":"Point"}
}