{
  "type": "Feature",
  "properties": {
    "gn:admin1_code":"38",
    "gn:asciiname":"Lesodacha",
    "gn:country_code":"RU",
    "gn:dem":100,
    "gn:feature_class":"P",
    "gn:feature_code":"PPL",
    "gn:name":"Lesodacha",
    "gn:population":0,
    "gn:timezone":"Europe/Moscow",
    "iso:country":"RU",
    "name:rus_x_preferred":[
        "\u041b\u0435\u0441\u043e\u0434\u0430\u0447\u0430"
    ],
    "wof:name":"Lesodacha",
    "wof:placetype":"locality"
},
  "geometry": {"coordinates":[40.94111,45.36861],"type":"Point"}
}