{
  "type": "Feature",
  "properties": {
    "gn:admin1_code":"55",
    "gn:asciiname":"Karavannyy",
    "gn:country_code":"RU",
    "gn:dem":106,
    "gn:feature_class":"P",
    "gn:feature_code":"PPL",
    "gn:name":"Karavannyy",
    "gn:population":0,
    "gn:timezone":"Asia/Yekaterinburg",
    "iso:country":"RU",
    "name:eng_x_preferred":[
        "Karavannyy"
    ],
    "name:nor_x_preferred":[
        "Karavannyj"
    ],
    "name:rus_x_preferred":[
        "\u041a\u0430\u0440\u0430\u0432\u0430\u043d\u043d\u044b\u0439"
    ],
    "wof:name":"Karavannyy",
    "wof:placetype":"locality"
},
  "geometry": {"coordinates":[55.64106999999999,51.69874],"type":"Point"}
}