{
  "type": "Feature",
  "properties": {
    "gn:admin1_code":"20",
    "gn:asciiname":"Butyrina",
    "gn:country_code":"RU",
    "gn:dem":492,
    "gn:feature_class":"P",
    "gn:feature_code":"PPL",
    "gn:name":"Butyrina",
    "gn:population":0,
    "gn:timezone":"Asia/Irkutsk",
    "iso:country":"RU",
    "name:eng_x_preferred":[
        "Butyrina"
    ],
    "name:nor_x_preferred":[
        "Butyrina"
    ],
    "name:rus_x_preferred":[
        "\u0411\u0443\u0442\u044b\u0440\u0438\u043d\u0430"
    ],
    "name:und_x_variant":[
        "Butyrki"
    ],
    "wof:name":"Butyrina",
    "wof:placetype":"locality"
},
  "geometry": {"coordinates":[104.70780000000001,54.4199],"type":"Point"}
}