{
  "type": "Feature",
  "properties": {
    "gn:admin1_code":"51",
    "gn:asciiname":"Gulikha",
    "gn:country_code":"RU",
    "gn:dem":107,
    "gn:feature_class":"P",
    "gn:feature_code":"PPL",
    "gn:name":"Gulikha",
    "gn:population":0,
    "gn:timezone":"Europe/Moscow",
    "iso:country":"RU",
    "name:rus_x_preferred":[
        "\u0413\u0443\u043b\u0438\u0445\u0430"
    ],
    "wof:name":"Gulikha",
    "wof:placetype":"locality"
},
  "geometry": {"coordinates":[45.25100000000001,57.0877],"type":"Point"}
}