{
  "type": "Feature",
  "properties": {
    "gn:admin1_code":"41",
    "gn:asciiname":"Obesta",
    "gn:country_code":"RU",
    "gn:dem":155,
    "gn:feature_class":"P",
    "gn:feature_code":"PPL",
    "gn:name":"Obesta",
    "gn:population":0,
    "gn:timezone":"Europe/Moscow",
    "iso:country":"RU",
    "name:rus_x_preferred":[
        "\u041e\u0431\u0435\u0441\u0442\u0430"
    ],
    "name:und_x_variant":[
        "\u041e\u0431\u0435\u0441\u0442\u0430"
    ],
    "wof:name":"Obesta",
    "wof:placetype":"locality"
},
  "geometry": {"coordinates":[34.2901,51.6489],"type":"Point"}
}