{
  "type": "Feature",
  "properties": {
    "iso:country":"RU",
    "name:rus_x_preferred":[
        "\u0421\u043e\u043a\u043e\u043b\u0438\u043d\u0430\u044f \u0433\u043e\u0440\u0430"
    ],
    "wof:name":"Sokolinaya Gora",
    "wof:placetype":"neighbourhood"
},
  "geometry": {"coordinates":[37.73156363281233,55.77369945849936],"type":"Point"}
}