{
  "type": "Feature",
  "properties": {
    "gn:admin1_code":"84",
    "gn:asciiname":"Makarovka",
    "gn:country_code":"RU",
    "gn:dem":184,
    "gn:feature_class":"P",
    "gn:feature_code":"PPL",
    "gn:name":"Makarovka",
    "gn:population":0,
    "gn:timezone":"Europe/Volgograd",
    "iso:country":"RU",
    "name:eng_x_preferred":[
        "Makarovka"
    ],
    "name:nor_x_preferred":[
        "Makarovka"
    ],
    "name:rus_x_preferred":[
        "\u041c\u0430\u043a\u0430\u0440\u043e\u0432\u043a\u0430"
    ],
    "name:und_x_variant":[
        "Merkel\u2019"
    ],
    "wof:name":"Makarovka",
    "wof:placetype":"locality"
},
  "geometry": {"coordinates":[45.28722,50.88578],"type":"Point"}
}