{
  "type": "Feature",
  "properties": {
    "gn:admin1_code":"9",
    "gn:asciiname":"Russkaya Matrenka",
    "gn:cc2":"RU",
    "gn:country_code":"RU",
    "gn:dem":94,
    "gn:feature_class":"P",
    "gn:feature_code":"PPL",
    "gn:name":"Russkaya Matr\u00ebnka",
    "gn:population":0,
    "gn:timezone":"Europe/Moscow",
    "iso:country":"RU",
    "name:rus_x_preferred":[
        "\u0420\u0443\u0441\u0441\u043a\u0430\u044f \u041c\u0430\u0442\u0440\u0451\u043d\u043a\u0430"
    ],
    "name:und_x_variant":[
        "Matrenka Russkaya",
        "Russkaya Matr\u00ebnka"
    ],
    "wof:name":"Russkaya Matrenka",
    "wof:placetype":"locality"
},
  "geometry": {"coordinates":[38.86667,50.66667],"type":"Point"}
}