{
  "type": "Feature",
  "properties": {
    "gn:admin1_code":"37",
    "gn:asciiname":"Troitskoye",
    "gn:country_code":"RU",
    "gn:dem":130,
    "gn:feature_class":"P",
    "gn:feature_code":"PPL",
    "gn:name":"Troitskoye",
    "gn:population":0,
    "gn:timezone":"Europe/Moscow",
    "iso:country":"RU",
    "name:rus_x_preferred":[
        "\u0422\u043f\u043e\u0438\u0446\u043a\u043e\u0435"
    ],
    "name:und_x_variant":[
        "\u0422\u043f\u043e\u0438\u0446\u043a\u043e\u0435"
    ],
    "wof:name":"Troitskoye",
    "wof:placetype":"locality"
},
  "geometry": {"coordinates":[42.7238,58.0161],"type":"Point"}
}