{
  "type": "Feature",
  "properties": {
    "gn:admin1_code":"90",
    "gn:asciiname":"Kos'va",
    "gn:country_code":"RU",
    "gn:dem":144,
    "gn:feature_class":"P",
    "gn:feature_code":"PPL",
    "gn:name":"Kos\u2019va",
    "gn:population":0,
    "gn:timezone":"Asia/Yekaterinburg",
    "iso:country":"RU",
    "name:rus_x_preferred":[
        "\u041a\u043e\u0441\u044c\u0432\u0430"
    ],
    "name:und_x_variant":[
        "Kos\u2019va",
        "\u041a\u043e\u0441\u044c\u0432\u0430"
    ],
    "wof:name":"Kos'va",
    "wof:placetype":"locality"
},
  "geometry": {"coordinates":[54.90167,59.20861],"type":"Point"}
}