{
  "type": "Feature",
  "properties": {
    "gn:admin1_code":"3",
    "gn:asciiname":"Terekta",
    "gn:country_code":"RU",
    "gn:dem":1066,
    "gn:feature_class":"P",
    "gn:feature_code":"PPL",
    "gn:name":"Terekta",
    "gn:population":0,
    "gn:timezone":"Asia/Omsk",
    "iso:country":"RU",
    "name:eng_x_preferred":[
        "Terekhta"
    ],
    "name:nor_x_preferred":[
        "Terekta"
    ],
    "name:rus_x_preferred":[
        "\u0422\u0435\u0440\u0435\u043a\u0442\u0430"
    ],
    "name:und_x_variant":[
        "Terekhta",
        "Terekta"
    ],
    "wof:name":"Terekta",
    "wof:placetype":"locality"
},
  "geometry": {"coordinates":[85.88039999999999,50.3007],"type":"Point"}
}