{
  "type": "Feature",
  "properties": {
    "gn:admin1_code":"10",
    "gn:asciiname":"Znamenka",
    "gn:country_code":"RU",
    "gn:dem":185,
    "gn:feature_class":"P",
    "gn:feature_code":"PPL",
    "gn:name":"Znamenka",
    "gn:population":0,
    "gn:timezone":"Europe/Moscow",
    "iso:country":"RU",
    "name:rus_x_preferred":[
        "\u0417\u043d\u0430\u043c\u0435\u043d\u043a\u0430"
    ],
    "name:und_x_variant":[
        "Stigaylovka",
        "Stegaylovka",
        "Znamenka"
    ],
    "wof:name":"Znamenka",
    "wof:placetype":"locality"
},
  "geometry": {"coordinates":[34.7028,52.3147],"type":"Point"}
}