{
  "type": "Feature",
  "properties": {
    "gn:admin1_code":"65",
    "gn:asciiname":"Kazakov",
    "gn:country_code":"RU",
    "gn:dem":165,
    "gn:feature_class":"P",
    "gn:feature_code":"PPL",
    "gn:name":"Kazakov",
    "gn:population":0,
    "gn:timezone":"Europe/Samara",
    "iso:country":"RU",
    "name:bel_x_preferred":[
        "\u041a\u0430\u0437\u0430\u043a\u043e\u045e"
    ],
    "name:bul_x_preferred":[
        "\u041a\u0430\u0437\u0430\u043a\u043e\u0432"
    ],
    "name:chv_x_preferred":[
        "\u041a\u0430\u0437\u0430\u043a\u043e\u0432"
    ],
    "name:deu_x_preferred":[
        "Kasakow"
    ],
    "name:fra_x_preferred":[
        "Kazakov"
    ],
    "name:ita_x_preferred":[
        "Kazakov"
    ],
    "name:rus_x_preferred":[
        "\u041a\u0430\u0437\u0430\u043a\u043e\u0432"
    ],
    "name:slv_x_preferred":[
        "Kazakov"
    ],
    "name:tat_x_preferred":[
        "\u041a\u0430\u0437\u0430\u043a\u043e\u0432"
    ],
    "name:ukr_x_preferred":[
        "\u041a\u0430\u0437\u0430\u043a\u043e\u0432"
    ],
    "wof:name":"Kazakov",
    "wof:placetype":"locality"
},
  "geometry": {"coordinates":[50.43333,53.63333000000001],"type":"Point"}
}