{
  "type": "Feature",
  "properties": {
    "gn:admin1_code":"51",
    "gn:asciiname":"Korovayevo",
    "gn:country_code":"RU",
    "gn:dem":173,
    "gn:feature_class":"P",
    "gn:feature_code":"PPL",
    "gn:name":"Korovayevo",
    "gn:population":0,
    "gn:timezone":"Europe/Moscow",
    "iso:country":"RU",
    "name:rus_x_preferred":[
        "\u041a\u043e\u0440\u043e\u0432\u0430\u0435\u0432\u043e"
    ],
    "wof:name":"Korovayevo",
    "wof:placetype":"locality"
},
  "geometry": {"coordinates":[42.5315,55.8775],"type":"Point"}
}