{
  "type": "Feature",
  "properties": {
    "gn:admin1_code":"88.0",
    "gn:asciiname":"Dikushi",
    "gn:country_code":"RU",
    "gn:dem":126,
    "gn:feature_class":"P",
    "gn:feature_code":"PPL",
    "gn:name":"Dikushi",
    "gn:population":0,
    "gn:timezone":"Europe/Moscow",
    "iso:country":"RU",
    "name:rus_x_preferred":[
        "\u0414\u0438\u043a\u0443\u0448\u0438"
    ],
    "name:und_x_variant":[
        "\u0414\u0438\u043a\u0443\u0448\u0438"
    ],
    "wof:name":"Dikushi",
    "wof:placetype":"locality"
},
  "geometry": {"coordinates":[39.481,58.2342],"type":"Point"}
}