{
  "type": "Feature",
  "properties": {
    "gn:admin1_code":"05",
    "gn:asciiname":"Mramornoye",
    "gn:cc2":"RU",
    "gn:country_code":"RU",
    "gn:dem":237,
    "gn:feature_class":"P",
    "gn:feature_code":"PPL",
    "gn:name":"Mramornoye",
    "gn:population":0,
    "gn:timezone":"Asia/Yakutsk",
    "iso:country":"RU",
    "name:rus_x_preferred":[
        "\u041c\u0440\u0430\u043c\u043e\u0440\u043d\u043e\u0435"
    ],
    "name:und_x_variant":[
        "Mramornyy",
        "Mramornoye",
        "\u041c\u0440\u0430\u043c\u043e\u0440\u043d\u043e\u0435"
    ],
    "wof:name":"Mramornoye",
    "wof:placetype":"locality"
},
  "geometry": {"coordinates":[128.28333000000001,52.13333],"type":"Point"}
}