{
  "type": "Feature",
  "properties": {
    "gn:admin1_code":"42",
    "gn:asciiname":"Trusovo",
    "gn:country_code":"RU",
    "gn:dem":24,
    "gn:feature_class":"P",
    "gn:feature_code":"PPL",
    "gn:name":"Trusovo",
    "gn:population":0,
    "gn:timezone":"Europe/Moscow",
    "iso:country":"RU",
    "name:che_x_preferred":[
        "\u0422\u0440\u0443\u0441\u043e\u0432\u043e"
    ],
    "name:rus_x_preferred":[
        "\u0422\u0440\u0443\u0441\u043e\u0432\u043e"
    ],
    "name:tgk_x_preferred":[
        "\u0422\u0440\u0443\u0441\u043e\u0432\u043e"
    ],
    "wof:name":"Trusovo",
    "wof:placetype":"locality"
},
  "geometry": {"coordinates":[32.24336,60.02886],"type":"Point"}
}