{
  "type": "Feature",
  "properties": {
    "gn:admin1_code":"42",
    "gn:asciiname":"Trusovo",
    "gn:country_code":"RU",
    "gn:dem":24,
    "gn:feature_class":"P",
    "gn:feature_code":"PPL",
    "gn:name":"Trusovo",
    "gn:population":0,
    "gn:timezone":"Europe/Moscow",
    "iso:country":"RU",
    "wof:name":"Trusovo",
    "wof:placetype":"locality"
},
  "geometry": {"coordinates":[32.24336,60.02886],"type":"Point"}
}