{
  "type": "Feature",
  "properties": {
    "gn:admin1_code":"42",
    "gn:asciiname":"Zhog",
    "gn:country_code":"RU",
    "gn:dem":76,
    "gn:feature_class":"P",
    "gn:feature_code":"PPL",
    "gn:name":"Zhog",
    "gn:population":0,
    "gn:timezone":"Europe/Moscow",
    "iso:country":"RU",
    "name:rus_x_preferred":[
        "\u0416\u043e\u0433"
    ],
    "name:und_x_variant":[
        "\u0416\u043e\u0433"
    ],
    "wof:name":"Zhog",
    "wof:placetype":"locality"
},
  "geometry": {"coordinates":[28.8774,58.9264],"type":"Point"}
}