{
  "type": "Feature",
  "properties": {
    "gn:admin1_code":"52",
    "gn:asciiname":"Nizhniye Tikkuly",
    "gn:country_code":"RU",
    "gn:dem":66,
    "gn:feature_class":"P",
    "gn:feature_code":"PPL",
    "gn:name":"Nizhniye Tikkuly",
    "gn:population":0,
    "gn:timezone":"Europe/Moscow",
    "iso:country":"RU",
    "name:rus_x_preferred":[
        "\u041d\u0438\u0436\u043d\u0438\u0435 \u0422\u0438\u043a\u043a\u0443\u043b\u044b"
    ],
    "wof:name":"Nizhniye Tikkuly",
    "wof:placetype":"locality"
},
  "geometry": {"coordinates":[32.49222,58.57535],"type":"Point"}
}