{
  "type": "Feature",
  "properties": {
    "gn:admin1_code":"90",
    "gn:asciiname":"Taush",
    "gn:country_code":"RU",
    "gn:dem":135,
    "gn:feature_class":"P",
    "gn:feature_code":"PPL",
    "gn:name":"Taush",
    "gn:population":0,
    "gn:timezone":"Asia/Yekaterinburg",
    "iso:country":"RU",
    "name:eng_x_preferred":[
        "Taush"
    ],
    "name:nor_x_preferred":[
        "Tausj"
    ],
    "name:rus_x_preferred":[
        "\u0422\u0430\u0443\u0448"
    ],
    "name:und_x_variant":[
        "Raush",
        "Taush"
    ],
    "wof:name":"Taush",
    "wof:placetype":"locality"
},
  "geometry": {"coordinates":[56.07751999999999,56.4299],"type":"Point"}
}