{
  "type": "Feature",
  "properties": {
    "gn:admin1_code":"72",
    "gn:asciiname":"Vtoraya Pokrovskaya",
    "gn:country_code":"RU",
    "gn:dem":166,
    "gn:feature_class":"P",
    "gn:feature_code":"PPL",
    "gn:name":"Vtoraya Pokrovskaya",
    "gn:population":0,
    "gn:timezone":"Europe/Moscow",
    "iso:country":"RU",
    "name:rus_x_preferred":[
        "\u0412\u0442\u043e\u0440\u0430\u044f \u041f\u043e\u043a\u0440\u043e\u0432\u0441\u043a\u0430\u044f"
    ],
    "name:und_x_variant":[
        "Pokrovskaya",
        "Kortsevo",
        "Vtoraya Pokrovskaya"
    ],
    "wof:name":"Vtoraya Pokrovskaya",
    "wof:placetype":"locality"
},
  "geometry": {"coordinates":[40.9633,52.4046],"type":"Point"}
}