{
  "type": "Feature",
  "properties": {
    "gn:admin1_code":"88.0",
    "gn:asciiname":"Levinskoye",
    "gn:country_code":"RU",
    "gn:dem":125,
    "gn:feature_class":"P",
    "gn:feature_code":"PPL",
    "gn:name":"Levinskoye",
    "gn:population":0,
    "gn:timezone":"Europe/Moscow",
    "iso:country":"RU",
    "name:rus_x_preferred":[
        "\u041b\u0435\u0432\u0438\u043d\u0441\u043a\u043e\u0435"
    ],
    "name:und_x_variant":[
        "\u041b\u0435\u0432\u0438\u043d\u0441\u043a\u043e\u0435"
    ],
    "wof:name":"Levinskoye",
    "wof:placetype":"locality"
},
  "geometry": {"coordinates":[40.30901,58.38925],"type":"Point"}
}