{
  "type": "Feature",
  "properties": {
    "gn:admin1_code":"47",
    "gn:asciiname":"Vtoraya Pyatiletka",
    "gn:country_code":"RU",
    "gn:dem":182,
    "gn:feature_class":"P",
    "gn:feature_code":"PPL",
    "gn:name":"Vtoraya Pyatiletka",
    "gn:population":0,
    "gn:timezone":"Europe/Moscow",
    "iso:country":"RU",
    "wof:name":"Vtoraya Pyatiletka",
    "wof:placetype":"locality"
},
  "geometry": {"coordinates":[38.23931,55.09125],"type":"Point"}
}