{
  "type": "Feature",
  "properties": {
    "gn:admin1_code":"33",
    "gn:asciiname":"Myasovskaya",
    "gn:country_code":"RU",
    "gn:dem":117,
    "gn:feature_class":"P",
    "gn:feature_code":"PPL",
    "gn:name":"Myasovskaya",
    "gn:population":0,
    "gn:timezone":"Europe/Kirov",
    "iso:country":"RU",
    "name:rus_x_preferred":[
        "\u041c\u044f\u0441\u043e\u0432\u0441\u043a\u0430\u044f"
    ],
    "wof:name":"Myasovskaya",
    "wof:placetype":"locality"
},
  "geometry": {"coordinates":[48.36221,60.38644],"type":"Point"}
}