{
  "type": "Feature",
  "properties": {
    "iso:country":"RU",
    "qs:name":"Valdayskiy Rayon",
    "qs:name_adm0":"Russia",
    "qs:name_adm1":"Novgorod Oblast",
    "qs:photos":34,
    "qs:photos_1k":7,
    "qs:photos_9k":1,
    "qs:photos_9r":2,
    "qs:photos_all":34,
    "qs:photos_sr":2,
    "qs:placetype":"Town",
    "qs:pop_sr":"0",
    "wof:name":"Valdayskiy Rayon",
    "wof:placetype":"locality"
},
  "geometry": {"coordinates":[33.339385,57.97789],"type":"Point"}
}