{
  "type": "Feature",
  "properties": {
    "gn:admin1_code":"85",
    "gn:asciiname":"Yuza",
    "gn:country_code":"RU",
    "gn:dem":153,
    "gn:feature_class":"P",
    "gn:feature_code":"PPL",
    "gn:name":"Yuza",
    "gn:population":0,
    "gn:timezone":"Europe/Moscow",
    "iso:country":"RU",
    "name:fas_x_preferred":[
        "\u06cc\u0648\u0632\u0627"
    ],
    "name:fra_x_preferred":[
        "Yuza"
    ],
    "name:ind_x_preferred":[
        "Yuza"
    ],
    "name:ita_x_preferred":[
        "Yuza"
    ],
    "name:jpn_x_preferred":[
        "\u904a\u4f50\u753a"
    ],
    "name:kor_x_preferred":[
        "\uc720\uc790\uc815"
    ],
    "name:msa_x_preferred":[
        "Yuza"
    ],
    "name:rus_x_preferred":[
        "\u042e\u0434\u0437\u0430"
    ],
    "name:spa_x_preferred":[
        "Yuza"
    ],
    "name:swe_x_preferred":[
        "Yuza"
    ],
    "name:tgl_x_preferred":[
        "Yuza"
    ],
    "name:ukr_x_preferred":[
        "\u042e\u0434\u0437\u0430"
    ],
    "name:urd_x_preferred":[
        "\u06cc\u0632\u0627"
    ],
    "name:zho_x_preferred":[
        "\u904a\u4f50\u753a"
    ],
    "wof:name":"Yuza",
    "wof:placetype":"locality"
},
  "geometry": {"coordinates":[43.11667,59.75],"type":"Point"}
}