{
  "type": "Feature",
  "properties": {
    "gn:admin1_code":"29",
    "gn:asciiname":"Krekovo",
    "gn:country_code":"RU",
    "gn:dem":121,
    "gn:feature_class":"P",
    "gn:feature_code":"PPL",
    "gn:name":"Krekovo",
    "gn:population":0,
    "gn:timezone":"Asia/Novokuznetsk",
    "iso:country":"RU",
    "name:rus_x_preferred":[
        "\u041a\u0440\u0435\u043a\u043e\u0432\u043e"
    ],
    "wof:name":"Krekovo",
    "wof:placetype":"locality"
},
  "geometry": {"coordinates":[85.87260000000001,55.5209],"type":"Point"}
}