{
  "type": "Feature",
  "properties": {
    "gn:admin1_code":"73",
    "gn:asciiname":"Spiridonovka",
    "gn:country_code":"RU",
    "gn:dem":119,
    "gn:feature_class":"P",
    "gn:feature_code":"PPL",
    "gn:name":"Spiridonovka",
    "gn:population":0,
    "gn:timezone":"Europe/Moscow",
    "iso:country":"RU",
    "name:eng_x_preferred":[
        "Spiridonovka"
    ],
    "name:nor_x_preferred":[
        "Spiridonovka"
    ],
    "name:rus_x_preferred":[
        "\u0421\u043f\u0438\u0440\u0438\u0434\u043e\u043d\u043e\u0432\u043a\u0430"
    ],
    "name:und_x_variant":[
        "\u0421\u043f\u0438\u0440\u0438\u0434\u043e\u043d\u043e\u0432\u043a\u0430",
        "Spiridonovka"
    ],
    "wof:name":"Spiridonovka",
    "wof:placetype":"locality"
},
  "geometry": {"coordinates":[52.06507,54.46264],"type":"Point"}
}