{
  "type": "Feature",
  "properties": {
    "gn:admin1_code":"33",
    "gn:asciiname":"Roslyakovo Ramen'ye",
    "gn:country_code":"RU",
    "gn:dem":100,
    "gn:feature_class":"P",
    "gn:feature_code":"PPL",
    "gn:name":"Roslyakovo Ramen\u2019ye",
    "gn:population":0,
    "gn:timezone":"Europe/Kirov",
    "iso:country":"RU",
    "name:rus_x_preferred":[
        "\u0420\u043e\u0441\u043b\u044f\u043a\u043e\u0432\u043e \u0420\u0430\u043c\u0435\u043d\u044c\u0435"
    ],
    "name:und_x_variant":[
        "Roslyakovo Ramen\u2019ye"
    ],
    "wof:name":"Roslyakovo Ramen'ye",
    "wof:placetype":"locality"
},
  "geometry": {"coordinates":[46.6653,60.1644],"type":"Point"}
}