{
  "type": "Feature",
  "properties": {
    "gn:admin1_code":"75",
    "gn:asciiname":"Mel'stroy",
    "gn:country_code":"RU",
    "gn:dem":97,
    "gn:feature_class":"P",
    "gn:feature_code":"PPL",
    "gn:name":"Mel\u2019stroy",
    "gn:population":0,
    "gn:timezone":"Asia/Tomsk",
    "iso:country":"RU",
    "name:rus_x_preferred":[
        "\u041c\u0435\u043b\u044c\u0441\u0442\u0440\u043e\u0439"
    ],
    "name:und_x_variant":[
        "Mel\u2019nikova",
        "Mel\u2019stroy",
        "\u041c\u0435\u043b\u044c\u0441\u0442\u0440\u043e\u0439"
    ],
    "wof:name":"Mel'stroy",
    "wof:placetype":"locality"
},
  "geometry": {"coordinates":[81.46666999999999,57.26667],"type":"Point"}
}