{
  "type": "Feature",
  "properties": {
    "gn:admin1_code":"61.0",
    "gn:asciiname":"Polyakov-Ivanovskiy",
    "gn:country_code":"RU",
    "gn:dem":92,
    "gn:feature_class":"P",
    "gn:feature_code":"PPL",
    "gn:name":"Polyakov-Ivanovskiy",
    "gn:population":0,
    "gn:timezone":"Europe/Moscow",
    "iso:country":"RU",
    "wof:name":"Polyakov-Ivanovskiy",
    "wof:placetype":"locality"
},
  "geometry": {"coordinates":[41.61667,48.82111],"type":"Point"}
}