{
  "type": "Feature",
  "properties": {
    "gn:admin1_code":"62",
    "gn:asciiname":"Yurasovo",
    "gn:country_code":"RU",
    "gn:dem":114,
    "gn:feature_class":"P",
    "gn:feature_code":"PPL",
    "gn:name":"Yurasovo",
    "gn:population":0,
    "gn:timezone":"Europe/Moscow",
    "iso:country":"RU",
    "name:rus_x_preferred":[
        "\u042e\u0440\u0430\u0441\u043e\u0432\u043e"
    ],
    "wof:name":"Yurasovo",
    "wof:placetype":"locality"
},
  "geometry": {"coordinates":[39.9647,54.5371],"type":"Point"}
}