{
  "type": "Feature",
  "properties": {
    "gn:admin1_code":"85",
    "gn:asciiname":"Sholomovo",
    "gn:country_code":"RU",
    "gn:dem":197,
    "gn:feature_class":"P",
    "gn:feature_code":"PPL",
    "gn:name":"Sholomovo",
    "gn:population":0,
    "gn:timezone":"Europe/Moscow",
    "iso:country":"RU",
    "name:eng_x_preferred":[
        "Shelomovo"
    ],
    "name:nor_x_preferred":[
        "Sjolomovo"
    ],
    "name:rus_x_preferred":[
        "\u0428\u043e\u043b\u043e\u043c\u043e\u0432\u043e"
    ],
    "name:und_x_variant":[
        "Islomovo",
        "Sholomovo"
    ],
    "wof:name":"Sholomovo",
    "wof:placetype":"locality"
},
  "geometry": {"coordinates":[39.33978,59.2383],"type":"Point"}
}