{
  "type": "Feature",
  "properties": {
    "gn:admin1_code":"56",
    "gn:asciiname":"Lysovka",
    "gn:country_code":"RU",
    "gn:dem":206,
    "gn:feature_class":"P",
    "gn:feature_code":"PPL",
    "gn:name":"Lysovka",
    "gn:population":0,
    "gn:timezone":"Europe/Moscow",
    "iso:country":"RU",
    "name:rus_x_preferred":[
        "\u041b\u044b\u0441\u043e\u0432\u043a\u0430"
    ],
    "wof:name":"Lysovka",
    "wof:placetype":"locality"
},
  "geometry": {"coordinates":[35.96143,52.75449],"type":"Point"}
}