{
  "type": "Feature",
  "properties": {
    "gn:admin1_code":"55",
    "gn:asciiname":"Novosovkhoznyy",
    "gn:country_code":"RU",
    "gn:dem":367,
    "gn:feature_class":"P",
    "gn:feature_code":"PPL",
    "gn:name":"Novosovkhoznyy",
    "gn:population":0,
    "gn:timezone":"Asia/Yekaterinburg",
    "iso:country":"RU",
    "name:rus_x_preferred":[
        "\u041d\u043e\u0432\u043e\u0441\u043e\u0432\u0445\u043e\u0437\u043d\u044b\u0439"
    ],
    "wof:name":"Novosovkhoznyy",
    "wof:placetype":"locality"
},
  "geometry": {"coordinates":[60.6044,51.3054],"type":"Point"}
}