{
  "type": "Feature",
  "properties": {
    "gn:admin1_code":"67",
    "gn:asciiname":"Slavyanka",
    "gn:country_code":"RU",
    "gn:dem":36,
    "gn:feature_class":"P",
    "gn:feature_code":"PPL",
    "gn:name":"Slavyanka",
    "gn:population":0,
    "gn:timezone":"Europe/Saratov",
    "iso:country":"RU",
    "name:ceb_x_preferred":[
        "Slavyanka"
    ],
    "name:deu_x_preferred":[
        "Slawjanka"
    ],
    "name:hye_x_preferred":[
        "\u054d\u056c\u0561\u057e\u0575\u0561\u0576\u056f\u0561"
    ],
    "name:jpn_x_preferred":[
        "\u30b9\u30e9\u30f4\u30e3\u30f3\u30ab"
    ],
    "name:kat_x_preferred":[
        "\u10e1\u10da\u10d0\u10d5\u10d8\u10d0\u10dc\u10d9\u10d0"
    ],
    "name:sco_x_preferred":[
        "Slavyanka"
    ],
    "name:swe_x_preferred":[
        "Slavyanka"
    ],
    "name:ukr_x_preferred":[
        "\u0421\u043b\u043e\u0432'\u044f\u043d\u043a\u0430"
    ],
    "name:und_x_variant":[
        "Brunnenfel\u2019d"
    ],
    "wof:name":"Slavyanka",
    "wof:placetype":"locality"
},
  "geometry": {"coordinates":[46.2492,51.84297],"type":"Point"}
}