{
  "type": "Feature",
  "properties": {
    "gn:admin1_code":"67",
    "gn:asciiname":"Slavyanka",
    "gn:country_code":"RU",
    "gn:dem":36,
    "gn:feature_class":"P",
    "gn:feature_code":"PPL",
    "gn:name":"Slavyanka",
    "gn:population":0,
    "gn:timezone":"Europe/Saratov",
    "iso:country":"RU",
    "name:und_x_variant":[
        "Brunnenfel\u2019d",
        "Slavyanka"
    ],
    "wof:name":"Slavyanka",
    "wof:placetype":"locality"
},
  "geometry": {"coordinates":[46.2492,51.84297],"type":"Point"}
}