{
  "type": "Feature",
  "properties": {
    "gn:admin1_code":"47.0",
    "gn:asciiname":"Glinki",
    "gn:country_code":"RU",
    "gn:dem":131,
    "gn:feature_class":"P",
    "gn:feature_code":"PPL",
    "gn:name":"Glinki",
    "gn:population":20,
    "gn:timezone":"Europe/Moscow",
    "iso:country":"RU",
    "name:rus_x_preferred":[
        "\u0413\u043b\u0438\u043d\u043a\u0438"
    ],
    "wof:name":"Glinki",
    "wof:placetype":"locality",
    "wof:population":20
},
  "geometry": {"coordinates":[37.52981,56.58624],"type":"Point"}
}