{
  "type": "Feature",
  "properties": {
    "gn:admin1_code":"60",
    "gn:asciiname":"Gunino",
    "gn:country_code":"RU",
    "gn:dem":68,
    "gn:feature_class":"P",
    "gn:feature_code":"PPL",
    "gn:name":"Gunino",
    "gn:population":0,
    "gn:timezone":"Europe/Moscow",
    "iso:country":"RU",
    "name:rus_x_preferred":[
        "\u0413\u0443\u043d\u0438\u043d\u043e"
    ],
    "wof:name":"Gunino",
    "wof:placetype":"locality"
},
  "geometry": {"coordinates":[28.25095,57.19459000000001],"type":"Point"}
}