{
  "type": "Feature",
  "properties": {
    "gn:admin1_code":"85",
    "gn:asciiname":"Lent'yevo",
    "gn:country_code":"RU",
    "gn:dem":113,
    "gn:feature_class":"P",
    "gn:feature_code":"PPL",
    "gn:name":"Lent\u2019yevo",
    "gn:population":0,
    "gn:timezone":"Europe/Moscow",
    "iso:country":"RU",
    "name:eng_x_preferred":[
        "Lent'yevo"
    ],
    "name:nor_x_preferred":[
        "Lentjevo"
    ],
    "name:rus_x_preferred":[
        "\u041b\u0435\u043d\u0442\u044c\u0435\u0432\u043e"
    ],
    "name:und_x_variant":[
        "Leont\u2019yevo",
        "Lentevo",
        "Lentovo",
        "Lent\u2019yevo"
    ],
    "wof:name":"Lent'yevo",
    "wof:placetype":"locality"
},
  "geometry": {"coordinates":[36.6028,58.9621],"type":"Point"}
}