{
  "type": "Feature",
  "properties": {
    "gn:admin1_code":"88.0",
    "gn:asciiname":"Alekseytsevo",
    "gn:country_code":"RU",
    "gn:dem":132,
    "gn:feature_class":"P",
    "gn:feature_code":"PPL",
    "gn:name":"Alekseytsevo",
    "gn:population":0,
    "gn:timezone":"Europe/Moscow",
    "iso:country":"RU",
    "name:nor_x_preferred":[
        "Aleksejtsevo"
    ],
    "name:rus_x_preferred":[
        "\u0410\u043b\u0435\u043a\u0441\u0435\u0439\u0446\u0435\u0432\u043e"
    ],
    "wof:name":"Alekseytsevo",
    "wof:placetype":"locality"
},
  "geometry": {"coordinates":[40.28689,58.08476999999999],"type":"Point"}
}