{
  "type": "Feature",
  "properties": {
    "gn:admin1_code":"62",
    "gn:asciiname":"Vysokiye Sechi",
    "gn:country_code":"RU",
    "gn:dem":89,
    "gn:feature_class":"P",
    "gn:feature_code":"PPL",
    "gn:name":"Vysokiye Sechi",
    "gn:population":0,
    "gn:timezone":"Europe/Moscow",
    "iso:country":"RU",
    "name:rus_x_preferred":[
        "\u0412\u044b\u0441\u043e\u043a\u0438\u0435 \u0421\u0435\u0447\u0438"
    ],
    "wof:name":"Vysokiye Sechi",
    "wof:placetype":"locality"
},
  "geometry": {"coordinates":[42.1514,54.5369],"type":"Point"}
}