{
  "type": "Feature",
  "properties": {
    "gn:admin1_code":"77",
    "gn:asciiname":"Spornoye",
    "gn:country_code":"RU",
    "gn:dem":202,
    "gn:feature_class":"P",
    "gn:feature_code":"PPL",
    "gn:name":"Spornoye",
    "gn:population":0,
    "gn:timezone":"Europe/Moscow",
    "iso:country":"RU",
    "name:rus_x_preferred":[
        "\u0421\u043f\u043e\u0440\u043d\u043e\u0435"
    ],
    "name:und_x_variant":[
        "\u0421\u043f\u043e\u0440\u043d\u043e\u0435"
    ],
    "wof:name":"Spornoye",
    "wof:placetype":"locality"
},
  "geometry": {"coordinates":[35.28333,58.33333],"type":"Point"}
}