{
  "type": "Feature",
  "properties": {
    "gn:admin1_code":"10",
    "gn:asciiname":"Sbrody",
    "gn:country_code":"RU",
    "gn:dem":185,
    "gn:feature_class":"P",
    "gn:feature_code":"PPL",
    "gn:name":"Sbrody",
    "gn:population":0,
    "gn:timezone":"Europe/Moscow",
    "iso:country":"RU",
    "name:rus_x_preferred":[
        "\u0421\u0431\u0440\u043e\u0434\u044b"
    ],
    "name:und_x_variant":[
        "\u0421\u0431\u0440\u043e\u0434\u044b"
    ],
    "wof:name":"Sbrody",
    "wof:placetype":"locality"
},
  "geometry": {"coordinates":[34.23667,53.43083000000001],"type":"Point"}
}