{
  "type": "Feature",
  "properties": {
    "gn:admin1_code":"71",
    "gn:asciiname":"Panteleyeva",
    "gn:country_code":"RU",
    "gn:dem":62,
    "gn:feature_class":"P",
    "gn:feature_code":"PPL",
    "gn:name":"Panteleyeva",
    "gn:population":0,
    "gn:timezone":"Asia/Yekaterinburg",
    "iso:country":"RU",
    "name:eng_x_preferred":[
        "Panteleyevo"
    ],
    "name:nor_x_preferred":[
        "Pantelejeva"
    ],
    "name:rus_x_preferred":[
        "\u041f\u0430\u043d\u0442\u0435\u043b\u0435\u0435\u0432\u0430"
    ],
    "name:und_x_variant":[
        "Panteleyeva"
    ],
    "wof:name":"Panteleyeva",
    "wof:placetype":"locality"
},
  "geometry": {"coordinates":[63.41059,59.32998000000001],"type":"Point"}
}