{
  "type": "Feature",
  "properties": {
    "gn:admin1_code":"7",
    "gn:asciiname":"Teplinka",
    "gn:country_code":"RU",
    "gn:dem":-18,
    "gn:feature_class":"P",
    "gn:feature_code":"PPL",
    "gn:name":"Teplinka",
    "gn:population":0,
    "gn:timezone":"Europe/Astrakhan",
    "iso:country":"RU",
    "name:rus_x_preferred":[
        "\u0422\u0435\u043f\u043b\u0438\u043d\u043a\u0430"
    ],
    "wof:name":"Teplinka",
    "wof:placetype":"locality"
},
  "geometry": {"coordinates":[48.52427,46.57738],"type":"Point"}
}