{
  "type": "Feature",
  "properties": {
    "gn:admin1_code":"17",
    "gn:asciiname":"Luguvalu",
    "gn:country_code":"RU",
    "gn:dem":-20,
    "gn:feature_class":"P",
    "gn:feature_code":"PPL",
    "gn:name":"Luguvalu",
    "gn:population":0,
    "gn:timezone":"Europe/Moscow",
    "iso:country":"RU",
    "name:rus_x_preferred":[
        "\u041b\u0443\u0433\u0443\u0432\u0430\u043b\u0443"
    ],
    "name:und_x_variant":[
        "\u041b\u0443\u0433\u0443\u0432\u0430\u043b\u0443"
    ],
    "wof:name":"Luguvalu",
    "wof:placetype":"locality"
},
  "geometry": {"coordinates":[47.28301,43.57456],"type":"Point"}
}