{
  "type": "Feature",
  "properties": {
    "gn:admin1_code":"51.0",
    "gn:asciiname":"Annekovo",
    "gn:country_code":"RU",
    "gn:dem":93,
    "gn:feature_class":"P",
    "gn:feature_code":"PPL",
    "gn:name":"Annekovo",
    "gn:population":0,
    "gn:timezone":"Europe/Moscow",
    "iso:country":"RU",
    "name:nor_x_preferred":[
        "Annekovo"
    ],
    "name:rus_x_preferred":[
        "\u0410\u043d\u043d\u0435\u043a\u043e\u0432\u043e"
    ],
    "wof:name":"Annekovo",
    "wof:placetype":"locality"
},
  "geometry": {"coordinates":[44.36667,55.48333],"type":"Point"}
}