{
  "type": "Feature",
  "properties": {
    "gn:admin1_code":"65.0",
    "gn:asciiname":"Zharenyy Bugor",
    "gn:country_code":"RU",
    "gn:dem":41,
    "gn:feature_class":"P",
    "gn:feature_code":"PPL",
    "gn:name":"Zharenyy Bugor",
    "gn:population":0,
    "gn:timezone":"Europe/Samara",
    "iso:country":"RU",
    "name:rus_x_preferred":[
        "\u0416\u0430\u0440\u0435\u043d\u044b\u0439 \u0411\u0443\u0433\u043e\u0440"
    ],
    "wof:name":"Zharenyy Bugor",
    "wof:placetype":"locality"
},
  "geometry": {"coordinates":[50.28101,53.5442],"type":"Point"}
}