{
  "type": "Feature",
  "properties": {
    "gn:admin1_code":"34",
    "gn:asciiname":"Sord",
    "gn:country_code":"RU",
    "gn:dem":148,
    "gn:feature_class":"P",
    "gn:feature_code":"PPL",
    "gn:name":"Sord",
    "gn:population":0,
    "gn:timezone":"Europe/Moscow",
    "iso:country":"RU",
    "name:rus_x_preferred":[
        "\u0421\u043e\u0440\u0434"
    ],
    "wof:name":"Sord",
    "wof:placetype":"locality"
},
  "geometry": {"coordinates":[49.4632,59.5432],"type":"Point"}
}