{
  "type": "Feature",
  "properties": {
    "gn:admin1_code":"76",
    "gn:asciiname":"Dubki",
    "gn:country_code":"RU",
    "gn:dem":214,
    "gn:feature_class":"P",
    "gn:feature_code":"PPL",
    "gn:name":"Dubki",
    "gn:population":0,
    "gn:timezone":"Europe/Moscow",
    "iso:country":"RU",
    "name:rus_x_preferred":[
        "\u0414\u0443\u0431\u043a\u0438"
    ],
    "wof:name":"Dubki",
    "wof:placetype":"locality"
},
  "geometry": {"coordinates":[38.1862,54.0037],"type":"Point"}
}