{
  "type": "Feature",
  "properties": {
    "gn:admin1_code":"52",
    "gn:asciiname":"Malyye Semeritsy",
    "gn:country_code":"RU",
    "gn:dem":141,
    "gn:feature_class":"P",
    "gn:feature_code":"PPL",
    "gn:name":"Malyye Semeritsy",
    "gn:population":0,
    "gn:timezone":"Europe/Moscow",
    "iso:country":"RU",
    "name:rus_x_preferred":[
        "\u041c\u0430\u043b\u044b\u0435 \u0421\u0435\u043c\u0435\u0440\u0438\u0446\u044b"
    ],
    "name:und_x_variant":[
        "\u041c\u0430\u043b\u044b\u0435 \u0421\u0435\u043c\u0435\u0440\u0438\u0446\u044b"
    ],
    "wof:name":"Malyye Semeritsy",
    "wof:placetype":"locality"
},
  "geometry": {"coordinates":[34.54809,58.14556999999999],"type":"Point"}
}