{
  "type": "Feature",
  "properties": {
    "gn:admin1_code":"69.0",
    "gn:asciiname":"Dosugovo",
    "gn:country_code":"RU",
    "gn:dem":201,
    "gn:feature_class":"P",
    "gn:feature_code":"PPL",
    "gn:name":"Dosugovo",
    "gn:population":0,
    "gn:timezone":"Europe/Moscow",
    "iso:country":"RU",
    "name:eng_x_preferred":[
        "Dosugovo"
    ],
    "name:nor_x_preferred":[
        "Dosugovo"
    ],
    "name:rus_x_preferred":[
        "\u0414\u043e\u0441\u0443\u0433\u043e\u0432\u043e"
    ],
    "wof:name":"Dosugovo",
    "wof:placetype":"locality"
},
  "geometry": {"coordinates":[31.70444,54.41802],"type":"Point"}
}