{
  "type": "Feature",
  "properties": {
    "gn:admin1_code":"42",
    "gn:asciiname":"Visnjovka",
    "gn:country_code":"RU",
    "gn:dem":18,
    "gn:feature_class":"P",
    "gn:feature_code":"PPL",
    "gn:name":"Vi\u0161njovka",
    "gn:population":0,
    "gn:timezone":"Europe/Moscow",
    "iso:country":"RU",
    "name:fin_x_preferred":[
        "P\u00e4llil\u00e4"
    ],
    "name:rus_x_preferred":[
        "\u041f\u044f\u043b\u043b\u0438\u043b\u044f"
    ],
    "name:und_x_variant":[
        "Pyallilya",
        "\u041f\u044f\u043b\u043b\u0438\u043b\u044f"
    ],
    "wof:name":"Visnjovka",
    "wof:placetype":"locality"
},
  "geometry": {"coordinates":[29.54945,60.52841],"type":"Point"}
}