{
  "type": "Feature",
  "properties": {
    "gn:country":"RU",
    "gn:fcode":"PPL",
    "gn:pop":1415,
    "iso:country":"RU",
    "name:ceb_x_preferred":[
        "Vidim"
    ],
    "name:eng_x_preferred":[
        "Vidim"
    ],
    "name:ita_x_preferred":[
        "Vidim"
    ],
    "name:nor_x_preferred":[
        "Vidim"
    ],
    "name:rus_x_preferred":[
        "\u0412\u0438\u0434\u0438\u043c"
    ],
    "name:swe_x_preferred":[
        "Vidim"
    ],
    "qs:name":"Vidim",
    "qs:photos_9r":0,
    "qs:photos_sr":0,
    "qs:pop_sr":"3",
    "wd:wordcount":27,
    "wof:name":"Vidim",
    "wof:placetype":"locality",
    "wof:population":1415
},
  "geometry": {"coordinates":[103.11060000000001,56.4088],"type":"Point"}
}