{
  "type": "Feature",
  "properties": {
    "gn:admin1_code":"85",
    "gn:asciiname":"Tupitsyno",
    "gn:country_code":"RU",
    "gn:dem":115,
    "gn:feature_class":"P",
    "gn:feature_code":"PPL",
    "gn:name":"Tupitsyno",
    "gn:population":0,
    "gn:timezone":"Europe/Moscow",
    "iso:country":"RU",
    "name:rus_x_preferred":[
        "\u0422\u0443\u043f\u0438\u0446\u044b\u043d\u043e"
    ],
    "wof:name":"Tupitsyno",
    "wof:placetype":"locality"
},
  "geometry": {"coordinates":[39.9448,59.5466],"type":"Point"}
}