{
  "type": "Feature",
  "properties": {
    "gn:admin1_code":"84.0",
    "gn:asciiname":"Davydovka",
    "gn:country_code":"RU",
    "gn:dem":139,
    "gn:feature_class":"P",
    "gn:feature_code":"PPL",
    "gn:name":"Davydovka",
    "gn:population":0,
    "gn:timezone":"Europe/Volgograd",
    "iso:country":"RU",
    "name:che_x_preferred":[
        "\u0414\u0430\u0432\u044b\u0434\u043e\u0432\u043a\u0430"
    ],
    "name:eng_x_preferred":[
        "Davydovka"
    ],
    "name:nor_x_preferred":[
        "Davydovka"
    ],
    "name:rus_x_preferred":[
        "\u0414\u0430\u0432\u044b\u0434\u043e\u0432\u043a\u0430"
    ],
    "name:und_x_variant":[
        "Dawydowka",
        "Davydovka"
    ],
    "wof:name":"Davydovka",
    "wof:placetype":"locality"
},
  "geometry": {"coordinates":[44.64367,49.29822],"type":"Point"}
}