{
  "type": "Feature",
  "properties": {
    "gn:admin1_code":"38",
    "gn:asciiname":"Novo-Kurchanskiy",
    "gn:cc2":"RU",
    "gn:country_code":"RU",
    "gn:dem":3,
    "gn:feature_class":"P",
    "gn:feature_code":"PPL",
    "gn:name":"Novo-Kurchanskiy",
    "gn:population":0,
    "gn:timezone":"Europe/Moscow",
    "iso:country":"RU",
    "name:rus_x_preferred":[
        "\u041d\u043e\u0432\u043e-\u041a\u0443\u0440\u0447\u0430\u043d\u0441\u043a\u0438\u0439"
    ],
    "name:und_x_variant":[
        "Novvy Kurchanskiy",
        "Novo-Kurchanskiy"
    ],
    "wof:name":"Novo-Kurchanskiy",
    "wof:placetype":"locality"
},
  "geometry": {"coordinates":[38.36667,45.97611],"type":"Point"}
}