{
  "type": "Feature",
  "properties": {
    "gn:admin1_code":"71",
    "gn:asciiname":"Zonal'nyy",
    "gn:country_code":"RU",
    "gn:dem":258,
    "gn:feature_class":"P",
    "gn:feature_code":"PPL",
    "gn:name":"Zonal\u2019nyy",
    "gn:population":0,
    "gn:timezone":"Asia/Yekaterinburg",
    "iso:country":"RU",
    "name:rus_x_preferred":[
        "\u0417\u043e\u043d\u0430\u043b\u044c\u043d\u044b\u0439"
    ],
    "name:und_x_variant":[
        "Zonal\u2019nyy",
        "Zonal\u2019naya"
    ],
    "wof:name":"Zonal'nyy",
    "wof:placetype":"locality"
},
  "geometry": {"coordinates":[60.11666999999999,57.88639000000001],"type":"Point"}
}