{
  "type": "Feature",
  "properties": {
    "gn:admin1_code":"33",
    "gn:asciiname":"Zherebtsovo",
    "gn:country_code":"RU",
    "gn:dem":196,
    "gn:feature_class":"P",
    "gn:feature_code":"PPL",
    "gn:name":"Zherebtsovo",
    "gn:population":0,
    "gn:timezone":"Europe/Kirov",
    "iso:country":"RU",
    "wof:name":"Zherebtsovo",
    "wof:placetype":"locality"
},
  "geometry": {"coordinates":[49.81833,58.87333],"type":"Point"}
}