{
  "type": "Feature",
  "properties": {
    "gn:admin1_code":"33",
    "gn:asciiname":"Malakhi",
    "gn:country_code":"RU",
    "gn:dem":143,
    "gn:feature_class":"P",
    "gn:feature_code":"PPL",
    "gn:name":"Malakhi",
    "gn:population":0,
    "gn:timezone":"Europe/Kirov",
    "iso:country":"RU",
    "name:eng_x_preferred":[
        "Malakhi"
    ],
    "name:nor_x_preferred":[
        "Malakhi"
    ],
    "name:rus_x_preferred":[
        "\u041c\u0430\u043b\u0430\u0445\u0438"
    ],
    "name:und_x_variant":[
        "\u041c\u0430\u043b\u0430\u0445\u0438",
        "Malakhi"
    ],
    "wof:name":"Malakhi",
    "wof:placetype":"locality"
},
  "geometry": {"coordinates":[51.55537,58.27045],"type":"Point"}
}