{
  "type": "Feature",
  "properties": {
    "gn:admin1_code":"20",
    "gn:asciiname":"Petrovo",
    "gn:cc2":"RU",
    "gn:country_code":"RU",
    "gn:dem":459,
    "gn:feature_class":"P",
    "gn:feature_code":"PPL",
    "gn:name":"Petrovo",
    "gn:population":0,
    "gn:timezone":"Asia/Irkutsk",
    "iso:country":"RU",
    "name:eng_x_preferred":[
        "Petrovo"
    ],
    "name:nor_x_preferred":[
        "Petrovo"
    ],
    "name:rus_x_preferred":[
        "\u041f\u0435\u0442\u0440\u043e\u0432\u043e"
    ],
    "name:und_x_variant":[
        "Petrovskoye",
        "\u041f\u0435\u0442\u0440\u043e\u0432\u043e",
        "Petrovo"
    ],
    "wof:name":"Petrovo",
    "wof:placetype":"locality"
},
  "geometry": {"coordinates":[105.22889000000001,54.49361],"type":"Point"}
}