{
  "type": "Feature",
  "properties": {
    "gn:admin1_code":"77",
    "gn:asciiname":"Maloye Sidel'nikovo",
    "gn:country_code":"RU",
    "gn:dem":147,
    "gn:feature_class":"P",
    "gn:feature_code":"PPL",
    "gn:name":"Maloye Sidel\u2019nikovo",
    "gn:population":0,
    "gn:timezone":"Europe/Moscow",
    "iso:country":"RU",
    "name:rus_x_preferred":[
        "\u041c\u0430\u043b\u043e\u0435 \u0421\u0438\u0434\u0435\u043b\u044c\u043d\u0438\u043a\u043e\u0432\u043e"
    ],
    "name:und_x_variant":[
        "Maloye Sidel\u2019nikovo",
        "\u041c\u0430\u043b\u043e\u0435 \u0421\u0438\u0434\u0435\u043b\u044c\u043d\u0438\u043a\u043e\u0432\u043e"
    ],
    "wof:name":"Maloye Sidel'nikovo",
    "wof:placetype":"locality"
},
  "geometry": {"coordinates":[36.7751,58.5036],"type":"Point"}
}