{
  "type": "Feature",
  "properties": {
    "gn:admin1_code":"43",
    "gn:asciiname":"Poselok Sakharnogo Zavoda",
    "gn:country_code":"RU",
    "gn:dem":141,
    "gn:feature_class":"P",
    "gn:feature_code":"PPL",
    "gn:name":"Pos\u00eblok Sakharnogo Zavoda",
    "gn:population":0,
    "gn:timezone":"Europe/Moscow",
    "iso:country":"RU",
    "name:rus_x_preferred":[
        "\u041f\u043e\u0441\u00eb\u043b\u043e\u043a \u0421\u0430\u0445\u0430\u0440\u043d\u043e\u0433\u043e \u0417\u0430\u0432\u043e\u0434\u0430"
    ],
    "name:und_x_variant":[
        "Pos\u00eblok Sakharnogo Zavoda"
    ],
    "wof:name":"Poselok Sakharnogo Zavoda",
    "wof:placetype":"locality"
},
  "geometry": {"coordinates":[39.0706,52.9123],"type":"Point"}
}