{
  "type": "Feature",
  "properties": {
    "gn:admin1_code":"40",
    "gn:asciiname":"Baraba",
    "gn:country_code":"RU",
    "gn:dem":106,
    "gn:feature_class":"P",
    "gn:feature_code":"PPL",
    "gn:name":"Baraba",
    "gn:population":0,
    "gn:timezone":"Asia/Yekaterinburg",
    "iso:country":"RU",
    "name:eng_x_preferred":[
        "Baraba"
    ],
    "name:nor_x_preferred":[
        "Baraba"
    ],
    "name:rus_x_preferred":[
        "\u0411\u0430\u0440\u0430\u0431\u0430"
    ],
    "name:und_x_variant":[
        "Barabinskoye",
        "\u0411\u0430\u0440\u0430\u0431\u0430",
        "Baraba"
    ],
    "wof:name":"Baraba",
    "wof:placetype":"locality"
},
  "geometry": {"coordinates":[63.14,55.95306],"type":"Point"}
}