{
  "type": "Feature",
  "properties": {
    "gn:admin1_code":"62",
    "gn:asciiname":"Shelkovaya",
    "gn:country_code":"RU",
    "gn:dem":96,
    "gn:feature_class":"P",
    "gn:feature_code":"PPL",
    "gn:name":"Sh\u00eblkovaya",
    "gn:population":0,
    "gn:timezone":"Europe/Moscow",
    "iso:country":"RU",
    "name:rus_x_preferred":[
        "\u0428\u0451\u043b\u043a\u043e\u0432\u0430\u044f"
    ],
    "name:und_x_variant":[
        "Sh\u00eblkovaya"
    ],
    "wof:name":"Shelkovaya",
    "wof:placetype":"locality"
},
  "geometry": {"coordinates":[40.2018,54.2256],"type":"Point"}
}