{
  "type": "Feature",
  "properties": {
    "gn:admin1_code":"33",
    "gn:asciiname":"Baimovo",
    "gn:country_code":"RU",
    "gn:dem":116,
    "gn:feature_class":"P",
    "gn:feature_code":"PPL",
    "gn:name":"Baimovo",
    "gn:population":0,
    "gn:timezone":"Europe/Kirov",
    "iso:country":"RU",
    "name:eng_x_preferred":[
        "Baimovo"
    ],
    "name:nor_x_preferred":[
        "Baimovo"
    ],
    "name:rus_x_preferred":[
        "\u0411\u0430\u0438\u043c\u043e\u0432\u043e"
    ],
    "name:und_x_variant":[
        "Baymovo",
        "\u0411\u0430\u0438\u043c\u043e\u0432\u043e",
        "Baimovo"
    ],
    "wof:name":"Baimovo",
    "wof:placetype":"locality"
},
  "geometry": {"coordinates":[50.1476,57.3133],"type":"Point"}
}