{
  "type": "Feature",
  "properties": {
    "gn:admin1_code":"40",
    "gn:asciiname":"Novyye Peski",
    "gn:country_code":"RU",
    "gn:dem":143,
    "gn:feature_class":"P",
    "gn:feature_code":"PPL",
    "gn:name":"Novyye Peski",
    "gn:population":0,
    "gn:timezone":"Asia/Yekaterinburg",
    "iso:country":"RU",
    "name:eng_x_preferred":[
        "Novyye Peski"
    ],
    "name:nor_x_preferred":[
        "Novopeski"
    ],
    "name:rus_x_preferred":[
        "\u041d\u043e\u0432\u043e\u043f\u0435\u0441\u043a\u0438"
    ],
    "name:rus_x_variant":[
        "\u041d\u043e\u0432\u044b\u0435 \u041f\u0435\u0441\u043a\u0438"
    ],
    "wof:name":"Novyye Peski",
    "wof:placetype":"locality"
},
  "geometry": {"coordinates":[63.90028,55.77861],"type":"Point"}
}