{
  "type": "Feature",
  "properties": {
    "gn:admin1_code":"33",
    "gn:asciiname":"Bushkovskaya",
    "gn:country_code":"RU",
    "gn:dem":102,
    "gn:feature_class":"P",
    "gn:feature_code":"PPL",
    "gn:name":"Bushkovskaya",
    "gn:population":0,
    "gn:timezone":"Europe/Kirov",
    "iso:country":"RU",
    "name:rus_x_preferred":[
        "\u0411\u0443\u0448\u043a\u043e\u0432\u0441\u043a\u0430\u044f"
    ],
    "wof:name":"Bushkovskaya",
    "wof:placetype":"locality"
},
  "geometry": {"coordinates":[48.05449,60.54958000000001],"type":"Point"}
}