{
  "type": "Feature",
  "properties": {
    "gn:admin1_code":"37",
    "gn:asciiname":"Vysokovka",
    "gn:country_code":"RU",
    "gn:dem":135,
    "gn:feature_class":"P",
    "gn:feature_code":"PPL",
    "gn:name":"Vysokovka",
    "gn:population":0,
    "gn:timezone":"Europe/Moscow",
    "iso:country":"RU",
    "name:rus_x_preferred":[
        "\u0412\u044b\u0441\u043e\u043a\u043e\u0432\u043a\u0430"
    ],
    "wof:name":"Vysokovka",
    "wof:placetype":"locality"
},
  "geometry": {"coordinates":[45.5613,58.4782],"type":"Point"}
}