{
  "type": "Feature",
  "properties": {
    "gn:admin1_code":"45",
    "gn:asciiname":"Alataykino",
    "gn:country_code":"RU",
    "gn:dem":94,
    "gn:feature_class":"P",
    "gn:feature_code":"PPL",
    "gn:name":"Alataykino",
    "gn:population":0,
    "gn:timezone":"Europe/Moscow",
    "iso:country":"RU",
    "name:rus_x_preferred":[
        "\u0410\u043b\u0430\u0442\u0430\u0439\u043a\u0438\u043d\u043e"
    ],
    "wof:name":"Alataykino",
    "wof:placetype":"locality"
},
  "geometry": {"coordinates":[46.9229,56.2695],"type":"Point"}
}