{
  "type": "Feature",
  "properties": {
    "gn:admin1_code":"77",
    "gn:asciiname":"Shablino",
    "gn:country_code":"RU",
    "gn:dem":133,
    "gn:feature_class":"P",
    "gn:feature_code":"PPL",
    "gn:name":"Shablino",
    "gn:population":0,
    "gn:timezone":"Europe/Moscow",
    "iso:country":"RU",
    "name:nor_x_preferred":[
        "Sjablino"
    ],
    "name:rus_x_preferred":[
        "\u0428\u0430\u0431\u043b\u0438\u043d\u043e"
    ],
    "wof:name":"Shablino",
    "wof:placetype":"locality"
},
  "geometry": {"coordinates":[35.89668,56.93184],"type":"Point"}
}