{
  "type": "Feature",
  "properties": {
    "gn:admin1_code":"9",
    "gn:asciiname":"Il'inka",
    "gn:country_code":"RU",
    "gn:dem":99,
    "gn:feature_class":"P",
    "gn:feature_code":"PPL",
    "gn:name":"Il\u2019inka",
    "gn:population":0,
    "gn:timezone":"Europe/Moscow",
    "iso:country":"RU",
    "name:eng_x_preferred":[
        "Il'inka"
    ],
    "name:nor_x_preferred":[
        "Ilinka"
    ],
    "name:rus_x_preferred":[
        "\u0418\u043b\u044c\u0438\u043d\u043a\u0430"
    ],
    "name:und_x_variant":[
        "Selo Il\u2019nskoe",
        "Il\u2019nskoe",
        "Il\u2019inka"
    ],
    "wof:name":"Il'inka",
    "wof:placetype":"locality"
},
  "geometry": {"coordinates":[38.5979,50.6402],"type":"Point"}
}