{
  "type": "Feature",
  "properties": {
    "gn:admin1_code":"77",
    "gn:asciiname":"Knyashchiny",
    "gn:country_code":"RU",
    "gn:dem":182,
    "gn:feature_class":"P",
    "gn:feature_code":"PPL",
    "gn:name":"Knyashchiny",
    "gn:population":0,
    "gn:timezone":"Europe/Moscow",
    "iso:country":"RU",
    "name:eng_x_preferred":[
        "Knyashchiny"
    ],
    "name:nor_x_preferred":[
        "Knjasjtsjiny"
    ],
    "name:rus_x_preferred":[
        "\u041a\u043d\u044f\u0449\u0438\u043d\u044b"
    ],
    "name:und_x_variant":[
        "\u041a\u043d\u044f\u0449\u0438\u043d\u044b",
        "Knyashchiny"
    ],
    "wof:name":"Knyashchiny",
    "wof:placetype":"locality"
},
  "geometry": {"coordinates":[34.58498,57.29834],"type":"Point"}
}