{
  "type": "Feature",
  "properties": {
    "gn:admin1_code":"20",
    "gn:asciiname":"Gorodok",
    "gn:country_code":"RU",
    "gn:dem":577,
    "gn:feature_class":"P",
    "gn:feature_code":"PPL",
    "gn:name":"Gorodok",
    "gn:population":0,
    "gn:timezone":"Asia/Irkutsk",
    "iso:country":"RU",
    "name:rus_x_preferred":[
        "\u0413\u043e\u0440\u043e\u0434\u043e\u043a"
    ],
    "name:und_x_variant":[
        "\u0413\u043e\u0440\u043e\u0434\u043e\u043a"
    ],
    "wof:name":"Gorodok",
    "wof:placetype":"locality"
},
  "geometry": {"coordinates":[100.45,53.91667],"type":"Point"}
}