{
  "type": "Feature",
  "properties": {
    "gn:admin1_code":"54",
    "gn:asciiname":"Kuskuny",
    "gn:country_code":"RU",
    "gn:dem":54,
    "gn:feature_class":"P",
    "gn:feature_code":"PPL",
    "gn:name":"Kuskuny",
    "gn:population":0,
    "gn:timezone":"Asia/Omsk",
    "iso:country":"RU",
    "name:rus_x_preferred":[
        "\u041a\u0443\u0441\u043a\u0443\u043d\u044b"
    ],
    "name:und_x_variant":[
        "\u041a\u0443\u0441\u043a\u0443\u043d\u044b"
    ],
    "wof:name":"Kuskuny",
    "wof:placetype":"locality"
},
  "geometry": {"coordinates":[72.456,57.5184],"type":"Point"}
}