{
  "type": "Feature",
  "properties": {
    "gn:admin1_code":"89",
    "gn:asciiname":"Ferganishki",
    "gn:country_code":"RU",
    "gn:dem":74,
    "gn:feature_class":"P",
    "gn:feature_code":"PPL",
    "gn:name":"Ferganishki",
    "gn:population":0,
    "gn:timezone":"Asia/Vladivostok",
    "iso:country":"RU",
    "name:rus_x_preferred":[
        "\u0424\u0435\u0440\u0433\u0430\u043d\u0438\u0448\u043a\u0438"
    ],
    "wof:name":"Ferganishki",
    "wof:placetype":"locality"
},
  "geometry": {"coordinates":[131.94999999999999,48.16667],"type":"Point"}
}