{
  "type": "Feature",
  "properties": {
    "gn:admin1_code":"93",
    "gn:asciiname":"Tutkhaltuy",
    "gn:country_code":"RU",
    "gn:dem":681,
    "gn:feature_class":"P",
    "gn:feature_code":"PPL",
    "gn:name":"Tutkhaltuy",
    "gn:population":0,
    "gn:timezone":"Asia/Chita",
    "iso:country":"RU",
    "name:eng_x_preferred":[
        "Tutkhaltuy"
    ],
    "name:nor_x_preferred":[
        "Tut-Khaltuj"
    ],
    "name:rus_x_preferred":[
        "\u0422\u0443\u0442-\u0425\u0430\u043b\u0442\u0443\u0439"
    ],
    "name:und_x_variant":[
        "Tutkhaltui",
        "Tutkhaltuy"
    ],
    "wof:name":"Tutkhaltuy",
    "wof:placetype":"locality"
},
  "geometry": {"coordinates":[114.1677,50.46071],"type":"Point"}
}