{
  "type": "Feature",
  "properties": {
    "gn:admin1_code":"47",
    "gn:asciiname":"Manyayevo",
    "gn:country_code":"RU",
    "gn:dem":176,
    "gn:feature_class":"P",
    "gn:feature_code":"PPL",
    "gn:name":"Manyayevo",
    "gn:population":0,
    "gn:timezone":"Europe/Moscow",
    "iso:country":"RU",
    "name:rus_x_preferred":[
        "\u041c\u0430\u043d\u044f\u0435\u0432\u043e"
    ],
    "name:und_x_variant":[
        "Minyayeva",
        "Manyayevo"
    ],
    "wof:name":"Manyayevo",
    "wof:placetype":"locality"
},
  "geometry": {"coordinates":[38.38902,55.15989],"type":"Point"}
}