{
  "type": "Feature",
  "properties": {
    "gn:admin1_code":"76",
    "gn:asciiname":"Lyamzino",
    "gn:country_code":"RU",
    "gn:dem":204,
    "gn:feature_class":"P",
    "gn:feature_code":"PPL",
    "gn:name":"Lyamzino",
    "gn:population":0,
    "gn:timezone":"Europe/Moscow",
    "iso:country":"RU",
    "name:rus_x_preferred":[
        "\u041b\u044f\u043c\u0437\u0438\u043d\u043e"
    ],
    "wof:name":"Lyamzino",
    "wof:placetype":"locality"
},
  "geometry": {"coordinates":[38.07045,54.36894],"type":"Point"}
}