{
  "type": "Feature",
  "properties": {
    "gn:admin1_code":"93",
    "gn:asciiname":"Nadezhdinskiy",
    "gn:country_code":"RU",
    "gn:dem":1236,
    "gn:feature_class":"P",
    "gn:feature_code":"PPL",
    "gn:name":"Nadezhdinskiy",
    "gn:population":0,
    "gn:timezone":"Asia/Chita",
    "iso:country":"RU",
    "name:rus_x_preferred":[
        "\u041d\u0430\u0434\u0435\u0436\u0434\u0438\u043d\u0441\u043a\u0438\u0439"
    ],
    "name:und_x_variant":[
        "\u041d\u0430\u0434\u0435\u0436\u0434\u0438\u043d\u0441\u043a\u0438\u0439"
    ],
    "wof:name":"Nadezhdinskiy",
    "wof:placetype":"locality"
},
  "geometry": {"coordinates":[111.90000000000001,49.96667],"type":"Point"}
}