{
  "type": "Feature",
  "properties": {
    "gn:admin1_code":"11",
    "gn:asciiname":"Veselyy",
    "gn:country_code":"RU",
    "gn:dem":1422,
    "gn:feature_class":"P",
    "gn:feature_code":"PPL",
    "gn:name":"Ves\u00eblyy",
    "gn:population":0,
    "gn:timezone":"Asia/Irkutsk",
    "iso:country":"RU",
    "wof:name":"Veselyy",
    "wof:placetype":"locality"
},
  "geometry": {"coordinates":[115.25,55.98333],"type":"Point"}
}