{
  "type": "Feature",
  "properties": {
    "gn:admin1_code":"72",
    "gn:asciiname":"Pavlovo-Titovo",
    "gn:country_code":"RU",
    "gn:dem":140,
    "gn:feature_class":"P",
    "gn:feature_code":"PPL",
    "gn:name":"Pavlovo-Titovo",
    "gn:population":0,
    "gn:timezone":"Europe/Moscow",
    "iso:country":"RU",
    "name:rus_x_preferred":[
        "\u041f\u0430\u0432\u043b\u043e\u0432\u043e-\u0422\u0438\u0442\u043e\u0432\u043e"
    ],
    "name:und_x_variant":[
        "Khvostovo",
        "Pavlovo-Titovo"
    ],
    "wof:name":"Pavlovo-Titovo",
    "wof:placetype":"locality"
},
  "geometry": {"coordinates":[40.7054,52.478],"type":"Point"}
}