{
  "type": "Feature",
  "properties": {
    "gn:admin1_code":"53",
    "gn:asciiname":"Tupitsino",
    "gn:cc2":"RU",
    "gn:country_code":"RU",
    "gn:dem":137,
    "gn:feature_class":"P",
    "gn:feature_code":"PPL",
    "gn:name":"Tupitsino",
    "gn:population":0,
    "gn:timezone":"Asia/Novosibirsk",
    "iso:country":"RU",
    "name:und_x_variant":[
        "Tupitsina",
        "Tupitsino"
    ],
    "wof:name":"Tupitsino",
    "wof:placetype":"locality"
},
  "geometry": {"coordinates":[80.73333000000002,54.81667],"type":"Point"}
}