{
  "type": "Feature",
  "properties": {
    "gn:admin1_code":"53",
    "gn:asciiname":"Uzen'kiy",
    "gn:country_code":"RU",
    "gn:dem":126,
    "gn:feature_class":"P",
    "gn:feature_code":"PPL",
    "gn:name":"Uzen\u2019kiy",
    "gn:population":0,
    "gn:timezone":"Asia/Novosibirsk",
    "iso:country":"RU",
    "wof:name":"Uzen'kiy",
    "wof:placetype":"locality"
},
  "geometry": {"coordinates":[78.61667,56.35],"type":"Point"}
}