{
  "type": "Feature",
  "properties": {
    "gn:admin1_code":"83.0",
    "gn:asciiname":"Lyubets",
    "gn:country_code":"RU",
    "gn:dem":110,
    "gn:feature_class":"P",
    "gn:feature_code":"PPL",
    "gn:name":"Lyubets",
    "gn:population":0,
    "gn:timezone":"Europe/Moscow",
    "iso:country":"RU",
    "name:rus_x_preferred":[
        "\u041b\u044e\u0431\u0435\u0446"
    ],
    "wof:name":"Lyubets",
    "wof:placetype":"locality"
},
  "geometry": {"coordinates":[41.20604,56.32955],"type":"Point"}
}