{
  "type": "Feature",
  "properties": {
    "gn:admin1_code":"42.0",
    "gn:admin2_code":"481965",
    "gn:asciiname":"Turovo",
    "gn:country_code":"RU",
    "gn:dem":43,
    "gn:feature_class":"P",
    "gn:feature_code":"PPL",
    "gn:name":"Turovo",
    "gn:population":0,
    "gn:timezone":"Europe/Moscow",
    "iso:country":"RU",
    "name:rus_x_preferred":[
        "\u0422\u0443\u0440\u043e\u0432\u043e"
    ],
    "wof:name":"Turovo",
    "wof:placetype":"locality"
},
  "geometry": {"coordinates":[30.79667,59.41167],"type":"Point"}
}