{
  "type": "Feature",
  "properties": {
    "gn:admin1_code":"69",
    "gn:asciiname":"Ozerensk",
    "gn:country_code":"RU",
    "gn:dem":216,
    "gn:feature_class":"P",
    "gn:feature_code":"PPL",
    "gn:name":"Ozerensk",
    "gn:population":0,
    "gn:timezone":"Europe/Moscow",
    "iso:country":"RU",
    "name:rus_x_preferred":[
        "\u041e\u0437\u0435\u0440\u0435\u043d\u0441\u043a"
    ],
    "name:und_x_variant":[
        "Ozerenok",
        "Ozerensk"
    ],
    "wof:name":"Ozerensk",
    "wof:placetype":"locality"
},
  "geometry": {"coordinates":[33.00336,54.52656999999999],"type":"Point"}
}