{
  "type": "Feature",
  "properties": {
    "gn:admin1_code":"37",
    "gn:asciiname":"Voznesenskoye",
    "gn:country_code":"RU",
    "gn:dem":201,
    "gn:feature_class":"P",
    "gn:feature_code":"PPL",
    "gn:name":"Voznesenskoye",
    "gn:population":0,
    "gn:timezone":"Europe/Moscow",
    "iso:country":"RU",
    "name:rus_x_preferred":[
        "\u0412\u043e\u0437\u043d\u0435\u0441\u0435\u043d\u0441\u043a\u043e\u0435"
    ],
    "name:und_x_variant":[
        "\u0412\u043e\u0437\u043d\u0435\u0441\u0435\u043d\u0441\u043a\u043e\u0435"
    ],
    "wof:name":"Voznesenskoye",
    "wof:placetype":"locality"
},
  "geometry": {"coordinates":[42.7678,58.8057],"type":"Point"}
}