{
  "type": "Feature",
  "properties": {
    "gn:admin1_code":"65",
    "gn:asciiname":"Mochazhinnyy",
    "gn:country_code":"RU",
    "gn:dem":103,
    "gn:feature_class":"P",
    "gn:feature_code":"PPL",
    "gn:name":"Mochazhinnyy",
    "gn:population":0,
    "gn:timezone":"Europe/Samara",
    "iso:country":"RU",
    "name:rus_x_preferred":[
        "\u041c\u043e\u0447\u0430\u0436\u0438\u043d\u043d\u044b\u0439"
    ],
    "name:und_x_variant":[
        "\u041c\u043e\u0447\u0430\u0436\u0438\u043d\u043d\u044b\u0439"
    ],
    "wof:name":"Mochazhinnyy",
    "wof:placetype":"locality"
},
  "geometry": {"coordinates":[50.18333,53.63333000000001],"type":"Point"}
}