{
  "type": "Feature",
  "properties": {
    "gn:admin1_code":"23",
    "gn:asciiname":"Osinovka",
    "gn:country_code":"RU",
    "gn:dem":14,
    "gn:feature_class":"P",
    "gn:feature_code":"PPL",
    "gn:name":"Osinovka",
    "gn:population":0,
    "gn:timezone":"Europe/Kaliningrad",
    "iso:country":"RU",
    "name:eng_x_preferred":[
        "Osinovka"
    ],
    "name:nor_x_preferred":[
        "Osinovka"
    ],
    "name:rus_x_preferred":[
        "\u041e\u0441\u0438\u043d\u043e\u0432\u043a\u0430"
    ],
    "name:und_x_variant":[
        "Stampelken",
        "\u041e\u0441\u0438\u043d\u043e\u0432\u043a\u0430",
        "Osinovka"
    ],
    "wof:name":"Osinovka",
    "wof:placetype":"locality"
},
  "geometry": {"coordinates":[20.97672,54.73284],"type":"Point"}
}