{
  "type": "Feature",
  "properties": {
    "gn:admin1_code":"73",
    "gn:asciiname":"Staryye Urgagary",
    "gn:country_code":"RU",
    "gn:dem":144,
    "gn:feature_class":"P",
    "gn:feature_code":"PPL",
    "gn:name":"Staryye Urgagary",
    "gn:population":0,
    "gn:timezone":"Europe/Moscow",
    "iso:country":"RU",
    "name:rus_x_preferred":[
        "\u0421\u0442\u0430\u0440\u044b\u0435 \u0423\u0440\u0433\u0430\u0433\u0430\u0440\u044b"
    ],
    "name:und_x_variant":[
        "\u0421\u0442\u0430\u0440\u044b\u0435 \u0423\u0440\u0433\u0430\u0433\u0430\u0440\u044b"
    ],
    "wof:name":"Staryye Urgagary",
    "wof:placetype":"locality"
},
  "geometry": {"coordinates":[50.0221,54.8917],"type":"Point"}
}