{
  "type": "Feature",
  "properties": {
    "gn:admin1_code":"8",
    "gn:asciiname":"Turkmenevo Pervoye",
    "gn:country_code":"RU",
    "gn:dem":397,
    "gn:feature_class":"P",
    "gn:feature_code":"PPL",
    "gn:name":"Turkmenevo Pervoye",
    "gn:population":0,
    "gn:timezone":"Asia/Yekaterinburg",
    "iso:country":"RU",
    "name:rus_x_preferred":[
        "\u0422\u0443\u0440\u043a\u043c\u0435\u043d\u0435\u0432\u043e \u041f\u0435\u0440\u0432\u043e\u0435"
    ],
    "wof:name":"Turkmenevo Pervoye",
    "wof:placetype":"locality"
},
  "geometry": {"coordinates":[58.52,52.8725],"type":"Point"}
}