{
  "type": "Feature",
  "properties": {
    "gn:admin1_code":"71.0",
    "gn:asciiname":"Aleksandrovskoye",
    "gn:country_code":"RU",
    "gn:dem":238,
    "gn:feature_class":"P",
    "gn:feature_code":"PPL",
    "gn:name":"Aleksandrovskoye",
    "gn:population":0,
    "gn:timezone":"Asia/Yekaterinburg",
    "iso:country":"RU",
    "name:eng_x_preferred":[
        "Aleksandrovskoye"
    ],
    "name:nor_x_preferred":[
        "Aleksandrovskoje"
    ],
    "name:rus_x_preferred":[
        "\u0410\u043b\u0435\u043a\u0441\u0430\u043d\u0434\u0440\u043e\u0432\u0441\u043a\u043e\u0435"
    ],
    "wof:name":"Aleksandrovskoye",
    "wof:placetype":"locality"
},
  "geometry": {"coordinates":[57.827,56.7132],"type":"Point"}
}