{
  "type": "Feature",
  "properties": {
    "gn:admin1_code":"69",
    "gn:asciiname":"Pozhar'",
    "gn:country_code":"RU",
    "gn:dem":189,
    "gn:feature_class":"P",
    "gn:feature_code":"PPL",
    "gn:name":"Pozhar\u2019",
    "gn:population":0,
    "gn:timezone":"Europe/Moscow",
    "iso:country":"RU",
    "name:rus_x_preferred":[
        "\u041f\u043e\u0436\u0430\u0440\u044c"
    ],
    "name:und_x_variant":[
        "Pozhar\u2019"
    ],
    "wof:name":"Pozhar'",
    "wof:placetype":"locality"
},
  "geometry": {"coordinates":[32.55722,53.66611],"type":"Point"}
}