{
  "type": "Feature",
  "properties": {
    "gn:admin1_code":"86",
    "gn:asciiname":"Varvarovka",
    "gn:country_code":"RU",
    "gn:dem":112,
    "gn:feature_class":"P",
    "gn:feature_code":"PPL",
    "gn:name":"Varvarovka",
    "gn:population":0,
    "gn:timezone":"Europe/Moscow",
    "iso:country":"RU",
    "name:rus_x_preferred":[
        "\u0412\u0430\u0432\u0430\u0440\u043e\u0432\u043a\u0430"
    ],
    "wof:name":"Varvarovka",
    "wof:placetype":"locality"
},
  "geometry": {"coordinates":[40.2251,50.2925],"type":"Point"}
}