{
  "type": "Feature",
  "properties": {
    "gn:admin1_code":"76",
    "gn:asciiname":"Proletarskaya Zvezda",
    "gn:country_code":"RU",
    "gn:dem":260,
    "gn:feature_class":"P",
    "gn:feature_code":"PPL",
    "gn:name":"Proletarskaya Zvezda",
    "gn:population":0,
    "gn:timezone":"Europe/Moscow",
    "iso:country":"RU",
    "name:und_x_variant":[
        "Zvezda",
        "Proletarskaya Zvezda"
    ],
    "wof:name":"Proletarskaya Zvezda",
    "wof:placetype":"locality"
},
  "geometry": {"coordinates":[36.77535,54.1248],"type":"Point"}
}