{
  "type": "Feature",
  "properties": {
    "gn:admin1_code":"10.0",
    "gn:asciiname":"Dobrun'",
    "gn:country_code":"RU",
    "gn:dem":160,
    "gn:feature_class":"P",
    "gn:feature_code":"PPL",
    "gn:name":"Dobrun\u2019",
    "gn:population":0,
    "gn:timezone":"Europe/Moscow",
    "iso:country":"RU",
    "name:rus_x_preferred":[
        "\u0414\u043e\u0431\u0440\u0443\u043d\u044c"
    ],
    "name:und_x_variant":[
        "Dobrun\u2019"
    ],
    "wof:name":"Dobrun'",
    "wof:placetype":"locality"
},
  "geometry": {"coordinates":[34.343,52.2804],"type":"Point"}
}