{
  "type": "Feature",
  "properties": {
    "gn:admin1_code":"88",
    "gn:asciiname":"Osinovitsy",
    "gn:country_code":"RU",
    "gn:dem":99,
    "gn:feature_class":"P",
    "gn:feature_code":"PPL",
    "gn:name":"Osinovitsy",
    "gn:population":0,
    "gn:timezone":"Europe/Moscow",
    "iso:country":"RU",
    "name:rus_x_preferred":[
        "\u041e\u0441\u0438\u043d\u043e\u0432\u0438\u0446\u044b"
    ],
    "wof:name":"Osinovitsy",
    "wof:placetype":"locality"
},
  "geometry": {"coordinates":[39.40718,57.31237],"type":"Point"}
}