{
  "type": "Feature",
  "properties": {
    "gn:admin1_code":"80",
    "gn:asciiname":"Gamy",
    "gn:country_code":"RU",
    "gn:dem":106,
    "gn:feature_class":"P",
    "gn:feature_code":"PPL",
    "gn:name":"Gamy",
    "gn:population":0,
    "gn:timezone":"Europe/Samara",
    "iso:country":"RU",
    "name:rus_x_preferred":[
        "\u0413\u0430\u043c\u044b"
    ],
    "name:und_x_variant":[
        "Katyshi-Gami",
        "Gamy",
        "\u0413\u0430\u043c\u044b"
    ],
    "wof:name":"Gamy",
    "wof:placetype":"locality"
},
  "geometry": {"coordinates":[53.81004,57.01473000000001],"type":"Point"}
}