{
  "type": "Feature",
  "properties": {
    "gn:admin1_code":"24.0",
    "gn:asciiname":"Barun",
    "gn:country_code":"RU",
    "gn:dem":5,
    "gn:feature_class":"P",
    "gn:feature_code":"PPL",
    "gn:name":"Barun",
    "gn:population":0,
    "gn:timezone":"Europe/Moscow",
    "iso:country":"RU",
    "name:ceb_x_preferred":[
        "Barun"
    ],
    "name:deu_x_preferred":[
        "Barun"
    ],
    "name:fra_x_preferred":[
        "Barun"
    ],
    "name:ita_x_preferred":[
        "Barun"
    ],
    "name:jpn_x_preferred":[
        "\u30d0\u30eb\u30f3"
    ],
    "name:nor_x_preferred":[
        "Barun"
    ],
    "name:rus_x_preferred":[
        "\u0411\u0430\u0440\u0443\u043d"
    ],
    "wof:name":"Barun",
    "wof:placetype":"locality"
},
  "geometry": {"coordinates":[45.755,47.66333],"type":"Point"}
}