{
  "type": "Feature",
  "properties": {
    "gn:admin1_code":"77",
    "gn:asciiname":"Myasnitsa",
    "gn:country_code":"RU",
    "gn:dem":234,
    "gn:feature_class":"P",
    "gn:feature_code":"PPL",
    "gn:name":"Myasnitsa",
    "gn:population":0,
    "gn:timezone":"Europe/Moscow",
    "iso:country":"RU",
    "name:rus_x_preferred":[
        "\u041c\u044f\u0441\u043d\u0438\u0446\u0430"
    ],
    "name:und_x_variant":[
        "\u041c\u044f\u0441\u043d\u0438\u0446\u0430"
    ],
    "wof:name":"Myasnitsa",
    "wof:placetype":"locality"
},
  "geometry": {"coordinates":[33.53332,56.22708000000001],"type":"Point"}
}