{
  "type": "Feature",
  "properties": {
    "gn:admin1_code":"90.0",
    "gn:asciiname":"Bol'shaya Zareka",
    "gn:country_code":"RU",
    "gn:dem":227,
    "gn:feature_class":"P",
    "gn:feature_code":"PPL",
    "gn:name":"Bol\u2019shaya Zareka",
    "gn:population":0,
    "gn:timezone":"Asia/Yekaterinburg",
    "iso:country":"RU",
    "name:rus_x_preferred":[
        "\u0411\u043e\u043b\u044c\u0448\u0430\u044f \u0417\u0430\u0440\u0435\u043a\u0430"
    ],
    "name:und_x_variant":[
        "Bol\u2019shaya Zareka"
    ],
    "wof:name":"Bol'shaya Zareka",
    "wof:placetype":"locality"
},
  "geometry": {"coordinates":[57.08333,57.78333000000001],"type":"Point"}
}