{
  "type": "Feature",
  "properties": {
    "gn:admin1_code":"65",
    "gn:asciiname":"Nikitinka",
    "gn:country_code":"RU",
    "gn:dem":125,
    "gn:feature_class":"P",
    "gn:feature_code":"PPL",
    "gn:name":"Nikitinka",
    "gn:population":0,
    "gn:timezone":"Europe/Samara",
    "iso:country":"RU",
    "name:eng_x_preferred":[
        "Nikitinka"
    ],
    "name:nor_x_preferred":[
        "Nikitinka"
    ],
    "name:rus_x_preferred":[
        "\u041d\u0438\u043a\u0438\u0442\u0438\u043d\u043a\u0430"
    ],
    "wof:name":"Nikitinka",
    "wof:placetype":"locality"
},
  "geometry": {"coordinates":[50.55649,53.93773],"type":"Point"}
}