{
  "type": "Feature",
  "properties": {
    "gn:country":"RU",
    "gn:fcode":"PPL",
    "gn:pop":150,
    "iso:country":"RU",
    "name:eng_x_preferred":[
        "Velikoretskoye"
    ],
    "name:nor_x_preferred":[
        "Velikoretskoje"
    ],
    "name:rus_x_preferred":[
        "\u0412\u0435\u043b\u0438\u043a\u043e\u0440\u0435\u0446\u043a\u043e\u0435"
    ],
    "qs:name":"Velikoretskoye",
    "qs:name_adm0":"Russia",
    "qs:name_adm1":"Kirov Oblast",
    "qs:photos_9k":1,
    "qs:photos_9r":1,
    "qs:photos_all":23,
    "qs:photos_sr":0,
    "qs:placetype":"Town",
    "qs:pop_sr":"1",
    "wof:name":"Velikoretskoye",
    "wof:placetype":"locality",
    "wof:population":150
},
  "geometry": {"coordinates":[49.05044,58.89479],"type":"Point"}
}