{
  "type": "Feature",
  "properties": {
    "gn:admin1_code":"69",
    "gn:asciiname":"Liptsy",
    "gn:country_code":"RU",
    "gn:dem":186,
    "gn:feature_class":"P",
    "gn:feature_code":"PPL",
    "gn:name":"Liptsy",
    "gn:population":0,
    "gn:timezone":"Europe/Moscow",
    "iso:country":"RU",
    "name:rus_x_preferred":[
        "\u041b\u0438\u043f\u0446\u044b"
    ],
    "name:und_x_variant":[
        "Lipetsy",
        "Liptsy"
    ],
    "wof:name":"Liptsy",
    "wof:placetype":"locality"
},
  "geometry": {"coordinates":[34.85787,55.73716],"type":"Point"}
}