{
  "type": "Feature",
  "properties": {
    "gn:admin1_code":"51",
    "gn:asciiname":"Petryayevo",
    "gn:country_code":"RU",
    "gn:dem":123,
    "gn:feature_class":"P",
    "gn:feature_code":"PPL",
    "gn:name":"Petryayevo",
    "gn:population":0,
    "gn:timezone":"Europe/Moscow",
    "iso:country":"RU",
    "name:rus_x_preferred":[
        "\u041f\u0435\u0442\u0440\u044f\u0435\u0432\u043e"
    ],
    "wof:name":"Petryayevo",
    "wof:placetype":"locality"
},
  "geometry": {"coordinates":[45.78019000000001,57.67359],"type":"Point"}
}