{
  "type": "Feature",
  "properties": {
    "gn:admin1_code":"86.0",
    "gn:asciiname":"Pereshchepnoy",
    "gn:country_code":"RU",
    "gn:dem":137,
    "gn:feature_class":"P",
    "gn:feature_code":"PPL",
    "gn:name":"Pereshchepnoy",
    "gn:population":0,
    "gn:timezone":"Europe/Moscow",
    "iso:country":"RU",
    "name:rus_x_preferred":[
        "\u041f\u0435\u0440\u0435\u0449\u0435\u043f\u043d\u043e\u0439"
    ],
    "wof:name":"Pereshchepnoy",
    "wof:placetype":"locality"
},
  "geometry": {"coordinates":[39.56284,50.0285],"type":"Point"}
}