{
  "type": "Feature",
  "properties": {
    "gn:admin1_code":"90",
    "gn:asciiname":"Gorodishche",
    "gn:country_code":"RU",
    "gn:dem":126,
    "gn:feature_class":"P",
    "gn:feature_code":"PPL",
    "gn:name":"Gorodishche",
    "gn:population":0,
    "gn:timezone":"Asia/Yekaterinburg",
    "iso:country":"RU",
    "name:ceb_x_preferred":[
        "Gorodishche"
    ],
    "name:rus_x_preferred":[
        "\u0413\u043e\u0440\u043e\u0434\u0438\u0449\u0435"
    ],
    "name:tgl_x_preferred":[
        "Gorodishche"
    ],
    "name:und_x_variant":[
        "\u0413\u043e\u0440\u043e\u0434\u0438\u0449\u0435"
    ],
    "name:zho_x_preferred":[
        "\u6208\u7f85\u5b63\u8b1d"
    ],
    "wof:name":"Gorodishche",
    "wof:placetype":"locality"
},
  "geometry": {"coordinates":[55.7574,58.9601],"type":"Point"}
}