{
  "type": "Feature",
  "properties": {
    "gn:admin1_code":"9.0",
    "gn:asciiname":"Shapori",
    "gn:country_code":"RU",
    "gn:dem":173,
    "gn:feature_class":"P",
    "gn:feature_code":"PPL",
    "gn:name":"Shapori",
    "gn:population":0,
    "gn:timezone":"Europe/Moscow",
    "iso:country":"RU",
    "name:und_x_variant":[
        "Shapari",
        "Shapori"
    ],
    "wof:name":"Shapori",
    "wof:placetype":"locality"
},
  "geometry": {"coordinates":[36.17948,50.53289],"type":"Point"}
}