{
  "type": "Feature",
  "properties": {
    "gn:admin1_code":"8",
    "gn:asciiname":"Takmakkaran",
    "gn:country_code":"RU",
    "gn:dem":240,
    "gn:feature_class":"P",
    "gn:feature_code":"PPL",
    "gn:name":"Takmakkaran",
    "gn:population":0,
    "gn:timezone":"Asia/Yekaterinburg",
    "iso:country":"RU",
    "name:bak_x_preferred":[
        "\u0422\u0443\u04a1\u043c\u0430\u04a1\u04a1\u0430\u0440\u0430\u043d"
    ],
    "name:che_x_preferred":[
        "\u0422\u0430\u043a\u043c\u0430\u043a\u043a\u0430\u0440\u0430\u043d"
    ],
    "name:chv_x_preferred":[
        "\u0422\u0430\u043a\u043c\u0430\u043a\u043a\u0430\u0440\u0430\u043d"
    ],
    "name:hye_x_preferred":[
        "\u054f\u0561\u056f\u0574\u0561\u056f\u0561\u0580\u0561\u0576"
    ],
    "name:kaz_x_preferred":[
        "\u0422\u0430\u043a\u043c\u0430\u043a\u043a\u0430\u0440\u0430\u043d"
    ],
    "name:kir_x_preferred":[
        "\u0422\u0430\u043a\u043c\u0430\u043a\u043a\u0430\u0440\u0430\u043d"
    ],
    "name:rus_x_preferred":[
        "\u0422\u0430\u043a\u043c\u0430\u043a\u043a\u0430\u0440\u0430\u043d"
    ],
    "name:tat_x_preferred":[
        "\u0422\u0443\u043a\u043c\u0430\u043a\u043a\u0430\u0440\u0430\u043d"
    ],
    "name:ukr_x_preferred":[
        "\u0422\u0430\u043a\u043c\u0430\u043a\u043a\u0430\u0440\u0430\u043d"
    ],
    "wof:name":"Takmakkaran",
    "wof:placetype":"locality"
},
  "geometry": {"coordinates":[54.0373,53.6413],"type":"Point"}
}