{
  "type": "Feature",
  "properties": {
    "gn:admin1_code":"88",
    "gn:asciiname":"Dubrovy",
    "gn:country_code":"RU",
    "gn:dem":124,
    "gn:feature_class":"P",
    "gn:feature_code":"PPL",
    "gn:name":"Dubrovy",
    "gn:population":0,
    "gn:timezone":"Europe/Moscow",
    "iso:country":"RU",
    "name:rus_x_preferred":[
        "\u0414\u0443\u0431\u0440\u043e\u0432\u044b"
    ],
    "name:und_x_variant":[
        "\u0414\u0443\u0431\u0440\u043e\u0432\u044b"
    ],
    "wof:name":"Dubrovy",
    "wof:placetype":"locality"
},
  "geometry": {"coordinates":[38.2309,57.837],"type":"Point"}
}