{
  "type": "Feature",
  "properties": {
    "gn:admin1_code":"47",
    "gn:asciiname":"Shokhovo",
    "gn:country_code":"RU",
    "gn:dem":202,
    "gn:feature_class":"P",
    "gn:feature_code":"PPL",
    "gn:name":"Shokhovo",
    "gn:population":0,
    "gn:timezone":"Europe/Moscow",
    "iso:country":"RU",
    "name:rus_x_preferred":[
        "\u0428\u043e\u0445\u043e\u0432\u043e"
    ],
    "wof:name":"Shokhovo",
    "wof:placetype":"locality"
},
  "geometry": {"coordinates":[35.72417,55.29778],"type":"Point"}
}