{
  "type": "Feature",
  "properties": {
    "gn:admin1_code":"33",
    "gn:asciiname":"Piksur",
    "gn:country_code":"RU",
    "gn:dem":154,
    "gn:feature_class":"P",
    "gn:feature_code":"PPL",
    "gn:name":"Piksur",
    "gn:population":0,
    "gn:timezone":"Europe/Kirov",
    "iso:country":"RU",
    "name:eng_x_preferred":[
        "Piksur"
    ],
    "name:nor_x_preferred":[
        "Piksur"
    ],
    "name:rus_x_preferred":[
        "\u041f\u0438\u043a\u0441\u0443\u0440"
    ],
    "wof:name":"Piksur",
    "wof:placetype":"locality"
},
  "geometry": {"coordinates":[47.99451,58.91125],"type":"Point"}
}