{
  "type": "Feature",
  "properties": {
    "gn:admin1_code":"88",
    "gn:asciiname":"Inarevo",
    "gn:country_code":"RU",
    "gn:dem":122,
    "gn:feature_class":"P",
    "gn:feature_code":"PPL",
    "gn:name":"Inar\u00ebvo",
    "gn:population":0,
    "gn:timezone":"Europe/Moscow",
    "iso:country":"RU",
    "name:rus_x_preferred":[
        "\u0418\u043d\u0430\u0440\u0451\u0432\u043e"
    ],
    "name:und_x_variant":[
        "Inar\u00ebvo"
    ],
    "wof:name":"Inarevo",
    "wof:placetype":"locality"
},
  "geometry": {"coordinates":[38.0782,57.4167],"type":"Point"}
}