{
  "type": "Feature",
  "properties": {
    "gn:admin1_code":"62",
    "gn:asciiname":"Pribrezhnyy",
    "gn:country_code":"RU",
    "gn:dem":97,
    "gn:feature_class":"P",
    "gn:feature_code":"PPL",
    "gn:name":"Pribrezhnyy",
    "gn:population":0,
    "gn:timezone":"Europe/Moscow",
    "iso:country":"RU",
    "name:rus_x_preferred":[
        "\u041f\u0440\u0438\u0431\u0440\u0435\u0436\u043d\u044b\u0439"
    ],
    "wof:name":"Pribrezhnyy",
    "wof:placetype":"locality"
},
  "geometry": {"coordinates":[40.912,54.3519],"type":"Point"}
}