{
  "type": "Feature",
  "properties": {
    "gn:admin1_code":"05",
    "gn:asciiname":"Molchanovo",
    "gn:country_code":"RU",
    "gn:dem":152,
    "gn:feature_class":"P",
    "gn:feature_code":"PPL",
    "gn:name":"Molchanovo",
    "gn:population":0,
    "gn:timezone":"Asia/Yakutsk",
    "iso:country":"RU",
    "name:eng_x_preferred":[
        "Molchanovo"
    ],
    "name:nor_x_preferred":[
        "Moltsjanovo"
    ],
    "name:rus_x_preferred":[
        "\u041c\u043e\u043b\u0447\u0430\u043d\u043e\u0432\u043e"
    ],
    "wof:name":"Molchanovo",
    "wof:placetype":"locality"
},
  "geometry": {"coordinates":[128.35984999999999,51.38173],"type":"Point"}
}