{
  "type": "Feature",
  "properties": {
    "gn:admin1_code":"73.0",
    "gn:asciiname":"Nizhniy Bikmet",
    "gn:country_code":"RU",
    "gn:dem":179,
    "gn:feature_class":"P",
    "gn:feature_code":"PPL",
    "gn:name":"Nizhniy Bikmet",
    "gn:population":0,
    "gn:timezone":"Europe/Moscow",
    "iso:country":"RU",
    "name:rus_x_preferred":[
        "\u041d\u0438\u0436\u043d\u0438\u0439 \u0411\u0438\u043a\u043c\u0435\u0442"
    ],
    "name:und_x_variant":[
        "Dragun Bikmet\u2019yevo",
        "Nizhniy Bikmet",
        "\u041d\u0438\u0436\u043d\u0438\u0439 \u0411\u0438\u043a\u043c\u0435\u0442"
    ],
    "wof:name":"Nizhniy Bikmet",
    "wof:placetype":"locality"
},
  "geometry": {"coordinates":[52.7357,55.3044],"type":"Point"}
}