{
  "type": "Feature",
  "properties": {
    "gn:admin1_code":"53",
    "gn:asciiname":"Drazhny-Tayly",
    "gn:country_code":"RU",
    "gn:dem":345,
    "gn:feature_class":"P",
    "gn:feature_code":"PPL",
    "gn:name":"Drazhny-Tayly",
    "gn:population":0,
    "gn:timezone":"Asia/Novosibirsk",
    "iso:country":"RU",
    "name:eng_x_preferred":[
        "Drazhny-Tayly"
    ],
    "name:nor_x_preferred":[
        "Drazjny-Tajly"
    ],
    "name:rus_x_preferred":[
        "\u0414\u0440\u0430\u0436\u043d\u044b-\u0422\u0430\u0439\u043b\u044b"
    ],
    "name:und_x_variant":[
        "\u0414\u0440\u0430\u0436\u043d\u044b-\u0422\u0430\u0439\u043b\u044b",
        "Drazhny-Tayly"
    ],
    "wof:name":"Drazhny-Tayly",
    "wof:placetype":"locality"
},
  "geometry": {"coordinates":[84.71666999999999,54.56667],"type":"Point"}
}