{
  "type": "Feature",
  "properties": {
    "gn:admin1_code":"33.0",
    "gn:asciiname":"Maloye Demino",
    "gn:country_code":"RU",
    "gn:dem":125,
    "gn:feature_class":"P",
    "gn:feature_code":"PPL",
    "gn:name":"Maloye D\u00ebmino",
    "gn:population":0,
    "gn:timezone":"Europe/Kirov",
    "iso:country":"RU",
    "name:rus_x_preferred":[
        "\u041c\u0430\u043b\u043e\u0435 \u0414\u0451\u043c\u0438\u043d\u043e"
    ],
    "name:und_x_variant":[
        "Maloye D\u00ebmino"
    ],
    "wof:name":"Maloye Demino",
    "wof:placetype":"locality"
},
  "geometry": {"coordinates":[48.81187,57.79245],"type":"Point"}
}