{
  "type": "Feature",
  "properties": {
    "gn:admin1_code":"25",
    "gn:asciiname":"Kos'movo",
    "gn:country_code":"RU",
    "gn:dem":170,
    "gn:feature_class":"P",
    "gn:feature_code":"PPL",
    "gn:name":"\u041a\u043e\u0441\u044c\u043c\u043e\u0432\u043e",
    "gn:population":0,
    "gn:timezone":"Europe/Moscow",
    "iso:country":"RU",
    "name:rus_x_preferred":[
        "\u041a\u043e\u0441\u044c\u043c\u043e\u0432\u043e"
    ],
    "name:und_x_variant":[
        "\u041a\u043e\u0441\u044c\u043c\u043e\u0432\u043e",
        "Kos\u2019movo"
    ],
    "wof:name":"Kos'movo",
    "wof:placetype":"locality"
},
  "geometry": {"coordinates":[35.45517,54.85259],"type":"Point"}
}