{
  "type": "Feature",
  "properties": {
    "gn:admin1_code":"12.0",
    "gn:asciiname":"Khalkin",
    "gn:country_code":"RU",
    "gn:dem":713,
    "gn:feature_class":"P",
    "gn:feature_code":"PPL",
    "gn:name":"Khalkin",
    "gn:population":0,
    "gn:timezone":"Europe/Moscow",
    "iso:country":"RU",
    "name:rus_x_preferred":[
        "\u0425\u0430\u043b\u043a\u0438\u043d"
    ],
    "wof:name":"Khalkin",
    "wof:placetype":"locality"
},
  "geometry": {"coordinates":[45.65028,42.85639000000001],"type":"Point"}
}