{
  "type": "Feature",
  "properties": {
    "gn:country":"RU",
    "gn:fcode":"ADM3",
    "gn:pop":0,
    "iso:country":"RU",
    "name:rus_x_preferred":[
        "\u0410\u043b\u0435\u043a\u0441\u0430\u0301\u043d\u0434\u0440\u043e\u0432\u0441\u043a\u0438\u0439 \u0440\u0430\u0439\u043e\u0301\u043d"
    ],
    "name:unk_x_variant":[
        "Alexandrovsky"
    ],
    "qs:name":"Aleksandrovskiy Rayon",
    "qs:photos_9r":0,
    "qs:photos_sr":0,
    "qs:pop_sr":"0",
    "wof:name":"Aleksandrovskiy Rayon",
    "wof:placetype":"localadmin",
    "wof:population":0
},
  "geometry": {"coordinates":[54.33333,52.75],"type":"Point"}
}