{
  "type": "Feature",
  "properties": {
    "iso:country":"RU",
    "name:rus_x_preferred":[
        "\u0421\u043e\u0441\u043d\u043e\u0432\u0441\u043a\u043e\u0435"
    ],
    "wof:name":"Sosnovskoye",
    "wof:placetype":"neighbourhood"
},
  "geometry": {"coordinates":[30.34526198496483,60.03252193259994],"type":"Point"}
}