{
  "type": "Feature",
  "properties": {
    "gn:admin1_code":"30",
    "gn:asciiname":"Kal'ma",
    "gn:country_code":"RU",
    "gn:dem":10,
    "gn:feature_class":"P",
    "gn:feature_code":"PPL",
    "gn:name":"Kal\u2019ma",
    "gn:population":0,
    "gn:timezone":"Asia/Vladivostok",
    "iso:country":"RU",
    "name:eng_x_preferred":[
        "Kal'ma"
    ],
    "name:nor_x_preferred":[
        "Kalma"
    ],
    "name:rus_x_preferred":[
        "\u041a\u0430\u043b\u044c\u043c\u0430"
    ],
    "name:und_x_variant":[
        "Karima",
        "Kal\u2019ma"
    ],
    "wof:name":"Kal'ma",
    "wof:placetype":"locality"
},
  "geometry": {"coordinates":[139.73582999999999,52.97083000000001],"type":"Point"}
}