{
  "type": "Feature",
  "properties": {
    "gn:admin1_code":"86",
    "gn:asciiname":"Ol'khov Log",
    "gn:country_code":"RU",
    "gn:dem":129,
    "gn:feature_class":"P",
    "gn:feature_code":"PPL",
    "gn:name":"Ol\u2019khov Log",
    "gn:population":0,
    "gn:timezone":"Europe/Moscow",
    "iso:country":"RU",
    "name:rus_x_preferred":[
        "\u041e\u043b\u044c\u0445\u043e\u0432 \u041b\u043e\u0433"
    ],
    "name:und_x_variant":[
        "Ol\u2019khov Log"
    ],
    "wof:name":"Ol'khov Log",
    "wof:placetype":"locality"
},
  "geometry": {"coordinates":[39.26246,50.56909],"type":"Point"}
}