{
  "type": "Feature",
  "properties": {
    "gn:admin1_code":"84",
    "gn:asciiname":"Tunin",
    "gn:country_code":"RU",
    "gn:dem":5,
    "gn:feature_class":"P",
    "gn:feature_code":"PPL",
    "gn:name":"Tunin",
    "gn:population":0,
    "gn:timezone":"Europe/Volgograd",
    "iso:country":"RU",
    "name:rus_x_preferred":[
        "\u0422\u0443\u043d\u0438\u043d"
    ],
    "wof:name":"Tunin",
    "wof:placetype":"locality"
},
  "geometry": {"coordinates":[45.68159,48.65066],"type":"Point"}
}