{
  "type": "Feature",
  "properties": {
    "gn:admin1_code":"63",
    "gn:asciiname":"Khotogor",
    "gn:country_code":"RU",
    "gn:dem":199,
    "gn:feature_class":"P",
    "gn:feature_code":"PPL",
    "gn:name":"Khotogor",
    "gn:population":0,
    "gn:timezone":"Asia/Yakutsk",
    "iso:country":"RU",
    "name:rus_x_preferred":[
        "\u0425\u043e\u0442\u043e\u0433\u043e\u0440"
    ],
    "name:und_x_variant":[
        "\u0425\u043e\u0442\u043e\u0433\u043e\u0440"
    ],
    "wof:name":"Khotogor",
    "wof:placetype":"locality"
},
  "geometry": {"coordinates":[132.94999999999999,68.73333000000001],"type":"Point"}
}