{
  "type": "Feature",
  "properties": {
    "gn:country":"RU",
    "gn:fcode":"PPL",
    "gn:population":0,
    "iso:country":"RU",
    "name:eng_x_preferred":[
        "Gruzinskaya Mamayka"
    ],
    "name:nor_x_preferred":[
        "Mamajka"
    ],
    "name:rus_x_preferred":[
        "\u041c\u0430\u043c\u0430\u0439\u043a\u0430"
    ],
    "name:rus_x_variant":[
        "\u0413\u0440\u0443\u0437\u0438\u043d\u0441\u043a\u0430\u044f \u041c\u0430\u043c\u0430\u0439\u043a\u0430"
    ],
    "name:und_x_variant":[
        "Mamayka"
    ],
    "qs:name":"Gruzinskaya Mamayka",
    "qs:name_adm0":"Russia",
    "qs:name_adm1":"Krasnodar Krai",
    "qs:photos_9k":1,
    "qs:photos_9r":1,
    "qs:photos_all":3,
    "qs:photos_sr":0,
    "qs:placetype":"Town",
    "qs:pop_sr":"0",
    "wof:name":"Gruzinskaya Mamayka",
    "wof:placetype":"locality",
    "wof:population":0
},
  "geometry": {"coordinates":[39.69912,43.62988],"type":"Point"}
}