{
  "type": "Feature",
  "properties": {
    "gn:admin1_code":"51",
    "gn:asciiname":"Lesunovo",
    "gn:country_code":"RU",
    "gn:dem":129,
    "gn:feature_class":"P",
    "gn:feature_code":"PPL",
    "gn:name":"Lesunovo",
    "gn:population":0,
    "gn:timezone":"Europe/Moscow",
    "iso:country":"RU",
    "name:eng_x_preferred":[
        "Lesunovo"
    ],
    "name:nor_x_preferred":[
        "Lesunovo"
    ],
    "name:rus_x_preferred":[
        "\u041b\u0435\u0441\u0443\u043d\u043e\u0432\u043e"
    ],
    "name:und_x_variant":[
        "\u041b\u0435\u0441\u0443\u043d\u043e\u0432\u043e",
        "Lesunovo"
    ],
    "wof:name":"Lesunovo",
    "wof:placetype":"locality"
},
  "geometry": {"coordinates":[43.12666,55.66896],"type":"Point"}
}