{
  "type": "Feature",
  "properties": {
    "gn:admin1_code":"40",
    "gn:asciiname":"Beloyarka Vtoraya",
    "gn:country_code":"RU",
    "gn:dem":127,
    "gn:feature_class":"P",
    "gn:feature_code":"PPL",
    "gn:name":"Beloyarka Vtoraya",
    "gn:population":0,
    "gn:timezone":"Asia/Yekaterinburg",
    "iso:country":"RU",
    "name:nor_x_preferred":[
        "Belojarka Vtoraja"
    ],
    "name:rus_x_preferred":[
        "\u0411\u0435\u043b\u043e\u044f\u0440\u043a\u0430 \u0412\u0442\u043e\u0440\u0430\u044f"
    ],
    "name:und_x_variant":[
        "Beloyarka Pervaya",
        "Beloyarka",
        "Beloyarka Vtoraya"
    ],
    "wof:name":"Beloyarka Vtoraya",
    "wof:placetype":"locality"
},
  "geometry": {"coordinates":[62.33333,55.85],"type":"Point"}
}