{
  "type": "Feature",
  "properties": {
    "gn:admin1_code":"7.0",
    "gn:asciiname":"Bobrov",
    "gn:country_code":"RU",
    "gn:dem":2,
    "gn:feature_class":"P",
    "gn:feature_code":"PPL",
    "gn:name":"Bobrov",
    "gn:population":0,
    "gn:timezone":"Europe/Astrakhan",
    "iso:country":"RU",
    "name:rus_x_preferred":[
        "\u0411\u043e\u0431\u0440\u043e\u0432"
    ],
    "name:und_x_variant":[
        "\u0411\u043e\u0431\u0440\u043e\u0432"
    ],
    "wof:name":"Bobrov",
    "wof:placetype":"locality"
},
  "geometry": {"coordinates":[45.47222,48.18583],"type":"Point"}
}