{
  "type": "Feature",
  "properties": {
    "gn:admin1_code":"52",
    "gn:asciiname":"Vasil'yevshchina",
    "gn:country_code":"RU",
    "gn:dem":33,
    "gn:feature_class":"P",
    "gn:feature_code":"PPL",
    "gn:name":"Vasil\u2019yevshchina",
    "gn:population":0,
    "gn:timezone":"Europe/Moscow",
    "iso:country":"RU",
    "name:rus_x_preferred":[
        "\u0412\u0430\u0441\u0438\u043b\u044c\u0435\u0432\u0449\u0438\u043d\u0430"
    ],
    "name:und_x_variant":[
        "Vasil\u2019yevshchina",
        "\u0412\u0430\u0441\u0438\u043b\u044c\u0435\u0432\u0449\u0438\u043d\u0430"
    ],
    "wof:name":"Vasil'yevshchina",
    "wof:placetype":"locality"
},
  "geometry": {"coordinates":[31.3756,57.84],"type":"Point"}
}