{
  "type": "Feature",
  "properties": {
    "gn:admin1_code":"41.0",
    "gn:asciiname":"Bereza",
    "gn:country_code":"RU",
    "gn:dem":158,
    "gn:feature_class":"P",
    "gn:feature_code":"PPL",
    "gn:name":"Ber\u00ebza",
    "gn:population":0,
    "gn:timezone":"Europe/Moscow",
    "iso:country":"RU",
    "name:ceb_x_preferred":[
        "Bereza"
    ],
    "name:deu_x_preferred":[
        "Beresa"
    ],
    "name:eng_x_preferred":[
        "Ber\u00ebza"
    ],
    "name:fra_x_preferred":[
        "Bereza"
    ],
    "name:hye_x_preferred":[
        "\u0532\u0565\u0580\u0575\u0578\u0566\u0561"
    ],
    "name:ita_x_preferred":[
        "Bereza"
    ],
    "name:pol_x_preferred":[
        "Bereza"
    ],
    "name:rus_x_preferred":[
        "\u0411\u0435\u0440\u0435\u0437\u0430"
    ],
    "name:rus_x_variant":[
        "\u0411\u0435\u0440\u0451\u0437\u0430"
    ],
    "name:spa_x_preferred":[
        "Bereza"
    ],
    "name:swe_x_preferred":[
        "Bereza"
    ],
    "name:ukr_x_preferred":[
        "\u0411\u0435\u0440\u0435\u0437\u0430"
    ],
    "wof:name":"Bereza",
    "wof:placetype":"locality"
},
  "geometry": {"coordinates":[34.9745,51.9579],"type":"Point"}
}