{
  "type": "Feature",
  "properties": {
    "gn:country":"RU",
    "gn:fcode":"PPL",
    "gn:population":2744,
    "iso:country":"RU",
    "name:eng_x_preferred":[
        "Stepantsevo"
    ],
    "name:nor_x_preferred":[
        "Stepantsevo"
    ],
    "name:rus_x_preferred":[
        "\u0421\u0442\u0435\u043f\u0430\u043d\u0446\u0435\u0432\u043e"
    ],
    "qs:name":"Stepantsevo",
    "qs:photos_9r":0,
    "qs:photos_sr":0,
    "qs:pop_sr":"4",
    "wof:name":"Stepantsevo",
    "wof:placetype":"locality",
    "wof:population":2744
},
  "geometry": {"coordinates":[41.7032,56.13143],"type":"Point"}
}