{
  "type": "Feature",
  "properties": {
    "gn:admin1_code":"90",
    "gn:asciiname":"Teklovka",
    "gn:country_code":"RU",
    "gn:dem":175,
    "gn:feature_class":"P",
    "gn:feature_code":"PPL",
    "gn:name":"Teklovka",
    "gn:population":0,
    "gn:timezone":"Asia/Yekaterinburg",
    "iso:country":"RU",
    "name:che_x_preferred":[
        "\u0422\u0435\u043a\u043b\u043e\u0432\u043a\u0430"
    ],
    "name:chv_x_preferred":[
        "\u0422\u0435\u043a\u043b\u043e\u0432\u043a\u0430"
    ],
    "name:rus_x_preferred":[
        "\u0422\u0435\u043a\u043b\u043e\u0432\u043a\u0430"
    ],
    "name:tat_x_preferred":[
        "\u0422\u0435\u043a\u043b\u043e\u0432\u043a\u0430"
    ],
    "wof:name":"Teklovka",
    "wof:placetype":"locality"
},
  "geometry": {"coordinates":[56.45338,56.39495],"type":"Point"}
}