{
  "type": "Feature",
  "properties": {
    "gn:admin1_code":"17",
    "gn:asciiname":"Karlanyurt",
    "gn:country_code":"RU",
    "gn:dem":164,
    "gn:feature_class":"P",
    "gn:feature_code":"PPL",
    "gn:name":"Karlanyurt",
    "gn:population":0,
    "gn:timezone":"Europe/Moscow",
    "iso:country":"RU",
    "name:rus_x_preferred":[
        "\u041a\u0430\u0440\u043b\u0430\u043d\u044e\u0440\u0442"
    ],
    "wof:name":"Karlanyurt",
    "wof:placetype":"locality"
},
  "geometry": {"coordinates":[46.64588,43.22958],"type":"Point"}
}