{
  "type": "Feature",
  "properties": {
    "gn:admin1_code":"23",
    "gn:asciiname":"Dorozhnoye",
    "gn:country_code":"RU",
    "gn:dem":14,
    "gn:feature_class":"P",
    "gn:feature_code":"PPL",
    "gn:name":"Dorozhnoye",
    "gn:population":0,
    "gn:timezone":"Europe/Kaliningrad",
    "iso:country":"RU",
    "name:rus_x_preferred":[
        "\u0414\u043e\u0440\u043e\u0436\u043d\u043e\u0435"
    ],
    "wof:name":"Dorozhnoye",
    "wof:placetype":"locality"
},
  "geometry": {"coordinates":[20.52137,54.65488000000001],"type":"Point"}
}