{
  "type": "Feature",
  "properties": {
    "gn:admin1_code":"72.0",
    "gn:asciiname":"Alekhinskiye Vyselki",
    "gn:country_code":"RU",
    "gn:dem":150,
    "gn:feature_class":"P",
    "gn:feature_code":"PPL",
    "gn:name":"Al\u00ebkhinskiye Vyselki",
    "gn:population":0,
    "gn:timezone":"Europe/Moscow",
    "iso:country":"RU",
    "name:nor_x_preferred":[
        "Aljokhinskije Vyselki"
    ],
    "name:rus_x_preferred":[
        "\u0410\u043b\u0451\u0445\u0438\u043d\u0441\u043a\u0438\u0435 \u0412\u044b\u0441\u0435\u043b\u043a\u0438"
    ],
    "name:und_x_variant":[
        "Alekhinskiye",
        "Al\u00ebkhinskiye Vyselki"
    ],
    "wof:name":"Alekhinskiye Vyselki",
    "wof:placetype":"locality"
},
  "geometry": {"coordinates":[41.27194,52.23306],"type":"Point"}
}