{
  "type": "Feature",
  "properties": {
    "gn:country":"RU",
    "gn:fcode":"PPL",
    "gn:population":0,
    "iso:country":"RU",
    "name:eng_x_preferred":[
        "Bunyr\u00ebvo"
    ],
    "name:nor_x_preferred":[
        "Bunyrevo"
    ],
    "name:rus_x_preferred":[
        "\u0411\u0443\u043d\u044b\u0440\u0435\u0432\u043e"
    ],
    "name:rus_x_variant":[
        "\u0411\u0443\u043d\u044b\u0440\u0451\u0432\u043e"
    ],
    "qs:name":"Bunyrevo",
    "qs:name_adm0":"Russia",
    "qs:name_adm1":"Tula Oblast",
    "qs:photos_9r":0,
    "qs:photos_sr":0,
    "qs:placetype":"Town",
    "qs:pop_sr":"0",
    "wof:name":"Bunyrevo",
    "wof:placetype":"locality",
    "wof:population":0
},
  "geometry": {"coordinates":[37.15025,54.56975],"type":"Point"}
}