{
  "type": "Feature",
  "properties": {
    "gn:admin1_code":"75",
    "gn:asciiname":"Vakhtovyy Poselok Tayezhnyy",
    "gn:country_code":"RU",
    "gn:dem":118,
    "gn:feature_class":"P",
    "gn:feature_code":"PPL",
    "gn:name":"Vakhtovyy Pos\u00eblok Tay\u00ebzhnyy",
    "gn:population":0,
    "gn:timezone":"Asia/Tomsk",
    "iso:country":"RU",
    "name:rus_x_preferred":[
        "\u0412\u0430\u0445\u0442\u043e\u0432\u044b\u0439 \u041f\u043e\u0441\u00eb\u043b\u043e\u043a \u0422\u0430\u00eb\u0436\u043d\u044b\u0439"
    ],
    "name:und_x_variant":[
        "Vakhtovyy Pos\u00eblok Tay\u00ebzhnyy"
    ],
    "wof:name":"Vakhtovyy Poselok Tayezhnyy",
    "wof:placetype":"locality"
},
  "geometry": {"coordinates":[85.22620000000001,57.273],"type":"Point"}
}