{
  "type": "Feature",
  "properties": {
    "gn:admin1_code":"84",
    "gn:asciiname":"Proletariy",
    "gn:country_code":"RU",
    "gn:dem":122,
    "gn:feature_class":"P",
    "gn:feature_code":"PPL",
    "gn:name":"Proletariy",
    "gn:population":0,
    "gn:timezone":"Europe/Volgograd",
    "iso:country":"RU",
    "name:rus_x_preferred":[
        "\u041f\u0440\u043e\u043b\u0435\u0442\u0430\u0440\u0438\u0439"
    ],
    "name:und_x_variant":[
        "\u041f\u0440\u043e\u043b\u0435\u0442\u0430\u0440\u0438\u0439"
    ],
    "wof:name":"Proletariy",
    "wof:placetype":"locality"
},
  "geometry": {"coordinates":[44.33333,49.36667],"type":"Point"}
}