{
  "type": "Feature",
  "properties": {
    "gn:country":"RU",
    "gn:fcode":"PPL",
    "gn:pop":0,
    "iso:country":"RU",
    "name:rus_x_preferred":[
        "\u041a\u043b\u0435\u0439\u043c\u0435\u043d\u043e\u0432\u043e"
    ],
    "name:unk_x_variant":[
        "\u041a\u043b\u0435\u0439\u043c\u0435\u043d\u043e\u0432\u043e"
    ],
    "qs:name":"Kleymenovo",
    "qs:name_adm0":"Russia",
    "qs:name_adm1":"Moscow Oblast",
    "qs:photos_9r":0,
    "qs:photos_sr":0,
    "qs:placetype":"Town",
    "qs:pop_sr":"0",
    "wof:name":"Kleymenovo",
    "wof:placetype":"locality",
    "wof:population":0
},
  "geometry": {"coordinates":[37.30921,55.02815],"type":"Point"}
}