{
  "type": "Feature",
  "properties": {
    "gn:admin1_code":"78",
    "gn:asciiname":"Berezino",
    "gn:country_code":"RU",
    "gn:dem":68,
    "gn:feature_class":"P",
    "gn:feature_code":"PPL",
    "gn:name":"Berezino",
    "gn:population":0,
    "gn:timezone":"Asia/Yekaterinburg",
    "iso:country":"RU",
    "name:eng_x_preferred":[
        "Berezino"
    ],
    "name:nor_x_preferred":[
        "Berezino"
    ],
    "name:rus_x_preferred":[
        "\u0411\u0435\u0440\u0435\u0437\u0438\u043d\u043e"
    ],
    "name:und_x_variant":[
        "Berezina",
        "\u0411\u0435\u0440\u0435\u0437\u0438\u043d\u043e",
        "Berezino"
    ],
    "wof:name":"Berezino",
    "wof:placetype":"locality"
},
  "geometry": {"coordinates":[70.45140000000001,56.81766],"type":"Point"}
}