{
  "type": "Feature",
  "properties": {
    "gn:admin1_code":"30",
    "gn:asciiname":"Shumnyy",
    "gn:country_code":"RU",
    "gn:dem":152,
    "gn:feature_class":"P",
    "gn:feature_code":"PPL",
    "gn:name":"Shumnyy",
    "gn:population":0,
    "gn:timezone":"Asia/Vladivostok",
    "iso:country":"RU",
    "name:eng_x_preferred":[
        "Shumnyy"
    ],
    "name:nor_x_preferred":[
        "Sjumnyj"
    ],
    "name:rus_x_preferred":[
        "\u0428\u0443\u043c\u043d\u044b\u0439"
    ],
    "wof:name":"Shumnyy",
    "wof:placetype":"locality"
},
  "geometry": {"coordinates":[134.98163,47.277],"type":"Point"}
}