{
  "type": "Feature",
  "properties": {
    "gn:admin1_code":"83",
    "gn:asciiname":"Selino",
    "gn:country_code":"RU",
    "gn:dem":115,
    "gn:feature_class":"P",
    "gn:feature_code":"PPL",
    "gn:name":"Selino",
    "gn:population":0,
    "gn:timezone":"Europe/Moscow",
    "iso:country":"RU",
    "name:cat_x_preferred":[
        "S\u00e9lino"
    ],
    "name:ell_x_preferred":[
        "\u0395\u03c0\u03b1\u03c1\u03c7\u03af\u03b1 \u03a3\u03b5\u03bb\u03af\u03bd\u03bf\u03c5"
    ],
    "name:eng_x_preferred":[
        "Selino"
    ],
    "name:fra_x_preferred":[
        "S\u00e9lino"
    ],
    "name:nor_x_preferred":[
        "Selino"
    ],
    "name:rus_x_preferred":[
        "\u0421\u0435\u043b\u0438\u043d\u043e"
    ],
    "name:und_x_variant":[
        "\u0421\u0435\u043b\u0438\u043d\u043e",
        "Selino"
    ],
    "wof:name":"Selino",
    "wof:placetype":"locality"
},
  "geometry": {"coordinates":[41.8411,55.4242],"type":"Point"}
}