{
  "type": "Feature",
  "properties": {
    "gn:admin1_code":"8.0",
    "gn:asciiname":"Al'mukhametovo",
    "gn:country_code":"RU",
    "gn:dem":354,
    "gn:feature_class":"P",
    "gn:feature_code":"PPL",
    "gn:name":"Al\u2019mukhametovo",
    "gn:population":0,
    "gn:timezone":"Asia/Yekaterinburg",
    "iso:country":"RU",
    "name:eng_x_preferred":[
        "Al'mukhametovo"
    ],
    "name:nor_x_preferred":[
        "Almukhametovo"
    ],
    "name:rus_x_preferred":[
        "\u0410\u043b\u044c\u043c\u0443\u0445\u0430\u043c\u0435\u0442\u043e\u0432\u043e"
    ],
    "name:und_x_variant":[
        "Al\u2019mukhametova",
        "Al\u2019mukhametovo"
    ],
    "wof:name":"Al'mukhametovo",
    "wof:placetype":"locality"
},
  "geometry": {"coordinates":[58.68972,53.02056],"type":"Point"}
}