{
  "type": "Feature",
  "properties": {
    "gn:admin1_code":"85.0",
    "gn:asciiname":"Anisimovo",
    "gn:country_code":"RU",
    "gn:dem":139,
    "gn:feature_class":"P",
    "gn:feature_code":"PPL",
    "gn:name":"Anisimovo",
    "gn:population":0,
    "gn:timezone":"Europe/Moscow",
    "iso:country":"RU",
    "name:nor_x_preferred":[
        "Anisimovo"
    ],
    "name:rus_x_preferred":[
        "\u0410\u043d\u0438\u0441\u0438\u043c\u043e\u0432\u043e"
    ],
    "name:und_x_variant":[
        "Anisimova"
    ],
    "wof:name":"Anisimovo",
    "wof:placetype":"locality"
},
  "geometry": {"coordinates":[35.1275,59.1746],"type":"Point"}
}