{
  "type": "Feature",
  "properties": {
    "gn:admin1_code":"33",
    "gn:asciiname":"Mochalishche",
    "gn:country_code":"RU",
    "gn:dem":161,
    "gn:feature_class":"P",
    "gn:feature_code":"PPL",
    "gn:name":"Mochalishche",
    "gn:population":0,
    "gn:timezone":"Europe/Kirov",
    "iso:country":"RU",
    "name:rus_x_preferred":[
        "\u041c\u043e\u0447\u0430\u043b\u0438\u0449\u0435"
    ],
    "name:und_x_variant":[
        "\u041c\u043e\u0447\u0430\u043b\u0438\u0449\u0435"
    ],
    "wof:name":"Mochalishche",
    "wof:placetype":"locality"
},
  "geometry": {"coordinates":[49.37681,58.28802],"type":"Point"}
}