{
  "type": "Feature",
  "properties": {
    "gn:admin1_code":"9",
    "gn:asciiname":"Staraya Maslovka",
    "gn:cc2":"RU",
    "gn:country_code":"RU",
    "gn:dem":120,
    "gn:feature_class":"P",
    "gn:feature_code":"PPL",
    "gn:name":"Staraya Maslovka",
    "gn:population":0,
    "gn:timezone":"Europe/Moscow",
    "iso:country":"RU",
    "name:rus_x_preferred":[
        "\u0421\u0442\u0430\u0440\u0430\u044f \u041c\u0430\u0441\u043b\u043e\u0432\u043a\u0430"
    ],
    "name:und_x_variant":[
        "Maslovka",
        "Staraya Maslovka",
        "\u0421\u0442\u0430\u0440\u0430\u044f \u041c\u0430\u0441\u043b\u043e\u0432\u043a\u0430"
    ],
    "wof:name":"Staraya Maslovka",
    "wof:placetype":"locality"
},
  "geometry": {"coordinates":[37.78583,50.87194],"type":"Point"}
}