{
  "type": "Feature",
  "properties": {
    "gn:admin1_code":"75",
    "gn:asciiname":"Nevol'kanak",
    "gn:country_code":"RU",
    "gn:dem":71,
    "gn:feature_class":"P",
    "gn:feature_code":"PPL",
    "gn:name":"Nevol\u2019kanak",
    "gn:population":0,
    "gn:timezone":"Asia/Tomsk",
    "iso:country":"RU",
    "name:rus_x_preferred":[
        "\u041d\u0435\u0432\u043e\u043b\u044c\u043a\u0430\u043d\u0430\u043a"
    ],
    "name:und_x_variant":[
        "Nevol\u2019kanak"
    ],
    "wof:name":"Nevol'kanak",
    "wof:placetype":"locality"
},
  "geometry": {"coordinates":[79.46666999999999,58.45],"type":"Point"}
}