{
  "type": "Feature",
  "properties": {
    "gn:admin1_code":"61",
    "gn:asciiname":"Rakitnyy",
    "gn:country_code":"RU",
    "gn:dem":38,
    "gn:feature_class":"P",
    "gn:feature_code":"PPL",
    "gn:name":"Rakitnyy",
    "gn:population":0,
    "gn:timezone":"Europe/Moscow",
    "iso:country":"RU",
    "name:eng_x_preferred":[
        "Rakitnyy"
    ],
    "name:nor_x_preferred":[
        "Rakitnyj"
    ],
    "name:rus_x_preferred":[
        "\u0420\u0430\u043a\u0438\u0442\u043d\u044b\u0439"
    ],
    "name:und_x_variant":[
        "Rakitny"
    ],
    "wof:name":"Rakitnyy",
    "wof:placetype":"locality"
},
  "geometry": {"coordinates":[40.31022,46.8968],"type":"Point"}
}