{
  "type": "Feature",
  "properties": {
    "gn:country":"RU",
    "gn:fcode":"PPL",
    "gn:pop":3152,
    "iso:country":"RU",
    "name:eng_x_preferred":[
        "Tunoshna"
    ],
    "name:nor_x_preferred":[
        "Tunosjna"
    ],
    "name:rus_x_preferred":[
        "\u0422\u0443\u043d\u043e\u0448\u043d\u0430"
    ],
    "name:unk_x_variant":[
        "Tunoshnoye"
    ],
    "qs:name":"Tunoshna",
    "qs:name_adm0":"Russia",
    "qs:name_adm1":"Yaroslavl Oblast",
    "qs:photos_9k":1,
    "qs:photos_9r":3,
    "qs:photos_all":106,
    "qs:photos_sr":0,
    "qs:placetype":"Town",
    "qs:pop_sr":"4",
    "wof:name":"Tunoshna",
    "wof:placetype":"locality",
    "wof:population":3152
},
  "geometry": {"coordinates":[40.12543,57.54589],"type":"Point"}
}