{
  "type": "Feature",
  "properties": {
    "gn:admin1_code":"80.0",
    "gn:asciiname":"Verkhniy Chumoy",
    "gn:country_code":"RU",
    "gn:dem":206,
    "gn:feature_class":"P",
    "gn:feature_code":"PPL",
    "gn:name":"Verkhniy Chumoy",
    "gn:population":0,
    "gn:timezone":"Europe/Samara",
    "iso:country":"RU",
    "name:rus_x_preferred":[
        "\u0412\u0435\u0440\u0445\u043d\u0438\u0439 \u0427\u0443\u043c\u043e\u0439"
    ],
    "wof:name":"Verkhniy Chumoy",
    "wof:placetype":"locality"
},
  "geometry": {"coordinates":[53.3954,57.3944],"type":"Point"}
}