{
  "type": "Feature",
  "properties": {
    "gn:admin1_code":"54",
    "gn:asciiname":"Lamanovo",
    "gn:country_code":"RU",
    "gn:dem":101,
    "gn:feature_class":"P",
    "gn:feature_code":"PPL",
    "gn:name":"Lamanovo",
    "gn:population":0,
    "gn:timezone":"Asia/Omsk",
    "iso:country":"RU",
    "name:eng_x_preferred":[
        "Lamanovo"
    ],
    "name:nor_x_preferred":[
        "Lamanovo"
    ],
    "name:rus_x_preferred":[
        "\u041b\u0430\u043c\u0430\u043d\u043e\u0432\u043e"
    ],
    "name:und_x_variant":[
        "Lamanova",
        "\u041b\u0430\u043c\u0430\u043d\u043e\u0432\u043e",
        "Lamanovo"
    ],
    "wof:name":"Lamanovo",
    "wof:placetype":"locality"
},
  "geometry": {"coordinates":[73.82944999999999,56.293],"type":"Point"}
}