{
  "type": "Feature",
  "properties": {
    "gn:admin1_code":"21",
    "gn:asciiname":"Kolbatskoye",
    "gn:country_code":"RU",
    "gn:dem":100,
    "gn:feature_class":"P",
    "gn:feature_code":"PPL",
    "gn:name":"Kolbatskoye",
    "gn:population":0,
    "gn:timezone":"Europe/Moscow",
    "iso:country":"RU",
    "name:rus_x_preferred":[
        "\u041a\u043e\u043b\u0431\u0430\u0442\u0441\u043a\u043e\u0435"
    ],
    "name:und_x_variant":[
        "\u041a\u043e\u043b\u0431\u0430\u0442\u0441\u043a\u043e\u0435"
    ],
    "wof:name":"Kolbatskoye",
    "wof:placetype":"locality"
},
  "geometry": {"coordinates":[41.41105,57.04345],"type":"Point"}
}