{
  "type": "Feature",
  "properties": {
    "gn:admin1_code":"90",
    "gn:asciiname":"Runy",
    "gn:country_code":"RU",
    "gn:dem":159,
    "gn:feature_class":"P",
    "gn:feature_code":"PPL",
    "gn:name":"Runy",
    "gn:population":0,
    "gn:timezone":"Asia/Yekaterinburg",
    "iso:country":"RU",
    "name:rus_x_preferred":[
        "\u0420\u0443\u043d\u044b"
    ],
    "name:und_x_variant":[
        "\u0420\u0443\u043d\u044b"
    ],
    "wof:name":"Runy",
    "wof:placetype":"locality"
},
  "geometry": {"coordinates":[56.38333000000001,59.68333000000001],"type":"Point"}
}