{
  "type": "Feature",
  "properties": {
    "gn:admin1_code":"55",
    "gn:asciiname":"Dzhelandy",
    "gn:country_code":"RU",
    "gn:dem":175,
    "gn:feature_class":"P",
    "gn:feature_code":"PPL",
    "gn:name":"Dzhelandy",
    "gn:population":0,
    "gn:timezone":"Asia/Yekaterinburg",
    "iso:country":"RU",
    "name:rus_x_preferred":[
        "\u0414\u0436\u0435\u043b\u0430\u043d\u0434\u044b"
    ],
    "wof:name":"Dzhelandy",
    "wof:placetype":"locality"
},
  "geometry": {"coordinates":[55.4789,51.5092],"type":"Point"}
}