{
  "type": "Feature",
  "properties": {
    "gn:admin1_code":"90",
    "gn:asciiname":"Melekhina",
    "gn:country_code":"RU",
    "gn:dem":159,
    "gn:feature_class":"P",
    "gn:feature_code":"PPL",
    "gn:name":"Melekhina",
    "gn:population":0,
    "gn:timezone":"Asia/Yekaterinburg",
    "iso:country":"RU",
    "name:eng_x_preferred":[
        "Melekhina"
    ],
    "name:nor_x_preferred":[
        "Melekhina"
    ],
    "name:rus_x_preferred":[
        "\u041c\u0435\u043b\u0435\u0445\u0438\u043d\u0430"
    ],
    "name:und_x_variant":[
        "Malekhina",
        "Melekhino",
        "Melekhina",
        "\u041c\u0435\u043b\u0435\u0445\u0438\u043d\u0430"
    ],
    "wof:name":"Melekhina",
    "wof:placetype":"locality"
},
  "geometry": {"coordinates":[55.0973,59.2713],"type":"Point"}
}