{
  "type": "Feature",
  "properties": {
    "gn:admin1_code":"69",
    "gn:asciiname":"Ol'sha-Dolgaya",
    "gn:country_code":"RU",
    "gn:dem":196,
    "gn:feature_class":"P",
    "gn:feature_code":"PPL",
    "gn:name":"Ol\u2019sha-Dolgaya",
    "gn:population":0,
    "gn:timezone":"Europe/Moscow",
    "iso:country":"RU",
    "name:rus_x_preferred":[
        "\u041e\u043b\u044c\u0448\u0430-\u0414\u043e\u043b\u0433\u0430\u044f"
    ],
    "name:und_x_variant":[
        "Ol\u2019sha",
        "Ol\u2019sha-Dolgaya"
    ],
    "wof:name":"Ol'sha-Dolgaya",
    "wof:placetype":"locality"
},
  "geometry": {"coordinates":[31.80079000000001,54.85181],"type":"Point"}
}