{
  "type": "Feature",
  "properties": {
    "gn:admin1_code":"63",
    "gn:asciiname":"Chay",
    "gn:cc2":"RU",
    "gn:country_code":"RU",
    "gn:dem":274,
    "gn:feature_class":"P",
    "gn:feature_code":"PPL",
    "gn:name":"Chay",
    "gn:population":0,
    "gn:timezone":"Asia/Vladivostok",
    "iso:country":"RU",
    "name:ceb_x_preferred":[
        "Chay"
    ],
    "name:deu_x_preferred":[
        "Chay"
    ],
    "name:ita_x_preferred":[
        "Chay"
    ],
    "name:nld_x_preferred":[
        "Chay"
    ],
    "name:pol_x_preferred":[
        "Chay"
    ],
    "name:rus_x_preferred":[
        "\u0427\u0430\u0439"
    ],
    "name:scn_x_preferred":[
        "Chay"
    ],
    "name:und_x_variant":[
        "Chay-Povarnya"
    ],
    "name:vie_x_preferred":[
        "Chay"
    ],
    "wof:name":"Chay",
    "wof:placetype":"locality"
},
  "geometry": {"coordinates":[140.86609999999999,72.84085999999998],"type":"Point"}
}