{
  "type": "Feature",
  "properties": {
    "gn:admin1_code":"30",
    "gn:asciiname":"Bol'shiye Sanniki",
    "gn:country_code":"RU",
    "gn:dem":47,
    "gn:feature_class":"P",
    "gn:feature_code":"PPL",
    "gn:name":"Bol\u2019shiye Sanniki",
    "gn:population":0,
    "gn:timezone":"Asia/Vladivostok",
    "iso:country":"RU",
    "name:rus_x_preferred":[
        "\u0411\u043e\u043b\u044c\u0448\u0438\u0435 \u0421\u0430\u043d\u043d\u0438\u043a\u0438"
    ],
    "name:und_x_variant":[
        "Bol\u2019shiye Sanniki",
        "\u0411\u043e\u043b\u044c\u0448\u0438\u0435 \u0421\u0430\u043d\u043d\u0438\u043a\u0438"
    ],
    "wof:name":"Bol'shiye Sanniki",
    "wof:placetype":"locality"
},
  "geometry": {"coordinates":[140.46093999999999,51.64714],"type":"Point"}
}