{
  "type": "Feature",
  "properties": {
    "gn:admin1_code":"52",
    "gn:asciiname":"Maloye Lanovshchino",
    "gn:country_code":"RU",
    "gn:dem":91,
    "gn:feature_class":"P",
    "gn:feature_code":"PPL",
    "gn:name":"Maloye Lanovshchino",
    "gn:population":0,
    "gn:timezone":"Europe/Moscow",
    "iso:country":"RU",
    "name:rus_x_preferred":[
        "\u041c\u0430\u043b\u043e\u0435 \u041b\u0430\u043d\u043e\u0432\u0449\u0438\u043d\u043e"
    ],
    "name:und_x_variant":[
        "Malaya Lanovshchina",
        "Maloye Lakovshino",
        "Maloye Lanovshchino",
        "\u041c\u0430\u043b\u043e\u0435 \u041b\u0430\u043d\u043e\u0432\u0449\u0438\u043d\u043e"
    ],
    "wof:name":"Maloye Lanovshchino",
    "wof:placetype":"locality"
},
  "geometry": {"coordinates":[32.47649000000001,58.88865],"type":"Point"}
}