{
  "type": "Feature",
  "properties": {
    "gn:admin1_code":"17",
    "gn:admin2_code":"Tsuntinskiy Rayon",
    "gn:asciiname":"Tindy",
    "gn:country_code":"RU",
    "gn:dem":2568,
    "gn:feature_class":"P",
    "gn:feature_code":"PPL",
    "gn:name":"Tindy",
    "gn:population":0,
    "gn:timezone":"Europe/Moscow",
    "iso:country":"RU",
    "name:spa_x_preferred":[
        "Snowboard"
    ],
    "wof:name":"Tindy",
    "wof:placetype":"locality"
},
  "geometry": {"coordinates":[45.81667,42.31667],"type":"Point"}
}