{
  "type": "Feature",
  "properties": {
    "gn:admin1_code":"40",
    "gn:asciiname":"Bydino",
    "gn:cc2":"RU",
    "gn:country_code":"RU",
    "gn:dem":122,
    "gn:feature_class":"P",
    "gn:feature_code":"PPL",
    "gn:name":"Bydino",
    "gn:population":0,
    "gn:timezone":"Asia/Yekaterinburg",
    "iso:country":"RU",
    "name:eng_x_preferred":[
        "Bydino"
    ],
    "name:nor_x_preferred":[
        "Bydino"
    ],
    "name:rus_x_preferred":[
        "\u0411\u044b\u0434\u0438\u043d\u043e"
    ],
    "name:und_x_variant":[
        "Bydina"
    ],
    "wof:name":"Bydino",
    "wof:placetype":"locality"
},
  "geometry": {"coordinates":[64.24250000000001,55.31361],"type":"Point"}
}