{
  "type": "Feature",
  "properties": {
    "gn:admin1_code":"62",
    "gn:asciiname":"Gureykino",
    "gn:country_code":"RU",
    "gn:dem":149,
    "gn:feature_class":"P",
    "gn:feature_code":"PPL",
    "gn:name":"Gureykino",
    "gn:population":0,
    "gn:timezone":"Europe/Moscow",
    "iso:country":"RU",
    "name:rus_x_preferred":[
        "\u0413\u0443\u0440\u0435\u0439\u043a\u0438\u043d\u043e"
    ],
    "wof:name":"Gureykino",
    "wof:placetype":"locality"
},
  "geometry": {"coordinates":[39.8732,54.5556],"type":"Point"}
}