{
  "type": "Feature",
  "properties": {
    "gn:admin1_code":"61",
    "gn:asciiname":"Kars",
    "gn:country_code":"RU",
    "gn:dem":93,
    "gn:feature_class":"P",
    "gn:feature_code":"PPL",
    "gn:name":"Kars",
    "gn:population":0,
    "gn:timezone":"Europe/Moscow",
    "iso:country":"RU",
    "name:rus_x_preferred":[
        "\u041a\u0430\u0440\u0441"
    ],
    "name:und_x_variant":[
        "\u041a\u0430\u0440\u0441"
    ],
    "wof:name":"Kars",
    "wof:placetype":"locality"
},
  "geometry": {"coordinates":[41.05972,46.75361],"type":"Point"}
}