{
  "type": "Feature",
  "properties": {
    "gn:admin1_code":"91",
    "gn:asciiname":"Chistoye Pole",
    "gn:country_code":"RU",
    "gn:dem":342,
    "gn:feature_class":"P",
    "gn:feature_code":"PPL",
    "gn:name":"Chistoye Pole",
    "gn:population":0,
    "gn:timezone":"Asia/Krasnoyarsk",
    "iso:country":"RU",
    "name:eng_x_preferred":[
        "Chistoye Pole"
    ],
    "name:nor_x_preferred":[
        "Tsjistoje Pole"
    ],
    "name:rus_x_preferred":[
        "\u0427\u0438\u0441\u0442\u043e\u0435 \u041f\u043e\u043b\u0435"
    ],
    "wof:name":"Chistoye Pole",
    "wof:placetype":"locality"
},
  "geometry": {"coordinates":[91.18138999999999,55.24806],"type":"Point"}
}