{
  "type": "Feature",
  "properties": {
    "gn:admin1_code":"86",
    "gn:asciiname":"Tereshkovo",
    "gn:country_code":"RU",
    "gn:dem":76,
    "gn:feature_class":"P",
    "gn:feature_code":"PPL",
    "gn:name":"Tereshkovo",
    "gn:population":0,
    "gn:timezone":"Europe/Moscow",
    "iso:country":"RU",
    "name:und_x_variant":[
        "Tereshkova",
        "Tereshkovo"
    ],
    "wof:name":"Tereshkovo",
    "wof:placetype":"locality"
},
  "geometry": {"coordinates":[40.65894,49.92115],"type":"Point"}
}