{
  "type": "Feature",
  "properties": {
    "gn:admin1_code":"56",
    "gn:asciiname":"Mayskiy Tsvetok",
    "gn:country_code":"RU",
    "gn:dem":222,
    "gn:feature_class":"P",
    "gn:feature_code":"PPL",
    "gn:name":"Mayskiy Tsvetok",
    "gn:population":0,
    "gn:timezone":"Europe/Moscow",
    "iso:country":"RU",
    "wof:name":"Mayskiy Tsvetok",
    "wof:placetype":"locality"
},
  "geometry": {"coordinates":[35.6025,52.565],"type":"Point"}
}