{
  "type": "Feature",
  "properties": {
    "gn:admin1_code":"77",
    "gn:asciiname":"Khakhilevo",
    "gn:country_code":"RU",
    "gn:dem":136,
    "gn:feature_class":"P",
    "gn:feature_code":"PPL",
    "gn:name":"Khakhilevo",
    "gn:population":0,
    "gn:timezone":"Europe/Moscow",
    "iso:country":"RU",
    "name:rus_x_preferred":[
        "\u0425\u0430\u0445\u0438\u043b\u0435\u0432\u043e"
    ],
    "wof:name":"Khakhilevo",
    "wof:placetype":"locality"
},
  "geometry": {"coordinates":[37.3786,58.4576],"type":"Point"}
}