{
  "type": "Feature",
  "properties": {
    "gn:admin1_code":"45.0",
    "gn:asciiname":"Enermuchash",
    "gn:country_code":"RU",
    "gn:dem":160,
    "gn:feature_class":"P",
    "gn:feature_code":"PPL",
    "gn:name":"Enermuchash",
    "gn:population":0,
    "gn:timezone":"Europe/Moscow",
    "iso:country":"RU",
    "name:rus_x_preferred":[
        "\u042d\u043d\u0435\u0440\u043c\u0443\u0447\u0430\u0448"
    ],
    "name:und_x_variant":[
        "Engermuchash",
        "Enermuchash",
        "\u042d\u043d\u0435\u0440\u043c\u0443\u0447\u0430\u0448"
    ],
    "wof:name":"Enermuchash",
    "wof:placetype":"locality"
},
  "geometry": {"coordinates":[48.68,57.03],"type":"Point"}
}