{
  "type": "Feature",
  "properties": {
    "gn:admin1_code":"83",
    "gn:asciiname":"Soroguzhino",
    "gn:country_code":"RU",
    "gn:dem":162,
    "gn:feature_class":"P",
    "gn:feature_code":"PPL",
    "gn:name":"Soroguzhino",
    "gn:population":0,
    "gn:timezone":"Europe/Moscow",
    "iso:country":"RU",
    "name:eng_x_preferred":[
        "Soroguzhino"
    ],
    "name:nor_x_preferred":[
        "Soroguzjino"
    ],
    "name:rus_x_preferred":[
        "\u0421\u043e\u0440\u043e\u0433\u0443\u0436\u0438\u043d\u043e"
    ],
    "wof:name":"Soroguzhino",
    "wof:placetype":"locality"
},
  "geometry": {"coordinates":[39.62401,56.58666],"type":"Point"}
}