{
  "type": "Feature",
  "properties": {
    "gn:admin1_code":"51",
    "gn:asciiname":"Tayga",
    "gn:country_code":"RU",
    "gn:dem":169,
    "gn:feature_class":"P",
    "gn:feature_code":"PPL",
    "gn:name":"Tayga",
    "gn:population":0,
    "gn:timezone":"Europe/Moscow",
    "iso:country":"RU",
    "name:rus_x_preferred":[
        "\u0422\u0430\u0439\u0433\u0430"
    ],
    "wof:name":"Tayga",
    "wof:placetype":"locality"
},
  "geometry": {"coordinates":[42.6833,55.1452],"type":"Point"}
}