{
  "type": "Feature",
  "properties": {
    "gn:admin1_code":"25",
    "gn:asciiname":"Kur'yanovo",
    "gn:country_code":"RU",
    "gn:dem":176,
    "gn:feature_class":"P",
    "gn:feature_code":"PPL",
    "gn:name":"Kur\u2019yanovo",
    "gn:population":0,
    "gn:timezone":"Europe/Moscow",
    "iso:country":"RU",
    "name:rus_x_preferred":[
        "\u041a\u0443\u0440\u044c\u044f\u043d\u043e\u0432\u043e"
    ],
    "name:und_x_variant":[
        "Kur\u2019yanovo",
        "\u041a\u0443\u0440\u044c\u044f\u043d\u043e\u0432\u043e"
    ],
    "wof:name":"Kur'yanovo",
    "wof:placetype":"locality"
},
  "geometry": {"coordinates":[36.64806,55.22221999999999],"type":"Point"}
}