{
  "type": "Feature",
  "properties": {
    "gn:admin1_code":"71",
    "gn:asciiname":"Malyy Lenevskiy Kordon",
    "gn:country_code":"RU",
    "gn:dem":214,
    "gn:feature_class":"P",
    "gn:feature_code":"PPL",
    "gn:name":"Malyy Lenevskiy Kordon",
    "gn:population":0,
    "gn:timezone":"Asia/Yekaterinburg",
    "iso:country":"RU",
    "name:rus_x_preferred":[
        "\u041c\u0430\u043b\u044b\u0439 \u041b\u0435\u043d\u0435\u0432\u0441\u043a\u0438\u0439 \u041a\u043e\u0440\u0434\u043e\u043d"
    ],
    "wof:name":"Malyy Lenevskiy Kordon",
    "wof:placetype":"locality"
},
  "geometry": {"coordinates":[61.4947,57.6361],"type":"Point"}
}