{
  "type": "Feature",
  "properties": {
    "gn:admin1_code":"16",
    "gn:asciiname":"Tuzi-Syarmus",
    "gn:country_code":"RU",
    "gn:dem":163,
    "gn:feature_class":"P",
    "gn:feature_code":"PPL",
    "gn:name":"Tuzi-Syarmus",
    "gn:population":0,
    "gn:timezone":"Europe/Moscow",
    "iso:country":"RU",
    "name:rus_x_preferred":[
        "\u0422\u0443\u0437\u0438-\u0421\u044f\u0440\u043c\u0443\u0441"
    ],
    "name:und_x_variant":[
        "Tuzi-Syarmuz",
        "Tuzi-Syarmusy",
        "Tuzi-Syarmus"
    ],
    "wof:name":"Tuzi-Syarmus",
    "wof:placetype":"locality"
},
  "geometry": {"coordinates":[47.13766,55.5807],"type":"Point"}
}