{
  "type": "Feature",
  "properties": {
    "gn:admin1_code":"23",
    "gn:asciiname":"Nizov'ye",
    "gn:country_code":"RU",
    "gn:dem":12,
    "gn:feature_class":"P",
    "gn:feature_code":"PPL",
    "gn:name":"Nizov\u2019ye",
    "gn:population":703,
    "gn:timezone":"Europe/Kaliningrad",
    "iso:country":"RU",
    "name:eng_x_preferred":[
        "Nizov'ye"
    ],
    "name:epo_x_preferred":[
        "Nizovje"
    ],
    "name:nor_x_preferred":[
        "Nizovje"
    ],
    "name:rus_x_preferred":[
        "\u041d\u0438\u0437\u043e\u0432\u044c\u0435"
    ],
    "name:und_x_variant":[
        "Val\u2019dau",
        "Waldau",
        "Nizov\u2019e",
        "\u041d\u0438\u0437\u043e\u0432\u044c\u0435",
        "Nizov\u2019ye"
    ],
    "wof:name":"Nizov'ye",
    "wof:placetype":"locality",
    "wof:population":703
},
  "geometry": {"coordinates":[20.73757,54.70206999999999],"type":"Point"}
}