{
  "type": "Feature",
  "properties": {
    "gn:admin1_code":"45",
    "gn:asciiname":"Tanagayevo",
    "gn:country_code":"RU",
    "gn:dem":141,
    "gn:feature_class":"P",
    "gn:feature_code":"PPL",
    "gn:name":"Tanagayevo",
    "gn:population":0,
    "gn:timezone":"Europe/Moscow",
    "iso:country":"RU",
    "name:rus_x_preferred":[
        "\u0422\u0430\u043d\u0430\u0433\u0430\u0435\u0432\u043e"
    ],
    "wof:name":"Tanagayevo",
    "wof:placetype":"locality"
},
  "geometry": {"coordinates":[48.4328,57.0891],"type":"Point"}
}