{
  "type": "Feature",
  "properties": {
    "gn:admin1_code":"45.0",
    "gn:asciiname":"Kugener",
    "gn:country_code":"RU",
    "gn:dem":137,
    "gn:feature_class":"P",
    "gn:feature_code":"PPL",
    "gn:name":"Kugener",
    "gn:population":0,
    "gn:timezone":"Europe/Moscow",
    "iso:country":"RU",
    "name:rus_x_preferred":[
        "\u041a\u0443\u0433\u0435\u043d\u0435\u0440"
    ],
    "name:und_x_variant":[
        "\u041a\u0443\u0433\u0435\u043d\u0435\u0440"
    ],
    "wof:name":"Kugener",
    "wof:placetype":"locality"
},
  "geometry": {"coordinates":[48.30833,56.98972],"type":"Point"}
}