{
  "type": "Feature",
  "properties": {
    "gn:admin1_code":"85.0",
    "gn:asciiname":"Kostyunikovo",
    "gn:country_code":"RU",
    "gn:dem":114,
    "gn:feature_class":"P",
    "gn:feature_code":"PPL",
    "gn:name":"Kostyunikovo",
    "gn:population":0,
    "gn:timezone":"Europe/Moscow",
    "iso:country":"RU",
    "name:rus_x_preferred":[
        "\u041a\u043e\u0441\u0442\u044e\u043d\u0438\u043a\u043e\u0432\u043e"
    ],
    "wof:name":"Kostyunikovo",
    "wof:placetype":"locality"
},
  "geometry": {"coordinates":[37.1296,60.6538],"type":"Point"}
}