{
  "type": "Feature",
  "properties": {
    "gn:admin1_code":"42",
    "gn:asciiname":"Kulygino",
    "gn:cc2":"RU",
    "gn:country_code":"RU",
    "gn:dem":173,
    "gn:feature_class":"P",
    "gn:feature_code":"PPL",
    "gn:name":"Kulygino",
    "gn:population":0,
    "gn:timezone":"Europe/Moscow",
    "iso:country":"RU",
    "name:rus_x_preferred":[
        "\u041a\u0443\u043b\u044b\u0433\u0438\u043d\u043e"
    ],
    "name:und_x_variant":[
        "Kutigino",
        "Kulygino",
        "\u041a\u0443\u043b\u044b\u0433\u0438\u043d\u043e"
    ],
    "wof:name":"Kulygino",
    "wof:placetype":"locality"
},
  "geometry": {"coordinates":[34.71667,60.01667],"type":"Point"}
}