{
  "type": "Feature",
  "properties": {
    "gn:admin1_code":"60",
    "gn:asciiname":"Shushulino",
    "gn:country_code":"RU",
    "gn:dem":128,
    "gn:feature_class":"P",
    "gn:feature_code":"PPL",
    "gn:name":"Shushulino",
    "gn:population":0,
    "gn:timezone":"Europe/Moscow",
    "iso:country":"RU",
    "name:rus_x_preferred":[
        "\u0428\u0443\u0448\u0443\u043b\u0438\u043d\u043e"
    ],
    "wof:name":"Shushulino",
    "wof:placetype":"locality"
},
  "geometry": {"coordinates":[30.25,56.38333000000001],"type":"Point"}
}