{
  "type": "Feature",
  "properties": {
    "gn:admin1_code":"73.0",
    "gn:asciiname":"Moksha",
    "gn:country_code":"RU",
    "gn:dem":129,
    "gn:feature_class":"P",
    "gn:feature_code":"PPL",
    "gn:name":"Moksha",
    "gn:population":0,
    "gn:timezone":"Europe/Moscow",
    "iso:country":"RU",
    "name:rus_x_preferred":[
        "\u041c\u043e\u043a\u0448\u0430"
    ],
    "name:und_x_variant":[
        "\u041c\u043e\u043a\u0448\u0430"
    ],
    "wof:name":"Moksha",
    "wof:placetype":"locality"
},
  "geometry": {"coordinates":[49.57523,56.31703],"type":"Point"}
}