{
  "type": "Feature",
  "properties": {
    "gn:admin1_code":"8",
    "gn:asciiname":"Voyady",
    "gn:country_code":"RU",
    "gn:dem":111,
    "gn:feature_class":"P",
    "gn:feature_code":"PPL",
    "gn:name":"Voyady",
    "gn:population":0,
    "gn:timezone":"Asia/Yekaterinburg",
    "iso:country":"RU",
    "name:eng_x_preferred":[
        "Voyady"
    ],
    "name:nor_x_preferred":[
        "Vojady"
    ],
    "name:rus_x_preferred":[
        "\u0412\u043e\u044f\u0434\u044b"
    ],
    "name:und_x_variant":[
        "Voyada",
        "Voyady"
    ],
    "wof:name":"Voyady",
    "wof:placetype":"locality"
},
  "geometry": {"coordinates":[54.6527,56.372],"type":"Point"}
}