{
  "type": "Feature",
  "properties": {
    "gn:admin1_code":"86",
    "gn:asciiname":"Nizhnedevitskiy",
    "gn:country_code":"RU",
    "gn:dem":244,
    "gn:feature_class":"P",
    "gn:feature_code":"PPL",
    "gn:name":"Nizhnedevitskiy",
    "gn:population":0,
    "gn:timezone":"Europe/Moscow",
    "iso:country":"RU",
    "name:rus_x_preferred":[
        "\u041d\u0438\u0436\u043d\u0435\u0434\u0435\u0432\u0438\u0446\u043a\u0438\u0439"
    ],
    "name:und_x_variant":[
        "Sovkhoz Nizhnedevitskiy",
        "Nizhnedevitskiy"
    ],
    "wof:name":"Nizhnedevitskiy",
    "wof:placetype":"locality"
},
  "geometry": {"coordinates":[38.2701,51.6235],"type":"Point"}
}