{
  "type": "Feature",
  "properties": {
    "gn:admin1_code":"60",
    "gn:asciiname":"Prezhikha",
    "gn:country_code":"RU",
    "gn:dem":156,
    "gn:feature_class":"P",
    "gn:feature_code":"PPL",
    "gn:name":"Prezhikha",
    "gn:population":0,
    "gn:timezone":"Europe/Moscow",
    "iso:country":"RU",
    "name:rus_x_preferred":[
        "\u041f\u0440\u0435\u0436\u0438\u0445\u0430"
    ],
    "wof:name":"Prezhikha",
    "wof:placetype":"locality"
},
  "geometry": {"coordinates":[30.8683,56.075],"type":"Point"}
}