{
  "type": "Feature",
  "properties": {
    "gn:admin1_code":"56",
    "gn:asciiname":"Don",
    "gn:country_code":"RU",
    "gn:dem":215,
    "gn:feature_class":"P",
    "gn:feature_code":"PPL",
    "gn:name":"Don",
    "gn:population":0,
    "gn:timezone":"Europe/Moscow",
    "iso:country":"RU",
    "name:ara_x_preferred":[
        "\u062f\u0648\u0646"
    ],
    "name:aze_x_preferred":[
        "Don"
    ],
    "name:bos_x_preferred":[
        "Don"
    ],
    "name:bre_x_preferred":[
        "Don"
    ],
    "name:bul_x_preferred":[
        "\u0414\u043e\u043d"
    ],
    "name:cat_x_preferred":[
        "Don"
    ],
    "name:ceb_x_preferred":[
        "Don"
    ],
    "name:ces_x_preferred":[
        "Don"
    ],
    "name:cym_x_preferred":[
        "Don"
    ],
    "name:dan_x_preferred":[
        "Don"
    ],
    "name:deu_x_preferred":[
        "Don"
    ],
    "name:eus_x_preferred":[
        "Don"
    ],
    "name:fas_x_preferred":[
        "\u062f\u0648\u0646"
    ],
    "name:fin_x_preferred":[
        "Don"
    ],
    "name:fra_x_preferred":[
        "Don"
    ],
    "name:fry_x_preferred":[
        "Don"
    ],
    "name:heb_x_preferred":[
        "\u05d3\u05d5\u05df"
    ],
    "name:hrv_x_preferred":[
        "Don"
    ],
    "name:hun_x_preferred":[
        "Don"
    ],
    "name:kat_x_preferred":[
        "\u10d3\u10dd\u10dc\u10d8"
    ],
    "name:kor_x_preferred":[
        "\ub3c8"
    ],
    "name:nld_x_preferred":[
        "Don"
    ],
    "name:nor_x_preferred":[
        "Don"
    ],
    "name:oss_x_preferred":[
        "\u0414\u043e\u043d"
    ],
    "name:pol_x_preferred":[
        "Don"
    ],
    "name:por_x_preferred":[
        "Don"
    ],
    "name:ron_x_preferred":[
        "Don"
    ],
    "name:rus_x_preferred":[
        "\u0414\u043e\u043d"
    ],
    "name:scn_x_preferred":[
        "Don"
    ],
    "name:slv_x_preferred":[
        "Don"
    ],
    "name:spa_x_preferred":[
        "Don"
    ],
    "name:srp_x_preferred":[
        "\u0414\u043e\u043d"
    ],
    "name:swe_x_preferred":[
        "Don"
    ],
    "name:tur_x_preferred":[
        "Don"
    ],
    "name:ukr_x_preferred":[
        "\u0414\u043e\u043d"
    ],
    "name:uzb_x_preferred":[
        "Don"
    ],
    "name:vie_x_preferred":[
        "Don"
    ],
    "name:vls_x_preferred":[
        "Don"
    ],
    "wof:name":"Don",
    "wof:placetype":"locality"
},
  "geometry": {"coordinates":[35.16278,52.4275],"type":"Point"}
}