{
  "type": "Feature",
  "properties": {
    "gn:admin1_code":"56",
    "gn:asciiname":"Don",
    "gn:country_code":"RU",
    "gn:dem":215,
    "gn:feature_class":"P",
    "gn:feature_code":"PPL",
    "gn:name":"Don",
    "gn:population":0,
    "gn:timezone":"Europe/Moscow",
    "iso:country":"RU",
    "name:rus_x_preferred":[
        "\u0414\u043e\u043d"
    ],
    "name:und_x_variant":[
        "\u0414\u043e\u043d"
    ],
    "wof:name":"Don",
    "wof:placetype":"locality"
},
  "geometry": {"coordinates":[35.16278,52.4275],"type":"Point"}
}