{
  "type": "Feature",
  "properties": {
    "gn:admin1_code":"29",
    "gn:asciiname":"Ust'-Akel'",
    "gn:country_code":"RU",
    "gn:dem":151,
    "gn:feature_class":"P",
    "gn:feature_code":"PPL",
    "gn:name":"Ust\u2019-Akel\u2019",
    "gn:population":0,
    "gn:timezone":"Asia/Novokuznetsk",
    "iso:country":"RU",
    "wof:name":"Ust'-Akel'",
    "wof:placetype":"locality"
},
  "geometry": {"coordinates":[87.13651,55.06707],"type":"Point"}
}