{
  "type": "Feature",
  "properties": {
    "gn:admin1_code":"77",
    "gn:asciiname":"Vasilevo",
    "gn:country_code":"RU",
    "gn:dem":201,
    "gn:feature_class":"P",
    "gn:feature_code":"PPL",
    "gn:name":"Vasil\u00ebvo",
    "gn:population":0,
    "gn:timezone":"Europe/Moscow",
    "iso:country":"RU",
    "name:rus_x_preferred":[
        "\u0412\u0430\u0441\u0438\u043b\u0451\u0432\u043e"
    ],
    "name:und_x_variant":[
        "Vasil\u00ebvo"
    ],
    "wof:name":"Vasilevo",
    "wof:placetype":"locality"
},
  "geometry": {"coordinates":[32.2876,55.72727],"type":"Point"}
}