{
  "type": "Feature",
  "properties": {
    "gn:admin1_code":"37",
    "gn:asciiname":"Ryabtsovo",
    "gn:country_code":"RU",
    "gn:dem":96,
    "gn:feature_class":"P",
    "gn:feature_code":"PPL",
    "gn:name":"Ryabtsovo",
    "gn:population":0,
    "gn:timezone":"Europe/Moscow",
    "iso:country":"RU",
    "name:und_x_variant":[
        "Ryabtsova",
        "Ryabtsovo"
    ],
    "wof:name":"Ryabtsovo",
    "wof:placetype":"locality"
},
  "geometry": {"coordinates":[41.252,58.24841],"type":"Point"}
}