{
  "type": "Feature",
  "properties": {
    "gn:admin1_code":"38",
    "gn:asciiname":"Kashtany",
    "gn:country_code":"RU",
    "gn:dem":202,
    "gn:feature_class":"P",
    "gn:feature_code":"PPL",
    "gn:name":"Kashtany",
    "gn:population":0,
    "gn:timezone":"Europe/Moscow",
    "iso:country":"RU",
    "name:nor_x_preferred":[
        "Kasjtany"
    ],
    "name:rus_x_preferred":[
        "\u041a\u0430\u0448\u0442\u0430\u043d\u044b"
    ],
    "name:und_x_variant":[
        "\u041a\u0430\u0448\u0442\u0430\u043d\u044b",
        "Kashtany"
    ],
    "wof:name":"Kashtany",
    "wof:placetype":"locality"
},
  "geometry": {"coordinates":[39.89957,43.52965],"type":"Point"}
}