{
  "type": "Feature",
  "properties": {
    "gn:admin1_code":"21.0",
    "gn:asciiname":"Medvedevo",
    "gn:country_code":"RU",
    "gn:dem":111,
    "gn:feature_class":"P",
    "gn:feature_code":"PPL",
    "gn:name":"Medvedevo",
    "gn:population":0,
    "gn:timezone":"Europe/Moscow",
    "iso:country":"RU",
    "name:rus_x_preferred":[
        "\u041c\u0435\u0434\u0432\u0435\u0434\u0435\u0432\u043e"
    ],
    "name:und_x_variant":[
        "\u041c\u0435\u0434\u0432\u0435\u0434\u0435\u0432\u043e"
    ],
    "wof:name":"Medvedevo",
    "wof:placetype":"locality"
},
  "geometry": {"coordinates":[42.61087,57.06043],"type":"Point"}
}