{
  "type": "Feature",
  "properties": {
    "gn:admin1_code":"20",
    "gn:asciiname":"Tayezhnyy",
    "gn:country_code":"RU",
    "gn:dem":555,
    "gn:feature_class":"P",
    "gn:feature_code":"PPL",
    "gn:name":"Tay\u00ebzhnyy",
    "gn:population":0,
    "gn:timezone":"Asia/Irkutsk",
    "iso:country":"RU",
    "name:eng_x_preferred":[
        "Tay\u00ebzhnyy"
    ],
    "name:nor_x_preferred":[
        "Tajezjnyj"
    ],
    "name:rus_x_preferred":[
        "\u0422\u0430\u0435\u0436\u043d\u044b\u0439"
    ],
    "name:rus_x_variant":[
        "\u0422\u0430\u0451\u0436\u043d\u044b\u0439"
    ],
    "wof:name":"Tayezhnyy",
    "wof:placetype":"locality"
},
  "geometry": {"coordinates":[101.4144,53.341],"type":"Point"}
}