{
  "type": "Feature",
  "properties": {
    "gn:admin1_code":"33",
    "gn:asciiname":"Khozyatino",
    "gn:country_code":"RU",
    "gn:dem":107,
    "gn:feature_class":"P",
    "gn:feature_code":"PPL",
    "gn:name":"Khozyatino",
    "gn:population":0,
    "gn:timezone":"Europe/Kirov",
    "iso:country":"RU",
    "name:rus_x_preferred":[
        "\u0425\u043e\u0437\u044f\u0442\u0438\u043d\u043e"
    ],
    "wof:name":"Khozyatino",
    "wof:placetype":"locality"
},
  "geometry": {"coordinates":[46.5563,60.1593],"type":"Point"}
}