{
  "type": "Feature",
  "properties": {
    "gn:admin1_code":"69",
    "gn:asciiname":"Maksimkovo",
    "gn:country_code":"RU",
    "gn:dem":205,
    "gn:feature_class":"P",
    "gn:feature_code":"PPL",
    "gn:name":"Maksimkovo",
    "gn:population":0,
    "gn:timezone":"Europe/Moscow",
    "iso:country":"RU",
    "name:rus_x_preferred":[
        "\u041c\u0430\u043a\u0441\u0438\u043c\u043a\u043e\u0432\u043e"
    ],
    "name:und_x_variant":[
        "\u041c\u0430\u043a\u0441\u0438\u043c\u043a\u043e\u0432\u043e"
    ],
    "wof:name":"Maksimkovo",
    "wof:placetype":"locality"
},
  "geometry": {"coordinates":[32.86306,53.76833000000001],"type":"Point"}
}