{
  "type": "Feature",
  "properties": {
    "gn:admin1_code":"62",
    "gn:asciiname":"Polenskoye",
    "gn:country_code":"RU",
    "gn:dem":129,
    "gn:feature_class":"P",
    "gn:feature_code":"PPL",
    "gn:name":"Polenskoye",
    "gn:population":0,
    "gn:timezone":"Europe/Moscow",
    "iso:country":"RU",
    "name:rus_x_preferred":[
        "\u041f\u043e\u043b\u0435\u043d\u0441\u043a\u043e\u0435"
    ],
    "wof:name":"Polenskoye",
    "wof:placetype":"locality"
},
  "geometry": {"coordinates":[39.8489,54.5101],"type":"Point"}
}