{
  "type": "Feature",
  "properties": {
    "gn:admin1_code":"42",
    "gn:asciiname":"Kaskovo",
    "gn:country_code":"RU",
    "gn:dem":54,
    "gn:feature_class":"P",
    "gn:feature_code":"PPL",
    "gn:name":"Kaskovo",
    "gn:population":0,
    "gn:timezone":"Europe/Moscow",
    "iso:country":"RU",
    "name:rus_x_preferred":[
        "\u041a\u0430\u0441\u043a\u043e\u0432\u043e"
    ],
    "wof:name":"Kaskovo",
    "wof:placetype":"locality"
},
  "geometry": {"coordinates":[30.05459,58.64885],"type":"Point"}
}