{
  "type": "Feature",
  "properties": {
    "gn:admin1_code":"55",
    "gn:asciiname":"Mirashkino",
    "gn:country_code":"RU",
    "gn:dem":80,
    "gn:feature_class":"P",
    "gn:feature_code":"PPL",
    "gn:name":"Mirashkino",
    "gn:population":0,
    "gn:timezone":"Asia/Yekaterinburg",
    "iso:country":"RU",
    "name:eng_x_preferred":[
        "Mirashkino"
    ],
    "name:nor_x_preferred":[
        "Mirosjkino"
    ],
    "name:rus_x_preferred":[
        "\u041c\u0438\u0440\u043e\u0448\u043a\u0438\u043d\u043e"
    ],
    "name:rus_x_variant":[
        "\u041c\u0438\u0440\u0430\u0448\u043a\u0438\u043d\u043e"
    ],
    "name:und_x_variant":[
        "Miroshkino",
        "Miroshkin"
    ],
    "wof:name":"Mirashkino",
    "wof:placetype":"locality"
},
  "geometry": {"coordinates":[52.4752,51.65525],"type":"Point"}
}