{
  "type": "Feature",
  "properties": {
    "gn:admin1_code":"80",
    "gn:asciiname":"Kykva",
    "gn:country_code":"RU",
    "gn:dem":185,
    "gn:feature_class":"P",
    "gn:feature_code":"PPL",
    "gn:name":"Kykva",
    "gn:population":0,
    "gn:timezone":"Europe/Samara",
    "iso:country":"RU",
    "name:eng_x_preferred":[
        "Kykva"
    ],
    "name:nor_x_preferred":[
        "Kykva"
    ],
    "name:rus_x_preferred":[
        "\u041a\u044b\u043a\u0432\u0430"
    ],
    "wof:name":"Kykva",
    "wof:placetype":"locality"
},
  "geometry": {"coordinates":[53.8409,57.3638],"type":"Point"}
}