{
  "type": "Feature",
  "properties": {
    "gn:admin1_code":"8",
    "gn:asciiname":"Tikhiy Klyuch",
    "gn:country_code":"RU",
    "gn:dem":495,
    "gn:feature_class":"P",
    "gn:feature_code":"PPL",
    "gn:name":"Tikhiy Klyuch",
    "gn:population":0,
    "gn:timezone":"Asia/Yekaterinburg",
    "iso:country":"RU",
    "name:rus_x_preferred":[
        "\u0422\u0438\u0445\u0438\u0439 \u041a\u043b\u044e\u0447"
    ],
    "wof:name":"Tikhiy Klyuch",
    "wof:placetype":"locality"
},
  "geometry": {"coordinates":[57.8446,53.9581],"type":"Point"}
}