{
  "type": "Feature",
  "properties": {
    "gn:admin1_code":"33",
    "gn:asciiname":"Gorushki",
    "gn:country_code":"RU",
    "gn:dem":241,
    "gn:feature_class":"P",
    "gn:feature_code":"PPL",
    "gn:name":"Gorushki",
    "gn:population":0,
    "gn:timezone":"Europe/Kirov",
    "iso:country":"RU",
    "name:rus_x_preferred":[
        "\u0413\u043e\u0440\u0443\u0448\u043a\u0438"
    ],
    "wof:name":"Gorushki",
    "wof:placetype":"locality"
},
  "geometry": {"coordinates":[51.73333,58.56667],"type":"Point"}
}