{
  "type": "Feature",
  "properties": {
    "gn:admin1_code":"42.0",
    "gn:asciiname":"Glazhevo",
    "gn:country_code":"RU",
    "gn:dem":48,
    "gn:feature_class":"P",
    "gn:feature_code":"PPL",
    "gn:name":"Glazhevo",
    "gn:population":0,
    "gn:timezone":"Europe/Moscow",
    "iso:country":"RU",
    "name:rus_x_preferred":[
        "\u0413\u043b\u0430\u0436\u0435\u0432\u043e"
    ],
    "wof:name":"Glazhevo",
    "wof:placetype":"locality"
},
  "geometry": {"coordinates":[32.11488,59.67574000000001],"type":"Point"}
}