{
  "type": "Feature",
  "properties": {
    "gn:admin1_code":"60",
    "gn:asciiname":"Noskovo",
    "gn:country_code":"RU",
    "gn:dem":134,
    "gn:feature_class":"P",
    "gn:feature_code":"PPL",
    "gn:name":"Noskovo",
    "gn:population":0,
    "gn:timezone":"Europe/Moscow",
    "iso:country":"RU",
    "name:rus_x_preferred":[
        "\u041d\u043e\u0441\u043a\u043e\u0432\u043e"
    ],
    "name:und_x_variant":[
        "\u041d\u043e\u0441\u043a\u043e\u0432\u043e"
    ],
    "wof:name":"Noskovo",
    "wof:placetype":"locality"
},
  "geometry": {"coordinates":[30.43333,56.31667],"type":"Point"}
}