{
  "type": "Feature",
  "properties": {
    "gn:admin1_code":"13",
    "gn:asciiname":"Sukharysh",
    "gn:country_code":"RU",
    "gn:dem":238,
    "gn:feature_class":"P",
    "gn:feature_code":"PPL",
    "gn:name":"Sukharysh",
    "gn:population":0,
    "gn:timezone":"Asia/Yekaterinburg",
    "iso:country":"RU",
    "name:rus_x_preferred":[
        "\u0421\u0443\u0445\u0430\u0440\u044b\u0448"
    ],
    "name:und_x_variant":[
        "\u0421\u0443\u0445\u0430\u0440\u044b\u0448"
    ],
    "wof:name":"Sukharysh",
    "wof:placetype":"locality"
},
  "geometry": {"coordinates":[61.0909,54.6781],"type":"Point"}
}