{
  "type": "Feature",
  "properties": {
    "gn:admin1_code":"70",
    "gn:asciiname":"Golubinyy",
    "gn:country_code":"RU",
    "gn:dem":92,
    "gn:feature_class":"P",
    "gn:feature_code":"PPL",
    "gn:name":"Golubinyy",
    "gn:population":0,
    "gn:timezone":"Europe/Moscow",
    "iso:country":"RU",
    "name:rus_x_preferred":[
        "\u0413\u043e\u043b\u0443\u0431\u0438\u043d\u044b\u0439"
    ],
    "name:und_x_variant":[
        "\u0413\u043e\u043b\u0443\u0431\u0438\u043d\u044b\u0439"
    ],
    "wof:name":"Golubinyy",
    "wof:placetype":"locality"
},
  "geometry": {"coordinates":[43.91917,45.57889],"type":"Point"}
}