{
  "type": "Feature",
  "properties": {
    "gn:admin1_code":"70",
    "gn:asciiname":"Makukhovskiy",
    "gn:country_code":"RU",
    "gn:dem":255,
    "gn:feature_class":"P",
    "gn:feature_code":"PPL",
    "gn:name":"Makukhovskiy",
    "gn:population":0,
    "gn:timezone":"Europe/Moscow",
    "iso:country":"RU",
    "name:rus_x_preferred":[
        "\u041c\u0430\u043a\u0443\u0445\u043e\u0432\u0441\u043a\u0438\u0439"
    ],
    "wof:name":"Makukhovskiy",
    "wof:placetype":"locality"
},
  "geometry": {"coordinates":[43.81889,43.99778],"type":"Point"}
}