{
  "type": "Feature",
  "properties": {
    "gn:admin1_code":"24",
    "gn:asciiname":"Bergin",
    "gn:country_code":"RU",
    "gn:dem":-11,
    "gn:feature_class":"P",
    "gn:feature_code":"PPL",
    "gn:name":"Bergin",
    "gn:population":0,
    "gn:timezone":"Europe/Moscow",
    "iso:country":"RU",
    "name:eng_x_preferred":[
        "Polynnyy"
    ],
    "name:nor_x_preferred":[
        "Polynnoje"
    ],
    "name:rus_x_preferred":[
        "\u041f\u043e\u043b\u044b\u043d\u043d\u043e\u0435"
    ],
    "name:rus_x_variant":[
        "\u0411\u0435\u0440\u0433\u0438\u043d"
    ],
    "name:und_x_variant":[
        "Khazyn",
        "Bergin",
        "Khazyk",
        "Polynnoye"
    ],
    "wof:name":"Bergin",
    "wof:placetype":"locality"
},
  "geometry": {"coordinates":[46.9403,46.8439],"type":"Point"}
}