{
  "type": "Feature",
  "properties": {
    "gn:admin1_code":"8",
    "gn:asciiname":"Sof'ino",
    "gn:country_code":"RU",
    "gn:dem":125,
    "gn:feature_class":"P",
    "gn:feature_code":"PPL",
    "gn:name":"Sof\u2019ino",
    "gn:population":0,
    "gn:timezone":"Asia/Yekaterinburg",
    "iso:country":"RU",
    "name:rus_x_preferred":[
        "\u0421\u043e\u0444\u044c\u0438\u043d\u043e"
    ],
    "name:und_x_variant":[
        "Sof\u2019ino"
    ],
    "wof:name":"Sof'ino",
    "wof:placetype":"locality"
},
  "geometry": {"coordinates":[56.25482,54.04828000000001],"type":"Point"}
}