{
  "type": "Feature",
  "properties": {
    "gn:admin1_code":"73",
    "gn:asciiname":"Nizhniy Simet",
    "gn:country_code":"RU",
    "gn:dem":127,
    "gn:feature_class":"P",
    "gn:feature_code":"PPL",
    "gn:name":"Nizhniy Simet",
    "gn:population":0,
    "gn:timezone":"Europe/Moscow",
    "iso:country":"RU",
    "name:rus_x_preferred":[
        "\u041d\u0438\u0436\u043d\u0438\u0439 \u0421\u0438\u043c\u0435\u0442"
    ],
    "name:und_x_variant":[
        "Nizhniy Semit",
        "Nizhniy Simet"
    ],
    "wof:name":"Nizhniy Simet",
    "wof:placetype":"locality"
},
  "geometry": {"coordinates":[50.2248,56.032],"type":"Point"}
}