{
  "type": "Feature",
  "properties": {
    "gn:admin1_code":"38",
    "gn:asciiname":"Krasnolit",
    "gn:country_code":"RU",
    "gn:dem":22,
    "gn:feature_class":"P",
    "gn:feature_code":"PPL",
    "gn:name":"Krasnolit",
    "gn:population":0,
    "gn:timezone":"Europe/Moscow",
    "iso:country":"RU",
    "name:rus_x_preferred":[
        "\u041a\u0440\u0430\u0441\u043d\u043e\u043b\u0438\u0442"
    ],
    "wof:name":"Krasnolit",
    "wof:placetype":"locality"
},
  "geometry": {"coordinates":[38.84243,45.15341],"type":"Point"}
}