{
  "type": "Feature",
  "properties": {
    "gn:admin1_code":"61",
    "gn:asciiname":"Potapov",
    "gn:country_code":"RU",
    "gn:dem":23,
    "gn:feature_class":"P",
    "gn:feature_code":"PPL",
    "gn:name":"Potapov",
    "gn:population":0,
    "gn:timezone":"Europe/Moscow",
    "iso:country":"RU",
    "name:eng_x_preferred":[
        "Potapov"
    ],
    "name:nor_x_preferred":[
        "Potapov"
    ],
    "name:rus_x_preferred":[
        "\u041f\u043e\u0442\u0430\u043f\u043e\u0432"
    ],
    "name:und_x_variant":[
        "\u041f\u043e\u0442\u0430\u043f\u043e\u0432",
        "Potapov"
    ],
    "wof:name":"Potapov",
    "wof:placetype":"locality"
},
  "geometry": {"coordinates":[41.93818,47.47132],"type":"Point"}
}