{
  "type": "Feature",
  "properties": {
    "gn:admin1_code":"91",
    "gn:asciiname":"Zubenkino",
    "gn:country_code":"RU",
    "gn:dem":258,
    "gn:feature_class":"P",
    "gn:feature_code":"PPL",
    "gn:name":"Zubenkino",
    "gn:population":0,
    "gn:timezone":"Asia/Krasnoyarsk",
    "iso:country":"RU",
    "name:eng_x_preferred":[
        "Zubenkina"
    ],
    "name:nor_x_preferred":[
        "Zubenkino"
    ],
    "name:rus_x_preferred":[
        "\u0417\u0443\u0431\u0435\u043d\u043a\u0438\u043d\u043e"
    ],
    "name:und_x_variant":[
        "Zubenkina",
        "Zubenkino"
    ],
    "wof:name":"Zubenkino",
    "wof:placetype":"locality"
},
  "geometry": {"coordinates":[96.69410000000001,56.2786],"type":"Point"}
}