{
  "type": "Feature",
  "properties": {
    "gn:admin1_code":"86.0",
    "gn:asciiname":"Utinovka",
    "gn:country_code":"RU",
    "gn:dem":216,
    "gn:feature_class":"P",
    "gn:feature_code":"PPL",
    "gn:name":"Utinovka",
    "gn:population":0,
    "gn:timezone":"Europe/Moscow",
    "iso:country":"RU",
    "name:rus_x_preferred":[
        "\u0423\u0442\u0438\u043d\u043e\u0432\u043a\u0430"
    ],
    "wof:name":"Utinovka",
    "wof:placetype":"locality"
},
  "geometry": {"coordinates":[40.8838,51.0595],"type":"Point"}
}