{
  "type": "Feature",
  "properties": {
    "gn:admin1_code":"61",
    "gn:asciiname":"Novobelyayevskiy",
    "gn:country_code":"RU",
    "gn:dem":58,
    "gn:feature_class":"P",
    "gn:feature_code":"PPL",
    "gn:name":"Novobelyayevskiy",
    "gn:population":0,
    "gn:timezone":"Europe/Moscow",
    "iso:country":"RU",
    "name:eng_x_preferred":[
        "Novobelyayevskiy"
    ],
    "name:nor_x_preferred":[
        "Novobeljaevskij"
    ],
    "name:rus_x_preferred":[
        "\u041d\u043e\u0432\u043e\u0431\u0435\u043b\u044f\u0435\u0432\u0441\u043a\u0438\u0439"
    ],
    "wof:name":"Novobelyayevskiy",
    "wof:placetype":"locality"
},
  "geometry": {"coordinates":[43.5629,47.2529],"type":"Point"}
}