{
  "type": "Feature",
  "properties": {
    "gn:admin1_code":"85",
    "gn:asciiname":"Perkhinskaya",
    "gn:country_code":"RU",
    "gn:dem":48,
    "gn:feature_class":"P",
    "gn:feature_code":"PPL",
    "gn:name":"Perkhinskaya",
    "gn:population":0,
    "gn:timezone":"Europe/Moscow",
    "iso:country":"RU",
    "name:eng_x_preferred":[
        "Perkhinskaya"
    ],
    "name:nor_x_preferred":[
        "Perkhinskaja"
    ],
    "name:rus_x_preferred":[
        "\u041f\u0435\u0440\u0445\u0438\u043d\u0441\u043a\u0430\u044f"
    ],
    "name:und_x_variant":[
        "Nizhnyaya Vodlitsa-Perkhinskaya",
        "Perhinskaja"
    ],
    "wof:name":"Perkhinskaya",
    "wof:placetype":"locality"
},
  "geometry": {"coordinates":[35.74293,60.83011],"type":"Point"}
}