{
  "type": "Feature",
  "properties": {
    "gn:admin1_code":"25.0",
    "gn:asciiname":"Verkhneye Ashkovo",
    "gn:country_code":"RU",
    "gn:dem":191,
    "gn:feature_class":"P",
    "gn:feature_code":"PPL",
    "gn:name":"Verkhneye Ashkovo",
    "gn:population":0,
    "gn:timezone":"Europe/Moscow",
    "iso:country":"RU",
    "name:und_x_variant":[
        "Ashkovo-Verkhneye",
        "Verkhneye Ashkovo"
    ],
    "wof:name":"Verkhneye Ashkovo",
    "wof:placetype":"locality"
},
  "geometry": {"coordinates":[34.75366,53.85296999999999],"type":"Point"}
}