{
  "type": "Feature",
  "properties": {
    "gn:admin1_code":"85.0",
    "gn:asciiname":"Dmitriyevo",
    "gn:country_code":"RU",
    "gn:dem":107,
    "gn:feature_class":"P",
    "gn:feature_code":"PPL",
    "gn:name":"Dmitriyevo",
    "gn:population":0,
    "gn:timezone":"Europe/Moscow",
    "iso:country":"RU",
    "name:rus_x_preferred":[
        "\u0414\u043c\u0438\u0442\u0440\u0438\u0435\u0432\u043e"
    ],
    "name:und_x_variant":[
        "Dmitriyevskoye",
        "Dmitriyevo",
        "\u0414\u043c\u0438\u0442\u0440\u0438\u0435\u0432\u043e"
    ],
    "wof:name":"Dmitriyevo",
    "wof:placetype":"locality"
},
  "geometry": {"coordinates":[44.44156,60.45967],"type":"Point"}
}