{
  "type": "Feature",
  "properties": {
    "gn:admin1_code":"13",
    "gn:asciiname":"Novoandreyevka",
    "gn:country_code":"RU",
    "gn:dem":299,
    "gn:feature_class":"P",
    "gn:feature_code":"PPL",
    "gn:name":"Novoandreyevka",
    "gn:population":0,
    "gn:timezone":"Asia/Yekaterinburg",
    "iso:country":"RU",
    "name:eng_x_preferred":[
        "Novoandreyevka"
    ],
    "name:nor_x_preferred":[
        "Novoandrejevka"
    ],
    "name:rus_x_preferred":[
        "\u041d\u043e\u0432\u043e\u0430\u043d\u0434\u0440\u0435\u0435\u0432\u043a\u0430"
    ],
    "name:und_x_variant":[
        "Novo-Andreyevskiy",
        "Novoandreyevskoye",
        "\u041d\u043e\u0432\u043e\u0430\u043d\u0434\u0440\u0435\u0435\u0432\u043a\u0430",
        "Novoandreyevka"
    ],
    "wof:name":"Novoandreyevka",
    "wof:placetype":"locality"
},
  "geometry": {"coordinates":[60.2282,55.335],"type":"Point"}
}