{
  "type": "Feature",
  "properties": {
    "gn:admin1_code":"41",
    "gn:asciiname":"Kolodez'ki",
    "gn:country_code":"RU",
    "gn:dem":185,
    "gn:feature_class":"P",
    "gn:feature_code":"PPL",
    "gn:name":"Kolodez\u2019ki",
    "gn:population":0,
    "gn:timezone":"Europe/Moscow",
    "iso:country":"RU",
    "name:rus_x_preferred":[
        "\u041a\u043e\u043b\u043e\u0434\u0435\u0437\u044c\u043a\u0438"
    ],
    "name:und_x_variant":[
        "Kolodez\u2019ki",
        "\u041a\u043e\u043b\u043e\u0434\u0435\u0437\u044c\u043a\u0438"
    ],
    "wof:name":"Kolodez'ki",
    "wof:placetype":"locality"
},
  "geometry": {"coordinates":[36.79222,51.82167000000001],"type":"Point"}
}