{
  "type": "Feature",
  "properties": {
    "gn:admin1_code":"67",
    "gn:asciiname":"Usovka",
    "gn:country_code":"RU",
    "gn:dem":26,
    "gn:feature_class":"P",
    "gn:feature_code":"PPL",
    "gn:name":"Usovka",
    "gn:population":0,
    "gn:timezone":"Europe/Saratov",
    "iso:country":"RU",
    "name:eng_x_preferred":[
        "Usovka"
    ],
    "name:nor_x_preferred":[
        "Usovka"
    ],
    "name:rus_x_preferred":[
        "\u0423\u0441\u043e\u0432\u043a\u0430"
    ],
    "wof:name":"Usovka",
    "wof:placetype":"locality"
},
  "geometry": {"coordinates":[46.48478,51.80358],"type":"Point"}
}