{
  "type": "Feature",
  "properties": {
    "gn:admin1_code":"25",
    "gn:asciiname":"Staroskakovskoye",
    "gn:country_code":"RU",
    "gn:dem":132,
    "gn:feature_class":"P",
    "gn:feature_code":"PPL",
    "gn:name":"Staroskakovskoye",
    "gn:population":0,
    "gn:timezone":"Europe/Moscow",
    "iso:country":"RU",
    "name:rus_x_preferred":[
        "\u0421\u0442\u0430\u0440\u043e\u0441\u043a\u0430\u043a\u043e\u0432\u0441\u043a\u043e\u0435"
    ],
    "name:und_x_variant":[
        "Staro-Skakovo",
        "Staroskakovskoye"
    ],
    "wof:name":"Staroskakovskoye",
    "wof:placetype":"locality"
},
  "geometry": {"coordinates":[35.98216,54.57397],"type":"Point"}
}