{
  "type": "Feature",
  "properties": {
    "gn:admin1_code":"63",
    "gn:asciiname":"Kazach'ye",
    "gn:country_code":"RU",
    "gn:dem":41,
    "gn:feature_class":"P",
    "gn:feature_code":"PPL",
    "gn:name":"Kazach\u2019ye",
    "gn:population":0,
    "gn:timezone":"Asia/Vladivostok",
    "iso:country":"RU",
    "name:eng_x_preferred":[
        "Kazach'ye"
    ],
    "name:nor_x_preferred":[
        "Kazatsje"
    ],
    "name:rus_x_preferred":[
        "\u041a\u0430\u0437\u0430\u0447\u044c\u0435"
    ],
    "name:und_x_variant":[
        "Kazache",
        "Kazach\u2019ye"
    ],
    "wof:name":"Kazach'ye",
    "wof:placetype":"locality"
},
  "geometry": {"coordinates":[136.20554999999999,70.74153000000003],"type":"Point"}
}