{
  "type": "Feature",
  "properties": {
    "gn:admin1_code":"60",
    "gn:asciiname":"Botakovo",
    "gn:country_code":"RU",
    "gn:dem":152,
    "gn:feature_class":"P",
    "gn:feature_code":"PPL",
    "gn:name":"Botakovo",
    "gn:population":0,
    "gn:timezone":"Europe/Moscow",
    "iso:country":"RU",
    "name:rus_x_preferred":[
        "\u0411\u043e\u0442\u0430\u043a\u043e\u0432\u043e"
    ],
    "wof:name":"Botakovo",
    "wof:placetype":"locality"
},
  "geometry": {"coordinates":[29.0688,56.5563],"type":"Point"}
}