{
  "type": "Feature",
  "properties": {
    "gn:admin1_code":"41.0",
    "gn:asciiname":"Bykanovskiye Vyselki",
    "gn:country_code":"RU",
    "gn:dem":215,
    "gn:feature_class":"P",
    "gn:feature_code":"PPL",
    "gn:name":"Bykanovskiye Vyselki",
    "gn:population":0,
    "gn:timezone":"Europe/Moscow",
    "iso:country":"RU",
    "name:rus_x_preferred":[
        "\u0411\u044b\u043a\u0430\u043d\u043e\u0432\u0441\u043a\u0438\u0435 \u0412\u044b\u0441\u0435\u043b\u043a\u0438"
    ],
    "wof:name":"Bykanovskiye Vyselki",
    "wof:placetype":"locality"
},
  "geometry": {"coordinates":[36.1225,51.33889],"type":"Point"}
}