{
  "type": "Feature",
  "properties": {
    "gn:admin1_code":"56",
    "gn:asciiname":"Khvoshchevka",
    "gn:country_code":"RU",
    "gn:dem":189,
    "gn:feature_class":"P",
    "gn:feature_code":"PPL",
    "gn:name":"Khvoshch\u00ebvka",
    "gn:population":0,
    "gn:timezone":"Europe/Moscow",
    "iso:country":"RU",
    "name:rus_x_preferred":[
        "\u0425\u0432\u043e\u0449\u0451\u0432\u043a\u0430"
    ],
    "name:und_x_variant":[
        "Khvoshch\u00ebvka",
        "\u0425\u0432\u043e\u0449\u0451\u0432\u043a\u0430"
    ],
    "wof:name":"Khvoshchevka",
    "wof:placetype":"locality"
},
  "geometry": {"coordinates":[37.65183,52.54065],"type":"Point"}
}