{
  "type": "Feature",
  "properties": {
    "gn:admin1_code":"46.0",
    "gn:asciiname":"Dubrovskoye",
    "gn:country_code":"RU",
    "gn:dem":116,
    "gn:feature_class":"P",
    "gn:feature_code":"PPL",
    "gn:name":"Dubrovskoye",
    "gn:population":0,
    "gn:timezone":"Europe/Moscow",
    "iso:country":"RU",
    "name:rus_x_preferred":[
        "\u0414\u0443\u0431\u0440\u043e\u0432\u0441\u043a\u043e\u0435"
    ],
    "name:und_x_variant":[
        "Staraya Puza",
        "Dubrovskoye",
        "\u0414\u0443\u0431\u0440\u043e\u0432\u0441\u043a\u043e\u0435"
    ],
    "wof:name":"Dubrovskoye",
    "wof:placetype":"locality"
},
  "geometry": {"coordinates":[45.42267,54.65235],"type":"Point"}
}