{
  "type": "Feature",
  "properties": {
    "gn:admin1_code":"40",
    "gn:asciiname":"Kalmyk-Abdrashevo",
    "gn:country_code":"RU",
    "gn:dem":169,
    "gn:feature_class":"P",
    "gn:feature_code":"PPL",
    "gn:name":"Kalmyk-Abdrashevo",
    "gn:population":0,
    "gn:timezone":"Asia/Yekaterinburg",
    "iso:country":"RU",
    "name:rus_x_preferred":[
        "\u041a\u0430\u043b\u043c\u044b\u043a-\u0410\u0431\u0434\u0440\u0430\u0448\u0435\u0432\u043e"
    ],
    "name:und_x_variant":[
        "\u041a\u0430\u043b\u043c\u044b\u043a-\u0410\u0431\u0434\u0440\u0430\u0448\u0435\u0432\u043e"
    ],
    "wof:name":"Kalmyk-Abdrashevo",
    "wof:placetype":"locality"
},
  "geometry": {"coordinates":[62.7466,54.9874],"type":"Point"}
}