{
  "type": "Feature",
  "properties": {
    "gn:admin1_code":"40",
    "gn:asciiname":"Komsomol'skaya",
    "gn:country_code":"RU",
    "gn:dem":138,
    "gn:feature_class":"P",
    "gn:feature_code":"PPL",
    "gn:name":"Komsomol\u2019skaya",
    "gn:population":0,
    "gn:timezone":"Asia/Yekaterinburg",
    "iso:country":"RU",
    "name:eng_x_preferred":[
        "Komsomol'skaya"
    ],
    "name:nor_x_preferred":[
        "Komsomolskaja"
    ],
    "name:rus_x_preferred":[
        "\u041a\u043e\u043c\u0441\u043e\u043c\u043e\u043b\u044c\u0441\u043a\u0430\u044f"
    ],
    "name:und_x_variant":[
        "\u041a\u043e\u043c\u0441\u043e\u043c\u043e\u043b\u044c\u0441\u043a\u0430\u044f",
        "Komsomol\u2019skaya"
    ],
    "wof:name":"Komsomol'skaya",
    "wof:placetype":"locality"
},
  "geometry": {"coordinates":[67.12860999999999,55.90889],"type":"Point"}
}