{
  "type": "Feature",
  "properties": {
    "gn:admin1_code":"78",
    "gn:asciiname":"Vostok",
    "gn:country_code":"RU",
    "gn:dem":137,
    "gn:feature_class":"P",
    "gn:feature_code":"PPL",
    "gn:name":"Vostok",
    "gn:population":0,
    "gn:timezone":"Asia/Yekaterinburg",
    "iso:country":"RU",
    "name:ara_x_preferred":[
        "\u0641\u0648\u0633\u062a\u0648\u0643"
    ],
    "name:aze_x_preferred":[
        "Vostok"
    ],
    "name:ben_x_preferred":[
        "\u09ad\u09b8\u09cd\u099f\u0995"
    ],
    "name:bul_x_preferred":[
        "\u0412\u043e\u0441\u0442\u043e\u043a"
    ],
    "name:cat_x_preferred":[
        "Vostok"
    ],
    "name:ceb_x_preferred":[
        "Vostok"
    ],
    "name:ces_x_preferred":[
        "Vostok"
    ],
    "name:deu_x_preferred":[
        "Wostok"
    ],
    "name:ell_x_preferred":[
        "\u0392\u03bf\u03c3\u03c4\u03cc\u03ba"
    ],
    "name:est_x_preferred":[
        "Vostok"
    ],
    "name:fas_x_preferred":[
        "\u0648\u0633\u062a\u0648\u06a9"
    ],
    "name:fin_x_preferred":[
        "Vostok"
    ],
    "name:fra_x_preferred":[
        "Vostok"
    ],
    "name:heb_x_preferred":[
        "\u05d5\u05d5\u05e1\u05d8\u05d5\u05e7"
    ],
    "name:hin_x_preferred":[
        "\u0935\u094b\u0938\u094d\u0924\u094b\u0915"
    ],
    "name:hun_x_preferred":[
        "Vosztok"
    ],
    "name:ind_x_preferred":[
        "Vostok"
    ],
    "name:ita_x_preferred":[
        "Vostok"
    ],
    "name:jpn_x_preferred":[
        "\u30dc\u30b9\u30c8\u30fc\u30af"
    ],
    "name:kor_x_preferred":[
        "\ubcf4\uc2a4\ud1a0\ud06c"
    ],
    "name:ltz_x_preferred":[
        "Wostok"
    ],
    "name:nld_x_preferred":[
        "Vostok"
    ],
    "name:nor_x_preferred":[
        "Vostok"
    ],
    "name:pol_x_preferred":[
        "Wostok"
    ],
    "name:por_x_preferred":[
        "Vostok"
    ],
    "name:rus_x_preferred":[
        "\u0412\u043e\u0441\u0442\u043e\u043a"
    ],
    "name:slk_x_preferred":[
        "Vostok"
    ],
    "name:slv_x_preferred":[
        "Vostok"
    ],
    "name:spa_x_preferred":[
        "Vostok"
    ],
    "name:swa_x_preferred":[
        "Vostok"
    ],
    "name:swe_x_preferred":[
        "Vostok"
    ],
    "name:tur_x_preferred":[
        "Vostok"
    ],
    "name:ukr_x_preferred":[
        "\u0412\u043e\u0441\u0442\u043e\u043a"
    ],
    "name:urd_x_preferred":[
        "\u0648\u0648\u0633\u0679\u0648\u06a9"
    ],
    "name:vie_x_preferred":[
        "\u0110\u1ea3o Vostok"
    ],
    "wof:name":"Vostok",
    "wof:placetype":"locality"
},
  "geometry": {"coordinates":[67.19923,56.03795],"type":"Point"}
}