{
  "type": "Feature",
  "properties": {
    "gn:admin1_code":"43",
    "gn:asciiname":"Goryushki",
    "gn:country_code":"RU",
    "gn:dem":148,
    "gn:feature_class":"P",
    "gn:feature_code":"PPL",
    "gn:name":"Goryushki",
    "gn:population":0,
    "gn:timezone":"Europe/Moscow",
    "iso:country":"RU",
    "name:rus_x_preferred":[
        "\u0413\u043e\u0440\u044e\u0448\u043a\u0438"
    ],
    "name:und_x_variant":[
        "\u0413\u043e\u0440\u044e\u0448\u043a\u0438"
    ],
    "wof:name":"Goryushki",
    "wof:placetype":"locality"
},
  "geometry": {"coordinates":[39.89487,53.41403],"type":"Point"}
}