{
  "type": "Feature",
  "properties": {
    "gn:admin1_code":"85",
    "gn:asciiname":"Kosyakovo",
    "gn:country_code":"RU",
    "gn:dem":160,
    "gn:feature_class":"P",
    "gn:feature_code":"PPL",
    "gn:name":"Kosyakovo",
    "gn:population":0,
    "gn:timezone":"Europe/Moscow",
    "iso:country":"RU",
    "name:rus_x_preferred":[
        "\u041a\u043e\u0441\u044f\u043a\u043e\u0432\u043e"
    ],
    "name:und_x_variant":[
        "\u041a\u043e\u0441\u044f\u043a\u043e\u0432\u043e"
    ],
    "wof:name":"Kosyakovo",
    "wof:placetype":"locality"
},
  "geometry": {"coordinates":[39.30644,59.35461],"type":"Point"}
}