{
  "type": "Feature",
  "properties": {
    "gn:admin1_code":"45",
    "gn:asciiname":"Bol'shoy Kuleyal",
    "gn:country_code":"RU",
    "gn:dem":181,
    "gn:feature_class":"P",
    "gn:feature_code":"PPL",
    "gn:name":"Bol\u2019shoy Kuleyal",
    "gn:population":0,
    "gn:timezone":"Europe/Moscow",
    "iso:country":"RU",
    "name:rus_x_preferred":[
        "\u0411\u043e\u043b\u044c\u0448\u043e\u0439 \u041a\u0443\u043b\u0435\u044f\u043b"
    ],
    "name:und_x_variant":[
        "Kul\u2019yal",
        "Bol\u2019shoy Kuleyal"
    ],
    "wof:name":"Bol'shoy Kuleyal",
    "wof:placetype":"locality"
},
  "geometry": {"coordinates":[48.91389,56.3825],"type":"Point"}
}