{
  "type": "Feature",
  "properties": {
    "gn:admin1_code":"17",
    "gn:asciiname":"Burkhimakhi",
    "gn:country_code":"RU",
    "gn:dem":1180,
    "gn:feature_class":"P",
    "gn:feature_code":"PPL",
    "gn:name":"Burkhimakhi",
    "gn:population":0,
    "gn:timezone":"Europe/Moscow",
    "iso:country":"RU",
    "name:rus_x_preferred":[
        "\u0411\u0443\u0440\u0445\u0438\u043c\u0430\u0445\u0438"
    ],
    "wof:name":"Burkhimakhi",
    "wof:placetype":"locality"
},
  "geometry": {"coordinates":[47.58607,42.3065],"type":"Point"}
}