{
  "type": "Feature",
  "properties": {
    "gn:admin1_code":"55",
    "gn:asciiname":"Skobelevo",
    "gn:country_code":"RU",
    "gn:dem":123,
    "gn:feature_class":"P",
    "gn:feature_code":"PPL",
    "gn:name":"Skobelevo",
    "gn:population":0,
    "gn:timezone":"Asia/Yekaterinburg",
    "iso:country":"RU",
    "name:bul_x_preferred":[
        "\u0421\u043a\u043e\u0431\u0435\u043b\u0435\u0432\u043e"
    ],
    "name:ceb_x_preferred":[
        "Skobelevo"
    ],
    "name:fra_x_preferred":[
        "Skobelevo"
    ],
    "name:pol_x_preferred":[
        "Skobelewo"
    ],
    "name:ron_x_preferred":[
        "Skobelevo"
    ],
    "name:rus_x_preferred":[
        "\u0421\u043a\u043e\u0431\u0435\u043b\u0435\u0432\u043e"
    ],
    "name:swe_x_preferred":[
        "Skobelevo"
    ],
    "name:ukr_x_preferred":[
        "\u0421\u043a\u043e\u0431\u0435\u043b\u0435\u0432\u043e"
    ],
    "wof:name":"Skobelevo",
    "wof:placetype":"locality"
},
  "geometry": {"coordinates":[52.3275,53.3629],"type":"Point"}
}