{
  "type": "Feature",
  "properties": {
    "gn:admin1_code":"32",
    "gn:asciiname":"Yuil'skiy Gorodok",
    "gn:country_code":"RU",
    "gn:dem":63,
    "gn:feature_class":"P",
    "gn:feature_code":"PPL",
    "gn:name":"Yuil\u2019skiy Gorodok",
    "gn:population":0,
    "gn:timezone":"Asia/Yekaterinburg",
    "iso:country":"RU",
    "name:und_x_variant":[
        "Yurty Yuil\u2019skiy Gordok",
        "Yuil\u2019skiy Gorodok"
    ],
    "wof:name":"Yuil'skiy Gorodok",
    "wof:placetype":"locality"
},
  "geometry": {"coordinates":[69.16667,63.55],"type":"Point"}
}