{
  "type": "Feature",
  "properties": {
    "gn:admin1_code":"91",
    "gn:asciiname":"Novomikhaylovka",
    "gn:country_code":"RU",
    "gn:dem":497,
    "gn:feature_class":"P",
    "gn:feature_code":"PPL",
    "gn:name":"Novomikhaylovka",
    "gn:population":0,
    "gn:timezone":"Asia/Krasnoyarsk",
    "iso:country":"RU",
    "name:rus_x_preferred":[
        "\u041d\u043e\u0432\u043e\u043c\u0438\u0445\u0430\u0439\u043b\u043e\u0432\u043a\u0430"
    ],
    "name:und_x_variant":[
        "Novaya Mikhaylovka",
        "Novomikhaylovka"
    ],
    "wof:name":"Novomikhaylovka",
    "wof:placetype":"locality"
},
  "geometry": {"coordinates":[93.7778,55.5629],"type":"Point"}
}