{
  "type": "Feature",
  "properties": {
    "gn:admin1_code":"33",
    "gn:asciiname":"Zapolena",
    "gn:country_code":"RU",
    "gn:dem":123,
    "gn:feature_class":"P",
    "gn:feature_code":"PPL",
    "gn:name":"Zapolena",
    "gn:population":0,
    "gn:timezone":"Europe/Kirov",
    "iso:country":"RU",
    "name:rus_x_preferred":[
        "\u0417\u0430\u043f\u043e\u043b\u0435\u043d\u0430"
    ],
    "name:und_x_variant":[
        "Zapolyane",
        "Zapolena"
    ],
    "wof:name":"Zapolena",
    "wof:placetype":"locality"
},
  "geometry": {"coordinates":[49.3527,57.332],"type":"Point"}
}