{
  "type": "Feature",
  "properties": {
    "gn:admin1_code":"61",
    "gn:asciiname":"Zagotskot",
    "gn:country_code":"RU",
    "gn:dem":108,
    "gn:feature_class":"P",
    "gn:feature_code":"PPL",
    "gn:name":"Zagotskot",
    "gn:population":0,
    "gn:timezone":"Europe/Moscow",
    "iso:country":"RU",
    "name:und_x_variant":[
        "\u0417\u0430\u0433\u043e\u0442\u0441\u043a\u043e\u0442"
    ],
    "wof:name":"Zagotskot",
    "wof:placetype":"locality"
},
  "geometry": {"coordinates":[40.97354,46.68173],"type":"Point"}
}