{
  "type": "Feature",
  "properties": {
    "gn:country":"RU",
    "gn:fcode":"PPLX",
    "gn:population":5136,
    "iso:country":"RU",
    "name:ceb_x_preferred":[
        "Shalinskiy Rayon"
    ],
    "name:che_x_preferred":[
        "Cemzavod"
    ],
    "name:che_x_variant":[
        "\u00c7\u00fcyrin-Evl",
        "\u0426\u0435\u043c\u0437\u0430\u0432\u043e\u0434",
        "\u0427\u0443\u044c\u0439\u0440\u0438\u043d-\u042d\u0432\u043b",
        "\u0428\u0435\u043b\u0430\u043d \u043a\u04c0\u043e\u0448\u0442"
    ],
    "name:deu_x_preferred":[
        "Schalinski rajon"
    ],
    "name:eng_x_preferred":[
        "Chiri-Yurt"
    ],
    "name:eng_x_variant":[
        "Shalinsky District"
    ],
    "name:est_x_preferred":[
        "\u0160ali rajoon"
    ],
    "name:hun_x_preferred":[
        "Sali j\u00e1r\u00e1s"
    ],
    "name:hye_x_preferred":[
        "\u0547\u0561\u056c\u056b\u0576\u057d\u056f\u056b \u0577\u0580\u057b\u0561\u0576"
    ],
    "name:ita_x_preferred":[
        "\u0160alinskij rajon"
    ],
    "name:kor_x_preferred":[
        "\uc0ec\ub9b0\uc2a4\ud0a4 \uad70"
    ],
    "name:nld_x_preferred":[
        "District Sjalinski"
    ],
    "name:nor_x_preferred":[
        "Tsjiri-Jurt"
    ],
    "name:oss_x_preferred":[
        "\u0428\u0430\u043b\u0438\u0439\u044b \u0440\u0430\u0439\u043e\u043d"
    ],
    "name:pol_x_preferred":[
        "Rejon szali\u0144ski"
    ],
    "name:rus_x_preferred":[
        "\u0427\u0438\u0440\u0438-\u042e\u0440\u0442"
    ],
    "name:rus_x_variant":[
        "\u010ciri-Jurt",
        "Nadre\u010d\u2019e",
        "\u041d\u0430\u0434\u0440\u0435\u0447\u044c\u0435",
        "\u0428\u0430\u043b\u0438\u043d\u0441\u043a\u0438\u0439 \u0440\u0430\u0439\u043e\u043d"
    ],
    "name:sco_x_preferred":[
        "Shalinsky Destrict"
    ],
    "name:srp_x_preferred":[
        "\u0428\u0430\u043b\u0438\u043d\u0441\u043a\u0438 \u0440\u0435\u0458\u043e\u043d"
    ],
    "name:tat_x_preferred":[
        "\u0428\u0430\u043b\u0438 \u0440\u0430\u0439\u043e\u043d\u044b"
    ],
    "name:tgk_x_preferred":[
        "\u041d\u043e\u04b3\u0438\u044f\u0438 \u0428\u0430\u043b\u0438\u043d\u0441\u043a\u0438\u0439"
    ],
    "name:ukr_x_preferred":[
        "\u0428\u0430\u043b\u0456\u043d\u0441\u044c\u043a\u0438\u0439 \u0440\u0430\u0439\u043e\u043d"
    ],
    "name:und_x_variant":[
        "Nadrech\u2019ye"
    ],
    "name:vie_x_preferred":[
        "Shalinsky"
    ],
    "name:war_x_preferred":[
        "Shalinsky"
    ],
    "name:zho_x_preferred":[
        "\u6c99\u91cc\u5dde"
    ],
    "qs:name":"Chiri-Yurt",
    "qs:photos_9r":0,
    "qs:photos_sr":0,
    "qs:pop_sr":"5",
    "wd:wordcount":749,
    "wof:name":"Chiri-Yurt",
    "wof:placetype":"neighbourhood",
    "wof:population":5136
},
  "geometry": {"coordinates":[45.74322,43.08869],"type":"Point"}
}