{
  "type": "Feature",
  "properties": {
    "gn:country":"RU",
    "gn:fcode":"PPLX",
    "gn:pop":5136,
    "iso:country":"RU",
    "name:che_x_preferred":[
        "Cemzavod"
    ],
    "name:che_x_variant":[
        "\u00c7\u00fcyrin-Evl",
        "\u0426\u0435\u043c\u0437\u0430\u0432\u043e\u0434",
        "\u0427\u0443\u044c\u0439\u0440\u0438\u043d-\u042d\u0432\u043b"
    ],
    "name:eng_x_preferred":[
        "Chiri-Yurt"
    ],
    "name:nor_x_preferred":[
        "Tsjiri-Jurt"
    ],
    "name:rus_x_preferred":[
        "\u0427\u0438\u0440\u0438-\u042e\u0440\u0442"
    ],
    "name:rus_x_variant":[
        "\u010ciri-Jurt",
        "Nadre\u010d\u2019e",
        "\u041d\u0430\u0434\u0440\u0435\u0447\u044c\u0435"
    ],
    "name:unk_x_variant":[
        "Nadrech\u2019ye"
    ],
    "qs:name":"Chiri-Yurt",
    "qs:photos_9r":0,
    "qs:photos_sr":0,
    "qs:pop_sr":"5",
    "wd:wordcount":749,
    "wof:name":"Chiri-Yurt",
    "wof:placetype":"neighbourhood",
    "wof:population":5136
},
  "geometry": {"coordinates":[45.74322,43.08869],"type":"Point"}
}