{
  "type": "Feature",
  "properties": {
    "gn:admin1_code":"56.0",
    "gn:asciiname":"Chizhi",
    "gn:country_code":"RU",
    "gn:dem":242,
    "gn:feature_class":"P",
    "gn:feature_code":"PPL",
    "gn:name":"Chizhi",
    "gn:population":0,
    "gn:timezone":"Europe/Moscow",
    "iso:country":"RU",
    "name:rus_x_preferred":[
        "\u0427\u0438\u0436\u0438"
    ],
    "name:und_x_variant":[
        "\u0427\u0438\u0436\u0438"
    ],
    "wof:name":"Chizhi",
    "wof:placetype":"locality"
},
  "geometry": {"coordinates":[36.47021,52.96511],"type":"Point"}
}