{
  "type": "Feature",
  "properties": {
    "gn:admin1_code":"80.0",
    "gn:asciiname":"Glukhovo",
    "gn:country_code":"RU",
    "gn:dem":86,
    "gn:feature_class":"P",
    "gn:feature_code":"PPL",
    "gn:name":"Glukhovo",
    "gn:population":0,
    "gn:timezone":"Europe/Samara",
    "iso:country":"RU",
    "wof:name":"Glukhovo",
    "wof:placetype":"locality"
},
  "geometry": {"coordinates":[53.66435,56.36255],"type":"Point"}
}