{
  "type": "Feature",
  "properties": {
    "gn:admin1_code":"37",
    "gn:asciiname":"Grishino",
    "gn:country_code":"RU",
    "gn:dem":118,
    "gn:feature_class":"P",
    "gn:feature_code":"PPL",
    "gn:name":"Grishino",
    "gn:population":0,
    "gn:timezone":"Europe/Moscow",
    "iso:country":"RU",
    "name:nor_x_preferred":[
        "Grisjino"
    ],
    "name:rus_x_preferred":[
        "\u0413\u0440\u0438\u0448\u0438\u043d\u043e"
    ],
    "wof:name":"Grishino",
    "wof:placetype":"locality"
},
  "geometry": {"coordinates":[41.42639000000001,58.80389],"type":"Point"}
}