{
  "type": "Feature",
  "properties": {
    "gn:admin1_code":"6",
    "gn:asciiname":"Tsenogora",
    "gn:country_code":"RU",
    "gn:dem":62,
    "gn:feature_class":"P",
    "gn:feature_code":"PPL",
    "gn:name":"Tsenogora",
    "gn:population":0,
    "gn:timezone":"Europe/Moscow",
    "iso:country":"RU",
    "name:eng_x_preferred":[
        "Tsenogora"
    ],
    "name:nor_x_preferred":[
        "Tsenogora"
    ],
    "name:rus_x_preferred":[
        "\u0426\u0435\u043d\u043e\u0433\u043e\u0440\u0430"
    ],
    "name:und_x_variant":[
        "Tsenogory"
    ],
    "wof:name":"Tsenogora",
    "wof:placetype":"locality"
},
  "geometry": {"coordinates":[46.7192,64.8792],"type":"Point"}
}