{
  "type": "Feature",
  "properties": {
    "gn:admin1_code":"20.0",
    "gn:asciiname":"Mishonkova",
    "gn:country_code":"RU",
    "gn:dem":564,
    "gn:feature_class":"P",
    "gn:feature_code":"PPL",
    "gn:name":"Mishonkova",
    "gn:population":0,
    "gn:timezone":"Asia/Irkutsk",
    "iso:country":"RU",
    "name:rus_x_preferred":[
        "\u041c\u0438\u0448\u043e\u043d\u043a\u043e\u0432\u0430"
    ],
    "wof:name":"Mishonkova",
    "wof:placetype":"locality"
},
  "geometry": {"coordinates":[104.39,52.65],"type":"Point"}
}