{
  "type": "Feature",
  "properties": {
    "gn:admin1_code":"60",
    "gn:asciiname":"Nekloch'",
    "gn:country_code":"RU",
    "gn:dem":52,
    "gn:feature_class":"P",
    "gn:feature_code":"PPL",
    "gn:name":"Nekloch\u2019",
    "gn:population":0,
    "gn:timezone":"Europe/Moscow",
    "iso:country":"RU",
    "name:rus_x_preferred":[
        "\u041d\u0435\u043a\u043b\u043e\u0447\u044c"
    ],
    "name:und_x_variant":[
        "Nekloch\u2019"
    ],
    "wof:name":"Nekloch'",
    "wof:placetype":"locality"
},
  "geometry": {"coordinates":[28.193,57.7198],"type":"Point"}
}