{
  "type": "Feature",
  "properties": {
    "gn:admin1_code":"19.0",
    "gn:asciiname":"Besht",
    "gn:country_code":"RU",
    "gn:dem":1879,
    "gn:feature_class":"P",
    "gn:feature_code":"PPL",
    "gn:name":"Besht",
    "gn:population":0,
    "gn:timezone":"Europe/Moscow",
    "iso:country":"RU",
    "name:nor_x_preferred":[
        "Besjt"
    ],
    "name:rus_x_preferred":[
        "\u0411\u0435\u0448\u0442"
    ],
    "wof:name":"Besht",
    "wof:placetype":"locality"
},
  "geometry": {"coordinates":[44.86667,42.81667],"type":"Point"}
}