{
  "type": "Feature",
  "properties": {
    "gn:admin1_code":"38",
    "gn:asciiname":"Suvorovskoye",
    "gn:country_code":"RU",
    "gn:dem":49,
    "gn:feature_class":"P",
    "gn:feature_code":"PPL",
    "gn:name":"Suvorovskoye",
    "gn:population":0,
    "gn:timezone":"Europe/Moscow",
    "iso:country":"RU",
    "name:eng_x_preferred":[
        "Suvorovskoye"
    ],
    "name:nor_x_preferred":[
        "Suvorovskoje"
    ],
    "name:rus_x_preferred":[
        "\u0421\u0443\u0432\u043e\u0440\u043e\u0432\u0441\u043a\u043e\u0435"
    ],
    "name:und_x_variant":[
        "Tret\u2019ya Rechka Kochety",
        "Rechka Kochety Tret\u2019ya",
        "Kochety Tret\u2019ya Rechka"
    ],
    "wof:name":"Suvorovskoye",
    "wof:placetype":"locality"
},
  "geometry": {"coordinates":[39.4349,45.27802],"type":"Point"}
}