{
  "type": "Feature",
  "properties": {
    "gn:admin1_code":"61",
    "gn:asciiname":"Novaya Kul'tura",
    "gn:country_code":"RU",
    "gn:dem":92,
    "gn:feature_class":"P",
    "gn:feature_code":"PPL",
    "gn:name":"Novaya Kul\u2019tura",
    "gn:population":0,
    "gn:timezone":"Europe/Moscow",
    "iso:country":"RU",
    "wof:name":"Novaya Kul'tura",
    "wof:placetype":"locality"
},
  "geometry": {"coordinates":[41.79306,49.18139],"type":"Point"}
}