{
  "type": "Feature",
  "properties": {
    "gn:country":"RU",
    "gn:fcode":"PPL",
    "gn:population":5693,
    "iso:country":"RU",
    "name:azb_x_preferred":[
        "\u062f\u0645\u06cc\u0627\u0646\u0632\u06a9"
    ],
    "name:bak_x_preferred":[
        "\u0414\u0435\u043c\u044f\u043d\u0441\u043a"
    ],
    "name:bel_x_preferred":[
        "\u0414\u0437\u044f\u043c\u044f\u043d\u0441\u043a"
    ],
    "name:bul_x_preferred":[
        "\u0414\u0435\u043c\u044f\u043d\u0441\u043a"
    ],
    "name:ceb_x_preferred":[
        "Demyansk"
    ],
    "name:che_x_preferred":[
        "\u0414\u0435\u043c\u044f\u043d\u0441\u043a"
    ],
    "name:crh_x_preferred":[
        "Dem\u00e2nsk"
    ],
    "name:dan_x_preferred":[
        "Demjansk"
    ],
    "name:deu_x_preferred":[
        "Demjansk"
    ],
    "name:eng_x_preferred":[
        "Demyansk"
    ],
    "name:epo_x_preferred":[
        "Demjansk"
    ],
    "name:est_x_preferred":[
        "Demjansk"
    ],
    "name:fas_x_preferred":[
        "\u062f\u0645\u06cc\u0627\u0646\u0633\u06a9"
    ],
    "name:fin_x_preferred":[
        "Demjansk"
    ],
    "name:fra_x_preferred":[
        "Demiansk"
    ],
    "name:heb_x_preferred":[
        "\u05d3\u05de\u05d9\u05d0\u05e0\u05e1\u05e7"
    ],
    "name:ita_x_preferred":[
        "Demjansk"
    ],
    "name:jpn_x_preferred":[
        "\u30c7\u30df\u30e3\u30f3\u30b9\u30af"
    ],
    "name:kor_x_preferred":[
        "\ub370\uba04\uc2a4\ud06c"
    ],
    "name:mkd_x_preferred":[
        "\u0414\u0435\u043c\u0458\u0430\u043d\u0441\u043a"
    ],
    "name:nld_x_preferred":[
        "Demjansk"
    ],
    "name:nor_x_preferred":[
        "Demjansk"
    ],
    "name:pol_x_preferred":[
        "Diemia\u0144sk"
    ],
    "name:rus_x_preferred":[
        "\u0414\u0435\u043c\u044f\u043d\u0441\u043a"
    ],
    "name:spa_x_preferred":[
        "Demiansk"
    ],
    "name:srp_x_preferred":[
        "\u0414\u0435\u043c\u0458\u0430\u043d\u0441\u043a"
    ],
    "name:swe_x_preferred":[
        "Demjansk"
    ],
    "name:ukr_x_preferred":[
        "\u0414\u0435\u043c'\u044f\u043d\u0441\u044c\u043a"
    ],
    "name:zho_x_preferred":[
        "\u5fb7\u7c73\u694a\u65af\u514b"
    ],
    "name:zho_x_variant":[
        "\u5091\u7c73\u63da\u65af\u514b"
    ],
    "qs:name":"Demyansk",
    "qs:photos_9r":0,
    "qs:photos_sr":0,
    "qs:pop_sr":"5",
    "wd:wordcount":1262,
    "wof:name":"Demyansk",
    "wof:placetype":"locality",
    "wof:population":5693
},
  "geometry": {"coordinates":[32.466,57.64301],"type":"Point"}
}