{
  "type": "Feature",
  "properties": {
    "gn:admin1_code":"53",
    "gn:asciiname":"Blizhniy",
    "gn:country_code":"RU",
    "gn:dem":164,
    "gn:feature_class":"P",
    "gn:feature_code":"PPL",
    "gn:name":"Blizhniy",
    "gn:population":0,
    "gn:timezone":"Asia/Novosibirsk",
    "iso:country":"RU",
    "name:rus_x_preferred":[
        "\u0411\u043b\u0438\u0436\u043d\u0438\u0439"
    ],
    "wof:name":"Blizhniy",
    "wof:placetype":"locality"
},
  "geometry": {"coordinates":[84.33333,55.91667],"type":"Point"}
}