{
  "type": "Feature",
  "properties": {
    "gn:admin1_code":"55",
    "gn:asciiname":"Medvedka",
    "gn:country_code":"RU",
    "gn:dem":72,
    "gn:feature_class":"P",
    "gn:feature_code":"PPL",
    "gn:name":"Medvedka",
    "gn:population":0,
    "gn:timezone":"Asia/Yekaterinburg",
    "iso:country":"RU",
    "name:bul_x_preferred":[
        "\u041c\u0435\u0434\u0432\u0435\u0434\u043a\u0430"
    ],
    "name:che_x_preferred":[
        "\u041c\u0435\u0434\u0432\u0435\u0434\u043a\u0430"
    ],
    "name:eng_x_preferred":[
        "Medvedka"
    ],
    "name:hye_x_preferred":[
        "\u0544\u0565\u0564\u057e\u0565\u0564\u056f\u0561"
    ],
    "name:nor_x_preferred":[
        "Medvedka"
    ],
    "name:rus_x_preferred":[
        "\u041c\u0435\u0434\u0432\u0435\u0434\u043a\u0430"
    ],
    "wof:name":"Medvedka",
    "wof:placetype":"locality"
},
  "geometry": {"coordinates":[52.4989,52.6318],"type":"Point"}
}