{
  "type": "Feature",
  "properties": {
    "gn:admin1_code":"51",
    "gn:asciiname":"Botalovo",
    "gn:country_code":"RU",
    "gn:dem":77,
    "gn:feature_class":"P",
    "gn:feature_code":"PPL",
    "gn:name":"Botalovo",
    "gn:population":0,
    "gn:timezone":"Europe/Moscow",
    "iso:country":"RU",
    "name:rus_x_preferred":[
        "\u0411\u043e\u0442\u0430\u043b\u043e\u0432\u043e"
    ],
    "wof:name":"Botalovo",
    "wof:placetype":"locality"
},
  "geometry": {"coordinates":[44.03276,56.38673000000001],"type":"Point"}
}