{
  "type": "Feature",
  "properties": {
    "gn:admin1_code":"42.0",
    "gn:asciiname":"Chegol'",
    "gn:country_code":"RU",
    "gn:dem":57,
    "gn:feature_class":"P",
    "gn:feature_code":"PPL",
    "gn:name":"Chegol\u2019",
    "gn:population":0,
    "gn:timezone":"Europe/Moscow",
    "iso:country":"RU",
    "name:rus_x_preferred":[
        "\u0427\u0435\u0433\u043e\u043b\u044c"
    ],
    "name:und_x_variant":[
        "Chegoli",
        "Chegol\u2019",
        "\u0427\u0435\u0433\u043e\u043b\u044c"
    ],
    "wof:name":"Chegol'",
    "wof:placetype":"locality"
},
  "geometry": {"coordinates":[29.93521,58.67956],"type":"Point"}
}