{
  "type": "Feature",
  "properties": {
    "gn:admin1_code":"33",
    "gn:asciiname":"Blagoveshchenskoye",
    "gn:country_code":"RU",
    "gn:dem":160,
    "gn:feature_class":"P",
    "gn:feature_code":"PPL",
    "gn:name":"Blagoveshchenskoye",
    "gn:population":0,
    "gn:timezone":"Europe/Kirov",
    "iso:country":"RU",
    "name:eng_x_preferred":[
        "Blagoveshchenskoye"
    ],
    "name:nor_x_preferred":[
        "Blagovesjtsjenskoje"
    ],
    "name:rus_x_preferred":[
        "\u0411\u043b\u0430\u0433\u043e\u0432\u0435\u0449\u0435\u043d\u0441\u043a\u043e\u0435"
    ],
    "wof:name":"Blagoveshchenskoye",
    "wof:placetype":"locality"
},
  "geometry": {"coordinates":[47.49477,58.46736],"type":"Point"}
}