{
  "type": "Feature",
  "properties": {
    "gn:admin1_code":"76.0",
    "gn:asciiname":"Bol'shoy Sukhodol",
    "gn:country_code":"RU",
    "gn:dem":232,
    "gn:feature_class":"P",
    "gn:feature_code":"PPL",
    "gn:name":"Bol\u2019shoy Sukhodol",
    "gn:population":0,
    "gn:timezone":"Europe/Moscow",
    "iso:country":"RU",
    "name:rus_x_preferred":[
        "\u0411\u043e\u043b\u044c\u0448\u043e\u0439 \u0421\u0443\u0445\u043e\u0434\u043e\u043b"
    ],
    "name:und_x_variant":[
        "Bol\u2019shoy Sukhodol"
    ],
    "wof:name":"Bol'shoy Sukhodol",
    "wof:placetype":"locality"
},
  "geometry": {"coordinates":[38.2689,53.7285],"type":"Point"}
}