{
  "type": "Feature",
  "properties": {
    "gn:admin1_code":"85",
    "gn:asciiname":"Yelekhovo",
    "gn:country_code":"RU",
    "gn:dem":108,
    "gn:feature_class":"P",
    "gn:feature_code":"PPL",
    "gn:name":"Yelekhovo",
    "gn:population":0,
    "gn:timezone":"Europe/Moscow",
    "iso:country":"RU",
    "name:eng_x_preferred":[
        "Yelekhovo"
    ],
    "name:nor_x_preferred":[
        "Jelekhovo"
    ],
    "name:rus_x_preferred":[
        "\u0415\u043b\u0435\u0445\u043e\u0432\u043e"
    ],
    "wof:name":"Yelekhovo",
    "wof:placetype":"locality"
},
  "geometry": {"coordinates":[37.35,59.05],"type":"Point"}
}