{
  "type": "Feature",
  "properties": {
    "gn:admin1_code":"51",
    "gn:asciiname":"Malyye Kilimary",
    "gn:country_code":"RU",
    "gn:dem":120,
    "gn:feature_class":"P",
    "gn:feature_code":"PPL",
    "gn:name":"Malyye Kilimary",
    "gn:population":0,
    "gn:timezone":"Europe/Moscow",
    "iso:country":"RU",
    "name:rus_x_preferred":[
        "\u041c\u0430\u043b\u044b\u0435 \u041a\u0438\u043b\u0438\u043c\u0430\u0440\u044b"
    ],
    "name:und_x_variant":[
        "Malyye Kilemary",
        "Malyye Kilimary",
        "Malyye Killimary"
    ],
    "wof:name":"Malyye Kilimary",
    "wof:placetype":"locality"
},
  "geometry": {"coordinates":[46.39294,57.03853],"type":"Point"}
}