{
  "type": "Feature",
  "properties": {
    "gn:admin1_code":"13",
    "gn:asciiname":"Baygazina",
    "gn:country_code":"RU",
    "gn:dem":258,
    "gn:feature_class":"P",
    "gn:feature_code":"PPL",
    "gn:name":"Baygazina",
    "gn:population":0,
    "gn:timezone":"Asia/Yekaterinburg",
    "iso:country":"RU",
    "name:eng_x_preferred":[
        "Baygazina"
    ],
    "name:nor_x_preferred":[
        "Bajgazina"
    ],
    "name:rus_x_preferred":[
        "\u0411\u0430\u0439\u0433\u0430\u0437\u0438\u043d\u0430"
    ],
    "wof:name":"Baygazina",
    "wof:placetype":"locality"
},
  "geometry": {"coordinates":[60.7906,55.1574],"type":"Point"}
}