{
  "type": "Feature",
  "properties": {
    "gn:admin1_code":"15",
    "gn:asciiname":"Val'kelvaam",
    "gn:country_code":"RU",
    "gn:dem":82,
    "gn:feature_class":"P",
    "gn:feature_code":"PPL",
    "gn:name":"Val\u2019kelvaam",
    "gn:population":0,
    "gn:timezone":"Asia/Anadyr",
    "iso:country":"RU",
    "wof:name":"Val'kelvaam",
    "wof:placetype":"locality"
},
  "geometry": {"coordinates":[177.61667,62.73333],"type":"Point"}
}