{
  "type": "Feature",
  "properties": {
    "gn:admin1_code":"8",
    "gn:asciiname":"Kash-Yelga",
    "gn:country_code":"RU",
    "gn:dem":97,
    "gn:feature_class":"P",
    "gn:feature_code":"PPL",
    "gn:name":"Kash-Yelga",
    "gn:population":0,
    "gn:timezone":"Asia/Yekaterinburg",
    "iso:country":"RU",
    "name:rus_x_preferred":[
        "\u041a\u0430\u0448-\u0415\u043b\u0433\u0430"
    ],
    "wof:name":"Kash-Yelga",
    "wof:placetype":"locality"
},
  "geometry": {"coordinates":[56.56667,54.53333000000001],"type":"Point"}
}