{
  "type": "Feature",
  "properties": {
    "gn:admin1_code":"15",
    "gn:asciiname":"Morokovo",
    "gn:country_code":"RU",
    "gn:dem":23,
    "gn:feature_class":"P",
    "gn:feature_code":"PPL",
    "gn:name":"Morokovo",
    "gn:population":0,
    "gn:timezone":"Asia/Anadyr",
    "iso:country":"RU",
    "name:rus_x_preferred":[
        "\u041c\u043e\u0440\u043e\u043a\u043e\u0432\u043e"
    ],
    "wof:name":"Morokovo",
    "wof:placetype":"locality"
},
  "geometry": {"coordinates":[171.91666999999995,65.15000000000001],"type":"Point"}
}