{
  "type": "Feature",
  "properties": {
    "gn:admin1_code":"25",
    "gn:asciiname":"Kholop'e",
    "gn:country_code":"RU",
    "gn:dem":225,
    "gn:feature_class":"P",
    "gn:feature_code":"PPL",
    "gn:name":"\u0425\u043e\u043b\u043e\u043f\u044c\u0435",
    "gn:population":0,
    "gn:timezone":"Europe/Moscow",
    "iso:country":"RU",
    "name:rus_x_preferred":[
        "\u0425\u043e\u043b\u043e\u043f\u044c\u0435"
    ],
    "name:und_x_variant":[
        "Kholop\u2019ye"
    ],
    "wof:name":"Kholop'e",
    "wof:placetype":"locality"
},
  "geometry": {"coordinates":[35.37806,54.00386],"type":"Point"}
}