{
  "type": "Feature",
  "properties": {
    "gn:admin1_code":"25",
    "gn:asciiname":"Pavlinovo",
    "gn:country_code":"RU",
    "gn:dem":195,
    "gn:feature_class":"P",
    "gn:feature_code":"PPL",
    "gn:name":"Pavlinovo",
    "gn:population":0,
    "gn:timezone":"Europe/Moscow",
    "iso:country":"RU",
    "name:eng_x_preferred":[
        "Pavlinovo"
    ],
    "name:nor_x_preferred":[
        "Pavlinovo"
    ],
    "name:rus_x_preferred":[
        "\u041f\u0430\u0432\u043b\u0438\u043d\u043e\u0432\u043e"
    ],
    "name:und_x_variant":[
        "Pavlikovo",
        "\u041f\u0430\u0432\u043b\u0438\u043d\u043e\u0432\u043e",
        "Pavlinovo"
    ],
    "wof:name":"Pavlinovo",
    "wof:placetype":"locality"
},
  "geometry": {"coordinates":[33.75592,54.48416],"type":"Point"}
}