{
  "type": "Feature",
  "properties": {
    "gn:admin1_code":"30",
    "gn:asciiname":"Solontsy",
    "gn:country_code":"RU",
    "gn:dem":18,
    "gn:feature_class":"P",
    "gn:feature_code":"PPL",
    "gn:name":"Solontsy",
    "gn:population":0,
    "gn:timezone":"Asia/Vladivostok",
    "iso:country":"RU",
    "name:eng_x_preferred":[
        "Solontsy"
    ],
    "name:nor_x_preferred":[
        "Solontsy"
    ],
    "name:rus_x_preferred":[
        "\u0421\u043e\u043b\u043e\u043d\u0446\u044b"
    ],
    "name:und_x_variant":[
        "Solankse"
    ],
    "wof:name":"Solontsy",
    "wof:placetype":"locality"
},
  "geometry": {"coordinates":[140.25133,52.25797],"type":"Point"}
}