{
  "type": "Feature",
  "properties": {
    "gn:admin1_code":"60",
    "gn:asciiname":"Shchipunovo",
    "gn:country_code":"RU",
    "gn:dem":149,
    "gn:feature_class":"P",
    "gn:feature_code":"PPL",
    "gn:name":"Shchipunovo",
    "gn:population":0,
    "gn:timezone":"Europe/Moscow",
    "iso:country":"RU",
    "name:rus_x_preferred":[
        "\u0429\u0438\u043f\u0443\u043d\u043e\u0432\u043e"
    ],
    "name:und_x_variant":[
        "Shipunovo",
        "Shchipunovo",
        "\u0429\u0438\u043f\u0443\u043d\u043e\u0432\u043e"
    ],
    "wof:name":"Shchipunovo",
    "wof:placetype":"locality"
},
  "geometry": {"coordinates":[30.86597,55.9085],"type":"Point"}
}