{
  "type": "Feature",
  "properties": {
    "gn:admin1_code":"47",
    "gn:asciiname":"Beketovo",
    "gn:country_code":"RU",
    "gn:dem":200,
    "gn:feature_class":"P",
    "gn:feature_code":"PPL",
    "gn:name":"Beketovo",
    "gn:population":0,
    "gn:timezone":"Europe/Moscow",
    "iso:country":"RU",
    "name:rus_x_preferred":[
        "\u0411\u0435\u043a\u0435\u0442\u043e\u0432\u043e"
    ],
    "name:und_x_variant":[
        "\u0411\u0435\u043a\u0435\u0442\u043e\u0432\u043e"
    ],
    "wof:name":"Beketovo",
    "wof:placetype":"locality"
},
  "geometry": {"coordinates":[36.5257,56.3353],"type":"Point"}
}