{
  "type": "Feature",
  "properties": {
    "gn:admin1_code":"20",
    "gn:asciiname":"Sharagul-Sachki",
    "gn:country_code":"RU",
    "gn:dem":518,
    "gn:feature_class":"P",
    "gn:feature_code":"PPL",
    "gn:name":"Sharagul-Sachki",
    "gn:population":0,
    "gn:timezone":"Asia/Irkutsk",
    "iso:country":"RU",
    "name:rus_x_preferred":[
        "\u0428\u0430\u0440\u0430\u0433\u0443\u043b-\u0421\u0430\u0447\u043a\u0438"
    ],
    "name:und_x_variant":[
        "Sheragul Sachki",
        "Ulus Dobryy Sharagul",
        "Dobr-Sharkey",
        "Ulus",
        "Sharagul-Sachki"
    ],
    "wof:name":"Sharagul-Sachki",
    "wof:placetype":"locality"
},
  "geometry": {"coordinates":[101.6722,53.4339],"type":"Point"}
}