{
  "type": "Feature",
  "properties": {
    "gn:admin1_code":"88",
    "gn:asciiname":"Meshkovo",
    "gn:country_code":"RU",
    "gn:dem":131,
    "gn:feature_class":"P",
    "gn:feature_code":"PPL",
    "gn:name":"Meshkovo",
    "gn:population":0,
    "gn:timezone":"Europe/Moscow",
    "iso:country":"RU",
    "name:rus_x_preferred":[
        "\u041c\u0435\u0448\u043a\u043e\u0432\u043e"
    ],
    "name:und_x_variant":[
        "\u041c\u0435\u0448\u043a\u043e\u0432\u043e"
    ],
    "wof:name":"Meshkovo",
    "wof:placetype":"locality"
},
  "geometry": {"coordinates":[38.6711,57.8813],"type":"Point"}
}