{
  "type": "Feature",
  "properties": {
    "gn:admin1_code":"69",
    "gn:asciiname":"Shelomki",
    "gn:country_code":"RU",
    "gn:dem":244,
    "gn:feature_class":"P",
    "gn:feature_code":"PPL",
    "gn:name":"Shelomki",
    "gn:population":0,
    "gn:timezone":"Europe/Moscow",
    "iso:country":"RU",
    "name:rus_x_preferred":[
        "\u0428\u0435\u043b\u043e\u043c\u043a\u0438"
    ],
    "wof:name":"Shelomki",
    "wof:placetype":"locality"
},
  "geometry": {"coordinates":[35.01694000000001,55.84194],"type":"Point"}
}