{
  "type": "Feature",
  "properties": {
    "gn:admin1_code":"62.0",
    "gn:asciiname":"Bol'shoy Kukuy",
    "gn:country_code":"RU",
    "gn:dem":141,
    "gn:feature_class":"P",
    "gn:feature_code":"PPL",
    "gn:name":"Bol\u2019shoy Kukuy",
    "gn:population":0,
    "gn:timezone":"Europe/Moscow",
    "iso:country":"RU",
    "name:rus_x_preferred":[
        "\u0411\u043e\u043b\u044c\u0448\u043e\u0439 \u041a\u0443\u043a\u0443\u0439"
    ],
    "name:und_x_variant":[
        "Bol\u2019shoy Kukuy"
    ],
    "wof:name":"Bol'shoy Kukuy",
    "wof:placetype":"locality"
},
  "geometry": {"coordinates":[40.48333,53.75],"type":"Point"}
}