{
  "type": "Feature",
  "properties": {
    "gn:admin1_code":"56",
    "gn:asciiname":"Melikhovo",
    "gn:country_code":"RU",
    "gn:dem":257,
    "gn:feature_class":"P",
    "gn:feature_code":"PPL",
    "gn:name":"Melikhovo",
    "gn:population":0,
    "gn:timezone":"Europe/Moscow",
    "iso:country":"RU",
    "name:rus_x_preferred":[
        "\u041c\u0435\u043b\u0438\u0445\u043e\u0432\u043e"
    ],
    "name:und_x_variant":[
        "\u041c\u0435\u043b\u0438\u0445\u043e\u0432\u043e"
    ],
    "wof:name":"Melikhovo",
    "wof:placetype":"locality"
},
  "geometry": {"coordinates":[35.44551,52.71092],"type":"Point"}
}