{
  "type": "Feature",
  "properties": {
    "gn:admin1_code":"69",
    "gn:asciiname":"Ryazanka",
    "gn:country_code":"RU",
    "gn:dem":225,
    "gn:feature_class":"P",
    "gn:feature_code":"PPL",
    "gn:name":"Ryazanka",
    "gn:population":0,
    "gn:timezone":"Europe/Moscow",
    "iso:country":"RU",
    "name:rus_x_preferred":[
        "\u0420\u044f\u0437\u0430\u043d\u043a\u0430"
    ],
    "wof:name":"Ryazanka",
    "wof:placetype":"locality"
},
  "geometry": {"coordinates":[33.68333,54.31667],"type":"Point"}
}