{
  "type": "Feature",
  "properties": {
    "gn:admin1_code":"91.0",
    "gn:asciiname":"Izumrudnyy",
    "gn:country_code":"RU",
    "gn:dem":285,
    "gn:feature_class":"P",
    "gn:feature_code":"PPL",
    "gn:name":"Izumrudnyy",
    "gn:population":0,
    "gn:timezone":"Asia/Krasnoyarsk",
    "iso:country":"RU",
    "name:rus_x_preferred":[
        "\u0418\u0437\u0443\u043c\u0440\u0443\u0434\u043d\u044b\u0439"
    ],
    "wof:name":"Izumrudnyy",
    "wof:placetype":"locality"
},
  "geometry": {"coordinates":[95.4251,55.654],"type":"Point"}
}