{
  "type": "Feature",
  "properties": {
    "gn:admin1_code":"77",
    "gn:asciiname":"Kileshino",
    "gn:country_code":"RU",
    "gn:dem":211,
    "gn:feature_class":"P",
    "gn:feature_code":"PPL",
    "gn:name":"Kileshino",
    "gn:population":0,
    "gn:timezone":"Europe/Moscow",
    "iso:country":"RU",
    "name:rus_x_preferred":[
        "\u041a\u0438\u043b\u0435\u0448\u0438\u043d\u043e"
    ],
    "name:und_x_variant":[
        "\u041a\u0438\u043b\u0435\u0448\u0438\u043d\u043e"
    ],
    "wof:name":"Kileshino",
    "wof:placetype":"locality"
},
  "geometry": {"coordinates":[33.45629,56.87933],"type":"Point"}
}