{
  "type": "Feature",
  "properties": {
    "gn:admin1_code":"54",
    "gn:asciiname":"Osokinskiy",
    "gn:country_code":"RU",
    "gn:dem":112,
    "gn:feature_class":"P",
    "gn:feature_code":"PPL",
    "gn:name":"Osokinskiy",
    "gn:population":0,
    "gn:timezone":"Asia/Omsk",
    "iso:country":"RU",
    "name:rus_x_preferred":[
        "\u041e\u0441\u043e\u043a\u0438\u043d\u0441\u043a\u0438\u0439"
    ],
    "wof:name":"Osokinskiy",
    "wof:placetype":"locality"
},
  "geometry": {"coordinates":[74.40000000000001,54.95],"type":"Point"}
}