{
  "type": "Feature",
  "properties": {
    "gn:admin1_code":"33",
    "gn:asciiname":"Lashino",
    "gn:country_code":"RU",
    "gn:dem":164,
    "gn:feature_class":"P",
    "gn:feature_code":"PPL",
    "gn:name":"Lashino",
    "gn:population":0,
    "gn:timezone":"Europe/Kirov",
    "iso:country":"RU",
    "name:rus_x_preferred":[
        "\u041b\u0430\u0448\u0438\u043d\u043e"
    ],
    "wof:name":"Lashino",
    "wof:placetype":"locality"
},
  "geometry": {"coordinates":[49.96787,58.26125],"type":"Point"}
}