{
  "type": "Feature",
  "properties": {
    "gn:country":"RU",
    "gn:fcode":"PPL",
    "gn:pop":0,
    "iso:country":"RU",
    "name:eng_x_preferred":[
        "Telepn\u00ebvo"
    ],
    "name:nor_x_preferred":[
        "Telepnevo"
    ],
    "name:rus_x_preferred":[
        "\u0422\u0435\u043b\u0435\u043f\u043d\u0435\u0432\u043e"
    ],
    "name:unk_x_variant":[
        "Telepneva"
    ],
    "qs:name":"Telepnevo",
    "qs:name_adm0":"Russia",
    "qs:name_adm1":"Smolensk Oblast",
    "qs:photos_9r":0,
    "qs:photos_sr":0,
    "qs:placetype":"Town",
    "qs:pop_sr":"0",
    "wof:name":"Telepnevo",
    "wof:placetype":"locality",
    "wof:population":0
},
  "geometry": {"coordinates":[34.5861,55.30583],"type":"Point"}
}