{
  "type": "Feature",
  "properties": {
    "gn:admin1_code":"38",
    "gn:asciiname":"Yevseyevskiy",
    "gn:country_code":"RU",
    "gn:dem":5,
    "gn:feature_class":"P",
    "gn:feature_code":"PPL",
    "gn:name":"Yevseyevskiy",
    "gn:population":0,
    "gn:timezone":"Europe/Moscow",
    "iso:country":"RU",
    "name:rus_x_preferred":[
        "\u0415\u0432\u0441\u0435\u0435\u0432\u0441\u043a\u0438\u0439"
    ],
    "wof:name":"Yevseyevskiy",
    "wof:placetype":"locality"
},
  "geometry": {"coordinates":[38.14966,45.04923],"type":"Point"}
}