{
  "type": "Feature",
  "properties": {
    "gn:admin1_code":"68",
    "gn:asciiname":"Ramonovo",
    "gn:country_code":"RU",
    "gn:dem":485,
    "gn:feature_class":"P",
    "gn:feature_code":"PPL",
    "gn:name":"Ramonovo",
    "gn:population":0,
    "gn:timezone":"Europe/Moscow",
    "iso:country":"RU",
    "name:rus_x_preferred":[
        "\u0420\u0430\u043c\u043e\u043d\u043e\u0432\u043e"
    ],
    "wof:name":"Ramonovo",
    "wof:placetype":"locality"
},
  "geometry": {"coordinates":[44.25802,43.12678],"type":"Point"}
}