{
  "type": "Feature",
  "properties": {
    "gn:admin1_code":"72",
    "gn:asciiname":"Maloye Montvidovo",
    "gn:country_code":"RU",
    "gn:dem":148,
    "gn:feature_class":"P",
    "gn:feature_code":"PPL",
    "gn:name":"Maloye Montvidovo",
    "gn:population":0,
    "gn:timezone":"Europe/Moscow",
    "iso:country":"RU",
    "name:rus_x_preferred":[
        "\u041c\u0430\u043b\u043e\u0435 \u041c\u043e\u043d\u0442\u0432\u0438\u0434\u043e\u0432\u043e"
    ],
    "wof:name":"Maloye Montvidovo",
    "wof:placetype":"locality"
},
  "geometry": {"coordinates":[40.9019,53.0732],"type":"Point"}
}