{
  "type": "Feature",
  "properties": {
    "gn:admin1_code":"53",
    "gn:asciiname":"Krupskoy",
    "gn:country_code":"RU",
    "gn:dem":138,
    "gn:feature_class":"P",
    "gn:feature_code":"PPL",
    "gn:name":"Krupskoy",
    "gn:population":0,
    "gn:timezone":"Asia/Novosibirsk",
    "iso:country":"RU",
    "name:eng_x_preferred":[
        "Krupskoy"
    ],
    "name:nor_x_preferred":[
        "Krupskoj"
    ],
    "name:rus_x_preferred":[
        "\u041a\u0440\u0443\u043f\u0441\u043a\u043e\u0439"
    ],
    "name:und_x_variant":[
        "Imeni Krupskoy"
    ],
    "wof:name":"Krupskoy",
    "wof:placetype":"locality"
},
  "geometry": {"coordinates":[82.7392,54.8299],"type":"Point"}
}