{
  "type": "Feature",
  "properties": {
    "gn:admin1_code":"68",
    "gn:asciiname":"Nogkau",
    "gn:country_code":"RU",
    "gn:dem":1588,
    "gn:feature_class":"P",
    "gn:feature_code":"PPL",
    "gn:name":"Nogkau",
    "gn:population":0,
    "gn:timezone":"Europe/Moscow",
    "iso:country":"RU",
    "name:rus_x_preferred":[
        "\u041d\u043e\u0433\u043a\u0430\u0443"
    ],
    "wof:name":"Nogkau",
    "wof:placetype":"locality"
},
  "geometry": {"coordinates":[44.04268,42.86678],"type":"Point"}
}