{
  "type": "Feature",
  "properties": {
    "gn:admin1_code":"85.0",
    "gn:asciiname":"Belovo",
    "gn:country_code":"RU",
    "gn:dem":133,
    "gn:feature_class":"P",
    "gn:feature_code":"PPL",
    "gn:name":"Belovo",
    "gn:population":0,
    "gn:timezone":"Europe/Moscow",
    "iso:country":"RU",
    "name:bul_x_preferred":[
        "\u0411\u0435\u043b\u043e\u0432\u043e"
    ],
    "name:ceb_x_preferred":[
        "Belovo"
    ],
    "name:ces_x_preferred":[
        "Belovo"
    ],
    "name:deu_x_preferred":[
        "Belowo"
    ],
    "name:ita_x_preferred":[
        "Belovo"
    ],
    "name:jpn_x_preferred":[
        "\u30d9\u30ed\u30f4\u30a9"
    ],
    "name:nld_x_preferred":[
        "Belovo"
    ],
    "name:nor_x_preferred":[
        "Belovo"
    ],
    "name:por_x_preferred":[
        "Belovo"
    ],
    "name:ron_x_preferred":[
        "Belovo"
    ],
    "name:rus_x_preferred":[
        "\u0411\u0435\u043b\u043e\u0432\u043e"
    ],
    "name:sco_x_preferred":[
        "Belovo"
    ],
    "name:spa_x_preferred":[
        "Belovo"
    ],
    "name:srp_x_preferred":[
        "\u0411\u0435\u043b\u043e\u0432\u043e"
    ],
    "name:swe_x_preferred":[
        "Belovo"
    ],
    "name:vie_x_preferred":[
        "Belovo"
    ],
    "wof:name":"Belovo",
    "wof:placetype":"locality"
},
  "geometry": {"coordinates":[40.94254,58.84338],"type":"Point"}
}