{
  "type": "Feature",
  "properties": {
    "gn:admin1_code":"76",
    "gn:asciiname":"Severnoye",
    "gn:country_code":"RU",
    "gn:dem":230,
    "gn:feature_class":"P",
    "gn:feature_code":"PPL",
    "gn:name":"Severnoye",
    "gn:population":0,
    "gn:timezone":"Europe/Moscow",
    "iso:country":"RU",
    "name:rus_x_preferred":[
        "\u0421\u0435\u0432\u0435\u0440\u043d\u043e\u0435"
    ],
    "wof:name":"Severnoye",
    "wof:placetype":"locality"
},
  "geometry": {"coordinates":[37.46734,53.38316999999999],"type":"Point"}
}