{
  "type": "Feature",
  "properties": {
    "gn:admin1_code":"23",
    "gn:asciiname":"Rosenberg",
    "gn:country_code":"RU",
    "gn:dem":17,
    "gn:feature_class":"P",
    "gn:feature_code":"PPL",
    "gn:name":"Rosenberg",
    "gn:population":0,
    "gn:timezone":"Europe/Kaliningrad",
    "iso:country":"RU",
    "wof:name":"Rosenberg",
    "wof:placetype":"locality"
},
  "geometry": {"coordinates":[19.93056,54.48694],"type":"Point"}
}