{
  "type": "Feature",
  "properties": {
    "gn:admin1_code":"85.0",
    "gn:asciiname":"Filimonovy Gari",
    "gn:country_code":"RU",
    "gn:dem":179,
    "gn:feature_class":"P",
    "gn:feature_code":"PPL",
    "gn:name":"Filimonovy Gari",
    "gn:population":0,
    "gn:timezone":"Europe/Moscow",
    "iso:country":"RU",
    "name:rus_x_preferred":[
        "\u0424\u0438\u043b\u0438\u043c\u043e\u043d\u043e\u0432\u044b \u0413\u0430\u0440\u0438"
    ],
    "name:und_x_variant":[
        "Filimonovy Gory",
        "Filimonovy Gari",
        "\u0424\u0438\u043b\u0438\u043c\u043e\u043d\u043e\u0432\u044b \u0413\u0430\u0440\u0438"
    ],
    "wof:name":"Filimonovy Gari",
    "wof:placetype":"locality"
},
  "geometry": {"coordinates":[45.72147,59.63069],"type":"Point"}
}