{
  "type": "Feature",
  "properties": {
    "gn:admin1_code":"89",
    "gn:asciiname":"Elyaksa",
    "gn:country_code":"RU",
    "gn:dem":33,
    "gn:feature_class":"P",
    "gn:feature_code":"PPL",
    "gn:name":"Elyaksa",
    "gn:population":0,
    "gn:timezone":"Asia/Vladivostok",
    "iso:country":"RU",
    "name:eng_x_preferred":[
        "Elyaksa"
    ],
    "name:nor_x_preferred":[
        "Eljaksa"
    ],
    "name:rus_x_preferred":[
        "\u042d\u043b\u044f\u043a\u0441\u0430"
    ],
    "name:und_x_variant":[
        "Elayaksa",
        "\u042d\u043b\u044f\u043a\u0441\u0430",
        "Elyaksa"
    ],
    "wof:name":"Elyaksa",
    "wof:placetype":"locality"
},
  "geometry": {"coordinates":[134.94149999999999,48.62792],"type":"Point"}
}