{
  "type": "Feature",
  "properties": {
    "gn:admin1_code":"73.0",
    "gn:asciiname":"Azalakovo",
    "gn:country_code":"RU",
    "gn:dem":109,
    "gn:feature_class":"P",
    "gn:feature_code":"PPL",
    "gn:name":"Azalakovo",
    "gn:population":0,
    "gn:timezone":"Europe/Moscow",
    "iso:country":"RU",
    "name:eng_x_preferred":[
        "Azalakovo"
    ],
    "name:nor_x_preferred":[
        "Azalakovo"
    ],
    "name:rus_x_preferred":[
        "\u0410\u0437\u0430\u043b\u0430\u043a\u043e\u0432\u043e"
    ],
    "name:und_x_variant":[
        "Azalak"
    ],
    "wof:name":"Azalakovo",
    "wof:placetype":"locality"
},
  "geometry": {"coordinates":[52.64093,55.33526],"type":"Point"}
}