{
  "type": "Feature",
  "properties": {
    "gn:admin1_code":"78",
    "gn:asciiname":"Kaimykova",
    "gn:country_code":"RU",
    "gn:dem":75,
    "gn:feature_class":"P",
    "gn:feature_code":"PPL",
    "gn:name":"Kaimykova",
    "gn:population":0,
    "gn:timezone":"Asia/Yekaterinburg",
    "iso:country":"RU",
    "name:rus_x_preferred":[
        "\u041a\u0430\u0438\u043c\u044b\u043a\u043e\u0432\u0430"
    ],
    "name:und_x_variant":[
        "\u041a\u0430\u0438\u043c\u044b\u043a\u043e\u0432\u0430"
    ],
    "wof:name":"Kaimykova",
    "wof:placetype":"locality"
},
  "geometry": {"coordinates":[71.65821,59.51163],"type":"Point"}
}