{
  "type": "Feature",
  "properties": {
    "gn:admin1_code":"77",
    "gn:asciiname":"Selivanovo",
    "gn:country_code":"RU",
    "gn:dem":183,
    "gn:feature_class":"P",
    "gn:feature_code":"PPL",
    "gn:name":"Selivanovo",
    "gn:population":0,
    "gn:timezone":"Europe/Moscow",
    "iso:country":"RU",
    "name:nor_x_preferred":[
        "Selivanovo"
    ],
    "name:rus_x_preferred":[
        "\u0421\u0435\u043b\u0438\u0432\u0430\u043d\u043e\u0432\u043e"
    ],
    "wof:name":"Selivanovo",
    "wof:placetype":"locality"
},
  "geometry": {"coordinates":[35.13003,56.31077],"type":"Point"}
}