{
  "type": "Feature",
  "properties": {
    "gn:admin1_code":"32",
    "gn:asciiname":"Bol'shoy Soboklond",
    "gn:country_code":"RU",
    "gn:dem":8,
    "gn:feature_class":"P",
    "gn:feature_code":"PPL",
    "gn:name":"Bol\u2019shoy Soboklond",
    "gn:population":0,
    "gn:timezone":"Asia/Yekaterinburg",
    "iso:country":"RU",
    "name:rus_x_preferred":[
        "\u0411\u043e\u043b\u044c\u0448\u043e\u0439 \u0421\u043e\u0431\u043e\u043a\u043b\u043e\u043d\u0434"
    ],
    "name:und_x_variant":[
        "Sobok-lont",
        "Bol\u2019shoy Soboklond"
    ],
    "wof:name":"Bol'shoy Soboklond",
    "wof:placetype":"locality"
},
  "geometry": {"coordinates":[63.95,63.05],"type":"Point"}
}