{
  "type": "Feature",
  "properties": {
    "gn:admin1_code":"17",
    "gn:asciiname":"Urtsamakhi",
    "gn:country_code":"RU",
    "gn:dem":1363,
    "gn:feature_class":"P",
    "gn:feature_code":"PPL",
    "gn:name":"Urtsamakhi",
    "gn:population":0,
    "gn:timezone":"Europe/Moscow",
    "iso:country":"RU",
    "wof:name":"Urtsamakhi",
    "wof:placetype":"locality"
},
  "geometry": {"coordinates":[47.27294000000001,42.34823],"type":"Point"}
}