{
  "type": "Feature",
  "properties": {
    "gn:admin1_code":"34",
    "gn:asciiname":"Lymva",
    "gn:country_code":"RU",
    "gn:dem":149,
    "gn:feature_class":"P",
    "gn:feature_code":"PPL",
    "gn:name":"Lymva",
    "gn:population":0,
    "gn:timezone":"Europe/Moscow",
    "iso:country":"RU",
    "name:rus_x_preferred":[
        "\u041b\u044b\u043c\u0432\u0430"
    ],
    "wof:name":"Lymva",
    "wof:placetype":"locality"
},
  "geometry": {"coordinates":[53.21135,62.1845],"type":"Point"}
}