{
  "type": "Feature",
  "properties": {
    "gn:admin1_code":"77.0",
    "gn:asciiname":"Glinniki",
    "gn:country_code":"RU",
    "gn:dem":121,
    "gn:feature_class":"P",
    "gn:feature_code":"PPL",
    "gn:name":"Glinniki",
    "gn:population":0,
    "gn:timezone":"Europe/Moscow",
    "iso:country":"RU",
    "name:eng_x_preferred":[
        "Glinniki"
    ],
    "name:nor_x_preferred":[
        "Glinniki"
    ],
    "name:rus_x_preferred":[
        "\u0413\u043b\u0438\u043d\u043d\u0438\u043a\u0438"
    ],
    "name:und_x_variant":[
        "\u0413\u043b\u0438\u043d\u043d\u0438\u043a\u0438",
        "Glinniki"
    ],
    "wof:name":"Glinniki",
    "wof:placetype":"locality"
},
  "geometry": {"coordinates":[36.73333,56.75],"type":"Point"}
}