{
  "type": "Feature",
  "properties": {
    "gn:admin1_code":"11",
    "gn:asciiname":"Yevdokiyeskiy",
    "gn:country_code":"RU",
    "gn:dem":925,
    "gn:feature_class":"P",
    "gn:feature_code":"PPL",
    "gn:name":"Yevdokiyeskiy",
    "gn:population":0,
    "gn:timezone":"Asia/Irkutsk",
    "iso:country":"RU",
    "wof:name":"Yevdokiyeskiy",
    "wof:placetype":"locality"
},
  "geometry": {"coordinates":[109.53704,55.92233],"type":"Point"}
}