{
  "type": "Feature",
  "properties": {
    "gn:country":"RU",
    "gn:fcode":"ADM3",
    "gn:population":92545,
    "iso:country":"RU",
    "name:ckb_x_preferred":[
        "\u0642\u06d5\u0632\u0627\u06a9\u0627\u0646\u06cc \u062a\u0627\u062c\u06cc\u06a9\u0633\u062a\u0627\u0646"
    ],
    "name:deu_x_preferred":[
        "Distrikt in Tadschikistan"
    ],
    "name:eng_x_preferred":[
        "district of Tajikistan"
    ],
    "name:fas_x_preferred":[
        "\u0646\u0627\u062d\u06cc\u0647\u200c\u0647\u0627\u06cc \u062a\u0627\u062c\u06cc\u06a9\u0633\u062a\u0627\u0646"
    ],
    "name:fin_x_preferred":[
        "Tad\u017eikistanin piirit"
    ],
    "name:ita_x_preferred":[
        "Distretti del Tagikistan"
    ],
    "name:nld_x_preferred":[
        "districten van Tadzjikistan"
    ],
    "name:rus_x_preferred":[
        "\u0421\u043e\u0432\u0435\u0442\u0441\u043a\u0438\u0439 \u0420\u0430\u0439\u043e\u043d"
    ],
    "name:rus_x_variant":[
        "\u0440\u0430\u0439\u043e\u043d \u0422\u0430\u0434\u0436\u0438\u043a\u0438\u0441\u0442\u0430\u043d\u0430"
    ],
    "name:swe_x_preferred":[
        "Tadzjikistans administrativa indelning"
    ],
    "name:tgk_x_preferred":[
        "\u041d\u043e\u04b3\u0438\u044f\u04b3\u043e\u0438 \u0422\u043e\u04b7\u0438\u043a\u0438\u0441\u0442\u043e\u043d"
    ],
    "name:ukr_x_preferred":[
        "\u0420\u0430\u0439\u043e\u043d\u0438 \u0422\u0430\u0434\u0436\u0438\u043a\u0438\u0441\u0442\u0430\u043d\u0443"
    ],
    "name:urd_x_preferred":[
        "\u062a\u0627\u062c\u06a9\u0633\u062a\u0627\u0646 \u06a9\u06d2 \u0627\u0636\u0644\u0627\u0639"
    ],
    "name:zho_x_preferred":[
        "\u5854\u5409\u514b\u65af\u5766\u7684\u884c\u653f\u533a"
    ],
    "qs:name":"Sovetskiy Rayon",
    "qs:photos_9r":0,
    "qs:photos_sr":0,
    "qs:pop_sr":"8",
    "wd:wordcount":246,
    "wof:name":"Sovetskiy Rayon",
    "wof:placetype":"localadmin",
    "wof:population":92545
},
  "geometry": {"coordinates":[41.45,52.71667],"type":"Point"}
}