{
  "type": "Feature",
  "properties": {
    "gn:country":"RU",
    "gn:fcode":"ADM3",
    "gn:pop":92545,
    "iso:country":"RU",
    "name:rus_x_preferred":[
        "\u0421\u043e\u0432\u0435\u0442\u0441\u043a\u0438\u0439 \u0420\u0430\u0439\u043e\u043d"
    ],
    "qs:name":"Sovetskiy Rayon",
    "qs:photos_9r":0,
    "qs:photos_sr":0,
    "qs:pop_sr":"8",
    "wd:wordcount":246,
    "wof:name":"Sovetskiy Rayon",
    "wof:placetype":"localadmin",
    "wof:population":92545
},
  "geometry": {"coordinates":[41.45,52.71667],"type":"Point"}
}