{
  "type": "Feature",
  "properties": {
    "gn:admin1_code":"73",
    "gn:asciiname":"Soloyaz",
    "gn:country_code":"RU",
    "gn:dem":250,
    "gn:feature_class":"P",
    "gn:feature_code":"PPL",
    "gn:name":"Soloyaz",
    "gn:population":0,
    "gn:timezone":"Europe/Moscow",
    "iso:country":"RU",
    "name:rus_x_preferred":[
        "\u0421\u043e\u043b\u043e\u044f\u0437"
    ],
    "name:und_x_variant":[
        "Soloyas\u2019",
        "Soloyaz",
        "\u0421\u043e\u043b\u043e\u044f\u0437"
    ],
    "wof:name":"Soloyaz",
    "wof:placetype":"locality"
},
  "geometry": {"coordinates":[52.91866,54.64378000000001],"type":"Point"}
}