{
  "type": "Feature",
  "properties": {
    "gn:admin1_code":"29",
    "gn:asciiname":"Zarechnyy",
    "gn:country_code":"RU",
    "gn:dem":316,
    "gn:feature_class":"P",
    "gn:feature_code":"PPL",
    "gn:name":"Zarechnyy",
    "gn:population":0,
    "gn:timezone":"Asia/Novokuznetsk",
    "iso:country":"RU",
    "name:rus_x_preferred":[
        "\u0417\u0430\u0440\u0435\u0447\u043d\u044b\u0439"
    ],
    "wof:name":"Zarechnyy",
    "wof:placetype":"locality"
},
  "geometry": {"coordinates":[85.73269999999999,54.2709],"type":"Point"}
}