{
  "type": "Feature",
  "properties": {
    "gn:admin1_code":"71",
    "gn:asciiname":"Chernoritskoye",
    "gn:country_code":"RU",
    "gn:dem":85,
    "gn:feature_class":"P",
    "gn:feature_code":"PPL",
    "gn:name":"Chernoritskoye",
    "gn:population":0,
    "gn:timezone":"Asia/Yekaterinburg",
    "iso:country":"RU",
    "name:eng_x_preferred":[
        "Chernoritskoye"
    ],
    "name:nor_x_preferred":[
        "Tsjernoritskoje"
    ],
    "name:rus_x_preferred":[
        "\u0427\u0435\u0440\u043d\u043e\u0440\u0438\u0446\u043a\u043e\u0435"
    ],
    "wof:name":"Chernoritskoye",
    "wof:placetype":"locality"
},
  "geometry": {"coordinates":[62.7493,57.4103],"type":"Point"}
}