{
  "type": "Feature",
  "properties": {
    "gn:admin1_code":"85.0",
    "gn:asciiname":"Isakovo",
    "gn:country_code":"RU",
    "gn:dem":165,
    "gn:feature_class":"P",
    "gn:feature_code":"PPL",
    "gn:name":"Isakovo",
    "gn:population":0,
    "gn:timezone":"Europe/Moscow",
    "iso:country":"RU",
    "name:rus_x_preferred":[
        "\u0418\u0441\u0430\u043a\u043e\u0432\u043e"
    ],
    "wof:name":"Isakovo",
    "wof:placetype":"locality"
},
  "geometry": {"coordinates":[37.6845,60.4359],"type":"Point"}
}