{
  "type": "Feature",
  "properties": {
    "gn:admin1_code":"53",
    "gn:asciiname":"Mironovka",
    "gn:country_code":"RU",
    "gn:dem":105,
    "gn:feature_class":"P",
    "gn:feature_code":"PPL",
    "gn:name":"Mironovka",
    "gn:population":0,
    "gn:timezone":"Asia/Novosibirsk",
    "iso:country":"RU",
    "name:eng_x_preferred":[
        "Mironovka"
    ],
    "name:nor_x_preferred":[
        "Mironovka"
    ],
    "name:rus_x_preferred":[
        "\u041c\u0438\u0440\u043e\u043d\u043e\u0432\u043a\u0430"
    ],
    "name:und_x_variant":[
        "\u041c\u0438\u0440\u043e\u043d\u043e\u0432\u043a\u0430",
        "Mironovka"
    ],
    "wof:name":"Mironovka",
    "wof:placetype":"locality"
},
  "geometry": {"coordinates":[76.14310999999999,54.5152],"type":"Point"}
}