{
  "type": "Feature",
  "properties": {
    "gn:admin1_code":"75.0",
    "gn:asciiname":"Leninskiy",
    "gn:country_code":"RU",
    "gn:dem":82,
    "gn:feature_class":"P",
    "gn:feature_code":"PPL",
    "gn:name":"Leninskiy",
    "gn:population":0,
    "gn:timezone":"Asia/Tomsk",
    "iso:country":"RU",
    "wof:name":"Leninskiy",
    "wof:placetype":"locality"
},
  "geometry": {"coordinates":[84.17114000000002,57.00476],"type":"Point"}
}