{
  "type": "Feature",
  "properties": {
    "gn:admin1_code":"69",
    "gn:asciiname":"Yeliseyevichi",
    "gn:country_code":"RU",
    "gn:dem":219,
    "gn:feature_class":"P",
    "gn:feature_code":"PPL",
    "gn:name":"Yeliseyevichi",
    "gn:population":0,
    "gn:timezone":"Europe/Moscow",
    "iso:country":"RU",
    "name:eng_x_preferred":[
        "Yeliseyevichi"
    ],
    "name:nor_x_preferred":[
        "Jelisejevitsji"
    ],
    "name:rus_x_preferred":[
        "\u0415\u043b\u0438\u0441\u0435\u0435\u0432\u0438\u0447\u0438"
    ],
    "wof:name":"Yeliseyevichi",
    "wof:placetype":"locality"
},
  "geometry": {"coordinates":[32.067,55.2796],"type":"Point"}
}