{
  "type": "Feature",
  "properties": {
    "gn:admin1_code":"77",
    "gn:asciiname":"Vysokovo",
    "gn:country_code":"RU",
    "gn:dem":157,
    "gn:feature_class":"P",
    "gn:feature_code":"PPL",
    "gn:name":"Vysokovo",
    "gn:population":0,
    "gn:timezone":"Europe/Moscow",
    "iso:country":"RU",
    "name:rus_x_preferred":[
        "\u0412\u044b\u0441\u043e\u043a\u043e\u0432\u043e"
    ],
    "wof:name":"Vysokovo",
    "wof:placetype":"locality"
},
  "geometry": {"coordinates":[36.4181,57.6902],"type":"Point"}
}