{
  "type": "Feature",
  "properties": {
    "gn:admin1_code":"41",
    "gn:asciiname":"Sotnikovo",
    "gn:country_code":"RU",
    "gn:dem":208,
    "gn:feature_class":"P",
    "gn:feature_code":"PPL",
    "gn:name":"Sotnikovo",
    "gn:population":0,
    "gn:timezone":"Europe/Moscow",
    "iso:country":"RU",
    "name:eng_x_preferred":[
        "Sotnikovo"
    ],
    "name:nor_x_preferred":[
        "Sotnikovo"
    ],
    "name:rus_x_preferred":[
        "\u0421\u043e\u0442\u043d\u0438\u043a\u043e\u0432\u043e"
    ],
    "name:und_x_variant":[
        "Arkhangelskoye"
    ],
    "wof:name":"Sotnikovo",
    "wof:placetype":"locality"
},
  "geometry": {"coordinates":[35.9708,52.1733],"type":"Point"}
}