{
  "type": "Feature",
  "properties": {
    "gn:admin1_code":"29",
    "gn:asciiname":"Magistral'nyy",
    "gn:country_code":"RU",
    "gn:dem":266,
    "gn:feature_class":"P",
    "gn:feature_code":"PPL",
    "gn:name":"Magistral\u2019nyy",
    "gn:population":0,
    "gn:timezone":"Asia/Novokuznetsk",
    "iso:country":"RU",
    "name:rus_x_preferred":[
        "\u041c\u0430\u0433\u0438\u0441\u0442\u0440\u0430\u043b\u044c\u043d\u044b\u0439"
    ],
    "name:und_x_variant":[
        "Magistral\u2019nyy",
        "\u041c\u0430\u0433\u0438\u0441\u0442\u0440\u0430\u043b\u044c\u043d\u044b\u0439"
    ],
    "wof:name":"Magistral'nyy",
    "wof:placetype":"locality"
},
  "geometry": {"coordinates":[85.29810000000001,55.184],"type":"Point"}
}