{
  "type": "Feature",
  "properties": {
    "gn:admin1_code":"56",
    "gn:asciiname":"Novo-Tsvetushchiy",
    "gn:country_code":"RU",
    "gn:dem":236,
    "gn:feature_class":"P",
    "gn:feature_code":"PPL",
    "gn:name":"Novo-Tsvetushchiy",
    "gn:population":0,
    "gn:timezone":"Europe/Moscow",
    "iso:country":"RU",
    "wof:name":"Novo-Tsvetushchiy",
    "wof:placetype":"locality"
},
  "geometry": {"coordinates":[35.59917,52.44944],"type":"Point"}
}