{
  "type": "Feature",
  "properties": {
    "gn:admin1_code":"54",
    "gn:asciiname":"Konovalikha",
    "gn:country_code":"RU",
    "gn:dem":90,
    "gn:feature_class":"P",
    "gn:feature_code":"PPL",
    "gn:name":"Konovalikha",
    "gn:population":0,
    "gn:timezone":"Asia/Omsk",
    "iso:country":"RU",
    "name:rus_x_preferred":[
        "\u041a\u043e\u043d\u043e\u0432\u0430\u043b\u0438\u0445\u0430"
    ],
    "name:und_x_variant":[
        "\u041a\u043e\u043d\u043e\u0432\u0430\u043b\u0438\u0445\u0430"
    ],
    "wof:name":"Konovalikha",
    "wof:placetype":"locality"
},
  "geometry": {"coordinates":[72.43899999999999,56.8441],"type":"Point"}
}