{
  "type": "Feature",
  "properties": {
    "gn:admin1_code":"56",
    "gn:asciiname":"Roshchenskiy",
    "gn:country_code":"RU",
    "gn:dem":230,
    "gn:feature_class":"P",
    "gn:feature_code":"PPL",
    "gn:name":"Roshchenskiy",
    "gn:population":0,
    "gn:timezone":"Europe/Moscow",
    "iso:country":"RU",
    "name:rus_x_preferred":[
        "\u0420\u043e\u0449\u0435\u043d\u0441\u043a\u0438\u0439"
    ],
    "name:und_x_variant":[
        "\u0420\u043e\u0449\u0435\u043d\u0441\u043a\u0438\u0439"
    ],
    "wof:name":"Roshchenskiy",
    "wof:placetype":"locality"
},
  "geometry": {"coordinates":[36.936,52.5095],"type":"Point"}
}