{
  "type": "Feature",
  "properties": {
    "gn:admin1_code":"32",
    "gn:asciiname":"Ust'-Balyk",
    "gn:country_code":"RU",
    "gn:dem":35,
    "gn:feature_class":"P",
    "gn:feature_code":"PPL",
    "gn:name":"Ust\u2019-Balyk",
    "gn:population":0,
    "gn:timezone":"Asia/Yekaterinburg",
    "iso:country":"RU",
    "wof:name":"Ust'-Balyk",
    "wof:placetype":"locality"
},
  "geometry": {"coordinates":[72.61043000000002,61.06918],"type":"Point"}
}