{
  "type": "Feature",
  "properties": {
    "gn:admin1_code":"23",
    "gn:asciiname":"Storozhevoye",
    "gn:cc2":"RU",
    "gn:country_code":"RU",
    "gn:dem":99,
    "gn:feature_class":"P",
    "gn:feature_code":"PPL",
    "gn:name":"Storozhevoye",
    "gn:population":0,
    "gn:timezone":"Europe/Kaliningrad",
    "iso:country":"RU",
    "name:rus_x_preferred":[
        "\u0421\u0442\u043e\u0440\u043e\u0436\u0435\u0432\u043e\u0435"
    ],
    "name:und_x_variant":[
        "Redden",
        "Storozhevoye",
        "\u0421\u0442\u043e\u0440\u043e\u0436\u0435\u0432\u043e\u0435"
    ],
    "wof:name":"Storozhevoye",
    "wof:placetype":"locality"
},
  "geometry": {"coordinates":[20.82222,54.38833],"type":"Point"}
}