{
  "type": "Feature",
  "properties": {
    "gn:admin1_code":"92",
    "gn:asciiname":"Verkhneye Kolpakovo",
    "gn:country_code":"RU",
    "gn:dem":43,
    "gn:feature_class":"P",
    "gn:feature_code":"PPL",
    "gn:name":"Verkhneye Kolpakovo",
    "gn:population":0,
    "gn:timezone":"Asia/Kamchatka",
    "iso:country":"RU",
    "wof:name":"Verkhneye Kolpakovo",
    "wof:placetype":"locality"
},
  "geometry": {"coordinates":[155.86667,54.63333000000001],"type":"Point"}
}