{
  "type": "Feature",
  "properties": {
    "gn:admin1_code":"43",
    "gn:asciiname":"Satino",
    "gn:country_code":"RU",
    "gn:dem":194,
    "gn:feature_class":"P",
    "gn:feature_code":"PPL",
    "gn:name":"Satino",
    "gn:population":0,
    "gn:timezone":"Europe/Moscow",
    "iso:country":"RU",
    "name:rus_x_preferred":[
        "\u0421\u0430\u0442\u0438\u043d\u043e"
    ],
    "name:und_x_variant":[
        "\u0421\u0430\u0442\u0438\u043d\u043e",
        "Urochishche Satino"
    ],
    "wof:name":"Satino",
    "wof:placetype":"locality"
},
  "geometry": {"coordinates":[39.44098,52.98193000000001],"type":"Point"}
}