{
  "type": "Feature",
  "properties": {
    "gn:admin1_code":"41",
    "gn:asciiname":"Prilepy",
    "gn:country_code":"RU",
    "gn:dem":187,
    "gn:feature_class":"P",
    "gn:feature_code":"PPL",
    "gn:name":"Prilepy",
    "gn:population":0,
    "gn:timezone":"Europe/Moscow",
    "iso:country":"RU",
    "name:rus_x_preferred":[
        "\u041f\u0440\u0438\u043b\u0435\u043f\u044b"
    ],
    "wof:name":"Prilepy",
    "wof:placetype":"locality"
},
  "geometry": {"coordinates":[37.3407,51.8674],"type":"Point"}
}