{
  "type": "Feature",
  "properties": {
    "gn:admin1_code":"60",
    "gn:asciiname":"Mokritsa",
    "gn:country_code":"RU",
    "gn:dem":99,
    "gn:feature_class":"P",
    "gn:feature_code":"PPL",
    "gn:name":"Mokritsa",
    "gn:population":0,
    "gn:timezone":"Europe/Moscow",
    "iso:country":"RU",
    "name:rus_x_preferred":[
        "\u041c\u043e\u043a\u0440\u0438\u0446\u0430"
    ],
    "name:und_x_variant":[
        "Mokritsy",
        "Mokritsa"
    ],
    "wof:name":"Mokritsa",
    "wof:placetype":"locality"
},
  "geometry": {"coordinates":[28.8962,57.24977],"type":"Point"}
}