{
  "type": "Feature",
  "properties": {
    "gn:admin1_code":"60",
    "gn:asciiname":"Dekhovo",
    "gn:country_code":"RU",
    "gn:dem":132,
    "gn:feature_class":"P",
    "gn:feature_code":"PPL",
    "gn:name":"Dekhovo",
    "gn:population":0,
    "gn:timezone":"Europe/Moscow",
    "iso:country":"RU",
    "name:rus_x_preferred":[
        "\u0414\u0435\u0445\u043e\u0432\u043e"
    ],
    "wof:name":"Dekhovo",
    "wof:placetype":"locality"
},
  "geometry": {"coordinates":[29.943,56.8772],"type":"Point"}
}