{
  "type": "Feature",
  "properties": {
    "gn:admin1_code":"29",
    "gn:asciiname":"Akimo-Annenka",
    "gn:country_code":"RU",
    "gn:dem":271,
    "gn:feature_class":"P",
    "gn:feature_code":"PPL",
    "gn:name":"Akimo-Annenka",
    "gn:population":0,
    "gn:timezone":"Asia/Novokuznetsk",
    "iso:country":"RU",
    "name:eng_x_preferred":[
        "Akimo-Annenka"
    ],
    "name:nor_x_preferred":[
        "Akimo-Annenka"
    ],
    "name:rus_x_preferred":[
        "\u0410\u043a\u0438\u043c\u043e-\u0410\u043d\u043d\u0435\u043d\u043a\u0430"
    ],
    "name:und_x_variant":[
        "Akimo-Anninskoye"
    ],
    "wof:name":"Akimo-Annenka",
    "wof:placetype":"locality"
},
  "geometry": {"coordinates":[88.79470000000001,56.08031],"type":"Point"}
}