{
  "type": "Feature",
  "properties": {
    "gn:admin1_code":"51",
    "gn:asciiname":"Shchedrino",
    "gn:country_code":"RU",
    "gn:dem":128,
    "gn:feature_class":"P",
    "gn:feature_code":"PPL",
    "gn:name":"Shchedrino",
    "gn:population":0,
    "gn:timezone":"Europe/Moscow",
    "iso:country":"RU",
    "name:rus_x_preferred":[
        "\u0429\u0435\u0434\u0440\u0438\u043d\u043e"
    ],
    "name:und_x_variant":[
        "\u0429\u0435\u0434\u0440\u0438\u043d\u043e"
    ],
    "wof:name":"Shchedrino",
    "wof:placetype":"locality"
},
  "geometry": {"coordinates":[42.7258,55.9286],"type":"Point"}
}