{
  "type": "Feature",
  "properties": {
    "gn:admin1_code":"31.0",
    "gn:asciiname":"Listvennyy",
    "gn:country_code":"RU",
    "gn:dem":443,
    "gn:feature_class":"P",
    "gn:feature_code":"PPL",
    "gn:name":"Listvennyy",
    "gn:population":0,
    "gn:timezone":"Asia/Krasnoyarsk",
    "iso:country":"RU",
    "name:rus_x_preferred":[
        "\u041b\u0438\u0441\u0442\u0432\u0435\u043d\u043d\u044b\u0439"
    ],
    "wof:name":"Listvennyy",
    "wof:placetype":"locality"
},
  "geometry": {"coordinates":[90.69167,54.81611],"type":"Point"}
}