{
  "type": "Feature",
  "properties": {
    "gn:country":"RU",
    "gn:fcode":"PPL",
    "gn:pop":0,
    "iso:country":"RU",
    "name:rus_x_preferred":[
        "\u042f\u0433\u0440\u044b"
    ],
    "name:unk_x_variant":[
        "Yagry"
    ],
    "qs:name":"Yagrysh",
    "qs:name_adm0":"Russia",
    "qs:name_adm1":"Arkhangelsk Oblast",
    "qs:photos_9r":0,
    "qs:photos_sr":0,
    "qs:placetype":"Town",
    "qs:pop_sr":"0",
    "wof:name":"Yagrysh",
    "wof:placetype":"locality",
    "wof:population":0
},
  "geometry": {"coordinates":[39.81028,64.59417000000001],"type":"Point"}
}