{
  "type": "Feature",
  "properties": {
    "gn:admin1_code":"64",
    "gn:admin2_code":"2128971",
    "gn:asciiname":"Kitaura",
    "gn:country_code":"RU",
    "gn:dem":4,
    "gn:feature_class":"P",
    "gn:feature_code":"PPL",
    "gn:name":"Kitaura",
    "gn:population":0,
    "gn:timezone":"Asia/Magadan",
    "iso:country":"RU",
    "name:jpn_x_preferred":[
        "\u5317\u6d66"
    ],
    "name:jpn_x_variant":[
        "\u304d\u305f\u3046\u3089",
        "\u30ad\u30bf\u30a6\u30e9"
    ],
    "wof:name":"Kitaura",
    "wof:placetype":"locality"
},
  "geometry": {"coordinates":[146.10706999999999,43.53744],"type":"Point"}
}