{
  "type": "Feature",
  "properties": {
    "gn:admin1_code":"52",
    "gn:asciiname":"Grebnya",
    "gn:country_code":"RU",
    "gn:dem":48,
    "gn:feature_class":"P",
    "gn:feature_code":"PPL",
    "gn:name":"Grebnya",
    "gn:population":0,
    "gn:timezone":"Europe/Moscow",
    "iso:country":"RU",
    "name:eng_x_preferred":[
        "Grebnya"
    ],
    "name:nor_x_preferred":[
        "Grebnja"
    ],
    "name:rus_x_preferred":[
        "\u0413\u0440\u0435\u0431\u043d\u044f"
    ],
    "name:und_x_variant":[
        "Gribnya"
    ],
    "wof:name":"Grebnya",
    "wof:placetype":"locality"
},
  "geometry": {"coordinates":[30.19427,58.03494],"type":"Point"}
}