{
  "type": "Feature",
  "properties": {
    "gn:admin1_code":"53.0",
    "gn:asciiname":"Zelenaya Roshcha",
    "gn:country_code":"RU",
    "gn:dem":130,
    "gn:feature_class":"P",
    "gn:feature_code":"PPL",
    "gn:name":"Zel\u00ebnaya Roshcha",
    "gn:population":0,
    "gn:timezone":"Asia/Novosibirsk",
    "iso:country":"RU",
    "name:rus_x_preferred":[
        "\u0417\u0435\u043b\u00eb\u043d\u0430\u044f \u0420\u043e\u0449\u0430"
    ],
    "name:und_x_variant":[
        "Zel\u00ebnaya Roshcha"
    ],
    "wof:name":"Zelenaya Roshcha",
    "wof:placetype":"locality"
},
  "geometry": {"coordinates":[83.05070000000001,54.744],"type":"Point"}
}