{
  "type": "Feature",
  "properties": {
    "gn:admin1_code":"72",
    "gn:asciiname":"Krasnoye Znamya",
    "gn:cc2":"RU",
    "gn:country_code":"RU",
    "gn:dem":163,
    "gn:feature_class":"P",
    "gn:feature_code":"PPL",
    "gn:name":"Krasnoye Znamya",
    "gn:population":0,
    "gn:timezone":"Europe/Moscow",
    "iso:country":"RU",
    "name:rus_x_preferred":[
        "\u041a\u0440\u0430\u0441\u043d\u043e\u0435 \u0417\u043d\u0430\u043c\u044f"
    ],
    "name:und_x_variant":[
        "Petrovskiy",
        "Krasnoye Znamya",
        "\u041a\u0440\u0430\u0441\u043d\u043e\u0435 \u0417\u043d\u0430\u043c\u044f"
    ],
    "wof:name":"Krasnoye Znamya",
    "wof:placetype":"locality"
},
  "geometry": {"coordinates":[41.3525,52.16111],"type":"Point"}
}