{
  "type": "Feature",
  "properties": {
    "gn:admin1_code":"33",
    "gn:asciiname":"Nadsadiny",
    "gn:country_code":"RU",
    "gn:dem":127,
    "gn:feature_class":"P",
    "gn:feature_code":"PPL",
    "gn:name":"Nadsadiny",
    "gn:population":0,
    "gn:timezone":"Europe/Kirov",
    "iso:country":"RU",
    "name:rus_x_preferred":[
        "\u041d\u0430\u0434\u0441\u0430\u0434\u0438\u043d\u044b"
    ],
    "wof:name":"Nadsadiny",
    "wof:placetype":"locality"
},
  "geometry": {"coordinates":[49.1374,58.3851],"type":"Point"}
}