{
  "type": "Feature",
  "properties": {
    "gn:admin1_code":"8",
    "gn:asciiname":"Staryye Sharashli",
    "gn:country_code":"RU",
    "gn:dem":102,
    "gn:feature_class":"P",
    "gn:feature_code":"PPL",
    "gn:name":"Staryye Sharashli",
    "gn:population":0,
    "gn:timezone":"Asia/Yekaterinburg",
    "iso:country":"RU",
    "name:aze_x_preferred":[
        "K\u00f6hn\u0259 \u015e\u0259r\u0259li"
    ],
    "name:bak_x_preferred":[
        "\u0418\u04ab\u043a\u0435 \u0428\u04d9\u0440\u04d9\u0448\u043b\u0435"
    ],
    "name:che_x_preferred":[
        "\u0421\u0442\u0430\u0440\u0438 \u0428\u0430\u0440\u0430\u0448\u043b\u0438"
    ],
    "name:eng_x_preferred":[
        "Staryye Sharashli"
    ],
    "name:hye_x_preferred":[
        "\u054d\u057f\u0561\u0580\u056b\u0565 \u0547\u0561\u0580\u0561\u0577\u056c\u056b"
    ],
    "name:kaz_x_preferred":[
        "\u0421\u0442\u0430\u0440\u044b\u0435 \u0428\u0430\u0440\u0430\u0448\u043b\u0438"
    ],
    "name:kir_x_preferred":[
        "\u0421\u0442\u0430\u0440\u044b\u0435 \u0428\u0430\u0440\u0430\u0448\u043b\u0438"
    ],
    "name:nor_x_preferred":[
        "Starye Sjarasjli"
    ],
    "name:rus_x_preferred":[
        "\u0421\u0442\u0430\u0440\u044b\u0435 \u0428\u0430\u0440\u0430\u0448\u043b\u0438"
    ],
    "name:tat_x_preferred":[
        "\u0418\u0441\u043a\u0435 \u0428\u04d9\u0440\u04d9\u0448\u043b\u0435"
    ],
    "name:und_x_variant":[
        "Sherashly",
        "Staryye Sharashly",
        "\u0421\u0442\u0430\u0440\u044b\u0435 \u0428\u0430\u0440\u0430\u0448\u043b\u0438",
        "Staryye Sharashli"
    ],
    "wof:name":"Staryye Sharashli",
    "wof:placetype":"locality"
},
  "geometry": {"coordinates":[53.75361,55.22056],"type":"Point"}
}