{
  "type": "Feature",
  "properties": {
    "gn:admin1_code":"8",
    "gn:asciiname":"Staryye Sharashli",
    "gn:country_code":"RU",
    "gn:dem":102,
    "gn:feature_class":"P",
    "gn:feature_code":"PPL",
    "gn:name":"Staryye Sharashli",
    "gn:population":0,
    "gn:timezone":"Asia/Yekaterinburg",
    "iso:country":"RU",
    "name:eng_x_preferred":[
        "Staryye Sharashli"
    ],
    "name:nor_x_preferred":[
        "Starye Sjarasjli"
    ],
    "name:rus_x_preferred":[
        "\u0421\u0442\u0430\u0440\u044b\u0435 \u0428\u0430\u0440\u0430\u0448\u043b\u0438"
    ],
    "name:und_x_variant":[
        "Sherashly",
        "Staryye Sharashly",
        "\u0421\u0442\u0430\u0440\u044b\u0435 \u0428\u0430\u0440\u0430\u0448\u043b\u0438",
        "Staryye Sharashli"
    ],
    "wof:name":"Staryye Sharashli",
    "wof:placetype":"locality"
},
  "geometry": {"coordinates":[53.75361,55.22056],"type":"Point"}
}