{
  "type": "Feature",
  "properties": {
    "gn:admin1_code":"73",
    "gn:asciiname":"Novoye Kamkino",
    "gn:country_code":"RU",
    "gn:dem":109,
    "gn:feature_class":"P",
    "gn:feature_code":"PPL",
    "gn:name":"Novoye Kamkino",
    "gn:population":0,
    "gn:timezone":"Europe/Moscow",
    "iso:country":"RU",
    "name:rus_x_preferred":[
        "\u041d\u043e\u0432\u043e\u0435 \u041a\u0430\u043c\u043a\u0438\u043d\u043e"
    ],
    "wof:name":"Novoye Kamkino",
    "wof:placetype":"locality"
},
  "geometry": {"coordinates":[50.0958,54.8716],"type":"Point"}
}