{
  "type": "Feature",
  "properties": {
    "gn:admin1_code":"33.0",
    "gn:asciiname":"Nagorena",
    "gn:country_code":"RU",
    "gn:dem":150,
    "gn:feature_class":"P",
    "gn:feature_code":"PPL",
    "gn:name":"Nagorena",
    "gn:population":0,
    "gn:timezone":"Europe/Kirov",
    "iso:country":"RU",
    "name:rus_x_preferred":[
        "\u041d\u0430\u0433\u043e\u0440\u0435\u043d\u0430"
    ],
    "name:und_x_variant":[
        "Nagorino",
        "Nagorena"
    ],
    "wof:name":"Nagorena",
    "wof:placetype":"locality"
},
  "geometry": {"coordinates":[50.05104,58.37914],"type":"Point"}
}