{
  "type": "Feature",
  "properties": {
    "gn:admin1_code":"47.0",
    "gn:asciiname":"Dorofeyevo",
    "gn:country_code":"RU",
    "gn:dem":115,
    "gn:feature_class":"P",
    "gn:feature_code":"PPL",
    "gn:name":"Dorofeyevo",
    "gn:population":0,
    "gn:timezone":"Europe/Moscow",
    "iso:country":"RU",
    "name:rus_x_preferred":[
        "\u0414\u043e\u0440\u043e\u0444\u0435\u0435\u0432\u043e"
    ],
    "name:und_x_variant":[
        "\u0414\u043e\u0440\u043e\u0444\u0435\u0435\u0432\u043e"
    ],
    "wof:name":"Dorofeyevo",
    "wof:placetype":"locality"
},
  "geometry": {"coordinates":[40.10826,55.2939],"type":"Point"}
}