{
  "type": "Feature",
  "properties": {
    "gn:admin1_code":"78",
    "gn:asciiname":"Syrovskiye",
    "gn:cc2":"RU",
    "gn:country_code":"RU",
    "gn:dem":95,
    "gn:feature_class":"P",
    "gn:feature_code":"PPL",
    "gn:name":"Syrovskiye",
    "gn:population":0,
    "gn:timezone":"Asia/Yekaterinburg",
    "iso:country":"RU",
    "name:und_x_variant":[
        "Yurty Syrovskiye",
        "Syrovskiye"
    ],
    "wof:name":"Syrovskiye",
    "wof:placetype":"locality"
},
  "geometry": {"coordinates":[71.90000000000001,59.21666999999999],"type":"Point"}
}