{
  "type": "Feature",
  "properties": {
    "gn:admin1_code":"42",
    "gn:asciiname":"Radoveli",
    "gn:country_code":"RU",
    "gn:dem":45,
    "gn:feature_class":"P",
    "gn:feature_code":"PPL",
    "gn:name":"Radoveli",
    "gn:population":0,
    "gn:timezone":"Europe/Moscow",
    "iso:country":"RU",
    "name:rus_x_preferred":[
        "\u0420\u0430\u0434\u043e\u0432\u0435\u043b\u0438"
    ],
    "wof:name":"Radoveli",
    "wof:placetype":"locality"
},
  "geometry": {"coordinates":[27.86871,59.08316],"type":"Point"}
}