{
  "type": "Feature",
  "properties": {
    "gn:admin1_code":"29",
    "gn:asciiname":"Bardyshevo",
    "gn:country_code":"RU",
    "gn:dem":577,
    "gn:feature_class":"P",
    "gn:feature_code":"PPL",
    "gn:name":"Bardyshevo",
    "gn:population":0,
    "gn:timezone":"Asia/Novokuznetsk",
    "iso:country":"RU",
    "name:nor_x_preferred":[
        "Bardysjevo"
    ],
    "name:rus_x_preferred":[
        "\u0411\u0430\u0440\u0434\u044b\u0448\u0435\u0432\u043e"
    ],
    "name:und_x_variant":[
        "Bedryshevo",
        "Bardyshevo"
    ],
    "wof:name":"Bardyshevo",
    "wof:placetype":"locality"
},
  "geometry": {"coordinates":[88.76666999999998,52.66667],"type":"Point"}
}