{
  "type": "Feature",
  "properties": {
    "gn:country":"RU",
    "gn:fcode":"PPL",
    "gn:pop":0,
    "iso:country":"RU",
    "name:eng_x_preferred":[
        "Yadromino"
    ],
    "name:nor_x_preferred":[
        "Jadromino"
    ],
    "name:rus_x_preferred":[
        "\u042f\u0434\u0440\u043e\u043c\u0438\u043d\u043e"
    ],
    "name:unk_x_variant":[
        "Yadremino"
    ],
    "qs:name":"Yadromino",
    "qs:name_adm0":"Russia",
    "qs:name_adm1":"Moscow Oblast",
    "qs:photos_9k":1,
    "qs:photos_9r":1,
    "qs:photos_all":7,
    "qs:photos_sr":0,
    "qs:placetype":"Town",
    "qs:pop_sr":"0",
    "wof:name":"Yadromino",
    "wof:placetype":"locality",
    "wof:population":0
},
  "geometry": {"coordinates":[36.59028,55.94417],"type":"Point"}
}