{
  "type": "Feature",
  "properties": {
    "gn:admin1_code":"69",
    "gn:asciiname":"Moskal'ki",
    "gn:country_code":"RU",
    "gn:dem":219,
    "gn:feature_class":"P",
    "gn:feature_code":"PPL",
    "gn:name":"Moskal\u2019ki",
    "gn:population":0,
    "gn:timezone":"Europe/Moscow",
    "iso:country":"RU",
    "name:rus_x_preferred":[
        "\u041c\u043e\u0441\u043a\u0430\u043b\u044c\u043a\u0438"
    ],
    "name:und_x_variant":[
        "Moskal\u2019ki"
    ],
    "wof:name":"Moskal'ki",
    "wof:placetype":"locality"
},
  "geometry": {"coordinates":[31.05,55.15],"type":"Point"}
}