{
  "type": "Feature",
  "properties": {
    "gn:admin1_code":"57",
    "gn:asciiname":"Ol'shanka",
    "gn:country_code":"RU",
    "gn:dem":185,
    "gn:feature_class":"P",
    "gn:feature_code":"PPL",
    "gn:name":"Ol\u2019shanka",
    "gn:population":0,
    "gn:timezone":"Europe/Moscow",
    "iso:country":"RU",
    "name:rus_x_preferred":[
        "\u041e\u043b\u044c\u0448\u0430\u043d\u043a\u0430"
    ],
    "name:und_x_variant":[
        "Ol\u2019shanka",
        "\u041e\u043b\u044c\u0448\u0430\u043d\u043a\u0430"
    ],
    "wof:name":"Ol'shanka",
    "wof:placetype":"locality"
},
  "geometry": {"coordinates":[43.18333,52.48333],"type":"Point"}
}