{
  "type": "Feature",
  "properties": {
    "gn:admin1_code":"28.0",
    "gn:asciiname":"Bol'shoy Kuganavolok",
    "gn:country_code":"RU",
    "gn:dem":118,
    "gn:feature_class":"P",
    "gn:feature_code":"PPL",
    "gn:name":"Bol\u2019shoy Kuganavolok",
    "gn:population":500,
    "gn:timezone":"Europe/Moscow",
    "iso:country":"RU",
    "name:eng_x_preferred":[
        "Bol'shoy Kuganavolok"
    ],
    "name:nor_x_preferred":[
        "Kuganavolok"
    ],
    "name:rus_x_preferred":[
        "\u041a\u0443\u0433\u0430\u043d\u0430\u0432\u043e\u043b\u043e\u043a"
    ],
    "name:rus_x_variant":[
        "\u0411\u043e\u043b\u044c\u0448\u043e\u0439 \u041a\u0443\u0433\u0430\u043d\u0430\u0432\u043e\u043b\u043e\u043a"
    ],
    "name:und_x_variant":[
        "Iso Kuhaniemi",
        "Kuganovolok",
        "Bol\u2019shoy Guknavolok",
        "Guknavolok",
        "Bol\u2019shoy Kuganavolok"
    ],
    "wof:name":"Bol'shoy Kuganavolok",
    "wof:placetype":"locality",
    "wof:population":500
},
  "geometry": {"coordinates":[36.88442,62.23568],"type":"Point"}
}