{
  "type": "Feature",
  "properties": {
    "gn:admin1_code":"62",
    "gn:asciiname":"Shakhmanovo",
    "gn:country_code":"RU",
    "gn:dem":129,
    "gn:feature_class":"P",
    "gn:feature_code":"PPL",
    "gn:name":"Shakhmanovo",
    "gn:population":0,
    "gn:timezone":"Europe/Moscow",
    "iso:country":"RU",
    "name:rus_x_preferred":[
        "\u0428\u0430\u0445\u043c\u0430\u043d\u043e\u0432\u043e"
    ],
    "wof:name":"Shakhmanovo",
    "wof:placetype":"locality"
},
  "geometry": {"coordinates":[39.5613,54.6493],"type":"Point"}
}