{
  "type": "Feature",
  "properties": {
    "gn:admin1_code":"51",
    "gn:asciiname":"Vily",
    "gn:country_code":"RU",
    "gn:dem":121,
    "gn:feature_class":"P",
    "gn:feature_code":"PPL",
    "gn:name":"Vily",
    "gn:population":0,
    "gn:timezone":"Europe/Moscow",
    "iso:country":"RU",
    "name:rus_x_preferred":[
        "\u0412\u0438\u043b\u044b"
    ],
    "wof:name":"Vily",
    "wof:placetype":"locality"
},
  "geometry": {"coordinates":[45.2101,54.8181],"type":"Point"}
}