{
  "type": "Feature",
  "properties": {
    "gn:admin1_code":"28",
    "gn:asciiname":"Shuoyarvi",
    "gn:country_code":"RU",
    "gn:dem":147,
    "gn:feature_class":"P",
    "gn:feature_code":"PPL",
    "gn:name":"Shuoyarvi",
    "gn:population":0,
    "gn:timezone":"Europe/Moscow",
    "iso:country":"RU",
    "name:fin_x_preferred":[
        "Suoj\u00e4rvi"
    ],
    "name:rus_x_preferred":[
        "\u0428\u0443\u043e\u044f\u0440\u0432\u0438"
    ],
    "name:und_x_variant":[
        "\u0428\u0443\u043e\u044f\u0440\u0432\u0438"
    ],
    "wof:name":"Shuoyarvi",
    "wof:placetype":"locality"
},
  "geometry": {"coordinates":[30.96667,64.71666999999999],"type":"Point"}
}