{
  "type": "Feature",
  "properties": {
    "gn:admin1_code":"77",
    "gn:asciiname":"L'ba Kroty",
    "gn:country_code":"RU",
    "gn:dem":186,
    "gn:feature_class":"P",
    "gn:feature_code":"PPL",
    "gn:name":"L\u2019ba Kroty",
    "gn:population":0,
    "gn:timezone":"Europe/Moscow",
    "iso:country":"RU",
    "wof:name":"L'ba Kroty",
    "wof:placetype":"locality"
},
  "geometry": {"coordinates":[32.87972,55.88028000000001],"type":"Point"}
}