{
  "type": "Feature",
  "properties": {
    "gn:admin1_code":"34.0",
    "gn:asciiname":"Denisovka",
    "gn:country_code":"RU",
    "gn:dem":30,
    "gn:feature_class":"P",
    "gn:feature_code":"PPL",
    "gn:name":"Denisovka",
    "gn:population":0,
    "gn:timezone":"Europe/Moscow",
    "iso:country":"RU",
    "name:ceb_x_preferred":[
        "Denisovka"
    ],
    "name:eng_x_preferred":[
        "Denisovka"
    ],
    "name:nor_x_preferred":[
        "Denisovka"
    ],
    "name:rus_x_preferred":[
        "\u0414\u0435\u043d\u0438\u0441\u043e\u0432\u043a\u0430"
    ],
    "name:swe_x_preferred":[
        "Denisovka"
    ],
    "name:und_x_variant":[
        "Minya",
        "Denisovskaya-Shchal\u2019ya-Bozh",
        "\u0414\u0435\u043d\u0438\u0441\u043e\u0432\u043a\u0430",
        "Denisovka"
    ],
    "wof:name":"Denisovka",
    "wof:placetype":"locality"
},
  "geometry": {"coordinates":[55.42859,66.20522],"type":"Point"}
}