{
  "type": "Feature",
  "properties": {
    "gn:admin1_code":"40",
    "gn:asciiname":"Pokrovka",
    "gn:country_code":"RU",
    "gn:dem":160,
    "gn:feature_class":"P",
    "gn:feature_code":"PPL",
    "gn:name":"Pokrovka",
    "gn:population":0,
    "gn:timezone":"Asia/Yekaterinburg",
    "iso:country":"RU",
    "name:eng_x_preferred":[
        "Pokrovka"
    ],
    "name:nor_x_preferred":[
        "Pokrovka"
    ],
    "name:rus_x_preferred":[
        "\u041f\u043e\u043a\u0440\u043e\u0432\u043a\u0430"
    ],
    "name:und_x_variant":[
        "\u041f\u043e\u043a\u0440\u043e\u0432\u043a\u0430",
        "Pokrovka"
    ],
    "wof:name":"Pokrovka",
    "wof:placetype":"locality"
},
  "geometry": {"coordinates":[65.32583000000001,54.83556],"type":"Point"}
}