{
  "type": "Feature",
  "properties": {
    "gn:admin1_code":"60",
    "gn:asciiname":"Vyazka",
    "gn:country_code":"RU",
    "gn:dem":123,
    "gn:feature_class":"P",
    "gn:feature_code":"PPL",
    "gn:name":"Vyazka",
    "gn:population":0,
    "gn:timezone":"Europe/Moscow",
    "iso:country":"RU",
    "name:eng_x_preferred":[
        "Vyazka"
    ],
    "name:nor_x_preferred":[
        "Vjazka"
    ],
    "name:rus_x_preferred":[
        "\u0412\u044f\u0437\u043a\u0430"
    ],
    "name:und_x_variant":[
        "Vyazki",
        "Vyazka"
    ],
    "wof:name":"Vyazka",
    "wof:placetype":"locality"
},
  "geometry": {"coordinates":[29.03495,58.43454000000001],"type":"Point"}
}