{
  "type": "Feature",
  "properties": {
    "gn:admin1_code":"77",
    "gn:asciiname":"Mishkovo",
    "gn:country_code":"RU",
    "gn:dem":215,
    "gn:feature_class":"P",
    "gn:feature_code":"PPL",
    "gn:name":"Mishkovo",
    "gn:population":0,
    "gn:timezone":"Europe/Moscow",
    "iso:country":"RU",
    "name:rus_x_preferred":[
        "\u041c\u0438\u0448\u043a\u043e\u0432\u043e"
    ],
    "wof:name":"Mishkovo",
    "wof:placetype":"locality"
},
  "geometry": {"coordinates":[32.10005,56.47371999999999],"type":"Point"}
}