{
  "type": "Feature",
  "properties": {
    "gn:admin1_code":"11",
    "gn:asciiname":"Kharauz",
    "gn:country_code":"RU",
    "gn:dem":453,
    "gn:feature_class":"P",
    "gn:feature_code":"PPL",
    "gn:name":"Kharauz",
    "gn:population":0,
    "gn:timezone":"Asia/Irkutsk",
    "iso:country":"RU",
    "name:rus_x_preferred":[
        "\u0425\u0430\u0440\u0430\u0443\u0437"
    ],
    "name:und_x_variant":[
        "\u0425\u0430\u0440\u0430\u0443\u0437"
    ],
    "wof:name":"Kharauz",
    "wof:placetype":"locality"
},
  "geometry": {"coordinates":[106.28333000000001,52.26667],"type":"Point"}
}