{
  "type": "Feature",
  "properties": {
    "gn:admin1_code":"60",
    "gn:asciiname":"Pruzhki",
    "gn:country_code":"RU",
    "gn:dem":87,
    "gn:feature_class":"P",
    "gn:feature_code":"PPL",
    "gn:name":"Pruzhki",
    "gn:population":0,
    "gn:timezone":"Europe/Moscow",
    "iso:country":"RU",
    "name:rus_x_preferred":[
        "\u041f\u0440\u0443\u0436\u043a\u0438"
    ],
    "wof:name":"Pruzhki",
    "wof:placetype":"locality"
},
  "geometry": {"coordinates":[28.77283,56.73881],"type":"Point"}
}