{
  "type": "Feature",
  "properties": {
    "gn:admin1_code":"71",
    "gn:asciiname":"Chernogorskiy",
    "gn:country_code":"RU",
    "gn:dem":83,
    "gn:feature_class":"P",
    "gn:feature_code":"PPL",
    "gn:name":"Chernogorskiy",
    "gn:population":0,
    "gn:timezone":"Asia/Yekaterinburg",
    "iso:country":"RU",
    "name:rus_x_preferred":[
        "\u0427\u0435\u0440\u043d\u043e\u0433\u043e\u0440\u0441\u043a\u0438\u0439"
    ],
    "name:und_x_variant":[
        "\u0427\u0435\u0440\u043d\u043e\u0433\u043e\u0440\u0441\u043a\u0438\u0439"
    ],
    "wof:name":"Chernogorskiy",
    "wof:placetype":"locality"
},
  "geometry": {"coordinates":[60.45,60.85],"type":"Point"}
}