{
  "type": "Feature",
  "properties": {
    "gn:admin1_code":"63",
    "gn:asciiname":"Ukachkina",
    "gn:country_code":"RU",
    "gn:dem":1,
    "gn:feature_class":"P",
    "gn:feature_code":"PPL",
    "gn:name":"Ukachkina",
    "gn:population":0,
    "gn:timezone":"Asia/Magadan",
    "iso:country":"RU",
    "wof:name":"Ukachkina",
    "wof:placetype":"locality"
},
  "geometry": {"coordinates":[161.16666999999995,68.59999999999999],"type":"Point"}
}