{
  "type": "Feature",
  "properties": {
    "gn:admin1_code":"23",
    "gn:asciiname":"Slavskoye",
    "gn:country_code":"RU",
    "gn:dem":42,
    "gn:feature_class":"P",
    "gn:feature_code":"PPL",
    "gn:name":"Slavskoye",
    "gn:population":0,
    "gn:timezone":"Europe/Kaliningrad",
    "iso:country":"RU",
    "name:che_x_preferred":[
        "\u0421\u043b\u0430\u0432\u0441\u043a\u0438"
    ],
    "name:deu_x_preferred":[
        "Slawskoje"
    ],
    "name:eng_x_preferred":[
        "Slavskoye"
    ],
    "name:hye_x_preferred":[
        "\u054d\u056c\u0561\u057e\u057d\u056f\u0578\u0565"
    ],
    "name:ita_x_preferred":[
        "Slavskoe"
    ],
    "name:lit_x_preferred":[
        "Kry\u017ebarkas"
    ],
    "name:nor_x_preferred":[
        "Slavskoje"
    ],
    "name:pol_x_preferred":[
        "S\u0142awskoje"
    ],
    "name:rus_x_preferred":[
        "\u0421\u043b\u0430\u0432\u0441\u043a\u043e\u0435"
    ],
    "name:ukr_x_preferred":[
        "\u0421\u043b\u0430\u0432\u0441\u044c\u043a\u0435"
    ],
    "name:und_x_variant":[
        "Evino",
        "Kreytsburg",
        "Kroytsburg",
        "Kreuzburg"
    ],
    "wof:name":"Slavskoye",
    "wof:placetype":"locality"
},
  "geometry": {"coordinates":[20.44082,54.49946],"type":"Point"}
}