{
  "type": "Feature",
  "properties": {
    "gn:admin1_code":"23",
    "gn:asciiname":"Slavskoye",
    "gn:country_code":"RU",
    "gn:dem":42,
    "gn:feature_class":"P",
    "gn:feature_code":"PPL",
    "gn:name":"Slavskoye",
    "gn:population":0,
    "gn:timezone":"Europe/Kaliningrad",
    "iso:country":"RU",
    "name:eng_x_preferred":[
        "Slavskoye"
    ],
    "name:nor_x_preferred":[
        "Slavskoje"
    ],
    "name:rus_x_preferred":[
        "\u0421\u043b\u0430\u0432\u0441\u043a\u043e\u0435"
    ],
    "name:und_x_variant":[
        "Evino",
        "Slavskoe",
        "Kreytsburg",
        "Kroytsburg",
        "Kreuzburg",
        "\u0421\u043b\u0430\u0432\u0441\u043a\u043e\u0435",
        "Slavskoye"
    ],
    "wof:name":"Slavskoye",
    "wof:placetype":"locality"
},
  "geometry": {"coordinates":[20.44082,54.49946],"type":"Point"}
}