{
  "type": "Feature",
  "properties": {
    "gn:admin1_code":"41",
    "gn:asciiname":"Nikulino",
    "gn:country_code":"RU",
    "gn:dem":173,
    "gn:feature_class":"P",
    "gn:feature_code":"PPL",
    "gn:name":"Nikulino",
    "gn:population":0,
    "gn:timezone":"Europe/Moscow",
    "iso:country":"RU",
    "name:rus_x_preferred":[
        "\u041d\u0438\u043a\u0443\u043b\u0438\u043d\u043e"
    ],
    "name:und_x_variant":[
        "Sluzhnya",
        "Nikulino",
        "\u041d\u0438\u043a\u0443\u043b\u0438\u043d\u043e"
    ],
    "wof:name":"Nikulino",
    "wof:placetype":"locality"
},
  "geometry": {"coordinates":[36.35688,52.01300000000001],"type":"Point"}
}