{
  "type": "Feature",
  "properties": {
    "gn:admin1_code":"8",
    "gn:asciiname":"Shmitovo",
    "gn:country_code":"RU",
    "gn:dem":111,
    "gn:feature_class":"P",
    "gn:feature_code":"PPL",
    "gn:name":"Shmitovo",
    "gn:population":0,
    "gn:timezone":"Asia/Yekaterinburg",
    "iso:country":"RU",
    "name:rus_x_preferred":[
        "\u0428\u043c\u0438\u0442\u043e\u0432\u043e"
    ],
    "name:und_x_variant":[
        "\u0428\u043c\u0438\u0442\u043e\u0432\u043e"
    ],
    "wof:name":"Shmitovo",
    "wof:placetype":"locality"
},
  "geometry": {"coordinates":[56.18333000000001,54.65],"type":"Point"}
}