{
  "type": "Feature",
  "properties": {
    "gn:admin1_code":"7.0",
    "gn:asciiname":"Gavrilovskiy Vtoroy",
    "gn:country_code":"RU",
    "gn:dem":-30,
    "gn:feature_class":"P",
    "gn:feature_code":"PPL",
    "gn:name":"Gavrilovskiy Vtoroy",
    "gn:population":0,
    "gn:timezone":"Europe/Astrakhan",
    "iso:country":"RU",
    "name:rus_x_preferred":[
        "\u0413\u0430\u0432\u0440\u0438\u043b\u043e\u0432\u0441\u043a\u0438\u0439 \u0412\u0442\u043e\u0440\u043e\u0439"
    ],
    "wof:name":"Gavrilovskiy Vtoroy",
    "wof:placetype":"locality"
},
  "geometry": {"coordinates":[47.76473,45.83435],"type":"Point"}
}