{
  "type": "Feature",
  "properties": {
    "gn:admin1_code":"37.0",
    "gn:asciiname":"Rodenovo",
    "gn:country_code":"RU",
    "gn:dem":115,
    "gn:feature_class":"P",
    "gn:feature_code":"PPL",
    "gn:name":"Rodenovo",
    "gn:population":0,
    "gn:timezone":"Europe/Moscow",
    "iso:country":"RU",
    "name:rus_x_preferred":[
        "\u0420\u043e\u0434\u0435\u043d\u043e\u0432\u043e"
    ],
    "wof:name":"Rodenovo",
    "wof:placetype":"locality"
},
  "geometry": {"coordinates":[42.9252,57.99851],"type":"Point"}
}