{
  "type": "Feature",
  "properties": {
    "gn:admin1_code":"63",
    "gn:asciiname":"Tegyul'tya",
    "gn:country_code":"RU",
    "gn:dem":181,
    "gn:feature_class":"P",
    "gn:feature_code":"PPL",
    "gn:name":"T\u00ebgyul\u2019tya",
    "gn:population":0,
    "gn:timezone":"Asia/Yakutsk",
    "iso:country":"RU",
    "name:eng_x_preferred":[
        "T\u00ebgyul'tya"
    ],
    "name:nor_x_preferred":[
        "Tegjultja"
    ],
    "name:rus_x_preferred":[
        "\u0422\u0435\u0433\u044e\u043b\u044c\u0442\u044f"
    ],
    "name:und_x_variant":[
        "Tegyulta-Terde",
        "Tegyutte-Terde",
        "T\u00ebgyul\u2019te-T\u00ebrd\u00eb",
        "T\u00ebgyul\u2019tya"
    ],
    "wof:name":"Tegyul'tya",
    "wof:placetype":"locality"
},
  "geometry": {"coordinates":[130.18523999999999,60.15841],"type":"Point"}
}