{
  "type": "Feature",
  "properties": {
    "gn:admin1_code":"46.0",
    "gn:asciiname":"Bol'shaya Pestrovka",
    "gn:country_code":"RU",
    "gn:dem":239,
    "gn:feature_class":"P",
    "gn:feature_code":"PPL",
    "gn:name":"Bol\u2019shaya Pestrovka",
    "gn:population":0,
    "gn:timezone":"Europe/Moscow",
    "iso:country":"RU",
    "name:rus_x_preferred":[
        "\u0411\u043e\u043b\u044c\u0448\u0430\u044f \u041f\u0435\u0441\u0442\u0440\u043e\u0432\u043a\u0430"
    ],
    "name:und_x_variant":[
        "Bol\u2019shaya Pestrovka",
        "\u0411\u043e\u043b\u044c\u0448\u0430\u044f \u041f\u0435\u0441\u0442\u0440\u043e\u0432\u043a\u0430"
    ],
    "wof:name":"Bol'shaya Pestrovka",
    "wof:placetype":"locality"
},
  "geometry": {"coordinates":[46.26667,54.56667],"type":"Point"}
}