{
  "type": "Feature",
  "properties": {
    "gn:admin1_code":"43",
    "gn:asciiname":"Losevka",
    "gn:country_code":"RU",
    "gn:dem":181,
    "gn:feature_class":"P",
    "gn:feature_code":"PPL",
    "gn:name":"Losevka",
    "gn:population":0,
    "gn:timezone":"Europe/Moscow",
    "iso:country":"RU",
    "name:rus_x_preferred":[
        "\u041b\u043e\u0441\u0435\u0432\u043a\u0430"
    ],
    "wof:name":"Losevka",
    "wof:placetype":"locality"
},
  "geometry": {"coordinates":[38.41667,52.46666999999999],"type":"Point"}
}