{
  "type": "Feature",
  "properties": {
    "gn:admin1_code":"77",
    "gn:asciiname":"Malygino",
    "gn:country_code":"RU",
    "gn:dem":138,
    "gn:feature_class":"P",
    "gn:feature_code":"PPL",
    "gn:name":"Malygino",
    "gn:population":0,
    "gn:timezone":"Europe/Moscow",
    "iso:country":"RU",
    "name:rus_x_preferred":[
        "\u041c\u0430\u043b\u044b\u0433\u0438\u043d\u043e"
    ],
    "name:und_x_variant":[
        "\u041c\u0430\u043b\u044b\u0433\u0438\u043d\u043e"
    ],
    "wof:name":"Malygino",
    "wof:placetype":"locality"
},
  "geometry": {"coordinates":[37.4244,57.4276],"type":"Point"}
}