{
  "type": "Feature",
  "properties": {
    "gn:admin1_code":"93",
    "gn:asciiname":"Khilkotoy",
    "gn:country_code":"RU",
    "gn:dem":687,
    "gn:feature_class":"P",
    "gn:feature_code":"PPL",
    "gn:name":"Khilkotoy",
    "gn:population":0,
    "gn:timezone":"Asia/Chita",
    "iso:country":"RU",
    "name:eng_x_preferred":[
        "Khilkotoy"
    ],
    "name:nor_x_preferred":[
        "Khilkotoj"
    ],
    "name:rus_x_preferred":[
        "\u0425\u0438\u043b\u043a\u043e\u0442\u043e\u0439"
    ],
    "name:und_x_variant":[
        "Khilkotoi"
    ],
    "wof:name":"Khilkotoy",
    "wof:placetype":"locality"
},
  "geometry": {"coordinates":[108.07658000000001,49.92104000000001],"type":"Point"}
}