{
  "type": "Feature",
  "properties": {
    "gn:admin1_code":"90.0",
    "gn:asciiname":"Orenki",
    "gn:country_code":"RU",
    "gn:dem":132,
    "gn:feature_class":"P",
    "gn:feature_code":"PPL",
    "gn:name":"Orenki",
    "gn:population":0,
    "gn:timezone":"Asia/Yekaterinburg",
    "iso:country":"RU",
    "name:rus_x_preferred":[
        "\u041e\u0440\u0435\u043d\u043a\u0438"
    ],
    "wof:name":"Orenki",
    "wof:placetype":"locality"
},
  "geometry": {"coordinates":[56.0248,58.4006],"type":"Point"}
}