{
  "type": "Feature",
  "properties": {
    "gn:admin1_code":"86",
    "gn:asciiname":"Khlebovka",
    "gn:country_code":"RU",
    "gn:dem":108,
    "gn:feature_class":"P",
    "gn:feature_code":"PPL",
    "gn:name":"Khlebovka",
    "gn:population":0,
    "gn:timezone":"Europe/Moscow",
    "iso:country":"RU",
    "name:rus_x_preferred":[
        "\u0425\u043b\u0435\u0431\u043e\u0432\u043a\u0430"
    ],
    "name:und_x_variant":[
        "\u0425\u043b\u0435\u0431\u043e\u0432\u043a\u0430"
    ],
    "wof:name":"Khlebovka",
    "wof:placetype":"locality"
},
  "geometry": {"coordinates":[40.95056,51.4375],"type":"Point"}
}