{
  "type": "Feature",
  "properties": {
    "gn:admin1_code":"34",
    "gn:asciiname":"Oshper",
    "gn:country_code":"RU",
    "gn:dem":83,
    "gn:feature_class":"P",
    "gn:feature_code":"PPL",
    "gn:name":"Oshper",
    "gn:population":0,
    "gn:timezone":"Europe/Moscow",
    "iso:country":"RU",
    "name:rus_x_preferred":[
        "\u041e\u0448\u043f\u0435\u0440"
    ],
    "wof:name":"Oshper",
    "wof:placetype":"locality"
},
  "geometry": {"coordinates":[61.06667,66.28333000000001],"type":"Point"}
}