{
  "type": "Feature",
  "properties": {
    "gn:admin1_code":"77",
    "gn:asciiname":"Yakshino",
    "gn:country_code":"RU",
    "gn:dem":179,
    "gn:feature_class":"P",
    "gn:feature_code":"PPL",
    "gn:name":"Yakshino",
    "gn:population":0,
    "gn:timezone":"Europe/Moscow",
    "iso:country":"RU",
    "name:rus_x_preferred":[
        "\u042f\u043a\u0448\u0438\u043d\u043e"
    ],
    "wof:name":"Yakshino",
    "wof:placetype":"locality"
},
  "geometry": {"coordinates":[37.1012,57.4883],"type":"Point"}
}