{
  "type": "Feature",
  "properties": {
    "gn:admin1_code":"4",
    "gn:asciiname":"Polovinkino",
    "gn:cc2":"RU",
    "gn:country_code":"RU",
    "gn:dem":218,
    "gn:feature_class":"P",
    "gn:feature_code":"PPL",
    "gn:name":"Polovinkino",
    "gn:population":0,
    "gn:timezone":"Asia/Barnaul",
    "iso:country":"RU",
    "name:eng_x_preferred":[
        "Polovinkino"
    ],
    "name:nor_x_preferred":[
        "Polovinkino"
    ],
    "name:rus_x_preferred":[
        "\u041f\u043e\u043b\u043e\u0432\u0438\u043d\u043a\u0438\u043d\u043e"
    ],
    "name:und_x_variant":[
        "Polovinkina",
        "\u041f\u043e\u043b\u043e\u0432\u0438\u043d\u043a\u0438\u043d\u043e",
        "Polovinkino"
    ],
    "wof:name":"Polovinkino",
    "wof:placetype":"locality"
},
  "geometry": {"coordinates":[81.25,51.41667],"type":"Point"}
}