{
  "type": "Feature",
  "properties": {
    "gn:admin1_code":"57",
    "gn:asciiname":"Rogachevka",
    "gn:country_code":"RU",
    "gn:dem":182,
    "gn:feature_class":"P",
    "gn:feature_code":"PPL",
    "gn:name":"Rogach\u00ebvka",
    "gn:population":0,
    "gn:timezone":"Europe/Moscow",
    "iso:country":"RU",
    "name:che_x_preferred":[
        "\u0420\u043e\u0433\u0430\u0447\u0451\u0432\u043a\u0430"
    ],
    "name:rus_x_preferred":[
        "\u0420\u043e\u0433\u0430\u0447\u0451\u0432\u043a\u0430"
    ],
    "name:und_x_variant":[
        "Rogach\u00ebvka",
        "\u0420\u043e\u0433\u0430\u0447\u0451\u0432\u043a\u0430"
    ],
    "wof:name":"Rogachevka",
    "wof:placetype":"locality"
},
  "geometry": {"coordinates":[43.59861,52.56446],"type":"Point"}
}