{
  "type": "Feature",
  "properties": {
    "gn:admin1_code":"76",
    "gn:asciiname":"Spitsynskiy",
    "gn:country_code":"RU",
    "gn:dem":219,
    "gn:feature_class":"P",
    "gn:feature_code":"PPL",
    "gn:name":"Spitsynskiy",
    "gn:population":0,
    "gn:timezone":"Europe/Moscow",
    "iso:country":"RU",
    "name:rus_x_preferred":[
        "\u0421\u043f\u0438\u0446\u044b\u043d\u0441\u043a\u0438\u0439"
    ],
    "name:und_x_variant":[
        "Spitsino",
        "Spitsynskiy",
        "\u0421\u043f\u0438\u0446\u044b\u043d\u0441\u043a\u0438\u0439"
    ],
    "wof:name":"Spitsynskiy",
    "wof:placetype":"locality"
},
  "geometry": {"coordinates":[38.01629000000001,54.58909],"type":"Point"}
}