{
  "type": "Feature",
  "properties": {
    "gn:admin1_code":"8",
    "gn:asciiname":"Uyankul'",
    "gn:country_code":"RU",
    "gn:dem":149,
    "gn:feature_class":"P",
    "gn:feature_code":"PPL",
    "gn:name":"Uyankul\u2019",
    "gn:population":0,
    "gn:timezone":"Asia/Yekaterinburg",
    "iso:country":"RU",
    "name:rus_x_preferred":[
        "\u0423\u044f\u043d\u043a\u0443\u043b\u044c"
    ],
    "name:und_x_variant":[
        "Uyankul\u2019",
        "\u0423\u044f\u043d\u043a\u0443\u043b\u044c"
    ],
    "wof:name":"Uyankul'",
    "wof:placetype":"locality"
},
  "geometry": {"coordinates":[56.6996,54.9971],"type":"Point"}
}