{
  "type": "Feature",
  "properties": {
    "gn:admin1_code":"69",
    "gn:asciiname":"Udovki",
    "gn:country_code":"RU",
    "gn:dem":211,
    "gn:feature_class":"P",
    "gn:feature_code":"PPL",
    "gn:name":"Udovki",
    "gn:population":0,
    "gn:timezone":"Europe/Moscow",
    "iso:country":"RU",
    "name:eng_x_preferred":[
        "Udovki"
    ],
    "name:nor_x_preferred":[
        "Udovki"
    ],
    "name:rus_x_preferred":[
        "\u0423\u0434\u043e\u0432\u043a\u0438"
    ],
    "wof:name":"Udovki",
    "wof:placetype":"locality"
},
  "geometry": {"coordinates":[31.2874,55.01828],"type":"Point"}
}