{
  "type": "Feature",
  "properties": {
    "gn:admin1_code":"20",
    "gn:asciiname":"Dagnik",
    "gn:country_code":"RU",
    "gn:dem":551,
    "gn:feature_class":"P",
    "gn:feature_code":"PPL",
    "gn:name":"Dagnik",
    "gn:population":0,
    "gn:timezone":"Asia/Irkutsk",
    "iso:country":"RU",
    "name:eng_x_preferred":[
        "Dagnik"
    ],
    "name:nor_x_preferred":[
        "Dagnik"
    ],
    "name:rus_x_preferred":[
        "\u0414\u0430\u0433\u043d\u0438\u043a"
    ],
    "name:und_x_variant":[
        "\u0414\u0430\u0433\u043d\u0438\u043a",
        "Dagnik"
    ],
    "wof:name":"Dagnik",
    "wof:placetype":"locality"
},
  "geometry": {"coordinates":[101.66833,53.35361],"type":"Point"}
}