{
  "type": "Feature",
  "properties": {
    "gn:admin1_code":"60",
    "gn:asciiname":"Vinokurovo",
    "gn:country_code":"RU",
    "gn:dem":89,
    "gn:feature_class":"P",
    "gn:feature_code":"PPL",
    "gn:name":"Vinokurovo",
    "gn:population":0,
    "gn:timezone":"Europe/Moscow",
    "iso:country":"RU",
    "name:che_x_preferred":[
        "\u0412\u0438\u043d\u043e\u043a\u0443\u0440\u043e\u0432\u043e"
    ],
    "name:chv_x_preferred":[
        "\u0412\u0438\u043d\u043e\u043a\u0443\u0440\u043e\u0432\u043e"
    ],
    "name:rus_x_preferred":[
        "\u0412\u0438\u043d\u043e\u043a\u0443\u0440\u043e\u0432\u043e"
    ],
    "name:tat_x_preferred":[
        "\u0412\u0438\u043d\u043e\u043a\u0443\u0440\u043e\u0432\u043e"
    ],
    "wof:name":"Vinokurovo",
    "wof:placetype":"locality"
},
  "geometry": {"coordinates":[28.83166,57.19349],"type":"Point"}
}