{
  "type": "Feature",
  "properties": {
    "gn:admin1_code":"11",
    "gn:asciiname":"Korsakovo",
    "gn:country_code":"RU",
    "gn:dem":461,
    "gn:feature_class":"P",
    "gn:feature_code":"PPL",
    "gn:name":"Korsakovo",
    "gn:population":0,
    "gn:timezone":"Asia/Irkutsk",
    "iso:country":"RU",
    "name:eng_x_preferred":[
        "Korsakovo"
    ],
    "name:nor_x_preferred":[
        "Korsakovo"
    ],
    "name:rus_x_preferred":[
        "\u041a\u043e\u0440\u0441\u0430\u043a\u043e\u0432\u043e"
    ],
    "name:und_x_variant":[
        "\u041a\u043e\u0440\u0441\u0430\u043a\u043e\u0432\u043e",
        "Korsakovo"
    ],
    "wof:name":"Korsakovo",
    "wof:placetype":"locality"
},
  "geometry": {"coordinates":[106.61944,52.24944],"type":"Point"}
}