{
  "type": "Feature",
  "properties": {
    "gn:admin1_code":"56",
    "gn:asciiname":"Budilovka",
    "gn:country_code":"RU",
    "gn:dem":172,
    "gn:feature_class":"P",
    "gn:feature_code":"PPL",
    "gn:name":"Budilovka",
    "gn:population":0,
    "gn:timezone":"Europe/Moscow",
    "iso:country":"RU",
    "name:rus_x_preferred":[
        "\u0411\u0443\u0434\u0438\u043b\u043e\u0432\u043a\u0430"
    ],
    "name:und_x_variant":[
        "\u0411\u0443\u0434\u0438\u043b\u043e\u0432\u043a\u0430"
    ],
    "wof:name":"Budilovka",
    "wof:placetype":"locality"
},
  "geometry": {"coordinates":[36.1249,52.8518],"type":"Point"}
}