{
  "type": "Feature",
  "properties": {
    "gn:admin1_code":"40",
    "gn:asciiname":"Niva",
    "gn:country_code":"RU",
    "gn:dem":155,
    "gn:feature_class":"P",
    "gn:feature_code":"PPL",
    "gn:name":"Niva",
    "gn:population":0,
    "gn:timezone":"Asia/Yekaterinburg",
    "iso:country":"RU",
    "name:rus_x_preferred":[
        "\u041d\u0438\u0432\u0430"
    ],
    "name:und_x_variant":[
        "\u041d\u0438\u0432\u0430"
    ],
    "wof:name":"Niva",
    "wof:placetype":"locality"
},
  "geometry": {"coordinates":[64.4175,55.36083000000001],"type":"Point"}
}