{
  "type": "Feature",
  "properties": {
    "gn:admin1_code":"51",
    "gn:asciiname":"Talashmanovo",
    "gn:country_code":"RU",
    "gn:dem":102,
    "gn:feature_class":"P",
    "gn:feature_code":"PPL",
    "gn:name":"Talashmanovo",
    "gn:population":0,
    "gn:timezone":"Europe/Moscow",
    "iso:country":"RU",
    "name:und_x_variant":[
        "Toloshmanovo",
        "Talashmanovo"
    ],
    "wof:name":"Talashmanovo",
    "wof:placetype":"locality"
},
  "geometry": {"coordinates":[42.95274000000001,56.27191],"type":"Point"}
}