{
  "type": "Feature",
  "properties": {
    "gn:admin1_code":"64",
    "gn:asciiname":"Potovo",
    "gn:cc2":"RU",
    "gn:country_code":"RU",
    "gn:dem":44,
    "gn:feature_class":"P",
    "gn:feature_code":"PPL",
    "gn:name":"Potovo",
    "gn:population":0,
    "gn:timezone":"Asia/Sakhalin",
    "iso:country":"RU",
    "name:rus_x_preferred":[
        "\u041f\u043e\u0442\u043e\u0432\u043e"
    ],
    "name:und_x_variant":[
        "Plyuvo",
        "Plyuyevo",
        "Potovo",
        "\u041f\u043e\u0442\u043e\u0432\u043e"
    ],
    "wof:name":"Potovo",
    "wof:placetype":"locality"
},
  "geometry": {"coordinates":[142.68333000000001,51.18333],"type":"Point"}
}