{
  "type": "Feature",
  "properties": {
    "gn:admin1_code":"28",
    "gn:asciiname":"Ontroinen",
    "gn:country_code":"RU",
    "gn:dem":79,
    "gn:feature_class":"P",
    "gn:feature_code":"PPL",
    "gn:name":"Ontroinen",
    "gn:population":0,
    "gn:timezone":"Europe/Moscow",
    "iso:country":"RU",
    "name:fin_x_preferred":[
        "Ontroinen"
    ],
    "name:rus_x_preferred":[
        "\u041e\u043d\u0442\u0440\u043e\u0438\u043d\u0435\u043d"
    ],
    "wof:name":"Ontroinen",
    "wof:placetype":"locality"
},
  "geometry": {"coordinates":[31.26932,61.74705],"type":"Point"}
}