{
  "type": "Feature",
  "properties": {
    "gn:admin1_code":"20",
    "gn:asciiname":"Onguren",
    "gn:cc2":"RU",
    "gn:country_code":"RU",
    "gn:dem":488,
    "gn:feature_class":"P",
    "gn:feature_code":"PPL",
    "gn:name":"Onguren",
    "gn:population":0,
    "gn:timezone":"Asia/Irkutsk",
    "iso:country":"RU",
    "name:eng_x_preferred":[
        "Onguren"
    ],
    "name:nor_x_preferred":[
        "Onguren"
    ],
    "name:rus_x_preferred":[
        "\u041e\u043d\u0433\u0443\u0440\u0435\u043d"
    ],
    "name:und_x_variant":[
        "Bol\u2019shoy Onguren"
    ],
    "wof:name":"Onguren",
    "wof:placetype":"locality"
},
  "geometry": {"coordinates":[107.59417000000001,53.63556],"type":"Point"}
}