{
  "type": "Feature",
  "properties": {
    "gn:admin1_code":"33",
    "gn:asciiname":"Toy-Doy",
    "gn:country_code":"RU",
    "gn:dem":200,
    "gn:feature_class":"P",
    "gn:feature_code":"PPL",
    "gn:name":"Toy-Doy",
    "gn:population":0,
    "gn:timezone":"Europe/Kirov",
    "iso:country":"RU",
    "name:rus_x_preferred":[
        "\u0422\u043e\u0439-\u0414\u043e\u0439"
    ],
    "wof:name":"Toy-Doy",
    "wof:placetype":"locality"
},
  "geometry": {"coordinates":[50.49611,58.67471999999999],"type":"Point"}
}