{
  "type": "Feature",
  "properties": {
    "gn:admin1_code":"29",
    "gn:asciiname":"Rybkhoz",
    "gn:country_code":"RU",
    "gn:dem":162,
    "gn:feature_class":"P",
    "gn:feature_code":"PPL",
    "gn:name":"Rybkhoz",
    "gn:population":0,
    "gn:timezone":"Asia/Novokuznetsk",
    "iso:country":"RU",
    "name:rus_x_preferred":[
        "\u0420\u044b\u0431\u0445\u043e\u0437"
    ],
    "wof:name":"Rybkhoz",
    "wof:placetype":"locality"
},
  "geometry": {"coordinates":[85.9794,55.2443],"type":"Point"}
}