{
  "type": "Feature",
  "properties": {
    "gn:admin1_code":"38.0",
    "gn:asciiname":"Nekhvoroshchanskiy",
    "gn:country_code":"RU",
    "gn:dem":69,
    "gn:feature_class":"P",
    "gn:feature_code":"PPL",
    "gn:name":"Nekhvoroshchanskiy",
    "gn:population":0,
    "gn:timezone":"Europe/Moscow",
    "iso:country":"RU",
    "name:rus_x_preferred":[
        "\u041d\u0435\u0445\u0432\u043e\u0440\u043e\u0449\u0430\u043d\u0441\u043a\u0438\u0439"
    ],
    "wof:name":"Nekhvoroshchanskiy",
    "wof:placetype":"locality"
},
  "geometry": {"coordinates":[40.43444,45.59417],"type":"Point"}
}