{
  "type": "Feature",
  "properties": {
    "gn:admin1_code":"55",
    "gn:asciiname":"Yablonevyy",
    "gn:country_code":"RU",
    "gn:dem":73,
    "gn:feature_class":"P",
    "gn:feature_code":"PPL",
    "gn:name":"Yablonevyy",
    "gn:population":0,
    "gn:timezone":"Asia/Yekaterinburg",
    "iso:country":"RU",
    "name:rus_x_preferred":[
        "\u042f\u0431\u043b\u043e\u043d\u0435\u0432\u044b\u0439"
    ],
    "name:und_x_variant":[
        "\u042f\u0431\u043b\u043e\u043d\u0435\u0432\u044b\u0439"
    ],
    "wof:name":"Yablonevyy",
    "wof:placetype":"locality"
},
  "geometry": {"coordinates":[52.5645,52.8632],"type":"Point"}
}