{
  "type": "Feature",
  "properties": {
    "gn:admin1_code":"4",
    "gn:asciiname":"Nikol'skiy",
    "gn:country_code":"RU",
    "gn:dem":133,
    "gn:feature_class":"P",
    "gn:feature_code":"PPL",
    "gn:name":"Nikol\u2019skiy",
    "gn:population":0,
    "gn:timezone":"Asia/Barnaul",
    "iso:country":"RU",
    "name:eng_x_preferred":[
        "Nikol'skiy"
    ],
    "name:nor_x_preferred":[
        "Nikolskij"
    ],
    "name:rus_x_preferred":[
        "\u041d\u0438\u043a\u043e\u043b\u044c\u0441\u043a\u0438\u0439"
    ],
    "name:und_x_variant":[
        "\u041d\u0438\u043a\u043e\u043b\u044c\u0441\u043a\u0438\u0439",
        "Nikol\u2019skiy"
    ],
    "wof:name":"Nikol'skiy",
    "wof:placetype":"locality"
},
  "geometry": {"coordinates":[79.09180000000001,53.3911],"type":"Point"}
}