{
  "type": "Feature",
  "properties": {
    "gn:admin1_code":"10",
    "gn:asciiname":"Tolbino",
    "gn:country_code":"RU",
    "gn:dem":203,
    "gn:feature_class":"P",
    "gn:feature_code":"PPL",
    "gn:name":"Tolbino",
    "gn:population":0,
    "gn:timezone":"Europe/Moscow",
    "iso:country":"RU",
    "name:rus_x_preferred":[
        "\u0422\u043e\u043b\u0431\u0438\u043d\u043e"
    ],
    "name:und_x_variant":[
        "\u0422\u043e\u043b\u0431\u0438\u043d\u043e",
        "Tolbina"
    ],
    "wof:name":"Tolbino",
    "wof:placetype":"locality"
},
  "geometry": {"coordinates":[33.53942,53.89717],"type":"Point"}
}