{
  "type": "Feature",
  "properties": {
    "gn:admin1_code":"51.0",
    "gn:asciiname":"Bezvernikovo",
    "gn:country_code":"RU",
    "gn:dem":83,
    "gn:feature_class":"P",
    "gn:feature_code":"PPL",
    "gn:name":"Bezvernikovo",
    "gn:population":0,
    "gn:timezone":"Europe/Moscow",
    "iso:country":"RU",
    "name:nor_x_preferred":[
        "Bezvernikovo"
    ],
    "name:rus_x_preferred":[
        "\u0411\u0435\u0437\u0432\u0435\u0440\u043d\u0438\u043a\u043e\u0432\u043e"
    ],
    "wof:name":"Bezvernikovo",
    "wof:placetype":"locality"
},
  "geometry": {"coordinates":[42.3314,55.583],"type":"Point"}
}