{
  "type": "Feature",
  "properties": {
    "gn:admin1_code":"20",
    "gn:asciiname":"Khogot",
    "gn:country_code":"RU",
    "gn:dem":617,
    "gn:feature_class":"P",
    "gn:feature_code":"PPL",
    "gn:name":"Khogot",
    "gn:population":0,
    "gn:timezone":"Asia/Irkutsk",
    "iso:country":"RU",
    "name:eng_x_preferred":[
        "Khogot"
    ],
    "name:nor_x_preferred":[
        "Khogot"
    ],
    "name:rus_x_preferred":[
        "\u0425\u043e\u0433\u043e\u0442"
    ],
    "name:und_x_variant":[
        "\u0425\u043e\u0433\u043e\u0442"
    ],
    "wof:name":"Khogot",
    "wof:placetype":"locality"
},
  "geometry": {"coordinates":[105.86472000000001,53.2375],"type":"Point"}
}