{
  "type": "Feature",
  "properties": {
    "gn:admin1_code":"88",
    "gn:asciiname":"Stroykovo",
    "gn:country_code":"RU",
    "gn:dem":115,
    "gn:feature_class":"P",
    "gn:feature_code":"PPL",
    "gn:name":"Stroykovo",
    "gn:population":0,
    "gn:timezone":"Europe/Moscow",
    "iso:country":"RU",
    "name:eng_x_preferred":[
        "Stroykovo"
    ],
    "name:nor_x_preferred":[
        "Strojkovo"
    ],
    "name:rus_x_preferred":[
        "\u0421\u0442\u0440\u043e\u0439\u043a\u043e\u0432\u043e"
    ],
    "wof:name":"Stroykovo",
    "wof:placetype":"locality"
},
  "geometry": {"coordinates":[40.31954,58.04773],"type":"Point"}
}