{
  "type": "Feature",
  "properties": {
    "gn:admin1_code":"69",
    "gn:asciiname":"Stayki",
    "gn:country_code":"RU",
    "gn:dem":176,
    "gn:feature_class":"P",
    "gn:feature_code":"PPL",
    "gn:name":"Stayki",
    "gn:population":0,
    "gn:timezone":"Europe/Moscow",
    "iso:country":"RU",
    "name:eng_x_preferred":[
        "Stayki"
    ],
    "name:nor_x_preferred":[
        "Stajki"
    ],
    "name:rus_x_preferred":[
        "\u0421\u0442\u0430\u0439\u043a\u0438"
    ],
    "wof:name":"Stayki",
    "wof:placetype":"locality"
},
  "geometry": {"coordinates":[32.0151,54.1234],"type":"Point"}
}