{
  "type": "Feature",
  "properties": {
    "gn:admin1_code":"40",
    "gn:asciiname":"Rytikovo",
    "gn:country_code":"RU",
    "gn:dem":139,
    "gn:feature_class":"P",
    "gn:feature_code":"PPL",
    "gn:name":"Rytikovo",
    "gn:population":0,
    "gn:timezone":"Asia/Yekaterinburg",
    "iso:country":"RU",
    "name:rus_x_preferred":[
        "\u0420\u044b\u0442\u0438\u043a\u043e\u0432\u043e"
    ],
    "wof:name":"Rytikovo",
    "wof:placetype":"locality"
},
  "geometry": {"coordinates":[63.45944,55.6525],"type":"Point"}
}