{
  "type": "Feature",
  "properties": {
    "gn:admin1_code":"16",
    "gn:asciiname":"Tyumerevo",
    "gn:country_code":"RU",
    "gn:dem":117,
    "gn:feature_class":"P",
    "gn:feature_code":"PPL",
    "gn:name":"Tyumerevo",
    "gn:population":0,
    "gn:timezone":"Europe/Moscow",
    "iso:country":"RU",
    "name:eng_x_preferred":[
        "Tyumerevo"
    ],
    "name:nor_x_preferred":[
        "Tjumerevo"
    ],
    "name:rus_x_preferred":[
        "\u0422\u044e\u043c\u0435\u0440\u0435\u0432\u043e"
    ],
    "wof:name":"Tyumerevo",
    "wof:placetype":"locality"
},
  "geometry": {"coordinates":[47.77206,55.44009000000001],"type":"Point"}
}