{
  "type": "Feature",
  "properties": {
    "gn:admin1_code":"55",
    "gn:asciiname":"Aeroport",
    "gn:country_code":"RU",
    "gn:dem":98,
    "gn:feature_class":"P",
    "gn:feature_code":"PPL",
    "gn:name":"Aeroport",
    "gn:population":0,
    "gn:timezone":"Asia/Yekaterinburg",
    "iso:country":"RU",
    "name:bel_x_preferred":[
        "\u0410\u044d\u0440\u0430\u043f\u043e\u0440\u0442"
    ],
    "name:dan_x_preferred":[
        "Aeroport"
    ],
    "name:ita_x_preferred":[
        "Aeroport"
    ],
    "name:pol_x_preferred":[
        "Aeroport"
    ],
    "name:rus_x_preferred":[
        "\u0410\u044d\u0440\u043e\u043f\u043e\u0440\u0442"
    ],
    "name:ukr_x_preferred":[
        "\u0410\u0435\u0440\u043e\u043f\u043e\u0440\u0442"
    ],
    "wof:name":"Aeroport",
    "wof:placetype":"locality"
},
  "geometry": {"coordinates":[55.31428,51.76305],"type":"Point"}
}