{
  "type": "Feature",
  "properties": {
    "gn:admin1_code":"27",
    "gn:asciiname":"Belaya Gora",
    "gn:country_code":"RU",
    "gn:dem":774,
    "gn:feature_class":"P",
    "gn:feature_code":"PPL",
    "gn:name":"Belaya Gora",
    "gn:population":0,
    "gn:timezone":"Europe/Moscow",
    "iso:country":"RU",
    "name:nor_x_preferred":[
        "Belaja Gora"
    ],
    "name:rus_x_preferred":[
        "\u0411\u0435\u043b\u0430\u044f \u0413\u043e\u0440\u0430"
    ],
    "wof:name":"Belaya Gora",
    "wof:placetype":"locality"
},
  "geometry": {"coordinates":[41.90701,43.88554],"type":"Point"}
}