{
  "type": "Feature",
  "properties": {
    "gn:admin1_code":"77",
    "gn:asciiname":"Poddub'ye",
    "gn:country_code":"RU",
    "gn:dem":125,
    "gn:feature_class":"P",
    "gn:feature_code":"PPL",
    "gn:name":"Poddub\u2019ye",
    "gn:population":0,
    "gn:timezone":"Europe/Moscow",
    "iso:country":"RU",
    "name:rus_x_preferred":[
        "\u041f\u043e\u0434\u0434\u0443\u0431\u044c\u0435"
    ],
    "name:und_x_variant":[
        "Poddub\u2019ye",
        "\u041f\u043e\u0434\u0434\u0443\u0431\u044c\u0435"
    ],
    "wof:name":"Poddub'ye",
    "wof:placetype":"locality"
},
  "geometry": {"coordinates":[36.10211,56.79929],"type":"Point"}
}