{
  "type": "Feature",
  "properties": {
    "gn:admin1_code":"46",
    "gn:asciiname":"Novoye Kadyshevo",
    "gn:country_code":"RU",
    "gn:dem":114,
    "gn:feature_class":"P",
    "gn:feature_code":"PPL",
    "gn:name":"Novoye Kadyshevo",
    "gn:population":0,
    "gn:timezone":"Europe/Moscow",
    "iso:country":"RU",
    "name:nor_x_preferred":[
        "Novoje Kadysjevo"
    ],
    "name:rus_x_preferred":[
        "\u041d\u043e\u0432\u043e\u0435 \u041a\u0430\u0434\u044b\u0448\u0435\u0432\u043e"
    ],
    "wof:name":"Novoye Kadyshevo",
    "wof:placetype":"locality"
},
  "geometry": {"coordinates":[43.69221,54.64336],"type":"Point"}
}