{
  "type": "Feature",
  "properties": {
    "gn:admin1_code":"47",
    "gn:asciiname":"Ovsyannikovo",
    "gn:cc2":"RU",
    "gn:country_code":"RU",
    "gn:dem":218,
    "gn:feature_class":"P",
    "gn:feature_code":"PPL",
    "gn:name":"Ovsyannikovo",
    "gn:population":0,
    "gn:timezone":"Europe/Moscow",
    "iso:country":"RU",
    "name:rus_x_preferred":[
        "\u041e\u0432\u0441\u044f\u043d\u043d\u0438\u043a\u043e\u0432\u043e"
    ],
    "name:und_x_variant":[
        "Ovsyanikovo",
        "Ovsyannikovo",
        "\u041e\u0432\u0441\u044f\u043d\u043d\u0438\u043a\u043e\u0432\u043e"
    ],
    "wof:name":"Ovsyannikovo",
    "wof:placetype":"locality"
},
  "geometry": {"coordinates":[35.71889,55.60611],"type":"Point"}
}