{
  "type": "Feature",
  "properties": {
    "gn:admin1_code":"13",
    "gn:asciiname":"Petromikhaylovka",
    "gn:country_code":"RU",
    "gn:dem":355,
    "gn:feature_class":"P",
    "gn:feature_code":"PPL",
    "gn:name":"Petromikhaylovka",
    "gn:population":0,
    "gn:timezone":"Asia/Yekaterinburg",
    "iso:country":"RU",
    "name:rus_x_preferred":[
        "\u041f\u0435\u0442\u0440\u043e\u043c\u0438\u0445\u0430\u0439\u043b\u043e\u0432\u043a\u0430"
    ],
    "name:und_x_variant":[
        "Petropavlovka",
        "Petromikhaylovka",
        "\u041f\u0435\u0442\u0440\u043e\u043c\u0438\u0445\u0430\u0439\u043b\u043e\u0432\u043a\u0430"
    ],
    "wof:name":"Petromikhaylovka",
    "wof:placetype":"locality"
},
  "geometry": {"coordinates":[58.8801,55.2986],"type":"Point"}
}