{
  "type": "Feature",
  "properties": {
    "gn:admin1_code":"88.0",
    "gn:asciiname":"Botvino",
    "gn:country_code":"RU",
    "gn:dem":140,
    "gn:feature_class":"P",
    "gn:feature_code":"PPL",
    "gn:name":"Botvino",
    "gn:population":0,
    "gn:timezone":"Europe/Moscow",
    "iso:country":"RU",
    "name:rus_x_preferred":[
        "\u0411\u043e\u0442\u0432\u0438\u043d\u043e"
    ],
    "wof:name":"Botvino",
    "wof:placetype":"locality"
},
  "geometry": {"coordinates":[38.7647,57.6204],"type":"Point"}
}