{
  "type": "Feature",
  "properties": {
    "gn:admin1_code":"16",
    "gn:asciiname":"Kosteryaki",
    "gn:country_code":"RU",
    "gn:dem":181,
    "gn:feature_class":"P",
    "gn:feature_code":"PPL",
    "gn:name":"Kosteryaki",
    "gn:population":0,
    "gn:timezone":"Europe/Moscow",
    "iso:country":"RU",
    "name:rus_x_preferred":[
        "\u041a\u043e\u0441\u0442\u0435\u0440\u044f\u043a\u0438"
    ],
    "name:und_x_variant":[
        "Kosteryakovo",
        "Kosteryaki"
    ],
    "wof:name":"Kosteryaki",
    "wof:placetype":"locality"
},
  "geometry": {"coordinates":[46.9079,55.9775],"type":"Point"}
}