{
  "type": "Feature",
  "properties": {
    "gn:admin1_code":"4",
    "gn:asciiname":"Purysevo",
    "gn:country_code":"RU",
    "gn:dem":151,
    "gn:feature_class":"P",
    "gn:feature_code":"PPL",
    "gn:name":"Purysevo",
    "gn:population":0,
    "gn:timezone":"Asia/Barnaul",
    "iso:country":"RU",
    "name:eng_x_preferred":[
        "Purysevo"
    ],
    "name:nor_x_preferred":[
        "Purysevo"
    ],
    "name:rus_x_preferred":[
        "\u041f\u0443\u0440\u044b\u0441\u0435\u0432\u043e"
    ],
    "wof:name":"Purysevo",
    "wof:placetype":"locality"
},
  "geometry": {"coordinates":[84.0907,53.9351],"type":"Point"}
}