{
  "type": "Feature",
  "properties": {
    "gn:admin1_code":"20",
    "gn:asciiname":"Pozdnyakova",
    "gn:country_code":"RU",
    "gn:dem":445,
    "gn:feature_class":"P",
    "gn:feature_code":"PPL",
    "gn:name":"Pozdnyakova",
    "gn:population":0,
    "gn:timezone":"Asia/Irkutsk",
    "iso:country":"RU",
    "name:rus_x_preferred":[
        "\u041f\u043e\u0437\u0434\u043d\u044f\u043a\u043e\u0432\u0430"
    ],
    "name:und_x_variant":[
        "Pozdnyakovo",
        "Pozdnyakova",
        "\u041f\u043e\u0437\u0434\u043d\u044f\u043a\u043e\u0432\u0430"
    ],
    "wof:name":"Pozdnyakova",
    "wof:placetype":"locality"
},
  "geometry": {"coordinates":[104.43333,52.48333],"type":"Point"}
}