{
  "type": "Feature",
  "properties": {
    "gn:admin1_code":"80.0",
    "gn:asciiname":"Gulekshur",
    "gn:country_code":"RU",
    "gn:dem":185,
    "gn:feature_class":"P",
    "gn:feature_code":"PPL",
    "gn:name":"Gulekshur",
    "gn:population":0,
    "gn:timezone":"Europe/Samara",
    "iso:country":"RU",
    "name:rus_x_preferred":[
        "\u0413\u0443\u043b\u0435\u043a\u0448\u0443\u0440"
    ],
    "wof:name":"Gulekshur",
    "wof:placetype":"locality"
},
  "geometry": {"coordinates":[52.348,57.9864],"type":"Point"}
}