{
  "type": "Feature",
  "properties": {
    "gn:admin1_code":"69",
    "gn:asciiname":"Igorevskaya",
    "gn:cc2":"RU",
    "gn:country_code":"RU",
    "gn:dem":241,
    "gn:feature_class":"P",
    "gn:feature_code":"PPL",
    "gn:name":"Igorevskaya",
    "gn:population":0,
    "gn:timezone":"Europe/Moscow",
    "iso:country":"RU",
    "name:eng_x_preferred":[
        "Igorevskaya"
    ],
    "name:nor_x_preferred":[
        "Igorevskaja"
    ],
    "name:rus_x_preferred":[
        "\u0418\u0433\u043e\u0440\u0435\u0432\u0441\u043a\u0430\u044f"
    ],
    "name:und_x_variant":[
        "Igor\u2019yevskaya",
        "\u0418\u0433\u043e\u0440\u0435\u0432\u0441\u043a\u0430\u044f",
        "Igorevskaya"
    ],
    "wof:name":"Igorevskaya",
    "wof:placetype":"locality"
},
  "geometry": {"coordinates":[33.28528,55.46333000000001],"type":"Point"}
}