{
  "type": "Feature",
  "properties": {
    "gn:admin1_code":"77",
    "gn:asciiname":"Lunevo",
    "gn:country_code":"RU",
    "gn:dem":199,
    "gn:feature_class":"P",
    "gn:feature_code":"PPL",
    "gn:name":"Lun\u00ebvo",
    "gn:population":0,
    "gn:timezone":"Europe/Moscow",
    "iso:country":"RU",
    "name:rus_x_preferred":[
        "\u041b\u0443\u043d\u0451\u0432\u043e"
    ],
    "name:und_x_variant":[
        "Lun\u00ebvo"
    ],
    "wof:name":"Lunevo",
    "wof:placetype":"locality"
},
  "geometry": {"coordinates":[34.471,56.19161999999999],"type":"Point"}
}