{
  "type": "Feature",
  "properties": {
    "gn:admin1_code":"41",
    "gn:asciiname":"Vtoroye Mal'tsevo",
    "gn:country_code":"RU",
    "gn:dem":164,
    "gn:feature_class":"P",
    "gn:feature_code":"PPL",
    "gn:name":"Vtoroye Mal\u2019tsevo",
    "gn:population":0,
    "gn:timezone":"Europe/Moscow",
    "iso:country":"RU",
    "name:rus_x_preferred":[
        "\u0412\u0442\u043e\u0440\u043e\u0435 \u041c\u0430\u043b\u044c\u0446\u0435\u0432\u043e"
    ],
    "name:und_x_variant":[
        "Vtoroye Mal\u2019tsevo"
    ],
    "wof:name":"Vtoroye Mal'tsevo",
    "wof:placetype":"locality"
},
  "geometry": {"coordinates":[35.6805,51.512],"type":"Point"}
}