{
  "type": "Feature",
  "properties": {
    "gn:admin1_code":"59",
    "gn:asciiname":"Shiryayevka",
    "gn:country_code":"RU",
    "gn:dem":121,
    "gn:feature_class":"P",
    "gn:feature_code":"PPL",
    "gn:name":"Shiryayevka",
    "gn:population":0,
    "gn:timezone":"Asia/Vladivostok",
    "iso:country":"RU",
    "name:eng_x_preferred":[
        "Shiryayevka"
    ],
    "name:nor_x_preferred":[
        "Sjirjaevka"
    ],
    "name:rus_x_preferred":[
        "\u0428\u0438\u0440\u044f\u0435\u0432\u043a\u0430"
    ],
    "name:und_x_variant":[
        "Romanovka",
        "Shiryayevskiy",
        "\u0428\u0438\u0440\u044f\u0435\u0432\u043a\u0430",
        "Shiryayevka"
    ],
    "wof:name":"Shiryayevka",
    "wof:placetype":"locality"
},
  "geometry": {"coordinates":[132.56571,43.97817],"type":"Point"}
}