{
  "type": "Feature",
  "properties": {
    "gn:admin1_code":"52",
    "gn:asciiname":"Polishchi",
    "gn:country_code":"RU",
    "gn:dem":100,
    "gn:feature_class":"P",
    "gn:feature_code":"PPL",
    "gn:name":"Polishchi",
    "gn:population":0,
    "gn:timezone":"Europe/Moscow",
    "iso:country":"RU",
    "wof:name":"Polishchi",
    "wof:placetype":"locality"
},
  "geometry": {"coordinates":[33.33917,58.44583000000001],"type":"Point"}
}