{
  "type": "Feature",
  "properties": {
    "gn:admin1_code":"77",
    "gn:asciiname":"Michurikha",
    "gn:country_code":"RU",
    "gn:dem":151,
    "gn:feature_class":"P",
    "gn:feature_code":"PPL",
    "gn:name":"Michurikha",
    "gn:population":0,
    "gn:timezone":"Europe/Moscow",
    "iso:country":"RU",
    "name:rus_x_preferred":[
        "\u041c\u0438\u0447\u0443\u0440\u0438\u0445\u0430"
    ],
    "name:und_x_variant":[
        "\u041c\u0438\u0447\u0443\u0440\u0438\u0445\u0430"
    ],
    "wof:name":"Michurikha",
    "wof:placetype":"locality"
},
  "geometry": {"coordinates":[36.8169,57.9655],"type":"Point"}
}