{
  "type": "Feature",
  "properties": {
    "gn:admin1_code":"56",
    "gn:asciiname":"Volodarskaya",
    "gn:country_code":"RU",
    "gn:dem":215,
    "gn:feature_class":"P",
    "gn:feature_code":"PPL",
    "gn:name":"Volodarskaya",
    "gn:population":0,
    "gn:timezone":"Europe/Moscow",
    "iso:country":"RU",
    "name:rus_x_preferred":[
        "\u0412\u043e\u043b\u043e\u0434\u0430\u0440\u0441\u043a\u0430\u044f"
    ],
    "name:und_x_variant":[
        "Sobakino",
        "Volodarskaya"
    ],
    "wof:name":"Volodarskaya",
    "wof:placetype":"locality"
},
  "geometry": {"coordinates":[36.2024,52.52963],"type":"Point"}
}