{
  "type": "Feature",
  "properties": {
    "gn:admin1_code":"77.0",
    "gn:asciiname":"Malaya Izbrizhka",
    "gn:country_code":"RU",
    "gn:dem":143,
    "gn:feature_class":"P",
    "gn:feature_code":"PPL",
    "gn:name":"Malaya Izbrizhka",
    "gn:population":0,
    "gn:timezone":"Europe/Moscow",
    "iso:country":"RU",
    "name:und_x_variant":[
        "Maloye Izbrizh\u2019ye",
        "Malaya Izbrizhka"
    ],
    "wof:name":"Malaya Izbrizhka",
    "wof:placetype":"locality"
},
  "geometry": {"coordinates":[35.46435,56.78793],"type":"Point"}
}