{
  "type": "Feature",
  "properties": {
    "gn:admin1_code":"53",
    "gn:asciiname":"Novodubrovskoye",
    "gn:cc2":"RU",
    "gn:country_code":"RU",
    "gn:dem":129,
    "gn:feature_class":"P",
    "gn:feature_code":"PPL",
    "gn:name":"Novodubrovskoye",
    "gn:population":0,
    "gn:timezone":"Asia/Novosibirsk",
    "iso:country":"RU",
    "name:eng_x_preferred":[
        "Novodubrovskoye"
    ],
    "name:nor_x_preferred":[
        "Novodubrovskoje"
    ],
    "name:rus_x_preferred":[
        "\u041d\u043e\u0432\u043e\u0434\u0443\u0431\u0440\u043e\u0432\u0441\u043a\u043e\u0435"
    ],
    "name:und_x_variant":[
        "Novodubrovskiy",
        "Novodubrovka",
        "\u041d\u043e\u0432\u043e\u0434\u0443\u0431\u0440\u043e\u0432\u0441\u043a\u043e\u0435",
        "Novodubrovskoye"
    ],
    "wof:name":"Novodubrovskoye",
    "wof:placetype":"locality"
},
  "geometry": {"coordinates":[79.97944,55.70639],"type":"Point"}
}