{
  "type": "Feature",
  "properties": {
    "gn:admin1_code":"42.0",
    "gn:asciiname":"Aropakkuzi",
    "gn:country_code":"RU",
    "gn:dem":112,
    "gn:feature_class":"P",
    "gn:feature_code":"PPL",
    "gn:name":"Aropakkuzi",
    "gn:population":0,
    "gn:timezone":"Europe/Moscow",
    "iso:country":"RU",
    "name:fin_x_preferred":[
        "Aropakkasi"
    ],
    "name:nor_x_preferred":[
        "Aropakkuzi"
    ],
    "name:rus_x_preferred":[
        "\u0410\u0440\u043e\u043f\u0430\u043a\u043a\u0443\u0437\u0438"
    ],
    "wof:name":"Aropakkuzi",
    "wof:placetype":"locality"
},
  "geometry": {"coordinates":[30.01,59.67639000000001],"type":"Point"}
}