{
  "type": "Feature",
  "properties": {
    "gn:admin1_code":"10",
    "gn:asciiname":"Lozitsy",
    "gn:country_code":"RU",
    "gn:dem":204,
    "gn:feature_class":"P",
    "gn:feature_code":"PPL",
    "gn:name":"Lozitsy",
    "gn:population":0,
    "gn:timezone":"Europe/Moscow",
    "iso:country":"RU",
    "name:rus_x_preferred":[
        "\u041b\u043e\u0437\u0438\u0446\u044b"
    ],
    "wof:name":"Lozitsy",
    "wof:placetype":"locality"
},
  "geometry": {"coordinates":[33.498,53.9924],"type":"Point"}
}