{
  "type": "Feature",
  "properties": {
    "gn:admin1_code":"55",
    "gn:asciiname":"Roza Lyuksemburg",
    "gn:country_code":"RU",
    "gn:dem":273,
    "gn:feature_class":"P",
    "gn:feature_code":"PPL",
    "gn:name":"Roza Lyuksemburg",
    "gn:population":0,
    "gn:timezone":"Asia/Yekaterinburg",
    "iso:country":"RU",
    "name:rus_x_preferred":[
        "\u0420\u043e\u0437\u0430 \u041b\u044e\u043a\u0441\u0435\u043c\u0431\u0443\u0440\u0433"
    ],
    "wof:name":"Roza Lyuksemburg",
    "wof:placetype":"locality"
},
  "geometry": {"coordinates":[57.66667,51.26667],"type":"Point"}
}