{
  "type": "Feature",
  "properties": {
    "gn:admin1_code":"71",
    "gn:asciiname":"Dubrovino",
    "gn:country_code":"RU",
    "gn:dem":120,
    "gn:feature_class":"P",
    "gn:feature_code":"PPL",
    "gn:name":"Dubrovino",
    "gn:population":0,
    "gn:timezone":"Asia/Yekaterinburg",
    "iso:country":"RU",
    "name:rus_x_preferred":[
        "\u0414\u0443\u0431\u0440\u043e\u0432\u0438\u043d\u043e"
    ],
    "name:und_x_variant":[
        "Novodubrovino",
        "Dubrovino"
    ],
    "wof:name":"Dubrovino",
    "wof:placetype":"locality"
},
  "geometry": {"coordinates":[63.31361,58.78059],"type":"Point"}
}