{
  "type": "Feature",
  "properties": {
    "gn:admin1_code":"77",
    "gn:asciiname":"Berezovo",
    "gn:country_code":"RU",
    "gn:dem":269,
    "gn:feature_class":"P",
    "gn:feature_code":"PPL",
    "gn:name":"Ber\u00ebzovo",
    "gn:population":0,
    "gn:timezone":"Europe/Moscow",
    "iso:country":"RU",
    "name:nor_x_preferred":[
        "Berezovo"
    ],
    "name:rus_x_preferred":[
        "\u0411\u0435\u0440\u0451\u0437\u043e\u0432\u043e"
    ],
    "name:und_x_variant":[
        "Ber\u00ebzovo"
    ],
    "wof:name":"Berezovo",
    "wof:placetype":"locality"
},
  "geometry": {"coordinates":[32.05833,56.54265],"type":"Point"}
}