{
  "type": "Feature",
  "properties": {
    "gn:admin1_code":"69",
    "gn:asciiname":"Lashutikha",
    "gn:country_code":"RU",
    "gn:dem":226,
    "gn:feature_class":"P",
    "gn:feature_code":"PPL",
    "gn:name":"Lashutikha",
    "gn:population":0,
    "gn:timezone":"Europe/Moscow",
    "iso:country":"RU",
    "name:rus_x_preferred":[
        "\u041b\u0430\u0448\u0443\u0442\u0438\u0445\u0430"
    ],
    "name:und_x_variant":[
        "\u041b\u0430\u0448\u0443\u0442\u0438\u0445\u0430"
    ],
    "wof:name":"Lashutikha",
    "wof:placetype":"locality"
},
  "geometry": {"coordinates":[33.78006,55.66794],"type":"Point"}
}