{
  "type": "Feature",
  "properties": {
    "gn:admin1_code":"91",
    "gn:asciiname":"Kuray",
    "gn:country_code":"RU",
    "gn:dem":207,
    "gn:feature_class":"P",
    "gn:feature_code":"PPL",
    "gn:name":"Kuray",
    "gn:population":0,
    "gn:timezone":"Asia/Krasnoyarsk",
    "iso:country":"RU",
    "name:eng_x_preferred":[
        "Kuray"
    ],
    "name:nor_x_preferred":[
        "Kuraj"
    ],
    "name:rus_x_preferred":[
        "\u041a\u0443\u0440\u0430\u0439"
    ],
    "name:und_x_variant":[
        "Kurayskoye",
        "Kuray"
    ],
    "wof:name":"Kuray",
    "wof:placetype":"locality"
},
  "geometry": {"coordinates":[95.49333,56.68694],"type":"Point"}
}