{
  "type": "Feature",
  "properties": {
    "gn:admin1_code":"88.0",
    "gn:asciiname":"Putrevo",
    "gn:country_code":"RU",
    "gn:dem":136,
    "gn:feature_class":"P",
    "gn:feature_code":"PPL",
    "gn:name":"Putrevo",
    "gn:population":0,
    "gn:timezone":"Europe/Moscow",
    "iso:country":"RU",
    "name:rus_x_preferred":[
        "\u041f\u0443\u0442\u0440\u0435\u0432\u043e"
    ],
    "wof:name":"Putrevo",
    "wof:placetype":"locality"
},
  "geometry": {"coordinates":[40.11673,58.40626],"type":"Point"}
}