{
  "type": "Feature",
  "properties": {
    "gn:admin1_code":"38",
    "gn:asciiname":"Sadovyy",
    "gn:cc2":"RU",
    "gn:country_code":"RU",
    "gn:dem":59,
    "gn:feature_class":"P",
    "gn:feature_code":"PPL",
    "gn:name":"Sadovyy",
    "gn:population":0,
    "gn:timezone":"Europe/Moscow",
    "iso:country":"RU",
    "name:rus_x_preferred":[
        "\u0421\u0430\u0434\u043e\u0432\u044b\u0439"
    ],
    "name:und_x_variant":[
        "Sadovskiy",
        "Sadovy",
        "Sadovyy"
    ],
    "wof:name":"Sadovyy",
    "wof:placetype":"locality"
},
  "geometry": {"coordinates":[40.93111,46.02528],"type":"Point"}
}