{
  "type": "Feature",
  "properties": {
    "gn:admin1_code":"13",
    "gn:asciiname":"Kamyshinka",
    "gn:country_code":"RU",
    "gn:dem":189,
    "gn:feature_class":"P",
    "gn:feature_code":"PPL",
    "gn:name":"Kamyshinka",
    "gn:population":0,
    "gn:timezone":"Asia/Yekaterinburg",
    "iso:country":"RU",
    "name:rus_x_preferred":[
        "\u041a\u0430\u043c\u044b\u0448\u0438\u043d\u043a\u0430"
    ],
    "name:und_x_variant":[
        "\u041a\u0430\u043c\u044b\u0448\u0438\u043d\u043a\u0430"
    ],
    "wof:name":"Kamyshinka",
    "wof:placetype":"locality"
},
  "geometry": {"coordinates":[61.6932,55.0235],"type":"Point"}
}