{
  "type": "Feature",
  "properties": {
    "gn:admin1_code":"73.0",
    "gn:asciiname":"Imeni Vorovskogo",
    "gn:country_code":"RU",
    "gn:dem":89,
    "gn:feature_class":"P",
    "gn:feature_code":"PPL",
    "gn:name":"Imeni Vorovskogo",
    "gn:population":0,
    "gn:timezone":"Europe/Moscow",
    "iso:country":"RU",
    "name:rus_x_preferred":[
        "\u0418\u043c\u0435\u043d\u0438 \u0412\u043e\u0440\u043e\u0432\u0441\u043a\u043e\u0433\u043e"
    ],
    "wof:name":"Imeni Vorovskogo",
    "wof:placetype":"locality"
},
  "geometry": {"coordinates":[53.1658,55.7068],"type":"Point"}
}