{
  "type": "Feature",
  "properties": {
    "gn:admin1_code":"37",
    "gn:asciiname":"Khoroshaya",
    "gn:country_code":"RU",
    "gn:dem":170,
    "gn:feature_class":"P",
    "gn:feature_code":"PPL",
    "gn:name":"Khoroshaya",
    "gn:population":0,
    "gn:timezone":"Europe/Moscow",
    "iso:country":"RU",
    "name:eng_x_preferred":[
        "Khoroshaya"
    ],
    "name:nor_x_preferred":[
        "Khorosjaja"
    ],
    "name:rus_x_preferred":[
        "\u0425\u043e\u0440\u043e\u0448\u0430\u044f"
    ],
    "name:und_x_variant":[
        "Kruglitsa",
        "\u0425\u043e\u0440\u043e\u0448\u0430\u044f",
        "Khoroshaya"
    ],
    "wof:name":"Khoroshaya",
    "wof:placetype":"locality"
},
  "geometry": {"coordinates":[46.33241,58.91205],"type":"Point"}
}