{
  "type": "Feature",
  "properties": {
    "gn:admin1_code":"91",
    "gn:asciiname":"Novonazimovo",
    "gn:country_code":"RU",
    "gn:dem":72,
    "gn:feature_class":"P",
    "gn:feature_code":"PPL",
    "gn:name":"Novonazimovo",
    "gn:population":0,
    "gn:timezone":"Asia/Krasnoyarsk",
    "iso:country":"RU",
    "name:eng_x_preferred":[
        "Novonazimovo"
    ],
    "name:nor_x_preferred":[
        "Novonazimovo"
    ],
    "name:rus_x_preferred":[
        "\u041d\u043e\u0432\u043e\u043d\u0430\u0437\u0438\u043c\u043e\u0432\u043e"
    ],
    "wof:name":"Novonazimovo",
    "wof:placetype":"locality"
},
  "geometry": {"coordinates":[90.815,59.57056],"type":"Point"}
}