{
  "type": "Feature",
  "properties": {
    "gn:admin1_code":"77",
    "gn:asciiname":"Punishche",
    "gn:country_code":"RU",
    "gn:dem":204,
    "gn:feature_class":"P",
    "gn:feature_code":"PPL",
    "gn:name":"Punishche",
    "gn:population":0,
    "gn:timezone":"Europe/Moscow",
    "iso:country":"RU",
    "name:rus_x_preferred":[
        "\u041f\u0443\u043d\u0438\u0449\u0435"
    ],
    "wof:name":"Punishche",
    "wof:placetype":"locality"
},
  "geometry": {"coordinates":[31.83333,55.76667],"type":"Point"}
}