{
  "type": "Feature",
  "properties": {
    "gn:admin1_code":"77",
    "gn:asciiname":"Glumilovo",
    "gn:country_code":"RU",
    "gn:dem":214,
    "gn:feature_class":"P",
    "gn:feature_code":"PPL",
    "gn:name":"Glumilovo",
    "gn:population":0,
    "gn:timezone":"Europe/Moscow",
    "iso:country":"RU",
    "name:rus_x_preferred":[
        "\u0413\u043b\u0443\u043c\u0438\u043b\u043e\u0432\u043e"
    ],
    "wof:name":"Glumilovo",
    "wof:placetype":"locality"
},
  "geometry": {"coordinates":[33.77694,57.40048],"type":"Point"}
}