{
  "type": "Feature",
  "properties": {
    "gn:admin1_code":"77",
    "gn:asciiname":"Rudnya",
    "gn:country_code":"RU",
    "gn:dem":169,
    "gn:feature_class":"P",
    "gn:feature_code":"PPL",
    "gn:name":"Rudnya",
    "gn:population":0,
    "gn:timezone":"Europe/Moscow",
    "iso:country":"RU",
    "name:eng_x_preferred":[
        "Rudnya"
    ],
    "name:nor_x_preferred":[
        "Rudnja"
    ],
    "name:rus_x_preferred":[
        "\u0420\u0443\u0434\u043d\u044f"
    ],
    "name:und_x_variant":[
        "\u0420\u0443\u0434\u043d\u044f",
        "Rudnya"
    ],
    "wof:name":"Rudnya",
    "wof:placetype":"locality"
},
  "geometry": {"coordinates":[31.58519,56.02623000000001],"type":"Point"}
}