{
  "type": "Feature",
  "properties": {
    "gn:admin1_code":"93",
    "gn:asciiname":"Verkhniy Stan",
    "gn:country_code":"RU",
    "gn:dem":942,
    "gn:feature_class":"P",
    "gn:feature_code":"PPL",
    "gn:name":"Verkhniy Stan",
    "gn:population":0,
    "gn:timezone":"Asia/Chita",
    "iso:country":"RU",
    "name:rus_x_preferred":[
        "\u0412\u0435\u0440\u0445\u043d\u0438\u0439 \u0421\u0442\u0430\u043d"
    ],
    "wof:name":"Verkhniy Stan",
    "wof:placetype":"locality"
},
  "geometry": {"coordinates":[112.47795000000001,49.76944],"type":"Point"}
}