{
  "type": "Feature",
  "properties": {
    "gn:admin1_code":"67",
    "gn:asciiname":"Medvedevka",
    "gn:country_code":"RU",
    "gn:dem":183,
    "gn:feature_class":"P",
    "gn:feature_code":"PPL",
    "gn:name":"Medvedevka",
    "gn:population":0,
    "gn:timezone":"Europe/Saratov",
    "iso:country":"RU",
    "name:eng_x_preferred":[
        "Medvedevka"
    ],
    "name:nor_x_preferred":[
        "Medvedevka"
    ],
    "name:rus_x_preferred":[
        "\u041c\u0435\u0434\u0432\u0435\u0434\u0435\u0432\u043a\u0430"
    ],
    "name:und_x_variant":[
        "Medevedevka",
        "Medvedevka"
    ],
    "wof:name":"Medvedevka",
    "wof:placetype":"locality"
},
  "geometry": {"coordinates":[44.89542,52.01545],"type":"Point"}
}