{
  "type": "Feature",
  "properties": {
    "gn:admin1_code":"13",
    "gn:asciiname":"Paduchin",
    "gn:country_code":"RU",
    "gn:dem":397,
    "gn:feature_class":"P",
    "gn:feature_code":"PPL",
    "gn:name":"Paduchin",
    "gn:population":0,
    "gn:timezone":"Asia/Yekaterinburg",
    "iso:country":"RU",
    "name:rus_x_preferred":[
        "\u041f\u0430\u0434\u0443\u0447\u0438\u043d"
    ],
    "name:und_x_variant":[
        "\u041f\u0430\u0434\u0443\u0447\u0438\u043d"
    ],
    "wof:name":"Paduchin",
    "wof:placetype":"locality"
},
  "geometry": {"coordinates":[60.13333000000001,54.78333000000001],"type":"Point"}
}