{
  "type": "Feature",
  "properties": {
    "gn:admin1_code":"88",
    "gn:asciiname":"Baksheyevo",
    "gn:country_code":"RU",
    "gn:dem":191,
    "gn:feature_class":"P",
    "gn:feature_code":"PPL",
    "gn:name":"Baksheyevo",
    "gn:population":0,
    "gn:timezone":"Europe/Moscow",
    "iso:country":"RU",
    "name:rus_x_preferred":[
        "\u0411\u0430\u043a\u0448\u0435\u0435\u0432\u043e"
    ],
    "wof:name":"Baksheyevo",
    "wof:placetype":"locality"
},
  "geometry": {"coordinates":[39.004,56.6841],"type":"Point"}
}