{
  "type": "Feature",
  "properties": {
    "gn:admin1_code":"65",
    "gn:asciiname":"Vysokaya Step'",
    "gn:country_code":"RU",
    "gn:dem":109,
    "gn:feature_class":"P",
    "gn:feature_code":"PPL",
    "gn:name":"Vysokaya Step\u2019",
    "gn:population":0,
    "gn:timezone":"Europe/Samara",
    "iso:country":"RU",
    "name:rus_x_preferred":[
        "\u0412\u044b\u0441\u043e\u043a\u0430\u044f \u0421\u0442\u0435\u043f\u044c"
    ],
    "name:und_x_variant":[
        "Vysokaya Step\u2019"
    ],
    "wof:name":"Vysokaya Step'",
    "wof:placetype":"locality"
},
  "geometry": {"coordinates":[50.06291,53.65601],"type":"Point"}
}