{
  "type": "Feature",
  "properties": {
    "gn:admin1_code":"33",
    "gn:asciiname":"Orekhovo",
    "gn:country_code":"RU",
    "gn:dem":113,
    "gn:feature_class":"P",
    "gn:feature_code":"PPL",
    "gn:name":"Orekhovo",
    "gn:population":0,
    "gn:timezone":"Europe/Kirov",
    "iso:country":"RU",
    "name:ceb_x_preferred":[
        "Orekhovo"
    ],
    "name:fra_x_preferred":[
        "Orekhovo"
    ],
    "name:rus_x_preferred":[
        "\u041e\u0440\u0435\u0445\u043e\u0432\u043e"
    ],
    "name:swe_x_preferred":[
        "Orekhovo"
    ],
    "wof:name":"Orekhovo",
    "wof:placetype":"locality"
},
  "geometry": {"coordinates":[50.4242,57.78569],"type":"Point"}
}