{
  "type": "Feature",
  "properties": {
    "gn:admin1_code":"22",
    "gn:asciiname":"Grabovets",
    "gn:country_code":"RU",
    "gn:dem":302,
    "gn:feature_class":"P",
    "gn:feature_code":"PPL",
    "gn:name":"Grabovets",
    "gn:population":0,
    "gn:timezone":"Europe/Moscow",
    "iso:country":"RU",
    "name:rus_x_preferred":[
        "\u0413\u0440\u0430\u0431\u043e\u0432\u0435\u0446"
    ],
    "name:und_x_variant":[
        "Grobtsovskiy",
        "Grabovets",
        "\u0413\u0440\u0430\u0431\u043e\u0432\u0435\u0446"
    ],
    "wof:name":"Grabovets",
    "wof:placetype":"locality"
},
  "geometry": {"coordinates":[43.73417,43.67944],"type":"Point"}
}