{
  "type": "Feature",
  "properties": {
    "gn:admin1_code":"34.0",
    "gn:asciiname":"Arkhipovka",
    "gn:country_code":"RU",
    "gn:dem":172,
    "gn:feature_class":"P",
    "gn:feature_code":"PPL",
    "gn:name":"Arkhipovka",
    "gn:population":0,
    "gn:timezone":"Europe/Moscow",
    "iso:country":"RU",
    "name:nor_x_preferred":[
        "Arkhipovka"
    ],
    "name:rus_x_preferred":[
        "\u0410\u0440\u0445\u0438\u043f\u043e\u0432\u043a\u0430"
    ],
    "wof:name":"Arkhipovka",
    "wof:placetype":"locality"
},
  "geometry": {"coordinates":[49.45225,59.49556],"type":"Point"}
}