{
  "type": "Feature",
  "properties": {
    "gn:admin1_code":"8",
    "gn:asciiname":"Il'keneyevo",
    "gn:country_code":"RU",
    "gn:dem":238,
    "gn:feature_class":"P",
    "gn:feature_code":"PPL",
    "gn:name":"Il\u2019keneyevo",
    "gn:population":0,
    "gn:timezone":"Asia/Yekaterinburg",
    "iso:country":"RU",
    "name:rus_x_preferred":[
        "\u0418\u043b\u044c\u043a\u0435\u043d\u0435\u0435\u0432\u043e"
    ],
    "name:und_x_variant":[
        "Il\u2019kineyevo",
        "Il\u2019keneyevo"
    ],
    "wof:name":"Il'keneyevo",
    "wof:placetype":"locality"
},
  "geometry": {"coordinates":[55.76667,52.86666999999999],"type":"Point"}
}