{
  "type": "Feature",
  "properties": {
    "gn:admin1_code":"52",
    "gn:asciiname":"Yamno",
    "gn:country_code":"RU",
    "gn:dem":75,
    "gn:feature_class":"P",
    "gn:feature_code":"PPL",
    "gn:name":"Yamno",
    "gn:population":0,
    "gn:timezone":"Europe/Moscow",
    "iso:country":"RU",
    "name:rus_x_preferred":[
        "\u042f\u043c\u043d\u043e"
    ],
    "name:und_x_variant":[
        "Yamna",
        "Yamno"
    ],
    "wof:name":"Yamno",
    "wof:placetype":"locality"
},
  "geometry": {"coordinates":[31.00257,57.53336],"type":"Point"}
}