{
  "type": "Feature",
  "properties": {
    "gn:admin1_code":"56",
    "gn:asciiname":"Yadrino",
    "gn:country_code":"RU",
    "gn:dem":156,
    "gn:feature_class":"P",
    "gn:feature_code":"PPL",
    "gn:name":"Yadrino",
    "gn:population":0,
    "gn:timezone":"Europe/Moscow",
    "iso:country":"RU",
    "name:che_x_preferred":[
        "\u042f\u0434\u0440\u0438\u043d\u043e"
    ],
    "name:rus_x_preferred":[
        "\u042f\u0434\u0440\u0438\u043d\u043e"
    ],
    "name:tgk_x_preferred":[
        "\u042f\u0434\u0440\u0438\u043d\u043e"
    ],
    "name:und_x_variant":[
        "Yandreno",
        "Yadrino"
    ],
    "wof:name":"Yadrino",
    "wof:placetype":"locality"
},
  "geometry": {"coordinates":[36.62345,53.24471],"type":"Point"}
}