{
  "type": "Feature",
  "properties": {
    "gn:admin1_code":"85",
    "gn:asciiname":"Yesyutkino",
    "gn:country_code":"RU",
    "gn:dem":178,
    "gn:feature_class":"P",
    "gn:feature_code":"PPL",
    "gn:name":"Yesyutkino",
    "gn:population":0,
    "gn:timezone":"Europe/Moscow",
    "iso:country":"RU",
    "name:rus_x_preferred":[
        "\u0415\u0441\u044e\u0442\u043a\u0438\u043d\u043e"
    ],
    "name:und_x_variant":[
        "\u0415\u0441\u044e\u0442\u043a\u0438\u043d\u043e"
    ],
    "wof:name":"Yesyutkino",
    "wof:placetype":"locality"
},
  "geometry": {"coordinates":[39.9038,59.0085],"type":"Point"}
}