{
  "type": "Feature",
  "properties": {
    "gn:country":"RU",
    "gn:fcode":"PPLX",
    "gn:population":0,
    "iso:country":"RU",
    "name:rus_x_preferred":[
        "\u0428\u0438\u0431\u0430\u043d\u043e\u0432\u043e"
    ],
    "qs:name":"Shibanovo",
    "qs:name_adm0":"Russia",
    "qs:name_adm1":"Moscow Oblast",
    "qs:photos":41,
    "qs:photos_1k":8,
    "qs:photos_9k":1,
    "qs:photos_9r":2,
    "qs:photos_all":41,
    "qs:photos_sr":2,
    "qs:placetype":"Suburb",
    "qs:pop_sr":"0",
    "wof:name":"Shibanovo",
    "wof:placetype":"neighbourhood",
    "wof:population":0
},
  "geometry": {"coordinates":[38.43333,55.76667],"type":"Point"}
}