{
  "type": "Feature",
  "properties": {
    "gn:admin1_code":"92",
    "gn:asciiname":"Asuvaam",
    "gn:country_code":"RU",
    "gn:dem":62,
    "gn:feature_class":"P",
    "gn:feature_code":"PPL",
    "gn:name":"Asuvaam",
    "gn:population":0,
    "gn:timezone":"Asia/Kamchatka",
    "iso:country":"RU",
    "name:nor_x_preferred":[
        "Asuvaam"
    ],
    "name:rus_x_preferred":[
        "\u0410\u0441\u0443\u0432\u0430\u0430\u043c"
    ],
    "name:und_x_variant":[
        "Asuveem"
    ],
    "wof:name":"Asuvaam",
    "wof:placetype":"locality"
},
  "geometry": {"coordinates":[169.73333,60.65],"type":"Point"}
}