{
  "type": "Feature",
  "properties": {
    "iso:country":"RU",
    "name:rus_x_preferred":[
        "\u041c\u0435\u0449\u0430\u043d\u0441\u043a\u0438\u0439"
    ],
    "wof:name":"Meshchansky",
    "wof:placetype":"neighbourhood"
},
  "geometry": {"coordinates":[37.6292457683159,55.77991525290669],"type":"Point"}
}