{
  "type": "Feature",
  "properties": {
    "gn:admin1_code":"88",
    "gn:asciiname":"Aleshino",
    "gn:country_code":"RU",
    "gn:dem":163,
    "gn:feature_class":"P",
    "gn:feature_code":"PPL",
    "gn:name":"Al\u00ebshino",
    "gn:population":0,
    "gn:timezone":"Europe/Moscow",
    "iso:country":"RU",
    "name:rus_x_preferred":[
        "\u0410\u043b\u0451\u0448\u0438\u043d\u043e"
    ],
    "name:und_x_variant":[
        "Al\u00ebshino"
    ],
    "wof:name":"Aleshino",
    "wof:placetype":"locality"
},
  "geometry": {"coordinates":[39.2303,56.9651],"type":"Point"}
}