{
  "type": "Feature",
  "properties": {
    "gn:admin1_code":"93",
    "gn:asciiname":"Talochi",
    "gn:country_code":"RU",
    "gn:dem":832,
    "gn:feature_class":"P",
    "gn:feature_code":"PPL",
    "gn:name":"Talochi",
    "gn:population":0,
    "gn:timezone":"Asia/Chita",
    "iso:country":"RU",
    "wof:name":"Talochi",
    "wof:placetype":"locality"
},
  "geometry": {"coordinates":[115.67917,53.73667],"type":"Point"}
}