{
  "type": "Feature",
  "properties": {
    "gn:admin1_code":"71",
    "gn:asciiname":"Vysotinka",
    "gn:country_code":"RU",
    "gn:dem":166,
    "gn:feature_class":"P",
    "gn:feature_code":"PPL",
    "gn:name":"Vysotinka",
    "gn:population":0,
    "gn:timezone":"Asia/Yekaterinburg",
    "iso:country":"RU",
    "name:eng_x_preferred":[
        "Vysotinka"
    ],
    "name:nor_x_preferred":[
        "Vysotinka"
    ],
    "name:rus_x_preferred":[
        "\u0412\u044b\u0441\u043e\u0442\u0438\u043d\u043a\u0430"
    ],
    "wof:name":"Vysotinka",
    "wof:placetype":"locality"
},
  "geometry": {"coordinates":[60.10491,60.17501],"type":"Point"}
}