{
  "type": "Feature",
  "properties": {
    "gn:admin1_code":"70",
    "gn:asciiname":"Berezovskiy",
    "gn:country_code":"RU",
    "gn:dem":135,
    "gn:feature_class":"P",
    "gn:feature_code":"PPL",
    "gn:name":"Ber\u00ebzovskiy",
    "gn:population":0,
    "gn:timezone":"Europe/Moscow",
    "iso:country":"RU",
    "name:eng_x_preferred":[
        "Ber\u00ebzovskiy"
    ],
    "name:rus_x_preferred":[
        "\u0411\u0435\u0440\u0435\u0437\u043e\u0432\u0441\u043a\u0438\u0439"
    ],
    "name:rus_x_variant":[
        "\u0411\u0435\u0440\u0451\u0437\u043e\u0432\u0441\u043a\u0438\u0439"
    ],
    "name:und_x_variant":[
        "Ber\u00ebzovskiy"
    ],
    "wof:name":"Berezovskiy",
    "wof:placetype":"locality"
},
  "geometry": {"coordinates":[43.33611,45.47889],"type":"Point"}
}