{
  "type": "Feature",
  "properties": {
    "gn:admin1_code":"47",
    "gn:asciiname":"Kanunovo",
    "gn:country_code":"RU",
    "gn:dem":152,
    "gn:feature_class":"P",
    "gn:feature_code":"PPL",
    "gn:name":"Kanunovo",
    "gn:population":0,
    "gn:timezone":"Europe/Moscow",
    "iso:country":"RU",
    "name:rus_x_preferred":[
        "\u041a\u0430\u043d\u0443\u043d\u043e\u0432\u043e"
    ],
    "wof:name":"Kanunovo",
    "wof:placetype":"locality"
},
  "geometry": {"coordinates":[38.05092,55.04369000000001],"type":"Point"}
}