{
  "type": "Feature",
  "properties": {
    "gn:admin1_code":"6.0",
    "gn:asciiname":"Poselok Chelomkhotskoy Bazy",
    "gn:country_code":"RU",
    "gn:dem":24,
    "gn:feature_class":"P",
    "gn:feature_code":"PPL",
    "gn:name":"Pos\u00eblok Chelomkhotskoy Bazy",
    "gn:population":0,
    "gn:timezone":"Europe/Moscow",
    "iso:country":"RU",
    "name:rus_x_preferred":[
        "\u041f\u043e\u0441\u0451\u043b\u043e\u043a \u0427\u0435\u043b\u043e\u043c\u0445\u043e\u0442\u0441\u043a\u043e\u0439 \u0411\u0430\u0437\u044b"
    ],
    "name:und_x_variant":[
        "Chelmokhta",
        "Pos\u00eblok Chelomkhotskoy Bazy"
    ],
    "wof:name":"Poselok Chelomkhotskoy Bazy",
    "wof:placetype":"locality"
},
  "geometry": {"coordinates":[41.7215,63.6594],"type":"Point"}
}