{
  "type": "Feature",
  "properties": {
    "gn:admin1_code":"73",
    "gn:asciiname":"Tash-Kichu",
    "gn:country_code":"RU",
    "gn:dem":198,
    "gn:feature_class":"P",
    "gn:feature_code":"PPL",
    "gn:name":"Tash-Kichu",
    "gn:population":0,
    "gn:timezone":"Europe/Moscow",
    "iso:country":"RU",
    "name:rus_x_preferred":[
        "\u0422\u0430\u0448-\u041a\u0438\u0447\u0443"
    ],
    "name:und_x_variant":[
        "\u0422\u0430\u0448-\u041a\u0438\u0447\u0443"
    ],
    "wof:name":"Tash-Kichu",
    "wof:placetype":"locality"
},
  "geometry": {"coordinates":[52.4575,55.5361],"type":"Point"}
}