{
  "type": "Feature",
  "properties": {
    "gn:admin1_code":"33.0",
    "gn:asciiname":"Lopari",
    "gn:country_code":"RU",
    "gn:dem":164,
    "gn:feature_class":"P",
    "gn:feature_code":"PPL",
    "gn:name":"Lopari",
    "gn:population":0,
    "gn:timezone":"Europe/Kirov",
    "iso:country":"RU",
    "name:rus_x_preferred":[
        "\u041b\u043e\u043f\u0430\u0440\u0438"
    ],
    "name:und_x_variant":[
        "\u041b\u043e\u043f\u0430\u0440\u0438"
    ],
    "wof:name":"Lopari",
    "wof:placetype":"locality"
},
  "geometry": {"coordinates":[49.98328,59.03581],"type":"Point"}
}