{
  "type": "Feature",
  "properties": {
    "gn:admin1_code":"31",
    "gn:asciiname":"Solomennyy Stan",
    "gn:cc2":"RU",
    "gn:country_code":"RU",
    "gn:dem":375,
    "gn:feature_class":"P",
    "gn:feature_code":"PPL",
    "gn:name":"Solomennyy Stan",
    "gn:population":0,
    "gn:timezone":"Asia/Krasnoyarsk",
    "iso:country":"RU",
    "name:rus_x_preferred":[
        "\u0421\u043e\u043b\u043e\u043c\u0435\u043d\u043d\u044b\u0439 \u0421\u0442\u0430\u043d"
    ],
    "name:und_x_variant":[
        "Solomenny Stan",
        "Solomennyy Stan",
        "\u0421\u043e\u043b\u043e\u043c\u0435\u043d\u043d\u044b\u0439 \u0421\u0442\u0430\u043d"
    ],
    "wof:name":"Solomennyy Stan",
    "wof:placetype":"locality"
},
  "geometry": {"coordinates":[90.81667,53.16667],"type":"Point"}
}