{
  "type": "Feature",
  "properties": {
    "gn:admin1_code":"71",
    "gn:asciiname":"Loz'vinskoye Yedineniye",
    "gn:country_code":"RU",
    "gn:dem":52,
    "gn:feature_class":"P",
    "gn:feature_code":"PPL",
    "gn:name":"Loz\u2019vinskoye Yedineniye",
    "gn:population":0,
    "gn:timezone":"Asia/Yekaterinburg",
    "iso:country":"RU",
    "name:rus_x_preferred":[
        "\u041b\u043e\u0437\u044c\u0432\u0438\u043d\u0441\u043a\u043e\u0435 \u0415\u0434\u0438\u043d\u0435\u043d\u0438\u0435"
    ],
    "name:und_x_variant":[
        "Loz\u2019vinskoye Yedineniye"
    ],
    "wof:name":"Loz'vinskoye Yedineniye",
    "wof:placetype":"locality"
},
  "geometry": {"coordinates":[60.61666999999999,60.55],"type":"Point"}
}