{
  "type": "Feature",
  "properties": {
    "gn:admin1_code":"21.0",
    "gn:asciiname":"Ryzhevo",
    "gn:country_code":"RU",
    "gn:dem":103,
    "gn:feature_class":"P",
    "gn:feature_code":"PPL",
    "gn:name":"Ryzh\u00ebvo",
    "gn:population":0,
    "gn:timezone":"Europe/Moscow",
    "iso:country":"RU",
    "name:rus_x_preferred":[
        "\u0420\u044b\u0436\u0451\u0432\u043e"
    ],
    "name:und_x_variant":[
        "Ryzh\u00ebvo"
    ],
    "wof:name":"Ryzhevo",
    "wof:placetype":"locality"
},
  "geometry": {"coordinates":[41.22167,56.66976],"type":"Point"}
}