{
  "type": "Feature",
  "properties": {
    "gn:admin1_code":"10",
    "gn:asciiname":"Dzhurovka",
    "gn:country_code":"RU",
    "gn:dem":174,
    "gn:feature_class":"P",
    "gn:feature_code":"PPL",
    "gn:name":"Dzhurovka",
    "gn:population":0,
    "gn:timezone":"Europe/Moscow",
    "iso:country":"RU",
    "name:rus_x_preferred":[
        "\u0414\u0436\u0443\u0440\u043e\u0432\u043a\u0430"
    ],
    "wof:name":"Dzhurovka",
    "wof:placetype":"locality"
},
  "geometry": {"coordinates":[33.1625,52.5735],"type":"Point"}
}