{
  "type": "Feature",
  "properties": {
    "gn:admin1_code":"17",
    "gn:asciiname":"Nizhniye Labkomakhi",
    "gn:country_code":"RU",
    "gn:dem":1565,
    "gn:feature_class":"P",
    "gn:feature_code":"PPL",
    "gn:name":"Nizhniye Labkomakhi",
    "gn:population":0,
    "gn:timezone":"Europe/Moscow",
    "iso:country":"RU",
    "name:rus_x_preferred":[
        "\u041d\u0438\u0436\u043d\u0438\u0435 \u041b\u0430\u0431\u043a\u043e\u043c\u0430\u0445\u0438"
    ],
    "name:und_x_variant":[
        "Nizhniye Lanko-Makhi",
        "Nizhniye Lobkomakhi",
        "Nizhniye Labkomakhi",
        "\u041d\u0438\u0436\u043d\u0438\u0435 \u041b\u0430\u0431\u043a\u043e\u043c\u0430\u0445\u0438"
    ],
    "wof:name":"Nizhniye Labkomakhi",
    "wof:placetype":"locality"
},
  "geometry": {"coordinates":[47.41873,42.35084000000001],"type":"Point"}
}