{
  "type": "Feature",
  "properties": {
    "gn:admin1_code":"77",
    "gn:asciiname":"Lesnyye",
    "gn:country_code":"RU",
    "gn:dem":172,
    "gn:feature_class":"P",
    "gn:feature_code":"PPL",
    "gn:name":"Lesnyye",
    "gn:population":0,
    "gn:timezone":"Europe/Moscow",
    "iso:country":"RU",
    "name:rus_x_preferred":[
        "\u041b\u0435\u0441\u043d\u044b\u0435"
    ],
    "name:und_x_variant":[
        "\u041b\u0435\u0441\u043d\u044b\u0435"
    ],
    "wof:name":"Lesnyye",
    "wof:placetype":"locality"
},
  "geometry": {"coordinates":[37.208,57.8006],"type":"Point"}
}