{
  "type": "Feature",
  "properties": {
    "gn:admin1_code":"61.0",
    "gn:asciiname":"Kurnosov",
    "gn:country_code":"RU",
    "gn:dem":83,
    "gn:feature_class":"P",
    "gn:feature_code":"PPL",
    "gn:name":"Kurnosov",
    "gn:population":0,
    "gn:timezone":"Europe/Moscow",
    "iso:country":"RU",
    "name:rus_x_preferred":[
        "\u041a\u0443\u0440\u043d\u043e\u0441\u043e\u0432"
    ],
    "name:und_x_variant":[
        "\u041a\u0443\u0440\u043d\u043e\u0441\u043e\u0432"
    ],
    "wof:name":"Kurnosov",
    "wof:placetype":"locality"
},
  "geometry": {"coordinates":[41.54778,48.76861],"type":"Point"}
}