{
  "type": "Feature",
  "properties": {
    "gn:admin1_code":"90",
    "gn:asciiname":"Shipitsyna",
    "gn:country_code":"RU",
    "gn:dem":155,
    "gn:feature_class":"P",
    "gn:feature_code":"PPL",
    "gn:name":"Shipitsyna",
    "gn:population":0,
    "gn:timezone":"Asia/Yekaterinburg",
    "iso:country":"RU",
    "name:che_x_preferred":[
        "\u0428\u0438\u043f\u0438\u0446\u044b\u043d\u0430"
    ],
    "name:koi_x_preferred":[
        "\u0428\u044b\u043f\u0438\u0447\u0438"
    ],
    "name:rus_x_preferred":[
        "\u0428\u0438\u043f\u0438\u0446\u044b\u043d\u0430"
    ],
    "name:und_x_variant":[
        "\u0428\u0438\u043f\u0438\u0446\u044b\u043d\u0430"
    ],
    "wof:name":"Shipitsyna",
    "wof:placetype":"locality"
},
  "geometry": {"coordinates":[54.73333,59.14722],"type":"Point"}
}