{
  "type": "Feature",
  "properties": {
    "gn:admin1_code":"77",
    "gn:asciiname":"Nizhniye Kotitsy",
    "gn:country_code":"RU",
    "gn:dem":205,
    "gn:feature_class":"P",
    "gn:feature_code":"PPL",
    "gn:name":"Nizhniye Kotitsy",
    "gn:population":0,
    "gn:timezone":"Europe/Moscow",
    "iso:country":"RU",
    "name:rus_x_preferred":[
        "\u041d\u0438\u0436\u043d\u0438\u0435 \u041a\u043e\u0442\u0438\u0446\u044b"
    ],
    "name:und_x_variant":[
        "Novyye Kotitsy",
        "Nizhniye Kotitsy"
    ],
    "wof:name":"Nizhniye Kotitsy",
    "wof:placetype":"locality"
},
  "geometry": {"coordinates":[33.28086,57.0295],"type":"Point"}
}