{
  "type": "Feature",
  "properties": {
    "gn:admin1_code":"77",
    "gn:asciiname":"Dor",
    "gn:country_code":"RU",
    "gn:dem":160,
    "gn:feature_class":"P",
    "gn:feature_code":"PPL",
    "gn:name":"Dor",
    "gn:population":0,
    "gn:timezone":"Europe/Moscow",
    "iso:country":"RU",
    "name:ceb_x_preferred":[
        "Dor"
    ],
    "name:ces_x_preferred":[
        "Dor"
    ],
    "name:deu_x_preferred":[
        "Dor"
    ],
    "name:fra_x_preferred":[
        "Dor"
    ],
    "name:hye_x_preferred":[
        "\u0534\u0578\u0580"
    ],
    "name:nld_x_preferred":[
        "Dor"
    ],
    "name:nor_x_preferred":[
        "Dor"
    ],
    "name:pol_x_preferred":[
        "Dor"
    ],
    "name:por_x_preferred":[
        "Dor"
    ],
    "name:rus_x_preferred":[
        "\u0414\u043e\u0440"
    ],
    "name:srp_x_preferred":[
        "\u0414\u043e\u0440"
    ],
    "name:swe_x_preferred":[
        "Dor"
    ],
    "wof:name":"Dor",
    "wof:placetype":"locality"
},
  "geometry": {"coordinates":[37.0973,57.9256],"type":"Point"}
}