{
  "type": "Feature",
  "properties": {
    "gn:admin1_code":"12",
    "gn:asciiname":"Ushkaloy",
    "gn:country_code":"RU",
    "gn:dem":712,
    "gn:feature_class":"P",
    "gn:feature_code":"PPL",
    "gn:name":"Ushkaloy",
    "gn:population":0,
    "gn:timezone":"Europe/Moscow",
    "iso:country":"RU",
    "name:che_x_preferred":[
        "U\u0161kaloj"
    ],
    "name:che_x_variant":[
        "U\u015fq\u00e4lla",
        "\u00dc\u015f-Qelli",
        "\u0423\u0448\u043a\u0445\u0430\u044c\u043b\u043b\u0430",
        "\u0423\u044c\u0448-\u041a\u0445\u0435\u043b\u043b\u0438"
    ],
    "name:rus_x_preferred":[
        "\u0423\u0448\u043a\u0430\u043b\u043e\u0439"
    ],
    "name:und_x_variant":[
        "Ushkoloy",
        "Ushkaloy"
    ],
    "wof:name":"Ushkaloy",
    "wof:placetype":"locality"
},
  "geometry": {"coordinates":[45.61623,42.77847],"type":"Point"}
}