{
  "type": "Feature",
  "properties": {
    "gn:admin1_code":"72",
    "gn:asciiname":"Grigor'yevka",
    "gn:country_code":"RU",
    "gn:dem":172,
    "gn:feature_class":"P",
    "gn:feature_code":"PPL",
    "gn:name":"Grigor\u2019yevka",
    "gn:population":0,
    "gn:timezone":"Europe/Moscow",
    "iso:country":"RU",
    "name:eng_x_preferred":[
        "Grigor'yevka"
    ],
    "name:nor_x_preferred":[
        "Grigorjevka"
    ],
    "name:rus_x_preferred":[
        "\u0413\u0440\u0438\u0433\u043e\u0440\u044c\u0435\u0432\u043a\u0430"
    ],
    "name:und_x_variant":[
        "Gfigor\u2019yevka",
        "\u0413\u0440\u0438\u0433\u043e\u0440\u044c\u0435\u0432\u043a\u0430",
        "Grigor\u2019yevka"
    ],
    "wof:name":"Grigor'yevka",
    "wof:placetype":"locality"
},
  "geometry": {"coordinates":[41.9604,51.67542],"type":"Point"}
}