{
  "type": "Feature",
  "properties": {
    "gn:admin1_code":"60",
    "gn:asciiname":"Ostrov",
    "gn:country_code":"RU",
    "gn:dem":34,
    "gn:feature_class":"P",
    "gn:feature_code":"PPL",
    "gn:name":"Ostrov",
    "gn:population":0,
    "gn:timezone":"Europe/Moscow",
    "iso:country":"RU",
    "name:rus_x_preferred":[
        "\u041e\u0441\u0442\u0440\u043e\u0432"
    ],
    "name:und_x_variant":[
        "\u041e\u0441\u0442\u0440\u043e\u0432"
    ],
    "wof:name":"Ostrov",
    "wof:placetype":"locality"
},
  "geometry": {"coordinates":[27.56124,58.28737],"type":"Point"}
}