{
  "type": "Feature",
  "properties": {
    "gn:admin1_code":"40",
    "gn:asciiname":"Vodolazovo",
    "gn:country_code":"RU",
    "gn:dem":156,
    "gn:feature_class":"P",
    "gn:feature_code":"PPL",
    "gn:name":"Vodolazovo",
    "gn:population":0,
    "gn:timezone":"Asia/Yekaterinburg",
    "iso:country":"RU",
    "name:rus_x_preferred":[
        "\u0412\u043e\u0434\u043e\u043b\u0430\u0437\u043e\u0432\u043e"
    ],
    "wof:name":"Vodolazovo",
    "wof:placetype":"locality"
},
  "geometry": {"coordinates":[62.3108,56.3805],"type":"Point"}
}