{
  "type": "Feature",
  "properties": {
    "gn:admin1_code":"67",
    "gn:asciiname":"Lopukhovka",
    "gn:country_code":"RU",
    "gn:dem":151,
    "gn:feature_class":"P",
    "gn:feature_code":"PPL",
    "gn:name":"Lopukhovka",
    "gn:population":0,
    "gn:timezone":"Europe/Saratov",
    "iso:country":"RU",
    "name:rus_x_preferred":[
        "\u041b\u043e\u043f\u0443\u0445\u043e\u0432\u043a\u0430"
    ],
    "name:und_x_variant":[
        "\u041b\u043e\u043f\u0443\u0445\u043e\u0432\u043a\u0430"
    ],
    "wof:name":"Lopukhovka",
    "wof:placetype":"locality"
},
  "geometry": {"coordinates":[44.85707,51.6753],"type":"Point"}
}