{
  "type": "Feature",
  "properties": {
    "gn:admin1_code":"72",
    "gn:asciiname":"Krasnyy Gorodok",
    "gn:cc2":"RU",
    "gn:country_code":"RU",
    "gn:dem":119,
    "gn:feature_class":"P",
    "gn:feature_code":"PPL",
    "gn:name":"Krasnyy Gorodok",
    "gn:population":0,
    "gn:timezone":"Europe/Moscow",
    "iso:country":"RU",
    "name:rus_x_preferred":[
        "\u041a\u0440\u0430\u0441\u043d\u044b\u0439 \u0413\u043e\u0440\u043e\u0434\u043e\u043a"
    ],
    "name:und_x_variant":[
        "Arlyapovo",
        "Krasnyy Gorodok",
        "\u041a\u0440\u0430\u0441\u043d\u044b\u0439 \u0413\u043e\u0440\u043e\u0434\u043e\u043a"
    ],
    "wof:name":"Krasnyy Gorodok",
    "wof:placetype":"locality"
},
  "geometry": {"coordinates":[40.45,52.78333000000001],"type":"Point"}
}