{
  "type": "Feature",
  "properties": {
    "gn:admin1_code":"43",
    "gn:asciiname":"Novotroitskoye",
    "gn:country_code":"RU",
    "gn:dem":146,
    "gn:feature_class":"P",
    "gn:feature_code":"PPL",
    "gn:name":"Novotroitskoye",
    "gn:population":0,
    "gn:timezone":"Europe/Moscow",
    "iso:country":"RU",
    "name:eng_x_preferred":[
        "Novotroitskoye"
    ],
    "name:nor_x_preferred":[
        "Novotroitskoje"
    ],
    "name:rus_x_preferred":[
        "\u041d\u043e\u0432\u043e\u0442\u0440\u043e\u0438\u0446\u043a\u043e\u0435"
    ],
    "name:und_x_variant":[
        "Pozdnyakovo",
        "Novo-Toitskoye",
        "\u041d\u043e\u0432\u043e\u0442\u0440\u043e\u0438\u0446\u043a\u043e\u0435",
        "Novotroitskoye"
    ],
    "wof:name":"Novotroitskoye",
    "wof:placetype":"locality"
},
  "geometry": {"coordinates":[38.054,52.37539],"type":"Point"}
}