{
  "type": "Feature",
  "properties": {
    "gn:admin1_code":"05",
    "gn:asciiname":"Lozovaya",
    "gn:country_code":"RU",
    "gn:dem":178,
    "gn:feature_class":"P",
    "gn:feature_code":"PPL",
    "gn:name":"Lozovaya",
    "gn:population":0,
    "gn:timezone":"Asia/Yakutsk",
    "iso:country":"RU",
    "name:eng_x_preferred":[
        "Lozovaya"
    ],
    "name:nor_x_preferred":[
        "Lozovaja"
    ],
    "name:rus_x_preferred":[
        "\u041b\u043e\u0437\u043e\u0432\u0430\u044f"
    ],
    "name:und_x_variant":[
        "Rozouaya",
        "Rozowaya",
        "\u041b\u043e\u0437\u043e\u0432\u0430\u044f",
        "Lozovaya"
    ],
    "wof:name":"Lozovaya",
    "wof:placetype":"locality"
},
  "geometry": {"coordinates":[128.31986000000001,50.77651],"type":"Point"}
}