{
  "type": "Feature",
  "properties": {
    "gn:admin1_code":"25.0",
    "gn:asciiname":"Srednyaya Fabrika",
    "gn:country_code":"RU",
    "gn:dem":139,
    "gn:feature_class":"P",
    "gn:feature_code":"PPL",
    "gn:name":"Srednyaya Fabrika",
    "gn:population":0,
    "gn:timezone":"Europe/Moscow",
    "iso:country":"RU",
    "wof:name":"Srednyaya Fabrika",
    "wof:placetype":"locality"
},
  "geometry": {"coordinates":[36.43518,54.43658000000001],"type":"Point"}
}