{
  "type": "Feature",
  "properties": {
    "gn:admin1_code":"63",
    "gn:asciiname":"Ulakhan-Syat",
    "gn:country_code":"RU",
    "gn:dem":173,
    "gn:feature_class":"P",
    "gn:feature_code":"PPL",
    "gn:name":"Ulakhan-Syat",
    "gn:population":0,
    "gn:timezone":"Asia/Yakutsk",
    "iso:country":"RU",
    "wof:name":"Ulakhan-Syat",
    "wof:placetype":"locality"
},
  "geometry": {"coordinates":[120.53333000000001,63.16667],"type":"Point"}
}