{
  "type": "Feature",
  "properties": {
    "gn:admin1_code":"60",
    "gn:asciiname":"Snegiri",
    "gn:country_code":"RU",
    "gn:dem":68,
    "gn:feature_class":"P",
    "gn:feature_code":"PPL",
    "gn:name":"Snegiri",
    "gn:population":0,
    "gn:timezone":"Europe/Moscow",
    "iso:country":"RU",
    "name:ceb_x_preferred":[
        "Snegiri"
    ],
    "name:che_x_preferred":[
        "\u0421\u043d\u0435\u0433\u0438\u0440\u0438"
    ],
    "name:fra_x_preferred":[
        "Snegiri"
    ],
    "name:ita_x_preferred":[
        "Snegiri"
    ],
    "name:rus_x_preferred":[
        "\u0421\u043d\u0435\u0433\u0438\u0440\u0438"
    ],
    "name:und_x_variant":[
        "Snigiri"
    ],
    "wof:name":"Snegiri",
    "wof:placetype":"locality"
},
  "geometry": {"coordinates":[28.50163,57.23746],"type":"Point"}
}