{
  "type": "Feature",
  "properties": {
    "gn:admin1_code":"69.0",
    "gn:asciiname":"Bol'shiye Rubaniki",
    "gn:country_code":"RU",
    "gn:dem":187,
    "gn:feature_class":"P",
    "gn:feature_code":"PPL",
    "gn:name":"Bol\u2019shiye Rubaniki",
    "gn:population":0,
    "gn:timezone":"Europe/Moscow",
    "iso:country":"RU",
    "name:rus_x_preferred":[
        "\u0411\u043e\u043b\u044c\u0448\u0438\u0435 \u0420\u0443\u0431\u0430\u043d\u0438\u043a\u0438"
    ],
    "name:und_x_variant":[
        "Bol\u2019shiye Rubaniki",
        "\u0411\u043e\u043b\u044c\u0448\u0438\u0435 \u0420\u0443\u0431\u0430\u043d\u0438\u043a\u0438"
    ],
    "wof:name":"Bol'shiye Rubaniki",
    "wof:placetype":"locality"
},
  "geometry": {"coordinates":[31.84556,55.53379],"type":"Point"}
}