{
  "type": "Feature",
  "properties": {
    "gn:admin1_code":"21",
    "gn:asciiname":"Terent'yevo",
    "gn:country_code":"RU",
    "gn:dem":126,
    "gn:feature_class":"P",
    "gn:feature_code":"PPL",
    "gn:name":"Terent\u2019yevo",
    "gn:population":0,
    "gn:timezone":"Europe/Moscow",
    "iso:country":"RU",
    "name:rus_x_preferred":[
        "\u0422\u0435\u0440\u0435\u043d\u0442\u044c\u0435\u0432\u043e"
    ],
    "name:und_x_variant":[
        "Terent\u2019yeva",
        "Teren\u2019kovo",
        "Terent\u2019yevo"
    ],
    "wof:name":"Terent'yevo",
    "wof:placetype":"locality"
},
  "geometry": {"coordinates":[40.46662,56.84446],"type":"Point"}
}