{
  "type": "Feature",
  "properties": {
    "gn:admin1_code":"52",
    "gn:asciiname":"Vetno",
    "gn:country_code":"RU",
    "gn:dem":72,
    "gn:feature_class":"P",
    "gn:feature_code":"PPL",
    "gn:name":"Vetno",
    "gn:population":0,
    "gn:timezone":"Europe/Moscow",
    "iso:country":"RU",
    "name:rus_x_preferred":[
        "\u0412\u0435\u0442\u043d\u043e"
    ],
    "wof:name":"Vetno",
    "wof:placetype":"locality"
},
  "geometry": {"coordinates":[30.8953,57.0275],"type":"Point"}
}