{
  "type": "Feature",
  "properties": {
    "gn:admin1_code":"63",
    "gn:asciiname":"Namtsyr",
    "gn:country_code":"RU",
    "gn:dem":226,
    "gn:feature_class":"P",
    "gn:feature_code":"PPL",
    "gn:name":"Namtsyr",
    "gn:population":0,
    "gn:timezone":"Asia/Yakutsk",
    "iso:country":"RU",
    "name:eng_x_preferred":[
        "Namtsyr"
    ],
    "name:nor_x_preferred":[
        "Namtsyr"
    ],
    "name:rus_x_preferred":[
        "\u041d\u0430\u043c\u0446\u044b\u0440"
    ],
    "name:und_x_variant":[
        "Namsyr"
    ],
    "wof:name":"Namtsyr",
    "wof:placetype":"locality"
},
  "geometry": {"coordinates":[129.47651000000002,62.20493],"type":"Point"}
}