{
  "type": "Feature",
  "properties": {
    "gn:admin1_code":"91",
    "gn:asciiname":"Bol'shaya Ket'",
    "gn:country_code":"RU",
    "gn:dem":169,
    "gn:feature_class":"P",
    "gn:feature_code":"PPL",
    "gn:name":"Bol\u2019shaya Ket\u2019",
    "gn:population":0,
    "gn:timezone":"Asia/Krasnoyarsk",
    "iso:country":"RU",
    "name:rus_x_preferred":[
        "\u0411\u043e\u043b\u044c\u0448\u0430\u044f \u041a\u0435\u0442\u044c"
    ],
    "name:und_x_variant":[
        "Bol\u2019she-Ketskaya",
        "Bol\u2019shaya Ket\u2019"
    ],
    "wof:name":"Bol'shaya Ket'",
    "wof:placetype":"locality"
},
  "geometry": {"coordinates":[91.74917000000001,57.65139],"type":"Point"}
}