{
  "type": "Feature",
  "properties": {
    "gn:admin1_code":"53",
    "gn:asciiname":"Tsvetnopol'ye",
    "gn:country_code":"RU",
    "gn:dem":102,
    "gn:feature_class":"P",
    "gn:feature_code":"PPL",
    "gn:name":"Tsvetnopol\u2019ye",
    "gn:population":0,
    "gn:timezone":"Asia/Novosibirsk",
    "iso:country":"RU",
    "name:eng_x_preferred":[
        "Tsvetnopol'ye"
    ],
    "name:nor_x_preferred":[
        "Tsvetnopolje"
    ],
    "name:rus_x_preferred":[
        "\u0426\u0432\u0435\u0442\u043d\u043e\u043f\u043e\u043b\u044c\u0435"
    ],
    "name:und_x_variant":[
        "Tsvetnopol\u2019skiy",
        "Tsvetnopol\u2019",
        "Tsvetnopol\u2019ye"
    ],
    "wof:name":"Tsvetnopol'ye",
    "wof:placetype":"locality"
},
  "geometry": {"coordinates":[76.10795999999998,54.42712],"type":"Point"}
}