{
  "type": "Feature",
  "properties": {
    "gn:admin1_code":"47",
    "gn:asciiname":"Matyushkino-Gribanovo",
    "gn:country_code":"RU",
    "gn:dem":130,
    "gn:feature_class":"P",
    "gn:feature_code":"PPL",
    "gn:name":"Matyushkino-Gribanovo",
    "gn:population":0,
    "gn:timezone":"Europe/Moscow",
    "iso:country":"RU",
    "name:nor_x_preferred":[
        "Matjusjkino-Gribanovo"
    ],
    "name:rus_x_preferred":[
        "\u041c\u0430\u0442\u044e\u0448\u043a\u0438\u043d\u043e-\u0413\u0440\u0438\u0431\u0430\u043d\u043e\u0432\u043e"
    ],
    "name:und_x_variant":[
        "Gribanovo",
        "Matyushkino-Gribanovo"
    ],
    "wof:name":"Matyushkino-Gribanovo",
    "wof:placetype":"locality"
},
  "geometry": {"coordinates":[35.96171,56.29685],"type":"Point"}
}