{
  "type": "Feature",
  "properties": {
    "gn:admin1_code":"9",
    "gn:asciiname":"Solntsevo",
    "gn:country_code":"RU",
    "gn:dem":234,
    "gn:feature_class":"P",
    "gn:feature_code":"PPL",
    "gn:name":"Solntsevo",
    "gn:population":0,
    "gn:timezone":"Europe/Moscow",
    "iso:country":"RU",
    "name:rus_x_preferred":[
        "\u0421\u043e\u043b\u043d\u0446\u0435\u0432\u043e"
    ],
    "name:und_x_variant":[
        "\u0421\u043e\u043b\u043d\u0446\u0435\u0432\u043e"
    ],
    "wof:name":"Solntsevo",
    "wof:placetype":"locality"
},
  "geometry": {"coordinates":[37.2592,51.194],"type":"Point"}
}