{
  "type": "Feature",
  "properties": {
    "gn:admin1_code":"52",
    "gn:asciiname":"Lachino",
    "gn:cc2":"RU",
    "gn:country_code":"RU",
    "gn:dem":165,
    "gn:feature_class":"P",
    "gn:feature_code":"PPL",
    "gn:name":"Lachino",
    "gn:population":0,
    "gn:timezone":"Europe/Moscow",
    "iso:country":"RU",
    "name:rus_x_preferred":[
        "\u041b\u0430\u0447\u0438\u043d\u043e"
    ],
    "name:und_x_variant":[
        "Lachina",
        "Lachino"
    ],
    "wof:name":"Lachino",
    "wof:placetype":"locality"
},
  "geometry": {"coordinates":[34.65111,59.09444000000001],"type":"Point"}
}