{
  "type": "Feature",
  "properties": {
    "gn:admin1_code":"33.0",
    "gn:asciiname":"Vedenidovtsy",
    "gn:country_code":"RU",
    "gn:dem":142,
    "gn:feature_class":"P",
    "gn:feature_code":"PPL",
    "gn:name":"Vedenidovtsy",
    "gn:population":0,
    "gn:timezone":"Europe/Kirov",
    "iso:country":"RU",
    "name:rus_x_preferred":[
        "\u0412\u0435\u0434\u0435\u043d\u0438\u0434\u043e\u0432\u0446\u044b"
    ],
    "wof:name":"Vedenidovtsy",
    "wof:placetype":"locality"
},
  "geometry": {"coordinates":[48.29675,58.94927],"type":"Point"}
}