{
  "type": "Feature",
  "properties": {
    "gn:admin1_code":"85",
    "gn:asciiname":"Barachevo",
    "gn:country_code":"RU",
    "gn:dem":121,
    "gn:feature_class":"P",
    "gn:feature_code":"PPL",
    "gn:name":"Barachevo",
    "gn:population":0,
    "gn:timezone":"Europe/Moscow",
    "iso:country":"RU",
    "name:rus_x_preferred":[
        "\u0411\u0430\u0440\u0430\u0447\u0435\u0432\u043e"
    ],
    "wof:name":"Barachevo",
    "wof:placetype":"locality"
},
  "geometry": {"coordinates":[39.856,59.273],"type":"Point"}
}