{
  "type": "Feature",
  "properties": {
    "gn:admin1_code":"41",
    "gn:asciiname":"Maloye Lukino",
    "gn:country_code":"RU",
    "gn:dem":189,
    "gn:feature_class":"P",
    "gn:feature_code":"PPL",
    "gn:name":"Maloye Lukino",
    "gn:population":0,
    "gn:timezone":"Europe/Moscow",
    "iso:country":"RU",
    "name:rus_x_preferred":[
        "\u041c\u0430\u043b\u043e\u0435 \u041b\u0443\u043a\u0438\u043d\u043e"
    ],
    "wof:name":"Maloye Lukino",
    "wof:placetype":"locality"
},
  "geometry": {"coordinates":[35.9828,51.7786],"type":"Point"}
}