{
  "type": "Feature",
  "properties": {
    "gn:admin1_code":"61",
    "gn:asciiname":"Ulanskiy",
    "gn:country_code":"RU",
    "gn:dem":89,
    "gn:feature_class":"P",
    "gn:feature_code":"PPL",
    "gn:name":"Ulanskiy",
    "gn:population":0,
    "gn:timezone":"Europe/Moscow",
    "iso:country":"RU",
    "name:rus_x_preferred":[
        "\u0423\u043b\u0430\u043d\u0441\u043a\u0438\u0439"
    ],
    "wof:name":"Ulanskiy",
    "wof:placetype":"locality"
},
  "geometry": {"coordinates":[43.0535,46.7633],"type":"Point"}
}