{
  "type": "Feature",
  "properties": {
    "gn:admin1_code":"42",
    "gn:asciiname":"Krivoy Navolok",
    "gn:country_code":"RU",
    "gn:dem":48,
    "gn:feature_class":"P",
    "gn:feature_code":"PPL",
    "gn:name":"Krivoy Navolok",
    "gn:population":0,
    "gn:timezone":"Europe/Moscow",
    "iso:country":"RU",
    "name:rus_x_preferred":[
        "\u041a\u0440\u0438\u0432\u043e\u0439 \u041d\u0430\u0432\u043e\u043b\u043e\u043a"
    ],
    "wof:name":"Krivoy Navolok",
    "wof:placetype":"locality"
},
  "geometry": {"coordinates":[33.47058,59.82921],"type":"Point"}
}