{
  "type": "Feature",
  "properties": {
    "gn:admin1_code":"10",
    "gn:asciiname":"Poselok Imeni Vorovskogo",
    "gn:cc2":"RU",
    "gn:country_code":"RU",
    "gn:dem":152,
    "gn:feature_class":"P",
    "gn:feature_code":"PPL",
    "gn:name":"Pos\u00eblok Imeni Vorovskogo",
    "gn:population":0,
    "gn:timezone":"Europe/Moscow",
    "iso:country":"RU",
    "name:rus_x_preferred":[
        "\u041f\u043e\u0441\u0451\u043b\u043e\u043a \u0418\u043c\u0435\u043d\u0438 \u0412\u043e\u0440\u043e\u0432\u0441\u043a\u043e\u0433\u043e"
    ],
    "name:und_x_variant":[
        "Vorovskogo",
        "Pos\u00eblok Imeni Vorovskogo",
        "\u041f\u043e\u0441\u0451\u043b\u043e\u043a \u0418\u043c\u0435\u043d\u0438 \u0412\u043e\u0440\u043e\u0432\u0441\u043a\u043e\u0433\u043e"
    ],
    "wof:name":"Poselok Imeni Vorovskogo",
    "wof:placetype":"locality"
},
  "geometry": {"coordinates":[34.38778,53.28639],"type":"Point"}
}