{
  "type": "Feature",
  "properties": {
    "gn:admin1_code":"73",
    "gn:asciiname":"Tatarskiy Yeltan",
    "gn:country_code":"RU",
    "gn:dem":123,
    "gn:feature_class":"P",
    "gn:feature_code":"PPL",
    "gn:name":"Tatarskiy Yeltan",
    "gn:population":0,
    "gn:timezone":"Europe/Moscow",
    "iso:country":"RU",
    "name:eng_x_preferred":[
        "Tatarskiy Yeltan"
    ],
    "name:nor_x_preferred":[
        "Tatarskij Jeltan"
    ],
    "name:rus_x_preferred":[
        "\u0422\u0430\u0442\u0430\u0440\u0441\u043a\u0438\u0439 \u0415\u043b\u0442\u0430\u043d"
    ],
    "name:und_x_variant":[
        "Yeltan\u2019-Tatarskaya",
        "Tatarskaya Yeltan\u2019",
        "Tatarskiy Yeltan",
        "\u0422\u0430\u0442\u0430\u0440\u0441\u043a\u0438\u0439 \u0415\u043b\u0442\u0430\u043d"
    ],
    "wof:name":"Tatarskiy Yeltan",
    "wof:placetype":"locality"
},
  "geometry": {"coordinates":[50.79147,55.11826],"type":"Point"}
}