{
  "type": "Feature",
  "properties": {
    "gn:admin1_code":"85",
    "gn:asciiname":"Gur'yevo",
    "gn:country_code":"RU",
    "gn:dem":142,
    "gn:feature_class":"P",
    "gn:feature_code":"PPL",
    "gn:name":"Gur\u2019yevo",
    "gn:population":0,
    "gn:timezone":"Europe/Moscow",
    "iso:country":"RU",
    "name:rus_x_preferred":[
        "\u0413\u0443\u0440\u044c\u0435\u0432\u043e"
    ],
    "name:und_x_variant":[
        "Gur\u2019yevo",
        "\u0413\u0443\u0440\u044c\u0435\u0432\u043e"
    ],
    "wof:name":"Gur'yevo",
    "wof:placetype":"locality"
},
  "geometry": {"coordinates":[41.21667,58.86666999999999],"type":"Point"}
}