{
  "type": "Feature",
  "properties": {
    "gn:admin1_code":"6",
    "gn:asciiname":"Zabolot'ye",
    "gn:country_code":"RU",
    "gn:dem":177,
    "gn:feature_class":"P",
    "gn:feature_code":"PPL",
    "gn:name":"Zabolot\u2019ye",
    "gn:population":0,
    "gn:timezone":"Europe/Moscow",
    "iso:country":"RU",
    "name:eng_x_preferred":[
        "Zabolot'ye"
    ],
    "name:nor_x_preferred":[
        "Zabolotskij Potsjinok"
    ],
    "name:rus_x_preferred":[
        "\u0417\u0430\u0431\u043e\u043b\u043e\u0442\u0441\u043a\u0438\u0439 \u041f\u043e\u0447\u0438\u043d\u043e\u043a"
    ],
    "name:und_x_variant":[
        "Pochinok Zabolotskiy",
        "Zabolotskiy",
        "Zabolotskiy Pochinok",
        "Zabolot\u2019ye"
    ],
    "wof:name":"Zabolot'ye",
    "wof:placetype":"locality"
},
  "geometry": {"coordinates":[45.30811,61.25153],"type":"Point"}
}