{
  "type": "Feature",
  "properties": {
    "gn:admin1_code":"33",
    "gn:asciiname":"Turino",
    "gn:country_code":"RU",
    "gn:dem":134,
    "gn:feature_class":"P",
    "gn:feature_code":"PPL",
    "gn:name":"Turino",
    "gn:population":0,
    "gn:timezone":"Europe/Kirov",
    "iso:country":"RU",
    "name:rus_x_preferred":[
        "\u0422\u0443\u0440\u0438\u043d\u043e"
    ],
    "name:und_x_variant":[
        "\u0422\u0443\u0440\u0438\u043d\u043e"
    ],
    "wof:name":"Turino",
    "wof:placetype":"locality"
},
  "geometry": {"coordinates":[47.0936,60.6756],"type":"Point"}
}