{
  "type": "Feature",
  "properties": {
    "gn:admin1_code":"62.0",
    "gn:asciiname":"Frolovo",
    "gn:country_code":"RU",
    "gn:dem":97,
    "gn:feature_class":"P",
    "gn:feature_code":"PPL",
    "gn:name":"Frolovo",
    "gn:population":0,
    "gn:timezone":"Europe/Moscow",
    "iso:country":"RU",
    "name:rus_x_preferred":[
        "\u0424\u0440\u043e\u043b\u043e\u0432\u043e"
    ],
    "name:und_x_variant":[
        "\u0424\u0440\u043e\u043b\u043e\u0432\u043e"
    ],
    "wof:name":"Frolovo",
    "wof:placetype":"locality"
},
  "geometry": {"coordinates":[40.1275,53.9588],"type":"Point"}
}