{
  "type": "Feature",
  "properties": {
    "gn:admin1_code":"62.0",
    "gn:asciiname":"Frolovo",
    "gn:country_code":"RU",
    "gn:dem":97,
    "gn:feature_class":"P",
    "gn:feature_code":"PPL",
    "gn:name":"Frolovo",
    "gn:population":0,
    "gn:timezone":"Europe/Moscow",
    "iso:country":"RU",
    "name:ara_x_preferred":[
        "\u0641\u0631\u0648\u0644\u0648\u0641\u0648"
    ],
    "name:azb_x_preferred":[
        "\u0641\u0631\u0648\u0644\u0648\u0641"
    ],
    "name:bel_x_preferred":[
        "\u0424\u0440\u043e\u043b\u0430\u0432\u0430"
    ],
    "name:bul_x_preferred":[
        "\u0424\u0440\u043e\u043b\u043e\u0432\u043e"
    ],
    "name:cat_x_preferred":[
        "Fr\u00f3lovo"
    ],
    "name:ceb_x_preferred":[
        "Frolovo"
    ],
    "name:deu_x_preferred":[
        "Frolowo"
    ],
    "name:epo_x_preferred":[
        "Frolovo"
    ],
    "name:est_x_preferred":[
        "Frolovo"
    ],
    "name:fas_x_preferred":[
        "\u0641\u0631\u0648\u0644\u0648\u0641"
    ],
    "name:fin_x_preferred":[
        "Frolovo"
    ],
    "name:fra_x_preferred":[
        "Frolovo"
    ],
    "name:hsb_x_preferred":[
        "Frolowo"
    ],
    "name:ita_x_preferred":[
        "Frolovo"
    ],
    "name:nno_x_preferred":[
        "Frolovo"
    ],
    "name:nor_x_preferred":[
        "Frolovo"
    ],
    "name:pol_x_preferred":[
        "Fro\u0142owo"
    ],
    "name:rus_x_preferred":[
        "\u0424\u0440\u043e\u043b\u043e\u0432\u043e"
    ],
    "name:srp_x_preferred":[
        "\u0424\u0440\u043e\u043b\u043e\u0432\u043e"
    ],
    "name:tat_x_preferred":[
        "\u0424\u0440\u043e\u043b\u043e\u0432\u043e"
    ],
    "name:tgl_x_preferred":[
        "Frolovo"
    ],
    "name:tur_x_preferred":[
        "Frolovo"
    ],
    "name:ukr_x_preferred":[
        "\u0424\u0440\u043e\u043b\u043e\u0432\u043e"
    ],
    "name:und_x_variant":[
        "\u0424\u0440\u043e\u043b\u043e\u0432\u043e"
    ],
    "name:vep_x_preferred":[
        "Frolovo"
    ],
    "name:vie_x_preferred":[
        "Frolovo"
    ],
    "name:war_x_preferred":[
        "Frolovo"
    ],
    "name:xal_x_preferred":[
        "\u0424\u0440\u043e\u043b\u043e\u0432\u043e \u0431\u0430\u043b\u04bb\u0441\u043d"
    ],
    "name:zho_x_preferred":[
        "\u5f17\u7f85\u6d1b\u6c83"
    ],
    "wof:name":"Frolovo",
    "wof:placetype":"locality"
},
  "geometry": {"coordinates":[40.1275,53.9588],"type":"Point"}
}