{
  "type": "Feature",
  "properties": {
    "gn:admin1_code":"73",
    "gn:asciiname":"Kzyl-Kachu",
    "gn:country_code":"RU",
    "gn:dem":285,
    "gn:feature_class":"P",
    "gn:feature_code":"PPL",
    "gn:name":"Kzyl-Kachu",
    "gn:population":0,
    "gn:timezone":"Europe/Moscow",
    "iso:country":"RU",
    "name:rus_x_preferred":[
        "\u041a\u0437\u044b\u043b-\u041a\u0430\u0447\u0443"
    ],
    "name:und_x_variant":[
        "\u041a\u0437\u044b\u043b-\u041a\u0430\u0447\u0443"
    ],
    "wof:name":"Kzyl-Kachu",
    "wof:placetype":"locality"
},
  "geometry": {"coordinates":[52.6725,54.8461],"type":"Point"}
}