{
  "type": "Feature",
  "properties": {
    "gn:admin1_code":"6",
    "gn:asciiname":"Ken'gozero",
    "gn:country_code":"RU",
    "gn:dem":67,
    "gn:feature_class":"P",
    "gn:feature_code":"PPL",
    "gn:name":"Ken\u2019gozero",
    "gn:population":0,
    "gn:timezone":"Europe/Moscow",
    "iso:country":"RU",
    "name:rus_x_preferred":[
        "\u041a\u0435\u043d\u044c\u0433\u043e\u0437\u0435\u0440\u043e"
    ],
    "name:und_x_variant":[
        "Ken\u2019gozero",
        "\u041a\u0435\u043d\u044c\u0433\u043e\u0437\u0435\u0440\u043e"
    ],
    "wof:name":"Ken'gozero",
    "wof:placetype":"locality"
},
  "geometry": {"coordinates":[40.23333,63.71666999999999],"type":"Point"}
}