{
  "type": "Feature",
  "properties": {
    "gn:admin1_code":"8.0",
    "gn:asciiname":"Atnyash",
    "gn:country_code":"RU",
    "gn:dem":182,
    "gn:feature_class":"P",
    "gn:feature_code":"PPL",
    "gn:name":"Atnyash",
    "gn:population":0,
    "gn:timezone":"Asia/Yekaterinburg",
    "iso:country":"RU",
    "name:eng_x_preferred":[
        "Atnyash"
    ],
    "name:nor_x_preferred":[
        "Atnjasj"
    ],
    "name:rus_x_preferred":[
        "\u0410\u0442\u043d\u044f\u0448"
    ],
    "name:und_x_variant":[
        "\u0410\u0442\u043d\u044f\u0448",
        "Atnyash"
    ],
    "wof:name":"Atnyash",
    "wof:placetype":"locality"
},
  "geometry": {"coordinates":[57.2213,55.57358000000001],"type":"Point"}
}