{
  "type": "Feature",
  "properties": {
    "gn:admin1_code":"21",
    "gn:asciiname":"Bukharovo",
    "gn:country_code":"RU",
    "gn:dem":124,
    "gn:feature_class":"P",
    "gn:feature_code":"PPL",
    "gn:name":"Bukharovo",
    "gn:population":0,
    "gn:timezone":"Europe/Moscow",
    "iso:country":"RU",
    "name:rus_x_preferred":[
        "\u0411\u0443\u0445\u0430\u0440\u043e\u0432\u043e"
    ],
    "wof:name":"Bukharovo",
    "wof:placetype":"locality"
},
  "geometry": {"coordinates":[40.98674000000001,56.94542],"type":"Point"}
}