{
  "type": "Feature",
  "properties": {
    "gn:admin1_code":"71",
    "gn:asciiname":"Kolyasnikova",
    "gn:country_code":"RU",
    "gn:dem":105,
    "gn:feature_class":"P",
    "gn:feature_code":"PPL",
    "gn:name":"Kolyasnikova",
    "gn:population":0,
    "gn:timezone":"Asia/Yekaterinburg",
    "iso:country":"RU",
    "name:eng_x_preferred":[
        "Kolyasnikova"
    ],
    "name:nor_x_preferred":[
        "Koljasnikova"
    ],
    "name:rus_x_preferred":[
        "\u041a\u043e\u043b\u044f\u0441\u043d\u0438\u043a\u043e\u0432\u0430"
    ],
    "name:und_x_variant":[
        "Kolyasnikovo",
        "\u041a\u043e\u043b\u044f\u0441\u043d\u0438\u043a\u043e\u0432\u0430",
        "Kolyasnikova"
    ],
    "wof:name":"Kolyasnikova",
    "wof:placetype":"locality"
},
  "geometry": {"coordinates":[62.5867,56.7442],"type":"Point"}
}