{
  "type": "Feature",
  "properties": {
    "gn:admin1_code":"77",
    "gn:asciiname":"Volovo",
    "gn:country_code":"RU",
    "gn:dem":201,
    "gn:feature_class":"P",
    "gn:feature_code":"PPL",
    "gn:name":"Volovo",
    "gn:population":0,
    "gn:timezone":"Europe/Moscow",
    "iso:country":"RU",
    "name:ceb_x_preferred":[
        "\u0412\u043e\u043b\u043e\u0432\u043e"
    ],
    "name:deu_x_preferred":[
        "Wolowo"
    ],
    "name:ita_x_preferred":[
        "Volovo"
    ],
    "name:rus_x_preferred":[
        "\u0412\u043e\u043b\u043e\u0432\u043e"
    ],
    "name:ukr_x_preferred":[
        "\u0412\u043e\u043b\u043e\u0432\u043e"
    ],
    "wof:name":"Volovo",
    "wof:placetype":"locality"
},
  "geometry": {"coordinates":[33.82751,56.27349],"type":"Point"}
}