{
  "type": "Feature",
  "properties": {
    "gn:admin1_code":"61",
    "gn:asciiname":"Skelyanskiy",
    "gn:country_code":"RU",
    "gn:dem":33,
    "gn:feature_class":"P",
    "gn:feature_code":"PPL",
    "gn:name":"Skelyanskiy",
    "gn:population":0,
    "gn:timezone":"Europe/Moscow",
    "iso:country":"RU",
    "name:rus_x_preferred":[
        "\u0421\u043a\u0435\u043b\u044f\u043d\u0441\u043a\u0438\u0439"
    ],
    "wof:name":"Skelyanskiy",
    "wof:placetype":"locality"
},
  "geometry": {"coordinates":[38.91139,47.78205],"type":"Point"}
}