{
  "type": "Feature",
  "properties": {
    "gn:admin1_code":"77",
    "gn:asciiname":"Syrtsevka",
    "gn:country_code":"RU",
    "gn:dem":141,
    "gn:feature_class":"P",
    "gn:feature_code":"PPL",
    "gn:name":"Syrtsevka",
    "gn:population":0,
    "gn:timezone":"Europe/Moscow",
    "iso:country":"RU",
    "name:eng_x_preferred":[
        "Syrtsevka"
    ],
    "name:nor_x_preferred":[
        "Syrtsevka"
    ],
    "name:rus_x_preferred":[
        "\u0421\u044b\u0440\u0446\u0435\u0432\u043a\u0430"
    ],
    "wof:name":"Syrtsevka",
    "wof:placetype":"locality"
},
  "geometry": {"coordinates":[36.44361,57.67056],"type":"Point"}
}