{
  "type": "Feature",
  "properties": {
    "gn:admin1_code":"17",
    "gn:admin2_code":"549104",
    "gn:asciiname":"Khindakh",
    "gn:country_code":"RU",
    "gn:dem":971,
    "gn:feature_class":"P",
    "gn:feature_code":"PPL",
    "gn:name":"Khindakh",
    "gn:population":0,
    "gn:timezone":"Europe/Moscow",
    "iso:country":"RU",
    "name:rus_x_preferred":[
        "\u0425\u0438\u043d\u0434\u0430\u0445"
    ],
    "name:und_x_variant":[
        "\u0425\u0438\u043d\u0434\u0430\u0445"
    ],
    "wof:name":"Khindakh",
    "wof:placetype":"locality"
},
  "geometry": {"coordinates":[46.57348,42.66019],"type":"Point"}
}