{
  "type": "Feature",
  "properties": {
    "gn:admin1_code":"64",
    "gn:asciiname":"Ostrovskiy",
    "gn:cc2":"RU",
    "gn:country_code":"RU",
    "gn:dem":49,
    "gn:feature_class":"P",
    "gn:feature_code":"PPL",
    "gn:name":"Ostrovskiy",
    "gn:population":0,
    "gn:timezone":"Asia/Sakhalin",
    "iso:country":"RU",
    "name:rus_x_preferred":[
        "\u041e\u0441\u0442\u0440\u043e\u0432\u0441\u043a\u0438\u0439"
    ],
    "name:und_x_variant":[
        "Kita-moshiro",
        "Ostrovskiy",
        "\u041e\u0441\u0442\u0440\u043e\u0432\u0441\u043a\u0438\u0439"
    ],
    "wof:name":"Ostrovskiy",
    "wof:placetype":"locality"
},
  "geometry": {"coordinates":[141.83333000000005,46.48333],"type":"Point"}
}