{
  "type": "Feature",
  "properties": {
    "gn:admin1_code":"77",
    "gn:asciiname":"Soblago",
    "gn:country_code":"RU",
    "gn:dem":221,
    "gn:feature_class":"P",
    "gn:feature_code":"PPL",
    "gn:name":"Soblago",
    "gn:population":0,
    "gn:timezone":"Europe/Moscow",
    "iso:country":"RU",
    "name:rus_x_preferred":[
        "\u0421\u043e\u0431\u043b\u0430\u0433\u043e"
    ],
    "wof:name":"Soblago",
    "wof:placetype":"locality"
},
  "geometry": {"coordinates":[32.65433,56.89203000000001],"type":"Point"}
}