{
  "type": "Feature",
  "properties": {
    "gn:admin1_code":"76",
    "gn:asciiname":"Cherenkovo",
    "gn:country_code":"RU",
    "gn:dem":183,
    "gn:feature_class":"P",
    "gn:feature_code":"PPL",
    "gn:name":"Cherenkovo",
    "gn:population":0,
    "gn:timezone":"Europe/Moscow",
    "iso:country":"RU",
    "name:rus_x_preferred":[
        "\u0427\u0435\u0440\u0435\u043d\u043a\u043e\u0432\u043e"
    ],
    "name:und_x_variant":[
        "\u0427\u0435\u0440\u0435\u043d\u043a\u043e\u0432\u043e"
    ],
    "wof:name":"Cherenkovo",
    "wof:placetype":"locality"
},
  "geometry": {"coordinates":[38.37953,53.32416],"type":"Point"}
}