{
  "type": "Feature",
  "properties": {
    "gn:admin1_code":"17",
    "gn:asciiname":"Nizhnyaya Tsukhta",
    "gn:country_code":"RU",
    "gn:dem":1454,
    "gn:feature_class":"P",
    "gn:feature_code":"PPL",
    "gn:name":"Nizhnyaya Tsukhta",
    "gn:population":0,
    "gn:timezone":"Europe/Moscow",
    "iso:country":"RU",
    "name:rus_x_preferred":[
        "\u041d\u0438\u0436\u043d\u044f\u044f \u0426\u0443\u0445\u0442\u0430"
    ],
    "name:und_x_variant":[
        "\u041d\u0438\u0436\u043d\u044f\u044f \u0426\u0443\u0445\u0442\u0430"
    ],
    "wof:name":"Nizhnyaya Tsukhta",
    "wof:placetype":"locality"
},
  "geometry": {"coordinates":[47.32396,42.34352],"type":"Point"}
}