{
  "type": "Feature",
  "properties": {
    "gn:admin1_code":"90.0",
    "gn:asciiname":"Mazunina",
    "gn:country_code":"RU",
    "gn:dem":182,
    "gn:feature_class":"P",
    "gn:feature_code":"PPL",
    "gn:name":"Mazunina",
    "gn:population":0,
    "gn:timezone":"Asia/Yekaterinburg",
    "iso:country":"RU",
    "name:che_x_preferred":[
        "\u041c\u0430\u0437\u0443\u043d\u0438\u043d\u0430"
    ],
    "name:rus_x_preferred":[
        "\u041c\u0430\u0437\u0443\u043d\u0438\u043d\u0430"
    ],
    "wof:name":"Mazunina",
    "wof:placetype":"locality"
},
  "geometry": {"coordinates":[54.6434,58.7211],"type":"Point"}
}