{
  "type": "Feature",
  "properties": {
    "gn:admin1_code":"73",
    "gn:asciiname":"Krutushka",
    "gn:country_code":"RU",
    "gn:dem":72,
    "gn:feature_class":"P",
    "gn:feature_code":"PPL",
    "gn:name":"Krutushka",
    "gn:population":0,
    "gn:timezone":"Europe/Moscow",
    "iso:country":"RU",
    "name:rus_x_preferred":[
        "\u041a\u0440\u0443\u0442\u0443\u0448\u043a\u0430"
    ],
    "wof:name":"Krutushka",
    "wof:placetype":"locality"
},
  "geometry": {"coordinates":[49.20375,55.92759],"type":"Point"}
}