{
  "type": "Feature",
  "properties": {
    "gn:admin1_code":"41.0",
    "gn:asciiname":"Verkhneye Gridino",
    "gn:country_code":"RU",
    "gn:dem":223,
    "gn:feature_class":"P",
    "gn:feature_code":"PPL",
    "gn:name":"Verkhneye Gridino",
    "gn:population":0,
    "gn:timezone":"Europe/Moscow",
    "iso:country":"RU",
    "name:rus_x_preferred":[
        "\u0412\u0435\u0440\u0445\u043d\u0435\u0435 \u0413\u0440\u0438\u0434\u0438\u043d\u043e"
    ],
    "name:und_x_variant":[
        "Vyshneye Gridino",
        "Verkhneye Gridino"
    ],
    "wof:name":"Verkhneye Gridino",
    "wof:placetype":"locality"
},
  "geometry": {"coordinates":[35.64444,51.395],"type":"Point"}
}