{
  "type": "Feature",
  "properties": {
    "gn:admin1_code":"53",
    "gn:asciiname":"Zykovo",
    "gn:country_code":"RU",
    "gn:dem":108,
    "gn:feature_class":"P",
    "gn:feature_code":"PPL",
    "gn:name":"Zykovo",
    "gn:population":0,
    "gn:timezone":"Asia/Novosibirsk",
    "iso:country":"RU",
    "name:eng_x_preferred":[
        "Zykovo"
    ],
    "name:nor_x_preferred":[
        "Zykovo"
    ],
    "name:rus_x_preferred":[
        "\u0417\u044b\u043a\u043e\u0432\u043e"
    ],
    "name:und_x_variant":[
        "Zykova"
    ],
    "wof:name":"Zykovo",
    "wof:placetype":"locality"
},
  "geometry": {"coordinates":[76.93986,55.67105],"type":"Point"}
}