{
  "type": "Feature",
  "properties": {
    "gn:admin1_code":"23",
    "gn:asciiname":"Novogur'yevskoye",
    "gn:country_code":"RU",
    "gn:dem":120,
    "gn:feature_class":"P",
    "gn:feature_code":"PPL",
    "gn:name":"Novogur\u2019yevskoye",
    "gn:population":0,
    "gn:timezone":"Europe/Kaliningrad",
    "iso:country":"RU",
    "name:rus_x_preferred":[
        "\u041d\u043e\u0432\u043e\u0433\u0443\u0440\u044c\u0435\u0432\u0441\u043a\u043e\u0435"
    ],
    "name:und_x_variant":[
        "Novogur\u2019yevskoye"
    ],
    "wof:name":"Novogur'yevskoye",
    "wof:placetype":"locality"
},
  "geometry": {"coordinates":[21.98572,54.46528000000001],"type":"Point"}
}