{
  "type": "Feature",
  "properties": {
    "gn:admin1_code":"90.0",
    "gn:asciiname":"Baranovo",
    "gn:country_code":"RU",
    "gn:dem":165,
    "gn:feature_class":"P",
    "gn:feature_code":"PPL",
    "gn:name":"Baranovo",
    "gn:population":0,
    "gn:timezone":"Asia/Yekaterinburg",
    "iso:country":"RU",
    "name:nor_x_preferred":[
        "Baranovo"
    ],
    "name:rus_x_preferred":[
        "\u0411\u0430\u0440\u0430\u043d\u043e\u0432\u043e"
    ],
    "name:und_x_variant":[
        "Baranova"
    ],
    "wof:name":"Baranovo",
    "wof:placetype":"locality"
},
  "geometry": {"coordinates":[55.1126,58.5775],"type":"Point"}
}