{
  "type": "Feature",
  "properties": {
    "gn:country":"RU",
    "gn:fcode":"PPL",
    "gn:population":0,
    "iso:country":"RU",
    "name:rus_x_preferred":[
        "\u041b\u0443\u0436\u043a\u0438"
    ],
    "qs:name":"Luzhki",
    "qs:name_adm0":"Russia",
    "qs:name_adm1":"Moscow Oblast",
    "qs:photos":16,
    "qs:photos_1k":3,
    "qs:photos_9k":1,
    "qs:photos_9r":1,
    "qs:photos_all":16,
    "qs:photos_sr":1,
    "qs:placetype":"Town",
    "qs:pop_sr":"0",
    "wof:name":"Luzhki",
    "wof:placetype":"locality",
    "wof:population":0
},
  "geometry": {"coordinates":[37.55808,54.85833],"type":"Point"}
}