{
  "type": "Feature",
  "properties": {
    "gn:admin1_code":"8",
    "gn:asciiname":"Zirikly",
    "gn:country_code":"RU",
    "gn:dem":183,
    "gn:feature_class":"P",
    "gn:feature_code":"PPL",
    "gn:name":"Zirikly",
    "gn:population":0,
    "gn:timezone":"Asia/Yekaterinburg",
    "iso:country":"RU",
    "name:aze_x_preferred":[
        "Erekli"
    ],
    "name:bak_x_preferred":[
        "\u0415\u0440\u0435\u043a\u043b\u0435"
    ],
    "name:che_x_preferred":[
        "\u0417\u0438\u0440\u0438\u043a\u043b\u044b"
    ],
    "name:hye_x_preferred":[
        "\u0536\u056b\u0580\u056b\u056f\u056c\u056b"
    ],
    "name:kaz_x_preferred":[
        "\u0417\u0438\u0440\u0438\u043a\u043b\u044b"
    ],
    "name:kir_x_preferred":[
        "\u0417\u0438\u0440\u0438\u043a\u043b\u044b"
    ],
    "name:rus_x_preferred":[
        "\u0417\u0438\u0440\u0438\u043a\u043b\u044b"
    ],
    "name:tat_x_preferred":[
        "\u0417\u0438\u0440\u0435\u043a\u043b\u0435"
    ],
    "name:und_x_variant":[
        "\u0417\u0438\u0440\u0438\u043a\u043b\u044b"
    ],
    "wof:name":"Zirikly",
    "wof:placetype":"locality"
},
  "geometry": {"coordinates":[53.7028,55.3024],"type":"Point"}
}