{
  "type": "Feature",
  "properties": {
    "gn:admin1_code":"69",
    "gn:asciiname":"Khripelevo",
    "gn:country_code":"RU",
    "gn:dem":187,
    "gn:feature_class":"P",
    "gn:feature_code":"PPL",
    "gn:name":"Khripel\u00ebvo",
    "gn:population":0,
    "gn:timezone":"Europe/Moscow",
    "iso:country":"RU",
    "name:eng_x_preferred":[
        "Khripel\u00ebvo"
    ],
    "name:nor_x_preferred":[
        "Khrepilevo"
    ],
    "name:rus_x_preferred":[
        "\u0425\u0440\u0435\u043f\u0438\u043b\u0435\u0432\u043e"
    ],
    "name:rus_x_variant":[
        "\u0425\u0440\u0438\u043f\u0435\u043b\u0451\u0432\u043e"
    ],
    "name:und_x_variant":[
        "Khripel\u00ebvo",
        "\u0425\u0440\u0438\u043f\u0435\u043b\u0451\u0432\u043e"
    ],
    "wof:name":"Khripelevo",
    "wof:placetype":"locality"
},
  "geometry": {"coordinates":[32.69389,53.79111],"type":"Point"}
}