{
  "type": "Feature",
  "properties": {
    "gn:country":"RU",
    "gn:fcode":"PPL",
    "gn:pop":1042,
    "iso:country":"RU",
    "name:eng_x_preferred":[
        "Kazachka"
    ],
    "name:nor_x_preferred":[
        "Kazatsjka"
    ],
    "name:rus_x_preferred":[
        "\u041a\u0430\u0437\u0430\u0447\u043a\u0430"
    ],
    "name:unk_x_variant":[
        "\u041a\u0430\u0437\u0430\u0447\u043a\u0430"
    ],
    "qs:name":"Kazachka",
    "qs:name_adm0":"Russia",
    "qs:name_adm1":"Tula Oblast",
    "qs:photos_9r":0,
    "qs:photos_sr":0,
    "qs:placetype":"Town",
    "qs:pop_sr":"3",
    "wof:name":"Kazachka",
    "wof:placetype":"locality",
    "wof:population":1042
},
  "geometry": {"coordinates":[38.0694,53.3644],"type":"Point"}
}