{
  "type": "Feature",
  "properties": {
    "gn:admin1_code":"44",
    "gn:asciiname":"Alachevo",
    "gn:country_code":"RU",
    "gn:dem":68,
    "gn:feature_class":"P",
    "gn:feature_code":"PPL",
    "gn:name":"Alachevo",
    "gn:population":0,
    "gn:timezone":"Asia/Magadan",
    "iso:country":"RU",
    "name:nor_x_preferred":[
        "Alatsjevo"
    ],
    "name:rus_x_preferred":[
        "\u0410\u043b\u0430\u0447\u0435\u0432\u043e"
    ],
    "name:und_x_variant":[
        "Eniktukan Alachevo",
        "Eniklukan",
        "Alachevo"
    ],
    "wof:name":"Alachevo",
    "wof:placetype":"locality"
},
  "geometry": {"coordinates":[158.73333,62.15],"type":"Point"}
}