{
  "type": "Feature",
  "properties": {
    "gn:admin1_code":"70",
    "gn:asciiname":"Rodnikovskoye",
    "gn:cc2":"RU",
    "gn:country_code":"RU",
    "gn:dem":91,
    "gn:feature_class":"P",
    "gn:feature_code":"PPL",
    "gn:name":"Rodnikovskoye",
    "gn:population":0,
    "gn:timezone":"Europe/Moscow",
    "iso:country":"RU",
    "name:eng_x_preferred":[
        "Rodnikovskoye"
    ],
    "name:nor_x_preferred":[
        "Rodnikovskoje"
    ],
    "name:rus_x_preferred":[
        "\u0420\u043e\u0434\u043d\u0438\u043a\u043e\u0432\u0441\u043a\u043e\u0435"
    ],
    "name:und_x_variant":[
        "Baychara",
        "\u0420\u043e\u0434\u043d\u0438\u043a\u043e\u0432\u0441\u043a\u043e\u0435",
        "Rodnikovskoye"
    ],
    "wof:name":"Rodnikovskoye",
    "wof:placetype":"locality"
},
  "geometry": {"coordinates":[44.09528,45.43556],"type":"Point"}
}