{
  "type": "Feature",
  "properties": {
    "gn:admin1_code":"40",
    "gn:asciiname":"Gorbuneshnoye",
    "gn:cc2":"RU",
    "gn:country_code":"RU",
    "gn:dem":139,
    "gn:feature_class":"P",
    "gn:feature_code":"PPL",
    "gn:name":"Gorbuneshnoye",
    "gn:population":0,
    "gn:timezone":"Asia/Yekaterinburg",
    "iso:country":"RU",
    "name:rus_x_preferred":[
        "\u0413\u043e\u0440\u0431\u0443\u043d\u0435\u0448\u043d\u043e\u0435"
    ],
    "name:und_x_variant":[
        "Gorbunovo",
        "Gorbukovo",
        "Gorbuneshnoye",
        "\u0413\u043e\u0440\u0431\u0443\u043d\u0435\u0448\u043d\u043e\u0435"
    ],
    "wof:name":"Gorbuneshnoye",
    "wof:placetype":"locality"
},
  "geometry": {"coordinates":[68.21222,55.07361],"type":"Point"}
}