{
  "type": "Feature",
  "properties": {
    "gn:admin1_code":"20",
    "gn:asciiname":"Pulyayevskaya",
    "gn:country_code":"RU",
    "gn:dem":632,
    "gn:feature_class":"P",
    "gn:feature_code":"PPL",
    "gn:name":"Pulyayevskaya",
    "gn:population":0,
    "gn:timezone":"Asia/Irkutsk",
    "iso:country":"RU",
    "name:rus_x_preferred":[
        "\u041f\u0443\u043b\u044f\u0435\u0432\u0441\u043a\u0430\u044f"
    ],
    "wof:name":"Pulyayevskaya",
    "wof:placetype":"locality"
},
  "geometry": {"coordinates":[105.11667,54.21666999999999],"type":"Point"}
}