{
  "type": "Feature",
  "properties": {
    "gn:admin1_code":"59.0",
    "gn:asciiname":"Yuzhnaya Liflandiya",
    "gn:country_code":"RU",
    "gn:dem":91,
    "gn:feature_class":"P",
    "gn:feature_code":"PPL",
    "gn:name":"Yuzhnaya Liflandiya",
    "gn:population":0,
    "gn:timezone":"Asia/Vladivostok",
    "iso:country":"RU",
    "wof:name":"Yuzhnaya Liflandiya",
    "wof:placetype":"locality"
},
  "geometry": {"coordinates":[132.38722000000001,43.06111],"type":"Point"}
}