{
  "type": "Feature",
  "properties": {
    "gn:admin1_code":"90",
    "gn:asciiname":"Obvinsk",
    "gn:country_code":"RU",
    "gn:dem":178,
    "gn:feature_class":"P",
    "gn:feature_code":"PPL",
    "gn:name":"Obvinsk",
    "gn:population":0,
    "gn:timezone":"Asia/Yekaterinburg",
    "iso:country":"RU",
    "name:eng_x_preferred":[
        "Obvinsk"
    ],
    "name:nor_x_preferred":[
        "Obvinsk"
    ],
    "name:rus_x_preferred":[
        "\u041e\u0431\u0432\u0438\u043d\u0441\u043a"
    ],
    "name:und_x_variant":[
        "Obvinskoye",
        "Obvinsk",
        "\u041e\u0431\u0432\u0438\u043d\u0441\u043a"
    ],
    "wof:name":"Obvinsk",
    "wof:placetype":"locality"
},
  "geometry": {"coordinates":[54.85098000000001,58.49699],"type":"Point"}
}