{
  "type": "Feature",
  "properties": {
    "gn:admin1_code":"51",
    "gn:asciiname":"Poletayki",
    "gn:country_code":"RU",
    "gn:dem":129,
    "gn:feature_class":"P",
    "gn:feature_code":"PPL",
    "gn:name":"Poletayki",
    "gn:population":0,
    "gn:timezone":"Europe/Moscow",
    "iso:country":"RU",
    "name:rus_x_preferred":[
        "\u041f\u043e\u043b\u0435\u0442\u0430\u0439\u043a\u0438"
    ],
    "name:und_x_variant":[
        "Poletai",
        "Poletayki"
    ],
    "wof:name":"Poletayki",
    "wof:placetype":"locality"
},
  "geometry": {"coordinates":[46.66225,57.55183],"type":"Point"}
}