{
  "type": "Feature",
  "properties": {
    "gn:admin1_code":"31",
    "gn:asciiname":"Malyye Arbaty",
    "gn:cc2":"RU",
    "gn:country_code":"RU",
    "gn:dem":429,
    "gn:feature_class":"P",
    "gn:feature_code":"PPL",
    "gn:name":"Malyye Arbaty",
    "gn:population":0,
    "gn:timezone":"Asia/Krasnoyarsk",
    "iso:country":"RU",
    "name:eng_x_preferred":[
        "Malyye Arbaty"
    ],
    "name:nor_x_preferred":[
        "Mal.Arbaty"
    ],
    "name:rus_x_preferred":[
        "\u041c\u0430\u043b.\u0410\u0440\u0431\u0430\u0442\u044b"
    ],
    "name:rus_x_variant":[
        "\u041c\u0430\u043b\u044b\u0435 \u0410\u0440\u0431\u0430\u0442\u044b"
    ],
    "name:und_x_variant":[
        "Malyy Arbat",
        "Malyye Arbaty",
        "\u041c\u0430\u043b\u044b\u0435 \u0410\u0440\u0431\u0430\u0442\u044b"
    ],
    "wof:name":"Malyye Arbaty",
    "wof:placetype":"locality"
},
  "geometry": {"coordinates":[90.31667,52.71666999999999],"type":"Point"}
}