{
  "type": "Feature",
  "properties": {
    "gn:admin1_code":"90",
    "gn:asciiname":"Ishimovo",
    "gn:country_code":"RU",
    "gn:dem":114,
    "gn:feature_class":"P",
    "gn:feature_code":"PPL",
    "gn:name":"Ishimovo",
    "gn:population":0,
    "gn:timezone":"Asia/Yekaterinburg",
    "iso:country":"RU",
    "name:eng_x_preferred":[
        "Ishimovo"
    ],
    "name:nor_x_preferred":[
        "Isjimovo"
    ],
    "name:rus_x_preferred":[
        "\u0418\u0448\u0438\u043c\u043e\u0432\u043e"
    ],
    "wof:name":"Ishimovo",
    "wof:placetype":"locality"
},
  "geometry": {"coordinates":[55.589,57.0099],"type":"Point"}
}