{
  "type": "Feature",
  "properties": {
    "gn:admin1_code":"20.0",
    "gn:asciiname":"Kvartsit",
    "gn:country_code":"RU",
    "gn:dem":432,
    "gn:feature_class":"P",
    "gn:feature_code":"PPL",
    "gn:name":"Kvartsit",
    "gn:population":0,
    "gn:timezone":"Asia/Krasnoyarsk",
    "iso:country":"RU",
    "name:rus_x_preferred":[
        "\u041a\u0432\u0430\u0440\u0446\u0438\u0442"
    ],
    "wof:name":"Kvartsit",
    "wof:placetype":"locality"
},
  "geometry": {"coordinates":[96.8468,55.8084],"type":"Point"}
}