{
  "type": "Feature",
  "properties": {
    "gn:admin1_code":"38",
    "gn:asciiname":"Shkol'noye",
    "gn:country_code":"RU",
    "gn:dem":78,
    "gn:feature_class":"P",
    "gn:feature_code":"PPL",
    "gn:name":"Shkol\u2019noye",
    "gn:population":0,
    "gn:timezone":"Europe/Moscow",
    "iso:country":"RU",
    "name:rus_x_preferred":[
        "\u0428\u043a\u043e\u043b\u044c\u043d\u043e\u0435"
    ],
    "name:und_x_variant":[
        "Shkol\u2019nyy",
        "Shkol\u2019ny",
        "Shkol\u2019noye"
    ],
    "wof:name":"Shkol'noye",
    "wof:placetype":"locality"
},
  "geometry": {"coordinates":[39.85698,44.91458],"type":"Point"}
}