{
  "type": "Feature",
  "properties": {
    "gn:admin1_code":"67",
    "gn:asciiname":"Gvardeyevka",
    "gn:country_code":"RU",
    "gn:dem":228,
    "gn:feature_class":"P",
    "gn:feature_code":"PPL",
    "gn:name":"Gvardeyevka",
    "gn:population":0,
    "gn:timezone":"Europe/Saratov",
    "iso:country":"RU",
    "name:rus_x_preferred":[
        "\u0413\u0432\u0430\u0440\u0434\u0435\u0435\u0432\u043a\u0430"
    ],
    "name:und_x_variant":[
        "\u0413\u0432\u0430\u0440\u0434\u0435\u0435\u0432\u043a\u0430"
    ],
    "wof:name":"Gvardeyevka",
    "wof:placetype":"locality"
},
  "geometry": {"coordinates":[45.18466,51.57659],"type":"Point"}
}