{
  "type": "Feature",
  "properties": {
    "gn:admin1_code":"71",
    "gn:asciiname":"Asbest",
    "gn:country_code":"RU",
    "gn:dem":280,
    "gn:feature_class":"P",
    "gn:feature_code":"PPL",
    "gn:name":"Asbest",
    "gn:population":0,
    "gn:timezone":"Asia/Yekaterinburg",
    "iso:country":"RU",
    "name:eng_x_preferred":[
        "Asbest"
    ],
    "name:nor_x_preferred":[
        "Asbest"
    ],
    "name:rus_x_preferred":[
        "\u0410\u0441\u0431\u0435\u0441\u0442"
    ],
    "name:und_x_variant":[
        "\u0410\u0441\u0431\u0435\u0441\u0442",
        "Asbest"
    ],
    "wof:name":"Asbest",
    "wof:placetype":"locality"
},
  "geometry": {"coordinates":[60.5226,56.4746],"type":"Point"}
}