{
  "type": "Feature",
  "properties": {
    "gn:admin1_code":"9.0",
    "gn:asciiname":"Selishko",
    "gn:country_code":"RU",
    "gn:dem":127,
    "gn:feature_class":"P",
    "gn:feature_code":"PPL",
    "gn:name":"Selishko",
    "gn:population":0,
    "gn:timezone":"Europe/Moscow",
    "iso:country":"RU",
    "name:rus_x_preferred":[
        "\u0421\u0435\u043b\u0438\u0448\u043a\u043e"
    ],
    "name:und_x_variant":[
        "Selishka"
    ],
    "wof:name":"Selishko",
    "wof:placetype":"locality"
},
  "geometry": {"coordinates":[37.05723,50.63975],"type":"Point"}
}