{
  "type": "Feature",
  "properties": {
    "gn:admin1_code":"37",
    "gn:asciiname":"Pezhenga-Tokarevo",
    "gn:country_code":"RU",
    "gn:dem":175,
    "gn:feature_class":"P",
    "gn:feature_code":"PPL",
    "gn:name":"Pezhenga-Tokar\u00ebvo",
    "gn:population":0,
    "gn:timezone":"Europe/Moscow",
    "iso:country":"RU",
    "name:rus_x_preferred":[
        "\u041f\u0435\u0436\u0435\u043d\u0433\u0430-\u0422\u043e\u043a\u0430\u0440\u0451\u0432\u043e"
    ],
    "name:und_x_variant":[
        "Tokar\u00ebvo",
        "Pezhenga-Tokar\u00ebvo",
        "\u041f\u0435\u0436\u0435\u043d\u0433\u0430-\u0422\u043e\u043a\u0430\u0440\u0451\u0432\u043e"
    ],
    "wof:name":"Pezhenga-Tokarevo",
    "wof:placetype":"locality"
},
  "geometry": {"coordinates":[44.25255,59.1586],"type":"Point"}
}