{
  "type": "Feature",
  "properties": {
    "gn:admin1_code":"80.0",
    "gn:asciiname":"Bragino",
    "gn:country_code":"RU",
    "gn:dem":226,
    "gn:feature_class":"P",
    "gn:feature_code":"PPL",
    "gn:name":"Bragino",
    "gn:population":0,
    "gn:timezone":"Europe/Samara",
    "iso:country":"RU",
    "name:rus_x_preferred":[
        "\u0411\u0440\u0430\u0433\u0438\u043d\u043e"
    ],
    "name:und_x_variant":[
        "Bragin",
        "Bragino"
    ],
    "wof:name":"Bragino",
    "wof:placetype":"locality"
},
  "geometry": {"coordinates":[53.4749,58.1592],"type":"Point"}
}