{
  "type": "Feature",
  "properties": {
    "gn:admin1_code":"76",
    "gn:asciiname":"Krasavka",
    "gn:country_code":"RU",
    "gn:dem":234,
    "gn:feature_class":"P",
    "gn:feature_code":"PPL",
    "gn:name":"Krasavka",
    "gn:population":0,
    "gn:timezone":"Europe/Moscow",
    "iso:country":"RU",
    "name:rus_x_preferred":[
        "\u041a\u0440\u0430\u0441\u0430\u0432\u043a\u0430"
    ],
    "name:und_x_variant":[
        "Krasovka",
        "Krasavka",
        "\u041a\u0440\u0430\u0441\u0430\u0432\u043a\u0430"
    ],
    "wof:name":"Krasavka",
    "wof:placetype":"locality"
},
  "geometry": {"coordinates":[38.19113,53.3613],"type":"Point"}
}