{
  "type": "Feature",
  "properties": {
    "gn:admin1_code":"8",
    "gn:asciiname":"Kamyshly",
    "gn:country_code":"RU",
    "gn:dem":372,
    "gn:feature_class":"P",
    "gn:feature_code":"PPL",
    "gn:name":"Kamyshly",
    "gn:population":0,
    "gn:timezone":"Asia/Yekaterinburg",
    "iso:country":"RU",
    "name:rus_x_preferred":[
        "\u041a\u0430\u043c\u044b\u0448\u043b\u044b"
    ],
    "wof:name":"Kamyshly",
    "wof:placetype":"locality"
},
  "geometry": {"coordinates":[55.04717,53.49373000000001],"type":"Point"}
}