{
  "type": "Feature",
  "properties": {
    "gn:country":"RU",
    "gn:fcode":"PPL",
    "gn:population":0,
    "iso:country":"RU",
    "name:fin_x_preferred":[
        "Rappula"
    ],
    "name:rus_x_preferred":[
        "\u0420\u0430\u043f\u043f\u043e\u043b\u043e\u0432\u043e"
    ],
    "qs:name":"Rappolovo",
    "qs:name_adm0":"Russia",
    "qs:name_adm1":"Leningrad Oblast",
    "qs:photos":51,
    "qs:photos_1k":10,
    "qs:photos_9k":1,
    "qs:photos_9r":2,
    "qs:photos_all":51,
    "qs:photos_sr":2,
    "qs:placetype":"Town",
    "qs:pop_sr":"0",
    "wof:name":"Rappolovo",
    "wof:placetype":"locality",
    "wof:population":0
},
  "geometry": {"coordinates":[30.43696,60.16359],"type":"Point"}
}