{
  "type": "Feature",
  "properties": {
    "gn:admin1_code":"69",
    "gn:asciiname":"Gorel'kovo",
    "gn:country_code":"RU",
    "gn:dem":246,
    "gn:feature_class":"P",
    "gn:feature_code":"PPL",
    "gn:name":"Gorel\u2019kovo",
    "gn:population":0,
    "gn:timezone":"Europe/Moscow",
    "iso:country":"RU",
    "name:rus_x_preferred":[
        "\u0413\u043e\u0440\u0435\u043b\u044c\u043a\u043e\u0432\u043e"
    ],
    "name:und_x_variant":[
        "Gorel\u2019kovo",
        "\u0413\u043e\u0440\u0435\u043b\u044c\u043a\u043e\u0432\u043e"
    ],
    "wof:name":"Gorel'kovo",
    "wof:placetype":"locality"
},
  "geometry": {"coordinates":[33.94361,55.42722],"type":"Point"}
}