{
  "type": "Feature",
  "properties": {
    "gn:admin1_code":"60",
    "gn:asciiname":"Matrunkino",
    "gn:country_code":"RU",
    "gn:dem":84,
    "gn:feature_class":"P",
    "gn:feature_code":"PPL",
    "gn:name":"Matrunkino",
    "gn:population":0,
    "gn:timezone":"Europe/Moscow",
    "iso:country":"RU",
    "name:rus_x_preferred":[
        "\u041c\u0430\u0442\u0440\u0443\u043d\u043a\u0438\u043d\u043e"
    ],
    "wof:name":"Matrunkino",
    "wof:placetype":"locality"
},
  "geometry": {"coordinates":[28.72548,56.96158000000001],"type":"Point"}
}