{
  "type": "Feature",
  "properties": {
    "gn:admin1_code":"69.0",
    "gn:asciiname":"Aksenino",
    "gn:country_code":"RU",
    "gn:dem":253,
    "gn:feature_class":"P",
    "gn:feature_code":"PPL",
    "gn:name":"Aksenino",
    "gn:population":0,
    "gn:timezone":"Europe/Moscow",
    "iso:country":"RU",
    "name:nor_x_preferred":[
        "Aksenino"
    ],
    "name:rus_x_preferred":[
        "\u0410\u043a\u0441\u0435\u043d\u0438\u043d\u043e"
    ],
    "name:und_x_variant":[
        "Aksyunina"
    ],
    "wof:name":"Aksenino",
    "wof:placetype":"locality"
},
  "geometry": {"coordinates":[33.70472,55.87139000000001],"type":"Point"}
}