{
  "type": "Feature",
  "properties": {
    "gn:admin1_code":"71",
    "gn:asciiname":"Zaufa",
    "gn:country_code":"RU",
    "gn:dem":200,
    "gn:feature_class":"P",
    "gn:feature_code":"PPL",
    "gn:name":"Zaufa",
    "gn:population":0,
    "gn:timezone":"Asia/Yekaterinburg",
    "iso:country":"RU",
    "name:und_x_variant":[
        "Vyselok",
        "Zaufa"
    ],
    "wof:name":"Zaufa",
    "wof:placetype":"locality"
},
  "geometry": {"coordinates":[57.74724000000001,56.48342],"type":"Point"}
}