{
  "type": "Feature",
  "properties": {
    "gn:admin1_code":"69",
    "gn:asciiname":"Shurkovo",
    "gn:country_code":"RU",
    "gn:dem":199,
    "gn:feature_class":"P",
    "gn:feature_code":"PPL",
    "gn:name":"Shurkovo",
    "gn:population":0,
    "gn:timezone":"Europe/Moscow",
    "iso:country":"RU",
    "name:rus_x_preferred":[
        "\u0428\u0443\u0440\u043a\u043e\u0432\u043e"
    ],
    "name:und_x_variant":[
        "Shurkino",
        "Shurkovo"
    ],
    "wof:name":"Shurkovo",
    "wof:placetype":"locality"
},
  "geometry": {"coordinates":[32.8737,55.4281],"type":"Point"}
}