{
  "type": "Feature",
  "properties": {
    "gn:admin1_code":"41.0",
    "gn:asciiname":"Buklyata",
    "gn:country_code":"RU",
    "gn:dem":180,
    "gn:feature_class":"P",
    "gn:feature_code":"PPL",
    "gn:name":"Buklyata",
    "gn:population":0,
    "gn:timezone":"Europe/Moscow",
    "iso:country":"RU",
    "name:rus_x_preferred":[
        "\u0411\u0443\u043a\u043b\u044f\u0442\u0430"
    ],
    "name:und_x_variant":[
        "Buklyatov"
    ],
    "wof:name":"Buklyata",
    "wof:placetype":"locality"
},
  "geometry": {"coordinates":[36.3764,52.06101],"type":"Point"}
}