{
  "type": "Feature",
  "properties": {
    "gn:admin1_code":"56",
    "gn:asciiname":"Yamskaya",
    "gn:cc2":"RU",
    "gn:country_code":"RU",
    "gn:dem":214,
    "gn:feature_class":"P",
    "gn:feature_code":"PPL",
    "gn:name":"Yamskaya",
    "gn:population":0,
    "gn:timezone":"Europe/Moscow",
    "iso:country":"RU",
    "name:und_x_variant":[
        "Yamskaya Sloboda",
        "Yamskaya"
    ],
    "wof:name":"Yamskaya",
    "wof:placetype":"locality"
},
  "geometry": {"coordinates":[36.01667,53.46666999999999],"type":"Point"}
}