{
  "type": "Feature",
  "properties": {
    "gn:admin1_code":"40",
    "gn:asciiname":"Desyatyy Oktyabr'",
    "gn:country_code":"RU",
    "gn:dem":138,
    "gn:feature_class":"P",
    "gn:feature_code":"PPL",
    "gn:name":"Desyatyy Oktyabr\u2019",
    "gn:population":0,
    "gn:timezone":"Asia/Yekaterinburg",
    "iso:country":"RU",
    "name:eng_x_preferred":[
        "Desyatyy Oktyabr'"
    ],
    "name:nor_x_preferred":[
        "Desiatyj Oktjabr"
    ],
    "name:rus_x_preferred":[
        "\u0414\u0435\u0441\u044f\u0442\u044b\u0439 \u041e\u043a\u0442\u044f\u0431\u0440\u044c"
    ],
    "name:und_x_variant":[
        "\u0414\u0435\u0441\u044f\u0442\u044b\u0439 \u041e\u043a\u0442\u044f\u0431\u0440\u044c",
        "Desyatyy Oktyabr\u2019"
    ],
    "wof:name":"Desyatyy Oktyabr'",
    "wof:placetype":"locality"
},
  "geometry": {"coordinates":[67.11389,55.29971999999999],"type":"Point"}
}