{
  "type": "Feature",
  "properties": {
    "gn:admin1_code":"77",
    "gn:asciiname":"Petryaytsevo",
    "gn:country_code":"RU",
    "gn:dem":188,
    "gn:feature_class":"P",
    "gn:feature_code":"PPL",
    "gn:name":"Petryaytsevo",
    "gn:population":0,
    "gn:timezone":"Europe/Moscow",
    "iso:country":"RU",
    "name:rus_x_preferred":[
        "\u041f\u0435\u0442\u0440\u044f\u0439\u0446\u0435\u0432\u043e"
    ],
    "wof:name":"Petryaytsevo",
    "wof:placetype":"locality"
},
  "geometry": {"coordinates":[36.9643,57.8876],"type":"Point"}
}