{
  "type": "Feature",
  "properties": {
    "gn:admin1_code":"57",
    "gn:asciiname":"Il'mino",
    "gn:country_code":"RU",
    "gn:dem":122,
    "gn:feature_class":"P",
    "gn:feature_code":"PPL",
    "gn:name":"Il\u2019mino",
    "gn:population":0,
    "gn:timezone":"Europe/Moscow",
    "iso:country":"RU",
    "name:eng_x_preferred":[
        "Il'mino"
    ],
    "name:nor_x_preferred":[
        "Ilmino"
    ],
    "name:rus_x_preferred":[
        "\u0418\u043b\u044c\u043c\u0438\u043d\u043e"
    ],
    "name:und_x_variant":[
        "Il\u2019mino"
    ],
    "wof:name":"Il'mino",
    "wof:placetype":"locality"
},
  "geometry": {"coordinates":[45.6576,53.79088],"type":"Point"}
}