{
  "type": "Feature",
  "properties": {
    "gn:admin1_code":"69",
    "gn:asciiname":"Massoly",
    "gn:country_code":"RU",
    "gn:dem":197,
    "gn:feature_class":"P",
    "gn:feature_code":"PPL",
    "gn:name":"Massoly",
    "gn:population":0,
    "gn:timezone":"Europe/Moscow",
    "iso:country":"RU",
    "name:rus_x_preferred":[
        "\u041c\u0430\u0441\u0441\u043e\u043b\u044b"
    ],
    "name:und_x_variant":[
        "Mosaly",
        "Massoly"
    ],
    "wof:name":"Massoly",
    "wof:placetype":"locality"
},
  "geometry": {"coordinates":[33.67312,54.6084],"type":"Point"}
}