{
  "type": "Feature",
  "properties": {
    "gn:admin1_code":"47",
    "gn:asciiname":"Muzhevo",
    "gn:country_code":"RU",
    "gn:dem":138,
    "gn:feature_class":"P",
    "gn:feature_code":"PPL",
    "gn:name":"Muzhevo",
    "gn:population":0,
    "gn:timezone":"Europe/Moscow",
    "iso:country":"RU",
    "name:rus_x_preferred":[
        "\u041c\u0443\u0436\u0435\u0432\u043e"
    ],
    "name:und_x_variant":[
        "\u041c\u0443\u0436\u0435\u0432\u043e"
    ],
    "wof:name":"Muzhevo",
    "wof:placetype":"locality"
},
  "geometry": {"coordinates":[36.85,56.45],"type":"Point"}
}