{
  "type": "Feature",
  "properties": {
    "gn:admin1_code":"37.0",
    "gn:asciiname":"Novoye Kubovo",
    "gn:country_code":"RU",
    "gn:dem":147,
    "gn:feature_class":"P",
    "gn:feature_code":"PPL",
    "gn:name":"Novoye Kubovo",
    "gn:population":0,
    "gn:timezone":"Europe/Moscow",
    "iso:country":"RU",
    "wof:name":"Novoye Kubovo",
    "wof:placetype":"locality"
},
  "geometry": {"coordinates":[41.64528,58.49056],"type":"Point"}
}