{
  "type": "Feature",
  "properties": {
    "gn:admin1_code":"71",
    "gn:asciiname":"Mostovaya",
    "gn:country_code":"RU",
    "gn:dem":91,
    "gn:feature_class":"P",
    "gn:feature_code":"PPL",
    "gn:name":"Mostovaya",
    "gn:population":0,
    "gn:timezone":"Asia/Yekaterinburg",
    "iso:country":"RU",
    "name:eng_x_preferred":[
        "Mostovaya"
    ],
    "name:nor_x_preferred":[
        "Mostovaja"
    ],
    "name:rus_x_preferred":[
        "\u041c\u043e\u0441\u0442\u043e\u0432\u0430\u044f"
    ],
    "wof:name":"Mostovaya",
    "wof:placetype":"locality"
},
  "geometry": {"coordinates":[62.53713000000001,57.24619000000001],"type":"Point"}
}