{
  "type": "Feature",
  "properties": {
    "gn:admin1_code":"37",
    "gn:asciiname":"Suvorovo",
    "gn:country_code":"RU",
    "gn:dem":186,
    "gn:feature_class":"P",
    "gn:feature_code":"PPL",
    "gn:name":"Suvorovo",
    "gn:population":0,
    "gn:timezone":"Europe/Moscow",
    "iso:country":"RU",
    "name:azb_x_preferred":[
        "\u0633\u0648\u0648\u0631\u0648\u0648"
    ],
    "name:bul_x_preferred":[
        "\u0421\u0443\u0432\u043e\u0440\u043e\u0432\u043e"
    ],
    "name:ceb_x_preferred":[
        "Suvorovo"
    ],
    "name:ckb_x_preferred":[
        "\u0633\u0648\u06a4\u06c6\u0631\u06c6\u06a4\u06c6"
    ],
    "name:fas_x_preferred":[
        "\u0633\u0648\u0648\u0648\u0631\u0648\u0641\u0648"
    ],
    "name:heb_x_preferred":[
        "\u05e1\u05d5\u05d1\u05d5\u05e8\u05d5\u05d1\u05d5"
    ],
    "name:jpn_x_preferred":[
        "\u30b9\u30f4\u30a9\u30ed\u30f4\u30a9"
    ],
    "name:nor_x_preferred":[
        "Suvororo"
    ],
    "name:pol_x_preferred":[
        "Suworowo"
    ],
    "name:por_x_preferred":[
        "Suvorovo"
    ],
    "name:ron_x_preferred":[
        "Suvorovo"
    ],
    "name:rus_x_preferred":[
        "\u0421\u0443\u0432\u043e\u0440\u043e\u0432\u043e"
    ],
    "name:spa_x_preferred":[
        "Suvorovo"
    ],
    "name:srp_x_preferred":[
        "\u0421\u0443\u0432\u043e\u0440\u043e\u0432\u043e"
    ],
    "name:tur_x_preferred":[
        "Kozluca"
    ],
    "name:ukr_x_preferred":[
        "\u0421\u0443\u0432\u043e\u0440\u043e\u0432\u043e"
    ],
    "name:vie_x_preferred":[
        "Suvorovo"
    ],
    "name:war_x_preferred":[
        "Suvorovo"
    ],
    "name:zho_x_preferred":[
        "\u8607\u6c83\u7f85\u6c83"
    ],
    "wof:name":"Suvorovo",
    "wof:placetype":"locality"
},
  "geometry": {"coordinates":[41.77627,57.85621],"type":"Point"}
}