{
  "type": "Feature",
  "properties": {
    "gn:admin1_code":"55",
    "gn:asciiname":"Zorovka",
    "gn:country_code":"RU",
    "gn:dem":191,
    "gn:feature_class":"P",
    "gn:feature_code":"PPL",
    "gn:name":"Zorovka",
    "gn:population":0,
    "gn:timezone":"Asia/Yekaterinburg",
    "iso:country":"RU",
    "name:rus_x_preferred":[
        "\u0417\u043e\u0440\u043e\u0432\u043a\u0430"
    ],
    "wof:name":"Zorovka",
    "wof:placetype":"locality"
},
  "geometry": {"coordinates":[53.4715,53.7746],"type":"Point"}
}