{
  "type": "Feature",
  "properties": {
    "gn:admin1_code":"34",
    "gn:asciiname":"Anikiyevka",
    "gn:country_code":"RU",
    "gn:dem":100,
    "gn:feature_class":"P",
    "gn:feature_code":"PPL",
    "gn:name":"Anikiyevka",
    "gn:population":0,
    "gn:timezone":"Europe/Moscow",
    "iso:country":"RU",
    "name:eng_x_preferred":[
        "Anikiyevka"
    ],
    "name:nor_x_preferred":[
        "Anikijevka"
    ],
    "name:rus_x_preferred":[
        "\u0410\u043d\u0438\u043a\u0438\u0435\u0432\u043a\u0430"
    ],
    "name:und_x_variant":[
        "Anikoviskaya"
    ],
    "wof:name":"Anikiyevka",
    "wof:placetype":"locality"
},
  "geometry": {"coordinates":[52.04901,61.89363],"type":"Point"}
}