{
  "type": "Feature",
  "properties": {
    "gn:admin1_code":"53",
    "gn:asciiname":"Kuybyshevskiy",
    "gn:country_code":"RU",
    "gn:dem":109,
    "gn:feature_class":"P",
    "gn:feature_code":"PPL",
    "gn:name":"Kuybyshevskiy",
    "gn:population":0,
    "gn:timezone":"Asia/Novosibirsk",
    "iso:country":"RU",
    "name:rus_x_preferred":[
        "\u041a\u0443\u0439\u0431\u044b\u0448\u0435\u0432\u0441\u043a\u0438\u0439"
    ],
    "wof:name":"Kuybyshevskiy",
    "wof:placetype":"locality"
},
  "geometry": {"coordinates":[78.26666999999998,55.48333],"type":"Point"}
}