{
  "type": "Feature",
  "properties": {
    "gn:admin1_code":"16",
    "gn:asciiname":"Arzyunakasy",
    "gn:country_code":"RU",
    "gn:dem":148,
    "gn:feature_class":"P",
    "gn:feature_code":"PPL",
    "gn:name":"Arzyunakasy",
    "gn:population":0,
    "gn:timezone":"Europe/Moscow",
    "iso:country":"RU",
    "name:rus_x_preferred":[
        "\u0410\u0440\u0437\u044e\u043d\u0430\u043a\u0430\u0441\u044b"
    ],
    "wof:name":"Arzyunakasy",
    "wof:placetype":"locality"
},
  "geometry": {"coordinates":[47.1075,55.8722],"type":"Point"}
}