{
  "type": "Feature",
  "properties": {
    "gn:admin1_code":"60",
    "gn:asciiname":"Valoviki",
    "gn:country_code":"RU",
    "gn:dem":192,
    "gn:feature_class":"P",
    "gn:feature_code":"PPL",
    "gn:name":"Valoviki",
    "gn:population":0,
    "gn:timezone":"Europe/Moscow",
    "iso:country":"RU",
    "name:rus_x_preferred":[
        "\u0412\u0430\u043b\u043e\u0432\u0438\u043a\u0438"
    ],
    "name:und_x_variant":[
        "\u0412\u0430\u043b\u043e\u0432\u0438\u043a\u0438"
    ],
    "wof:name":"Valoviki",
    "wof:placetype":"locality"
},
  "geometry": {"coordinates":[29.8247,56.5856],"type":"Point"}
}