{
  "type": "Feature",
  "properties": {
    "gn:admin1_code":"85",
    "gn:asciiname":"Fedyuninskaya",
    "gn:country_code":"RU",
    "gn:dem":93,
    "gn:feature_class":"P",
    "gn:feature_code":"PPL",
    "gn:name":"Fedyuninskaya",
    "gn:population":0,
    "gn:timezone":"Europe/Moscow",
    "iso:country":"RU",
    "name:rus_x_preferred":[
        "\u0424\u0435\u0434\u044e\u043d\u0438\u043d\u0441\u043a\u0430\u044f"
    ],
    "wof:name":"Fedyuninskaya",
    "wof:placetype":"locality"
},
  "geometry": {"coordinates":[46.4908,60.0634],"type":"Point"}
}