{
  "type": "Feature",
  "properties": {
    "gn:admin1_code":"37",
    "gn:asciiname":"Kucherikha",
    "gn:country_code":"RU",
    "gn:dem":118,
    "gn:feature_class":"P",
    "gn:feature_code":"PPL",
    "gn:name":"Kucherikha",
    "gn:population":0,
    "gn:timezone":"Europe/Moscow",
    "iso:country":"RU",
    "name:rus_x_preferred":[
        "\u041a\u0443\u0447\u0435\u0440\u0438\u0445\u0430"
    ],
    "wof:name":"Kucherikha",
    "wof:placetype":"locality"
},
  "geometry": {"coordinates":[45.4651,58.5727],"type":"Point"}
}