{
  "type": "Feature",
  "properties": {
    "gn:admin1_code":"63",
    "gn:asciiname":"Khampaday",
    "gn:country_code":"RU",
    "gn:dem":235,
    "gn:feature_class":"P",
    "gn:feature_code":"PPL",
    "gn:name":"Khampaday",
    "gn:population":0,
    "gn:timezone":"Asia/Yakutsk",
    "iso:country":"RU",
    "name:eng_x_preferred":[
        "Khampaday"
    ],
    "name:nor_x_preferred":[
        "Khampadaj"
    ],
    "name:rus_x_preferred":[
        "\u0425\u0430\u043c\u043f\u0430\u0434\u0430\u0439"
    ],
    "name:und_x_variant":[
        "Khampaaday",
        "\u0425\u0430\u043c\u043f\u0430\u0434\u0430\u0439",
        "Khampaday"
    ],
    "wof:name":"Khampaday",
    "wof:placetype":"locality"
},
  "geometry": {"coordinates":[128.21311,61.86867],"type":"Point"}
}