{
  "type": "Feature",
  "properties": {
    "gn:admin1_code":"21",
    "gn:asciiname":"Kuligi",
    "gn:country_code":"RU",
    "gn:dem":140,
    "gn:feature_class":"P",
    "gn:feature_code":"PPL",
    "gn:name":"Kuligi",
    "gn:population":0,
    "gn:timezone":"Europe/Moscow",
    "iso:country":"RU",
    "name:rus_x_preferred":[
        "\u041a\u0443\u043b\u0438\u0433\u0438"
    ],
    "wof:name":"Kuligi",
    "wof:placetype":"locality"
},
  "geometry": {"coordinates":[40.30952,56.84388000000001],"type":"Point"}
}