{
  "type": "Feature",
  "properties": {
    "gn:country":"RU",
    "gn:fcode":"PPL",
    "gn:population":0,
    "iso:country":"RU",
    "name:rus_x_preferred":[
        "\u0421\u0435\u043b\u0438\u0445\u043e\u0432\u043e"
    ],
    "name:und_x_variant":[
        "Selekhovo"
    ],
    "qs:name":"Selikhovo",
    "qs:name_adm0":"Russia",
    "qs:name_adm1":"Tver Oblast",
    "qs:photos_9r":0,
    "qs:photos_sr":0,
    "qs:placetype":"Town",
    "qs:pop_sr":"0",
    "wof:name":"Selikhovo",
    "wof:placetype":"locality",
    "wof:population":0
},
  "geometry": {"coordinates":[32.87455,56.69066],"type":"Point"}
}