{
  "type": "Feature",
  "properties": {
    "gn:admin1_code":"91",
    "gn:asciiname":"Shapkino",
    "gn:country_code":"RU",
    "gn:dem":140,
    "gn:feature_class":"P",
    "gn:feature_code":"PPL",
    "gn:name":"Shapkino",
    "gn:population":0,
    "gn:timezone":"Asia/Krasnoyarsk",
    "iso:country":"RU",
    "name:che_x_preferred":[
        "\u0428\u0430\u043f\u043a\u0438\u043d\u043e"
    ],
    "name:eng_x_preferred":[
        "Shapkino"
    ],
    "name:hye_x_preferred":[
        "\u0547\u0561\u057a\u056f\u056b\u0576\u0578"
    ],
    "name:nor_x_preferred":[
        "Sjapkino"
    ],
    "name:rus_x_preferred":[
        "\u0428\u0430\u043f\u043a\u0438\u043d\u043e"
    ],
    "wof:name":"Shapkino",
    "wof:placetype":"locality"
},
  "geometry": {"coordinates":[93.0427,57.8945],"type":"Point"}
}