{
  "type": "Feature",
  "properties": {
    "gn:admin1_code":"42",
    "gn:asciiname":"Kharagenichi",
    "gn:country_code":"RU",
    "gn:dem":191,
    "gn:feature_class":"P",
    "gn:feature_code":"PPL",
    "gn:name":"Kharagenichi",
    "gn:population":0,
    "gn:timezone":"Europe/Moscow",
    "iso:country":"RU",
    "name:rus_x_preferred":[
        "\u0425\u0430\u0440\u0430\u0433\u0435\u043d\u0438\u0447\u0438"
    ],
    "name:und_x_variant":[
        "Ust\u2019ye",
        "Joensuu",
        "Kharagenichi",
        "\u0425\u0430\u0440\u0430\u0433\u0435\u043d\u0438\u0447\u0438"
    ],
    "wof:name":"Kharagenichi",
    "wof:placetype":"locality"
},
  "geometry": {"coordinates":[34.6539,60.2002],"type":"Point"}
}