{
  "type": "Feature",
  "properties": {
    "gn:admin1_code":"62.0",
    "gn:asciiname":"Chembar",
    "gn:country_code":"RU",
    "gn:dem":144,
    "gn:feature_class":"P",
    "gn:feature_code":"PPL",
    "gn:name":"Ch\u00ebmbar",
    "gn:population":0,
    "gn:timezone":"Europe/Moscow",
    "iso:country":"RU",
    "name:rus_x_preferred":[
        "\u0427\u00eb\u043c\u0431\u0430\u0440"
    ],
    "name:und_x_variant":[
        "Chembor",
        "Ch\u00ebmbar"
    ],
    "wof:name":"Chembar",
    "wof:placetype":"locality"
},
  "geometry": {"coordinates":[40.6168,54.1312],"type":"Point"}
}