{
  "type": "Feature",
  "properties": {
    "gn:admin1_code":"62",
    "gn:asciiname":"Pal'chinki",
    "gn:country_code":"RU",
    "gn:dem":128,
    "gn:feature_class":"P",
    "gn:feature_code":"PPL",
    "gn:name":"Pal\u2019chinki",
    "gn:population":0,
    "gn:timezone":"Europe/Moscow",
    "iso:country":"RU",
    "name:rus_x_preferred":[
        "\u041f\u0430\u043b\u044c\u0447\u0438\u043d\u043a\u0438"
    ],
    "name:und_x_variant":[
        "Pal\u2019chinki",
        "\u041f\u0430\u043b\u044c\u0447\u0438\u043d\u043a\u0438"
    ],
    "wof:name":"Pal'chinki",
    "wof:placetype":"locality"
},
  "geometry": {"coordinates":[41.25039,54.87791],"type":"Point"}
}