{
  "type": "Feature",
  "properties": {
    "gn:admin1_code":"64",
    "gn:asciiname":"Sopochnaya",
    "gn:cc2":"RU",
    "gn:country_code":"RU",
    "gn:dem":-9999,
    "gn:feature_class":"P",
    "gn:feature_code":"PPL",
    "gn:name":"Sopochnaya",
    "gn:population":0,
    "gn:timezone":"Asia/Sakhalin",
    "iso:country":"RU",
    "name:rus_x_preferred":[
        "\u0421\u043e\u043f\u043e\u0447\u043d\u0430\u044f"
    ],
    "name:und_x_variant":[
        "Moshiri",
        "Mosiri",
        "Sopochnaya"
    ],
    "wof:name":"Sopochnaya",
    "wof:placetype":"locality"
},
  "geometry": {"coordinates":[143.33333000000005,46.43333],"type":"Point"}
}