{
  "type": "Feature",
  "properties": {
    "gn:admin1_code":"52.0",
    "gn:asciiname":"Glazovo",
    "gn:country_code":"RU",
    "gn:dem":162,
    "gn:feature_class":"P",
    "gn:feature_code":"PPL",
    "gn:name":"Glazovo",
    "gn:population":0,
    "gn:timezone":"Europe/Moscow",
    "iso:country":"RU",
    "name:eng_x_preferred":[
        "Glazovo"
    ],
    "name:nor_x_preferred":[
        "Glazovo"
    ],
    "name:rus_x_preferred":[
        "\u0413\u043b\u0430\u0437\u043e\u0432\u043e"
    ],
    "wof:name":"Glazovo",
    "wof:placetype":"locality"
},
  "geometry": {"coordinates":[35.09197,58.33406],"type":"Point"}
}