{
  "type": "Feature",
  "properties": {
    "gn:admin1_code":"77",
    "gn:asciiname":"Khomutikha",
    "gn:country_code":"RU",
    "gn:dem":156,
    "gn:feature_class":"P",
    "gn:feature_code":"PPL",
    "gn:name":"Khomutikha",
    "gn:population":0,
    "gn:timezone":"Europe/Moscow",
    "iso:country":"RU",
    "name:eng_x_preferred":[
        "Khomutikha"
    ],
    "name:nor_x_preferred":[
        "Khomutikha"
    ],
    "name:rus_x_preferred":[
        "\u0425\u043e\u043c\u0443\u0442\u0438\u0445\u0430"
    ],
    "name:und_x_variant":[
        "\u0425\u043e\u043c\u0443\u0442\u0438\u0445\u0430",
        "Khomutikha"
    ],
    "wof:name":"Khomutikha",
    "wof:placetype":"locality"
},
  "geometry": {"coordinates":[35.80955,57.72111999999999],"type":"Point"}
}