{
  "type": "Feature",
  "properties": {
    "gn:admin1_code":"32",
    "gn:asciiname":"Yendra",
    "gn:country_code":"RU",
    "gn:dem":34,
    "gn:feature_class":"P",
    "gn:feature_code":"PPL",
    "gn:name":"Yendra",
    "gn:population":0,
    "gn:timezone":"Asia/Yekaterinburg",
    "iso:country":"RU",
    "name:eng_x_preferred":[
        "Yendra"
    ],
    "name:nor_x_preferred":[
        "Jendra"
    ],
    "name:rus_x_preferred":[
        "\u0415\u043d\u0434\u0440\u0430"
    ],
    "wof:name":"Yendra",
    "wof:placetype":"locality"
},
  "geometry": {"coordinates":[67.9096,60.71145],"type":"Point"}
}