{
  "type": "Feature",
  "properties": {
    "gn:admin1_code":"6",
    "gn:asciiname":"Pesochnyy",
    "gn:country_code":"RU",
    "gn:dem":72,
    "gn:feature_class":"P",
    "gn:feature_code":"PPL",
    "gn:name":"Pesochnyy",
    "gn:population":0,
    "gn:timezone":"Europe/Moscow",
    "iso:country":"RU",
    "name:rus_x_preferred":[
        "\u041f\u0435\u0441\u043e\u0447\u043d\u044b\u0439"
    ],
    "wof:name":"Pesochnyy",
    "wof:placetype":"locality"
},
  "geometry": {"coordinates":[48.3966,61.9324],"type":"Point"}
}