{
  "type": "Feature",
  "properties": {
    "gn:country":"RU",
    "gn:fcode":"PPL",
    "gn:pop":0,
    "iso:country":"RU",
    "name:rus_x_preferred":[
        "\u0427\u0435\u0442\u0440\u044f\u043a\u043e\u0432\u043e"
    ],
    "name:unk_x_variant":[
        "\u0427\u0435\u0442\u0440\u044f\u043a\u043e\u0432\u043e"
    ],
    "qs:name":"Chetryakovo",
    "qs:name_adm0":"Russia",
    "qs:name_adm1":"Kostroma Oblast",
    "qs:photos_9r":0,
    "qs:photos_sr":0,
    "qs:placetype":"Town",
    "qs:pop_sr":"0",
    "wof:name":"Chetryakovo",
    "wof:placetype":"locality",
    "wof:population":0
},
  "geometry": {"coordinates":[42.13341,59.05722],"type":"Point"}
}