{
  "type": "Feature",
  "properties": {
    "gn:admin1_code":"73",
    "gn:asciiname":"Koshkino",
    "gn:country_code":"RU",
    "gn:dem":83,
    "gn:feature_class":"P",
    "gn:feature_code":"PPL",
    "gn:name":"Koshkino",
    "gn:population":0,
    "gn:timezone":"Europe/Moscow",
    "iso:country":"RU",
    "name:eng_x_preferred":[
        "Koshkino"
    ],
    "name:nor_x_preferred":[
        "Kosjkino"
    ],
    "name:rus_x_preferred":[
        "\u041a\u043e\u0448\u043a\u0438\u043d\u043e"
    ],
    "wof:name":"Koshkino",
    "wof:placetype":"locality"
},
  "geometry": {"coordinates":[50.8046,56.3296],"type":"Point"}
}