{
  "type": "Feature",
  "properties": {
    "gn:admin1_code":"73",
    "gn:asciiname":"Novyye Karamaly",
    "gn:country_code":"RU",
    "gn:dem":196,
    "gn:feature_class":"P",
    "gn:feature_code":"PPL",
    "gn:name":"Novyye Karamaly",
    "gn:population":0,
    "gn:timezone":"Europe/Moscow",
    "iso:country":"RU",
    "name:bak_x_preferred":[
        "\u042f\u04a3\u044b \u04a0\u0430\u0440\u0430\u043c\u0430\u043b\u044b"
    ],
    "name:che_x_preferred":[
        "\u041d\u043e\u0432\u044b\u0435 \u041a\u0430\u0440\u0430\u043c\u0430\u043b\u044b"
    ],
    "name:hye_x_preferred":[
        "\u0546\u0578\u057e\u056b\u0565 \u053f\u0561\u0580\u0561\u0574\u0561\u056c\u056b"
    ],
    "name:kat_x_preferred":[
        "\u10dc\u10dd\u10d5\u10d8\u10d4-\u10d9\u10d0\u10e0\u10d0\u10db\u10d0\u10da\u10d8"
    ],
    "name:kaz_x_preferred":[
        "\u0416\u0430\u04a3\u0430 \u041a\u0430\u0440\u0430\u043c\u0430\u043b\u044b"
    ],
    "name:kir_x_preferred":[
        "\u0416\u0430\u04a3\u044b \u041a\u0430\u0440\u0430\u043c\u0430\u043b\u044b"
    ],
    "name:rus_x_preferred":[
        "\u041d\u043e\u0432\u044b\u0435 \u041a\u0430\u0440\u0430\u043c\u0430\u043b\u044b"
    ],
    "name:tat_x_preferred":[
        "\u042f\u04a3\u0430 \u041a\u0430\u0440\u0430\u043c\u0430\u043b\u044b"
    ],
    "name:ukr_x_preferred":[
        "\u041d\u043e\u0432\u0456 \u041a\u0430\u0440\u0430\u043c\u0430\u043b\u0438"
    ],
    "wof:name":"Novyye Karamaly",
    "wof:placetype":"locality"
},
  "geometry": {"coordinates":[53.5404,55.2745],"type":"Point"}
}