{
  "type": "Feature",
  "properties": {
    "gn:admin1_code":"73",
    "gn:asciiname":"Novyye Karamaly",
    "gn:country_code":"RU",
    "gn:dem":196,
    "gn:feature_class":"P",
    "gn:feature_code":"PPL",
    "gn:name":"Novyye Karamaly",
    "gn:population":0,
    "gn:timezone":"Europe/Moscow",
    "iso:country":"RU",
    "name:rus_x_preferred":[
        "\u041d\u043e\u0432\u044b\u0435 \u041a\u0430\u0440\u0430\u043c\u0430\u043b\u044b"
    ],
    "name:und_x_variant":[
        "\u041d\u043e\u0432\u044b\u0435 \u041a\u0430\u0440\u0430\u043c\u0430\u043b\u044b"
    ],
    "wof:name":"Novyye Karamaly",
    "wof:placetype":"locality"
},
  "geometry": {"coordinates":[53.5404,55.2745],"type":"Point"}
}