{
  "type": "Feature",
  "properties": {
    "gn:admin1_code":"47.0",
    "gn:asciiname":"Belaya Kolp'",
    "gn:country_code":"RU",
    "gn:dem":175,
    "gn:feature_class":"P",
    "gn:feature_code":"PPL",
    "gn:name":"Belaya Kolp\u2019",
    "gn:population":0,
    "gn:timezone":"Europe/Moscow",
    "iso:country":"RU",
    "name:eng_x_preferred":[
        "Belaya Kolp"
    ],
    "name:nor_x_preferred":[
        "Belaja Kolp"
    ],
    "name:rus_x_preferred":[
        "\u0411\u0435\u043b\u0430\u044f \u041a\u043e\u043b\u043f\u044c"
    ],
    "name:und_x_variant":[
        "\u0411\u0435\u043b\u0430\u044f \u041a\u043e\u043b\u043f\u044c",
        "Belaya Kolp\u2019"
    ],
    "wof:name":"Belaya Kolp'",
    "wof:placetype":"locality"
},
  "geometry": {"coordinates":[35.66459000000001,56.09183],"type":"Point"}
}