{
  "type": "Feature",
  "properties": {
    "gn:admin1_code":"21.0",
    "gn:asciiname":"Lokhanino",
    "gn:country_code":"RU",
    "gn:dem":125,
    "gn:feature_class":"P",
    "gn:feature_code":"PPL",
    "gn:name":"Lokhanino",
    "gn:population":0,
    "gn:timezone":"Europe/Moscow",
    "iso:country":"RU",
    "name:nor_x_preferred":[
        "Lokhanino"
    ],
    "name:rus_x_preferred":[
        "\u041b\u043e\u0445\u0430\u043d\u0438\u043d\u043e"
    ],
    "wof:name":"Lokhanino",
    "wof:placetype":"locality"
},
  "geometry": {"coordinates":[42.91386,56.63132],"type":"Point"}
}