{
  "type": "Feature",
  "properties": {
    "gn:admin1_code":"85",
    "gn:asciiname":"Larinskaya",
    "gn:country_code":"RU",
    "gn:dem":153,
    "gn:feature_class":"P",
    "gn:feature_code":"PPL",
    "gn:name":"Larinskaya",
    "gn:population":0,
    "gn:timezone":"Europe/Moscow",
    "iso:country":"RU",
    "name:rus_x_preferred":[
        "\u041b\u0430\u0440\u0438\u043d\u0441\u043a\u0430\u044f"
    ],
    "wof:name":"Larinskaya",
    "wof:placetype":"locality"
},
  "geometry": {"coordinates":[44.26763,60.37688000000001],"type":"Point"}
}