{
  "type": "Feature",
  "properties": {
    "gn:admin1_code":"38",
    "gn:asciiname":"Troitskiy",
    "gn:country_code":"RU",
    "gn:dem":377,
    "gn:feature_class":"P",
    "gn:feature_code":"PPL",
    "gn:name":"Troitskiy",
    "gn:population":0,
    "gn:timezone":"Europe/Moscow",
    "iso:country":"RU",
    "name:rus_x_preferred":[
        "\u0422\u0440\u043e\u0438\u0446\u043a\u0438\u0439"
    ],
    "wof:name":"Troitskiy",
    "wof:placetype":"locality"
},
  "geometry": {"coordinates":[41.4546,44.5288],"type":"Point"}
}