{
  "type": "Feature",
  "properties": {
    "gn:admin1_code":"8",
    "gn:asciiname":"Utyaganovo",
    "gn:country_code":"RU",
    "gn:dem":511,
    "gn:feature_class":"P",
    "gn:feature_code":"PPL",
    "gn:name":"Utyaganovo",
    "gn:population":0,
    "gn:timezone":"Asia/Yekaterinburg",
    "iso:country":"RU",
    "name:aze_x_preferred":[
        "Ut\u0259q\u0259n"
    ],
    "name:bak_x_preferred":[
        "\u04ae\u0442\u04d9\u0433\u04d9\u043d"
    ],
    "name:che_x_preferred":[
        "\u0423\u0442\u044f\u0433\u0430\u043d\u043e\u0432\u043e"
    ],
    "name:eng_x_preferred":[
        "Utyaganovo"
    ],
    "name:hye_x_preferred":[
        "\u0548\u0582\u057f\u0575\u0561\u0563\u0561\u0576\u0578\u057e\u0578"
    ],
    "name:kat_x_preferred":[
        "\u10e3\u10e2\u10d8\u10d0\u10d2\u10d0\u10dc\u10dd\u10d5\u10dd"
    ],
    "name:kaz_x_preferred":[
        "\u0423\u0442\u044f\u0433\u0430\u043d"
    ],
    "name:kir_x_preferred":[
        "\u0423\u0442\u044f\u0433\u0430\u043d"
    ],
    "name:nor_x_preferred":[
        "Utjaganovo"
    ],
    "name:rus_x_preferred":[
        "\u0423\u0442\u044f\u0433\u0430\u043d\u043e\u0432\u043e"
    ],
    "name:tat_x_preferred":[
        "\u04ae\u0442\u04d9\u0433\u04d9\u043d"
    ],
    "name:ukr_x_preferred":[
        "\u0423\u0442\u044f\u0433\u0430\u043d\u043e\u0432\u043e"
    ],
    "name:und_x_variant":[
        "Utyaganova"
    ],
    "wof:name":"Utyaganovo",
    "wof:placetype":"locality"
},
  "geometry": {"coordinates":[58.3151,53.3959],"type":"Point"}
}