{
  "type": "Feature",
  "properties": {
    "gn:admin1_code":"8",
    "gn:asciiname":"Utyaganovo",
    "gn:country_code":"RU",
    "gn:dem":511,
    "gn:feature_class":"P",
    "gn:feature_code":"PPL",
    "gn:name":"Utyaganovo",
    "gn:population":0,
    "gn:timezone":"Asia/Yekaterinburg",
    "iso:country":"RU",
    "name:eng_x_preferred":[
        "Utyaganovo"
    ],
    "name:nor_x_preferred":[
        "Utjaganovo"
    ],
    "name:rus_x_preferred":[
        "\u0423\u0442\u044f\u0433\u0430\u043d\u043e\u0432\u043e"
    ],
    "name:und_x_variant":[
        "Utyaganova",
        "Utyaganovo"
    ],
    "wof:name":"Utyaganovo",
    "wof:placetype":"locality"
},
  "geometry": {"coordinates":[58.3151,53.3959],"type":"Point"}
}