{
  "type": "Feature",
  "properties": {
    "gn:admin1_code":"83.0",
    "gn:asciiname":"Berezhki",
    "gn:country_code":"RU",
    "gn:dem":113,
    "gn:feature_class":"P",
    "gn:feature_code":"PPL",
    "gn:name":"Berezhki",
    "gn:population":0,
    "gn:timezone":"Europe/Moscow",
    "iso:country":"RU",
    "name:nor_x_preferred":[
        "Berezjki"
    ],
    "name:rus_x_preferred":[
        "\u0411\u0435\u0440\u0435\u0436\u043a\u0438"
    ],
    "name:und_x_variant":[
        "Berezhni",
        "Berezhki"
    ],
    "wof:name":"Berezhki",
    "wof:placetype":"locality"
},
  "geometry": {"coordinates":[40.85486,55.91598000000001],"type":"Point"}
}