{
  "type": "Feature",
  "properties": {
    "gn:admin1_code":"24",
    "gn:asciiname":"Greydernoye",
    "gn:cc2":"RU",
    "gn:country_code":"RU",
    "gn:dem":-1,
    "gn:feature_class":"P",
    "gn:feature_code":"PPL",
    "gn:name":"Greydernoye",
    "gn:population":0,
    "gn:timezone":"Europe/Moscow",
    "iso:country":"RU",
    "name:rus_x_preferred":[
        "\u0413\u0440\u0435\u0439\u0434\u0435\u0440\u043d\u043e\u0435"
    ],
    "name:und_x_variant":[
        "Omn-Keryul\u2019chi",
        "Greydernoye",
        "\u0413\u0440\u0435\u0439\u0434\u0435\u0440\u043d\u043e\u0435"
    ],
    "wof:name":"Greydernoye",
    "wof:placetype":"locality"
},
  "geometry": {"coordinates":[45.0125,46.88972],"type":"Point"}
}