{
  "type": "Feature",
  "properties": {
    "gn:admin1_code":"8",
    "gn:asciiname":"Ulu-Yelan'",
    "gn:country_code":"RU",
    "gn:dem":142,
    "gn:feature_class":"P",
    "gn:feature_code":"PPL",
    "gn:name":"Ulu-Yelan\u2019",
    "gn:population":0,
    "gn:timezone":"Asia/Yekaterinburg",
    "iso:country":"RU",
    "name:rus_x_preferred":[
        "\u0423\u043b\u0443-\u0415\u043b\u0430\u043d\u044c"
    ],
    "name:und_x_variant":[
        "Ulu-Yelan\u2019"
    ],
    "wof:name":"Ulu-Yelan'",
    "wof:placetype":"locality"
},
  "geometry": {"coordinates":[57.0593,54.7409],"type":"Point"}
}