{
  "type": "Feature",
  "properties": {
    "gn:admin1_code":"30",
    "gn:asciiname":"Alanap",
    "gn:country_code":"RU",
    "gn:dem":359,
    "gn:feature_class":"P",
    "gn:feature_code":"PPL",
    "gn:name":"Alanap",
    "gn:population":0,
    "gn:timezone":"Asia/Vladivostok",
    "iso:country":"RU",
    "name:eng_x_preferred":[
        "Alanap"
    ],
    "name:rus_x_preferred":[
        "\u0410\u043b\u0430\u043d\u0430\u0439"
    ],
    "name:rus_x_variant":[
        "\u0410\u043b\u0430\u043d\u0430\u043f"
    ],
    "name:und_x_variant":[
        "Karavanova",
        "Alakaya",
        "Alanap"
    ],
    "wof:name":"Alanap",
    "wof:placetype":"locality"
},
  "geometry": {"coordinates":[132.0598,50.05077],"type":"Point"}
}