{
  "type": "Feature",
  "properties": {
    "gn:admin1_code":"86.0",
    "gn:asciiname":"Burlyayevka",
    "gn:country_code":"RU",
    "gn:dem":116,
    "gn:feature_class":"P",
    "gn:feature_code":"PPL",
    "gn:name":"Burlyayevka",
    "gn:population":0,
    "gn:timezone":"Europe/Moscow",
    "iso:country":"RU",
    "name:rus_x_preferred":[
        "\u0411\u0443\u0440\u043b\u044f\u0435\u0432\u043a\u0430"
    ],
    "name:und_x_variant":[
        "Burlyaevka",
        "Burlyayevka",
        "\u0411\u0443\u0440\u043b\u044f\u0435\u0432\u043a\u0430"
    ],
    "wof:name":"Burlyayevka",
    "wof:placetype":"locality"
},
  "geometry": {"coordinates":[41.3366,50.9962],"type":"Point"}
}