{
  "type": "Feature",
  "properties": {
    "gn:admin1_code":"76",
    "gn:asciiname":"Kartashevo",
    "gn:country_code":"RU",
    "gn:dem":125,
    "gn:feature_class":"P",
    "gn:feature_code":"PPL",
    "gn:name":"Kartash\u00ebvo",
    "gn:population":0,
    "gn:timezone":"Europe/Moscow",
    "iso:country":"RU",
    "name:rus_x_preferred":[
        "\u041a\u0430\u0440\u0442\u0430\u0448\u0451\u0432\u043e"
    ],
    "name:und_x_variant":[
        "Kartash\u00ebvo"
    ],
    "wof:name":"Kartashevo",
    "wof:placetype":"locality"
},
  "geometry": {"coordinates":[37.19708,54.55799],"type":"Point"}
}