{
  "type": "Feature",
  "properties": {
    "gn:admin1_code":"8",
    "gn:asciiname":"Korneyevka",
    "gn:country_code":"RU",
    "gn:dem":202,
    "gn:feature_class":"P",
    "gn:feature_code":"PPL",
    "gn:name":"Korneyevka",
    "gn:population":0,
    "gn:timezone":"Asia/Yekaterinburg",
    "iso:country":"RU",
    "name:rus_x_preferred":[
        "\u041a\u043e\u0440\u043d\u0435\u0435\u0432\u043a\u0430"
    ],
    "wof:name":"Korneyevka",
    "wof:placetype":"locality"
},
  "geometry": {"coordinates":[55.48555,53.46702],"type":"Point"}
}