{
  "type": "Feature",
  "properties": {
    "gn:admin1_code":"81",
    "gn:asciiname":"Rebrovka",
    "gn:country_code":"RU",
    "gn:dem":241,
    "gn:feature_class":"P",
    "gn:feature_code":"PPL",
    "gn:name":"Rebrovka",
    "gn:population":0,
    "gn:timezone":"Europe/Ulyanovsk",
    "iso:country":"RU",
    "name:rus_x_preferred":[
        "\u0420\u0435\u0431\u0440\u043e\u0432\u043a\u0430"
    ],
    "name:und_x_variant":[
        "\u0420\u0435\u0431\u0440\u043e\u0432\u043a\u0430"
    ],
    "wof:name":"Rebrovka",
    "wof:placetype":"locality"
},
  "geometry": {"coordinates":[46.8094,53.9859],"type":"Point"}
}