{
  "type": "Feature",
  "properties": {
    "gn:admin1_code":"60",
    "gn:asciiname":"Lyady",
    "gn:cc2":"RU",
    "gn:country_code":"RU",
    "gn:dem":107,
    "gn:feature_class":"P",
    "gn:feature_code":"PPL",
    "gn:name":"Lyady",
    "gn:population":0,
    "gn:timezone":"Europe/Moscow",
    "iso:country":"RU",
    "name:bel_x_preferred":[
        "\u041b\u044f\u0434\u044b"
    ],
    "name:hye_x_preferred":[
        "\u053c\u0575\u0561\u0564\u056b"
    ],
    "name:rus_x_preferred":[
        "\u041b\u044f\u0434\u044b"
    ],
    "name:ukr_x_preferred":[
        "\u041b\u044f\u0434\u0438"
    ],
    "name:und_x_variant":[
        "Bol\u2019shiye Lyady",
        "Lyady"
    ],
    "wof:name":"Lyady",
    "wof:placetype":"locality"
},
  "geometry": {"coordinates":[29.91667,57.01667],"type":"Point"}
}