{
  "type": "Feature",
  "properties": {
    "gn:admin1_code":"46",
    "gn:asciiname":"Novochadovo",
    "gn:country_code":"RU",
    "gn:dem":155,
    "gn:feature_class":"P",
    "gn:feature_code":"PPL",
    "gn:name":"Novochadovo",
    "gn:population":0,
    "gn:timezone":"Europe/Moscow",
    "iso:country":"RU",
    "name:nor_x_preferred":[
        "Novotsjadovo"
    ],
    "name:rus_x_preferred":[
        "\u041d\u043e\u0432\u043e\u0447\u0430\u0434\u043e\u0432\u043e"
    ],
    "wof:name":"Novochadovo",
    "wof:placetype":"locality"
},
  "geometry": {"coordinates":[43.3297,54.39966999999999],"type":"Point"}
}