{
  "type": "Feature",
  "properties": {
    "gn:admin1_code":"69.0",
    "gn:asciiname":"Batyushkovo",
    "gn:country_code":"RU",
    "gn:dem":187,
    "gn:feature_class":"P",
    "gn:feature_code":"PPL",
    "gn:name":"Batyushkovo",
    "gn:population":0,
    "gn:timezone":"Europe/Moscow",
    "iso:country":"RU",
    "name:nor_x_preferred":[
        "Batjusjkovo"
    ],
    "name:rus_x_preferred":[
        "\u0411\u0430\u0442\u044e\u0448\u043a\u043e\u0432\u043e"
    ],
    "name:und_x_variant":[
        "Batyushkova",
        "Batyushkovo"
    ],
    "wof:name":"Batyushkovo",
    "wof:placetype":"locality"
},
  "geometry": {"coordinates":[35.01,55.19667],"type":"Point"}
}