{
  "type": "Feature",
  "properties": {
    "gn:admin1_code":"90.0",
    "gn:asciiname":"Bystraya",
    "gn:country_code":"RU",
    "gn:dem":114,
    "gn:feature_class":"P",
    "gn:feature_code":"PPL",
    "gn:name":"Bystraya",
    "gn:population":0,
    "gn:timezone":"Asia/Yekaterinburg",
    "iso:country":"RU",
    "name:eng_x_preferred":[
        "Bystraya"
    ],
    "name:nor_x_preferred":[
        "Bystraja"
    ],
    "name:rus_x_preferred":[
        "\u0411\u044b\u0441\u0442\u0440\u0430\u044f"
    ],
    "wof:name":"Bystraya",
    "wof:placetype":"locality"
},
  "geometry": {"coordinates":[56.2452,59.25899999999999],"type":"Point"}
}