{
  "type": "Feature",
  "properties": {
    "gn:admin1_code":"53",
    "gn:asciiname":"Pokrovo-Donskoy",
    "gn:cc2":"RU",
    "gn:country_code":"RU",
    "gn:dem":148,
    "gn:feature_class":"P",
    "gn:feature_code":"PPL",
    "gn:name":"Pokrovo-Donskoy",
    "gn:population":0,
    "gn:timezone":"Asia/Novosibirsk",
    "iso:country":"RU",
    "name:rus_x_preferred":[
        "\u041f\u043e\u043a\u0440\u043e\u0432\u043e-\u0414\u043e\u043d\u0441\u043a\u043e\u0439"
    ],
    "name:und_x_variant":[
        "Pokrovkso-Donskoy",
        "Pokrovo-Donskoy"
    ],
    "wof:name":"Pokrovo-Donskoy",
    "wof:placetype":"locality"
},
  "geometry": {"coordinates":[79.91667,55.16667],"type":"Point"}
}