{
  "type": "Feature",
  "properties": {
    "gn:admin1_code":"47",
    "gn:asciiname":"Bogaikha",
    "gn:country_code":"RU",
    "gn:dem":251,
    "gn:feature_class":"P",
    "gn:feature_code":"PPL",
    "gn:name":"Bogaikha",
    "gn:population":0,
    "gn:timezone":"Europe/Moscow",
    "iso:country":"RU",
    "name:rus_x_preferred":[
        "\u0411\u043e\u0433\u0430\u0438\u0445\u0430"
    ],
    "wof:name":"Bogaikha",
    "wof:placetype":"locality"
},
  "geometry": {"coordinates":[36.4481,56.2208],"type":"Point"}
}