{
  "type": "Feature",
  "properties": {
    "gn:admin1_code":"51.0",
    "gn:asciiname":"Nikitkino",
    "gn:country_code":"RU",
    "gn:dem":85,
    "gn:feature_class":"P",
    "gn:feature_code":"PPL",
    "gn:name":"Nikitkino",
    "gn:population":0,
    "gn:timezone":"Europe/Moscow",
    "iso:country":"RU",
    "name:nor_x_preferred":[
        "Nikitkino"
    ],
    "name:rus_x_preferred":[
        "\u041d\u0438\u043a\u0438\u0442\u043a\u0438\u043d\u043e"
    ],
    "wof:name":"Nikitkino",
    "wof:placetype":"locality"
},
  "geometry": {"coordinates":[43.16864,56.7457],"type":"Point"}
}