{
  "type": "Feature",
  "properties": {
    "gn:admin1_code":"9",
    "gn:asciiname":"Spodaryushino",
    "gn:country_code":"RU",
    "gn:dem":133,
    "gn:feature_class":"P",
    "gn:feature_code":"PPL",
    "gn:name":"Spodaryushino",
    "gn:population":0,
    "gn:timezone":"Europe/Moscow",
    "iso:country":"RU",
    "name:rus_x_preferred":[
        "\u0421\u043f\u043e\u0434\u0430\u0440\u044e\u0448\u0438\u043d\u043e"
    ],
    "wof:name":"Spodaryushino",
    "wof:placetype":"locality"
},
  "geometry": {"coordinates":[35.4899,50.5051],"type":"Point"}
}