{
  "type": "Feature",
  "properties": {
    "gn:admin1_code":"61",
    "gn:asciiname":"Shchepkin",
    "gn:country_code":"RU",
    "gn:dem":44,
    "gn:feature_class":"P",
    "gn:feature_code":"PPL",
    "gn:name":"Shchepkin",
    "gn:population":0,
    "gn:timezone":"Europe/Moscow",
    "iso:country":"RU",
    "name:rus_x_preferred":[
        "\u0429\u0435\u043f\u043a\u0438\u043d"
    ],
    "wof:name":"Shchepkin",
    "wof:placetype":"locality"
},
  "geometry": {"coordinates":[38.91667,47.61667],"type":"Point"}
}