{
  "type": "Feature",
  "properties": {
    "gn:admin1_code":"53",
    "gn:asciiname":"Stepnogutovo",
    "gn:country_code":"RU",
    "gn:dem":180,
    "gn:feature_class":"P",
    "gn:feature_code":"PPL",
    "gn:name":"Stepnogutovo",
    "gn:population":0,
    "gn:timezone":"Asia/Novosibirsk",
    "iso:country":"RU",
    "name:eng_x_preferred":[
        "Stepno-Gutovo"
    ],
    "name:nor_x_preferred":[
        "Stepnogutovo"
    ],
    "name:rus_x_preferred":[
        "\u0421\u0442\u0435\u043f\u043d\u043e\u0433\u0443\u0442\u043e\u0432\u043e"
    ],
    "name:und_x_variant":[
        "Gutova",
        "Stepnoye Gutovo"
    ],
    "wof:name":"Stepnogutovo",
    "wof:placetype":"locality"
},
  "geometry": {"coordinates":[84.96556,54.84861],"type":"Point"}
}