{
  "type": "Feature",
  "properties": {
    "gn:admin1_code":"71",
    "gn:asciiname":"Leninskiy",
    "gn:country_code":"RU",
    "gn:dem":175,
    "gn:feature_class":"P",
    "gn:feature_code":"PPL",
    "gn:name":"Leninskiy",
    "gn:population":0,
    "gn:timezone":"Asia/Yekaterinburg",
    "iso:country":"RU",
    "name:rus_x_preferred":[
        "\u041b\u0435\u043d\u0438\u043d\u0441\u043a\u0438\u0439"
    ],
    "wof:name":"Leninskiy",
    "wof:placetype":"locality"
},
  "geometry": {"coordinates":[61.8445,56.4343],"type":"Point"}
}