{
  "type": "Feature",
  "properties": {
    "gn:admin1_code":"88",
    "gn:asciiname":"Pachebolka",
    "gn:country_code":"RU",
    "gn:dem":103,
    "gn:feature_class":"P",
    "gn:feature_code":"PPL",
    "gn:name":"Pachebolka",
    "gn:population":0,
    "gn:timezone":"Europe/Moscow",
    "iso:country":"RU",
    "name:eng_x_preferred":[
        "Pachebolka"
    ],
    "name:nor_x_preferred":[
        "Patsjebolka"
    ],
    "name:rus_x_preferred":[
        "\u041f\u0430\u0447\u0435\u0431\u043e\u043b\u043a\u0430"
    ],
    "wof:name":"Pachebolka",
    "wof:placetype":"locality"
},
  "geometry": {"coordinates":[39.0106,58.33776],"type":"Point"}
}