{
  "type": "Feature",
  "properties": {
    "gn:admin1_code":"30",
    "gn:asciiname":"Vol",
    "gn:country_code":"RU",
    "gn:dem":54,
    "gn:feature_class":"P",
    "gn:feature_code":"PPL",
    "gn:name":"Vol",
    "gn:population":0,
    "gn:timezone":"Asia/Vladivostok",
    "iso:country":"RU",
    "name:ces_x_preferred":[
        "Vol"
    ],
    "name:deu_x_preferred":[
        "Vol"
    ],
    "name:fra_x_preferred":[
        "Vol"
    ],
    "name:hat_x_preferred":[
        "V\u00f2l"
    ],
    "name:jpn_x_preferred":[
        "Vol"
    ],
    "name:srp_x_preferred":[
        "\u0412\u043e\u043b"
    ],
    "wof:name":"Vol",
    "wof:placetype":"locality"
},
  "geometry": {"coordinates":[133.75,48.75],"type":"Point"}
}