{
  "type": "Feature",
  "properties": {
    "gn:admin1_code":"84",
    "gn:asciiname":"Podchinnyy",
    "gn:country_code":"RU",
    "gn:dem":192,
    "gn:feature_class":"P",
    "gn:feature_code":"PPL",
    "gn:name":"Podchinnyy",
    "gn:population":0,
    "gn:timezone":"Europe/Volgograd",
    "iso:country":"RU",
    "name:eng_x_preferred":[
        "Podchinnyy"
    ],
    "name:nor_x_preferred":[
        "Podtsjinnyj"
    ],
    "name:rus_x_preferred":[
        "\u041f\u043e\u0434\u0447\u0438\u043d\u043d\u044b\u0439"
    ],
    "name:und_x_variant":[
        "Krattske",
        "Podchinennyy",
        "Kratske",
        "\u041f\u043e\u0434\u0447\u0438\u043d\u043d\u044b\u0439",
        "Podchinnyy"
    ],
    "wof:name":"Podchinnyy",
    "wof:placetype":"locality"
},
  "geometry": {"coordinates":[45.22273,50.87823],"type":"Point"}
}