{
  "type": "Feature",
  "properties": {
    "gn:admin1_code":"42",
    "gn:asciiname":"Kondushi-Kraskova",
    "gn:cc2":"RU",
    "gn:country_code":"RU",
    "gn:dem":90,
    "gn:feature_class":"P",
    "gn:feature_code":"PPL",
    "gn:name":"Kondushi-Kraskova",
    "gn:population":0,
    "gn:timezone":"Europe/Moscow",
    "iso:country":"RU",
    "name:rus_x_preferred":[
        "\u041a\u043e\u043d\u0434\u0443\u0448\u0438-\u041a\u0440\u0430\u0441\u043a\u043e\u0432\u0430"
    ],
    "name:und_x_variant":[
        "Kraskova",
        "Kondushi-Kraskova"
    ],
    "wof:name":"Kondushi-Kraskova",
    "wof:placetype":"locality"
},
  "geometry": {"coordinates":[33.41667,60.85],"type":"Point"}
}