{
  "type": "Feature",
  "properties": {
    "gn:admin1_code":"6.0",
    "gn:asciiname":"Yelsozero",
    "gn:country_code":"RU",
    "gn:dem":84,
    "gn:feature_class":"P",
    "gn:feature_code":"PPL",
    "gn:name":"Yelsozero",
    "gn:population":0,
    "gn:timezone":"Europe/Moscow",
    "iso:country":"RU",
    "name:eng_x_preferred":[
        "Yelsozero"
    ],
    "name:nor_x_preferred":[
        "Jelsozero"
    ],
    "name:rus_x_preferred":[
        "\u0415\u043b\u0441\u043e\u0437\u0435\u0440\u043e"
    ],
    "wof:name":"Yelsozero",
    "wof:placetype":"locality"
},
  "geometry": {"coordinates":[41.6508,62.5875],"type":"Point"}
}