{
  "type": "Feature",
  "properties": {
    "gn:admin1_code":"30.0",
    "gn:asciiname":"Barkhatnyy",
    "gn:country_code":"RU",
    "gn:dem":89,
    "gn:feature_class":"P",
    "gn:feature_code":"PPL",
    "gn:name":"Barkhatnyy",
    "gn:population":0,
    "gn:timezone":"Asia/Vladivostok",
    "iso:country":"RU",
    "name:rus_x_preferred":[
        "\u0411\u0430\u0440\u0445\u0430\u0442\u043d\u044b\u0439"
    ],
    "wof:name":"Barkhatnyy",
    "wof:placetype":"locality"
},
  "geometry": {"coordinates":[134.26648,46.85306],"type":"Point"}
}