{
  "type": "Feature",
  "properties": {
    "gn:country":"RU",
    "gn:fcode":"PPL",
    "gn:pop":7835,
    "iso:country":"RU",
    "name:ara_x_preferred":[
        "\u0628\u0648\u0644\u064a\u0633\u0643"
    ],
    "name:azb_x_preferred":[
        "\u067e\u0648\u0644\u0633\u06a9"
    ],
    "name:aze_x_preferred":[
        "Polessk"
    ],
    "name:bel_x_preferred":[
        "\u041f\u0430\u043b\u0435\u0441\u043a"
    ],
    "name:ceb_x_preferred":[
        "Polessk"
    ],
    "name:ces_x_preferred":[
        "Polessk"
    ],
    "name:che_x_preferred":[
        "\u041f\u043e\u043b\u0435\u0441\u0441\u043a"
    ],
    "name:chv_x_preferred":[
        "\u041f\u043e\u043b\u0435\u0441\u0441\u043a"
    ],
    "name:deu_x_preferred":[
        "Polessk"
    ],
    "name:eng_x_preferred":[
        "Polessk"
    ],
    "name:epo_x_preferred":[
        "Polessk"
    ],
    "name:est_x_preferred":[
        "Polessk"
    ],
    "name:fas_x_preferred":[
        "\u067e\u0648\u0644\u0633\u06a9"
    ],
    "name:fin_x_preferred":[
        "Polessk"
    ],
    "name:fra_x_preferred":[
        "Polessk"
    ],
    "name:hsb_x_preferred":[
        "Polessk"
    ],
    "name:hye_x_preferred":[
        "\u054a\u0578\u056c\u0565\u057d\u056f"
    ],
    "name:ita_x_preferred":[
        "Polessk"
    ],
    "name:jpn_x_preferred":[
        "\u30dd\u30ec\u30c3\u30b9\u30af"
    ],
    "name:kor_x_preferred":[
        "\ud3f4\ub808\uc2a4\ud06c"
    ],
    "name:lav_x_preferred":[
        "Po\u013ceska"
    ],
    "name:lit_x_historical":[
        "Labguva"
    ],
    "name:lit_x_preferred":[
        "Poleskas"
    ],
    "name:lit_x_variant":[
        "Labguva"
    ],
    "name:nld_x_preferred":[
        "Polessk"
    ],
    "name:nno_x_preferred":[
        "Polessk"
    ],
    "name:nob_x_preferred":[
        "Polessk"
    ],
    "name:nor_x_preferred":[
        "Polessk"
    ],
    "name:pol_x_preferred":[
        "Polessk"
    ],
    "name:ron_x_preferred":[
        "Polessk"
    ],
    "name:rus_x_preferred":[
        "\u041f\u043e\u043b\u0435\u0441\u0441\u043a"
    ],
    "name:slv_x_preferred":[
        "Polessk"
    ],
    "name:srp_x_preferred":[
        "\u041f\u043e\u0459\u0435\u0441\u043a"
    ],
    "name:swe_x_preferred":[
        "Polessk"
    ],
    "name:tat_x_preferred":[
        "\u041f\u043e\u043b\u0435\u0441\u0441\u043a"
    ],
    "name:tgl_x_preferred":[
        "Polessk"
    ],
    "name:ukr_x_preferred":[
        "\u041f\u043e\u043b\u0454\u0441\u044c\u043a"
    ],
    "name:unk_x_variant":[
        "Labiau"
    ],
    "name:vep_x_preferred":[
        "Polessk"
    ],
    "name:war_x_preferred":[
        "Polessk"
    ],
    "name:zho_x_preferred":[
        "\u6ce2\u5217\u65af\u514b"
    ],
    "qs:name":"Polessk",
    "qs:name_adm0":"Russia",
    "qs:name_adm1":"Kaliningrad Oblast",
    "qs:photos_9k":1,
    "qs:photos_9r":1,
    "qs:photos_all":3,
    "qs:photos_sr":0,
    "qs:placetype":"Town",
    "qs:pop_sr":"5",
    "wd:wordcount":871,
    "wof:name":"Polessk",
    "wof:placetype":"locality",
    "wof:population":7835
},
  "geometry": {"coordinates":[21.10279,54.86205],"type":"Point"}
}