{
  "type": "Feature",
  "properties": {
    "gn:admin1_code":"54",
    "gn:asciiname":"Karbainovo",
    "gn:country_code":"RU",
    "gn:dem":94,
    "gn:feature_class":"P",
    "gn:feature_code":"PPL",
    "gn:name":"Karbainovo",
    "gn:population":0,
    "gn:timezone":"Asia/Omsk",
    "iso:country":"RU",
    "name:eng_x_preferred":[
        "Karbainovo"
    ],
    "name:nor_x_preferred":[
        "Karbainovo"
    ],
    "name:rus_x_preferred":[
        "\u041a\u0430\u0440\u0431\u0430\u0438\u043d\u043e\u0432\u043e"
    ],
    "name:und_x_variant":[
        "Karbanova",
        "\u041a\u0430\u0440\u0431\u0430\u0438\u043d\u043e\u0432\u043e",
        "Karbainovo"
    ],
    "wof:name":"Karbainovo",
    "wof:placetype":"locality"
},
  "geometry": {"coordinates":[72.73921999999997,56.18975],"type":"Point"}
}