{
  "type": "Feature",
  "properties": {
    "gn:admin1_code":"53",
    "gn:asciiname":"Abushkan",
    "gn:country_code":"RU",
    "gn:dem":107,
    "gn:feature_class":"P",
    "gn:feature_code":"PPL",
    "gn:name":"Abushkan",
    "gn:population":0,
    "gn:timezone":"Asia/Novosibirsk",
    "iso:country":"RU",
    "name:nor_x_preferred":[
        "Abusjkan"
    ],
    "name:rus_x_preferred":[
        "\u0410\u0431\u0443\u0448\u043a\u0430\u043d"
    ],
    "name:und_x_variant":[
        "Abushkah",
        "Abyshkan",
        "Abushkan"
    ],
    "wof:name":"Abushkan",
    "wof:placetype":"locality"
},
  "geometry": {"coordinates":[76.16592,54.72181],"type":"Point"}
}