{
  "type": "Feature",
  "properties": {
    "gn:admin1_code":"60",
    "gn:asciiname":"Pukhtevo",
    "gn:country_code":"RU",
    "gn:dem":152,
    "gn:feature_class":"P",
    "gn:feature_code":"PPL",
    "gn:name":"Pukht\u00ebvo",
    "gn:population":0,
    "gn:timezone":"Europe/Moscow",
    "iso:country":"RU",
    "name:rus_x_preferred":[
        "\u041f\u0443\u0445\u0442\u0451\u0432\u043e"
    ],
    "name:und_x_variant":[
        "Pukht\u00ebvo",
        "\u041f\u0443\u0445\u0442\u0451\u0432\u043e"
    ],
    "wof:name":"Pukhtevo",
    "wof:placetype":"locality"
},
  "geometry": {"coordinates":[30.9014,56.2609],"type":"Point"}
}