{
  "type": "Feature",
  "properties": {
    "gn:admin1_code":"25",
    "gn:asciiname":"Losinoye",
    "gn:country_code":"RU",
    "gn:dem":213,
    "gn:feature_class":"P",
    "gn:feature_code":"PPL",
    "gn:name":"Losinoye",
    "gn:population":0,
    "gn:timezone":"Europe/Moscow",
    "iso:country":"RU",
    "name:rus_x_preferred":[
        "\u041b\u043e\u0441\u0438\u043d\u043e\u0435"
    ],
    "name:und_x_variant":[
        "\u041b\u043e\u0441\u0438\u043d\u043e\u0435"
    ],
    "wof:name":"Losinoye",
    "wof:placetype":"locality"
},
  "geometry": {"coordinates":[34.48528,54.1875],"type":"Point"}
}