{
  "type": "Feature",
  "properties": {
    "gn:admin1_code":"76",
    "gn:asciiname":"Luzhki",
    "gn:country_code":"RU",
    "gn:dem":196,
    "gn:feature_class":"P",
    "gn:feature_code":"PPL",
    "gn:name":"Luzhki",
    "gn:population":0,
    "gn:timezone":"Europe/Moscow",
    "iso:country":"RU",
    "name:nor_x_preferred":[
        "Luzjki"
    ],
    "name:rus_x_preferred":[
        "\u041b\u0443\u0436\u043a\u0438"
    ],
    "wof:name":"Luzhki",
    "wof:placetype":"locality"
},
  "geometry": {"coordinates":[36.67862,54.06035],"type":"Point"}
}