{
  "type": "Feature",
  "properties": {
    "gn:admin1_code":"23",
    "gn:asciiname":"Kar'yernoye",
    "gn:country_code":"RU",
    "gn:dem":0,
    "gn:feature_class":"P",
    "gn:feature_code":"PPL",
    "gn:name":"Kar\u2019yernoye",
    "gn:population":0,
    "gn:timezone":"Europe/Kaliningrad",
    "iso:country":"RU",
    "name:rus_x_preferred":[
        "\u041a\u0430\u0440\u044c\u0435\u0440\u043d\u043e\u0435"
    ],
    "name:und_x_variant":[
        "Kar\u2019yernoye",
        "\u041a\u0430\u0440\u044c\u0435\u0440\u043d\u043e\u0435"
    ],
    "wof:name":"Kar'yernoye",
    "wof:placetype":"locality"
},
  "geometry": {"coordinates":[20.57623,54.92012],"type":"Point"}
}