{
  "type": "Feature",
  "properties": {
    "gn:admin1_code":"8",
    "gn:asciiname":"Nikiforovka",
    "gn:country_code":"RU",
    "gn:dem":153,
    "gn:feature_class":"P",
    "gn:feature_code":"PPL",
    "gn:name":"Nikiforovka",
    "gn:population":0,
    "gn:timezone":"Asia/Yekaterinburg",
    "iso:country":"RU",
    "name:rus_x_preferred":[
        "\u041d\u0438\u043a\u0438\u0444\u043e\u0440\u043e\u0432\u043a\u0430"
    ],
    "wof:name":"Nikiforovka",
    "wof:placetype":"locality"
},
  "geometry": {"coordinates":[56.08333,53.65],"type":"Point"}
}