{
  "type": "Feature",
  "properties": {
    "gn:admin1_code":"52",
    "gn:asciiname":"Vyatka",
    "gn:country_code":"RU",
    "gn:dem":132,
    "gn:feature_class":"P",
    "gn:feature_code":"PPL",
    "gn:name":"Vyatka",
    "gn:population":0,
    "gn:timezone":"Europe/Moscow",
    "iso:country":"RU",
    "name:bul_x_preferred":[
        "\u0412\u044f\u0442\u043a\u0430"
    ],
    "name:cat_x_preferred":[
        "Vyatka"
    ],
    "name:ceb_x_preferred":[
        "Vyatka"
    ],
    "name:ces_x_preferred":[
        "Vjatka"
    ],
    "name:deu_x_preferred":[
        "Wjatka"
    ],
    "name:eng_x_preferred":[
        "Vyatka"
    ],
    "name:fin_x_preferred":[
        "Vjatka"
    ],
    "name:hye_x_preferred":[
        "\u054e\u0575\u0561\u057f\u056f\u0561"
    ],
    "name:ita_x_preferred":[
        "Vjatka"
    ],
    "name:lat_x_preferred":[
        "Viatca"
    ],
    "name:lav_x_preferred":[
        "Vjatka"
    ],
    "name:nld_x_preferred":[
        "Vjatka"
    ],
    "name:nor_x_preferred":[
        "Vjatka"
    ],
    "name:pol_x_preferred":[
        "Wiatka"
    ],
    "name:rus_x_preferred":[
        "\u0412\u044f\u0442\u043a\u0430"
    ],
    "name:swe_x_preferred":[
        "Vjatka"
    ],
    "name:ukr_x_preferred":[
        "\u0412\u044f\u0442\u043a\u0430"
    ],
    "wof:name":"Vyatka",
    "wof:placetype":"locality"
},
  "geometry": {"coordinates":[35.66857,58.46769000000001],"type":"Point"}
}