{
  "type": "Feature",
  "properties": {
    "gn:admin1_code":"52",
    "gn:asciiname":"Vyatka",
    "gn:country_code":"RU",
    "gn:dem":132,
    "gn:feature_class":"P",
    "gn:feature_code":"PPL",
    "gn:name":"Vyatka",
    "gn:population":0,
    "gn:timezone":"Europe/Moscow",
    "iso:country":"RU",
    "name:eng_x_preferred":[
        "Vyatka"
    ],
    "name:nor_x_preferred":[
        "Vjatka"
    ],
    "name:rus_x_preferred":[
        "\u0412\u044f\u0442\u043a\u0430"
    ],
    "name:und_x_variant":[
        "\u0412\u044f\u0442\u043a\u0430",
        "Vyatka"
    ],
    "wof:name":"Vyatka",
    "wof:placetype":"locality"
},
  "geometry": {"coordinates":[35.66857,58.46769000000001],"type":"Point"}
}