{
  "type": "Feature",
  "properties": {
    "gn:admin1_code":"52",
    "gn:asciiname":"Vyatka",
    "gn:country_code":"RU",
    "gn:dem":132,
    "gn:feature_class":"P",
    "gn:feature_code":"PPL",
    "gn:name":"Vyatka",
    "gn:population":0,
    "gn:timezone":"Europe/Moscow",
    "iso:country":"RU",
    "name:ben_x_preferred":[
        "\u09ac\u09cd\u09af\u09be\u09a4\u0995\u09be"
    ],
    "name:bul_x_preferred":[
        "\u0412\u044f\u0442\u043a\u0430"
    ],
    "name:cat_x_preferred":[
        "Vyatka"
    ],
    "name:ceb_x_preferred":[
        "Vyatka"
    ],
    "name:ces_x_preferred":[
        "Vjatka"
    ],
    "name:deu_x_preferred":[
        "Wjatka"
    ],
    "name:ell_x_preferred":[
        "\u0392\u03b9\u03ac\u03c4\u03ba\u03b1"
    ],
    "name:eng_x_preferred":[
        "Vyatka"
    ],
    "name:fin_x_preferred":[
        "Vjatka"
    ],
    "name:hin_x_preferred":[
        "\u0935\u094d\u092f\u0924\u094d\u0915\u093e"
    ],
    "name:hye_x_preferred":[
        "\u054e\u0575\u0561\u057f\u056f\u0561"
    ],
    "name:ind_x_preferred":[
        "Vyatka"
    ],
    "name:ita_x_preferred":[
        "Vjatka"
    ],
    "name:kor_x_preferred":[
        "\ubc4c\ud2b8\uce74"
    ],
    "name:lat_x_preferred":[
        "Viatca"
    ],
    "name:lav_x_preferred":[
        "Vjatka"
    ],
    "name:nld_x_preferred":[
        "Vjatka"
    ],
    "name:nor_x_preferred":[
        "Vjatka"
    ],
    "name:pol_x_preferred":[
        "Wiatka"
    ],
    "name:rus_x_preferred":[
        "\u0412\u044f\u0442\u043a\u0430"
    ],
    "name:swe_x_preferred":[
        "Vjatka"
    ],
    "name:ukr_x_preferred":[
        "\u0412\u044f\u0442\u043a\u0430"
    ],
    "name:urd_x_preferred":[
        "\u0648\u06cc\u0627\u0679\u06a9\u0627"
    ],
    "name:vie_x_preferred":[
        "S\u00f4ng Vyatka"
    ],
    "wof:name":"Vyatka",
    "wof:placetype":"locality"
},
  "geometry": {"coordinates":[35.66857,58.46769],"type":"Point"}
}