{
  "type": "Feature",
  "properties": {
    "gn:admin1_code":"90",
    "gn:asciiname":"Tukmany",
    "gn:country_code":"RU",
    "gn:dem":169,
    "gn:feature_class":"P",
    "gn:feature_code":"PPL",
    "gn:name":"Tukmany",
    "gn:population":0,
    "gn:timezone":"Asia/Yekaterinburg",
    "iso:country":"RU",
    "name:rus_x_preferred":[
        "\u0422\u0443\u043a\u043c\u0430\u043d\u044b"
    ],
    "wof:name":"Tukmany",
    "wof:placetype":"locality"
},
  "geometry": {"coordinates":[57.8123,57.0799],"type":"Point"}
}