{
  "type": "Feature",
  "properties": {
    "gn:admin1_code":"77",
    "gn:asciiname":"Vit'bino",
    "gn:country_code":"RU",
    "gn:dem":238,
    "gn:feature_class":"P",
    "gn:feature_code":"PPL",
    "gn:name":"Vit\u2019bino",
    "gn:population":0,
    "gn:timezone":"Europe/Moscow",
    "iso:country":"RU",
    "name:rus_x_preferred":[
        "\u0412\u0438\u0442\u044c\u0431\u0438\u043d\u043e"
    ],
    "name:und_x_variant":[
        "Vit\u2019bino"
    ],
    "wof:name":"Vit'bino",
    "wof:placetype":"locality"
},
  "geometry": {"coordinates":[32.16683,56.97636],"type":"Point"}
}