{
  "type": "Feature",
  "properties": {
    "gn:admin1_code":"23",
    "gn:asciiname":"Georgiyevskoye",
    "gn:country_code":"RU",
    "gn:dem":25,
    "gn:feature_class":"P",
    "gn:feature_code":"PPL",
    "gn:name":"Georgiyevskoye",
    "gn:population":0,
    "gn:timezone":"Europe/Kaliningrad",
    "iso:country":"RU",
    "name:rus_x_preferred":[
        "\u0413\u0435\u043e\u0440\u0433\u0438\u0435\u0432\u0441\u043a\u043e\u0435"
    ],
    "wof:name":"Georgiyevskoye",
    "wof:placetype":"locality"
},
  "geometry": {"coordinates":[20.62944,54.835],"type":"Point"}
}