{
  "type": "Feature",
  "properties": {
    "gn:admin1_code":"41",
    "gn:asciiname":"Durnovka",
    "gn:country_code":"RU",
    "gn:dem":197,
    "gn:feature_class":"P",
    "gn:feature_code":"PPL",
    "gn:name":"Durnovka",
    "gn:population":0,
    "gn:timezone":"Europe/Moscow",
    "iso:country":"RU",
    "name:rus_x_preferred":[
        "\u0414\u0443\u0440\u043d\u043e\u0432\u043a\u0430"
    ],
    "wof:name":"Durnovka",
    "wof:placetype":"locality"
},
  "geometry": {"coordinates":[37.1648,51.8432],"type":"Point"}
}