{
  "type": "Feature",
  "properties": {
    "gn:admin1_code":"17",
    "gn:asciiname":"Vanashimakhi",
    "gn:country_code":"RU",
    "gn:dem":1161,
    "gn:feature_class":"P",
    "gn:feature_code":"PPL",
    "gn:name":"Vanashimakhi",
    "gn:population":0,
    "gn:timezone":"Europe/Moscow",
    "iso:country":"RU",
    "wof:name":"Vanashimakhi",
    "wof:placetype":"locality"
},
  "geometry": {"coordinates":[47.24032,42.62227],"type":"Point"}
}