{
  "type": "Feature",
  "properties": {
    "gn:country":"RU",
    "gn:fcode":"PPL",
    "gn:population":0,
    "iso:country":"RU",
    "name:rus_x_preferred":[
        "\u041d\u043e\u0432\u0438\u043d\u043a\u0430"
    ],
    "name:und_x_variant":[
        "Pos\u00eblok Novinka"
    ],
    "qs:name":"Novinka",
    "qs:name_adm0":"Russia",
    "qs:name_adm1":"Leningrad Oblast",
    "qs:photos_9r":0,
    "qs:photos_sr":0,
    "qs:placetype":"Town",
    "qs:pop_sr":"0",
    "wof:name":"Novinka",
    "wof:placetype":"locality",
    "wof:population":0
},
  "geometry": {"coordinates":[30.37139,59.18556],"type":"Point"}
}