{
  "type": "Feature",
  "properties": {
    "gn:admin1_code":"8.0",
    "gn:asciiname":"Verkhnyaya Barabanovka",
    "gn:country_code":"RU",
    "gn:dem":160,
    "gn:feature_class":"P",
    "gn:feature_code":"PPL",
    "gn:name":"Verkhnyaya Barabanovka",
    "gn:population":0,
    "gn:timezone":"Asia/Yekaterinburg",
    "iso:country":"RU",
    "name:rus_x_preferred":[
        "\u0412\u0435\u0440\u0445\u043d\u044f\u044f \u0411\u0430\u0440\u0430\u0431\u0430\u043d\u043e\u0432\u043a\u0430"
    ],
    "wof:name":"Verkhnyaya Barabanovka",
    "wof:placetype":"locality"
},
  "geometry": {"coordinates":[55.3227,56.2938],"type":"Point"}
}