{
  "type": "Feature",
  "properties": {
    "gn:admin1_code":"45",
    "gn:asciiname":"Pabaynur",
    "gn:country_code":"RU",
    "gn:dem":166,
    "gn:feature_class":"P",
    "gn:feature_code":"PPL",
    "gn:name":"Pabaynur",
    "gn:population":0,
    "gn:timezone":"Europe/Moscow",
    "iso:country":"RU",
    "name:rus_x_preferred":[
        "\u041f\u0430\u0431\u0430\u0439\u043d\u0443\u0440"
    ],
    "name:und_x_variant":[
        "Pobaynur"
    ],
    "wof:name":"Pabaynur",
    "wof:placetype":"locality"
},
  "geometry": {"coordinates":[50.1777,56.5807],"type":"Point"}
}