{
  "type": "Feature",
  "properties": {
    "gn:admin1_code":"62",
    "gn:asciiname":"Poplevino",
    "gn:country_code":"RU",
    "gn:dem":106,
    "gn:feature_class":"P",
    "gn:feature_code":"PPL",
    "gn:name":"Popl\u00ebvino",
    "gn:population":0,
    "gn:timezone":"Europe/Moscow",
    "iso:country":"RU",
    "name:eng_x_preferred":[
        "Popl\u00ebvino"
    ],
    "name:nor_x_preferred":[
        "Poplevino"
    ],
    "name:rus_x_preferred":[
        "\u041f\u043e\u043f\u043b\u0435\u0432\u0438\u043d\u043e"
    ],
    "name:rus_x_variant":[
        "\u041f\u043e\u043f\u043b\u0451\u0432\u0438\u043d\u043e"
    ],
    "name:und_x_variant":[
        "Peplevino",
        "Popl\u00ebvino",
        "\u041f\u043e\u043f\u043b\u0451\u0432\u0438\u043d\u043e"
    ],
    "wof:name":"Poplevino",
    "wof:placetype":"locality"
},
  "geometry": {"coordinates":[40.0938,53.7962],"type":"Point"}
}