{
  "type": "Feature",
  "properties": {
    "gn:admin1_code":"57",
    "gn:asciiname":"Goryushi",
    "gn:country_code":"RU",
    "gn:dem":246,
    "gn:feature_class":"P",
    "gn:feature_code":"PPL",
    "gn:name":"Goryushi",
    "gn:population":0,
    "gn:timezone":"Europe/Moscow",
    "iso:country":"RU",
    "name:rus_x_preferred":[
        "\u0413\u043e\u0440\u044e\u0448\u0438"
    ],
    "name:und_x_variant":[
        "\u0413\u043e\u0440\u044e\u0448\u0438"
    ],
    "wof:name":"Goryushi",
    "wof:placetype":"locality"
},
  "geometry": {"coordinates":[45.68333,52.63333000000001],"type":"Point"}
}