{
  "type": "Feature",
  "properties": {
    "gn:admin1_code":"13.0",
    "gn:asciiname":"Smorodinka",
    "gn:country_code":"RU",
    "gn:dem":352,
    "gn:feature_class":"P",
    "gn:feature_code":"PPL",
    "gn:name":"Smorodinka",
    "gn:population":0,
    "gn:timezone":"Asia/Yekaterinburg",
    "iso:country":"RU",
    "name:rus_x_preferred":[
        "\u0421\u043c\u043e\u0440\u043e\u0434\u0438\u043d\u043a\u0430"
    ],
    "wof:name":"Smorodinka",
    "wof:placetype":"locality"
},
  "geometry": {"coordinates":[59.03639,52.6775],"type":"Point"}
}