{
  "type": "Feature",
  "properties": {
    "gn:admin1_code":"69",
    "gn:asciiname":"Levkova",
    "gn:country_code":"RU",
    "gn:dem":220,
    "gn:feature_class":"P",
    "gn:feature_code":"PPL",
    "gn:name":"Levkova",
    "gn:population":0,
    "gn:timezone":"Europe/Moscow",
    "iso:country":"RU",
    "name:eng_x_preferred":[
        "Levkova"
    ],
    "name:nor_x_preferred":[
        "Levkovo"
    ],
    "name:rus_x_preferred":[
        "\u041b\u0435\u0432\u043a\u043e\u0432\u043e"
    ],
    "name:rus_x_variant":[
        "\u041b\u0435\u0432\u043a\u043e\u0432\u0430"
    ],
    "name:und_x_variant":[
        "\u041b\u0435\u0432\u043a\u043e\u0432\u0430"
    ],
    "wof:name":"Levkova",
    "wof:placetype":"locality"
},
  "geometry": {"coordinates":[33.15722,55.23167],"type":"Point"}
}