{
  "type": "Feature",
  "properties": {
    "gn:admin1_code":"27",
    "gn:asciiname":"Musht",
    "gn:country_code":"RU",
    "gn:dem":1610,
    "gn:feature_class":"P",
    "gn:feature_code":"PPL",
    "gn:name":"Musht",
    "gn:population":0,
    "gn:timezone":"Europe/Moscow",
    "iso:country":"RU",
    "name:rus_x_preferred":[
        "\u041c\u0443\u0448\u0442"
    ],
    "wof:name":"Musht",
    "wof:placetype":"locality"
},
  "geometry": {"coordinates":[42.665,43.70583],"type":"Point"}
}