{
  "type": "Feature",
  "properties": {
    "gn:admin1_code":"10",
    "gn:asciiname":"Belyy Kolodets",
    "gn:country_code":"RU",
    "gn:dem":194,
    "gn:feature_class":"P",
    "gn:feature_code":"PPL",
    "gn:name":"Belyy Kolodets",
    "gn:population":0,
    "gn:timezone":"Europe/Moscow",
    "iso:country":"RU",
    "name:nor_x_preferred":[
        "Belyj Kolodez"
    ],
    "name:rus_x_preferred":[
        "\u0411\u0435\u043b\u044b\u0439 \u041a\u043e\u043b\u043e\u0434\u0435\u0446"
    ],
    "name:und_x_variant":[
        "Belyy Kolodez",
        "Belyy Kolodets"
    ],
    "wof:name":"Belyy Kolodets",
    "wof:placetype":"locality"
},
  "geometry": {"coordinates":[34.8051,52.191],"type":"Point"}
}