{
  "type": "Feature",
  "properties": {
    "gn:admin1_code":"86",
    "gn:asciiname":"Monastyr'shchenka",
    "gn:country_code":"RU",
    "gn:dem":116,
    "gn:feature_class":"P",
    "gn:feature_code":"PPL",
    "gn:name":"Monastyr\u2019shchenka",
    "gn:population":0,
    "gn:timezone":"Europe/Moscow",
    "iso:country":"RU",
    "name:rus_x_preferred":[
        "\u041c\u043e\u043d\u0430\u0441\u0442\u044b\u0440\u044c\u0449\u0435\u043d\u043a\u0430"
    ],
    "name:und_x_variant":[
        "Manastyr\u2019shchenka",
        "Monastyr\u2019shchenka",
        "\u041c\u043e\u043d\u0430\u0441\u0442\u044b\u0440\u044c\u0449\u0435\u043d\u043a\u0430"
    ],
    "wof:name":"Monastyr'shchenka",
    "wof:placetype":"locality"
},
  "geometry": {"coordinates":[39.25214,51.63497],"type":"Point"}
}