{
  "type": "Feature",
  "properties": {
    "gn:admin1_code":"47",
    "gn:asciiname":"Novoshchapovo",
    "gn:country_code":"RU",
    "gn:dem":192,
    "gn:feature_class":"P",
    "gn:feature_code":"PPL",
    "gn:name":"Novoshchapovo",
    "gn:population":850,
    "gn:timezone":"Europe/Moscow",
    "iso:country":"RU",
    "name:eng_x_preferred":[
        "Novoshchapovo"
    ],
    "name:nor_x_preferred":[
        "Novosjtsjapovo"
    ],
    "name:rus_x_preferred":[
        "\u041d\u043e\u0432\u043e\u0449\u0430\u043f\u043e\u0432\u043e"
    ],
    "name:und_x_variant":[
        "Novoye Shchapovo"
    ],
    "wof:name":"Novoshchapovo",
    "wof:placetype":"locality",
    "wof:population":850
},
  "geometry": {"coordinates":[36.79939,56.37286],"type":"Point"}
}