{
  "type": "Feature",
  "properties": {
    "gn:admin1_code":"86.0",
    "gn:asciiname":"Babyakovo",
    "gn:country_code":"RU",
    "gn:dem":101,
    "gn:feature_class":"P",
    "gn:feature_code":"PPL",
    "gn:name":"Babyakovo",
    "gn:population":0,
    "gn:timezone":"Europe/Moscow",
    "iso:country":"RU",
    "name:eng_x_preferred":[
        "Babyakovo"
    ],
    "name:nor_x_preferred":[
        "Babjakovo"
    ],
    "name:rus_x_preferred":[
        "\u0411\u0430\u0431\u044f\u043a\u043e\u0432\u043e"
    ],
    "name:und_x_variant":[
        "Bobyakino",
        "Babyakino",
        "Bobyakovo",
        "Babyakovo"
    ],
    "wof:name":"Babyakovo",
    "wof:placetype":"locality"
},
  "geometry": {"coordinates":[39.37441,51.68605],"type":"Point"}
}