{
  "type": "Feature",
  "properties": {
    "gn:admin1_code":"83",
    "gn:asciiname":"Kamenka",
    "gn:country_code":"RU",
    "gn:dem":172,
    "gn:feature_class":"P",
    "gn:feature_code":"PPL",
    "gn:name":"Kamenka",
    "gn:population":0,
    "gn:timezone":"Europe/Moscow",
    "iso:country":"RU",
    "name:aze_x_preferred":[
        "Kamenka"
    ],
    "name:bel_x_preferred":[
        "\u041a\u0430\u043c\u0435\u043d\u043a\u0430"
    ],
    "name:ben_x_preferred":[
        "\u0995\u09be\u09ae\u09c7\u0999\u09cd\u0995\u09be"
    ],
    "name:ceb_x_preferred":[
        "Kamenka"
    ],
    "name:ces_x_preferred":[
        "Kamenka"
    ],
    "name:deu_x_preferred":[
        "Kamenka"
    ],
    "name:ell_x_preferred":[
        "\u039a\u03b1\u03bc\u03ad\u03bd\u03ba\u03b1"
    ],
    "name:epo_x_preferred":[
        "Kamenka"
    ],
    "name:est_x_preferred":[
        "Kamenka"
    ],
    "name:fin_x_preferred":[
        "Kamenka"
    ],
    "name:fra_x_preferred":[
        "Kamenka"
    ],
    "name:heb_x_preferred":[
        "\u05e7\u05de\u05e0\u05e7\u05d4"
    ],
    "name:hin_x_preferred":[
        "\u0915\u093e\u092e\u0947\u0902\u0915\u093e"
    ],
    "name:hye_x_preferred":[
        "\u053f\u0561\u0574\u0565\u0576\u056f\u0561"
    ],
    "name:ind_x_preferred":[
        "Kamenka"
    ],
    "name:ita_x_preferred":[
        "Kamenka"
    ],
    "name:jpn_x_preferred":[
        "\u30ab\u30e1\u30f3\u30ab"
    ],
    "name:kat_x_preferred":[
        "\u10d9\u10d0\u10db\u10d4\u10dc\u10d9\u10d0"
    ],
    "name:kaz_x_preferred":[
        "\u041a\u0430\u043c\u0435\u043d\u043a\u0430"
    ],
    "name:kor_x_preferred":[
        "\uce74\uba58\uce74"
    ],
    "name:lav_x_preferred":[
        "Kamenka"
    ],
    "name:lit_x_preferred":[
        "Kamenka"
    ],
    "name:myv_x_preferred":[
        "\u041a\u0430\u043c\u0435\u043d\u043a\u0430"
    ],
    "name:rus_x_preferred":[
        "\u041a\u0430\u043c\u0435\u043d\u043a\u0430"
    ],
    "name:spa_x_preferred":[
        "Kamenka"
    ],
    "name:srp_x_preferred":[
        "\u041a\u0430\u043c\u0435\u043d\u043a\u0430"
    ],
    "name:swe_x_preferred":[
        "Kamenka"
    ],
    "name:ukr_x_preferred":[
        "\u041a\u0430\u043c\u0435\u043d\u043a\u0430"
    ],
    "name:urd_x_preferred":[
        "\u06a9\u0627\u0645\u06cc\u0646\u06a9\u0627"
    ],
    "name:vie_x_preferred":[
        "Kamenka"
    ],
    "wof:name":"Kamenka",
    "wof:placetype":"locality"
},
  "geometry": {"coordinates":[39.3776,56.67277],"type":"Point"}
}