{
  "type": "Feature",
  "properties": {
    "gn:admin1_code":"78",
    "gn:asciiname":"Priirtyshskiy",
    "gn:country_code":"RU",
    "gn:dem":71,
    "gn:feature_class":"P",
    "gn:feature_code":"PPL",
    "gn:name":"Priirtyshskiy",
    "gn:population":0,
    "gn:timezone":"Asia/Yekaterinburg",
    "iso:country":"RU",
    "name:eng_x_preferred":[
        "Priirtyshskiy"
    ],
    "name:nor_x_preferred":[
        "Priirtysjskij"
    ],
    "name:rus_x_preferred":[
        "\u041f\u0440\u0438\u0438\u0440\u0442\u044b\u0448\u0441\u043a\u0438\u0439"
    ],
    "name:und_x_variant":[
        "\u041f\u0440\u0438\u0438\u0440\u0442\u044b\u0448\u0441\u043a\u0438\u0439",
        "Priirtyshskiy"
    ],
    "wof:name":"Priirtyshskiy",
    "wof:placetype":"locality"
},
  "geometry": {"coordinates":[68.38333,58.16667],"type":"Point"}
}