{
  "type": "Feature",
  "properties": {
    "gn:admin1_code":"13",
    "gn:asciiname":"Uralets",
    "gn:country_code":"RU",
    "gn:dem":321,
    "gn:feature_class":"P",
    "gn:feature_code":"PPL",
    "gn:name":"Uralets",
    "gn:population":0,
    "gn:timezone":"Asia/Yekaterinburg",
    "iso:country":"RU",
    "wof:name":"Uralets",
    "wof:placetype":"locality"
},
  "geometry": {"coordinates":[58.96666999999999,52.96666999999999],"type":"Point"}
}