{
  "type": "Feature",
  "properties": {
    "gn:admin1_code":"8.0",
    "gn:asciiname":"Atyashevo",
    "gn:country_code":"RU",
    "gn:dem":273,
    "gn:feature_class":"P",
    "gn:feature_code":"PPL",
    "gn:name":"Atyashevo",
    "gn:population":0,
    "gn:timezone":"Asia/Yekaterinburg",
    "iso:country":"RU",
    "name:eng_x_preferred":[
        "Atyachevo"
    ],
    "name:rus_x_preferred":[
        "\u0410\u0442\u044f\u0448\u0435\u0432\u043e"
    ],
    "name:und_x_variant":[
        "Atyaseva",
        "Atyasevo",
        "Atyashevo"
    ],
    "wof:name":"Atyashevo",
    "wof:placetype":"locality"
},
  "geometry": {"coordinates":[55.2558,53.0474],"type":"Point"}
}