{
  "type": "Feature",
  "properties": {
    "gn:admin1_code":"77",
    "gn:asciiname":"Nerudnyy",
    "gn:country_code":"RU",
    "gn:dem":203,
    "gn:feature_class":"P",
    "gn:feature_code":"PPL",
    "gn:name":"Nerudnyy",
    "gn:population":0,
    "gn:timezone":"Europe/Moscow",
    "iso:country":"RU",
    "name:rus_x_preferred":[
        "\u041d\u0435\u0440\u0443\u0434\u043d\u044b\u0439"
    ],
    "wof:name":"Nerudnyy",
    "wof:placetype":"locality"
},
  "geometry": {"coordinates":[34.74566,56.89099],"type":"Point"}
}