{
  "type": "Feature",
  "properties": {
    "gn:admin1_code":"85",
    "gn:asciiname":"Karyatino",
    "gn:country_code":"RU",
    "gn:dem":155,
    "gn:feature_class":"P",
    "gn:feature_code":"PPL",
    "gn:name":"Karyatino",
    "gn:population":0,
    "gn:timezone":"Europe/Moscow",
    "iso:country":"RU",
    "name:rus_x_preferred":[
        "\u041a\u0430\u0440\u044f\u0442\u0438\u043d\u043e"
    ],
    "name:und_x_variant":[
        "\u041a\u0430\u0440\u044f\u0442\u0438\u043d\u043e",
        "Koryakino"
    ],
    "wof:name":"Karyatino",
    "wof:placetype":"locality"
},
  "geometry": {"coordinates":[38.8401,59.8152],"type":"Point"}
}