{
  "type": "Feature",
  "properties": {
    "gn:admin1_code":"8",
    "gn:asciiname":"Rudniki",
    "gn:country_code":"RU",
    "gn:dem":235,
    "gn:feature_class":"P",
    "gn:feature_code":"PPL",
    "gn:name":"Rudniki",
    "gn:population":0,
    "gn:timezone":"Asia/Yekaterinburg",
    "iso:country":"RU",
    "name:bel_x_preferred":[
        "\u0420\u0443\u0434\u043d\u0456\u043a\u0456"
    ],
    "name:ceb_x_preferred":[
        "Rudniki"
    ],
    "name:deu_x_preferred":[
        "Rudnyky"
    ],
    "name:fra_x_preferred":[
        "Rudniki"
    ],
    "name:hye_x_preferred":[
        "\u054c\u0578\u0582\u0564\u0576\u056b\u056f\u056b"
    ],
    "name:lit_x_preferred":[
        "Rudnikai"
    ],
    "name:nld_x_preferred":[
        "Rudniki"
    ],
    "name:pol_x_preferred":[
        "Rudniki"
    ],
    "name:rus_x_preferred":[
        "\u0420\u0443\u0434\u043d\u0438\u043a\u0438"
    ],
    "name:ukr_x_preferred":[
        "\u0420\u0443\u0434\u043d\u0438\u043a\u0438"
    ],
    "wof:name":"Rudniki",
    "wof:placetype":"locality"
},
  "geometry": {"coordinates":[54.38333000000001,53.86666999999999],"type":"Point"}
}