{
  "type": "Feature",
  "properties": {
    "gn:admin1_code":"28",
    "gn:asciiname":"Kiviyarvi",
    "gn:cc2":"RU",
    "gn:country_code":"RU",
    "gn:dem":141,
    "gn:feature_class":"P",
    "gn:feature_code":"PPL",
    "gn:name":"Kiviyarvi",
    "gn:population":0,
    "gn:timezone":"Europe/Moscow",
    "iso:country":"RU",
    "name:fin_x_preferred":[
        "Kivij\u00e4rvi"
    ],
    "name:rus_x_preferred":[
        "\u041a\u0438\u0432\u0438\u044f\u0440\u0432\u0438"
    ],
    "wof:name":"Kiviyarvi",
    "wof:placetype":"locality"
},
  "geometry": {"coordinates":[31.96667,62.16667],"type":"Point"}
}