{
  "type": "Feature",
  "properties": {
    "gn:admin1_code":"13",
    "gn:asciiname":"Kabanskoye",
    "gn:country_code":"RU",
    "gn:dem":175,
    "gn:feature_class":"P",
    "gn:feature_code":"PPL",
    "gn:name":"Kabanskoye",
    "gn:population":0,
    "gn:timezone":"Asia/Yekaterinburg",
    "iso:country":"RU",
    "name:rus_x_preferred":[
        "\u041a\u0430\u0431\u0430\u043d\u0441\u043a\u043e\u0435"
    ],
    "wof:name":"Kabanskoye",
    "wof:placetype":"locality"
},
  "geometry": {"coordinates":[61.7452,56.1425],"type":"Point"}
}