{
  "type": "Feature",
  "properties": {
    "gn:admin1_code":"34",
    "gn:asciiname":"Nebdino",
    "gn:country_code":"RU",
    "gn:dem":87,
    "gn:feature_class":"P",
    "gn:feature_code":"PPL",
    "gn:name":"N\u00ebbdino",
    "gn:population":0,
    "gn:timezone":"Europe/Moscow",
    "iso:country":"RU",
    "name:eng_x_preferred":[
        "N\u00ebbdino"
    ],
    "name:nor_x_preferred":[
        "Nebdino"
    ],
    "name:rus_x_preferred":[
        "\u041d\u0435\u0431\u0434\u0438\u043d\u043e"
    ],
    "name:rus_x_variant":[
        "\u041d\u0451\u0431\u0434\u0438\u043d\u043e"
    ],
    "name:und_x_variant":[
        "Nebdin",
        "Nebdyn",
        "N\u00ebbdino",
        "\u041d\u0451\u0431\u0434\u0438\u043d\u043e"
    ],
    "wof:name":"Nebdino",
    "wof:placetype":"locality"
},
  "geometry": {"coordinates":[52.12676,61.9082],"type":"Point"}
}