{
  "type": "Feature",
  "properties": {
    "gn:admin1_code":"60",
    "gn:asciiname":"Markovo",
    "gn:country_code":"RU",
    "gn:dem":51,
    "gn:feature_class":"P",
    "gn:feature_code":"PPL",
    "gn:name":"Markovo",
    "gn:population":0,
    "gn:timezone":"Europe/Moscow",
    "iso:country":"RU",
    "name:bel_x_preferred":[
        "\u041c\u0430\u0440\u043a\u0430\u0432\u0430"
    ],
    "name:bos_x_preferred":[
        "Markovo"
    ],
    "name:bul_x_preferred":[
        "\u041c\u0430\u0440\u043a\u043e\u0432\u043e"
    ],
    "name:ceb_x_preferred":[
        "Markovo"
    ],
    "name:fra_x_preferred":[
        "Markovo"
    ],
    "name:hun_x_preferred":[
        "Markovo"
    ],
    "name:ron_x_preferred":[
        "Markovo"
    ],
    "name:rus_x_preferred":[
        "\u041c\u0430\u0440\u043a\u043e\u0432\u043e"
    ],
    "name:slv_x_preferred":[
        "Markovo"
    ],
    "name:srp_x_preferred":[
        "\u041c\u0430\u0440\u043a\u043e\u0432\u043e"
    ],
    "name:swe_x_preferred":[
        "Markovo"
    ],
    "name:ukr_x_preferred":[
        "\u041c\u0430\u0440\u043a\u043e\u0432\u0435"
    ],
    "wof:name":"Markovo",
    "wof:placetype":"locality"
},
  "geometry": {"coordinates":[28.23783,57.36399],"type":"Point"}
}