{
  "type": "Feature",
  "properties": {
    "gn:admin1_code":"90",
    "gn:asciiname":"Gornyy",
    "gn:country_code":"RU",
    "gn:dem":183,
    "gn:feature_class":"P",
    "gn:feature_code":"PPL",
    "gn:name":"Gornyy",
    "gn:population":0,
    "gn:timezone":"Asia/Yekaterinburg",
    "iso:country":"RU",
    "name:rus_x_preferred":[
        "\u0413\u043e\u0440\u043d\u044b\u0439"
    ],
    "name:und_x_variant":[
        "\u0413\u043e\u0440\u043d\u044b\u0439"
    ],
    "wof:name":"Gornyy",
    "wof:placetype":"locality"
},
  "geometry": {"coordinates":[56.6255,57.8304],"type":"Point"}
}