{
  "type": "Feature",
  "properties": {
    "gn:admin1_code":"16",
    "gn:asciiname":"Malyye Arabuzi",
    "gn:country_code":"RU",
    "gn:dem":84,
    "gn:feature_class":"P",
    "gn:feature_code":"PPL",
    "gn:name":"Malyye Arabuzi",
    "gn:population":0,
    "gn:timezone":"Europe/Moscow",
    "iso:country":"RU",
    "name:rus_x_preferred":[
        "\u041c\u0430\u043b\u044b\u0435 \u0410\u0440\u0430\u0431\u0443\u0437\u0438"
    ],
    "wof:name":"Malyye Arabuzi",
    "wof:placetype":"locality"
},
  "geometry": {"coordinates":[46.45,55.08333],"type":"Point"}
}