{
  "type": "Feature",
  "properties": {
    "gn:admin1_code":"54",
    "gn:asciiname":"Lobkovo",
    "gn:country_code":"RU",
    "gn:dem":88,
    "gn:feature_class":"P",
    "gn:feature_code":"PPL",
    "gn:name":"Lobkovo",
    "gn:population":0,
    "gn:timezone":"Asia/Omsk",
    "iso:country":"RU",
    "name:eng_x_preferred":[
        "Lobkovo"
    ],
    "name:nor_x_preferred":[
        "Lobkovo"
    ],
    "name:rus_x_preferred":[
        "\u041b\u043e\u0431\u043a\u043e\u0432\u043e"
    ],
    "wof:name":"Lobkovo",
    "wof:placetype":"locality"
},
  "geometry": {"coordinates":[73.56635,54.70233],"type":"Point"}
}