{
  "type": "Feature",
  "properties": {
    "gn:admin1_code":"05",
    "gn:asciiname":"Lidinskiy",
    "gn:country_code":"RU",
    "gn:dem":666,
    "gn:feature_class":"P",
    "gn:feature_code":"PPL",
    "gn:name":"Lidinskiy",
    "gn:population":0,
    "gn:timezone":"Asia/Yakutsk",
    "iso:country":"RU",
    "name:rus_x_preferred":[
        "\u041b\u0438\u0434\u0438\u043d\u0441\u043a\u0438\u0439"
    ],
    "wof:name":"Lidinskiy",
    "wof:placetype":"locality"
},
  "geometry": {"coordinates":[128.83333000000002,55.05],"type":"Point"}
}