{
  "type": "Feature",
  "properties": {
    "gn:admin1_code":"56",
    "gn:asciiname":"Suvorovo",
    "gn:country_code":"RU",
    "gn:dem":264,
    "gn:feature_class":"P",
    "gn:feature_code":"PPL",
    "gn:name":"Suvorovo",
    "gn:population":0,
    "gn:timezone":"Europe/Moscow",
    "iso:country":"RU",
    "name:eng_x_preferred":[
        "Suvorovo"
    ],
    "name:nor_x_preferred":[
        "Suvorovo"
    ],
    "name:rus_x_preferred":[
        "\u0421\u0443\u0432\u043e\u0440\u043e\u0432\u043e"
    ],
    "name:und_x_variant":[
        "Suvorova",
        "Suvorovo"
    ],
    "wof:name":"Suvorovo",
    "wof:placetype":"locality"
},
  "geometry": {"coordinates":[36.69016,53.05789],"type":"Point"}
}