{
  "type": "Feature",
  "properties": {
    "gn:admin1_code":"90.0",
    "gn:asciiname":"Bazhino",
    "gn:country_code":"RU",
    "gn:dem":140,
    "gn:feature_class":"P",
    "gn:feature_code":"PPL",
    "gn:name":"Bazhino",
    "gn:population":0,
    "gn:timezone":"Asia/Yekaterinburg",
    "iso:country":"RU",
    "name:koi_x_preferred":[
        "\u0411\u0430\u0436\u0438\u043d"
    ],
    "name:rus_x_preferred":[
        "\u0411\u0430\u0436\u0438\u043d\u043e"
    ],
    "wof:name":"Bazhino",
    "wof:placetype":"locality"
},
  "geometry": {"coordinates":[55.2061,58.6678],"type":"Point"}
}