{
  "type": "Feature",
  "properties": {
    "gn:admin1_code":"85",
    "gn:asciiname":"Vyal'ye",
    "gn:country_code":"RU",
    "gn:dem":152,
    "gn:feature_class":"P",
    "gn:feature_code":"PPL",
    "gn:name":"Vyal\u2019ye",
    "gn:population":0,
    "gn:timezone":"Europe/Moscow",
    "iso:country":"RU",
    "name:rus_x_preferred":[
        "\u0412\u044f\u043b\u044c\u0435"
    ],
    "name:und_x_variant":[
        "Val\u2019ya",
        "Vyal\u2019ya",
        "Vyal\u2019ye Buldyshkino",
        "Vyal\u2019ye",
        "\u0412\u044f\u043b\u044c\u0435"
    ],
    "wof:name":"Vyal'ye",
    "wof:placetype":"locality"
},
  "geometry": {"coordinates":[35.1678,59.157],"type":"Point"}
}