{
  "type": "Feature",
  "properties": {
    "gn:admin1_code":"83",
    "gn:asciiname":"Tolstovo",
    "gn:country_code":"RU",
    "gn:dem":148,
    "gn:feature_class":"P",
    "gn:feature_code":"PPL",
    "gn:name":"Tolstovo",
    "gn:population":0,
    "gn:timezone":"Europe/Moscow",
    "iso:country":"RU",
    "name:und_x_variant":[
        "Tolstova",
        "Tolstovo"
    ],
    "wof:name":"Tolstovo",
    "wof:placetype":"locality"
},
  "geometry": {"coordinates":[40.39128,55.93626],"type":"Point"}
}