{
  "type": "Feature",
  "properties": {
    "gn:admin1_code":"37",
    "gn:asciiname":"Vaganovo",
    "gn:country_code":"RU",
    "gn:dem":189,
    "gn:feature_class":"P",
    "gn:feature_code":"PPL",
    "gn:name":"Vaganovo",
    "gn:population":0,
    "gn:timezone":"Europe/Moscow",
    "iso:country":"RU",
    "name:rus_x_preferred":[
        "\u0412\u0430\u0433\u0430\u043d\u043e\u0432\u043e"
    ],
    "wof:name":"Vaganovo",
    "wof:placetype":"locality"
},
  "geometry": {"coordinates":[42.68233,58.43203000000001],"type":"Point"}
}