{
  "type": "Feature",
  "properties": {
    "gn:admin1_code":"6",
    "gn:asciiname":"Stepychevskaya",
    "gn:country_code":"RU",
    "gn:dem":30,
    "gn:feature_class":"P",
    "gn:feature_code":"PPL",
    "gn:name":"Stepychevskaya",
    "gn:population":0,
    "gn:timezone":"Europe/Moscow",
    "iso:country":"RU",
    "name:eng_x_preferred":[
        "Stepychevskaya"
    ],
    "name:nor_x_preferred":[
        "Stepatsjevskaja"
    ],
    "name:rus_x_preferred":[
        "\u0421\u0442\u0435\u043f\u0430\u0447\u0435\u0432\u0441\u043a\u0430\u044f"
    ],
    "name:rus_x_variant":[
        "\u0421\u0442\u0435\u043f\u044b\u0447\u0435\u0432\u0441\u043a\u0430\u044f"
    ],
    "name:und_x_variant":[
        "\u0421\u0442\u0435\u043f\u044b\u0447\u0435\u0432\u0441\u043a\u0430\u044f"
    ],
    "wof:name":"Stepychevskaya",
    "wof:placetype":"locality"
},
  "geometry": {"coordinates":[42.88449,62.41875],"type":"Point"}
}