{
  "type": "Feature",
  "properties": {
    "gn:admin1_code":"80",
    "gn:asciiname":"Valamaz",
    "gn:country_code":"RU",
    "gn:dem":164,
    "gn:feature_class":"P",
    "gn:feature_code":"PPL",
    "gn:name":"Valamaz",
    "gn:population":0,
    "gn:timezone":"Europe/Samara",
    "iso:country":"RU",
    "name:eng_x_preferred":[
        "Valamaz"
    ],
    "name:nor_x_preferred":[
        "Valamaz"
    ],
    "name:rus_x_preferred":[
        "\u0412\u0430\u043b\u0430\u043c\u0430\u0437"
    ],
    "wof:name":"Valamaz",
    "wof:placetype":"locality"
},
  "geometry": {"coordinates":[52.0594,57.4559],"type":"Point"}
}