{
  "type": "Feature",
  "properties": {
    "gn:admin1_code":"77",
    "gn:asciiname":"Tolstikovo",
    "gn:country_code":"RU",
    "gn:dem":193,
    "gn:feature_class":"P",
    "gn:feature_code":"PPL",
    "gn:name":"Tolstikovo",
    "gn:population":0,
    "gn:timezone":"Europe/Moscow",
    "iso:country":"RU",
    "name:rus_x_preferred":[
        "\u0422\u043e\u043b\u0441\u0442\u0438\u043a\u043e\u0432\u043e"
    ],
    "wof:name":"Tolstikovo",
    "wof:placetype":"locality"
},
  "geometry": {"coordinates":[36.8135,58.3257],"type":"Point"}
}