{
  "type": "Feature",
  "properties": {
    "gn:admin1_code":"37",
    "gn:asciiname":"Klevantsevo",
    "gn:country_code":"RU",
    "gn:dem":122,
    "gn:feature_class":"P",
    "gn:feature_code":"PPL",
    "gn:name":"Klevantsevo",
    "gn:population":0,
    "gn:timezone":"Europe/Moscow",
    "iso:country":"RU",
    "name:eng_x_preferred":[
        "Klevantsevo"
    ],
    "name:nor_x_preferred":[
        "Klevantsevo"
    ],
    "name:rus_x_preferred":[
        "\u041a\u043b\u0435\u0432\u0430\u043d\u0446\u0435\u0432\u043e"
    ],
    "name:und_x_variant":[
        "Klevantsovo",
        "\u041a\u043b\u0435\u0432\u0430\u043d\u0446\u0435\u0432\u043e",
        "Klevantsevo"
    ],
    "wof:name":"Klevantsevo",
    "wof:placetype":"locality"
},
  "geometry": {"coordinates":[42.45059000000001,57.82102],"type":"Point"}
}