{
  "type": "Feature",
  "properties": {
    "gn:admin1_code":"52",
    "gn:asciiname":"Malyy Donets",
    "gn:country_code":"RU",
    "gn:dem":27,
    "gn:feature_class":"P",
    "gn:feature_code":"PPL",
    "gn:name":"Malyy Donets",
    "gn:population":0,
    "gn:timezone":"Europe/Moscow",
    "iso:country":"RU",
    "name:rus_x_preferred":[
        "\u041c\u0430\u043b\u044b\u0439 \u0414\u043e\u043d\u0435\u0446"
    ],
    "name:und_x_variant":[
        "\u041c\u0430\u043b\u044b\u0439 \u0414\u043e\u043d\u0435\u0446"
    ],
    "wof:name":"Malyy Donets",
    "wof:placetype":"locality"
},
  "geometry": {"coordinates":[31.16667,58.38333000000001],"type":"Point"}
}