{
  "type": "Feature",
  "properties": {
    "gn:admin1_code":"63",
    "gn:asciiname":"Chapayevo",
    "gn:country_code":"RU",
    "gn:dem":170,
    "gn:feature_class":"P",
    "gn:feature_code":"PPL",
    "gn:name":"Chapayevo",
    "gn:population":0,
    "gn:timezone":"Asia/Yakutsk",
    "iso:country":"RU",
    "name:ceb_x_preferred":[
        "Chapayevo"
    ],
    "name:eng_x_preferred":[
        "Chapayevo"
    ],
    "name:nor_x_preferred":[
        "Tsjapajevo"
    ],
    "name:rus_x_preferred":[
        "\u0427\u0430\u043f\u0430\u0435\u0432\u043e"
    ],
    "name:swe_x_preferred":[
        "Chapayevo"
    ],
    "name:und_x_variant":[
        "\u0427\u0430\u043f\u0430\u0435\u0432\u043e",
        "Chapayevo"
    ],
    "wof:name":"Chapayevo",
    "wof:placetype":"locality"
},
  "geometry": {"coordinates":[117.11083000000001,60.13194],"type":"Point"}
}