{
  "type": "Feature",
  "properties": {
    "iso:country":"RU",
    "name:ceb_x_preferred":[
        "Petro-Slavyanka"
    ],
    "name:fra_x_preferred":[
        "Petro-Slavianka"
    ],
    "name:rus_x_preferred":[
        "\u041f\u0435\u0442\u0440\u043e-\u0421\u043b\u0430\u0432\u044f\u043d\u043a\u0430"
    ],
    "name:sco_x_preferred":[
        "Petro-Slavyanka"
    ],
    "wof:name":"Petro-Slavyanka",
    "wof:placetype":"neighbourhood"
},
  "geometry": {"coordinates":[30.51429929389691,59.80167730253246],"type":"Point"}
}