{
  "type": "Feature",
  "properties": {
    "gn:admin1_code":"77",
    "gn:asciiname":"Molokhovo",
    "gn:country_code":"RU",
    "gn:dem":228,
    "gn:feature_class":"P",
    "gn:feature_code":"PPL",
    "gn:name":"Molokhovo",
    "gn:population":0,
    "gn:timezone":"Europe/Moscow",
    "iso:country":"RU",
    "name:rus_x_preferred":[
        "\u041c\u043e\u043b\u043e\u0445\u043e\u0432\u043e"
    ],
    "wof:name":"Molokhovo",
    "wof:placetype":"locality"
},
  "geometry": {"coordinates":[32.70539,56.54713],"type":"Point"}
}