{
  "type": "Feature",
  "properties": {
    "gn:admin1_code":"6",
    "gn:asciiname":"Revpol'ye",
    "gn:country_code":"RU",
    "gn:dem":57,
    "gn:feature_class":"P",
    "gn:feature_code":"PPL",
    "gn:name":"Revpol\u2019ye",
    "gn:population":0,
    "gn:timezone":"Europe/Moscow",
    "iso:country":"RU",
    "name:rus_x_preferred":[
        "\u0420\u0435\u0432\u043f\u043e\u043b\u044c\u0435"
    ],
    "name:und_x_variant":[
        "Revpol\u2019ye"
    ],
    "wof:name":"Revpol'ye",
    "wof:placetype":"locality"
},
  "geometry": {"coordinates":[43.88333,64.66667],"type":"Point"}
}