{
  "type": "Feature",
  "properties": {
    "gn:admin1_code":"60",
    "gn:asciiname":"Podborov'ye Vtoroye",
    "gn:country_code":"RU",
    "gn:dem":73,
    "gn:feature_class":"P",
    "gn:feature_code":"PPL",
    "gn:name":"Podborov\u2019ye Vtoroye",
    "gn:population":0,
    "gn:timezone":"Europe/Moscow",
    "iso:country":"RU",
    "name:rus_x_preferred":[
        "\u041f\u043e\u0434\u0431\u043e\u0440\u043e\u0432\u044c\u0435 \u0412\u0442\u043e\u0440\u043e\u0435"
    ],
    "name:und_x_variant":[
        "Podborov\u2019ye",
        "Podborov\u2019ye Vtoroye"
    ],
    "wof:name":"Podborov'ye Vtoroye",
    "wof:placetype":"locality"
},
  "geometry": {"coordinates":[28.4857,57.94651999999999],"type":"Point"}
}