{
  "type": "Feature",
  "properties": {
    "gn:admin1_code":"60",
    "gn:asciiname":"Mylenki",
    "gn:country_code":"RU",
    "gn:dem":198,
    "gn:feature_class":"P",
    "gn:feature_code":"PPL",
    "gn:name":"Mylenki",
    "gn:population":0,
    "gn:timezone":"Europe/Moscow",
    "iso:country":"RU",
    "name:rus_x_preferred":[
        "\u041c\u044b\u043b\u0435\u043d\u043a\u0438"
    ],
    "name:und_x_variant":[
        "\u041c\u044b\u043b\u0435\u043d\u043a\u0438"
    ],
    "wof:name":"Mylenki",
    "wof:placetype":"locality"
},
  "geometry": {"coordinates":[29.8279,56.182],"type":"Point"}
}