{
  "type": "Feature",
  "properties": {
    "gn:admin1_code":"8",
    "gn:asciiname":"Sakmar",
    "gn:country_code":"RU",
    "gn:dem":512,
    "gn:feature_class":"P",
    "gn:feature_code":"PPL",
    "gn:name":"Sakmar",
    "gn:population":0,
    "gn:timezone":"Asia/Yekaterinburg",
    "iso:country":"RU",
    "name:eng_x_preferred":[
        "Sakmar"
    ],
    "name:nor_x_preferred":[
        "Sakmar"
    ],
    "name:rus_x_preferred":[
        "\u0421\u0430\u043a\u043c\u0430\u0440"
    ],
    "name:und_x_variant":[
        "Novyy Sakmar",
        "\u0421\u0430\u043a\u043c\u0430\u0440",
        "Sakmar"
    ],
    "wof:name":"Sakmar",
    "wof:placetype":"locality"
},
  "geometry": {"coordinates":[58.14333000000001,52.82611],"type":"Point"}
}