{
  "type": "Feature",
  "properties": {
    "gn:admin1_code":"51",
    "gn:asciiname":"Severnyy",
    "gn:country_code":"RU",
    "gn:dem":137,
    "gn:feature_class":"P",
    "gn:feature_code":"PPL",
    "gn:name":"Severnyy",
    "gn:population":0,
    "gn:timezone":"Europe/Moscow",
    "iso:country":"RU",
    "name:rus_x_preferred":[
        "\u0421\u0435\u0432\u0435\u0440\u043d\u044b\u0439"
    ],
    "wof:name":"Severnyy",
    "wof:placetype":"locality"
},
  "geometry": {"coordinates":[46.4295,57.8154],"type":"Point"}
}