{
  "type": "Feature",
  "properties": {
    "gn:admin1_code":"51",
    "gn:asciiname":"Severnyy",
    "gn:country_code":"RU",
    "gn:dem":137,
    "gn:feature_class":"P",
    "gn:feature_code":"PPL",
    "gn:name":"Severnyy",
    "gn:population":0,
    "gn:timezone":"Europe/Moscow",
    "iso:country":"RU",
    "name:ara_x_preferred":[
        "\u0633\u064a\u0641\u064a\u0631\u0646\u064a"
    ],
    "name:ben_x_preferred":[
        "\u09b8\u09c7\u09ad\u09c7\u09b0\u09a8\u09bf"
    ],
    "name:ell_x_preferred":[
        "\u03a3\u03b5\u03b2\u03ad\u03c1\u03bd\u03b9\u03b9"
    ],
    "name:fas_x_preferred":[
        "\u0633\u0648\u0631\u0646\u06cc"
    ],
    "name:fra_x_preferred":[
        "Severnyy"
    ],
    "name:heb_x_preferred":[
        "\u05e1\u05d5\u05d5\u05e8\u05e0\u05d9"
    ],
    "name:hin_x_preferred":[
        "\u0938\u0935\u0930\u094d\u0928\u0940"
    ],
    "name:hun_x_preferred":[
        "Severnyy"
    ],
    "name:ind_x_preferred":[
        "Severnyy"
    ],
    "name:jpn_x_preferred":[
        "\u30bb\u30f4\u30a7\u30eb\u30cc\u30a3"
    ],
    "name:kor_x_preferred":[
        "\uc138\ubca0\ub974\ub2c8"
    ],
    "name:por_x_preferred":[
        "Severny"
    ],
    "name:rus_x_preferred":[
        "\u0421\u0435\u0432\u0435\u0440\u043d\u044b\u0439"
    ],
    "name:spa_x_preferred":[
        "Severnyy"
    ],
    "name:swe_x_preferred":[
        "Severnyj"
    ],
    "name:tur_x_preferred":[
        "Severnyy"
    ],
    "name:ukr_x_preferred":[
        "\u0421\u0454\u0432\u0454\u0440\u043d\u0438\u0439"
    ],
    "name:urd_x_preferred":[
        "\u0633\u06cc\u0648\u0631\u0646\u06cc"
    ],
    "name:vie_x_preferred":[
        "Severnyy"
    ],
    "name:zho_cn_x_preferred":[
        "\u8c22\u97e6\u5c14\u5185\u5c9b"
    ],
    "name:zho_tw_x_preferred":[
        "\u585e\u7dad\u5c3c"
    ],
    "wof:name":"Severnyy",
    "wof:placetype":"locality"
},
  "geometry": {"coordinates":[46.4295,57.8154],"type":"Point"}
}