{
  "type": "Feature",
  "properties": {
    "gn:admin1_code":"71",
    "gn:asciiname":"Malaya Laya",
    "gn:country_code":"RU",
    "gn:dem":229,
    "gn:feature_class":"P",
    "gn:feature_code":"PPL",
    "gn:name":"Malaya Laya",
    "gn:population":0,
    "gn:timezone":"Asia/Yekaterinburg",
    "iso:country":"RU",
    "name:rus_x_preferred":[
        "\u041c\u0430\u043b\u0430\u044f \u041b\u0430\u044f"
    ],
    "name:und_x_variant":[
        "Laya",
        "Malaya Laya",
        "\u041c\u0430\u043b\u0430\u044f \u041b\u0430\u044f"
    ],
    "wof:name":"Malaya Laya",
    "wof:placetype":"locality"
},
  "geometry": {"coordinates":[59.883,58.1217],"type":"Point"}
}