{
  "type": "Feature",
  "properties": {
    "gn:admin1_code":"33.0",
    "gn:asciiname":"Chashchiny",
    "gn:country_code":"RU",
    "gn:dem":135,
    "gn:feature_class":"P",
    "gn:feature_code":"PPL",
    "gn:name":"Chashchiny",
    "gn:population":0,
    "gn:timezone":"Europe/Kirov",
    "iso:country":"RU",
    "name:rus_x_preferred":[
        "\u0427\u0430\u0449\u0438\u043d\u044b"
    ],
    "wof:name":"Chashchiny",
    "wof:placetype":"locality"
},
  "geometry": {"coordinates":[48.87012,58.3072],"type":"Point"}
}