{
  "type": "Feature",
  "properties": {
    "gn:admin1_code":"67",
    "gn:asciiname":"Shilo-Golitsyno",
    "gn:country_code":"RU",
    "gn:dem":156,
    "gn:feature_class":"P",
    "gn:feature_code":"PPL",
    "gn:name":"Shilo-Golitsyno",
    "gn:population":0,
    "gn:timezone":"Europe/Saratov",
    "iso:country":"RU",
    "name:eng_x_preferred":[
        "Shilo-Golitsyno"
    ],
    "name:nor_x_preferred":[
        "Sjilo-Golitsyno"
    ],
    "name:rus_x_preferred":[
        "\u0428\u0438\u043b\u043e-\u0413\u043e\u043b\u0438\u0446\u044b\u043d\u043e"
    ],
    "name:und_x_variant":[
        "Shilo-Galitsino",
        "Shilovo-Galitsino"
    ],
    "wof:name":"Shilo-Golitsyno",
    "wof:placetype":"locality"
},
  "geometry": {"coordinates":[43.7374,52.2233],"type":"Point"}
}