{
  "type": "Feature",
  "properties": {
    "gn:admin1_code":"77",
    "gn:asciiname":"Nivishchi",
    "gn:cc2":"RU",
    "gn:country_code":"RU",
    "gn:dem":245,
    "gn:feature_class":"P",
    "gn:feature_code":"PPL",
    "gn:name":"Nivishchi",
    "gn:population":0,
    "gn:timezone":"Europe/Moscow",
    "iso:country":"RU",
    "name:rus_x_preferred":[
        "\u041d\u0438\u0432\u0438\u0449\u0438"
    ],
    "name:und_x_variant":[
        "Nevishchi",
        "Nivishche",
        "Nivishchi"
    ],
    "wof:name":"Nivishchi",
    "wof:placetype":"locality"
},
  "geometry": {"coordinates":[32.43694,56.8675],"type":"Point"}
}