{
  "type": "Feature",
  "properties": {
    "gn:admin1_code":"25",
    "gn:asciiname":"Ovsorokskoy",
    "gn:country_code":"RU",
    "gn:dem":206,
    "gn:feature_class":"P",
    "gn:feature_code":"PPL",
    "gn:name":"Ovsorokskoy",
    "gn:population":0,
    "gn:timezone":"Europe/Moscow",
    "iso:country":"RU",
    "name:rus_x_preferred":[
        "\u041e\u0432\u0441\u043e\u0440\u043e\u043a\u0441\u043a\u043e\u0439"
    ],
    "name:und_x_variant":[
        "Ovsoradskiy",
        "Ovsorokskoy"
    ],
    "wof:name":"Ovsorokskoy",
    "wof:placetype":"locality"
},
  "geometry": {"coordinates":[35.00336,53.75052],"type":"Point"}
}