{
  "type": "Feature",
  "properties": {
    "gn:admin1_code":"7",
    "gn:asciiname":"Malyy Bugor",
    "gn:country_code":"RU",
    "gn:dem":-21,
    "gn:feature_class":"P",
    "gn:feature_code":"PPL",
    "gn:name":"Malyy Bugor",
    "gn:population":0,
    "gn:timezone":"Europe/Astrakhan",
    "iso:country":"RU",
    "name:rus_x_preferred":[
        "\u041c\u0430\u043b\u044b\u0439 \u0411\u0443\u0433\u043e\u0440"
    ],
    "wof:name":"Malyy Bugor",
    "wof:placetype":"locality"
},
  "geometry": {"coordinates":[48.48543,46.4357],"type":"Point"}
}