{
  "type": "Feature",
  "properties": {
    "gn:admin1_code":"10",
    "gn:asciiname":"Okop",
    "gn:country_code":"RU",
    "gn:dem":181,
    "gn:feature_class":"P",
    "gn:feature_code":"PPL",
    "gn:name":"Okop",
    "gn:population":0,
    "gn:timezone":"Europe/Moscow",
    "iso:country":"RU",
    "name:rus_x_preferred":[
        "\u041e\u043a\u043e\u043f"
    ],
    "name:und_x_variant":[
        "Okopskiy",
        "Okop"
    ],
    "wof:name":"Okop",
    "wof:placetype":"locality"
},
  "geometry": {"coordinates":[33.49048,53.18849],"type":"Point"}
}