{
  "type": "Feature",
  "properties": {
    "gn:admin1_code":"30",
    "gn:asciiname":"Slavyanka",
    "gn:country_code":"RU",
    "gn:dem":26,
    "gn:feature_class":"P",
    "gn:feature_code":"PPL",
    "gn:name":"Slavyanka",
    "gn:population":0,
    "gn:timezone":"Asia/Vladivostok",
    "iso:country":"RU",
    "name:eng_x_preferred":[
        "Slavyanka"
    ],
    "name:nor_x_preferred":[
        "Slavjanka"
    ],
    "name:rus_x_preferred":[
        "\u0421\u043b\u0430\u0432\u044f\u043d\u043a\u0430"
    ],
    "wof:name":"Slavyanka",
    "wof:placetype":"locality"
},
  "geometry": {"coordinates":[136.77440000000001,49.46875],"type":"Point"}
}