{
  "type": "Feature",
  "properties": {
    "gn:admin1_code":"84.0",
    "gn:asciiname":"Dryaglovskiy",
    "gn:country_code":"RU",
    "gn:dem":140,
    "gn:feature_class":"P",
    "gn:feature_code":"PPL",
    "gn:name":"Dryaglovskiy",
    "gn:population":0,
    "gn:timezone":"Europe/Volgograd",
    "iso:country":"RU",
    "name:rus_x_preferred":[
        "\u0414\u0440\u044f\u0433\u043b\u043e\u0432\u0441\u043a\u0438\u0439"
    ],
    "name:und_x_variant":[
        "\u0414\u0440\u044f\u0433\u043b\u043e\u0432\u0441\u043a\u0438\u0439"
    ],
    "wof:name":"Dryaglovskiy",
    "wof:placetype":"locality"
},
  "geometry": {"coordinates":[41.507,50.6586],"type":"Point"}
}