{
  "type": "Feature",
  "properties": {
    "gn:admin1_code":"51.0",
    "gn:asciiname":"Basy",
    "gn:country_code":"RU",
    "gn:dem":113,
    "gn:feature_class":"P",
    "gn:feature_code":"PPL",
    "gn:name":"Basy",
    "gn:population":0,
    "gn:timezone":"Europe/Moscow",
    "iso:country":"RU",
    "name:nor_x_preferred":[
        "Basy"
    ],
    "name:rus_x_preferred":[
        "\u0411\u0430\u0441\u044b"
    ],
    "wof:name":"Basy",
    "wof:placetype":"locality"
},
  "geometry": {"coordinates":[47.32068,57.89603],"type":"Point"}
}