{
  "type": "Feature",
  "properties": {
    "gn:admin1_code":"56.0",
    "gn:asciiname":"Berezuyevka",
    "gn:country_code":"RU",
    "gn:dem":212,
    "gn:feature_class":"P",
    "gn:feature_code":"PPL",
    "gn:name":"Berezuyevka",
    "gn:population":0,
    "gn:timezone":"Europe/Moscow",
    "iso:country":"RU",
    "name:nor_x_preferred":[
        "Berezujevka"
    ],
    "name:rus_x_preferred":[
        "\u0411\u0435\u0440\u0435\u0437\u0443\u0435\u0432\u043a\u0430"
    ],
    "wof:name":"Berezuyevka",
    "wof:placetype":"locality"
},
  "geometry": {"coordinates":[35.44580999999999,53.15071999999999],"type":"Point"}
}