{
  "type": "Feature",
  "properties": {
    "gn:admin1_code":"45.0",
    "gn:asciiname":"Aldiyarovo",
    "gn:country_code":"RU",
    "gn:dem":205,
    "gn:feature_class":"P",
    "gn:feature_code":"PPL",
    "gn:name":"Aldiyarovo",
    "gn:population":0,
    "gn:timezone":"Europe/Moscow",
    "iso:country":"RU",
    "name:nor_x_preferred":[
        "Aldijarovo"
    ],
    "name:rus_x_preferred":[
        "\u0410\u043b\u0434\u0438\u044f\u0440\u043e\u0432\u043e"
    ],
    "wof:name":"Aldiyarovo",
    "wof:placetype":"locality"
},
  "geometry": {"coordinates":[49.00111,56.93],"type":"Point"}
}