{
  "type": "Feature",
  "properties": {
    "gn:admin1_code":"84",
    "gn:asciiname":"Dubovskiy",
    "gn:country_code":"RU",
    "gn:dem":79,
    "gn:feature_class":"P",
    "gn:feature_code":"PPL",
    "gn:name":"Dubovskiy",
    "gn:population":0,
    "gn:timezone":"Europe/Volgograd",
    "iso:country":"RU",
    "name:rus_x_preferred":[
        "\u0414\u0443\u0431\u043e\u0432\u0441\u043a\u0438\u0439"
    ],
    "wof:name":"Dubovskiy",
    "wof:placetype":"locality"
},
  "geometry": {"coordinates":[41.989,50.5314],"type":"Point"}
}