{
  "type": "Feature",
  "properties": {
    "gn:admin1_code":"57.0",
    "gn:asciiname":"Dubasovo",
    "gn:country_code":"RU",
    "gn:dem":196,
    "gn:feature_class":"P",
    "gn:feature_code":"PPL",
    "gn:name":"Dubasovo",
    "gn:population":30,
    "gn:timezone":"Europe/Moscow",
    "iso:country":"RU",
    "name:rus_x_preferred":[
        "\u0414\u0443\u0431\u0430\u0441\u043e\u0432\u043e"
    ],
    "name:und_x_variant":[
        "\u0414\u0443\u0431\u0430\u0441\u043e\u0432\u043e"
    ],
    "wof:name":"Dubasovo",
    "wof:placetype":"locality",
    "wof:population":30
},
  "geometry": {"coordinates":[42.90781,53.54314],"type":"Point"}
}