{
  "type": "Feature",
  "properties": {
    "gn:admin1_code":"34",
    "gn:asciiname":"Kazhym",
    "gn:country_code":"RU",
    "gn:dem":135,
    "gn:feature_class":"P",
    "gn:feature_code":"PPL",
    "gn:name":"Kazhym",
    "gn:population":0,
    "gn:timezone":"Europe/Moscow",
    "iso:country":"RU",
    "name:eng_x_preferred":[
        "Kazhym"
    ],
    "name:nor_x_preferred":[
        "Kazjim"
    ],
    "name:rus_x_preferred":[
        "\u041a\u0430\u0436\u0438\u043c"
    ],
    "name:rus_x_variant":[
        "\u041a\u0430\u0436\u044b\u043c"
    ],
    "name:und_x_variant":[
        "Kazhimskiy",
        "Kazhim"
    ],
    "wof:name":"Kazhym",
    "wof:placetype":"locality"
},
  "geometry": {"coordinates":[51.54194,60.33438],"type":"Point"}
}