{
  "type": "Feature",
  "properties": {
    "gn:admin1_code":"38",
    "gn:asciiname":"Papay",
    "gn:country_code":"RU",
    "gn:dem":202,
    "gn:feature_class":"P",
    "gn:feature_code":"PPL",
    "gn:name":"Papay",
    "gn:population":0,
    "gn:timezone":"Europe/Moscow",
    "iso:country":"RU",
    "name:rus_x_preferred":[
        "\u041f\u0430\u043f\u0430\u0439"
    ],
    "name:und_x_variant":[
        "\u041f\u0430\u043f\u0430\u0439"
    ],
    "wof:name":"Papay",
    "wof:placetype":"locality"
},
  "geometry": {"coordinates":[38.41167,44.58528],"type":"Point"}
}