{
  "type": "Feature",
  "properties": {
    "gn:admin1_code":"67.0",
    "gn:asciiname":"Bukatovka",
    "gn:country_code":"RU",
    "gn:dem":21,
    "gn:feature_class":"P",
    "gn:feature_code":"PPL",
    "gn:name":"Bukatovka",
    "gn:population":0,
    "gn:timezone":"Europe/Saratov",
    "iso:country":"RU",
    "name:eng_x_preferred":[
        "Bukatovka"
    ],
    "name:nor_x_preferred":[
        "Bukatovka"
    ],
    "name:rus_x_preferred":[
        "\u0411\u0443\u043a\u0430\u0442\u043e\u0432\u043a\u0430"
    ],
    "name:und_x_variant":[
        "\u0411\u0443\u043a\u0430\u0442\u043e\u0432\u043a\u0430",
        "Bukatovka"
    ],
    "wof:name":"Bukatovka",
    "wof:placetype":"locality"
},
  "geometry": {"coordinates":[46.61,51.86194],"type":"Point"}
}