{
  "type": "Feature",
  "properties": {
    "gn:admin1_code":"34",
    "gn:asciiname":"Korol'ki",
    "gn:country_code":"RU",
    "gn:dem":151,
    "gn:feature_class":"P",
    "gn:feature_code":"PPL",
    "gn:name":"Korol\u2019ki",
    "gn:population":0,
    "gn:timezone":"Europe/Moscow",
    "iso:country":"RU",
    "name:rus_x_preferred":[
        "\u041a\u043e\u0440\u043e\u043b\u044c\u043a\u0438"
    ],
    "name:und_x_variant":[
        "Korolevskaya",
        "Korol\u2019ki"
    ],
    "wof:name":"Korol'ki",
    "wof:placetype":"locality"
},
  "geometry": {"coordinates":[49.58481,59.43716],"type":"Point"}
}