{
  "type": "Feature",
  "properties": {
    "gn:admin1_code":"85",
    "gn:asciiname":"Starina",
    "gn:country_code":"RU",
    "gn:dem":192,
    "gn:feature_class":"P",
    "gn:feature_code":"PPL",
    "gn:name":"Starina",
    "gn:population":0,
    "gn:timezone":"Europe/Moscow",
    "iso:country":"RU",
    "name:eng_x_preferred":[
        "Starina"
    ],
    "name:nor_x_preferred":[
        "Starina"
    ],
    "name:rus_x_preferred":[
        "\u0421\u0442\u0430\u0440\u0438\u043d\u0430"
    ],
    "name:und_x_variant":[
        "\u0421\u0442\u0430\u0440\u0438\u043d\u0430",
        "Starina"
    ],
    "wof:name":"Starina",
    "wof:placetype":"locality"
},
  "geometry": {"coordinates":[44.69079,59.59806999999999],"type":"Point"}
}