{
  "type": "Feature",
  "properties": {
    "gn:admin1_code":"88",
    "gn:asciiname":"Pozharovo",
    "gn:country_code":"RU",
    "gn:dem":153,
    "gn:feature_class":"P",
    "gn:feature_code":"PPL",
    "gn:name":"Pozharovo",
    "gn:population":0,
    "gn:timezone":"Europe/Moscow",
    "iso:country":"RU",
    "name:rus_x_preferred":[
        "\u041f\u043e\u0436\u0430\u0440\u043e\u0432\u043e"
    ],
    "name:und_x_variant":[
        "\u041f\u043e\u0436\u0430\u0440\u043e\u0432\u043e"
    ],
    "wof:name":"Pozharovo",
    "wof:placetype":"locality"
},
  "geometry": {"coordinates":[40.08333,57.88333000000001],"type":"Point"}
}