{
  "type": "Feature",
  "properties": {
    "gn:admin1_code":"69",
    "gn:asciiname":"Gorokhova",
    "gn:country_code":"RU",
    "gn:dem":184,
    "gn:feature_class":"P",
    "gn:feature_code":"PPL",
    "gn:name":"Gorokhova",
    "gn:population":0,
    "gn:timezone":"Europe/Moscow",
    "iso:country":"RU",
    "name:rus_x_preferred":[
        "\u0413\u043e\u0440\u043e\u0445\u043e\u0432\u0430"
    ],
    "name:und_x_variant":[
        "\u0413\u043e\u0440\u043e\u0445\u043e\u0432\u0430"
    ],
    "wof:name":"Gorokhova",
    "wof:placetype":"locality"
},
  "geometry": {"coordinates":[31.74292,54.71516],"type":"Point"}
}