{
  "type": "Feature",
  "properties": {
    "gn:admin1_code":"57",
    "gn:asciiname":"Novyy Svet",
    "gn:country_code":"RU",
    "gn:dem":276,
    "gn:feature_class":"P",
    "gn:feature_code":"PPL",
    "gn:name":"Novyy Svet",
    "gn:population":0,
    "gn:timezone":"Europe/Moscow",
    "iso:country":"RU",
    "name:rus_x_preferred":[
        "\u041d\u043e\u0432\u044b\u0439 \u0421\u0432\u0435\u0442"
    ],
    "name:und_x_variant":[
        "Novy Svet",
        "Novyy Svet"
    ],
    "wof:name":"Novyy Svet",
    "wof:placetype":"locality"
},
  "geometry": {"coordinates":[45.94067,53.33819],"type":"Point"}
}