{
  "type": "Feature",
  "properties": {
    "gn:admin1_code":"25.0",
    "gn:asciiname":"Buda",
    "gn:country_code":"RU",
    "gn:dem":227,
    "gn:feature_class":"P",
    "gn:feature_code":"PPL",
    "gn:name":"Buda",
    "gn:population":0,
    "gn:timezone":"Europe/Moscow",
    "iso:country":"RU",
    "name:eng_x_preferred":[
        "Buda"
    ],
    "name:nor_x_preferred":[
        "Buda"
    ],
    "name:rus_x_preferred":[
        "\u0411\u0443\u0434\u0430"
    ],
    "name:und_x_variant":[
        "\u0411\u0443\u0434\u0430",
        "Buda"
    ],
    "wof:name":"Buda",
    "wof:placetype":"locality"
},
  "geometry": {"coordinates":[34.46389,54.16806],"type":"Point"}
}