{
  "type": "Feature",
  "properties": {
    "gn:admin1_code":"28",
    "gn:asciiname":"Nyukhcha",
    "gn:country_code":"RU",
    "gn:dem":21,
    "gn:feature_class":"P",
    "gn:feature_code":"PPL",
    "gn:name":"Nyukhcha",
    "gn:population":0,
    "gn:timezone":"Europe/Moscow",
    "iso:country":"RU",
    "name:eng_x_preferred":[
        "Nyukhcha"
    ],
    "name:fin_x_preferred":[
        "Njuht\u0161a"
    ],
    "name:nor_x_preferred":[
        "Njukhtsja"
    ],
    "name:rus_x_preferred":[
        "\u041d\u044e\u0445\u0447\u0430"
    ],
    "name:und_x_variant":[
        "Selo Nyukhcha",
        "Njuhtsa",
        "Nyukhotskoye",
        "Njuchtsha",
        "\u041d\u044e\u0445\u0447\u0430",
        "Nyukhcha"
    ],
    "wof:name":"Nyukhcha",
    "wof:placetype":"locality"
},
  "geometry": {"coordinates":[36.25386,63.9241],"type":"Point"}
}