{
  "type": "Feature",
  "properties": {
    "gn:admin1_code":"44",
    "gn:asciiname":"Kotel",
    "gn:country_code":"RU",
    "gn:dem":461,
    "gn:feature_class":"P",
    "gn:feature_code":"PPL",
    "gn:name":"Kotel",
    "gn:population":0,
    "gn:timezone":"Asia/Magadan",
    "iso:country":"RU",
    "name:rus_x_preferred":[
        "\u041a\u043e\u0442\u0435\u043b"
    ],
    "name:und_x_variant":[
        "\u041a\u043e\u0442\u0435\u043b"
    ],
    "wof:name":"Kotel",
    "wof:placetype":"locality"
},
  "geometry": {"coordinates":[152.44999999999999,62.26667],"type":"Point"}
}