{
  "type": "Feature",
  "properties": {
    "gn:admin1_code":"44",
    "gn:asciiname":"Kotel",
    "gn:country_code":"RU",
    "gn:dem":461,
    "gn:feature_class":"P",
    "gn:feature_code":"PPL",
    "gn:name":"Kotel",
    "gn:population":0,
    "gn:timezone":"Asia/Magadan",
    "iso:country":"RU",
    "name:bar_x_preferred":[
        "Kotel"
    ],
    "name:bos_x_preferred":[
        "Kotel"
    ],
    "name:ceb_x_preferred":[
        "Kotel"
    ],
    "name:ces_x_preferred":[
        "Kotel"
    ],
    "name:deu_x_preferred":[
        "Kotel"
    ],
    "name:fra_x_preferred":[
        "Kotel"
    ],
    "name:heb_x_preferred":[
        "\u05db\u05d5\u05ea\u05dc"
    ],
    "name:ita_x_preferred":[
        "Kotel"
    ],
    "name:rus_x_preferred":[
        "\u041a\u043e\u0442\u0435\u043b"
    ],
    "name:slv_x_preferred":[
        "Kotel"
    ],
    "name:swe_x_preferred":[
        "Kotel"
    ],
    "name:vie_x_preferred":[
        "Kotel"
    ],
    "wof:name":"Kotel",
    "wof:placetype":"locality"
},
  "geometry": {"coordinates":[152.44999999999999,62.26667],"type":"Point"}
}