{
  "type": "Feature",
  "properties": {
    "gn:admin1_code":"52",
    "gn:asciiname":"Mshaga",
    "gn:country_code":"RU",
    "gn:dem":26,
    "gn:feature_class":"P",
    "gn:feature_code":"PPL",
    "gn:name":"Mshaga",
    "gn:population":0,
    "gn:timezone":"Europe/Moscow",
    "iso:country":"RU",
    "name:rus_x_preferred":[
        "\u041c\u0448\u0430\u0433\u0430"
    ],
    "wof:name":"Mshaga",
    "wof:placetype":"locality"
},
  "geometry": {"coordinates":[31.55059,58.53556],"type":"Point"}
}