{
  "type": "Feature",
  "properties": {
    "gn:admin1_code":"91",
    "gn:asciiname":"Kumasinka",
    "gn:country_code":"RU",
    "gn:dem":460,
    "gn:feature_class":"P",
    "gn:feature_code":"PPL",
    "gn:name":"Kumasinka",
    "gn:population":0,
    "gn:timezone":"Asia/Krasnoyarsk",
    "iso:country":"RU",
    "name:rus_x_preferred":[
        "\u041a\u0443\u043c\u0430\u0441\u0438\u043d\u043a\u0430"
    ],
    "wof:name":"Kumasinka",
    "wof:placetype":"locality"
},
  "geometry": {"coordinates":[94.25,55.35],"type":"Point"}
}