{
  "type": "Feature",
  "properties": {
    "gn:admin1_code":"93",
    "gn:asciiname":"Alashir",
    "gn:country_code":"RU",
    "gn:dem":689,
    "gn:feature_class":"P",
    "gn:feature_code":"PPL",
    "gn:name":"Alashir",
    "gn:population":0,
    "gn:timezone":"Asia/Chita",
    "iso:country":"RU",
    "name:nor_x_preferred":[
        "Alasjir"
    ],
    "name:rus_x_preferred":[
        "\u0410\u043b\u0430\u0448\u0438\u0440"
    ],
    "name:und_x_variant":[
        "Alishary",
        "Alashir"
    ],
    "wof:name":"Alashir",
    "wof:placetype":"locality"
},
  "geometry": {"coordinates":[120.13333,51.95],"type":"Point"}
}