{
  "type": "Feature",
  "properties": {
    "gn:admin1_code":"10.0",
    "gn:asciiname":"Chernavka",
    "gn:country_code":"RU",
    "gn:dem":165,
    "gn:feature_class":"P",
    "gn:feature_code":"PPL",
    "gn:name":"Chernavka",
    "gn:population":0,
    "gn:timezone":"Europe/Moscow",
    "iso:country":"RU",
    "name:rus_x_preferred":[
        "\u0427\u0435\u0440\u043d\u0430\u0432\u043a\u0430"
    ],
    "name:und_x_variant":[
        "\u0427\u0435\u0440\u043d\u0430\u0432\u043a\u0430"
    ],
    "wof:name":"Chernavka",
    "wof:placetype":"locality"
},
  "geometry": {"coordinates":[32.76459000000001,53.41008000000001],"type":"Point"}
}