{
  "type": "Feature",
  "properties": {
    "gn:admin1_code":"33",
    "gn:asciiname":"Sovunyata",
    "gn:country_code":"RU",
    "gn:dem":169,
    "gn:feature_class":"P",
    "gn:feature_code":"PPL",
    "gn:name":"Sovunyata",
    "gn:population":0,
    "gn:timezone":"Europe/Kirov",
    "iso:country":"RU",
    "name:rus_x_preferred":[
        "\u0421\u043e\u0432\u0443\u043d\u044f\u0442\u0430"
    ],
    "wof:name":"Sovunyata",
    "wof:placetype":"locality"
},
  "geometry": {"coordinates":[50.5066,59.0103],"type":"Point"}
}