{
  "type": "Feature",
  "properties": {
    "gn:admin1_code":"73",
    "gn:asciiname":"Tatarskiy Shugan",
    "gn:country_code":"RU",
    "gn:dem":168,
    "gn:feature_class":"P",
    "gn:feature_code":"PPL",
    "gn:name":"Tatarskiy Shugan",
    "gn:population":0,
    "gn:timezone":"Europe/Moscow",
    "iso:country":"RU",
    "name:eng_x_preferred":[
        "Tatarskiy Shugan"
    ],
    "name:nor_x_preferred":[
        "Tatarskij Sjugan"
    ],
    "name:rus_x_preferred":[
        "\u0422\u0430\u0442\u0430\u0440\u0441\u043a\u0438\u0439 \u0428\u0443\u0433\u0430\u043d"
    ],
    "name:und_x_variant":[
        "Ushugan"
    ],
    "wof:name":"Tatarskiy Shugan",
    "wof:placetype":"locality"
},
  "geometry": {"coordinates":[53.02721999999999,55.14278],"type":"Point"}
}