{
  "type": "Feature",
  "properties": {
    "gn:admin1_code":"60",
    "gn:asciiname":"Troshnevka",
    "gn:country_code":"RU",
    "gn:dem":203,
    "gn:feature_class":"P",
    "gn:feature_code":"PPL",
    "gn:name":"Troshn\u00ebvka",
    "gn:population":0,
    "gn:timezone":"Europe/Moscow",
    "iso:country":"RU",
    "name:rus_x_preferred":[
        "\u0422\u0440\u043e\u0448\u043d\u0451\u0432\u043a\u0430"
    ],
    "name:und_x_variant":[
        "Troshn\u00ebvka"
    ],
    "wof:name":"Troshnevka",
    "wof:placetype":"locality"
},
  "geometry": {"coordinates":[29.3844,56.7696],"type":"Point"}
}