{
  "type": "Feature",
  "properties": {
    "gn:admin1_code":"53",
    "gn:asciiname":"Gruzdevka",
    "gn:country_code":"RU",
    "gn:dem":148,
    "gn:feature_class":"P",
    "gn:feature_code":"PPL",
    "gn:name":"Gruzdevka",
    "gn:population":0,
    "gn:timezone":"Asia/Novosibirsk",
    "iso:country":"RU",
    "name:eng_x_preferred":[
        "Gruzdevka"
    ],
    "name:nor_x_preferred":[
        "Gruzdevka"
    ],
    "name:rus_x_preferred":[
        "\u0413\u0440\u0443\u0437\u0434\u0435\u0432\u043a\u0430"
    ],
    "wof:name":"Gruzdevka",
    "wof:placetype":"locality"
},
  "geometry": {"coordinates":[80.00166999999998,55.25556],"type":"Point"}
}