{
  "type": "Feature",
  "properties": {
    "gn:admin1_code":"77",
    "gn:asciiname":"Vlasovka",
    "gn:country_code":"RU",
    "gn:dem":287,
    "gn:feature_class":"P",
    "gn:feature_code":"PPL",
    "gn:name":"Vlasovka",
    "gn:population":0,
    "gn:timezone":"Europe/Moscow",
    "iso:country":"RU",
    "wof:name":"Vlasovka",
    "wof:placetype":"locality"
},
  "geometry": {"coordinates":[33.29222,56.52861],"type":"Point"}
}