{
  "type": "Feature",
  "properties": {
    "gn:admin1_code":"29",
    "gn:asciiname":"Burovka",
    "gn:country_code":"RU",
    "gn:dem":370,
    "gn:feature_class":"P",
    "gn:feature_code":"PPL",
    "gn:name":"Burovka",
    "gn:population":0,
    "gn:timezone":"Asia/Novokuznetsk",
    "iso:country":"RU",
    "name:rus_x_preferred":[
        "\u0411\u0443\u0440\u043e\u0432\u043a\u0430"
    ],
    "name:und_x_variant":[
        "\u0411\u0443\u0440\u043e\u0432\u043a\u0430"
    ],
    "wof:name":"Burovka",
    "wof:placetype":"locality"
},
  "geometry": {"coordinates":[87.3246,53.3961],"type":"Point"}
}