{
  "type": "Feature",
  "properties": {
    "gn:admin1_code":"52",
    "gn:asciiname":"Sable",
    "gn:country_code":"RU",
    "gn:dem":49,
    "gn:feature_class":"P",
    "gn:feature_code":"PPL",
    "gn:name":"Sable",
    "gn:population":0,
    "gn:timezone":"Europe/Moscow",
    "iso:country":"RU",
    "name:rus_x_preferred":[
        "\u0421\u0430\u0431\u043b\u0435"
    ],
    "name:und_x_variant":[
        "\u0421\u0430\u0431\u043b\u0435"
    ],
    "wof:name":"Sable",
    "wof:placetype":"locality"
},
  "geometry": {"coordinates":[30.61309,58.55989],"type":"Point"}
}