{
  "type": "Feature",
  "properties": {
    "gn:admin1_code":"88",
    "gn:asciiname":"Osovyye",
    "gn:country_code":"RU",
    "gn:dem":89,
    "gn:feature_class":"P",
    "gn:feature_code":"PPL",
    "gn:name":"Osovyye",
    "gn:population":0,
    "gn:timezone":"Europe/Moscow",
    "iso:country":"RU",
    "name:rus_x_preferred":[
        "\u041e\u0441\u043e\u0432\u044b\u0435"
    ],
    "wof:name":"Osovyye",
    "wof:placetype":"locality"
},
  "geometry": {"coordinates":[39.7187,57.6181],"type":"Point"}
}