{
  "type": "Feature",
  "properties": {
    "gn:admin1_code":"4",
    "gn:asciiname":"Degtyarka",
    "gn:country_code":"RU",
    "gn:dem":230,
    "gn:feature_class":"P",
    "gn:feature_code":"PPL",
    "gn:name":"Degtyarka",
    "gn:population":0,
    "gn:timezone":"Asia/Barnaul",
    "iso:country":"RU",
    "name:che_x_preferred":[
        "\u0414\u0435\u0433\u0442\u044f\u0440\u043a\u0430"
    ],
    "name:rus_x_preferred":[
        "\u0414\u0435\u0433\u0442\u044f\u0440\u043a\u0430"
    ],
    "name:und_x_variant":[
        "\u0414\u0435\u0433\u0442\u044f\u0440\u043a\u0430"
    ],
    "wof:name":"Degtyarka",
    "wof:placetype":"locality"
},
  "geometry": {"coordinates":[82.40000000000001,52.86666999999999],"type":"Point"}
}