{
  "type": "Feature",
  "properties": {
    "gn:country":"RU",
    "gn:fcode":"PPL",
    "gn:population":0,
    "iso:country":"RU",
    "name:eng_x_preferred":[
        "Borovoye"
    ],
    "name:nor_x_preferred":[
        "Borovoje"
    ],
    "name:rus_x_preferred":[
        "\u0411\u043e\u0440\u043e\u0432\u043e\u0435"
    ],
    "qs:name":"Borovoye",
    "qs:name_adm0":"Russia",
    "qs:name_adm1":"Novosibirsk Oblast",
    "qs:photos_9r":0,
    "qs:photos_sr":0,
    "qs:placetype":"Town",
    "qs:pop_sr":"0",
    "wof:name":"Borovoye",
    "wof:placetype":"locality",
    "wof:population":0
},
  "geometry": {"coordinates":[82.63979999999999,54.6918],"type":"Point"}
}