{
  "type": "Feature",
  "properties": {
    "gn:admin1_code":"63",
    "gn:asciiname":"Batamay",
    "gn:country_code":"RU",
    "gn:dem":83,
    "gn:feature_class":"P",
    "gn:feature_code":"PPL",
    "gn:name":"Batamay",
    "gn:population":0,
    "gn:timezone":"Asia/Yakutsk",
    "iso:country":"RU",
    "name:nor_x_preferred":[
        "Batamaj"
    ],
    "name:rus_x_preferred":[
        "\u0411\u0430\u0442\u0430\u043c\u0430\u0439"
    ],
    "name:und_x_variant":[
        "Aldan",
        "Ust Aldansk",
        "Ust\u2019-Aldan",
        "Batamay"
    ],
    "wof:name":"Batamay",
    "wof:placetype":"locality"
},
  "geometry": {"coordinates":[129.41866000000002,63.52573],"type":"Point"}
}