{
  "type": "Feature",
  "properties": {
    "gn:admin1_code":"61",
    "gn:asciiname":"Novosal'skiy",
    "gn:country_code":"RU",
    "gn:dem":52,
    "gn:feature_class":"P",
    "gn:feature_code":"PPL",
    "gn:name":"Novosal\u2019skiy",
    "gn:population":0,
    "gn:timezone":"Europe/Moscow",
    "iso:country":"RU",
    "name:eng_x_preferred":[
        "Novosal'skiy"
    ],
    "name:nor_x_preferred":[
        "Novosalskij"
    ],
    "name:rus_x_preferred":[
        "\u041d\u043e\u0432\u043e\u0441\u0430\u043b\u044c\u0441\u043a\u0438\u0439"
    ],
    "name:und_x_variant":[
        "Prishib",
        "\u041d\u043e\u0432\u043e\u0441\u0430\u043b\u044c\u0441\u043a\u0438\u0439",
        "Novosal\u2019skiy"
    ],
    "wof:name":"Novosal'skiy",
    "wof:placetype":"locality"
},
  "geometry": {"coordinates":[43.2164,47.3031],"type":"Point"}
}