{
  "type": "Feature",
  "properties": {
    "gn:country":"RU",
    "gn:fcode":"PPL",
    "gn:pop":15241,
    "iso:country":"RU",
    "name:eng_x_preferred":[
        "Novosilikatnyy"
    ],
    "name:nor_x_preferred":[
        "Novosilikatnyj"
    ],
    "name:rus_x_preferred":[
        "\u041d\u043e\u0432\u043e\u0441\u0438\u043b\u0438\u043a\u0430\u0442\u043d\u044b\u0439"
    ],
    "name:unk_x_variant":[
        "Novosilikatnyy"
    ],
    "qs:name":"Novosilikatniy",
    "qs:name_adm0":"Russia",
    "qs:name_adm1":"Altai Krai",
    "qs:photos_9r":0,
    "qs:photos_sr":0,
    "qs:placetype":"Town",
    "qs:pop_sr":"6",
    "wof:name":"Novosilikatniy",
    "wof:placetype":"locality",
    "wof:population":15241
},
  "geometry": {"coordinates":[83.62389,53.30972],"type":"Point"}
}