{
  "type": "Feature",
  "properties": {
    "gn:admin1_code":"71",
    "gn:asciiname":"Kadochnikovo",
    "gn:country_code":"RU",
    "gn:dem":287,
    "gn:feature_class":"P",
    "gn:feature_code":"PPL",
    "gn:name":"Kadochnikovo",
    "gn:population":0,
    "gn:timezone":"Asia/Yekaterinburg",
    "iso:country":"RU",
    "name:rus_x_preferred":[
        "\u041a\u0430\u0434\u043e\u0447\u043d\u0438\u043a\u043e\u0432\u043e"
    ],
    "name:und_x_variant":[
        "Yezhova",
        "Kadochnikova",
        "Kadochnikovo",
        "\u041a\u0430\u0434\u043e\u0447\u043d\u0438\u043a\u043e\u0432\u043e"
    ],
    "wof:name":"Kadochnikovo",
    "wof:placetype":"locality"
},
  "geometry": {"coordinates":[58.05585,56.48118],"type":"Point"}
}