{
  "type": "Feature",
  "properties": {
    "gn:admin1_code":"33",
    "gn:asciiname":"Makarovskaya",
    "gn:country_code":"RU",
    "gn:dem":166,
    "gn:feature_class":"P",
    "gn:feature_code":"PPL",
    "gn:name":"Makarovskaya",
    "gn:population":0,
    "gn:timezone":"Europe/Kirov",
    "iso:country":"RU",
    "name:rus_x_preferred":[
        "\u041c\u0430\u043a\u0430\u0440\u043e\u0432\u0441\u043a\u0430\u044f"
    ],
    "name:und_x_variant":[
        "\u041c\u0430\u043a\u0430\u0440\u043e\u0432\u0441\u043a\u0430\u044f"
    ],
    "wof:name":"Makarovskaya",
    "wof:placetype":"locality"
},
  "geometry": {"coordinates":[52.48333,59.56667],"type":"Point"}
}