{
  "type": "Feature",
  "properties": {
    "gn:admin1_code":"80",
    "gn:asciiname":"Kekoran",
    "gn:country_code":"RU",
    "gn:dem":187,
    "gn:feature_class":"P",
    "gn:feature_code":"PPL",
    "gn:name":"Kekoran",
    "gn:population":0,
    "gn:timezone":"Europe/Samara",
    "iso:country":"RU",
    "name:eng_x_preferred":[
        "Kekoran"
    ],
    "name:nor_x_preferred":[
        "Kekoran"
    ],
    "name:rus_x_preferred":[
        "\u041a\u0435\u043a\u043e\u0440\u0430\u043d"
    ],
    "name:und_x_variant":[
        "\u041a\u0435\u043a\u043e\u0440\u0430\u043d",
        "Kekoran"
    ],
    "wof:name":"Kekoran",
    "wof:placetype":"locality"
},
  "geometry": {"coordinates":[52.9789,57.21135],"type":"Point"}
}