{
  "type": "Feature",
  "properties": {
    "gn:admin1_code":"77",
    "gn:asciiname":"Vorsino",
    "gn:country_code":"RU",
    "gn:dem":157,
    "gn:feature_class":"P",
    "gn:feature_code":"PPL",
    "gn:name":"Vorsino",
    "gn:population":0,
    "gn:timezone":"Europe/Moscow",
    "iso:country":"RU",
    "name:rus_x_preferred":[
        "\u0412\u043e\u0440\u0441\u0438\u043d\u043e"
    ],
    "wof:name":"Vorsino",
    "wof:placetype":"locality"
},
  "geometry": {"coordinates":[36.4169,58.4234],"type":"Point"}
}