{
  "type": "Feature",
  "properties": {
    "gn:admin1_code":"84",
    "gn:asciiname":"Lestyukhin",
    "gn:country_code":"RU",
    "gn:dem":93,
    "gn:feature_class":"P",
    "gn:feature_code":"PPL",
    "gn:name":"Lestyukhin",
    "gn:population":0,
    "gn:timezone":"Europe/Volgograd",
    "iso:country":"RU",
    "name:eng_x_preferred":[
        "Lestyukhin"
    ],
    "name:nor_x_preferred":[
        "Lestjukhin"
    ],
    "name:rus_x_preferred":[
        "\u041b\u0435\u0441\u0442\u044e\u0445\u0438\u043d"
    ],
    "wof:name":"Lestyukhin",
    "wof:placetype":"locality"
},
  "geometry": {"coordinates":[42.9587,50.6652],"type":"Point"}
}