{
  "type": "Feature",
  "properties": {
    "gn:admin1_code":"61",
    "gn:asciiname":"Zhatva",
    "gn:country_code":"RU",
    "gn:dem":78,
    "gn:feature_class":"P",
    "gn:feature_code":"PPL",
    "gn:name":"Zhatva",
    "gn:population":0,
    "gn:timezone":"Europe/Moscow",
    "iso:country":"RU",
    "wof:name":"Zhatva",
    "wof:placetype":"locality"
},
  "geometry": {"coordinates":[38.7853,47.43851],"type":"Point"}
}