{
  "type": "Feature",
  "properties": {
    "gn:admin1_code":"8.0",
    "gn:asciiname":"Araslanovo",
    "gn:country_code":"RU",
    "gn:dem":173,
    "gn:feature_class":"P",
    "gn:feature_code":"PPL",
    "gn:name":"Araslanovo",
    "gn:population":0,
    "gn:timezone":"Asia/Yekaterinburg",
    "iso:country":"RU",
    "name:nor_x_preferred":[
        "Araslanovo"
    ],
    "name:rus_x_preferred":[
        "\u0410\u0440\u0430\u0441\u043b\u0430\u043d\u043e\u0432\u043e"
    ],
    "name:und_x_variant":[
        "Arslanovskiy"
    ],
    "wof:name":"Araslanovo",
    "wof:placetype":"locality"
},
  "geometry": {"coordinates":[56.10126,53.01829],"type":"Point"}
}