{
  "type": "Feature",
  "properties": {
    "gn:admin1_code":"84",
    "gn:asciiname":"Novosel'skiy",
    "gn:country_code":"RU",
    "gn:dem":155,
    "gn:feature_class":"P",
    "gn:feature_code":"PPL",
    "gn:name":"Novosel\u2019skiy",
    "gn:population":0,
    "gn:timezone":"Europe/Volgograd",
    "iso:country":"RU",
    "name:eng_x_preferred":[
        "Novosel'skiy"
    ],
    "name:nor_x_preferred":[
        "Novoselskij"
    ],
    "name:rus_x_preferred":[
        "\u041d\u043e\u0432\u043e\u0441\u0435\u043b\u044c\u0441\u043a\u0438\u0439"
    ],
    "name:und_x_variant":[
        "Neygeymovskiy",
        "Rote-Fane",
        "Neygemovskiy",
        "\u041d\u043e\u0432\u043e\u0441\u0435\u043b\u044c\u0441\u043a\u0438\u0439",
        "Novosel\u2019skiy"
    ],
    "wof:name":"Novosel'skiy",
    "wof:placetype":"locality"
},
  "geometry": {"coordinates":[42.9846,50.3732],"type":"Point"}
}