{
  "type": "Feature",
  "properties": {
    "gn:admin1_code":"75",
    "gn:asciiname":"Rogalevo",
    "gn:country_code":"RU",
    "gn:dem":102,
    "gn:feature_class":"P",
    "gn:feature_code":"PPL",
    "gn:name":"Rogal\u00ebvo",
    "gn:population":0,
    "gn:timezone":"Asia/Tomsk",
    "iso:country":"RU",
    "name:eng_x_preferred":[
        "Rogal\u00ebvo"
    ],
    "name:nor_x_preferred":[
        "Rogalevo"
    ],
    "name:rus_x_preferred":[
        "\u0420\u043e\u0433\u0430\u043b\u0435\u0432\u043e"
    ],
    "name:rus_x_variant":[
        "\u0420\u043e\u0433\u0430\u043b\u0451\u0432\u043e"
    ],
    "name:und_x_variant":[
        "Rogal\u00ebvo",
        "\u0420\u043e\u0433\u0430\u043b\u0451\u0432\u043e"
    ],
    "wof:name":"Rogalevo",
    "wof:placetype":"locality"
},
  "geometry": {"coordinates":[79.61124000000002,57.49536],"type":"Point"}
}