{
  "type": "Feature",
  "properties": {
    "gn:admin1_code":"38",
    "gn:asciiname":"Podkugoyeyskiy",
    "gn:country_code":"RU",
    "gn:dem":26,
    "gn:feature_class":"P",
    "gn:feature_code":"PPL",
    "gn:name":"Podkugoyeyskiy",
    "gn:population":0,
    "gn:timezone":"Europe/Moscow",
    "iso:country":"RU",
    "name:und_x_variant":[
        "\u041f\u043e\u0434\u043a\u0443\u0433\u043e\u0435\u0439\u0441\u043a\u0438\u0439"
    ],
    "wof:name":"Podkugoyeyskiy",
    "wof:placetype":"locality"
},
  "geometry": {"coordinates":[40.03905,46.53821],"type":"Point"}
}