{
  "type": "Feature",
  "properties": {
    "gn:admin1_code":"88",
    "gn:asciiname":"Kharnevo",
    "gn:country_code":"RU",
    "gn:dem":119,
    "gn:feature_class":"P",
    "gn:feature_code":"PPL",
    "gn:name":"Kharn\u00ebvo",
    "gn:population":0,
    "gn:timezone":"Europe/Moscow",
    "iso:country":"RU",
    "name:rus_x_preferred":[
        "\u0425\u0430\u0440\u043d\u0451\u0432\u043e"
    ],
    "name:und_x_variant":[
        "Kharn\u00ebvo"
    ],
    "wof:name":"Kharnevo",
    "wof:placetype":"locality"
},
  "geometry": {"coordinates":[39.74046,57.419],"type":"Point"}
}