{
  "type": "Feature",
  "properties": {
    "gn:admin1_code":"70.0",
    "gn:asciiname":"Burgun-Madzhary",
    "gn:cc2":"RU",
    "gn:country_code":"RU",
    "gn:dem":85,
    "gn:feature_class":"P",
    "gn:feature_code":"PPL",
    "gn:name":"Burgun-Madzhary",
    "gn:population":0,
    "gn:timezone":"Europe/Moscow",
    "iso:country":"RU",
    "name:eng_x_preferred":[
        "Burgun-Madzhary"
    ],
    "name:nor_x_preferred":[
        "Burgun-Madzjary"
    ],
    "name:rus_x_preferred":[
        "\u0411\u0443\u0440\u0433\u0443\u043d-\u041c\u0430\u0434\u0436\u0430\u0440\u044b"
    ],
    "name:und_x_variant":[
        "Burgan-Madzhary"
    ],
    "wof:name":"Burgun-Madzhary",
    "wof:placetype":"locality"
},
  "geometry": {"coordinates":[44.48222,44.82889],"type":"Point"}
}