{
  "type": "Feature",
  "properties": {
    "gn:admin1_code":"13",
    "gn:asciiname":"Urazbayeva",
    "gn:country_code":"RU",
    "gn:dem":300,
    "gn:feature_class":"P",
    "gn:feature_code":"PPL",
    "gn:name":"Urazbayeva",
    "gn:population":0,
    "gn:timezone":"Asia/Yekaterinburg",
    "iso:country":"RU",
    "name:eng_x_preferred":[
        "Urazbayeva"
    ],
    "name:nor_x_preferred":[
        "Urazbajeva"
    ],
    "name:rus_x_preferred":[
        "\u0423\u0440\u0430\u0437\u0431\u0430\u0435\u0432\u0430"
    ],
    "name:rus_x_variant":[
        "\u0423\u0440\u0437\u0430\u0431\u0430\u0435\u0432\u0430"
    ],
    "wof:name":"Urazbayeva",
    "wof:placetype":"locality"
},
  "geometry": {"coordinates":[60.34278000000001,55.18361],"type":"Point"}
}