{
  "type": "Feature",
  "properties": {
    "gn:admin1_code":"43",
    "gn:asciiname":"Lisogradka",
    "gn:country_code":"RU",
    "gn:dem":126,
    "gn:feature_class":"P",
    "gn:feature_code":"PPL",
    "gn:name":"Lisogradka",
    "gn:population":0,
    "gn:timezone":"Europe/Moscow",
    "iso:country":"RU",
    "name:rus_x_preferred":[
        "\u041b\u0438\u0441\u043e\u0433\u0440\u0430\u0434\u043a\u0430"
    ],
    "name:und_x_variant":[
        "Lesogradskaya",
        "Lisogradka"
    ],
    "wof:name":"Lisogradka",
    "wof:placetype":"locality"
},
  "geometry": {"coordinates":[39.75894,53.52129],"type":"Point"}
}