{
  "type": "Feature",
  "properties": {
    "gn:admin1_code":"69.0",
    "gn:asciiname":"Aristovo",
    "gn:country_code":"RU",
    "gn:dem":202,
    "gn:feature_class":"P",
    "gn:feature_code":"PPL",
    "gn:name":"Aristovo",
    "gn:population":0,
    "gn:timezone":"Europe/Moscow",
    "iso:country":"RU",
    "name:nor_x_preferred":[
        "Aristovo"
    ],
    "name:rus_x_preferred":[
        "\u0410\u0440\u0438\u0441\u0442\u043e\u0432\u043e"
    ],
    "name:und_x_variant":[
        "Arestovo"
    ],
    "wof:name":"Aristovo",
    "wof:placetype":"locality"
},
  "geometry": {"coordinates":[34.40048,55.97666],"type":"Point"}
}