{
  "type": "Feature",
  "properties": {
    "gn:admin1_code":"77",
    "gn:asciiname":"Sukhanovo",
    "gn:country_code":"RU",
    "gn:dem":136,
    "gn:feature_class":"P",
    "gn:feature_code":"PPL",
    "gn:name":"Sukhanovo",
    "gn:population":0,
    "gn:timezone":"Europe/Moscow",
    "iso:country":"RU",
    "name:rus_x_preferred":[
        "\u0421\u0443\u0445\u0430\u043d\u043e\u0432\u043e"
    ],
    "name:und_x_variant":[
        "\u0421\u0443\u0445\u0430\u043d\u043e\u0432\u043e"
    ],
    "wof:name":"Sukhanovo",
    "wof:placetype":"locality"
},
  "geometry": {"coordinates":[37.65,57.51667],"type":"Point"}
}