{
  "type": "Feature",
  "properties": {
    "gn:admin1_code":"42",
    "gn:asciiname":"Malaya Bronnitsa",
    "gn:country_code":"RU",
    "gn:dem":47,
    "gn:feature_class":"P",
    "gn:feature_code":"PPL",
    "gn:name":"Malaya Bronnitsa",
    "gn:population":0,
    "gn:timezone":"Europe/Moscow",
    "iso:country":"RU",
    "name:rus_x_preferred":[
        "\u041c\u0430\u043b\u0430\u044f \u0411\u0440\u043e\u043d\u043d\u0438\u0446\u0430"
    ],
    "name:und_x_variant":[
        "\u041c\u0430\u043b\u0430\u044f \u0411\u0440\u043e\u043d\u043d\u0438\u0446\u0430"
    ],
    "wof:name":"Malaya Bronnitsa",
    "wof:placetype":"locality"
},
  "geometry": {"coordinates":[31.18333,59.18333000000001],"type":"Point"}
}