{
  "type": "Feature",
  "properties": {
    "gn:admin1_code":"85",
    "gn:asciiname":"Karpovo",
    "gn:country_code":"RU",
    "gn:dem":136,
    "gn:feature_class":"P",
    "gn:feature_code":"PPL",
    "gn:name":"Karpovo",
    "gn:population":0,
    "gn:timezone":"Europe/Moscow",
    "iso:country":"RU",
    "name:eng_x_preferred":[
        "Karpovo"
    ],
    "name:nor_x_preferred":[
        "Karpovo"
    ],
    "name:rus_x_preferred":[
        "\u041a\u0430\u0440\u043f\u043e\u0432\u043e"
    ],
    "name:und_x_variant":[
        "\u041a\u0430\u0440\u043f\u043e\u0432\u043e",
        "Karpovo"
    ],
    "wof:name":"Karpovo",
    "wof:placetype":"locality"
},
  "geometry": {"coordinates":[36.7387,60.0233],"type":"Point"}
}