{
  "type": "Feature",
  "properties": {
    "gn:admin1_code":"46",
    "gn:asciiname":"Redkodub'ye",
    "gn:country_code":"RU",
    "gn:dem":101,
    "gn:feature_class":"P",
    "gn:feature_code":"PPL",
    "gn:name":"Redkodub\u2019ye",
    "gn:population":0,
    "gn:timezone":"Europe/Moscow",
    "iso:country":"RU",
    "name:eng_x_preferred":[
        "Redkodub'ye"
    ],
    "name:nor_x_preferred":[
        "Redkodubje"
    ],
    "name:rus_x_preferred":[
        "\u0420\u0435\u0434\u043a\u043e\u0434\u0443\u0431\u044c\u0435"
    ],
    "name:und_x_variant":[
        "Redkodub\u2019ye"
    ],
    "wof:name":"Redkodub'ye",
    "wof:placetype":"locality"
},
  "geometry": {"coordinates":[46.17171,54.81469],"type":"Point"}
}