{
  "type": "Feature",
  "properties": {
    "gn:admin1_code":"71",
    "gn:asciiname":"Firsovo",
    "gn:country_code":"RU",
    "gn:dem":69,
    "gn:feature_class":"P",
    "gn:feature_code":"PPL",
    "gn:name":"Firsovo",
    "gn:population":0,
    "gn:timezone":"Asia/Yekaterinburg",
    "iso:country":"RU",
    "name:rus_x_preferred":[
        "\u0424\u0438\u0440\u0441\u043e\u0432\u043e"
    ],
    "wof:name":"Firsovo",
    "wof:placetype":"locality"
},
  "geometry": {"coordinates":[63.1759,58.07505],"type":"Point"}
}