{
  "type": "Feature",
  "properties": {
    "gn:admin1_code":"53",
    "gn:asciiname":"Los'",
    "gn:country_code":"RU",
    "gn:dem":150,
    "gn:feature_class":"P",
    "gn:feature_code":"PPL",
    "gn:name":"Los\u2019",
    "gn:population":0,
    "gn:timezone":"Asia/Novosibirsk",
    "iso:country":"RU",
    "name:eng_x_preferred":[
        "Los'"
    ],
    "name:nor_x_preferred":[
        "Los"
    ],
    "name:rus_x_preferred":[
        "\u041b\u043e\u0441\u044c"
    ],
    "name:und_x_variant":[
        "\u041b\u043e\u0441\u044c",
        "Los\u2019"
    ],
    "wof:name":"Los'",
    "wof:placetype":"locality"
},
  "geometry": {"coordinates":[82.0574,55.6165],"type":"Point"}
}