{
  "type": "Feature",
  "properties": {
    "gn:admin1_code":"93",
    "gn:asciiname":"Etytey",
    "gn:country_code":"RU",
    "gn:dem":830,
    "gn:feature_class":"P",
    "gn:feature_code":"PPL",
    "gn:name":"Etytey",
    "gn:population":0,
    "gn:timezone":"Asia/Chita",
    "iso:country":"RU",
    "name:eng_x_preferred":[
        "Etytey"
    ],
    "name:nor_x_preferred":[
        "Etytej"
    ],
    "name:rus_x_preferred":[
        "\u042d\u0442\u044b\u0442\u0435\u0439"
    ],
    "name:und_x_variant":[
        "Etytei",
        "Etygey"
    ],
    "wof:name":"Etytey",
    "wof:placetype":"locality"
},
  "geometry": {"coordinates":[108.47483,50.29798],"type":"Point"}
}