{
  "type": "Feature",
  "properties": {
    "gn:admin1_code":"53",
    "gn:asciiname":"Kurundus",
    "gn:country_code":"RU",
    "gn:dem":208,
    "gn:feature_class":"P",
    "gn:feature_code":"PPL",
    "gn:name":"Kurundus",
    "gn:population":0,
    "gn:timezone":"Asia/Novosibirsk",
    "iso:country":"RU",
    "name:eng_x_preferred":[
        "Kurundus"
    ],
    "name:nor_x_preferred":[
        "Kurundus"
    ],
    "name:rus_x_preferred":[
        "\u041a\u0443\u0440\u0443\u043d\u0434\u0443\u0441"
    ],
    "wof:name":"Kurundus",
    "wof:placetype":"locality"
},
  "geometry": {"coordinates":[84.7897,55.0577],"type":"Point"}
}