{
  "type": "Feature",
  "properties": {
    "gn:admin1_code":"25",
    "gn:asciiname":"Kurovskoye",
    "gn:country_code":"RU",
    "gn:dem":213,
    "gn:feature_class":"P",
    "gn:feature_code":"PPL",
    "gn:name":"Kurovskoye",
    "gn:population":0,
    "gn:timezone":"Europe/Moscow",
    "iso:country":"RU",
    "name:rus_x_preferred":[
        "\u041a\u0443\u0440\u043e\u0432\u0441\u043a\u043e\u0435"
    ],
    "wof:name":"Kurovskoye",
    "wof:placetype":"locality"
},
  "geometry": {"coordinates":[35.92205,54.244],"type":"Point"}
}