{
  "type": "Feature",
  "properties": {
    "gn:admin1_code":"62",
    "gn:asciiname":"Stuble",
    "gn:country_code":"RU",
    "gn:dem":160,
    "gn:feature_class":"P",
    "gn:feature_code":"PPL",
    "gn:name":"Stuble",
    "gn:population":0,
    "gn:timezone":"Europe/Moscow",
    "iso:country":"RU",
    "name:eng_x_preferred":[
        "Stuble"
    ],
    "name:nor_x_preferred":[
        "Stuble"
    ],
    "name:rus_x_preferred":[
        "\u0421\u0442\u0443\u0431\u043b\u0435"
    ],
    "name:und_x_variant":[
        "\u0421\u0442\u0443\u0431\u043b\u0435",
        "Stuble"
    ],
    "wof:name":"Stuble",
    "wof:placetype":"locality"
},
  "geometry": {"coordinates":[39.0386,54.3133],"type":"Point"}
}