{
  "type": "Feature",
  "properties": {
    "gn:admin1_code":"88",
    "gn:asciiname":"Gribovo",
    "gn:country_code":"RU",
    "gn:dem":127,
    "gn:feature_class":"P",
    "gn:feature_code":"PPL",
    "gn:name":"Gribovo",
    "gn:population":0,
    "gn:timezone":"Europe/Moscow",
    "iso:country":"RU",
    "name:rus_x_preferred":[
        "\u0413\u0440\u0438\u0431\u043e\u0432\u043e"
    ],
    "wof:name":"Gribovo",
    "wof:placetype":"locality"
},
  "geometry": {"coordinates":[38.90994,58.17018],"type":"Point"}
}