{
  "type": "Feature",
  "properties": {
    "gn:admin1_code":"85",
    "gn:asciiname":"Novozhilikha",
    "gn:country_code":"RU",
    "gn:dem":130,
    "gn:feature_class":"P",
    "gn:feature_code":"PPL",
    "gn:name":"Novozhilikha",
    "gn:population":0,
    "gn:timezone":"Europe/Moscow",
    "iso:country":"RU",
    "name:rus_x_preferred":[
        "\u041d\u043e\u0432\u043e\u0436\u0438\u043b\u0438\u0445\u0430"
    ],
    "wof:name":"Novozhilikha",
    "wof:placetype":"locality"
},
  "geometry": {"coordinates":[40.10443,60.42484],"type":"Point"}
}