{
  "type": "Feature",
  "properties": {
    "gn:admin1_code":"52",
    "gn:asciiname":"Krasnoslud'ye",
    "gn:country_code":"RU",
    "gn:dem":77,
    "gn:feature_class":"P",
    "gn:feature_code":"PPL",
    "gn:name":"Krasnoslud\u2019ye",
    "gn:population":0,
    "gn:timezone":"Europe/Moscow",
    "iso:country":"RU",
    "name:rus_x_preferred":[
        "\u041a\u0440\u0430\u0441\u043d\u043e\u0441\u043b\u0443\u0434\u044c\u0435"
    ],
    "name:und_x_variant":[
        "Krasnoslud\u2019ya",
        "Krasnoslud\u2019ye",
        "\u041a\u0440\u0430\u0441\u043d\u043e\u0441\u043b\u0443\u0434\u044c\u0435"
    ],
    "wof:name":"Krasnoslud'ye",
    "wof:placetype":"locality"
},
  "geometry": {"coordinates":[31.35,57.31667],"type":"Point"}
}