{
  "type": "Feature",
  "properties": {
    "gn:admin1_code":"85",
    "gn:asciiname":"Shuklino",
    "gn:country_code":"RU",
    "gn:dem":110,
    "gn:feature_class":"P",
    "gn:feature_code":"PPL",
    "gn:name":"Shuklino",
    "gn:population":0,
    "gn:timezone":"Europe/Moscow",
    "iso:country":"RU",
    "name:rus_x_preferred":[
        "\u0428\u0443\u043a\u043b\u0438\u043d\u043e"
    ],
    "wof:name":"Shuklino",
    "wof:placetype":"locality"
},
  "geometry": {"coordinates":[36.5856,58.9025],"type":"Point"}
}