{
  "type": "Feature",
  "properties": {
    "gn:admin1_code":"8",
    "gn:asciiname":"Kyzyrbak",
    "gn:country_code":"RU",
    "gn:dem":286,
    "gn:feature_class":"P",
    "gn:feature_code":"PPL",
    "gn:name":"Kyzyrbak",
    "gn:population":0,
    "gn:timezone":"Asia/Yekaterinburg",
    "iso:country":"RU",
    "name:rus_x_preferred":[
        "\u041a\u044b\u0437\u044b\u0440\u0431\u0430\u043a"
    ],
    "name:und_x_variant":[
        "Kazyrbak",
        "Kozyrbak",
        "Kyzyrbak"
    ],
    "wof:name":"Kyzyrbak",
    "wof:placetype":"locality"
},
  "geometry": {"coordinates":[58.2149,55.2138],"type":"Point"}
}