{
  "type": "Feature",
  "properties": {
    "gn:admin1_code":"51",
    "gn:asciiname":"Kuz'miyar",
    "gn:country_code":"RU",
    "gn:dem":105,
    "gn:feature_class":"P",
    "gn:feature_code":"PPL",
    "gn:name":"Kuz\u2019miyar",
    "gn:population":0,
    "gn:timezone":"Europe/Moscow",
    "iso:country":"RU",
    "name:eng_x_preferred":[
        "Kuz'miyar"
    ],
    "name:nor_x_preferred":[
        "Kuzmijar"
    ],
    "name:rus_x_preferred":[
        "\u041a\u0443\u0437\u044c\u043c\u0438\u044f\u0440"
    ],
    "name:und_x_variant":[
        "\u041a\u0443\u0437\u044c\u043c\u0438\u044f\u0440",
        "Kuz\u2019miyar"
    ],
    "wof:name":"Kuz'miyar",
    "wof:placetype":"locality"
},
  "geometry": {"coordinates":[45.48753,56.3758],"type":"Point"}
}