{
  "type": "Feature",
  "properties": {
    "gn:admin1_code":"38",
    "gn:asciiname":"Karskiy",
    "gn:country_code":"RU",
    "gn:dem":126,
    "gn:feature_class":"P",
    "gn:feature_code":"PPL",
    "gn:name":"Karskiy",
    "gn:population":0,
    "gn:timezone":"Europe/Moscow",
    "iso:country":"RU",
    "name:rus_x_preferred":[
        "\u041a\u0430\u0440\u0441\u043a\u0438\u0439"
    ],
    "wof:name":"Karskiy",
    "wof:placetype":"locality"
},
  "geometry": {"coordinates":[38.50694,44.82528],"type":"Point"}
}