{
  "type": "Feature",
  "properties": {
    "gn:admin1_code":"16",
    "gn:asciiname":"Mokshino",
    "gn:country_code":"RU",
    "gn:dem":155,
    "gn:feature_class":"P",
    "gn:feature_code":"PPL",
    "gn:name":"Mokshino",
    "gn:population":0,
    "gn:timezone":"Europe/Moscow",
    "iso:country":"RU",
    "name:rus_x_preferred":[
        "\u041c\u043e\u043a\u0448\u0438\u043d\u043e"
    ],
    "name:und_x_variant":[
        "\u041c\u043e\u043a\u0448\u0438\u043d\u043e"
    ],
    "wof:name":"Mokshino",
    "wof:placetype":"locality"
},
  "geometry": {"coordinates":[47.15609,56.00674],"type":"Point"}
}