{
  "type": "Feature",
  "properties": {
    "gn:admin1_code":"84",
    "gn:asciiname":"Smirnov",
    "gn:country_code":"RU",
    "gn:dem":23,
    "gn:feature_class":"P",
    "gn:feature_code":"PPL",
    "gn:name":"Smirnov",
    "gn:population":0,
    "gn:timezone":"Europe/Volgograd",
    "iso:country":"RU",
    "name:deu_x_preferred":[
        "Smirnov"
    ],
    "name:fin_x_preferred":[
        "Smirnov"
    ],
    "name:fra_x_preferred":[
        "Smirnov"
    ],
    "name:rus_x_preferred":[
        "\u0421\u043c\u0438\u0440\u043d\u043e\u0432"
    ],
    "name:und_x_variant":[
        "\u0421\u043c\u0438\u0440\u043d\u043e\u0432"
    ],
    "wof:name":"Smirnov",
    "wof:placetype":"locality"
},
  "geometry": {"coordinates":[45.33333,49.05],"type":"Point"}
}