{
  "type": "Feature",
  "properties": {
    "gn:admin1_code":"55",
    "gn:asciiname":"Kuz'minka",
    "gn:country_code":"RU",
    "gn:dem":66,
    "gn:feature_class":"P",
    "gn:feature_code":"PPL",
    "gn:name":"Kuz\u2019minka",
    "gn:population":0,
    "gn:timezone":"Asia/Yekaterinburg",
    "iso:country":"RU",
    "name:eng_x_preferred":[
        "Kuz'minka"
    ],
    "name:nor_x_preferred":[
        "Kuzminka"
    ],
    "name:rus_x_preferred":[
        "\u041a\u0443\u0437\u044c\u043c\u0438\u043d\u043a\u0430"
    ],
    "name:und_x_variant":[
        "Kuz\u2019minskiy",
        "\u041a\u0443\u0437\u044c\u043c\u0438\u043d\u043a\u0430",
        "Kuz\u2019minka"
    ],
    "wof:name":"Kuz'minka",
    "wof:placetype":"locality"
},
  "geometry": {"coordinates":[52.64808000000001,51.64514000000001],"type":"Point"}
}