{
  "type": "Feature",
  "properties": {
    "gn:admin1_code":"83",
    "gn:asciiname":"Bol'shevik",
    "gn:country_code":"RU",
    "gn:dem":194,
    "gn:feature_class":"P",
    "gn:feature_code":"PPL",
    "gn:name":"Bol\u2019shevik",
    "gn:population":0,
    "gn:timezone":"Europe/Moscow",
    "iso:country":"RU",
    "name:rus_x_preferred":[
        "\u0411\u043e\u043b\u044c\u0448\u0435\u0432\u0438\u043a"
    ],
    "name:und_x_variant":[
        "Bol\u2019shevik"
    ],
    "wof:name":"Bol'shevik",
    "wof:placetype":"locality"
},
  "geometry": {"coordinates":[39.4148,56.38972],"type":"Point"}
}