{
  "type": "Feature",
  "properties": {
    "gn:admin1_code":"55.0",
    "gn:asciiname":"Burenino",
    "gn:cc2":"RU",
    "gn:country_code":"RU",
    "gn:dem":97,
    "gn:feature_class":"P",
    "gn:feature_code":"PPL",
    "gn:name":"Burenino",
    "gn:population":0,
    "gn:timezone":"Asia/Yekaterinburg",
    "iso:country":"RU",
    "name:eng_x_preferred":[
        "Burenino"
    ],
    "name:nor_x_preferred":[
        "Burenino"
    ],
    "name:rus_x_preferred":[
        "\u0411\u0443\u0440\u0435\u043d\u0438\u043d\u043e"
    ],
    "name:und_x_variant":[
        "Bureninskiy"
    ],
    "wof:name":"Burenino",
    "wof:placetype":"locality"
},
  "geometry": {"coordinates":[52.83361,51.97778],"type":"Point"}
}