{
  "type": "Feature",
  "properties": {
    "gn:country":"RU",
    "gn:fcode":"PPL",
    "gn:population":0,
    "iso:country":"RU",
    "name:fin_x_preferred":[
        "Tokkari"
    ],
    "name:rus_x_preferred":[
        "\u0422\u043e\u043a\u043a\u0430\u0440\u0438"
    ],
    "qs:name":"Tokkari",
    "qs:name_adm0":"Russia",
    "qs:name_adm1":"Leningrad Oblast",
    "qs:photos_9r":0,
    "qs:photos_sr":0,
    "qs:placetype":"Town",
    "qs:pop_sr":"0",
    "wof:name":"Tokkari",
    "wof:placetype":"locality",
    "wof:population":0
},
  "geometry": {"coordinates":[30.64301,59.94512],"type":"Point"}
}