{
  "type": "Feature",
  "properties": {
    "gn:admin1_code":"85",
    "gn:asciiname":"Osnovinskaya",
    "gn:country_code":"RU",
    "gn:dem":148,
    "gn:feature_class":"P",
    "gn:feature_code":"PPL",
    "gn:name":"Osnovinskaya",
    "gn:population":0,
    "gn:timezone":"Europe/Moscow",
    "iso:country":"RU",
    "name:rus_x_preferred":[
        "\u041e\u0441\u043d\u043e\u0432\u0438\u043d\u0441\u043a\u0430\u044f"
    ],
    "wof:name":"Osnovinskaya",
    "wof:placetype":"locality"
},
  "geometry": {"coordinates":[41.85928,60.60952],"type":"Point"}
}