{
  "type": "Feature",
  "properties": {
    "gn:admin1_code":"65",
    "gn:asciiname":"Malorechensk",
    "gn:country_code":"RU",
    "gn:dem":104,
    "gn:feature_class":"P",
    "gn:feature_code":"PPL",
    "gn:name":"Malorechensk",
    "gn:population":0,
    "gn:timezone":"Europe/Samara",
    "iso:country":"RU",
    "name:rus_x_preferred":[
        "\u041c\u0430\u043b\u043e\u0440\u0435\u0447\u0435\u043d\u0441\u043a"
    ],
    "wof:name":"Malorechensk",
    "wof:placetype":"locality"
},
  "geometry": {"coordinates":[51.096,53.5262],"type":"Point"}
}