{
  "type": "Feature",
  "properties": {
    "gn:admin1_code":"52",
    "gn:asciiname":"Vekshino",
    "gn:country_code":"RU",
    "gn:dem":62,
    "gn:feature_class":"P",
    "gn:feature_code":"PPL",
    "gn:name":"Vekshino",
    "gn:population":0,
    "gn:timezone":"Europe/Moscow",
    "iso:country":"RU",
    "name:eng_x_preferred":[
        "Vekshino"
    ],
    "name:nor_x_preferred":[
        "Veksjino"
    ],
    "name:rus_x_preferred":[
        "\u0412\u0435\u043a\u0448\u0438\u043d\u043e"
    ],
    "wof:name":"Vekshino",
    "wof:placetype":"locality"
},
  "geometry": {"coordinates":[31.20916,57.62379],"type":"Point"}
}