{
  "type": "Feature",
  "properties": {
    "gn:admin1_code":"60.0",
    "gn:asciiname":"Krapivenka",
    "gn:country_code":"RU",
    "gn:dem":47,
    "gn:feature_class":"P",
    "gn:feature_code":"PPL",
    "gn:name":"Krapivenka",
    "gn:population":0,
    "gn:timezone":"Europe/Moscow",
    "iso:country":"RU",
    "name:rus_x_preferred":[
        "\u041a\u0440\u0430\u043f\u0438\u0432\u0435\u043d\u043a\u0430"
    ],
    "wof:name":"Krapivenka",
    "wof:placetype":"locality"
},
  "geometry": {"coordinates":[28.1109,58.4563],"type":"Point"}
}