{
  "type": "Feature",
  "properties": {
    "gn:admin1_code":"23",
    "gn:asciiname":"Perevalovo",
    "gn:country_code":"RU",
    "gn:dem":28,
    "gn:feature_class":"P",
    "gn:feature_code":"PPL",
    "gn:name":"Perevalovo",
    "gn:population":0,
    "gn:timezone":"Europe/Kaliningrad",
    "iso:country":"RU",
    "name:rus_x_preferred":[
        "\u041f\u0435\u0440\u0435\u0432\u0430\u043b\u043e\u0432\u043e"
    ],
    "name:und_x_variant":[
        "Muldschen",
        "Muldszen",
        "Mul\u2019dzhen",
        "Mulden",
        "Perevalovo"
    ],
    "wof:name":"Perevalovo",
    "wof:placetype":"locality"
},
  "geometry": {"coordinates":[21.42912,54.50004000000001],"type":"Point"}
}