{
  "type": "Feature",
  "properties": {
    "gn:admin1_code":"73",
    "gn:asciiname":"Novyye Yerykly",
    "gn:country_code":"RU",
    "gn:dem":170,
    "gn:feature_class":"P",
    "gn:feature_code":"PPL",
    "gn:name":"Novyye Yerykly",
    "gn:population":0,
    "gn:timezone":"Europe/Moscow",
    "iso:country":"RU",
    "name:rus_x_preferred":[
        "\u041d\u043e\u0432\u044b\u0435 \u0415\u0440\u044b\u043a\u043b\u044b"
    ],
    "name:und_x_variant":[
        "Novaya Yeykla",
        "Novyye Yerykly"
    ],
    "wof:name":"Novyye Yerykly",
    "wof:placetype":"locality"
},
  "geometry": {"coordinates":[52.13346,55.5553],"type":"Point"}
}