{
  "type": "Feature",
  "properties": {
    "gn:admin1_code":"37",
    "gn:asciiname":"Verevkino",
    "gn:cc2":"RU",
    "gn:country_code":"RU",
    "gn:dem":176,
    "gn:feature_class":"P",
    "gn:feature_code":"PPL",
    "gn:name":"Ver\u00ebvkino",
    "gn:population":0,
    "gn:timezone":"Europe/Moscow",
    "iso:country":"RU",
    "name:und_x_variant":[
        "Verevkina",
        "Ver\u00ebvkino"
    ],
    "wof:name":"Verevkino",
    "wof:placetype":"locality"
},
  "geometry": {"coordinates":[41.67083,57.81721999999999],"type":"Point"}
}