{
  "type": "Feature",
  "properties": {
    "gn:admin1_code":"30",
    "gn:asciiname":"Chlya",
    "gn:country_code":"RU",
    "gn:dem":16,
    "gn:feature_class":"P",
    "gn:feature_code":"PPL",
    "gn:name":"Chlya",
    "gn:population":0,
    "gn:timezone":"Asia/Vladivostok",
    "iso:country":"RU",
    "name:eng_x_preferred":[
        "Chlya"
    ],
    "name:nor_x_preferred":[
        "Tsjlja"
    ],
    "name:rus_x_preferred":[
        "\u0427\u043b\u044f"
    ],
    "name:und_x_variant":[
        "\u0427\u043b\u044f",
        "Chlya"
    ],
    "wof:name":"Chlya",
    "wof:placetype":"locality"
},
  "geometry": {"coordinates":[140.19574,53.54267],"type":"Point"}
}