{
  "type": "Feature",
  "properties": {
    "gn:admin1_code":"63",
    "gn:asciiname":"Tompo",
    "gn:country_code":"RU",
    "gn:dem":407,
    "gn:feature_class":"P",
    "gn:feature_code":"PPL",
    "gn:name":"Tompo",
    "gn:population":0,
    "gn:timezone":"Asia/Vladivostok",
    "iso:country":"RU",
    "name:eng_x_preferred":[
        "Tompo"
    ],
    "name:nor_x_preferred":[
        "Tompo"
    ],
    "name:rus_x_preferred":[
        "\u0422\u043e\u043c\u043f\u043e"
    ],
    "name:und_x_variant":[
        "Tomponskaya-Kul\u2019tbaza",
        "Tompovskaya-Kul\u2019tbaza",
        "Tompo"
    ],
    "wof:name":"Tompo",
    "wof:placetype":"locality"
},
  "geometry": {"coordinates":[135.85225,63.91414],"type":"Point"}
}