{
  "type": "Feature",
  "properties": {
    "gn:admin1_code":"41",
    "gn:asciiname":"Malinovskiy",
    "gn:country_code":"RU",
    "gn:dem":183,
    "gn:feature_class":"P",
    "gn:feature_code":"PPL",
    "gn:name":"Malinovskiy",
    "gn:population":0,
    "gn:timezone":"Europe/Moscow",
    "iso:country":"RU",
    "name:rus_x_preferred":[
        "\u041c\u0430\u043b\u0438\u043d\u043e\u0432\u0441\u043a\u0438\u0439"
    ],
    "wof:name":"Malinovskiy",
    "wof:placetype":"locality"
},
  "geometry": {"coordinates":[34.9074,51.8385],"type":"Point"}
}