{
  "type": "Feature",
  "properties": {
    "gn:admin1_code":"46",
    "gn:asciiname":"Kazeyevskiy",
    "gn:country_code":"RU",
    "gn:dem":254,
    "gn:feature_class":"P",
    "gn:feature_code":"PPL",
    "gn:name":"Kazeyevskiy",
    "gn:population":0,
    "gn:timezone":"Europe/Moscow",
    "iso:country":"RU",
    "name:rus_x_preferred":[
        "\u041a\u0430\u0437\u0435\u0435\u0432\u0441\u043a\u0438\u0439"
    ],
    "wof:name":"Kazeyevskiy",
    "wof:placetype":"locality"
},
  "geometry": {"coordinates":[44.3862,53.742],"type":"Point"}
}