{
  "type": "Feature",
  "properties": {
    "gn:admin1_code":"1.0",
    "gn:asciiname":"Kirov",
    "gn:country_code":"RU",
    "gn:dem":86,
    "gn:feature_class":"P",
    "gn:feature_code":"PPL",
    "gn:name":"Kirov",
    "gn:population":0,
    "gn:timezone":"Europe/Moscow",
    "iso:country":"RU",
    "name:rus_x_preferred":[
        "\u041a\u0438\u0440\u043e\u0432"
    ],
    "name:und_x_variant":[
        "\u041a\u0438\u0440\u043e\u0432"
    ],
    "wof:name":"Kirov",
    "wof:placetype":"locality"
},
  "geometry": {"coordinates":[40.26972,45.08889],"type":"Point"}
}