{
  "type": "Feature",
  "properties": {
    "gn:admin1_code":"9.0",
    "gn:asciiname":"Gvozdikov",
    "gn:country_code":"RU",
    "gn:dem":180,
    "gn:feature_class":"P",
    "gn:feature_code":"PPL",
    "gn:name":"Gvozdikov",
    "gn:population":0,
    "gn:timezone":"Europe/Moscow",
    "iso:country":"RU",
    "name:rus_x_preferred":[
        "\u0413\u0432\u043e\u0437\u0434\u0438\u043a\u043e\u0432"
    ],
    "name:und_x_variant":[
        "\u0413\u0432\u043e\u0437\u0434\u0438\u043a\u043e\u0432"
    ],
    "wof:name":"Gvozdikov",
    "wof:placetype":"locality"
},
  "geometry": {"coordinates":[38.6902,50.3588],"type":"Point"}
}