{
  "type": "Feature",
  "properties": {
    "gn:admin1_code":"56.0",
    "gn:asciiname":"Davydova",
    "gn:country_code":"RU",
    "gn:dem":217,
    "gn:feature_class":"P",
    "gn:feature_code":"PPL",
    "gn:name":"Davydova",
    "gn:population":0,
    "gn:timezone":"Europe/Moscow",
    "iso:country":"RU",
    "name:rus_x_preferred":[
        "\u0414\u0430\u0432\u044b\u0434\u043e\u0432\u0430"
    ],
    "wof:name":"Davydova",
    "wof:placetype":"locality"
},
  "geometry": {"coordinates":[34.99786,52.78728],"type":"Point"}
}