{
  "type": "Feature",
  "properties": {
    "gn:admin1_code":"72",
    "gn:asciiname":"Tatarshchina",
    "gn:country_code":"RU",
    "gn:dem":155,
    "gn:feature_class":"P",
    "gn:feature_code":"PPL",
    "gn:name":"Tatarshchina",
    "gn:population":0,
    "gn:timezone":"Europe/Moscow",
    "iso:country":"RU",
    "name:und_x_variant":[
        "Tatarshchino",
        "Tatarshchino Vtoraya",
        "Tatarshchina"
    ],
    "wof:name":"Tatarshchina",
    "wof:placetype":"locality"
},
  "geometry": {"coordinates":[42.02159,52.83595],"type":"Point"}
}