{
  "type": "Feature",
  "properties": {
    "gn:admin1_code":"88.0",
    "gn:asciiname":"Shigino",
    "gn:country_code":"RU",
    "gn:dem":93,
    "gn:feature_class":"P",
    "gn:feature_code":"PPL",
    "gn:name":"Shigino",
    "gn:population":0,
    "gn:timezone":"Europe/Moscow",
    "iso:country":"RU",
    "name:rus_x_preferred":[
        "\u0428\u0438\u0433\u0438\u043d\u043e"
    ],
    "wof:name":"Shigino",
    "wof:placetype":"locality"
},
  "geometry": {"coordinates":[40.66664,58.02822],"type":"Point"}
}