{
  "type": "Feature",
  "properties": {
    "gn:admin1_code":"25",
    "gn:asciiname":"Zelenyy",
    "gn:country_code":"RU",
    "gn:dem":216,
    "gn:feature_class":"P",
    "gn:feature_code":"PPL",
    "gn:name":"Zel\u00ebnyy",
    "gn:population":0,
    "gn:timezone":"Europe/Moscow",
    "iso:country":"RU",
    "name:und_x_variant":[
        "Zelenaya Roshcha",
        "Zel\u00ebnyy"
    ],
    "wof:name":"Zelenyy",
    "wof:placetype":"locality"
},
  "geometry": {"coordinates":[35.35284,53.64841],"type":"Point"}
}