{
  "type": "Feature",
  "properties": {
    "gn:admin1_code":"75",
    "gn:asciiname":"Mizurkino",
    "gn:cc2":"RU",
    "gn:country_code":"RU",
    "gn:dem":49,
    "gn:feature_class":"P",
    "gn:feature_code":"PPL",
    "gn:name":"Mizurkino",
    "gn:population":0,
    "gn:timezone":"Asia/Tomsk",
    "iso:country":"RU",
    "name:rus_x_preferred":[
        "\u041c\u0438\u0437\u0443\u0440\u043a\u0438\u043d\u043e"
    ],
    "name:und_x_variant":[
        "Mizurkina",
        "Mizurkino"
    ],
    "wof:name":"Mizurkino",
    "wof:placetype":"locality"
},
  "geometry": {"coordinates":[81.08333,59.15],"type":"Point"}
}