{
  "type": "Feature",
  "properties": {
    "gn:admin1_code":"55",
    "gn:asciiname":"Sobolevo",
    "gn:cc2":"RU",
    "gn:country_code":"RU",
    "gn:dem":59,
    "gn:feature_class":"P",
    "gn:feature_code":"PPL",
    "gn:name":"Sobolevo",
    "gn:population":0,
    "gn:timezone":"Asia/Yekaterinburg",
    "iso:country":"RU",
    "name:eng_x_preferred":[
        "Sobolevo"
    ],
    "name:nor_x_preferred":[
        "Sobolevo"
    ],
    "name:rus_x_preferred":[
        "\u0421\u043e\u0431\u043e\u043b\u0435\u0432\u043e"
    ],
    "name:und_x_variant":[
        "Sobolevsk",
        "Sobolev"
    ],
    "wof:name":"Sobolevo",
    "wof:placetype":"locality"
},
  "geometry": {"coordinates":[51.71667,51.93333],"type":"Point"}
}