{
  "type": "Feature",
  "properties": {
    "gn:admin1_code":"40",
    "gn:asciiname":"Dolgovka",
    "gn:cc2":"RU",
    "gn:country_code":"RU",
    "gn:dem":132,
    "gn:feature_class":"P",
    "gn:feature_code":"PPL",
    "gn:name":"Dolgovka",
    "gn:population":0,
    "gn:timezone":"Asia/Yekaterinburg",
    "iso:country":"RU",
    "name:eng_x_preferred":[
        "Dolgovka"
    ],
    "name:nor_x_preferred":[
        "Dolgovka"
    ],
    "name:rus_x_preferred":[
        "\u0414\u043e\u043b\u0433\u043e\u0432\u043a\u0430"
    ],
    "name:und_x_variant":[
        "Dolgovskoye",
        "\u0414\u043e\u043b\u0433\u043e\u0432\u043a\u0430",
        "Dolgovka"
    ],
    "wof:name":"Dolgovka",
    "wof:placetype":"locality"
},
  "geometry": {"coordinates":[64.14305999999999,54.97194],"type":"Point"}
}