{
  "type": "Feature",
  "properties": {
    "gn:admin1_code":"55",
    "gn:asciiname":"Stepnoy",
    "gn:country_code":"RU",
    "gn:dem":143,
    "gn:feature_class":"P",
    "gn:feature_code":"PPL",
    "gn:name":"Stepnoy",
    "gn:population":0,
    "gn:timezone":"Asia/Yekaterinburg",
    "iso:country":"RU",
    "name:rus_x_preferred":[
        "\u0421\u0442\u0435\u043f\u043d\u043e\u0439"
    ],
    "wof:name":"Stepnoy",
    "wof:placetype":"locality"
},
  "geometry": {"coordinates":[53.4709,52.6154],"type":"Point"}
}