{
  "type": "Feature",
  "properties": {
    "gn:admin1_code":"52",
    "gn:asciiname":"Sukhoyedovo",
    "gn:country_code":"RU",
    "gn:dem":175,
    "gn:feature_class":"P",
    "gn:feature_code":"PPL",
    "gn:name":"Sukhoyedovo",
    "gn:population":0,
    "gn:timezone":"Europe/Moscow",
    "iso:country":"RU",
    "name:rus_x_preferred":[
        "\u0421\u0443\u0445\u043e\u0435\u0434\u043e\u0432\u043e"
    ],
    "wof:name":"Sukhoyedovo",
    "wof:placetype":"locality"
},
  "geometry": {"coordinates":[33.76667,58.21666999999999],"type":"Point"}
}