{
  "type": "Feature",
  "properties": {
    "gn:admin1_code":"70.0",
    "gn:asciiname":"Umrikhina",
    "gn:country_code":"RU",
    "gn:dem":240,
    "gn:feature_class":"P",
    "gn:feature_code":"PPL",
    "gn:name":"Umrikhina",
    "gn:population":0,
    "gn:timezone":"Europe/Moscow",
    "iso:country":"RU",
    "wof:name":"Umrikhina",
    "wof:placetype":"locality"
},
  "geometry": {"coordinates":[42.09389,45.41306],"type":"Point"}
}