{
  "type": "Feature",
  "properties": {
    "gn:admin1_code":"52",
    "gn:asciiname":"Runitsy",
    "gn:country_code":"RU",
    "gn:dem":177,
    "gn:feature_class":"P",
    "gn:feature_code":"PPL",
    "gn:name":"Runitsy",
    "gn:population":0,
    "gn:timezone":"Europe/Moscow",
    "iso:country":"RU",
    "name:eng_x_preferred":[
        "Runitsy"
    ],
    "name:nor_x_preferred":[
        "Runitsy"
    ],
    "name:rus_x_preferred":[
        "\u0420\u0443\u043d\u0438\u0446\u044b"
    ],
    "name:und_x_variant":[
        "Runnitsy",
        "Runitsy"
    ],
    "wof:name":"Runitsy",
    "wof:placetype":"locality"
},
  "geometry": {"coordinates":[32.04085,57.24025],"type":"Point"}
}