{
  "type": "Feature",
  "properties": {
    "gn:admin1_code":"8",
    "gn:asciiname":"Novyy Atkul'",
    "gn:country_code":"RU",
    "gn:dem":111,
    "gn:feature_class":"P",
    "gn:feature_code":"PPL",
    "gn:name":"Novyy Atkul\u2019",
    "gn:population":0,
    "gn:timezone":"Asia/Yekaterinburg",
    "iso:country":"RU",
    "name:rus_x_preferred":[
        "\u041d\u043e\u0432\u044b\u0439 \u0410\u0442\u043a\u0443\u043b\u044c"
    ],
    "name:und_x_variant":[
        "Novyy Atkul\u2019"
    ],
    "wof:name":"Novyy Atkul'",
    "wof:placetype":"locality"
},
  "geometry": {"coordinates":[54.72225,55.96286],"type":"Point"}
}