{
  "type": "Feature",
  "properties": {
    "gn:admin1_code":"25",
    "gn:asciiname":"Gribovka",
    "gn:country_code":"RU",
    "gn:dem":189,
    "gn:feature_class":"P",
    "gn:feature_code":"PPL",
    "gn:name":"Gribovka",
    "gn:population":0,
    "gn:timezone":"Europe/Moscow",
    "iso:country":"RU",
    "name:che_x_preferred":[
        "\u0413\u0440\u0438\u0431\u043e\u0432\u043a\u0430"
    ],
    "name:rus_x_preferred":[
        "\u0413\u0440\u0438\u0431\u043e\u0432\u043a\u0430"
    ],
    "name:tgk_x_preferred":[
        "\u0413\u0440\u0438\u0431\u043e\u0432\u043a\u0430"
    ],
    "name:und_x_variant":[
        "\u0413\u0440\u0438\u0431\u043e\u0432\u043a\u0430"
    ],
    "wof:name":"Gribovka",
    "wof:placetype":"locality"
},
  "geometry": {"coordinates":[33.88030999999999,54.03518],"type":"Point"}
}