{
  "type": "Feature",
  "properties": {
    "gn:admin1_code":"31",
    "gn:asciiname":"Znamenityy",
    "gn:cc2":"RU",
    "gn:country_code":"RU",
    "gn:dem":1237,
    "gn:feature_class":"P",
    "gn:feature_code":"PPL",
    "gn:name":"Znamenityy",
    "gn:population":0,
    "gn:timezone":"Asia/Krasnoyarsk",
    "iso:country":"RU",
    "name:und_x_variant":[
        "Znamenityi",
        "Znamenity",
        "Znamenityy"
    ],
    "wof:name":"Znamenityy",
    "wof:placetype":"locality"
},
  "geometry": {"coordinates":[89.16667,54.43333000000001],"type":"Point"}
}