{
  "type": "Feature",
  "properties": {
    "gn:admin1_code":"45.0",
    "gn:asciiname":"Sukhodoyevo",
    "gn:country_code":"RU",
    "gn:dem":157,
    "gn:feature_class":"P",
    "gn:feature_code":"PPL",
    "gn:name":"Sukhodoyevo",
    "gn:population":0,
    "gn:timezone":"Europe/Moscow",
    "iso:country":"RU",
    "name:rus_x_preferred":[
        "\u0421\u0443\u0445\u043e\u0434\u043e\u0435\u0432\u043e"
    ],
    "wof:name":"Sukhodoyevo",
    "wof:placetype":"locality"
},
  "geometry": {"coordinates":[49.92582,56.58814],"type":"Point"}
}