{
  "type": "Feature",
  "properties": {
    "gn:admin1_code":"60.0",
    "gn:asciiname":"Borovik",
    "gn:country_code":"RU",
    "gn:dem":34,
    "gn:feature_class":"P",
    "gn:feature_code":"PPL",
    "gn:name":"Borovik",
    "gn:population":0,
    "gn:timezone":"Europe/Moscow",
    "iso:country":"RU",
    "name:eng_x_preferred":[
        "Borovik"
    ],
    "name:nor_x_preferred":[
        "Borovik"
    ],
    "name:rus_x_preferred":[
        "\u0411\u043e\u0440\u043e\u0432\u0438\u043a"
    ],
    "name:und_x_variant":[
        "\u0411\u043e\u0440\u043e\u0432\u0438\u043a",
        "Borovik"
    ],
    "wof:name":"Borovik",
    "wof:placetype":"locality"
},
  "geometry": {"coordinates":[27.99215,58.22828000000001],"type":"Point"}
}