{
  "type": "Feature",
  "properties": {
    "gn:admin1_code":"8",
    "gn:asciiname":"Tardavka",
    "gn:country_code":"RU",
    "gn:dem":311,
    "gn:feature_class":"P",
    "gn:feature_code":"PPL",
    "gn:name":"Tardavka",
    "gn:population":0,
    "gn:timezone":"Asia/Yekaterinburg",
    "iso:country":"RU",
    "name:eng_x_preferred":[
        "Tardavka"
    ],
    "name:nor_x_preferred":[
        "Tardavka"
    ],
    "name:rus_x_preferred":[
        "\u0422\u0430\u0440\u0434\u0430\u0432\u043a\u0430"
    ],
    "name:und_x_variant":[
        "Tardovka",
        "Tardavka"
    ],
    "wof:name":"Tardavka",
    "wof:placetype":"locality"
},
  "geometry": {"coordinates":[58.6373,55.6563],"type":"Point"}
}