{
  "type": "Feature",
  "properties": {
    "gn:admin1_code":"8",
    "gn:asciiname":"Tardavka",
    "gn:country_code":"RU",
    "gn:dem":311,
    "gn:feature_class":"P",
    "gn:feature_code":"PPL",
    "gn:name":"Tardavka",
    "gn:population":0,
    "gn:timezone":"Asia/Yekaterinburg",
    "iso:country":"RU",
    "name:bak_x_preferred":[
        "\u0422\u0430\u0440\u0499\u0430\u0443"
    ],
    "name:eng_x_preferred":[
        "Tardavka"
    ],
    "name:hye_x_preferred":[
        "\u054f\u0561\u0580\u0564\u0561\u057e\u056f\u0561"
    ],
    "name:kat_x_preferred":[
        "\u10e2\u10d0\u10e0\u10d3\u10d0\u10d5\u10d9\u10d0"
    ],
    "name:nor_x_preferred":[
        "Tardavka"
    ],
    "name:rus_x_preferred":[
        "\u0422\u0430\u0440\u0434\u0430\u0432\u043a\u0430"
    ],
    "name:tat_x_preferred":[
        "\u0422\u0430\u0440\u0434\u0430\u0443"
    ],
    "name:und_x_variant":[
        "Tardovka",
        "Tardavka"
    ],
    "wof:name":"Tardavka",
    "wof:placetype":"locality"
},
  "geometry": {"coordinates":[58.6373,55.6563],"type":"Point"}
}