{
  "type": "Feature",
  "properties": {
    "gn:admin1_code":"8",
    "gn:asciiname":"Yakshivanovo",
    "gn:country_code":"RU",
    "gn:dem":88,
    "gn:feature_class":"P",
    "gn:feature_code":"PPL",
    "gn:name":"Yakshivanovo",
    "gn:population":0,
    "gn:timezone":"Asia/Yekaterinburg",
    "iso:country":"RU",
    "name:rus_x_preferred":[
        "\u042f\u043a\u0448\u0438\u0432\u0430\u043d\u043e\u0432\u043e"
    ],
    "name:und_x_variant":[
        "\u042f\u043a\u0448\u0438\u0432\u0430\u043d\u043e\u0432\u043e"
    ],
    "wof:name":"Yakshivanovo",
    "wof:placetype":"locality"
},
  "geometry": {"coordinates":[55.9098,54.9338],"type":"Point"}
}