{
  "type": "Feature",
  "properties": {
    "gn:admin1_code":"61.0",
    "gn:asciiname":"Nikolayevskiy",
    "gn:country_code":"RU",
    "gn:dem":62,
    "gn:feature_class":"P",
    "gn:feature_code":"PPL",
    "gn:name":"Nikolayevskiy",
    "gn:population":0,
    "gn:timezone":"Europe/Moscow",
    "iso:country":"RU",
    "name:rus_x_preferred":[
        "\u041d\u0438\u043a\u043e\u043b\u0430\u0435\u0432\u0441\u043a\u0438\u0439"
    ],
    "wof:name":"Nikolayevskiy",
    "wof:placetype":"locality"
},
  "geometry": {"coordinates":[42.4306,46.6734],"type":"Point"}
}