{
  "type": "Feature",
  "properties": {
    "gn:admin1_code":"30",
    "gn:asciiname":"Apkoroshi",
    "gn:country_code":"RU",
    "gn:dem":79,
    "gn:feature_class":"P",
    "gn:feature_code":"PPL",
    "gn:name":"Apkoroshi",
    "gn:population":0,
    "gn:timezone":"Asia/Vladivostok",
    "iso:country":"RU",
    "name:nor_x_preferred":[
        "Apkorosji"
    ],
    "name:rus_x_preferred":[
        "\u0410\u043f\u043a\u043e\u0440\u043e\u0448\u0438"
    ],
    "wof:name":"Apkoroshi",
    "wof:placetype":"locality"
},
  "geometry": {"coordinates":[136.51667,52.83333],"type":"Point"}
}