{
  "type": "Feature",
  "properties": {
    "gn:admin1_code":"42",
    "gn:asciiname":"Karavay",
    "gn:country_code":"RU",
    "gn:dem":65,
    "gn:feature_class":"P",
    "gn:feature_code":"PPL",
    "gn:name":"Karavay",
    "gn:population":0,
    "gn:timezone":"Europe/Moscow",
    "iso:country":"RU",
    "name:fin_x_preferred":[
        "Korovaisi"
    ],
    "name:rus_x_preferred":[
        "\u041a\u0430\u0440\u0430\u0432\u0430\u0439"
    ],
    "wof:name":"Karavay",
    "wof:placetype":"locality"
},
  "geometry": {"coordinates":[28.66839,59.62892],"type":"Point"}
}