{
  "type": "Feature",
  "properties": {
    "gn:admin1_code":"60",
    "gn:asciiname":"Khmelishche",
    "gn:country_code":"RU",
    "gn:dem":163,
    "gn:feature_class":"P",
    "gn:feature_code":"PPL",
    "gn:name":"Khmelishche",
    "gn:population":0,
    "gn:timezone":"Europe/Moscow",
    "iso:country":"RU",
    "name:rus_x_preferred":[
        "\u0425\u043c\u0435\u043b\u0438\u0449\u0435"
    ],
    "name:und_x_variant":[
        "\u0425\u043c\u0435\u043b\u0438\u0449\u0435"
    ],
    "wof:name":"Khmelishche",
    "wof:placetype":"locality"
},
  "geometry": {"coordinates":[30.77494,55.91333],"type":"Point"}
}