{
  "type": "Feature",
  "properties": {
    "gn:admin1_code":"20",
    "gn:asciiname":"Gogon",
    "gn:country_code":"RU",
    "gn:dem":562,
    "gn:feature_class":"P",
    "gn:feature_code":"PPL",
    "gn:name":"Gogon",
    "gn:population":0,
    "gn:timezone":"Asia/Irkutsk",
    "iso:country":"RU",
    "name:eng_x_preferred":[
        "Gogon"
    ],
    "name:nor_x_preferred":[
        "Gogon"
    ],
    "name:rus_x_preferred":[
        "\u0413\u043e\u0433\u043e\u043d"
    ],
    "wof:name":"Gogon",
    "wof:placetype":"locality"
},
  "geometry": {"coordinates":[105.39583,53.92167],"type":"Point"}
}