{
  "type": "Feature",
  "properties": {
    "gn:admin1_code":"77",
    "gn:asciiname":"Makeyevskoye",
    "gn:cc2":"RU",
    "gn:country_code":"RU",
    "gn:dem":147,
    "gn:feature_class":"P",
    "gn:feature_code":"PPL",
    "gn:name":"Makeyevskoye",
    "gn:population":0,
    "gn:timezone":"Europe/Moscow",
    "iso:country":"RU",
    "name:rus_x_preferred":[
        "\u041c\u0430\u043a\u0435\u0435\u0432\u0441\u043a\u043e\u0435"
    ],
    "name:und_x_variant":[
        "Mokeyevskoye",
        "Makeyevskoye"
    ],
    "wof:name":"Makeyevskoye",
    "wof:placetype":"locality"
},
  "geometry": {"coordinates":[35.61889,57.79806],"type":"Point"}
}