{
  "type": "Feature",
  "properties": {
    "gn:admin1_code":"88",
    "gn:asciiname":"Nagornyy",
    "gn:country_code":"RU",
    "gn:dem":158,
    "gn:feature_class":"P",
    "gn:feature_code":"PPL",
    "gn:name":"Nagornyy",
    "gn:population":686,
    "gn:timezone":"Europe/Moscow",
    "iso:country":"RU",
    "name:rus_x_preferred":[
        "\u041d\u0430\u0433\u043e\u0440\u043d\u044b\u0439"
    ],
    "wof:name":"Nagornyy",
    "wof:placetype":"locality",
    "wof:population":686
},
  "geometry": {"coordinates":[39.83833,57.56114],"type":"Point"}
}