{
  "type": "Feature",
  "properties": {
    "gn:admin1_code":"52.0",
    "gn:asciiname":"Belets",
    "gn:country_code":"RU",
    "gn:dem":23,
    "gn:feature_class":"P",
    "gn:feature_code":"PPL",
    "gn:name":"Belets",
    "gn:population":0,
    "gn:timezone":"Europe/Moscow",
    "iso:country":"RU",
    "name:nor_x_preferred":[
        "Belets"
    ],
    "name:rus_x_preferred":[
        "\u0411\u0435\u043b\u0435\u0446"
    ],
    "wof:name":"Belets",
    "wof:placetype":"locality"
},
  "geometry": {"coordinates":[30.82716,58.24936999999999],"type":"Point"}
}