{
  "type": "Feature",
  "properties": {
    "gn:admin1_code":"20",
    "gn:asciiname":"Ulus Sharagul",
    "gn:cc2":"RU",
    "gn:country_code":"RU",
    "gn:dem":550,
    "gn:feature_class":"P",
    "gn:feature_code":"PPL",
    "gn:name":"Ulus Sharagul",
    "gn:population":0,
    "gn:timezone":"Asia/Irkutsk",
    "iso:country":"RU",
    "name:und_x_variant":[
        "Khud-Sharkey",
        "Ulus Khud-Sharagul",
        "Ulus Sharagul"
    ],
    "wof:name":"Ulus Sharagul",
    "wof:placetype":"locality"
},
  "geometry": {"coordinates":[101.76667,53.41667],"type":"Point"}
}