{
  "type": "Feature",
  "properties": {
    "gn:admin1_code":"11",
    "gn:asciiname":"Nadezhdinskiy",
    "gn:cc2":"RU",
    "gn:country_code":"RU",
    "gn:dem":1355,
    "gn:feature_class":"P",
    "gn:feature_code":"PPL",
    "gn:name":"Nadezhdinskiy",
    "gn:population":0,
    "gn:timezone":"Asia/Irkutsk",
    "iso:country":"RU",
    "name:rus_x_preferred":[
        "\u041d\u0430\u0434\u0435\u0436\u0434\u0438\u043d\u0441\u043a\u0438\u0439"
    ],
    "name:und_x_variant":[
        "Nadezhdinski",
        "Nadezhdinskiy",
        "\u041d\u0430\u0434\u0435\u0436\u0434\u0438\u043d\u0441\u043a\u0438\u0439"
    ],
    "wof:name":"Nadezhdinskiy",
    "wof:placetype":"locality"
},
  "geometry": {"coordinates":[113.56667,55.48333],"type":"Point"}
}