{
  "type": "Feature",
  "properties": {
    "gn:admin1_code":"67",
    "gn:asciiname":"Ryumino",
    "gn:country_code":"RU",
    "gn:dem":157,
    "gn:feature_class":"P",
    "gn:feature_code":"PPL",
    "gn:name":"Ryumino",
    "gn:population":0,
    "gn:timezone":"Europe/Saratov",
    "iso:country":"RU",
    "name:rus_x_preferred":[
        "\u0420\u044e\u043c\u0438\u043d\u043e"
    ],
    "wof:name":"Ryumino",
    "wof:placetype":"locality"
},
  "geometry": {"coordinates":[43.52031,52.12778],"type":"Point"}
}