{
  "type": "Feature",
  "properties": {
    "gn:admin1_code":"70",
    "gn:asciiname":"Podkumok",
    "gn:country_code":"RU",
    "gn:dem":708,
    "gn:feature_class":"P",
    "gn:feature_code":"PPL",
    "gn:name":"Podkumok",
    "gn:population":0,
    "gn:timezone":"Europe/Moscow",
    "iso:country":"RU",
    "name:rus_x_preferred":[
        "\u041f\u043e\u0434\u043a\u0443\u043c\u043e\u043a"
    ],
    "name:und_x_variant":[
        "\u041f\u043e\u0434\u043a\u0443\u043c\u043e\u043a"
    ],
    "wof:name":"Podkumok",
    "wof:placetype":"locality"
},
  "geometry": {"coordinates":[42.75778,43.95139],"type":"Point"}
}