{
  "type": "Feature",
  "properties": {
    "gn:admin1_code":"40",
    "gn:asciiname":"Dvortsy",
    "gn:country_code":"RU",
    "gn:dem":113,
    "gn:feature_class":"P",
    "gn:feature_code":"PPL",
    "gn:name":"Dvortsy",
    "gn:population":0,
    "gn:timezone":"Asia/Yekaterinburg",
    "iso:country":"RU",
    "name:eng_x_preferred":[
        "Dvortsy"
    ],
    "name:nor_x_preferred":[
        "Dvortsy"
    ],
    "name:rus_x_preferred":[
        "\u0414\u0432\u043e\u0440\u0446\u044b"
    ],
    "wof:name":"Dvortsy",
    "wof:placetype":"locality"
},
  "geometry": {"coordinates":[64.55929999999999,56.5202],"type":"Point"}
}