{
  "type": "Feature",
  "properties": {
    "gn:admin1_code":"88",
    "gn:asciiname":"Gorodishchi",
    "gn:country_code":"RU",
    "gn:dem":112,
    "gn:feature_class":"P",
    "gn:feature_code":"PPL",
    "gn:name":"Gorodishchi",
    "gn:population":0,
    "gn:timezone":"Europe/Moscow",
    "iso:country":"RU",
    "name:rus_x_preferred":[
        "\u0413\u043e\u0440\u043e\u0434\u0438\u0449\u0438"
    ],
    "name:und_x_variant":[
        "\u0413\u043e\u0440\u043e\u0434\u0438\u0449\u0438"
    ],
    "wof:name":"Gorodishchi",
    "wof:placetype":"locality"
},
  "geometry": {"coordinates":[38.5676,57.7042],"type":"Point"}
}