{
  "type": "Feature",
  "properties": {
    "gn:admin1_code":"90",
    "gn:asciiname":"Zaborskoye",
    "gn:country_code":"RU",
    "gn:dem":146,
    "gn:feature_class":"P",
    "gn:feature_code":"PPL",
    "gn:name":"Zaborskoye",
    "gn:population":0,
    "gn:timezone":"Asia/Yekaterinburg",
    "iso:country":"RU",
    "name:rus_x_preferred":[
        "\u0417\u0430\u0431\u043e\u0440\u0441\u043a\u043e\u0435"
    ],
    "wof:name":"Zaborskoye",
    "wof:placetype":"locality"
},
  "geometry": {"coordinates":[56.5289,57.4561],"type":"Point"}
}