{
  "type": "Feature",
  "properties": {
    "gn:admin1_code":"69",
    "gn:asciiname":"Savenki",
    "gn:country_code":"RU",
    "gn:dem":224,
    "gn:feature_class":"P",
    "gn:feature_code":"PPL",
    "gn:name":"Savenki",
    "gn:population":0,
    "gn:timezone":"Europe/Moscow",
    "iso:country":"RU",
    "name:che_x_preferred":[
        "\u0421\u0430\u0432\u0435\u043d\u043a\u0438"
    ],
    "name:eng_x_preferred":[
        "Savenki"
    ],
    "name:nor_x_preferred":[
        "Savenki"
    ],
    "name:rus_x_preferred":[
        "\u0421\u0430\u0432\u0435\u043d\u043a\u0438"
    ],
    "name:und_x_variant":[
        "\u0421\u0430\u0432\u0435\u043d\u043a\u0438",
        "Savenki"
    ],
    "wof:name":"Savenki",
    "wof:placetype":"locality"
},
  "geometry": {"coordinates":[34.45627,55.51226],"type":"Point"}
}