{
  "type": "Feature",
  "properties": {
    "gn:admin1_code":"52.0",
    "gn:asciiname":"Bol'shoye Nikulino",
    "gn:country_code":"RU",
    "gn:dem":230,
    "gn:feature_class":"P",
    "gn:feature_code":"PPL",
    "gn:name":"Bol\u2019shoye Nikulino",
    "gn:population":0,
    "gn:timezone":"Europe/Moscow",
    "iso:country":"RU",
    "name:rus_x_preferred":[
        "\u0411\u043e\u043b\u044c\u0448\u043e\u0435 \u041d\u0438\u043a\u0443\u043b\u0438\u043d\u043e"
    ],
    "name:und_x_variant":[
        "Bol\u2019shoye Mikulino",
        "Bol\u2019shoye Nikulino"
    ],
    "wof:name":"Bol'shoye Nikulino",
    "wof:placetype":"locality"
},
  "geometry": {"coordinates":[33.77918,59.17389],"type":"Point"}
}