{
  "type": "Feature",
  "properties": {
    "gn:admin1_code":"38.0",
    "gn:asciiname":"Baturino",
    "gn:country_code":"RU",
    "gn:dem":350,
    "gn:feature_class":"P",
    "gn:feature_code":"PPL",
    "gn:name":"Baturino",
    "gn:population":0,
    "gn:timezone":"Europe/Moscow",
    "iso:country":"RU",
    "name:rus_x_preferred":[
        "\u0411\u0430\u0442\u0443\u0440\u0438\u043d\u043e"
    ],
    "wof:name":"Baturino",
    "wof:placetype":"locality"
},
  "geometry": {"coordinates":[39.91722,43.59806],"type":"Point"}
}