{
  "type": "Feature",
  "properties": {
    "gn:admin1_code":"54",
    "gn:asciiname":"Krugloye",
    "gn:country_code":"RU",
    "gn:dem":110,
    "gn:feature_class":"P",
    "gn:feature_code":"PPL",
    "gn:name":"Krugloye",
    "gn:population":0,
    "gn:timezone":"Asia/Omsk",
    "iso:country":"RU",
    "name:che_x_preferred":[
        "\u041a\u0440\u0443\u0433\u043b\u0438"
    ],
    "name:rus_x_preferred":[
        "\u041a\u0440\u0443\u0433\u043b\u043e\u0435"
    ],
    "name:tgk_x_preferred":[
        "\u041a\u0440\u0443\u0433\u043b\u043e\u0435"
    ],
    "name:und_x_variant":[
        "\u041a\u0440\u0443\u0433\u043b\u043e\u0435"
    ],
    "wof:name":"Krugloye",
    "wof:placetype":"locality"
},
  "geometry": {"coordinates":[73.93333,55.36666999999999],"type":"Point"}
}