{
  "type": "Feature",
  "properties": {
    "gn:admin1_code":"60",
    "gn:asciiname":"Suvorovo",
    "gn:country_code":"RU",
    "gn:dem":122,
    "gn:feature_class":"P",
    "gn:feature_code":"PPL",
    "gn:name":"Suvorovo",
    "gn:population":0,
    "gn:timezone":"Europe/Moscow",
    "iso:country":"RU",
    "name:rus_x_preferred":[
        "\u0421\u0443\u0432\u043e\u0440\u043e\u0432\u043e"
    ],
    "name:und_x_variant":[
        "\u0421\u0443\u0432\u043e\u0440\u043e\u0432\u043e"
    ],
    "wof:name":"Suvorovo",
    "wof:placetype":"locality"
},
  "geometry": {"coordinates":[30.92527,56.38914000000001],"type":"Point"}
}