{
  "type": "Feature",
  "properties": {
    "gn:admin1_code":"84",
    "gn:asciiname":"Grishinskiy",
    "gn:country_code":"RU",
    "gn:dem":66,
    "gn:feature_class":"P",
    "gn:feature_code":"PPL",
    "gn:name":"Grishinskiy",
    "gn:population":0,
    "gn:timezone":"Europe/Volgograd",
    "iso:country":"RU",
    "name:eng_x_preferred":[
        "Grishinskiy"
    ],
    "name:nor_x_preferred":[
        "Grisjinskij"
    ],
    "name:rus_x_preferred":[
        "\u0413\u0440\u0438\u0448\u0438\u043d\u0441\u043a\u0438\u0439"
    ],
    "name:und_x_variant":[
        "Grishin",
        "\u0413\u0440\u0438\u0448\u0438\u043d\u0441\u043a\u0438\u0439",
        "Grishinskiy"
    ],
    "wof:name":"Grishinskiy",
    "wof:placetype":"locality"
},
  "geometry": {"coordinates":[42.4734,50.0168],"type":"Point"}
}