{
  "type": "Feature",
  "properties": {
    "gn:admin1_code":"8",
    "gn:asciiname":"Ik-Vershina",
    "gn:country_code":"RU",
    "gn:dem":323,
    "gn:feature_class":"P",
    "gn:feature_code":"PPL",
    "gn:name":"Ik-Vershina",
    "gn:population":0,
    "gn:timezone":"Asia/Yekaterinburg",
    "iso:country":"RU",
    "name:bak_x_preferred":[
        "\u042b\u04a1-\u0412\u0435\u0440\u0448\u0438\u043d\u0430"
    ],
    "name:che_x_preferred":[
        "\u0418\u043a-\u0412\u0435\u0440\u0448\u0438\u043d\u0430"
    ],
    "name:hye_x_preferred":[
        "\u053b\u056f-\u054e\u0565\u0580\u0577\u056b\u0576\u0561"
    ],
    "name:kaz_x_preferred":[
        "\u0418\u043a-\u0412\u0435\u0440\u0448\u0438\u043d\u0430"
    ],
    "name:kir_x_preferred":[
        "\u0418\u043a-\u0412\u0435\u0440\u0448\u0438\u043d\u0430"
    ],
    "name:rus_x_preferred":[
        "\u0418\u043a-\u0412\u0435\u0440\u0448\u0438\u043d\u0430"
    ],
    "name:tat_x_preferred":[
        "\u042b\u043a\u0431\u0430\u0448"
    ],
    "name:ukr_x_preferred":[
        "\u0406\u043a-\u0412\u0435\u0440\u0448\u0438\u043d\u0430"
    ],
    "name:und_x_variant":[
        "Ik-Vershino",
        "Ik-Vershina",
        "\u0418\u043a-\u0412\u0435\u0440\u0448\u0438\u043d\u0430"
    ],
    "wof:name":"Ik-Vershina",
    "wof:placetype":"locality"
},
  "geometry": {"coordinates":[54.08333,53.95],"type":"Point"}
}