{
  "type": "Feature",
  "properties": {
    "gn:admin1_code":"63",
    "gn:asciiname":"Diring",
    "gn:country_code":"RU",
    "gn:dem":194,
    "gn:feature_class":"P",
    "gn:feature_code":"PPL",
    "gn:name":"Diring",
    "gn:population":0,
    "gn:timezone":"Asia/Yakutsk",
    "iso:country":"RU",
    "name:eng_x_preferred":[
        "Diring"
    ],
    "name:nor_x_preferred":[
        "Diring"
    ],
    "name:rus_x_preferred":[
        "\u0414\u0438\u0440\u0438\u043d\u0433"
    ],
    "name:und_x_variant":[
        "\u0414\u0438\u0440\u0438\u043d\u0433",
        "Diring"
    ],
    "wof:name":"Diring",
    "wof:placetype":"locality"
},
  "geometry": {"coordinates":[132.12402,61.84551999999999],"type":"Point"}
}