{
  "type": "Feature",
  "properties": {
    "gn:admin1_code":"88",
    "gn:asciiname":"Aleksino",
    "gn:country_code":"RU",
    "gn:dem":168,
    "gn:feature_class":"P",
    "gn:feature_code":"PPL",
    "gn:name":"Aleksino",
    "gn:population":0,
    "gn:timezone":"Europe/Moscow",
    "iso:country":"RU",
    "name:rus_x_preferred":[
        "\u0410\u043b\u0435\u043a\u0441\u0438\u043d\u043e"
    ],
    "wof:name":"Aleksino",
    "wof:placetype":"locality"
},
  "geometry": {"coordinates":[38.7046,57.2146],"type":"Point"}
}