{
  "type": "Feature",
  "properties": {
    "gn:admin1_code":"33.0",
    "gn:asciiname":"Permyaki",
    "gn:country_code":"RU",
    "gn:dem":152,
    "gn:feature_class":"P",
    "gn:feature_code":"PPL",
    "gn:name":"Permyaki",
    "gn:population":0,
    "gn:timezone":"Europe/Kirov",
    "iso:country":"RU",
    "name:che_x_preferred":[
        "\u041f\u0435\u0440\u043c\u044f\u043a\u0438"
    ],
    "name:rus_x_preferred":[
        "\u041f\u0435\u0440\u043c\u044f\u043a\u0438"
    ],
    "wof:name":"Permyaki",
    "wof:placetype":"locality"
},
  "geometry": {"coordinates":[48.48486,57.87135],"type":"Point"}
}