{
  "type": "Feature",
  "properties": {
    "gn:admin1_code":"17",
    "gn:admin2_code":"Tsuntinskiy Rayon",
    "gn:asciiname":"Otsikh",
    "gn:country_code":"RU",
    "gn:dem":1811,
    "gn:feature_class":"P",
    "gn:feature_code":"PPL",
    "gn:name":"Otsikh",
    "gn:population":0,
    "gn:timezone":"Europe/Moscow",
    "iso:country":"RU",
    "name:rus_x_preferred":[
        "\u041e\u0446\u0438\u0445"
    ],
    "name:und_x_variant":[
        "\u041e\u0446\u0438\u0445"
    ],
    "wof:name":"Otsikh",
    "wof:placetype":"locality"
},
  "geometry": {"coordinates":[45.87558,42.23297],"type":"Point"}
}