{
  "type": "Feature",
  "properties": {
    "gn:admin1_code":"45.0",
    "gn:asciiname":"Tatarskiy Chodrayal",
    "gn:country_code":"RU",
    "gn:dem":153,
    "gn:feature_class":"P",
    "gn:feature_code":"PPL",
    "gn:name":"Tatarskiy Chodrayal",
    "gn:population":0,
    "gn:timezone":"Europe/Moscow",
    "iso:country":"RU",
    "name:rus_x_preferred":[
        "\u0422\u0430\u0442\u0430\u0440\u0441\u043a\u0438\u0439 \u0427\u043e\u0434\u0440\u0430\u044f\u043b"
    ],
    "wof:name":"Tatarskiy Chodrayal",
    "wof:placetype":"locality"
},
  "geometry": {"coordinates":[49.34056,56.40778],"type":"Point"}
}