{
  "type": "Feature",
  "properties": {
    "gn:admin1_code":"38.0",
    "gn:asciiname":"Fontalovskaya",
    "gn:country_code":"RU",
    "gn:dem":60,
    "gn:feature_class":"P",
    "gn:feature_code":"PPL",
    "gn:name":"Fontalovskaya",
    "gn:population":0,
    "gn:timezone":"Europe/Moscow",
    "iso:country":"RU",
    "name:cat_x_preferred":[
        "Fontal\u00f3vskaia"
    ],
    "name:che_x_preferred":[
        "\u0424\u043e\u043d\u0442\u0430\u043b\u043e\u0432\u0441\u043a\u0438"
    ],
    "name:rus_x_preferred":[
        "\u0424\u043e\u043d\u0442\u0430\u043b\u043e\u0432\u0441\u043a\u0430\u044f"
    ],
    "name:spa_x_preferred":[
        "Fontalovskaya"
    ],
    "name:und_x_variant":[
        "Fontonowskaja",
        "Fontan",
        "Fontanowskaja",
        "Fontalovskaya",
        "\u0424\u043e\u043d\u0442\u0430\u043b\u043e\u0432\u0441\u043a\u0430\u044f"
    ],
    "wof:name":"Fontalovskaya",
    "wof:placetype":"locality"
},
  "geometry": {"coordinates":[36.93601,45.36403],"type":"Point"}
}