{
  "type": "Feature",
  "properties": {
    "gn:admin1_code":"67.0",
    "gn:asciiname":"Bobrovyy Gay",
    "gn:country_code":"RU",
    "gn:dem":41,
    "gn:feature_class":"P",
    "gn:feature_code":"PPL",
    "gn:name":"Bobrovyy Gay",
    "gn:population":0,
    "gn:timezone":"Europe/Saratov",
    "iso:country":"RU",
    "name:eng_x_preferred":[
        "Bobrov Gay"
    ],
    "name:nor_x_preferred":[
        "Bobrovyj Gaj"
    ],
    "name:rus_x_preferred":[
        "\u0411\u043e\u0431\u0440\u043e\u0432\u044b\u0439 \u0413\u0430\u0439"
    ],
    "name:und_x_variant":[
        "Bobrov Gay",
        "Bobrovyy Gay"
    ],
    "wof:name":"Bobrovyy Gay",
    "wof:placetype":"locality"
},
  "geometry": {"coordinates":[49.3972,51.6648],"type":"Point"}
}