{
  "type": "Feature",
  "properties": {
    "gn:country":"RU",
    "gn:fcode":"PPL",
    "gn:pop":0,
    "iso:country":"RU",
    "name:nor_x_preferred":[
        "Berjozovka"
    ],
    "name:rus_x_preferred":[
        "\u0411\u0435\u0440\u0451\u0437\u043e\u0432\u043a\u0430"
    ],
    "name:unk_x_variant":[
        "Ber\u00ebzovka"
    ],
    "qs:name":"Berezovka",
    "qs:name_adm0":"Russia",
    "qs:name_adm1":"Altai Krai",
    "qs:photos_9r":0,
    "qs:photos_sr":0,
    "qs:placetype":"Town",
    "qs:pop_sr":"0",
    "wd:wordcount":39,
    "wof:name":"Berezovka",
    "wof:placetype":"locality",
    "wof:population":0
},
  "geometry": {"coordinates":[84.0009,53.4034],"type":"Point"}
}