{
  "type": "Feature",
  "properties": {
    "gn:admin1_code":"52.0",
    "gn:asciiname":"Orekhovno Pervoye",
    "gn:country_code":"RU",
    "gn:dem":166,
    "gn:feature_class":"P",
    "gn:feature_code":"PPL",
    "gn:name":"Orekhovno Pervoye",
    "gn:population":0,
    "gn:timezone":"Europe/Moscow",
    "iso:country":"RU",
    "wof:name":"Orekhovno Pervoye",
    "wof:placetype":"locality"
},
  "geometry": {"coordinates":[33.33278,58.30139000000001],"type":"Point"}
}