{
  "type": "Feature",
  "properties": {
    "gn:country":"RU",
    "gn:fcode":"PPL",
    "gn:population":0,
    "iso:country":"RU",
    "name:eng_x_preferred":[
        "Yelshanka"
    ],
    "name:nor_x_preferred":[
        "Jelsjanka"
    ],
    "name:rus_x_preferred":[
        "\u0415\u043b\u0448\u0430\u043d\u043a\u0430"
    ],
    "qs:name":"Yelshanka",
    "qs:name_adm0":"Russia",
    "qs:name_adm1":"Saratov Oblast",
    "qs:photos_9r":0,
    "qs:photos_sr":0,
    "qs:placetype":"Town",
    "qs:pop_sr":"0",
    "wof:name":"Yelshanka",
    "wof:placetype":"locality",
    "wof:population":0
},
  "geometry": {"coordinates":[46.39972,51.81389],"type":"Point"}
}