{
  "type": "Feature",
  "properties": {
    "gn:admin1_code":"90.0",
    "gn:asciiname":"Aspa",
    "gn:country_code":"RU",
    "gn:dem":204,
    "gn:feature_class":"P",
    "gn:feature_code":"PPL",
    "gn:name":"Aspa",
    "gn:population":0,
    "gn:timezone":"Asia/Yekaterinburg",
    "iso:country":"RU",
    "name:eng_x_preferred":[
        "Aspa"
    ],
    "name:nor_x_preferred":[
        "Aspa"
    ],
    "name:rus_x_preferred":[
        "\u0410\u0441\u043f\u0430"
    ],
    "wof:name":"Aspa",
    "wof:placetype":"locality"
},
  "geometry": {"coordinates":[56.34086,56.85596999999999],"type":"Point"}
}