{
  "type": "Feature",
  "properties": {
    "gn:admin1_code":"71",
    "gn:asciiname":"Rudnyy",
    "gn:country_code":"RU",
    "gn:dem":330,
    "gn:feature_class":"P",
    "gn:feature_code":"PPL",
    "gn:name":"Rudnyy",
    "gn:population":0,
    "gn:timezone":"Asia/Yekaterinburg",
    "iso:country":"RU",
    "name:rus_x_preferred":[
        "\u0420\u0443\u0434\u043d\u044b\u0439"
    ],
    "wof:name":"Rudnyy",
    "wof:placetype":"locality"
},
  "geometry": {"coordinates":[60.6367,56.7229],"type":"Point"}
}