{
  "type": "Feature",
  "properties": {
    "gn:admin1_code":"69",
    "gn:asciiname":"Merkuchevo",
    "gn:country_code":"RU",
    "gn:dem":224,
    "gn:feature_class":"P",
    "gn:feature_code":"PPL",
    "gn:name":"Merkuchevo",
    "gn:population":0,
    "gn:timezone":"Europe/Moscow",
    "iso:country":"RU",
    "name:eng_x_preferred":[
        "Merkuchevo"
    ],
    "name:nor_x_preferred":[
        "Merkutsjevo"
    ],
    "name:rus_x_preferred":[
        "\u041c\u0435\u0440\u043a\u0443\u0447\u0435\u0432\u043e"
    ],
    "name:und_x_variant":[
        "\u041c\u0435\u0440\u043a\u0443\u0447\u0435\u0432\u043e",
        "Merkuchevo"
    ],
    "wof:name":"Merkuchevo",
    "wof:placetype":"locality"
},
  "geometry": {"coordinates":[34.32224,55.36864],"type":"Point"}
}