{
  "type": "Feature",
  "properties": {
    "gn:admin1_code":"85",
    "gn:asciiname":"Pleso",
    "gn:country_code":"RU",
    "gn:dem":92,
    "gn:feature_class":"P",
    "gn:feature_code":"PPL",
    "gn:name":"Pl\u00ebso",
    "gn:population":0,
    "gn:timezone":"Europe/Moscow",
    "iso:country":"RU",
    "name:rus_x_preferred":[
        "\u041f\u043b\u0451\u0441\u043e"
    ],
    "name:und_x_variant":[
        "Pl\u00ebso"
    ],
    "wof:name":"Pleso",
    "wof:placetype":"locality"
},
  "geometry": {"coordinates":[46.4073,60.0305],"type":"Point"}
}