{
  "type": "Feature",
  "properties": {
    "gn:admin1_code":"69",
    "gn:asciiname":"Krestets",
    "gn:country_code":"RU",
    "gn:dem":186,
    "gn:feature_class":"P",
    "gn:feature_code":"PPL",
    "gn:name":"Krestets",
    "gn:population":0,
    "gn:timezone":"Europe/Moscow",
    "iso:country":"RU",
    "name:rus_x_preferred":[
        "\u041a\u0440\u0435\u0441\u0442\u0435\u0446"
    ],
    "name:und_x_variant":[
        "\u041a\u0440\u0435\u0441\u0442\u0435\u0446"
    ],
    "wof:name":"Krestets",
    "wof:placetype":"locality"
},
  "geometry": {"coordinates":[34.75,55.73333],"type":"Point"}
}