{
  "type": "Feature",
  "properties": {
    "gn:admin1_code":"51",
    "gn:asciiname":"Zyablitsa",
    "gn:country_code":"RU",
    "gn:dem":121,
    "gn:feature_class":"P",
    "gn:feature_code":"PPL",
    "gn:name":"Zyablitsa",
    "gn:population":0,
    "gn:timezone":"Europe/Moscow",
    "iso:country":"RU",
    "name:rus_x_preferred":[
        "\u0417\u044f\u0431\u043b\u0438\u0446\u0430"
    ],
    "name:und_x_variant":[
        "\u0417\u044f\u0431\u043b\u0438\u0446\u0430"
    ],
    "wof:name":"Zyablitsa",
    "wof:placetype":"locality"
},
  "geometry": {"coordinates":[44.9573,57.4427],"type":"Point"}
}