{
  "type": "Feature",
  "properties": {
    "gn:admin1_code":"56",
    "gn:asciiname":"Kuliga",
    "gn:country_code":"RU",
    "gn:dem":174,
    "gn:feature_class":"P",
    "gn:feature_code":"PPL",
    "gn:name":"Kuliga",
    "gn:population":0,
    "gn:timezone":"Europe/Moscow",
    "iso:country":"RU",
    "name:che_x_preferred":[
        "\u041a\u0443\u043b\u0438\u0433\u0430"
    ],
    "name:rus_x_preferred":[
        "\u041a\u0443\u043b\u0438\u0433\u0430"
    ],
    "name:tgk_x_preferred":[
        "\u041a\u0443\u043b\u0438\u0433\u0430"
    ],
    "wof:name":"Kuliga",
    "wof:placetype":"locality"
},
  "geometry": {"coordinates":[35.8342,52.5199],"type":"Point"}
}