{
  "type": "Feature",
  "properties": {
    "gn:admin1_code":"54",
    "gn:asciiname":"Krasnoyarka",
    "gn:country_code":"RU",
    "gn:dem":110,
    "gn:feature_class":"P",
    "gn:feature_code":"PPL",
    "gn:name":"Krasnoyarka",
    "gn:population":0,
    "gn:timezone":"Asia/Omsk",
    "iso:country":"RU",
    "name:eng_x_preferred":[
        "Krasnoyarka"
    ],
    "name:nor_x_preferred":[
        "Krasnojarka"
    ],
    "name:rus_x_preferred":[
        "\u041a\u0440\u0430\u0441\u043d\u043e\u044f\u0440\u043a\u0430"
    ],
    "name:und_x_variant":[
        "Krasnoyarskoye",
        "\u041a\u0440\u0430\u0441\u043d\u043e\u044f\u0440\u043a\u0430",
        "Krasnoyarka"
    ],
    "wof:name":"Krasnoyarka",
    "wof:placetype":"locality"
},
  "geometry": {"coordinates":[72.67228,54.38583000000001],"type":"Point"}
}