{
  "type": "Feature",
  "properties": {
    "gn:admin1_code":"11",
    "gn:asciiname":"Durbenskaya",
    "gn:country_code":"RU",
    "gn:dem":582,
    "gn:feature_class":"P",
    "gn:feature_code":"PPL",
    "gn:name":"Durbenskaya",
    "gn:population":0,
    "gn:timezone":"Asia/Irkutsk",
    "iso:country":"RU",
    "wof:name":"Durbenskaya",
    "wof:placetype":"locality"
},
  "geometry": {"coordinates":[106.27611,50.50917000000001],"type":"Point"}
}