{
  "type": "Feature",
  "properties": {
    "gn:admin1_code":"60",
    "gn:asciiname":"Telezhniki",
    "gn:country_code":"RU",
    "gn:dem":152,
    "gn:feature_class":"P",
    "gn:feature_code":"PPL",
    "gn:name":"Telezhniki",
    "gn:population":0,
    "gn:timezone":"Europe/Moscow",
    "iso:country":"RU",
    "name:rus_x_preferred":[
        "\u0422\u0435\u043b\u0435\u0436\u043d\u0438\u043a\u0438"
    ],
    "wof:name":"Telezhniki",
    "wof:placetype":"locality"
},
  "geometry": {"coordinates":[28.8785,56.22026999999999],"type":"Point"}
}