{
  "type": "Feature",
  "properties": {
    "gn:admin1_code":"30",
    "gn:asciiname":"Umal'tinski'y",
    "gn:country_code":"RU",
    "gn:dem":769,
    "gn:feature_class":"P",
    "gn:feature_code":"PPL",
    "gn:name":"Umal\u2019tinski\u2019y",
    "gn:population":0,
    "gn:timezone":"Asia/Vladivostok",
    "iso:country":"RU",
    "name:eng_x_preferred":[
        "Umal'tinski'y"
    ],
    "name:nor_x_preferred":[
        "Umaltinskij"
    ],
    "name:rus_x_preferred":[
        "\u0423\u043c\u0430\u043b\u044c\u0442\u0438\u043d\u0441\u043a\u0438\u0439"
    ],
    "name:und_x_variant":[
        "Polovinka",
        "Ul\u2019matinskiy",
        "Zaimka Polovinka",
        "Umal\u2019tinski\u2019y"
    ],
    "wof:name":"Umal'tinski'y",
    "wof:placetype":"locality"
},
  "geometry": {"coordinates":[133.59999999999999,51.93333],"type":"Point"}
}