{
  "type": "Feature",
  "properties": {
    "gn:admin1_code":"23",
    "gn:asciiname":"Bilshofen",
    "gn:country_code":"RU",
    "gn:dem":89,
    "gn:feature_class":"P",
    "gn:feature_code":"PPL",
    "gn:name":"Bilsh\u00f6fen",
    "gn:population":0,
    "gn:timezone":"Europe/Kaliningrad",
    "iso:country":"RU",
    "wof:name":"Bilshofen",
    "wof:placetype":"locality"
},
  "geometry": {"coordinates":[20.05917,54.42471999999999],"type":"Point"}
}