{
  "type": "Feature",
  "properties": {
    "gn:admin1_code":"90.0",
    "gn:asciiname":"Oreshkovo",
    "gn:country_code":"RU",
    "gn:dem":141,
    "gn:feature_class":"P",
    "gn:feature_code":"PPL",
    "gn:name":"Oreshkovo",
    "gn:population":0,
    "gn:timezone":"Asia/Yekaterinburg",
    "iso:country":"RU",
    "name:rus_x_preferred":[
        "\u041e\u0440\u0435\u0448\u043a\u043e\u0432\u043e"
    ],
    "wof:name":"Oreshkovo",
    "wof:placetype":"locality"
},
  "geometry": {"coordinates":[55.6549,58.7992],"type":"Point"}
}