{
  "type": "Feature",
  "properties": {
    "gn:admin1_code":"10",
    "gn:asciiname":"Rakov",
    "gn:country_code":"RU",
    "gn:dem":140,
    "gn:feature_class":"P",
    "gn:feature_code":"PPL",
    "gn:name":"Rakov",
    "gn:population":0,
    "gn:timezone":"Europe/Moscow",
    "iso:country":"RU",
    "name:ceb_x_preferred":[
        "Rakov"
    ],
    "name:ces_x_preferred":[
        "Rakov"
    ],
    "name:deu_x_preferred":[
        "Rakov"
    ],
    "name:rus_x_preferred":[
        "\u0420\u0430\u043a\u043e\u0432"
    ],
    "name:slk_x_preferred":[
        "Rakov"
    ],
    "name:swe_x_preferred":[
        "Rakov"
    ],
    "wof:name":"Rakov",
    "wof:placetype":"locality"
},
  "geometry": {"coordinates":[33.3237,52.5626],"type":"Point"}
}