{
  "type": "Feature",
  "properties": {
    "gn:admin1_code":"60",
    "gn:asciiname":"Cherno",
    "gn:country_code":"RU",
    "gn:dem":87,
    "gn:feature_class":"P",
    "gn:feature_code":"PPL",
    "gn:name":"Cherno",
    "gn:population":0,
    "gn:timezone":"Europe/Moscow",
    "iso:country":"RU",
    "name:rus_x_preferred":[
        "\u0427\u0435\u0440\u043d\u043e"
    ],
    "name:ukr_x_preferred":[
        "\u0427\u0435\u0440\u043d\u043e"
    ],
    "wof:name":"Cherno",
    "wof:placetype":"locality"
},
  "geometry": {"coordinates":[28.2389,58.8436],"type":"Point"}
}