{
  "type": "Feature",
  "properties": {
    "gn:admin1_code":"8",
    "gn:asciiname":"Kargala",
    "gn:country_code":"RU",
    "gn:dem":490,
    "gn:feature_class":"P",
    "gn:feature_code":"PPL",
    "gn:name":"Kargala",
    "gn:population":0,
    "gn:timezone":"Asia/Yekaterinburg",
    "iso:country":"RU",
    "name:rus_x_preferred":[
        "\u041a\u0430\u0440\u0433\u0430\u043b\u0430"
    ],
    "name:und_x_variant":[
        "\u041a\u0430\u0440\u0433\u0430\u043b\u0430"
    ],
    "wof:name":"Kargala",
    "wof:placetype":"locality"
},
  "geometry": {"coordinates":[57.0944,52.1244],"type":"Point"}
}