{
  "type": "Feature",
  "properties": {
    "gn:admin1_code":"16",
    "gn:asciiname":"Bolshiye Tokshiki",
    "gn:country_code":"RU",
    "gn:dem":159,
    "gn:feature_class":"P",
    "gn:feature_code":"PPL",
    "gn:name":"Bolshiye Tokshiki",
    "gn:population":0,
    "gn:timezone":"Europe/Moscow",
    "iso:country":"RU",
    "name:rus_x_preferred":[
        "\u0411\u043e\u043b\u0448\u0438\u0435 \u0422\u043e\u043a\u0448\u0438\u043a\u0438"
    ],
    "name:und_x_variant":[
        "Toksh",
        "Tokshiki",
        "Bolshiye Tokshiki",
        "\u0411\u043e\u043b\u0448\u0438\u0435 \u0422\u043e\u043a\u0448\u0438\u043a\u0438"
    ],
    "wof:name":"Bolshiye Tokshiki",
    "wof:placetype":"locality"
},
  "geometry": {"coordinates":[46.65069,55.92643],"type":"Point"}
}