{
  "type": "Feature",
  "properties": {
    "gn:admin1_code":"85",
    "gn:asciiname":"Krutets",
    "gn:country_code":"RU",
    "gn:dem":197,
    "gn:feature_class":"P",
    "gn:feature_code":"PPL",
    "gn:name":"Krutets",
    "gn:population":0,
    "gn:timezone":"Europe/Moscow",
    "iso:country":"RU",
    "name:eng_x_preferred":[
        "Krutets"
    ],
    "name:nor_x_preferred":[
        "Krutets"
    ],
    "name:rus_x_preferred":[
        "\u041a\u0440\u0443\u0442\u0435\u0446"
    ],
    "wof:name":"Krutets",
    "wof:placetype":"locality"
},
  "geometry": {"coordinates":[44.68444,59.91686],"type":"Point"}
}