{
  "type": "Feature",
  "properties": {
    "gn:admin1_code":"25",
    "gn:asciiname":"Matyukovo",
    "gn:country_code":"RU",
    "gn:dem":194,
    "gn:feature_class":"P",
    "gn:feature_code":"PPL",
    "gn:name":"Matyukovo",
    "gn:population":0,
    "gn:timezone":"Europe/Moscow",
    "iso:country":"RU",
    "name:eng_x_preferred":[
        "Matyukovo"
    ],
    "name:nor_x_preferred":[
        "Matjukovo"
    ],
    "name:rus_x_preferred":[
        "\u041c\u0430\u0442\u044e\u043a\u043e\u0432\u043e"
    ],
    "name:und_x_variant":[
        "\u041c\u0430\u0442\u044e\u043a\u043e\u0432\u043e",
        "Matyukovo"
    ],
    "wof:name":"Matyukovo",
    "wof:placetype":"locality"
},
  "geometry": {"coordinates":[35.82849,54.41583000000001],"type":"Point"}
}