{
  "type": "Feature",
  "properties": {
    "gn:admin1_code":"33",
    "gn:asciiname":"Mikhaylovskoye",
    "gn:country_code":"RU",
    "gn:dem":129,
    "gn:feature_class":"P",
    "gn:feature_code":"PPL",
    "gn:name":"Mikhaylovskoye",
    "gn:population":0,
    "gn:timezone":"Europe/Kirov",
    "iso:country":"RU",
    "name:rus_x_preferred":[
        "\u041c\u0438\u0445\u0430\u0439\u043b\u043e\u0432\u0441\u043a\u043e\u0435"
    ],
    "name:und_x_variant":[
        "\u041c\u0438\u0445\u0430\u0439\u043b\u043e\u0432\u0441\u043a\u043e\u0435"
    ],
    "wof:name":"Mikhaylovskoye",
    "wof:placetype":"locality"
},
  "geometry": {"coordinates":[49.83333,56.91667],"type":"Point"}
}