{
  "type": "Feature",
  "properties": {
    "gn:admin1_code":"77",
    "gn:asciiname":"Rastoropovo",
    "gn:country_code":"RU",
    "gn:dem":166,
    "gn:feature_class":"P",
    "gn:feature_code":"PPL",
    "gn:name":"Rastoropovo",
    "gn:population":0,
    "gn:timezone":"Europe/Moscow",
    "iso:country":"RU",
    "name:rus_x_preferred":[
        "\u0420\u0430\u0441\u0442\u043e\u0440\u043e\u043f\u043e\u0432\u043e"
    ],
    "wof:name":"Rastoropovo",
    "wof:placetype":"locality"
},
  "geometry": {"coordinates":[36.7365,58.4293],"type":"Point"}
}