{
  "type": "Feature",
  "properties": {
    "gn:admin1_code":"80.0",
    "gn:asciiname":"Chernyshi",
    "gn:country_code":"RU",
    "gn:dem":204,
    "gn:feature_class":"P",
    "gn:feature_code":"PPL",
    "gn:name":"Chernyshi",
    "gn:population":0,
    "gn:timezone":"Europe/Samara",
    "iso:country":"RU",
    "name:rus_x_preferred":[
        "\u0427\u0435\u0440\u043d\u044b\u0448\u0438"
    ],
    "wof:name":"Chernyshi",
    "wof:placetype":"locality"
},
  "geometry": {"coordinates":[52.2869,57.7596],"type":"Point"}
}