{
  "type": "Feature",
  "properties": {
    "gn:admin1_code":"85.0",
    "gn:asciiname":"Kiyevskaya",
    "gn:country_code":"RU",
    "gn:dem":156,
    "gn:feature_class":"P",
    "gn:feature_code":"PPL",
    "gn:name":"Kiyevskaya",
    "gn:population":0,
    "gn:timezone":"Europe/Moscow",
    "iso:country":"RU",
    "name:rus_x_preferred":[
        "\u041a\u0438\u0435\u0432\u0441\u043a\u0430\u044f"
    ],
    "wof:name":"Kiyevskaya",
    "wof:placetype":"locality"
},
  "geometry": {"coordinates":[39.6139,60.1411],"type":"Point"}
}