{
  "type": "Feature",
  "properties": {
    "gn:admin1_code":"67",
    "gn:asciiname":"Nonkin",
    "gn:country_code":"RU",
    "gn:dem":96,
    "gn:feature_class":"P",
    "gn:feature_code":"PPL",
    "gn:name":"Nonkin",
    "gn:population":0,
    "gn:timezone":"Europe/Saratov",
    "iso:country":"RU",
    "name:rus_x_preferred":[
        "\u041d\u043e\u043d\u043a\u0438\u043d"
    ],
    "wof:name":"Nonkin",
    "wof:placetype":"locality"
},
  "geometry": {"coordinates":[49.9555,51.3087],"type":"Point"}
}