{
  "type": "Feature",
  "properties": {
    "gn:admin1_code":"85",
    "gn:asciiname":"Ploskovo",
    "gn:country_code":"RU",
    "gn:dem":194,
    "gn:feature_class":"P",
    "gn:feature_code":"PPL",
    "gn:name":"Ploskovo",
    "gn:population":0,
    "gn:timezone":"Europe/Moscow",
    "iso:country":"RU",
    "name:rus_x_preferred":[
        "\u041f\u043b\u043e\u0441\u043a\u043e\u0432\u043e"
    ],
    "name:und_x_variant":[
        "Ploskoye",
        "Ploskovo",
        "\u041f\u043b\u043e\u0441\u043a\u043e\u0432\u043e"
    ],
    "wof:name":"Ploskovo",
    "wof:placetype":"locality"
},
  "geometry": {"coordinates":[41.02139,59.94409],"type":"Point"}
}