{
  "type": "Feature",
  "properties": {
    "gn:admin1_code":"88",
    "gn:asciiname":"Bol'shoye Ivan'kovo",
    "gn:country_code":"RU",
    "gn:dem":139,
    "gn:feature_class":"P",
    "gn:feature_code":"PPL",
    "gn:name":"Bol\u2019shoye Ivan\u2019kovo",
    "gn:population":0,
    "gn:timezone":"Europe/Moscow",
    "iso:country":"RU",
    "name:rus_x_preferred":[
        "\u0411\u043e\u043b\u044c\u0448\u043e\u0435 \u0418\u0432\u0430\u043d\u044c\u043a\u043e\u0432\u043e"
    ],
    "name:und_x_variant":[
        "Bol\u2019shoye Ivan\u2019kovo"
    ],
    "wof:name":"Bol'shoye Ivan'kovo",
    "wof:placetype":"locality"
},
  "geometry": {"coordinates":[37.8826,58.1444],"type":"Point"}
}