{
  "type": "Feature",
  "properties": {
    "gn:admin1_code":"77",
    "gn:asciiname":"Griganovo",
    "gn:country_code":"RU",
    "gn:dem":178,
    "gn:feature_class":"P",
    "gn:feature_code":"PPL",
    "gn:name":"Griganovo",
    "gn:population":0,
    "gn:timezone":"Europe/Moscow",
    "iso:country":"RU",
    "name:rus_x_preferred":[
        "\u0413\u0440\u0438\u0433\u0430\u043d\u043e\u0432\u043e"
    ],
    "wof:name":"Griganovo",
    "wof:placetype":"locality"
},
  "geometry": {"coordinates":[34.78349,57.34506],"type":"Point"}
}