{
  "type": "Feature",
  "properties": {
    "gn:admin1_code":"76",
    "gn:asciiname":"Churakovo",
    "gn:country_code":"RU",
    "gn:dem":209,
    "gn:feature_class":"P",
    "gn:feature_code":"PPL",
    "gn:name":"Churakovo",
    "gn:population":0,
    "gn:timezone":"Europe/Moscow",
    "iso:country":"RU",
    "name:rus_x_preferred":[
        "\u0427\u0443\u0440\u0430\u043a\u043e\u0432\u043e"
    ],
    "name:und_x_variant":[
        "\u0427\u0443\u0440\u0430\u043a\u043e\u0432\u043e"
    ],
    "wof:name":"Churakovo",
    "wof:placetype":"locality"
},
  "geometry": {"coordinates":[37.14528,53.83083000000001],"type":"Point"}
}