{
  "type": "Feature",
  "properties": {
    "gn:admin1_code":"6",
    "gn:asciiname":"Toymushka",
    "gn:country_code":"RU",
    "gn:dem":52,
    "gn:feature_class":"P",
    "gn:feature_code":"PPL",
    "gn:name":"Toymushka",
    "gn:population":0,
    "gn:timezone":"Europe/Moscow",
    "iso:country":"RU",
    "name:rus_x_preferred":[
        "\u0422\u043e\u0439\u043c\u0443\u0448\u043a\u0430"
    ],
    "wof:name":"Toymushka",
    "wof:placetype":"locality"
},
  "geometry": {"coordinates":[44.9772,62.2464],"type":"Point"}
}