{
  "type": "Feature",
  "properties": {
    "gn:admin1_code":"12",
    "gn:admin2_code":"Itum-Kalinskiy Rayon",
    "gn:asciiname":"Khulandoy",
    "gn:country_code":"RU",
    "gn:dem":1788,
    "gn:feature_class":"P",
    "gn:feature_code":"PPL",
    "gn:name":"Khulandoy",
    "gn:population":0,
    "gn:timezone":"Europe/Moscow",
    "iso:country":"RU",
    "name:che_x_preferred":[
        "Xulanda"
    ],
    "name:che_x_variant":[
        "\u0425\u0443\u043b\u0430\u043d\u0434\u0430"
    ],
    "name:rus_x_preferred":[
        "\u0425\u0443\u043b\u0430\u043d\u0434\u043e\u0439"
    ],
    "name:und_x_variant":[
        "Hulandoj"
    ],
    "wof:name":"Khulandoy",
    "wof:placetype":"locality"
},
  "geometry": {"coordinates":[45.756,42.55494],"type":"Point"}
}