{
  "type": "Feature",
  "properties": {
    "gn:admin1_code":"80",
    "gn:asciiname":"Povarenki",
    "gn:country_code":"RU",
    "gn:dem":99,
    "gn:feature_class":"P",
    "gn:feature_code":"PPL",
    "gn:name":"Povar\u00ebnki",
    "gn:population":0,
    "gn:timezone":"Europe/Samara",
    "iso:country":"RU",
    "name:nor_x_preferred":[
        "Povarjonki"
    ],
    "name:rus_x_preferred":[
        "\u041f\u043e\u0432\u0430\u0440\u0451\u043d\u043a\u0438"
    ],
    "name:und_x_variant":[
        "Poverenki",
        "Povar\u00ebnki"
    ],
    "wof:name":"Povarenki",
    "wof:placetype":"locality"
},
  "geometry": {"coordinates":[53.78898,56.82906],"type":"Point"}
}