{
  "type": "Feature",
  "properties": {
    "gn:admin1_code":"47",
    "gn:asciiname":"Mukovnino",
    "gn:country_code":"RU",
    "gn:dem":138,
    "gn:feature_class":"P",
    "gn:feature_code":"PPL",
    "gn:name":"Mukovnino",
    "gn:population":0,
    "gn:timezone":"Europe/Moscow",
    "iso:country":"RU",
    "name:rus_x_preferred":[
        "\u041c\u0443\u043a\u043e\u0432\u043d\u0438\u043d\u043e"
    ],
    "wof:name":"Mukovnino",
    "wof:placetype":"locality"
},
  "geometry": {"coordinates":[37.12187,55.07746],"type":"Point"}
}