{
  "type": "Feature",
  "properties": {
    "gn:admin1_code":"77",
    "gn:asciiname":"Gorovatka",
    "gn:country_code":"RU",
    "gn:dem":216,
    "gn:feature_class":"P",
    "gn:feature_code":"PPL",
    "gn:name":"Gorovatka",
    "gn:population":0,
    "gn:timezone":"Europe/Moscow",
    "iso:country":"RU",
    "name:rus_x_preferred":[
        "\u0413\u043e\u0440\u043e\u0432\u0430\u0442\u043a\u0430"
    ],
    "wof:name":"Gorovatka",
    "wof:placetype":"locality"
},
  "geometry": {"coordinates":[32.24072,55.72415],"type":"Point"}
}