{
  "type": "Feature",
  "properties": {
    "gn:admin1_code":"75",
    "gn:asciiname":"Vertikos",
    "gn:country_code":"RU",
    "gn:dem":63,
    "gn:feature_class":"P",
    "gn:feature_code":"PPL",
    "gn:name":"Vertikos",
    "gn:population":0,
    "gn:timezone":"Asia/Tomsk",
    "iso:country":"RU",
    "name:eng_x_preferred":[
        "Vertikos"
    ],
    "name:nor_x_preferred":[
        "Vertikos"
    ],
    "name:rus_x_preferred":[
        "\u0412\u0435\u0440\u0442\u0438\u043a\u043e\u0441"
    ],
    "name:und_x_variant":[
        "Vertikoye"
    ],
    "wof:name":"Vertikos",
    "wof:placetype":"locality"
},
  "geometry": {"coordinates":[79.67104,59.38823000000001],"type":"Point"}
}