{
  "type": "Feature",
  "properties": {
    "gn:admin1_code":"73",
    "gn:asciiname":"Baytuganovo",
    "gn:country_code":"RU",
    "gn:dem":139,
    "gn:feature_class":"P",
    "gn:feature_code":"PPL",
    "gn:name":"Baytuganovo",
    "gn:population":0,
    "gn:timezone":"Europe/Moscow",
    "iso:country":"RU",
    "name:rus_x_preferred":[
        "\u0411\u0430\u0439\u0442\u0443\u0433\u0430\u043d\u043e\u0432\u043e"
    ],
    "name:und_x_variant":[
        "\u0411\u0430\u0439\u0442\u0443\u0433\u0430\u043d\u043e\u0432\u043e"
    ],
    "wof:name":"Baytuganovo",
    "wof:placetype":"locality"
},
  "geometry": {"coordinates":[53.3012,55.9636],"type":"Point"}
}