{
  "type": "Feature",
  "properties": {
    "gn:admin1_code":"55",
    "gn:asciiname":"Tarkhany",
    "gn:country_code":"RU",
    "gn:dem":135,
    "gn:feature_class":"P",
    "gn:feature_code":"PPL",
    "gn:name":"Tarkhany",
    "gn:population":0,
    "gn:timezone":"Asia/Yekaterinburg",
    "iso:country":"RU",
    "name:rus_x_preferred":[
        "\u0422\u0430\u0440\u0445\u0430\u043d\u044b"
    ],
    "name:und_x_variant":[
        "Tarkhan",
        "\u0422\u0430\u0440\u0445\u0430\u043d\u044b"
    ],
    "wof:name":"Tarkhany",
    "wof:placetype":"locality"
},
  "geometry": {"coordinates":[53.13333000000001,53.43333000000001],"type":"Point"}
}