{
  "type": "Feature",
  "properties": {
    "gn:admin1_code":"63",
    "gn:asciiname":"Balagannaakh",
    "gn:country_code":"RU",
    "gn:dem":62,
    "gn:feature_class":"P",
    "gn:feature_code":"PPL",
    "gn:name":"Balagannaakh",
    "gn:population":0,
    "gn:timezone":"Asia/Yakutsk",
    "iso:country":"RU",
    "name:nor_x_preferred":[
        "Balagannaakh"
    ],
    "name:rus_x_preferred":[
        "\u0411\u0430\u043b\u0430\u0433\u0430\u043d\u043d\u0430\u0430\u0445"
    ],
    "name:und_x_variant":[
        "Balagannakh"
    ],
    "wof:name":"Balagannaakh",
    "wof:placetype":"locality"
},
  "geometry": {"coordinates":[126.59999999999999,63.73333],"type":"Point"}
}