{
  "type": "Feature",
  "properties": {
    "gn:admin1_code":"47",
    "gn:asciiname":"Vysokiye Dvoriki",
    "gn:country_code":"RU",
    "gn:dem":205,
    "gn:feature_class":"P",
    "gn:feature_code":"PPL",
    "gn:name":"Vysokiye Dvoriki",
    "gn:population":0,
    "gn:timezone":"Europe/Moscow",
    "iso:country":"RU",
    "wof:name":"Vysokiye Dvoriki",
    "wof:placetype":"locality"
},
  "geometry": {"coordinates":[37.42492,54.84928000000001],"type":"Point"}
}