{
  "type": "Feature",
  "properties": {
    "gn:admin1_code":"81",
    "gn:asciiname":"Vyselki Popovoy Mel'nitsy",
    "gn:country_code":"RU",
    "gn:dem":158,
    "gn:feature_class":"P",
    "gn:feature_code":"PPL",
    "gn:name":"Vyselki Popovoy Mel\u2019nitsy",
    "gn:population":0,
    "gn:timezone":"Europe/Ulyanovsk",
    "iso:country":"RU",
    "name:rus_x_preferred":[
        "\u0412\u044b\u0441\u0435\u043b\u043a\u0438 \u041f\u043e\u043f\u043e\u0432\u043e\u0439 \u041c\u0435\u043b\u044c\u043d\u0438\u0446\u044b"
    ],
    "name:und_x_variant":[
        "Vyselki Popovoy Mel\u2019nitsy",
        "\u0412\u044b\u0441\u0435\u043b\u043a\u0438 \u041f\u043e\u043f\u043e\u0432\u043e\u0439 \u041c\u0435\u043b\u044c\u043d\u0438\u0446\u044b"
    ],
    "wof:name":"Vyselki Popovoy Mel'nitsy",
    "wof:placetype":"locality"
},
  "geometry": {"coordinates":[47.1063,53.7408],"type":"Point"}
}