{
  "type": "Feature",
  "properties": {
    "gn:admin1_code":"67",
    "gn:asciiname":"Poselok Pervyy",
    "gn:cc2":"RU",
    "gn:country_code":"RU",
    "gn:dem":52,
    "gn:feature_class":"P",
    "gn:feature_code":"PPL",
    "gn:name":"Pos\u00eblok Pervyy",
    "gn:population":0,
    "gn:timezone":"Europe/Saratov",
    "iso:country":"RU",
    "name:rus_x_preferred":[
        "\u041f\u043e\u0441\u0451\u043b\u043e\u043a \u041f\u0435\u0440\u0432\u044b\u0439"
    ],
    "name:und_x_variant":[
        "Pervyy",
        "Pos\u00eblok Pervyy"
    ],
    "wof:name":"Poselok Pervyy",
    "wof:placetype":"locality"
},
  "geometry": {"coordinates":[47.71667,52.23333],"type":"Point"}
}