{
  "type": "Feature",
  "properties": {
    "gn:admin1_code":"88",
    "gn:asciiname":"Vyatskoye",
    "gn:country_code":"RU",
    "gn:dem":99,
    "gn:feature_class":"P",
    "gn:feature_code":"PPL",
    "gn:name":"Vyatskoye",
    "gn:population":0,
    "gn:timezone":"Europe/Moscow",
    "iso:country":"RU",
    "name:eng_x_preferred":[
        "Vyatskoye"
    ],
    "name:nor_x_preferred":[
        "Vjatskoje"
    ],
    "name:rus_x_preferred":[
        "\u0412\u044f\u0442\u0441\u043a\u043e\u0435"
    ],
    "wof:name":"Vyatskoye",
    "wof:placetype":"locality"
},
  "geometry": {"coordinates":[40.26465,57.86656],"type":"Point"}
}