{
  "type": "Feature",
  "properties": {
    "gn:admin1_code":"91",
    "gn:asciiname":"Poloy",
    "gn:cc2":"RU",
    "gn:country_code":"RU",
    "gn:dem":14,
    "gn:feature_class":"P",
    "gn:feature_code":"PPL",
    "gn:name":"Poloy",
    "gn:population":0,
    "gn:timezone":"Asia/Krasnoyarsk",
    "iso:country":"RU",
    "name:eng_x_preferred":[
        "Poloy"
    ],
    "name:nor_x_preferred":[
        "Poloj"
    ],
    "name:rus_x_preferred":[
        "\u041f\u043e\u043b\u043e\u0439"
    ],
    "name:und_x_variant":[
        "Poloi"
    ],
    "wof:name":"Poloy",
    "wof:placetype":"locality"
},
  "geometry": {"coordinates":[86.56667,66.73333000000001],"type":"Point"}
}