{
  "type": "Feature",
  "properties": {
    "gn:admin1_code":"85",
    "gn:asciiname":"Perkhino",
    "gn:country_code":"RU",
    "gn:dem":134,
    "gn:feature_class":"P",
    "gn:feature_code":"PPL",
    "gn:name":"Perkhino",
    "gn:population":0,
    "gn:timezone":"Europe/Moscow",
    "iso:country":"RU",
    "name:rus_x_preferred":[
        "\u041f\u0435\u0440\u0445\u0438\u043d\u043e"
    ],
    "name:und_x_variant":[
        "\u041f\u0435\u0440\u0445\u0438\u043d\u043e"
    ],
    "wof:name":"Perkhino",
    "wof:placetype":"locality"
},
  "geometry": {"coordinates":[38.5291,59.8627],"type":"Point"}
}