{
  "type": "Feature",
  "properties": {
    "gn:admin1_code":"7",
    "gn:asciiname":"Nizhnyaya Sultanovka",
    "gn:country_code":"RU",
    "gn:dem":-25,
    "gn:feature_class":"P",
    "gn:feature_code":"PPL",
    "gn:name":"Nizhnyaya Sultanovka",
    "gn:population":0,
    "gn:timezone":"Europe/Astrakhan",
    "iso:country":"RU",
    "name:rus_x_preferred":[
        "\u041d\u0438\u0436\u043d\u044f\u044f \u0421\u0443\u043b\u0442\u0430\u043d\u043e\u0432\u043a\u0430"
    ],
    "name:und_x_variant":[
        "Nizhnaya Sultanovka",
        "Nizhnyaya Sultanovka"
    ],
    "wof:name":"Nizhnyaya Sultanovka",
    "wof:placetype":"locality"
},
  "geometry": {"coordinates":[48.46228,46.28100000000001],"type":"Point"}
}