{
  "type": "Feature",
  "properties": {
    "gn:admin1_code":"71",
    "gn:asciiname":"Neymyshevo",
    "gn:country_code":"RU",
    "gn:dem":66,
    "gn:feature_class":"P",
    "gn:feature_code":"PPL",
    "gn:name":"Neymyshevo",
    "gn:population":0,
    "gn:timezone":"Asia/Yekaterinburg",
    "iso:country":"RU",
    "name:eng_x_preferred":[
        "Neymyshevo"
    ],
    "name:nor_x_preferred":[
        "Nejmysjevo"
    ],
    "name:rus_x_preferred":[
        "\u041d\u0435\u0439\u043c\u044b\u0448\u0435\u0432\u043e"
    ],
    "name:und_x_variant":[
        "Neymysheva",
        "Neymyshevo"
    ],
    "wof:name":"Neymyshevo",
    "wof:placetype":"locality"
},
  "geometry": {"coordinates":[63.08342,58.12937],"type":"Point"}
}