{
  "type": "Feature",
  "properties": {
    "gn:admin1_code":"83",
    "gn:asciiname":"Savinskaya",
    "gn:country_code":"RU",
    "gn:dem":127,
    "gn:feature_class":"P",
    "gn:feature_code":"PPL",
    "gn:name":"Savinskaya",
    "gn:population":0,
    "gn:timezone":"Europe/Moscow",
    "iso:country":"RU",
    "name:rus_x_preferred":[
        "\u0421\u0430\u0432\u0438\u043d\u0441\u043a\u0430\u044f"
    ],
    "wof:name":"Savinskaya",
    "wof:placetype":"locality"
},
  "geometry": {"coordinates":[40.38944,55.66436],"type":"Point"}
}