{
  "type": "Feature",
  "properties": {
    "gn:admin1_code":"85",
    "gn:asciiname":"Baskakovo",
    "gn:country_code":"RU",
    "gn:dem":129,
    "gn:feature_class":"P",
    "gn:feature_code":"PPL",
    "gn:name":"Baskakovo",
    "gn:population":0,
    "gn:timezone":"Europe/Moscow",
    "iso:country":"RU",
    "name:rus_x_preferred":[
        "\u0411\u0430\u0441\u043a\u0430\u043a\u043e\u0432\u043e"
    ],
    "wof:name":"Baskakovo",
    "wof:placetype":"locality"
},
  "geometry": {"coordinates":[38.03477,59.08605],"type":"Point"}
}