{
  "type": "Feature",
  "properties": {
    "gn:admin1_code":"16",
    "gn:asciiname":"Sirmaposi",
    "gn:country_code":"RU",
    "gn:dem":152,
    "gn:feature_class":"P",
    "gn:feature_code":"PPL",
    "gn:name":"Sirmaposi",
    "gn:population":0,
    "gn:timezone":"Europe/Moscow",
    "iso:country":"RU",
    "name:rus_x_preferred":[
        "\u0421\u0438\u0440\u043c\u0430\u043f\u043e\u0441\u0438"
    ],
    "name:und_x_variant":[
        "\u0421\u0438\u0440\u043c\u0430\u043f\u043e\u0441\u0438"
    ],
    "wof:name":"Sirmaposi",
    "wof:placetype":"locality"
},
  "geometry": {"coordinates":[47.30324,56.01152],"type":"Point"}
}