{
  "type": "Feature",
  "properties": {
    "gn:admin1_code":"13",
    "gn:asciiname":"Ibragimova",
    "gn:country_code":"RU",
    "gn:dem":198,
    "gn:feature_class":"P",
    "gn:feature_code":"PPL",
    "gn:name":"Ibragimova",
    "gn:population":0,
    "gn:timezone":"Asia/Yekaterinburg",
    "iso:country":"RU",
    "name:rus_x_preferred":[
        "\u0418\u0431\u0440\u0430\u0433\u0438\u043c\u043e\u0432\u0430"
    ],
    "name:und_x_variant":[
        "\u0418\u0431\u0440\u0430\u0433\u0438\u043c\u043e\u0432\u0430"
    ],
    "wof:name":"Ibragimova",
    "wof:placetype":"locality"
},
  "geometry": {"coordinates":[61.45,55.58333],"type":"Point"}
}