{
  "type": "Feature",
  "properties": {
    "gn:admin1_code":"10",
    "gn:asciiname":"Gribovy Dvory",
    "gn:country_code":"RU",
    "gn:dem":211,
    "gn:feature_class":"P",
    "gn:feature_code":"PPL",
    "gn:name":"Gribovy Dvory",
    "gn:population":0,
    "gn:timezone":"Europe/Moscow",
    "iso:country":"RU",
    "name:rus_x_preferred":[
        "\u0413\u0440\u0438\u0431\u043e\u0432\u044b \u0414\u0432\u043e\u0440\u044b"
    ],
    "name:und_x_variant":[
        "\u0413\u0440\u0438\u0431\u043e\u0432\u044b \u0414\u0432\u043e\u0440\u044b"
    ],
    "wof:name":"Gribovy Dvory",
    "wof:placetype":"locality"
},
  "geometry": {"coordinates":[35.0647,53.11763000000001],"type":"Point"}
}