{
  "type": "Feature",
  "properties": {
    "gn:admin1_code":"42.0",
    "gn:admin2_code":"472350",
    "gn:asciiname":"Beseda",
    "gn:country_code":"RU",
    "gn:dem":94,
    "gn:feature_class":"P",
    "gn:feature_code":"PPL",
    "gn:name":"Beseda",
    "gn:population":0,
    "gn:timezone":"Europe/Moscow",
    "iso:country":"RU",
    "name:nor_x_preferred":[
        "Beseda"
    ],
    "name:rus_x_preferred":[
        "\u0411\u0435\u0441\u0435\u0434\u0430"
    ],
    "wof:name":"Beseda",
    "wof:placetype":"locality"
},
  "geometry": {"coordinates":[28.97002,59.35193],"type":"Point"}
}