{
  "type": "Feature",
  "properties": {
    "gn:admin1_code":"65",
    "gn:asciiname":"Svetlyy Klyuch",
    "gn:country_code":"RU",
    "gn:dem":124,
    "gn:feature_class":"P",
    "gn:feature_code":"PPL",
    "gn:name":"Svetlyy Klyuch",
    "gn:population":0,
    "gn:timezone":"Europe/Samara",
    "iso:country":"RU",
    "name:und_x_variant":[
        "Svetly Klyuch",
        "Svetlyy Klyuch"
    ],
    "wof:name":"Svetlyy Klyuch",
    "wof:placetype":"locality"
},
  "geometry": {"coordinates":[51.78333,54.46666999999999],"type":"Point"}
}