{
  "type": "Feature",
  "properties": {
    "gn:admin1_code":"90",
    "gn:asciiname":"Solman",
    "gn:country_code":"RU",
    "gn:dem":146,
    "gn:feature_class":"P",
    "gn:feature_code":"PPL",
    "gn:name":"Solman",
    "gn:population":0,
    "gn:timezone":"Asia/Yekaterinburg",
    "iso:country":"RU",
    "name:eng_x_preferred":[
        "Solman"
    ],
    "name:nor_x_preferred":[
        "Solman"
    ],
    "name:rus_x_preferred":[
        "\u0421\u043e\u043b\u043c\u0430\u043d"
    ],
    "wof:name":"Solman",
    "wof:placetype":"locality"
},
  "geometry": {"coordinates":[56.01667,60.08333],"type":"Point"}
}