{
  "type": "Feature",
  "properties": {
    "gn:admin1_code":"9.0",
    "gn:asciiname":"Fakovka",
    "gn:country_code":"RU",
    "gn:dem":115,
    "gn:feature_class":"P",
    "gn:feature_code":"PPL",
    "gn:name":"Fakovka",
    "gn:population":0,
    "gn:timezone":"Europe/Moscow",
    "iso:country":"RU",
    "name:rus_x_preferred":[
        "\u0424\u0430\u043a\u043e\u0432\u043a\u0430"
    ],
    "name:und_x_variant":[
        "\u0424\u0430\u043a\u043e\u0432\u043a\u0430"
    ],
    "wof:name":"Fakovka",
    "wof:placetype":"locality"
},
  "geometry": {"coordinates":[37.0281,50.5874],"type":"Point"}
}