{
  "type": "Feature",
  "properties": {
    "gn:country":"RU",
    "gn:fcode":"PPL",
    "gn:pop":0,
    "iso:country":"RU",
    "name:nor_x_preferred":[
        "Arkhangelskoje"
    ],
    "name:rus_x_preferred":[
        "\u0410\u0440\u0445\u0430\u043d\u0433\u0435\u043b\u044c\u0441\u043a\u043e\u0435"
    ],
    "name:unk_x_variant":[
        "Arkhangel\u2019sk"
    ],
    "qs:name":"Arkhangel'skoe",
    "qs:name_adm0":"Russia",
    "qs:name_adm1":"Moscow Oblast",
    "qs:photos_9k":1,
    "qs:photos_9r":1,
    "qs:photos_all":6,
    "qs:photos_sr":0,
    "qs:placetype":"Town",
    "qs:pop_sr":"0",
    "wof:name":"Arkhangel'skoe",
    "wof:placetype":"locality",
    "wof:population":0
},
  "geometry": {"coordinates":[35.9625,55.32194],"type":"Point"}
}