{
  "type": "Feature",
  "properties": {
    "gn:admin1_code":"8",
    "gn:asciiname":"Malokachakovo",
    "gn:cc2":"RU",
    "gn:country_code":"RU",
    "gn:dem":83,
    "gn:feature_class":"P",
    "gn:feature_code":"PPL",
    "gn:name":"Malokachakovo",
    "gn:population":0,
    "gn:timezone":"Asia/Yekaterinburg",
    "iso:country":"RU",
    "name:rus_x_preferred":[
        "\u041c\u0430\u043b\u043e\u043a\u0430\u0447\u0430\u043a\u043e\u0432\u043e"
    ],
    "name:und_x_variant":[
        "Malyy Kachak",
        "Malokachakovo",
        "\u041c\u0430\u043b\u043e\u043a\u0430\u0447\u0430\u043a\u043e\u0432\u043e"
    ],
    "wof:name":"Malokachakovo",
    "wof:placetype":"locality"
},
  "geometry": {"coordinates":[55.16778000000001,55.89611],"type":"Point"}
}