{
  "type": "Feature",
  "properties": {
    "gn:admin1_code":"42",
    "gn:asciiname":"Novoye Ust'ye",
    "gn:country_code":"RU",
    "gn:dem":14,
    "gn:feature_class":"P",
    "gn:feature_code":"PPL",
    "gn:name":"Novoye Ust\u2019ye",
    "gn:population":0,
    "gn:timezone":"Europe/Moscow",
    "iso:country":"RU",
    "name:rus_x_preferred":[
        "\u041d\u043e\u0432\u043e\u0435 \u0423\u0441\u0442\u044c\u0435"
    ],
    "name:und_x_variant":[
        "Novoye Ust\u2019ye",
        "\u041d\u043e\u0432\u043e\u0435 \u0423\u0441\u0442\u044c\u0435"
    ],
    "wof:name":"Novoye Ust'ye",
    "wof:placetype":"locality"
},
  "geometry": {"coordinates":[28.8266,59.76596],"type":"Point"}
}