{
  "type": "Feature",
  "properties": {
    "gn:country":"RU",
    "gn:fcode":"PPL",
    "gn:population":0,
    "iso:country":"RU",
    "name:bel_x_preferred":[
        "\u0412\u043e\u043b\u043a\u0430\u0432\u0430"
    ],
    "name:est_x_preferred":[
        "Volkovo"
    ],
    "name:hye_x_preferred":[
        "\u054e\u0578\u056c\u056f\u0578\u057e\u0578"
    ],
    "name:rus_x_preferred":[
        "\u0412\u043e\u043b\u043a\u043e\u0432\u043e"
    ],
    "name:tat_x_preferred":[
        "\u0412\u043e\u043b\u043a\u043e\u0432\u043e"
    ],
    "name:ukr_x_preferred":[
        "\u0412\u043e\u043b\u043a\u043e\u0432\u043e"
    ],
    "qs:name":"Volkovo",
    "qs:name_adm0":"Russia",
    "qs:name_adm1":"Moscow Oblast",
    "qs:photos":226,
    "qs:photos_1k":46,
    "qs:photos_9k":1,
    "qs:photos_9r":4,
    "qs:photos_all":226,
    "qs:photos_sr":4,
    "qs:placetype":"Town",
    "qs:pop_sr":"0",
    "wd:wordcount":40,
    "wof:name":"Volkovo",
    "wof:placetype":"locality",
    "wof:population":0
},
  "geometry": {"coordinates":[37.68972,55.91583],"type":"Point"}
}