{
  "type": "Feature",
  "properties": {
    "gn:country":"RU",
    "gn:fcode":"PPL",
    "gn:pop":0,
    "iso:country":"RU",
    "qs:name":"Volkovo",
    "qs:name_adm0":"Russia",
    "qs:name_adm1":"Moscow Oblast",
    "qs:photos":226,
    "qs:photos_1k":46,
    "qs:photos_9k":1,
    "qs:photos_9r":4,
    "qs:photos_all":226,
    "qs:photos_sr":4,
    "qs:placetype":"Town",
    "qs:pop_sr":"0",
    "wd:wordcount":40,
    "wof:name":"Volkovo",
    "wof:placetype":"locality",
    "wof:population":0
},
  "geometry": {"coordinates":[37.68972,55.91583],"type":"Point"}
}