{
  "type": "Feature",
  "properties": {
    "gn:admin1_code":"70",
    "gn:asciiname":"Kamennobrodskiy",
    "gn:cc2":"RU",
    "gn:country_code":"RU",
    "gn:dem":199,
    "gn:feature_class":"P",
    "gn:feature_code":"PPL",
    "gn:name":"Kamennobrodskiy",
    "gn:population":0,
    "gn:timezone":"Europe/Moscow",
    "iso:country":"RU",
    "name:und_x_variant":[
        "Sovkhoz Kamennobrodskiy"
    ],
    "wof:name":"Kamennobrodskiy",
    "wof:placetype":"locality"
},
  "geometry": {"coordinates":[41.36389000000001,45.35361],"type":"Point"}
}