{
  "type": "Feature",
  "properties": {
    "gn:admin1_code":"69",
    "gn:asciiname":"Sadki",
    "gn:country_code":"RU",
    "gn:dem":222,
    "gn:feature_class":"P",
    "gn:feature_code":"PPL",
    "gn:name":"Sadki",
    "gn:population":0,
    "gn:timezone":"Europe/Moscow",
    "iso:country":"RU",
    "name:ceb_x_preferred":[
        "Sadki"
    ],
    "name:nld_x_preferred":[
        "Sadki"
    ],
    "name:pol_x_preferred":[
        "Sadki"
    ],
    "name:rus_x_preferred":[
        "\u0421\u0430\u0434\u043a\u0438"
    ],
    "name:ukr_x_preferred":[
        "\u0421\u0430\u0434\u043a\u0456"
    ],
    "name:und_x_variant":[
        "\u0421\u0430\u0434\u043a\u0438"
    ],
    "wof:name":"Sadki",
    "wof:placetype":"locality"
},
  "geometry": {"coordinates":[33.04806,54.63549],"type":"Point"}
}