{
  "type": "Feature",
  "properties": {
    "gn:admin1_code":"90",
    "gn:asciiname":"Vysokaya Gora",
    "gn:country_code":"RU",
    "gn:dem":228,
    "gn:feature_class":"P",
    "gn:feature_code":"PPL",
    "gn:name":"Vysokaya Gora",
    "gn:population":0,
    "gn:timezone":"Asia/Yekaterinburg",
    "iso:country":"RU",
    "wof:name":"Vysokaya Gora",
    "wof:placetype":"locality"
},
  "geometry": {"coordinates":[53.98026,59.13877],"type":"Point"}
}