{
  "type": "Feature",
  "properties": {
    "gn:admin1_code":"81",
    "gn:asciiname":"Vyry",
    "gn:country_code":"RU",
    "gn:dem":177,
    "gn:feature_class":"P",
    "gn:feature_code":"PPL",
    "gn:name":"Vyry",
    "gn:population":0,
    "gn:timezone":"Europe/Ulyanovsk",
    "iso:country":"RU",
    "name:eng_x_preferred":[
        "Vyry"
    ],
    "name:nor_x_preferred":[
        "Vyry"
    ],
    "name:rus_x_preferred":[
        "\u0412\u044b\u0440\u044b"
    ],
    "wof:name":"Vyry",
    "wof:placetype":"locality"
},
  "geometry": {"coordinates":[47.7993,54.1937],"type":"Point"}
}