{
  "type": "Feature",
  "properties": {
    "gn:admin1_code":"10",
    "gn:asciiname":"Kovalevka",
    "gn:country_code":"RU",
    "gn:dem":168,
    "gn:feature_class":"P",
    "gn:feature_code":"PPL",
    "gn:name":"Kovalevka",
    "gn:population":0,
    "gn:timezone":"Europe/Moscow",
    "iso:country":"RU",
    "name:rus_x_preferred":[
        "\u041a\u043e\u0432\u0430\u043b\u0435\u0432\u043a\u0430"
    ],
    "name:und_x_variant":[
        "\u041a\u043e\u0432\u0430\u043b\u0435\u0432\u043a\u0430"
    ],
    "wof:name":"Kovalevka",
    "wof:placetype":"locality"
},
  "geometry": {"coordinates":[33.03972,52.63028000000001],"type":"Point"}
}