{
  "type": "Feature",
  "properties": {
    "gn:admin1_code":"72",
    "gn:asciiname":"Novoye Tarbeyevo",
    "gn:country_code":"RU",
    "gn:dem":120,
    "gn:feature_class":"P",
    "gn:feature_code":"PPL",
    "gn:name":"Novoye Tarbeyevo",
    "gn:population":0,
    "gn:timezone":"Europe/Moscow",
    "iso:country":"RU",
    "name:eng_x_preferred":[
        "Novotarbeyevo"
    ],
    "name:nor_x_preferred":[
        "Nov. Tarbejevo"
    ],
    "name:rus_x_preferred":[
        "\u041d\u043e\u0432. \u0422\u0430\u0440\u0431\u0435\u0435\u0432\u043e"
    ],
    "name:rus_x_variant":[
        "\u041d\u043e\u0432\u043e\u0435 \u0422\u0430\u0440\u0431\u0435\u0435\u0432\u043e"
    ],
    "name:und_x_variant":[
        "Novotarbeyevo"
    ],
    "wof:name":"Novoye Tarbeyevo",
    "wof:placetype":"locality"
},
  "geometry": {"coordinates":[40.2602,52.8392],"type":"Point"}
}