{
  "type": "Feature",
  "properties": {
    "gn:admin1_code":"8",
    "gn:asciiname":"Novotroyevka",
    "gn:country_code":"RU",
    "gn:dem":118,
    "gn:feature_class":"P",
    "gn:feature_code":"PPL",
    "gn:name":"Novotroyevka",
    "gn:population":0,
    "gn:timezone":"Asia/Yekaterinburg",
    "iso:country":"RU",
    "name:bak_x_preferred":[
        "\u042f\u04a3\u044b \u0422\u0440\u043e\u0435\u0432\u043a\u0430"
    ],
    "name:che_x_preferred":[
        "\u041d\u043e\u0432\u043e\u0442\u0440\u043e\u0435\u0432\u043a\u0430"
    ],
    "name:hye_x_preferred":[
        "\u0546\u0578\u057e\u0578\u057f\u0580\u0578\u0587\u056f\u0561"
    ],
    "name:kaz_x_preferred":[
        "\u0416\u0430\u04a3\u0430 \u0442\u0440\u043e\u0435\u0432\u043a\u0430"
    ],
    "name:kir_x_preferred":[
        "\u0416\u0430\u04a3\u044b \u0442\u0440\u043e\u0435\u0432\u043a\u0430"
    ],
    "name:rus_x_preferred":[
        "\u041d\u043e\u0432\u043e\u0442\u0440\u043e\u0435\u0432\u043a\u0430"
    ],
    "name:tat_x_preferred":[
        "\u041d\u043e\u0432\u043e\u0442\u0440\u043e\u0435\u0432\u043a\u0430"
    ],
    "name:ukr_x_preferred":[
        "\u041d\u043e\u0432\u043e\u0442\u0440\u043e\u0454\u0432\u043a\u0430"
    ],
    "name:und_x_variant":[
        "Novostroyevka",
        "Novotroyevka",
        "\u041d\u043e\u0432\u043e\u0442\u0440\u043e\u0435\u0432\u043a\u0430"
    ],
    "wof:name":"Novotroyevka",
    "wof:placetype":"locality"
},
  "geometry": {"coordinates":[56.16387,53.77374],"type":"Point"}
}