{
  "type": "Feature",
  "properties": {
    "gn:admin1_code":"8",
    "gn:asciiname":"Novotroyevka",
    "gn:country_code":"RU",
    "gn:dem":118,
    "gn:feature_class":"P",
    "gn:feature_code":"PPL",
    "gn:name":"Novotroyevka",
    "gn:population":0,
    "gn:timezone":"Asia/Yekaterinburg",
    "iso:country":"RU",
    "name:rus_x_preferred":[
        "\u041d\u043e\u0432\u043e\u0442\u0440\u043e\u0435\u0432\u043a\u0430"
    ],
    "name:und_x_variant":[
        "Novostroyevka",
        "Novotroyevka",
        "\u041d\u043e\u0432\u043e\u0442\u0440\u043e\u0435\u0432\u043a\u0430"
    ],
    "wof:name":"Novotroyevka",
    "wof:placetype":"locality"
},
  "geometry": {"coordinates":[56.16387,53.77374],"type":"Point"}
}