{
  "type": "Feature",
  "properties": {
    "gn:admin1_code":"33",
    "gn:asciiname":"Ushakovo",
    "gn:country_code":"RU",
    "gn:dem":113,
    "gn:feature_class":"P",
    "gn:feature_code":"PPL",
    "gn:name":"Ushakovo",
    "gn:population":0,
    "gn:timezone":"Europe/Kirov",
    "iso:country":"RU",
    "name:rus_x_preferred":[
        "\u0423\u0448\u0430\u043a\u043e\u0432\u043e"
    ],
    "wof:name":"Ushakovo",
    "wof:placetype":"locality"
},
  "geometry": {"coordinates":[47.1007,57.3637],"type":"Point"}
}