{
  "type": "Feature",
  "properties": {
    "gn:admin1_code":"90",
    "gn:asciiname":"Timino",
    "gn:country_code":"RU",
    "gn:dem":181,
    "gn:feature_class":"P",
    "gn:feature_code":"PPL",
    "gn:name":"Timino",
    "gn:population":0,
    "gn:timezone":"Asia/Yekaterinburg",
    "iso:country":"RU",
    "name:che_x_preferred":[
        "\u0422\u0438\u043c\u0438\u043d\u043e"
    ],
    "name:eng_x_preferred":[
        "Timino"
    ],
    "name:koi_x_preferred":[
        "\u041a\u0438\u043c\u0438\u043d\u0447\u0438"
    ],
    "name:nor_x_preferred":[
        "Timino"
    ],
    "name:rus_x_preferred":[
        "\u0422\u0438\u043c\u0438\u043d\u043e"
    ],
    "wof:name":"Timino",
    "wof:placetype":"locality"
},
  "geometry": {"coordinates":[55.4275,59.0931],"type":"Point"}
}