{
  "type": "Feature",
  "properties": {
    "gn:admin1_code":"61",
    "gn:asciiname":"Yerofeyevo-Kalitvenskaya",
    "gn:country_code":"RU",
    "gn:dem":69,
    "gn:feature_class":"P",
    "gn:feature_code":"PPL",
    "gn:name":"Yerofeyevo-Kalitvenskaya",
    "gn:population":0,
    "gn:timezone":"Europe/Moscow",
    "iso:country":"RU",
    "wof:name":"Yerofeyevo-Kalitvenskaya",
    "wof:placetype":"locality"
},
  "geometry": {"coordinates":[40.58333,48.56667],"type":"Point"}
}