{
  "type": "Feature",
  "properties": {
    "gn:admin1_code":"10",
    "gn:asciiname":"Krutoye",
    "gn:country_code":"RU",
    "gn:dem":195,
    "gn:feature_class":"P",
    "gn:feature_code":"PPL",
    "gn:name":"Krutoye",
    "gn:population":0,
    "gn:timezone":"Europe/Moscow",
    "iso:country":"RU",
    "name:che_x_preferred":[
        "\u041a\u0440\u0443\u0442\u043e\u0439"
    ],
    "name:rus_x_preferred":[
        "\u041a\u0440\u0443\u0442\u043e\u0435"
    ],
    "name:tgk_x_preferred":[
        "\u041a\u0440\u0443\u0442\u043e\u0435"
    ],
    "wof:name":"Krutoye",
    "wof:placetype":"locality"
},
  "geometry": {"coordinates":[34.73958,52.96139],"type":"Point"}
}