{
  "type": "Feature",
  "properties": {
    "gn:admin1_code":"77",
    "gn:asciiname":"Zaluzh'ye",
    "gn:country_code":"RU",
    "gn:dem":184,
    "gn:feature_class":"P",
    "gn:feature_code":"PPL",
    "gn:name":"Zaluzh\u2019ye",
    "gn:population":0,
    "gn:timezone":"Europe/Moscow",
    "iso:country":"RU",
    "name:rus_x_preferred":[
        "\u0417\u0430\u043b\u0443\u0436\u044c\u0435"
    ],
    "name:und_x_variant":[
        "Zaluzh\u2019ye"
    ],
    "wof:name":"Zaluzh'ye",
    "wof:placetype":"locality"
},
  "geometry": {"coordinates":[32.02475,56.18591],"type":"Point"}
}