{
  "type": "Feature",
  "properties": {
    "gn:admin1_code":"88",
    "gn:asciiname":"Utkino",
    "gn:country_code":"RU",
    "gn:dem":140,
    "gn:feature_class":"P",
    "gn:feature_code":"PPL",
    "gn:name":"Utkino",
    "gn:population":0,
    "gn:timezone":"Europe/Moscow",
    "iso:country":"RU",
    "name:rus_x_preferred":[
        "\u0423\u0442\u043a\u0438\u043d\u043e"
    ],
    "wof:name":"Utkino",
    "wof:placetype":"locality"
},
  "geometry": {"coordinates":[39.05108,57.73252],"type":"Point"}
}