{
  "type": "Feature",
  "properties": {
    "gn:admin1_code":"11",
    "gn:asciiname":"Kedrovaya",
    "gn:country_code":"RU",
    "gn:dem":464,
    "gn:feature_class":"P",
    "gn:feature_code":"PPL",
    "gn:name":"Kedrovaya",
    "gn:population":0,
    "gn:timezone":"Asia/Irkutsk",
    "iso:country":"RU",
    "name:rus_x_preferred":[
        "\u041a\u0435\u0434\u0440\u043e\u0432\u0430\u044f"
    ],
    "name:und_x_variant":[
        "\u041a\u0435\u0434\u0440\u043e\u0432\u0430\u044f"
    ],
    "wof:name":"Kedrovaya",
    "wof:placetype":"locality"
},
  "geometry": {"coordinates":[104.9323,51.5132],"type":"Point"}
}