{
  "type": "Feature",
  "properties": {
    "gn:admin1_code":"13",
    "gn:asciiname":"Nagaybakskiy",
    "gn:country_code":"RU",
    "gn:dem":414,
    "gn:feature_class":"P",
    "gn:feature_code":"PPL",
    "gn:name":"Nagaybakskiy",
    "gn:population":0,
    "gn:timezone":"Asia/Yekaterinburg",
    "iso:country":"RU",
    "name:eng_x_preferred":[
        "Nagaybakskiy"
    ],
    "name:nor_x_preferred":[
        "Nagajbakskij"
    ],
    "name:rus_x_preferred":[
        "\u041d\u0430\u0433\u0430\u0439\u0431\u0430\u043a\u0441\u043a\u0438\u0439"
    ],
    "name:und_x_variant":[
        "\u041d\u0430\u0433\u0430\u0439\u0431\u0430\u043a\u0441\u043a\u0438\u0439",
        "Nagaybakskiy"
    ],
    "wof:name":"Nagaybakskiy",
    "wof:placetype":"locality"
},
  "geometry": {"coordinates":[59.53361,53.545],"type":"Point"}
}