{
  "type": "Feature",
  "properties": {
    "gn:admin1_code":"25",
    "gn:asciiname":"Rassudovo",
    "gn:country_code":"RU",
    "gn:dem":197,
    "gn:feature_class":"P",
    "gn:feature_code":"PPL",
    "gn:name":"Rassudovo",
    "gn:population":0,
    "gn:timezone":"Europe/Moscow",
    "iso:country":"RU",
    "name:rus_x_preferred":[
        "\u0420\u0430\u0441\u0441\u0443\u0434\u043e\u0432\u043e"
    ],
    "name:und_x_variant":[
        "\u0420\u0430\u0441\u0441\u0443\u0434\u043e\u0432\u043e"
    ],
    "wof:name":"Rassudovo",
    "wof:placetype":"locality"
},
  "geometry": {"coordinates":[35.87624,54.41891],"type":"Point"}
}