{
  "type": "Feature",
  "properties": {
    "gn:admin1_code":"4",
    "gn:asciiname":"Poperechnaya",
    "gn:country_code":"RU",
    "gn:dem":339,
    "gn:feature_class":"P",
    "gn:feature_code":"PPL",
    "gn:name":"Poperechnaya",
    "gn:population":0,
    "gn:timezone":"Asia/Barnaul",
    "iso:country":"RU",
    "name:rus_x_preferred":[
        "\u041f\u043e\u043f\u0435\u0440\u0435\u0447\u043d\u0430\u044f"
    ],
    "wof:name":"Poperechnaya",
    "wof:placetype":"locality"
},
  "geometry": {"coordinates":[85.5367,53.8806],"type":"Point"}
}