{
  "type": "Feature",
  "properties": {
    "gn:admin1_code":"65",
    "gn:asciiname":"Ryzhevoy",
    "gn:country_code":"RU",
    "gn:dem":205,
    "gn:feature_class":"P",
    "gn:feature_code":"PPL",
    "gn:name":"Ryzhevoy",
    "gn:population":0,
    "gn:timezone":"Europe/Samara",
    "iso:country":"RU",
    "name:rus_x_preferred":[
        "\u0420\u044b\u0436\u0435\u0432\u043e\u0439"
    ],
    "name:und_x_variant":[
        "\u0420\u044b\u0436\u0435\u0432\u043e\u0439"
    ],
    "wof:name":"Ryzhevoy",
    "wof:placetype":"locality"
},
  "geometry": {"coordinates":[51.3176,54.3646],"type":"Point"}
}