{
  "type": "Feature",
  "properties": {
    "gn:admin1_code":"51",
    "gn:asciiname":"Kotovka",
    "gn:country_code":"RU",
    "gn:dem":129,
    "gn:feature_class":"P",
    "gn:feature_code":"PPL",
    "gn:name":"Kotovka",
    "gn:population":0,
    "gn:timezone":"Europe/Moscow",
    "iso:country":"RU",
    "name:eng_x_preferred":[
        "Kotovka"
    ],
    "name:nor_x_preferred":[
        "Kotovka"
    ],
    "name:rus_x_preferred":[
        "\u041a\u043e\u0442\u043e\u0432\u043a\u0430"
    ],
    "name:und_x_variant":[
        "\u041a\u043e\u0442\u043e\u0432\u043a\u0430",
        "Kotovka"
    ],
    "wof:name":"Kotovka",
    "wof:placetype":"locality"
},
  "geometry": {"coordinates":[43.00181,55.27974],"type":"Point"}
}