{
  "type": "Feature",
  "properties": {
    "gn:admin1_code":"20",
    "gn:asciiname":"Ichera",
    "gn:country_code":"RU",
    "gn:dem":248,
    "gn:feature_class":"P",
    "gn:feature_code":"PPL",
    "gn:name":"Ich\u00ebra",
    "gn:population":0,
    "gn:timezone":"Asia/Irkutsk",
    "iso:country":"RU",
    "name:eng_x_preferred":[
        "Ich\u00ebra"
    ],
    "name:nor_x_preferred":[
        "Itsjera"
    ],
    "name:rus_x_preferred":[
        "\u0418\u0447\u0435\u0440\u0430"
    ],
    "name:rus_x_variant":[
        "\u0418\u0447\u0451\u0440\u0430"
    ],
    "name:und_x_variant":[
        "Ich\u00ebra",
        "\u0418\u0447\u0451\u0440\u0430"
    ],
    "wof:name":"Ichera",
    "wof:placetype":"locality"
},
  "geometry": {"coordinates":[109.76027999999999,58.51306],"type":"Point"}
}