{
  "type": "Feature",
  "properties": {
    "gn:admin1_code":"60",
    "gn:asciiname":"Smetsova",
    "gn:country_code":"RU",
    "gn:dem":181,
    "gn:feature_class":"P",
    "gn:feature_code":"PPL",
    "gn:name":"Smetsova",
    "gn:population":0,
    "gn:timezone":"Europe/Moscow",
    "iso:country":"RU",
    "name:rus_x_preferred":[
        "\u0421\u043c\u0435\u0446\u043e\u0432\u0430"
    ],
    "name:und_x_variant":[
        "\u0421\u043c\u0435\u0446\u043e\u0432\u0430"
    ],
    "wof:name":"Smetsova",
    "wof:placetype":"locality"
},
  "geometry": {"coordinates":[29.81667,55.93333000000001],"type":"Point"}
}