{
  "type": "Feature",
  "properties": {
    "gn:admin1_code":"43",
    "gn:asciiname":"Pisarevo",
    "gn:country_code":"RU",
    "gn:dem":166,
    "gn:feature_class":"P",
    "gn:feature_code":"PPL",
    "gn:name":"Pisarevo",
    "gn:population":0,
    "gn:timezone":"Europe/Moscow",
    "iso:country":"RU",
    "name:rus_x_preferred":[
        "\u041f\u0438\u0441\u0430\u0440\u0435\u0432\u043e"
    ],
    "name:und_x_variant":[
        "Pisarovo",
        "Pisarevo"
    ],
    "wof:name":"Pisarevo",
    "wof:placetype":"locality"
},
  "geometry": {"coordinates":[38.63319,53.29261],"type":"Point"}
}