{
  "type": "Feature",
  "properties": {
    "gn:admin1_code":"25",
    "gn:asciiname":"Pupovka",
    "gn:country_code":"RU",
    "gn:dem":163,
    "gn:feature_class":"P",
    "gn:feature_code":"PPL",
    "gn:name":"Pupovka",
    "gn:population":0,
    "gn:timezone":"Europe/Moscow",
    "iso:country":"RU",
    "name:rus_x_preferred":[
        "\u041f\u0443\u043f\u043e\u0432\u043a\u0430"
    ],
    "wof:name":"Pupovka",
    "wof:placetype":"locality"
},
  "geometry": {"coordinates":[35.21694,54.80333],"type":"Point"}
}