{
  "type": "Feature",
  "properties": {
    "gn:admin1_code":"84",
    "gn:asciiname":"Rog-Izmaylovskiy",
    "gn:country_code":"RU",
    "gn:dem":89,
    "gn:feature_class":"P",
    "gn:feature_code":"PPL",
    "gn:name":"Rog-Izmaylovskiy",
    "gn:population":0,
    "gn:timezone":"Europe/Volgograd",
    "iso:country":"RU",
    "name:eng_x_preferred":[
        "Rog-Izmaylovskiy"
    ],
    "name:nor_x_preferred":[
        "Rog-Izmajlovskij"
    ],
    "name:rus_x_preferred":[
        "\u0420\u043e\u0433-\u0418\u0437\u043c\u0430\u0439\u043b\u043e\u0432\u0441\u043a\u0438\u0439"
    ],
    "name:und_x_variant":[
        "\u0420\u043e\u0433-\u0418\u0437\u043c\u0430\u0439\u043b\u043e\u0432\u0441\u043a\u0438\u0439",
        "Rog-Izmaylovskiy"
    ],
    "wof:name":"Rog-Izmaylovskiy",
    "wof:placetype":"locality"
},
  "geometry": {"coordinates":[42.7463,50.6508],"type":"Point"}
}