{
  "type": "Feature",
  "properties": {
    "gn:admin1_code":"6.0",
    "gn:asciiname":"Poselok Kholm",
    "gn:country_code":"RU",
    "gn:dem":35,
    "gn:feature_class":"P",
    "gn:feature_code":"PPL",
    "gn:name":"Pos\u00eblok Kholm",
    "gn:population":0,
    "gn:timezone":"Europe/Moscow",
    "iso:country":"RU",
    "name:rus_x_preferred":[
        "\u041f\u043e\u0441\u0451\u043b\u043e\u043a \u0425\u043e\u043b\u043c"
    ],
    "name:und_x_variant":[
        "Pos\u00eblok Kholm"
    ],
    "wof:name":"Poselok Kholm",
    "wof:placetype":"locality"
},
  "geometry": {"coordinates":[43.5334,64.7054],"type":"Point"}
}