{
  "type": "Feature",
  "properties": {
    "gn:admin1_code":"29",
    "gn:asciiname":"Cheremushki",
    "gn:country_code":"RU",
    "gn:dem":230,
    "gn:feature_class":"P",
    "gn:feature_code":"PPL",
    "gn:name":"Cheremushki",
    "gn:population":0,
    "gn:timezone":"Asia/Novokuznetsk",
    "iso:country":"RU",
    "name:rus_x_preferred":[
        "\u0427\u0435\u0440\u0435\u043c\u0443\u0448\u043a\u0438"
    ],
    "wof:name":"Cheremushki",
    "wof:placetype":"locality"
},
  "geometry": {"coordinates":[85.9178,55.6117],"type":"Point"}
}