{
  "type": "Feature",
  "properties": {
    "gn:admin1_code":"06",
    "gn:asciiname":"Yefremkovskaya",
    "gn:cc2":"RU",
    "gn:country_code":"RU",
    "gn:dem":114,
    "gn:feature_class":"P",
    "gn:feature_code":"PPL",
    "gn:name":"Yefremkovskaya",
    "gn:population":0,
    "gn:timezone":"Europe/Moscow",
    "iso:country":"RU",
    "name:che_x_preferred":[
        "\u0415\u0444\u0440\u0435\u043c\u043a\u043e\u0432\u0441\u043a\u0438"
    ],
    "name:ita_x_preferred":[
        "Efremovskaja"
    ],
    "name:rus_x_preferred":[
        "\u0415\u0444\u0440\u0435\u043c\u043a\u043e\u0432\u0441\u043a\u0430\u044f"
    ],
    "name:tat_x_preferred":[
        "\u0415\u0444\u0440\u0435\u043c\u043a\u043e\u0432\u0441\u043a\u0430\u044f"
    ],
    "name:tgk_x_preferred":[
        "\u0415\u0444\u0440\u0435\u043c\u043a\u043e\u0432\u0441\u043a\u0430\u044f"
    ],
    "name:und_x_variant":[
        "Yefremovskaya",
        "Yefremkovskaya"
    ],
    "wof:name":"Yefremkovskaya",
    "wof:placetype":"locality"
},
  "geometry": {"coordinates":[42.09417,61.33722],"type":"Point"}
}