{
  "type": "Feature",
  "properties": {
    "gn:admin1_code":"8",
    "gn:asciiname":"Novofedorovka",
    "gn:country_code":"RU",
    "gn:dem":276,
    "gn:feature_class":"P",
    "gn:feature_code":"PPL",
    "gn:name":"Novof\u00ebdorovka",
    "gn:population":0,
    "gn:timezone":"Asia/Yekaterinburg",
    "iso:country":"RU",
    "name:rus_x_preferred":[
        "\u041d\u043e\u0432\u043e\u0444\u0451\u0434\u043e\u0440\u043e\u0432\u043a\u0430"
    ],
    "name:und_x_variant":[
        "Novof\u00ebdorovka",
        "\u041d\u043e\u0432\u043e\u0444\u0451\u0434\u043e\u0440\u043e\u0432\u043a\u0430"
    ],
    "wof:name":"Novofedorovka",
    "wof:placetype":"locality"
},
  "geometry": {"coordinates":[54.6424,53.5041],"type":"Point"}
}