{
  "type": "Feature",
  "properties": {
    "gn:admin1_code":"17",
    "gn:asciiname":"Aybala",
    "gn:country_code":"RU",
    "gn:dem":-2,
    "gn:feature_class":"P",
    "gn:feature_code":"PPL",
    "gn:name":"Aybala",
    "gn:population":0,
    "gn:timezone":"Europe/Moscow",
    "iso:country":"RU",
    "name:nor_x_preferred":[
        "Ajbala"
    ],
    "name:rus_x_preferred":[
        "\u0410\u0439\u0431\u0430\u043b\u0430"
    ],
    "wof:name":"Aybala",
    "wof:placetype":"locality"
},
  "geometry": {"coordinates":[46.77916,43.53052],"type":"Point"}
}