{
  "type": "Feature",
  "properties": {
    "gn:admin1_code":"83",
    "gn:asciiname":"Zlobayevo",
    "gn:country_code":"RU",
    "gn:dem":108,
    "gn:feature_class":"P",
    "gn:feature_code":"PPL",
    "gn:name":"Zlobayevo",
    "gn:population":0,
    "gn:timezone":"Europe/Moscow",
    "iso:country":"RU",
    "name:rus_x_preferred":[
        "\u0417\u043b\u043e\u0431\u0430\u0435\u0432\u043e"
    ],
    "name:und_x_variant":[
        "Zlobiyevo"
    ],
    "wof:name":"Zlobayevo",
    "wof:placetype":"locality"
},
  "geometry": {"coordinates":[42.1671,55.9909],"type":"Point"}
}