{
  "type": "Feature",
  "properties": {
    "gn:admin1_code":"62",
    "gn:asciiname":"Karandeyevo",
    "gn:country_code":"RU",
    "gn:dem":163,
    "gn:feature_class":"P",
    "gn:feature_code":"PPL",
    "gn:name":"Karandeyevo",
    "gn:population":0,
    "gn:timezone":"Europe/Moscow",
    "iso:country":"RU",
    "name:rus_x_preferred":[
        "\u041a\u0430\u0440\u0430\u043d\u0434\u0435\u0435\u0432\u043e"
    ],
    "name:und_x_variant":[
        "\u041a\u0430\u0440\u0430\u043d\u0434\u0435\u0435\u0432\u043e"
    ],
    "wof:name":"Karandeyevo",
    "wof:placetype":"locality"
},
  "geometry": {"coordinates":[41.1269,53.52045],"type":"Point"}
}