{
  "type": "Feature",
  "properties": {
    "gn:admin1_code":"63",
    "gn:asciiname":"Oyusardakh",
    "gn:country_code":"RU",
    "gn:dem":37,
    "gn:feature_class":"P",
    "gn:feature_code":"PPL",
    "gn:name":"Oyusardakh",
    "gn:population":0,
    "gn:timezone":"Asia/Magadan",
    "iso:country":"RU",
    "name:che_x_preferred":[
        "\u041e\u0439\u0443\u0441\u0430\u0440\u0434\u0430\u0445"
    ],
    "name:eng_x_preferred":[
        "Oyusardakh"
    ],
    "name:nor_x_preferred":[
        "Ojusardakh"
    ],
    "name:rus_x_preferred":[
        "\u041e\u0439\u0443\u0441\u0430\u0440\u0434\u0430\u0445"
    ],
    "name:rus_x_variant":[
        "\u041e\u044e\u0441\u0430\u0440\u0434\u0430\u0445"
    ],
    "name:und_x_variant":[
        "Oyusardaakh",
        "Oysurdakh",
        "Oyseerach"
    ],
    "wof:name":"Oyusardakh",
    "wof:placetype":"locality"
},
  "geometry": {"coordinates":[154.70844,68.27675000000001],"type":"Point"}
}