{
  "type": "Feature",
  "properties": {
    "gn:admin1_code":"88",
    "gn:asciiname":"Vaulino",
    "gn:country_code":"RU",
    "gn:dem":140,
    "gn:feature_class":"P",
    "gn:feature_code":"PPL",
    "gn:name":"Vaulino",
    "gn:population":0,
    "gn:timezone":"Europe/Moscow",
    "iso:country":"RU",
    "name:rus_x_preferred":[
        "\u0412\u0430\u0443\u043b\u0438\u043d\u043e"
    ],
    "wof:name":"Vaulino",
    "wof:placetype":"locality"
},
  "geometry": {"coordinates":[39.00006,57.74527],"type":"Point"}
}