{
  "type": "Feature",
  "properties": {
    "gn:admin1_code":"91.0",
    "gn:asciiname":"Progress",
    "gn:country_code":"RU",
    "gn:dem":280,
    "gn:feature_class":"P",
    "gn:feature_code":"PPL",
    "gn:name":"Progress",
    "gn:population":0,
    "gn:timezone":"Asia/Krasnoyarsk",
    "iso:country":"RU",
    "name:rus_x_preferred":[
        "\u041f\u0440\u043e\u0433\u0440\u0435\u0441\u0441"
    ],
    "wof:name":"Progress",
    "wof:placetype":"locality"
},
  "geometry": {"coordinates":[90.04889,55.835],"type":"Point"}
}