{
  "type": "Feature",
  "properties": {
    "gn:admin1_code":"33.0",
    "gn:asciiname":"Vas'kintsy",
    "gn:country_code":"RU",
    "gn:dem":150,
    "gn:feature_class":"P",
    "gn:feature_code":"PPL",
    "gn:name":"Vas\u2019kintsy",
    "gn:population":0,
    "gn:timezone":"Europe/Kirov",
    "iso:country":"RU",
    "name:rus_x_preferred":[
        "\u0412\u0430\u0441\u044c\u043a\u0438\u043d\u0446\u044b"
    ],
    "name:und_x_variant":[
        "Vas\u2019kintsy",
        "Vaskintsy"
    ],
    "wof:name":"Vas'kintsy",
    "wof:placetype":"locality"
},
  "geometry": {"coordinates":[50.21695,58.43782],"type":"Point"}
}