{
  "type": "Feature",
  "properties": {
    "gn:admin1_code":"21.0",
    "gn:asciiname":"Nikulikha",
    "gn:country_code":"RU",
    "gn:dem":80,
    "gn:feature_class":"P",
    "gn:feature_code":"PPL",
    "gn:name":"Nikulikha",
    "gn:population":0,
    "gn:timezone":"Europe/Moscow",
    "iso:country":"RU",
    "name:rus_x_preferred":[
        "\u041d\u0438\u043a\u0443\u043b\u0438\u0445\u0430"
    ],
    "wof:name":"Nikulikha",
    "wof:placetype":"locality"
},
  "geometry": {"coordinates":[41.96288,56.45706],"type":"Point"}
}