{
  "type": "Feature",
  "properties": {
    "gn:admin1_code":"42",
    "gn:asciiname":"Nizhneye Koyrovo",
    "gn:cc2":"RU",
    "gn:country_code":"RU",
    "gn:dem":47,
    "gn:feature_class":"P",
    "gn:feature_code":"PPL",
    "gn:name":"Nizhneye Koyrovo",
    "gn:population":0,
    "gn:timezone":"Europe/Moscow",
    "iso:country":"RU",
    "name:und_x_variant":[
        "Nizhneye Kayrovo"
    ],
    "wof:name":"Nizhneye Koyrovo",
    "wof:placetype":"locality"
},
  "geometry": {"coordinates":[30.26667,59.78333000000001],"type":"Point"}
}