{
  "type": "Feature",
  "properties": {
    "gn:admin1_code":"63",
    "gn:asciiname":"Mengyuryuen",
    "gn:country_code":"RU",
    "gn:dem":142,
    "gn:feature_class":"P",
    "gn:feature_code":"PPL",
    "gn:name":"Mengyuryuen",
    "gn:population":0,
    "gn:timezone":"Asia/Yakutsk",
    "iso:country":"RU",
    "name:rus_x_preferred":[
        "\u041c\u0435\u043d\u0433\u044e\u0440\u044e\u044d\u043d"
    ],
    "name:und_x_variant":[
        "Mengyuryuyen",
        "Mengyuryuen"
    ],
    "wof:name":"Mengyuryuen",
    "wof:placetype":"locality"
},
  "geometry": {"coordinates":[133.06253000000001,62.81521],"type":"Point"}
}