{
  "type": "Feature",
  "properties": {
    "gn:admin1_code":"72",
    "gn:asciiname":"Rybkino",
    "gn:country_code":"RU",
    "gn:dem":145,
    "gn:feature_class":"P",
    "gn:feature_code":"PPL",
    "gn:name":"Rybkino",
    "gn:population":0,
    "gn:timezone":"Europe/Moscow",
    "iso:country":"RU",
    "name:rus_x_preferred":[
        "\u0420\u044b\u0431\u043a\u0438\u043d\u043e"
    ],
    "wof:name":"Rybkino",
    "wof:placetype":"locality"
},
  "geometry": {"coordinates":[41.44511,51.96156],"type":"Point"}
}