{
  "type": "Feature",
  "properties": {
    "gn:admin1_code":"8",
    "gn:asciiname":"Nagretdinovo",
    "gn:country_code":"RU",
    "gn:dem":220,
    "gn:feature_class":"P",
    "gn:feature_code":"PPL",
    "gn:name":"Nagretdinovo",
    "gn:population":0,
    "gn:timezone":"Asia/Yekaterinburg",
    "iso:country":"RU",
    "name:rus_x_preferred":[
        "\u041d\u0430\u0433\u0440\u0435\u0442\u0434\u0438\u043d\u043e\u0432\u043e"
    ],
    "name:und_x_variant":[
        "\u041d\u0430\u0433\u0440\u0435\u0442\u0434\u0438\u043d\u043e\u0432\u043e"
    ],
    "wof:name":"Nagretdinovo",
    "wof:placetype":"locality"
},
  "geometry": {"coordinates":[56.31965,55.60652],"type":"Point"}
}