{
  "type": "Feature",
  "properties": {
    "gn:admin1_code":"4",
    "gn:asciiname":"Agrosvet",
    "gn:country_code":"RU",
    "gn:dem":202,
    "gn:feature_class":"P",
    "gn:feature_code":"PPL",
    "gn:name":"Agrosvet",
    "gn:population":0,
    "gn:timezone":"Asia/Barnaul",
    "iso:country":"RU",
    "name:rus_x_preferred":[
        "\u0410\u0433\u0440\u043e\u0441\u0432\u0435\u0442"
    ],
    "wof:name":"Agrosvet",
    "wof:placetype":"locality"
},
  "geometry": {"coordinates":[82.7272,53.1532],"type":"Point"}
}