{
  "type": "Feature",
  "properties": {
    "gn:admin1_code":"29",
    "gn:asciiname":"Stantsionnyy",
    "gn:country_code":"RU",
    "gn:dem":256,
    "gn:feature_class":"P",
    "gn:feature_code":"PPL",
    "gn:name":"Stantsionnyy",
    "gn:population":0,
    "gn:timezone":"Asia/Novokuznetsk",
    "iso:country":"RU",
    "name:rus_x_preferred":[
        "\u0421\u0442\u0430\u043d\u0446\u0438\u043e\u043d\u043d\u044b\u0439"
    ],
    "wof:name":"Stantsionnyy",
    "wof:placetype":"locality"
},
  "geometry": {"coordinates":[85.22306,55.36666999999999],"type":"Point"}
}