{
  "type": "Feature",
  "properties": {
    "gn:admin1_code":"28",
    "gn:asciiname":"Zhitnitskaya",
    "gn:cc2":"RU",
    "gn:country_code":"RU",
    "gn:dem":23,
    "gn:feature_class":"P",
    "gn:feature_code":"PPL",
    "gn:name":"Zhitnitskaya",
    "gn:population":0,
    "gn:timezone":"Europe/Moscow",
    "iso:country":"RU",
    "name:und_x_variant":[
        "Zhitnitsa",
        "Zhitnitskaya"
    ],
    "wof:name":"Zhitnitskaya",
    "wof:placetype":"locality"
},
  "geometry": {"coordinates":[35.56667,62.43333000000001],"type":"Point"}
}