{
  "type": "Feature",
  "properties": {
    "gn:admin1_code":"30",
    "gn:asciiname":"Inya",
    "gn:country_code":"RU",
    "gn:dem":5,
    "gn:feature_class":"P",
    "gn:feature_code":"PPL",
    "gn:name":"Inya",
    "gn:population":0,
    "gn:timezone":"Asia/Vladivostok",
    "iso:country":"RU",
    "name:rus_x_preferred":[
        "\u0418\u043d\u044f"
    ],
    "name:und_x_variant":[
        "Inskaya",
        "Inya"
    ],
    "wof:name":"Inya",
    "wof:placetype":"locality"
},
  "geometry": {"coordinates":[144.82552999999999,59.39155],"type":"Point"}
}