{
  "type": "Feature",
  "properties": {
    "gn:admin1_code":"52",
    "gn:asciiname":"Bobovishche",
    "gn:country_code":"RU",
    "gn:dem":111,
    "gn:feature_class":"P",
    "gn:feature_code":"PPL",
    "gn:name":"Bobovishche",
    "gn:population":0,
    "gn:timezone":"Europe/Moscow",
    "iso:country":"RU",
    "name:rus_x_preferred":[
        "\u0411\u043e\u0431\u043e\u0432\u0438\u0449\u0435"
    ],
    "wof:name":"Bobovishche",
    "wof:placetype":"locality"
},
  "geometry": {"coordinates":[31.5692,57.1049],"type":"Point"}
}