{
  "type": "Feature",
  "properties": {
    "gn:admin1_code":"10",
    "gn:asciiname":"Sadovyy",
    "gn:country_code":"RU",
    "gn:dem":206,
    "gn:feature_class":"P",
    "gn:feature_code":"PPL",
    "gn:name":"Sadovyy",
    "gn:population":0,
    "gn:timezone":"Europe/Moscow",
    "iso:country":"RU",
    "name:rus_x_preferred":[
        "\u0421\u0430\u0434\u043e\u0432\u044b\u0439"
    ],
    "name:und_x_variant":[
        "Malyy P\u2019yavitskiy",
        "Sadovyy"
    ],
    "wof:name":"Sadovyy",
    "wof:placetype":"locality"
},
  "geometry": {"coordinates":[34.47009,52.91636999999999],"type":"Point"}
}