{
  "type": "Feature",
  "properties": {
    "gn:country":"RU",
    "gn:fcode":"PPL",
    "gn:population":2078,
    "iso:country":"RU",
    "name:eng_x_preferred":[
        "Nyda"
    ],
    "name:nor_x_preferred":[
        "Nyda"
    ],
    "name:rus_x_preferred":[
        "\u041d\u044b\u0434\u0430"
    ],
    "qs:name":"Nyda",
    "qs:photos_9r":0,
    "qs:photos_sr":0,
    "qs:pop_sr":"4",
    "wof:name":"Nyda",
    "wof:placetype":"locality",
    "wof:population":2078
},
  "geometry": {"coordinates":[72.92278,66.62472],"type":"Point"}
}