{
  "type": "Feature",
  "properties": {
    "gn:admin1_code":"77",
    "gn:asciiname":"Ponomar'kovo",
    "gn:country_code":"RU",
    "gn:dem":143,
    "gn:feature_class":"P",
    "gn:feature_code":"PPL",
    "gn:name":"Ponomar\u2019kovo",
    "gn:population":0,
    "gn:timezone":"Europe/Moscow",
    "iso:country":"RU",
    "name:nor_x_preferred":[
        "Ponomarkovo"
    ],
    "name:rus_x_preferred":[
        "\u041f\u043e\u043d\u043e\u043c\u0430\u0440\u044c\u043a\u043e\u0432\u043e"
    ],
    "name:und_x_variant":[
        "Ponomar\u2019kovo"
    ],
    "wof:name":"Ponomar'kovo",
    "wof:placetype":"locality"
},
  "geometry": {"coordinates":[35.62779000000001,56.49945],"type":"Point"}
}