{
  "type": "Feature",
  "properties": {
    "gn:admin1_code":"41",
    "gn:asciiname":"Polnyy",
    "gn:country_code":"RU",
    "gn:dem":165,
    "gn:feature_class":"P",
    "gn:feature_code":"PPL",
    "gn:name":"Polnyy",
    "gn:population":0,
    "gn:timezone":"Europe/Moscow",
    "iso:country":"RU",
    "name:rus_x_preferred":[
        "\u041f\u043e\u043b\u043d\u044b\u0439"
    ],
    "name:und_x_variant":[
        "Polny",
        "Polnyy"
    ],
    "wof:name":"Polnyy",
    "wof:placetype":"locality"
},
  "geometry": {"coordinates":[36.46038,51.55823],"type":"Point"}
}