{
  "type": "Feature",
  "properties": {
    "gn:country":"RU",
    "gn:fcode":"PPL",
    "gn:pop":0,
    "iso:country":"RU",
    "name:rus_x_preferred":[
        "\u0414\u0430\u043b\u044c\u043d\u044f\u044f \u0418\u0433\u0443\u043c\u0435\u043d\u043a\u0430"
    ],
    "name:unk_x_variant":[
        "Dal\u2019naya Igumenka"
    ],
    "qs:name":"Dal'nyaya Igumenka",
    "qs:name_adm0":"Russia",
    "qs:name_adm1":"Belgorod Oblast",
    "qs:photos_9r":0,
    "qs:photos_sr":0,
    "qs:placetype":"Town",
    "qs:pop_sr":"0",
    "wof:name":"Dal'nyaya Igumenka",
    "wof:placetype":"locality",
    "wof:population":0
},
  "geometry": {"coordinates":[36.73767,50.69175],"type":"Point"}
}