{
  "type": "Feature",
  "properties": {
    "gn:admin1_code":"9.0",
    "gn:asciiname":"Nevedomyy Kolodez'",
    "gn:country_code":"RU",
    "gn:dem":171,
    "gn:feature_class":"P",
    "gn:feature_code":"PPL",
    "gn:name":"Nevedomyy Kolodez\u2019",
    "gn:population":0,
    "gn:timezone":"Europe/Moscow",
    "iso:country":"RU",
    "wof:name":"Nevedomyy Kolodez'",
    "wof:placetype":"locality"
},
  "geometry": {"coordinates":[36.07006,50.70099],"type":"Point"}
}