{
  "type": "Feature",
  "properties": {
    "gn:admin1_code":"4",
    "gn:asciiname":"Shchebenistyy",
    "gn:country_code":"RU",
    "gn:dem":644,
    "gn:feature_class":"P",
    "gn:feature_code":"PPL",
    "gn:name":"Shchebenistyy",
    "gn:population":0,
    "gn:timezone":"Asia/Barnaul",
    "iso:country":"RU",
    "name:rus_x_preferred":[
        "\u0429\u0435\u0431\u0435\u043d\u0438\u0441\u0442\u044b\u0439"
    ],
    "name:und_x_variant":[
        "\u0429\u0435\u0431\u0435\u043d\u0438\u0441\u0442\u044b\u0439"
    ],
    "wof:name":"Shchebenistyy",
    "wof:placetype":"locality"
},
  "geometry": {"coordinates":[85.53333000000001,51.81667],"type":"Point"}
}