{
  "type": "Feature",
  "properties": {
    "gn:admin1_code":"77",
    "gn:asciiname":"Nosonovka",
    "gn:country_code":"RU",
    "gn:dem":239,
    "gn:feature_class":"P",
    "gn:feature_code":"PPL",
    "gn:name":"Nosonovka",
    "gn:population":0,
    "gn:timezone":"Europe/Moscow",
    "iso:country":"RU",
    "wof:name":"Nosonovka",
    "wof:placetype":"locality"
},
  "geometry": {"coordinates":[32.04555999999999,56.94806],"type":"Point"}
}