{
  "type": "Feature",
  "properties": {
    "gn:admin1_code":"51.0",
    "gn:asciiname":"Novaya",
    "gn:country_code":"RU",
    "gn:dem":109,
    "gn:feature_class":"P",
    "gn:feature_code":"PPL",
    "gn:name":"Novaya",
    "gn:population":0,
    "gn:timezone":"Europe/Moscow",
    "iso:country":"RU",
    "name:nor_x_preferred":[
        "Novaja"
    ],
    "name:rus_x_preferred":[
        "\u041d\u043e\u0432\u0430\u044f"
    ],
    "wof:name":"Novaya",
    "wof:placetype":"locality"
},
  "geometry": {"coordinates":[43.0977,56.66453000000001],"type":"Point"}
}