{
  "type": "Feature",
  "properties": {
    "gn:admin1_code":"91.0",
    "gn:asciiname":"Konok",
    "gn:country_code":"RU",
    "gn:dem":381,
    "gn:feature_class":"P",
    "gn:feature_code":"PPL",
    "gn:name":"Konok",
    "gn:population":0,
    "gn:timezone":"Asia/Krasnoyarsk",
    "iso:country":"RU",
    "name:rus_x_preferred":[
        "\u041a\u043e\u043d\u043e\u043a"
    ],
    "wof:name":"Konok",
    "wof:placetype":"locality"
},
  "geometry": {"coordinates":[94.4932,55.4503],"type":"Point"}
}