{
  "type": "Feature",
  "properties": {
    "gn:admin1_code":"37.0",
    "gn:asciiname":"Manyl'tsevo",
    "gn:country_code":"RU",
    "gn:dem":121,
    "gn:feature_class":"P",
    "gn:feature_code":"PPL",
    "gn:name":"Manyl\u2019tsevo",
    "gn:population":0,
    "gn:timezone":"Europe/Moscow",
    "iso:country":"RU",
    "name:rus_x_preferred":[
        "\u041c\u0430\u043d\u044b\u043b\u044c\u0446\u0435\u0432\u043e"
    ],
    "name:und_x_variant":[
        "Manyl\u2019tsevo",
        "\u041c\u0430\u043d\u044b\u043b\u044c\u0446\u0435\u0432\u043e"
    ],
    "wof:name":"Manyl'tsevo",
    "wof:placetype":"locality"
},
  "geometry": {"coordinates":[41.36429,57.67034],"type":"Point"}
}