{
  "type": "Feature",
  "properties": {
    "gn:admin1_code":"90",
    "gn:asciiname":"Sobol'ki",
    "gn:country_code":"RU",
    "gn:dem":135,
    "gn:feature_class":"P",
    "gn:feature_code":"PPL",
    "gn:name":"Sobol\u2019ki",
    "gn:population":0,
    "gn:timezone":"Asia/Yekaterinburg",
    "iso:country":"RU",
    "name:nor_x_preferred":[
        "Sobolki"
    ],
    "name:rus_x_preferred":[
        "\u0421\u043e\u0431\u043e\u043b\u044c\u043a\u0438"
    ],
    "name:und_x_variant":[
        "Sobol\u2019ki"
    ],
    "wof:name":"Sobol'ki",
    "wof:placetype":"locality"
},
  "geometry": {"coordinates":[56.5473,58.8855],"type":"Point"}
}