{
  "type": "Feature",
  "properties": {
    "gn:admin1_code":"60",
    "gn:asciiname":"Dolysets",
    "gn:country_code":"RU",
    "gn:dem":100,
    "gn:feature_class":"P",
    "gn:feature_code":"PPL",
    "gn:name":"Dolysets",
    "gn:population":0,
    "gn:timezone":"Europe/Moscow",
    "iso:country":"RU",
    "name:rus_x_preferred":[
        "\u0414\u043e\u043b\u044b\u0441\u0435\u0446"
    ],
    "wof:name":"Dolysets",
    "wof:placetype":"locality"
},
  "geometry": {"coordinates":[29.0697,56.877],"type":"Point"}
}