{
  "type": "Feature",
  "properties": {
    "gn:admin1_code":"21",
    "gn:asciiname":"Sidorino",
    "gn:country_code":"RU",
    "gn:dem":129,
    "gn:feature_class":"P",
    "gn:feature_code":"PPL",
    "gn:name":"Sidorino",
    "gn:population":0,
    "gn:timezone":"Europe/Moscow",
    "iso:country":"RU",
    "name:rus_x_preferred":[
        "\u0421\u0438\u0434\u043e\u0440\u0438\u043d\u043e"
    ],
    "wof:name":"Sidorino",
    "wof:placetype":"locality"
},
  "geometry": {"coordinates":[40.53044000000001,56.78055],"type":"Point"}
}