{
  "type": "Feature",
  "properties": {
    "gn:admin1_code":"70.0",
    "gn:asciiname":"Charikov",
    "gn:country_code":"RU",
    "gn:dem":129,
    "gn:feature_class":"P",
    "gn:feature_code":"PPL",
    "gn:name":"Charikov",
    "gn:population":0,
    "gn:timezone":"Europe/Moscow",
    "iso:country":"RU",
    "name:rus_x_preferred":[
        "\u0427\u0430\u0440\u0438\u043a\u043e\u0432"
    ],
    "name:und_x_variant":[
        "\u0427\u0430\u0440\u0438\u043a\u043e\u0432"
    ],
    "wof:name":"Charikov",
    "wof:placetype":"locality"
},
  "geometry": {"coordinates":[44.21528,44.42278],"type":"Point"}
}