{
  "type": "Feature",
  "properties": {
    "gn:admin1_code":"10",
    "gn:asciiname":"Morozovshchina",
    "gn:country_code":"RU",
    "gn:dem":174,
    "gn:feature_class":"P",
    "gn:feature_code":"PPL",
    "gn:name":"Morozovshchina",
    "gn:population":0,
    "gn:timezone":"Europe/Moscow",
    "iso:country":"RU",
    "name:rus_x_preferred":[
        "\u041c\u043e\u0440\u043e\u0437\u043e\u0432\u0449\u0438\u043d\u0430"
    ],
    "name:und_x_variant":[
        "\u041c\u043e\u0440\u043e\u0437\u043e\u0432\u0449\u0438\u043d\u0430"
    ],
    "wof:name":"Morozovshchina",
    "wof:placetype":"locality"
},
  "geometry": {"coordinates":[32.18399,52.67616],"type":"Point"}
}