{
  "type": "Feature",
  "properties": {
    "gn:admin1_code":"69",
    "gn:asciiname":"Gostimlya",
    "gn:country_code":"RU",
    "gn:dem":197,
    "gn:feature_class":"P",
    "gn:feature_code":"PPL",
    "gn:name":"Gostimlya",
    "gn:population":0,
    "gn:timezone":"Europe/Moscow",
    "iso:country":"RU",
    "name:rus_x_preferred":[
        "\u0413\u043e\u0441\u0442\u0438\u043c\u043b\u044f"
    ],
    "wof:name":"Gostimlya",
    "wof:placetype":"locality"
},
  "geometry": {"coordinates":[32.06662,54.41791],"type":"Point"}
}