{
  "type": "Feature",
  "properties": {
    "gn:admin1_code":"62",
    "gn:asciiname":"Malino",
    "gn:country_code":"RU",
    "gn:dem":100,
    "gn:feature_class":"P",
    "gn:feature_code":"PPL",
    "gn:name":"Malino",
    "gn:population":0,
    "gn:timezone":"Europe/Moscow",
    "iso:country":"RU",
    "name:bos_x_preferred":[
        "Malino"
    ],
    "name:ceb_x_preferred":[
        "Malino"
    ],
    "name:rus_x_preferred":[
        "\u041c\u0430\u043b\u0438\u043d\u043e"
    ],
    "name:swe_x_preferred":[
        "Malino"
    ],
    "name:und_x_variant":[
        "\u041c\u0430\u043b\u0438\u043d\u043e"
    ],
    "wof:name":"Malino",
    "wof:placetype":"locality"
},
  "geometry": {"coordinates":[40.3735,54.5359],"type":"Point"}
}