{
  "type": "Feature",
  "properties": {
    "gn:admin1_code":"47",
    "gn:asciiname":"Tumenskoye",
    "gn:country_code":"RU",
    "gn:dem":142,
    "gn:feature_class":"P",
    "gn:feature_code":"PPL",
    "gn:name":"Tumenskoye",
    "gn:population":0,
    "gn:timezone":"Europe/Moscow",
    "iso:country":"RU",
    "name:eng_x_preferred":[
        "Tumenskoye"
    ],
    "name:nor_x_preferred":[
        "Tumenskoje"
    ],
    "name:rus_x_preferred":[
        "\u0422\u0443\u043c\u0435\u043d\u0441\u043a\u043e\u0435"
    ],
    "wof:name":"Tumenskoye",
    "wof:placetype":"locality"
},
  "geometry": {"coordinates":[38.5281,55.007],"type":"Point"}
}