{
  "type": "Feature",
  "properties": {
    "gn:admin1_code":"84.0",
    "gn:asciiname":"Dva Dereva",
    "gn:country_code":"RU",
    "gn:dem":174,
    "gn:feature_class":"P",
    "gn:feature_code":"PPL",
    "gn:name":"Dva Dereva",
    "gn:population":0,
    "gn:timezone":"Europe/Volgograd",
    "iso:country":"RU",
    "name:rus_x_preferred":[
        "\u0414\u0432\u0430 \u0414\u0435\u0440\u0435\u0432\u0430"
    ],
    "wof:name":"Dva Dereva",
    "wof:placetype":"locality"
},
  "geometry": {"coordinates":[42.224,50.1021],"type":"Point"}
}