{
  "type": "Feature",
  "properties": {
    "gn:admin1_code":"75",
    "gn:asciiname":"Nulevoy Piket",
    "gn:country_code":"RU",
    "gn:dem":81,
    "gn:feature_class":"P",
    "gn:feature_code":"PPL",
    "gn:name":"Nulevoy Piket",
    "gn:population":0,
    "gn:timezone":"Asia/Tomsk",
    "iso:country":"RU",
    "name:eng_x_preferred":[
        "Nulevoy Piket"
    ],
    "name:rus_x_preferred":[
        "\u041d\u0443\u043b\u0435\u0432\u043e\u0439-\u041f\u0438\u043a\u0435\u0442"
    ],
    "name:rus_x_variant":[
        "\u041d\u0443\u043b\u0435\u0432\u043e\u0439 \u041f\u0438\u043a\u0435\u0442"
    ],
    "name:und_x_variant":[
        "Nulevoy"
    ],
    "wof:name":"Nulevoy Piket",
    "wof:placetype":"locality"
},
  "geometry": {"coordinates":[85.1463,57.7745],"type":"Point"}
}