{
  "type": "Feature",
  "properties": {
    "gn:admin1_code":"30",
    "gn:asciiname":"Rybalka Pervaya",
    "gn:country_code":"RU",
    "gn:dem":176,
    "gn:feature_class":"P",
    "gn:feature_code":"PPL",
    "gn:name":"Rybalka Pervaya",
    "gn:population":0,
    "gn:timezone":"Asia/Vladivostok",
    "iso:country":"RU",
    "name:rus_x_preferred":[
        "\u0420\u044b\u0431\u0430\u043b\u043a\u0430 \u041f\u0435\u0440\u0432\u0430\u044f"
    ],
    "wof:name":"Rybalka Pervaya",
    "wof:placetype":"locality"
},
  "geometry": {"coordinates":[132.98333,53.88333000000001],"type":"Point"}
}