{
  "type": "Feature",
  "properties": {
    "gn:admin1_code":"47",
    "gn:asciiname":"Kholuyanikha",
    "gn:country_code":"RU",
    "gn:dem":212,
    "gn:feature_class":"P",
    "gn:feature_code":"PPL",
    "gn:name":"Kholuyanikha",
    "gn:population":0,
    "gn:timezone":"Europe/Moscow",
    "iso:country":"RU",
    "name:rus_x_preferred":[
        "\u0425\u043e\u043b\u0443\u044f\u043d\u0438\u0445\u0430"
    ],
    "name:und_x_variant":[
        "\u0425\u043e\u043b\u0443\u044f\u043d\u0438\u0445\u0430"
    ],
    "wof:name":"Kholuyanikha",
    "wof:placetype":"locality"
},
  "geometry": {"coordinates":[36.62472,55.93417],"type":"Point"}
}