{
  "type": "Feature",
  "properties": {
    "gn:admin1_code":"17.0",
    "gn:admin2_code":"549104",
    "gn:asciiname":"Arani",
    "gn:country_code":"RU",
    "gn:dem":1683,
    "gn:feature_class":"P",
    "gn:feature_code":"PPL",
    "gn:name":"Arani",
    "gn:population":0,
    "gn:timezone":"Europe/Moscow",
    "iso:country":"RU",
    "name:ceb_x_preferred":[
        "Arani"
    ],
    "name:deu_x_preferred":[
        "Arani"
    ],
    "name:ita_x_preferred":[
        "Arani"
    ],
    "name:msa_x_preferred":[
        "Arani"
    ],
    "name:nld_x_preferred":[
        "Arani"
    ],
    "name:nor_x_preferred":[
        "Arani"
    ],
    "name:rus_x_preferred":[
        "\u0410\u0440\u0430\u043d\u0438"
    ],
    "name:spa_x_preferred":[
        "Arani"
    ],
    "name:swe_x_preferred":[
        "Arani"
    ],
    "wof:name":"Arani",
    "wof:placetype":"locality"
},
  "geometry": {"coordinates":[46.7228,42.55694],"type":"Point"}
}