{
  "type": "Feature",
  "properties": {
    "gn:admin1_code":"60",
    "gn:asciiname":"Khrushcheli",
    "gn:country_code":"RU",
    "gn:dem":165,
    "gn:feature_class":"P",
    "gn:feature_code":"PPL",
    "gn:name":"Khrushcheli",
    "gn:population":0,
    "gn:timezone":"Europe/Moscow",
    "iso:country":"RU",
    "name:rus_x_preferred":[
        "\u0425\u0440\u0443\u0449\u0435\u043b\u0438"
    ],
    "wof:name":"Khrushcheli",
    "wof:placetype":"locality"
},
  "geometry": {"coordinates":[30.9114,56.073],"type":"Point"}
}