{
  "type": "Feature",
  "properties": {
    "gn:admin1_code":"73",
    "gn:asciiname":"Staroye Slyakovo",
    "gn:country_code":"RU",
    "gn:dem":98,
    "gn:feature_class":"P",
    "gn:feature_code":"PPL",
    "gn:name":"Staroye Slyakovo",
    "gn:population":0,
    "gn:timezone":"Europe/Moscow",
    "iso:country":"RU",
    "name:nor_x_preferred":[
        "Staroje Sljakovo"
    ],
    "name:rus_x_preferred":[
        "\u0421\u0442\u0430\u0440\u043e\u0435 \u0421\u043b\u044f\u043a\u043e\u0432\u043e"
    ],
    "name:und_x_variant":[
        "Sredneye Slyakovo",
        "Staroye Slyakovo"
    ],
    "wof:name":"Staroye Slyakovo",
    "wof:placetype":"locality"
},
  "geometry": {"coordinates":[53.51111,56.17647],"type":"Point"}
}