{
  "type": "Feature",
  "properties": {
    "gn:admin1_code":"8",
    "gn:asciiname":"Nizhniye Usly",
    "gn:country_code":"RU",
    "gn:dem":171,
    "gn:feature_class":"P",
    "gn:feature_code":"PPL",
    "gn:name":"Nizhniye Usly",
    "gn:population":0,
    "gn:timezone":"Asia/Yekaterinburg",
    "iso:country":"RU",
    "name:rus_x_preferred":[
        "\u041d\u0438\u0436\u043d\u0438\u0435 \u0423\u0441\u043b\u044b"
    ],
    "wof:name":"Nizhniye Usly",
    "wof:placetype":"locality"
},
  "geometry": {"coordinates":[55.60876,53.70427],"type":"Point"}
}