{
  "type": "Feature",
  "properties": {
    "gn:admin1_code":"38",
    "gn:asciiname":"Mar'inskiy",
    "gn:country_code":"RU",
    "gn:dem":213,
    "gn:feature_class":"P",
    "gn:feature_code":"PPL",
    "gn:name":"Mar\u2019inskiy",
    "gn:population":0,
    "gn:timezone":"Europe/Moscow",
    "iso:country":"RU",
    "name:rus_x_preferred":[
        "\u041c\u0430\u0440\u044c\u0438\u043d\u0441\u043a\u0438\u0439"
    ],
    "name:und_x_variant":[
        "Mor\u2019inskiy",
        "Mar\u2019inskiy"
    ],
    "wof:name":"Mar'inskiy",
    "wof:placetype":"locality"
},
  "geometry": {"coordinates":[40.89722,45.05639],"type":"Point"}
}