{
  "type": "Feature",
  "properties": {
    "gn:admin1_code":"53",
    "gn:asciiname":"Pautovskiy",
    "gn:country_code":"RU",
    "gn:dem":138,
    "gn:feature_class":"P",
    "gn:feature_code":"PPL",
    "gn:name":"Pautovskiy",
    "gn:population":0,
    "gn:timezone":"Asia/Novosibirsk",
    "iso:country":"RU",
    "name:eng_x_preferred":[
        "Pautovskiy"
    ],
    "name:nor_x_preferred":[
        "Pautovskij"
    ],
    "name:rus_x_preferred":[
        "\u041f\u0430\u0443\u0442\u043e\u0432\u0441\u043a\u0438\u0439"
    ],
    "name:und_x_variant":[
        "Pikhtovskaya"
    ],
    "wof:name":"Pautovskiy",
    "wof:placetype":"locality"
},
  "geometry": {"coordinates":[82.7572,55.5652],"type":"Point"}
}