{
  "type": "Feature",
  "properties": {
    "gn:admin1_code":"75",
    "gn:asciiname":"Yelegecheva",
    "gn:country_code":"RU",
    "gn:dem":111,
    "gn:feature_class":"P",
    "gn:feature_code":"PPL",
    "gn:name":"Yelegecheva",
    "gn:population":0,
    "gn:timezone":"Asia/Tomsk",
    "iso:country":"RU",
    "wof:name":"Yelegecheva",
    "wof:placetype":"locality"
},
  "geometry": {"coordinates":[83.33333,56.43333000000001],"type":"Point"}
}