{
  "type": "Feature",
  "properties": {
    "gn:admin1_code":"20",
    "gn:asciiname":"Nikol'skaya",
    "gn:country_code":"RU",
    "gn:dem":375,
    "gn:feature_class":"P",
    "gn:feature_code":"PPL",
    "gn:name":"Nikol\u2019skaya",
    "gn:population":0,
    "gn:timezone":"Asia/Irkutsk",
    "iso:country":"RU",
    "name:eng_x_preferred":[
        "Nikol'skaya"
    ],
    "name:nor_x_preferred":[
        "Nikolskij"
    ],
    "name:rus_x_preferred":[
        "\u041d\u0438\u043a\u043e\u043b\u044c\u0441\u043a\u0438\u0439"
    ],
    "name:rus_x_variant":[
        "\u041d\u0438\u043a\u043e\u043b\u044c\u0441\u043a\u0430\u044f"
    ],
    "name:und_x_variant":[
        "Nikol\u2019skaya",
        "\u041d\u0438\u043a\u043e\u043b\u044c\u0441\u043a\u0430\u044f"
    ],
    "wof:name":"Nikol'skaya",
    "wof:placetype":"locality"
},
  "geometry": {"coordinates":[98.46666999999999,55.65],"type":"Point"}
}