{
  "type": "Feature",
  "properties": {
    "gn:admin1_code":"55",
    "gn:asciiname":"Ponikla",
    "gn:country_code":"RU",
    "gn:dem":110,
    "gn:feature_class":"P",
    "gn:feature_code":"PPL",
    "gn:name":"Ponikla",
    "gn:population":0,
    "gn:timezone":"Asia/Yekaterinburg",
    "iso:country":"RU",
    "name:eng_x_preferred":[
        "Ponikla"
    ],
    "name:nor_x_preferred":[
        "Ponikla"
    ],
    "name:rus_x_preferred":[
        "\u041f\u043e\u043d\u0438\u043a\u043b\u0430"
    ],
    "name:und_x_variant":[
        "\u041f\u043e\u043d\u0438\u043a\u043b\u0430",
        "Ponikla"
    ],
    "wof:name":"Ponikla",
    "wof:placetype":"locality"
},
  "geometry": {"coordinates":[52.4881,53.5429],"type":"Point"}
}