{
  "type": "Feature",
  "properties": {
    "gn:admin1_code":"57",
    "gn:asciiname":"Lesnoy",
    "gn:cc2":"RU",
    "gn:country_code":"RU",
    "gn:dem":251,
    "gn:feature_class":"P",
    "gn:feature_code":"PPL",
    "gn:name":"Lesnoy",
    "gn:population":0,
    "gn:timezone":"Europe/Moscow",
    "iso:country":"RU",
    "name:rus_x_preferred":[
        "\u041b\u0435\u0441\u043d\u043e\u0439"
    ],
    "name:und_x_variant":[
        "Batrak",
        "Lesnoy",
        "\u041b\u0435\u0441\u043d\u043e\u0439"
    ],
    "wof:name":"Lesnoy",
    "wof:placetype":"locality"
},
  "geometry": {"coordinates":[43.33333,53.33333],"type":"Point"}
}