{
  "type": "Feature",
  "properties": {
    "gn:admin1_code":"10",
    "gn:asciiname":"Ivano-Prokh",
    "gn:country_code":"RU",
    "gn:dem":173,
    "gn:feature_class":"P",
    "gn:feature_code":"PPL",
    "gn:name":"Ivano-Prokh",
    "gn:population":0,
    "gn:timezone":"Europe/Moscow",
    "iso:country":"RU",
    "name:rus_x_preferred":[
        "\u0418\u0432\u0430\u043d\u043e-\u041f\u0440\u043e\u0445"
    ],
    "wof:name":"Ivano-Prokh",
    "wof:placetype":"locality"
},
  "geometry": {"coordinates":[32.81333,53.3575],"type":"Point"}
}