{
  "type": "Feature",
  "properties": {
    "gn:admin1_code":"67",
    "gn:asciiname":"Shilovka",
    "gn:country_code":"RU",
    "gn:dem":180,
    "gn:feature_class":"P",
    "gn:feature_code":"PPL",
    "gn:name":"Shilovka",
    "gn:population":0,
    "gn:timezone":"Europe/Saratov",
    "iso:country":"RU",
    "name:rus_x_preferred":[
        "\u0428\u0438\u043b\u043e\u0432\u043a\u0430"
    ],
    "wof:name":"Shilovka",
    "wof:placetype":"locality"
},
  "geometry": {"coordinates":[44.55461,52.23925],"type":"Point"}
}