{
  "type": "Feature",
  "properties": {
    "gn:admin1_code":"8.0",
    "gn:asciiname":"Cheraul",
    "gn:country_code":"RU",
    "gn:dem":116,
    "gn:feature_class":"P",
    "gn:feature_code":"PPL",
    "gn:name":"Cheraul",
    "gn:population":0,
    "gn:timezone":"Asia/Yekaterinburg",
    "iso:country":"RU",
    "name:rus_x_preferred":[
        "\u0427\u0435\u0440\u0430\u0443\u043b"
    ],
    "name:und_x_variant":[
        "Cheraulovo",
        "Cheraul",
        "\u0427\u0435\u0440\u0430\u0443\u043b"
    ],
    "wof:name":"Cheraul",
    "wof:placetype":"locality"
},
  "geometry": {"coordinates":[54.9293,56.0712],"type":"Point"}
}