{
  "type": "Feature",
  "properties": {
    "gn:admin1_code":"77",
    "gn:asciiname":"Plotnitsa",
    "gn:country_code":"RU",
    "gn:dem":119,
    "gn:feature_class":"P",
    "gn:feature_code":"PPL",
    "gn:name":"Plotnitsa",
    "gn:population":0,
    "gn:timezone":"Europe/Moscow",
    "iso:country":"RU",
    "name:rus_x_preferred":[
        "\u041f\u043b\u043e\u0442\u043d\u0438\u0446\u0430"
    ],
    "name:und_x_variant":[
        "\u041f\u043b\u043e\u0442\u043d\u0438\u0446\u0430"
    ],
    "wof:name":"Plotnitsa",
    "wof:placetype":"locality"
},
  "geometry": {"coordinates":[37.8344,57.0724],"type":"Point"}
}