{
  "type": "Feature",
  "properties": {
    "gn:admin1_code":"73",
    "gn:asciiname":"Urazbakhtino",
    "gn:country_code":"RU",
    "gn:dem":80,
    "gn:feature_class":"P",
    "gn:feature_code":"PPL",
    "gn:name":"Urazbakhtino",
    "gn:population":0,
    "gn:timezone":"Europe/Moscow",
    "iso:country":"RU",
    "name:eng_x_preferred":[
        "Urazbakhtino"
    ],
    "name:nor_x_preferred":[
        "Urazbakhtino"
    ],
    "name:rus_x_preferred":[
        "\u0423\u0440\u0430\u0437\u0431\u0430\u0445\u0442\u0438\u043d\u043e"
    ],
    "wof:name":"Urazbakhtino",
    "wof:placetype":"locality"
},
  "geometry": {"coordinates":[51.13552,55.58984],"type":"Point"}
}