{
  "type": "Feature",
  "properties": {
    "gn:admin1_code":"42",
    "gn:admin2_code":"575409",
    "gn:asciiname":"Kazennoye Selo",
    "gn:cc2":"RU",
    "gn:country_code":"RU",
    "gn:dem":127,
    "gn:feature_class":"P",
    "gn:feature_code":"PPL",
    "gn:name":"Kaz\u00ebnnoye Selo",
    "gn:population":0,
    "gn:timezone":"Europe/Moscow",
    "iso:country":"RU",
    "name:eng_x_preferred":[
        "Kaz\u00ebnnoye Selo"
    ],
    "name:nor_x_preferred":[
        "Kazennoje Selo"
    ],
    "name:rus_x_preferred":[
        "\u041a\u0430\u0437\u0435\u043d\u043d\u043e\u0435 \u0421\u0435\u043b\u043e"
    ],
    "name:rus_x_variant":[
        "\u041a\u0430\u0437\u0451\u043d\u043d\u043e\u0435 \u0421\u0435\u043b\u043e"
    ],
    "name:und_x_variant":[
        "Selo",
        "Kaz\u00ebnnoye Selo"
    ],
    "wof:name":"Kazennoye Selo",
    "wof:placetype":"locality"
},
  "geometry": {"coordinates":[34.32056,59.64083],"type":"Point"}
}