{
  "type": "Feature",
  "properties": {
    "gn:admin1_code":"17",
    "gn:admin2_code":"Tsuntinskiy Rayon",
    "gn:asciiname":"Retlob",
    "gn:country_code":"RU",
    "gn:dem":1855,
    "gn:feature_class":"P",
    "gn:feature_code":"PPL",
    "gn:name":"Retlob",
    "gn:population":0,
    "gn:timezone":"Europe/Moscow",
    "iso:country":"RU",
    "name:rus_x_preferred":[
        "\u0420\u0435\u0442\u043b\u043e\u0431"
    ],
    "name:und_x_variant":[
        "\u0420\u0435\u0442\u043b\u043e\u0431"
    ],
    "wof:name":"Retlob",
    "wof:placetype":"locality"
},
  "geometry": {"coordinates":[45.8289,42.24411],"type":"Point"}
}