{
  "type": "Feature",
  "properties": {
    "gn:country":"RU",
    "gn:fcode":"PPL",
    "gn:pop":9834,
    "iso:country":"RU",
    "name:bel_x_preferred":[
        "\u041b\u0435\u043d\u0456\u043d\u0441\u043a\u0456"
    ],
    "name:cat_x_preferred":[
        "L\u00e9ninski"
    ],
    "name:deu_x_preferred":[
        "Leninski"
    ],
    "name:eng_x_preferred":[
        "Leninskiy"
    ],
    "name:ita_x_preferred":[
        "Leninskij"
    ],
    "name:nor_x_preferred":[
        "Leninskij"
    ],
    "name:rus_x_preferred":[
        "\u041b\u0435\u043d\u0438\u043d\u0441\u043a\u0438\u0439"
    ],
    "name:sco_x_preferred":[
        "Leninsky"
    ],
    "name:spa_x_preferred":[
        "L\u00e9ninski"
    ],
    "name:swe_x_preferred":[
        "Leninskij"
    ],
    "name:tat_x_preferred":[
        "\u041b\u0435\u043d\u0438\u043d\u0441\u043a\u0438\u0439"
    ],
    "name:ukr_x_preferred":[
        "\u041b\u0435\u043d\u0456\u043d\u0441\u044c\u043a\u0438\u0439"
    ],
    "qs:name":"Leninskiy",
    "qs:name_adm0":"Russia",
    "qs:name_adm1":"Tula Oblast",
    "qs:photos_9k":1,
    "qs:photos_9r":1,
    "qs:photos_all":6,
    "qs:photos_sr":0,
    "qs:placetype":"Town",
    "qs:pop_sr":"5",
    "wd:wordcount":126,
    "wof:name":"Leninskiy",
    "wof:placetype":"locality",
    "wof:population":9834
},
  "geometry": {"coordinates":[37.45926,54.28768],"type":"Point"}
}