{
  "type": "Feature",
  "properties": {
    "gn:admin1_code":"05",
    "gn:asciiname":"Chagoyan",
    "gn:country_code":"RU",
    "gn:dem":189,
    "gn:feature_class":"P",
    "gn:feature_code":"PPL",
    "gn:name":"Chagoyan",
    "gn:population":0,
    "gn:timezone":"Asia/Yakutsk",
    "iso:country":"RU",
    "name:che_x_preferred":[
        "\u0427\u0430\u0433\u043e\u044f\u043d"
    ],
    "name:eng_x_preferred":[
        "Chagoyan"
    ],
    "name:nor_x_preferred":[
        "Tsjagojan"
    ],
    "name:rus_x_preferred":[
        "\u0427\u0430\u0433\u043e\u044f\u043d"
    ],
    "name:tgk_x_preferred":[
        "\u0427\u0430\u0433\u043e\u044f\u043d"
    ],
    "wof:name":"Chagoyan",
    "wof:placetype":"locality"
},
  "geometry": {"coordinates":[128.23853,52.13362],"type":"Point"}
}