{
  "type": "Feature",
  "properties": {
    "gn:admin1_code":"61",
    "gn:asciiname":"Veseloye",
    "gn:country_code":"RU",
    "gn:dem":50,
    "gn:feature_class":"P",
    "gn:feature_code":"PPL",
    "gn:name":"Veseloye",
    "gn:population":0,
    "gn:timezone":"Europe/Moscow",
    "iso:country":"RU",
    "name:eng_x_preferred":[
        "Veseloye"
    ],
    "name:nor_x_preferred":[
        "Veseloje"
    ],
    "name:rus_x_preferred":[
        "\u0412\u0435\u0441\u0435\u043b\u043e\u0435"
    ],
    "name:rus_x_variant":[
        "\u0412\u0435\u0441\u0451\u043b\u043e\u0435"
    ],
    "wof:name":"Veseloye",
    "wof:placetype":"locality"
},
  "geometry": {"coordinates":[41.99618,46.25739],"type":"Point"}
}