{
  "type": "Feature",
  "properties": {
    "gn:admin1_code":"85",
    "gn:asciiname":"Gryada",
    "gn:country_code":"RU",
    "gn:dem":177,
    "gn:feature_class":"P",
    "gn:feature_code":"PPL",
    "gn:name":"Gryada",
    "gn:population":0,
    "gn:timezone":"Europe/Moscow",
    "iso:country":"RU",
    "name:che_x_preferred":[
        "\u0413\u0440\u044f\u0434\u0430"
    ],
    "name:rus_x_preferred":[
        "\u0413\u0440\u044f\u0434\u0430"
    ],
    "wof:name":"Gryada",
    "wof:placetype":"locality"
},
  "geometry": {"coordinates":[36.3346,58.659],"type":"Point"}
}