{
  "type": "Feature",
  "properties": {
    "gn:admin1_code":"62",
    "gn:asciiname":"Maloye Trepol'ye",
    "gn:country_code":"RU",
    "gn:dem":153,
    "gn:feature_class":"P",
    "gn:feature_code":"PPL",
    "gn:name":"Maloye Trepol\u2019ye",
    "gn:population":0,
    "gn:timezone":"Europe/Moscow",
    "iso:country":"RU",
    "name:rus_x_preferred":[
        "\u041c\u0430\u043b\u043e\u0435 \u0422\u0440\u0435\u043f\u043e\u043b\u044c\u0435"
    ],
    "name:und_x_variant":[
        "Maloye Trepol\u2019ye"
    ],
    "wof:name":"Maloye Trepol'ye",
    "wof:placetype":"locality"
},
  "geometry": {"coordinates":[38.85668,54.33152],"type":"Point"}
}