{
  "type": "Feature",
  "properties": {
    "gn:admin1_code":"56",
    "gn:asciiname":"Gretsevo",
    "gn:cc2":"RU",
    "gn:country_code":"RU",
    "gn:dem":190,
    "gn:feature_class":"P",
    "gn:feature_code":"PPL",
    "gn:name":"Grets\u00ebvo",
    "gn:population":0,
    "gn:timezone":"Europe/Moscow",
    "iso:country":"RU",
    "name:rus_x_preferred":[
        "\u0413\u0440\u0435\u0446\u0451\u0432\u043e"
    ],
    "name:und_x_variant":[
        "Grevtsevo",
        "Grets\u00ebvo",
        "\u0413\u0440\u0435\u0446\u0451\u0432\u043e"
    ],
    "wof:name":"Gretsevo",
    "wof:placetype":"locality"
},
  "geometry": {"coordinates":[37.08306,52.53444],"type":"Point"}
}