{
  "type": "Feature",
  "properties": {
    "gn:admin1_code":"90",
    "gn:asciiname":"Lenino",
    "gn:country_code":"RU",
    "gn:dem":143,
    "gn:feature_class":"P",
    "gn:feature_code":"PPL",
    "gn:name":"Lenino",
    "gn:population":0,
    "gn:timezone":"Asia/Yekaterinburg",
    "iso:country":"RU",
    "name:eng_x_preferred":[
        "Lenino"
    ],
    "name:nor_x_preferred":[
        "Lenino"
    ],
    "name:rus_x_preferred":[
        "\u041b\u0435\u043d\u0438\u043d\u043e"
    ],
    "name:und_x_variant":[
        "\u041b\u0435\u043d\u0438\u043d\u043e"
    ],
    "wof:name":"Lenino",
    "wof:placetype":"locality"
},
  "geometry": {"coordinates":[55.5565,58.1668],"type":"Point"}
}