{
  "type": "Feature",
  "properties": {
    "gn:admin1_code":"53",
    "gn:asciiname":"Khabarovskiy",
    "gn:country_code":"RU",
    "gn:dem":139,
    "gn:feature_class":"P",
    "gn:feature_code":"PPL",
    "gn:name":"Khabarovskiy",
    "gn:population":0,
    "gn:timezone":"Asia/Novosibirsk",
    "iso:country":"RU",
    "name:rus_x_preferred":[
        "\u0425\u0430\u0431\u0430\u0440\u043e\u0432\u0441\u043a\u0438\u0439"
    ],
    "name:und_x_variant":[
        "\u0425\u0430\u0431\u0430\u0440\u043e\u0432\u0441\u043a\u0438\u0439"
    ],
    "wof:name":"Khabarovskiy",
    "wof:placetype":"locality"
},
  "geometry": {"coordinates":[79.63333,55.41667],"type":"Point"}
}