{
  "type": "Feature",
  "properties": {
    "gn:admin1_code":"49",
    "gn:asciiname":"Ruch'i",
    "gn:country_code":"RU",
    "gn:dem":89,
    "gn:feature_class":"P",
    "gn:feature_code":"PPL",
    "gn:name":"Ruch\u2019i",
    "gn:population":0,
    "gn:timezone":"Europe/Moscow",
    "iso:country":"RU",
    "name:eng_x_preferred":[
        "Ruch'i"
    ],
    "name:fin_x_preferred":[
        "Rutsi"
    ],
    "name:nor_x_preferred":[
        "Rutsji"
    ],
    "name:rus_x_preferred":[
        "\u0420\u0443\u0447\u044c\u0438"
    ],
    "name:und_x_variant":[
        "\u0420\u0443\u0447\u044c\u0438",
        "Ruch\u2019i"
    ],
    "wof:name":"Ruch'i",
    "wof:placetype":"locality"
},
  "geometry": {"coordinates":[32.19167,67.00721999999999],"type":"Point"}
}