{
  "type": "Feature",
  "properties": {
    "gn:admin1_code":"17.0",
    "gn:asciiname":"Karaman Sed'moy",
    "gn:country_code":"RU",
    "gn:dem":-20,
    "gn:feature_class":"P",
    "gn:feature_code":"PPL",
    "gn:name":"Karaman Sed\u2019moy",
    "gn:population":0,
    "gn:timezone":"Europe/Moscow",
    "iso:country":"RU",
    "name:rus_x_preferred":[
        "\u041a\u0430\u0440\u0430\u043c\u0430\u043d \u0421\u0435\u0434\u044c\u043c\u043e\u0439"
    ],
    "name:und_x_variant":[
        "Karaman Sed\u2019moy",
        "\u041a\u0430\u0440\u0430\u043c\u0430\u043d \u0421\u0435\u0434\u044c\u043c\u043e\u0439"
    ],
    "wof:name":"Karaman Sed'moy",
    "wof:placetype":"locality"
},
  "geometry": {"coordinates":[47.46167,43.05389],"type":"Point"}
}