{
  "type": "Feature",
  "properties": {
    "iso:country":"RU",
    "name:rus_x_preferred":[
        "\u0421\u0435\u0441\u0442\u0440\u043e\u0440\u0435\u0446\u043a"
    ],
    "wof:name":"Sestroretsk",
    "wof:placetype":"neighbourhood"
},
  "geometry": {"coordinates":[29.95307276175521,60.09661258688669],"type":"Point"}
}