{
  "type": "Feature",
  "properties": {
    "iso:country":"RU",
    "name:ara_x_preferred":[
        "\u0633\u0633\u062a\u0631\u0648\u0631\u062a\u0633\u0643"
    ],
    "name:bar_x_preferred":[
        "Sestrorezk"
    ],
    "name:bel_x_preferred":[
        "\u0421\u0435\u0441\u0442\u0440\u0430\u0440\u044d\u0446\u043a"
    ],
    "name:bul_x_preferred":[
        "\u0421\u0435\u0441\u0442\u0440\u043e\u0440\u0435\u0446\u043a"
    ],
    "name:ceb_x_preferred":[
        "Sestroretsk"
    ],
    "name:dan_x_preferred":[
        "Systerb\u00e4ck"
    ],
    "name:deu_x_preferred":[
        "Sestrorezk"
    ],
    "name:epo_x_preferred":[
        "Sestroreck"
    ],
    "name:est_x_preferred":[
        "Sestroretsk"
    ],
    "name:fas_x_preferred":[
        "\u0633\u0633\u062a\u0631\u0648\u0631\u062a\u0633\u06a9"
    ],
    "name:fin_x_preferred":[
        "Siestarjoki"
    ],
    "name:fra_x_preferred":[
        "Sestroretsk"
    ],
    "name:glv_x_preferred":[
        "Sestroretsk"
    ],
    "name:hsb_x_preferred":[
        "Sestrorjeck"
    ],
    "name:kat_x_preferred":[
        "\u10e1\u10d4\u10e1\u10e2\u10e0\u10dd\u10e0\u10d4\u10ea\u10d9\u10d8"
    ],
    "name:kor_x_preferred":[
        "\uc138\uc2a4\ud2b8\ub85c\ub808\uce20\ud06c"
    ],
    "name:lav_x_preferred":[
        "Sestrorecka"
    ],
    "name:lit_x_preferred":[
        "Sestroreckas"
    ],
    "name:nno_x_preferred":[
        "Sestroretsk"
    ],
    "name:nor_x_preferred":[
        "Sestroretsk"
    ],
    "name:pol_x_preferred":[
        "Siestrorieck"
    ],
    "name:ron_x_preferred":[
        "Sestrore\u021bk"
    ],
    "name:rus_x_preferred":[
        "\u0421\u0435\u0441\u0442\u0440\u043e\u0440\u0435\u0446\u043a"
    ],
    "name:sco_x_preferred":[
        "Sestroretsk"
    ],
    "name:srp_x_preferred":[
        "\u0421\u0435\u0441\u0442\u0440\u043e\u0440\u0435\u0446\u043a"
    ],
    "name:swe_x_preferred":[
        "Systerb\u00e4ck"
    ],
    "name:tat_x_preferred":[
        "\u0421\u0435\u0441\u0442\u0440\u043e\u0440\u0435\u0446\u043a"
    ],
    "name:tgk_x_preferred":[
        "\u0421\u0435\u0441\u0442\u0440\u043e\u0440\u0435\u0442\u0441\u043a"
    ],
    "name:tgl_x_preferred":[
        "Sestroretsk"
    ],
    "name:tur_x_preferred":[
        "Sestroretsk"
    ],
    "name:ukr_x_preferred":[
        "\u0421\u0435\u0441\u0442\u0440\u043e\u0440\u0454\u0446\u044c\u043a"
    ],
    "name:vep_x_preferred":[
        "Sestroreck"
    ],
    "name:zho_x_preferred":[
        "\u8b1d\u65af\u5f97\u7f85\u5217\u8328\u514b"
    ],
    "wof:name":"Sestroretsk",
    "wof:placetype":"neighbourhood"
},
  "geometry": {"coordinates":[29.95307276175521,60.09661258688669],"type":"Point"}
}