{
  "type": "Feature",
  "properties": {
    "gn:admin1_code":"51",
    "gn:asciiname":"Kanava",
    "gn:country_code":"RU",
    "gn:dem":133,
    "gn:feature_class":"P",
    "gn:feature_code":"PPL",
    "gn:name":"Kanava",
    "gn:population":0,
    "gn:timezone":"Europe/Moscow",
    "iso:country":"RU",
    "name:rus_x_preferred":[
        "\u041a\u0430\u043d\u0430\u0432\u0430"
    ],
    "wof:name":"Kanava",
    "wof:placetype":"locality"
},
  "geometry": {"coordinates":[46.5858,57.7193],"type":"Point"}
}