{
  "type": "Feature",
  "properties": {
    "gn:admin1_code":"13",
    "gn:asciiname":"Malaya Kazakbayeva",
    "gn:country_code":"RU",
    "gn:dem":164,
    "gn:feature_class":"P",
    "gn:feature_code":"PPL",
    "gn:name":"Malaya Kazakbayeva",
    "gn:population":0,
    "gn:timezone":"Asia/Yekaterinburg",
    "iso:country":"RU",
    "name:rus_x_preferred":[
        "\u041c\u0430\u043b\u0430\u044f \u041a\u0430\u0437\u0430\u043a\u0431\u0430\u0435\u0432\u0430"
    ],
    "name:und_x_variant":[
        "Malaya Kazykbayeva",
        "Malaya Kazakbayeva"
    ],
    "wof:name":"Malaya Kazakbayeva",
    "wof:placetype":"locality"
},
  "geometry": {"coordinates":[61.5809,55.9043],"type":"Point"}
}