{
  "type": "Feature",
  "properties": {
    "gn:admin1_code":"42",
    "gn:asciiname":"Shcheleyki",
    "gn:cc2":"RU",
    "gn:country_code":"RU",
    "gn:dem":63,
    "gn:feature_class":"P",
    "gn:feature_code":"PPL",
    "gn:name":"Shcheleyki",
    "gn:population":0,
    "gn:timezone":"Europe/Moscow",
    "iso:country":"RU",
    "name:eng_x_preferred":[
        "Shcheleyki"
    ],
    "name:fin_x_preferred":[
        "Kallio"
    ],
    "name:nor_x_preferred":[
        "Sjtsjelejki"
    ],
    "name:rus_x_preferred":[
        "\u0429\u0435\u043b\u0435\u0439\u043a\u0438"
    ],
    "name:und_x_variant":[
        "Shcheleyka"
    ],
    "name:vep_x_preferred":[
        "Kal\u2019l\u2019o"
    ],
    "wof:name":"Shcheleyki",
    "wof:placetype":"locality"
},
  "geometry": {"coordinates":[35.64686,61.10908000000001],"type":"Point"}
}