{
  "type": "Feature",
  "properties": {
    "gn:admin1_code":"69",
    "gn:asciiname":"Istopki",
    "gn:country_code":"RU",
    "gn:dem":199,
    "gn:feature_class":"P",
    "gn:feature_code":"PPL",
    "gn:name":"Istopki",
    "gn:population":0,
    "gn:timezone":"Europe/Moscow",
    "iso:country":"RU",
    "name:rus_x_preferred":[
        "\u0418\u0441\u0442\u043e\u043f\u043a\u0438"
    ],
    "wof:name":"Istopki",
    "wof:placetype":"locality"
},
  "geometry": {"coordinates":[33.63054,54.53795],"type":"Point"}
}