{
  "type": "Feature",
  "properties": {
    "gn:admin1_code":"10.0",
    "gn:asciiname":"Dobrylevo",
    "gn:country_code":"RU",
    "gn:dem":133,
    "gn:feature_class":"P",
    "gn:feature_code":"PPL",
    "gn:name":"Dobrylevo",
    "gn:population":0,
    "gn:timezone":"Europe/Moscow",
    "iso:country":"RU",
    "name:rus_x_preferred":[
        "\u0414\u043e\u0431\u0440\u044b\u043b\u0435\u0432\u043e"
    ],
    "name:und_x_variant":[
        "\u0414\u043e\u0431\u0440\u044b\u043b\u0435\u0432\u043e"
    ],
    "wof:name":"Dobrylevo",
    "wof:placetype":"locality"
},
  "geometry": {"coordinates":[33.51667,52.35],"type":"Point"}
}