{
  "type": "Feature",
  "properties": {
    "gn:admin1_code":"11",
    "gn:asciiname":"Ulan-Makit",
    "gn:country_code":"RU",
    "gn:dem":532,
    "gn:feature_class":"P",
    "gn:feature_code":"PPL",
    "gn:name":"Ulan-Makit",
    "gn:population":0,
    "gn:timezone":"Asia/Irkutsk",
    "iso:country":"RU",
    "name:eng_x_preferred":[
        "Ulan-Makit"
    ],
    "name:nor_x_preferred":[
        "Ulan-Makit"
    ],
    "name:rus_x_preferred":[
        "\u0423\u043b\u0430\u043d-\u041c\u0430\u043a\u0438\u0442"
    ],
    "wof:name":"Ulan-Makit",
    "wof:placetype":"locality"
},
  "geometry": {"coordinates":[114.63333,56.31667],"type":"Point"}
}