{
  "type": "Feature",
  "properties": {
    "gn:admin1_code":"16.0",
    "gn:asciiname":"Bezbozhnik",
    "gn:country_code":"RU",
    "gn:dem":86,
    "gn:feature_class":"P",
    "gn:feature_code":"PPL",
    "gn:name":"Bezbozhnik",
    "gn:population":0,
    "gn:timezone":"Europe/Moscow",
    "iso:country":"RU",
    "name:nor_x_preferred":[
        "Bezbozjnik"
    ],
    "name:rus_x_preferred":[
        "\u0411\u0435\u0437\u0431\u043e\u0436\u043d\u0438\u043a"
    ],
    "wof:name":"Bezbozhnik",
    "wof:placetype":"locality"
},
  "geometry": {"coordinates":[46.72572,54.74977],"type":"Point"}
}