{
  "type": "Feature",
  "properties": {
    "gn:admin1_code":"43",
    "gn:asciiname":"Prirech'ye",
    "gn:country_code":"RU",
    "gn:dem":122,
    "gn:feature_class":"P",
    "gn:feature_code":"PPL",
    "gn:name":"Prirech\u2019ye",
    "gn:population":0,
    "gn:timezone":"Europe/Moscow",
    "iso:country":"RU",
    "name:rus_x_preferred":[
        "\u041f\u0440\u0438\u0440\u0435\u0447\u044c\u0435"
    ],
    "name:und_x_variant":[
        "Prirech\u2019ye",
        "\u041f\u0440\u0438\u0440\u0435\u0447\u044c\u0435"
    ],
    "wof:name":"Prirech'ye",
    "wof:placetype":"locality"
},
  "geometry": {"coordinates":[38.3658,52.4991],"type":"Point"}
}