{
  "type": "Feature",
  "properties": {
    "gn:admin1_code":"47",
    "gn:asciiname":"Kharlanikha",
    "gn:country_code":"RU",
    "gn:dem":190,
    "gn:feature_class":"P",
    "gn:feature_code":"PPL",
    "gn:name":"Kharlanikha",
    "gn:population":0,
    "gn:timezone":"Europe/Moscow",
    "iso:country":"RU",
    "name:rus_x_preferred":[
        "\u0425\u0430\u0440\u043b\u0430\u043d\u0438\u0445\u0430"
    ],
    "wof:name":"Kharlanikha",
    "wof:placetype":"locality"
},
  "geometry": {"coordinates":[38.36667,56.21666999999999],"type":"Point"}
}