{
  "type": "Feature",
  "properties": {
    "gn:admin1_code":"37",
    "gn:asciiname":"Iraklikha",
    "gn:country_code":"RU",
    "gn:dem":192,
    "gn:feature_class":"P",
    "gn:feature_code":"PPL",
    "gn:name":"Iraklikha",
    "gn:population":0,
    "gn:timezone":"Europe/Moscow",
    "iso:country":"RU",
    "name:eng_x_preferred":[
        "Iraklikha"
    ],
    "name:nor_x_preferred":[
        "Iraklikha"
    ],
    "name:rus_x_preferred":[
        "\u0418\u0440\u0430\u043a\u043b\u0438\u0445\u0430"
    ],
    "name:und_x_variant":[
        "\u0418\u0440\u0430\u043a\u043b\u0438\u0445\u0430",
        "Iraklikha"
    ],
    "wof:name":"Iraklikha",
    "wof:placetype":"locality"
},
  "geometry": {"coordinates":[45.7077,58.95721999999999],"type":"Point"}
}