{
  "type": "Feature",
  "properties": {
    "gn:admin1_code":"51",
    "gn:asciiname":"Kobylkino",
    "gn:country_code":"RU",
    "gn:dem":163,
    "gn:feature_class":"P",
    "gn:feature_code":"PPL",
    "gn:name":"Kobylkino",
    "gn:population":0,
    "gn:timezone":"Europe/Moscow",
    "iso:country":"RU",
    "name:rus_x_preferred":[
        "\u041a\u043e\u0431\u044b\u043b\u043a\u0438\u043d\u043e"
    ],
    "wof:name":"Kobylkino",
    "wof:placetype":"locality"
},
  "geometry": {"coordinates":[42.7895,55.9216],"type":"Point"}
}