{
  "type": "Feature",
  "properties": {
    "gn:admin1_code":"80.0",
    "gn:asciiname":"Artimony",
    "gn:country_code":"RU",
    "gn:dem":147,
    "gn:feature_class":"P",
    "gn:feature_code":"PPL",
    "gn:name":"Artimony",
    "gn:population":0,
    "gn:timezone":"Europe/Samara",
    "iso:country":"RU",
    "name:nor_x_preferred":[
        "Artimony"
    ],
    "name:rus_x_preferred":[
        "\u0410\u0440\u0442\u0438\u043c\u043e\u043d\u044b"
    ],
    "wof:name":"Artimony",
    "wof:placetype":"locality"
},
  "geometry": {"coordinates":[53.81667,57.08333],"type":"Point"}
}