{
  "type": "Feature",
  "properties": {
    "gn:admin1_code":"76",
    "gn:asciiname":"Chernyy",
    "gn:country_code":"RU",
    "gn:dem":224,
    "gn:feature_class":"P",
    "gn:feature_code":"PPL",
    "gn:name":"Chernyy",
    "gn:population":0,
    "gn:timezone":"Europe/Moscow",
    "iso:country":"RU",
    "name:rus_x_preferred":[
        "\u0427\u0435\u0440\u043d\u044b\u0439"
    ],
    "name:und_x_variant":[
        "\u0427\u0435\u0440\u043d\u044b\u0439"
    ],
    "wof:name":"Chernyy",
    "wof:placetype":"locality"
},
  "geometry": {"coordinates":[36.81472,54.05944],"type":"Point"}
}