{
  "type": "Feature",
  "properties": {
    "gn:admin1_code":"10",
    "gn:asciiname":"Natal'in",
    "gn:country_code":"RU",
    "gn:dem":170,
    "gn:feature_class":"P",
    "gn:feature_code":"PPL",
    "gn:name":"Natal\u2019in",
    "gn:population":0,
    "gn:timezone":"Europe/Moscow",
    "iso:country":"RU",
    "name:rus_x_preferred":[
        "\u041d\u0430\u0442\u0430\u043b\u044c\u0438\u043d"
    ],
    "name:rus_x_variant":[
        "Natal\u2019in",
        "Natal\u2019in-Khutor"
    ],
    "wof:name":"Natal'in",
    "wof:placetype":"locality"
},
  "geometry": {"coordinates":[33.0136,52.5168],"type":"Point"}
}