{
  "type": "Feature",
  "properties": {
    "gn:admin1_code":"85",
    "gn:asciiname":"Yangosar'",
    "gn:country_code":"RU",
    "gn:dem":189,
    "gn:feature_class":"P",
    "gn:feature_code":"PPL",
    "gn:name":"Yangosar\u2019",
    "gn:population":0,
    "gn:timezone":"Europe/Moscow",
    "iso:country":"RU",
    "name:eng_x_preferred":[
        "Yangosor'"
    ],
    "name:nor_x_preferred":[
        "Jangosar"
    ],
    "name:rus_x_preferred":[
        "\u042f\u043d\u0433\u043e\u0441\u0430\u0440\u044c"
    ],
    "name:und_x_variant":[
        "\u042f\u043d\u0433\u043e\u0441\u0430\u0440\u044c",
        "Yangosar\u2019",
        "Yangosor\u2019"
    ],
    "wof:name":"Yangosar'",
    "wof:placetype":"locality"
},
  "geometry": {"coordinates":[39.36657,59.04686],"type":"Point"}
}