{
  "type": "Feature",
  "properties": {
    "gn:admin1_code":"33",
    "gn:asciiname":"Shvechata",
    "gn:country_code":"RU",
    "gn:dem":172,
    "gn:feature_class":"P",
    "gn:feature_code":"PPL",
    "gn:name":"Shvechata",
    "gn:population":0,
    "gn:timezone":"Europe/Kirov",
    "iso:country":"RU",
    "name:eng_x_preferred":[
        "Shvechata"
    ],
    "name:nor_x_preferred":[
        "Sjvetsjata"
    ],
    "name:rus_x_preferred":[
        "\u0428\u0432\u0435\u0447\u0430\u0442\u0430"
    ],
    "wof:name":"Shvechata",
    "wof:placetype":"locality"
},
  "geometry": {"coordinates":[47.8485,59.05928],"type":"Point"}
}