{
  "type": "Feature",
  "properties": {
    "gn:admin1_code":"65",
    "gn:asciiname":"Semenovka",
    "gn:country_code":"RU",
    "gn:dem":74,
    "gn:feature_class":"P",
    "gn:feature_code":"PPL",
    "gn:name":"Sem\u00ebnovka",
    "gn:population":0,
    "gn:timezone":"Europe/Samara",
    "iso:country":"RU",
    "name:eng_x_preferred":[
        "Sem\u00ebnovka"
    ],
    "name:nor_x_preferred":[
        "Semenovka"
    ],
    "name:rus_x_preferred":[
        "\u0421\u0435\u043c\u0435\u043d\u043e\u0432\u043a\u0430"
    ],
    "name:rus_x_variant":[
        "\u0421\u0435\u043c\u0451\u043d\u043e\u0432\u043a\u0430"
    ],
    "wof:name":"Semenovka",
    "wof:placetype":"locality"
},
  "geometry": {"coordinates":[51.34251,53.54298000000001],"type":"Point"}
}