{
  "type": "Feature",
  "properties": {
    "gn:admin1_code":"88.0",
    "gn:asciiname":"Nastas'ino",
    "gn:country_code":"RU",
    "gn:dem":117,
    "gn:feature_class":"P",
    "gn:feature_code":"PPL",
    "gn:name":"Nastas\u2019ino",
    "gn:population":0,
    "gn:timezone":"Europe/Moscow",
    "iso:country":"RU",
    "name:rus_x_preferred":[
        "\u041d\u0430\u0441\u0442\u0430\u0441\u044c\u0438\u043d\u043e"
    ],
    "name:und_x_variant":[
        "Nastas\u2019ino"
    ],
    "wof:name":"Nastas'ino",
    "wof:placetype":"locality"
},
  "geometry": {"coordinates":[40.93986,58.31535],"type":"Point"}
}