{
  "type": "Feature",
  "properties": {
    "gn:admin1_code":"77.0",
    "gn:asciiname":"Biryuchevo",
    "gn:cc2":"RU",
    "gn:country_code":"RU",
    "gn:dem":219,
    "gn:feature_class":"P",
    "gn:feature_code":"PPL",
    "gn:name":"Biryuch\u00ebvo",
    "gn:population":0,
    "gn:timezone":"Europe/Moscow",
    "iso:country":"RU",
    "name:eng_x_preferred":[
        "Biryuch\u00ebvo"
    ],
    "name:nor_x_preferred":[
        "Birjutsjevo"
    ],
    "name:rus_x_preferred":[
        "\u0411\u0438\u0440\u044e\u0447\u0435\u0432\u043e"
    ],
    "name:rus_x_variant":[
        "\u0411\u0438\u0440\u044e\u0447\u0451\u0432\u043e"
    ],
    "name:und_x_variant":[
        "Biryucheva"
    ],
    "wof:name":"Biryuchevo",
    "wof:placetype":"locality"
},
  "geometry": {"coordinates":[35.29111,57.37222],"type":"Point"}
}