{
  "type": "Feature",
  "properties": {
    "gn:admin1_code":"73.0",
    "gn:asciiname":"Bolkhovka",
    "gn:cc2":"RU",
    "gn:country_code":"RU",
    "gn:dem":108,
    "gn:feature_class":"P",
    "gn:feature_code":"PPL",
    "gn:name":"Bolkhovka",
    "gn:population":0,
    "gn:timezone":"Europe/Moscow",
    "iso:country":"RU",
    "name:rus_x_preferred":[
        "\u0411\u043e\u043b\u0445\u043e\u0432\u043a\u0430"
    ],
    "name:und_x_variant":[
        "Gorki",
        "Bolkhovka",
        "\u0411\u043e\u043b\u0445\u043e\u0432\u043a\u0430"
    ],
    "wof:name":"Bolkhovka",
    "wof:placetype":"locality"
},
  "geometry": {"coordinates":[49.58333,54.95],"type":"Point"}
}