{
  "type": "Feature",
  "properties": {
    "gn:admin1_code":"53",
    "gn:asciiname":"Sukhaya Kamenka",
    "gn:country_code":"RU",
    "gn:dem":222,
    "gn:feature_class":"P",
    "gn:feature_code":"PPL",
    "gn:name":"Sukhaya Kamenka",
    "gn:population":0,
    "gn:timezone":"Asia/Novosibirsk",
    "iso:country":"RU",
    "name:rus_x_preferred":[
        "\u0421\u0443\u0445\u0430\u044f \u041a\u0430\u043c\u0435\u043d\u043a\u0430"
    ],
    "name:und_x_variant":[
        "\u0421\u0443\u0445\u0430\u044f \u041a\u0430\u043c\u0435\u043d\u043a\u0430"
    ],
    "wof:name":"Sukhaya Kamenka",
    "wof:placetype":"locality"
},
  "geometry": {"coordinates":[83.95,54.46666999999999],"type":"Point"}
}