{
  "type": "Feature",
  "properties": {
    "gn:admin1_code":"37.0",
    "gn:asciiname":"Samkovo",
    "gn:country_code":"RU",
    "gn:dem":110,
    "gn:feature_class":"P",
    "gn:feature_code":"PPL",
    "gn:name":"Samkovo",
    "gn:population":0,
    "gn:timezone":"Europe/Moscow",
    "iso:country":"RU",
    "name:che_x_preferred":[
        "\u0421\u0430\u043c\u043a\u043e\u0432\u043e"
    ],
    "name:koi_x_preferred":[
        "\u0421\u0430\u043c\u043a\u043e\u0432"
    ],
    "name:rus_x_preferred":[
        "\u0421\u0430\u043c\u043a\u043e\u0432\u043e"
    ],
    "wof:name":"Samkovo",
    "wof:placetype":"locality"
},
  "geometry": {"coordinates":[40.84609,57.73346],"type":"Point"}
}