{
  "type": "Feature",
  "properties": {
    "gn:admin1_code":"53",
    "gn:asciiname":"Koykrylgan",
    "gn:country_code":"RU",
    "gn:dem":115,
    "gn:feature_class":"P",
    "gn:feature_code":"PPL",
    "gn:name":"Koykrylgan",
    "gn:population":0,
    "gn:timezone":"Asia/Novosibirsk",
    "iso:country":"RU",
    "name:rus_x_preferred":[
        "\u041a\u043e\u0439\u043a\u0440\u044b\u043b\u0433\u0430\u043d"
    ],
    "wof:name":"Koykrylgan",
    "wof:placetype":"locality"
},
  "geometry": {"coordinates":[78.25,53.63333000000001],"type":"Point"}
}