{
  "type": "Feature",
  "properties": {
    "gn:country":"RU",
    "gn:fcode":"PPL",
    "gn:pop":796,
    "iso:country":"RU",
    "name:eng_x_preferred":[
        "Medvedka"
    ],
    "name:nor_x_preferred":[
        "Medvedka"
    ],
    "name:rus_x_preferred":[
        "\u041c\u0435\u0434\u0432\u0435\u0434\u043a\u0430"
    ],
    "name:unk_x_variant":[
        "\u041c\u0435\u0434\u0432\u0435\u0434\u043a\u0430"
    ],
    "qs:name":"Medvedka",
    "qs:photos_9r":0,
    "qs:photos_sr":0,
    "qs:pop_sr":"2",
    "wof:name":"Medvedka",
    "wof:placetype":"locality",
    "wof:population":796
},
  "geometry": {"coordinates":[59.1036,58.7406],"type":"Point"}
}