{
  "type": "Feature",
  "properties": {
    "gn:admin1_code":"42",
    "gn:asciiname":"Ronkovitsy",
    "gn:country_code":"RU",
    "gn:dem":157,
    "gn:feature_class":"P",
    "gn:feature_code":"PPL",
    "gn:name":"Ronkovitsy",
    "gn:population":0,
    "gn:timezone":"Europe/Moscow",
    "iso:country":"RU",
    "name:fin_x_preferred":[
        "Ronkovitsa"
    ],
    "name:nor_x_preferred":[
        "Ronkovitsy"
    ],
    "name:rus_x_preferred":[
        "\u0420\u043e\u043d\u043a\u043e\u0432\u0438\u0446\u044b"
    ],
    "wof:name":"Ronkovitsy",
    "wof:placetype":"locality"
},
  "geometry": {"coordinates":[29.42935,59.53256],"type":"Point"}
}