{
  "type": "Feature",
  "properties": {
    "gn:admin1_code":"71",
    "gn:asciiname":"Medvezhka",
    "gn:country_code":"RU",
    "gn:dem":246,
    "gn:feature_class":"P",
    "gn:feature_code":"PPL",
    "gn:name":"Medvezhka",
    "gn:population":0,
    "gn:timezone":"Asia/Yekaterinburg",
    "iso:country":"RU",
    "name:rus_x_preferred":[
        "\u041c\u0435\u0434\u0432\u0435\u0436\u043a\u0430"
    ],
    "wof:name":"Medvezhka",
    "wof:placetype":"locality"
},
  "geometry": {"coordinates":[61.01667,57.41667],"type":"Point"}
}