{
  "type": "Feature",
  "properties": {
    "gn:admin1_code":"85",
    "gn:asciiname":"Roksa",
    "gn:country_code":"RU",
    "gn:dem":85,
    "gn:feature_class":"P",
    "gn:feature_code":"PPL",
    "gn:name":"Roksa",
    "gn:population":0,
    "gn:timezone":"Europe/Moscow",
    "iso:country":"RU",
    "name:rus_x_preferred":[
        "\u0420\u043e\u043a\u0441\u0430"
    ],
    "name:und_x_variant":[
        "\u0420\u043e\u043a\u0441\u0430"
    ],
    "wof:name":"Roksa",
    "wof:placetype":"locality"
},
  "geometry": {"coordinates":[35.53333,60.78333000000001],"type":"Point"}
}