{
  "type": "Feature",
  "properties": {
    "gn:admin1_code":"77",
    "gn:asciiname":"Nikitino",
    "gn:country_code":"RU",
    "gn:dem":264,
    "gn:feature_class":"P",
    "gn:feature_code":"PPL",
    "gn:name":"Nikitino",
    "gn:population":0,
    "gn:timezone":"Europe/Moscow",
    "iso:country":"RU",
    "name:rus_x_preferred":[
        "\u041d\u0438\u043a\u0438\u0442\u0438\u043d\u043e"
    ],
    "name:und_x_variant":[
        "Nikitinskiye",
        "Nikitskiye",
        "Nikitino",
        "\u041d\u0438\u043a\u0438\u0442\u0438\u043d\u043e"
    ],
    "wof:name":"Nikitino",
    "wof:placetype":"locality"
},
  "geometry": {"coordinates":[33.20066,56.32796],"type":"Point"}
}