{
  "type": "Feature",
  "properties": {
    "gn:admin1_code":"13.0",
    "gn:asciiname":"Verkhnyaya Luka",
    "gn:country_code":"RU",
    "gn:dem":294,
    "gn:feature_class":"P",
    "gn:feature_code":"PPL",
    "gn:name":"Verkhnyaya Luka",
    "gn:population":0,
    "gn:timezone":"Asia/Yekaterinburg",
    "iso:country":"RU",
    "name:rus_x_preferred":[
        "\u0412\u0435\u0440\u0445\u043d\u044f\u044f \u041b\u0443\u043a\u0430"
    ],
    "name:und_x_variant":[
        "Bol\u2019shaya Luka",
        "Verkhnyaya Luka"
    ],
    "wof:name":"Verkhnyaya Luka",
    "wof:placetype":"locality"
},
  "geometry": {"coordinates":[58.1514,55.1163],"type":"Point"}
}