{
  "type": "Feature",
  "properties": {
    "gn:admin1_code":"6.0",
    "gn:asciiname":"Sarchema",
    "gn:country_code":"RU",
    "gn:dem":133,
    "gn:feature_class":"P",
    "gn:feature_code":"PPL",
    "gn:name":"Sarchema",
    "gn:population":0,
    "gn:timezone":"Europe/Moscow",
    "iso:country":"RU",
    "name:rus_x_preferred":[
        "\u0421\u0430\u0440\u0447\u0435\u043c\u0430"
    ],
    "wof:name":"Sarchema",
    "wof:placetype":"locality"
},
  "geometry": {"coordinates":[46.2422,62.6718],"type":"Point"}
}