{
  "type": "Feature",
  "properties": {
    "gn:admin1_code":"33",
    "gn:asciiname":"Voron'ye",
    "gn:country_code":"RU",
    "gn:dem":218,
    "gn:feature_class":"P",
    "gn:feature_code":"PPL",
    "gn:name":"Voron\u2019y\u00eb",
    "gn:population":0,
    "gn:timezone":"Europe/Kirov",
    "iso:country":"RU",
    "name:eng_x_preferred":[
        "Voron'y\u00eb"
    ],
    "name:nor_x_preferred":[
        "Voronje"
    ],
    "name:rus_x_preferred":[
        "\u0412\u043e\u0440\u043e\u043d\u044c\u0435"
    ],
    "name:rus_x_variant":[
        "\u0412\u043e\u0440\u043e\u043d\u044c\u0451"
    ],
    "name:und_x_variant":[
        "Kopyly",
        "Voron\u2019y\u00eb"
    ],
    "wof:name":"Voron'ye",
    "wof:placetype":"locality"
},
  "geometry": {"coordinates":[49.48405,57.93677],"type":"Point"}
}