{
  "type": "Feature",
  "properties": {
    "gn:admin1_code":"86",
    "gn:asciiname":"Otrada",
    "gn:country_code":"RU",
    "gn:dem":168,
    "gn:feature_class":"P",
    "gn:feature_code":"PPL",
    "gn:name":"Otrada",
    "gn:population":0,
    "gn:timezone":"Europe/Moscow",
    "iso:country":"RU",
    "name:rus_x_preferred":[
        "\u041e\u0442\u0440\u0430\u0434\u0430"
    ],
    "name:und_x_variant":[
        "\u041e\u0442\u0440\u0430\u0434\u0430"
    ],
    "wof:name":"Otrada",
    "wof:placetype":"locality"
},
  "geometry": {"coordinates":[40.1895,51.6667],"type":"Point"}
}