{
  "type": "Feature",
  "properties": {
    "gn:admin1_code":"54",
    "gn:asciiname":"Kopeykino",
    "gn:country_code":"RU",
    "gn:dem":67,
    "gn:feature_class":"P",
    "gn:feature_code":"PPL",
    "gn:name":"Kopeykino",
    "gn:population":0,
    "gn:timezone":"Asia/Omsk",
    "iso:country":"RU",
    "name:eng_x_preferred":[
        "Kopeykina"
    ],
    "name:nor_x_preferred":[
        "Kopejkino"
    ],
    "name:rus_x_preferred":[
        "\u041a\u043e\u043f\u0435\u0439\u043a\u0438\u043d\u043e"
    ],
    "name:und_x_variant":[
        "Kopeykina",
        "\u041a\u043e\u043f\u0435\u0439\u043a\u0438\u043d\u043e"
    ],
    "wof:name":"Kopeykino",
    "wof:placetype":"locality"
},
  "geometry": {"coordinates":[74.12033000000002,56.98298000000001],"type":"Point"}
}