{
  "type": "Feature",
  "properties": {
    "gn:admin1_code":"33",
    "gn:asciiname":"Krutogory",
    "gn:country_code":"RU",
    "gn:dem":147,
    "gn:feature_class":"P",
    "gn:feature_code":"PPL",
    "gn:name":"Krutogory",
    "gn:population":0,
    "gn:timezone":"Europe/Moscow",
    "iso:country":"RU",
    "name:rus_x_preferred":[
        "\u041a\u0440\u0443\u0442\u043e\u0433\u043e\u0440\u044b"
    ],
    "wof:name":"Krutogory",
    "wof:placetype":"locality"
},
  "geometry": {"coordinates":[49.43333,57.05],"type":"Point"}
}