{
  "type": "Feature",
  "properties": {
    "gn:admin1_code":"71",
    "gn:asciiname":"Davydovo",
    "gn:country_code":"RU",
    "gn:dem":65,
    "gn:feature_class":"P",
    "gn:feature_code":"PPL",
    "gn:name":"Davydovo",
    "gn:population":0,
    "gn:timezone":"Asia/Yekaterinburg",
    "iso:country":"RU",
    "name:eng_x_preferred":[
        "Davydovo"
    ],
    "name:nor_x_preferred":[
        "Davydovo"
    ],
    "name:rus_x_preferred":[
        "\u0414\u0430\u0432\u044b\u0434\u043e\u0432\u043e"
    ],
    "name:und_x_variant":[
        "Davydova"
    ],
    "wof:name":"Davydovo",
    "wof:placetype":"locality"
},
  "geometry": {"coordinates":[63.35457,58.14544],"type":"Point"}
}