{
  "type": "Feature",
  "properties": {
    "gn:admin1_code":"53",
    "gn:asciiname":"Karmakla",
    "gn:country_code":"RU",
    "gn:dem":114,
    "gn:feature_class":"P",
    "gn:feature_code":"PPL",
    "gn:name":"Karmakla",
    "gn:population":0,
    "gn:timezone":"Asia/Novosibirsk",
    "iso:country":"RU",
    "name:eng_x_preferred":[
        "Karmakla"
    ],
    "name:nor_x_preferred":[
        "Karmakla"
    ],
    "name:rus_x_preferred":[
        "\u041a\u0430\u0440\u043c\u0430\u043a\u043b\u0430"
    ],
    "name:und_x_variant":[
        "Karmaklinskaya",
        "\u041a\u0430\u0440\u043c\u0430\u043a\u043b\u0430",
        "Karmakla"
    ],
    "wof:name":"Karmakla",
    "wof:placetype":"locality"
},
  "geometry": {"coordinates":[78.40993,54.96395],"type":"Point"}
}