{
  "type": "Feature",
  "properties": {
    "gn:admin1_code":"9",
    "gn:asciiname":"Lazurnoye",
    "gn:country_code":"RU",
    "gn:dem":203,
    "gn:feature_class":"P",
    "gn:feature_code":"PPL",
    "gn:name":"Lazurnoye",
    "gn:population":0,
    "gn:timezone":"Europe/Moscow",
    "iso:country":"RU",
    "name:rus_x_preferred":[
        "\u041b\u0430\u0437\u0443\u0440\u043d\u043e\u0435"
    ],
    "wof:name":"Lazurnoye",
    "wof:placetype":"locality"
},
  "geometry": {"coordinates":[38.0698,50.4925],"type":"Point"}
}