{
  "type": "Feature",
  "properties": {
    "gn:admin1_code":"28",
    "gn:asciiname":"Tambitsy Rechka",
    "gn:cc2":"RU",
    "gn:country_code":"RU",
    "gn:dem":31,
    "gn:feature_class":"P",
    "gn:feature_code":"PPL",
    "gn:name":"Tambitsy Rechka",
    "gn:population":0,
    "gn:timezone":"Europe/Moscow",
    "iso:country":"RU",
    "name:und_x_variant":[
        "Rechka",
        "Tambitsajoki",
        "Tambitsy Rechka"
    ],
    "wof:name":"Tambitsy Rechka",
    "wof:placetype":"locality"
},
  "geometry": {"coordinates":[35.55,62.23333],"type":"Point"}
}