{
  "type": "Feature",
  "properties": {
    "gn:admin1_code":"75",
    "gn:asciiname":"Maksimkin Yar",
    "gn:cc2":"RU",
    "gn:country_code":"RU",
    "gn:dem":97,
    "gn:feature_class":"P",
    "gn:feature_code":"PPL",
    "gn:name":"Maksimkin Yar",
    "gn:population":0,
    "gn:timezone":"Asia/Tomsk",
    "iso:country":"RU",
    "name:eng_x_preferred":[
        "Maksimkin Yar"
    ],
    "name:nor_x_preferred":[
        "Maksimkin Jar"
    ],
    "name:rus_x_preferred":[
        "\u041c\u0430\u043a\u0441\u0438\u043c\u043a\u0438\u043d \u042f\u0440"
    ],
    "name:und_x_variant":[
        "Maksimoyarovskoye",
        "Makimoyarovskoe",
        "Maksimoyarskoye"
    ],
    "wof:name":"Maksimkin Yar",
    "wof:placetype":"locality"
},
  "geometry": {"coordinates":[86.80694,58.67139],"type":"Point"}
}