{
  "type": "Feature",
  "properties": {
    "gn:admin1_code":"37",
    "gn:asciiname":"Mityurevo",
    "gn:country_code":"RU",
    "gn:dem":180,
    "gn:feature_class":"P",
    "gn:feature_code":"PPL",
    "gn:name":"Mityurevo",
    "gn:population":0,
    "gn:timezone":"Europe/Moscow",
    "iso:country":"RU",
    "name:rus_x_preferred":[
        "\u041c\u0438\u0442\u044e\u0440\u0435\u0432\u043e"
    ],
    "name:und_x_variant":[
        "\u041c\u0438\u0442\u044e\u0440\u0435\u0432\u043e"
    ],
    "wof:name":"Mityurevo",
    "wof:placetype":"locality"
},
  "geometry": {"coordinates":[42.3977,58.3485],"type":"Point"}
}