{
  "type": "Feature",
  "properties": {
    "gn:admin1_code":"47.0",
    "gn:asciiname":"Blokhino",
    "gn:country_code":"RU",
    "gn:dem":141,
    "gn:feature_class":"P",
    "gn:feature_code":"PPL",
    "gn:name":"Blokhino",
    "gn:population":0,
    "gn:timezone":"Europe/Moscow",
    "iso:country":"RU",
    "name:bak_x_preferred":[
        "\u0411\u043b\u043e\u0445\u0438\u043d"
    ],
    "name:che_x_preferred":[
        "\u0411\u043b\u043e\u0445\u0438\u043d\u043e"
    ],
    "name:hye_x_preferred":[
        "\u0532\u056c\u0578\u056d\u056b\u0576\u0578"
    ],
    "name:kaz_x_preferred":[
        "\u0411\u043b\u043e\u0445\u0438\u043d\u043e"
    ],
    "name:kir_x_preferred":[
        "\u0411\u043b\u043e\u0445\u0438\u043d\u043e"
    ],
    "name:rus_x_preferred":[
        "\u0411\u043b\u043e\u0445\u0438\u043d\u043e"
    ],
    "name:tat_x_preferred":[
        "\u0411\u043b\u043e\u0445\u0438\u043d\u043e"
    ],
    "name:ukr_x_preferred":[
        "\u0411\u043b\u043e\u0445\u0456\u043d\u043e"
    ],
    "wof:name":"Blokhino",
    "wof:placetype":"locality"
},
  "geometry": {"coordinates":[39.03333,55.18333000000001],"type":"Point"}
}