{
  "type": "Feature",
  "properties": {
    "gn:admin1_code":"55",
    "gn:asciiname":"Troitskoye",
    "gn:country_code":"RU",
    "gn:dem":115,
    "gn:feature_class":"P",
    "gn:feature_code":"PPL",
    "gn:name":"Troitskoye",
    "gn:population":0,
    "gn:timezone":"Asia/Yekaterinburg",
    "iso:country":"RU",
    "name:rus_x_preferred":[
        "\u0422\u0440\u043e\u0438\u0446\u043a\u043e\u0435"
    ],
    "name:und_x_variant":[
        "\u0422\u0440\u043e\u0438\u0446\u043a\u043e\u0435"
    ],
    "wof:name":"Troitskoye",
    "wof:placetype":"locality"
},
  "geometry": {"coordinates":[52.81087,53.36082],"type":"Point"}
}