{
  "type": "Feature",
  "properties": {
    "gn:admin1_code":"61",
    "gn:asciiname":"Pishvanov",
    "gn:country_code":"RU",
    "gn:dem":96,
    "gn:feature_class":"P",
    "gn:feature_code":"PPL",
    "gn:name":"Pishvanov",
    "gn:population":0,
    "gn:timezone":"Europe/Moscow",
    "iso:country":"RU",
    "name:eng_x_preferred":[
        "Pishvanov"
    ],
    "name:nor_x_preferred":[
        "Pisjvanov"
    ],
    "name:rus_x_preferred":[
        "\u041f\u0438\u0448\u0432\u0430\u043d\u043e\u0432"
    ],
    "name:und_x_variant":[
        "\u041f\u0438\u0448\u0432\u0430\u043d\u043e\u0432",
        "Pishvanov"
    ],
    "wof:name":"Pishvanov",
    "wof:placetype":"locality"
},
  "geometry": {"coordinates":[40.60631,46.78995],"type":"Point"}
}