{
  "type": "Feature",
  "properties": {
    "gn:admin1_code":"42",
    "gn:asciiname":"Pereyarovo",
    "gn:country_code":"RU",
    "gn:dem":132,
    "gn:feature_class":"P",
    "gn:feature_code":"PPL",
    "gn:name":"Pereyarovo",
    "gn:population":0,
    "gn:timezone":"Europe/Moscow",
    "iso:country":"RU",
    "name:fin_x_preferred":[
        "Per\u00e4j\u00e4rvi"
    ],
    "name:nor_x_preferred":[
        "Perejarovo"
    ],
    "name:rus_x_preferred":[
        "\u041f\u0435\u0440\u0435\u044f\u0440\u043e\u0432\u043e"
    ],
    "wof:name":"Pereyarovo",
    "wof:placetype":"locality"
},
  "geometry": {"coordinates":[29.77025,59.63418000000001],"type":"Point"}
}