{
  "type": "Feature",
  "properties": {
    "gn:admin1_code":"85",
    "gn:asciiname":"Lezha",
    "gn:country_code":"RU",
    "gn:dem":129,
    "gn:feature_class":"P",
    "gn:feature_code":"PPL",
    "gn:name":"Lezha",
    "gn:population":0,
    "gn:timezone":"Europe/Moscow",
    "iso:country":"RU",
    "name:eng_x_preferred":[
        "Lezha"
    ],
    "name:nor_x_preferred":[
        "Lezja"
    ],
    "name:rus_x_preferred":[
        "\u041b\u0435\u0436\u0430"
    ],
    "wof:name":"Lezha",
    "wof:placetype":"locality"
},
  "geometry": {"coordinates":[40.76181,58.93084],"type":"Point"}
}