{
  "type": "Feature",
  "properties": {
    "gn:admin1_code":"60.0",
    "gn:asciiname":"Borshchevichi",
    "gn:country_code":"RU",
    "gn:dem":133,
    "gn:feature_class":"P",
    "gn:feature_code":"PPL",
    "gn:name":"Borshchevichi",
    "gn:population":0,
    "gn:timezone":"Europe/Moscow",
    "iso:country":"RU",
    "name:rus_x_preferred":[
        "\u0411\u043e\u0440\u0449\u0435\u0432\u0438\u0447\u0438"
    ],
    "name:und_x_variant":[
        "Barshevichi",
        "Bor\u0161t\u0161evit\u0161i",
        "Borshchevichi"
    ],
    "wof:name":"Borshchevichi",
    "wof:placetype":"locality"
},
  "geometry": {"coordinates":[27.79501,57.67161],"type":"Point"}
}