{
  "type": "Feature",
  "properties": {
    "gn:admin1_code":"6",
    "gn:asciiname":"Leont'yevskaya",
    "gn:country_code":"RU",
    "gn:dem":55,
    "gn:feature_class":"P",
    "gn:feature_code":"PPL",
    "gn:name":"Leont\u2019yevskaya",
    "gn:population":0,
    "gn:timezone":"Europe/Moscow",
    "iso:country":"RU",
    "name:rus_x_preferred":[
        "\u041b\u0435\u043e\u043d\u0442\u044c\u0435\u0432\u0441\u043a\u0430\u044f"
    ],
    "name:und_x_variant":[
        "Pakhomovo",
        "Leont\u2019yevskaya"
    ],
    "wof:name":"Leont'yevskaya",
    "wof:placetype":"locality"
},
  "geometry": {"coordinates":[42.91011,61.18881],"type":"Point"}
}