{
  "type": "Feature",
  "properties": {
    "gn:admin1_code":"60.0",
    "gn:asciiname":"Dvortsy",
    "gn:country_code":"RU",
    "gn:dem":115,
    "gn:feature_class":"P",
    "gn:feature_code":"PPL",
    "gn:name":"Dvortsy",
    "gn:population":0,
    "gn:timezone":"Europe/Moscow",
    "iso:country":"RU",
    "name:rus_x_preferred":[
        "\u0414\u0432\u043e\u0440\u0446\u044b"
    ],
    "wof:name":"Dvortsy",
    "wof:placetype":"locality"
},
  "geometry": {"coordinates":[29.79238,56.91481],"type":"Point"}
}