{
  "type": "Feature",
  "properties": {
    "gn:admin1_code":"69",
    "gn:asciiname":"Ponar'",
    "gn:country_code":"RU",
    "gn:dem":154,
    "gn:feature_class":"P",
    "gn:feature_code":"PPL",
    "gn:name":"Ponar\u2019",
    "gn:population":0,
    "gn:timezone":"Europe/Moscow",
    "iso:country":"RU",
    "name:rus_x_preferred":[
        "\u041f\u043e\u043d\u0430\u0440\u044c"
    ],
    "name:und_x_variant":[
        "Ponar\u2019"
    ],
    "wof:name":"Ponar'",
    "wof:placetype":"locality"
},
  "geometry": {"coordinates":[31.87089000000001,54.00811],"type":"Point"}
}