{
  "type": "Feature",
  "properties": {
    "gn:admin1_code":"40",
    "gn:asciiname":"Kostylevo",
    "gn:country_code":"RU",
    "gn:dem":153,
    "gn:feature_class":"P",
    "gn:feature_code":"PPL",
    "gn:name":"Kostyl\u00ebvo",
    "gn:population":0,
    "gn:timezone":"Asia/Yekaterinburg",
    "iso:country":"RU",
    "name:eng_x_preferred":[
        "Kostyl\u00ebvo"
    ],
    "name:nor_x_preferred":[
        "Kostylevo"
    ],
    "name:rus_x_preferred":[
        "\u041a\u043e\u0441\u0442\u044b\u043b\u0435\u0432\u043e"
    ],
    "name:rus_x_variant":[
        "\u041a\u043e\u0441\u0442\u044b\u043b\u0451\u0432\u043e"
    ],
    "wof:name":"Kostylevo",
    "wof:placetype":"locality"
},
  "geometry": {"coordinates":[64.28055999999999,54.75361],"type":"Point"}
}