{
  "type": "Feature",
  "properties": {
    "gn:admin1_code":"65",
    "gn:asciiname":"Uchastok Sok",
    "gn:country_code":"RU",
    "gn:dem":56,
    "gn:feature_class":"P",
    "gn:feature_code":"PPL",
    "gn:name":"Uchastok Sok",
    "gn:population":0,
    "gn:timezone":"Europe/Samara",
    "iso:country":"RU",
    "name:rus_x_preferred":[
        "\u0423\u0447\u0430\u0441\u0442\u043e\u043a \u0421\u043e\u043a"
    ],
    "wof:name":"Uchastok Sok",
    "wof:placetype":"locality"
},
  "geometry": {"coordinates":[51.1244,53.9127],"type":"Point"}
}