{
  "type": "Feature",
  "properties": {
    "gn:admin1_code":"34",
    "gn:asciiname":"Verkhnyaya Sedka",
    "gn:country_code":"RU",
    "gn:dem":137,
    "gn:feature_class":"P",
    "gn:feature_code":"PPL",
    "gn:name":"Verkhnyaya Sedka",
    "gn:population":0,
    "gn:timezone":"Europe/Moscow",
    "iso:country":"RU",
    "name:rus_x_preferred":[
        "\u0412\u0435\u0440\u0445\u043d\u044f\u044f \u0421\u0435\u0434\u043a\u0430"
    ],
    "wof:name":"Verkhnyaya Sedka",
    "wof:placetype":"locality"
},
  "geometry": {"coordinates":[49.81628,60.04649000000001],"type":"Point"}
}