{
  "type": "Feature",
  "properties": {
    "gn:country":"RU",
    "gn:fcode":"PPL",
    "gn:population":17084,
    "iso:country":"RU",
    "name:ara_x_preferred":[
        "\u0628\u0648\u0643\u0627\u062a\u0634\u064a"
    ],
    "name:azb_x_preferred":[
        "\u067e\u0648\u06a9\u0627\u0686\u06cc"
    ],
    "name:aze_x_preferred":[
        "Poka\u00e7i"
    ],
    "name:bel_x_preferred":[
        "\u041f\u043e\u043a\u0430\u0447\u044b"
    ],
    "name:bul_x_preferred":[
        "\u041f\u043e\u043a\u0430\u0447\u0438"
    ],
    "name:ceb_x_preferred":[
        "Pokachi"
    ],
    "name:deu_x_preferred":[
        "Pokatschi"
    ],
    "name:eng_x_preferred":[
        "Pokachi"
    ],
    "name:epo_x_preferred":[
        "Poka\u0109i"
    ],
    "name:est_x_preferred":[
        "Pokat\u0161i"
    ],
    "name:fas_x_preferred":[
        "\u067e\u0648\u06a9\u0627\u0686\u06cc"
    ],
    "name:fin_x_preferred":[
        "Pokat\u0161i"
    ],
    "name:fra_x_preferred":[
        "Pokatchi"
    ],
    "name:hsb_x_preferred":[
        "Poka\u010di"
    ],
    "name:hye_x_preferred":[
        "\u054a\u0578\u056f\u0561\u0579\u056b"
    ],
    "name:ita_x_preferred":[
        "Poka\u010di"
    ],
    "name:nld_x_preferred":[
        "Pokatsji"
    ],
    "name:nno_x_preferred":[
        "Pokatsji"
    ],
    "name:nob_x_preferred":[
        "Pokatsji"
    ],
    "name:pol_x_preferred":[
        "Pokaczi"
    ],
    "name:rus_x_preferred":[
        "\u041f\u043e\u043a\u0430\u0447\u0438"
    ],
    "name:srp_x_preferred":[
        "\u041f\u043e\u043a\u0430\u0447\u0438"
    ],
    "name:tat_x_preferred":[
        "\u041f\u043e\u043a\u0430\u0447\u0438"
    ],
    "name:tgk_x_preferred":[
        "\u041f\u043e\u043a\u0430\u0447\u0438"
    ],
    "name:tgl_x_preferred":[
        "Pokachi"
    ],
    "name:tur_x_preferred":[
        "Poka\u00e7i"
    ],
    "name:vep_x_preferred":[
        "Poka\u010di"
    ],
    "name:vie_x_preferred":[
        "Pokachi"
    ],
    "name:war_x_preferred":[
        "Pokachi"
    ],
    "name:zho_x_preferred":[
        "\u6ce2\u5361\u5947"
    ],
    "qs:name":"Pokachi",
    "qs:photos_9r":0,
    "qs:photos_sr":0,
    "qs:pop_sr":"6",
    "wd:wordcount":846,
    "wof:name":"Pokachi",
    "wof:placetype":"locality",
    "wof:population":17084
},
  "geometry": {"coordinates":[75.36827,61.71982],"type":"Point"}
}