{
  "type": "Feature",
  "properties": {
    "gn:admin1_code":"25",
    "gn:asciiname":"Sakharnoye Pole",
    "gn:country_code":"RU",
    "gn:dem":195,
    "gn:feature_class":"P",
    "gn:feature_code":"PPL",
    "gn:name":"Sakharnoye Pole",
    "gn:population":0,
    "gn:timezone":"Europe/Moscow",
    "iso:country":"RU",
    "name:rus_x_preferred":[
        "\u0421\u0430\u0445\u0430\u0440\u043d\u043e\u0435 \u041f\u043e\u043b\u0435"
    ],
    "name:und_x_variant":[
        "\u0421\u0430\u0445\u0430\u0440\u043d\u043e\u0435 \u041f\u043e\u043b\u0435"
    ],
    "wof:name":"Sakharnoye Pole",
    "wof:placetype":"locality"
},
  "geometry": {"coordinates":[34.60926,53.52338],"type":"Point"}
}