{
  "type": "Feature",
  "properties": {
    "gn:admin1_code":"80.0",
    "gn:asciiname":"Malyy Zetym",
    "gn:country_code":"RU",
    "gn:dem":181,
    "gn:feature_class":"P",
    "gn:feature_code":"PPL",
    "gn:name":"Malyy Zetym",
    "gn:population":0,
    "gn:timezone":"Europe/Samara",
    "iso:country":"RU",
    "name:rus_x_preferred":[
        "\u041c\u0430\u043b\u044b\u0439 \u0417\u0435\u0442\u044b\u043c"
    ],
    "wof:name":"Malyy Zetym",
    "wof:placetype":"locality"
},
  "geometry": {"coordinates":[53.816,57.6134],"type":"Point"}
}