{
  "type": "Feature",
  "properties": {
    "gn:admin1_code":"47",
    "gn:asciiname":"Shugarovo",
    "gn:country_code":"RU",
    "gn:dem":165,
    "gn:feature_class":"P",
    "gn:feature_code":"PPL",
    "gn:name":"Shugarovo",
    "gn:population":0,
    "gn:timezone":"Europe/Moscow",
    "iso:country":"RU",
    "name:rus_x_preferred":[
        "\u0428\u0443\u0433\u0430\u0440\u043e\u0432\u043e"
    ],
    "name:und_x_variant":[
        "Shugar\u00ebvo",
        "Shugarovo"
    ],
    "wof:name":"Shugarovo",
    "wof:placetype":"locality"
},
  "geometry": {"coordinates":[37.98953,55.07208000000001],"type":"Point"}
}