{
  "type": "Feature",
  "properties": {
    "gn:admin1_code":"83",
    "gn:asciiname":"Zhartsy",
    "gn:country_code":"RU",
    "gn:dem":127,
    "gn:feature_class":"P",
    "gn:feature_code":"PPL",
    "gn:name":"Zhartsy",
    "gn:population":0,
    "gn:timezone":"Europe/Moscow",
    "iso:country":"RU",
    "name:und_x_variant":[
        "Staryy Zharets",
        "Staryye Zhartsy",
        "Zhartsy"
    ],
    "wof:name":"Zhartsy",
    "wof:placetype":"locality"
},
  "geometry": {"coordinates":[41.36667,55.98333],"type":"Point"}
}