{
  "type": "Feature",
  "properties": {
    "gn:admin1_code":"46",
    "gn:asciiname":"Bol'shiye Pichineyskiye Vyselki",
    "gn:country_code":"RU",
    "gn:dem":116,
    "gn:feature_class":"P",
    "gn:feature_code":"PPL",
    "gn:name":"Bol\u2019shiye Pichineyskiye Vyselki",
    "gn:population":0,
    "gn:timezone":"Europe/Moscow",
    "iso:country":"RU",
    "name:rus_x_preferred":[
        "\u0411\u043e\u043b\u044c\u0448\u0438\u0435 \u041f\u0438\u0447\u0438\u043d\u0435\u0439\u0441\u043a\u0438\u0435 \u0412\u044b\u0441\u0435\u043b\u043a\u0438"
    ],
    "name:und_x_variant":[
        "Bol\u2019shiye Pichineyskiye Vyselki"
    ],
    "wof:name":"Bol'shiye Pichineyskiye Vyselki",
    "wof:placetype":"locality"
},
  "geometry": {"coordinates":[45.8748,54.6073],"type":"Point"}
}