{
  "type": "Feature",
  "properties": {
    "gn:admin1_code":"51.0",
    "gn:asciiname":"Bykov Maydan",
    "gn:country_code":"RU",
    "gn:dem":192,
    "gn:feature_class":"P",
    "gn:feature_code":"PPL",
    "gn:name":"Bykov Maydan",
    "gn:population":0,
    "gn:timezone":"Europe/Moscow",
    "iso:country":"RU",
    "name:rus_x_preferred":[
        "\u0411\u044b\u043a\u043e\u0432 \u041c\u0430\u0439\u0434\u0430\u043d"
    ],
    "wof:name":"Bykov Maydan",
    "wof:placetype":"locality"
},
  "geometry": {"coordinates":[44.29874,55.2597],"type":"Point"}
}