{
  "type": "Feature",
  "properties": {
    "gn:admin1_code":"69",
    "gn:asciiname":"Sloboda",
    "gn:country_code":"RU",
    "gn:dem":196,
    "gn:feature_class":"P",
    "gn:feature_code":"PPL",
    "gn:name":"Sloboda",
    "gn:population":0,
    "gn:timezone":"Europe/Moscow",
    "iso:country":"RU",
    "name:bel_x_preferred":[
        "\u0421\u043b\u0430\u0431\u0430\u0434\u0430"
    ],
    "name:deu_x_preferred":[
        "Sloboda"
    ],
    "name:est_x_preferred":[
        "Sloboda"
    ],
    "name:eus_x_preferred":[
        "Sloboda"
    ],
    "name:fin_x_preferred":[
        "Sloboda"
    ],
    "name:fra_x_preferred":[
        "Sloboda"
    ],
    "name:hrv_x_preferred":[
        "Sloboda"
    ],
    "name:ind_x_preferred":[
        "Sloboda"
    ],
    "name:ita_x_preferred":[
        "Sloboda"
    ],
    "name:jpn_x_preferred":[
        "\u30b9\u30ed\u30dc\u30c0"
    ],
    "name:lav_x_preferred":[
        "Sloboda"
    ],
    "name:mkd_x_preferred":[
        "\u0421\u043b\u043e\u0431\u043e\u0434\u0430"
    ],
    "name:nld_x_preferred":[
        "Sloboda"
    ],
    "name:nno_x_preferred":[
        "Sloboda"
    ],
    "name:nor_x_preferred":[
        "Sloboda"
    ],
    "name:pol_x_preferred":[
        "S\u0142oboda"
    ],
    "name:rus_x_preferred":[
        "\u0421\u043b\u043e\u0431\u043e\u0434\u0430"
    ],
    "name:spa_x_preferred":[
        "Slobod\u00e1"
    ],
    "name:tat_x_preferred":[
        "\u0411\u0438\u0441\u0442\u04d9"
    ],
    "name:ukr_x_preferred":[
        "\u0421\u043b\u043e\u0431\u043e\u0434\u0430"
    ],
    "wof:name":"Sloboda",
    "wof:placetype":"locality"
},
  "geometry": {"coordinates":[32.27041,54.35633000000001],"type":"Point"}
}