{
  "type": "Feature",
  "properties": {
    "gn:admin1_code":"81.0",
    "gn:asciiname":"Allagunovka",
    "gn:country_code":"RU",
    "gn:dem":67,
    "gn:feature_class":"P",
    "gn:feature_code":"PPL",
    "gn:name":"Allagunovka",
    "gn:population":0,
    "gn:timezone":"Europe/Ulyanovsk",
    "iso:country":"RU",
    "name:eng_x_preferred":[
        "Allagunovka"
    ],
    "name:rus_x_preferred":[
        "\u0410\u043b\u043b\u0430\u0433\u0443\u043b\u043e\u0432\u043e"
    ],
    "name:rus_x_variant":[
        "\u0410\u043b\u043b\u0430\u0433\u0443\u043d\u043e\u0432\u043a\u0430"
    ],
    "wof:name":"Allagunovka",
    "wof:placetype":"locality"
},
  "geometry": {"coordinates":[49.58333,54.05],"type":"Point"}
}