{
  "type": "Feature",
  "properties": {
    "gn:admin1_code":"11",
    "gn:asciiname":"Ust'-Khasurta",
    "gn:country_code":"RU",
    "gn:dem":614,
    "gn:feature_class":"P",
    "gn:feature_code":"PPL",
    "gn:name":"Ust\u2019-Khasurta",
    "gn:population":0,
    "gn:timezone":"Asia/Irkutsk",
    "iso:country":"RU",
    "name:rus_x_preferred":[
        "\u0423\u0441\u0442\u044c-\u0425\u0430\u0441\u0443\u0440\u0442\u0430"
    ],
    "name:und_x_variant":[
        "Ust\u2019-Khasurta"
    ],
    "wof:name":"Ust'-Khasurta",
    "wof:placetype":"locality"
},
  "geometry": {"coordinates":[108.712,52.32763],"type":"Point"}
}