{
  "type": "Feature",
  "properties": {
    "gn:admin1_code":"77.0",
    "gn:asciiname":"Bereznitsy",
    "gn:country_code":"RU",
    "gn:dem":181,
    "gn:feature_class":"P",
    "gn:feature_code":"PPL",
    "gn:name":"Bereznitsy",
    "gn:population":0,
    "gn:timezone":"Europe/Moscow",
    "iso:country":"RU",
    "name:eng_x_preferred":[
        "Bereznitsy"
    ],
    "name:nor_x_preferred":[
        "Bereznitsy"
    ],
    "name:rus_x_preferred":[
        "\u0411\u0435\u0440\u0435\u0437\u043d\u0438\u0446\u044b"
    ],
    "name:und_x_variant":[
        "\u0411\u0435\u0440\u0435\u0437\u043d\u0438\u0446\u044b",
        "Bereznitsy"
    ],
    "wof:name":"Bereznitsy",
    "wof:placetype":"locality"
},
  "geometry": {"coordinates":[36.3109,58.48374],"type":"Point"}
}