{
  "type": "Feature",
  "properties": {
    "gn:admin1_code":"78",
    "gn:asciiname":"Mengarskaya",
    "gn:country_code":"RU",
    "gn:dem":77,
    "gn:feature_class":"P",
    "gn:feature_code":"PPL",
    "gn:name":"Mengarskaya",
    "gn:population":0,
    "gn:timezone":"Asia/Yekaterinburg",
    "iso:country":"RU",
    "name:rus_x_preferred":[
        "\u041c\u0435\u043d\u0433\u0430\u0440\u0441\u043a\u0430\u044f"
    ],
    "name:und_x_variant":[
        "Katushi",
        "Mengarskaya",
        "\u041c\u0435\u043d\u0433\u0430\u0440\u0441\u043a\u0430\u044f"
    ],
    "wof:name":"Mengarskaya",
    "wof:placetype":"locality"
},
  "geometry": {"coordinates":[65.91244,56.71701],"type":"Point"}
}