{
  "type": "Feature",
  "properties": {
    "gn:admin1_code":"71",
    "gn:asciiname":"Sabyanino",
    "gn:cc2":"RU",
    "gn:country_code":"RU",
    "gn:dem":78,
    "gn:feature_class":"P",
    "gn:feature_code":"PPL",
    "gn:name":"Sabyanino",
    "gn:population":0,
    "gn:timezone":"Asia/Yekaterinburg",
    "iso:country":"RU",
    "name:eng_x_preferred":[
        "Sabyanino"
    ],
    "name:nor_x_preferred":[
        "Sobjanino"
    ],
    "name:rus_x_preferred":[
        "\u0421\u043e\u0431\u044f\u043d\u0438\u043d\u043e"
    ],
    "name:rus_x_variant":[
        "\u0421\u0430\u0431\u044f\u043d\u0438\u043d\u043e"
    ],
    "name:und_x_variant":[
        "Sobyaninskiy",
        "Sabyaninskiy"
    ],
    "wof:name":"Sabyanino",
    "wof:placetype":"locality"
},
  "geometry": {"coordinates":[60.51667,60.98333],"type":"Point"}
}