{
  "type": "Feature",
  "properties": {
    "gn:admin1_code":"61",
    "gn:asciiname":"Yelizavetov",
    "gn:cc2":"RU",
    "gn:country_code":"RU",
    "gn:dem":81,
    "gn:feature_class":"P",
    "gn:feature_code":"PPL",
    "gn:name":"Yelizavetov",
    "gn:population":0,
    "gn:timezone":"Europe/Moscow",
    "iso:country":"RU",
    "name:und_x_variant":[
        "Yelizavetovka",
        "Yelizavetov"
    ],
    "wof:name":"Yelizavetov",
    "wof:placetype":"locality"
},
  "geometry": {"coordinates":[38.68333,47.31667],"type":"Point"}
}