{
  "type": "Feature",
  "properties": {
    "gn:admin1_code":"73",
    "gn:asciiname":"Murali",
    "gn:country_code":"RU",
    "gn:dem":122,
    "gn:feature_class":"P",
    "gn:feature_code":"PPL",
    "gn:name":"Murali",
    "gn:population":0,
    "gn:timezone":"Europe/Moscow",
    "iso:country":"RU",
    "name:deu_x_preferred":[
        "Murali"
    ],
    "name:mal_x_preferred":[
        "\u0d2e\u0d41\u0d30\u0d33\u0d3f"
    ],
    "name:rus_x_preferred":[
        "\u041c\u0443\u0440\u0430\u043b\u0438"
    ],
    "name:tat_x_preferred":[
        "\u041c\u04e9\u0440\u04d9\u043b\u0435"
    ],
    "wof:name":"Murali",
    "wof:placetype":"locality"
},
  "geometry": {"coordinates":[50.1648,56.1787],"type":"Point"}
}