{
  "type": "Feature",
  "properties": {
    "gn:admin1_code":"28",
    "gn:asciiname":"Vagvozero",
    "gn:cc2":"RU",
    "gn:country_code":"RU",
    "gn:dem":92,
    "gn:feature_class":"P",
    "gn:feature_code":"PPL",
    "gn:name":"Vagvozero",
    "gn:population":0,
    "gn:timezone":"Europe/Moscow",
    "iso:country":"RU",
    "name:eng_x_preferred":[
        "Vagvozero"
    ],
    "name:fin_x_preferred":[
        "Vahj\u00e4rvi"
    ],
    "name:nor_x_preferred":[
        "Vagvozero"
    ],
    "name:rus_x_preferred":[
        "\u0412\u0430\u0433\u0432\u043e\u0437\u0435\u0440\u043e"
    ],
    "name:und_x_variant":[
        "Vagozero",
        "Vagvozero"
    ],
    "wof:name":"Vagvozero",
    "wof:placetype":"locality"
},
  "geometry": {"coordinates":[33.08052,61.3765],"type":"Point"}
}