{
  "type": "Feature",
  "properties": {
    "gn:admin1_code":"25",
    "gn:asciiname":"Matchino",
    "gn:country_code":"RU",
    "gn:dem":211,
    "gn:feature_class":"P",
    "gn:feature_code":"PPL",
    "gn:name":"Matchino",
    "gn:population":0,
    "gn:timezone":"Europe/Moscow",
    "iso:country":"RU",
    "name:rus_x_preferred":[
        "\u041c\u0430\u0442\u0447\u0438\u043d\u043e"
    ],
    "name:und_x_variant":[
        "\u041c\u0430\u0442\u0447\u0438\u043d\u043e"
    ],
    "wof:name":"Matchino",
    "wof:placetype":"locality"
},
  "geometry": {"coordinates":[35.03066,54.17785],"type":"Point"}
}