{
  "type": "Feature",
  "properties": {
    "gn:admin1_code":"77.0",
    "gn:asciiname":"Dubishchi",
    "gn:country_code":"RU",
    "gn:dem":167,
    "gn:feature_class":"P",
    "gn:feature_code":"PPL",
    "gn:name":"Dubishchi",
    "gn:population":0,
    "gn:timezone":"Europe/Moscow",
    "iso:country":"RU",
    "name:rus_x_preferred":[
        "\u0414\u0443\u0431\u0438\u0449\u0438"
    ],
    "name:und_x_variant":[
        "\u0414\u0443\u0431\u0438\u0449\u0438"
    ],
    "wof:name":"Dubishchi",
    "wof:placetype":"locality"
},
  "geometry": {"coordinates":[36.14922,58.13038],"type":"Point"}
}