{
  "type": "Feature",
  "properties": {
    "gn:admin1_code":"25.0",
    "gn:asciiname":"Dubrovo",
    "gn:country_code":"RU",
    "gn:dem":196,
    "gn:feature_class":"P",
    "gn:feature_code":"PPL",
    "gn:name":"Dubrovo",
    "gn:population":0,
    "gn:timezone":"Europe/Moscow",
    "iso:country":"RU",
    "name:che_x_preferred":[
        "\u0414\u0443\u0431\u0440\u043e\u0432\u043e"
    ],
    "name:eng_x_preferred":[
        "Dubrovo"
    ],
    "name:nor_x_preferred":[
        "Dubrovo"
    ],
    "name:rus_x_preferred":[
        "\u0414\u0443\u0431\u0440\u043e\u0432\u043e"
    ],
    "name:und_x_variant":[
        "Dubrova",
        "\u0414\u0443\u0431\u0440\u043e\u0432\u043e",
        "Dubrovo"
    ],
    "wof:name":"Dubrovo",
    "wof:placetype":"locality"
},
  "geometry": {"coordinates":[34.26203,54.1998],"type":"Point"}
}