{
  "type": "Feature",
  "properties": {
    "gn:admin1_code":"71",
    "gn:asciiname":"Malyye Karshi",
    "gn:country_code":"RU",
    "gn:dem":232,
    "gn:feature_class":"P",
    "gn:feature_code":"PPL",
    "gn:name":"Malyye Karshi",
    "gn:population":0,
    "gn:timezone":"Asia/Yekaterinburg",
    "iso:country":"RU",
    "name:rus_x_preferred":[
        "\u041c\u0430\u043b\u044b\u0435 \u041a\u0430\u0440\u0448\u0438"
    ],
    "name:und_x_variant":[
        "\u041c\u0430\u043b\u044b\u0435 \u041a\u0430\u0440\u0448\u0438"
    ],
    "wof:name":"Malyye Karshi",
    "wof:placetype":"locality"
},
  "geometry": {"coordinates":[58.01667,56.85],"type":"Point"}
}