{
  "type": "Feature",
  "properties": {
    "gn:admin1_code":"88",
    "gn:asciiname":"Kaplino",
    "gn:country_code":"RU",
    "gn:dem":134,
    "gn:feature_class":"P",
    "gn:feature_code":"PPL",
    "gn:name":"Kaplino",
    "gn:population":0,
    "gn:timezone":"Europe/Moscow",
    "iso:country":"RU",
    "name:rus_x_preferred":[
        "\u041a\u0430\u043f\u043b\u0438\u043d\u043e"
    ],
    "wof:name":"Kaplino",
    "wof:placetype":"locality"
},
  "geometry": {"coordinates":[38.0939,58.0365],"type":"Point"}
}