{
  "type": "Feature",
  "properties": {
    "gn:admin1_code":"84.0",
    "gn:asciiname":"Gromlenovskiy",
    "gn:country_code":"RU",
    "gn:dem":184,
    "gn:feature_class":"P",
    "gn:feature_code":"PPL",
    "gn:name":"Gromlenovskiy",
    "gn:population":0,
    "gn:timezone":"Europe/Volgograd",
    "iso:country":"RU",
    "name:rus_x_preferred":[
        "\u0413\u0440\u043e\u043c\u043b\u0435\u043d\u043e\u0432\u0441\u043a\u0438\u0439"
    ],
    "name:und_x_variant":[
        "Gramlenovskiy",
        "Gromlenovskiy"
    ],
    "wof:name":"Gromlenovskiy",
    "wof:placetype":"locality"
},
  "geometry": {"coordinates":[41.42,50.7235],"type":"Point"}
}