{
  "type": "Feature",
  "properties": {
    "gn:admin1_code":"21",
    "gn:asciiname":"Novlyanskoye",
    "gn:country_code":"RU",
    "gn:dem":129,
    "gn:feature_class":"P",
    "gn:feature_code":"PPL",
    "gn:name":"Novlyanskoye",
    "gn:population":0,
    "gn:timezone":"Europe/Moscow",
    "iso:country":"RU",
    "name:eng_x_preferred":[
        "Novlyanskoye"
    ],
    "name:nor_x_preferred":[
        "Novljanskoje"
    ],
    "name:rus_x_preferred":[
        "\u041d\u043e\u0432\u043b\u044f\u043d\u0441\u043a\u043e\u0435"
    ],
    "name:und_x_variant":[
        "\u041d\u043e\u0432\u043b\u044f\u043d\u0441\u043a\u043e\u0435",
        "Novlyanskoye"
    ],
    "wof:name":"Novlyanskoye",
    "wof:placetype":"locality"
},
  "geometry": {"coordinates":[41.72707,57.45113000000001],"type":"Point"}
}