{
  "type": "Feature",
  "properties": {
    "gn:admin1_code":"6",
    "gn:asciiname":"Lopatino",
    "gn:country_code":"RU",
    "gn:dem":75,
    "gn:feature_class":"P",
    "gn:feature_code":"PPL",
    "gn:name":"Lopatino",
    "gn:population":0,
    "gn:timezone":"Europe/Moscow",
    "iso:country":"RU",
    "name:rus_x_preferred":[
        "\u041b\u043e\u043f\u0430\u0442\u0438\u043d\u043e"
    ],
    "name:und_x_variant":[
        "Lokatina",
        "Lopatino",
        "\u041b\u043e\u043f\u0430\u0442\u0438\u043d\u043e"
    ],
    "wof:name":"Lopatino",
    "wof:placetype":"locality"
},
  "geometry": {"coordinates":[48.87846,62.06501],"type":"Point"}
}