{
  "type": "Feature",
  "properties": {
    "gn:admin1_code":"85",
    "gn:asciiname":"Markovskaya",
    "gn:country_code":"RU",
    "gn:dem":158,
    "gn:feature_class":"P",
    "gn:feature_code":"PPL",
    "gn:name":"Markovskaya",
    "gn:population":0,
    "gn:timezone":"Europe/Moscow",
    "iso:country":"RU",
    "name:rus_x_preferred":[
        "\u041c\u0430\u0440\u043a\u043e\u0432\u0441\u043a\u0430\u044f"
    ],
    "wof:name":"Markovskaya",
    "wof:placetype":"locality"
},
  "geometry": {"coordinates":[37.23333,59.45],"type":"Point"}
}