{
  "type": "Feature",
  "properties": {
    "gn:admin1_code":"77",
    "gn:asciiname":"Belki",
    "gn:country_code":"RU",
    "gn:dem":186,
    "gn:feature_class":"P",
    "gn:feature_code":"PPL",
    "gn:name":"Belki",
    "gn:population":0,
    "gn:timezone":"Europe/Moscow",
    "iso:country":"RU",
    "name:nor_x_preferred":[
        "Belki"
    ],
    "name:rus_x_preferred":[
        "\u0411\u0435\u043b\u043a\u0438"
    ],
    "wof:name":"Belki",
    "wof:placetype":"locality"
},
  "geometry": {"coordinates":[32.21833,55.99444],"type":"Point"}
}