{
  "type": "Feature",
  "properties": {
    "gn:admin1_code":"8.0",
    "gn:asciiname":"Cherlak",
    "gn:country_code":"RU",
    "gn:dem":80,
    "gn:feature_class":"P",
    "gn:feature_code":"PPL",
    "gn:name":"Cherlak",
    "gn:population":0,
    "gn:timezone":"Asia/Yekaterinburg",
    "iso:country":"RU",
    "name:eng_x_preferred":[
        "Cherlak"
    ],
    "name:nor_x_preferred":[
        "Tsjerlak"
    ],
    "name:rus_x_preferred":[
        "\u0427\u0435\u0440\u043b\u0430\u043a"
    ],
    "wof:name":"Cherlak",
    "wof:placetype":"locality"
},
  "geometry": {"coordinates":[54.75755,55.74005],"type":"Point"}
}