{
  "type": "Feature",
  "properties": {
    "gn:admin1_code":"64",
    "gn:asciiname":"Nizhniye Pochinki",
    "gn:cc2":"RU",
    "gn:country_code":"RU",
    "gn:dem":-9999,
    "gn:feature_class":"P",
    "gn:feature_code":"PPL",
    "gn:name":"Nizhniye Pochinki",
    "gn:population":0,
    "gn:timezone":"Asia/Sakhalin",
    "iso:country":"RU",
    "name:rus_x_preferred":[
        "\u041d\u0438\u0436\u043d\u0438\u0435 \u041f\u043e\u0447\u0438\u043d\u043a\u0438"
    ],
    "name:und_x_variant":[
        "Potinki",
        "Nizhne-Pochinki",
        "Minami-iketsuki",
        "Minami-ikezuki",
        "Minami-ikedzuki",
        "Nizhniye Pochinki",
        "\u041d\u0438\u0436\u043d\u0438\u0435 \u041f\u043e\u0447\u0438\u043d\u043a\u0438"
    ],
    "wof:name":"Nizhniye Pochinki",
    "wof:placetype":"locality"
},
  "geometry": {"coordinates":[142.36667,46.48333],"type":"Point"}
}