{
  "type": "Feature",
  "properties": {
    "gn:admin1_code":"60",
    "gn:asciiname":"Yamkino",
    "gn:country_code":"RU",
    "gn:dem":72,
    "gn:feature_class":"P",
    "gn:feature_code":"PPL",
    "gn:name":"Yamkino",
    "gn:population":0,
    "gn:timezone":"Europe/Moscow",
    "iso:country":"RU",
    "name:eng_x_preferred":[
        "Yamkino"
    ],
    "name:nor_x_preferred":[
        "Jamkino"
    ],
    "name:rus_x_preferred":[
        "\u042f\u043c\u043a\u0438\u043d\u043e"
    ],
    "wof:name":"Yamkino",
    "wof:placetype":"locality"
},
  "geometry": {"coordinates":[29.30879,57.90483],"type":"Point"}
}