{
  "type": "Feature",
  "properties": {
    "gn:admin1_code":"33",
    "gn:asciiname":"Mukhachi",
    "gn:country_code":"RU",
    "gn:dem":161,
    "gn:feature_class":"P",
    "gn:feature_code":"PPL",
    "gn:name":"Mukhachi",
    "gn:population":0,
    "gn:timezone":"Europe/Kirov",
    "iso:country":"RU",
    "name:eng_x_preferred":[
        "Mukhachi"
    ],
    "name:nor_x_preferred":[
        "Mukhatsji"
    ],
    "name:rus_x_preferred":[
        "\u041c\u0443\u0445\u0430\u0447\u0438"
    ],
    "wof:name":"Mukhachi",
    "wof:placetype":"locality"
},
  "geometry": {"coordinates":[50.70063,57.87701],"type":"Point"}
}