{
  "type": "Feature",
  "properties": {
    "gn:admin1_code":"65",
    "gn:asciiname":"Putilovskiy",
    "gn:country_code":"RU",
    "gn:dem":87,
    "gn:feature_class":"P",
    "gn:feature_code":"PPL",
    "gn:name":"Putilovskiy",
    "gn:population":0,
    "gn:timezone":"Europe/Samara",
    "iso:country":"RU",
    "name:rus_x_preferred":[
        "\u041f\u0443\u0442\u0438\u043b\u043e\u0432\u0441\u043a\u0438\u0439"
    ],
    "wof:name":"Putilovskiy",
    "wof:placetype":"locality"
},
  "geometry": {"coordinates":[51.0053,52.3513],"type":"Point"}
}