{
  "type": "Feature",
  "properties": {
    "gn:admin1_code":"52",
    "gn:asciiname":"Kamenka",
    "gn:country_code":"RU",
    "gn:dem":162,
    "gn:feature_class":"P",
    "gn:feature_code":"PPL",
    "gn:name":"Kamenka",
    "gn:population":0,
    "gn:timezone":"Europe/Moscow",
    "iso:country":"RU",
    "name:aze_x_preferred":[
        "Kamenka"
    ],
    "name:bel_x_preferred":[
        "\u041a\u0430\u043c\u0435\u043d\u043a\u0430"
    ],
    "name:ceb_x_preferred":[
        "Kamenka"
    ],
    "name:ces_x_preferred":[
        "Kamenka"
    ],
    "name:deu_x_preferred":[
        "Kamenka"
    ],
    "name:epo_x_preferred":[
        "Kamenka"
    ],
    "name:est_x_preferred":[
        "Kamenka"
    ],
    "name:fin_x_preferred":[
        "Kamenka"
    ],
    "name:fra_x_preferred":[
        "Kamenka"
    ],
    "name:hye_x_preferred":[
        "\u053f\u0561\u0574\u0565\u0576\u056f\u0561"
    ],
    "name:ita_x_preferred":[
        "Kamenka"
    ],
    "name:kat_x_preferred":[
        "\u10d9\u10d0\u10db\u10d4\u10dc\u10d9\u10d0"
    ],
    "name:kaz_x_preferred":[
        "\u041a\u0430\u043c\u0435\u043d\u043a\u0430"
    ],
    "name:lav_x_preferred":[
        "Kamenka"
    ],
    "name:lit_x_preferred":[
        "Kamenka"
    ],
    "name:myv_x_preferred":[
        "\u041a\u0430\u043c\u0435\u043d\u043a\u0430"
    ],
    "name:rus_x_preferred":[
        "\u041a\u0430\u043c\u0435\u043d\u043a\u0430"
    ],
    "name:srp_x_preferred":[
        "\u041a\u0430\u043c\u0435\u043d\u043a\u0430"
    ],
    "name:swe_x_preferred":[
        "Kamenka"
    ],
    "name:ukr_x_preferred":[
        "\u041a\u0430\u043c\u0435\u043d\u043a\u0430"
    ],
    "wof:name":"Kamenka",
    "wof:placetype":"locality"
},
  "geometry": {"coordinates":[34.53333,58.93333000000001],"type":"Point"}
}