{
  "type": "Feature",
  "properties": {
    "gn:admin1_code":"8.0",
    "gn:asciiname":"Annenkovo",
    "gn:country_code":"RU",
    "gn:dem":362,
    "gn:feature_class":"P",
    "gn:feature_code":"PPL",
    "gn:name":"Annenkovo",
    "gn:population":0,
    "gn:timezone":"Asia/Yekaterinburg",
    "iso:country":"RU",
    "name:bak_x_preferred":[
        "\u0410\u043d\u043d\u0435\u043d\u043a\u043e\u0432"
    ],
    "name:che_x_preferred":[
        "\u0410\u043d\u043d\u0435\u043d\u043a\u043e\u0432\u043e"
    ],
    "name:hye_x_preferred":[
        "\u0531\u0576\u0576\u0565\u0576\u056f\u0578\u057e\u0578"
    ],
    "name:kaz_x_preferred":[
        "\u0410\u043d\u043d\u0435\u043d\u043a"
    ],
    "name:kir_x_preferred":[
        "\u0410\u043d\u043d\u0435\u043d\u043a"
    ],
    "name:nor_x_preferred":[
        "Annenkovo"
    ],
    "name:rus_x_preferred":[
        "\u0410\u043d\u043d\u0435\u043d\u043a\u043e\u0432\u043e"
    ],
    "name:tat_x_preferred":[
        "\u0410\u043d\u043d\u0435\u043d\u043a\u043e\u0432\u043e"
    ],
    "name:ukr_x_preferred":[
        "\u0410\u043d\u043d\u0435\u043d\u043a\u043e\u0432\u043e"
    ],
    "wof:name":"Annenkovo",
    "wof:placetype":"locality"
},
  "geometry": {"coordinates":[54.25,54.05],"type":"Point"}
}