{
  "type": "Feature",
  "properties": {
    "gn:admin1_code":"8",
    "gn:asciiname":"Pervyy May",
    "gn:country_code":"RU",
    "gn:dem":399,
    "gn:feature_class":"P",
    "gn:feature_code":"PPL",
    "gn:name":"Pervyy May",
    "gn:population":0,
    "gn:timezone":"Asia/Yekaterinburg",
    "iso:country":"RU",
    "name:eng_x_preferred":[
        "Pervyy May"
    ],
    "name:nor_x_preferred":[
        "Pervyj Maj"
    ],
    "name:rus_x_preferred":[
        "\u041f\u0435\u0440\u0432\u044b\u0439 \u041c\u0430\u0439"
    ],
    "name:und_x_variant":[
        "Pervomayskiy",
        "\u041f\u0435\u0440\u0432\u044b\u0439 \u041c\u0430\u0439",
        "Pervyy May"
    ],
    "wof:name":"Pervyy May",
    "wof:placetype":"locality"
},
  "geometry": {"coordinates":[59.6975,54.4304],"type":"Point"}
}