{
  "type": "Feature",
  "properties": {
    "gn:admin1_code":"52.0",
    "gn:asciiname":"Glistnitsy",
    "gn:country_code":"RU",
    "gn:dem":178,
    "gn:feature_class":"P",
    "gn:feature_code":"PPL",
    "gn:name":"Glistnitsy",
    "gn:population":0,
    "gn:timezone":"Europe/Moscow",
    "iso:country":"RU",
    "name:rus_x_preferred":[
        "\u0413\u043b\u0438\u0441\u0442\u043d\u0438\u0446\u044b"
    ],
    "wof:name":"Glistnitsy",
    "wof:placetype":"locality"
},
  "geometry": {"coordinates":[33.75,58.25],"type":"Point"}
}