{
  "type": "Feature",
  "properties": {
    "gn:admin1_code":"80.0",
    "gn:asciiname":"Papanevo",
    "gn:country_code":"RU",
    "gn:dem":199,
    "gn:feature_class":"P",
    "gn:feature_code":"PPL",
    "gn:name":"Papanevo",
    "gn:population":0,
    "gn:timezone":"Europe/Samara",
    "iso:country":"RU",
    "name:rus_x_preferred":[
        "\u041f\u0430\u043f\u0430\u043d\u0435\u0432\u043e"
    ],
    "wof:name":"Papanevo",
    "wof:placetype":"locality"
},
  "geometry": {"coordinates":[51.9919,57.9494],"type":"Point"}
}