{
  "type": "Feature",
  "properties": {
    "gn:admin1_code":"42",
    "gn:asciiname":"Pyatchino",
    "gn:country_code":"RU",
    "gn:dem":66,
    "gn:feature_class":"P",
    "gn:feature_code":"PPL",
    "gn:name":"Pyatchino",
    "gn:population":0,
    "gn:timezone":"Europe/Moscow",
    "iso:country":"RU",
    "name:eng_x_preferred":[
        "Pyatchino"
    ],
    "name:fin_x_preferred":[
        "P\u00e4tsin\u00e4"
    ],
    "name:nor_x_preferred":[
        "Pjattsjino"
    ],
    "name:rus_x_preferred":[
        "\u041f\u044f\u0442\u0447\u0438\u043d\u043e"
    ],
    "name:und_x_variant":[
        "Pyatchina",
        "\u041f\u044f\u0442\u0447\u0438\u043d\u043e",
        "Pyatchino"
    ],
    "wof:name":"Pyatchino",
    "wof:placetype":"locality"
},
  "geometry": {"coordinates":[28.66508,59.71106999999999],"type":"Point"}
}