{
  "type": "Feature",
  "properties": {
    "gn:admin1_code":"54",
    "gn:asciiname":"Putintsevo",
    "gn:country_code":"RU",
    "gn:dem":93,
    "gn:feature_class":"P",
    "gn:feature_code":"PPL",
    "gn:name":"Putintsevo",
    "gn:population":0,
    "gn:timezone":"Asia/Omsk",
    "iso:country":"RU",
    "name:rus_x_preferred":[
        "\u041f\u0443\u0442\u0438\u043d\u0446\u0435\u0432\u043e"
    ],
    "wof:name":"Putintsevo",
    "wof:placetype":"locality"
},
  "geometry": {"coordinates":[73.25331,54.79641],"type":"Point"}
}