{
  "type": "Feature",
  "properties": {
    "gn:admin1_code":"60.0",
    "gn:asciiname":"Drykushki",
    "gn:country_code":"RU",
    "gn:dem":86,
    "gn:feature_class":"P",
    "gn:feature_code":"PPL",
    "gn:name":"Drykushki",
    "gn:population":0,
    "gn:timezone":"Europe/Moscow",
    "iso:country":"RU",
    "name:rus_x_preferred":[
        "\u0414\u0440\u044b\u043a\u0443\u0448\u043a\u0438"
    ],
    "name:und_x_variant":[
        "Drikashki",
        "Drykoshki",
        "Drykushki"
    ],
    "wof:name":"Drykushki",
    "wof:placetype":"locality"
},
  "geometry": {"coordinates":[28.0955,56.96144],"type":"Point"}
}