{
  "type": "Feature",
  "properties": {
    "gn:admin1_code":"13",
    "gn:asciiname":"Voronino",
    "gn:country_code":"RU",
    "gn:dem":340,
    "gn:feature_class":"P",
    "gn:feature_code":"PPL",
    "gn:name":"Voronino",
    "gn:population":0,
    "gn:timezone":"Asia/Yekaterinburg",
    "iso:country":"RU",
    "name:rus_x_preferred":[
        "\u0412\u043e\u0440\u043e\u043d\u0438\u043d\u043e"
    ],
    "name:und_x_variant":[
        "Voronina",
        "Voronino"
    ],
    "wof:name":"Voronino",
    "wof:placetype":"locality"
},
  "geometry": {"coordinates":[60.4666,54.32663],"type":"Point"}
}