{
  "type": "Feature",
  "properties": {
    "gn:admin1_code":"56",
    "gn:asciiname":"Soroch'i Kusty",
    "gn:country_code":"RU",
    "gn:dem":237,
    "gn:feature_class":"P",
    "gn:feature_code":"PPL",
    "gn:name":"Soroch\u2019i Kusty",
    "gn:population":0,
    "gn:timezone":"Europe/Moscow",
    "iso:country":"RU",
    "name:rus_x_preferred":[
        "\u0421\u043e\u0440\u043e\u0447\u044c\u0438 \u041a\u0443\u0441\u0442\u044b"
    ],
    "name:und_x_variant":[
        "Soroch\u2019i Kusty"
    ],
    "wof:name":"Soroch'i Kusty",
    "wof:placetype":"locality"
},
  "geometry": {"coordinates":[36.39197,52.62214],"type":"Point"}
}