{
  "type": "Feature",
  "properties": {
    "gn:admin1_code":"61",
    "gn:asciiname":"Kozinka",
    "gn:country_code":"RU",
    "gn:dem":32,
    "gn:feature_class":"P",
    "gn:feature_code":"PPL",
    "gn:name":"Kozinka",
    "gn:population":0,
    "gn:timezone":"Europe/Moscow",
    "iso:country":"RU",
    "name:che_x_preferred":[
        "\u041a\u043e\u0437\u0438\u043d\u043a\u0430"
    ],
    "name:rus_x_preferred":[
        "\u041a\u043e\u0437\u0438\u043d\u043a\u0430"
    ],
    "name:tgk_x_preferred":[
        "\u041a\u043e\u0437\u0438\u043d\u043a\u0430"
    ],
    "name:und_x_variant":[
        "\u041a\u043e\u0437\u0438\u043d\u043a\u0430"
    ],
    "wof:name":"Kozinka",
    "wof:placetype":"locality"
},
  "geometry": {"coordinates":[41.91747,47.34765],"type":"Point"}
}