{
  "type": "Feature",
  "properties": {
    "gn:admin1_code":"80.0",
    "gn:asciiname":"Vasilyata",
    "gn:country_code":"RU",
    "gn:dem":246,
    "gn:feature_class":"P",
    "gn:feature_code":"PPL",
    "gn:name":"Vasilyata",
    "gn:population":0,
    "gn:timezone":"Europe/Samara",
    "iso:country":"RU",
    "name:rus_x_preferred":[
        "\u0412\u0430\u0441\u0438\u043b\u044f\u0442\u0430"
    ],
    "wof:name":"Vasilyata",
    "wof:placetype":"locality"
},
  "geometry": {"coordinates":[53.4728,58.419],"type":"Point"}
}