{
  "type": "Feature",
  "properties": {
    "gn:admin1_code":"69",
    "gn:asciiname":"Novyye Golovachi",
    "gn:country_code":"RU",
    "gn:dem":217,
    "gn:feature_class":"P",
    "gn:feature_code":"PPL",
    "gn:name":"Novyye Golovachi",
    "gn:population":0,
    "gn:timezone":"Europe/Moscow",
    "iso:country":"RU",
    "name:eng_x_preferred":[
        "Novyye Golovachi"
    ],
    "name:nor_x_preferred":[
        "Novo-Golovatsji"
    ],
    "name:rus_x_preferred":[
        "\u041d\u043e\u0432\u043e-\u0413\u043e\u043b\u043e\u0432\u0430\u0447\u0438"
    ],
    "name:rus_x_variant":[
        "\u041d\u043e\u0432\u044b\u0435 \u0413\u043e\u043b\u043e\u0432\u0430\u0447\u0438"
    ],
    "wof:name":"Novyye Golovachi",
    "wof:placetype":"locality"
},
  "geometry": {"coordinates":[32.8601,54.20962],"type":"Point"}
}