{
  "type": "Feature",
  "properties": {
    "gn:admin1_code":"75",
    "gn:asciiname":"Astal'tseva",
    "gn:country_code":"RU",
    "gn:dem":95,
    "gn:feature_class":"P",
    "gn:feature_code":"PPL",
    "gn:name":"Astal\u2019tseva",
    "gn:population":0,
    "gn:timezone":"Asia/Tomsk",
    "iso:country":"RU",
    "name:nor_x_preferred":[
        "Astaltseva"
    ],
    "name:rus_x_preferred":[
        "\u0410\u0441\u0442\u0430\u043b\u044c\u0446\u0435\u0432\u0430"
    ],
    "name:und_x_variant":[
        "Astal\u2019tseva"
    ],
    "wof:name":"Astal'tseva",
    "wof:placetype":"locality"
},
  "geometry": {"coordinates":[83.88333,56.46666999999999],"type":"Point"}
}