{
  "type": "Feature",
  "properties": {
    "gn:admin1_code":"53",
    "gn:asciiname":"Pervomayskiy",
    "gn:cc2":"RU",
    "gn:country_code":"RU",
    "gn:dem":146,
    "gn:feature_class":"P",
    "gn:feature_code":"PPL",
    "gn:name":"Pervomayskiy",
    "gn:population":0,
    "gn:timezone":"Asia/Novosibirsk",
    "iso:country":"RU",
    "name:eng_x_preferred":[
        "Pervomayskiy"
    ],
    "name:rus_x_preferred":[
        "\u0427\u0435\u0440\u043d\u044f\u0432\u0441\u043a\u0438\u0439"
    ],
    "name:rus_x_variant":[
        "\u041f\u0435\u0440\u0432\u043e\u043c\u0430\u0439\u0441\u043a\u0438\u0439"
    ],
    "name:und_x_variant":[
        "Chernyavskaya",
        "Chernyavskiy",
        "\u041f\u0435\u0440\u0432\u043e\u043c\u0430\u0439\u0441\u043a\u0438\u0439",
        "Pervomayskiy"
    ],
    "wof:name":"Pervomayskiy",
    "wof:placetype":"locality"
},
  "geometry": {"coordinates":[80.18611,55.045],"type":"Point"}
}