{
  "type": "Feature",
  "properties": {
    "gn:admin1_code":"64",
    "gn:asciiname":"Golovnino",
    "gn:country_code":"RU",
    "gn:dem":11,
    "gn:feature_class":"P",
    "gn:feature_code":"PPL",
    "gn:name":"Golovnino",
    "gn:population":0,
    "gn:timezone":"Asia/Tokyo",
    "iso:country":"RU",
    "name:rus_x_preferred":[
        "\u0413\u043e\u043b\u043e\u0432\u043d\u0438\u043d\u043e"
    ],
    "name:und_x_variant":[
        "Tomarimura",
        "Tomari",
        "Golovnino"
    ],
    "wof:name":"Golovnino",
    "wof:placetype":"locality"
},
  "geometry": {"coordinates":[145.51946000000001,43.73682],"type":"Point"}
}