{
  "type": "Feature",
  "properties": {
    "gn:admin1_code":"8",
    "gn:asciiname":"Fan'",
    "gn:country_code":"RU",
    "gn:dem":261,
    "gn:feature_class":"P",
    "gn:feature_code":"PPL",
    "gn:name":"Fan\u2019",
    "gn:population":0,
    "gn:timezone":"Asia/Yekaterinburg",
    "iso:country":"RU",
    "name:rus_x_preferred":[
        "\u0424\u0430\u043d\u044c"
    ],
    "name:und_x_variant":[
        "Fan\u2019",
        "\u0424\u0430\u043d\u044c"
    ],
    "wof:name":"Fan'",
    "wof:placetype":"locality"
},
  "geometry": {"coordinates":[54.7576,54.1326],"type":"Point"}
}