{
  "type": "Feature",
  "properties": {
    "gn:admin1_code":"25",
    "gn:asciiname":"Molostovo",
    "gn:country_code":"RU",
    "gn:dem":182,
    "gn:feature_class":"P",
    "gn:feature_code":"PPL",
    "gn:name":"Molostovo",
    "gn:population":0,
    "gn:timezone":"Europe/Moscow",
    "iso:country":"RU",
    "name:rus_x_preferred":[
        "\u041c\u043e\u043b\u043e\u0441\u0442\u043e\u0432\u043e"
    ],
    "name:und_x_variant":[
        "\u041c\u043e\u043b\u043e\u0441\u0442\u043e\u0432\u043e"
    ],
    "wof:name":"Molostovo",
    "wof:placetype":"locality"
},
  "geometry": {"coordinates":[35.60999,54.2966],"type":"Point"}
}