{
  "type": "Feature",
  "properties": {
    "gn:admin1_code":"31",
    "gn:asciiname":"Malyy Monok",
    "gn:country_code":"RU",
    "gn:dem":610,
    "gn:feature_class":"P",
    "gn:feature_code":"PPL",
    "gn:name":"Malyy Monok",
    "gn:population":0,
    "gn:timezone":"Asia/Krasnoyarsk",
    "iso:country":"RU",
    "name:eng_x_preferred":[
        "Malyy Monok"
    ],
    "name:nor_x_preferred":[
        "Mal.Monok"
    ],
    "name:rus_x_preferred":[
        "\u041c\u0430\u043b.\u041c\u043e\u043d\u043e\u043a"
    ],
    "name:rus_x_variant":[
        "\u041c\u0430\u043b\u044b\u0439 \u041c\u043e\u043d\u043e\u043a"
    ],
    "name:und_x_variant":[
        "\u041c\u0430\u043b\u044b\u0439 \u041c\u043e\u043d\u043e\u043a"
    ],
    "wof:name":"Malyy Monok",
    "wof:placetype":"locality"
},
  "geometry": {"coordinates":[90.43333,52.83333],"type":"Point"}
}