{
  "type": "Feature",
  "properties": {
    "gn:admin1_code":"10",
    "gn:asciiname":"Kostyrin",
    "gn:country_code":"RU",
    "gn:dem":167,
    "gn:feature_class":"P",
    "gn:feature_code":"PPL",
    "gn:name":"Kostyrin",
    "gn:population":0,
    "gn:timezone":"Europe/Moscow",
    "iso:country":"RU",
    "name:rus_x_preferred":[
        "\u041a\u043e\u0441\u0442\u044b\u0440\u0438\u043d"
    ],
    "wof:name":"Kostyrin",
    "wof:placetype":"locality"
},
  "geometry": {"coordinates":[32.4625,52.8719],"type":"Point"}
}