{
  "type": "Feature",
  "properties": {
    "gn:admin1_code":"67",
    "gn:asciiname":"Irinovka",
    "gn:country_code":"RU",
    "gn:dem":127,
    "gn:feature_class":"P",
    "gn:feature_code":"PPL",
    "gn:name":"Irinovka",
    "gn:population":0,
    "gn:timezone":"Europe/Saratov",
    "iso:country":"RU",
    "name:eng_x_preferred":[
        "Irinovka"
    ],
    "name:nor_x_preferred":[
        "Irinovka"
    ],
    "name:rus_x_preferred":[
        "\u0418\u0440\u0438\u043d\u043e\u0432\u043a\u0430"
    ],
    "wof:name":"Irinovka",
    "wof:placetype":"locality"
},
  "geometry": {"coordinates":[46.23249000000001,51.99873],"type":"Point"}
}