{
  "type": "Feature",
  "properties": {
    "gn:admin1_code":"62.0",
    "gn:asciiname":"Chermnyye",
    "gn:country_code":"RU",
    "gn:dem":103,
    "gn:feature_class":"P",
    "gn:feature_code":"PPL",
    "gn:name":"Chermnyye",
    "gn:population":0,
    "gn:timezone":"Europe/Moscow",
    "iso:country":"RU",
    "name:eng_x_preferred":[
        "Chermnyye"
    ],
    "name:nor_x_preferred":[
        "Tsjermnye"
    ],
    "name:rus_x_preferred":[
        "\u0427\u0435\u0440\u043c\u043d\u044b\u0435"
    ],
    "name:und_x_variant":[
        "Cheremnoye",
        "Chermnoye",
        "Chernyye"
    ],
    "wof:name":"Chermnyye",
    "wof:placetype":"locality"
},
  "geometry": {"coordinates":[42.4876,54.4261],"type":"Point"}
}