{
  "type": "Feature",
  "properties": {
    "gn:admin1_code":"45.0",
    "gn:asciiname":"Malyy Kiner",
    "gn:country_code":"RU",
    "gn:dem":178,
    "gn:feature_class":"P",
    "gn:feature_code":"PPL",
    "gn:name":"Malyy Kiner",
    "gn:population":0,
    "gn:timezone":"Europe/Moscow",
    "iso:country":"RU",
    "name:rus_x_preferred":[
        "\u041c\u0430\u043b\u044b\u0439 \u041a\u0438\u043d\u0435\u0440"
    ],
    "wof:name":"Malyy Kiner",
    "wof:placetype":"locality"
},
  "geometry": {"coordinates":[49.77363,56.45274000000001],"type":"Point"}
}