{
  "type": "Feature",
  "properties": {
    "gn:admin1_code":"42",
    "gn:asciiname":"Malyy Sabsk",
    "gn:country_code":"RU",
    "gn:dem":33,
    "gn:feature_class":"P",
    "gn:feature_code":"PPL",
    "gn:name":"Malyy Sabsk",
    "gn:population":0,
    "gn:timezone":"Europe/Moscow",
    "iso:country":"RU",
    "name:nor_x_preferred":[
        "Malyj Sabsk"
    ],
    "name:rus_x_preferred":[
        "\u041c\u0430\u043b\u044b\u0439 \u0421\u0430\u0431\u0441\u043a"
    ],
    "wof:name":"Malyy Sabsk",
    "wof:placetype":"locality"
},
  "geometry": {"coordinates":[29.01528,59.13021],"type":"Point"}
}