{
  "type": "Feature",
  "properties": {
    "gn:admin1_code":"28",
    "gn:asciiname":"Verkhneolonetskiy",
    "gn:country_code":"RU",
    "gn:dem":146,
    "gn:feature_class":"P",
    "gn:feature_code":"PPL",
    "gn:name":"Verkhneolonetskiy",
    "gn:population":0,
    "gn:timezone":"Europe/Moscow",
    "iso:country":"RU",
    "name:fin_x_preferred":[
        "Vuorusj\u00e4rvi"
    ],
    "wof:name":"Verkhneolonetskiy",
    "wof:placetype":"locality"
},
  "geometry": {"coordinates":[33.25287,61.45846],"type":"Point"}
}