{
  "type": "Feature",
  "properties": {
    "gn:admin1_code":"34",
    "gn:asciiname":"Chum",
    "gn:country_code":"RU",
    "gn:dem":123,
    "gn:feature_class":"P",
    "gn:feature_code":"PPL",
    "gn:name":"Chum",
    "gn:population":0,
    "gn:timezone":"Europe/Moscow",
    "iso:country":"RU",
    "name:rus_x_preferred":[
        "\u0427\u0443\u043c"
    ],
    "name:und_x_variant":[
        "\u0427\u0443\u043c"
    ],
    "wof:name":"Chum",
    "wof:placetype":"locality"
},
  "geometry": {"coordinates":[63.16667,67.09999999999999],"type":"Point"}
}