{
  "type": "Feature",
  "properties": {
    "gn:country":"RU",
    "gn:fcode":"PPL",
    "gn:pop":0,
    "iso:country":"RU",
    "name:rus_x_preferred":[
        "\u041a\u0443\u043a\u0448\u0435\u0432\u043e"
    ],
    "name:unk_x_variant":[
        "Kukshevo"
    ],
    "qs:name":"Kushel\u00ebvo",
    "qs:name_adm0":"Russia",
    "qs:name_adm1":"Moscow Oblast",
    "qs:photos_9r":0,
    "qs:photos_sr":0,
    "qs:placetype":"Town",
    "qs:pop_sr":"0",
    "wof:name":"Kushel\u00ebvo",
    "wof:placetype":"locality",
    "wof:population":0
},
  "geometry": {"coordinates":[37.18352,55.49286],"type":"Point"}
}