{
  "type": "Feature",
  "properties": {
    "gn:admin1_code":"28",
    "gn:asciiname":"Konda",
    "gn:cc2":"RU",
    "gn:country_code":"RU",
    "gn:dem":170,
    "gn:feature_class":"P",
    "gn:feature_code":"PPL",
    "gn:name":"Konda",
    "gn:population":0,
    "gn:timezone":"Europe/Moscow",
    "iso:country":"RU",
    "name:ceb_x_preferred":[
        "Konda"
    ],
    "name:deu_x_preferred":[
        "Konda"
    ],
    "name:fin_x_preferred":[
        "Konta"
    ],
    "name:fra_x_preferred":[
        "Konda"
    ],
    "name:ita_x_preferred":[
        "Konda"
    ],
    "name:rus_x_preferred":[
        "\u041a\u043e\u043d\u0434\u0430"
    ],
    "name:swe_x_preferred":[
        "Konda"
    ],
    "wof:name":"Konda",
    "wof:placetype":"locality"
},
  "geometry": {"coordinates":[30.47831,65.53686],"type":"Point"}
}