{
  "type": "Feature",
  "properties": {
    "gn:admin1_code":"10",
    "gn:asciiname":"Lesnovka",
    "gn:country_code":"RU",
    "gn:dem":157,
    "gn:feature_class":"P",
    "gn:feature_code":"PPL",
    "gn:name":"Lesnovka",
    "gn:population":0,
    "gn:timezone":"Europe/Moscow",
    "iso:country":"RU",
    "name:rus_x_preferred":[
        "\u041b\u0435\u0441\u043d\u043e\u0432\u043a\u0430"
    ],
    "name:und_x_variant":[
        "Lesnaya"
    ],
    "wof:name":"Lesnovka",
    "wof:placetype":"locality"
},
  "geometry": {"coordinates":[32.04986,52.73376],"type":"Point"}
}