{
  "type": "Feature",
  "properties": {
    "gn:admin1_code":"90",
    "gn:asciiname":"Urada",
    "gn:country_code":"RU",
    "gn:dem":176,
    "gn:feature_class":"P",
    "gn:feature_code":"PPL",
    "gn:name":"Urada",
    "gn:population":0,
    "gn:timezone":"Asia/Yekaterinburg",
    "iso:country":"RU",
    "name:eng_x_preferred":[
        "Urada"
    ],
    "name:nor_x_preferred":[
        "Urada"
    ],
    "name:rus_x_preferred":[
        "\u0423\u0440\u0430\u0434\u0430"
    ],
    "wof:name":"Urada",
    "wof:placetype":"locality"
},
  "geometry": {"coordinates":[54.8701,56.4162],"type":"Point"}
}