{
  "type": "Feature",
  "properties": {
    "gn:admin1_code":"25.0",
    "gn:asciiname":"Gostizha",
    "gn:country_code":"RU",
    "gn:dem":218,
    "gn:feature_class":"P",
    "gn:feature_code":"PPL",
    "gn:name":"Gostizha",
    "gn:population":0,
    "gn:timezone":"Europe/Moscow",
    "iso:country":"RU",
    "name:rus_x_preferred":[
        "\u0413\u043e\u0441\u0442\u0438\u0436\u0430"
    ],
    "wof:name":"Gostizha",
    "wof:placetype":"locality"
},
  "geometry": {"coordinates":[34.73917,54.29306],"type":"Point"}
}