{
  "type": "Feature",
  "properties": {
    "gn:admin1_code":"16",
    "gn:asciiname":"Novoposelennaya Tayaba",
    "gn:country_code":"RU",
    "gn:dem":153,
    "gn:feature_class":"P",
    "gn:feature_code":"PPL",
    "gn:name":"Novoposel\u00ebnnaya Tayaba",
    "gn:population":0,
    "gn:timezone":"Europe/Moscow",
    "iso:country":"RU",
    "name:rus_x_preferred":[
        "\u041d\u043e\u0432\u043e\u043f\u043e\u0441\u0435\u043b\u0451\u043d\u043d\u0430\u044f \u0422\u0430\u044f\u0431\u0430"
    ],
    "name:und_x_variant":[
        "Novaya Toyaba",
        "Novo Poselok Toyaba",
        "Novoposel\u00ebnnaya Tayaba",
        "\u041d\u043e\u0432\u043e\u043f\u043e\u0441\u0435\u043b\u0451\u043d\u043d\u0430\u044f \u0422\u0430\u044f\u0431\u0430"
    ],
    "wof:name":"Novoposelennaya Tayaba",
    "wof:placetype":"locality"
},
  "geometry": {"coordinates":[47.99548,55.28346],"type":"Point"}
}