{
  "type": "Feature",
  "properties": {
    "gn:admin1_code":"4",
    "gn:asciiname":"Nizhnyaya Petrovka",
    "gn:country_code":"RU",
    "gn:dem":140,
    "gn:feature_class":"P",
    "gn:feature_code":"PPL",
    "gn:name":"Nizhnyaya Petrovka",
    "gn:population":0,
    "gn:timezone":"Asia/Barnaul",
    "iso:country":"RU",
    "name:rus_x_preferred":[
        "\u041d\u0438\u0436\u043d\u044f\u044f \u041f\u0435\u0442\u0440\u043e\u0432\u043a\u0430"
    ],
    "name:und_x_variant":[
        "Nizhne-Petrovskiy",
        "Nizhnyaya Petrovskiy",
        "Nizhnyaya Petrovka"
    ],
    "wof:name":"Nizhnyaya Petrovka",
    "wof:placetype":"locality"
},
  "geometry": {"coordinates":[83.8467,52.9139],"type":"Point"}
}