{
  "type": "Feature",
  "properties": {
    "gn:admin1_code":"56",
    "gn:asciiname":"Zarya",
    "gn:country_code":"RU",
    "gn:dem":225,
    "gn:feature_class":"P",
    "gn:feature_code":"PPL",
    "gn:name":"Zarya",
    "gn:population":0,
    "gn:timezone":"Europe/Moscow",
    "iso:country":"RU",
    "name:rus_x_preferred":[
        "\u0417\u0430\u0440\u044f"
    ],
    "name:und_x_variant":[
        "Tsurki",
        "Zarya",
        "\u0417\u0430\u0440\u044f"
    ],
    "wof:name":"Zarya",
    "wof:placetype":"locality"
},
  "geometry": {"coordinates":[36.58552,52.99413000000001],"type":"Point"}
}