{
  "type": "Feature",
  "properties": {
    "gn:admin1_code":"53",
    "gn:asciiname":"Urgun",
    "gn:country_code":"RU",
    "gn:dem":178,
    "gn:feature_class":"P",
    "gn:feature_code":"PPL",
    "gn:name":"Urgun",
    "gn:population":0,
    "gn:timezone":"Asia/Novosibirsk",
    "iso:country":"RU",
    "name:eng_x_preferred":[
        "Urgun"
    ],
    "name:nor_x_preferred":[
        "Urgun"
    ],
    "name:rus_x_preferred":[
        "\u0423\u0440\u0433\u0443\u043d"
    ],
    "wof:name":"Urgun",
    "wof:placetype":"locality"
},
  "geometry": {"coordinates":[83.4285,54.5051],"type":"Point"}
}