{
  "type": "Feature",
  "properties": {
    "gn:admin1_code":"25",
    "gn:asciiname":"Klenki",
    "gn:country_code":"RU",
    "gn:dem":186,
    "gn:feature_class":"P",
    "gn:feature_code":"PPL",
    "gn:name":"Klenki",
    "gn:population":0,
    "gn:timezone":"Europe/Moscow",
    "iso:country":"RU",
    "name:rus_x_preferred":[
        "\u041a\u043b\u0435\u043d\u043a\u0438"
    ],
    "wof:name":"Klenki",
    "wof:placetype":"locality"
},
  "geometry": {"coordinates":[34.56089,53.53438000000001],"type":"Point"}
}