{
  "type": "Feature",
  "properties": {
    "gn:admin1_code":"9.0",
    "gn:asciiname":"Yachnevo",
    "gn:country_code":"RU",
    "gn:dem":206,
    "gn:feature_class":"P",
    "gn:feature_code":"PPL",
    "gn:name":"Yachnevo",
    "gn:population":0,
    "gn:timezone":"Europe/Moscow",
    "iso:country":"RU",
    "name:rus_x_preferred":[
        "\u042f\u0447\u043d\u0435\u0432\u043e"
    ],
    "name:und_x_variant":[
        "Yachnev",
        "Yachnevo"
    ],
    "wof:name":"Yachnevo",
    "wof:placetype":"locality"
},
  "geometry": {"coordinates":[36.5794,50.63751],"type":"Point"}
}