{
  "type": "Feature",
  "properties": {
    "gn:admin1_code":"51",
    "gn:asciiname":"Chudikha",
    "gn:country_code":"RU",
    "gn:dem":117,
    "gn:feature_class":"P",
    "gn:feature_code":"PPL",
    "gn:name":"Chudikha",
    "gn:population":0,
    "gn:timezone":"Europe/Moscow",
    "iso:country":"RU",
    "name:rus_x_preferred":[
        "\u0427\u0443\u0434\u0438\u0445\u0430"
    ],
    "wof:name":"Chudikha",
    "wof:placetype":"locality"
},
  "geometry": {"coordinates":[45.5208,57.8975],"type":"Point"}
}