{
  "type": "Feature",
  "properties": {
    "gn:admin1_code":"33",
    "gn:asciiname":"Maloye Zabor'ye",
    "gn:country_code":"RU",
    "gn:dem":82,
    "gn:feature_class":"P",
    "gn:feature_code":"PPL",
    "gn:name":"Maloye Zabor\u2019ye",
    "gn:population":0,
    "gn:timezone":"Europe/Kirov",
    "iso:country":"RU",
    "name:rus_x_preferred":[
        "\u041c\u0430\u043b\u043e\u0435 \u0417\u0430\u0431\u043e\u0440\u044c\u0435"
    ],
    "name:und_x_variant":[
        "Maloye Zabor\u2019ye"
    ],
    "wof:name":"Maloye Zabor'ye",
    "wof:placetype":"locality"
},
  "geometry": {"coordinates":[47.5232,60.6585],"type":"Point"}
}