{
  "type": "Feature",
  "properties": {
    "gn:admin1_code":"33",
    "gn:asciiname":"Prislon",
    "gn:country_code":"RU",
    "gn:dem":101,
    "gn:feature_class":"P",
    "gn:feature_code":"PPL",
    "gn:name":"Prislon",
    "gn:population":0,
    "gn:timezone":"Europe/Kirov",
    "iso:country":"RU",
    "name:rus_x_preferred":[
        "\u041f\u0440\u0438\u0441\u043b\u043e\u043d"
    ],
    "wof:name":"Prislon",
    "wof:placetype":"locality"
},
  "geometry": {"coordinates":[47.0105,60.2959],"type":"Point"}
}