{
  "type": "Feature",
  "properties": {
    "gn:admin1_code":"55",
    "gn:asciiname":"Put' Lenina",
    "gn:country_code":"RU",
    "gn:dem":138,
    "gn:feature_class":"P",
    "gn:feature_code":"PPL",
    "gn:name":"Put\u2019 Lenina",
    "gn:population":0,
    "gn:timezone":"Asia/Yekaterinburg",
    "iso:country":"RU",
    "name:rus_x_preferred":[
        "\u041f\u0443\u0442\u044c \u041b\u0435\u043d\u0438\u043d\u0430"
    ],
    "name:und_x_variant":[
        "Put\u2019 Lenina"
    ],
    "wof:name":"Put' Lenina",
    "wof:placetype":"locality"
},
  "geometry": {"coordinates":[52.7683,53.6794],"type":"Point"}
}