{
  "type": "Feature",
  "properties": {
    "gn:admin1_code":"10",
    "gn:asciiname":"Gorchaki",
    "gn:country_code":"RU",
    "gn:dem":160,
    "gn:feature_class":"P",
    "gn:feature_code":"PPL",
    "gn:name":"Gorchaki",
    "gn:population":0,
    "gn:timezone":"Europe/Moscow",
    "iso:country":"RU",
    "name:bak_x_preferred":[
        "\u0413\u043e\u0440\u0447\u0430\u043a\u0438"
    ],
    "name:che_x_preferred":[
        "\u0413\u043e\u0440\u0447\u0430\u043a\u0438"
    ],
    "name:hye_x_preferred":[
        "\u0533\u0578\u0580\u0579\u0561\u056f\u056b"
    ],
    "name:kaz_x_preferred":[
        "\u0413\u043e\u0440\u0447\u0430\u043a\u0438"
    ],
    "name:kir_x_preferred":[
        "\u0413\u043e\u0440\u0447\u0430\u043a\u0438"
    ],
    "name:rus_x_preferred":[
        "\u0413\u043e\u0440\u0447\u0430\u043a\u0438"
    ],
    "name:tat_x_preferred":[
        "\u0413\u043e\u0440\u0447\u0430\u043a\u0438"
    ],
    "name:ukr_x_preferred":[
        "\u0413\u043e\u0440\u0447\u0430\u043a\u0438"
    ],
    "name:und_x_variant":[
        "\u0413\u043e\u0440\u0447\u0430\u043a\u0438"
    ],
    "wof:name":"Gorchaki",
    "wof:placetype":"locality"
},
  "geometry": {"coordinates":[32.45417,52.58889],"type":"Point"}
}