{
  "type": "Feature",
  "properties": {
    "gn:admin1_code":"52",
    "gn:asciiname":"Novyy Novosel",
    "gn:country_code":"RU",
    "gn:dem":68,
    "gn:feature_class":"P",
    "gn:feature_code":"PPL",
    "gn:name":"Novyy Novos\u00ebl",
    "gn:population":0,
    "gn:timezone":"Europe/Moscow",
    "iso:country":"RU",
    "name:eng_x_preferred":[
        "Novyy Novos\u00ebl"
    ],
    "name:nor_x_preferred":[
        "Nov.Novosel"
    ],
    "name:rus_x_preferred":[
        "\u041d\u043e\u0432.\u041d\u043e\u0432\u043e\u0441\u0435\u043b"
    ],
    "name:rus_x_variant":[
        "\u041d\u043e\u0432\u044b\u0439 \u041d\u043e\u0432\u043e\u0441\u0451\u043b"
    ],
    "name:und_x_variant":[
        "Novyy Novos\u00ebl"
    ],
    "wof:name":"Novyy Novosel",
    "wof:placetype":"locality"
},
  "geometry": {"coordinates":[32.2757,57.5078],"type":"Point"}
}