{
  "type": "Feature",
  "properties": {
    "gn:admin1_code":"51.0",
    "gn:asciiname":"Kalinki",
    "gn:country_code":"RU",
    "gn:dem":95,
    "gn:feature_class":"P",
    "gn:feature_code":"PPL",
    "gn:name":"Kalinki",
    "gn:population":0,
    "gn:timezone":"Europe/Moscow",
    "iso:country":"RU",
    "name:azb_x_preferred":[
        "\u06a9\u0627\u0644\u06cc\u0646\u06a9\u06cc"
    ],
    "name:fas_x_preferred":[
        "\u06a9\u0627\u0644\u06cc\u0646\u06a9\u06cc"
    ],
    "name:fra_x_preferred":[
        "Kalinki"
    ],
    "name:pol_x_preferred":[
        "Kalinki"
    ],
    "name:ukr_x_preferred":[
        "\u041a\u0430\u043b\u0456\u043d\u043a\u0456"
    ],
    "wof:name":"Kalinki",
    "wof:placetype":"locality"
},
  "geometry": {"coordinates":[43.6244,56.84767],"type":"Point"}
}