{
  "type": "Feature",
  "properties": {
    "gn:admin1_code":"8",
    "gn:asciiname":"Verkhniye Bishindy",
    "gn:country_code":"RU",
    "gn:dem":143,
    "gn:feature_class":"P",
    "gn:feature_code":"PPL",
    "gn:name":"Verkhniye Bishindy",
    "gn:population":0,
    "gn:timezone":"Asia/Yekaterinburg",
    "iso:country":"RU",
    "name:eng_x_preferred":[
        "Verkhniye Bishindy"
    ],
    "name:nor_x_preferred":[
        "Verkhnije Bisjindy"
    ],
    "name:rus_x_preferred":[
        "\u0412\u0435\u0440\u0445\u043d\u0438\u0435 \u0411\u0438\u0448\u0438\u043d\u0434\u044b"
    ],
    "wof:name":"Verkhniye Bishindy",
    "wof:placetype":"locality"
},
  "geometry": {"coordinates":[53.70623000000001,54.47749],"type":"Point"}
}