{
  "type": "Feature",
  "properties": {
    "gn:admin1_code":"4",
    "gn:asciiname":"Voskhod",
    "gn:country_code":"RU",
    "gn:dem":155,
    "gn:feature_class":"P",
    "gn:feature_code":"PPL",
    "gn:name":"Voskhod",
    "gn:population":0,
    "gn:timezone":"Asia/Barnaul",
    "iso:country":"RU",
    "name:rus_x_preferred":[
        "\u0412\u043e\u0441\u0445\u043e\u0434"
    ],
    "wof:name":"Voskhod",
    "wof:placetype":"locality"
},
  "geometry": {"coordinates":[84.27630000000001,53.9895],"type":"Point"}
}