{
  "type": "Feature",
  "properties": {
    "gn:admin1_code":"85",
    "gn:asciiname":"Popovka",
    "gn:cc2":"RU",
    "gn:country_code":"RU",
    "gn:dem":143,
    "gn:feature_class":"P",
    "gn:feature_code":"PPL",
    "gn:name":"Popovka",
    "gn:population":0,
    "gn:timezone":"Europe/Moscow",
    "iso:country":"RU",
    "name:ceb_x_preferred":[
        "Popovka"
    ],
    "name:est_x_preferred":[
        "Popovka"
    ],
    "name:rus_x_preferred":[
        "\u041f\u043e\u043f\u043e\u0432\u043a\u0430"
    ],
    "name:swe_x_preferred":[
        "Popovka"
    ],
    "name:und_x_variant":[
        "Pechen\u2019gskaya Popovka"
    ],
    "wof:name":"Popovka",
    "wof:placetype":"locality"
},
  "geometry": {"coordinates":[38.76667,60.63333000000001],"type":"Point"}
}