{
  "type": "Feature",
  "properties": {
    "gn:admin1_code":"88",
    "gn:asciiname":"Ramen'ye",
    "gn:country_code":"RU",
    "gn:dem":123,
    "gn:feature_class":"P",
    "gn:feature_code":"PPL",
    "gn:name":"Ramen\u2019ye",
    "gn:population":0,
    "gn:timezone":"Europe/Moscow",
    "iso:country":"RU",
    "name:rus_x_preferred":[
        "\u0420\u0430\u043c\u0435\u043d\u044c\u0435"
    ],
    "name:und_x_variant":[
        "Ramen\u2019ye",
        "Rameshki"
    ],
    "wof:name":"Ramen'ye",
    "wof:placetype":"locality"
},
  "geometry": {"coordinates":[38.5725,57.9742],"type":"Point"}
}