{
  "type": "Feature",
  "properties": {
    "gn:admin1_code":"37.0",
    "gn:asciiname":"Filisovo",
    "gn:country_code":"RU",
    "gn:dem":172,
    "gn:feature_class":"P",
    "gn:feature_code":"PPL",
    "gn:name":"Filisovo",
    "gn:population":0,
    "gn:timezone":"Europe/Moscow",
    "iso:country":"RU",
    "name:rus_x_preferred":[
        "\u0424\u0438\u043b\u0438\u0441\u043e\u0432\u043e"
    ],
    "name:und_x_variant":[
        "Filisova",
        "Filisovo"
    ],
    "wof:name":"Filisovo",
    "wof:placetype":"locality"
},
  "geometry": {"coordinates":[41.79976,57.85526],"type":"Point"}
}