{
  "type": "Feature",
  "properties": {
    "gn:admin1_code":"65",
    "gn:asciiname":"Neronovka",
    "gn:country_code":"RU",
    "gn:dem":45,
    "gn:feature_class":"P",
    "gn:feature_code":"PPL",
    "gn:name":"Neronovka",
    "gn:population":0,
    "gn:timezone":"Europe/Samara",
    "iso:country":"RU",
    "name:eng_x_preferred":[
        "Neronovka"
    ],
    "name:nor_x_preferred":[
        "Neronovka"
    ],
    "name:rus_x_preferred":[
        "\u041d\u0435\u0440\u043e\u043d\u043e\u0432\u043a\u0430"
    ],
    "wof:name":"Neronovka",
    "wof:placetype":"locality"
},
  "geometry": {"coordinates":[51.01915,53.87796],"type":"Point"}
}