{
  "type": "Feature",
  "properties": {
    "gn:admin1_code":"37",
    "gn:asciiname":"Malaya Izbenka",
    "gn:country_code":"RU",
    "gn:dem":202,
    "gn:feature_class":"P",
    "gn:feature_code":"PPL",
    "gn:name":"Malaya Izbenka",
    "gn:population":0,
    "gn:timezone":"Europe/Moscow",
    "iso:country":"RU",
    "name:rus_x_preferred":[
        "\u041c\u0430\u043b\u0430\u044f \u0418\u0437\u0431\u0435\u043d\u043a\u0430"
    ],
    "wof:name":"Malaya Izbenka",
    "wof:placetype":"locality"
},
  "geometry": {"coordinates":[45.133,58.8358],"type":"Point"}
}