{
  "type": "Feature",
  "properties": {
    "gn:admin1_code":"10.0",
    "gn:asciiname":"Dushatin",
    "gn:country_code":"RU",
    "gn:dem":164,
    "gn:feature_class":"P",
    "gn:feature_code":"PPL",
    "gn:name":"Dushatin",
    "gn:population":0,
    "gn:timezone":"Europe/Moscow",
    "iso:country":"RU",
    "name:eng_x_preferred":[
        "Dushatin"
    ],
    "name:nor_x_preferred":[
        "Dusjatino"
    ],
    "name:rus_x_preferred":[
        "\u0414\u0443\u0448\u0430\u0442\u0438\u043d\u043e"
    ],
    "name:rus_x_variant":[
        "\u0414\u0443\u0448\u0430\u0442\u0438\u043d"
    ],
    "wof:name":"Dushatin",
    "wof:placetype":"locality"
},
  "geometry": {"coordinates":[32.27370999999999,53.06666],"type":"Point"}
}