{
  "type": "Feature",
  "properties": {
    "gn:admin1_code":"61",
    "gn:asciiname":"Mikhaylovskiy",
    "gn:cc2":"RU",
    "gn:country_code":"RU",
    "gn:dem":57,
    "gn:feature_class":"P",
    "gn:feature_code":"PPL",
    "gn:name":"Mikhaylovskiy",
    "gn:population":0,
    "gn:timezone":"Europe/Moscow",
    "iso:country":"RU",
    "name:rus_x_preferred":[
        "\u041c\u0438\u0445\u0430\u0439\u043b\u043e\u0432\u0441\u043a\u0438\u0439"
    ],
    "name:und_x_variant":[
        "Mikhalevskiy",
        "Mikhaylevskiy",
        "Mikhaylovskiy",
        "\u041c\u0438\u0445\u0430\u0439\u043b\u043e\u0432\u0441\u043a\u0438\u0439"
    ],
    "wof:name":"Mikhaylovskiy",
    "wof:placetype":"locality"
},
  "geometry": {"coordinates":[41.53333,47.28333],"type":"Point"}
}