{
  "type": "Feature",
  "properties": {
    "gn:country":"RU",
    "gn:fcode":"PPL",
    "gn:pop":3709,
    "iso:country":"RU",
    "name:ceb_x_preferred":[
        "Iki-Burul"
    ],
    "name:che_x_preferred":[
        "\u0418\u043a\u0438-\u0411\u0443\u0440\u0443\u043b"
    ],
    "name:eng_x_preferred":[
        "Iki-Burul"
    ],
    "name:hsb_x_preferred":[
        "Iki-Burul"
    ],
    "name:hun_x_preferred":[
        "Iki-Burul"
    ],
    "name:mon_x_preferred":[
        "\u0418\u0445\u0431\u0443\u0443\u0440\u0430\u043b"
    ],
    "name:nor_x_preferred":[
        "Iki-Burul"
    ],
    "name:rus_x_preferred":[
        "\u0418\u043a\u0438-\u0411\u0443\u0440\u0443\u043b"
    ],
    "name:unk_x_variant":[
        "Chonin-Sala"
    ],
    "qs:name":"Iki-Burul",
    "qs:name_adm0":"Russia",
    "qs:name_adm1":"Kalmykia Republic",
    "qs:photos_9r":0,
    "qs:photos_sr":0,
    "qs:placetype":"Town",
    "qs:pop_sr":"4",
    "wd:wordcount":222,
    "wof:name":"Iki-Burul",
    "wof:placetype":"locality",
    "wof:population":3709
},
  "geometry": {"coordinates":[44.64722,45.82083],"type":"Point"}
}