{
  "type": "Feature",
  "properties": {
    "gn:admin1_code":"6.0",
    "gn:asciiname":"Khimicheskiy Les",
    "gn:country_code":"RU",
    "gn:dem":209,
    "gn:feature_class":"P",
    "gn:feature_code":"PPL",
    "gn:name":"Khimicheskiy Les",
    "gn:population":0,
    "gn:timezone":"Europe/Moscow",
    "iso:country":"RU",
    "name:rus_x_preferred":[
        "\u0425\u0438\u043c\u0438\u0447\u0435\u0441\u043a\u0438\u0439 \u041b\u0435\u0441"
    ],
    "wof:name":"Khimicheskiy Les",
    "wof:placetype":"locality"
},
  "geometry": {"coordinates":[40.2759,61.6671],"type":"Point"}
}