{
  "type": "Feature",
  "properties": {
    "gn:admin1_code":"17",
    "gn:admin2_code":"549104",
    "gn:asciiname":"Matlas",
    "gn:country_code":"RU",
    "gn:dem":1857,
    "gn:feature_class":"P",
    "gn:feature_code":"PPL",
    "gn:name":"Matlas",
    "gn:population":0,
    "gn:timezone":"Europe/Moscow",
    "iso:country":"RU",
    "name:rus_x_preferred":[
        "\u041c\u0430\u0442\u043b\u0430\u0441"
    ],
    "name:und_x_variant":[
        "\u041c\u0430\u0442\u043b\u0430\u0441"
    ],
    "wof:name":"Matlas",
    "wof:placetype":"locality"
},
  "geometry": {"coordinates":[46.60742,42.59471],"type":"Point"}
}