{
  "type": "Feature",
  "properties": {
    "gn:admin1_code":"45",
    "gn:asciiname":"Peredovik",
    "gn:country_code":"RU",
    "gn:dem":61,
    "gn:feature_class":"P",
    "gn:feature_code":"PPL",
    "gn:name":"Peredovik",
    "gn:population":0,
    "gn:timezone":"Europe/Moscow",
    "iso:country":"RU",
    "name:rus_x_preferred":[
        "\u041f\u0435\u0440\u0435\u0434\u043e\u0432\u0438\u043a"
    ],
    "wof:name":"Peredovik",
    "wof:placetype":"locality"
},
  "geometry": {"coordinates":[48.2945,55.9358],"type":"Point"}
}