{
  "type": "Feature",
  "properties": {
    "gn:admin1_code":"33.0",
    "gn:asciiname":"Vaseniny",
    "gn:country_code":"RU",
    "gn:dem":136,
    "gn:feature_class":"P",
    "gn:feature_code":"PPL",
    "gn:name":"Vaseniny",
    "gn:population":0,
    "gn:timezone":"Europe/Kirov",
    "iso:country":"RU",
    "name:rus_x_preferred":[
        "\u0412\u0430\u0441\u0451\u043d\u0438\u043d\u044b"
    ],
    "wof:name":"Vaseniny",
    "wof:placetype":"locality"
},
  "geometry": {"coordinates":[49.18013,58.81436],"type":"Point"}
}