{
  "type": "Feature",
  "properties": {
    "gn:admin1_code":"33",
    "gn:asciiname":"Red'kiny",
    "gn:country_code":"RU",
    "gn:dem":120,
    "gn:feature_class":"P",
    "gn:feature_code":"PPL",
    "gn:name":"Red\u2019kiny",
    "gn:population":0,
    "gn:timezone":"Europe/Kirov",
    "iso:country":"RU",
    "name:rus_x_preferred":[
        "\u0420\u0435\u0434\u044c\u043a\u0438\u043d\u044b"
    ],
    "name:und_x_variant":[
        "Red\u2019kiny",
        "Red\u2019kino"
    ],
    "wof:name":"Red'kiny",
    "wof:placetype":"locality"
},
  "geometry": {"coordinates":[49.7069,57.7162],"type":"Point"}
}