{
  "type": "Feature",
  "properties": {
    "gn:admin1_code":"15",
    "gn:asciiname":"Baimka",
    "gn:country_code":"RU",
    "gn:dem":519,
    "gn:feature_class":"P",
    "gn:feature_code":"PPL",
    "gn:name":"Baimka",
    "gn:population":0,
    "gn:timezone":"Asia/Anadyr",
    "iso:country":"RU",
    "name:nor_x_preferred":[
        "Baimka"
    ],
    "name:rus_x_preferred":[
        "\u0411\u0430\u0438\u043c\u043a\u0430"
    ],
    "wof:name":"Baimka",
    "wof:placetype":"locality"
},
  "geometry": {"coordinates":[164.58333000000005,66.48333000000001],"type":"Point"}
}