{
  "type": "Feature",
  "properties": {
    "gn:admin1_code":"56",
    "gn:asciiname":"Krasnoznamenets",
    "gn:country_code":"RU",
    "gn:dem":182,
    "gn:feature_class":"P",
    "gn:feature_code":"PPL",
    "gn:name":"Krasnoznamenets",
    "gn:population":0,
    "gn:timezone":"Europe/Moscow",
    "iso:country":"RU",
    "name:rus_x_preferred":[
        "\u041a\u0440\u0430\u0441\u043d\u043e\u0437\u043d\u0430\u043c\u0435\u043d\u0435\u0446"
    ],
    "name:und_x_variant":[
        "\u041a\u0440\u0430\u0441\u043d\u043e\u0437\u043d\u0430\u043c\u0435\u043d\u0435\u0446"
    ],
    "wof:name":"Krasnoznamenets",
    "wof:placetype":"locality"
},
  "geometry": {"coordinates":[35.48404,52.98558000000001],"type":"Point"}
}