{
  "type": "Feature",
  "properties": {
    "gn:admin1_code":"77",
    "gn:asciiname":"Zayevo",
    "gn:country_code":"RU",
    "gn:dem":246,
    "gn:feature_class":"P",
    "gn:feature_code":"PPL",
    "gn:name":"Zayevo",
    "gn:population":0,
    "gn:timezone":"Europe/Moscow",
    "iso:country":"RU",
    "name:eng_x_preferred":[
        "Zayevo"
    ],
    "name:nor_x_preferred":[
        "Zajevo"
    ],
    "name:rus_x_preferred":[
        "\u0417\u0430\u0435\u0432\u043e"
    ],
    "wof:name":"Zayevo",
    "wof:placetype":"locality"
},
  "geometry": {"coordinates":[32.75335,57.00136],"type":"Point"}
}