{
  "type": "Feature",
  "properties": {
    "gn:admin1_code":"47.0",
    "gn:asciiname":"Bogorodsk",
    "gn:country_code":"RU",
    "gn:dem":151,
    "gn:feature_class":"P",
    "gn:feature_code":"PPL",
    "gn:name":"Bogorodsk",
    "gn:population":0,
    "gn:timezone":"Europe/Moscow",
    "iso:country":"RU",
    "name:rus_x_preferred":[
        "\u0411\u043e\u0433\u043e\u0440\u043e\u0434\u0441\u043a"
    ],
    "name:sco_x_preferred":[
        "Bogorodsk"
    ],
    "wof:name":"Bogorodsk",
    "wof:placetype":"locality"
},
  "geometry": {"coordinates":[38.45,55.85],"type":"Point"}
}