{
  "type": "Feature",
  "properties": {
    "gn:admin1_code":"70",
    "gn:asciiname":"Kozhevnikov",
    "gn:country_code":"RU",
    "gn:dem":298,
    "gn:feature_class":"P",
    "gn:feature_code":"PPL",
    "gn:name":"Kozhevnikov",
    "gn:population":0,
    "gn:timezone":"Europe/Moscow",
    "iso:country":"RU",
    "name:rus_x_preferred":[
        "\u041a\u043e\u0436\u0435\u0432\u043d\u0438\u043a\u043e\u0432"
    ],
    "name:und_x_variant":[
        "\u041a\u043e\u0436\u0435\u0432\u043d\u0438\u043a\u043e\u0432"
    ],
    "wof:name":"Kozhevnikov",
    "wof:placetype":"locality"
},
  "geometry": {"coordinates":[42.15972,45.19028],"type":"Point"}
}