{
  "type": "Feature",
  "properties": {
    "gn:admin1_code":"9.0",
    "gn:asciiname":"Anpilovka",
    "gn:country_code":"RU",
    "gn:dem":124,
    "gn:feature_class":"P",
    "gn:feature_code":"PPL",
    "gn:name":"Anpilovka",
    "gn:population":0,
    "gn:timezone":"Europe/Moscow",
    "iso:country":"RU",
    "name:nor_x_preferred":[
        "Anpilovka"
    ],
    "name:rus_x_preferred":[
        "\u0410\u043d\u043f\u0438\u043b\u043e\u0432\u043a\u0430"
    ],
    "name:und_x_variant":[
        "Bor-Malyavinka",
        "Bor-Anpilovka"
    ],
    "wof:name":"Anpilovka",
    "wof:placetype":"locality"
},
  "geometry": {"coordinates":[37.8765,51.25899999999999],"type":"Point"}
}