{
  "type": "Feature",
  "properties": {
    "gn:admin1_code":"85",
    "gn:asciiname":"Logduz",
    "gn:country_code":"RU",
    "gn:dem":174,
    "gn:feature_class":"P",
    "gn:feature_code":"PPL",
    "gn:name":"Logduz",
    "gn:population":0,
    "gn:timezone":"Europe/Moscow",
    "iso:country":"RU",
    "name:eng_x_preferred":[
        "Logduz"
    ],
    "name:nor_x_preferred":[
        "Logduz"
    ],
    "name:rus_x_preferred":[
        "\u041b\u043e\u0433\u0434\u0443\u0437"
    ],
    "name:und_x_variant":[
        "Logdus",
        "\u041b\u043e\u0433\u0434\u0443\u0437",
        "Logduz"
    ],
    "wof:name":"Logduz",
    "wof:placetype":"locality"
},
  "geometry": {"coordinates":[44.72827,59.99407],"type":"Point"}
}