{
  "type": "Feature",
  "properties": {
    "gn:admin1_code":"86.0",
    "gn:asciiname":"Peski-Khar'kovskiye",
    "gn:country_code":"RU",
    "gn:dem":116,
    "gn:feature_class":"P",
    "gn:feature_code":"PPL",
    "gn:name":"Peski-Khar\u2019kovskiye",
    "gn:population":0,
    "gn:timezone":"Europe/Moscow",
    "iso:country":"RU",
    "wof:name":"Peski-Khar'kovskiye",
    "wof:placetype":"locality"
},
  "geometry": {"coordinates":[39.26933,50.94523],"type":"Point"}
}