{
  "type": "Feature",
  "properties": {
    "gn:admin1_code":"61",
    "gn:asciiname":"Samsonov",
    "gn:country_code":"RU",
    "gn:dem":112,
    "gn:feature_class":"P",
    "gn:feature_code":"PPL",
    "gn:name":"Samsonov",
    "gn:population":0,
    "gn:timezone":"Europe/Moscow",
    "iso:country":"RU",
    "name:rus_x_preferred":[
        "\u0421\u0430\u043c\u0441\u043e\u043d\u043e\u0432"
    ],
    "wof:name":"Samsonov",
    "wof:placetype":"locality"
},
  "geometry": {"coordinates":[41.0075,49.45028],"type":"Point"}
}