{
  "type": "Feature",
  "properties": {
    "gn:admin1_code":"60",
    "gn:asciiname":"Podel'no",
    "gn:country_code":"RU",
    "gn:dem":126,
    "gn:feature_class":"P",
    "gn:feature_code":"PPL",
    "gn:name":"Podel\u2019no",
    "gn:population":0,
    "gn:timezone":"Europe/Moscow",
    "iso:country":"RU",
    "name:rus_x_preferred":[
        "\u041f\u043e\u0434\u0435\u043b\u044c\u043d\u043e"
    ],
    "name:und_x_variant":[
        "Podel\u2019no",
        "\u041f\u043e\u0434\u0435\u043b\u044c\u043d\u043e"
    ],
    "wof:name":"Podel'no",
    "wof:placetype":"locality"
},
  "geometry": {"coordinates":[29.033,56.8138],"type":"Point"}
}