{
  "type": "Feature",
  "properties": {
    "gn:admin1_code":"33",
    "gn:asciiname":"Shumilovo",
    "gn:country_code":"RU",
    "gn:dem":158,
    "gn:feature_class":"P",
    "gn:feature_code":"PPL",
    "gn:name":"Shumilovo",
    "gn:population":0,
    "gn:timezone":"Europe/Kirov",
    "iso:country":"RU",
    "name:rus_x_preferred":[
        "\u0428\u0443\u043c\u0438\u043b\u043e\u0432\u043e"
    ],
    "wof:name":"Shumilovo",
    "wof:placetype":"locality"
},
  "geometry": {"coordinates":[49.3948,58.0557],"type":"Point"}
}