{
  "type": "Feature",
  "properties": {
    "gn:admin1_code":"52",
    "gn:asciiname":"Lyamtsino",
    "gn:country_code":"RU",
    "gn:dem":143,
    "gn:feature_class":"P",
    "gn:feature_code":"PPL",
    "gn:name":"Lyamtsino",
    "gn:population":0,
    "gn:timezone":"Europe/Moscow",
    "iso:country":"RU",
    "name:rus_x_preferred":[
        "\u041b\u044f\u043c\u0446\u0438\u043d\u043e"
    ],
    "wof:name":"Lyamtsino",
    "wof:placetype":"locality"
},
  "geometry": {"coordinates":[35.8417,58.48845],"type":"Point"}
}