{
  "type": "Feature",
  "properties": {
    "gn:admin1_code":"52",
    "gn:asciiname":"Lukinshchino",
    "gn:country_code":"RU",
    "gn:dem":28,
    "gn:feature_class":"P",
    "gn:feature_code":"PPL",
    "gn:name":"Lukinshchino",
    "gn:population":0,
    "gn:timezone":"Europe/Moscow",
    "iso:country":"RU",
    "name:rus_x_preferred":[
        "\u041b\u0443\u043a\u0438\u043d\u0449\u0438\u043d\u043e"
    ],
    "wof:name":"Lukinshchino",
    "wof:placetype":"locality"
},
  "geometry": {"coordinates":[31.18308,58.38656999999999],"type":"Point"}
}