{
  "type": "Feature",
  "properties": {
    "gn:admin1_code":"33",
    "gn:asciiname":"Sukhodol",
    "gn:country_code":"RU",
    "gn:dem":88,
    "gn:feature_class":"P",
    "gn:feature_code":"PPL",
    "gn:name":"Sukhodol",
    "gn:population":0,
    "gn:timezone":"Europe/Kirov",
    "iso:country":"RU",
    "name:rus_x_preferred":[
        "\u0421\u0443\u0445\u043e\u0434\u043e\u043b"
    ],
    "name:und_x_variant":[
        "\u0421\u0443\u0445\u043e\u0434\u043e\u043b"
    ],
    "wof:name":"Sukhodol",
    "wof:placetype":"locality"
},
  "geometry": {"coordinates":[48.61667,57.86666999999999],"type":"Point"}
}