{
  "type": "Feature",
  "properties": {
    "gn:admin1_code":"54",
    "gn:asciiname":"Lyubimovo",
    "gn:country_code":"RU",
    "gn:dem":73,
    "gn:feature_class":"P",
    "gn:feature_code":"PPL",
    "gn:name":"Lyubimovo",
    "gn:population":0,
    "gn:timezone":"Asia/Omsk",
    "iso:country":"RU",
    "name:rus_x_preferred":[
        "\u041b\u044e\u0431\u0438\u043c\u043e\u0432\u043e"
    ],
    "name:und_x_variant":[
        "\u041b\u044e\u0431\u0438\u043c\u043e\u0432\u043e"
    ],
    "wof:name":"Lyubimovo",
    "wof:placetype":"locality"
},
  "geometry": {"coordinates":[74.12430000000001,56.7039],"type":"Point"}
}