{
  "type": "Feature",
  "properties": {
    "gn:admin1_code":"60",
    "gn:asciiname":"Dymokor'ye",
    "gn:country_code":"RU",
    "gn:dem":72,
    "gn:feature_class":"P",
    "gn:feature_code":"PPL",
    "gn:name":"Dymokor\u2019ye",
    "gn:population":0,
    "gn:timezone":"Europe/Moscow",
    "iso:country":"RU",
    "name:rus_x_preferred":[
        "\u0414\u044b\u043c\u043e\u043a\u043e\u0440\u044c\u0435"
    ],
    "name:und_x_variant":[
        "Dymokar\u2019",
        "Dymokor\u2019ye"
    ],
    "wof:name":"Dymokor'ye",
    "wof:placetype":"locality"
},
  "geometry": {"coordinates":[28.15769,58.87729],"type":"Point"}
}