{
  "type": "Feature",
  "properties": {
    "gn:admin1_code":"76",
    "gn:asciiname":"Lutovinskiye Vyselki",
    "gn:country_code":"RU",
    "gn:dem":222,
    "gn:feature_class":"P",
    "gn:feature_code":"PPL",
    "gn:name":"Lutovinskiye Vyselki",
    "gn:population":0,
    "gn:timezone":"Europe/Moscow",
    "iso:country":"RU",
    "wof:name":"Lutovinskiye Vyselki",
    "wof:placetype":"locality"
},
  "geometry": {"coordinates":[37.75101,53.32715],"type":"Point"}
}