{
  "type": "Feature",
  "properties": {
    "gn:admin1_code":"84.0",
    "gn:asciiname":"Somovskiy",
    "gn:country_code":"RU",
    "gn:dem":84,
    "gn:feature_class":"P",
    "gn:feature_code":"PPL",
    "gn:name":"Somovskiy",
    "gn:population":0,
    "gn:timezone":"Europe/Volgograd",
    "iso:country":"RU",
    "name:rus_x_preferred":[
        "\u0421\u043e\u043c\u043e\u0432\u0441\u043a\u0438\u0439"
    ],
    "wof:name":"Somovskiy",
    "wof:placetype":"locality"
},
  "geometry": {"coordinates":[41.8696,51.0141],"type":"Point"}
}