{
  "type": "Feature",
  "properties": {
    "gn:admin1_code":"13",
    "gn:asciiname":"Repino",
    "gn:country_code":"RU",
    "gn:dem":219,
    "gn:feature_class":"P",
    "gn:feature_code":"PPL",
    "gn:name":"Repino",
    "gn:population":0,
    "gn:timezone":"Asia/Yekaterinburg",
    "iso:country":"RU",
    "name:eng_x_preferred":[
        "Repino"
    ],
    "name:nor_x_preferred":[
        "Repino"
    ],
    "name:rus_x_preferred":[
        "\u0420\u0435\u043f\u0438\u043d\u043e"
    ],
    "wof:name":"Repino",
    "wof:placetype":"locality"
},
  "geometry": {"coordinates":[61.06100000000001,54.2014],"type":"Point"}
}