{
  "type": "Feature",
  "properties": {
    "gn:admin1_code":"85",
    "gn:asciiname":"Zakharovskoye",
    "gn:country_code":"RU",
    "gn:dem":133,
    "gn:feature_class":"P",
    "gn:feature_code":"PPL",
    "gn:name":"Zakharovskoye",
    "gn:population":0,
    "gn:timezone":"Europe/Moscow",
    "iso:country":"RU",
    "name:rus_x_preferred":[
        "\u0417\u0430\u0445\u0430\u0440\u043e\u0432\u0441\u043a\u043e\u0435"
    ],
    "name:und_x_variant":[
        "\u0417\u0430\u0445\u0430\u0440\u043e\u0432\u0441\u043a\u043e\u0435"
    ],
    "wof:name":"Zakharovskoye",
    "wof:placetype":"locality"
},
  "geometry": {"coordinates":[36.3547,58.7736],"type":"Point"}
}