{
  "type": "Feature",
  "properties": {
    "gn:admin1_code":"46.0",
    "gn:asciiname":"Demina Polyana",
    "gn:country_code":"RU",
    "gn:dem":185,
    "gn:feature_class":"P",
    "gn:feature_code":"PPL",
    "gn:name":"D\u00ebmina Polyana",
    "gn:population":0,
    "gn:timezone":"Europe/Moscow",
    "iso:country":"RU",
    "name:rus_x_preferred":[
        "\u0414\u0451\u043c\u0438\u043d\u0430 \u041f\u043e\u043b\u044f\u043d\u0430"
    ],
    "name:und_x_variant":[
        "D\u00ebmina Polyana"
    ],
    "wof:name":"Demina Polyana",
    "wof:placetype":"locality"
},
  "geometry": {"coordinates":[44.15106,54.46563],"type":"Point"}
}