{
  "type": "Feature",
  "properties": {
    "gn:admin1_code":"60",
    "gn:asciiname":"Degtyari",
    "gn:country_code":"RU",
    "gn:dem":85,
    "gn:feature_class":"P",
    "gn:feature_code":"PPL",
    "gn:name":"Degtyari",
    "gn:population":0,
    "gn:timezone":"Europe/Moscow",
    "iso:country":"RU",
    "name:rus_x_preferred":[
        "\u0414\u0435\u0433\u0442\u044f\u0440\u0438"
    ],
    "wof:name":"Degtyari",
    "wof:placetype":"locality"
},
  "geometry": {"coordinates":[28.60119000000001,56.99333000000001],"type":"Point"}
}