{
  "type": "Feature",
  "properties": {
    "gn:admin1_code":"90",
    "gn:asciiname":"Severo-Vostochnyy",
    "gn:country_code":"RU",
    "gn:dem":356,
    "gn:feature_class":"P",
    "gn:feature_code":"PPL",
    "gn:name":"Severo-Vostochnyy",
    "gn:population":0,
    "gn:timezone":"Asia/Yekaterinburg",
    "iso:country":"RU",
    "name:rus_x_preferred":[
        "\u0421\u0435\u0432\u0435\u0440\u043e-\u0412\u043e\u0441\u0442\u043e\u0447\u043d\u044b\u0439"
    ],
    "wof:name":"Severo-Vostochnyy",
    "wof:placetype":"locality"
},
  "geometry": {"coordinates":[57.8532,58.57899999999999],"type":"Point"}
}