{
  "type": "Feature",
  "properties": {
    "gn:admin1_code":"72.0",
    "gn:asciiname":"Gay",
    "gn:country_code":"RU",
    "gn:dem":128,
    "gn:feature_class":"P",
    "gn:feature_code":"PPL",
    "gn:name":"Gay",
    "gn:population":0,
    "gn:timezone":"Europe/Moscow",
    "iso:country":"RU",
    "name:rus_x_preferred":[
        "\u0413\u0430\u0439"
    ],
    "name:und_x_variant":[
        "\u0413\u0430\u0439"
    ],
    "wof:name":"Gay",
    "wof:placetype":"locality"
},
  "geometry": {"coordinates":[41.43194,52.6575],"type":"Point"}
}