{
  "type": "Feature",
  "properties": {
    "gn:admin1_code":"47.0",
    "gn:asciiname":"Amerevo",
    "gn:country_code":"RU",
    "gn:dem":134,
    "gn:feature_class":"P",
    "gn:feature_code":"PPL",
    "gn:name":"Amerevo",
    "gn:population":0,
    "gn:timezone":"Europe/Moscow",
    "iso:country":"RU",
    "name:nor_x_preferred":[
        "Amerevo"
    ],
    "name:rus_x_preferred":[
        "\u0410\u043c\u0435\u0440\u0435\u0432\u043e"
    ],
    "name:und_x_variant":[
        "Amerovo"
    ],
    "wof:name":"Amerevo",
    "wof:placetype":"locality"
},
  "geometry": {"coordinates":[38.04647,55.91781999999999],"type":"Point"}
}