{
  "type": "Feature",
  "properties": {
    "gn:admin1_code":"8.0",
    "gn:asciiname":"Berlog",
    "gn:country_code":"RU",
    "gn:dem":263,
    "gn:feature_class":"P",
    "gn:feature_code":"PPL",
    "gn:name":"Berlog",
    "gn:population":0,
    "gn:timezone":"Asia/Yekaterinburg",
    "iso:country":"RU",
    "name:nor_x_preferred":[
        "Berlog"
    ],
    "name:rus_x_preferred":[
        "\u0411\u0435\u0440\u043b\u043e\u0433"
    ],
    "wof:name":"Berlog",
    "wof:placetype":"locality"
},
  "geometry": {"coordinates":[57.06667,55.78333000000001],"type":"Point"}
}