{
  "type": "Feature",
  "properties": {
    "gn:admin1_code":"64",
    "gn:asciiname":"Izvestkovyy",
    "gn:country_code":"RU",
    "gn:dem":300,
    "gn:feature_class":"P",
    "gn:feature_code":"PPL",
    "gn:name":"Izvestkovyy",
    "gn:population":0,
    "gn:timezone":"Asia/Sakhalin",
    "iso:country":"RU",
    "name:eng_x_preferred":[
        "Izvestkovyy"
    ],
    "name:nor_x_preferred":[
        "Izvestkovyj"
    ],
    "name:rus_x_preferred":[
        "\u0418\u0437\u0432\u0435\u0441\u0442\u043a\u043e\u0432\u044b\u0439"
    ],
    "name:und_x_variant":[
        "\u0418\u0437\u0432\u0435\u0441\u0442\u043a\u043e\u0432\u044b\u0439",
        "Izvestkovyy"
    ],
    "wof:name":"Izvestkovyy",
    "wof:placetype":"locality"
},
  "geometry": {"coordinates":[143.36667,49.95],"type":"Point"}
}