{
  "type": "Feature",
  "properties": {
    "gn:admin1_code":"81",
    "gn:asciiname":"Krasnyy Bor",
    "gn:country_code":"RU",
    "gn:dem":137,
    "gn:feature_class":"P",
    "gn:feature_code":"PPL",
    "gn:name":"Krasnyy Bor",
    "gn:population":0,
    "gn:timezone":"Europe/Ulyanovsk",
    "iso:country":"RU",
    "name:eng_x_preferred":[
        "Krasnyy Bor"
    ],
    "name:nor_x_preferred":[
        "Krasnyj Bor"
    ],
    "name:rus_x_preferred":[
        "\u041a\u0440\u0430\u0441\u043d\u044b\u0439 \u0411\u043e\u0440"
    ],
    "name:und_x_variant":[
        "\u041a\u0440\u0430\u0441\u043d\u044b\u0439 \u0411\u043e\u0440",
        "Krasnyy Bor"
    ],
    "wof:name":"Krasnyy Bor",
    "wof:placetype":"locality"
},
  "geometry": {"coordinates":[47.2461,54.0014],"type":"Point"}
}