{
  "type": "Feature",
  "properties": {
    "gn:admin1_code":"46.0",
    "gn:asciiname":"Zhdanovka",
    "gn:country_code":"RU",
    "gn:dem":205,
    "gn:feature_class":"P",
    "gn:feature_code":"PPL",
    "gn:name":"Zhdanovka",
    "gn:population":0,
    "gn:timezone":"Europe/Moscow",
    "iso:country":"RU",
    "name:rus_x_preferred":[
        "\u0416\u0434\u0430\u043d\u043e\u0432\u043a\u0430"
    ],
    "wof:name":"Zhdanovka",
    "wof:placetype":"locality"
},
  "geometry": {"coordinates":[44.8515,54.24357],"type":"Point"}
}