{
  "type": "Feature",
  "properties": {
    "gn:admin1_code":"57",
    "gn:asciiname":"Macha-Anuchino",
    "gn:country_code":"RU",
    "gn:dem":204,
    "gn:feature_class":"P",
    "gn:feature_code":"PPL",
    "gn:name":"Macha-Anuchino",
    "gn:population":0,
    "gn:timezone":"Europe/Moscow",
    "iso:country":"RU",
    "name:rus_x_preferred":[
        "\u041c\u0430\u0447\u0430-\u0410\u043d\u0443\u0447\u0438\u043d\u043e"
    ],
    "name:und_x_variant":[
        "Macha-Onuchino",
        "Macha-Anuchino",
        "\u041c\u0430\u0447\u0430-\u0410\u043d\u0443\u0447\u0438\u043d\u043e"
    ],
    "wof:name":"Macha-Anuchino",
    "wof:placetype":"locality"
},
  "geometry": {"coordinates":[43.59481,52.65189],"type":"Point"}
}