{
  "type": "Feature",
  "properties": {
    "gn:admin1_code":"41.0",
    "gn:asciiname":"Bavykino",
    "gn:country_code":"RU",
    "gn:dem":162,
    "gn:feature_class":"P",
    "gn:feature_code":"PPL",
    "gn:name":"Bavykino",
    "gn:population":0,
    "gn:timezone":"Europe/Moscow",
    "iso:country":"RU",
    "name:nor_x_preferred":[
        "Balykino"
    ],
    "name:rus_x_preferred":[
        "\u0411\u0430\u0432\u044b\u043a\u0438\u043d\u043e"
    ],
    "name:und_x_variant":[
        "Bavykino"
    ],
    "wof:name":"Bavykino",
    "wof:placetype":"locality"
},
  "geometry": {"coordinates":[36.25413,51.17652],"type":"Point"}
}