{
  "type": "Feature",
  "properties": {
    "gn:admin1_code":"21.0",
    "gn:asciiname":"Shestakovo",
    "gn:country_code":"RU",
    "gn:dem":115,
    "gn:feature_class":"P",
    "gn:feature_code":"PPL",
    "gn:name":"Shestakovo",
    "gn:population":0,
    "gn:timezone":"Europe/Moscow",
    "iso:country":"RU",
    "name:che_x_preferred":[
        "\u0428\u0435\u0441\u0442\u0430\u043a\u043e\u0432\u043e"
    ],
    "name:hye_x_preferred":[
        "\u0547\u0565\u057d\u057f\u0561\u056f\u0578\u057e\u0578"
    ],
    "name:ita_x_preferred":[
        "\u0160estakovo"
    ],
    "name:nor_x_preferred":[
        "Sjestakovo"
    ],
    "name:rus_x_preferred":[
        "\u0428\u0435\u0441\u0442\u0430\u043a\u043e\u0432\u043e"
    ],
    "wof:name":"Shestakovo",
    "wof:placetype":"locality"
},
  "geometry": {"coordinates":[42.65088,56.67568000000001],"type":"Point"}
}