{
  "type": "Feature",
  "properties": {
    "gn:admin1_code":"80",
    "gn:asciiname":"Yuldyr'",
    "gn:country_code":"RU",
    "gn:dem":217,
    "gn:feature_class":"P",
    "gn:feature_code":"PPL",
    "gn:name":"Yuldyr\u2019",
    "gn:population":0,
    "gn:timezone":"Europe/Samara",
    "iso:country":"RU",
    "name:eng_x_preferred":[
        "Yuldyr'"
    ],
    "name:nor_x_preferred":[
        "Juldyr"
    ],
    "name:rus_x_preferred":[
        "\u042e\u043b\u0434\u044b\u0440\u044c"
    ],
    "name:und_x_variant":[
        "Yuldyr\u2019"
    ],
    "wof:name":"Yuldyr'",
    "wof:placetype":"locality"
},
  "geometry": {"coordinates":[53.43333000000001,58.08333],"type":"Point"}
}