{
  "type": "Feature",
  "properties": {
    "gn:admin1_code":"51",
    "gn:asciiname":"Yaz",
    "gn:country_code":"RU",
    "gn:dem":151,
    "gn:feature_class":"P",
    "gn:feature_code":"PPL",
    "gn:name":"Yaz",
    "gn:population":0,
    "gn:timezone":"Europe/Moscow",
    "iso:country":"RU",
    "name:eng_x_preferred":[
        "Yaz"
    ],
    "name:nor_x_preferred":[
        "Jaz"
    ],
    "name:rus_x_preferred":[
        "\u042f\u0437"
    ],
    "name:und_x_variant":[
        "\u042f\u0437"
    ],
    "wof:name":"Yaz",
    "wof:placetype":"locality"
},
  "geometry": {"coordinates":[45.21437,54.89341],"type":"Point"}
}