{
  "type": "Feature",
  "properties": {
    "gn:admin1_code":"11",
    "gn:asciiname":"Tokhoy",
    "gn:country_code":"RU",
    "gn:dem":635,
    "gn:feature_class":"P",
    "gn:feature_code":"PPL",
    "gn:name":"Tokhoy",
    "gn:population":0,
    "gn:timezone":"Asia/Irkutsk",
    "iso:country":"RU",
    "name:eng_x_preferred":[
        "Tokhoy"
    ],
    "name:nor_x_preferred":[
        "Tokhoj"
    ],
    "name:rus_x_preferred":[
        "\u0422\u043e\u0445\u043e\u0439"
    ],
    "name:und_x_variant":[
        "Tologoy",
        "Takhoy Settlement",
        "Ulus Takhoy",
        "Takhoy",
        "Ulus Tulum"
    ],
    "wof:name":"Tokhoy",
    "wof:placetype":"locality"
},
  "geometry": {"coordinates":[106.61351000000001,51.36784],"type":"Point"}
}