{
  "type": "Feature",
  "properties": {
    "gn:admin1_code":"63",
    "gn:asciiname":"Ulakhan-Tala",
    "gn:country_code":"RU",
    "gn:dem":210,
    "gn:feature_class":"P",
    "gn:feature_code":"PPL",
    "gn:name":"Ulakhan-Tala",
    "gn:population":0,
    "gn:timezone":"Asia/Vladivostok",
    "iso:country":"RU",
    "wof:name":"Ulakhan-Tala",
    "wof:placetype":"locality"
},
  "geometry": {"coordinates":[135.92622,67.29078],"type":"Point"}
}