{
  "type": "Feature",
  "properties": {
    "gn:admin1_code":"72",
    "gn:asciiname":"Kriusha",
    "gn:country_code":"RU",
    "gn:dem":156,
    "gn:feature_class":"P",
    "gn:feature_code":"PPL",
    "gn:name":"Kriusha",
    "gn:population":0,
    "gn:timezone":"Europe/Moscow",
    "iso:country":"RU",
    "name:rus_x_preferred":[
        "\u041a\u0440\u0438\u0443\u0448\u0430"
    ],
    "name:und_x_variant":[
        "Krivusha",
        "Kriusha",
        "\u041a\u0440\u0438\u0443\u0448\u0430"
    ],
    "wof:name":"Kriusha",
    "wof:placetype":"locality"
},
  "geometry": {"coordinates":[40.8623,52.49800000000001],"type":"Point"}
}