{
  "type": "Feature",
  "properties": {
    "gn:admin1_code":"84.0",
    "gn:asciiname":"Shutovka",
    "gn:country_code":"RU",
    "gn:dem":-10,
    "gn:feature_class":"P",
    "gn:feature_code":"PPL",
    "gn:name":"Shutovka",
    "gn:population":0,
    "gn:timezone":"Europe/Volgograd",
    "iso:country":"RU",
    "wof:name":"Shutovka",
    "wof:placetype":"locality"
},
  "geometry": {"coordinates":[44.72472,48.55417],"type":"Point"}
}