{
  "type": "Feature",
  "properties": {
    "gn:admin1_code":"65",
    "gn:asciiname":"Ul'yanovskiy",
    "gn:country_code":"RU",
    "gn:dem":126,
    "gn:feature_class":"P",
    "gn:feature_code":"PPL",
    "gn:name":"Ul\u2019yanovskiy",
    "gn:population":0,
    "gn:timezone":"Europe/Samara",
    "iso:country":"RU",
    "name:rus_x_preferred":[
        "Ul\u2019yanovskiy"
    ],
    "name:rus_x_variant":[
        "\u0423\u043b\u044c\u044f\u043d\u043e\u0432\u0441\u043a\u0438\u0439",
        "Ul\u2019yanovets"
    ],
    "wof:name":"Ul'yanovskiy",
    "wof:placetype":"locality"
},
  "geometry": {"coordinates":[48.9278,53.3676],"type":"Point"}
}