{
  "type": "Feature",
  "properties": {
    "gn:admin1_code":"20",
    "gn:asciiname":"Malyshevka",
    "gn:country_code":"RU",
    "gn:dem":419,
    "gn:feature_class":"P",
    "gn:feature_code":"PPL",
    "gn:name":"Malyshevka",
    "gn:population":0,
    "gn:timezone":"Asia/Irkutsk",
    "iso:country":"RU",
    "name:eng_x_preferred":[
        "Malyshevka"
    ],
    "name:nor_x_preferred":[
        "Malysjevka"
    ],
    "name:rus_x_preferred":[
        "\u041c\u0430\u043b\u044b\u0448\u0435\u0432\u043a\u0430"
    ],
    "name:und_x_variant":[
        "Malyshevskoye"
    ],
    "wof:name":"Malyshevka",
    "wof:placetype":"locality"
},
  "geometry": {"coordinates":[103.3875,53.7375],"type":"Point"}
}