{
  "type": "Feature",
  "properties": {
    "gn:admin1_code":"40",
    "gn:asciiname":"Ural'tsevskoye",
    "gn:country_code":"RU",
    "gn:dem":147,
    "gn:feature_class":"P",
    "gn:feature_code":"PPL",
    "gn:name":"Ural\u2019tsevskoye",
    "gn:population":0,
    "gn:timezone":"Asia/Yekaterinburg",
    "iso:country":"RU",
    "name:eng_x_preferred":[
        "Ural'tsevskoye"
    ],
    "name:nor_x_preferred":[
        "Uraltsevskoje"
    ],
    "name:rus_x_preferred":[
        "\u0423\u0440\u0430\u043b\u044c\u0446\u0435\u0432\u0441\u043a\u043e\u0435"
    ],
    "name:und_x_variant":[
        "Uralets",
        "Ural\u2019tsevskoye"
    ],
    "wof:name":"Ural'tsevskoye",
    "wof:placetype":"locality"
},
  "geometry": {"coordinates":[63.1133,56.4218],"type":"Point"}
}