{
  "type": "Feature",
  "properties": {
    "gn:admin1_code":"10",
    "gn:asciiname":"Staropochep'ye",
    "gn:country_code":"RU",
    "gn:dem":182,
    "gn:feature_class":"P",
    "gn:feature_code":"PPL",
    "gn:name":"Staropochep\u2019ye",
    "gn:population":0,
    "gn:timezone":"Europe/Moscow",
    "iso:country":"RU",
    "name:eng_x_preferred":[
        "Staropochep'ye"
    ],
    "name:nor_x_preferred":[
        "Staropotsjelje"
    ],
    "name:rus_x_preferred":[
        "\u0421\u0442\u0430\u0440\u043e\u043f\u043e\u0447\u0435\u043b\u044c\u0435"
    ],
    "name:rus_x_variant":[
        "\u0421\u0442\u0430\u0440\u043e\u043f\u043e\u0447\u0435\u043f\u044c\u0435"
    ],
    "name:und_x_variant":[
        "Staropochep\u2019ye",
        "\u0421\u0442\u0430\u0440\u043e\u043f\u043e\u0447\u0435\u043f\u044c\u0435"
    ],
    "wof:name":"Staropochep'ye",
    "wof:placetype":"locality"
},
  "geometry": {"coordinates":[33.27642,52.98622],"type":"Point"}
}