{
  "type": "Feature",
  "properties": {
    "gn:admin1_code":"75",
    "gn:asciiname":"Tailashevka",
    "gn:country_code":"RU",
    "gn:dem":119,
    "gn:feature_class":"P",
    "gn:feature_code":"PPL",
    "gn:name":"Tailash\u00ebvka",
    "gn:population":0,
    "gn:timezone":"Asia/Tomsk",
    "iso:country":"RU",
    "wof:name":"Tailashevka",
    "wof:placetype":"locality"
},
  "geometry": {"coordinates":[83.61667,57.23333],"type":"Point"}
}