{
  "type": "Feature",
  "properties": {
    "gn:admin1_code":"60",
    "gn:asciiname":"Mazikha",
    "gn:country_code":"RU",
    "gn:dem":65,
    "gn:feature_class":"P",
    "gn:feature_code":"PPL",
    "gn:name":"Mazikha",
    "gn:population":0,
    "gn:timezone":"Europe/Moscow",
    "iso:country":"RU",
    "name:eng_x_preferred":[
        "Mar'insko"
    ],
    "name:nor_x_preferred":[
        "Marinsko"
    ],
    "name:rus_x_preferred":[
        "\u041c\u0430\u0440\u044c\u0438\u043d\u0441\u043a\u043e"
    ],
    "name:rus_x_variant":[
        "\u041c\u0430\u0437\u0438\u0445\u0430"
    ],
    "name:und_x_variant":[
        "\u041c\u0430\u0440\u044c\u0438\u043d\u0441\u043a\u043e",
        "Mar\u2019insko",
        "Mazikha"
    ],
    "wof:name":"Mazikha",
    "wof:placetype":"locality"
},
  "geometry": {"coordinates":[28.04846,58.74071],"type":"Point"}
}