{
  "type": "Feature",
  "properties": {
    "gn:admin1_code":"88",
    "gn:asciiname":"Motylevo",
    "gn:country_code":"RU",
    "gn:dem":159,
    "gn:feature_class":"P",
    "gn:feature_code":"PPL",
    "gn:name":"Motyl\u00ebvo",
    "gn:population":0,
    "gn:timezone":"Europe/Moscow",
    "iso:country":"RU",
    "name:rus_x_preferred":[
        "\u041c\u043e\u0442\u044b\u043b\u0451\u0432\u043e"
    ],
    "name:und_x_variant":[
        "Motyl\u00ebvo"
    ],
    "wof:name":"Motylevo",
    "wof:placetype":"locality"
},
  "geometry": {"coordinates":[39.7594,57.859],"type":"Point"}
}