{
  "type": "Feature",
  "properties": {
    "gn:admin1_code":"52",
    "gn:asciiname":"Soson'ye",
    "gn:country_code":"RU",
    "gn:dem":157,
    "gn:feature_class":"P",
    "gn:feature_code":"PPL",
    "gn:name":"Soson\u2019ye",
    "gn:population":0,
    "gn:timezone":"Europe/Moscow",
    "iso:country":"RU",
    "name:rus_x_preferred":[
        "\u0421\u043e\u0441\u043e\u043d\u044c\u0435"
    ],
    "name:und_x_variant":[
        "Soson\u2019ye",
        "\u0421\u043e\u0441\u043e\u043d\u044c\u0435"
    ],
    "wof:name":"Soson'ye",
    "wof:placetype":"locality"
},
  "geometry": {"coordinates":[34.83333,58.98333],"type":"Point"}
}