{
  "type": "Feature",
  "properties": {
    "gn:admin1_code":"45.0",
    "gn:asciiname":"Yakaysurt",
    "gn:country_code":"RU",
    "gn:dem":169,
    "gn:feature_class":"P",
    "gn:feature_code":"PPL",
    "gn:name":"Yakaysurt",
    "gn:population":0,
    "gn:timezone":"Europe/Moscow",
    "iso:country":"RU",
    "name:rus_x_preferred":[
        "\u042f\u043a\u0430\u0439\u0441\u0443\u0440\u0442"
    ],
    "wof:name":"Yakaysurt",
    "wof:placetype":"locality"
},
  "geometry": {"coordinates":[48.90972,56.8225],"type":"Point"}
}