{
  "type": "Feature",
  "properties": {
    "gn:admin1_code":"91",
    "gn:asciiname":"Georgiyevka",
    "gn:country_code":"RU",
    "gn:dem":206,
    "gn:feature_class":"P",
    "gn:feature_code":"PPL",
    "gn:name":"Georgiyevka",
    "gn:population":0,
    "gn:timezone":"Asia/Krasnoyarsk",
    "iso:country":"RU",
    "name:eng_x_preferred":[
        "Georgiyevka"
    ],
    "name:nor_x_preferred":[
        "Georgijevka"
    ],
    "name:rus_x_preferred":[
        "\u0413\u0435\u043e\u0440\u0433\u0438\u0435\u0432\u043a\u0430"
    ],
    "wof:name":"Georgiyevka",
    "wof:placetype":"locality"
},
  "geometry": {"coordinates":[89.34555999999998,56.39361],"type":"Point"}
}