{
  "type": "Feature",
  "properties": {
    "gn:admin1_code":"1.0",
    "gn:asciiname":"Bulavimov",
    "gn:country_code":"RU",
    "gn:dem":237,
    "gn:feature_class":"P",
    "gn:feature_code":"PPL",
    "gn:name":"Bulavimov",
    "gn:population":0,
    "gn:timezone":"Europe/Moscow",
    "iso:country":"RU",
    "name:rus_x_preferred":[
        "\u0411\u0443\u043b\u0430\u0432\u0438\u043c\u043e\u0432"
    ],
    "wof:name":"Bulavimov",
    "wof:placetype":"locality"
},
  "geometry": {"coordinates":[40.20222,44.7025],"type":"Point"}
}