{
  "type": "Feature",
  "properties": {
    "gn:admin1_code":"83.0",
    "gn:asciiname":"Suromna",
    "gn:country_code":"RU",
    "gn:dem":141,
    "gn:feature_class":"P",
    "gn:feature_code":"PPL",
    "gn:name":"Suromna",
    "gn:population":0,
    "gn:timezone":"Europe/Moscow",
    "iso:country":"RU",
    "name:rus_x_preferred":[
        "\u0421\u0443\u0440\u043e\u043c\u043d\u0430"
    ],
    "wof:name":"Suromna",
    "wof:placetype":"locality"
},
  "geometry": {"coordinates":[40.49033,56.19214],"type":"Point"}
}