{
  "type": "Feature",
  "properties": {
    "gn:admin1_code":"91",
    "gn:asciiname":"Temra",
    "gn:country_code":"RU",
    "gn:dem":380,
    "gn:feature_class":"P",
    "gn:feature_code":"PPL",
    "gn:name":"Temra",
    "gn:population":0,
    "gn:timezone":"Asia/Krasnoyarsk",
    "iso:country":"RU",
    "name:eng_x_preferred":[
        "Temra"
    ],
    "name:nor_x_preferred":[
        "Temra"
    ],
    "name:rus_x_preferred":[
        "\u0422\u0435\u043c\u0440\u0430"
    ],
    "wof:name":"Temra",
    "wof:placetype":"locality"
},
  "geometry": {"coordinates":[89.27143000000002,55.43617],"type":"Point"}
}