{
  "type": "Feature",
  "properties": {
    "gn:admin1_code":"6.0",
    "gn:asciiname":"Vagino-Navolok",
    "gn:country_code":"RU",
    "gn:dem":-9999,
    "gn:feature_class":"P",
    "gn:feature_code":"PPL",
    "gn:name":"Vagino-Navolok",
    "gn:population":0,
    "gn:timezone":"Europe/Moscow",
    "iso:country":"RU",
    "name:rus_x_preferred":[
        "\u0412\u0430\u0433\u0438\u043d\u043e-\u041d\u0430\u0432\u043e\u043b\u043e\u043a"
    ],
    "wof:name":"Vagino-Navolok",
    "wof:placetype":"locality"
},
  "geometry": {"coordinates":[40.2787,64.5779],"type":"Point"}
}