{
  "type": "Feature",
  "properties": {
    "gn:admin1_code":"60.0",
    "gn:asciiname":"Borovichi",
    "gn:country_code":"RU",
    "gn:dem":103,
    "gn:feature_class":"P",
    "gn:feature_code":"PPL",
    "gn:name":"Borovichi",
    "gn:population":0,
    "gn:timezone":"Europe/Moscow",
    "iso:country":"RU",
    "name:rus_x_preferred":[
        "\u0411\u043e\u0440\u043e\u0432\u0438\u0447\u0438"
    ],
    "name:und_x_variant":[
        "\u0411\u043e\u0440\u043e\u0432\u0438\u0447\u0438"
    ],
    "wof:name":"Borovichi",
    "wof:placetype":"locality"
},
  "geometry": {"coordinates":[30.13362,57.13818000000001],"type":"Point"}
}