{
  "type": "Feature",
  "properties": {
    "gn:admin1_code":"67.0",
    "gn:asciiname":"Prichernavskaya",
    "gn:country_code":"RU",
    "gn:dem":137,
    "gn:feature_class":"P",
    "gn:feature_code":"PPL",
    "gn:name":"Prichernavskaya",
    "gn:population":0,
    "gn:timezone":"Europe/Saratov",
    "iso:country":"RU",
    "wof:name":"Prichernavskaya",
    "wof:placetype":"locality"
},
  "geometry": {"coordinates":[47.13979000000001,52.14031],"type":"Point"}
}