{
  "type": "Feature",
  "properties": {
    "gn:admin1_code":"75",
    "gn:asciiname":"Yarovoye",
    "gn:cc2":"RU",
    "gn:country_code":"RU",
    "gn:dem":107,
    "gn:feature_class":"P",
    "gn:feature_code":"PPL",
    "gn:name":"Yarovoye",
    "gn:population":0,
    "gn:timezone":"Asia/Tomsk",
    "iso:country":"RU",
    "name:und_x_variant":[
        "Yarovoy",
        "Yarovoye"
    ],
    "wof:name":"Yarovoye",
    "wof:placetype":"locality"
},
  "geometry": {"coordinates":[79.56667,57.53333000000001],"type":"Point"}
}