{
  "type": "Feature",
  "properties": {
    "gn:admin1_code":"77",
    "gn:asciiname":"Glubochitsa",
    "gn:country_code":"RU",
    "gn:dem":212,
    "gn:feature_class":"P",
    "gn:feature_code":"PPL",
    "gn:name":"Glubochitsa",
    "gn:population":0,
    "gn:timezone":"Europe/Moscow",
    "iso:country":"RU",
    "name:rus_x_preferred":[
        "\u0413\u043b\u0443\u0431\u043e\u0447\u0438\u0446\u0430"
    ],
    "wof:name":"Glubochitsa",
    "wof:placetype":"locality"
},
  "geometry": {"coordinates":[33.15002,57.23972],"type":"Point"}
}