{
  "type": "Feature",
  "properties": {
    "gn:admin1_code":"11",
    "gn:asciiname":"Dubinino",
    "gn:country_code":"RU",
    "gn:dem":469,
    "gn:feature_class":"P",
    "gn:feature_code":"PPL",
    "gn:name":"Dubinino",
    "gn:population":0,
    "gn:timezone":"Asia/Irkutsk",
    "iso:country":"RU",
    "name:eng_x_preferred":[
        "Dubinino"
    ],
    "name:hye_x_preferred":[
        "\u0534\u0578\u0582\u0562\u056b\u0576\u056b\u0576\u0578"
    ],
    "name:nor_x_preferred":[
        "Dubinino"
    ],
    "name:rus_x_preferred":[
        "\u0414\u0443\u0431\u0438\u043d\u0438\u043d\u043e"
    ],
    "name:ukr_x_preferred":[
        "\u0414\u0443\u0431\u0456\u043d\u0456\u043d\u043e"
    ],
    "name:und_x_variant":[
        "\u0414\u0443\u0431\u0438\u043d\u0438\u043d\u043e",
        "Dubinino"
    ],
    "wof:name":"Dubinino",
    "wof:placetype":"locality"
},
  "geometry": {"coordinates":[106.76416999999999,52.29722],"type":"Point"}
}