{
  "type": "Feature",
  "properties": {
    "gn:admin1_code":"52",
    "gn:asciiname":"Krasnaya Zarya",
    "gn:country_code":"RU",
    "gn:dem":126,
    "gn:feature_class":"P",
    "gn:feature_code":"PPL",
    "gn:name":"Krasnaya Zarya",
    "gn:population":0,
    "gn:timezone":"Europe/Moscow",
    "iso:country":"RU",
    "name:rus_x_preferred":[
        "\u041a\u0440\u0430\u0441\u043d\u0430\u044f \u0417\u0430\u0440\u044f"
    ],
    "name:und_x_variant":[
        "Durmany",
        "Durman",
        "Krasnaya Zarya",
        "\u041a\u0440\u0430\u0441\u043d\u0430\u044f \u0417\u0430\u0440\u044f"
    ],
    "wof:name":"Krasnaya Zarya",
    "wof:placetype":"locality"
},
  "geometry": {"coordinates":[35.72904000000001,58.60949],"type":"Point"}
}