{
  "type": "Feature",
  "properties": {
    "gn:admin1_code":"53",
    "gn:asciiname":"Shchelchikha",
    "gn:country_code":"RU",
    "gn:dem":107,
    "gn:feature_class":"P",
    "gn:feature_code":"PPL",
    "gn:name":"Shchelchikha",
    "gn:population":0,
    "gn:timezone":"Asia/Novosibirsk",
    "iso:country":"RU",
    "name:eng_x_preferred":[
        "Shchelchikha"
    ],
    "name:nor_x_preferred":[
        "Sjtsjeltsjikha"
    ],
    "name:rus_x_preferred":[
        "\u0429\u0435\u043b\u0447\u0438\u0445\u0430"
    ],
    "name:und_x_variant":[
        "\u0429\u0435\u043b\u0447\u0438\u0445\u0430",
        "Shchelchikha"
    ],
    "wof:name":"Shchelchikha",
    "wof:placetype":"locality"
},
  "geometry": {"coordinates":[78.39113,54.66556],"type":"Point"}
}