{
  "type": "Feature",
  "properties": {
    "gn:admin1_code":"10",
    "gn:asciiname":"Sosnovyy Bor",
    "gn:country_code":"RU",
    "gn:dem":161,
    "gn:feature_class":"P",
    "gn:feature_code":"PPL",
    "gn:name":"Sosnovyy Bor",
    "gn:population":2,
    "gn:timezone":"Europe/Moscow",
    "iso:country":"RU",
    "name:rus_x_preferred":[
        "\u0421\u043e\u0441\u043d\u043e\u0432\u044b\u0439 \u0411\u043e\u0440"
    ],
    "wof:name":"Sosnovyy Bor",
    "wof:placetype":"locality",
    "wof:population":2
},
  "geometry": {"coordinates":[31.7778,52.3361],"type":"Point"}
}