{
  "type": "Feature",
  "properties": {
    "gn:admin1_code":"41",
    "gn:asciiname":"Pozhidayevka",
    "gn:country_code":"RU",
    "gn:dem":250,
    "gn:feature_class":"P",
    "gn:feature_code":"PPL",
    "gn:name":"Pozhidayevka",
    "gn:population":0,
    "gn:timezone":"Europe/Moscow",
    "iso:country":"RU",
    "name:rus_x_preferred":[
        "\u041f\u043e\u0436\u0438\u0434\u0430\u0435\u0432\u043a\u0430"
    ],
    "name:und_x_variant":[
        "\u041f\u043e\u0436\u0438\u0434\u0430\u0435\u0432\u043a\u0430"
    ],
    "wof:name":"Pozhidayevka",
    "wof:placetype":"locality"
},
  "geometry": {"coordinates":[36.81056,51.90889],"type":"Point"}
}