{
  "type": "Feature",
  "properties": {
    "gn:admin1_code":"7",
    "gn:asciiname":"Kazennyy Bugor",
    "gn:country_code":"RU",
    "gn:dem":-25,
    "gn:feature_class":"P",
    "gn:feature_code":"PPL",
    "gn:name":"Kaz\u00ebnnyy Bugor",
    "gn:population":0,
    "gn:timezone":"Europe/Astrakhan",
    "iso:country":"RU",
    "name:rus_x_preferred":[
        "\u041a\u0430\u0437\u0451\u043d\u043d\u044b\u0439 \u0411\u0443\u0433\u043e\u0440"
    ],
    "name:und_x_variant":[
        "Kaz\u00ebnnyy Bugor"
    ],
    "wof:name":"Kazennyy Bugor",
    "wof:placetype":"locality"
},
  "geometry": {"coordinates":[48.65982,46.22633],"type":"Point"}
}