{
  "type": "Feature",
  "properties": {
    "gn:admin1_code":"83",
    "gn:asciiname":"Podlesnyy",
    "gn:country_code":"RU",
    "gn:dem":137,
    "gn:feature_class":"P",
    "gn:feature_code":"PPL",
    "gn:name":"Podlesnyy",
    "gn:population":0,
    "gn:timezone":"Europe/Moscow",
    "iso:country":"RU",
    "name:rus_x_preferred":[
        "\u041f\u043e\u0434\u043b\u0435\u0441\u043d\u044b\u0439"
    ],
    "wof:name":"Podlesnyy",
    "wof:placetype":"locality"
},
  "geometry": {"coordinates":[39.64448,56.73461999999999],"type":"Point"}
}