{
  "type": "Feature",
  "properties": {
    "gn:admin1_code":"61",
    "gn:asciiname":"Sukhaya-Krynka",
    "gn:country_code":"RU",
    "gn:dem":136,
    "gn:feature_class":"P",
    "gn:feature_code":"PPL",
    "gn:name":"Sukhaya-Krynka",
    "gn:population":0,
    "gn:timezone":"Europe/Moscow",
    "iso:country":"RU",
    "name:rus_x_preferred":[
        "\u0421\u0443\u0445\u0430\u044f-\u041a\u0440\u044b\u043d\u043a\u0430"
    ],
    "wof:name":"Sukhaya-Krynka",
    "wof:placetype":"locality"
},
  "geometry": {"coordinates":[38.66139,47.65519000000001],"type":"Point"}
}