{
  "type": "Feature",
  "properties": {
    "gn:admin1_code":"88",
    "gn:asciiname":"Borovaya",
    "gn:country_code":"RU",
    "gn:dem":96,
    "gn:feature_class":"P",
    "gn:feature_code":"PPL",
    "gn:name":"Borovaya",
    "gn:population":0,
    "gn:timezone":"Europe/Moscow",
    "iso:country":"RU",
    "name:rus_x_preferred":[
        "\u0411\u043e\u0440\u043e\u0432\u0430\u044f"
    ],
    "wof:name":"Borovaya",
    "wof:placetype":"locality"
},
  "geometry": {"coordinates":[39.7339,57.49836],"type":"Point"}
}