{
  "type": "Feature",
  "properties": {
    "gn:admin1_code":"10",
    "gn:asciiname":"Polovetskiy",
    "gn:country_code":"RU",
    "gn:dem":191,
    "gn:feature_class":"P",
    "gn:feature_code":"PPL",
    "gn:name":"Polovetskiy",
    "gn:population":0,
    "gn:timezone":"Europe/Moscow",
    "iso:country":"RU",
    "name:rus_x_preferred":[
        "\u041f\u043e\u043b\u043e\u0432\u0435\u0446\u043a\u0438\u0439"
    ],
    "wof:name":"Polovetskiy",
    "wof:placetype":"locality"
},
  "geometry": {"coordinates":[33.68534,52.7049],"type":"Point"}
}