{
  "type": "Feature",
  "properties": {
    "gn:admin1_code":"46.0",
    "gn:asciiname":"Bol'shiye Mordovskiye Poshaty",
    "gn:country_code":"RU",
    "gn:dem":117,
    "gn:feature_class":"P",
    "gn:feature_code":"PPL",
    "gn:name":"Bol\u2019shiye Mordovskiye Poshaty",
    "gn:population":0,
    "gn:timezone":"Europe/Moscow",
    "iso:country":"RU",
    "name:nor_x_preferred":[
        "Bolsjije Mordovskije Posjaty"
    ],
    "name:rus_x_preferred":[
        "\u0411\u043e\u043b\u044c\u0448\u0438\u0435 \u041c\u043e\u0440\u0434\u043e\u0432\u0441\u043a\u0438\u0435 \u041f\u043e\u0448\u0430\u0442\u044b"
    ],
    "name:und_x_variant":[
        "Bol\u2019shiye Poshaty",
        "Bol\u2019shiye Mordovskiye Poshaty"
    ],
    "wof:name":"Bol'shiye Mordovskiye Poshaty",
    "wof:placetype":"locality"
},
  "geometry": {"coordinates":[43.70175,54.66024],"type":"Point"}
}