{
  "type": "Feature",
  "properties": {
    "gn:admin1_code":"73",
    "gn:asciiname":"Staroye Alimovo",
    "gn:country_code":"RU",
    "gn:dem":86,
    "gn:feature_class":"P",
    "gn:feature_code":"PPL",
    "gn:name":"Staroye Alimovo",
    "gn:population":0,
    "gn:timezone":"Europe/Moscow",
    "iso:country":"RU",
    "name:rus_x_preferred":[
        "\u0421\u0442\u0430\u0440\u043e\u0435 \u0410\u043b\u0438\u043c\u043e\u0432\u043e"
    ],
    "name:und_x_variant":[
        "\u0421\u0442\u0430\u0440\u043e\u0435 \u0410\u043b\u0438\u043c\u043e\u0432\u043e"
    ],
    "wof:name":"Staroye Alimovo",
    "wof:placetype":"locality"
},
  "geometry": {"coordinates":[54.04481,55.62658],"type":"Point"}
}