{
  "type": "Feature",
  "properties": {
    "gn:admin1_code":"88",
    "gn:asciiname":"Maloye Dubrovo",
    "gn:country_code":"RU",
    "gn:dem":101,
    "gn:feature_class":"P",
    "gn:feature_code":"PPL",
    "gn:name":"Maloye Dubrovo",
    "gn:population":0,
    "gn:timezone":"Europe/Moscow",
    "iso:country":"RU",
    "name:rus_x_preferred":[
        "\u041c\u0430\u043b\u043e\u0435 \u0414\u0443\u0431\u0440\u043e\u0432\u043e"
    ],
    "wof:name":"Maloye Dubrovo",
    "wof:placetype":"locality"
},
  "geometry": {"coordinates":[39.31924,57.29539000000001],"type":"Point"}
}