{
  "type": "Feature",
  "properties": {
    "gn:admin1_code":"65.0",
    "gn:asciiname":"Dubovaya Roshcha",
    "gn:country_code":"RU",
    "gn:dem":104,
    "gn:feature_class":"P",
    "gn:feature_code":"PPL",
    "gn:name":"Dubovaya Roshcha",
    "gn:population":0,
    "gn:timezone":"Europe/Samara",
    "iso:country":"RU",
    "name:rus_x_preferred":[
        "\u0414\u0443\u0431\u043e\u0432\u0430\u044f \u0420\u043e\u0449\u0430"
    ],
    "wof:name":"Dubovaya Roshcha",
    "wof:placetype":"locality"
},
  "geometry": {"coordinates":[50.03058,53.68604000000001],"type":"Point"}
}