{
  "type": "Feature",
  "properties": {
    "gn:admin1_code":"41.0",
    "gn:asciiname":"Shcheka",
    "gn:country_code":"RU",
    "gn:dem":197,
    "gn:feature_class":"P",
    "gn:feature_code":"PPL",
    "gn:name":"Shcheka",
    "gn:population":0,
    "gn:timezone":"Europe/Moscow",
    "iso:country":"RU",
    "name:rus_x_preferred":[
        "\u0429\u0435\u043a\u0430"
    ],
    "wof:name":"Shcheka",
    "wof:placetype":"locality"
},
  "geometry": {"coordinates":[35.2574,52.2912],"type":"Point"}
}