{
  "type": "Feature",
  "properties": {
    "gn:admin1_code":"72",
    "gn:asciiname":"Ilovay-Brigadirskoye",
    "gn:country_code":"RU",
    "gn:dem":142,
    "gn:feature_class":"P",
    "gn:feature_code":"PPL",
    "gn:name":"Ilovay-Brigadirskoye",
    "gn:population":0,
    "gn:timezone":"Europe/Moscow",
    "iso:country":"RU",
    "name:rus_x_preferred":[
        "\u0418\u043b\u043e\u0432\u0430\u0439-\u0411\u0440\u0438\u0433\u0430\u0434\u0438\u0440\u0441\u043a\u043e\u0435"
    ],
    "name:und_x_variant":[
        "\u0418\u043b\u043e\u0432\u0430\u0439-\u0411\u0440\u0438\u0433\u0430\u0434\u0438\u0440\u0441\u043a\u043e\u0435"
    ],
    "wof:name":"Ilovay-Brigadirskoye",
    "wof:placetype":"locality"
},
  "geometry": {"coordinates":[40.3361,53.1017],"type":"Point"}
}