{
  "type": "Feature",
  "properties": {
    "gn:admin1_code":"90",
    "gn:asciiname":"Samkovo",
    "gn:country_code":"RU",
    "gn:dem":217,
    "gn:feature_class":"P",
    "gn:feature_code":"PPL",
    "gn:name":"Samkovo",
    "gn:population":0,
    "gn:timezone":"Asia/Yekaterinburg",
    "iso:country":"RU",
    "name:eng_x_preferred":[
        "Samkovo"
    ],
    "name:nor_x_preferred":[
        "Samkovo"
    ],
    "name:rus_x_preferred":[
        "\u0421\u0430\u043c\u043a\u043e\u0432\u043e"
    ],
    "name:und_x_variant":[
        "Samkova",
        "Samkovo",
        "\u0421\u0430\u043c\u043a\u043e\u0432\u043e"
    ],
    "wof:name":"Samkovo",
    "wof:placetype":"locality"
},
  "geometry": {"coordinates":[54.0807,58.9404],"type":"Point"}
}