{
  "type": "Feature",
  "properties": {
    "gn:admin1_code":"51.0",
    "gn:asciiname":"Dolgoye",
    "gn:country_code":"RU",
    "gn:dem":190,
    "gn:feature_class":"P",
    "gn:feature_code":"PPL",
    "gn:name":"Dolgoye",
    "gn:population":0,
    "gn:timezone":"Europe/Moscow",
    "iso:country":"RU",
    "name:rus_x_preferred":[
        "\u0414\u043e\u043b\u0433\u043e\u0435"
    ],
    "name:und_x_variant":[
        "\u0414\u043e\u043b\u0433\u043e\u0435"
    ],
    "wof:name":"Dolgoye",
    "wof:placetype":"locality"
},
  "geometry": {"coordinates":[45.10339000000001,55.86575],"type":"Point"}
}