{
  "type": "Feature",
  "properties": {
    "gn:admin1_code":"91",
    "gn:asciiname":"Kazantsevo",
    "gn:country_code":"RU",
    "gn:dem":30,
    "gn:feature_class":"P",
    "gn:feature_code":"PPL",
    "gn:name":"Kazantsevo",
    "gn:population":0,
    "gn:timezone":"Asia/Krasnoyarsk",
    "iso:country":"RU",
    "name:eng_x_preferred":[
        "Kazantsevo"
    ],
    "name:nor_x_preferred":[
        "Kazantsevo"
    ],
    "name:rus_x_preferred":[
        "\u041a\u0430\u0437\u0430\u043d\u0446\u0435\u0432\u043e"
    ],
    "wof:name":"Kazantsevo",
    "wof:placetype":"locality"
},
  "geometry": {"coordinates":[83.77861,69.84056],"type":"Point"}
}