{
  "type": "Feature",
  "properties": {
    "gn:admin1_code":"42.0",
    "gn:asciiname":"Ruch'i",
    "gn:country_code":"RU",
    "gn:dem":27,
    "gn:feature_class":"P",
    "gn:feature_code":"PPL",
    "gn:name":"Ruch'i",
    "gn:population":0,
    "gn:timezone":"Europe/Moscow",
    "iso:country":"RU",
    "name:fin_x_preferred":[
        "Ojaj\u00e4rvi"
    ],
    "wof:name":"Ruch'i",
    "wof:placetype":"locality"
},
  "geometry": {"coordinates":[29.56764,61.14373000000001],"type":"Point"}
}