{
  "type": "Feature",
  "properties": {
    "gn:admin1_code":"41.0",
    "gn:asciiname":"Kursko-Ol'khovatka",
    "gn:country_code":"RU",
    "gn:dem":217,
    "gn:feature_class":"P",
    "gn:feature_code":"PPL",
    "gn:name":"Kursko-Ol\u2019khovatka",
    "gn:population":0,
    "gn:timezone":"Europe/Moscow",
    "iso:country":"RU",
    "name:rus_x_preferred":[
        "\u041a\u0443\u0440\u0441\u043a\u043e-\u041e\u043b\u044c\u0445\u043e\u0432\u0430\u0442\u043a\u0430"
    ],
    "name:und_x_variant":[
        "Kursko-Ol\u2019khovatka",
        "\u041a\u0443\u0440\u0441\u043a\u043e-\u041e\u043b\u044c\u0445\u043e\u0432\u0430\u0442\u043a\u0430"
    ],
    "wof:name":"Kursko-Ol'khovatka",
    "wof:placetype":"locality"
},
  "geometry": {"coordinates":[36.82747,51.98316],"type":"Point"}
}