{
  "type": "Feature",
  "properties": {
    "gn:admin1_code":"57",
    "gn:asciiname":"Morevka",
    "gn:cc2":"RU",
    "gn:country_code":"RU",
    "gn:dem":234,
    "gn:feature_class":"P",
    "gn:feature_code":"PPL",
    "gn:name":"Mor\u00ebvka",
    "gn:population":0,
    "gn:timezone":"Europe/Moscow",
    "iso:country":"RU",
    "name:rus_x_preferred":[
        "\u041c\u043e\u0440\u0451\u0432\u043a\u0430"
    ],
    "name:und_x_variant":[
        "Mor\u2019yevka",
        "Mor\u00ebvka"
    ],
    "wof:name":"Morevka",
    "wof:placetype":"locality"
},
  "geometry": {"coordinates":[45.35,52.63333000000001],"type":"Point"}
}