{
  "type": "Feature",
  "properties": {
    "gn:admin1_code":"47",
    "gn:asciiname":"Khovan'",
    "gn:country_code":"RU",
    "gn:dem":249,
    "gn:feature_class":"P",
    "gn:feature_code":"PPL",
    "gn:name":"Khovan\u2019",
    "gn:population":0,
    "gn:timezone":"Europe/Moscow",
    "iso:country":"RU",
    "name:eng_x_preferred":[
        "Khovan'"
    ],
    "name:nor_x_preferred":[
        "Khovan"
    ],
    "name:rus_x_preferred":[
        "\u0425\u043e\u0432\u0430\u043d\u044c"
    ],
    "name:und_x_variant":[
        "Khovan\u2019"
    ],
    "wof:name":"Khovan'",
    "wof:placetype":"locality"
},
  "geometry": {"coordinates":[35.50309,55.99746],"type":"Point"}
}