{
  "type": "Feature",
  "properties": {
    "gn:admin1_code":"85",
    "gn:asciiname":"Melekhovo",
    "gn:country_code":"RU",
    "gn:dem":126,
    "gn:feature_class":"P",
    "gn:feature_code":"PPL",
    "gn:name":"Melekhovo",
    "gn:population":0,
    "gn:timezone":"Europe/Moscow",
    "iso:country":"RU",
    "name:rus_x_preferred":[
        "\u041c\u0435\u043b\u0435\u0445\u043e\u0432\u043e"
    ],
    "wof:name":"Melekhovo",
    "wof:placetype":"locality"
},
  "geometry": {"coordinates":[38.5982,59.8651],"type":"Point"}
}