{
  "type": "Feature",
  "properties": {
    "gn:admin1_code":"83",
    "gn:asciiname":"Zolotovo",
    "gn:country_code":"RU",
    "gn:dem":106,
    "gn:feature_class":"P",
    "gn:feature_code":"PPL",
    "gn:name":"Zolotovo",
    "gn:population":0,
    "gn:timezone":"Europe/Moscow",
    "iso:country":"RU",
    "name:eng_x_preferred":[
        "Zolotovo"
    ],
    "name:nor_x_preferred":[
        "Zolotovo"
    ],
    "name:rus_x_preferred":[
        "\u0417\u043e\u043b\u043e\u0442\u043e\u0432\u043e"
    ],
    "wof:name":"Zolotovo",
    "wof:placetype":"locality"
},
  "geometry": {"coordinates":[42.21856,56.01712],"type":"Point"}
}