{
  "type": "Feature",
  "properties": {
    "gn:admin1_code":"93",
    "gn:asciiname":"Krasnokamensk",
    "gn:country_code":"RU",
    "gn:dem":707,
    "gn:feature_class":"P",
    "gn:feature_code":"PPL",
    "gn:name":"Krasnokamensk",
    "gn:population":0,
    "gn:timezone":"Asia/Chita",
    "iso:country":"RU",
    "name:ceb_x_preferred":[
        "Krasnokamensk"
    ],
    "name:nld_x_preferred":[
        "Krasnokamensk"
    ],
    "name:rus_x_preferred":[
        "\u041a\u0440\u0430\u0441\u043d\u043e\u043a\u0430\u043c\u0435\u043d\u0441\u043a"
    ],
    "wof:name":"Krasnokamensk",
    "wof:placetype":"locality"
},
  "geometry": {"coordinates":[118.1828,50.0982],"type":"Point"}
}