{
  "type": "Feature",
  "properties": {
    "gn:admin1_code":"51",
    "gn:asciiname":"Natal'ino",
    "gn:country_code":"RU",
    "gn:dem":87,
    "gn:feature_class":"P",
    "gn:feature_code":"PPL",
    "gn:name":"Natal\u2019ino",
    "gn:population":0,
    "gn:timezone":"Europe/Moscow",
    "iso:country":"RU",
    "name:eng_x_preferred":[
        "Natal'ino"
    ],
    "name:nor_x_preferred":[
        "Natalino"
    ],
    "name:rus_x_preferred":[
        "\u041d\u0430\u0442\u0430\u043b\u044c\u0438\u043d\u043e"
    ],
    "name:und_x_variant":[
        "\u041d\u0430\u0442\u0430\u043b\u044c\u0438\u043d\u043e",
        "Natal\u2019ino"
    ],
    "wof:name":"Natal'ino",
    "wof:placetype":"locality"
},
  "geometry": {"coordinates":[42.51917,55.53083],"type":"Point"}
}