{
  "type": "Feature",
  "properties": {
    "gn:admin1_code":"91",
    "gn:asciiname":"Dalay",
    "gn:country_code":"RU",
    "gn:dem":238,
    "gn:feature_class":"P",
    "gn:feature_code":"PPL",
    "gn:name":"Dalay",
    "gn:population":0,
    "gn:timezone":"Asia/Krasnoyarsk",
    "iso:country":"RU",
    "name:eng_x_preferred":[
        "Dalay"
    ],
    "name:nor_x_preferred":[
        "Dalaj"
    ],
    "name:rus_x_preferred":[
        "\u0414\u0430\u043b\u0430\u0439"
    ],
    "name:und_x_variant":[
        "Dalayskaya",
        "Dalay"
    ],
    "wof:name":"Dalay",
    "wof:placetype":"locality"
},
  "geometry": {"coordinates":[95.90528,56.29167],"type":"Point"}
}