{
  "type": "Feature",
  "properties": {
    "gn:admin1_code":"55",
    "gn:asciiname":"Staryy Sokulak",
    "gn:country_code":"RU",
    "gn:dem":223,
    "gn:feature_class":"P",
    "gn:feature_code":"PPL",
    "gn:name":"Staryy Sokulak",
    "gn:population":0,
    "gn:timezone":"Asia/Yekaterinburg",
    "iso:country":"RU",
    "name:eng_x_preferred":[
        "Staryy Sokulak"
    ],
    "name:nor_x_preferred":[
        "Star.Sokulak"
    ],
    "name:rus_x_preferred":[
        "\u0421\u0442\u0430\u0440.\u0421\u043e\u043a\u0443\u043b\u0430\u043a"
    ],
    "name:rus_x_variant":[
        "\u0421\u0442\u0430\u0440\u044b\u0439 \u0421\u043e\u043a\u0443\u043b\u0430\u043a"
    ],
    "name:und_x_variant":[
        "Staryy Sakulak"
    ],
    "wof:name":"Staryy Sokulak",
    "wof:placetype":"locality"
},
  "geometry": {"coordinates":[56.4057,52.05657],"type":"Point"}
}