{
  "type": "Feature",
  "properties": {
    "gn:admin1_code":"90",
    "gn:asciiname":"Verkhniy Supych",
    "gn:country_code":"RU",
    "gn:dem":257,
    "gn:feature_class":"P",
    "gn:feature_code":"PPL",
    "gn:name":"Verkhniy Supych",
    "gn:population":0,
    "gn:timezone":"Asia/Yekaterinburg",
    "iso:country":"RU",
    "wof:name":"Verkhniy Supych",
    "wof:placetype":"locality"
},
  "geometry": {"coordinates":[57.31667,58.51667],"type":"Point"}
}