{
  "type": "Feature",
  "properties": {
    "gn:admin1_code":"85.0",
    "gn:asciiname":"Bol'shoye Kalinnikovo",
    "gn:country_code":"RU",
    "gn:dem":183,
    "gn:feature_class":"P",
    "gn:feature_code":"PPL",
    "gn:name":"Bol\u2019shoye Kalinnikovo",
    "gn:population":0,
    "gn:timezone":"Europe/Moscow",
    "iso:country":"RU",
    "name:rus_x_preferred":[
        "\u0411\u043e\u043b\u044c\u0448\u043e\u0435 \u041a\u0430\u043b\u0438\u043d\u043d\u0438\u043a\u043e\u0432\u043e"
    ],
    "name:und_x_variant":[
        "Bol\u2019shoye Kalinnikovo",
        "\u0411\u043e\u043b\u044c\u0448\u043e\u0435 \u041a\u0430\u043b\u0438\u043d\u043d\u0438\u043a\u043e\u0432\u043e"
    ],
    "wof:name":"Bol'shoye Kalinnikovo",
    "wof:placetype":"locality"
},
  "geometry": {"coordinates":[37.81473,59.40108000000001],"type":"Point"}
}