{
  "type": "Feature",
  "properties": {
    "gn:admin1_code":"7",
    "gn:asciiname":"Yamana",
    "gn:country_code":"RU",
    "gn:dem":-26,
    "gn:feature_class":"P",
    "gn:feature_code":"PPL",
    "gn:name":"Yamana",
    "gn:population":0,
    "gn:timezone":"Europe/Astrakhan",
    "iso:country":"RU",
    "name:ceb_x_preferred":[
        "Yamana"
    ],
    "name:eng_x_preferred":[
        "Yamana"
    ],
    "name:fra_x_preferred":[
        "Yamana"
    ],
    "name:nor_x_preferred":[
        "Jamana"
    ],
    "name:rus_x_preferred":[
        "\u042f\u043c\u0430\u043d\u0430"
    ],
    "name:swe_x_preferred":[
        "Yamana"
    ],
    "wof:name":"Yamana",
    "wof:placetype":"locality"
},
  "geometry": {"coordinates":[48.1975,45.98083],"type":"Point"}
}