{
  "type": "Feature",
  "properties": {
    "gn:admin1_code":"75",
    "gn:asciiname":"Bondarka",
    "gn:country_code":"RU",
    "gn:dem":47,
    "gn:feature_class":"P",
    "gn:feature_code":"PPL",
    "gn:name":"Bondarka",
    "gn:population":0,
    "gn:timezone":"Asia/Tomsk",
    "iso:country":"RU",
    "name:eng_x_preferred":[
        "Bondarka"
    ],
    "name:nor_x_preferred":[
        "Bondarka"
    ],
    "name:rus_x_preferred":[
        "\u0411\u043e\u043d\u0434\u0430\u0440\u043a\u0430"
    ],
    "wof:name":"Bondarka",
    "wof:placetype":"locality"
},
  "geometry": {"coordinates":[80.72278,59.03139],"type":"Point"}
}