{
  "type": "Feature",
  "properties": {
    "gn:admin1_code":"47",
    "gn:asciiname":"Bugaylovo",
    "gn:country_code":"RU",
    "gn:dem":219,
    "gn:feature_class":"P",
    "gn:feature_code":"PPL",
    "gn:name":"Bugaylovo",
    "gn:population":0,
    "gn:timezone":"Europe/Moscow",
    "iso:country":"RU",
    "name:rus_x_preferred":[
        "\u0411\u0443\u0433\u0430\u0439\u043b\u043e\u0432\u043e"
    ],
    "name:und_x_variant":[
        "\u0411\u0443\u0433\u0430\u0439\u043b\u043e\u0432\u043e"
    ],
    "wof:name":"Bugaylovo",
    "wof:placetype":"locality"
},
  "geometry": {"coordinates":[36.11667,55.4425],"type":"Point"}
}