{
  "type": "Feature",
  "properties": {
    "gn:admin1_code":"3",
    "gn:asciiname":"Kyrlyk",
    "gn:country_code":"RU",
    "gn:dem":1199,
    "gn:feature_class":"P",
    "gn:feature_code":"PPL",
    "gn:name":"Kyrlyk",
    "gn:population":0,
    "gn:timezone":"Asia/Omsk",
    "iso:country":"RU",
    "name:eng_x_preferred":[
        "Kyrlyk"
    ],
    "name:nor_x_preferred":[
        "Kyrlyk"
    ],
    "name:rus_x_preferred":[
        "\u041a\u044b\u0440\u043b\u044b\u043a"
    ],
    "wof:name":"Kyrlyk",
    "wof:placetype":"locality"
},
  "geometry": {"coordinates":[84.93333,50.73333],"type":"Point"}
}