{
  "type": "Feature",
  "properties": {
    "gn:admin1_code":"23",
    "gn:asciiname":"Bogdanovo",
    "gn:country_code":"RU",
    "gn:dem":112,
    "gn:feature_class":"P",
    "gn:feature_code":"PPL",
    "gn:name":"Bogdanovo",
    "gn:population":0,
    "gn:timezone":"Europe/Kaliningrad",
    "iso:country":"RU",
    "name:che_x_preferred":[
        "\u0411\u043e\u0433\u0434\u0430\u043d\u043e\u0432\u043e"
    ],
    "name:rus_x_preferred":[
        "\u0411\u043e\u0433\u0434\u0430\u043d\u043e\u0432\u043e"
    ],
    "wof:name":"Bogdanovo",
    "wof:placetype":"locality"
},
  "geometry": {"coordinates":[21.97308,54.3974],"type":"Point"}
}