{
  "type": "Feature",
  "properties": {
    "gn:admin1_code":"65",
    "gn:asciiname":"Bezvodovka",
    "gn:country_code":"RU",
    "gn:dem":122,
    "gn:feature_class":"P",
    "gn:feature_code":"PPL",
    "gn:name":"Bezvodovka",
    "gn:population":0,
    "gn:timezone":"Europe/Samara",
    "iso:country":"RU",
    "name:rus_x_preferred":[
        "\u0411\u0435\u0437\u0432\u043e\u0434\u043e\u0432\u043a\u0430"
    ],
    "name:und_x_variant":[
        "\u0411\u0435\u0437\u0432\u043e\u0434\u043e\u0432\u043a\u0430"
    ],
    "wof:name":"Bezvodovka",
    "wof:placetype":"locality"
},
  "geometry": {"coordinates":[51.1314,54.2746],"type":"Point"}
}