{
  "type": "Feature",
  "properties": {
    "gn:admin1_code":"29",
    "gn:asciiname":"Shchebzavod",
    "gn:country_code":"RU",
    "gn:dem":256,
    "gn:feature_class":"P",
    "gn:feature_code":"PPL",
    "gn:name":"Shchebzavod",
    "gn:population":0,
    "gn:timezone":"Asia/Novokuznetsk",
    "iso:country":"RU",
    "name:rus_x_preferred":[
        "\u0429\u0435\u0431\u0437\u0430\u0432\u043e\u0434"
    ],
    "name:und_x_variant":[
        "Drobil\u2019nyy",
        "Shchebzavod"
    ],
    "wof:name":"Shchebzavod",
    "wof:placetype":"locality"
},
  "geometry": {"coordinates":[86.17189999999999,54.191],"type":"Point"}
}