{
  "type": "Feature",
  "properties": {
    "gn:admin1_code":"54",
    "gn:asciiname":"Dve Tysyachi Pyat'sot Sorokovoy Kilometr",
    "gn:country_code":"RU",
    "gn:dem":124,
    "gn:feature_class":"P",
    "gn:feature_code":"PPL",
    "gn:name":"Dve Tysyachi Pyat\u2019sot Sorokovoy Kilometr",
    "gn:population":0,
    "gn:timezone":"Asia/Omsk",
    "iso:country":"RU",
    "name:rus_x_preferred":[
        "\u0414\u0432\u0435 \u0422\u044b\u0441\u044f\u0447\u0438 \u041f\u044f\u0442\u044c\u0441\u043e\u0442 \u0421\u043e\u0440\u043e\u043a\u043e\u0432\u043e\u0439 \u041a\u0438\u043b\u043e\u043c\u0435\u0442\u0440"
    ],
    "name:und_x_variant":[
        "Dve Tysyachi Pyat\u2019sot Sorokovoy Kilometr",
        "\u0414\u0432\u0435 \u0422\u044b\u0441\u044f\u0447\u0438 \u041f\u044f\u0442\u044c\u0441\u043e\u0442 \u0421\u043e\u0440\u043e\u043a\u043e\u0432\u043e\u0439 \u041a\u0438\u043b\u043e\u043c\u0435\u0442\u0440"
    ],
    "wof:name":"Dve Tysyachi Pyat'sot Sorokovoy Kilometr",
    "wof:placetype":"locality"
},
  "geometry": {"coordinates":[71.0557,55.6698],"type":"Point"}
}