{
  "type": "Feature",
  "properties": {
    "gn:admin1_code":"34",
    "gn:asciiname":"Kipiyevo",
    "gn:country_code":"RU",
    "gn:dem":39,
    "gn:feature_class":"P",
    "gn:feature_code":"PPL",
    "gn:name":"Kipiyevo",
    "gn:population":0,
    "gn:timezone":"Europe/Moscow",
    "iso:country":"RU",
    "name:eng_x_preferred":[
        "Kipiyevo"
    ],
    "name:nor_x_preferred":[
        "Kipijevo"
    ],
    "name:rus_x_preferred":[
        "\u041a\u0438\u043f\u0438\u0435\u0432\u043e"
    ],
    "name:und_x_variant":[
        "Kipievo",
        "Kipiyeva",
        "\u041a\u0438\u043f\u0438\u0435\u0432\u043e",
        "Kipiyevo"
    ],
    "wof:name":"Kipiyevo",
    "wof:placetype":"locality"
},
  "geometry": {"coordinates":[54.51689,65.66191999999999],"type":"Point"}
}