{
  "type": "Feature",
  "properties": {
    "gn:admin1_code":"63",
    "gn:asciiname":"Tiyeriliki",
    "gn:country_code":"RU",
    "gn:dem":193,
    "gn:feature_class":"P",
    "gn:feature_code":"PPL",
    "gn:name":"Tiyeriliki",
    "gn:population":0,
    "gn:timezone":"Asia/Yakutsk",
    "iso:country":"RU",
    "name:eng_x_preferred":[
        "Tiyeriliki"
    ],
    "name:nor_x_preferred":[
        "Tijeriliki"
    ],
    "name:rus_x_preferred":[
        "\u0422\u0438\u0435\u0440\u0438\u043b\u0438\u043a\u0438"
    ],
    "wof:name":"Tiyeriliki",
    "wof:placetype":"locality"
},
  "geometry": {"coordinates":[131.91981999999999,61.07447],"type":"Point"}
}