{
  "type": "Feature",
  "properties": {
    "gn:admin1_code":"75",
    "gn:asciiname":"Nyurol'skiy",
    "gn:country_code":"RU",
    "gn:dem":59,
    "gn:feature_class":"P",
    "gn:feature_code":"PPL",
    "gn:name":"Nyurol\u2019skiy",
    "gn:population":0,
    "gn:timezone":"Asia/Tomsk",
    "iso:country":"RU",
    "name:rus_x_preferred":[
        "\u041d\u044e\u0440\u043e\u043b\u044c\u0441\u043a\u0438\u0439"
    ],
    "name:und_x_variant":[
        "Nyurol\u2019skiy",
        "\u041d\u044e\u0440\u043e\u043b\u044c\u0441\u043a\u0438\u0439"
    ],
    "wof:name":"Nyurol'skiy",
    "wof:placetype":"locality"
},
  "geometry": {"coordinates":[78.08333,58.96666999999999],"type":"Point"}
}