{
  "type": "Feature",
  "properties": {
    "gn:admin1_code":"29",
    "gn:asciiname":"Amzas",
    "gn:country_code":"RU",
    "gn:dem":368,
    "gn:feature_class":"P",
    "gn:feature_code":"PPL",
    "gn:name":"Amzas",
    "gn:population":0,
    "gn:timezone":"Asia/Novokuznetsk",
    "iso:country":"RU",
    "name:eng_x_preferred":[
        "Amzas"
    ],
    "name:nor_x_preferred":[
        "Amzas"
    ],
    "name:rus_x_preferred":[
        "\u0410\u043c\u0437\u0430\u0441"
    ],
    "wof:name":"Amzas",
    "wof:placetype":"locality"
},
  "geometry": {"coordinates":[87.5394,53.0118],"type":"Point"}
}