{
  "type": "Feature",
  "properties": {
    "gn:admin1_code":"52",
    "gn:asciiname":"Maloye Mezhurech'ye",
    "gn:country_code":"RU",
    "gn:dem":83,
    "gn:feature_class":"P",
    "gn:feature_code":"PPL",
    "gn:name":"Maloye Mezhurech\u2019ye",
    "gn:population":0,
    "gn:timezone":"Europe/Moscow",
    "iso:country":"RU",
    "name:rus_x_preferred":[
        "\u041c\u0430\u043b\u043e\u0435 \u041c\u0435\u0436\u0443\u0440\u0435\u0447\u044c\u0435"
    ],
    "name:und_x_variant":[
        "Maloye Mezhurech\u2019ye",
        "\u041c\u0430\u043b\u043e\u0435 \u041c\u0435\u0436\u0443\u0440\u0435\u0447\u044c\u0435"
    ],
    "wof:name":"Maloye Mezhurech'ye",
    "wof:placetype":"locality"
},
  "geometry": {"coordinates":[30.81667,57.88333000000001],"type":"Point"}
}