{
  "type": "Feature",
  "properties": {
    "gn:admin1_code":"61",
    "gn:asciiname":"Semimayachnyy",
    "gn:country_code":"RU",
    "gn:dem":34,
    "gn:feature_class":"P",
    "gn:feature_code":"PPL",
    "gn:name":"Semimayachnyy",
    "gn:population":0,
    "gn:timezone":"Europe/Moscow",
    "iso:country":"RU",
    "name:rus_x_preferred":[
        "\u0421\u0435\u043c\u0438\u043c\u0430\u044f\u0447\u043d\u044b\u0439"
    ],
    "name:und_x_variant":[
        "Semimayachny",
        "Semimayachnyy",
        "\u0421\u0435\u043c\u0438\u043c\u0430\u044f\u0447\u043d\u044b\u0439"
    ],
    "wof:name":"Semimayachnyy",
    "wof:placetype":"locality"
},
  "geometry": {"coordinates":[40.71335,47.92383],"type":"Point"}
}