{
  "type": "Feature",
  "properties": {
    "gn:admin1_code":"90.0",
    "gn:asciiname":"Bykovo",
    "gn:country_code":"RU",
    "gn:dem":205,
    "gn:feature_class":"P",
    "gn:feature_code":"PPL",
    "gn:name":"Bykovo",
    "gn:population":0,
    "gn:timezone":"Asia/Yekaterinburg",
    "iso:country":"RU",
    "name:eng_x_preferred":[
        "Bykovo"
    ],
    "name:nor_x_preferred":[
        "Bykovo"
    ],
    "name:rus_x_preferred":[
        "\u0411\u044b\u043a\u043e\u0432\u043e"
    ],
    "name:und_x_variant":[
        "Bykova",
        "Bykovo",
        "\u0411\u044b\u043a\u043e\u0432\u043e"
    ],
    "wof:name":"Bykovo",
    "wof:placetype":"locality"
},
  "geometry": {"coordinates":[55.2902,59.8465],"type":"Point"}
}