{
  "type": "Feature",
  "properties": {
    "gn:admin1_code":"85",
    "gn:asciiname":"Pavshino",
    "gn:country_code":"RU",
    "gn:dem":62,
    "gn:feature_class":"P",
    "gn:feature_code":"PPL",
    "gn:name":"Pavshino",
    "gn:population":0,
    "gn:timezone":"Europe/Moscow",
    "iso:country":"RU",
    "name:rus_x_preferred":[
        "\u041f\u0430\u0432\u0448\u0438\u043d\u043e"
    ],
    "wof:name":"Pavshino",
    "wof:placetype":"locality"
},
  "geometry": {"coordinates":[46.4775,60.8064],"type":"Point"}
}