{
  "type": "Feature",
  "properties": {
    "gn:admin1_code":"83.0",
    "gn:asciiname":"Bol'shoy Sanchur",
    "gn:country_code":"RU",
    "gn:dem":132,
    "gn:feature_class":"P",
    "gn:feature_code":"PPL",
    "gn:name":"Bol\u2019shoy Sanchur",
    "gn:population":0,
    "gn:timezone":"Europe/Moscow",
    "iso:country":"RU",
    "name:rus_x_preferred":[
        "\u0411\u043e\u043b\u044c\u0448\u043e\u0439 \u0421\u0430\u043d\u0447\u0443\u0440"
    ],
    "name:und_x_variant":[
        "Sanchur",
        "Bol\u2019shoy Sanchur",
        "\u0411\u043e\u043b\u044c\u0448\u043e\u0439 \u0421\u0430\u043d\u0447\u0443\u0440"
    ],
    "wof:name":"Bol'shoy Sanchur",
    "wof:placetype":"locality"
},
  "geometry": {"coordinates":[41.75,55.18333000000001],"type":"Point"}
}