{
  "type": "Feature",
  "properties": {
    "gn:admin1_code":"87",
    "gn:asciiname":"Staryy Kiyevat",
    "gn:country_code":"RU",
    "gn:dem":1,
    "gn:feature_class":"P",
    "gn:feature_code":"PPL",
    "gn:name":"Staryy Kiyevat",
    "gn:population":0,
    "gn:timezone":"Asia/Yekaterinburg",
    "iso:country":"RU",
    "name:eng_x_preferred":[
        "Staryy Kiyevat"
    ],
    "name:nor_x_preferred":[
        "Staryj-Kijevat"
    ],
    "name:rus_x_preferred":[
        "\u0421\u0442\u0430\u0440\u044b\u0439-\u041a\u0438\u0435\u0432\u0430\u0442"
    ],
    "name:rus_x_variant":[
        "\u0421\u0442\u0430\u0440\u044b\u0439 \u041a\u0438\u0435\u0432\u0430\u0442"
    ],
    "name:und_x_variant":[
        "\u0421\u0442\u0430\u0440\u044b\u0439 \u041a\u0438\u0435\u0432\u0430\u0442"
    ],
    "wof:name":"Staryy Kiyevat",
    "wof:placetype":"locality"
},
  "geometry": {"coordinates":[64.715,65.26786],"type":"Point"}
}