{
  "type": "Feature",
  "properties": {
    "gn:admin1_code":"38",
    "gn:asciiname":"Dunayskiy",
    "gn:country_code":"RU",
    "gn:dem":200,
    "gn:feature_class":"P",
    "gn:feature_code":"PPL",
    "gn:name":"Dunayskiy",
    "gn:population":0,
    "gn:timezone":"Europe/Moscow",
    "iso:country":"RU",
    "name:rus_x_preferred":[
        "\u0414\u0443\u043d\u0430\u0439\u0441\u043a\u0438\u0439"
    ],
    "name:und_x_variant":[
        "\u0414\u0443\u043d\u0430\u0439\u0441\u043a\u0438\u0439"
    ],
    "wof:name":"Dunayskiy",
    "wof:placetype":"locality"
},
  "geometry": {"coordinates":[39.8075,44.56889],"type":"Point"}
}