{
  "type": "Feature",
  "properties": {
    "gn:admin1_code":"85",
    "gn:asciiname":"Oksino",
    "gn:country_code":"RU",
    "gn:dem":151,
    "gn:feature_class":"P",
    "gn:feature_code":"PPL",
    "gn:name":"Oksino",
    "gn:population":0,
    "gn:timezone":"Europe/Moscow",
    "iso:country":"RU",
    "name:rus_x_preferred":[
        "\u041e\u043a\u0441\u0438\u043d\u043e"
    ],
    "wof:name":"Oksino",
    "wof:placetype":"locality"
},
  "geometry": {"coordinates":[38.9062,59.7324],"type":"Point"}
}