{
  "type": "Feature",
  "properties": {
    "gn:admin1_code":"86.0",
    "gn:asciiname":"Mostishche",
    "gn:country_code":"RU",
    "gn:dem":102,
    "gn:feature_class":"P",
    "gn:feature_code":"PPL",
    "gn:name":"Mostishche",
    "gn:population":0,
    "gn:timezone":"Europe/Moscow",
    "iso:country":"RU",
    "name:rus_x_preferred":[
        "\u041c\u043e\u0441\u0442\u0438\u0449\u0435"
    ],
    "name:und_x_variant":[
        "Mostishchi",
        "Mostishche"
    ],
    "wof:name":"Mostishche",
    "wof:placetype":"locality"
},
  "geometry": {"coordinates":[39.09973,51.02848],"type":"Point"}
}