{
  "type": "Feature",
  "properties": {
    "gn:admin1_code":"10.0",
    "gn:asciiname":"Atrakin'",
    "gn:country_code":"RU",
    "gn:dem":174,
    "gn:feature_class":"P",
    "gn:feature_code":"PPL",
    "gn:name":"Atrakin\u2019",
    "gn:population":0,
    "gn:timezone":"Europe/Moscow",
    "iso:country":"RU",
    "name:nor_x_preferred":[
        "Atrakin"
    ],
    "name:rus_x_preferred":[
        "\u0410\u0442\u0440\u0430\u043a\u0438\u043d\u044c"
    ],
    "name:und_x_variant":[
        "Trokin\u2019ya",
        "Atrakin\u2019"
    ],
    "wof:name":"Atrakin'",
    "wof:placetype":"locality"
},
  "geometry": {"coordinates":[34.285,52.24111],"type":"Point"}
}