{
  "type": "Feature",
  "properties": {
    "gn:admin1_code":"38.0",
    "gn:asciiname":"Budennyy",
    "gn:cc2":"RU",
    "gn:country_code":"RU",
    "gn:dem":15,
    "gn:feature_class":"P",
    "gn:feature_code":"PPL",
    "gn:name":"Bud\u00ebnnyy",
    "gn:population":0,
    "gn:timezone":"Europe/Moscow",
    "iso:country":"RU",
    "name:rus_x_preferred":[
        "\u0411\u0443\u0434\u0451\u043d\u043d\u044b\u0439"
    ],
    "name:und_x_variant":[
        "Imeni Budennogo",
        "Khutora Imeni Budennogo",
        "Bud\u00ebnnyy"
    ],
    "wof:name":"Budennyy",
    "wof:placetype":"locality"
},
  "geometry": {"coordinates":[39.54278,46.59444000000001],"type":"Point"}
}