{
  "type": "Feature",
  "properties": {
    "gn:admin1_code":"60",
    "gn:asciiname":"Yushino",
    "gn:country_code":"RU",
    "gn:dem":75,
    "gn:feature_class":"P",
    "gn:feature_code":"PPL",
    "gn:name":"Yushino",
    "gn:population":0,
    "gn:timezone":"Europe/Moscow",
    "iso:country":"RU",
    "name:rus_x_preferred":[
        "\u042e\u0448\u0438\u043d\u043e"
    ],
    "wof:name":"Yushino",
    "wof:placetype":"locality"
},
  "geometry": {"coordinates":[28.64384,57.11826],"type":"Point"}
}