{
  "type": "Feature",
  "properties": {
    "gn:admin1_code":"86",
    "gn:asciiname":"Peskovatka",
    "gn:country_code":"RU",
    "gn:dem":99,
    "gn:feature_class":"P",
    "gn:feature_code":"PPL",
    "gn:name":"Peskovatka",
    "gn:population":0,
    "gn:timezone":"Europe/Moscow",
    "iso:country":"RU",
    "name:rus_x_preferred":[
        "\u041f\u0435\u0441\u043a\u043e\u0432\u0430\u0442\u043a\u0430"
    ],
    "name:und_x_variant":[
        "\u041f\u0435\u0441\u043a\u043e\u0432\u0430\u0442\u043a\u0430"
    ],
    "wof:name":"Peskovatka",
    "wof:placetype":"locality"
},
  "geometry": {"coordinates":[39.00861,51.05056],"type":"Point"}
}