{
  "type": "Feature",
  "properties": {
    "gn:admin1_code":"8",
    "gn:asciiname":"Sarayly",
    "gn:country_code":"RU",
    "gn:dem":204,
    "gn:feature_class":"P",
    "gn:feature_code":"PPL",
    "gn:name":"Sarayly",
    "gn:population":0,
    "gn:timezone":"Asia/Yekaterinburg",
    "iso:country":"RU",
    "name:eng_x_preferred":[
        "Sarayly"
    ],
    "name:nor_x_preferred":[
        "Sarajly"
    ],
    "name:rus_x_preferred":[
        "\u0421\u0430\u0440\u0430\u0439\u043b\u044b"
    ],
    "name:und_x_variant":[
        "\u0421\u0430\u0440\u0430\u0439\u043b\u044b",
        "Sarayly"
    ],
    "wof:name":"Sarayly",
    "wof:placetype":"locality"
},
  "geometry": {"coordinates":[55.05175,54.53732],"type":"Point"}
}