{
  "type": "Feature",
  "properties": {
    "gn:admin1_code":"30",
    "gn:asciiname":"Pobeda",
    "gn:country_code":"RU",
    "gn:dem":51,
    "gn:feature_class":"P",
    "gn:feature_code":"PPL",
    "gn:name":"Pobeda",
    "gn:population":0,
    "gn:timezone":"Asia/Vladivostok",
    "iso:country":"RU",
    "name:eng_x_preferred":[
        "Pobeda"
    ],
    "name:nor_x_preferred":[
        "Pobeda"
    ],
    "name:rus_x_preferred":[
        "\u041f\u043e\u0431\u0435\u0434\u0430"
    ],
    "name:und_x_variant":[
        "Pebeda",
        "\u041f\u043e\u0431\u0435\u0434\u0430",
        "Pobeda"
    ],
    "wof:name":"Pobeda",
    "wof:placetype":"locality"
},
  "geometry": {"coordinates":[134.32759999999999,49.06211],"type":"Point"}
}