{
  "type": "Feature",
  "properties": {
    "gn:admin1_code":"44",
    "gn:asciiname":"Kulu",
    "gn:country_code":"RU",
    "gn:dem":617,
    "gn:feature_class":"P",
    "gn:feature_code":"PPL",
    "gn:name":"Kulu",
    "gn:population":0,
    "gn:timezone":"Asia/Magadan",
    "iso:country":"RU",
    "name:ceb_x_preferred":[
        "Kulu"
    ],
    "name:deu_x_preferred":[
        "Kulu"
    ],
    "name:eng_x_preferred":[
        "Kulu"
    ],
    "name:fra_x_preferred":[
        "Kulu"
    ],
    "name:ita_x_preferred":[
        "Kulu"
    ],
    "name:min_x_preferred":[
        "Kulu"
    ],
    "name:nld_x_preferred":[
        "Kullu"
    ],
    "name:nor_x_preferred":[
        "Kulu"
    ],
    "name:rus_x_preferred":[
        "\u041a\u0443\u043b\u0443"
    ],
    "name:swe_x_preferred":[
        "Kulu"
    ],
    "name:und_x_variant":[
        "Kulinskaya",
        "\u041a\u0443\u043b\u0443",
        "Kulu"
    ],
    "wof:name":"Kulu",
    "wof:placetype":"locality"
},
  "geometry": {"coordinates":[147.43153000000001,61.88157],"type":"Point"}
}