{
  "type": "Feature",
  "properties": {
    "gn:admin1_code":"45",
    "gn:asciiname":"Vidyakino",
    "gn:country_code":"RU",
    "gn:dem":122,
    "gn:feature_class":"P",
    "gn:feature_code":"PPL",
    "gn:name":"Vidyakino",
    "gn:population":0,
    "gn:timezone":"Europe/Moscow",
    "iso:country":"RU",
    "name:rus_x_preferred":[
        "\u0412\u0438\u0434\u044f\u043a\u0438\u043d\u043e"
    ],
    "wof:name":"Vidyakino",
    "wof:placetype":"locality"
},
  "geometry": {"coordinates":[47.88221,56.97143000000001],"type":"Point"}
}