{
  "type": "Feature",
  "properties": {
    "gn:admin1_code":"46",
    "gn:asciiname":"Nadezhdinskiy",
    "gn:country_code":"RU",
    "gn:dem":183,
    "gn:feature_class":"P",
    "gn:feature_code":"PPL",
    "gn:name":"Nadezhdinskiy",
    "gn:population":0,
    "gn:timezone":"Europe/Moscow",
    "iso:country":"RU",
    "name:rus_x_preferred":[
        "\u041d\u0430\u0434\u0435\u0436\u0434\u0438\u043d\u0441\u043a\u0438\u0439"
    ],
    "wof:name":"Nadezhdinskiy",
    "wof:placetype":"locality"
},
  "geometry": {"coordinates":[45.679,54.8904],"type":"Point"}
}