{
  "type": "Feature",
  "properties": {
    "gn:admin1_code":"43.0",
    "gn:asciiname":"Bogoroditskoye Tret'ye",
    "gn:country_code":"RU",
    "gn:dem":130,
    "gn:feature_class":"P",
    "gn:feature_code":"PPL",
    "gn:name":"Bogoroditskoye Tret\u2019ye",
    "gn:population":0,
    "gn:timezone":"Europe/Moscow",
    "iso:country":"RU",
    "name:rus_x_preferred":[
        "\u0411\u043e\u0433\u043e\u0440\u043e\u0434\u0438\u0442\u0441\u043a\u043e\u0435 \u0422\u0440\u0435\u0442\u044c\u0435"
    ],
    "name:und_x_variant":[
        "Tret\u2019ye Bogoroditskoye",
        "Bogoroditskoye Tret\u2019ye"
    ],
    "wof:name":"Bogoroditskoye Tret'ye",
    "wof:placetype":"locality"
},
  "geometry": {"coordinates":[40.35056,52.27167],"type":"Point"}
}