{
  "type": "Feature",
  "properties": {
    "gn:admin1_code":"10",
    "gn:asciiname":"Nizhniye Bordovichi",
    "gn:country_code":"RU",
    "gn:dem":154,
    "gn:feature_class":"P",
    "gn:feature_code":"PPL",
    "gn:name":"Nizhniye Bordovichi",
    "gn:population":0,
    "gn:timezone":"Europe/Moscow",
    "iso:country":"RU",
    "name:rus_x_preferred":[
        "\u041d\u0438\u0436\u043d\u0438\u0435 \u0411\u043e\u0440\u0434\u043e\u0432\u0438\u0447\u0438"
    ],
    "name:und_x_variant":[
        "\u041d\u0438\u0436\u043d\u0438\u0435 \u0411\u043e\u0440\u0434\u043e\u0432\u0438\u0447\u0438"
    ],
    "wof:name":"Nizhniye Bordovichi",
    "wof:placetype":"locality"
},
  "geometry": {"coordinates":[34.22333,53.31166999999999],"type":"Point"}
}