{
  "type": "Feature",
  "properties": {
    "gn:admin1_code":"6",
    "gn:asciiname":"Pritykinskaya",
    "gn:country_code":"RU",
    "gn:dem":86,
    "gn:feature_class":"P",
    "gn:feature_code":"PPL",
    "gn:name":"Pritykinskaya",
    "gn:population":0,
    "gn:timezone":"Europe/Moscow",
    "iso:country":"RU",
    "name:eng_x_preferred":[
        "Pritykinskaya"
    ],
    "name:nor_x_preferred":[
        "Pritykinskaja"
    ],
    "name:rus_x_preferred":[
        "\u041f\u0440\u0438\u0442\u044b\u043a\u0438\u043d\u0441\u043a\u0430\u044f"
    ],
    "name:und_x_variant":[
        "\u041f\u0440\u0438\u0442\u044b\u043a\u0438\u043d\u0441\u043a\u0430\u044f",
        "Pritykinskaya"
    ],
    "wof:name":"Pritykinskaya",
    "wof:placetype":"locality"
},
  "geometry": {"coordinates":[41.7771,60.9452],"type":"Point"}
}