{
  "type": "Feature",
  "properties": {
    "gn:admin1_code":"60",
    "gn:asciiname":"Berezino",
    "gn:country_code":"RU",
    "gn:dem":59,
    "gn:feature_class":"P",
    "gn:feature_code":"PPL",
    "gn:name":"Berezino",
    "gn:population":0,
    "gn:timezone":"Europe/Moscow",
    "iso:country":"RU",
    "name:rus_x_preferred":[
        "\u0411\u0435\u0440\u0435\u0437\u0438\u043d\u043e"
    ],
    "wof:name":"Berezino",
    "wof:placetype":"locality"
},
  "geometry": {"coordinates":[28.1668,57.48321],"type":"Point"}
}