{
  "type": "Feature",
  "properties": {
    "gn:admin1_code":"8",
    "gn:asciiname":"Novoyuzeyevo",
    "gn:country_code":"RU",
    "gn:dem":147,
    "gn:feature_class":"P",
    "gn:feature_code":"PPL",
    "gn:name":"Novoyuzeyevo",
    "gn:population":0,
    "gn:timezone":"Asia/Yekaterinburg",
    "iso:country":"RU",
    "name:rus_x_preferred":[
        "\u041d\u043e\u0432\u043e\u044e\u0437\u0435\u0435\u0432\u043e"
    ],
    "name:und_x_variant":[
        "\u041d\u043e\u0432\u043e\u044e\u0437\u0435\u0435\u0432\u043e"
    ],
    "wof:name":"Novoyuzeyevo",
    "wof:placetype":"locality"
},
  "geometry": {"coordinates":[53.73333,54.96666999999999],"type":"Point"}
}