{
  "type": "Feature",
  "properties": {
    "gn:admin1_code":"61",
    "gn:asciiname":"Novostepnoy",
    "gn:country_code":"RU",
    "gn:dem":85,
    "gn:feature_class":"P",
    "gn:feature_code":"PPL",
    "gn:name":"Novostepnoy",
    "gn:population":0,
    "gn:timezone":"Europe/Moscow",
    "iso:country":"RU",
    "name:rus_x_preferred":[
        "\u041d\u043e\u0432\u043e\u0441\u0442\u0435\u043f\u043d\u043e\u0439"
    ],
    "wof:name":"Novostepnoy",
    "wof:placetype":"locality"
},
  "geometry": {"coordinates":[40.84861,46.26083],"type":"Point"}
}