{
  "type": "Feature",
  "properties": {
    "gn:admin1_code":"20",
    "gn:asciiname":"Donskaya",
    "gn:country_code":"RU",
    "gn:dem":465,
    "gn:feature_class":"P",
    "gn:feature_code":"PPL",
    "gn:name":"Donskaya",
    "gn:population":0,
    "gn:timezone":"Asia/Irkutsk",
    "iso:country":"RU",
    "name:rus_x_preferred":[
        "\u0414\u043e\u043d\u0441\u043a\u0430\u044f"
    ],
    "wof:name":"Donskaya",
    "wof:placetype":"locality"
},
  "geometry": {"coordinates":[103.13249999999999,53.01056],"type":"Point"}
}