{
  "type": "Feature",
  "properties": {
    "gn:admin1_code":"4",
    "gn:asciiname":"Lozhkino",
    "gn:country_code":"RU",
    "gn:dem":262,
    "gn:feature_class":"P",
    "gn:feature_code":"PPL",
    "gn:name":"Lozhkino",
    "gn:population":0,
    "gn:timezone":"Asia/Barnaul",
    "iso:country":"RU",
    "name:eng_x_preferred":[
        "Lozhkino"
    ],
    "name:nor_x_preferred":[
        "Lozjkino"
    ],
    "name:rus_x_preferred":[
        "\u041b\u043e\u0436\u043a\u0438\u043d\u043e"
    ],
    "name:und_x_variant":[
        "Lozhkinskoye",
        "Lozhkin",
        "Lozhkino"
    ],
    "wof:name":"Lozhkino",
    "wof:placetype":"locality"
},
  "geometry": {"coordinates":[85.44741999999999,52.83679],"type":"Point"}
}