{
  "type": "Feature",
  "properties": {
    "gn:admin1_code":"56",
    "gn:asciiname":"Rakitnaya",
    "gn:country_code":"RU",
    "gn:dem":187,
    "gn:feature_class":"P",
    "gn:feature_code":"PPL",
    "gn:name":"Rakitnaya",
    "gn:population":0,
    "gn:timezone":"Europe/Moscow",
    "iso:country":"RU",
    "name:rus_x_preferred":[
        "\u0420\u0430\u043a\u0438\u0442\u043d\u0430\u044f"
    ],
    "name:und_x_variant":[
        "Kobyl\u2019skaya",
        "Kobylinskaya",
        "Rakitnaya"
    ],
    "wof:name":"Rakitnaya",
    "wof:placetype":"locality"
},
  "geometry": {"coordinates":[35.50418,53.29398000000001],"type":"Point"}
}