{
  "type": "Feature",
  "properties": {
    "gn:admin1_code":"54",
    "gn:asciiname":"Martyushevo",
    "gn:country_code":"RU",
    "gn:dem":120,
    "gn:feature_class":"P",
    "gn:feature_code":"PPL",
    "gn:name":"Martyushevo",
    "gn:population":0,
    "gn:timezone":"Asia/Omsk",
    "iso:country":"RU",
    "name:eng_x_preferred":[
        "Martyushevo"
    ],
    "name:nor_x_preferred":[
        "Martjusjevo"
    ],
    "name:rus_x_preferred":[
        "\u041c\u0430\u0440\u0442\u044e\u0448\u0435\u0432\u043e"
    ],
    "name:und_x_variant":[
        "Martasheva",
        "\u041c\u0430\u0440\u0442\u044e\u0448\u0435\u0432\u043e",
        "Martyushevo"
    ],
    "wof:name":"Martyushevo",
    "wof:placetype":"locality"
},
  "geometry": {"coordinates":[74.51217,57.11875],"type":"Point"}
}