{
  "type": "Feature",
  "properties": {
    "gn:admin1_code":"73",
    "gn:asciiname":"Yarak-Churma",
    "gn:country_code":"RU",
    "gn:dem":126,
    "gn:feature_class":"P",
    "gn:feature_code":"PPL",
    "gn:name":"Yarak-Churma",
    "gn:population":0,
    "gn:timezone":"Europe/Moscow",
    "iso:country":"RU",
    "name:rus_x_preferred":[
        "\u042f\u0440\u0430\u043a-\u0427\u0443\u0440\u043c\u0430"
    ],
    "wof:name":"Yarak-Churma",
    "wof:placetype":"locality"
},
  "geometry": {"coordinates":[50.1552,56.3808],"type":"Point"}
}