{
  "type": "Feature",
  "properties": {
    "gn:admin1_code":"31",
    "gn:asciiname":"Kubayka",
    "gn:country_code":"RU",
    "gn:dem":1003,
    "gn:feature_class":"P",
    "gn:feature_code":"PPL",
    "gn:name":"Kubayka",
    "gn:population":0,
    "gn:timezone":"Asia/Krasnoyarsk",
    "iso:country":"RU",
    "name:eng_x_preferred":[
        "Kubayka"
    ],
    "name:nor_x_preferred":[
        "Kubajka"
    ],
    "name:rus_x_preferred":[
        "\u041a\u0443\u0431\u0430\u0439\u043a\u0430"
    ],
    "wof:name":"Kubayka",
    "wof:placetype":"locality"
},
  "geometry": {"coordinates":[89.83221999999998,52.33889],"type":"Point"}
}