{
  "type": "Feature",
  "properties": {
    "gn:admin1_code":"93",
    "gn:asciiname":"Yuzhno-Pokrovskiy",
    "gn:country_code":"RU",
    "gn:dem":1014,
    "gn:feature_class":"P",
    "gn:feature_code":"PPL",
    "gn:name":"Yuzhno-Pokrovskiy",
    "gn:population":0,
    "gn:timezone":"Asia/Chita",
    "iso:country":"RU",
    "name:und_x_variant":[
        "Yuzhnyy Pokrovskiy",
        "Yuzhno-Pokrovskiy"
    ],
    "wof:name":"Yuzhno-Pokrovskiy",
    "wof:placetype":"locality"
},
  "geometry": {"coordinates":[117.65000000000001,50.71667],"type":"Point"}
}