{
  "type": "Feature",
  "properties": {
    "gn:admin1_code":"33",
    "gn:asciiname":"Petryata",
    "gn:cc2":"RU",
    "gn:country_code":"RU",
    "gn:dem":280,
    "gn:feature_class":"P",
    "gn:feature_code":"PPL",
    "gn:name":"Petryata",
    "gn:population":0,
    "gn:timezone":"Europe/Kirov",
    "iso:country":"RU",
    "name:che_x_preferred":[
        "\u041f\u0435\u0442\u0440\u044f\u0442\u0430"
    ],
    "name:rus_x_preferred":[
        "\u041f\u0435\u0442\u0440\u044f\u0442\u0430"
    ],
    "name:und_x_variant":[
        "Petryatskaya",
        "Petryata",
        "\u041f\u0435\u0442\u0440\u044f\u0442\u0430"
    ],
    "wof:name":"Petryata",
    "wof:placetype":"locality"
},
  "geometry": {"coordinates":[53.78333000000001,59.11666999999999],"type":"Point"}
}