{
  "type": "Feature",
  "properties": {
    "gn:admin1_code":"57.0",
    "gn:asciiname":"Blagodatka",
    "gn:country_code":"RU",
    "gn:dem":261,
    "gn:feature_class":"P",
    "gn:feature_code":"PPL",
    "gn:name":"Blagodatka",
    "gn:population":0,
    "gn:timezone":"Europe/Moscow",
    "iso:country":"RU",
    "name:rus_x_preferred":[
        "\u0411\u043b\u0430\u0433\u043e\u0434\u0430\u0442\u043a\u0430"
    ],
    "name:und_x_variant":[
        "Blagodatko",
        "Blagodatka"
    ],
    "wof:name":"Blagodatka",
    "wof:placetype":"locality"
},
  "geometry": {"coordinates":[46.42638,53.09731],"type":"Point"}
}