{
  "type": "Feature",
  "properties": {
    "gn:admin1_code":"90",
    "gn:asciiname":"Semkova",
    "gn:country_code":"RU",
    "gn:dem":104,
    "gn:feature_class":"P",
    "gn:feature_code":"PPL",
    "gn:name":"Semkova",
    "gn:population":0,
    "gn:timezone":"Asia/Yekaterinburg",
    "iso:country":"RU",
    "name:nor_x_preferred":[
        "Semkova"
    ],
    "name:rus_x_preferred":[
        "\u0421\u0435\u043c\u043a\u043e\u0432\u0430"
    ],
    "wof:name":"Semkova",
    "wof:placetype":"locality"
},
  "geometry": {"coordinates":[56.16667,58.61666999999999],"type":"Point"}
}