{
  "type": "Feature",
  "properties": {
    "gn:admin1_code":"60",
    "gn:asciiname":"Sukhlovo",
    "gn:country_code":"RU",
    "gn:dem":42,
    "gn:feature_class":"P",
    "gn:feature_code":"PPL",
    "gn:name":"Sukhlovo",
    "gn:population":0,
    "gn:timezone":"Europe/Moscow",
    "iso:country":"RU",
    "name:eng_x_preferred":[
        "Sukhlovo"
    ],
    "name:nor_x_preferred":[
        "Sukhlovo"
    ],
    "name:rus_x_preferred":[
        "\u0421\u0443\u0445\u043b\u043e\u0432\u043e"
    ],
    "name:und_x_variant":[
        "\u0421\u0443\u0445\u043b\u043e\u0432\u043e",
        "Sukhlovo"
    ],
    "wof:name":"Sukhlovo",
    "wof:placetype":"locality"
},
  "geometry": {"coordinates":[29.75099,57.98123],"type":"Point"}
}