{
  "type": "Feature",
  "properties": {
    "gn:country":"RU",
    "gn:fcode":"PPL",
    "gn:population":3778,
    "iso:country":"RU",
    "name:eng_x_preferred":[
        "Gerga"
    ],
    "name:nor_x_preferred":[
        "Gerga"
    ],
    "name:rus_x_preferred":[
        "\u0413\u0435\u0440\u0433\u0430"
    ],
    "qs:name":"Gerga",
    "qs:photos_9r":0,
    "qs:photos_sr":0,
    "qs:pop_sr":"4",
    "wof:name":"Gerga",
    "wof:placetype":"locality",
    "wof:population":3778
},
  "geometry": {"coordinates":[47.96333,42.34645],"type":"Point"}
}