{
  "type": "Feature",
  "properties": {
    "gn:admin1_code":"10",
    "gn:asciiname":"Kozhanovka",
    "gn:country_code":"RU",
    "gn:dem":142,
    "gn:feature_class":"P",
    "gn:feature_code":"PPL",
    "gn:name":"Kozhanovka",
    "gn:population":0,
    "gn:timezone":"Europe/Moscow",
    "iso:country":"RU",
    "name:rus_x_preferred":[
        "\u041a\u043e\u0436\u0430\u043d\u043e\u0432\u043a\u0430"
    ],
    "wof:name":"Kozhanovka",
    "wof:placetype":"locality"
},
  "geometry": {"coordinates":[34.07667,53.08917],"type":"Point"}
}