{
  "type": "Feature",
  "properties": {
    "gn:admin1_code":"33.0",
    "gn:asciiname":"Vasilenki",
    "gn:country_code":"RU",
    "gn:dem":127,
    "gn:feature_class":"P",
    "gn:feature_code":"PPL",
    "gn:name":"Vasil\u00ebnki",
    "gn:population":0,
    "gn:timezone":"Europe/Kirov",
    "iso:country":"RU",
    "name:rus_x_preferred":[
        "\u0412\u0430\u0441\u0438\u043b\u0451\u043d\u043a\u0438"
    ],
    "name:und_x_variant":[
        "Vasil\u00ebnki"
    ],
    "wof:name":"Vasilenki",
    "wof:placetype":"locality"
},
  "geometry": {"coordinates":[48.84068,57.74875],"type":"Point"}
}