{
  "type": "Feature",
  "properties": {
    "gn:admin1_code":"77",
    "gn:asciiname":"Nosovitsy",
    "gn:country_code":"RU",
    "gn:dem":228,
    "gn:feature_class":"P",
    "gn:feature_code":"PPL",
    "gn:name":"Nosovitsy",
    "gn:population":0,
    "gn:timezone":"Europe/Moscow",
    "iso:country":"RU",
    "name:rus_x_preferred":[
        "\u041d\u043e\u0441\u043e\u0432\u0438\u0446\u044b"
    ],
    "name:und_x_variant":[
        "Nosovitsa",
        "Nosovitsy"
    ],
    "wof:name":"Nosovitsy",
    "wof:placetype":"locality"
},
  "geometry": {"coordinates":[32.81791,57.08813000000001],"type":"Point"}
}