{
  "type": "Feature",
  "properties": {
    "gn:admin1_code":"64",
    "gn:asciiname":"Suvorovka",
    "gn:country_code":"RU",
    "gn:dem":3,
    "gn:feature_class":"P",
    "gn:feature_code":"PPL",
    "gn:name":"Suvorovka",
    "gn:population":0,
    "gn:timezone":"Asia/Sakhalin",
    "iso:country":"RU",
    "wof:name":"Suvorovka",
    "wof:placetype":"locality"
},
  "geometry": {"coordinates":[141.98333,53.46666999999999],"type":"Point"}
}