{
  "type": "Feature",
  "properties": {
    "gn:admin1_code":"67",
    "gn:asciiname":"Kholmanka",
    "gn:country_code":"RU",
    "gn:dem":55,
    "gn:feature_class":"P",
    "gn:feature_code":"PPL",
    "gn:name":"Kholmanka",
    "gn:population":0,
    "gn:timezone":"Europe/Saratov",
    "iso:country":"RU",
    "name:eng_x_preferred":[
        "Kholmanka"
    ],
    "name:nor_x_preferred":[
        "Kholmanka"
    ],
    "name:rus_x_preferred":[
        "\u0425\u043e\u043b\u043c\u0430\u043d\u043a\u0430"
    ],
    "name:und_x_variant":[
        "Fedotov",
        "Kholmanskiy",
        "Kholmanki"
    ],
    "wof:name":"Kholmanka",
    "wof:placetype":"locality"
},
  "geometry": {"coordinates":[50.42921,51.66318],"type":"Point"}
}