{
  "type": "Feature",
  "properties": {
    "gn:admin1_code":"77",
    "gn:asciiname":"Malyy Dorok",
    "gn:country_code":"RU",
    "gn:dem":210,
    "gn:feature_class":"P",
    "gn:feature_code":"PPL",
    "gn:name":"Malyy Dorok",
    "gn:population":0,
    "gn:timezone":"Europe/Moscow",
    "iso:country":"RU",
    "name:rus_x_preferred":[
        "\u041c\u0430\u043b\u044b\u0439 \u0414\u043e\u0440\u043e\u043a"
    ],
    "name:und_x_variant":[
        "\u041c\u0430\u043b\u044b\u0439 \u0414\u043e\u0440\u043e\u043a"
    ],
    "wof:name":"Malyy Dorok",
    "wof:placetype":"locality"
},
  "geometry": {"coordinates":[36.9688,57.9534],"type":"Point"}
}