{
  "type": "Feature",
  "properties": {
    "gn:admin1_code":"7.0",
    "gn:asciiname":"Breusovo",
    "gn:cc2":"RU",
    "gn:country_code":"RU",
    "gn:dem":14,
    "gn:feature_class":"P",
    "gn:feature_code":"PPL",
    "gn:name":"Breusovo",
    "gn:population":0,
    "gn:timezone":"Europe/Astrakhan",
    "iso:country":"RU",
    "name:rus_x_preferred":[
        "\u0411\u0440\u0435\u0443\u0441\u043e\u0432\u043e"
    ],
    "name:und_x_variant":[
        "Breusova",
        "Breusovo"
    ],
    "wof:name":"Breusovo",
    "wof:placetype":"locality"
},
  "geometry": {"coordinates":[45.88333,48.63333],"type":"Point"}
}