{
  "type": "Feature",
  "properties": {
    "gn:admin1_code":"52",
    "gn:asciiname":"Malyy Utorgosh",
    "gn:country_code":"RU",
    "gn:dem":68,
    "gn:feature_class":"P",
    "gn:feature_code":"PPL",
    "gn:name":"Malyy Utorgosh",
    "gn:population":0,
    "gn:timezone":"Europe/Moscow",
    "iso:country":"RU",
    "name:eng_x_preferred":[
        "Malyy Utorgosh"
    ],
    "name:nor_x_preferred":[
        "Mal.Utorgosj"
    ],
    "name:rus_x_preferred":[
        "\u041c\u0430\u043b.\u0423\u0442\u043e\u0440\u0433\u043e\u0448"
    ],
    "name:rus_x_variant":[
        "\u041c\u0430\u043b\u044b\u0439 \u0423\u0442\u043e\u0440\u0433\u043e\u0448"
    ],
    "name:und_x_variant":[
        "\u041c\u0430\u043b\u044b\u0439 \u0423\u0442\u043e\u0440\u0433\u043e\u0448"
    ],
    "wof:name":"Malyy Utorgosh",
    "wof:placetype":"locality"
},
  "geometry": {"coordinates":[29.91389,58.26444],"type":"Point"}
}