{
  "type": "Feature",
  "properties": {
    "gn:admin1_code":"77",
    "gn:asciiname":"Shchetinino",
    "gn:country_code":"RU",
    "gn:dem":215,
    "gn:feature_class":"P",
    "gn:feature_code":"PPL",
    "gn:name":"Shchetinino",
    "gn:population":0,
    "gn:timezone":"Europe/Moscow",
    "iso:country":"RU",
    "name:rus_x_preferred":[
        "\u0429\u0435\u0442\u0438\u043d\u0438\u043d\u043e"
    ],
    "name:und_x_variant":[
        "\u0429\u0435\u0442\u0438\u043d\u0438\u043d\u043e"
    ],
    "wof:name":"Shchetinino",
    "wof:placetype":"locality"
},
  "geometry": {"coordinates":[34.53076,56.42874000000001],"type":"Point"}
}