{
  "type": "Feature",
  "properties": {
    "gn:admin1_code":"52.0",
    "gn:asciiname":"Chernavino",
    "gn:country_code":"RU",
    "gn:dem":167,
    "gn:feature_class":"P",
    "gn:feature_code":"PPL",
    "gn:name":"Chernavino",
    "gn:population":0,
    "gn:timezone":"Europe/Moscow",
    "iso:country":"RU",
    "name:rus_x_preferred":[
        "\u0427\u0435\u0440\u043d\u0430\u0432\u0438\u043d\u043e"
    ],
    "wof:name":"Chernavino",
    "wof:placetype":"locality"
},
  "geometry": {"coordinates":[35.46667,58.68333000000001],"type":"Point"}
}