{
  "type": "Feature",
  "properties": {
    "gn:admin1_code":"63",
    "gn:asciiname":"Zludyanka",
    "gn:country_code":"RU",
    "gn:dem":8,
    "gn:feature_class":"P",
    "gn:feature_code":"PPL",
    "gn:name":"Zludyanka",
    "gn:population":0,
    "gn:timezone":"Asia/Magadan",
    "iso:country":"RU",
    "wof:name":"Zludyanka",
    "wof:placetype":"locality"
},
  "geometry": {"coordinates":[160.69983999999999,68.40191999999999],"type":"Point"}
}