{
  "type": "Feature",
  "properties": {
    "gn:admin1_code":"10",
    "gn:asciiname":"Smotrova Buda",
    "gn:country_code":"RU",
    "gn:dem":177,
    "gn:feature_class":"P",
    "gn:feature_code":"PPL",
    "gn:name":"Smotrova Buda",
    "gn:population":0,
    "gn:timezone":"Europe/Moscow",
    "iso:country":"RU",
    "name:eng_x_preferred":[
        "Smotrova Buda"
    ],
    "name:nor_x_preferred":[
        "Smotrova-Buda"
    ],
    "name:rus_x_preferred":[
        "\u0421\u043c\u043e\u0442\u0440\u043e\u0432\u0430-\u0411\u0443\u0434\u0430"
    ],
    "name:rus_x_variant":[
        "\u0421\u043c\u043e\u0442\u0440\u043e\u0432\u0430 \u0411\u0443\u0434\u0430"
    ],
    "name:und_x_variant":[
        "\u0421\u043c\u043e\u0442\u0440\u043e\u0432\u0430 \u0411\u0443\u0434\u0430"
    ],
    "wof:name":"Smotrova Buda",
    "wof:placetype":"locality"
},
  "geometry": {"coordinates":[32.29142,52.67417],"type":"Point"}
}