{
  "type": "Feature",
  "properties": {
    "gn:admin1_code":"61",
    "gn:asciiname":"Levoberezhnyy",
    "gn:country_code":"RU",
    "gn:dem":9,
    "gn:feature_class":"P",
    "gn:feature_code":"PPL",
    "gn:name":"Levoberezhnyy",
    "gn:population":0,
    "gn:timezone":"Europe/Moscow",
    "iso:country":"RU",
    "name:rus_x_preferred":[
        "\u041b\u0435\u0432\u043e\u0431\u0435\u0440\u0435\u0436\u043d\u044b\u0439"
    ],
    "name:und_x_variant":[
        "Aleksandrovka",
        "Levoberezhnyy"
    ],
    "wof:name":"Levoberezhnyy",
    "wof:placetype":"locality"
},
  "geometry": {"coordinates":[39.62937,46.95677],"type":"Point"}
}