{
  "type": "Feature",
  "properties": {
    "gn:admin1_code":"33",
    "gn:asciiname":"Tolokonniki",
    "gn:country_code":"RU",
    "gn:dem":184,
    "gn:feature_class":"P",
    "gn:feature_code":"PPL",
    "gn:name":"Tolokonniki",
    "gn:population":0,
    "gn:timezone":"Europe/Kirov",
    "iso:country":"RU",
    "name:eng_x_preferred":[
        "Tolokonniki"
    ],
    "name:nor_x_preferred":[
        "Tolokonniki"
    ],
    "name:rus_x_preferred":[
        "\u0422\u043e\u043b\u043e\u043a\u043e\u043d\u043d\u0438\u043a\u0438"
    ],
    "wof:name":"Tolokonniki",
    "wof:placetype":"locality"
},
  "geometry": {"coordinates":[50.50841,58.11825],"type":"Point"}
}