{
  "type": "Feature",
  "properties": {
    "gn:admin1_code":"61",
    "gn:asciiname":"Istomino",
    "gn:cc2":"RU",
    "gn:country_code":"RU",
    "gn:dem":17,
    "gn:feature_class":"P",
    "gn:feature_code":"PPL",
    "gn:name":"Istomino",
    "gn:population":0,
    "gn:timezone":"Europe/Moscow",
    "iso:country":"RU",
    "name:eng_x_preferred":[
        "Istomino"
    ],
    "name:nor_x_preferred":[
        "Istomino"
    ],
    "name:rus_x_preferred":[
        "\u0418\u0441\u0442\u043e\u043c\u0438\u043d\u043e"
    ],
    "name:und_x_variant":[
        "Zhlobin",
        "Kolkhozny",
        "Kolkhozyy"
    ],
    "wof:name":"Istomino",
    "wof:placetype":"locality"
},
  "geometry": {"coordinates":[39.86639,47.0825],"type":"Point"}
}