{
  "type": "Feature",
  "properties": {
    "gn:admin1_code":"92",
    "gn:asciiname":"Kozyrevskiy",
    "gn:country_code":"RU",
    "gn:dem":49,
    "gn:feature_class":"P",
    "gn:feature_code":"PPL",
    "gn:name":"Kozyrevskiy",
    "gn:population":0,
    "gn:timezone":"Asia/Kamchatka",
    "iso:country":"RU",
    "name:rus_x_preferred":[
        "\u041a\u043e\u0437\u044b\u0440\u0435\u0432\u0441\u043a\u0438\u0439"
    ],
    "wof:name":"Kozyrevskiy",
    "wof:placetype":"locality"
},
  "geometry": {"coordinates":[160.06666999999999,56.26667],"type":"Point"}
}