{
  "type": "Feature",
  "properties": {
    "gn:admin1_code":"52",
    "gn:asciiname":"Klevitsy",
    "gn:country_code":"RU",
    "gn:dem":72,
    "gn:feature_class":"P",
    "gn:feature_code":"PPL",
    "gn:name":"Klevitsy",
    "gn:population":0,
    "gn:timezone":"Europe/Moscow",
    "iso:country":"RU",
    "name:rus_x_preferred":[
        "\u041a\u043b\u0435\u0432\u0438\u0446\u044b"
    ],
    "name:und_x_variant":[
        "\u041a\u043b\u0435\u0432\u0438\u0446\u044b"
    ],
    "wof:name":"Klevitsy",
    "wof:placetype":"locality"
},
  "geometry": {"coordinates":[30.49089,57.97815],"type":"Point"}
}