{
  "type": "Feature",
  "properties": {
    "gn:admin1_code":"69",
    "gn:asciiname":"Kovalevka",
    "gn:country_code":"RU",
    "gn:dem":228,
    "gn:feature_class":"P",
    "gn:feature_code":"PPL",
    "gn:name":"Koval\u00ebvka",
    "gn:population":0,
    "gn:timezone":"Europe/Moscow",
    "iso:country":"RU",
    "name:rus_x_preferred":[
        "\u041a\u043e\u0432\u0430\u043b\u0451\u0432\u043a\u0430"
    ],
    "name:und_x_variant":[
        "Koval\u00ebvka"
    ],
    "wof:name":"Kovalevka",
    "wof:placetype":"locality"
},
  "geometry": {"coordinates":[32.10572,54.70205],"type":"Point"}
}