{
  "type": "Feature",
  "properties": {
    "gn:admin1_code":"17",
    "gn:admin2_code":"557977",
    "gn:asciiname":"Ala",
    "gn:country_code":"RU",
    "gn:dem":1180,
    "gn:feature_class":"P",
    "gn:feature_code":"PPL",
    "gn:name":"Ala",
    "gn:population":0,
    "gn:timezone":"Europe/Moscow",
    "iso:country":"RU",
    "name:nor_x_preferred":[
        "Ala"
    ],
    "name:rus_x_preferred":[
        "\u0410\u043b\u0430"
    ],
    "wof:name":"Ala",
    "wof:placetype":"locality"
},
  "geometry": {"coordinates":[46.83833,42.41583],"type":"Point"}
}