{
  "type": "Feature",
  "properties": {
    "gn:admin1_code":"17",
    "gn:admin2_code":"557977",
    "gn:asciiname":"Ala",
    "gn:country_code":"RU",
    "gn:dem":1180,
    "gn:feature_class":"P",
    "gn:feature_code":"PPL",
    "gn:name":"Ala",
    "gn:population":0,
    "gn:timezone":"Europe/Moscow",
    "iso:country":"RU",
    "name:arg_x_preferred":[
        "Ala"
    ],
    "name:ast_x_preferred":[
        "Nala"
    ],
    "name:bel_x_preferred":[
        "\u0410\u043b\u0430"
    ],
    "name:cat_x_preferred":[
        "Ala"
    ],
    "name:ceb_x_preferred":[
        "Ala"
    ],
    "name:ces_x_preferred":[
        "Ala"
    ],
    "name:deu_x_preferred":[
        "Ala"
    ],
    "name:est_x_preferred":[
        "Ala"
    ],
    "name:eus_x_preferred":[
        "Ala"
    ],
    "name:fas_x_preferred":[
        "\u0639\u0644\u0627\u0621"
    ],
    "name:fin_x_preferred":[
        "Ala"
    ],
    "name:fra_x_preferred":[
        "Ala"
    ],
    "name:heb_x_preferred":[
        "Ala"
    ],
    "name:hun_x_preferred":[
        "Ala"
    ],
    "name:hye_x_preferred":[
        "\u0531\u056c\u0561"
    ],
    "name:lat_x_preferred":[
        "Ala"
    ],
    "name:lav_x_preferred":[
        "ALA"
    ],
    "name:lmo_x_preferred":[
        "Ala"
    ],
    "name:nld_x_preferred":[
        "Ala"
    ],
    "name:nor_x_preferred":[
        "Ala"
    ],
    "name:pms_x_preferred":[
        "Ala"
    ],
    "name:pol_x_preferred":[
        "Ala"
    ],
    "name:por_x_preferred":[
        "Ala"
    ],
    "name:rus_x_preferred":[
        "\u0410\u043b\u0430"
    ],
    "name:scn_x_preferred":[
        "Ala"
    ],
    "name:spa_x_preferred":[
        "Ala"
    ],
    "name:srp_x_preferred":[
        "Ala"
    ],
    "name:swe_x_preferred":[
        "Ala"
    ],
    "name:ukr_x_preferred":[
        "\u0410\u043b\u0430"
    ],
    "name:vol_x_preferred":[
        "Ala"
    ],
    "wof:name":"Ala",
    "wof:placetype":"locality"
},
  "geometry": {"coordinates":[46.83833,42.41583],"type":"Point"}
}