{
  "type": "Feature",
  "properties": {
    "gn:admin1_code":"56",
    "gn:asciiname":"Kukuy",
    "gn:country_code":"RU",
    "gn:dem":200,
    "gn:feature_class":"P",
    "gn:feature_code":"PPL",
    "gn:name":"Kukuy",
    "gn:population":0,
    "gn:timezone":"Europe/Moscow",
    "iso:country":"RU",
    "name:rus_x_preferred":[
        "\u041a\u0443\u043a\u0443\u0439"
    ],
    "name:und_x_variant":[
        "\u041a\u0443\u043a\u0443\u0439"
    ],
    "wof:name":"Kukuy",
    "wof:placetype":"locality"
},
  "geometry": {"coordinates":[37.66423,52.67802],"type":"Point"}
}