{
  "type": "Feature",
  "properties": {
    "gn:admin1_code":"3",
    "gn:asciiname":"Uozhan",
    "gn:country_code":"RU",
    "gn:dem":547,
    "gn:feature_class":"P",
    "gn:feature_code":"PPL",
    "gn:name":"Uozhan",
    "gn:population":0,
    "gn:timezone":"Asia/Omsk",
    "iso:country":"RU",
    "name:che_x_preferred":[
        "\u0423\u043e\u0436\u0430\u043d"
    ],
    "name:eng_x_preferred":[
        "Uozhan"
    ],
    "name:nor_x_preferred":[
        "Uozjan"
    ],
    "name:rus_x_preferred":[
        "\u0423\u043e\u0436\u0430\u043d"
    ],
    "name:tat_x_preferred":[
        "\u0423\u043e\u0436\u0430\u043d"
    ],
    "name:ukr_x_preferred":[
        "\u0423\u043e\u0436\u0430\u043d"
    ],
    "name:und_x_variant":[
        "Uzzhan"
    ],
    "wof:name":"Uozhan",
    "wof:placetype":"locality"
},
  "geometry": {"coordinates":[86.14914,51.32244],"type":"Point"}
}