{
  "type": "Feature",
  "properties": {
    "gn:admin1_code":"90",
    "gn:asciiname":"Pleso",
    "gn:country_code":"RU",
    "gn:dem":126,
    "gn:feature_class":"P",
    "gn:feature_code":"PPL",
    "gn:name":"Pl\u00ebso",
    "gn:population":0,
    "gn:timezone":"Asia/Yekaterinburg",
    "iso:country":"RU",
    "name:eng_x_preferred":[
        "Pl\u00ebso"
    ],
    "name:nor_x_preferred":[
        "Pleso"
    ],
    "name:rus_x_preferred":[
        "\u041f\u043b\u0435\u0441\u043e"
    ],
    "name:rus_x_variant":[
        "\u041f\u043b\u0451\u0441\u043e"
    ],
    "name:und_x_variant":[
        "Ploso"
    ],
    "wof:name":"Pleso",
    "wof:placetype":"locality"
},
  "geometry": {"coordinates":[53.89744,60.25591],"type":"Point"}
}