{
  "type": "Feature",
  "properties": {
    "gn:admin1_code":"85",
    "gn:asciiname":"Skorodum",
    "gn:country_code":"RU",
    "gn:dem":75,
    "gn:feature_class":"P",
    "gn:feature_code":"PPL",
    "gn:name":"Skorodum",
    "gn:population":0,
    "gn:timezone":"Europe/Moscow",
    "iso:country":"RU",
    "name:rus_x_preferred":[
        "\u0421\u043a\u043e\u0440\u043e\u0434\u0443\u043c"
    ],
    "name:und_x_variant":[
        "\u0421\u043a\u043e\u0440\u043e\u0434\u0443\u043c"
    ],
    "wof:name":"Skorodum",
    "wof:placetype":"locality"
},
  "geometry": {"coordinates":[46.2022,60.6177],"type":"Point"}
}