{
  "type": "Feature",
  "properties": {
    "gn:admin1_code":"71",
    "gn:asciiname":"Lomovskiy",
    "gn:country_code":"RU",
    "gn:dem":286,
    "gn:feature_class":"P",
    "gn:feature_code":"PPL",
    "gn:name":"Lomovskiy",
    "gn:population":0,
    "gn:timezone":"Asia/Yekaterinburg",
    "iso:country":"RU",
    "name:rus_x_preferred":[
        "\u041b\u043e\u043c\u043e\u0432\u0441\u043a\u0438\u0439"
    ],
    "wof:name":"Lomovskiy",
    "wof:placetype":"locality"
},
  "geometry": {"coordinates":[59.8834,57.4551],"type":"Point"}
}