{
  "type": "Feature",
  "properties": {
    "gn:admin1_code":"60",
    "gn:asciiname":"Kursko",
    "gn:country_code":"RU",
    "gn:dem":96,
    "gn:feature_class":"P",
    "gn:feature_code":"PPL",
    "gn:name":"Kursko",
    "gn:population":0,
    "gn:timezone":"Europe/Moscow",
    "iso:country":"RU",
    "name:azb_x_preferred":[
        "\u06a9\u0648\u0631\u0633\u06a9\u0648"
    ],
    "name:ceb_x_preferred":[
        "Kursko"
    ],
    "name:fas_x_preferred":[
        "\u06a9\u0648\u0631\u0633\u06a9\u0648"
    ],
    "name:fra_x_preferred":[
        "Kursko"
    ],
    "name:nld_x_preferred":[
        "Kursko"
    ],
    "name:pol_x_preferred":[
        "Kursko"
    ],
    "name:rus_x_preferred":[
        "\u041a\u0443\u0440\u0441\u043a\u043e"
    ],
    "name:ukr_x_preferred":[
        "\u041a\u0443\u0440\u0441\u044c\u043a\u043e"
    ],
    "name:und_x_variant":[
        "\u041a\u0443\u0440\u0441\u043a\u043e"
    ],
    "wof:name":"Kursko",
    "wof:placetype":"locality"
},
  "geometry": {"coordinates":[28.8333,58.3822],"type":"Point"}
}