{
  "type": "Feature",
  "properties": {
    "gn:admin1_code":"33",
    "gn:asciiname":"Tolstik",
    "gn:country_code":"RU",
    "gn:dem":96,
    "gn:feature_class":"P",
    "gn:feature_code":"PPL",
    "gn:name":"Tolstik",
    "gn:population":0,
    "gn:timezone":"Europe/Kirov",
    "iso:country":"RU",
    "name:eng_x_preferred":[
        "Tolstik"
    ],
    "name:nor_x_preferred":[
        "Tolstik"
    ],
    "name:rus_x_preferred":[
        "\u0422\u043e\u043b\u0441\u0442\u0438\u043a"
    ],
    "wof:name":"Tolstik",
    "wof:placetype":"locality"
},
  "geometry": {"coordinates":[49.32097,57.50126],"type":"Point"}
}