{
  "type": "Feature",
  "properties": {
    "gn:admin1_code":"55",
    "gn:asciiname":"Semykino",
    "gn:country_code":"RU",
    "gn:dem":315,
    "gn:feature_class":"P",
    "gn:feature_code":"PPL",
    "gn:name":"Semykino",
    "gn:population":0,
    "gn:timezone":"Asia/Yekaterinburg",
    "iso:country":"RU",
    "name:rus_x_preferred":[
        "\u0421\u0435\u043c\u044b\u043a\u0438\u043d\u043e"
    ],
    "name:und_x_variant":[
        "\u0421\u0435\u043c\u044b\u043a\u0438\u043d\u043e"
    ],
    "wof:name":"Semykino",
    "wof:placetype":"locality"
},
  "geometry": {"coordinates":[53.0221,54.32869],"type":"Point"}
}