{
  "type": "Feature",
  "properties": {
    "gn:admin1_code":"68",
    "gn:asciiname":"Kusovo",
    "gn:country_code":"RU",
    "gn:dem":413,
    "gn:feature_class":"P",
    "gn:feature_code":"PPL",
    "gn:name":"Kusovo",
    "gn:population":0,
    "gn:timezone":"Europe/Moscow",
    "iso:country":"RU",
    "name:rus_x_preferred":[
        "\u041a\u0443\u0441\u043e\u0432\u043e"
    ],
    "name:und_x_variant":[
        "Prikurpskiy",
        "Kusov",
        "Kusovo"
    ],
    "wof:name":"Kusovo",
    "wof:placetype":"locality"
},
  "geometry": {"coordinates":[44.42376,43.44768],"type":"Point"}
}