{
  "type": "Feature",
  "properties": {
    "gn:admin1_code":"8.0",
    "gn:asciiname":"Galiullinka",
    "gn:country_code":"RU",
    "gn:dem":177,
    "gn:feature_class":"P",
    "gn:feature_code":"PPL",
    "gn:name":"Galiullinka",
    "gn:population":0,
    "gn:timezone":"Asia/Yekaterinburg",
    "iso:country":"RU",
    "name:aze_x_preferred":[
        "Q\u0259liulla"
    ],
    "name:bak_x_preferred":[
        "\u0492\u04d9\u043b\u0438\u0443\u043b\u043b\u0430"
    ],
    "name:che_x_preferred":[
        "\u0413\u0430\u043b\u0438\u0443\u043b\u0438\u043d\u043a\u0430"
    ],
    "name:hye_x_preferred":[
        "\u0533\u0561\u056c\u056b\u0578\u0582\u056c\u056b\u0576\u056f\u0561"
    ],
    "name:kaz_x_preferred":[
        "\u0413\u0430\u043b\u0438\u0443\u043b\u0438\u043d\u043a\u0430"
    ],
    "name:rus_x_preferred":[
        "\u0413\u0430\u043b\u0438\u0443\u043b\u043b\u0438\u043d\u043a\u0430"
    ],
    "name:tat_x_preferred":[
        "\u0413\u0430\u043b\u0438\u0443\u043b\u043b\u0430"
    ],
    "name:und_x_variant":[
        "Goliullinka",
        "Galiullinka"
    ],
    "wof:name":"Galiullinka",
    "wof:placetype":"locality"
},
  "geometry": {"coordinates":[53.55889000000001,55.18972],"type":"Point"}
}