{
  "type": "Feature",
  "properties": {
    "gn:admin1_code":"38",
    "gn:asciiname":"Chelbas",
    "gn:country_code":"RU",
    "gn:dem":51,
    "gn:feature_class":"P",
    "gn:feature_code":"PPL",
    "gn:name":"Chelbas",
    "gn:population":0,
    "gn:timezone":"Europe/Moscow",
    "iso:country":"RU",
    "name:rus_x_preferred":[
        "\u0427\u0435\u043b\u0431\u0430\u0441"
    ],
    "wof:name":"Chelbas",
    "wof:placetype":"locality"
},
  "geometry": {"coordinates":[39.98931,45.81015],"type":"Point"}
}