{
  "type": "Feature",
  "properties": {
    "gn:admin1_code":"83",
    "gn:asciiname":"Kolenovo",
    "gn:cc2":"RU",
    "gn:country_code":"RU",
    "gn:dem":168,
    "gn:feature_class":"P",
    "gn:feature_code":"PPL",
    "gn:name":"Kolenovo",
    "gn:population":0,
    "gn:timezone":"Europe/Moscow",
    "iso:country":"RU",
    "name:rus_x_preferred":[
        "\u041a\u043e\u043b\u0435\u043d\u043e\u0432\u043e"
    ],
    "name:und_x_variant":[
        "Kolenova",
        "Kolenovo",
        "\u041a\u043e\u043b\u0435\u043d\u043e\u0432\u043e"
    ],
    "wof:name":"Kolenovo",
    "wof:placetype":"locality"
},
  "geometry": {"coordinates":[39.16667,56.11666999999999],"type":"Point"}
}