{
  "type": "Feature",
  "properties": {
    "gn:admin1_code":"10",
    "gn:asciiname":"Novosovetskiy",
    "gn:country_code":"RU",
    "gn:dem":177,
    "gn:feature_class":"P",
    "gn:feature_code":"PPL",
    "gn:name":"Novosovetskiy",
    "gn:population":0,
    "gn:timezone":"Europe/Moscow",
    "iso:country":"RU",
    "name:rus_x_preferred":[
        "\u041d\u043e\u0432\u043e\u0441\u043e\u0432\u0435\u0442\u0441\u043a\u0438\u0439"
    ],
    "wof:name":"Novosovetskiy",
    "wof:placetype":"locality"
},
  "geometry": {"coordinates":[33.5234,53.1907],"type":"Point"}
}