{
  "type": "Feature",
  "properties": {
    "gn:admin1_code":"17.0",
    "gn:asciiname":"Maran",
    "gn:country_code":"RU",
    "gn:dem":1938,
    "gn:feature_class":"P",
    "gn:feature_code":"PPL",
    "gn:name":"Maran",
    "gn:population":0,
    "gn:timezone":"Europe/Moscow",
    "iso:country":"RU",
    "name:fra_x_preferred":[
        "Maran"
    ],
    "name:heb_x_preferred":[
        "\u05de\u05e8\u05df"
    ],
    "name:lad_x_preferred":[
        "Maran"
    ],
    "name:spa_x_preferred":[
        "Maran"
    ],
    "name:vie_x_preferred":[
        "Maran"
    ],
    "wof:name":"Maran",
    "wof:placetype":"locality"
},
  "geometry": {"coordinates":[46.63556,42.36444],"type":"Point"}
}