{
  "type": "Feature",
  "properties": {
    "gn:admin1_code":"17.0",
    "gn:asciiname":"Maran",
    "gn:country_code":"RU",
    "gn:dem":1938,
    "gn:feature_class":"P",
    "gn:feature_code":"PPL",
    "gn:name":"Maran",
    "gn:population":0,
    "gn:timezone":"Europe/Moscow",
    "iso:country":"RU",
    "wof:name":"Maran",
    "wof:placetype":"locality"
},
  "geometry": {"coordinates":[46.63556,42.36444],"type":"Point"}
}