{
  "type": "Feature",
  "properties": {
    "gn:admin1_code":"33",
    "gn:asciiname":"Kul'tura",
    "gn:country_code":"RU",
    "gn:dem":169,
    "gn:feature_class":"P",
    "gn:feature_code":"PPL",
    "gn:name":"Kul\u2019tura",
    "gn:population":0,
    "gn:timezone":"Europe/Kirov",
    "iso:country":"RU",
    "name:rus_x_preferred":[
        "\u041a\u0443\u043b\u044c\u0442\u0443\u0440\u0430"
    ],
    "name:und_x_variant":[
        "Kul\u2019tura",
        "\u041a\u0443\u043b\u044c\u0442\u0443\u0440\u0430"
    ],
    "wof:name":"Kul'tura",
    "wof:placetype":"locality"
},
  "geometry": {"coordinates":[48.2486,59.8301],"type":"Point"}
}