{
  "type": "Feature",
  "properties": {
    "gn:admin1_code":"63",
    "gn:asciiname":"Basylay-Alasa",
    "gn:country_code":"RU",
    "gn:dem":235,
    "gn:feature_class":"P",
    "gn:feature_code":"PPL",
    "gn:name":"Basylay-Alasa",
    "gn:population":0,
    "gn:timezone":"Asia/Yakutsk",
    "iso:country":"RU",
    "name:nor_x_preferred":[
        "Basylaj-Alasa"
    ],
    "name:rus_x_preferred":[
        "\u0411\u0430\u0441\u044b\u043b\u0430\u0439-\u0410\u043b\u0430\u0441\u0430"
    ],
    "name:und_x_variant":[
        "Basylay-Alaasa",
        "Basylay-Alasa"
    ],
    "wof:name":"Basylay-Alasa",
    "wof:placetype":"locality"
},
  "geometry": {"coordinates":[132.57578999999998,61.7892],"type":"Point"}
}