{
  "type": "Feature",
  "properties": {
    "gn:admin1_code":"52",
    "gn:asciiname":"Ossiya",
    "gn:country_code":"RU",
    "gn:dem":48,
    "gn:feature_class":"P",
    "gn:feature_code":"PPL",
    "gn:name":"Ossiya",
    "gn:population":0,
    "gn:timezone":"Europe/Moscow",
    "iso:country":"RU",
    "name:eng_x_preferred":[
        "Ossiya"
    ],
    "name:nor_x_preferred":[
        "Osia"
    ],
    "name:rus_x_preferred":[
        "\u041e\u0441\u0438\u044f"
    ],
    "name:rus_x_variant":[
        "\u041e\u0441\u0441\u0438\u044f"
    ],
    "name:und_x_variant":[
        "Osiya",
        "Ossiya",
        "\u041e\u0441\u0441\u0438\u044f"
    ],
    "wof:name":"Ossiya",
    "wof:placetype":"locality"
},
  "geometry": {"coordinates":[31.24217,58.7547],"type":"Point"}
}