{
  "type": "Feature",
  "properties": {
    "gn:admin1_code":"47",
    "gn:asciiname":"Kholmets",
    "gn:country_code":"RU",
    "gn:dem":238,
    "gn:feature_class":"P",
    "gn:feature_code":"PPL",
    "gn:name":"Kholmets",
    "gn:population":0,
    "gn:timezone":"Europe/Moscow",
    "iso:country":"RU",
    "name:eng_x_preferred":[
        "Kholmets"
    ],
    "name:nor_x_preferred":[
        "Khelmets"
    ],
    "name:rus_x_preferred":[
        "\u0425\u044d\u043b\u043c\u0435\u0446"
    ],
    "name:rus_x_variant":[
        "\u0425\u043e\u043b\u043c\u0435\u0446"
    ],
    "wof:name":"Kholmets",
    "wof:placetype":"locality"
},
  "geometry": {"coordinates":[35.50939,55.84733000000001],"type":"Point"}
}