{
  "type": "Feature",
  "properties": {
    "gn:admin1_code":"8",
    "gn:asciiname":"Ural'sk",
    "gn:country_code":"RU",
    "gn:dem":457,
    "gn:feature_class":"P",
    "gn:feature_code":"PPL",
    "gn:name":"Ural\u2019sk",
    "gn:population":0,
    "gn:timezone":"Asia/Yekaterinburg",
    "iso:country":"RU",
    "name:eng_x_preferred":[
        "Ural'sk"
    ],
    "name:nor_x_preferred":[
        "Uralsk"
    ],
    "name:rus_x_preferred":[
        "\u0423\u0440\u0430\u043b\u044c\u0441\u043a"
    ],
    "name:und_x_variant":[
        "Ural\u2019skiy",
        "Ural\u2019sk"
    ],
    "wof:name":"Ural'sk",
    "wof:placetype":"locality"
},
  "geometry": {"coordinates":[59.125,54.1219],"type":"Point"}
}