{
  "type": "Feature",
  "properties": {
    "gn:admin1_code":"47",
    "gn:asciiname":"Zakubezh'ye",
    "gn:country_code":"RU",
    "gn:dem":140,
    "gn:feature_class":"P",
    "gn:feature_code":"PPL",
    "gn:name":"Zakubezh\u2019ye",
    "gn:population":0,
    "gn:timezone":"Europe/Moscow",
    "iso:country":"RU",
    "name:eng_x_preferred":[
        "Zakubezh'ye"
    ],
    "name:nor_x_preferred":[
        "Zakubezje"
    ],
    "name:rus_x_preferred":[
        "\u0417\u0430\u043a\u0443\u0431\u0435\u0436\u044c\u0435"
    ],
    "name:und_x_variant":[
        "Zakubezh\u2019ye"
    ],
    "wof:name":"Zakubezh'ye",
    "wof:placetype":"locality"
},
  "geometry": {"coordinates":[37.98333,56.65],"type":"Point"}
}