{
  "type": "Feature",
  "properties": {
    "gn:admin1_code":"69",
    "gn:asciiname":"Sofiyevka",
    "gn:country_code":"RU",
    "gn:dem":238,
    "gn:feature_class":"P",
    "gn:feature_code":"PPL",
    "gn:name":"Sofiyevka",
    "gn:population":0,
    "gn:timezone":"Europe/Moscow",
    "iso:country":"RU",
    "name:rus_x_preferred":[
        "\u0421\u043e\u0444\u0438\u0435\u0432\u043a\u0430"
    ],
    "wof:name":"Sofiyevka",
    "wof:placetype":"locality"
},
  "geometry": {"coordinates":[33.1943,54.62833000000001],"type":"Point"}
}