{
  "type": "Feature",
  "properties": {
    "gn:admin1_code":"25",
    "gn:asciiname":"Arefino",
    "gn:country_code":"RU",
    "gn:dem":235,
    "gn:feature_class":"P",
    "gn:feature_code":"PPL",
    "gn:name":"Arefino",
    "gn:population":0,
    "gn:timezone":"Europe/Moscow",
    "iso:country":"RU",
    "name:nor_x_preferred":[
        "Arefino"
    ],
    "name:rus_x_preferred":[
        "\u0410\u0440\u0435\u0444\u0438\u043d\u043e"
    ],
    "wof:name":"Arefino",
    "wof:placetype":"locality"
},
  "geometry": {"coordinates":[33.79722,54.39056],"type":"Point"}
}