{
  "type": "Feature",
  "properties": {
    "gn:admin1_code":"51",
    "gn:asciiname":"Oshary",
    "gn:country_code":"RU",
    "gn:dem":152,
    "gn:feature_class":"P",
    "gn:feature_code":"PPL",
    "gn:name":"Oshary",
    "gn:population":0,
    "gn:timezone":"Europe/Moscow",
    "iso:country":"RU",
    "name:eng_x_preferred":[
        "Oshary"
    ],
    "name:nor_x_preferred":[
        "Osjary"
    ],
    "name:rus_x_preferred":[
        "\u041e\u0448\u0430\u0440\u044b"
    ],
    "wof:name":"Oshary",
    "wof:placetype":"locality"
},
  "geometry": {"coordinates":[46.93381,57.73559],"type":"Point"}
}