{
  "type": "Feature",
  "properties": {
    "gn:admin1_code":"51",
    "gn:asciiname":"Ivashevka",
    "gn:country_code":"RU",
    "gn:dem":147,
    "gn:feature_class":"P",
    "gn:feature_code":"PPL",
    "gn:name":"Ivash\u00ebvka",
    "gn:population":0,
    "gn:timezone":"Europe/Moscow",
    "iso:country":"RU",
    "name:rus_x_preferred":[
        "\u0418\u0432\u0430\u0448\u0451\u0432\u043a\u0430"
    ],
    "name:und_x_variant":[
        "Ivash\u00ebvka",
        "\u0418\u0432\u0430\u0448\u0451\u0432\u043a\u0430"
    ],
    "wof:name":"Ivashevka",
    "wof:placetype":"locality"
},
  "geometry": {"coordinates":[45.10312,54.49929],"type":"Point"}
}