{
  "type": "Feature",
  "properties": {
    "gn:admin1_code":"49",
    "gn:asciiname":"Niva",
    "gn:country_code":"RU",
    "gn:dem":147,
    "gn:feature_class":"P",
    "gn:feature_code":"PPL",
    "gn:name":"Niva",
    "gn:population":0,
    "gn:timezone":"Europe/Moscow",
    "iso:country":"RU",
    "name:ara_x_preferred":[
        "\u0646\u064a\u0641\u0627"
    ],
    "name:bul_x_preferred":[
        "\u041d\u0438\u0432\u0430"
    ],
    "name:ceb_x_preferred":[
        "Niva"
    ],
    "name:ces_x_preferred":[
        "Niva"
    ],
    "name:deu_x_preferred":[
        "Niva"
    ],
    "name:epo_x_preferred":[
        "Niva"
    ],
    "name:est_x_preferred":[
        "Niva"
    ],
    "name:fin_x_preferred":[
        "Niva"
    ],
    "name:fra_x_preferred":[
        "Niva"
    ],
    "name:hye_x_preferred":[
        "\u0546\u056b\u057e\u0561"
    ],
    "name:ita_x_preferred":[
        "Niva"
    ],
    "name:lit_x_preferred":[
        "Niva"
    ],
    "name:nld_x_preferred":[
        "Niva"
    ],
    "name:nor_x_preferred":[
        "Niva"
    ],
    "name:rus_x_preferred":[
        "\u041d\u0438\u0432\u0430"
    ],
    "name:slk_x_preferred":[
        "Niva"
    ],
    "name:spa_x_preferred":[
        "Niva"
    ],
    "name:ukr_x_preferred":[
        "\u041d\u0438\u0432\u0430"
    ],
    "wof:name":"Niva",
    "wof:placetype":"locality"
},
  "geometry": {"coordinates":[32.65,67.43333],"type":"Point"}
}