{
  "type": "Feature",
  "properties": {
    "gn:admin1_code":"33.0",
    "gn:asciiname":"Chupraki",
    "gn:country_code":"RU",
    "gn:dem":125,
    "gn:feature_class":"P",
    "gn:feature_code":"PPL",
    "gn:name":"Chupraki",
    "gn:population":0,
    "gn:timezone":"Europe/Kirov",
    "iso:country":"RU",
    "name:rus_x_preferred":[
        "\u0427\u0443\u043f\u0440\u0430\u043a\u0438"
    ],
    "wof:name":"Chupraki",
    "wof:placetype":"locality"
},
  "geometry": {"coordinates":[49.65361,57.37311999999999],"type":"Point"}
}