{
  "type": "Feature",
  "properties": {
    "gn:admin1_code":"81",
    "gn:asciiname":"Russkaya Bekshanka",
    "gn:country_code":"RU",
    "gn:dem":187,
    "gn:feature_class":"P",
    "gn:feature_code":"PPL",
    "gn:name":"Russkaya Bekshanka",
    "gn:population":0,
    "gn:timezone":"Europe/Ulyanovsk",
    "iso:country":"RU",
    "name:rus_x_preferred":[
        "\u0420\u0443\u0441\u0441\u043a\u0430\u044f \u0411\u0435\u043a\u0448\u0430\u043d\u043a\u0430"
    ],
    "wof:name":"Russkaya Bekshanka",
    "wof:placetype":"locality"
},
  "geometry": {"coordinates":[47.09221,53.39223000000001],"type":"Point"}
}