{
  "type": "Feature",
  "properties": {
    "gn:admin1_code":"8",
    "gn:asciiname":"Yulayevo",
    "gn:country_code":"RU",
    "gn:dem":335,
    "gn:feature_class":"P",
    "gn:feature_code":"PPL",
    "gn:name":"Yulayevo",
    "gn:population":0,
    "gn:timezone":"Asia/Yekaterinburg",
    "iso:country":"RU",
    "name:rus_x_preferred":[
        "\u042e\u043b\u0430\u0435\u0432\u043e"
    ],
    "name:und_x_variant":[
        "Shaganayevo",
        "Shaganayeva",
        "Yulayevo"
    ],
    "wof:name":"Yulayevo",
    "wof:placetype":"locality"
},
  "geometry": {"coordinates":[57.9974,55.128],"type":"Point"}
}