{
  "type": "Feature",
  "properties": {
    "gn:admin1_code":"8",
    "gn:asciiname":"Predtecheno",
    "gn:country_code":"RU",
    "gn:dem":126,
    "gn:feature_class":"P",
    "gn:feature_code":"PPL",
    "gn:name":"Predtecheno",
    "gn:population":0,
    "gn:timezone":"Asia/Yekaterinburg",
    "iso:country":"RU",
    "name:rus_x_preferred":[
        "\u041f\u0440\u0435\u0434\u0442\u0435\u0447\u0435\u043d\u043e"
    ],
    "name:und_x_variant":[
        "\u041f\u0440\u0435\u0434\u0442\u0435\u0447\u0435\u043d\u043e",
        "Predtechino"
    ],
    "wof:name":"Predtecheno",
    "wof:placetype":"locality"
},
  "geometry": {"coordinates":[53.83333,54.95],"type":"Point"}
}