{
  "type": "Feature",
  "properties": {
    "gn:admin1_code":"47.0",
    "gn:asciiname":"Bershovo",
    "gn:country_code":"RU",
    "gn:dem":174,
    "gn:feature_class":"P",
    "gn:feature_code":"PPL",
    "gn:name":"Bershovo",
    "gn:population":0,
    "gn:timezone":"Europe/Moscow",
    "iso:country":"RU",
    "name:nor_x_preferred":[
        "Bersjovo"
    ],
    "name:rus_x_preferred":[
        "\u0411\u0435\u0440\u0448\u043e\u0432\u043e"
    ],
    "wof:name":"Bershovo",
    "wof:placetype":"locality"
},
  "geometry": {"coordinates":[37.68955,55.10511],"type":"Point"}
}