{
  "type": "Feature",
  "properties": {
    "gn:admin1_code":"29",
    "gn:asciiname":"Inchenkovo",
    "gn:country_code":"RU",
    "gn:dem":377,
    "gn:feature_class":"P",
    "gn:feature_code":"PPL",
    "gn:name":"Inchenkovo",
    "gn:population":0,
    "gn:timezone":"Asia/Novokuznetsk",
    "iso:country":"RU",
    "name:rus_x_preferred":[
        "\u0418\u043d\u0447\u0435\u043d\u043a\u043e\u0432\u043e"
    ],
    "name:und_x_variant":[
        "Inchenkova",
        "Inchenkovo"
    ],
    "wof:name":"Inchenkovo",
    "wof:placetype":"locality"
},
  "geometry": {"coordinates":[86.37779999999999,54.0606],"type":"Point"}
}