{
  "type": "Feature",
  "properties": {
    "gn:admin1_code":"10",
    "gn:asciiname":"Kazennoye Uzkoye",
    "gn:country_code":"RU",
    "gn:dem":193,
    "gn:feature_class":"P",
    "gn:feature_code":"PPL",
    "gn:name":"Kaz\u00ebnnoye Uzkoye",
    "gn:population":0,
    "gn:timezone":"Europe/Moscow",
    "iso:country":"RU",
    "name:rus_x_preferred":[
        "\u041a\u0430\u0437\u0451\u043d\u043d\u043e\u0435 \u0423\u0437\u043a\u043e\u0435"
    ],
    "name:und_x_variant":[
        "Kaz\u00ebnnaya Uzskaya",
        "Kaz\u00ebnnoye Uzkoye"
    ],
    "wof:name":"Kazennoye Uzkoye",
    "wof:placetype":"locality"
},
  "geometry": {"coordinates":[33.2337,53.7546],"type":"Point"}
}