{
  "type": "Feature",
  "properties": {
    "gn:admin1_code":"28",
    "gn:asciiname":"Peltoni",
    "gn:cc2":"RU",
    "gn:country_code":"RU",
    "gn:dem":88,
    "gn:feature_class":"P",
    "gn:feature_code":"PPL",
    "gn:name":"Peltoni",
    "gn:population":0,
    "gn:timezone":"Europe/Moscow",
    "iso:country":"RU",
    "name:fin_x_preferred":[
        "Peltonen"
    ],
    "name:rus_x_preferred":[
        "\u041f\u0435\u043b\u0442\u043e\u043d\u0438"
    ],
    "name:und_x_variant":[
        "Peltyn\u2019",
        "Peltoni",
        "\u041f\u0435\u043b\u0442\u043e\u043d\u0438"
    ],
    "wof:name":"Peltoni",
    "wof:placetype":"locality"
},
  "geometry": {"coordinates":[32.75093,65.95220999999999],"type":"Point"}
}