{
  "type": "Feature",
  "properties": {
    "gn:admin1_code":"88",
    "gn:asciiname":"Burchakovo",
    "gn:country_code":"RU",
    "gn:dem":164,
    "gn:feature_class":"P",
    "gn:feature_code":"PPL",
    "gn:name":"Burchakovo",
    "gn:population":0,
    "gn:timezone":"Europe/Moscow",
    "iso:country":"RU",
    "name:rus_x_preferred":[
        "\u0411\u0443\u0440\u0447\u0430\u043a\u043e\u0432\u043e"
    ],
    "wof:name":"Burchakovo",
    "wof:placetype":"locality"
},
  "geometry": {"coordinates":[39.40481,57.00998000000001],"type":"Point"}
}