{
  "type": "Feature",
  "properties": {
    "iso:country":"RU",
    "name:rus_x_preferred":[
        "\u041c\u0435\u0449\u0430\u043d\u0441\u043a\u0438\u0439"
    ],
    "wof:name":"Yakimanka",
    "wof:placetype":"neighbourhood"
},
  "geometry": {"coordinates":[37.60795974686362,55.73110093186913],"type":"Point"}
}