{
  "type": "Feature",
  "properties": {
    "gn:admin1_code":"85",
    "gn:asciiname":"Ishutino",
    "gn:country_code":"RU",
    "gn:dem":90,
    "gn:feature_class":"P",
    "gn:feature_code":"PPL",
    "gn:name":"Ishutino",
    "gn:population":0,
    "gn:timezone":"Europe/Moscow",
    "iso:country":"RU",
    "name:rus_x_preferred":[
        "\u0418\u0448\u0443\u0442\u0438\u043d\u043e"
    ],
    "wof:name":"Ishutino",
    "wof:placetype":"locality"
},
  "geometry": {"coordinates":[46.2111,60.7714],"type":"Point"}
}