{
  "type": "Feature",
  "properties": {
    "gn:admin1_code":"25",
    "gn:asciiname":"Timashevo",
    "gn:country_code":"RU",
    "gn:dem":154,
    "gn:feature_class":"P",
    "gn:feature_code":"PPL",
    "gn:name":"Timash\u00ebvo",
    "gn:population":0,
    "gn:timezone":"Europe/Moscow",
    "iso:country":"RU",
    "name:rus_x_preferred":[
        "\u0422\u0438\u043c\u0430\u0448\u043e\u0432\u043e"
    ],
    "name:und_x_variant":[
        "Timash\u00ebvo"
    ],
    "wof:name":"Timashevo",
    "wof:placetype":"locality"
},
  "geometry": {"coordinates":[36.48222,55.14028],"type":"Point"}
}