{
  "type": "Feature",
  "properties": {
    "gn:admin1_code":"83.0",
    "gn:asciiname":"Rot'kovo",
    "gn:country_code":"RU",
    "gn:dem":91,
    "gn:feature_class":"P",
    "gn:feature_code":"PPL",
    "gn:name":"Rot\u2019kovo",
    "gn:population":0,
    "gn:timezone":"Europe/Moscow",
    "iso:country":"RU",
    "name:nor_x_preferred":[
        "Rotkovo"
    ],
    "name:rus_x_preferred":[
        "\u0420\u043e\u0442\u044c\u043a\u043e\u0432\u043e"
    ],
    "name:und_x_variant":[
        "Rot\u2019kovo"
    ],
    "wof:name":"Rot'kovo",
    "wof:placetype":"locality"
},
  "geometry": {"coordinates":[42.32789,56.00283],"type":"Point"}
}