{
  "type": "Feature",
  "properties": {
    "gn:admin1_code":"44",
    "gn:asciiname":"Nizhniy Seymchan",
    "gn:cc2":"RU",
    "gn:country_code":"RU",
    "gn:dem":198,
    "gn:feature_class":"P",
    "gn:feature_code":"PPL",
    "gn:name":"Nizhniy Seymchan",
    "gn:population":0,
    "gn:timezone":"Asia/Magadan",
    "iso:country":"RU",
    "name:rus_x_preferred":[
        "\u041d\u0438\u0436\u043d\u0438\u0439 \u0421\u0435\u0439\u043c\u0447\u0430\u043d"
    ],
    "name:und_x_variant":[
        "Iskra",
        "Nizhniy Seymchan"
    ],
    "wof:name":"Nizhniy Seymchan",
    "wof:placetype":"locality"
},
  "geometry": {"coordinates":[152.41666999999995,62.91667],"type":"Point"}
}