{
  "type": "Feature",
  "properties": {
    "gn:admin1_code":"85.0",
    "gn:asciiname":"Aganino",
    "gn:country_code":"RU",
    "gn:dem":201,
    "gn:feature_class":"P",
    "gn:feature_code":"PPL",
    "gn:name":"Aganino",
    "gn:population":0,
    "gn:timezone":"Europe/Moscow",
    "iso:country":"RU",
    "name:nor_x_preferred":[
        "Aganino"
    ],
    "name:rus_x_preferred":[
        "\u0410\u0433\u0430\u043d\u0438\u043d\u043e"
    ],
    "wof:name":"Aganino",
    "wof:placetype":"locality"
},
  "geometry": {"coordinates":[35.53911,60.06778000000001],"type":"Point"}
}