{
  "type": "Feature",
  "properties": {
    "gn:admin1_code":"33",
    "gn:asciiname":"Sukhorech'ye",
    "gn:country_code":"RU",
    "gn:dem":92,
    "gn:feature_class":"P",
    "gn:feature_code":"PPL",
    "gn:name":"Sukhorech\u2019ye",
    "gn:population":0,
    "gn:timezone":"Europe/Moscow",
    "iso:country":"RU",
    "name:eng_x_preferred":[
        "Sukhorech'ye"
    ],
    "name:nor_x_preferred":[
        "Sukhoretsje"
    ],
    "name:rus_x_preferred":[
        "\u0421\u0443\u0445\u043e\u0440\u0435\u0447\u044c\u0435"
    ],
    "name:und_x_variant":[
        "\u0421\u0443\u0445\u043e\u0440\u0435\u0447\u044c\u0435",
        "Sukhorech\u2019ye"
    ],
    "wof:name":"Sukhorech'ye",
    "wof:placetype":"locality"
},
  "geometry": {"coordinates":[47.17646,56.83919],"type":"Point"}
}