{
  "type": "Feature",
  "properties": {
    "gn:admin1_code":"56",
    "gn:asciiname":"Khanyki",
    "gn:country_code":"RU",
    "gn:dem":182,
    "gn:feature_class":"P",
    "gn:feature_code":"PPL",
    "gn:name":"Khanyki",
    "gn:population":0,
    "gn:timezone":"Europe/Moscow",
    "iso:country":"RU",
    "name:rus_x_preferred":[
        "\u0425\u0430\u043d\u044b\u043a\u0438"
    ],
    "name:und_x_variant":[
        "Khanyk",
        "Khanyki",
        "\u0425\u0430\u043d\u044b\u043a\u0438"
    ],
    "wof:name":"Khanyki",
    "wof:placetype":"locality"
},
  "geometry": {"coordinates":[37.27215,52.01412],"type":"Point"}
}