{
  "type": "Feature",
  "properties": {
    "gn:admin1_code":"81.0",
    "gn:asciiname":"Chasovnya Verkhnyaya",
    "gn:country_code":"RU",
    "gn:dem":111,
    "gn:feature_class":"P",
    "gn:feature_code":"PPL",
    "gn:name":"Chasovnya Verkhnyaya",
    "gn:population":0,
    "gn:timezone":"Europe/Ulyanovsk",
    "iso:country":"RU",
    "name:rus_x_preferred":[
        "\u0427\u0430\u0441\u043e\u0432\u043d\u044f \u0412\u0435\u0440\u0445\u043d\u044f\u044f"
    ],
    "name:und_x_variant":[
        "\u0427\u0430\u0441\u043e\u0432\u043d\u044f \u0412\u0435\u0440\u0445\u043d\u044f\u044f"
    ],
    "wof:name":"Chasovnya Verkhnyaya",
    "wof:placetype":"locality"
},
  "geometry": {"coordinates":[48.55,54.35],"type":"Point"}
}