{
  "type": "Feature",
  "properties": {
    "gn:admin1_code":"54",
    "gn:asciiname":"Kolos",
    "gn:country_code":"RU",
    "gn:dem":84,
    "gn:feature_class":"P",
    "gn:feature_code":"PPL",
    "gn:name":"Kolos",
    "gn:population":0,
    "gn:timezone":"Asia/Omsk",
    "iso:country":"RU",
    "name:bel_x_preferred":[
        "\u041a\u043e\u043b\u0430\u0441"
    ],
    "name:ceb_x_preferred":[
        "Kolos"
    ],
    "name:deu_x_preferred":[
        "Kolos"
    ],
    "name:pol_x_preferred":[
        "Kolos"
    ],
    "name:rus_x_preferred":[
        "\u041a\u043e\u043b\u043e\u0441"
    ],
    "name:swe_x_preferred":[
        "Kolos"
    ],
    "name:ukr_x_preferred":[
        "\u041a\u043e\u043b\u043e\u0441"
    ],
    "name:und_x_variant":[
        "\u041a\u043e\u043b\u043e\u0441"
    ],
    "wof:name":"Kolos",
    "wof:placetype":"locality"
},
  "geometry": {"coordinates":[73.08333,55.51667],"type":"Point"}
}