{
  "type": "Feature",
  "properties": {
    "gn:admin1_code":"77",
    "gn:asciiname":"Ozery",
    "gn:country_code":"RU",
    "gn:dem":172,
    "gn:feature_class":"P",
    "gn:feature_code":"PPL",
    "gn:name":"Oz\u00ebry",
    "gn:population":0,
    "gn:timezone":"Europe/Moscow",
    "iso:country":"RU",
    "name:rus_x_preferred":[
        "\u041e\u0437\u0451\u0440\u044b"
    ],
    "name:und_x_variant":[
        "Oz\u00ebry"
    ],
    "wof:name":"Ozery",
    "wof:placetype":"locality"
},
  "geometry": {"coordinates":[32.2951,55.99139],"type":"Point"}
}