{
  "type": "Feature",
  "properties": {
    "gn:admin1_code":"52",
    "gn:asciiname":"Molochkovo",
    "gn:country_code":"RU",
    "gn:dem":40,
    "gn:feature_class":"P",
    "gn:feature_code":"PPL",
    "gn:name":"Molochkovo",
    "gn:population":0,
    "gn:timezone":"Europe/Moscow",
    "iso:country":"RU",
    "name:rus_x_preferred":[
        "\u041c\u043e\u043b\u043e\u0447\u043a\u043e\u0432\u043e"
    ],
    "name:und_x_variant":[
        "\u041c\u043e\u043b\u043e\u0447\u043a\u043e\u0432\u043e"
    ],
    "wof:name":"Molochkovo",
    "wof:placetype":"locality"
},
  "geometry": {"coordinates":[30.20272000000001,58.10067],"type":"Point"}
}