{
  "type": "Feature",
  "properties": {
    "gn:admin1_code":"85",
    "gn:asciiname":"Limenskiy",
    "gn:country_code":"RU",
    "gn:dem":111,
    "gn:feature_class":"P",
    "gn:feature_code":"PPL",
    "gn:name":"Limenskiy",
    "gn:population":0,
    "gn:timezone":"Europe/Moscow",
    "iso:country":"RU",
    "name:rus_x_preferred":[
        "\u041b\u0438\u043c\u0435\u043d\u0441\u043a\u0438\u0439"
    ],
    "name:und_x_variant":[
        "\u041b\u0438\u043c\u0435\u043d\u0441\u043a\u0438\u0439"
    ],
    "wof:name":"Limenskiy",
    "wof:placetype":"locality"
},
  "geometry": {"coordinates":[40.05342,59.24406],"type":"Point"}
}