{
  "type": "Feature",
  "properties": {
    "gn:admin1_code":"64",
    "gn:asciiname":"Kazakevichi",
    "gn:cc2":"RU",
    "gn:country_code":"RU",
    "gn:dem":94,
    "gn:feature_class":"P",
    "gn:feature_code":"PPL",
    "gn:name":"Kazakevichi",
    "gn:population":0,
    "gn:timezone":"Asia/Sakhalin",
    "iso:country":"RU",
    "name:rus_x_preferred":[
        "\u041a\u0430\u0437\u0430\u043a\u0435\u0432\u0438\u0447\u0438"
    ],
    "name:und_x_variant":[
        "Tokonbo",
        "Kazakakevich",
        "Tokombo",
        "Kazakevichi"
    ],
    "wof:name":"Kazakevichi",
    "wof:placetype":"locality"
},
  "geometry": {"coordinates":[141.86667,46.65],"type":"Point"}
}