{
  "type": "Feature",
  "properties": {
    "gn:admin1_code":"63",
    "gn:asciiname":"Kabachkova",
    "gn:cc2":"RU",
    "gn:country_code":"RU",
    "gn:dem":2,
    "gn:feature_class":"P",
    "gn:feature_code":"PPL",
    "gn:name":"Kabachkova",
    "gn:population":0,
    "gn:timezone":"Asia/Magadan",
    "iso:country":"RU",
    "name:rus_x_preferred":[
        "\u041a\u0430\u0431\u0430\u0447\u043a\u043e\u0432\u0430"
    ],
    "name:und_x_variant":[
        "Kabachkovo",
        "Kabachkova",
        "\u041a\u0430\u0431\u0430\u0447\u043a\u043e\u0432\u0430"
    ],
    "wof:name":"Kabachkova",
    "wof:placetype":"locality"
},
  "geometry": {"coordinates":[161.48333,69.31667],"type":"Point"}
}