{
  "type": "Feature",
  "properties": {
    "gn:admin1_code":"34",
    "gn:asciiname":"Sed-Nyrd",
    "gn:country_code":"RU",
    "gn:dem":71,
    "gn:feature_class":"P",
    "gn:feature_code":"PPL",
    "gn:name":"S\u00ebd-Nyrd",
    "gn:population":0,
    "gn:timezone":"Europe/Moscow",
    "iso:country":"RU",
    "name:rus_x_preferred":[
        "\u0421\u0451\u0434-\u041d\u044b\u0440\u0434"
    ],
    "name:und_x_variant":[
        "S\u00ebd-Nyrd",
        "\u0421\u0451\u0434-\u041d\u044b\u0440\u0434"
    ],
    "wof:name":"Sed-Nyrd",
    "wof:placetype":"locality"
},
  "geometry": {"coordinates":[59.60824,66.89673000000001],"type":"Point"}
}