{
  "type": "Feature",
  "properties": {
    "gn:admin1_code":"84",
    "gn:asciiname":"Karpunin",
    "gn:country_code":"RU",
    "gn:dem":37,
    "gn:feature_class":"P",
    "gn:feature_code":"PPL",
    "gn:name":"Karpunin",
    "gn:population":0,
    "gn:timezone":"Europe/Volgograd",
    "iso:country":"RU",
    "name:rus_x_preferred":[
        "\u041a\u0430\u0440\u043f\u0443\u043d\u0438\u043d"
    ],
    "name:und_x_variant":[
        "\u041a\u0430\u0440\u043f\u0443\u043d\u0438\u043d"
    ],
    "wof:name":"Karpunin",
    "wof:placetype":"locality"
},
  "geometry": {"coordinates":[45.32062,50.10724],"type":"Point"}
}