{
  "type": "Feature",
  "properties": {
    "iso:country":"RU",
    "qs:name":"Zaluchnoe",
    "qs:name_adm0":"Russia",
    "qs:name_adm1":"Moscow Oblast",
    "qs:photos":19,
    "qs:photos_1k":4,
    "qs:photos_9k":1,
    "qs:photos_9r":1,
    "qs:photos_all":19,
    "qs:photos_sr":1,
    "qs:placetype":"Town",
    "qs:pop_sr":"0",
    "wof:name":"Zaluchnoe",
    "wof:placetype":"locality"
},
  "geometry": {"coordinates":[36.201537,55.213356],"type":"Point"}
}