{
  "type": "Feature",
  "properties": {
    "gn:admin1_code":"69",
    "gn:asciiname":"Shirkovo",
    "gn:country_code":"RU",
    "gn:dem":223,
    "gn:feature_class":"P",
    "gn:feature_code":"PPL",
    "gn:name":"Shirkovo",
    "gn:population":0,
    "gn:timezone":"Europe/Moscow",
    "iso:country":"RU",
    "name:rus_x_preferred":[
        "\u0428\u0438\u0440\u043a\u043e\u0432\u043e"
    ],
    "wof:name":"Shirkovo",
    "wof:placetype":"locality"
},
  "geometry": {"coordinates":[31.6228,54.5306],"type":"Point"}
}