{
  "type": "Feature",
  "properties": {
    "gn:admin1_code":"20",
    "gn:asciiname":"Pesterevskiy",
    "gn:country_code":"RU",
    "gn:dem":606,
    "gn:feature_class":"P",
    "gn:feature_code":"PPL",
    "gn:name":"Pesterevskiy",
    "gn:population":0,
    "gn:timezone":"Asia/Irkutsk",
    "iso:country":"RU",
    "name:eng_x_preferred":[
        "Pesterevskiy"
    ],
    "name:nor_x_preferred":[
        "Pesterevskij"
    ],
    "name:rus_x_preferred":[
        "\u041f\u0435\u0441\u0442\u0435\u0440\u0435\u0432\u0441\u043a\u0438\u0439"
    ],
    "wof:name":"Pesterevskiy",
    "wof:placetype":"locality"
},
  "geometry": {"coordinates":[113.40000000000001,57.96666999999999],"type":"Point"}
}