{
  "type": "Feature",
  "properties": {
    "gn:admin1_code":"91",
    "gn:asciiname":"Batov",
    "gn:country_code":"RU",
    "gn:dem":274,
    "gn:feature_class":"P",
    "gn:feature_code":"PPL",
    "gn:name":"Batov",
    "gn:population":0,
    "gn:timezone":"Asia/Krasnoyarsk",
    "iso:country":"RU",
    "name:eng_x_preferred":[
        "Batov"
    ],
    "name:nor_x_preferred":[
        "Batov"
    ],
    "name:rus_x_preferred":[
        "\u0411\u0430\u0442\u043e\u0432"
    ],
    "name:slv_x_preferred":[
        "Batov"
    ],
    "name:und_x_variant":[
        "Botovskoye",
        "Batovka"
    ],
    "wof:name":"Batov",
    "wof:placetype":"locality"
},
  "geometry": {"coordinates":[94.59056,56.83556],"type":"Point"}
}