{
  "type": "Feature",
  "properties": {
    "gn:admin1_code":"38",
    "gn:asciiname":"Obolonskiy",
    "gn:cc2":"RU",
    "gn:country_code":"RU",
    "gn:dem":2,
    "gn:feature_class":"P",
    "gn:feature_code":"PPL",
    "gn:name":"Obolonskiy",
    "gn:population":0,
    "gn:timezone":"Europe/Moscow",
    "iso:country":"RU",
    "name:rus_x_preferred":[
        "\u041e\u0431\u043e\u043b\u043e\u043d\u0441\u043a\u0438\u0439"
    ],
    "name:und_x_variant":[
        "Kazachiy",
        "Obolorskiy",
        "Obolonskiy"
    ],
    "wof:name":"Obolonskiy",
    "wof:placetype":"locality"
},
  "geometry": {"coordinates":[38.16583,45.05],"type":"Point"}
}