{
  "type": "Feature",
  "properties": {
    "gn:admin1_code":"86",
    "gn:asciiname":"Rudkino",
    "gn:country_code":"RU",
    "gn:dem":102,
    "gn:feature_class":"P",
    "gn:feature_code":"PPL",
    "gn:name":"Rudkino",
    "gn:population":0,
    "gn:timezone":"Europe/Moscow",
    "iso:country":"RU",
    "name:eng_x_preferred":[
        "Rudkino"
    ],
    "name:nor_x_preferred":[
        "Rudkino"
    ],
    "name:rus_x_preferred":[
        "\u0420\u0443\u0434\u043a\u0438\u043d\u043e"
    ],
    "wof:name":"Rudkino",
    "wof:placetype":"locality"
},
  "geometry": {"coordinates":[39.0426,51.42627],"type":"Point"}
}