{
  "type": "Feature",
  "properties": {
    "gn:admin1_code":"76",
    "gn:asciiname":"Kineyevo",
    "gn:country_code":"RU",
    "gn:dem":222,
    "gn:feature_class":"P",
    "gn:feature_code":"PPL",
    "gn:name":"Kineyevo",
    "gn:population":0,
    "gn:timezone":"Europe/Moscow",
    "iso:country":"RU",
    "name:rus_x_preferred":[
        "\u041a\u0438\u043d\u0435\u0435\u0432\u043e"
    ],
    "wof:name":"Kineyevo",
    "wof:placetype":"locality"
},
  "geometry": {"coordinates":[37.64943,54.61838],"type":"Point"}
}