{
  "type": "Feature",
  "properties": {
    "gn:admin1_code":"69",
    "gn:asciiname":"Zhichitsy",
    "gn:country_code":"RU",
    "gn:dem":202,
    "gn:feature_class":"P",
    "gn:feature_code":"PPL",
    "gn:name":"Zhichitsy",
    "gn:population":0,
    "gn:timezone":"Europe/Moscow",
    "iso:country":"RU",
    "name:eng_x_preferred":[
        "Zhichitsy"
    ],
    "name:nor_x_preferred":[
        "Zjitsjitsy"
    ],
    "name:rus_x_preferred":[
        "\u0416\u0438\u0447\u0438\u0446\u044b"
    ],
    "wof:name":"Zhichitsy",
    "wof:placetype":"locality"
},
  "geometry": {"coordinates":[31.28942,55.10773],"type":"Point"}
}