{
  "type": "Feature",
  "properties": {
    "gn:admin1_code":"8",
    "gn:asciiname":"Kazyrovo",
    "gn:country_code":"RU",
    "gn:dem":173,
    "gn:feature_class":"P",
    "gn:feature_code":"PPL",
    "gn:name":"Kazyrovo",
    "gn:population":0,
    "gn:timezone":"Asia/Yekaterinburg",
    "iso:country":"RU",
    "name:rus_x_preferred":[
        "\u041a\u0430\u0437\u044b\u0440\u043e\u0432\u043e"
    ],
    "name:und_x_variant":[
        "\u041a\u0430\u0437\u044b\u0440\u043e\u0432\u043e"
    ],
    "wof:name":"Kazyrovo",
    "wof:placetype":"locality"
},
  "geometry": {"coordinates":[55.68333000000001,54.78333000000001],"type":"Point"}
}