{
  "type": "Feature",
  "properties": {
    "gn:admin1_code":"9.0",
    "gn:asciiname":"Plamya Novoy Zhizni",
    "gn:country_code":"RU",
    "gn:dem":219,
    "gn:feature_class":"P",
    "gn:feature_code":"PPL",
    "gn:name":"Plamya Novoy Zhizni",
    "gn:population":0,
    "gn:timezone":"Europe/Moscow",
    "iso:country":"RU",
    "name:rus_x_preferred":[
        "\u041f\u043b\u0430\u043c\u044f \u041d\u043e\u0432\u043e\u0439 \u0416\u0438\u0437\u043d\u0438"
    ],
    "wof:name":"Plamya Novoy Zhizni",
    "wof:placetype":"locality"
},
  "geometry": {"coordinates":[38.0385,50.9233],"type":"Point"}
}