{
  "type": "Feature",
  "properties": {
    "gn:admin1_code":"88",
    "gn:asciiname":"Ostashevo",
    "gn:country_code":"RU",
    "gn:dem":152,
    "gn:feature_class":"P",
    "gn:feature_code":"PPL",
    "gn:name":"Ostash\u00ebvo",
    "gn:population":0,
    "gn:timezone":"Europe/Moscow",
    "iso:country":"RU",
    "name:rus_x_preferred":[
        "\u041e\u0441\u0442\u0430\u0448\u0451\u0432\u043e"
    ],
    "name:und_x_variant":[
        "Ostash\u00ebvo"
    ],
    "wof:name":"Ostashevo",
    "wof:placetype":"locality"
},
  "geometry": {"coordinates":[39.3261,57.8189],"type":"Point"}
}