{
  "type": "Feature",
  "properties": {
    "gn:admin1_code":"17",
    "gn:admin2_code":"549104",
    "gn:asciiname":"Tanusi",
    "gn:country_code":"RU",
    "gn:dem":1939,
    "gn:feature_class":"P",
    "gn:feature_code":"PPL",
    "gn:name":"Tanusi",
    "gn:population":0,
    "gn:timezone":"Europe/Moscow",
    "iso:country":"RU",
    "name:rus_x_preferred":[
        "\u0422\u0430\u043d\u0443\u0441\u0438"
    ],
    "wof:name":"Tanusi",
    "wof:placetype":"locality"
},
  "geometry": {"coordinates":[46.69233,42.58233],"type":"Point"}
}