{
  "type": "Feature",
  "properties": {
    "gn:admin1_code":"73",
    "gn:asciiname":"Staroye Mazino",
    "gn:country_code":"RU",
    "gn:dem":96,
    "gn:feature_class":"P",
    "gn:feature_code":"PPL",
    "gn:name":"Staroye Mazino",
    "gn:population":0,
    "gn:timezone":"Europe/Moscow",
    "iso:country":"RU",
    "name:eng_x_preferred":[
        "Staroye Mazino"
    ],
    "name:nor_x_preferred":[
        "Staroje Mazino"
    ],
    "name:rus_x_preferred":[
        "\u0421\u0442\u0430\u0440\u043e\u0435 \u041c\u0430\u0437\u0438\u043d\u043e"
    ],
    "name:und_x_variant":[
        "\u0421\u0442\u0430\u0440\u043e\u0435 \u041c\u0430\u0437\u0438\u043d\u043e",
        "Staroye Mazino"
    ],
    "wof:name":"Staroye Mazino",
    "wof:placetype":"locality"
},
  "geometry": {"coordinates":[53.05637,55.64908000000001],"type":"Point"}
}