{
  "type": "Feature",
  "properties": {
    "gn:admin1_code":"65",
    "gn:asciiname":"Zaitkino",
    "gn:country_code":"RU",
    "gn:dem":146,
    "gn:feature_class":"P",
    "gn:feature_code":"PPL",
    "gn:name":"Zaitkino",
    "gn:population":0,
    "gn:timezone":"Europe/Samara",
    "iso:country":"RU",
    "name:rus_x_preferred":[
        "\u0417\u0430\u0438\u0442\u043a\u0438\u043d\u043e"
    ],
    "wof:name":"Zaitkino",
    "wof:placetype":"locality"
},
  "geometry": {"coordinates":[51.0904,54.427],"type":"Point"}
}