{
  "type": "Feature",
  "properties": {
    "gn:admin1_code":"69",
    "gn:asciiname":"Lusavino",
    "gn:country_code":"RU",
    "gn:dem":223,
    "gn:feature_class":"P",
    "gn:feature_code":"PPL",
    "gn:name":"Lusavino",
    "gn:population":0,
    "gn:timezone":"Europe/Moscow",
    "iso:country":"RU",
    "name:rus_x_preferred":[
        "\u041b\u0443\u0441\u0430\u0432\u0438\u043d\u043e"
    ],
    "name:und_x_variant":[
        "Lustino",
        "Lusavino",
        "\u041b\u0443\u0441\u0430\u0432\u0438\u043d\u043e"
    ],
    "wof:name":"Lusavino",
    "wof:placetype":"locality"
},
  "geometry": {"coordinates":[33.33339,55.08003000000001],"type":"Point"}
}