{
  "type": "Feature",
  "properties": {
    "gn:admin1_code":"69",
    "gn:asciiname":"Magalinshchina",
    "gn:country_code":"RU",
    "gn:dem":217,
    "gn:feature_class":"P",
    "gn:feature_code":"PPL",
    "gn:name":"Magalinshchina",
    "gn:population":0,
    "gn:timezone":"Europe/Moscow",
    "iso:country":"RU",
    "name:rus_x_preferred":[
        "\u041c\u0430\u0433\u0430\u043b\u0438\u043d\u0449\u0438\u043d\u0430"
    ],
    "name:und_x_variant":[
        "Mogalinshchina",
        "Magalinshchina"
    ],
    "wof:name":"Magalinshchina",
    "wof:placetype":"locality"
},
  "geometry": {"coordinates":[32.09861,54.8267],"type":"Point"}
}