{
  "type": "Feature",
  "properties": {
    "gn:admin1_code":"20",
    "gn:asciiname":"Bozhekhan",
    "gn:country_code":"RU",
    "gn:dem":671,
    "gn:feature_class":"P",
    "gn:feature_code":"PPL",
    "gn:name":"Bozhekhan",
    "gn:population":0,
    "gn:timezone":"Asia/Irkutsk",
    "iso:country":"RU",
    "name:rus_x_preferred":[
        "\u0411\u043e\u0436\u0435\u0445\u0430\u043d"
    ],
    "name:und_x_variant":[
        "\u0411\u043e\u0436\u0435\u0445\u0430\u043d"
    ],
    "wof:name":"Bozhekhan",
    "wof:placetype":"locality"
},
  "geometry": {"coordinates":[104.86667,53.06667],"type":"Point"}
}