{
  "type": "Feature",
  "properties": {
    "gn:admin1_code":"38.0",
    "gn:asciiname":"Bichevoy",
    "gn:country_code":"RU",
    "gn:dem":38,
    "gn:feature_class":"P",
    "gn:feature_code":"PPL",
    "gn:name":"Bichevoy",
    "gn:population":0,
    "gn:timezone":"Europe/Moscow",
    "iso:country":"RU",
    "name:rus_x_preferred":[
        "\u0411\u0438\u0447e\u0432o\u0439"
    ],
    "name:und_x_variant":[
        "\u0411\u0438\u0447e\u0432o\u0439",
        "Bich\u00ebvyy"
    ],
    "wof:name":"Bichevoy",
    "wof:placetype":"locality"
},
  "geometry": {"coordinates":[39.59579,46.24294],"type":"Point"}
}