{
  "type": "Feature",
  "properties": {
    "gn:admin1_code":"85",
    "gn:asciiname":"Povarovo",
    "gn:country_code":"RU",
    "gn:dem":139,
    "gn:feature_class":"P",
    "gn:feature_code":"PPL",
    "gn:name":"Povarovo",
    "gn:population":0,
    "gn:timezone":"Europe/Moscow",
    "iso:country":"RU",
    "name:rus_x_preferred":[
        "\u041f\u043e\u0432\u0430\u0440\u043e\u0432\u043e"
    ],
    "name:sco_x_preferred":[
        "Povarovo"
    ],
    "wof:name":"Povarovo",
    "wof:placetype":"locality"
},
  "geometry": {"coordinates":[38.73508,58.92921],"type":"Point"}
}