{
  "type": "Feature",
  "properties": {
    "gn:country":"RU",
    "gn:fcode":"PPL",
    "gn:population":1142,
    "iso:country":"RU",
    "name:che_x_preferred":[
        "\u0423\u0434\u0430\u0440\u043d\u0438"
    ],
    "name:eng_x_preferred":[
        "Udarnyy"
    ],
    "name:eng_x_variant":[
        "Udarny"
    ],
    "name:hye_x_preferred":[
        "\u0548\u0582\u0564\u0561\u057c\u0576\u056b"
    ],
    "name:nor_x_preferred":[
        "Udarnyj"
    ],
    "name:pol_x_preferred":[
        "Udarnyj"
    ],
    "name:rus_x_preferred":[
        "\u0423\u0434\u0430\u0440\u043d\u044b\u0439"
    ],
    "qs:name":"Udarnyy",
    "qs:photos_9r":0,
    "qs:photos_sr":0,
    "qs:pop_sr":"3",
    "wof:name":"Udarnyy",
    "wof:placetype":"locality",
    "wof:population":1142
},
  "geometry": {"coordinates":[42.50528,44.34917],"type":"Point"}
}