{
  "type": "Feature",
  "properties": {
    "gn:admin1_code":"16",
    "gn:asciiname":"Novoye Kotyakovo",
    "gn:country_code":"RU",
    "gn:dem":137,
    "gn:feature_class":"P",
    "gn:feature_code":"PPL",
    "gn:name":"Novoye Kotyakovo",
    "gn:population":0,
    "gn:timezone":"Europe/Moscow",
    "iso:country":"RU",
    "name:rus_x_preferred":[
        "\u041d\u043e\u0432\u043e\u0435 \u041a\u043e\u0442\u044f\u043a\u043e\u0432\u043e"
    ],
    "name:und_x_variant":[
        "\u041d\u043e\u0432\u043e\u0435 \u041a\u043e\u0442\u044f\u043a\u043e\u0432\u043e"
    ],
    "wof:name":"Novoye Kotyakovo",
    "wof:placetype":"locality"
},
  "geometry": {"coordinates":[47.5779,55.10097],"type":"Point"}
}