{
  "type": "Feature",
  "properties": {
    "gn:admin1_code":"33",
    "gn:asciiname":"Zemtsy",
    "gn:country_code":"RU",
    "gn:dem":124,
    "gn:feature_class":"P",
    "gn:feature_code":"PPL",
    "gn:name":"Zemtsy",
    "gn:population":0,
    "gn:timezone":"Europe/Kirov",
    "iso:country":"RU",
    "name:rus_x_preferred":[
        "\u0417\u0435\u043c\u0446\u044b"
    ],
    "name:und_x_variant":[
        "Zemts\u2019",
        "Zemtsy"
    ],
    "wof:name":"Zemtsy",
    "wof:placetype":"locality"
},
  "geometry": {"coordinates":[48.352,58.1433],"type":"Point"}
}