{
  "type": "Feature",
  "properties": {
    "gn:admin1_code":"10",
    "gn:asciiname":"Radinsk",
    "gn:country_code":"RU",
    "gn:dem":142,
    "gn:feature_class":"P",
    "gn:feature_code":"PPL",
    "gn:name":"Radinsk",
    "gn:population":0,
    "gn:timezone":"Europe/Moscow",
    "iso:country":"RU",
    "name:rus_x_preferred":[
        "\u0420\u0430\u0434\u0438\u043d\u0441\u043a"
    ],
    "name:und_x_variant":[
        "Yatskovka",
        "Radinsk",
        "\u0420\u0430\u0434\u0438\u043d\u0441\u043a",
        "Radiisk"
    ],
    "wof:name":"Radinsk",
    "wof:placetype":"locality"
},
  "geometry": {"coordinates":[33.84711,52.63601],"type":"Point"}
}