{
  "type": "Feature",
  "properties": {
    "gn:admin1_code":"71.0",
    "gn:asciiname":"Bol'shaya Imennaya",
    "gn:country_code":"RU",
    "gn:dem":185,
    "gn:feature_class":"P",
    "gn:feature_code":"PPL",
    "gn:name":"Bol\u2019shaya Imennaya",
    "gn:population":0,
    "gn:timezone":"Asia/Yekaterinburg",
    "iso:country":"RU",
    "name:rus_x_preferred":[
        "\u0411\u043e\u043b\u044c\u0448\u0430\u044f \u0418\u043c\u0435\u043d\u043d\u0430\u044f"
    ],
    "name:und_x_variant":[
        "Bol\u2019she-Imennaya",
        "Bol\u2019shaya Imennaya"
    ],
    "wof:name":"Bol'shaya Imennaya",
    "wof:placetype":"locality"
},
  "geometry": {"coordinates":[59.8775,58.56028000000001],"type":"Point"}
}