{
  "type": "Feature",
  "properties": {
    "gn:admin1_code":"77",
    "gn:asciiname":"Filino",
    "gn:country_code":"RU",
    "gn:dem":166,
    "gn:feature_class":"P",
    "gn:feature_code":"PPL",
    "gn:name":"Filino",
    "gn:population":0,
    "gn:timezone":"Europe/Moscow",
    "iso:country":"RU",
    "name:nor_x_preferred":[
        "Filino"
    ],
    "name:rus_x_preferred":[
        "\u0424\u0438\u043b\u0438\u043d\u043e"
    ],
    "wof:name":"Filino",
    "wof:placetype":"locality"
},
  "geometry": {"coordinates":[35.1064,56.5846],"type":"Point"}
}