{
  "type": "Feature",
  "properties": {
    "gn:admin1_code":"77",
    "gn:asciiname":"Kiselkino",
    "gn:country_code":"RU",
    "gn:dem":147,
    "gn:feature_class":"P",
    "gn:feature_code":"PPL",
    "gn:name":"Kiselkino",
    "gn:population":0,
    "gn:timezone":"Europe/Moscow",
    "iso:country":"RU",
    "name:rus_x_preferred":[
        "\u041a\u0438\u0441\u0435\u043b\u043a\u0438\u043d\u043e"
    ],
    "name:und_x_variant":[
        "\u041a\u0438\u0441\u0435\u043b\u043a\u0438\u043d\u043e"
    ],
    "wof:name":"Kiselkino",
    "wof:placetype":"locality"
},
  "geometry": {"coordinates":[36.63077,57.71725],"type":"Point"}
}