{
  "type": "Feature",
  "properties": {
    "gn:admin1_code":"83",
    "gn:asciiname":"Khvoynyy",
    "gn:country_code":"RU",
    "gn:dem":209,
    "gn:feature_class":"P",
    "gn:feature_code":"PPL",
    "gn:name":"Khvoynyy",
    "gn:population":0,
    "gn:timezone":"Europe/Moscow",
    "iso:country":"RU",
    "name:rus_x_preferred":[
        "\u0425\u0432\u043e\u0439\u043d\u044b\u0439"
    ],
    "wof:name":"Khvoynyy",
    "wof:placetype":"locality"
},
  "geometry": {"coordinates":[39.51448,56.53398000000001],"type":"Point"}
}