{
  "type": "Feature",
  "properties": {
    "gn:admin1_code":"77",
    "gn:asciiname":"Shuvalov",
    "gn:country_code":"RU",
    "gn:dem":219,
    "gn:feature_class":"P",
    "gn:feature_code":"PPL",
    "gn:name":"Shuvalov",
    "gn:population":0,
    "gn:timezone":"Europe/Moscow",
    "iso:country":"RU",
    "name:rus_x_preferred":[
        "\u0428\u0443\u0432\u0430\u043b\u043e\u0432"
    ],
    "name:und_x_variant":[
        "\u0428\u0443\u0432\u0430\u043b\u043e\u0432"
    ],
    "wof:name":"Shuvalov",
    "wof:placetype":"locality"
},
  "geometry": {"coordinates":[34.44036,56.94284],"type":"Point"}
}