{
  "type": "Feature",
  "properties": {
    "gn:admin1_code":"42",
    "gn:admin2_code":"575409",
    "gn:asciiname":"Pavlovskiye Kontsy",
    "gn:country_code":"RU",
    "gn:dem":101,
    "gn:feature_class":"P",
    "gn:feature_code":"PPL",
    "gn:name":"Pavlovskiye Kontsy",
    "gn:population":0,
    "gn:timezone":"Europe/Moscow",
    "iso:country":"RU",
    "name:rus_x_preferred":[
        "\u041f\u0430\u0432\u043b\u043e\u0432\u0441\u043a\u0438\u0435 \u041a\u043e\u043d\u0446\u044b"
    ],
    "name:und_x_variant":[
        "Pavlovskiy Konets",
        "Pavlovskiye Kontsy",
        "\u041f\u0430\u0432\u043b\u043e\u0432\u0441\u043a\u0438\u0435 \u041a\u043e\u043d\u0446\u044b"
    ],
    "wof:name":"Pavlovskiye Kontsy",
    "wof:placetype":"locality"
},
  "geometry": {"coordinates":[33.93958,59.61044],"type":"Point"}
}