{
  "type": "Feature",
  "properties": {
    "gn:admin1_code":"12.0",
    "gn:asciiname":"Chokhoy",
    "gn:country_code":"RU",
    "gn:dem":1696,
    "gn:feature_class":"P",
    "gn:feature_code":"PPL",
    "gn:name":"Chokhoy",
    "gn:population":0,
    "gn:timezone":"Europe/Moscow",
    "iso:country":"RU",
    "name:rus_x_preferred":[
        "\u0427\u043e\u0445\u043e\u0439"
    ],
    "wof:name":"Chokhoy",
    "wof:placetype":"locality"
},
  "geometry": {"coordinates":[45.52333,42.77806],"type":"Point"}
}