{
  "type": "Feature",
  "properties": {
    "gn:admin1_code":"25",
    "gn:asciiname":"Rogachi",
    "gn:country_code":"RU",
    "gn:dem":172,
    "gn:feature_class":"P",
    "gn:feature_code":"PPL",
    "gn:name":"Rogachi",
    "gn:population":0,
    "gn:timezone":"Europe/Moscow",
    "iso:country":"RU",
    "name:rus_x_preferred":[
        "\u0420\u043e\u0433\u0430\u0447\u0438"
    ],
    "name:und_x_variant":[
        "Rogachevskiy",
        "Rogachi",
        "\u0420\u043e\u0433\u0430\u0447\u0438"
    ],
    "wof:name":"Rogachi",
    "wof:placetype":"locality"
},
  "geometry": {"coordinates":[35.90376,53.89627],"type":"Point"}
}