{
  "type": "Feature",
  "properties": {
    "gn:admin1_code":"52",
    "gn:asciiname":"Novoye Shchetinovo",
    "gn:country_code":"RU",
    "gn:dem":169,
    "gn:feature_class":"P",
    "gn:feature_code":"PPL",
    "gn:name":"Novoye Shchetinovo",
    "gn:population":0,
    "gn:timezone":"Europe/Moscow",
    "iso:country":"RU",
    "name:rus_x_preferred":[
        "\u041d\u043e\u0432\u043e\u0435 \u0429\u0435\u0442\u0438\u043d\u043e\u0432\u043e"
    ],
    "name:und_x_variant":[
        "\u041d\u043e\u0432\u043e\u0435 \u0429\u0435\u0442\u0438\u043d\u043e\u0432\u043e"
    ],
    "wof:name":"Novoye Shchetinovo",
    "wof:placetype":"locality"
},
  "geometry": {"coordinates":[34.42619000000001,58.5096],"type":"Point"}
}