{
  "type": "Feature",
  "properties": {
    "gn:admin1_code":"77",
    "gn:asciiname":"Papino",
    "gn:country_code":"RU",
    "gn:dem":211,
    "gn:feature_class":"P",
    "gn:feature_code":"PPL",
    "gn:name":"Papino",
    "gn:population":0,
    "gn:timezone":"Europe/Moscow",
    "iso:country":"RU",
    "name:rus_x_preferred":[
        "\u041f\u0430\u043f\u0438\u043d\u043e"
    ],
    "name:und_x_variant":[
        "\u041f\u0430\u043f\u0438\u043d\u043e"
    ],
    "wof:name":"Papino",
    "wof:placetype":"locality"
},
  "geometry": {"coordinates":[34.32019,56.15855],"type":"Point"}
}