{
  "type": "Feature",
  "properties": {
    "gn:admin1_code":"87",
    "gn:asciiname":"Kikkiakki",
    "gn:cc2":"RU",
    "gn:country_code":"RU",
    "gn:dem":48,
    "gn:feature_class":"P",
    "gn:feature_code":"PPL",
    "gn:name":"Kikkiakki",
    "gn:population":0,
    "gn:timezone":"Asia/Yekaterinburg",
    "iso:country":"RU",
    "name:eng_x_preferred":[
        "Kikkiakki"
    ],
    "name:nor_x_preferred":[
        "Kikkiakki"
    ],
    "name:rus_x_preferred":[
        "\u041a\u0438\u043a\u043a\u0438\u0430\u043a\u043a\u0438"
    ],
    "name:und_x_variant":[
        "Kikiakki",
        "\u041a\u0438\u043a\u043a\u0438\u0430\u043a\u043a\u0438",
        "Kikkiakki"
    ],
    "wof:name":"Kikkiakki",
    "wof:placetype":"locality"
},
  "geometry": {"coordinates":[82.76416999999999,63.79],"type":"Point"}
}