{
  "type": "Feature",
  "properties": {
    "gn:admin1_code":"17",
    "gn:asciiname":"Tsirkhe",
    "gn:country_code":"RU",
    "gn:dem":2059,
    "gn:feature_class":"P",
    "gn:feature_code":"PPL",
    "gn:name":"Tsirkhe",
    "gn:population":0,
    "gn:timezone":"Europe/Moscow",
    "iso:country":"RU",
    "name:rus_x_preferred":[
        "\u0426\u0438\u0440\u0445\u0435"
    ],
    "name:und_x_variant":[
        "Tsirkha",
        "Tsirkhe"
    ],
    "wof:name":"Tsirkhe",
    "wof:placetype":"locality"
},
  "geometry": {"coordinates":[47.59679000000001,41.91513],"type":"Point"}
}