{
  "type": "Feature",
  "properties": {
    "gn:admin1_code":"56",
    "gn:asciiname":"Rzhavets",
    "gn:country_code":"RU",
    "gn:dem":227,
    "gn:feature_class":"P",
    "gn:feature_code":"PPL",
    "gn:name":"Rzhavets",
    "gn:population":0,
    "gn:timezone":"Europe/Moscow",
    "iso:country":"RU",
    "name:rus_x_preferred":[
        "\u0420\u0436\u0430\u0432\u0435\u0446"
    ],
    "name:und_x_variant":[
        "\u0420\u0436\u0430\u0432\u0435\u0446"
    ],
    "wof:name":"Rzhavets",
    "wof:placetype":"locality"
},
  "geometry": {"coordinates":[37.35,52.78333000000001],"type":"Point"}
}