{
  "type": "Feature",
  "properties": {
    "gn:admin1_code":"52",
    "gn:asciiname":"Zapol'ye",
    "gn:country_code":"RU",
    "gn:dem":96,
    "gn:feature_class":"P",
    "gn:feature_code":"PPL",
    "gn:name":"Zapol\u2019ye",
    "gn:population":0,
    "gn:timezone":"Europe/Moscow",
    "iso:country":"RU",
    "name:eng_x_preferred":[
        "Zapol'ye"
    ],
    "name:nor_x_preferred":[
        "Zapolje"
    ],
    "name:rus_x_preferred":[
        "\u0417\u0430\u043f\u043e\u043b\u044c\u0435"
    ],
    "name:und_x_variant":[
        "Zapol\u2019ye"
    ],
    "wof:name":"Zapol'ye",
    "wof:placetype":"locality"
},
  "geometry": {"coordinates":[30.70429,57.36625],"type":"Point"}
}