{
  "type": "Feature",
  "properties": {
    "gn:admin1_code":"69",
    "gn:asciiname":"Krivalevka",
    "gn:country_code":"RU",
    "gn:dem":226,
    "gn:feature_class":"P",
    "gn:feature_code":"PPL",
    "gn:name":"Krivalevka",
    "gn:population":0,
    "gn:timezone":"Europe/Moscow",
    "iso:country":"RU",
    "name:rus_x_preferred":[
        "\u041a\u0440\u0438\u0432\u0430\u043b\u0435\u0432\u043a\u0430"
    ],
    "wof:name":"Krivalevka",
    "wof:placetype":"locality"
},
  "geometry": {"coordinates":[33.95194,54.90861],"type":"Point"}
}