{
  "type": "Feature",
  "properties": {
    "gn:admin1_code":"62",
    "gn:asciiname":"Svobodnyy",
    "gn:country_code":"RU",
    "gn:dem":89,
    "gn:feature_class":"P",
    "gn:feature_code":"PPL",
    "gn:name":"Svobodnyy",
    "gn:population":0,
    "gn:timezone":"Europe/Moscow",
    "iso:country":"RU",
    "name:ben_x_preferred":[
        "\u09b8\u09ad\u09cb\u09ac\u09cb\u09a6\u09cb\u09a8\u09bf"
    ],
    "name:ell_x_preferred":[
        "\u03a3\u03b2\u03cc\u03bc\u03c0\u03bf\u03bd\u03c4\u03bd\u03b9"
    ],
    "name:hin_x_preferred":[
        "\u0938\u094d\u0935\u094b\u092c\u094b\u0926\u094d\u0928\u0940"
    ],
    "name:ind_x_preferred":[
        "Svobodnyy"
    ],
    "name:por_x_preferred":[
        "Svobodny"
    ],
    "name:rus_x_preferred":[
        "\u0421\u0432\u043e\u0431\u043e\u0434\u043d\u044b\u0439"
    ],
    "wof:name":"Svobodnyy",
    "wof:placetype":"locality"
},
  "geometry": {"coordinates":[42.0676,54.5697],"type":"Point"}
}