{
  "type": "Feature",
  "properties": {
    "gn:admin1_code":"57",
    "gn:asciiname":"Ul'yanovka",
    "gn:country_code":"RU",
    "gn:dem":207,
    "gn:feature_class":"P",
    "gn:feature_code":"PPL",
    "gn:name":"Ul\u2019yanovka",
    "gn:population":0,
    "gn:timezone":"Europe/Moscow",
    "iso:country":"RU",
    "name:rus_x_preferred":[
        "\u0423\u043b\u044c\u044f\u043d\u043e\u0432\u043a\u0430"
    ],
    "name:und_x_variant":[
        "Ul\u2019yanovskiy",
        "Ul\u2019yanovka"
    ],
    "wof:name":"Ul'yanovka",
    "wof:placetype":"locality"
},
  "geometry": {"coordinates":[44.68557,52.57962],"type":"Point"}
}