{
  "type": "Feature",
  "properties": {
    "gn:admin1_code":"8",
    "gn:asciiname":"Khamitovo",
    "gn:country_code":"RU",
    "gn:dem":507,
    "gn:feature_class":"P",
    "gn:feature_code":"PPL",
    "gn:name":"Khamitovo",
    "gn:population":0,
    "gn:timezone":"Asia/Yekaterinburg",
    "iso:country":"RU",
    "name:eng_x_preferred":[
        "Khamitovo"
    ],
    "name:nor_x_preferred":[
        "Khamitovo"
    ],
    "name:rus_x_preferred":[
        "\u0425\u0430\u043c\u0438\u0442\u043e\u0432\u043e"
    ],
    "name:und_x_variant":[
        "Khamitova",
        "\u0425\u0430\u043c\u0438\u0442\u043e\u0432\u043e",
        "Khamitovo"
    ],
    "wof:name":"Khamitovo",
    "wof:placetype":"locality"
},
  "geometry": {"coordinates":[57.9855,53.5017],"type":"Point"}
}