{
  "type": "Feature",
  "properties": {
    "gn:admin1_code":"8",
    "gn:asciiname":"Khamitovo",
    "gn:country_code":"RU",
    "gn:dem":507,
    "gn:feature_class":"P",
    "gn:feature_code":"PPL",
    "gn:name":"Khamitovo",
    "gn:population":0,
    "gn:timezone":"Asia/Yekaterinburg",
    "iso:country":"RU",
    "name:aze_x_preferred":[
        "X\u0259mit"
    ],
    "name:bak_x_preferred":[
        "\u0425\u04d9\u043c\u0438\u0442"
    ],
    "name:che_x_preferred":[
        "\u0425\u0430\u043c\u0438\u0442\u043e\u0432\u043e"
    ],
    "name:eng_x_preferred":[
        "Khamitovo"
    ],
    "name:hye_x_preferred":[
        "\u053d\u0561\u0574\u056b\u057f\u0578\u057e\u0578"
    ],
    "name:kat_x_preferred":[
        "\u10ee\u10d0\u10db\u10d8\u10e2\u10dd\u10d5\u10dd"
    ],
    "name:kaz_x_preferred":[
        "\u0425\u0430\u043c\u0438\u0442"
    ],
    "name:kir_x_preferred":[
        "\u0425\u0430\u043c\u0438\u0442"
    ],
    "name:nor_x_preferred":[
        "Khamitovo"
    ],
    "name:rus_x_preferred":[
        "\u0425\u0430\u043c\u0438\u0442\u043e\u0432\u043e"
    ],
    "name:tat_x_preferred":[
        "\u0425\u04d9\u043c\u0438\u0442"
    ],
    "name:ukr_x_preferred":[
        "\u0425\u0430\u043c\u0456\u0442\u043e\u0432\u043e"
    ],
    "name:und_x_variant":[
        "Khamitova",
        "\u0425\u0430\u043c\u0438\u0442\u043e\u0432\u043e",
        "Khamitovo"
    ],
    "wof:name":"Khamitovo",
    "wof:placetype":"locality"
},
  "geometry": {"coordinates":[57.9855,53.5017],"type":"Point"}
}