{
  "type": "Feature",
  "properties": {
    "gn:admin1_code":"59",
    "gn:asciiname":"Nezametnoye",
    "gn:country_code":"RU",
    "gn:dem":216,
    "gn:feature_class":"P",
    "gn:feature_code":"PPL",
    "gn:name":"Nezametnoye",
    "gn:population":0,
    "gn:timezone":"Asia/Vladivostok",
    "iso:country":"RU",
    "name:eng_x_preferred":[
        "Nezametnoye"
    ],
    "name:nor_x_preferred":[
        "Nezametnoje"
    ],
    "name:rus_x_preferred":[
        "\u041d\u0435\u0437\u0430\u043c\u0435\u0442\u043d\u043e\u0435"
    ],
    "name:und_x_variant":[
        "Nezametnyy"
    ],
    "wof:name":"Nezametnoye",
    "wof:placetype":"locality"
},
  "geometry": {"coordinates":[134.89868999999999,45.95486],"type":"Point"}
}