{
  "type": "Feature",
  "properties": {
    "gn:admin1_code":"7",
    "gn:asciiname":"Myshkin",
    "gn:country_code":"RU",
    "gn:dem":-9,
    "gn:feature_class":"P",
    "gn:feature_code":"PPL",
    "gn:name":"Myshkin",
    "gn:population":0,
    "gn:timezone":"Europe/Astrakhan",
    "iso:country":"RU",
    "name:rus_x_preferred":[
        "\u041c\u044b\u0448\u043a\u0438\u043d"
    ],
    "wof:name":"Myshkin",
    "wof:placetype":"locality"
},
  "geometry": {"coordinates":[45.41667,48.41667],"type":"Point"}
}