{
  "type": "Feature",
  "properties": {
    "gn:admin1_code":"69",
    "gn:asciiname":"Ledniki",
    "gn:country_code":"RU",
    "gn:dem":206,
    "gn:feature_class":"P",
    "gn:feature_code":"PPL",
    "gn:name":"Ledniki",
    "gn:population":0,
    "gn:timezone":"Europe/Moscow",
    "iso:country":"RU",
    "name:rus_x_preferred":[
        "\u041b\u0435\u0434\u043d\u0438\u043a\u0438"
    ],
    "wof:name":"Ledniki",
    "wof:placetype":"locality"
},
  "geometry": {"coordinates":[32.11889,54.47667],"type":"Point"}
}