{
  "type": "Feature",
  "properties": {
    "gn:admin1_code":"53",
    "gn:asciiname":"Malaya Krutishka",
    "gn:country_code":"RU",
    "gn:dem":257,
    "gn:feature_class":"P",
    "gn:feature_code":"PPL",
    "gn:name":"Malaya Krutishka",
    "gn:population":0,
    "gn:timezone":"Asia/Novosibirsk",
    "iso:country":"RU",
    "name:eng_x_preferred":[
        "Malaya Krutishka"
    ],
    "name:nor_x_preferred":[
        "Mal.Krutisjka"
    ],
    "name:rus_x_preferred":[
        "\u041c\u0430\u043b.\u041a\u0440\u0443\u0442\u0438\u0448\u043a\u0430"
    ],
    "name:rus_x_variant":[
        "\u041c\u0430\u043b\u0430\u044f \u041a\u0440\u0443\u0442\u0438\u0448\u043a\u0430"
    ],
    "name:und_x_variant":[
        "Krutishka",
        "Malaya Krutishka"
    ],
    "wof:name":"Malaya Krutishka",
    "wof:placetype":"locality"
},
  "geometry": {"coordinates":[81.87520000000001,54.06399999999999],"type":"Point"}
}