{
  "type": "Feature",
  "properties": {
    "gn:admin1_code":"5",
    "gn:asciiname":"Uspenovka",
    "gn:country_code":"RU",
    "gn:dem":154,
    "gn:feature_class":"P",
    "gn:feature_code":"PPL",
    "gn:name":"Uspenovka",
    "gn:population":0,
    "gn:timezone":"Asia/Yakutsk",
    "iso:country":"RU",
    "name:eng_x_preferred":[
        "Uspenovka"
    ],
    "name:nor_x_preferred":[
        "Uspenovka"
    ],
    "name:rus_x_preferred":[
        "\u0423\u0441\u043f\u0435\u043d\u043e\u0432\u043a\u0430"
    ],
    "name:und_x_variant":[
        "Uspenskiy",
        "Uspenovka"
    ],
    "wof:name":"Uspenovka",
    "wof:placetype":"locality"
},
  "geometry": {"coordinates":[129.22701999999998,49.69384],"type":"Point"}
}