{
  "type": "Feature",
  "properties": {
    "gn:admin1_code":"56",
    "gn:asciiname":"Yasnaya Polyana",
    "gn:country_code":"RU",
    "gn:dem":223,
    "gn:feature_class":"P",
    "gn:feature_code":"PPL",
    "gn:name":"Yasnaya Polyana",
    "gn:population":0,
    "gn:timezone":"Europe/Moscow",
    "iso:country":"RU",
    "name:rus_x_preferred":[
        "\u042f\u0441\u043d\u0430\u044f \u041f\u043e\u043b\u044f\u043d\u0430"
    ],
    "name:und_x_variant":[
        "\u042f\u0441\u043d\u0430\u044f \u041f\u043e\u043b\u044f\u043d\u0430"
    ],
    "wof:name":"Yasnaya Polyana",
    "wof:placetype":"locality"
},
  "geometry": {"coordinates":[36.9548,52.4542],"type":"Point"}
}