{
  "type": "Feature",
  "properties": {
    "gn:admin1_code":"44",
    "gn:asciiname":"Kuntuk",
    "gn:country_code":"RU",
    "gn:dem":42,
    "gn:feature_class":"P",
    "gn:feature_code":"PPL",
    "gn:name":"Kuntuk",
    "gn:population":0,
    "gn:timezone":"Asia/Magadan",
    "iso:country":"RU",
    "name:rus_x_preferred":[
        "\u041a\u0443\u043d\u0442\u0443\u043a"
    ],
    "wof:name":"Kuntuk",
    "wof:placetype":"locality"
},
  "geometry": {"coordinates":[148.18333000000001,59.78333000000001],"type":"Point"}
}