{
  "type": "Feature",
  "properties": {
    "gn:admin1_code":"77",
    "gn:asciiname":"Starobislovo",
    "gn:country_code":"RU",
    "gn:dem":144,
    "gn:feature_class":"P",
    "gn:feature_code":"PPL",
    "gn:name":"Starobislovo",
    "gn:population":0,
    "gn:timezone":"Europe/Moscow",
    "iso:country":"RU",
    "name:eng_x_preferred":[
        "Starobislovo"
    ],
    "name:nor_x_preferred":[
        "Starobislovo"
    ],
    "name:rus_x_preferred":[
        "\u0421\u0442\u0430\u0440\u043e\u0431\u0438\u0441\u043b\u043e\u0432\u043e"
    ],
    "name:und_x_variant":[
        "\u0421\u0442\u0430\u0440\u043e\u0431\u0438\u0441\u043b\u043e\u0432\u043e",
        "Starobislovo"
    ],
    "wof:name":"Starobislovo",
    "wof:placetype":"locality"
},
  "geometry": {"coordinates":[38.17694,57.10889],"type":"Point"}
}