{
  "type": "Feature",
  "properties": {
    "gn:admin1_code":"33",
    "gn:asciiname":"Koryakovo",
    "gn:country_code":"RU",
    "gn:dem":126,
    "gn:feature_class":"P",
    "gn:feature_code":"PPL",
    "gn:name":"Koryakovo",
    "gn:population":0,
    "gn:timezone":"Europe/Kirov",
    "iso:country":"RU",
    "name:rus_x_preferred":[
        "\u041a\u043e\u0440\u044f\u043a\u043e\u0432\u043e"
    ],
    "wof:name":"Koryakovo",
    "wof:placetype":"locality"
},
  "geometry": {"coordinates":[48.86776,57.62004],"type":"Point"}
}