{
  "type": "Feature",
  "properties": {
    "gn:admin1_code":"30",
    "gn:asciiname":"Urak",
    "gn:country_code":"RU",
    "gn:dem":863,
    "gn:feature_class":"P",
    "gn:feature_code":"PPL",
    "gn:name":"Urak",
    "gn:population":0,
    "gn:timezone":"Asia/Vladivostok",
    "iso:country":"RU",
    "wof:name":"Urak",
    "wof:placetype":"locality"
},
  "geometry": {"coordinates":[141.06666999999999,59.86666999999999],"type":"Point"}
}