{
  "type": "Feature",
  "properties": {
    "gn:admin1_code":"38",
    "gn:asciiname":"Novonikolayevskaya",
    "gn:country_code":"RU",
    "gn:dem":3,
    "gn:feature_class":"P",
    "gn:feature_code":"PPL",
    "gn:name":"Novonikolayevskaya",
    "gn:population":0,
    "gn:timezone":"Europe/Moscow",
    "iso:country":"RU",
    "name:eng_x_preferred":[
        "Novonikolayevskaya"
    ],
    "name:nor_x_preferred":[
        "Novonikolajevskaja"
    ],
    "name:rus_x_preferred":[
        "\u041d\u043e\u0432\u043e\u043d\u0438\u043a\u043e\u043b\u0430\u0435\u0432\u0441\u043a\u0430\u044f"
    ],
    "name:und_x_variant":[
        "Novaya Nikolayevskaya",
        "\u041d\u043e\u0432\u043e\u043d\u0438\u043a\u043e\u043b\u0430\u0435\u0432\u0441\u043a\u0430\u044f",
        "Novonikolayevskaya"
    ],
    "wof:name":"Novonikolayevskaya",
    "wof:placetype":"locality"
},
  "geometry": {"coordinates":[38.37494,45.58639],"type":"Point"}
}