{
  "type": "Feature",
  "properties": {
    "gn:admin1_code":"90",
    "gn:asciiname":"Lyagayevo",
    "gn:country_code":"RU",
    "gn:dem":189,
    "gn:feature_class":"P",
    "gn:feature_code":"PPL",
    "gn:name":"Lyagayevo",
    "gn:population":0,
    "gn:timezone":"Asia/Yekaterinburg",
    "iso:country":"RU",
    "name:che_x_preferred":[
        "\u041b\u044f\u0433\u0430\u0435\u0432\u043e"
    ],
    "name:eng_x_preferred":[
        "Lyagayevo"
    ],
    "name:nor_x_preferred":[
        "Ljagajevo"
    ],
    "name:rus_x_preferred":[
        "\u041b\u044f\u0433\u0430\u0435\u0432\u043e"
    ],
    "name:und_x_variant":[
        "Lyagayeva",
        "Lyagayevo",
        "\u041b\u044f\u0433\u0430\u0435\u0432\u043e"
    ],
    "wof:name":"Lyagayevo",
    "wof:placetype":"locality"
},
  "geometry": {"coordinates":[54.215,59.5926],"type":"Point"}
}