{
  "type": "Feature",
  "properties": {
    "gn:admin1_code":"86",
    "gn:asciiname":"Viktorov",
    "gn:country_code":"RU",
    "gn:dem":76,
    "gn:feature_class":"P",
    "gn:feature_code":"PPL",
    "gn:name":"Viktorov",
    "gn:population":0,
    "gn:timezone":"Europe/Moscow",
    "iso:country":"RU",
    "name:rus_x_preferred":[
        "\u0412\u0438\u043a\u0442\u043e\u0440\u043e\u0432"
    ],
    "wof:name":"Viktorov",
    "wof:placetype":"locality"
},
  "geometry": {"coordinates":[40.8477,50.2036],"type":"Point"}
}