{
  "type": "Feature",
  "properties": {
    "gn:admin1_code":"53",
    "gn:asciiname":"Karasi",
    "gn:country_code":"RU",
    "gn:dem":108,
    "gn:feature_class":"P",
    "gn:feature_code":"PPL",
    "gn:name":"Karasi",
    "gn:population":0,
    "gn:timezone":"Asia/Novosibirsk",
    "iso:country":"RU",
    "name:eng_x_preferred":[
        "Karasi"
    ],
    "name:nor_x_preferred":[
        "Karasi"
    ],
    "name:rus_x_preferred":[
        "\u041a\u0430\u0440\u0430\u0441\u0438"
    ],
    "name:und_x_variant":[
        "Karas\u2019ya",
        "Karasi"
    ],
    "wof:name":"Karasi",
    "wof:placetype":"locality"
},
  "geometry": {"coordinates":[77.65517,54.07346],"type":"Point"}
}