{
  "type": "Feature",
  "properties": {
    "gn:admin1_code":"16",
    "gn:asciiname":"Kushelga",
    "gn:country_code":"RU",
    "gn:dem":139,
    "gn:feature_class":"P",
    "gn:feature_code":"PPL",
    "gn:name":"Kushelga",
    "gn:population":0,
    "gn:timezone":"Europe/Moscow",
    "iso:country":"RU",
    "name:rus_x_preferred":[
        "\u041a\u0443\u0448\u0435\u043b\u0433\u0430"
    ],
    "wof:name":"Kushelga",
    "wof:placetype":"locality"
},
  "geometry": {"coordinates":[47.8258,55.2633],"type":"Point"}
}