{
  "type": "Feature",
  "properties": {
    "gn:admin1_code":"28",
    "gn:asciiname":"Miynala",
    "gn:country_code":"RU",
    "gn:dem":121,
    "gn:feature_class":"P",
    "gn:feature_code":"PPL",
    "gn:name":"Miynala",
    "gn:population":0,
    "gn:timezone":"Europe/Moscow",
    "iso:country":"RU",
    "name:fin_x_preferred":[
        "Miinola"
    ],
    "name:rus_x_preferred":[
        "\u041c\u0438\u0439\u043d\u0430\u043b\u0430"
    ],
    "wof:name":"Miynala",
    "wof:placetype":"locality"
},
  "geometry": {"coordinates":[32.93333,61.86666999999999],"type":"Point"}
}