{
  "type": "Feature",
  "properties": {
    "gn:admin1_code":"91.0",
    "gn:asciiname":"Novaya Doroga",
    "gn:country_code":"RU",
    "gn:dem":325,
    "gn:feature_class":"P",
    "gn:feature_code":"PPL",
    "gn:name":"Novaya Doroga",
    "gn:population":0,
    "gn:timezone":"Asia/Krasnoyarsk",
    "iso:country":"RU",
    "name:rus_x_preferred":[
        "\u041d\u043e\u0432\u0430\u044f \u0414\u043e\u0440\u043e\u0433\u0430"
    ],
    "wof:name":"Novaya Doroga",
    "wof:placetype":"locality"
},
  "geometry": {"coordinates":[91.31012,56.15375],"type":"Point"}
}