{
  "type": "Feature",
  "properties": {
    "gn:admin1_code":"64",
    "gn:asciiname":"Korsakovka",
    "gn:country_code":"RU",
    "gn:dem":5,
    "gn:feature_class":"P",
    "gn:feature_code":"PPL",
    "gn:name":"Korsakovka",
    "gn:population":0,
    "gn:timezone":"Asia/Sakhalin",
    "iso:country":"RU",
    "name:eng_x_preferred":[
        "Korsakovka"
    ],
    "name:nor_x_preferred":[
        "Korsakovka"
    ],
    "name:rus_x_preferred":[
        "\u041a\u043e\u0440\u0441\u0430\u043a\u043e\u0432\u043a\u0430"
    ],
    "name:und_x_variant":[
        "Karsakovka",
        "\u041a\u043e\u0440\u0441\u0430\u043a\u043e\u0432\u043a\u0430",
        "Korsakovka"
    ],
    "wof:name":"Korsakovka",
    "wof:placetype":"locality"
},
  "geometry": {"coordinates":[142.16897,50.87277],"type":"Point"}
}