{
  "type": "Feature",
  "properties": {
    "gn:country":"RU",
    "gn:fcode":"PPL",
    "gn:population":400,
    "iso:country":"RU",
    "name:rus_x_preferred":[
        "\u041d\u043e\u0432\u043b\u0435\u043d\u0441\u043a\u043e\u0435"
    ],
    "name:und_x_variant":[
        "Novlinskaya"
    ],
    "qs:name":"Novlenskoe",
    "qs:name_adm0":"Russia",
    "qs:name_adm1":"Moscow Oblast",
    "qs:photos_9k":1,
    "qs:photos_9r":1,
    "qs:photos_all":8,
    "qs:photos_sr":0,
    "qs:placetype":"Town",
    "qs:pop_sr":"2",
    "wof:name":"Novlenskoe",
    "wof:placetype":"locality",
    "wof:population":400
},
  "geometry": {"coordinates":[37.79332,55.48349],"type":"Point"}
}