{
  "type": "Feature",
  "properties": {
    "gn:admin1_code":"61",
    "gn:asciiname":"Mamonkin",
    "gn:country_code":"RU",
    "gn:dem":81,
    "gn:feature_class":"P",
    "gn:feature_code":"PPL",
    "gn:name":"Mamonkin",
    "gn:population":0,
    "gn:timezone":"Europe/Moscow",
    "iso:country":"RU",
    "name:eng_x_preferred":[
        "Mamonkin"
    ],
    "name:nor_x_preferred":[
        "Mamonkin"
    ],
    "name:rus_x_preferred":[
        "\u041c\u0430\u043c\u043e\u043d\u043a\u0438\u043d"
    ],
    "wof:name":"Mamonkin",
    "wof:placetype":"locality"
},
  "geometry": {"coordinates":[43.5645,46.894],"type":"Point"}
}