{
  "type": "Feature",
  "properties": {
    "gn:admin1_code":"54",
    "gn:asciiname":"Yelizavetinka",
    "gn:country_code":"RU",
    "gn:dem":128,
    "gn:feature_class":"P",
    "gn:feature_code":"PPL",
    "gn:name":"Yelizavetinka",
    "gn:population":0,
    "gn:timezone":"Asia/Omsk",
    "iso:country":"RU",
    "name:eng_x_preferred":[
        "Yelizavetinka"
    ],
    "name:nor_x_preferred":[
        "Jelizavetinka"
    ],
    "name:rus_x_preferred":[
        "\u0415\u043b\u0438\u0437\u0430\u0432\u0435\u0442\u0438\u043d\u043a\u0430"
    ],
    "wof:name":"Yelizavetinka",
    "wof:placetype":"locality"
},
  "geometry": {"coordinates":[70.77406999999999,55.6119],"type":"Point"}
}