{
  "type": "Feature",
  "properties": {
    "gn:admin1_code":"69",
    "gn:asciiname":"Zikeyevo",
    "gn:country_code":"RU",
    "gn:dem":206,
    "gn:feature_class":"P",
    "gn:feature_code":"PPL",
    "gn:name":"Zikeyevo",
    "gn:population":0,
    "gn:timezone":"Europe/Moscow",
    "iso:country":"RU",
    "name:und_x_variant":[
        "Zekeyevo"
    ],
    "wof:name":"Zikeyevo",
    "wof:placetype":"locality"
},
  "geometry": {"coordinates":[34.99413,55.69688000000001],"type":"Point"}
}