{
  "type": "Feature",
  "properties": {
    "gn:admin1_code":"34",
    "gn:asciiname":"Patrakovo",
    "gn:country_code":"RU",
    "gn:dem":153,
    "gn:feature_class":"P",
    "gn:feature_code":"PPL",
    "gn:name":"Patrakovo",
    "gn:population":0,
    "gn:timezone":"Europe/Moscow",
    "iso:country":"RU",
    "name:eng_x_preferred":[
        "Patrakovo"
    ],
    "name:nor_x_preferred":[
        "Patrakovo"
    ],
    "name:rus_x_preferred":[
        "\u041f\u0430\u0442\u0440\u0430\u043a\u043e\u0432\u043e"
    ],
    "name:und_x_variant":[
        "\u041f\u0430\u0442\u0440\u0430\u043a\u043e\u0432\u043e",
        "Patrakovo"
    ],
    "wof:name":"Patrakovo",
    "wof:placetype":"locality"
},
  "geometry": {"coordinates":[48.81791,64.06663],"type":"Point"}
}