{
  "type": "Feature",
  "properties": {
    "gn:admin1_code":"61.0",
    "gn:asciiname":"Belyanin",
    "gn:country_code":"RU",
    "gn:dem":3,
    "gn:feature_class":"P",
    "gn:feature_code":"PPL",
    "gn:name":"Belyanin",
    "gn:population":0,
    "gn:timezone":"Europe/Moscow",
    "iso:country":"RU",
    "name:eng_x_preferred":[
        "Belyanin"
    ],
    "name:nor_x_preferred":[
        "Beljanin"
    ],
    "name:rus_x_preferred":[
        "\u0411\u0435\u043b\u044f\u043d\u0438\u043d"
    ],
    "wof:name":"Belyanin",
    "wof:placetype":"locality"
},
  "geometry": {"coordinates":[40.34194,47.29528],"type":"Point"}
}