{
  "type": "Feature",
  "properties": {
    "gn:admin1_code":"4",
    "gn:asciiname":"Naumovka",
    "gn:country_code":"RU",
    "gn:dem":271,
    "gn:feature_class":"P",
    "gn:feature_code":"PPL",
    "gn:name":"Naumovka",
    "gn:population":0,
    "gn:timezone":"Asia/Barnaul",
    "iso:country":"RU",
    "name:eng_x_preferred":[
        "Naumovka"
    ],
    "name:nor_x_preferred":[
        "Naumovka"
    ],
    "name:rus_x_preferred":[
        "\u041d\u0430\u0443\u043c\u043e\u0432\u043a\u0430"
    ],
    "name:und_x_variant":[
        "Naumovskiy",
        "Naumovka"
    ],
    "wof:name":"Naumovka",
    "wof:placetype":"locality"
},
  "geometry": {"coordinates":[80.4483,51.0301],"type":"Point"}
}