{
  "type": "Feature",
  "properties": {
    "gn:admin1_code":"88",
    "gn:asciiname":"Nesterovka",
    "gn:country_code":"RU",
    "gn:dem":142,
    "gn:feature_class":"P",
    "gn:feature_code":"PPL",
    "gn:name":"Nesterovka",
    "gn:population":0,
    "gn:timezone":"Europe/Moscow",
    "iso:country":"RU",
    "name:rus_x_preferred":[
        "\u041d\u0435\u0441\u0442\u0435\u0440\u043e\u0432\u043a\u0430"
    ],
    "name:und_x_variant":[
        "\u041d\u0435\u0441\u0442\u0435\u0440\u043e\u0432\u043a\u0430"
    ],
    "wof:name":"Nesterovka",
    "wof:placetype":"locality"
},
  "geometry": {"coordinates":[37.9728,57.9164],"type":"Point"}
}