{
  "type": "Feature",
  "properties": {
    "gn:admin1_code":"76",
    "gn:asciiname":"Pogoreloye",
    "gn:country_code":"RU",
    "gn:dem":157,
    "gn:feature_class":"P",
    "gn:feature_code":"PPL",
    "gn:name":"Pogoreloye",
    "gn:population":0,
    "gn:timezone":"Europe/Moscow",
    "iso:country":"RU",
    "name:rus_x_preferred":[
        "\u041f\u043e\u0433\u043e\u0440\u0435\u043b\u043e\u0435"
    ],
    "name:und_x_variant":[
        "\u041f\u043e\u0433\u043e\u0440\u0435\u043b\u043e\u0435"
    ],
    "wof:name":"Pogoreloye",
    "wof:placetype":"locality"
},
  "geometry": {"coordinates":[36.31733,53.71777],"type":"Point"}
}