{
  "type": "Feature",
  "properties": {
    "gn:admin1_code":"42.0",
    "gn:asciiname":"Bolshoye Gertovo",
    "gn:country_code":"RU",
    "gn:dem":39,
    "gn:feature_class":"P",
    "gn:feature_code":"PPL",
    "gn:name":"Bolshoye Gertovo",
    "gn:population":0,
    "gn:timezone":"Europe/Moscow",
    "iso:country":"RU",
    "name:fin_x_preferred":[
        "Suomen Jerttova"
    ],
    "name:rus_x_preferred":[
        "\u0411\u043e\u043b\u044c\u0448\u043e\u0435 \u0413\u0435\u0440\u0442\u043e\u0432\u043e"
    ],
    "wof:name":"Bolshoye Gertovo",
    "wof:placetype":"locality"
},
  "geometry": {"coordinates":[30.81699,59.62871],"type":"Point"}
}