{
  "type": "Feature",
  "properties": {
    "gn:admin1_code":"33",
    "gn:asciiname":"Tarasovy",
    "gn:country_code":"RU",
    "gn:dem":114,
    "gn:feature_class":"P",
    "gn:feature_code":"PPL",
    "gn:name":"Tarasovy",
    "gn:population":0,
    "gn:timezone":"Europe/Kirov",
    "iso:country":"RU",
    "name:rus_x_preferred":[
        "\u0422\u0430\u0440\u0430\u0441\u043e\u0432\u044b"
    ],
    "name:und_x_variant":[
        "Tarasovo",
        "Tarasovy"
    ],
    "wof:name":"Tarasovy",
    "wof:placetype":"locality"
},
  "geometry": {"coordinates":[48.76141,58.32471999999999],"type":"Point"}
}