{
  "type": "Feature",
  "properties": {
    "gn:country":"RU",
    "gn:fcode":"PPL",
    "gn:population":1109,
    "iso:country":"RU",
    "name:ceb_x_preferred":[
        "Svetlaya"
    ],
    "name:eng_x_preferred":[
        "Svetlaya"
    ],
    "name:nld_x_preferred":[
        "Svetlaja"
    ],
    "name:nor_x_preferred":[
        "Svetlaja"
    ],
    "name:pol_x_preferred":[
        "Swiet\u0142aja"
    ],
    "name:rus_x_preferred":[
        "\u0421\u0432\u0435\u0442\u043b\u0430\u044f"
    ],
    "name:und_x_variant":[
        "Svetloe"
    ],
    "qs:name":"Svetlaya",
    "qs:photos_9r":0,
    "qs:photos_sr":0,
    "qs:pop_sr":"3",
    "wd:wordcount":78,
    "wof:name":"Svetlaya",
    "wof:placetype":"locality",
    "wof:population":1109
},
  "geometry": {"coordinates":[138.32973000000001,46.54217],"type":"Point"}
}