{
  "type": "Feature",
  "properties": {
    "gn:admin1_code":"61.0",
    "gn:asciiname":"Krasina",
    "gn:country_code":"RU",
    "gn:dem":69,
    "gn:feature_class":"P",
    "gn:feature_code":"PPL",
    "gn:name":"Krasina",
    "gn:population":0,
    "gn:timezone":"Europe/Moscow",
    "iso:country":"RU",
    "name:rus_x_preferred":[
        "\u041a\u0440\u0430\u0441\u0438\u043d\u0430"
    ],
    "name:und_x_variant":[
        "\u041a\u0440\u0430\u0441\u0438\u043d\u0430"
    ],
    "wof:name":"Krasina",
    "wof:placetype":"locality"
},
  "geometry": {"coordinates":[41.12371,48.87611],"type":"Point"}
}