{
  "type": "Feature",
  "properties": {
    "gn:admin1_code":"43",
    "gn:asciiname":"Ivanovka Pervaya",
    "gn:country_code":"RU",
    "gn:dem":214,
    "gn:feature_class":"P",
    "gn:feature_code":"PPL",
    "gn:name":"Ivanovka Pervaya",
    "gn:population":0,
    "gn:timezone":"Europe/Moscow",
    "iso:country":"RU",
    "name:rus_x_preferred":[
        "\u0418\u0432\u0430\u043d\u043e\u0432\u043a\u0430 \u041f\u0435\u0440\u0432\u0430\u044f"
    ],
    "wof:name":"Ivanovka Pervaya",
    "wof:placetype":"locality"
},
  "geometry": {"coordinates":[38.6668,53.0799],"type":"Point"}
}