{
  "type": "Feature",
  "properties": {
    "gn:admin1_code":"13",
    "gn:asciiname":"Novyy Miass",
    "gn:country_code":"RU",
    "gn:dem":267,
    "gn:feature_class":"P",
    "gn:feature_code":"PPL",
    "gn:name":"Novyy Miass",
    "gn:population":0,
    "gn:timezone":"Asia/Yekaterinburg",
    "iso:country":"RU",
    "name:rus_x_preferred":[
        "\u041d\u043e\u0432\u044b\u0439 \u041c\u0438\u0430\u0441\u0441"
    ],
    "wof:name":"Novyy Miass",
    "wof:placetype":"locality"
},
  "geometry": {"coordinates":[60.5134,55.3168],"type":"Point"}
}