{
  "type": "Feature",
  "properties": {
    "gn:admin1_code":"47",
    "gn:asciiname":"Kul'pino",
    "gn:country_code":"RU",
    "gn:dem":160,
    "gn:feature_class":"P",
    "gn:feature_code":"PPL",
    "gn:name":"Kul\u2019pino",
    "gn:population":0,
    "gn:timezone":"Europe/Moscow",
    "iso:country":"RU",
    "name:nor_x_preferred":[
        "Kulpino"
    ],
    "name:rus_x_preferred":[
        "\u041a\u0443\u043b\u044c\u043f\u0438\u043d\u043e"
    ],
    "name:und_x_variant":[
        "Kul\u2019pino"
    ],
    "wof:name":"Kul'pino",
    "wof:placetype":"locality"
},
  "geometry": {"coordinates":[35.64407,56.16183],"type":"Point"}
}