{
  "type": "Feature",
  "properties": {
    "gn:admin1_code":"40",
    "gn:asciiname":"Beloye Ozero",
    "gn:country_code":"RU",
    "gn:dem":167,
    "gn:feature_class":"P",
    "gn:feature_code":"PPL",
    "gn:name":"Beloye Ozero",
    "gn:population":0,
    "gn:timezone":"Asia/Yekaterinburg",
    "iso:country":"RU",
    "name:nor_x_preferred":[
        "Beloje Ozero"
    ],
    "name:rus_x_preferred":[
        "\u0411\u0435\u043b\u043e\u0435 \u041e\u0437\u0435\u0440\u043e"
    ],
    "wof:name":"Beloye Ozero",
    "wof:placetype":"locality"
},
  "geometry": {"coordinates":[62.7297,55.0581],"type":"Point"}
}