{
  "type": "Feature",
  "properties": {
    "gn:admin1_code":"33",
    "gn:asciiname":"Simakhino",
    "gn:country_code":"RU",
    "gn:dem":206,
    "gn:feature_class":"P",
    "gn:feature_code":"PPL",
    "gn:name":"Simakhino",
    "gn:population":0,
    "gn:timezone":"Europe/Kirov",
    "iso:country":"RU",
    "name:eng_x_preferred":[
        "Simakhino"
    ],
    "name:nor_x_preferred":[
        "Simakhino"
    ],
    "name:rus_x_preferred":[
        "\u0421\u0438\u043c\u0430\u0445\u0438\u043d\u043e"
    ],
    "wof:name":"Simakhino",
    "wof:placetype":"locality"
},
  "geometry": {"coordinates":[49.46488,57.77398],"type":"Point"}
}