{
  "type": "Feature",
  "properties": {
    "gn:admin1_code":"4",
    "gn:asciiname":"Voykovskiy",
    "gn:country_code":"RU",
    "gn:dem":285,
    "gn:feature_class":"P",
    "gn:feature_code":"PPL",
    "gn:name":"Voykovskiy",
    "gn:population":0,
    "gn:timezone":"Asia/Barnaul",
    "iso:country":"RU",
    "wof:name":"Voykovskiy",
    "wof:placetype":"locality"
},
  "geometry": {"coordinates":[81.48333000000002,51.26667],"type":"Point"}
}