{
  "type": "Feature",
  "properties": {
    "gn:admin1_code":"4",
    "gn:asciiname":"Sokharevo",
    "gn:country_code":"RU",
    "gn:dem":233,
    "gn:feature_class":"P",
    "gn:feature_code":"PPL",
    "gn:name":"Sokharevo",
    "gn:population":0,
    "gn:timezone":"Asia/Barnaul",
    "iso:country":"RU",
    "name:eng_x_preferred":[
        "Sokharevo"
    ],
    "name:nor_x_preferred":[
        "Sokharevo"
    ],
    "name:rus_x_preferred":[
        "\u0421\u043e\u0445\u0430\u0440\u0435\u0432\u043e"
    ],
    "name:und_x_variant":[
        "Sukhareva"
    ],
    "wof:name":"Sokharevo",
    "wof:placetype":"locality"
},
  "geometry": {"coordinates":[84.86306,53.31361],"type":"Point"}
}