{
  "type": "Feature",
  "properties": {
    "gn:admin1_code":"33",
    "gn:asciiname":"Skachek",
    "gn:country_code":"RU",
    "gn:dem":191,
    "gn:feature_class":"P",
    "gn:feature_code":"PPL",
    "gn:name":"Skach\u00ebk",
    "gn:population":0,
    "gn:timezone":"Europe/Kirov",
    "iso:country":"RU",
    "name:rus_x_preferred":[
        "\u0421\u043a\u0430\u0447\u0451\u043a"
    ],
    "name:und_x_variant":[
        "Skach\u00ebk"
    ],
    "wof:name":"Skachek",
    "wof:placetype":"locality"
},
  "geometry": {"coordinates":[53.16667,59.91667],"type":"Point"}
}