{
  "type": "Feature",
  "properties": {
    "gn:admin1_code":"90",
    "gn:asciiname":"Nizhnyaya Atnyashka",
    "gn:country_code":"RU",
    "gn:dem":190,
    "gn:feature_class":"P",
    "gn:feature_code":"PPL",
    "gn:name":"Nizhnyaya Atnyashka",
    "gn:population":0,
    "gn:timezone":"Asia/Yekaterinburg",
    "iso:country":"RU",
    "name:rus_x_preferred":[
        "\u041d\u0438\u0436\u043d\u044f\u044f \u0410\u0442\u043d\u044f\u0448\u043a\u0430"
    ],
    "wof:name":"Nizhnyaya Atnyashka",
    "wof:placetype":"locality"
},
  "geometry": {"coordinates":[56.16667,56.46666999999999],"type":"Point"}
}