{
  "type": "Feature",
  "properties": {
    "gn:admin1_code":"33",
    "gn:asciiname":"Nazarovy",
    "gn:country_code":"RU",
    "gn:dem":117,
    "gn:feature_class":"P",
    "gn:feature_code":"PPL",
    "gn:name":"Nazarovy",
    "gn:population":0,
    "gn:timezone":"Europe/Kirov",
    "iso:country":"RU",
    "name:rus_x_preferred":[
        "\u041d\u0430\u0437\u0430\u0440\u043e\u0432\u044b"
    ],
    "name:und_x_variant":[
        "\u041d\u0430\u0437\u0430\u0440\u043e\u0432\u044b"
    ],
    "wof:name":"Nazarovy",
    "wof:placetype":"locality"
},
  "geometry": {"coordinates":[48.94326,58.57444],"type":"Point"}
}