{
  "type": "Feature",
  "properties": {
    "gn:admin1_code":"90",
    "gn:asciiname":"Rogali",
    "gn:country_code":"RU",
    "gn:dem":158,
    "gn:feature_class":"P",
    "gn:feature_code":"PPL",
    "gn:name":"Rogali",
    "gn:population":0,
    "gn:timezone":"Asia/Yekaterinburg",
    "iso:country":"RU",
    "name:eng_x_preferred":[
        "Rogali"
    ],
    "name:nor_x_preferred":[
        "Rogali"
    ],
    "name:rus_x_preferred":[
        "\u0420\u043e\u0433\u0430\u043b\u0438"
    ],
    "wof:name":"Rogali",
    "wof:placetype":"locality"
},
  "geometry": {"coordinates":[54.56957,57.94274],"type":"Point"}
}