{
  "type": "Feature",
  "properties": {
    "gn:admin1_code":"41",
    "gn:asciiname":"Ozerovo",
    "gn:country_code":"RU",
    "gn:dem":202,
    "gn:feature_class":"P",
    "gn:feature_code":"PPL",
    "gn:name":"Ozerovo",
    "gn:population":0,
    "gn:timezone":"Europe/Moscow",
    "iso:country":"RU",
    "name:eng_x_preferred":[
        "Ozerovo"
    ],
    "name:nor_x_preferred":[
        "Ozerovo"
    ],
    "name:rus_x_preferred":[
        "\u041e\u0437\u0435\u0440\u043e\u0432\u043e"
    ],
    "wof:name":"Ozerovo",
    "wof:placetype":"locality"
},
  "geometry": {"coordinates":[36.54889,52.02194],"type":"Point"}
}