{
  "type": "Feature",
  "properties": {
    "gn:admin1_code":"16",
    "gn:asciiname":"Kiv'yaly",
    "gn:country_code":"RU",
    "gn:dem":124,
    "gn:feature_class":"P",
    "gn:feature_code":"PPL",
    "gn:name":"Kiv\u2019yaly",
    "gn:population":0,
    "gn:timezone":"Europe/Moscow",
    "iso:country":"RU",
    "name:rus_x_preferred":[
        "\u041a\u0438\u0432\u044c\u044f\u043b\u044b"
    ],
    "name:und_x_variant":[
        "Kiv\u2019yaly"
    ],
    "wof:name":"Kiv'yaly",
    "wof:placetype":"locality"
},
  "geometry": {"coordinates":[46.8638,55.6517],"type":"Point"}
}