{
  "type": "Feature",
  "properties": {
    "gn:admin1_code":"73",
    "gn:asciiname":"Yerykla",
    "gn:country_code":"RU",
    "gn:dem":118,
    "gn:feature_class":"P",
    "gn:feature_code":"PPL",
    "gn:name":"Yerykla",
    "gn:population":0,
    "gn:timezone":"Europe/Moscow",
    "iso:country":"RU",
    "name:eng_x_preferred":[
        "Yerykla"
    ],
    "name:nor_x_preferred":[
        "Jerykla"
    ],
    "name:rus_x_preferred":[
        "\u0415\u0440\u044b\u043a\u043b\u0430"
    ],
    "name:und_x_variant":[
        "\u0415\u0440\u044b\u043a\u043b\u0430"
    ],
    "wof:name":"Yerykla",
    "wof:placetype":"locality"
},
  "geometry": {"coordinates":[50.21582,54.9524],"type":"Point"}
}