{
  "type": "Feature",
  "properties": {
    "gn:admin1_code":"69.0",
    "gn:asciiname":"Burtsevo",
    "gn:country_code":"RU",
    "gn:dem":214,
    "gn:feature_class":"P",
    "gn:feature_code":"PPL",
    "gn:name":"Burtsevo",
    "gn:population":0,
    "gn:timezone":"Europe/Moscow",
    "iso:country":"RU",
    "name:eng_x_preferred":[
        "Burtsevo"
    ],
    "name:nor_x_preferred":[
        "Burtsevo"
    ],
    "name:rus_x_preferred":[
        "\u0411\u0443\u0440\u0446\u0435\u0432\u043e"
    ],
    "name:und_x_variant":[
        "Burtsova",
        "\u0411\u0443\u0440\u0446\u0435\u0432\u043e",
        "Burtsevo"
    ],
    "wof:name":"Burtsevo",
    "wof:placetype":"locality"
},
  "geometry": {"coordinates":[34.36878,55.62131],"type":"Point"}
}