{
  "type": "Feature",
  "properties": {
    "gn:admin1_code":"42.0",
    "gn:asciiname":"Bol'shoy Syrets",
    "gn:country_code":"RU",
    "gn:dem":64,
    "gn:feature_class":"P",
    "gn:feature_code":"PPL",
    "gn:name":"Bol\u2019shoy Syrets",
    "gn:population":0,
    "gn:timezone":"Europe/Moscow",
    "iso:country":"RU",
    "name:rus_x_preferred":[
        "\u0411\u043e\u043b\u044c\u0448\u043e\u0439 \u0421\u044b\u0440\u0435\u0446"
    ],
    "name:und_x_variant":[
        "Bol\u2019shoy Syrets"
    ],
    "wof:name":"Bol'shoy Syrets",
    "wof:placetype":"locality"
},
  "geometry": {"coordinates":[30.08242000000001,58.68173],"type":"Point"}
}