{
  "type": "Feature",
  "properties": {
    "gn:admin1_code":"77",
    "gn:asciiname":"Chernyatino",
    "gn:country_code":"RU",
    "gn:dem":267,
    "gn:feature_class":"P",
    "gn:feature_code":"PPL",
    "gn:name":"Chernyatino",
    "gn:population":0,
    "gn:timezone":"Europe/Moscow",
    "iso:country":"RU",
    "name:rus_x_preferred":[
        "\u0427\u0435\u0440\u043d\u044f\u0442\u0438\u043d\u043e"
    ],
    "wof:name":"Chernyatino",
    "wof:placetype":"locality"
},
  "geometry": {"coordinates":[32.53111,56.51889],"type":"Point"}
}