{
  "type": "Feature",
  "properties": {
    "gn:admin1_code":"52.0",
    "gn:asciiname":"Danilovshchina",
    "gn:country_code":"RU",
    "gn:dem":103,
    "gn:feature_class":"P",
    "gn:feature_code":"PPL",
    "gn:name":"Danilovshchina",
    "gn:population":0,
    "gn:timezone":"Europe/Moscow",
    "iso:country":"RU",
    "name:rus_x_preferred":[
        "\u0414\u0430\u043d\u0438\u043b\u043e\u0432\u0449\u0438\u043d\u0430"
    ],
    "wof:name":"Danilovshchina",
    "wof:placetype":"locality"
},
  "geometry": {"coordinates":[31.46,57.10944],"type":"Point"}
}