{
  "type": "Feature",
  "properties": {
    "gn:admin1_code":"80.0",
    "gn:asciiname":"Kel'dykovo",
    "gn:country_code":"RU",
    "gn:dem":193,
    "gn:feature_class":"P",
    "gn:feature_code":"PPL",
    "gn:name":"Kel\u2019dykovo",
    "gn:population":0,
    "gn:timezone":"Europe/Samara",
    "iso:country":"RU",
    "name:rus_x_preferred":[
        "\u041a\u0435\u043b\u044c\u0434\u044b\u043a\u043e\u0432\u043e"
    ],
    "name:und_x_variant":[
        "Kel\u2019dykovo"
    ],
    "wof:name":"Kel'dykovo",
    "wof:placetype":"locality"
},
  "geometry": {"coordinates":[52.9235,58.1425],"type":"Point"}
}