{
  "type": "Feature",
  "properties": {
    "gn:admin1_code":"88",
    "gn:asciiname":"Lom",
    "gn:country_code":"RU",
    "gn:dem":156,
    "gn:feature_class":"P",
    "gn:feature_code":"PPL",
    "gn:name":"Lom",
    "gn:population":0,
    "gn:timezone":"Europe/Moscow",
    "iso:country":"RU",
    "name:eng_x_preferred":[
        "Lom"
    ],
    "name:nor_x_preferred":[
        "Lom"
    ],
    "name:rus_x_preferred":[
        "\u041b\u043e\u043c"
    ],
    "name:und_x_variant":[
        "\u041b\u043e\u043c",
        "Lom"
    ],
    "wof:name":"Lom",
    "wof:placetype":"locality"
},
  "geometry": {"coordinates":[40.07295,58.26827],"type":"Point"}
}