{
  "type": "Feature",
  "properties": {
    "gn:admin1_code":"47",
    "gn:asciiname":"Kosilovo",
    "gn:country_code":"RU",
    "gn:dem":249,
    "gn:feature_class":"P",
    "gn:feature_code":"PPL",
    "gn:name":"Kosilovo",
    "gn:population":0,
    "gn:timezone":"Europe/Moscow",
    "iso:country":"RU",
    "name:rus_x_preferred":[
        "\u041a\u043e\u0441\u0438\u043b\u043e\u0432\u043e"
    ],
    "name:und_x_variant":[
        "\u041a\u043e\u0441\u0438\u043b\u043e\u0432\u043e"
    ],
    "wof:name":"Kosilovo",
    "wof:placetype":"locality"
},
  "geometry": {"coordinates":[35.29563,55.87034],"type":"Point"}
}