{
  "type": "Feature",
  "properties": {
    "gn:admin1_code":"9.0",
    "gn:asciiname":"Nekrasov",
    "gn:country_code":"RU",
    "gn:dem":224,
    "gn:feature_class":"P",
    "gn:feature_code":"PPL",
    "gn:name":"Nekrasov",
    "gn:population":0,
    "gn:timezone":"Europe/Moscow",
    "iso:country":"RU",
    "name:slv_x_preferred":[
        "Nekrasov"
    ],
    "wof:name":"Nekrasov",
    "wof:placetype":"locality"
},
  "geometry": {"coordinates":[36.84,50.91972],"type":"Point"}
}