{
  "type": "Feature",
  "properties": {
    "gn:admin1_code":"87",
    "gn:asciiname":"Tarkasale",
    "gn:country_code":"RU",
    "gn:dem":16,
    "gn:feature_class":"P",
    "gn:feature_code":"PPL",
    "gn:name":"Tarkasale",
    "gn:population":0,
    "gn:timezone":"Asia/Yekaterinburg",
    "iso:country":"RU",
    "name:eng_x_preferred":[
        "Tarkasale"
    ],
    "name:nor_x_preferred":[
        "Tarkosale"
    ],
    "name:rus_x_preferred":[
        "\u0422\u0430\u0440\u043a\u043e\u0441\u0430\u043b\u0435"
    ],
    "wof:name":"Tarkasale",
    "wof:placetype":"locality"
},
  "geometry": {"coordinates":[71.87663000000001,68.35297],"type":"Point"}
}