{
  "type": "Feature",
  "properties": {
    "gn:admin1_code":"91",
    "gn:asciiname":"Artel'nog",
    "gn:country_code":"RU",
    "gn:dem":112,
    "gn:feature_class":"P",
    "gn:feature_code":"PPL",
    "gn:name":"Artel\u2019nog",
    "gn:population":0,
    "gn:timezone":"Asia/Krasnoyarsk",
    "iso:country":"RU",
    "name:eng_x_preferred":[
        "Artel'nog"
    ],
    "name:rus_x_preferred":[
        "\u0410\u0440\u0442\u0435\u043b\u044c\u043d\u043e\u0435"
    ],
    "name:rus_x_variant":[
        "\u0410\u0440\u0442\u0435\u043b\u044c\u043d\u043e\u0433"
    ],
    "name:und_x_variant":[
        "Artel\u2019nog"
    ],
    "wof:name":"Artel'nog",
    "wof:placetype":"locality"
},
  "geometry": {"coordinates":[92.98361,61.33889],"type":"Point"}
}