{
  "type": "Feature",
  "properties": {
    "gn:admin1_code":"41",
    "gn:asciiname":"Lozovskoye",
    "gn:country_code":"RU",
    "gn:dem":154,
    "gn:feature_class":"P",
    "gn:feature_code":"PPL",
    "gn:name":"Lozovskoye",
    "gn:population":0,
    "gn:timezone":"Europe/Moscow",
    "iso:country":"RU",
    "name:rus_x_preferred":[
        "\u041b\u043e\u0437\u043e\u0432\u0441\u043a\u043e\u0435"
    ],
    "wof:name":"Lozovskoye",
    "wof:placetype":"locality"
},
  "geometry": {"coordinates":[35.81278,51.64806],"type":"Point"}
}