{
  "type": "Feature",
  "properties": {
    "gn:admin1_code":"71.0",
    "gn:asciiname":"Fotiyeva",
    "gn:country_code":"RU",
    "gn:dem":221,
    "gn:feature_class":"P",
    "gn:feature_code":"PPL",
    "gn:name":"Fotiyeva",
    "gn:population":0,
    "gn:timezone":"Asia/Yekaterinburg",
    "iso:country":"RU",
    "name:rus_x_preferred":[
        "\u0424\u043e\u0442\u0438\u0435\u0432\u0430"
    ],
    "name:und_x_variant":[
        "\u0424\u043e\u0442\u0438\u0435\u0432\u0430"
    ],
    "wof:name":"Fotiyeva",
    "wof:placetype":"locality"
},
  "geometry": {"coordinates":[59.95,57.88333000000001],"type":"Point"}
}