{
  "type": "Feature",
  "properties": {
    "gn:admin1_code":"84",
    "gn:asciiname":"Manoylin",
    "gn:country_code":"RU",
    "gn:dem":121,
    "gn:feature_class":"P",
    "gn:feature_code":"PPL",
    "gn:name":"Manoylin",
    "gn:population":0,
    "gn:timezone":"Europe/Volgograd",
    "iso:country":"RU",
    "name:eng_x_preferred":[
        "Manoylin"
    ],
    "name:nor_x_preferred":[
        "Manojlin"
    ],
    "name:rus_x_preferred":[
        "\u041c\u0430\u043d\u043e\u0439\u043b\u0438\u043d"
    ],
    "name:und_x_variant":[
        "\u041c\u0430\u043d\u043e\u0439\u043b\u0438\u043d",
        "Manoylin"
    ],
    "wof:name":"Manoylin",
    "wof:placetype":"locality"
},
  "geometry": {"coordinates":[42.90268,49.00928],"type":"Point"}
}