{
  "type": "Feature",
  "properties": {
    "gn:admin1_code":"05",
    "gn:asciiname":"Chervonaya Armiya",
    "gn:country_code":"RU",
    "gn:dem":214,
    "gn:feature_class":"P",
    "gn:feature_code":"PPL",
    "gn:name":"Chervonaya Armiya",
    "gn:population":0,
    "gn:timezone":"Asia/Yakutsk",
    "iso:country":"RU",
    "name:che_x_preferred":[
        "\u0427\u0435\u0440\u0432\u043e\u043d\u0438 \u0410\u0440\u043c\u0438"
    ],
    "name:rus_x_preferred":[
        "\u0427\u0435\u0440\u0432\u043e\u043d\u0430\u044f \u0410\u0440\u043c\u0438\u044f"
    ],
    "name:und_x_variant":[
        "Chervona Armiya",
        "Chervonaya Armiya"
    ],
    "wof:name":"Chervonaya Armiya",
    "wof:placetype":"locality"
},
  "geometry": {"coordinates":[129.48887999999999,50.13526],"type":"Point"}
}