{
  "type": "Feature",
  "properties": {
    "gn:admin1_code":"91",
    "gn:asciiname":"Volkova",
    "gn:country_code":"RU",
    "gn:dem":423,
    "gn:feature_class":"P",
    "gn:feature_code":"PPL",
    "gn:name":"Volkova",
    "gn:population":0,
    "gn:timezone":"Asia/Krasnoyarsk",
    "iso:country":"RU",
    "wof:name":"Volkova",
    "wof:placetype":"locality"
},
  "geometry": {"coordinates":[92.61667,53.41667],"type":"Point"}
}