{
  "type": "Feature",
  "properties": {
    "gn:admin1_code":"43",
    "gn:asciiname":"Stepets",
    "gn:country_code":"RU",
    "gn:dem":116,
    "gn:feature_class":"P",
    "gn:feature_code":"PPL",
    "gn:name":"Stepets",
    "gn:population":0,
    "gn:timezone":"Europe/Moscow",
    "iso:country":"RU",
    "name:rus_x_preferred":[
        "\u0421\u0442\u0435\u043f\u0435\u0446"
    ],
    "name:und_x_variant":[
        "\u0421\u0442\u0435\u043f\u0435\u0446"
    ],
    "wof:name":"Stepets",
    "wof:placetype":"locality"
},
  "geometry": {"coordinates":[39.3965,52.3735],"type":"Point"}
}