{
  "type": "Feature",
  "properties": {
    "gn:admin1_code":"45",
    "gn:asciiname":"Malinkino",
    "gn:country_code":"RU",
    "gn:dem":134,
    "gn:feature_class":"P",
    "gn:feature_code":"PPL",
    "gn:name":"Malinkino",
    "gn:population":0,
    "gn:timezone":"Europe/Moscow",
    "iso:country":"RU",
    "name:rus_x_preferred":[
        "\u041c\u0430\u043b\u0438\u043d\u043a\u0438\u043d\u043e"
    ],
    "name:und_x_variant":[
        "\u041c\u0430\u043b\u0438\u043d\u043a\u0438\u043d\u043e"
    ],
    "wof:name":"Malinkino",
    "wof:placetype":"locality"
},
  "geometry": {"coordinates":[49.62427,56.9858],"type":"Point"}
}