{
  "type": "Feature",
  "properties": {
    "gn:admin1_code":"12.0",
    "gn:asciiname":"Bas-Gordali",
    "gn:country_code":"RU",
    "gn:dem":705,
    "gn:feature_class":"P",
    "gn:feature_code":"PPL",
    "gn:name":"Bas-Gordali",
    "gn:population":0,
    "gn:timezone":"Europe/Moscow",
    "iso:country":"RU",
    "name:che_x_preferred":[
        "Basa"
    ],
    "name:che_x_variant":[
        "Araderix",
        "\u0410\u0440\u0430\u0434\u0435\u0440\u0438\u0445",
        "\u0411\u0430\u0441\u0430"
    ],
    "name:nor_x_preferred":[
        "Bas-Gordali"
    ],
    "name:rus_x_preferred":[
        "\u0411\u0430\u0441-\u0413\u043e\u0440\u0434\u0430\u043b\u0438"
    ],
    "name:und_x_variant":[
        "Araderikh",
        "Bas-Gardali",
        "Basa-Gordali"
    ],
    "wof:name":"Bas-Gordali",
    "wof:placetype":"locality"
},
  "geometry": {"coordinates":[46.20996,43.04402],"type":"Point"}
}