{
  "type": "Feature",
  "properties": {
    "gn:admin1_code":"21.0",
    "gn:asciiname":"Stepurino",
    "gn:country_code":"RU",
    "gn:dem":110,
    "gn:feature_class":"P",
    "gn:feature_code":"PPL",
    "gn:name":"Stepurino",
    "gn:population":0,
    "gn:timezone":"Europe/Moscow",
    "iso:country":"RU",
    "name:rus_x_preferred":[
        "\u0421\u0442\u0435\u043f\u0443\u0440\u0438\u043d\u043e"
    ],
    "name:und_x_variant":[
        "\u0421\u0442\u0435\u043f\u0443\u0440\u0438\u043d\u043e"
    ],
    "wof:name":"Stepurino",
    "wof:placetype":"locality"
},
  "geometry": {"coordinates":[42.32832,57.0186],"type":"Point"}
}