{
  "type": "Feature",
  "properties": {
    "gn:admin1_code":"77.0",
    "gn:asciiname":"Dulovo",
    "gn:country_code":"RU",
    "gn:dem":213,
    "gn:feature_class":"P",
    "gn:feature_code":"PPL",
    "gn:name":"Dulovo",
    "gn:population":0,
    "gn:timezone":"Europe/Moscow",
    "iso:country":"RU",
    "name:rus_x_preferred":[
        "\u0414\u0443\u043b\u043e\u0432\u043e"
    ],
    "wof:name":"Dulovo",
    "wof:placetype":"locality"
},
  "geometry": {"coordinates":[32.21558,56.5423],"type":"Point"}
}