{
  "type": "Feature",
  "properties": {
    "gn:admin1_code":"61.0",
    "gn:asciiname":"Astakhov",
    "gn:country_code":"RU",
    "gn:dem":38,
    "gn:feature_class":"P",
    "gn:feature_code":"PPL",
    "gn:name":"Astakhov",
    "gn:population":0,
    "gn:timezone":"Europe/Moscow",
    "iso:country":"RU",
    "name:nor_x_preferred":[
        "Astakhovka"
    ],
    "name:rus_x_preferred":[
        "\u0410\u0441\u0442\u0430\u0445\u043e\u0432"
    ],
    "name:und_x_variant":[
        "Astakhovskiy"
    ],
    "wof:name":"Astakhov",
    "wof:placetype":"locality"
},
  "geometry": {"coordinates":[40.30263,48.46178],"type":"Point"}
}