{
  "type": "Feature",
  "properties": {
    "gn:admin1_code":"70.0",
    "gn:asciiname":"Glubokiy",
    "gn:country_code":"RU",
    "gn:dem":144,
    "gn:feature_class":"P",
    "gn:feature_code":"PPL",
    "gn:name":"Glubokiy",
    "gn:population":0,
    "gn:timezone":"Europe/Moscow",
    "iso:country":"RU",
    "name:eng_x_preferred":[
        "Glubokiy"
    ],
    "name:nor_x_preferred":[
        "Glubokij"
    ],
    "name:rus_x_preferred":[
        "\u0413\u043b\u0443\u0431\u043e\u043a\u0438\u0439"
    ],
    "name:und_x_variant":[
        "\u0413\u043b\u0443\u0431\u043e\u043a\u0438\u0439",
        "Glubokiy"
    ],
    "wof:name":"Glubokiy",
    "wof:placetype":"locality"
},
  "geometry": {"coordinates":[44.14583,44.41722],"type":"Point"}
}