{
  "type": "Feature",
  "properties": {
    "gn:admin1_code":"62",
    "gn:asciiname":"Korostino",
    "gn:country_code":"RU",
    "gn:dem":144,
    "gn:feature_class":"P",
    "gn:feature_code":"PPL",
    "gn:name":"Korostino",
    "gn:population":0,
    "gn:timezone":"Europe/Moscow",
    "iso:country":"RU",
    "name:rus_x_preferred":[
        "\u041a\u043e\u0440\u043e\u0441\u0442\u0438\u043d\u043e"
    ],
    "name:und_x_variant":[
        "\u041a\u043e\u0440\u043e\u0441\u0442\u0438\u043d\u043e"
    ],
    "wof:name":"Korostino",
    "wof:placetype":"locality"
},
  "geometry": {"coordinates":[41.38555,55.03628000000001],"type":"Point"}
}