{
  "type": "Feature",
  "properties": {
    "gn:admin1_code":"51",
    "gn:asciiname":"Maloye Rybushkino",
    "gn:country_code":"RU",
    "gn:dem":127,
    "gn:feature_class":"P",
    "gn:feature_code":"PPL",
    "gn:name":"Maloye Rybushkino",
    "gn:population":0,
    "gn:timezone":"Europe/Moscow",
    "iso:country":"RU",
    "name:rus_x_preferred":[
        "\u041c\u0430\u043b\u043e\u0435 \u0420\u044b\u0431\u0443\u0448\u043a\u0438\u043d\u043e"
    ],
    "wof:name":"Maloye Rybushkino",
    "wof:placetype":"locality"
},
  "geometry": {"coordinates":[45.77499,55.42486],"type":"Point"}
}