{
  "type": "Feature",
  "properties": {
    "gn:admin1_code":"86.0",
    "gn:asciiname":"Gavril'sk",
    "gn:country_code":"RU",
    "gn:dem":104,
    "gn:feature_class":"P",
    "gn:feature_code":"PPL",
    "gn:name":"Gavril\u2019sk",
    "gn:population":0,
    "gn:timezone":"Europe/Moscow",
    "iso:country":"RU",
    "name:eng_x_preferred":[
        "Gavril'sk"
    ],
    "name:nor_x_preferred":[
        "Gavrilsk"
    ],
    "name:rus_x_preferred":[
        "\u0413\u0430\u0432\u0440\u0438\u043b\u044c\u0441\u043a"
    ],
    "name:und_x_variant":[
        "Gavrilovka",
        "Gavril\u2019sk"
    ],
    "wof:name":"Gavril'sk",
    "wof:placetype":"locality"
},
  "geometry": {"coordinates":[40.35694,50.43083],"type":"Point"}
}