{
  "type": "Feature",
  "properties": {
    "gn:admin1_code":"27.0",
    "gn:asciiname":"Adil'-Khalk",
    "gn:country_code":"RU",
    "gn:dem":443,
    "gn:feature_class":"P",
    "gn:feature_code":"PPL",
    "gn:name":"Adil\u2019-Khalk",
    "gn:population":0,
    "gn:timezone":"Europe/Moscow",
    "iso:country":"RU",
    "name:nor_x_preferred":[
        "Adil-Khalk"
    ],
    "name:rus_x_preferred":[
        "\u0410\u0434\u0438\u043b\u044c-\u0425\u0430\u043b\u043a"
    ],
    "name:rus_x_variant":[
        "Adil\u2019-Khalk"
    ],
    "name:und_x_variant":[
        "Mansurovskiy",
        "Adil\u2019-Khalk"
    ],
    "wof:name":"Adil'-Khalk",
    "wof:placetype":"locality"
},
  "geometry": {"coordinates":[41.9265,44.3565],"type":"Point"}
}