{
  "type": "Feature",
  "properties": {
    "gn:admin1_code":"60",
    "gn:asciiname":"Kuptsovo",
    "gn:country_code":"RU",
    "gn:dem":91,
    "gn:feature_class":"P",
    "gn:feature_code":"PPL",
    "gn:name":"Kuptsovo",
    "gn:population":0,
    "gn:timezone":"Europe/Moscow",
    "iso:country":"RU",
    "name:rus_x_preferred":[
        "\u041a\u0443\u043f\u0446\u043e\u0432\u043e"
    ],
    "name:und_x_variant":[
        "Kupts\u00ebvo",
        "Kuptsovo"
    ],
    "wof:name":"Kuptsovo",
    "wof:placetype":"locality"
},
  "geometry": {"coordinates":[28.49472,56.98674000000001],"type":"Point"}
}