{
  "type": "Feature",
  "properties": {
    "gn:country":"RU",
    "gn:fcode":"PPL",
    "gn:population":0,
    "iso:country":"RU",
    "name:che_x_preferred":[
        "\u0413\u0440\u043e\u043c\u043e\u0432\u043e"
    ],
    "name:deu_x_preferred":[
        "Gromowo"
    ],
    "name:eng_x_preferred":[
        "Gromovo"
    ],
    "name:epo_x_preferred":[
        "Gromovo"
    ],
    "name:fas_x_preferred":[
        "\u0641\u0631\u0648\u062f\u06af\u0627\u0647 \u06af\u0631\u0627\u0645\u0648\u0648"
    ],
    "name:fin_x_preferred":[
        "Sakkola"
    ],
    "name:fra_x_preferred":[
        "Gromovo"
    ],
    "name:nld_x_preferred":[
        "Gromovo"
    ],
    "name:nob_x_preferred":[
        "Gromovo"
    ],
    "name:rus_x_preferred":[
        "\u0413\u0440\u043e\u043c\u043e\u0432\u043e"
    ],
    "name:sco_x_preferred":[
        "Gromovo"
    ],
    "name:swe_x_preferred":[
        "Sakkola"
    ],
    "name:tgk_x_preferred":[
        "\u0424\u0443\u0440\u0443\u0434\u0433\u043e\u04b3\u0438 \u0433\u0440\u043e\u043c\u0443\u0432"
    ],
    "name:ukr_x_preferred":[
        "\u0413\u0440\u043e\u043c\u043e\u0432\u043e"
    ],
    "name:zho_x_preferred":[
        "\u85a9\u79d1\u79d1\u62c9"
    ],
    "qs:name":"Gromovo",
    "qs:name_adm0":"Russia",
    "qs:name_adm1":"Leningrad Oblast",
    "qs:photos_9k":1,
    "qs:photos_9r":1,
    "qs:photos_all":2,
    "qs:photos_sr":0,
    "qs:placetype":"Town",
    "qs:pop_sr":"0",
    "wd:wordcount":127,
    "wof:name":"Gromovo",
    "wof:placetype":"locality",
    "wof:population":0
},
  "geometry": {"coordinates":[30.21824,60.69806],"type":"Point"}
}