{
  "type": "Feature",
  "properties": {
    "gn:admin1_code":"90.0",
    "gn:asciiname":"Sorvino",
    "gn:country_code":"RU",
    "gn:dem":126,
    "gn:feature_class":"P",
    "gn:feature_code":"PPL",
    "gn:name":"Sorvino",
    "gn:population":0,
    "gn:timezone":"Asia/Yekaterinburg",
    "iso:country":"RU",
    "name:rus_x_preferred":[
        "\u0421\u043e\u0440\u0432\u0438\u043d\u043e"
    ],
    "wof:name":"Sorvino",
    "wof:placetype":"locality"
},
  "geometry": {"coordinates":[56.3494,59.6818],"type":"Point"}
}