{
  "type": "Feature",
  "properties": {
    "gn:admin1_code":"3.0",
    "gn:asciiname":"Tikhon'kaya",
    "gn:country_code":"RU",
    "gn:dem":931,
    "gn:feature_class":"P",
    "gn:feature_code":"PPL",
    "gn:name":"Tikhon\u2019kaya",
    "gn:population":0,
    "gn:timezone":"Asia/Omsk",
    "iso:country":"RU",
    "name:rus_x_preferred":[
        "\u0422\u0438\u0445\u043e\u043d\u044c\u043a\u0430\u044f"
    ],
    "name:und_x_variant":[
        "Tikhon\u2019kaya"
    ],
    "wof:name":"Tikhon'kaya",
    "wof:placetype":"locality"
},
  "geometry": {"coordinates":[85.7992,50.2025],"type":"Point"}
}