{
  "type": "Feature",
  "properties": {
    "gn:admin1_code":"42",
    "gn:asciiname":"Khinovino",
    "gn:country_code":"RU",
    "gn:dem":63,
    "gn:feature_class":"P",
    "gn:feature_code":"PPL",
    "gn:name":"Khinovino",
    "gn:population":0,
    "gn:timezone":"Europe/Moscow",
    "iso:country":"RU",
    "name:rus_x_preferred":[
        "\u0425\u0438\u043d\u043e\u0432\u0438\u043d\u043e"
    ],
    "wof:name":"Khinovino",
    "wof:placetype":"locality"
},
  "geometry": {"coordinates":[30.61667000000001,58.83333],"type":"Point"}
}