{
  "type": "Feature",
  "properties": {
    "gn:admin1_code":"62",
    "gn:asciiname":"Kushchapino",
    "gn:country_code":"RU",
    "gn:dem":101,
    "gn:feature_class":"P",
    "gn:feature_code":"PPL",
    "gn:name":"Kushchapino",
    "gn:population":0,
    "gn:timezone":"Europe/Moscow",
    "iso:country":"RU",
    "name:rus_x_preferred":[
        "\u041a\u0443\u0449\u0430\u043f\u0438\u043d\u043e"
    ],
    "wof:name":"Kushchapino",
    "wof:placetype":"locality"
},
  "geometry": {"coordinates":[42.5206,54.6063],"type":"Point"}
}