{
  "type": "Feature",
  "properties": {
    "gn:admin1_code":"53",
    "gn:asciiname":"Balta",
    "gn:country_code":"RU",
    "gn:dem":142,
    "gn:feature_class":"P",
    "gn:feature_code":"PPL",
    "gn:name":"Balta",
    "gn:population":0,
    "gn:timezone":"Asia/Novosibirsk",
    "iso:country":"RU",
    "name:ceb_x_preferred":[
        "Balta"
    ],
    "name:deu_x_preferred":[
        "Balta"
    ],
    "name:eng_x_preferred":[
        "Balta"
    ],
    "name:epo_x_preferred":[
        "Balta"
    ],
    "name:est_x_preferred":[
        "Balta"
    ],
    "name:fra_x_preferred":[
        "Balta"
    ],
    "name:hye_x_preferred":[
        "\u0532\u0561\u056c\u057f\u0561"
    ],
    "name:ita_x_preferred":[
        "Balta"
    ],
    "name:kaz_x_preferred":[
        "\u0411\u0430\u043b\u0442\u0430"
    ],
    "name:lav_x_preferred":[
        "Balta"
    ],
    "name:nds_x_preferred":[
        "Balta"
    ],
    "name:nld_x_preferred":[
        "Balta"
    ],
    "name:nor_x_preferred":[
        "Balta"
    ],
    "name:pol_x_preferred":[
        "Balta"
    ],
    "name:por_x_preferred":[
        "Balta"
    ],
    "name:ron_x_preferred":[
        "Balta"
    ],
    "name:rus_x_preferred":[
        "\u0411\u0430\u043b\u0442\u0430"
    ],
    "name:spa_x_preferred":[
        "Balta"
    ],
    "name:srp_x_preferred":[
        "\u0411\u0430\u043b\u0442\u0430"
    ],
    "name:swe_x_preferred":[
        "Balta"
    ],
    "name:ukr_x_preferred":[
        "\u0411\u0430\u043b\u0442\u0430"
    ],
    "name:und_x_variant":[
        "\u0411\u0430\u043b\u0442\u0430",
        "Balta"
    ],
    "name:vol_x_preferred":[
        "Balta"
    ],
    "wof:name":"Balta",
    "wof:placetype":"locality"
},
  "geometry": {"coordinates":[83.87299999999998,55.5166],"type":"Point"}
}