{
  "type": "Feature",
  "properties": {
    "gn:admin1_code":"69",
    "gn:asciiname":"Stanichki",
    "gn:country_code":"RU",
    "gn:dem":228,
    "gn:feature_class":"P",
    "gn:feature_code":"PPL",
    "gn:name":"Stanichki",
    "gn:population":0,
    "gn:timezone":"Europe/Moscow",
    "iso:country":"RU",
    "name:eng_x_preferred":[
        "Stanichki"
    ],
    "name:nor_x_preferred":[
        "Stanitsjki"
    ],
    "name:rus_x_preferred":[
        "\u0421\u0442\u0430\u043d\u0438\u0447\u043a\u0438"
    ],
    "wof:name":"Stanichki",
    "wof:placetype":"locality"
},
  "geometry": {"coordinates":[32.03303,54.72183],"type":"Point"}
}