{
  "type": "Feature",
  "properties": {
    "gn:admin1_code":"05",
    "gn:asciiname":"Albazinka",
    "gn:country_code":"RU",
    "gn:dem":176,
    "gn:feature_class":"P",
    "gn:feature_code":"PPL",
    "gn:name":"Albazinka",
    "gn:population":0,
    "gn:timezone":"Asia/Yakutsk",
    "iso:country":"RU",
    "name:eng_x_preferred":[
        "Albazinka"
    ],
    "name:nor_x_preferred":[
        "Albazinka"
    ],
    "name:rus_x_preferred":[
        "\u0410\u043b\u0431\u0430\u0437\u0438\u043d\u043a\u0430"
    ],
    "wof:name":"Albazinka",
    "wof:placetype":"locality"
},
  "geometry": {"coordinates":[129.03648000000001,50.08600000000001],"type":"Point"}
}