{
  "type": "Feature",
  "properties": {
    "gn:country":"RU",
    "gn:fcode":"PPL",
    "gn:pop":3702,
    "iso:country":"RU",
    "name:arm_x_preferred":[
        "\u0546\u0578\u057e\u0578\u0563\u0578\u0582\u0580\u0578\u057e\u057d\u056f\u056b\u0575"
    ],
    "name:dut_x_preferred":[
        "Novogurovsky"
    ],
    "name:eng_x_preferred":[
        "Novogurovskiy"
    ],
    "name:ger_x_preferred":[
        "Nowogurowski"
    ],
    "name:ita_x_preferred":[
        "Novogurovskij"
    ],
    "name:nor_x_preferred":[
        "Novogurovskij"
    ],
    "name:rus_x_preferred":[
        "\u041d\u043e\u0432\u043e\u0433\u0443\u0440\u043e\u0432\u0441\u043a\u0438\u0439"
    ],
    "qs:name":"Novogurovskiy",
    "qs:name_adm0":"Russia",
    "qs:name_adm1":"Tula Oblast",
    "qs:photos_9r":0,
    "qs:photos_sr":0,
    "qs:placetype":"Town",
    "qs:pop_sr":"4",
    "wof:name":"Novogurovskiy",
    "wof:placetype":"locality",
    "wof:population":3702
},
  "geometry": {"coordinates":[37.33709,54.46782],"type":"Point"}
}