{
  "type": "Feature",
  "properties": {
    "gn:admin1_code":"8.0",
    "gn:asciiname":"Bazilevka",
    "gn:country_code":"RU",
    "gn:dem":305,
    "gn:feature_class":"P",
    "gn:feature_code":"PPL",
    "gn:name":"Bazilevka",
    "gn:population":0,
    "gn:timezone":"Asia/Yekaterinburg",
    "iso:country":"RU",
    "name:nor_x_preferred":[
        "Bazilevka"
    ],
    "name:rus_x_preferred":[
        "\u0411\u0430\u0437\u0438\u043b\u0435\u0432\u043a\u0430"
    ],
    "wof:name":"Bazilevka",
    "wof:placetype":"locality"
},
  "geometry": {"coordinates":[55.38333000000001,52.96666999999999],"type":"Point"}
}