{
  "type": "Feature",
  "properties": {
    "gn:admin1_code":"71",
    "gn:asciiname":"Kostousovskiy Rudnik",
    "gn:country_code":"RU",
    "gn:dem":193,
    "gn:feature_class":"P",
    "gn:feature_code":"PPL",
    "gn:name":"Kostousovskiy Rudnik",
    "gn:population":0,
    "gn:timezone":"Asia/Yekaterinburg",
    "iso:country":"RU",
    "name:rus_x_preferred":[
        "\u041a\u043e\u0441\u0442\u043e\u0443\u0441\u043e\u0432\u0441\u043a\u0438\u0439 \u0420\u0443\u0434\u043d\u0438\u043a"
    ],
    "name:und_x_variant":[
        "\u041a\u043e\u0441\u0442\u043e\u0443\u0441\u043e\u0432\u0441\u043a\u0438\u0439 \u0420\u0443\u0434\u043d\u0438\u043a"
    ],
    "wof:name":"Kostousovskiy Rudnik",
    "wof:placetype":"locality"
},
  "geometry": {"coordinates":[61.2268,57.3676],"type":"Point"}
}