{
  "type": "Feature",
  "properties": {
    "gn:admin1_code":"33",
    "gn:asciiname":"Tarasovo",
    "gn:country_code":"RU",
    "gn:dem":103,
    "gn:feature_class":"P",
    "gn:feature_code":"PPL",
    "gn:name":"Tarasovo",
    "gn:population":0,
    "gn:timezone":"Europe/Kirov",
    "iso:country":"RU",
    "name:rus_x_preferred":[
        "\u0422\u0430\u0440\u0430\u0441\u043e\u0432\u043e"
    ],
    "wof:name":"Tarasovo",
    "wof:placetype":"locality"
},
  "geometry": {"coordinates":[47.8674,57.3212],"type":"Point"}
}