{
  "type": "Feature",
  "properties": {
    "gn:admin1_code":"60",
    "gn:asciiname":"Prudtsy",
    "gn:cc2":"RU",
    "gn:country_code":"RU",
    "gn:dem":101,
    "gn:feature_class":"P",
    "gn:feature_code":"PPL",
    "gn:name":"Prudtsy",
    "gn:population":0,
    "gn:timezone":"Europe/Moscow",
    "iso:country":"RU",
    "name:rus_x_preferred":[
        "\u041f\u0440\u0443\u0434\u0446\u044b"
    ],
    "name:und_x_variant":[
        "Pruttsy",
        "Prudtsy"
    ],
    "wof:name":"Prudtsy",
    "wof:placetype":"locality"
},
  "geometry": {"coordinates":[30.48333,57.65],"type":"Point"}
}