{
  "type": "Feature",
  "properties": {
    "gn:country":"RU",
    "gn:fcode":"PPL",
    "gn:population":3724,
    "iso:country":"RU",
    "name:che_x_preferred":[
        "\u0421\u0435\u0440\u0435\u0434\u043a\u0430"
    ],
    "name:eng_x_preferred":[
        "Seredka"
    ],
    "name:nor_x_preferred":[
        "Seredka"
    ],
    "name:rus_x_preferred":[
        "\u0421\u0435\u0440\u0451\u0434\u043a\u0430"
    ],
    "name:rus_x_variant":[
        "Ser\u00ebdka"
    ],
    "qs:name":"Seredka",
    "qs:name_adm0":"Russia",
    "qs:name_adm1":"Pskov Oblast",
    "qs:photos_9r":0,
    "qs:photos_sr":0,
    "qs:placetype":"Town",
    "qs:pop_sr":"4",
    "wd:wordcount":179,
    "wof:name":"Seredka",
    "wof:placetype":"locality",
    "wof:population":3724
},
  "geometry": {"coordinates":[28.18576,58.15838],"type":"Point"}
}