{
  "type": "Feature",
  "properties": {
    "gn:admin1_code":"15",
    "gn:asciiname":"Tumanskaya",
    "gn:cc2":"RU",
    "gn:country_code":"RU",
    "gn:dem":5,
    "gn:feature_class":"P",
    "gn:feature_code":"PPL",
    "gn:name":"Tumanskaya",
    "gn:population":0,
    "gn:timezone":"Asia/Anadyr",
    "iso:country":"RU",
    "name:eng_x_preferred":[
        "Tumanskaya"
    ],
    "name:nor_x_preferred":[
        "Tumanskij"
    ],
    "name:rus_x_preferred":[
        "\u0422\u0443\u043c\u0430\u043d\u0441\u043a\u0438\u0439"
    ],
    "name:und_x_variant":[
        "Tumanskiy"
    ],
    "wof:name":"Tumanskaya",
    "wof:placetype":"locality"
},
  "geometry": {"coordinates":[178.19999999999999,63.96666999999999],"type":"Point"}
}