{
  "type": "Feature",
  "properties": {
    "gn:admin1_code":"78",
    "gn:asciiname":"Pokrovskoye",
    "gn:country_code":"RU",
    "gn:dem":53,
    "gn:feature_class":"P",
    "gn:feature_code":"PPL",
    "gn:name":"Pokrovskoye",
    "gn:population":0,
    "gn:timezone":"Asia/Yekaterinburg",
    "iso:country":"RU",
    "name:cat_x_preferred":[
        "Pokr\u00f3vskoie"
    ],
    "name:ces_x_preferred":[
        "Pokrovskoje"
    ],
    "name:che_x_preferred":[
        "\u041f\u043e\u043a\u0440\u043e\u0432\u0441\u043a\u0438"
    ],
    "name:eng_x_preferred":[
        "Pokrovskoye"
    ],
    "name:fin_x_preferred":[
        "Pokrovskoje"
    ],
    "name:fry_x_preferred":[
        "Pokrovskoje"
    ],
    "name:hrv_x_preferred":[
        "Pokrovskoje"
    ],
    "name:hun_x_preferred":[
        "Pokrovszkoje"
    ],
    "name:nor_x_preferred":[
        "Pokrovskoje"
    ],
    "name:rus_x_preferred":[
        "\u041f\u043e\u043a\u0440\u043e\u0432\u0441\u043a\u043e\u0435"
    ],
    "name:spa_x_preferred":[
        "Pokr\u00f3vskoye"
    ],
    "name:swe_x_preferred":[
        "Pokrovskoje"
    ],
    "name:ukr_x_preferred":[
        "\u041f\u043e\u043a\u0440\u043e\u0432\u0441\u044c\u043a\u0435"
    ],
    "name:und_x_variant":[
        "\u041f\u043e\u043a\u0440\u043e\u0432\u0441\u043a\u043e\u0435",
        "Pokrovskoye"
    ],
    "wof:name":"Pokrovskoye",
    "wof:placetype":"locality"
},
  "geometry": {"coordinates":[66.79389,57.24028000000001],"type":"Point"}
}