{
  "type": "Feature",
  "properties": {
    "gn:admin1_code":"29",
    "gn:asciiname":"Listvyanka",
    "gn:country_code":"RU",
    "gn:dem":246,
    "gn:feature_class":"P",
    "gn:feature_code":"PPL",
    "gn:name":"Listvyanka",
    "gn:population":0,
    "gn:timezone":"Asia/Novokuznetsk",
    "iso:country":"RU",
    "name:eng_x_preferred":[
        "Listvyanka"
    ],
    "name:nor_x_preferred":[
        "Listvjanka"
    ],
    "name:rus_x_preferred":[
        "\u041b\u0438\u0441\u0442\u0432\u044f\u043d\u043a\u0430"
    ],
    "name:und_x_variant":[
        "\u041b\u0438\u0441\u0442\u0432\u044f\u043d\u043a\u0430",
        "Listvyanka"
    ],
    "wof:name":"Listvyanka",
    "wof:placetype":"locality"
},
  "geometry": {"coordinates":[88.39480999999998,56.06703],"type":"Point"}
}