{
  "type": "Feature",
  "properties": {
    "gn:admin1_code":"33",
    "gn:asciiname":"Staryy Iryuk",
    "gn:country_code":"RU",
    "gn:dem":134,
    "gn:feature_class":"P",
    "gn:feature_code":"PPL",
    "gn:name":"Staryy Iryuk",
    "gn:population":0,
    "gn:timezone":"Europe/Kirov",
    "iso:country":"RU",
    "name:eng_x_preferred":[
        "Staryy Iryuk"
    ],
    "name:nor_x_preferred":[
        "Star.Irjuk"
    ],
    "name:rus_x_preferred":[
        "\u0421\u0442\u0430\u0440.\u0418\u0440\u044e\u043a"
    ],
    "name:rus_x_variant":[
        "\u0421\u0442\u0430\u0440\u044b\u0439 \u0418\u0440\u044e\u043a"
    ],
    "name:und_x_variant":[
        "Iryuk",
        "Staryy Iryuk",
        "\u0421\u0442\u0430\u0440\u044b\u0439 \u0418\u0440\u044e\u043a"
    ],
    "wof:name":"Staryy Iryuk",
    "wof:placetype":"locality"
},
  "geometry": {"coordinates":[50.5603,56.5585],"type":"Point"}
}