{
  "type": "Feature",
  "properties": {
    "gn:admin1_code":"69",
    "gn:asciiname":"Mikhaylovka",
    "gn:country_code":"RU",
    "gn:dem":207,
    "gn:feature_class":"P",
    "gn:feature_code":"PPL",
    "gn:name":"Mikhaylovka",
    "gn:population":0,
    "gn:timezone":"Europe/Moscow",
    "iso:country":"RU",
    "name:ceb_x_preferred":[
        "Mikhaylovka"
    ],
    "name:eng_x_preferred":[
        "Mikhaylovka"
    ],
    "name:nor_x_preferred":[
        "Mikhajlovka"
    ],
    "name:rus_x_preferred":[
        "\u041c\u0438\u0445\u0430\u0439\u043b\u043e\u0432\u043a\u0430"
    ],
    "name:swe_x_preferred":[
        "Mikhaylovka"
    ],
    "name:ukr_x_preferred":[
        "\u041c\u0438\u0445\u0430\u0439\u043b\u043e\u0432\u043a\u0430"
    ],
    "name:und_x_variant":[
        "Michailowka",
        "Mikhaylovka"
    ],
    "wof:name":"Mikhaylovka",
    "wof:placetype":"locality"
},
  "geometry": {"coordinates":[32.9717,54.89496],"type":"Point"}
}