{
  "type": "Feature",
  "properties": {
    "iso:country":"RU",
    "name:che_x_preferred":[
        "\u0410\u043c\u0431\u0430\u0440\u0447\u0438\u043a"
    ],
    "name:eng_x_preferred":[
        "Ambarchik"
    ],
    "name:fra_x_preferred":[
        "Ambartchik"
    ],
    "name:hrv_x_preferred":[
        "Ambar\u010dik"
    ],
    "name:ind_x_preferred":[
        "Ambarchik"
    ],
    "name:lit_x_preferred":[
        "Ambar\u010dikas"
    ],
    "name:nld_x_preferred":[
        "Ambartsjik"
    ],
    "name:pol_x_preferred":[
        "Ambarczyk"
    ],
    "name:rus_x_preferred":[
        "\u0410\u043c\u0431\u0430\u0440\u0447\u0438\u043a"
    ],
    "name:sah_x_preferred":[
        "\u0410\u043c\u0431\u0430\u0440\u0447\u0438\u043a"
    ],
    "ne:ADM0CAP":0.0,
    "ne:ADM0NAME":"Russia",
    "ne:ADM0_A3":"RUS",
    "ne:ADM1NAME":"Sakha (Yakutia)",
    "ne:ADMIN1_COD":0,
    "ne:CAPALT":0,
    "ne:CHANGED":4,
    "ne:CHECKME":2,
    "ne:COMPARE":0,
    "ne:DIFFASCII":0,
    "ne:DIFFNOTE":"Location adjusted.",
    "ne:ELEVATION":0.0,
    "ne:FEATURECLA":"Historic place",
    "ne:GEONAMEID":-1,
    "ne:GEONAMESNO":"Top 50 ranks with no GeoNames match due to small population, not in GeoNames, or poor NEV placement.",
    "ne:GN_POP":0,
    "ne:GTOPO30":0.0,
    "ne:ISO_A2":"RU",
    "ne:LABELRANK":2,
    "ne:LATITUDE":69.651006,
    "ne:LONGITUDE":162.333595,
    "ne:LS_MATCH":0,
    "ne:LS_NAME":"Ambarchik",
    "ne:MAX_AREAKM":0.0,
    "ne:MAX_AREAMI":0.0,
    "ne:MAX_BBXMAX":0.0,
    "ne:MAX_BBXMIN":0.0,
    "ne:MAX_BBYMAX":0.0,
    "ne:MAX_BBYMIN":0.0,
    "ne:MAX_NATSCA":0.0,
    "ne:MAX_PERKM":0.0,
    "ne:MAX_PERMI":0.0,
    "ne:MAX_POP10":0,
    "ne:MAX_POP20":0,
    "ne:MAX_POP300":0,
    "ne:MAX_POP310":0,
    "ne:MAX_POP50":0,
    "ne:MEAN_BBXC":0.0,
    "ne:MEAN_BBYC":0.0,
    "ne:MEGACITY":0,
    "ne:MIN_AREAKM":0.0,
    "ne:MIN_AREAMI":0.0,
    "ne:MIN_BBXMAX":0.0,
    "ne:MIN_BBXMIN":0.0,
    "ne:MIN_BBYMAX":0.0,
    "ne:MIN_BBYMIN":0.0,
    "ne:MIN_PERKM":0.0,
    "ne:MIN_PERMI":0.0,
    "ne:NAME":"Ambarchik",
    "ne:NAMEASCII":"Ambarchik",
    "ne:NAMEDIFF":0,
    "ne:NATSCALE":50,
    "ne:POP1950":0,
    "ne:POP1955":0,
    "ne:POP1960":0,
    "ne:POP1965":0,
    "ne:POP1970":0,
    "ne:POP1975":0,
    "ne:POP1980":0,
    "ne:POP1985":0,
    "ne:POP1990":0,
    "ne:POP1995":0,
    "ne:POP2000":0,
    "ne:POP2005":0,
    "ne:POP2010":0,
    "ne:POP2015":0,
    "ne:POP2020":0,
    "ne:POP2025":0,
    "ne:POP2050":0,
    "ne:POP_MAX":0,
    "ne:POP_MIN":0,
    "ne:POP_OTHER":0,
    "ne:RANK_MAX":0,
    "ne:RANK_MIN":0,
    "ne:SCALERANK":4,
    "ne:SOV0NAME":"Russia",
    "ne:SOV_A3":"RUS",
    "ne:UN_FID":0,
    "ne:UN_LAT":0.0,
    "ne:UN_LONG":0.0,
    "ne:WORLDCITY":0,
    "ne:min_zoom":5.6,
    "wof:name":"Ambarchik",
    "wof:placetype":"locality"
},
  "geometry": {"coordinates":[162.33359492924774,69.65100567542538],"type":"Point"}
}