{
  "type": "Feature",
  "properties": {
    "gn:admin1_code":"51",
    "gn:asciiname":"Paromovo",
    "gn:country_code":"RU",
    "gn:dem":120,
    "gn:feature_class":"P",
    "gn:feature_code":"PPL",
    "gn:name":"Paromovo",
    "gn:population":0,
    "gn:timezone":"Europe/Moscow",
    "iso:country":"RU",
    "name:rus_x_preferred":[
        "\u041f\u0430\u0440\u043e\u043c\u043e\u0432\u043e"
    ],
    "name:und_x_variant":[
        "\u041f\u0430\u0440\u043e\u043c\u043e\u0432\u043e"
    ],
    "wof:name":"Paromovo",
    "wof:placetype":"locality"
},
  "geometry": {"coordinates":[44.44341,56.67399],"type":"Point"}
}