{
  "type": "Feature",
  "properties": {
    "gn:admin1_code":"75",
    "gn:asciiname":"Novyy Vasyugan",
    "gn:country_code":"RU",
    "gn:dem":85,
    "gn:feature_class":"P",
    "gn:feature_code":"PPL",
    "gn:name":"Novyy Vasyugan",
    "gn:population":0,
    "gn:timezone":"Asia/Tomsk",
    "iso:country":"RU",
    "name:eng_x_preferred":[
        "Novyy Vasyugan"
    ],
    "name:nor_x_preferred":[
        "Nov.Vasiugan"
    ],
    "name:rus_x_preferred":[
        "\u041d\u043e\u0432.\u0412\u0430\u0441\u044e\u0433\u0430\u043d"
    ],
    "name:rus_x_variant":[
        "\u041d\u043e\u0432\u044b\u0439 \u0412\u0430\u0441\u044e\u0433\u0430\u043d"
    ],
    "name:und_x_variant":[
        "\u041d\u043e\u0432\u044b\u0439 \u0412\u0430\u0441\u044e\u0433\u0430\u043d"
    ],
    "wof:name":"Novyy Vasyugan",
    "wof:placetype":"locality"
},
  "geometry": {"coordinates":[76.4954,58.5738],"type":"Point"}
}