{
  "type": "Feature",
  "properties": {
    "gn:admin1_code":"90",
    "gn:asciiname":"Rayevo",
    "gn:country_code":"RU",
    "gn:dem":166,
    "gn:feature_class":"P",
    "gn:feature_code":"PPL",
    "gn:name":"Rayevo",
    "gn:population":0,
    "gn:timezone":"Asia/Yekaterinburg",
    "iso:country":"RU",
    "name:rus_x_preferred":[
        "\u0420\u0430\u0435\u0432\u043e"
    ],
    "wof:name":"Rayevo",
    "wof:placetype":"locality"
},
  "geometry": {"coordinates":[57.5332,57.275],"type":"Point"}
}