{
  "type": "Feature",
  "properties": {
    "gn:admin1_code":"17",
    "gn:admin2_code":"571887",
    "gn:asciiname":"Ortakolo",
    "gn:country_code":"RU",
    "gn:dem":654,
    "gn:feature_class":"P",
    "gn:feature_code":"PPL",
    "gn:name":"Ortakolo",
    "gn:population":0,
    "gn:timezone":"Europe/Moscow",
    "iso:country":"RU",
    "name:rus_x_preferred":[
        "\u041e\u0440\u0442\u0430\u043a\u043e\u043b\u043e"
    ],
    "name:und_x_variant":[
        "Ortokolo",
        "Ortakolo",
        "\u041e\u0440\u0442\u0430\u043a\u043e\u043b\u043e"
    ],
    "wof:name":"Ortakolo",
    "wof:placetype":"locality"
},
  "geometry": {"coordinates":[46.38882,42.67057],"type":"Point"}
}