{
  "type": "Feature",
  "properties": {
    "gn:admin1_code":"90",
    "gn:asciiname":"Os'ka",
    "gn:country_code":"RU",
    "gn:dem":175,
    "gn:feature_class":"P",
    "gn:feature_code":"PPL",
    "gn:name":"Os\u2019ka",
    "gn:population":0,
    "gn:timezone":"Asia/Yekaterinburg",
    "iso:country":"RU",
    "name:eng_x_preferred":[
        "Os'ka"
    ],
    "name:nor_x_preferred":[
        "Oska"
    ],
    "name:rus_x_preferred":[
        "\u041e\u0441\u044c\u043a\u0430"
    ],
    "name:und_x_variant":[
        "Os\u2019ka"
    ],
    "wof:name":"Os'ka",
    "wof:placetype":"locality"
},
  "geometry": {"coordinates":[53.92449000000001,60.74658],"type":"Point"}
}