{
  "type": "Feature",
  "properties": {
    "gn:admin1_code":"37.0",
    "gn:asciiname":"Agutino",
    "gn:country_code":"RU",
    "gn:dem":156,
    "gn:feature_class":"P",
    "gn:feature_code":"PPL",
    "gn:name":"Agutino",
    "gn:population":0,
    "gn:timezone":"Europe/Moscow",
    "iso:country":"RU",
    "name:nor_x_preferred":[
        "Agutino"
    ],
    "name:rus_x_preferred":[
        "\u0410\u0433\u0443\u0442\u0438\u043d\u043e"
    ],
    "wof:name":"Agutino",
    "wof:placetype":"locality"
},
  "geometry": {"coordinates":[42.49048,58.94044],"type":"Point"}
}