{
  "type": "Feature",
  "properties": {
    "gn:admin1_code":"75",
    "gn:asciiname":"Strezhnoye",
    "gn:cc2":"RU",
    "gn:country_code":"RU",
    "gn:dem":68,
    "gn:feature_class":"P",
    "gn:feature_code":"PPL",
    "gn:name":"Strezhnoye",
    "gn:population":0,
    "gn:timezone":"Asia/Tomsk",
    "iso:country":"RU",
    "name:eng_x_preferred":[
        "Strezhnoye"
    ],
    "name:nor_x_preferred":[
        "Strezjnoje"
    ],
    "name:rus_x_preferred":[
        "\u0421\u0442\u0440\u0435\u0436\u043d\u043e\u0435"
    ],
    "name:und_x_variant":[
        "Strezhnaya",
        "\u0421\u0442\u0440\u0435\u0436\u043d\u043e\u0435",
        "Strezhnoye"
    ],
    "wof:name":"Strezhnoye",
    "wof:placetype":"locality"
},
  "geometry": {"coordinates":[84.03333000000001,57.75],"type":"Point"}
}