{
  "type": "Feature",
  "properties": {
    "gn:admin1_code":"10",
    "gn:asciiname":"Proletarskiy",
    "gn:country_code":"RU",
    "gn:dem":143,
    "gn:feature_class":"P",
    "gn:feature_code":"PPL",
    "gn:name":"Proletarskiy",
    "gn:population":0,
    "gn:timezone":"Europe/Moscow",
    "iso:country":"RU",
    "name:rus_x_preferred":[
        "\u041f\u0440\u043e\u043b\u0435\u0442\u0430\u0440\u0441\u043a\u0438\u0439"
    ],
    "wof:name":"Proletarskiy",
    "wof:placetype":"locality"
},
  "geometry": {"coordinates":[33.2986,52.6473],"type":"Point"}
}