{
  "type": "Feature",
  "properties": {
    "gn:admin1_code":"65",
    "gn:asciiname":"Imeni Marta",
    "gn:country_code":"RU",
    "gn:dem":59,
    "gn:feature_class":"P",
    "gn:feature_code":"PPL",
    "gn:name":"Imeni Marta",
    "gn:population":0,
    "gn:timezone":"Europe/Samara",
    "iso:country":"RU",
    "name:rus_x_preferred":[
        "\u0418\u043c\u0435\u043d\u0438 \u041c\u0430\u0440\u0442\u0430"
    ],
    "wof:name":"Imeni Marta",
    "wof:placetype":"locality"
},
  "geometry": {"coordinates":[50.03333,52.23333],"type":"Point"}
}