{
  "type": "Feature",
  "properties": {
    "gn:admin1_code":"75",
    "gn:asciiname":"Petrovo",
    "gn:country_code":"RU",
    "gn:dem":78,
    "gn:feature_class":"P",
    "gn:feature_code":"PPL",
    "gn:name":"Petrovo",
    "gn:population":0,
    "gn:timezone":"Asia/Tomsk",
    "iso:country":"RU",
    "name:bos_x_preferred":[
        "Petrovo"
    ],
    "name:bul_x_preferred":[
        "\u041f\u0435\u0442\u0440\u043e\u0432\u043e"
    ],
    "name:ceb_x_preferred":[
        "Petrovo"
    ],
    "name:deu_x_preferred":[
        "Petrowo"
    ],
    "name:eng_x_preferred":[
        "Petrova"
    ],
    "name:eus_x_preferred":[
        "Petrovo"
    ],
    "name:fra_x_preferred":[
        "Petrovo"
    ],
    "name:ita_x_preferred":[
        "Petrovo"
    ],
    "name:nld_x_preferred":[
        "Petrovo"
    ],
    "name:nor_x_preferred":[
        "Petrovo"
    ],
    "name:pol_x_preferred":[
        "Petrowo"
    ],
    "name:ron_x_preferred":[
        "Petrovo"
    ],
    "name:rus_x_preferred":[
        "\u041f\u0435\u0442\u0440\u043e\u0432\u043e"
    ],
    "name:srp_x_preferred":[
        "\u041f\u0435\u0442\u0440\u043e\u0432\u043e"
    ],
    "name:swe_x_preferred":[
        "Petrovo"
    ],
    "name:ukr_x_preferred":[
        "\u041f\u0435\u0442\u0440\u043e\u0432\u043e"
    ],
    "wof:name":"Petrovo",
    "wof:placetype":"locality"
},
  "geometry": {"coordinates":[84.82058000000001,56.53778000000001],"type":"Point"}
}