{
  "type": "Feature",
  "properties": {
    "gn:admin1_code":"21.0",
    "gn:asciiname":"Staryy Sezukh",
    "gn:country_code":"RU",
    "gn:dem":97,
    "gn:feature_class":"P",
    "gn:feature_code":"PPL",
    "gn:name":"Staryy Sezukh",
    "gn:population":0,
    "gn:timezone":"Europe/Moscow",
    "iso:country":"RU",
    "name:nor_x_preferred":[
        "Staryj Sezukh"
    ],
    "name:rus_x_preferred":[
        "\u0421\u0442\u0430\u0440\u044b\u0439 \u0421\u0435\u0437\u0443\u0445"
    ],
    "wof:name":"Staryy Sezukh",
    "wof:placetype":"locality"
},
  "geometry": {"coordinates":[42.70602,56.48328000000001],"type":"Point"}
}