{
  "type": "Feature",
  "properties": {
    "gn:admin1_code":"51",
    "gn:asciiname":"Burepolom",
    "gn:country_code":"RU",
    "gn:dem":106,
    "gn:feature_class":"P",
    "gn:feature_code":"PPL",
    "gn:name":"Burepolom",
    "gn:population":0,
    "gn:timezone":"Europe/Moscow",
    "iso:country":"RU",
    "name:eng_x_preferred":[
        "Burepolom"
    ],
    "name:nor_x_preferred":[
        "Burepolom"
    ],
    "name:rus_x_preferred":[
        "\u0411\u0443\u0440\u0435\u043f\u043e\u043b\u043e\u043c"
    ],
    "name:und_x_variant":[
        "Odoshnur"
    ],
    "wof:name":"Burepolom",
    "wof:placetype":"locality"
},
  "geometry": {"coordinates":[47.35994,57.95643000000001],"type":"Point"}
}