{
  "type": "Feature",
  "properties": {
    "gn:admin1_code":"73",
    "gn:asciiname":"Shaymurzino",
    "gn:country_code":"RU",
    "gn:dem":125,
    "gn:feature_class":"P",
    "gn:feature_code":"PPL",
    "gn:name":"Shaymurzino",
    "gn:population":0,
    "gn:timezone":"Europe/Moscow",
    "iso:country":"RU",
    "name:und_x_variant":[
        "Novoye Shaymurzino",
        "Shaymurzino"
    ],
    "wof:name":"Shaymurzino",
    "wof:placetype":"locality"
},
  "geometry": {"coordinates":[48.09801,54.80506],"type":"Point"}
}