{
  "type": "Feature",
  "properties": {
    "gn:admin1_code":"60",
    "gn:asciiname":"Dmitrovo",
    "gn:country_code":"RU",
    "gn:dem":195,
    "gn:feature_class":"P",
    "gn:feature_code":"PPL",
    "gn:name":"Dmitrovo",
    "gn:population":0,
    "gn:timezone":"Europe/Moscow",
    "iso:country":"RU",
    "name:rus_x_preferred":[
        "\u0414\u043c\u0438\u0442\u0440\u043e\u0432\u043e"
    ],
    "name:und_x_variant":[
        "\u0414\u043c\u0438\u0442\u0440\u043e\u0432\u043e"
    ],
    "wof:name":"Dmitrovo",
    "wof:placetype":"locality"
},
  "geometry": {"coordinates":[29.6772,56.2482],"type":"Point"}
}