{
  "type": "Feature",
  "properties": {
    "gn:admin1_code":"84",
    "gn:asciiname":"Kolodeznyy",
    "gn:country_code":"RU",
    "gn:dem":91,
    "gn:feature_class":"P",
    "gn:feature_code":"PPL",
    "gn:name":"Kolodeznyy",
    "gn:population":0,
    "gn:timezone":"Europe/Volgograd",
    "iso:country":"RU",
    "name:rus_x_preferred":[
        "\u041a\u043e\u043b\u043e\u0434\u0435\u0437\u043d\u044b\u0439"
    ],
    "name:und_x_variant":[
        "Khutor Kolodeznyy",
        "Koledeznyy",
        "Kolodeznyy",
        "\u041a\u043e\u043b\u043e\u0434\u0435\u0437\u043d\u044b\u0439"
    ],
    "wof:name":"Kolodeznyy",
    "wof:placetype":"locality"
},
  "geometry": {"coordinates":[42.7004,49.8804],"type":"Point"}
}