{
  "type": "Feature",
  "properties": {
    "gn:admin1_code":"47",
    "gn:asciiname":"Yelizarovo",
    "gn:cc2":"RU",
    "gn:country_code":"RU",
    "gn:dem":247,
    "gn:feature_class":"P",
    "gn:feature_code":"PPL",
    "gn:name":"Yelizarovo",
    "gn:population":0,
    "gn:timezone":"Europe/Moscow",
    "iso:country":"RU",
    "name:und_x_variant":[
        "Yelizorovo",
        "Yelizarovo"
    ],
    "wof:name":"Yelizarovo",
    "wof:placetype":"locality"
},
  "geometry": {"coordinates":[37.08333,56.26667],"type":"Point"}
}