{
  "type": "Feature",
  "properties": {
    "gn:admin1_code":"75",
    "gn:asciiname":"Chernil'shchikovo",
    "gn:country_code":"RU",
    "gn:dem":86,
    "gn:feature_class":"P",
    "gn:feature_code":"PPL",
    "gn:name":"Chernil\u2019shchikovo",
    "gn:population":0,
    "gn:timezone":"Asia/Tomsk",
    "iso:country":"RU",
    "name:eng_x_preferred":[
        "Chernil'shchikova"
    ],
    "name:rus_x_preferred":[
        "\u0427\u0435\u0440\u043d\u0438\u043b\u044c\u0449\u0438\u043a\u043e\u0432\u043e"
    ],
    "name:rus_x_variant":[
        "\u0427\u0435\u0440\u043d\u0438\u043b\u044c\u0449\u0438\u043a\u043e\u0432o"
    ],
    "name:und_x_variant":[
        "Chernil\u2019shchikova",
        "Chernil\u2019shchikovo",
        "\u0427\u0435\u0440\u043d\u0438\u043b\u044c\u0449\u0438\u043a\u043e\u0432o"
    ],
    "wof:name":"Chernil'shchikovo",
    "wof:placetype":"locality"
},
  "geometry": {"coordinates":[84.72556,56.67],"type":"Point"}
}