{
  "type": "Feature",
  "properties": {
    "gn:admin1_code":"85",
    "gn:asciiname":"Meldan'",
    "gn:country_code":"RU",
    "gn:dem":188,
    "gn:feature_class":"P",
    "gn:feature_code":"PPL",
    "gn:name":"Meldan\u2019",
    "gn:population":0,
    "gn:timezone":"Europe/Moscow",
    "iso:country":"RU",
    "name:rus_x_preferred":[
        "\u041c\u0435\u043b\u0434\u0430\u043d\u044c"
    ],
    "name:und_x_variant":[
        "Meldan\u2019"
    ],
    "wof:name":"Meldan'",
    "wof:placetype":"locality"
},
  "geometry": {"coordinates":[39.1471,59.3774],"type":"Point"}
}