{
  "type": "Feature",
  "properties": {
    "gn:admin1_code":"24.0",
    "gn:asciiname":"Belorechenka",
    "gn:country_code":"RU",
    "gn:dem":-5,
    "gn:feature_class":"P",
    "gn:feature_code":"PPL",
    "gn:name":"Belorechenka",
    "gn:population":0,
    "gn:timezone":"Europe/Moscow",
    "iso:country":"RU",
    "name:nor_x_preferred":[
        "Beloretsjenka"
    ],
    "name:rus_x_preferred":[
        "\u0411\u0435\u043b\u043e\u0440\u0435\u0447\u0435\u043d\u043a\u0430"
    ],
    "wof:name":"Belorechenka",
    "wof:placetype":"locality"
},
  "geometry": {"coordinates":[44.87833,46.69111],"type":"Point"}
}