{
  "type": "Feature",
  "properties": {
    "gn:admin1_code":"80.0",
    "gn:asciiname":"Staraya Vozhoyka",
    "gn:country_code":"RU",
    "gn:dem":125,
    "gn:feature_class":"P",
    "gn:feature_code":"PPL",
    "gn:name":"Staraya Vozhoyka",
    "gn:population":0,
    "gn:timezone":"Europe/Samara",
    "iso:country":"RU",
    "wof:name":"Staraya Vozhoyka",
    "wof:placetype":"locality"
},
  "geometry": {"coordinates":[53.14805,57.00405],"type":"Point"}
}