{
  "type": "Feature",
  "properties": {
    "gn:admin1_code":"73",
    "gn:asciiname":"Irekle",
    "gn:country_code":"RU",
    "gn:dem":243,
    "gn:feature_class":"P",
    "gn:feature_code":"PPL",
    "gn:name":"Irekle",
    "gn:population":0,
    "gn:timezone":"Europe/Moscow",
    "iso:country":"RU",
    "name:rus_x_preferred":[
        "\u0418\u0440\u0435\u043a\u043b\u0435"
    ],
    "name:und_x_variant":[
        "\u0418\u0440\u0435\u043a\u043b\u0435"
    ],
    "wof:name":"Irekle",
    "wof:placetype":"locality"
},
  "geometry": {"coordinates":[52.5377,55.0439],"type":"Point"}
}