{
  "type": "Feature",
  "properties": {
    "gn:admin1_code":"33",
    "gn:asciiname":"Savino",
    "gn:country_code":"RU",
    "gn:dem":105,
    "gn:feature_class":"P",
    "gn:feature_code":"PPL",
    "gn:name":"Savino",
    "gn:population":0,
    "gn:timezone":"Europe/Kirov",
    "iso:country":"RU",
    "name:ceb_x_preferred":[
        "Savino"
    ],
    "name:deu_x_preferred":[
        "Savino"
    ],
    "name:ita_x_preferred":[
        "Savino"
    ],
    "name:pol_x_preferred":[
        "Savino"
    ],
    "name:rus_x_preferred":[
        "\u0421\u0430\u0432\u0438\u043d\u043e"
    ],
    "wof:name":"Savino",
    "wof:placetype":"locality"
},
  "geometry": {"coordinates":[46.7329,60.1597],"type":"Point"}
}