{
  "type": "Feature",
  "properties": {
    "gn:admin1_code":"88",
    "gn:asciiname":"Putilovo",
    "gn:country_code":"RU",
    "gn:dem":128,
    "gn:feature_class":"P",
    "gn:feature_code":"PPL",
    "gn:name":"Putilovo",
    "gn:population":0,
    "gn:timezone":"Europe/Moscow",
    "iso:country":"RU",
    "name:und_x_variant":[
        "Putilova",
        "Putilovo"
    ],
    "wof:name":"Putilovo",
    "wof:placetype":"locality"
},
  "geometry": {"coordinates":[40.06858,57.21941999999999],"type":"Point"}
}