{
  "type": "Feature",
  "properties": {
    "gn:admin1_code":"0.0",
    "gn:asciiname":"Karla Libknekhta",
    "gn:country_code":"RU",
    "gn:dem":148,
    "gn:feature_class":"P",
    "gn:feature_code":"PPL",
    "gn:name":"Karla Libknekhta",
    "gn:population":0,
    "gn:timezone":"Europe/Moscow",
    "iso:country":"RU",
    "name:eng_x_preferred":[
        "Karla Libknekhta"
    ],
    "name:nor_x_preferred":[
        "Karl-Libknekht"
    ],
    "name:rus_x_preferred":[
        "\u041a\u0430\u0440\u043b-\u041b\u0438\u0431\u043a\u043d\u0435\u0445\u0442"
    ],
    "name:rus_x_variant":[
        "\u041a\u0430\u0440\u043b\u0430 \u041b\u0438\u0431\u043a\u043d\u0435\u0445\u0442\u0430"
    ],
    "name:und_x_variant":[
        "Imeni Karla Libknekhta",
        "Karl Libknekht",
        "Kobylina",
        "Karla Libknekhta",
        "\u041a\u0430\u0440\u043b\u0430 \u041b\u0438\u0431\u043a\u043d\u0435\u0445\u0442\u0430"
    ],
    "wof:name":"Karla Libknekhta",
    "wof:placetype":"locality"
},
  "geometry": {"coordinates":[37.19897,59.95346],"type":"Point"}
}