{
  "type": "Feature",
  "properties": {
    "gn:admin1_code":"86",
    "gn:asciiname":"Orlyanovka",
    "gn:country_code":"RU",
    "gn:dem":166,
    "gn:feature_class":"P",
    "gn:feature_code":"PPL",
    "gn:name":"Orlyanovka",
    "gn:population":0,
    "gn:timezone":"Europe/Moscow",
    "iso:country":"RU",
    "name:rus_x_preferred":[
        "\u041e\u0440\u043b\u044f\u043d\u043e\u0432\u043a\u0430"
    ],
    "wof:name":"Orlyanovka",
    "wof:placetype":"locality"
},
  "geometry": {"coordinates":[40.7139,51.7211],"type":"Point"}
}