{
  "type": "Feature",
  "properties": {
    "gn:admin1_code":"84",
    "gn:asciiname":"Grachi",
    "gn:country_code":"RU",
    "gn:dem":72,
    "gn:feature_class":"P",
    "gn:feature_code":"PPL",
    "gn:name":"Grachi",
    "gn:population":0,
    "gn:timezone":"Europe/Volgograd",
    "iso:country":"RU",
    "name:eng_x_preferred":[
        "Grachi"
    ],
    "name:fra_x_preferred":[
        "Grachi"
    ],
    "name:ita_x_preferred":[
        "Grachi"
    ],
    "name:nor_x_preferred":[
        "Gratsji"
    ],
    "name:pol_x_preferred":[
        "Grachi"
    ],
    "name:por_x_preferred":[
        "Grachi"
    ],
    "name:rus_x_preferred":[
        "\u0413\u0440\u0430\u0447\u0438"
    ],
    "name:spa_x_preferred":[
        "Grachi"
    ],
    "name:srp_x_preferred":[
        "\u0413\u0440\u0430\u0447\u0438"
    ],
    "name:und_x_variant":[
        "\u0413\u0440\u0430\u0447\u0438",
        "Grachi"
    ],
    "wof:name":"Grachi",
    "wof:placetype":"locality"
},
  "geometry": {"coordinates":[44.30504000000001,48.95439],"type":"Point"}
}