{
  "type": "Feature",
  "properties": {
    "gn:admin1_code":"47",
    "gn:asciiname":"Kupelitsy",
    "gn:country_code":"RU",
    "gn:dem":197,
    "gn:feature_class":"P",
    "gn:feature_code":"PPL",
    "gn:name":"Kupelitsy",
    "gn:population":0,
    "gn:timezone":"Europe/Moscow",
    "iso:country":"RU",
    "name:rus_x_preferred":[
        "\u041a\u0443\u043f\u0435\u043b\u0438\u0446\u044b"
    ],
    "wof:name":"Kupelitsy",
    "wof:placetype":"locality"
},
  "geometry": {"coordinates":[36.25472,55.35389],"type":"Point"}
}