{
  "type": "Feature",
  "properties": {
    "gn:admin1_code":"86.0",
    "gn:asciiname":"Semilukskiy Leskhoz",
    "gn:country_code":"RU",
    "gn:dem":151,
    "gn:feature_class":"P",
    "gn:feature_code":"PPL",
    "gn:name":"Semilukskiy Leskhoz",
    "gn:population":0,
    "gn:timezone":"Europe/Moscow",
    "iso:country":"RU",
    "wof:name":"Semilukskiy Leskhoz",
    "wof:placetype":"locality"
},
  "geometry": {"coordinates":[39.15939,51.75411],"type":"Point"}
}