{
  "type": "Feature",
  "properties": {
    "gn:admin1_code":"88",
    "gn:asciiname":"Oderikhino",
    "gn:country_code":"RU",
    "gn:dem":150,
    "gn:feature_class":"P",
    "gn:feature_code":"PPL",
    "gn:name":"Oderikhino",
    "gn:population":0,
    "gn:timezone":"Europe/Moscow",
    "iso:country":"RU",
    "name:rus_x_preferred":[
        "\u041e\u0434\u0435\u0440\u0438\u0445\u0438\u043d\u043e"
    ],
    "wof:name":"Oderikhino",
    "wof:placetype":"locality"
},
  "geometry": {"coordinates":[39.17119,56.87455],"type":"Point"}
}