{
  "type": "Feature",
  "properties": {
    "gn:admin1_code":"28",
    "gn:asciiname":"Piytsiyeki",
    "gn:country_code":"RU",
    "gn:dem":164,
    "gn:feature_class":"P",
    "gn:feature_code":"PPL",
    "gn:name":"Piytsiy\u00ebki",
    "gn:population":0,
    "gn:timezone":"Europe/Moscow",
    "iso:country":"RU",
    "name:eng_x_preferred":[
        "Piytsiy\u00ebki"
    ],
    "name:fin_x_preferred":[
        "Piitsijoki"
    ],
    "name:nor_x_preferred":[
        "Pijtsijeki"
    ],
    "name:rus_x_preferred":[
        "\u041f\u0438\u0439\u0442\u0441\u0438\u0435\u043a\u0438"
    ],
    "name:rus_x_variant":[
        "\u041f\u0438\u0439\u0446\u0438\u0451\u043a\u0438"
    ],
    "name:und_x_variant":[
        "Piytsiy\u00ebki",
        "\u041f\u0438\u0439\u0446\u0438\u0451\u043a\u0438"
    ],
    "wof:name":"Piytsiyeki",
    "wof:placetype":"locality"
},
  "geometry": {"coordinates":[32.10308,62.03135],"type":"Point"}
}