{
  "type": "Feature",
  "properties": {
    "gn:admin1_code":"69",
    "gn:asciiname":"Zamalich'ye",
    "gn:country_code":"RU",
    "gn:dem":239,
    "gn:feature_class":"P",
    "gn:feature_code":"PPL",
    "gn:name":"Zamalich\u2019ye",
    "gn:population":0,
    "gn:timezone":"Europe/Moscow",
    "iso:country":"RU",
    "name:rus_x_preferred":[
        "\u0417\u0430\u043c\u0430\u043b\u0438\u0447\u044c\u0435"
    ],
    "name:und_x_variant":[
        "Zamalich\u2019ye"
    ],
    "wof:name":"Zamalich'ye",
    "wof:placetype":"locality"
},
  "geometry": {"coordinates":[32.303,55.23141],"type":"Point"}
}