{
  "type": "Feature",
  "properties": {
    "gn:admin1_code":"54",
    "gn:asciiname":"Karatal",
    "gn:country_code":"RU",
    "gn:dem":100,
    "gn:feature_class":"P",
    "gn:feature_code":"PPL",
    "gn:name":"Karatal",
    "gn:population":0,
    "gn:timezone":"Asia/Omsk",
    "iso:country":"RU",
    "name:eng_x_preferred":[
        "Karatal"
    ],
    "name:nor_x_preferred":[
        "Karatal"
    ],
    "name:rus_x_preferred":[
        "\u041a\u0430\u0440\u0430\u0442\u0430\u043b"
    ],
    "wof:name":"Karatal",
    "wof:placetype":"locality"
},
  "geometry": {"coordinates":[74.28416999999997,53.99056],"type":"Point"}
}