{
  "type": "Feature",
  "properties": {
    "gn:admin1_code":"17.0",
    "gn:asciiname":"Korsh",
    "gn:country_code":"RU",
    "gn:dem":1799,
    "gn:feature_class":"P",
    "gn:feature_code":"PPL",
    "gn:name":"Korsh",
    "gn:population":0,
    "gn:timezone":"Europe/Moscow",
    "iso:country":"RU",
    "name:rus_x_preferred":[
        "\u041a\u043e\u0440\u0448"
    ],
    "wof:name":"Korsh",
    "wof:placetype":"locality"
},
  "geometry": {"coordinates":[47.06211,41.66952],"type":"Point"}
}