{
  "type": "Feature",
  "properties": {
    "gn:admin1_code":"38.0",
    "gn:asciiname":"Primorskiy",
    "gn:country_code":"RU",
    "gn:dem":8,
    "gn:feature_class":"P",
    "gn:feature_code":"PPL",
    "gn:name":"Primorskiy",
    "gn:population":0,
    "gn:timezone":"Europe/Moscow",
    "iso:country":"RU",
    "name:rus_x_preferred":[
        "\u041f\u0440\u0438\u043c\u043e\u0440\u0441\u043a\u0438\u0439"
    ],
    "wof:name":"Primorskiy",
    "wof:placetype":"locality"
},
  "geometry": {"coordinates":[38.31526,46.05896],"type":"Point"}
}