{
  "type": "Feature",
  "properties": {
    "gn:admin1_code":"69",
    "gn:asciiname":"Rzhaven'ye",
    "gn:country_code":"RU",
    "gn:dem":203,
    "gn:feature_class":"P",
    "gn:feature_code":"PPL",
    "gn:name":"Rzhaven\u2019ye",
    "gn:population":0,
    "gn:timezone":"Europe/Moscow",
    "iso:country":"RU",
    "name:rus_x_preferred":[
        "\u0420\u0436\u0430\u0432\u0435\u043d\u044c\u0435"
    ],
    "name:und_x_variant":[
        "Rzhaven\u2019ye",
        "\u0420\u0436\u0430\u0432\u0435\u043d\u044c\u0435",
        "Rzhavin\u2019ye"
    ],
    "wof:name":"Rzhaven'ye",
    "wof:placetype":"locality"
},
  "geometry": {"coordinates":[34.20884,55.88782],"type":"Point"}
}