{
  "type": "Feature",
  "properties": {
    "gn:admin1_code":"71",
    "gn:asciiname":"Lenevskoye",
    "gn:country_code":"RU",
    "gn:dem":200,
    "gn:feature_class":"P",
    "gn:feature_code":"PPL",
    "gn:name":"Lenevskoye",
    "gn:population":0,
    "gn:timezone":"Asia/Yekaterinburg",
    "iso:country":"RU",
    "name:eng_x_preferred":[
        "Lenevskoye"
    ],
    "name:nor_x_preferred":[
        "Lenevskoje"
    ],
    "name:rus_x_preferred":[
        "\u041b\u0435\u043d\u0435\u0432\u0441\u043a\u043e\u0435"
    ],
    "name:und_x_variant":[
        "\u041b\u0435\u043d\u0435\u0432\u0441\u043a\u043e\u0435",
        "Lenevskoye"
    ],
    "wof:name":"Lenevskoye",
    "wof:placetype":"locality"
},
  "geometry": {"coordinates":[61.37924,57.58643000000001],"type":"Point"}
}