{
  "type": "Feature",
  "properties": {
    "gn:admin1_code":"20",
    "gn:asciiname":"Yey",
    "gn:country_code":"RU",
    "gn:dem":415,
    "gn:feature_class":"P",
    "gn:feature_code":"PPL",
    "gn:name":"Yey",
    "gn:population":0,
    "gn:timezone":"Asia/Irkutsk",
    "iso:country":"RU",
    "name:rus_x_preferred":[
        "\u0415\u0439"
    ],
    "wof:name":"Yey",
    "wof:placetype":"locality"
},
  "geometry": {"coordinates":[102.6143,53.8272],"type":"Point"}
}