{
  "type": "Feature",
  "properties": {
    "gn:admin1_code":"45",
    "gn:asciiname":"Morkiyaly",
    "gn:country_code":"RU",
    "gn:dem":100,
    "gn:feature_class":"P",
    "gn:feature_code":"PPL",
    "gn:name":"Morkiyaly",
    "gn:population":0,
    "gn:timezone":"Europe/Moscow",
    "iso:country":"RU",
    "name:rus_x_preferred":[
        "\u041c\u043e\u0440\u043a\u0438\u044f\u043b\u044b"
    ],
    "name:und_x_variant":[
        "Morkiyal",
        "Morkiyaly"
    ],
    "wof:name":"Morkiyaly",
    "wof:placetype":"locality"
},
  "geometry": {"coordinates":[48.50947,55.95146],"type":"Point"}
}