{
  "type": "Feature",
  "properties": {
    "gn:admin1_code":"54",
    "gn:asciiname":"Priozerka",
    "gn:country_code":"RU",
    "gn:dem":112,
    "gn:feature_class":"P",
    "gn:feature_code":"PPL",
    "gn:name":"Prioz\u00ebrka",
    "gn:population":0,
    "gn:timezone":"Asia/Omsk",
    "iso:country":"RU",
    "name:eng_x_preferred":[
        "Prioz\u00ebrnaya"
    ],
    "name:nor_x_preferred":[
        "Priozerka"
    ],
    "name:rus_x_preferred":[
        "\u041f\u0440\u0438\u043e\u0437\u0435\u0440\u043a\u0430"
    ],
    "name:rus_x_variant":[
        "\u041f\u0440\u0438\u043e\u0437\u0451\u0440\u043a\u0430"
    ],
    "name:und_x_variant":[
        "Prioz\u00ebrka"
    ],
    "wof:name":"Priozerka",
    "wof:placetype":"locality"
},
  "geometry": {"coordinates":[72.58507,56.10735],"type":"Point"}
}