{
  "type": "Feature",
  "properties": {
    "gn:admin1_code":"37.0",
    "gn:asciiname":"Aferovo",
    "gn:country_code":"RU",
    "gn:dem":89,
    "gn:feature_class":"P",
    "gn:feature_code":"PPL",
    "gn:name":"Af\u00ebrovo",
    "gn:population":0,
    "gn:timezone":"Europe/Moscow",
    "iso:country":"RU",
    "wof:name":"Aferovo",
    "wof:placetype":"locality"
},
  "geometry": {"coordinates":[40.85892,57.80295],"type":"Point"}
}