{
  "type": "Feature",
  "properties": {
    "gn:admin1_code":"42",
    "gn:asciiname":"Sumino",
    "gn:country_code":"RU",
    "gn:dem":146,
    "gn:feature_class":"P",
    "gn:feature_code":"PPL",
    "gn:name":"Sumino",
    "gn:population":0,
    "gn:timezone":"Europe/Moscow",
    "iso:country":"RU",
    "name:fin_x_preferred":[
        "Sumina"
    ],
    "name:nor_x_preferred":[
        "Sumino"
    ],
    "name:rus_x_preferred":[
        "\u0421\u0443\u043c\u0438\u043d\u043e"
    ],
    "wof:name":"Sumino",
    "wof:placetype":"locality"
},
  "geometry": {"coordinates":[29.47651,59.47206],"type":"Point"}
}