{
  "type": "Feature",
  "properties": {
    "gn:admin1_code":"69",
    "gn:asciiname":"Klemyatino",
    "gn:country_code":"RU",
    "gn:dem":203,
    "gn:feature_class":"P",
    "gn:feature_code":"PPL",
    "gn:name":"Klemyatino",
    "gn:population":0,
    "gn:timezone":"Europe/Moscow",
    "iso:country":"RU",
    "name:rus_x_preferred":[
        "\u041a\u043b\u0435\u043c\u044f\u0442\u0438\u043d\u043e"
    ],
    "wof:name":"Klemyatino",
    "wof:placetype":"locality"
},
  "geometry": {"coordinates":[32.84395,54.7462],"type":"Point"}
}