{
  "type": "Feature",
  "properties": {
    "gn:admin1_code":"77",
    "gn:asciiname":"Karganovy",
    "gn:cc2":"RU",
    "gn:country_code":"RU",
    "gn:dem":194,
    "gn:feature_class":"P",
    "gn:feature_code":"PPL",
    "gn:name":"Karganovy",
    "gn:population":0,
    "gn:timezone":"Europe/Moscow",
    "iso:country":"RU",
    "name:rus_x_preferred":[
        "\u041a\u0430\u0440\u0433\u0430\u043d\u043e\u0432\u044b"
    ],
    "name:und_x_variant":[
        "Karganovo",
        "Karganovy",
        "\u041a\u0430\u0440\u0433\u0430\u043d\u043e\u0432\u044b"
    ],
    "wof:name":"Karganovy",
    "wof:placetype":"locality"
},
  "geometry": {"coordinates":[34.58333,56.26667],"type":"Point"}
}