{
  "type": "Feature",
  "properties": {
    "gn:admin1_code":"65",
    "gn:asciiname":"Redkaya Bereza",
    "gn:country_code":"RU",
    "gn:dem":84,
    "gn:feature_class":"P",
    "gn:feature_code":"PPL",
    "gn:name":"Redkaya Ber\u00ebza",
    "gn:population":0,
    "gn:timezone":"Europe/Samara",
    "iso:country":"RU",
    "name:rus_x_preferred":[
        "\u0420\u0435\u0434\u043a\u0430\u044f \u0411\u0435\u0440\u0451\u0437\u0430"
    ],
    "name:und_x_variant":[
        "Redkaya Ber\u00ebza"
    ],
    "wof:name":"Redkaya Bereza",
    "wof:placetype":"locality"
},
  "geometry": {"coordinates":[51.107,54.5691],"type":"Point"}
}