{
  "type": "Feature",
  "properties": {
    "gn:admin1_code":"71.0",
    "gn:asciiname":"Cherlak",
    "gn:country_code":"RU",
    "gn:dem":255,
    "gn:feature_class":"P",
    "gn:feature_code":"PPL",
    "gn:name":"Cherlak",
    "gn:population":0,
    "gn:timezone":"Asia/Yekaterinburg",
    "iso:country":"RU",
    "name:ben_x_preferred":[
        "\u099a\u09c7\u09b0\u09cd\u09b2\u09c7\u0995"
    ],
    "name:ell_x_preferred":[
        "\u03a4\u03c3\u03b5\u03c1\u03bb\u03ac\u03ba"
    ],
    "name:fas_x_preferred":[
        "\u0686\u0631\u0644\u0627\u06a9"
    ],
    "name:fra_x_preferred":[
        "Tcherlak"
    ],
    "name:hin_x_preferred":[
        "\u091a\u0947\u0930\u0932\u0948\u0915"
    ],
    "name:ind_x_preferred":[
        "Cherlak"
    ],
    "name:ita_x_preferred":[
        "Cherlak"
    ],
    "name:jpn_x_preferred":[
        "\u30c1\u30a7\u30eb\u30e9\u30af"
    ],
    "name:kor_x_preferred":[
        "\uccbc\ub77d"
    ],
    "name:rus_x_preferred":[
        "\u0427\u0435\u0440\u043b\u0430\u043a"
    ],
    "name:spa_x_preferred":[
        "Cherlak"
    ],
    "name:swe_x_preferred":[
        "Tjerlak"
    ],
    "name:tur_x_preferred":[
        "Cherlak"
    ],
    "name:ukr_x_preferred":[
        "\u0427\u0435\u0440\u043b\u0430\u043a"
    ],
    "name:und_x_variant":[
        "Charlan",
        "Cherlak"
    ],
    "name:urd_x_preferred":[
        "\u0686\u06cc\u0631\u0644\u0627\u06a9"
    ],
    "name:vie_x_preferred":[
        "Cherlak"
    ],
    "name:zho_cn_x_preferred":[
        "\u5207\u62c9\u514b"
    ],
    "name:zho_tw_x_preferred":[
        "\u5207\u723e\u62c9\u514b"
    ],
    "wof:name":"Cherlak",
    "wof:placetype":"locality"
},
  "geometry": {"coordinates":[57.91669,56.40212],"type":"Point"}
}