{
  "type": "Feature",
  "properties": {
    "gn:admin1_code":"71.0",
    "gn:asciiname":"Cherlak",
    "gn:country_code":"RU",
    "gn:dem":255,
    "gn:feature_class":"P",
    "gn:feature_code":"PPL",
    "gn:name":"Cherlak",
    "gn:population":0,
    "gn:timezone":"Asia/Yekaterinburg",
    "iso:country":"RU",
    "name:rus_x_preferred":[
        "\u0427\u0435\u0440\u043b\u0430\u043a"
    ],
    "name:und_x_variant":[
        "Charlan",
        "Cherlak",
        "\u0427\u0435\u0440\u043b\u0430\u043a"
    ],
    "wof:name":"Cherlak",
    "wof:placetype":"locality"
},
  "geometry": {"coordinates":[57.91669,56.40212],"type":"Point"}
}