{
  "type": "Feature",
  "properties": {
    "gn:admin1_code":"8",
    "gn:asciiname":"Kalmakovo",
    "gn:country_code":"RU",
    "gn:dem":141,
    "gn:feature_class":"P",
    "gn:feature_code":"PPL",
    "gn:name":"Kalmakovo",
    "gn:population":0,
    "gn:timezone":"Asia/Yekaterinburg",
    "iso:country":"RU",
    "name:aze_x_preferred":[
        "Kalmak"
    ],
    "name:bak_x_preferred":[
        "\u04a0\u0430\u043b\u043c\u0430\u04a1"
    ],
    "name:che_x_preferred":[
        "\u041a\u0430\u043b\u043c\u0430\u043a\u043e\u0432\u043e"
    ],
    "name:hye_x_preferred":[
        "\u053f\u0561\u056c\u0574\u0561\u056f\u0578\u057e\u0578"
    ],
    "name:kat_x_preferred":[
        "\u10d9\u10d0\u10da\u10db\u10d0\u10d9\u10dd\u10d5\u10dd"
    ],
    "name:kaz_x_preferred":[
        "\u041a\u0430\u043b\u043c\u0430\u043a"
    ],
    "name:kir_x_preferred":[
        "\u041a\u0430\u043b\u043c\u0430\u043a"
    ],
    "name:rus_x_preferred":[
        "\u041a\u0430\u043b\u043c\u0430\u043a\u043e\u0432\u043e"
    ],
    "name:tat_x_preferred":[
        "\u041a\u0430\u043b\u043c\u0430\u043a"
    ],
    "name:ukr_x_preferred":[
        "\u041a\u0430\u043b\u043c\u0430\u043a\u043e\u0432\u043e"
    ],
    "name:und_x_variant":[
        "\u041a\u0430\u043b\u043c\u0430\u043a\u043e\u0432\u043e"
    ],
    "wof:name":"Kalmakovo",
    "wof:placetype":"locality"
},
  "geometry": {"coordinates":[56.479,53.6381],"type":"Point"}
}