{
  "type": "Feature",
  "properties": {
    "gn:admin1_code":"8",
    "gn:asciiname":"Kalmakovo",
    "gn:country_code":"RU",
    "gn:dem":141,
    "gn:feature_class":"P",
    "gn:feature_code":"PPL",
    "gn:name":"Kalmakovo",
    "gn:population":0,
    "gn:timezone":"Asia/Yekaterinburg",
    "iso:country":"RU",
    "name:rus_x_preferred":[
        "\u041a\u0430\u043b\u043c\u0430\u043a\u043e\u0432\u043e"
    ],
    "name:und_x_variant":[
        "\u041a\u0430\u043b\u043c\u0430\u043a\u043e\u0432\u043e"
    ],
    "wof:name":"Kalmakovo",
    "wof:placetype":"locality"
},
  "geometry": {"coordinates":[56.479,53.6381],"type":"Point"}
}