{
  "type": "Feature",
  "properties": {
    "gn:admin1_code":"25",
    "gn:asciiname":"Kolyshkino Pervoye",
    "gn:country_code":"RU",
    "gn:dem":153,
    "gn:feature_class":"P",
    "gn:feature_code":"PPL",
    "gn:name":"Kolyshkino Pervoye",
    "gn:population":0,
    "gn:timezone":"Europe/Moscow",
    "iso:country":"RU",
    "name:rus_x_preferred":[
        "\u041a\u043e\u043b\u044b\u0448\u043a\u0438\u043d\u043e"
    ],
    "name:und_x_variant":[
        "Kolyshkino",
        "Kolyshkino Pervoye"
    ],
    "wof:name":"Kolyshkino Pervoye",
    "wof:placetype":"locality"
},
  "geometry": {"coordinates":[35.69889000000001,54.59528],"type":"Point"}
}