{
  "type": "Feature",
  "properties": {
    "gn:admin1_code":"6",
    "gn:asciiname":"Zavel'ye",
    "gn:country_code":"RU",
    "gn:dem":115,
    "gn:feature_class":"P",
    "gn:feature_code":"PPL",
    "gn:name":"Zavel\u2019ye",
    "gn:population":0,
    "gn:timezone":"Europe/Moscow",
    "iso:country":"RU",
    "name:rus_x_preferred":[
        "Zavel\u2019ye"
    ],
    "name:rus_x_variant":[
        "\u0417\u0430\u0432\u0435\u043b\u044c\u0435"
    ],
    "name:und_x_variant":[
        "Rylkovskaya",
        "Rylkovskoye"
    ],
    "wof:name":"Zavel'ye",
    "wof:placetype":"locality"
},
  "geometry": {"coordinates":[41.2798,61.0973],"type":"Point"}
}