{
  "type": "Feature",
  "properties": {
    "gn:admin1_code":"69",
    "gn:asciiname":"Los'mino",
    "gn:country_code":"RU",
    "gn:dem":232,
    "gn:feature_class":"P",
    "gn:feature_code":"PPL",
    "gn:name":"Los\u2019mino",
    "gn:population":0,
    "gn:timezone":"Europe/Moscow",
    "iso:country":"RU",
    "name:eng_x_preferred":[
        "Los'mino"
    ],
    "name:nor_x_preferred":[
        "Losmino"
    ],
    "name:rus_x_preferred":[
        "\u041b\u043e\u0441\u044c\u043c\u0438\u043d\u043e"
    ],
    "name:und_x_variant":[
        "Krasnoye Los\u2019mino",
        "\u041b\u043e\u0441\u044c\u043c\u0438\u043d\u043e",
        "Los\u2019mino"
    ],
    "wof:name":"Los'mino",
    "wof:placetype":"locality"
},
  "geometry": {"coordinates":[34.40439,55.06806],"type":"Point"}
}