{
  "type": "Feature",
  "properties": {
    "gn:admin1_code":"65",
    "gn:asciiname":"Zapadnyy",
    "gn:country_code":"RU",
    "gn:dem":50,
    "gn:feature_class":"P",
    "gn:feature_code":"PPL",
    "gn:name":"Zapadnyy",
    "gn:population":0,
    "gn:timezone":"Europe/Samara",
    "iso:country":"RU",
    "name:rus_x_preferred":[
        "\u0417\u0430\u043f\u0430\u0434\u043d\u044b\u0439"
    ],
    "name:und_x_variant":[
        "\u0417\u0430\u043f\u0430\u0434\u043d\u044b\u0439"
    ],
    "wof:name":"Zapadnyy",
    "wof:placetype":"locality"
},
  "geometry": {"coordinates":[51.129,53.045],"type":"Point"}
}