{
  "type": "Feature",
  "properties": {
    "gn:admin1_code":"77",
    "gn:asciiname":"Maloye Ivan'kovo",
    "gn:country_code":"RU",
    "gn:dem":176,
    "gn:feature_class":"P",
    "gn:feature_code":"PPL",
    "gn:name":"Maloye Ivan\u2019kovo",
    "gn:population":0,
    "gn:timezone":"Europe/Moscow",
    "iso:country":"RU",
    "name:rus_x_preferred":[
        "\u041c\u0430\u043b\u043e\u0435 \u0418\u0432\u0430\u043d\u044c\u043a\u043e\u0432\u043e"
    ],
    "name:und_x_variant":[
        "Maloye Ivan\u2019kovo",
        "\u041c\u0430\u043b\u043e\u0435 \u0418\u0432\u0430\u043d\u044c\u043a\u043e\u0432\u043e"
    ],
    "wof:name":"Maloye Ivan'kovo",
    "wof:placetype":"locality"
},
  "geometry": {"coordinates":[35.16667,58.05],"type":"Point"}
}