{
  "type": "Feature",
  "properties": {
    "gn:admin1_code":"63",
    "gn:asciiname":"Menkerya",
    "gn:country_code":"RU",
    "gn:dem":60,
    "gn:feature_class":"P",
    "gn:feature_code":"PPL",
    "gn:name":"Menkerya",
    "gn:population":0,
    "gn:timezone":"Asia/Yakutsk",
    "iso:country":"RU",
    "name:eng_x_preferred":[
        "Menkerya"
    ],
    "name:nor_x_preferred":[
        "Menkere"
    ],
    "name:rus_x_preferred":[
        "\u041c\u044d\u043d\u043a\u044d\u0440\u044d"
    ],
    "name:rus_x_variant":[
        "\u041c\u0435\u043d\u043a\u0435\u0440\u044f"
    ],
    "name:und_x_variant":[
        "Oybyn"
    ],
    "wof:name":"Menkerya",
    "wof:placetype":"locality"
},
  "geometry": {"coordinates":[123.34744999999999,67.9889],"type":"Point"}
}