{
  "type": "Feature",
  "properties": {
    "gn:admin1_code":"60",
    "gn:asciiname":"Somino",
    "gn:country_code":"RU",
    "gn:dem":158,
    "gn:feature_class":"P",
    "gn:feature_code":"PPL",
    "gn:name":"Somino",
    "gn:population":0,
    "gn:timezone":"Europe/Moscow",
    "iso:country":"RU",
    "name:rus_x_preferred":[
        "\u0421\u043e\u043c\u0438\u043d\u043e"
    ],
    "wof:name":"Somino",
    "wof:placetype":"locality"
},
  "geometry": {"coordinates":[29.48115,56.05451],"type":"Point"}
}