{
  "type": "Feature",
  "properties": {
    "gn:admin1_code":"80.0",
    "gn:asciiname":"Bulgurt",
    "gn:country_code":"RU",
    "gn:dem":117,
    "gn:feature_class":"P",
    "gn:feature_code":"PPL",
    "gn:name":"Bulgurt",
    "gn:population":0,
    "gn:timezone":"Europe/Samara",
    "iso:country":"RU",
    "name:rus_x_preferred":[
        "\u0411\u0443\u043b\u0433\u0443\u0440\u0442"
    ],
    "wof:name":"Bulgurt",
    "wof:placetype":"locality"
},
  "geometry": {"coordinates":[52.42145,56.7572],"type":"Point"}
}