{
  "type": "Feature",
  "properties": {
    "gn:admin1_code":"85",
    "gn:asciiname":"Mitinskaya",
    "gn:country_code":"RU",
    "gn:dem":201,
    "gn:feature_class":"P",
    "gn:feature_code":"PPL",
    "gn:name":"Mitinskaya",
    "gn:population":0,
    "gn:timezone":"Europe/Moscow",
    "iso:country":"RU",
    "name:che_x_preferred":[
        "\u041c\u0438\u0442\u0438\u043d\u0441\u043a\u0438"
    ],
    "name:rus_x_preferred":[
        "\u041c\u0438\u0442\u0438\u043d\u0441\u043a\u0430\u044f"
    ],
    "wof:name":"Mitinskaya",
    "wof:placetype":"locality"
},
  "geometry": {"coordinates":[40.95911,60.52862],"type":"Point"}
}