{
  "type": "Feature",
  "properties": {
    "gn:admin1_code":"76",
    "gn:asciiname":"Bogdanovka",
    "gn:country_code":"RU",
    "gn:dem":190,
    "gn:feature_class":"P",
    "gn:feature_code":"PPL",
    "gn:name":"Bogdanovka",
    "gn:population":0,
    "gn:timezone":"Europe/Moscow",
    "iso:country":"RU",
    "name:cat_x_preferred":[
        "Bogdanovka"
    ],
    "name:deu_x_preferred":[
        "Bogdanowka"
    ],
    "name:heb_x_preferred":[
        "\u05d1\u05d5\u05d2\u05d3\u05e0\u05d5\u05d1\u05e7\u05d4"
    ],
    "name:ind_x_preferred":[
        "Bogdanovka"
    ],
    "name:spa_x_preferred":[
        "Bogdanovka"
    ],
    "wof:name":"Bogdanovka",
    "wof:placetype":"locality"
},
  "geometry": {"coordinates":[37.91905,54.08446],"type":"Point"}
}