{
  "type": "Feature",
  "properties": {
    "gn:admin1_code":"33",
    "gn:asciiname":"Kolodkiny",
    "gn:country_code":"RU",
    "gn:dem":158,
    "gn:feature_class":"P",
    "gn:feature_code":"PPL",
    "gn:name":"Kolodkiny",
    "gn:population":0,
    "gn:timezone":"Europe/Kirov",
    "iso:country":"RU",
    "name:rus_x_preferred":[
        "\u041a\u043e\u043b\u043e\u0434\u043a\u0438\u043d\u044b"
    ],
    "name:und_x_variant":[
        "Knyazevo",
        "Kolodkino",
        "Kolodkiny",
        "\u041a\u043e\u043b\u043e\u0434\u043a\u0438\u043d\u044b"
    ],
    "wof:name":"Kolodkiny",
    "wof:placetype":"locality"
},
  "geometry": {"coordinates":[50.15417,58.86056],"type":"Point"}
}