{
  "type": "Feature",
  "properties": {
    "gn:admin1_code":"16",
    "gn:asciiname":"Syutpylykh",
    "gn:country_code":"RU",
    "gn:dem":137,
    "gn:feature_class":"P",
    "gn:feature_code":"PPL",
    "gn:name":"Syutpylykh",
    "gn:population":0,
    "gn:timezone":"Europe/Moscow",
    "iso:country":"RU",
    "name:rus_x_preferred":[
        "\u0421\u044e\u0442\u043f\u043b\u044b\u0445"
    ],
    "wof:name":"Syutpylykh",
    "wof:placetype":"locality"
},
  "geometry": {"coordinates":[47.43282,55.96271],"type":"Point"}
}