{
  "type": "Feature",
  "properties": {
    "gn:admin1_code":"42",
    "gn:asciiname":"Kal'shenitsy",
    "gn:country_code":"RU",
    "gn:dem":139,
    "gn:feature_class":"P",
    "gn:feature_code":"PPL",
    "gn:name":"Kal\u2019shenitsy",
    "gn:population":0,
    "gn:timezone":"Europe/Moscow",
    "iso:country":"RU",
    "name:rus_x_preferred":[
        "\u041a\u0430\u043b\u044c\u0448\u0435\u043d\u0438\u0446\u044b"
    ],
    "name:und_x_variant":[
        "Kat\u0161enitsi",
        "Kal\u2019shenitsy",
        "\u041a\u0430\u043b\u044c\u0448\u0435\u043d\u0438\u0446\u044b"
    ],
    "wof:name":"Kal'shenitsy",
    "wof:placetype":"locality"
},
  "geometry": {"coordinates":[33.90863,60.30866],"type":"Point"}
}