{
  "type": "Feature",
  "properties": {
    "gn:admin1_code":"69",
    "gn:asciiname":"Kichigino",
    "gn:country_code":"RU",
    "gn:dem":197,
    "gn:feature_class":"P",
    "gn:feature_code":"PPL",
    "gn:name":"Kichigino",
    "gn:population":0,
    "gn:timezone":"Europe/Moscow",
    "iso:country":"RU",
    "name:rus_x_preferred":[
        "\u041a\u0438\u0447\u0438\u0433\u0438\u043d\u043e"
    ],
    "name:und_x_variant":[
        "\u041a\u0438\u0447\u0438\u0433\u0438\u043d\u043e"
    ],
    "wof:name":"Kichigino",
    "wof:placetype":"locality"
},
  "geometry": {"coordinates":[34.71892,55.64843000000001],"type":"Point"}
}