{
  "type": "Feature",
  "properties": {
    "gn:admin1_code":"69",
    "gn:asciiname":"Pesnevo",
    "gn:country_code":"RU",
    "gn:dem":217,
    "gn:feature_class":"P",
    "gn:feature_code":"PPL",
    "gn:name":"Pesnevo",
    "gn:population":0,
    "gn:timezone":"Europe/Moscow",
    "iso:country":"RU",
    "name:rus_x_preferred":[
        "\u041f\u0435\u0441\u043d\u0435\u0432\u043e"
    ],
    "wof:name":"Pesnevo",
    "wof:placetype":"locality"
},
  "geometry": {"coordinates":[32.58528,55.23694],"type":"Point"}
}