{
  "type": "Feature",
  "properties": {
    "gn:admin1_code":"3",
    "gn:asciiname":"Aktal",
    "gn:country_code":"RU",
    "gn:dem":1810,
    "gn:feature_class":"P",
    "gn:feature_code":"PPL",
    "gn:name":"Aktal",
    "gn:population":0,
    "gn:timezone":"Asia/Omsk",
    "iso:country":"RU",
    "name:che_x_preferred":[
        "\u0410\u043a\u0442\u0430\u043b"
    ],
    "name:eng_x_preferred":[
        "Aktal"
    ],
    "name:nor_x_preferred":[
        "Aktal"
    ],
    "name:rus_x_preferred":[
        "\u0410\u043a\u0442\u0430\u043b"
    ],
    "name:tat_x_preferred":[
        "\u0410\u043a\u0442\u0430\u043b"
    ],
    "name:ukr_x_preferred":[
        "\u0410\u043a\u0442\u0430\u043b"
    ],
    "name:und_x_variant":[
        "\u0410\u043a\u0442\u0430\u043b",
        "Aktal"
    ],
    "wof:name":"Aktal",
    "wof:placetype":"locality"
},
  "geometry": {"coordinates":[88.86667,49.91667],"type":"Point"}
}