{
  "type": "Feature",
  "properties": {
    "gn:admin1_code":"12.0",
    "gn:asciiname":"Dobosoy",
    "gn:country_code":"RU",
    "gn:dem":977,
    "gn:feature_class":"P",
    "gn:feature_code":"PPL",
    "gn:name":"Dobosoy",
    "gn:population":0,
    "gn:timezone":"Europe/Moscow",
    "iso:country":"RU",
    "name:rus_x_preferred":[
        "\u0414\u043e\u0431\u043e\u0441\u043e\u0439"
    ],
    "wof:name":"Dobosoy",
    "wof:placetype":"locality"
},
  "geometry": {"coordinates":[45.83083,42.77833],"type":"Point"}
}