{
  "type": "Feature",
  "properties": {
    "gn:admin1_code":"77",
    "gn:asciiname":"Saltykovo",
    "gn:country_code":"RU",
    "gn:dem":135,
    "gn:feature_class":"P",
    "gn:feature_code":"PPL",
    "gn:name":"Saltykovo",
    "gn:population":0,
    "gn:timezone":"Europe/Moscow",
    "iso:country":"RU",
    "name:rus_x_preferred":[
        "\u0421\u0430\u043b\u0442\u044b\u043a\u043e\u0432\u043e"
    ],
    "name:und_x_variant":[
        "\u0421\u0430\u043b\u0442\u044b\u043a\u043e\u0432\u043e"
    ],
    "wof:name":"Saltykovo",
    "wof:placetype":"locality"
},
  "geometry": {"coordinates":[37.36667,57.43333000000001],"type":"Point"}
}