{
  "type": "Feature",
  "properties": {
    "gn:admin1_code":"10.0",
    "gn:asciiname":"Chakhov",
    "gn:country_code":"RU",
    "gn:dem":134,
    "gn:feature_class":"P",
    "gn:feature_code":"PPL",
    "gn:name":"Chakhov",
    "gn:population":0,
    "gn:timezone":"Europe/Moscow",
    "iso:country":"RU",
    "name:rus_x_preferred":[
        "\u0427\u0430\u0445\u043e\u0432"
    ],
    "name:und_x_variant":[
        "\u0427\u0430\u0445\u043e\u0432"
    ],
    "wof:name":"Chakhov",
    "wof:placetype":"locality"
},
  "geometry": {"coordinates":[31.9173,52.687],"type":"Point"}
}