{
  "type": "Feature",
  "properties": {
    "gn:admin1_code":"56",
    "gn:asciiname":"Logovaya",
    "gn:country_code":"RU",
    "gn:dem":247,
    "gn:feature_class":"P",
    "gn:feature_code":"PPL",
    "gn:name":"Logovaya",
    "gn:population":0,
    "gn:timezone":"Europe/Moscow",
    "iso:country":"RU",
    "name:rus_x_preferred":[
        "\u041b\u043e\u0433\u043e\u0432\u0430\u044f"
    ],
    "name:und_x_variant":[
        "Gnidovka",
        "Logovaya"
    ],
    "wof:name":"Logovaya",
    "wof:placetype":"locality"
},
  "geometry": {"coordinates":[37.33815,52.94058],"type":"Point"}
}