{
  "type": "Feature",
  "properties": {
    "gn:admin1_code":"76",
    "gn:asciiname":"Konino",
    "gn:country_code":"RU",
    "gn:dem":177,
    "gn:feature_class":"P",
    "gn:feature_code":"PPL",
    "gn:name":"Konino",
    "gn:population":0,
    "gn:timezone":"Europe/Moscow",
    "iso:country":"RU",
    "name:rus_x_preferred":[
        "\u041a\u043e\u043d\u0438\u043d\u043e"
    ],
    "name:und_x_variant":[
        "\u041a\u043e\u043d\u0438\u043d\u043e"
    ],
    "wof:name":"Konino",
    "wof:placetype":"locality"
},
  "geometry": {"coordinates":[37.31186,54.3412],"type":"Point"}
}