{
  "type": "Feature",
  "properties": {
    "gn:admin1_code":"85.0",
    "gn:asciiname":"Fedotevo",
    "gn:country_code":"RU",
    "gn:dem":162,
    "gn:feature_class":"P",
    "gn:feature_code":"PPL",
    "gn:name":"Fedotevo",
    "gn:population":0,
    "gn:timezone":"Europe/Moscow",
    "iso:country":"RU",
    "name:rus_x_preferred":[
        "\u0424\u0435\u0434\u043e\u0442\u0435\u0432\u043e"
    ],
    "wof:name":"Fedotevo",
    "wof:placetype":"locality"
},
  "geometry": {"coordinates":[40.95328,59.12853000000001],"type":"Point"}
}