{
  "type": "Feature",
  "properties": {
    "gn:admin1_code":"88",
    "gn:asciiname":"Gubtsevo",
    "gn:country_code":"RU",
    "gn:dem":130,
    "gn:feature_class":"P",
    "gn:feature_code":"PPL",
    "gn:name":"Gubts\u00ebvo",
    "gn:population":0,
    "gn:timezone":"Europe/Moscow",
    "iso:country":"RU",
    "name:rus_x_preferred":[
        "\u0413\u0443\u0431\u0446\u0451\u0432\u043e"
    ],
    "name:und_x_variant":[
        "Gubts\u00ebvo"
    ],
    "wof:name":"Gubtsevo",
    "wof:placetype":"locality"
},
  "geometry": {"coordinates":[39.71634,57.7132],"type":"Point"}
}