{
  "type": "Feature",
  "properties": {
    "gn:admin1_code":"80",
    "gn:asciiname":"Mazunino",
    "gn:country_code":"RU",
    "gn:dem":73,
    "gn:feature_class":"P",
    "gn:feature_code":"PPL",
    "gn:name":"Mazunino",
    "gn:population":0,
    "gn:timezone":"Europe/Samara",
    "iso:country":"RU",
    "name:eng_x_preferred":[
        "Mazunino"
    ],
    "name:nor_x_preferred":[
        "Mazunino"
    ],
    "name:rus_x_preferred":[
        "\u041c\u0430\u0437\u0443\u043d\u0438\u043d\u043e"
    ],
    "name:und_x_variant":[
        "Masunino",
        "Mazunina"
    ],
    "wof:name":"Mazunino",
    "wof:placetype":"locality"
},
  "geometry": {"coordinates":[54.0032,56.3176],"type":"Point"}
}