{
  "type": "Feature",
  "properties": {
    "gn:admin1_code":"33.0",
    "gn:asciiname":"Chicherino",
    "gn:country_code":"RU",
    "gn:dem":187,
    "gn:feature_class":"P",
    "gn:feature_code":"PPL",
    "gn:name":"Chich\u00ebrino",
    "gn:population":0,
    "gn:timezone":"Europe/Kirov",
    "iso:country":"RU",
    "name:rus_x_preferred":[
        "\u0427\u0438\u0447\u0435\u0440\u0438\u043d\u043e"
    ],
    "name:und_x_variant":[
        "Chich\u00ebrino"
    ],
    "wof:name":"Chicherino",
    "wof:placetype":"locality"
},
  "geometry": {"coordinates":[49.53727,59.0138],"type":"Point"}
}