{
  "type": "Feature",
  "properties": {
    "gn:admin1_code":"60.0",
    "gn:asciiname":"Bryanchaninovo",
    "gn:country_code":"RU",
    "gn:dem":56,
    "gn:feature_class":"P",
    "gn:feature_code":"PPL",
    "gn:name":"Bryanchaninovo",
    "gn:population":0,
    "gn:timezone":"Europe/Moscow",
    "iso:country":"RU",
    "name:rus_x_preferred":[
        "\u0411\u0440\u044f\u043d\u0447\u0430\u043d\u0438\u043d\u043e\u0432\u043e"
    ],
    "name:und_x_variant":[
        "\u0411\u0440\u044f\u043d\u0447\u0430\u043d\u0438\u043d\u043e\u0432\u043e"
    ],
    "wof:name":"Bryanchaninovo",
    "wof:placetype":"locality"
},
  "geometry": {"coordinates":[28.23333,57.26667],"type":"Point"}
}