{
  "type": "Feature",
  "properties": {
    "gn:admin1_code":"41",
    "gn:asciiname":"Verkhne-Ozernaya",
    "gn:cc2":"RU",
    "gn:country_code":"RU",
    "gn:dem":219,
    "gn:feature_class":"P",
    "gn:feature_code":"PPL",
    "gn:name":"Verkhne-Oz\u00ebrnaya",
    "gn:population":0,
    "gn:timezone":"Europe/Moscow",
    "iso:country":"RU",
    "name:und_x_variant":[
        "Novo Ozornoye",
        "Novoye Ozernoye",
        "Verkhne-Oz\u00ebrnaya"
    ],
    "wof:name":"Verkhne-Ozernaya",
    "wof:placetype":"locality"
},
  "geometry": {"coordinates":[36.77665,51.68543],"type":"Point"}
}