{
  "type": "Feature",
  "properties": {
    "gn:admin1_code":"27.0",
    "gn:asciiname":"Apsua",
    "gn:country_code":"RU",
    "gn:dem":426,
    "gn:feature_class":"P",
    "gn:feature_code":"PPL",
    "gn:name":"Apsua",
    "gn:population":0,
    "gn:timezone":"Europe/Moscow",
    "iso:country":"RU",
    "name:nor_x_preferred":[
        "Apsua"
    ],
    "name:rus_x_preferred":[
        "\u0410\u043f\u0441\u0443\u0430"
    ],
    "wof:name":"Apsua",
    "wof:placetype":"locality"
},
  "geometry": {"coordinates":[41.7971,44.4481],"type":"Point"}
}