{
  "type": "Feature",
  "properties": {
    "gn:admin1_code":"45",
    "gn:asciiname":"Saber",
    "gn:country_code":"RU",
    "gn:dem":198,
    "gn:feature_class":"P",
    "gn:feature_code":"PPL",
    "gn:name":"Saber",
    "gn:population":0,
    "gn:timezone":"Europe/Moscow",
    "iso:country":"RU",
    "name:rus_x_preferred":[
        "\u0421\u0430\u0431\u0435\u0440"
    ],
    "name:und_x_variant":[
        "Saber-Muchash",
        "Saber",
        "\u0421\u0430\u0431\u0435\u0440"
    ],
    "wof:name":"Saber",
    "wof:placetype":"locality"
},
  "geometry": {"coordinates":[48.9675,56.83971999999999],"type":"Point"}
}