{
  "type": "Feature",
  "properties": {
    "gn:admin1_code":"60",
    "gn:asciiname":"Lashutino",
    "gn:country_code":"RU",
    "gn:dem":125,
    "gn:feature_class":"P",
    "gn:feature_code":"PPL",
    "gn:name":"Lashutino",
    "gn:population":0,
    "gn:timezone":"Europe/Moscow",
    "iso:country":"RU",
    "name:rus_x_preferred":[
        "\u041b\u0430\u0448\u0443\u0442\u0438\u043d\u043e"
    ],
    "wof:name":"Lashutino",
    "wof:placetype":"locality"
},
  "geometry": {"coordinates":[28.93988,56.55938],"type":"Point"}
}