{
  "type": "Feature",
  "properties": {
    "gn:admin1_code":"13.0",
    "gn:asciiname":"Metallurgicheskiy",
    "gn:country_code":"RU",
    "gn:dem":245,
    "gn:feature_class":"P",
    "gn:feature_code":"PPL",
    "gn:name":"Metallurgicheskiy",
    "gn:population":0,
    "gn:timezone":"Asia/Yekaterinburg",
    "iso:country":"RU",
    "name:rus_x_preferred":[
        "\u041c\u0435\u0442\u0430\u043b\u043b\u0443\u0440\u0433\u0438\u0447\u0435\u0441\u043a\u0438\u0439"
    ],
    "wof:name":"Metallurgicheskiy",
    "wof:placetype":"locality"
},
  "geometry": {"coordinates":[61.39459,55.2647],"type":"Point"}
}