{
  "type": "Feature",
  "properties": {
    "gn:admin1_code":"85",
    "gn:asciiname":"Gursevo",
    "gn:country_code":"RU",
    "gn:dem":213,
    "gn:feature_class":"P",
    "gn:feature_code":"PPL",
    "gn:name":"Gursevo",
    "gn:population":0,
    "gn:timezone":"Europe/Moscow",
    "iso:country":"RU",
    "name:rus_x_preferred":[
        "\u0413\u0443\u0440\u0441\u0435\u0432\u043e"
    ],
    "name:und_x_variant":[
        "\u0413\u0443\u0440\u0441\u0435\u0432\u043e"
    ],
    "wof:name":"Gursevo",
    "wof:placetype":"locality"
},
  "geometry": {"coordinates":[40.45,58.81667],"type":"Point"}
}