{
  "type": "Feature",
  "properties": {
    "gn:admin1_code":"43",
    "gn:asciiname":"Volotovskiye Ozerki",
    "gn:country_code":"RU",
    "gn:dem":152,
    "gn:feature_class":"P",
    "gn:feature_code":"PPL",
    "gn:name":"Volotovskiye Ozerki",
    "gn:population":0,
    "gn:timezone":"Europe/Moscow",
    "iso:country":"RU",
    "name:rus_x_preferred":[
        "\u0412\u043e\u043b\u043e\u0442\u043e\u0432\u0441\u043a\u0438\u0435 \u041e\u0437\u0435\u0440\u043a\u0438"
    ],
    "name:und_x_variant":[
        "\u0412\u043e\u043b\u043e\u0442\u043e\u0432\u0441\u043a\u0438\u0435 \u041e\u0437\u0435\u0440\u043a\u0438"
    ],
    "wof:name":"Volotovskiye Ozerki",
    "wof:placetype":"locality"
},
  "geometry": {"coordinates":[39.17386,52.89098000000001],"type":"Point"}
}