{
  "type": "Feature",
  "properties": {
    "gn:admin1_code":"86",
    "gn:asciiname":"Nizhniy Ol'shan",
    "gn:country_code":"RU",
    "gn:dem":94,
    "gn:feature_class":"P",
    "gn:feature_code":"PPL",
    "gn:name":"Nizhniy Ol\u2019shan",
    "gn:population":0,
    "gn:timezone":"Europe/Moscow",
    "iso:country":"RU",
    "name:eng_x_preferred":[
        "Nizhniy Ol'shan"
    ],
    "name:nor_x_preferred":[
        "Nizjnij Olsjan"
    ],
    "name:rus_x_preferred":[
        "\u041d\u0438\u0436\u043d\u0438\u0439 \u041e\u043b\u044c\u0448\u0430\u043d"
    ],
    "name:und_x_variant":[
        "Ol\u2019shevka",
        "Nizhnyaya Ol\u2019shan",
        "Nizhnyaya Ol\u2019shevka",
        "Nizhniy Ol\u2019shan"
    ],
    "wof:name":"Nizhniy Ol'shan",
    "wof:placetype":"locality"
},
  "geometry": {"coordinates":[38.9222,50.7575],"type":"Point"}
}