{
  "type": "Feature",
  "properties": {
    "gn:admin1_code":"11",
    "gn:asciiname":"Kiran",
    "gn:country_code":"RU",
    "gn:dem":610,
    "gn:feature_class":"P",
    "gn:feature_code":"PPL",
    "gn:name":"Kiran",
    "gn:population":0,
    "gn:timezone":"Asia/Irkutsk",
    "iso:country":"RU",
    "name:ceb_x_preferred":[
        "Kiran"
    ],
    "name:deu_x_preferred":[
        "Kiran"
    ],
    "name:hin_x_preferred":[
        "\u0915\u093f\u0930\u0923"
    ],
    "name:rus_x_preferred":[
        "\u041a\u0438\u0440\u0430\u043d"
    ],
    "wof:name":"Kiran",
    "wof:placetype":"locality"
},
  "geometry": {"coordinates":[106.71611,50.33806],"type":"Point"}
}