{
  "type": "Feature",
  "properties": {
    "gn:admin1_code":"33",
    "gn:asciiname":"Shmelikha",
    "gn:country_code":"RU",
    "gn:dem":144,
    "gn:feature_class":"P",
    "gn:feature_code":"PPL",
    "gn:name":"Shmelikha",
    "gn:population":0,
    "gn:timezone":"Europe/Kirov",
    "iso:country":"RU",
    "name:eng_x_preferred":[
        "Shmelikha"
    ],
    "name:nor_x_preferred":[
        "Sjmelikha"
    ],
    "name:rus_x_preferred":[
        "\u0428\u043c\u0435\u043b\u0438\u0445\u0430"
    ],
    "name:und_x_variant":[
        "Lashino"
    ],
    "wof:name":"Shmelikha",
    "wof:placetype":"locality"
},
  "geometry": {"coordinates":[49.94527,58.25795],"type":"Point"}
}