{
  "type": "Feature",
  "properties": {
    "gn:admin1_code":"10",
    "gn:asciiname":"Zelenyy Listok",
    "gn:country_code":"RU",
    "gn:dem":204,
    "gn:feature_class":"P",
    "gn:feature_code":"PPL",
    "gn:name":"Zel\u00ebnyy Listok",
    "gn:population":0,
    "gn:timezone":"Europe/Moscow",
    "iso:country":"RU",
    "name:rus_x_preferred":[
        "\u0417\u0435\u043b\u0451\u043d\u044b\u0439 \u041b\u0438\u0441\u0442\u043e\u043a"
    ],
    "name:und_x_variant":[
        "Vodyanka",
        "Zel\u00ebnyy Listok"
    ],
    "wof:name":"Zelenyy Listok",
    "wof:placetype":"locality"
},
  "geometry": {"coordinates":[34.1792,51.9887],"type":"Point"}
}