{
  "type": "Feature",
  "properties": {
    "gn:admin1_code":"17.0",
    "gn:asciiname":"Berikey",
    "gn:country_code":"RU",
    "gn:dem":29,
    "gn:feature_class":"P",
    "gn:feature_code":"PPL",
    "gn:name":"Berikey",
    "gn:population":0,
    "gn:timezone":"Europe/Moscow",
    "iso:country":"RU",
    "name:eng_x_preferred":[
        "Berikey"
    ],
    "name:nor_x_preferred":[
        "Berikej"
    ],
    "name:rus_x_preferred":[
        "\u0411\u0435\u0440\u0438\u043a\u0435\u0439"
    ],
    "name:und_x_variant":[
        "\u0411\u0435\u0440\u0438\u043a\u0435\u0439",
        "Berikey"
    ],
    "wof:name":"Berikey",
    "wof:placetype":"locality"
},
  "geometry": {"coordinates":[48.0606,42.2236],"type":"Point"}
}