{
  "type": "Feature",
  "properties": {
    "gn:admin1_code":"77",
    "gn:asciiname":"Gorka",
    "gn:country_code":"RU",
    "gn:dem":234,
    "gn:feature_class":"P",
    "gn:feature_code":"PPL",
    "gn:name":"Gorka",
    "gn:population":0,
    "gn:timezone":"Europe/Moscow",
    "iso:country":"RU",
    "name:eng_x_preferred":[
        "Gorka"
    ],
    "name:nor_x_preferred":[
        "Gorka"
    ],
    "name:rus_x_preferred":[
        "\u0413\u043e\u0440\u043a\u0430"
    ],
    "name:und_x_variant":[
        "Gorki"
    ],
    "wof:name":"Gorka",
    "wof:placetype":"locality"
},
  "geometry": {"coordinates":[34.5718,57.25114],"type":"Point"}
}