{
  "type": "Feature",
  "properties": {
    "gn:admin1_code":"33",
    "gn:asciiname":"Osinovskaya",
    "gn:country_code":"RU",
    "gn:dem":195,
    "gn:feature_class":"P",
    "gn:feature_code":"PPL",
    "gn:name":"Osinovskaya",
    "gn:population":0,
    "gn:timezone":"Europe/Kirov",
    "iso:country":"RU",
    "name:rus_x_preferred":[
        "\u041e\u0441\u0438\u043d\u043e\u0432\u0441\u043a\u0430\u044f"
    ],
    "name:und_x_variant":[
        "\u041e\u0441\u0438\u043d\u043e\u0432\u0441\u043a\u0430\u044f"
    ],
    "wof:name":"Osinovskaya",
    "wof:placetype":"locality"
},
  "geometry": {"coordinates":[48.43333,59.61666999999999],"type":"Point"}
}