{
  "type": "Feature",
  "properties": {
    "gn:admin1_code":"77",
    "gn:asciiname":"Kochemli",
    "gn:country_code":"RU",
    "gn:dem":184,
    "gn:feature_class":"P",
    "gn:feature_code":"PPL",
    "gn:name":"Kochemli",
    "gn:population":0,
    "gn:timezone":"Europe/Moscow",
    "iso:country":"RU",
    "name:rus_x_preferred":[
        "\u041a\u043e\u0447\u0435\u043c\u043b\u0438"
    ],
    "name:und_x_variant":[
        "Kachemli",
        "Kochemli"
    ],
    "wof:name":"Kochemli",
    "wof:placetype":"locality"
},
  "geometry": {"coordinates":[37.01667,57.41667],"type":"Point"}
}