{
  "type": "Feature",
  "properties": {
    "gn:admin1_code":"69.0",
    "gn:asciiname":"Fedorovskiye",
    "gn:country_code":"RU",
    "gn:dem":221,
    "gn:feature_class":"P",
    "gn:feature_code":"PPL",
    "gn:name":"F\u00ebdorovskiye",
    "gn:population":0,
    "gn:timezone":"Europe/Moscow",
    "iso:country":"RU",
    "name:rus_x_preferred":[
        "\u0424\u0451\u0434\u043e\u0440\u043e\u0432\u0441\u043a\u0438\u0435"
    ],
    "name:und_x_variant":[
        "F\u00ebdorovskiye",
        "\u0424\u0451\u0434\u043e\u0440\u043e\u0432\u0441\u043a\u0438\u0435"
    ],
    "wof:name":"Fedorovskiye",
    "wof:placetype":"locality"
},
  "geometry": {"coordinates":[32.94333,54.80694],"type":"Point"}
}