{
  "type": "Feature",
  "properties": {
    "gn:admin1_code":"33.0",
    "gn:asciiname":"Domrachenki",
    "gn:country_code":"RU",
    "gn:dem":132,
    "gn:feature_class":"P",
    "gn:feature_code":"PPL",
    "gn:name":"Domrachenki",
    "gn:population":0,
    "gn:timezone":"Europe/Kirov",
    "iso:country":"RU",
    "name:rus_x_preferred":[
        "\u0414\u043e\u043c\u0440\u0430\u0447\u0435\u043d\u043a\u0438"
    ],
    "name:und_x_variant":[
        "Domrachevy",
        "Domrachenki",
        "\u0414\u043e\u043c\u0440\u0430\u0447\u0435\u043d\u043a\u0438"
    ],
    "wof:name":"Domrachenki",
    "wof:placetype":"locality"
},
  "geometry": {"coordinates":[49.42968,58.74768],"type":"Point"}
}