{
  "type": "Feature",
  "properties": {
    "gn:admin1_code":"83",
    "gn:asciiname":"Vorogovo",
    "gn:country_code":"RU",
    "gn:dem":169,
    "gn:feature_class":"P",
    "gn:feature_code":"PPL",
    "gn:name":"Vorogovo",
    "gn:population":0,
    "gn:timezone":"Europe/Moscow",
    "iso:country":"RU",
    "name:rus_x_preferred":[
        "\u0412\u043e\u0440\u043e\u0433\u043e\u0432\u043e"
    ],
    "wof:name":"Vorogovo",
    "wof:placetype":"locality"
},
  "geometry": {"coordinates":[39.36626,56.6403],"type":"Point"}
}