{
  "type": "Feature",
  "properties": {
    "gn:admin1_code":"23",
    "gn:asciiname":"Vishnevoye",
    "gn:country_code":"RU",
    "gn:dem":17,
    "gn:feature_class":"P",
    "gn:feature_code":"PPL",
    "gn:name":"Vishn\u00ebvoye",
    "gn:population":0,
    "gn:timezone":"Europe/Kaliningrad",
    "iso:country":"RU",
    "name:und_x_variant":[
        "Kapkeim",
        "Vishn\u00ebvoye"
    ],
    "wof:name":"Vishnevoye",
    "wof:placetype":"locality"
},
  "geometry": {"coordinates":[20.9059,54.63373000000001],"type":"Point"}
}