{
  "type": "Feature",
  "properties": {
    "gn:admin1_code":"47",
    "gn:asciiname":"Lidino",
    "gn:country_code":"RU",
    "gn:dem":130,
    "gn:feature_class":"P",
    "gn:feature_code":"PPL",
    "gn:name":"Lidino",
    "gn:population":0,
    "gn:timezone":"Europe/Moscow",
    "iso:country":"RU",
    "name:rus_x_preferred":[
        "\u041b\u0438\u0434\u0438\u043d\u043e"
    ],
    "name:und_x_variant":[
        "Lidinka",
        "Lidino",
        "\u041b\u0438\u0434\u0438\u043d\u043e"
    ],
    "wof:name":"Lidino",
    "wof:placetype":"locality"
},
  "geometry": {"coordinates":[38.7534,55.43878],"type":"Point"}
}