{
  "type": "Feature",
  "properties": {
    "gn:admin1_code":"73",
    "gn:asciiname":"Lyutkino",
    "gn:country_code":"RU",
    "gn:dem":110,
    "gn:feature_class":"P",
    "gn:feature_code":"PPL",
    "gn:name":"Lyutkino",
    "gn:population":0,
    "gn:timezone":"Europe/Moscow",
    "iso:country":"RU",
    "name:eng_x_preferred":[
        "Lyutkino"
    ],
    "name:nor_x_preferred":[
        "Ljutkino"
    ],
    "name:rus_x_preferred":[
        "\u041b\u044e\u0442\u043a\u0438\u043d\u043e"
    ],
    "name:und_x_variant":[
        "Lyuskino",
        "Lyuzkino",
        "Lyutkino"
    ],
    "wof:name":"Lyutkino",
    "wof:placetype":"locality"
},
  "geometry": {"coordinates":[49.59357,55.64733],"type":"Point"}
}