{
  "type": "Feature",
  "properties": {
    "gn:admin1_code":"69",
    "gn:asciiname":"Pnevo",
    "gn:country_code":"RU",
    "gn:dem":196,
    "gn:feature_class":"P",
    "gn:feature_code":"PPL",
    "gn:name":"Pn\u00ebvo",
    "gn:population":0,
    "gn:timezone":"Europe/Moscow",
    "iso:country":"RU",
    "name:rus_x_preferred":[
        "\u041f\u043d\u0451\u0432\u043e"
    ],
    "name:und_x_variant":[
        "Pn\u00ebvo"
    ],
    "wof:name":"Pnevo",
    "wof:placetype":"locality"
},
  "geometry": {"coordinates":[32.64587,54.8921],"type":"Point"}
}