{
  "type": "Feature",
  "properties": {
    "gn:admin1_code":"10",
    "gn:asciiname":"Biryukoy",
    "gn:country_code":"RU",
    "gn:dem":167,
    "gn:feature_class":"P",
    "gn:feature_code":"PPL",
    "gn:name":"Biryukoy",
    "gn:population":0,
    "gn:timezone":"Europe/Moscow",
    "iso:country":"RU",
    "name:rus_x_preferred":[
        "\u0411\u0438\u0440\u044e\u043a\u043e\u0439"
    ],
    "wof:name":"Biryukoy",
    "wof:placetype":"locality"
},
  "geometry": {"coordinates":[32.50444,52.8575],"type":"Point"}
}