{
  "type": "Feature",
  "properties": {
    "gn:admin1_code":"92",
    "gn:asciiname":"Utka",
    "gn:country_code":"RU",
    "gn:dem":37,
    "gn:feature_class":"P",
    "gn:feature_code":"PPL",
    "gn:name":"Utka",
    "gn:population":0,
    "gn:timezone":"Asia/Kamchatka",
    "iso:country":"RU",
    "name:eng_x_preferred":[
        "Utka"
    ],
    "name:nor_x_preferred":[
        "Utka"
    ],
    "name:rus_x_preferred":[
        "\u0423\u0442\u043a\u0430"
    ],
    "wof:name":"Utka",
    "wof:placetype":"locality"
},
  "geometry": {"coordinates":[156.36160000000001,53.14136],"type":"Point"}
}