{
  "type": "Feature",
  "properties": {
    "gn:admin1_code":"47",
    "gn:asciiname":"Kalininskoye",
    "gn:country_code":"RU",
    "gn:dem":169,
    "gn:feature_class":"P",
    "gn:feature_code":"PPL",
    "gn:name":"Kalininskoye",
    "gn:population":0,
    "gn:timezone":"Europe/Moscow",
    "iso:country":"RU",
    "name:rus_x_preferred":[
        "\u041a\u0430\u043b\u0438\u043d\u0438\u043d\u0441\u043a\u043e\u0435"
    ],
    "name:und_x_variant":[
        "\u041a\u0430\u043b\u0438\u043d\u0438\u043d\u0441\u043a\u043e\u0435"
    ],
    "wof:name":"Kalininskoye",
    "wof:placetype":"locality"
},
  "geometry": {"coordinates":[38.88333,54.43333000000001],"type":"Point"}
}