{
  "type": "Feature",
  "properties": {
    "gn:admin1_code":"52",
    "gn:asciiname":"Ivankovo",
    "gn:country_code":"RU",
    "gn:dem":40,
    "gn:feature_class":"P",
    "gn:feature_code":"PPL",
    "gn:name":"Ivankovo",
    "gn:population":0,
    "gn:timezone":"Europe/Moscow",
    "iso:country":"RU",
    "name:rus_x_preferred":[
        "\u0418\u0432\u0430\u043d\u043a\u043e\u0432\u043e"
    ],
    "name:und_x_variant":[
        "\u0418\u0432\u0430\u043d\u043a\u043e\u0432\u043e"
    ],
    "wof:name":"Ivankovo",
    "wof:placetype":"locality"
},
  "geometry": {"coordinates":[31.68333,58.63333000000001],"type":"Point"}
}