{
  "type": "Feature",
  "properties": {
    "gn:admin1_code":"37",
    "gn:asciiname":"Nevzorikha",
    "gn:country_code":"RU",
    "gn:dem":127,
    "gn:feature_class":"P",
    "gn:feature_code":"PPL",
    "gn:name":"Nevzorikha",
    "gn:population":0,
    "gn:timezone":"Europe/Moscow",
    "iso:country":"RU",
    "name:rus_x_preferred":[
        "\u041d\u0435\u0432\u0437\u043e\u0440\u0438\u0445\u0430"
    ],
    "name:und_x_variant":[
        "\u041d\u0435\u0432\u0437\u043e\u0440\u0438\u0445\u0430"
    ],
    "wof:name":"Nevzorikha",
    "wof:placetype":"locality"
},
  "geometry": {"coordinates":[45.4852,58.697],"type":"Point"}
}