{
  "type": "Feature",
  "properties": {
    "gn:admin1_code":"90.0",
    "gn:asciiname":"Savenki",
    "gn:country_code":"RU",
    "gn:dem":133,
    "gn:feature_class":"P",
    "gn:feature_code":"PPL",
    "gn:name":"Savenki",
    "gn:population":0,
    "gn:timezone":"Asia/Yekaterinburg",
    "iso:country":"RU",
    "name:che_x_preferred":[
        "\u0421\u0430\u0432\u0435\u043d\u043a\u0438"
    ],
    "name:rus_x_preferred":[
        "\u0421\u0430\u0432\u0435\u043d\u043a\u0438"
    ],
    "wof:name":"Savenki",
    "wof:placetype":"locality"
},
  "geometry": {"coordinates":[55.7836,58.6463],"type":"Point"}
}