{
  "type": "Feature",
  "properties": {
    "gn:admin1_code":"55",
    "gn:asciiname":"Kyzylbulak",
    "gn:country_code":"RU",
    "gn:dem":121,
    "gn:feature_class":"P",
    "gn:feature_code":"PPL",
    "gn:name":"Kyzylbulak",
    "gn:population":0,
    "gn:timezone":"Asia/Yekaterinburg",
    "iso:country":"RU",
    "name:eng_x_preferred":[
        "Kyzylbulak"
    ],
    "name:nor_x_preferred":[
        "Kyzylbulak"
    ],
    "name:rus_x_preferred":[
        "\u041a\u044b\u0437\u044b\u043b\u0431\u0443\u043b\u0430\u043a"
    ],
    "name:und_x_variant":[
        "Kzyl-Bulak",
        "Kyzylbulak"
    ],
    "wof:name":"Kyzylbulak",
    "wof:placetype":"locality"
},
  "geometry": {"coordinates":[55.36963000000001,51.05225],"type":"Point"}
}