{
  "type": "Feature",
  "properties": {
    "gn:admin1_code":"24",
    "gn:asciiname":"Kordon",
    "gn:country_code":"RU",
    "gn:dem":50,
    "gn:feature_class":"P",
    "gn:feature_code":"PPL",
    "gn:name":"Kordon",
    "gn:population":0,
    "gn:timezone":"Europe/Moscow",
    "iso:country":"RU",
    "name:rus_x_preferred":[
        "\u041a\u043e\u0440\u0434\u043e\u043d"
    ],
    "name:und_x_variant":[
        "\u041a\u043e\u0440\u0434\u043e\u043d"
    ],
    "wof:name":"Kordon",
    "wof:placetype":"locality"
},
  "geometry": {"coordinates":[44.19972,45.78694],"type":"Point"}
}