{
  "type": "Feature",
  "properties": {
    "gn:admin1_code":"86.0",
    "gn:asciiname":"Glinkino",
    "gn:country_code":"RU",
    "gn:dem":93,
    "gn:feature_class":"P",
    "gn:feature_code":"PPL",
    "gn:name":"Glinkino",
    "gn:population":0,
    "gn:timezone":"Europe/Volgograd",
    "iso:country":"RU",
    "name:rus_x_preferred":[
        "\u0413\u043b\u0438\u043d\u043a\u0438\u043d\u043e"
    ],
    "name:und_x_variant":[
        "Pos\u00eblok Glinki",
        "Glinki",
        "Glinkino"
    ],
    "wof:name":"Glinkino",
    "wof:placetype":"locality"
},
  "geometry": {"coordinates":[41.8121,51.1132],"type":"Point"}
}