{
  "type": "Feature",
  "properties": {
    "gn:admin1_code":"53",
    "gn:asciiname":"Tyngiza",
    "gn:country_code":"RU",
    "gn:dem":120,
    "gn:feature_class":"P",
    "gn:feature_code":"PPL",
    "gn:name":"Tyngiza",
    "gn:population":0,
    "gn:timezone":"Asia/Novosibirsk",
    "iso:country":"RU",
    "name:eng_x_preferred":[
        "Tyngiza"
    ],
    "name:nor_x_preferred":[
        "Tyngiza"
    ],
    "name:rus_x_preferred":[
        "\u0422\u044b\u043d\u0433\u0438\u0437\u0430"
    ],
    "wof:name":"Tyngiza",
    "wof:placetype":"locality"
},
  "geometry": {"coordinates":[76.71925,56.91981],"type":"Point"}
}