{
  "type": "Feature",
  "properties": {
    "gn:admin1_code":"85",
    "gn:asciiname":"Bobrovskoye",
    "gn:country_code":"RU",
    "gn:dem":150,
    "gn:feature_class":"P",
    "gn:feature_code":"PPL",
    "gn:name":"Bobrovskoye",
    "gn:population":0,
    "gn:timezone":"Europe/Moscow",
    "iso:country":"RU",
    "name:rus_x_preferred":[
        "\u0411\u043e\u0431\u0440\u043e\u0432\u0441\u043a\u043e\u0435"
    ],
    "wof:name":"Bobrovskoye",
    "wof:placetype":"locality"
},
  "geometry": {"coordinates":[39.8668,59.8073],"type":"Point"}
}