{
  "type": "Feature",
  "properties": {
    "gn:admin1_code":"16.0",
    "gn:asciiname":"Bogatyrevo",
    "gn:country_code":"RU",
    "gn:dem":91,
    "gn:feature_class":"P",
    "gn:feature_code":"PPL",
    "gn:name":"Bogatyr\u00ebvo",
    "gn:population":0,
    "gn:timezone":"Europe/Moscow",
    "iso:country":"RU",
    "name:rus_x_preferred":[
        "\u0411\u043e\u0433\u0430\u0442\u044b\u0440\u0451\u0432\u043e"
    ],
    "name:und_x_variant":[
        "Bogatyr\u00ebvo",
        "\u0411\u043e\u0433\u0430\u0442\u044b\u0440\u0451\u0432\u043e"
    ],
    "wof:name":"Bogatyrevo",
    "wof:placetype":"locality"
},
  "geometry": {"coordinates":[47.28878,55.85326],"type":"Point"}
}