{
  "type": "Feature",
  "properties": {
    "gn:admin1_code":"55",
    "gn:asciiname":"Kutluyevo",
    "gn:country_code":"RU",
    "gn:dem":159,
    "gn:feature_class":"P",
    "gn:feature_code":"PPL",
    "gn:name":"Kutluyevo",
    "gn:population":0,
    "gn:timezone":"Asia/Yekaterinburg",
    "iso:country":"RU",
    "name:rus_x_preferred":[
        "\u041a\u0443\u0442\u043b\u0443\u0435\u0432\u043e"
    ],
    "name:und_x_variant":[
        "\u041a\u0443\u0442\u043b\u0443\u0435\u0432\u043e",
        "Kitluyevo"
    ],
    "wof:name":"Kutluyevo",
    "wof:placetype":"locality"
},
  "geometry": {"coordinates":[53.25,53.51667],"type":"Point"}
}