{
  "type": "Feature",
  "properties": {
    "gn:admin1_code":"45",
    "gn:asciiname":"Yushkovo",
    "gn:country_code":"RU",
    "gn:dem":138,
    "gn:feature_class":"P",
    "gn:feature_code":"PPL",
    "gn:name":"Yushkovo",
    "gn:population":0,
    "gn:timezone":"Europe/Moscow",
    "iso:country":"RU",
    "name:rus_x_preferred":[
        "\u042e\u0448\u043a\u043e\u0432\u043e"
    ],
    "wof:name":"Yushkovo",
    "wof:placetype":"locality"
},
  "geometry": {"coordinates":[48.08583,56.7125],"type":"Point"}
}