{
  "type": "Feature",
  "properties": {
    "gn:admin1_code":"69",
    "gn:asciiname":"Sorokoletovo",
    "gn:country_code":"RU",
    "gn:dem":226,
    "gn:feature_class":"P",
    "gn:feature_code":"PPL",
    "gn:name":"Sorokoletovo",
    "gn:population":0,
    "gn:timezone":"Europe/Moscow",
    "iso:country":"RU",
    "name:und_x_variant":[
        "Sorokaletovo"
    ],
    "wof:name":"Sorokoletovo",
    "wof:placetype":"locality"
},
  "geometry": {"coordinates":[34.45593,55.47482],"type":"Point"}
}