{
  "type": "Feature",
  "properties": {
    "gn:admin1_code":"86",
    "gn:asciiname":"Sotnitskaya",
    "gn:country_code":"RU",
    "gn:dem":94,
    "gn:feature_class":"P",
    "gn:feature_code":"PPL",
    "gn:name":"Sotnitskaya",
    "gn:population":0,
    "gn:timezone":"Europe/Moscow",
    "iso:country":"RU",
    "name:rus_x_preferred":[
        "\u0421\u043e\u0442\u043d\u0438\u0446\u043a\u0430\u044f"
    ],
    "name:und_x_variant":[
        "Sotnitskiy",
        "Sotnitskoye",
        "Sotnitskaya"
    ],
    "wof:name":"Sotnitskaya",
    "wof:placetype":"locality"
},
  "geometry": {"coordinates":[39.62063,50.28721],"type":"Point"}
}