{
  "type": "Feature",
  "properties": {
    "gn:admin1_code":"51.0",
    "gn:asciiname":"Onucheno",
    "gn:country_code":"RU",
    "gn:dem":190,
    "gn:feature_class":"P",
    "gn:feature_code":"PPL",
    "gn:name":"Onucheno",
    "gn:population":0,
    "gn:timezone":"Europe/Moscow",
    "iso:country":"RU",
    "name:rus_x_preferred":[
        "\u041e\u043d\u0443\u0447\u0435\u043d\u043e"
    ],
    "name:und_x_variant":[
        "\u041e\u043d\u0443\u0447\u0435\u043d\u043e"
    ],
    "wof:name":"Onucheno",
    "wof:placetype":"locality"
},
  "geometry": {"coordinates":[43.54233,55.2123],"type":"Point"}
}