{
  "type": "Feature",
  "properties": {
    "gn:admin1_code":"8.0",
    "gn:asciiname":"Shartymka",
    "gn:country_code":"RU",
    "gn:dem":429,
    "gn:feature_class":"P",
    "gn:feature_code":"PPL",
    "gn:name":"Shartymka",
    "gn:population":0,
    "gn:timezone":"Asia/Yekaterinburg",
    "iso:country":"RU",
    "name:rus_x_preferred":[
        "\u0428\u0430\u0440\u0442\u044b\u043c\u043a\u0430"
    ],
    "wof:name":"Shartymka",
    "wof:placetype":"locality"
},
  "geometry": {"coordinates":[59.6023,54.495],"type":"Point"}
}