{
  "type": "Feature",
  "properties": {
    "gn:admin1_code":"53",
    "gn:asciiname":"Novolyubomirovka",
    "gn:cc2":"RU",
    "gn:country_code":"RU",
    "gn:dem":110,
    "gn:feature_class":"P",
    "gn:feature_code":"PPL",
    "gn:name":"Novolyubomirovka",
    "gn:population":0,
    "gn:timezone":"Asia/Novosibirsk",
    "iso:country":"RU",
    "name:rus_x_preferred":[
        "\u041d\u043e\u0432\u043e\u043b\u044e\u0431\u043e\u043c\u0438\u0440\u043e\u0432\u043a\u0430"
    ],
    "name:und_x_variant":[
        "Novaya Lyubomirovka",
        "Novolyubomirovka",
        "\u041d\u043e\u0432\u043e\u043b\u044e\u0431\u043e\u043c\u0438\u0440\u043e\u0432\u043a\u0430"
    ],
    "wof:name":"Novolyubomirovka",
    "wof:placetype":"locality"
},
  "geometry": {"coordinates":[77.40000000000001,56.15],"type":"Point"}
}