{
  "type": "Feature",
  "properties": {
    "gn:admin1_code":"77",
    "gn:asciiname":"Lesnichestvo Yam",
    "gn:country_code":"RU",
    "gn:dem":236,
    "gn:feature_class":"P",
    "gn:feature_code":"PPL",
    "gn:name":"Lesnichestvo Yam",
    "gn:population":0,
    "gn:timezone":"Europe/Moscow",
    "iso:country":"RU",
    "name:rus_x_preferred":[
        "\u041b\u0435\u0441\u043d\u0438\u0447\u0435\u0441\u0442\u0432\u043e \u042f\u043c"
    ],
    "name:und_x_variant":[
        "Yam",
        "Lesnichestvo Yam"
    ],
    "wof:name":"Lesnichestvo Yam",
    "wof:placetype":"locality"
},
  "geometry": {"coordinates":[32.07850999999999,56.88896999999999],"type":"Point"}
}