{
  "type": "Feature",
  "properties": {
    "gn:admin1_code":"42",
    "gn:asciiname":"Sotovo",
    "gn:country_code":"RU",
    "gn:dem":57,
    "gn:feature_class":"P",
    "gn:feature_code":"PPL",
    "gn:name":"Sotovo",
    "gn:population":0,
    "gn:timezone":"Europe/Moscow",
    "iso:country":"RU",
    "name:rus_x_preferred":[
        "\u0421\u043e\u0442\u043e\u0432\u043e"
    ],
    "wof:name":"Sotovo",
    "wof:placetype":"locality"
},
  "geometry": {"coordinates":[31.87962000000001,59.71912],"type":"Point"}
}