{
  "type": "Feature",
  "properties": {
    "gn:admin1_code":"76",
    "gn:asciiname":"Klyuchi Dubrava",
    "gn:country_code":"RU",
    "gn:dem":219,
    "gn:feature_class":"P",
    "gn:feature_code":"PPL",
    "gn:name":"Klyuchi Dubrava",
    "gn:population":0,
    "gn:timezone":"Europe/Moscow",
    "iso:country":"RU",
    "name:rus_x_preferred":[
        "\u041a\u043b\u044e\u0447\u0438 \u0414\u0443\u0431\u0440\u0430\u0432\u0430"
    ],
    "wof:name":"Klyuchi Dubrava",
    "wof:placetype":"locality"
},
  "geometry": {"coordinates":[37.30778,53.76971999999999],"type":"Point"}
}