{
  "type": "Feature",
  "properties": {
    "gn:admin1_code":"41",
    "gn:asciiname":"Marfinskiye Vyselki",
    "gn:country_code":"RU",
    "gn:dem":218,
    "gn:feature_class":"P",
    "gn:feature_code":"PPL",
    "gn:name":"Marfinskiye Vyselki",
    "gn:population":0,
    "gn:timezone":"Europe/Moscow",
    "iso:country":"RU",
    "name:rus_x_preferred":[
        "\u041c\u0430\u0440\u0444\u0438\u043d\u0441\u043a\u0438\u0435 \u0412\u044b\u0441\u0435\u043b\u043a\u0438"
    ],
    "wof:name":"Marfinskiye Vyselki",
    "wof:placetype":"locality"
},
  "geometry": {"coordinates":[36.5518,52.1943],"type":"Point"}
}