{
  "type": "Feature",
  "properties": {
    "gn:admin1_code":"13",
    "gn:asciiname":"Volkova",
    "gn:country_code":"RU",
    "gn:dem":437,
    "gn:feature_class":"P",
    "gn:feature_code":"PPL",
    "gn:name":"Volkova",
    "gn:population":0,
    "gn:timezone":"Asia/Yekaterinburg",
    "iso:country":"RU",
    "name:rus_x_preferred":[
        "\u0412\u043e\u043b\u043a\u043e\u0432\u0430"
    ],
    "wof:name":"Volkova",
    "wof:placetype":"locality"
},
  "geometry": {"coordinates":[59.481,55.6878],"type":"Point"}
}