{
  "type": "Feature",
  "properties": {
    "gn:admin1_code":"52",
    "gn:asciiname":"Vyachkovo",
    "gn:country_code":"RU",
    "gn:dem":59,
    "gn:feature_class":"P",
    "gn:feature_code":"PPL",
    "gn:name":"Vyachkovo",
    "gn:population":0,
    "gn:timezone":"Europe/Moscow",
    "iso:country":"RU",
    "name:rus_x_preferred":[
        "\u0412\u044f\u0447\u043a\u043e\u0432\u043e"
    ],
    "wof:name":"Vyachkovo",
    "wof:placetype":"locality"
},
  "geometry": {"coordinates":[31.027,57.9236],"type":"Point"}
}