{
  "type": "Feature",
  "properties": {
    "gn:admin1_code":"43",
    "gn:asciiname":"Kotleyevka",
    "gn:country_code":"RU",
    "gn:dem":176,
    "gn:feature_class":"P",
    "gn:feature_code":"PPL",
    "gn:name":"Kotleyevka",
    "gn:population":0,
    "gn:timezone":"Europe/Moscow",
    "iso:country":"RU",
    "name:rus_x_preferred":[
        "\u041a\u043e\u0442\u043b\u0435\u0435\u0432\u043a\u0430"
    ],
    "name:und_x_variant":[
        "Alennaya",
        "Kotleyevka",
        "\u041a\u043e\u0442\u043b\u0435\u0435\u0432\u043a\u0430",
        "Kotleyeva"
    ],
    "wof:name":"Kotleyevka",
    "wof:placetype":"locality"
},
  "geometry": {"coordinates":[38.72849,52.24003],"type":"Point"}
}