{
  "type": "Feature",
  "properties": {
    "gn:admin1_code":"6",
    "gn:asciiname":"Oseredok",
    "gn:country_code":"RU",
    "gn:dem":3,
    "gn:feature_class":"P",
    "gn:feature_code":"PPL",
    "gn:name":"Oseredok",
    "gn:population":0,
    "gn:timezone":"Europe/Moscow",
    "iso:country":"RU",
    "name:rus_x_preferred":[
        "\u041e\u0441\u0435\u0440\u0435\u0434\u043e\u043a"
    ],
    "name:und_x_variant":[
        "Oseredskaya",
        "Oseredok"
    ],
    "wof:name":"Oseredok",
    "wof:placetype":"locality"
},
  "geometry": {"coordinates":[41.5298,63.8146],"type":"Point"}
}