{
  "type": "Feature",
  "properties": {
    "gn:admin1_code":"44",
    "gn:asciiname":"Akhaveym",
    "gn:country_code":"RU",
    "gn:dem":88,
    "gn:feature_class":"P",
    "gn:feature_code":"PPL",
    "gn:name":"Akhaveym",
    "gn:population":0,
    "gn:timezone":"Asia/Magadan",
    "iso:country":"RU",
    "name:eng_x_preferred":[
        "Akhaveym"
    ],
    "name:rus_x_preferred":[
        "\u0410\u0445\u0430\u0432\u0435\u0435\u043c"
    ],
    "name:rus_x_variant":[
        "\u0410\u0445\u0430\u0432\u0435\u0439\u043c"
    ],
    "name:und_x_variant":[
        "Akhaveyem"
    ],
    "wof:name":"Akhaveym",
    "wof:placetype":"locality"
},
  "geometry": {"coordinates":[160.48226,62.49914],"type":"Point"}
}