{
  "type": "Feature",
  "properties": {
    "gn:country":"RU",
    "gn:fcode":"PPL",
    "gn:population":430,
    "iso:country":"RU",
    "name:ceb_x_preferred":[
        "Tyungur"
    ],
    "name:che_x_preferred":[
        "\u0422\u044e\u043d\u0433\u0443\u0440"
    ],
    "name:eng_x_preferred":[
        "Tyungur"
    ],
    "name:hye_x_preferred":[
        "\u054f\u0575\u0578\u0582\u0576\u0563\u0578\u0582\u0580"
    ],
    "name:nor_x_preferred":[
        "Tjungur"
    ],
    "name:rus_x_preferred":[
        "\u0422\u044e\u043d\u0433\u0443\u0440"
    ],
    "name:tat_x_preferred":[
        "\u0422\u044e\u043d\u0433\u0443\u0440"
    ],
    "name:ukr_x_preferred":[
        "\u0422\u044e\u043d\u0433\u0443\u0440"
    ],
    "qs:name":"Tyungur",
    "qs:name_adm0":"Russia",
    "qs:name_adm1":"Altai Republic",
    "qs:photos_9k":1,
    "qs:photos_9r":3,
    "qs:photos_all":82,
    "qs:photos_sr":0,
    "qs:placetype":"Town",
    "qs:pop_sr":"2",
    "wof:name":"Tyungur",
    "wof:placetype":"locality",
    "wof:population":430
},
  "geometry": {"coordinates":[86.31605,50.16126],"type":"Point"}
}