{
  "type": "Feature",
  "properties": {
    "gn:admin1_code":"41",
    "gn:asciiname":"Sukmanovka",
    "gn:country_code":"RU",
    "gn:dem":196,
    "gn:feature_class":"P",
    "gn:feature_code":"PPL",
    "gn:name":"Sukmanovka",
    "gn:population":0,
    "gn:timezone":"Europe/Moscow",
    "iso:country":"RU",
    "name:rus_x_preferred":[
        "\u0421\u0443\u043a\u043c\u0430\u043d\u043e\u0432\u043a\u0430"
    ],
    "wof:name":"Sukmanovka",
    "wof:placetype":"locality"
},
  "geometry": {"coordinates":[38.2171,51.8341],"type":"Point"}
}