{
  "type": "Feature",
  "properties": {
    "gn:admin1_code":"77",
    "gn:asciiname":"Kozhakino",
    "gn:country_code":"RU",
    "gn:dem":189,
    "gn:feature_class":"P",
    "gn:feature_code":"PPL",
    "gn:name":"Kozhakino",
    "gn:population":0,
    "gn:timezone":"Europe/Moscow",
    "iso:country":"RU",
    "name:rus_x_preferred":[
        "\u041a\u043e\u0436\u0430\u043a\u0438\u043d\u043e"
    ],
    "name:und_x_variant":[
        "\u041a\u043e\u0436\u0430\u043a\u0438\u043d\u043e"
    ],
    "wof:name":"Kozhakino",
    "wof:placetype":"locality"
},
  "geometry": {"coordinates":[34.45702,57.3567],"type":"Point"}
}