{
  "type": "Feature",
  "properties": {
    "gn:country":"RU",
    "gn:fcode":"PPL",
    "gn:population":0,
    "iso:country":"RU",
    "name:bel_x_preferred":[
        "\u041c\u0456\u0440\u043d\u044b"
    ],
    "name:cat_x_preferred":[
        "Mirni"
    ],
    "name:ceb_x_preferred":[
        "\u041c\u0438\u0440\u043d\u044b\u0439"
    ],
    "name:ces_x_preferred":[
        "Mirnyj"
    ],
    "name:deu_x_preferred":[
        "Mirny"
    ],
    "name:epo_x_preferred":[
        "Mirnij"
    ],
    "name:est_x_preferred":[
        "Mirn\u00f5i"
    ],
    "name:fin_x_preferred":[
        "Mirnyi"
    ],
    "name:fra_x_preferred":[
        "Mirny"
    ],
    "name:hun_x_preferred":[
        "Mirnij"
    ],
    "name:hye_x_preferred":[
        "\u0544\u056b\u0580\u0576\u056b"
    ],
    "name:ita_x_preferred":[
        "Mirnyj"
    ],
    "name:kor_x_preferred":[
        "\ubbf8\ub974\ub2c8"
    ],
    "name:lav_x_preferred":[
        "Mirnija"
    ],
    "name:nld_x_preferred":[
        "Mirny"
    ],
    "name:nor_x_preferred":[
        "Mirnyj"
    ],
    "name:pol_x_preferred":[
        "Mirny"
    ],
    "name:rus_x_preferred":[
        "\u041c\u0438\u0440\u043d\u044b\u0439"
    ],
    "name:spa_x_preferred":[
        "Mirni"
    ],
    "name:srp_x_preferred":[
        "\u041c\u0438\u0440\u043d\u0438"
    ],
    "name:tat_x_preferred":[
        "\u041c\u0438\u0440\u043d\u044b\u0439"
    ],
    "name:ukr_x_preferred":[
        "\u041c\u0438\u0440\u043d\u0438\u0439"
    ],
    "name:und_x_variant":[
        "Mirnyy"
    ],
    "name:vep_x_preferred":[
        "Mirnii"
    ],
    "name:zho_x_preferred":[
        "\u7c73\u5c14\u5185"
    ],
    "qs:name":"Mirniy",
    "qs:name_adm0":"Russia",
    "qs:name_adm1":"Moscow Oblast",
    "qs:photos_9k":1,
    "qs:photos_9r":1,
    "qs:photos_all":8,
    "qs:photos_sr":0,
    "qs:placetype":"Town",
    "qs:pop_sr":"0",
    "wd:wordcount":180,
    "wof:name":"Mirniy",
    "wof:placetype":"locality",
    "wof:population":0
},
  "geometry": {"coordinates":[37.95,55.61],"type":"Point"}
}