{
  "type": "Feature",
  "properties": {
    "gn:country":"RU",
    "gn:fcode":"PPL",
    "gn:pop":0,
    "iso:country":"RU",
    "name:rus_x_preferred":[
        "\u041c\u0438\u0440\u043d\u044b\u0439"
    ],
    "name:unk_x_variant":[
        "Mirnyy"
    ],
    "qs:name":"Mirniy",
    "qs:name_adm0":"Russia",
    "qs:name_adm1":"Moscow Oblast",
    "qs:photos_9k":1,
    "qs:photos_9r":1,
    "qs:photos_all":8,
    "qs:photos_sr":0,
    "qs:placetype":"Town",
    "qs:pop_sr":"0",
    "wd:wordcount":180,
    "wof:name":"Mirniy",
    "wof:placetype":"locality",
    "wof:population":0
},
  "geometry": {"coordinates":[37.95,55.61],"type":"Point"}
}