{
  "type": "Feature",
  "properties": {
    "gn:admin1_code":"53",
    "gn:asciiname":"Novoplotnikovo",
    "gn:country_code":"RU",
    "gn:dem":115,
    "gn:feature_class":"P",
    "gn:feature_code":"PPL",
    "gn:name":"Novoplotnikovo",
    "gn:population":0,
    "gn:timezone":"Asia/Novosibirsk",
    "iso:country":"RU",
    "name:eng_x_preferred":[
        "Novoplotnikovo"
    ],
    "name:nor_x_preferred":[
        "Novoplotnikovo"
    ],
    "name:rus_x_preferred":[
        "\u041d\u043e\u0432\u043e\u043f\u043b\u043e\u0442\u043d\u0438\u043a\u043e\u0432\u043e"
    ],
    "name:und_x_variant":[
        "Novo-Plotnikova"
    ],
    "wof:name":"Novoplotnikovo",
    "wof:placetype":"locality"
},
  "geometry": {"coordinates":[78.19598000000001,55.83125],"type":"Point"}
}