{
  "type": "Feature",
  "properties": {
    "gn:admin1_code":"55",
    "gn:asciiname":"Ozernoye",
    "gn:cc2":"RU",
    "gn:country_code":"RU",
    "gn:dem":53,
    "gn:feature_class":"P",
    "gn:feature_code":"PPL",
    "gn:name":"Oz\u00ebrnoye",
    "gn:population":0,
    "gn:timezone":"Asia/Yekaterinburg",
    "iso:country":"RU",
    "name:eng_x_preferred":[
        "Oz\u00ebrnoye"
    ],
    "name:nor_x_preferred":[
        "Ozernoje"
    ],
    "name:rus_x_preferred":[
        "\u041e\u0437\u0435\u0440\u043d\u043e\u0435"
    ],
    "name:rus_x_variant":[
        "\u041e\u0437\u0451\u0440\u043d\u043e\u0435"
    ],
    "name:und_x_variant":[
        "Novo-Ozerni",
        "Ozernyy"
    ],
    "wof:name":"Ozernoye",
    "wof:placetype":"locality"
},
  "geometry": {"coordinates":[51.46667,51.76667],"type":"Point"}
}