{
  "type": "Feature",
  "properties": {
    "gn:admin1_code":"88",
    "gn:asciiname":"Lipovtsy",
    "gn:country_code":"RU",
    "gn:dem":132,
    "gn:feature_class":"P",
    "gn:feature_code":"PPL",
    "gn:name":"Lipovtsy",
    "gn:population":0,
    "gn:timezone":"Europe/Moscow",
    "iso:country":"RU",
    "name:rus_x_preferred":[
        "\u041b\u0438\u043f\u043e\u0432\u0446\u044b"
    ],
    "name:und_x_variant":[
        "\u041b\u0438\u043f\u043e\u0432\u0446\u044b"
    ],
    "wof:name":"Lipovtsy",
    "wof:placetype":"locality"
},
  "geometry": {"coordinates":[38.3385,57.0419],"type":"Point"}
}