{
  "type": "Feature",
  "properties": {
    "gn:admin1_code":"42.0",
    "gn:asciiname":"Karvala",
    "gn:country_code":"RU",
    "gn:dem":124,
    "gn:feature_class":"P",
    "gn:feature_code":"PPL",
    "gn:name":"Karvala",
    "gn:population":0,
    "gn:timezone":"Europe/Moscow",
    "iso:country":"RU",
    "name:rus_x_preferred":[
        "\u041a\u0430\u0440\u0432\u0430\u043b\u0430"
    ],
    "wof:name":"Karvala",
    "wof:placetype":"locality"
},
  "geometry": {"coordinates":[30.16472000000001,59.68666999999999],"type":"Point"}
}