{
  "type": "Feature",
  "properties": {
    "gn:admin1_code":"62",
    "gn:asciiname":"Vozrozhden'ye",
    "gn:country_code":"RU",
    "gn:dem":174,
    "gn:feature_class":"P",
    "gn:feature_code":"PPL",
    "gn:name":"Vozrozhden\u2019ye",
    "gn:population":0,
    "gn:timezone":"Europe/Moscow",
    "iso:country":"RU",
    "name:eng_x_preferred":[
        "Vozrozhdeniye"
    ],
    "name:nor_x_preferred":[
        "Vozrozjdenje"
    ],
    "name:rus_x_preferred":[
        "\u0412\u043e\u0437\u0440\u043e\u0436\u0434\u0435\u043d\u044c\u0435"
    ],
    "name:und_x_variant":[
        "Vozrozhdeniye",
        "Vozrozhden\u2019ye"
    ],
    "wof:name":"Vozrozhden'ye",
    "wof:placetype":"locality"
},
  "geometry": {"coordinates":[39.5243,54.0237],"type":"Point"}
}