{
  "type": "Feature",
  "properties": {
    "gn:admin1_code":"52",
    "gn:asciiname":"Osotno",
    "gn:country_code":"RU",
    "gn:dem":202,
    "gn:feature_class":"P",
    "gn:feature_code":"PPL",
    "gn:name":"Osotno",
    "gn:population":0,
    "gn:timezone":"Europe/Moscow",
    "iso:country":"RU",
    "name:rus_x_preferred":[
        "\u041e\u0441\u043e\u0442\u043d\u043e"
    ],
    "wof:name":"Osotno",
    "wof:placetype":"locality"
},
  "geometry": {"coordinates":[32.89532,57.53227],"type":"Point"}
}