{
  "type": "Feature",
  "properties": {
    "gn:admin1_code":"52.0",
    "gn:asciiname":"Filistovo",
    "gn:country_code":"RU",
    "gn:dem":170,
    "gn:feature_class":"P",
    "gn:feature_code":"PPL",
    "gn:name":"Filistovo",
    "gn:population":0,
    "gn:timezone":"Europe/Moscow",
    "iso:country":"RU",
    "name:rus_x_preferred":[
        "\u0424\u0438\u043b\u0438\u0441\u0442\u043e\u0432\u043e"
    ],
    "wof:name":"Filistovo",
    "wof:placetype":"locality"
},
  "geometry": {"coordinates":[34.31667,58.81667],"type":"Point"}
}