{
  "type": "Feature",
  "properties": {
    "gn:country":"RU",
    "gn:fcode":"PPL",
    "gn:pop":0,
    "iso:country":"RU",
    "name:rus_x_preferred":[
        "\u0421\u0432\u0435\u0440\u0434\u043b\u043e\u0432\u0430"
    ],
    "name:unk_x_variant":[
        "\u0421\u0432\u0435\u0440\u0434\u043b\u043e\u0432\u0430"
    ],
    "qs:name":"Sverdlova",
    "qs:name_adm0":"Russia",
    "qs:name_adm1":"Sverdlovsk Oblast",
    "qs:photos_9r":0,
    "qs:photos_sr":0,
    "qs:placetype":"Town",
    "qs:pop_sr":"0",
    "wof:name":"Sverdlova",
    "wof:placetype":"locality",
    "wof:population":0
},
  "geometry": {"coordinates":[61.4135,57.0546],"type":"Point"}
}