{
  "type": "Feature",
  "properties": {
    "gn:admin1_code":"77",
    "gn:asciiname":"Bol'shaya Petrovka",
    "gn:country_code":"RU",
    "gn:dem":138,
    "gn:feature_class":"P",
    "gn:feature_code":"PPL",
    "gn:name":"Bol\u2019shaya Petrovka",
    "gn:population":0,
    "gn:timezone":"Europe/Moscow",
    "iso:country":"RU",
    "name:rus_x_preferred":[
        "\u0411\u043e\u043b\u044c\u0448\u0430\u044f \u041f\u0435\u0442\u0440\u043e\u0432\u043a\u0430"
    ],
    "name:und_x_variant":[
        "Bol\u2019shaya Petrovka"
    ],
    "wof:name":"Bol'shaya Petrovka",
    "wof:placetype":"locality"
},
  "geometry": {"coordinates":[37.7303,57.6185],"type":"Point"}
}