{
  "type": "Feature",
  "properties": {
    "gn:admin1_code":"65",
    "gn:asciiname":"Novoye Yeremkino",
    "gn:country_code":"RU",
    "gn:dem":148,
    "gn:feature_class":"P",
    "gn:feature_code":"PPL",
    "gn:name":"Novoye Yer\u00ebmkino",
    "gn:population":0,
    "gn:timezone":"Europe/Samara",
    "iso:country":"RU",
    "name:eng_x_preferred":[
        "Novoye Yeremkino"
    ],
    "name:nor_x_preferred":[
        "Novoje Jeremkino"
    ],
    "name:rus_x_preferred":[
        "\u041d\u043e\u0432\u043e\u0435 \u0415\u0440\u0451\u043c\u043a\u0438\u043d\u043e"
    ],
    "name:rus_x_variant":[
        "Novoye Yer\u00ebmkino"
    ],
    "wof:name":"Novoye Yeremkino",
    "wof:placetype":"locality"
},
  "geometry": {"coordinates":[49.8655,53.653],"type":"Point"}
}