{
  "type": "Feature",
  "properties": {
    "gn:admin1_code":"4",
    "gn:asciiname":"Novo-Alekseyevskiy",
    "gn:country_code":"RU",
    "gn:dem":193,
    "gn:feature_class":"P",
    "gn:feature_code":"PPL",
    "gn:name":"Novo-Alekseyevskiy",
    "gn:population":0,
    "gn:timezone":"Asia/Barnaul",
    "iso:country":"RU",
    "name:rus_x_preferred":[
        "\u041d\u043e\u0432\u043e-\u0410\u043b\u0435\u043a\u0441\u0435\u0435\u0432\u0441\u043a\u0438\u0439"
    ],
    "wof:name":"Novo-Alekseyevskiy",
    "wof:placetype":"locality"
},
  "geometry": {"coordinates":[81.63333,51.88333],"type":"Point"}
}