{
  "type": "Feature",
  "properties": {
    "gn:country":"RU",
    "gn:fcode":"PPL",
    "gn:population":4305,
    "iso:country":"RU",
    "name:bel_x_preferred":[
        "\u0414\u0430\u043d\u0441\u043a\u0456"
    ],
    "name:ceb_x_preferred":[
        "\u0414\u043e\u043d\u0441\u043a\u043e\u0439"
    ],
    "name:che_x_preferred":[
        "\u0414\u043e\u043d\u0441\u043a\u043e\u0439"
    ],
    "name:deu_x_preferred":[
        "Donskoi"
    ],
    "name:eng_x_preferred":[
        "Donskoye"
    ],
    "name:fin_x_preferred":[
        "Donskoi"
    ],
    "name:hye_x_preferred":[
        "\u0534\u0578\u0576\u057d\u056f\u0578\u0575"
    ],
    "name:ita_x_preferred":[
        "Donskoj"
    ],
    "name:nob_x_preferred":[
        "Donskoj"
    ],
    "name:nor_x_preferred":[
        "Donskoje"
    ],
    "name:pol_x_preferred":[
        "Donskoj"
    ],
    "name:rus_x_preferred":[
        "\u0414\u043e\u043d\u0441\u043a\u043e\u0435"
    ],
    "name:rus_x_variant":[
        "\u0414\u043e\u043d\u0441\u043a\u043e\u0439"
    ],
    "name:spa_x_preferred":[
        "Donsk\u00f3i"
    ],
    "name:ukr_x_preferred":[
        "\u0414\u043e\u043d\u0441\u044c\u043a\u0438\u0439"
    ],
    "name:und_x_variant":[
        "Donskaya"
    ],
    "qs:name":"Donskoye",
    "qs:name_adm0":"Russia",
    "qs:name_adm1":"Tambov Oblast",
    "qs:photos_9k":1,
    "qs:photos_9r":1,
    "qs:photos_all":1,
    "qs:photos_sr":0,
    "qs:placetype":"Town",
    "qs:pop_sr":"4",
    "wd:wordcount":93,
    "wof:name":"Donskoye",
    "wof:placetype":"locality",
    "wof:population":4305
},
  "geometry": {"coordinates":[41.47759,52.77495],"type":"Point"}
}