{
  "type": "Feature",
  "properties": {
    "gn:country":"RU",
    "gn:fcode":"PPL",
    "gn:pop":4305,
    "iso:country":"RU",
    "name:eng_x_preferred":[
        "Donskoye"
    ],
    "name:nor_x_preferred":[
        "Donskoje"
    ],
    "name:rus_x_preferred":[
        "\u0414\u043e\u043d\u0441\u043a\u043e\u0435"
    ],
    "name:unk_x_variant":[
        "Donskaya"
    ],
    "qs:name":"Donskoye",
    "qs:name_adm0":"Russia",
    "qs:name_adm1":"Tambov Oblast",
    "qs:photos_9k":1,
    "qs:photos_9r":1,
    "qs:photos_all":1,
    "qs:photos_sr":0,
    "qs:placetype":"Town",
    "qs:pop_sr":"4",
    "wd:wordcount":93,
    "wof:name":"Donskoye",
    "wof:placetype":"locality",
    "wof:population":4305
},
  "geometry": {"coordinates":[41.47759,52.77495],"type":"Point"}
}