{
  "type": "Feature",
  "properties": {
    "gn:admin1_code":"69",
    "gn:asciiname":"Samodurovo",
    "gn:country_code":"RU",
    "gn:dem":205,
    "gn:feature_class":"P",
    "gn:feature_code":"PPL",
    "gn:name":"Samodurovo",
    "gn:population":0,
    "gn:timezone":"Europe/Moscow",
    "iso:country":"RU",
    "name:rus_x_preferred":[
        "\u0421\u0430\u043c\u043e\u0434\u0443\u0440\u043e\u0432\u043e"
    ],
    "wof:name":"Samodurovo",
    "wof:placetype":"locality"
},
  "geometry": {"coordinates":[32.10889,55.05389],"type":"Point"}
}