{
  "type": "Feature",
  "properties": {
    "gn:admin1_code":"17",
    "gn:asciiname":"Kutisha",
    "gn:country_code":"RU",
    "gn:dem":1487,
    "gn:feature_class":"P",
    "gn:feature_code":"PPL",
    "gn:name":"Kutisha",
    "gn:population":0,
    "gn:timezone":"Europe/Moscow",
    "iso:country":"RU",
    "name:rus_x_preferred":[
        "\u041a\u0443\u0442\u0438\u0448\u0430"
    ],
    "wof:name":"Kutisha",
    "wof:placetype":"locality"
},
  "geometry": {"coordinates":[47.28055,42.42354],"type":"Point"}
}