{
  "type": "Feature",
  "properties": {
    "gn:admin1_code":"81",
    "gn:asciiname":"Oktyabr'skiy",
    "gn:country_code":"RU",
    "gn:dem":89,
    "gn:feature_class":"P",
    "gn:feature_code":"PPL",
    "gn:name":"Oktyabr\u2019skiy",
    "gn:population":0,
    "gn:timezone":"Europe/Ulyanovsk",
    "iso:country":"RU",
    "name:eng_x_preferred":[
        "Oktyabr'skiy"
    ],
    "name:nor_x_preferred":[
        "Oktjabrskij"
    ],
    "name:rus_x_preferred":[
        "\u041e\u043a\u0442\u044f\u0431\u0440\u044c\u0441\u043a\u0438\u0439"
    ],
    "name:und_x_variant":[
        "Oktyabr\u2019skiy"
    ],
    "wof:name":"Oktyabr'skiy",
    "wof:placetype":"locality"
},
  "geometry": {"coordinates":[48.70531,54.34068000000001],"type":"Point"}
}