{
  "type": "Feature",
  "properties": {
    "gn:admin1_code":"60",
    "gn:asciiname":"Patrekhnovo",
    "gn:country_code":"RU",
    "gn:dem":48,
    "gn:feature_class":"P",
    "gn:feature_code":"PPL",
    "gn:name":"Patrekhnovo",
    "gn:population":0,
    "gn:timezone":"Europe/Moscow",
    "iso:country":"RU",
    "name:che_x_preferred":[
        "\u041f\u043e\u0442\u0440\u0435\u0445\u043d\u043e\u0432\u043e"
    ],
    "name:eng_x_preferred":[
        "Patrekhnovo"
    ],
    "name:nor_x_preferred":[
        "Potrekhnovo"
    ],
    "name:rus_x_preferred":[
        "\u041f\u043e\u0442\u0440\u0435\u0445\u043d\u043e\u0432\u043e"
    ],
    "name:rus_x_variant":[
        "\u041f\u0430\u0442\u0440\u0435\u0445\u043d\u043e\u0432\u043e"
    ],
    "wof:name":"Patrekhnovo",
    "wof:placetype":"locality"
},
  "geometry": {"coordinates":[27.99435,58.96081],"type":"Point"}
}