{
  "type": "Feature",
  "properties": {
    "gn:admin1_code":"55",
    "gn:asciiname":"Varshavka",
    "gn:country_code":"RU",
    "gn:dem":130,
    "gn:feature_class":"P",
    "gn:feature_code":"PPL",
    "gn:name":"Varshavka",
    "gn:population":0,
    "gn:timezone":"Asia/Yekaterinburg",
    "iso:country":"RU",
    "name:eng_x_preferred":[
        "Varshavka"
    ],
    "name:nor_x_preferred":[
        "Varsjavka"
    ],
    "name:rus_x_preferred":[
        "\u0412\u0430\u0440\u0448\u0430\u0432\u043a\u0430"
    ],
    "wof:name":"Varshavka",
    "wof:placetype":"locality"
},
  "geometry": {"coordinates":[53.2734,52.0096],"type":"Point"}
}