{
  "type": "Feature",
  "properties": {
    "gn:admin1_code":"59",
    "gn:asciiname":"Frolovka",
    "gn:country_code":"RU",
    "gn:dem":124,
    "gn:feature_class":"P",
    "gn:feature_code":"PPL",
    "gn:name":"Frolovka",
    "gn:population":0,
    "gn:timezone":"Asia/Vladivostok",
    "iso:country":"RU",
    "name:eng_x_preferred":[
        "Frolovka"
    ],
    "name:nor_x_preferred":[
        "Frolovka"
    ],
    "name:rus_x_preferred":[
        "\u0424\u0440\u043e\u043b\u043e\u0432\u043a\u0430"
    ],
    "name:und_x_variant":[
        "\u0424\u0440\u043e\u043b\u043e\u0432\u043a\u0430",
        "Frolovka"
    ],
    "wof:name":"Frolovka",
    "wof:placetype":"locality"
},
  "geometry": {"coordinates":[133.26778000000002,43.20891],"type":"Point"}
}