{
  "type": "Feature",
  "properties": {
    "gn:admin1_code":"42.0",
    "gn:asciiname":"Bol'shiye Sluditsy",
    "gn:country_code":"RU",
    "gn:dem":52,
    "gn:feature_class":"P",
    "gn:feature_code":"PPL",
    "gn:name":"Bol\u2019shiye Sluditsy",
    "gn:population":13,
    "gn:timezone":"Europe/Moscow",
    "iso:country":"RU",
    "name:eng_x_preferred":[
        "Bol'shiye Sluditsy"
    ],
    "name:fin_x_preferred":[
        "Suuri-Lutsankyl\u00e4"
    ],
    "name:nor_x_preferred":[
        "Sluditsy"
    ],
    "name:rus_x_preferred":[
        "\u0421\u043b\u0443\u0434\u0438\u0446\u044b"
    ],
    "name:rus_x_variant":[
        "\u0411\u043e\u043b\u044c\u0448\u0438\u0435 \u0421\u043b\u0443\u0434\u0438\u0446\u044b"
    ],
    "name:und_x_variant":[
        "Bol\u2019shiye Sluditsy"
    ],
    "wof:name":"Bol'shiye Sluditsy",
    "wof:placetype":"locality",
    "wof:population":13
},
  "geometry": {"coordinates":[30.485,59.29167],"type":"Point"}
}