{
  "type": "Feature",
  "properties": {
    "gn:admin1_code":"85",
    "gn:asciiname":"Veregonets",
    "gn:country_code":"RU",
    "gn:dem":117,
    "gn:feature_class":"P",
    "gn:feature_code":"PPL",
    "gn:name":"Veregonets",
    "gn:population":0,
    "gn:timezone":"Europe/Moscow",
    "iso:country":"RU",
    "name:rus_x_preferred":[
        "\u0412\u0435\u0440\u0435\u0433\u043e\u043d\u0435\u0446"
    ],
    "name:und_x_variant":[
        "Novo-Veregonets",
        "Veregonets"
    ],
    "wof:name":"Veregonets",
    "wof:placetype":"locality"
},
  "geometry": {"coordinates":[37.9291,60.0363],"type":"Point"}
}