{
  "type": "Feature",
  "properties": {
    "gn:admin1_code":"85",
    "gn:asciiname":"Krivodino",
    "gn:country_code":"RU",
    "gn:dem":139,
    "gn:feature_class":"P",
    "gn:feature_code":"PPL",
    "gn:name":"Krivodino",
    "gn:population":0,
    "gn:timezone":"Europe/Moscow",
    "iso:country":"RU",
    "name:rus_x_preferred":[
        "\u041a\u0440\u0438\u0432\u043e\u0434\u0438\u043d\u043e"
    ],
    "name:und_x_variant":[
        "\u041a\u0440\u0438\u0432\u043e\u0434\u0438\u043d\u043e"
    ],
    "wof:name":"Krivodino",
    "wof:placetype":"locality"
},
  "geometry": {"coordinates":[39.96522,58.97016],"type":"Point"}
}