{
  "type": "Feature",
  "properties": {
    "gn:admin1_code":"54",
    "gn:asciiname":"Kolomenka",
    "gn:country_code":"RU",
    "gn:dem":99,
    "gn:feature_class":"P",
    "gn:feature_code":"PPL",
    "gn:name":"Kolomenka",
    "gn:population":0,
    "gn:timezone":"Asia/Omsk",
    "iso:country":"RU",
    "name:eng_x_preferred":[
        "Kolomenka"
    ],
    "name:nor_x_preferred":[
        "Kolomenka"
    ],
    "name:rus_x_preferred":[
        "\u041a\u043e\u043b\u043e\u043c\u0435\u043d\u043a\u0430"
    ],
    "name:und_x_variant":[
        "Kulomzinskiy",
        "Kulomzino"
    ],
    "wof:name":"Kolomenka",
    "wof:placetype":"locality"
},
  "geometry": {"coordinates":[71.83207,56.30132],"type":"Point"}
}