{
  "type": "Feature",
  "properties": {
    "gn:admin1_code":"56",
    "gn:asciiname":"Krivtsovo-Lyubutskoye",
    "gn:country_code":"RU",
    "gn:dem":224,
    "gn:feature_class":"P",
    "gn:feature_code":"PPL",
    "gn:name":"Krivtsovo-Lyubutskoye",
    "gn:population":0,
    "gn:timezone":"Europe/Moscow",
    "iso:country":"RU",
    "name:rus_x_preferred":[
        "\u041a\u0440\u0438\u0432\u0446\u043e\u0432\u043e-\u041b\u044e\u0431\u0443\u0446\u043a\u043e\u0435"
    ],
    "wof:name":"Krivtsovo-Lyubutskoye",
    "wof:placetype":"locality"
},
  "geometry": {"coordinates":[35.7816,52.5753],"type":"Point"}
}