{
  "type": "Feature",
  "properties": {
    "gn:admin1_code":"85",
    "gn:asciiname":"Sen'kino",
    "gn:country_code":"RU",
    "gn:dem":188,
    "gn:feature_class":"P",
    "gn:feature_code":"PPL",
    "gn:name":"Sen\u2019kino",
    "gn:population":0,
    "gn:timezone":"Europe/Moscow",
    "iso:country":"RU",
    "name:rus_x_preferred":[
        "\u0421\u0435\u043d\u044c\u043a\u0438\u043d\u043e"
    ],
    "name:und_x_variant":[
        "Sen\u2019kino",
        "\u0421\u0435\u043d\u044c\u043a\u0438\u043d\u043e"
    ],
    "wof:name":"Sen'kino",
    "wof:placetype":"locality"
},
  "geometry": {"coordinates":[41.01667,59.16667],"type":"Point"}
}