{
  "type": "Feature",
  "properties": {
    "gn:admin1_code":"71",
    "gn:asciiname":"Dubasova",
    "gn:country_code":"RU",
    "gn:dem":213,
    "gn:feature_class":"P",
    "gn:feature_code":"PPL",
    "gn:name":"Dubasova",
    "gn:population":0,
    "gn:timezone":"Asia/Yekaterinburg",
    "iso:country":"RU",
    "name:rus_x_preferred":[
        "\u0414\u0443\u0431\u0430\u0441\u043e\u0432\u0430"
    ],
    "name:und_x_variant":[
        "\u0414\u0443\u0431\u0430\u0441\u043e\u0432\u0430"
    ],
    "wof:name":"Dubasova",
    "wof:placetype":"locality"
},
  "geometry": {"coordinates":[60.59996999999999,57.68622],"type":"Point"}
}