{
  "type": "Feature",
  "properties": {
    "gn:admin1_code":"90.0",
    "gn:asciiname":"Byrma",
    "gn:country_code":"RU",
    "gn:dem":187,
    "gn:feature_class":"P",
    "gn:feature_code":"PPL",
    "gn:name":"Byrma",
    "gn:population":0,
    "gn:timezone":"Asia/Yekaterinburg",
    "iso:country":"RU",
    "name:eng_x_preferred":[
        "Byrma"
    ],
    "name:nor_x_preferred":[
        "Byrma"
    ],
    "name:rus_x_preferred":[
        "\u0411\u044b\u0440\u043c\u0430"
    ],
    "wof:name":"Byrma",
    "wof:placetype":"locality"
},
  "geometry": {"coordinates":[57.6983,57.2124],"type":"Point"}
}