{
  "type": "Feature",
  "properties": {
    "gn:country":"RU",
    "gn:fcode":"PPL",
    "gn:pop":0,
    "iso:country":"RU",
    "name:unk_x_variant":[
        "Syabryanitsy"
    ],
    "qs:name":"Syabrenitsj",
    "qs:name_adm0":"Russia",
    "qs:name_adm1":"Novgorod Oblast",
    "qs:photos":9,
    "qs:photos_1k":2,
    "qs:photos_9k":1,
    "qs:photos_9r":1,
    "qs:photos_all":9,
    "qs:photos_sr":1,
    "qs:placetype":"Town",
    "qs:pop_sr":"0",
    "wof:name":"Syabrenitsj",
    "wof:placetype":"locality",
    "wof:population":0
},
  "geometry": {"coordinates":[31.61667,59.13333],"type":"Point"}
}