{
  "type": "Feature",
  "properties": {
    "gn:admin1_code":"77",
    "gn:asciiname":"Val'no",
    "gn:country_code":"RU",
    "gn:dem":279,
    "gn:feature_class":"P",
    "gn:feature_code":"PPL",
    "gn:name":"Val\u2019no",
    "gn:population":0,
    "gn:timezone":"Europe/Moscow",
    "iso:country":"RU",
    "name:rus_x_preferred":[
        "\u0412a\u043b\u044c\u043d\u043e"
    ],
    "name:und_x_variant":[
        "Val\u2019no"
    ],
    "wof:name":"Val'no",
    "wof:placetype":"locality"
},
  "geometry": {"coordinates":[32.11137,57.10007],"type":"Point"}
}