{
  "type": "Feature",
  "properties": {
    "gn:admin1_code":"8.0",
    "gn:asciiname":"Managaz",
    "gn:country_code":"RU",
    "gn:dem":116,
    "gn:feature_class":"P",
    "gn:feature_code":"PPL",
    "gn:name":"Managaz",
    "gn:population":0,
    "gn:timezone":"Asia/Yekaterinburg",
    "iso:country":"RU",
    "name:rus_x_preferred":[
        "\u041c\u0430\u043d\u0430\u0433\u0430\u0437"
    ],
    "wof:name":"Managaz",
    "wof:placetype":"locality"
},
  "geometry": {"coordinates":[55.9524,56.1469],"type":"Point"}
}