{
  "type": "Feature",
  "properties": {
    "gn:admin1_code":"8",
    "gn:asciiname":"Novaya Derevnya",
    "gn:country_code":"RU",
    "gn:dem":109,
    "gn:feature_class":"P",
    "gn:feature_code":"PPL",
    "gn:name":"Novaya Derevnya",
    "gn:population":0,
    "gn:timezone":"Asia/Yekaterinburg",
    "iso:country":"RU",
    "name:rus_x_preferred":[
        "\u041d\u043e\u0432\u0430\u044f \u0414\u0435\u0440\u0435\u0432\u043d\u044f"
    ],
    "name:und_x_variant":[
        "\u041d\u043e\u0432\u0430\u044f \u0414\u0435\u0440\u0435\u0432\u043d\u044f"
    ],
    "wof:name":"Novaya Derevnya",
    "wof:placetype":"locality"
},
  "geometry": {"coordinates":[56.71666999999999,54.43333000000001],"type":"Point"}
}