{
  "type": "Feature",
  "properties": {
    "gn:admin1_code":"47",
    "gn:asciiname":"Zaozer'ye",
    "gn:country_code":"RU",
    "gn:dem":138,
    "gn:feature_class":"P",
    "gn:feature_code":"PPL",
    "gn:name":"Zaoz\u00ebr\u2019ye",
    "gn:population":0,
    "gn:timezone":"Europe/Moscow",
    "iso:country":"RU",
    "name:und_x_variant":[
        "Rozhdestvo",
        "Zaoz\u00ebr\u2019ye"
    ],
    "wof:name":"Zaozer'ye",
    "wof:placetype":"locality"
},
  "geometry": {"coordinates":[38.65072,55.83476999999999],"type":"Point"}
}