{
  "type": "Feature",
  "properties": {
    "gn:admin1_code":"47",
    "gn:asciiname":"Petrovskoye",
    "gn:country_code":"RU",
    "gn:dem":247,
    "gn:feature_class":"P",
    "gn:feature_code":"PPL",
    "gn:name":"Petrovskoye",
    "gn:population":0,
    "gn:timezone":"Europe/Moscow",
    "iso:country":"RU",
    "name:eng_x_preferred":[
        "Petrovskoye"
    ],
    "name:nor_x_preferred":[
        "Petrovskoje"
    ],
    "name:rus_x_preferred":[
        "\u041f\u0435\u0442\u0440\u043e\u0432\u0441\u043a\u043e\u0435"
    ],
    "name:und_x_variant":[
        "\u041f\u0435\u0442\u0440\u043e\u0432\u0441\u043a\u043e\u0435",
        "Petrovskoye"
    ],
    "wof:name":"Petrovskoye",
    "wof:placetype":"locality"
},
  "geometry": {"coordinates":[36.46667,56.25],"type":"Point"}
}