{
  "type": "Feature",
  "properties": {
    "gn:admin1_code":"83",
    "gn:asciiname":"Krasnyy Ruchey",
    "gn:country_code":"RU",
    "gn:dem":162,
    "gn:feature_class":"P",
    "gn:feature_code":"PPL",
    "gn:name":"Krasnyy Ruchey",
    "gn:population":0,
    "gn:timezone":"Europe/Moscow",
    "iso:country":"RU",
    "name:rus_x_preferred":[
        "\u041a\u0440\u0430\u0441\u043d\u044b\u0439 \u0420\u0443\u0447\u0435\u0439"
    ],
    "wof:name":"Krasnyy Ruchey",
    "wof:placetype":"locality"
},
  "geometry": {"coordinates":[39.3444,56.3753],"type":"Point"}
}