{
  "type": "Feature",
  "properties": {
    "gn:admin1_code":"73",
    "gn:asciiname":"Verkhniy Baylar",
    "gn:country_code":"RU",
    "gn:dem":158,
    "gn:feature_class":"P",
    "gn:feature_code":"PPL",
    "gn:name":"Verkhniy Baylar",
    "gn:population":0,
    "gn:timezone":"Europe/Moscow",
    "iso:country":"RU",
    "name:rus_x_preferred":[
        "\u0412\u0435\u0440\u0445\u043d\u0438\u0439 \u0411\u0430\u0439\u043b\u0430\u0440"
    ],
    "name:und_x_variant":[
        "\u0412\u0435\u0440\u0445\u043d\u0438\u0439 \u0411\u0430\u0439\u043b\u0430\u0440"
    ],
    "wof:name":"Verkhniy Baylar",
    "wof:placetype":"locality"
},
  "geometry": {"coordinates":[52.7393,55.7198],"type":"Point"}
}