{
  "type": "Feature",
  "properties": {
    "gn:admin1_code":"56",
    "gn:asciiname":"Vtoroye Teter'ye",
    "gn:country_code":"RU",
    "gn:dem":228,
    "gn:feature_class":"P",
    "gn:feature_code":"PPL",
    "gn:name":"Vtoroye Teter\u2019y\u00eb",
    "gn:population":0,
    "gn:timezone":"Europe/Moscow",
    "iso:country":"RU",
    "wof:name":"Vtoroye Teter'ye",
    "wof:placetype":"locality"
},
  "geometry": {"coordinates":[36.83333,52.66667],"type":"Point"}
}