{
  "type": "Feature",
  "properties": {
    "gn:admin1_code":"73",
    "gn:asciiname":"Staryy Shimber",
    "gn:country_code":"RU",
    "gn:dem":123,
    "gn:feature_class":"P",
    "gn:feature_code":"PPL",
    "gn:name":"Staryy Shimber",
    "gn:population":0,
    "gn:timezone":"Europe/Moscow",
    "iso:country":"RU",
    "name:rus_x_preferred":[
        "\u0421\u0442\u0430\u0440\u044b\u0439 \u0428\u0438\u043c\u0431\u0435\u0440"
    ],
    "name:und_x_variant":[
        "Staraya Shimbir\u2019",
        "Staryy Shimber"
    ],
    "wof:name":"Staryy Shimber",
    "wof:placetype":"locality"
},
  "geometry": {"coordinates":[49.27361,56.26583],"type":"Point"}
}