{
  "type": "Feature",
  "properties": {
    "gn:admin1_code":"71",
    "gn:asciiname":"Uralets",
    "gn:country_code":"RU",
    "gn:dem":378,
    "gn:feature_class":"P",
    "gn:feature_code":"PPL",
    "gn:name":"Uralets",
    "gn:population":0,
    "gn:timezone":"Asia/Yekaterinburg",
    "iso:country":"RU",
    "name:eng_x_preferred":[
        "Uralets"
    ],
    "name:nor_x_preferred":[
        "Uralets"
    ],
    "name:rus_x_preferred":[
        "\u0423\u0440\u0430\u043b\u0435\u0446"
    ],
    "name:und_x_variant":[
        "Pervomayskiy"
    ],
    "wof:name":"Uralets",
    "wof:placetype":"locality"
},
  "geometry": {"coordinates":[59.6296,57.6382],"type":"Point"}
}