{
  "type": "Feature",
  "properties": {
    "gn:admin1_code":"77",
    "gn:asciiname":"Klyuchek",
    "gn:country_code":"RU",
    "gn:dem":259,
    "gn:feature_class":"P",
    "gn:feature_code":"PPL",
    "gn:name":"Klyuchek",
    "gn:population":0,
    "gn:timezone":"Europe/Moscow",
    "iso:country":"RU",
    "name:rus_x_preferred":[
        "\u041a\u043b\u044e\u0447\u0435\u043a"
    ],
    "name:und_x_variant":[
        "\u041a\u043b\u044e\u0447\u0435\u043a"
    ],
    "wof:name":"Klyuchek",
    "wof:placetype":"locality"
},
  "geometry": {"coordinates":[32.06667,56.78333000000001],"type":"Point"}
}