{
  "type": "Feature",
  "properties": {
    "gn:admin1_code":"84.0",
    "gn:asciiname":"Glubokovskiy",
    "gn:country_code":"RU",
    "gn:dem":50,
    "gn:feature_class":"P",
    "gn:feature_code":"PPL",
    "gn:name":"Glubokovskiy",
    "gn:population":0,
    "gn:timezone":"Europe/Volgograd",
    "iso:country":"RU",
    "name:eng_x_preferred":[
        "Glubokovskiy"
    ],
    "name:nor_x_preferred":[
        "Glubokovskij"
    ],
    "name:rus_x_preferred":[
        "\u0413\u043b\u0443\u0431\u043e\u043a\u043e\u0432\u0441\u043a\u0438\u0439"
    ],
    "wof:name":"Glubokovskiy",
    "wof:placetype":"locality"
},
  "geometry": {"coordinates":[42.9055,49.4633],"type":"Point"}
}