{
  "type": "Feature",
  "properties": {
    "gn:admin1_code":"21.0",
    "gn:asciiname":"Boteyevo",
    "gn:country_code":"RU",
    "gn:dem":127,
    "gn:feature_class":"P",
    "gn:feature_code":"PPL",
    "gn:name":"Boteyevo",
    "gn:population":0,
    "gn:timezone":"Europe/Moscow",
    "iso:country":"RU",
    "name:rus_x_preferred":[
        "\u0411\u043e\u0442\u0435\u0435\u0432\u043e"
    ],
    "wof:name":"Boteyevo",
    "wof:placetype":"locality"
},
  "geometry": {"coordinates":[41.09889,57.27472],"type":"Point"}
}