{
  "type": "Feature",
  "properties": {
    "gn:admin1_code":"60",
    "gn:asciiname":"Beshenkino",
    "gn:country_code":"RU",
    "gn:dem":170,
    "gn:feature_class":"P",
    "gn:feature_code":"PPL",
    "gn:name":"Beshenkino",
    "gn:population":0,
    "gn:timezone":"Europe/Moscow",
    "iso:country":"RU",
    "name:rus_x_preferred":[
        "\u0411\u0435\u0448\u0435\u043d\u043a\u0438\u043d\u043e"
    ],
    "wof:name":"Beshenkino",
    "wof:placetype":"locality"
},
  "geometry": {"coordinates":[29.2453,56.666],"type":"Point"}
}