{
  "type": "Feature",
  "properties": {
    "gn:admin1_code":"84",
    "gn:asciiname":"Zhutovo Pervoye",
    "gn:country_code":"RU",
    "gn:dem":60,
    "gn:feature_class":"P",
    "gn:feature_code":"PPL",
    "gn:name":"Zhutovo Pervoye",
    "gn:population":0,
    "gn:timezone":"Europe/Volgograd",
    "iso:country":"RU",
    "name:und_x_variant":[
        "Khutovo",
        "Zhutov Pervyy",
        "Zhutovo Pervoye"
    ],
    "wof:name":"Zhutovo Pervoye",
    "wof:placetype":"locality"
},
  "geometry": {"coordinates":[43.77262,47.94938],"type":"Point"}
}