{
  "type": "Feature",
  "properties": {
    "gn:admin1_code":"13",
    "gn:asciiname":"Logovoy",
    "gn:country_code":"RU",
    "gn:dem":247,
    "gn:feature_class":"P",
    "gn:feature_code":"PPL",
    "gn:name":"Logovoy",
    "gn:population":0,
    "gn:timezone":"Asia/Yekaterinburg",
    "iso:country":"RU",
    "name:rus_x_preferred":[
        "\u041b\u043e\u0433\u043e\u0432\u043e\u0439"
    ],
    "wof:name":"Logovoy",
    "wof:placetype":"locality"
},
  "geometry": {"coordinates":[61.0692,54.0035],"type":"Point"}
}