{
  "type": "Feature",
  "properties": {
    "gn:admin1_code":"33",
    "gn:asciiname":"Kurganovskiy",
    "gn:country_code":"RU",
    "gn:dem":164,
    "gn:feature_class":"P",
    "gn:feature_code":"PPL",
    "gn:name":"Kurganovskiy",
    "gn:population":0,
    "gn:timezone":"Europe/Kirov",
    "iso:country":"RU",
    "name:rus_x_preferred":[
        "\u041a\u0443\u0440\u0433\u0430\u043d\u043e\u0432\u0441\u043a\u0438\u0439"
    ],
    "wof:name":"Kurganovskiy",
    "wof:placetype":"locality"
},
  "geometry": {"coordinates":[49.6191,57.1442],"type":"Point"}
}