{
  "type": "Feature",
  "properties": {
    "gn:admin1_code":"33.0",
    "gn:asciiname":"Shagadaki",
    "gn:country_code":"RU",
    "gn:dem":148,
    "gn:feature_class":"P",
    "gn:feature_code":"PPL",
    "gn:name":"Shagadaki",
    "gn:population":0,
    "gn:timezone":"Europe/Kirov",
    "iso:country":"RU",
    "name:rus_x_preferred":[
        "\u0428\u0430\u0433\u0430\u0434\u0430\u043a\u0438"
    ],
    "name:und_x_variant":[
        "\u0428\u0430\u0433\u0430\u0434\u0430\u043a\u0438"
    ],
    "wof:name":"Shagadaki",
    "wof:placetype":"locality"
},
  "geometry": {"coordinates":[48.2104,57.35635],"type":"Point"}
}