{
  "type": "Feature",
  "properties": {
    "gn:admin1_code":"46",
    "gn:asciiname":"Novyye Verkhissy",
    "gn:country_code":"RU",
    "gn:dem":168,
    "gn:feature_class":"P",
    "gn:feature_code":"PPL",
    "gn:name":"Novyye Verkhissy",
    "gn:population":0,
    "gn:timezone":"Europe/Moscow",
    "iso:country":"RU",
    "name:eng_x_preferred":[
        "Novyye Verkhissy"
    ],
    "name:nor_x_preferred":[
        "Nov.Verkhisy"
    ],
    "name:rus_x_preferred":[
        "\u041d\u043e\u0432.\u0412\u0435\u0440\u0445\u0438\u0441\u044b"
    ],
    "name:rus_x_variant":[
        "\u041d\u043e\u0432\u044b\u0435 \u0412\u0435\u0440\u0445\u0438\u0441\u0441\u044b"
    ],
    "name:und_x_variant":[
        "Novyye Verkhisy"
    ],
    "wof:name":"Novyye Verkhissy",
    "wof:placetype":"locality"
},
  "geometry": {"coordinates":[44.5593,53.84723],"type":"Point"}
}