{
  "type": "Feature",
  "properties": {
    "gn:admin1_code":"8",
    "gn:asciiname":"Pushkinskiy",
    "gn:country_code":"RU",
    "gn:dem":228,
    "gn:feature_class":"P",
    "gn:feature_code":"PPL",
    "gn:name":"Pushkinskiy",
    "gn:population":0,
    "gn:timezone":"Asia/Yekaterinburg",
    "iso:country":"RU",
    "name:rus_x_preferred":[
        "\u041f\u0443\u0448\u043a\u0438\u043d\u0441\u043a\u0438\u0439"
    ],
    "name:und_x_variant":[
        "Pushkina",
        "Pushkinskiy"
    ],
    "wof:name":"Pushkinskiy",
    "wof:placetype":"locality"
},
  "geometry": {"coordinates":[56.11361,54.02435],"type":"Point"}
}