{
  "type": "Feature",
  "properties": {
    "gn:admin1_code":"20.0",
    "gn:asciiname":"Zabanovskiy",
    "gn:country_code":"RU",
    "gn:dem":397,
    "gn:feature_class":"P",
    "gn:feature_code":"PPL",
    "gn:name":"Zabanovskiy",
    "gn:population":0,
    "gn:timezone":"Asia/Irkutsk",
    "iso:country":"RU",
    "name:rus_x_preferred":[
        "\u0417\u0430\u0431\u0430\u043d\u043e\u0432\u0441\u043a\u0438\u0439"
    ],
    "wof:name":"Zabanovskiy",
    "wof:placetype":"locality"
},
  "geometry": {"coordinates":[103.76860000000001,53.4439],"type":"Point"}
}