{
  "type": "Feature",
  "properties": {
    "gn:admin1_code":"89",
    "gn:asciiname":"Pompeyevka",
    "gn:country_code":"RU",
    "gn:dem":100,
    "gn:feature_class":"P",
    "gn:feature_code":"PPL",
    "gn:name":"Pompeyevka",
    "gn:population":0,
    "gn:timezone":"Asia/Vladivostok",
    "iso:country":"RU",
    "name:eng_x_preferred":[
        "Pompeyevka"
    ],
    "name:nor_x_preferred":[
        "Pompejevka"
    ],
    "name:rus_x_preferred":[
        "\u041f\u043e\u043c\u043f\u0435\u0435\u0432\u043a\u0430"
    ],
    "name:und_x_variant":[
        "\u041f\u043e\u043c\u043f\u0435\u0435\u0432\u043a\u0430",
        "Pompeyevka"
    ],
    "wof:name":"Pompeyevka",
    "wof:placetype":"locality"
},
  "geometry": {"coordinates":[130.80784,48.34898],"type":"Point"}
}