{
  "type": "Feature",
  "properties": {
    "gn:admin1_code":"77",
    "gn:asciiname":"Kolynevo",
    "gn:country_code":"RU",
    "gn:dem":174,
    "gn:feature_class":"P",
    "gn:feature_code":"PPL",
    "gn:name":"Kolynevo",
    "gn:population":0,
    "gn:timezone":"Europe/Moscow",
    "iso:country":"RU",
    "name:rus_x_preferred":[
        "\u041a\u043e\u043b\u044b\u043d\u0435\u0432\u043e"
    ],
    "name:und_x_variant":[
        "\u041a\u043e\u043b\u044b\u043d\u0435\u0432\u043e"
    ],
    "wof:name":"Kolynevo",
    "wof:placetype":"locality"
},
  "geometry": {"coordinates":[36.87365,58.61949],"type":"Point"}
}