{
  "type": "Feature",
  "properties": {
    "gn:admin1_code":"53",
    "gn:asciiname":"Ryazanovka",
    "gn:cc2":"RU",
    "gn:country_code":"RU",
    "gn:dem":149,
    "gn:feature_class":"P",
    "gn:feature_code":"PPL",
    "gn:name":"Ryazanovka",
    "gn:population":0,
    "gn:timezone":"Asia/Novosibirsk",
    "iso:country":"RU",
    "name:rus_x_preferred":[
        "\u0420\u044f\u0437\u0430\u043d\u043e\u0432\u043a\u0430"
    ],
    "name:und_x_variant":[
        "Ryazanovskiy",
        "Ryazanovka"
    ],
    "wof:name":"Ryazanovka",
    "wof:placetype":"locality"
},
  "geometry": {"coordinates":[83.59999999999999,55.51667],"type":"Point"}
}