{
  "type": "Feature",
  "properties": {
    "gn:admin1_code":"77.0",
    "gn:asciiname":"Degtevo",
    "gn:country_code":"RU",
    "gn:dem":187,
    "gn:feature_class":"P",
    "gn:feature_code":"PPL",
    "gn:name":"D\u00ebgtevo",
    "gn:population":0,
    "gn:timezone":"Europe/Moscow",
    "iso:country":"RU",
    "name:rus_x_preferred":[
        "\u0414\u0451\u0433\u0442\u0435\u0432o"
    ],
    "name:und_x_variant":[
        "D\u00ebgteva",
        "D\u00ebgtevo"
    ],
    "wof:name":"Degtevo",
    "wof:placetype":"locality"
},
  "geometry": {"coordinates":[32.89159,56.11176],"type":"Point"}
}