{
  "type": "Feature",
  "properties": {
    "gn:admin1_code":"77",
    "gn:asciiname":"Vysokoye",
    "gn:country_code":"RU",
    "gn:dem":175,
    "gn:feature_class":"P",
    "gn:feature_code":"PPL",
    "gn:name":"Vysokoye",
    "gn:population":0,
    "gn:timezone":"Europe/Moscow",
    "iso:country":"RU",
    "name:und_x_variant":[
        "Vysokovo",
        "Vysokoye"
    ],
    "wof:name":"Vysokoye",
    "wof:placetype":"locality"
},
  "geometry": {"coordinates":[34.91101,56.70198000000001],"type":"Point"}
}