{
  "type": "Feature",
  "properties": {
    "gn:admin1_code":"84.0",
    "gn:asciiname":"Dubinin",
    "gn:country_code":"RU",
    "gn:dem":88,
    "gn:feature_class":"P",
    "gn:feature_code":"PPL",
    "gn:name":"Dubinin",
    "gn:population":0,
    "gn:timezone":"Europe/Volgograd",
    "iso:country":"RU",
    "name:rus_x_preferred":[
        "\u0414\u0443\u0431\u0438\u043d\u0438\u043d"
    ],
    "name:slv_x_preferred":[
        "Dubinin"
    ],
    "name:und_x_variant":[
        "Dubininskiy",
        "Dubinin"
    ],
    "wof:name":"Dubinin",
    "wof:placetype":"locality"
},
  "geometry": {"coordinates":[44.12021,48.74475],"type":"Point"}
}