{
  "type": "Feature",
  "properties": {
    "gn:admin1_code":"65",
    "gn:asciiname":"Kolybelovka",
    "gn:country_code":"RU",
    "gn:dem":145,
    "gn:feature_class":"P",
    "gn:feature_code":"PPL",
    "gn:name":"Kolybelovka",
    "gn:population":0,
    "gn:timezone":"Europe/Samara",
    "iso:country":"RU",
    "name:rus_x_preferred":[
        "\u041a\u043e\u043b\u044b\u0431\u0435\u043b\u043e\u0432\u043a\u0430"
    ],
    "name:und_x_variant":[
        "Kolybelovko",
        "Kolybelovka",
        "\u041a\u043e\u043b\u044b\u0431\u0435\u043b\u043e\u0432\u043a\u0430"
    ],
    "wof:name":"Kolybelovka",
    "wof:placetype":"locality"
},
  "geometry": {"coordinates":[49.9115,52.6744],"type":"Point"}
}