{
  "type": "Feature",
  "properties": {
    "gn:country":"RU",
    "gn:fcode":"PPL",
    "gn:pop":0,
    "iso:country":"RU",
    "name:cat_x_preferred":[
        "subbotniks"
    ],
    "name:deu_x_preferred":[
        "Subbotniki"
    ],
    "name:eng_x_preferred":[
        "Subbotniki"
    ],
    "name:eng_x_variant":[
        "Subbotniks"
    ],
    "name:fra_x_preferred":[
        "Subbotniks"
    ],
    "name:heb_x_preferred":[
        "\u05e1\u05d5\u05d1\u05d5\u05d8\u05e0\u05d9\u05e7\u05d9\u05dd"
    ],
    "name:mkd_x_preferred":[
        "\u0441\u0430\u0431\u043e\u0442\u043d\u0438\u0446\u0438"
    ],
    "name:nld_x_preferred":[
        "Subbotniks"
    ],
    "name:nob_x_preferred":[
        "Subbotnikere"
    ],
    "name:nor_x_preferred":[
        "Subbotniki"
    ],
    "name:rus_x_preferred":[
        "\u0421\u0443\u0431\u0431\u043e\u0442\u043d\u0438\u043a\u0438"
    ],
    "name:rus_x_variant":[
        "\u0441\u0443\u0431\u0431\u043e\u0442\u043d\u0438\u043a\u0438"
    ],
    "name:unk_x_variant":[
        "\u0421\u0443\u0431\u0431\u043e\u0442\u043d\u0438\u043a\u0438"
    ],
    "name:zho_x_preferred":[
        "\u56b4\u5b88\u5b89\u606f\u65e5\u7684\u57fa\u7763\u5f92"
    ],
    "qs:name":"Subbotniki",
    "qs:name_adm0":"Russia",
    "qs:name_adm1":"Perm Krai",
    "qs:photos":18,
    "qs:photos_1k":4,
    "qs:photos_9k":1,
    "qs:photos_9r":1,
    "qs:photos_all":18,
    "qs:photos_sr":1,
    "qs:placetype":"Town",
    "qs:pop_sr":"0",
    "wd:wordcount":2306,
    "wof:name":"Subbotniki",
    "wof:placetype":"locality",
    "wof:population":0
},
  "geometry": {"coordinates":[54.60791,58.03058],"type":"Point"}
}