{
  "type": "Feature",
  "properties": {
    "gn:admin1_code":"65",
    "gn:asciiname":"Leningradskiy",
    "gn:country_code":"RU",
    "gn:dem":117,
    "gn:feature_class":"P",
    "gn:feature_code":"PPL",
    "gn:name":"Leningradskiy",
    "gn:population":0,
    "gn:timezone":"Europe/Samara",
    "iso:country":"RU",
    "name:rus_x_preferred":[
        "\u041b\u0435\u043d\u0438\u043d\u0433\u0440\u0430\u0434\u0441\u043a\u0438\u0439"
    ],
    "name:und_x_variant":[
        "Leningradka",
        "Leningradskiy"
    ],
    "wof:name":"Leningradskiy",
    "wof:placetype":"locality"
},
  "geometry": {"coordinates":[51.1466,52.43600000000001],"type":"Point"}
}