{
  "type": "Feature",
  "properties": {
    "gn:admin1_code":"13",
    "gn:asciiname":"Khersonskiy",
    "gn:country_code":"RU",
    "gn:dem":212,
    "gn:feature_class":"P",
    "gn:feature_code":"PPL",
    "gn:name":"Khersonskiy",
    "gn:population":0,
    "gn:timezone":"Asia/Yekaterinburg",
    "iso:country":"RU",
    "name:rus_x_preferred":[
        "\u0425\u0435\u0440\u0441\u043e\u043d\u0441\u043a\u0438\u0439"
    ],
    "name:und_x_variant":[
        "Khersonskiy Tretiy",
        "Khersonskiy"
    ],
    "wof:name":"Khersonskiy",
    "wof:placetype":"locality"
},
  "geometry": {"coordinates":[61.2261,54.0466],"type":"Point"}
}