{
  "type": "Feature",
  "properties": {
    "gn:admin1_code":"52",
    "gn:asciiname":"Vyselok Bekhovo",
    "gn:country_code":"RU",
    "gn:dem":71,
    "gn:feature_class":"P",
    "gn:feature_code":"PPL",
    "gn:name":"Vyselok B\u00ebkhovo",
    "gn:population":0,
    "gn:timezone":"Europe/Moscow",
    "iso:country":"RU",
    "name:und_x_variant":[
        "B\u00ebkhovo",
        "Vyselok B\u00ebkhovo"
    ],
    "wof:name":"Vyselok Bekhovo",
    "wof:placetype":"locality"
},
  "geometry": {"coordinates":[30.57612,58.01452],"type":"Point"}
}