{
  "type": "Feature",
  "properties": {
    "gn:admin1_code":"34",
    "gn:asciiname":"Maritsy",
    "gn:country_code":"RU",
    "gn:dem":38,
    "gn:feature_class":"P",
    "gn:feature_code":"PPL",
    "gn:name":"Maritsy",
    "gn:population":0,
    "gn:timezone":"Europe/Moscow",
    "iso:country":"RU",
    "name:rus_x_preferred":[
        "\u041c\u0430\u0440\u0438\u0446\u044b"
    ],
    "name:und_x_variant":[
        "Mar\u2019ichi",
        "Listvenichnaya",
        "Maritsy"
    ],
    "wof:name":"Maritsy",
    "wof:placetype":"locality"
},
  "geometry": {"coordinates":[52.24573,66.76456999999999],"type":"Point"}
}