{
  "type": "Feature",
  "properties": {
    "gn:admin1_code":"16",
    "gn:asciiname":"Syadorga-Sirmy",
    "gn:country_code":"RU",
    "gn:dem":149,
    "gn:feature_class":"P",
    "gn:feature_code":"PPL",
    "gn:name":"Syadorga-Sirmy",
    "gn:population":0,
    "gn:timezone":"Europe/Moscow",
    "iso:country":"RU",
    "name:rus_x_preferred":[
        "\u0421\u044f\u0434\u043e\u0440\u0433\u0430-\u0421\u0438\u0440\u043c\u044b"
    ],
    "name:und_x_variant":[
        "Syadorgi-Sirma",
        "Syadorga-Sirmy"
    ],
    "wof:name":"Syadorga-Sirmy",
    "wof:placetype":"locality"
},
  "geometry": {"coordinates":[47.49113,55.42741],"type":"Point"}
}