{
  "type": "Feature",
  "properties": {
    "gn:admin1_code":"86",
    "gn:asciiname":"Nikolo-Varvarinka",
    "gn:country_code":"RU",
    "gn:dem":138,
    "gn:feature_class":"P",
    "gn:feature_code":"PPL",
    "gn:name":"Nikolo-Varvarinka",
    "gn:population":0,
    "gn:timezone":"Europe/Moscow",
    "iso:country":"RU",
    "name:rus_x_preferred":[
        "\u041d\u0438\u043a\u043e\u043b\u043e-\u0412\u0430\u0440\u0432\u0430\u0440\u0438\u043d\u043a\u0430"
    ],
    "name:und_x_variant":[
        "Nikolo-Varvarski",
        "Nikolo-Varvarinka"
    ],
    "wof:name":"Nikolo-Varvarinka",
    "wof:placetype":"locality"
},
  "geometry": {"coordinates":[39.9787,51.00266],"type":"Point"}
}