{
  "type": "Feature",
  "properties": {
    "gn:admin1_code":"64",
    "gn:asciiname":"Dautu",
    "gn:cc2":"RU",
    "gn:country_code":"RU",
    "gn:dem":1,
    "gn:feature_class":"P",
    "gn:feature_code":"PPL",
    "gn:name":"Dautu",
    "gn:population":0,
    "gn:timezone":"Asia/Sakhalin",
    "iso:country":"RU",
    "name:rus_x_preferred":[
        "\u0414\u0430\u0443\u0442\u0443"
    ],
    "name:und_x_variant":[
        "Doutu",
        "Dautu",
        "\u0414\u0430\u0443\u0442\u0443"
    ],
    "wof:name":"Dautu",
    "wof:placetype":"locality"
},
  "geometry": {"coordinates":[143.33333000000005,51.61667],"type":"Point"}
}