{
  "type": "Feature",
  "properties": {
    "gn:admin1_code":"28",
    "gn:asciiname":"Salola",
    "gn:country_code":"RU",
    "gn:dem":146,
    "gn:feature_class":"P",
    "gn:feature_code":"PPL",
    "gn:name":"Salola",
    "gn:population":0,
    "gn:timezone":"Europe/Moscow",
    "iso:country":"RU",
    "name:rus_x_preferred":[
        "\u0421\u0430\u043b\u043e\u043b\u0430"
    ],
    "name:und_x_variant":[
        "\u0421\u0430\u043b\u043e\u043b\u0430"
    ],
    "wof:name":"Salola",
    "wof:placetype":"locality"
},
  "geometry": {"coordinates":[32.192,62.20891],"type":"Point"}
}