{
  "type": "Feature",
  "properties": {
    "gn:admin1_code":"60",
    "gn:asciiname":"Merlyakovo",
    "gn:country_code":"RU",
    "gn:dem":149,
    "gn:feature_class":"P",
    "gn:feature_code":"PPL",
    "gn:name":"Merlyakovo",
    "gn:population":0,
    "gn:timezone":"Europe/Moscow",
    "iso:country":"RU",
    "name:rus_x_preferred":[
        "\u041c\u0435\u0440\u043b\u044f\u043a\u043e\u0432\u043e"
    ],
    "wof:name":"Merlyakovo",
    "wof:placetype":"locality"
},
  "geometry": {"coordinates":[30.07553,56.79888],"type":"Point"}
}