{
  "type": "Feature",
  "properties": {
    "gn:admin1_code":"70",
    "gn:asciiname":"Peskovskiy",
    "gn:country_code":"RU",
    "gn:dem":590,
    "gn:feature_class":"P",
    "gn:feature_code":"PPL",
    "gn:name":"Peskovskiy",
    "gn:population":0,
    "gn:timezone":"Europe/Moscow",
    "iso:country":"RU",
    "name:rus_x_preferred":[
        "\u041f\u0435\u0441\u043a\u043e\u0432\u0441\u043a\u0438\u0439"
    ],
    "wof:name":"Peskovskiy",
    "wof:placetype":"locality"
},
  "geometry": {"coordinates":[43.0825,43.96889],"type":"Point"}
}