{
  "type": "Feature",
  "properties": {
    "gn:admin1_code":"63",
    "gn:asciiname":"Khomustakh",
    "gn:cc2":"RU",
    "gn:country_code":"RU",
    "gn:dem":117,
    "gn:feature_class":"P",
    "gn:feature_code":"PPL",
    "gn:name":"Khomustakh",
    "gn:population":0,
    "gn:timezone":"Asia/Yakutsk",
    "iso:country":"RU",
    "name:eng_x_preferred":[
        "Khomustakh"
    ],
    "name:nor_x_preferred":[
        "Khomustakh"
    ],
    "name:rus_x_preferred":[
        "\u0425\u043e\u043c\u0443\u0441\u0442\u0430\u0445"
    ],
    "name:und_x_variant":[
        "Khomustaakh"
    ],
    "wof:name":"Khomustakh",
    "wof:placetype":"locality"
},
  "geometry": {"coordinates":[120.53444,63.47556],"type":"Point"}
}