{
  "type": "Feature",
  "properties": {
    "gn:admin1_code":"55",
    "gn:asciiname":"Pravoberezhnyy",
    "gn:country_code":"RU",
    "gn:dem":119,
    "gn:feature_class":"P",
    "gn:feature_code":"PPL",
    "gn:name":"Pravoberezhnyy",
    "gn:population":0,
    "gn:timezone":"Asia/Yekaterinburg",
    "iso:country":"RU",
    "name:rus_x_preferred":[
        "\u041f\u0440\u0430\u0432\u043e\u0431\u0435\u0440\u0435\u0436\u043d\u044b\u0439"
    ],
    "name:und_x_variant":[
        "\u041f\u0440\u0430\u0432\u043e\u0431\u0435\u0440\u0435\u0436\u043d\u044b\u0439"
    ],
    "wof:name":"Pravoberezhnyy",
    "wof:placetype":"locality"
},
  "geometry": {"coordinates":[56.24687,51.53778],"type":"Point"}
}