{
  "type": "Feature",
  "properties": {
    "gn:admin1_code":"73",
    "gn:asciiname":"Staryy Bagryat Yelkhovo",
    "gn:country_code":"RU",
    "gn:dem":85,
    "gn:feature_class":"P",
    "gn:feature_code":"PPL",
    "gn:name":"Staryy Bagryat Yelkhovo",
    "gn:population":0,
    "gn:timezone":"Europe/Moscow",
    "iso:country":"RU",
    "name:rus_x_preferred":[
        "\u0421\u0442\u0430\u0440\u044b\u0439 \u0411\u0430\u0433\u0440\u044f\u0442 \u0415\u043b\u0445\u043e\u0432\u043e"
    ],
    "name:und_x_variant":[
        "Staryy Bagryash",
        "Stary Bagryash",
        "Staryy Bagryazh",
        "Staryy Bagryat Yelkhovo",
        "\u0421\u0442\u0430\u0440\u044b\u0439 \u0411\u0430\u0433\u0440\u044f\u0442 \u0415\u043b\u0445\u043e\u0432\u043e",
        "Staryy Bagryazh-Yelkhovo"
    ],
    "wof:name":"Staryy Bagryat Yelkhovo",
    "wof:placetype":"locality"
},
  "geometry": {"coordinates":[51.62314,54.89095],"type":"Point"}
}