{
  "type": "Feature",
  "properties": {
    "gn:admin1_code":"13",
    "gn:asciiname":"Salgan",
    "gn:country_code":"RU",
    "gn:dem":430,
    "gn:feature_class":"P",
    "gn:feature_code":"PPL",
    "gn:name":"Salgan",
    "gn:population":0,
    "gn:timezone":"Asia/Yekaterinburg",
    "iso:country":"RU",
    "name:eng_x_preferred":[
        "Salgan"
    ],
    "name:nor_x_preferred":[
        "Salgan"
    ],
    "name:rus_x_preferred":[
        "\u0421\u0430\u043b\u0433\u0430\u043d"
    ],
    "name:und_x_variant":[
        "\u0421\u0430\u043b\u0433\u0430\u043d",
        "Salgan"
    ],
    "wof:name":"Salgan",
    "wof:placetype":"locality"
},
  "geometry": {"coordinates":[59.3165,55.1795],"type":"Point"}
}