{
  "type": "Feature",
  "properties": {
    "gn:admin1_code":"71",
    "gn:asciiname":"Chernoles'ye",
    "gn:country_code":"RU",
    "gn:dem":69,
    "gn:feature_class":"P",
    "gn:feature_code":"PPL",
    "gn:name":"Chernoles\u2019ye",
    "gn:population":0,
    "gn:timezone":"Asia/Yekaterinburg",
    "iso:country":"RU",
    "name:rus_x_preferred":[
        "\u0427\u0435\u0440\u043d\u043e\u043b\u0435\u0441\u044c\u0435"
    ],
    "name:und_x_variant":[
        "Chernoles\u2019ye",
        "\u0427\u0435\u0440\u043d\u043e\u043b\u0435\u0441\u044c\u0435"
    ],
    "wof:name":"Chernoles'ye",
    "wof:placetype":"locality"
},
  "geometry": {"coordinates":[63.08333,57.66667],"type":"Point"}
}