{
  "type": "Feature",
  "properties": {
    "gn:admin1_code":"52",
    "gn:asciiname":"Podol",
    "gn:country_code":"RU",
    "gn:dem":160,
    "gn:feature_class":"P",
    "gn:feature_code":"PPL",
    "gn:name":"Podol",
    "gn:population":0,
    "gn:timezone":"Europe/Moscow",
    "iso:country":"RU",
    "name:deu_x_preferred":[
        "Podol"
    ],
    "name:fas_x_preferred":[
        "\u067e\u062f\u0644"
    ],
    "name:msa_x_preferred":[
        "Podol"
    ],
    "name:rus_x_preferred":[
        "\u041f\u043e\u0434\u043e\u043b"
    ],
    "name:und_x_variant":[
        "\u041f\u043e\u0434\u043e\u043b"
    ],
    "wof:name":"Podol",
    "wof:placetype":"locality"
},
  "geometry": {"coordinates":[34.96667,58.56667],"type":"Point"}
}