{
  "type": "Feature",
  "properties": {
    "gn:admin1_code":"60",
    "gn:asciiname":"Shaurino",
    "gn:country_code":"RU",
    "gn:dem":132,
    "gn:feature_class":"P",
    "gn:feature_code":"PPL",
    "gn:name":"Shaurino",
    "gn:population":0,
    "gn:timezone":"Europe/Moscow",
    "iso:country":"RU",
    "name:rus_x_preferred":[
        "\u0428\u0430\u0443\u0440\u0438\u043d\u043e"
    ],
    "wof:name":"Shaurino",
    "wof:placetype":"locality"
},
  "geometry": {"coordinates":[29.4909,56.9793],"type":"Point"}
}