{
  "type": "Feature",
  "properties": {
    "gn:admin1_code":"88",
    "gn:asciiname":"Verigino",
    "gn:country_code":"RU",
    "gn:dem":143,
    "gn:feature_class":"P",
    "gn:feature_code":"PPL",
    "gn:name":"Verigino",
    "gn:population":0,
    "gn:timezone":"Europe/Moscow",
    "iso:country":"RU",
    "name:rus_x_preferred":[
        "\u0412\u0435\u0440\u0438\u0433\u0438\u043d\u043e"
    ],
    "wof:name":"Verigino",
    "wof:placetype":"locality"
},
  "geometry": {"coordinates":[39.82497,57.96158000000001],"type":"Point"}
}