{
  "type": "Feature",
  "properties": {
    "gn:admin1_code":"45",
    "gn:asciiname":"Pishtenger",
    "gn:country_code":"RU",
    "gn:dem":113,
    "gn:feature_class":"P",
    "gn:feature_code":"PPL",
    "gn:name":"Pishtenger",
    "gn:population":0,
    "gn:timezone":"Europe/Moscow",
    "iso:country":"RU",
    "name:rus_x_preferred":[
        "\u041f\u0438\u0448\u0442\u0435\u043d\u0433\u0435\u0440"
    ],
    "wof:name":"Pishtenger",
    "wof:placetype":"locality"
},
  "geometry": {"coordinates":[47.99787,56.87706],"type":"Point"}
}