{
  "type": "Feature",
  "properties": {
    "gn:admin1_code":"52",
    "gn:asciiname":"Karpushina",
    "gn:country_code":"RU",
    "gn:dem":50,
    "gn:feature_class":"P",
    "gn:feature_code":"PPL",
    "gn:name":"Karpushina",
    "gn:population":0,
    "gn:timezone":"Europe/Moscow",
    "iso:country":"RU",
    "name:rus_x_preferred":[
        "\u041a\u0430\u0440\u043f\u0443\u0448\u0438\u043d\u0430"
    ],
    "name:und_x_variant":[
        "\u041a\u0430\u0440\u043f\u0443\u0448\u0438\u043d\u0430"
    ],
    "wof:name":"Karpushina",
    "wof:placetype":"locality"
},
  "geometry": {"coordinates":[30.08333,58.01667],"type":"Point"}
}