{
  "type": "Feature",
  "properties": {
    "gn:admin1_code":"52",
    "gn:asciiname":"Paledi",
    "gn:country_code":"RU",
    "gn:dem":158,
    "gn:feature_class":"P",
    "gn:feature_code":"PPL",
    "gn:name":"Paledi",
    "gn:population":0,
    "gn:timezone":"Europe/Moscow",
    "iso:country":"RU",
    "name:rus_x_preferred":[
        "\u041f\u0430\u043b\u0435\u0434\u0438"
    ],
    "name:und_x_variant":[
        "\u041f\u0430\u043b\u0435\u0434\u0438"
    ],
    "wof:name":"Paledi",
    "wof:placetype":"locality"
},
  "geometry": {"coordinates":[34.73333,58.93333000000001],"type":"Point"}
}