{
  "type": "Feature",
  "properties": {
    "gn:admin1_code":"24",
    "gn:asciiname":"Teyegin-Gerl",
    "gn:country_code":"RU",
    "gn:dem":-13,
    "gn:feature_class":"P",
    "gn:feature_code":"PPL",
    "gn:name":"Teyegin-Gerl",
    "gn:population":0,
    "gn:timezone":"Europe/Moscow",
    "iso:country":"RU",
    "name:rus_x_preferred":[
        "\u0422\u0435\u0435\u0433\u0438\u043d-\u0413\u0435\u0440\u043b"
    ],
    "wof:name":"Teyegin-Gerl",
    "wof:placetype":"locality"
},
  "geometry": {"coordinates":[45.6503,46.1333],"type":"Point"}
}