{
  "type": "Feature",
  "properties": {
    "gn:admin1_code":"63",
    "gn:asciiname":"Nel'gese",
    "gn:country_code":"RU",
    "gn:dem":101,
    "gn:feature_class":"P",
    "gn:feature_code":"PPL",
    "gn:name":"Nel\u2019gese",
    "gn:population":0,
    "gn:timezone":"Asia/Vladivostok",
    "iso:country":"RU",
    "name:eng_x_preferred":[
        "Nel'gese"
    ],
    "name:nor_x_preferred":[
        "Nelgese"
    ],
    "name:rus_x_preferred":[
        "\u041d\u0435\u043b\u044c\u0433\u0435\u0441\u0435"
    ],
    "name:und_x_variant":[
        "Nel\u2019gese"
    ],
    "wof:name":"Nel'gese",
    "wof:placetype":"locality"
},
  "geometry": {"coordinates":[134.67514,67.99264000000001],"type":"Point"}
}