{
  "type": "Feature",
  "properties": {
    "gn:admin1_code":"10",
    "gn:asciiname":"Voznesensk",
    "gn:country_code":"RU",
    "gn:dem":171,
    "gn:feature_class":"P",
    "gn:feature_code":"PPL",
    "gn:name":"Voznesensk",
    "gn:population":0,
    "gn:timezone":"Europe/Moscow",
    "iso:country":"RU",
    "name:ara_x_preferred":[
        "\u0641\u0648\u0632\u0646\u064a\u0633\u064a\u0646\u0633\u0643"
    ],
    "name:azb_x_preferred":[
        "\u0648\u0632\u0646\u0633\u0646\u0633\u06a9"
    ],
    "name:bel_x_preferred":[
        "\u0412\u0430\u0437\u043d\u044d\u0441\u044d\u043d\u0441\u043a"
    ],
    "name:bul_x_preferred":[
        "\u0412\u043e\u0437\u043d\u0435\u0441\u0435\u043d\u0441\u043a"
    ],
    "name:ceb_x_preferred":[
        "Voznesensk"
    ],
    "name:ces_x_preferred":[
        "Voznesensk"
    ],
    "name:crh_x_preferred":[
        "Voznesensk"
    ],
    "name:deu_x_preferred":[
        "Wosnessensk"
    ],
    "name:fas_x_preferred":[
        "\u0648\u0632\u0646\u0633\u0646\u0633\u06a9"
    ],
    "name:fra_x_preferred":[
        "Voznessensk"
    ],
    "name:heb_x_preferred":[
        "\u05d5\u05d5\u05d6\u05e0\u05e1\u05e0\u05e1\u05e7"
    ],
    "name:hsb_x_preferred":[
        "Woznesensk"
    ],
    "name:hye_x_preferred":[
        "\u054e\u0578\u0566\u0576\u0565\u057d\u0565\u0576\u057d\u056f"
    ],
    "name:ita_x_preferred":[
        "Voznesens'k"
    ],
    "name:kat_x_preferred":[
        "\u10d5\u10dd\u10d6\u10dc\u10d4\u10e1\u10d4\u10dc\u10e1\u10d9\u10d8"
    ],
    "name:lav_x_preferred":[
        "Voznesenska"
    ],
    "name:lit_x_preferred":[
        "Voznesenskas"
    ],
    "name:nno_x_preferred":[
        "Voznesensk"
    ],
    "name:pol_x_preferred":[
        "Wozniesie\u0144sk"
    ],
    "name:ron_x_preferred":[
        "Voznesensk"
    ],
    "name:rus_x_preferred":[
        "\u0412\u043e\u0437\u043d\u0435\u0441\u0435\u043d\u0441\u043a"
    ],
    "name:srp_x_preferred":[
        "\u0412\u043e\u0437\u043d\u0435\u0441\u0435\u043d\u0441\u043a"
    ],
    "name:swe_x_preferred":[
        "Voznesensk"
    ],
    "name:tat_x_preferred":[
        "Voznesensk"
    ],
    "name:ukr_x_preferred":[
        "\u0412\u043e\u0437\u043d\u0435\u0441\u0435\u043d\u0441\u044c\u043a"
    ],
    "name:vie_x_preferred":[
        "Voznesensk"
    ],
    "name:zho_x_preferred":[
        "\u6c83\u8332\u6d85\u5148\u65af\u514b"
    ],
    "wof:name":"Voznesensk",
    "wof:placetype":"locality"
},
  "geometry": {"coordinates":[34.1855,52.8212],"type":"Point"}
}