{
  "type": "Feature",
  "properties": {
    "gn:admin1_code":"38",
    "gn:asciiname":"Gudko-Limanskiy",
    "gn:country_code":"RU",
    "gn:dem":10,
    "gn:feature_class":"P",
    "gn:feature_code":"PPL",
    "gn:name":"Gudko-Limanskiy",
    "gn:population":0,
    "gn:timezone":"Europe/Moscow",
    "iso:country":"RU",
    "name:rus_x_preferred":[
        "\u0413\u0443\u0434\u043a\u043e-\u041b\u0438\u043c\u0430\u043d\u0441\u043a\u0438\u0439"
    ],
    "name:und_x_variant":[
        "Gudkovo-Limanovskiy",
        "Gudko-Limanskiy",
        "\u0413\u0443\u0434\u043a\u043e-\u041b\u0438\u043c\u0430\u043d\u0441\u043a\u0438\u0439",
        "Gudkovo-Limanskiy"
    ],
    "wof:name":"Gudko-Limanskiy",
    "wof:placetype":"locality"
},
  "geometry": {"coordinates":[39.43843,46.6217],"type":"Point"}
}