{
  "type": "Feature",
  "properties": {
    "gn:admin1_code":"65",
    "gn:asciiname":"Verkhnedol'sk",
    "gn:country_code":"RU",
    "gn:dem":116,
    "gn:feature_class":"P",
    "gn:feature_code":"PPL",
    "gn:name":"Verkhnedol\u2019sk",
    "gn:population":0,
    "gn:timezone":"Europe/Samara",
    "iso:country":"RU",
    "name:rus_x_preferred":[
        "\u0412\u0435\u0440\u0445\u043d\u0435\u0434\u043e\u043b\u044c\u0441\u043a"
    ],
    "name:und_x_variant":[
        "Verkhnedol\u2019sk",
        "\u0412\u0435\u0440\u0445\u043d\u0435\u0434\u043e\u043b\u044c\u0441\u043a"
    ],
    "wof:name":"Verkhnedol'sk",
    "wof:placetype":"locality"
},
  "geometry": {"coordinates":[50.7419,52.5132],"type":"Point"}
}