{
  "type": "Feature",
  "properties": {
    "gn:admin1_code":"46",
    "gn:asciiname":"Staraya Samayevka",
    "gn:country_code":"RU",
    "gn:dem":159,
    "gn:feature_class":"P",
    "gn:feature_code":"PPL",
    "gn:name":"Staraya Samayevka",
    "gn:population":0,
    "gn:timezone":"Europe/Moscow",
    "iso:country":"RU",
    "name:nor_x_preferred":[
        "Staraja Samajevka"
    ],
    "name:rus_x_preferred":[
        "\u0421\u0442\u0430\u0440\u0430\u044f \u0421\u0430\u043c\u0430\u0435\u0432\u043a\u0430"
    ],
    "wof:name":"Staraya Samayevka",
    "wof:placetype":"locality"
},
  "geometry": {"coordinates":[43.68003,54.22051],"type":"Point"}
}