{
  "type": "Feature",
  "properties": {
    "gn:admin1_code":"50",
    "gn:asciiname":"Novaya Tonya",
    "gn:country_code":"RU",
    "gn:dem":165,
    "gn:feature_class":"P",
    "gn:feature_code":"PPL",
    "gn:name":"Novaya Tonya",
    "gn:population":0,
    "gn:timezone":"Europe/Moscow",
    "iso:country":"RU",
    "name:rus_x_preferred":[
        "\u041d\u043e\u0432\u0430\u044f \u0422\u043e\u043d\u044f"
    ],
    "wof:name":"Novaya Tonya",
    "wof:placetype":"locality"
},
  "geometry": {"coordinates":[43.85331,68.44365000000001],"type":"Point"}
}