{
  "type": "Feature",
  "properties": {
    "gn:admin1_code":"91",
    "gn:asciiname":"Baykan",
    "gn:country_code":"RU",
    "gn:dem":311,
    "gn:feature_class":"P",
    "gn:feature_code":"PPL",
    "gn:name":"Baykan",
    "gn:population":0,
    "gn:timezone":"Asia/Krasnoyarsk",
    "iso:country":"RU",
    "name:ceb_x_preferred":[
        "Baykan"
    ],
    "name:deu_x_preferred":[
        "Baykan"
    ],
    "name:fra_x_preferred":[
        "Baykan"
    ],
    "name:kur_x_preferred":[
        "Haw\u00eal"
    ],
    "name:mrj_x_preferred":[
        "\u0411\u0430\u0439\u043a\u0430\u043d"
    ],
    "name:msa_x_preferred":[
        "Baykan"
    ],
    "name:nld_x_preferred":[
        "Baykan"
    ],
    "name:nor_x_preferred":[
        "Bajkan"
    ],
    "name:nor_x_variant":[
        "Baykan"
    ],
    "name:pnb_x_preferred":[
        "\u0636\u0644\u0639 \u0628\u06cc\u06a9\u0627\u0646"
    ],
    "name:rus_x_preferred":[
        "\u0411\u0430\u0439\u043a\u0430\u043d"
    ],
    "name:swa_x_preferred":[
        "Baykan"
    ],
    "name:tur_x_preferred":[
        "Baykan"
    ],
    "name:urd_x_preferred":[
        "\u0628\u06d2\u062e\u0627\u0646"
    ],
    "name:vie_x_preferred":[
        "Baykan"
    ],
    "name:zho_x_preferred":[
        "\u5df4\u4f0a\u574e"
    ],
    "wof:name":"Baykan",
    "wof:placetype":"locality"
},
  "geometry": {"coordinates":[96.38333,56.86666999999999],"type":"Point"}
}