{
  "type": "Feature",
  "properties": {
    "gn:admin1_code":"91",
    "gn:asciiname":"Baykan",
    "gn:country_code":"RU",
    "gn:dem":311,
    "gn:feature_class":"P",
    "gn:feature_code":"PPL",
    "gn:name":"Baykan",
    "gn:population":0,
    "gn:timezone":"Asia/Krasnoyarsk",
    "iso:country":"RU",
    "name:nor_x_preferred":[
        "Bajkan"
    ],
    "name:rus_x_preferred":[
        "\u0411\u0430\u0439\u043a\u0430\u043d"
    ],
    "wof:name":"Baykan",
    "wof:placetype":"locality"
},
  "geometry": {"coordinates":[96.38333,56.86666999999999],"type":"Point"}
}