{
  "type": "Feature",
  "properties": {
    "gn:admin1_code":"51.0",
    "gn:asciiname":"Bol'shaya Rudka",
    "gn:country_code":"RU",
    "gn:dem":157,
    "gn:feature_class":"P",
    "gn:feature_code":"PPL",
    "gn:name":"Bol\u2019shaya Rudka",
    "gn:population":0,
    "gn:timezone":"Europe/Moscow",
    "iso:country":"RU",
    "name:rus_x_preferred":[
        "\u0411\u043e\u043b\u044c\u0448\u0430\u044f \u0420\u0443\u0434\u043a\u0430"
    ],
    "name:und_x_variant":[
        "Bol\u2019shaya Rutka",
        "Bol\u2019shaya Rudka"
    ],
    "wof:name":"Bol'shaya Rudka",
    "wof:placetype":"locality"
},
  "geometry": {"coordinates":[46.72608,57.12334],"type":"Point"}
}