{
  "type": "Feature",
  "properties": {
    "gn:admin1_code":"92",
    "gn:asciiname":"Ust'-Belogolovoye",
    "gn:country_code":"RU",
    "gn:dem":16,
    "gn:feature_class":"P",
    "gn:feature_code":"PPL",
    "gn:name":"Ust\u2019-Belogolovoye",
    "gn:population":0,
    "gn:timezone":"Asia/Kamchatka",
    "iso:country":"RU",
    "wof:name":"Ust'-Belogolovoye",
    "wof:placetype":"locality"
},
  "geometry": {"coordinates":[156.59999999999999,57.05],"type":"Point"}
}