{
  "type": "Feature",
  "properties": {
    "gn:admin1_code":"60",
    "gn:asciiname":"Fedonovo",
    "gn:country_code":"RU",
    "gn:dem":152,
    "gn:feature_class":"P",
    "gn:feature_code":"PPL",
    "gn:name":"Fedonovo",
    "gn:population":0,
    "gn:timezone":"Europe/Moscow",
    "iso:country":"RU",
    "name:rus_x_preferred":[
        "\u0424\u0435\u0434\u043e\u043d\u043e\u0432\u043e"
    ],
    "name:und_x_variant":[
        "\u0424\u0435\u0434\u043e\u043d\u043e\u0432\u043e"
    ],
    "wof:name":"Fedonovo",
    "wof:placetype":"locality"
},
  "geometry": {"coordinates":[29.4384,56.955],"type":"Point"}
}