{
  "type": "Feature",
  "properties": {
    "gn:admin1_code":"45",
    "gn:asciiname":"Mamaykino",
    "gn:country_code":"RU",
    "gn:dem":138,
    "gn:feature_class":"P",
    "gn:feature_code":"PPL",
    "gn:name":"Mamaykino",
    "gn:population":0,
    "gn:timezone":"Europe/Moscow",
    "iso:country":"RU",
    "name:rus_x_preferred":[
        "\u041c\u0430\u043c\u0430\u0439\u043a\u0438\u043d\u043e"
    ],
    "name:und_x_variant":[
        "Mamayeva",
        "Mamaykino",
        "\u041c\u0430\u043c\u0430\u0439\u043a\u0438\u043d\u043e"
    ],
    "wof:name":"Mamaykino",
    "wof:placetype":"locality"
},
  "geometry": {"coordinates":[49.385,56.39],"type":"Point"}
}