{
  "type": "Feature",
  "properties": {
    "gn:admin1_code":"73",
    "gn:asciiname":"Buraly-Chishma",
    "gn:country_code":"RU",
    "gn:dem":238,
    "gn:feature_class":"P",
    "gn:feature_code":"PPL",
    "gn:name":"Buraly-Chishma",
    "gn:population":0,
    "gn:timezone":"Europe/Moscow",
    "iso:country":"RU",
    "name:rus_x_preferred":[
        "\u0411\u0443\u0440\u0430\u043b\u044b-\u0427\u0438\u0448\u043c\u0430"
    ],
    "name:und_x_variant":[
        "\u0411\u0443\u0440\u0430\u043b\u044b-\u0427\u0438\u0448\u043c\u0430"
    ],
    "wof:name":"Buraly-Chishma",
    "wof:placetype":"locality"
},
  "geometry": {"coordinates":[52.4878,55.0855],"type":"Point"}
}