{
  "type": "Feature",
  "properties": {
    "gn:admin1_code":"8",
    "gn:asciiname":"Kuzgun-Akhmerovo",
    "gn:country_code":"RU",
    "gn:dem":537,
    "gn:feature_class":"P",
    "gn:feature_code":"PPL",
    "gn:name":"Kuzgun-Akhmerovo",
    "gn:population":0,
    "gn:timezone":"Asia/Yekaterinburg",
    "iso:country":"RU",
    "name:bak_x_preferred":[
        "\u04a0\u043e\u0499\u0493\u043e\u043d-\u04d8\u0445\u043c\u04d9\u0440"
    ],
    "name:che_x_preferred":[
        "\u041a\u0443\u0437\u0433\u0443\u043d-\u0410\u0445\u043c\u0435\u0440\u043e\u0432\u043e"
    ],
    "name:hye_x_preferred":[
        "\u053f\u0578\u0582\u0566\u0563\u0578\u0582\u0576-\u0531\u056d\u0574\u0565\u0580\u0578\u057e\u0578"
    ],
    "name:kat_x_preferred":[
        "\u10d9\u10e3\u10d6\u10d2\u10e3\u10dc-\u10d0\u10ee\u10db\u10d4\u10e0\u10dd\u10d5\u10dd"
    ],
    "name:kaz_x_preferred":[
        "\u041a\u0443\u0437\u0433\u0443\u043d-\u0410\u0445\u043c\u0435\u0440"
    ],
    "name:rus_x_preferred":[
        "\u041a\u0443\u0437\u0433\u0443\u043d-\u0410\u0445\u043c\u0435\u0440\u043e\u0432\u043e"
    ],
    "name:tat_x_preferred":[
        "\u041a\u043e\u0437\u0433\u044b\u043d-\u04d8\u0445\u043c\u04d9\u0440"
    ],
    "name:ukr_x_preferred":[
        "\u041a\u0443\u0437\u0433\u0443\u043d-\u0410\u0445\u043c\u0435\u0440\u043e\u0432\u043e"
    ],
    "name:und_x_variant":[
        "\u041a\u0443\u0437\u0433\u0443\u043d-\u0410\u0445\u043c\u0435\u0440\u043e\u0432\u043e"
    ],
    "wof:name":"Kuzgun-Akhmerovo",
    "wof:placetype":"locality"
},
  "geometry": {"coordinates":[58.2495,53.9918],"type":"Point"}
}