{
  "type": "Feature",
  "properties": {
    "gn:admin1_code":"8",
    "gn:asciiname":"Kuzgun-Akhmerovo",
    "gn:country_code":"RU",
    "gn:dem":537,
    "gn:feature_class":"P",
    "gn:feature_code":"PPL",
    "gn:name":"Kuzgun-Akhmerovo",
    "gn:population":0,
    "gn:timezone":"Asia/Yekaterinburg",
    "iso:country":"RU",
    "name:rus_x_preferred":[
        "\u041a\u0443\u0437\u0433\u0443\u043d-\u0410\u0445\u043c\u0435\u0440\u043e\u0432\u043e"
    ],
    "name:und_x_variant":[
        "\u041a\u0443\u0437\u0433\u0443\u043d-\u0410\u0445\u043c\u0435\u0440\u043e\u0432\u043e"
    ],
    "wof:name":"Kuzgun-Akhmerovo",
    "wof:placetype":"locality"
},
  "geometry": {"coordinates":[58.2495,53.9918],"type":"Point"}
}