{
  "type": "Feature",
  "properties": {
    "gn:admin1_code":"60",
    "gn:asciiname":"Shlepetnya",
    "gn:country_code":"RU",
    "gn:dem":95,
    "gn:feature_class":"P",
    "gn:feature_code":"PPL",
    "gn:name":"Shlepetnya",
    "gn:population":0,
    "gn:timezone":"Europe/Moscow",
    "iso:country":"RU",
    "name:rus_x_preferred":[
        "\u0428\u043b\u0435\u043f\u0435\u0442\u043d\u044f"
    ],
    "wof:name":"Shlepetnya",
    "wof:placetype":"locality"
},
  "geometry": {"coordinates":[28.73999,56.70584],"type":"Point"}
}