{
  "type": "Feature",
  "properties": {
    "gn:admin1_code":"77",
    "gn:asciiname":"Gorskiy Ostrov",
    "gn:country_code":"RU",
    "gn:dem":240,
    "gn:feature_class":"P",
    "gn:feature_code":"PPL",
    "gn:name":"Gorskiy Ostrov",
    "gn:population":0,
    "gn:timezone":"Europe/Moscow",
    "iso:country":"RU",
    "name:rus_x_preferred":[
        "\u0413\u043e\u0440\u0441\u043a\u0438\u0439 \u041e\u0441\u0442\u0440\u043e\u0432"
    ],
    "wof:name":"Gorskiy Ostrov",
    "wof:placetype":"locality"
},
  "geometry": {"coordinates":[32.64,56.55861],"type":"Point"}
}