{
  "type": "Feature",
  "properties": {
    "gn:admin1_code":"55",
    "gn:asciiname":"Stebnovskiy",
    "gn:country_code":"RU",
    "gn:dem":123,
    "gn:feature_class":"P",
    "gn:feature_code":"PPL",
    "gn:name":"Stebnovskiy",
    "gn:population":0,
    "gn:timezone":"Asia/Yekaterinburg",
    "iso:country":"RU",
    "name:rus_x_preferred":[
        "\u0421\u0442\u0435\u0431\u043d\u043e\u0432\u0441\u043a\u0438\u0439"
    ],
    "name:und_x_variant":[
        "\u0421\u0442\u0435\u0431\u043d\u043e\u0432\u0441\u043a\u0438\u0439"
    ],
    "wof:name":"Stebnovskiy",
    "wof:placetype":"locality"
},
  "geometry": {"coordinates":[52.36667,53.48333],"type":"Point"}
}