{
  "type": "Feature",
  "properties": {
    "gn:admin1_code":"60",
    "gn:asciiname":"Yeniki",
    "gn:country_code":"RU",
    "gn:dem":101,
    "gn:feature_class":"P",
    "gn:feature_code":"PPL",
    "gn:name":"Yeniki",
    "gn:population":0,
    "gn:timezone":"Europe/Moscow",
    "iso:country":"RU",
    "name:lav_x_preferred":[
        "Ioniki"
    ],
    "name:und_x_variant":[
        "Krasnyy Ostrov",
        "Yeniki"
    ],
    "wof:name":"Yeniki",
    "wof:placetype":"locality"
},
  "geometry": {"coordinates":[27.92505,56.76312],"type":"Point"}
}