{
  "type": "Feature",
  "properties": {
    "gn:admin1_code":"88.0",
    "gn:asciiname":"Yurkovo",
    "gn:country_code":"RU",
    "gn:dem":112,
    "gn:feature_class":"P",
    "gn:feature_code":"PPL",
    "gn:name":"Yurkovo",
    "gn:population":0,
    "gn:timezone":"Europe/Moscow",
    "iso:country":"RU",
    "name:che_x_preferred":[
        "\u042e\u0440\u043a\u043e\u0432\u043e"
    ],
    "name:rus_x_preferred":[
        "\u042e\u0440\u043a\u043e\u0432\u043e"
    ],
    "wof:name":"Yurkovo",
    "wof:placetype":"locality"
},
  "geometry": {"coordinates":[40.37592,58.37317],"type":"Point"}
}