{
  "type": "Feature",
  "properties": {
    "gn:admin1_code":"88.0",
    "gn:asciiname":"Bol'shoye Filimonovo",
    "gn:country_code":"RU",
    "gn:dem":91,
    "gn:feature_class":"P",
    "gn:feature_code":"PPL",
    "gn:name":"Bol\u2019shoye Filimonovo",
    "gn:population":0,
    "gn:timezone":"Europe/Moscow",
    "iso:country":"RU",
    "wof:name":"Bol'shoye Filimonovo",
    "wof:placetype":"locality"
},
  "geometry": {"coordinates":[40.04455,57.56424000000001],"type":"Point"}
}