{
  "type": "Feature",
  "properties": {
    "gn:admin1_code":"33",
    "gn:asciiname":"Rvachi",
    "gn:country_code":"RU",
    "gn:dem":130,
    "gn:feature_class":"P",
    "gn:feature_code":"PPL",
    "gn:name":"Rvachi",
    "gn:population":0,
    "gn:timezone":"Europe/Kirov",
    "iso:country":"RU",
    "name:rus_x_preferred":[
        "\u0420\u0432\u0430\u0447\u0438"
    ],
    "name:und_x_variant":[
        "\u0420\u0432\u0430\u0447\u0438"
    ],
    "wof:name":"Rvachi",
    "wof:placetype":"locality"
},
  "geometry": {"coordinates":[48.3425,58.16444],"type":"Point"}
}