{
  "type": "Feature",
  "properties": {
    "gn:admin1_code":"45.0",
    "gn:asciiname":"Byvayenki",
    "gn:country_code":"RU",
    "gn:dem":168,
    "gn:feature_class":"P",
    "gn:feature_code":"PPL",
    "gn:name":"Byvayenki",
    "gn:population":0,
    "gn:timezone":"Europe/Moscow",
    "iso:country":"RU",
    "name:rus_x_preferred":[
        "\u0411\u044b\u0432\u0430\u0435\u043d\u043a\u0438"
    ],
    "name:und_x_variant":[
        "\u0411\u044b\u0432\u0430\u0435\u043d\u043a\u0438"
    ],
    "wof:name":"Byvayenki",
    "wof:placetype":"locality"
},
  "geometry": {"coordinates":[48.63472,56.93833000000001],"type":"Point"}
}