{
  "type": "Feature",
  "properties": {
    "gn:admin1_code":"13",
    "gn:asciiname":"Khudyakovo",
    "gn:country_code":"RU",
    "gn:dem":156,
    "gn:feature_class":"P",
    "gn:feature_code":"PPL",
    "gn:name":"Khudyakovo",
    "gn:population":0,
    "gn:timezone":"Asia/Yekaterinburg",
    "iso:country":"RU",
    "name:rus_x_preferred":[
        "\u0425\u0443\u0434\u044f\u043a\u043e\u0432\u043e"
    ],
    "name:und_x_variant":[
        "Khudyakovo Pervoye",
        "Khudyakovo"
    ],
    "wof:name":"Khudyakovo",
    "wof:placetype":"locality"
},
  "geometry": {"coordinates":[61.7082,55.2771],"type":"Point"}
}