{
  "type": "Feature",
  "properties": {
    "gn:admin1_code":"56",
    "gn:asciiname":"Vasil'yevka Pervaya",
    "gn:country_code":"RU",
    "gn:dem":211,
    "gn:feature_class":"P",
    "gn:feature_code":"PPL",
    "gn:name":"Vasil\u2019yevka Pervaya",
    "gn:population":0,
    "gn:timezone":"Europe/Moscow",
    "iso:country":"RU",
    "name:rus_x_preferred":[
        "\u0412\u0430\u0441\u0438\u043b\u044c\u0435\u0432\u043a\u0430 \u041f\u0435\u0440\u0432\u0430\u044f"
    ],
    "name:und_x_variant":[
        "Kobyl\u00ebnka",
        "Vasil\u2019yevka Pervaya"
    ],
    "wof:name":"Vasil'yevka Pervaya",
    "wof:placetype":"locality"
},
  "geometry": {"coordinates":[36.9333,52.2753],"type":"Point"}
}