{
  "type": "Feature",
  "properties": {
    "gn:admin1_code":"51",
    "gn:asciiname":"Koz'ye Boloto",
    "gn:country_code":"RU",
    "gn:dem":141,
    "gn:feature_class":"P",
    "gn:feature_code":"PPL",
    "gn:name":"Koz\u2019ye Boloto",
    "gn:population":0,
    "gn:timezone":"Europe/Moscow",
    "iso:country":"RU",
    "name:rus_x_preferred":[
        "\u041a\u043e\u0437\u044c\u0435 \u0411\u043e\u043b\u043e\u0442\u043e"
    ],
    "name:und_x_variant":[
        "Kos\u2019ye Boloto",
        "Koz\u2019ye Boloto",
        "\u041a\u043e\u0437\u044c\u0435 \u0411\u043e\u043b\u043e\u0442\u043e"
    ],
    "wof:name":"Koz'ye Boloto",
    "wof:placetype":"locality"
},
  "geometry": {"coordinates":[42.25,55.01667],"type":"Point"}
}