{
  "type": "Feature",
  "properties": {
    "gn:admin1_code":"25",
    "gn:asciiname":"Malistovo",
    "gn:country_code":"RU",
    "gn:dem":225,
    "gn:feature_class":"P",
    "gn:feature_code":"PPL",
    "gn:name":"Malistovo",
    "gn:population":0,
    "gn:timezone":"Europe/Moscow",
    "iso:country":"RU",
    "name:rus_x_preferred":[
        "\u041c\u0430\u043b\u0438\u0441\u0442\u043e\u0432\u043e"
    ],
    "name:und_x_variant":[
        "Mal\u2019stova",
        "Malistovo",
        "\u041c\u0430\u043b\u0438\u0441\u0442\u043e\u0432\u043e"
    ],
    "wof:name":"Malistovo",
    "wof:placetype":"locality"
},
  "geometry": {"coordinates":[34.08992,54.27093000000001],"type":"Point"}
}