{
  "type": "Feature",
  "properties": {
    "gn:admin1_code":"90",
    "gn:asciiname":"Maloye Golyshevo",
    "gn:country_code":"RU",
    "gn:dem":212,
    "gn:feature_class":"P",
    "gn:feature_code":"PPL",
    "gn:name":"Maloye Golyshevo",
    "gn:population":0,
    "gn:timezone":"Asia/Yekaterinburg",
    "iso:country":"RU",
    "name:rus_x_preferred":[
        "\u041c\u0430\u043b\u043e\u0435 \u0413\u043e\u043b\u044b\u0448\u0435\u0432\u043e"
    ],
    "name:und_x_variant":[
        "Malaya Golysh\u00ebva",
        "Maloye Golyshevo"
    ],
    "wof:name":"Maloye Golyshevo",
    "wof:placetype":"locality"
},
  "geometry": {"coordinates":[57.1019,57.6512],"type":"Point"}
}