{
  "type": "Feature",
  "properties": {
    "gn:admin1_code":"84.0",
    "gn:asciiname":"Baranovka",
    "gn:country_code":"RU",
    "gn:dem":28,
    "gn:feature_class":"P",
    "gn:feature_code":"PPL",
    "gn:name":"Baranovka",
    "gn:population":0,
    "gn:timezone":"Europe/Volgograd",
    "iso:country":"RU",
    "name:ceb_x_preferred":[
        "Baranovka"
    ],
    "name:eng_x_preferred":[
        "Baranovka"
    ],
    "name:nor_x_preferred":[
        "Baranovka"
    ],
    "name:rus_x_preferred":[
        "\u0411\u0430\u0440\u0430\u043d\u043e\u0432\u043a\u0430"
    ],
    "name:swe_x_preferred":[
        "Baranovka"
    ],
    "name:und_x_variant":[
        "Knorovka",
        "\u0411\u0430\u0440\u0430\u043d\u043e\u0432\u043a\u0430",
        "Baranovka"
    ],
    "wof:name":"Baranovka",
    "wof:placetype":"locality"
},
  "geometry": {"coordinates":[46.16564,49.9849],"type":"Point"}
}