{
  "type": "Feature",
  "properties": {
    "gn:admin1_code":"85.0",
    "gn:asciiname":"Sjargozero",
    "gn:country_code":"RU",
    "gn:dem":190,
    "gn:feature_class":"P",
    "gn:feature_code":"PPL",
    "gn:name":"Sjargozero",
    "gn:population":0,
    "gn:timezone":"Europe/Moscow",
    "iso:country":"RU",
    "name:fin_x_preferred":[
        "S\u00e4rkij\u00e4rvi"
    ],
    "wof:name":"Sjargozero",
    "wof:placetype":"locality"
},
  "geometry": {"coordinates":[36.01009000000001,60.51912],"type":"Point"}
}