{
  "type": "Feature",
  "properties": {
    "gn:admin1_code":"90",
    "gn:asciiname":"Polva",
    "gn:country_code":"RU",
    "gn:dem":175,
    "gn:feature_class":"P",
    "gn:feature_code":"PPL",
    "gn:name":"Polva",
    "gn:population":0,
    "gn:timezone":"Asia/Yekaterinburg",
    "iso:country":"RU",
    "name:eng_x_preferred":[
        "Polva"
    ],
    "name:nor_x_preferred":[
        "Polva"
    ],
    "name:rus_x_preferred":[
        "\u041f\u043e\u043b\u0432\u0430"
    ],
    "wof:name":"Polva",
    "wof:placetype":"locality"
},
  "geometry": {"coordinates":[54.4623,58.6709],"type":"Point"}
}