{
  "type": "Feature",
  "properties": {
    "gn:admin1_code":"20",
    "gn:asciiname":"Verkhnyaya Zima",
    "gn:country_code":"RU",
    "gn:dem":472,
    "gn:feature_class":"P",
    "gn:feature_code":"PPL",
    "gn:name":"Verkhnyaya Zima",
    "gn:population":0,
    "gn:timezone":"Asia/Irkutsk",
    "iso:country":"RU",
    "name:rus_x_preferred":[
        "\u0412\u0435\u0440\u0445\u043d\u044f\u044f \u0417\u0438\u043c\u0430"
    ],
    "name:und_x_variant":[
        "Verkhne-Ziminskoye",
        "Verkhnyaya Zima"
    ],
    "wof:name":"Verkhnyaya Zima",
    "wof:placetype":"locality"
},
  "geometry": {"coordinates":[101.7831,53.7961],"type":"Point"}
}