{
  "type": "Feature",
  "properties": {
    "gn:admin1_code":"81.0",
    "gn:asciiname":"Beketovka",
    "gn:country_code":"RU",
    "gn:dem":62,
    "gn:feature_class":"P",
    "gn:feature_code":"PPL",
    "gn:name":"Beketovka",
    "gn:population":0,
    "gn:timezone":"Europe/Ulyanovsk",
    "iso:country":"RU",
    "name:eng_x_preferred":[
        "Beketovka"
    ],
    "name:nor_x_preferred":[
        "Beketovka"
    ],
    "name:rus_x_preferred":[
        "\u0411\u0435\u043a\u0435\u0442\u043e\u0432\u043a\u0430"
    ],
    "name:und_x_variant":[
        "\u0411\u0435\u043a\u0435\u0442\u043e\u0432\u043a\u0430",
        "Beketovka"
    ],
    "wof:name":"Beketovka",
    "wof:placetype":"locality"
},
  "geometry": {"coordinates":[49.26667,54.85],"type":"Point"}
}