{
  "type": "Feature",
  "properties": {
    "gn:admin1_code":"69",
    "gn:asciiname":"Fomina",
    "gn:country_code":"RU",
    "gn:dem":210,
    "gn:feature_class":"P",
    "gn:feature_code":"PPL",
    "gn:name":"Fomina",
    "gn:population":0,
    "gn:timezone":"Europe/Moscow",
    "iso:country":"RU",
    "name:rus_x_preferred":[
        "\u0424\u043e\u043c\u0438\u043d\u0430"
    ],
    "name:und_x_variant":[
        "\u0424\u043e\u043c\u0438\u043d\u0430"
    ],
    "wof:name":"Fomina",
    "wof:placetype":"locality"
},
  "geometry": {"coordinates":[33.11683,54.84538000000001],"type":"Point"}
}