{
  "type": "Feature",
  "properties": {
    "gn:admin1_code":"77",
    "gn:asciiname":"Pavlovskoye",
    "gn:country_code":"RU",
    "gn:dem":227,
    "gn:feature_class":"P",
    "gn:feature_code":"PPL",
    "gn:name":"Pavlovskoye",
    "gn:population":0,
    "gn:timezone":"Europe/Moscow",
    "iso:country":"RU",
    "name:rus_x_preferred":[
        "\u041f\u0430\u0432\u043b\u043e\u0432\u0441\u043a\u043e\u0435"
    ],
    "wof:name":"Pavlovskoye",
    "wof:placetype":"locality"
},
  "geometry": {"coordinates":[34.30689,57.16239],"type":"Point"}
}