{
  "type": "Feature",
  "properties": {
    "gn:admin1_code":"42",
    "gn:asciiname":"Rozgrino",
    "gn:country_code":"RU",
    "gn:dem":187,
    "gn:feature_class":"P",
    "gn:feature_code":"PPL",
    "gn:name":"Rozgrino",
    "gn:population":0,
    "gn:timezone":"Europe/Moscow",
    "iso:country":"RU",
    "name:rus_x_preferred":[
        "\u0420\u043e\u0437\u0433\u0440\u0438\u043d\u043e"
    ],
    "wof:name":"Rozgrino",
    "wof:placetype":"locality"
},
  "geometry": {"coordinates":[34.38333,59.85],"type":"Point"}
}