{
  "type": "Feature",
  "properties": {
    "gn:admin1_code":"71",
    "gn:asciiname":"Vaganovo",
    "gn:country_code":"RU",
    "gn:dem":56,
    "gn:feature_class":"P",
    "gn:feature_code":"PPL",
    "gn:name":"Vaganovo",
    "gn:population":0,
    "gn:timezone":"Asia/Yekaterinburg",
    "iso:country":"RU",
    "name:rus_x_preferred":[
        "\u0412\u0430\u0433\u0430\u043d\u043e\u0432\u043e"
    ],
    "name:und_x_variant":[
        "\u0412\u0430\u0433\u0430\u043d\u043e\u0432\u043e"
    ],
    "wof:name":"Vaganovo",
    "wof:placetype":"locality"
},
  "geometry": {"coordinates":[65.52970000000001,57.9795],"type":"Point"}
}