{
  "type": "Feature",
  "properties": {
    "gn:admin1_code":"54",
    "gn:asciiname":"Atak",
    "gn:country_code":"RU",
    "gn:dem":72,
    "gn:feature_class":"P",
    "gn:feature_code":"PPL",
    "gn:name":"Atak",
    "gn:population":0,
    "gn:timezone":"Asia/Omsk",
    "iso:country":"RU",
    "name:eng_x_preferred":[
        "Atak"
    ],
    "name:nor_x_preferred":[
        "Atak"
    ],
    "name:rus_x_preferred":[
        "\u0410\u0442\u0430\u043a"
    ],
    "wof:name":"Atak",
    "wof:placetype":"locality"
},
  "geometry": {"coordinates":[74.6401,56.80438],"type":"Point"}
}