{
  "type": "Feature",
  "properties": {
    "gn:admin1_code":"50.0",
    "gn:asciiname":"Beloshchel'ye",
    "gn:country_code":"RU",
    "gn:dem":39,
    "gn:feature_class":"P",
    "gn:feature_code":"PPL",
    "gn:name":"Beloshchel\u2019ye",
    "gn:population":0,
    "gn:timezone":"Europe/Moscow",
    "iso:country":"RU",
    "name:nor_x_preferred":[
        "Belosjtsjelje"
    ],
    "name:rus_x_preferred":[
        "\u0411\u0435\u043b\u043e\u0449\u0435\u043b\u044c\u0435"
    ],
    "name:und_x_variant":[
        "Beloye Shchel\u2019ve",
        "Beloshchel\u2019ye"
    ],
    "wof:name":"Beloshchel'ye",
    "wof:placetype":"locality"
},
  "geometry": {"coordinates":[47.73333,67.16667],"type":"Point"}
}