{
  "type": "Feature",
  "properties": {
    "gn:admin1_code":"56",
    "gn:asciiname":"Mayaki",
    "gn:country_code":"RU",
    "gn:dem":223,
    "gn:feature_class":"P",
    "gn:feature_code":"PPL",
    "gn:name":"Mayaki",
    "gn:population":0,
    "gn:timezone":"Europe/Moscow",
    "iso:country":"RU",
    "name:rus_x_preferred":[
        "\u041c\u0430\u044f\u043a\u0438"
    ],
    "name:und_x_variant":[
        "\u041c\u0430\u044f\u043a\u0438"
    ],
    "wof:name":"Mayaki",
    "wof:placetype":"locality"
},
  "geometry": {"coordinates":[35.3761,53.01648],"type":"Point"}
}