{
  "type": "Feature",
  "properties": {
    "gn:admin1_code":"50",
    "gn:asciiname":"Shpindler",
    "gn:cc2":"RU",
    "gn:country_code":"RU",
    "gn:dem":-9999,
    "gn:feature_class":"P",
    "gn:feature_code":"PPL",
    "gn:name":"Shpindler",
    "gn:population":0,
    "gn:timezone":"Europe/Moscow",
    "iso:country":"RU",
    "name:rus_x_preferred":[
        "\u0428\u043f\u0438\u043d\u0434\u043b\u0435\u0440"
    ],
    "name:und_x_variant":[
        "Stoybishche Shpindlera",
        "Stanovishche Shpindlera",
        "Shpindler"
    ],
    "wof:name":"Shpindler",
    "wof:placetype":"locality"
},
  "geometry": {"coordinates":[62.66667,69.73333000000001],"type":"Point"}
}