{
  "type": "Feature",
  "properties": {
    "gn:admin1_code":"69",
    "gn:asciiname":"Rokot",
    "gn:country_code":"RU",
    "gn:dem":199,
    "gn:feature_class":"P",
    "gn:feature_code":"PPL",
    "gn:name":"Rokot",
    "gn:population":0,
    "gn:timezone":"Europe/Moscow",
    "iso:country":"RU",
    "name:eng_x_preferred":[
        "Rokot"
    ],
    "name:nor_x_preferred":[
        "Rokot"
    ],
    "name:rus_x_preferred":[
        "\u0420\u043e\u043a\u043e\u0442"
    ],
    "name:und_x_variant":[
        "\u0420\u043e\u043a\u043e\u0442",
        "Rokot"
    ],
    "wof:name":"Rokot",
    "wof:placetype":"locality"
},
  "geometry": {"coordinates":[31.30675,54.98568],"type":"Point"}
}