{
  "type": "Feature",
  "properties": {
    "gn:admin1_code":"69",
    "gn:asciiname":"Rokot",
    "gn:country_code":"RU",
    "gn:dem":199,
    "gn:feature_class":"P",
    "gn:feature_code":"PPL",
    "gn:name":"Rokot",
    "gn:population":0,
    "gn:timezone":"Europe/Moscow",
    "iso:country":"RU",
    "name:ara_x_preferred":[
        "\u0635\u0627\u0631\u0648\u062e \u0631\u0648\u0643\u0648\u062a"
    ],
    "name:bul_x_preferred":[
        "\u0420\u043e\u043a\u043e\u0442"
    ],
    "name:cat_x_preferred":[
        "R\u00f3kot"
    ],
    "name:ces_x_preferred":[
        "Rokot"
    ],
    "name:deu_x_preferred":[
        "Rockot"
    ],
    "name:eng_x_preferred":[
        "Rokot"
    ],
    "name:fin_x_preferred":[
        "Rockot"
    ],
    "name:fra_x_preferred":[
        "Rockot"
    ],
    "name:glg_x_preferred":[
        "Rokot"
    ],
    "name:hrv_x_preferred":[
        "Rokot"
    ],
    "name:hun_x_preferred":[
        "Rokot"
    ],
    "name:ind_x_preferred":[
        "Rokot"
    ],
    "name:ita_x_preferred":[
        "Rokot"
    ],
    "name:jpn_x_preferred":[
        "\u30ed\u30b3\u30c3\u30c8"
    ],
    "name:mal_x_preferred":[
        "\u0d31\u0d4b\u0d15\u0d4d\u0d15\u0d4b\u0d1f\u0d4d\u0d1f\u0d4d"
    ],
    "name:nld_x_preferred":[
        "Rokot"
    ],
    "name:nor_x_preferred":[
        "Rokot"
    ],
    "name:pol_x_preferred":[
        "Rokot"
    ],
    "name:por_x_preferred":[
        "Rokot"
    ],
    "name:rus_x_preferred":[
        "\u0420\u043e\u043a\u043e\u0442"
    ],
    "name:slv_x_preferred":[
        "Rokot"
    ],
    "name:spa_x_preferred":[
        "Rokot"
    ],
    "name:tur_x_preferred":[
        "Rokot"
    ],
    "name:ukr_x_preferred":[
        "\u0420\u043e\u043a\u043e\u0442"
    ],
    "name:und_x_variant":[
        "\u0420\u043e\u043a\u043e\u0442",
        "Rokot"
    ],
    "name:zho_x_preferred":[
        "\u547c\u5578\u8fd0\u8f7d\u706b\u7bad"
    ],
    "wof:name":"Rokot",
    "wof:placetype":"locality"
},
  "geometry": {"coordinates":[31.30675,54.98568],"type":"Point"}
}