{
  "type": "Feature",
  "properties": {
    "gn:country":"RU",
    "gn:fcode":"PPL",
    "gn:population":3209,
    "iso:country":"RU",
    "name:che_x_preferred":[
        "\u015eaman-Yurt"
    ],
    "name:che_x_variant":[
        "\u015eawmin-Yurt",
        "\u0428\u0430\u0406\u043c\u0438\u043d-\u042e\u0440\u0442",
        "\u0428\u0430\u043c\u0430\u043d-\u042e\u0440\u0442"
    ],
    "name:nor_x_preferred":[
        "Sjaami-Jurt"
    ],
    "name:rus_x_preferred":[
        "\u0428\u0430\u0430\u043c\u0438-\u042e\u0440\u0442"
    ],
    "name:rus_x_variant":[
        "\u0160aami-Jurt",
        "Zel\u00ebnaja Ro\u0161\u010da",
        "\u0417\u0435\u043b\u0451\u043d\u0430\u044f \u0420\u043e\u0449\u0430"
    ],
    "name:und_x_variant":[
        "Zel\u00ebnaya Roshcha"
    ],
    "qs:name":"Shaami-Yurt",
    "qs:name_adm0":"Russia",
    "qs:name_adm1":"Chechnya Republic",
    "qs:photos_9r":0,
    "qs:photos_sr":0,
    "qs:placetype":"Town",
    "qs:pop_sr":"4",
    "wof:name":"Shaami-Yurt",
    "wof:placetype":"locality",
    "wof:population":3209
},
  "geometry": {"coordinates":[45.39203,43.22632],"type":"Point"}
}