{
  "type": "Feature",
  "properties": {
    "gn:admin1_code":"56",
    "gn:asciiname":"Kromskoy",
    "gn:country_code":"RU",
    "gn:dem":240,
    "gn:feature_class":"P",
    "gn:feature_code":"PPL",
    "gn:name":"Kromskoy",
    "gn:population":0,
    "gn:timezone":"Europe/Moscow",
    "iso:country":"RU",
    "name:rus_x_preferred":[
        "\u041a\u0440\u043e\u043c\u0441\u043a\u043e\u0439"
    ],
    "wof:name":"Kromskoy",
    "wof:placetype":"locality"
},
  "geometry": {"coordinates":[35.7613,52.6329],"type":"Point"}
}