{
  "type": "Feature",
  "properties": {
    "gn:admin1_code":"72.0",
    "gn:asciiname":"Arkad'yevka",
    "gn:country_code":"RU",
    "gn:dem":157,
    "gn:feature_class":"P",
    "gn:feature_code":"PPL",
    "gn:name":"Arkad\u2019yevka",
    "gn:population":0,
    "gn:timezone":"Europe/Moscow",
    "iso:country":"RU",
    "name:nor_x_preferred":[
        "Arkadjevka"
    ],
    "name:rus_x_preferred":[
        "\u0410\u0440\u043a\u0430\u0434\u044c\u0435\u0432\u043a\u0430"
    ],
    "name:und_x_variant":[
        "Arkad\u2019yevka"
    ],
    "wof:name":"Arkad'yevka",
    "wof:placetype":"locality"
},
  "geometry": {"coordinates":[40.5675,53.09721999999999],"type":"Point"}
}