{
  "type": "Feature",
  "properties": {
    "gn:admin1_code":"21",
    "gn:asciiname":"Leont'yevo",
    "gn:country_code":"RU",
    "gn:dem":139,
    "gn:feature_class":"P",
    "gn:feature_code":"PPL",
    "gn:name":"Leont\u2019yevo",
    "gn:population":0,
    "gn:timezone":"Europe/Moscow",
    "iso:country":"RU",
    "name:rus_x_preferred":[
        "\u041b\u0435\u043e\u043d\u0442\u044c\u0435\u0432\u043e"
    ],
    "name:und_x_variant":[
        "Leont\u2019yevo",
        "\u041b\u0435\u043e\u043d\u0442\u044c\u0435\u0432\u043e"
    ],
    "wof:name":"Leont'yevo",
    "wof:placetype":"locality"
},
  "geometry": {"coordinates":[40.71667,57.23333],"type":"Point"}
}