{
  "type": "Feature",
  "properties": {
    "gn:admin1_code":"16.0",
    "gn:asciiname":"Bol'shiye Mamyshi",
    "gn:country_code":"RU",
    "gn:dem":154,
    "gn:feature_class":"P",
    "gn:feature_code":"PPL",
    "gn:name":"Bol\u2019shiye Mamyshi",
    "gn:population":0,
    "gn:timezone":"Europe/Moscow",
    "iso:country":"RU",
    "name:rus_x_preferred":[
        "\u0411\u043e\u043b\u044c\u0448\u0438\u0435 \u041c\u0430\u043c\u044b\u0448\u0438"
    ],
    "name:und_x_variant":[
        "Bol\u2019shiye Mamyshi",
        "\u0411\u043e\u043b\u044c\u0448\u0438\u0435 \u041c\u0430\u043c\u044b\u0448\u0438"
    ],
    "wof:name":"Bol'shiye Mamyshi",
    "wof:placetype":"locality"
},
  "geometry": {"coordinates":[46.95988,55.96393000000001],"type":"Point"}
}