{
  "type": "Feature",
  "properties": {
    "gn:admin1_code":"86",
    "gn:asciiname":"Kocherga",
    "gn:country_code":"RU",
    "gn:dem":88,
    "gn:feature_class":"P",
    "gn:feature_code":"PPL",
    "gn:name":"Kocherga",
    "gn:population":0,
    "gn:timezone":"Europe/Moscow",
    "iso:country":"RU",
    "name:eng_x_preferred":[
        "Kocherga"
    ],
    "name:nor_x_preferred":[
        "Kotsjerga"
    ],
    "name:rus_x_preferred":[
        "\u041a\u043e\u0447\u0435\u0440\u0433\u0430"
    ],
    "wof:name":"Kocherga",
    "wof:placetype":"locality"
},
  "geometry": {"coordinates":[41.54889,51.08],"type":"Point"}
}