{
  "type": "Feature",
  "properties": {
    "gn:admin1_code":"42",
    "gn:asciiname":"Nizino",
    "gn:country_code":"RU",
    "gn:dem":13,
    "gn:feature_class":"P",
    "gn:feature_code":"PPL",
    "gn:name":"Nizino",
    "gn:population":0,
    "gn:timezone":"Europe/Moscow",
    "iso:country":"RU",
    "name:rus_x_preferred":[
        "\u041d\u0438\u0437\u0438\u043d\u043e"
    ],
    "name:und_x_variant":[
        "\u041d\u0438\u0437\u0438\u043d\u043e"
    ],
    "wof:name":"Nizino",
    "wof:placetype":"locality"
},
  "geometry": {"coordinates":[32.64243,60.17699],"type":"Point"}
}