{
  "type": "Feature",
  "properties": {
    "gn:admin1_code":"43",
    "gn:asciiname":"Krasnaya Pal'na",
    "gn:country_code":"RU",
    "gn:dem":171,
    "gn:feature_class":"P",
    "gn:feature_code":"PPL",
    "gn:name":"Krasnaya Pal\u2019na",
    "gn:population":0,
    "gn:timezone":"Europe/Moscow",
    "iso:country":"RU",
    "name:rus_x_preferred":[
        "\u041a\u0440\u0430\u0441\u043d\u0430\u044f \u041f\u0430\u043b\u044c\u043d\u0430"
    ],
    "name:und_x_variant":[
        "Krasnaya Polyana",
        "Krasnaya Pol\u2019na",
        "Krasnaya Pal\u2019na"
    ],
    "wof:name":"Krasnaya Pal'na",
    "wof:placetype":"locality"
},
  "geometry": {"coordinates":[38.49457,52.88668000000001],"type":"Point"}
}