{
  "type": "Feature",
  "properties": {
    "gn:admin1_code":"52",
    "gn:asciiname":"Kluksovo",
    "gn:country_code":"RU",
    "gn:dem":63,
    "gn:feature_class":"P",
    "gn:feature_code":"PPL",
    "gn:name":"Kluksovo",
    "gn:population":0,
    "gn:timezone":"Europe/Moscow",
    "iso:country":"RU",
    "name:rus_x_preferred":[
        "\u041a\u043b\u0443\u043a\u0441\u043e\u0432\u043e"
    ],
    "wof:name":"Kluksovo",
    "wof:placetype":"locality"
},
  "geometry": {"coordinates":[32.0495,57.7025],"type":"Point"}
}