{
  "type": "Feature",
  "properties": {
    "gn:admin1_code":"85.0",
    "gn:asciiname":"Bakurskoye",
    "gn:country_code":"RU",
    "gn:dem":161,
    "gn:feature_class":"P",
    "gn:feature_code":"PPL",
    "gn:name":"Bakurskoye",
    "gn:population":0,
    "gn:timezone":"Europe/Moscow",
    "iso:country":"RU",
    "name:nor_x_preferred":[
        "Bakurskoje"
    ],
    "name:rus_x_preferred":[
        "\u0411\u0430\u043a\u0443\u0440\u0441\u043a\u043e\u0435"
    ],
    "wof:name":"Bakurskoye",
    "wof:placetype":"locality"
},
  "geometry": {"coordinates":[41.07991,59.61122],"type":"Point"}
}