{
  "type": "Feature",
  "properties": {
    "gn:admin1_code":"20",
    "gn:asciiname":"Ranovskaya",
    "gn:country_code":"RU",
    "gn:dem":497,
    "gn:feature_class":"P",
    "gn:feature_code":"PPL",
    "gn:name":"Ranovskaya",
    "gn:population":0,
    "gn:timezone":"Asia/Irkutsk",
    "iso:country":"RU",
    "name:und_x_variant":[
        "Pos\u00eblok Zabituy",
        "Ranovskaya"
    ],
    "wof:name":"Ranovskaya",
    "wof:placetype":"locality"
},
  "geometry": {"coordinates":[102.83333,53.28333000000001],"type":"Point"}
}