{
  "type": "Feature",
  "properties": {
    "gn:admin1_code":"33.0",
    "gn:asciiname":"Andryushkino",
    "gn:country_code":"RU",
    "gn:dem":119,
    "gn:feature_class":"P",
    "gn:feature_code":"PPL",
    "gn:name":"Andryushkino",
    "gn:population":0,
    "gn:timezone":"Europe/Kirov",
    "iso:country":"RU",
    "name:nor_x_preferred":[
        "Andrjusjkino"
    ],
    "name:rus_x_preferred":[
        "\u0410\u043d\u0434\u0440\u044e\u0448\u043a\u0438\u043d\u043e"
    ],
    "name:und_x_variant":[
        "Andrushkino",
        "Andryushkino"
    ],
    "wof:name":"Andryushkino",
    "wof:placetype":"locality"
},
  "geometry": {"coordinates":[50.93928,57.09823000000001],"type":"Point"}
}