{
  "type": "Feature",
  "properties": {
    "gn:admin1_code":"33",
    "gn:asciiname":"Moiseyeva Gora",
    "gn:country_code":"RU",
    "gn:dem":111,
    "gn:feature_class":"P",
    "gn:feature_code":"PPL",
    "gn:name":"Moiseyeva Gora",
    "gn:population":0,
    "gn:timezone":"Europe/Kirov",
    "iso:country":"RU",
    "name:rus_x_preferred":[
        "\u041c\u043e\u0438\u0441\u0435\u0435\u0432\u0430 \u0413\u043e\u0440\u0430"
    ],
    "name:und_x_variant":[
        "Gorka",
        "Moiseyeva Gora"
    ],
    "wof:name":"Moiseyeva Gora",
    "wof:placetype":"locality"
},
  "geometry": {"coordinates":[48.06822,60.56563000000001],"type":"Point"}
}