{
  "type": "Feature",
  "properties": {
    "gn:admin1_code":"4",
    "gn:asciiname":"Pereyaslavka",
    "gn:country_code":"RU",
    "gn:dem":217,
    "gn:feature_class":"P",
    "gn:feature_code":"PPL",
    "gn:name":"Pereyaslavka",
    "gn:population":0,
    "gn:timezone":"Asia/Barnaul",
    "iso:country":"RU",
    "name:bel_x_preferred":[
        "\u041f\u0435\u0440\u0430\u044f\u0441\u043b\u0430\u045e\u043a\u0430"
    ],
    "name:che_x_preferred":[
        "\u041f\u0435\u0440\u0435\u044f\u0441\u043b\u0430\u0432\u043a\u0430"
    ],
    "name:deu_x_preferred":[
        "Perejaslawka"
    ],
    "name:hye_x_preferred":[
        "\u054a\u0565\u0580\u0565\u0575\u0561\u057d\u056c\u0561\u057e\u056f\u0561"
    ],
    "name:jpn_x_preferred":[
        "\u30da\u30ec\u30e4\u30fc\u30b9\u30e9\u30d5\u30ab"
    ],
    "name:rus_x_preferred":[
        "\u041f\u0435\u0440\u0435\u044f\u0441\u043b\u0430\u0432\u043a\u0430"
    ],
    "wof:name":"Pereyaslavka",
    "wof:placetype":"locality"
},
  "geometry": {"coordinates":[83.101,52.8802],"type":"Point"}
}