{
  "type": "Feature",
  "properties": {
    "gn:admin1_code":"4",
    "gn:asciiname":"Pereyaslavka",
    "gn:country_code":"RU",
    "gn:dem":217,
    "gn:feature_class":"P",
    "gn:feature_code":"PPL",
    "gn:name":"Pereyaslavka",
    "gn:population":0,
    "gn:timezone":"Asia/Barnaul",
    "iso:country":"RU",
    "name:rus_x_preferred":[
        "\u041f\u0435\u0440\u0435\u044f\u0441\u043b\u0430\u0432\u043a\u0430"
    ],
    "wof:name":"Pereyaslavka",
    "wof:placetype":"locality"
},
  "geometry": {"coordinates":[83.101,52.8802],"type":"Point"}
}