{
  "type": "Feature",
  "properties": {
    "gn:admin1_code":"30",
    "gn:asciiname":"Dzhari",
    "gn:country_code":"RU",
    "gn:dem":43,
    "gn:feature_class":"P",
    "gn:feature_code":"PPL",
    "gn:name":"Dzhari",
    "gn:population":0,
    "gn:timezone":"Asia/Vladivostok",
    "iso:country":"RU",
    "name:rus_x_preferred":[
        "\u0414\u0436\u0430\u0440\u0438"
    ],
    "wof:name":"Dzhari",
    "wof:placetype":"locality"
},
  "geometry": {"coordinates":[136.51886000000002,49.43795],"type":"Point"}
}