{
  "type": "Feature",
  "properties": {
    "gn:admin1_code":"55",
    "gn:asciiname":"Malogasvitskoye",
    "gn:country_code":"RU",
    "gn:dem":82,
    "gn:feature_class":"P",
    "gn:feature_code":"PPL",
    "gn:name":"Malogasvitskoye",
    "gn:population":0,
    "gn:timezone":"Asia/Yekaterinburg",
    "iso:country":"RU",
    "name:rus_x_preferred":[
        "\u041c\u0430\u043b\u043e\u0433\u0430\u0441\u0432\u0438\u0446\u043a\u043e\u0435"
    ],
    "name:und_x_variant":[
        "Malo Gosvitskoye",
        "Malogasvitskoye",
        "\u041c\u0430\u043b\u043e\u0433\u0430\u0441\u0432\u0438\u0446\u043a\u043e\u0435"
    ],
    "wof:name":"Malogasvitskoye",
    "wof:placetype":"locality"
},
  "geometry": {"coordinates":[52.57773,52.90861],"type":"Point"}
}