{
  "type": "Feature",
  "properties": {
    "gn:admin1_code":"29",
    "gn:asciiname":"Udarnyy",
    "gn:country_code":"RU",
    "gn:dem":587,
    "gn:feature_class":"P",
    "gn:feature_code":"PPL",
    "gn:name":"Udarnyy",
    "gn:population":0,
    "gn:timezone":"Asia/Novokuznetsk",
    "iso:country":"RU",
    "name:eng_x_preferred":[
        "Udarnyy"
    ],
    "name:nor_x_preferred":[
        "Udarnyj"
    ],
    "name:rus_x_preferred":[
        "\u0423\u0434\u0430\u0440\u043d\u044b\u0439"
    ],
    "wof:name":"Udarnyy",
    "wof:placetype":"locality"
},
  "geometry": {"coordinates":[88.15000000000001,55.03333000000001],"type":"Point"}
}