{
  "type": "Feature",
  "properties": {
    "gn:admin1_code":"85",
    "gn:asciiname":"Yarilovo",
    "gn:country_code":"RU",
    "gn:dem":145,
    "gn:feature_class":"P",
    "gn:feature_code":"PPL",
    "gn:name":"Yarilovo",
    "gn:population":0,
    "gn:timezone":"Europe/Moscow",
    "iso:country":"RU",
    "name:rus_x_preferred":[
        "\u042f\u0440\u0438\u043b\u043e\u0432\u043e"
    ],
    "wof:name":"Yarilovo",
    "wof:placetype":"locality"
},
  "geometry": {"coordinates":[39.9524,59.1717],"type":"Point"}
}