{
  "type": "Feature",
  "properties": {
    "gn:admin1_code":"47",
    "gn:asciiname":"Verkhneye Khoroshevo",
    "gn:country_code":"RU",
    "gn:dem":153,
    "gn:feature_class":"P",
    "gn:feature_code":"PPL",
    "gn:name":"Verkhneye Khoroshevo",
    "gn:population":0,
    "gn:timezone":"Europe/Moscow",
    "iso:country":"RU",
    "name:und_x_variant":[
        "Verkheye Khoroshevo",
        "Verkhneye Khoroshevo"
    ],
    "wof:name":"Verkhneye Khoroshevo",
    "wof:placetype":"locality"
},
  "geometry": {"coordinates":[38.64633,55.08866999999999],"type":"Point"}
}