{
  "type": "Feature",
  "properties": {
    "gn:admin1_code":"91",
    "gn:asciiname":"Verkhniy Ingash",
    "gn:country_code":"RU",
    "gn:dem":292,
    "gn:feature_class":"P",
    "gn:feature_code":"PPL",
    "gn:name":"Verkhniy Ingash",
    "gn:population":0,
    "gn:timezone":"Asia/Krasnoyarsk",
    "iso:country":"RU",
    "name:eng_x_preferred":[
        "Verkhniy Ingash"
    ],
    "name:rus_x_preferred":[
        "\u0412\u0435\u0440\u0445.\u0438\u043d\u0433\u0430\u0448"
    ],
    "name:rus_x_variant":[
        "\u0412\u0435\u0440\u0445.\u0418\u043d\u0433\u0430\u0448",
        "\u0412\u0435\u0440\u0445\u043d\u0438\u0439 \u0418\u043d\u0433\u0430\u0448"
    ],
    "wof:name":"Verkhniy Ingash",
    "wof:placetype":"locality"
},
  "geometry": {"coordinates":[96.43640000000001,56.2073],"type":"Point"}
}