{
  "type": "Feature",
  "properties": {
    "gn:admin1_code":"20",
    "gn:asciiname":"Kanegir",
    "gn:country_code":"RU",
    "gn:dem":491,
    "gn:feature_class":"P",
    "gn:feature_code":"PPL",
    "gn:name":"Kanegir",
    "gn:population":0,
    "gn:timezone":"Asia/Irkutsk",
    "iso:country":"RU",
    "name:rus_x_preferred":[
        "\u041a\u0430\u043d\u0435\u0433\u0438\u0440"
    ],
    "wof:name":"Kanegir",
    "wof:placetype":"locality"
},
  "geometry": {"coordinates":[102.25,54.35],"type":"Point"}
}