{
  "type": "Feature",
  "properties": {
    "gn:admin1_code":"91",
    "gn:asciiname":"Stan Mironovskiy Pervyy",
    "gn:cc2":"RU",
    "gn:country_code":"RU",
    "gn:dem":26,
    "gn:feature_class":"P",
    "gn:feature_code":"PPL",
    "gn:name":"Stan Mironovskiy Pervyy",
    "gn:population":0,
    "gn:timezone":"Asia/Krasnoyarsk",
    "iso:country":"RU",
    "name:rus_x_preferred":[
        "\u0421\u0442\u0430\u043d \u041c\u0438\u0440\u043e\u043d\u043e\u0432\u0441\u043a\u0438\u0439 \u041f\u0435\u0440\u0432\u044b\u0439"
    ],
    "name:und_x_variant":[
        "Mironovskiy",
        "Stan Mironovskiy",
        "Stan Mironovskiy Pervyy"
    ],
    "wof:name":"Stan Mironovskiy Pervyy",
    "wof:placetype":"locality"
},
  "geometry": {"coordinates":[95.25,71.08333],"type":"Point"}
}