{
  "type": "Feature",
  "properties": {
    "gn:admin1_code":"85.0",
    "gn:asciiname":"Davydovskaya",
    "gn:country_code":"RU",
    "gn:dem":139,
    "gn:feature_class":"P",
    "gn:feature_code":"PPL",
    "gn:name":"Davydovskaya",
    "gn:population":0,
    "gn:timezone":"Europe/Moscow",
    "iso:country":"RU",
    "name:rus_x_preferred":[
        "\u0414\u0430\u0432\u044b\u0434\u043e\u0432\u0441\u043a\u0430\u044f"
    ],
    "name:und_x_variant":[
        "\u0414\u0430\u0432\u044b\u0434\u043e\u0432\u0441\u043a\u0430\u044f"
    ],
    "wof:name":"Davydovskaya",
    "wof:placetype":"locality"
},
  "geometry": {"coordinates":[41.09551,60.15436999999999],"type":"Point"}
}