{
  "type": "Feature",
  "properties": {
    "gn:admin1_code":"88",
    "gn:asciiname":"Rechkovo",
    "gn:country_code":"RU",
    "gn:dem":110,
    "gn:feature_class":"P",
    "gn:feature_code":"PPL",
    "gn:name":"Rechkovo",
    "gn:population":0,
    "gn:timezone":"Europe/Moscow",
    "iso:country":"RU",
    "name:rus_x_preferred":[
        "\u0420\u0435\u0447\u043a\u043e\u0432\u043e"
    ],
    "name:und_x_variant":[
        "\u0420\u0435\u0447\u043a\u043e\u0432\u043e"
    ],
    "wof:name":"Rechkovo",
    "wof:placetype":"locality"
},
  "geometry": {"coordinates":[38.2595,57.8462],"type":"Point"}
}