{
  "type": "Feature",
  "properties": {
    "gn:admin1_code":"52.0",
    "gn:asciiname":"Berezovka",
    "gn:country_code":"RU",
    "gn:dem":201,
    "gn:feature_class":"P",
    "gn:feature_code":"PPL",
    "gn:name":"Ber\u00ebzovka",
    "gn:population":100,
    "gn:timezone":"Europe/Moscow",
    "iso:country":"RU",
    "name:eng_x_preferred":[
        "Ber\u00ebzovka"
    ],
    "name:rus_x_preferred":[
        "\u0411\u0435\u0440\u0435\u0437\u043e\u0432\u043a\u0430"
    ],
    "name:rus_x_variant":[
        "\u0411\u0435\u0440\u0451\u0437\u043e\u0432\u043a\u0430"
    ],
    "name:und_x_variant":[
        "Ber\u00ebzovka"
    ],
    "wof:name":"Berezovka",
    "wof:placetype":"locality",
    "wof:population":100
},
  "geometry": {"coordinates":[33.473,58.21925],"type":"Point"}
}