{
  "type": "Feature",
  "properties": {
    "gn:admin1_code":"9.0",
    "gn:asciiname":"Chervona Dibrovka",
    "gn:country_code":"RU",
    "gn:dem":128,
    "gn:feature_class":"P",
    "gn:feature_code":"PPL",
    "gn:name":"Chervona Dibrovka",
    "gn:population":0,
    "gn:timezone":"Europe/Moscow",
    "iso:country":"RU",
    "name:rus_x_preferred":[
        "\u0427\u0435\u0440\u0432\u043e\u043d\u0430 \u0414\u0438\u0431\u0440\u043e\u0432\u043a\u0430"
    ],
    "name:und_x_variant":[
        "Chervonnaya Dubravka",
        "Chervona Dibrovka"
    ],
    "wof:name":"Chervona Dibrovka",
    "wof:placetype":"locality"
},
  "geometry": {"coordinates":[37.2828,50.5264],"type":"Point"}
}