{
  "type": "Feature",
  "properties": {
    "gn:admin1_code":"40",
    "gn:asciiname":"Khokhly",
    "gn:country_code":"RU",
    "gn:dem":172,
    "gn:feature_class":"P",
    "gn:feature_code":"PPL",
    "gn:name":"Khokhly",
    "gn:population":0,
    "gn:timezone":"Asia/Yekaterinburg",
    "iso:country":"RU",
    "name:eng_x_preferred":[
        "Khokhly"
    ],
    "name:nor_x_preferred":[
        "Khokhly"
    ],
    "name:rus_x_preferred":[
        "\u0425\u043e\u0445\u043b\u044b"
    ],
    "wof:name":"Khokhly",
    "wof:placetype":"locality"
},
  "geometry": {"coordinates":[63.48611,55.23721999999999],"type":"Point"}
}