{
  "type": "Feature",
  "properties": {
    "gn:admin1_code":"47",
    "gn:asciiname":"Poryadino",
    "gn:cc2":"RU",
    "gn:country_code":"RU",
    "gn:dem":192,
    "gn:feature_class":"P",
    "gn:feature_code":"PPL",
    "gn:name":"Poryadino",
    "gn:population":0,
    "gn:timezone":"Europe/Moscow",
    "iso:country":"RU",
    "name:rus_x_preferred":[
        "\u041f\u043e\u0440\u044f\u0434\u0438\u043d\u043e"
    ],
    "name:und_x_variant":[
        "Poryadine",
        "Poryadino"
    ],
    "wof:name":"Poryadino",
    "wof:placetype":"locality"
},
  "geometry": {"coordinates":[36.515,55.31667],"type":"Point"}
}