{
  "type": "Feature",
  "properties": {
    "gn:admin1_code":"33.0",
    "gn:asciiname":"Susany",
    "gn:country_code":"RU",
    "gn:dem":141,
    "gn:feature_class":"P",
    "gn:feature_code":"PPL",
    "gn:name":"Susany",
    "gn:population":0,
    "gn:timezone":"Europe/Kirov",
    "iso:country":"RU",
    "name:rus_x_preferred":[
        "\u0421\u0443\u0441\u0430\u043d\u044b"
    ],
    "wof:name":"Susany",
    "wof:placetype":"locality"
},
  "geometry": {"coordinates":[51.0484,58.0722],"type":"Point"}
}