{
  "type": "Feature",
  "properties": {
    "gn:admin1_code":"60.0",
    "gn:asciiname":"Artemy",
    "gn:country_code":"RU",
    "gn:dem":57,
    "gn:feature_class":"P",
    "gn:feature_code":"PPL",
    "gn:name":"Artemy",
    "gn:population":0,
    "gn:timezone":"Europe/Moscow",
    "iso:country":"RU",
    "name:nor_x_preferred":[
        "Artemy"
    ],
    "name:rus_x_preferred":[
        "\u0410\u0440\u0442\u0435\u043c\u044b"
    ],
    "wof:name":"Artemy",
    "wof:placetype":"locality"
},
  "geometry": {"coordinates":[28.05794,57.29957],"type":"Point"}
}