{
  "type": "Feature",
  "properties": {
    "gn:admin1_code":"78",
    "gn:asciiname":"Dronova",
    "gn:country_code":"RU",
    "gn:dem":138,
    "gn:feature_class":"P",
    "gn:feature_code":"PPL",
    "gn:name":"Dronova",
    "gn:population":0,
    "gn:timezone":"Asia/Yekaterinburg",
    "iso:country":"RU",
    "name:eng_x_preferred":[
        "Dronova"
    ],
    "name:nor_x_preferred":[
        "Dronova"
    ],
    "name:rus_x_preferred":[
        "\u0414\u0440\u043e\u043d\u043e\u0432\u0430"
    ],
    "name:rus_x_variant":[
        "\u0414\u0440\u043e\u043d\u043e\u0432\u043e"
    ],
    "name:und_x_variant":[
        "Dronovo"
    ],
    "wof:name":"Dronova",
    "wof:placetype":"locality"
},
  "geometry": {"coordinates":[66.7529,56.35358000000001],"type":"Point"}
}