{
  "type": "Feature",
  "properties": {
    "gn:admin1_code":"61.0",
    "gn:asciiname":"Chernikov",
    "gn:country_code":"RU",
    "gn:dem":187,
    "gn:feature_class":"P",
    "gn:feature_code":"PPL",
    "gn:name":"Chernikov",
    "gn:population":0,
    "gn:timezone":"Europe/Moscow",
    "iso:country":"RU",
    "name:rus_x_preferred":[
        "\u0427\u0435\u0440\u043d\u0438\u043a\u043e\u0432"
    ],
    "name:ukr_x_preferred":[
        "Chernykov"
    ],
    "name:und_x_variant":[
        "\u0427\u0435\u0440\u043d\u0438\u043a\u043e\u0432"
    ],
    "wof:name":"Chernikov",
    "wof:placetype":"locality"
},
  "geometry": {"coordinates":[39.77654,47.82173],"type":"Point"}
}