{
  "type": "Feature",
  "properties": {
    "gn:admin1_code":"41",
    "gn:asciiname":"Sredniye Apochki",
    "gn:country_code":"RU",
    "gn:dem":171,
    "gn:feature_class":"P",
    "gn:feature_code":"PPL",
    "gn:name":"Sredniye Apochki",
    "gn:population":0,
    "gn:timezone":"Europe/Moscow",
    "iso:country":"RU",
    "name:rus_x_preferred":[
        "\u0421\u0440\u0435\u0434\u043d\u0438\u0435 \u0410\u043f\u043e\u0447\u043a\u0438"
    ],
    "wof:name":"Sredniye Apochki",
    "wof:placetype":"locality"
},
  "geometry": {"coordinates":[37.686,51.5216],"type":"Point"}
}