{
  "type": "Feature",
  "properties": {
    "gn:admin1_code":"61",
    "gn:asciiname":"Novaya Nadezhda",
    "gn:country_code":"RU",
    "gn:dem":165,
    "gn:feature_class":"P",
    "gn:feature_code":"PPL",
    "gn:name":"Novaya Nadezhda",
    "gn:population":0,
    "gn:timezone":"Europe/Moscow",
    "iso:country":"RU",
    "name:eng_x_preferred":[
        "Novaya Nadezhda"
    ],
    "name:nor_x_preferred":[
        "Novaja Nadezjda"
    ],
    "name:rus_x_preferred":[
        "\u041d\u043e\u0432\u0430\u044f \u041d\u0430\u0434\u0435\u0436\u0434\u0430"
    ],
    "name:und_x_variant":[
        "\u041d\u043e\u0432\u0430\u044f \u041d\u0430\u0434\u0435\u0436\u0434\u0430",
        "Novaya Nadezhda"
    ],
    "wof:name":"Novaya Nadezhda",
    "wof:placetype":"locality"
},
  "geometry": {"coordinates":[39.07556,47.84444000000001],"type":"Point"}
}