{
  "type": "Feature",
  "properties": {
    "gn:admin1_code":"76.0",
    "gn:asciiname":"Chentsovy Dvory",
    "gn:country_code":"RU",
    "gn:dem":230,
    "gn:feature_class":"P",
    "gn:feature_code":"PPL",
    "gn:name":"Chentsovy Dvory",
    "gn:population":0,
    "gn:timezone":"Europe/Moscow",
    "iso:country":"RU",
    "name:eng_x_preferred":[
        "Chentsovy Dvory"
    ],
    "name:nor_x_preferred":[
        "Tsjentsovy Dvory"
    ],
    "name:rus_x_preferred":[
        "\u0427\u0435\u043d\u0446\u043e\u0432\u044b \u0414\u0432\u043e\u0440\u044b"
    ],
    "name:und_x_variant":[
        "Chantsovo"
    ],
    "wof:name":"Chentsovy Dvory",
    "wof:placetype":"locality"
},
  "geometry": {"coordinates":[37.0059,53.91953],"type":"Point"}
}