{
  "type": "Feature",
  "properties": {
    "gn:admin1_code":"61",
    "gn:asciiname":"Kermek",
    "gn:country_code":"RU",
    "gn:dem":26,
    "gn:feature_class":"P",
    "gn:feature_code":"PPL",
    "gn:name":"Kermek",
    "gn:population":0,
    "gn:timezone":"Europe/Moscow",
    "iso:country":"RU",
    "name:rus_x_preferred":[
        "\u041a\u0435\u0440\u043c\u0435\u043a"
    ],
    "wof:name":"Kermek",
    "wof:placetype":"locality"
},
  "geometry": {"coordinates":[41.507,46.6553],"type":"Point"}
}