{
  "type": "Feature",
  "properties": {
    "gn:admin1_code":"41",
    "gn:asciiname":"Parmenovka",
    "gn:country_code":"RU",
    "gn:dem":163,
    "gn:feature_class":"P",
    "gn:feature_code":"PPL",
    "gn:name":"Parmenovka",
    "gn:population":0,
    "gn:timezone":"Europe/Moscow",
    "iso:country":"RU",
    "name:rus_x_preferred":[
        "\u041f\u0430\u0440\u043c\u0435\u043d\u043e\u0432\u043a\u0430"
    ],
    "wof:name":"Parmenovka",
    "wof:placetype":"locality"
},
  "geometry": {"coordinates":[34.3876,51.5561],"type":"Point"}
}