{
  "type": "Feature",
  "properties": {
    "gn:admin1_code":"53",
    "gn:asciiname":"Novospassk",
    "gn:country_code":"RU",
    "gn:dem":115,
    "gn:feature_class":"P",
    "gn:feature_code":"PPL",
    "gn:name":"Novospassk",
    "gn:population":0,
    "gn:timezone":"Asia/Novosibirsk",
    "iso:country":"RU",
    "name:che_x_preferred":[
        "\u041d\u043e\u0432\u043e\u0441\u043f\u0430\u0441\u0441\u043a"
    ],
    "name:eng_x_preferred":[
        "Novospassk"
    ],
    "name:nor_x_preferred":[
        "Novospassk"
    ],
    "name:rus_x_preferred":[
        "\u041d\u043e\u0432\u043e\u0441\u043f\u0430\u0441\u0441\u043a"
    ],
    "name:tgk_x_preferred":[
        "\u041d\u043e\u0432\u043e\u0441\u043f\u0430\u0441\u043a"
    ],
    "name:und_x_variant":[
        "Novospasskoye",
        "Novo-Spasskaya",
        "\u041d\u043e\u0432\u043e\u0441\u043f\u0430\u0441\u0441\u043a",
        "Novospassk"
    ],
    "wof:name":"Novospassk",
    "wof:placetype":"locality"
},
  "geometry": {"coordinates":[78.18256,55.11406],"type":"Point"}
}