{
  "type": "Feature",
  "properties": {
    "gn:admin1_code":"55",
    "gn:asciiname":"Sharypka",
    "gn:country_code":"RU",
    "gn:dem":323,
    "gn:feature_class":"P",
    "gn:feature_code":"PPL",
    "gn:name":"Sharypka",
    "gn:population":0,
    "gn:timezone":"Asia/Yekaterinburg",
    "iso:country":"RU",
    "name:eng_x_preferred":[
        "Sharypka"
    ],
    "name:nor_x_preferred":[
        "Sjarypka"
    ],
    "name:rus_x_preferred":[
        "\u0428\u0430\u0440\u044b\u043f\u043a\u0430"
    ],
    "name:und_x_variant":[
        "Sharypovo"
    ],
    "wof:name":"Sharypka",
    "wof:placetype":"locality"
},
  "geometry": {"coordinates":[58.522,51.3634],"type":"Point"}
}