{
  "type": "Feature",
  "properties": {
    "gn:admin1_code":"86",
    "gn:asciiname":"Karachun",
    "gn:country_code":"RU",
    "gn:dem":138,
    "gn:feature_class":"P",
    "gn:feature_code":"PPL",
    "gn:name":"Karachun",
    "gn:population":0,
    "gn:timezone":"Europe/Moscow",
    "iso:country":"RU",
    "name:eng_x_preferred":[
        "Karachun"
    ],
    "name:nor_x_preferred":[
        "Karatsjun"
    ],
    "name:rus_x_preferred":[
        "\u041a\u0430\u0440\u0430\u0447\u0443\u043d"
    ],
    "wof:name":"Karachun",
    "wof:placetype":"locality"
},
  "geometry": {"coordinates":[39.35887,52.01328],"type":"Point"}
}