{
  "type": "Feature",
  "properties": {
    "gn:admin1_code":"53",
    "gn:asciiname":"Malo-Chernaya",
    "gn:country_code":"RU",
    "gn:dem":147,
    "gn:feature_class":"P",
    "gn:feature_code":"PPL",
    "gn:name":"Malo-Ch\u00ebrnaya",
    "gn:population":0,
    "gn:timezone":"Asia/Novosibirsk",
    "iso:country":"RU",
    "wof:name":"Malo-Chernaya",
    "wof:placetype":"locality"
},
  "geometry": {"coordinates":[84.51666999999998,56.01667],"type":"Point"}
}