{
  "type": "Feature",
  "properties": {
    "gn:admin1_code":"43",
    "gn:asciiname":"Semenetskiy",
    "gn:cc2":"RU",
    "gn:country_code":"RU",
    "gn:dem":197,
    "gn:feature_class":"P",
    "gn:feature_code":"PPL",
    "gn:name":"Semenetskiy",
    "gn:population":0,
    "gn:timezone":"Europe/Moscow",
    "iso:country":"RU",
    "name:rus_x_preferred":[
        "\u0421\u0435\u043c\u0435\u043d\u0435\u0442\u0441\u043a\u0438\u0439"
    ],
    "name:und_x_variant":[
        "Semenetskiy Khutor",
        "Semenetskiy",
        "\u0421\u0435\u043c\u0435\u043d\u0435\u0442\u0441\u043a\u0438\u0439"
    ],
    "wof:name":"Semenetskiy",
    "wof:placetype":"locality"
},
  "geometry": {"coordinates":[37.91917,52.90556],"type":"Point"}
}