{
  "type": "Feature",
  "properties": {
    "gn:admin1_code":"80",
    "gn:asciiname":"Rozhki",
    "gn:country_code":"RU",
    "gn:dem":144,
    "gn:feature_class":"P",
    "gn:feature_code":"PPL",
    "gn:name":"Rozhki",
    "gn:population":0,
    "gn:timezone":"Europe/Samara",
    "iso:country":"RU",
    "name:eng_x_preferred":[
        "Rozhki"
    ],
    "name:nor_x_preferred":[
        "Rozjki"
    ],
    "name:rus_x_preferred":[
        "\u0420\u043e\u0436\u043a\u0438"
    ],
    "name:und_x_variant":[
        "\u0420\u043e\u0436\u043a\u0438",
        "Rozhki"
    ],
    "wof:name":"Rozhki",
    "wof:placetype":"locality"
},
  "geometry": {"coordinates":[52.35068,57.29686],"type":"Point"}
}