{
  "type": "Feature",
  "properties": {
    "gn:admin1_code":"57",
    "gn:asciiname":"Lipovka",
    "gn:country_code":"RU",
    "gn:dem":184,
    "gn:feature_class":"P",
    "gn:feature_code":"PPL",
    "gn:name":"Lipovka",
    "gn:population":0,
    "gn:timezone":"Europe/Moscow",
    "iso:country":"RU",
    "name:rus_x_preferred":[
        "\u041b\u0438\u043f\u043e\u0432\u043a\u0430"
    ],
    "name:und_x_variant":[
        "\u041b\u0438\u043f\u043e\u0432\u043a\u0430"
    ],
    "wof:name":"Lipovka",
    "wof:placetype":"locality"
},
  "geometry": {"coordinates":[43.29166,52.73487],"type":"Point"}
}