{
  "type": "Feature",
  "properties": {
    "gn:admin1_code":"9.0",
    "gn:asciiname":"Lugovoye",
    "gn:country_code":"RU",
    "gn:dem":195,
    "gn:feature_class":"P",
    "gn:feature_code":"PPL",
    "gn:name":"Lugovoye",
    "gn:population":0,
    "gn:timezone":"Europe/Moscow",
    "iso:country":"RU",
    "name:rus_x_preferred":[
        "\u041b\u0443\u0433\u043e\u0432\u043e\u0435"
    ],
    "name:und_x_variant":[
        "Lugovoy"
    ],
    "wof:name":"Lugovoye",
    "wof:placetype":"locality"
},
  "geometry": {"coordinates":[38.6001,50.3443],"type":"Point"}
}