{
  "type": "Feature",
  "properties": {
    "gn:admin1_code":"61.0",
    "gn:asciiname":"Batlayevskaya",
    "gn:country_code":"RU",
    "gn:dem":22,
    "gn:feature_class":"P",
    "gn:feature_code":"PPL",
    "gn:name":"Batlayevskaya",
    "gn:population":0,
    "gn:timezone":"Europe/Moscow",
    "iso:country":"RU",
    "name:nor_x_preferred":[
        "Batlajevskaja"
    ],
    "name:rus_x_preferred":[
        "\u0411\u0430\u0442\u043b\u0430\u0435\u0432\u0441\u043a\u0430\u044f"
    ],
    "wof:name":"Batlayevskaya",
    "wof:placetype":"locality"
},
  "geometry": {"coordinates":[41.58139,47.18278],"type":"Point"}
}