{
  "type": "Feature",
  "properties": {
    "gn:admin1_code":"51",
    "gn:asciiname":"Sergeytsevo",
    "gn:country_code":"RU",
    "gn:dem":170,
    "gn:feature_class":"P",
    "gn:feature_code":"PPL",
    "gn:name":"Sergeytsevo",
    "gn:population":0,
    "gn:timezone":"Europe/Moscow",
    "iso:country":"RU",
    "name:rus_x_preferred":[
        "\u0421\u0435\u0440\u0433\u0435\u0439\u0446\u0435\u0432\u043e"
    ],
    "wof:name":"Sergeytsevo",
    "wof:placetype":"locality"
},
  "geometry": {"coordinates":[43.27533,55.81146999999999],"type":"Point"}
}