{
  "type": "Feature",
  "properties": {
    "gn:admin1_code":"17",
    "gn:asciiname":"Sovetskoye",
    "gn:country_code":"RU",
    "gn:dem":235,
    "gn:feature_class":"P",
    "gn:feature_code":"PPL",
    "gn:name":"Sovetskoye",
    "gn:population":0,
    "gn:timezone":"Europe/Moscow",
    "iso:country":"RU",
    "name:eng_x_preferred":[
        "Sovetskoye"
    ],
    "name:nor_x_preferred":[
        "Sovetskoje"
    ],
    "name:rus_x_preferred":[
        "\u0421\u043e\u0432\u0435\u0442\u0441\u043a\u043e\u0435"
    ],
    "name:und_x_variant":[
        "Mamrash",
        "Mamrach"
    ],
    "wof:name":"Sovetskoye",
    "wof:placetype":"locality"
},
  "geometry": {"coordinates":[48.32729000000001,41.72989000000001],"type":"Point"}
}