{
  "type": "Feature",
  "properties": {
    "gn:admin1_code":"62",
    "gn:asciiname":"Pervo",
    "gn:country_code":"RU",
    "gn:dem":138,
    "gn:feature_class":"P",
    "gn:feature_code":"PPL",
    "gn:name":"Pervo",
    "gn:population":0,
    "gn:timezone":"Europe/Moscow",
    "iso:country":"RU",
    "name:eng_x_preferred":[
        "Pervo"
    ],
    "name:nor_x_preferred":[
        "Pervo"
    ],
    "name:rus_x_preferred":[
        "\u041f\u0435\u0440\u0432\u043e"
    ],
    "name:und_x_variant":[
        "\u041f\u0435\u0440\u0432\u043e",
        "Pervo"
    ],
    "wof:name":"Pervo",
    "wof:placetype":"locality"
},
  "geometry": {"coordinates":[41.44278,54.83056],"type":"Point"}
}