{
  "type": "Feature",
  "properties": {
    "gn:admin1_code":"85",
    "gn:asciiname":"Tirkovo",
    "gn:country_code":"RU",
    "gn:dem":159,
    "gn:feature_class":"P",
    "gn:feature_code":"PPL",
    "gn:name":"Tirkovo",
    "gn:population":0,
    "gn:timezone":"Europe/Moscow",
    "iso:country":"RU",
    "name:rus_x_preferred":[
        "\u0422\u0438\u0440\u043a\u043e\u0432\u043e"
    ],
    "wof:name":"Tirkovo",
    "wof:placetype":"locality"
},
  "geometry": {"coordinates":[38.34932,59.37055],"type":"Point"}
}