{
  "type": "Feature",
  "properties": {
    "gn:admin1_code":"17",
    "gn:asciiname":"Kadamakhi",
    "gn:country_code":"RU",
    "gn:dem":1355,
    "gn:feature_class":"P",
    "gn:feature_code":"PPL",
    "gn:name":"Kadamakhi",
    "gn:population":0,
    "gn:timezone":"Europe/Moscow",
    "iso:country":"RU",
    "name:rus_x_preferred":[
        "\u041a\u0430\u0434\u0430\u043c\u0430\u0445\u0438"
    ],
    "name:und_x_variant":[
        "\u041a\u0430\u0434\u0430\u043c\u0430\u0445\u0438"
    ],
    "wof:name":"Kadamakhi",
    "wof:placetype":"locality"
},
  "geometry": {"coordinates":[47.38194,42.29833],"type":"Point"}
}