{
  "type": "Feature",
  "properties": {
    "gn:admin1_code":"45",
    "gn:asciiname":"Malaya Tursha",
    "gn:country_code":"RU",
    "gn:dem":117,
    "gn:feature_class":"P",
    "gn:feature_code":"PPL",
    "gn:name":"Malaya Tursha",
    "gn:population":0,
    "gn:timezone":"Europe/Moscow",
    "iso:country":"RU",
    "name:eng_x_preferred":[
        "Malaya Tursha"
    ],
    "name:nor_x_preferred":[
        "Mal.Tursja"
    ],
    "name:rus_x_preferred":[
        "\u041c\u0430\u043b.\u0422\u0443\u0440\u0448\u0430"
    ],
    "name:rus_x_variant":[
        "\u041c\u0430\u043b\u0430\u044f \u0422\u0443\u0440\u0448\u0430"
    ],
    "name:und_x_variant":[
        "\u041c\u0430\u043b\u0430\u044f \u0422\u0443\u0440\u0448\u0430"
    ],
    "wof:name":"Malaya Tursha",
    "wof:placetype":"locality"
},
  "geometry": {"coordinates":[47.59318,56.88758000000001],"type":"Point"}
}