{
  "type": "Feature",
  "properties": {
    "gn:admin1_code":"40",
    "gn:asciiname":"Uval",
    "gn:country_code":"RU",
    "gn:dem":86,
    "gn:feature_class":"P",
    "gn:feature_code":"PPL",
    "gn:name":"Uval",
    "gn:population":0,
    "gn:timezone":"Asia/Yekaterinburg",
    "iso:country":"RU",
    "name:eng_x_preferred":[
        "Uval"
    ],
    "name:nor_x_preferred":[
        "Uval"
    ],
    "name:rus_x_preferred":[
        "\u0423\u0432\u0430\u043b"
    ],
    "wof:name":"Uval",
    "wof:placetype":"locality"
},
  "geometry": {"coordinates":[65.37056,55.37778],"type":"Point"}
}