{
  "type": "Feature",
  "properties": {
    "gn:admin1_code":"85",
    "gn:asciiname":"Nizhniy An'goboy",
    "gn:country_code":"RU",
    "gn:dem":163,
    "gn:feature_class":"P",
    "gn:feature_code":"PPL",
    "gn:name":"Nizhniy An\u2019goboy",
    "gn:population":0,
    "gn:timezone":"Europe/Moscow",
    "iso:country":"RU",
    "name:rus_x_preferred":[
        "\u041d\u0438\u0436\u043d\u0438\u0439 \u0410\u043d\u044c\u0433\u043e\u0431\u043e\u0439"
    ],
    "name:und_x_variant":[
        "Nizhniy An\u2019goboy",
        "\u041d\u0438\u0436\u043d\u0438\u0439 \u0410\u043d\u044c\u0433\u043e\u0431\u043e\u0439"
    ],
    "wof:name":"Nizhniy An'goboy",
    "wof:placetype":"locality"
},
  "geometry": {"coordinates":[38.20384,59.40371999999999],"type":"Point"}
}