{
  "type": "Feature",
  "properties": {
    "gn:admin1_code":"21",
    "gn:asciiname":"Lipovaya Roshcha",
    "gn:country_code":"RU",
    "gn:dem":125,
    "gn:feature_class":"P",
    "gn:feature_code":"PPL",
    "gn:name":"Lipovaya Roshcha",
    "gn:population":0,
    "gn:timezone":"Europe/Moscow",
    "iso:country":"RU",
    "name:rus_x_preferred":[
        "\u041b\u0438\u043f\u043e\u0432\u0430\u044f \u0420\u043e\u0449\u0430"
    ],
    "wof:name":"Lipovaya Roshcha",
    "wof:placetype":"locality"
},
  "geometry": {"coordinates":[40.267,56.6375],"type":"Point"}
}