{
  "type": "Feature",
  "properties": {
    "gn:admin1_code":"52",
    "gn:asciiname":"Staryy Lug",
    "gn:country_code":"RU",
    "gn:dem":72,
    "gn:feature_class":"P",
    "gn:feature_code":"PPL",
    "gn:name":"Staryy Lug",
    "gn:population":0,
    "gn:timezone":"Europe/Moscow",
    "iso:country":"RU",
    "name:rus_x_preferred":[
        "\u0421\u0442\u0430\u0440\u044b\u0439 \u041b\u0443\u0433"
    ],
    "wof:name":"Staryy Lug",
    "wof:placetype":"locality"
},
  "geometry": {"coordinates":[29.74801,58.32057],"type":"Point"}
}