{
  "type": "Feature",
  "properties": {
    "gn:admin1_code":"51",
    "gn:asciiname":"Migalikha",
    "gn:country_code":"RU",
    "gn:dem":161,
    "gn:feature_class":"P",
    "gn:feature_code":"PPL",
    "gn:name":"Migalikha",
    "gn:population":0,
    "gn:timezone":"Europe/Moscow",
    "iso:country":"RU",
    "name:eng_x_preferred":[
        "Migalikha"
    ],
    "name:nor_x_preferred":[
        "Migalikha"
    ],
    "name:rus_x_preferred":[
        "\u041c\u0438\u0433\u0430\u043b\u0438\u0445\u0430"
    ],
    "name:und_x_variant":[
        "\u041c\u0438\u0433\u0430\u043b\u0438\u0445\u0430",
        "Migalikha"
    ],
    "wof:name":"Migalikha",
    "wof:placetype":"locality"
},
  "geometry": {"coordinates":[43.77494,55.8013],"type":"Point"}
}