{
  "type": "Feature",
  "properties": {
    "gn:admin1_code":"69",
    "gn:asciiname":"Shakhmatovo",
    "gn:country_code":"RU",
    "gn:dem":213,
    "gn:feature_class":"P",
    "gn:feature_code":"PPL",
    "gn:name":"Shakhmatovo",
    "gn:population":0,
    "gn:timezone":"Europe/Moscow",
    "iso:country":"RU",
    "name:rus_x_preferred":[
        "\u0428\u0430\u0445\u043c\u0430\u0442\u043e\u0432\u043e"
    ],
    "name:und_x_variant":[
        "\u0428\u0430\u0445\u043c\u0430\u0442\u043e\u0432\u043e"
    ],
    "wof:name":"Shakhmatovo",
    "wof:placetype":"locality"
},
  "geometry": {"coordinates":[35.09599,55.64102],"type":"Point"}
}