{
  "type": "Feature",
  "properties": {
    "gn:admin1_code":"61",
    "gn:asciiname":"Vtoro-Karpovskiy",
    "gn:country_code":"RU",
    "gn:dem":100,
    "gn:feature_class":"P",
    "gn:feature_code":"PPL",
    "gn:name":"Vtoro-Karpovskiy",
    "gn:population":0,
    "gn:timezone":"Europe/Moscow",
    "iso:country":"RU",
    "wof:name":"Vtoro-Karpovskiy",
    "wof:placetype":"locality"
},
  "geometry": {"coordinates":[41.02241,49.06984],"type":"Point"}
}