{
  "type": "Feature",
  "properties": {
    "gn:admin1_code":"69",
    "gn:asciiname":"Goryany",
    "gn:country_code":"RU",
    "gn:dem":239,
    "gn:feature_class":"P",
    "gn:feature_code":"PPL",
    "gn:name":"Goryany",
    "gn:population":0,
    "gn:timezone":"Europe/Moscow",
    "iso:country":"RU",
    "name:rus_x_preferred":[
        "\u0413\u043e\u0440\u044f\u043d\u044b"
    ],
    "wof:name":"Goryany",
    "wof:placetype":"locality"
},
  "geometry": {"coordinates":[32.11805,54.72203],"type":"Point"}
}