{
  "type": "Feature",
  "properties": {
    "gn:admin1_code":"22",
    "gn:asciiname":"Yantarnoye",
    "gn:country_code":"RU",
    "gn:dem":235,
    "gn:feature_class":"P",
    "gn:feature_code":"PPL",
    "gn:name":"Yantarnoye",
    "gn:population":0,
    "gn:timezone":"Europe/Moscow",
    "iso:country":"RU",
    "name:und_x_variant":[
        "Lagernyy",
        "Yantarnoye"
    ],
    "wof:name":"Yantarnoye",
    "wof:placetype":"locality"
},
  "geometry": {"coordinates":[43.88333,43.76528],"type":"Point"}
}