{
  "type": "Feature",
  "properties": {
    "gn:admin1_code":"33.0",
    "gn:asciiname":"Kuzhlevka",
    "gn:country_code":"RU",
    "gn:dem":109,
    "gn:feature_class":"P",
    "gn:feature_code":"PPL",
    "gn:name":"Kuzhl\u00ebvka",
    "gn:population":0,
    "gn:timezone":"Europe/Kirov",
    "iso:country":"RU",
    "name:rus_x_preferred":[
        "\u041a\u0443\u0436\u043b\u0451\u0432\u043a\u0430"
    ],
    "name:und_x_variant":[
        "Kuzhl\u00ebvka",
        "\u041a\u0443\u0436\u043b\u0451\u0432\u043a\u0430"
    ],
    "wof:name":"Kuzhlevka",
    "wof:placetype":"locality"
},
  "geometry": {"coordinates":[48.39611,58.57833],"type":"Point"}
}