{
  "type": "Feature",
  "properties": {
    "gn:admin1_code":"69.0",
    "gn:asciiname":"Galyshkino",
    "gn:country_code":"RU",
    "gn:dem":219,
    "gn:feature_class":"P",
    "gn:feature_code":"PPL",
    "gn:name":"Galyshkino",
    "gn:population":0,
    "gn:timezone":"Europe/Moscow",
    "iso:country":"RU",
    "name:rus_x_preferred":[
        "\u0413\u0430\u043b\u044b\u0448\u043a\u0438\u043d\u043e"
    ],
    "name:und_x_variant":[
        "\u0413\u0430\u043b\u044b\u0448\u043a\u0438\u043d\u043e"
    ],
    "wof:name":"Galyshkino",
    "wof:placetype":"locality"
},
  "geometry": {"coordinates":[35.27972000000001,55.63111],"type":"Point"}
}