{
  "type": "Feature",
  "properties": {
    "gn:admin1_code":"84",
    "gn:asciiname":"Stepnovskiy",
    "gn:country_code":"RU",
    "gn:dem":32,
    "gn:feature_class":"P",
    "gn:feature_code":"PPL",
    "gn:name":"Stepnovskiy",
    "gn:population":0,
    "gn:timezone":"Europe/Volgograd",
    "iso:country":"RU",
    "name:eng_x_preferred":[
        "Stepnovskiy"
    ],
    "name:nor_x_preferred":[
        "Stepnovskij"
    ],
    "name:rus_x_preferred":[
        "\u0421\u0442\u0435\u043f\u043d\u043e\u0432\u0441\u043a\u0438\u0439"
    ],
    "name:und_x_variant":[
        "Stepnovka",
        "Stepnoy"
    ],
    "wof:name":"Stepnovskiy",
    "wof:placetype":"locality"
},
  "geometry": {"coordinates":[45.81487,49.94314],"type":"Point"}
}