{
  "type": "Feature",
  "properties": {
    "gn:admin1_code":"87",
    "gn:asciiname":"Yegommalymgort",
    "gn:country_code":"RU",
    "gn:dem":20,
    "gn:feature_class":"P",
    "gn:feature_code":"PPL",
    "gn:name":"Yegommalymgort",
    "gn:population":0,
    "gn:timezone":"Asia/Yekaterinburg",
    "iso:country":"RU",
    "wof:name":"Yegommalymgort",
    "wof:placetype":"locality"
},
  "geometry": {"coordinates":[66.15000000000001,64.93333],"type":"Point"}
}