{
  "type": "Feature",
  "properties": {
    "gn:admin1_code":"61",
    "gn:asciiname":"Nemashkov",
    "gn:cc2":"RU",
    "gn:country_code":"RU",
    "gn:dem":110,
    "gn:feature_class":"P",
    "gn:feature_code":"PPL",
    "gn:name":"Nemashkov",
    "gn:population":0,
    "gn:timezone":"Europe/Moscow",
    "iso:country":"RU",
    "name:rus_x_preferred":[
        "\u041d\u0435\u043c\u0430\u0448\u043a\u043e\u0432"
    ],
    "name:und_x_variant":[
        "Nemoshkanov",
        "Nemashkov"
    ],
    "wof:name":"Nemashkov",
    "wof:placetype":"locality"
},
  "geometry": {"coordinates":[43.75583,46.51],"type":"Point"}
}