{
  "type": "Feature",
  "properties": {
    "gn:admin1_code":"47",
    "gn:asciiname":"Tsaplino",
    "gn:country_code":"RU",
    "gn:dem":119,
    "gn:feature_class":"P",
    "gn:feature_code":"PPL",
    "gn:name":"Tsaplino",
    "gn:population":0,
    "gn:timezone":"Europe/Moscow",
    "iso:country":"RU",
    "name:und_x_variant":[
        "Tsaplina",
        "Tsaplino"
    ],
    "wof:name":"Tsaplino",
    "wof:placetype":"locality"
},
  "geometry": {"coordinates":[38.91821,55.49242],"type":"Point"}
}