{
  "type": "Feature",
  "properties": {
    "gn:admin1_code":"77",
    "gn:asciiname":"Bol'shoy Dorok",
    "gn:country_code":"RU",
    "gn:dem":208,
    "gn:feature_class":"P",
    "gn:feature_code":"PPL",
    "gn:name":"Bol\u2019shoy Dorok",
    "gn:population":0,
    "gn:timezone":"Europe/Moscow",
    "iso:country":"RU",
    "name:rus_x_preferred":[
        "\u0411\u043e\u043b\u044c\u0448\u043e\u0439 \u0414\u043e\u0440\u043e\u043a"
    ],
    "name:und_x_variant":[
        "Bol\u2019shoy Dorok"
    ],
    "wof:name":"Bol'shoy Dorok",
    "wof:placetype":"locality"
},
  "geometry": {"coordinates":[36.9535,57.9425],"type":"Point"}
}