{
  "type": "Feature",
  "properties": {
    "gn:admin1_code":"33",
    "gn:asciiname":"Myakishi",
    "gn:country_code":"RU",
    "gn:dem":154,
    "gn:feature_class":"P",
    "gn:feature_code":"PPL",
    "gn:name":"Myakishi",
    "gn:population":0,
    "gn:timezone":"Europe/Kirov",
    "iso:country":"RU",
    "name:eng_x_preferred":[
        "Myakishi"
    ],
    "name:nor_x_preferred":[
        "Mjakisji"
    ],
    "name:rus_x_preferred":[
        "\u041c\u044f\u043a\u0438\u0448\u0438"
    ],
    "name:und_x_variant":[
        "\u041c\u044f\u043a\u0438\u0448\u0438",
        "Myakishi"
    ],
    "wof:name":"Myakishi",
    "wof:placetype":"locality"
},
  "geometry": {"coordinates":[49.05029,57.87499],"type":"Point"}
}