{
  "type": "Feature",
  "properties": {
    "gn:admin1_code":"57",
    "gn:asciiname":"Morozovka",
    "gn:country_code":"RU",
    "gn:dem":221,
    "gn:feature_class":"P",
    "gn:feature_code":"PPL",
    "gn:name":"Morozovka",
    "gn:population":0,
    "gn:timezone":"Europe/Moscow",
    "iso:country":"RU",
    "name:rus_x_preferred":[
        "\u041c\u043e\u0440\u043e\u0437\u043e\u0432\u043a\u0430"
    ],
    "name:und_x_variant":[
        "\u041c\u043e\u0440\u043e\u0437\u043e\u0432\u043a\u0430"
    ],
    "wof:name":"Morozovka",
    "wof:placetype":"locality"
},
  "geometry": {"coordinates":[46.1341,53.1526],"type":"Point"}
}