{
  "type": "Feature",
  "properties": {
    "gn:admin1_code":"84",
    "gn:asciiname":"Starokondal'",
    "gn:country_code":"RU",
    "gn:dem":162,
    "gn:feature_class":"P",
    "gn:feature_code":"PPL",
    "gn:name":"Starokondal\u2019",
    "gn:population":0,
    "gn:timezone":"Europe/Volgograd",
    "iso:country":"RU",
    "name:rus_x_preferred":[
        "\u0421\u0442\u0430\u0440\u043e\u043a\u043e\u043d\u0434\u0430\u043b\u044c"
    ],
    "name:und_x_variant":[
        "Staraya Kondal\u2019",
        "Starokondal\u2019"
    ],
    "wof:name":"Starokondal'",
    "wof:placetype":"locality"
},
  "geometry": {"coordinates":[44.45,50.55],"type":"Point"}
}