{
  "type": "Feature",
  "properties": {
    "gn:admin1_code":"69",
    "gn:asciiname":"Tur",
    "gn:country_code":"RU",
    "gn:dem":216,
    "gn:feature_class":"P",
    "gn:feature_code":"PPL",
    "gn:name":"Tur",
    "gn:population":0,
    "gn:timezone":"Europe/Moscow",
    "iso:country":"RU",
    "name:bel_x_preferred":[
        "\u0422\u0443\u0440"
    ],
    "name:bul_x_preferred":[
        "\u0422\u0443\u0440"
    ],
    "name:ceb_x_preferred":[
        "Tur"
    ],
    "name:dan_x_preferred":[
        "Tur"
    ],
    "name:deu_x_preferred":[
        "Tur"
    ],
    "name:fra_x_preferred":[
        "Tur"
    ],
    "name:hye_x_preferred":[
        "\u054f\u0578\u0582\u0580"
    ],
    "name:nor_x_preferred":[
        "Tur"
    ],
    "name:pol_x_preferred":[
        "Tur"
    ],
    "name:rus_x_preferred":[
        "\u0422\u0443\u0440"
    ],
    "name:slk_x_preferred":[
        "Tur"
    ],
    "name:slv_x_preferred":[
        "Tur"
    ],
    "name:srp_x_preferred":[
        "\u0422\u0443\u0440"
    ],
    "name:swe_x_preferred":[
        "Tur"
    ],
    "name:tur_x_preferred":[
        "Tur"
    ],
    "name:ukr_x_preferred":[
        "\u0422\u0443\u0440"
    ],
    "name:uzb_x_preferred":[
        "Tur"
    ],
    "wof:name":"Tur",
    "wof:placetype":"locality"
},
  "geometry": {"coordinates":[30.90903,54.8946],"type":"Point"}
}