{
  "type": "Feature",
  "properties": {
    "gn:admin1_code":"62",
    "gn:asciiname":"Nikitinskoye",
    "gn:country_code":"RU",
    "gn:dem":185,
    "gn:feature_class":"P",
    "gn:feature_code":"PPL",
    "gn:name":"Nikitinskoye",
    "gn:population":0,
    "gn:timezone":"Europe/Moscow",
    "iso:country":"RU",
    "name:rus_x_preferred":[
        "\u041d\u0438\u043a\u0438\u0442\u0438\u043d\u0441\u043a\u043e\u0435"
    ],
    "name:und_x_variant":[
        "\u041d\u0438\u043a\u0438\u0442\u0438\u043d\u0441\u043a\u043e\u0435"
    ],
    "wof:name":"Nikitinskoye",
    "wof:placetype":"locality"
},
  "geometry": {"coordinates":[39.7216,54.2993],"type":"Point"}
}