{
  "type": "Feature",
  "properties": {
    "gn:admin1_code":"53",
    "gn:asciiname":"Voskresenka",
    "gn:country_code":"RU",
    "gn:dem":94,
    "gn:feature_class":"P",
    "gn:feature_code":"PPL",
    "gn:name":"Voskresenka",
    "gn:population":0,
    "gn:timezone":"Asia/Novosibirsk",
    "iso:country":"RU",
    "name:che_x_preferred":[
        "\u0412\u043e\u0441\u043a\u0440\u0435\u0441\u0435\u043d\u043a\u0430"
    ],
    "name:eng_x_preferred":[
        "Voskresenka"
    ],
    "name:nor_x_preferred":[
        "Voskresenka"
    ],
    "name:rus_x_preferred":[
        "\u0412\u043e\u0441\u043a\u0440\u0435\u0441\u0435\u043d\u043a\u0430"
    ],
    "wof:name":"Voskresenka",
    "wof:placetype":"locality"
},
  "geometry": {"coordinates":[76.15385999999999,56.43845],"type":"Point"}
}