{
  "type": "Feature",
  "properties": {
    "gn:admin1_code":"70.0",
    "gn:asciiname":"Chumakov",
    "gn:country_code":"RU",
    "gn:dem":287,
    "gn:feature_class":"P",
    "gn:feature_code":"PPL",
    "gn:name":"Chumakov",
    "gn:population":0,
    "gn:timezone":"Europe/Moscow",
    "iso:country":"RU",
    "name:bel_x_preferred":[
        "\u0427\u0443\u043c\u0430\u043a\u043e\u045e"
    ],
    "name:deu_x_preferred":[
        "Tschumakow"
    ],
    "name:rus_x_preferred":[
        "\u0427\u0443\u043c\u0430\u043a\u043e\u0432"
    ],
    "name:slv_x_preferred":[
        "\u010cumakov"
    ],
    "wof:name":"Chumakov",
    "wof:placetype":"locality"
},
  "geometry": {"coordinates":[43.12056,44.58917],"type":"Point"}
}