{
  "type": "Feature",
  "properties": {
    "gn:admin1_code":"90",
    "gn:asciiname":"Kamashor",
    "gn:country_code":"RU",
    "gn:dem":170,
    "gn:feature_class":"P",
    "gn:feature_code":"PPL",
    "gn:name":"Kamashor",
    "gn:population":0,
    "gn:timezone":"Asia/Yekaterinburg",
    "iso:country":"RU",
    "name:che_x_preferred":[
        "\u041a\u0430\u043c\u0430\u0448\u043e\u0440"
    ],
    "name:koi_x_preferred":[
        "\u041a\u0430\u043c\u0430\u0448\u043e\u0440"
    ],
    "name:rus_x_preferred":[
        "\u041a\u0430\u043c\u0430\u0448\u043e\u0440"
    ],
    "name:und_x_variant":[
        "Votyakova",
        "Kamashor",
        "\u041a\u0430\u043c\u0430\u0448\u043e\u0440"
    ],
    "wof:name":"Kamashor",
    "wof:placetype":"locality"
},
  "geometry": {"coordinates":[54.6768,59.2026],"type":"Point"}
}