{
  "type": "Feature",
  "properties": {
    "gn:admin1_code":"60",
    "gn:asciiname":"Zaput'ye",
    "gn:country_code":"RU",
    "gn:dem":55,
    "gn:feature_class":"P",
    "gn:feature_code":"PPL",
    "gn:name":"Zaput\u2019ye",
    "gn:population":0,
    "gn:timezone":"Europe/Moscow",
    "iso:country":"RU",
    "name:rus_x_preferred":[
        "\u0417\u0430\u043f\u0443\u0442\u044c\u0435"
    ],
    "name:und_x_variant":[
        "Zaput\u2019ye"
    ],
    "wof:name":"Zaput'ye",
    "wof:placetype":"locality"
},
  "geometry": {"coordinates":[28.03519,57.82142],"type":"Point"}
}