{
  "type": "Feature",
  "properties": {
    "gn:admin1_code":"90",
    "gn:asciiname":"Verkhnyaya Osh'ya",
    "gn:country_code":"RU",
    "gn:dem":149,
    "gn:feature_class":"P",
    "gn:feature_code":"PPL",
    "gn:name":"Verkhnyaya Osh\u2019ya",
    "gn:population":0,
    "gn:timezone":"Asia/Yekaterinburg",
    "iso:country":"RU",
    "name:rus_x_preferred":[
        "\u0412\u0435\u0440\u0445\u043d\u044f\u044f \u041e\u0448\u044c\u044f"
    ],
    "name:und_x_variant":[
        "Verkhnyaya Osh\u2019ya"
    ],
    "wof:name":"Verkhnyaya Osh'ya",
    "wof:placetype":"locality"
},
  "geometry": {"coordinates":[54.92667,56.55405],"type":"Point"}
}