{
  "type": "Feature",
  "properties": {
    "gn:admin1_code":"52",
    "gn:asciiname":"Malyye Dubovitsy",
    "gn:cc2":"RU",
    "gn:country_code":"RU",
    "gn:dem":39,
    "gn:feature_class":"P",
    "gn:feature_code":"PPL",
    "gn:name":"Malyye Dubovitsy",
    "gn:population":0,
    "gn:timezone":"Europe/Moscow",
    "iso:country":"RU",
    "name:rus_x_preferred":[
        "\u041c\u0430\u043b\u044b\u0435 \u0414\u0443\u0431\u043e\u0432\u0438\u0446\u044b"
    ],
    "name:und_x_variant":[
        "Zhuravki",
        "Malyye Dubovitsy",
        "\u041c\u0430\u043b\u044b\u0435 \u0414\u0443\u0431\u043e\u0432\u0438\u0446\u044b"
    ],
    "wof:name":"Malyye Dubovitsy",
    "wof:placetype":"locality"
},
  "geometry": {"coordinates":[31.23333,57.86666999999999],"type":"Point"}
}