{
  "type": "Feature",
  "properties": {
    "gn:admin1_code":"44",
    "gn:asciiname":"Neryuchi",
    "gn:country_code":"RU",
    "gn:dem":711,
    "gn:feature_class":"P",
    "gn:feature_code":"PPL",
    "gn:name":"Neryuchi",
    "gn:population":0,
    "gn:timezone":"Asia/Magadan",
    "iso:country":"RU",
    "name:rus_x_preferred":[
        "\u041d\u0435\u0440\u044e\u0447\u0438"
    ],
    "name:und_x_variant":[
        "Neryuchinskiy",
        "Neryuchi"
    ],
    "wof:name":"Neryuchi",
    "wof:placetype":"locality"
},
  "geometry": {"coordinates":[147.02305000000001,61.88041],"type":"Point"}
}