{
  "type": "Feature",
  "properties": {
    "gn:admin1_code":"61.0",
    "gn:asciiname":"Gamzha",
    "gn:country_code":"RU",
    "gn:dem":143,
    "gn:feature_class":"P",
    "gn:feature_code":"PPL",
    "gn:name":"Gamzha",
    "gn:population":0,
    "gn:timezone":"Europe/Moscow",
    "iso:country":"RU",
    "name:rus_x_preferred":[
        "\u0413\u0430\u043c\u0436\u0430"
    ],
    "name:und_x_variant":[
        "\u0413\u0430\u043c\u0436\u0430"
    ],
    "wof:name":"Gamzha",
    "wof:placetype":"locality"
},
  "geometry": {"coordinates":[44.13333,47.16667],"type":"Point"}
}