{
  "type": "Feature",
  "properties": {
    "gn:admin1_code":"77",
    "gn:asciiname":"Matveyevskoye",
    "gn:country_code":"RU",
    "gn:dem":159,
    "gn:feature_class":"P",
    "gn:feature_code":"PPL",
    "gn:name":"Matveyevskoye",
    "gn:population":0,
    "gn:timezone":"Europe/Moscow",
    "iso:country":"RU",
    "name:nor_x_preferred":[
        "Matvejevskoje"
    ],
    "name:rus_x_preferred":[
        "\u041c\u0430\u0442\u0432\u0435\u0435\u0432\u0441\u043a\u043e\u0435"
    ],
    "wof:name":"Matveyevskoye",
    "wof:placetype":"locality"
},
  "geometry": {"coordinates":[35.7609,56.52618],"type":"Point"}
}