{
  "type": "Feature",
  "properties": {
    "gn:admin1_code":"52",
    "gn:asciiname":"Toropina Mel'nitsa",
    "gn:country_code":"RU",
    "gn:dem":95,
    "gn:feature_class":"P",
    "gn:feature_code":"PPL",
    "gn:name":"Toropina Mel\u2019nitsa",
    "gn:population":0,
    "gn:timezone":"Europe/Moscow",
    "iso:country":"RU",
    "wof:name":"Toropina Mel'nitsa",
    "wof:placetype":"locality"
},
  "geometry": {"coordinates":[33.68167,58.57083000000001],"type":"Point"}
}