{
  "type": "Feature",
  "properties": {
    "gn:admin1_code":"49",
    "gn:asciiname":"Malaya Lopatka",
    "gn:country_code":"RU",
    "gn:dem":-9999,
    "gn:feature_class":"P",
    "gn:feature_code":"PPL",
    "gn:name":"Malaya Lopatka",
    "gn:population":0,
    "gn:timezone":"Europe/Moscow",
    "iso:country":"RU",
    "name:rus_x_preferred":[
        "\u041c\u0430\u043b\u0430\u044f \u041b\u043e\u043f\u0430\u0442\u043a\u0430"
    ],
    "name:und_x_variant":[
        "Zapornaya Stantsiya Lopatkina",
        "Lopatina",
        "Malaya Lopatka"
    ],
    "wof:name":"Malaya Lopatka",
    "wof:placetype":"locality"
},
  "geometry": {"coordinates":[32.43905,69.44795000000001],"type":"Point"}
}