{
  "type": "Feature",
  "properties": {
    "gn:admin1_code":"7.0",
    "gn:asciiname":"Besnyaki",
    "gn:country_code":"RU",
    "gn:dem":-25,
    "gn:feature_class":"P",
    "gn:feature_code":"PPL",
    "gn:name":"Besnyaki",
    "gn:population":0,
    "gn:timezone":"Europe/Astrakhan",
    "iso:country":"RU",
    "name:nor_x_preferred":[
        "Besnjaki"
    ],
    "name:rus_x_preferred":[
        "\u0411\u0435\u0441\u043d\u044f\u043a\u0438"
    ],
    "wof:name":"Besnyaki",
    "wof:placetype":"locality"
},
  "geometry": {"coordinates":[47.32194000000001,45.95028],"type":"Point"}
}