{
  "type": "Feature",
  "properties": {
    "gn:admin1_code":"42",
    "gn:admin2_code":"472711",
    "gn:asciiname":"Kivuya",
    "gn:country_code":"RU",
    "gn:dem":49,
    "gn:feature_class":"P",
    "gn:feature_code":"PPL",
    "gn:name":"Kivuya",
    "gn:population":0,
    "gn:timezone":"Europe/Moscow",
    "iso:country":"RU",
    "name:eng_x_preferred":[
        "Kivuya"
    ],
    "name:nor_x_preferred":[
        "Kivuja"
    ],
    "name:rus_x_preferred":[
        "\u041a\u0438\u0432\u0443\u044f"
    ],
    "wof:name":"Kivuya",
    "wof:placetype":"locality"
},
  "geometry": {"coordinates":[32.8229,60.07425],"type":"Point"}
}