{
  "type": "Feature",
  "properties": {
    "gn:admin1_code":"41",
    "gn:asciiname":"Verkhneye Soskovo",
    "gn:country_code":"RU",
    "gn:dem":191,
    "gn:feature_class":"P",
    "gn:feature_code":"PPL",
    "gn:name":"Verkhneye Soskovo",
    "gn:population":0,
    "gn:timezone":"Europe/Moscow",
    "iso:country":"RU",
    "name:rus_x_preferred":[
        "\u0412\u0435\u0440\u0445\u043d\u0435\u0435 \u0421\u043e\u0441\u043a\u043e\u0432\u043e"
    ],
    "name:und_x_variant":[
        "Saskova-Lomnya",
        "Saskova",
        "Soskova",
        "Verkhneye Soskovo"
    ],
    "wof:name":"Verkhneye Soskovo",
    "wof:placetype":"locality"
},
  "geometry": {"coordinates":[35.6963,51.7714],"type":"Point"}
}