{
  "type": "Feature",
  "properties": {
    "gn:admin1_code":"8",
    "gn:asciiname":"Tuzlukush",
    "gn:country_code":"RU",
    "gn:dem":213,
    "gn:feature_class":"P",
    "gn:feature_code":"PPL",
    "gn:name":"Tuzlukush",
    "gn:population":0,
    "gn:timezone":"Asia/Yekaterinburg",
    "iso:country":"RU",
    "name:eng_x_preferred":[
        "Tuzlukush"
    ],
    "name:nor_x_preferred":[
        "Tuzlukusj"
    ],
    "name:rus_x_preferred":[
        "\u0422\u0443\u0437\u043b\u0443\u043a\u0443\u0448"
    ],
    "name:und_x_variant":[
        "Tuzlukushevo",
        "Tuzlukush",
        "\u0422\u0443\u0437\u043b\u0443\u043a\u0443\u0448"
    ],
    "wof:name":"Tuzlukush",
    "wof:placetype":"locality"
},
  "geometry": {"coordinates":[54.15,54.25],"type":"Point"}
}