{
  "type": "Feature",
  "properties": {
    "gn:admin1_code":"76",
    "gn:asciiname":"Babinka",
    "gn:country_code":"RU",
    "gn:dem":176,
    "gn:feature_class":"P",
    "gn:feature_code":"PPL",
    "gn:name":"Babinka",
    "gn:population":0,
    "gn:timezone":"Europe/Moscow",
    "iso:country":"RU",
    "name:nor_x_preferred":[
        "Babinka"
    ],
    "name:rus_x_preferred":[
        "\u0411\u0430\u0431\u0438\u043d\u043a\u0430"
    ],
    "wof:name":"Babinka",
    "wof:placetype":"locality"
},
  "geometry": {"coordinates":[38.33776,53.87891],"type":"Point"}
}