{
  "type": "Feature",
  "properties": {
    "gn:admin1_code":"6",
    "gn:asciiname":"Makharovskaya",
    "gn:cc2":"RU",
    "gn:country_code":"RU",
    "gn:dem":57,
    "gn:feature_class":"P",
    "gn:feature_code":"PPL",
    "gn:name":"Makharovskaya",
    "gn:population":0,
    "gn:timezone":"Europe/Moscow",
    "iso:country":"RU",
    "name:eng_x_preferred":[
        "Makharovskaya"
    ],
    "name:nor_x_preferred":[
        "Makarovskaja"
    ],
    "name:rus_x_preferred":[
        "\u041c\u0430\u043a\u0430\u0440\u043e\u0432\u0441\u043a\u0430\u044f"
    ],
    "name:rus_x_variant":[
        "\u041c\u0430\u0445\u0430\u0440\u043e\u0432\u0441\u043a\u0430\u044f"
    ],
    "name:und_x_variant":[
        "Makarovskaya",
        "Makharovskaya",
        "\u041c\u0430\u0445\u0430\u0440\u043e\u0432\u0441\u043a\u0430\u044f"
    ],
    "wof:name":"Makharovskaya",
    "wof:placetype":"locality"
},
  "geometry": {"coordinates":[42.23167,61.49444],"type":"Point"}
}