{
  "type": "Feature",
  "properties": {
    "gn:admin1_code":"69",
    "gn:asciiname":"Pudyshi",
    "gn:country_code":"RU",
    "gn:dem":252,
    "gn:feature_class":"P",
    "gn:feature_code":"PPL",
    "gn:name":"Pudyshi",
    "gn:population":0,
    "gn:timezone":"Europe/Moscow",
    "iso:country":"RU",
    "wof:name":"Pudyshi",
    "wof:placetype":"locality"
},
  "geometry": {"coordinates":[34.97358,55.85513],"type":"Point"}
}