{
  "type": "Feature",
  "properties": {
    "gn:admin1_code":"60",
    "gn:asciiname":"Volosochevo",
    "gn:country_code":"RU",
    "gn:dem":69,
    "gn:feature_class":"P",
    "gn:feature_code":"PPL",
    "gn:name":"Volosochevo",
    "gn:population":0,
    "gn:timezone":"Europe/Moscow",
    "iso:country":"RU",
    "name:rus_x_preferred":[
        "\u0412\u043e\u043b\u043e\u0441\u043e\u0447\u0435\u0432\u043e"
    ],
    "wof:name":"Volosochevo",
    "wof:placetype":"locality"
},
  "geometry": {"coordinates":[28.7261,57.8322],"type":"Point"}
}