{
  "type": "Feature",
  "properties": {
    "gn:admin1_code":"62",
    "gn:asciiname":"Golovanovo",
    "gn:country_code":"RU",
    "gn:dem":126,
    "gn:feature_class":"P",
    "gn:feature_code":"PPL",
    "gn:name":"Golovanovo",
    "gn:population":0,
    "gn:timezone":"Europe/Moscow",
    "iso:country":"RU",
    "name:eng_x_preferred":[
        "Golovanovo"
    ],
    "name:nor_x_preferred":[
        "Golovanovo"
    ],
    "name:rus_x_preferred":[
        "\u0413\u043e\u043b\u043e\u0432\u0430\u043d\u043e\u0432\u043e"
    ],
    "name:und_x_variant":[
        "Uralovka"
    ],
    "wof:name":"Golovanovo",
    "wof:placetype":"locality"
},
  "geometry": {"coordinates":[40.45277,54.92616],"type":"Point"}
}