{
  "type": "Feature",
  "properties": {
    "gn:admin1_code":"11",
    "gn:asciiname":"Bulukhan",
    "gn:country_code":"RU",
    "gn:dem":551,
    "gn:feature_class":"P",
    "gn:feature_code":"PPL",
    "gn:name":"Bulukhan",
    "gn:population":0,
    "gn:timezone":"Asia/Irkutsk",
    "iso:country":"RU",
    "name:rus_x_preferred":[
        "\u0411\u0443\u043b\u0443\u0445\u0430\u043d"
    ],
    "name:und_x_variant":[
        "Bulukkhan",
        "Bulukhan"
    ],
    "wof:name":"Bulukhan",
    "wof:placetype":"locality"
},
  "geometry": {"coordinates":[111.17099,54.85626],"type":"Point"}
}