{
  "type": "Feature",
  "properties": {
    "gn:admin1_code":"37",
    "gn:asciiname":"Potapovo",
    "gn:country_code":"RU",
    "gn:dem":163,
    "gn:feature_class":"P",
    "gn:feature_code":"PPL",
    "gn:name":"Potapovo",
    "gn:population":0,
    "gn:timezone":"Europe/Moscow",
    "iso:country":"RU",
    "name:rus_x_preferred":[
        "\u041f\u043e\u0442\u0430\u043f\u043e\u0432\u043e"
    ],
    "wof:name":"Potapovo",
    "wof:placetype":"locality"
},
  "geometry": {"coordinates":[42.95077,58.81898],"type":"Point"}
}