{
  "type": "Feature",
  "properties": {
    "gn:admin1_code":"85",
    "gn:asciiname":"Trukhino",
    "gn:country_code":"RU",
    "gn:dem":137,
    "gn:feature_class":"P",
    "gn:feature_code":"PPL",
    "gn:name":"Trukhino",
    "gn:population":0,
    "gn:timezone":"Europe/Moscow",
    "iso:country":"RU",
    "name:rus_x_preferred":[
        "\u0422\u0440\u0443\u0445\u0438\u043d\u043e"
    ],
    "name:und_x_variant":[
        "\u0422\u0440\u0443\u0445\u0438\u043d\u043e"
    ],
    "wof:name":"Trukhino",
    "wof:placetype":"locality"
},
  "geometry": {"coordinates":[35.27294000000001,58.97888],"type":"Point"}
}