{
  "type": "Feature",
  "properties": {
    "gn:admin1_code":"69.0",
    "gn:asciiname":"Galiski",
    "gn:country_code":"RU",
    "gn:dem":171,
    "gn:feature_class":"P",
    "gn:feature_code":"PPL",
    "gn:name":"Galiski",
    "gn:population":0,
    "gn:timezone":"Europe/Moscow",
    "iso:country":"RU",
    "name:rus_x_preferred":[
        "\u0413\u0430\u043b\u0438\u0441\u043a\u0438"
    ],
    "name:und_x_variant":[
        "\u0413\u0430\u043b\u0438\u0441\u043a\u0438"
    ],
    "wof:name":"Galiski",
    "wof:placetype":"locality"
},
  "geometry": {"coordinates":[31.45926,55.18996],"type":"Point"}
}