{
  "type": "Feature",
  "properties": {
    "gn:admin1_code":"4.0",
    "gn:asciiname":"Pervomayskoye",
    "gn:country_code":"RU",
    "gn:dem":243,
    "gn:feature_class":"P",
    "gn:feature_code":"PPL",
    "gn:name":"Pervomayskoye",
    "gn:population":6500,
    "gn:timezone":"Asia/Barnaul",
    "iso:country":"RU",
    "wof:name":"Pervomayskoye",
    "wof:placetype":"locality",
    "wof:population":6500
},
  "geometry": {"coordinates":[85.25769,52.59888],"type":"Point"}
}