{
  "type": "Feature",
  "properties": {
    "gn:admin1_code":"37.0",
    "gn:asciiname":"Yuryatino",
    "gn:country_code":"RU",
    "gn:dem":160,
    "gn:feature_class":"P",
    "gn:feature_code":"PPL",
    "gn:name":"Yuryatino",
    "gn:population":0,
    "gn:timezone":"Europe/Moscow",
    "iso:country":"RU",
    "wof:name":"Yuryatino",
    "wof:placetype":"locality"
},
  "geometry": {"coordinates":[42.35049,57.9857],"type":"Point"}
}