{
  "type": "Feature",
  "properties": {
    "gn:admin1_code":"64",
    "gn:asciiname":"Lyutovskaya",
    "gn:cc2":"RU",
    "gn:country_code":"RU",
    "gn:dem":188,
    "gn:feature_class":"P",
    "gn:feature_code":"PPL",
    "gn:name":"Lyutovskaya",
    "gn:population":0,
    "gn:timezone":"Asia/Sakhalin",
    "iso:country":"RU",
    "name:rus_x_preferred":[
        "\u041b\u044e\u0442\u043e\u0432\u0441\u043a\u0430\u044f"
    ],
    "name:und_x_variant":[
        "Tomizawa",
        "Lyutovskaya",
        "\u041b\u044e\u0442\u043e\u0432\u0441\u043a\u0430\u044f"
    ],
    "wof:name":"Lyutovskaya",
    "wof:placetype":"locality"
},
  "geometry": {"coordinates":[142.23333,47.08333],"type":"Point"}
}