{
  "type": "Feature",
  "properties": {
    "gn:admin1_code":"4.0",
    "gn:asciiname":"Tyagun-Talovskiy",
    "gn:country_code":"RU",
    "gn:dem":329,
    "gn:feature_class":"P",
    "gn:feature_code":"PPL",
    "gn:name":"Tyagun-Talovskiy",
    "gn:population":0,
    "gn:timezone":"Asia/Barnaul",
    "iso:country":"RU",
    "name:rus_x_preferred":[
        "\u0422\u044f\u0433\u0443\u043d-\u0422\u0430\u043b\u043e\u0432\u0441\u043a\u0438\u0439"
    ],
    "wof:name":"Tyagun-Talovskiy",
    "wof:placetype":"locality"
},
  "geometry": {"coordinates":[85.7003,53.9759],"type":"Point"}
}