{
  "type": "Feature",
  "properties": {
    "gn:admin1_code":"90",
    "gn:asciiname":"Nizhniy Koz'myash",
    "gn:country_code":"RU",
    "gn:dem":174,
    "gn:feature_class":"P",
    "gn:feature_code":"PPL",
    "gn:name":"Nizhniy Koz\u2019myash",
    "gn:population":0,
    "gn:timezone":"Asia/Yekaterinburg",
    "iso:country":"RU",
    "name:rus_x_preferred":[
        "\u041d\u0438\u0436\u043d\u0438\u0439 \u041a\u043e\u0437\u044c\u043c\u044f\u0448"
    ],
    "name:und_x_variant":[
        "Nizhniy Koz\u2019myash"
    ],
    "wof:name":"Nizhniy Koz'myash",
    "wof:placetype":"locality"
},
  "geometry": {"coordinates":[56.32064,56.5288],"type":"Point"}
}