{
  "type": "Feature",
  "properties": {
    "gn:admin1_code":"69",
    "gn:asciiname":"Boltutino",
    "gn:country_code":"RU",
    "gn:dem":219,
    "gn:feature_class":"P",
    "gn:feature_code":"PPL",
    "gn:name":"Boltutino",
    "gn:population":0,
    "gn:timezone":"Europe/Moscow",
    "iso:country":"RU",
    "name:rus_x_preferred":[
        "\u0411\u043e\u043b\u0442\u0443\u0442\u0438\u043d\u043e"
    ],
    "name:und_x_variant":[
        "\u0411\u043e\u043b\u0442\u0443\u0442\u0438\u043d\u043e"
    ],
    "wof:name":"Boltutino",
    "wof:placetype":"locality"
},
  "geometry": {"coordinates":[33.42389,54.73944],"type":"Point"}
}