{
  "type": "Feature",
  "properties": {
    "gn:admin1_code":"64",
    "gn:asciiname":"Lovetskaya",
    "gn:country_code":"RU",
    "gn:dem":8,
    "gn:feature_class":"P",
    "gn:feature_code":"PPL",
    "gn:name":"Lovetskaya",
    "gn:population":0,
    "gn:timezone":"Asia/Sakhalin",
    "iso:country":"RU",
    "name:rus_x_preferred":[
        "\u041b\u043e\u0432\u0435\u0442\u0441\u043a\u0430\u044f"
    ],
    "name:und_x_variant":[
        "T\u014dbushi",
        "Lovetskoye",
        "T\u00f4busi",
        "Levetskoye",
        "Lovetskaya",
        "\u041b\u043e\u0432\u0435\u0442\u0441\u043a\u0430\u044f"
    ],
    "wof:name":"Lovetskaya",
    "wof:placetype":"locality"
},
  "geometry": {"coordinates":[141.86676,46.70229000000001],"type":"Point"}
}