{
  "type": "Feature",
  "properties": {
    "gn:admin1_code":"21",
    "gn:asciiname":"Mosyakovo",
    "gn:country_code":"RU",
    "gn:dem":139,
    "gn:feature_class":"P",
    "gn:feature_code":"PPL",
    "gn:name":"Mosyakovo",
    "gn:population":0,
    "gn:timezone":"Europe/Moscow",
    "iso:country":"RU",
    "name:rus_x_preferred":[
        "\u041c\u043e\u0441\u044f\u043a\u043e\u0432\u043e"
    ],
    "wof:name":"Mosyakovo",
    "wof:placetype":"locality"
},
  "geometry": {"coordinates":[40.26376,56.84639],"type":"Point"}
}