{
  "type": "Feature",
  "properties": {
    "gn:admin1_code":"28",
    "gn:asciiname":"Lumbushi-Krasil'nikovo",
    "gn:country_code":"RU",
    "gn:dem":38,
    "gn:feature_class":"P",
    "gn:feature_code":"PPL",
    "gn:name":"Lumbushi-Krasil\u2019nikovo",
    "gn:population":0,
    "gn:timezone":"Europe/Moscow",
    "iso:country":"RU",
    "name:rus_x_preferred":[
        "\u041b\u0443\u043c\u0431\u0443\u0448\u0438-\u041a\u0440\u0430\u0441\u0438\u043b\u044c\u043d\u0438\u043a\u043e\u0432\u043e"
    ],
    "name:und_x_variant":[
        "Krasil\u2019nikovo",
        "Lumbushi-Krasil\u2019nikovo",
        "\u041b\u0443\u043c\u0431\u0443\u0448\u0438-\u041a\u0440\u0430\u0441\u0438\u043b\u044c\u043d\u0438\u043a\u043e\u0432\u043e"
    ],
    "wof:name":"Lumbushi-Krasil'nikovo",
    "wof:placetype":"locality"
},
  "geometry": {"coordinates":[34.51667,62.91667],"type":"Point"}
}