{
  "type": "Feature",
  "properties": {
    "gn:admin1_code":"61",
    "gn:asciiname":"Ilyukhin",
    "gn:country_code":"RU",
    "gn:dem":51,
    "gn:feature_class":"P",
    "gn:feature_code":"PPL",
    "gn:name":"Ilyukhin",
    "gn:population":0,
    "gn:timezone":"Europe/Moscow",
    "iso:country":"RU",
    "name:rus_x_preferred":[
        "\u0418\u043b\u044e\u0445\u0438\u043d"
    ],
    "name:und_x_variant":[
        "\u0418\u043b\u044e\u0445\u0438\u043d"
    ],
    "wof:name":"Ilyukhin",
    "wof:placetype":"locality"
},
  "geometry": {"coordinates":[40.54005,48.50678],"type":"Point"}
}