{
  "type": "Feature",
  "properties": {
    "gn:admin1_code":"88",
    "gn:asciiname":"Kostyayevo",
    "gn:country_code":"RU",
    "gn:dem":106,
    "gn:feature_class":"P",
    "gn:feature_code":"PPL",
    "gn:name":"Kostyayevo",
    "gn:population":0,
    "gn:timezone":"Europe/Moscow",
    "iso:country":"RU",
    "name:rus_x_preferred":[
        "\u041a\u043e\u0441\u0442\u044f\u0435\u0432\u043e"
    ],
    "wof:name":"Kostyayevo",
    "wof:placetype":"locality"
},
  "geometry": {"coordinates":[39.5375,57.67097],"type":"Point"}
}