{
  "type": "Feature",
  "properties": {
    "gn:admin1_code":"33.0",
    "gn:asciiname":"Butorinskaya",
    "gn:country_code":"RU",
    "gn:dem":173,
    "gn:feature_class":"P",
    "gn:feature_code":"PPL",
    "gn:name":"Butorinskaya",
    "gn:population":0,
    "gn:timezone":"Europe/Kirov",
    "iso:country":"RU",
    "name:eng_x_preferred":[
        "Butorinskaya"
    ],
    "name:nor_x_preferred":[
        "Butorinskaja"
    ],
    "name:rus_x_preferred":[
        "\u0411\u0443\u0442\u043e\u0440\u0438\u043d\u0441\u043a\u0430\u044f"
    ],
    "name:und_x_variant":[
        "Buturinskaya",
        "\u0411\u0443\u0442\u043e\u0440\u0438\u043d\u0441\u043a\u0430\u044f",
        "Butorinskaya"
    ],
    "wof:name":"Butorinskaya",
    "wof:placetype":"locality"
},
  "geometry": {"coordinates":[47.2445,58.46236],"type":"Point"}
}