{
  "type": "Feature",
  "properties": {
    "gn:admin1_code":"93",
    "gn:asciiname":"Nanagry",
    "gn:country_code":"RU",
    "gn:dem":514,
    "gn:feature_class":"P",
    "gn:feature_code":"PPL",
    "gn:name":"Nanagry",
    "gn:population":0,
    "gn:timezone":"Asia/Chita",
    "iso:country":"RU",
    "name:rus_x_preferred":[
        "\u041d\u0430\u043d\u0430\u0433\u0440\u044b"
    ],
    "wof:name":"Nanagry",
    "wof:placetype":"locality"
},
  "geometry": {"coordinates":[118.29867,53.23965],"type":"Point"}
}