{
  "type": "Feature",
  "properties": {
    "gn:admin1_code":"73",
    "gn:asciiname":"Staraya Zadorovka",
    "gn:country_code":"RU",
    "gn:dem":169,
    "gn:feature_class":"P",
    "gn:feature_code":"PPL",
    "gn:name":"Staraya Zadorovka",
    "gn:population":0,
    "gn:timezone":"Europe/Moscow",
    "iso:country":"RU",
    "name:rus_x_preferred":[
        "\u0421\u0442\u0430\u0440\u0430\u044f \u0417\u0430\u0434\u043e\u0440\u043e\u0432\u043a\u0430"
    ],
    "name:und_x_variant":[
        "Staraya Zaderovka",
        "Staraya Zadorovka"
    ],
    "wof:name":"Staraya Zadorovka",
    "wof:placetype":"locality"
},
  "geometry": {"coordinates":[47.64394,54.70478000000001],"type":"Point"}
}