{
  "type": "Feature",
  "properties": {
    "gn:admin1_code":"86",
    "gn:asciiname":"Obrez",
    "gn:country_code":"RU",
    "gn:dem":113,
    "gn:feature_class":"P",
    "gn:feature_code":"PPL",
    "gn:name":"Obrez",
    "gn:population":0,
    "gn:timezone":"Europe/Moscow",
    "iso:country":"RU",
    "name:rus_x_preferred":[
        "\u041e\u0431\u0440\u0435\u0437"
    ],
    "name:und_x_variant":[
        "\u041e\u0431\u0440\u0435\u0437"
    ],
    "wof:name":"Obrez",
    "wof:placetype":"locality"
},
  "geometry": {"coordinates":[38.5266,51.0608],"type":"Point"}
}