{
  "type": "Feature",
  "properties": {
    "gn:admin1_code":"86.0",
    "gn:asciiname":"Naumovskiy",
    "gn:country_code":"RU",
    "gn:dem":104,
    "gn:feature_class":"P",
    "gn:feature_code":"PPL",
    "gn:name":"Naumovskiy",
    "gn:population":0,
    "gn:timezone":"Europe/Moscow",
    "iso:country":"RU",
    "wof:name":"Naumovskiy",
    "wof:placetype":"locality"
},
  "geometry": {"coordinates":[41.19167,51.41917],"type":"Point"}
}