{
  "type": "Feature",
  "properties": {
    "gn:admin1_code":"88.0",
    "gn:asciiname":"Dor-Vaganskiy",
    "gn:country_code":"RU",
    "gn:dem":150,
    "gn:feature_class":"P",
    "gn:feature_code":"PPL",
    "gn:name":"Dor-Vaganskiy",
    "gn:population":0,
    "gn:timezone":"Europe/Moscow",
    "iso:country":"RU",
    "name:rus_x_preferred":[
        "\u0414\u043e\u0440-\u0412\u0430\u0433\u0430\u043d\u0441\u043a\u0438\u0439"
    ],
    "wof:name":"Dor-Vaganskiy",
    "wof:placetype":"locality"
},
  "geometry": {"coordinates":[40.10404000000001,58.45331],"type":"Point"}
}