{
  "type": "Feature",
  "properties": {
    "gn:admin1_code":"20",
    "gn:asciiname":"Kultuk",
    "gn:country_code":"RU",
    "gn:dem":458,
    "gn:feature_class":"P",
    "gn:feature_code":"PPL",
    "gn:name":"Kultuk",
    "gn:population":0,
    "gn:timezone":"Asia/Irkutsk",
    "iso:country":"RU",
    "name:eng_x_preferred":[
        "Kultuk"
    ],
    "name:nor_x_preferred":[
        "Kultuk"
    ],
    "name:rus_x_preferred":[
        "\u041a\u0443\u043b\u0442\u0443\u043a"
    ],
    "name:und_x_variant":[
        "\u041a\u0443\u043b\u0442\u0443\u043a",
        "Kultuk"
    ],
    "wof:name":"Kultuk",
    "wof:placetype":"locality"
},
  "geometry": {"coordinates":[103.48111,52.56306],"type":"Point"}
}