{
  "type": "Feature",
  "properties": {
    "gn:admin1_code":"88",
    "gn:asciiname":"Balakirevo",
    "gn:country_code":"RU",
    "gn:dem":146,
    "gn:feature_class":"P",
    "gn:feature_code":"PPL",
    "gn:name":"Balakirevo",
    "gn:population":0,
    "gn:timezone":"Europe/Moscow",
    "iso:country":"RU",
    "name:ara_x_preferred":[
        "\u0628\u0627\u0644\u0627\u0643\u0627\u064a\u0631\u0641\u0648"
    ],
    "name:che_x_preferred":[
        "\u0411\u0430\u043b\u0430\u043a\u0438\u0440\u0435\u0432\u043e"
    ],
    "name:deu_x_preferred":[
        "Balakirewo"
    ],
    "name:ita_x_preferred":[
        "Balakirevo"
    ],
    "name:pol_x_preferred":[
        "Ba\u0142akiriewo"
    ],
    "name:rus_x_preferred":[
        "\u0411\u0430\u043b\u0430\u043a\u0438\u0440\u0435\u0432\u043e"
    ],
    "wof:name":"Balakirevo",
    "wof:placetype":"locality"
},
  "geometry": {"coordinates":[39.44149,57.56385],"type":"Point"}
}