{
  "type": "Feature",
  "properties": {
    "gn:admin1_code":"69",
    "gn:asciiname":"Litivlya",
    "gn:country_code":"RU",
    "gn:dem":174,
    "gn:feature_class":"P",
    "gn:feature_code":"PPL",
    "gn:name":"Litivlya",
    "gn:population":0,
    "gn:timezone":"Europe/Moscow",
    "iso:country":"RU",
    "name:eng_x_preferred":[
        "Litivlya"
    ],
    "name:nor_x_preferred":[
        "Litivlja"
    ],
    "name:rus_x_preferred":[
        "\u041b\u0438\u0442\u0438\u0432\u043b\u044f"
    ],
    "name:und_x_variant":[
        "\u041b\u0438\u0442\u0438\u0432\u043b\u044f",
        "Litivlya"
    ],
    "wof:name":"Litivlya",
    "wof:placetype":"locality"
},
  "geometry": {"coordinates":[31.27333,54.63916999999999],"type":"Point"}
}