{
  "type": "Feature",
  "properties": {
    "gn:admin1_code":"61",
    "gn:asciiname":"Mayskiy",
    "gn:country_code":"RU",
    "gn:dem":93,
    "gn:feature_class":"P",
    "gn:feature_code":"PPL",
    "gn:name":"Mayskiy",
    "gn:population":0,
    "gn:timezone":"Europe/Moscow",
    "iso:country":"RU",
    "name:rus_x_preferred":[
        "\u041c\u0430\u0439\u0441\u043a\u0438\u0439"
    ],
    "wof:name":"Mayskiy",
    "wof:placetype":"locality"
},
  "geometry": {"coordinates":[41.02861,46.49639000000001],"type":"Point"}
}