{
  "type": "Feature",
  "properties": {
    "gn:admin1_code":"60",
    "gn:asciiname":"Polyakovo",
    "gn:country_code":"RU",
    "gn:dem":96,
    "gn:feature_class":"P",
    "gn:feature_code":"PPL",
    "gn:name":"Polyakovo",
    "gn:population":0,
    "gn:timezone":"Europe/Moscow",
    "iso:country":"RU",
    "name:rus_x_preferred":[
        "\u041f\u043e\u043b\u044f\u043a\u043e\u0432\u043e"
    ],
    "wof:name":"Polyakovo",
    "wof:placetype":"locality"
},
  "geometry": {"coordinates":[28.08309,56.80974000000001],"type":"Point"}
}