{
  "type": "Feature",
  "properties": {
    "gn:admin1_code":"17.0",
    "gn:asciiname":"Arbakol'",
    "gn:country_code":"RU",
    "gn:dem":-22,
    "gn:feature_class":"P",
    "gn:feature_code":"PPL",
    "gn:name":"Arbakol\u2019",
    "gn:population":0,
    "gn:timezone":"Europe/Moscow",
    "iso:country":"RU",
    "name:nor_x_preferred":[
        "Arbakol"
    ],
    "name:rus_x_preferred":[
        "\u0410\u0440\u0431\u0430\u043a\u043e\u043b\u044c"
    ],
    "name:und_x_variant":[
        "Arbakoly",
        "Arbakol\u2019"
    ],
    "wof:name":"Arbakol'",
    "wof:placetype":"locality"
},
  "geometry": {"coordinates":[47.22917,43.89528],"type":"Point"}
}