{
  "type": "Feature",
  "properties": {
    "gn:admin1_code":"72",
    "gn:asciiname":"Pustovalovo",
    "gn:country_code":"RU",
    "gn:dem":168,
    "gn:feature_class":"P",
    "gn:feature_code":"PPL",
    "gn:name":"Pustovalovo",
    "gn:population":0,
    "gn:timezone":"Europe/Moscow",
    "iso:country":"RU",
    "name:rus_x_preferred":[
        "\u041f\u0443\u0441\u0442\u043e\u0432\u0430\u043b\u043e\u0432\u043e"
    ],
    "name:und_x_variant":[
        "Pustovalavka",
        "Pustovalovka",
        "Pustovalovo",
        "\u041f\u0443\u0441\u0442\u043e\u0432\u0430\u043b\u043e\u0432\u043e"
    ],
    "wof:name":"Pustovalovo",
    "wof:placetype":"locality"
},
  "geometry": {"coordinates":[41.83376,51.92408],"type":"Point"}
}