{
  "type": "Feature",
  "properties": {
    "gn:admin1_code":"59",
    "gn:asciiname":"Nikolo-Mikhaylovka",
    "gn:country_code":"RU",
    "gn:dem":130,
    "gn:feature_class":"P",
    "gn:feature_code":"PPL",
    "gn:name":"Nikolo-Mikhaylovka",
    "gn:population":0,
    "gn:timezone":"Asia/Vladivostok",
    "iso:country":"RU",
    "name:eng_x_preferred":[
        "Nikolo-Mikhaylovka"
    ],
    "name:nor_x_preferred":[
        "Nikolo-Mikhajlovka"
    ],
    "name:rus_x_preferred":[
        "\u041d\u0438\u043a\u043e\u043b\u043e-\u041c\u0438\u0445\u0430\u0439\u043b\u043e\u0432\u043a\u0430"
    ],
    "wof:name":"Nikolo-Mikhaylovka",
    "wof:placetype":"locality"
},
  "geometry": {"coordinates":[133.63768000000002,44.7084],"type":"Point"}
}