{
  "type": "Feature",
  "properties": {
    "gn:admin1_code":"42",
    "gn:admin2_code":"575409",
    "gn:asciiname":"Karpovskaya",
    "gn:cc2":"RU",
    "gn:country_code":"RU",
    "gn:dem":182,
    "gn:feature_class":"P",
    "gn:feature_code":"PPL",
    "gn:name":"Karpovskaya",
    "gn:population":0,
    "gn:timezone":"Europe/Moscow",
    "iso:country":"RU",
    "name:rus_x_preferred":[
        "\u041a\u0430\u0440\u043f\u043e\u0432\u0441\u043a\u0430\u044f"
    ],
    "name:und_x_variant":[
        "Karpovskoye",
        "Karpovskaya"
    ],
    "wof:name":"Karpovskaya",
    "wof:placetype":"locality"
},
  "geometry": {"coordinates":[34.27139,59.58416999999999],"type":"Point"}
}