{
  "type": "Feature",
  "properties": {
    "gn:admin1_code":"67.0",
    "gn:asciiname":"Abalikha",
    "gn:country_code":"RU",
    "gn:dem":238,
    "gn:feature_class":"P",
    "gn:feature_code":"PPL",
    "gn:name":"Abalikha",
    "gn:population":0,
    "gn:timezone":"Europe/Saratov",
    "iso:country":"RU",
    "name:nor_x_preferred":[
        "Abalikha"
    ],
    "name:rus_x_preferred":[
        "\u0410\u0431\u0430\u043b\u0438\u0445\u0430"
    ],
    "name:und_x_variant":[
        "Abolikha"
    ],
    "wof:name":"Abalikha",
    "wof:placetype":"locality"
},
  "geometry": {"coordinates":[46.06667,52.46666999999999],"type":"Point"}
}