{
  "type": "Feature",
  "properties": {
    "gn:country":"RU",
    "gn:fcode":"PPL",
    "gn:population":2189,
    "iso:country":"RU",
    "name:eng_x_preferred":[
        "Losinyy"
    ],
    "name:nor_x_preferred":[
        "Losinyj"
    ],
    "name:rus_x_preferred":[
        "\u041b\u043e\u0441\u0438\u043d\u044b\u0439"
    ],
    "qs:name":"Losinyy",
    "qs:name_adm0":"Russia",
    "qs:name_adm1":"Sverdlovsk Oblast",
    "qs:photos_9r":0,
    "qs:photos_sr":0,
    "qs:placetype":"Town",
    "qs:pop_sr":"4",
    "wof:name":"Losinyy",
    "wof:placetype":"locality",
    "wof:population":2189
},
  "geometry": {"coordinates":[61.06663,57.13862],"type":"Point"}
}