{
  "type": "Feature",
  "properties": {
    "gn:admin1_code":"83",
    "gn:asciiname":"Stepanovo",
    "gn:country_code":"RU",
    "gn:dem":138,
    "gn:feature_class":"P",
    "gn:feature_code":"PPL",
    "gn:name":"Stepanovo",
    "gn:population":0,
    "gn:timezone":"Europe/Moscow",
    "iso:country":"RU",
    "name:eng_x_preferred":[
        "Stepanovo"
    ],
    "name:nor_x_preferred":[
        "Stepanovo"
    ],
    "name:rus_x_preferred":[
        "\u0421\u0442\u0435\u043f\u0430\u043d\u043e\u0432\u043e"
    ],
    "name:und_x_variant":[
        "\u0421\u0442\u0435\u043f\u0430\u043d\u043e\u0432\u043e",
        "Stepanovo"
    ],
    "wof:name":"Stepanovo",
    "wof:placetype":"locality"
},
  "geometry": {"coordinates":[40.4433,55.85204],"type":"Point"}
}