{
  "type": "Feature",
  "properties": {
    "gn:admin1_code":"60",
    "gn:asciiname":"Nivy",
    "gn:country_code":"RU",
    "gn:dem":177,
    "gn:feature_class":"P",
    "gn:feature_code":"PPL",
    "gn:name":"Nivy",
    "gn:population":0,
    "gn:timezone":"Europe/Moscow",
    "iso:country":"RU",
    "name:rus_x_preferred":[
        "\u041d\u0438\u0432\u044b"
    ],
    "name:und_x_variant":[
        "\u041d\u0438\u0432\u044b"
    ],
    "wof:name":"Nivy",
    "wof:placetype":"locality"
},
  "geometry": {"coordinates":[30.9968,56.3867],"type":"Point"}
}