{
  "type": "Feature",
  "properties": {
    "gn:admin1_code":"85",
    "gn:asciiname":"Izlyadeyevo",
    "gn:country_code":"RU",
    "gn:dem":166,
    "gn:feature_class":"P",
    "gn:feature_code":"PPL",
    "gn:name":"Izlyadeyevo",
    "gn:population":0,
    "gn:timezone":"Europe/Moscow",
    "iso:country":"RU",
    "name:rus_x_preferred":[
        "\u0418\u0437\u043b\u044f\u0434\u0435\u0435\u0432\u043e"
    ],
    "name:und_x_variant":[
        "\u0418\u0437\u043b\u044f\u0434\u0435\u0435\u0432\u043e"
    ],
    "wof:name":"Izlyadeyevo",
    "wof:placetype":"locality"
},
  "geometry": {"coordinates":[36.3694,58.5158],"type":"Point"}
}