{
  "type": "Feature",
  "properties": {
    "gn:admin1_code":"69",
    "gn:asciiname":"Pastrikhovo",
    "gn:country_code":"RU",
    "gn:dem":257,
    "gn:feature_class":"P",
    "gn:feature_code":"PPL",
    "gn:name":"Pastrikhovo",
    "gn:population":0,
    "gn:timezone":"Europe/Moscow",
    "iso:country":"RU",
    "name:rus_x_preferred":[
        "\u041f\u0430\u0441\u0442\u0440\u0438\u0445\u043e\u0432\u043e"
    ],
    "name:und_x_variant":[
        "Pastrikhovo"
    ],
    "wof:name":"Pastrikhovo",
    "wof:placetype":"locality"
},
  "geometry": {"coordinates":[32.1701,55.2497],"type":"Point"}
}