{
  "type": "Feature",
  "properties": {
    "gn:admin1_code":"65",
    "gn:asciiname":"Obrazets",
    "gn:country_code":"RU",
    "gn:dem":35,
    "gn:feature_class":"P",
    "gn:feature_code":"PPL",
    "gn:name":"Obrazets",
    "gn:population":0,
    "gn:timezone":"Europe/Samara",
    "iso:country":"RU",
    "name:rus_x_preferred":[
        "\u041e\u0431\u0440\u0430\u0437\u0435\u0446"
    ],
    "wof:name":"Obrazets",
    "wof:placetype":"locality"
},
  "geometry": {"coordinates":[50.76667,53.26667],"type":"Point"}
}