{
  "type": "Feature",
  "properties": {
    "gn:admin1_code":"37",
    "gn:asciiname":"Sorokinskiy",
    "gn:country_code":"RU",
    "gn:dem":132,
    "gn:feature_class":"P",
    "gn:feature_code":"PPL",
    "gn:name":"Sorokinskiy",
    "gn:population":0,
    "gn:timezone":"Europe/Moscow",
    "iso:country":"RU",
    "name:rus_x_preferred":[
        "\u0421\u043e\u0440\u043e\u043a\u0438\u043d\u0441\u043a\u0438\u0439"
    ],
    "name:und_x_variant":[
        "\u0421\u043e\u0440\u043e\u043a\u0438\u043d\u0441\u043a\u0438\u0439"
    ],
    "wof:name":"Sorokinskiy",
    "wof:placetype":"locality"
},
  "geometry": {"coordinates":[46.66387,58.67556],"type":"Point"}
}