{
  "type": "Feature",
  "properties": {
    "gn:admin1_code":"67",
    "gn:asciiname":"Irgiz",
    "gn:country_code":"RU",
    "gn:dem":38,
    "gn:feature_class":"P",
    "gn:feature_code":"PPL",
    "gn:name":"Irgiz",
    "gn:population":0,
    "gn:timezone":"Europe/Saratov",
    "iso:country":"RU",
    "name:ces_x_preferred":[
        "Irgiz"
    ],
    "name:deu_x_preferred":[
        "Irgis"
    ],
    "name:hun_x_preferred":[
        "Irgiz"
    ],
    "name:ita_x_preferred":[
        "Irgiz"
    ],
    "name:rus_x_preferred":[
        "\u0418\u0440\u0433\u0438\u0437"
    ],
    "wof:name":"Irgiz",
    "wof:placetype":"locality"
},
  "geometry": {"coordinates":[48.5025,51.9382],"type":"Point"}
}