{
  "type": "Feature",
  "properties": {
    "gn:admin1_code":"28",
    "gn:asciiname":"Valasozero",
    "gn:country_code":"RU",
    "gn:dem":84,
    "gn:feature_class":"P",
    "gn:feature_code":"PPL",
    "gn:name":"Valasozero",
    "gn:population":0,
    "gn:timezone":"Europe/Moscow",
    "iso:country":"RU",
    "name:fin_x_preferred":[
        "Valasj\u00e4rvi"
    ],
    "wof:name":"Valasozero",
    "wof:placetype":"locality"
},
  "geometry": {"coordinates":[32.88071,66.19448],"type":"Point"}
}