{
  "type": "Feature",
  "properties": {
    "gn:admin1_code":"41",
    "gn:asciiname":"Kamenka Pervaya",
    "gn:country_code":"RU",
    "gn:dem":253,
    "gn:feature_class":"P",
    "gn:feature_code":"PPL",
    "gn:name":"Kamenka Pervaya",
    "gn:population":0,
    "gn:timezone":"Europe/Moscow",
    "iso:country":"RU",
    "name:rus_x_preferred":[
        "\u041a\u0430\u043c\u0435\u043d\u043a\u0430 \u041f\u0435\u0440\u0432\u0430\u044f"
    ],
    "name:und_x_variant":[
        "Khmelevoye",
        "Kamenka",
        "Kamenka Pervaya"
    ],
    "wof:name":"Kamenka Pervaya",
    "wof:placetype":"locality"
},
  "geometry": {"coordinates":[37.0087,51.5386],"type":"Point"}
}