{
  "type": "Feature",
  "properties": {
    "gn:admin1_code":"60",
    "gn:asciiname":"Ferovo",
    "gn:country_code":"RU",
    "gn:dem":155,
    "gn:feature_class":"P",
    "gn:feature_code":"PPL",
    "gn:name":"Ferovo",
    "gn:population":0,
    "gn:timezone":"Europe/Moscow",
    "iso:country":"RU",
    "name:rus_x_preferred":[
        "\u0424\u0435\u0440\u043e\u0432\u043e"
    ],
    "wof:name":"Ferovo",
    "wof:placetype":"locality"
},
  "geometry": {"coordinates":[30.4843,56.1119],"type":"Point"}
}