{
  "type": "Feature",
  "properties": {
    "gn:admin1_code":"10",
    "gn:asciiname":"Komarovskiy",
    "gn:country_code":"RU",
    "gn:dem":218,
    "gn:feature_class":"P",
    "gn:feature_code":"PPL",
    "gn:name":"Komarovskiy",
    "gn:population":0,
    "gn:timezone":"Europe/Moscow",
    "iso:country":"RU",
    "name:rus_x_preferred":[
        "\u041a\u043e\u043c\u0430\u0440\u043e\u0432\u0441\u043a\u0438\u0439"
    ],
    "wof:name":"Komarovskiy",
    "wof:placetype":"locality"
},
  "geometry": {"coordinates":[34.8464,52.3838],"type":"Point"}
}