{
  "type": "Feature",
  "properties": {
    "gn:admin1_code":"60",
    "gn:asciiname":"Suk'yankino",
    "gn:country_code":"RU",
    "gn:dem":149,
    "gn:feature_class":"P",
    "gn:feature_code":"PPL",
    "gn:name":"Suk\u2019yankino",
    "gn:population":0,
    "gn:timezone":"Europe/Moscow",
    "iso:country":"RU",
    "name:rus_x_preferred":[
        "\u0421\u0443\u043a\u044c\u044f\u043d\u043a\u0438\u043d\u043e"
    ],
    "name:und_x_variant":[
        "Suk\u2019yankino",
        "\u0421\u0443\u043a\u044c\u044f\u043d\u043a\u0438\u043d\u043e"
    ],
    "wof:name":"Suk'yankino",
    "wof:placetype":"locality"
},
  "geometry": {"coordinates":[30.5173,56.1336],"type":"Point"}
}