{
  "type": "Feature",
  "properties": {
    "gn:admin1_code":"10.0",
    "gn:asciiname":"Golevsk",
    "gn:country_code":"RU",
    "gn:dem":162,
    "gn:feature_class":"P",
    "gn:feature_code":"PPL",
    "gn:name":"Golevsk",
    "gn:population":0,
    "gn:timezone":"Europe/Moscow",
    "iso:country":"RU",
    "name:rus_x_preferred":[
        "\u0413\u043e\u043b\u0435\u0432\u0441\u043a"
    ],
    "name:und_x_variant":[
        "\u0413\u043e\u043b\u0435\u0432\u0441\u043a",
        "Golevskaya"
    ],
    "wof:name":"Golevsk",
    "wof:placetype":"locality"
},
  "geometry": {"coordinates":[33.77267,52.66672],"type":"Point"}
}