{
  "type": "Feature",
  "properties": {
    "gn:admin1_code":"93",
    "gn:asciiname":"Ust'-Turga",
    "gn:country_code":"RU",
    "gn:dem":645,
    "gn:feature_class":"P",
    "gn:feature_code":"PPL",
    "gn:name":"Ust\u2019-Turga",
    "gn:population":0,
    "gn:timezone":"Asia/Chita",
    "iso:country":"RU",
    "wof:name":"Ust'-Turga",
    "wof:placetype":"locality"
},
  "geometry": {"coordinates":[115.71666999999999,50.83333],"type":"Point"}
}