{
  "type": "Feature",
  "properties": {
    "gn:admin1_code":"83.0",
    "gn:asciiname":"Stepkovo",
    "gn:country_code":"RU",
    "gn:dem":122,
    "gn:feature_class":"P",
    "gn:feature_code":"PPL",
    "gn:name":"Stepkovo",
    "gn:population":0,
    "gn:timezone":"Europe/Moscow",
    "iso:country":"RU",
    "name:nor_x_preferred":[
        "Stepkovo"
    ],
    "name:rus_x_preferred":[
        "\u0421\u0442\u0435\u043f\u043a\u043e\u0432\u043e"
    ],
    "wof:name":"Stepkovo",
    "wof:placetype":"locality"
},
  "geometry": {"coordinates":[42.03397,56.14277],"type":"Point"}
}