{
  "type": "Feature",
  "properties": {
    "gn:admin1_code":"69",
    "gn:asciiname":"Dementeyevka",
    "gn:country_code":"RU",
    "gn:dem":219,
    "gn:feature_class":"P",
    "gn:feature_code":"PPL",
    "gn:name":"Dementeyevka",
    "gn:population":0,
    "gn:timezone":"Europe/Moscow",
    "iso:country":"RU",
    "name:rus_x_preferred":[
        "\u0414\u0435\u043c\u0435\u043d\u0442\u0435\u0435\u0432\u043a\u0430"
    ],
    "name:und_x_variant":[
        "\u0414\u0435\u043c\u0435\u043d\u0442\u0435\u0435\u0432\u043a\u0430"
    ],
    "wof:name":"Dementeyevka",
    "wof:placetype":"locality"
},
  "geometry": {"coordinates":[33.45139,54.66917],"type":"Point"}
}