{
  "type": "Feature",
  "properties": {
    "gn:admin1_code":"21.0",
    "gn:asciiname":"Demidovo",
    "gn:country_code":"RU",
    "gn:dem":113,
    "gn:feature_class":"P",
    "gn:feature_code":"PPL",
    "gn:name":"Demidovo",
    "gn:population":0,
    "gn:timezone":"Europe/Moscow",
    "iso:country":"RU",
    "name:che_x_preferred":[
        "\u0414\u0435\u043c\u0438\u0434\u043e\u0432\u043e"
    ],
    "name:rus_x_preferred":[
        "\u0414\u0435\u043c\u0438\u0434\u043e\u0432\u043e"
    ],
    "wof:name":"Demidovo",
    "wof:placetype":"locality"
},
  "geometry": {"coordinates":[41.86004000000001,57.27549000000001],"type":"Point"}
}