{
  "type": "Feature",
  "properties": {
    "gn:admin1_code":"33",
    "gn:asciiname":"Svetlakovy",
    "gn:country_code":"RU",
    "gn:dem":168,
    "gn:feature_class":"P",
    "gn:feature_code":"PPL",
    "gn:name":"Svetlakovy",
    "gn:population":0,
    "gn:timezone":"Europe/Kirov",
    "iso:country":"RU",
    "name:und_x_variant":[
        "Svetlakovskiy",
        "Svetlakovskaya",
        "Svetlakovy"
    ],
    "wof:name":"Svetlakovy",
    "wof:placetype":"locality"
},
  "geometry": {"coordinates":[52.96802,59.28426],"type":"Point"}
}