{
  "type": "Feature",
  "properties": {
    "gn:admin1_code":"77.0",
    "gn:asciiname":"Boyarnikovo",
    "gn:country_code":"RU",
    "gn:dem":237,
    "gn:feature_class":"P",
    "gn:feature_code":"PPL",
    "gn:name":"Boyarnikovo",
    "gn:population":0,
    "gn:timezone":"Europe/Moscow",
    "iso:country":"RU",
    "name:rus_x_preferred":[
        "\u0411\u043e\u044f\u0440\u043d\u0438\u043a\u043e\u0432\u043e"
    ],
    "name:und_x_variant":[
        "\u0411\u043e\u044f\u0440\u043d\u0438\u043a\u043e\u0432\u043e"
    ],
    "wof:name":"Boyarnikovo",
    "wof:placetype":"locality"
},
  "geometry": {"coordinates":[34.41432,56.64836],"type":"Point"}
}