{
  "type": "Feature",
  "properties": {
    "gn:admin1_code":"90",
    "gn:asciiname":"Shchekolova",
    "gn:country_code":"RU",
    "gn:dem":193,
    "gn:feature_class":"P",
    "gn:feature_code":"PPL",
    "gn:name":"Shchekolova",
    "gn:population":0,
    "gn:timezone":"Asia/Yekaterinburg",
    "iso:country":"RU",
    "name:rus_x_preferred":[
        "\u0429\u0435\u043a\u043e\u043b\u043e\u0432\u0430"
    ],
    "name:und_x_variant":[
        "\u0429\u0435\u043a\u043e\u043b\u043e\u0432\u0430"
    ],
    "wof:name":"Shchekolova",
    "wof:placetype":"locality"
},
  "geometry": {"coordinates":[54.5087,59.2837],"type":"Point"}
}