{
  "type": "Feature",
  "properties": {
    "gn:admin1_code":"88.0",
    "gn:asciiname":"Safronovo",
    "gn:country_code":"RU",
    "gn:dem":99,
    "gn:feature_class":"P",
    "gn:feature_code":"PPL",
    "gn:name":"Safronovo",
    "gn:population":0,
    "gn:timezone":"Europe/Moscow",
    "iso:country":"RU",
    "name:rus_x_preferred":[
        "\u0421\u0430\u0444\u0440\u043e\u043d\u043e\u0432\u043e"
    ],
    "name:und_x_variant":[
        "Sopronovo",
        "Safronovo"
    ],
    "wof:name":"Safronovo",
    "wof:placetype":"locality"
},
  "geometry": {"coordinates":[40.45219,58.09541],"type":"Point"}
}