{
  "type": "Feature",
  "properties": {
    "gn:admin1_code":"11",
    "gn:asciiname":"Moygoty",
    "gn:country_code":"RU",
    "gn:dem":1009,
    "gn:feature_class":"P",
    "gn:feature_code":"PPL",
    "gn:name":"Moygoty",
    "gn:population":0,
    "gn:timezone":"Asia/Irkutsk",
    "iso:country":"RU",
    "name:rus_x_preferred":[
        "\u041c\u043e\u0439\u0433\u043e\u0442\u044b"
    ],
    "name:und_x_variant":[
        "Mogoyty",
        "Moygoty"
    ],
    "wof:name":"Moygoty",
    "wof:placetype":"locality"
},
  "geometry": {"coordinates":[101.3882,51.6476],"type":"Point"}
}