{
  "type": "Feature",
  "properties": {
    "gn:admin1_code":"37",
    "gn:asciiname":"Shuyskiy Pochinok",
    "gn:country_code":"RU",
    "gn:dem":97,
    "gn:feature_class":"P",
    "gn:feature_code":"PPL",
    "gn:name":"Shuyskiy Pochinok",
    "gn:population":0,
    "gn:timezone":"Europe/Moscow",
    "iso:country":"RU",
    "name:rus_x_preferred":[
        "\u0428\u0443\u0439\u0441\u043a\u0438\u0439 \u041f\u043e\u0447\u0438\u043d\u043e\u043a"
    ],
    "name:und_x_variant":[
        "\u0428\u0443\u0439\u0441\u043a\u0438\u0439 \u041f\u043e\u0447\u0438\u043d\u043e\u043a"
    ],
    "wof:name":"Shuyskiy Pochinok",
    "wof:placetype":"locality"
},
  "geometry": {"coordinates":[43.36733,57.93896],"type":"Point"}
}