{
  "type": "Feature",
  "properties": {
    "gn:admin1_code":"90.0",
    "gn:asciiname":"Yeldushino",
    "gn:country_code":"RU",
    "gn:dem":123,
    "gn:feature_class":"P",
    "gn:feature_code":"PPL",
    "gn:name":"Yeldushino",
    "gn:population":0,
    "gn:timezone":"Asia/Yekaterinburg",
    "iso:country":"RU",
    "name:rus_x_preferred":[
        "\u0415\u043b\u0434\u0443\u0448\u0438\u043d\u043e"
    ],
    "wof:name":"Yeldushino",
    "wof:placetype":"locality"
},
  "geometry": {"coordinates":[55.6102,57.292],"type":"Point"}
}