{
  "type": "Feature",
  "properties": {
    "gn:admin1_code":"33.0",
    "gn:asciiname":"Mezentsy",
    "gn:country_code":"RU",
    "gn:dem":117,
    "gn:feature_class":"P",
    "gn:feature_code":"PPL",
    "gn:name":"Mezentsy",
    "gn:population":0,
    "gn:timezone":"Europe/Kirov",
    "iso:country":"RU",
    "name:rus_x_preferred":[
        "\u041c\u0435\u0437\u0435\u043d\u0446\u044b"
    ],
    "name:und_x_variant":[
        "\u041c\u0435\u0437\u0435\u043d\u0446\u044b"
    ],
    "wof:name":"Mezentsy",
    "wof:placetype":"locality"
},
  "geometry": {"coordinates":[48.63261,57.75234],"type":"Point"}
}