{
  "type": "Feature",
  "properties": {
    "gn:admin1_code":"77",
    "gn:asciiname":"Penskiy",
    "gn:country_code":"RU",
    "gn:dem":237,
    "gn:feature_class":"P",
    "gn:feature_code":"PPL",
    "gn:name":"Penskiy",
    "gn:population":0,
    "gn:timezone":"Europe/Moscow",
    "iso:country":"RU",
    "name:eng_x_preferred":[
        "Penskiy"
    ],
    "name:nor_x_preferred":[
        "Penskij"
    ],
    "name:rus_x_preferred":[
        "\u041f\u0435\u043d\u0441\u043a\u0438\u0439"
    ],
    "wof:name":"Penskiy",
    "wof:placetype":"locality"
},
  "geometry": {"coordinates":[33.49313,56.04495],"type":"Point"}
}