{
  "type": "Feature",
  "properties": {
    "gn:admin1_code":"11",
    "gn:asciiname":"Akhalik",
    "gn:country_code":"RU",
    "gn:dem":856,
    "gn:feature_class":"P",
    "gn:feature_code":"PPL",
    "gn:name":"Akhalik",
    "gn:population":0,
    "gn:timezone":"Asia/Irkutsk",
    "iso:country":"RU",
    "name:eng_x_preferred":[
        "Akhalik"
    ],
    "name:nor_x_preferred":[
        "Akhalik"
    ],
    "name:rus_x_preferred":[
        "\u0410\u0445\u0430\u043b\u0438\u043a"
    ],
    "name:und_x_variant":[
        "Akhdlik",
        "Akhalig"
    ],
    "wof:name":"Akhalik",
    "wof:placetype":"locality"
},
  "geometry": {"coordinates":[102.67829999999999,51.7846],"type":"Point"}
}