{
  "type": "Feature",
  "properties": {
    "gn:admin1_code":"45.0",
    "gn:asciiname":"Bol'shaya Munamar'",
    "gn:country_code":"RU",
    "gn:dem":147,
    "gn:feature_class":"P",
    "gn:feature_code":"PPL",
    "gn:name":"Bol\u2019shaya Munamar\u2019",
    "gn:population":0,
    "gn:timezone":"Europe/Volgograd",
    "iso:country":"RU",
    "name:rus_x_preferred":[
        "\u0411\u043e\u043b\u044c\u0448\u0430\u044f \u041c\u0443\u043d\u0430\u043c\u0430\u0440\u044c"
    ],
    "name:und_x_variant":[
        "Bol\u2019shaya Munamar\u2019"
    ],
    "wof:name":"Bol'shaya Munamar'",
    "wof:placetype":"locality"
},
  "geometry": {"coordinates":[49.72985,56.9638],"type":"Point"}
}