{
  "type": "Feature",
  "properties": {
    "gn:admin1_code":"84.0",
    "gn:asciiname":"Verkhne-Zubrilovskiy",
    "gn:country_code":"RU",
    "gn:dem":132,
    "gn:feature_class":"P",
    "gn:feature_code":"PPL",
    "gn:name":"Verkhne-Zubrilovskiy",
    "gn:population":0,
    "gn:timezone":"Europe/Volgograd",
    "iso:country":"RU",
    "wof:name":"Verkhne-Zubrilovskiy",
    "wof:placetype":"locality"
},
  "geometry": {"coordinates":[42.69327,51.20982],"type":"Point"}
}