{
  "type": "Feature",
  "properties": {
    "gn:admin1_code":"57",
    "gn:asciiname":"Kazeyevka",
    "gn:country_code":"RU",
    "gn:dem":155,
    "gn:feature_class":"P",
    "gn:feature_code":"PPL",
    "gn:name":"Kazeyevka",
    "gn:population":0,
    "gn:timezone":"Europe/Moscow",
    "iso:country":"RU",
    "name:rus_x_preferred":[
        "\u041a\u0430\u0437\u0435\u0435\u0432\u043a\u0430"
    ],
    "name:und_x_variant":[
        "Kozeyevka",
        "Kazeyevka"
    ],
    "wof:name":"Kazeyevka",
    "wof:placetype":"locality"
},
  "geometry": {"coordinates":[45.2023,53.02163],"type":"Point"}
}