{
  "type": "Feature",
  "properties": {
    "gn:admin1_code":"85",
    "gn:asciiname":"Sushniki",
    "gn:country_code":"RU",
    "gn:dem":138,
    "gn:feature_class":"P",
    "gn:feature_code":"PPL",
    "gn:name":"Sushniki",
    "gn:population":0,
    "gn:timezone":"Europe/Moscow",
    "iso:country":"RU",
    "name:rus_x_preferred":[
        "\u0421\u0443\u0448\u043d\u0438\u043a\u0438"
    ],
    "name:und_x_variant":[
        "\u0421\u0443\u0448\u043d\u0438\u043a\u0438"
    ],
    "wof:name":"Sushniki",
    "wof:placetype":"locality"
},
  "geometry": {"coordinates":[46.2127,60.0366],"type":"Point"}
}