{
  "type": "Feature",
  "properties": {
    "gn:admin1_code":"05",
    "gn:asciiname":"Mukhinka",
    "gn:cc2":"RU",
    "gn:country_code":"RU",
    "gn:dem":253,
    "gn:feature_class":"P",
    "gn:feature_code":"PPL",
    "gn:name":"Mukhinka",
    "gn:population":0,
    "gn:timezone":"Asia/Yakutsk",
    "iso:country":"RU",
    "name:rus_x_preferred":[
        "\u041c\u0443\u0445\u0438\u043d\u043a\u0430"
    ],
    "name:und_x_variant":[
        "Birsherta",
        "Mukhinka"
    ],
    "wof:name":"Mukhinka",
    "wof:placetype":"locality"
},
  "geometry": {"coordinates":[127.61667,50.55],"type":"Point"}
}