{
  "type": "Feature",
  "properties": {
    "gn:admin1_code":"87",
    "gn:asciiname":"Lagas'gort",
    "gn:country_code":"RU",
    "gn:dem":20,
    "gn:feature_class":"P",
    "gn:feature_code":"PPL",
    "gn:name":"Lagas\u2019gort",
    "gn:population":0,
    "gn:timezone":"Asia/Yekaterinburg",
    "iso:country":"RU",
    "name:rus_x_preferred":[
        "\u041b\u0430\u0433\u0430\u0441\u044c\u0433\u043e\u0440\u0442"
    ],
    "name:und_x_variant":[
        "Lagas\u2019gort",
        "\u041b\u0430\u0433\u0430\u0441\u044c\u0433\u043e\u0440\u0442"
    ],
    "wof:name":"Lagas'gort",
    "wof:placetype":"locality"
},
  "geometry": {"coordinates":[66.65000000000001,65.09999999999999],"type":"Point"}
}