{
  "type": "Feature",
  "properties": {
    "gn:admin1_code":"61.0",
    "gn:asciiname":"Getmanov",
    "gn:country_code":"RU",
    "gn:dem":173,
    "gn:feature_class":"P",
    "gn:feature_code":"PPL",
    "gn:name":"Getmanov",
    "gn:population":0,
    "gn:timezone":"Europe/Moscow",
    "iso:country":"RU",
    "name:rus_x_preferred":[
        "\u0413\u0435\u0442\u043c\u0430\u043d\u043e\u0432"
    ],
    "name:und_x_variant":[
        "\u0413\u0435\u0442\u043c\u0430\u043d\u043e\u0432"
    ],
    "wof:name":"Getmanov",
    "wof:placetype":"locality"
},
  "geometry": {"coordinates":[40.33104,49.05513],"type":"Point"}
}