{
  "type": "Feature",
  "properties": {
    "gn:admin1_code":"37",
    "gn:asciiname":"Sarayevo",
    "gn:country_code":"RU",
    "gn:dem":126,
    "gn:feature_class":"P",
    "gn:feature_code":"PPL",
    "gn:name":"Sarayevo",
    "gn:population":0,
    "gn:timezone":"Europe/Moscow",
    "iso:country":"RU",
    "name:bak_x_preferred":[
        "\u04ba\u0430\u0440\u0430\u0439"
    ],
    "name:che_x_preferred":[
        "\u0421\u0430\u0440\u0430\u0435\u0432\u043e"
    ],
    "name:hye_x_preferred":[
        "\u054d\u0561\u0580\u0561\u0587\u0578"
    ],
    "name:kat_x_preferred":[
        "\u10e1\u10d0\u10e0\u10d0\u10d4\u10d5\u10dd"
    ],
    "name:kaz_x_preferred":[
        "\u0421\u0430\u0440\u0430"
    ],
    "name:kir_x_preferred":[
        "\u0421\u0430\u0440\u0430"
    ],
    "name:rus_x_preferred":[
        "\u0421\u0430\u0440\u0430\u0435\u0432\u043e"
    ],
    "name:tat_x_preferred":[
        "\u0421\u0430\u0440\u0430\u0439"
    ],
    "name:ukr_x_preferred":[
        "\u0421\u0430\u0440\u0430\u0454\u0432\u043e"
    ],
    "wof:name":"Sarayevo",
    "wof:placetype":"locality"
},
  "geometry": {"coordinates":[40.85702,57.422],"type":"Point"}
}