{
  "type": "Feature",
  "properties": {
    "gn:admin1_code":"4",
    "gn:asciiname":"Rechka",
    "gn:country_code":"RU",
    "gn:dem":263,
    "gn:feature_class":"P",
    "gn:feature_code":"PPL",
    "gn:name":"Rechka",
    "gn:population":0,
    "gn:timezone":"Asia/Barnaul",
    "iso:country":"RU",
    "name:rus_x_preferred":[
        "\u0420\u0435\u0447\u043a\u0430"
    ],
    "name:und_x_variant":[
        "\u0420\u0435\u0447\u043a\u0430"
    ],
    "wof:name":"Rechka",
    "wof:placetype":"locality"
},
  "geometry": {"coordinates":[80.51666999999998,53.58333],"type":"Point"}
}