{
  "type": "Feature",
  "properties": {
    "gn:admin1_code":"05",
    "gn:asciiname":"Gornoye",
    "gn:country_code":"RU",
    "gn:dem":204,
    "gn:feature_class":"P",
    "gn:feature_code":"PPL",
    "gn:name":"Gornoye",
    "gn:population":0,
    "gn:timezone":"Asia/Yakutsk",
    "iso:country":"RU",
    "name:eng_x_preferred":[
        "Gornoye"
    ],
    "name:nor_x_preferred":[
        "Gornoje"
    ],
    "name:rus_x_preferred":[
        "\u0413\u043e\u0440\u043d\u043e\u0435"
    ],
    "name:und_x_variant":[
        "Gornoye Kalashnikovo",
        "\u0413\u043e\u0440\u043d\u043e\u0435",
        "Gornoye"
    ],
    "wof:name":"Gornoye",
    "wof:placetype":"locality"
},
  "geometry": {"coordinates":[128.17963999999998,52.28479],"type":"Point"}
}