{
  "type": "Feature",
  "properties": {
    "gn:admin1_code":"42.0",
    "gn:asciiname":"Fisheva Gora",
    "gn:country_code":"RU",
    "gn:dem":57,
    "gn:feature_class":"P",
    "gn:feature_code":"PPL",
    "gn:name":"Fisheva Gora",
    "gn:population":0,
    "gn:timezone":"Europe/Moscow",
    "iso:country":"RU",
    "name:rus_x_preferred":[
        "\u0424\u0438\u0448\u0435\u0432\u0430 \u0413\u043e\u0440\u0430"
    ],
    "name:und_x_variant":[
        "\u0424\u0438\u0448\u0435\u0432\u0430 \u0413\u043e\u0440\u0430"
    ],
    "wof:name":"Fisheva Gora",
    "wof:placetype":"locality"
},
  "geometry": {"coordinates":[33.53816,59.65621],"type":"Point"}
}