{
  "type": "Feature",
  "properties": {
    "gn:admin1_code":"51",
    "gn:asciiname":"Men'shikovo",
    "gn:country_code":"RU",
    "gn:dem":117,
    "gn:feature_class":"P",
    "gn:feature_code":"PPL",
    "gn:name":"Men\u2019shikovo",
    "gn:population":0,
    "gn:timezone":"Europe/Moscow",
    "iso:country":"RU",
    "name:rus_x_preferred":[
        "\u041c\u0435\u043d\u044c\u0448\u0438\u043a\u043e\u0432\u043e"
    ],
    "name:und_x_variant":[
        "Men\u2019shikovo",
        "\u041c\u0435\u043d\u044c\u0448\u0438\u043a\u043e\u0432\u043e"
    ],
    "wof:name":"Men'shikovo",
    "wof:placetype":"locality"
},
  "geometry": {"coordinates":[44.975,57.4505],"type":"Point"}
}