{
  "type": "Feature",
  "properties": {
    "gn:admin1_code":"42",
    "gn:asciiname":"Myagozero-Podgor'ye",
    "gn:country_code":"RU",
    "gn:dem":201,
    "gn:feature_class":"P",
    "gn:feature_code":"PPL",
    "gn:name":"Myagozero-Podgor\u2019ye",
    "gn:population":0,
    "gn:timezone":"Europe/Moscow",
    "iso:country":"RU",
    "name:rus_x_preferred":[
        "\u041c\u044f\u0433\u043e\u0437\u0435\u0440\u043e-\u041f\u043e\u0434\u0433\u043e\u0440\u044c\u0435"
    ],
    "name:und_x_variant":[
        "Podgor\u2019ye",
        "Myagozero-Podgor\u2019ye"
    ],
    "wof:name":"Myagozero-Podgor'ye",
    "wof:placetype":"locality"
},
  "geometry": {"coordinates":[34.83333,60.35],"type":"Point"}
}