{
  "type": "Feature",
  "properties": {
    "gn:admin1_code":"17",
    "gn:admin2_code":"480804",
    "gn:asciiname":"Tenla",
    "gn:country_code":"RU",
    "gn:dem":1592,
    "gn:feature_class":"P",
    "gn:feature_code":"PPL",
    "gn:name":"Tenla",
    "gn:population":0,
    "gn:timezone":"Europe/Moscow",
    "iso:country":"RU",
    "name:rus_x_preferred":[
        "\u0422\u0435\u043d\u043b\u0430"
    ],
    "name:und_x_variant":[
        "\u0422\u0435\u043d\u043b\u0430"
    ],
    "wof:name":"Tenla",
    "wof:placetype":"locality"
},
  "geometry": {"coordinates":[46.12981,42.46544],"type":"Point"}
}