{
  "type": "Feature",
  "properties": {
    "gn:admin1_code":"84.0",
    "gn:asciiname":"Firsovka",
    "gn:country_code":"RU",
    "gn:dem":47,
    "gn:feature_class":"P",
    "gn:feature_code":"PPL",
    "gn:name":"Firsovka",
    "gn:population":0,
    "gn:timezone":"Europe/Volgograd",
    "iso:country":"RU",
    "name:rus_x_preferred":[
        "\u0424\u0438\u0440\u0441\u043e\u0432\u043aa"
    ],
    "name:und_x_variant":[
        "Firsov"
    ],
    "wof:name":"Firsovka",
    "wof:placetype":"locality"
},
  "geometry": {"coordinates":[42.25245,48.09965],"type":"Point"}
}