{
  "type": "Feature",
  "properties": {
    "gn:admin1_code":"33.0",
    "gn:asciiname":"Yeremeyevskaya",
    "gn:country_code":"RU",
    "gn:dem":144,
    "gn:feature_class":"P",
    "gn:feature_code":"PPL",
    "gn:name":"Yeremeyevskaya",
    "gn:population":0,
    "gn:timezone":"Europe/Kirov",
    "iso:country":"RU",
    "name:rus_x_preferred":[
        "\u0415\u0440\u0435\u043c\u0435\u0435\u0432\u0441\u043a\u0430\u044f"
    ],
    "wof:name":"Yeremeyevskaya",
    "wof:placetype":"locality"
},
  "geometry": {"coordinates":[48.27426,58.22868],"type":"Point"}
}