{
  "type": "Feature",
  "properties": {
    "gn:admin1_code":"69",
    "gn:asciiname":"Shanikha",
    "gn:country_code":"RU",
    "gn:dem":228,
    "gn:feature_class":"P",
    "gn:feature_code":"PPL",
    "gn:name":"Shanikha",
    "gn:population":0,
    "gn:timezone":"Europe/Moscow",
    "iso:country":"RU",
    "name:eng_x_preferred":[
        "Shanikha"
    ],
    "name:nor_x_preferred":[
        "Sjanikha"
    ],
    "name:rus_x_preferred":[
        "\u0428\u0430\u043d\u0438\u0445\u0430"
    ],
    "wof:name":"Shanikha",
    "wof:placetype":"locality"
},
  "geometry": {"coordinates":[34.01685,55.7334],"type":"Point"}
}