{
  "type": "Feature",
  "properties": {
    "gn:admin1_code":"33.0",
    "gn:asciiname":"Chernyye Chezhegi",
    "gn:country_code":"RU",
    "gn:dem":148,
    "gn:feature_class":"P",
    "gn:feature_code":"PPL",
    "gn:name":"Ch\u00ebrnyye Chezhegi",
    "gn:population":0,
    "gn:timezone":"Europe/Kirov",
    "iso:country":"RU",
    "name:rus_x_preferred":[
        "\u0427\u0451\u0440\u043d\u044b\u0435 \u0427\u0435\u0436\u0435\u0433\u0438"
    ],
    "name:und_x_variant":[
        "Ch\u00ebrnyye Chizhigi",
        "Ch\u00ebrnyye Chezhegi",
        "\u0427\u0451\u0440\u043d\u044b\u0435 \u0427\u0435\u0436\u0435\u0433\u0438"
    ],
    "wof:name":"Chernyye Chezhegi",
    "wof:placetype":"locality"
},
  "geometry": {"coordinates":[50.04258,58.48408000000001],"type":"Point"}
}