{
  "type": "Feature",
  "properties": {
    "gn:admin1_code":"43",
    "gn:asciiname":"Guguyevka",
    "gn:country_code":"RU",
    "gn:dem":209,
    "gn:feature_class":"P",
    "gn:feature_code":"PPL",
    "gn:name":"Guguyevka",
    "gn:population":0,
    "gn:timezone":"Europe/Moscow",
    "iso:country":"RU",
    "name:rus_x_preferred":[
        "\u0413\u0443\u0433\u0443\u0435\u0432\u043a\u0430"
    ],
    "name:und_x_variant":[
        "\u0413\u0443\u0433\u0443\u0435\u0432\u043a\u0430"
    ],
    "wof:name":"Guguyevka",
    "wof:placetype":"locality"
},
  "geometry": {"coordinates":[38.98288,53.42771],"type":"Point"}
}