{
  "type": "Feature",
  "properties": {
    "gn:admin1_code":"24.0",
    "gn:asciiname":"Altn-Bulg",
    "gn:country_code":"RU",
    "gn:dem":2,
    "gn:feature_class":"P",
    "gn:feature_code":"PPL",
    "gn:name":"Altn-Bulg",
    "gn:population":0,
    "gn:timezone":"Europe/Moscow",
    "iso:country":"RU",
    "name:eng_x_preferred":[
        "Altn-Bulg"
    ],
    "name:nor_x_preferred":[
        "Altn-Bulg"
    ],
    "name:rus_x_preferred":[
        "\u0410\u043b\u0442\u043d-\u0411\u0443\u043b\u0433"
    ],
    "name:und_x_variant":[
        "\u0410\u043b\u0442\u043d-\u0411\u0443\u043b\u0433",
        "Altn-Bulg"
    ],
    "wof:name":"Altn-Bulg",
    "wof:placetype":"locality"
},
  "geometry": {"coordinates":[45.5991,46.9846],"type":"Point"}
}