{
  "type": "Feature",
  "properties": {
    "gn:admin1_code":"63",
    "gn:asciiname":"Kiriyestyakh",
    "gn:country_code":"RU",
    "gn:dem":274,
    "gn:feature_class":"P",
    "gn:feature_code":"PPL",
    "gn:name":"Kiriyestyakh",
    "gn:population":0,
    "gn:timezone":"Asia/Yakutsk",
    "iso:country":"RU",
    "name:eng_x_preferred":[
        "Kiriyestyakh"
    ],
    "name:nor_x_preferred":[
        "Kirijestjakh"
    ],
    "name:rus_x_preferred":[
        "\u041a\u0438\u0440\u0438\u0435\u0441\u0442\u044f\u0445"
    ],
    "wof:name":"Kiriyestyakh",
    "wof:placetype":"locality"
},
  "geometry": {"coordinates":[127.34390999999999,62.2712],"type":"Point"}
}