{
  "type": "Feature",
  "properties": {
    "gn:admin1_code":"40",
    "gn:asciiname":"Pershino",
    "gn:country_code":"RU",
    "gn:dem":119,
    "gn:feature_class":"P",
    "gn:feature_code":"PPL",
    "gn:name":"Pershino",
    "gn:population":0,
    "gn:timezone":"Asia/Yekaterinburg",
    "iso:country":"RU",
    "name:eng_x_preferred":[
        "Pershino"
    ],
    "name:nor_x_preferred":[
        "Persjino"
    ],
    "name:rus_x_preferred":[
        "\u041f\u0435\u0440\u0448\u0438\u043d\u043e"
    ],
    "name:und_x_variant":[
        "Pershinskoye",
        "\u041f\u0435\u0440\u0448\u0438\u043d\u043e",
        "Pershino"
    ],
    "wof:name":"Pershino",
    "wof:placetype":"locality"
},
  "geometry": {"coordinates":[65.3956,56.088],"type":"Point"}
}