{
  "type": "Feature",
  "properties": {
    "gn:admin1_code":"63",
    "gn:asciiname":"Bol'shoy Peleduy",
    "gn:country_code":"RU",
    "gn:dem":181,
    "gn:feature_class":"P",
    "gn:feature_code":"PPL",
    "gn:name":"Bol\u2019shoy Peleduy",
    "gn:population":0,
    "gn:timezone":"Asia/Yakutsk",
    "iso:country":"RU",
    "name:eng_x_preferred":[
        "Bol'shoy Peleduy"
    ],
    "name:nor_x_preferred":[
        "Bolsjoj Peleduj"
    ],
    "name:rus_x_preferred":[
        "\u0411\u043e\u043b\u044c\u0448\u043e\u0439 \u041f\u0435\u043b\u0435\u0434\u0443\u0439"
    ],
    "name:und_x_variant":[
        "Bol\u2019shoy Peleduy"
    ],
    "wof:name":"Bol'shoy Peleduy",
    "wof:placetype":"locality"
},
  "geometry": {"coordinates":[112.78333000000001,59.65],"type":"Point"}
}