{
  "type": "Feature",
  "properties": {
    "gn:admin1_code":"73",
    "gn:asciiname":"Poselok Stroitel'no-Montazhnoye Predpriyatiye-341",
    "gn:country_code":"RU",
    "gn:dem":88,
    "gn:feature_class":"P",
    "gn:feature_code":"PPL",
    "gn:name":"Pos\u00eblok Stroitel\u2019no-Montazhnoye Predpriyatiye-341",
    "gn:population":0,
    "gn:timezone":"Europe/Moscow",
    "iso:country":"RU",
    "name:rus_x_preferred":[
        "\u041f\u043e\u0441\u0451\u043b\u043e\u043a \u0421\u0442\u0440\u043e\u0438\u0442\u0435\u043b\u044c\u043d\u043e-\u041c\u043e\u043d\u0442\u0430\u0436\u043d\u043e\u0435 \u041f\u0440\u0435\u0434\u043f\u0440\u0438\u044f\u0442\u0438\u0435-341"
    ],
    "name:und_x_variant":[
        "Pos\u00eblok Stroitel\u2019no-Montazhnoye Predpriyatiye-341"
    ],
    "wof:name":"Poselok Stroitel'no-Montazhnoye Predpriyatiye-341",
    "wof:placetype":"locality"
},
  "geometry": {"coordinates":[49.25396,55.75194000000001],"type":"Point"}
}