{
  "type": "Feature",
  "properties": {
    "gn:admin1_code":"51",
    "gn:asciiname":"Osipovka",
    "gn:country_code":"RU",
    "gn:dem":142,
    "gn:feature_class":"P",
    "gn:feature_code":"PPL",
    "gn:name":"Osipovka",
    "gn:population":0,
    "gn:timezone":"Europe/Moscow",
    "iso:country":"RU",
    "name:bak_x_preferred":[
        "\u041e\u0441\u0438\u043f\u043e\u0432\u043a\u0430"
    ],
    "name:che_x_preferred":[
        "\u041e\u0441\u0438\u043f\u043e\u0432\u043a\u0430"
    ],
    "name:eng_x_preferred":[
        "Osipovka"
    ],
    "name:hye_x_preferred":[
        "\u0555\u057d\u056b\u057a\u0578\u057e\u056f\u0561"
    ],
    "name:kaz_x_preferred":[
        "\u041e\u0441\u0438\u043f\u043e\u0432\u043a\u0430"
    ],
    "name:kir_x_preferred":[
        "\u041e\u0441\u0438\u043f\u043e\u0432\u043a\u0430"
    ],
    "name:nor_x_preferred":[
        "Osipovka"
    ],
    "name:rus_x_preferred":[
        "\u041e\u0441\u0438\u043f\u043e\u0432\u043a\u0430"
    ],
    "name:tat_x_preferred":[
        "\u041e\u0441\u0438\u043f\u043e\u0432\u043a\u0430"
    ],
    "wof:name":"Osipovka",
    "wof:placetype":"locality"
},
  "geometry": {"coordinates":[42.2654,55.0632],"type":"Point"}
}