{
  "type": "Feature",
  "properties": {
    "gn:admin1_code":"71",
    "gn:asciiname":"Sazhina",
    "gn:country_code":"RU",
    "gn:dem":298,
    "gn:feature_class":"P",
    "gn:feature_code":"PPL",
    "gn:name":"Sazhina",
    "gn:population":0,
    "gn:timezone":"Asia/Yekaterinburg",
    "iso:country":"RU",
    "name:rus_x_preferred":[
        "\u0421\u0430\u0436\u0438\u043d\u0430"
    ],
    "name:und_x_variant":[
        "\u0421\u0430\u0436\u0438\u043d\u0430"
    ],
    "wof:name":"Sazhina",
    "wof:placetype":"locality"
},
  "geometry": {"coordinates":[58.4696,56.7987],"type":"Point"}
}