{
  "type": "Feature",
  "properties": {
    "gn:admin1_code":"91.0",
    "gn:asciiname":"Buzunovo",
    "gn:country_code":"RU",
    "gn:dem":166,
    "gn:feature_class":"P",
    "gn:feature_code":"PPL",
    "gn:name":"Buzunovo",
    "gn:population":0,
    "gn:timezone":"Asia/Krasnoyarsk",
    "iso:country":"RU",
    "name:eng_x_preferred":[
        "Buzunovo"
    ],
    "name:nor_x_preferred":[
        "Buzunovo"
    ],
    "name:rus_x_preferred":[
        "\u0411\u0443\u0437\u0443\u043d\u043e\u0432\u043e"
    ],
    "wof:name":"Buzunovo",
    "wof:placetype":"locality"
},
  "geometry": {"coordinates":[93.32389000000001,56.69889000000001],"type":"Point"}
}