{
  "type": "Feature",
  "properties": {
    "gn:admin1_code":"25",
    "gn:asciiname":"Simendyayevo",
    "gn:country_code":"RU",
    "gn:dem":226,
    "gn:feature_class":"P",
    "gn:feature_code":"PPL",
    "gn:name":"Simendyayevo",
    "gn:population":0,
    "gn:timezone":"Europe/Moscow",
    "iso:country":"RU",
    "name:nor_x_preferred":[
        "Simendjaevo"
    ],
    "name:rus_x_preferred":[
        "\u0421\u0438\u043c\u0435\u043d\u0434\u044f\u0435\u0432\u043e"
    ],
    "wof:name":"Simendyayevo",
    "wof:placetype":"locality"
},
  "geometry": {"coordinates":[36.55016,54.81828],"type":"Point"}
}