{
  "type": "Feature",
  "properties": {
    "gn:admin1_code":"73",
    "gn:asciiname":"Sredneye Devyatovo",
    "gn:country_code":"RU",
    "gn:dem":96,
    "gn:feature_class":"P",
    "gn:feature_code":"PPL",
    "gn:name":"Sredneye Devyatovo",
    "gn:population":0,
    "gn:timezone":"Europe/Moscow",
    "iso:country":"RU",
    "name:rus_x_preferred":[
        "\u0421\u0440\u0435\u0434\u043d\u0435\u0435 \u0414\u0435\u0432\u044f\u0442\u043e\u0432\u043e"
    ],
    "wof:name":"Sredneye Devyatovo",
    "wof:placetype":"locality"
},
  "geometry": {"coordinates":[49.66518,55.49441],"type":"Point"}
}