{
  "type": "Feature",
  "properties": {
    "gn:admin1_code":"91.0",
    "gn:asciiname":"Lesouchastok Vtoroy",
    "gn:country_code":"RU",
    "gn:dem":247,
    "gn:feature_class":"P",
    "gn:feature_code":"PPL",
    "gn:name":"Lesouchastok Vtoroy",
    "gn:population":0,
    "gn:timezone":"Asia/Krasnoyarsk",
    "iso:country":"RU",
    "name:rus_x_preferred":[
        "\u041b\u0435\u0441\u043e\u0443\u0447\u0430\u0441\u0442\u043e\u043a \u0412\u0442\u043e\u0440\u043e\u0439"
    ],
    "wof:name":"Lesouchastok Vtoroy",
    "wof:placetype":"locality"
},
  "geometry": {"coordinates":[94.0493,56.0172],"type":"Point"}
}