{
  "type": "Feature",
  "properties": {
    "gn:admin1_code":"88",
    "gn:asciiname":"Lavrent'yev Kholm",
    "gn:country_code":"RU",
    "gn:dem":212,
    "gn:feature_class":"P",
    "gn:feature_code":"PPL",
    "gn:name":"Lavrent\u2019yev Kholm",
    "gn:population":0,
    "gn:timezone":"Europe/Moscow",
    "iso:country":"RU",
    "name:rus_x_preferred":[
        "\u041b\u0430\u0432\u0440\u0435\u043d\u0442\u044c\u0435\u0432 \u0425\u043e\u043b\u043c"
    ],
    "name:und_x_variant":[
        "Lavrent\u2019yev Kholm"
    ],
    "wof:name":"Lavrent'yev Kholm",
    "wof:placetype":"locality"
},
  "geometry": {"coordinates":[39.32728,57.4803],"type":"Point"}
}