{
  "type": "Feature",
  "properties": {
    "gn:admin1_code":"60",
    "gn:asciiname":"Lykovo",
    "gn:cc2":"RU",
    "gn:country_code":"RU",
    "gn:dem":80,
    "gn:feature_class":"P",
    "gn:feature_code":"PPL",
    "gn:name":"Lykovo",
    "gn:population":0,
    "gn:timezone":"Europe/Moscow",
    "iso:country":"RU",
    "name:che_x_preferred":[
        "\u041b\u044b\u043a\u043e\u0432\u043e"
    ],
    "name:rus_x_preferred":[
        "\u041b\u044b\u043a\u043e\u0432\u043e"
    ],
    "name:und_x_variant":[
        "Likava",
        "Lykovo",
        "\u041b\u044b\u043a\u043e\u0432\u043e"
    ],
    "wof:name":"Lykovo",
    "wof:placetype":"locality"
},
  "geometry": {"coordinates":[27.96667,56.93333000000001],"type":"Point"}
}