{
  "type": "Feature",
  "properties": {
    "gn:admin1_code":"33.0",
    "gn:asciiname":"Dudyri",
    "gn:country_code":"RU",
    "gn:dem":135,
    "gn:feature_class":"P",
    "gn:feature_code":"PPL",
    "gn:name":"Dudyri",
    "gn:population":0,
    "gn:timezone":"Europe/Kirov",
    "iso:country":"RU",
    "name:rus_x_preferred":[
        "\u0414\u0443\u0434\u044b\u0440\u0438"
    ],
    "name:und_x_variant":[
        "\u0414\u0443\u0434\u044b\u0440\u0438"
    ],
    "wof:name":"Dudyri",
    "wof:placetype":"locality"
},
  "geometry": {"coordinates":[50.43333,57.78333000000001],"type":"Point"}
}