{
  "type": "Feature",
  "properties": {
    "gn:admin1_code":"88",
    "gn:asciiname":"Rushinovo",
    "gn:country_code":"RU",
    "gn:dem":168,
    "gn:feature_class":"P",
    "gn:feature_code":"PPL",
    "gn:name":"Rushinovo",
    "gn:population":0,
    "gn:timezone":"Europe/Moscow",
    "iso:country":"RU",
    "name:rus_x_preferred":[
        "\u0420\u0443\u0448\u0438\u043d\u043e\u0432\u043e"
    ],
    "wof:name":"Rushinovo",
    "wof:placetype":"locality"
},
  "geometry": {"coordinates":[39.13666,56.86853000000001],"type":"Point"}
}