{
  "type": "Feature",
  "properties": {
    "gn:admin1_code":"51.0",
    "gn:asciiname":"Lbovo",
    "gn:country_code":"RU",
    "gn:dem":130,
    "gn:feature_class":"P",
    "gn:feature_code":"PPL",
    "gn:name":"Lbovo",
    "gn:population":0,
    "gn:timezone":"Europe/Moscow",
    "iso:country":"RU",
    "name:nor_x_preferred":[
        "Lbovo"
    ],
    "name:rus_x_preferred":[
        "\u041b\u0431\u043e\u0432\u043e"
    ],
    "wof:name":"Lbovo",
    "wof:placetype":"locality"
},
  "geometry": {"coordinates":[43.59431,56.8732],"type":"Point"}
}