{
  "type": "Feature",
  "properties": {
    "gn:admin1_code":"28",
    "gn:asciiname":"Khyarkinmyaki",
    "gn:country_code":"RU",
    "gn:dem":102,
    "gn:feature_class":"P",
    "gn:feature_code":"PPL",
    "gn:name":"Khyarkinmyaki",
    "gn:population":0,
    "gn:timezone":"Europe/Moscow",
    "iso:country":"RU",
    "name:fin_x_preferred":[
        "H\u00e4rkinm\u00e4ki"
    ],
    "name:rus_x_preferred":[
        "\u0425\u044f\u0440\u043a\u0438\u043d\u043c\u044f\u043a\u0438"
    ],
    "wof:name":"Khyarkinmyaki",
    "wof:placetype":"locality"
},
  "geometry": {"coordinates":[30.36192,61.94194],"type":"Point"}
}