{
  "type": "Feature",
  "properties": {
    "gn:admin1_code":"68",
    "gn:asciiname":"Predgornoye",
    "gn:country_code":"RU",
    "gn:dem":379,
    "gn:feature_class":"P",
    "gn:feature_code":"PPL",
    "gn:name":"Predgornoye",
    "gn:population":0,
    "gn:timezone":"Europe/Moscow",
    "iso:country":"RU",
    "name:rus_x_preferred":[
        "\u041f\u0440\u0435\u0434\u0433\u043e\u0440\u043d\u043e\u0435"
    ],
    "name:und_x_variant":[
        "Malgobekskaya Balka",
        "Predgornoye"
    ],
    "wof:name":"Predgornoye",
    "wof:placetype":"locality"
},
  "geometry": {"coordinates":[44.69258,43.56374],"type":"Point"}
}