{
  "type": "Feature",
  "properties": {
    "gn:admin1_code":"73",
    "gn:asciiname":"Mukmin-Karatay",
    "gn:country_code":"RU",
    "gn:dem":115,
    "gn:feature_class":"P",
    "gn:feature_code":"PPL",
    "gn:name":"Mukmin-Karatay",
    "gn:population":0,
    "gn:timezone":"Europe/Moscow",
    "iso:country":"RU",
    "name:eng_x_preferred":[
        "Mukmin Karatay"
    ],
    "name:nor_x_preferred":[
        "Mukmin-Karataj"
    ],
    "name:rus_x_preferred":[
        "\u041c\u0443\u043a\u043c\u0438\u043d-\u041a\u0430\u0440\u0430\u0442\u0430\u0439"
    ],
    "name:und_x_variant":[
        "Mukmihkaramay",
        "Mukmin-Karatay",
        "\u041c\u0443\u043a\u043c\u0438\u043d-\u041a\u0430\u0440\u0430\u0442\u0430\u0439"
    ],
    "wof:name":"Mukmin-Karatay",
    "wof:placetype":"locality"
},
  "geometry": {"coordinates":[52.04832,54.58357],"type":"Point"}
}