{
  "type": "Feature",
  "properties": {
    "gn:admin1_code":"69",
    "gn:asciiname":"Surmenevo",
    "gn:country_code":"RU",
    "gn:dem":213,
    "gn:feature_class":"P",
    "gn:feature_code":"PPL",
    "gn:name":"Surmen\u00ebvo",
    "gn:population":0,
    "gn:timezone":"Europe/Moscow",
    "iso:country":"RU",
    "name:rus_x_preferred":[
        "\u0421y\u0440\u043c\u0435\u043d\u0451\u0432o"
    ],
    "name:und_x_variant":[
        "Sermel\u00ebva",
        "Surmen\u00ebvo",
        "\u0421y\u0440\u043c\u0435\u043d\u0451\u0432o"
    ],
    "wof:name":"Surmenevo",
    "wof:placetype":"locality"
},
  "geometry": {"coordinates":[32.98745,55.06553],"type":"Point"}
}