{
  "type": "Feature",
  "properties": {
    "gn:admin1_code":"91",
    "gn:asciiname":"Ozhigova",
    "gn:country_code":"RU",
    "gn:dem":67,
    "gn:feature_class":"P",
    "gn:feature_code":"PPL",
    "gn:name":"Ozhigova",
    "gn:population":0,
    "gn:timezone":"Asia/Krasnoyarsk",
    "iso:country":"RU",
    "name:rus_x_preferred":[
        "\u041e\u0436\u0438\u0433\u043e\u0432\u0430"
    ],
    "wof:name":"Ozhigova",
    "wof:placetype":"locality"
},
  "geometry": {"coordinates":[92.11667,58.51667],"type":"Point"}
}