{
  "type": "Feature",
  "properties": {
    "gn:admin1_code":"6.0",
    "gn:asciiname":"Antipinskaya",
    "gn:country_code":"RU",
    "gn:dem":96,
    "gn:feature_class":"P",
    "gn:feature_code":"PPL",
    "gn:name":"Antipinskaya",
    "gn:population":0,
    "gn:timezone":"Europe/Moscow",
    "iso:country":"RU",
    "name:nor_x_preferred":[
        "Antipinskaja"
    ],
    "name:rus_x_preferred":[
        "\u0410\u043d\u0442\u0438\u043f\u0438\u043d\u0441\u043a\u0430\u044f"
    ],
    "wof:name":"Antipinskaya",
    "wof:placetype":"locality"
},
  "geometry": {"coordinates":[45.47642000000001,61.63266],"type":"Point"}
}