{
  "type": "Feature",
  "properties": {
    "gn:admin1_code":"76",
    "gn:asciiname":"Veret'ye",
    "gn:country_code":"RU",
    "gn:dem":135,
    "gn:feature_class":"P",
    "gn:feature_code":"PPL",
    "gn:name":"Veret\u2019y\u00eb",
    "gn:population":0,
    "gn:timezone":"Europe/Moscow",
    "iso:country":"RU",
    "wof:name":"Veret'ye",
    "wof:placetype":"locality"
},
  "geometry": {"coordinates":[36.275,54.13293],"type":"Point"}
}