{
  "type": "Feature",
  "properties": {
    "gn:admin1_code":"28",
    "gn:asciiname":"Uslag Enda",
    "gn:cc2":"RU",
    "gn:country_code":"RU",
    "gn:dem":46,
    "gn:feature_class":"P",
    "gn:feature_code":"PPL",
    "gn:name":"Uslag Enda",
    "gn:population":0,
    "gn:timezone":"Europe/Moscow",
    "iso:country":"RU",
    "name:fin_x_preferred":[
        "Onta"
    ],
    "name:und_x_variant":[
        "Uslag Onda",
        "Uslag Enda"
    ],
    "wof:name":"Uslag Enda",
    "wof:placetype":"locality"
},
  "geometry": {"coordinates":[34.18333,63.98333],"type":"Point"}
}