{
  "type": "Feature",
  "properties": {
    "gn:admin1_code":"73.0",
    "gn:asciiname":"Abla",
    "gn:country_code":"RU",
    "gn:dem":87,
    "gn:feature_class":"P",
    "gn:feature_code":"PPL",
    "gn:name":"Abla",
    "gn:population":0,
    "gn:timezone":"Europe/Moscow",
    "iso:country":"RU",
    "name:ara_x_preferred":[
        "\u0639\u0628\u0644\u0629"
    ],
    "name:arg_x_preferred":[
        "Abla"
    ],
    "name:ast_x_preferred":[
        "Abla"
    ],
    "name:azb_x_preferred":[
        "\u0622\u0628\u0644\u0627"
    ],
    "name:bul_x_preferred":[
        "\u0410\u0431\u043b\u0430"
    ],
    "name:cat_x_preferred":[
        "Abla"
    ],
    "name:ceb_x_preferred":[
        "Abla"
    ],
    "name:deu_x_preferred":[
        "Abla"
    ],
    "name:epo_x_preferred":[
        "Abla"
    ],
    "name:eus_x_preferred":[
        "Abla"
    ],
    "name:fas_x_preferred":[
        "\u0622\u0628\u0644\u0627"
    ],
    "name:fra_x_preferred":[
        "Abla"
    ],
    "name:glg_x_preferred":[
        "Abla"
    ],
    "name:hak_x_preferred":[
        "Abla"
    ],
    "name:hat_x_preferred":[
        "Abla"
    ],
    "name:hun_x_preferred":[
        "Abla"
    ],
    "name:ina_x_preferred":[
        "Abla"
    ],
    "name:ita_x_preferred":[
        "Abla"
    ],
    "name:mkd_x_preferred":[
        "\u0410\u0431\u043b\u0430"
    ],
    "name:msa_x_preferred":[
        "Abla"
    ],
    "name:nld_x_preferred":[
        "Abla"
    ],
    "name:nor_x_preferred":[
        "Abla"
    ],
    "name:oci_x_preferred":[
        "Abla"
    ],
    "name:pol_x_preferred":[
        "Abla"
    ],
    "name:por_x_preferred":[
        "Abla"
    ],
    "name:ron_x_preferred":[
        "Abla"
    ],
    "name:rus_x_preferred":[
        "\u0410\u0431\u043b\u0430"
    ],
    "name:spa_x_preferred":[
        "Abla"
    ],
    "name:swe_x_preferred":[
        "Abla"
    ],
    "name:tur_x_preferred":[
        "Abla"
    ],
    "name:ukr_x_preferred":[
        "\u0410\u0431\u043b\u0430"
    ],
    "name:uzb_x_preferred":[
        "Abla"
    ],
    "name:vie_x_preferred":[
        "Abla"
    ],
    "name:war_x_preferred":[
        "Abla"
    ],
    "name:zho_x_preferred":[
        "\u963f\u592b\u62c9"
    ],
    "wof:name":"Abla",
    "wof:placetype":"locality"
},
  "geometry": {"coordinates":[49.25611,56.07556],"type":"Point"}
}