{
  "type": "Feature",
  "properties": {
    "gn:admin1_code":"73.0",
    "gn:asciiname":"Abla",
    "gn:country_code":"RU",
    "gn:dem":87,
    "gn:feature_class":"P",
    "gn:feature_code":"PPL",
    "gn:name":"Abla",
    "gn:population":0,
    "gn:timezone":"Europe/Moscow",
    "iso:country":"RU",
    "name:nor_x_preferred":[
        "Abla"
    ],
    "name:rus_x_preferred":[
        "\u0410\u0431\u043b\u0430"
    ],
    "wof:name":"Abla",
    "wof:placetype":"locality"
},
  "geometry": {"coordinates":[49.25611,56.07556],"type":"Point"}
}