{
  "type": "Feature",
  "properties": {
    "gn:admin1_code":"33",
    "gn:asciiname":"Kishkil'",
    "gn:country_code":"RU",
    "gn:dem":88,
    "gn:feature_class":"P",
    "gn:feature_code":"PPL",
    "gn:name":"Kishkil\u2019",
    "gn:population":0,
    "gn:timezone":"Europe/Kirov",
    "iso:country":"RU",
    "name:eng_x_preferred":[
        "Kishkil'"
    ],
    "name:nor_x_preferred":[
        "Kisjkil"
    ],
    "name:rus_x_preferred":[
        "\u041a\u0438\u0448\u043a\u0438\u043b\u044c"
    ],
    "name:und_x_variant":[
        "Kishkil\u2019"
    ],
    "wof:name":"Kishkil'",
    "wof:placetype":"locality"
},
  "geometry": {"coordinates":[48.62512,57.879],"type":"Point"}
}