{
  "type": "Feature",
  "properties": {
    "gn:admin1_code":"91",
    "gn:asciiname":"Novosemenovka",
    "gn:country_code":"RU",
    "gn:dem":287,
    "gn:feature_class":"P",
    "gn:feature_code":"PPL",
    "gn:name":"Novosem\u00ebnovka",
    "gn:population":0,
    "gn:timezone":"Asia/Krasnoyarsk",
    "iso:country":"RU",
    "name:eng_x_preferred":[
        "Novosemenovka"
    ],
    "name:nor_x_preferred":[
        "Novosemenovka"
    ],
    "name:rus_x_preferred":[
        "\u041d\u043e\u0432\u043e\u0441\u0435\u043c\u0435\u043d\u043e\u0432\u043a\u0430"
    ],
    "name:rus_x_variant":[
        "\u041d\u043e\u0432\u043e\u0441\u0435\u043c\u0451\u043d\u043e\u0432\u043a\u0430"
    ],
    "name:und_x_variant":[
        "Bayev",
        "Basa Tatarskiy",
        "Novosem\u00ebnovka"
    ],
    "wof:name":"Novosemenovka",
    "wof:placetype":"locality"
},
  "geometry": {"coordinates":[95.94444,56.40806],"type":"Point"}
}