{
  "type": "Feature",
  "properties": {
    "gn:admin1_code":"69",
    "gn:asciiname":"Korobanovo",
    "gn:country_code":"RU",
    "gn:dem":246,
    "gn:feature_class":"P",
    "gn:feature_code":"PPL",
    "gn:name":"Korobanovo",
    "gn:population":0,
    "gn:timezone":"Europe/Moscow",
    "iso:country":"RU",
    "name:rus_x_preferred":[
        "\u041a\u043e\u0440\u043e\u0431\u0430\u043d\u043e\u0432\u043e"
    ],
    "wof:name":"Korobanovo",
    "wof:placetype":"locality"
},
  "geometry": {"coordinates":[34.39875,55.41022],"type":"Point"}
}