{
  "type": "Feature",
  "properties": {
    "gn:admin1_code":"37",
    "gn:asciiname":"Nikitskoye",
    "gn:country_code":"RU",
    "gn:dem":161,
    "gn:feature_class":"P",
    "gn:feature_code":"PPL",
    "gn:name":"Nikitskoye",
    "gn:population":0,
    "gn:timezone":"Europe/Moscow",
    "iso:country":"RU",
    "name:rus_x_preferred":[
        "\u041d\u0438\u043a\u0438\u0442\u0441\u043a\u043e\u0435"
    ],
    "name:und_x_variant":[
        "Nikifskoye",
        "Nikitskoye",
        "\u041d\u0438\u043a\u0438\u0442\u0441\u043a\u043e\u0435"
    ],
    "wof:name":"Nikitskoye",
    "wof:placetype":"locality"
},
  "geometry": {"coordinates":[44.20222,58.54382],"type":"Point"}
}