{
  "type": "Feature",
  "properties": {
    "gn:admin1_code":"77",
    "gn:asciiname":"Poteshkino",
    "gn:country_code":"RU",
    "gn:dem":185,
    "gn:feature_class":"P",
    "gn:feature_code":"PPL",
    "gn:name":"Poteshkino",
    "gn:population":0,
    "gn:timezone":"Europe/Moscow",
    "iso:country":"RU",
    "name:rus_x_preferred":[
        "\u041f\u043e\u0442\u0435\u0448\u043a\u0438\u043d\u043e"
    ],
    "name:und_x_variant":[
        "\u041f\u043e\u0442\u0435\u0448\u043a\u0438\u043d\u043e"
    ],
    "wof:name":"Poteshkino",
    "wof:placetype":"locality"
},
  "geometry": {"coordinates":[37.4042,58.2979],"type":"Point"}
}