{
  "type": "Feature",
  "properties": {
    "gn:admin1_code":"56",
    "gn:asciiname":"Yasnoye Solntse",
    "gn:country_code":"RU",
    "gn:dem":200,
    "gn:feature_class":"P",
    "gn:feature_code":"PPL",
    "gn:name":"Yasnoye Solntse",
    "gn:population":0,
    "gn:timezone":"Europe/Moscow",
    "iso:country":"RU",
    "wof:name":"Yasnoye Solntse",
    "wof:placetype":"locality"
},
  "geometry": {"coordinates":[35.83611,52.87861],"type":"Point"}
}