{
  "type": "Feature",
  "properties": {
    "gn:admin1_code":"72",
    "gn:asciiname":"Pavlovka",
    "gn:country_code":"RU",
    "gn:dem":116,
    "gn:feature_class":"P",
    "gn:feature_code":"PPL",
    "gn:name":"Pavlovka",
    "gn:population":0,
    "gn:timezone":"Europe/Moscow",
    "iso:country":"RU",
    "name:ceb_x_preferred":[
        "Pavlovka"
    ],
    "name:deu_x_preferred":[
        "Pawlowka"
    ],
    "name:rus_x_preferred":[
        "\u041f\u0430\u0432\u043b\u043e\u0432\u043a\u0430"
    ],
    "name:tat_x_preferred":[
        "\u041f\u0430\u0432\u043b\u043e\u0432\u043a\u0430"
    ],
    "name:ukr_x_preferred":[
        "\u041f\u0430\u0432\u043b\u043e\u0432\u043a\u0430"
    ],
    "wof:name":"Pavlovka",
    "wof:placetype":"locality"
},
  "geometry": {"coordinates":[41.78094,53.53771999999999],"type":"Point"}
}