{
  "type": "Feature",
  "properties": {
    "gn:admin1_code":"90",
    "gn:asciiname":"Tokari",
    "gn:country_code":"RU",
    "gn:dem":287,
    "gn:feature_class":"P",
    "gn:feature_code":"PPL",
    "gn:name":"Tokari",
    "gn:population":0,
    "gn:timezone":"Asia/Yekaterinburg",
    "iso:country":"RU",
    "name:eng_x_preferred":[
        "Tokari"
    ],
    "name:nor_x_preferred":[
        "Tokari"
    ],
    "name:rus_x_preferred":[
        "\u0422\u043e\u043a\u0430\u0440\u0438"
    ],
    "wof:name":"Tokari",
    "wof:placetype":"locality"
},
  "geometry": {"coordinates":[54.27839,57.93429],"type":"Point"}
}