{
  "type": "Feature",
  "properties": {
    "gn:admin1_code":"79",
    "gn:asciiname":"Mezhegey",
    "gn:cc2":"RU",
    "gn:country_code":"RU",
    "gn:dem":787,
    "gn:feature_class":"P",
    "gn:feature_code":"PPL",
    "gn:name":"Mezhegey",
    "gn:population":0,
    "gn:timezone":"Asia/Krasnoyarsk",
    "iso:country":"RU",
    "name:eng_x_preferred":[
        "Mezhegey"
    ],
    "name:nor_x_preferred":[
        "Mezjegej"
    ],
    "name:rus_x_preferred":[
        "\u041c\u0435\u0436\u0435\u0433\u0435\u0439"
    ],
    "name:und_x_variant":[
        "Alaak",
        "\u041c\u0435\u0436\u0435\u0433\u0435\u0439",
        "Mezhegey"
    ],
    "wof:name":"Mezhegey",
    "wof:placetype":"locality"
},
  "geometry": {"coordinates":[94.36667,51.25],"type":"Point"}
}