{
  "type": "Feature",
  "properties": {
    "gn:admin1_code":"31",
    "gn:asciiname":"Kop'yevo",
    "gn:country_code":"RU",
    "gn:dem":383,
    "gn:feature_class":"P",
    "gn:feature_code":"PPL",
    "gn:name":"Kop\u2019yevo",
    "gn:population":0,
    "gn:timezone":"Asia/Krasnoyarsk",
    "iso:country":"RU",
    "name:eng_x_preferred":[
        "Kop'yevo"
    ],
    "name:rus_x_preferred":[
        "\u041a\u043e\u043f\u044c\u0435\u0432\u043e"
    ],
    "name:und_x_variant":[
        "Kop\u2019yeva",
        "Kop\u2019yevo"
    ],
    "wof:name":"Kop'yevo",
    "wof:placetype":"locality"
},
  "geometry": {"coordinates":[89.84860999999999,55.0375],"type":"Point"}
}