{
  "type": "Feature",
  "properties": {
    "gn:admin1_code":"91",
    "gn:asciiname":"Kayak",
    "gn:cc2":"RU",
    "gn:country_code":"RU",
    "gn:dem":55,
    "gn:feature_class":"P",
    "gn:feature_code":"PPL",
    "gn:name":"Kayak",
    "gn:population":0,
    "gn:timezone":"Asia/Krasnoyarsk",
    "iso:country":"RU",
    "name:eng_x_preferred":[
        "Kayak"
    ],
    "name:nor_x_preferred":[
        "Kajak"
    ],
    "name:rus_x_preferred":[
        "\u041a\u0430\u044f\u043a"
    ],
    "name:und_x_variant":[
        "Staryy Kayak",
        "Kayak"
    ],
    "wof:name":"Kayak",
    "wof:placetype":"locality"
},
  "geometry": {"coordinates":[103.21666999999999,71.53333000000001],"type":"Point"}
}