{
  "type": "Feature",
  "properties": {
    "gn:admin1_code":"91",
    "gn:asciiname":"Kayak",
    "gn:cc2":"RU",
    "gn:country_code":"RU",
    "gn:dem":55,
    "gn:feature_class":"P",
    "gn:feature_code":"PPL",
    "gn:name":"Kayak",
    "gn:population":0,
    "gn:timezone":"Asia/Krasnoyarsk",
    "iso:country":"RU",
    "name:ara_x_preferred":[
        "\u0643\u0627\u064a\u0627\u0643"
    ],
    "name:ast_x_preferred":[
        "Kayak"
    ],
    "name:aze_x_preferred":[
        "Kayak"
    ],
    "name:bul_x_preferred":[
        "\u041a\u0430\u044f\u043a"
    ],
    "name:cat_x_preferred":[
        "Caiac"
    ],
    "name:ces_x_preferred":[
        "Kajak"
    ],
    "name:dan_x_preferred":[
        "Kajak"
    ],
    "name:deu_x_preferred":[
        "Kajak"
    ],
    "name:eng_x_preferred":[
        "Kayak"
    ],
    "name:epo_x_preferred":[
        "Kajako"
    ],
    "name:est_x_preferred":[
        "Kajak"
    ],
    "name:eus_x_preferred":[
        "Kayak"
    ],
    "name:fas_x_preferred":[
        "\u06a9\u0627\u06cc\u0627\u06a9"
    ],
    "name:fin_x_preferred":[
        "Kajakki"
    ],
    "name:fra_x_preferred":[
        "Kayak"
    ],
    "name:gla_x_preferred":[
        "Kayak"
    ],
    "name:gle_x_preferred":[
        "Cadhc"
    ],
    "name:heb_x_preferred":[
        "\u05e7\u05d9\u05d0\u05e7"
    ],
    "name:hrv_x_preferred":[
        "Kajak"
    ],
    "name:hun_x_preferred":[
        "Kajak"
    ],
    "name:ind_x_preferred":[
        "Kayak"
    ],
    "name:isl_x_preferred":[
        "H\u00fa\u00f0keipur"
    ],
    "name:ita_x_preferred":[
        "Kayak"
    ],
    "name:jav_x_preferred":[
        "Kayak"
    ],
    "name:jpn_x_preferred":[
        "\u30ab\u30e4\u30c3\u30af"
    ],
    "name:kal_x_preferred":[
        "Qajaq"
    ],
    "name:kan_x_preferred":[
        "\u0c95\u0caf\u0cbe\u0c95\u0ccd"
    ],
    "name:lav_x_preferred":[
        "Smail\u012bte"
    ],
    "name:lit_x_preferred":[
        "Kajakas"
    ],
    "name:mkd_x_preferred":[
        "\u041a\u0430\u0458\u0430\u043a"
    ],
    "name:msa_x_preferred":[
        "Kayak"
    ],
    "name:nld_x_preferred":[
        "Kajak"
    ],
    "name:nno_x_preferred":[
        "Kajakk"
    ],
    "name:nor_x_preferred":[
        "Kajak"
    ],
    "name:nor_x_variant":[
        "Kajakk"
    ],
    "name:pol_x_preferred":[
        "Kajak"
    ],
    "name:por_x_preferred":[
        "Caiaque"
    ],
    "name:ron_x_preferred":[
        "Caiac"
    ],
    "name:rus_x_preferred":[
        "\u041a\u0430\u044f\u043a"
    ],
    "name:sah_x_preferred":[
        "\u041a\u0430\u0439\u0430\u0430\u043a"
    ],
    "name:sco_x_preferred":[
        "Kayak"
    ],
    "name:slk_x_preferred":[
        "Kajak"
    ],
    "name:slv_x_preferred":[
        "Kajak"
    ],
    "name:spa_x_preferred":[
        "Kayak"
    ],
    "name:srp_x_preferred":[
        "\u041a\u0430\u0458\u0430\u043a"
    ],
    "name:swa_x_preferred":[
        "Kayaki"
    ],
    "name:swe_x_preferred":[
        "Kajak"
    ],
    "name:tgl_x_preferred":[
        "Kayak"
    ],
    "name:tha_x_preferred":[
        "\u0e04\u0e32\u0e22\u0e31\u0e01"
    ],
    "name:tur_x_preferred":[
        "Kayak"
    ],
    "name:ukr_x_preferred":[
        "\u041a\u0430\u044f\u043a"
    ],
    "name:und_x_variant":[
        "Staryy Kayak",
        "Kayak"
    ],
    "name:vie_x_preferred":[
        "Kayak"
    ],
    "wof:name":"Kayak",
    "wof:placetype":"locality"
},
  "geometry": {"coordinates":[103.21666999999999,71.53333000000001],"type":"Point"}
}