{
  "type": "Feature",
  "properties": {
    "gn:country":"RU",
    "gn:fcode":"PPLX",
    "gn:population":0,
    "iso:country":"RU",
    "name:afr_x_preferred":[
        "Presnenski"
    ],
    "name:azb_x_preferred":[
        "\u067e\u0631\u0632\u0646\u0646\u0627\u06cc\u0633\u06a9\u0627\u06cc"
    ],
    "name:aze_x_preferred":[
        "Presnenski rayonu"
    ],
    "name:bel_x_preferred":[
        "\u041f\u0440\u044d\u0441\u043d\u0435\u043d\u0441\u043a\u0456 \u0440\u0430\u0451\u043d"
    ],
    "name:bul_x_preferred":[
        "\u041f\u0440\u0435\u0441\u043d\u0435\u043d\u0441\u043a\u0438 \u0440\u0430\u0439\u043e\u043d"
    ],
    "name:ceb_x_preferred":[
        "Presnensky District"
    ],
    "name:ces_x_preferred":[
        "Presn\u011bnsk\u00fd raj\u00f3n"
    ],
    "name:dan_x_preferred":[
        "Presnja"
    ],
    "name:deu_x_preferred":[
        "Presnenski"
    ],
    "name:eng_x_preferred":[
        "Presnensky District"
    ],
    "name:epo_x_preferred":[
        "Presnenskij"
    ],
    "name:est_x_preferred":[
        "Presnja rajoon"
    ],
    "name:fra_x_preferred":[
        "Presnenski"
    ],
    "name:heb_x_preferred":[
        "\u05e4\u05e8\u05e1\u05e0\u05e0\u05e1\u05e7\u05d9 \u05e8\u05d0\u05d9\u05d5\u05df"
    ],
    "name:hun_x_preferred":[
        "Presnenszkij ker\u00fclet"
    ],
    "name:hun_x_variant":[
        "Presznyenszkij ker\u00fclet"
    ],
    "name:hye_x_preferred":[
        "\u054a\u0580\u0565\u057d\u0576\u0565\u0576\u057d\u056f\u056b \u0577\u0580\u057b\u0561\u0576"
    ],
    "name:hyw_x_preferred":[
        "\u0553\u0580\u0565\u057d\u0576\u0565\u0576\u057d\u0584\u056b \u0577\u0580\u057b\u0561\u0576"
    ],
    "name:ita_x_preferred":[
        "Presnenskij"
    ],
    "name:jpn_x_preferred":[
        "\u30d7\u30ec\u30b9\u30cb\u30e3\u5730\u533a"
    ],
    "name:nan_x_preferred":[
        "Presnensky Ko\u0101n"
    ],
    "name:nld_x_preferred":[
        "District Presnenski"
    ],
    "name:nob_x_preferred":[
        "Presnensij-distriktet"
    ],
    "name:por_x_preferred":[
        "Presnensky"
    ],
    "name:rus_x_preferred":[
        "\u041a\u0440\u0430\u0441\u043d\u0430\u044f \u041f\u0440\u0435\u0441\u043d\u044f"
    ],
    "name:rus_x_variant":[
        "\u041f\u0440\u0435\u0441\u043d\u0435\u043d\u0441\u043a\u0438\u0439",
        "\u041f\u0440\u0435\u0441\u043d\u0435\u043d\u0441\u043a\u0438\u0439 \u0440\u0430\u0439\u043e\u043d"
    ],
    "name:sco_x_preferred":[
        "Presnensky Destrict"
    ],
    "name:swe_x_preferred":[
        "Presnenskij"
    ],
    "name:tgk_x_preferred":[
        "\u041d\u043e\u04b3\u0438\u044f\u0438 \u041f\u0440\u0435\u0441\u043d\u0435\u043d\u0441\u043a\u0438\u0439"
    ],
    "name:ukr_x_preferred":[
        "\u041f\u0440\u0435\u0441\u043d\u0435\u043d\u0441\u044c\u043a\u0438\u0439"
    ],
    "name:und_x_variant":[
        "Krasnaya Presnya"
    ],
    "name:zho_x_preferred":[
        "\u666e\u5217\u65af\u59ae\u5a6d\u5340"
    ],
    "qs:name":"Presnensky",
    "qs:name_adm0":"Russia",
    "qs:name_adm1":"Moscow Federal City",
    "qs:photos":186,
    "qs:photos_1k":38,
    "qs:photos_9k":1,
    "qs:photos_9r":4,
    "qs:photos_all":186,
    "qs:photos_sr":4,
    "qs:placetype":"Suburb",
    "qs:pop_sr":"0",
    "wd:wordcount":1095,
    "wof:name":"Presnensky",
    "wof:placetype":"neighbourhood",
    "wof:population":0
},
  "geometry": {"coordinates":[37.55,55.75],"type":"Point"}
}