{
  "type": "Feature",
  "properties": {
    "gn:admin1_code":"85",
    "gn:asciiname":"Zybulino",
    "gn:country_code":"RU",
    "gn:dem":146,
    "gn:feature_class":"P",
    "gn:feature_code":"PPL",
    "gn:name":"Zybulino",
    "gn:population":0,
    "gn:timezone":"Europe/Moscow",
    "iso:country":"RU",
    "name:rus_x_preferred":[
        "\u0417\u044b\u0431\u0443\u043b\u0438\u043d\u043e"
    ],
    "wof:name":"Zybulino",
    "wof:placetype":"locality"
},
  "geometry": {"coordinates":[35.0728,59.1061],"type":"Point"}
}