{
  "type": "Feature",
  "properties": {
    "gn:admin1_code":"56",
    "gn:asciiname":"Paseka",
    "gn:country_code":"RU",
    "gn:dem":251,
    "gn:feature_class":"P",
    "gn:feature_code":"PPL",
    "gn:name":"Paseka",
    "gn:population":0,
    "gn:timezone":"Europe/Moscow",
    "iso:country":"RU",
    "name:rus_x_preferred":[
        "\u041f\u0430\u0441\u0435\u043a\u0430"
    ],
    "wof:name":"Paseka",
    "wof:placetype":"locality"
},
  "geometry": {"coordinates":[35.2104,52.3882],"type":"Point"}
}