{
  "type": "Feature",
  "properties": {
    "gn:admin1_code":"84",
    "gn:asciiname":"Rybkin",
    "gn:country_code":"RU",
    "gn:dem":115,
    "gn:feature_class":"P",
    "gn:feature_code":"PPL",
    "gn:name":"Rybkin",
    "gn:population":0,
    "gn:timezone":"Europe/Volgograd",
    "iso:country":"RU",
    "name:rus_x_preferred":[
        "\u0420\u044b\u0431\u043a\u0438\u043d"
    ],
    "name:und_x_variant":[
        "\u0420\u044b\u0431\u043a\u0438\u043d"
    ],
    "wof:name":"Rybkin",
    "wof:placetype":"locality"
},
  "geometry": {"coordinates":[42.81118,49.21987],"type":"Point"}
}