{
  "type": "Feature",
  "properties": {
    "gn:admin1_code":"37",
    "gn:asciiname":"Voronino",
    "gn:country_code":"RU",
    "gn:dem":189,
    "gn:feature_class":"P",
    "gn:feature_code":"PPL",
    "gn:name":"Voronino",
    "gn:population":0,
    "gn:timezone":"Europe/Moscow",
    "iso:country":"RU",
    "name:rus_x_preferred":[
        "\u0412\u043e\u0440\u043e\u043d\u0438\u043d\u043e"
    ],
    "wof:name":"Voronino",
    "wof:placetype":"locality"
},
  "geometry": {"coordinates":[42.5714,58.5186],"type":"Point"}
}