{
  "type": "Feature",
  "properties": {
    "gn:admin1_code":"13",
    "gn:asciiname":"Chernomorka",
    "gn:country_code":"RU",
    "gn:dem":206,
    "gn:feature_class":"P",
    "gn:feature_code":"PPL",
    "gn:name":"Chernomorka",
    "gn:population":0,
    "gn:timezone":"Asia/Yekaterinburg",
    "iso:country":"RU",
    "name:rus_x_preferred":[
        "\u0427\u0435\u0440\u043d\u043e\u043c\u043e\u0440\u043a\u0430"
    ],
    "name:und_x_variant":[
        "\u0427\u0435\u0440\u043d\u043e\u043c\u043e\u0440\u043a\u0430"
    ],
    "wof:name":"Chernomorka",
    "wof:placetype":"locality"
},
  "geometry": {"coordinates":[61.8381,54.1541],"type":"Point"}
}