{
  "type": "Feature",
  "properties": {
    "gn:admin1_code":"63",
    "gn:asciiname":"Kumakh-Sygy",
    "gn:country_code":"RU",
    "gn:dem":225,
    "gn:feature_class":"P",
    "gn:feature_code":"PPL",
    "gn:name":"Kumakh-Sygy",
    "gn:population":0,
    "gn:timezone":"Asia/Magadan",
    "iso:country":"RU",
    "name:eng_x_preferred":[
        "Kumakh-Sygy"
    ],
    "name:nor_x_preferred":[
        "Kumakh-Sysy"
    ],
    "name:rus_x_preferred":[
        "\u041a\u0443\u043c\u0430\u0445-\u0421\u044b\u0441\u044b"
    ],
    "name:rus_x_variant":[
        "\u041a\u0443\u043c\u0430\u0445-\u0421\u044b\u0433\u044b"
    ],
    "wof:name":"Kumakh-Sygy",
    "wof:placetype":"locality"
},
  "geometry": {"coordinates":[143.3579,66.34544],"type":"Point"}
}