{
  "type": "Feature",
  "properties": {
    "gn:admin1_code":"47",
    "gn:asciiname":"Puptsevo",
    "gn:country_code":"RU",
    "gn:dem":194,
    "gn:feature_class":"P",
    "gn:feature_code":"PPL",
    "gn:name":"Puptsevo",
    "gn:population":0,
    "gn:timezone":"Europe/Moscow",
    "iso:country":"RU",
    "name:rus_x_preferred":[
        "\u041f\u0443\u043f\u0446\u0435\u0432\u043e"
    ],
    "wof:name":"Puptsevo",
    "wof:placetype":"locality"
},
  "geometry": {"coordinates":[36.34938,56.24353000000001],"type":"Point"}
}