{
  "type": "Feature",
  "properties": {
    "gn:admin1_code":"33",
    "gn:asciiname":"Verkhneivkino",
    "gn:country_code":"RU",
    "gn:dem":231,
    "gn:feature_class":"P",
    "gn:feature_code":"PPL",
    "gn:name":"Verkhneivkino",
    "gn:population":0,
    "gn:timezone":"Europe/Kirov",
    "iso:country":"RU",
    "name:rus_x_preferred":[
        "\u0412\u0435\u0440\u0445\u043d\u0435\u0438\u0432\u043a\u0438\u043d\u043e"
    ],
    "name:und_x_variant":[
        "Ivkino",
        "Verkhneivkino"
    ],
    "wof:name":"Verkhneivkino",
    "wof:placetype":"locality"
},
  "geometry": {"coordinates":[49.4995,57.8893],"type":"Point"}
}