{
  "type": "Feature",
  "properties": {
    "gn:admin1_code":"54",
    "gn:asciiname":"Zaborskaya",
    "gn:country_code":"RU",
    "gn:dem":81,
    "gn:feature_class":"P",
    "gn:feature_code":"PPL",
    "gn:name":"Zaborskaya",
    "gn:population":0,
    "gn:timezone":"Asia/Omsk",
    "iso:country":"RU",
    "wof:name":"Zaborskaya",
    "wof:placetype":"locality"
},
  "geometry": {"coordinates":[72.71666999999999,57.23333],"type":"Point"}
}