{
  "type": "Feature",
  "properties": {
    "gn:admin1_code":"71",
    "gn:asciiname":"Mosina",
    "gn:country_code":"RU",
    "gn:dem":190,
    "gn:feature_class":"P",
    "gn:feature_code":"PPL",
    "gn:name":"Mosina",
    "gn:population":0,
    "gn:timezone":"Asia/Yekaterinburg",
    "iso:country":"RU",
    "name:azb_x_preferred":[
        "\u0645\u0648\u0634\u06cc\u0646\u0627"
    ],
    "name:bel_x_preferred":[
        "\u041c\u0430\u0441\u0456\u043d\u0430"
    ],
    "name:ceb_x_preferred":[
        "Mosina"
    ],
    "name:ces_x_preferred":[
        "Mosina"
    ],
    "name:deu_x_preferred":[
        "Mosina"
    ],
    "name:epo_x_preferred":[
        "Mosina"
    ],
    "name:fas_x_preferred":[
        "\u0645\u0648\u0634\u06cc\u0646\u0627"
    ],
    "name:fin_x_preferred":[
        "Mosina"
    ],
    "name:fra_x_preferred":[
        "Mosina"
    ],
    "name:jav_x_preferred":[
        "Mosina"
    ],
    "name:lav_x_preferred":[
        "Mosina"
    ],
    "name:lit_x_preferred":[
        "Mosina"
    ],
    "name:msa_x_preferred":[
        "Mosina"
    ],
    "name:nld_x_preferred":[
        "Mosina"
    ],
    "name:pol_x_preferred":[
        "Mosina"
    ],
    "name:por_x_preferred":[
        "Mosina"
    ],
    "name:ron_x_preferred":[
        "Mosina"
    ],
    "name:rus_x_preferred":[
        "\u041c\u043e\u0441\u0438\u043d\u0430"
    ],
    "name:slk_x_preferred":[
        "Mosina"
    ],
    "name:srp_x_preferred":[
        "\u041c\u043e\u0441\u0438\u043d\u0430"
    ],
    "name:swe_x_preferred":[
        "Mosina"
    ],
    "name:ukr_x_preferred":[
        "\u041c\u043e\u0441\u0456\u043d\u0430"
    ],
    "name:vie_x_preferred":[
        "Mosina"
    ],
    "name:zho_x_preferred":[
        "\u83ab\u897f\u7d0d"
    ],
    "wof:name":"Mosina",
    "wof:placetype":"locality"
},
  "geometry": {"coordinates":[61.7117,56.6111],"type":"Point"}
}