{
  "type": "Feature",
  "properties": {
    "gn:admin1_code":"71",
    "gn:asciiname":"Mosina",
    "gn:country_code":"RU",
    "gn:dem":190,
    "gn:feature_class":"P",
    "gn:feature_code":"PPL",
    "gn:name":"Mosina",
    "gn:population":0,
    "gn:timezone":"Asia/Yekaterinburg",
    "iso:country":"RU",
    "name:rus_x_preferred":[
        "\u041c\u043e\u0441\u0438\u043d\u0430"
    ],
    "name:und_x_variant":[
        "\u041c\u043e\u0441\u0438\u043d\u0430"
    ],
    "wof:name":"Mosina",
    "wof:placetype":"locality"
},
  "geometry": {"coordinates":[61.7117,56.6111],"type":"Point"}
}