{
  "type": "Feature",
  "properties": {
    "gn:admin1_code":"69",
    "gn:asciiname":"Novyy Krupets",
    "gn:country_code":"RU",
    "gn:dem":189,
    "gn:feature_class":"P",
    "gn:feature_code":"PPL",
    "gn:name":"Novyy Krupets",
    "gn:population":0,
    "gn:timezone":"Europe/Moscow",
    "iso:country":"RU",
    "name:rus_x_preferred":[
        "\u041d\u043e\u0432\u044b\u0439 \u041a\u0440\u0443\u043f\u0435\u0446"
    ],
    "wof:name":"Novyy Krupets",
    "wof:placetype":"locality"
},
  "geometry": {"coordinates":[33.2003,53.7552],"type":"Point"}
}