{
  "type": "Feature",
  "properties": {
    "gn:admin1_code":"81",
    "gn:asciiname":"Amirovka",
    "gn:country_code":"RU",
    "gn:dem":131,
    "gn:feature_class":"P",
    "gn:feature_code":"PPL",
    "gn:name":"Amirovka",
    "gn:population":0,
    "gn:timezone":"Europe/Ulyanovsk",
    "iso:country":"RU",
    "name:che_x_preferred":[
        "\u0410\u043c\u0438\u0440\u043e\u0432\u043a\u0430"
    ],
    "name:chv_x_preferred":[
        "\u0410\u043c\u0438\u0440\u043e\u0432\u043a\u0430"
    ],
    "name:rus_x_preferred":[
        "\u0410\u043c\u0438\u0440\u043e\u0432\u043a\u0430"
    ],
    "name:tat_x_preferred":[
        "\u04d8\u043c\u0438\u0440"
    ],
    "wof:name":"Amirovka",
    "wof:placetype":"locality"
},
  "geometry": {"coordinates":[50.146,54.1851],"type":"Point"}
}