{
  "type": "Feature",
  "properties": {
    "gn:admin1_code":"13",
    "gn:asciiname":"Klyuchevka Vtoraya",
    "gn:country_code":"RU",
    "gn:dem":319,
    "gn:feature_class":"P",
    "gn:feature_code":"PPL",
    "gn:name":"Klyuch\u00ebvka Vtoraya",
    "gn:population":0,
    "gn:timezone":"Asia/Yekaterinburg",
    "iso:country":"RU",
    "name:eng_x_preferred":[
        "Klyuch\u00ebvka Vtoraya"
    ],
    "name:nor_x_preferred":[
        "Kljutsjevka"
    ],
    "name:rus_x_preferred":[
        "\u041a\u043b\u044e\u0447\u0435\u0432\u043a\u0430"
    ],
    "name:rus_x_variant":[
        "\u041a\u043b\u044e\u0447\u0451\u0432\u043a\u0430 \u0412\u0442\u043e\u0440\u0430\u044f"
    ],
    "name:und_x_variant":[
        "Klyuchevskiy",
        "Klyuchevskiy Vtoroy",
        "Klyuchovka Vtoraya"
    ],
    "wof:name":"Klyuchevka Vtoraya",
    "wof:placetype":"locality"
},
  "geometry": {"coordinates":[60.506,54.7129],"type":"Point"}
}