{
  "type": "Feature",
  "properties": {
    "gn:admin1_code":"25",
    "gn:asciiname":"Gorodets",
    "gn:country_code":"RU",
    "gn:dem":163,
    "gn:feature_class":"P",
    "gn:feature_code":"PPL",
    "gn:name":"Gorodets",
    "gn:population":0,
    "gn:timezone":"Europe/Moscow",
    "iso:country":"RU",
    "name:rus_x_preferred":[
        "\u0413\u043e\u0440\u043e\u0434\u0435\u0446"
    ],
    "name:und_x_variant":[
        "Gorodets"
    ],
    "wof:name":"Gorodets",
    "wof:placetype":"locality"
},
  "geometry": {"coordinates":[35.05222,54.78056],"type":"Point"}
}