{
  "type": "Feature",
  "properties": {
    "gn:admin1_code":"52",
    "gn:asciiname":"Gusiny",
    "gn:country_code":"RU",
    "gn:dem":205,
    "gn:feature_class":"P",
    "gn:feature_code":"PPL",
    "gn:name":"Gusiny",
    "gn:population":0,
    "gn:timezone":"Europe/Moscow",
    "iso:country":"RU",
    "name:rus_x_preferred":[
        "\u0413\u0443\u0441\u0438\u043d\u044b"
    ],
    "name:und_x_variant":[
        "\u0413\u0443\u0441\u0438\u043d\u044b"
    ],
    "wof:name":"Gusiny",
    "wof:placetype":"locality"
},
  "geometry": {"coordinates":[33.45,58.95],"type":"Point"}
}