{
  "type": "Feature",
  "properties": {
    "gn:admin1_code":"71",
    "gn:asciiname":"Kapushkanka",
    "gn:country_code":"RU",
    "gn:dem":350,
    "gn:feature_class":"P",
    "gn:feature_code":"PPL",
    "gn:name":"Kapushkanka",
    "gn:population":0,
    "gn:timezone":"Asia/Yekaterinburg",
    "iso:country":"RU",
    "name:rus_x_preferred":[
        "\u041a\u0430\u043f\u0443\u0448\u043a\u0430\u043d\u043a\u0430"
    ],
    "wof:name":"Kapushkanka",
    "wof:placetype":"locality"
},
  "geometry": {"coordinates":[58.95558000000001,56.10767],"type":"Point"}
}