{
  "type": "Feature",
  "properties": {
    "gn:admin1_code":"10",
    "gn:asciiname":"Sedki",
    "gn:country_code":"RU",
    "gn:dem":190,
    "gn:feature_class":"P",
    "gn:feature_code":"PPL",
    "gn:name":"Sedki",
    "gn:population":0,
    "gn:timezone":"Europe/Moscow",
    "iso:country":"RU",
    "name:rus_x_preferred":[
        "\u0421\u0435\u0434\u043a\u0438"
    ],
    "name:und_x_variant":[
        "Syadki",
        "Sedki"
    ],
    "wof:name":"Sedki",
    "wof:placetype":"locality"
},
  "geometry": {"coordinates":[33.04105,53.09168],"type":"Point"}
}