{
  "type": "Feature",
  "properties": {
    "gn:admin1_code":"60",
    "gn:asciiname":"Sukhanovka",
    "gn:country_code":"RU",
    "gn:dem":224,
    "gn:feature_class":"P",
    "gn:feature_code":"PPL",
    "gn:name":"Sukhanovka",
    "gn:population":0,
    "gn:timezone":"Europe/Moscow",
    "iso:country":"RU",
    "name:rus_x_preferred":[
        "\u0421\u0443\u0445\u0430\u043d\u043e\u0432\u043a\u0430"
    ],
    "wof:name":"Sukhanovka",
    "wof:placetype":"locality"
},
  "geometry": {"coordinates":[29.8626,56.1954],"type":"Point"}
}