{
  "type": "Feature",
  "properties": {
    "gn:admin1_code":"52.0",
    "gn:asciiname":"Bol'shoy Zakhod",
    "gn:country_code":"RU",
    "gn:dem":62,
    "gn:feature_class":"P",
    "gn:feature_code":"PPL",
    "gn:name":"Bol\u2019shoy Zakhod",
    "gn:population":0,
    "gn:timezone":"Europe/Moscow",
    "iso:country":"RU",
    "name:rus_x_preferred":[
        "\u0411\u043e\u043b\u044c\u0448\u043e\u0439 \u0417\u0430\u0445\u043e\u0434"
    ],
    "name:und_x_variant":[
        "Sachod",
        "Bol\u2019shoy Zakhod"
    ],
    "wof:name":"Bol'shoy Zakhod",
    "wof:placetype":"locality"
},
  "geometry": {"coordinates":[31.97278,57.97995],"type":"Point"}
}