{
  "type": "Feature",
  "properties": {
    "gn:admin1_code":"5",
    "gn:asciiname":"Zakharovka",
    "gn:country_code":"RU",
    "gn:dem":174,
    "gn:feature_class":"P",
    "gn:feature_code":"PPL",
    "gn:name":"Zakharovka",
    "gn:population":0,
    "gn:timezone":"Asia/Yakutsk",
    "iso:country":"RU",
    "name:und_x_variant":[
        "Zakhar\u2019yevka",
        "Zakharovka"
    ],
    "wof:name":"Zakharovka",
    "wof:placetype":"locality"
},
  "geometry": {"coordinates":[128.29669999999999,50.64074],"type":"Point"}
}