{
  "type": "Feature",
  "properties": {
    "gn:admin1_code":"21.0",
    "gn:asciiname":"Shlykovo",
    "gn:country_code":"RU",
    "gn:dem":111,
    "gn:feature_class":"P",
    "gn:feature_code":"PPL",
    "gn:name":"Shlykovo",
    "gn:population":0,
    "gn:timezone":"Europe/Moscow",
    "iso:country":"RU",
    "name:nor_x_preferred":[
        "Sjlykovo"
    ],
    "name:rus_x_preferred":[
        "\u0428\u043b\u044b\u043a\u043e\u0432\u043e"
    ],
    "wof:name":"Shlykovo",
    "wof:placetype":"locality"
},
  "geometry": {"coordinates":[42.58294,56.69413],"type":"Point"}
}