{
  "type": "Feature",
  "properties": {
    "gn:admin1_code":"46.0",
    "gn:asciiname":"Apollonovka",
    "gn:country_code":"RU",
    "gn:dem":207,
    "gn:feature_class":"P",
    "gn:feature_code":"PPL",
    "gn:name":"Apollonovka",
    "gn:population":0,
    "gn:timezone":"Europe/Moscow",
    "iso:country":"RU",
    "name:rus_x_preferred":[
        "\u0410\u043f\u043e\u043b\u043b\u043e\u043d\u043e\u0432\u043a\u0430"
    ],
    "wof:name":"Apollonovka",
    "wof:placetype":"locality"
},
  "geometry": {"coordinates":[44.97572,54.28361999999999],"type":"Point"}
}