{
  "type": "Feature",
  "properties": {
    "gn:admin1_code":"47",
    "gn:asciiname":"Novomaykovo",
    "gn:country_code":"RU",
    "gn:dem":127,
    "gn:feature_class":"P",
    "gn:feature_code":"PPL",
    "gn:name":"Novomaykovo",
    "gn:population":0,
    "gn:timezone":"Europe/Moscow",
    "iso:country":"RU",
    "name:rus_x_preferred":[
        "\u041d\u043e\u0432\u043e\u043c\u0430\u0439\u043a\u043e\u0432\u043e"
    ],
    "name:und_x_variant":[
        "\u041d\u043e\u0432\u043e\u043c\u0430\u0439\u043a\u043e\u0432\u043e"
    ],
    "wof:name":"Novomaykovo",
    "wof:placetype":"locality"
},
  "geometry": {"coordinates":[38.47661,55.32004000000001],"type":"Point"}
}