{
  "type": "Feature",
  "properties": {
    "gn:admin1_code":"53",
    "gn:asciiname":"Krasnaya Roshcha",
    "gn:country_code":"RU",
    "gn:dem":158,
    "gn:feature_class":"P",
    "gn:feature_code":"PPL",
    "gn:name":"Krasnaya Roshcha",
    "gn:population":0,
    "gn:timezone":"Asia/Novosibirsk",
    "iso:country":"RU",
    "name:rus_x_preferred":[
        "\u041a\u0440\u0430\u0441\u043d\u0430\u044f \u0420\u043e\u0449\u0430"
    ],
    "wof:name":"Krasnaya Roshcha",
    "wof:placetype":"locality"
},
  "geometry": {"coordinates":[80.36667,54.46666999999999],"type":"Point"}
}