{
  "type": "Feature",
  "properties": {
    "gn:admin1_code":"92",
    "gn:asciiname":"Tonkiy",
    "gn:country_code":"RU",
    "gn:dem":2,
    "gn:feature_class":"P",
    "gn:feature_code":"PPL",
    "gn:name":"Tonkiy",
    "gn:population":0,
    "gn:timezone":"Asia/Kamchatka",
    "iso:country":"RU",
    "wof:name":"Tonkiy",
    "wof:placetype":"locality"
},
  "geometry": {"coordinates":[162.74413999999999,56.30682],"type":"Point"}
}