{
  "type": "Feature",
  "properties": {
    "gn:admin1_code":"45.0",
    "gn:asciiname":"Apanayevo",
    "gn:country_code":"RU",
    "gn:dem":159,
    "gn:feature_class":"P",
    "gn:feature_code":"PPL",
    "gn:name":"Apanayevo",
    "gn:population":0,
    "gn:timezone":"Europe/Moscow",
    "iso:country":"RU",
    "name:nor_x_preferred":[
        "Apanajevo"
    ],
    "name:rus_x_preferred":[
        "\u0410\u043f\u0430\u043d\u0430\u0435\u0432\u043e"
    ],
    "wof:name":"Apanayevo",
    "wof:placetype":"locality"
},
  "geometry": {"coordinates":[48.90972,56.445],"type":"Point"}
}