{
  "type": "Feature",
  "properties": {
    "gn:admin1_code":"60",
    "gn:asciiname":"Mezhnik",
    "gn:country_code":"RU",
    "gn:dem":78,
    "gn:feature_class":"P",
    "gn:feature_code":"PPL",
    "gn:name":"Mezhnik",
    "gn:population":0,
    "gn:timezone":"Europe/Moscow",
    "iso:country":"RU",
    "name:rus_x_preferred":[
        "\u041c\u0435\u0436\u043d\u0438\u043a"
    ],
    "name:und_x_variant":[
        "Mezhik",
        "Mezhnik",
        "\u041c\u0435\u0436\u043d\u0438\u043a"
    ],
    "wof:name":"Mezhnik",
    "wof:placetype":"locality"
},
  "geometry": {"coordinates":[30.11367000000001,57.78787],"type":"Point"}
}