{
  "type": "Feature",
  "properties": {
    "gn:admin1_code":"77",
    "gn:asciiname":"Sukovo",
    "gn:country_code":"RU",
    "gn:dem":234,
    "gn:feature_class":"P",
    "gn:feature_code":"PPL",
    "gn:name":"Sukovo",
    "gn:population":0,
    "gn:timezone":"Europe/Moscow",
    "iso:country":"RU",
    "name:eng_x_preferred":[
        "Sukovo"
    ],
    "name:nor_x_preferred":[
        "Sukovo"
    ],
    "name:rus_x_preferred":[
        "\u0421\u0443\u043a\u043e\u0432\u043e"
    ],
    "name:und_x_variant":[
        "\u0421\u0443\u043a\u043e\u0432\u043e",
        "Sukovo"
    ],
    "wof:name":"Sukovo",
    "wof:placetype":"locality"
},
  "geometry": {"coordinates":[33.95814,56.51433000000001],"type":"Point"}
}