{
  "type": "Feature",
  "properties": {
    "gn:admin1_code":"29",
    "gn:asciiname":"Vostok-Ugol'",
    "gn:country_code":"RU",
    "gn:dem":289,
    "gn:feature_class":"P",
    "gn:feature_code":"PPL",
    "gn:name":"Vostok-Ugol\u2019",
    "gn:population":0,
    "gn:timezone":"Asia/Novokuznetsk",
    "iso:country":"RU",
    "name:rus_x_preferred":[
        "\u0412\u043e\u0441\u0442\u043e\u043a-\u0423\u0433\u043e\u043b\u044c"
    ],
    "name:und_x_variant":[
        "Vostok-Ugol\u2019"
    ],
    "wof:name":"Vostok-Ugol'",
    "wof:placetype":"locality"
},
  "geometry": {"coordinates":[87.0582,53.5683],"type":"Point"}
}