{
  "type": "Feature",
  "properties": {
    "gn:admin1_code":"33",
    "gn:asciiname":"Pleshkovo",
    "gn:country_code":"RU",
    "gn:dem":120,
    "gn:feature_class":"P",
    "gn:feature_code":"PPL",
    "gn:name":"Pleshkovo",
    "gn:population":0,
    "gn:timezone":"Europe/Kirov",
    "iso:country":"RU",
    "name:rus_x_preferred":[
        "\u041f\u043b\u0435\u0448\u043a\u043e\u0432\u043e"
    ],
    "name:und_x_variant":[
        "\u041f\u043b\u0435\u0448\u043a\u043e\u0432\u043e"
    ],
    "wof:name":"Pleshkovo",
    "wof:placetype":"locality"
},
  "geometry": {"coordinates":[50.2742,57.9383],"type":"Point"}
}