{
  "type": "Feature",
  "properties": {
    "gn:admin1_code":"7.0",
    "gn:asciiname":"Chimbya",
    "gn:country_code":"RU",
    "gn:dem":-25,
    "gn:feature_class":"P",
    "gn:feature_code":"PPL",
    "gn:name":"Chimbya",
    "gn:population":0,
    "gn:timezone":"Europe/Astrakhan",
    "iso:country":"RU",
    "name:rus_x_preferred":[
        "\u0427\u0438\u043c\u0431\u044f"
    ],
    "name:und_x_variant":[
        "\u0427\u0438\u043c\u0431\u044f"
    ],
    "wof:name":"Chimbya",
    "wof:placetype":"locality"
},
  "geometry": {"coordinates":[47.43861,45.70361],"type":"Point"}
}