{
  "type": "Feature",
  "properties": {
    "gn:admin1_code":"67",
    "gn:asciiname":"Molodezhnyy",
    "gn:country_code":"RU",
    "gn:dem":44,
    "gn:feature_class":"P",
    "gn:feature_code":"PPL",
    "gn:name":"Molod\u00ebzhnyy",
    "gn:population":0,
    "gn:timezone":"Europe/Saratov",
    "iso:country":"RU",
    "name:rus_x_preferred":[
        "Molod\u00ebzhnyy"
    ],
    "name:rus_x_variant":[
        "\u041c\u043e\u043b\u043e\u0434\u00eb\u0436\u043d\u044b\u0439"
    ],
    "wof:name":"Molodezhnyy",
    "wof:placetype":"locality"
},
  "geometry": {"coordinates":[49.5373,51.9465],"type":"Point"}
}