{
  "type": "Feature",
  "properties": {
    "gn:admin1_code":"56",
    "gn:asciiname":"Tolmachevo",
    "gn:country_code":"RU",
    "gn:dem":202,
    "gn:feature_class":"P",
    "gn:feature_code":"PPL",
    "gn:name":"Tolmach\u00ebvo",
    "gn:population":0,
    "gn:timezone":"Europe/Moscow",
    "iso:country":"RU",
    "name:rus_x_preferred":[
        "\u0422\u043e\u043b\u043c\u0430\u0447\u0451\u0432\u043e"
    ],
    "name:und_x_variant":[
        "Tolmach\u00ebvo"
    ],
    "wof:name":"Tolmachevo",
    "wof:placetype":"locality"
},
  "geometry": {"coordinates":[35.4424,52.6264],"type":"Point"}
}