{
  "type": "Feature",
  "properties": {
    "gn:admin1_code":"76",
    "gn:asciiname":"Lunevka",
    "gn:country_code":"RU",
    "gn:dem":236,
    "gn:feature_class":"P",
    "gn:feature_code":"PPL",
    "gn:name":"Lun\u00ebvka",
    "gn:population":0,
    "gn:timezone":"Europe/Moscow",
    "iso:country":"RU",
    "name:rus_x_preferred":[
        "\u041b\u0443\u043d\u0451\u0432\u043a\u0430"
    ],
    "name:und_x_variant":[
        "Lun\u00ebvka"
    ],
    "wof:name":"Lunevka",
    "wof:placetype":"locality"
},
  "geometry": {"coordinates":[38.01607,53.5086],"type":"Point"}
}