{
  "type": "Feature",
  "properties": {
    "gn:admin1_code":"78",
    "gn:asciiname":"Novoye Lybayevo",
    "gn:country_code":"RU",
    "gn:dem":62,
    "gn:feature_class":"P",
    "gn:feature_code":"PPL",
    "gn:name":"Novoye Lybayevo",
    "gn:population":0,
    "gn:timezone":"Asia/Yekaterinburg",
    "iso:country":"RU",
    "name:eng_x_preferred":[
        "Novoye Lybayevo"
    ],
    "name:nor_x_preferred":[
        "Novolybajevo"
    ],
    "name:rus_x_preferred":[
        "\u041d\u043e\u0432\u043e\u043b\u044b\u0431\u0430\u0435\u0432\u043e"
    ],
    "name:rus_x_variant":[
        "\u041d\u043e\u0432\u043e\u0435 \u041b\u044b\u0431\u0430\u0435\u0432\u043e"
    ],
    "name:und_x_variant":[
        "Novo-Lybayevo",
        "Novoye Lybayevo",
        "\u041d\u043e\u0432\u043e\u0435 \u041b\u044b\u0431\u0430\u0435\u0432\u043e"
    ],
    "wof:name":"Novoye Lybayevo",
    "wof:placetype":"locality"
},
  "geometry": {"coordinates":[66.3489,56.48874],"type":"Point"}
}