{
  "type": "Feature",
  "properties": {
    "gn:admin1_code":"45",
    "gn:asciiname":"Polyana",
    "gn:country_code":"RU",
    "gn:dem":93,
    "gn:feature_class":"P",
    "gn:feature_code":"PPL",
    "gn:name":"Polyana",
    "gn:population":0,
    "gn:timezone":"Europe/Moscow",
    "iso:country":"RU",
    "name:rus_x_preferred":[
        "\u041f\u043e\u043b\u044f\u043d\u0430"
    ],
    "wof:name":"Polyana",
    "wof:placetype":"locality"
},
  "geometry": {"coordinates":[46.18014,56.28824],"type":"Point"}
}