{
  "type": "Feature",
  "properties": {
    "gn:gn_country":"RU",
    "gn:gn_fcode":"PPL",
    "gn:gn_pop":0,
    "iso:country":"RU",
    "name:eng_x_preferred":[
        "Kaz'minskoye"
    ],
    "name:nor_x_preferred":[
        "Kazminskoje"
    ],
    "name:rus_x_preferred":[
        "\u041a\u0430\u0437\u044c\u043c\u0438\u043d\u0441\u043a\u043e\u0435"
    ],
    "name:rus_x_variant":[
        "Kaz\u2019minskoye",
        "Koz\u2019minskoye"
    ],
    "name:unk_x_variant":[
        "Koz\u2019minskoye"
    ],
    "qs_pg:aaroncc":"RU",
    "qs_pg:gn_country":"RU",
    "qs_pg:gn_fcode":"PPL",
    "qs_pg:gn_pop":0,
    "qs_pg:name":"Kaz'minskoye",
    "qs_pg:name_adm0":"Russia",
    "qs_pg:name_adm1":"Stavropol Krai",
    "qs_pg:photos_9r":0,
    "qs_pg:photos_sr":0,
    "qs_pg:pop_sr":6,
    "qs_pg:qs_pg_placetype":"locality",
    "qs_pg:qs_pg_placetype_gp":"Town",
    "qs_pg:woe_adm0":23424936,
    "woe:adm0_id":23424936,
    "woe:name_adm0":"Russia",
    "woe:name_adm1":"Stavropol Krai",
    "woe:placetype":"Town",
    "wof:name":"Kaz'minskoye",
    "wof:placetype":"locality"
},
  "geometry": {"coordinates":[41.6734,44.5872],"type":"Point"}
}