{
  "type": "Feature",
  "properties": {
    "gn:admin1_code":"56",
    "gn:asciiname":"Masal'skaya",
    "gn:country_code":"RU",
    "gn:dem":189,
    "gn:feature_class":"P",
    "gn:feature_code":"PPL",
    "gn:name":"Masal\u2019skaya",
    "gn:population":0,
    "gn:timezone":"Europe/Moscow",
    "iso:country":"RU",
    "name:rus_x_preferred":[
        "\u041c\u0430\u0441\u0430\u043b\u044c\u0441\u043a\u0430\u044f"
    ],
    "name:und_x_variant":[
        "Masal\u2019skaya",
        "\u041c\u0430\u0441\u0430\u043b\u044c\u0441\u043a\u0430\u044f"
    ],
    "wof:name":"Masal'skaya",
    "wof:placetype":"locality"
},
  "geometry": {"coordinates":[35.90649000000001,53.23703],"type":"Point"}
}