{
  "type": "Feature",
  "properties": {
    "gn:admin1_code":"77",
    "gn:asciiname":"Akulino",
    "gn:country_code":"RU",
    "gn:dem":218,
    "gn:feature_class":"P",
    "gn:feature_code":"PPL",
    "gn:name":"Akulino",
    "gn:population":0,
    "gn:timezone":"Europe/Moscow",
    "iso:country":"RU",
    "name:nor_x_preferred":[
        "Akulino"
    ],
    "name:rus_x_preferred":[
        "\u0410\u043a\u0443\u043b\u0438\u043d\u043e"
    ],
    "wof:name":"Akulino",
    "wof:placetype":"locality"
},
  "geometry": {"coordinates":[33.15889,55.91194],"type":"Point"}
}