{
  "type": "Feature",
  "properties": {
    "gn:admin1_code":"84.0",
    "gn:asciiname":"Bulekovskiy",
    "gn:country_code":"RU",
    "gn:dem":95,
    "gn:feature_class":"P",
    "gn:feature_code":"PPL",
    "gn:name":"Bulekovskiy",
    "gn:population":0,
    "gn:timezone":"Europe/Volgograd",
    "iso:country":"RU",
    "name:rus_x_preferred":[
        "\u0411\u0443\u043b\u0435\u043a\u043e\u0432\u0441\u043a\u0438\u0439"
    ],
    "name:und_x_variant":[
        "\u0411\u0443\u043b\u0435\u043a\u043e\u0432\u0441\u043a\u0438\u0439"
    ],
    "wof:name":"Bulekovskiy",
    "wof:placetype":"locality"
},
  "geometry": {"coordinates":[41.8142,50.6522],"type":"Point"}
}