{
  "type": "Feature",
  "properties": {
    "gn:admin1_code":"51.0",
    "gn:asciiname":"Bol'shaya Bortna",
    "gn:country_code":"RU",
    "gn:dem":124,
    "gn:feature_class":"P",
    "gn:feature_code":"PPL",
    "gn:name":"Bol\u2019shaya Bortna",
    "gn:population":0,
    "gn:timezone":"Europe/Moscow",
    "iso:country":"RU",
    "name:rus_x_preferred":[
        "\u0411\u043e\u043b\u044c\u0448\u0430\u044f \u0411\u043e\u0440\u0442\u043d\u0430"
    ],
    "name:und_x_variant":[
        "Bol\u2019shoye Bortnoye",
        "Bol\u2019shaya Bortnaya",
        "Bol\u2019shaya Bortna",
        "\u0411\u043e\u043b\u044c\u0448\u0430\u044f \u0411\u043e\u0440\u0442\u043d\u0430"
    ],
    "wof:name":"Bol'shaya Bortna",
    "wof:placetype":"locality"
},
  "geometry": {"coordinates":[44.41513,57.01509],"type":"Point"}
}