{
  "type": "Feature",
  "properties": {
    "gn:admin1_code":"38.0",
    "gn:asciiname":"Vozrozhdeniye",
    "gn:country_code":"RU",
    "gn:dem":90,
    "gn:feature_class":"P",
    "gn:feature_code":"PPL",
    "gn:name":"Vozrozhdeniye",
    "gn:population":0,
    "gn:timezone":"Europe/Moscow",
    "iso:country":"RU",
    "name:fin_x_preferred":[
        "Vozro\u017edenije"
    ],
    "name:fra_x_preferred":[
        "Vozrozhdeniye"
    ],
    "name:hrv_x_preferred":[
        "Vozro\u017edenije"
    ],
    "name:lit_x_preferred":[
        "Vozro\u017edenij\u0117"
    ],
    "name:pol_x_preferred":[
        "Wozro\u017cdienije"
    ],
    "name:por_x_preferred":[
        "Vozhrozhdenie"
    ],
    "name:rus_x_preferred":[
        "\u0412\u043e\u0437\u0440\u043e\u0436\u0434\u0435\u043d\u0438\u0435"
    ],
    "name:sco_x_preferred":[
        "Vozrozhdeniye"
    ],
    "name:spa_x_preferred":[
        "Vozrozhdenie"
    ],
    "wof:name":"Vozrozhdeniye",
    "wof:placetype":"locality"
},
  "geometry": {"coordinates":[40.00639,45.19028],"type":"Point"}
}