{
  "type": "Feature",
  "properties": {
    "gn:admin1_code":"43",
    "gn:asciiname":"Natal'yevka",
    "gn:country_code":"RU",
    "gn:dem":150,
    "gn:feature_class":"P",
    "gn:feature_code":"PPL",
    "gn:name":"Natal\u2019yevka",
    "gn:population":0,
    "gn:timezone":"Europe/Moscow",
    "iso:country":"RU",
    "name:rus_x_preferred":[
        "\u041d\u0430\u0442\u0430\u043b\u044c\u0435\u0432\u043a\u0430"
    ],
    "name:und_x_variant":[
        "Natal\u2019yevka"
    ],
    "wof:name":"Natal'yevka",
    "wof:placetype":"locality"
},
  "geometry": {"coordinates":[38.04708,52.09403],"type":"Point"}
}