{
  "type": "Feature",
  "properties": {
    "gn:admin1_code":"37.0",
    "gn:asciiname":"Levkovo",
    "gn:country_code":"RU",
    "gn:dem":120,
    "gn:feature_class":"P",
    "gn:feature_code":"PPL",
    "gn:name":"Levkovo",
    "gn:population":0,
    "gn:timezone":"Europe/Moscow",
    "iso:country":"RU",
    "name:rus_x_preferred":[
        "\u041b\u0435\u0432\u043a\u043e\u0432\u043e"
    ],
    "name:und_x_variant":[
        "\u041b\u0435\u0432\u043a\u043e\u0432\u043e"
    ],
    "wof:name":"Levkovo",
    "wof:placetype":"locality"
},
  "geometry": {"coordinates":[42.26116,57.66141],"type":"Point"}
}