{
  "type": "Feature",
  "properties": {
    "gn:admin1_code":"60",
    "gn:asciiname":"Play",
    "gn:country_code":"RU",
    "gn:dem":168,
    "gn:feature_class":"P",
    "gn:feature_code":"PPL",
    "gn:name":"Play",
    "gn:population":0,
    "gn:timezone":"Europe/Moscow",
    "iso:country":"RU",
    "name:cat_x_preferred":[
        "Play"
    ],
    "name:ces_x_preferred":[
        "Play"
    ],
    "name:dan_x_preferred":[
        "Play"
    ],
    "name:deu_x_preferred":[
        "Play"
    ],
    "name:fin_x_preferred":[
        "Play"
    ],
    "name:fra_x_preferred":[
        "Play"
    ],
    "name:hun_x_preferred":[
        "Play"
    ],
    "name:ita_x_preferred":[
        "Play"
    ],
    "name:kor_x_preferred":[
        "\ud50c\ub808\uc774"
    ],
    "name:nld_x_preferred":[
        "Play"
    ],
    "name:pol_x_preferred":[
        "Play"
    ],
    "name:por_x_preferred":[
        "Play"
    ],
    "name:rus_x_preferred":[
        "Play"
    ],
    "name:spa_x_preferred":[
        "Play"
    ],
    "name:swe_x_preferred":[
        "Play"
    ],
    "name:tgl_x_preferred":[
        "Play"
    ],
    "name:ukr_x_preferred":[
        "Play"
    ],
    "name:zho_x_preferred":[
        "Play"
    ],
    "wof:name":"Play",
    "wof:placetype":"locality"
},
  "geometry": {"coordinates":[30.27083,56.36056],"type":"Point"}
}