{
  "type": "Feature",
  "properties": {
    "gn:admin1_code":"85.0",
    "gn:asciiname":"Bol'shoye Palozero",
    "gn:country_code":"RU",
    "gn:dem":65,
    "gn:feature_class":"P",
    "gn:feature_code":"PPL",
    "gn:name":"Bol\u2019shoye Palozero",
    "gn:population":0,
    "gn:timezone":"Europe/Moscow",
    "iso:country":"RU",
    "name:rus_x_preferred":[
        "\u0411\u043e\u043b\u044c\u0448\u043e\u0435 \u041f\u0430\u043b\u043e\u0437\u0435\u0440\u043e"
    ],
    "name:und_x_variant":[
        "Iso Palj\u00e4rvi",
        "Bol\u2019shoye Polozero",
        "Bol\u2019shoye Palozero"
    ],
    "wof:name":"Bol'shoye Palozero",
    "wof:placetype":"locality"
},
  "geometry": {"coordinates":[36.35,60.98333],"type":"Point"}
}