{
  "type": "Feature",
  "properties": {
    "gn:admin1_code":"13",
    "gn:asciiname":"Minka",
    "gn:country_code":"RU",
    "gn:dem":335,
    "gn:feature_class":"P",
    "gn:feature_code":"PPL",
    "gn:name":"Minka",
    "gn:population":0,
    "gn:timezone":"Asia/Yekaterinburg",
    "iso:country":"RU",
    "name:deu_x_preferred":[
        "Minka"
    ],
    "name:eng_x_preferred":[
        "Minka"
    ],
    "name:fas_x_preferred":[
        "\u0645\u06cc\u0646\u06a9\u0627"
    ],
    "name:fra_x_preferred":[
        "Minka"
    ],
    "name:ita_x_preferred":[
        "Minka"
    ],
    "name:jpn_x_preferred":[
        "\u65e5\u672c\u306e\u6c11\u5bb6"
    ],
    "name:mal_x_preferred":[
        "\u0d2e\u0d3f\u0d7b\u0d15"
    ],
    "name:nor_x_preferred":[
        "Minka"
    ],
    "name:por_x_preferred":[
        "Minka"
    ],
    "name:ron_x_preferred":[
        "Minka"
    ],
    "name:rus_x_preferred":[
        "\u041c\u0438\u043d\u043a\u0430"
    ],
    "name:slk_x_preferred":[
        "Minka"
    ],
    "name:spa_x_preferred":[
        "Minka"
    ],
    "name:tam_x_preferred":[
        "\u0bae\u0bbf\u0ba9\u0bcd\u0b95\u0bbe"
    ],
    "name:ukr_x_preferred":[
        "\u041c\u0456\u043d\u043a\u0430"
    ],
    "name:und_x_variant":[
        "Pos\u00eblok Minka"
    ],
    "wof:name":"Minka",
    "wof:placetype":"locality"
},
  "geometry": {"coordinates":[58.2708,54.9419],"type":"Point"}
}