{
  "type": "Feature",
  "properties": {
    "gn:admin1_code":"13",
    "gn:asciiname":"Minka",
    "gn:country_code":"RU",
    "gn:dem":335,
    "gn:feature_class":"P",
    "gn:feature_code":"PPL",
    "gn:name":"Minka",
    "gn:population":0,
    "gn:timezone":"Asia/Yekaterinburg",
    "iso:country":"RU",
    "name:eng_x_preferred":[
        "Minka"
    ],
    "name:nor_x_preferred":[
        "Minka"
    ],
    "name:rus_x_preferred":[
        "\u041c\u0438\u043d\u043a\u0430"
    ],
    "name:und_x_variant":[
        "\u041c\u0438\u043d\u043a\u0430",
        "Minka",
        "Pos\u00eblok Minka"
    ],
    "wof:name":"Minka",
    "wof:placetype":"locality"
},
  "geometry": {"coordinates":[58.2708,54.9419],"type":"Point"}
}