{
  "type": "Feature",
  "properties": {
    "gn:admin1_code":"52",
    "gn:asciiname":"Vysokogor'ye",
    "gn:country_code":"RU",
    "gn:dem":194,
    "gn:feature_class":"P",
    "gn:feature_code":"PPL",
    "gn:name":"Vysokogor\u2019ye",
    "gn:population":0,
    "gn:timezone":"Europe/Moscow",
    "iso:country":"RU",
    "name:und_x_variant":[
        "Ch\u00ebrtova",
        "Chertova Gora",
        "Vysokogor\u2019ye"
    ],
    "wof:name":"Vysokogor'ye",
    "wof:placetype":"locality"
},
  "geometry": {"coordinates":[34.69076,58.51114000000001],"type":"Point"}
}