{
  "type": "Feature",
  "properties": {
    "gn:admin1_code":"51.0",
    "gn:asciiname":"Bogorodskoye",
    "gn:country_code":"RU",
    "gn:dem":95,
    "gn:feature_class":"P",
    "gn:feature_code":"PPL",
    "gn:name":"Bogorodskoye",
    "gn:population":0,
    "gn:timezone":"Europe/Moscow",
    "iso:country":"RU",
    "name:eng_x_preferred":[
        "Bogorodskoye"
    ],
    "name:nor_x_preferred":[
        "Bogorodskoje"
    ],
    "name:rus_x_preferred":[
        "\u0411\u043e\u0433\u043e\u0440\u043e\u0434\u0441\u043a\u043e\u0435"
    ],
    "wof:name":"Bogorodskoye",
    "wof:placetype":"locality"
},
  "geometry": {"coordinates":[45.52186,56.78051],"type":"Point"}
}