{
  "type": "Feature",
  "properties": {
    "gn:admin1_code":"7",
    "gn:asciiname":"Vetlyanka",
    "gn:country_code":"RU",
    "gn:dem":0,
    "gn:feature_class":"P",
    "gn:feature_code":"PPL",
    "gn:name":"Vetlyanka",
    "gn:population":0,
    "gn:timezone":"Europe/Astrakhan",
    "iso:country":"RU",
    "name:che_x_preferred":[
        "\u0412\u0435\u0442\u043b\u044f\u043d\u043a\u0430"
    ],
    "name:eng_x_preferred":[
        "Vetlyanka"
    ],
    "name:nor_x_preferred":[
        "Vetljanka"
    ],
    "name:rus_x_preferred":[
        "\u0412\u0435\u0442\u043b\u044f\u043d\u043a\u0430"
    ],
    "name:tgk_x_preferred":[
        "\u0412\u0435\u0442\u043b\u044f\u043d\u043a\u0430"
    ],
    "wof:name":"Vetlyanka",
    "wof:placetype":"locality"
},
  "geometry": {"coordinates":[46.63222,47.635],"type":"Point"}
}