{
  "type": "Feature",
  "properties": {
    "gn:admin1_code":"80",
    "gn:asciiname":"Novyy Utchan",
    "gn:country_code":"RU",
    "gn:dem":124,
    "gn:feature_class":"P",
    "gn:feature_code":"PPL",
    "gn:name":"Novyy Utchan",
    "gn:population":0,
    "gn:timezone":"Europe/Samara",
    "iso:country":"RU",
    "name:rus_x_preferred":[
        "\u041d\u043e\u0432\u044b\u0439 \u0423\u0442\u0447\u0430\u043d"
    ],
    "wof:name":"Novyy Utchan",
    "wof:placetype":"locality"
},
  "geometry": {"coordinates":[52.38104000000001,56.16702],"type":"Point"}
}