{
  "type": "Feature",
  "properties": {
    "gn:admin1_code":"54",
    "gn:asciiname":"Mogil'no-Posel'skoye",
    "gn:country_code":"RU",
    "gn:dem":86,
    "gn:feature_class":"P",
    "gn:feature_code":"PPL",
    "gn:name":"Mogil\u2019no-Posel\u2019skoye",
    "gn:population":0,
    "gn:timezone":"Asia/Omsk",
    "iso:country":"RU",
    "name:rus_x_preferred":[
        "\u041c\u043e\u0433\u0438\u043b\u044c\u043d\u043e-\u041f\u043e\u0441\u0435\u043b\u044c\u0441\u043a\u043e\u0435"
    ],
    "name:und_x_variant":[
        "Mogil\u2019noye",
        "Mogil\u2019no-Posel\u2019skoye",
        "\u041c\u043e\u0433\u0438\u043b\u044c\u043d\u043e-\u041f\u043e\u0441\u0435\u043b\u044c\u0441\u043a\u043e\u0435"
    ],
    "wof:name":"Mogil'no-Posel'skoye",
    "wof:placetype":"locality"
},
  "geometry": {"coordinates":[74.45695000000001,55.92284],"type":"Point"}
}