{
  "type": "Feature",
  "properties": {
    "gn:admin1_code":"75",
    "gn:asciiname":"Vambaly",
    "gn:country_code":"RU",
    "gn:dem":145,
    "gn:feature_class":"P",
    "gn:feature_code":"PPL",
    "gn:name":"Vambaly",
    "gn:population":0,
    "gn:timezone":"Asia/Tomsk",
    "iso:country":"RU",
    "name:eng_x_preferred":[
        "Vambaly"
    ],
    "name:nor_x_preferred":[
        "Vambaly"
    ],
    "name:rus_x_preferred":[
        "\u0412\u0430\u043c\u0431\u0430\u043b\u044b"
    ],
    "name:und_x_variant":[
        "Vambala",
        "Vambaly",
        "\u0412\u0430\u043c\u0431\u0430\u043b\u044b"
    ],
    "wof:name":"Vambaly",
    "wof:placetype":"locality"
},
  "geometry": {"coordinates":[86.73480000000001,56.66262],"type":"Point"}
}