{
  "type": "Feature",
  "properties": {
    "gn:admin1_code":"77",
    "gn:asciiname":"Bol'shoye Kon'shino",
    "gn:country_code":"RU",
    "gn:dem":217,
    "gn:feature_class":"P",
    "gn:feature_code":"PPL",
    "gn:name":"Bol\u2019shoye Kon\u2019shino",
    "gn:population":0,
    "gn:timezone":"Europe/Moscow",
    "iso:country":"RU",
    "name:rus_x_preferred":[
        "\u0411\u043e\u043b\u044c\u0448\u043e\u0435 \u041a\u043e\u043d\u044c\u0448\u0438\u043d\u043e"
    ],
    "name:und_x_variant":[
        "Bol\u2019shoye Kon\u2019shino"
    ],
    "wof:name":"Bol'shoye Kon'shino",
    "wof:placetype":"locality"
},
  "geometry": {"coordinates":[33.74341,56.73174],"type":"Point"}
}