{
  "type": "Feature",
  "properties": {
    "gn:admin1_code":"23",
    "gn:asciiname":"Grivino",
    "gn:country_code":"RU",
    "gn:dem":23,
    "gn:feature_class":"P",
    "gn:feature_code":"PPL",
    "gn:name":"Grivino",
    "gn:population":0,
    "gn:timezone":"Europe/Kaliningrad",
    "iso:country":"RU",
    "name:rus_x_preferred":[
        "\u0413\u0440\u0438\u0432\u0438\u043d\u043e"
    ],
    "wof:name":"Grivino",
    "wof:placetype":"locality"
},
  "geometry": {"coordinates":[22.13333,54.82556],"type":"Point"}
}