{
  "type": "Feature",
  "properties": {
    "gn:admin1_code":"33",
    "gn:asciiname":"Mokino",
    "gn:country_code":"RU",
    "gn:dem":173,
    "gn:feature_class":"P",
    "gn:feature_code":"PPL",
    "gn:name":"Mokino",
    "gn:population":0,
    "gn:timezone":"Europe/Kirov",
    "iso:country":"RU",
    "name:eng_x_preferred":[
        "Mokino"
    ],
    "name:nor_x_preferred":[
        "Mokino"
    ],
    "name:rus_x_preferred":[
        "\u041c\u043e\u043a\u0438\u043d\u043e"
    ],
    "wof:name":"Mokino",
    "wof:placetype":"locality"
},
  "geometry": {"coordinates":[49.19,57.43825],"type":"Point"}
}