{
  "type": "Feature",
  "properties": {
    "gn:admin1_code":"88",
    "gn:asciiname":"Ivakino",
    "gn:country_code":"RU",
    "gn:dem":186,
    "gn:feature_class":"P",
    "gn:feature_code":"PPL",
    "gn:name":"Ivakino",
    "gn:population":0,
    "gn:timezone":"Europe/Moscow",
    "iso:country":"RU",
    "name:rus_x_preferred":[
        "\u0418\u0432\u0430\u043a\u0438\u043d\u043e"
    ],
    "wof:name":"Ivakino",
    "wof:placetype":"locality"
},
  "geometry": {"coordinates":[39.20336,57.19286999999999],"type":"Point"}
}