{
  "type": "Feature",
  "properties": {
    "gn:admin1_code":"54",
    "gn:asciiname":"Shchelkanovka",
    "gn:country_code":"RU",
    "gn:dem":115,
    "gn:feature_class":"P",
    "gn:feature_code":"PPL",
    "gn:name":"Shchelkanovka",
    "gn:population":0,
    "gn:timezone":"Asia/Omsk",
    "iso:country":"RU",
    "name:eng_x_preferred":[
        "Shchelkanovka"
    ],
    "name:nor_x_preferred":[
        "Sjtsjelkanovka"
    ],
    "name:rus_x_preferred":[
        "\u0429\u0435\u043b\u043a\u0430\u043d\u043e\u0432\u043a\u0430"
    ],
    "name:und_x_variant":[
        "Shelkanovskiy",
        "\u0429\u0435\u043b\u043a\u0430\u043d\u043e\u0432\u043a\u0430",
        "Shchelkanovka"
    ],
    "wof:name":"Shchelkanovka",
    "wof:placetype":"locality"
},
  "geometry": {"coordinates":[75.96889,56.98652],"type":"Point"}
}