{
  "type": "Feature",
  "properties": {
    "gn:admin1_code":"83",
    "gn:asciiname":"Gorlovka",
    "gn:country_code":"RU",
    "gn:dem":103,
    "gn:feature_class":"P",
    "gn:feature_code":"PPL",
    "gn:name":"Gorlovka",
    "gn:population":0,
    "gn:timezone":"Europe/Moscow",
    "iso:country":"RU",
    "name:rus_x_preferred":[
        "\u0413\u043e\u0440\u043b\u043e\u0432\u043a\u0430"
    ],
    "name:und_x_variant":[
        "\u0413\u043e\u0440\u043b\u043e\u0432\u043a\u0430"
    ],
    "wof:name":"Gorlovka",
    "wof:placetype":"locality"
},
  "geometry": {"coordinates":[42.1871,55.9082],"type":"Point"}
}