{
  "type": "Feature",
  "properties": {
    "gn:admin1_code":"33.0",
    "gn:asciiname":"Vaga",
    "gn:country_code":"RU",
    "gn:dem":167,
    "gn:feature_class":"P",
    "gn:feature_code":"PPL",
    "gn:name":"Vaga",
    "gn:population":0,
    "gn:timezone":"Europe/Kirov",
    "iso:country":"RU",
    "name:ceb_x_preferred":[
        "Vaga"
    ],
    "name:fra_x_preferred":[
        "Vaga"
    ],
    "name:hrv_x_preferred":[
        "Vaga"
    ],
    "name:lat_x_preferred":[
        "Vaga"
    ],
    "name:lit_x_preferred":[
        "Vaga"
    ],
    "name:nld_x_preferred":[
        "Vaga"
    ],
    "name:pol_x_preferred":[
        "Vaga"
    ],
    "name:por_x_preferred":[
        "Vaga"
    ],
    "name:rus_x_preferred":[
        "\u0412\u0430\u0433\u0430"
    ],
    "name:spa_x_preferred":[
        "Vaga"
    ],
    "name:srp_x_preferred":[
        "\u0412\u0430\u0433\u0430"
    ],
    "name:swe_x_preferred":[
        "Vaga"
    ],
    "name:ukr_x_preferred":[
        "\u0412\u0430\u0433\u0430"
    ],
    "wof:name":"Vaga",
    "wof:placetype":"locality"
},
  "geometry": {"coordinates":[50.095,59.06583000000001],"type":"Point"}
}