{
  "type": "Feature",
  "properties": {
    "gn:admin1_code":"33.0",
    "gn:asciiname":"Pitibayevo",
    "gn:country_code":"RU",
    "gn:dem":119,
    "gn:feature_class":"P",
    "gn:feature_code":"PPL",
    "gn:name":"Pitibayevo",
    "gn:population":0,
    "gn:timezone":"Europe/Kirov",
    "iso:country":"RU",
    "name:rus_x_preferred":[
        "\u041f\u0438\u0442\u0438\u0431\u0430\u0435\u0432\u043e"
    ],
    "name:und_x_variant":[
        "\u041f\u0438\u0442\u0438\u0431\u0430\u0435\u0432\u043e"
    ],
    "wof:name":"Pitibayevo",
    "wof:placetype":"locality"
},
  "geometry": {"coordinates":[48.47122,57.43143000000001],"type":"Point"}
}