{
  "type": "Feature",
  "properties": {
    "gn:admin1_code":"42",
    "gn:asciiname":"Sirokasska",
    "gn:country_code":"RU",
    "gn:dem":51,
    "gn:feature_class":"P",
    "gn:feature_code":"PPL",
    "gn:name":"Sirokasska",
    "gn:population":0,
    "gn:timezone":"Europe/Moscow",
    "iso:country":"RU",
    "name:fin_x_preferred":[
        "Sirokaski"
    ],
    "name:rus_x_preferred":[
        "\u0421\u0438\u0440\u043e\u043a\u0430\u0441\u0441\u043a\u0430"
    ],
    "name:und_x_variant":[
        "\u0421\u0438\u0440\u043e\u043a\u0430\u0441\u0441\u043a\u0430"
    ],
    "wof:name":"Sirokasska",
    "wof:placetype":"locality"
},
  "geometry": {"coordinates":[31.65288,59.86799],"type":"Point"}
}