{
  "type": "Feature",
  "properties": {
    "gn:admin1_code":"60.0",
    "gn:asciiname":"Blyanitsy",
    "gn:country_code":"RU",
    "gn:dem":57,
    "gn:feature_class":"P",
    "gn:feature_code":"PPL",
    "gn:name":"Blyanitsy",
    "gn:population":0,
    "gn:timezone":"Europe/Moscow",
    "iso:country":"RU",
    "name:rus_x_preferred":[
        "\u0411\u043b\u044f\u043d\u0438\u0446\u044b"
    ],
    "name:und_x_variant":[
        "\u0411\u043b\u044f\u043d\u0438\u0446\u044b"
    ],
    "wof:name":"Blyanitsy",
    "wof:placetype":"locality"
},
  "geometry": {"coordinates":[29.46699000000001,57.81469],"type":"Point"}
}