{
  "type": "Feature",
  "properties": {
    "gn:admin1_code":"60",
    "gn:asciiname":"Yevanovo",
    "gn:country_code":"RU",
    "gn:dem":53,
    "gn:feature_class":"P",
    "gn:feature_code":"PPL",
    "gn:name":"Yevanovo",
    "gn:population":0,
    "gn:timezone":"Europe/Moscow",
    "iso:country":"RU",
    "name:rus_x_preferred":[
        "\u0415\u0432\u0430\u043d\u043e\u0432\u043e"
    ],
    "wof:name":"Yevanovo",
    "wof:placetype":"locality"
},
  "geometry": {"coordinates":[28.45068,57.54319],"type":"Point"}
}