{
  "type": "Feature",
  "properties": {
    "gn:admin1_code":"23",
    "gn:asciiname":"Krasnoznamenskoye",
    "gn:country_code":"RU",
    "gn:dem":53,
    "gn:feature_class":"P",
    "gn:feature_code":"PPL",
    "gn:name":"Krasnoznamenskoye",
    "gn:population":0,
    "gn:timezone":"Europe/Kaliningrad",
    "iso:country":"RU",
    "name:rus_x_preferred":[
        "\u041a\u0440\u0430\u0441\u043d\u043e\u0437\u043d\u0430\u043c\u0435\u043d\u0441\u043a\u043e\u0435"
    ],
    "name:und_x_variant":[
        "Dollst\u00e4dt",
        "Krasnoznamenskoye"
    ],
    "wof:name":"Krasnoznamenskoye",
    "wof:placetype":"locality"
},
  "geometry": {"coordinates":[20.54095,54.48206999999999],"type":"Point"}
}