{
  "type": "Feature",
  "properties": {
    "gn:admin1_code":"62",
    "gn:asciiname":"Zhernovki",
    "gn:country_code":"RU",
    "gn:dem":189,
    "gn:feature_class":"P",
    "gn:feature_code":"PPL",
    "gn:name":"Zhernovki",
    "gn:population":0,
    "gn:timezone":"Europe/Moscow",
    "iso:country":"RU",
    "name:rus_x_preferred":[
        "\u0416\u0435\u0440\u043d\u043e\u0432\u043a\u0438"
    ],
    "wof:name":"Zhernovki",
    "wof:placetype":"locality"
},
  "geometry": {"coordinates":[39.28818,53.749],"type":"Point"}
}