{
  "type": "Feature",
  "properties": {
    "gn:admin1_code":"40",
    "gn:asciiname":"Pustuyeva",
    "gn:country_code":"RU",
    "gn:dem":130,
    "gn:feature_class":"P",
    "gn:feature_code":"PPL",
    "gn:name":"Pustuyeva",
    "gn:population":0,
    "gn:timezone":"Asia/Yekaterinburg",
    "iso:country":"RU",
    "name:rus_x_preferred":[
        "\u041f\u0443\u0441\u0442\u0443\u0435\u0432\u0430"
    ],
    "name:und_x_variant":[
        "\u041f\u0443\u0441\u0442\u0443\u0435\u0432\u0430"
    ],
    "wof:name":"Pustuyeva",
    "wof:placetype":"locality"
},
  "geometry": {"coordinates":[64.79179999999999,56.0269],"type":"Point"}
}