{
  "type": "Feature",
  "properties": {
    "gn:admin1_code":"90.0",
    "gn:asciiname":"Naumki",
    "gn:country_code":"RU",
    "gn:dem":115,
    "gn:feature_class":"P",
    "gn:feature_code":"PPL",
    "gn:name":"Naumki",
    "gn:population":0,
    "gn:timezone":"Asia/Yekaterinburg",
    "iso:country":"RU",
    "name:rus_x_preferred":[
        "\u041d\u0430\u0443\u043c\u043a\u0438"
    ],
    "wof:name":"Naumki",
    "wof:placetype":"locality"
},
  "geometry": {"coordinates":[54.80396,57.36169],"type":"Point"}
}