{
  "type": "Feature",
  "properties": {
    "gn:country":"RU",
    "gn:fcode":"PPL",
    "gn:population":13,
    "iso:country":"RU",
    "name:nor_x_preferred":[
        "Batlakhatli"
    ],
    "name:rus_x_preferred":[
        "\u0411\u0430\u0442\u043b\u0430\u0445\u0430\u0442\u043b\u0438"
    ],
    "qs:name":"Batlakhatli",
    "qs:photos_9r":0,
    "qs:photos_sr":0,
    "qs:pop_sr":"1",
    "wof:name":"Batlakhatli",
    "wof:placetype":"locality",
    "wof:population":13
},
  "geometry": {"coordinates":[46.05686,42.58482],"type":"Point"}
}