{
  "type": "Feature",
  "properties": {
    "gn:admin1_code":"88.0",
    "gn:asciiname":"Prechistoye",
    "gn:country_code":"RU",
    "gn:dem":114,
    "gn:feature_class":"P",
    "gn:feature_code":"PPL",
    "gn:name":"Prechistoye",
    "gn:population":0,
    "gn:timezone":"Europe/Moscow",
    "iso:country":"RU",
    "name:rus_x_preferred":[
        "\u041f\u0440\u0435\u0447\u0438\u0441\u0442\u043e\u0435"
    ],
    "name:und_x_variant":[
        "\u041f\u0440\u0435\u0447\u0438\u0441\u0442\u043e\u0435"
    ],
    "wof:name":"Prechistoye",
    "wof:placetype":"locality"
},
  "geometry": {"coordinates":[40.70574000000001,58.14307],"type":"Point"}
}