{
  "type": "Feature",
  "properties": {
    "gn:admin1_code":"77",
    "gn:asciiname":"Maloye Kozino",
    "gn:country_code":"RU",
    "gn:dem":229,
    "gn:feature_class":"P",
    "gn:feature_code":"PPL",
    "gn:name":"Maloye Kozino",
    "gn:population":0,
    "gn:timezone":"Europe/Moscow",
    "iso:country":"RU",
    "name:che_x_preferred":[
        "\u041c\u0430\u043b\u0438 \u041a\u043e\u0437\u0438\u043d\u043e"
    ],
    "name:ita_x_preferred":[
        "Maloe Kozino"
    ],
    "name:rus_x_preferred":[
        "\u041c\u0430\u043b\u043e\u0435 \u041a\u043e\u0437\u0438\u043d\u043e"
    ],
    "name:und_x_variant":[
        "\u041c\u0430\u043b\u043e\u0435 \u041a\u043e\u0437\u0438\u043d\u043e"
    ],
    "wof:name":"Maloye Kozino",
    "wof:placetype":"locality"
},
  "geometry": {"coordinates":[33.18333,56.25],"type":"Point"}
}