{
  "type": "Feature",
  "properties": {
    "gn:admin1_code":"41",
    "gn:asciiname":"Sosonki",
    "gn:country_code":"RU",
    "gn:dem":197,
    "gn:feature_class":"P",
    "gn:feature_code":"PPL",
    "gn:name":"Sosonki",
    "gn:population":0,
    "gn:timezone":"Europe/Moscow",
    "iso:country":"RU",
    "name:rus_x_preferred":[
        "\u0421\u043e\u0441\u043e\u043d\u043a\u0438"
    ],
    "wof:name":"Sosonki",
    "wof:placetype":"locality"
},
  "geometry": {"coordinates":[35.2914,51.8876],"type":"Point"}
}