{
  "type": "Feature",
  "properties": {
    "gn:admin1_code":"60",
    "gn:asciiname":"Baslaki",
    "gn:country_code":"RU",
    "gn:dem":56,
    "gn:feature_class":"P",
    "gn:feature_code":"PPL",
    "gn:name":"Baslaki",
    "gn:population":0,
    "gn:timezone":"Europe/Moscow",
    "iso:country":"RU",
    "name:rus_x_preferred":[
        "\u0411\u0430\u0441\u043b\u0430\u043a\u0438"
    ],
    "wof:name":"Baslaki",
    "wof:placetype":"locality"
},
  "geometry": {"coordinates":[28.13208,57.3987],"type":"Point"}
}