{
  "type": "Feature",
  "properties": {
    "gn:admin1_code":"77",
    "gn:asciiname":"Oshukovo",
    "gn:country_code":"RU",
    "gn:dem":165,
    "gn:feature_class":"P",
    "gn:feature_code":"PPL",
    "gn:name":"Oshukovo",
    "gn:population":0,
    "gn:timezone":"Europe/Moscow",
    "iso:country":"RU",
    "name:rus_x_preferred":[
        "\u041e\u0448\u0443\u043a\u043e\u0432\u043e"
    ],
    "name:und_x_variant":[
        "\u041e\u0448\u0443\u043a\u043e\u0432\u043e"
    ],
    "wof:name":"Oshukovo",
    "wof:placetype":"locality"
},
  "geometry": {"coordinates":[37.0026,58.1679],"type":"Point"}
}