{
  "type": "Feature",
  "properties": {
    "gn:admin1_code":"53",
    "gn:asciiname":"Lepokurovo",
    "gn:country_code":"RU",
    "gn:dem":111,
    "gn:feature_class":"P",
    "gn:feature_code":"PPL",
    "gn:name":"Lepokurovo",
    "gn:population":0,
    "gn:timezone":"Asia/Novosibirsk",
    "iso:country":"RU",
    "name:eng_x_preferred":[
        "Lepokurovo"
    ],
    "name:nor_x_preferred":[
        "Lepokurovo"
    ],
    "name:rus_x_preferred":[
        "\u041b\u0435\u043f\u043e\u043a\u0443\u0440\u043e\u0432\u043e"
    ],
    "name:und_x_variant":[
        "Lepokurova"
    ],
    "wof:name":"Lepokurovo",
    "wof:placetype":"locality"
},
  "geometry": {"coordinates":[78.22214,54.233],"type":"Point"}
}