{
  "type": "Feature",
  "properties": {
    "gn:admin1_code":"9.0",
    "gn:asciiname":"Kositsyno",
    "gn:country_code":"RU",
    "gn:dem":204,
    "gn:feature_class":"P",
    "gn:feature_code":"PPL",
    "gn:name":"Kositsyno",
    "gn:population":0,
    "gn:timezone":"Europe/Moscow",
    "iso:country":"RU",
    "name:rus_x_preferred":[
        "\u041a\u043e\u0441\u0438\u0446\u044b\u043d\u043e"
    ],
    "name:und_x_variant":[
        "Kositsino",
        "Kositsyno"
    ],
    "wof:name":"Kositsyno",
    "wof:placetype":"locality"
},
  "geometry": {"coordinates":[37.87919,50.69763],"type":"Point"}
}