{
  "type": "Feature",
  "properties": {
    "gn:admin1_code":"86.0",
    "gn:asciiname":"Dolgomakhovatka",
    "gn:country_code":"RU",
    "gn:dem":181,
    "gn:feature_class":"P",
    "gn:feature_code":"PPL",
    "gn:name":"Dolgomakhovatka",
    "gn:population":0,
    "gn:timezone":"Europe/Moscow",
    "iso:country":"RU",
    "name:rus_x_preferred":[
        "\u0414\u043e\u043b\u0433\u043e\u043c\u0430\u0445\u043e\u0432\u0430\u0442\u043a\u0430"
    ],
    "name:und_x_variant":[
        "\u0414\u043e\u043b\u0433\u043e\u043c\u0430\u0445\u043e\u0432\u0430\u0442\u043a\u0430"
    ],
    "wof:name":"Dolgomakhovatka",
    "wof:placetype":"locality"
},
  "geometry": {"coordinates":[38.5244,51.8862],"type":"Point"}
}