{
  "type": "Feature",
  "properties": {
    "gn:admin1_code":"53",
    "gn:asciiname":"Grivenskiy",
    "gn:country_code":"RU",
    "gn:dem":122,
    "gn:feature_class":"P",
    "gn:feature_code":"PPL",
    "gn:name":"Grivenskiy",
    "gn:population":0,
    "gn:timezone":"Asia/Novosibirsk",
    "iso:country":"RU",
    "name:eng_x_preferred":[
        "Grivenskiy"
    ],
    "name:nor_x_preferred":[
        "Grivenskij"
    ],
    "name:rus_x_preferred":[
        "\u0413\u0440\u0438\u0432\u0435\u043d\u0441\u043a\u0438\u0439"
    ],
    "name:und_x_variant":[
        "\u0413\u0440\u0438\u0432\u0435\u043d\u0441\u043a\u0438\u0439",
        "Grivenskiy"
    ],
    "wof:name":"Grivenskiy",
    "wof:placetype":"locality"
},
  "geometry": {"coordinates":[79.03203000000001,54.95477],"type":"Point"}
}