{
  "type": "Feature",
  "properties": {
    "gn:admin1_code":"73.0",
    "gn:asciiname":"Alkino",
    "gn:country_code":"RU",
    "gn:dem":172,
    "gn:feature_class":"P",
    "gn:feature_code":"PPL",
    "gn:name":"Alkino",
    "gn:population":0,
    "gn:timezone":"Europe/Moscow",
    "iso:country":"RU",
    "name:nor_x_preferred":[
        "Alkino"
    ],
    "name:rus_x_preferred":[
        "\u0410\u043b\u043a\u0438\u043d\u043e"
    ],
    "wof:name":"Alkino",
    "wof:placetype":"locality"
},
  "geometry": {"coordinates":[51.14574,55.80964],"type":"Point"}
}