{
  "type": "Feature",
  "properties": {
    "gn:admin1_code":"41",
    "gn:asciiname":"Rudka",
    "gn:country_code":"RU",
    "gn:dem":181,
    "gn:feature_class":"P",
    "gn:feature_code":"PPL",
    "gn:name":"Rudka",
    "gn:population":0,
    "gn:timezone":"Europe/Moscow",
    "iso:country":"RU",
    "name:bel_x_preferred":[
        "\u0420\u0443\u0434\u043a\u0430"
    ],
    "name:ceb_x_preferred":[
        "Rudka"
    ],
    "name:deu_x_preferred":[
        "Rudka"
    ],
    "name:fra_x_preferred":[
        "Rudka"
    ],
    "name:ita_x_preferred":[
        "Rudka"
    ],
    "name:lit_x_preferred":[
        "Rudka"
    ],
    "name:nld_x_preferred":[
        "Rudka"
    ],
    "name:pol_x_preferred":[
        "Rudka"
    ],
    "name:rus_x_preferred":[
        "\u0420\u0443\u0434\u043a\u0430"
    ],
    "name:swe_x_preferred":[
        "Rudka"
    ],
    "name:ukr_x_preferred":[
        "\u0420\u0443\u0434\u043a\u0430"
    ],
    "wof:name":"Rudka",
    "wof:placetype":"locality"
},
  "geometry": {"coordinates":[35.7265,52.0022],"type":"Point"}
}