{
  "type": "Feature",
  "properties": {
    "gn:admin1_code":"77.0",
    "gn:asciiname":"Cheremushnitsy",
    "gn:country_code":"RU",
    "gn:dem":294,
    "gn:feature_class":"P",
    "gn:feature_code":"PPL",
    "gn:name":"Cheremushnitsy",
    "gn:population":0,
    "gn:timezone":"Europe/Moscow",
    "iso:country":"RU",
    "name:rus_x_preferred":[
        "\u0427\u0435\u0440\u0435\u043c\u0443\u0448\u043d\u0438\u0446\u044b"
    ],
    "name:und_x_variant":[
        "\u0427\u0435\u0440\u0435\u043c\u0443\u0448\u043d\u0438\u0446\u044b"
    ],
    "wof:name":"Cheremushnitsy",
    "wof:placetype":"locality"
},
  "geometry": {"coordinates":[33.20357,56.47965],"type":"Point"}
}