{
  "type": "Feature",
  "properties": {
    "gn:admin1_code":"33",
    "gn:asciiname":"Glushonki",
    "gn:country_code":"RU",
    "gn:dem":158,
    "gn:feature_class":"P",
    "gn:feature_code":"PPL",
    "gn:name":"Glushonki",
    "gn:population":0,
    "gn:timezone":"Europe/Kirov",
    "iso:country":"RU",
    "name:rus_x_preferred":[
        "\u0413\u043b\u0443\u0448\u043e\u043d\u043a\u0438"
    ],
    "wof:name":"Glushonki",
    "wof:placetype":"locality"
},
  "geometry": {"coordinates":[49.44264,58.43048],"type":"Point"}
}