{
  "type": "Feature",
  "properties": {
    "gn:admin1_code":"52",
    "gn:asciiname":"Tashino",
    "gn:country_code":"RU",
    "gn:dem":48,
    "gn:feature_class":"P",
    "gn:feature_code":"PPL",
    "gn:name":"Tashino",
    "gn:population":0,
    "gn:timezone":"Europe/Moscow",
    "iso:country":"RU",
    "wof:name":"Tashino",
    "wof:placetype":"locality"
},
  "geometry": {"coordinates":[30.10459,58.66323000000001],"type":"Point"}
}