{
  "type": "Feature",
  "properties": {
    "gn:admin1_code":"05",
    "gn:asciiname":"Gashchenka",
    "gn:country_code":"RU",
    "gn:dem":150,
    "gn:feature_class":"P",
    "gn:feature_code":"PPL",
    "gn:name":"Gashchenka",
    "gn:population":0,
    "gn:timezone":"Asia/Yakutsk",
    "iso:country":"RU",
    "name:che_x_preferred":[
        "\u0413\u0430\u0449\u0435\u043d\u043a\u0430"
    ],
    "name:eng_x_preferred":[
        "Gashchenka"
    ],
    "name:rus_x_preferred":[
        "\u0413\u0430\u0448\u0438\u043d\u043e"
    ],
    "name:rus_x_variant":[
        "\u0413\u0430\u0449\u0435\u043d\u043a\u0430"
    ],
    "name:und_x_variant":[
        "Pashchenko",
        "Gashenko"
    ],
    "wof:name":"Gashchenka",
    "wof:placetype":"locality"
},
  "geometry": {"coordinates":[128.37493999999998,51.51034],"type":"Point"}
}