{
  "type": "Feature",
  "properties": {
    "gn:admin1_code":"13",
    "gn:asciiname":"Kuramshina",
    "gn:country_code":"RU",
    "gn:dem":261,
    "gn:feature_class":"P",
    "gn:feature_code":"PPL",
    "gn:name":"Kuramshina",
    "gn:population":0,
    "gn:timezone":"Asia/Yekaterinburg",
    "iso:country":"RU",
    "name:rus_x_preferred":[
        "\u041a\u0443\u0440\u0430\u043c\u0448\u0438\u043d\u0430"
    ],
    "wof:name":"Kuramshina",
    "wof:placetype":"locality"
},
  "geometry": {"coordinates":[60.8408,55.1641],"type":"Point"}
}