{
  "type": "Feature",
  "properties": {
    "gn:admin1_code":"9.0",
    "gn:asciiname":"Borisovka",
    "gn:country_code":"RU",
    "gn:dem":140,
    "gn:feature_class":"P",
    "gn:feature_code":"PPL",
    "gn:name":"Borisovka",
    "gn:population":14148,
    "gn:timezone":"Europe/Moscow",
    "iso:country":"RU",
    "name:eng_x_preferred":[
        "Borisovka"
    ],
    "name:lav_x_preferred":[
        "Borisovka"
    ],
    "name:nor_x_preferred":[
        "Borisovka"
    ],
    "name:rus_x_preferred":[
        "\u0411\u043e\u0440\u0438\u0441\u043e\u0432\u043a\u0430"
    ],
    "name:und_x_variant":[
        "Bohsouka"
    ],
    "wof:name":"Borisovka",
    "wof:placetype":"locality",
    "wof:population":14148
},
  "geometry": {"coordinates":[36.01549,50.60155],"type":"Point"}
}