{
  "type": "Feature",
  "properties": {
    "gn:admin1_code":"86",
    "gn:asciiname":"Stanovoy",
    "gn:country_code":"RU",
    "gn:dem":183,
    "gn:feature_class":"P",
    "gn:feature_code":"PPL",
    "gn:name":"Stanovoy",
    "gn:population":0,
    "gn:timezone":"Europe/Moscow",
    "iso:country":"RU",
    "name:rus_x_preferred":[
        "\u0421\u0442\u0430\u043d\u043e\u0432\u043e\u0439"
    ],
    "name:und_x_variant":[
        "\u0421\u0442\u0430\u043d\u043e\u0432\u043e\u0439"
    ],
    "wof:name":"Stanovoy",
    "wof:placetype":"locality"
},
  "geometry": {"coordinates":[39.85401,50.34057],"type":"Point"}
}