{
  "type": "Feature",
  "properties": {
    "gn:admin1_code":"57",
    "gn:asciiname":"Trakhaniotovo",
    "gn:country_code":"RU",
    "gn:dem":229,
    "gn:feature_class":"P",
    "gn:feature_code":"PPL",
    "gn:name":"Trakhaniotovo",
    "gn:population":0,
    "gn:timezone":"Europe/Moscow",
    "iso:country":"RU",
    "name:eng_x_preferred":[
        "Trakhaniotovo"
    ],
    "name:nor_x_preferred":[
        "Trakhaniotovo"
    ],
    "name:rus_x_preferred":[
        "\u0422\u0440\u0430\u0445\u0430\u043d\u0438\u043e\u0442\u043e\u0432\u043e"
    ],
    "name:und_x_variant":[
        "Trakhniorovo",
        "Trakhanistovo",
        "Trakhniotovo",
        "\u0422\u0440\u0430\u0445\u0430\u043d\u0438\u043e\u0442\u043e\u0432\u043e",
        "Trakhaniotovo"
    ],
    "wof:name":"Trakhaniotovo",
    "wof:placetype":"locality"
},
  "geometry": {"coordinates":[46.56471,53.24449],"type":"Point"}
}