{
  "type": "Feature",
  "properties": {
    "gn:admin1_code":"43",
    "gn:asciiname":"Sukhoy Semenek",
    "gn:cc2":"RU",
    "gn:country_code":"RU",
    "gn:dem":249,
    "gn:feature_class":"P",
    "gn:feature_code":"PPL",
    "gn:name":"Sukhoy Semen\u00ebk",
    "gn:population":0,
    "gn:timezone":"Europe/Moscow",
    "iso:country":"RU",
    "name:rus_x_preferred":[
        "\u0421\u0443\u0445\u043e\u0439 \u0421\u0435\u043c\u0435\u043d\u0451\u043a"
    ],
    "name:und_x_variant":[
        "Sukhoy Semenik",
        "Sukhiye Semenki",
        "Sukhoy Semen\u00ebk",
        "\u0421\u0443\u0445\u043e\u0439 \u0421\u0435\u043c\u0435\u043d\u0451\u043a"
    ],
    "wof:name":"Sukhoy Semenek",
    "wof:placetype":"locality"
},
  "geometry": {"coordinates":[37.91,52.72722],"type":"Point"}
}