{
  "type": "Feature",
  "properties": {
    "gn:admin1_code":"53.0",
    "gn:asciiname":"Pereselencheskiy",
    "gn:country_code":"RU",
    "gn:dem":105,
    "gn:feature_class":"P",
    "gn:feature_code":"PPL",
    "gn:name":"Pereselencheskiy",
    "gn:population":0,
    "gn:timezone":"Asia/Novosibirsk",
    "iso:country":"RU",
    "name:rus_x_preferred":[
        "\u041f\u0435\u0440\u0435\u0441\u0435\u043b\u0435\u043d\u0447\u0435\u0441\u043a\u0438\u0439"
    ],
    "wof:name":"Pereselencheskiy",
    "wof:placetype":"locality"
},
  "geometry": {"coordinates":[77.61294000000002,54.07901],"type":"Point"}
}