{
  "type": "Feature",
  "properties": {
    "gn:admin1_code":"56",
    "gn:asciiname":"Dedov",
    "gn:country_code":"RU",
    "gn:dem":240,
    "gn:feature_class":"P",
    "gn:feature_code":"PPL",
    "gn:name":"Dedov",
    "gn:population":0,
    "gn:timezone":"Europe/Moscow",
    "iso:country":"RU",
    "name:rus_x_preferred":[
        "\u0414\u0435\u0434\u043e\u0432"
    ],
    "name:und_x_variant":[
        "\u0414\u0435\u0434\u043e\u0432"
    ],
    "wof:name":"Dedov",
    "wof:placetype":"locality"
},
  "geometry": {"coordinates":[37.17361,53.25194000000001],"type":"Point"}
}