{
  "type": "Feature",
  "properties": {
    "gn:admin1_code":"60",
    "gn:asciiname":"Kudyayevo",
    "gn:country_code":"RU",
    "gn:dem":109,
    "gn:feature_class":"P",
    "gn:feature_code":"PPL",
    "gn:name":"Kudyayevo",
    "gn:population":0,
    "gn:timezone":"Europe/Moscow",
    "iso:country":"RU",
    "name:rus_x_preferred":[
        "\u041a\u0443\u0434\u044f\u0435\u0432\u043e"
    ],
    "name:und_x_variant":[
        "Kudyayeva",
        "Kudyayevo"
    ],
    "wof:name":"Kudyayevo",
    "wof:placetype":"locality"
},
  "geometry": {"coordinates":[29.37447,57.21638000000001],"type":"Point"}
}