{
  "type": "Feature",
  "properties": {
    "gn:country":"RU",
    "gn:fcode":"PPL",
    "gn:pop":15100,
    "iso:country":"RU",
    "name:ara_x_preferred":[
        "\u0628\u0648\u062a\u0634\u064a\u0628"
    ],
    "name:azb_x_preferred":[
        "\u067e\u0648\u0686\u0627\u067e"
    ],
    "name:bel_x_preferred":[
        "\u041f\u043e\u0447\u0430\u043f"
    ],
    "name:bul_x_preferred":[
        "\u041f\u043e\u0447\u0435\u043f"
    ],
    "name:cat_x_preferred":[
        "Potxep"
    ],
    "name:che_x_preferred":[
        "\u041f\u043e\u0447\u0435\u043f"
    ],
    "name:chi_x_preferred":[
        "\u6ce2\u5207\u666e"
    ],
    "name:cze_x_preferred":[
        "Po\u010dep"
    ],
    "name:dut_x_preferred":[
        "Potsjep"
    ],
    "name:eng_x_preferred":[
        "Pochep"
    ],
    "name:epo_x_preferred":[
        "Po\u0109ep"
    ],
    "name:fin_x_preferred":[
        "Pot\u0161ep"
    ],
    "name:fre_x_preferred":[
        "Potchep"
    ],
    "name:ger_x_preferred":[
        "Potschep"
    ],
    "name:hsb_x_preferred":[
        "Po\u010dep"
    ],
    "name:ita_x_preferred":[
        "Po\u010dep"
    ],
    "name:jpn_x_preferred":[
        "\u30dd\u30fc\u30c1\u30a7\u30d7"
    ],
    "name:kor_x_preferred":[
        "\ud3ec\uccb4\ud504"
    ],
    "name:lav_x_preferred":[
        "Po\u010depa"
    ],
    "name:nno_x_preferred":[
        "Potsjep"
    ],
    "name:nob_x_preferred":[
        "Potsjep"
    ],
    "name:nor_x_preferred":[
        "Potsjep"
    ],
    "name:per_x_preferred":[
        "\u067e\u0648\u0686\u067e"
    ],
    "name:pol_x_preferred":[
        "Poczep"
    ],
    "name:rus_x_preferred":[
        "\u041f\u043e\u0447\u0435\u043f"
    ],
    "name:slv_x_preferred":[
        "Po\u010dep"
    ],
    "name:spa_x_preferred":[
        "Pochep"
    ],
    "name:srp_x_preferred":[
        "\u041f\u043e\u0447\u0435\u043f"
    ],
    "name:swe_x_preferred":[
        "Potjep"
    ],
    "name:tat_x_preferred":[
        "\u041f\u043e\u0447\u0435\u043f"
    ],
    "name:tgk_x_preferred":[
        "\u041f\u043e\u0447\u0435\u043f"
    ],
    "name:tgl_x_preferred":[
        "Pochep"
    ],
    "name:ukr_x_preferred":[
        "\u041f\u043e\u0447\u0435\u043f"
    ],
    "name:vep_x_preferred":[
        "Po\u010dep"
    ],
    "name:war_x_preferred":[
        "Pochep"
    ],
    "name:xal_x_preferred":[
        "\u041f\u043e\u0447\u0435\u043f \u0431\u0430\u043b\u04bb\u0441\u043d"
    ],
    "qs:name":"Poch\u00ebp",
    "qs:photos_9r":0,
    "qs:photos_sr":0,
    "qs:pop_sr":"6",
    "wd:wordcount":166,
    "wof:name":"Poch\u00ebp",
    "wof:placetype":"locality",
    "wof:population":15100
},
  "geometry": {"coordinates":[33.4464,52.9336],"type":"Point"}
}