{
  "type": "Feature",
  "properties": {
    "gn:admin1_code":"80",
    "gn:asciiname":"Porshur",
    "gn:country_code":"RU",
    "gn:dem":79,
    "gn:feature_class":"P",
    "gn:feature_code":"PPL",
    "gn:name":"Porshur",
    "gn:population":0,
    "gn:timezone":"Europe/Samara",
    "iso:country":"RU",
    "name:rus_x_preferred":[
        "\u041f\u043e\u0440\u0448\u0443\u0440"
    ],
    "name:und_x_variant":[
        "\u041f\u043e\u0440\u0448\u0443\u0440"
    ],
    "wof:name":"Porshur",
    "wof:placetype":"locality"
},
  "geometry": {"coordinates":[51.70576,56.02513],"type":"Point"}
}