{
  "type": "Feature",
  "properties": {
    "gn:admin1_code":"77",
    "gn:asciiname":"Sverkuny",
    "gn:country_code":"RU",
    "gn:dem":207,
    "gn:feature_class":"P",
    "gn:feature_code":"PPL",
    "gn:name":"Sverkuny",
    "gn:population":0,
    "gn:timezone":"Europe/Moscow",
    "iso:country":"RU",
    "name:rus_x_preferred":[
        "\u0421\u0432\u0435\u0440\u043a\u0443\u043d\u044b"
    ],
    "wof:name":"Sverkuny",
    "wof:placetype":"locality"
},
  "geometry": {"coordinates":[32.8547,55.8047],"type":"Point"}
}