{
  "type": "Feature",
  "properties": {
    "gn:admin1_code":"75",
    "gn:asciiname":"Tolmachevo",
    "gn:country_code":"RU",
    "gn:dem":60,
    "gn:feature_class":"P",
    "gn:feature_code":"PPL",
    "gn:name":"Tolmach\u00ebvo",
    "gn:population":0,
    "gn:timezone":"Asia/Tomsk",
    "iso:country":"RU",
    "name:eng_x_preferred":[
        "Tolmach\u00ebvo"
    ],
    "name:nor_x_preferred":[
        "Tolmatsjevo"
    ],
    "name:rus_x_preferred":[
        "\u0422\u043e\u043b\u043c\u0430\u0447\u0435\u0432\u043e"
    ],
    "name:und_x_variant":[
        "Tolmach\u00ebvo"
    ],
    "wof:name":"Tolmachevo",
    "wof:placetype":"locality"
},
  "geometry": {"coordinates":[81.44024,58.70809000000001],"type":"Point"}
}