{
  "type": "Feature",
  "properties": {
    "gn:admin1_code":"60",
    "gn:asciiname":"Monino",
    "gn:country_code":"RU",
    "gn:dem":233,
    "gn:feature_class":"P",
    "gn:feature_code":"PPL",
    "gn:name":"Monino",
    "gn:population":0,
    "gn:timezone":"Europe/Moscow",
    "iso:country":"RU",
    "name:bel_x_preferred":[
        "\u041c\u043e\u043d\u0456\u043d\u0430"
    ],
    "name:ceb_x_preferred":[
        "Monino"
    ],
    "name:ces_x_preferred":[
        "Monino"
    ],
    "name:che_x_preferred":[
        "\u041c\u043e\u043d\u0438\u043d\u043e"
    ],
    "name:deu_x_preferred":[
        "Monino"
    ],
    "name:eng_x_preferred":[
        "Monino"
    ],
    "name:fra_x_preferred":[
        "Monino"
    ],
    "name:nor_x_preferred":[
        "Monino"
    ],
    "name:pol_x_preferred":[
        "Monino"
    ],
    "name:rus_x_preferred":[
        "\u041c\u043e\u043d\u0438\u043d\u043e"
    ],
    "name:ukr_x_preferred":[
        "\u041c\u043e\u043d\u0456\u043d\u043e"
    ],
    "wof:name":"Monino",
    "wof:placetype":"locality"
},
  "geometry": {"coordinates":[29.57241,56.62955],"type":"Point"}
}