{
  "type": "Feature",
  "properties": {
    "gn:admin1_code":"54",
    "gn:asciiname":"Krasnyy Tsvet",
    "gn:country_code":"RU",
    "gn:dem":118,
    "gn:feature_class":"P",
    "gn:feature_code":"PPL",
    "gn:name":"Krasnyy Tsvet",
    "gn:population":0,
    "gn:timezone":"Asia/Omsk",
    "iso:country":"RU",
    "name:rus_x_preferred":[
        "\u041a\u0440\u0430\u0441\u043d\u044b\u0439 \u0426\u0432\u0435\u0442"
    ],
    "name:und_x_variant":[
        "\u041a\u0440\u0430\u0441\u043d\u044b\u0439 \u0426\u0432\u0435\u0442"
    ],
    "wof:name":"Krasnyy Tsvet",
    "wof:placetype":"locality"
},
  "geometry": {"coordinates":[71.92,55.057],"type":"Point"}
}