{
  "type": "Feature",
  "properties": {
    "gn:admin1_code":"65",
    "gn:asciiname":"Gidroturbinnyy",
    "gn:country_code":"RU",
    "gn:dem":55,
    "gn:feature_class":"P",
    "gn:feature_code":"PPL",
    "gn:name":"Gidroturbinnyy",
    "gn:population":0,
    "gn:timezone":"Europe/Samara",
    "iso:country":"RU",
    "name:rus_x_preferred":[
        "\u0413\u0438\u0434\u0440\u043e\u0442\u0443\u0440\u0431\u0438\u043d\u043d\u044b\u0439"
    ],
    "wof:name":"Gidroturbinnyy",
    "wof:placetype":"locality"
},
  "geometry": {"coordinates":[48.5028,53.1887],"type":"Point"}
}