{
  "type": "Feature",
  "properties": {
    "gn:admin1_code":"41.0",
    "gn:asciiname":"Barkovka",
    "gn:country_code":"RU",
    "gn:dem":261,
    "gn:feature_class":"P",
    "gn:feature_code":"PPL",
    "gn:name":"Barkovka",
    "gn:population":0,
    "gn:timezone":"Europe/Moscow",
    "iso:country":"RU",
    "name:nor_x_preferred":[
        "Barkovka"
    ],
    "name:rus_x_preferred":[
        "\u0411\u0430\u0440\u043a\u043e\u0432\u043a\u0430"
    ],
    "wof:name":"Barkovka",
    "wof:placetype":"locality"
},
  "geometry": {"coordinates":[36.89011,51.69932],"type":"Point"}
}