{
  "type": "Feature",
  "properties": {
    "gn:admin1_code":"71",
    "gn:asciiname":"Kamen'",
    "gn:country_code":"RU",
    "gn:dem":184,
    "gn:feature_class":"P",
    "gn:feature_code":"PPL",
    "gn:name":"Kamen\u2019",
    "gn:population":0,
    "gn:timezone":"Asia/Yekaterinburg",
    "iso:country":"RU",
    "name:rus_x_preferred":[
        "\u041a\u0430\u043c\u0435\u043d\u044c"
    ],
    "name:und_x_variant":[
        "Kamen\u2019",
        "\u041a\u0430\u043c\u0435\u043d\u044c"
    ],
    "wof:name":"Kamen'",
    "wof:placetype":"locality"
},
  "geometry": {"coordinates":[60.06667,60.83333],"type":"Point"}
}