{
  "type": "Feature",
  "properties": {
    "gn:admin1_code":"4",
    "gn:asciiname":"Stolbovo",
    "gn:country_code":"RU",
    "gn:dem":152,
    "gn:feature_class":"P",
    "gn:feature_code":"PPL",
    "gn:name":"Stolbovo",
    "gn:population":0,
    "gn:timezone":"Asia/Barnaul",
    "iso:country":"RU",
    "name:eng_x_preferred":[
        "Stolbovo"
    ],
    "name:nor_x_preferred":[
        "Stolbovo"
    ],
    "name:rus_x_preferred":[
        "\u0421\u0442\u043e\u043b\u0431\u043e\u0432\u043e"
    ],
    "name:und_x_variant":[
        "Stolbovskoye",
        "Stolbovo"
    ],
    "wof:name":"Stolbovo",
    "wof:placetype":"locality"
},
  "geometry": {"coordinates":[81.4708,53.92],"type":"Point"}
}