{
  "type": "Feature",
  "properties": {
    "gn:admin1_code":"83",
    "gn:asciiname":"Ploski",
    "gn:country_code":"RU",
    "gn:dem":211,
    "gn:feature_class":"P",
    "gn:feature_code":"PPL",
    "gn:name":"Ploski",
    "gn:population":0,
    "gn:timezone":"Europe/Moscow",
    "iso:country":"RU",
    "name:rus_x_preferred":[
        "\u041f\u043b\u043e\u0441\u043a\u0438"
    ],
    "wof:name":"Ploski",
    "wof:placetype":"locality"
},
  "geometry": {"coordinates":[39.4425,56.4482],"type":"Point"}
}