{
  "type": "Feature",
  "properties": {
    "gn:admin1_code":"85",
    "gn:asciiname":"Vozgrikha",
    "gn:country_code":"RU",
    "gn:dem":137,
    "gn:feature_class":"P",
    "gn:feature_code":"PPL",
    "gn:name":"Vozgrikha",
    "gn:population":0,
    "gn:timezone":"Europe/Moscow",
    "iso:country":"RU",
    "name:rus_x_preferred":[
        "\u0412\u043e\u0437\u0433\u0440\u0438\u0445\u0430"
    ],
    "name:und_x_variant":[
        "Vozgrykha",
        "Vozgrikha",
        "\u0412\u043e\u0437\u0433\u0440\u0438\u0445\u0430"
    ],
    "wof:name":"Vozgrikha",
    "wof:placetype":"locality"
},
  "geometry": {"coordinates":[36.13736,58.69031],"type":"Point"}
}