{
  "type": "Feature",
  "properties": {
    "gn:admin1_code":"90.0",
    "gn:asciiname":"Yershi",
    "gn:country_code":"RU",
    "gn:dem":110,
    "gn:feature_class":"P",
    "gn:feature_code":"PPL",
    "gn:name":"Yershi",
    "gn:population":0,
    "gn:timezone":"Asia/Yekaterinburg",
    "iso:country":"RU",
    "name:rus_x_preferred":[
        "\u0415\u0440\u0448\u0438"
    ],
    "wof:name":"Yershi",
    "wof:placetype":"locality"
},
  "geometry": {"coordinates":[55.5267,58.592],"type":"Point"}
}