{
  "type": "Feature",
  "properties": {
    "gn:admin1_code":"56",
    "gn:asciiname":"Ledna",
    "gn:country_code":"RU",
    "gn:dem":208,
    "gn:feature_class":"P",
    "gn:feature_code":"PPL",
    "gn:name":"Ledna",
    "gn:population":0,
    "gn:timezone":"Europe/Moscow",
    "iso:country":"RU",
    "name:rus_x_preferred":[
        "\u041b\u0435\u0434\u043d\u0430"
    ],
    "name:und_x_variant":[
        "\u041b\u0435\u0434\u043d\u0430"
    ],
    "wof:name":"Ledna",
    "wof:placetype":"locality"
},
  "geometry": {"coordinates":[35.80593,52.96001999999999],"type":"Point"}
}