{
  "type": "Feature",
  "properties": {
    "gn:admin1_code":"93",
    "gn:asciiname":"Atsa",
    "gn:country_code":"RU",
    "gn:dem":835,
    "gn:feature_class":"P",
    "gn:feature_code":"PPL",
    "gn:name":"Atsa",
    "gn:population":0,
    "gn:timezone":"Asia/Chita",
    "iso:country":"RU",
    "name:nor_x_preferred":[
        "Atsa"
    ],
    "name:rus_x_preferred":[
        "\u0410\u0446\u0430"
    ],
    "wof:name":"Atsa",
    "wof:placetype":"locality"
},
  "geometry": {"coordinates":[109.55185,50.48597],"type":"Point"}
}