{
  "type": "Feature",
  "properties": {
    "gn:admin1_code":"55",
    "gn:asciiname":"Volostnovka",
    "gn:country_code":"RU",
    "gn:dem":113,
    "gn:feature_class":"P",
    "gn:feature_code":"PPL",
    "gn:name":"Volostnovka",
    "gn:population":0,
    "gn:timezone":"Asia/Yekaterinburg",
    "iso:country":"RU",
    "name:eng_x_preferred":[
        "Volostnovka"
    ],
    "name:nor_x_preferred":[
        "Volostnovka"
    ],
    "name:rus_x_preferred":[
        "\u0412\u043e\u043b\u043e\u0441\u0442\u043d\u043e\u0432\u043a\u0430"
    ],
    "name:und_x_variant":[
        "Kindelinskiy",
        "Volostnovskiy",
        "Volostnovka"
    ],
    "wof:name":"Volostnovka",
    "wof:placetype":"locality"
},
  "geometry": {"coordinates":[53.81475,51.79513],"type":"Point"}
}