{
  "type": "Feature",
  "properties": {
    "gn:admin1_code":"51.0",
    "gn:asciiname":"Maloye Orlovskoye",
    "gn:country_code":"RU",
    "gn:dem":100,
    "gn:feature_class":"P",
    "gn:feature_code":"PPL",
    "gn:name":"Maloye Orlovskoye",
    "gn:population":0,
    "gn:timezone":"Europe/Moscow",
    "iso:country":"RU",
    "name:rus_x_preferred":[
        "\u041c\u0430\u043b\u043e\u0435 \u041e\u0440\u043b\u043e\u0432\u0441\u043a\u043e\u0435"
    ],
    "name:und_x_variant":[
        "Orlovskiy",
        "Maloye Orlovskoye"
    ],
    "wof:name":"Maloye Orlovskoye",
    "wof:placetype":"locality"
},
  "geometry": {"coordinates":[44.65801,56.43286],"type":"Point"}
}