{
  "type": "Feature",
  "properties": {
    "gn:admin1_code":"63",
    "gn:asciiname":"Tyube",
    "gn:country_code":"RU",
    "gn:dem":133,
    "gn:feature_class":"P",
    "gn:feature_code":"PPL",
    "gn:name":"Tyube",
    "gn:population":0,
    "gn:timezone":"Asia/Yakutsk",
    "iso:country":"RU",
    "name:eng_x_preferred":[
        "Tyube"
    ],
    "name:nor_x_preferred":[
        "Tjube"
    ],
    "name:rus_x_preferred":[
        "\u0422\u044e\u0431\u0435"
    ],
    "wof:name":"Tyube",
    "wof:placetype":"locality"
},
  "geometry": {"coordinates":[120.17456,60.28825],"type":"Point"}
}