{
  "type": "Feature",
  "properties": {
    "gn:admin1_code":"59",
    "gn:asciiname":"Verkhneye Akhobe",
    "gn:cc2":"RU",
    "gn:country_code":"RU",
    "gn:dem":175,
    "gn:feature_class":"P",
    "gn:feature_code":"PPL",
    "gn:name":"Verkhneye Akhobe",
    "gn:population":0,
    "gn:timezone":"Asia/Vladivostok",
    "iso:country":"RU",
    "name:und_x_variant":[
        "Verkhneye Agobe",
        "Verkhneye Akhobe"
    ],
    "wof:name":"Verkhneye Akhobe",
    "wof:placetype":"locality"
},
  "geometry": {"coordinates":[135.81666999999999,44.56667],"type":"Point"}
}