{
  "type": "Feature",
  "properties": {
    "gn:admin1_code":"59",
    "gn:asciiname":"Ekipazhnyy",
    "gn:country_code":"RU",
    "gn:dem":24,
    "gn:feature_class":"P",
    "gn:feature_code":"PPL",
    "gn:name":"Ekipazhnyy",
    "gn:population":0,
    "gn:timezone":"Asia/Vladivostok",
    "iso:country":"RU",
    "name:eng_x_preferred":[
        "Ekipazhnyy"
    ],
    "name:nor_x_preferred":[
        "Ekipazjnyj"
    ],
    "name:rus_x_preferred":[
        "\u042d\u043a\u0438\u043f\u0430\u0436\u043d\u044b\u0439"
    ],
    "name:und_x_variant":[
        "Ekipaznnyy",
        "Ekypazhnyy"
    ],
    "wof:name":"Ekipazhnyy",
    "wof:placetype":"locality"
},
  "geometry": {"coordinates":[131.86587,43.01151],"type":"Point"}
}