{
  "type": "Feature",
  "properties": {
    "gn:admin1_code":"60",
    "gn:asciiname":"Sazonovo",
    "gn:cc2":"RU",
    "gn:country_code":"RU",
    "gn:dem":163,
    "gn:feature_class":"P",
    "gn:feature_code":"PPL",
    "gn:name":"Sazonovo",
    "gn:population":0,
    "gn:timezone":"Europe/Moscow",
    "iso:country":"RU",
    "name:rus_x_preferred":[
        "\u0421\u0430\u0437\u043e\u043d\u043e\u0432\u043e"
    ],
    "name:und_x_variant":[
        "Sazonova",
        "Sazonovo",
        "\u0421\u0430\u0437\u043e\u043d\u043e\u0432\u043e"
    ],
    "wof:name":"Sazonovo",
    "wof:placetype":"locality"
},
  "geometry": {"coordinates":[30.93333,56.13333000000001],"type":"Point"}
}