{
  "type": "Feature",
  "properties": {
    "gn:admin1_code":"85.0",
    "gn:asciiname":"Yermolinskaya",
    "gn:country_code":"RU",
    "gn:dem":134,
    "gn:feature_class":"P",
    "gn:feature_code":"PPL",
    "gn:name":"Yermolinskaya",
    "gn:population":0,
    "gn:timezone":"Europe/Moscow",
    "iso:country":"RU",
    "name:rus_x_preferred":[
        "\u0415\u0440\u043c\u043e\u043b\u0438\u043d\u0441\u043a\u0430\u044f"
    ],
    "wof:name":"Yermolinskaya",
    "wof:placetype":"locality"
},
  "geometry": {"coordinates":[39.3148,59.9992],"type":"Point"}
}