{
  "type": "Feature",
  "properties": {
    "gn:admin1_code":"6.0",
    "gn:asciiname":"Timonino",
    "gn:country_code":"RU",
    "gn:dem":80,
    "gn:feature_class":"P",
    "gn:feature_code":"PPL",
    "gn:name":"Timonino",
    "gn:population":0,
    "gn:timezone":"Europe/Moscow",
    "iso:country":"RU",
    "name:rus_x_preferred":[
        "\u0422\u0438\u043c\u043e\u043d\u0438\u043d\u043e"
    ],
    "wof:name":"Timonino",
    "wof:placetype":"locality"
},
  "geometry": {"coordinates":[41.9725,61.5162],"type":"Point"}
}