{
  "type": "Feature",
  "properties": {
    "gn:admin1_code":"85",
    "gn:asciiname":"Gan'ki",
    "gn:country_code":"RU",
    "gn:dem":125,
    "gn:feature_class":"P",
    "gn:feature_code":"PPL",
    "gn:name":"Gan\u2019ki",
    "gn:population":0,
    "gn:timezone":"Europe/Moscow",
    "iso:country":"RU",
    "name:rus_x_preferred":[
        "\u0413\u0430\u043d\u044c\u043a\u0438"
    ],
    "name:und_x_variant":[
        "Gan\u2019ki",
        "\u0413\u0430\u043d\u044c\u043a\u0438"
    ],
    "wof:name":"Gan'ki",
    "wof:placetype":"locality"
},
  "geometry": {"coordinates":[36.4718,58.8327],"type":"Point"}
}