{
  "type": "Feature",
  "properties": {
    "gn:admin1_code":"60",
    "gn:asciiname":"Zagoski",
    "gn:country_code":"RU",
    "gn:dem":98,
    "gn:feature_class":"P",
    "gn:feature_code":"PPL",
    "gn:name":"Zagoski",
    "gn:population":10,
    "gn:timezone":"Europe/Moscow",
    "iso:country":"RU",
    "name:rus_x_preferred":[
        "\u0417\u0430\u0433\u043e\u0441\u043a\u0438"
    ],
    "wof:name":"Zagoski",
    "wof:placetype":"locality",
    "wof:population":10
},
  "geometry": {"coordinates":[28.99614,56.98787],"type":"Point"}
}