{
  "type": "Feature",
  "properties": {
    "gn:admin1_code":"72",
    "gn:asciiname":"Prokudskiye Mosty",
    "gn:country_code":"RU",
    "gn:dem":109,
    "gn:feature_class":"P",
    "gn:feature_code":"PPL",
    "gn:name":"Prokudskiye Mosty",
    "gn:population":0,
    "gn:timezone":"Europe/Moscow",
    "iso:country":"RU",
    "name:und_x_variant":[
        "Prokudskiy",
        "Prokudskiye Mosty"
    ],
    "wof:name":"Prokudskiye Mosty",
    "wof:placetype":"locality"
},
  "geometry": {"coordinates":[41.83925,53.18064],"type":"Point"}
}