{
  "type": "Feature",
  "properties": {
    "gn:admin1_code":"69.0",
    "gn:asciiname":"Andronovo",
    "gn:country_code":"RU",
    "gn:dem":216,
    "gn:feature_class":"P",
    "gn:feature_code":"PPL",
    "gn:name":"Andronovo",
    "gn:population":0,
    "gn:timezone":"Europe/Moscow",
    "iso:country":"RU",
    "name:nor_x_preferred":[
        "Andronovo"
    ],
    "name:rus_x_preferred":[
        "\u0410\u043d\u0434\u0440\u043e\u043d\u043e\u0432\u043e"
    ],
    "wof:name":"Andronovo",
    "wof:placetype":"locality"
},
  "geometry": {"coordinates":[32.46228,55.22472],"type":"Point"}
}