{
  "type": "Feature",
  "properties": {
    "gn:admin1_code":"60",
    "gn:asciiname":"Bochkino",
    "gn:country_code":"RU",
    "gn:dem":78,
    "gn:feature_class":"P",
    "gn:feature_code":"PPL",
    "gn:name":"Bochkino",
    "gn:population":0,
    "gn:timezone":"Europe/Moscow",
    "iso:country":"RU",
    "name:rus_x_preferred":[
        "\u0411\u043e\u0447\u043a\u0438\u043d\u043e"
    ],
    "wof:name":"Bochkino",
    "wof:placetype":"locality"
},
  "geometry": {"coordinates":[28.86657,57.5625],"type":"Point"}
}