{
  "type": "Feature",
  "properties": {
    "gn:admin1_code":"53",
    "gn:asciiname":"Kamyshinka",
    "gn:country_code":"RU",
    "gn:dem":130,
    "gn:feature_class":"P",
    "gn:feature_code":"PPL",
    "gn:name":"Kamyshinka",
    "gn:population":0,
    "gn:timezone":"Asia/Novosibirsk",
    "iso:country":"RU",
    "name:eng_x_preferred":[
        "Kamyshinka"
    ],
    "name:nor_x_preferred":[
        "Kamysjinka"
    ],
    "name:rus_x_preferred":[
        "\u041a\u0430\u043c\u044b\u0448\u0438\u043d\u043a\u0430"
    ],
    "name:und_x_variant":[
        "Kamyshenka"
    ],
    "wof:name":"Kamyshinka",
    "wof:placetype":"locality"
},
  "geometry": {"coordinates":[82.3411,53.6426],"type":"Point"}
}