{
  "type": "Feature",
  "properties": {
    "gn:admin1_code":"42",
    "gn:asciiname":"Tammisuo",
    "gn:country_code":"RU",
    "gn:dem":7,
    "gn:feature_class":"P",
    "gn:feature_code":"PPL",
    "gn:name":"Tammisuo",
    "gn:population":0,
    "gn:timezone":"Europe/Moscow",
    "iso:country":"RU",
    "name:und_x_variant":[
        "Tammisuyu",
        "Tammisuo"
    ],
    "wof:name":"Tammisuo",
    "wof:placetype":"locality"
},
  "geometry": {"coordinates":[28.80791,60.73333],"type":"Point"}
}