{
  "type": "Feature",
  "properties": {
    "gn:admin1_code":"60",
    "gn:asciiname":"Terekhi",
    "gn:country_code":"RU",
    "gn:dem":59,
    "gn:feature_class":"P",
    "gn:feature_code":"PPL",
    "gn:name":"Ter\u00ebkhi",
    "gn:population":0,
    "gn:timezone":"Europe/Moscow",
    "iso:country":"RU",
    "name:rus_x_preferred":[
        "\u0422\u0435\u0440\u0451\u0445\u0438"
    ],
    "name:und_x_variant":[
        "Ter\u00ebkhi"
    ],
    "wof:name":"Terekhi",
    "wof:placetype":"locality"
},
  "geometry": {"coordinates":[28.27829,57.25066999999999],"type":"Point"}
}