{
  "type": "Feature",
  "properties": {
    "gn:admin1_code":"67",
    "gn:asciiname":"Staraya Lopatka",
    "gn:country_code":"RU",
    "gn:dem":197,
    "gn:feature_class":"P",
    "gn:feature_code":"PPL",
    "gn:name":"Staraya Lopatka",
    "gn:population":0,
    "gn:timezone":"Europe/Saratov",
    "iso:country":"RU",
    "name:rus_x_preferred":[
        "\u0421\u0442\u0430\u0440\u0430\u044f \u041b\u043e\u043f\u0430\u0442\u043a\u0430"
    ],
    "name:und_x_variant":[
        "\u0421\u0442\u0430\u0440\u0430\u044f \u041b\u043e\u043f\u0430\u0442\u043a\u0430"
    ],
    "wof:name":"Staraya Lopatka",
    "wof:placetype":"locality"
},
  "geometry": {"coordinates":[45.50782,52.37793],"type":"Point"}
}