{
  "type": "Feature",
  "properties": {
    "gn:admin1_code":"85",
    "gn:asciiname":"Sorka",
    "gn:cc2":"RU",
    "gn:country_code":"RU",
    "gn:dem":151,
    "gn:feature_class":"P",
    "gn:feature_code":"PPL",
    "gn:name":"Sorka",
    "gn:population":0,
    "gn:timezone":"Europe/Moscow",
    "iso:country":"RU",
    "name:eng_x_preferred":[
        "Sorka"
    ],
    "name:nor_x_preferred":[
        "Sorka"
    ],
    "name:rus_x_preferred":[
        "\u0421\u043e\u0440\u043a\u0430"
    ],
    "name:und_x_variant":[
        "Serka",
        "Sorki",
        "\u0421\u043e\u0440\u043a\u0430",
        "Sorka"
    ],
    "wof:name":"Sorka",
    "wof:placetype":"locality"
},
  "geometry": {"coordinates":[36.06667,59.65],"type":"Point"}
}