{
  "type": "Feature",
  "properties": {
    "gn:admin1_code":"47.0",
    "gn:asciiname":"Stolbovo",
    "gn:country_code":"RU",
    "gn:dem":175,
    "gn:feature_class":"P",
    "gn:feature_code":"PPL",
    "gn:name":"Stolbovo",
    "gn:population":0,
    "gn:timezone":"Europe/Moscow",
    "iso:country":"RU",
    "name:rus_x_preferred":[
        "\u0421\u0442\u043e\u043b\u0431\u043e\u0432\u043e"
    ],
    "wof:name":"Stolbovo",
    "wof:placetype":"locality"
},
  "geometry": {"coordinates":[37.47,55.56],"type":"Point"}
}