{
  "type": "Feature",
  "properties": {
    "gn:admin1_code":"77",
    "gn:asciiname":"Prokazovo",
    "gn:country_code":"RU",
    "gn:dem":165,
    "gn:feature_class":"P",
    "gn:feature_code":"PPL",
    "gn:name":"Prokazovo",
    "gn:population":0,
    "gn:timezone":"Europe/Moscow",
    "iso:country":"RU",
    "name:rus_x_preferred":[
        "\u041f\u0440\u043e\u043a\u0430\u0437\u043e\u0432\u043e"
    ],
    "wof:name":"Prokazovo",
    "wof:placetype":"locality"
},
  "geometry": {"coordinates":[34.22519,58.07735],"type":"Point"}
}