{
  "type": "Feature",
  "properties": {
    "gn:admin1_code":"38.0",
    "gn:asciiname":"Kanevskiy",
    "gn:country_code":"RU",
    "gn:dem":364,
    "gn:feature_class":"P",
    "gn:feature_code":"PPL",
    "gn:name":"Kanevskiy",
    "gn:population":0,
    "gn:timezone":"Europe/Moscow",
    "iso:country":"RU",
    "name:rus_x_preferred":[
        "\u041a\u0430\u043d\u0435\u0432\u0441\u043a\u0438\u0439"
    ],
    "name:und_x_variant":[
        "Konevskiy",
        "Kanevskiy",
        "\u041a\u0430\u043d\u0435\u0432\u0441\u043a\u0438\u0439"
    ],
    "wof:name":"Kanevskiy",
    "wof:placetype":"locality"
},
  "geometry": {"coordinates":[41.4362,44.5644],"type":"Point"}
}