{
  "type": "Feature",
  "properties": {
    "gn:admin1_code":"77",
    "gn:asciiname":"Churilkovo",
    "gn:country_code":"RU",
    "gn:dem":141,
    "gn:feature_class":"P",
    "gn:feature_code":"PPL",
    "gn:name":"Churilkovo",
    "gn:population":0,
    "gn:timezone":"Europe/Moscow",
    "iso:country":"RU",
    "name:rus_x_preferred":[
        "\u0427\u0443\u0440\u0438\u043b\u043a\u043e\u0432\u043e"
    ],
    "wof:name":"Churilkovo",
    "wof:placetype":"locality"
},
  "geometry": {"coordinates":[36.788,57.7779],"type":"Point"}
}