{
  "type": "Feature",
  "properties": {
    "gn:admin1_code":"70",
    "gn:asciiname":"Inozemtsevo",
    "gn:cc2":"RU",
    "gn:country_code":"RU",
    "gn:dem":469,
    "gn:feature_class":"P",
    "gn:feature_code":"PPL",
    "gn:name":"Inozemtsevo",
    "gn:population":0,
    "gn:timezone":"Europe/Moscow",
    "iso:country":"RU",
    "name:ceb_x_preferred":[
        "Inozemtsevo"
    ],
    "name:che_x_preferred":[
        "\u0418\u043d\u043e\u0437\u0435\u043c\u0446\u0435\u0432\u043e"
    ],
    "name:deu_x_preferred":[
        "Inosemzewo"
    ],
    "name:hye_x_preferred":[
        "\u053b\u0576\u0578\u0566\u0565\u0574\u0581\u0587\u0578"
    ],
    "name:pol_x_preferred":[
        "Inoziemcewo"
    ],
    "name:rus_x_preferred":[
        "\u0418\u043d\u043e\u0437\u0435\u043c\u0446\u0435\u0432\u043e"
    ],
    "name:und_x_variant":[
        "Kapel\u2019nitsa",
        "Inozemtsevo",
        "\u0418\u043d\u043e\u0437\u0435\u043c\u0446\u0435\u0432\u043e"
    ],
    "wof:name":"Inozemtsevo",
    "wof:placetype":"locality"
},
  "geometry": {"coordinates":[43.13528,44.08389],"type":"Point"}
}