{
  "type": "Feature",
  "properties": {
    "gn:admin1_code":"90.0",
    "gn:asciiname":"Fedotova",
    "gn:country_code":"RU",
    "gn:dem":152,
    "gn:feature_class":"P",
    "gn:feature_code":"PPL",
    "gn:name":"Fedotova",
    "gn:population":0,
    "gn:timezone":"Asia/Yekaterinburg",
    "iso:country":"RU",
    "name:che_x_preferred":[
        "\u0424\u0435\u0434\u043e\u0442\u043e\u0432\u0430"
    ],
    "name:koi_x_preferred":[
        "\u041f\u0435\u0434\u04e7\u0442\u043e\u0432\u0447\u0438"
    ],
    "name:rus_x_preferred":[
        "\u0424\u0435\u0434\u043e\u0442\u043e\u0432\u0430"
    ],
    "wof:name":"Fedotova",
    "wof:placetype":"locality"
},
  "geometry": {"coordinates":[54.7364,59.1538],"type":"Point"}
}