{
  "type": "Feature",
  "properties": {
    "gn:admin1_code":"73.0",
    "gn:asciiname":"Chumachka",
    "gn:country_code":"RU",
    "gn:dem":111,
    "gn:feature_class":"P",
    "gn:feature_code":"PPL",
    "gn:name":"Chumachka",
    "gn:population":0,
    "gn:timezone":"Europe/Moscow",
    "iso:country":"RU",
    "name:rus_x_preferred":[
        "\u0427\u0443\u043c\u0430\u0447\u043a\u0430"
    ],
    "name:und_x_variant":[
        "Chumanka",
        "Chumachka"
    ],
    "wof:name":"Chumachka",
    "wof:placetype":"locality"
},
  "geometry": {"coordinates":[51.73183,54.79874],"type":"Point"}
}