{
  "type": "Feature",
  "properties": {
    "gn:admin1_code":"29",
    "gn:asciiname":"Ust'-Uzas",
    "gn:country_code":"RU",
    "gn:dem":512,
    "gn:feature_class":"P",
    "gn:feature_code":"PPL",
    "gn:name":"Ust\u2019-Uzas",
    "gn:population":0,
    "gn:timezone":"Asia/Novokuznetsk",
    "iso:country":"RU",
    "name:eng_x_preferred":[
        "Ust'-Uzas"
    ],
    "name:nor_x_preferred":[
        "Ust-Uzas"
    ],
    "name:rus_x_preferred":[
        "\u0423\u0441\u0442\u044c-\u0423\u0437\u0430\u0441"
    ],
    "name:und_x_variant":[
        "Ust\u2019-Uzas"
    ],
    "wof:name":"Ust'-Uzas",
    "wof:placetype":"locality"
},
  "geometry": {"coordinates":[88.74755999999999,52.56243000000001],"type":"Point"}
}