{
  "type": "Feature",
  "properties": {
    "gn:admin1_code":"21.0",
    "gn:asciiname":"Bol'shaya Molyabukha",
    "gn:country_code":"RU",
    "gn:dem":109,
    "gn:feature_class":"P",
    "gn:feature_code":"PPL",
    "gn:name":"Bol\u2019shaya Molyabukha",
    "gn:population":0,
    "gn:timezone":"Europe/Moscow",
    "iso:country":"RU",
    "name:und_x_variant":[
        "Molyabukha-Bol\u2019shaya",
        "Bol\u2019shaya Molyabukha"
    ],
    "wof:name":"Bol'shaya Molyabukha",
    "wof:placetype":"locality"
},
  "geometry": {"coordinates":[42.45873,56.8644],"type":"Point"}
}