{
  "type": "Feature",
  "properties": {
    "gn:admin1_code":"53",
    "gn:asciiname":"Nochka",
    "gn:country_code":"RU",
    "gn:dem":105,
    "gn:feature_class":"P",
    "gn:feature_code":"PPL",
    "gn:name":"Nochka",
    "gn:population":0,
    "gn:timezone":"Asia/Novosibirsk",
    "iso:country":"RU",
    "name:eng_x_preferred":[
        "Nochka"
    ],
    "name:nor_x_preferred":[
        "Notsjka"
    ],
    "name:rus_x_preferred":[
        "\u041d\u043e\u0447\u043a\u0430"
    ],
    "name:und_x_variant":[
        "Kochka"
    ],
    "wof:name":"Nochka",
    "wof:placetype":"locality"
},
  "geometry": {"coordinates":[76.97593000000001,55.81509000000001],"type":"Point"}
}