{
  "type": "Feature",
  "properties": {
    "gn:admin1_code":"52",
    "gn:asciiname":"Maloye Lyapino",
    "gn:country_code":"RU",
    "gn:dem":30,
    "gn:feature_class":"P",
    "gn:feature_code":"PPL",
    "gn:name":"Maloye Lyapino",
    "gn:population":0,
    "gn:timezone":"Europe/Moscow",
    "iso:country":"RU",
    "name:rus_x_preferred":[
        "\u041c\u0430\u043b\u043e\u0435 \u041b\u044f\u043f\u0438\u043d\u043e"
    ],
    "name:und_x_variant":[
        "\u041c\u0430\u043b\u043e\u0435 \u041b\u044f\u043f\u0438\u043d\u043e"
    ],
    "wof:name":"Maloye Lyapino",
    "wof:placetype":"locality"
},
  "geometry": {"coordinates":[31.11667000000001,58.51667],"type":"Point"}
}