{
  "type": "Feature",
  "properties": {
    "gn:gn_country":"RU",
    "gn:gn_fcode":"PPL",
    "gn:gn_pop":5647,
    "gn:population":5647,
    "iso:country":"RU",
    "name:arm_x_preferred":[
        "\u0548\u0582\u057d\u057f-\u0549\u0561\u0580\u056b\u0577\u057d\u056f\u0561\u0575\u0561 \u054a\u0580\u056b\u057d\u057f\u0561\u0576"
    ],
    "name:che_x_preferred":[
        "\u0423\u0441\u0442\u044c-\u0427\u0430\u0440\u044b\u0448\u0441\u043a\u0438 \u041f\u0440\u0438\u0441\u0442\u0430\u043d\u044c"
    ],
    "name:dut_x_preferred":[
        "Ust-Charyshskaya Pristan"
    ],
    "name:eng_x_preferred":[
        "Ust'-Charyshskaya Pristan'"
    ],
    "name:fre_x_preferred":[
        "Oust-Tcharychka\u00efa Pristan"
    ],
    "name:ger_x_preferred":[
        "Ust-Tscharyschskaja Pristan"
    ],
    "name:nor_x_preferred":[
        "Ust-Tsjarysjskaja Pristan"
    ],
    "name:rus_x_preferred":[
        "\u0423\u0441\u0442\u044c-\u0427\u0430\u0440\u044b\u0448\u0441\u043a\u0430\u044f \u041f\u0440\u0438\u0441\u0442\u0430\u043d\u044c"
    ],
    "name:unk_x_variant":[
        "Ust\u2019-Charysh"
    ],
    "qs_pg:aaroncc":"RU",
    "qs_pg:gn_country":"RU",
    "qs_pg:gn_fcode":"PPL",
    "qs_pg:gn_pop":5647,
    "qs_pg:name":"Ust'-Charyshskaya Pristan'",
    "qs_pg:name_adm0":"Russia",
    "qs_pg:name_adm1":"Altai Krai",
    "qs_pg:photos_9r":0,
    "qs_pg:photos_sr":0,
    "qs_pg:pop_sr":5,
    "qs_pg:qs_pg_placetype":"locality",
    "qs_pg:qs_pg_placetype_gp":"Town",
    "qs_pg:woe_adm0":23424936,
    "woe:adm0_id":23424936,
    "woe:name_adm0":"Russia",
    "woe:name_adm1":"Altai Krai",
    "woe:placetype":"Town",
    "wof:name":"Ust'-Charyshskaya Pristan'",
    "wof:placetype":"locality",
    "wof:population":5647
},
  "geometry": {"coordinates":[83.6635,52.3934],"type":"Point"}
}