{
  "type": "Feature",
  "properties": {
    "gn:admin1_code":"77",
    "gn:asciiname":"Rogozikha",
    "gn:country_code":"RU",
    "gn:dem":175,
    "gn:feature_class":"P",
    "gn:feature_code":"PPL",
    "gn:name":"Rogozikha",
    "gn:population":0,
    "gn:timezone":"Europe/Moscow",
    "iso:country":"RU",
    "name:rus_x_preferred":[
        "\u0420\u043e\u0433\u043e\u0437\u0438\u0445\u0430"
    ],
    "wof:name":"Rogozikha",
    "wof:placetype":"locality"
},
  "geometry": {"coordinates":[35.15,58.13333000000001],"type":"Point"}
}