{
  "type": "Feature",
  "properties": {
    "gn:admin1_code":"51.0",
    "gn:asciiname":"Bol'shoye Chir'yevo",
    "gn:country_code":"RU",
    "gn:dem":93,
    "gn:feature_class":"P",
    "gn:feature_code":"PPL",
    "gn:name":"Bol\u2019shoye Chir\u2019y\u00ebvo",
    "gn:population":0,
    "gn:timezone":"Europe/Moscow",
    "iso:country":"RU",
    "name:rus_x_preferred":[
        "\u0411\u043e\u043b\u044c\u0448\u043e\u0435 \u0427\u0438\u0440\u044c\u0451\u0432\u043e"
    ],
    "name:und_x_variant":[
        "Bol\u2019shoye Chir\u2019y\u00ebvo"
    ],
    "wof:name":"Bol'shoye Chir'yevo",
    "wof:placetype":"locality"
},
  "geometry": {"coordinates":[42.95,55.91667],"type":"Point"}
}