{
  "type": "Feature",
  "properties": {
    "gn:admin1_code":"20",
    "gn:asciiname":"Vershina Tutury",
    "gn:country_code":"RU",
    "gn:dem":836,
    "gn:feature_class":"P",
    "gn:feature_code":"PPL",
    "gn:name":"Vershina Tutury",
    "gn:population":0,
    "gn:timezone":"Asia/Irkutsk",
    "iso:country":"RU",
    "name:eng_x_preferred":[
        "Vershina Tutury"
    ],
    "name:nor_x_preferred":[
        "Versjina Tutury"
    ],
    "name:rus_x_preferred":[
        "\u0412\u0435\u0440\u0448\u0438\u043d\u0430 \u0422\u0443\u0442\u0443\u0440\u044b"
    ],
    "wof:name":"Vershina Tutury",
    "wof:placetype":"locality"
},
  "geometry": {"coordinates":[106.20152,54.43313000000001],"type":"Point"}
}