{
  "type": "Feature",
  "properties": {
    "gn:admin1_code":"80.0",
    "gn:asciiname":"Russkaya-Bab'ya",
    "gn:country_code":"RU",
    "gn:dem":194,
    "gn:feature_class":"P",
    "gn:feature_code":"PPL",
    "gn:name":"Russkaya-Bab\u2019ya",
    "gn:population":0,
    "gn:timezone":"Europe/Samara",
    "iso:country":"RU",
    "name:eng_x_preferred":[
        "Russkaya-Bab'ya"
    ],
    "name:nor_x_preferred":[
        "Russkaja Babja"
    ],
    "name:rus_x_preferred":[
        "\u0420\u0443\u0441\u0441\u043a\u0430\u044f \u0411\u0430\u0431\u044c\u044f"
    ],
    "name:rus_x_variant":[
        "\u0420\u0443\u0441\u0441\u043a\u0430\u044f-\u0411\u0430\u0431\u044c\u044f"
    ],
    "name:und_x_variant":[
        "Bob\u2019ya-Russkaya",
        "Bob\u2019ya",
        "Russkaya-Bab\u2019ya"
    ],
    "wof:name":"Russkaya-Bab'ya",
    "wof:placetype":"locality"
},
  "geometry": {"coordinates":[51.54986,57.06869],"type":"Point"}
}