{
  "type": "Feature",
  "properties": {
    "gn:admin1_code":"44",
    "gn:asciiname":"Ust'-Nemchen",
    "gn:country_code":"RU",
    "gn:dem":481,
    "gn:feature_class":"P",
    "gn:feature_code":"PPL",
    "gn:name":"Ust\u2019-Nemchen",
    "gn:population":0,
    "gn:timezone":"Asia/Magadan",
    "iso:country":"RU",
    "name:und_x_variant":[
        "Ust\u2019-Nerega",
        "Ust\u2019-Nemchen"
    ],
    "wof:name":"Ust'-Nemchen",
    "wof:placetype":"locality"
},
  "geometry": {"coordinates":[151.50654,61.86526],"type":"Point"}
}