{
  "type": "Feature",
  "properties": {
    "gn:admin1_code":"54",
    "gn:asciiname":"Yur'yevka",
    "gn:country_code":"RU",
    "gn:dem":114,
    "gn:feature_class":"P",
    "gn:feature_code":"PPL",
    "gn:name":"Yur\u2019yevka",
    "gn:population":0,
    "gn:timezone":"Asia/Omsk",
    "iso:country":"RU",
    "name:eng_x_preferred":[
        "Yur'yevka"
    ],
    "name:nor_x_preferred":[
        "Jurjevka"
    ],
    "name:rus_x_preferred":[
        "\u042e\u0440\u044c\u0435\u0432\u043a\u0430"
    ],
    "name:und_x_variant":[
        "Yur\u2019yevka"
    ],
    "wof:name":"Yur'yevka",
    "wof:placetype":"locality"
},
  "geometry": {"coordinates":[74.94029999999999,57.19],"type":"Point"}
}