{
  "type": "Feature",
  "properties": {
    "gn:admin1_code":"80",
    "gn:asciiname":"Oreshniki",
    "gn:country_code":"RU",
    "gn:dem":182,
    "gn:feature_class":"P",
    "gn:feature_code":"PPL",
    "gn:name":"Oreshniki",
    "gn:population":0,
    "gn:timezone":"Europe/Samara",
    "iso:country":"RU",
    "name:rus_x_preferred":[
        "\u041e\u0440\u0435\u0448\u043d\u0438\u043a\u0438"
    ],
    "name:und_x_variant":[
        "\u041e\u0440\u0435\u0448\u043d\u0438\u043a\u0438"
    ],
    "wof:name":"Oreshniki",
    "wof:placetype":"locality"
},
  "geometry": {"coordinates":[53.83333,56.28333000000001],"type":"Point"}
}