{
  "type": "Feature",
  "properties": {
    "gn:admin1_code":"43",
    "gn:asciiname":"Oranovka",
    "gn:country_code":"RU",
    "gn:dem":195,
    "gn:feature_class":"P",
    "gn:feature_code":"PPL",
    "gn:name":"Oranovka",
    "gn:population":0,
    "gn:timezone":"Europe/Moscow",
    "iso:country":"RU",
    "name:rus_x_preferred":[
        "\u041e\u0440\u0430\u043d\u043e\u0432\u043a\u0430"
    ],
    "wof:name":"Oranovka",
    "wof:placetype":"locality"
},
  "geometry": {"coordinates":[38.346,52.4432],"type":"Point"}
}