{
  "type": "Feature",
  "properties": {
    "gn:admin1_code":"47",
    "gn:asciiname":"Starikovo",
    "gn:country_code":"RU",
    "gn:dem":260,
    "gn:feature_class":"P",
    "gn:feature_code":"PPL",
    "gn:name":"Starikovo",
    "gn:population":0,
    "gn:timezone":"Europe/Moscow",
    "iso:country":"RU",
    "name:nor_x_preferred":[
        "Starikovo"
    ],
    "name:rus_x_preferred":[
        "\u0421\u0442\u0430\u0440\u0438\u043a\u043e\u0432\u043e"
    ],
    "wof:name":"Starikovo",
    "wof:placetype":"locality"
},
  "geometry": {"coordinates":[35.58410999999999,56.02921],"type":"Point"}
}