{
  "type": "Feature",
  "properties": {
    "gn:admin1_code":"85",
    "gn:asciiname":"Kundyukovo",
    "gn:country_code":"RU",
    "gn:dem":124,
    "gn:feature_class":"P",
    "gn:feature_code":"PPL",
    "gn:name":"Kundyukovo",
    "gn:population":0,
    "gn:timezone":"Europe/Moscow",
    "iso:country":"RU",
    "name:rus_x_preferred":[
        "\u041a\u0443\u043d\u0434\u044e\u043a\u043e\u0432\u043e"
    ],
    "name:und_x_variant":[
        "\u041a\u0443\u043d\u0434\u044e\u043a\u043e\u0432\u043e"
    ],
    "wof:name":"Kundyukovo",
    "wof:placetype":"locality"
},
  "geometry": {"coordinates":[38.4749,59.8307],"type":"Point"}
}