{
  "type": "Feature",
  "properties": {
    "gn:admin1_code":"8",
    "gn:asciiname":"Itkuchukovo",
    "gn:country_code":"RU",
    "gn:dem":184,
    "gn:feature_class":"P",
    "gn:feature_code":"PPL",
    "gn:name":"Itkuchukovo",
    "gn:population":0,
    "gn:timezone":"Asia/Yekaterinburg",
    "iso:country":"RU",
    "name:rus_x_preferred":[
        "\u0418\u0442\u043a\u0443\u0447\u0443\u043a\u043e\u0432\u043e"
    ],
    "name:und_x_variant":[
        "Itkuchukova",
        "Itkuchukovo",
        "\u0418\u0442\u043a\u0443\u0447\u0443\u043a\u043e\u0432\u043e"
    ],
    "wof:name":"Itkuchukovo",
    "wof:placetype":"locality"
},
  "geometry": {"coordinates":[56.31154,52.9979],"type":"Point"}
}