{
  "type": "Feature",
  "properties": {
    "gn:admin1_code":"8",
    "gn:asciiname":"Mikhelevskiy",
    "gn:country_code":"RU",
    "gn:dem":290,
    "gn:feature_class":"P",
    "gn:feature_code":"PPL",
    "gn:name":"Mikhelevskiy",
    "gn:population":0,
    "gn:timezone":"Asia/Yekaterinburg",
    "iso:country":"RU",
    "name:rus_x_preferred":[
        "\u041c\u0438\u0445\u0435\u043b\u0435\u0432\u0441\u043a\u0438\u0439"
    ],
    "name:und_x_variant":[
        "Mikhelevskoye",
        "Mikhelevskiy"
    ],
    "wof:name":"Mikhelevskiy",
    "wof:placetype":"locality"
},
  "geometry": {"coordinates":[55.71666999999999,52.68333000000001],"type":"Point"}
}