{
  "type": "Feature",
  "properties": {
    "gn:admin1_code":"52",
    "gn:asciiname":"Korotsko",
    "gn:country_code":"RU",
    "gn:dem":233,
    "gn:feature_class":"P",
    "gn:feature_code":"PPL",
    "gn:name":"Korotsko",
    "gn:population":0,
    "gn:timezone":"Europe/Moscow",
    "iso:country":"RU",
    "name:rus_x_preferred":[
        "\u041a\u043e\u0440\u043e\u0442\u0441\u043a\u043e"
    ],
    "wof:name":"Korotsko",
    "wof:placetype":"locality"
},
  "geometry": {"coordinates":[33.24667,57.93833000000001],"type":"Point"}
}