{
  "type": "Feature",
  "properties": {
    "gn:admin1_code":"17",
    "gn:asciiname":"Kumtorkala",
    "gn:cc2":"RU",
    "gn:country_code":"RU",
    "gn:dem":63,
    "gn:feature_class":"P",
    "gn:feature_code":"PPL",
    "gn:name":"Kumtorkala",
    "gn:population":0,
    "gn:timezone":"Europe/Moscow",
    "iso:country":"RU",
    "name:rus_x_preferred":[
        "\u041a\u0443\u043c\u0442\u043e\u0440\u043a\u0430\u043b\u0430"
    ],
    "name:und_x_variant":[
        "Kizil-Yurt",
        "Kut-Torkalyeh",
        "Kumtorkala"
    ],
    "wof:name":"Kumtorkala",
    "wof:placetype":"locality"
},
  "geometry": {"coordinates":[47.24694,43.0025],"type":"Point"}
}