{
  "type": "Feature",
  "properties": {
    "gn:admin1_code":"84",
    "gn:asciiname":"Inga",
    "gn:country_code":"RU",
    "gn:dem":122,
    "gn:feature_class":"P",
    "gn:feature_code":"PPL",
    "gn:name":"Inga",
    "gn:population":0,
    "gn:timezone":"Europe/Volgograd",
    "iso:country":"RU",
    "name:rus_x_preferred":[
        "\u0418\u043d\u0433\u0430"
    ],
    "wof:name":"Inga",
    "wof:placetype":"locality"
},
  "geometry": {"coordinates":[44.33243,48.52977],"type":"Point"}
}