{
  "type": "Feature",
  "properties": {
    "gn:admin1_code":"76",
    "gn:asciiname":"Kauchukpromkhoz",
    "gn:country_code":"RU",
    "gn:dem":244,
    "gn:feature_class":"P",
    "gn:feature_code":"PPL",
    "gn:name":"Kauchukpromkhoz",
    "gn:population":0,
    "gn:timezone":"Europe/Moscow",
    "iso:country":"RU",
    "name:rus_x_preferred":[
        "\u041a\u0430\u0443\u0447\u0443\u043a\u043f\u0440\u043e\u043c\u0445\u043e\u0437"
    ],
    "name:und_x_variant":[
        "\u041a\u0430\u0443\u0447\u0443\u043a\u043f\u0440\u043e\u043c\u0445\u043e\u0437"
    ],
    "wof:name":"Kauchukpromkhoz",
    "wof:placetype":"locality"
},
  "geometry": {"coordinates":[37.52389,53.60972],"type":"Point"}
}