{
  "type": "Feature",
  "properties": {
    "gn:admin1_code":"25",
    "gn:asciiname":"Al'shan'",
    "gn:country_code":"RU",
    "gn:dem":193,
    "gn:feature_class":"P",
    "gn:feature_code":"PPL",
    "gn:name":"Al\u2019shan\u2019",
    "gn:population":0,
    "gn:timezone":"Europe/Moscow",
    "iso:country":"RU",
    "name:nor_x_preferred":[
        "Alsjan"
    ],
    "name:rus_x_preferred":[
        "\u0410\u043b\u044c\u0448\u0430\u043d\u044c"
    ],
    "name:und_x_variant":[
        "Al\u2019shan\u2019"
    ],
    "wof:name":"Al'shan'",
    "wof:placetype":"locality"
},
  "geometry": {"coordinates":[35.06667,53.64861],"type":"Point"}
}