{
  "type": "Feature",
  "properties": {
    "gn:admin1_code":"28",
    "gn:asciiname":"Manunmyaki",
    "gn:country_code":"RU",
    "gn:dem":104,
    "gn:feature_class":"P",
    "gn:feature_code":"PPL",
    "gn:name":"Manunmyaki",
    "gn:population":0,
    "gn:timezone":"Europe/Moscow",
    "iso:country":"RU",
    "name:fin_x_preferred":[
        "Manunm\u00e4ki"
    ],
    "name:rus_x_preferred":[
        "\u041c\u0430\u043d\u0443\u043d\u043c\u044f\u043a\u0438"
    ],
    "wof:name":"Manunmyaki",
    "wof:placetype":"locality"
},
  "geometry": {"coordinates":[31.27962,61.95389],"type":"Point"}
}