{
  "type": "Feature",
  "properties": {
    "gn:admin1_code":"70",
    "gn:asciiname":"Kaskadnyy",
    "gn:country_code":"RU",
    "gn:dem":398,
    "gn:feature_class":"P",
    "gn:feature_code":"PPL",
    "gn:name":"Kaskadnyy",
    "gn:population":0,
    "gn:timezone":"Europe/Moscow",
    "iso:country":"RU",
    "name:eng_x_preferred":[
        "Kaskadnyy"
    ],
    "name:nor_x_preferred":[
        "Kaskadnyj"
    ],
    "name:rus_x_preferred":[
        "\u041a\u0430\u0441\u043a\u0430\u0434\u043d\u044b\u0439"
    ],
    "name:und_x_variant":[
        "\u041a\u0430\u0441\u043a\u0430\u0434\u043d\u044b\u0439",
        "Kaskadnyy"
    ],
    "wof:name":"Kaskadnyy",
    "wof:placetype":"locality"
},
  "geometry": {"coordinates":[42.23139000000001,44.60778],"type":"Point"}
}