{
  "type": "Feature",
  "properties": {
    "gn:admin1_code":"90.0",
    "gn:asciiname":"Bol'shoy Dubovik",
    "gn:country_code":"RU",
    "gn:dem":177,
    "gn:feature_class":"P",
    "gn:feature_code":"PPL",
    "gn:name":"Bol\u2019shoy Dubovik",
    "gn:population":0,
    "gn:timezone":"Asia/Yekaterinburg",
    "iso:country":"RU",
    "name:rus_x_preferred":[
        "\u0411\u043e\u043b\u044c\u0448\u043e\u0439 \u0414\u0443\u0431\u043e\u0432\u0438\u043a"
    ],
    "name:und_x_variant":[
        "Bol\u2019shoy Dubovik"
    ],
    "wof:name":"Bol'shoy Dubovik",
    "wof:placetype":"locality"
},
  "geometry": {"coordinates":[55.22637,56.64525],"type":"Point"}
}