{
  "type": "Feature",
  "properties": {
    "gn:admin1_code":"6",
    "gn:asciiname":"Ukhta-Tobolkino",
    "gn:country_code":"RU",
    "gn:dem":130,
    "gn:feature_class":"P",
    "gn:feature_code":"PPL",
    "gn:name":"Ukhta-Tobolkino",
    "gn:population":0,
    "gn:timezone":"Europe/Moscow",
    "iso:country":"RU",
    "name:eng_x_preferred":[
        "Ukhta-Tobolkino"
    ],
    "name:nor_x_preferred":[
        "Tobolkino"
    ],
    "name:rus_x_preferred":[
        "\u0422\u043e\u0431\u043e\u043b\u043a\u0438\u043d\u043e"
    ],
    "name:und_x_variant":[
        "Tobolkino",
        "Ukhta-Tobolkino"
    ],
    "wof:name":"Ukhta-Tobolkino",
    "wof:placetype":"locality"
},
  "geometry": {"coordinates":[38.55836,61.19671],"type":"Point"}
}