{
  "type": "Feature",
  "properties": {
    "gn:admin1_code":"10",
    "gn:asciiname":"Kozlovskiy",
    "gn:country_code":"RU",
    "gn:dem":186,
    "gn:feature_class":"P",
    "gn:feature_code":"PPL",
    "gn:name":"Kozlovskiy",
    "gn:population":0,
    "gn:timezone":"Europe/Moscow",
    "iso:country":"RU",
    "name:rus_x_preferred":[
        "\u041a\u043e\u0437\u043b\u043e\u0432\u0441\u043a\u0438\u0439"
    ],
    "wof:name":"Kozlovskiy",
    "wof:placetype":"locality"
},
  "geometry": {"coordinates":[33.2002,53.0993],"type":"Point"}
}