{
  "type": "Feature",
  "properties": {
    "gn:admin1_code":"38.0",
    "gn:asciiname":"Chemburka",
    "gn:country_code":"RU",
    "gn:dem":7,
    "gn:feature_class":"P",
    "gn:feature_code":"PPL",
    "gn:name":"Chemburka",
    "gn:population":0,
    "gn:timezone":"Europe/Moscow",
    "iso:country":"RU",
    "name:rus_x_preferred":[
        "\u0427\u0435\u043c\u0431\u0443\u0440\u043a\u0430"
    ],
    "name:und_x_variant":[
        "\u0427\u0435\u043c\u0431\u0443\u0440\u043a\u0430"
    ],
    "wof:name":"Chemburka",
    "wof:placetype":"locality"
},
  "geometry": {"coordinates":[37.34611,44.92917],"type":"Point"}
}