{
  "type": "Feature",
  "properties": {
    "gn:admin1_code":"77",
    "gn:asciiname":"Izvedovo",
    "gn:country_code":"RU",
    "gn:dem":211,
    "gn:feature_class":"P",
    "gn:feature_code":"PPL",
    "gn:name":"Izvedovo",
    "gn:population":0,
    "gn:timezone":"Europe/Moscow",
    "iso:country":"RU",
    "name:rus_x_preferred":[
        "\u0418\u0437\u0432\u0435\u0434\u043e\u0432\u043e"
    ],
    "wof:name":"Izvedovo",
    "wof:placetype":"locality"
},
  "geometry": {"coordinates":[32.73944,56.94056],"type":"Point"}
}