{
  "type": "Feature",
  "properties": {
    "gn:admin1_code":"90",
    "gn:asciiname":"Ust'-Turka",
    "gn:country_code":"RU",
    "gn:dem":134,
    "gn:feature_class":"P",
    "gn:feature_code":"PPL",
    "gn:name":"Ust\u2019-Turka",
    "gn:population":0,
    "gn:timezone":"Asia/Yekaterinburg",
    "iso:country":"RU",
    "name:eng_x_preferred":[
        "Ust'-Turka"
    ],
    "name:nor_x_preferred":[
        "Ust-Turka"
    ],
    "name:rus_x_preferred":[
        "\u0423\u0441\u0442\u044c-\u0422\u0443\u0440\u043a\u0430"
    ],
    "name:und_x_variant":[
        "Ust\u2019-Turka"
    ],
    "wof:name":"Ust'-Turka",
    "wof:placetype":"locality"
},
  "geometry": {"coordinates":[56.59343000000001,57.21538],"type":"Point"}
}