{
  "type": "Feature",
  "properties": {
    "gn:admin1_code":"85",
    "gn:asciiname":"Malakhovo",
    "gn:country_code":"RU",
    "gn:dem":141,
    "gn:feature_class":"P",
    "gn:feature_code":"PPL",
    "gn:name":"Malakhovo",
    "gn:population":0,
    "gn:timezone":"Europe/Moscow",
    "iso:country":"RU",
    "name:eng_x_preferred":[
        "Malakhovo"
    ],
    "name:nor_x_preferred":[
        "Malakhovo"
    ],
    "name:rus_x_preferred":[
        "\u041c\u0430\u043b\u0430\u0445\u043e\u0432\u043e"
    ],
    "wof:name":"Malakhovo",
    "wof:placetype":"locality"
},
  "geometry": {"coordinates":[36.2479,59.4658],"type":"Point"}
}