{
  "type": "Feature",
  "properties": {
    "gn:admin1_code":"8.0",
    "gn:asciiname":"Bakaldinskoye",
    "gn:country_code":"RU",
    "gn:dem":149,
    "gn:feature_class":"P",
    "gn:feature_code":"PPL",
    "gn:name":"Bakaldinskoye",
    "gn:population":0,
    "gn:timezone":"Asia/Yekaterinburg",
    "iso:country":"RU",
    "name:aze_x_preferred":[
        "Bakald\u0131"
    ],
    "name:bak_x_preferred":[
        "\u0411\u0430\u04a1\u0430\u043b\u0434\u044b"
    ],
    "name:che_x_preferred":[
        "\u0411\u0430\u043a\u0430\u043b\u0434\u0438\u043d\u0441\u043a\u0438"
    ],
    "name:eng_x_preferred":[
        "Bakaldinskoye"
    ],
    "name:hye_x_preferred":[
        "\u0532\u0561\u056f\u0561\u056c\u0564\u056b\u0576\u057d\u056f\u0578\u0565"
    ],
    "name:kat_x_preferred":[
        "\u10d1\u10d0\u10d9\u10d0\u10da\u10d3\u10d8\u10dc\u10e1\u10d9\u10dd\u10d4"
    ],
    "name:kaz_x_preferred":[
        "\u0411\u0430\u043a\u0430\u043b\u0434\u0438\u043d"
    ],
    "name:kir_x_preferred":[
        "\u0411\u0430\u043a\u0430\u043b\u0434\u0438\u043d"
    ],
    "name:nor_x_preferred":[
        "Bakaldinskoje"
    ],
    "name:rus_x_preferred":[
        "\u0411\u0430\u043a\u0430\u043b\u0434\u0438\u043d\u0441\u043a\u043e\u0435"
    ],
    "name:tat_x_preferred":[
        "\u0411\u0430\u043a\u0430\u043b\u0434\u044b"
    ],
    "name:ukr_x_preferred":[
        "\u0411\u0430\u043a\u0430\u043b\u0434\u0456\u043d\u0441\u044c\u043a\u0435"
    ],
    "name:und_x_variant":[
        "\u0411\u0430\u043a\u0430\u043b\u0434\u0438\u043d\u0441\u043a\u043e\u0435",
        "Bakaldinskoye"
    ],
    "wof:name":"Bakaldinskoye",
    "wof:placetype":"locality"
},
  "geometry": {"coordinates":[56.90598000000001,54.43142],"type":"Point"}
}