{
  "type": "Feature",
  "properties": {
    "gn:admin1_code":"8.0",
    "gn:asciiname":"Bakaldinskoye",
    "gn:country_code":"RU",
    "gn:dem":149,
    "gn:feature_class":"P",
    "gn:feature_code":"PPL",
    "gn:name":"Bakaldinskoye",
    "gn:population":0,
    "gn:timezone":"Asia/Yekaterinburg",
    "iso:country":"RU",
    "name:eng_x_preferred":[
        "Bakaldinskoye"
    ],
    "name:nor_x_preferred":[
        "Bakaldinskoje"
    ],
    "name:rus_x_preferred":[
        "\u0411\u0430\u043a\u0430\u043b\u0434\u0438\u043d\u0441\u043a\u043e\u0435"
    ],
    "name:und_x_variant":[
        "\u0411\u0430\u043a\u0430\u043b\u0434\u0438\u043d\u0441\u043a\u043e\u0435",
        "Bakaldinskoye"
    ],
    "wof:name":"Bakaldinskoye",
    "wof:placetype":"locality"
},
  "geometry": {"coordinates":[56.90598000000001,54.43142],"type":"Point"}
}