{
  "type": "Feature",
  "properties": {
    "gn:admin1_code":"53",
    "gn:asciiname":"Osinnikovskiy",
    "gn:country_code":"RU",
    "gn:dem":121,
    "gn:feature_class":"P",
    "gn:feature_code":"PPL",
    "gn:name":"Osinnikovskiy",
    "gn:population":0,
    "gn:timezone":"Asia/Novosibirsk",
    "iso:country":"RU",
    "name:rus_x_preferred":[
        "\u041e\u0441\u0438\u043d\u043d\u0438\u043a\u043e\u0432\u0441\u043a\u0438\u0439"
    ],
    "name:und_x_variant":[
        "Osinniki"
    ],
    "wof:name":"Osinnikovskiy",
    "wof:placetype":"locality"
},
  "geometry": {"coordinates":[78.79439000000001,53.89073000000001],"type":"Point"}
}