{
  "type": "Feature",
  "properties": {
    "gn:admin1_code":"76",
    "gn:asciiname":"Bol'shoye Khlynovo",
    "gn:country_code":"RU",
    "gn:dem":198,
    "gn:feature_class":"P",
    "gn:feature_code":"PPL",
    "gn:name":"Bol\u2019shoye Khlynovo",
    "gn:population":0,
    "gn:timezone":"Europe/Moscow",
    "iso:country":"RU",
    "wof:name":"Bol'shoye Khlynovo",
    "wof:placetype":"locality"
},
  "geometry": {"coordinates":[37.3414,54.16934000000001],"type":"Point"}
}