{
  "type": "Feature",
  "properties": {
    "gn:admin1_code":"69",
    "gn:asciiname":"Shcherbino",
    "gn:country_code":"RU",
    "gn:dem":221,
    "gn:feature_class":"P",
    "gn:feature_code":"PPL",
    "gn:name":"Shcherbino",
    "gn:population":0,
    "gn:timezone":"Europe/Moscow",
    "iso:country":"RU",
    "name:eng_x_preferred":[
        "Staroye Shcherbino"
    ],
    "name:nor_x_preferred":[
        "Sjtsjerbino"
    ],
    "name:rus_x_preferred":[
        "\u0429\u0435\u0440\u0431\u0438\u043d\u043e"
    ],
    "name:und_x_variant":[
        "Shcherbino"
    ],
    "wof:name":"Shcherbino",
    "wof:placetype":"locality"
},
  "geometry": {"coordinates":[32.96264,54.45446999999999],"type":"Point"}
}