{
  "type": "Feature",
  "properties": {
    "gn:admin1_code":"47",
    "gn:asciiname":"Shaburnovo",
    "gn:country_code":"RU",
    "gn:dem":188,
    "gn:feature_class":"P",
    "gn:feature_code":"PPL",
    "gn:name":"Shaburnovo",
    "gn:population":1155,
    "gn:timezone":"Europe/Moscow",
    "iso:country":"RU",
    "name:eng_x_preferred":[
        "Shaburnovo"
    ],
    "name:nor_x_preferred":[
        "Sjaburnovo"
    ],
    "name:rus_x_preferred":[
        "\u0428\u0430\u0431\u0443\u0440\u043d\u043e\u0432\u043e"
    ],
    "name:und_x_variant":[
        "\u0428\u0430\u0431\u0443\u0440\u043d\u043e\u0432\u043e",
        "Shaburnovo"
    ],
    "wof:name":"Shaburnovo",
    "wof:placetype":"locality",
    "wof:population":1155
},
  "geometry": {"coordinates":[37.93333,56.55],"type":"Point"}
}