{
  "type": "Feature",
  "properties": {
    "gn:admin1_code":"60",
    "gn:asciiname":"Punishche",
    "gn:country_code":"RU",
    "gn:dem":193,
    "gn:feature_class":"P",
    "gn:feature_code":"PPL",
    "gn:name":"Punishche",
    "gn:population":0,
    "gn:timezone":"Europe/Moscow",
    "iso:country":"RU",
    "name:rus_x_preferred":[
        "\u041f\u0443\u043d\u0438\u0449\u0435"
    ],
    "name:und_x_variant":[
        "\u041f\u0443\u043d\u0438\u0449\u0435"
    ],
    "wof:name":"Punishche",
    "wof:placetype":"locality"
},
  "geometry": {"coordinates":[29.8559,56.1452],"type":"Point"}
}