{
  "type": "Feature",
  "properties": {
    "gn:admin1_code":"25",
    "gn:asciiname":"Maloye Viselevo",
    "gn:country_code":"RU",
    "gn:dem":192,
    "gn:feature_class":"P",
    "gn:feature_code":"PPL",
    "gn:name":"Maloye Visel\u00ebvo",
    "gn:population":0,
    "gn:timezone":"Europe/Moscow",
    "iso:country":"RU",
    "name:rus_x_preferred":[
        "\u041c\u0430\u043b\u043e\u0435 \u0412\u0438\u0441\u0435\u043b\u0451\u0432\u043e"
    ],
    "name:und_x_variant":[
        "Maloye Visel\u00ebvo",
        "\u041c\u0430\u043b\u043e\u0435 \u0412\u0438\u0441\u0435\u043b\u0451\u0432\u043e"
    ],
    "wof:name":"Maloye Viselevo",
    "wof:placetype":"locality"
},
  "geometry": {"coordinates":[34.95,54.88333000000001],"type":"Point"}
}