{
  "type": "Feature",
  "properties": {
    "gn:admin1_code":"52",
    "gn:asciiname":"Yeskino",
    "gn:country_code":"RU",
    "gn:dem":146,
    "gn:feature_class":"P",
    "gn:feature_code":"PPL",
    "gn:name":"Yeskino",
    "gn:population":0,
    "gn:timezone":"Europe/Moscow",
    "iso:country":"RU",
    "name:eng_x_preferred":[
        "Yeskino"
    ],
    "name:nor_x_preferred":[
        "Jeskino"
    ],
    "name:rus_x_preferred":[
        "\u0415\u0441\u044c\u043a\u0438\u043d\u043e"
    ],
    "wof:name":"Yeskino",
    "wof:placetype":"locality"
},
  "geometry": {"coordinates":[35.56289,58.79651],"type":"Point"}
}