{
  "type": "Feature",
  "properties": {
    "gn:admin1_code":"60",
    "gn:asciiname":"Volochagino",
    "gn:country_code":"RU",
    "gn:dem":186,
    "gn:feature_class":"P",
    "gn:feature_code":"PPL",
    "gn:name":"Volochagino",
    "gn:population":0,
    "gn:timezone":"Europe/Moscow",
    "iso:country":"RU",
    "name:rus_x_preferred":[
        "\u0412\u043e\u043b\u043e\u0447\u0430\u0433\u0438\u043d\u043e"
    ],
    "wof:name":"Volochagino",
    "wof:placetype":"locality"
},
  "geometry": {"coordinates":[29.3162,56.5076],"type":"Point"}
}