{
  "type": "Feature",
  "properties": {
    "gn:admin1_code":"38",
    "gn:asciiname":"Nekrasovskiy",
    "gn:cc2":"RU",
    "gn:country_code":"RU",
    "gn:dem":15,
    "gn:feature_class":"P",
    "gn:feature_code":"PPL",
    "gn:name":"Nekrasovskiy",
    "gn:population":0,
    "gn:timezone":"Europe/Moscow",
    "iso:country":"RU",
    "name:und_x_variant":[
        "Nekrasov"
    ],
    "wof:name":"Nekrasovskiy",
    "wof:placetype":"locality"
},
  "geometry": {"coordinates":[39.08167,45.66722],"type":"Point"}
}