{
  "type": "Feature",
  "properties": {
    "gn:admin1_code":"8",
    "gn:asciiname":"Musagitovo",
    "gn:country_code":"RU",
    "gn:dem":216,
    "gn:feature_class":"P",
    "gn:feature_code":"PPL",
    "gn:name":"Musagitovo",
    "gn:population":0,
    "gn:timezone":"Asia/Yekaterinburg",
    "iso:country":"RU",
    "name:bak_x_preferred":[
        "\u041c\u04e9\u0441\u04d9\u0493\u0438\u0442"
    ],
    "name:che_x_preferred":[
        "\u041c\u0443\u0441\u0430\u0433\u0438\u0442\u043e\u0432\u043e"
    ],
    "name:hye_x_preferred":[
        "\u0544\u0578\u0582\u057d\u0561\u0563\u056b\u057f\u0578\u057e\u0578"
    ],
    "name:kaz_x_preferred":[
        "\u041c\u0443\u0441\u0430\u0433\u0438\u0442"
    ],
    "name:kir_x_preferred":[
        "\u041c\u0443\u0441\u0430\u0433\u0438\u0442"
    ],
    "name:rus_x_preferred":[
        "\u041c\u0443\u0441\u0430\u0433\u0438\u0442\u043e\u0432\u043e"
    ],
    "name:tat_x_preferred":[
        "\u041c\u04e9\u0441\u04d9\u0433\u044b\u0439\u0442\u044c"
    ],
    "name:ukr_x_preferred":[
        "\u041c\u0443\u0441\u0430\u0433\u0456\u0442\u043e\u0432\u043e"
    ],
    "name:und_x_variant":[
        "Musagitova",
        "Musagitovo",
        "\u041c\u0443\u0441\u0430\u0433\u0438\u0442\u043e\u0432\u043e"
    ],
    "wof:name":"Musagitovo",
    "wof:placetype":"locality"
},
  "geometry": {"coordinates":[55.34906,54.27474],"type":"Point"}
}