{
  "type": "Feature",
  "properties": {
    "gn:admin1_code":"90",
    "gn:asciiname":"Gurina",
    "gn:country_code":"RU",
    "gn:dem":263,
    "gn:feature_class":"P",
    "gn:feature_code":"PPL",
    "gn:name":"Gurina",
    "gn:population":0,
    "gn:timezone":"Asia/Yekaterinburg",
    "iso:country":"RU",
    "name:rus_x_preferred":[
        "\u0413\u0443\u0440\u0438\u043d\u0430"
    ],
    "name:und_x_variant":[
        "Turina",
        "Gurina"
    ],
    "wof:name":"Gurina",
    "wof:placetype":"locality"
},
  "geometry": {"coordinates":[57.51714000000001,60.11033000000001],"type":"Point"}
}