{
  "type": "Feature",
  "properties": {
    "gn:admin1_code":"10",
    "gn:asciiname":"Koltovo",
    "gn:country_code":"RU",
    "gn:dem":183,
    "gn:feature_class":"P",
    "gn:feature_code":"PPL",
    "gn:name":"Koltovo",
    "gn:population":0,
    "gn:timezone":"Europe/Moscow",
    "iso:country":"RU",
    "name:rus_x_preferred":[
        "\u041a\u043e\u043b\u0442\u043e\u0432\u043e"
    ],
    "name:und_x_variant":[
        "\u041a\u043e\u043b\u0442\u043e\u0432\u043e"
    ],
    "wof:name":"Koltovo",
    "wof:placetype":"locality"
},
  "geometry": {"coordinates":[34.1219,53.27134],"type":"Point"}
}