{
  "type": "Feature",
  "properties": {
    "gn:admin1_code":"53",
    "gn:asciiname":"Medyakovskiy",
    "gn:cc2":"RU",
    "gn:country_code":"RU",
    "gn:dem":134,
    "gn:feature_class":"P",
    "gn:feature_code":"PPL",
    "gn:name":"Medyakovskiy",
    "gn:population":0,
    "gn:timezone":"Asia/Novosibirsk",
    "iso:country":"RU",
    "name:eng_x_preferred":[
        "Medyakovskiy"
    ],
    "name:nor_x_preferred":[
        "Medjakovskij"
    ],
    "name:rus_x_preferred":[
        "\u041c\u0435\u0434\u044f\u043a\u043e\u0432\u0441\u043a\u0438\u0439"
    ],
    "name:und_x_variant":[
        "Amirovskiy"
    ],
    "wof:name":"Medyakovskiy",
    "wof:placetype":"locality"
},
  "geometry": {"coordinates":[80.50083000000002,55.53444],"type":"Point"}
}