{
  "type": "Feature",
  "properties": {
    "gn:admin1_code":"76",
    "gn:asciiname":"Dubenskiye",
    "gn:country_code":"RU",
    "gn:dem":213,
    "gn:feature_class":"P",
    "gn:feature_code":"PPL",
    "gn:name":"Dubenskiye",
    "gn:population":0,
    "gn:timezone":"Europe/Moscow",
    "iso:country":"RU",
    "name:rus_x_preferred":[
        "\u0414\u0443\u0431\u0435\u043d\u0441\u043a\u0438\u0435"
    ],
    "name:und_x_variant":[
        "\u0414\u0443\u0431\u0435\u043d\u0441\u043a\u0438\u0435"
    ],
    "wof:name":"Dubenskiye",
    "wof:placetype":"locality"
},
  "geometry": {"coordinates":[35.97972,53.75722],"type":"Point"}
}