{
  "type": "Feature",
  "properties": {
    "gn:admin1_code":"37",
    "gn:asciiname":"Lipovo",
    "gn:country_code":"RU",
    "gn:dem":174,
    "gn:feature_class":"P",
    "gn:feature_code":"PPL",
    "gn:name":"Lipovo",
    "gn:population":0,
    "gn:timezone":"Europe/Moscow",
    "iso:country":"RU",
    "name:fin_x_preferred":[
        "Lipovo"
    ],
    "name:lit_x_preferred":[
        "Lipovas"
    ],
    "name:pol_x_preferred":[
        "Lipowo"
    ],
    "name:rus_x_preferred":[
        "\u041b\u0438\u043f\u043e\u0432\u043e"
    ],
    "name:srp_x_preferred":[
        "\u041b\u0438\u043f\u043e\u0432\u043e"
    ],
    "name:ukr_x_preferred":[
        "\u041b\u0456\u043f\u043e\u0432\u043e"
    ],
    "name:und_x_variant":[
        "\u041b\u0438\u043f\u043e\u0432\u043e"
    ],
    "wof:name":"Lipovo",
    "wof:placetype":"locality"
},
  "geometry": {"coordinates":[45.5468,58.8769],"type":"Point"}
}