{
  "type": "Feature",
  "properties": {
    "gn:admin1_code":"67",
    "gn:asciiname":"Slavin",
    "gn:country_code":"RU",
    "gn:dem":69,
    "gn:feature_class":"P",
    "gn:feature_code":"PPL",
    "gn:name":"Slavin",
    "gn:population":0,
    "gn:timezone":"Europe/Saratov",
    "iso:country":"RU",
    "name:rus_x_preferred":[
        "\u0421\u043b\u0430\u0432\u0438\u043d"
    ],
    "name:und_x_variant":[
        "Slavinskiy",
        "Slavin",
        "\u0421\u043b\u0430\u0432\u0438\u043d"
    ],
    "wof:name":"Slavin",
    "wof:placetype":"locality"
},
  "geometry": {"coordinates":[49.169,51.1528],"type":"Point"}
}