{
  "type": "Feature",
  "properties": {
    "gn:admin1_code":"43",
    "gn:asciiname":"Vednoye",
    "gn:country_code":"RU",
    "gn:dem":157,
    "gn:feature_class":"P",
    "gn:feature_code":"PPL",
    "gn:name":"Vednoye",
    "gn:population":0,
    "gn:timezone":"Europe/Moscow",
    "iso:country":"RU",
    "name:eng_x_preferred":[
        "Vednoye"
    ],
    "name:nor_x_preferred":[
        "Vednoje"
    ],
    "name:rus_x_preferred":[
        "\u0412\u0435\u0434\u043d\u043e\u0435"
    ],
    "name:und_x_variant":[
        "\u0412\u0435\u0434\u043d\u043e\u0435",
        "Vednoye"
    ],
    "wof:name":"Vednoye",
    "wof:placetype":"locality"
},
  "geometry": {"coordinates":[39.78568,53.48964],"type":"Point"}
}