{
  "type": "Feature",
  "properties": {
    "gn:admin1_code":"05",
    "gn:asciiname":"Atamanovka",
    "gn:country_code":"RU",
    "gn:dem":121,
    "gn:feature_class":"P",
    "gn:feature_code":"PPL",
    "gn:name":"Atamanovka",
    "gn:population":0,
    "gn:timezone":"Asia/Yakutsk",
    "iso:country":"RU",
    "name:nor_x_preferred":[
        "Atamanovka"
    ],
    "name:rus_x_preferred":[
        "\u0410\u0442\u0430\u043c\u0430\u043d\u043e\u0432\u043a\u0430"
    ],
    "wof:name":"Atamanovka",
    "wof:placetype":"locality"
},
  "geometry": {"coordinates":[130.46666999999999,49.08333],"type":"Point"}
}