{
  "type": "Feature",
  "properties": {
    "gn:admin1_code":"73",
    "gn:asciiname":"Lagerka",
    "gn:country_code":"RU",
    "gn:dem":148,
    "gn:feature_class":"P",
    "gn:feature_code":"PPL",
    "gn:name":"Lagerka",
    "gn:population":0,
    "gn:timezone":"Europe/Moscow",
    "iso:country":"RU",
    "name:rus_x_preferred":[
        "\u041b\u0430\u0433\u0435\u0440\u043a\u0430"
    ],
    "name:und_x_variant":[
        "\u041b\u0430\u0433\u0435\u0440\u043a\u0430"
    ],
    "wof:name":"Lagerka",
    "wof:placetype":"locality"
},
  "geometry": {"coordinates":[51.75,54.66667],"type":"Point"}
}