{
  "type": "Feature",
  "properties": {
    "gn:admin1_code":"88",
    "gn:asciiname":"Yakushikha",
    "gn:country_code":"RU",
    "gn:dem":151,
    "gn:feature_class":"P",
    "gn:feature_code":"PPL",
    "gn:name":"Yakushikha",
    "gn:population":0,
    "gn:timezone":"Europe/Moscow",
    "iso:country":"RU",
    "wof:name":"Yakushikha",
    "wof:placetype":"locality"
},
  "geometry": {"coordinates":[40.35897,57.47126],"type":"Point"}
}