{
  "type": "Feature",
  "properties": {
    "gn:admin1_code":"65",
    "gn:asciiname":"Sovkhoz Imeni Maslennikova",
    "gn:country_code":"RU",
    "gn:dem":32,
    "gn:feature_class":"P",
    "gn:feature_code":"PPL",
    "gn:name":"Sovkhoz Imeni Maslennikova",
    "gn:population":0,
    "gn:timezone":"Europe/Samara",
    "iso:country":"RU",
    "name:rus_x_preferred":[
        "\u0421\u043e\u0432\u0445\u043e\u0437 \u0418\u043c\u0435\u043d\u0438 \u041c\u0430\u0441\u043b\u0435\u043d\u043d\u0438\u043a\u043e\u0432\u0430"
    ],
    "name:und_x_variant":[
        "Sovkhoz Imeni Maslenikova"
    ],
    "wof:name":"Sovkhoz Imeni Maslennikova",
    "wof:placetype":"locality"
},
  "geometry": {"coordinates":[49.9397,53.1631],"type":"Point"}
}