{
  "type": "Feature",
  "properties": {
    "gn:admin1_code":"75",
    "gn:asciiname":"Ipatova",
    "gn:country_code":"RU",
    "gn:dem":168,
    "gn:feature_class":"P",
    "gn:feature_code":"PPL",
    "gn:name":"Ipatova",
    "gn:population":0,
    "gn:timezone":"Asia/Tomsk",
    "iso:country":"RU",
    "name:rus_x_preferred":[
        "\u0418\u043f\u0430\u0442\u043e\u0432\u0430"
    ],
    "name:und_x_variant":[
        "\u0418\u043f\u0430\u0442\u043e\u0432\u0430"
    ],
    "wof:name":"Ipatova",
    "wof:placetype":"locality"
},
  "geometry": {"coordinates":[85.05,56.31667],"type":"Point"}
}