{
  "type": "Feature",
  "properties": {
    "gn:admin1_code":"41.0",
    "gn:asciiname":"Volchanka",
    "gn:country_code":"RU",
    "gn:dem":198,
    "gn:feature_class":"P",
    "gn:feature_code":"PPL",
    "gn:name":"Volchanka",
    "gn:population":0,
    "gn:timezone":"Europe/Moscow",
    "iso:country":"RU",
    "name:rus_x_preferred":[
        "\u0412\u043e\u043b\u0447\u0430\u043d\u043a\u0430"
    ],
    "wof:name":"Volchanka",
    "wof:placetype":"locality"
},
  "geometry": {"coordinates":[37.0759,51.9852],"type":"Point"}
}