{
  "type": "Feature",
  "properties": {
    "gn:admin1_code":"51",
    "gn:asciiname":"Zameshaikha",
    "gn:country_code":"RU",
    "gn:dem":108,
    "gn:feature_class":"P",
    "gn:feature_code":"PPL",
    "gn:name":"Zameshaikha",
    "gn:population":0,
    "gn:timezone":"Europe/Moscow",
    "iso:country":"RU",
    "name:rus_x_preferred":[
        "\u0417\u0430\u043c\u0435\u0448\u0430\u0438\u0445\u0430"
    ],
    "wof:name":"Zameshaikha",
    "wof:placetype":"locality"
},
  "geometry": {"coordinates":[44.9326,57.3621],"type":"Point"}
}