{
  "type": "Feature",
  "properties": {
    "gn:admin1_code":"9.0",
    "gn:asciiname":"Bryanskiye Lipyagi",
    "gn:country_code":"RU",
    "gn:dem":190,
    "gn:feature_class":"P",
    "gn:feature_code":"PPL",
    "gn:name":"Bryanskiye Lipyagi",
    "gn:population":0,
    "gn:timezone":"Europe/Moscow",
    "iso:country":"RU",
    "name:rus_x_preferred":[
        "\u0411\u0440\u044f\u043d\u0441\u043a\u0438\u0435 \u041b\u0438\u043f\u044f\u0433\u0438"
    ],
    "name:und_x_variant":[
        "\u0411\u0440\u044f\u043d\u0441\u043a\u0438\u0435 \u041b\u0438\u043f\u044f\u0433\u0438"
    ],
    "wof:name":"Bryanskiye Lipyagi",
    "wof:placetype":"locality"
},
  "geometry": {"coordinates":[38.369,50.1588],"type":"Point"}
}