{
  "type": "Feature",
  "properties": {
    "gn:admin1_code":"8",
    "gn:asciiname":"Uzyanbash",
    "gn:country_code":"RU",
    "gn:dem":711,
    "gn:feature_class":"P",
    "gn:feature_code":"PPL",
    "gn:name":"Uzyanbash",
    "gn:population":0,
    "gn:timezone":"Asia/Yekaterinburg",
    "iso:country":"RU",
    "name:bak_x_preferred":[
        "\u04ae\u0499\u04d9\u043d\u0431\u0430\u0448"
    ],
    "name:che_x_preferred":[
        "\u0423\u0437\u044f\u043d\u0431\u0430\u0448"
    ],
    "name:eng_x_preferred":[
        "Uzyanbash"
    ],
    "name:hye_x_preferred":[
        "\u0548\u0582\u0566\u0575\u0561\u0576\u0562\u0561\u0577"
    ],
    "name:kat_x_preferred":[
        "\u10e3\u10d6\u10d8\u10d0\u10dc\u10d1\u10d0\u10e8\u10d8"
    ],
    "name:kaz_x_preferred":[
        "\u0423\u0437\u044f\u043d\u0431\u0430\u0448"
    ],
    "name:nor_x_preferred":[
        "Uzianbasj"
    ],
    "name:rus_x_preferred":[
        "\u0423\u0437\u044f\u043d\u0431\u0430\u0448"
    ],
    "name:tat_x_preferred":[
        "\u04ae\u0437\u04d9\u043d\u0431\u0430\u0448"
    ],
    "name:ukr_x_preferred":[
        "\u0423\u0437\u044f\u043d\u0431\u0430\u0448"
    ],
    "name:und_x_variant":[
        "Uzyak-Bash"
    ],
    "wof:name":"Uzyanbash",
    "wof:placetype":"locality"
},
  "geometry": {"coordinates":[58.2442,53.6799],"type":"Point"}
}