{
  "type": "Feature",
  "properties": {
    "gn:admin1_code":"8",
    "gn:asciiname":"Uzyanbash",
    "gn:country_code":"RU",
    "gn:dem":711,
    "gn:feature_class":"P",
    "gn:feature_code":"PPL",
    "gn:name":"Uzyanbash",
    "gn:population":0,
    "gn:timezone":"Asia/Yekaterinburg",
    "iso:country":"RU",
    "name:eng_x_preferred":[
        "Uzyanbash"
    ],
    "name:nor_x_preferred":[
        "Uzianbasj"
    ],
    "name:rus_x_preferred":[
        "\u0423\u0437\u044f\u043d\u0431\u0430\u0448"
    ],
    "name:und_x_variant":[
        "Uzyak-Bash",
        "Uzyanbash"
    ],
    "wof:name":"Uzyanbash",
    "wof:placetype":"locality"
},
  "geometry": {"coordinates":[58.2442,53.6799],"type":"Point"}
}