{
  "type": "Feature",
  "properties": {
    "gn:admin1_code":"85",
    "gn:asciiname":"Mar'inskaya",
    "gn:country_code":"RU",
    "gn:dem":184,
    "gn:feature_class":"P",
    "gn:feature_code":"PPL",
    "gn:name":"Mar\u2019inskaya",
    "gn:population":0,
    "gn:timezone":"Europe/Moscow",
    "iso:country":"RU",
    "name:rus_x_preferred":[
        "\u041c\u0430\u0440\u044c\u0438\u043d\u0441\u043a\u0430\u044f"
    ],
    "name:und_x_variant":[
        "Mar\u2019inskaya"
    ],
    "wof:name":"Mar'inskaya",
    "wof:placetype":"locality"
},
  "geometry": {"coordinates":[41.4277,59.87197],"type":"Point"}
}