{
  "type": "Feature",
  "properties": {
    "gn:admin1_code":"91",
    "gn:asciiname":"Dzhebskiy Most",
    "gn:country_code":"RU",
    "gn:dem":456,
    "gn:feature_class":"P",
    "gn:feature_code":"PPL",
    "gn:name":"Dzhebskiy Most",
    "gn:population":0,
    "gn:timezone":"Asia/Krasnoyarsk",
    "iso:country":"RU",
    "name:rus_x_preferred":[
        "\u0414\u0436\u0435\u0431\u0441\u043a\u0438\u0439 \u041c\u043e\u0441\u0442"
    ],
    "wof:name":"Dzhebskiy Most",
    "wof:placetype":"locality"
},
  "geometry": {"coordinates":[93.41333,54.235],"type":"Point"}
}