{
  "type": "Feature",
  "properties": {
    "gn:admin1_code":"28",
    "gn:asciiname":"Marvyavara",
    "gn:cc2":"RU",
    "gn:country_code":"RU",
    "gn:dem":180,
    "gn:feature_class":"P",
    "gn:feature_code":"PPL",
    "gn:name":"Marvyavara",
    "gn:population":0,
    "gn:timezone":"Europe/Moscow",
    "iso:country":"RU",
    "name:rus_x_preferred":[
        "\u041c\u0430\u0440\u0432\u044f\u0432\u0430\u0440\u0430"
    ],
    "name:und_x_variant":[
        "Marjavaara",
        "Marvyavara"
    ],
    "wof:name":"Marvyavara",
    "wof:placetype":"locality"
},
  "geometry": {"coordinates":[32.16667,62.38333000000001],"type":"Point"}
}