{
  "type": "Feature",
  "properties": {
    "gn:admin1_code":"12.0",
    "gn:asciiname":"Yerdy-Chu",
    "gn:country_code":"RU",
    "gn:dem":2052,
    "gn:feature_class":"P",
    "gn:feature_code":"PPL",
    "gn:name":"Yerdy-Chu",
    "gn:population":0,
    "gn:timezone":"Europe/Moscow",
    "iso:country":"RU",
    "wof:name":"Yerdy-Chu",
    "wof:placetype":"locality"
},
  "geometry": {"coordinates":[45.18667,42.82889],"type":"Point"}
}