{
  "type": "Feature",
  "properties": {
    "gn:admin1_code":"20",
    "gn:asciiname":"Dal'nyaya Zakora",
    "gn:country_code":"RU",
    "gn:dem":449,
    "gn:feature_class":"P",
    "gn:feature_code":"PPL",
    "gn:name":"Dal\u2019nyaya Zakora",
    "gn:population":0,
    "gn:timezone":"Asia/Irkutsk",
    "iso:country":"RU",
    "name:eng_x_preferred":[
        "Dal'nyaya Zakora"
    ],
    "name:nor_x_preferred":[
        "Dalnjaja-Zakora"
    ],
    "name:rus_x_preferred":[
        "\u0414\u0430\u043b\u044c\u043d\u044f\u044f-\u0417\u0430\u043a\u043e\u0440\u0430"
    ],
    "name:rus_x_variant":[
        "\u0414\u0430\u043b\u044c\u043d\u044f\u044f \u0417\u0430\u043a\u043e\u0440\u0430"
    ],
    "name:und_x_variant":[
        "Dal\u2019nezakora",
        "Dal\u2019nezakorskaya",
        "Dal\u2019nyaya Zakora"
    ],
    "wof:name":"Dal'nyaya Zakora",
    "wof:placetype":"locality"
},
  "geometry": {"coordinates":[104.72709999999999,54.6553],"type":"Point"}
}