{
  "type": "Feature",
  "properties": {
    "gn:admin1_code":"30",
    "gn:asciiname":"Mul'ki",
    "gn:country_code":"RU",
    "gn:dem":5,
    "gn:feature_class":"P",
    "gn:feature_code":"PPL",
    "gn:name":"Mul\u2019ki",
    "gn:population":0,
    "gn:timezone":"Asia/Vladivostok",
    "iso:country":"RU",
    "name:rus_x_preferred":[
        "\u041c\u0443\u043b\u044c\u043a\u0438"
    ],
    "name:und_x_variant":[
        "Mul\u2019ki",
        "\u041c\u0443\u043b\u044c\u043a\u0438"
    ],
    "wof:name":"Mul'ki",
    "wof:placetype":"locality"
},
  "geometry": {"coordinates":[140.41666999999998,51.85],"type":"Point"}
}