{
  "type": "Feature",
  "properties": {
    "gn:admin1_code":"41",
    "gn:asciiname":"Verkhne-Ol'khovatoye",
    "gn:country_code":"RU",
    "gn:dem":193,
    "gn:feature_class":"P",
    "gn:feature_code":"PPL",
    "gn:name":"Verkhne-Ol\u2019khovatoye",
    "gn:population":0,
    "gn:timezone":"Europe/Moscow",
    "iso:country":"RU",
    "name:und_x_variant":[
        "Verkhneye Ol\u2019khovatoye",
        "Verkhne-Ol\u2019khovatoye"
    ],
    "wof:name":"Verkhne-Ol'khovatoye",
    "wof:placetype":"locality"
},
  "geometry": {"coordinates":[36.99606,51.99479],"type":"Point"}
}