{
  "type": "Feature",
  "properties": {
    "gn:admin1_code":"51",
    "gn:asciiname":"Malyy Maydan",
    "gn:country_code":"RU",
    "gn:dem":111,
    "gn:feature_class":"P",
    "gn:feature_code":"PPL",
    "gn:name":"Malyy Maydan",
    "gn:population":0,
    "gn:timezone":"Europe/Moscow",
    "iso:country":"RU",
    "name:rus_x_preferred":[
        "\u041c\u0430\u043b\u044b\u0439 \u041c\u0430\u0439\u0434\u0430\u043d"
    ],
    "wof:name":"Malyy Maydan",
    "wof:placetype":"locality"
},
  "geometry": {"coordinates":[42.9864,54.8137],"type":"Point"}
}