{
  "type": "Feature",
  "properties": {
    "gn:admin1_code":"60",
    "gn:asciiname":"Alyablevo",
    "gn:country_code":"RU",
    "gn:dem":157,
    "gn:feature_class":"P",
    "gn:feature_code":"PPL",
    "gn:name":"Alyablevo",
    "gn:population":0,
    "gn:timezone":"Europe/Moscow",
    "iso:country":"RU",
    "name:rus_x_preferred":[
        "\u0410\u043b\u044f\u0431\u043b\u0435\u0432\u043e"
    ],
    "wof:name":"Alyablevo",
    "wof:placetype":"locality"
},
  "geometry": {"coordinates":[29.8286,56.0106],"type":"Point"}
}