{
  "type": "Feature",
  "properties": {
    "gn:admin1_code":"33",
    "gn:asciiname":"Sludka",
    "gn:country_code":"RU",
    "gn:dem":112,
    "gn:feature_class":"P",
    "gn:feature_code":"PPL",
    "gn:name":"Sludka",
    "gn:population":0,
    "gn:timezone":"Europe/Kirov",
    "iso:country":"RU",
    "name:che_x_preferred":[
        "\u0421\u043b\u0443\u0434\u043a\u0430"
    ],
    "name:chv_x_preferred":[
        "\u0421\u043b\u0443\u0434\u043a\u0430"
    ],
    "name:eng_x_preferred":[
        "Sludka"
    ],
    "name:nor_x_preferred":[
        "Sludka"
    ],
    "name:rus_x_preferred":[
        "\u0421\u043b\u0443\u0434\u043a\u0430"
    ],
    "name:tat_x_preferred":[
        "\u0421\u043b\u0443\u0434\u043a\u0430"
    ],
    "name:und_x_variant":[
        "\u0421\u043b\u0443\u0434\u043a\u0430",
        "Sludka"
    ],
    "wof:name":"Sludka",
    "wof:placetype":"locality"
},
  "geometry": {"coordinates":[50.29845,57.72156999999999],"type":"Point"}
}