{
  "type": "Feature",
  "properties": {
    "gn:admin1_code":"15",
    "gn:asciiname":"Chechen",
    "gn:cc2":"RU",
    "gn:country_code":"RU",
    "gn:dem":361,
    "gn:feature_class":"P",
    "gn:feature_code":"PPL",
    "gn:name":"Chechen",
    "gn:population":0,
    "gn:timezone":"Asia/Anadyr",
    "iso:country":"RU",
    "name:deu_x_preferred":[
        "Tschetschenisch"
    ],
    "name:fin_x_preferred":[
        "T\u0161et\u0161eeni"
    ],
    "name:nor_x_preferred":[
        "Tsjetsjen"
    ],
    "name:oss_x_preferred":[
        "\u0426\u00e6\u0446\u00e6\u0439\u043d\u0430\u0433"
    ],
    "name:rus_x_preferred":[
        "\u0427\u0435\u0447\u0435\u043d"
    ],
    "name:und_x_variant":[
        "Chenchen",
        "Chechin",
        "Chechen"
    ],
    "wof:name":"Chechen",
    "wof:placetype":"locality"
},
  "geometry": {"coordinates":[-172.84999999999999,64.36667],"type":"Point"}
}