{
  "type": "Feature",
  "properties": {
    "gn:admin1_code":"25",
    "gn:asciiname":"Mokryye Dvory",
    "gn:country_code":"RU",
    "gn:dem":167,
    "gn:feature_class":"P",
    "gn:feature_code":"PPL",
    "gn:name":"Mokryye Dvory",
    "gn:population":0,
    "gn:timezone":"Europe/Moscow",
    "iso:country":"RU",
    "name:rus_x_preferred":[
        "\u041c\u043e\u043a\u0440\u044b\u0435 \u0414\u0432\u043e\u0440\u044b"
    ],
    "name:und_x_variant":[
        "Mokryye Dvoriki",
        "Mokryye Dvory"
    ],
    "wof:name":"Mokryye Dvory",
    "wof:placetype":"locality"
},
  "geometry": {"coordinates":[35.25654,53.53678000000001],"type":"Point"}
}