{
  "type": "Feature",
  "properties": {
    "gn:admin1_code":"10",
    "gn:asciiname":"Borshchovka",
    "gn:country_code":"RU",
    "gn:dem":150,
    "gn:feature_class":"P",
    "gn:feature_code":"PPL",
    "gn:name":"Borshchovka",
    "gn:population":0,
    "gn:timezone":"Europe/Moscow",
    "iso:country":"RU",
    "name:rus_x_preferred":[
        "\u0411\u043e\u0440\u0449\u043e\u0432\u043a\u0430"
    ],
    "name:und_x_variant":[
        "Borshch\u00ebvka"
    ],
    "wof:name":"Borshchovka",
    "wof:placetype":"locality"
},
  "geometry": {"coordinates":[31.9255,52.6132],"type":"Point"}
}