{
  "type": "Feature",
  "properties": {
    "gn:admin1_code":"77",
    "gn:asciiname":"Konoplino",
    "gn:country_code":"RU",
    "gn:dem":191,
    "gn:feature_class":"P",
    "gn:feature_code":"PPL",
    "gn:name":"Konoplino",
    "gn:population":0,
    "gn:timezone":"Europe/Moscow",
    "iso:country":"RU",
    "name:rus_x_preferred":[
        "\u041a\u043e\u043d\u043e\u043f\u043b\u0438\u043d\u043e"
    ],
    "name:und_x_variant":[
        "\u041a\u043e\u043d\u043e\u043f\u043b\u0438\u043d\u043e"
    ],
    "wof:name":"Konoplino",
    "wof:placetype":"locality"
},
  "geometry": {"coordinates":[36.2898,58.1951],"type":"Point"}
}