{
  "type": "Feature",
  "properties": {
    "gn:admin1_code":"47",
    "gn:asciiname":"Ivoylovo",
    "gn:country_code":"RU",
    "gn:dem":202,
    "gn:feature_class":"P",
    "gn:feature_code":"PPL",
    "gn:name":"Ivoylovo",
    "gn:population":0,
    "gn:timezone":"Europe/Moscow",
    "iso:country":"RU",
    "name:rus_x_preferred":[
        "\u0418\u0432\u043e\u0439\u043b\u043e\u0432\u043e"
    ],
    "wof:name":"Ivoylovo",
    "wof:placetype":"locality"
},
  "geometry": {"coordinates":[36.26709,55.91953],"type":"Point"}
}