{
  "type": "Feature",
  "properties": {
    "gn:admin1_code":"6",
    "gn:asciiname":"Viled'",
    "gn:country_code":"RU",
    "gn:dem":98,
    "gn:feature_class":"P",
    "gn:feature_code":"PPL",
    "gn:name":"Viled\u2019",
    "gn:population":0,
    "gn:timezone":"Europe/Moscow",
    "iso:country":"RU",
    "name:eng_x_preferred":[
        "Viled'"
    ],
    "name:nor_x_preferred":[
        "Viled"
    ],
    "name:rus_x_preferred":[
        "\u0412\u0438\u043b\u0435\u0434\u044c"
    ],
    "name:und_x_variant":[
        "Viled\u2019"
    ],
    "wof:name":"Viled'",
    "wof:placetype":"locality"
},
  "geometry": {"coordinates":[47.52055,61.3069],"type":"Point"}
}