{
  "type": "Feature",
  "properties": {
    "gn:admin1_code":"76",
    "gn:asciiname":"Bibikovo",
    "gn:country_code":"RU",
    "gn:dem":229,
    "gn:feature_class":"P",
    "gn:feature_code":"PPL",
    "gn:name":"Bibikovo",
    "gn:population":0,
    "gn:timezone":"Europe/Moscow",
    "iso:country":"RU",
    "name:rus_x_preferred":[
        "\u0411\u0438\u0431\u0438\u043a\u043e\u0432\u043e"
    ],
    "name:und_x_variant":[
        "\u0411\u0438\u0431\u0438\u043a\u043e\u0432\u043e"
    ],
    "wof:name":"Bibikovo",
    "wof:placetype":"locality"
},
  "geometry": {"coordinates":[38.15055,53.95577],"type":"Point"}
}