{
  "type": "Feature",
  "properties": {
    "gn:admin1_code":"8",
    "gn:asciiname":"Umetbayevo",
    "gn:country_code":"RU",
    "gn:dem":464,
    "gn:feature_class":"P",
    "gn:feature_code":"PPL",
    "gn:name":"Umetbayevo",
    "gn:population":0,
    "gn:timezone":"Asia/Yekaterinburg",
    "iso:country":"RU",
    "name:aze_x_preferred":[
        "\u00d6t\u00f6mbay"
    ],
    "name:bak_x_preferred":[
        "\u04e8\u043c\u04e9\u0442\u0431\u0430\u0439"
    ],
    "name:che_x_preferred":[
        "\u0423\u043c\u0435\u0442\u0431\u0430\u0435\u0432\u043e"
    ],
    "name:eng_x_preferred":[
        "Umetbayevo"
    ],
    "name:hye_x_preferred":[
        "\u0548\u0582\u0574\u0565\u057f\u0562\u0561\u0587\u0578"
    ],
    "name:kaz_x_preferred":[
        "\u0423\u043c\u0435\u0442\u0431\u0430"
    ],
    "name:kir_x_preferred":[
        "\u0423\u043c\u0435\u0442\u0431\u0430"
    ],
    "name:nor_x_preferred":[
        "Umetbajevo"
    ],
    "name:rus_x_preferred":[
        "\u0423\u043c\u0435\u0442\u0431\u0430\u0435\u0432\u043e"
    ],
    "name:tat_x_preferred":[
        "\u04e8\u043c\u0435\u0442\u0431\u0430\u0439"
    ],
    "name:ukr_x_preferred":[
        "\u0423\u043c\u0435\u0442\u0431\u0430\u0454\u0432\u043e"
    ],
    "name:und_x_variant":[
        "Umitbayeva",
        "Umetbayeva",
        "Umetbayevo"
    ],
    "wof:name":"Umetbayevo",
    "wof:placetype":"locality"
},
  "geometry": {"coordinates":[57.2504,53.7181],"type":"Point"}
}