{
  "type": "Feature",
  "properties": {
    "gn:admin1_code":"8",
    "gn:asciiname":"Igenche",
    "gn:country_code":"RU",
    "gn:dem":212,
    "gn:feature_class":"P",
    "gn:feature_code":"PPL",
    "gn:name":"Igenche",
    "gn:population":0,
    "gn:timezone":"Asia/Yekaterinburg",
    "iso:country":"RU",
    "name:bak_x_preferred":[
        "\u0418\u0433\u0435\u043d\u0441\u0435"
    ],
    "name:che_x_preferred":[
        "\u0418\u0433\u0435\u043d\u0447\u0435"
    ],
    "name:hye_x_preferred":[
        "\u053b\u0563\u0565\u0576\u0579\u0565"
    ],
    "name:kat_x_preferred":[
        "\u10d8\u10d2\u10d4\u10dc\u10e9\u10d4"
    ],
    "name:kaz_x_preferred":[
        "\u0418\u0433\u0435\u043d\u0447\u0435"
    ],
    "name:kir_x_preferred":[
        "\u0418\u0433\u0435\u043d\u0447\u0435"
    ],
    "name:rus_x_preferred":[
        "\u0418\u0433\u0435\u043d\u0447\u0435"
    ],
    "name:tat_x_preferred":[
        "\u0418\u0433\u0435\u043d\u0447\u0435"
    ],
    "name:ukr_x_preferred":[
        "\u0406\u0433\u0435\u043d\u0447\u0435"
    ],
    "wof:name":"Igenche",
    "wof:placetype":"locality"
},
  "geometry": {"coordinates":[55.61738,53.98317],"type":"Point"}
}