{
  "type": "Feature",
  "properties": {
    "gn:admin1_code":"47.0",
    "gn:asciiname":"Brevnovo",
    "gn:country_code":"RU",
    "gn:dem":219,
    "gn:feature_class":"P",
    "gn:feature_code":"PPL",
    "gn:name":"Brevnovo",
    "gn:population":0,
    "gn:timezone":"Europe/Moscow",
    "iso:country":"RU",
    "name:rus_x_preferred":[
        "\u0411\u0440\u0435\u0432\u043d\u043e\u0432\u043e"
    ],
    "wof:name":"Brevnovo",
    "wof:placetype":"locality"
},
  "geometry": {"coordinates":[38.21667,56.21666999999999],"type":"Point"}
}