{
  "type": "Feature",
  "properties": {
    "gn:admin1_code":"86.0",
    "gn:asciiname":"Loshchina",
    "gn:country_code":"RU",
    "gn:dem":78,
    "gn:feature_class":"P",
    "gn:feature_code":"PPL",
    "gn:name":"Loshchina",
    "gn:population":0,
    "gn:timezone":"Europe/Moscow",
    "iso:country":"RU",
    "name:rus_x_preferred":[
        "\u041b\u043e\u0449\u0438\u043d\u0430"
    ],
    "wof:name":"Loshchina",
    "wof:placetype":"locality"
},
  "geometry": {"coordinates":[39.89447,50.13552],"type":"Point"}
}