{
  "type": "Feature",
  "properties": {
    "gn:admin1_code":"91",
    "gn:asciiname":"Zaledeyevo",
    "gn:country_code":"RU",
    "gn:dem":84,
    "gn:feature_class":"P",
    "gn:feature_code":"PPL",
    "gn:name":"Zaledeyevo",
    "gn:population":0,
    "gn:timezone":"Asia/Krasnoyarsk",
    "iso:country":"RU",
    "name:rus_x_preferred":[
        "\u0417\u0430\u043b\u0435\u0434\u0435\u0435\u0432\u043e"
    ],
    "name:und_x_variant":[
        "Zalideyeva",
        "Zeledeyeva",
        "Zaledeyevo"
    ],
    "wof:name":"Zaledeyevo",
    "wof:placetype":"locality"
},
  "geometry": {"coordinates":[92.2933,58.468],"type":"Point"}
}