{
  "type": "Feature",
  "properties": {
    "gn:admin1_code":"47",
    "gn:asciiname":"Ryukhovskoye",
    "gn:country_code":"RU",
    "gn:dem":240,
    "gn:feature_class":"P",
    "gn:feature_code":"PPL",
    "gn:name":"Ryukhovskoye",
    "gn:population":0,
    "gn:timezone":"Europe/Moscow",
    "iso:country":"RU",
    "name:rus_x_preferred":[
        "\u0420\u044e\u0445\u043e\u0432\u0441\u043a\u043e\u0435"
    ],
    "wof:name":"Ryukhovskoye",
    "wof:placetype":"locality"
},
  "geometry": {"coordinates":[35.91102,55.95117],"type":"Point"}
}