{
  "type": "Feature",
  "properties": {
    "gn:admin1_code":"8",
    "gn:asciiname":"Tenyayevo",
    "gn:country_code":"RU",
    "gn:dem":347,
    "gn:feature_class":"P",
    "gn:feature_code":"PPL",
    "gn:name":"Tenyayevo",
    "gn:population":0,
    "gn:timezone":"Asia/Yekaterinburg",
    "iso:country":"RU",
    "name:eng_x_preferred":[
        "Tenyayevo"
    ],
    "name:nor_x_preferred":[
        "Tenjaevo"
    ],
    "name:rus_x_preferred":[
        "\u0422\u0435\u043d\u044f\u0435\u0432\u043e"
    ],
    "name:und_x_variant":[
        "Tonyayevo",
        "Tenyayevo"
    ],
    "wof:name":"Tenyayevo",
    "wof:placetype":"locality"
},
  "geometry": {"coordinates":[55.1044,53.2217],"type":"Point"}
}