{
  "type": "Feature",
  "properties": {
    "gn:admin1_code":"90",
    "gn:asciiname":"Verkhnyaya Pikhtovka",
    "gn:cc2":"RU",
    "gn:country_code":"RU",
    "gn:dem":252,
    "gn:feature_class":"P",
    "gn:feature_code":"PPL",
    "gn:name":"Verkhnyaya Pikhtovka",
    "gn:population":0,
    "gn:timezone":"Asia/Yekaterinburg",
    "iso:country":"RU",
    "name:und_x_variant":[
        "Verkhne-Pikhtovka"
    ],
    "wof:name":"Verkhnyaya Pikhtovka",
    "wof:placetype":"locality"
},
  "geometry": {"coordinates":[54.05,59.15],"type":"Point"}
}