{
  "type": "Feature",
  "properties": {
    "gn:admin1_code":"33",
    "gn:asciiname":"Shchetniki",
    "gn:country_code":"RU",
    "gn:dem":165,
    "gn:feature_class":"P",
    "gn:feature_code":"PPL",
    "gn:name":"Shchetniki",
    "gn:population":0,
    "gn:timezone":"Europe/Kirov",
    "iso:country":"RU",
    "name:rus_x_preferred":[
        "\u0429\u0435\u0442\u043d\u0438\u043a\u0438"
    ],
    "wof:name":"Shchetniki",
    "wof:placetype":"locality"
},
  "geometry": {"coordinates":[49.5427,58.5151],"type":"Point"}
}