{
  "type": "Feature",
  "properties": {
    "gn:admin1_code":"81",
    "gn:asciiname":"Startsev",
    "gn:country_code":"RU",
    "gn:dem":265,
    "gn:feature_class":"P",
    "gn:feature_code":"PPL",
    "gn:name":"Startsev",
    "gn:population":0,
    "gn:timezone":"Europe/Ulyanovsk",
    "iso:country":"RU",
    "name:rus_x_preferred":[
        "\u0421\u0442\u0430\u0440\u0446\u0435\u0432"
    ],
    "name:und_x_variant":[
        "\u0421\u0442\u0430\u0440\u0446\u0435\u0432"
    ],
    "wof:name":"Startsev",
    "wof:placetype":"locality"
},
  "geometry": {"coordinates":[47.5928,54.1197],"type":"Point"}
}