{
  "type": "Feature",
  "properties": {
    "gn:country":"RU",
    "gn:fcode":"PPL",
    "gn:population":0,
    "iso:country":"RU",
    "name:nor_x_preferred":[
        "Rezvan"
    ],
    "name:rus_x_preferred":[
        "\u0420\u0435\u0437\u0432\u0430\u043d\u044c"
    ],
    "name:und_x_variant":[
        "Rezvan\u2019"
    ],
    "qs:name":"Rezvan'",
    "qs:name_adm0":"Russia",
    "qs:name_adm1":"Kaluga Oblast",
    "qs:photos":15,
    "qs:photos_1k":3,
    "qs:photos_9k":1,
    "qs:photos_9r":1,
    "qs:photos_all":15,
    "qs:photos_sr":1,
    "qs:placetype":"Town",
    "qs:pop_sr":"0",
    "wof:name":"Rezvan'",
    "wof:placetype":"locality",
    "wof:population":0
},
  "geometry": {"coordinates":[36.10442,54.52866],"type":"Point"}
}