{
  "type": "Feature",
  "properties": {
    "gn:admin1_code":"6",
    "gn:asciiname":"Rakhtino",
    "gn:country_code":"RU",
    "gn:dem":72,
    "gn:feature_class":"P",
    "gn:feature_code":"PPL",
    "gn:name":"Rakhtino",
    "gn:population":0,
    "gn:timezone":"Europe/Moscow",
    "iso:country":"RU",
    "name:rus_x_preferred":[
        "\u0420\u0430\u0445\u0442\u0438\u043d\u043e"
    ],
    "name:und_x_variant":[
        "\u0420\u0430\u0445\u0442\u0438\u043d\u043e"
    ],
    "wof:name":"Rakhtino",
    "wof:placetype":"locality"
},
  "geometry": {"coordinates":[39.59298,62.35859],"type":"Point"}
}