{
  "type": "Feature",
  "properties": {
    "gn:admin1_code":"47",
    "gn:asciiname":"Titovo",
    "gn:cc2":"RU",
    "gn:country_code":"RU",
    "gn:dem":195,
    "gn:feature_class":"P",
    "gn:feature_code":"PPL",
    "gn:name":"Titovo",
    "gn:population":0,
    "gn:timezone":"Europe/Moscow",
    "iso:country":"RU",
    "name:und_x_variant":[
        "Bol\u2019shoye Titovo",
        "Titovo"
    ],
    "wof:name":"Titovo",
    "wof:placetype":"locality"
},
  "geometry": {"coordinates":[37.15,56.25],"type":"Point"}
}