{
  "type": "Feature",
  "properties": {
    "gn:admin1_code":"63",
    "gn:asciiname":"Shanskoye",
    "gn:country_code":"RU",
    "gn:dem":9,
    "gn:feature_class":"P",
    "gn:feature_code":"PPL",
    "gn:name":"Shanskoye",
    "gn:population":0,
    "gn:timezone":"Asia/Magadan",
    "iso:country":"RU",
    "name:rus_x_preferred":[
        "\u0428\u0430\u043d\u0441\u043a\u043e\u0435"
    ],
    "name:und_x_variant":[
        "\u0428\u0430\u043d\u0441\u043a\u043e\u0435"
    ],
    "wof:name":"Shanskoye",
    "wof:placetype":"locality"
},
  "geometry": {"coordinates":[147.41666999999995,70.11667],"type":"Point"}
}