{
  "type": "Feature",
  "properties": {
    "gn:admin1_code":"42",
    "gn:asciiname":"Kissulovo",
    "gn:country_code":"RU",
    "gn:dem":52,
    "gn:feature_class":"P",
    "gn:feature_code":"PPL",
    "gn:name":"Kissulovo",
    "gn:population":0,
    "gn:timezone":"Europe/Moscow",
    "iso:country":"RU",
    "name:rus_x_preferred":[
        "\u041a\u0438\u0441\u0441\u0443\u043b\u043e\u0432\u043e"
    ],
    "name:und_x_variant":[
        "\u041a\u0438\u0441\u0441\u0443\u043b\u043e\u0432\u043e"
    ],
    "wof:name":"Kissulovo",
    "wof:placetype":"locality"
},
  "geometry": {"coordinates":[30.36667000000001,60.21666999999999],"type":"Point"}
}