{
  "type": "Feature",
  "properties": {
    "gn:admin1_code":"47",
    "gn:asciiname":"Psotino",
    "gn:country_code":"RU",
    "gn:dem":108,
    "gn:feature_class":"P",
    "gn:feature_code":"PPL",
    "gn:name":"Psotino",
    "gn:population":0,
    "gn:timezone":"Europe/Moscow",
    "iso:country":"RU",
    "name:rus_x_preferred":[
        "\u041f\u0441\u043e\u0442\u0438\u043d\u043e"
    ],
    "name:und_x_variant":[
        "\u041f\u0441\u043e\u0442\u0438\u043d\u043e"
    ],
    "wof:name":"Psotino",
    "wof:placetype":"locality"
},
  "geometry": {"coordinates":[39.19201,54.96815],"type":"Point"}
}