{
  "type": "Feature",
  "properties": {
    "gn:admin1_code":"78",
    "gn:asciiname":"Glubokaya",
    "gn:country_code":"RU",
    "gn:dem":128,
    "gn:feature_class":"P",
    "gn:feature_code":"PPL",
    "gn:name":"Glubokaya",
    "gn:population":0,
    "gn:timezone":"Asia/Yekaterinburg",
    "iso:country":"RU",
    "name:eng_x_preferred":[
        "Glubokaya"
    ],
    "name:nor_x_preferred":[
        "Glubokaja"
    ],
    "name:rus_x_preferred":[
        "\u0413\u043b\u0443\u0431\u043e\u043a\u0430\u044f"
    ],
    "wof:name":"Glubokaya",
    "wof:placetype":"locality"
},
  "geometry": {"coordinates":[68.18621,56.44866999999999],"type":"Point"}
}