{
  "type": "Feature",
  "properties": {
    "gn:admin1_code":"85",
    "gn:asciiname":"Zakhar'ino",
    "gn:country_code":"RU",
    "gn:dem":193,
    "gn:feature_class":"P",
    "gn:feature_code":"PPL",
    "gn:name":"Zakhar\u2019ino",
    "gn:population":0,
    "gn:timezone":"Europe/Moscow",
    "iso:country":"RU",
    "name:rus_x_preferred":[
        "\u0417\u0430\u0445\u0430\u0440\u044c\u0438\u043d\u043e"
    ],
    "name:und_x_variant":[
        "Zakhar\u2019ino",
        "\u0417\u0430\u0445\u0430\u0440\u044c\u0438\u043d\u043e"
    ],
    "wof:name":"Zakhar'ino",
    "wof:placetype":"locality"
},
  "geometry": {"coordinates":[39.042,59.3289],"type":"Point"}
}