{
  "type": "Feature",
  "properties": {
    "gn:admin1_code":"28",
    "gn:asciiname":"Leppyasil'ta",
    "gn:country_code":"RU",
    "gn:dem":11,
    "gn:feature_class":"P",
    "gn:feature_code":"PPL",
    "gn:name":"Leppyasil\u2019ta",
    "gn:population":0,
    "gn:timezone":"Europe/Moscow",
    "iso:country":"RU",
    "name:eng_x_preferred":[
        "Leppyasil'ta"
    ],
    "name:nor_x_preferred":[
        "Leppjasilta"
    ],
    "name:rus_x_preferred":[
        "\u041b\u0435\u043f\u043f\u044f\u0441\u0438\u043b\u0442\u0430"
    ],
    "name:rus_x_variant":[
        "\u041b\u0435\u043f\u043f\u044f\u0441\u0438\u043b\u044c\u0442\u0430"
    ],
    "name:und_x_variant":[
        "Lyappyasilta",
        "Lepp\u00e4silta",
        "Leppyasil\u2019ta",
        "\u041b\u0435\u043f\u043f\u044f\u0441\u0438\u043b\u044c\u0442\u0430"
    ],
    "wof:name":"Leppyasil'ta",
    "wof:placetype":"locality"
},
  "geometry": {"coordinates":[31.26667,61.68333000000001],"type":"Point"}
}