{
  "type": "Feature",
  "properties": {
    "gn:admin1_code":"8",
    "gn:asciiname":"Urnyak",
    "gn:cc2":"RU",
    "gn:country_code":"RU",
    "gn:dem":138,
    "gn:feature_class":"P",
    "gn:feature_code":"PPL",
    "gn:name":"Urnyak",
    "gn:population":0,
    "gn:timezone":"Asia/Yekaterinburg",
    "iso:country":"RU",
    "name:eng_x_preferred":[
        "Urnyak"
    ],
    "name:nor_x_preferred":[
        "Urnjak"
    ],
    "name:rus_x_preferred":[
        "\u0423\u0440\u043d\u044f\u043a"
    ],
    "name:und_x_variant":[
        "Urnyakovo"
    ],
    "wof:name":"Urnyak",
    "wof:placetype":"locality"
},
  "geometry": {"coordinates":[54.76416999999999,55.02833],"type":"Point"}
}