{
  "type": "Feature",
  "properties": {
    "gn:admin1_code":"13",
    "gn:asciiname":"Kalininskiy",
    "gn:country_code":"RU",
    "gn:dem":363,
    "gn:feature_class":"P",
    "gn:feature_code":"PPL",
    "gn:name":"Kalininskiy",
    "gn:population":0,
    "gn:timezone":"Asia/Yekaterinburg",
    "iso:country":"RU",
    "name:eng_x_preferred":[
        "Kalininskiy"
    ],
    "name:nor_x_preferred":[
        "Kalininskij"
    ],
    "name:rus_x_preferred":[
        "\u041a\u0430\u043b\u0438\u043d\u0438\u043d\u0441\u043a\u0438\u0439"
    ],
    "wof:name":"Kalininskiy",
    "wof:placetype":"locality"
},
  "geometry": {"coordinates":[59.6925,52.51139000000001],"type":"Point"}
}