{
  "type": "Feature",
  "properties": {
    "gn:admin1_code":"88",
    "gn:asciiname":"Berlyukovo",
    "gn:country_code":"RU",
    "gn:dem":179,
    "gn:feature_class":"P",
    "gn:feature_code":"PPL",
    "gn:name":"Berlyukovo",
    "gn:population":0,
    "gn:timezone":"Europe/Moscow",
    "iso:country":"RU",
    "name:rus_x_preferred":[
        "\u0411\u0435\u0440\u043b\u044e\u043a\u043e\u0432\u043e"
    ],
    "wof:name":"Berlyukovo",
    "wof:placetype":"locality"
},
  "geometry": {"coordinates":[39.41545,57.43372],"type":"Point"}
}