{
  "type": "Feature",
  "properties": {
    "gn:admin1_code":"61.0",
    "gn:asciiname":"Kozyrev",
    "gn:country_code":"RU",
    "gn:dem":137,
    "gn:feature_class":"P",
    "gn:feature_code":"PPL",
    "gn:name":"Kozyrev",
    "gn:population":0,
    "gn:timezone":"Europe/Moscow",
    "iso:country":"RU",
    "name:rus_x_preferred":[
        "\u041a\u043e\u0437\u044b\u0440\u0435\u0432"
    ],
    "name:und_x_variant":[
        "\u041a\u043e\u0437\u044b\u0440\u0435\u0432"
    ],
    "wof:name":"Kozyrev",
    "wof:placetype":"locality"
},
  "geometry": {"coordinates":[40.12027,49.07243],"type":"Point"}
}