{
  "type": "Feature",
  "properties": {
    "iso:country":"RU",
    "qs:name":"Pavel'tsevo",
    "qs:name_adm0":"Russia",
    "qs:name_adm1":"Moscow Oblast",
    "qs:photos":8,
    "qs:photos_1k":2,
    "qs:photos_9k":1,
    "qs:photos_9r":1,
    "qs:photos_all":8,
    "qs:photos_sr":1,
    "qs:placetype":"Town",
    "qs:pop_sr":"0",
    "wof:name":"Pavel'tsevo",
    "wof:placetype":"locality"
},
  "geometry": {"coordinates":[37.49936,55.9701265],"type":"Point"}
}