{
  "type": "Feature",
  "properties": {
    "gn:admin1_code":"9",
    "gn:asciiname":"Ostapovka",
    "gn:country_code":"RU",
    "gn:dem":205,
    "gn:feature_class":"P",
    "gn:feature_code":"PPL",
    "gn:name":"Ostapovka",
    "gn:population":0,
    "gn:timezone":"Europe/Moscow",
    "iso:country":"RU",
    "name:rus_x_preferred":[
        "\u041e\u0441\u0442\u0430\u043f\u043e\u0432\u043a\u0430"
    ],
    "name:und_x_variant":[
        "\u041e\u0441\u0442\u0430\u043f\u043e\u0432\u043a\u0430"
    ],
    "wof:name":"Ostapovka",
    "wof:placetype":"locality"
},
  "geometry": {"coordinates":[37.5155,50.6489],"type":"Point"}
}