{
  "type": "Feature",
  "properties": {
    "gn:admin1_code":"77",
    "gn:asciiname":"Pankratovo",
    "gn:country_code":"RU",
    "gn:dem":176,
    "gn:feature_class":"P",
    "gn:feature_code":"PPL",
    "gn:name":"Pankratovo",
    "gn:population":0,
    "gn:timezone":"Europe/Moscow",
    "iso:country":"RU",
    "name:rus_x_preferred":[
        "\u041f\u0430\u043d\u043a\u0440\u0430\u0442\u043e\u0432\u043e"
    ],
    "wof:name":"Pankratovo",
    "wof:placetype":"locality"
},
  "geometry": {"coordinates":[37.0702,57.4021],"type":"Point"}
}