{
  "type": "Feature",
  "properties": {
    "gn:admin1_code":"32",
    "gn:asciiname":"Pashiya",
    "gn:country_code":"RU",
    "gn:dem":48,
    "gn:feature_class":"P",
    "gn:feature_code":"PPL",
    "gn:name":"Pashiya",
    "gn:population":0,
    "gn:timezone":"Asia/Yekaterinburg",
    "iso:country":"RU",
    "name:bul_x_preferred":[
        "\u041f\u0430\u0448\u0438\u044f"
    ],
    "name:che_x_preferred":[
        "\u041f\u0430\u0448\u0438\u044f"
    ],
    "name:hye_x_preferred":[
        "\u054a\u0561\u0577\u056b\u0575\u0561"
    ],
    "name:rus_x_preferred":[
        "\u041f\u0430\u0448\u0438\u044f"
    ],
    "wof:name":"Pashiya",
    "wof:placetype":"locality"
},
  "geometry": {"coordinates":[65.63467,59.67862],"type":"Point"}
}