{
  "type": "Feature",
  "properties": {
    "gn:admin1_code":"45",
    "gn:asciiname":"Mamasevo",
    "gn:country_code":"RU",
    "gn:dem":100,
    "gn:feature_class":"P",
    "gn:feature_code":"PPL",
    "gn:name":"Mamasevo",
    "gn:population":0,
    "gn:timezone":"Europe/Moscow",
    "iso:country":"RU",
    "name:rus_x_preferred":[
        "\u041c\u0430\u043c\u0430\u0441\u0435\u0432\u043e"
    ],
    "wof:name":"Mamasevo",
    "wof:placetype":"locality"
},
  "geometry": {"coordinates":[48.3486,55.9043],"type":"Point"}
}