{
  "type": "Feature",
  "properties": {
    "gn:admin1_code":"63",
    "gn:asciiname":"Chukrop",
    "gn:country_code":"RU",
    "gn:dem":57,
    "gn:feature_class":"P",
    "gn:feature_code":"PPL",
    "gn:name":"Chukrop",
    "gn:population":0,
    "gn:timezone":"Asia/Magadan",
    "iso:country":"RU",
    "name:rus_x_preferred":[
        "\u0427\u0443\u043a\u0440\u043e\u043f"
    ],
    "wof:name":"Chukrop",
    "wof:placetype":"locality"
},
  "geometry": {"coordinates":[156.96666999999999,68.78333000000001],"type":"Point"}
}