{
  "type": "Feature",
  "properties": {
    "gn:admin1_code":"90.0",
    "gn:asciiname":"Yelisyata",
    "gn:country_code":"RU",
    "gn:dem":278,
    "gn:feature_class":"P",
    "gn:feature_code":"PPL",
    "gn:name":"Yelisyata",
    "gn:population":0,
    "gn:timezone":"Asia/Yekaterinburg",
    "iso:country":"RU",
    "name:rus_x_preferred":[
        "\u0415\u043b\u0438\u0441\u044f\u0442\u0430"
    ],
    "wof:name":"Yelisyata",
    "wof:placetype":"locality"
},
  "geometry": {"coordinates":[55.8908,58.3298],"type":"Point"}
}