{
  "type": "Feature",
  "properties": {
    "gn:admin1_code":"21.0",
    "gn:asciiname":"Ploskiryata",
    "gn:country_code":"RU",
    "gn:dem":113,
    "gn:feature_class":"P",
    "gn:feature_code":"PPL",
    "gn:name":"Ploskiryata",
    "gn:population":0,
    "gn:timezone":"Europe/Moscow",
    "iso:country":"RU",
    "name:nor_x_preferred":[
        "Ploskirjata"
    ],
    "name:rus_x_preferred":[
        "\u041f\u043b\u043e\u0441\u043a\u0438\u0440\u044f\u0442\u0430"
    ],
    "wof:name":"Ploskiryata",
    "wof:placetype":"locality"
},
  "geometry": {"coordinates":[42.59721,56.80366],"type":"Point"}
}