{
  "type": "Feature",
  "properties": {
    "gn:admin1_code":"91.0",
    "gn:asciiname":"Sukhorechenskiy",
    "gn:country_code":"RU",
    "gn:dem":316,
    "gn:feature_class":"P",
    "gn:feature_code":"PPL",
    "gn:name":"Sukhorechenskiy",
    "gn:population":0,
    "gn:timezone":"Asia/Krasnoyarsk",
    "iso:country":"RU",
    "name:rus_x_preferred":[
        "\u0421\u0443\u0445\u043e\u0440\u0435\u0447\u0435\u043d\u0441\u043a\u0438\u0439"
    ],
    "wof:name":"Sukhorechenskiy",
    "wof:placetype":"locality"
},
  "geometry": {"coordinates":[90.08528,55.59306],"type":"Point"}
}