{
  "type": "Feature",
  "properties": {
    "gn:admin1_code":"43",
    "gn:asciiname":"Zarya",
    "gn:country_code":"RU",
    "gn:dem":145,
    "gn:feature_class":"P",
    "gn:feature_code":"PPL",
    "gn:name":"Zarya",
    "gn:population":0,
    "gn:timezone":"Europe/Moscow",
    "iso:country":"RU",
    "name:ara_x_preferred":[
        "\u0632\u0627\u0631\u064a\u0627"
    ],
    "name:bul_x_preferred":[
        "\u0417\u0430\u0440\u044f"
    ],
    "name:cat_x_preferred":[
        "Zari\u00e0"
    ],
    "name:ces_x_preferred":[
        "Zarja"
    ],
    "name:dan_x_preferred":[
        "Zarja"
    ],
    "name:deu_x_preferred":[
        "Sarja"
    ],
    "name:fas_x_preferred":[
        "\u0632\u0627\u0631\u06cc\u0627"
    ],
    "name:fin_x_preferred":[
        "Zarya"
    ],
    "name:fra_x_preferred":[
        "Zarya"
    ],
    "name:hun_x_preferred":[
        "Zarja"
    ],
    "name:ind_x_preferred":[
        "Zarya"
    ],
    "name:ita_x_preferred":[
        "Zarja"
    ],
    "name:jpn_x_preferred":[
        "\u30b6\u30fc\u30ea\u30e3"
    ],
    "name:kor_x_preferred":[
        "\uc790\ub7b4 \ubaa8\ub4c8"
    ],
    "name:lat_x_preferred":[
        "Zaria"
    ],
    "name:lav_x_preferred":[
        "Zarja"
    ],
    "name:lit_x_preferred":[
        "Zaria"
    ],
    "name:ltz_x_preferred":[
        "Sarja"
    ],
    "name:msa_x_preferred":[
        "Zarya"
    ],
    "name:nor_x_preferred":[
        "Zarja"
    ],
    "name:pol_x_preferred":[
        "Zaria"
    ],
    "name:por_x_preferred":[
        "Zarya"
    ],
    "name:rus_x_preferred":[
        "\u0417\u0430\u0440\u044f"
    ],
    "name:slk_x_preferred":[
        "Zaria"
    ],
    "name:spa_x_preferred":[
        "Zary\u00e1"
    ],
    "name:srp_x_preferred":[
        "\u0417\u0430\u0440\u0458\u0430"
    ],
    "name:swe_x_preferred":[
        "Zarja"
    ],
    "name:tam_x_preferred":[
        "\u0b9a\u0bb0\u0bcd\u0baf\u0bbe"
    ],
    "name:tha_x_preferred":[
        "\u0e0b\u0e32\u0e23\u0e4c\u0e22\u0e32"
    ],
    "name:ukr_x_preferred":[
        "\u0417\u0430\u0440\u044f"
    ],
    "name:vie_x_preferred":[
        "Zarya"
    ],
    "name:zho_x_preferred":[
        "\u66d9\u5149\u865f\u529f\u80fd\u8ca8\u8259"
    ],
    "wof:name":"Zarya",
    "wof:placetype":"locality"
},
  "geometry": {"coordinates":[40.3805,52.15600000000001],"type":"Point"}
}