{
  "type": "Feature",
  "properties": {
    "gn:admin1_code":"54",
    "gn:asciiname":"Kamyshino",
    "gn:country_code":"RU",
    "gn:dem":87,
    "gn:feature_class":"P",
    "gn:feature_code":"PPL",
    "gn:name":"Kamyshino",
    "gn:population":0,
    "gn:timezone":"Asia/Omsk",
    "iso:country":"RU",
    "name:eng_x_preferred":[
        "Kamyshino"
    ],
    "name:nor_x_preferred":[
        "Kamysjino"
    ],
    "name:rus_x_preferred":[
        "\u041a\u0430\u043c\u044b\u0448\u0438\u043d\u043e"
    ],
    "wof:name":"Kamyshino",
    "wof:placetype":"locality"
},
  "geometry": {"coordinates":[73.52483000000002,54.76233000000001],"type":"Point"}
}