{
  "type": "Feature",
  "properties": {
    "gn:admin1_code":"42.0",
    "gn:asciiname":"Bylkinoye",
    "gn:cc2":"RU",
    "gn:country_code":"RU",
    "gn:dem":121,
    "gn:feature_class":"P",
    "gn:feature_code":"PPL",
    "gn:name":"Bylkinoye",
    "gn:population":0,
    "gn:timezone":"Europe/Moscow",
    "iso:country":"RU",
    "name:fin_x_preferred":[
        "Ylentel\u00e4"
    ],
    "name:rus_x_preferred":[
        "\u0411\u044b\u043b\u043a\u0438\u043d\u043e\u0435"
    ],
    "name:und_x_variant":[
        "Yulyantelya",
        "Bylkinoye"
    ],
    "wof:name":"Bylkinoye",
    "wof:placetype":"locality"
},
  "geometry": {"coordinates":[30.02443,60.52123],"type":"Point"}
}