{
  "type": "Feature",
  "properties": {
    "gn:admin1_code":"47.0",
    "gn:asciiname":"Dvoryaninovo",
    "gn:country_code":"RU",
    "gn:dem":146,
    "gn:feature_class":"P",
    "gn:feature_code":"PPL",
    "gn:name":"Dvoryaninovo",
    "gn:population":0,
    "gn:timezone":"Europe/Moscow",
    "iso:country":"RU",
    "name:rus_x_preferred":[
        "\u0414\u0432\u043e\u0440\u044f\u043d\u0438\u043d\u043e\u0432\u043e"
    ],
    "wof:name":"Dvoryaninovo",
    "wof:placetype":"locality"
},
  "geometry": {"coordinates":[38.03333,55.05],"type":"Point"}
}