{
  "type": "Feature",
  "properties": {
    "gn:admin1_code":"62",
    "gn:asciiname":"Neklyudovo",
    "gn:country_code":"RU",
    "gn:dem":128,
    "gn:feature_class":"P",
    "gn:feature_code":"PPL",
    "gn:name":"Neklyudovo",
    "gn:population":0,
    "gn:timezone":"Europe/Moscow",
    "iso:country":"RU",
    "name:rus_x_preferred":[
        "\u041d\u0435\u043a\u043b\u044e\u0434\u043e\u0432\u043e"
    ],
    "wof:name":"Neklyudovo",
    "wof:placetype":"locality"
},
  "geometry": {"coordinates":[41.3078,54.8798],"type":"Point"}
}