{
  "type": "Feature",
  "properties": {
    "gn:admin1_code":"9",
    "gn:asciiname":"Kruchenyy",
    "gn:country_code":"RU",
    "gn:dem":221,
    "gn:feature_class":"P",
    "gn:feature_code":"PPL",
    "gn:name":"Kruchenyy",
    "gn:population":0,
    "gn:timezone":"Europe/Moscow",
    "iso:country":"RU",
    "name:rus_x_preferred":[
        "\u041a\u0440\u0443\u0447\u0435\u043d\u044b\u0439"
    ],
    "name:und_x_variant":[
        "Kruchennyy"
    ],
    "wof:name":"Kruchenyy",
    "wof:placetype":"locality"
},
  "geometry": {"coordinates":[37.18278,50.85592000000001],"type":"Point"}
}