{
  "type": "Feature",
  "properties": {
    "gn:admin1_code":"28",
    "gn:asciiname":"Peldozha",
    "gn:country_code":"RU",
    "gn:dem":100,
    "gn:feature_class":"P",
    "gn:feature_code":"PPL",
    "gn:name":"Peldozha",
    "gn:population":0,
    "gn:timezone":"Europe/Moscow",
    "iso:country":"RU",
    "name:fin_x_preferred":[
        "Peltoinen"
    ],
    "name:rus_x_preferred":[
        "\u041f\u0435\u043b\u0434\u043e\u0436\u0430"
    ],
    "name:und_x_variant":[
        "\u041f\u0435\u043b\u0434\u043e\u0436\u0430"
    ],
    "wof:name":"Peldozha",
    "wof:placetype":"locality"
},
  "geometry": {"coordinates":[33.65203,61.60273000000001],"type":"Point"}
}