{
  "type": "Feature",
  "properties": {
    "gn:admin1_code":"4",
    "gn:asciiname":"Novyy Vostok",
    "gn:cc2":"RU",
    "gn:country_code":"RU",
    "gn:dem":129,
    "gn:feature_class":"P",
    "gn:feature_code":"PPL",
    "gn:name":"Novyy Vostok",
    "gn:population":0,
    "gn:timezone":"Asia/Barnaul",
    "iso:country":"RU",
    "name:eng_x_preferred":[
        "Novyy Vostok"
    ],
    "name:nor_x_preferred":[
        "Novyj Vostok"
    ],
    "name:rus_x_preferred":[
        "\u041d\u043e\u0432\u044b\u0439 \u0412\u043e\u0441\u0442\u043e\u043a"
    ],
    "name:und_x_variant":[
        "Novo-Vostochnyy"
    ],
    "wof:name":"Novyy Vostok",
    "wof:placetype":"locality"
},
  "geometry": {"coordinates":[79.48333000000002,52.36667],"type":"Point"}
}