{
  "type": "Feature",
  "properties": {
    "gn:admin1_code":"41",
    "gn:asciiname":"Ladygina",
    "gn:country_code":"RU",
    "gn:dem":147,
    "gn:feature_class":"P",
    "gn:feature_code":"PPL",
    "gn:name":"Ladygina",
    "gn:population":0,
    "gn:timezone":"Europe/Moscow",
    "iso:country":"RU",
    "name:rus_x_preferred":[
        "\u041b\u0430\u0434\u044b\u0433\u0438\u043d\u0430"
    ],
    "name:und_x_variant":[
        "\u041b\u0430\u0434\u044b\u0433\u0438\u043d\u0430"
    ],
    "wof:name":"Ladygina",
    "wof:placetype":"locality"
},
  "geometry": {"coordinates":[34.7764,51.6994],"type":"Point"}
}