{
  "type": "Feature",
  "properties": {
    "gn:admin1_code":"54",
    "gn:asciiname":"Usyul'gan",
    "gn:country_code":"RU",
    "gn:dem":93,
    "gn:feature_class":"P",
    "gn:feature_code":"PPL",
    "gn:name":"Usyul\u2019gan",
    "gn:population":0,
    "gn:timezone":"Asia/Omsk",
    "iso:country":"RU",
    "name:eng_x_preferred":[
        "Usyul'gan"
    ],
    "name:nor_x_preferred":[
        "Usiulgan"
    ],
    "name:rus_x_preferred":[
        "\u0423\u0441\u044e\u043b\u044c\u0433\u0430\u043d"
    ],
    "name:und_x_variant":[
        "Usyul\u2019gan"
    ],
    "wof:name":"Usyul'gan",
    "wof:placetype":"locality"
},
  "geometry": {"coordinates":[74.03019999999999,57.2704],"type":"Point"}
}