{
  "type": "Feature",
  "properties": {
    "gn:admin1_code":"37",
    "gn:asciiname":"Ileshevo",
    "gn:country_code":"RU",
    "gn:dem":124,
    "gn:feature_class":"P",
    "gn:feature_code":"PPL",
    "gn:name":"Ileshevo",
    "gn:population":300,
    "gn:timezone":"Europe/Moscow",
    "iso:country":"RU",
    "name:rus_x_preferred":[
        "\u0418\u043b\u0435\u0448\u0435\u0432\u043e"
    ],
    "name:und_x_variant":[
        "\u0418\u043b\u0435\u0448\u0435\u0432\u043e"
    ],
    "wof:name":"Ileshevo",
    "wof:placetype":"locality",
    "wof:population":300
},
  "geometry": {"coordinates":[44.12347000000001,58.95331],"type":"Point"}
}