{
  "type": "Feature",
  "properties": {
    "gn:admin1_code":"42",
    "gn:asciiname":"Zhabino",
    "gn:country_code":"RU",
    "gn:dem":9,
    "gn:feature_class":"P",
    "gn:feature_code":"PPL",
    "gn:name":"Zhabino",
    "gn:population":0,
    "gn:timezone":"Europe/Moscow",
    "iso:country":"RU",
    "name:fin_x_preferred":[
        "Saapina"
    ],
    "name:rus_x_preferred":[
        "\u0416\u0430\u0431\u0438\u043d\u043e"
    ],
    "wof:name":"Zhabino",
    "wof:placetype":"locality"
},
  "geometry": {"coordinates":[28.47699,59.42871],"type":"Point"}
}