{
  "type": "Feature",
  "properties": {
    "gn:admin1_code":"37.0",
    "gn:asciiname":"Andriyanovskoye",
    "gn:country_code":"RU",
    "gn:dem":136,
    "gn:feature_class":"P",
    "gn:feature_code":"PPL",
    "gn:name":"Andriyanovskoye",
    "gn:population":0,
    "gn:timezone":"Europe/Moscow",
    "iso:country":"RU",
    "name:und_x_variant":[
        "Andrianovskoye",
        "Andriyanovskoye"
    ],
    "wof:name":"Andriyanovskoye",
    "wof:placetype":"locality"
},
  "geometry": {"coordinates":[41.34628,58.31259],"type":"Point"}
}