{
  "type": "Feature",
  "properties": {
    "gn:admin1_code":"91",
    "gn:asciiname":"Shunery",
    "gn:country_code":"RU",
    "gn:dem":297,
    "gn:feature_class":"P",
    "gn:feature_code":"PPL",
    "gn:name":"Shunery",
    "gn:population":0,
    "gn:timezone":"Asia/Krasnoyarsk",
    "iso:country":"RU",
    "name:eng_x_preferred":[
        "Shunery"
    ],
    "name:nor_x_preferred":[
        "Sjunery"
    ],
    "name:rus_x_preferred":[
        "\u0428\u0443\u043d\u0435\u0440\u044b"
    ],
    "wof:name":"Shunery",
    "wof:placetype":"locality"
},
  "geometry": {"coordinates":[91.58528,53.12833000000001],"type":"Point"}
}