{
  "type": "Feature",
  "properties": {
    "gn:admin1_code":"15",
    "gn:asciiname":"Kurupkan",
    "gn:cc2":"RU",
    "gn:country_code":"RU",
    "gn:dem":25,
    "gn:feature_class":"P",
    "gn:feature_code":"PPL",
    "gn:name":"Kurupkan",
    "gn:population":0,
    "gn:timezone":"Asia/Anadyr",
    "iso:country":"RU",
    "name:rus_x_preferred":[
        "\u041a\u0443\u0440\u0443\u043f\u043a\u0430\u043d"
    ],
    "name:und_x_variant":[
        "Kurupka",
        "Kurupkan"
    ],
    "wof:name":"Kurupkan",
    "wof:placetype":"locality"
},
  "geometry": {"coordinates":[-174.23333,64.66667],"type":"Point"}
}