{
  "type": "Feature",
  "properties": {
    "gn:admin1_code":"76",
    "gn:asciiname":"Isakovo",
    "gn:country_code":"RU",
    "gn:dem":202,
    "gn:feature_class":"P",
    "gn:feature_code":"PPL",
    "gn:name":"Isakovo",
    "gn:population":0,
    "gn:timezone":"Europe/Moscow",
    "iso:country":"RU",
    "name:nor_x_preferred":[
        "Isakovo"
    ],
    "name:rus_x_preferred":[
        "\u0418\u0441\u0430\u043a\u043e\u0432\u043e"
    ],
    "wof:name":"Isakovo",
    "wof:placetype":"locality"
},
  "geometry": {"coordinates":[36.67758,54.27711],"type":"Point"}
}