{
  "type": "Feature",
  "properties": {
    "gn:admin1_code":"21.0",
    "gn:asciiname":"Mit'ka",
    "gn:country_code":"RU",
    "gn:dem":118,
    "gn:feature_class":"P",
    "gn:feature_code":"PPL",
    "gn:name":"Mit\u2019ka",
    "gn:population":0,
    "gn:timezone":"Europe/Moscow",
    "iso:country":"RU",
    "name:nor_x_preferred":[
        "Mitka"
    ],
    "name:rus_x_preferred":[
        "\u041c\u0438\u0442\u044c\u043a\u0430"
    ],
    "name:und_x_variant":[
        "Mit\u2019ka"
    ],
    "wof:name":"Mit'ka",
    "wof:placetype":"locality"
},
  "geometry": {"coordinates":[42.62372,56.66406],"type":"Point"}
}