{
  "type": "Feature",
  "properties": {
    "gn:admin1_code":"10",
    "gn:asciiname":"Sverdlov",
    "gn:country_code":"RU",
    "gn:dem":160,
    "gn:feature_class":"P",
    "gn:feature_code":"PPL",
    "gn:name":"Sverdlov",
    "gn:population":0,
    "gn:timezone":"Europe/Moscow",
    "iso:country":"RU",
    "name:rus_x_preferred":[
        "\u0421\u0432\u0435\u0440\u0434\u043b\u043e\u0432"
    ],
    "name:und_x_variant":[
        "\u0421\u0432\u0435\u0440\u0434\u043b\u043e\u0432"
    ],
    "wof:name":"Sverdlov",
    "wof:placetype":"locality"
},
  "geometry": {"coordinates":[32.4094,52.8561],"type":"Point"}
}