{
  "type": "Feature",
  "properties": {
    "gn:admin1_code":"25",
    "gn:asciiname":"Khotenka",
    "gn:country_code":"RU",
    "gn:dem":210,
    "gn:feature_class":"P",
    "gn:feature_code":"PPL",
    "gn:name":"Khotenka",
    "gn:population":0,
    "gn:timezone":"Europe/Moscow",
    "iso:country":"RU",
    "name:rus_x_preferred":[
        "\u0425\u0430\u0442\u0435\u043d\u043a\u0430"
    ],
    "name:und_x_variant":[
        "Khatenka",
        "Khotenka"
    ],
    "wof:name":"Khotenka",
    "wof:placetype":"locality"
},
  "geometry": {"coordinates":[35.7736,54.11946999999999],"type":"Point"}
}