{
  "type": "Feature",
  "properties": {
    "gn:admin1_code":"20",
    "gn:asciiname":"Kosoy Brod",
    "gn:country_code":"RU",
    "gn:dem":306,
    "gn:feature_class":"P",
    "gn:feature_code":"PPL",
    "gn:name":"Kosoy Brod",
    "gn:population":0,
    "gn:timezone":"Asia/Irkutsk",
    "iso:country":"RU",
    "name:rus_x_preferred":[
        "\u041a\u043e\u0441\u043e\u0439 \u0411\u0440\u043e\u0434"
    ],
    "wof:name":"Kosoy Brod",
    "wof:placetype":"locality"
},
  "geometry": {"coordinates":[98.5702,55.448],"type":"Point"}
}