{
  "type": "Feature",
  "properties": {
    "gn:admin1_code":"64",
    "gn:asciiname":"Pozharskoye",
    "gn:country_code":"RU",
    "gn:dem":82,
    "gn:feature_class":"P",
    "gn:feature_code":"PPL",
    "gn:name":"Pozharskoye",
    "gn:population":0,
    "gn:timezone":"Asia/Sakhalin",
    "iso:country":"RU",
    "name:eng_x_preferred":[
        "Pozharskoye"
    ],
    "name:nor_x_preferred":[
        "Pozjarskoje"
    ],
    "name:rus_x_preferred":[
        "\u041f\u043e\u0436\u0430\u0440\u0441\u043a\u043e\u0435"
    ],
    "name:und_x_variant":[
        "Mizuho",
        "Tanho",
        "Midzukho"
    ],
    "wof:name":"Pozharskoye",
    "wof:placetype":"locality"
},
  "geometry": {"coordinates":[142.27788000000001,46.88149],"type":"Point"}
}