{
  "type": "Feature",
  "properties": {
    "gn:admin1_code":"84",
    "gn:asciiname":"Zatonovskiy",
    "gn:cc2":"RU",
    "gn:country_code":"RU",
    "gn:dem":74,
    "gn:feature_class":"P",
    "gn:feature_code":"PPL",
    "gn:name":"Zatonovskiy",
    "gn:population":0,
    "gn:timezone":"Europe/Volgograd",
    "iso:country":"RU",
    "name:und_x_variant":[
        "Khutor Zatonskiy",
        "Zatonovskiy"
    ],
    "wof:name":"Zatonovskiy",
    "wof:placetype":"locality"
},
  "geometry": {"coordinates":[42.01667,50.26667],"type":"Point"}
}