{
  "type": "Feature",
  "properties": {
    "gn:admin1_code":"7",
    "gn:asciiname":"Protochnoye",
    "gn:country_code":"RU",
    "gn:dem":-19,
    "gn:feature_class":"P",
    "gn:feature_code":"PPL",
    "gn:name":"Protochnoye",
    "gn:population":0,
    "gn:timezone":"Europe/Astrakhan",
    "iso:country":"RU",
    "name:che_x_preferred":[
        "\u041f\u0440\u043e\u0442\u043e\u0447\u043d\u0438"
    ],
    "name:eng_x_preferred":[
        "Protochnoye"
    ],
    "name:nor_x_preferred":[
        "Prototsjnoje"
    ],
    "name:rus_x_preferred":[
        "\u041f\u0440\u043e\u0442\u043e\u0447\u043d\u043e\u0435"
    ],
    "name:tgk_x_preferred":[
        "\u041f\u0440\u043e\u0442\u043e\u0447\u043d\u043e\u0435"
    ],
    "name:und_x_variant":[
        "Bantir",
        "Bontir"
    ],
    "wof:name":"Protochnoye",
    "wof:placetype":"locality"
},
  "geometry": {"coordinates":[47.30192,45.89195],"type":"Point"}
}