{
  "type": "Feature",
  "properties": {
    "gn:admin1_code":"21.0",
    "gn:asciiname":"Lomy Malyye",
    "gn:country_code":"RU",
    "gn:dem":126,
    "gn:feature_class":"P",
    "gn:feature_code":"PPL",
    "gn:name":"Lomy Malyye",
    "gn:population":0,
    "gn:timezone":"Europe/Moscow",
    "iso:country":"RU",
    "name:rus_x_preferred":[
        "\u041b\u043e\u043c\u044b \u041c\u0430\u043b\u044b\u0435"
    ],
    "name:und_x_variant":[
        "Malyye Lomy",
        "Lomy Malyye"
    ],
    "wof:name":"Lomy Malyye",
    "wof:placetype":"locality"
},
  "geometry": {"coordinates":[41.91263,56.99276999999999],"type":"Point"}
}