{
  "type": "Feature",
  "properties": {
    "gn:admin1_code":"9",
    "gn:asciiname":"Nechayevka",
    "gn:country_code":"RU",
    "gn:dem":130,
    "gn:feature_class":"P",
    "gn:feature_code":"PPL",
    "gn:name":"Nechayevka",
    "gn:population":0,
    "gn:timezone":"Europe/Moscow",
    "iso:country":"RU",
    "name:rus_x_preferred":[
        "\u041d\u0435\u0447\u0430\u0435\u0432\u043a\u0430"
    ],
    "wof:name":"Nechayevka",
    "wof:placetype":"locality"
},
  "geometry": {"coordinates":[37.91891,50.74913],"type":"Point"}
}