{
  "type": "Feature",
  "properties": {
    "gn:admin1_code":"53",
    "gn:asciiname":"Obraztsovo",
    "gn:country_code":"RU",
    "gn:dem":122,
    "gn:feature_class":"P",
    "gn:feature_code":"PPL",
    "gn:name":"Obraztsovo",
    "gn:population":0,
    "gn:timezone":"Asia/Novosibirsk",
    "iso:country":"RU",
    "name:rus_x_preferred":[
        "\u041e\u0431\u0440\u0430\u0437\u0446\u043e\u0432\u043e"
    ],
    "name:und_x_variant":[
        "Obraztsovyy",
        "Obraztsovo"
    ],
    "wof:name":"Obraztsovo",
    "wof:placetype":"locality"
},
  "geometry": {"coordinates":[78.26666999999998,56.36666999999999],"type":"Point"}
}