{
  "type": "Feature",
  "properties": {
    "gn:admin1_code":"60",
    "gn:asciiname":"Rechki Pervyye",
    "gn:country_code":"RU",
    "gn:dem":62,
    "gn:feature_class":"P",
    "gn:feature_code":"PPL",
    "gn:name":"Rechki Pervyye",
    "gn:population":0,
    "gn:timezone":"Europe/Moscow",
    "iso:country":"RU",
    "name:rus_x_preferred":[
        "\u0420\u0435\u0447\u043a\u0438 \u041f\u0435\u0440\u0432\u044b\u0435"
    ],
    "wof:name":"Rechki Pervyye",
    "wof:placetype":"locality"
},
  "geometry": {"coordinates":[28.7939,57.7719],"type":"Point"}
}