{
  "type": "Feature",
  "properties": {
    "gn:country":"RU",
    "gn:fcode":"PPL",
    "gn:pop":0,
    "iso:country":"RU",
    "name:rus_x_preferred":[
        "\u041d\u0435\u0444\u0435\u0434\u044c\u0435\u0432\u043e"
    ],
    "name:unk_x_variant":[
        "Nefedovo"
    ],
    "qs:name":"Nefed'evo",
    "qs:name_adm0":"Russia",
    "qs:name_adm1":"Moscow Oblast",
    "qs:photos_9k":1,
    "qs:photos_9r":1,
    "qs:photos_all":1,
    "qs:photos_sr":0,
    "qs:placetype":"Town",
    "qs:pop_sr":"0",
    "wof:name":"Nefed'evo",
    "wof:placetype":"locality",
    "wof:population":0
},
  "geometry": {"coordinates":[37.14004,55.89645],"type":"Point"}
}