{
  "type": "Feature",
  "properties": {
    "gn:admin1_code":"54",
    "gn:asciiname":"Kalachevo",
    "gn:country_code":"RU",
    "gn:dem":90,
    "gn:feature_class":"P",
    "gn:feature_code":"PPL",
    "gn:name":"Kalach\u00ebvo",
    "gn:population":0,
    "gn:timezone":"Asia/Omsk",
    "iso:country":"RU",
    "name:rus_x_preferred":[
        "\u041a\u0430\u043b\u0430\u0447\u0451\u0432\u043e"
    ],
    "name:und_x_variant":[
        "Kalach\u00ebvo"
    ],
    "wof:name":"Kalachevo",
    "wof:placetype":"locality"
},
  "geometry": {"coordinates":[73.32663000000002,54.76872],"type":"Point"}
}