{
  "type": "Feature",
  "properties": {
    "gn:admin1_code":"8",
    "gn:asciiname":"Yunusovo",
    "gn:country_code":"RU",
    "gn:dem":332,
    "gn:feature_class":"P",
    "gn:feature_code":"PPL",
    "gn:name":"Yunusovo",
    "gn:population":0,
    "gn:timezone":"Asia/Yekaterinburg",
    "iso:country":"RU",
    "name:eng_x_preferred":[
        "Yunusovo"
    ],
    "name:nor_x_preferred":[
        "Junusovo"
    ],
    "name:rus_x_preferred":[
        "\u042e\u043d\u0443\u0441\u043e\u0432\u043e"
    ],
    "name:und_x_variant":[
        "Yunusova",
        "Yunusovo"
    ],
    "wof:name":"Yunusovo",
    "wof:placetype":"locality"
},
  "geometry": {"coordinates":[58.07100000000001,55.0606],"type":"Point"}
}