{
  "type": "Feature",
  "properties": {
    "gn:admin1_code":"40.0",
    "gn:asciiname":"Kylman",
    "gn:country_code":"RU",
    "gn:dem":65,
    "gn:feature_class":"P",
    "gn:feature_code":"PPL",
    "gn:name":"Kylman",
    "gn:population":0,
    "gn:timezone":"Asia/Yekaterinburg",
    "iso:country":"RU",
    "name:rus_x_preferred":[
        "\u041a\u044b\u043b\u043c\u0430\u043d"
    ],
    "wof:name":"Kylman",
    "wof:placetype":"locality"
},
  "geometry": {"coordinates":[64.9469,56.3679],"type":"Point"}
}