{
  "type": "Feature",
  "properties": {
    "gn:admin1_code":"76",
    "gn:asciiname":"Oznabishino",
    "gn:country_code":"RU",
    "gn:dem":176,
    "gn:feature_class":"P",
    "gn:feature_code":"PPL",
    "gn:name":"Oznabishino",
    "gn:population":0,
    "gn:timezone":"Europe/Moscow",
    "iso:country":"RU",
    "name:rus_x_preferred":[
        "\u041e\u0437\u043d\u0430\u0431\u0438\u0448\u0438\u043d\u043e"
    ],
    "name:und_x_variant":[
        "Oznobishino",
        "Oznabishino"
    ],
    "wof:name":"Oznabishino",
    "wof:placetype":"locality"
},
  "geometry": {"coordinates":[37.79991,53.36418000000001],"type":"Point"}
}