{
  "type": "Feature",
  "properties": {
    "gn:admin1_code":"85",
    "gn:asciiname":"Voronino",
    "gn:country_code":"RU",
    "gn:dem":134,
    "gn:feature_class":"P",
    "gn:feature_code":"PPL",
    "gn:name":"Voronino",
    "gn:population":0,
    "gn:timezone":"Europe/Moscow",
    "iso:country":"RU",
    "name:eng_x_preferred":[
        "Voronino"
    ],
    "name:nor_x_preferred":[
        "Korolevo"
    ],
    "name:rus_x_preferred":[
        "\u041a\u043e\u0440\u043e\u043b\u0435\u0432\u043e"
    ],
    "name:rus_x_variant":[
        "\u0412\u043e\u0440\u043e\u043d\u0438\u043d\u043e"
    ],
    "wof:name":"Voronino",
    "wof:placetype":"locality"
},
  "geometry": {"coordinates":[38.7871,60.6421],"type":"Point"}
}