{
  "type": "Feature",
  "properties": {
    "gn:admin1_code":"61",
    "gn:asciiname":"Rostovskiy",
    "gn:cc2":"RU",
    "gn:country_code":"RU",
    "gn:dem":79,
    "gn:feature_class":"P",
    "gn:feature_code":"PPL",
    "gn:name":"Rostovskiy",
    "gn:population":0,
    "gn:timezone":"Europe/Moscow",
    "iso:country":"RU",
    "name:rus_x_preferred":[
        "\u0420\u043e\u0441\u0442\u043e\u0432\u0441\u043a\u0438\u0439"
    ],
    "name:und_x_variant":[
        "Zhirov",
        "Rostovskiy",
        "\u0420\u043e\u0441\u0442\u043e\u0432\u0441\u043a\u0438\u0439"
    ],
    "wof:name":"Rostovskiy",
    "wof:placetype":"locality"
},
  "geometry": {"coordinates":[40.36333,46.63806],"type":"Point"}
}