{
  "type": "Feature",
  "properties": {
    "gn:admin1_code":"76",
    "gn:asciiname":"Grishinkovo",
    "gn:country_code":"RU",
    "gn:dem":203,
    "gn:feature_class":"P",
    "gn:feature_code":"PPL",
    "gn:name":"Grishinkovo",
    "gn:population":0,
    "gn:timezone":"Europe/Moscow",
    "iso:country":"RU",
    "name:rus_x_preferred":[
        "\u0413\u0440\u0438\u0448\u0438\u043d\u043a\u043e\u0432\u043e"
    ],
    "name:und_x_variant":[
        "Grishenkovo",
        "Grishinkovo",
        "\u0413\u0440\u0438\u0448\u0438\u043d\u043a\u043e\u0432\u043e"
    ],
    "wof:name":"Grishinkovo",
    "wof:placetype":"locality"
},
  "geometry": {"coordinates":[36.56338,53.69134],"type":"Point"}
}