{
  "type": "Feature",
  "properties": {
    "gn:admin1_code":"77.0",
    "gn:asciiname":"Bol'shiye Del'ki",
    "gn:country_code":"RU",
    "gn:dem":171,
    "gn:feature_class":"P",
    "gn:feature_code":"PPL",
    "gn:name":"Bol\u2019shiye Del\u2019ki",
    "gn:population":0,
    "gn:timezone":"Europe/Moscow",
    "iso:country":"RU",
    "name:rus_x_preferred":[
        "\u0411\u043e\u043b\u044c\u0448\u0438\u0435 \u0414\u0435\u043b\u044c\u043a\u0438"
    ],
    "name:und_x_variant":[
        "Bol\u2019shiye Deliki",
        "Bol\u2019shiye Del\u2019ki",
        "\u0411\u043e\u043b\u044c\u0448\u0438\u0435 \u0414\u0435\u043b\u044c\u043a\u0438"
    ],
    "wof:name":"Bol'shiye Del'ki",
    "wof:placetype":"locality"
},
  "geometry": {"coordinates":[36.72464,58.23783],"type":"Point"}
}