{
  "type": "Feature",
  "properties": {
    "gn:admin1_code":"60",
    "gn:asciiname":"Makei",
    "gn:country_code":"RU",
    "gn:dem":118,
    "gn:feature_class":"P",
    "gn:feature_code":"PPL",
    "gn:name":"Makei",
    "gn:population":0,
    "gn:timezone":"Europe/Moscow",
    "iso:country":"RU",
    "name:rus_x_preferred":[
        "\u041c\u0430\u043a\u0435\u043d\u0435"
    ],
    "name:rus_x_variant":[
        "\u041c\u0430\u043a\u0435\u0438"
    ],
    "name:und_x_variant":[
        "Makene"
    ],
    "wof:name":"Makei",
    "wof:placetype":"locality"
},
  "geometry": {"coordinates":[28.27941,56.37459000000001],"type":"Point"}
}