{
  "type": "Feature",
  "properties": {
    "gn:country":"RU",
    "gn:fcode":"PPL",
    "gn:pop":3599,
    "iso:country":"RU",
    "name:eng_x_preferred":[
        "Izhma"
    ],
    "name:nor_x_preferred":[
        "Izjma"
    ],
    "name:rus_x_preferred":[
        "\u0418\u0436\u043c\u0430"
    ],
    "name:unk_x_variant":[
        "Ishma"
    ],
    "qs:name":"Izhma",
    "qs:photos_9r":0,
    "qs:photos_sr":0,
    "qs:pop_sr":"4",
    "wd:wordcount":62,
    "wof:name":"Izhma",
    "wof:placetype":"locality",
    "wof:population":3599
},
  "geometry": {"coordinates":[53.91128,65.00833],"type":"Point"}
}