{
  "type": "Feature",
  "properties": {
    "gn:admin1_code":"88.0",
    "gn:asciiname":"Zapovednik",
    "gn:country_code":"RU",
    "gn:dem":90,
    "gn:feature_class":"P",
    "gn:feature_code":"PPL",
    "gn:name":"Zapovednik",
    "gn:population":0,
    "gn:timezone":"Europe/Moscow",
    "iso:country":"RU",
    "name:und_x_variant":[
        "Zapovednik Vyselok",
        "Zapovednik"
    ],
    "wof:name":"Zapovednik",
    "wof:placetype":"locality"
},
  "geometry": {"coordinates":[40.95168,58.19761],"type":"Point"}
}