{
  "type": "Feature",
  "properties": {
    "gn:admin1_code":"88.0",
    "gn:asciiname":"Zapovednik",
    "gn:country_code":"RU",
    "gn:dem":90,
    "gn:feature_class":"P",
    "gn:feature_code":"PPL",
    "gn:name":"Zapovednik",
    "gn:population":0,
    "gn:timezone":"Europe/Moscow",
    "iso:country":"RU",
    "name:deu_x_preferred":[
        "Sapowednik"
    ],
    "name:fin_x_preferred":[
        "Zapovednik"
    ],
    "name:fra_x_preferred":[
        "Zapovednik"
    ],
    "name:nld_x_preferred":[
        "Zapovednik"
    ],
    "name:rus_x_preferred":[
        "\u0417\u0430\u043f\u043e\u0432\u0435\u0434\u043d\u0438\u043a"
    ],
    "name:spa_x_preferred":[
        "Zapov\u00e9dnik"
    ],
    "name:ukr_x_preferred":[
        "\u0417\u0430\u043f\u043e\u0432\u0456\u0434\u043d\u0438\u043a"
    ],
    "name:und_x_variant":[
        "Zapovednik Vyselok"
    ],
    "wof:name":"Zapovednik",
    "wof:placetype":"locality"
},
  "geometry": {"coordinates":[40.95168,58.19761],"type":"Point"}
}