{
  "type": "Feature",
  "properties": {
    "gn:admin1_code":"13",
    "gn:asciiname":"Natal'inskiy",
    "gn:country_code":"RU",
    "gn:dem":320,
    "gn:feature_class":"P",
    "gn:feature_code":"PPL",
    "gn:name":"Natal\u2019inskiy",
    "gn:population":0,
    "gn:timezone":"Asia/Yekaterinburg",
    "iso:country":"RU",
    "name:eng_x_preferred":[
        "Natal'inskiy"
    ],
    "name:nor_x_preferred":[
        "Natalinka"
    ],
    "name:rus_x_preferred":[
        "\u041d\u0430\u0442\u0430\u043b\u044c\u0438\u043d\u043a\u0430"
    ],
    "name:rus_x_variant":[
        "\u041d\u0430\u0442\u0430\u043b\u044c\u0438\u043d\u0441\u043a\u0438\u0439"
    ],
    "name:und_x_variant":[
        "Natal\u2019inskiy",
        "\u041d\u0430\u0442\u0430\u043b\u044c\u0438\u043d\u0441\u043a\u0438\u0439"
    ],
    "wof:name":"Natal'inskiy",
    "wof:placetype":"locality"
},
  "geometry": {"coordinates":[60.40881,53.56287],"type":"Point"}
}