{
  "type": "Feature",
  "properties": {
    "gn:admin1_code":"8",
    "gn:asciiname":"Kugarchino",
    "gn:country_code":"RU",
    "gn:dem":110,
    "gn:feature_class":"P",
    "gn:feature_code":"PPL",
    "gn:name":"Kugarchino",
    "gn:population":0,
    "gn:timezone":"Asia/Yekaterinburg",
    "iso:country":"RU",
    "name:eng_x_preferred":[
        "Kugarchino"
    ],
    "name:nor_x_preferred":[
        "Kugartsjino"
    ],
    "name:rus_x_preferred":[
        "\u041a\u0443\u0433\u0430\u0440\u0447\u0438\u043d\u043e"
    ],
    "wof:name":"Kugarchino",
    "wof:placetype":"locality"
},
  "geometry": {"coordinates":[55.08484,55.87274],"type":"Point"}
}