{
  "type": "Feature",
  "properties": {
    "gn:admin1_code":"69",
    "gn:asciiname":"Larino",
    "gn:country_code":"RU",
    "gn:dem":188,
    "gn:feature_class":"P",
    "gn:feature_code":"PPL",
    "gn:name":"Larino",
    "gn:population":0,
    "gn:timezone":"Europe/Moscow",
    "iso:country":"RU",
    "name:ara_x_preferred":[
        "\u0644\u0627\u0631\u064a\u0646\u0648"
    ],
    "name:azb_x_preferred":[
        "\u0644\u0627\u0631\u06cc\u0646\u0648"
    ],
    "name:bel_x_preferred":[
        "\u041b\u0430\u0440\u044b\u043d\u0430"
    ],
    "name:bul_x_preferred":[
        "\u041b\u0430\u0440\u0438\u043d\u043e"
    ],
    "name:ceb_x_preferred":[
        "Larino"
    ],
    "name:deu_x_preferred":[
        "Larino"
    ],
    "name:epo_x_preferred":[
        "Larino"
    ],
    "name:eus_x_preferred":[
        "Larino"
    ],
    "name:fas_x_preferred":[
        "\u0644\u0627\u0631\u06cc\u0646\u0648"
    ],
    "name:fra_x_preferred":[
        "Larino"
    ],
    "name:hun_x_preferred":[
        "Larino"
    ],
    "name:hye_x_preferred":[
        "\u053c\u0561\u0580\u056b\u0576\u0578"
    ],
    "name:ina_x_preferred":[
        "Larino"
    ],
    "name:ita_x_preferred":[
        "Larino"
    ],
    "name:jpn_x_preferred":[
        "\u30e9\u30ea\u30fc\u30ce"
    ],
    "name:kor_x_preferred":[
        "\ub77c\ub9ac\ub178"
    ],
    "name:lat_x_preferred":[
        "Larinum"
    ],
    "name:lmo_x_preferred":[
        "Larino"
    ],
    "name:msa_x_preferred":[
        "Larino"
    ],
    "name:nap_x_preferred":[
        "Larino"
    ],
    "name:nld_x_preferred":[
        "Larino"
    ],
    "name:pms_x_preferred":[
        "Larino"
    ],
    "name:pol_x_preferred":[
        "Larino"
    ],
    "name:por_x_preferred":[
        "Larino"
    ],
    "name:ron_x_preferred":[
        "Larino"
    ],
    "name:rus_x_preferred":[
        "\u041b\u0430\u0440\u0438\u043d\u043e"
    ],
    "name:scn_x_preferred":[
        "Larinu"
    ],
    "name:spa_x_preferred":[
        "Larino"
    ],
    "name:srp_x_preferred":[
        "\u041b\u0430\u0440\u0438\u043d\u043e"
    ],
    "name:tgl_x_preferred":[
        "Larino"
    ],
    "name:tur_x_preferred":[
        "Larino"
    ],
    "name:ukr_x_preferred":[
        "\u041b\u0430\u0440\u0438\u043d\u043e"
    ],
    "name:uzb_x_preferred":[
        "Larino"
    ],
    "name:vie_x_preferred":[
        "Larino"
    ],
    "name:vol_x_preferred":[
        "Larino"
    ],
    "name:war_x_preferred":[
        "Larino"
    ],
    "name:zho_x_preferred":[
        "\u62c9\u91cc\u8bfa"
    ],
    "wof:name":"Larino",
    "wof:placetype":"locality"
},
  "geometry": {"coordinates":[33.57583,55.23694],"type":"Point"}
}