{
  "type": "Feature",
  "properties": {
    "gn:admin1_code":"54",
    "gn:asciiname":"Lyublino",
    "gn:country_code":"RU",
    "gn:dem":118,
    "gn:feature_class":"P",
    "gn:feature_code":"PPL",
    "gn:name":"Lyublino",
    "gn:population":0,
    "gn:timezone":"Asia/Omsk",
    "iso:country":"RU",
    "name:ceb_x_preferred":[
        "\u041b\u044e\u0431\u043b\u0438\u043d\u043e"
    ],
    "name:deu_x_preferred":[
        "Ljublino"
    ],
    "name:hye_x_preferred":[
        "\u053c\u0575\u0578\u0582\u0562\u056c\u056b\u0576\u0578"
    ],
    "name:ita_x_preferred":[
        "Ljublino"
    ],
    "name:rus_x_preferred":[
        "\u041b\u044e\u0431\u043b\u0438\u043d\u043e"
    ],
    "name:ukr_x_preferred":[
        "\u041b\u044e\u0431\u043b\u0456\u043d\u043e"
    ],
    "wof:name":"Lyublino",
    "wof:placetype":"locality"
},
  "geometry": {"coordinates":[71.59999999999999,54.18333000000001],"type":"Point"}
}