{
  "type": "Feature",
  "properties": {
    "gn:admin1_code":"73",
    "gn:asciiname":"Urazayevo",
    "gn:country_code":"RU",
    "gn:dem":65,
    "gn:feature_class":"P",
    "gn:feature_code":"PPL",
    "gn:name":"Urazayevo",
    "gn:population":0,
    "gn:timezone":"Europe/Moscow",
    "iso:country":"RU",
    "name:rus_x_preferred":[
        "\u0423\u0440\u0430\u0437\u0430\u0435\u0432\u043e"
    ],
    "name:und_x_variant":[
        "\u0423\u0440\u0430\u0437\u0430\u0435\u0432\u043e"
    ],
    "wof:name":"Urazayevo",
    "wof:placetype":"locality"
},
  "geometry": {"coordinates":[53.9351,55.7561],"type":"Point"}
}