{
  "type": "Feature",
  "properties": {
    "gn:admin1_code":"73",
    "gn:asciiname":"Urazayevo",
    "gn:country_code":"RU",
    "gn:dem":65,
    "gn:feature_class":"P",
    "gn:feature_code":"PPL",
    "gn:name":"Urazayevo",
    "gn:population":0,
    "gn:timezone":"Europe/Moscow",
    "iso:country":"RU",
    "name:aze_x_preferred":[
        "Urazay"
    ],
    "name:bak_x_preferred":[
        "\u0423\u0440\u0430\u0437\u0430\u0439"
    ],
    "name:che_x_preferred":[
        "\u0423\u0440\u0430\u0437\u0430\u0435\u0432\u043e"
    ],
    "name:hye_x_preferred":[
        "\u0548\u0582\u0580\u0561\u0566\u0561\u0587\u0578"
    ],
    "name:kaz_x_preferred":[
        "\u0423\u0440\u0430\u0437\u0430"
    ],
    "name:kir_x_preferred":[
        "\u0423\u0440\u0430\u0437\u0430"
    ],
    "name:rus_x_preferred":[
        "\u0423\u0440\u0430\u0437\u0430\u0435\u0432\u043e"
    ],
    "name:tat_x_preferred":[
        "\u0423\u0440\u0430\u0437\u0430\u0439"
    ],
    "wof:name":"Urazayevo",
    "wof:placetype":"locality"
},
  "geometry": {"coordinates":[53.9351,55.7561],"type":"Point"}
}