{
  "type": "Feature",
  "properties": {
    "gn:admin1_code":"51",
    "gn:asciiname":"Otary",
    "gn:country_code":"RU",
    "gn:dem":117,
    "gn:feature_class":"P",
    "gn:feature_code":"PPL",
    "gn:name":"Otary",
    "gn:population":0,
    "gn:timezone":"Europe/Moscow",
    "iso:country":"RU",
    "name:rus_x_preferred":[
        "\u041e\u0442\u0430\u0440\u044b"
    ],
    "wof:name":"Otary",
    "wof:placetype":"locality"
},
  "geometry": {"coordinates":[46.3984,57.4113],"type":"Point"}
}