{
  "type": "Feature",
  "properties": {
    "gn:admin1_code":"68.0",
    "gn:asciiname":"Dzivgis",
    "gn:country_code":"RU",
    "gn:dem":1209,
    "gn:feature_class":"P",
    "gn:feature_code":"PPL",
    "gn:name":"Dzivgis",
    "gn:population":0,
    "gn:timezone":"Europe/Moscow",
    "iso:country":"RU",
    "name:rus_x_preferred":[
        "\u0414\u0437\u0438\u0432\u0433\u0438\u0441"
    ],
    "name:und_x_variant":[
        "Azivgus",
        "Dzivgus",
        "Dzivgis"
    ],
    "wof:name":"Dzivgis",
    "wof:placetype":"locality"
},
  "geometry": {"coordinates":[44.31023,42.87377],"type":"Point"}
}