{
  "type": "Feature",
  "properties": {
    "gn:admin1_code":"76.0",
    "gn:asciiname":"Dubiki",
    "gn:country_code":"RU",
    "gn:dem":220,
    "gn:feature_class":"P",
    "gn:feature_code":"PPL",
    "gn:name":"Dubiki",
    "gn:population":0,
    "gn:timezone":"Europe/Moscow",
    "iso:country":"RU",
    "name:eng_x_preferred":[
        "Dubiki"
    ],
    "name:nor_x_preferred":[
        "Dubiki"
    ],
    "name:rus_x_preferred":[
        "\u0414\u0443\u0431\u0438\u043a\u0438"
    ],
    "name:und_x_variant":[
        "\u0414\u0443\u0431\u0438\u043a\u0438",
        "Dubiki"
    ],
    "wof:name":"Dubiki",
    "wof:placetype":"locality"
},
  "geometry": {"coordinates":[38.0656,53.10254000000001],"type":"Point"}
}