{
  "type": "Feature",
  "properties": {
    "gn:admin1_code":"62",
    "gn:asciiname":"Pen'ki",
    "gn:country_code":"RU",
    "gn:dem":95,
    "gn:feature_class":"P",
    "gn:feature_code":"PPL",
    "gn:name":"Pen\u2019ki",
    "gn:population":0,
    "gn:timezone":"Europe/Moscow",
    "iso:country":"RU",
    "name:eng_x_preferred":[
        "Pen'ki"
    ],
    "name:nor_x_preferred":[
        "Penki"
    ],
    "name:rus_x_preferred":[
        "\u041f\u0435\u043d\u044c\u043a\u0438"
    ],
    "name:und_x_variant":[
        "Pen\u2019ki"
    ],
    "wof:name":"Pen'ki",
    "wof:placetype":"locality"
},
  "geometry": {"coordinates":[41.86457,54.59911999999999],"type":"Point"}
}