{
  "type": "Feature",
  "properties": {
    "gn:country":"RU",
    "gn:fcode":"PPL",
    "gn:population":1118,
    "iso:country":"RU",
    "name:bel_x_preferred":[
        "\u0425\u0443\u0436\u044b\u0440"
    ],
    "name:ceb_x_preferred":[
        "Khuzhir"
    ],
    "name:ces_x_preferred":[
        "Chu\u017eir"
    ],
    "name:che_x_preferred":[
        "\u0425\u0443\u0436\u0438\u0440"
    ],
    "name:eng_x_preferred":[
        "Khuzhir"
    ],
    "name:fra_x_preferred":[
        "Khoujir"
    ],
    "name:fra_x_variant":[
        "Koujir"
    ],
    "name:hye_x_preferred":[
        "\u053d\u0578\u0582\u056a\u056b\u0580"
    ],
    "name:ita_x_preferred":[
        "Chu\u017eir"
    ],
    "name:lit_x_preferred":[
        "Chu\u017eyras"
    ],
    "name:nld_x_preferred":[
        "Choezjir"
    ],
    "name:pol_x_preferred":[
        "Chu\u017cyr"
    ],
    "name:rus_x_preferred":[
        "\u041c\u0430\u043b.\u0425\u0443\u0436\u0438\u0440"
    ],
    "name:rus_x_variant":[
        "\u0425\u0443\u0436\u0438\u0440"
    ],
    "name:tgk_x_preferred":[
        "\u0425\u0443\u0436\u0438\u0440"
    ],
    "name:und_x_variant":[
        "Khuzhirtuy"
    ],
    "qs:name":"Khuzhir",
    "qs:name_adm0":"Russia",
    "qs:name_adm1":"Irkutsk Oblast",
    "qs:photos":967,
    "qs:photos_1k":196,
    "qs:photos_9k":4,
    "qs:photos_9r":6,
    "qs:photos_all":967,
    "qs:photos_sr":10,
    "qs:placetype":"Town",
    "qs:pop_sr":"3",
    "wd:wordcount":83,
    "wof:name":"Khuzhir",
    "wof:placetype":"locality",
    "wof:population":1118
},
  "geometry": {"coordinates":[107.33972,53.19389],"type":"Point"}
}