{
  "type": "Feature",
  "properties": {
    "gn:admin1_code":"60",
    "gn:asciiname":"Golodnitsa",
    "gn:country_code":"RU",
    "gn:dem":150,
    "gn:feature_class":"P",
    "gn:feature_code":"PPL",
    "gn:name":"Golodnitsa",
    "gn:population":0,
    "gn:timezone":"Europe/Moscow",
    "iso:country":"RU",
    "name:rus_x_preferred":[
        "\u0413\u043e\u043b\u043e\u0434\u043d\u0438\u0446\u0430"
    ],
    "wof:name":"Golodnitsa",
    "wof:placetype":"locality"
},
  "geometry": {"coordinates":[30.2095,56.0298],"type":"Point"}
}