{
  "type": "Feature",
  "properties": {
    "gn:admin1_code":"33.0",
    "gn:asciiname":"Zyamino",
    "gn:country_code":"RU",
    "gn:dem":202,
    "gn:feature_class":"P",
    "gn:feature_code":"PPL",
    "gn:name":"Zyamino",
    "gn:population":0,
    "gn:timezone":"Europe/Kirov",
    "iso:country":"RU",
    "name:rus_x_preferred":[
        "\u0417\u044f\u043c\u0438\u043d\u043e"
    ],
    "wof:name":"Zyamino",
    "wof:placetype":"locality"
},
  "geometry": {"coordinates":[50.47583,58.67111],"type":"Point"}
}