{
  "type": "Feature",
  "properties": {
    "gn:admin1_code":"69",
    "gn:asciiname":"Kazino",
    "gn:country_code":"RU",
    "gn:dem":223,
    "gn:feature_class":"P",
    "gn:feature_code":"PPL",
    "gn:name":"Kazino",
    "gn:population":0,
    "gn:timezone":"Europe/Moscow",
    "iso:country":"RU",
    "name:rus_x_preferred":[
        "\u041a\u0430\u0437\u0438\u043d\u043e"
    ],
    "wof:name":"Kazino",
    "wof:placetype":"locality"
},
  "geometry": {"coordinates":[32.08333,54.95],"type":"Point"}
}