{
  "type": "Feature",
  "properties": {
    "gn:admin1_code":"73.0",
    "gn:asciiname":"Bayukovo",
    "gn:country_code":"RU",
    "gn:dem":136,
    "gn:feature_class":"P",
    "gn:feature_code":"PPL",
    "gn:name":"Bayukovo",
    "gn:population":0,
    "gn:timezone":"Asia/Yekaterinburg",
    "iso:country":"RU",
    "name:eng_x_preferred":[
        "Bayukovo"
    ],
    "name:rus_x_preferred":[
        "\u0411\u0430\u044e\u043a\u043e\u0432\u0430"
    ],
    "name:rus_x_variant":[
        "\u0411\u0430\u044e\u043a\u043e\u0432\u043e"
    ],
    "name:und_x_variant":[
        "Bayukova"
    ],
    "wof:name":"Bayukovo",
    "wof:placetype":"locality"
},
  "geometry": {"coordinates":[53.58722,55.2175],"type":"Point"}
}