{
  "type": "Feature",
  "properties": {
    "gn:admin1_code":"85.0",
    "gn:asciiname":"Kiprino",
    "gn:country_code":"RU",
    "gn:dem":158,
    "gn:feature_class":"P",
    "gn:feature_code":"PPL",
    "gn:name":"Kiprino",
    "gn:population":0,
    "gn:timezone":"Europe/Moscow",
    "iso:country":"RU",
    "name:che_x_preferred":[
        "\u041a\u0438\u043f\u0440\u0438\u043d\u043e"
    ],
    "name:rus_x_preferred":[
        "\u041a\u0438\u043f\u0440\u0438\u043d\u043e"
    ],
    "wof:name":"Kiprino",
    "wof:placetype":"locality"
},
  "geometry": {"coordinates":[38.6097,60.4801],"type":"Point"}
}