{
  "type": "Feature",
  "properties": {
    "gn:admin1_code":"62",
    "gn:asciiname":"Lipetskiy",
    "gn:country_code":"RU",
    "gn:dem":123,
    "gn:feature_class":"P",
    "gn:feature_code":"PPL",
    "gn:name":"Lipetskiy",
    "gn:population":0,
    "gn:timezone":"Europe/Moscow",
    "iso:country":"RU",
    "name:rus_x_preferred":[
        "\u041b\u0438\u043f\u0435\u0446\u043a\u0438\u0439"
    ],
    "name:und_x_variant":[
        "Lipitski",
        "Lipitskiy",
        "Lipetskiy"
    ],
    "wof:name":"Lipetskiy",
    "wof:placetype":"locality"
},
  "geometry": {"coordinates":[40.5405,54.2029],"type":"Point"}
}