{
  "type": "Feature",
  "properties": {
    "gn:admin1_code":"90",
    "gn:asciiname":"Shulan",
    "gn:country_code":"RU",
    "gn:dem":195,
    "gn:feature_class":"P",
    "gn:feature_code":"PPL",
    "gn:name":"Shulan",
    "gn:population":0,
    "gn:timezone":"Asia/Yekaterinburg",
    "iso:country":"RU",
    "name:ara_x_preferred":[
        "\u0634\u0648\u0644\u0627\u0646"
    ],
    "name:ceb_x_preferred":[
        "Shulan"
    ],
    "name:deu_x_preferred":[
        "Shulan"
    ],
    "name:fas_x_preferred":[
        "\u0634\u0648\u0644\u0627\u0646"
    ],
    "name:fra_x_preferred":[
        "Shulan"
    ],
    "name:heb_x_preferred":[
        "\u05e9\u05d5\u05dc\u05d0\u05df"
    ],
    "name:hun_x_preferred":[
        "Shulan"
    ],
    "name:ita_x_preferred":[
        "Shulan"
    ],
    "name:jpn_x_preferred":[
        "\u8212\u862d\u5e02"
    ],
    "name:kik_x_preferred":[
        "Shulan"
    ],
    "name:kor_x_preferred":[
        "\uc218\ub780\uc2dc"
    ],
    "name:mlg_x_preferred":[
        "Shulan"
    ],
    "name:nld_x_preferred":[
        "Shulan"
    ],
    "name:nor_x_preferred":[
        "Shulan"
    ],
    "name:pol_x_preferred":[
        "Shulan"
    ],
    "name:rus_x_preferred":[
        "\u0428\u0443\u043b\u0430\u043d"
    ],
    "name:rus_x_variant":[
        "\u0428\u0443\u043b\u0430\u043d\u044c"
    ],
    "name:swe_x_preferred":[
        "Shulan"
    ],
    "name:urd_x_preferred":[
        "\u0634\u0648\u0644\u0627\u0646"
    ],
    "name:vie_x_preferred":[
        "Th\u01b0 Lan"
    ],
    "name:zho_x_preferred":[
        "\u8212\u5170\u5e02"
    ],
    "wof:name":"Shulan",
    "wof:placetype":"locality"
},
  "geometry": {"coordinates":[54.0358,58.25131],"type":"Point"}
}