{
  "type": "Feature",
  "properties": {
    "gn:admin1_code":"84",
    "gn:asciiname":"Vyrypetskogo",
    "gn:country_code":"RU",
    "gn:dem":25,
    "gn:feature_class":"P",
    "gn:feature_code":"PPL",
    "gn:name":"Vyrypetskogo",
    "gn:population":0,
    "gn:timezone":"Europe/Volgograd",
    "iso:country":"RU",
    "wof:name":"Vyrypetskogo",
    "wof:placetype":"locality"
},
  "geometry": {"coordinates":[45.61667,49.35],"type":"Point"}
}