{
  "type": "Feature",
  "properties": {
    "gn:admin1_code":"45",
    "gn:asciiname":"Orekhovka",
    "gn:country_code":"RU",
    "gn:dem":114,
    "gn:feature_class":"P",
    "gn:feature_code":"PPL",
    "gn:name":"Orekhovka",
    "gn:population":0,
    "gn:timezone":"Europe/Moscow",
    "iso:country":"RU",
    "name:rus_x_preferred":[
        "\u041e\u0440\u0435\u0445\u043e\u0432\u043a\u0430"
    ],
    "name:und_x_variant":[
        "\u041e\u0440\u0435\u0445\u043e\u0432\u043a\u0430"
    ],
    "wof:name":"Orekhovka",
    "wof:placetype":"locality"
},
  "geometry": {"coordinates":[47.68262,56.63587],"type":"Point"}
}