{
  "type": "Feature",
  "properties": {
    "gn:admin1_code":"33.0",
    "gn:asciiname":"Chetveriki",
    "gn:country_code":"RU",
    "gn:dem":197,
    "gn:feature_class":"P",
    "gn:feature_code":"PPL",
    "gn:name":"Chetveriki",
    "gn:population":0,
    "gn:timezone":"Europe/Kirov",
    "iso:country":"RU",
    "name:rus_x_preferred":[
        "\u0427\u0435\u0442\u0432\u0435\u0440\u0438\u043a\u0438"
    ],
    "wof:name":"Chetveriki",
    "wof:placetype":"locality"
},
  "geometry": {"coordinates":[50.36667,58.13333000000001],"type":"Point"}
}