{
  "type": "Feature",
  "properties": {
    "gn:admin1_code":"33",
    "gn:asciiname":"Ponomarevskiy",
    "gn:country_code":"RU",
    "gn:dem":139,
    "gn:feature_class":"P",
    "gn:feature_code":"PPL",
    "gn:name":"Ponomar\u00ebvskiy",
    "gn:population":0,
    "gn:timezone":"Europe/Kirov",
    "iso:country":"RU",
    "name:rus_x_preferred":[
        "\u041f\u043e\u043d\u043e\u043c\u0430\u0440\u0451\u0432\u0441\u043a\u0438\u0439"
    ],
    "name:und_x_variant":[
        "Ponomar\u00ebvskiy"
    ],
    "wof:name":"Ponomarevskiy",
    "wof:placetype":"locality"
},
  "geometry": {"coordinates":[47.93333,60.35],"type":"Point"}
}