{
  "type": "Feature",
  "properties": {
    "gn:admin1_code":"59",
    "gn:asciiname":"Tavayza",
    "gn:cc2":"RU",
    "gn:country_code":"RU",
    "gn:dem":28,
    "gn:feature_class":"P",
    "gn:feature_code":"PPL",
    "gn:name":"Tavayza",
    "gn:population":0,
    "gn:timezone":"Asia/Vladivostok",
    "iso:country":"RU",
    "name:und_x_variant":[
        "Russkoye"
    ],
    "wof:name":"Tavayza",
    "wof:placetype":"locality"
},
  "geometry": {"coordinates":[136.78556,45.18639],"type":"Point"}
}