{
  "type": "Feature",
  "properties": {
    "gn:admin1_code":"15",
    "gn:asciiname":"Kul'telyvik",
    "gn:country_code":"RU",
    "gn:dem":284,
    "gn:feature_class":"P",
    "gn:feature_code":"PPL",
    "gn:name":"Kul\u2019telyvik",
    "gn:population":0,
    "gn:timezone":"Asia/Anadyr",
    "iso:country":"RU",
    "name:rus_x_preferred":[
        "\u041a\u0443\u043b\u044c\u0442\u0435\u043b\u044b\u0432\u0438\u043a"
    ],
    "name:und_x_variant":[
        "Retkaurgun",
        "Kul\u2019telyvik"
    ],
    "wof:name":"Kul'telyvik",
    "wof:placetype":"locality"
},
  "geometry": {"coordinates":[-173.83333000000005,64.71666999999999],"type":"Point"}
}