{
  "type": "Feature",
  "properties": {
    "gn:country":"RU",
    "gn:fcode":"PPL",
    "gn:population":169,
    "iso:country":"RU",
    "name:eng_x_preferred":[
        "Krinitsa"
    ],
    "name:nor_x_preferred":[
        "Krinitsa"
    ],
    "name:rus_x_preferred":[
        "\u041a\u0440\u0438\u043d\u0438\u0446\u0430"
    ],
    "qs:name":"Krinitsa",
    "qs:photos_9r":0,
    "qs:photos_sr":0,
    "qs:pop_sr":"1",
    "wof:name":"Krinitsa",
    "wof:placetype":"locality",
    "wof:population":169
},
  "geometry": {"coordinates":[38.3429,44.3886],"type":"Point"}
}