{
  "type": "Feature",
  "properties": {
    "gn:admin1_code":"80",
    "gn:asciiname":"Kechur",
    "gn:country_code":"RU",
    "gn:dem":112,
    "gn:feature_class":"P",
    "gn:feature_code":"PPL",
    "gn:name":"Kechur",
    "gn:population":0,
    "gn:timezone":"Europe/Samara",
    "iso:country":"RU",
    "name:eng_x_preferred":[
        "Kechur"
    ],
    "name:nor_x_preferred":[
        "Ketsjur"
    ],
    "name:rus_x_preferred":[
        "\u041a\u0435\u0447\u0443\u0440"
    ],
    "wof:name":"Kechur",
    "wof:placetype":"locality"
},
  "geometry": {"coordinates":[52.88783000000001,56.60667],"type":"Point"}
}