{
  "type": "Feature",
  "properties": {
    "gn:elevation":234,
    "iso:country":"RU",
    "name:ceb_x_preferred":[
        "Chelyabinsk Airport"
    ],
    "name:deu_x_preferred":[
        "Flughafen Tscheljabinsk"
    ],
    "name:eng_x_preferred":[
        "Chelyabinsk Airport"
    ],
    "name:eng_x_variant":[
        "CEK",
        "KCEK"
    ],
    "name:fas_x_preferred":[
        "\u0641\u0631\u0648\u062f\u06af\u0627\u0647 \u0686\u0644\u06cc\u0627\u0628\u06cc\u0646\u0633\u06a9"
    ],
    "name:fra_x_preferred":[
        "A\u00e9roport de Tcheliabinsk"
    ],
    "name:fra_x_variant":[
        "a\u00e9roport de Tcheliabinsk"
    ],
    "name:heb_x_preferred":[
        "\u05e0\u05de\u05dc \u05d4\u05ea\u05e2\u05d5\u05e4\u05d4 \u05e6'\u05dc\u05d9\u05d0\u05d1\u05d9\u05e0\u05e1\u05e7"
    ],
    "name:hun_x_preferred":[
        "Cseljabinszki rep\u00fcl\u0151t\u00e9r"
    ],
    "name:hye_x_preferred":[
        "\u0549\u0565\u056c\u0575\u0561\u0562\u056b\u0576\u057d\u056f"
    ],
    "name:ind_x_preferred":[
        "Bandar Udara Chelyabinsk"
    ],
    "name:ita_x_preferred":[
        "Aeroporto di \u010celjabinsk"
    ],
    "name:jpn_x_preferred":[
        "\u30d0\u30e9\u30f3\u30b8\u30ce\u7a7a\u6e2f"
    ],
    "name:jpn_x_variant":[
        "\u30c1\u30a7\u30ea\u30e3\u30d3\u30f3\u30b9\u30af\u7a7a\u6e2f"
    ],
    "name:kor_x_preferred":[
        "\uccbc\ub7b4\ube48\uc2a4\ud06c \uacf5\ud56d"
    ],
    "name:msa_x_preferred":[
        "Lapangan Terbang Balandino"
    ],
    "name:nld_x_preferred":[
        "Tsjeljabinsk"
    ],
    "name:nno_x_preferred":[
        "Tsjeljabinsk lufthamn"
    ],
    "name:nob_x_preferred":[
        "Tsjeljabinsk lufthavn"
    ],
    "name:pol_x_preferred":[
        "Port lotniczy Czelabi\u0144sk"
    ],
    "name:ron_x_preferred":[
        "Aeroportul Chelyabinsk"
    ],
    "name:rus_x_preferred":[
        "\u0427\u0435\u043b\u044f\u0431\u0438\u043d\u0441\u043a"
    ],
    "name:rus_x_variant":[
        "\u041c\u0435\u0436\u0434\u0443\u043d\u0430\u0440\u043e\u0434\u043d\u044b\u0439 \u0430\u044d\u0440\u043e\u043f\u043e\u0440\u0442 \u0427\u0435\u043b\u044f\u0431\u0438\u043d\u0441\u043a"
    ],
    "name:srp_x_preferred":[
        "\u0427\u0435\u0459\u0430\u0431\u0438\u043d\u0441\u043a"
    ],
    "name:tgk_x_preferred":[
        "\u0424\u0443\u0440\u0443\u0434\u0433\u043e\u04b3\u0438 \u0447\u043b\u0438\u043e\u0431\u0438\u043d\u0441\u043a"
    ],
    "name:tur_x_preferred":[
        "\u00c7elyabinsk Havaliman\u0131"
    ],
    "name:ukr_x_preferred":[
        "\u0427\u0435\u043b\u044f\u0431\u0456\u043d\u0441\u044c\u043a"
    ],
    "name:vie_x_preferred":[
        "S\u00e2n bay Chelyabinsk"
    ],
    "name:zho_x_preferred":[
        "\u8eca\u91cc\u96c5\u8cd3\u65af\u514b\u6a5f\u5834"
    ],
    "oa:elevation_ft":"769",
    "oa:type":"medium_airport",
    "wd:wordcount":428,
    "woe:hierarchy":{
        "country_id":23424936,
        "county_id":12598116,
        "planet_id":1,
        "state_id":2346893
    },
    "wof:name":"Chelyabinsk Balandino Airport",
    "wof:placetype":"campus"
},
  "geometry": {"coordinates":[61.5033,55.305801],"type":"Point"}
}