{
  "type": "Feature",
  "properties": {
    "gn:admin1_code":"21",
    "gn:asciiname":"Sobantseyevo",
    "gn:country_code":"RU",
    "gn:dem":145,
    "gn:feature_class":"P",
    "gn:feature_code":"PPL",
    "gn:name":"Sobantseyevo",
    "gn:population":0,
    "gn:timezone":"Europe/Moscow",
    "iso:country":"RU",
    "name:und_x_variant":[
        "Sebantsevo",
        "Sobantseyevo"
    ],
    "wof:name":"Sobantseyevo",
    "wof:placetype":"locality"
},
  "geometry": {"coordinates":[40.81868,57.23631999999999],"type":"Point"}
}