{
  "type": "Feature",
  "properties": {
    "gn:admin1_code":"25",
    "gn:asciiname":"Prudnovo",
    "gn:country_code":"RU",
    "gn:dem":184,
    "gn:feature_class":"P",
    "gn:feature_code":"PPL",
    "gn:name":"Prudnovo",
    "gn:population":0,
    "gn:timezone":"Europe/Moscow",
    "iso:country":"RU",
    "name:rus_x_preferred":[
        "\u041f\u0440\u0443\u0434\u043d\u043e\u0432\u043e"
    ],
    "wof:name":"Prudnovo",
    "wof:placetype":"locality"
},
  "geometry": {"coordinates":[35.92816,54.83141],"type":"Point"}
}