{
  "type": "Feature",
  "properties": {
    "gn:admin1_code":"23",
    "gn:asciiname":"Golovkino",
    "gn:cc2":"RU",
    "gn:country_code":"RU",
    "gn:dem":-2,
    "gn:feature_class":"P",
    "gn:feature_code":"PPL",
    "gn:name":"Golovkino",
    "gn:population":0,
    "gn:timezone":"Europe/Kaliningrad",
    "iso:country":"RU",
    "name:eng_x_preferred":[
        "Golovkino"
    ],
    "name:nor_x_preferred":[
        "Golovkino"
    ],
    "name:rus_x_preferred":[
        "\u0413\u043e\u043b\u043e\u0432\u043a\u0438\u043d\u043e"
    ],
    "name:und_x_variant":[
        "Elchwerder",
        "Nemonien",
        "Nemoniyen",
        "Nemon\u2019yen",
        "Nemonen",
        "\u0413\u043e\u043b\u043e\u0432\u043a\u0438\u043d\u043e",
        "Golovkino"
    ],
    "wof:name":"Golovkino",
    "wof:placetype":"locality"
},
  "geometry": {"coordinates":[21.27222,54.98056],"type":"Point"}
}