{
  "type": "Feature",
  "properties": {
    "gn:admin1_code":"10",
    "gn:asciiname":"Lyubovsho",
    "gn:country_code":"RU",
    "gn:dem":138,
    "gn:feature_class":"P",
    "gn:feature_code":"PPL",
    "gn:name":"Lyubovsho",
    "gn:population":1379,
    "gn:timezone":"Europe/Moscow",
    "iso:country":"RU",
    "name:eng_x_preferred":[
        "Lyubovsho"
    ],
    "name:nor_x_preferred":[
        "Ljubovsja"
    ],
    "name:rus_x_preferred":[
        "\u041b\u044e\u0431\u043e\u0432\u0448\u043e"
    ],
    "name:und_x_variant":[
        "Lyubovsha",
        "Lyubavsho"
    ],
    "wof:name":"Lyubovsho",
    "wof:placetype":"locality",
    "wof:population":1379
},
  "geometry": {"coordinates":[31.5422,52.9851],"type":"Point"}
}