{
  "type": "Feature",
  "properties": {
    "gn:admin1_code":"20",
    "gn:asciiname":"Babkha",
    "gn:country_code":"RU",
    "gn:dem":476,
    "gn:feature_class":"P",
    "gn:feature_code":"PPL",
    "gn:name":"Babkha",
    "gn:population":0,
    "gn:timezone":"Asia/Irkutsk",
    "iso:country":"RU",
    "name:rus_x_preferred":[
        "\u0411\u0430\u0431\u0445\u0430"
    ],
    "wof:name":"Babkha",
    "wof:placetype":"locality"
},
  "geometry": {"coordinates":[104.08669999999999,51.5328],"type":"Point"}
}