{
  "type": "Feature",
  "properties": {
    "gn:admin1_code":"75",
    "gn:asciiname":"Katyl'ga",
    "gn:country_code":"RU",
    "gn:dem":66,
    "gn:feature_class":"P",
    "gn:feature_code":"PPL",
    "gn:name":"Katyl\u2019ga",
    "gn:population":0,
    "gn:timezone":"Asia/Tomsk",
    "iso:country":"RU",
    "name:eng_x_preferred":[
        "Katyl'ga"
    ],
    "name:nor_x_preferred":[
        "Katylga"
    ],
    "name:rus_x_preferred":[
        "\u041a\u0430\u0442\u044b\u043b\u044c\u0433\u0430"
    ],
    "name:und_x_variant":[
        "Yurty Katyl\u2019ga",
        "\u041a\u0430\u0442\u044b\u043b\u044c\u0433\u0430",
        "Katyl\u2019ga"
    ],
    "wof:name":"Katyl'ga",
    "wof:placetype":"locality"
},
  "geometry": {"coordinates":[76.69528000000003,59.06528],"type":"Point"}
}