{
  "type": "Feature",
  "properties": {
    "gn:admin1_code":"60",
    "gn:asciiname":"Gryadishche",
    "gn:country_code":"RU",
    "gn:dem":56,
    "gn:feature_class":"P",
    "gn:feature_code":"PPL",
    "gn:name":"Gryadishche",
    "gn:population":0,
    "gn:timezone":"Europe/Moscow",
    "iso:country":"RU",
    "name:eng_x_preferred":[
        "Gryadishche"
    ],
    "name:nor_x_preferred":[
        "Grjadisjtsje"
    ],
    "name:rus_x_preferred":[
        "\u0413\u0440\u044f\u0434\u0438\u0449\u0435"
    ],
    "wof:name":"Gryadishche",
    "wof:placetype":"locality"
},
  "geometry": {"coordinates":[28.18069,58.13373000000001],"type":"Point"}
}