{
  "type": "Feature",
  "properties": {
    "gn:admin1_code":"78",
    "gn:asciiname":"Peshnevo",
    "gn:country_code":"RU",
    "gn:dem":131,
    "gn:feature_class":"P",
    "gn:feature_code":"PPL",
    "gn:name":"Peshn\u00ebvo",
    "gn:population":0,
    "gn:timezone":"Asia/Yekaterinburg",
    "iso:country":"RU",
    "name:eng_x_preferred":[
        "Peshn\u00ebvo"
    ],
    "name:nor_x_preferred":[
        "Pesjnevo"
    ],
    "name:rus_x_preferred":[
        "\u041f\u0435\u0448\u043d\u0435\u0432\u043e"
    ],
    "name:rus_x_variant":[
        "\u041f\u0435\u0448\u043d\u0451\u0432\u043e"
    ],
    "wof:name":"Peshnevo",
    "wof:placetype":"locality"
},
  "geometry": {"coordinates":[69.41212,55.55702],"type":"Point"}
}