{
  "type": "Feature",
  "properties": {
    "gn:admin1_code":"60.0",
    "gn:asciiname":"Babiy Mokh",
    "gn:country_code":"RU",
    "gn:dem":93,
    "gn:feature_class":"P",
    "gn:feature_code":"PPL",
    "gn:name":"Babiy Mokh",
    "gn:population":0,
    "gn:timezone":"Europe/Moscow",
    "iso:country":"RU",
    "name:nor_x_preferred":[
        "Babij Mokh"
    ],
    "name:rus_x_preferred":[
        "\u0411\u0430\u0431\u0438\u0439 \u041c\u043e\u0445"
    ],
    "name:und_x_variant":[
        "Bab\u2019ino",
        "Babij Mochs",
        "Babiy Mokh"
    ],
    "wof:name":"Babiy Mokh",
    "wof:placetype":"locality"
},
  "geometry": {"coordinates":[27.96424,56.86176999999999],"type":"Point"}
}