{
  "type": "Feature",
  "properties": {
    "gn:admin1_code":"4",
    "gn:asciiname":"Pivochnyy",
    "gn:country_code":"RU",
    "gn:dem":464,
    "gn:feature_class":"P",
    "gn:feature_code":"PPL",
    "gn:name":"Pivochnyy",
    "gn:population":0,
    "gn:timezone":"Asia/Barnaul",
    "iso:country":"RU",
    "name:rus_x_preferred":[
        "\u041f\u0438\u0432\u043e\u0447\u043d\u044b\u0439"
    ],
    "wof:name":"Pivochnyy",
    "wof:placetype":"locality"
},
  "geometry": {"coordinates":[84.76666999999998,51.85],"type":"Point"}
}