{
  "type": "Feature",
  "properties": {
    "gn:admin1_code":"52",
    "gn:asciiname":"Semytino",
    "gn:country_code":"RU",
    "gn:dem":138,
    "gn:feature_class":"P",
    "gn:feature_code":"PPL",
    "gn:name":"Semytino",
    "gn:population":0,
    "gn:timezone":"Europe/Moscow",
    "iso:country":"RU",
    "name:che_x_preferred":[
        "\u0421\u0435\u043c\u044b\u0442\u0438\u043d\u043e"
    ],
    "name:rus_x_preferred":[
        "\u0421\u0435\u043c\u044b\u0442\u0438\u043d\u043e"
    ],
    "name:und_x_variant":[
        "Semutino",
        "Semytino",
        "\u0421\u0435\u043c\u044b\u0442\u0438\u043d\u043e"
    ],
    "wof:name":"Semytino",
    "wof:placetype":"locality"
},
  "geometry": {"coordinates":[35.80988,58.48786],"type":"Point"}
}