{
  "type": "Feature",
  "properties": {
    "gn:admin1_code":"71",
    "gn:asciiname":"Kryazh",
    "gn:country_code":"RU",
    "gn:dem":255,
    "gn:feature_class":"P",
    "gn:feature_code":"PPL",
    "gn:name":"Kryazh",
    "gn:population":0,
    "gn:timezone":"Asia/Yekaterinburg",
    "iso:country":"RU",
    "name:rus_x_preferred":[
        "\u041a\u0440\u044f\u0436"
    ],
    "name:und_x_variant":[
        "\u041a\u0440\u044f\u0436"
    ],
    "wof:name":"Kryazh",
    "wof:placetype":"locality"
},
  "geometry": {"coordinates":[58.18992,57.43669000000001],"type":"Point"}
}