{
  "type": "Feature",
  "properties": {
    "gn:admin1_code":"91",
    "gn:asciiname":"Ust'yansk",
    "gn:country_code":"RU",
    "gn:dem":232,
    "gn:feature_class":"P",
    "gn:feature_code":"PPL",
    "gn:name":"Ust\u2019yansk",
    "gn:population":0,
    "gn:timezone":"Asia/Krasnoyarsk",
    "iso:country":"RU",
    "name:eng_x_preferred":[
        "Ust'yansk"
    ],
    "name:nor_x_preferred":[
        "Ustjansk"
    ],
    "name:rus_x_preferred":[
        "\u0423\u0441\u0442\u044c\u044f\u043d\u0441\u043a"
    ],
    "name:und_x_variant":[
        "Ust\u2019yanskoye",
        "Ust\u2019yansk"
    ],
    "wof:name":"Ust'yansk",
    "wof:placetype":"locality"
},
  "geometry": {"coordinates":[96.01600000000001,56.5234],"type":"Point"}
}