{
  "type": "Feature",
  "properties": {
    "gn:admin1_code":"9",
    "gn:asciiname":"Staryy Redkodub",
    "gn:country_code":"RU",
    "gn:dem":192,
    "gn:feature_class":"P",
    "gn:feature_code":"PPL",
    "gn:name":"Staryy Redkodub",
    "gn:population":0,
    "gn:timezone":"Europe/Moscow",
    "iso:country":"RU",
    "name:rus_x_preferred":[
        "\u0421\u0442\u0430\u0440\u044b\u0439 \u0420\u0435\u0434\u043a\u043e\u0434\u0443\u0431"
    ],
    "name:und_x_variant":[
        "Stary Redkodub",
        "Staryy Redkodub",
        "\u0421\u0442\u0430\u0440\u044b\u0439 \u0420\u0435\u0434\u043a\u043e\u0434\u0443\u0431"
    ],
    "wof:name":"Staryy Redkodub",
    "wof:placetype":"locality"
},
  "geometry": {"coordinates":[38.375,50.9385],"type":"Point"}
}