{
  "type": "Feature",
  "properties": {
    "gn:admin1_code":"52",
    "gn:asciiname":"Klenovets",
    "gn:country_code":"RU",
    "gn:dem":77,
    "gn:feature_class":"P",
    "gn:feature_code":"PPL",
    "gn:name":"Klenovets",
    "gn:population":0,
    "gn:timezone":"Europe/Moscow",
    "iso:country":"RU",
    "name:rus_x_preferred":[
        "\u041a\u043b\u0435\u043d\u043e\u0432\u0435\u0446"
    ],
    "wof:name":"Klenovets",
    "wof:placetype":"locality"
},
  "geometry": {"coordinates":[30.6825,57.8907],"type":"Point"}
}