{
  "type": "Feature",
  "properties": {
    "gn:admin1_code":"61.0",
    "gn:asciiname":"Bulochkin",
    "gn:country_code":"RU",
    "gn:dem":81,
    "gn:feature_class":"P",
    "gn:feature_code":"PPL",
    "gn:name":"Bulochkin",
    "gn:population":0,
    "gn:timezone":"Europe/Moscow",
    "iso:country":"RU",
    "name:rus_x_preferred":[
        "\u0411\u0443\u043b\u043e\u0447\u043a\u0438\u043d"
    ],
    "name:und_x_variant":[
        "Bulotskin",
        "Bulochkin",
        "\u0411\u0443\u043b\u043e\u0447\u043a\u0438\u043d"
    ],
    "wof:name":"Bulochkin",
    "wof:placetype":"locality"
},
  "geometry": {"coordinates":[40.51784,47.02624],"type":"Point"}
}