{
  "type": "Feature",
  "properties": {
    "gn:admin1_code":"77.0",
    "gn:asciiname":"Afanas'yevo",
    "gn:country_code":"RU",
    "gn:dem":146,
    "gn:feature_class":"P",
    "gn:feature_code":"PPL",
    "gn:name":"Afanas\u2019yevo",
    "gn:population":0,
    "gn:timezone":"Europe/Moscow",
    "iso:country":"RU",
    "name:nor_x_preferred":[
        "Afanasievo"
    ],
    "name:rus_x_preferred":[
        "\u0410\u0444\u0430\u043d\u0430\u0441\u044c\u0435\u0432\u043e"
    ],
    "name:und_x_variant":[
        "Afanas\u2019yevo"
    ],
    "wof:name":"Afanas'yevo",
    "wof:placetype":"locality"
},
  "geometry": {"coordinates":[35.38043,56.68689000000001],"type":"Point"}
}