{
  "type": "Feature",
  "properties": {
    "gn:admin1_code":"37",
    "gn:asciiname":"Khomutovo",
    "gn:country_code":"RU",
    "gn:dem":138,
    "gn:feature_class":"P",
    "gn:feature_code":"PPL",
    "gn:name":"Khomutovo",
    "gn:population":0,
    "gn:timezone":"Europe/Moscow",
    "iso:country":"RU",
    "name:nor_x_preferred":[
        "Khomutovo"
    ],
    "name:rus_x_preferred":[
        "\u0425\u043e\u043c\u0443\u0442\u043e\u0432\u043e"
    ],
    "wof:name":"Khomutovo",
    "wof:placetype":"locality"
},
  "geometry": {"coordinates":[40.83073,57.46821],"type":"Point"}
}