{
  "type": "Feature",
  "properties": {
    "gn:admin1_code":"61",
    "gn:asciiname":"Nadezhda",
    "gn:country_code":"RU",
    "gn:dem":31,
    "gn:feature_class":"P",
    "gn:feature_code":"PPL",
    "gn:name":"Nadezhda",
    "gn:population":0,
    "gn:timezone":"Europe/Moscow",
    "iso:country":"RU",
    "name:rus_x_preferred":[
        "\u041d\u0430\u0434\u0435\u0436\u0434\u0430"
    ],
    "name:ukr_x_preferred":[
        "Nadyezhda"
    ],
    "name:und_x_variant":[
        "Novaya Nadezhda",
        "Nadezhda"
    ],
    "wof:name":"Nadezhda",
    "wof:placetype":"locality"
},
  "geometry": {"coordinates":[38.83856,47.64476],"type":"Point"}
}