{
  "type": "Feature",
  "properties": {
    "gn:admin1_code":"10",
    "gn:asciiname":"Staraya Pogoshch'",
    "gn:country_code":"RU",
    "gn:dem":154,
    "gn:feature_class":"P",
    "gn:feature_code":"PPL",
    "gn:name":"Staraya Pogoshch\u2019",
    "gn:population":0,
    "gn:timezone":"Europe/Moscow",
    "iso:country":"RU",
    "name:rus_x_preferred":[
        "\u0421\u0442\u0430\u0440\u0430\u044f \u041f\u043e\u0433\u043e\u0449\u044c"
    ],
    "name:rus_x_variant":[
        "Staraya Pogoshch\u2019",
        "Stary Pogoshch\u2019"
    ],
    "name:und_x_variant":[
        "Pogoshch"
    ],
    "wof:name":"Staraya Pogoshch'",
    "wof:placetype":"locality"
},
  "geometry": {"coordinates":[33.91164000000001,52.36906],"type":"Point"}
}