{
  "type": "Feature",
  "properties": {
    "gn:admin1_code":"61",
    "gn:asciiname":"Dvuruch'ye",
    "gn:country_code":"RU",
    "gn:dem":36,
    "gn:feature_class":"P",
    "gn:feature_code":"PPL",
    "gn:name":"Dvuruch\u2019ye",
    "gn:population":0,
    "gn:timezone":"Europe/Moscow",
    "iso:country":"RU",
    "name:rus_x_preferred":[
        "\u0414\u0432\u0443\u0440\u0443\u0447\u044c\u0435"
    ],
    "name:und_x_variant":[
        "Dvuruch\u2019ye",
        "Dvurech\u2019ye"
    ],
    "wof:name":"Dvuruch'ye",
    "wof:placetype":"locality"
},
  "geometry": {"coordinates":[40.0546,46.8501],"type":"Point"}
}