{
  "type": "Feature",
  "properties": {
    "gn:admin1_code":"60",
    "gn:asciiname":"Prokopino",
    "gn:country_code":"RU",
    "gn:dem":170,
    "gn:feature_class":"P",
    "gn:feature_code":"PPL",
    "gn:name":"Prokopino",
    "gn:population":0,
    "gn:timezone":"Europe/Moscow",
    "iso:country":"RU",
    "name:rus_x_preferred":[
        "\u041f\u0440\u043e\u043a\u043e\u043f\u0438\u043d\u043e"
    ],
    "name:und_x_variant":[
        "\u041f\u0440\u043e\u043a\u043e\u043f\u0438\u043d\u043e"
    ],
    "wof:name":"Prokopino",
    "wof:placetype":"locality"
},
  "geometry": {"coordinates":[30.0277,56.7909],"type":"Point"}
}