{
  "type": "Feature",
  "properties": {
    "iso:country":"RU",
    "qs:name":"Priozerskiy Rayon",
    "qs:name_adm0":"Russia",
    "qs:name_adm1":"Leningrad Oblast",
    "qs:photos":77,
    "qs:photos_1k":16,
    "qs:photos_9k":1,
    "qs:photos_9r":3,
    "qs:photos_all":77,
    "qs:photos_sr":3,
    "qs:placetype":"Town",
    "qs:pop_sr":"0",
    "wof:name":"Priozerskiy Rayon",
    "wof:placetype":"locality"
},
  "geometry": {"coordinates":[30.123169,61.031207],"type":"Point"}
}