{
  "type": "Feature",
  "properties": {
    "gn:admin1_code":"77.0",
    "gn:asciiname":"Feshkovo",
    "gn:country_code":"RU",
    "gn:dem":259,
    "gn:feature_class":"P",
    "gn:feature_code":"PPL",
    "gn:name":"Feshkovo",
    "gn:population":0,
    "gn:timezone":"Europe/Moscow",
    "iso:country":"RU",
    "name:rus_x_preferred":[
        "\u0424\u0435\u0448\u043a\u043e\u0432\u043e"
    ],
    "wof:name":"Feshkovo",
    "wof:placetype":"locality"
},
  "geometry": {"coordinates":[33.87902,57.13351],"type":"Point"}
}