{
  "type": "Feature",
  "properties": {
    "gn:admin1_code":"73",
    "gn:asciiname":"Novoye Mamonino",
    "gn:country_code":"RU",
    "gn:dem":62,
    "gn:feature_class":"P",
    "gn:feature_code":"PPL",
    "gn:name":"Novoye Mamonino",
    "gn:population":0,
    "gn:timezone":"Europe/Moscow",
    "iso:country":"RU",
    "name:rus_x_preferred":[
        "\u041d\u043e\u0432oe \u041c\u0430\u043c\u043e\u043d\u0438\u043d\u043e"
    ],
    "wof:name":"Novoye Mamonino",
    "wof:placetype":"locality"
},
  "geometry": {"coordinates":[49.29762,55.95786],"type":"Point"}
}