{
  "type": "Feature",
  "properties": {
    "gn:admin1_code":"6",
    "gn:asciiname":"Shetogorka",
    "gn:country_code":"RU",
    "gn:dem":183,
    "gn:feature_class":"P",
    "gn:feature_code":"PPL",
    "gn:name":"Shetogorka",
    "gn:population":0,
    "gn:timezone":"Europe/Moscow",
    "iso:country":"RU",
    "name:rus_x_preferred":[
        "\u0428\u0435\u0442\u043e\u0433\u043e\u0440\u043a\u0430"
    ],
    "wof:name":"Shetogorka",
    "wof:placetype":"locality"
},
  "geometry": {"coordinates":[43.66667,63.55],"type":"Point"}
}