{
  "type": "Feature",
  "properties": {
    "gn:admin1_code":"49",
    "gn:asciiname":"Hoikkala",
    "gn:cc2":"RU",
    "gn:country_code":"RU",
    "gn:dem":174,
    "gn:feature_class":"P",
    "gn:feature_code":"PPL",
    "gn:name":"Hoikkala",
    "gn:population":0,
    "gn:timezone":"Europe/Moscow",
    "iso:country":"RU",
    "name:rus_x_preferred":[
        "\u0425\u043e\u0439\u043a\u043a\u0430\u043b\u0430"
    ],
    "name:und_x_variant":[
        "Khoykkala"
    ],
    "wof:name":"Hoikkala",
    "wof:placetype":"locality"
},
  "geometry": {"coordinates":[30.13138,66.77729000000001],"type":"Point"}
}