{
  "type": "Feature",
  "properties": {
    "gn:admin1_code":"69",
    "gn:asciiname":"Pecherskaya Buda",
    "gn:country_code":"RU",
    "gn:dem":173,
    "gn:feature_class":"P",
    "gn:feature_code":"PPL",
    "gn:name":"Pecherskaya Buda",
    "gn:population":0,
    "gn:timezone":"Europe/Moscow",
    "iso:country":"RU",
    "name:rus_x_preferred":[
        "\u041f\u0435\u0447\u0435\u0440\u0441\u043a\u0430\u044f \u0411\u0443\u0434\u0430"
    ],
    "wof:name":"Pecherskaya Buda",
    "wof:placetype":"locality"
},
  "geometry": {"coordinates":[32.29616,54.11878000000001],"type":"Point"}
}