{
  "type": "Feature",
  "properties": {
    "gn:admin1_code":"85.0",
    "gn:asciiname":"Anikovskaya",
    "gn:country_code":"RU",
    "gn:dem":163,
    "gn:feature_class":"P",
    "gn:feature_code":"PPL",
    "gn:name":"Anikovskaya",
    "gn:population":0,
    "gn:timezone":"Europe/Moscow",
    "iso:country":"RU",
    "name:nor_x_preferred":[
        "Anikovskaja"
    ],
    "name:rus_x_preferred":[
        "\u0410\u043d\u0438\u043a\u043e\u0432\u0441\u043a\u0430\u044f"
    ],
    "wof:name":"Anikovskaya",
    "wof:placetype":"locality"
},
  "geometry": {"coordinates":[40.72284000000001,60.0223],"type":"Point"}
}