{
  "type": "Feature",
  "properties": {
    "gn:admin1_code":"8",
    "gn:asciiname":"Cheganly",
    "gn:country_code":"RU",
    "gn:dem":186,
    "gn:feature_class":"P",
    "gn:feature_code":"PPL",
    "gn:name":"Cheganly",
    "gn:population":0,
    "gn:timezone":"Asia/Yekaterinburg",
    "iso:country":"RU",
    "name:bak_x_preferred":[
        "\u0421\u0430\u0493\u0430\u043d\u043b\u044b"
    ],
    "name:che_x_preferred":[
        "\u0427\u0435\u0433\u0430\u043d\u043b\u044b"
    ],
    "name:hye_x_preferred":[
        "\u0549\u0565\u0563\u0561\u0576\u056c\u056b"
    ],
    "name:kaz_x_preferred":[
        "\u0427\u0435\u0433\u0430\u043d\u043b\u044b"
    ],
    "name:rus_x_preferred":[
        "\u0427\u0435\u0433\u0430\u043d\u043b\u044b"
    ],
    "name:tat_x_preferred":[
        "\u0427\u0430\u0433\u0430\u043d\u043b\u044b"
    ],
    "name:ukr_x_preferred":[
        "\u0427\u0435\u0433\u0430\u043d\u043b\u0438"
    ],
    "wof:name":"Cheganly",
    "wof:placetype":"locality"
},
  "geometry": {"coordinates":[54.0865,54.2578],"type":"Point"}
}