{
  "type": "Feature",
  "properties": {
    "gn:admin1_code":"80",
    "gn:asciiname":"Staraya Igra",
    "gn:country_code":"RU",
    "gn:dem":114,
    "gn:feature_class":"P",
    "gn:feature_code":"PPL",
    "gn:name":"Staraya Igra",
    "gn:population":0,
    "gn:timezone":"Europe/Samara",
    "iso:country":"RU",
    "name:rus_x_preferred":[
        "\u0421\u0442\u0430\u0440\u0430\u044f \u0418\u0433\u0440\u0430"
    ],
    "wof:name":"Staraya Igra",
    "wof:placetype":"locality"
},
  "geometry": {"coordinates":[52.1474,55.9331],"type":"Point"}
}