{
  "type": "Feature",
  "properties": {
    "gn:admin1_code":"91",
    "gn:asciiname":"Minushka",
    "gn:country_code":"RU",
    "gn:dem":294,
    "gn:feature_class":"P",
    "gn:feature_code":"PPL",
    "gn:name":"Minushka",
    "gn:population":0,
    "gn:timezone":"Asia/Krasnoyarsk",
    "iso:country":"RU",
    "name:eng_x_preferred":[
        "Minushka"
    ],
    "name:nor_x_preferred":[
        "Minusjka"
    ],
    "name:rus_x_preferred":[
        "\u041c\u0438\u043d\u0443\u0448\u043a\u0430"
    ],
    "wof:name":"Minushka",
    "wof:placetype":"locality"
},
  "geometry": {"coordinates":[95.89490000000001,55.4007],"type":"Point"}
}