{
  "type": "Feature",
  "properties": {
    "gn:admin1_code":"60",
    "gn:asciiname":"Borovskiye",
    "gn:country_code":"RU",
    "gn:dem":86,
    "gn:feature_class":"P",
    "gn:feature_code":"PPL",
    "gn:name":"Borovskiye",
    "gn:population":0,
    "gn:timezone":"Europe/Moscow",
    "iso:country":"RU",
    "name:rus_x_preferred":[
        "\u0411\u043e\u0440\u043e\u0432\u0441\u043a\u0438\u0435"
    ],
    "wof:name":"Borovskiye",
    "wof:placetype":"locality"
},
  "geometry": {"coordinates":[28.33687,57.25958000000001],"type":"Point"}
}