{
  "type": "Feature",
  "properties": {
    "gn:admin1_code":"71",
    "gn:asciiname":"Savinova",
    "gn:country_code":"RU",
    "gn:dem":109,
    "gn:feature_class":"P",
    "gn:feature_code":"PPL",
    "gn:name":"Savinova",
    "gn:population":0,
    "gn:timezone":"Asia/Yekaterinburg",
    "iso:country":"RU",
    "name:eng_x_preferred":[
        "Savinova"
    ],
    "name:nor_x_preferred":[
        "Savinova"
    ],
    "name:rus_x_preferred":[
        "\u0421\u0430\u0432\u0438\u043d\u043e\u0432\u0430"
    ],
    "name:und_x_variant":[
        "Savinovo"
    ],
    "wof:name":"Savinova",
    "wof:placetype":"locality"
},
  "geometry": {"coordinates":[60.33702,59.0208],"type":"Point"}
}