{
  "type": "Feature",
  "properties": {
    "gn:admin1_code":"86",
    "gn:asciiname":"Partizan",
    "gn:country_code":"RU",
    "gn:dem":144,
    "gn:feature_class":"P",
    "gn:feature_code":"PPL",
    "gn:name":"Partizan",
    "gn:population":0,
    "gn:timezone":"Europe/Moscow",
    "iso:country":"RU",
    "name:bos_x_preferred":[
        "Partizan"
    ],
    "name:ceb_x_preferred":[
        "Partizan"
    ],
    "name:deu_x_preferred":[
        "Partizan"
    ],
    "name:fra_x_preferred":[
        "Partizan"
    ],
    "name:hrv_x_preferred":[
        "Partizan"
    ],
    "name:hun_x_preferred":[
        "Partiz\u00e1n"
    ],
    "name:kor_x_preferred":[
        "\ube68\uce58\uc0b0"
    ],
    "name:mon_x_preferred":[
        "\u041f\u0430\u0440\u0442\u0438\u0437\u0430\u043d"
    ],
    "name:ron_x_preferred":[
        "Partizan"
    ],
    "name:rus_x_preferred":[
        "\u041f\u0430\u0440\u0442\u0438\u0437\u0430\u043d"
    ],
    "name:srp_x_preferred":[
        "\u041f\u0430\u0440\u0442\u0438\u0437\u0430\u043d"
    ],
    "name:swe_x_preferred":[
        "Partizan"
    ],
    "name:tur_x_preferred":[
        "Partizan"
    ],
    "name:ukr_x_preferred":[
        "\u041f\u0430\u0440\u0442\u0438\u0437\u0430\u043d"
    ],
    "wof:name":"Partizan",
    "wof:placetype":"locality"
},
  "geometry": {"coordinates":[40.076,51.5237],"type":"Point"}
}