{
  "type": "Feature",
  "properties": {
    "gn:admin1_code":"90",
    "gn:asciiname":"Verkhniy Shavlyash",
    "gn:country_code":"RU",
    "gn:dem":165,
    "gn:feature_class":"P",
    "gn:feature_code":"PPL",
    "gn:name":"Verkhniy Shavlyash",
    "gn:population":0,
    "gn:timezone":"Asia/Yekaterinburg",
    "iso:country":"RU",
    "name:rus_x_preferred":[
        "\u0412\u0435\u0440\u0445\u043d\u0438\u0439 \u0428\u0430\u0432\u043b\u044f\u0448"
    ],
    "wof:name":"Verkhniy Shavlyash",
    "wof:placetype":"locality"
},
  "geometry": {"coordinates":[56.5578,57.4236],"type":"Point"}
}