{
  "type": "Feature",
  "properties": {
    "gn:admin1_code":"6.0",
    "gn:asciiname":"Krivyye Ozera",
    "gn:country_code":"RU",
    "gn:dem":29,
    "gn:feature_class":"P",
    "gn:feature_code":"PPL",
    "gn:name":"Krivyye Oz\u00ebra",
    "gn:population":0,
    "gn:timezone":"Europe/Moscow",
    "iso:country":"RU",
    "name:rus_x_preferred":[
        "\u041a\u0440\u0438\u0432\u044b\u0435 \u041e\u0437\u0451\u0440\u0430"
    ],
    "name:und_x_variant":[
        "Krivyye Oz\u00ebra"
    ],
    "wof:name":"Krivyye Ozera",
    "wof:placetype":"locality"
},
  "geometry": {"coordinates":[43.2423,64.8801],"type":"Point"}
}