{
  "type": "Feature",
  "properties": {
    "gn:admin1_code":"90",
    "gn:asciiname":"Kalinichi",
    "gn:country_code":"RU",
    "gn:dem":195,
    "gn:feature_class":"P",
    "gn:feature_code":"PPL",
    "gn:name":"Kalinichi",
    "gn:population":0,
    "gn:timezone":"Asia/Yekaterinburg",
    "iso:country":"RU",
    "name:che_x_preferred":[
        "\u041a\u0430\u043b\u0438\u043d\u0438\u0447\u0438"
    ],
    "name:rus_x_preferred":[
        "\u041a\u0430\u043b\u0438\u043d\u0438\u0447\u0438"
    ],
    "name:und_x_variant":[
        "\u041a\u0430\u043b\u0438\u043d\u0438\u0447\u0438"
    ],
    "wof:name":"Kalinichi",
    "wof:placetype":"locality"
},
  "geometry": {"coordinates":[56.7467,57.5902],"type":"Point"}
}