{
  "type": "Feature",
  "properties": {
    "gn:admin1_code":"84",
    "gn:asciiname":"Verbovskiy",
    "gn:country_code":"RU",
    "gn:dem":37,
    "gn:feature_class":"P",
    "gn:feature_code":"PPL",
    "gn:name":"Verbovskiy",
    "gn:population":0,
    "gn:timezone":"Europe/Volgograd",
    "iso:country":"RU",
    "name:eng_x_preferred":[
        "Verbovskiy"
    ],
    "name:nor_x_preferred":[
        "Verbovskij"
    ],
    "name:rus_x_preferred":[
        "\u0412\u0435\u0440\u0431\u043e\u0432\u0441\u043a\u0438\u0439"
    ],
    "name:und_x_variant":[
        "\u0412\u0435\u0440\u0431\u043e\u0432\u0441\u043a\u0438\u0439",
        "Verbovskiy"
    ],
    "wof:name":"Verbovskiy",
    "wof:placetype":"locality"
},
  "geometry": {"coordinates":[43.57664000000001,48.51566],"type":"Point"}
}