{
  "type": "Feature",
  "properties": {
    "gn:admin1_code":"53",
    "gn:asciiname":"Novoalekseyevka",
    "gn:country_code":"RU",
    "gn:dem":103,
    "gn:feature_class":"P",
    "gn:feature_code":"PPL",
    "gn:name":"Novoalekseyevka",
    "gn:population":0,
    "gn:timezone":"Asia/Novosibirsk",
    "iso:country":"RU",
    "name:eng_x_preferred":[
        "Novoalekseyevka"
    ],
    "name:nor_x_preferred":[
        "Novoaleksejevka"
    ],
    "name:rus_x_preferred":[
        "\u041d\u043e\u0432\u043e\u0430\u043b\u0435\u043a\u0441\u0435\u0435\u0432\u043a\u0430"
    ],
    "wof:name":"Novoalekseyevka",
    "wof:placetype":"locality"
},
  "geometry": {"coordinates":[76.60724,54.78647],"type":"Point"}
}