{
  "type": "Feature",
  "properties": {
    "gn:admin1_code":"73",
    "gn:asciiname":"Rybopitomnik Sokury",
    "gn:country_code":"RU",
    "gn:dem":55,
    "gn:feature_class":"P",
    "gn:feature_code":"PPL",
    "gn:name":"Rybopitomnik Sokury",
    "gn:population":0,
    "gn:timezone":"Europe/Moscow",
    "iso:country":"RU",
    "name:rus_x_preferred":[
        "\u0420\u044b\u0431\u043e\u043f\u0438\u0442\u043e\u043c\u043d\u0438\u043a \u0421\u043e\u043a\u0443\u0440\u044b"
    ],
    "wof:name":"Rybopitomnik Sokury",
    "wof:placetype":"locality"
},
  "geometry": {"coordinates":[49.38916,55.58443000000001],"type":"Point"}
}