{
  "type": "Feature",
  "properties": {
    "gn:admin1_code":"90",
    "gn:asciiname":"Sim",
    "gn:country_code":"RU",
    "gn:dem":152,
    "gn:feature_class":"P",
    "gn:feature_code":"PPL",
    "gn:name":"Sim",
    "gn:population":0,
    "gn:timezone":"Asia/Yekaterinburg",
    "iso:country":"RU",
    "name:bre_x_preferred":[
        "Sim"
    ],
    "name:cat_x_preferred":[
        "Sim"
    ],
    "name:ceb_x_preferred":[
        "Sim"
    ],
    "name:eng_x_preferred":[
        "Sim"
    ],
    "name:kat_x_preferred":[
        "\u10e1\u10d8\u10db\u10d8"
    ],
    "name:nld_x_preferred":[
        "Sim"
    ],
    "name:nor_x_preferred":[
        "Sim"
    ],
    "name:por_x_preferred":[
        "Sim"
    ],
    "name:rus_x_preferred":[
        "\u0421\u0438\u043c"
    ],
    "name:spa_x_preferred":[
        "Sim"
    ],
    "name:swe_x_preferred":[
        "SIM"
    ],
    "name:und_x_variant":[
        "Tsentral\u2019nyy Sim",
        "Vogulka",
        "Sim",
        "\u0421\u0438\u043c"
    ],
    "name:vie_x_preferred":[
        "Sim"
    ],
    "wof:name":"Sim",
    "wof:placetype":"locality"
},
  "geometry": {"coordinates":[57.3539,59.8681],"type":"Point"}
}