{
  "type": "Feature",
  "properties": {
    "gn:admin1_code":"44",
    "gn:asciiname":"Nagayevo",
    "gn:cc2":"RU",
    "gn:country_code":"RU",
    "gn:dem":46,
    "gn:feature_class":"P",
    "gn:feature_code":"PPL",
    "gn:name":"Nagayevo",
    "gn:population":0,
    "gn:timezone":"Asia/Magadan",
    "iso:country":"RU",
    "name:rus_x_preferred":[
        "\u041d\u0430\u0433\u0430\u0435\u0432\u043e"
    ],
    "name:und_x_variant":[
        "Nagaevo",
        "Nagayeuo",
        "Nagayevo",
        "\u041d\u0430\u0433\u0430\u0435\u0432\u043e",
        "Nogaevo",
        "Naga\u2019yeva"
    ],
    "wof:name":"Nagayevo",
    "wof:placetype":"locality"
},
  "geometry": {"coordinates":[150.78333000000001,59.55],"type":"Point"}
}