{
  "type": "Feature",
  "properties": {
    "gn:admin1_code":"77",
    "gn:asciiname":"Kriushino",
    "gn:country_code":"RU",
    "gn:dem":211,
    "gn:feature_class":"P",
    "gn:feature_code":"PPL",
    "gn:name":"Kriushino",
    "gn:population":0,
    "gn:timezone":"Europe/Moscow",
    "iso:country":"RU",
    "name:rus_x_preferred":[
        "\u041a\u0440\u0438y\u0448\u0438\u043d\u043e"
    ],
    "name:und_x_variant":[
        "Krivshino",
        "Kriushino"
    ],
    "wof:name":"Kriushino",
    "wof:placetype":"locality"
},
  "geometry": {"coordinates":[32.74494,56.72097],"type":"Point"}
}