{
  "type": "Feature",
  "properties": {
    "gn:admin1_code":"45.0",
    "gn:asciiname":"Kugunur",
    "gn:country_code":"RU",
    "gn:dem":143,
    "gn:feature_class":"P",
    "gn:feature_code":"PPL",
    "gn:name":"Kugunur",
    "gn:population":0,
    "gn:timezone":"Europe/Moscow",
    "iso:country":"RU",
    "name:rus_x_preferred":[
        "\u041a\u0443\u0433\u0443\u043d\u0443\u0440"
    ],
    "wof:name":"Kugunur",
    "wof:placetype":"locality"
},
  "geometry": {"coordinates":[48.22444,56.19306],"type":"Point"}
}