{
  "type": "Feature",
  "properties": {
    "gn:admin1_code":"52.0",
    "gn:asciiname":"Bol'shoye Yel'no",
    "gn:country_code":"RU",
    "gn:dem":119,
    "gn:feature_class":"P",
    "gn:feature_code":"PPL",
    "gn:name":"Bol\u2019shoye Yel\u2019no",
    "gn:population":0,
    "gn:timezone":"Europe/Moscow",
    "iso:country":"RU",
    "name:rus_x_preferred":[
        "\u0411\u043e\u043b\u044c\u0448\u043e\u0435 \u0415\u043b\u044c\u043d\u043e"
    ],
    "name:und_x_variant":[
        "Bol\u2019shaya Yel\u2019nya",
        "Bol\u2019shoye Yel\u2019no",
        "\u0411\u043e\u043b\u044c\u0448\u043e\u0435 \u0415\u043b\u044c\u043d\u043e"
    ],
    "wof:name":"Bol'shoye Yel'no",
    "wof:placetype":"locality"
},
  "geometry": {"coordinates":[31.36502,56.9815],"type":"Point"}
}