{
  "type": "Feature",
  "properties": {
    "gn:admin1_code":"38",
    "gn:asciiname":"Kirkorova",
    "gn:country_code":"RU",
    "gn:dem":358,
    "gn:feature_class":"P",
    "gn:feature_code":"PPL",
    "gn:name":"Kirkorova",
    "gn:population":0,
    "gn:timezone":"Europe/Moscow",
    "iso:country":"RU",
    "wof:name":"Kirkorova",
    "wof:placetype":"locality"
},
  "geometry": {"coordinates":[39.21778,44.41528],"type":"Point"}
}