{
  "type": "Feature",
  "properties": {
    "gn:admin1_code":"34",
    "gn:asciiname":"Ruzga-Yel'",
    "gn:country_code":"RU",
    "gn:dem":155,
    "gn:feature_class":"P",
    "gn:feature_code":"PPL",
    "gn:name":"Ruzga-Y\u00ebl\u2019",
    "gn:population":0,
    "gn:timezone":"Europe/Moscow",
    "iso:country":"RU",
    "name:rus_x_preferred":[
        "\u0420\u0443\u0437\u0433\u0430-\u0401\u043b\u044c"
    ],
    "name:und_x_variant":[
        "Ruzga-Y\u00ebl\u2019",
        "\u0420\u0443\u0437\u0433\u0430-\u0401\u043b\u044c"
    ],
    "wof:name":"Ruzga-Yel'",
    "wof:placetype":"locality"
},
  "geometry": {"coordinates":[49.31667,59.65],"type":"Point"}
}