{
  "type": "Feature",
  "properties": {
    "gn:admin1_code":"28",
    "gn:admin2_code":"505244",
    "gn:asciiname":"Yashezero",
    "gn:cc2":"RU",
    "gn:country_code":"RU",
    "gn:dem":52,
    "gn:feature_class":"P",
    "gn:feature_code":"PPL",
    "gn:name":"Yash\u00ebzero",
    "gn:population":0,
    "gn:timezone":"Europe/Moscow",
    "iso:country":"RU",
    "name:eng_x_preferred":[
        "Yash\u00ebzero"
    ],
    "name:fin_x_preferred":[
        "J\u00e4\u00e4sj\u00e4rvi"
    ],
    "name:nor_x_preferred":[
        "Jasjezero"
    ],
    "name:rus_x_preferred":[
        "\u042f\u0448\u0435\u0437\u0435\u0440\u043e"
    ],
    "name:und_x_variant":[
        "Yashozero"
    ],
    "wof:name":"Yashezero",
    "wof:placetype":"locality"
},
  "geometry": {"coordinates":[34.94167,61.32745],"type":"Point"}
}