{
  "type": "Feature",
  "properties": {
    "gn:admin1_code":"57",
    "gn:asciiname":"Novaya Nazvanovka",
    "gn:country_code":"RU",
    "gn:dem":183,
    "gn:feature_class":"P",
    "gn:feature_code":"PPL",
    "gn:name":"Novaya Nazvanovka",
    "gn:population":0,
    "gn:timezone":"Europe/Moscow",
    "iso:country":"RU",
    "name:rus_x_preferred":[
        "\u041d\u043e\u0432\u0430\u044f \u041d\u0430\u0437\u0432\u0430\u043d\u043e\u0432\u043a\u0430"
    ],
    "name:und_x_variant":[
        "Novonazvanovka",
        "Novaya Nazvanovka"
    ],
    "wof:name":"Novaya Nazvanovka",
    "wof:placetype":"locality"
},
  "geometry": {"coordinates":[44.49555,52.61152],"type":"Point"}
}