{
  "type": "Feature",
  "properties": {
    "gn:admin1_code":"77",
    "gn:asciiname":"Chaplinka",
    "gn:country_code":"RU",
    "gn:dem":134,
    "gn:feature_class":"P",
    "gn:feature_code":"PPL",
    "gn:name":"Chaplinka",
    "gn:population":0,
    "gn:timezone":"Europe/Moscow",
    "iso:country":"RU",
    "name:rus_x_preferred":[
        "\u0427\u0430\u043f\u043b\u0438\u043d\u043a\u0430"
    ],
    "wof:name":"Chaplinka",
    "wof:placetype":"locality"
},
  "geometry": {"coordinates":[37.8114,57.2915],"type":"Point"}
}