{
  "type": "Feature",
  "properties": {
    "gn:admin1_code":"11",
    "gn:asciiname":"Nizhnyaya Stepanikha",
    "gn:country_code":"RU",
    "gn:dem":879,
    "gn:feature_class":"P",
    "gn:feature_code":"PPL",
    "gn:name":"Nizhnyaya Stepanikha",
    "gn:population":0,
    "gn:timezone":"Asia/Irkutsk",
    "iso:country":"RU",
    "name:rus_x_preferred":[
        "\u041d\u0438\u0436\u043d\u044f\u044f \u0421\u0442\u0435\u043f\u0430\u043d\u0438\u0445\u0430"
    ],
    "name:und_x_variant":[
        "\u041d\u0438\u0436\u043d\u044f\u044f \u0421\u0442\u0435\u043f\u0430\u043d\u0438\u0445\u0430"
    ],
    "wof:name":"Nizhnyaya Stepanikha",
    "wof:placetype":"locality"
},
  "geometry": {"coordinates":[114.09999999999999,54.53333000000001],"type":"Point"}
}