{
  "type": "Feature",
  "properties": {
    "gn:admin1_code":"57",
    "gn:asciiname":"Koshkarovo",
    "gn:country_code":"RU",
    "gn:dem":210,
    "gn:feature_class":"P",
    "gn:feature_code":"PPL",
    "gn:name":"Koshkarovo",
    "gn:population":0,
    "gn:timezone":"Europe/Moscow",
    "iso:country":"RU",
    "name:rus_x_preferred":[
        "\u041a\u043e\u0448\u043a\u0430\u0440\u043e\u0432\u043e"
    ],
    "name:und_x_variant":[
        "\u041a\u043e\u0448\u043a\u0430\u0440\u043e\u0432\u043e"
    ],
    "wof:name":"Koshkarovo",
    "wof:placetype":"locality"
},
  "geometry": {"coordinates":[43.64327,53.03491],"type":"Point"}
}