{
  "type": "Feature",
  "properties": {
    "gn:admin1_code":"83.0",
    "gn:asciiname":"Bezvodnoye",
    "gn:country_code":"RU",
    "gn:dem":132,
    "gn:feature_class":"P",
    "gn:feature_code":"PPL",
    "gn:name":"Bezvodnoye",
    "gn:population":0,
    "gn:timezone":"Europe/Moscow",
    "iso:country":"RU",
    "name:rus_x_preferred":[
        "\u0411\u0435\u0437\u0432\u043e\u0434\u043d\u043e\u0435"
    ],
    "wof:name":"Bezvodnoye",
    "wof:placetype":"locality"
},
  "geometry": {"coordinates":[40.0103,56.19178],"type":"Point"}
}