{
  "type": "Feature",
  "properties": {
    "gn:admin1_code":"20",
    "gn:asciiname":"Verkhnemartynovo",
    "gn:country_code":"RU",
    "gn:dem":302,
    "gn:feature_class":"P",
    "gn:feature_code":"PPL",
    "gn:name":"Verkhnemartynovo",
    "gn:population":0,
    "gn:timezone":"Asia/Irkutsk",
    "iso:country":"RU",
    "wof:name":"Verkhnemartynovo",
    "wof:placetype":"locality"
},
  "geometry": {"coordinates":[108.16804999999999,56.88906],"type":"Point"}
}