{
  "type": "Feature",
  "properties": {
    "gn:admin1_code":"3",
    "gn:asciiname":"Vtoraya Ulyuta",
    "gn:country_code":"RU",
    "gn:dem":1127,
    "gn:feature_class":"P",
    "gn:feature_code":"PPL",
    "gn:name":"Vtoraya Ulyuta",
    "gn:population":0,
    "gn:timezone":"Asia/Omsk",
    "iso:country":"RU",
    "wof:name":"Vtoraya Ulyuta",
    "wof:placetype":"locality"
},
  "geometry": {"coordinates":[86.23333000000002,50.95],"type":"Point"}
}