{
  "type": "Feature",
  "properties": {
    "gn:country":"RU",
    "gn:fcode":"PPL",
    "gn:population":3371,
    "iso:country":"RU",
    "name:eng_x_preferred":[
        "Uzunovo"
    ],
    "name:nor_x_preferred":[
        "Uzunovo"
    ],
    "name:rus_x_preferred":[
        "\u0423\u0437\u0443\u043d\u043e\u0432\u043e"
    ],
    "qs:name":"Uzunovo",
    "qs:photos_9r":0,
    "qs:photos_sr":0,
    "qs:pop_sr":"4",
    "wof:name":"Uzunovo",
    "wof:placetype":"locality",
    "wof:population":3371
},
  "geometry": {"coordinates":[38.61734,54.53858],"type":"Point"}
}