{
  "type": "Feature",
  "properties": {
    "iso:country":"RU",
    "name:eng_x_variant":[
        "Chertanovo North"
    ],
    "name:rus_x_preferred":[
        "\u0427\u0435\u0440\u0442\u0430\u043d\u043e\u0432\u043e \u0421\u0435\u0432\u0435\u0440\u043d\u043e\u0435"
    ],
    "wof:name":"Chertanovo Severnoye",
    "wof:placetype":"neighbourhood"
},
  "geometry": {"coordinates":[37.60550689824404,55.63183065227551],"type":"Point"}
}