{
  "type": "Feature",
  "properties": {
    "gn:admin1_code":"84",
    "gn:asciiname":"Zolotari",
    "gn:country_code":"RU",
    "gn:dem":27,
    "gn:feature_class":"P",
    "gn:feature_code":"PPL",
    "gn:name":"Zolotari",
    "gn:population":0,
    "gn:timezone":"Europe/Volgograd",
    "iso:country":"RU",
    "name:eng_x_preferred":[
        "Zolotari"
    ],
    "name:nor_x_preferred":[
        "Zolotari"
    ],
    "name:rus_x_preferred":[
        "\u0417\u043e\u043b\u043e\u0442\u0430\u0440\u0438"
    ],
    "wof:name":"Zolotari",
    "wof:placetype":"locality"
},
  "geometry": {"coordinates":[46.44994000000001,49.76281],"type":"Point"}
}