{
  "type": "Feature",
  "properties": {
    "gn:admin1_code":"61.0",
    "gn:asciiname":"Denisovo-Nikolayevka",
    "gn:cc2":"RU",
    "gn:country_code":"RU",
    "gn:dem":73,
    "gn:feature_class":"P",
    "gn:feature_code":"PPL",
    "gn:name":"Denisovo-Nikolayevka",
    "gn:population":0,
    "gn:timezone":"Europe/Moscow",
    "iso:country":"RU",
    "name:rus_x_preferred":[
        "\u0414\u0435\u043d\u0438\u0441\u043e\u0432\u043e-\u041d\u0438\u043a\u043e\u043b\u0430\u0435\u0432\u043a\u0430"
    ],
    "name:und_x_variant":[
        "Denisovo-Vasil\u2019yevka",
        "Denisovo-Nikolayevka",
        "\u0414\u0435\u043d\u0438\u0441\u043e\u0432\u043e-\u041d\u0438\u043a\u043e\u043b\u0430\u0435\u0432\u043a\u0430"
    ],
    "wof:name":"Denisovo-Nikolayevka",
    "wof:placetype":"locality"
},
  "geometry": {"coordinates":[39.28333,47.75806],"type":"Point"}
}