{
  "type": "Feature",
  "properties": {
    "gn:admin1_code":"57.0",
    "gn:asciiname":"Akimovshchina",
    "gn:country_code":"RU",
    "gn:dem":157,
    "gn:feature_class":"P",
    "gn:feature_code":"PPL",
    "gn:name":"Akimovshchina",
    "gn:population":0,
    "gn:timezone":"Europe/Moscow",
    "iso:country":"RU",
    "name:nor_x_preferred":[
        "Akimovsjtsjina"
    ],
    "name:rus_x_preferred":[
        "\u0410\u043a\u0438\u043c\u043e\u0432\u0449\u0438\u043d\u0430"
    ],
    "name:und_x_variant":[
        "Yakimovshchino",
        "Akimovshchina"
    ],
    "wof:name":"Akimovshchina",
    "wof:placetype":"locality"
},
  "geometry": {"coordinates":[43.60549,53.7484],"type":"Point"}
}