{
  "type": "Feature",
  "properties": {
    "gn:admin1_code":"47",
    "gn:admin2_code":"472430",
    "gn:asciiname":"Shishkovo",
    "gn:country_code":"RU",
    "gn:dem":147,
    "gn:feature_class":"P",
    "gn:feature_code":"PPL",
    "gn:name":"Shishkovo",
    "gn:population":0,
    "gn:timezone":"Europe/Moscow",
    "iso:country":"RU",
    "name:nor_x_preferred":[
        "Sjisjkovo"
    ],
    "name:rus_x_preferred":[
        "\u0428\u0438\u0448\u043a\u043e\u0432\u043e"
    ],
    "wof:name":"Shishkovo",
    "wof:placetype":"locality"
},
  "geometry": {"coordinates":[35.90952,56.15257],"type":"Point"}
}