{
  "type": "Feature",
  "properties": {
    "gn:admin1_code":"62",
    "gn:asciiname":"Novoye Romanovo",
    "gn:country_code":"RU",
    "gn:dem":130,
    "gn:feature_class":"P",
    "gn:feature_code":"PPL",
    "gn:name":"Novoye Romanovo",
    "gn:population":0,
    "gn:timezone":"Europe/Moscow",
    "iso:country":"RU",
    "name:rus_x_preferred":[
        "\u041d\u043e\u0432\u043e\u0435 \u0420\u043e\u043c\u0430\u043d\u043e\u0432\u043e"
    ],
    "name:und_x_variant":[
        "\u041d\u043e\u0432\u043e\u0435 \u0420\u043e\u043c\u0430\u043d\u043e\u0432\u043e"
    ],
    "wof:name":"Novoye Romanovo",
    "wof:placetype":"locality"
},
  "geometry": {"coordinates":[41.81667,54.11666999999999],"type":"Point"}
}