{
  "type": "Feature",
  "properties": {
    "gn:admin1_code":"60",
    "gn:asciiname":"Shkarino",
    "gn:country_code":"RU",
    "gn:dem":67,
    "gn:feature_class":"P",
    "gn:feature_code":"PPL",
    "gn:name":"Shkarino",
    "gn:population":0,
    "gn:timezone":"Europe/Moscow",
    "iso:country":"RU",
    "name:rus_x_preferred":[
        "\u0428\u043a\u0430\u0440\u0438\u043d\u043e"
    ],
    "wof:name":"Shkarino",
    "wof:placetype":"locality"
},
  "geometry": {"coordinates":[28.12375,57.4351],"type":"Point"}
}