{
  "type": "Feature",
  "properties": {
    "gn:admin1_code":"56",
    "gn:asciiname":"Podchernoye",
    "gn:country_code":"RU",
    "gn:dem":233,
    "gn:feature_class":"P",
    "gn:feature_code":"PPL",
    "gn:name":"Podch\u00ebrnoye",
    "gn:population":0,
    "gn:timezone":"Europe/Moscow",
    "iso:country":"RU",
    "name:rus_x_preferred":[
        "\u041f\u043e\u0434\u0447\u0451\u0440\u043d\u043e\u0435"
    ],
    "name:und_x_variant":[
        "Podch\u00ebrnoye",
        "\u041f\u043e\u0434\u0447\u0451\u0440\u043d\u043e\u0435"
    ],
    "wof:name":"Podchernoye",
    "wof:placetype":"locality"
},
  "geometry": {"coordinates":[36.44842,53.02858000000001],"type":"Point"}
}