{
  "type": "Feature",
  "properties": {
    "gn:admin1_code":"21",
    "gn:asciiname":"Pandino",
    "gn:country_code":"RU",
    "gn:dem":139,
    "gn:feature_class":"P",
    "gn:feature_code":"PPL",
    "gn:name":"Pandino",
    "gn:population":0,
    "gn:timezone":"Europe/Moscow",
    "iso:country":"RU",
    "name:rus_x_preferred":[
        "\u041f\u0430\u043d\u0434\u0438\u043d\u043e"
    ],
    "name:und_x_variant":[
        "Pondino",
        "Pandino",
        "\u041f\u0430\u043d\u0434\u0438\u043d\u043e"
    ],
    "wof:name":"Pandino",
    "wof:placetype":"locality"
},
  "geometry": {"coordinates":[41.98643,57.19436],"type":"Point"}
}