{
  "type": "Feature",
  "properties": {
    "gn:admin1_code":"21",
    "gn:asciiname":"Pandino",
    "gn:country_code":"RU",
    "gn:dem":139,
    "gn:feature_class":"P",
    "gn:feature_code":"PPL",
    "gn:name":"Pandino",
    "gn:population":0,
    "gn:timezone":"Europe/Moscow",
    "iso:country":"RU",
    "name:azb_x_preferred":[
        "\u067e\u0627\u0646\u062f\u06cc\u0646\u0648"
    ],
    "name:bul_x_preferred":[
        "\u041f\u0430\u043d\u0434\u0438\u043d\u043e"
    ],
    "name:ceb_x_preferred":[
        "Pandino"
    ],
    "name:deu_x_preferred":[
        "Pandino"
    ],
    "name:epo_x_preferred":[
        "Pandino"
    ],
    "name:eus_x_preferred":[
        "Pandino"
    ],
    "name:fas_x_preferred":[
        "\u067e\u0627\u0646\u062f\u06cc\u0646\u0648"
    ],
    "name:fra_x_preferred":[
        "Pandino"
    ],
    "name:hun_x_preferred":[
        "Pandino"
    ],
    "name:hye_x_preferred":[
        "\u054a\u0561\u0576\u0564\u056b\u0576\u0578"
    ],
    "name:ita_x_preferred":[
        "Pandino"
    ],
    "name:jpn_x_preferred":[
        "\u30d1\u30f3\u30c7\u30a3\u30fc\u30ce"
    ],
    "name:kaz_x_preferred":[
        "\u041f\u0430\u043d\u0434\u0438\u043d\u043e"
    ],
    "name:lat_x_preferred":[
        "Pandinum"
    ],
    "name:lmo_x_preferred":[
        "Pand\u00ec"
    ],
    "name:msa_x_preferred":[
        "Pandino"
    ],
    "name:nap_x_preferred":[
        "Pandino"
    ],
    "name:nld_x_preferred":[
        "Pandino"
    ],
    "name:pms_x_preferred":[
        "Pandino"
    ],
    "name:pol_x_preferred":[
        "Pandino"
    ],
    "name:por_x_preferred":[
        "Pandino"
    ],
    "name:ron_x_preferred":[
        "Pandino"
    ],
    "name:rus_x_preferred":[
        "\u041f\u0430\u043d\u0434\u0438\u043d\u043e"
    ],
    "name:scn_x_preferred":[
        "Pandino"
    ],
    "name:spa_x_preferred":[
        "Pandino"
    ],
    "name:srp_x_preferred":[
        "\u041f\u0430\u043d\u0434\u0438\u043d\u043e"
    ],
    "name:tur_x_preferred":[
        "Pandino"
    ],
    "name:ukr_x_preferred":[
        "\u041f\u0430\u043d\u0434\u0456\u043d\u043e"
    ],
    "name:und_x_variant":[
        "Pondino"
    ],
    "name:uzb_x_preferred":[
        "Pandino"
    ],
    "name:vie_x_preferred":[
        "Pandino"
    ],
    "name:vol_x_preferred":[
        "Pandino"
    ],
    "name:war_x_preferred":[
        "Pandino"
    ],
    "name:zho_x_preferred":[
        "\u6f58\u8fea\u8bfa"
    ],
    "wof:name":"Pandino",
    "wof:placetype":"locality"
},
  "geometry": {"coordinates":[41.98643,57.19436],"type":"Point"}
}