{
  "type": "Feature",
  "properties": {
    "gn:admin1_code":"10",
    "gn:asciiname":"Kharitonovka",
    "gn:country_code":"RU",
    "gn:dem":174,
    "gn:feature_class":"P",
    "gn:feature_code":"PPL",
    "gn:name":"Kharitonovka",
    "gn:population":0,
    "gn:timezone":"Europe/Moscow",
    "iso:country":"RU",
    "name:eng_x_preferred":[
        "Kharitonovka"
    ],
    "name:nor_x_preferred":[
        "Kharitonovka"
    ],
    "name:rus_x_preferred":[
        "\u0425\u0430\u0440\u0438\u0442\u043e\u043d\u043e\u0432\u043a\u0430"
    ],
    "wof:name":"Kharitonovka",
    "wof:placetype":"locality"
},
  "geometry": {"coordinates":[33.00419,53.39921],"type":"Point"}
}