{
  "type": "Feature",
  "properties": {
    "gn:admin1_code":"73",
    "gn:asciiname":"Karaduvan",
    "gn:country_code":"RU",
    "gn:dem":93,
    "gn:feature_class":"P",
    "gn:feature_code":"PPL",
    "gn:name":"Karaduvan",
    "gn:population":0,
    "gn:timezone":"Europe/Moscow",
    "iso:country":"RU",
    "name:rus_x_preferred":[
        "\u041a\u0430\u0440\u0430\u0434\u0443\u0432\u0430\u043d"
    ],
    "wof:name":"Karaduvan",
    "wof:placetype":"locality"
},
  "geometry": {"coordinates":[50.1015,56.3445],"type":"Point"}
}