{
  "type": "Feature",
  "properties": {
    "gn:admin1_code":"25.0",
    "gn:asciiname":"Kuklino",
    "gn:country_code":"RU",
    "gn:dem":207,
    "gn:feature_class":"P",
    "gn:feature_code":"PPL",
    "gn:name":"Kuklino",
    "gn:population":0,
    "gn:timezone":"Europe/Moscow",
    "iso:country":"RU",
    "name:und_x_variant":[
        "Verkhneye Kuklino",
        "Kuklino"
    ],
    "wof:name":"Kuklino",
    "wof:placetype":"locality"
},
  "geometry": {"coordinates":[35.10013,54.06876],"type":"Point"}
}