{
  "type": "Feature",
  "properties": {
    "gn:admin1_code":"61",
    "gn:asciiname":"Khankhotinskiy",
    "gn:country_code":"RU",
    "gn:dem":77,
    "gn:feature_class":"P",
    "gn:feature_code":"PPL",
    "gn:name":"Khankhotinskiy",
    "gn:population":0,
    "gn:timezone":"Europe/Moscow",
    "iso:country":"RU",
    "name:rus_x_preferred":[
        "\u0425\u0430\u043d\u0445\u043e\u0442\u0438\u043d\u0441\u043a\u0438\u0439"
    ],
    "name:und_x_variant":[
        "\u0425\u0430\u043d\u0445\u043e\u0442\u0438\u043d\u0441\u043a\u0438\u0439"
    ],
    "wof:name":"Khankhotinskiy",
    "wof:placetype":"locality"
},
  "geometry": {"coordinates":[40.66167,46.44611],"type":"Point"}
}