{
  "type": "Feature",
  "properties": {
    "gn:admin1_code":"81.0",
    "gn:asciiname":"Yulovka",
    "gn:country_code":"RU",
    "gn:dem":291,
    "gn:feature_class":"P",
    "gn:feature_code":"PPL",
    "gn:name":"Yulovka",
    "gn:population":0,
    "gn:timezone":"Europe/Ulyanovsk",
    "iso:country":"RU",
    "name:rus_x_preferred":[
        "\u042e\u043b\u043e\u0432\u043a\u0430"
    ],
    "wof:name":"Yulovka",
    "wof:placetype":"locality"
},
  "geometry": {"coordinates":[46.6143,53.8937],"type":"Point"}
}