{
  "type": "Feature",
  "properties": {
    "gn:admin1_code":"10",
    "gn:asciiname":"Petrovskiy",
    "gn:country_code":"RU",
    "gn:dem":182,
    "gn:feature_class":"P",
    "gn:feature_code":"PPL",
    "gn:name":"Petrovskiy",
    "gn:population":0,
    "gn:timezone":"Europe/Moscow",
    "iso:country":"RU",
    "name:rus_x_preferred":[
        "\u041f\u0435\u0442\u0440\u043e\u0432\u0441\u043a\u0438\u0439"
    ],
    "name:und_x_variant":[
        "Petrovskii",
        "Petrovskiy",
        "\u041f\u0435\u0442\u0440\u043e\u0432\u0441\u043a\u0438\u0439"
    ],
    "wof:name":"Petrovskiy",
    "wof:placetype":"locality"
},
  "geometry": {"coordinates":[33.70531,52.80773000000001],"type":"Point"}
}