{
  "type": "Feature",
  "properties": {
    "gn:admin1_code":"33",
    "gn:asciiname":"Sumchino",
    "gn:country_code":"RU",
    "gn:dem":173,
    "gn:feature_class":"P",
    "gn:feature_code":"PPL",
    "gn:name":"Sumchino",
    "gn:population":0,
    "gn:timezone":"Europe/Kirov",
    "iso:country":"RU",
    "name:eng_x_preferred":[
        "Sumchino"
    ],
    "name:nor_x_preferred":[
        "Sumtsjino"
    ],
    "name:rus_x_preferred":[
        "\u0421\u0443\u043c\u0447\u0438\u043d\u043e"
    ],
    "wof:name":"Sumchino",
    "wof:placetype":"locality"
},
  "geometry": {"coordinates":[51.53235,59.50628],"type":"Point"}
}