{
  "type": "Feature",
  "properties": {
    "gn:admin1_code":"47.0",
    "gn:asciiname":"Fedyukovo",
    "gn:country_code":"RU",
    "gn:dem":146,
    "gn:feature_class":"P",
    "gn:feature_code":"PPL",
    "gn:name":"Fedyukovo",
    "gn:population":0,
    "gn:timezone":"Europe/Moscow",
    "iso:country":"RU",
    "name:rus_x_preferred":[
        "\u0424\u0435\u0434\u044e\u043a\u043e\u0432\u043e"
    ],
    "name:und_x_variant":[
        "Fedyukova",
        "Fedyukovo"
    ],
    "wof:name":"Fedyukovo",
    "wof:placetype":"locality"
},
  "geometry": {"coordinates":[37.69256,55.51444],"type":"Point"}
}