{
  "type": "Feature",
  "properties": {
    "gn:admin1_code":"20",
    "gn:asciiname":"Sharagun",
    "gn:cc2":"RU",
    "gn:country_code":"RU",
    "gn:dem":461,
    "gn:feature_class":"P",
    "gn:feature_code":"PPL",
    "gn:name":"Sharagun",
    "gn:population":0,
    "gn:timezone":"Asia/Irkutsk",
    "iso:country":"RU",
    "name:rus_x_preferred":[
        "\u0428\u0430\u0440\u0430\u0433\u0443\u043d"
    ],
    "name:und_x_variant":[
        "Sheragun",
        "Sharagun",
        "\u0428\u0430\u0440\u0430\u0433\u0443\u043d"
    ],
    "wof:name":"Sharagun",
    "wof:placetype":"locality"
},
  "geometry": {"coordinates":[102.63333,52.78333000000001],"type":"Point"}
}