{
  "type": "Feature",
  "properties": {
    "gn:admin1_code":"60",
    "gn:asciiname":"Lekhovo",
    "gn:country_code":"RU",
    "gn:dem":83,
    "gn:feature_class":"P",
    "gn:feature_code":"PPL",
    "gn:name":"Lekhovo",
    "gn:population":0,
    "gn:timezone":"Europe/Moscow",
    "iso:country":"RU",
    "name:rus_x_preferred":[
        "\u041b\u0435\u0445\u043e\u0432\u043e"
    ],
    "name:und_x_variant":[
        "\u041b\u0435\u0445\u043e\u0432\u043e"
    ],
    "wof:name":"Lekhovo",
    "wof:placetype":"locality"
},
  "geometry": {"coordinates":[30.6486,56.7842],"type":"Point"}
}