{
  "type": "Feature",
  "properties": {
    "gn:admin1_code":"51",
    "gn:asciiname":"Loginovka",
    "gn:country_code":"RU",
    "gn:dem":195,
    "gn:feature_class":"P",
    "gn:feature_code":"PPL",
    "gn:name":"Loginovka",
    "gn:population":0,
    "gn:timezone":"Europe/Moscow",
    "iso:country":"RU",
    "name:rus_x_preferred":[
        "\u041b\u043e\u0433\u0438\u043d\u043e\u0432\u043a\u0430"
    ],
    "wof:name":"Loginovka",
    "wof:placetype":"locality"
},
  "geometry": {"coordinates":[45.2557,54.9312],"type":"Point"}
}