{
  "type": "Feature",
  "properties": {
    "gn:admin1_code":"77",
    "gn:asciiname":"Tuboss",
    "gn:country_code":"RU",
    "gn:dem":162,
    "gn:feature_class":"P",
    "gn:feature_code":"PPL",
    "gn:name":"Tuboss",
    "gn:population":0,
    "gn:timezone":"Europe/Moscow",
    "iso:country":"RU",
    "name:und_x_variant":[
        "Tubos",
        "Tubas",
        "Tuboss"
    ],
    "wof:name":"Tuboss",
    "wof:placetype":"locality"
},
  "geometry": {"coordinates":[34.3921,57.85608000000001],"type":"Point"}
}