{
  "type": "Feature",
  "properties": {
    "gn:admin1_code":"42",
    "gn:asciiname":"Korpiya",
    "gn:country_code":"RU",
    "gn:dem":154,
    "gn:feature_class":"P",
    "gn:feature_code":"PPL",
    "gn:name":"Korpiya",
    "gn:population":0,
    "gn:timezone":"Europe/Moscow",
    "iso:country":"RU",
    "name:rus_x_preferred":[
        "\u041a\u043e\u0440\u043f\u0438\u044f"
    ],
    "wof:name":"Korpiya",
    "wof:placetype":"locality"
},
  "geometry": {"coordinates":[29.35,59.51667],"type":"Point"}
}