{
  "type": "Feature",
  "properties": {
    "gn:admin1_code":"45.0",
    "gn:asciiname":"Kichiyer",
    "gn:country_code":"RU",
    "gn:dem":71,
    "gn:feature_class":"P",
    "gn:feature_code":"PPL",
    "gn:name":"Kichiyer",
    "gn:population":0,
    "gn:timezone":"Europe/Moscow",
    "iso:country":"RU",
    "name:rus_x_preferred":[
        "\u041a\u0438\u0447\u0438\u0435\u0440"
    ],
    "name:und_x_variant":[
        "\u041a\u0438\u0447\u0438\u0435\u0440"
    ],
    "wof:name":"Kichiyer",
    "wof:placetype":"locality"
},
  "geometry": {"coordinates":[48.34944,56.07417],"type":"Point"}
}