{
  "type": "Feature",
  "properties": {
    "gn:admin1_code":"34.0",
    "gn:asciiname":"Chernoborskaya",
    "gn:country_code":"RU",
    "gn:dem":36,
    "gn:feature_class":"P",
    "gn:feature_code":"PPL",
    "gn:name":"Chernoborskaya",
    "gn:population":0,
    "gn:timezone":"Europe/Moscow",
    "iso:country":"RU",
    "name:eng_x_preferred":[
        "Chernoborskaya"
    ],
    "name:nor_x_preferred":[
        "Tsjernoborskaja"
    ],
    "name:rus_x_preferred":[
        "\u0427\u0435\u0440\u043d\u043e\u0431\u043e\u0440\u0441\u043a\u0430\u044f"
    ],
    "name:und_x_variant":[
        "Chernoborskaya Izba",
        "Chernoberskaya"
    ],
    "wof:name":"Chernoborskaya",
    "wof:placetype":"locality"
},
  "geometry": {"coordinates":[53.65261,65.18720999999999],"type":"Point"}
}