{
  "type": "Feature",
  "properties": {
    "gn:admin1_code":"33.0",
    "gn:asciiname":"Froly",
    "gn:country_code":"RU",
    "gn:dem":180,
    "gn:feature_class":"P",
    "gn:feature_code":"PPL",
    "gn:name":"Froly",
    "gn:population":0,
    "gn:timezone":"Europe/Kirov",
    "iso:country":"RU",
    "name:rus_x_preferred":[
        "\u0424\u0440\u043e\u043b\u044b"
    ],
    "name:und_x_variant":[
        "\u0424\u0440\u043e\u043b\u044b"
    ],
    "wof:name":"Froly",
    "wof:placetype":"locality"
},
  "geometry": {"coordinates":[49.32406,58.97376],"type":"Point"}
}