{
  "type": "Feature",
  "properties": {
    "gn:admin1_code":"16.0",
    "gn:asciiname":"Bardino",
    "gn:country_code":"RU",
    "gn:dem":103,
    "gn:feature_class":"P",
    "gn:feature_code":"PPL",
    "gn:name":"Bardino",
    "gn:population":0,
    "gn:timezone":"Europe/Moscow",
    "iso:country":"RU",
    "name:nor_x_preferred":[
        "Bardino"
    ],
    "name:rus_x_preferred":[
        "\u0411\u0430\u0440\u0434\u0438\u043d\u043e"
    ],
    "wof:name":"Bardino",
    "wof:placetype":"locality"
},
  "geometry": {"coordinates":[46.28333,55.23333],"type":"Point"}
}