{
  "type": "Feature",
  "properties": {
    "gn:admin1_code":"38",
    "gn:asciiname":"Konsulov",
    "gn:country_code":"RU",
    "gn:dem":36,
    "gn:feature_class":"P",
    "gn:feature_code":"PPL",
    "gn:name":"Konsulov",
    "gn:population":0,
    "gn:timezone":"Europe/Moscow",
    "iso:country":"RU",
    "name:rus_x_preferred":[
        "\u041a\u043e\u043d\u0441\u0443\u043b\u043e\u0432"
    ],
    "name:und_x_variant":[
        "\u041a\u043e\u043d\u0441\u0443\u043b\u043e\u0432"
    ],
    "wof:name":"Konsulov",
    "wof:placetype":"locality"
},
  "geometry": {"coordinates":[38.81139,44.79167],"type":"Point"}
}