{
  "type": "Feature",
  "properties": {
    "gn:country":"RU",
    "gn:fcode":"PPL",
    "gn:population":0,
    "iso:country":"RU",
    "name:eng_x_preferred":[
        "Lun\u00ebvo"
    ],
    "name:nor_x_preferred":[
        "Lunevo"
    ],
    "name:rus_x_preferred":[
        "\u041b\u0443\u043d\u0435\u0432\u043e"
    ],
    "name:rus_x_variant":[
        "\u041b\u0443\u043d\u0451\u0432\u043e"
    ],
    "name:und_x_variant":[
        "Luneva"
    ],
    "qs:name":"Lun\u00ebvo",
    "qs:name_adm0":"Russia",
    "qs:name_adm1":"Kostroma Oblast",
    "qs:photos_9r":0,
    "qs:photos_sr":0,
    "qs:placetype":"Town",
    "qs:pop_sr":"0",
    "wof:name":"Lun\u00ebvo",
    "wof:placetype":"locality",
    "wof:population":0
},
  "geometry": {"coordinates":[41.09446,57.54767],"type":"Point"}
}