{
  "type": "Feature",
  "properties": {
    "gn:admin1_code":"62",
    "gn:asciiname":"Poselok Imeni Lenina",
    "gn:country_code":"RU",
    "gn:dem":103,
    "gn:feature_class":"P",
    "gn:feature_code":"PPL",
    "gn:name":"Pos\u00eblok Imeni Lenina",
    "gn:population":0,
    "gn:timezone":"Europe/Moscow",
    "iso:country":"RU",
    "name:rus_x_preferred":[
        "\u041f\u043e\u0441\u0451\u043b\u043e\u043a \u0418\u043c\u0435\u043d\u0438 \u041b\u0435\u043d\u0438\u043d\u0430"
    ],
    "name:und_x_variant":[
        "Pos\u00eblok Imeni Lenina"
    ],
    "wof:name":"Poselok Imeni Lenina",
    "wof:placetype":"locality"
},
  "geometry": {"coordinates":[40.88536,54.84454],"type":"Point"}
}