{
  "type": "Feature",
  "properties": {
    "gn:country":"RU",
    "gn:fcode":"PPL",
    "gn:population":3722,
    "iso:country":"RU",
    "name:eng_x_preferred":[
        "Ovsyanka"
    ],
    "name:nor_x_preferred":[
        "Ovsianka"
    ],
    "name:rus_x_preferred":[
        "\u041e\u0432\u0441\u044f\u043d\u043a\u0430"
    ],
    "qs:name":"Ovsyanka",
    "qs:name_adm0":"Russia",
    "qs:name_adm1":"Krasnoyarsk Krai",
    "qs:photos_9k":1,
    "qs:photos_9r":1,
    "qs:photos_all":10,
    "qs:photos_sr":0,
    "qs:placetype":"Town",
    "qs:pop_sr":"4",
    "wof:name":"Ovsyanka",
    "wof:placetype":"locality",
    "wof:population":3722
},
  "geometry": {"coordinates":[92.572,55.9583],"type":"Point"}
}