{
  "type": "Feature",
  "properties": {
    "gn:admin1_code":"55",
    "gn:asciiname":"Verkhnepavlushkino",
    "gn:country_code":"RU",
    "gn:dem":160,
    "gn:feature_class":"P",
    "gn:feature_code":"PPL",
    "gn:name":"Verkhnepavlushkino",
    "gn:population":0,
    "gn:timezone":"Asia/Yekaterinburg",
    "iso:country":"RU",
    "name:eng_x_preferred":[
        "Verkhnepavlushkino"
    ],
    "name:nor_x_preferred":[
        "Verkhnepavlusjkino"
    ],
    "name:rus_x_preferred":[
        "\u0412\u0435\u0440\u0445\u043d\u0435\u043f\u0430\u0432\u043b\u0443\u0448\u043a\u0438\u043d\u043e"
    ],
    "name:und_x_variant":[
        "Verkhneye Pavlushkino"
    ],
    "wof:name":"Verkhnepavlushkino",
    "wof:placetype":"locality"
},
  "geometry": {"coordinates":[53.03333000000001,53.91667],"type":"Point"}
}