{
  "type": "Feature",
  "properties": {
    "gn:admin1_code":"60",
    "gn:asciiname":"Klyukino",
    "gn:country_code":"RU",
    "gn:dem":94,
    "gn:feature_class":"P",
    "gn:feature_code":"PPL",
    "gn:name":"Klyukino",
    "gn:population":0,
    "gn:timezone":"Europe/Moscow",
    "iso:country":"RU",
    "name:rus_x_preferred":[
        "\u041a\u043b\u044e\u043a\u0438\u043d\u043e"
    ],
    "wof:name":"Klyukino",
    "wof:placetype":"locality"
},
  "geometry": {"coordinates":[28.70254000000001,56.86012],"type":"Point"}
}