{
  "type": "Feature",
  "properties": {
    "gn:admin1_code":"33.0",
    "gn:asciiname":"Zhirikhanovy",
    "gn:country_code":"RU",
    "gn:dem":152,
    "gn:feature_class":"P",
    "gn:feature_code":"PPL",
    "gn:name":"Zhirikhanovy",
    "gn:population":0,
    "gn:timezone":"Europe/Kirov",
    "iso:country":"RU",
    "name:rus_x_preferred":[
        "\u0416\u0438\u0440\u0438\u0445\u0430\u043d\u043e\u0432\u044b"
    ],
    "wof:name":"Zhirikhanovy",
    "wof:placetype":"locality"
},
  "geometry": {"coordinates":[48.8165,58.93632],"type":"Point"}
}