{
  "type": "Feature",
  "properties": {
    "gn:admin1_code":"38.0",
    "gn:asciiname":"Bol'shelugskiy",
    "gn:country_code":"RU",
    "gn:dem":24,
    "gn:feature_class":"P",
    "gn:feature_code":"PPL",
    "gn:name":"Bol\u2019shelugskiy",
    "gn:population":0,
    "gn:timezone":"Europe/Moscow",
    "iso:country":"RU",
    "name:rus_x_preferred":[
        "\u0411\u043e\u043b\u044c\u0448\u0435\u043b\u0443\u0433\u0441\u043a\u0438\u0439"
    ],
    "name:und_x_variant":[
        "Bol\u2019shelugskiy"
    ],
    "wof:name":"Bol'shelugskiy",
    "wof:placetype":"locality"
},
  "geometry": {"coordinates":[38.24607,46.61686],"type":"Point"}
}