{
  "type": "Feature",
  "properties": {
    "gn:admin1_code":"53.0",
    "gn:asciiname":"Shadrikha",
    "gn:country_code":"RU",
    "gn:dem":133,
    "gn:feature_class":"P",
    "gn:feature_code":"PPL",
    "gn:name":"Shadrikha",
    "gn:population":0,
    "gn:timezone":"Asia/Novosibirsk",
    "iso:country":"RU",
    "name:rus_x_preferred":[
        "\u0428\u0430\u0434\u0440\u0438\u0445\u0430"
    ],
    "wof:name":"Shadrikha",
    "wof:placetype":"locality"
},
  "geometry": {"coordinates":[83.1985,54.812],"type":"Point"}
}