{
  "type": "Feature",
  "properties": {
    "gn:admin1_code":"60",
    "gn:asciiname":"Krapivno",
    "gn:country_code":"RU",
    "gn:dem":70,
    "gn:feature_class":"P",
    "gn:feature_code":"PPL",
    "gn:name":"Krapivno",
    "gn:population":0,
    "gn:timezone":"Europe/Moscow",
    "iso:country":"RU",
    "name:rus_x_preferred":[
        "\u041a\u0440\u0430\u043f\u0438\u0432\u043d\u043e"
    ],
    "wof:name":"Krapivno",
    "wof:placetype":"locality"
},
  "geometry": {"coordinates":[28.1336,58.807],"type":"Point"}
}