{
  "type": "Feature",
  "properties": {
    "gn:admin1_code":"84.0",
    "gn:asciiname":"Chizhi",
    "gn:country_code":"RU",
    "gn:dem":184,
    "gn:feature_class":"P",
    "gn:feature_code":"PPL",
    "gn:name":"Chizhi",
    "gn:population":0,
    "gn:timezone":"Europe/Volgograd",
    "iso:country":"RU",
    "name:rus_x_preferred":[
        "\u0427\u0438\u0436\u0438"
    ],
    "name:und_x_variant":[
        "Chizhnovka",
        "Chizhi"
    ],
    "wof:name":"Chizhi",
    "wof:placetype":"locality"
},
  "geometry": {"coordinates":[45.01042,50.63098],"type":"Point"}
}