{
  "type": "Feature",
  "properties": {
    "gn:admin1_code":"51",
    "gn:asciiname":"Bogatyrikha",
    "gn:country_code":"RU",
    "gn:dem":137,
    "gn:feature_class":"P",
    "gn:feature_code":"PPL",
    "gn:name":"Bogatyrikha",
    "gn:population":0,
    "gn:timezone":"Europe/Moscow",
    "iso:country":"RU",
    "name:rus_x_preferred":[
        "\u0411\u043e\u0433\u0430\u0442\u044b\u0440\u0438\u0445\u0430"
    ],
    "wof:name":"Bogatyrikha",
    "wof:placetype":"locality"
},
  "geometry": {"coordinates":[45.124,57.1339],"type":"Point"}
}