{
  "type": "Feature",
  "properties": {
    "gn:admin1_code":"84",
    "gn:asciiname":"Rozovskiy",
    "gn:country_code":"RU",
    "gn:dem":211,
    "gn:feature_class":"P",
    "gn:feature_code":"PPL",
    "gn:name":"Rozovskiy",
    "gn:population":0,
    "gn:timezone":"Europe/Volgograd",
    "iso:country":"RU",
    "name:rus_x_preferred":[
        "\u0420\u043e\u0437\u043e\u0432\u0441\u043a\u0438\u0439"
    ],
    "wof:name":"Rozovskiy",
    "wof:placetype":"locality"
},
  "geometry": {"coordinates":[41.471,50.7636],"type":"Point"}
}