{
  "type": "Feature",
  "properties": {
    "gn:admin1_code":"72.0",
    "gn:asciiname":"Duplyatovo-Maslovo",
    "gn:country_code":"RU",
    "gn:dem":159,
    "gn:feature_class":"P",
    "gn:feature_code":"PPL",
    "gn:name":"Duplyatovo-Maslovo",
    "gn:population":0,
    "gn:timezone":"Europe/Moscow",
    "iso:country":"RU",
    "name:eng_x_preferred":[
        "Duplyatovo-Maslovo"
    ],
    "name:nor_x_preferred":[
        "Dupljatovo-Maslovo"
    ],
    "name:rus_x_preferred":[
        "\u0414\u0443\u043f\u043b\u044f\u0442\u043e\u0432\u043e-\u041c\u0430\u0441\u043b\u043e\u0432\u043e"
    ],
    "name:und_x_variant":[
        "Duplyato-Maslovo",
        "Duplyato-Maslovka",
        "Duplyatovo-Maslovo"
    ],
    "wof:name":"Duplyatovo-Maslovo",
    "wof:placetype":"locality"
},
  "geometry": {"coordinates":[41.21985,52.37319],"type":"Point"}
}