{
  "type": "Feature",
  "properties": {
    "gn:admin1_code":"21",
    "gn:asciiname":"Kruttsy",
    "gn:country_code":"RU",
    "gn:dem":126,
    "gn:feature_class":"P",
    "gn:feature_code":"PPL",
    "gn:name":"Kruttsy",
    "gn:population":0,
    "gn:timezone":"Europe/Moscow",
    "iso:country":"RU",
    "name:rus_x_preferred":[
        "\u041a\u0440\u0443\u0442\u0446\u044b"
    ],
    "name:und_x_variant":[
        "\u041a\u0440\u0443\u0442\u0446\u044b"
    ],
    "wof:name":"Kruttsy",
    "wof:placetype":"locality"
},
  "geometry": {"coordinates":[41.66475,57.1765],"type":"Point"}
}