{
  "type": "Feature",
  "properties": {
    "gn:admin1_code":"33",
    "gn:asciiname":"Isakovtsy",
    "gn:country_code":"RU",
    "gn:dem":224,
    "gn:feature_class":"P",
    "gn:feature_code":"PPL",
    "gn:name":"Isakovtsy",
    "gn:population":0,
    "gn:timezone":"Europe/Kirov",
    "iso:country":"RU",
    "name:rus_x_preferred":[
        "\u0418\u0441\u0430\u043a\u043e\u0432\u0446\u044b"
    ],
    "wof:name":"Isakovtsy",
    "wof:placetype":"locality"
},
  "geometry": {"coordinates":[51.34234,59.51342],"type":"Point"}
}