{
  "type": "Feature",
  "properties": {
    "gn:admin1_code":"73",
    "gn:asciiname":"Staryye Yumraly",
    "gn:country_code":"RU",
    "gn:dem":90,
    "gn:feature_class":"P",
    "gn:feature_code":"PPL",
    "gn:name":"Staryye Yumraly",
    "gn:population":0,
    "gn:timezone":"Europe/Moscow",
    "iso:country":"RU",
    "name:eng_x_preferred":[
        "Staryye Yumraly"
    ],
    "name:nor_x_preferred":[
        "Staryj Jumraly"
    ],
    "name:rus_x_preferred":[
        "\u0421\u0442\u0430\u0440\u044b\u0439 \u042e\u043c\u0440\u0430\u043b\u044b"
    ],
    "name:rus_x_variant":[
        "\u0421\u0442\u0430\u0440\u044b\u0435 \u042e\u043c\u0440\u0430\u043b\u044b"
    ],
    "name:und_x_variant":[
        "Staryye Yurmaly"
    ],
    "wof:name":"Staryye Yumraly",
    "wof:placetype":"locality"
},
  "geometry": {"coordinates":[48.59538,55.13348000000001],"type":"Point"}
}