{
  "type": "Feature",
  "properties": {
    "gn:admin1_code":"88.0",
    "gn:asciiname":"Luchinskoye",
    "gn:country_code":"RU",
    "gn:dem":120,
    "gn:feature_class":"P",
    "gn:feature_code":"PPL",
    "gn:name":"Luchinskoye",
    "gn:population":0,
    "gn:timezone":"Europe/Moscow",
    "iso:country":"RU",
    "name:rus_x_preferred":[
        "\u041b\u0443\u0447\u0438\u043d\u0441\u043a\u043e\u0435"
    ],
    "name:und_x_variant":[
        "\u041b\u0443\u0447\u0438\u043d\u0441\u043a\u043e\u0435"
    ],
    "wof:name":"Luchinskoye",
    "wof:placetype":"locality"
},
  "geometry": {"coordinates":[40.35592000000001,58.33317],"type":"Point"}
}