{
  "type": "Feature",
  "properties": {
    "gn:admin1_code":"21",
    "gn:asciiname":"Pischugovo",
    "gn:country_code":"RU",
    "gn:dem":147,
    "gn:feature_class":"P",
    "gn:feature_code":"PPL",
    "gn:name":"Pischugovo",
    "gn:population":0,
    "gn:timezone":"Europe/Moscow",
    "iso:country":"RU",
    "name:und_x_variant":[
        "Pichugovo",
        "Pischugovo"
    ],
    "wof:name":"Pischugovo",
    "wof:placetype":"locality"
},
  "geometry": {"coordinates":[40.47948,57.05823],"type":"Point"}
}