{
  "type": "Feature",
  "properties": {
    "gn:admin1_code":"80",
    "gn:asciiname":"Lyamshur-Vishur",
    "gn:country_code":"RU",
    "gn:dem":130,
    "gn:feature_class":"P",
    "gn:feature_code":"PPL",
    "gn:name":"Lyamshur-Vishur",
    "gn:population":0,
    "gn:timezone":"Europe/Samara",
    "iso:country":"RU",
    "name:rus_x_preferred":[
        "\u041b\u044f\u043c\u0448\u0443\u0440-\u0412\u0438\u0448\u0443\u0440"
    ],
    "name:und_x_variant":[
        "Pashur-Vishur",
        "Lyamshur-Vishur",
        "\u041b\u044f\u043c\u0448\u0443\u0440-\u0412\u0438\u0448\u0443\u0440"
    ],
    "wof:name":"Lyamshur-Vishur",
    "wof:placetype":"locality"
},
  "geometry": {"coordinates":[53.67371,57.22279],"type":"Point"}
}