{
  "type": "Feature",
  "properties": {
    "gn:admin1_code":"60",
    "gn:asciiname":"Runtsevo",
    "gn:country_code":"RU",
    "gn:dem":61,
    "gn:feature_class":"P",
    "gn:feature_code":"PPL",
    "gn:name":"Runtsevo",
    "gn:population":0,
    "gn:timezone":"Europe/Moscow",
    "iso:country":"RU",
    "name:rus_x_preferred":[
        "\u0420\u0443\u043d\u0446\u0435\u0432\u043e"
    ],
    "name:rus_x_variant":[
        "\u0420\u0443\u0431\u0446\u043e\u0432\u043e"
    ],
    "name:und_x_variant":[
        "Rubtsovo"
    ],
    "wof:name":"Runtsevo",
    "wof:placetype":"locality"
},
  "geometry": {"coordinates":[28.03628,57.57463000000001],"type":"Point"}
}