{
  "type": "Feature",
  "properties": {
    "gn:admin1_code":"71",
    "gn:asciiname":"Suvory",
    "gn:country_code":"RU",
    "gn:dem":138,
    "gn:feature_class":"P",
    "gn:feature_code":"PPL",
    "gn:name":"Suvory",
    "gn:population":0,
    "gn:timezone":"Asia/Yekaterinburg",
    "iso:country":"RU",
    "name:eng_x_preferred":[
        "Suvory"
    ],
    "name:nor_x_preferred":[
        "Suvory"
    ],
    "name:rus_x_preferred":[
        "\u0421\u0443\u0432\u043e\u0440\u044b"
    ],
    "name:und_x_variant":[
        "Suvorog",
        "Suvory"
    ],
    "wof:name":"Suvory",
    "wof:placetype":"locality"
},
  "geometry": {"coordinates":[62.3318,56.5413],"type":"Point"}
}