{
  "type": "Feature",
  "properties": {
    "gn:admin1_code":"88",
    "gn:asciiname":"Yukovo",
    "gn:country_code":"RU",
    "gn:dem":118,
    "gn:feature_class":"P",
    "gn:feature_code":"PPL",
    "gn:name":"Yukovo",
    "gn:population":0,
    "gn:timezone":"Europe/Moscow",
    "iso:country":"RU",
    "name:rus_x_preferred":[
        "\u042e\u043a\u043e\u0432\u043e"
    ],
    "wof:name":"Yukovo",
    "wof:placetype":"locality"
},
  "geometry": {"coordinates":[39.65128,57.51756999999999],"type":"Point"}
}