{
  "type": "Feature",
  "properties": {
    "gn:admin1_code":"4",
    "gn:asciiname":"Chernokorovnikovo",
    "gn:country_code":"RU",
    "gn:dem":200,
    "gn:feature_class":"P",
    "gn:feature_code":"PPL",
    "gn:name":"Chernokorovnikovo",
    "gn:population":0,
    "gn:timezone":"Asia/Barnaul",
    "iso:country":"RU",
    "name:eng_x_preferred":[
        "Chernokorovnikovo"
    ],
    "name:nor_x_preferred":[
        "Tsjernokorovnikovo"
    ],
    "name:rus_x_preferred":[
        "\u0427\u0435\u0440\u043d\u043e\u043a\u043e\u0440\u043e\u0432\u043d\u0438\u043a\u043e\u0432\u043e"
    ],
    "name:und_x_variant":[
        "Cherno-Korovnikovskiy"
    ],
    "wof:name":"Chernokorovnikovo",
    "wof:placetype":"locality"
},
  "geometry": {"coordinates":[80.46980000000001,51.6172],"type":"Point"}
}