{
  "type": "Feature",
  "properties": {
    "gn:admin1_code":"77",
    "gn:asciiname":"Zavrazh'ye",
    "gn:country_code":"RU",
    "gn:dem":180,
    "gn:feature_class":"P",
    "gn:feature_code":"PPL",
    "gn:name":"Zavrazh\u2019ye",
    "gn:population":0,
    "gn:timezone":"Europe/Moscow",
    "iso:country":"RU",
    "name:rus_x_preferred":[
        "\u0417\u0430\u0432\u0440\u0430\u0436\u044c\u0435"
    ],
    "name:und_x_variant":[
        "Zavrazh\u2019ye",
        "\u0417\u0430\u0432\u0440\u0430\u0436\u044c\u0435"
    ],
    "wof:name":"Zavrazh'ye",
    "wof:placetype":"locality"
},
  "geometry": {"coordinates":[36.5867,58.3582],"type":"Point"}
}