{
  "type": "Feature",
  "properties": {
    "gn:admin1_code":"83",
    "gn:asciiname":"Pesochnoye",
    "gn:country_code":"RU",
    "gn:dem":114,
    "gn:feature_class":"P",
    "gn:feature_code":"PPL",
    "gn:name":"Pesochnoye",
    "gn:population":0,
    "gn:timezone":"Europe/Moscow",
    "iso:country":"RU",
    "name:rus_x_preferred":[
        "\u041f\u0435\u0441\u043e\u0447\u043d\u043e\u0435"
    ],
    "name:und_x_variant":[
        "Pesochnovo",
        "Pesochnoye"
    ],
    "wof:name":"Pesochnoye",
    "wof:placetype":"locality"
},
  "geometry": {"coordinates":[40.66296,56.39094],"type":"Point"}
}