{
  "type": "Feature",
  "properties": {
    "gn:admin1_code":"63",
    "gn:asciiname":"Kachikattsy",
    "gn:country_code":"RU",
    "gn:dem":111,
    "gn:feature_class":"P",
    "gn:feature_code":"PPL",
    "gn:name":"Kachikattsy",
    "gn:population":0,
    "gn:timezone":"Asia/Yakutsk",
    "iso:country":"RU",
    "name:eng_x_preferred":[
        "Kachikattsy"
    ],
    "name:nor_x_preferred":[
        "Katsjikattsy"
    ],
    "name:rus_x_preferred":[
        "\u041a\u0430\u0447\u0438\u043a\u0430\u0442\u0446\u044b"
    ],
    "name:und_x_variant":[
        "Sysy-Basa",
        "Kochekattsy",
        "\u041a\u0430\u0447\u0438\u043a\u0430\u0442\u0446\u044b",
        "Kachikattsy"
    ],
    "wof:name":"Kachikattsy",
    "wof:placetype":"locality"
},
  "geometry": {"coordinates":[128.94493,61.32079],"type":"Point"}
}