{
  "type": "Feature",
  "properties": {
    "gn:admin1_code":"70.0",
    "gn:asciiname":"Urochische Krasnyy Chongarets",
    "gn:country_code":"RU",
    "gn:dem":270,
    "gn:feature_class":"P",
    "gn:feature_code":"PPL",
    "gn:name":"Urochische Krasnyy Chongarets",
    "gn:population":0,
    "gn:timezone":"Europe/Moscow",
    "iso:country":"RU",
    "name:eng_x_preferred":[
        "Krasnyy Chongarets"
    ],
    "name:nor_x_preferred":[
        "Krasnyj Tsjongarets"
    ],
    "name:rus_x_preferred":[
        "\u0423\u0440\u043e\u0447\u0438\u0433\u0449\u0435 \u041a\u0440\u0430\u0441\u043d\u044b\u0439 \u0427\u043e\u043d\u0433\u0430\u0440\u0435\u0446"
    ],
    "name:und_x_variant":[
        "Chongarets",
        "Urochische Krasnyy Chongarets"
    ],
    "wof:name":"Urochische Krasnyy Chongarets",
    "wof:placetype":"locality"
},
  "geometry": {"coordinates":[43.10333,44.5025],"type":"Point"}
}