{
  "type": "Feature",
  "properties": {
    "gn:admin1_code":"54",
    "gn:asciiname":"Yachenka",
    "gn:country_code":"RU",
    "gn:dem":96,
    "gn:feature_class":"P",
    "gn:feature_code":"PPL",
    "gn:name":"Yachenka",
    "gn:population":0,
    "gn:timezone":"Asia/Omsk",
    "iso:country":"RU",
    "wof:name":"Yachenka",
    "wof:placetype":"locality"
},
  "geometry": {"coordinates":[73.76666999999998,56.56667],"type":"Point"}
}