{
  "type": "Feature",
  "properties": {
    "gn:country":"RU",
    "gn:fcode":"PPL",
    "gn:population":0,
    "iso:country":"RU",
    "name:nor_x_preferred":[
        "Akberdina"
    ],
    "name:rus_x_preferred":[
        "\u0410\u043a\u0431\u0435\u0440\u0434\u0438\u043d\u043e"
    ],
    "name:und_x_variant":[
        "Akberdino"
    ],
    "qs:name":"Akberdina",
    "qs:name_adm0":"Russia",
    "qs:name_adm1":"Bashkortostan Republic",
    "qs:photos_9r":0,
    "qs:photos_sr":0,
    "qs:placetype":"Town",
    "qs:pop_sr":"0",
    "wof:name":"Akberdina",
    "wof:placetype":"locality",
    "wof:population":0
},
  "geometry": {"coordinates":[56.1841,54.5931],"type":"Point"}
}