{
  "type": "Feature",
  "properties": {
    "gn:admin1_code":"69",
    "gn:asciiname":"Gorenka",
    "gn:country_code":"RU",
    "gn:dem":232,
    "gn:feature_class":"P",
    "gn:feature_code":"PPL",
    "gn:name":"Gorenka",
    "gn:population":0,
    "gn:timezone":"Europe/Moscow",
    "iso:country":"RU",
    "name:rus_x_preferred":[
        "\u0413\u043e\u0440\u0435\u043d\u043aa"
    ],
    "name:und_x_variant":[
        "Gorenki",
        "Gorenka"
    ],
    "wof:name":"Gorenka",
    "wof:placetype":"locality"
},
  "geometry": {"coordinates":[32.46259000000001,55.28276],"type":"Point"}
}