{
  "type": "Feature",
  "properties": {
    "gn:admin1_code":"46",
    "gn:asciiname":"Smol'nyy",
    "gn:country_code":"RU",
    "gn:dem":102,
    "gn:feature_class":"P",
    "gn:feature_code":"PPL",
    "gn:name":"Smol\u2019nyy",
    "gn:population":0,
    "gn:timezone":"Europe/Moscow",
    "iso:country":"RU",
    "name:rus_x_preferred":[
        "\u0421\u043c\u043e\u043b\u044c\u043d\u044b\u0439"
    ],
    "name:und_x_variant":[
        "Lespromkhoz",
        "Smol\u2019nyy",
        "\u0421\u043c\u043e\u043b\u044c\u043d\u044b\u0439"
    ],
    "wof:name":"Smol'nyy",
    "wof:placetype":"locality"
},
  "geometry": {"coordinates":[45.30508,54.72335],"type":"Point"}
}