{
  "type": "Feature",
  "properties": {
    "gn:admin1_code":"60",
    "gn:asciiname":"Rubtsy",
    "gn:country_code":"RU",
    "gn:dem":97,
    "gn:feature_class":"P",
    "gn:feature_code":"PPL",
    "gn:name":"Rubtsy",
    "gn:population":0,
    "gn:timezone":"Europe/Moscow",
    "iso:country":"RU",
    "name:rus_x_preferred":[
        "\u0420\u0443\u0431\u0446\u044b"
    ],
    "wof:name":"Rubtsy",
    "wof:placetype":"locality"
},
  "geometry": {"coordinates":[28.73124,57.03165],"type":"Point"}
}