{
  "type": "Feature",
  "properties": {
    "gn:admin1_code":"47.0",
    "gn:asciiname":"Pyatovskoye",
    "gn:country_code":"RU",
    "gn:dem":188,
    "gn:feature_class":"P",
    "gn:feature_code":"PPL",
    "gn:name":"Pyatovskoye",
    "gn:population":0,
    "gn:timezone":"Europe/Moscow",
    "iso:country":"RU",
    "name:rus_x_preferred":[
        "\u041f\u044f\u0442\u043e\u0432\u0441\u043a\u043e\u0435"
    ],
    "name:und_x_variant":[
        "\u041f\u044f\u0442\u043e\u0432\u0441\u043a\u043e\u0435"
    ],
    "wof:name":"Pyatovskoye",
    "wof:placetype":"locality"
},
  "geometry": {"coordinates":[37.18,55.52],"type":"Point"}
}