{
  "type": "Feature",
  "properties": {
    "gn:admin1_code":"21",
    "gn:asciiname":"Kurochkino",
    "gn:country_code":"RU",
    "gn:dem":128,
    "gn:feature_class":"P",
    "gn:feature_code":"PPL",
    "gn:name":"Kurochkino",
    "gn:population":0,
    "gn:timezone":"Europe/Moscow",
    "iso:country":"RU",
    "name:rus_x_preferred":[
        "\u041a\u0443\u0440\u043e\u0447\u043a\u0438\u043d\u043e"
    ],
    "name:und_x_variant":[
        "Kurochkina",
        "Kurochkino"
    ],
    "wof:name":"Kurochkino",
    "wof:placetype":"locality"
},
  "geometry": {"coordinates":[41.50502,57.30278000000001],"type":"Point"}
}