{
  "type": "Feature",
  "properties": {
    "gn:country":"RU",
    "gn:fcode":"PPL",
    "gn:pop":1701,
    "iso:country":"RU",
    "name:eng_x_preferred":[
        "Severka"
    ],
    "name:nor_x_preferred":[
        "Severka"
    ],
    "name:rus_x_preferred":[
        "\u0421\u0435\u0432\u0435\u0440\u043a\u0430"
    ],
    "name:unk_x_variant":[
        "Severnaya"
    ],
    "qs:name":"Severka",
    "qs:photos_9r":0,
    "qs:photos_sr":0,
    "qs:pop_sr":"3",
    "wof:name":"Severka",
    "wof:placetype":"locality",
    "wof:population":1701
},
  "geometry": {"coordinates":[79.28333000000001,52.13333],"type":"Point"}
}