{
  "type": "Feature",
  "properties": {
    "gn:admin1_code":"34",
    "gn:asciiname":"Ipatovo",
    "gn:country_code":"RU",
    "gn:dem":92,
    "gn:feature_class":"P",
    "gn:feature_code":"PPL",
    "gn:name":"Ipatovo",
    "gn:population":50,
    "gn:timezone":"Europe/Moscow",
    "iso:country":"RU",
    "name:eng_x_preferred":[
        "Ipatovo"
    ],
    "name:nor_x_preferred":[
        "Ipatovo"
    ],
    "name:rus_x_preferred":[
        "\u0418\u043f\u0430\u0442\u043e\u0432\u043e"
    ],
    "name:und_x_variant":[
        "Ipatovka",
        "\u0418\u043f\u0430\u0442\u043e\u0432\u043e",
        "Ipatovo"
    ],
    "wof:name":"Ipatovo",
    "wof:placetype":"locality",
    "wof:population":50
},
  "geometry": {"coordinates":[50.05165,61.85755],"type":"Point"}
}