{
  "type": "Feature",
  "properties": {
    "gn:admin1_code":"91",
    "gn:asciiname":"Aydara",
    "gn:country_code":"RU",
    "gn:dem":108,
    "gn:feature_class":"P",
    "gn:feature_code":"PPL",
    "gn:name":"Aydara",
    "gn:population":0,
    "gn:timezone":"Asia/Krasnoyarsk",
    "iso:country":"RU",
    "name:eng_x_preferred":[
        "Aydara"
    ],
    "name:nor_x_preferred":[
        "Ajdara"
    ],
    "name:rus_x_preferred":[
        "\u0410\u0439\u0434\u0430\u0440\u0430"
    ],
    "wof:name":"Aydara",
    "wof:placetype":"locality"
},
  "geometry": {"coordinates":[88.39139,58.52389],"type":"Point"}
}