{
  "type": "Feature",
  "properties": {
    "gn:admin1_code":"6",
    "gn:asciiname":"Voymozero",
    "gn:country_code":"RU",
    "gn:dem":13,
    "gn:feature_class":"P",
    "gn:feature_code":"PPL",
    "gn:name":"Voymozero",
    "gn:population":0,
    "gn:timezone":"Europe/Moscow",
    "iso:country":"RU",
    "name:eng_x_preferred":[
        "Voymozero"
    ],
    "name:nor_x_preferred":[
        "Vojmozero"
    ],
    "name:rus_x_preferred":[
        "\u0412\u043e\u0439\u043c\u043e\u0437\u0435\u0440\u043e"
    ],
    "wof:name":"Voymozero",
    "wof:placetype":"locality"
},
  "geometry": {"coordinates":[38.9511,63.49432],"type":"Point"}
}