{
  "type": "Feature",
  "properties": {
    "gn:admin1_code":"16",
    "gn:asciiname":"Urezekasy",
    "gn:country_code":"RU",
    "gn:dem":164,
    "gn:feature_class":"P",
    "gn:feature_code":"PPL",
    "gn:name":"Urezekasy",
    "gn:population":0,
    "gn:timezone":"Europe/Moscow",
    "iso:country":"RU",
    "name:rus_x_preferred":[
        "\u0423\u0440\u0435\u0437\u0435\u043a\u0430\u0441\u044b"
    ],
    "name:und_x_variant":[
        "Urezo-Kasy",
        "Urezekasy"
    ],
    "wof:name":"Urezekasy",
    "wof:placetype":"locality"
},
  "geometry": {"coordinates":[47.65225,55.91868],"type":"Point"}
}