{
  "type": "Feature",
  "properties": {
    "gn:admin1_code":"90",
    "gn:asciiname":"Malaya Usa",
    "gn:country_code":"RU",
    "gn:dem":161,
    "gn:feature_class":"P",
    "gn:feature_code":"PPL",
    "gn:name":"Malaya Usa",
    "gn:population":0,
    "gn:timezone":"Asia/Yekaterinburg",
    "iso:country":"RU",
    "name:eng_x_preferred":[
        "Malaya Usa"
    ],
    "name:nor_x_preferred":[
        "Mal.Usa"
    ],
    "name:rus_x_preferred":[
        "\u041c\u0430\u043b.\u0423\u0441\u0430"
    ],
    "name:rus_x_variant":[
        "\u041c\u0430\u043b\u0430\u044f \u0423\u0441\u0430"
    ],
    "name:und_x_variant":[
        "\u041c\u0430\u043b\u0430\u044f \u0423\u0441\u0430"
    ],
    "wof:name":"Malaya Usa",
    "wof:placetype":"locality"
},
  "geometry": {"coordinates":[54.90512,56.80062],"type":"Point"}
}