{
  "type": "Feature",
  "properties": {
    "gn:admin1_code":"10",
    "gn:asciiname":"Zarnitsa",
    "gn:country_code":"RU",
    "gn:dem":185,
    "gn:feature_class":"P",
    "gn:feature_code":"PPL",
    "gn:name":"Zarnitsa",
    "gn:population":0,
    "gn:timezone":"Europe/Moscow",
    "iso:country":"RU",
    "name:bel_x_preferred":[
        "\u0417\u0430\u0440\u043d\u0456\u0446\u0430"
    ],
    "name:rus_x_preferred":[
        "\u0417\u0430\u0440\u043d\u0438\u0446\u0430"
    ],
    "name:ukr_x_preferred":[
        "\u0417\u0430\u0440\u043d\u0438\u0446\u044f"
    ],
    "wof:name":"Zarnitsa",
    "wof:placetype":"locality"
},
  "geometry": {"coordinates":[34.28028,52.51639],"type":"Point"}
}