{
  "type": "Feature",
  "properties": {
    "gn:admin1_code":"69",
    "gn:asciiname":"Mazovskaya",
    "gn:cc2":"RU",
    "gn:country_code":"RU",
    "gn:dem":217,
    "gn:feature_class":"P",
    "gn:feature_code":"PPL",
    "gn:name":"Mazovskaya",
    "gn:population":0,
    "gn:timezone":"Europe/Moscow",
    "iso:country":"RU",
    "name:rus_x_preferred":[
        "\u041c\u0430\u0437\u043e\u0432\u0441\u043a\u0430\u044f"
    ],
    "name:und_x_variant":[
        "Mazorskaya",
        "Mazovskaya",
        "\u041c\u0430\u0437\u043e\u0432\u0441\u043a\u0430\u044f"
    ],
    "wof:name":"Mazovskaya",
    "wof:placetype":"locality"
},
  "geometry": {"coordinates":[33.35,54.98333],"type":"Point"}
}