{
  "type": "Feature",
  "properties": {
    "gn:admin1_code":"84.0",
    "gn:asciiname":"Belogurov",
    "gn:country_code":"RU",
    "gn:dem":27,
    "gn:feature_class":"P",
    "gn:feature_code":"PPL",
    "gn:name":"Belogurov",
    "gn:population":0,
    "gn:timezone":"Europe/Volgograd",
    "iso:country":"RU",
    "name:nor_x_preferred":[
        "Belogurov"
    ],
    "name:rus_x_preferred":[
        "\u0411\u0435\u043b\u043e\u0433\u0443\u0440\u043e\u0432"
    ],
    "wof:name":"Belogurov",
    "wof:placetype":"locality"
},
  "geometry": {"coordinates":[46.35,49.76667],"type":"Point"}
}