{
  "type": "Feature",
  "properties": {
    "gn:admin1_code":"57",
    "gn:asciiname":"Mazyrinka",
    "gn:country_code":"RU",
    "gn:dem":220,
    "gn:feature_class":"P",
    "gn:feature_code":"PPL",
    "gn:name":"Mazyrinka",
    "gn:population":0,
    "gn:timezone":"Europe/Moscow",
    "iso:country":"RU",
    "name:rus_x_preferred":[
        "\u041c\u0430\u0437\u044b\u0440\u0438\u043d\u043a\u0430"
    ],
    "name:und_x_variant":[
        "\u041c\u0430\u0437\u044b\u0440\u0438\u043d\u043a\u0430"
    ],
    "wof:name":"Mazyrinka",
    "wof:placetype":"locality"
},
  "geometry": {"coordinates":[44.8344,53.325],"type":"Point"}
}