{
  "type": "Feature",
  "properties": {
    "gn:admin1_code":"67",
    "gn:asciiname":"Kurganov",
    "gn:country_code":"RU",
    "gn:dem":26,
    "gn:feature_class":"P",
    "gn:feature_code":"PPL",
    "gn:name":"Kurganov",
    "gn:population":0,
    "gn:timezone":"Europe/Saratov",
    "iso:country":"RU",
    "name:rus_x_preferred":[
        "\u041a\u0443\u0440\u0433\u0430\u043d\u043e\u0432"
    ],
    "wof:name":"Kurganov",
    "wof:placetype":"locality"
},
  "geometry": {"coordinates":[48.21002,50.20474],"type":"Point"}
}