{
  "type": "Feature",
  "properties": {
    "gn:admin1_code":"17.0",
    "gn:asciiname":"Agachkala",
    "gn:country_code":"RU",
    "gn:dem":687,
    "gn:feature_class":"P",
    "gn:feature_code":"PPL",
    "gn:name":"Agachkala",
    "gn:population":0,
    "gn:timezone":"Europe/Moscow",
    "iso:country":"RU",
    "name:nor_x_preferred":[
        "Agatsjkala"
    ],
    "name:rus_x_preferred":[
        "\u0410\u0433\u0430\u0447\u043a\u0430\u043b\u0430"
    ],
    "wof:name":"Agachkala",
    "wof:placetype":"locality"
},
  "geometry": {"coordinates":[47.07599,42.76698],"type":"Point"}
}