{
  "type": "Feature",
  "properties": {
    "gn:admin1_code":"37.0",
    "gn:asciiname":"Abrosimovo",
    "gn:country_code":"RU",
    "gn:dem":148,
    "gn:feature_class":"P",
    "gn:feature_code":"PPL",
    "gn:name":"Abrosimovo",
    "gn:population":0,
    "gn:timezone":"Europe/Moscow",
    "iso:country":"RU",
    "name:eng_x_preferred":[
        "Abrosimovo"
    ],
    "name:nor_x_preferred":[
        "Abrosimovo"
    ],
    "name:rus_x_preferred":[
        "\u0410\u0431\u0440\u043e\u0441\u0438\u043c\u043e\u0432\u043e"
    ],
    "wof:name":"Abrosimovo",
    "wof:placetype":"locality"
},
  "geometry": {"coordinates":[44.12063,58.31479],"type":"Point"}
}