{
  "type": "Feature",
  "properties": {
    "gn:admin1_code":"47.0",
    "gn:admin2_code":"579462",
    "gn:asciiname":"Pestovo",
    "gn:country_code":"RU",
    "gn:dem":130,
    "gn:elevation":"148.0",
    "gn:feature_class":"P",
    "gn:feature_code":"PPL",
    "gn:name":"Pestovo",
    "gn:population":135,
    "gn:timezone":"Europe/Moscow",
    "iso:country":"RU",
    "name:eng_x_preferred":[
        "Pestovo"
    ],
    "name:rus_x_preferred":[
        "\u041f\u0435\u0441\u0442\u043e\u0432\u043e"
    ],
    "wof:name":"Pestovo",
    "wof:placetype":"locality",
    "wof:population":135
},
  "geometry": {"coordinates":[38.052,55.74],"type":"Point"}
}