{
  "type": "Feature",
  "properties": {
    "gn:admin1_code":"60",
    "gn:asciiname":"Barabany",
    "gn:country_code":"RU",
    "gn:dem":82,
    "gn:feature_class":"P",
    "gn:feature_code":"PPL",
    "gn:name":"Barabany",
    "gn:population":0,
    "gn:timezone":"Europe/Moscow",
    "iso:country":"RU",
    "name:rus_x_preferred":[
        "\u0411\u0430\u0440\u0430\u0431\u0430\u043d\u044b"
    ],
    "wof:name":"Barabany",
    "wof:placetype":"locality"
},
  "geometry": {"coordinates":[28.68431,56.79475],"type":"Point"}
}