{
  "type": "Feature",
  "properties": {
    "gn:admin1_code":"60",
    "gn:asciiname":"Starishnyy Bor",
    "gn:country_code":"RU",
    "gn:dem":37,
    "gn:feature_class":"P",
    "gn:feature_code":"PPL",
    "gn:name":"Starishnyy Bor",
    "gn:population":0,
    "gn:timezone":"Europe/Moscow",
    "iso:country":"RU",
    "name:rus_x_preferred":[
        "\u0421\u0442\u0430\u0440\u0438\u0448\u043d\u044b\u0439 \u0411\u043e\u0440"
    ],
    "wof:name":"Starishnyy Bor",
    "wof:placetype":"locality"
},
  "geometry": {"coordinates":[28.0766,58.1072],"type":"Point"}
}