{
  "type": "Feature",
  "properties": {
    "gn:admin1_code":"52",
    "gn:asciiname":"Korshikovo",
    "gn:country_code":"RU",
    "gn:dem":172,
    "gn:feature_class":"P",
    "gn:feature_code":"PPL",
    "gn:name":"Korshikovo",
    "gn:population":0,
    "gn:timezone":"Europe/Moscow",
    "iso:country":"RU",
    "name:rus_x_preferred":[
        "\u041a\u043e\u0440\u0448\u0438\u043a\u043e\u0432\u043e"
    ],
    "wof:name":"Korshikovo",
    "wof:placetype":"locality"
},
  "geometry": {"coordinates":[35.10112,58.34106],"type":"Point"}
}