{
  "type": "Feature",
  "properties": {
    "gn:admin1_code":"45",
    "gn:asciiname":"Mari-Shoi",
    "gn:country_code":"RU",
    "gn:dem":181,
    "gn:feature_class":"P",
    "gn:feature_code":"PPL",
    "gn:name":"Mari-Shoi",
    "gn:population":0,
    "gn:timezone":"Europe/Moscow",
    "iso:country":"RU",
    "name:eng_x_preferred":[
        "Mari-Shoi"
    ],
    "name:nor_x_preferred":[
        "Mari-Sjoi"
    ],
    "name:rus_x_preferred":[
        "\u041c\u0430\u0440\u0438-\u0428\u043e\u0438"
    ],
    "wof:name":"Mari-Shoi",
    "wof:placetype":"locality"
},
  "geometry": {"coordinates":[49.09611,56.6875],"type":"Point"}
}