{
  "type": "Feature",
  "properties": {
    "gn:admin1_code":"42",
    "gn:asciiname":"Novinka",
    "gn:cc2":"RU",
    "gn:country_code":"RU",
    "gn:dem":5,
    "gn:feature_class":"P",
    "gn:feature_code":"PPL",
    "gn:name":"Novinka",
    "gn:population":0,
    "gn:timezone":"Europe/Moscow",
    "iso:country":"RU",
    "name:fin_x_preferred":[
        "Rasalahti"
    ],
    "name:rus_x_preferred":[
        "\u0420\u0430\u0441\u0430\u043b\u0430\u0445\u0442\u0438"
    ],
    "name:und_x_variant":[
        "Rasalaks",
        "Rasalakhti"
    ],
    "wof:name":"Novinka",
    "wof:placetype":"locality"
},
  "geometry": {"coordinates":[28.58351,60.72333],"type":"Point"}
}