{
  "type": "Feature",
  "properties": {
    "gn:admin1_code":"67",
    "gn:asciiname":"Kutseba",
    "gn:country_code":"RU",
    "gn:dem":97,
    "gn:feature_class":"P",
    "gn:feature_code":"PPL",
    "gn:name":"Kutseba",
    "gn:population":0,
    "gn:timezone":"Europe/Saratov",
    "iso:country":"RU",
    "name:rus_x_preferred":[
        "\u041a\u0443\u0446\u0435\u0431\u0430"
    ],
    "name:und_x_variant":[
        "\u041a\u0443\u0446\u0435\u0431\u0430"
    ],
    "wof:name":"Kutseba",
    "wof:placetype":"locality"
},
  "geometry": {"coordinates":[50.65,51.76667],"type":"Point"}
}