{
  "type": "Feature",
  "properties": {
    "gn:admin1_code":"55",
    "gn:asciiname":"Ishmuratovo",
    "gn:country_code":"RU",
    "gn:dem":215,
    "gn:feature_class":"P",
    "gn:feature_code":"PPL",
    "gn:name":"Ishmuratovo",
    "gn:population":0,
    "gn:timezone":"Asia/Yekaterinburg",
    "iso:country":"RU",
    "name:rus_x_preferred":[
        "\u0418\u0448\u043c\u0443\u0440\u0430\u0442\u043e\u0432\u043e"
    ],
    "name:und_x_variant":[
        "Ishmuratova",
        "Ishmuratovo",
        "\u0418\u0448\u043c\u0443\u0440\u0430\u0442\u043e\u0432\u043e"
    ],
    "wof:name":"Ishmuratovo",
    "wof:placetype":"locality"
},
  "geometry": {"coordinates":[57.4103,51.4521],"type":"Point"}
}