{
  "type": "Feature",
  "properties": {
    "iso:country":"RU",
    "qs:name":"Tosnenskiy Rayon",
    "qs:name_adm0":"Russia",
    "qs:name_adm1":"Leningrad Oblast",
    "qs:photos":13,
    "qs:photos_1k":3,
    "qs:photos_9k":1,
    "qs:photos_9r":1,
    "qs:photos_all":13,
    "qs:photos_sr":1,
    "qs:placetype":"Town",
    "qs:pop_sr":"0",
    "wof:name":"Tosnenskiy Rayon",
    "wof:placetype":"locality"
},
  "geometry": {"coordinates":[30.891966,59.538343],"type":"Point"}
}