{
  "type": "Feature",
  "properties": {
    "gn:admin1_code":"73",
    "gn:asciiname":"Malinovoye",
    "gn:country_code":"RU",
    "gn:dem":64,
    "gn:feature_class":"P",
    "gn:feature_code":"PPL",
    "gn:name":"Malinovoye",
    "gn:population":0,
    "gn:timezone":"Europe/Moscow",
    "iso:country":"RU",
    "name:rus_x_preferred":[
        "\u041c\u0430\u043b\u0438\u043d\u043e\u0432\u043e\u0435"
    ],
    "name:und_x_variant":[
        "\u041c\u0430\u043b\u0438\u043d\u043e\u0432\u043e\u0435"
    ],
    "wof:name":"Malinovoye",
    "wof:placetype":"locality"
},
  "geometry": {"coordinates":[50.6611,55.4856],"type":"Point"}
}