{
  "type": "Feature",
  "properties": {
    "gn:admin1_code":"55",
    "gn:asciiname":"Dolinovka",
    "gn:country_code":"RU",
    "gn:dem":228,
    "gn:feature_class":"P",
    "gn:feature_code":"PPL",
    "gn:name":"Dolinovka",
    "gn:population":0,
    "gn:timezone":"Asia/Yekaterinburg",
    "iso:country":"RU",
    "name:rus_x_preferred":[
        "\u0414\u043e\u043b\u0438\u043d\u043e\u0432\u043a\u0430"
    ],
    "name:und_x_variant":[
        "\u0414\u043e\u043b\u0438\u043d\u043e\u0432\u043a\u0430"
    ],
    "wof:name":"Dolinovka",
    "wof:placetype":"locality"
},
  "geometry": {"coordinates":[54.4515,52.3345],"type":"Point"}
}