{
  "type": "Feature",
  "properties": {
    "gn:admin1_code":"85",
    "gn:asciiname":"Koshkina",
    "gn:cc2":"RU",
    "gn:country_code":"RU",
    "gn:dem":247,
    "gn:feature_class":"P",
    "gn:feature_code":"PPL",
    "gn:name":"Koshkina",
    "gn:population":0,
    "gn:timezone":"Europe/Moscow",
    "iso:country":"RU",
    "name:rus_x_preferred":[
        "\u041a\u043e\u0448\u043a\u0438\u043d\u0430"
    ],
    "name:und_x_variant":[
        "Koshkino",
        "Ko\u0161kina",
        "Koshkina"
    ],
    "wof:name":"Koshkina",
    "wof:placetype":"locality"
},
  "geometry": {"coordinates":[37.03333,61.45],"type":"Point"}
}