{
  "type": "Feature",
  "properties": {
    "gn:admin1_code":"76.0",
    "gn:asciiname":"Begino",
    "gn:country_code":"RU",
    "gn:dem":176,
    "gn:feature_class":"P",
    "gn:feature_code":"PPL",
    "gn:name":"Begino",
    "gn:population":0,
    "gn:timezone":"Europe/Moscow",
    "iso:country":"RU",
    "name:eng_x_preferred":[
        "Begino"
    ],
    "name:rus_x_preferred":[
        "\u0411\u0435\u0442\u0438\u043d\u043e"
    ],
    "name:rus_x_variant":[
        "\u0411\u0435\u0433\u0438\u043d\u043e"
    ],
    "wof:name":"Begino",
    "wof:placetype":"locality"
},
  "geometry": {"coordinates":[37.05195,53.82405],"type":"Point"}
}