{
  "type": "Feature",
  "properties": {
    "gn:admin1_code":"87",
    "gn:asciiname":"Syadaykharvuta",
    "gn:country_code":"RU",
    "gn:dem":-9999,
    "gn:feature_class":"P",
    "gn:feature_code":"PPL",
    "gn:name":"Syadaykharvuta",
    "gn:population":0,
    "gn:timezone":"Asia/Yekaterinburg",
    "iso:country":"RU",
    "name:und_x_variant":[
        "Faktoriya Syaday-Kharvuta",
        "Syadaykharvuta"
    ],
    "wof:name":"Syadaykharvuta",
    "wof:placetype":"locality"
},
  "geometry": {"coordinates":[73.94116,67.16667],"type":"Point"}
}