{
  "type": "Feature",
  "properties": {
    "gn:admin1_code":"83.0",
    "gn:asciiname":"Yuzhnyy",
    "gn:country_code":"RU",
    "gn:dem":149,
    "gn:feature_class":"P",
    "gn:feature_code":"PPL",
    "gn:name":"Yuzhnyy",
    "gn:population":0,
    "gn:timezone":"Europe/Moscow",
    "iso:country":"RU",
    "name:eng_x_preferred":[
        "Yuzhnyy"
    ],
    "name:nor_x_preferred":[
        "Juzjnyj"
    ],
    "name:rus_x_preferred":[
        "\u042e\u0436\u043d\u044b\u0439"
    ],
    "wof:name":"Yuzhnyy",
    "wof:placetype":"locality"
},
  "geometry": {"coordinates":[41.26667,55.35889],"type":"Point"}
}