{
  "type": "Feature",
  "properties": {
    "gn:admin1_code":"37",
    "gn:asciiname":"Nikulino",
    "gn:country_code":"RU",
    "gn:dem":154,
    "gn:feature_class":"P",
    "gn:feature_code":"PPL",
    "gn:name":"Nikulino",
    "gn:population":0,
    "gn:timezone":"Europe/Moscow",
    "iso:country":"RU",
    "name:rus_x_preferred":[
        "\u041d\u0438\u043a\u0443\u043b\u0438\u043d\u043e"
    ],
    "wof:name":"Nikulino",
    "wof:placetype":"locality"
},
  "geometry": {"coordinates":[42.0147,58.0795],"type":"Point"}
}