{
  "type": "Feature",
  "properties": {
    "gn:admin1_code":"67.0",
    "gn:asciiname":"Bol'shoy Krasnyy Yar",
    "gn:country_code":"RU",
    "gn:dem":26,
    "gn:feature_class":"P",
    "gn:feature_code":"PPL",
    "gn:name":"Bol\u2019shoy Krasnyy Yar",
    "gn:population":0,
    "gn:timezone":"Europe/Saratov",
    "iso:country":"RU",
    "name:rus_x_preferred":[
        "\u0411\u043e\u043b\u044c\u0448\u043e\u0439 \u041a\u0440\u0430\u0441\u043d\u044b\u0439 \u042f\u0440"
    ],
    "name:und_x_variant":[
        "Krasnyy Yar",
        "Bol\u2019shoy Krasnyy Yar"
    ],
    "wof:name":"Bol'shoy Krasnyy Yar",
    "wof:placetype":"locality"
},
  "geometry": {"coordinates":[48.15,52.25],"type":"Point"}
}