{
  "type": "Feature",
  "properties": {
    "gn:admin1_code":"33.0",
    "gn:asciiname":"Zagaynovy",
    "gn:country_code":"RU",
    "gn:dem":107,
    "gn:feature_class":"P",
    "gn:feature_code":"PPL",
    "gn:name":"Zagaynovy",
    "gn:population":0,
    "gn:timezone":"Europe/Kirov",
    "iso:country":"RU",
    "name:rus_x_preferred":[
        "\u0417\u0430\u0433\u0430\u0439\u043d\u043e\u0432\u044b"
    ],
    "wof:name":"Zagaynovy",
    "wof:placetype":"locality"
},
  "geometry": {"coordinates":[48.3637,58.6052],"type":"Point"}
}