{
  "type": "Feature",
  "properties": {
    "gn:admin1_code":"88",
    "gn:asciiname":"Pozobovo",
    "gn:country_code":"RU",
    "gn:dem":146,
    "gn:feature_class":"P",
    "gn:feature_code":"PPL",
    "gn:name":"Pozobovo",
    "gn:population":0,
    "gn:timezone":"Europe/Moscow",
    "iso:country":"RU",
    "name:rus_x_preferred":[
        "\u041f\u043e\u0437\u043e\u0431\u043e\u0432\u043e"
    ],
    "wof:name":"Pozobovo",
    "wof:placetype":"locality"
},
  "geometry": {"coordinates":[39.9412,57.42952],"type":"Point"}
}