{
  "type": "Feature",
  "properties": {
    "gn:admin1_code":"25",
    "gn:asciiname":"Krosna",
    "gn:country_code":"RU",
    "gn:dem":219,
    "gn:feature_class":"P",
    "gn:feature_code":"PPL",
    "gn:name":"Krosna",
    "gn:population":0,
    "gn:timezone":"Europe/Moscow",
    "iso:country":"RU",
    "name:ceb_x_preferred":[
        "Krosna"
    ],
    "name:deu_x_preferred":[
        "Krosna"
    ],
    "name:est_x_preferred":[
        "Krosna"
    ],
    "name:fin_x_preferred":[
        "Krosna"
    ],
    "name:ita_x_preferred":[
        "Krosna"
    ],
    "name:lit_x_preferred":[
        "Krosna"
    ],
    "name:nor_x_preferred":[
        "Krosna"
    ],
    "name:pol_x_preferred":[
        "Krasna"
    ],
    "name:rus_x_preferred":[
        "\u041a\u0440\u043e\u0441\u043d\u0430"
    ],
    "name:swe_x_preferred":[
        "Krosna"
    ],
    "wof:name":"Krosna",
    "wof:placetype":"locality"
},
  "geometry": {"coordinates":[36.63656,54.54183],"type":"Point"}
}