{
  "type": "Feature",
  "properties": {
    "gn:admin1_code":"8.0",
    "gn:asciiname":"Aterbash",
    "gn:country_code":"RU",
    "gn:dem":240,
    "gn:feature_class":"P",
    "gn:feature_code":"PPL",
    "gn:name":"Aterbash",
    "gn:population":0,
    "gn:timezone":"Asia/Yekaterinburg",
    "iso:country":"RU",
    "name:nor_x_preferred":[
        "Aterbasj"
    ],
    "name:rus_x_preferred":[
        "\u0410\u0442\u0435\u0440\u0431\u0430\u0448"
    ],
    "wof:name":"Aterbash",
    "wof:placetype":"locality"
},
  "geometry": {"coordinates":[56.61451,55.72734000000001],"type":"Point"}
}