{
  "type": "Feature",
  "properties": {
    "gn:admin1_code":"77",
    "gn:asciiname":"Nivishche",
    "gn:country_code":"RU",
    "gn:dem":183,
    "gn:feature_class":"P",
    "gn:feature_code":"PPL",
    "gn:name":"Nivishche",
    "gn:population":0,
    "gn:timezone":"Europe/Moscow",
    "iso:country":"RU",
    "name:rus_x_preferred":[
        "\u041d\u0438\u0432\u0438\u0449\u0435"
    ],
    "name:und_x_variant":[
        "\u041d\u0438\u0432\u0438\u0449\u0435"
    ],
    "wof:name":"Nivishche",
    "wof:placetype":"locality"
},
  "geometry": {"coordinates":[34.99932,57.64211],"type":"Point"}
}