{
  "type": "Feature",
  "properties": {
    "gn:admin1_code":"73",
    "gn:asciiname":"Urumshirma",
    "gn:country_code":"RU",
    "gn:dem":98,
    "gn:feature_class":"P",
    "gn:feature_code":"PPL",
    "gn:name":"Urumshirma",
    "gn:population":0,
    "gn:timezone":"Europe/Moscow",
    "iso:country":"RU",
    "name:rus_x_preferred":[
        "\u0423\u0440\u0443\u043c\u0448\u0438\u0440\u043c\u0430"
    ],
    "name:und_x_variant":[
        "Urumsherma"
    ],
    "wof:name":"Urumshirma",
    "wof:placetype":"locality"
},
  "geometry": {"coordinates":[50.29861,55.8959],"type":"Point"}
}