{
  "type": "Feature",
  "properties": {
    "gn:admin1_code":"37",
    "gn:asciiname":"Malyshevo",
    "gn:country_code":"RU",
    "gn:dem":182,
    "gn:feature_class":"P",
    "gn:feature_code":"PPL",
    "gn:name":"Malyshevo",
    "gn:population":0,
    "gn:timezone":"Europe/Moscow",
    "iso:country":"RU",
    "name:eng_x_preferred":[
        "Malyshevo"
    ],
    "name:nor_x_preferred":[
        "Malysjevo"
    ],
    "name:rus_x_preferred":[
        "\u041c\u0430\u043b\u044b\u0448\u0435\u0432\u043e"
    ],
    "name:und_x_variant":[
        "\u041c\u0430\u043b\u044b\u0448\u0435\u0432\u043e",
        "Malyshevo"
    ],
    "wof:name":"Malyshevo",
    "wof:placetype":"locality"
},
  "geometry": {"coordinates":[42.33752,58.29525],"type":"Point"}
}