{
  "type": "Feature",
  "properties": {
    "gn:admin1_code":"42.0",
    "gn:asciiname":"Storozhevoye",
    "gn:country_code":"RU",
    "gn:dem":12,
    "gn:feature_class":"P",
    "gn:feature_code":"PPL",
    "gn:name":"Storozhevoye",
    "gn:population":0,
    "gn:timezone":"Europe/Moscow",
    "iso:country":"RU",
    "name:fin_x_preferred":[
        "Kuurnanpohja"
    ],
    "wof:name":"Storozhevoye",
    "wof:placetype":"locality"
},
  "geometry": {"coordinates":[28.76298,61.0496],"type":"Point"}
}