{
  "type": "Feature",
  "properties": {
    "gn:admin1_code":"43",
    "gn:asciiname":"Yevlanovka",
    "gn:country_code":"RU",
    "gn:dem":148,
    "gn:feature_class":"P",
    "gn:feature_code":"PPL",
    "gn:name":"Yevlanovka",
    "gn:population":0,
    "gn:timezone":"Europe/Moscow",
    "iso:country":"RU",
    "name:rus_x_preferred":[
        "\u0415\u0432\u043b\u0430\u043d\u043e\u0432\u043a\u0430"
    ],
    "wof:name":"Yevlanovka",
    "wof:placetype":"locality"
},
  "geometry": {"coordinates":[40.4629,52.2183],"type":"Point"}
}