{
  "type": "Feature",
  "properties": {
    "gn:admin1_code":"37",
    "gn:asciiname":"Ugol'skoye",
    "gn:country_code":"RU",
    "gn:dem":116,
    "gn:feature_class":"P",
    "gn:feature_code":"PPL",
    "gn:name":"Ugol\u2019skoye",
    "gn:population":0,
    "gn:timezone":"Europe/Moscow",
    "iso:country":"RU",
    "name:eng_x_preferred":[
        "Ugol'skoye"
    ],
    "name:nor_x_preferred":[
        "Ugolskoje"
    ],
    "name:rus_x_preferred":[
        "\u0423\u0433\u043e\u043b\u044c\u0441\u043a\u043e\u0435"
    ],
    "name:und_x_variant":[
        "Ugol\u2019skoye"
    ],
    "wof:name":"Ugol'skoye",
    "wof:placetype":"locality"
},
  "geometry": {"coordinates":[42.20549000000001,57.61103000000001],"type":"Point"}
}