{
  "type": "Feature",
  "properties": {
    "gn:admin1_code":"38",
    "gn:asciiname":"Orekhov Kut",
    "gn:country_code":"RU",
    "gn:dem":2,
    "gn:feature_class":"P",
    "gn:feature_code":"PPL",
    "gn:name":"Orekhov Kut",
    "gn:population":0,
    "gn:timezone":"Europe/Moscow",
    "iso:country":"RU",
    "name:rus_x_preferred":[
        "\u041e\u0440\u0435\u0445\u043e\u0432 \u041a\u0443\u0442"
    ],
    "wof:name":"Orekhov Kut",
    "wof:placetype":"locality"
},
  "geometry": {"coordinates":[37.37322,45.23803],"type":"Point"}
}