{
  "type": "Feature",
  "properties": {
    "gn:admin1_code":"61",
    "gn:asciiname":"Il'ichevka",
    "gn:country_code":"RU",
    "gn:dem":129,
    "gn:feature_class":"P",
    "gn:feature_code":"PPL",
    "gn:name":"Il\u2019ich\u00ebvka",
    "gn:population":0,
    "gn:timezone":"Europe/Moscow",
    "iso:country":"RU",
    "name:rus_x_preferred":[
        "\u0418\u043b\u044c\u0438\u0447\u0451\u0432\u043a\u0430"
    ],
    "name:und_x_variant":[
        "Il\u2019icha",
        "Pos\u00eblok Il\u2019icha",
        "Il\u2019ich\u00ebvka"
    ],
    "wof:name":"Il'ichevka",
    "wof:placetype":"locality"
},
  "geometry": {"coordinates":[39.88111,47.74083],"type":"Point"}
}