{
  "type": "Feature",
  "properties": {
    "gn:admin1_code":"63",
    "gn:asciiname":"Krasnaya Zvezda",
    "gn:country_code":"RU",
    "gn:dem":746,
    "gn:feature_class":"P",
    "gn:feature_code":"PPL",
    "gn:name":"Krasnaya Zvezda",
    "gn:population":0,
    "gn:timezone":"Asia/Yakutsk",
    "iso:country":"RU",
    "name:eng_x_preferred":[
        "Krasnaya Zvezda"
    ],
    "name:nor_x_preferred":[
        "Krasnaja Zvezda"
    ],
    "name:rus_x_preferred":[
        "\u041a\u0440\u0430\u0441\u043d\u0430\u044f \u0417\u0432\u0435\u0437\u0434\u0430"
    ],
    "name:und_x_variant":[
        "\u041a\u0440\u0430\u0441\u043d\u0430\u044f \u0417\u0432\u0435\u0437\u0434\u0430",
        "Krasnaya Zvezda"
    ],
    "wof:name":"Krasnaya Zvezda",
    "wof:placetype":"locality"
},
  "geometry": {"coordinates":[125.00991,58.18648],"type":"Point"}
}