{
  "type": "Feature",
  "properties": {
    "gn:admin1_code":"77",
    "gn:asciiname":"Strana Sovetov",
    "gn:country_code":"RU",
    "gn:dem":238,
    "gn:feature_class":"P",
    "gn:feature_code":"PPL",
    "gn:name":"Strana Sovetov",
    "gn:population":0,
    "gn:timezone":"Europe/Moscow",
    "iso:country":"RU",
    "name:rus_x_preferred":[
        "\u0421\u0442\u0440\u0430\u043d\u0430 \u0421\u043e\u0432\u0435\u0442\u043e\u0432"
    ],
    "wof:name":"Strana Sovetov",
    "wof:placetype":"locality"
},
  "geometry": {"coordinates":[34.11155,56.78952],"type":"Point"}
}