{
  "type": "Feature",
  "properties": {
    "gn:admin1_code":"85",
    "gn:asciiname":"Slobodishcha",
    "gn:country_code":"RU",
    "gn:dem":132,
    "gn:feature_class":"P",
    "gn:feature_code":"PPL",
    "gn:name":"Slobodishcha",
    "gn:population":0,
    "gn:timezone":"Europe/Moscow",
    "iso:country":"RU",
    "name:rus_x_preferred":[
        "\u0421\u043b\u043e\u0431\u043e\u0434\u0438\u0449\u0430"
    ],
    "name:und_x_variant":[
        "\u0421\u043b\u043e\u0431\u043e\u0434\u0438\u0449\u0430"
    ],
    "wof:name":"Slobodishcha",
    "wof:placetype":"locality"
},
  "geometry": {"coordinates":[39.40763,59.3466],"type":"Point"}
}