{
  "type": "Feature",
  "properties": {
    "gn:admin1_code":"33.0",
    "gn:asciiname":"Malaya Kurba",
    "gn:country_code":"RU",
    "gn:dem":112,
    "gn:feature_class":"P",
    "gn:feature_code":"PPL",
    "gn:name":"Malaya Kurba",
    "gn:population":0,
    "gn:timezone":"Europe/Kirov",
    "iso:country":"RU",
    "name:rus_x_preferred":[
        "\u041c\u0430\u043b\u0430\u044f \u041a\u0443\u0440\u0431\u0430"
    ],
    "wof:name":"Malaya Kurba",
    "wof:placetype":"locality"
},
  "geometry": {"coordinates":[48.9809,57.1971],"type":"Point"}
}