{
  "type": "Feature",
  "properties": {
    "gn:admin1_code":"56",
    "gn:asciiname":"Posiden'",
    "gn:country_code":"RU",
    "gn:dem":211,
    "gn:feature_class":"P",
    "gn:feature_code":"PPL",
    "gn:name":"Posiden\u2019",
    "gn:population":0,
    "gn:timezone":"Europe/Moscow",
    "iso:country":"RU",
    "name:rus_x_preferred":[
        "\u041f\u043e\u0441\u0438\u0434\u0435\u043d\u044c"
    ],
    "name:und_x_variant":[
        "Posiden\u2019",
        "\u041f\u043e\u0441\u0438\u0434\u0435\u043d\u044c"
    ],
    "wof:name":"Posiden'",
    "wof:placetype":"locality"
},
  "geometry": {"coordinates":[35.57889,53.37583000000001],"type":"Point"}
}