{
  "type": "Feature",
  "properties": {
    "gn:country":"RU",
    "gn:fcode":"PPL",
    "gn:population":1468,
    "iso:country":"RU",
    "name:eng_x_preferred":[
        "Krasnyy Profintern"
    ],
    "name:nor_x_preferred":[
        "Krasnyj Profintern"
    ],
    "name:rus_x_preferred":[
        "\u041a\u0440\u0430\u0441\u043d\u044b\u0439 \u041f\u0440\u043e\u0444\u0438\u043d\u0442\u0435\u0440\u043d"
    ],
    "name:und_x_variant":[
        "Guzitsino"
    ],
    "qs:name":"Krasnyy Profintern",
    "qs:name_adm0":"Russia",
    "qs:name_adm1":"Yaroslavl Oblast",
    "qs:photos_9k":1,
    "qs:photos_9r":1,
    "qs:photos_all":1,
    "qs:photos_sr":0,
    "qs:placetype":"Town",
    "qs:pop_sr":"3",
    "wof:name":"Krasnyy Profintern",
    "wof:placetype":"locality",
    "wof:population":1468
},
  "geometry": {"coordinates":[40.43502,57.74459],"type":"Point"}
}