{
  "type": "Feature",
  "properties": {
    "gn:admin1_code":"90.0",
    "gn:asciiname":"Filagino",
    "gn:country_code":"RU",
    "gn:dem":138,
    "gn:feature_class":"P",
    "gn:feature_code":"PPL",
    "gn:name":"Filagino",
    "gn:population":0,
    "gn:timezone":"Asia/Yekaterinburg",
    "iso:country":"RU",
    "name:nor_x_preferred":[
        "Filagino"
    ],
    "name:rus_x_preferred":[
        "\u0424\u0438\u043b\u0430\u0433\u0438\u043d\u043e"
    ],
    "name:und_x_variant":[
        "Filagina"
    ],
    "wof:name":"Filagino",
    "wof:placetype":"locality"
},
  "geometry": {"coordinates":[56.642,58.841],"type":"Point"}
}