{
  "type": "Feature",
  "properties": {
    "gn:admin1_code":"67.0",
    "gn:asciiname":"Furmanovo",
    "gn:country_code":"RU",
    "gn:dem":71,
    "gn:feature_class":"P",
    "gn:feature_code":"PPL",
    "gn:name":"Furmanovo",
    "gn:population":0,
    "gn:timezone":"Europe/Saratov",
    "iso:country":"RU",
    "name:eng_x_preferred":[
        "Furmanovo"
    ],
    "name:nor_x_preferred":[
        "Furmanovo"
    ],
    "name:rus_x_preferred":[
        "\u0424\u0443\u0440\u043c\u0430\u043d\u043e\u0432\u043e"
    ],
    "name:und_x_variant":[
        "Brunnengraben"
    ],
    "wof:name":"Furmanovo",
    "wof:placetype":"locality"
},
  "geometry": {"coordinates":[47.33971,51.65787],"type":"Point"}
}