{
  "type": "Feature",
  "properties": {
    "gn:admin1_code":"91",
    "gn:asciiname":"Mikhalevka",
    "gn:country_code":"RU",
    "gn:dem":252,
    "gn:feature_class":"P",
    "gn:feature_code":"PPL",
    "gn:name":"Mikhal\u00ebvka",
    "gn:population":0,
    "gn:timezone":"Asia/Krasnoyarsk",
    "iso:country":"RU",
    "name:rus_x_preferred":[
        "\u041c\u0438\u0445\u0430\u043b\u0451\u0432\u043a\u0430"
    ],
    "name:und_x_variant":[
        "Mikhaylovka",
        "Mikhal\u00ebvka"
    ],
    "wof:name":"Mikhalevka",
    "wof:placetype":"locality"
},
  "geometry": {"coordinates":[94.895,55.9536],"type":"Point"}
}