{
  "type": "Feature",
  "properties": {
    "gn:admin1_code":"56",
    "gn:asciiname":"Novyy Tim",
    "gn:country_code":"RU",
    "gn:dem":149,
    "gn:feature_class":"P",
    "gn:feature_code":"PPL",
    "gn:name":"Novyy Tim",
    "gn:population":0,
    "gn:timezone":"Europe/Moscow",
    "iso:country":"RU",
    "name:rus_x_preferred":[
        "\u041d\u043e\u0432\u044b\u0439 \u0422\u0438\u043c"
    ],
    "wof:name":"Novyy Tim",
    "wof:placetype":"locality"
},
  "geometry": {"coordinates":[37.36388,52.22595],"type":"Point"}
}