{
  "type": "Feature",
  "properties": {
    "gn:admin1_code":"51",
    "gn:asciiname":"Malyye Ashkaty",
    "gn:country_code":"RU",
    "gn:dem":143,
    "gn:feature_class":"P",
    "gn:feature_code":"PPL",
    "gn:name":"Malyye Ashkaty",
    "gn:population":0,
    "gn:timezone":"Europe/Moscow",
    "iso:country":"RU",
    "name:rus_x_preferred":[
        "\u041c\u0430\u043b\u044b\u0435 \u0410\u0448\u043a\u0430\u0442\u044b"
    ],
    "wof:name":"Malyye Ashkaty",
    "wof:placetype":"locality"
},
  "geometry": {"coordinates":[47.1422,57.6458],"type":"Point"}
}