{
  "type": "Feature",
  "properties": {
    "gn:admin1_code":"91",
    "gn:asciiname":"Yekaterininskiy",
    "gn:country_code":"RU",
    "gn:dem":308,
    "gn:feature_class":"P",
    "gn:feature_code":"PPL",
    "gn:name":"Yekaterininskiy",
    "gn:population":0,
    "gn:timezone":"Asia/Krasnoyarsk",
    "iso:country":"RU",
    "wof:name":"Yekaterininskiy",
    "wof:placetype":"locality"
},
  "geometry": {"coordinates":[93.78333000000001,57.15],"type":"Point"}
}