{
  "type": "Feature",
  "properties": {
    "gn:admin1_code":"71",
    "gn:asciiname":"Zhukovo",
    "gn:country_code":"RU",
    "gn:dem":161,
    "gn:feature_class":"P",
    "gn:feature_code":"PPL",
    "gn:name":"Zhukovo",
    "gn:population":0,
    "gn:timezone":"Asia/Yekaterinburg",
    "iso:country":"RU",
    "name:rus_x_preferred":[
        "\u0416\u0443\u043a\u043e\u0432\u043e"
    ],
    "name:und_x_variant":[
        "\u0416\u0443\u043a\u043e\u0432\u043e",
        "Zhukova"
    ],
    "wof:name":"Zhukovo",
    "wof:placetype":"locality"
},
  "geometry": {"coordinates":[61.53284,57.49678],"type":"Point"}
}