{
  "type": "Feature",
  "properties": {
    "gn:admin1_code":"77",
    "gn:asciiname":"Varvarina Gora",
    "gn:country_code":"RU",
    "gn:dem":174,
    "gn:feature_class":"P",
    "gn:feature_code":"PPL",
    "gn:name":"Varvarina Gora",
    "gn:population":0,
    "gn:timezone":"Europe/Moscow",
    "iso:country":"RU",
    "name:rus_x_preferred":[
        "\u0412\u0430\u0440\u0432\u0430\u0440\u0438\u043d\u0430 \u0413\u043e\u0440\u0430"
    ],
    "name:und_x_variant":[
        "Varvarova-Gora"
    ],
    "wof:name":"Varvarina Gora",
    "wof:placetype":"locality"
},
  "geometry": {"coordinates":[35.44437,58.23846],"type":"Point"}
}