{
  "type": "Feature",
  "properties": {
    "gn:admin1_code":"33.0",
    "gn:asciiname":"Brityshi",
    "gn:country_code":"RU",
    "gn:dem":147,
    "gn:feature_class":"P",
    "gn:feature_code":"PPL",
    "gn:name":"Brityshi",
    "gn:population":0,
    "gn:timezone":"Europe/Kirov",
    "iso:country":"RU",
    "name:rus_x_preferred":[
        "\u0411\u0440\u0438\u0442\u044b\u0448\u0438"
    ],
    "name:und_x_variant":[
        "\u0411\u0440\u0438\u0442\u044b\u0448\u0438"
    ],
    "wof:name":"Brityshi",
    "wof:placetype":"locality"
},
  "geometry": {"coordinates":[48.13333,58.33333],"type":"Point"}
}