{
  "type": "Feature",
  "properties": {
    "gn:admin1_code":"33.0",
    "gn:asciiname":"Palasino",
    "gn:country_code":"RU",
    "gn:dem":187,
    "gn:feature_class":"P",
    "gn:feature_code":"PPL",
    "gn:name":"Palasino",
    "gn:population":0,
    "gn:timezone":"Europe/Kirov",
    "iso:country":"RU",
    "name:rus_x_preferred":[
        "\u041f\u0430\u043b\u0430\u0441\u0438\u043d\u043e"
    ],
    "wof:name":"Palasino",
    "wof:placetype":"locality"
},
  "geometry": {"coordinates":[48.75067,58.95981],"type":"Point"}
}