{
  "type": "Feature",
  "properties": {
    "gn:admin1_code":"55",
    "gn:asciiname":"Kislyatka",
    "gn:country_code":"RU",
    "gn:dem":285,
    "gn:feature_class":"P",
    "gn:feature_code":"PPL",
    "gn:name":"Kislyatka",
    "gn:population":0,
    "gn:timezone":"Asia/Yekaterinburg",
    "iso:country":"RU",
    "name:rus_x_preferred":[
        "\u041a\u0438\u0441\u043b\u044f\u0442\u043a\u0430"
    ],
    "wof:name":"Kislyatka",
    "wof:placetype":"locality"
},
  "geometry": {"coordinates":[54.48333,52.78333000000001],"type":"Point"}
}