{
  "type": "Feature",
  "properties": {
    "gn:admin1_code":"60.0",
    "gn:asciiname":"Brodovichi-Zapol'ye",
    "gn:country_code":"RU",
    "gn:dem":90,
    "gn:feature_class":"P",
    "gn:feature_code":"PPL",
    "gn:name":"Brodovichi-Zapol\u2019ye",
    "gn:population":0,
    "gn:timezone":"Europe/Moscow",
    "iso:country":"RU",
    "name:rus_x_preferred":[
        "\u0411\u0440\u043e\u0434\u043e\u0432\u0438\u0447\u0438-\u0417\u0430\u043f\u043e\u043b\u044c\u0435"
    ],
    "name:und_x_variant":[
        "Brodovichi-Zapol\u2019ye"
    ],
    "wof:name":"Brodovichi-Zapol'ye",
    "wof:placetype":"locality"
},
  "geometry": {"coordinates":[29.28332,57.5873],"type":"Point"}
}