{
  "type": "Feature",
  "properties": {
    "gn:admin1_code":"41.0",
    "gn:asciiname":"Afanas'yevka",
    "gn:country_code":"RU",
    "gn:dem":204,
    "gn:feature_class":"P",
    "gn:feature_code":"PPL",
    "gn:name":"Afanas\u2019yevka",
    "gn:population":0,
    "gn:timezone":"Europe/Moscow",
    "iso:country":"RU",
    "name:nor_x_preferred":[
        "Afanasievskoje"
    ],
    "name:rus_x_preferred":[
        "\u0410\u0444\u0430\u043d\u0430\u0441\u044c\u0435\u0432\u043a\u0430"
    ],
    "name:und_x_variant":[
        "Afanas\u2019yevskoye",
        "Afanas\u2019yevka"
    ],
    "wof:name":"Afanas'yevka",
    "wof:placetype":"locality"
},
  "geometry": {"coordinates":[37.5365,51.7297],"type":"Point"}
}