{
  "type": "Feature",
  "properties": {
    "gn:admin1_code":"52",
    "gn:asciiname":"Vnuto",
    "gn:country_code":"RU",
    "gn:dem":235,
    "gn:feature_class":"P",
    "gn:feature_code":"PPL",
    "gn:name":"Vnuto",
    "gn:population":0,
    "gn:timezone":"Europe/Moscow",
    "iso:country":"RU",
    "name:rus_x_preferred":[
        "\u0412\u043d\u0443\u0442\u043e"
    ],
    "wof:name":"Vnuto",
    "wof:placetype":"locality"
},
  "geometry": {"coordinates":[33.91715,58.89723000000001],"type":"Point"}
}