{
  "type": "Feature",
  "properties": {
    "gn:admin1_code":"73",
    "gn:asciiname":"Kyr-Tavgel'dino",
    "gn:country_code":"RU",
    "gn:dem":123,
    "gn:feature_class":"P",
    "gn:feature_code":"PPL",
    "gn:name":"Kyr-Tavgel\u2019dino",
    "gn:population":0,
    "gn:timezone":"Europe/Moscow",
    "iso:country":"RU",
    "name:und_x_variant":[
        "Krashoye",
        "Kyr-Tavgel\u2019dino"
    ],
    "wof:name":"Kyr-Tavgel'dino",
    "wof:placetype":"locality"
},
  "geometry": {"coordinates":[48.14383,55.10356],"type":"Point"}
}