{
  "type": "Feature",
  "properties": {
    "gn:admin1_code":"85",
    "gn:asciiname":"Davydkovo",
    "gn:country_code":"RU",
    "gn:dem":172,
    "gn:feature_class":"P",
    "gn:feature_code":"PPL",
    "gn:name":"Davydkovo",
    "gn:population":0,
    "gn:timezone":"Europe/Moscow",
    "iso:country":"RU",
    "name:che_x_preferred":[
        "\u0414\u0430\u0432\u044b\u0434\u043a\u043e\u0432\u043e"
    ],
    "name:rus_x_preferred":[
        "\u0414\u0430\u0432\u044b\u0434\u043a\u043e\u0432\u043e"
    ],
    "name:und_x_variant":[
        "\u0414\u0430\u0432\u044b\u0434\u043a\u043e\u0432\u043e"
    ],
    "wof:name":"Davydkovo",
    "wof:placetype":"locality"
},
  "geometry": {"coordinates":[38.8045,59.4317],"type":"Point"}
}