{
  "type": "Feature",
  "properties": {
    "gn:admin1_code":"25",
    "gn:asciiname":"Kolchevka",
    "gn:country_code":"RU",
    "gn:dem":159,
    "gn:feature_class":"P",
    "gn:feature_code":"PPL",
    "gn:name":"Kolchevka",
    "gn:population":0,
    "gn:timezone":"Europe/Moscow",
    "iso:country":"RU",
    "name:rus_x_preferred":[
        "\u041a\u043e\u043b\u0447\u0435\u0432\u043a\u0430"
    ],
    "wof:name":"Kolchevka",
    "wof:placetype":"locality"
},
  "geometry": {"coordinates":[35.10972,53.85694],"type":"Point"}
}