{
  "type": "Feature",
  "properties": {
    "gn:admin1_code":"21.0",
    "gn:asciiname":"Andronikha",
    "gn:country_code":"RU",
    "gn:dem":99,
    "gn:feature_class":"P",
    "gn:feature_code":"PPL",
    "gn:name":"Andronikha",
    "gn:population":0,
    "gn:timezone":"Europe/Moscow",
    "iso:country":"RU",
    "name:eng_x_preferred":[
        "Andronikha"
    ],
    "name:nor_x_preferred":[
        "Andronikha"
    ],
    "name:rus_x_preferred":[
        "\u0410\u043d\u0434\u0440\u043e\u043d\u0438\u0445\u0430"
    ],
    "wof:name":"Andronikha",
    "wof:placetype":"locality"
},
  "geometry": {"coordinates":[42.35037,57.54344],"type":"Point"}
}