{
  "type": "Feature",
  "properties": {
    "gn:admin1_code":"84",
    "gn:asciiname":"Maksari",
    "gn:country_code":"RU",
    "gn:dem":95,
    "gn:feature_class":"P",
    "gn:feature_code":"PPL",
    "gn:name":"Maksari",
    "gn:population":0,
    "gn:timezone":"Europe/Volgograd",
    "iso:country":"RU",
    "name:rus_x_preferred":[
        "\u041c\u0430\u043a\u0441\u0430\u0440\u0438"
    ],
    "name:und_x_variant":[
        "Maskari",
        "Maksai",
        "Maksari",
        "\u041c\u0430\u043a\u0441\u0430\u0440\u0438"
    ],
    "wof:name":"Maksari",
    "wof:placetype":"locality"
},
  "geometry": {"coordinates":[42.63808,49.10565],"type":"Point"}
}