{
  "type": "Feature",
  "properties": {
    "gn:admin1_code":"69",
    "gn:asciiname":"Chal'",
    "gn:country_code":"RU",
    "gn:dem":212,
    "gn:feature_class":"P",
    "gn:feature_code":"PPL",
    "gn:name":"Chal\u2019",
    "gn:population":0,
    "gn:timezone":"Europe/Moscow",
    "iso:country":"RU",
    "name:rus_x_preferred":[
        "\u0427\u0430\u043b\u044c"
    ],
    "name:und_x_variant":[
        "Chal\u2019",
        "\u0427\u0430\u043b\u044c"
    ],
    "wof:name":"Chal'",
    "wof:placetype":"locality"
},
  "geometry": {"coordinates":[35.0125,55.25417],"type":"Point"}
}