{
  "type": "Feature",
  "properties": {
    "gn:admin1_code":"37.0",
    "gn:asciiname":"Demenevo",
    "gn:country_code":"RU",
    "gn:dem":164,
    "gn:feature_class":"P",
    "gn:feature_code":"PPL",
    "gn:name":"Demenevo",
    "gn:population":0,
    "gn:timezone":"Europe/Moscow",
    "iso:country":"RU",
    "name:rus_x_preferred":[
        "\u0414\u0435\u043c\u0435\u043d\u0435\u0432\u043e"
    ],
    "name:und_x_variant":[
        "\u0414\u0435\u043c\u0435\u043d\u0435\u0432\u043e"
    ],
    "wof:name":"Demenevo",
    "wof:placetype":"locality"
},
  "geometry": {"coordinates":[41.30806,57.97384],"type":"Point"}
}