{
  "type": "Feature",
  "properties": {
    "gn:admin1_code":"67",
    "gn:asciiname":"Verkhnyaya Bannovka",
    "gn:country_code":"RU",
    "gn:dem":124,
    "gn:feature_class":"P",
    "gn:feature_code":"PPL",
    "gn:name":"Verkhnyaya Bannovka",
    "gn:population":0,
    "gn:timezone":"Europe/Saratov",
    "iso:country":"RU",
    "name:und_x_variant":[
        "Verkhnyaya",
        "Verkhnyaya Bannovka"
    ],
    "wof:name":"Verkhnyaya Bannovka",
    "wof:placetype":"locality"
},
  "geometry": {"coordinates":[45.58715,50.71739],"type":"Point"}
}