{
  "type": "Feature",
  "properties": {
    "gn:admin1_code":"47.0",
    "gn:asciiname":"Annenki",
    "gn:country_code":"RU",
    "gn:dem":114,
    "gn:feature_class":"P",
    "gn:feature_code":"PPL",
    "gn:name":"Annenki",
    "gn:population":0,
    "gn:timezone":"Europe/Moscow",
    "iso:country":"RU",
    "name:nor_x_preferred":[
        "Annenki"
    ],
    "name:rus_x_preferred":[
        "\u0410\u043d\u043d\u0435\u043d\u043a\u0438"
    ],
    "name:und_x_variant":[
        "Annenka"
    ],
    "wof:name":"Annenki",
    "wof:placetype":"locality"
},
  "geometry": {"coordinates":[39.41209,55.17237],"type":"Point"}
}