{
  "type": "Feature",
  "properties": {
    "gn:admin1_code":"69.0",
    "gn:asciiname":"Bol'shoye Zagor'ye",
    "gn:country_code":"RU",
    "gn:dem":184,
    "gn:feature_class":"P",
    "gn:feature_code":"PPL",
    "gn:name":"Bol\u2019shoye Zagor\u2019ye",
    "gn:population":0,
    "gn:timezone":"Europe/Moscow",
    "iso:country":"RU",
    "name:rus_x_preferred":[
        "\u0411\u043e\u043b\u044c\u0448\u043e\u0435 \u0417\u0430\u0433\u043e\u0440\u044c\u0435"
    ],
    "name:und_x_variant":[
        "Zagor\u2019ye",
        "Bol\u2019shoye Zagor\u2019ye",
        "\u0411\u043e\u043b\u044c\u0448\u043e\u0435 \u0417\u0430\u0433\u043e\u0440\u044c\u0435"
    ],
    "wof:name":"Bol'shoye Zagor'ye",
    "wof:placetype":"locality"
},
  "geometry": {"coordinates":[31.71712,54.97938000000001],"type":"Point"}
}