{
  "type": "Feature",
  "properties": {
    "gn:admin1_code":"52.0",
    "gn:asciiname":"Domashi",
    "gn:country_code":"RU",
    "gn:dem":211,
    "gn:feature_class":"P",
    "gn:feature_code":"PPL",
    "gn:name":"Domashi",
    "gn:population":0,
    "gn:timezone":"Europe/Moscow",
    "iso:country":"RU",
    "name:rus_x_preferred":[
        "\u0414\u043e\u043c\u0430\u0448\u0438"
    ],
    "wof:name":"Domashi",
    "wof:placetype":"locality"
},
  "geometry": {"coordinates":[32.7435,57.7576],"type":"Point"}
}