{
  "type": "Feature",
  "properties": {
    "gn:admin1_code":"40",
    "gn:asciiname":"Bachantseva",
    "gn:country_code":"RU",
    "gn:dem":63,
    "gn:feature_class":"P",
    "gn:feature_code":"PPL",
    "gn:name":"Bachantseva",
    "gn:population":0,
    "gn:timezone":"Asia/Yekaterinburg",
    "iso:country":"RU",
    "name:nor_x_preferred":[
        "Batsjantseva"
    ],
    "name:rus_x_preferred":[
        "\u0411\u0430\u0447\u0430\u043d\u0446\u0435\u0432\u0430"
    ],
    "wof:name":"Bachantseva",
    "wof:placetype":"locality"
},
  "geometry": {"coordinates":[65.60056,55.8375],"type":"Point"}
}