{
  "type": "Feature",
  "properties": {
    "gn:admin1_code":"91",
    "gn:asciiname":"Khabaydak",
    "gn:country_code":"RU",
    "gn:dem":575,
    "gn:feature_class":"P",
    "gn:feature_code":"PPL",
    "gn:name":"Khabaydak",
    "gn:population":0,
    "gn:timezone":"Asia/Krasnoyarsk",
    "iso:country":"RU",
    "name:eng_x_preferred":[
        "Khabaydak"
    ],
    "name:nor_x_preferred":[
        "Khabajdak"
    ],
    "name:rus_x_preferred":[
        "\u0425\u0430\u0431\u0430\u0439\u0434\u0430\u043a"
    ],
    "wof:name":"Khabaydak",
    "wof:placetype":"locality"
},
  "geometry": {"coordinates":[93.989,54.9464],"type":"Point"}
}