{
  "type": "Feature",
  "properties": {
    "gn:admin1_code":"60",
    "gn:asciiname":"Krutsy",
    "gn:country_code":"RU",
    "gn:dem":72,
    "gn:feature_class":"P",
    "gn:feature_code":"PPL",
    "gn:name":"Krutsy",
    "gn:population":0,
    "gn:timezone":"Europe/Moscow",
    "iso:country":"RU",
    "name:rus_x_preferred":[
        "\u041a\u0440\u0443\u0446\u044b"
    ],
    "wof:name":"Krutsy",
    "wof:placetype":"locality"
},
  "geometry": {"coordinates":[28.49044,57.10467],"type":"Point"}
}