{
  "type": "Feature",
  "properties": {
    "gn:admin1_code":"56.0",
    "gn:asciiname":"Berezki",
    "gn:country_code":"RU",
    "gn:dem":189,
    "gn:feature_class":"P",
    "gn:feature_code":"PPL",
    "gn:name":"Ber\u00ebzki",
    "gn:population":0,
    "gn:timezone":"Europe/Moscow",
    "iso:country":"RU",
    "name:nor_x_preferred":[
        "Berjozki"
    ],
    "name:rus_x_preferred":[
        "\u0411\u0435\u0440\u0451\u0437\u043a\u0438"
    ],
    "name:und_x_variant":[
        "Ber\u00ebzki"
    ],
    "wof:name":"Berezki",
    "wof:placetype":"locality"
},
  "geometry": {"coordinates":[37.79747,52.23576],"type":"Point"}
}