{
  "type": "Feature",
  "properties": {
    "gn:admin1_code":"83",
    "gn:asciiname":"Novobusino",
    "gn:country_code":"RU",
    "gn:dem":194,
    "gn:feature_class":"P",
    "gn:feature_code":"PPL",
    "gn:name":"Novobusino",
    "gn:population":0,
    "gn:timezone":"Europe/Moscow",
    "iso:country":"RU",
    "name:eng_x_preferred":[
        "Novobusino"
    ],
    "name:nor_x_preferred":[
        "Novobusino"
    ],
    "name:rus_x_preferred":[
        "\u041d\u043e\u0432\u043e\u0431\u0443\u0441\u0438\u043d\u043e"
    ],
    "name:und_x_variant":[
        "Novoye",
        "Novobusino"
    ],
    "wof:name":"Novobusino",
    "wof:placetype":"locality"
},
  "geometry": {"coordinates":[39.67574000000001,56.28706],"type":"Point"}
}