{
  "type": "Feature",
  "properties": {
    "gn:admin1_code":"16.0",
    "gn:asciiname":"Avyr-Sirmy",
    "gn:country_code":"RU",
    "gn:dem":128,
    "gn:feature_class":"P",
    "gn:feature_code":"PPL",
    "gn:name":"Avyr-Sirmy",
    "gn:population":0,
    "gn:timezone":"Europe/Moscow",
    "iso:country":"RU",
    "name:nor_x_preferred":[
        "Avyr-Sirmy"
    ],
    "name:rus_x_preferred":[
        "\u0410\u0432\u044b\u0440-\u0421\u0438\u0440\u043c\u044b"
    ],
    "name:und_x_variant":[
        "Avyr-Sirma",
        "Avyr-Sirmi"
    ],
    "wof:name":"Avyr-Sirmy",
    "wof:placetype":"locality"
},
  "geometry": {"coordinates":[46.8222,55.66774],"type":"Point"}
}