{
  "type": "Feature",
  "properties": {
    "gn:admin1_code":"8",
    "gn:asciiname":"Kirikeyevo",
    "gn:country_code":"RU",
    "gn:dem":294,
    "gn:feature_class":"P",
    "gn:feature_code":"PPL",
    "gn:name":"Kirikeyevo",
    "gn:population":0,
    "gn:timezone":"Asia/Yekaterinburg",
    "iso:country":"RU",
    "name:eng_x_preferred":[
        "Kirikeyevo"
    ],
    "name:nor_x_preferred":[
        "Kirikejevo"
    ],
    "name:rus_x_preferred":[
        "\u041a\u0438\u0440\u0438\u043a\u0435\u0435\u0432\u043e"
    ],
    "name:und_x_variant":[
        "Kirineyeva",
        "Kirikeyeva",
        "\u041a\u0438\u0440\u0438\u043a\u0435\u0435\u0432\u043e",
        "Kirikeyevo"
    ],
    "wof:name":"Kirikeyevo",
    "wof:placetype":"locality"
},
  "geometry": {"coordinates":[59.23194,56.06778000000001],"type":"Point"}
}