{
  "type": "Feature",
  "properties": {
    "gn:admin1_code":"8",
    "gn:asciiname":"Kirikeyevo",
    "gn:country_code":"RU",
    "gn:dem":294,
    "gn:feature_class":"P",
    "gn:feature_code":"PPL",
    "gn:name":"Kirikeyevo",
    "gn:population":0,
    "gn:timezone":"Asia/Yekaterinburg",
    "iso:country":"RU",
    "name:bak_x_preferred":[
        "\u04a0\u0430\u0440\u0430\u04a1\u0430\u0439"
    ],
    "name:che_x_preferred":[
        "\u041a\u0438\u0440\u0438\u043a\u0435\u0435\u0432\u043e"
    ],
    "name:eng_x_preferred":[
        "Kirikeyevo"
    ],
    "name:hye_x_preferred":[
        "\u053f\u056b\u0580\u056b\u056f\u0565\u0587\u0578"
    ],
    "name:kat_x_preferred":[
        "\u10d9\u10d8\u10e0\u10d8\u10d9\u10d4\u10d4\u10d5\u10dd"
    ],
    "name:kaz_x_preferred":[
        "\u041a\u0438\u0440\u0438\u043a\u0435"
    ],
    "name:kir_x_preferred":[
        "\u041a\u0438\u0440\u0438\u043a\u0435"
    ],
    "name:nor_x_preferred":[
        "Kirikejevo"
    ],
    "name:rus_x_preferred":[
        "\u041a\u0438\u0440\u0438\u043a\u0435\u0435\u0432\u043e"
    ],
    "name:tat_x_preferred":[
        "\u041a\u04d9\u0440\u043a\u04d9\u0439"
    ],
    "name:und_x_variant":[
        "Kirineyeva",
        "Kirikeyeva"
    ],
    "wof:name":"Kirikeyevo",
    "wof:placetype":"locality"
},
  "geometry": {"coordinates":[59.23194,56.06778000000001],"type":"Point"}
}