{
  "type": "Feature",
  "properties": {
    "gn:admin1_code":"88",
    "gn:asciiname":"Osoyevo",
    "gn:country_code":"RU",
    "gn:dem":180,
    "gn:feature_class":"P",
    "gn:feature_code":"PPL",
    "gn:name":"Osoyevo",
    "gn:population":0,
    "gn:timezone":"Europe/Moscow",
    "iso:country":"RU",
    "name:rus_x_preferred":[
        "\u041e\u0441\u043e\u0435\u0432\u043e"
    ],
    "wof:name":"Osoyevo",
    "wof:placetype":"locality"
},
  "geometry": {"coordinates":[39.41355,56.99222],"type":"Point"}
}