{
  "type": "Feature",
  "properties": {
    "gn:admin1_code":"33",
    "gn:asciiname":"Lezhni",
    "gn:country_code":"RU",
    "gn:dem":180,
    "gn:feature_class":"P",
    "gn:feature_code":"PPL",
    "gn:name":"Lezhni",
    "gn:population":0,
    "gn:timezone":"Europe/Kirov",
    "iso:country":"RU",
    "name:rus_x_preferred":[
        "\u041b\u0435\u0436\u043d\u0438"
    ],
    "name:und_x_variant":[
        "\u041b\u0435\u0436\u043d\u0438"
    ],
    "wof:name":"Lezhni",
    "wof:placetype":"locality"
},
  "geometry": {"coordinates":[51.73333,57.93333000000001],"type":"Point"}
}