{
  "type": "Feature",
  "properties": {
    "gn:admin1_code":"54",
    "gn:asciiname":"Khristolyubovka",
    "gn:country_code":"RU",
    "gn:dem":125,
    "gn:feature_class":"P",
    "gn:feature_code":"PPL",
    "gn:name":"Khristolyubovka",
    "gn:population":0,
    "gn:timezone":"Asia/Omsk",
    "iso:country":"RU",
    "name:eng_x_preferred":[
        "Khristolyubovka"
    ],
    "name:nor_x_preferred":[
        "Khristoljubovka"
    ],
    "name:rus_x_preferred":[
        "\u0425\u0440\u0438\u0441\u0442\u043e\u043b\u044e\u0431\u043e\u0432\u043a\u0430"
    ],
    "name:und_x_variant":[
        "\u0425\u0440\u0438\u0441\u0442\u043e\u043b\u044e\u0431\u043e\u0432\u043a\u0430",
        "Khristolyubovka"
    ],
    "wof:name":"Khristolyubovka",
    "wof:placetype":"locality"
},
  "geometry": {"coordinates":[75.60433,56.8074],"type":"Point"}
}