{
  "type": "Feature",
  "properties": {
    "gn:admin1_code":"40",
    "gn:asciiname":"Kopyrino",
    "gn:cc2":"RU",
    "gn:country_code":"RU",
    "gn:dem":136,
    "gn:feature_class":"P",
    "gn:feature_code":"PPL",
    "gn:name":"Kopyrino",
    "gn:population":0,
    "gn:timezone":"Asia/Yekaterinburg",
    "iso:country":"RU",
    "name:rus_x_preferred":[
        "\u041a\u043e\u043f\u044b\u0440\u0438\u043d\u043e"
    ],
    "name:und_x_variant":[
        "Kopyrina",
        "Kopyrino"
    ],
    "wof:name":"Kopyrino",
    "wof:placetype":"locality"
},
  "geometry": {"coordinates":[67.395,55.33583],"type":"Point"}
}