{
  "type": "Feature",
  "properties": {
    "gn:admin1_code":"63",
    "gn:asciiname":"Bedeme",
    "gn:country_code":"RU",
    "gn:dem":142,
    "gn:feature_class":"P",
    "gn:feature_code":"PPL",
    "gn:name":"Bedem\u00eb",
    "gn:population":0,
    "gn:timezone":"Asia/Yakutsk",
    "iso:country":"RU",
    "name:che_x_preferred":[
        "\u0411\u0435\u0434\u0435\u043c\u0451"
    ],
    "name:hye_x_preferred":[
        "\u0532\u0565\u0564\u0565\u0574\u0575\u0578"
    ],
    "name:nor_x_preferred":[
        "Bedemjo"
    ],
    "name:rus_x_preferred":[
        "\u0411\u0435\u0434\u0435\u043c\u0451"
    ],
    "name:sah_x_preferred":[
        "\u0411\u044d\u0434\u044c\u0438\u043c\u044d"
    ],
    "name:und_x_variant":[
        "Bedzhime",
        "Bedem\u00eb"
    ],
    "wof:name":"Bedeme",
    "wof:placetype":"locality"
},
  "geometry": {"coordinates":[130.54374999999999,62.00585],"type":"Point"}
}