{
  "type": "Feature",
  "properties": {
    "gn:admin1_code":"72",
    "gn:asciiname":"Surava",
    "gn:country_code":"RU",
    "gn:dem":156,
    "gn:feature_class":"P",
    "gn:feature_code":"PPL",
    "gn:name":"Surava",
    "gn:population":0,
    "gn:timezone":"Europe/Moscow",
    "iso:country":"RU",
    "name:cat_x_preferred":[
        "Surava"
    ],
    "name:ceb_x_preferred":[
        "Surava"
    ],
    "name:deu_x_preferred":[
        "Surava"
    ],
    "name:eng_x_preferred":[
        "Surava"
    ],
    "name:epo_x_preferred":[
        "Surava"
    ],
    "name:fra_x_preferred":[
        "Surava"
    ],
    "name:ita_x_preferred":[
        "Surava"
    ],
    "name:lmo_x_preferred":[
        "Surava"
    ],
    "name:msa_x_preferred":[
        "Surava"
    ],
    "name:nld_x_preferred":[
        "Surava"
    ],
    "name:nno_x_preferred":[
        "Surava"
    ],
    "name:nor_x_preferred":[
        "Surava"
    ],
    "name:pms_x_preferred":[
        "Surava"
    ],
    "name:por_x_preferred":[
        "Surava"
    ],
    "name:roh_x_preferred":[
        "Surava"
    ],
    "name:rus_x_preferred":[
        "\u0421\u0443\u0440\u0430\u0432\u0430"
    ],
    "name:spa_x_preferred":[
        "Surava"
    ],
    "name:sqi_x_preferred":[
        "Surava"
    ],
    "name:swe_x_preferred":[
        "Surava"
    ],
    "name:uzb_x_preferred":[
        "Surava"
    ],
    "name:vol_x_preferred":[
        "Surava"
    ],
    "name:war_x_preferred":[
        "Surava"
    ],
    "name:zho_x_preferred":[
        "\u8607\u62c9\u74e6"
    ],
    "wof:name":"Surava",
    "wof:placetype":"locality"
},
  "geometry": {"coordinates":[41.27215,52.93739],"type":"Point"}
}