{
  "type": "Feature",
  "properties": {
    "gn:admin1_code":"72",
    "gn:asciiname":"Surava",
    "gn:country_code":"RU",
    "gn:dem":156,
    "gn:feature_class":"P",
    "gn:feature_code":"PPL",
    "gn:name":"Surava",
    "gn:population":0,
    "gn:timezone":"Europe/Moscow",
    "iso:country":"RU",
    "name:eng_x_preferred":[
        "Surava"
    ],
    "name:nor_x_preferred":[
        "Surava"
    ],
    "name:rus_x_preferred":[
        "\u0421\u0443\u0440\u0430\u0432\u0430"
    ],
    "wof:name":"Surava",
    "wof:placetype":"locality"
},
  "geometry": {"coordinates":[41.27215,52.93739],"type":"Point"}
}