{
  "type": "Feature",
  "properties": {
    "gn:admin1_code":"42.0",
    "gn:admin2_code":"575409",
    "gn:asciiname":"Finikovo",
    "gn:cc2":"RU",
    "gn:country_code":"RU",
    "gn:dem":137,
    "gn:feature_class":"P",
    "gn:feature_code":"PPL",
    "gn:name":"Finikovo",
    "gn:population":0,
    "gn:timezone":"Europe/Moscow",
    "iso:country":"RU",
    "name:rus_x_preferred":[
        "\u0424\u0438\u043d\u0438\u043a\u043e\u0432\u043e"
    ],
    "name:und_x_variant":[
        "Fenikovo",
        "Finikovo"
    ],
    "wof:name":"Finikovo",
    "wof:placetype":"locality"
},
  "geometry": {"coordinates":[34.31194,59.60972],"type":"Point"}
}