{
  "type": "Feature",
  "properties": {
    "gn:admin1_code":"52",
    "gn:asciiname":"Krupichino",
    "gn:country_code":"RU",
    "gn:dem":16,
    "gn:feature_class":"P",
    "gn:feature_code":"PPL",
    "gn:name":"Krupichino",
    "gn:population":0,
    "gn:timezone":"Europe/Moscow",
    "iso:country":"RU",
    "name:rus_x_preferred":[
        "\u041a\u0440\u0443\u043f\u0438\u0447\u0438\u043d\u043e"
    ],
    "wof:name":"Krupichino",
    "wof:placetype":"locality"
},
  "geometry": {"coordinates":[31.75,58.98333],"type":"Point"}
}