{
  "type": "Feature",
  "properties": {
    "gn:admin1_code":"52",
    "gn:asciiname":"Andrekhnovo",
    "gn:country_code":"RU",
    "gn:dem":250,
    "gn:feature_class":"P",
    "gn:feature_code":"PPL",
    "gn:name":"Andrekhnovo",
    "gn:population":0,
    "gn:timezone":"Europe/Moscow",
    "iso:country":"RU",
    "name:rus_x_preferred":[
        "\u0410\u043d\u0434\u0440\u0435\u0445\u043d\u043e\u0432\u043e"
    ],
    "wof:name":"Andrekhnovo",
    "wof:placetype":"locality"
},
  "geometry": {"coordinates":[32.83947,57.51036],"type":"Point"}
}