{
  "type": "Feature",
  "properties": {
    "gn:country":"RU",
    "gn:fcode":"PPL",
    "gn:pop":3179,
    "iso:country":"RU",
    "name:ara_x_preferred":[
        "\u0623\u0643\u0633\u0627\u0643\u0648\u0641\u0648"
    ],
    "name:azb_x_preferred":[
        "\u0627\u06a9\u0633\u0627\u06a9\u0648\u0648"
    ],
    "name:bul_x_preferred":[
        "\u0410\u043a\u0441\u0430\u043a\u043e\u0432\u043e"
    ],
    "name:ceb_x_preferred":[
        "Obshtina Aksakovo"
    ],
    "name:ckb_x_preferred":[
        "\u0626\u0627\u06a9\u0633\u0627\u06a9\u06c6\u06a4\u06c6"
    ],
    "name:deu_x_preferred":[
        "Aksakowo"
    ],
    "name:eng_x_preferred":[
        "Aksakovo"
    ],
    "name:fas_x_preferred":[
        "\u0622\u06a9\u0633\u0627\u06a9\u0648\u0648\u0648"
    ],
    "name:fra_x_preferred":[
        "Aksakovo"
    ],
    "name:jpn_x_preferred":[
        "\u30a2\u30af\u30b5\u30b3\u30f4\u30a9"
    ],
    "name:kaz_x_preferred":[
        "\u0410\u043a\u0441\u0430\u043a\u043e\u0432\u043e"
    ],
    "name:nld_x_preferred":[
        "Aksakovo"
    ],
    "name:pol_x_preferred":[
        "Aksakowo"
    ],
    "name:por_x_preferred":[
        "Aksakovo"
    ],
    "name:ron_x_preferred":[
        "Aksakovo"
    ],
    "name:rus_x_preferred":[
        "\u0410\u043a\u0441\u0430\u043a\u043e\u0432\u043e"
    ],
    "name:spa_x_preferred":[
        "Aksakovo"
    ],
    "name:srp_x_preferred":[
        "\u0410\u043a\u0441\u0430\u043a\u043e\u0432\u043e"
    ],
    "name:swe_x_preferred":[
        "Obsjtina Aksakovo"
    ],
    "name:tur_x_preferred":[
        "Acemler"
    ],
    "name:ukr_x_preferred":[
        "\u0410\u043a\u0441\u0430\u043a\u043e\u0432\u043e"
    ],
    "name:vie_x_preferred":[
        "Aksakovo"
    ],
    "name:war_x_preferred":[
        "Aksakovo"
    ],
    "name:zho_x_preferred":[
        "\u963f\u514b\u85a9\u79d1\u6c83"
    ],
    "qs:name":"Aksakovo",
    "qs:photos_9r":0,
    "qs:photos_sr":0,
    "qs:pop_sr":"4",
    "wd:elevation":99.0,
    "wd:wordcount":107,
    "wof:name":"Aksakovo",
    "wof:placetype":"locality",
    "wof:population":3179
},
  "geometry": {"coordinates":[54.15,54.03333],"type":"Point"}
}