{
  "type": "Feature",
  "properties": {
    "gn:country":"RU",
    "gn:fcode":"PPL",
    "gn:pop":3179,
    "iso:country":"RU",
    "name:eng_x_preferred":[
        "Aksakovo"
    ],
    "name:rus_x_preferred":[
        "\u0410\u043a\u0441\u0430\u043a\u043e\u0432\u043e"
    ],
    "qs:name":"Aksakovo",
    "qs:photos_9r":0,
    "qs:photos_sr":0,
    "qs:pop_sr":"4",
    "wd:elevation":99.0,
    "wd:wordcount":107,
    "wof:name":"Aksakovo",
    "wof:placetype":"locality",
    "wof:population":3179
},
  "geometry": {"coordinates":[54.15,54.03333],"type":"Point"}
}