{
  "type": "Feature",
  "properties": {
    "gn:admin1_code":"80",
    "gn:asciiname":"Yefremovo",
    "gn:country_code":"RU",
    "gn:dem":239,
    "gn:feature_class":"P",
    "gn:feature_code":"PPL",
    "gn:name":"Yefremovo",
    "gn:population":0,
    "gn:timezone":"Europe/Samara",
    "iso:country":"RU",
    "name:rus_x_preferred":[
        "\u0415\u0444\u0440\u0435\u043c\u043e\u0432\u043e"
    ],
    "wof:name":"Yefremovo",
    "wof:placetype":"locality"
},
  "geometry": {"coordinates":[53.9027,58.0201],"type":"Point"}
}