{
  "type": "Feature",
  "properties": {
    "gn:admin1_code":"37",
    "gn:asciiname":"Smorodintsy",
    "gn:cc2":"RU",
    "gn:country_code":"RU",
    "gn:dem":154,
    "gn:feature_class":"P",
    "gn:feature_code":"PPL",
    "gn:name":"Smorodintsy",
    "gn:population":0,
    "gn:timezone":"Europe/Moscow",
    "iso:country":"RU",
    "name:rus_x_preferred":[
        "\u0421\u043c\u043e\u0440\u043e\u0434\u0438\u043d\u0446\u044b"
    ],
    "name:und_x_variant":[
        "Vshivtsevo",
        "Smorodintsy",
        "\u0421\u043c\u043e\u0440\u043e\u0434\u0438\u043d\u0446\u044b"
    ],
    "wof:name":"Smorodintsy",
    "wof:placetype":"locality"
},
  "geometry": {"coordinates":[45.71667,58.88333000000001],"type":"Point"}
}