{
  "type": "Feature",
  "properties": {
    "gn:admin1_code":"77",
    "gn:asciiname":"Mereykino",
    "gn:country_code":"RU",
    "gn:dem":189,
    "gn:feature_class":"P",
    "gn:feature_code":"PPL",
    "gn:name":"Mereykino",
    "gn:population":0,
    "gn:timezone":"Europe/Moscow",
    "iso:country":"RU",
    "name:nor_x_preferred":[
        "Merejkino"
    ],
    "name:rus_x_preferred":[
        "\u041c\u0435\u0440\u0435\u0439\u043a\u0438\u043d\u043e"
    ],
    "name:und_x_variant":[
        "Mireykino",
        "Mereykino"
    ],
    "wof:name":"Mereykino",
    "wof:placetype":"locality"
},
  "geometry": {"coordinates":[35.27658,56.18434],"type":"Point"}
}