{
  "type": "Feature",
  "properties": {
    "gn:admin1_code":"69",
    "gn:asciiname":"Zlatoustovo",
    "gn:country_code":"RU",
    "gn:dem":183,
    "gn:feature_class":"P",
    "gn:feature_code":"PPL",
    "gn:name":"Zlatoustovo",
    "gn:population":0,
    "gn:timezone":"Europe/Moscow",
    "iso:country":"RU",
    "name:bul_x_preferred":[
        "\u0417\u043b\u0430\u0442\u043e\u0443\u0441\u0442\u043e\u0432\u043e"
    ],
    "name:eng_x_preferred":[
        "Zlatoustovo"
    ],
    "name:fas_x_preferred":[
        "\u0632\u0644\u0627\u062a\u0648\u0633\u062a\u0648\u0648\u0648"
    ],
    "name:kaz_x_preferred":[
        "\u0417\u043b\u0430\u0442\u043e\u0443\u0441\u0442\u043e\u0432\u043e"
    ],
    "name:nor_x_preferred":[
        "Zlatousovo"
    ],
    "name:pol_x_preferred":[
        "Z\u0142atoustowo"
    ],
    "name:ron_x_preferred":[
        "Zlatoustovo"
    ],
    "name:rus_x_preferred":[
        "\u0417\u043b\u0430\u0442\u043e\u0443\u0441\u043e\u0432\u043e"
    ],
    "name:rus_x_variant":[
        "\u0417\u043b\u0430\u0442\u043e\u0443\u0441\u0442\u043e\u0432\u043e"
    ],
    "name:ukr_x_preferred":[
        "\u0417\u043b\u0430\u0442\u043e\u0443\u0441\u0442\u043e\u0432\u043e"
    ],
    "wof:name":"Zlatoustovo",
    "wof:placetype":"locality"
},
  "geometry": {"coordinates":[34.81697,55.71995],"type":"Point"}
}