{
  "type": "Feature",
  "properties": {
    "gn:admin1_code":"69",
    "gn:asciiname":"Zlatoustovo",
    "gn:country_code":"RU",
    "gn:dem":183,
    "gn:feature_class":"P",
    "gn:feature_code":"PPL",
    "gn:name":"Zlatoustovo",
    "gn:population":0,
    "gn:timezone":"Europe/Moscow",
    "iso:country":"RU",
    "name:eng_x_preferred":[
        "Zlatoustovo"
    ],
    "name:nor_x_preferred":[
        "Zlatousovo"
    ],
    "name:rus_x_preferred":[
        "\u0417\u043b\u0430\u0442\u043e\u0443\u0441\u043e\u0432\u043e"
    ],
    "wof:name":"Zlatoustovo",
    "wof:placetype":"locality"
},
  "geometry": {"coordinates":[34.81697,55.71995],"type":"Point"}
}