{
  "type": "Feature",
  "properties": {
    "gn:admin1_code":"45",
    "gn:asciiname":"Iletnur",
    "gn:country_code":"RU",
    "gn:dem":112,
    "gn:feature_class":"P",
    "gn:feature_code":"PPL",
    "gn:name":"Iletnur",
    "gn:population":0,
    "gn:timezone":"Europe/Moscow",
    "iso:country":"RU",
    "name:rus_x_preferred":[
        "\u0418\u043b\u0435\u0442\u043d\u0443\u0440"
    ],
    "wof:name":"Iletnur",
    "wof:placetype":"locality"
},
  "geometry": {"coordinates":[49.405,56.57056],"type":"Point"}
}