{
  "type": "Feature",
  "properties": {
    "gn:admin1_code":"75",
    "gn:asciiname":"Sosnina",
    "gn:country_code":"RU",
    "gn:dem":13,
    "gn:feature_class":"P",
    "gn:feature_code":"PPL",
    "gn:name":"Sosnina",
    "gn:population":0,
    "gn:timezone":"Asia/Tomsk",
    "iso:country":"RU",
    "name:und_x_variant":[
        "\u0421\u043e\u0441\u043d\u0438\u043d\u0430"
    ],
    "wof:name":"Sosnina",
    "wof:placetype":"locality"
},
  "geometry": {"coordinates":[77.05278,60.71417],"type":"Point"}
}