{
  "type": "Feature",
  "properties": {
    "gn:admin1_code":"56",
    "gn:asciiname":"Khitrovka",
    "gn:country_code":"RU",
    "gn:dem":231,
    "gn:feature_class":"P",
    "gn:feature_code":"PPL",
    "gn:name":"Khitrovka",
    "gn:population":0,
    "gn:timezone":"Europe/Moscow",
    "iso:country":"RU",
    "name:ces_x_preferred":[
        "Chitrovka"
    ],
    "name:deu_x_preferred":[
        "Chitrowka"
    ],
    "name:fra_x_preferred":[
        "Khitrovka"
    ],
    "name:rus_x_preferred":[
        "\u0425\u0438\u0442\u0440\u043e\u0432\u043a\u0430"
    ],
    "name:rus_x_variant":[
        "\u0425\u0438\u0442\u0440\u043e\u0432\u0441\u043a\u0430\u044f \u043f\u043b\u043e\u0449\u0430\u0434\u044c"
    ],
    "name:und_x_variant":[
        "\u0425\u0438\u0442\u0440\u043e\u0432\u043a\u0430"
    ],
    "wof:name":"Khitrovka",
    "wof:placetype":"locality"
},
  "geometry": {"coordinates":[35.6318,52.4377],"type":"Point"}
}