{
  "type": "Feature",
  "properties": {
    "gn:admin1_code":"53",
    "gn:asciiname":"Lezhnevskiy",
    "gn:cc2":"RU",
    "gn:country_code":"RU",
    "gn:dem":142,
    "gn:feature_class":"P",
    "gn:feature_code":"PPL",
    "gn:name":"Lezhnevskiy",
    "gn:population":0,
    "gn:timezone":"Asia/Novosibirsk",
    "iso:country":"RU",
    "name:eng_x_preferred":[
        "Lezhnevskiy"
    ],
    "name:nor_x_preferred":[
        "Lezjnevskij"
    ],
    "name:rus_x_preferred":[
        "\u041b\u0435\u0436\u043d\u0435\u0432\u0441\u043a\u0438\u0439"
    ],
    "name:und_x_variant":[
        "Lezhn\u00ebvo",
        "\u041b\u0435\u0436\u043d\u0435\u0432\u0441\u043a\u0438\u0439",
        "Lezhnevskiy"
    ],
    "wof:name":"Lezhnevskiy",
    "wof:placetype":"locality"
},
  "geometry": {"coordinates":[80.64278,55.06721999999999],"type":"Point"}
}