{
  "type": "Feature",
  "properties": {
    "gn:admin1_code":"69",
    "gn:asciiname":"Shapurovka",
    "gn:country_code":"RU",
    "gn:dem":205,
    "gn:feature_class":"P",
    "gn:feature_code":"PPL",
    "gn:name":"Shapurovka",
    "gn:population":0,
    "gn:timezone":"Europe/Moscow",
    "iso:country":"RU",
    "name:rus_x_preferred":[
        "\u0428\u0430\u043f\u0443\u0440\u043e\u0432\u043a\u0430"
    ],
    "wof:name":"Shapurovka",
    "wof:placetype":"locality"
},
  "geometry": {"coordinates":[32.08639,54.32806],"type":"Point"}
}