{
  "type": "Feature",
  "properties": {
    "gn:admin1_code":"91.0",
    "gn:asciiname":"Angaloy",
    "gn:country_code":"RU",
    "gn:dem":299,
    "gn:feature_class":"P",
    "gn:feature_code":"PPL",
    "gn:name":"Angaloy",
    "gn:population":0,
    "gn:timezone":"Asia/Krasnoyarsk",
    "iso:country":"RU",
    "name:rus_x_preferred":[
        "\u0410\u043d\u0433\u0430\u043b\u043e\u0439"
    ],
    "wof:name":"Angaloy",
    "wof:placetype":"locality"
},
  "geometry": {"coordinates":[93.15000000000001,55.4995],"type":"Point"}
}