{
  "type": "Feature",
  "properties": {
    "gn:admin1_code":"60",
    "gn:asciiname":"Glazanovo",
    "gn:country_code":"RU",
    "gn:dem":106,
    "gn:feature_class":"P",
    "gn:feature_code":"PPL",
    "gn:name":"Glazanovo",
    "gn:population":0,
    "gn:timezone":"Europe/Moscow",
    "iso:country":"RU",
    "name:rus_x_preferred":[
        "\u0413\u043b\u0430\u0437\u0430\u043d\u043e\u0432\u043e"
    ],
    "wof:name":"Glazanovo",
    "wof:placetype":"locality"
},
  "geometry": {"coordinates":[28.68229,56.81437],"type":"Point"}
}