{
  "type": "Feature",
  "properties": {
    "gn:admin1_code":"3.0",
    "gn:asciiname":"Maralovodka",
    "gn:country_code":"RU",
    "gn:dem":1032,
    "gn:feature_class":"P",
    "gn:feature_code":"PPL",
    "gn:name":"Maralovodka",
    "gn:population":0,
    "gn:timezone":"Asia/Omsk",
    "iso:country":"RU",
    "name:rus_x_preferred":[
        "\u041c\u0430\u0440\u0430\u043b\u043e\u0432\u043e\u0434\u043a\u0430"
    ],
    "wof:name":"Maralovodka",
    "wof:placetype":"locality"
},
  "geometry": {"coordinates":[85.4632,50.1185],"type":"Point"}
}