{
  "type": "Feature",
  "properties": {
    "gn:admin1_code":"72",
    "gn:asciiname":"Vtoraya Likharevka",
    "gn:country_code":"RU",
    "gn:dem":172,
    "gn:feature_class":"P",
    "gn:feature_code":"PPL",
    "gn:name":"Vtoraya Likhar\u00ebvka",
    "gn:population":0,
    "gn:timezone":"Europe/Moscow",
    "iso:country":"RU",
    "wof:name":"Vtoraya Likharevka",
    "wof:placetype":"locality"
},
  "geometry": {"coordinates":[41.95831,51.70496],"type":"Point"}
}