{
  "type": "Feature",
  "properties": {
    "gn:admin1_code":"37",
    "gn:asciiname":"Gorbachevo",
    "gn:country_code":"RU",
    "gn:dem":173,
    "gn:feature_class":"P",
    "gn:feature_code":"PPL",
    "gn:name":"Gorbachevo",
    "gn:population":0,
    "gn:timezone":"Europe/Moscow",
    "iso:country":"RU",
    "name:eng_x_preferred":[
        "Gorbachevo"
    ],
    "name:nor_x_preferred":[
        "Gorbatsjevo"
    ],
    "name:rus_x_preferred":[
        "\u0413\u043e\u0440\u0431\u0430\u0447\u0435\u0432\u043e"
    ],
    "name:und_x_variant":[
        "\u0413\u043e\u0440\u0431\u0430\u0447\u0435\u0432\u043e",
        "Gorbachevo"
    ],
    "wof:name":"Gorbachevo",
    "wof:placetype":"locality"
},
  "geometry": {"coordinates":[42.65658,59.09179],"type":"Point"}
}