{
  "type": "Feature",
  "properties": {
    "gn:admin1_code":"61",
    "gn:asciiname":"Kikidzi",
    "gn:country_code":"RU",
    "gn:dem":105,
    "gn:feature_class":"P",
    "gn:feature_code":"PPL",
    "gn:name":"Kikidzi",
    "gn:population":0,
    "gn:timezone":"Europe/Moscow",
    "iso:country":"RU",
    "name:rus_x_preferred":[
        "\u041a\u0438\u043a\u0438\u0434\u0437\u0438"
    ],
    "wof:name":"Kikidzi",
    "wof:placetype":"locality"
},
  "geometry": {"coordinates":[40.80877,49.31309],"type":"Point"}
}