{
  "type": "Feature",
  "properties": {
    "gn:admin1_code":"69",
    "gn:asciiname":"Konets",
    "gn:country_code":"RU",
    "gn:dem":203,
    "gn:feature_class":"P",
    "gn:feature_code":"PPL",
    "gn:name":"Konets",
    "gn:population":0,
    "gn:timezone":"Europe/Moscow",
    "iso:country":"RU",
    "name:rus_x_preferred":[
        "\u041a\u043e\u043d\u0435\u0446"
    ],
    "name:und_x_variant":[
        "\u041a\u043e\u043d\u0435\u0446"
    ],
    "wof:name":"Konets",
    "wof:placetype":"locality"
},
  "geometry": {"coordinates":[32.09361,55.62694000000001],"type":"Point"}
}