{
  "type": "Feature",
  "properties": {
    "gn:admin1_code":"8",
    "gn:asciiname":"Tarasovka",
    "gn:country_code":"RU",
    "gn:dem":131,
    "gn:feature_class":"P",
    "gn:feature_code":"PPL",
    "gn:name":"Tarasovka",
    "gn:population":0,
    "gn:timezone":"Asia/Yekaterinburg",
    "iso:country":"RU",
    "name:bak_x_preferred":[
        "\u0422\u0430\u0440\u0430\u0441\u043e\u0432\u043a\u0430"
    ],
    "name:che_x_preferred":[
        "\u0422\u0430\u0440\u0430\u0441\u043e\u0432\u043a\u0430"
    ],
    "name:hye_x_preferred":[
        "\u054f\u0561\u0580\u0561\u057d\u0578\u057e\u056f\u0561"
    ],
    "name:kaz_x_preferred":[
        "\u0422\u0430\u0440\u0430\u0441\u043e\u0432\u043a\u0430"
    ],
    "name:kir_x_preferred":[
        "\u0422\u0430\u0440\u0430\u0441\u043e\u0432\u043a\u0430"
    ],
    "name:rus_x_preferred":[
        "\u0422\u0430\u0440\u0430\u0441\u043e\u0432\u043a\u0430"
    ],
    "name:tat_x_preferred":[
        "\u0422\u0430\u0440\u0430\u0441\u043e\u0432\u043a\u0430"
    ],
    "wof:name":"Tarasovka",
    "wof:placetype":"locality"
},
  "geometry": {"coordinates":[54.87017,55.61922],"type":"Point"}
}