{
  "type": "Feature",
  "properties": {
    "gn:admin1_code":"5",
    "gn:asciiname":"Vinogradovka",
    "gn:country_code":"RU",
    "gn:dem":178,
    "gn:feature_class":"P",
    "gn:feature_code":"PPL",
    "gn:name":"Vinogradovka",
    "gn:population":0,
    "gn:timezone":"Asia/Yakutsk",
    "iso:country":"RU",
    "name:eng_x_preferred":[
        "Vinogradovka"
    ],
    "name:nor_x_preferred":[
        "Vinogradovka"
    ],
    "name:rus_x_preferred":[
        "\u0412\u0438\u043d\u043e\u0433\u0440\u0430\u0434\u043e\u0432\u043a\u0430"
    ],
    "wof:name":"Vinogradovka",
    "wof:placetype":"locality"
},
  "geometry": {"coordinates":[129.40825000000001,49.6643],"type":"Point"}
}