{
  "type": "Feature",
  "properties": {
    "gn:admin1_code":"28",
    "gn:asciiname":"Ninisel'ga",
    "gn:country_code":"RU",
    "gn:dem":155,
    "gn:feature_class":"P",
    "gn:feature_code":"PPL",
    "gn:name":"Ninisel\u2019ga",
    "gn:population":0,
    "gn:timezone":"Europe/Moscow",
    "iso:country":"RU",
    "name:fin_x_preferred":[
        "Niiniselk\u00e4"
    ],
    "name:rus_x_preferred":[
        "\u041d\u0438\u043d\u0438\u0441\u0435\u043b\u044c\u0433\u0430"
    ],
    "name:und_x_variant":[
        "Ninisel\u2019ga",
        "\u041d\u0438\u043d\u0438\u0441\u0435\u043b\u044c\u0433\u0430"
    ],
    "wof:name":"Ninisel'ga",
    "wof:placetype":"locality"
},
  "geometry": {"coordinates":[32.89155,61.94419],"type":"Point"}
}