{
  "type": "Feature",
  "properties": {
    "gn:admin1_code":"85",
    "gn:asciiname":"Klemenovo",
    "gn:country_code":"RU",
    "gn:dem":131,
    "gn:feature_class":"P",
    "gn:feature_code":"PPL",
    "gn:name":"Klem\u00ebnovo",
    "gn:population":0,
    "gn:timezone":"Europe/Moscow",
    "iso:country":"RU",
    "name:eng_x_preferred":[
        "Klem\u00ebnovo"
    ],
    "name:nor_x_preferred":[
        "Klemenevo"
    ],
    "name:rus_x_preferred":[
        "\u041a\u043b\u0435\u043c\u0435\u043d\u0435\u0432\u043e"
    ],
    "name:rus_x_variant":[
        "\u041a\u043b\u0435\u043c\u0451\u043d\u043e\u0432\u043e"
    ],
    "name:und_x_variant":[
        "Klem\u00ebnovo",
        "\u041a\u043b\u0435\u043c\u0451\u043d\u043e\u0432\u043e"
    ],
    "wof:name":"Klemenovo",
    "wof:placetype":"locality"
},
  "geometry": {"coordinates":[38.9721,60.0185],"type":"Point"}
}