{
  "type": "Feature",
  "properties": {
    "gn:admin1_code":"60",
    "gn:asciiname":"Kokarevo",
    "gn:country_code":"RU",
    "gn:dem":151,
    "gn:feature_class":"P",
    "gn:feature_code":"PPL",
    "gn:name":"Kokarevo",
    "gn:population":0,
    "gn:timezone":"Europe/Moscow",
    "iso:country":"RU",
    "name:rus_x_preferred":[
        "\u041a\u043e\u043aa\u0440\u0435\u0432\u043e"
    ],
    "name:und_x_variant":[
        "Kokorevo",
        "Kokarevo"
    ],
    "wof:name":"Kokarevo",
    "wof:placetype":"locality"
},
  "geometry": {"coordinates":[30.08969,56.05713000000001],"type":"Point"}
}