{
  "type": "Feature",
  "properties": {
    "gn:admin1_code":"32",
    "gn:asciiname":"Malyye Shogany",
    "gn:cc2":"RU",
    "gn:country_code":"RU",
    "gn:dem":32,
    "gn:feature_class":"P",
    "gn:feature_code":"PPL",
    "gn:name":"Malyye Shogany",
    "gn:population":0,
    "gn:timezone":"Asia/Yekaterinburg",
    "iso:country":"RU",
    "name:eng_x_preferred":[
        "Malyye Shogany"
    ],
    "name:nor_x_preferred":[
        "Mal.Sjogany"
    ],
    "name:rus_x_preferred":[
        "\u041c\u0430\u043b.\u0428\u043e\u0433\u0430\u043d\u044b"
    ],
    "name:rus_x_variant":[
        "\u041c\u0430\u043b\u044b\u0435 \u0428\u043e\u0433\u0430\u043d\u044b"
    ],
    "name:und_x_variant":[
        "Malyye Shagany"
    ],
    "wof:name":"Malyye Shogany",
    "wof:placetype":"locality"
},
  "geometry": {"coordinates":[63.88333000000001,64.03333000000001],"type":"Point"}
}