{
  "type": "Feature",
  "properties": {
    "gn:admin1_code":"81",
    "gn:asciiname":"Kirzyat'",
    "gn:country_code":"RU",
    "gn:dem":103,
    "gn:feature_class":"P",
    "gn:feature_code":"PPL",
    "gn:name":"Kirzyat\u2019",
    "gn:population":0,
    "gn:timezone":"Europe/Ulyanovsk",
    "iso:country":"RU",
    "name:eng_x_preferred":[
        "Kirzyat'"
    ],
    "name:nor_x_preferred":[
        "Kirziat"
    ],
    "name:rus_x_preferred":[
        "\u041a\u0438\u0440\u0437\u044f\u0442\u044c"
    ],
    "name:und_x_variant":[
        "\u041a\u0438\u0440\u0437\u044f\u0442\u044c",
        "Kirzyat\u2019"
    ],
    "wof:name":"Kirzyat'",
    "wof:placetype":"locality"
},
  "geometry": {"coordinates":[46.7063,54.4037],"type":"Point"}
}