{
  "type": "Feature",
  "properties": {
    "gn:admin1_code":"33",
    "gn:asciiname":"Koty",
    "gn:country_code":"RU",
    "gn:dem":187,
    "gn:feature_class":"P",
    "gn:feature_code":"PPL",
    "gn:name":"Koty",
    "gn:population":0,
    "gn:timezone":"Europe/Kirov",
    "iso:country":"RU",
    "name:bel_x_preferred":[
        "\u041a\u0430\u0442\u044b"
    ],
    "name:pol_x_preferred":[
        "Koty"
    ],
    "name:rus_x_preferred":[
        "\u041a\u043e\u0442\u044b"
    ],
    "name:ukr_x_preferred":[
        "\u041a\u043e\u0442\u0438"
    ],
    "name:und_x_variant":[
        "\u041a\u043e\u0442\u044b"
    ],
    "wof:name":"Koty",
    "wof:placetype":"locality"
},
  "geometry": {"coordinates":[50.75,58.63333000000001],"type":"Point"}
}