{
  "type": "Feature",
  "properties": {
    "gn:admin1_code":"88",
    "gn:asciiname":"Zhavoronkovo",
    "gn:country_code":"RU",
    "gn:dem":116,
    "gn:feature_class":"P",
    "gn:feature_code":"PPL",
    "gn:name":"Zhavoronkovo",
    "gn:population":0,
    "gn:timezone":"Europe/Moscow",
    "iso:country":"RU",
    "name:rus_x_preferred":[
        "\u0416\u0430\u0432\u043e\u0440\u043e\u043d\u043a\u043e\u0432\u043e"
    ],
    "wof:name":"Zhavoronkovo",
    "wof:placetype":"locality"
},
  "geometry": {"coordinates":[39.80327,57.83272],"type":"Point"}
}