{
  "type": "Feature",
  "properties": {
    "gn:admin1_code":"83",
    "gn:asciiname":"Mashki",
    "gn:country_code":"RU",
    "gn:dem":106,
    "gn:feature_class":"P",
    "gn:feature_code":"PPL",
    "gn:name":"Mashki",
    "gn:population":0,
    "gn:timezone":"Europe/Moscow",
    "iso:country":"RU",
    "name:rus_x_preferred":[
        "\u041c\u0430\u0448\u043a\u0438"
    ],
    "wof:name":"Mashki",
    "wof:placetype":"locality"
},
  "geometry": {"coordinates":[40.9481,56.3935],"type":"Point"}
}