{
  "type": "Feature",
  "properties": {
    "gn:admin1_code":"56",
    "gn:asciiname":"Lisiy",
    "gn:country_code":"RU",
    "gn:dem":227,
    "gn:feature_class":"P",
    "gn:feature_code":"PPL",
    "gn:name":"Lisiy",
    "gn:population":0,
    "gn:timezone":"Europe/Moscow",
    "iso:country":"RU",
    "name:rus_x_preferred":[
        "\u041b\u0438\u0441\u0438\u0439"
    ],
    "name:und_x_variant":[
        "\u041b\u0438\u0441\u0438\u0439"
    ],
    "wof:name":"Lisiy",
    "wof:placetype":"locality"
},
  "geometry": {"coordinates":[36.4137,52.5177],"type":"Point"}
}