{
  "type": "Feature",
  "properties": {
    "gn:admin1_code":"93",
    "gn:asciiname":"Gulinga",
    "gn:country_code":"RU",
    "gn:dem":1241,
    "gn:feature_class":"P",
    "gn:feature_code":"PPL",
    "gn:name":"Gulinga",
    "gn:population":0,
    "gn:timezone":"Asia/Chita",
    "iso:country":"RU",
    "name:rus_x_preferred":[
        "\u0413\u0443\u043b\u0438\u043d\u0433\u0430"
    ],
    "name:und_x_variant":[
        "\u0413\u0443\u043b\u0438\u043d\u0433\u0430"
    ],
    "wof:name":"Gulinga",
    "wof:placetype":"locality"
},
  "geometry": {"coordinates":[116.84999999999999,55.75],"type":"Point"}
}