{
  "type": "Feature",
  "properties": {
    "gn:admin1_code":"8",
    "gn:asciiname":"Sarty",
    "gn:country_code":"RU",
    "gn:dem":218,
    "gn:feature_class":"P",
    "gn:feature_code":"PPL",
    "gn:name":"Sarty",
    "gn:population":0,
    "gn:timezone":"Asia/Yekaterinburg",
    "iso:country":"RU",
    "name:rus_x_preferred":[
        "\u0421\u0430\u0440\u0442\u044b"
    ],
    "wof:name":"Sarty",
    "wof:placetype":"locality"
},
  "geometry": {"coordinates":[58.25194000000001,55.54917],"type":"Point"}
}