{
  "type": "Feature",
  "properties": {
    "gn:admin1_code":"65",
    "gn:asciiname":"Salamasy",
    "gn:country_code":"RU",
    "gn:dem":65,
    "gn:feature_class":"P",
    "gn:feature_code":"PPL",
    "gn:name":"Salamasy",
    "gn:population":0,
    "gn:timezone":"Europe/Samara",
    "iso:country":"RU",
    "name:rus_x_preferred":[
        "\u0421\u0430\u043b\u0430\u043c\u0430\u0441\u044b"
    ],
    "name:und_x_variant":[
        "\u0421\u0430\u043b\u0430\u043c\u0430\u0441\u044b"
    ],
    "wof:name":"Salamasy",
    "wof:placetype":"locality"
},
  "geometry": {"coordinates":[51.081,53.905],"type":"Point"}
}