{
  "type": "Feature",
  "properties": {
    "gn:admin1_code":"52",
    "gn:asciiname":"Lyubane",
    "gn:country_code":"RU",
    "gn:dem":50,
    "gn:feature_class":"P",
    "gn:feature_code":"PPL",
    "gn:name":"Lyubane",
    "gn:population":0,
    "gn:timezone":"Europe/Moscow",
    "iso:country":"RU",
    "name:rus_x_preferred":[
        "\u041b\u044e\u0431\u0430\u043d\u0435"
    ],
    "wof:name":"Lyubane",
    "wof:placetype":"locality"
},
  "geometry": {"coordinates":[30.20864000000001,58.34243000000001],"type":"Point"}
}