{
  "type": "Feature",
  "properties": {
    "gn:admin1_code":"42",
    "gn:asciiname":"Lepuya",
    "gn:cc2":"RU",
    "gn:country_code":"RU",
    "gn:dem":162,
    "gn:feature_class":"P",
    "gn:feature_code":"PPL",
    "gn:name":"Lepuya",
    "gn:population":0,
    "gn:timezone":"Europe/Moscow",
    "iso:country":"RU",
    "name:rus_x_preferred":[
        "\u041b\u0435\u043f\u0443\u044f"
    ],
    "name:und_x_variant":[
        "Lepuyo",
        "Lepuya"
    ],
    "wof:name":"Lepuya",
    "wof:placetype":"locality"
},
  "geometry": {"coordinates":[34.28889,59.83139],"type":"Point"}
}