{
  "type": "Feature",
  "properties": {
    "gn:admin1_code":"4",
    "gn:asciiname":"Cheremushkino",
    "gn:country_code":"RU",
    "gn:dem":160,
    "gn:feature_class":"P",
    "gn:feature_code":"PPL",
    "gn:name":"Cheremushkino",
    "gn:population":0,
    "gn:timezone":"Asia/Barnaul",
    "iso:country":"RU",
    "name:eng_x_preferred":[
        "Cheremushkino"
    ],
    "name:nor_x_preferred":[
        "Tsjeremusjkino"
    ],
    "name:rus_x_preferred":[
        "\u0427\u0435\u0440\u0435\u043c\u0443\u0448\u043a\u0438\u043d\u043e"
    ],
    "wof:name":"Cheremushkino",
    "wof:placetype":"locality"
},
  "geometry": {"coordinates":[84.28583,54.01056],"type":"Point"}
}