{
  "type": "Feature",
  "properties": {
    "gn:admin1_code":"60",
    "gn:asciiname":"Ostrova",
    "gn:country_code":"RU",
    "gn:dem":54,
    "gn:feature_class":"P",
    "gn:feature_code":"PPL",
    "gn:name":"Ostrova",
    "gn:population":0,
    "gn:timezone":"Europe/Moscow",
    "iso:country":"RU",
    "name:eng_x_preferred":[
        "Ostrova"
    ],
    "name:nor_x_preferred":[
        "Ostrova"
    ],
    "name:rus_x_preferred":[
        "\u041e\u0441\u0442\u0440\u043e\u0432\u0430"
    ],
    "name:und_x_variant":[
        "Krasnaya Ostrova"
    ],
    "wof:name":"Ostrova",
    "wof:placetype":"locality"
},
  "geometry": {"coordinates":[29.67166,57.83258000000001],"type":"Point"}
}