{
  "type": "Feature",
  "properties": {
    "gn:admin1_code":"8",
    "gn:asciiname":"Sorvikha",
    "gn:country_code":"RU",
    "gn:dem":111,
    "gn:feature_class":"P",
    "gn:feature_code":"PPL",
    "gn:name":"Sorvikha",
    "gn:population":0,
    "gn:timezone":"Asia/Yekaterinburg",
    "iso:country":"RU",
    "name:bak_x_preferred":[
        "\u0421\u0430\u0440\u0443\u0430"
    ],
    "name:che_x_preferred":[
        "\u0421\u043e\u0440\u0432\u0438\u0445\u0430"
    ],
    "name:eng_x_preferred":[
        "Sorvikha"
    ],
    "name:hye_x_preferred":[
        "\u054d\u0578\u0580\u057e\u056b\u056d\u0561"
    ],
    "name:kaz_x_preferred":[
        "\u0421\u043e\u0440\u0432\u0438\u0445\u0430"
    ],
    "name:kir_x_preferred":[
        "\u0421\u043e\u0440\u0432\u0438\u0445\u0430"
    ],
    "name:nor_x_preferred":[
        "Sorvikha"
    ],
    "name:rus_x_preferred":[
        "\u0421\u043e\u0440\u0432\u0438\u0445\u0430"
    ],
    "name:tat_x_preferred":[
        "\u0421\u04d9\u0440\u0432\u04d9"
    ],
    "name:und_x_variant":[
        "\u0421\u043e\u0440\u0432\u0438\u0445\u0430",
        "Sorvikha"
    ],
    "wof:name":"Sorvikha",
    "wof:placetype":"locality"
},
  "geometry": {"coordinates":[55.84889,55.235],"type":"Point"}
}