{
  "type": "Feature",
  "properties": {
    "gn:admin1_code":"77",
    "gn:asciiname":"Tushitovo",
    "gn:country_code":"RU",
    "gn:dem":154,
    "gn:feature_class":"P",
    "gn:feature_code":"PPL",
    "gn:name":"Tushitovo",
    "gn:population":0,
    "gn:timezone":"Europe/Moscow",
    "iso:country":"RU",
    "name:rus_x_preferred":[
        "\u0422\u0443\u0448\u0438\u0442\u043e\u0432\u043e"
    ],
    "wof:name":"Tushitovo",
    "wof:placetype":"locality"
},
  "geometry": {"coordinates":[36.6506,58.21],"type":"Point"}
}