{
  "type": "Feature",
  "properties": {
    "gn:admin1_code":"57",
    "gn:asciiname":"Vsevolodovka",
    "gn:country_code":"RU",
    "gn:dem":229,
    "gn:feature_class":"P",
    "gn:feature_code":"PPL",
    "gn:name":"Vsevolodovka",
    "gn:population":0,
    "gn:timezone":"Europe/Moscow",
    "iso:country":"RU",
    "name:rus_x_preferred":[
        "\u0412\u0441\u0435\u0432\u043e\u043b\u043e\u0434\u043e\u0432\u043a\u0430"
    ],
    "name:und_x_variant":[
        "\u0412\u0441\u0435\u0432\u043e\u043b\u043e\u0434\u043e\u0432\u043a\u0430",
        "Vsevolovka"
    ],
    "wof:name":"Vsevolodovka",
    "wof:placetype":"locality"
},
  "geometry": {"coordinates":[44.40841,53.08729],"type":"Point"}
}