{
  "type": "Feature",
  "properties": {
    "gn:admin1_code":"88",
    "gn:asciiname":"Volzhskiy",
    "gn:country_code":"RU",
    "gn:dem":98,
    "gn:feature_class":"P",
    "gn:feature_code":"PPL",
    "gn:name":"Volzhskiy",
    "gn:population":0,
    "gn:timezone":"Europe/Moscow",
    "iso:country":"RU",
    "name:hun_x_preferred":[
        "Volzsszkij"
    ],
    "name:rus_x_preferred":[
        "\u0412\u043e\u043b\u0436\u0441\u043a\u0438\u0439"
    ],
    "wof:name":"Volzhskiy",
    "wof:placetype":"locality"
},
  "geometry": {"coordinates":[39.64907,57.80857],"type":"Point"}
}