{
  "type": "Feature",
  "properties": {
    "gn:admin1_code":"91",
    "gn:asciiname":"Yar-Pan-Ty-Ya",
    "gn:country_code":"RU",
    "gn:dem":27,
    "gn:feature_class":"P",
    "gn:feature_code":"PPL",
    "gn:name":"Yar-Pan-Ty-Ya",
    "gn:population":0,
    "gn:timezone":"Asia/Krasnoyarsk",
    "iso:country":"RU",
    "wof:name":"Yar-Pan-Ty-Ya",
    "wof:placetype":"locality"
},
  "geometry": {"coordinates":[80.83333,70.16667],"type":"Point"}
}