{
  "type": "Feature",
  "properties": {
    "gn:admin1_code":"88.0",
    "gn:asciiname":"Pokrovskaya",
    "gn:country_code":"RU",
    "gn:dem":124,
    "gn:feature_class":"P",
    "gn:feature_code":"PPL",
    "gn:name":"Pokrovskaya",
    "gn:population":0,
    "gn:timezone":"Europe/Moscow",
    "iso:country":"RU",
    "name:rus_x_preferred":[
        "\u041f\u043e\u043a\u0440\u043e\u0432\u0441\u043a\u0430\u044f"
    ],
    "wof:name":"Pokrovskaya",
    "wof:placetype":"locality"
},
  "geometry": {"coordinates":[40.93902,58.33048],"type":"Point"}
}