{
  "type": "Feature",
  "properties": {
    "gn:admin1_code":"59",
    "gn:asciiname":"Knyazhevka",
    "gn:country_code":"RU",
    "gn:dem":66,
    "gn:feature_class":"P",
    "gn:feature_code":"PPL",
    "gn:name":"Knyazhevka",
    "gn:population":0,
    "gn:timezone":"Asia/Vladivostok",
    "iso:country":"RU",
    "name:rus_x_preferred":[
        "\u041a\u043d\u044f\u0436\u0435\u0432\u0441\u043a\u043e\u0435"
    ],
    "name:und_x_variant":[
        "Knyazherskiy",
        "Knyazhevka",
        "Knyazhevskoye"
    ],
    "wof:name":"Knyazhevka",
    "wof:placetype":"locality"
},
  "geometry": {"coordinates":[133.73548,46.0831],"type":"Point"}
}