{
  "type": "Feature",
  "properties": {
    "gn:admin1_code":"33",
    "gn:asciiname":"Zubarevo",
    "gn:country_code":"RU",
    "gn:dem":148,
    "gn:feature_class":"P",
    "gn:feature_code":"PPL",
    "gn:name":"Zubar\u00ebvo",
    "gn:population":0,
    "gn:timezone":"Europe/Kirov",
    "iso:country":"RU",
    "name:rus_x_preferred":[
        "\u0417\u0443\u0431\u0430\u0440\u0451\u0432\u043e"
    ],
    "name:und_x_variant":[
        "Zubar\u00ebvo"
    ],
    "wof:name":"Zubarevo",
    "wof:placetype":"locality"
},
  "geometry": {"coordinates":[47.5206,60.7466],"type":"Point"}
}