{
  "type": "Feature",
  "properties": {
    "gn:admin1_code":"75",
    "gn:asciiname":"Luchanovo",
    "gn:country_code":"RU",
    "gn:dem":117,
    "gn:feature_class":"P",
    "gn:feature_code":"PPL",
    "gn:name":"Luchanovo",
    "gn:population":0,
    "gn:timezone":"Asia/Tomsk",
    "iso:country":"RU",
    "name:eng_x_preferred":[
        "Luchanovo"
    ],
    "name:nor_x_preferred":[
        "Lutsjanovo"
    ],
    "name:rus_x_preferred":[
        "\u041b\u0443\u0447\u0430\u043d\u043e\u0432\u043e"
    ],
    "name:und_x_variant":[
        "Luchanova"
    ],
    "wof:name":"Luchanovo",
    "wof:placetype":"locality"
},
  "geometry": {"coordinates":[85.05144,56.35259],"type":"Point"}
}