{
  "type": "Feature",
  "properties": {
    "gn:admin1_code":"9",
    "gn:asciiname":"Gavshin",
    "gn:country_code":"RU",
    "gn:dem":211,
    "gn:feature_class":"P",
    "gn:feature_code":"PPL",
    "gn:name":"Gavshin",
    "gn:population":0,
    "gn:timezone":"Europe/Moscow",
    "iso:country":"RU",
    "name:rus_x_preferred":[
        "\u0413\u0430\u0432\u0448\u0438\u043d"
    ],
    "wof:name":"Gavshin",
    "wof:placetype":"locality"
},
  "geometry": {"coordinates":[38.2817,50.9321],"type":"Point"}
}