{
  "type": "Feature",
  "properties": {
    "gn:admin1_code":"55.0",
    "gn:asciiname":"Burannoye",
    "gn:country_code":"RU",
    "gn:dem":94,
    "gn:feature_class":"P",
    "gn:feature_code":"PPL",
    "gn:name":"Burannoye",
    "gn:population":0,
    "gn:timezone":"Asia/Yekaterinburg",
    "iso:country":"RU",
    "name:eng_x_preferred":[
        "Burannoye"
    ],
    "name:nor_x_preferred":[
        "Burannoje"
    ],
    "name:rus_x_preferred":[
        "\u0411\u0443\u0440\u0430\u043d\u043d\u043e\u0435"
    ],
    "name:und_x_variant":[
        "Burannoje",
        "Burenni",
        "\u0411\u0443\u0440\u0430\u043d\u043d\u043e\u0435",
        "Burannoye"
    ],
    "wof:name":"Burannoye",
    "wof:placetype":"locality"
},
  "geometry": {"coordinates":[54.46803000000001,50.97706],"type":"Point"}
}