{
  "type": "Feature",
  "properties": {
    "iso:country":"RU",
    "name:rus_x_preferred":[
        "\u0420\u0430\u0437\u0434\u0435\u043b\u044c\u043d\u0430\u044f"
    ],
    "wof:name":"Razdel'naja",
    "wof:placetype":"neighbourhood"
},
  "geometry": {"coordinates":[30.02276731586512,60.01382394266484],"type":"Point"}
}