{
  "type": "Feature",
  "properties": {
    "gn:admin1_code":"69",
    "gn:asciiname":"Yamnoye",
    "gn:country_code":"RU",
    "gn:dem":189,
    "gn:feature_class":"P",
    "gn:feature_code":"PPL",
    "gn:name":"Yamnoye",
    "gn:population":0,
    "gn:timezone":"Europe/Moscow",
    "iso:country":"RU",
    "name:bel_x_preferred":[
        "\u042f\u043c\u043d\u0430\u0435"
    ],
    "name:hye_x_preferred":[
        "\u0545\u0561\u0574\u0576\u0578\u0565"
    ],
    "name:rus_x_preferred":[
        "\u042f\u043c\u043d\u043e\u0435"
    ],
    "name:tat_x_preferred":[
        "\u042f\u043c\u043d\u043e\u0435"
    ],
    "name:ukr_x_preferred":[
        "\u042f\u043c\u043d\u0435"
    ],
    "wof:name":"Yamnoye",
    "wof:placetype":"locality"
},
  "geometry": {"coordinates":[34.44724,55.77132],"type":"Point"}
}