{
  "type": "Feature",
  "properties": {
    "gn:admin1_code":"86.0",
    "gn:asciiname":"Lebedev",
    "gn:country_code":"RU",
    "gn:dem":169,
    "gn:feature_class":"P",
    "gn:feature_code":"PPL",
    "gn:name":"Lebedev",
    "gn:population":0,
    "gn:timezone":"Europe/Moscow",
    "iso:country":"RU",
    "name:pol_x_preferred":[
        "Lebiediew"
    ],
    "name:rus_x_preferred":[
        "\u041b\u0435\u0431\u0435\u0434\u0435\u0432"
    ],
    "name:slv_x_preferred":[
        "Lebedjev"
    ],
    "wof:name":"Lebedev",
    "wof:placetype":"locality"
},
  "geometry": {"coordinates":[39.73328,49.87629],"type":"Point"}
}