{
  "type": "Feature",
  "properties": {
    "gn:admin1_code":"60",
    "gn:asciiname":"Chernonosy",
    "gn:country_code":"RU",
    "gn:dem":173,
    "gn:feature_class":"P",
    "gn:feature_code":"PPL",
    "gn:name":"Chernonosy",
    "gn:population":0,
    "gn:timezone":"Europe/Moscow",
    "iso:country":"RU",
    "name:rus_x_preferred":[
        "\u0427\u0435\u0440\u043d\u043e\u043d\u043e\u0441\u044b"
    ],
    "name:und_x_variant":[
        "\u0427\u0435\u0440\u043d\u043e\u043d\u043e\u0441\u044b"
    ],
    "wof:name":"Chernonosy",
    "wof:placetype":"locality"
},
  "geometry": {"coordinates":[30.1806,56.1701],"type":"Point"}
}