{
  "type": "Feature",
  "properties": {
    "gn:admin1_code":"33.0",
    "gn:asciiname":"Novaya Lema",
    "gn:country_code":"RU",
    "gn:dem":168,
    "gn:feature_class":"P",
    "gn:feature_code":"PPL",
    "gn:name":"Novaya Lema",
    "gn:population":0,
    "gn:timezone":"Europe/Kirov",
    "iso:country":"RU",
    "name:rus_x_preferred":[
        "\u041d\u043e\u0432\u0430\u044f \u041b\u0435\u043c\u0430"
    ],
    "wof:name":"Novaya Lema",
    "wof:placetype":"locality"
},
  "geometry": {"coordinates":[50.99993,58.07416],"type":"Point"}
}