{
  "type": "Feature",
  "properties": {
    "gn:admin1_code":"55",
    "gn:asciiname":"Orekhovka",
    "gn:country_code":"RU",
    "gn:dem":329,
    "gn:feature_class":"P",
    "gn:feature_code":"PPL",
    "gn:name":"Orekhovka",
    "gn:population":0,
    "gn:timezone":"Asia/Yekaterinburg",
    "iso:country":"RU",
    "name:eng_x_preferred":[
        "Orekhovka"
    ],
    "name:nor_x_preferred":[
        "Orekhovka"
    ],
    "name:rus_x_preferred":[
        "\u041e\u0440\u0435\u0445\u043e\u0432\u043a\u0430"
    ],
    "name:und_x_variant":[
        "Taraksayskiy",
        "Taraksaiski",
        "\u041e\u0440\u0435\u0445\u043e\u0432\u043a\u0430",
        "Orekhovka"
    ],
    "wof:name":"Orekhovka",
    "wof:placetype":"locality"
},
  "geometry": {"coordinates":[60.3122,51.2589],"type":"Point"}
}