{
  "type": "Feature",
  "properties": {
    "gn:admin1_code":"76",
    "gn:asciiname":"Kuneyevo",
    "gn:country_code":"RU",
    "gn:dem":174,
    "gn:feature_class":"P",
    "gn:feature_code":"PPL",
    "gn:name":"Kuneyevo",
    "gn:population":0,
    "gn:timezone":"Europe/Moscow",
    "iso:country":"RU",
    "name:rus_x_preferred":[
        "\u041a\u0443\u043d\u0435\u0435\u0432\u043e"
    ],
    "wof:name":"Kuneyevo",
    "wof:placetype":"locality"
},
  "geometry": {"coordinates":[37.91182,54.61046],"type":"Point"}
}