{
  "type": "Feature",
  "properties": {
    "gn:admin1_code":"6",
    "gn:asciiname":"Zatuyskaya",
    "gn:country_code":"RU",
    "gn:dem":36,
    "gn:feature_class":"P",
    "gn:feature_code":"PPL",
    "gn:name":"Zatuyskaya",
    "gn:population":0,
    "gn:timezone":"Europe/Moscow",
    "iso:country":"RU",
    "name:eng_x_preferred":[
        "Zatuyskaya"
    ],
    "name:nor_x_preferred":[
        "Zatujskaja"
    ],
    "name:rus_x_preferred":[
        "\u0417\u0430\u0442\u0443\u0439\u0441\u043a\u0430\u044f"
    ],
    "wof:name":"Zatuyskaya",
    "wof:placetype":"locality"
},
  "geometry": {"coordinates":[42.37167,61.67889],"type":"Point"}
}