{
  "type": "Feature",
  "properties": {
    "gn:admin1_code":"33",
    "gn:asciiname":"Malaya Kil'mez'",
    "gn:country_code":"RU",
    "gn:dem":122,
    "gn:feature_class":"P",
    "gn:feature_code":"PPL",
    "gn:name":"Malaya Kil\u2019mez\u2019",
    "gn:population":0,
    "gn:timezone":"Europe/Kirov",
    "iso:country":"RU",
    "name:rus_x_preferred":[
        "\u041c\u0430\u043b\u0430\u044f \u041a\u0438\u043b\u044c\u043c\u0435\u0437\u044c"
    ],
    "name:und_x_variant":[
        "Malaya Kil\u2019mez\u2019"
    ],
    "wof:name":"Malaya Kil'mez'",
    "wof:placetype":"locality"
},
  "geometry": {"coordinates":[51.04114000000001,56.92694],"type":"Point"}
}