{
  "type": "Feature",
  "properties": {
    "gn:admin1_code":"85.0",
    "gn:asciiname":"Maloye Brodino",
    "gn:country_code":"RU",
    "gn:dem":134,
    "gn:feature_class":"P",
    "gn:feature_code":"PPL",
    "gn:name":"Maloye Brodino",
    "gn:population":0,
    "gn:timezone":"Europe/Moscow",
    "iso:country":"RU",
    "name:rus_x_preferred":[
        "\u041c\u0430\u043b\u043e\u0435 \u0411\u0440\u043e\u0434\u0438\u043d\u043e"
    ],
    "name:und_x_variant":[
        "\u041c\u0430\u043b\u043e\u0435 \u0411\u0440\u043e\u0434\u0438\u043d\u043e"
    ],
    "wof:name":"Maloye Brodino",
    "wof:placetype":"locality"
},
  "geometry": {"coordinates":[40.67417,58.89666999999999],"type":"Point"}
}