{
  "type": "Feature",
  "properties": {
    "gn:admin1_code":"63",
    "gn:asciiname":"Mekimde",
    "gn:country_code":"RU",
    "gn:dem":149,
    "gn:feature_class":"P",
    "gn:feature_code":"PPL",
    "gn:name":"Mekimde",
    "gn:population":0,
    "gn:timezone":"Asia/Yakutsk",
    "iso:country":"RU",
    "name:eng_x_preferred":[
        "Mekimde"
    ],
    "name:nor_x_preferred":[
        "Mekimdja"
    ],
    "name:rus_x_preferred":[
        "\u041c\u0435\u043a\u0438\u043c\u0434\u044f"
    ],
    "name:rus_x_variant":[
        "\u041c\u0435\u043a\u0438\u043c\u0434\u0435"
    ],
    "name:und_x_variant":[
        "\u041c\u0435\u043a\u0438\u043c\u0434\u0435"
    ],
    "wof:name":"Mekimde",
    "wof:placetype":"locality"
},
  "geometry": {"coordinates":[120.95646000000001,60.80396],"type":"Point"}
}