{
  "type": "Feature",
  "properties": {
    "gn:admin1_code":"77.0",
    "gn:asciiname":"Bol'shiye Selishi",
    "gn:country_code":"RU",
    "gn:dem":136,
    "gn:feature_class":"P",
    "gn:feature_code":"PPL",
    "gn:name":"Bol\u2019shiye Selishi",
    "gn:population":0,
    "gn:timezone":"Europe/Moscow",
    "iso:country":"RU",
    "name:nor_x_preferred":[
        "Bolsjije Selisji"
    ],
    "name:rus_x_preferred":[
        "\u0411\u043e\u043b\u044c\u0448\u0438\u0435 \u0421\u0435\u043b\u0438\u0448\u0438"
    ],
    "name:und_x_variant":[
        "Bol\u2019shoye Selishche",
        "Bol\u2019shiye Selishchi",
        "Bol\u2019shiye Selishi"
    ],
    "wof:name":"Bol'shiye Selishi",
    "wof:placetype":"locality"
},
  "geometry": {"coordinates":[35.87264000000001,56.50781],"type":"Point"}
}