{
  "type": "Feature",
  "properties": {
    "gn:admin1_code":"91.0",
    "gn:asciiname":"Berezovaya Roshcha",
    "gn:country_code":"RU",
    "gn:dem":346,
    "gn:feature_class":"P",
    "gn:feature_code":"PPL",
    "gn:name":"Ber\u00ebzovaya Roshcha",
    "gn:population":0,
    "gn:timezone":"Asia/Krasnoyarsk",
    "iso:country":"RU",
    "name:nor_x_preferred":[
        "Berjozovaja Rosjtsja"
    ],
    "name:rus_x_preferred":[
        "\u0411\u0435\u0440\u0451\u0437\u043e\u0432\u0430\u044f \u0420\u043e\u0449\u0430"
    ],
    "name:und_x_variant":[
        "Ber\u00ebzovaya Roshcha"
    ],
    "wof:name":"Berezovaya Roshcha",
    "wof:placetype":"locality"
},
  "geometry": {"coordinates":[90.02056,55.72278000000001],"type":"Point"}
}