{
  "type": "Feature",
  "properties": {
    "gn:country":"RU",
    "gn:fcode":"PPL",
    "gn:pop":0,
    "iso:country":"RU",
    "name:rus_x_preferred":[
        "\u041b\u044b\u0441\u044b\u0435 \u0413\u043e\u0440\u044b"
    ],
    "name:unk_x_variant":[
        "Lysyye Gory"
    ],
    "qs:name":"Lysyye Gorj",
    "qs:name_adm0":"Russia",
    "qs:name_adm1":"Tambov Oblast",
    "qs:photos_9k":1,
    "qs:photos_9r":1,
    "qs:photos_all":5,
    "qs:photos_sr":0,
    "qs:placetype":"Town",
    "qs:pop_sr":"0",
    "wof:name":"Lysyye Gorj",
    "wof:placetype":"locality",
    "wof:population":0
},
  "geometry": {"coordinates":[41.23145,52.8476],"type":"Point"}
}