{
  "type": "Feature",
  "properties": {
    "gn:admin1_code":"45",
    "gn:asciiname":"Toktarsola",
    "gn:country_code":"RU",
    "gn:dem":158,
    "gn:feature_class":"P",
    "gn:feature_code":"PPL",
    "gn:name":"Toktarsola",
    "gn:population":0,
    "gn:timezone":"Europe/Moscow",
    "iso:country":"RU",
    "name:rus_x_preferred":[
        "\u0422\u043e\u043a\u0442\u0430\u0440\u0441\u043e\u043b\u0430"
    ],
    "wof:name":"Toktarsola",
    "wof:placetype":"locality"
},
  "geometry": {"coordinates":[48.71833,56.92361],"type":"Point"}
}