{
  "type": "Feature",
  "properties": {
    "gn:admin1_code":"27",
    "gn:asciiname":"Tallyk",
    "gn:country_code":"RU",
    "gn:dem":604,
    "gn:feature_class":"P",
    "gn:feature_code":"PPL",
    "gn:name":"Tallyk",
    "gn:population":0,
    "gn:timezone":"Europe/Moscow",
    "iso:country":"RU",
    "name:rus_x_preferred":[
        "\u0422\u0430\u043b\u043b\u044b\u043a"
    ],
    "name:und_x_variant":[
        "\u0422\u0430\u043b\u043b\u044b\u043a"
    ],
    "wof:name":"Tallyk",
    "wof:placetype":"locality"
},
  "geometry": {"coordinates":[42.352,44.154],"type":"Point"}
}