{
  "type": "Feature",
  "properties": {
    "gn:admin1_code":"41.0",
    "gn:asciiname":"Bogorodetskoye",
    "gn:country_code":"RU",
    "gn:dem":220,
    "gn:feature_class":"P",
    "gn:feature_code":"PPL",
    "gn:name":"Bogorodetskoye",
    "gn:population":0,
    "gn:timezone":"Europe/Moscow",
    "iso:country":"RU",
    "name:rus_x_preferred":[
        "\u0411\u043e\u0433\u043e\u0440\u043e\u0434\u0435\u0442\u0441\u043a\u043e\u0435"
    ],
    "name:und_x_variant":[
        "\u0411\u043e\u0433\u043e\u0440\u043e\u0434\u0435\u0442\u0441\u043a\u043e\u0435"
    ],
    "wof:name":"Bogorodetskoye",
    "wof:placetype":"locality"
},
  "geometry": {"coordinates":[36.7282,52.01264000000001],"type":"Point"}
}