{
  "type": "Feature",
  "properties": {
    "gn:admin1_code":"76",
    "gn:asciiname":"Grekov Khutor",
    "gn:country_code":"RU",
    "gn:dem":205,
    "gn:feature_class":"P",
    "gn:feature_code":"PPL",
    "gn:name":"Grekov Khutor",
    "gn:population":0,
    "gn:timezone":"Europe/Moscow",
    "iso:country":"RU",
    "name:rus_x_preferred":[
        "\u0413\u0440\u0435\u043a\u043e\u0432 \u0425\u0443\u0442\u043e\u0440"
    ],
    "name:und_x_variant":[
        "Grekovskiy",
        "Grenov Khutor"
    ],
    "wof:name":"Grekov Khutor",
    "wof:placetype":"locality"
},
  "geometry": {"coordinates":[38.59243,53.20011],"type":"Point"}
}