{
  "type": "Feature",
  "properties": {
    "gn:admin1_code":"19.0",
    "gn:asciiname":"Galashki",
    "gn:country_code":"RU",
    "gn:dem":622,
    "gn:feature_class":"P",
    "gn:feature_code":"PPL",
    "gn:name":"Galashki",
    "gn:population":0,
    "gn:timezone":"Europe/Moscow",
    "iso:country":"RU",
    "name:ara_x_preferred":[
        "\u063a\u0627\u0644\u0627\u0634\u0643\u064a"
    ],
    "name:che_x_preferred":[
        "\u0413\u0430\u043b\u0430\u0448\u043a\u0438\u0435"
    ],
    "name:deu_x_preferred":[
        "Galaschki"
    ],
    "name:epo_x_preferred":[
        "Gala\u015dko"
    ],
    "name:hye_x_preferred":[
        "\u0533\u0561\u056c\u0561\u0577\u056f\u056b"
    ],
    "name:inh_x_preferred":[
        "\u0413\u0430\u043b\u0430\u0448\u043a\u0435"
    ],
    "name:oss_x_preferred":[
        "\u0413\u0430\u043b\u0430\u0448\u043a\u0438"
    ],
    "name:rus_x_preferred":[
        "\u0413\u0430\u043b\u0430\u0448\u043a\u0438"
    ],
    "name:und_x_variant":[
        "Pervomayskiy",
        "Pervomayskoye",
        "Galashki"
    ],
    "wof:name":"Galashki",
    "wof:placetype":"locality"
},
  "geometry": {"coordinates":[44.9875,43.08806],"type":"Point"}
}