{
  "type": "Feature",
  "properties": {
    "gn:admin1_code":"28.0",
    "gn:asciiname":"Akkola",
    "gn:country_code":"RU",
    "gn:dem":189,
    "gn:feature_class":"P",
    "gn:feature_code":"PPL",
    "gn:name":"Akkola",
    "gn:population":0,
    "gn:timezone":"Europe/Moscow",
    "iso:country":"RU",
    "name:eng_x_preferred":[
        "Akkola"
    ],
    "name:fin_x_preferred":[
        "Akkala"
    ],
    "name:nor_x_preferred":[
        "Akkola"
    ],
    "name:rus_x_preferred":[
        "\u0410\u043a\u043a\u043e\u043b\u0430"
    ],
    "name:und_x_variant":[
        "\u0410\u043a\u043a\u043e\u043b\u0430",
        "Akkola"
    ],
    "wof:name":"Akkola",
    "wof:placetype":"locality"
},
  "geometry": {"coordinates":[30.8403,65.65222],"type":"Point"}
}