{
  "type": "Feature",
  "properties": {
    "gn:admin1_code":"53",
    "gn:asciiname":"Bokson",
    "gn:country_code":"RU",
    "gn:dem":121,
    "gn:feature_class":"P",
    "gn:feature_code":"PPL",
    "gn:name":"Bokson",
    "gn:population":0,
    "gn:timezone":"Asia/Novosibirsk",
    "iso:country":"RU",
    "name:rus_x_preferred":[
        "\u0411\u043e\u043a\u0441\u043e\u043d"
    ],
    "name:und_x_variant":[
        "\u0411\u043e\u043a\u0441\u043e\u043d"
    ],
    "wof:name":"Bokson",
    "wof:placetype":"locality"
},
  "geometry": {"coordinates":[84.01666999999998,55.78333000000001],"type":"Point"}
}