{
  "type": "Feature",
  "properties": {
    "gn:admin1_code":"3",
    "gn:asciiname":"Albas",
    "gn:country_code":"RU",
    "gn:dem":595,
    "gn:feature_class":"P",
    "gn:feature_code":"PPL",
    "gn:name":"Albas",
    "gn:population":0,
    "gn:timezone":"Asia/Omsk",
    "iso:country":"RU",
    "name:ceb_x_preferred":[
        "Albas"
    ],
    "name:deu_x_preferred":[
        "Albas"
    ],
    "name:est_x_preferred":[
        "Albas"
    ],
    "name:eus_x_preferred":[
        "Albas"
    ],
    "name:fra_x_preferred":[
        "Albas"
    ],
    "name:ita_x_preferred":[
        "Albas"
    ],
    "name:nds_x_preferred":[
        "Albas"
    ],
    "name:nld_x_preferred":[
        "Albas"
    ],
    "name:nor_x_preferred":[
        "Albas"
    ],
    "name:oci_x_preferred":[
        "Alb\u00e0s"
    ],
    "name:pms_x_preferred":[
        "Albas"
    ],
    "name:pol_x_preferred":[
        "Albas"
    ],
    "name:por_x_preferred":[
        "Albas"
    ],
    "name:rus_x_preferred":[
        "\u0410\u043b\u0431\u0430\u0441"
    ],
    "name:rus_x_variant":[
        "\u0410\u043b\u044c\u0431\u0430\u0441"
    ],
    "name:slk_x_preferred":[
        "Albas"
    ],
    "name:spa_x_preferred":[
        "Albas"
    ],
    "name:swe_x_preferred":[
        "Albas"
    ],
    "name:ukr_x_preferred":[
        "\u0410\u043b\u044c\u0431\u0430\u0441"
    ],
    "wof:name":"Albas",
    "wof:placetype":"locality"
},
  "geometry": {"coordinates":[88.03333000000001,52.25],"type":"Point"}
}