{
  "type": "Feature",
  "properties": {
    "gn:admin1_code":"3",
    "gn:asciiname":"Albas",
    "gn:country_code":"RU",
    "gn:dem":595,
    "gn:feature_class":"P",
    "gn:feature_code":"PPL",
    "gn:name":"Albas",
    "gn:population":0,
    "gn:timezone":"Asia/Omsk",
    "iso:country":"RU",
    "name:nor_x_preferred":[
        "Albas"
    ],
    "name:rus_x_preferred":[
        "\u0410\u043b\u0431\u0430\u0441"
    ],
    "wof:name":"Albas",
    "wof:placetype":"locality"
},
  "geometry": {"coordinates":[88.03333000000001,52.25],"type":"Point"}
}