{
  "type": "Feature",
  "properties": {
    "gn:admin1_code":"88",
    "gn:asciiname":"Stroytsino",
    "gn:country_code":"RU",
    "gn:dem":169,
    "gn:feature_class":"P",
    "gn:feature_code":"PPL",
    "gn:name":"Stroytsino",
    "gn:population":0,
    "gn:timezone":"Europe/Moscow",
    "iso:country":"RU",
    "name:rus_x_preferred":[
        "\u0421\u0442\u0440\u043e\u0439\u0446\u0438\u043d\u043e"
    ],
    "name:und_x_variant":[
        "\u0421\u0442\u0440\u043e\u0439\u0446\u0438\u043d\u043e"
    ],
    "wof:name":"Stroytsino",
    "wof:placetype":"locality"
},
  "geometry": {"coordinates":[38.8199,57.1801],"type":"Point"}
}