{
  "type": "Feature",
  "properties": {
    "gn:admin1_code":"6",
    "gn:asciiname":"Priluki",
    "gn:country_code":"RU",
    "gn:dem":57,
    "gn:feature_class":"P",
    "gn:feature_code":"PPL",
    "gn:name":"Priluki",
    "gn:population":0,
    "gn:timezone":"Europe/Moscow",
    "iso:country":"RU",
    "name:eng_x_preferred":[
        "Priluki"
    ],
    "name:nor_x_preferred":[
        "Priluki"
    ],
    "name:rus_x_preferred":[
        "\u041f\u0440\u0438\u043b\u0443\u043a\u0438"
    ],
    "name:und_x_variant":[
        "Prilutskaya"
    ],
    "wof:name":"Priluki",
    "wof:placetype":"locality"
},
  "geometry": {"coordinates":[42.38003,61.30704],"type":"Point"}
}