{
  "type": "Feature",
  "properties": {
    "gn:admin1_code":"90.0",
    "gn:asciiname":"Ust'-Vishera",
    "gn:country_code":"RU",
    "gn:dem":136,
    "gn:feature_class":"P",
    "gn:feature_code":"PPL",
    "gn:name":"Ust\u2019-Vishera",
    "gn:population":0,
    "gn:timezone":"Asia/Yekaterinburg",
    "iso:country":"RU",
    "name:rus_x_preferred":[
        "\u0423\u0441\u0442\u044c-\u0412\u0438\u0448\u0435\u0440\u0430"
    ],
    "name:und_x_variant":[
        "Ust\u2019-Vishera"
    ],
    "wof:name":"Ust'-Vishera",
    "wof:placetype":"locality"
},
  "geometry": {"coordinates":[56.4279,59.8971],"type":"Point"}
}