{
  "type": "Feature",
  "properties": {
    "gn:admin1_code":"27",
    "gn:asciiname":"Severnyy Priyut",
    "gn:country_code":"RU",
    "gn:dem":2064,
    "gn:feature_class":"P",
    "gn:feature_code":"PPL",
    "gn:name":"Severnyy Priyut",
    "gn:population":0,
    "gn:timezone":"Europe/Moscow",
    "iso:country":"RU",
    "name:rus_x_preferred":[
        "\u0421\u0435\u0432\u0435\u0440\u043d\u044b\u0439 \u041f\u0440\u0438\u044e\u0442"
    ],
    "wof:name":"Severnyy Priyut",
    "wof:placetype":"locality"
},
  "geometry": {"coordinates":[41.8274,43.25329],"type":"Point"}
}