{
  "type": "Feature",
  "properties": {
    "gn:admin1_code":"69",
    "gn:asciiname":"Gorlova",
    "gn:cc2":"RU",
    "gn:country_code":"RU",
    "gn:dem":218,
    "gn:feature_class":"P",
    "gn:feature_code":"PPL",
    "gn:name":"Gorlova",
    "gn:population":0,
    "gn:timezone":"Europe/Moscow",
    "iso:country":"RU",
    "name:rus_x_preferred":[
        "\u0413\u043e\u0440\u043b\u043e\u0432\u0430"
    ],
    "name:und_x_variant":[
        "Gorlovo",
        "Gorlova",
        "\u0413\u043e\u0440\u043b\u043e\u0432\u0430"
    ],
    "wof:name":"Gorlova",
    "wof:placetype":"locality"
},
  "geometry": {"coordinates":[33.7275,55.21361],"type":"Point"}
}