{
  "type": "Feature",
  "properties": {
    "gn:admin1_code":"77",
    "gn:asciiname":"Gorodok",
    "gn:country_code":"RU",
    "gn:dem":240,
    "gn:feature_class":"P",
    "gn:feature_code":"PPL",
    "gn:name":"Gorodok",
    "gn:population":0,
    "gn:timezone":"Europe/Moscow",
    "iso:country":"RU",
    "name:ceb_x_preferred":[
        "Gorodok"
    ],
    "name:ces_x_preferred":[
        "Gorodok"
    ],
    "name:ita_x_preferred":[
        "Gorodok"
    ],
    "name:rus_x_preferred":[
        "\u0413\u043e\u0440\u043e\u0434\u043e\u043a"
    ],
    "name:spa_x_preferred":[
        "Gorodok"
    ],
    "name:swe_x_preferred":[
        "Gorodok"
    ],
    "wof:name":"Gorodok",
    "wof:placetype":"locality"
},
  "geometry": {"coordinates":[32.89,56.84166999999999],"type":"Point"}
}