{
  "type": "Feature",
  "properties": {
    "gn:admin1_code":"16",
    "gn:asciiname":"Timer-Sirma",
    "gn:country_code":"RU",
    "gn:dem":165,
    "gn:feature_class":"P",
    "gn:feature_code":"PPL",
    "gn:name":"Timer-Sirma",
    "gn:population":0,
    "gn:timezone":"Europe/Moscow",
    "iso:country":"RU",
    "name:rus_x_preferred":[
        "\u0422\u0438\u043c\u0435\u0440-\u0421\u0438\u0440\u043c\u0430"
    ],
    "wof:name":"Timer-Sirma",
    "wof:placetype":"locality"
},
  "geometry": {"coordinates":[47.12551,56.03182],"type":"Point"}
}