{
  "type": "Feature",
  "properties": {
    "gn:admin1_code":"37",
    "gn:asciiname":"Shchepino",
    "gn:country_code":"RU",
    "gn:dem":178,
    "gn:feature_class":"P",
    "gn:feature_code":"PPL",
    "gn:name":"Shchepino",
    "gn:population":0,
    "gn:timezone":"Europe/Moscow",
    "iso:country":"RU",
    "name:rus_x_preferred":[
        "\u0429\u0435\u043f\u0438\u043d\u043e"
    ],
    "wof:name":"Shchepino",
    "wof:placetype":"locality"
},
  "geometry": {"coordinates":[42.02,58.5992],"type":"Point"}
}