{
  "type": "Feature",
  "properties": {
    "gn:admin1_code":"33.0",
    "gn:asciiname":"Chekal'skiy",
    "gn:country_code":"RU",
    "gn:dem":72,
    "gn:feature_class":"P",
    "gn:feature_code":"PPL",
    "gn:name":"Chekal\u2019skiy",
    "gn:population":0,
    "gn:timezone":"Europe/Kirov",
    "iso:country":"RU",
    "name:rus_x_preferred":[
        "\u0427\u0435\u043a\u0430\u043b\u044c\u0441\u043a\u0438\u0439"
    ],
    "name:und_x_variant":[
        "Chekalki",
        "Chekal\u2019skiy"
    ],
    "wof:name":"Chekal'skiy",
    "wof:placetype":"locality"
},
  "geometry": {"coordinates":[50.56099,56.93106],"type":"Point"}
}