{
  "type": "Feature",
  "properties": {
    "gn:admin1_code":"88",
    "gn:asciiname":"Bryantsevo",
    "gn:country_code":"RU",
    "gn:dem":141,
    "gn:feature_class":"P",
    "gn:feature_code":"PPL",
    "gn:name":"Bryantsevo",
    "gn:population":0,
    "gn:timezone":"Europe/Moscow",
    "iso:country":"RU",
    "name:rus_x_preferred":[
        "\u0411\u0440\u044f\u043d\u0446\u0435\u0432\u043e"
    ],
    "wof:name":"Bryantsevo",
    "wof:placetype":"locality"
},
  "geometry": {"coordinates":[39.6526,57.7818],"type":"Point"}
}