{
  "type": "Feature",
  "properties": {
    "gn:admin1_code":"90",
    "gn:asciiname":"Razepino",
    "gn:country_code":"RU",
    "gn:dem":191,
    "gn:feature_class":"P",
    "gn:feature_code":"PPL",
    "gn:name":"Razepino",
    "gn:population":0,
    "gn:timezone":"Asia/Yekaterinburg",
    "iso:country":"RU",
    "name:rus_x_preferred":[
        "\u0420\u0430\u0437\u0435\u043f\u0438\u043d\u043e"
    ],
    "name:und_x_variant":[
        "\u0420\u0430\u0437\u0435\u043f\u0438\u043d\u043e"
    ],
    "wof:name":"Razepino",
    "wof:placetype":"locality"
},
  "geometry": {"coordinates":[56.7134,57.4558],"type":"Point"}
}