{
  "type": "Feature",
  "properties": {
    "gn:admin1_code":"77.0",
    "gn:asciiname":"Bol'shiye Nivy",
    "gn:country_code":"RU",
    "gn:dem":224,
    "gn:feature_class":"P",
    "gn:feature_code":"PPL",
    "gn:name":"Bol\u2019shiye Nivy",
    "gn:population":0,
    "gn:timezone":"Europe/Moscow",
    "iso:country":"RU",
    "name:rus_x_preferred":[
        "\u0411\u043e\u043b\u044c\u0448\u0438\u0435 \u041d\u0438\u0432\u044b"
    ],
    "name:und_x_variant":[
        "Bol\u2019shiye Nivy"
    ],
    "wof:name":"Bol'shiye Nivy",
    "wof:placetype":"locality"
},
  "geometry": {"coordinates":[33.47363,56.99182],"type":"Point"}
}