{
  "type": "Feature",
  "properties": {
    "gn:admin1_code":"73",
    "gn:asciiname":"Yazly-Artash",
    "gn:country_code":"RU",
    "gn:dem":140,
    "gn:feature_class":"P",
    "gn:feature_code":"PPL",
    "gn:name":"Yazly-Artash",
    "gn:population":0,
    "gn:timezone":"Europe/Moscow",
    "iso:country":"RU",
    "name:rus_x_preferred":[
        "\u042f\u0437\u043b\u044b-\u0410\u0440\u0442\u0430\u0448"
    ],
    "name:und_x_variant":[
        "\u042f\u0437\u043b\u044b-\u0410\u0440\u0442\u0430\u0448"
    ],
    "wof:name":"Yazly-Artash",
    "wof:placetype":"locality"
},
  "geometry": {"coordinates":[50.6499,55.9658],"type":"Point"}
}