{
  "type": "Feature",
  "properties": {
    "gn:admin1_code":"10",
    "gn:asciiname":"Klimenkov",
    "gn:country_code":"RU",
    "gn:dem":177,
    "gn:feature_class":"P",
    "gn:feature_code":"PPL",
    "gn:name":"Klimenkov",
    "gn:population":0,
    "gn:timezone":"Europe/Moscow",
    "iso:country":"RU",
    "name:rus_x_preferred":[
        "\u041a\u043b\u0438\u043c\u0435\u043d\u043a\u043e\u0432"
    ],
    "name:und_x_variant":[
        "\u041a\u043b\u0438\u043c\u0435\u043d\u043a\u043e\u0432"
    ],
    "wof:name":"Klimenkov",
    "wof:placetype":"locality"
},
  "geometry": {"coordinates":[32.92111,52.30778],"type":"Point"}
}