{
  "type": "Feature",
  "properties": {
    "gn:admin1_code":"45",
    "gn:asciiname":"Yashtuga",
    "gn:country_code":"RU",
    "gn:dem":149,
    "gn:feature_class":"P",
    "gn:feature_code":"PPL",
    "gn:name":"Yashtuga",
    "gn:population":0,
    "gn:timezone":"Europe/Moscow",
    "iso:country":"RU",
    "name:rus_x_preferred":[
        "\u042f\u0448\u0442\u0443\u0433\u0430"
    ],
    "wof:name":"Yashtuga",
    "wof:placetype":"locality"
},
  "geometry": {"coordinates":[46.2281,56.0721],"type":"Point"}
}