{
  "type": "Feature",
  "properties": {
    "gn:admin1_code":"85",
    "gn:asciiname":"Polezhayevo",
    "gn:country_code":"RU",
    "gn:dem":215,
    "gn:feature_class":"P",
    "gn:feature_code":"PPL",
    "gn:name":"Polezhayevo",
    "gn:population":0,
    "gn:timezone":"Europe/Moscow",
    "iso:country":"RU",
    "name:eng_x_preferred":[
        "Polezhayevo"
    ],
    "name:nor_x_preferred":[
        "Polezjajevo"
    ],
    "name:rus_x_preferred":[
        "\u041f\u043e\u043b\u0435\u0436\u0430\u0435\u0432\u043e"
    ],
    "name:und_x_variant":[
        "Polezhayevka"
    ],
    "wof:name":"Polezhayevo",
    "wof:placetype":"locality"
},
  "geometry": {"coordinates":[44.94463,59.51246],"type":"Point"}
}