{
  "type": "Feature",
  "properties": {
    "gn:admin1_code":"53",
    "gn:asciiname":"Novorozino",
    "gn:country_code":"RU",
    "gn:dem":109,
    "gn:feature_class":"P",
    "gn:feature_code":"PPL",
    "gn:name":"Novorozino",
    "gn:population":0,
    "gn:timezone":"Asia/Novosibirsk",
    "iso:country":"RU",
    "name:eng_x_preferred":[
        "Novorozino"
    ],
    "name:nor_x_preferred":[
        "Novorozino"
    ],
    "name:rus_x_preferred":[
        "\u041d\u043e\u0432\u043e\u0440\u043e\u0437\u0438\u043d\u043e"
    ],
    "name:und_x_variant":[
        "Novo-Rozikha"
    ],
    "wof:name":"Novorozino",
    "wof:placetype":"locality"
},
  "geometry": {"coordinates":[77.78466999999998,54.64934],"type":"Point"}
}