{
  "type": "Feature",
  "properties": {
    "gn:admin1_code":"83.0",
    "gn:asciiname":"Kadyyevo",
    "gn:country_code":"RU",
    "gn:dem":123,
    "gn:feature_class":"P",
    "gn:feature_code":"PPL",
    "gn:name":"Kadyyevo",
    "gn:population":0,
    "gn:timezone":"Europe/Moscow",
    "iso:country":"RU",
    "name:rus_x_preferred":[
        "\u041a\u0430\u0434\u044b\u0435\u0432\u043e"
    ],
    "wof:name":"Kadyyevo",
    "wof:placetype":"locality"
},
  "geometry": {"coordinates":[40.3672,56.00189],"type":"Point"}
}