{
  "type": "Feature",
  "properties": {
    "gn:admin1_code":"37.0",
    "gn:asciiname":"Vlasovo",
    "gn:country_code":"RU",
    "gn:dem":96,
    "gn:feature_class":"P",
    "gn:feature_code":"PPL",
    "gn:name":"Vlasovo",
    "gn:population":0,
    "gn:timezone":"Europe/Moscow",
    "iso:country":"RU",
    "wof:name":"Vlasovo",
    "wof:placetype":"locality"
},
  "geometry": {"coordinates":[40.73096,57.40196],"type":"Point"}
}