{
  "type": "Feature",
  "properties": {
    "gn:admin1_code":"87",
    "gn:asciiname":"Vorkuta",
    "gn:cc2":"RU",
    "gn:country_code":"RU",
    "gn:dem":-9999,
    "gn:feature_class":"P",
    "gn:feature_code":"PPL",
    "gn:name":"Vorkuta",
    "gn:population":0,
    "gn:timezone":"Asia/Yekaterinburg",
    "iso:country":"RU",
    "name:und_x_variant":[
        "Varkuta",
        "Vorkuta"
    ],
    "wof:name":"Vorkuta",
    "wof:placetype":"locality"
},
  "geometry": {"coordinates":[70.13333,66.36667],"type":"Point"}
}