{
  "type": "Feature",
  "properties": {
    "gn:admin1_code":"51.0",
    "gn:asciiname":"Sal'kovo",
    "gn:country_code":"RU",
    "gn:dem":159,
    "gn:feature_class":"P",
    "gn:feature_code":"PPL",
    "gn:name":"Sal\u2019kovo",
    "gn:population":0,
    "gn:timezone":"Europe/Moscow",
    "iso:country":"RU",
    "name:rus_x_preferred":[
        "\u0421\u0430\u043b\u044c\u043a\u043e\u0432\u043e"
    ],
    "name:und_x_variant":[
        "Sal\u2019kovo",
        "\u0421\u0430\u043b\u044c\u043a\u043e\u0432\u043e"
    ],
    "wof:name":"Sal'kovo",
    "wof:placetype":"locality"
},
  "geometry": {"coordinates":[43.28213,55.84387],"type":"Point"}
}