{
  "type": "Feature",
  "properties": {
    "gn:admin1_code":"76.0",
    "gn:asciiname":"Dolmatovo",
    "gn:country_code":"RU",
    "gn:dem":241,
    "gn:feature_class":"P",
    "gn:feature_code":"PPL",
    "gn:name":"Dolmatovo",
    "gn:population":0,
    "gn:timezone":"Europe/Moscow",
    "iso:country":"RU",
    "name:rus_x_preferred":[
        "\u0414\u043e\u043b\u043c\u0430\u0442\u043e\u0432\u043e"
    ],
    "name:und_x_variant":[
        "Dolmatskiye Dvory",
        "Dolmatovskiye Dvory",
        "Dolmatovo",
        "\u0414\u043e\u043b\u043c\u0430\u0442\u043e\u0432\u043e"
    ],
    "wof:name":"Dolmatovo",
    "wof:placetype":"locality"
},
  "geometry": {"coordinates":[36.75998,53.39797],"type":"Point"}
}