{
  "type": "Feature",
  "properties": {
    "gn:admin1_code":"85.0",
    "gn:asciiname":"Denin Ugol",
    "gn:country_code":"RU",
    "gn:dem":141,
    "gn:feature_class":"P",
    "gn:feature_code":"PPL",
    "gn:name":"Denin Ugol",
    "gn:population":0,
    "gn:timezone":"Europe/Moscow",
    "iso:country":"RU",
    "name:rus_x_preferred":[
        "\u0414\u0435\u043d\u0438\u043d \u0423\u0433\u043e\u043b"
    ],
    "name:und_x_variant":[
        "\u0414\u0435\u043d\u0438\u043d \u0423\u0433\u043e\u043b"
    ],
    "wof:name":"Denin Ugol",
    "wof:placetype":"locality"
},
  "geometry": {"coordinates":[36.85172,61.14729000000001],"type":"Point"}
}