{
  "type": "Feature",
  "properties": {
    "gn:admin1_code":"6",
    "gn:asciiname":"Vononga",
    "gn:country_code":"RU",
    "gn:dem":140,
    "gn:feature_class":"P",
    "gn:feature_code":"PPL",
    "gn:name":"Vononga",
    "gn:population":0,
    "gn:timezone":"Europe/Moscow",
    "iso:country":"RU",
    "name:eng_x_preferred":[
        "Vononga"
    ],
    "name:nor_x_preferred":[
        "Vonongskaja"
    ],
    "name:rus_x_preferred":[
        "\u0412\u043e\u043d\u043e\u043d\u0433\u0441\u043a\u0430\u044f"
    ],
    "wof:name":"Vononga",
    "wof:placetype":"locality"
},
  "geometry": {"coordinates":[38.27052,62.68294],"type":"Point"}
}