{
  "type": "Feature",
  "properties": {
    "gn:admin1_code":"60",
    "gn:asciiname":"Chernyy Ruchey",
    "gn:country_code":"RU",
    "gn:dem":157,
    "gn:feature_class":"P",
    "gn:feature_code":"PPL",
    "gn:name":"Ch\u00ebrnyy Ruchey",
    "gn:population":0,
    "gn:timezone":"Europe/Moscow",
    "iso:country":"RU",
    "name:rus_x_preferred":[
        "\u0427\u0451\u0440\u043d\u044b\u0439 \u0420\u0443\u0447\u0435\u0439"
    ],
    "name:und_x_variant":[
        "Ch\u00ebrnyy Ruchey",
        "\u0427\u0451\u0440\u043d\u044b\u0439 \u0420\u0443\u0447\u0435\u0439"
    ],
    "wof:name":"Chernyy Ruchey",
    "wof:placetype":"locality"
},
  "geometry": {"coordinates":[29.0745,56.3717],"type":"Point"}
}