{
  "type": "Feature",
  "properties": {
    "gn:admin1_code":"71",
    "gn:asciiname":"Yermakova",
    "gn:country_code":"RU",
    "gn:dem":92,
    "gn:feature_class":"P",
    "gn:feature_code":"PPL",
    "gn:name":"Yermakova",
    "gn:population":0,
    "gn:timezone":"Asia/Yekaterinburg",
    "iso:country":"RU",
    "name:eng_x_preferred":[
        "Yermakova"
    ],
    "name:nor_x_preferred":[
        "Jermakova"
    ],
    "name:rus_x_preferred":[
        "\u0415\u0440\u043c\u0430\u043a\u043e\u0432\u0430"
    ],
    "wof:name":"Yermakova",
    "wof:placetype":"locality"
},
  "geometry": {"coordinates":[64.29375999999999,57.41315],"type":"Point"}
}