{
  "type": "Feature",
  "properties": {
    "gn:admin1_code":"77",
    "gn:asciiname":"Malinniki",
    "gn:country_code":"RU",
    "gn:dem":210,
    "gn:feature_class":"P",
    "gn:feature_code":"PPL",
    "gn:name":"Malinniki",
    "gn:population":3,
    "gn:timezone":"Europe/Moscow",
    "iso:country":"RU",
    "name:rus_x_preferred":[
        "\u041c\u0430\u043b\u0438\u043d\u043d\u0438\u043a\u0438"
    ],
    "name:und_x_variant":[
        "\u041c\u0430\u043b\u0438\u043d\u043d\u0438\u043a\u0438"
    ],
    "wof:name":"Malinniki",
    "wof:placetype":"locality",
    "wof:population":3
},
  "geometry": {"coordinates":[34.58575,56.66206],"type":"Point"}
}