{
  "type": "Feature",
  "properties": {
    "gn:admin1_code":"77",
    "gn:asciiname":"Borovlevo",
    "gn:country_code":"RU",
    "gn:dem":153,
    "gn:feature_class":"P",
    "gn:feature_code":"PPL",
    "gn:name":"Borovlevo",
    "gn:population":0,
    "gn:timezone":"Europe/Moscow",
    "iso:country":"RU",
    "name:nor_x_preferred":[
        "Borovlevo"
    ],
    "name:rus_x_preferred":[
        "\u0411\u043e\u0440\u043e\u0432\u043b\u0435\u0432\u043e"
    ],
    "wof:name":"Borovlevo",
    "wof:placetype":"locality"
},
  "geometry": {"coordinates":[35.93125999999999,56.79286999999999],"type":"Point"}
}