{
  "type": "Feature",
  "properties": {
    "gn:admin1_code":"56",
    "gn:asciiname":"Luzhnoy",
    "gn:country_code":"RU",
    "gn:dem":243,
    "gn:feature_class":"P",
    "gn:feature_code":"PPL",
    "gn:name":"Luzhnoy",
    "gn:population":0,
    "gn:timezone":"Europe/Moscow",
    "iso:country":"RU",
    "name:rus_x_preferred":[
        "\u041b\u0443\u0436\u043d\u043e\u0439"
    ],
    "name:und_x_variant":[
        "\u041b\u0443\u0436\u043d\u043e\u0439"
    ],
    "wof:name":"Luzhnoy",
    "wof:placetype":"locality"
},
  "geometry": {"coordinates":[37.51667,52.95],"type":"Point"}
}