{
  "type": "Feature",
  "properties": {
    "gn:admin1_code":"23",
    "gn:asciiname":"Iskrovo",
    "gn:country_code":"RU",
    "gn:dem":23,
    "gn:feature_class":"P",
    "gn:feature_code":"PPL",
    "gn:name":"Iskrovo",
    "gn:population":0,
    "gn:timezone":"Europe/Kaliningrad",
    "iso:country":"RU",
    "name:rus_x_preferred":[
        "\u0418\u0441\u043a\u0440\u043e\u0432\u043e"
    ],
    "name:und_x_variant":[
        "Ringels",
        "Iskrovo"
    ],
    "wof:name":"Iskrovo",
    "wof:placetype":"locality"
},
  "geometry": {"coordinates":[20.42779,54.87454],"type":"Point"}
}