{
  "type": "Feature",
  "properties": {
    "gn:admin1_code":"41.0",
    "gn:asciiname":"Belyy Kolodez'",
    "gn:country_code":"RU",
    "gn:dem":180,
    "gn:feature_class":"P",
    "gn:feature_code":"PPL",
    "gn:name":"Belyy Kolodez\u2019",
    "gn:population":0,
    "gn:timezone":"Europe/Moscow",
    "iso:country":"RU",
    "name:nor_x_preferred":[
        "Belyj Kolodez"
    ],
    "name:rus_x_preferred":[
        "\u0411\u0435\u043b\u044b\u0439 \u041a\u043e\u043b\u043e\u0434\u0435\u0437\u044c"
    ],
    "name:und_x_variant":[
        "Bely Kolodez",
        "Belyy Kolodez\u2019"
    ],
    "wof:name":"Belyy Kolodez'",
    "wof:placetype":"locality"
},
  "geometry": {"coordinates":[35.2307,52.0258],"type":"Point"}
}