{
  "type": "Feature",
  "properties": {
    "gn:admin1_code":"42",
    "gn:asciiname":"Lapsino",
    "gn:country_code":"RU",
    "gn:dem":77,
    "gn:feature_class":"P",
    "gn:feature_code":"PPL",
    "gn:name":"Lapsino",
    "gn:population":0,
    "gn:timezone":"Europe/Moscow",
    "iso:country":"RU",
    "name:rus_x_preferred":[
        "\u041b\u0430\u043f\u0441\u0438\u043d\u043e"
    ],
    "wof:name":"Lapsino",
    "wof:placetype":"locality"
},
  "geometry": {"coordinates":[28.43333,59.05],"type":"Point"}
}