{
  "type": "Feature",
  "properties": {
    "gn:admin1_code":"33.0",
    "gn:asciiname":"Ovchinnikovy",
    "gn:country_code":"RU",
    "gn:dem":158,
    "gn:feature_class":"P",
    "gn:feature_code":"PPL",
    "gn:name":"Ovchinnikovy",
    "gn:population":0,
    "gn:timezone":"Europe/Kirov",
    "iso:country":"RU",
    "name:rus_x_preferred":[
        "\u041e\u0432\u0447\u0438\u043d\u043d\u0438\u043a\u043e\u0432\u044b"
    ],
    "name:und_x_variant":[
        "\u041e\u0432\u0447\u0438\u043d\u043d\u0438\u043a\u043e\u0432\u044b"
    ],
    "wof:name":"Ovchinnikovy",
    "wof:placetype":"locality"
},
  "geometry": {"coordinates":[48.48139000000001,58.41944],"type":"Point"}
}