{
  "type": "Feature",
  "properties": {
    "gn:admin1_code":"69",
    "gn:asciiname":"Bityukovo",
    "gn:country_code":"RU",
    "gn:dem":204,
    "gn:feature_class":"P",
    "gn:feature_code":"PPL",
    "gn:name":"Bityukovo",
    "gn:population":0,
    "gn:timezone":"Europe/Moscow",
    "iso:country":"RU",
    "name:rus_x_preferred":[
        "\u0411\u0438\u0442\u044e\u043a\u043e\u0432\u043e"
    ],
    "name:und_x_variant":[
        "\u0411\u0438\u0442\u044e\u043a\u043e\u0432\u043e"
    ],
    "wof:name":"Bityukovo",
    "wof:placetype":"locality"
},
  "geometry": {"coordinates":[34.99439,55.7248],"type":"Point"}
}