{
  "type": "Feature",
  "properties": {
    "gn:country":"RU",
    "gn:fcode":"PPL",
    "gn:pop":3868,
    "iso:country":"RU",
    "name:eng_x_preferred":[
        "Shabrovskiy"
    ],
    "name:nor_x_preferred":[
        "Sjabrovskij"
    ],
    "name:rus_x_preferred":[
        "\u0428\u0430\u0431\u0440\u043e\u0432\u0441\u043a\u0438\u0439"
    ],
    "name:unk_x_variant":[
        "Pereskachka"
    ],
    "qs:name":"Shabrovskiy",
    "qs:photos_9r":0,
    "qs:photos_sr":0,
    "qs:pop_sr":"4",
    "wof:name":"Shabrovskiy",
    "wof:placetype":"locality",
    "wof:population":3868
},
  "geometry": {"coordinates":[60.58065,56.63597],"type":"Point"}
}