{
  "type": "Feature",
  "properties": {
    "gn:admin1_code":"84",
    "gn:asciiname":"Mololkin",
    "gn:country_code":"RU",
    "gn:dem":15,
    "gn:feature_class":"P",
    "gn:feature_code":"PPL",
    "gn:name":"Mololkin",
    "gn:population":0,
    "gn:timezone":"Europe/Volgograd",
    "iso:country":"RU",
    "name:rus_x_preferred":[
        "\u041c\u043e\u043b\u043e\u043b\u043a\u0438\u043d"
    ],
    "wof:name":"Mololkin",
    "wof:placetype":"locality"
},
  "geometry": {"coordinates":[46.92415,49.04689000000001],"type":"Point"}
}