{
  "type": "Feature",
  "properties": {
    "gn:admin1_code":"60",
    "gn:asciiname":"Lyubyantsy",
    "gn:country_code":"RU",
    "gn:dem":58,
    "gn:feature_class":"P",
    "gn:feature_code":"PPL",
    "gn:name":"Lyubyantsy",
    "gn:population":0,
    "gn:timezone":"Europe/Moscow",
    "iso:country":"RU",
    "name:rus_x_preferred":[
        "\u041b\u044e\u0431\u044f\u043d\u0446\u044b"
    ],
    "name:und_x_variant":[
        "\u041b\u044e\u0431\u044f\u043d\u0446\u044b"
    ],
    "wof:name":"Lyubyantsy",
    "wof:placetype":"locality"
},
  "geometry": {"coordinates":[30.0082,57.9177],"type":"Point"}
}