{
  "type": "Feature",
  "properties": {
    "gn:admin1_code":"85.0",
    "gn:asciiname":"Bonga",
    "gn:country_code":"RU",
    "gn:dem":146,
    "gn:feature_class":"P",
    "gn:feature_code":"PPL",
    "gn:name":"Bonga",
    "gn:population":0,
    "gn:timezone":"Europe/Moscow",
    "iso:country":"RU",
    "name:amh_x_preferred":[
        "\u1266\u1295\u130b"
    ],
    "name:deu_x_preferred":[
        "Bonga"
    ],
    "name:fra_x_preferred":[
        "Bonga"
    ],
    "name:ita_x_preferred":[
        "Bonga"
    ],
    "name:pol_x_preferred":[
        "Bonga"
    ],
    "name:ron_x_preferred":[
        "Bonga"
    ],
    "name:rus_x_preferred":[
        "\u0411\u043e\u043d\u0433\u0430"
    ],
    "name:und_x_variant":[
        "\u0411\u043e\u043d\u0433\u0430"
    ],
    "wof:name":"Bonga",
    "wof:placetype":"locality"
},
  "geometry": {"coordinates":[39.55,60.53333000000001],"type":"Point"}
}