{
  "type": "Feature",
  "properties": {
    "gn:admin1_code":"76",
    "gn:asciiname":"Ozerki",
    "gn:country_code":"RU",
    "gn:dem":219,
    "gn:feature_class":"P",
    "gn:feature_code":"PPL",
    "gn:name":"Ozerki",
    "gn:population":0,
    "gn:timezone":"Europe/Moscow",
    "iso:country":"RU",
    "name:rus_x_preferred":[
        "\u041e\u0437\u0435\u0440\u043a\u0438"
    ],
    "name:und_x_variant":[
        "\u041e\u0437\u0435\u0440\u043a\u0438"
    ],
    "wof:name":"Ozerki",
    "wof:placetype":"locality"
},
  "geometry": {"coordinates":[37.9228,53.51798],"type":"Point"}
}