{
  "type": "Feature",
  "properties": {
    "gn:admin1_code":"63",
    "gn:asciiname":"Kiseleva",
    "gn:cc2":"RU",
    "gn:country_code":"RU",
    "gn:dem":9,
    "gn:feature_class":"P",
    "gn:feature_code":"PPL",
    "gn:name":"Kisel\u00ebva",
    "gn:population":0,
    "gn:timezone":"Asia/Magadan",
    "iso:country":"RU",
    "name:rus_x_preferred":[
        "\u041a\u0438\u0441\u0435\u043b\u0451\u0432\u0430"
    ],
    "name:und_x_variant":[
        "Povarnya Kiseleva",
        "Kiselevo",
        "Kisel\u00ebva",
        "\u041a\u0438\u0441\u0435\u043b\u0451\u0432\u0430"
    ],
    "wof:name":"Kiseleva",
    "wof:placetype":"locality"
},
  "geometry": {"coordinates":[148.33333000000005,71.53333000000001],"type":"Point"}
}