{
  "type": "Feature",
  "properties": {
    "gn:admin1_code":"85",
    "gn:asciiname":"Tekstil'shchiki",
    "gn:country_code":"RU",
    "gn:dem":118,
    "gn:feature_class":"P",
    "gn:feature_code":"PPL",
    "gn:name":"Tekstil\u2019shchiki",
    "gn:population":0,
    "gn:timezone":"Europe/Moscow",
    "iso:country":"RU",
    "name:eng_x_preferred":[
        "Tekstil'shchiki"
    ],
    "name:nor_x_preferred":[
        "Tekstilsjtsjiki"
    ],
    "name:rus_x_preferred":[
        "\u0422\u0435\u043a\u0441\u0442\u0438\u043b\u044c\u0449\u0438\u043a\u0438"
    ],
    "name:und_x_variant":[
        "Tekstil\u2019shchiki"
    ],
    "wof:name":"Tekstil'shchiki",
    "wof:placetype":"locality"
},
  "geometry": {"coordinates":[42.82433,59.96131999999999],"type":"Point"}
}