{
  "type": "Feature",
  "properties": {
    "gn:admin1_code":"52.0",
    "gn:asciiname":"Duplya",
    "gn:country_code":"RU",
    "gn:dem":97,
    "gn:feature_class":"P",
    "gn:feature_code":"PPL",
    "gn:name":"Duplya",
    "gn:population":0,
    "gn:timezone":"Europe/Moscow",
    "iso:country":"RU",
    "name:rus_x_preferred":[
        "\u0414\u0443\u043f\u043b\u044f"
    ],
    "name:und_x_variant":[
        "\u0414\u0443\u043f\u043b\u044f"
    ],
    "wof:name":"Duplya",
    "wof:placetype":"locality"
},
  "geometry": {"coordinates":[32.96667,58.98333],"type":"Point"}
}