{
  "type": "Feature",
  "properties": {
    "gn:admin1_code":"85",
    "gn:asciiname":"Barovo",
    "gn:country_code":"RU",
    "gn:dem":113,
    "gn:feature_class":"P",
    "gn:feature_code":"PPL",
    "gn:name":"Barovo",
    "gn:population":0,
    "gn:timezone":"Europe/Moscow",
    "iso:country":"RU",
    "name:bul_x_preferred":[
        "\u0411\u0430\u0440\u043e\u0432\u043e"
    ],
    "name:fra_x_preferred":[
        "Barovo"
    ],
    "name:kat_x_preferred":[
        "\u10d1\u10d0\u10e0\u10dd\u10d5\u10dd"
    ],
    "name:mkd_x_preferred":[
        "\u0411\u0430\u0440\u043e\u0432\u043e"
    ],
    "name:por_x_preferred":[
        "Barovo"
    ],
    "name:rus_x_preferred":[
        "\u0411\u0430\u0440\u043e\u0432\u043e"
    ],
    "name:sqi_x_preferred":[
        "Barova"
    ],
    "name:srp_x_preferred":[
        "\u0411\u0430\u0440\u043e\u0432\u043e"
    ],
    "wof:name":"Barovo",
    "wof:placetype":"locality"
},
  "geometry": {"coordinates":[38.55351,59.1871],"type":"Point"}
}