{
  "type": "Feature",
  "properties": {
    "gn:admin1_code":"90.0",
    "gn:asciiname":"Bol'shoy Drovosek",
    "gn:country_code":"RU",
    "gn:dem":170,
    "gn:feature_class":"P",
    "gn:feature_code":"PPL",
    "gn:name":"Bol\u2019shoy Drovosek",
    "gn:population":0,
    "gn:timezone":"Asia/Yekaterinburg",
    "iso:country":"RU",
    "name:nor_x_preferred":[
        "Bolsjoj Drovosek"
    ],
    "name:rus_x_preferred":[
        "\u0411\u043e\u043b\u044c\u0448\u043e\u0439 \u0414\u0440\u043e\u0432\u043e\u0441\u0435\u043a"
    ],
    "name:und_x_variant":[
        "Bol\u2019shoy Drovosek"
    ],
    "wof:name":"Bol'shoy Drovosek",
    "wof:placetype":"locality"
},
  "geometry": {"coordinates":[56.5787,58.0833],"type":"Point"}
}