{
  "type": "Feature",
  "properties": {
    "gn:admin1_code":"11",
    "gn:asciiname":"Bom",
    "gn:country_code":"RU",
    "gn:dem":723,
    "gn:feature_class":"P",
    "gn:feature_code":"PPL",
    "gn:name":"Bom",
    "gn:population":0,
    "gn:timezone":"Asia/Irkutsk",
    "iso:country":"RU",
    "name:eng_x_preferred":[
        "Bom"
    ],
    "name:nor_x_preferred":[
        "Bom"
    ],
    "name:rus_x_preferred":[
        "\u0411\u043e\u043c"
    ],
    "name:und_x_variant":[
        "\u0411\u043e\u043c",
        "Bom"
    ],
    "wof:name":"Bom",
    "wof:placetype":"locality"
},
  "geometry": {"coordinates":[108.02885999999999,51.22474],"type":"Point"}
}