{
  "type": "Feature",
  "properties": {
    "gn:admin1_code":"51",
    "gn:asciiname":"Strelyazhka",
    "gn:country_code":"RU",
    "gn:dem":136,
    "gn:feature_class":"P",
    "gn:feature_code":"PPL",
    "gn:name":"Strelyazhka",
    "gn:population":0,
    "gn:timezone":"Europe/Moscow",
    "iso:country":"RU",
    "name:rus_x_preferred":[
        "\u0421\u0442\u0440\u0435\u043b\u044f\u0436\u043a\u0430"
    ],
    "name:und_x_variant":[
        "\u0421\u0442\u0440\u0435\u043b\u044f\u0436\u043a\u0430"
    ],
    "wof:name":"Strelyazhka",
    "wof:placetype":"locality"
},
  "geometry": {"coordinates":[46.0596,57.632],"type":"Point"}
}