{
  "type": "Feature",
  "properties": {
    "gn:admin1_code":"38",
    "gn:asciiname":"Magrovskiy",
    "gn:country_code":"RU",
    "gn:dem":54,
    "gn:feature_class":"P",
    "gn:feature_code":"PPL",
    "gn:name":"Magrovskiy",
    "gn:population":0,
    "gn:timezone":"Europe/Moscow",
    "iso:country":"RU",
    "name:rus_x_preferred":[
        "\u041c\u0430\u0433\u0440\u043e\u0432\u0441\u043a\u0438\u0439"
    ],
    "name:und_x_variant":[
        "\u041c\u0430\u0433\u0440\u043e\u0432\u0441\u043a\u0438\u0439"
    ],
    "wof:name":"Magrovskiy",
    "wof:placetype":"locality"
},
  "geometry": {"coordinates":[39.51667,46.51667],"type":"Point"}
}