{
  "type": "Feature",
  "properties": {
    "gn:country":"RU",
    "gn:fcode":"PPL",
    "gn:pop":37329,
    "iso:country":"RU",
    "name:ara_x_preferred":[
        "\u0628\u0631\u0648\u062a\u0641\u064a\u0646\u0648"
    ],
    "name:azb_x_preferred":[
        "\u067e\u0631\u0648\u062a\u0648\u06cc\u0646\u0648"
    ],
    "name:aze_x_preferred":[
        "Protvino"
    ],
    "name:bel_x_preferred":[
        "\u041f\u0440\u0430\u0442\u0432\u0456\u043d\u043e"
    ],
    "name:bul_x_preferred":[
        "\u041f\u0440\u043e\u0442\u0432\u0438\u043d\u043e"
    ],
    "name:chi_x_preferred":[
        "\u666e\u7f85\u7279\u7dad\u8afe"
    ],
    "name:chv_x_preferred":[
        "\u041f\u0440\u043e\u0442\u0432\u0438\u043d\u043e"
    ],
    "name:deu_x_preferred":[
        "Protwino"
    ],
    "name:dut_x_preferred":[
        "Protvino"
    ],
    "name:eng_x_preferred":[
        "Protvino"
    ],
    "name:epo_x_preferred":[
        "Protvino"
    ],
    "name:est_x_preferred":[
        "Protvino"
    ],
    "name:fas_x_preferred":[
        "\u067e\u0631\u0648\u062a\u0648\u06cc\u0646\u0648"
    ],
    "name:fin_x_preferred":[
        "Protvino"
    ],
    "name:fre_x_preferred":[
        "Protvino"
    ],
    "name:ger_x_preferred":[
        "Protwino"
    ],
    "name:hsb_x_preferred":[
        "Protwino"
    ],
    "name:ita_x_preferred":[
        "Protvino"
    ],
    "name:lit_x_preferred":[
        "Protvinas"
    ],
    "name:nno_x_preferred":[
        "Protvino"
    ],
    "name:nob_x_preferred":[
        "Protvino"
    ],
    "name:nor_x_preferred":[
        "Protvino"
    ],
    "name:per_x_preferred":[
        "\u067e\u0631\u0648\u062a\u0648\u06cc\u0646\u0648"
    ],
    "name:pnb_x_preferred":[
        "\u067e\u0631\u0648\u062a\u0648\u06cc\u0646\u0648"
    ],
    "name:pol_x_preferred":[
        "Protwino"
    ],
    "name:por_x_preferred":[
        "Protvino"
    ],
    "name:rus_x_preferred":[
        "\u041f\u0440\u043e\u0442\u0432\u0438\u043d\u043e"
    ],
    "name:srp_x_preferred":[
        "\u041f\u0440\u043e\u0442\u0432\u0438\u043d\u043e"
    ],
    "name:tat_x_preferred":[
        "\u041f\u0440\u043e\u0442\u0432\u0438\u043d\u043e"
    ],
    "name:tgk_x_preferred":[
        "\u041f\u0440\u043e\u0442\u0432\u0438\u043d\u043e"
    ],
    "name:tgl_x_preferred":[
        "Protvino"
    ],
    "name:tur_x_preferred":[
        "Protvino"
    ],
    "name:ukr_x_preferred":[
        "\u041f\u0440\u043e\u0442\u0432\u0456\u043d\u043e"
    ],
    "name:vie_x_preferred":[
        "Protvino"
    ],
    "name:war_x_preferred":[
        "Protvino"
    ],
    "name:xal_x_preferred":[
        "\u041f\u0440\u043e\u0442\u0432\u0438\u043d\u043e \u0431\u0430\u043b\u04bb\u0441\u043d"
    ],
    "name:zho_x_preferred":[
        "\u666e\u7f85\u7279\u7dad\u8afe"
    ],
    "qs:name":"Protvino",
    "qs:name_adm0":"Russia",
    "qs:name_adm1":"Moscow Oblast",
    "qs:photos":235,
    "qs:photos_1k":48,
    "qs:photos_9k":1,
    "qs:photos_9r":4,
    "qs:photos_all":235,
    "qs:photos_sr":4,
    "qs:placetype":"Town",
    "qs:pop_sr":"7",
    "wd:wordcount":876,
    "wof:name":"Protvino",
    "wof:placetype":"locality",
    "wof:population":37329
},
  "geometry": {"coordinates":[37.21584,54.8682],"type":"Point"}
}