{
  "type": "Feature",
  "properties": {
    "gn:admin1_code":"16",
    "gn:asciiname":"Kukary",
    "gn:country_code":"RU",
    "gn:dem":179,
    "gn:feature_class":"P",
    "gn:feature_code":"PPL",
    "gn:name":"Kukary",
    "gn:population":0,
    "gn:timezone":"Europe/Moscow",
    "iso:country":"RU",
    "name:fas_x_preferred":[
        "\u06a9\u0648\u06a9\u0631\u06cc"
    ],
    "name:msa_x_preferred":[
        "Kukary"
    ],
    "name:rus_x_preferred":[
        "\u041a\u0443\u043a\u0430\u0440\u044b"
    ],
    "wof:name":"Kukary",
    "wof:placetype":"locality"
},
  "geometry": {"coordinates":[47.66405,55.75959],"type":"Point"}
}