{
  "type": "Feature",
  "properties": {
    "gn:admin1_code":"8",
    "gn:asciiname":"Minzitarovo",
    "gn:country_code":"RU",
    "gn:dem":137,
    "gn:feature_class":"P",
    "gn:feature_code":"PPL",
    "gn:name":"Minzitarovo",
    "gn:population":0,
    "gn:timezone":"Asia/Yekaterinburg",
    "iso:country":"RU",
    "name:bak_x_preferred":[
        "\u041c\u0435\u04a3\u0439\u0435\u0442\u04d9\u0440"
    ],
    "name:che_x_preferred":[
        "\u041c\u0438\u043d\u0437\u0438\u0442\u0430\u0440\u043e\u0432\u043e"
    ],
    "name:chv_x_preferred":[
        "\u041c\u0438\u043d\u0437\u0438\u0442\u0430\u0440\u043e\u0432\u043e"
    ],
    "name:eng_x_preferred":[
        "Minzitarovo"
    ],
    "name:hye_x_preferred":[
        "\u0544\u056b\u0576\u0566\u056b\u057f\u0561\u0580\u0578\u057e\u0578"
    ],
    "name:kaz_x_preferred":[
        "\u041c\u0438\u043d\u0437\u0438\u0442\u0430\u0440"
    ],
    "name:kir_x_preferred":[
        "\u041c\u0438\u043d\u0437\u0438\u0442\u0430\u0440"
    ],
    "name:nor_x_preferred":[
        "Minzitarovo"
    ],
    "name:rus_x_preferred":[
        "\u041c\u0438\u043d\u0437\u0438\u0442\u0430\u0440\u043e\u0432\u043e"
    ],
    "name:tat_x_preferred":[
        "\u041c\u0438\u04a3\u0497\u0438\u0442\u04d9\u0440"
    ],
    "name:ukr_x_preferred":[
        "\u041c\u0456\u043d\u0437\u0456\u0442\u0430\u0440\u043e\u0432\u043e"
    ],
    "wof:name":"Minzitarovo",
    "wof:placetype":"locality"
},
  "geometry": {"coordinates":[56.4717,54.9185],"type":"Point"}
}