{
  "type": "Feature",
  "properties": {
    "gn:admin1_code":"60",
    "gn:asciiname":"Malaya Slobodka",
    "gn:country_code":"RU",
    "gn:dem":82,
    "gn:feature_class":"P",
    "gn:feature_code":"PPL",
    "gn:name":"Malaya Slobodka",
    "gn:population":0,
    "gn:timezone":"Europe/Moscow",
    "iso:country":"RU",
    "name:rus_x_preferred":[
        "\u041c\u0430\u043b\u0430\u044f \u0421\u043b\u043e\u0431\u043e\u0434\u043a\u0430"
    ],
    "wof:name":"Malaya Slobodka",
    "wof:placetype":"locality"
},
  "geometry": {"coordinates":[31.26667,57.08333],"type":"Point"}
}