{
  "type": "Feature",
  "properties": {
    "gn:admin1_code":"72.0",
    "gn:asciiname":"Bezukladovka",
    "gn:country_code":"RU",
    "gn:dem":173,
    "gn:feature_class":"P",
    "gn:feature_code":"PPL",
    "gn:name":"Bezukladovka",
    "gn:population":0,
    "gn:timezone":"Europe/Moscow",
    "iso:country":"RU",
    "name:nor_x_preferred":[
        "Bezukladovka"
    ],
    "name:rus_x_preferred":[
        "\u0411\u0435\u0437\u0443\u043a\u043b\u0430\u0434\u043e\u0432\u043a\u0430"
    ],
    "wof:name":"Bezukladovka",
    "wof:placetype":"locality"
},
  "geometry": {"coordinates":[41.11832,52.00351],"type":"Point"}
}