{
  "type": "Feature",
  "properties": {
    "gn:admin1_code":"33",
    "gn:asciiname":"Sarinka",
    "gn:country_code":"RU",
    "gn:dem":122,
    "gn:feature_class":"P",
    "gn:feature_code":"PPL",
    "gn:name":"Sarinka",
    "gn:population":0,
    "gn:timezone":"Europe/Kirov",
    "iso:country":"RU",
    "name:eng_x_preferred":[
        "Sarinka"
    ],
    "name:nor_x_preferred":[
        "Sarinka"
    ],
    "name:rus_x_preferred":[
        "\u0421\u0430\u0440\u0438\u043d\u043a\u0430"
    ],
    "wof:name":"Sarinka",
    "wof:placetype":"locality"
},
  "geometry": {"coordinates":[50.83453,57.08447],"type":"Point"}
}