{
  "type": "Feature",
  "properties": {
    "gn:admin1_code":"8",
    "gn:asciiname":"Staroarzamatovo",
    "gn:country_code":"RU",
    "gn:dem":175,
    "gn:feature_class":"P",
    "gn:feature_code":"PPL",
    "gn:name":"Staroarzamatovo",
    "gn:population":0,
    "gn:timezone":"Asia/Yekaterinburg",
    "iso:country":"RU",
    "name:eng_x_preferred":[
        "Staroarzamatovo"
    ],
    "name:nor_x_preferred":[
        "Staroarzamatovo"
    ],
    "name:rus_x_preferred":[
        "\u0421\u0442\u0430\u0440\u043e\u0430\u0440\u0437\u0430\u043c\u0430\u0442\u043e\u0432\u043e"
    ],
    "wof:name":"Staroarzamatovo",
    "wof:placetype":"locality"
},
  "geometry": {"coordinates":[56.09986,55.62237],"type":"Point"}
}