{
  "type": "Feature",
  "properties": {
    "gn:admin1_code":"52",
    "gn:asciiname":"Kipriya",
    "gn:country_code":"RU",
    "gn:dem":215,
    "gn:feature_class":"P",
    "gn:feature_code":"PPL",
    "gn:name":"Kipriya",
    "gn:population":0,
    "gn:timezone":"Europe/Moscow",
    "iso:country":"RU",
    "name:eng_x_preferred":[
        "Kipriya"
    ],
    "name:nor_x_preferred":[
        "Kipria"
    ],
    "name:rus_x_preferred":[
        "\u041a\u0438\u043f\u0440\u0438\u044f"
    ],
    "wof:name":"Kipriya",
    "wof:placetype":"locality"
},
  "geometry": {"coordinates":[33.82372,58.99027],"type":"Point"}
}