{
  "type": "Feature",
  "properties": {
    "gn:admin1_code":"42",
    "gn:asciiname":"Kureshi",
    "gn:country_code":"RU",
    "gn:dem":73,
    "gn:feature_class":"P",
    "gn:feature_code":"PPL",
    "gn:name":"Kureshi",
    "gn:population":0,
    "gn:timezone":"Europe/Moscow",
    "iso:country":"RU",
    "name:rus_x_preferred":[
        "\u041a\u0443\u0440\u0435\u0448\u0438"
    ],
    "wof:name":"Kureshi",
    "wof:placetype":"locality"
},
  "geometry": {"coordinates":[28.59797,59.03961],"type":"Point"}
}