{
  "type": "Feature",
  "properties": {
    "gn:admin1_code":"81",
    "gn:asciiname":"Volchanka",
    "gn:country_code":"RU",
    "gn:dem":125,
    "gn:feature_class":"P",
    "gn:feature_code":"PPL",
    "gn:name":"Volchanka",
    "gn:population":0,
    "gn:timezone":"Europe/Ulyanovsk",
    "iso:country":"RU",
    "name:eng_x_preferred":[
        "Volchanka"
    ],
    "name:nor_x_preferred":[
        "Voltsjanka"
    ],
    "name:rus_x_preferred":[
        "\u0412\u043e\u043b\u0447\u0430\u043d\u043a\u0430"
    ],
    "wof:name":"Volchanka",
    "wof:placetype":"locality"
},
  "geometry": {"coordinates":[48.15194,53.01139000000001],"type":"Point"}
}