{
  "type": "Feature",
  "properties": {
    "gn:admin1_code":"70.0",
    "gn:asciiname":"Fazannyy",
    "gn:country_code":"RU",
    "gn:dem":301,
    "gn:feature_class":"P",
    "gn:feature_code":"PPL",
    "gn:name":"Fazannyy",
    "gn:population":0,
    "gn:timezone":"Europe/Moscow",
    "iso:country":"RU",
    "name:rus_x_preferred":[
        "\u0424\u0430\u0437\u0430\u043d\u043d\u044b\u0439"
    ],
    "name:und_x_variant":[
        "\u0424\u0430\u0437\u0430\u043d\u043d\u044b\u0439"
    ],
    "wof:name":"Fazannyy",
    "wof:placetype":"locality"
},
  "geometry": {"coordinates":[43.59167,44.04167],"type":"Point"}
}