{
  "type": "Feature",
  "properties": {
    "gn:admin1_code":"51",
    "gn:asciiname":"Sosnovka",
    "gn:country_code":"RU",
    "gn:dem":158,
    "gn:feature_class":"P",
    "gn:feature_code":"PPL",
    "gn:name":"Sosnovka",
    "gn:population":0,
    "gn:timezone":"Europe/Moscow",
    "iso:country":"RU",
    "name:bak_x_preferred":[
        "\u0421\u043e\u0441\u043d\u043e\u0432\u043a\u0430"
    ],
    "name:bel_x_preferred":[
        "\u0421\u0430\u0441\u043d\u043e\u045e\u043a\u0430"
    ],
    "name:ceb_x_preferred":[
        "Sosnovka"
    ],
    "name:hun_x_preferred":[
        "Szosznovka"
    ],
    "name:hye_x_preferred":[
        "\u054d\u0578\u057d\u0576\u0578\u057e\u056f\u0561"
    ],
    "name:ita_x_preferred":[
        "Sosnovka"
    ],
    "name:kaz_x_preferred":[
        "\u0421\u043e\u0441\u043d\u043e\u0432\u043a\u0430"
    ],
    "name:lit_x_preferred":[
        "Sosnuvka"
    ],
    "name:rus_x_preferred":[
        "\u0421\u043e\u0441\u043d\u043e\u0432\u043a\u0430"
    ],
    "name:swe_x_preferred":[
        "Sosnovka"
    ],
    "name:tat_x_preferred":[
        "\u0421\u043e\u0441\u043d\u043e\u0432\u043a\u0430"
    ],
    "name:ukr_x_preferred":[
        "\u0421\u043e\u0441\u043d\u043e\u0432\u043a\u0430"
    ],
    "name:und_x_variant":[
        "Krasnoselovo",
        "Krasnoselova",
        "Sosnovka",
        "\u0421\u043e\u0441\u043d\u043e\u0432\u043a\u0430"
    ],
    "wof:name":"Sosnovka",
    "wof:placetype":"locality"
},
  "geometry": {"coordinates":[44.58048,55.88608000000001],"type":"Point"}
}