{
  "type": "Feature",
  "properties": {
    "gn:admin1_code":"61.0",
    "gn:asciiname":"Bogatov",
    "gn:country_code":"RU",
    "gn:dem":36,
    "gn:feature_class":"P",
    "gn:feature_code":"PPL",
    "gn:name":"Bogatov",
    "gn:population":0,
    "gn:timezone":"Europe/Moscow",
    "iso:country":"RU",
    "name:eng_x_preferred":[
        "Bogatov"
    ],
    "name:nor_x_preferred":[
        "Bogatov"
    ],
    "name:rus_x_preferred":[
        "\u0411\u043e\u0433\u0430\u0442\u043e\u0432"
    ],
    "wof:name":"Bogatov",
    "wof:placetype":"locality"
},
  "geometry": {"coordinates":[40.79393,48.09691],"type":"Point"}
}