{
  "type": "Feature",
  "properties": {
    "gn:admin1_code":"40",
    "gn:asciiname":"Ostrovnoye",
    "gn:country_code":"RU",
    "gn:dem":128,
    "gn:feature_class":"P",
    "gn:feature_code":"PPL",
    "gn:name":"Ostrovnoye",
    "gn:population":0,
    "gn:timezone":"Asia/Yekaterinburg",
    "iso:country":"RU",
    "name:rus_x_preferred":[
        "\u041e\u0441\u0442\u0440\u043e\u0432\u043d\u043e\u0435"
    ],
    "name:und_x_variant":[
        "\u041e\u0441\u0442\u0440\u043e\u0432\u043d\u043e\u0435"
    ],
    "wof:name":"Ostrovnoye",
    "wof:placetype":"locality"
},
  "geometry": {"coordinates":[66.78278,55.21528000000001],"type":"Point"}
}