{
  "type": "Feature",
  "properties": {
    "gn:country":"RU",
    "gn:fcode":"PPL",
    "gn:pop":3359,
    "iso:country":"RU",
    "name:nor_x_preferred":[
        "Kara-Tjube"
    ],
    "name:rus_x_preferred":[
        "\u041a\u0430\u0440\u0430-\u0422\u044e\u0431\u0435"
    ],
    "name:unk_x_variant":[
        "\u041a\u0430\u0440\u0430-\u0422\u044e\u0431\u0435"
    ],
    "qs:name":"Kara-Tyube",
    "qs:photos_9r":0,
    "qs:photos_sr":0,
    "qs:pop_sr":"4",
    "wd:wordcount":13,
    "wof:name":"Kara-Tyube",
    "wof:placetype":"locality",
    "wof:population":3359
},
  "geometry": {"coordinates":[45.43694,44.63361],"type":"Point"}
}