{
  "type": "Feature",
  "properties": {
    "gn:admin1_code":"13",
    "gn:asciiname":"Vpered",
    "gn:country_code":"RU",
    "gn:dem":364,
    "gn:feature_class":"P",
    "gn:feature_code":"PPL",
    "gn:name":"Vper\u00ebd",
    "gn:population":0,
    "gn:timezone":"Asia/Yekaterinburg",
    "iso:country":"RU",
    "name:rus_x_preferred":[
        "\u0412\u043f\u0435\u0440\u0451\u0434"
    ],
    "name:und_x_variant":[
        "Vper\u00ebd"
    ],
    "wof:name":"Vpered",
    "wof:placetype":"locality"
},
  "geometry": {"coordinates":[59.5236,53.2186],"type":"Point"}
}