{
  "type": "Feature",
  "properties": {
    "gn:admin1_code":"85",
    "gn:asciiname":"Orlovskaya",
    "gn:country_code":"RU",
    "gn:dem":157,
    "gn:feature_class":"P",
    "gn:feature_code":"PPL",
    "gn:name":"Orlovskaya",
    "gn:population":0,
    "gn:timezone":"Europe/Moscow",
    "iso:country":"RU",
    "name:rus_x_preferred":[
        "\u041e\u0440\u043b\u043e\u0432\u0441\u043a\u0430\u044f"
    ],
    "name:und_x_variant":[
        "\u041e\u0440\u043b\u043e\u0432\u0441\u043a\u0430\u044f"
    ],
    "wof:name":"Orlovskaya",
    "wof:placetype":"locality"
},
  "geometry": {"coordinates":[41.67727,60.21876999999999],"type":"Point"}
}