{
  "type": "Feature",
  "properties": {
    "gn:admin1_code":"37",
    "gn:asciiname":"Dyurbenevo",
    "gn:country_code":"RU",
    "gn:dem":179,
    "gn:feature_class":"P",
    "gn:feature_code":"PPL",
    "gn:name":"Dyurben\u00ebvo",
    "gn:population":0,
    "gn:timezone":"Europe/Moscow",
    "iso:country":"RU",
    "name:rus_x_preferred":[
        "\u0414\u044e\u0440\u0431\u0435\u043d\u0451\u0432\u043e"
    ],
    "name:und_x_variant":[
        "Dyurben\u00ebvo"
    ],
    "wof:name":"Dyurbenevo",
    "wof:placetype":"locality"
},
  "geometry": {"coordinates":[42.7208,58.6827],"type":"Point"}
}