{
  "type": "Feature",
  "properties": {
    "gn:admin1_code":"77",
    "gn:asciiname":"Dushino",
    "gn:country_code":"RU",
    "gn:dem":158,
    "gn:feature_class":"P",
    "gn:feature_code":"PPL",
    "gn:name":"Dushino",
    "gn:population":0,
    "gn:timezone":"Europe/Moscow",
    "iso:country":"RU",
    "name:rus_x_preferred":[
        "\u0414\u0443\u0448\u0438\u043d\u043e"
    ],
    "name:und_x_variant":[
        "\u0414\u0443\u0448\u0438\u043d\u043e"
    ],
    "wof:name":"Dushino",
    "wof:placetype":"locality"
},
  "geometry": {"coordinates":[37.2892,57.5437],"type":"Point"}
}