{
  "type": "Feature",
  "properties": {
    "gn:admin1_code":"85.0",
    "gn:asciiname":"Belovo",
    "gn:country_code":"RU",
    "gn:dem":206,
    "gn:feature_class":"P",
    "gn:feature_code":"PPL",
    "gn:name":"Belovo",
    "gn:population":0,
    "gn:timezone":"Europe/Moscow",
    "iso:country":"RU",
    "name:nor_x_preferred":[
        "Belovo"
    ],
    "name:rus_x_preferred":[
        "\u0411\u0435\u043b\u043e\u0432\u043e"
    ],
    "wof:name":"Belovo",
    "wof:placetype":"locality"
},
  "geometry": {"coordinates":[40.98333,59.86666999999999],"type":"Point"}
}