{
  "type": "Feature",
  "properties": {
    "gn:admin1_code":"63",
    "gn:asciiname":"Suchchun",
    "gn:cc2":"RU",
    "gn:country_code":"RU",
    "gn:dem":26,
    "gn:feature_class":"P",
    "gn:feature_code":"PPL",
    "gn:name":"Suchchun",
    "gn:population":0,
    "gn:timezone":"Asia/Magadan",
    "iso:country":"RU",
    "name:eng_x_preferred":[
        "Suchchun"
    ],
    "name:nor_x_preferred":[
        "Sutsjtsjino"
    ],
    "name:rus_x_preferred":[
        "\u0421\u0443\u0447\u0447\u0438\u043d\u043e"
    ],
    "name:rus_x_variant":[
        "\u0421\u0443\u0447\u0447\u0443\u043d"
    ],
    "name:und_x_variant":[
        "Sutchan",
        "Suchchun",
        "\u0421\u0443\u0447\u0447\u0443\u043d"
    ],
    "wof:name":"Suchchun",
    "wof:placetype":"locality"
},
  "geometry": {"coordinates":[152.33333000000005,68.26666999999999],"type":"Point"}
}