{
  "type": "Feature",
  "properties": {
    "gn:admin1_code":"85",
    "gn:asciiname":"Afanasovo",
    "gn:country_code":"RU",
    "gn:dem":155,
    "gn:feature_class":"P",
    "gn:feature_code":"PPL",
    "gn:name":"Afanasovo",
    "gn:population":0,
    "gn:timezone":"Europe/Moscow",
    "iso:country":"RU",
    "name:rus_x_preferred":[
        "\u0410\u0444\u0430\u043d\u0430\u0441\u043e\u0432\u043e"
    ],
    "wof:name":"Afanasovo",
    "wof:placetype":"locality"
},
  "geometry": {"coordinates":[36.066,59.7793],"type":"Point"}
}