{
  "type": "Feature",
  "properties": {
    "gn:admin1_code":"25.0",
    "gn:asciiname":"Gavrilovka",
    "gn:country_code":"RU",
    "gn:dem":202,
    "gn:feature_class":"P",
    "gn:feature_code":"PPL",
    "gn:name":"Gavrilovka",
    "gn:population":0,
    "gn:timezone":"Europe/Moscow",
    "iso:country":"RU",
    "name:eng_x_preferred":[
        "Gavrilovka"
    ],
    "name:nor_x_preferred":[
        "Gavrilovka"
    ],
    "name:rus_x_preferred":[
        "\u0413\u0430\u0432\u0440\u0438\u043b\u043e\u0432\u043a\u0430"
    ],
    "name:und_x_variant":[
        "\u0413\u0430\u0432\u0440\u0438\u043b\u043e\u0432\u043a\u0430",
        "Gavrilovka"
    ],
    "wof:name":"Gavrilovka",
    "wof:placetype":"locality"
},
  "geometry": {"coordinates":[34.55306,54.06611],"type":"Point"}
}