{
  "type": "Feature",
  "properties": {
    "gn:admin1_code":"05",
    "gn:asciiname":"Pereselenets",
    "gn:country_code":"RU",
    "gn:dem":333,
    "gn:feature_class":"P",
    "gn:feature_code":"PPL",
    "gn:name":"Pereselenets",
    "gn:population":0,
    "gn:timezone":"Asia/Yakutsk",
    "iso:country":"RU",
    "name:eng_x_preferred":[
        "Pereselenets"
    ],
    "name:nor_x_preferred":[
        "Pereselenets"
    ],
    "name:rus_x_preferred":[
        "\u041f\u0435\u0440\u0435\u0441\u0435\u043b\u0435\u043d\u0435\u0446"
    ],
    "name:und_x_variant":[
        "Pereselencheski",
        "Pereselencheskiy",
        "\u041f\u0435\u0440\u0435\u0441\u0435\u043b\u0435\u043d\u0435\u0446",
        "Pereselenets"
    ],
    "wof:name":"Pereselenets",
    "wof:placetype":"locality"
},
  "geometry": {"coordinates":[127.09039,52.37875],"type":"Point"}
}