{
  "type": "Feature",
  "properties": {
    "gn:admin1_code":"40.0",
    "gn:asciiname":"Ganicheva",
    "gn:country_code":"RU",
    "gn:dem":69,
    "gn:feature_class":"P",
    "gn:feature_code":"PPL",
    "gn:name":"Ganicheva",
    "gn:population":0,
    "gn:timezone":"Asia/Yekaterinburg",
    "iso:country":"RU",
    "name:rus_x_preferred":[
        "\u0413\u0430\u043d\u0438\u0447\u0435\u0432\u0430"
    ],
    "wof:name":"Ganicheva",
    "wof:placetype":"locality"
},
  "geometry": {"coordinates":[64.5686,56.153],"type":"Point"}
}