{
  "type": "Feature",
  "properties": {
    "gn:admin1_code":"33.0",
    "gn:asciiname":"Zdravnitsa",
    "gn:country_code":"RU",
    "gn:dem":152,
    "gn:feature_class":"P",
    "gn:feature_code":"PPL",
    "gn:name":"Zdravnitsa",
    "gn:population":0,
    "gn:timezone":"Europe/Kirov",
    "iso:country":"RU",
    "name:rus_x_preferred":[
        "\u0417\u0434\u0440\u0430\u0432\u043d\u0438\u0446\u0430"
    ],
    "wof:name":"Zdravnitsa",
    "wof:placetype":"locality"
},
  "geometry": {"coordinates":[50.3397,58.4648],"type":"Point"}
}