{
  "type": "Feature",
  "properties": {
    "gn:admin1_code":"51",
    "gn:asciiname":"Tatarka",
    "gn:country_code":"RU",
    "gn:dem":131,
    "gn:feature_class":"P",
    "gn:feature_code":"PPL",
    "gn:name":"Tatarka",
    "gn:population":0,
    "gn:timezone":"Europe/Moscow",
    "iso:country":"RU",
    "name:eng_x_preferred":[
        "Tatarka"
    ],
    "name:nor_x_preferred":[
        "Tatarka"
    ],
    "name:rus_x_preferred":[
        "\u0422\u0430\u0442\u0430\u0440\u043a\u0430"
    ],
    "wof:name":"Tatarka",
    "wof:placetype":"locality"
},
  "geometry": {"coordinates":[44.2056,56.9989],"type":"Point"}
}