{
  "type": "Feature",
  "properties": {
    "gn:admin1_code":"21",
    "gn:asciiname":"Ostretsovo",
    "gn:country_code":"RU",
    "gn:dem":120,
    "gn:feature_class":"P",
    "gn:feature_code":"PPL",
    "gn:name":"Ostretsovo",
    "gn:population":0,
    "gn:timezone":"Europe/Moscow",
    "iso:country":"RU",
    "name:eng_x_preferred":[
        "Ostretsovo"
    ],
    "name:nor_x_preferred":[
        "Ostretsovo"
    ],
    "name:rus_x_preferred":[
        "\u041e\u0441\u0442\u0440\u0435\u0446\u043e\u0432\u043e"
    ],
    "wof:name":"Ostretsovo",
    "wof:placetype":"locality"
},
  "geometry": {"coordinates":[41.55797000000001,57.20414],"type":"Point"}
}