{
  "type": "Feature",
  "properties": {
    "gn:admin1_code":"47",
    "gn:asciiname":"Voronovo",
    "gn:country_code":"RU",
    "gn:dem":142,
    "gn:feature_class":"P",
    "gn:feature_code":"PPL",
    "gn:name":"Voronovo",
    "gn:population":0,
    "gn:timezone":"Europe/Moscow",
    "iso:country":"RU",
    "name:und_x_variant":[
        "Voronova",
        "Voronovo"
    ],
    "wof:name":"Voronovo",
    "wof:placetype":"locality"
},
  "geometry": {"coordinates":[38.57892,55.5996],"type":"Point"}
}