{
  "type": "Feature",
  "properties": {
    "gn:country":"RU",
    "gn:fcode":"PPL",
    "gn:population":0,
    "iso:country":"RU",
    "name:rus_x_preferred":[
        "\u042e\u043d\u044b\u0439 \u041b\u0435\u043d\u0438\u043d\u0435\u0446"
    ],
    "qs:name":"Yunyy Leninets",
    "qs:name_adm0":"Russia",
    "qs:name_adm1":"Novosibirsk Oblast",
    "qs:photos_9r":0,
    "qs:photos_sr":0,
    "qs:placetype":"Town",
    "qs:pop_sr":"0",
    "wof:name":"Yunyy Leninets",
    "wof:placetype":"locality",
    "wof:population":0
},
  "geometry": {"coordinates":[83.0102,54.891],"type":"Point"}
}