{
  "type": "Feature",
  "properties": {
    "gn:admin1_code":"56",
    "gn:asciiname":"Stanovoy Kolodez'",
    "gn:country_code":"RU",
    "gn:dem":241,
    "gn:feature_class":"P",
    "gn:feature_code":"PPL",
    "gn:name":"Stanovoy Kolodez\u2019",
    "gn:population":0,
    "gn:timezone":"Europe/Moscow",
    "iso:country":"RU",
    "name:eng_x_preferred":[
        "Stanovoy Kolodez'"
    ],
    "name:nor_x_preferred":[
        "Stanovoj Kolodez"
    ],
    "name:rus_x_preferred":[
        "\u0421\u0442\u0430\u043d\u043e\u0432\u043e\u0439 \u041a\u043e\u043b\u043e\u0434\u0435\u0437\u044c"
    ],
    "name:und_x_variant":[
        "Butyrki",
        "\u0421\u0442\u0430\u043d\u043e\u0432\u043e\u0439 \u041a\u043e\u043b\u043e\u0434\u0435\u0437\u044c",
        "Stanovoy Kolodez\u2019"
    ],
    "wof:name":"Stanovoy Kolodez'",
    "wof:placetype":"locality"
},
  "geometry": {"coordinates":[36.26217000000001,52.82929],"type":"Point"}
}