{
  "type": "Feature",
  "properties": {
    "gn:admin1_code":"8.0",
    "gn:asciiname":"Ayuchevo",
    "gn:country_code":"RU",
    "gn:dem":141,
    "gn:feature_class":"P",
    "gn:feature_code":"PPL",
    "gn:name":"Ayuchevo",
    "gn:population":0,
    "gn:timezone":"Asia/Yekaterinburg",
    "iso:country":"RU",
    "name:eng_x_preferred":[
        "Ayuchevo"
    ],
    "name:nor_x_preferred":[
        "Ajutsjevo"
    ],
    "name:rus_x_preferred":[
        "\u0410\u044e\u0447\u0435\u0432\u043e"
    ],
    "wof:name":"Ayuchevo",
    "wof:placetype":"locality"
},
  "geometry": {"coordinates":[55.78454,53.43737],"type":"Point"}
}