{
  "type": "Feature",
  "properties": {
    "gn:admin1_code":"30",
    "gn:asciiname":"Bichi",
    "gn:country_code":"RU",
    "gn:dem":20,
    "gn:feature_class":"P",
    "gn:feature_code":"PPL",
    "gn:name":"Bichi",
    "gn:population":0,
    "gn:timezone":"Asia/Vladivostok",
    "iso:country":"RU",
    "name:ceb_x_preferred":[
        "Bichi"
    ],
    "name:eng_x_preferred":[
        "Bichi"
    ],
    "name:fra_x_preferred":[
        "Bichi"
    ],
    "name:hau_x_preferred":[
        "Bichi"
    ],
    "name:ita_x_preferred":[
        "Bichi"
    ],
    "name:nor_x_preferred":[
        "Bitsji"
    ],
    "name:por_x_preferred":[
        "Bichi"
    ],
    "name:rus_x_preferred":[
        "\u0411\u0438\u0447\u0438"
    ],
    "name:spa_x_preferred":[
        "Bichi"
    ],
    "wof:name":"Bichi",
    "wof:placetype":"locality"
},
  "geometry": {"coordinates":[137.65651,50.74896],"type":"Point"}
}