{
  "type": "Feature",
  "properties": {
    "gn:admin1_code":"8.0",
    "gn:asciiname":"Demskiy",
    "gn:country_code":"RU",
    "gn:dem":143,
    "gn:feature_class":"P",
    "gn:feature_code":"PPL",
    "gn:name":"D\u00ebmskiy",
    "gn:population":0,
    "gn:timezone":"Asia/Yekaterinburg",
    "iso:country":"RU",
    "name:eng_x_preferred":[
        "D\u00ebmskiy"
    ],
    "name:nor_x_preferred":[
        "Demskij"
    ],
    "name:rus_x_preferred":[
        "\u0414\u0435\u043c\u0441\u043a\u0438\u0439"
    ],
    "name:rus_x_variant":[
        "\u0414\u0451\u043c\u0441\u043a\u0438\u0439"
    ],
    "name:und_x_variant":[
        "D\u00ebmskiy",
        "\u0414\u0451\u043c\u0441\u043a\u0438\u0439"
    ],
    "wof:name":"Demskiy",
    "wof:placetype":"locality"
},
  "geometry": {"coordinates":[54.4499,53.5354],"type":"Point"}
}