{
  "type": "Feature",
  "properties": {
    "gn:admin1_code":"72",
    "gn:asciiname":"Shushpan-Verstovka",
    "gn:country_code":"RU",
    "gn:dem":158,
    "gn:feature_class":"P",
    "gn:feature_code":"PPL",
    "gn:name":"Shushpan-Verstovka",
    "gn:population":0,
    "gn:timezone":"Europe/Moscow",
    "iso:country":"RU",
    "name:rus_x_preferred":[
        "\u0428\u0443\u0448\u043f\u0430\u043d-\u0412\u0435\u0440\u0441\u0442\u043e\u0432\u043a\u0430"
    ],
    "name:und_x_variant":[
        "\u0428\u0443\u0448\u043f\u0430\u043d-\u0412\u0435\u0440\u0441\u0442\u043e\u0432\u043a\u0430"
    ],
    "wof:name":"Shushpan-Verstovka",
    "wof:placetype":"locality"
},
  "geometry": {"coordinates":[40.7379,53.477],"type":"Point"}
}