{
  "type": "Feature",
  "properties": {
    "gn:admin1_code":"51",
    "gn:asciiname":"Bakhtino",
    "gn:country_code":"RU",
    "gn:dem":116,
    "gn:feature_class":"P",
    "gn:feature_code":"PPL",
    "gn:name":"Bakhtino",
    "gn:population":0,
    "gn:timezone":"Europe/Moscow",
    "iso:country":"RU",
    "name:rus_x_preferred":[
        "\u0411\u0430\u0445\u0442\u0438\u043d\u043e"
    ],
    "name:und_x_variant":[
        "\u0411\u0430\u0445\u0442\u0438\u043d\u043e"
    ],
    "wof:name":"Bakhtino",
    "wof:placetype":"locality"
},
  "geometry": {"coordinates":[46.5829,57.0604],"type":"Point"}
}