{
  "type": "Feature",
  "properties": {
    "gn:admin1_code":"52",
    "gn:asciiname":"Sharapovo",
    "gn:country_code":"RU",
    "gn:dem":126,
    "gn:feature_class":"P",
    "gn:feature_code":"PPL",
    "gn:name":"Sharapovo",
    "gn:population":0,
    "gn:timezone":"Europe/Moscow",
    "iso:country":"RU",
    "name:rus_x_preferred":[
        "\u0428\u0430\u0440\u0430\u043f\u043e\u0432\u043e"
    ],
    "wof:name":"Sharapovo",
    "wof:placetype":"locality"
},
  "geometry": {"coordinates":[34.08333,58.33333],"type":"Point"}
}