{
  "type": "Feature",
  "properties": {
    "gn:admin1_code":"40",
    "gn:asciiname":"Pervomayka",
    "gn:country_code":"RU",
    "gn:dem":173,
    "gn:feature_class":"P",
    "gn:feature_code":"PPL",
    "gn:name":"Pervomayka",
    "gn:population":0,
    "gn:timezone":"Asia/Yekaterinburg",
    "iso:country":"RU",
    "name:ceb_x_preferred":[
        "Pervomayka"
    ],
    "name:rus_x_preferred":[
        "\u041f\u0435\u0440\u0432\u043e\u043c\u0430\u0439\u043a\u0430"
    ],
    "name:swe_x_preferred":[
        "Pervomayka"
    ],
    "wof:name":"Pervomayka",
    "wof:placetype":"locality"
},
  "geometry": {"coordinates":[63.2561,54.3402],"type":"Point"}
}