{
  "type": "Feature",
  "properties": {
    "gn:admin1_code":"77",
    "gn:asciiname":"Burtsevo",
    "gn:country_code":"RU",
    "gn:dem":215,
    "gn:feature_class":"P",
    "gn:feature_code":"PPL",
    "gn:name":"Burtsevo",
    "gn:population":0,
    "gn:timezone":"Europe/Moscow",
    "iso:country":"RU",
    "name:rus_x_preferred":[
        "\u0411\u0443\u0440\u0446\u0435\u0432\u043e"
    ],
    "name:und_x_variant":[
        "\u0411\u0443\u0440\u0446\u0435\u0432\u043e"
    ],
    "wof:name":"Burtsevo",
    "wof:placetype":"locality"
},
  "geometry": {"coordinates":[33.34361,56.67972],"type":"Point"}
}