{
  "type": "Feature",
  "properties": {
    "gn:admin1_code":"77",
    "gn:asciiname":"Slabtsovo",
    "gn:country_code":"RU",
    "gn:dem":179,
    "gn:feature_class":"P",
    "gn:feature_code":"PPL",
    "gn:name":"Slabtsovo",
    "gn:population":0,
    "gn:timezone":"Europe/Moscow",
    "iso:country":"RU",
    "name:rus_x_preferred":[
        "\u0421\u043b\u0430\u0431\u0446\u043e\u0432\u043e"
    ],
    "name:und_x_variant":[
        "Slobodtsevo",
        "Sloobodtseva",
        "Slobtsovo",
        "Slabtsovo"
    ],
    "wof:name":"Slabtsovo",
    "wof:placetype":"locality"
},
  "geometry": {"coordinates":[34.70630999999999,56.19128000000001],"type":"Point"}
}