{
  "type": "Feature",
  "properties": {
    "gn:admin1_code":"6",
    "gn:asciiname":"Ozero Lomovoye",
    "gn:country_code":"RU",
    "gn:dem":103,
    "gn:feature_class":"P",
    "gn:feature_code":"PPL",
    "gn:name":"Ozero Lomovoye",
    "gn:population":0,
    "gn:timezone":"Europe/Moscow",
    "iso:country":"RU",
    "name:rus_x_preferred":[
        "\u041e\u0437\u0435\u0440\u043e \u041b\u043e\u043c\u043e\u0432\u043e\u0435"
    ],
    "wof:name":"Ozero Lomovoye",
    "wof:placetype":"locality"
},
  "geometry": {"coordinates":[40.65,64.03333000000001],"type":"Point"}
}