{
  "type": "Feature",
  "properties": {
    "gn:admin1_code":"85",
    "gn:asciiname":"Lukovchina",
    "gn:country_code":"RU",
    "gn:dem":151,
    "gn:feature_class":"P",
    "gn:feature_code":"PPL",
    "gn:name":"Lukovchina",
    "gn:population":0,
    "gn:timezone":"Europe/Moscow",
    "iso:country":"RU",
    "name:rus_x_preferred":[
        "\u041b\u0443\u043a\u043e\u0432\u0447\u0438\u043d\u0430"
    ],
    "wof:name":"Lukovchina",
    "wof:placetype":"locality"
},
  "geometry": {"coordinates":[38.0877,60.2974],"type":"Point"}
}