{
  "type": "Feature",
  "properties": {
    "gn:admin1_code":"65",
    "gn:asciiname":"Podlesnyy",
    "gn:country_code":"RU",
    "gn:dem":33,
    "gn:feature_class":"P",
    "gn:feature_code":"PPL",
    "gn:name":"Podlesnyy",
    "gn:population":0,
    "gn:timezone":"Europe/Samara",
    "iso:country":"RU",
    "name:rus_x_preferred":[
        "\u041f\u043e\u0434\u043b\u0435\u0441\u043d\u044b\u0439"
    ],
    "name:und_x_variant":[
        "Podlesny",
        "Podlesnyy"
    ],
    "wof:name":"Podlesnyy",
    "wof:placetype":"locality"
},
  "geometry": {"coordinates":[50.59372000000001,53.16651],"type":"Point"}
}