{
  "type": "Feature",
  "properties": {
    "gn:admin1_code":"67.0",
    "gn:asciiname":"Bobov",
    "gn:country_code":"RU",
    "gn:dem":99,
    "gn:feature_class":"P",
    "gn:feature_code":"PPL",
    "gn:name":"Bobov",
    "gn:population":0,
    "gn:timezone":"Europe/Saratov",
    "iso:country":"RU",
    "name:rus_x_preferred":[
        "\u0411\u043e\u0431\u043e\u0432"
    ],
    "wof:name":"Bobov",
    "wof:placetype":"locality"
},
  "geometry": {"coordinates":[48.4958,51.5889],"type":"Point"}
}