{
  "type": "Feature",
  "properties": {
    "gn:country":"RU",
    "gn:fcode":"PPL",
    "gn:population":0,
    "iso:country":"RU",
    "name:rus_x_preferred":[
        "\u0421\u0442\u0435\u043f\u0430\u043d\u044c\u043a\u043e\u0432\u043e"
    ],
    "name:und_x_variant":[
        "Stepan\u2019kovo"
    ],
    "qs:name":"Stepan'kovo",
    "qs:name_adm0":"Russia",
    "qs:name_adm1":"Moscow Oblast",
    "qs:photos":245,
    "qs:photos_1k":50,
    "qs:photos_9k":1,
    "qs:photos_9r":4,
    "qs:photos_all":245,
    "qs:photos_sr":4,
    "qs:placetype":"Town",
    "qs:pop_sr":"0",
    "wof:name":"Stepan'kovo",
    "wof:placetype":"locality",
    "wof:population":0
},
  "geometry": {"coordinates":[37.63333,56.03333],"type":"Point"}
}