{
  "type": "Feature",
  "properties": {
    "gn:admin1_code":"4",
    "gn:asciiname":"Danilovskiy",
    "gn:country_code":"RU",
    "gn:dem":170,
    "gn:feature_class":"P",
    "gn:feature_code":"PPL",
    "gn:name":"Danilovskiy",
    "gn:population":0,
    "gn:timezone":"Asia/Barnaul",
    "iso:country":"RU",
    "name:rus_x_preferred":[
        "\u0414\u0430\u043d\u0438\u043b\u043e\u0432\u0441\u043a\u0438\u0439"
    ],
    "name:und_x_variant":[
        "\u0414\u0430\u043d\u0438\u043b\u043e\u0432\u0441\u043a\u0438\u0439"
    ],
    "wof:name":"Danilovskiy",
    "wof:placetype":"locality"
},
  "geometry": {"coordinates":[80.75,52.91667],"type":"Point"}
}