{
  "type": "Feature",
  "properties": {
    "gn:admin1_code":"88",
    "gn:asciiname":"Timokhino",
    "gn:country_code":"RU",
    "gn:dem":196,
    "gn:feature_class":"P",
    "gn:feature_code":"PPL",
    "gn:name":"Timokhino",
    "gn:population":0,
    "gn:timezone":"Europe/Moscow",
    "iso:country":"RU",
    "name:rus_x_preferred":[
        "\u0422\u0438\u043c\u043e\u0445\u0438\u043d\u043e"
    ],
    "wof:name":"Timokhino",
    "wof:placetype":"locality"
},
  "geometry": {"coordinates":[39.28664000000001,57.53125],"type":"Point"}
}