{
  "type": "Feature",
  "properties": {
    "gn:admin1_code":"25",
    "gn:asciiname":"Shakhovo",
    "gn:country_code":"RU",
    "gn:dem":174,
    "gn:feature_class":"P",
    "gn:feature_code":"PPL",
    "gn:name":"Shakhovo",
    "gn:population":0,
    "gn:timezone":"Europe/Moscow",
    "iso:country":"RU",
    "name:rus_x_preferred":[
        "\u0428\u0430\u0445\u043e\u0432\u043e"
    ],
    "name:und_x_variant":[
        "\u0428\u0430\u0445\u043e\u0432\u043e"
    ],
    "wof:name":"Shakhovo",
    "wof:placetype":"locality"
},
  "geometry": {"coordinates":[34.92472,54.59694],"type":"Point"}
}