{
  "type": "Feature",
  "properties": {
    "gn:admin1_code":"69",
    "gn:asciiname":"Kazenki",
    "gn:country_code":"RU",
    "gn:dem":198,
    "gn:feature_class":"P",
    "gn:feature_code":"PPL",
    "gn:name":"Kazenki",
    "gn:population":0,
    "gn:timezone":"Europe/Moscow",
    "iso:country":"RU",
    "name:rus_x_preferred":[
        "\u041a\u0430\u0437\u0435\u043d\u043a\u0438"
    ],
    "name:und_x_variant":[
        "\u041a\u0430\u0437\u0435\u043d\u043a\u0438"
    ],
    "wof:name":"Kazenki",
    "wof:placetype":"locality"
},
  "geometry": {"coordinates":[34.59942,55.0921],"type":"Point"}
}