{
  "type": "Feature",
  "properties": {
    "gn:admin1_code":"71",
    "gn:asciiname":"Prytkova",
    "gn:country_code":"RU",
    "gn:dem":72,
    "gn:feature_class":"P",
    "gn:feature_code":"PPL",
    "gn:name":"Prytkova",
    "gn:population":0,
    "gn:timezone":"Asia/Yekaterinburg",
    "iso:country":"RU",
    "name:eng_x_preferred":[
        "Prytkova"
    ],
    "name:nor_x_preferred":[
        "Prytkova"
    ],
    "name:rus_x_preferred":[
        "\u041f\u0440\u044b\u0442\u043a\u043e\u0432\u0430"
    ],
    "wof:name":"Prytkova",
    "wof:placetype":"locality"
},
  "geometry": {"coordinates":[63.42137,57.58365],"type":"Point"}
}