{
  "type": "Feature",
  "properties": {
    "gn:admin1_code":"86",
    "gn:asciiname":"Malyy Kislyay",
    "gn:country_code":"RU",
    "gn:dem":95,
    "gn:feature_class":"P",
    "gn:feature_code":"PPL",
    "gn:name":"Malyy Kislyay",
    "gn:population":0,
    "gn:timezone":"Europe/Moscow",
    "iso:country":"RU",
    "name:rus_x_preferred":[
        "\u041c\u0430\u043b\u044b\u0439 \u041a\u0438\u0441\u043b\u044f\u0439"
    ],
    "name:und_x_variant":[
        "\u041c\u0430\u043b\u044b\u0439 \u041a\u0438\u0441\u043b\u044f\u0439"
    ],
    "wof:name":"Malyy Kislyay",
    "wof:placetype":"locality"
},
  "geometry": {"coordinates":[40.1323,50.8722],"type":"Point"}
}