{
  "type": "Feature",
  "properties": {
    "iso:country":"RU",
    "name:rus_x_preferred":[
        "\u041d\u043e\u0432\u0430\u044f \u0418\u0436\u043e\u0440\u0430"
    ],
    "wof:name":"Nova Izhora",
    "wof:placetype":"neighbourhood"
},
  "geometry": {"coordinates":[30.56682770167436,59.72647267096421],"type":"Point"}
}