{
  "type": "Feature",
  "properties": {
    "gn:admin1_code":"52",
    "gn:asciiname":"Pestovo",
    "gn:country_code":"RU",
    "gn:dem":197,
    "gn:feature_class":"P",
    "gn:feature_code":"PPL",
    "gn:name":"Pestovo",
    "gn:population":0,
    "gn:timezone":"Europe/Moscow",
    "iso:country":"RU",
    "name:rus_x_preferred":[
        "\u041f\u0435\u0441\u0442\u043e\u0432\u043e"
    ],
    "name:und_x_variant":[
        "\u041f\u0435\u0441\u0442\u043e\u0432\u043e"
    ],
    "wof:name":"Pestovo",
    "wof:placetype":"locality"
},
  "geometry": {"coordinates":[32.9038,58.32214000000001],"type":"Point"}
}