{
  "type": "Feature",
  "properties": {
    "gn:admin1_code":"67",
    "gn:asciiname":"Bol'shoy Vyazok",
    "gn:country_code":"RU",
    "gn:dem":70,
    "gn:feature_class":"P",
    "gn:feature_code":"PPL",
    "gn:name":"Bol\u2019shoy Vyazok",
    "gn:population":0,
    "gn:timezone":"Europe/Saratov",
    "iso:country":"RU",
    "name:rus_x_preferred":[
        "Bol\u2019shoy Vyazok"
    ],
    "name:rus_x_variant":[
        "\u0411\u043e\u043b\u044c\u0448\u043e\u0439 \u0412\u044f\u0437\u043e\u043a"
    ],
    "wof:name":"Bol'shoy Vyazok",
    "wof:placetype":"locality"
},
  "geometry": {"coordinates":[48.0255,50.8193],"type":"Point"}
}