{
  "type": "Feature",
  "properties": {
    "gn:admin1_code":"80",
    "gn:asciiname":"Novyye Gayny",
    "gn:country_code":"RU",
    "gn:dem":146,
    "gn:feature_class":"P",
    "gn:feature_code":"PPL",
    "gn:name":"Novyye Gayny",
    "gn:population":0,
    "gn:timezone":"Europe/Samara",
    "iso:country":"RU",
    "name:rus_x_preferred":[
        "\u041d\u043e\u0432\u044b\u0435 \u0413\u0430\u0439\u043d\u044b"
    ],
    "name:und_x_variant":[
        "\u041d\u043e\u0432\u044b\u0435 \u0413\u0430\u0439\u043d\u044b"
    ],
    "wof:name":"Novyye Gayny",
    "wof:placetype":"locality"
},
  "geometry": {"coordinates":[51.43789,57.31632],"type":"Point"}
}