{
  "type": "Feature",
  "properties": {
    "gn:admin1_code":"76",
    "gn:asciiname":"Sukhotino",
    "gn:country_code":"RU",
    "gn:dem":195,
    "gn:feature_class":"P",
    "gn:feature_code":"PPL",
    "gn:name":"Sukhotino",
    "gn:population":0,
    "gn:timezone":"Europe/Moscow",
    "iso:country":"RU",
    "name:rus_x_preferred":[
        "\u0421\u0443\u0445\u043e\u0442\u0438\u043d\u043e"
    ],
    "wof:name":"Sukhotino",
    "wof:placetype":"locality"
},
  "geometry": {"coordinates":[37.33351,54.59135],"type":"Point"}
}