{
  "type": "Feature",
  "properties": {
    "gn:admin1_code":"42",
    "gn:asciiname":"Kopsala",
    "gn:country_code":"RU",
    "gn:dem":13,
    "gn:feature_class":"P",
    "gn:feature_code":"PPL",
    "gn:name":"Kopsala",
    "gn:population":0,
    "gn:timezone":"Europe/Moscow",
    "iso:country":"RU",
    "name:fin_x_preferred":[
        "Kopsala"
    ],
    "name:rus_x_preferred":[
        "\u041a\u043e\u043f\u0441\u0430\u043b\u0430"
    ],
    "name:und_x_variant":[
        "\u041a\u043e\u043f\u0441\u0430\u043b\u0430"
    ],
    "wof:name":"Kopsala",
    "wof:placetype":"locality"
},
  "geometry": {"coordinates":[29.8562,61.17726999999999],"type":"Point"}
}