{
  "type": "Feature",
  "properties": {
    "gn:admin1_code":"28",
    "gn:asciiname":"Pryakka",
    "gn:country_code":"RU",
    "gn:dem":136,
    "gn:feature_class":"P",
    "gn:feature_code":"PPL",
    "gn:name":"Pryakka",
    "gn:population":0,
    "gn:timezone":"Europe/Moscow",
    "iso:country":"RU",
    "name:fin_x_preferred":[
        "Pr\u00e4kk\u00e4"
    ],
    "name:rus_x_preferred":[
        "\u041f\u0440\u044f\u043a\u043a\u0430"
    ],
    "name:und_x_variant":[
        "Pryakki",
        "Pryakka",
        "\u041f\u0440\u044f\u043a\u043a\u0430"
    ],
    "wof:name":"Pryakka",
    "wof:placetype":"locality"
},
  "geometry": {"coordinates":[33.59345,61.64027],"type":"Point"}
}