{
  "type": "Feature",
  "properties": {
    "gn:admin1_code":"57",
    "gn:asciiname":"Morsovo",
    "gn:country_code":"RU",
    "gn:dem":127,
    "gn:feature_class":"P",
    "gn:feature_code":"PPL",
    "gn:name":"Morsovo",
    "gn:population":0,
    "gn:timezone":"Europe/Moscow",
    "iso:country":"RU",
    "name:eng_x_preferred":[
        "Morsovo"
    ],
    "name:nor_x_preferred":[
        "Morsovo"
    ],
    "name:rus_x_preferred":[
        "\u041c\u043e\u0440\u0441\u043e\u0432\u043e"
    ],
    "name:und_x_variant":[
        "Marsovo",
        "\u041c\u043e\u0440\u0441\u043e\u0432\u043e",
        "Morsovo"
    ],
    "wof:name":"Morsovo",
    "wof:placetype":"locality"
},
  "geometry": {"coordinates":[42.32136,53.7394],"type":"Point"}
}