{
  "type": "Feature",
  "properties": {
    "gn:admin1_code":"84",
    "gn:asciiname":"Ruzheynikovskiy",
    "gn:country_code":"RU",
    "gn:dem":140,
    "gn:feature_class":"P",
    "gn:feature_code":"PPL",
    "gn:name":"Ruzheynikovskiy",
    "gn:population":0,
    "gn:timezone":"Europe/Volgograd",
    "iso:country":"RU",
    "name:rus_x_preferred":[
        "\u0420\u0443\u0436\u0435\u0439\u043d\u0438\u043a\u043e\u0432\u0441\u043a\u0438\u0439"
    ],
    "wof:name":"Ruzheynikovskiy",
    "wof:placetype":"locality"
},
  "geometry": {"coordinates":[42.4691,50.9844],"type":"Point"}
}