{
  "type": "Feature",
  "properties": {
    "gn:admin1_code":"32",
    "gn:asciiname":"Mokrovskaya",
    "gn:country_code":"RU",
    "gn:dem":35,
    "gn:feature_class":"P",
    "gn:feature_code":"PPL",
    "gn:name":"Mokrovskaya",
    "gn:population":0,
    "gn:timezone":"Asia/Yekaterinburg",
    "iso:country":"RU",
    "name:eng_x_preferred":[
        "Mokrovskaya"
    ],
    "name:nor_x_preferred":[
        "Mokrovka"
    ],
    "name:rus_x_preferred":[
        "\u041c\u043e\u043a\u0440\u043e\u0432\u043a\u0430"
    ],
    "name:rus_x_variant":[
        "\u041c\u043e\u043a\u0440\u043e\u0432\u0441\u043a\u0430\u044f"
    ],
    "name:und_x_variant":[
        "\u041c\u043e\u043a\u0440\u043e\u0432\u0441\u043a\u0430\u044f"
    ],
    "wof:name":"Mokrovskaya",
    "wof:placetype":"locality"
},
  "geometry": {"coordinates":[67.16667,59.66667],"type":"Point"}
}