{
  "type": "Feature",
  "properties": {
    "gn:admin1_code":"81",
    "gn:asciiname":"Muravey",
    "gn:country_code":"RU",
    "gn:dem":128,
    "gn:feature_class":"P",
    "gn:feature_code":"PPL",
    "gn:name":"Muravey",
    "gn:population":0,
    "gn:timezone":"Europe/Ulyanovsk",
    "iso:country":"RU",
    "name:rus_x_preferred":[
        "\u041c\u0443\u0440\u0430\u0432\u0435\u0439"
    ],
    "wof:name":"Muravey",
    "wof:placetype":"locality"
},
  "geometry": {"coordinates":[47.8925,53.9872],"type":"Point"}
}