{
  "type": "Feature",
  "properties": {
    "gn:admin1_code":"70.0",
    "gn:asciiname":"Sadovyy",
    "gn:country_code":"RU",
    "gn:dem":150,
    "gn:feature_class":"P",
    "gn:feature_code":"PPL",
    "gn:name":"Sadovyy",
    "gn:population":0,
    "gn:timezone":"Europe/Moscow",
    "iso:country":"RU",
    "wof:name":"Sadovyy",
    "wof:placetype":"locality"
},
  "geometry": {"coordinates":[44.17333,44.37389],"type":"Point"}
}