{
  "type": "Feature",
  "properties": {
    "gn:country":"RU",
    "gn:fcode":"PPL",
    "gn:population":0,
    "iso:country":"RU",
    "name:bel_x_preferred":[
        "\u0414\u0437\u043c\u0456\u0442\u0440\u044b\u0435\u045e\u043a\u0430"
    ],
    "name:cat_x_preferred":[
        "Dm\u00edtrievka"
    ],
    "name:ceb_x_preferred":[
        "\u0414\u043c\u0438\u0442\u0440\u0438\u0435\u0432\u043a\u0430"
    ],
    "name:deu_x_preferred":[
        "Dmitrijewka"
    ],
    "name:eng_x_preferred":[
        "Dmitriyevka"
    ],
    "name:hye_x_preferred":[
        "\u0534\u0574\u056b\u057f\u0580\u056b\u0587\u056f\u0561"
    ],
    "name:kaz_x_preferred":[
        "\u0414\u043c\u0438\u0442\u0440\u0438\u0435\u0432\u043a\u0430"
    ],
    "name:lav_x_preferred":[
        "Dmitrijevka"
    ],
    "name:nld_x_preferred":[
        "Dmitrijevka"
    ],
    "name:nor_x_preferred":[
        "Dmitrijevka"
    ],
    "name:pol_x_preferred":[
        "Dmitrijewka"
    ],
    "name:rus_x_preferred":[
        "\u0414\u043c\u0438\u0442\u0440\u0438\u0435\u0432\u043a\u0430"
    ],
    "name:ukr_x_preferred":[
        "\u0414\u043c\u0438\u0442\u0440\u0456\u0454\u0432\u043a\u0430"
    ],
    "qs:name":"Dmitriyevka",
    "qs:name_adm0":"Russia",
    "qs:name_adm1":"Bashkortostan Republic",
    "qs:photos_9r":0,
    "qs:photos_sr":0,
    "qs:placetype":"Town",
    "qs:pop_sr":"0",
    "wd:wordcount":2278,
    "wof:name":"Dmitriyevka",
    "wof:placetype":"locality",
    "wof:population":0
},
  "geometry": {"coordinates":[55.80611,54.81389],"type":"Point"}
}