{
  "type": "Feature",
  "properties": {
    "gn:country":"RU",
    "gn:fcode":"PPL",
    "gn:population":0,
    "iso:country":"RU",
    "name:eng_x_preferred":[
        "Dmitriyevka"
    ],
    "name:nor_x_preferred":[
        "Dmitrijevka"
    ],
    "name:rus_x_preferred":[
        "\u0414\u043c\u0438\u0442\u0440\u0438\u0435\u0432\u043a\u0430"
    ],
    "qs:name":"Dmitriyevka",
    "qs:name_adm0":"Russia",
    "qs:name_adm1":"Bashkortostan Republic",
    "qs:photos_9r":0,
    "qs:photos_sr":0,
    "qs:placetype":"Town",
    "qs:pop_sr":"0",
    "wd:wordcount":2278,
    "wof:name":"Dmitriyevka",
    "wof:placetype":"locality",
    "wof:population":0
},
  "geometry": {"coordinates":[55.80611,54.81389],"type":"Point"}
}