{
  "type": "Feature",
  "properties": {
    "gn:admin1_code":"72",
    "gn:asciiname":"Kazyvan'",
    "gn:country_code":"RU",
    "gn:dem":136,
    "gn:feature_class":"P",
    "gn:feature_code":"PPL",
    "gn:name":"Kazyvan\u2019",
    "gn:population":0,
    "gn:timezone":"Europe/Moscow",
    "iso:country":"RU",
    "name:rus_x_preferred":[
        "\u041a\u0430\u0437\u044b\u0432\u0430\u043d\u044c"
    ],
    "name:und_x_variant":[
        "Kazyvan\u2019"
    ],
    "wof:name":"Kazyvan'",
    "wof:placetype":"locality"
},
  "geometry": {"coordinates":[41.73978,52.95918],"type":"Point"}
}