{
  "type": "Feature",
  "properties": {
    "gn:admin1_code":"8",
    "gn:asciiname":"Tazlarovo",
    "gn:country_code":"RU",
    "gn:dem":175,
    "gn:feature_class":"P",
    "gn:feature_code":"PPL",
    "gn:name":"Tazlarovo",
    "gn:population":0,
    "gn:timezone":"Asia/Yekaterinburg",
    "iso:country":"RU",
    "name:bak_x_preferred":[
        "\u0422\u0430\u0499\u043b\u0430\u0440"
    ],
    "name:che_x_preferred":[
        "\u0422\u0430\u0437\u043b\u0430\u0440\u043e\u0432\u043e"
    ],
    "name:eng_x_preferred":[
        "Tazlarovo"
    ],
    "name:hye_x_preferred":[
        "\u054f\u0561\u0566\u056c\u0561\u0580\u0578\u057e\u0578"
    ],
    "name:kaz_x_preferred":[
        "\u0422\u0430\u0437\u043b\u0430\u0440"
    ],
    "name:kir_x_preferred":[
        "\u0422\u0430\u0437\u043b\u0430\u0440"
    ],
    "name:nor_x_preferred":[
        "Tazlarovo"
    ],
    "name:rus_x_preferred":[
        "\u0422\u0430\u0437\u043b\u0430\u0440\u043e\u0432\u043e"
    ],
    "name:tat_x_preferred":[
        "\u0422\u0430\u0437\u043b\u0430\u0440"
    ],
    "name:ukr_x_preferred":[
        "\u0422\u0430\u0437\u043b\u0430\u0440\u043e\u0432\u043e"
    ],
    "wof:name":"Tazlarovo",
    "wof:placetype":"locality"
},
  "geometry": {"coordinates":[56.685,52.14611],"type":"Point"}
}