{
  "type": "Feature",
  "properties": {
    "gn:admin1_code":"8",
    "gn:asciiname":"Staryy Kainlyk",
    "gn:country_code":"RU",
    "gn:dem":70,
    "gn:feature_class":"P",
    "gn:feature_code":"PPL",
    "gn:name":"Staryy Kainlyk",
    "gn:population":0,
    "gn:timezone":"Asia/Yekaterinburg",
    "iso:country":"RU",
    "name:rus_x_preferred":[
        "\u0421\u0442\u0430\u0440\u044b\u0439 \u041a\u0430\u0438\u043d\u043b\u044b\u043a"
    ],
    "name:und_x_variant":[
        "Staroye Kainlykovo",
        "Staryy Kainlyk"
    ],
    "wof:name":"Staryy Kainlyk",
    "wof:placetype":"locality"
},
  "geometry": {"coordinates":[54.43108,55.77231999999999],"type":"Point"}
}