{
  "type": "Feature",
  "properties": {
    "gn:admin1_code":"53",
    "gn:asciiname":"Kazanka",
    "gn:country_code":"RU",
    "gn:dem":105,
    "gn:feature_class":"P",
    "gn:feature_code":"PPL",
    "gn:name":"Kazanka",
    "gn:population":0,
    "gn:timezone":"Asia/Novosibirsk",
    "iso:country":"RU",
    "name:bul_x_preferred":[
        "\u041a\u0430\u0437\u0430\u043d\u043a\u0430"
    ],
    "name:ceb_x_preferred":[
        "Kazanka"
    ],
    "name:ces_x_preferred":[
        "Kazanka"
    ],
    "name:deu_x_preferred":[
        "Kasanka"
    ],
    "name:fra_x_preferred":[
        "Kazanka"
    ],
    "name:hun_x_preferred":[
        "Kazanka"
    ],
    "name:pol_x_preferred":[
        "Kazanka"
    ],
    "name:rus_x_preferred":[
        "\u041a\u0430\u0437\u0430\u043d\u043a\u0430"
    ],
    "name:swe_x_preferred":[
        "Kasanka"
    ],
    "name:ukr_x_preferred":[
        "\u041a\u0430\u0437\u0430\u043d\u043a\u0430"
    ],
    "wof:name":"Kazanka",
    "wof:placetype":"locality"
},
  "geometry": {"coordinates":[76.09999999999999,55.08333],"type":"Point"}
}