{
  "type": "Feature",
  "properties": {
    "gn:admin1_code":"42",
    "gn:asciiname":"Sukhoye",
    "gn:country_code":"RU",
    "gn:dem":31,
    "gn:feature_class":"P",
    "gn:feature_code":"PPL",
    "gn:name":"Sukhoye",
    "gn:population":0,
    "gn:timezone":"Europe/Moscow",
    "iso:country":"RU",
    "name:eng_x_preferred":[
        "Sukhoye"
    ],
    "name:nor_x_preferred":[
        "Sukhoje"
    ],
    "name:rus_x_preferred":[
        "\u0421\u0443\u0445\u043e\u0435"
    ],
    "name:und_x_variant":[
        "\u0421\u0443\u0445\u043e\u0435",
        "Sukhoye"
    ],
    "wof:name":"Sukhoye",
    "wof:placetype":"locality"
},
  "geometry": {"coordinates":[31.73478,60.01735],"type":"Point"}
}