{
  "type": "Feature",
  "properties": {
    "gn:admin1_code":"20",
    "gn:asciiname":"Baznyy",
    "gn:country_code":"RU",
    "gn:dem":619,
    "gn:feature_class":"P",
    "gn:feature_code":"PPL",
    "gn:name":"Baznyy",
    "gn:population":0,
    "gn:timezone":"Asia/Irkutsk",
    "iso:country":"RU",
    "name:eng_x_preferred":[
        "Baznyy"
    ],
    "name:nor_x_preferred":[
        "Baznyj"
    ],
    "name:rus_x_preferred":[
        "\u0411\u0430\u0437\u043d\u044b\u0439"
    ],
    "wof:name":"Baznyy",
    "wof:placetype":"locality"
},
  "geometry": {"coordinates":[116.61667,57.41667],"type":"Point"}
}