{
  "type": "Feature",
  "properties": {
    "gn:admin1_code":"65",
    "gn:asciiname":"Dachnyy",
    "gn:country_code":"RU",
    "gn:dem":78,
    "gn:feature_class":"P",
    "gn:feature_code":"PPL",
    "gn:name":"Dachnyy",
    "gn:population":0,
    "gn:timezone":"Europe/Samara",
    "iso:country":"RU",
    "name:rus_x_preferred":[
        "\u0414\u0430\u0447\u043d\u044b\u0439"
    ],
    "wof:name":"Dachnyy",
    "wof:placetype":"locality"
},
  "geometry": {"coordinates":[51.0258,53.7593],"type":"Point"}
}