{
  "type": "Feature",
  "properties": {
    "gn:admin1_code":"72.0",
    "gn:asciiname":"Dubovoye",
    "gn:country_code":"RU",
    "gn:dem":148,
    "gn:feature_class":"P",
    "gn:feature_code":"PPL",
    "gn:name":"Dubovoye",
    "gn:population":0,
    "gn:timezone":"Europe/Moscow",
    "iso:country":"RU",
    "name:che_x_preferred":[
        "\u0414\u0443\u0431\u043e\u0432\u0438"
    ],
    "name:rus_x_preferred":[
        "\u0414\u0443\u0431\u043e\u0432\u043e\u0435"
    ],
    "name:und_x_variant":[
        "\u0414\u0443\u0431\u043e\u0432\u043e\u0435"
    ],
    "wof:name":"Dubovoye",
    "wof:placetype":"locality"
},
  "geometry": {"coordinates":[40.3005,52.6081],"type":"Point"}
}