{
  "type": "Feature",
  "properties": {
    "gn:admin1_code":"42",
    "gn:asciiname":"Novoye Berezno",
    "gn:country_code":"RU",
    "gn:dem":60,
    "gn:feature_class":"P",
    "gn:feature_code":"PPL",
    "gn:name":"Novoye Berezno",
    "gn:population":0,
    "gn:timezone":"Europe/Moscow",
    "iso:country":"RU",
    "name:rus_x_preferred":[
        "\u041d\u043e\u0432\u043e\u0435 \u0411\u0435\u0440\u0435\u0437\u043d\u043e"
    ],
    "name:und_x_variant":[
        "\u041d\u043e\u0432\u043e\u0435 \u0411\u0435\u0440\u0435\u0437\u043d\u043e"
    ],
    "wof:name":"Novoye Berezno",
    "wof:placetype":"locality"
},
  "geometry": {"coordinates":[30.73333,58.88333000000001],"type":"Point"}
}