{
  "type": "Feature",
  "properties": {
    "gn:admin1_code":"76",
    "gn:asciiname":"Malyye Baydiki",
    "gn:country_code":"RU",
    "gn:dem":236,
    "gn:feature_class":"P",
    "gn:feature_code":"PPL",
    "gn:name":"Malyye Baydiki",
    "gn:population":0,
    "gn:timezone":"Europe/Moscow",
    "iso:country":"RU",
    "name:rus_x_preferred":[
        "\u041c\u0430\u043b\u044b\u0435 \u0411\u0430\u0439\u0434\u0438\u043a\u0438"
    ],
    "wof:name":"Malyye Baydiki",
    "wof:placetype":"locality"
},
  "geometry": {"coordinates":[37.65189,54.3421],"type":"Point"}
}