{
  "type": "Feature",
  "properties": {
    "gn:admin1_code":"77",
    "gn:asciiname":"Bronnikovo",
    "gn:country_code":"RU",
    "gn:dem":148,
    "gn:feature_class":"P",
    "gn:feature_code":"PPL",
    "gn:name":"Bronnikovo",
    "gn:population":0,
    "gn:timezone":"Europe/Moscow",
    "iso:country":"RU",
    "name:rus_x_preferred":[
        "\u0411\u0440\u043e\u043d\u043d\u0438\u043a\u043e\u0432\u043e"
    ],
    "name:und_x_variant":[
        "\u0411\u0440\u043e\u043d\u043d\u0438\u043a\u043e\u0432\u043e"
    ],
    "wof:name":"Bronnikovo",
    "wof:placetype":"locality"
},
  "geometry": {"coordinates":[37.1268,58.4558],"type":"Point"}
}