{
  "type": "Feature",
  "properties": {
    "gn:country":"RU",
    "gn:fcode":"PPLX",
    "gn:pop":0,
    "iso:country":"RU",
    "name:rus_x_preferred":[
        "\u041c\u0443\u0440\u0430\u0432\u044c\u0451\u0432\u043a\u0430"
    ],
    "name:unk_x_variant":[
        "Muravl\u00ebvka"
    ],
    "qs:name":"Murav'y\u00ebvka",
    "qs:name_adm0":"Russia",
    "qs:name_adm1":"Saratov Oblast",
    "qs:photos":3,
    "qs:photos_1k":1,
    "qs:photos_9k":1,
    "qs:photos_9r":1,
    "qs:photos_all":3,
    "qs:photos_sr":1,
    "qs:placetype":"Suburb",
    "qs:pop_sr":"0",
    "wof:name":"Murav'y\u00ebvka",
    "wof:placetype":"neighbourhood",
    "wof:population":0
},
  "geometry": {"coordinates":[45.93333,51.51667],"type":"Point"}
}