{
  "type": "Feature",
  "properties": {
    "gn:admin1_code":"8",
    "gn:asciiname":"Starobiryuchevo",
    "gn:country_code":"RU",
    "gn:dem":113,
    "gn:feature_class":"P",
    "gn:feature_code":"PPL",
    "gn:name":"Starobiryuchevo",
    "gn:population":0,
    "gn:timezone":"Asia/Yekaterinburg",
    "iso:country":"RU",
    "name:eng_x_preferred":[
        "Starobiryuchevo"
    ],
    "name:nor_x_preferred":[
        "Starobirjutsjevo"
    ],
    "name:rus_x_preferred":[
        "\u0421\u0442\u0430\u0440\u043e\u0431\u0438\u0440\u044e\u0447\u0435\u0432\u043e"
    ],
    "name:und_x_variant":[
        "Staroye Biryuchevo",
        "Staraya Biryucheva",
        "\u0421\u0442\u0430\u0440\u043e\u0431\u0438\u0440\u044e\u0447\u0435\u0432\u043e",
        "Starobiryuchevo"
    ],
    "wof:name":"Starobiryuchevo",
    "wof:placetype":"locality"
},
  "geometry": {"coordinates":[56.59121,55.25559000000001],"type":"Point"}
}