{
  "type": "Feature",
  "properties": {
    "gn:admin1_code":"65.0",
    "gn:asciiname":"Chistovka",
    "gn:country_code":"RU",
    "gn:dem":142,
    "gn:feature_class":"P",
    "gn:feature_code":"PPL",
    "gn:name":"Chistovka",
    "gn:population":0,
    "gn:timezone":"Europe/Samara",
    "iso:country":"RU",
    "name:eng_x_preferred":[
        "Chistovka"
    ],
    "name:nor_x_preferred":[
        "Tsjistovka"
    ],
    "name:rus_x_preferred":[
        "\u0427\u0438\u0441\u0442\u043e\u0432\u043a\u0430"
    ],
    "name:und_x_variant":[
        "\u0427\u0438\u0441\u0442\u043e\u0432\u043a\u0430",
        "Chistovka"
    ],
    "wof:name":"Chistovka",
    "wof:placetype":"locality"
},
  "geometry": {"coordinates":[50.91658,54.21845],"type":"Point"}
}