{
  "type": "Feature",
  "properties": {
    "gn:admin1_code":"93",
    "gn:asciiname":"Nizhniye Kularki",
    "gn:country_code":"RU",
    "gn:dem":394,
    "gn:feature_class":"P",
    "gn:feature_code":"PPL",
    "gn:name":"Nizhniye Kularki",
    "gn:population":0,
    "gn:timezone":"Asia/Chita",
    "iso:country":"RU",
    "name:eng_x_preferred":[
        "Nizhniye Kularki"
    ],
    "name:nor_x_preferred":[
        "Nizj.Kularki"
    ],
    "name:rus_x_preferred":[
        "\u041d\u0438\u0436.\u041a\u0443\u043b\u0430\u0440\u043a\u0438"
    ],
    "name:rus_x_variant":[
        "\u041d\u0438\u0436\u043d\u0438\u0435 \u041a\u0443\u043b\u0430\u0440\u043a\u0438"
    ],
    "name:und_x_variant":[
        "Nizhnyaya Kularki",
        "Nizhne-Kularki",
        "Nizhne-Kularskiy",
        "Nizhniye Kularki",
        "\u041d\u0438\u0436\u043d\u0438\u0435 \u041a\u0443\u043b\u0430\u0440\u043a\u0438"
    ],
    "wof:name":"Nizhniye Kularki",
    "wof:placetype":"locality"
},
  "geometry": {"coordinates":[118.95359999999999,52.86888],"type":"Point"}
}