{
  "type": "Feature",
  "properties": {
    "gn:admin1_code":"8.0",
    "gn:asciiname":"Buzenka",
    "gn:country_code":"RU",
    "gn:dem":113,
    "gn:feature_class":"P",
    "gn:feature_code":"PPL",
    "gn:name":"Buzenka",
    "gn:population":0,
    "gn:timezone":"Asia/Yekaterinburg",
    "iso:country":"RU",
    "name:rus_x_preferred":[
        "\u0411\u0443\u0437\u0435\u043d\u043a\u0430"
    ],
    "name:und_x_variant":[
        "Buzanka",
        "Buzenka"
    ],
    "wof:name":"Buzenka",
    "wof:placetype":"locality"
},
  "geometry": {"coordinates":[56.5616,54.5506],"type":"Point"}
}