{
  "type": "Feature",
  "properties": {
    "gn:admin1_code":"24",
    "gn:asciiname":"Tsomok",
    "gn:country_code":"RU",
    "gn:dem":-28,
    "gn:feature_class":"P",
    "gn:feature_code":"PPL",
    "gn:name":"Tsomok",
    "gn:population":0,
    "gn:timezone":"Europe/Moscow",
    "iso:country":"RU",
    "wof:name":"Tsomok",
    "wof:placetype":"locality"
},
  "geometry": {"coordinates":[47.22778,45.48083],"type":"Point"}
}