{
  "type": "Feature",
  "properties": {
    "gn:admin1_code":"70.0",
    "gn:asciiname":"Bratskiy Soyuz",
    "gn:country_code":"RU",
    "gn:dem":108,
    "gn:feature_class":"P",
    "gn:feature_code":"PPL",
    "gn:name":"Bratskiy Soyuz",
    "gn:population":0,
    "gn:timezone":"Europe/Moscow",
    "iso:country":"RU",
    "wof:name":"Bratskiy Soyuz",
    "wof:placetype":"locality"
},
  "geometry": {"coordinates":[41.95,45.85],"type":"Point"}
}