{
  "type": "Feature",
  "properties": {
    "gn:admin1_code":"45.0",
    "gn:asciiname":"Fokino",
    "gn:country_code":"RU",
    "gn:dem":138,
    "gn:feature_class":"P",
    "gn:feature_code":"PPL",
    "gn:name":"Fokino",
    "gn:population":0,
    "gn:timezone":"Europe/Moscow",
    "iso:country":"RU",
    "name:rus_x_preferred":[
        "\u0424\u043e\u043a\u0438\u043d\u043e"
    ],
    "name:und_x_variant":[
        "\u0424\u043e\u043a\u0438\u043d\u043e"
    ],
    "wof:name":"Fokino",
    "wof:placetype":"locality"
},
  "geometry": {"coordinates":[48.49611,56.75833000000001],"type":"Point"}
}