{
  "type": "Feature",
  "properties": {
    "gn:admin1_code":"45.0",
    "gn:asciiname":"Fokino",
    "gn:country_code":"RU",
    "gn:dem":138,
    "gn:feature_class":"P",
    "gn:feature_code":"PPL",
    "gn:name":"Fokino",
    "gn:population":0,
    "gn:timezone":"Europe/Moscow",
    "iso:country":"RU",
    "name:bel_x_preferred":[
        "\u0424\u043e\u043a\u0456\u043d\u0430"
    ],
    "name:bul_x_preferred":[
        "\u0424\u043e\u043a\u0438\u043d\u043e"
    ],
    "name:ceb_x_preferred":[
        "Fokino"
    ],
    "name:ces_x_preferred":[
        "Fokino"
    ],
    "name:deu_x_preferred":[
        "Fokino"
    ],
    "name:epo_x_preferred":[
        "Fokino"
    ],
    "name:fin_x_preferred":[
        "Fokino"
    ],
    "name:fra_x_preferred":[
        "Fokino"
    ],
    "name:hrv_x_preferred":[
        "Fokino"
    ],
    "name:ita_x_preferred":[
        "Fokino"
    ],
    "name:jpn_x_preferred":[
        "\u30d5\u30a9\u30fc\u30ad\u30ce"
    ],
    "name:kor_x_preferred":[
        "\ud3ec\ud0a4\ub178"
    ],
    "name:nld_x_preferred":[
        "Fokino"
    ],
    "name:nor_x_preferred":[
        "Fokino"
    ],
    "name:pol_x_preferred":[
        "Fokino"
    ],
    "name:rus_x_preferred":[
        "\u0424\u043e\u043a\u0438\u043d\u043e"
    ],
    "name:srp_x_preferred":[
        "\u0424\u043e\u043a\u0438\u043d\u043e"
    ],
    "name:ukr_x_preferred":[
        "\u0424\u043e\u043a\u0438\u043d\u043e"
    ],
    "name:vep_x_preferred":[
        "Fokino"
    ],
    "name:zho_x_preferred":[
        "\u798f\u57fa\u8bfa"
    ],
    "wof:name":"Fokino",
    "wof:placetype":"locality"
},
  "geometry": {"coordinates":[48.49611,56.75833000000001],"type":"Point"}
}