{
  "type": "Feature",
  "properties": {
    "gn:admin1_code":"17",
    "gn:admin2_code":"583776",
    "gn:asciiname":"Tukita",
    "gn:country_code":"RU",
    "gn:dem":1912,
    "gn:feature_class":"P",
    "gn:feature_code":"PPL",
    "gn:name":"Tukita",
    "gn:population":0,
    "gn:timezone":"Europe/Moscow",
    "iso:country":"RU",
    "name:rus_x_preferred":[
        "\u0422\u0443\u043a\u0438\u0442\u0430"
    ],
    "name:und_x_variant":[
        "\u0422\u0443\u043a\u0438\u0442\u0430"
    ],
    "wof:name":"Tukita",
    "wof:placetype":"locality"
},
  "geometry": {"coordinates":[46.37242,42.57316],"type":"Point"}
}