{
  "type": "Feature",
  "properties": {
    "gn:admin1_code":"85.0",
    "gn:asciiname":"Trifonovo",
    "gn:country_code":"RU",
    "gn:dem":148,
    "gn:feature_class":"P",
    "gn:feature_code":"PPL",
    "gn:name":"Trifonovo",
    "gn:population":0,
    "gn:timezone":"Europe/Moscow",
    "iso:country":"RU",
    "name:rus_x_preferred":[
        "\u0422\u0440\u0438\u0444\u043e\u043d\u043e\u0432\u043e"
    ],
    "wof:name":"Trifonovo",
    "wof:placetype":"locality"
},
  "geometry": {"coordinates":[38.0806,60.6389],"type":"Point"}
}