{
  "type": "Feature",
  "properties": {
    "gn:admin1_code":"87",
    "gn:asciiname":"Fedulki",
    "gn:country_code":"RU",
    "gn:dem":24,
    "gn:feature_class":"P",
    "gn:feature_code":"PPL",
    "gn:name":"Fedulki",
    "gn:population":0,
    "gn:timezone":"Asia/Yekaterinburg",
    "iso:country":"RU",
    "name:eng_x_preferred":[
        "Fedulki"
    ],
    "name:nor_x_preferred":[
        "Fedulki"
    ],
    "name:rus_x_preferred":[
        "\u0424\u0435\u0434\u0443\u043b\u043a\u0438"
    ],
    "wof:name":"Fedulki",
    "wof:placetype":"locality"
},
  "geometry": {"coordinates":[66.25,64.96666999999999],"type":"Point"}
}