{
  "type": "Feature",
  "properties": {
    "gn:admin1_code":"86.0",
    "gn:asciiname":"Plyasovo-Kitayevo",
    "gn:country_code":"RU",
    "gn:dem":147,
    "gn:feature_class":"P",
    "gn:feature_code":"PPL",
    "gn:name":"Plyasovo-Kitayevo",
    "gn:population":0,
    "gn:timezone":"Europe/Moscow",
    "iso:country":"RU",
    "name:rus_x_preferred":[
        "\u041f\u043b\u044f\u0441\u043e\u0432\u043e-\u041a\u0438\u0442\u0430\u0435\u0432\u043e"
    ],
    "wof:name":"Plyasovo-Kitayevo",
    "wof:placetype":"locality"
},
  "geometry": {"coordinates":[39.67076,51.71233],"type":"Point"}
}