{
  "type": "Feature",
  "properties": {
    "gn:admin1_code":"79",
    "gn:asciiname":"Chirgalandy",
    "gn:cc2":"RU",
    "gn:country_code":"RU",
    "gn:dem":1371,
    "gn:feature_class":"P",
    "gn:feature_code":"PPL",
    "gn:name":"Chirgalandy",
    "gn:population":0,
    "gn:timezone":"Asia/Krasnoyarsk",
    "iso:country":"RU",
    "name:rus_x_preferred":[
        "\u0427\u0438\u0440\u0433\u0430\u043b\u0430\u043d\u0434\u044b"
    ],
    "name:und_x_variant":[
        "T\u00ebre-Kh\u00ebl\u2019",
        "Jirgalanta",
        "Chirgalandy",
        "\u0427\u0438\u0440\u0433\u0430\u043b\u0430\u043d\u0434\u044b"
    ],
    "wof:name":"Chirgalandy",
    "wof:placetype":"locality"
},
  "geometry": {"coordinates":[97.21805999999999,50.58611],"type":"Point"}
}