{
  "type": "Feature",
  "properties": {
    "gn:admin1_code":"21",
    "gn:asciiname":"Morozovo",
    "gn:country_code":"RU",
    "gn:dem":131,
    "gn:feature_class":"P",
    "gn:feature_code":"PPL",
    "gn:name":"Morozovo",
    "gn:population":0,
    "gn:timezone":"Europe/Moscow",
    "iso:country":"RU",
    "name:rus_x_preferred":[
        "\u041c\u043e\u0440\u043e\u0437\u043e\u0432\u043e"
    ],
    "name:und_x_variant":[
        "\u041c\u043e\u0440\u043e\u0437\u043e\u0432\u043e"
    ],
    "wof:name":"Morozovo",
    "wof:placetype":"locality"
},
  "geometry": {"coordinates":[41.04769,57.25541],"type":"Point"}
}