{
  "type": "Feature",
  "properties": {
    "gn:admin1_code":"60",
    "gn:asciiname":"Skovron'kovo",
    "gn:country_code":"RU",
    "gn:dem":146,
    "gn:feature_class":"P",
    "gn:feature_code":"PPL",
    "gn:name":"Skovron\u2019kovo",
    "gn:population":0,
    "gn:timezone":"Europe/Moscow",
    "iso:country":"RU",
    "name:rus_x_preferred":[
        "\u0421\u043a\u043e\u0432\u0440\u043e\u043d\u044c\u043a\u043e\u0432\u043e"
    ],
    "name:und_x_variant":[
        "Skovron\u2019kovo",
        "\u0421\u043a\u043e\u0432\u0440\u043e\u043d\u044c\u043a\u043e\u0432\u043e"
    ],
    "wof:name":"Skovron'kovo",
    "wof:placetype":"locality"
},
  "geometry": {"coordinates":[29.0764,56.2351],"type":"Point"}
}