{
  "type": "Feature",
  "properties": {
    "gn:admin1_code":"92",
    "gn:asciiname":"Voyampolka-Osedlaya",
    "gn:cc2":"RU",
    "gn:country_code":"RU",
    "gn:dem":12,
    "gn:feature_class":"P",
    "gn:feature_code":"PPL",
    "gn:name":"Voyampolka-Osedlaya",
    "gn:population":0,
    "gn:timezone":"Asia/Kamchatka",
    "iso:country":"RU",
    "name:eng_x_preferred":[
        "Voyampolka-Osedlaya"
    ],
    "name:nor_x_preferred":[
        "Vojampolka"
    ],
    "name:rus_x_preferred":[
        "\u0412\u043e\u044f\u043c\u043f\u043e\u043b\u043a\u0430"
    ],
    "name:und_x_variant":[
        "Vayampalka",
        "Voyampolka",
        "Voyampolka-Osedlaya"
    ],
    "wof:name":"Voyampolka-Osedlaya",
    "wof:placetype":"locality"
},
  "geometry": {"coordinates":[159.36667,58.43333000000001],"type":"Point"}
}