{
  "type": "Feature",
  "properties": {
    "gn:admin1_code":"62",
    "gn:asciiname":"Pistsovo",
    "gn:country_code":"RU",
    "gn:dem":174,
    "gn:feature_class":"P",
    "gn:feature_code":"PPL",
    "gn:name":"Pistsovo",
    "gn:population":0,
    "gn:timezone":"Europe/Moscow",
    "iso:country":"RU",
    "name:rus_x_preferred":[
        "\u041f\u0438\u0441\u0446\u043e\u0432\u043e"
    ],
    "name:und_x_variant":[
        "Pestsovo"
    ],
    "wof:name":"Pistsovo",
    "wof:placetype":"locality"
},
  "geometry": {"coordinates":[39.5843,54.4628],"type":"Point"}
}