{
  "type": "Feature",
  "properties": {
    "gn:admin1_code":"73",
    "gn:asciiname":"Yevlevo",
    "gn:country_code":"RU",
    "gn:dem":144,
    "gn:feature_class":"P",
    "gn:feature_code":"PPL",
    "gn:name":"Yevlevo",
    "gn:population":0,
    "gn:timezone":"Europe/Moscow",
    "iso:country":"RU",
    "name:rus_x_preferred":[
        "\u0415\u0432\u043b\u0435\u0432\u043e"
    ],
    "name:und_x_variant":[
        "\u0415\u0432\u043b\u0435\u0432\u043e"
    ],
    "wof:name":"Yevlevo",
    "wof:placetype":"locality"
},
  "geometry": {"coordinates":[52.2366,55.5199],"type":"Point"}
}