{
  "type": "Feature",
  "properties": {
    "gn:admin1_code":"62",
    "gn:asciiname":"Sten'kino",
    "gn:country_code":"RU",
    "gn:dem":166,
    "gn:feature_class":"P",
    "gn:feature_code":"PPL",
    "gn:name":"Sten\u2019kino",
    "gn:population":0,
    "gn:timezone":"Europe/Moscow",
    "iso:country":"RU",
    "name:rus_x_preferred":[
        "\u0421\u0442\u0435\u043d\u044c\u043a\u0438\u043d\u043e"
    ],
    "name:und_x_variant":[
        "Sten\u2019kino"
    ],
    "wof:name":"Sten'kino",
    "wof:placetype":"locality"
},
  "geometry": {"coordinates":[39.7265,54.5417],"type":"Point"}
}