{
  "type": "Feature",
  "properties": {
    "gn:admin1_code":"85",
    "gn:asciiname":"Striga",
    "gn:country_code":"RU",
    "gn:dem":65,
    "gn:feature_class":"P",
    "gn:feature_code":"PPL",
    "gn:name":"Striga",
    "gn:population":0,
    "gn:timezone":"Europe/Moscow",
    "iso:country":"RU",
    "name:rus_x_preferred":[
        "\u0421\u0442\u0440\u0438\u0433\u0430"
    ],
    "name:und_x_variant":[
        "\u0421\u0442\u0440\u0438\u0433\u0430"
    ],
    "wof:name":"Striga",
    "wof:placetype":"locality"
},
  "geometry": {"coordinates":[46.3384,60.7952],"type":"Point"}
}