{
  "type": "Feature",
  "properties": {
    "gn:admin1_code":"85",
    "gn:asciiname":"Striga",
    "gn:country_code":"RU",
    "gn:dem":65,
    "gn:feature_class":"P",
    "gn:feature_code":"PPL",
    "gn:name":"Striga",
    "gn:population":0,
    "gn:timezone":"Europe/Moscow",
    "iso:country":"RU",
    "name:ara_x_preferred":[
        "\u062f\u063a\u0644 \u0627\u0644\u0633\u0627\u062d\u0631\u0629"
    ],
    "name:cat_x_preferred":[
        "Striga"
    ],
    "name:ceb_x_preferred":[
        "Striga"
    ],
    "name:deu_x_preferred":[
        "Striga"
    ],
    "name:fra_x_preferred":[
        "Striga"
    ],
    "name:jpn_x_preferred":[
        "\u30b9\u30c8\u30e9\u30a4\u30ac\u5c5e"
    ],
    "name:kor_x_preferred":[
        "\uc2a4\ud2b8\ub9ac\uac00"
    ],
    "name:nld_x_preferred":[
        "Striga"
    ],
    "name:pol_x_preferred":[
        "Striga"
    ],
    "name:por_x_preferred":[
        "Striga"
    ],
    "name:rus_x_preferred":[
        "\u0421\u0442\u0440\u0438\u0433\u0430"
    ],
    "name:sna_x_preferred":[
        "Karoyi"
    ],
    "name:spa_x_preferred":[
        "Striga"
    ],
    "name:swa_x_preferred":[
        "Guguchawi"
    ],
    "name:swe_x_preferred":[
        "Striga"
    ],
    "name:und_x_variant":[
        "\u0421\u0442\u0440\u0438\u0433\u0430"
    ],
    "name:war_x_preferred":[
        "Striga"
    ],
    "name:zho_x_preferred":[
        "\u72ec\u811a\u91d1\u5c5e"
    ],
    "wof:name":"Striga",
    "wof:placetype":"locality"
},
  "geometry": {"coordinates":[46.3384,60.7952],"type":"Point"}
}