{
  "type": "Feature",
  "properties": {
    "gn:admin1_code":"72",
    "gn:asciiname":"Maslovka",
    "gn:country_code":"RU",
    "gn:dem":135,
    "gn:feature_class":"P",
    "gn:feature_code":"PPL",
    "gn:name":"Maslovka",
    "gn:population":0,
    "gn:timezone":"Europe/Moscow",
    "iso:country":"RU",
    "name:rus_x_preferred":[
        "\u041c\u0430\u0441\u043b\u043e\u0432\u043a\u0430"
    ],
    "wof:name":"Maslovka",
    "wof:placetype":"locality"
},
  "geometry": {"coordinates":[41.28083,52.46278],"type":"Point"}
}