{
  "type": "Feature",
  "properties": {
    "gn:admin1_code":"73",
    "gn:asciiname":"Poltavka",
    "gn:country_code":"RU",
    "gn:dem":323,
    "gn:feature_class":"P",
    "gn:feature_code":"PPL",
    "gn:name":"Poltavka",
    "gn:population":0,
    "gn:timezone":"Asia/Yekaterinburg",
    "iso:country":"RU",
    "name:rus_x_preferred":[
        "\u041f\u043e\u043b\u0442\u0430\u0432\u043a\u0430"
    ],
    "name:und_x_variant":[
        "\u041f\u043e\u043b\u0442\u0430\u0432\u043a\u0430"
    ],
    "wof:name":"Poltavka",
    "wof:placetype":"locality"
},
  "geometry": {"coordinates":[52.5661,54.3499],"type":"Point"}
}