{
  "type": "Feature",
  "properties": {
    "gn:admin1_code":"69",
    "gn:asciiname":"Kuleshevo",
    "gn:country_code":"RU",
    "gn:dem":234,
    "gn:feature_class":"P",
    "gn:feature_code":"PPL",
    "gn:name":"Kuleshevo",
    "gn:population":0,
    "gn:timezone":"Europe/Moscow",
    "iso:country":"RU",
    "name:rus_x_preferred":[
        "\u041a\u0443\u043b\u0435\u0448\u0435\u0432\u043e"
    ],
    "wof:name":"Kuleshevo",
    "wof:placetype":"locality"
},
  "geometry": {"coordinates":[33.85889,55.245],"type":"Point"}
}