{
  "type": "Feature",
  "properties": {
    "gn:admin1_code":"77",
    "gn:asciiname":"Borkino",
    "gn:country_code":"RU",
    "gn:dem":250,
    "gn:feature_class":"P",
    "gn:feature_code":"PPL",
    "gn:name":"Borkino",
    "gn:population":0,
    "gn:timezone":"Europe/Moscow",
    "iso:country":"RU",
    "name:rus_x_preferred":[
        "\u0411\u043e\u0440\u043a\u0438\u043d\u043e"
    ],
    "name:und_x_variant":[
        "\u0411\u043e\u0440\u043a\u0438\u043d\u043e"
    ],
    "wof:name":"Borkino",
    "wof:placetype":"locality"
},
  "geometry": {"coordinates":[34.52897,56.72751],"type":"Point"}
}