{
  "type": "Feature",
  "properties": {
    "gn:admin1_code":"6",
    "gn:asciiname":"Ostakhino",
    "gn:cc2":"RU",
    "gn:country_code":"RU",
    "gn:dem":109,
    "gn:feature_class":"P",
    "gn:feature_code":"PPL",
    "gn:name":"Ostakhino",
    "gn:population":0,
    "gn:timezone":"Europe/Moscow",
    "iso:country":"RU",
    "name:eng_x_preferred":[
        "Ostakhino"
    ],
    "name:nor_x_preferred":[
        "Ostakhino"
    ],
    "name:rus_x_preferred":[
        "\u041e\u0441\u0442\u0430\u0445\u0438\u043d\u043e"
    ],
    "name:und_x_variant":[
        "Ostakhinskaya"
    ],
    "wof:name":"Ostakhino",
    "wof:placetype":"locality"
},
  "geometry": {"coordinates":[42.21972,61.91167],"type":"Point"}
}