{
  "type": "Feature",
  "properties": {
    "gn:admin1_code":"13.0",
    "gn:asciiname":"Anbashskaya",
    "gn:country_code":"RU",
    "gn:dem":263,
    "gn:feature_class":"P",
    "gn:feature_code":"PPL",
    "gn:name":"Anbashskaya",
    "gn:population":0,
    "gn:timezone":"Asia/Yekaterinburg",
    "iso:country":"RU",
    "name:rus_x_preferred":[
        "\u0410\u043d\u0431\u0430\u0448\u0441\u043a\u0430\u044f"
    ],
    "wof:name":"Anbashskaya",
    "wof:placetype":"locality"
},
  "geometry": {"coordinates":[60.5363,55.6416],"type":"Point"}
}