{
  "type": "Feature",
  "properties": {
    "gn:admin1_code":"57.0",
    "gn:asciiname":"Zhelobok",
    "gn:country_code":"RU",
    "gn:dem":239,
    "gn:feature_class":"P",
    "gn:feature_code":"PPL",
    "gn:name":"Zhelobok",
    "gn:population":0,
    "gn:timezone":"Europe/Moscow",
    "iso:country":"RU",
    "name:rus_x_preferred":[
        "\u0416\u0435\u043b\u043e\u0431\u043e\u043a"
    ],
    "wof:name":"Zhelobok",
    "wof:placetype":"locality"
},
  "geometry": {"coordinates":[45.37512,53.16208],"type":"Point"}
}