{
  "type": "Feature",
  "properties": {
    "gn:admin1_code":"71",
    "gn:asciiname":"Razdol'ye",
    "gn:country_code":"RU",
    "gn:dem":63,
    "gn:feature_class":"P",
    "gn:feature_code":"PPL",
    "gn:name":"Razdol\u2019ye",
    "gn:population":0,
    "gn:timezone":"Asia/Yekaterinburg",
    "iso:country":"RU",
    "name:rus_x_preferred":[
        "\u0420\u0430\u0437\u0434\u043e\u043b\u044c\u0435"
    ],
    "name:und_x_variant":[
        "Razdol\u2019ye"
    ],
    "wof:name":"Razdol'ye",
    "wof:placetype":"locality"
},
  "geometry": {"coordinates":[64.41425,57.63799],"type":"Point"}
}