{
  "type": "Feature",
  "properties": {
    "gn:admin1_code":"60",
    "gn:asciiname":"Proshkino",
    "gn:country_code":"RU",
    "gn:dem":91,
    "gn:feature_class":"P",
    "gn:feature_code":"PPL",
    "gn:name":"Proshkino",
    "gn:population":0,
    "gn:timezone":"Europe/Moscow",
    "iso:country":"RU",
    "name:rus_x_preferred":[
        "\u041f\u0440\u043e\u0448\u043a\u0438\u043d\u043e"
    ],
    "name:und_x_variant":[
        "\u041f\u0440\u043e\u0448\u043a\u0438\u043d\u043e"
    ],
    "wof:name":"Proshkino",
    "wof:placetype":"locality"
},
  "geometry": {"coordinates":[28.2855,58.1702],"type":"Point"}
}