{
  "type": "Feature",
  "properties": {
    "gn:admin1_code":"91",
    "gn:asciiname":"Tolstomysovo",
    "gn:country_code":"RU",
    "gn:dem":172,
    "gn:feature_class":"P",
    "gn:feature_code":"PPL",
    "gn:name":"Tolstomysovo",
    "gn:population":0,
    "gn:timezone":"Asia/Krasnoyarsk",
    "iso:country":"RU",
    "name:eng_x_preferred":[
        "Tolstomysovo"
    ],
    "name:nor_x_preferred":[
        "Tolstomysovo"
    ],
    "name:rus_x_preferred":[
        "\u0422\u043e\u043b\u0441\u0442\u043e\u043c\u044b\u0441\u043e\u0432\u043e"
    ],
    "wof:name":"Tolstomysovo",
    "wof:placetype":"locality"
},
  "geometry": {"coordinates":[93.37778,56.41889000000001],"type":"Point"}
}