{
  "type": "Feature",
  "properties": {
    "gn:admin1_code":"64",
    "gn:asciiname":"Muz'ma",
    "gn:country_code":"RU",
    "gn:dem":1,
    "gn:feature_class":"P",
    "gn:feature_code":"PPL",
    "gn:name":"Muz\u2019ma",
    "gn:population":0,
    "gn:timezone":"Asia/Sakhalin",
    "iso:country":"RU",
    "name:rus_x_preferred":[
        "\u041c\u0443\u0437\u044c\u043c\u0430"
    ],
    "name:und_x_variant":[
        "Muz\u2019m",
        "Muz\u2019ma"
    ],
    "wof:name":"Muz'ma",
    "wof:placetype":"locality"
},
  "geometry": {"coordinates":[141.81666999999999,53.23333],"type":"Point"}
}