{
  "type": "Feature",
  "properties": {
    "gn:admin1_code":"77.0",
    "gn:asciiname":"Ferezna",
    "gn:country_code":"RU",
    "gn:dem":138,
    "gn:feature_class":"P",
    "gn:feature_code":"PPL",
    "gn:name":"Ferezna",
    "gn:population":0,
    "gn:timezone":"Europe/Moscow",
    "iso:country":"RU",
    "name:rus_x_preferred":[
        "\u0424\u0435\u0440\u0435\u0437\u043d\u0430"
    ],
    "wof:name":"Ferezna",
    "wof:placetype":"locality"
},
  "geometry": {"coordinates":[35.74148,57.70539],"type":"Point"}
}