{
  "type": "Feature",
  "properties": {
    "gn:admin1_code":"77",
    "gn:asciiname":"Panshino",
    "gn:country_code":"RU",
    "gn:dem":145,
    "gn:feature_class":"P",
    "gn:feature_code":"PPL",
    "gn:name":"Panshino",
    "gn:population":0,
    "gn:timezone":"Europe/Moscow",
    "iso:country":"RU",
    "name:rus_x_preferred":[
        "\u041f\u0430\u043d\u0448\u0438\u043d\u043e"
    ],
    "wof:name":"Panshino",
    "wof:placetype":"locality"
},
  "geometry": {"coordinates":[36.2516,58.3894],"type":"Point"}
}