{
  "type": "Feature",
  "properties": {
    "gn:country":"RU",
    "gn:fcode":"ADMD",
    "gn:population":0,
    "iso:country":"RU",
    "name:eng_x_preferred":[
        "Dmitrovskiy Rayon"
    ],
    "name:rus_x_preferred":[
        "\u0414\u043c\u0438\u0442\u0440\u043e\u0432\u0441\u043a\u0438\u0439 \u0440\u0430\u0439\u043e\u043d"
    ],
    "qs:name":"Dmitrovskiy Rayon",
    "qs:photos_9r":0,
    "qs:photos_sr":0,
    "qs:pop_sr":"0",
    "wof:name":"Dmitrovskiy Rayon",
    "wof:placetype":"localadmin",
    "wof:population":0
},
  "geometry": {"coordinates":[37.58333,56.35],"type":"Point"}
}