{
  "type": "Feature",
  "properties": {
    "gn:admin1_code":"55",
    "gn:asciiname":"Ponomarevskiy",
    "gn:cc2":"RU",
    "gn:country_code":"RU",
    "gn:dem":245,
    "gn:feature_class":"P",
    "gn:feature_code":"PPL",
    "gn:name":"Ponomar\u00ebvskiy",
    "gn:population":0,
    "gn:timezone":"Asia/Yekaterinburg",
    "iso:country":"RU",
    "name:rus_x_preferred":[
        "\u041f\u043e\u043d\u043e\u043c\u0430\u0440\u0451\u0432\u0441\u043a\u0438\u0439"
    ],
    "name:und_x_variant":[
        "Ponomarevka",
        "Ponomar\u00ebvskiy"
    ],
    "wof:name":"Ponomarevskiy",
    "wof:placetype":"locality"
},
  "geometry": {"coordinates":[53.93333000000001,53.26667],"type":"Point"}
}