{
  "type": "Feature",
  "properties": {
    "gn:admin1_code":"10",
    "gn:asciiname":"Prolysovo",
    "gn:country_code":"RU",
    "gn:dem":165,
    "gn:feature_class":"P",
    "gn:feature_code":"PPL",
    "gn:name":"Prolysovo",
    "gn:population":0,
    "gn:timezone":"Europe/Moscow",
    "iso:country":"RU",
    "name:eng_x_preferred":[
        "Prolysovo"
    ],
    "name:nor_x_preferred":[
        "Prolysovo"
    ],
    "name:rus_x_preferred":[
        "\u041f\u0440\u043e\u043b\u044b\u0441\u043e\u0432\u043e"
    ],
    "name:und_x_variant":[
        "Prolysoye"
    ],
    "wof:name":"Prolysovo",
    "wof:placetype":"locality"
},
  "geometry": {"coordinates":[34.13310999999999,52.87463],"type":"Point"}
}