{
  "type": "Feature",
  "properties": {
    "gn:admin1_code":"41",
    "gn:asciiname":"Zhidenovka",
    "gn:country_code":"RU",
    "gn:dem":170,
    "gn:feature_class":"P",
    "gn:feature_code":"PPL",
    "gn:name":"Zhid\u00ebnovka",
    "gn:population":0,
    "gn:timezone":"Europe/Moscow",
    "iso:country":"RU",
    "name:rus_x_preferred":[
        "\u0416\u0438\u0434\u0451\u043d\u043e\u0432\u043a\u0430"
    ],
    "name:und_x_variant":[
        "Zhed\u00ebnovka",
        "Zhid\u00ebnovka"
    ],
    "wof:name":"Zhidenovka",
    "wof:placetype":"locality"
},
  "geometry": {"coordinates":[34.9156,52.03656],"type":"Point"}
}