{
  "type": "Feature",
  "properties": {
    "gn:admin1_code":"54",
    "gn:asciiname":"Nemirovka",
    "gn:country_code":"RU",
    "gn:dem":116,
    "gn:feature_class":"P",
    "gn:feature_code":"PPL",
    "gn:name":"Nemirovka",
    "gn:population":0,
    "gn:timezone":"Asia/Omsk",
    "iso:country":"RU",
    "name:eng_x_preferred":[
        "Nemirovka"
    ],
    "name:nor_x_preferred":[
        "Nemirovka"
    ],
    "name:rus_x_preferred":[
        "\u041d\u0435\u043c\u0438\u0440\u043e\u0432\u043a\u0430"
    ],
    "wof:name":"Nemirovka",
    "wof:placetype":"locality"
},
  "geometry": {"coordinates":[73.88138000000002,54.92527],"type":"Point"}
}