{
  "type": "Feature",
  "properties": {
    "gn:admin1_code":"60",
    "gn:asciiname":"Osinkina",
    "gn:country_code":"RU",
    "gn:dem":75,
    "gn:feature_class":"P",
    "gn:feature_code":"PPL",
    "gn:name":"Osinkina",
    "gn:population":0,
    "gn:timezone":"Europe/Moscow",
    "iso:country":"RU",
    "name:rus_x_preferred":[
        "\u041e\u0441\u0438\u043d\u043a\u0438\u043d\u0430"
    ],
    "name:und_x_variant":[
        "Osinkino",
        "Osinkina"
    ],
    "wof:name":"Osinkina",
    "wof:placetype":"locality"
},
  "geometry": {"coordinates":[29.23821,57.09849000000001],"type":"Point"}
}