{
  "type": "Feature",
  "properties": {
    "gn:admin1_code":"20",
    "gn:asciiname":"Nashata",
    "gn:country_code":"RU",
    "gn:dem":537,
    "gn:feature_class":"P",
    "gn:feature_code":"PPL",
    "gn:name":"Nashata",
    "gn:population":0,
    "gn:timezone":"Asia/Irkutsk",
    "iso:country":"RU",
    "name:eng_x_preferred":[
        "Nashata"
    ],
    "name:nor_x_preferred":[
        "Nasjata"
    ],
    "name:rus_x_preferred":[
        "\u041d\u0430\u0448\u0430\u0442\u0430"
    ],
    "name:und_x_variant":[
        "Nashatinski",
        "Nashatinskiy"
    ],
    "wof:name":"Nashata",
    "wof:placetype":"locality"
},
  "geometry": {"coordinates":[104.43083,53.24278],"type":"Point"}
}