{
  "type": "Feature",
  "properties": {
    "gn:admin1_code":"63",
    "gn:asciiname":"Chernousovo",
    "gn:cc2":"RU",
    "gn:country_code":"RU",
    "gn:dem":4,
    "gn:feature_class":"P",
    "gn:feature_code":"PPL",
    "gn:name":"Chernousovo",
    "gn:population":0,
    "gn:timezone":"Asia/Magadan",
    "iso:country":"RU",
    "name:rus_x_preferred":[
        "\u0427\u0435\u0440\u043d\u043e\u0443\u0441\u043e\u0432\u043e"
    ],
    "name:und_x_variant":[
        "Chernousova",
        "Chernousovo",
        "\u0427\u0435\u0440\u043d\u043e\u0443\u0441\u043e\u0432\u043e"
    ],
    "wof:name":"Chernousovo",
    "wof:placetype":"locality"
},
  "geometry": {"coordinates":[161.28333000000001,68.83333],"type":"Point"}
}