{
  "type": "Feature",
  "properties": {
    "gn:admin1_code":"10",
    "gn:asciiname":"Gorozhanskiy",
    "gn:country_code":"RU",
    "gn:dem":169,
    "gn:feature_class":"P",
    "gn:feature_code":"PPL",
    "gn:name":"Gorozhanskiy",
    "gn:population":0,
    "gn:timezone":"Europe/Moscow",
    "iso:country":"RU",
    "name:rus_x_preferred":[
        "\u0413\u043e\u0440\u043e\u0436\u0430\u043d\u0441\u043a\u0438\u0439"
    ],
    "name:und_x_variant":[
        "\u0413\u043e\u0440\u043e\u0436\u0430\u043d\u0441\u043a\u0438\u0439"
    ],
    "wof:name":"Gorozhanskiy",
    "wof:placetype":"locality"
},
  "geometry": {"coordinates":[34.03722,52.29667],"type":"Point"}
}