{
  "type": "Feature",
  "properties": {
    "gn:admin1_code":"28",
    "gn:asciiname":"Khirvisal'ma",
    "gn:country_code":"RU",
    "gn:dem":170,
    "gn:feature_class":"P",
    "gn:feature_code":"PPL",
    "gn:name":"Khirvisal\u2019ma",
    "gn:population":0,
    "gn:timezone":"Europe/Moscow",
    "iso:country":"RU",
    "name:eng_x_preferred":[
        "Khirvisal'ma"
    ],
    "name:fin_x_preferred":[
        "Hirvisalmi"
    ],
    "name:nor_x_preferred":[
        "Khirvisalmi"
    ],
    "name:rus_x_preferred":[
        "\u0425\u0438\u0440\u0432\u0438\u0441\u0430\u043b\u043c\u0438"
    ],
    "name:rus_x_variant":[
        "\u0425\u0438\u0440\u0432\u0438\u0441\u0430\u043b\u044c\u043c\u0430"
    ],
    "name:und_x_variant":[
        "Khirvisal\u2019ma",
        "\u0425\u0438\u0440\u0432\u0438\u0441\u0430\u043b\u044c\u043c\u0430"
    ],
    "wof:name":"Khirvisal'ma",
    "wof:placetype":"locality"
},
  "geometry": {"coordinates":[30.75934,65.48595],"type":"Point"}
}