{
  "type": "Feature",
  "properties": {
    "gn:admin1_code":"86",
    "gn:asciiname":"Verkhosnovka",
    "gn:country_code":"RU",
    "gn:dem":191,
    "gn:feature_class":"P",
    "gn:feature_code":"PPL",
    "gn:name":"Verkhosnovka",
    "gn:population":0,
    "gn:timezone":"Europe/Moscow",
    "iso:country":"RU",
    "name:rus_x_preferred":[
        "\u0412\u0435\u0440\u0445\u043e\u0441\u043d\u043e\u0432\u043a\u0430"
    ],
    "wof:name":"Verkhosnovka",
    "wof:placetype":"locality"
},
  "geometry": {"coordinates":[38.5623,51.9935],"type":"Point"}
}