{
  "type": "Feature",
  "properties": {
    "gn:admin1_code":"33.0",
    "gn:asciiname":"Nizhnyaya Kokovka",
    "gn:country_code":"RU",
    "gn:dem":91,
    "gn:feature_class":"P",
    "gn:feature_code":"PPL",
    "gn:name":"Nizhnyaya Kokovka",
    "gn:population":0,
    "gn:timezone":"Europe/Kirov",
    "iso:country":"RU",
    "name:rus_x_preferred":[
        "\u041d\u0438\u0436\u043d\u044f\u044f \u041a\u043e\u043a\u043e\u0432\u043a\u0430"
    ],
    "wof:name":"Nizhnyaya Kokovka",
    "wof:placetype":"locality"
},
  "geometry": {"coordinates":[48.58761,57.58954],"type":"Point"}
}