{
  "type": "Feature",
  "properties": {
    "gn:admin1_code":"33.0",
    "gn:asciiname":"Vakhrushonki",
    "gn:country_code":"RU",
    "gn:dem":189,
    "gn:feature_class":"P",
    "gn:feature_code":"PPL",
    "gn:name":"Vakhrushonki",
    "gn:population":0,
    "gn:timezone":"Europe/Kirov",
    "iso:country":"RU",
    "name:rus_x_preferred":[
        "\u0412\u0430\u0445\u0440\u0443\u0448\u043e\u043d\u043a\u0438"
    ],
    "wof:name":"Vakhrushonki",
    "wof:placetype":"locality"
},
  "geometry": {"coordinates":[48.49639000000001,59.08694000000001],"type":"Point"}
}