{
  "type": "Feature",
  "properties": {
    "gn:admin1_code":"88",
    "gn:asciiname":"Mertvichino",
    "gn:country_code":"RU",
    "gn:dem":226,
    "gn:feature_class":"P",
    "gn:feature_code":"PPL",
    "gn:name":"Mertvichino",
    "gn:population":0,
    "gn:timezone":"Europe/Moscow",
    "iso:country":"RU",
    "name:rus_x_preferred":[
        "\u041c\u0435\u0440\u0442\u0432\u0438\u0447\u0438\u043d\u043e"
    ],
    "name:und_x_variant":[
        "\u041c\u0435\u0440\u0442\u0432\u0438\u0447\u0438\u043d\u043e",
        "Mertvigino",
        "Mertvitino"
    ],
    "wof:name":"Mertvichino",
    "wof:placetype":"locality"
},
  "geometry": {"coordinates":[38.5653,57.2212],"type":"Point"}
}