{
  "type": "Feature",
  "properties": {
    "gn:admin1_code":"34",
    "gn:asciiname":"Varlamovka",
    "gn:country_code":"RU",
    "gn:dem":102,
    "gn:feature_class":"P",
    "gn:feature_code":"PPL",
    "gn:name":"Varlamovka",
    "gn:population":0,
    "gn:timezone":"Europe/Moscow",
    "iso:country":"RU",
    "name:eng_x_preferred":[
        "Varlamovka"
    ],
    "name:nor_x_preferred":[
        "Varlamovka"
    ],
    "name:rus_x_preferred":[
        "\u0412\u0430\u0440\u043b\u0430\u043c\u043e\u0432\u043a\u0430"
    ],
    "name:und_x_variant":[
        "Varlam",
        "Varlmovka",
        "Varlamovo",
        "Varlamovka"
    ],
    "wof:name":"Varlamovka",
    "wof:placetype":"locality"
},
  "geometry": {"coordinates":[54.88599,61.90962],"type":"Point"}
}