{
  "type": "Feature",
  "properties": {
    "gn:admin1_code":"86",
    "gn:asciiname":"Okry",
    "gn:country_code":"RU",
    "gn:dem":110,
    "gn:feature_class":"P",
    "gn:feature_code":"PPL",
    "gn:name":"Okry",
    "gn:population":0,
    "gn:timezone":"Europe/Moscow",
    "iso:country":"RU",
    "name:rus_x_preferred":[
        "\u041e\u043a\u0440\u044b"
    ],
    "name:und_x_variant":[
        "Akry",
        "Okry",
        "\u041e\u043a\u0440\u044b"
    ],
    "wof:name":"Okry",
    "wof:placetype":"locality"
},
  "geometry": {"coordinates":[41.51889,51.72306],"type":"Point"}
}