{
  "type": "Feature",
  "properties": {
    "gn:admin1_code":"33",
    "gn:asciiname":"Nemchenyata",
    "gn:country_code":"RU",
    "gn:dem":147,
    "gn:feature_class":"P",
    "gn:feature_code":"PPL",
    "gn:name":"Nemchenyata",
    "gn:population":0,
    "gn:timezone":"Europe/Kirov",
    "iso:country":"RU",
    "name:rus_x_preferred":[
        "\u041d\u0435\u043c\u0447\u0435\u043d\u044f\u0442\u0430"
    ],
    "name:und_x_variant":[
        "Nemchanyato",
        "Nemchenyata",
        "\u041d\u0435\u043c\u0447\u0435\u043d\u044f\u0442\u0430"
    ],
    "wof:name":"Nemchenyata",
    "wof:placetype":"locality"
},
  "geometry": {"coordinates":[47.05958,58.29345],"type":"Point"}
}