{
  "type": "Feature",
  "properties": {
    "gn:admin1_code":"51",
    "gn:asciiname":"Maloye Okulovo",
    "gn:country_code":"RU",
    "gn:dem":82,
    "gn:feature_class":"P",
    "gn:feature_code":"PPL",
    "gn:name":"Maloye Okulovo",
    "gn:population":0,
    "gn:timezone":"Europe/Moscow",
    "iso:country":"RU",
    "name:rus_x_preferred":[
        "\u041c\u0430\u043b\u043e\u0435 \u041e\u043a\u0443\u043b\u043e\u0432\u043e"
    ],
    "wof:name":"Maloye Okulovo",
    "wof:placetype":"locality"
},
  "geometry": {"coordinates":[42.1294,55.5774],"type":"Point"}
}