{
  "type": "Feature",
  "properties": {
    "gn:admin1_code":"90",
    "gn:asciiname":"Kamsplav",
    "gn:country_code":"RU",
    "gn:dem":113,
    "gn:feature_class":"P",
    "gn:feature_code":"PPL",
    "gn:name":"Kamsplav",
    "gn:population":0,
    "gn:timezone":"Asia/Yekaterinburg",
    "iso:country":"RU",
    "name:rus_x_preferred":[
        "\u041a\u0430\u043c\u0441\u043f\u043b\u0430\u0432"
    ],
    "wof:name":"Kamsplav",
    "wof:placetype":"locality"
},
  "geometry": {"coordinates":[57.3301,58.2069],"type":"Point"}
}