{
  "type": "Feature",
  "properties": {
    "gn:admin1_code":"85",
    "gn:asciiname":"Romashevskiy",
    "gn:country_code":"RU",
    "gn:dem":90,
    "gn:feature_class":"P",
    "gn:feature_code":"PPL",
    "gn:name":"Romashevskiy",
    "gn:population":0,
    "gn:timezone":"Europe/Moscow",
    "iso:country":"RU",
    "name:rus_x_preferred":[
        "\u0420\u043e\u043c\u0430\u0448\u0435\u0432\u0441\u043a\u0438\u0439"
    ],
    "wof:name":"Romashevskiy",
    "wof:placetype":"locality"
},
  "geometry": {"coordinates":[43.34247,60.49813],"type":"Point"}
}