{
  "type": "Feature",
  "properties": {
    "gn:admin1_code":"17",
    "gn:asciiname":"Moksob",
    "gn:country_code":"RU",
    "gn:dem":26,
    "gn:feature_class":"P",
    "gn:feature_code":"PPL",
    "gn:name":"Moksob",
    "gn:population":0,
    "gn:timezone":"Europe/Moscow",
    "iso:country":"RU",
    "name:rus_x_preferred":[
        "\u041c\u043e\u043a\u0441\u043e\u0431"
    ],
    "wof:name":"Moksob",
    "wof:placetype":"locality"
},
  "geometry": {"coordinates":[46.48735,43.43469],"type":"Point"}
}