{
  "type": "Feature",
  "properties": {
    "gn:admin1_code":"13",
    "gn:asciiname":"Vishnevyy",
    "gn:country_code":"RU",
    "gn:dem":302,
    "gn:feature_class":"P",
    "gn:feature_code":"PPL",
    "gn:name":"Vishn\u00ebvyy",
    "gn:population":0,
    "gn:timezone":"Asia/Yekaterinburg",
    "iso:country":"RU",
    "name:eng_x_preferred":[
        "Vishn\u00ebvyy"
    ],
    "name:nor_x_preferred":[
        "Visjnevyj"
    ],
    "name:rus_x_preferred":[
        "\u0412\u0438\u0448\u043d\u0435\u0432\u044b\u0439"
    ],
    "name:rus_x_variant":[
        "\u0412\u0438\u0448\u043d\u0451\u0432\u044b\u0439"
    ],
    "name:und_x_variant":[
        "Vishn\u00ebvyy"
    ],
    "wof:name":"Vishnevyy",
    "wof:placetype":"locality"
},
  "geometry": {"coordinates":[60.6089,52.9415],"type":"Point"}
}