{
  "type": "Feature",
  "properties": {
    "gn:admin1_code":"16",
    "gn:asciiname":"Kalaykasy",
    "gn:country_code":"RU",
    "gn:dem":195,
    "gn:feature_class":"P",
    "gn:feature_code":"PPL",
    "gn:name":"Kalaykasy",
    "gn:population":0,
    "gn:timezone":"Europe/Moscow",
    "iso:country":"RU",
    "name:eng_x_preferred":[
        "Kalaykasy"
    ],
    "name:nor_x_preferred":[
        "Kadikasy"
    ],
    "name:rus_x_preferred":[
        "\u041a\u0430\u0434\u0438\u043a\u0430\u0441\u044b"
    ],
    "name:rus_x_variant":[
        "\u041a\u0430\u043b\u0430\u0439\u043a\u0430\u0441\u044b"
    ],
    "name:und_x_variant":[
        "Kalai-Kasy",
        "Kalaykasy",
        "\u041a\u0430\u043b\u0430\u0439\u043a\u0430\u0441\u044b"
    ],
    "wof:name":"Kalaykasy",
    "wof:placetype":"locality"
},
  "geometry": {"coordinates":[46.88056,56.05967],"type":"Point"}
}