{
  "type": "Feature",
  "properties": {
    "gn:admin1_code":"67",
    "gn:asciiname":"Prudovoy",
    "gn:country_code":"RU",
    "gn:dem":208,
    "gn:feature_class":"P",
    "gn:feature_code":"PPL",
    "gn:name":"Prudovoy",
    "gn:population":0,
    "gn:timezone":"Europe/Saratov",
    "iso:country":"RU",
    "name:eng_x_preferred":[
        "Prudovoy"
    ],
    "name:nor_x_preferred":[
        "Prudovoj"
    ],
    "name:rus_x_preferred":[
        "\u041f\u0440\u0443\u0434\u043e\u0432\u043e\u0439"
    ],
    "wof:name":"Prudovoy",
    "wof:placetype":"locality"
},
  "geometry": {"coordinates":[44.3848,51.9966],"type":"Point"}
}