{
  "type": "Feature",
  "properties": {
    "gn:admin1_code":"88",
    "gn:asciiname":"Ovsetsovka",
    "gn:country_code":"RU",
    "gn:dem":137,
    "gn:feature_class":"P",
    "gn:feature_code":"PPL",
    "gn:name":"Ovsetsovka",
    "gn:population":0,
    "gn:timezone":"Europe/Moscow",
    "iso:country":"RU",
    "name:rus_x_preferred":[
        "\u041e\u0432\u0441\u0435\u0446\u043e\u0432\u043a\u0430"
    ],
    "wof:name":"Ovsetsovka",
    "wof:placetype":"locality"
},
  "geometry": {"coordinates":[39.03778,57.66395],"type":"Point"}
}