{
  "type": "Feature",
  "properties": {
    "gn:admin1_code":"5",
    "gn:asciiname":"Yadrino",
    "gn:country_code":"RU",
    "gn:dem":219,
    "gn:feature_class":"P",
    "gn:feature_code":"PPL",
    "gn:name":"Yadrino",
    "gn:population":0,
    "gn:timezone":"Asia/Vladivostok",
    "iso:country":"RU",
    "name:che_x_preferred":[
        "\u042f\u0434\u0440\u0438\u043d\u043e"
    ],
    "name:eng_x_preferred":[
        "Yadrino"
    ],
    "name:nor_x_preferred":[
        "Jadrino"
    ],
    "name:rus_x_preferred":[
        "\u042f\u0434\u0440\u0438\u043d\u043e"
    ],
    "name:tgk_x_preferred":[
        "\u042f\u0434\u0440\u0438\u043d\u043e"
    ],
    "name:und_x_variant":[
        "Yadrin",
        "Yadrino"
    ],
    "wof:name":"Yadrino",
    "wof:placetype":"locality"
},
  "geometry": {"coordinates":[131.02516,48.975],"type":"Point"}
}