{
  "type": "Feature",
  "properties": {
    "gn:admin1_code":"85.0",
    "gn:asciiname":"Shugino",
    "gn:country_code":"RU",
    "gn:dem":138,
    "gn:feature_class":"P",
    "gn:feature_code":"PPL",
    "gn:name":"Shugino",
    "gn:population":0,
    "gn:timezone":"Europe/Moscow",
    "iso:country":"RU",
    "name:rus_x_preferred":[
        "\u0428\u0443\u0433\u0438\u043d\u043e"
    ],
    "wof:name":"Shugino",
    "wof:placetype":"locality"
},
  "geometry": {"coordinates":[37.7513,60.5222],"type":"Point"}
}