{
  "type": "Feature",
  "properties": {
    "gn:admin1_code":"31",
    "gn:asciiname":"Novorossiyskoye",
    "gn:cc2":"RU",
    "gn:country_code":"RU",
    "gn:dem":350,
    "gn:feature_class":"P",
    "gn:feature_code":"PPL",
    "gn:name":"Novorossiyskoye",
    "gn:population":0,
    "gn:timezone":"Asia/Krasnoyarsk",
    "iso:country":"RU",
    "name:eng_x_preferred":[
        "Novorossiyskoye"
    ],
    "name:nor_x_preferred":[
        "Novorossijskoje"
    ],
    "name:rus_x_preferred":[
        "\u041d\u043e\u0432\u043e\u0440\u043e\u0441\u0441\u0438\u0439\u0441\u043a\u043e\u0435"
    ],
    "name:und_x_variant":[
        "Minusinskiy"
    ],
    "wof:name":"Novorossiyskoye",
    "wof:placetype":"locality"
},
  "geometry": {"coordinates":[91.59083,53.38166999999999],"type":"Point"}
}