{
  "type": "Feature",
  "properties": {
    "gn:admin1_code":"33",
    "gn:asciiname":"Kruteyevskaya",
    "gn:country_code":"RU",
    "gn:dem":167,
    "gn:feature_class":"P",
    "gn:feature_code":"PPL",
    "gn:name":"Kruteyevskaya",
    "gn:population":0,
    "gn:timezone":"Europe/Kirov",
    "iso:country":"RU",
    "name:rus_x_preferred":[
        "\u041a\u0440\u0443\u0442\u0435\u0435\u0432\u0441\u043a\u0430\u044f"
    ],
    "wof:name":"Kruteyevskaya",
    "wof:placetype":"locality"
},
  "geometry": {"coordinates":[49.897,57.9318],"type":"Point"}
}