{
  "type": "Feature",
  "properties": {
    "gn:admin1_code":"77.0",
    "gn:asciiname":"Bol'shaya Molyavnya",
    "gn:country_code":"RU",
    "gn:dem":222,
    "gn:feature_class":"P",
    "gn:feature_code":"PPL",
    "gn:name":"Bol\u2019shaya Molyavnya",
    "gn:population":0,
    "gn:timezone":"Europe/Moscow",
    "iso:country":"RU",
    "name:eng_x_preferred":[
        "Bol'shaya Molyavnya"
    ],
    "name:nor_x_preferred":[
        "Bolsjaja Maljavnja"
    ],
    "name:rus_x_preferred":[
        "\u0411\u043e\u043b\u044c\u0448\u0430\u044f \u041c\u0430\u043b\u044f\u0432\u043d\u044f"
    ],
    "name:rus_x_variant":[
        "\u0411\u043e\u043b\u044c\u0448\u0430\u044f \u041c\u043e\u043b\u044f\u0432\u043d\u044f"
    ],
    "name:und_x_variant":[
        "Malyabnya",
        "Molyavnya",
        "Malyavnya",
        "Bol\u2019shaya Molyavnya"
    ],
    "wof:name":"Bol'shaya Molyavnya",
    "wof:placetype":"locality"
},
  "geometry": {"coordinates":[33.57502,55.95563000000001],"type":"Point"}
}