{
  "type": "Feature",
  "properties": {
    "gn:admin1_code":"42",
    "gn:asciiname":"Malaya Paluya",
    "gn:country_code":"RU",
    "gn:dem":159,
    "gn:feature_class":"P",
    "gn:feature_code":"PPL",
    "gn:name":"Malaya Paluya",
    "gn:population":0,
    "gn:timezone":"Europe/Moscow",
    "iso:country":"RU",
    "name:rus_x_preferred":[
        "\u041c\u0430\u043b\u0430\u044f \u041f\u0430\u043b\u0443\u044f"
    ],
    "name:und_x_variant":[
        "\u041c\u0430\u043b\u0430\u044f \u041f\u0430\u043b\u0443\u044f"
    ],
    "wof:name":"Malaya Paluya",
    "wof:placetype":"locality"
},
  "geometry": {"coordinates":[34.30972,59.86028],"type":"Point"}
}