{
  "type": "Feature",
  "properties": {
    "gn:admin1_code":"88.0",
    "gn:asciiname":"Bukhalovo",
    "gn:country_code":"RU",
    "gn:dem":90,
    "gn:feature_class":"P",
    "gn:feature_code":"PPL",
    "gn:name":"Bukhalovo",
    "gn:population":0,
    "gn:timezone":"Europe/Moscow",
    "iso:country":"RU",
    "name:eng_x_preferred":[
        "Bukhalovo"
    ],
    "name:nor_x_preferred":[
        "Bukhalovo"
    ],
    "name:rus_x_preferred":[
        "\u0411\u0443\u0445\u0430\u043b\u043e\u0432\u043e"
    ],
    "name:und_x_variant":[
        "Sidorovo",
        "Bukholovo"
    ],
    "wof:name":"Bukhalovo",
    "wof:placetype":"locality"
},
  "geometry": {"coordinates":[40.53395,57.944],"type":"Point"}
}