{
  "type": "Feature",
  "properties": {
    "gn:admin1_code":"63",
    "gn:asciiname":"Dva Balagana",
    "gn:country_code":"RU",
    "gn:dem":208,
    "gn:feature_class":"P",
    "gn:feature_code":"PPL",
    "gn:name":"Dva Balagana",
    "gn:population":0,
    "gn:timezone":"Asia/Yakutsk",
    "iso:country":"RU",
    "name:rus_x_preferred":[
        "\u0414\u0432\u0430 \u0411\u0430\u043b\u0430\u0433\u0430\u043d\u0430"
    ],
    "name:und_x_variant":[
        "\u0414\u0432\u0430 \u0411\u0430\u043b\u0430\u0433\u0430\u043d\u0430"
    ],
    "wof:name":"Dva Balagana",
    "wof:placetype":"locality"
},
  "geometry": {"coordinates":[122.76667,70.76666999999998],"type":"Point"}
}