{
  "type": "Feature",
  "properties": {
    "gn:admin1_code":"54",
    "gn:asciiname":"Smolenskiy",
    "gn:country_code":"RU",
    "gn:dem":97,
    "gn:feature_class":"P",
    "gn:feature_code":"PPL",
    "gn:name":"Smolenskiy",
    "gn:population":0,
    "gn:timezone":"Asia/Omsk",
    "iso:country":"RU",
    "name:rus_x_preferred":[
        "\u0421\u043c\u043e\u043b\u0435\u043d\u0441\u043a\u0438\u0439"
    ],
    "wof:name":"Smolenskiy",
    "wof:placetype":"locality"
},
  "geometry": {"coordinates":[72.71666999999999,57.76667],"type":"Point"}
}