{
  "type": "Feature",
  "properties": {
    "gn:admin1_code":"77",
    "gn:asciiname":"Davydovo",
    "gn:country_code":"RU",
    "gn:dem":137,
    "gn:feature_class":"P",
    "gn:feature_code":"PPL",
    "gn:name":"Davydovo",
    "gn:population":0,
    "gn:timezone":"Europe/Moscow",
    "iso:country":"RU",
    "name:rus_x_preferred":[
        "\u0414\u0430\u0432\u044b\u0434\u043e\u0432\u043e"
    ],
    "wof:name":"Davydovo",
    "wof:placetype":"locality"
},
  "geometry": {"coordinates":[36.1517,57.0398],"type":"Point"}
}