{
  "type": "Feature",
  "properties": {
    "gn:admin1_code":"81",
    "gn:asciiname":"Pan'shino",
    "gn:country_code":"RU",
    "gn:dem":68,
    "gn:feature_class":"P",
    "gn:feature_code":"PPL",
    "gn:name":"Pan\u2019shino",
    "gn:population":0,
    "gn:timezone":"Europe/Ulyanovsk",
    "iso:country":"RU",
    "name:eng_x_preferred":[
        "Pan'shino"
    ],
    "name:nor_x_preferred":[
        "Pansjino"
    ],
    "name:rus_x_preferred":[
        "Pan\u2019shino"
    ],
    "name:rus_x_variant":[
        "\u041f\u0430\u043d\u044c\u0448\u0438\u043d\u043e"
    ],
    "wof:name":"Pan'shino",
    "wof:placetype":"locality"
},
  "geometry": {"coordinates":[48.4552,52.9264],"type":"Point"}
}