{
  "type": "Feature",
  "properties": {
    "gn:admin1_code":"84",
    "gn:asciiname":"Verkhnerubezhnyy",
    "gn:country_code":"RU",
    "gn:dem":44,
    "gn:feature_class":"P",
    "gn:feature_code":"PPL",
    "gn:name":"Verkhnerubezhnyy",
    "gn:population":0,
    "gn:timezone":"Europe/Volgograd",
    "iso:country":"RU",
    "name:eng_x_preferred":[
        "Verkhnerubezhnyy"
    ],
    "name:nor_x_preferred":[
        "Verkhnerubezjnyj"
    ],
    "name:rus_x_preferred":[
        "\u0412\u0435\u0440\u0445\u043d\u0435\u0440\u0443\u0431\u0435\u0436\u043d\u044b\u0439"
    ],
    "name:und_x_variant":[
        "Verkhne-Rubezhenskiy",
        "\u0412\u0435\u0440\u0445\u043d\u0435\u0440\u0443\u0431\u0435\u0436\u043d\u044b\u0439",
        "Verkhnerubezhnyy"
    ],
    "wof:name":"Verkhnerubezhnyy",
    "wof:placetype":"locality"
},
  "geometry": {"coordinates":[43.16137,48.25772],"type":"Point"}
}