{
  "type": "Feature",
  "properties": {
    "gn:admin1_code":"25",
    "gn:asciiname":"Shishkino",
    "gn:country_code":"RU",
    "gn:dem":217,
    "gn:feature_class":"P",
    "gn:feature_code":"PPL",
    "gn:name":"Shishkino",
    "gn:population":0,
    "gn:timezone":"Europe/Moscow",
    "iso:country":"RU",
    "name:che_x_preferred":[
        "\u0428\u0438\u0448\u043a\u0438\u043d\u043e"
    ],
    "name:eng_x_preferred":[
        "Shishkino"
    ],
    "name:nor_x_preferred":[
        "Sjisjkino"
    ],
    "name:rus_x_preferred":[
        "\u0428\u0438\u0448\u043a\u0438\u043d\u043e"
    ],
    "wof:name":"Shishkino",
    "wof:placetype":"locality"
},
  "geometry": {"coordinates":[34.74056,54.43861],"type":"Point"}
}