{
  "type": "Feature",
  "properties": {
    "gn:admin1_code":"52.0",
    "gn:asciiname":"Bakharikha",
    "gn:country_code":"RU",
    "gn:dem":109,
    "gn:feature_class":"P",
    "gn:feature_code":"PPL",
    "gn:name":"Bakharikha",
    "gn:population":0,
    "gn:timezone":"Europe/Moscow",
    "iso:country":"RU",
    "name:eng_x_preferred":[
        "Bakharikha"
    ],
    "name:nor_x_preferred":[
        "Bakharikha"
    ],
    "name:rus_x_preferred":[
        "\u0411\u0430\u0445\u0430\u0440\u0438\u0445\u0430"
    ],
    "name:und_x_variant":[
        "\u0411\u0430\u0445\u0430\u0440\u0438\u0445\u0430",
        "Bakharikha"
    ],
    "wof:name":"Bakharikha",
    "wof:placetype":"locality"
},
  "geometry": {"coordinates":[33.08293,58.94945],"type":"Point"}
}