{
  "type": "Feature",
  "properties": {
    "gn:admin1_code":"6",
    "gn:asciiname":"Levogorochnaya",
    "gn:country_code":"RU",
    "gn:dem":128,
    "gn:feature_class":"P",
    "gn:feature_code":"PPL",
    "gn:name":"Levogorochnaya",
    "gn:population":0,
    "gn:timezone":"Europe/Moscow",
    "iso:country":"RU",
    "name:eng_x_preferred":[
        "Levogorochnaya"
    ],
    "name:nor_x_preferred":[
        "Levogorotsjnaja"
    ],
    "name:rus_x_preferred":[
        "\u041b\u0435\u0432\u043e\u0433\u043e\u0440\u043e\u0447\u043d\u0430\u044f"
    ],
    "name:und_x_variant":[
        "\u041b\u0435\u0432\u043e\u0433\u043e\u0440\u043e\u0447\u043d\u0430\u044f",
        "Levogorochnaya"
    ],
    "wof:name":"Levogorochnaya",
    "wof:placetype":"locality"
},
  "geometry": {"coordinates":[43.86694,61.51722],"type":"Point"}
}