{
  "type": "Feature",
  "properties": {
    "gn:admin1_code":"88",
    "gn:asciiname":"Bezmentsevo",
    "gn:country_code":"RU",
    "gn:dem":119,
    "gn:feature_class":"P",
    "gn:feature_code":"PPL",
    "gn:name":"Bezmentsevo",
    "gn:population":0,
    "gn:timezone":"Europe/Moscow",
    "iso:country":"RU",
    "name:rus_x_preferred":[
        "\u0411\u0435\u0437\u043c\u0435\u043d\u0446\u0435\u0432\u043e"
    ],
    "wof:name":"Bezmentsevo",
    "wof:placetype":"locality"
},
  "geometry": {"coordinates":[39.38315,57.35241],"type":"Point"}
}