{
  "type": "Feature",
  "properties": {
    "gn:admin1_code":"73",
    "gn:asciiname":"Petropavlovskoye",
    "gn:country_code":"RU",
    "gn:dem":295,
    "gn:feature_class":"P",
    "gn:feature_code":"PPL",
    "gn:name":"Petropavlovskoye",
    "gn:population":0,
    "gn:timezone":"Europe/Moscow",
    "iso:country":"RU",
    "name:rus_x_preferred":[
        "\u041f\u0435\u0442\u0440\u043e\u043f\u0430\u0432\u043b\u043e\u0432\u0441\u043a\u043e\u0435"
    ],
    "wof:name":"Petropavlovskoye",
    "wof:placetype":"locality"
},
  "geometry": {"coordinates":[53.11666999999999,54.35],"type":"Point"}
}