{
  "type": "Feature",
  "properties": {
    "gn:admin1_code":"38",
    "gn:asciiname":"Starogermanovskiy",
    "gn:cc2":"RU",
    "gn:country_code":"RU",
    "gn:dem":159,
    "gn:feature_class":"P",
    "gn:feature_code":"PPL",
    "gn:name":"Starogermanovskiy",
    "gn:population":0,
    "gn:timezone":"Europe/Moscow",
    "iso:country":"RU",
    "name:rus_x_preferred":[
        "\u0421\u0442\u0430\u0440\u043e\u0433\u0435\u0440\u043c\u0430\u043d\u043e\u0432\u0441\u043a\u0438\u0439"
    ],
    "name:und_x_variant":[
        "Germanovskiy",
        "Starogetmanovskiy",
        "Starogermanovskiy"
    ],
    "wof:name":"Starogermanovskiy",
    "wof:placetype":"locality"
},
  "geometry": {"coordinates":[40.77667,45.08583],"type":"Point"}
}