{
  "type": "Feature",
  "properties": {
    "gn:admin1_code":"77",
    "gn:asciiname":"Polyany",
    "gn:country_code":"RU",
    "gn:dem":163,
    "gn:feature_class":"P",
    "gn:feature_code":"PPL",
    "gn:name":"Polyany",
    "gn:population":0,
    "gn:timezone":"Europe/Moscow",
    "iso:country":"RU",
    "name:bel_x_preferred":[
        "\u041f\u0430\u043b\u044f\u043d\u044b"
    ],
    "name:eng_x_preferred":[
        "Polyany"
    ],
    "name:nor_x_preferred":[
        "Poljany"
    ],
    "name:rus_x_preferred":[
        "\u041f\u043e\u043b\u044f\u043d\u044b"
    ],
    "name:ukr_x_preferred":[
        "\u041f\u043e\u043b\u044f\u043d\u0438"
    ],
    "name:und_x_variant":[
        "\u041f\u043e\u043b\u044f\u043d\u044b",
        "Polyany"
    ],
    "wof:name":"Polyany",
    "wof:placetype":"locality"
},
  "geometry": {"coordinates":[37.4076,58.01206],"type":"Point"}
}