{
  "type": "Feature",
  "properties": {
    "gn:admin1_code":"76",
    "gn:asciiname":"Novyye Gorki",
    "gn:country_code":"RU",
    "gn:dem":227,
    "gn:feature_class":"P",
    "gn:feature_code":"PPL",
    "gn:name":"Novyye Gorki",
    "gn:population":0,
    "gn:timezone":"Europe/Moscow",
    "iso:country":"RU",
    "name:rus_x_preferred":[
        "\u041d\u043e\u0432\u044b\u0435 \u0413\u043e\u0440\u043a\u0438"
    ],
    "wof:name":"Novyye Gorki",
    "wof:placetype":"locality"
},
  "geometry": {"coordinates":[37.20583,53.40083000000001],"type":"Point"}
}