{
  "type": "Feature",
  "properties": {
    "gn:admin1_code":"73",
    "gn:asciiname":"Toyma",
    "gn:country_code":"RU",
    "gn:dem":97,
    "gn:feature_class":"P",
    "gn:feature_code":"PPL",
    "gn:name":"Toyma",
    "gn:population":0,
    "gn:timezone":"Europe/Moscow",
    "iso:country":"RU",
    "name:und_x_variant":[
        "Toima",
        "Toyma"
    ],
    "wof:name":"Toyma",
    "wof:placetype":"locality"
},
  "geometry": {"coordinates":[52.39318,56.0111],"type":"Point"}
}