{
  "type": "Feature",
  "properties": {
    "gn:admin1_code":"27.0",
    "gn:asciiname":"Erken-Shakhar",
    "gn:country_code":"RU",
    "gn:dem":428,
    "gn:feature_class":"P",
    "gn:feature_code":"PPL",
    "gn:name":"Erken-Shakhar",
    "gn:population":0,
    "gn:timezone":"Europe/Moscow",
    "iso:country":"RU",
    "name:che_x_preferred":[
        "\u042d\u0440\u043a\u0438\u043d-\u0428\u0430\u0445\u0430\u0440"
    ],
    "name:deu_x_preferred":[
        "Erken-Schachar"
    ],
    "name:eng_x_preferred":[
        "Erken-Shakhar"
    ],
    "name:hye_x_preferred":[
        "\u0537\u0580\u056f\u0565\u0576-\u0547\u0561\u056d\u0561\u0580"
    ],
    "name:kaz_x_preferred":[
        "\u0415\u0440\u043a\u0456\u043d \u0428\u0430\u04bb\u0430\u0440"
    ],
    "name:nor_x_preferred":[
        "Erken-Sjakhar"
    ],
    "name:rus_x_preferred":[
        "\u042d\u0440\u043a\u0435\u043d-\u0428\u0430\u0445\u0430\u0440"
    ],
    "name:ukr_x_preferred":[
        "\u0415\u0440\u043a\u0456\u043d-\u0428\u0430\u0445\u0430\u0440"
    ],
    "wof:name":"Erken-Shakhar",
    "wof:placetype":"locality"
},
  "geometry": {"coordinates":[41.9584,44.3778],"type":"Point"}
}