{
  "type": "Feature",
  "properties": {
    "gn:admin1_code":"27.0",
    "gn:asciiname":"Erken-Shakhar",
    "gn:country_code":"RU",
    "gn:dem":428,
    "gn:feature_class":"P",
    "gn:feature_code":"PPL",
    "gn:name":"Erken-Shakhar",
    "gn:population":0,
    "gn:timezone":"Europe/Moscow",
    "iso:country":"RU",
    "name:eng_x_preferred":[
        "Erken-Shakhar"
    ],
    "name:nor_x_preferred":[
        "Erken-Sjakhar"
    ],
    "name:rus_x_preferred":[
        "\u042d\u0440\u043a\u0435\u043d-\u0428\u0430\u0445\u0430\u0440"
    ],
    "name:und_x_variant":[
        "\u042d\u0440\u043a\u0435\u043d-\u0428\u0430\u0445\u0430\u0440",
        "Erken-Shakhar"
    ],
    "wof:name":"Erken-Shakhar",
    "wof:placetype":"locality"
},
  "geometry": {"coordinates":[41.9584,44.3778],"type":"Point"}
}