{
  "type": "Feature",
  "properties": {
    "gn:admin1_code":"84",
    "gn:asciiname":"Ryazankin",
    "gn:country_code":"RU",
    "gn:dem":38,
    "gn:feature_class":"P",
    "gn:feature_code":"PPL",
    "gn:name":"Ryazankin",
    "gn:population":0,
    "gn:timezone":"Europe/Moscow",
    "iso:country":"RU",
    "name:rus_x_preferred":[
        "\u0420\u044f\u0437\u0430\u043d\u043a\u0438\u043d"
    ],
    "wof:name":"Ryazankin",
    "wof:placetype":"locality"
},
  "geometry": {"coordinates":[42.39361,48.03139],"type":"Point"}
}