{
  "type": "Feature",
  "properties": {
    "gn:admin1_code":"77",
    "gn:asciiname":"Matveykovo",
    "gn:country_code":"RU",
    "gn:dem":175,
    "gn:feature_class":"P",
    "gn:feature_code":"PPL",
    "gn:name":"Matveykovo",
    "gn:population":0,
    "gn:timezone":"Europe/Moscow",
    "iso:country":"RU",
    "name:rus_x_preferred":[
        "\u041c\u0430\u0442\u0432\u0435\u0439\u043a\u043e\u0432\u043e"
    ],
    "name:und_x_variant":[
        "\u041c\u0430\u0442\u0432\u0435\u0439\u043a\u043e\u0432\u043e"
    ],
    "wof:name":"Matveykovo",
    "wof:placetype":"locality"
},
  "geometry": {"coordinates":[35.64958,57.2947],"type":"Point"}
}