{
  "type": "Feature",
  "properties": {
    "gn:admin1_code":"56",
    "gn:asciiname":"Peshkovo",
    "gn:country_code":"RU",
    "gn:dem":231,
    "gn:feature_class":"P",
    "gn:feature_code":"PPL",
    "gn:name":"Peshkovo",
    "gn:population":0,
    "gn:timezone":"Europe/Moscow",
    "iso:country":"RU",
    "name:eng_x_preferred":[
        "Peshkovo"
    ],
    "name:nor_x_preferred":[
        "Pesjkovo"
    ],
    "name:rus_x_preferred":[
        "\u041f\u0435\u0448\u043a\u043e\u0432\u043e"
    ],
    "name:und_x_variant":[
        "Gremyachinskiye Vyselki",
        "\u041f\u0435\u0448\u043a\u043e\u0432\u043e",
        "Peshkovo"
    ],
    "wof:name":"Peshkovo",
    "wof:placetype":"locality"
},
  "geometry": {"coordinates":[37.70694,52.59414],"type":"Point"}
}