{
  "type": "Feature",
  "properties": {
    "gn:admin1_code":"8.0",
    "gn:asciiname":"Balkan",
    "gn:country_code":"RU",
    "gn:dem":230,
    "gn:feature_class":"P",
    "gn:feature_code":"PPL",
    "gn:name":"Balkan",
    "gn:population":0,
    "gn:timezone":"Asia/Yekaterinburg",
    "iso:country":"RU",
    "name:nor_x_preferred":[
        "Balkan"
    ],
    "name:rus_x_preferred":[
        "\u0411\u0430\u043b\u043a\u0430\u043d"
    ],
    "wof:name":"Balkan",
    "wof:placetype":"locality"
},
  "geometry": {"coordinates":[55.2693,53.97438],"type":"Point"}
}