{
  "type": "Feature",
  "properties": {
    "gn:admin1_code":"62",
    "gn:asciiname":"Kvartal Sorok Vos'moy",
    "gn:country_code":"RU",
    "gn:dem":150,
    "gn:feature_class":"P",
    "gn:feature_code":"PPL",
    "gn:name":"Kvartal Sorok Vos\u2019moy",
    "gn:population":0,
    "gn:timezone":"Europe/Moscow",
    "iso:country":"RU",
    "name:rus_x_preferred":[
        "\u041a\u0432\u0430\u0440\u0442\u0430\u043b \u0421\u043e\u0440\u043e\u043a \u0412\u043e\u0441\u044c\u043c\u043e\u0439"
    ],
    "name:und_x_variant":[
        "Kvartal Sorok Vos\u2019moy"
    ],
    "wof:name":"Kvartal Sorok Vos'moy",
    "wof:placetype":"locality"
},
  "geometry": {"coordinates":[42.3379,54.9465],"type":"Point"}
}