{
  "type": "Feature",
  "properties": {
    "gn:admin1_code":"13",
    "gn:asciiname":"Feklino",
    "gn:country_code":"RU",
    "gn:dem":172,
    "gn:feature_class":"P",
    "gn:feature_code":"PPL",
    "gn:name":"F\u00ebklino",
    "gn:population":0,
    "gn:timezone":"Asia/Yekaterinburg",
    "iso:country":"RU",
    "name:eng_x_preferred":[
        "F\u00ebklino"
    ],
    "name:nor_x_preferred":[
        "Feklino"
    ],
    "name:rus_x_preferred":[
        "\u0424\u0435\u043a\u043b\u0438\u043d\u043e"
    ],
    "name:rus_x_variant":[
        "\u0424\u0451\u043a\u043b\u0438\u043d\u043e"
    ],
    "name:und_x_variant":[
        "F\u00ebklino",
        "\u0424\u0451\u043a\u043b\u0438\u043d\u043e"
    ],
    "wof:name":"Feklino",
    "wof:placetype":"locality"
},
  "geometry": {"coordinates":[62.5169,55.5303],"type":"Point"}
}