{
  "type": "Feature",
  "properties": {
    "gn:admin1_code":"91",
    "gn:asciiname":"Voznesenka",
    "gn:country_code":"RU",
    "gn:dem":274,
    "gn:feature_class":"P",
    "gn:feature_code":"PPL",
    "gn:name":"Voznesenka",
    "gn:population":0,
    "gn:timezone":"Asia/Krasnoyarsk",
    "iso:country":"RU",
    "name:eng_x_preferred":[
        "Voznesenka"
    ],
    "name:nor_x_preferred":[
        "Voznesenka"
    ],
    "name:rus_x_preferred":[
        "\u0412\u043e\u0437\u043d\u0435\u0441\u0435\u043d\u043a\u0430"
    ],
    "name:und_x_variant":[
        "Voznesenskaya"
    ],
    "wof:name":"Voznesenka",
    "wof:placetype":"locality"
},
  "geometry": {"coordinates":[95.05645,56.65675],"type":"Point"}
}