{
  "type": "Feature",
  "properties": {
    "gn:admin1_code":"69",
    "gn:asciiname":"Usty Romanovskiye",
    "gn:cc2":"RU",
    "gn:country_code":"RU",
    "gn:dem":199,
    "gn:feature_class":"P",
    "gn:feature_code":"PPL",
    "gn:name":"Usty Romanovskiye",
    "gn:population":0,
    "gn:timezone":"Europe/Moscow",
    "iso:country":"RU",
    "name:und_x_variant":[
        "Usty",
        "Usty Romanovskiye"
    ],
    "wof:name":"Usty Romanovskiye",
    "wof:placetype":"locality"
},
  "geometry": {"coordinates":[32.74111,55.6075],"type":"Point"}
}