{
  "type": "Feature",
  "properties": {
    "gn:admin1_code":"88",
    "gn:asciiname":"Bliny",
    "gn:country_code":"RU",
    "gn:dem":126,
    "gn:feature_class":"P",
    "gn:feature_code":"PPL",
    "gn:name":"Bliny",
    "gn:population":0,
    "gn:timezone":"Europe/Moscow",
    "iso:country":"RU",
    "name:rus_x_preferred":[
        "\u0411\u043b\u0438\u043d\u044b"
    ],
    "name:und_x_variant":[
        "\u0411\u043b\u0438\u043d\u044b"
    ],
    "wof:name":"Bliny",
    "wof:placetype":"locality"
},
  "geometry": {"coordinates":[38.7778,57.6826],"type":"Point"}
}