{
  "type": "Feature",
  "properties": {
    "gn:admin1_code":"90",
    "gn:asciiname":"Kulikovo",
    "gn:country_code":"RU",
    "gn:dem":127,
    "gn:feature_class":"P",
    "gn:feature_code":"PPL",
    "gn:name":"Kulikovo",
    "gn:population":0,
    "gn:timezone":"Asia/Yekaterinburg",
    "iso:country":"RU",
    "name:eng_x_preferred":[
        "Kulikovo"
    ],
    "name:nor_x_preferred":[
        "Kulikovo"
    ],
    "name:rus_x_preferred":[
        "\u041a\u0443\u043b\u0438\u043a\u043e\u0432\u043e"
    ],
    "wof:name":"Kulikovo",
    "wof:placetype":"locality"
},
  "geometry": {"coordinates":[56.9801,58.1585],"type":"Point"}
}