{
  "type": "Feature",
  "properties": {
    "gn:admin1_code":"23",
    "gn:asciiname":"Vorob'yevo",
    "gn:country_code":"RU",
    "gn:dem":5,
    "gn:feature_class":"P",
    "gn:feature_code":"PPL",
    "gn:name":"Vorob\u2019yevo",
    "gn:population":0,
    "gn:timezone":"Europe/Kaliningrad",
    "iso:country":"RU",
    "name:eng_x_preferred":[
        "Vorob'yevo"
    ],
    "name:nor_x_preferred":[
        "Vorobjevo"
    ],
    "name:rus_x_preferred":[
        "\u0412\u043e\u0440\u043e\u0431\u044c\u0435\u0432\u043e"
    ],
    "name:und_x_variant":[
        "Ober Heiligenwalde",
        "Vorob\u2019yevo"
    ],
    "wof:name":"Vorob'yevo",
    "wof:placetype":"locality"
},
  "geometry": {"coordinates":[20.82513,54.69854],"type":"Point"}
}