{
  "type": "Feature",
  "properties": {
    "gn:admin1_code":"84",
    "gn:asciiname":"Petrov",
    "gn:country_code":"RU",
    "gn:dem":34,
    "gn:feature_class":"P",
    "gn:feature_code":"PPL",
    "gn:name":"Petrov",
    "gn:population":0,
    "gn:timezone":"Europe/Volgograd",
    "iso:country":"RU",
    "name:rus_x_preferred":[
        "\u041f\u0435\u0442\u0440\u043e\u0432"
    ],
    "name:und_x_variant":[
        "\u041f\u0435\u0442\u0440\u043e\u0432"
    ],
    "wof:name":"Petrov",
    "wof:placetype":"locality"
},
  "geometry": {"coordinates":[45.41667,49.61667],"type":"Point"}
}