{
  "type": "Feature",
  "properties": {
    "gn:admin1_code":"71",
    "gn:asciiname":"Novoyamovo",
    "gn:country_code":"RU",
    "gn:dem":143,
    "gn:feature_class":"P",
    "gn:feature_code":"PPL",
    "gn:name":"Novoyamovo",
    "gn:population":0,
    "gn:timezone":"Asia/Yekaterinburg",
    "iso:country":"RU",
    "name:rus_x_preferred":[
        "\u041d\u043e\u0432\u043e\u044f\u043c\u043e\u0432\u043e"
    ],
    "name:und_x_variant":[
        "Yanovo",
        "Novoyamovo",
        "\u041d\u043e\u0432\u043e\u044f\u043c\u043e\u0432\u043e"
    ],
    "wof:name":"Novoyamovo",
    "wof:placetype":"locality"
},
  "geometry": {"coordinates":[61.73304,57.91371],"type":"Point"}
}