{
  "type": "Feature",
  "properties": {
    "gn:admin1_code":"10",
    "gn:asciiname":"Dyukarevo",
    "gn:country_code":"RU",
    "gn:dem":222,
    "gn:feature_class":"P",
    "gn:feature_code":"PPL",
    "gn:name":"Dyukarevo",
    "gn:population":0,
    "gn:timezone":"Europe/Moscow",
    "iso:country":"RU",
    "name:rus_x_preferred":[
        "\u0414\u044e\u043a\u0430\u0440\u0435\u0432\u043e"
    ],
    "wof:name":"Dyukarevo",
    "wof:placetype":"locality"
},
  "geometry": {"coordinates":[34.94195,52.96276999999999],"type":"Point"}
}