{
  "type": "Feature",
  "properties": {
    "gn:admin1_code":"67",
    "gn:asciiname":"Rtishchevo",
    "gn:country_code":"RU",
    "gn:dem":210,
    "gn:feature_class":"P",
    "gn:feature_code":"PPL",
    "gn:name":"Rtishchevo",
    "gn:population":44013,
    "gn:timezone":"Europe/Saratov",
    "iso:country":"RU",
    "name:ara_x_preferred":[
        "\u0631\u062a\u064a\u0634\u062a\u0634\u064a\u0641\u0648"
    ],
    "name:aze_x_preferred":[
        "Rti\u015fevo"
    ],
    "name:bel_x_preferred":[
        "\u0413\u043e\u0440\u0430\u0434 \u0420\u0446\u0456\u0448\u0447\u0430\u0432\u0430"
    ],
    "name:bul_x_preferred":[
        "\u0420\u0442\u0438\u0448\u0447\u0435\u0432\u043e"
    ],
    "name:cat_x_preferred":[
        "Rt\u00edsxevo"
    ],
    "name:ces_x_preferred":[
        "Rti\u0161\u010devo"
    ],
    "name:eng_x_preferred":[
        "Rtishchevo"
    ],
    "name:epo_x_preferred":[
        "Rti\u015d\u0109evo"
    ],
    "name:est_x_preferred":[
        "Rti\u0161t\u0161evo"
    ],
    "name:fas_x_preferred":[
        "\u0631\u062a\u06cc\u0634\u0686\u0641\u0648"
    ],
    "name:fin_x_preferred":[
        "Rti\u0161t\u0161evo"
    ],
    "name:fra_x_preferred":[
        "Rtichtchevo"
    ],
    "name:hrv_x_preferred":[
        "Rti\u0161\u010devo"
    ],
    "name:hsb_x_preferred":[
        "Rti\u0161\u0107ewo"
    ],
    "name:ita_x_preferred":[
        "Rti\u0161\u010devo"
    ],
    "name:lit_x_preferred":[
        "Rti\u0161\u010devas"
    ],
    "name:nno_x_preferred":[
        "Rtisjtsjevo"
    ],
    "name:nor_x_preferred":[
        "Rtisjtsjevo"
    ],
    "name:pol_x_preferred":[
        "Rtiszczewo"
    ],
    "name:por_x_preferred":[
        "Rtichtchevo"
    ],
    "name:ron_x_preferred":[
        "Rti\u0219cevo"
    ],
    "name:rus_x_preferred":[
        "\u0420\u0442\u0438\u0449\u0435\u0432\u043e"
    ],
    "name:spa_x_preferred":[
        "Rt\u00edshchevo"
    ],
    "name:srp_x_preferred":[
        "\u0420\u0442\u0438\u0448\u0447\u0435\u0432\u043e"
    ],
    "name:swe_x_preferred":[
        "Rtisjtjevo"
    ],
    "name:tgk_x_preferred":[
        "\u0420\u0442\u0438\u0448\u0435\u0432\u043e"
    ],
    "name:und_x_variant":[
        "Rtischtschewo",
        "Rtishchevo",
        "\u0420\u0442\u0438\u0449\u0435\u0432\u043e"
    ],
    "name:xal_x_preferred":[
        "\u0420\u0442\u0438\u0449\u0435\u0432\u043e \u0431\u0430\u043b\u04bb\u0441\u043d"
    ],
    "name:zho_x_preferred":[
        "\u52d2\u5b63\u8b1d\u6c83"
    ],
    "wof:name":"Rtishchevo",
    "wof:placetype":"locality",
    "wof:population":44013
},
  "geometry": {"coordinates":[43.78745,52.26041],"type":"Point"}
}