{
  "type": "Feature",
  "properties": {
    "gn:admin1_code":"47",
    "gn:asciiname":"Sidorkovo",
    "gn:country_code":"RU",
    "gn:dem":211,
    "gn:feature_class":"P",
    "gn:feature_code":"PPL",
    "gn:name":"Sidorkovo",
    "gn:population":0,
    "gn:timezone":"Europe/Moscow",
    "iso:country":"RU",
    "name:rus_x_preferred":[
        "\u0421\u0438\u0434\u043e\u0440\u043a\u043e\u0432\u043e"
    ],
    "name:und_x_variant":[
        "\u0421\u0438\u0434\u043e\u0440\u043a\u043e\u0432\u043e"
    ],
    "wof:name":"Sidorkovo",
    "wof:placetype":"locality"
},
  "geometry": {"coordinates":[36.6076,56.2808],"type":"Point"}
}