{
  "type": "Feature",
  "properties": {
    "gn:admin1_code":"05",
    "gn:asciiname":"Skobel'tsyno",
    "gn:country_code":"RU",
    "gn:dem":99,
    "gn:feature_class":"P",
    "gn:feature_code":"PPL",
    "gn:name":"Skobel\u2019tsyno",
    "gn:population":0,
    "gn:timezone":"Asia/Yakutsk",
    "iso:country":"RU",
    "name:eng_x_preferred":[
        "Skobel'tsyno"
    ],
    "name:nor_x_preferred":[
        "Skobeltsino"
    ],
    "name:rus_x_preferred":[
        "\u0421\u043a\u043e\u0431\u0435\u043b\u044c\u0446\u0438\u043d\u043e"
    ],
    "name:rus_x_variant":[
        "\u0421\u043a\u043e\u0431\u0435\u043b\u044c\u0446\u044b\u043d\u043e"
    ],
    "name:und_x_variant":[
        "Skobelitsyno",
        "Skobel\u2019tsino",
        "Skobel\u2019tsyno"
    ],
    "wof:name":"Skobel'tsyno",
    "wof:placetype":"locality"
},
  "geometry": {"coordinates":[129.54478,49.41056],"type":"Point"}
}