{
  "type": "Feature",
  "properties": {
    "gn:admin1_code":"24",
    "gn:asciiname":"Tsubu",
    "gn:country_code":"RU",
    "gn:dem":-16,
    "gn:feature_class":"P",
    "gn:feature_code":"PPL",
    "gn:name":"Tsubu",
    "gn:population":0,
    "gn:timezone":"Europe/Moscow",
    "iso:country":"RU",
    "wof:name":"Tsubu",
    "wof:placetype":"locality"
},
  "geometry": {"coordinates":[46.27639,45.465],"type":"Point"}
}