{
  "type": "Feature",
  "properties": {
    "gn:admin1_code":"41.0",
    "gn:asciiname":"Belyye Berega",
    "gn:country_code":"RU",
    "gn:dem":156,
    "gn:feature_class":"P",
    "gn:feature_code":"PPL",
    "gn:name":"Belyye Berega",
    "gn:population":0,
    "gn:timezone":"Europe/Moscow",
    "iso:country":"RU",
    "name:nor_x_preferred":[
        "Belye Berega"
    ],
    "name:rus_x_preferred":[
        "\u0411\u0435\u043b\u044b\u0435 \u0411\u0435\u0440\u0435\u0433\u0430"
    ],
    "wof:name":"Belyye Berega",
    "wof:placetype":"locality"
},
  "geometry": {"coordinates":[35.01722,51.975],"type":"Point"}
}