{
  "type": "Feature",
  "properties": {
    "gn:country":"RU",
    "gn:fcode":"PPL",
    "gn:population":0,
    "iso:country":"RU",
    "name:che_x_preferred":[
        "\u041d\u043e\u0432\u043e\u0436\u0438\u043b\u043e\u0432\u043e"
    ],
    "name:fin_x_preferred":[
        "Miettil\u00e4"
    ],
    "name:rus_x_preferred":[
        "\u041d\u043e\u0432\u043e\u0436\u0438\u043b\u043e\u0432\u043e"
    ],
    "qs:name":"Novozhilovo",
    "qs:name_adm0":"Russia",
    "qs:name_adm1":"Leningrad Oblast",
    "qs:photos_9r":0,
    "qs:photos_sr":0,
    "qs:placetype":"Town",
    "qs:pop_sr":"0",
    "wof:name":"Novozhilovo",
    "wof:placetype":"locality",
    "wof:population":0
},
  "geometry": {"coordinates":[30.15883,60.51111],"type":"Point"}
}