{
  "type": "Feature",
  "properties": {
    "gn:admin1_code":"16",
    "gn:asciiname":"Uvarovka",
    "gn:country_code":"RU",
    "gn:dem":84,
    "gn:feature_class":"P",
    "gn:feature_code":"PPL",
    "gn:name":"Uvarovka",
    "gn:population":0,
    "gn:timezone":"Europe/Moscow",
    "iso:country":"RU",
    "name:che_x_preferred":[
        "\u0423\u0432\u0430\u0440\u043e\u0432\u043a\u0430"
    ],
    "name:rus_x_preferred":[
        "\u0423\u0432\u0430\u0440\u043e\u0432\u043a\u0430"
    ],
    "wof:name":"Uvarovka",
    "wof:placetype":"locality"
},
  "geometry": {"coordinates":[46.68333,54.73333],"type":"Point"}
}