{
  "type": "Feature",
  "properties": {
    "gn:admin1_code":"33",
    "gn:asciiname":"Mezeni",
    "gn:country_code":"RU",
    "gn:dem":135,
    "gn:feature_class":"P",
    "gn:feature_code":"PPL",
    "gn:name":"Mezeni",
    "gn:population":0,
    "gn:timezone":"Europe/Kirov",
    "iso:country":"RU",
    "name:rus_x_preferred":[
        "\u041c\u0435\u0437\u0435\u043d\u0438"
    ],
    "wof:name":"Mezeni",
    "wof:placetype":"locality"
},
  "geometry": {"coordinates":[50.8141,59.1797],"type":"Point"}
}