{
  "type": "Feature",
  "properties": {
    "gn:admin1_code":"10",
    "gn:asciiname":"Golubeya",
    "gn:country_code":"RU",
    "gn:dem":188,
    "gn:feature_class":"P",
    "gn:feature_code":"PPL",
    "gn:name":"Golubeya",
    "gn:population":0,
    "gn:timezone":"Europe/Moscow",
    "iso:country":"RU",
    "name:rus_x_preferred":[
        "\u0413\u043e\u043b\u0443\u0431\u0435\u044f"
    ],
    "wof:name":"Golubeya",
    "wof:placetype":"locality"
},
  "geometry": {"coordinates":[33.64861,53.61639],"type":"Point"}
}