{
  "type": "Feature",
  "properties": {
    "gn:admin1_code":"37",
    "gn:asciiname":"Bystrovo",
    "gn:country_code":"RU",
    "gn:dem":115,
    "gn:feature_class":"P",
    "gn:feature_code":"PPL",
    "gn:name":"Bystrovo",
    "gn:population":0,
    "gn:timezone":"Europe/Moscow",
    "iso:country":"RU",
    "name:rus_x_preferred":[
        "\u0411\u044b\u0441\u0442\u0440\u043e\u0432\u043e"
    ],
    "name:und_x_variant":[
        "\u0411\u044b\u0441\u0442\u0440\u043e\u0432\u043e"
    ],
    "wof:name":"Bystrovo",
    "wof:placetype":"locality"
},
  "geometry": {"coordinates":[46.3042,58.3417],"type":"Point"}
}