{
  "type": "Feature",
  "properties": {
    "gn:admin1_code":"60",
    "gn:asciiname":"Nochlegovo",
    "gn:country_code":"RU",
    "gn:dem":165,
    "gn:feature_class":"P",
    "gn:feature_code":"PPL",
    "gn:name":"Nochlegovo",
    "gn:population":0,
    "gn:timezone":"Europe/Moscow",
    "iso:country":"RU",
    "name:eng_x_preferred":[
        "Nochlegovo"
    ],
    "name:nor_x_preferred":[
        "Notsjlegovo"
    ],
    "name:rus_x_preferred":[
        "\u041d\u043e\u0447\u043b\u0435\u0433\u043e\u0432\u043e"
    ],
    "name:und_x_variant":[
        "\u041d\u043e\u0447\u043b\u0435\u0433\u043e\u0432\u043e",
        "Nochlegovo"
    ],
    "wof:name":"Nochlegovo",
    "wof:placetype":"locality"
},
  "geometry": {"coordinates":[29.03242,56.50244],"type":"Point"}
}