{
  "type": "Feature",
  "properties": {
    "gn:admin1_code":"8",
    "gn:asciiname":"Novyye Kazanchi",
    "gn:country_code":"RU",
    "gn:dem":131,
    "gn:feature_class":"P",
    "gn:feature_code":"PPL",
    "gn:name":"Novyye Kazanchi",
    "gn:population":0,
    "gn:timezone":"Asia/Yekaterinburg",
    "iso:country":"RU",
    "name:eng_x_preferred":[
        "Novokazanchi"
    ],
    "name:nor_x_preferred":[
        "Nov.Kazantsji"
    ],
    "name:rus_x_preferred":[
        "\u041d\u043e\u0432.\u041a\u0430\u0437\u0430\u043d\u0447\u0438"
    ],
    "name:rus_x_variant":[
        "\u041d\u043e\u0432\u044b\u0435 \u041a\u0430\u0437\u0430\u043d\u0447\u0438"
    ],
    "name:und_x_variant":[
        "Kazanchina",
        "Novokazanchi",
        "Novyye Kazanchi"
    ],
    "wof:name":"Novyye Kazanchi",
    "wof:placetype":"locality"
},
  "geometry": {"coordinates":[56.28372,56.2841],"type":"Point"}
}