{
  "type": "Feature",
  "properties": {
    "gn:admin1_code":"8",
    "gn:asciiname":"Novyye Kazanchi",
    "gn:country_code":"RU",
    "gn:dem":131,
    "gn:feature_class":"P",
    "gn:feature_code":"PPL",
    "gn:name":"Novyye Kazanchi",
    "gn:population":0,
    "gn:timezone":"Asia/Yekaterinburg",
    "iso:country":"RU",
    "name:aze_x_preferred":[
        "Yeni Kazans\u0131"
    ],
    "name:bak_x_preferred":[
        "\u042f\u04a3\u044b \u04a0\u0430\u0499\u0430\u043d\u0441\u044b"
    ],
    "name:che_x_preferred":[
        "\u041d\u043e\u0432\u0438 \u041a\u0430\u0437\u0430\u043d\u0447\u0438"
    ],
    "name:eng_x_preferred":[
        "Novokazanchi"
    ],
    "name:hye_x_preferred":[
        "\u0546\u0578\u057e\u056b\u0565 \u053f\u0561\u0566\u0561\u0576\u0579\u056b"
    ],
    "name:kat_x_preferred":[
        "\u10dc\u10dd\u10d5\u10d8\u10d4-\u10d9\u10d0\u10d6\u10d0\u10dc\u10e9\u10d8"
    ],
    "name:kaz_x_preferred":[
        "\u0416\u0430\u04a3\u0430 \u041a\u0430\u0437\u0430\u043d\u0447\u0438"
    ],
    "name:kir_x_preferred":[
        "\u0416\u0430\u04a3\u044b \u041a\u0430\u0437\u0430\u043d\u0447\u0438"
    ],
    "name:nor_x_preferred":[
        "Nov.Kazantsji"
    ],
    "name:rus_x_preferred":[
        "\u041d\u043e\u0432.\u041a\u0430\u0437\u0430\u043d\u0447\u0438"
    ],
    "name:rus_x_variant":[
        "\u041d\u043e\u0432\u044b\u0435 \u041a\u0430\u0437\u0430\u043d\u0447\u0438"
    ],
    "name:tat_x_preferred":[
        "\u042f\u04a3\u0430 \u041a\u0430\u0437\u0430\u043d\u0447\u044b"
    ],
    "name:und_x_variant":[
        "Kazanchina",
        "Novokazanchi",
        "Novyye Kazanchi"
    ],
    "wof:name":"Novyye Kazanchi",
    "wof:placetype":"locality"
},
  "geometry": {"coordinates":[56.28372,56.2841],"type":"Point"}
}