{
  "type": "Feature",
  "properties": {
    "gn:admin1_code":"9",
    "gn:asciiname":"Otradovskiy",
    "gn:country_code":"RU",
    "gn:dem":175,
    "gn:feature_class":"P",
    "gn:feature_code":"PPL",
    "gn:name":"Otradovskiy",
    "gn:population":0,
    "gn:timezone":"Europe/Moscow",
    "iso:country":"RU",
    "name:rus_x_preferred":[
        "\u041e\u0442\u0440\u0430\u0434\u043e\u0432\u0441\u043a\u0438\u0439"
    ],
    "wof:name":"Otradovskiy",
    "wof:placetype":"locality"
},
  "geometry": {"coordinates":[35.6985,50.7411],"type":"Point"}
}