{
  "type": "Feature",
  "properties": {
    "gn:admin1_code":"29",
    "gn:asciiname":"Bol'shoy Berchikul'",
    "gn:country_code":"RU",
    "gn:dem":372,
    "gn:feature_class":"P",
    "gn:feature_code":"PPL",
    "gn:name":"Bol\u2019shoy Berchikul\u2019",
    "gn:population":0,
    "gn:timezone":"Asia/Novokuznetsk",
    "iso:country":"RU",
    "name:eng_x_preferred":[
        "Bol'shoy Berchikul'"
    ],
    "name:nor_x_preferred":[
        "Bertsjikul"
    ],
    "name:rus_x_preferred":[
        "\u0411\u0435\u0440\u0447\u0438\u043a\u0443\u043b\u044c"
    ],
    "name:rus_x_variant":[
        "\u0411\u043e\u043b\u044c\u0448\u043e\u0439 \u0411\u0435\u0440\u0447\u0438\u043a\u0443\u043b\u044c"
    ],
    "name:und_x_variant":[
        "Berchikul\u2019",
        "Bol\u2019shoy Berchikul\u2019"
    ],
    "wof:name":"Bol'shoy Berchikul'",
    "wof:placetype":"locality"
},
  "geometry": {"coordinates":[88.30110999999999,55.63833],"type":"Point"}
}