{
  "type": "Feature",
  "properties": {
    "gn:admin1_code":"85",
    "gn:asciiname":"Lep Ruchey",
    "gn:country_code":"RU",
    "gn:dem":93,
    "gn:feature_class":"P",
    "gn:feature_code":"PPL",
    "gn:name":"Lep Ruchey",
    "gn:population":0,
    "gn:timezone":"Europe/Moscow",
    "iso:country":"RU",
    "name:rus_x_preferred":[
        "\u041b\u0435\u043f \u0420\u0443\u0447\u0435\u0439"
    ],
    "name:und_x_variant":[
        "Lepp\u00e4oja",
        "Lep Ruchey"
    ],
    "wof:name":"Lep Ruchey",
    "wof:placetype":"locality"
},
  "geometry": {"coordinates":[36.09945,60.98044],"type":"Point"}
}