{
  "type": "Feature",
  "properties": {
    "gn:admin1_code":"37",
    "gn:asciiname":"Samylovo",
    "gn:country_code":"RU",
    "gn:dem":133,
    "gn:feature_class":"P",
    "gn:feature_code":"PPL",
    "gn:name":"Samylovo",
    "gn:population":0,
    "gn:timezone":"Europe/Moscow",
    "iso:country":"RU",
    "name:eng_x_preferred":[
        "Samylovo"
    ],
    "name:nor_x_preferred":[
        "Samylovo"
    ],
    "name:rus_x_preferred":[
        "\u0421\u0430\u043c\u044b\u043b\u043e\u0432\u043e"
    ],
    "name:und_x_variant":[
        "\u0421\u0430\u043c\u044b\u043b\u043e\u0432\u043e",
        "Samylovo"
    ],
    "wof:name":"Samylovo",
    "wof:placetype":"locality"
},
  "geometry": {"coordinates":[44.66548,58.24777],"type":"Point"}
}