{
  "type": "Feature",
  "properties": {
    "gn:admin1_code":"63",
    "gn:asciiname":"Perekratnyy",
    "gn:country_code":"RU",
    "gn:dem":471,
    "gn:feature_class":"P",
    "gn:feature_code":"PPL",
    "gn:name":"Perekratnyy",
    "gn:population":0,
    "gn:timezone":"Asia/Yakutsk",
    "iso:country":"RU",
    "name:eng_x_preferred":[
        "Perekratnyy"
    ],
    "name:nor_x_preferred":[
        "Perekatnyj"
    ],
    "name:rus_x_preferred":[
        "\u041f\u0435\u0440\u0435\u043a\u0430\u0442\u043d\u044b\u0439"
    ],
    "name:rus_x_variant":[
        "\u041f\u0435\u0440\u0435\u043a\u0440\u0430\u0442\u043d\u044b\u0439"
    ],
    "wof:name":"Perekratnyy",
    "wof:placetype":"locality"
},
  "geometry": {"coordinates":[124.35766,58.47616],"type":"Point"}
}