{
  "type": "Feature",
  "properties": {
    "gn:admin1_code":"75",
    "gn:asciiname":"Polynyanka",
    "gn:cc2":"RU",
    "gn:country_code":"RU",
    "gn:dem":109,
    "gn:feature_class":"P",
    "gn:feature_code":"PPL",
    "gn:name":"Polynyanka",
    "gn:population":0,
    "gn:timezone":"Asia/Tomsk",
    "iso:country":"RU",
    "name:eng_x_preferred":[
        "Polynyanka"
    ],
    "name:nor_x_preferred":[
        "Polynjanka"
    ],
    "name:rus_x_preferred":[
        "\u041f\u043e\u043b\u044b\u043d\u044f\u043d\u043a\u0430"
    ],
    "name:und_x_variant":[
        "Polonyanka"
    ],
    "wof:name":"Polynyanka",
    "wof:placetype":"locality"
},
  "geometry": {"coordinates":[82.51361,56.95333],"type":"Point"}
}