{
  "type": "Feature",
  "properties": {
    "gn:admin1_code":"77",
    "gn:asciiname":"Manuylovo",
    "gn:country_code":"RU",
    "gn:dem":205,
    "gn:feature_class":"P",
    "gn:feature_code":"PPL",
    "gn:name":"Manuylovo",
    "gn:population":0,
    "gn:timezone":"Europe/Moscow",
    "iso:country":"RU",
    "name:rus_x_preferred":[
        "\u041c\u0430\u043d\u0443\u0439\u043b\u043e\u0432\u043e"
    ],
    "name:und_x_variant":[
        "Manuilova",
        "Manuilovo",
        "Manuylovo"
    ],
    "wof:name":"Manuylovo",
    "wof:placetype":"locality"
},
  "geometry": {"coordinates":[34.53233,56.32691],"type":"Point"}
}