{
  "type": "Feature",
  "properties": {
    "gn:admin1_code":"77.0",
    "gn:asciiname":"Alabuzino",
    "gn:country_code":"RU",
    "gn:dem":140,
    "gn:feature_class":"P",
    "gn:feature_code":"PPL",
    "gn:name":"Alabuzino",
    "gn:population":0,
    "gn:timezone":"Europe/Moscow",
    "iso:country":"RU",
    "name:eng_x_preferred":[
        "Alabuzino"
    ],
    "name:nor_x_preferred":[
        "Alabuzino"
    ],
    "name:rus_x_preferred":[
        "\u0410\u043b\u0430\u0431\u0443\u0437\u0438\u043d\u043e"
    ],
    "name:und_x_variant":[
        "\u0410\u043b\u0430\u0431\u0443\u0437\u0438\u043d\u043e",
        "Alabuzino"
    ],
    "wof:name":"Alabuzino",
    "wof:placetype":"locality"
},
  "geometry": {"coordinates":[36.60644,57.83731],"type":"Point"}
}