{
  "type": "Feature",
  "properties": {
    "gn:admin1_code":"69",
    "gn:asciiname":"Khotenov",
    "gn:country_code":"RU",
    "gn:dem":206,
    "gn:feature_class":"P",
    "gn:feature_code":"PPL",
    "gn:name":"Khotenov",
    "gn:population":0,
    "gn:timezone":"Europe/Moscow",
    "iso:country":"RU",
    "name:rus_x_preferred":[
        "\u0425\u043e\u0442\u0435\u043d\u043e\u0432"
    ],
    "name:und_x_variant":[
        "\u0425\u043e\u0442\u0435\u043d\u043e\u0432",
        "Khotenov"
    ],
    "wof:name":"Khotenov",
    "wof:placetype":"locality"
},
  "geometry": {"coordinates":[32.9173,55.0411],"type":"Point"}
}