{
  "type": "Feature",
  "properties": {
    "gn:admin1_code":"76",
    "gn:asciiname":"Novougol'nyy",
    "gn:country_code":"RU",
    "gn:dem":225,
    "gn:feature_class":"P",
    "gn:feature_code":"PPL",
    "gn:name":"Novougol\u2019nyy",
    "gn:population":0,
    "gn:timezone":"Europe/Moscow",
    "iso:country":"RU",
    "name:rus_x_preferred":[
        "\u041d\u043e\u0432\u043e\u0443\u0433\u043e\u043b\u044c\u043d\u044b\u0439"
    ],
    "name:und_x_variant":[
        "Novougol\u2019nyy",
        "\u041d\u043e\u0432\u043e\u0443\u0433\u043e\u043b\u044c\u043d\u044b\u0439"
    ],
    "wof:name":"Novougol'nyy",
    "wof:placetype":"locality"
},
  "geometry": {"coordinates":[38.29469,53.986],"type":"Point"}
}