{
  "type": "Feature",
  "properties": {
    "gn:admin1_code":"88",
    "gn:asciiname":"Gorki-Kamenskiye",
    "gn:country_code":"RU",
    "gn:dem":123,
    "gn:feature_class":"P",
    "gn:feature_code":"PPL",
    "gn:name":"Gorki-Kamenskiye",
    "gn:population":0,
    "gn:timezone":"Europe/Moscow",
    "iso:country":"RU",
    "name:rus_x_preferred":[
        "\u0413\u043e\u0440\u043a\u0438-\u041a\u0430\u043c\u0435\u043d\u0441\u043a\u0438\u0435"
    ],
    "wof:name":"Gorki-Kamenskiye",
    "wof:placetype":"locality"
},
  "geometry": {"coordinates":[37.9893,57.4083],"type":"Point"}
}