{
  "type": "Feature",
  "properties": {
    "gn:admin1_code":"90",
    "gn:asciiname":"Yevropeyskaya",
    "gn:country_code":"RU",
    "gn:dem":377,
    "gn:feature_class":"P",
    "gn:feature_code":"PPL",
    "gn:name":"Yevropeyskaya",
    "gn:population":0,
    "gn:timezone":"Asia/Yekaterinburg",
    "iso:country":"RU",
    "name:che_x_preferred":[
        "\u0415\u0432\u0440\u043e\u043f\u0435\u0439\u0441\u043a\u0438"
    ],
    "name:rus_x_preferred":[
        "\u0415\u0432\u0440\u043e\u043f\u0435\u0439\u0441\u043a\u0430\u044f"
    ],
    "wof:name":"Yevropeyskaya",
    "wof:placetype":"locality"
},
  "geometry": {"coordinates":[59.27083,58.45806],"type":"Point"}
}