{
  "type": "Feature",
  "properties": {
    "gn:admin1_code":"29",
    "gn:asciiname":"Tri Tysyachi Vosem'sot Pyatyy Kilometr",
    "gn:country_code":"RU",
    "gn:dem":256,
    "gn:feature_class":"P",
    "gn:feature_code":"PPL",
    "gn:name":"Tri Tysyachi Vosem\u2019sot Pyatyy Kilometr",
    "gn:population":0,
    "gn:timezone":"Asia/Novokuznetsk",
    "iso:country":"RU",
    "name:rus_x_preferred":[
        "\u0422\u0440\u0438 \u0422\u044b\u0441\u044f\u0447\u0438 \u0412\u043e\u0441\u0435\u043c\u044c\u0441\u043e\u0442 \u041f\u044f\u0442\u044b\u0439 \u041a\u0438\u043b\u043e\u043c\u0435\u0442\u0440"
    ],
    "name:und_x_variant":[
        "Tri Tysyachi Vosem\u2019sot Pyatyy Kilometr",
        "\u0422\u0440\u0438 \u0422\u044b\u0441\u044f\u0447\u0438 \u0412\u043e\u0441\u0435\u043c\u044c\u0441\u043e\u0442 \u041f\u044f\u0442\u044b\u0439 \u041a\u0438\u043b\u043e\u043c\u0435\u0442\u0440"
    ],
    "wof:name":"Tri Tysyachi Vosem'sot Pyatyy Kilometr",
    "wof:placetype":"locality"
},
  "geometry": {"coordinates":[88.9616,56.066],"type":"Point"}
}