{
  "type": "Feature",
  "properties": {
    "gn:admin1_code":"10",
    "gn:asciiname":"Novyye Darkovichi",
    "gn:country_code":"RU",
    "gn:dem":174,
    "gn:feature_class":"P",
    "gn:feature_code":"PPL",
    "gn:name":"Novyye Darkovichi",
    "gn:population":0,
    "gn:timezone":"Europe/Moscow",
    "iso:country":"RU",
    "name:rus_x_preferred":[
        "\u041d\u043e\u0432\u044b\u0435 \u0414\u0430\u0440\u043a\u043e\u0432\u0438\u0447\u0438"
    ],
    "name:und_x_variant":[
        "\u041d\u043e\u0432\u044b\u0435 \u0414\u0430\u0440\u043a\u043e\u0432\u0438\u0447\u0438"
    ],
    "wof:name":"Novyye Darkovichi",
    "wof:placetype":"locality"
},
  "geometry": {"coordinates":[34.32372,53.38663],"type":"Point"}
}