{
  "type": "Feature",
  "properties": {
    "gn:admin1_code":"47.0",
    "gn:asciiname":"Bol'shiye Gorki",
    "gn:country_code":"RU",
    "gn:dem":193,
    "gn:feature_class":"P",
    "gn:feature_code":"PPL",
    "gn:name":"Bol\u2019shiye Gorki",
    "gn:population":0,
    "gn:timezone":"Europe/Moscow",
    "iso:country":"RU",
    "name:rus_x_preferred":[
        "\u0411\u043e\u043b\u044c\u0448\u0438\u0435 \u0413\u043e\u0440\u043a\u0438"
    ],
    "name:und_x_variant":[
        "Gorki",
        "Bol\u2019shiye Gorki",
        "\u0411\u043e\u043b\u044c\u0448\u0438\u0435 \u0413\u043e\u0440\u043a\u0438"
    ],
    "wof:name":"Bol'shiye Gorki",
    "wof:placetype":"locality"
},
  "geometry": {"coordinates":[36.50333,55.42361],"type":"Point"}
}