{
  "type": "Feature",
  "properties": {
    "gn:admin1_code":"53",
    "gn:asciiname":"Novoichinskoye",
    "gn:country_code":"RU",
    "gn:dem":112,
    "gn:feature_class":"P",
    "gn:feature_code":"PPL",
    "gn:name":"Novoichinskoye",
    "gn:population":0,
    "gn:timezone":"Asia/Novosibirsk",
    "iso:country":"RU",
    "name:eng_x_preferred":[
        "Novoichinskoye"
    ],
    "name:nor_x_preferred":[
        "Novoitsjinskoje"
    ],
    "name:rus_x_preferred":[
        "\u041d\u043e\u0432\u043e\u0438\u0447\u0438\u043d\u0441\u043a\u043e\u0435"
    ],
    "name:und_x_variant":[
        "Ichinskiy",
        "\u041d\u043e\u0432\u043e\u0438\u0447\u0438\u043d\u0441\u043a\u043e\u0435",
        "Novoichinskoye"
    ],
    "wof:name":"Novoichinskoye",
    "wof:placetype":"locality"
},
  "geometry": {"coordinates":[77.62068000000002,55.66192],"type":"Point"}
}