{
  "type": "Feature",
  "properties": {
    "gn:admin1_code":"56",
    "gn:asciiname":"Rassyl'naya",
    "gn:country_code":"RU",
    "gn:dem":166,
    "gn:feature_class":"P",
    "gn:feature_code":"PPL",
    "gn:name":"Rassyl\u2019naya",
    "gn:population":0,
    "gn:timezone":"Europe/Moscow",
    "iso:country":"RU",
    "name:rus_x_preferred":[
        "\u0420\u0430\u0441\u0441\u044b\u043b\u044c\u043d\u0430\u044f"
    ],
    "name:und_x_variant":[
        "Rassyl\u2019naya",
        "\u0420\u0430\u0441\u0441\u044b\u043b\u044c\u043d\u0430\u044f"
    ],
    "wof:name":"Rassyl'naya",
    "wof:placetype":"locality"
},
  "geometry": {"coordinates":[35.82158,52.71703],"type":"Point"}
}