{
  "type": "Feature",
  "properties": {
    "gn:admin1_code":"73.0",
    "gn:asciiname":"Chirsha",
    "gn:country_code":"RU",
    "gn:dem":107,
    "gn:feature_class":"P",
    "gn:feature_code":"PPL",
    "gn:name":"Chirsha",
    "gn:population":0,
    "gn:timezone":"Europe/Moscow",
    "iso:country":"RU",
    "name:rus_x_preferred":[
        "\u0427\u0438\u0440\u0448\u0430"
    ],
    "name:und_x_variant":[
        "Chirshi",
        "Chirsha"
    ],
    "wof:name":"Chirsha",
    "wof:placetype":"locality"
},
  "geometry": {"coordinates":[49.22306,56.08722],"type":"Point"}
}