{
  "type": "Feature",
  "properties": {
    "gn:admin1_code":"76",
    "gn:asciiname":"Lubyanka",
    "gn:country_code":"RU",
    "gn:dem":140,
    "gn:feature_class":"P",
    "gn:feature_code":"PPL",
    "gn:name":"Lubyanka",
    "gn:population":0,
    "gn:timezone":"Europe/Moscow",
    "iso:country":"RU",
    "name:rus_x_preferred":[
        "\u041b\u0443\u0431\u044f\u043d\u043a\u0430"
    ],
    "name:und_x_variant":[
        "\u041b\u0443\u0431\u044f\u043d\u043a\u0430"
    ],
    "wof:name":"Lubyanka",
    "wof:placetype":"locality"
},
  "geometry": {"coordinates":[38.4846,53.2016],"type":"Point"}
}