{
  "type": "Feature",
  "properties": {
    "gn:admin1_code":"42",
    "gn:asciiname":"Graviynoye",
    "gn:cc2":"RU",
    "gn:country_code":"RU",
    "gn:dem":17,
    "gn:feature_class":"P",
    "gn:feature_code":"PPL",
    "gn:name":"Graviynoye",
    "gn:population":0,
    "gn:timezone":"Europe/Moscow",
    "iso:country":"RU",
    "name:fin_x_preferred":[
        "Saaroinen"
    ],
    "name:rus_x_preferred":[
        "\u0413\u0440\u0430\u0432\u0438\u0439\u043d\u043e\u0435"
    ],
    "name:und_x_variant":[
        "Simola",
        "Graviynoye",
        "\u0413\u0440\u0430\u0432\u0438\u0439\u043d\u043e\u0435"
    ],
    "wof:name":"Graviynoye",
    "wof:placetype":"locality"
},
  "geometry": {"coordinates":[30.65,60.55],"type":"Point"}
}