{
  "type": "Feature",
  "properties": {
    "gn:admin1_code":"33.0",
    "gn:asciiname":"Sherdynyata",
    "gn:country_code":"RU",
    "gn:dem":236,
    "gn:feature_class":"P",
    "gn:feature_code":"PPL",
    "gn:name":"Sherdynyata",
    "gn:population":0,
    "gn:timezone":"Europe/Kirov",
    "iso:country":"RU",
    "name:rus_x_preferred":[
        "\u0428\u0435\u0440\u0434\u044b\u043d\u044f\u0442\u0430"
    ],
    "name:und_x_variant":[
        "Sherdinyata"
    ],
    "wof:name":"Sherdynyata",
    "wof:placetype":"locality"
},
  "geometry": {"coordinates":[53.5189,58.5959],"type":"Point"}
}