{
  "type": "Feature",
  "properties": {
    "gn:admin1_code":"61.0",
    "gn:asciiname":"Pogorelovo",
    "gn:country_code":"RU",
    "gn:dem":37,
    "gn:feature_class":"P",
    "gn:feature_code":"PPL",
    "gn:name":"Pogorelovo",
    "gn:population":0,
    "gn:timezone":"Europe/Moscow",
    "iso:country":"RU",
    "name:rus_x_preferred":[
        "\u041f\u043e\u0433\u043e\u0440\u0435\u043b\u043e\u0432\u043e"
    ],
    "wof:name":"Pogorelovo",
    "wof:placetype":"locality"
},
  "geometry": {"coordinates":[40.28725,48.43093],"type":"Point"}
}