{
  "type": "Feature",
  "properties": {
    "gn:admin1_code":"47",
    "gn:asciiname":"Avdot'ino",
    "gn:country_code":"RU",
    "gn:dem":131,
    "gn:feature_class":"P",
    "gn:feature_code":"PPL",
    "gn:name":"\u0410\u0432\u0434\u043e\u0442\u044c\u0438\u043d\u043e",
    "gn:population":0,
    "gn:timezone":"Europe/Moscow",
    "iso:country":"RU",
    "name:rus_x_preferred":[
        "\u0410\u0432\u0434\u043e\u0442\u044c\u0438\u043d\u043e"
    ],
    "name:und_x_variant":[
        "Avdot\u2019ino",
        "\u0410\u0432\u0434\u043e\u0442\u044c\u0438\u043d\u043e"
    ],
    "wof:name":"Avdot'ino",
    "wof:placetype":"locality"
},
  "geometry": {"coordinates":[37.72173,55.42294],"type":"Point"}
}