{
  "type": "Feature",
  "properties": {
    "gn:admin1_code":"77",
    "gn:asciiname":"Lunyakovo",
    "gn:country_code":"RU",
    "gn:dem":174,
    "gn:feature_class":"P",
    "gn:feature_code":"PPL",
    "gn:name":"Lunyakovo",
    "gn:population":0,
    "gn:timezone":"Europe/Moscow",
    "iso:country":"RU",
    "name:rus_x_preferred":[
        "\u041b\u0443\u043d\u044f\u043a\u043e\u0432\u043e"
    ],
    "wof:name":"Lunyakovo",
    "wof:placetype":"locality"
},
  "geometry": {"coordinates":[34.87003,56.79325],"type":"Point"}
}