{
  "type": "Feature",
  "properties": {
    "gn:admin1_code":"42.0",
    "gn:asciiname":"Buslovo",
    "gn:country_code":"RU",
    "gn:dem":32,
    "gn:feature_class":"P",
    "gn:feature_code":"PPL",
    "gn:name":"Buslovo",
    "gn:population":0,
    "gn:timezone":"Europe/Moscow",
    "iso:country":"RU",
    "name:fin_x_preferred":[
        "Houniala"
    ],
    "wof:name":"Buslovo",
    "wof:placetype":"locality"
},
  "geometry": {"coordinates":[28.40464,60.8273],"type":"Point"}
}