{
  "type": "Feature",
  "properties": {
    "gn:admin1_code":"88",
    "gn:asciiname":"Rykovo",
    "gn:country_code":"RU",
    "gn:dem":186,
    "gn:feature_class":"P",
    "gn:feature_code":"PPL",
    "gn:name":"Rykovo",
    "gn:population":0,
    "gn:timezone":"Europe/Moscow",
    "iso:country":"RU",
    "name:eng_x_preferred":[
        "Rykovo"
    ],
    "name:nor_x_preferred":[
        "Rykovo"
    ],
    "name:rus_x_preferred":[
        "\u0420\u044b\u043a\u043e\u0432\u043e"
    ],
    "wof:name":"Rykovo",
    "wof:placetype":"locality"
},
  "geometry": {"coordinates":[38.90144,56.96252],"type":"Point"}
}