{
  "type": "Feature",
  "properties": {
    "gn:admin1_code":"57.0",
    "gn:asciiname":"Dobryane",
    "gn:country_code":"RU",
    "gn:dem":190,
    "gn:feature_class":"P",
    "gn:feature_code":"PPL",
    "gn:name":"Dobryane",
    "gn:population":0,
    "gn:timezone":"Europe/Moscow",
    "iso:country":"RU",
    "name:rus_x_preferred":[
        "\u0414\u043e\u0431\u0440\u044f\u043d\u0435"
    ],
    "name:und_x_variant":[
        "\u0414\u043e\u0431\u0440\u044f\u043d\u0435"
    ],
    "wof:name":"Dobryane",
    "wof:placetype":"locality"
},
  "geometry": {"coordinates":[43.38333,52.41667],"type":"Point"}
}