{
  "type": "Feature",
  "properties": {
    "gn:admin1_code":"86",
    "gn:asciiname":"Zaton",
    "gn:country_code":"RU",
    "gn:dem":211,
    "gn:feature_class":"P",
    "gn:feature_code":"PPL",
    "gn:name":"Zaton",
    "gn:population":0,
    "gn:timezone":"Europe/Moscow",
    "iso:country":"RU",
    "name:rus_x_preferred":[
        "\u0417\u0430\u0442\u043e\u043d"
    ],
    "name:und_x_variant":[
        "Zatonskoye"
    ],
    "wof:name":"Zaton",
    "wof:placetype":"locality"
},
  "geometry": {"coordinates":[40.7361,50.6507],"type":"Point"}
}