{
  "type": "Feature",
  "properties": {
    "gn:admin1_code":"52.0",
    "gn:asciiname":"Bol'shoye Obrech'ye",
    "gn:country_code":"RU",
    "gn:dem":180,
    "gn:feature_class":"P",
    "gn:feature_code":"PPL",
    "gn:name":"Bol\u2019shoye Obrech\u2019ye",
    "gn:population":0,
    "gn:timezone":"Europe/Moscow",
    "iso:country":"RU",
    "name:nor_x_preferred":[
        "Bolsjoje Obretsje"
    ],
    "name:rus_x_preferred":[
        "\u0411\u043e\u043b\u044c\u0448\u043e\u0435 \u041e\u0431\u0440\u0435\u0447\u044c\u0435"
    ],
    "name:und_x_variant":[
        "Bol\u2019shoye Obrech\u2019ye"
    ],
    "wof:name":"Bol'shoye Obrech'ye",
    "wof:placetype":"locality"
},
  "geometry": {"coordinates":[33.96288,58.62765],"type":"Point"}
}