{
  "type": "Feature",
  "properties": {
    "gn:admin1_code":"17.0",
    "gn:asciiname":"Balkhar",
    "gn:country_code":"RU",
    "gn:dem":1672,
    "gn:feature_class":"P",
    "gn:feature_code":"PPL",
    "gn:name":"Balkhar",
    "gn:population":0,
    "gn:timezone":"Europe/Moscow",
    "iso:country":"RU",
    "name:eng_x_preferred":[
        "Balkhar"
    ],
    "name:nor_x_preferred":[
        "Balkhar"
    ],
    "name:rus_x_preferred":[
        "\u0411\u0430\u043b\u0445\u0430\u0440"
    ],
    "wof:name":"Balkhar",
    "wof:placetype":"locality"
},
  "geometry": {"coordinates":[47.23041,42.28],"type":"Point"}
}