{
  "type": "Feature",
  "properties": {
    "gn:admin1_code":"54",
    "gn:asciiname":"Basargul'",
    "gn:country_code":"RU",
    "gn:dem":58,
    "gn:feature_class":"P",
    "gn:feature_code":"PPL",
    "gn:name":"Basargul\u2019",
    "gn:population":0,
    "gn:timezone":"Asia/Omsk",
    "iso:country":"RU",
    "name:rus_x_preferred":[
        "\u0411\u0430\u0441\u0430\u0440\u0433\u0443\u043b\u044c"
    ],
    "name:und_x_variant":[
        "Basargul\u2019"
    ],
    "wof:name":"Basargul'",
    "wof:placetype":"locality"
},
  "geometry": {"coordinates":[70.7059,57.2715],"type":"Point"}
}