{
  "type": "Feature",
  "properties": {
    "gn:admin1_code":"91",
    "gn:asciiname":"Danilki",
    "gn:country_code":"RU",
    "gn:dem":196,
    "gn:feature_class":"P",
    "gn:feature_code":"PPL",
    "gn:name":"Danilki",
    "gn:population":0,
    "gn:timezone":"Asia/Krasnoyarsk",
    "iso:country":"RU",
    "name:eng_x_preferred":[
        "Danilki"
    ],
    "name:nor_x_preferred":[
        "Danilki"
    ],
    "name:rus_x_preferred":[
        "\u0414\u0430\u043d\u0438\u043b\u043a\u0438"
    ],
    "wof:name":"Danilki",
    "wof:placetype":"locality"
},
  "geometry": {"coordinates":[94.53135,57.30198000000001],"type":"Point"}
}