{
  "type": "Feature",
  "properties": {
    "gn:admin1_code":"63",
    "gn:asciiname":"Sordongnook",
    "gn:cc2":"RU",
    "gn:country_code":"RU",
    "gn:dem":27,
    "gn:feature_class":"P",
    "gn:feature_code":"PPL",
    "gn:name":"Sordongnook",
    "gn:population":0,
    "gn:timezone":"Asia/Vladivostok",
    "iso:country":"RU",
    "name:rus_x_preferred":[
        "\u0421\u043e\u0440\u0434\u043e\u043d\u0433\u043d\u043e\u043e\u043a"
    ],
    "name:und_x_variant":[
        "Sordongookh",
        "Sordongnook",
        "\u0421\u043e\u0440\u0434\u043e\u043d\u0433\u043d\u043e\u043e\u043a"
    ],
    "wof:name":"Sordongnook",
    "wof:placetype":"locality"
},
  "geometry": {"coordinates":[138.78333000000001,71.11667],"type":"Point"}
}