{
  "type": "Feature",
  "properties": {
    "gn:admin1_code":"69",
    "gn:asciiname":"Kolodnya",
    "gn:country_code":"RU",
    "gn:dem":215,
    "gn:feature_class":"P",
    "gn:feature_code":"PPL",
    "gn:name":"Kolodnya",
    "gn:population":0,
    "gn:timezone":"Europe/Moscow",
    "iso:country":"RU",
    "name:rus_x_preferred":[
        "\u041a\u043e\u043b\u043e\u0434\u043d\u044f"
    ],
    "name:und_x_variant":[
        "\u041a\u043e\u043b\u043e\u0434\u043d\u044f"
    ],
    "wof:name":"Kolodnya",
    "wof:placetype":"locality"
},
  "geometry": {"coordinates":[34.07194,55.80278000000001],"type":"Point"}
}