{
  "type": "Feature",
  "properties": {
    "gn:admin1_code":"45",
    "gn:asciiname":"Chernyy Klyuch",
    "gn:country_code":"RU",
    "gn:dem":110,
    "gn:feature_class":"P",
    "gn:feature_code":"PPL",
    "gn:name":"Ch\u00ebrnyy Klyuch",
    "gn:population":0,
    "gn:timezone":"Europe/Moscow",
    "iso:country":"RU",
    "name:rus_x_preferred":[
        "\u0427\u0451\u0440\u043d\u044b\u0439 \u041a\u043b\u044e\u0447"
    ],
    "name:und_x_variant":[
        "Ch\u00ebrnyy Klyuch"
    ],
    "wof:name":"Chernyy Klyuch",
    "wof:placetype":"locality"
},
  "geometry": {"coordinates":[47.98109,56.95523000000001],"type":"Point"}
}