{
  "type": "Feature",
  "properties": {
    "gn:admin1_code":"93",
    "gn:asciiname":"Chalbuchi",
    "gn:country_code":"RU",
    "gn:dem":417,
    "gn:feature_class":"P",
    "gn:feature_code":"PPL",
    "gn:name":"Chalbuchi",
    "gn:population":0,
    "gn:timezone":"Asia/Chita",
    "iso:country":"RU",
    "name:eng_x_preferred":[
        "Chalbuchi"
    ],
    "name:nor_x_preferred":[
        "Tsjalbutsji"
    ],
    "name:rus_x_preferred":[
        "\u0427\u0430\u043b\u0431\u0443\u0447\u0438"
    ],
    "name:und_x_variant":[
        "Chalbucha"
    ],
    "wof:name":"Chalbuchi",
    "wof:placetype":"locality"
},
  "geometry": {"coordinates":[118.62575,52.45287],"type":"Point"}
}