{
  "type": "Feature",
  "properties": {
    "gn:admin1_code":"10",
    "gn:asciiname":"Livornoye",
    "gn:country_code":"RU",
    "gn:dem":134,
    "gn:feature_class":"P",
    "gn:feature_code":"PPL",
    "gn:name":"Livornoye",
    "gn:population":0,
    "gn:timezone":"Europe/Moscow",
    "iso:country":"RU",
    "name:rus_x_preferred":[
        "\u041b\u0438\u0432\u043e\u0440\u043doe"
    ],
    "name:und_x_variant":[
        "\u041b\u0438\u0432\u043e\u0440\u043doe",
        "Livornya"
    ],
    "wof:name":"Livornoye",
    "wof:placetype":"locality"
},
  "geometry": {"coordinates":[32.12596,52.15174],"type":"Point"}
}