{
  "type": "Feature",
  "properties": {
    "gn:admin1_code":"69",
    "gn:asciiname":"Prigor'ye Nomer Tretiy",
    "gn:country_code":"RU",
    "gn:dem":188,
    "gn:feature_class":"P",
    "gn:feature_code":"PPL",
    "gn:name":"Prigor\u2019ye Nomer Tretiy",
    "gn:population":0,
    "gn:timezone":"Europe/Moscow",
    "iso:country":"RU",
    "name:rus_x_preferred":[
        "\u041f\u0440\u0438\u0433\u043e\u0440\u044c\u0435 \u041d\u043e\u043c\u0435\u0440 \u0422\u0440\u0435\u0442\u0438\u0439"
    ],
    "name:und_x_variant":[
        "Prigor\u2019ye Nomer Tretiy",
        "\u041f\u0440\u0438\u0433\u043e\u0440\u044c\u0435 \u041d\u043e\u043c\u0435\u0440 \u0422\u0440\u0435\u0442\u0438\u0439"
    ],
    "wof:name":"Prigor'ye Nomer Tretiy",
    "wof:placetype":"locality"
},
  "geometry": {"coordinates":[33.16667,53.81667],"type":"Point"}
}