{
  "type": "Feature",
  "properties": {
    "gn:admin1_code":"60",
    "gn:asciiname":"Gorelaya Roshcha",
    "gn:country_code":"RU",
    "gn:dem":71,
    "gn:feature_class":"P",
    "gn:feature_code":"PPL",
    "gn:name":"Gorelaya Roshcha",
    "gn:population":0,
    "gn:timezone":"Europe/Moscow",
    "iso:country":"RU",
    "name:rus_x_preferred":[
        "\u0413\u043e\u0440\u0435\u043b\u0430\u044f \u0420\u043e\u0449\u0430"
    ],
    "wof:name":"Gorelaya Roshcha",
    "wof:placetype":"locality"
},
  "geometry": {"coordinates":[28.45226,57.40884000000001],"type":"Point"}
}