{
  "type": "Feature",
  "properties": {
    "gn:admin1_code":"4",
    "gn:asciiname":"Kurskiy Vtoroy",
    "gn:country_code":"RU",
    "gn:dem":138,
    "gn:feature_class":"P",
    "gn:feature_code":"PPL",
    "gn:name":"Kurskiy Vtoroy",
    "gn:population":0,
    "gn:timezone":"Asia/Barnaul",
    "iso:country":"RU",
    "name:rus_x_preferred":[
        "\u041a\u0443\u0440\u0441\u043a\u0438\u0439 \u0412\u0442\u043e\u0440\u043e\u0439"
    ],
    "wof:name":"Kurskiy Vtoroy",
    "wof:placetype":"locality"
},
  "geometry": {"coordinates":[80.96666999999999,53.41667],"type":"Point"}
}