{
  "type": "Feature",
  "properties": {
    "gn:admin1_code":"77",
    "gn:asciiname":"Klyuchevaya",
    "gn:country_code":"RU",
    "gn:dem":282,
    "gn:feature_class":"P",
    "gn:feature_code":"PPL",
    "gn:name":"Klyuchevaya",
    "gn:population":0,
    "gn:timezone":"Europe/Moscow",
    "iso:country":"RU",
    "name:rus_x_preferred":[
        "\u041a\u043b\u044e\u0447\u0435\u0432\u0430\u044f"
    ],
    "name:und_x_variant":[
        "\u041a\u043b\u044e\u0447\u0435\u0432\u0430\u044f"
    ],
    "wof:name":"Klyuchevaya",
    "wof:placetype":"locality"
},
  "geometry": {"coordinates":[33.14244,56.46835],"type":"Point"}
}