{
  "type": "Feature",
  "properties": {
    "gn:admin1_code":"33",
    "gn:asciiname":"Shapta",
    "gn:country_code":"RU",
    "gn:dem":126,
    "gn:feature_class":"P",
    "gn:feature_code":"PPL",
    "gn:name":"Shapta",
    "gn:population":0,
    "gn:timezone":"Europe/Kirov",
    "iso:country":"RU",
    "name:eng_x_preferred":[
        "Shapta"
    ],
    "name:nor_x_preferred":[
        "Sjapta"
    ],
    "name:rus_x_preferred":[
        "\u0428\u0430\u043f\u0442\u0430"
    ],
    "wof:name":"Shapta",
    "wof:placetype":"locality"
},
  "geometry": {"coordinates":[47.05686,57.2187],"type":"Point"}
}