{
  "type": "Feature",
  "properties": {
    "gn:admin1_code":"40",
    "gn:asciiname":"Yachmenevo",
    "gn:country_code":"RU",
    "gn:dem":90,
    "gn:feature_class":"P",
    "gn:feature_code":"PPL",
    "gn:name":"Yachmenevo",
    "gn:population":0,
    "gn:timezone":"Asia/Yekaterinburg",
    "iso:country":"RU",
    "name:rus_x_preferred":[
        "\u042f\u0447\u043c\u0435\u043d\u0435\u0432\u043e"
    ],
    "name:und_x_variant":[
        "Yachenenevskoye",
        "Yachmenevskoye",
        "Yachmenevo"
    ],
    "wof:name":"Yachmenevo",
    "wof:placetype":"locality"
},
  "geometry": {"coordinates":[63.267,56.1354],"type":"Point"}
}