{
  "type": "Feature",
  "properties": {
    "gn:admin1_code":"63",
    "gn:asciiname":"Khakhsyr",
    "gn:country_code":"RU",
    "gn:dem":218,
    "gn:feature_class":"P",
    "gn:feature_code":"PPL",
    "gn:name":"Khakhsyr",
    "gn:population":0,
    "gn:timezone":"Asia/Yakutsk",
    "iso:country":"RU",
    "name:eng_x_preferred":[
        "Khakhsyr"
    ],
    "name:nor_x_preferred":[
        "Khakhsyk"
    ],
    "name:rus_x_preferred":[
        "\u0425\u0430\u0445\u0441\u044b\u043a"
    ],
    "name:rus_x_variant":[
        "\u0425\u0430\u0445\u0441\u044b\u0440"
    ],
    "wof:name":"Khakhsyr",
    "wof:placetype":"locality"
},
  "geometry": {"coordinates":[129.59999999999999,61.76667],"type":"Point"}
}