{
  "type": "Feature",
  "properties": {
    "gn:admin1_code":"55",
    "gn:asciiname":"Krasnaya Tabunovka",
    "gn:country_code":"RU",
    "gn:dem":99,
    "gn:feature_class":"P",
    "gn:feature_code":"PPL",
    "gn:name":"Krasnaya Tabunovka",
    "gn:population":0,
    "gn:timezone":"Asia/Yekaterinburg",
    "iso:country":"RU",
    "name:rus_x_preferred":[
        "\u041a\u0440\u0430\u0441\u043d\u0430\u044f \u0422\u0430\u0431\u0443\u043d\u043e\u0432\u043a\u0430"
    ],
    "name:und_x_variant":[
        "\u041a\u0440\u0430\u0441\u043d\u0430\u044f \u0422\u0430\u0431\u0443\u043d\u043e\u0432\u043a\u0430"
    ],
    "wof:name":"Krasnaya Tabunovka",
    "wof:placetype":"locality"
},
  "geometry": {"coordinates":[53.15,52.61666999999999],"type":"Point"}
}