{
  "type": "Feature",
  "properties": {
    "gn:admin1_code":"20",
    "gn:asciiname":"Chayandra",
    "gn:country_code":"RU",
    "gn:dem":1393,
    "gn:feature_class":"P",
    "gn:feature_code":"PPL",
    "gn:name":"Chayandra",
    "gn:population":0,
    "gn:timezone":"Asia/Irkutsk",
    "iso:country":"RU",
    "name:eng_x_preferred":[
        "Chayandra"
    ],
    "name:nor_x_preferred":[
        "Tsjajandra"
    ],
    "name:rus_x_preferred":[
        "\u0427\u0430\u044f\u043d\u0434\u0440\u0430"
    ],
    "name:und_x_variant":[
        "\u0427\u0430\u044f\u043d\u0434\u0440\u0430",
        "Chayandra"
    ],
    "wof:name":"Chayandra",
    "wof:placetype":"locality"
},
  "geometry": {"coordinates":[115.23333,57.16667],"type":"Point"}
}