{
  "type": "Feature",
  "properties": {
    "gn:admin1_code":"85",
    "gn:asciiname":"Sredniy Mityug",
    "gn:country_code":"RU",
    "gn:dem":170,
    "gn:feature_class":"P",
    "gn:feature_code":"PPL",
    "gn:name":"Sredniy Mityug",
    "gn:population":0,
    "gn:timezone":"Europe/Moscow",
    "iso:country":"RU",
    "name:rus_x_preferred":[
        "\u0421\u0440\u0435\u0434\u043d\u0438\u0439 \u041c\u0438\u0442\u044e\u0433"
    ],
    "name:und_x_variant":[
        "\u0421\u0440\u0435\u0434\u043d\u0438\u0439 \u041c\u0438\u0442\u044e\u0433"
    ],
    "wof:name":"Sredniy Mityug",
    "wof:placetype":"locality"
},
  "geometry": {"coordinates":[44.31667,59.33333],"type":"Point"}
}