{
  "type": "Feature",
  "properties": {
    "gn:admin1_code":"10.0",
    "gn:asciiname":"Budvenets",
    "gn:country_code":"RU",
    "gn:dem":181,
    "gn:feature_class":"P",
    "gn:feature_code":"PPL",
    "gn:name":"Budvenets",
    "gn:population":0,
    "gn:timezone":"Europe/Moscow",
    "iso:country":"RU",
    "name:rus_x_preferred":[
        "\u0411\u0443\u0434\u0432\u0435\u043d\u0435\u0446"
    ],
    "name:und_x_variant":[
        "Budvinets",
        "Budvenets"
    ],
    "wof:name":"Budvenets",
    "wof:placetype":"locality"
},
  "geometry": {"coordinates":[33.077,53.6544],"type":"Point"}
}