{
  "type": "Feature",
  "properties": {
    "gn:admin1_code":"16",
    "gn:asciiname":"Sirikkasy",
    "gn:country_code":"RU",
    "gn:dem":104,
    "gn:feature_class":"P",
    "gn:feature_code":"PPL",
    "gn:name":"Sirikkasy",
    "gn:population":0,
    "gn:timezone":"Europe/Moscow",
    "iso:country":"RU",
    "name:rus_x_preferred":[
        "\u0421\u0438\u0440\u0438\u043a\u043a\u0430\u0441\u044b"
    ],
    "wof:name":"Sirikkasy",
    "wof:placetype":"locality"
},
  "geometry": {"coordinates":[46.51393,55.74249],"type":"Point"}
}