{
  "type": "Feature",
  "properties": {
    "gn:admin1_code":"40",
    "gn:asciiname":"Bakharevo",
    "gn:country_code":"RU",
    "gn:dem":65,
    "gn:feature_class":"P",
    "gn:feature_code":"PPL",
    "gn:name":"Bakhar\u00ebvo",
    "gn:population":0,
    "gn:timezone":"Asia/Yekaterinburg",
    "iso:country":"RU",
    "name:eng_x_preferred":[
        "Bakhar\u00ebva"
    ],
    "name:rus_x_preferred":[
        "\u0411\u0430\u0445\u0430\u0440\u0435\u0432\u043e"
    ],
    "name:rus_x_variant":[
        "\u0411\u0430\u0445\u0430\u0440\u0451\u0432\u043e"
    ],
    "name:und_x_variant":[
        "Bakhar\u00ebvo"
    ],
    "wof:name":"Bakharevo",
    "wof:placetype":"locality"
},
  "geometry": {"coordinates":[64.58750000000001,56.1439],"type":"Point"}
}