{
  "type": "Feature",
  "properties": {
    "gn:admin1_code":"65",
    "gn:asciiname":"Lugovskoy",
    "gn:country_code":"RU",
    "gn:dem":124,
    "gn:feature_class":"P",
    "gn:feature_code":"PPL",
    "gn:name":"Lugovskoy",
    "gn:population":0,
    "gn:timezone":"Europe/Samara",
    "iso:country":"RU",
    "name:rus_x_preferred":[
        "\u041b\u0443\u0433\u043e\u0432\u0441\u043a\u043e\u0439"
    ],
    "wof:name":"Lugovskoy",
    "wof:placetype":"locality"
},
  "geometry": {"coordinates":[48.7569,53.6503],"type":"Point"}
}