{
  "type": "Feature",
  "properties": {
    "gn:admin1_code":"47",
    "gn:asciiname":"Novinki",
    "gn:country_code":"RU",
    "gn:dem":171,
    "gn:feature_class":"P",
    "gn:feature_code":"PPL",
    "gn:name":"Novinki",
    "gn:population":0,
    "gn:timezone":"Europe/Moscow",
    "iso:country":"RU",
    "name:nor_x_preferred":[
        "Novinki"
    ],
    "name:rus_x_preferred":[
        "\u041d\u043e\u0432\u0438\u043d\u043a\u0438"
    ],
    "wof:name":"Novinki",
    "wof:placetype":"locality"
},
  "geometry": {"coordinates":[35.74031,56.08943000000001],"type":"Point"}
}