{
  "type": "Feature",
  "properties": {
    "gn:admin1_code":"37",
    "gn:asciiname":"Novinskoye",
    "gn:country_code":"RU",
    "gn:dem":188,
    "gn:feature_class":"P",
    "gn:feature_code":"PPL",
    "gn:name":"Novinskoye",
    "gn:population":0,
    "gn:timezone":"Europe/Moscow",
    "iso:country":"RU",
    "name:rus_x_preferred":[
        "\u041d\u043e\u0432\u0438\u043d\u0441\u043a\u043e\u0435"
    ],
    "name:und_x_variant":[
        "\u041d\u043e\u0432\u0438\u043d\u0441\u043a\u043e\u0435"
    ],
    "wof:name":"Novinskoye",
    "wof:placetype":"locality"
},
  "geometry": {"coordinates":[42.8557,58.2484],"type":"Point"}
}