{
  "type": "Feature",
  "properties": {
    "gn:admin1_code":"85.0",
    "gn:asciiname":"Chukharitsa",
    "gn:country_code":"RU",
    "gn:dem":137,
    "gn:feature_class":"P",
    "gn:feature_code":"PPL",
    "gn:name":"Chukharitsa",
    "gn:population":0,
    "gn:timezone":"Europe/Moscow",
    "iso:country":"RU",
    "name:nor_x_preferred":[
        "Tsjukharitsa"
    ],
    "name:rus_x_preferred":[
        "\u0427\u0443\u0445\u0430\u0440\u0438\u0446a"
    ],
    "name:und_x_variant":[
        "\u0427\u0443\u0445\u0430\u0440\u0438\u0446a",
        "Chukharitsy",
        "Chukharitsa"
    ],
    "wof:name":"Chukharitsa",
    "wof:placetype":"locality"
},
  "geometry": {"coordinates":[41.01667,58.82333000000001],"type":"Point"}
}