{
  "type": "Feature",
  "properties": {
    "gn:admin1_code":"90",
    "gn:asciiname":"Korobeyniki",
    "gn:country_code":"RU",
    "gn:dem":173,
    "gn:feature_class":"P",
    "gn:feature_code":"PPL",
    "gn:name":"Korobeyniki",
    "gn:population":0,
    "gn:timezone":"Asia/Yekaterinburg",
    "iso:country":"RU",
    "name:rus_x_preferred":[
        "\u041a\u043e\u0440\u043e\u0431\u0435\u0439\u043d\u0438\u043a\u0438"
    ],
    "name:und_x_variant":[
        "Korobeynikovo",
        "Korobeyniki"
    ],
    "wof:name":"Korobeyniki",
    "wof:placetype":"locality"
},
  "geometry": {"coordinates":[56.25717,56.71245],"type":"Point"}
}