{
  "type": "Feature",
  "properties": {
    "gn:admin1_code":"54",
    "gn:asciiname":"Alekseyevka",
    "gn:country_code":"RU",
    "gn:dem":118,
    "gn:feature_class":"P",
    "gn:feature_code":"PPL",
    "gn:name":"Alekseyevka",
    "gn:population":0,
    "gn:timezone":"Asia/Omsk",
    "iso:country":"RU",
    "name:ben_x_preferred":[
        "\u0986\u09b2\u09c7\u0995\u09b8\u09c7\u0987\u09ad\u0995\u09be"
    ],
    "name:ell_x_preferred":[
        "\u0391\u03bb\u03b5\u03be\u03ad\u03b5\u03b2\u03ba\u03b1"
    ],
    "name:hin_x_preferred":[
        "\u090f\u0932\u0947\u0915\u094d\u0938\u0947\u092f\u0947\u0935\u094d\u0915\u093e"
    ],
    "name:ind_x_preferred":[
        "Alekseyevka"
    ],
    "name:jpn_x_preferred":[
        "\u30a2\u30ec\u30af\u30bb\u30a4\u30a8\u30d5\u30ab"
    ],
    "name:kor_x_preferred":[
        "\uc54c\ub809\uc138\uc608\ud504\uce74"
    ],
    "name:rus_x_preferred":[
        "\u0410\u043b\u0435\u043a\u0441\u0435\u0435\u0432\u043a\u0430"
    ],
    "name:spa_x_preferred":[
        "Alekseyevka"
    ],
    "name:swe_x_preferred":[
        "Aleksejevka"
    ],
    "name:vie_x_preferred":[
        "Alekseyevka"
    ],
    "wof:name":"Alekseyevka",
    "wof:placetype":"locality"
},
  "geometry": {"coordinates":[73.60420000000001,54.1935],"type":"Point"}
}