{
  "type": "Feature",
  "properties": {
    "gn:admin1_code":"10",
    "gn:asciiname":"Yurasov Khutor",
    "gn:country_code":"RU",
    "gn:dem":178,
    "gn:feature_class":"P",
    "gn:feature_code":"PPL",
    "gn:name":"Yurasov Khutor",
    "gn:population":0,
    "gn:timezone":"Europe/Moscow",
    "iso:country":"RU",
    "name:eng_x_preferred":[
        "Yurasov Khutor"
    ],
    "name:nor_x_preferred":[
        "Jurasov-Khutor"
    ],
    "name:rus_x_preferred":[
        "\u042e\u0440\u0430\u0441\u043e\u0432-\u0425\u0443\u0442\u043e\u0440"
    ],
    "name:rus_x_variant":[
        "\u042e\u0440\u0430\u0441\u043e\u0432 \u0425\u0443\u0442\u043e\u0440"
    ],
    "wof:name":"Yurasov Khutor",
    "wof:placetype":"locality"
},
  "geometry": {"coordinates":[34.5246,52.1405],"type":"Point"}
}