{
  "type": "Feature",
  "properties": {
    "gn:admin1_code":"54",
    "gn:asciiname":"Snezhnyy",
    "gn:country_code":"RU",
    "gn:dem":83,
    "gn:feature_class":"P",
    "gn:feature_code":"PPL",
    "gn:name":"Snezhnyy",
    "gn:population":0,
    "gn:timezone":"Asia/Omsk",
    "iso:country":"RU",
    "name:rus_x_preferred":[
        "\u0421\u043d\u0435\u0436\u043d\u044b\u0439"
    ],
    "wof:name":"Snezhnyy",
    "wof:placetype":"locality"
},
  "geometry": {"coordinates":[73.1503,55.0325],"type":"Point"}
}