{
  "type": "Feature",
  "properties": {
    "gn:admin1_code":"88",
    "gn:asciiname":"Trufantsevo",
    "gn:country_code":"RU",
    "gn:dem":127,
    "gn:feature_class":"P",
    "gn:feature_code":"PPL",
    "gn:name":"Trufantsevo",
    "gn:population":0,
    "gn:timezone":"Europe/Moscow",
    "iso:country":"RU",
    "name:rus_x_preferred":[
        "\u0422\u0440\u0443\u0444\u0430\u043d\u0446\u0435\u0432\u043e"
    ],
    "name:und_x_variant":[
        "Trufanovo",
        "Trufantsevo"
    ],
    "wof:name":"Trufantsevo",
    "wof:placetype":"locality"
},
  "geometry": {"coordinates":[39.1226,57.45438000000001],"type":"Point"}
}