{
  "type": "Feature",
  "properties": {
    "gn:admin1_code":"77",
    "gn:asciiname":"Lyakhonovo",
    "gn:cc2":"RU",
    "gn:country_code":"RU",
    "gn:dem":231,
    "gn:feature_class":"P",
    "gn:feature_code":"PPL",
    "gn:name":"Lyakhonovo",
    "gn:population":0,
    "gn:timezone":"Europe/Moscow",
    "iso:country":"RU",
    "name:rus_x_preferred":[
        "\u041b\u044f\u0445\u043e\u043d\u043e\u0432\u043e"
    ],
    "name:und_x_variant":[
        "Lyakhova",
        "Lyakhonovo",
        "\u041b\u044f\u0445\u043e\u043d\u043e\u0432\u043e"
    ],
    "wof:name":"Lyakhonovo",
    "wof:placetype":"locality"
},
  "geometry": {"coordinates":[32.75,57.11666999999999],"type":"Point"}
}