{
  "type": "Feature",
  "properties": {
    "gn:admin1_code":"9",
    "gn:asciiname":"Novodevichiy",
    "gn:country_code":"RU",
    "gn:dem":163,
    "gn:feature_class":"P",
    "gn:feature_code":"PPL",
    "gn:name":"Novodevichiy",
    "gn:population":0,
    "gn:timezone":"Europe/Moscow",
    "iso:country":"RU",
    "name:rus_x_preferred":[
        "\u041d\u043e\u0432\u043e\u0434\u0435\u0432\u0438\u0447\u0438\u0439"
    ],
    "wof:name":"Novodevichiy",
    "wof:placetype":"locality"
},
  "geometry": {"coordinates":[37.5826,50.4838],"type":"Point"}
}