{
  "type": "Feature",
  "properties": {
    "gn:admin1_code":"63",
    "gn:asciiname":"Shkolog",
    "gn:cc2":"RU",
    "gn:country_code":"RU",
    "gn:dem":182,
    "gn:feature_class":"P",
    "gn:feature_code":"PPL",
    "gn:name":"Shkolog",
    "gn:population":0,
    "gn:timezone":"Asia/Vladivostok",
    "iso:country":"RU",
    "name:rus_x_preferred":[
        "\u0428\u043a\u043e\u043b\u043e\u0433"
    ],
    "name:und_x_variant":[
        "Shikolog",
        "Shkolog",
        "\u0428\u043a\u043e\u043b\u043e\u0433"
    ],
    "wof:name":"Shkolog",
    "wof:placetype":"locality"
},
  "geometry": {"coordinates":[135.06666999999999,60.46666999999999],"type":"Point"}
}