{
  "type": "Feature",
  "properties": {
    "gn:admin1_code":"51",
    "gn:asciiname":"Aksenovo",
    "gn:country_code":"RU",
    "gn:dem":118,
    "gn:feature_class":"P",
    "gn:feature_code":"PPL",
    "gn:name":"Aks\u00ebnovo",
    "gn:population":0,
    "gn:timezone":"Europe/Moscow",
    "iso:country":"RU",
    "name:rus_x_preferred":[
        "\u0410\u043a\u0441\u0451\u043d\u043e\u0432\u043e"
    ],
    "name:und_x_variant":[
        "Aks\u00ebnovo",
        "\u0410\u043a\u0441\u0451\u043d\u043e\u0432\u043e"
    ],
    "wof:name":"Aksenovo",
    "wof:placetype":"locality"
},
  "geometry": {"coordinates":[44.6494,57.0568],"type":"Point"}
}