{
  "type": "Feature",
  "properties": {
    "gn:admin1_code":"4",
    "gn:asciiname":"Gusinaya Lyaga",
    "gn:country_code":"RU",
    "gn:dem":112,
    "gn:feature_class":"P",
    "gn:feature_code":"PPL",
    "gn:name":"Gusinaya Lyaga",
    "gn:population":0,
    "gn:timezone":"Asia/Barnaul",
    "iso:country":"RU",
    "name:eng_x_preferred":[
        "Gusinaya Lyaga"
    ],
    "name:nor_x_preferred":[
        "Gusinaja-Ljaga"
    ],
    "name:rus_x_preferred":[
        "\u0413\u0443\u0441\u0438\u043d\u0430\u044f-\u041b\u044f\u0433\u0430"
    ],
    "name:rus_x_variant":[
        "\u0413\u0443\u0441\u0438\u043d\u0430\u044f \u041b\u044f\u0433\u0430"
    ],
    "name:und_x_variant":[
        "Gusino-Lyaga",
        "Gusinaya Lyaga",
        "\u0413\u0443\u0441\u0438\u043d\u0430\u044f \u041b\u044f\u0433\u0430"
    ],
    "wof:name":"Gusinaya Lyaga",
    "wof:placetype":"locality"
},
  "geometry": {"coordinates":[78.3939,53.40600000000001],"type":"Point"}
}