{
  "type": "Feature",
  "properties": {
    "gn:admin1_code":"70",
    "gn:asciiname":"Gor'ko-Balkovskiye",
    "gn:cc2":"RU",
    "gn:country_code":"RU",
    "gn:dem":428,
    "gn:feature_class":"P",
    "gn:feature_code":"PPL",
    "gn:name":"Gor'ko-Balkovskiye",
    "gn:population":0,
    "gn:timezone":"Europe/Moscow",
    "iso:country":"RU",
    "name:und_x_variant":[
        "Gor'ka Bolkovskiy",
        "Gor'ka-Balkovskiy"
    ],
    "wof:name":"Gor'ko-Balkovskiye",
    "wof:placetype":"locality"
},
  "geometry": {"coordinates":[42.45083,44.89972],"type":"Point"}
}