{
  "type": "Feature",
  "properties": {
    "gn:admin1_code":"67.0",
    "gn:asciiname":"Kamenskiy",
    "gn:country_code":"RU",
    "gn:dem":84,
    "gn:feature_class":"P",
    "gn:feature_code":"PPL",
    "gn:name":"Kamenskiy",
    "gn:population":0,
    "gn:timezone":"Europe/Saratov",
    "iso:country":"RU",
    "name:rus_x_preferred":[
        "\u041a\u0430\u043c\u0435\u043d\u0441\u043a\u0438\u0439"
    ],
    "name:und_x_variant":[
        "\u041a\u0430\u043c\u0435\u043d\u0441\u043a\u0438\u0439"
    ],
    "wof:name":"Kamenskiy",
    "wof:placetype":"locality"
},
  "geometry": {"coordinates":[45.76555,51.65104],"type":"Point"}
}