{
  "type": "Feature",
  "properties": {
    "gn:admin1_code":"17",
    "gn:admin2_code":"Shamil'skiy Rayon",
    "gn:asciiname":"Tlyakh",
    "gn:country_code":"RU",
    "gn:dem":1364,
    "gn:feature_class":"P",
    "gn:feature_code":"PPL",
    "gn:name":"Tlyakh",
    "gn:population":0,
    "gn:timezone":"Europe/Moscow",
    "iso:country":"RU",
    "name:rus_x_preferred":[
        "\u0422\u043b\u044f\u0445"
    ],
    "name:und_x_variant":[
        "\u0422\u043b\u044f\u0445"
    ],
    "wof:name":"Tlyakh",
    "wof:placetype":"locality"
},
  "geometry": {"coordinates":[46.54796,42.38751],"type":"Point"}
}