{
  "type": "Feature",
  "properties": {
    "gn:admin1_code":"88",
    "gn:asciiname":"Zhoglovo",
    "gn:country_code":"RU",
    "gn:dem":176,
    "gn:feature_class":"P",
    "gn:feature_code":"PPL",
    "gn:name":"Zhoglovo",
    "gn:population":0,
    "gn:timezone":"Europe/Moscow",
    "iso:country":"RU",
    "name:rus_x_preferred":[
        "\u0416\u043e\u0433\u043b\u043e\u0432\u043e"
    ],
    "wof:name":"Zhoglovo",
    "wof:placetype":"locality"
},
  "geometry": {"coordinates":[39.22294,57.14695],"type":"Point"}
}