{
  "type": "Feature",
  "properties": {
    "gn:admin1_code":"73",
    "gn:asciiname":"Leninizm",
    "gn:country_code":"RU",
    "gn:dem":136,
    "gn:feature_class":"P",
    "gn:feature_code":"PPL",
    "gn:name":"Leninizm",
    "gn:population":0,
    "gn:timezone":"Europe/Moscow",
    "iso:country":"RU",
    "name:rus_x_preferred":[
        "\u041b\u0435\u043d\u0438\u043d\u0438\u0437\u043c"
    ],
    "name:und_x_variant":[
        "\u041b\u0435\u043d\u0438\u043d\u0438\u0437\u043c"
    ],
    "wof:name":"Leninizm",
    "wof:placetype":"locality"
},
  "geometry": {"coordinates":[52.9836,55.5828],"type":"Point"}
}