{
  "type": "Feature",
  "properties": {
    "gn:admin1_code":"43",
    "gn:asciiname":"Khripunovka",
    "gn:country_code":"RU",
    "gn:dem":207,
    "gn:feature_class":"P",
    "gn:feature_code":"PPL",
    "gn:name":"Khripunovka",
    "gn:population":0,
    "gn:timezone":"Europe/Moscow",
    "iso:country":"RU",
    "name:rus_x_preferred":[
        "\u0425\u0440\u0438\u043f\u0443\u043d\u043e\u0432\u043a\u0430"
    ],
    "wof:name":"Khripunovka",
    "wof:placetype":"locality"
},
  "geometry": {"coordinates":[39.5008,53.4132],"type":"Point"}
}