{
  "type": "Feature",
  "properties": {
    "gn:admin1_code":"16",
    "gn:asciiname":"Malyye Katrasy",
    "gn:country_code":"RU",
    "gn:dem":189,
    "gn:feature_class":"P",
    "gn:feature_code":"PPL",
    "gn:name":"Malyye Katrasy",
    "gn:population":0,
    "gn:timezone":"Europe/Moscow",
    "iso:country":"RU",
    "name:rus_x_preferred":[
        "\u041c\u0430\u043b\u044b\u0435 \u041a\u0430\u0442\u0440\u0430\u0441\u044b"
    ],
    "name:und_x_variant":[
        "Malyye Katrasi",
        "Malyye Katrasy",
        "\u041c\u0430\u043b\u044b\u0435 \u041a\u0430\u0442\u0440\u0430\u0441\u044b"
    ],
    "wof:name":"Malyye Katrasy",
    "wof:placetype":"locality"
},
  "geometry": {"coordinates":[47.11198,56.08022],"type":"Point"}
}