{
  "type": "Feature",
  "properties": {
    "gn:admin1_code":"37.0",
    "gn:asciiname":"Karimovo",
    "gn:country_code":"RU",
    "gn:dem":108,
    "gn:feature_class":"P",
    "gn:feature_code":"PPL",
    "gn:name":"Karimovo",
    "gn:population":0,
    "gn:timezone":"Europe/Moscow",
    "iso:country":"RU",
    "name:bak_x_preferred":[
        "\u041a\u04d9\u0440\u0438\u043c"
    ],
    "name:che_x_preferred":[
        "\u041a\u0430\u0440\u0438\u043c\u043e\u0432\u043e"
    ],
    "name:hye_x_preferred":[
        "\u053f\u0561\u0580\u056b\u0574\u0578\u057e\u0578"
    ],
    "name:kaz_x_preferred":[
        "\u041a\u0430\u0440\u0438\u043c"
    ],
    "name:kir_x_preferred":[
        "\u041a\u0430\u0440\u0438\u043c"
    ],
    "name:rus_x_preferred":[
        "\u041a\u0430\u0440\u0438\u043c\u043e\u0432\u043e"
    ],
    "name:tat_x_preferred":[
        "\u041a\u04d9\u0440\u0438\u043c"
    ],
    "name:ukr_x_preferred":[
        "\u041a\u0430\u0440\u0456\u043c\u043e\u0432\u043e"
    ],
    "wof:name":"Karimovo",
    "wof:placetype":"locality"
},
  "geometry": {"coordinates":[40.87838,57.72375],"type":"Point"}
}