{
  "type": "Feature",
  "properties": {
    "gn:admin1_code":"13",
    "gn:asciiname":"Tatishchevo",
    "gn:country_code":"RU",
    "gn:dem":306,
    "gn:feature_class":"P",
    "gn:feature_code":"PPL",
    "gn:name":"Tatishchevo",
    "gn:population":0,
    "gn:timezone":"Asia/Yekaterinburg",
    "iso:country":"RU",
    "name:deu_x_preferred":[
        "Tatischtschewo"
    ],
    "name:eng_x_preferred":[
        "Tatishchevo"
    ],
    "name:nor_x_preferred":[
        "Tatisjtsjevo"
    ],
    "name:rus_x_preferred":[
        "\u0422\u0430\u0442\u0438\u0449\u0435\u0432\u043e"
    ],
    "name:und_x_variant":[
        "Novotatishchevskiy",
        "Oztishchevskiy",
        "Tatishchevo"
    ],
    "wof:name":"Tatishchevo",
    "wof:placetype":"locality"
},
  "geometry": {"coordinates":[60.38061999999999,53.36093],"type":"Point"}
}