{
  "type": "Feature",
  "properties": {
    "gn:admin1_code":"56",
    "gn:asciiname":"Mikhneva",
    "gn:country_code":"RU",
    "gn:dem":158,
    "gn:feature_class":"P",
    "gn:feature_code":"PPL",
    "gn:name":"Mikhn\u00ebva",
    "gn:population":0,
    "gn:timezone":"Europe/Moscow",
    "iso:country":"RU",
    "name:rus_x_preferred":[
        "\u041c\u0438\u0445\u043d\u0451\u0432\u0430"
    ],
    "name:und_x_variant":[
        "Mikhanovo",
        "Mikhn\u00ebvo",
        "Mikhn\u00ebva",
        "\u041c\u0438\u0445\u043d\u0451\u0432\u0430"
    ],
    "wof:name":"Mikhneva",
    "wof:placetype":"locality"
},
  "geometry": {"coordinates":[36.04388,53.5353],"type":"Point"}
}