{
  "type": "Feature",
  "properties": {
    "gn:admin1_code":"90",
    "gn:asciiname":"Buzhdym",
    "gn:country_code":"RU",
    "gn:dem":149,
    "gn:feature_class":"P",
    "gn:feature_code":"PPL",
    "gn:name":"Buzhdym",
    "gn:population":0,
    "gn:timezone":"Asia/Yekaterinburg",
    "iso:country":"RU",
    "name:eng_x_preferred":[
        "Buzhdym"
    ],
    "name:nor_x_preferred":[
        "Buzjdym"
    ],
    "name:rus_x_preferred":[
        "\u0411\u0443\u0436\u0434\u044b\u043c"
    ],
    "name:und_x_variant":[
        "\u0411\u0443\u0436\u0434\u044b\u043c"
    ],
    "wof:name":"Buzhdym",
    "wof:placetype":"locality"
},
  "geometry": {"coordinates":[54.8888,59.6623],"type":"Point"}
}