{
  "type": "Feature",
  "properties": {
    "gn:admin1_code":"43",
    "gn:asciiname":"Topki",
    "gn:country_code":"RU",
    "gn:dem":149,
    "gn:feature_class":"P",
    "gn:feature_code":"PPL",
    "gn:name":"Topki",
    "gn:population":0,
    "gn:timezone":"Europe/Moscow",
    "iso:country":"RU",
    "name:ben_x_preferred":[
        "\u09a4\u09cb\u09aa\u0995\u09bf"
    ],
    "name:ell_x_preferred":[
        "\u03a4\u03cc\u03c0\u03ba\u03b9"
    ],
    "name:eng_x_preferred":[
        "Topki"
    ],
    "name:heb_x_preferred":[
        "\u05d8\u05d5\u05e4\u05e7\u05d9"
    ],
    "name:hin_x_preferred":[
        "\u0924\u094b\u092a\u094d\u0938\u094d\u0915\u0940"
    ],
    "name:ind_x_preferred":[
        "Topki"
    ],
    "name:jpn_x_preferred":[
        "\u30c8\u30d7\u30ad"
    ],
    "name:kor_x_preferred":[
        "\ud1b1\ud0a4"
    ],
    "name:nor_x_preferred":[
        "Topki"
    ],
    "name:rus_x_preferred":[
        "\u0422\u043e\u043f\u043a\u0438"
    ],
    "name:spa_x_preferred":[
        "Topki"
    ],
    "name:urd_x_preferred":[
        "\u0679\u0648\u067e\u06a9\u06cc"
    ],
    "wof:name":"Topki",
    "wof:placetype":"locality"
},
  "geometry": {"coordinates":[39.60608,53.33723],"type":"Point"}
}