{
  "type": "Feature",
  "properties": {
    "gn:admin1_code":"43",
    "gn:asciiname":"Topki",
    "gn:country_code":"RU",
    "gn:dem":149,
    "gn:feature_class":"P",
    "gn:feature_code":"PPL",
    "gn:name":"Topki",
    "gn:population":0,
    "gn:timezone":"Europe/Moscow",
    "iso:country":"RU",
    "name:eng_x_preferred":[
        "Topki"
    ],
    "name:nor_x_preferred":[
        "Topki"
    ],
    "name:rus_x_preferred":[
        "\u0422\u043e\u043f\u043a\u0438"
    ],
    "name:und_x_variant":[
        "\u0422\u043e\u043f\u043a\u0438",
        "Topki"
    ],
    "wof:name":"Topki",
    "wof:placetype":"locality"
},
  "geometry": {"coordinates":[39.60608,53.33723000000001],"type":"Point"}
}