{
  "type": "Feature",
  "properties": {
    "gn:admin1_code":"69",
    "gn:asciiname":"Yezhevitsy",
    "gn:country_code":"RU",
    "gn:dem":226,
    "gn:feature_class":"P",
    "gn:feature_code":"PPL",
    "gn:name":"Yezh\u00ebvitsy",
    "gn:population":0,
    "gn:timezone":"Europe/Moscow",
    "iso:country":"RU",
    "wof:name":"Yezhevitsy",
    "wof:placetype":"locality"
},
  "geometry": {"coordinates":[34.49085,55.0913],"type":"Point"}
}