{
  "type": "Feature",
  "properties": {
    "gn:admin1_code":"85.0",
    "gn:asciiname":"Dekteritsa",
    "gn:country_code":"RU",
    "gn:dem":165,
    "gn:feature_class":"P",
    "gn:feature_code":"PPL",
    "gn:name":"Dekteritsa",
    "gn:population":0,
    "gn:timezone":"Europe/Moscow",
    "iso:country":"RU",
    "name:rus_x_preferred":[
        "\u0414\u0435\u043a\u0442\u0435\u0440\u0438\u0446\u0430"
    ],
    "name:und_x_variant":[
        "Denteritsa",
        "Dekteritsa",
        "\u0414\u0435\u043a\u0442\u0435\u0440\u0438\u0446\u0430"
    ],
    "wof:name":"Dekteritsa",
    "wof:placetype":"locality"
},
  "geometry": {"coordinates":[39.34173,59.46218],"type":"Point"}
}