{
  "type": "Feature",
  "properties": {
    "gn:admin1_code":"47",
    "gn:asciiname":"Kobelevo",
    "gn:country_code":"RU",
    "gn:dem":127,
    "gn:feature_class":"P",
    "gn:feature_code":"PPL",
    "gn:name":"Kobel\u00ebvo",
    "gn:population":0,
    "gn:timezone":"Europe/Moscow",
    "iso:country":"RU",
    "name:rus_x_preferred":[
        "\u041a\u043e\u0431\u0435\u043b\u0451\u0432\u043e"
    ],
    "name:und_x_variant":[
        "Kobel\u00ebvo"
    ],
    "wof:name":"Kobelevo",
    "wof:placetype":"locality"
},
  "geometry": {"coordinates":[39.50053,55.6388],"type":"Point"}
}