{
  "type": "Feature",
  "properties": {
    "gn:admin1_code":"25",
    "gn:asciiname":"Kostyukovo",
    "gn:country_code":"RU",
    "gn:dem":156,
    "gn:feature_class":"P",
    "gn:feature_code":"PPL",
    "gn:name":"Kostyukovo",
    "gn:population":0,
    "gn:timezone":"Europe/Moscow",
    "iso:country":"RU",
    "name:rus_x_preferred":[
        "\u041a\u043e\u0441\u0442\u044e\u043a\u043e\u0432\u043e"
    ],
    "wof:name":"Kostyukovo",
    "wof:placetype":"locality"
},
  "geometry": {"coordinates":[35.01556,54.89833],"type":"Point"}
}