{
  "type": "Feature",
  "properties": {
    "gn:admin1_code":"33",
    "gn:asciiname":"Bol'shaya Lyzhnya",
    "gn:country_code":"RU",
    "gn:dem":144,
    "gn:feature_class":"P",
    "gn:feature_code":"PPL",
    "gn:name":"Bol\u2019shaya Lyzhnya",
    "gn:population":0,
    "gn:timezone":"Europe/Kirov",
    "iso:country":"RU",
    "name:rus_x_preferred":[
        "\u0411\u043e\u043b\u044c\u0448\u0430\u044f \u041b\u044b\u0436\u043d\u044f"
    ],
    "name:und_x_variant":[
        "Bol\u2019shaya Lyzhnya"
    ],
    "wof:name":"Bol'shaya Lyzhnya",
    "wof:placetype":"locality"
},
  "geometry": {"coordinates":[47.2851,57.2567],"type":"Point"}
}