{
  "type": "Feature",
  "properties": {
    "gn:admin1_code":"61",
    "gn:asciiname":"Nikol'skaya",
    "gn:country_code":"RU",
    "gn:dem":66,
    "gn:feature_class":"P",
    "gn:feature_code":"PPL",
    "gn:name":"Nikol\u2019skaya",
    "gn:population":0,
    "gn:timezone":"Europe/Moscow",
    "iso:country":"RU",
    "name:eng_x_preferred":[
        "Nikol'skaya"
    ],
    "name:nor_x_preferred":[
        "Nikolskaja"
    ],
    "name:rus_x_preferred":[
        "\u041d\u0438\u043a\u043e\u043b\u044c\u0441\u043a\u0430\u044f"
    ],
    "name:und_x_variant":[
        "Nikolsko-Pokrovskaya",
        "Nikol\u2019skaya"
    ],
    "wof:name":"Nikol'skaya",
    "wof:placetype":"locality"
},
  "geometry": {"coordinates":[40.68129,48.95657],"type":"Point"}
}