{
  "type": "Feature",
  "properties": {
    "gn:admin1_code":"55",
    "gn:asciiname":"Sergushino",
    "gn:country_code":"RU",
    "gn:dem":198,
    "gn:feature_class":"P",
    "gn:feature_code":"PPL",
    "gn:name":"Sergushino",
    "gn:population":0,
    "gn:timezone":"Asia/Yekaterinburg",
    "iso:country":"RU",
    "name:eng_x_preferred":[
        "Sergushkino"
    ],
    "name:nor_x_preferred":[
        "Sergusjkino"
    ],
    "name:rus_x_preferred":[
        "\u0421\u0435\u0440\u0433\u0443\u0448\u0438\u043d\u043e"
    ],
    "name:und_x_variant":[
        "Sergushino"
    ],
    "wof:name":"Sergushino",
    "wof:placetype":"locality"
},
  "geometry": {"coordinates":[53.22848000000001,54.04166],"type":"Point"}
}