{
  "type": "Feature",
  "properties": {
    "gn:admin1_code":"57",
    "gn:asciiname":"Michkas",
    "gn:country_code":"RU",
    "gn:dem":131,
    "gn:feature_class":"P",
    "gn:feature_code":"PPL",
    "gn:name":"Michkas",
    "gn:population":0,
    "gn:timezone":"Europe/Moscow",
    "iso:country":"RU",
    "name:eng_x_preferred":[
        "Michkass"
    ],
    "name:nor_x_preferred":[
        "Mitsjkas"
    ],
    "name:rus_x_preferred":[
        "\u041c\u0438\u0447\u043a\u0430\u0441"
    ],
    "name:und_x_variant":[
        "Michkassy",
        "Michkas"
    ],
    "wof:name":"Michkas",
    "wof:placetype":"locality"
},
  "geometry": {"coordinates":[45.53019000000001,53.67100000000001],"type":"Point"}
}