{
  "type": "Feature",
  "properties": {
    "gn:admin1_code":"30",
    "gn:asciiname":"Kuravinka",
    "gn:country_code":"RU",
    "gn:dem":484,
    "gn:feature_class":"P",
    "gn:feature_code":"PPL",
    "gn:name":"Kuravinka",
    "gn:population":0,
    "gn:timezone":"Asia/Vladivostok",
    "iso:country":"RU",
    "name:rus_x_preferred":[
        "\u041a\u0443\u0440\u0430\u0432\u0438\u043d\u043a\u0430"
    ],
    "name:und_x_variant":[
        "\u041a\u0443\u0440\u0430\u0432\u0438\u043d\u043a\u0430"
    ],
    "wof:name":"Kuravinka",
    "wof:placetype":"locality"
},
  "geometry": {"coordinates":[131.90000000000001,50.03333],"type":"Point"}
}