{
  "type": "Feature",
  "properties": {
    "gn:admin1_code":"17",
    "gn:admin2_code":"550476",
    "gn:asciiname":"Tsiyab-Tsoloda",
    "gn:cc2":"RU",
    "gn:country_code":"RU",
    "gn:dem":140,
    "gn:feature_class":"P",
    "gn:feature_code":"PPL",
    "gn:name":"Tsiyab-Tsoloda",
    "gn:population":0,
    "gn:timezone":"Europe/Moscow",
    "iso:country":"RU",
    "name:rus_x_preferred":[
        "\u0426\u0438\u044f\u0431-\u0426\u043e\u043b\u043e\u0434\u0430"
    ],
    "name:und_x_variant":[
        "Gerzel\u2019-Kutan",
        "Tsiyab-Tsoloda",
        "\u0426\u0438\u044f\u0431-\u0426\u043e\u043b\u043e\u0434\u0430"
    ],
    "wof:name":"Tsiyab-Tsoloda",
    "wof:placetype":"locality"
},
  "geometry": {"coordinates":[46.41694,43.25167],"type":"Point"}
}