{
  "type": "Feature",
  "properties": {
    "gn:admin1_code":"52.0",
    "gn:asciiname":"Kotovo",
    "gn:country_code":"RU",
    "gn:dem":88,
    "gn:feature_class":"P",
    "gn:feature_code":"PPL",
    "gn:name":"Kotovo",
    "gn:population":0,
    "gn:timezone":"Europe/Moscow",
    "iso:country":"RU",
    "name:hye_x_preferred":[
        "\u053f\u0578\u057f\u0578\u057e\u0578"
    ],
    "wof:name":"Kotovo",
    "wof:placetype":"locality"
},
  "geometry": {"coordinates":[33.47111,58.48556],"type":"Point"}
}