{
  "type": "Feature",
  "properties": {
    "gn:admin1_code":"33",
    "gn:asciiname":"Korosteli",
    "gn:country_code":"RU",
    "gn:dem":159,
    "gn:feature_class":"P",
    "gn:feature_code":"PPL",
    "gn:name":"Korosteli",
    "gn:population":0,
    "gn:timezone":"Europe/Kirov",
    "iso:country":"RU",
    "name:rus_x_preferred":[
        "\u041a\u043e\u0440\u043e\u0441\u0442\u0435\u043b\u0438"
    ],
    "wof:name":"Korosteli",
    "wof:placetype":"locality"
},
  "geometry": {"coordinates":[51.00132,58.39462],"type":"Point"}
}