{
  "type": "Feature",
  "properties": {
    "gn:admin1_code":"61",
    "gn:asciiname":"Mavor-Grekovskiy",
    "gn:country_code":"RU",
    "gn:dem":210,
    "gn:feature_class":"P",
    "gn:feature_code":"PPL",
    "gn:name":"Mavor-Grekovskiy",
    "gn:population":0,
    "gn:timezone":"Europe/Moscow",
    "iso:country":"RU",
    "name:rus_x_preferred":[
        "\u041c\u0430\u0432\u043e\u0440-\u0413\u0440\u0435\u043a\u043e\u0432\u0441\u043a\u0438\u0439"
    ],
    "wof:name":"Mavor-Grekovskiy",
    "wof:placetype":"locality"
},
  "geometry": {"coordinates":[40.20389,49.62611],"type":"Point"}
}