{
  "type": "Feature",
  "properties": {
    "gn:admin1_code":"9",
    "gn:asciiname":"Koshlakovo",
    "gn:country_code":"RU",
    "gn:dem":116,
    "gn:feature_class":"P",
    "gn:feature_code":"PPL",
    "gn:name":"Koshlakovo",
    "gn:population":0,
    "gn:timezone":"Europe/Moscow",
    "iso:country":"RU",
    "name:rus_x_preferred":[
        "\u041a\u043e\u0448\u043b\u0430\u043a\u043e\u0432\u043e"
    ],
    "name:und_x_variant":[
        "Kashlakovo",
        "Kopilakovo",
        "Koshlakovo"
    ],
    "wof:name":"Koshlakovo",
    "wof:placetype":"locality"
},
  "geometry": {"coordinates":[36.87695,50.51265],"type":"Point"}
}