{
  "type": "Feature",
  "properties": {
    "gn:admin1_code":"63",
    "gn:asciiname":"Kurun-Kenkga",
    "gn:cc2":"RU",
    "gn:country_code":"RU",
    "gn:dem":583,
    "gn:feature_class":"P",
    "gn:feature_code":"PPL",
    "gn:name":"Kurun-Kenkga",
    "gn:population":0,
    "gn:timezone":"Asia/Yakutsk",
    "iso:country":"RU",
    "name:rus_x_preferred":[
        "\u041a\u0443\u0440\u0443\u043d-\u041a\u0435\u043d\u043a\u0433\u0430"
    ],
    "name:und_x_variant":[
        "Kurung-Kyunkyu",
        "Kurun-Kenkyu",
        "Kurun-Kenkga",
        "\u041a\u0443\u0440\u0443\u043d-\u041a\u0435\u043d\u043a\u0433\u0430"
    ],
    "wof:name":"Kurun-Kenkga",
    "wof:placetype":"locality"
},
  "geometry": {"coordinates":[127.16667,59.93333000000001],"type":"Point"}
}