{
  "type": "Feature",
  "properties": {
    "gn:admin1_code":"24.0",
    "gn:asciiname":"Imeni Molotova",
    "gn:country_code":"RU",
    "gn:dem":-18,
    "gn:feature_class":"P",
    "gn:feature_code":"PPL",
    "gn:name":"Imeni Molotova",
    "gn:population":0,
    "gn:timezone":"Europe/Moscow",
    "iso:country":"RU",
    "name:rus_x_preferred":[
        "\u0418\u043c\u0435\u043d\u0438 \u041c\u043e\u043b\u043e\u0442\u043e\u0432\u0430"
    ],
    "wof:name":"Imeni Molotova",
    "wof:placetype":"locality"
},
  "geometry": {"coordinates":[46.35167,45.62639],"type":"Point"}
}