{
  "type": "Feature",
  "properties": {
    "gn:admin1_code":"28",
    "gn:asciiname":"Pertozero",
    "gn:country_code":"RU",
    "gn:dem":115,
    "gn:feature_class":"P",
    "gn:feature_code":"PPL",
    "gn:name":"Pertozero",
    "gn:population":0,
    "gn:timezone":"Europe/Moscow",
    "iso:country":"RU",
    "name:eng_x_preferred":[
        "Pertozero"
    ],
    "name:fin_x_preferred":[
        "Perttij\u00e4rvi"
    ],
    "name:nor_x_preferred":[
        "Pertozero"
    ],
    "name:rus_x_preferred":[
        "\u041f\u0435\u0440\u0442\u043e\u0437\u0435\u0440\u043e"
    ],
    "wof:name":"Pertozero",
    "wof:placetype":"locality"
},
  "geometry": {"coordinates":[33.15857,64.16606],"type":"Point"}
}