{
  "type": "Feature",
  "properties": {
    "gn:admin1_code":"65",
    "gn:asciiname":"Privol'nyy",
    "gn:country_code":"RU",
    "gn:dem":160,
    "gn:feature_class":"P",
    "gn:feature_code":"PPL",
    "gn:name":"Privol\u2019nyy",
    "gn:population":0,
    "gn:timezone":"Europe/Samara",
    "iso:country":"RU",
    "name:rus_x_preferred":[
        "\u041f\u0440\u0438\u0432\u043e\u043b\u044c\u043d\u044b\u0439"
    ],
    "name:und_x_variant":[
        "Privol\u2019ny",
        "Privol\u2019nyy"
    ],
    "wof:name":"Privol'nyy",
    "wof:placetype":"locality"
},
  "geometry": {"coordinates":[51.56667,52.75],"type":"Point"}
}