{
  "type": "Feature",
  "properties": {
    "gn:admin1_code":"28",
    "gn:asciiname":"Ramentsy",
    "gn:country_code":"RU",
    "gn:dem":169,
    "gn:feature_class":"P",
    "gn:feature_code":"PPL",
    "gn:name":"Ramentsy",
    "gn:population":0,
    "gn:timezone":"Europe/Moscow",
    "iso:country":"RU",
    "name:eng_x_preferred":[
        "Ramentsy"
    ],
    "name:nor_x_preferred":[
        "Ramentsy"
    ],
    "name:rus_x_preferred":[
        "\u0420\u0430\u043c\u0435\u043d\u0446\u044b"
    ],
    "wof:name":"Ramentsy",
    "wof:placetype":"locality"
},
  "geometry": {"coordinates":[34.31621,63.27824],"type":"Point"}
}