{
  "type": "Feature",
  "properties": {
    "gn:admin1_code":"77",
    "gn:asciiname":"Zaklin'ye",
    "gn:country_code":"RU",
    "gn:dem":196,
    "gn:feature_class":"P",
    "gn:feature_code":"PPL",
    "gn:name":"Zaklin\u2019ye",
    "gn:population":0,
    "gn:timezone":"Europe/Moscow",
    "iso:country":"RU",
    "name:rus_x_preferred":[
        "\u0417\u0430\u043a\u043b\u0438\u043d\u044c\u0435"
    ],
    "name:und_x_variant":[
        "Zaklin\u2019ye"
    ],
    "wof:name":"Zaklin'ye",
    "wof:placetype":"locality"
},
  "geometry": {"coordinates":[36.2179,57.4518],"type":"Point"}
}