{
  "type": "Feature",
  "properties": {
    "gn:admin1_code":"8",
    "gn:asciiname":"Novyye Sarly",
    "gn:country_code":"RU",
    "gn:dem":112,
    "gn:feature_class":"P",
    "gn:feature_code":"PPL",
    "gn:name":"Novyye Sarly",
    "gn:population":0,
    "gn:timezone":"Asia/Yekaterinburg",
    "iso:country":"RU",
    "name:rus_x_preferred":[
        "\u041d\u043e\u0432\u044b\u0435 \u0421\u0430\u0440\u043b\u044b"
    ],
    "wof:name":"Novyye Sarly",
    "wof:placetype":"locality"
},
  "geometry": {"coordinates":[53.48333,54.98333],"type":"Point"}
}