{
  "type": "Feature",
  "properties": {
    "gn:admin1_code":"47",
    "gn:asciiname":"Kuznetsy",
    "gn:country_code":"RU",
    "gn:dem":139,
    "gn:feature_class":"P",
    "gn:feature_code":"PPL",
    "gn:name":"Kuznetsy",
    "gn:population":0,
    "gn:timezone":"Europe/Moscow",
    "iso:country":"RU",
    "wof:name":"Kuznetsy",
    "wof:placetype":"locality"
},
  "geometry": {"coordinates":[39.59128,55.41161],"type":"Point"}
}