{
  "type": "Feature",
  "properties": {
    "gn:admin1_code":"85",
    "gn:asciiname":"Vasil'yevskoye",
    "gn:country_code":"RU",
    "gn:dem":108,
    "gn:feature_class":"P",
    "gn:feature_code":"PPL",
    "gn:name":"Vasil\u2019yevskoye",
    "gn:population":0,
    "gn:timezone":"Europe/Moscow",
    "iso:country":"RU",
    "name:rus_x_preferred":[
        "\u0412\u0430\u0441\u0438\u043b\u044c\u0435\u0432\u0441\u043a\u043e\u0435"
    ],
    "name:und_x_variant":[
        "Vasil\u2019yevskoye",
        "\u0412\u0430\u0441\u0438\u043b\u044c\u0435\u0432\u0441\u043a\u043e\u0435"
    ],
    "wof:name":"Vasil'yevskoye",
    "wof:placetype":"locality"
},
  "geometry": {"coordinates":[38.0198,58.9666],"type":"Point"}
}