{
  "type": "Feature",
  "properties": {
    "gn:admin1_code":"85",
    "gn:asciiname":"Alferovo",
    "gn:country_code":"RU",
    "gn:dem":166,
    "gn:feature_class":"P",
    "gn:feature_code":"PPL",
    "gn:name":"Alferovo",
    "gn:population":0,
    "gn:timezone":"Europe/Moscow",
    "iso:country":"RU",
    "name:rus_x_preferred":[
        "\u0410\u043b\u0444\u0435\u0440\u043e\u0432\u043e"
    ],
    "name:und_x_variant":[
        "\u0410\u043b\u0444\u0435\u0440\u043e\u0432\u043e"
    ],
    "wof:name":"Alferovo",
    "wof:placetype":"locality"
},
  "geometry": {"coordinates":[38.90174,59.13036999999999],"type":"Point"}
}