{
  "type": "Feature",
  "properties": {
    "gn:admin1_code":"7.0",
    "gn:asciiname":"Kryazhevoye",
    "gn:country_code":"RU",
    "gn:dem":-23,
    "gn:feature_class":"P",
    "gn:feature_code":"PPL",
    "gn:name":"Kryazhevoye",
    "gn:population":0,
    "gn:timezone":"Europe/Astrakhan",
    "iso:country":"RU",
    "name:che_x_preferred":[
        "\u041a\u0440\u044f\u0436\u0435\u0432\u0438"
    ],
    "name:eng_x_preferred":[
        "Kryazhevoye"
    ],
    "name:nor_x_preferred":[
        "Krjazjevoje"
    ],
    "name:rus_x_preferred":[
        "\u041a\u0440\u044f\u0436\u0435\u0432\u043e\u0435"
    ],
    "name:tgk_x_preferred":[
        "\u041a\u0440\u044f\u0436\u0435\u0432\u043e\u0435"
    ],
    "name:und_x_variant":[
        "\u041a\u0440\u044f\u0436\u0435\u0432\u043e\u0435",
        "Kryazhevoye"
    ],
    "wof:name":"Kryazhevoye",
    "wof:placetype":"locality"
},
  "geometry": {"coordinates":[47.52787,45.85702],"type":"Point"}
}