{
  "type": "Feature",
  "properties": {
    "gn:admin1_code":"62",
    "gn:asciiname":"Pryamoglyadovo",
    "gn:country_code":"RU",
    "gn:dem":162,
    "gn:feature_class":"P",
    "gn:feature_code":"PPL",
    "gn:name":"Pryamoglyadovo",
    "gn:population":0,
    "gn:timezone":"Europe/Moscow",
    "iso:country":"RU",
    "name:rus_x_preferred":[
        "\u041f\u0440\u044f\u043c\u043e\u0433\u043b\u044f\u0434\u043e\u0432\u043e"
    ],
    "name:und_x_variant":[
        "Verkhneye Pryamoglyadovo",
        "Pryamoglyadovo"
    ],
    "wof:name":"Pryamoglyadovo",
    "wof:placetype":"locality"
},
  "geometry": {"coordinates":[38.99497,53.58218],"type":"Point"}
}