{
  "type": "Feature",
  "properties": {
    "gn:admin1_code":"63",
    "gn:asciiname":"Endybal",
    "gn:country_code":"RU",
    "gn:dem":727,
    "gn:feature_class":"P",
    "gn:feature_code":"PPL",
    "gn:name":"Endybal",
    "gn:population":0,
    "gn:timezone":"Asia/Yakutsk",
    "iso:country":"RU",
    "name:eng_x_preferred":[
        "Endybal"
    ],
    "name:nor_x_preferred":[
        "Endybal"
    ],
    "name:rus_x_preferred":[
        "\u042d\u043d\u0434\u044b\u0431\u0430\u043b"
    ],
    "name:und_x_variant":[
        "Endybal\u2019sk",
        "Endybaal",
        "\u042d\u043d\u0434\u044b\u0431\u0430\u043b",
        "Endybal"
    ],
    "wof:name":"Endybal",
    "wof:placetype":"locality"
},
  "geometry": {"coordinates":[130.27776,65.61802],"type":"Point"}
}