{
  "type": "Feature",
  "properties": {
    "gn:admin1_code":"42",
    "gn:asciiname":"Myagitsevo",
    "gn:country_code":"RU",
    "gn:dem":110,
    "gn:feature_class":"P",
    "gn:feature_code":"PPL",
    "gn:name":"Myagitsevo",
    "gn:population":0,
    "gn:timezone":"Europe/Moscow",
    "iso:country":"RU",
    "name:rus_x_preferred":[
        "\u041c\u044f\u0433\u0438\u0446\u0435\u0432\u043e"
    ],
    "name:und_x_variant":[
        "M\u00e4kit\u0161evo",
        "Myagitsevo",
        "\u041c\u044f\u0433\u0438\u0446\u0435\u0432\u043e"
    ],
    "wof:name":"Myagitsevo",
    "wof:placetype":"locality"
},
  "geometry": {"coordinates":[34.29437,60.2395],"type":"Point"}
}