{
  "type": "Feature",
  "properties": {
    "gn:admin1_code":"47",
    "gn:asciiname":"Khrabrovo",
    "gn:country_code":"RU",
    "gn:dem":246,
    "gn:feature_class":"P",
    "gn:feature_code":"PPL",
    "gn:name":"Khrabrovo",
    "gn:population":0,
    "gn:timezone":"Europe/Moscow",
    "iso:country":"RU",
    "name:rus_x_preferred":[
        "\u0425\u0440\u0430\u0431\u0440\u043e\u0432\u043e"
    ],
    "wof:name":"Khrabrovo",
    "wof:placetype":"locality"
},
  "geometry": {"coordinates":[35.65667,55.44111],"type":"Point"}
}