{
  "type": "Feature",
  "properties": {
    "gn:admin1_code":"61",
    "gn:asciiname":"Gorobtsovskiy",
    "gn:country_code":"RU",
    "gn:dem":112,
    "gn:feature_class":"P",
    "gn:feature_code":"PPL",
    "gn:name":"Gorobtsovskiy",
    "gn:population":0,
    "gn:timezone":"Europe/Moscow",
    "iso:country":"RU",
    "name:rus_x_preferred":[
        "\u0413\u043e\u0440\u043e\u0431\u0446\u043e\u0432\u0441\u043a\u0438\u0439"
    ],
    "name:und_x_variant":[
        "\u0413\u043e\u0440\u043e\u0431\u0446\u043e\u0432\u0441\u043a\u0438\u0439"
    ],
    "wof:name":"Gorobtsovskiy",
    "wof:placetype":"locality"
},
  "geometry": {"coordinates":[40.15667,49.40361],"type":"Point"}
}