{
  "type": "Feature",
  "properties": {
    "gn:country":"RU",
    "gn:fcode":"PPL",
    "gn:pop":3904,
    "iso:country":"RU",
    "name:ceb_x_preferred":[
        "Karamakhi"
    ],
    "name:che_x_preferred":[
        "\u041a\u0430\u0440\u0430\u043c\u0430\u0445\u0438"
    ],
    "name:eng_x_preferred":[
        "Karamakhi"
    ],
    "name:fra_x_preferred":[
        "Karamakhi"
    ],
    "name:hye_x_preferred":[
        "\u053f\u0561\u0580\u0561\u0574\u0561\u056d\u056b"
    ],
    "name:lez_x_preferred":[
        "\u041a\u0430\u0440\u0430\u043c\u0430\u0445\u0438"
    ],
    "name:nld_x_preferred":[
        "Karamakhi"
    ],
    "name:rus_x_preferred":[
        "\u041a\u0430\u0440\u0430-\u041c\u0430\u0445\u0438"
    ],
    "name:rus_x_variant":[
        "\u041a\u0430\u0440\u0430\u043c\u0430\u0445\u0438"
    ],
    "name:spa_x_preferred":[
        "Karamaji"
    ],
    "name:unk_x_variant":[
        "\u041a\u0430\u0440\u0430\u043c\u0430\u0445\u0438"
    ],
    "qs:name":"Karamakhi",
    "qs:name_adm0":"Russia",
    "qs:name_adm1":"Dagestan Republic",
    "qs:photos_9r":0,
    "qs:photos_sr":0,
    "qs:placetype":"Town",
    "qs:pop_sr":"4",
    "wd:wordcount":540,
    "wof:name":"Karamakhi",
    "wof:placetype":"locality",
    "wof:population":3904
},
  "geometry": {"coordinates":[47.26017,42.61934],"type":"Point"}
}