{
  "type": "Feature",
  "properties": {
    "gn:admin1_code":"61",
    "gn:asciiname":"Novaya Palestina",
    "gn:country_code":"RU",
    "gn:dem":46,
    "gn:feature_class":"P",
    "gn:feature_code":"PPL",
    "gn:name":"Novaya Palestina",
    "gn:population":0,
    "gn:timezone":"Europe/Moscow",
    "iso:country":"RU",
    "name:rus_x_preferred":[
        "\u041d\u043e\u0432\u0430\u044f \u041f\u0430\u043b\u0435\u0441\u0442\u0438\u043d\u0430"
    ],
    "wof:name":"Novaya Palestina",
    "wof:placetype":"locality"
},
  "geometry": {"coordinates":[41.05904,46.15051],"type":"Point"}
}