{
  "type": "Feature",
  "properties": {
    "gn:admin1_code":"38.0",
    "gn:asciiname":"Budkov",
    "gn:country_code":"RU",
    "gn:dem":223,
    "gn:feature_class":"P",
    "gn:feature_code":"PPL",
    "gn:name":"Budkov",
    "gn:population":0,
    "gn:timezone":"Europe/Moscow",
    "iso:country":"RU",
    "name:ces_x_preferred":[
        "Budkov"
    ],
    "name:fra_x_preferred":[
        "Budkov"
    ],
    "name:hun_x_preferred":[
        "Budkov"
    ],
    "name:ita_x_preferred":[
        "Budkov"
    ],
    "name:nld_x_preferred":[
        "Budkov"
    ],
    "name:rus_x_preferred":[
        "\u0411\u0443\u0442\u043a\u043e\u0432"
    ],
    "name:slk_x_preferred":[
        "Budkov"
    ],
    "name:srp_x_preferred":[
        "\u0411\u0443\u0442\u043a\u043e\u0432"
    ],
    "name:ukr_x_preferred":[
        "\u0411\u0443\u0442\u043a\u043e\u0432"
    ],
    "wof:name":"Budkov",
    "wof:placetype":"locality"
},
  "geometry": {"coordinates":[41.31167,45.11194],"type":"Point"}
}