{
  "type": "Feature",
  "properties": {
    "gn:admin1_code":"78",
    "gn:asciiname":"Kolycheva",
    "gn:country_code":"RU",
    "gn:dem":116,
    "gn:feature_class":"P",
    "gn:feature_code":"PPL",
    "gn:name":"Kolych\u00ebva",
    "gn:population":0,
    "gn:timezone":"Asia/Yekaterinburg",
    "iso:country":"RU",
    "name:rus_x_preferred":[
        "\u041a\u043e\u043b\u044b\u0447\u0451\u0432\u0430"
    ],
    "name:und_x_variant":[
        "Kolych\u00ebva",
        "\u041a\u043e\u043b\u044b\u0447\u0451\u0432\u0430"
    ],
    "wof:name":"Kolycheva",
    "wof:placetype":"locality"
},
  "geometry": {"coordinates":[67.46478,56.82694],"type":"Point"}
}