{
  "type": "Feature",
  "properties": {
    "gn:admin1_code":"90.0",
    "gn:asciiname":"Dzhigolanka",
    "gn:country_code":"RU",
    "gn:dem":290,
    "gn:feature_class":"P",
    "gn:feature_code":"PPL",
    "gn:name":"Dzhigolanka",
    "gn:population":0,
    "gn:timezone":"Asia/Yekaterinburg",
    "iso:country":"RU",
    "name:rus_x_preferred":[
        "\u0414\u0436\u0438\u0433\u043e\u043b\u0430\u043d\u043a\u0430"
    ],
    "name:und_x_variant":[
        "\u0414\u0436\u0438\u0433\u043e\u043b\u0430\u043d\u043a\u0430"
    ],
    "wof:name":"Dzhigolanka",
    "wof:placetype":"locality"
},
  "geometry": {"coordinates":[58.18333000000001,59.95],"type":"Point"}
}