{
  "type": "Feature",
  "properties": {
    "gn:admin1_code":"34",
    "gn:asciiname":"Stepanovskaya",
    "gn:country_code":"RU",
    "gn:dem":80,
    "gn:feature_class":"P",
    "gn:feature_code":"PPL",
    "gn:name":"Stepanovskaya",
    "gn:population":0,
    "gn:timezone":"Europe/Moscow",
    "iso:country":"RU",
    "name:eng_x_preferred":[
        "Stepanovskaya"
    ],
    "name:nor_x_preferred":[
        "Stepanovskaja"
    ],
    "name:rus_x_preferred":[
        "\u0421\u0442\u0435\u043f\u0430\u043d\u043e\u0432\u0441\u043a\u0430\u044f"
    ],
    "wof:name":"Stepanovskaya",
    "wof:placetype":"locality"
},
  "geometry": {"coordinates":[51.89012,64.97418],"type":"Point"}
}