{
  "type": "Feature",
  "properties": {
    "gn:admin1_code":"63",
    "gn:asciiname":"Anna-Tolono",
    "gn:country_code":"RU",
    "gn:dem":255,
    "gn:feature_class":"P",
    "gn:feature_code":"PPL",
    "gn:name":"Anna-Tolono",
    "gn:population":0,
    "gn:timezone":"Asia/Yakutsk",
    "iso:country":"RU",
    "name:eng_x_preferred":[
        "Anna-Tolono"
    ],
    "name:nor_x_preferred":[
        "Anna-Tolono"
    ],
    "name:rus_x_preferred":[
        "\u0410\u043d\u043d\u0430-\u0422\u043e\u043b\u043e\u043d\u043e"
    ],
    "wof:name":"Anna-Tolono",
    "wof:placetype":"locality"
},
  "geometry": {"coordinates":[126.25,62.08333],"type":"Point"}
}