{
  "type": "Feature",
  "properties": {
    "gn:admin1_code":"91",
    "gn:asciiname":"Ust'-Tuyeusha",
    "gn:country_code":"RU",
    "gn:dem":451,
    "gn:feature_class":"P",
    "gn:feature_code":"PPL",
    "gn:name":"Ust\u2019-Tuyeusha",
    "gn:population":0,
    "gn:timezone":"Asia/Krasnoyarsk",
    "iso:country":"RU",
    "wof:name":"Ust'-Tuyeusha",
    "wof:placetype":"locality"
},
  "geometry": {"coordinates":[96.41667,56.01667],"type":"Point"}
}