{
  "type": "Feature",
  "properties": {
    "gn:admin1_code":"7",
    "gn:asciiname":"Dianovka",
    "gn:country_code":"RU",
    "gn:dem":-22,
    "gn:feature_class":"P",
    "gn:feature_code":"PPL",
    "gn:name":"Dianovka",
    "gn:population":0,
    "gn:timezone":"Europe/Astrakhan",
    "iso:country":"RU",
    "name:rus_x_preferred":[
        "\u0414\u0438\u0430\u043d\u043e\u0432\u043a\u0430"
    ],
    "wof:name":"Dianovka",
    "wof:placetype":"locality"
},
  "geometry": {"coordinates":[48.60376,46.4208],"type":"Point"}
}