{
  "type": "Feature",
  "properties": {
    "gn:admin1_code":"53",
    "gn:asciiname":"Zamost'ye",
    "gn:country_code":"RU",
    "gn:dem":138,
    "gn:feature_class":"P",
    "gn:feature_code":"PPL",
    "gn:name":"Zamost\u2019ye",
    "gn:population":0,
    "gn:timezone":"Asia/Novosibirsk",
    "iso:country":"RU",
    "wof:name":"Zamost'ye",
    "wof:placetype":"locality"
},
  "geometry": {"coordinates":[82.90000000000001,55.76667],"type":"Point"}
}