{
  "type": "Feature",
  "properties": {
    "gn:admin1_code":"57",
    "gn:asciiname":"Kamaleyka",
    "gn:country_code":"RU",
    "gn:dem":252,
    "gn:feature_class":"P",
    "gn:feature_code":"PPL",
    "gn:name":"Kamaleyka",
    "gn:population":0,
    "gn:timezone":"Europe/Moscow",
    "iso:country":"RU",
    "name:rus_x_preferred":[
        "\u041a\u0430\u043c\u0430\u043b\u0435\u0439\u043a\u0430"
    ],
    "name:und_x_variant":[
        "\u041a\u0430\u043c\u0430\u043b\u0435\u0439\u043a\u0430"
    ],
    "wof:name":"Kamaleyka",
    "wof:placetype":"locality"
},
  "geometry": {"coordinates":[45.71667,53.46666999999999],"type":"Point"}
}