{
  "type": "Feature",
  "properties": {
    "gn:admin1_code":"4",
    "gn:asciiname":"Ust'-Shirokaya",
    "gn:country_code":"RU",
    "gn:dem":773,
    "gn:feature_class":"P",
    "gn:feature_code":"PPL",
    "gn:name":"Ust\u2019-Shirokaya",
    "gn:population":0,
    "gn:timezone":"Asia/Barnaul",
    "iso:country":"RU",
    "wof:name":"Ust'-Shirokaya",
    "wof:placetype":"locality"
},
  "geometry": {"coordinates":[85.21666999999999,51.81667],"type":"Point"}
}