{
  "type": "Feature",
  "properties": {
    "gn:admin1_code":"23",
    "gn:asciiname":"Balashevskoye",
    "gn:country_code":"RU",
    "gn:dem":5,
    "gn:feature_class":"P",
    "gn:feature_code":"PPL",
    "gn:name":"Balashevskoye",
    "gn:population":0,
    "gn:timezone":"Europe/Kaliningrad",
    "iso:country":"RU",
    "name:nor_x_preferred":[
        "Balasjevskoje"
    ],
    "name:rus_x_preferred":[
        "\u0411\u0430\u043b\u0430\u0448\u0435\u0432\u0441\u043a\u043e\u0435"
    ],
    "name:und_x_variant":[
        "Mezhdurech\u2019ye",
        "Balashevskoye"
    ],
    "wof:name":"Balashevskoye",
    "wof:placetype":"locality"
},
  "geometry": {"coordinates":[21.33472,54.62639],"type":"Point"}
}