{
  "type": "Feature",
  "properties": {
    "gn:admin1_code":"6.0",
    "gn:asciiname":"Ostrov",
    "gn:country_code":"RU",
    "gn:dem":75,
    "gn:feature_class":"P",
    "gn:feature_code":"PPL",
    "gn:name":"Ostrov",
    "gn:population":0,
    "gn:timezone":"Europe/Moscow",
    "iso:country":"RU",
    "name:bel_x_preferred":[
        "\u0412\u043e\u0441\u0442\u0440\u0430\u045e"
    ],
    "name:bul_x_preferred":[
        "\u041e\u0441\u0442\u0440\u043e\u0432"
    ],
    "name:ceb_x_preferred":[
        "Ostrov"
    ],
    "name:ces_x_preferred":[
        "Ostrov"
    ],
    "name:deu_x_preferred":[
        "Ostrov"
    ],
    "name:epo_x_preferred":[
        "Ostrov"
    ],
    "name:eus_x_preferred":[
        "Ostrov"
    ],
    "name:fin_x_preferred":[
        "Ostrov"
    ],
    "name:fra_x_preferred":[
        "Ostrov"
    ],
    "name:heb_x_preferred":[
        "\u05d0\u05d5\u05e1\u05d8\u05e8\u05d5\u05d1"
    ],
    "name:hrv_x_preferred":[
        "Ostrov"
    ],
    "name:hun_x_preferred":[
        "Ostrov"
    ],
    "name:ita_x_preferred":[
        "Ostrov"
    ],
    "name:lav_x_preferred":[
        "Ostrova"
    ],
    "name:lit_x_preferred":[
        "Ostruvas"
    ],
    "name:nld_x_preferred":[
        "Ostrov"
    ],
    "name:nor_x_preferred":[
        "Ostrov"
    ],
    "name:pol_x_preferred":[
        "Ostrov"
    ],
    "name:ron_x_preferred":[
        "Ostrov"
    ],
    "name:rue_x_preferred":[
        "\u041e\u0441\u0442\u0440\u043e\u0432"
    ],
    "name:rus_x_preferred":[
        "\u041e\u0441\u0442\u0440\u043e\u0432"
    ],
    "name:sah_x_preferred":[
        "\u0410\u0440\u044b\u044b"
    ],
    "name:sco_x_preferred":[
        "Ostrov"
    ],
    "name:slk_x_preferred":[
        "Ostrov"
    ],
    "name:spa_x_preferred":[
        "Ostrov"
    ],
    "name:srp_x_preferred":[
        "\u041e\u0441\u0442\u0440\u043e\u0432"
    ],
    "name:swe_x_preferred":[
        "Ostrov"
    ],
    "name:tgl_x_preferred":[
        "Ostrov"
    ],
    "name:ukr_x_preferred":[
        "\u041e\u0441\u0442\u0440\u0456\u0432"
    ],
    "name:zho_x_preferred":[
        "\u5967\u65af\u7279\u91cc\u592b"
    ],
    "wof:name":"Ostrov",
    "wof:placetype":"locality"
},
  "geometry": {"coordinates":[40.9714,61.674],"type":"Point"}
}