{
  "type": "Feature",
  "properties": {
    "gn:admin1_code":"20",
    "gn:asciiname":"Nizhnechirkina",
    "gn:country_code":"RU",
    "gn:dem":463,
    "gn:feature_class":"P",
    "gn:feature_code":"PPL",
    "gn:name":"Nizhnechirkina",
    "gn:population":0,
    "gn:timezone":"Asia/Irkutsk",
    "iso:country":"RU",
    "name:eng_x_preferred":[
        "Nizhnechirkina"
    ],
    "name:nor_x_preferred":[
        "Nizjnetsjirkina"
    ],
    "name:rus_x_preferred":[
        "\u041d\u0438\u0436\u043d\u0435\u0447\u0438\u0440\u043a\u0438\u043d\u0430"
    ],
    "name:und_x_variant":[
        "Nizhnecherkina",
        "Nizhneye Chirkino"
    ],
    "wof:name":"Nizhnechirkina",
    "wof:placetype":"locality"
},
  "geometry": {"coordinates":[102.1438,53.9013],"type":"Point"}
}