{
  "type": "Feature",
  "properties": {
    "gn:admin1_code":"60",
    "gn:asciiname":"Lyutskovo",
    "gn:country_code":"RU",
    "gn:dem":95,
    "gn:feature_class":"P",
    "gn:feature_code":"PPL",
    "gn:name":"Lyutskovo",
    "gn:population":0,
    "gn:timezone":"Europe/Moscow",
    "iso:country":"RU",
    "name:rus_x_preferred":[
        "\u041b\u044e\u0434\u0441\u043a\u043e\u0435"
    ],
    "name:rus_x_variant":[
        "\u041b\u044e\u0446\u043a\u043e\u0432\u043e"
    ],
    "name:und_x_variant":[
        "Lyudskoye"
    ],
    "wof:name":"Lyutskovo",
    "wof:placetype":"locality"
},
  "geometry": {"coordinates":[28.50374,56.73624],"type":"Point"}
}