{
  "type": "Feature",
  "properties": {
    "gn:admin1_code":"73",
    "gn:asciiname":"Usayevo",
    "gn:country_code":"RU",
    "gn:dem":188,
    "gn:feature_class":"P",
    "gn:feature_code":"PPL",
    "gn:name":"Usayevo",
    "gn:population":0,
    "gn:timezone":"Europe/Moscow",
    "iso:country":"RU",
    "name:rus_x_preferred":[
        "\u0423\u0441\u0430\u0435\u0432\u043e"
    ],
    "name:und_x_variant":[
        "\u0423\u0441\u0430\u0435\u0432\u043e"
    ],
    "wof:name":"Usayevo",
    "wof:placetype":"locality"
},
  "geometry": {"coordinates":[52.4155,55.3793],"type":"Point"}
}