{
  "type": "Feature",
  "properties": {
    "gn:admin1_code":"44",
    "gn:asciiname":"Beringa",
    "gn:country_code":"RU",
    "gn:dem":-9999,
    "gn:feature_class":"P",
    "gn:feature_code":"PPL",
    "gn:name":"Beringa",
    "gn:population":0,
    "gn:timezone":"Asia/Magadan",
    "iso:country":"RU",
    "name:nor_x_preferred":[
        "Beringa"
    ],
    "name:rus_x_preferred":[
        "\u0411\u0435\u0440\u0438\u043d\u0433\u0430"
    ],
    "wof:name":"Beringa",
    "wof:placetype":"locality"
},
  "geometry": {"coordinates":[149.05916999999999,59.20056],"type":"Point"}
}