{
  "type": "Feature",
  "properties": {
    "gn:admin1_code":"85.0",
    "gn:asciiname":"Pirozhkovo",
    "gn:country_code":"RU",
    "gn:dem":181,
    "gn:feature_class":"P",
    "gn:feature_code":"PPL",
    "gn:name":"Pirozhkovo",
    "gn:population":0,
    "gn:timezone":"Europe/Moscow",
    "iso:country":"RU",
    "name:rus_x_preferred":[
        "\u041f\u0438\u0440\u043e\u0436\u043a\u043e\u0432\u043e"
    ],
    "name:und_x_variant":[
        "\u041f\u0438\u0440\u043e\u0436\u043a\u043e\u0432\u043e"
    ],
    "wof:name":"Pirozhkovo",
    "wof:placetype":"locality"
},
  "geometry": {"coordinates":[40.34106,58.78784],"type":"Point"}
}