{
  "type": "Feature",
  "properties": {
    "gn:admin1_code":"60.0",
    "gn:asciiname":"Bor Bolonev",
    "gn:country_code":"RU",
    "gn:dem":100,
    "gn:feature_class":"P",
    "gn:feature_code":"PPL",
    "gn:name":"Bor Bolon\u00ebv",
    "gn:population":0,
    "gn:timezone":"Europe/Moscow",
    "iso:country":"RU",
    "name:rus_x_preferred":[
        "\u0411\u043e\u0440 \u0411\u043e\u043b\u043e\u043d\u0451\u0432"
    ],
    "name:und_x_variant":[
        "Bor Bolonov",
        "Bor Bolon\u00ebv",
        "\u0411\u043e\u0440 \u0411\u043e\u043b\u043e\u043d\u0451\u0432"
    ],
    "wof:name":"Bor Bolonev",
    "wof:placetype":"locality"
},
  "geometry": {"coordinates":[30.65185,56.73226999999999],"type":"Point"}
}