{
  "type": "Feature",
  "properties": {
    "gn:admin1_code":"60",
    "gn:asciiname":"Ivakhino",
    "gn:country_code":"RU",
    "gn:dem":56,
    "gn:feature_class":"P",
    "gn:feature_code":"PPL",
    "gn:name":"Ivakhino",
    "gn:population":0,
    "gn:timezone":"Europe/Moscow",
    "iso:country":"RU",
    "name:rus_x_preferred":[
        "\u0418\u0432\u0430\u0445\u0438\u043d\u043e"
    ],
    "wof:name":"Ivakhino",
    "wof:placetype":"locality"
},
  "geometry": {"coordinates":[28.18208,57.41095],"type":"Point"}
}