{
  "type": "Feature",
  "properties": {
    "gn:admin1_code":"25",
    "gn:asciiname":"Nosykino",
    "gn:country_code":"RU",
    "gn:dem":187,
    "gn:feature_class":"P",
    "gn:feature_code":"PPL",
    "gn:name":"Nosykino",
    "gn:population":0,
    "gn:timezone":"Europe/Moscow",
    "iso:country":"RU",
    "name:nor_x_preferred":[
        "Nosykino"
    ],
    "name:rus_x_preferred":[
        "\u041d\u043e\u0441\u044b\u043a\u0438\u043d\u043e"
    ],
    "wof:name":"Nosykino",
    "wof:placetype":"locality"
},
  "geometry": {"coordinates":[36.05986,54.83266999999999],"type":"Point"}
}