{
  "type": "Feature",
  "properties": {
    "gn:admin1_code":"23",
    "gn:asciiname":"Belyy Yar",
    "gn:country_code":"RU",
    "gn:dem":19,
    "gn:feature_class":"P",
    "gn:feature_code":"PPL",
    "gn:name":"Belyy Yar",
    "gn:population":0,
    "gn:timezone":"Europe/Kaliningrad",
    "iso:country":"RU",
    "name:nor_x_preferred":[
        "Belyj Jar"
    ],
    "name:rus_x_preferred":[
        "\u0411\u0435\u043b\u044b\u0439 \u042f\u0440"
    ],
    "wof:name":"Belyy Yar",
    "wof:placetype":"locality"
},
  "geometry": {"coordinates":[21.25167,54.5125],"type":"Point"}
}