{
  "type": "Feature",
  "properties": {
    "gn:admin1_code":"20",
    "gn:asciiname":"Makarovskaya",
    "gn:country_code":"RU",
    "gn:dem":415,
    "gn:feature_class":"P",
    "gn:feature_code":"PPL",
    "gn:name":"Makarovskaya",
    "gn:population":0,
    "gn:timezone":"Asia/Irkutsk",
    "iso:country":"RU",
    "name:rus_x_preferred":[
        "\u041c\u0430\u043a\u0430\u0440\u043e\u0432\u0441\u043a\u0430\u044f"
    ],
    "wof:name":"Makarovskaya",
    "wof:placetype":"locality"
},
  "geometry": {"coordinates":[103.4692,53.1909],"type":"Point"}
}