{
  "type": "Feature",
  "properties": {
    "gn:admin1_code":"77",
    "gn:asciiname":"Iverovskoye",
    "gn:country_code":"RU",
    "gn:dem":183,
    "gn:feature_class":"P",
    "gn:feature_code":"PPL",
    "gn:name":"Iverovskoye",
    "gn:population":0,
    "gn:timezone":"Europe/Moscow",
    "iso:country":"RU",
    "name:nor_x_preferred":[
        "Iverovskoje"
    ],
    "name:rus_x_preferred":[
        "\u0418\u0432\u0435\u0440\u043e\u0432\u0441\u043a\u043e\u0435"
    ],
    "wof:name":"Iverovskoye",
    "wof:placetype":"locality"
},
  "geometry": {"coordinates":[35.01953,56.60243000000001],"type":"Point"}
}