{
  "type": "Feature",
  "properties": {
    "gn:admin1_code":"41.0",
    "gn:asciiname":"Chernyy Olekh",
    "gn:country_code":"RU",
    "gn:dem":158,
    "gn:feature_class":"P",
    "gn:feature_code":"PPL",
    "gn:name":"Ch\u00ebrnyy Olekh",
    "gn:population":0,
    "gn:timezone":"Europe/Moscow",
    "iso:country":"RU",
    "name:rus_x_preferred":[
        "\u0427\u0451\u0440\u043d\u044b\u0439 \u041e\u043b\u0435\u0445"
    ],
    "name:und_x_variant":[
        "Cherno-Olekh",
        "Cherno-Oleg",
        "Ch\u00ebrnyy Olekh",
        "\u0427\u0451\u0440\u043d\u044b\u0439 \u041e\u043b\u0435\u0445"
    ],
    "wof:name":"Chernyy Olekh",
    "wof:placetype":"locality"
},
  "geometry": {"coordinates":[35.5194,51.1896],"type":"Point"}
}