{
  "type": "Feature",
  "properties": {
    "gn:admin1_code":"34",
    "gn:asciiname":"Pomozdino",
    "gn:country_code":"RU",
    "gn:dem":118,
    "gn:feature_class":"P",
    "gn:feature_code":"PPL",
    "gn:name":"Pomozdino",
    "gn:population":0,
    "gn:timezone":"Europe/Moscow",
    "iso:country":"RU",
    "name:eng_x_preferred":[
        "Pomozdino"
    ],
    "name:nor_x_preferred":[
        "Pomozdino"
    ],
    "name:rus_x_preferred":[
        "\u041f\u043e\u043c\u043e\u0437\u0434\u0438\u043d\u043e"
    ],
    "name:und_x_variant":[
        "\u041f\u043e\u043c\u043e\u0437\u0434\u0438\u043d\u043e",
        "Pomozdino"
    ],
    "wof:name":"Pomozdino",
    "wof:placetype":"locality"
},
  "geometry": {"coordinates":[54.1873,62.19551],"type":"Point"}
}