{
  "type": "Feature",
  "properties": {
    "gn:admin1_code":"45.0",
    "gn:asciiname":"Yankeyevo",
    "gn:country_code":"RU",
    "gn:dem":167,
    "gn:feature_class":"P",
    "gn:feature_code":"PPL",
    "gn:name":"Yankeyevo",
    "gn:population":0,
    "gn:timezone":"Europe/Moscow",
    "iso:country":"RU",
    "name:rus_x_preferred":[
        "\u042f\u043d\u043a\u0435\u0435\u0432\u043e"
    ],
    "wof:name":"Yankeyevo",
    "wof:placetype":"locality"
},
  "geometry": {"coordinates":[48.59139,56.84333],"type":"Point"}
}