{
  "type": "Feature",
  "properties": {
    "gn:admin1_code":"90",
    "gn:asciiname":"Tatarskaya Shishmara",
    "gn:country_code":"RU",
    "gn:dem":171,
    "gn:feature_class":"P",
    "gn:feature_code":"PPL",
    "gn:name":"Tatarskaya Shishmara",
    "gn:population":0,
    "gn:timezone":"Asia/Yekaterinburg",
    "iso:country":"RU",
    "name:eng_x_preferred":[
        "Tatarskaya Shishmara"
    ],
    "name:nor_x_preferred":[
        "Tat.Sjisjmara"
    ],
    "name:rus_x_preferred":[
        "\u0422\u0430\u0442.\u0428\u0438\u0448\u043c\u0430\u0440\u0430"
    ],
    "name:und_x_variant":[
        "Shishmara",
        "Tatarskaya Shishmara"
    ],
    "wof:name":"Tatarskaya Shishmara",
    "wof:placetype":"locality"
},
  "geometry": {"coordinates":[56.4077,57.17609],"type":"Point"}
}