{
  "type": "Feature",
  "properties": {
    "gn:admin1_code":"6",
    "gn:asciiname":"Gusino",
    "gn:country_code":"RU",
    "gn:dem":167,
    "gn:feature_class":"P",
    "gn:feature_code":"PPL",
    "gn:name":"Gusino",
    "gn:population":0,
    "gn:timezone":"Europe/Moscow",
    "iso:country":"RU",
    "name:eng_x_preferred":[
        "Gusino"
    ],
    "name:nor_x_preferred":[
        "Gusino"
    ],
    "name:rus_x_preferred":[
        "\u0413\u0443\u0441\u0438\u043d\u043e"
    ],
    "wof:name":"Gusino",
    "wof:placetype":"locality"
},
  "geometry": {"coordinates":[47.45,61.88333000000001],"type":"Point"}
}