{
  "type": "Feature",
  "properties": {
    "gn:admin1_code":"80",
    "gn:asciiname":"Sannikovo",
    "gn:country_code":"RU",
    "gn:dem":164,
    "gn:feature_class":"P",
    "gn:feature_code":"PPL",
    "gn:name":"Sannikovo",
    "gn:population":0,
    "gn:timezone":"Europe/Samara",
    "iso:country":"RU",
    "name:eng_x_preferred":[
        "Sannikovo"
    ],
    "name:nor_x_preferred":[
        "Sannikovo"
    ],
    "name:rus_x_preferred":[
        "\u0421\u0430\u043d\u043d\u0438\u043a\u043e\u0432\u043e"
    ],
    "name:und_x_variant":[
        "\u0421\u0430\u043d\u043d\u0438\u043a\u043e\u0432\u043e",
        "Sannikovo"
    ],
    "wof:name":"Sannikovo",
    "wof:placetype":"locality"
},
  "geometry": {"coordinates":[52.18543,56.23174],"type":"Point"}
}