{
  "type": "Feature",
  "properties": {
    "gn:admin1_code":"11",
    "gn:asciiname":"Dodo-Ichetuy",
    "gn:country_code":"RU",
    "gn:dem":688,
    "gn:feature_class":"P",
    "gn:feature_code":"PPL",
    "gn:name":"Dodo-Ichetuy",
    "gn:population":0,
    "gn:timezone":"Asia/Irkutsk",
    "iso:country":"RU",
    "name:eng_x_preferred":[
        "Dodo-Ichetuy"
    ],
    "name:nor_x_preferred":[
        "Dodo-Itsjetuj"
    ],
    "name:rus_x_preferred":[
        "\u0414\u043e\u0434\u043e-\u0418\u0447\u0435\u0442\u0443\u0439"
    ],
    "name:und_x_variant":[
        "Novyye Ichety",
        "Bulun Ichety",
        "Nov Ichet\u00f6",
        "Ichetuy",
        "Igotoiskaya",
        "Ichetuyskiy"
    ],
    "wof:name":"Dodo-Ichetuy",
    "wof:placetype":"locality"
},
  "geometry": {"coordinates":[105.45820000000001,50.6365],"type":"Point"}
}