{
  "type": "Feature",
  "properties": {
    "gn:admin1_code":"15",
    "gn:asciiname":"Il'muv'ye",
    "gn:country_code":"RU",
    "gn:dem":4,
    "gn:feature_class":"P",
    "gn:feature_code":"PPL",
    "gn:name":"Il\u2019muv\u2019ye",
    "gn:population":0,
    "gn:timezone":"Asia/Anadyr",
    "iso:country":"RU",
    "name:rus_x_preferred":[
        "\u0418\u043b\u044c\u043c\u0443\u0432\u044c\u0435"
    ],
    "name:und_x_variant":[
        "Ilmurye",
        "Ilmuvge",
        "Il\u2019muv\u2019ye",
        "\u0418\u043b\u044c\u043c\u0443\u0432\u044c\u0435"
    ],
    "wof:name":"Il'muv'ye",
    "wof:placetype":"locality"
},
  "geometry": {"coordinates":[173.98471000000001,64.94426999999999],"type":"Point"}
}