{
  "type": "Feature",
  "properties": {
    "gn:admin1_code":"61.0",
    "gn:asciiname":"Bobrov",
    "gn:country_code":"RU",
    "gn:dem":182,
    "gn:feature_class":"P",
    "gn:feature_code":"PPL",
    "gn:name":"Bobrov",
    "gn:population":0,
    "gn:timezone":"Europe/Moscow",
    "iso:country":"RU",
    "name:bel_x_preferred":[
        "\u0411\u0430\u0431\u0440\u043e\u045e"
    ],
    "name:cat_x_preferred":[
        "Bobrov"
    ],
    "name:ceb_x_preferred":[
        "Bobrov"
    ],
    "name:deu_x_preferred":[
        "Bobrov"
    ],
    "name:fra_x_preferred":[
        "Bobrov"
    ],
    "name:hun_x_preferred":[
        "Bobrov"
    ],
    "name:ita_x_preferred":[
        "Bobrov"
    ],
    "name:kor_x_preferred":[
        "\ubcf4\ube0c\ub85c\ud504"
    ],
    "name:pih_x_preferred":[
        "Bobrov"
    ],
    "name:por_x_preferred":[
        "Bobrov"
    ],
    "name:ron_x_preferred":[
        "Bobrov"
    ],
    "name:rus_x_preferred":[
        "\u0411\u043e\u0431\u0440\u043e\u0432"
    ],
    "name:slv_x_preferred":[
        "Bobrov"
    ],
    "name:spa_x_preferred":[
        "Bobrov"
    ],
    "name:srp_x_preferred":[
        "\u0411\u043e\u0431\u0440\u043e\u0432"
    ],
    "name:ukr_x_preferred":[
        "\u0411\u043e\u0431\u0440\u043e\u0432"
    ],
    "wof:name":"Bobrov",
    "wof:placetype":"locality"
},
  "geometry": {"coordinates":[39.82293,47.97532],"type":"Point"}
}