{
  "type": "Feature",
  "properties": {
    "gn:admin1_code":"90",
    "gn:asciiname":"Mosino",
    "gn:country_code":"RU",
    "gn:dem":244,
    "gn:feature_class":"P",
    "gn:feature_code":"PPL",
    "gn:name":"Mosino",
    "gn:population":0,
    "gn:timezone":"Asia/Yekaterinburg",
    "iso:country":"RU",
    "name:nor_x_preferred":[
        "Mosino"
    ],
    "name:rus_x_preferred":[
        "\u041c\u043e\u0441\u0438\u043d\u043e"
    ],
    "wof:name":"Mosino",
    "wof:placetype":"locality"
},
  "geometry": {"coordinates":[56.81667,58.68333000000001],"type":"Point"}
}