{
  "type": "Feature",
  "properties": {
    "gn:admin1_code":"05",
    "gn:asciiname":"Fevral'sk",
    "gn:country_code":"RU",
    "gn:dem":282,
    "gn:feature_class":"P",
    "gn:feature_code":"PPL",
    "gn:name":"Fevral\u2019sk",
    "gn:population":0,
    "gn:timezone":"Asia/Yakutsk",
    "iso:country":"RU",
    "name:eng_x_preferred":[
        "Fevral'sk"
    ],
    "name:rus_x_preferred":[
        "\u0424\u0435\u0432\u0440\u0430\u043b\u044c\u0441\u043a\u043e\u0435"
    ],
    "name:rus_x_variant":[
        "\u0424\u0435\u0432\u0440\u0430\u043b\u044c\u0441\u043a"
    ],
    "name:und_x_variant":[
        "Fevral\u2019skiy",
        "Fevralskiv",
        "Fevral\u2019skoye",
        "Fevral\u2019sk",
        "\u0424\u0435\u0432\u0440\u0430\u043b\u044c\u0441\u043a"
    ],
    "wof:name":"Fevral'sk",
    "wof:placetype":"locality"
},
  "geometry": {"coordinates":[130.87593000000001,52.45506999999999],"type":"Point"}
}