{
  "type": "Feature",
  "properties": {
    "gn:admin1_code":"15",
    "gn:asciiname":"Komsomol'skiy",
    "gn:country_code":"RU",
    "gn:dem":174,
    "gn:feature_class":"P",
    "gn:feature_code":"PPL",
    "gn:name":"Komsomol\u2019skiy",
    "gn:population":0,
    "gn:timezone":"Asia/Anadyr",
    "iso:country":"RU",
    "name:eng_x_preferred":[
        "Komsomol'skiy"
    ],
    "name:nor_x_preferred":[
        "Komsomolskij"
    ],
    "name:rus_x_preferred":[
        "\u041a\u043e\u043c\u0441\u043e\u043c\u043e\u043b\u044c\u0441\u043a\u0438\u0439"
    ],
    "name:und_x_variant":[
        "Komsomol\u2019skiy",
        "\u041a\u043e\u043c\u0441\u043e\u043c\u043e\u043b\u044c\u0441\u043a\u0438\u0439"
    ],
    "wof:name":"Komsomol'skiy",
    "wof:placetype":"locality"
},
  "geometry": {"coordinates":[172.74368000000001,69.13175],"type":"Point"}
}