{
  "type": "Feature",
  "properties": {
    "gn:admin1_code":"15",
    "gn:asciiname":"Komsomol'skiy",
    "gn:country_code":"RU",
    "gn:dem":174,
    "gn:feature_class":"P",
    "gn:feature_code":"PPL",
    "gn:name":"Komsomol\u2019skiy",
    "gn:population":0,
    "gn:timezone":"Asia/Anadyr",
    "iso:country":"RU",
    "name:che_x_preferred":[
        "\u041a\u043e\u043c\u0441\u043e\u043c\u043e\u043b\u044c\u0441\u043a\u0438\u0439"
    ],
    "name:eng_x_preferred":[
        "Komsomol'skiy"
    ],
    "name:hye_x_preferred":[
        "\u053f\u0578\u0574\u057d\u0578\u0574\u0578\u056c\u057d\u056f\u056b"
    ],
    "name:nld_x_preferred":[
        "Komsomolski"
    ],
    "name:nor_x_preferred":[
        "Komsomolskij"
    ],
    "name:rus_x_preferred":[
        "\u041a\u043e\u043c\u0441\u043e\u043c\u043e\u043b\u044c\u0441\u043a\u0438\u0439"
    ],
    "name:ukr_x_preferred":[
        "\u041a\u043e\u043c\u0441\u043e\u043c\u043e\u043b\u044c\u0441\u044c\u043a\u0438\u0439"
    ],
    "name:und_x_variant":[
        "Komsomol\u2019skiy",
        "\u041a\u043e\u043c\u0441\u043e\u043c\u043e\u043b\u044c\u0441\u043a\u0438\u0439"
    ],
    "name:urd_x_preferred":[
        "\u06a9\u0648\u0645\u0633\u0648\u0645\u0648\u0644\u0633\u06a9\u06cc"
    ],
    "name:war_x_preferred":[
        "Komsomolsky"
    ],
    "name:zho_x_preferred":[
        "\u5171\u9752\u57ce"
    ],
    "wof:name":"Komsomol'skiy",
    "wof:placetype":"locality"
},
  "geometry": {"coordinates":[172.74368000000001,69.13175],"type":"Point"}
}