{
  "type": "Feature",
  "properties": {
    "gn:admin1_code":"42",
    "gn:asciiname":"Shushino",
    "gn:country_code":"RU",
    "gn:dem":32,
    "gn:feature_class":"P",
    "gn:feature_code":"PPL",
    "gn:name":"Shushino",
    "gn:population":0,
    "gn:timezone":"Europe/Moscow",
    "iso:country":"RU",
    "name:fin_x_preferred":[
        "Sylij\u00e4rvi"
    ],
    "name:rus_x_preferred":[
        "\u0428\u0443\u0448\u0438\u043d\u043e"
    ],
    "name:und_x_variant":[
        "Khyunninen",
        "Shushino"
    ],
    "wof:name":"Shushino",
    "wof:placetype":"locality"
},
  "geometry": {"coordinates":[29.75566,61.05085],"type":"Point"}
}