{
  "type": "Feature",
  "properties": {
    "gn:admin1_code":"41.0",
    "gn:asciiname":"Sel'skiy Rogachik",
    "gn:country_code":"RU",
    "gn:dem":179,
    "gn:feature_class":"P",
    "gn:feature_code":"PPL",
    "gn:name":"Sel\u2019skiy Rogachik",
    "gn:population":0,
    "gn:timezone":"Europe/Moscow",
    "iso:country":"RU",
    "name:rus_x_preferred":[
        "\u0421\u0435\u043b\u044c\u0441\u043a\u0438\u0439 \u0420\u043e\u0433\u0430\u0447\u0438\u043a"
    ],
    "name:und_x_variant":[
        "Sel\u2019skiy Rogachik"
    ],
    "wof:name":"Sel'skiy Rogachik",
    "wof:placetype":"locality"
},
  "geometry": {"coordinates":[37.2631,51.8004],"type":"Point"}
}