{
  "type": "Feature",
  "properties": {
    "gn:admin1_code":"80",
    "gn:asciiname":"Shashur",
    "gn:country_code":"RU",
    "gn:dem":214,
    "gn:feature_class":"P",
    "gn:feature_code":"PPL",
    "gn:name":"Shashur",
    "gn:population":0,
    "gn:timezone":"Europe/Samara",
    "iso:country":"RU",
    "name:rus_x_preferred":[
        "\u0428\u0430\u0448\u0443\u0440"
    ],
    "wof:name":"Shashur",
    "wof:placetype":"locality"
},
  "geometry": {"coordinates":[52.78333000000001,56.86666999999999],"type":"Point"}
}