{
  "type": "Feature",
  "properties": {
    "gn:admin1_code":"55",
    "gn:asciiname":"Sagarchin",
    "gn:country_code":"RU",
    "gn:dem":141,
    "gn:feature_class":"P",
    "gn:feature_code":"PPL",
    "gn:name":"Sagarchin",
    "gn:population":0,
    "gn:timezone":"Asia/Yekaterinburg",
    "iso:country":"RU",
    "name:eng_x_preferred":[
        "Sagarchin"
    ],
    "name:nor_x_preferred":[
        "Sagartsjin"
    ],
    "name:rus_x_preferred":[
        "\u0421\u0430\u0433\u0430\u0440\u0447\u0438\u043d"
    ],
    "name:und_x_variant":[
        "Sagarchi",
        "\u0421\u0430\u0433\u0430\u0440\u0447\u0438\u043d",
        "Sagarchin"
    ],
    "wof:name":"Sagarchin",
    "wof:placetype":"locality"
},
  "geometry": {"coordinates":[55.91058,50.90254],"type":"Point"}
}