{
  "type": "Feature",
  "properties": {
    "gn:admin1_code":"77",
    "gn:asciiname":"Podsosen'ye",
    "gn:country_code":"RU",
    "gn:dem":200,
    "gn:feature_class":"P",
    "gn:feature_code":"PPL",
    "gn:name":"Podsosen\u2019ye",
    "gn:population":0,
    "gn:timezone":"Europe/Moscow",
    "iso:country":"RU",
    "name:rus_x_preferred":[
        "\u041f\u043e\u0434\u0441\u043e\u0441\u0435\u043d\u044c\u0435"
    ],
    "name:und_x_variant":[
        "Podsoson\u2019ye",
        "Podsosen\u2019ye"
    ],
    "wof:name":"Podsosen'ye",
    "wof:placetype":"locality"
},
  "geometry": {"coordinates":[31.81512,56.41118],"type":"Point"}
}