{
  "type": "Feature",
  "properties": {
    "gn:admin1_code":"55",
    "gn:asciiname":"Koltubanka",
    "gn:country_code":"RU",
    "gn:dem":83,
    "gn:feature_class":"P",
    "gn:feature_code":"PPL",
    "gn:name":"Koltubanka",
    "gn:population":0,
    "gn:timezone":"Asia/Yekaterinburg",
    "iso:country":"RU",
    "name:eng_x_preferred":[
        "Koltubanka"
    ],
    "name:nor_x_preferred":[
        "Koltubajka"
    ],
    "name:rus_x_preferred":[
        "\u041a\u043e\u043b\u0442\u0443\u0431\u0430\u0439\u043a\u0430"
    ],
    "name:rus_x_variant":[
        "\u041a\u043e\u043b\u0442\u0443\u0431\u0430\u043d\u043a\u0430"
    ],
    "wof:name":"Koltubanka",
    "wof:placetype":"locality"
},
  "geometry": {"coordinates":[51.911,52.933],"type":"Point"}
}