{
  "type": "Feature",
  "properties": {
    "gn:country":"RU",
    "gn:fcode":"PPL",
    "gn:population":0,
    "iso:country":"RU",
    "name:eng_x_preferred":[
        "Sonskiy"
    ],
    "name:nor_x_preferred":[
        "Sonskij"
    ],
    "name:rus_x_preferred":[
        "\u0421\u043e\u043d\u0441\u043a\u0438\u0439"
    ],
    "name:und_x_variant":[
        "Son"
    ],
    "qs:name":"Sonskiy",
    "qs:name_adm0":"Russia",
    "qs:name_adm1":"Khakassia Republic",
    "qs:photos_9r":0,
    "qs:photos_sr":0,
    "qs:placetype":"Town",
    "qs:pop_sr":"3",
    "wof:name":"Sonskiy",
    "wof:placetype":"locality",
    "wof:population":0
},
  "geometry": {"coordinates":[90.21333,54.17861],"type":"Point"}
}