{
  "type": "Feature",
  "properties": {
    "gn:admin1_code":"85",
    "gn:asciiname":"Legitovo",
    "gn:country_code":"RU",
    "gn:dem":155,
    "gn:feature_class":"P",
    "gn:feature_code":"PPL",
    "gn:name":"Legitovo",
    "gn:population":0,
    "gn:timezone":"Europe/Moscow",
    "iso:country":"RU",
    "name:eng_x_preferred":[
        "Legitovo"
    ],
    "name:nor_x_preferred":[
        "Legitovo"
    ],
    "name:rus_x_preferred":[
        "\u041b\u0435\u0433\u0438\u0442\u043e\u0432\u043e"
    ],
    "name:und_x_variant":[
        "\u041b\u0435\u0433\u0438\u0442\u043e\u0432\u043e",
        "Legitovo"
    ],
    "wof:name":"Legitovo",
    "wof:placetype":"locality"
},
  "geometry": {"coordinates":[43.96617,59.38258],"type":"Point"}
}