{
  "type": "Feature",
  "properties": {
    "gn:admin1_code":"25",
    "gn:asciiname":"Mamonovo",
    "gn:country_code":"RU",
    "gn:dem":192,
    "gn:feature_class":"P",
    "gn:feature_code":"PPL",
    "gn:name":"Mamonovo",
    "gn:population":0,
    "gn:timezone":"Europe/Moscow",
    "iso:country":"RU",
    "name:rus_x_preferred":[
        "\u041c\u0430\u043c\u043e\u043d\u043e\u0432\u043e"
    ],
    "name:und_x_variant":[
        "Mamonova",
        "Mamonovo",
        "\u041c\u0430\u043c\u043e\u043d\u043e\u0432\u043e"
    ],
    "wof:name":"Mamonovo",
    "wof:placetype":"locality"
},
  "geometry": {"coordinates":[35.54972,54.89972],"type":"Point"}
}