{
  "type": "Feature",
  "properties": {
    "gn:admin1_code":"77",
    "gn:asciiname":"Nikulina Gora",
    "gn:country_code":"RU",
    "gn:dem":157,
    "gn:feature_class":"P",
    "gn:feature_code":"PPL",
    "gn:name":"Nikulina Gora",
    "gn:population":0,
    "gn:timezone":"Europe/Moscow",
    "iso:country":"RU",
    "name:rus_x_preferred":[
        "\u041d\u0438\u043a\u0443\u043b\u0438\u043d\u0430 \u0413\u043e\u0440\u0430"
    ],
    "name:und_x_variant":[
        "Mikulina Gora",
        "Nikulina Gora",
        "\u041d\u0438\u043a\u0443\u043b\u0438\u043d\u0430 \u0413\u043e\u0440\u0430"
    ],
    "wof:name":"Nikulina Gora",
    "wof:placetype":"locality"
},
  "geometry": {"coordinates":[35.5853,57.131],"type":"Point"}
}