{
  "type": "Feature",
  "properties": {
    "gn:admin1_code":"16",
    "gn:asciiname":"Simekeykasy",
    "gn:country_code":"RU",
    "gn:dem":98,
    "gn:feature_class":"P",
    "gn:feature_code":"PPL",
    "gn:name":"Simekeykasy",
    "gn:population":0,
    "gn:timezone":"Europe/Moscow",
    "iso:country":"RU",
    "name:rus_x_preferred":[
        "\u0421\u0438\u043c\u0435\u043a\u0435\u0439\u043a\u0430\u0441\u044b"
    ],
    "name:und_x_variant":[
        "Semikey-Kasy",
        "Simekeykasy"
    ],
    "wof:name":"Simekeykasy",
    "wof:placetype":"locality"
},
  "geometry": {"coordinates":[46.44801,55.84127],"type":"Point"}
}