{
  "type": "Feature",
  "properties": {
    "gn:admin1_code":"77",
    "gn:asciiname":"Sokerino",
    "gn:country_code":"RU",
    "gn:dem":145,
    "gn:feature_class":"P",
    "gn:feature_code":"PPL",
    "gn:name":"Sokerino",
    "gn:population":0,
    "gn:timezone":"Europe/Moscow",
    "iso:country":"RU",
    "name:rus_x_preferred":[
        "\u0421\u043e\u043a\u0435\u0440\u0438\u043d\u043e"
    ],
    "wof:name":"Sokerino",
    "wof:placetype":"locality"
},
  "geometry": {"coordinates":[36.0114,58.1553],"type":"Point"}
}