{
  "type": "Feature",
  "properties": {
    "gn:admin1_code":"53",
    "gn:asciiname":"Mikhaylovka",
    "gn:country_code":"RU",
    "gn:dem":108,
    "gn:feature_class":"P",
    "gn:feature_code":"PPL",
    "gn:name":"Mikhaylovka",
    "gn:population":0,
    "gn:timezone":"Asia/Novosibirsk",
    "iso:country":"RU",
    "name:ben_x_preferred":[
        "\u09ae\u09bf\u0996\u09be\u0987\u09b2\u09cb\u09ad\u0995\u09be"
    ],
    "name:ceb_x_preferred":[
        "Mikhaylovka"
    ],
    "name:ell_x_preferred":[
        "\u039c\u03b9\u03c7\u03b1\u03b9\u03bb\u03bf\u03b2\u03ba\u03b1"
    ],
    "name:eng_x_preferred":[
        "Mikhaylovka"
    ],
    "name:heb_x_preferred":[
        "\u05de\u05d9\u05db\u05d0\u05d9\u05dc\u05d5\u05d1\u05e7\u05d4"
    ],
    "name:hin_x_preferred":[
        "\u092e\u093f\u0916\u093e\u092f\u0932\u094b\u0935\u094d\u0915\u093e"
    ],
    "name:ind_x_preferred":[
        "Mikhaylovka"
    ],
    "name:kor_x_preferred":[
        "\ubbf8\ud558\uc77c\ub85c\ud504\uce74"
    ],
    "name:nor_x_preferred":[
        "Mikhajlovka"
    ],
    "name:rus_x_preferred":[
        "\u041c\u0438\u0445\u0430\u0439\u043b\u043e\u0432\u043a\u0430"
    ],
    "name:spa_x_preferred":[
        "Mikhaylovka"
    ],
    "name:swe_x_preferred":[
        "Mikhaylovka"
    ],
    "name:ukr_x_preferred":[
        "\u041c\u0438\u0445\u0430\u0439\u043b\u043e\u0432\u043a\u0430"
    ],
    "name:urd_x_preferred":[
        "\u0645\u06cc\u06a9\u06be\u0627\u0626\u06d2\u0644\u0648\u06a9\u0627"
    ],
    "name:vie_x_preferred":[
        "Mikhaylovka"
    ],
    "wof:name":"Mikhaylovka",
    "wof:placetype":"locality"
},
  "geometry": {"coordinates":[78.56319999999999,54.56666],"type":"Point"}
}