{
  "type": "Feature",
  "properties": {
    "gn:admin1_code":"55",
    "gn:asciiname":"Novosel'noye",
    "gn:country_code":"RU",
    "gn:dem":89,
    "gn:feature_class":"P",
    "gn:feature_code":"PPL",
    "gn:name":"Novosel\u2019noye",
    "gn:population":0,
    "gn:timezone":"Asia/Yekaterinburg",
    "iso:country":"RU",
    "name:rus_x_preferred":[
        "\u041d\u043e\u0432\u043e\u0441\u0435\u043b\u044c\u043d\u043e\u0435"
    ],
    "name:und_x_variant":[
        "Novosel\u2019nyy",
        "Novosel\u2019noye",
        "\u041d\u043e\u0432\u043e\u0441\u0435\u043b\u044c\u043d\u043e\u0435"
    ],
    "wof:name":"Novosel'noye",
    "wof:placetype":"locality"
},
  "geometry": {"coordinates":[52.75731,51.9437],"type":"Point"}
}