{
  "type": "Feature",
  "properties": {
    "gn:admin1_code":"10",
    "gn:asciiname":"Mirnyy",
    "gn:country_code":"RU",
    "gn:dem":175,
    "gn:feature_class":"P",
    "gn:feature_code":"PPL",
    "gn:name":"Mirnyy",
    "gn:population":0,
    "gn:timezone":"Europe/Moscow",
    "iso:country":"RU",
    "name:ben_x_preferred":[
        "\u09ae\u09bf\u09b0\u09a8\u09bf"
    ],
    "name:ell_x_preferred":[
        "\u039c\u03af\u03c1\u03bd\u03b9"
    ],
    "name:hin_x_preferred":[
        "\u092e\u093f\u0930\u0928\u0940"
    ],
    "name:rus_x_preferred":[
        "\u041c\u0438\u0440\u043d\u044b\u0439"
    ],
    "name:und_x_variant":[
        "Zhvaki",
        "Mirnyy"
    ],
    "wof:name":"Mirnyy",
    "wof:placetype":"locality"
},
  "geometry": {"coordinates":[32.98864,52.44556],"type":"Point"}
}