{
  "type": "Feature",
  "properties": {
    "gn:admin1_code":"10",
    "gn:asciiname":"Mirnyy",
    "gn:country_code":"RU",
    "gn:dem":175,
    "gn:feature_class":"P",
    "gn:feature_code":"PPL",
    "gn:name":"Mirnyy",
    "gn:population":0,
    "gn:timezone":"Europe/Moscow",
    "iso:country":"RU",
    "name:rus_x_preferred":[
        "\u041c\u0438\u0440\u043d\u044b\u0439"
    ],
    "name:und_x_variant":[
        "Zhvaki",
        "Mirnyy",
        "\u041c\u0438\u0440\u043d\u044b\u0439"
    ],
    "wof:name":"Mirnyy",
    "wof:placetype":"locality"
},
  "geometry": {"coordinates":[32.98864,52.44556],"type":"Point"}
}