{
  "type": "Feature",
  "properties": {
    "gn:admin1_code":"72",
    "gn:asciiname":"Kryukovka",
    "gn:country_code":"RU",
    "gn:dem":122,
    "gn:feature_class":"P",
    "gn:feature_code":"PPL",
    "gn:name":"Kryukovka",
    "gn:population":0,
    "gn:timezone":"Europe/Moscow",
    "iso:country":"RU",
    "name:rus_x_preferred":[
        "\u041a\u0440\u044e\u043a\u043e\u0432\u043a\u0430"
    ],
    "name:und_x_variant":[
        "Kryukovo",
        "Kryukovka"
    ],
    "wof:name":"Kryukovka",
    "wof:placetype":"locality"
},
  "geometry": {"coordinates":[40.5467,52.7674],"type":"Point"}
}