{
  "type": "Feature",
  "properties": {
    "gn:admin1_code":"61.0",
    "gn:asciiname":"Zheleznodorozhnyy",
    "gn:country_code":"RU",
    "gn:dem":56,
    "gn:feature_class":"P",
    "gn:feature_code":"PPL",
    "gn:name":"Zheleznodorozhnyy",
    "gn:population":0,
    "gn:timezone":"Europe/Moscow",
    "iso:country":"RU",
    "name:eng_x_preferred":[
        "Zheleznodorozhnyy"
    ],
    "name:nor_x_preferred":[
        "Zjeleznodorozjnyj"
    ],
    "name:rus_x_preferred":[
        "\u0416\u0435\u043b\u0435\u0437\u043d\u043e\u0434\u043e\u0440\u043e\u0436\u043d\u044b\u0439"
    ],
    "name:und_x_variant":[
        "Bednyak",
        "Zheleznodorozhnyy"
    ],
    "wof:name":"Zheleznodorozhnyy",
    "wof:placetype":"locality"
},
  "geometry": {"coordinates":[41.98697,47.93579],"type":"Point"}
}