{
  "type": "Feature",
  "properties": {
    "gn:admin1_code":"61.0",
    "gn:asciiname":"Budkovskiy",
    "gn:country_code":"RU",
    "gn:dem":103,
    "gn:feature_class":"P",
    "gn:feature_code":"PPL",
    "gn:name":"Budkovskiy",
    "gn:population":0,
    "gn:timezone":"Europe/Moscow",
    "iso:country":"RU",
    "name:rus_x_preferred":[
        "\u0411\u0443\u0434\u043a\u043e\u0432\u0441\u043a\u0438\u0439"
    ],
    "name:und_x_variant":[
        "\u0411\u0443\u0434\u043a\u043e\u0432\u0441\u043a\u0438\u0439"
    ],
    "wof:name":"Budkovskiy",
    "wof:placetype":"locality"
},
  "geometry": {"coordinates":[41.52667,48.98],"type":"Point"}
}