{
  "type": "Feature",
  "properties": {
    "gn:admin1_code":"56",
    "gn:asciiname":"Belyy Nemed",
    "gn:country_code":"RU",
    "gn:dem":178,
    "gn:feature_class":"P",
    "gn:feature_code":"PPL",
    "gn:name":"Belyy Nemed",
    "gn:population":0,
    "gn:timezone":"Europe/Moscow",
    "iso:country":"RU",
    "name:nor_x_preferred":[
        "Belyj Nemed"
    ],
    "name:rus_x_preferred":[
        "\u0411\u0435\u043b\u044b\u0439 \u041d\u0435\u043c\u0435\u0434"
    ],
    "wof:name":"Belyy Nemed",
    "wof:placetype":"locality"
},
  "geometry": {"coordinates":[35.6669,52.3027],"type":"Point"}
}