{
  "type": "Feature",
  "properties": {
    "gn:admin1_code":"24.0",
    "gn:asciiname":"Bergin Khuduk",
    "gn:country_code":"RU",
    "gn:dem":1,
    "gn:feature_class":"P",
    "gn:feature_code":"PPL",
    "gn:name":"Bergin Khuduk",
    "gn:population":0,
    "gn:timezone":"Europe/Moscow",
    "iso:country":"RU",
    "name:nor_x_preferred":[
        "Bergin Khuduk"
    ],
    "name:rus_x_preferred":[
        "\u0411\u0435\u0440\u0433\u0438\u043d \u0425\u0443\u0434\u0443\u043a"
    ],
    "wof:name":"Bergin Khuduk",
    "wof:placetype":"locality"
},
  "geometry": {"coordinates":[44.91972,47.43472],"type":"Point"}
}