{
  "type": "Feature",
  "properties": {
    "gn:admin1_code":"77",
    "gn:asciiname":"Yurkino",
    "gn:country_code":"RU",
    "gn:dem":150,
    "gn:feature_class":"P",
    "gn:feature_code":"PPL",
    "gn:name":"Yurkino",
    "gn:population":0,
    "gn:timezone":"Europe/Moscow",
    "iso:country":"RU",
    "name:rus_x_preferred":[
        "\u042e\u0440\u043a\u0438\u043d\u043e"
    ],
    "wof:name":"Yurkino",
    "wof:placetype":"locality"
},
  "geometry": {"coordinates":[36.5714,57.7712],"type":"Point"}
}