{
  "type": "Feature",
  "properties": {
    "gn:admin1_code":"88",
    "gn:asciiname":"Yefanovo",
    "gn:country_code":"RU",
    "gn:dem":111,
    "gn:feature_class":"P",
    "gn:feature_code":"PPL",
    "gn:name":"Yefanovo",
    "gn:population":0,
    "gn:timezone":"Europe/Moscow",
    "iso:country":"RU",
    "name:rus_x_preferred":[
        "\u0415\u0444\u0430\u043d\u043e\u0432\u043e"
    ],
    "wof:name":"Yefanovo",
    "wof:placetype":"locality"
},
  "geometry": {"coordinates":[38.20536,58.10459],"type":"Point"}
}