{
  "type": "Feature",
  "properties": {
    "gn:admin1_code":"76",
    "gn:asciiname":"Medvedev",
    "gn:country_code":"RU",
    "gn:dem":241,
    "gn:feature_class":"P",
    "gn:feature_code":"PPL",
    "gn:name":"Medvedev",
    "gn:population":0,
    "gn:timezone":"Europe/Moscow",
    "iso:country":"RU",
    "name:rus_x_preferred":[
        "\u041c\u0435\u0434\u0432\u0435\u0434\u0435\u0432"
    ],
    "name:slv_x_preferred":[
        "Medvedev"
    ],
    "wof:name":"Medvedev",
    "wof:placetype":"locality"
},
  "geometry": {"coordinates":[38.1228,53.4996],"type":"Point"}
}