{
  "type": "Feature",
  "properties": {
    "gn:admin1_code":"62.0",
    "gn:asciiname":"Fedosovo",
    "gn:country_code":"RU",
    "gn:dem":140,
    "gn:feature_class":"P",
    "gn:feature_code":"PPL",
    "gn:name":"Fedosovo",
    "gn:population":0,
    "gn:timezone":"Europe/Moscow",
    "iso:country":"RU",
    "name:eng_x_preferred":[
        "Fedosovo"
    ],
    "name:nor_x_preferred":[
        "Fedosovo"
    ],
    "name:rus_x_preferred":[
        "\u0424\u0435\u0434\u043e\u0441\u043e\u0432\u043e"
    ],
    "name:und_x_variant":[
        "Fedosova Polyana",
        "\u0424\u0435\u0434\u043e\u0441\u043e\u0432\u043e",
        "Fedosovo"
    ],
    "wof:name":"Fedosovo",
    "wof:placetype":"locality"
},
  "geometry": {"coordinates":[41.40695,53.95967],"type":"Point"}
}