{
  "type": "Feature",
  "properties": {
    "gn:admin1_code":"21",
    "gn:asciiname":"Kornilovo",
    "gn:country_code":"RU",
    "gn:dem":132,
    "gn:feature_class":"P",
    "gn:feature_code":"PPL",
    "gn:name":"Kornilovo",
    "gn:population":0,
    "gn:timezone":"Europe/Moscow",
    "iso:country":"RU",
    "name:rus_x_preferred":[
        "\u041a\u043e\u0440\u043d\u0438\u043b\u043e\u0432\u043e"
    ],
    "wof:name":"Kornilovo",
    "wof:placetype":"locality"
},
  "geometry": {"coordinates":[41.89261,57.5818],"type":"Point"}
}