{
  "type": "Feature",
  "properties": {
    "gn:admin1_code":"60",
    "gn:asciiname":"Smolyakovo",
    "gn:country_code":"RU",
    "gn:dem":178,
    "gn:feature_class":"P",
    "gn:feature_code":"PPL",
    "gn:name":"Smolyakovo",
    "gn:population":0,
    "gn:timezone":"Europe/Moscow",
    "iso:country":"RU",
    "name:rus_x_preferred":[
        "\u0421\u043c\u043e\u043b\u044f\u043a\u043e\u0432\u043e"
    ],
    "wof:name":"Smolyakovo",
    "wof:placetype":"locality"
},
  "geometry": {"coordinates":[29.7873,56.0637],"type":"Point"}
}