{
  "type": "Feature",
  "properties": {
    "gn:admin1_code":"93",
    "gn:asciiname":"Nelyaty",
    "gn:country_code":"RU",
    "gn:dem":512,
    "gn:feature_class":"P",
    "gn:feature_code":"PPL",
    "gn:name":"Nelyaty",
    "gn:population":0,
    "gn:timezone":"Asia/Chita",
    "iso:country":"RU",
    "name:eng_x_preferred":[
        "Nelyaty"
    ],
    "name:nor_x_preferred":[
        "Neljaty"
    ],
    "name:rus_x_preferred":[
        "\u041d\u0435\u043b\u044f\u0442\u044b"
    ],
    "name:und_x_variant":[
        "\u041d\u0435\u043b\u044f\u0442\u044b",
        "Nelyaty"
    ],
    "wof:name":"Nelyaty",
    "wof:placetype":"locality"
},
  "geometry": {"coordinates":[115.70193999999999,56.49417],"type":"Point"}
}