{
  "type": "Feature",
  "properties": {
    "gn:admin1_code":"8",
    "gn:asciiname":"Sandugach",
    "gn:country_code":"RU",
    "gn:dem":140,
    "gn:feature_class":"P",
    "gn:feature_code":"PPL",
    "gn:name":"Sandugach",
    "gn:population":0,
    "gn:timezone":"Asia/Yekaterinburg",
    "iso:country":"RU",
    "name:rus_x_preferred":[
        "\u0421\u0430\u043d\u0434\u0443\u0433\u0430\u0447"
    ],
    "wof:name":"Sandugach",
    "wof:placetype":"locality"
},
  "geometry": {"coordinates":[56.29025,56.04313000000001],"type":"Point"}
}