{
  "type": "Feature",
  "properties": {
    "gn:admin1_code":"8",
    "gn:asciiname":"Sandugach",
    "gn:country_code":"RU",
    "gn:dem":140,
    "gn:feature_class":"P",
    "gn:feature_code":"PPL",
    "gn:name":"Sandugach",
    "gn:population":0,
    "gn:timezone":"Asia/Yekaterinburg",
    "iso:country":"RU",
    "name:aze_x_preferred":[
        "Sandura\u00e7"
    ],
    "name:bak_x_preferred":[
        "\u04ba\u0430\u043d\u0434\u0443\u0493\u0430\u0441"
    ],
    "name:che_x_preferred":[
        "\u0421\u0430\u043d\u0434\u0443\u0433\u0430\u0447"
    ],
    "name:hye_x_preferred":[
        "\u054d\u0561\u0576\u0564\u0578\u0582\u0563\u0561\u0579"
    ],
    "name:kaz_x_preferred":[
        "\u0421\u0430\u043d\u0434\u0443\u0433\u0430\u0447"
    ],
    "name:kir_x_preferred":[
        "\u0421\u0430\u043d\u0434\u0443\u0433\u0430\u0447"
    ],
    "name:rus_x_preferred":[
        "\u0421\u0430\u043d\u0434\u0443\u0433\u0430\u0447"
    ],
    "name:tat_x_preferred":[
        "\u0421\u0430\u043d\u0434\u0443\u0433\u0430\u0447"
    ],
    "wof:name":"Sandugach",
    "wof:placetype":"locality"
},
  "geometry": {"coordinates":[56.29025,56.04313000000001],"type":"Point"}
}