{
  "type": "Feature",
  "properties": {
    "gn:admin1_code":"81",
    "gn:asciiname":"Krasnopolka",
    "gn:country_code":"RU",
    "gn:dem":131,
    "gn:feature_class":"P",
    "gn:feature_code":"PPL",
    "gn:name":"Krasnopolka",
    "gn:population":0,
    "gn:timezone":"Europe/Ulyanovsk",
    "iso:country":"RU",
    "name:eng_x_preferred":[
        "Krasnopolka"
    ],
    "name:nor_x_preferred":[
        "Krasnopolka"
    ],
    "name:rus_x_preferred":[
        "\u041a\u0440\u0430\u0441\u043d\u043e\u043f\u043e\u043b\u043a\u0430"
    ],
    "name:und_x_variant":[
        "\u041a\u0440\u0430\u0441\u043d\u043e\u043f\u043e\u043b\u043a\u0430",
        "Krasnopolka"
    ],
    "wof:name":"Krasnopolka",
    "wof:placetype":"locality"
},
  "geometry": {"coordinates":[46.92192,54.1653],"type":"Point"}
}