{
  "type": "Feature",
  "properties": {
    "gn:admin1_code":"90",
    "gn:asciiname":"Tigunova",
    "gn:country_code":"RU",
    "gn:dem":279,
    "gn:feature_class":"P",
    "gn:feature_code":"PPL",
    "gn:name":"Tigunova",
    "gn:population":0,
    "gn:timezone":"Asia/Yekaterinburg",
    "iso:country":"RU",
    "wof:name":"Tigunova",
    "wof:placetype":"locality"
},
  "geometry": {"coordinates":[57.91667,57.56667],"type":"Point"}
}