{
  "type": "Feature",
  "properties": {
    "gn:admin1_code":"90.0",
    "gn:asciiname":"Gari",
    "gn:country_code":"RU",
    "gn:dem":119,
    "gn:feature_class":"P",
    "gn:feature_code":"PPL",
    "gn:name":"Gari",
    "gn:population":0,
    "gn:timezone":"Asia/Yekaterinburg",
    "iso:country":"RU",
    "name:rus_x_preferred":[
        "\u0413\u0430\u0440\u0438"
    ],
    "wof:name":"Gari",
    "wof:placetype":"locality"
},
  "geometry": {"coordinates":[54.92265,57.29278000000001],"type":"Point"}
}