{
  "type": "Feature",
  "properties": {
    "gn:admin1_code":"53",
    "gn:asciiname":"Volovo",
    "gn:country_code":"RU",
    "gn:dem":108,
    "gn:feature_class":"P",
    "gn:feature_code":"PPL",
    "gn:name":"Volovo",
    "gn:population":0,
    "gn:timezone":"Asia/Novosibirsk",
    "iso:country":"RU",
    "name:ceb_x_preferred":[
        "\u0412\u043e\u043b\u043e\u0432\u043e"
    ],
    "name:deu_x_preferred":[
        "Wolowo"
    ],
    "name:eng_x_preferred":[
        "Volovo"
    ],
    "name:ita_x_preferred":[
        "Volovo"
    ],
    "name:nor_x_preferred":[
        "Volovo"
    ],
    "name:rus_x_preferred":[
        "\u0412\u043e\u043b\u043e\u0432\u043e"
    ],
    "name:ukr_x_preferred":[
        "\u0412\u043e\u043b\u043e\u0432\u043e"
    ],
    "name:und_x_variant":[
        "Volovoy"
    ],
    "wof:name":"Volovo",
    "wof:placetype":"locality"
},
  "geometry": {"coordinates":[75.90996,54.83136],"type":"Point"}
}