{
  "type": "Feature",
  "properties": {
    "gn:admin1_code":"25",
    "gn:asciiname":"Rusinovo",
    "gn:country_code":"RU",
    "gn:dem":182,
    "gn:feature_class":"P",
    "gn:feature_code":"PPL",
    "gn:name":"Rusinovo",
    "gn:population":0,
    "gn:timezone":"Europe/Moscow",
    "iso:country":"RU",
    "name:nor_x_preferred":[
        "Rusinovo"
    ],
    "name:rus_x_preferred":[
        "\u0420\u0443\u0441\u0438\u043d\u043e\u0432\u043e"
    ],
    "wof:name":"Rusinovo",
    "wof:placetype":"locality"
},
  "geometry": {"coordinates":[36.73482,54.66212],"type":"Point"}
}