{
  "type": "Feature",
  "properties": {
    "gn:admin1_code":"33.0",
    "gn:asciiname":"Igumnovo",
    "gn:country_code":"RU",
    "gn:dem":117,
    "gn:feature_class":"P",
    "gn:feature_code":"PPL",
    "gn:name":"Igumnovo",
    "gn:population":0,
    "gn:timezone":"Europe/Kirov",
    "iso:country":"RU",
    "name:eng_x_preferred":[
        "Igumnovo"
    ],
    "name:nor_x_preferred":[
        "Igumnovo"
    ],
    "name:rus_x_preferred":[
        "\u0418\u0433\u0443\u043c\u043d\u043e\u0432\u043e"
    ],
    "wof:name":"Igumnovo",
    "wof:placetype":"locality"
},
  "geometry": {"coordinates":[50.59143,58.4856],"type":"Point"}
}