{
  "type": "Feature",
  "properties": {
    "gn:admin1_code":"54",
    "gn:asciiname":"Bulekbay",
    "gn:country_code":"RU",
    "gn:dem":108,
    "gn:feature_class":"P",
    "gn:feature_code":"PPL",
    "gn:name":"Bulekbay",
    "gn:population":0,
    "gn:timezone":"Asia/Omsk",
    "iso:country":"RU",
    "name:rus_x_preferred":[
        "\u0411\u0443\u043b\u0435\u043a\u0431\u0430\u0439"
    ],
    "name:und_x_variant":[
        "\u0411\u0443\u043b\u0435\u043a\u0431\u0430\u0439"
    ],
    "wof:name":"Bulekbay",
    "wof:placetype":"locality"
},
  "geometry": {"coordinates":[73.01666999999998,54.55],"type":"Point"}
}