{
  "type": "Feature",
  "properties": {
    "gn:admin1_code":"61",
    "gn:asciiname":"Krasnaya Zvezda",
    "gn:country_code":"RU",
    "gn:dem":104,
    "gn:feature_class":"P",
    "gn:feature_code":"PPL",
    "gn:name":"Krasnaya Zvezda",
    "gn:population":0,
    "gn:timezone":"Europe/Moscow",
    "iso:country":"RU",
    "name:rus_x_preferred":[
        "\u041a\u0440\u0430\u0441\u043d\u0430\u044f \u0417\u0432\u0435\u0437\u0434\u0430"
    ],
    "name:und_x_variant":[
        "\u041a\u0440\u0430\u0441\u043d\u0430\u044f \u0417\u0432\u0435\u0437\u0434\u0430"
    ],
    "wof:name":"Krasnaya Zvezda",
    "wof:placetype":"locality"
},
  "geometry": {"coordinates":[40.82786,46.90283],"type":"Point"}
}