{
  "type": "Feature",
  "properties": {
    "gn:admin1_code":"45.0",
    "gn:asciiname":"Pomashnur",
    "gn:country_code":"RU",
    "gn:dem":224,
    "gn:feature_class":"P",
    "gn:feature_code":"PPL",
    "gn:name":"Pomashnur",
    "gn:population":0,
    "gn:timezone":"Europe/Moscow",
    "iso:country":"RU",
    "name:rus_x_preferred":[
        "\u041f\u043e\u043c\u0430\u0448\u043d\u0443\u0440"
    ],
    "name:und_x_variant":[
        "\u041f\u043e\u043c\u0430\u0448\u043d\u0443\u0440"
    ],
    "wof:name":"Pomashnur",
    "wof:placetype":"locality"
},
  "geometry": {"coordinates":[49.01056,56.77611],"type":"Point"}
}