{
  "type": "Feature",
  "properties": {
    "gn:admin1_code":"51.0",
    "gn:asciiname":"Lipeley",
    "gn:country_code":"RU",
    "gn:dem":168,
    "gn:feature_class":"P",
    "gn:feature_code":"PPL",
    "gn:name":"Lipeley",
    "gn:population":0,
    "gn:timezone":"Europe/Moscow",
    "iso:country":"RU",
    "name:rus_x_preferred":[
        "\u041b\u0438\u043f\u0435\u043b\u0435\u0439"
    ],
    "wof:name":"Lipeley",
    "wof:placetype":"locality"
},
  "geometry": {"coordinates":[43.17283,55.26232],"type":"Point"}
}