{
  "type": "Feature",
  "properties": {
    "gn:admin1_code":"6",
    "gn:asciiname":"Kal'i",
    "gn:country_code":"RU",
    "gn:dem":29,
    "gn:feature_class":"P",
    "gn:feature_code":"PPL",
    "gn:name":"Kal\u2019i",
    "gn:population":0,
    "gn:timezone":"Europe/Moscow",
    "iso:country":"RU",
    "name:eng_x_preferred":[
        "Kal'i"
    ],
    "name:nor_x_preferred":[
        "Kali"
    ],
    "name:rus_x_preferred":[
        "\u041a\u0430\u043b\u044c\u0438"
    ],
    "name:und_x_variant":[
        "Makarovskaya",
        "\u041a\u0430\u043b\u044c\u0438",
        "Kal\u2019i"
    ],
    "wof:name":"Kal'i",
    "wof:placetype":"locality"
},
  "geometry": {"coordinates":[42.0693,63.1441],"type":"Point"}
}