{
  "type": "Feature",
  "properties": {
    "gn:admin1_code":"43.0",
    "gn:asciiname":"Bessonoye",
    "gn:country_code":"RU",
    "gn:dem":180,
    "gn:feature_class":"P",
    "gn:feature_code":"PPL",
    "gn:name":"Bessonoye",
    "gn:population":0,
    "gn:timezone":"Europe/Moscow",
    "iso:country":"RU",
    "name:nor_x_preferred":[
        "Bessonoje"
    ],
    "name:rus_x_preferred":[
        "\u0411\u0435\u0441\u0441\u043e\u043d\u043e\u0435"
    ],
    "wof:name":"Bessonoye",
    "wof:placetype":"locality"
},
  "geometry": {"coordinates":[39.33333,52.98333],"type":"Point"}
}