{
  "type": "Feature",
  "properties": {
    "gn:admin1_code":"47",
    "gn:asciiname":"Marchugi",
    "gn:country_code":"RU",
    "gn:dem":113,
    "gn:feature_class":"P",
    "gn:feature_code":"PPL",
    "gn:name":"Marchugi",
    "gn:population":0,
    "gn:timezone":"Europe/Moscow",
    "iso:country":"RU",
    "name:eng_x_preferred":[
        "Marchugi"
    ],
    "name:nor_x_preferred":[
        "Martsjugi"
    ],
    "name:rus_x_preferred":[
        "\u041c\u0430\u0440\u0447\u0443\u0433\u0438"
    ],
    "wof:name":"Marchugi",
    "wof:placetype":"locality"
},
  "geometry": {"coordinates":[38.55643,55.36161],"type":"Point"}
}