{
  "type": "Feature",
  "properties": {
    "gn:admin1_code":"8",
    "gn:asciiname":"Volostnovka",
    "gn:country_code":"RU",
    "gn:dem":221,
    "gn:feature_class":"P",
    "gn:feature_code":"PPL",
    "gn:name":"Volostnovka",
    "gn:population":0,
    "gn:timezone":"Asia/Yekaterinburg",
    "iso:country":"RU",
    "name:eng_x_preferred":[
        "Volostnovka"
    ],
    "name:nor_x_preferred":[
        "Volostnovka"
    ],
    "name:rus_x_preferred":[
        "\u0412\u043e\u043b\u043e\u0441\u0442\u043d\u043e\u0432\u043a\u0430"
    ],
    "wof:name":"Volostnovka",
    "wof:placetype":"locality"
},
  "geometry": {"coordinates":[56.23183,52.81841],"type":"Point"}
}