{
  "type": "Feature",
  "properties": {
    "gn:admin1_code":"40",
    "gn:asciiname":"Sinara",
    "gn:cc2":"RU",
    "gn:country_code":"RU",
    "gn:dem":94,
    "gn:feature_class":"P",
    "gn:feature_code":"PPL",
    "gn:name":"Sinara",
    "gn:population":0,
    "gn:timezone":"Asia/Yekaterinburg",
    "iso:country":"RU",
    "name:rus_x_preferred":[
        "\u0421\u0438\u043d\u0430\u0440\u0430"
    ],
    "name:und_x_variant":[
        "Medvedeva",
        "Sinara",
        "\u0421\u0438\u043d\u0430\u0440\u0430"
    ],
    "wof:name":"Sinara",
    "wof:placetype":"locality"
},
  "geometry": {"coordinates":[62.35,56.28333000000001],"type":"Point"}
}