{
  "type": "Feature",
  "properties": {
    "gn:admin1_code":"88.0",
    "gn:asciiname":"Bryushinino",
    "gn:country_code":"RU",
    "gn:dem":137,
    "gn:feature_class":"P",
    "gn:feature_code":"PPL",
    "gn:name":"Bryushinino",
    "gn:population":0,
    "gn:timezone":"Europe/Moscow",
    "iso:country":"RU",
    "name:rus_x_preferred":[
        "\u0411\u0440\u044e\u0448\u0438\u043d\u0438\u043d\u043e"
    ],
    "name:und_x_variant":[
        "\u0411\u0440\u044e\u0448\u0438\u043d\u0438\u043d\u043e"
    ],
    "wof:name":"Bryushinino",
    "wof:placetype":"locality"
},
  "geometry": {"coordinates":[40.67907,58.53445],"type":"Point"}
}