{
  "type": "Feature",
  "properties": {
    "gn:admin1_code":"52",
    "gn:asciiname":"Strelitsy",
    "gn:country_code":"RU",
    "gn:dem":57,
    "gn:feature_class":"P",
    "gn:feature_code":"PPL",
    "gn:name":"Strelitsy",
    "gn:population":0,
    "gn:timezone":"Europe/Moscow",
    "iso:country":"RU",
    "name:rus_x_preferred":[
        "\u0421\u0442\u0440\u0435\u043b\u0438\u0446\u044b"
    ],
    "name:und_x_variant":[
        "\u0421\u0442\u0440\u0435\u043b\u0438\u0446\u044b"
    ],
    "wof:name":"Strelitsy",
    "wof:placetype":"locality"
},
  "geometry": {"coordinates":[31.96667,57.81667],"type":"Point"}
}