{
  "type": "Feature",
  "properties": {
    "gn:admin1_code":"55",
    "gn:asciiname":"Novopoltavka",
    "gn:country_code":"RU",
    "gn:dem":236,
    "gn:feature_class":"P",
    "gn:feature_code":"PPL",
    "gn:name":"Novopoltavka",
    "gn:population":0,
    "gn:timezone":"Europe/Moscow",
    "iso:country":"RU",
    "name:rus_x_preferred":[
        "\u041d\u043e\u0432\u043e\u043f\u043e\u043b\u0442\u0430\u0432\u043a\u0430"
    ],
    "name:und_x_variant":[
        "\u041d\u043e\u0432\u043e\u043f\u043e\u043b\u0442\u0430\u0432\u043a\u0430"
    ],
    "wof:name":"Novopoltavka",
    "wof:placetype":"locality"
},
  "geometry": {"coordinates":[52.6158,54.3578],"type":"Point"}
}