{
  "type": "Feature",
  "properties": {
    "gn:admin1_code":"17",
    "gn:asciiname":"Kambulat",
    "gn:country_code":"RU",
    "gn:dem":-11,
    "gn:feature_class":"P",
    "gn:feature_code":"PPL",
    "gn:name":"Kambulat",
    "gn:population":0,
    "gn:timezone":"Europe/Moscow",
    "iso:country":"RU",
    "name:rus_x_preferred":[
        "\u041a\u0430\u043c\u0431\u0443\u043b\u0430\u0442"
    ],
    "name:und_x_variant":[
        "\u041a\u0430\u043c\u0431\u0443\u043b\u0430\u0442"
    ],
    "wof:name":"Kambulat",
    "wof:placetype":"locality"
},
  "geometry": {"coordinates":[46.99987,43.48911],"type":"Point"}
}