{
  "type": "Feature",
  "properties": {
    "gn:admin1_code":"3",
    "gn:asciiname":"Taldushka",
    "gn:cc2":"RU",
    "gn:country_code":"RU",
    "gn:dem":298,
    "gn:feature_class":"P",
    "gn:feature_code":"PPL",
    "gn:name":"Taldushka",
    "gn:population":0,
    "gn:timezone":"Asia/Omsk",
    "iso:country":"RU",
    "name:und_x_variant":[
        "Tavdushka",
        "Taldushka"
    ],
    "wof:name":"Taldushka",
    "wof:placetype":"locality"
},
  "geometry": {"coordinates":[85.7255,51.83018],"type":"Point"}
}