{
  "type": "Feature",
  "properties": {
    "gn:country":"RU",
    "gn:fcode":"PPL",
    "gn:population":650,
    "iso:country":"RU",
    "name:eng_x_preferred":[
        "Sofiysk"
    ],
    "name:nor_x_preferred":[
        "Sofijsk"
    ],
    "name:rus_x_preferred":[
        "\u0421\u043e\u0444\u0438\u0439\u0441\u043a"
    ],
    "name:und_x_variant":[
        "Sosiiskii-Priisk"
    ],
    "qs:name":"Sofiysk",
    "qs:photos_9r":0,
    "qs:photos_sr":0,
    "qs:pop_sr":"2",
    "wof:name":"Sofiysk",
    "wof:placetype":"locality",
    "wof:population":650
},
  "geometry": {"coordinates":[133.99401,52.25621],"type":"Point"}
}