{
  "type": "Feature",
  "properties": {
    "gn:admin1_code":"79",
    "gn:asciiname":"Yrban",
    "gn:country_code":"RU",
    "gn:dem":862,
    "gn:feature_class":"P",
    "gn:feature_code":"PPL",
    "gn:name":"Yrban",
    "gn:population":0,
    "gn:timezone":"Asia/Krasnoyarsk",
    "iso:country":"RU",
    "name:eng_x_preferred":[
        "Yrban"
    ],
    "name:nor_x_preferred":[
        "Yrban"
    ],
    "name:rus_x_preferred":[
        "\u042b\u0440\u0431\u0430\u043d"
    ],
    "wof:name":"Yrban",
    "wof:placetype":"locality"
},
  "geometry": {"coordinates":[95.72562000000001,52.71378000000001],"type":"Point"}
}