{
  "type": "Feature",
  "properties": {
    "gn:admin1_code":"42",
    "gn:asciiname":"Podbor'ye",
    "gn:country_code":"RU",
    "gn:dem":39,
    "gn:feature_class":"P",
    "gn:feature_code":"PPL",
    "gn:name":"Podbor\u2019ye",
    "gn:population":0,
    "gn:timezone":"Europe/Moscow",
    "iso:country":"RU",
    "name:eng_x_preferred":[
        "Podbor'ye"
    ],
    "name:nor_x_preferred":[
        "Podborje"
    ],
    "name:rus_x_preferred":[
        "\u041f\u043e\u0434\u0431\u043e\u0440\u044c\u0435"
    ],
    "name:und_x_variant":[
        "Podbor\u2019ye"
    ],
    "wof:name":"Podbor'ye",
    "wof:placetype":"locality"
},
  "geometry": {"coordinates":[32.98268,59.74333000000001],"type":"Point"}
}