{
  "type": "Feature",
  "properties": {
    "gn:admin1_code":"51",
    "gn:asciiname":"Falino",
    "gn:country_code":"RU",
    "gn:dem":109,
    "gn:feature_class":"P",
    "gn:feature_code":"PPL",
    "gn:name":"Falino",
    "gn:population":0,
    "gn:timezone":"Europe/Moscow",
    "iso:country":"RU",
    "name:rus_x_preferred":[
        "\u0424\u0430\u043b\u0438\u043d\u043e"
    ],
    "wof:name":"Falino",
    "wof:placetype":"locality"
},
  "geometry": {"coordinates":[45.0068,57.4694],"type":"Point"}
}