{
  "type": "Feature",
  "properties": {
    "gn:admin1_code":"61",
    "gn:asciiname":"Kulinkin",
    "gn:country_code":"RU",
    "gn:dem":128,
    "gn:feature_class":"P",
    "gn:feature_code":"PPL",
    "gn:name":"Kulinkin",
    "gn:population":0,
    "gn:timezone":"Europe/Moscow",
    "iso:country":"RU",
    "name:rus_x_preferred":[
        "\u041a\u0443\u043b\u0438\u043d\u043a\u0438\u043d"
    ],
    "wof:name":"Kulinkin",
    "wof:placetype":"locality"
},
  "geometry": {"coordinates":[40.98722,49.69778],"type":"Point"}
}