{
  "type": "Feature",
  "properties": {
    "gn:admin1_code":"38",
    "gn:asciiname":"Zvezdochka",
    "gn:country_code":"RU",
    "gn:dem":78,
    "gn:feature_class":"P",
    "gn:feature_code":"PPL",
    "gn:name":"Zv\u00ebzdochka",
    "gn:population":0,
    "gn:timezone":"Europe/Moscow",
    "iso:country":"RU",
    "name:rus_x_preferred":[
        "\u0417\u0432\u0451\u0437\u0434\u043e\u0447\u043a\u0430"
    ],
    "name:und_x_variant":[
        "Zv\u00ebzochka",
        "Zv\u00ebzdochka"
    ],
    "wof:name":"Zvezdochka",
    "wof:placetype":"locality"
},
  "geometry": {"coordinates":[39.5725,46.7753],"type":"Point"}
}