{
  "type": "Feature",
  "properties": {
    "gn:admin1_code":"62",
    "gn:asciiname":"Kondrokovo",
    "gn:country_code":"RU",
    "gn:dem":115,
    "gn:feature_class":"P",
    "gn:feature_code":"PPL",
    "gn:name":"Kondrokovo",
    "gn:population":0,
    "gn:timezone":"Europe/Moscow",
    "iso:country":"RU",
    "name:rus_x_preferred":[
        "\u041a\u043e\u043d\u0434\u0440\u043e\u043a\u043e\u0432\u043e"
    ],
    "wof:name":"Kondrokovo",
    "wof:placetype":"locality"
},
  "geometry": {"coordinates":[41.3005,55.0798],"type":"Point"}
}