{
  "type": "Feature",
  "properties": {
    "gn:admin1_code":"20",
    "gn:asciiname":"Imikhse-Buz",
    "gn:country_code":"RU",
    "gn:dem":679,
    "gn:feature_class":"P",
    "gn:feature_code":"PPL",
    "gn:name":"Imikhse-Buz",
    "gn:population":0,
    "gn:timezone":"Asia/Irkutsk",
    "iso:country":"RU",
    "name:rus_x_preferred":[
        "\u0418\u043c\u0438\u0445\u0441\u0435-\u0411\u0443\u0437"
    ],
    "name:und_x_variant":[
        "\u0418\u043c\u0438\u0445\u0441\u0435-\u0411\u0443\u0437"
    ],
    "wof:name":"Imikhse-Buz",
    "wof:placetype":"locality"
},
  "geometry": {"coordinates":[106.51667,52.86666999999999],"type":"Point"}
}