{
  "type": "Feature",
  "properties": {
    "gn:admin1_code":"42",
    "gn:admin2_code":"6695196",
    "gn:asciiname":"Vesnino",
    "gn:country_code":"RU",
    "gn:dem":19,
    "gn:feature_class":"P",
    "gn:feature_code":"PPL",
    "gn:name":"Vesnino",
    "gn:population":0,
    "gn:timezone":"Europe/Moscow",
    "iso:country":"RU",
    "name:eng_x_preferred":[
        "Vesnino"
    ],
    "name:fin_x_historical":[
        "Kahvenitsa"
    ],
    "name:fin_x_preferred":[
        "Kahvenitsa"
    ],
    "name:rus_x_preferred":[
        "\u0412\u0435\u0441\u043d\u0438\u043d\u043e"
    ],
    "name:und_x_variant":[
        "Kakhvenitsa"
    ],
    "wof:name":"Vesnino",
    "wof:placetype":"locality"
},
  "geometry": {"coordinates":[30.09284,60.82935],"type":"Point"}
}