{
  "type": "Feature",
  "properties": {
    "gn:admin1_code":"73",
    "gn:asciiname":"Uyut",
    "gn:country_code":"RU",
    "gn:dem":98,
    "gn:feature_class":"P",
    "gn:feature_code":"PPL",
    "gn:name":"Uyut",
    "gn:population":0,
    "gn:timezone":"Europe/Moscow",
    "iso:country":"RU",
    "name:rus_x_preferred":[
        "\u0423\u044e\u0442"
    ],
    "name:und_x_variant":[
        "\u0423\u044e\u0442"
    ],
    "wof:name":"Uyut",
    "wof:placetype":"locality"
},
  "geometry": {"coordinates":[50.28757,55.95046],"type":"Point"}
}