{
  "type": "Feature",
  "properties": {
    "gn:admin1_code":"77",
    "gn:asciiname":"Volosovo",
    "gn:country_code":"RU",
    "gn:dem":163,
    "gn:feature_class":"P",
    "gn:feature_code":"PPL",
    "gn:name":"Volosovo",
    "gn:population":0,
    "gn:timezone":"Europe/Moscow",
    "iso:country":"RU",
    "name:rus_x_preferred":[
        "\u0412\u043e\u043b\u043e\u0441\u043e\u0432\u043e"
    ],
    "name:und_x_variant":[
        "\u0412\u043e\u043b\u043e\u0441\u043e\u0432\u043e"
    ],
    "wof:name":"Volosovo",
    "wof:placetype":"locality"
},
  "geometry": {"coordinates":[36.9924,58.5267],"type":"Point"}
}