{
  "type": "Feature",
  "properties": {
    "gn:admin1_code":"13",
    "gn:asciiname":"Utarka",
    "gn:country_code":"RU",
    "gn:dem":358,
    "gn:feature_class":"P",
    "gn:feature_code":"PPL",
    "gn:name":"Utarka",
    "gn:population":0,
    "gn:timezone":"Asia/Yekaterinburg",
    "iso:country":"RU",
    "name:rus_x_preferred":[
        "\u0423\u0442\u0430\u0440\u043a\u0430"
    ],
    "wof:name":"Utarka",
    "wof:placetype":"locality"
},
  "geometry": {"coordinates":[59.36278000000001,53.14028],"type":"Point"}
}