{
  "type": "Feature",
  "properties": {
    "gn:admin1_code":"64",
    "gn:asciiname":"Artemovskiy",
    "gn:country_code":"RU",
    "gn:dem":204,
    "gn:feature_class":"P",
    "gn:feature_code":"PPL",
    "gn:name":"Art\u00ebmovskiy",
    "gn:population":0,
    "gn:timezone":"Asia/Sakhalin",
    "iso:country":"RU",
    "name:ben_x_preferred":[
        "\u0986\u09b0\u09cd\u09a4\u09c7\u09ae\u09cb\u09ad\u09b8\u09cd\u0995\u09bf"
    ],
    "name:heb_x_preferred":[
        "\u05d0\u05e8\u05d8\u05de\u05d5\u05d1\u05e1\u05e7\u05d9"
    ],
    "name:hin_x_preferred":[
        "\u0906\u0930\u094d\u0924\u0947\u092e\u094b\u0935\u0938\u094d\u0915\u093c\u0940"
    ],
    "name:hun_x_preferred":[
        "Artjomovszkij"
    ],
    "name:ind_x_preferred":[
        "Artemovskiy"
    ],
    "name:jpn_x_preferred":[
        "\u30a2\u30eb\u30c6\u30e2\u30d5\u30b9\u30ad\u30fc"
    ],
    "name:nor_x_preferred":[
        "Artjomovskij"
    ],
    "name:por_x_preferred":[
        "Artyomovsky"
    ],
    "name:rus_x_preferred":[
        "\u0410\u0440\u0442\u0451\u043c\u043e\u0432\u0441\u043a\u0438\u0439"
    ],
    "name:spa_x_preferred":[
        "Artemovskiy"
    ],
    "name:und_x_variant":[
        "Okusawa",
        "Okuzawa",
        "Art\u00ebmovskiy"
    ],
    "name:vie_x_preferred":[
        "Artemovskiy"
    ],
    "wof:name":"Artemovskiy",
    "wof:placetype":"locality"
},
  "geometry": {"coordinates":[142.25,47.76667],"type":"Point"}
}