{
  "type": "Feature",
  "properties": {
    "gn:admin1_code":"64",
    "gn:asciiname":"Artemovskiy",
    "gn:country_code":"RU",
    "gn:dem":204,
    "gn:feature_class":"P",
    "gn:feature_code":"PPL",
    "gn:name":"Art\u00ebmovskiy",
    "gn:population":0,
    "gn:timezone":"Asia/Sakhalin",
    "iso:country":"RU",
    "name:nor_x_preferred":[
        "Artjomovskij"
    ],
    "name:rus_x_preferred":[
        "\u0410\u0440\u0442\u0451\u043c\u043e\u0432\u0441\u043a\u0438\u0439"
    ],
    "name:und_x_variant":[
        "Okusawa",
        "Okuzawa",
        "Art\u00ebmovskiy"
    ],
    "wof:name":"Artemovskiy",
    "wof:placetype":"locality"
},
  "geometry": {"coordinates":[142.25,47.76667],"type":"Point"}
}