{
  "type": "Feature",
  "properties": {
    "gn:admin1_code":"61",
    "gn:asciiname":"Platov",
    "gn:country_code":"RU",
    "gn:dem":131,
    "gn:feature_class":"P",
    "gn:feature_code":"PPL",
    "gn:name":"Platov",
    "gn:population":0,
    "gn:timezone":"Europe/Moscow",
    "iso:country":"RU",
    "name:rus_x_preferred":[
        "\u041f\u043b\u0430\u0442\u043e\u0432"
    ],
    "name:und_x_variant":[
        "\u041f\u043b\u0430\u0442\u043e\u0432"
    ],
    "wof:name":"Platov",
    "wof:placetype":"locality"
},
  "geometry": {"coordinates":[41.67752,49.09111],"type":"Point"}
}