{
  "type": "Feature",
  "properties": {
    "gn:admin1_code":"80.0",
    "gn:asciiname":"Tyuriki",
    "gn:country_code":"RU",
    "gn:dem":177,
    "gn:feature_class":"P",
    "gn:feature_code":"PPL",
    "gn:name":"Tyuriki",
    "gn:population":0,
    "gn:timezone":"Europe/Samara",
    "iso:country":"RU",
    "name:rus_x_preferred":[
        "\u0422\u044e\u0440\u0438\u043a\u0438"
    ],
    "wof:name":"Tyuriki",
    "wof:placetype":"locality"
},
  "geometry": {"coordinates":[51.78026,58.15721],"type":"Point"}
}