{
  "type": "Feature",
  "properties": {
    "gn:admin1_code":"4",
    "gn:asciiname":"Bekhtemir-Anikino",
    "gn:country_code":"RU",
    "gn:dem":210,
    "gn:feature_class":"P",
    "gn:feature_code":"PPL",
    "gn:name":"Bekhtemir-Anikino",
    "gn:population":110,
    "gn:timezone":"Asia/Barnaul",
    "iso:country":"RU",
    "name:nor_x_preferred":[
        "Bekhtemir-Anikino"
    ],
    "name:rus_x_preferred":[
        "\u0411\u0435\u0445\u0442\u0435\u043c\u0438\u0440-\u0410\u043d\u0438\u043a\u0438\u043d\u043e"
    ],
    "name:und_x_variant":[
        "Vekhtemirskak",
        "Bekhtemir"
    ],
    "wof:name":"Bekhtemir-Anikino",
    "wof:placetype":"locality",
    "wof:population":110
},
  "geometry": {"coordinates":[85.80194,52.655],"type":"Point"}
}