{
  "type": "Feature",
  "properties": {
    "gn:admin1_code":"91",
    "gn:asciiname":"Bugarikta",
    "gn:country_code":"RU",
    "gn:dem":408,
    "gn:feature_class":"P",
    "gn:feature_code":"PPL",
    "gn:name":"Bugarikta",
    "gn:population":0,
    "gn:timezone":"Asia/Krasnoyarsk",
    "iso:country":"RU",
    "name:rus_x_preferred":[
        "\u0411\u0443\u0433\u0430\u0440\u0438\u043a\u0442\u0430"
    ],
    "wof:name":"Bugarikta",
    "wof:placetype":"locality"
},
  "geometry": {"coordinates":[90.33333,64.91667],"type":"Point"}
}