{
  "type": "Feature",
  "properties": {
    "gn:admin1_code":"11",
    "gn:asciiname":"Chebukchen",
    "gn:cc2":"RU",
    "gn:country_code":"RU",
    "gn:dem":779,
    "gn:feature_class":"P",
    "gn:feature_code":"PPL",
    "gn:name":"Chebukchen",
    "gn:population":0,
    "gn:timezone":"Asia/Irkutsk",
    "iso:country":"RU",
    "name:eng_x_preferred":[
        "Chebukchen"
    ],
    "name:nor_x_preferred":[
        "Tsjebuktsjen"
    ],
    "name:rus_x_preferred":[
        "\u0427\u0435\u0431\u0443\u043a\u0447\u0435\u043d"
    ],
    "name:und_x_variant":[
        "Ulus Shebykshen",
        "Shebykshen",
        "\u0427\u0435\u0431\u0443\u043a\u0447\u0435\u043d",
        "Chebukchen"
    ],
    "wof:name":"Chebukchen",
    "wof:placetype":"locality"
},
  "geometry": {"coordinates":[110.33333,53.76667],"type":"Point"}
}