{
  "type": "Feature",
  "properties": {
    "gn:admin1_code":"63",
    "gn:asciiname":"Billi",
    "gn:cc2":"RU",
    "gn:country_code":"RU",
    "gn:dem":28,
    "gn:feature_class":"P",
    "gn:feature_code":"PPL",
    "gn:name":"Billi",
    "gn:population":0,
    "gn:timezone":"Asia/Magadan",
    "iso:country":"RU",
    "name:rus_x_preferred":[
        "\u0411\u0438\u043b\u043b\u0438"
    ],
    "name:und_x_variant":[
        "Bili",
        "Billi"
    ],
    "wof:name":"Billi",
    "wof:placetype":"locality"
},
  "geometry": {"coordinates":[152.19999999999999,68.83333],"type":"Point"}
}