{
  "type": "Feature",
  "properties": {
    "gn:admin1_code":"68",
    "gn:asciiname":"Sredniy Urukh",
    "gn:country_code":"RU",
    "gn:dem":522,
    "gn:feature_class":"P",
    "gn:feature_code":"PPL",
    "gn:name":"Sredniy Urukh",
    "gn:population":0,
    "gn:timezone":"Europe/Moscow",
    "iso:country":"RU",
    "name:rus_x_preferred":[
        "\u0421\u0440\u0435\u0434\u043d\u0438\u0439 \u0423\u0440\u0443\u0445"
    ],
    "wof:name":"Sredniy Urukh",
    "wof:placetype":"locality"
},
  "geometry": {"coordinates":[43.99166,43.26554],"type":"Point"}
}