{
  "type": "Feature",
  "properties": {
    "gn:admin1_code":"3",
    "gn:asciiname":"Nizhniy Uymon",
    "gn:country_code":"RU",
    "gn:dem":919,
    "gn:feature_class":"P",
    "gn:feature_code":"PPL",
    "gn:name":"Nizhniy Uymon",
    "gn:population":0,
    "gn:timezone":"Asia/Omsk",
    "iso:country":"RU",
    "name:rus_x_preferred":[
        "\u041d\u0438\u0436\u043d\u0438\u0439 \u0423\u0439\u043c\u043e\u043d"
    ],
    "wof:name":"Nizhniy Uymon",
    "wof:placetype":"locality"
},
  "geometry": {"coordinates":[85.9323,50.2026],"type":"Point"}
}