{
  "type": "Feature",
  "properties": {
    "gn:admin1_code":"21",
    "gn:asciiname":"Yelyunino",
    "gn:country_code":"RU",
    "gn:dem":113,
    "gn:feature_class":"P",
    "gn:feature_code":"PPL",
    "gn:name":"Yelyunino",
    "gn:population":0,
    "gn:timezone":"Europe/Moscow",
    "iso:country":"RU",
    "wof:name":"Yelyunino",
    "wof:placetype":"locality"
},
  "geometry": {"coordinates":[41.1689,56.98652],"type":"Point"}
}