{
  "type": "Feature",
  "properties": {
    "gn:admin1_code":"69",
    "gn:asciiname":"Lunino",
    "gn:country_code":"RU",
    "gn:dem":219,
    "gn:feature_class":"P",
    "gn:feature_code":"PPL",
    "gn:name":"Lunino",
    "gn:population":0,
    "gn:timezone":"Europe/Moscow",
    "iso:country":"RU",
    "name:rus_x_preferred":[
        "\u041b\u0443\u043d\u0438\u043d\u043e"
    ],
    "name:und_x_variant":[
        "\u041b\u0443\u043d\u0438\u043d\u043e"
    ],
    "wof:name":"Lunino",
    "wof:placetype":"locality"
},
  "geometry": {"coordinates":[31.52997,54.53688],"type":"Point"}
}