{
  "type": "Feature",
  "properties": {
    "gn:admin1_code":"34",
    "gn:asciiname":"Kushshor",
    "gn:country_code":"RU",
    "gn:dem":30,
    "gn:feature_class":"P",
    "gn:feature_code":"PPL",
    "gn:name":"Kushshor",
    "gn:population":0,
    "gn:timezone":"Europe/Moscow",
    "iso:country":"RU",
    "name:eng_x_preferred":[
        "Kushshor"
    ],
    "name:nor_x_preferred":[
        "Kusjsjor"
    ],
    "name:rus_x_preferred":[
        "\u041a\u0443\u0448\u0448\u043e\u0440"
    ],
    "wof:name":"Kushshor",
    "wof:placetype":"locality"
},
  "geometry": {"coordinates":[56.57066,66.16728000000001],"type":"Point"}
}