{
  "type": "Feature",
  "properties": {
    "gn:admin1_code":"11",
    "gn:asciiname":"Tarbagatay",
    "gn:country_code":"RU",
    "gn:dem":775,
    "gn:feature_class":"P",
    "gn:feature_code":"PPL",
    "gn:name":"Tarbagatay",
    "gn:population":0,
    "gn:timezone":"Asia/Irkutsk",
    "iso:country":"RU",
    "name:rus_x_preferred":[
        "\u0422\u0430\u0440\u0431\u0430\u0433\u0430\u0442\u0430\u0439"
    ],
    "name:und_x_variant":[
        "Tarbagatay-Adag"
    ],
    "wof:name":"Tarbagatay",
    "wof:placetype":"locality"
},
  "geometry": {"coordinates":[109.28274,51.75825],"type":"Point"}
}