{
  "type": "Feature",
  "properties": {
    "gn:admin1_code":"56.0",
    "gn:asciiname":"Gatishchenskiye Vyselki",
    "gn:cc2":"RU",
    "gn:country_code":"RU",
    "gn:dem":208,
    "gn:feature_class":"P",
    "gn:feature_code":"PPL",
    "gn:name":"Gatishchenskiye Vyselki",
    "gn:population":0,
    "gn:timezone":"Europe/Moscow",
    "iso:country":"RU",
    "name:rus_x_preferred":[
        "\u0413\u0430\u0442\u0438\u0449\u0435\u043d\u0441\u043a\u0438\u0435 \u0412\u044b\u0441\u0435\u043b\u043a\u0438"
    ],
    "name:und_x_variant":[
        "Red\u2019kino",
        "Gatishchenskiye",
        "Gatishchenskiye Vyselki"
    ],
    "wof:name":"Gatishchenskiye Vyselki",
    "wof:placetype":"locality"
},
  "geometry": {"coordinates":[37.85,52.21667],"type":"Point"}
}