{
  "type": "Feature",
  "properties": {
    "gn:admin1_code":"4.0",
    "gn:asciiname":"Mashenka",
    "gn:country_code":"RU",
    "gn:dem":694,
    "gn:feature_class":"P",
    "gn:feature_code":"PPL",
    "gn:name":"Mashenka",
    "gn:population":0,
    "gn:timezone":"Asia/Barnaul",
    "iso:country":"RU",
    "name:rus_x_preferred":[
        "\u041c\u0430\u0448\u0435\u043d\u043a\u0430"
    ],
    "wof:name":"Mashenka",
    "wof:placetype":"locality"
},
  "geometry": {"coordinates":[83.86920000000001,51.257],"type":"Point"}
}