{
  "type": "Feature",
  "properties": {
    "gn:admin1_code":"77",
    "gn:asciiname":"Martyshovo",
    "gn:country_code":"RU",
    "gn:dem":167,
    "gn:feature_class":"P",
    "gn:feature_code":"PPL",
    "gn:name":"Martyshovo",
    "gn:population":0,
    "gn:timezone":"Europe/Moscow",
    "iso:country":"RU",
    "name:rus_x_preferred":[
        "\u041c\u0430\u0440\u0442\u044b\u0448o\u0432\u043e"
    ],
    "name:rus_x_variant":[
        "\u041c\u0430\u0440\u0442\u044b\u0448\u0435\u0432\u043e"
    ],
    "name:und_x_variant":[
        "Martyshevo"
    ],
    "wof:name":"Martyshovo",
    "wof:placetype":"locality"
},
  "geometry": {"coordinates":[35.41219,58.23761],"type":"Point"}
}