{
  "type": "Feature",
  "properties": {
    "gn:admin1_code":"42",
    "gn:asciiname":"Vinnitsy-Kobyliy Navolok",
    "gn:cc2":"RU",
    "gn:country_code":"RU",
    "gn:dem":72,
    "gn:feature_class":"P",
    "gn:feature_code":"PPL",
    "gn:name":"Vinnitsy-Kobyliy Navolok",
    "gn:population":0,
    "gn:timezone":"Europe/Moscow",
    "iso:country":"RU",
    "name:und_x_variant":[
        "Kobyliy Navolok",
        "Vinnitsy-Kobyliy Navolok"
    ],
    "wof:name":"Vinnitsy-Kobyliy Navolok",
    "wof:placetype":"locality"
},
  "geometry": {"coordinates":[34.71667,60.61666999999999],"type":"Point"}
}