{
  "type": "Feature",
  "properties": {
    "gn:admin1_code":"8",
    "gn:asciiname":"Utyashevo",
    "gn:country_code":"RU",
    "gn:dem":542,
    "gn:feature_class":"P",
    "gn:feature_code":"PPL",
    "gn:name":"Utyashevo",
    "gn:population":0,
    "gn:timezone":"Asia/Yekaterinburg",
    "iso:country":"RU",
    "wof:name":"Utyashevo",
    "wof:placetype":"locality"
},
  "geometry": {"coordinates":[56.96666999999999,53.98333],"type":"Point"}
}