{
  "type": "Feature",
  "properties": {
    "gn:admin1_code":"37",
    "gn:asciiname":"Krutik",
    "gn:country_code":"RU",
    "gn:dem":134,
    "gn:feature_class":"P",
    "gn:feature_code":"PPL",
    "gn:name":"Krutik",
    "gn:population":0,
    "gn:timezone":"Europe/Moscow",
    "iso:country":"RU",
    "name:rus_x_preferred":[
        "\u041a\u0440\u0443\u0442\u0438\u043a"
    ],
    "name:und_x_variant":[
        "Pochinok",
        "Krutik"
    ],
    "wof:name":"Krutik",
    "wof:placetype":"locality"
},
  "geometry": {"coordinates":[41.00133,57.97292],"type":"Point"}
}