{
  "type": "Feature",
  "properties": {
    "gn:admin1_code":"53",
    "gn:asciiname":"Surguty",
    "gn:country_code":"RU",
    "gn:dem":130,
    "gn:feature_class":"P",
    "gn:feature_code":"PPL",
    "gn:name":"Surguty",
    "gn:population":0,
    "gn:timezone":"Asia/Novosibirsk",
    "iso:country":"RU",
    "name:eng_x_preferred":[
        "Surguty"
    ],
    "name:nor_x_preferred":[
        "Surguty"
    ],
    "name:rus_x_preferred":[
        "\u0421\u0443\u0440\u0433\u0443\u0442\u044b"
    ],
    "name:und_x_variant":[
        "Aul Surgutovskiy",
        "\u0421\u0443\u0440\u0433\u0443\u0442\u044b",
        "Surguty"
    ],
    "wof:name":"Surguty",
    "wof:placetype":"locality"
},
  "geometry": {"coordinates":[78.71833000000002,56.06261],"type":"Point"}
}