{
  "type": "Feature",
  "properties": {
    "gn:country":"RU",
    "gn:fcode":"PPL",
    "gn:pop":0,
    "iso:country":"RU",
    "name:rus_x_preferred":[
        "\u041a\u0440\u0438\u0432\u0438\u0446\u044b"
    ],
    "name:unk_x_variant":[
        "Krivitsy"
    ],
    "qs:name":"Krivitsj",
    "qs:name_adm0":"Russia",
    "qs:name_adm1":"Leningrad Oblast",
    "qs:photos_9r":0,
    "qs:photos_sr":0,
    "qs:placetype":"Town",
    "qs:pop_sr":"0",
    "wof:name":"Krivitsj",
    "wof:placetype":"locality",
    "wof:population":0
},
  "geometry": {"coordinates":[28.15516,59.00326],"type":"Point"}
}