{
  "type": "Feature",
  "properties": {
    "gn:admin1_code":"47",
    "gn:asciiname":"Sukonnikovo",
    "gn:cc2":"RU",
    "gn:country_code":"RU",
    "gn:dem":218,
    "gn:feature_class":"P",
    "gn:feature_code":"PPL",
    "gn:name":"Sukonnikovo",
    "gn:population":0,
    "gn:timezone":"Europe/Moscow",
    "iso:country":"RU",
    "name:rus_x_preferred":[
        "\u0421\u0443\u043a\u043e\u043d\u043d\u0438\u043a\u043e\u0432\u043e"
    ],
    "name:und_x_variant":[
        "Sukannikovo",
        "Sukonniki",
        "Sukonnikovo"
    ],
    "wof:name":"Sukonnikovo",
    "wof:placetype":"locality"
},
  "geometry": {"coordinates":[35.62028,55.48694],"type":"Point"}
}