{
  "type": "Feature",
  "properties": {
    "gn:admin1_code":"9.0",
    "gn:asciiname":"Kholodnyy",
    "gn:country_code":"RU",
    "gn:dem":224,
    "gn:feature_class":"P",
    "gn:feature_code":"PPL",
    "gn:name":"Kholodnyy",
    "gn:population":0,
    "gn:timezone":"Europe/Moscow",
    "iso:country":"RU",
    "name:rus_x_preferred":[
        "\u0425\u043e\u043b\u043e\u0434\u043d\u044b\u0439"
    ],
    "wof:name":"Kholodnyy",
    "wof:placetype":"locality"
},
  "geometry": {"coordinates":[37.08697,50.83536],"type":"Point"}
}