{
  "type": "Feature",
  "properties": {
    "gn:admin1_code":"9.0",
    "gn:asciiname":"Zhilin Kolodez'",
    "gn:country_code":"RU",
    "gn:dem":206,
    "gn:feature_class":"P",
    "gn:feature_code":"PPL",
    "gn:name":"Zhilin Kolodez\u2019",
    "gn:population":0,
    "gn:timezone":"Europe/Moscow",
    "iso:country":"RU",
    "name:rus_x_preferred":[
        "\u0416\u0438\u043b\u0438\u043d \u041a\u043e\u043b\u043e\u0434\u0435\u0437\u044c"
    ],
    "name:und_x_variant":[
        "Zhilin Kolodez\u2019",
        "Zhilin Kolodets"
    ],
    "wof:name":"Zhilin Kolodez'",
    "wof:placetype":"locality"
},
  "geometry": {"coordinates":[37.41589000000001,51.00091],"type":"Point"}
}