{
  "type": "Feature",
  "properties": {
    "gn:admin1_code":"60",
    "gn:asciiname":"Mamony",
    "gn:country_code":"RU",
    "gn:dem":91,
    "gn:feature_class":"P",
    "gn:feature_code":"PPL",
    "gn:name":"Mamony",
    "gn:population":0,
    "gn:timezone":"Europe/Moscow",
    "iso:country":"RU",
    "name:rus_x_preferred":[
        "\u041c\u0430\u043c\u043e\u043d\u044b"
    ],
    "wof:name":"Mamony",
    "wof:placetype":"locality"
},
  "geometry": {"coordinates":[28.35248,56.94036],"type":"Point"}
}