{
  "type": "Feature",
  "properties": {
    "gn:admin1_code":"91",
    "gn:asciiname":"Vyatka",
    "gn:country_code":"RU",
    "gn:dem":378,
    "gn:feature_class":"P",
    "gn:feature_code":"PPL",
    "gn:name":"Vyatka",
    "gn:population":0,
    "gn:timezone":"Asia/Krasnoyarsk",
    "iso:country":"RU",
    "name:eng_x_preferred":[
        "Vyatka"
    ],
    "name:nor_x_preferred":[
        "Vjatka"
    ],
    "name:rus_x_preferred":[
        "\u0412\u044f\u0442\u043a\u0430"
    ],
    "wof:name":"Vyatka",
    "wof:placetype":"locality"
},
  "geometry": {"coordinates":[94.8703,55.3462],"type":"Point"}
}