{
  "type": "Feature",
  "properties": {
    "gn:admin1_code":"41",
    "gn:asciiname":"Zhideyevka",
    "gn:country_code":"RU",
    "gn:dem":166,
    "gn:feature_class":"P",
    "gn:feature_code":"PPL",
    "gn:name":"Zhideyevka",
    "gn:population":0,
    "gn:timezone":"Europe/Moscow",
    "iso:country":"RU",
    "name:rus_x_preferred":[
        "\u0416\u0438\u0434\u0435\u0435\u0432\u043a\u0430"
    ],
    "wof:name":"Zhideyevka",
    "wof:placetype":"locality"
},
  "geometry": {"coordinates":[35.4528,52.1923],"type":"Point"}
}