{
  "type": "Feature",
  "properties": {
    "gn:admin1_code":"67",
    "gn:asciiname":"Tarakhovka",
    "gn:country_code":"RU",
    "gn:dem":148,
    "gn:feature_class":"P",
    "gn:feature_code":"PPL",
    "gn:name":"Tarakhovka",
    "gn:population":0,
    "gn:timezone":"Europe/Saratov",
    "iso:country":"RU",
    "name:eng_x_preferred":[
        "Tarakhovka"
    ],
    "name:nor_x_preferred":[
        "Tarakhovka"
    ],
    "name:rus_x_preferred":[
        "\u0422\u0430\u0440\u0430\u0445\u043e\u0432\u043a\u0430"
    ],
    "wof:name":"Tarakhovka",
    "wof:placetype":"locality"
},
  "geometry": {"coordinates":[50.75,51.73333],"type":"Point"}
}