{
  "type": "Feature",
  "properties": {
    "gn:admin1_code":"85.0",
    "gn:asciiname":"Charozero",
    "gn:country_code":"RU",
    "gn:dem":128,
    "gn:feature_class":"P",
    "gn:feature_code":"PPL",
    "gn:name":"Charozero",
    "gn:population":0,
    "gn:timezone":"Europe/Moscow",
    "iso:country":"RU",
    "name:eng_x_preferred":[
        "Charozero"
    ],
    "name:nor_x_preferred":[
        "Tsjarozero"
    ],
    "name:rus_x_preferred":[
        "\u0427\u0430\u0440\u043e\u0437\u0435\u0440\u043e"
    ],
    "wof:name":"Charozero",
    "wof:placetype":"locality"
},
  "geometry": {"coordinates":[38.6606,60.4563],"type":"Point"}
}