{
  "type": "Feature",
  "properties": {
    "gn:admin1_code":"61",
    "gn:asciiname":"Voronovo",
    "gn:country_code":"RU",
    "gn:dem":75,
    "gn:feature_class":"P",
    "gn:feature_code":"PPL",
    "gn:name":"Voronovo",
    "gn:population":0,
    "gn:timezone":"Europe/Moscow",
    "iso:country":"RU",
    "name:rus_x_preferred":[
        "\u0412\u043e\u0440\u043e\u043d\u043e\u0432\u043e"
    ],
    "name:und_x_variant":[
        "\u0412\u043e\u0440\u043e\u043d\u043e\u0432\u043e"
    ],
    "wof:name":"Voronovo",
    "wof:placetype":"locality"
},
  "geometry": {"coordinates":[40.93081,46.48139000000001],"type":"Point"}
}