{
  "type": "Feature",
  "properties": {
    "gn:admin1_code":"77",
    "gn:asciiname":"Timoshkino",
    "gn:country_code":"RU",
    "gn:dem":212,
    "gn:feature_class":"P",
    "gn:feature_code":"PPL",
    "gn:name":"Timoshkino",
    "gn:population":0,
    "gn:timezone":"Europe/Moscow",
    "iso:country":"RU",
    "name:eng_x_preferred":[
        "Timoshkino"
    ],
    "name:nor_x_preferred":[
        "Timosjkino"
    ],
    "name:rus_x_preferred":[
        "\u0422\u0438\u043c\u043e\u0448\u043a\u0438\u043d\u043e"
    ],
    "name:und_x_variant":[
        "\u0422\u0438\u043c\u043e\u0448\u043a\u0438\u043d\u043e"
    ],
    "wof:name":"Timoshkino",
    "wof:placetype":"locality"
},
  "geometry": {"coordinates":[36.93763,58.39248000000001],"type":"Point"}
}