{
  "type": "Feature",
  "properties": {
    "gn:admin1_code":"77.0",
    "gn:asciiname":"Dorki",
    "gn:country_code":"RU",
    "gn:dem":239,
    "gn:feature_class":"P",
    "gn:feature_code":"PPL",
    "gn:name":"Dorki",
    "gn:population":0,
    "gn:timezone":"Europe/Moscow",
    "iso:country":"RU",
    "name:rus_x_preferred":[
        "\u0414\u043e\u0440\u043a\u0438"
    ],
    "name:und_x_variant":[
        "\u0414\u043e\u0440\u043a\u0438"
    ],
    "wof:name":"Dorki",
    "wof:placetype":"locality"
},
  "geometry": {"coordinates":[33.58805,56.6807],"type":"Point"}
}