{
  "type": "Feature",
  "properties": {
    "gn:admin1_code":"77",
    "gn:asciiname":"Koshelevo",
    "gn:country_code":"RU",
    "gn:dem":230,
    "gn:feature_class":"P",
    "gn:feature_code":"PPL",
    "gn:name":"Koshelevo",
    "gn:population":0,
    "gn:timezone":"Europe/Moscow",
    "iso:country":"RU",
    "name:rus_x_preferred":[
        "\u041a\u043e\u0448\u0435\u043b\u0435\u0432\u043e"
    ],
    "name:und_x_variant":[
        "\u041a\u043e\u0448\u0435\u043b\u0435\u0432\u043e"
    ],
    "wof:name":"Koshelevo",
    "wof:placetype":"locality"
},
  "geometry": {"coordinates":[33.07165,56.3258],"type":"Point"}
}