{
  "type": "Feature",
  "properties": {
    "gn:admin1_code":"6",
    "gn:asciiname":"Patrakeyevka",
    "gn:country_code":"RU",
    "gn:dem":11,
    "gn:feature_class":"P",
    "gn:feature_code":"PPL",
    "gn:name":"Patrakeyevka",
    "gn:population":0,
    "gn:timezone":"Europe/Moscow",
    "iso:country":"RU",
    "name:che_x_preferred":[
        "\u041f\u0430\u0442\u0440\u0430\u043a\u0435\u0435\u0432\u043a\u0430"
    ],
    "name:eng_x_preferred":[
        "Patrakeyevka"
    ],
    "name:ita_x_preferred":[
        "Patrakeevka"
    ],
    "name:nor_x_preferred":[
        "Patrakejevka"
    ],
    "name:rus_x_preferred":[
        "\u041f\u0430\u0442\u0440\u0430\u043a\u0435\u0435\u0432\u043a\u0430"
    ],
    "name:und_x_variant":[
        "Patrakeyevskoye"
    ],
    "wof:name":"Patrakeyevka",
    "wof:placetype":"locality"
},
  "geometry": {"coordinates":[40.38639000000001,64.96278000000001],"type":"Point"}
}