{
  "type": "Feature",
  "properties": {
    "gn:admin1_code":"33.0",
    "gn:asciiname":"Skutiny",
    "gn:country_code":"RU",
    "gn:dem":147,
    "gn:feature_class":"P",
    "gn:feature_code":"PPL",
    "gn:name":"Skutiny",
    "gn:population":0,
    "gn:timezone":"Europe/Kirov",
    "iso:country":"RU",
    "name:rus_x_preferred":[
        "\u0421\u043a\u0443\u0442\u0438\u043d\u044b"
    ],
    "name:und_x_variant":[
        "Skutino",
        "Skutiny"
    ],
    "wof:name":"Skutiny",
    "wof:placetype":"locality"
},
  "geometry": {"coordinates":[48.85944,59.00556],"type":"Point"}
}