{
  "type": "Feature",
  "properties": {
    "gn:admin1_code":"65",
    "gn:asciiname":"Zarya",
    "gn:country_code":"RU",
    "gn:dem":47,
    "gn:feature_class":"P",
    "gn:feature_code":"PPL",
    "gn:name":"Zarya",
    "gn:population":0,
    "gn:timezone":"Europe/Samara",
    "iso:country":"RU",
    "name:rus_x_preferred":[
        "\u0417\u0430\u0440\u044f"
    ],
    "name:und_x_variant":[
        "Novaya Zarya",
        "Zarya"
    ],
    "wof:name":"Zarya",
    "wof:placetype":"locality"
},
  "geometry": {"coordinates":[50.29502,53.73448000000001],"type":"Point"}
}