{
  "type": "Feature",
  "properties": {
    "gn:admin1_code":"85",
    "gn:asciiname":"Zakryshkino",
    "gn:country_code":"RU",
    "gn:dem":139,
    "gn:feature_class":"P",
    "gn:feature_code":"PPL",
    "gn:name":"Zakryshkino",
    "gn:population":0,
    "gn:timezone":"Europe/Moscow",
    "iso:country":"RU",
    "name:rus_x_preferred":[
        "\u0417\u0430\u043a\u0440\u044b\u0448\u043a\u0438\u043d\u043e"
    ],
    "wof:name":"Zakryshkino",
    "wof:placetype":"locality"
},
  "geometry": {"coordinates":[39.7372,59.19473000000001],"type":"Point"}
}