{
  "type": "Feature",
  "properties": {
    "gn:admin1_code":"55.0",
    "gn:asciiname":"Aytuar",
    "gn:country_code":"RU",
    "gn:dem":174,
    "gn:feature_class":"P",
    "gn:feature_code":"PPL",
    "gn:name":"Aytuar",
    "gn:population":0,
    "gn:timezone":"Asia/Yekaterinburg",
    "iso:country":"RU",
    "name:eng_x_preferred":[
        "Aytuar"
    ],
    "name:nor_x_preferred":[
        "Ajtuar"
    ],
    "name:rus_x_preferred":[
        "\u0410\u0439\u0442\u0443\u0430\u0440"
    ],
    "name:und_x_variant":[
        "Aytuarka",
        "\u0410\u0439\u0442\u0443\u0430\u0440",
        "Aytuar"
    ],
    "wof:name":"Aytuar",
    "wof:placetype":"locality"
},
  "geometry": {"coordinates":[57.6621,51.1151],"type":"Point"}
}