{
  "type": "Feature",
  "properties": {
    "gn:admin1_code":"60",
    "gn:asciiname":"Golyashi",
    "gn:country_code":"RU",
    "gn:dem":177,
    "gn:feature_class":"P",
    "gn:feature_code":"PPL",
    "gn:name":"Golyashi",
    "gn:population":0,
    "gn:timezone":"Europe/Moscow",
    "iso:country":"RU",
    "name:rus_x_preferred":[
        "\u0413\u043e\u043b\u044f\u0448\u0438"
    ],
    "name:und_x_variant":[
        "\u0413\u043e\u043b\u044f\u0448\u0438"
    ],
    "wof:name":"Golyashi",
    "wof:placetype":"locality"
},
  "geometry": {"coordinates":[30.06667,56.18333000000001],"type":"Point"}
}