{
  "type": "Feature",
  "properties": {
    "gn:admin1_code":"88",
    "gn:asciiname":"Golyshkino",
    "gn:country_code":"RU",
    "gn:dem":126,
    "gn:feature_class":"P",
    "gn:feature_code":"PPL",
    "gn:name":"Golyshkino",
    "gn:population":0,
    "gn:timezone":"Europe/Moscow",
    "iso:country":"RU",
    "name:rus_x_preferred":[
        "\u0413\u043e\u043b\u044b\u0448\u043a\u0438\u043d\u043e"
    ],
    "wof:name":"Golyshkino",
    "wof:placetype":"locality"
},
  "geometry": {"coordinates":[38.34,57.7722],"type":"Point"}
}