{
  "type": "Feature",
  "properties": {
    "gn:admin1_code":"88.0",
    "gn:asciiname":"Retivtsevo",
    "gn:country_code":"RU",
    "gn:dem":127,
    "gn:feature_class":"P",
    "gn:feature_code":"PPL",
    "gn:name":"Retivtsevo",
    "gn:population":0,
    "gn:timezone":"Europe/Moscow",
    "iso:country":"RU",
    "name:rus_x_preferred":[
        "\u0420\u0435\u0442\u0438\u0432\u0446\u0435\u0432\u043e"
    ],
    "wof:name":"Retivtsevo",
    "wof:placetype":"locality"
},
  "geometry": {"coordinates":[40.45904,58.43119],"type":"Point"}
}