{
  "type": "Feature",
  "properties": {
    "gn:admin1_code":"29",
    "gn:asciiname":"Kokuy",
    "gn:country_code":"RU",
    "gn:dem":199,
    "gn:feature_class":"P",
    "gn:feature_code":"PPL",
    "gn:name":"Kokuy",
    "gn:population":0,
    "gn:timezone":"Asia/Novokuznetsk",
    "iso:country":"RU",
    "name:eng_x_preferred":[
        "Kokuy"
    ],
    "name:nor_x_preferred":[
        "Kokuj"
    ],
    "name:rus_x_preferred":[
        "\u041a\u043e\u043a\u0443\u0439"
    ],
    "name:und_x_variant":[
        "\u041a\u043e\u043a\u0443\u0439",
        "Kokuy"
    ],
    "wof:name":"Kokuy",
    "wof:placetype":"locality"
},
  "geometry": {"coordinates":[85.0196,55.3301],"type":"Point"}
}