{
  "type": "Feature",
  "properties": {
    "gn:admin1_code":"30",
    "gn:asciiname":"Dal'zha",
    "gn:country_code":"RU",
    "gn:dem":33,
    "gn:feature_class":"P",
    "gn:feature_code":"PPL",
    "gn:name":"Dal\u2019zha",
    "gn:population":0,
    "gn:timezone":"Asia/Vladivostok",
    "iso:country":"RU",
    "name:rus_x_preferred":[
        "\u0414\u0430\u043b\u044c\u0436\u0430"
    ],
    "name:und_x_variant":[
        "Beloryssiy",
        "Khutor Dal\u2019ta",
        "Dal\u2019zha"
    ],
    "wof:name":"Dal'zha",
    "wof:placetype":"locality"
},
  "geometry": {"coordinates":[139.46666999999999,53.06667],"type":"Point"}
}