{
  "type": "Feature",
  "properties": {
    "gn:admin1_code":"23",
    "gn:asciiname":"Shchukino",
    "gn:cc2":"RU",
    "gn:country_code":"RU",
    "gn:dem":16,
    "gn:feature_class":"P",
    "gn:feature_code":"PPL",
    "gn:name":"Shchukino",
    "gn:population":0,
    "gn:timezone":"Europe/Kaliningrad",
    "iso:country":"RU",
    "name:und_x_variant":[
        "Zandlyauken",
        "Sandfelde"
    ],
    "wof:name":"Shchukino",
    "wof:placetype":"locality"
},
  "geometry": {"coordinates":[21.77333,54.98556],"type":"Point"}
}