{
  "type": "Feature",
  "properties": {
    "gn:admin1_code":"45.0",
    "gn:asciiname":"Lepeshkino",
    "gn:country_code":"RU",
    "gn:dem":161,
    "gn:feature_class":"P",
    "gn:feature_code":"PPL",
    "gn:name":"Lepeshkino",
    "gn:population":0,
    "gn:timezone":"Europe/Moscow",
    "iso:country":"RU",
    "name:rus_x_preferred":[
        "\u041b\u0435\u043f\u0435\u0448\u043a\u0438\u043d\u043e"
    ],
    "wof:name":"Lepeshkino",
    "wof:placetype":"locality"
},
  "geometry": {"coordinates":[49.09194,56.95417],"type":"Point"}
}