{
  "type": "Feature",
  "properties": {
    "gn:admin1_code":"12.0",
    "gn:asciiname":"Aslanbek-Sheripovo",
    "gn:country_code":"RU",
    "gn:dem":971,
    "gn:feature_class":"P",
    "gn:feature_code":"PPL",
    "gn:name":"Aslanbek-Sheripovo",
    "gn:population":0,
    "gn:timezone":"Europe/Moscow",
    "iso:country":"RU",
    "name:che_x_preferred":[
        "Aslanbek-\u015eeripovo"
    ],
    "name:che_x_variant":[
        "Gaten-Kale",
        "\u0120\u00e4ttin-Qelli",
        "Solne\u00e7noe",
        "\u0413\u0430\u0442\u0435\u043d-\u041a\u0430\u043b\u0435",
        "\u0413\u0406\u0430\u044c\u0442\u0442\u0438\u043d-\u041a\u0445\u0435\u043b\u043b\u0438",
        "\u0421\u043e\u043b\u043d\u0435\u0447\u043d\u043e\u0435"
    ],
    "name:nor_x_preferred":[
        "Aslanbek-Sjeripovo"
    ],
    "name:rus_x_preferred":[
        "\u0410\u0441\u043b\u0430\u043d\u0431\u0435\u043a-\u0428\u0435\u0440\u0438\u043f\u043e\u0432\u043e"
    ],
    "name:rus_x_variant":[
        "Aslanbek-\u0160eripovo",
        "\u0413\u0430\u0442\u044b\u043d-\u041a\u0430\u043b\u0435"
    ],
    "name:und_x_variant":[
        "Solnechnoye",
        "Aslambek-Sheripovo",
        "Aslanbek-Sheripovo",
        "Gatyn-Kale"
    ],
    "wof:name":"Aslanbek-Sheripovo",
    "wof:placetype":"locality"
},
  "geometry": {"coordinates":[45.75415,42.84284],"type":"Point"}
}