{
  "type": "Feature",
  "properties": {
    "gn:admin1_code":"30",
    "gn:asciiname":"Nizhnyaya Gavan'",
    "gn:country_code":"RU",
    "gn:dem":24,
    "gn:feature_class":"P",
    "gn:feature_code":"PPL",
    "gn:name":"Nizhnyaya Gavan\u2019",
    "gn:population":0,
    "gn:timezone":"Asia/Vladivostok",
    "iso:country":"RU",
    "name:rus_x_preferred":[
        "\u041d\u0438\u0436\u043d\u044f\u044f \u0413\u0430\u0432\u0430\u043d\u044c"
    ],
    "name:und_x_variant":[
        "Gavan\u2019",
        "Nizhnyaya Gavan\u2019"
    ],
    "wof:name":"Nizhnyaya Gavan'",
    "wof:placetype":"locality"
},
  "geometry": {"coordinates":[140.42373999999998,52.44019],"type":"Point"}
}