{
  "type": "Feature",
  "properties": {
    "gn:admin1_code":"38.0",
    "gn:asciiname":"Beysuzhek Vtoroy",
    "gn:country_code":"RU",
    "gn:dem":47,
    "gn:feature_class":"P",
    "gn:feature_code":"PPL",
    "gn:name":"Beysuzhek Vtoroy",
    "gn:population":0,
    "gn:timezone":"Europe/Moscow",
    "iso:country":"RU",
    "name:nor_x_preferred":[
        "Bejsuzjek Vtoroj"
    ],
    "name:rus_x_preferred":[
        "\u0411\u0435\u0439\u0441\u0443\u0436\u0435\u043a \u0412\u0442\u043e\u0440\u043e\u0439"
    ],
    "wof:name":"Beysuzhek Vtoroy",
    "wof:placetype":"locality"
},
  "geometry": {"coordinates":[39.74047,45.48604],"type":"Point"}
}