{
  "type": "Feature",
  "properties": {
    "gn:admin1_code":"55",
    "gn:asciiname":"Vanyushino",
    "gn:country_code":"RU",
    "gn:dem":286,
    "gn:feature_class":"P",
    "gn:feature_code":"PPL",
    "gn:name":"Vanyushino",
    "gn:population":0,
    "gn:timezone":"Asia/Yekaterinburg",
    "iso:country":"RU",
    "name:rus_x_preferred":[
        "\u0412\u0430\u043d\u044e\u0448\u0438\u043d\u043e"
    ],
    "wof:name":"Vanyushino",
    "wof:placetype":"locality"
},
  "geometry": {"coordinates":[54.83333,53.15],"type":"Point"}
}