{
  "type": "Feature",
  "properties": {
    "gn:admin1_code":"51",
    "gn:asciiname":"Umay",
    "gn:country_code":"RU",
    "gn:dem":101,
    "gn:feature_class":"P",
    "gn:feature_code":"PPL",
    "gn:name":"Umay",
    "gn:population":0,
    "gn:timezone":"Europe/Moscow",
    "iso:country":"RU",
    "name:eng_x_preferred":[
        "Umay"
    ],
    "name:nor_x_preferred":[
        "Umaj"
    ],
    "name:rus_x_preferred":[
        "\u0423\u043c\u0430\u0439"
    ],
    "name:und_x_variant":[
        "Umai",
        "Umay"
    ],
    "wof:name":"Umay",
    "wof:placetype":"locality"
},
  "geometry": {"coordinates":[44.33731,55.45652],"type":"Point"}
}