{
  "type": "Feature",
  "properties": {
    "gn:admin1_code":"51",
    "gn:asciiname":"Umay",
    "gn:country_code":"RU",
    "gn:dem":101,
    "gn:feature_class":"P",
    "gn:feature_code":"PPL",
    "gn:name":"Umay",
    "gn:population":0,
    "gn:timezone":"Europe/Moscow",
    "iso:country":"RU",
    "name:azb_x_preferred":[
        "\u0627\u0648\u0645\u0627\u06cc"
    ],
    "name:aze_x_preferred":[
        "Umay"
    ],
    "name:cat_x_preferred":[
        "Umai"
    ],
    "name:deu_x_preferred":[
        "Umay"
    ],
    "name:eng_x_preferred":[
        "Umay"
    ],
    "name:kaz_x_preferred":[
        "\u04b0\u043c\u0430\u0439 \u0430\u043d\u0430"
    ],
    "name:kir_x_preferred":[
        "\u0423\u043c\u0430\u0439 \u044d\u043d\u0435"
    ],
    "name:nor_x_preferred":[
        "Umaj"
    ],
    "name:rus_x_preferred":[
        "\u0423\u043c\u0430\u0439"
    ],
    "name:sco_x_preferred":[
        "Umay"
    ],
    "name:slv_x_preferred":[
        "Umaj"
    ],
    "name:spa_x_preferred":[
        "Umai"
    ],
    "name:tur_x_preferred":[
        "Umay"
    ],
    "wof:name":"Umay",
    "wof:placetype":"locality"
},
  "geometry": {"coordinates":[44.33731,55.45652],"type":"Point"}
}