{
  "type": "Feature",
  "properties": {
    "gn:admin1_code":"60",
    "gn:asciiname":"Kolomnitsa",
    "gn:country_code":"RU",
    "gn:dem":53,
    "gn:feature_class":"P",
    "gn:feature_code":"PPL",
    "gn:name":"Kolomnitsa",
    "gn:population":0,
    "gn:timezone":"Europe/Moscow",
    "iso:country":"RU",
    "name:rus_x_preferred":[
        "\u041a\u043e\u043b\u043e\u043c\u043d\u0438\u0446\u0430"
    ],
    "wof:name":"Kolomnitsa",
    "wof:placetype":"locality"
},
  "geometry": {"coordinates":[28.18877,57.41837],"type":"Point"}
}