{
  "type": "Feature",
  "properties": {
    "gn:admin1_code":"85.0",
    "gn:asciiname":"Bakulino",
    "gn:country_code":"RU",
    "gn:dem":152,
    "gn:feature_class":"P",
    "gn:feature_code":"PPL",
    "gn:name":"Bakulino",
    "gn:population":0,
    "gn:timezone":"Europe/Moscow",
    "iso:country":"RU",
    "name:nor_x_preferred":[
        "Bakulino"
    ],
    "name:rus_x_preferred":[
        "\u0411\u0430\u043a\u0443\u043b\u0438\u043d\u043e"
    ],
    "wof:name":"Bakulino",
    "wof:placetype":"locality"
},
  "geometry": {"coordinates":[40.06058,59.68012],"type":"Point"}
}