{
  "type": "Feature",
  "properties": {
    "gn:admin1_code":"37",
    "gn:asciiname":"Petrushenki",
    "gn:country_code":"RU",
    "gn:dem":138,
    "gn:feature_class":"P",
    "gn:feature_code":"PPL",
    "gn:name":"Petrushenki",
    "gn:population":0,
    "gn:timezone":"Europe/Moscow",
    "iso:country":"RU",
    "name:rus_x_preferred":[
        "\u041f\u0435\u0442\u0440\u0443\u0448\u0435\u043d\u043a\u0438"
    ],
    "name:und_x_variant":[
        "\u041f\u0435\u0442\u0440\u0443\u0448\u0435\u043d\u043a\u0438"
    ],
    "wof:name":"Petrushenki",
    "wof:placetype":"locality"
},
  "geometry": {"coordinates":[46.7151,59.159],"type":"Point"}
}