{
  "type": "Feature",
  "properties": {
    "gn:admin1_code":"16",
    "gn:asciiname":"Burtasy",
    "gn:country_code":"RU",
    "gn:dem":152,
    "gn:feature_class":"P",
    "gn:feature_code":"PPL",
    "gn:name":"Burtasy",
    "gn:population":0,
    "gn:timezone":"Europe/Moscow",
    "iso:country":"RU",
    "name:eng_x_preferred":[
        "Burtasy"
    ],
    "name:nor_x_preferred":[
        "Burtasy"
    ],
    "name:rus_x_preferred":[
        "\u0411\u0443\u0440\u0442\u0430\u0441\u044b"
    ],
    "name:und_x_variant":[
        "Toldy-Burtasy",
        "Burdasy"
    ],
    "wof:name":"Burtasy",
    "wof:placetype":"locality"
},
  "geometry": {"coordinates":[46.86017,55.49895],"type":"Point"}
}