{
  "type": "Feature",
  "properties": {
    "gn:admin1_code":"52.0",
    "gn:asciiname":"Drunikha",
    "gn:country_code":"RU",
    "gn:dem":91,
    "gn:feature_class":"P",
    "gn:feature_code":"PPL",
    "gn:name":"Drunikha",
    "gn:population":0,
    "gn:timezone":"Europe/Moscow",
    "iso:country":"RU",
    "name:rus_x_preferred":[
        "\u0414\u0440\u0443\u043d\u0438\u0445\u0430"
    ],
    "wof:name":"Drunikha",
    "wof:placetype":"locality"
},
  "geometry": {"coordinates":[30.83983,57.41333],"type":"Point"}
}