{
  "type": "Feature",
  "properties": {
    "gn:admin1_code":"51",
    "gn:asciiname":"Staryye Klyuchishchi",
    "gn:country_code":"RU",
    "gn:dem":101,
    "gn:feature_class":"P",
    "gn:feature_code":"PPL",
    "gn:name":"Staryye Klyuchishchi",
    "gn:population":0,
    "gn:timezone":"Europe/Moscow",
    "iso:country":"RU",
    "name:rus_x_preferred":[
        "\u0421\u0442\u0430\u0440\u044b\u0435 \u041a\u043b\u044e\u0447\u0438\u0449\u0438"
    ],
    "name:und_x_variant":[
        "Klyuchishchi",
        "Staryye Klyuchishchi"
    ],
    "wof:name":"Staryye Klyuchishchi",
    "wof:placetype":"locality"
},
  "geometry": {"coordinates":[44.22367,56.0088],"type":"Point"}
}