{
  "type": "Feature",
  "properties": {
    "gn:admin1_code":"60",
    "gn:asciiname":"Dymovo",
    "gn:country_code":"RU",
    "gn:dem":70,
    "gn:feature_class":"P",
    "gn:feature_code":"PPL",
    "gn:name":"Dymovo",
    "gn:population":0,
    "gn:timezone":"Europe/Moscow",
    "iso:country":"RU",
    "name:rus_x_preferred":[
        "\u0414\u044b\u043c\u043e\u0432\u043e"
    ],
    "wof:name":"Dymovo",
    "wof:placetype":"locality"
},
  "geometry": {"coordinates":[28.7972,57.49012],"type":"Point"}
}