{
  "type": "Feature",
  "properties": {
    "gn:admin1_code":"52",
    "gn:asciiname":"Maloye Zaborov'ye",
    "gn:country_code":"RU",
    "gn:dem":47,
    "gn:feature_class":"P",
    "gn:feature_code":"PPL",
    "gn:name":"Maloye Zaborov\u2019ye",
    "gn:population":0,
    "gn:timezone":"Europe/Moscow",
    "iso:country":"RU",
    "name:rus_x_preferred":[
        "\u041c\u0430\u043b\u043e\u0435 \u0417\u0430\u0431\u043e\u0440\u043e\u0432\u044c\u0435"
    ],
    "name:und_x_variant":[
        "Maloye Zaborov\u2019ye"
    ],
    "wof:name":"Maloye Zaborov'ye",
    "wof:placetype":"locality"
},
  "geometry": {"coordinates":[30.23631,58.11346],"type":"Point"}
}