{
  "type": "Feature",
  "properties": {
    "gn:admin1_code":"88",
    "gn:asciiname":"Likhinino",
    "gn:country_code":"RU",
    "gn:dem":134,
    "gn:feature_class":"P",
    "gn:feature_code":"PPL",
    "gn:name":"Likhinino",
    "gn:population":0,
    "gn:timezone":"Europe/Moscow",
    "iso:country":"RU",
    "name:rus_x_preferred":[
        "\u041b\u0438\u0445\u0438\u043d\u0438\u043d\u043e"
    ],
    "wof:name":"Likhinino",
    "wof:placetype":"locality"
},
  "geometry": {"coordinates":[39.062,57.68104],"type":"Point"}
}