{
  "type": "Feature",
  "properties": {
    "gn:admin1_code":"53",
    "gn:asciiname":"Rassolkino",
    "gn:cc2":"RU",
    "gn:country_code":"RU",
    "gn:dem":247,
    "gn:feature_class":"P",
    "gn:feature_code":"PPL",
    "gn:name":"Rassolkino",
    "gn:population":0,
    "gn:timezone":"Asia/Novosibirsk",
    "iso:country":"RU",
    "name:eng_x_preferred":[
        "Rassolkino"
    ],
    "name:nor_x_preferred":[
        "Rassolkino"
    ],
    "name:rus_x_preferred":[
        "\u0420\u0430\u0441\u0441\u043e\u043b\u043a\u0438\u043d\u043e"
    ],
    "name:und_x_variant":[
        "Rassolkina",
        "Rassolino",
        "\u0420\u0430\u0441\u0441\u043e\u043b\u043a\u0438\u043d\u043e",
        "Rassolkino"
    ],
    "wof:name":"Rassolkino",
    "wof:placetype":"locality"
},
  "geometry": {"coordinates":[84.43333,54.85],"type":"Point"}
}