{
  "type": "Feature",
  "properties": {
    "gn:admin1_code":"32",
    "gn:asciiname":"Ush'ya",
    "gn:country_code":"RU",
    "gn:dem":42,
    "gn:feature_class":"P",
    "gn:feature_code":"PPL",
    "gn:name":"Ush\u2019ya",
    "gn:population":0,
    "gn:timezone":"Asia/Yekaterinburg",
    "iso:country":"RU",
    "name:eng_x_preferred":[
        "Ush'ya"
    ],
    "name:nor_x_preferred":[
        "Usja"
    ],
    "name:rus_x_preferred":[
        "\u0423\u0448\u044c\u044f"
    ],
    "name:und_x_variant":[
        "Ush\u2019ya"
    ],
    "wof:name":"Ush'ya",
    "wof:placetype":"locality"
},
  "geometry": {"coordinates":[64.47105999999999,60.22026],"type":"Point"}
}