{
  "type": "Feature",
  "properties": {
    "gn:admin1_code":"21",
    "gn:asciiname":"Strelkovo",
    "gn:country_code":"RU",
    "gn:dem":146,
    "gn:feature_class":"P",
    "gn:feature_code":"PPL",
    "gn:name":"Strelkovo",
    "gn:population":0,
    "gn:timezone":"Europe/Moscow",
    "iso:country":"RU",
    "name:und_x_variant":[
        "Strelkovo Vtoroye",
        "Strelkovo"
    ],
    "wof:name":"Strelkovo",
    "wof:placetype":"locality"
},
  "geometry": {"coordinates":[40.73366,57.09802],"type":"Point"}
}