{
  "type": "Feature",
  "properties": {
    "gn:admin1_code":"76",
    "gn:asciiname":"Palushkin",
    "gn:country_code":"RU",
    "gn:dem":237,
    "gn:feature_class":"P",
    "gn:feature_code":"PPL",
    "gn:name":"Palushkin",
    "gn:population":0,
    "gn:timezone":"Europe/Moscow",
    "iso:country":"RU",
    "wof:name":"Palushkin",
    "wof:placetype":"locality"
},
  "geometry": {"coordinates":[38.29083,53.08639],"type":"Point"}
}