{
  "type": "Feature",
  "properties": {
    "gn:admin1_code":"59",
    "gn:asciiname":"Venevitinovo",
    "gn:country_code":"RU",
    "gn:dem":16,
    "gn:feature_class":"P",
    "gn:feature_code":"PPL",
    "gn:name":"Venevitinovo",
    "gn:population":85,
    "gn:timezone":"Asia/Vladivostok",
    "iso:country":"RU",
    "name:rus_x_preferred":[
        "\u0412\u0435\u043d\u0435\u0432\u0438\u0442\u0438\u043d\u043e\u0432\u043e"
    ],
    "name:und_x_variant":[
        "Isayeva",
        "Venevitinovo"
    ],
    "wof:name":"Venevitinovo",
    "wof:placetype":"locality",
    "wof:population":85
},
  "geometry": {"coordinates":[131.7457,43.42086],"type":"Point"}
}