{
  "type": "Feature",
  "properties": {
    "gn:admin1_code":"60",
    "gn:asciiname":"Kapalygino",
    "gn:country_code":"RU",
    "gn:dem":103,
    "gn:feature_class":"P",
    "gn:feature_code":"PPL",
    "gn:name":"Kapalygino",
    "gn:population":0,
    "gn:timezone":"Europe/Moscow",
    "iso:country":"RU",
    "name:rus_x_preferred":[
        "\u041a\u0430\u043f\u0430\u043b\u044b\u0433\u0438\u043d\u043e"
    ],
    "wof:name":"Kapalygino",
    "wof:placetype":"locality"
},
  "geometry": {"coordinates":[30.16667,57.03333000000001],"type":"Point"}
}