{
  "type": "Feature",
  "properties": {
    "gn:admin1_code":"77",
    "gn:asciiname":"Kozlikha",
    "gn:country_code":"RU",
    "gn:dem":146,
    "gn:feature_class":"P",
    "gn:feature_code":"PPL",
    "gn:name":"Kozlikha",
    "gn:population":0,
    "gn:timezone":"Europe/Moscow",
    "iso:country":"RU",
    "name:rus_x_preferred":[
        "\u041a\u043e\u0437\u043b\u0438\u0445\u0430"
    ],
    "wof:name":"Kozlikha",
    "wof:placetype":"locality"
},
  "geometry": {"coordinates":[37.4689,57.6148],"type":"Point"}
}