{
  "type": "Feature",
  "properties": {
    "gn:admin1_code":"56",
    "gn:asciiname":"Sutolka",
    "gn:country_code":"RU",
    "gn:dem":249,
    "gn:feature_class":"P",
    "gn:feature_code":"PPL",
    "gn:name":"Sutolka",
    "gn:population":0,
    "gn:timezone":"Europe/Moscow",
    "iso:country":"RU",
    "name:rus_x_preferred":[
        "\u0421\u0443\u0442\u043e\u043b\u043a\u0430"
    ],
    "name:und_x_variant":[
        "\u0421\u0443\u0442\u043e\u043b\u043a\u0430"
    ],
    "wof:name":"Sutolka",
    "wof:placetype":"locality"
},
  "geometry": {"coordinates":[36.97252,52.87586],"type":"Point"}
}