{
  "type": "Feature",
  "properties": {
    "gn:admin1_code":"8",
    "gn:asciiname":"Mokhovoye Boloto",
    "gn:country_code":"RU",
    "gn:dem":300,
    "gn:feature_class":"P",
    "gn:feature_code":"PPL",
    "gn:name":"Mokhovoye Boloto",
    "gn:population":0,
    "gn:timezone":"Asia/Yekaterinburg",
    "iso:country":"RU",
    "name:rus_x_preferred":[
        "\u041c\u043e\u0445\u043e\u0432\u043e\u0435 \u0411\u043e\u043b\u043e\u0442\u043e"
    ],
    "name:und_x_variant":[
        "\u041c\u043e\u0445\u043e\u0432\u043e\u0435 \u0411\u043e\u043b\u043e\u0442\u043e"
    ],
    "wof:name":"Mokhovoye Boloto",
    "wof:placetype":"locality"
},
  "geometry": {"coordinates":[53.92653000000001,54.12243],"type":"Point"}
}