{
  "type": "Feature",
  "properties": {
    "gn:admin1_code":"53",
    "gn:asciiname":"Shilovo-Kur'ya",
    "gn:country_code":"RU",
    "gn:dem":112,
    "gn:feature_class":"P",
    "gn:feature_code":"PPL",
    "gn:name":"Shilovo-Kur\u2019ya",
    "gn:population":0,
    "gn:timezone":"Asia/Novosibirsk",
    "iso:country":"RU",
    "name:eng_x_preferred":[
        "Shilovo-Kur'ya"
    ],
    "name:nor_x_preferred":[
        "Sjilovo-Kurja"
    ],
    "name:rus_x_preferred":[
        "\u0428\u0438\u043b\u043e\u0432\u043e-\u041a\u0443\u0440\u044c\u044f"
    ],
    "name:und_x_variant":[
        "Shilova",
        "Shilovo-Kur\u2019ya"
    ],
    "wof:name":"Shilovo-Kur'ya",
    "wof:placetype":"locality"
},
  "geometry": {"coordinates":[78.18213,53.8075],"type":"Point"}
}