{
  "type": "Feature",
  "properties": {
    "gn:admin1_code":"40",
    "gn:asciiname":"Chekalina",
    "gn:country_code":"RU",
    "gn:dem":103,
    "gn:feature_class":"P",
    "gn:feature_code":"PPL",
    "gn:name":"Chekalina",
    "gn:population":0,
    "gn:timezone":"Asia/Yekaterinburg",
    "iso:country":"RU",
    "name:rus_x_preferred":[
        "\u0427\u0435\u043a\u0430\u043b\u0438\u043d\u0430"
    ],
    "name:und_x_variant":[
        "\u0427\u0435\u043a\u0430\u043b\u0438\u043d\u0430"
    ],
    "wof:name":"Chekalina",
    "wof:placetype":"locality"
},
  "geometry": {"coordinates":[64.71250000000001,56.5114],"type":"Point"}
}