{
  "type": "Feature",
  "properties": {
    "gn:admin1_code":"75",
    "gn:asciiname":"Novokorotkino",
    "gn:country_code":"RU",
    "gn:dem":80,
    "gn:feature_class":"P",
    "gn:feature_code":"PPL",
    "gn:name":"Novokorotkino",
    "gn:population":0,
    "gn:timezone":"Asia/Tomsk",
    "iso:country":"RU",
    "name:rus_x_preferred":[
        "\u041d\u043e\u0432\u043e\u043a\u043e\u0440\u043e\u0442\u043a\u0438\u043d\u043e"
    ],
    "wof:name":"Novokorotkino",
    "wof:placetype":"locality"
},
  "geometry": {"coordinates":[82.87430000000001,58.0053],"type":"Point"}
}