{
  "type": "Feature",
  "properties": {
    "gn:admin1_code":"69",
    "gn:asciiname":"Fed'kovo",
    "gn:country_code":"RU",
    "gn:dem":209,
    "gn:feature_class":"P",
    "gn:feature_code":"PPL",
    "gn:name":"Fed\u2019kovo",
    "gn:population":0,
    "gn:timezone":"Europe/Moscow",
    "iso:country":"RU",
    "name:rus_x_preferred":[
        "\u0424\u0435\u0434\u044c\u043a\u043e\u0432\u043e"
    ],
    "name:und_x_variant":[
        "Fed\u2019kovo"
    ],
    "wof:name":"Fed'kovo",
    "wof:placetype":"locality"
},
  "geometry": {"coordinates":[35.01028,55.23667],"type":"Point"}
}