{
  "type": "Feature",
  "properties": {
    "gn:country":"RU",
    "gn:fcode":"PPL",
    "gn:pop":4331,
    "iso:country":"RU",
    "name:ara_x_preferred":[
        "\u063a\u0627\u064a\u0646\u064a\u060c \u0643\u0648\u0645\u064a-\u0628\u064a\u0631\u0645\u062c\u0627\u0643"
    ],
    "name:arm_x_preferred":[
        "\u0533\u0561\u0575\u0576\u056b"
    ],
    "name:che_x_preferred":[
        "\u0413\u0430\u0439\u043d\u044b"
    ],
    "name:dut_x_preferred":[
        "Gayny"
    ],
    "name:eng_x_preferred":[
        "Gayny"
    ],
    "name:fin_x_preferred":[
        "Gainy"
    ],
    "name:hun_x_preferred":[
        "Gajni"
    ],
    "name:ita_x_preferred":[
        "Gajny"
    ],
    "name:koi_x_preferred":[
        "\u0413\u0430\u0439\u043d\u0430"
    ],
    "name:rus_x_preferred":[
        "\u0413\u0430\u0438\u043d\u044b"
    ],
    "name:rus_x_variant":[
        "\u0413\u0430\u0439\u043d\u044b"
    ],
    "name:tat_x_preferred":[
        "\u0413\u0430\u0439\u043d\u04d9"
    ],
    "name:unk_x_variant":[
        "Gainskoje"
    ],
    "qs:name":"Gayny",
    "qs:photos_9r":0,
    "qs:photos_sr":0,
    "qs:pop_sr":"4",
    "wd:wordcount":34,
    "wof:name":"Gayny",
    "wof:placetype":"locality",
    "wof:population":4331
},
  "geometry": {"coordinates":[54.32412,60.30707],"type":"Point"}
}