{
  "type": "Feature",
  "properties": {
    "gn:admin1_code":"69",
    "gn:asciiname":"Ilyushkino",
    "gn:country_code":"RU",
    "gn:dem":228,
    "gn:feature_class":"P",
    "gn:feature_code":"PPL",
    "gn:name":"Ilyushkino",
    "gn:population":0,
    "gn:timezone":"Europe/Moscow",
    "iso:country":"RU",
    "name:rus_x_preferred":[
        "\u0418\u043b\u044e\u0448\u043a\u0438\u043d\u043e"
    ],
    "name:und_x_variant":[
        "\u0418\u043b\u044e\u0448\u043a\u0438\u043d\u043e"
    ],
    "wof:name":"Ilyushkino",
    "wof:placetype":"locality"
},
  "geometry": {"coordinates":[33.79481,55.79505],"type":"Point"}
}