{
  "type": "Feature",
  "properties": {
    "gn:admin1_code":"37",
    "gn:asciiname":"Yakunintsy",
    "gn:country_code":"RU",
    "gn:dem":182,
    "gn:feature_class":"P",
    "gn:feature_code":"PPL",
    "gn:name":"Yakunintsy",
    "gn:population":0,
    "gn:timezone":"Europe/Moscow",
    "iso:country":"RU",
    "name:rus_x_preferred":[
        "\u042f\u043a\u0443\u043d\u0438\u043d\u0446\u044b"
    ],
    "name:und_x_variant":[
        "\u042f\u043a\u0443\u043d\u0438\u043d\u0446\u044b"
    ],
    "wof:name":"Yakunintsy",
    "wof:placetype":"locality"
},
  "geometry": {"coordinates":[46.92,59.0698],"type":"Point"}
}