{
  "type": "Feature",
  "properties": {
    "gn:admin1_code":"72",
    "gn:asciiname":"Yekaterinino",
    "gn:country_code":"RU",
    "gn:dem":142,
    "gn:feature_class":"P",
    "gn:feature_code":"PPL",
    "gn:name":"Yekaterinino",
    "gn:population":0,
    "gn:timezone":"Europe/Moscow",
    "iso:country":"RU",
    "name:eng_x_preferred":[
        "Yekaterinino"
    ],
    "name:nor_x_preferred":[
        "Jekaterinino"
    ],
    "name:rus_x_preferred":[
        "\u0415\u043a\u0430\u0442\u0435\u0440\u0438\u043d\u0438\u043d\u043e"
    ],
    "wof:name":"Yekaterinino",
    "wof:placetype":"locality"
},
  "geometry": {"coordinates":[40.836,52.9904],"type":"Point"}
}