{
  "type": "Feature",
  "properties": {
    "gn:admin1_code":"77",
    "gn:asciiname":"Golovkovo",
    "gn:country_code":"RU",
    "gn:dem":120,
    "gn:feature_class":"P",
    "gn:feature_code":"PPL",
    "gn:name":"Golovkovo",
    "gn:population":0,
    "gn:timezone":"Europe/Moscow",
    "iso:country":"RU",
    "name:rus_x_preferred":[
        "\u0413\u043e\u043b\u043e\u0432\u043a\u043e\u0432\u043e"
    ],
    "name:und_x_variant":[
        "\u0413\u043e\u043b\u043e\u0432\u043a\u043e\u0432\u043e"
    ],
    "wof:name":"Golovkovo",
    "wof:placetype":"locality"
},
  "geometry": {"coordinates":[38.1041,57.0539],"type":"Point"}
}