{
  "type": "Feature",
  "properties": {
    "gn:admin1_code":"76",
    "gn:asciiname":"Yasnyy",
    "gn:country_code":"RU",
    "gn:dem":204,
    "gn:feature_class":"P",
    "gn:feature_code":"PPL",
    "gn:name":"Yasnyy",
    "gn:population":0,
    "gn:timezone":"Europe/Moscow",
    "iso:country":"RU",
    "name:rus_x_preferred":[
        "\u042f\u0441\u043d\u044b\u0439"
    ],
    "wof:name":"Yasnyy",
    "wof:placetype":"locality"
},
  "geometry": {"coordinates":[38.6324,53.96957],"type":"Point"}
}