{
  "type": "Feature",
  "properties": {
    "gn:admin1_code":"56",
    "gn:asciiname":"Verkhnyaya Fedotovka",
    "gn:cc2":"RU",
    "gn:country_code":"RU",
    "gn:dem":199,
    "gn:feature_class":"P",
    "gn:feature_code":"PPL",
    "gn:name":"Verkhnyaya Fedotovka",
    "gn:population":0,
    "gn:timezone":"Europe/Moscow",
    "iso:country":"RU",
    "name:und_x_variant":[
        "Ivanovskoye",
        "Verkhnyaya Fedotovka"
    ],
    "wof:name":"Verkhnyaya Fedotovka",
    "wof:placetype":"locality"
},
  "geometry": {"coordinates":[35.64139,52.74611],"type":"Point"}
}