{
  "type": "Feature",
  "properties": {
    "gn:admin1_code":"80",
    "gn:asciiname":"Verkhnyaya Yus'",
    "gn:country_code":"RU",
    "gn:dem":117,
    "gn:feature_class":"P",
    "gn:feature_code":"PPL",
    "gn:name":"Verkhnyaya Yus\u2019",
    "gn:population":0,
    "gn:timezone":"Europe/Samara",
    "iso:country":"RU",
    "name:und_x_variant":[
        "Russkaya Yus\u2019",
        "Verkhniy Yus-Russkiy",
        "Verkhnyaya Yus\u2019"
    ],
    "wof:name":"Verkhnyaya Yus'",
    "wof:placetype":"locality"
},
  "geometry": {"coordinates":[51.78934,56.99641],"type":"Point"}
}