{
  "type": "Feature",
  "properties": {
    "gn:admin1_code":"27.0",
    "gn:asciiname":"Dzhegonas",
    "gn:country_code":"RU",
    "gn:dem":1072,
    "gn:feature_class":"P",
    "gn:feature_code":"PPL",
    "gn:name":"Dzhegonas",
    "gn:population":0,
    "gn:timezone":"Europe/Moscow",
    "iso:country":"RU",
    "name:rus_x_preferred":[
        "\u0414\u0436\u0435\u0433\u043e\u043d\u0430\u0441"
    ],
    "name:und_x_variant":[
        "\u0414\u0436\u0435\u0433\u043e\u043d\u0430\u0441"
    ],
    "wof:name":"Dzhegonas",
    "wof:placetype":"locality"
},
  "geometry": {"coordinates":[42.17194,44.0475],"type":"Point"}
}