{
  "type": "Feature",
  "properties": {
    "gn:admin1_code":"29",
    "gn:asciiname":"Nizhnyaya Taymenka",
    "gn:country_code":"RU",
    "gn:dem":108,
    "gn:feature_class":"P",
    "gn:feature_code":"PPL",
    "gn:name":"Nizhnyaya Taymenka",
    "gn:population":0,
    "gn:timezone":"Asia/Novokuznetsk",
    "iso:country":"RU",
    "name:rus_x_preferred":[
        "\u041d\u0438\u0436\u043d\u044f\u044f \u0422\u0430\u0439\u043c\u0435\u043d\u043a\u0430"
    ],
    "name:und_x_variant":[
        "Malaya Taymenka",
        "Nizhnyaya Taymenka",
        "\u041d\u0438\u0436\u043d\u044f\u044f \u0422\u0430\u0439\u043c\u0435\u043d\u043a\u0430"
    ],
    "wof:name":"Nizhnyaya Taymenka",
    "wof:placetype":"locality"
},
  "geometry": {"coordinates":[85.22029999999999,55.6708],"type":"Point"}
}