{
  "type": "Feature",
  "properties": {
    "gn:admin1_code":"88.0",
    "gn:asciiname":"Berendyaki",
    "gn:country_code":"RU",
    "gn:dem":129,
    "gn:feature_class":"P",
    "gn:feature_code":"PPL",
    "gn:name":"Berendyaki",
    "gn:population":0,
    "gn:timezone":"Europe/Moscow",
    "iso:country":"RU",
    "name:eng_x_preferred":[
        "Berendyaki"
    ],
    "name:nor_x_preferred":[
        "Berendjaki"
    ],
    "name:rus_x_preferred":[
        "\u0411\u0435\u0440\u0435\u043d\u0434\u044f\u043a\u0438"
    ],
    "wof:name":"Berendyaki",
    "wof:placetype":"locality"
},
  "geometry": {"coordinates":[39.38102,58.78271],"type":"Point"}
}