{
  "type": "Feature",
  "properties": {
    "gn:admin1_code":"70.0",
    "gn:asciiname":"Artezian-Mangit",
    "gn:country_code":"RU",
    "gn:dem":83,
    "gn:feature_class":"P",
    "gn:feature_code":"PPL",
    "gn:name":"Artezian-Mangit",
    "gn:population":0,
    "gn:timezone":"Europe/Moscow",
    "iso:country":"RU",
    "name:nor_x_preferred":[
        "Artezian-Mangit"
    ],
    "name:rus_x_preferred":[
        "\u0410\u0440\u0442\u0435\u0437\u0438\u0430\u043d-\u041c\u0430\u043d\u0433\u0438\u0442"
    ],
    "wof:name":"Artezian-Mangit",
    "wof:placetype":"locality"
},
  "geometry": {"coordinates":[44.76083,44.50944000000001],"type":"Point"}
}