{
  "type": "Feature",
  "properties": {
    "gn:admin1_code":"38.0",
    "gn:asciiname":"Kislovodskiy",
    "gn:country_code":"RU",
    "gn:dem":543,
    "gn:feature_class":"P",
    "gn:feature_code":"PPL",
    "gn:name":"Kislovodskiy",
    "gn:population":0,
    "gn:timezone":"Europe/Moscow",
    "iso:country":"RU",
    "wof:name":"Kislovodskiy",
    "wof:placetype":"locality"
},
  "geometry": {"coordinates":[41.5075,44.26778],"type":"Point"}
}