{
  "type": "Feature",
  "properties": {
    "gn:admin1_code":"85.0",
    "gn:asciiname":"Daraukha",
    "gn:country_code":"RU",
    "gn:dem":209,
    "gn:feature_class":"P",
    "gn:feature_code":"PPL",
    "gn:name":"Daraukha",
    "gn:population":0,
    "gn:timezone":"Europe/Moscow",
    "iso:country":"RU",
    "name:rus_x_preferred":[
        "\u0414\u0430\u0440\u0430\u0443\u0445\u0430"
    ],
    "wof:name":"Daraukha",
    "wof:placetype":"locality"
},
  "geometry": {"coordinates":[38.36667,58.86666999999999],"type":"Point"}
}