{
  "type": "Feature",
  "properties": {
    "gn:admin1_code":"88",
    "gn:asciiname":"Vasil'tsevo",
    "gn:country_code":"RU",
    "gn:dem":119,
    "gn:feature_class":"P",
    "gn:feature_code":"PPL",
    "gn:name":"Vasil\u2019tsevo",
    "gn:population":0,
    "gn:timezone":"Europe/Moscow",
    "iso:country":"RU",
    "name:rus_x_preferred":[
        "\u0412\u0430\u0441\u0438\u044c\u0446\u0435\u0432\u043e"
    ],
    "name:und_x_variant":[
        "Vasil\u2019tsevo"
    ],
    "wof:name":"Vasil'tsevo",
    "wof:placetype":"locality"
},
  "geometry": {"coordinates":[39.78784,57.81971],"type":"Point"}
}