{
  "type": "Feature",
  "properties": {
    "gn:admin1_code":"77.0",
    "gn:asciiname":"Babino",
    "gn:country_code":"RU",
    "gn:dem":257,
    "gn:feature_class":"P",
    "gn:feature_code":"PPL",
    "gn:name":"Babino",
    "gn:population":0,
    "gn:timezone":"Europe/Moscow",
    "iso:country":"RU",
    "name:eng_x_preferred":[
        "Babino"
    ],
    "name:nor_x_preferred":[
        "Babino"
    ],
    "name:rus_x_preferred":[
        "\u0411\u0430\u0431\u0438\u043d\u043e"
    ],
    "name:und_x_variant":[
        "\u0411\u0430\u0431\u0438\u043d\u043e",
        "Babino"
    ],
    "wof:name":"Babino",
    "wof:placetype":"locality"
},
  "geometry": {"coordinates":[34.28408,56.73468],"type":"Point"}
}