{
  "type": "Feature",
  "properties": {
    "iso:country":"RU",
    "qs:name":"Pal'mnikken",
    "qs:name_adm0":"Russia",
    "qs:name_adm1":"Kaliningrad Oblast",
    "qs:photos":109,
    "qs:photos_1k":22,
    "qs:photos_9k":1,
    "qs:photos_9r":3,
    "qs:photos_all":109,
    "qs:photos_sr":3,
    "qs:placetype":"Town",
    "qs:pop_sr":"0",
    "wof:name":"Pal'mnikken",
    "wof:placetype":"locality"
},
  "geometry": {"coordinates":[19.934005,54.868309],"type":"Point"}
}