{
  "type": "Feature",
  "properties": {
    "gn:admin1_code":"54",
    "gn:asciiname":"Bol'shaya Pristan'",
    "gn:country_code":"RU",
    "gn:dem":100,
    "gn:feature_class":"P",
    "gn:feature_code":"PPL",
    "gn:name":"Bol\u2019shaya Pristan\u2019",
    "gn:population":0,
    "gn:timezone":"Asia/Omsk",
    "iso:country":"RU",
    "name:rus_x_preferred":[
        "\u0411\u043e\u043b\u044c\u0448\u0430\u044f \u041f\u0440\u0438\u0441\u0442\u0430\u043d\u044c"
    ],
    "name:und_x_variant":[
        "Bol\u2019shaya Pristan\u2019"
    ],
    "wof:name":"Bol'shaya Pristan'",
    "wof:placetype":"locality"
},
  "geometry": {"coordinates":[73.61667,57.38333000000001],"type":"Point"}
}