{
  "type": "Feature",
  "properties": {
    "gn:admin1_code":"34",
    "gn:asciiname":"Lazurnyy",
    "gn:country_code":"RU",
    "gn:dem":56,
    "gn:feature_class":"P",
    "gn:feature_code":"PPL",
    "gn:name":"Lazurnyy",
    "gn:population":0,
    "gn:timezone":"Europe/Moscow",
    "iso:country":"RU",
    "name:eng_x_preferred":[
        "Lazurnyy"
    ],
    "name:nor_x_preferred":[
        "Lazurnyj"
    ],
    "name:rus_x_preferred":[
        "\u041b\u0430\u0437\u0443\u0440\u043d\u044b\u0439"
    ],
    "wof:name":"Lazurnyy",
    "wof:placetype":"locality"
},
  "geometry": {"coordinates":[59.05017,65.63602],"type":"Point"}
}