{
  "type": "Feature",
  "properties": {
    "gn:admin1_code":"72",
    "gn:asciiname":"Krest'yanka",
    "gn:country_code":"RU",
    "gn:dem":169,
    "gn:feature_class":"P",
    "gn:feature_code":"PPL",
    "gn:name":"Krest\u2019yanka",
    "gn:population":0,
    "gn:timezone":"Europe/Moscow",
    "iso:country":"RU",
    "name:rus_x_preferred":[
        "\u041a\u0440\u0435\u0441\u0442\u044c\u044f\u043d\u043a\u0430"
    ],
    "name:und_x_variant":[
        "Krest\u2019yanka",
        "\u041a\u0440\u0435\u0441\u0442\u044c\u044f\u043d\u043a\u0430"
    ],
    "wof:name":"Krest'yanka",
    "wof:placetype":"locality"
},
  "geometry": {"coordinates":[41.16667,52.38333],"type":"Point"}
}