{
  "type": "Feature",
  "properties": {
    "gn:admin1_code":"41",
    "gn:asciiname":"Kilikino",
    "gn:country_code":"RU",
    "gn:dem":172,
    "gn:feature_class":"P",
    "gn:feature_code":"PPL",
    "gn:name":"Kilikino",
    "gn:population":0,
    "gn:timezone":"Europe/Moscow",
    "iso:country":"RU",
    "name:rus_x_preferred":[
        "\u041a\u0438\u043b\u0438\u043a\u0438\u043d\u043e"
    ],
    "name:und_x_variant":[
        "Kil\u2019kino",
        "Kilikino"
    ],
    "wof:name":"Kilikino",
    "wof:placetype":"locality"
},
  "geometry": {"coordinates":[35.1478,52.2226],"type":"Point"}
}