{
  "type": "Feature",
  "properties": {
    "gn:admin1_code":"6",
    "gn:asciiname":"Rossokhi",
    "gn:country_code":"RU",
    "gn:dem":90,
    "gn:feature_class":"P",
    "gn:feature_code":"PPL",
    "gn:name":"Rossokhi",
    "gn:population":0,
    "gn:timezone":"Europe/Moscow",
    "iso:country":"RU",
    "name:eng_x_preferred":[
        "Rossokhi"
    ],
    "name:nor_x_preferred":[
        "Rossokha"
    ],
    "name:rus_x_preferred":[
        "\u0420\u043e\u0441\u0441\u043e\u0445\u0430"
    ],
    "name:rus_x_variant":[
        "\u0420\u043e\u0441\u0441\u043e\u0445\u0438"
    ],
    "name:und_x_variant":[
        "Rassokhi",
        "Rossokhi",
        "\u0420\u043e\u0441\u0441\u043e\u0445\u0438"
    ],
    "wof:name":"Rossokhi",
    "wof:placetype":"locality"
},
  "geometry": {"coordinates":[43.21201,61.83356],"type":"Point"}
}