{
  "type": "Feature",
  "properties": {
    "gn:admin1_code":"77.0",
    "gn:asciiname":"Chernyy Dor",
    "gn:country_code":"RU",
    "gn:dem":226,
    "gn:feature_class":"P",
    "gn:feature_code":"PPL",
    "gn:name":"Ch\u00ebrnyy Dor",
    "gn:population":0,
    "gn:timezone":"Europe/Moscow",
    "iso:country":"RU",
    "name:rus_x_preferred":[
        "\u0427\u0451\u0440\u043d\u044b\u0439 \u0414\u043e\u0440"
    ],
    "name:und_x_variant":[
        "Chernozem",
        "Cherny Dor",
        "Ch\u00ebrnyy Dor"
    ],
    "wof:name":"Chernyy Dor",
    "wof:placetype":"locality"
},
  "geometry": {"coordinates":[33.28716,57.2372],"type":"Point"}
}