{
  "type": "Feature",
  "properties": {
    "gn:country":"RU",
    "gn:fcode":"PPL",
    "gn:population":854,
    "iso:country":"RU",
    "name:eng_x_preferred":[
        "Spornoye"
    ],
    "name:nor_x_preferred":[
        "Spornoje"
    ],
    "name:rus_x_preferred":[
        "\u0421\u043f\u043e\u0440\u043d\u043e\u0435"
    ],
    "name:und_x_variant":[
        "Sporn\u00f6y"
    ],
    "qs:name":"Spornoye",
    "qs:photos_9r":0,
    "qs:photos_sr":0,
    "qs:pop_sr":"2",
    "wof:name":"Spornoye",
    "wof:placetype":"locality",
    "wof:population":854
},
  "geometry": {"coordinates":[151.10581999999999,62.34106],"type":"Point"}
}