{
  "type": "Feature",
  "properties": {
    "gn:admin1_code":"4.0",
    "gn:asciiname":"Nevskiy",
    "gn:country_code":"RU",
    "gn:dem":278,
    "gn:feature_class":"P",
    "gn:feature_code":"PPL",
    "gn:name":"Nevskiy",
    "gn:population":0,
    "gn:timezone":"Asia/Barnaul",
    "iso:country":"RU",
    "name:rus_x_preferred":[
        "\u041d\u0435\u0432\u0441\u043a\u0438\u0439"
    ],
    "wof:name":"Nevskiy",
    "wof:placetype":"locality"
},
  "geometry": {"coordinates":[81.7073,52.2987],"type":"Point"}
}