{
  "type": "Feature",
  "properties": {
    "gn:admin1_code":"77",
    "gn:asciiname":"Orlovo",
    "gn:country_code":"RU",
    "gn:dem":168,
    "gn:feature_class":"P",
    "gn:feature_code":"PPL",
    "gn:name":"Orlovo",
    "gn:population":0,
    "gn:timezone":"Europe/Moscow",
    "iso:country":"RU",
    "name:rus_x_preferred":[
        "\u041e\u0440\u043b\u043e\u0432\u043e"
    ],
    "name:und_x_variant":[
        "\u041e\u0440\u043b\u043e\u0432\u043e"
    ],
    "wof:name":"Orlovo",
    "wof:placetype":"locality"
},
  "geometry": {"coordinates":[35.56625,58.42206],"type":"Point"}
}