{
  "type": "Feature",
  "properties": {
    "gn:admin1_code":"69",
    "gn:asciiname":"Lenkino",
    "gn:country_code":"RU",
    "gn:dem":189,
    "gn:feature_class":"P",
    "gn:feature_code":"PPL",
    "gn:name":"Lenkino",
    "gn:population":0,
    "gn:timezone":"Europe/Moscow",
    "iso:country":"RU",
    "name:rus_x_preferred":[
        "\u041b\u0435\u043d\u043a\u0438\u043d\u043e"
    ],
    "name:und_x_variant":[
        "Lenkina",
        "Lenkino",
        "\u041b\u0435\u043d\u043a\u0438\u043d\u043e"
    ],
    "wof:name":"Lenkino",
    "wof:placetype":"locality"
},
  "geometry": {"coordinates":[33.62058,54.89238],"type":"Point"}
}