{
  "type": "Feature",
  "properties": {
    "gn:admin1_code":"10",
    "gn:asciiname":"Nesvoyevka",
    "gn:country_code":"RU",
    "gn:dem":151,
    "gn:feature_class":"P",
    "gn:feature_code":"PPL",
    "gn:name":"Nesvoy\u00ebvka",
    "gn:population":0,
    "gn:timezone":"Europe/Moscow",
    "iso:country":"RU",
    "name:rus_x_preferred":[
        "\u041d\u0435\u0441\u0432\u043e\u0451\u0432\u043a\u0430"
    ],
    "name:und_x_variant":[
        "Nesvoy\u00ebvka"
    ],
    "wof:name":"Nesvoyevka",
    "wof:placetype":"locality"
},
  "geometry": {"coordinates":[31.6085,52.7143],"type":"Point"}
}