{
  "type": "Feature",
  "properties": {
    "gn:admin1_code":"29",
    "gn:asciiname":"Ail",
    "gn:country_code":"RU",
    "gn:dem":253,
    "gn:feature_class":"P",
    "gn:feature_code":"PPL",
    "gn:name":"Ail",
    "gn:population":0,
    "gn:timezone":"Asia/Novokuznetsk",
    "iso:country":"RU",
    "name:fra_x_preferred":[
        "Ail"
    ],
    "name:nor_x_preferred":[
        "Ail"
    ],
    "name:oci_x_preferred":[
        "Alh"
    ],
    "name:rus_x_preferred":[
        "\u0410\u0438\u043b"
    ],
    "wof:name":"Ail",
    "wof:placetype":"locality"
},
  "geometry": {"coordinates":[87.21666999999999,53.33333],"type":"Point"}
}