{
  "type": "Feature",
  "properties": {
    "gn:admin1_code":"47.0",
    "gn:asciiname":"Tefanovo",
    "gn:country_code":"RU",
    "gn:dem":182,
    "gn:feature_class":"P",
    "gn:feature_code":"PPL",
    "gn:name":"Tefanovo",
    "gn:population":0,
    "gn:timezone":"Europe/Moscow",
    "iso:country":"RU",
    "name:rus_x_preferred":[
        "\u0422\u0435\u0444\u0430\u043d\u043e\u0432\u043e"
    ],
    "wof:name":"Tefanovo",
    "wof:placetype":"locality"
},
  "geometry": {"coordinates":[37.45667,56.15528000000001],"type":"Point"}
}