{
  "type": "Feature",
  "properties": {
    "gn:admin1_code":"52",
    "gn:asciiname":"Sergino",
    "gn:country_code":"RU",
    "gn:dem":180,
    "gn:feature_class":"P",
    "gn:feature_code":"PPL",
    "gn:name":"Sergino",
    "gn:population":0,
    "gn:timezone":"Europe/Moscow",
    "iso:country":"RU",
    "name:rus_x_preferred":[
        "\u0421\u0435\u0440\u0433\u0438\u043d\u043e"
    ],
    "name:ukr_x_preferred":[
        "\u0421\u0435\u0440\u0433\u0438\u043d\u043e"
    ],
    "name:und_x_variant":[
        "\u0421\u0435\u0440\u0433\u0438\u043d\u043e"
    ],
    "wof:name":"Sergino",
    "wof:placetype":"locality"
},
  "geometry": {"coordinates":[34.66452,58.58127],"type":"Point"}
}