{
  "type": "Feature",
  "properties": {
    "gn:admin1_code":"23",
    "gn:asciiname":"Mal'tsevo",
    "gn:country_code":"RU",
    "gn:dem":94,
    "gn:feature_class":"P",
    "gn:feature_code":"PPL",
    "gn:name":"Mal\u2019tsevo",
    "gn:population":0,
    "gn:timezone":"Europe/Kaliningrad",
    "iso:country":"RU",
    "name:eng_x_preferred":[
        "Mal'tsevo"
    ],
    "name:nor_x_preferred":[
        "Maltsevo"
    ],
    "name:rus_x_preferred":[
        "\u041c\u0430\u043b\u044c\u0446\u0435\u0432\u043e"
    ],
    "name:und_x_variant":[
        "\u041c\u0430\u043b\u044c\u0446\u0435\u0432\u043e",
        "Mal\u2019tsevo"
    ],
    "wof:name":"Mal'tsevo",
    "wof:placetype":"locality"
},
  "geometry": {"coordinates":[21.72116,54.37422],"type":"Point"}
}