{
  "type": "Feature",
  "properties": {
    "gn:admin1_code":"31",
    "gn:asciiname":"Zakhar'yevskiy",
    "gn:country_code":"RU",
    "gn:dem":873,
    "gn:feature_class":"P",
    "gn:feature_code":"PPL",
    "gn:name":"Zakhar\u2019yevskiy",
    "gn:population":0,
    "gn:timezone":"Asia/Krasnoyarsk",
    "iso:country":"RU",
    "name:eng_x_preferred":[
        "Zakhar'yevskiy"
    ],
    "name:nor_x_preferred":[
        "Zakharjevskij"
    ],
    "name:rus_x_preferred":[
        "\u0417\u0430\u0445\u0430\u0440\u044c\u0435\u0432\u0441\u043a\u0438\u0439"
    ],
    "name:und_x_variant":[
        "Zakhar\u2019yevskiy"
    ],
    "wof:name":"Zakhar'yevskiy",
    "wof:placetype":"locality"
},
  "geometry": {"coordinates":[89.19226,52.25782],"type":"Point"}
}