{
  "type": "Feature",
  "properties": {
    "gn:admin1_code":"23",
    "gn:asciiname":"Dovatorovka",
    "gn:country_code":"RU",
    "gn:dem":15,
    "gn:feature_class":"P",
    "gn:feature_code":"PPL",
    "gn:name":"Dovatorovka",
    "gn:population":0,
    "gn:timezone":"Europe/Kaliningrad",
    "iso:country":"RU",
    "name:rus_x_preferred":[
        "\u0414\u043e\u0432\u0430\u0442\u043e\u0440\u043e\u0432\u043a\u0430"
    ],
    "wof:name":"Dovatorovka",
    "wof:placetype":"locality"
},
  "geometry": {"coordinates":[21.73535,54.65169],"type":"Point"}
}