{
  "type": "Feature",
  "properties": {
    "gn:admin1_code":"77",
    "gn:asciiname":"Starovo-Ponizov'ye",
    "gn:country_code":"RU",
    "gn:dem":155,
    "gn:feature_class":"P",
    "gn:feature_code":"PPL",
    "gn:name":"Starovo-Ponizov\u2019ye",
    "gn:population":0,
    "gn:timezone":"Europe/Moscow",
    "iso:country":"RU",
    "name:rus_x_preferred":[
        "\u0421\u0442\u0430\u0440\u043e\u0432\u043e-\u041f\u043e\u043d\u0438\u0437\u043e\u0432\u044c\u0435"
    ],
    "name:und_x_variant":[
        "Starovo-Ponizov\u2019ye"
    ],
    "wof:name":"Starovo-Ponizov'ye",
    "wof:placetype":"locality"
},
  "geometry": {"coordinates":[36.5856,57.2472],"type":"Point"}
}