{
  "type": "Feature",
  "properties": {
    "gn:admin1_code":"77",
    "gn:asciiname":"Vol'nyye Kulakovki",
    "gn:country_code":"RU",
    "gn:dem":253,
    "gn:feature_class":"P",
    "gn:feature_code":"PPL",
    "gn:name":"Vol\u2019nyye Kulakovki",
    "gn:population":0,
    "gn:timezone":"Europe/Moscow",
    "iso:country":"RU",
    "name:und_x_variant":[
        "Kulakovka",
        "Vol\u2019nyye Kulakovki"
    ],
    "wof:name":"Vol'nyye Kulakovki",
    "wof:placetype":"locality"
},
  "geometry": {"coordinates":[33.56862,56.09666],"type":"Point"}
}