{
  "type": "Feature",
  "properties": {
    "gn:admin1_code":"8",
    "gn:asciiname":"Kuz'minovka",
    "gn:country_code":"RU",
    "gn:dem":236,
    "gn:feature_class":"P",
    "gn:feature_code":"PPL",
    "gn:name":"Kuz\u2019minovka",
    "gn:population":0,
    "gn:timezone":"Asia/Yekaterinburg",
    "iso:country":"RU",
    "name:eng_x_preferred":[
        "Kuz'minovka"
    ],
    "name:nor_x_preferred":[
        "Kuzminovka"
    ],
    "name:rus_x_preferred":[
        "\u041a\u0443\u0437\u044c\u043c\u0438\u043d\u043e\u0432\u043a\u0430"
    ],
    "name:und_x_variant":[
        "Kuz\u2019minovskiy",
        "Kuz\u2019minovka"
    ],
    "wof:name":"Kuz'minovka",
    "wof:placetype":"locality"
},
  "geometry": {"coordinates":[56.67574000000001,52.69584],"type":"Point"}
}