{
  "type": "Feature",
  "properties": {
    "gn:admin1_code":"38",
    "gn:asciiname":"Yeremin",
    "gn:country_code":"RU",
    "gn:dem":46,
    "gn:feature_class":"P",
    "gn:feature_code":"PPL",
    "gn:name":"Yer\u00ebmin",
    "gn:population":0,
    "gn:timezone":"Europe/Moscow",
    "iso:country":"RU",
    "name:rus_x_preferred":[
        "\u0415\u0440\u0451\u043c\u0438\u043d"
    ],
    "name:und_x_variant":[
        "Yer\u00ebmin"
    ],
    "wof:name":"Yeremin",
    "wof:placetype":"locality"
},
  "geometry": {"coordinates":[40.0404,45.5472],"type":"Point"}
}