{
  "type": "Feature",
  "properties": {
    "gn:admin1_code":"53",
    "gn:asciiname":"Kryuchnaya",
    "gn:cc2":"RU",
    "gn:country_code":"RU",
    "gn:dem":84,
    "gn:feature_class":"P",
    "gn:feature_code":"PPL",
    "gn:name":"Kryuchnaya",
    "gn:population":0,
    "gn:timezone":"Asia/Novosibirsk",
    "iso:country":"RU",
    "name:rus_x_preferred":[
        "\u041a\u0440\u044e\u0447\u043d\u0430\u044f"
    ],
    "name:und_x_variant":[
        "Kryuchnyy",
        "Kryuchnaya"
    ],
    "wof:name":"Kryuchnaya",
    "wof:placetype":"locality"
},
  "geometry": {"coordinates":[76.28333000000001,56.48333],"type":"Point"}
}