{
  "type": "Feature",
  "properties": {
    "gn:admin1_code":"44",
    "gn:asciiname":"Oyra",
    "gn:country_code":"RU",
    "gn:dem":4,
    "gn:feature_class":"P",
    "gn:feature_code":"PPL",
    "gn:name":"Oyra",
    "gn:population":0,
    "gn:timezone":"Asia/Magadan",
    "iso:country":"RU",
    "name:rus_x_preferred":[
        "\u041e\u0439\u0440\u0430"
    ],
    "wof:name":"Oyra",
    "wof:placetype":"locality"
},
  "geometry": {"coordinates":[149.94721999999999,59.70972],"type":"Point"}
}