{
  "type": "Feature",
  "properties": {
    "gn:admin1_code":"75",
    "gn:asciiname":"Yarki",
    "gn:country_code":"RU",
    "gn:dem":79,
    "gn:feature_class":"P",
    "gn:feature_code":"PPL",
    "gn:name":"Yarki",
    "gn:population":0,
    "gn:timezone":"Asia/Tomsk",
    "iso:country":"RU",
    "name:eng_x_preferred":[
        "Yarki"
    ],
    "name:nor_x_preferred":[
        "Jarki"
    ],
    "name:rus_x_preferred":[
        "\u042f\u0440\u043a\u0438"
    ],
    "wof:name":"Yarki",
    "wof:placetype":"locality"
},
  "geometry": {"coordinates":[81.99674,57.52081],"type":"Point"}
}