{
  "type": "Feature",
  "properties": {
    "gn:admin1_code":"77",
    "gn:asciiname":"Stolipino",
    "gn:country_code":"RU",
    "gn:dem":179,
    "gn:feature_class":"P",
    "gn:feature_code":"PPL",
    "gn:name":"Stolipino",
    "gn:population":0,
    "gn:timezone":"Europe/Moscow",
    "iso:country":"RU",
    "name:rus_x_preferred":[
        "\u0421\u0442\u043e\u043b\u0438\u043f\u0438\u043d\u043e"
    ],
    "name:und_x_variant":[
        "Stolypino",
        "Stolipino",
        "\u0421\u0442\u043e\u043b\u0438\u043f\u0438\u043d\u043e"
    ],
    "wof:name":"Stolipino",
    "wof:placetype":"locality"
},
  "geometry": {"coordinates":[34.85372,56.25699],"type":"Point"}
}