{
  "type": "Feature",
  "properties": {
    "gn:admin1_code":"85",
    "gn:asciiname":"Markov",
    "gn:country_code":"RU",
    "gn:dem":132,
    "gn:feature_class":"P",
    "gn:feature_code":"PPL",
    "gn:name":"Markov",
    "gn:population":0,
    "gn:timezone":"Europe/Moscow",
    "iso:country":"RU",
    "name:eng_x_preferred":[
        "Markov"
    ],
    "name:nor_x_preferred":[
        "Markovskoje"
    ],
    "name:rus_x_preferred":[
        "\u041c\u0430\u0440\u043a\u043e\u0432\u0441\u043a\u043e\u0435"
    ],
    "name:rus_x_variant":[
        "\u041c\u0430\u0440\u043a\u043e\u0432"
    ],
    "name:und_x_variant":[
        "\u041c\u0430\u0440\u043a\u043e\u0432"
    ],
    "wof:name":"Markov",
    "wof:placetype":"locality"
},
  "geometry": {"coordinates":[40.45426,59.43129],"type":"Point"}
}