{
  "type": "Feature",
  "properties": {
    "gn:admin1_code":"75",
    "gn:asciiname":"Voznesenka",
    "gn:country_code":"RU",
    "gn:dem":106,
    "gn:feature_class":"P",
    "gn:feature_code":"PPL",
    "gn:name":"Voznesenka",
    "gn:population":0,
    "gn:timezone":"Asia/Tomsk",
    "iso:country":"RU",
    "name:eng_x_preferred":[
        "Voznesenka"
    ],
    "name:nor_x_preferred":[
        "Voznesenka"
    ],
    "name:rus_x_preferred":[
        "\u0412\u043e\u0437\u043d\u0435\u0441\u0435\u043d\u043a\u0430"
    ],
    "wof:name":"Voznesenka",
    "wof:placetype":"locality"
},
  "geometry": {"coordinates":[83.63408000000003,57.08111],"type":"Point"}
}