{
  "type": "Feature",
  "properties": {
    "gn:admin1_code":"64",
    "gn:asciiname":"Rybnovsk",
    "gn:country_code":"RU",
    "gn:dem":5,
    "gn:feature_class":"P",
    "gn:feature_code":"PPL",
    "gn:name":"Rybnovsk",
    "gn:population":0,
    "gn:timezone":"Asia/Sakhalin",
    "iso:country":"RU",
    "name:eng_x_preferred":[
        "Rybnovsk"
    ],
    "name:nor_x_preferred":[
        "Rybnovsk"
    ],
    "name:rus_x_preferred":[
        "\u0420\u044b\u0431\u043d\u043e\u0432\u0441\u043a"
    ],
    "name:und_x_variant":[
        "Fishery Number Five",
        "Shumlovo",
        "Rybnovskii Zavod",
        "Rybnyy Promysel Nomer Pyatyy"
    ],
    "wof:name":"Rybnovsk",
    "wof:placetype":"locality"
},
  "geometry": {"coordinates":[141.79674,53.25436],"type":"Point"}
}