{
  "type": "Feature",
  "properties": {
    "gn:admin1_code":"76",
    "gn:asciiname":"Serebryanyy",
    "gn:country_code":"RU",
    "gn:dem":255,
    "gn:feature_class":"P",
    "gn:feature_code":"PPL",
    "gn:name":"Serebryanyy",
    "gn:population":0,
    "gn:timezone":"Europe/Moscow",
    "iso:country":"RU",
    "name:rus_x_preferred":[
        "\u0421\u0435\u0440\u0435\u0431\u0440\u044f\u043d\u044b\u0439"
    ],
    "name:und_x_variant":[
        "Serebryany",
        "Serebryanyy",
        "\u0421\u0435\u0440\u0435\u0431\u0440\u044f\u043d\u044b\u0439"
    ],
    "wof:name":"Serebryanyy",
    "wof:placetype":"locality"
},
  "geometry": {"coordinates":[37.21776,53.53471],"type":"Point"}
}