{
  "type": "Feature",
  "properties": {
    "gn:admin1_code":"76.0",
    "gn:asciiname":"Belino",
    "gn:country_code":"RU",
    "gn:dem":238,
    "gn:feature_class":"P",
    "gn:feature_code":"PPL",
    "gn:name":"Belino",
    "gn:population":0,
    "gn:timezone":"Europe/Moscow",
    "iso:country":"RU",
    "name:nor_x_preferred":[
        "Belino"
    ],
    "name:rus_x_preferred":[
        "\u0411\u0435\u043b\u0438\u043d\u043e"
    ],
    "wof:name":"Belino",
    "wof:placetype":"locality"
},
  "geometry": {"coordinates":[36.75633,53.53616],"type":"Point"}
}