{
  "type": "Feature",
  "properties": {
    "gn:admin1_code":"33.0",
    "gn:asciiname":"Semenki",
    "gn:country_code":"RU",
    "gn:dem":122,
    "gn:feature_class":"P",
    "gn:feature_code":"PPL",
    "gn:name":"Sem\u00ebnki",
    "gn:population":0,
    "gn:timezone":"Europe/Kirov",
    "iso:country":"RU",
    "name:rus_x_preferred":[
        "\u0421\u0435\u043c\u0451\u043d\u043a\u0438"
    ],
    "name:und_x_variant":[
        "Sem\u00ebnki",
        "\u0421\u0435\u043c\u0451\u043d\u043a\u0438"
    ],
    "wof:name":"Semenki",
    "wof:placetype":"locality"
},
  "geometry": {"coordinates":[50.65215,58.4633],"type":"Point"}
}