{
  "type": "Feature",
  "properties": {
    "gn:admin1_code":"25",
    "gn:asciiname":"Pokrov",
    "gn:country_code":"RU",
    "gn:dem":200,
    "gn:feature_class":"P",
    "gn:feature_code":"PPL",
    "gn:name":"Pokrov",
    "gn:population":0,
    "gn:timezone":"Europe/Moscow",
    "iso:country":"RU",
    "name:bar_x_preferred":[
        "Pokrow"
    ],
    "name:bel_x_preferred":[
        "\u041f\u0430\u043a\u0440\u043e\u045e"
    ],
    "name:deu_x_preferred":[
        "Pokrow"
    ],
    "name:eng_x_preferred":[
        "Pokrov"
    ],
    "name:hsb_x_preferred":[
        "Pokrow"
    ],
    "name:ita_x_preferred":[
        "Pokrov"
    ],
    "name:kor_x_preferred":[
        "\ud3ec\ud06c\ub85c\ud504"
    ],
    "name:nno_x_preferred":[
        "Pokrov"
    ],
    "name:nor_x_preferred":[
        "Pokrov"
    ],
    "name:pol_x_preferred":[
        "Pokrow"
    ],
    "name:rus_x_preferred":[
        "\u041f\u043e\u043a\u0440\u043e\u0432"
    ],
    "name:slk_x_preferred":[
        "Pokrov"
    ],
    "name:ukr_x_preferred":[
        "\u041f\u043e\u043a\u0440\u043e\u0432"
    ],
    "name:und_x_variant":[
        "\u041f\u043e\u043a\u0440\u043e\u0432",
        "Pokrov"
    ],
    "wof:name":"Pokrov",
    "wof:placetype":"locality"
},
  "geometry": {"coordinates":[35.23637,54.25553000000001],"type":"Point"}
}