{
  "type": "Feature",
  "properties": {
    "gn:admin1_code":"77",
    "gn:asciiname":"Medvedevo",
    "gn:country_code":"RU",
    "gn:dem":164,
    "gn:feature_class":"P",
    "gn:feature_code":"PPL",
    "gn:name":"Medvedevo",
    "gn:population":0,
    "gn:timezone":"Europe/Moscow",
    "iso:country":"RU",
    "name:rus_x_preferred":[
        "\u041c\u0435\u0434\u0432\u0435\u0434\u0435\u0432\u043e"
    ],
    "wof:name":"Medvedevo",
    "wof:placetype":"locality"
},
  "geometry": {"coordinates":[34.29648,58.08006999999999],"type":"Point"}
}