{
  "type": "Feature",
  "properties": {
    "gn:country":"RU",
    "gn:fcode":"PPL",
    "gn:population":576,
    "iso:country":"RU",
    "name:est_x_preferred":[
        "Pulkovo"
    ],
    "name:fin_x_preferred":[
        "Pulkkala"
    ],
    "name:fin_x_variant":[
        "Pulkovo"
    ],
    "name:ita_x_preferred":[
        "Pulkovo"
    ],
    "name:jpn_x_preferred":[
        "\u30d7\u30eb\u30b3\u30f4\u30a9"
    ],
    "name:lav_x_preferred":[
        "Pulkova"
    ],
    "name:nor_x_preferred":[
        "Pulkovo"
    ],
    "name:rus_x_preferred":[
        "\u041f\u0443\u043b\u043a\u043e\u0432\u043e"
    ],
    "name:swe_x_preferred":[
        "Pulkovo"
    ],
    "name:ukr_x_preferred":[
        "\u041f\u0443\u043b\u043a\u043e\u0432\u043e"
    ],
    "qs:name":"Pulkovo",
    "qs:photos_9r":0,
    "qs:photos_sr":0,
    "qs:pop_sr":"2",
    "wd:wordcount":54,
    "wof:name":"Pulkovo",
    "wof:placetype":"locality",
    "wof:population":576
},
  "geometry": {"coordinates":[29.19438,59.97458],"type":"Point"}
}