{
  "type": "Feature",
  "properties": {
    "gn:admin1_code":"42",
    "gn:asciiname":"Guseva Gora",
    "gn:country_code":"RU",
    "gn:dem":63,
    "gn:feature_class":"P",
    "gn:feature_code":"PPL",
    "gn:name":"Gus\u00ebva Gora",
    "gn:population":0,
    "gn:timezone":"Europe/Moscow",
    "iso:country":"RU",
    "name:rus_x_preferred":[
        "\u0413\u0443\u0441\u00eb\u0432\u0430 \u0413\u043e\u0440\u0430"
    ],
    "name:und_x_variant":[
        "Gus\u00ebva Gora"
    ],
    "wof:name":"Guseva Gora",
    "wof:placetype":"locality"
},
  "geometry": {"coordinates":[28.2771,58.9506],"type":"Point"}
}