{
  "type": "Feature",
  "properties": {
    "gn:admin1_code":"47",
    "gn:asciiname":"Stankovo",
    "gn:country_code":"RU",
    "gn:dem":130,
    "gn:feature_class":"P",
    "gn:feature_code":"PPL",
    "gn:name":"Stankovo",
    "gn:population":0,
    "gn:timezone":"Europe/Moscow",
    "iso:country":"RU",
    "name:rus_x_preferred":[
        "\u0421\u0442\u0430\u043d\u043a\u043e\u0432\u043e"
    ],
    "wof:name":"Stankovo",
    "wof:placetype":"locality"
},
  "geometry": {"coordinates":[37.36761,55.0115],"type":"Point"}
}