{
  "type": "Feature",
  "properties": {
    "gn:admin1_code":"12.0",
    "gn:asciiname":"Zamay-Yurt",
    "gn:country_code":"RU",
    "gn:dem":356,
    "gn:feature_class":"P",
    "gn:feature_code":"PPL",
    "gn:name":"Zamay-Yurt",
    "gn:population":0,
    "gn:timezone":"Europe/Moscow",
    "iso:country":"RU",
    "name:che_x_preferred":[
        "Zama-Yurt"
    ],
    "name:che_x_variant":[
        "\u00c7arax",
        "\u0427\u0430\u0440\u0430\u0445",
        "\u0417\u0430\u043c\u0430-\u042e\u0440\u0442"
    ],
    "name:rus_x_preferred":[
        "\u0417\u0430\u043c\u0430\u0439-\u042e\u0440\u0442"
    ],
    "name:und_x_variant":[
        "Charakh",
        "Zamaj-Jurt",
        "Zamay-Yurt"
    ],
    "wof:name":"Zamay-Yurt",
    "wof:placetype":"locality"
},
  "geometry": {"coordinates":[46.37832,43.15032],"type":"Point"}
}