{
  "type": "Feature",
  "properties": {
    "gn:admin1_code":"63",
    "gn:asciiname":"Usun-Kyuyel'",
    "gn:country_code":"RU",
    "gn:dem":13,
    "gn:feature_class":"P",
    "gn:feature_code":"PPL",
    "gn:name":"Usun-Kyuy\u00ebl\u2019",
    "gn:population":0,
    "gn:timezone":"Asia/Magadan",
    "iso:country":"RU",
    "name:und_x_variant":[
        "Ugun-Kel\u2019",
        "Usun-Kyuy\u00ebl\u2019"
    ],
    "wof:name":"Usun-Kyuyel'",
    "wof:placetype":"locality"
},
  "geometry": {"coordinates":[154.58333000000005,67.63333],"type":"Point"}
}