{
  "type": "Feature",
  "properties": {
    "gn:admin1_code":"52",
    "gn:asciiname":"Pleshchevo",
    "gn:country_code":"RU",
    "gn:dem":204,
    "gn:feature_class":"P",
    "gn:feature_code":"PPL",
    "gn:name":"Pleshch\u00ebvo",
    "gn:population":0,
    "gn:timezone":"Europe/Moscow",
    "iso:country":"RU",
    "name:rus_x_preferred":[
        "\u041f\u043b\u0435\u0449\u0451\u0432\u043e"
    ],
    "name:und_x_variant":[
        "Pleshch\u00ebvo"
    ],
    "wof:name":"Pleshchevo",
    "wof:placetype":"locality"
},
  "geometry": {"coordinates":[32.66764000000001,57.51748000000001],"type":"Point"}
}