{
  "type": "Feature",
  "properties": {
    "gn:admin1_code":"20",
    "gn:asciiname":"Katarbey",
    "gn:country_code":"RU",
    "gn:dem":544,
    "gn:feature_class":"P",
    "gn:feature_code":"PPL",
    "gn:name":"Katarbey",
    "gn:population":0,
    "gn:timezone":"Asia/Irkutsk",
    "iso:country":"RU",
    "name:eng_x_preferred":[
        "Katarbey"
    ],
    "name:nor_x_preferred":[
        "Katarbej"
    ],
    "name:rus_x_preferred":[
        "\u041a\u0430\u0442\u0430\u0440\u0431\u0435\u0439"
    ],
    "name:und_x_variant":[
        "\u041a\u0430\u0442\u0430\u0440\u0431\u0435\u0439",
        "Katarbey"
    ],
    "wof:name":"Katarbey",
    "wof:placetype":"locality"
},
  "geometry": {"coordinates":[99.681,54.36713],"type":"Point"}
}