{
  "type": "Feature",
  "properties": {
    "gn:admin1_code":"8",
    "gn:asciiname":"Staroamirovo",
    "gn:country_code":"RU",
    "gn:dem":123,
    "gn:feature_class":"P",
    "gn:feature_code":"PPL",
    "gn:name":"Staroamirovo",
    "gn:population":0,
    "gn:timezone":"Asia/Yekaterinburg",
    "iso:country":"RU",
    "name:bak_x_preferred":[
        "\u0418\u04ab\u043a\u0435 \u04d8\u043c\u0438\u0440"
    ],
    "name:che_x_preferred":[
        "\u0421\u0442\u0430\u0440\u043e\u0430\u043c\u0438\u0440\u043e\u0432\u043e"
    ],
    "name:hye_x_preferred":[
        "\u054d\u057f\u0561\u0580\u0578\u0561\u0574\u056b\u0580\u0578\u057e\u0578"
    ],
    "name:kaz_x_preferred":[
        "\u0415\u0441\u043a\u0456 \u0430\u043c\u0438\u0440"
    ],
    "name:kir_x_preferred":[
        "\u042d\u0441\u043a\u0438 \u0430\u043c\u0438\u0440"
    ],
    "name:rus_x_preferred":[
        "\u0421\u0442\u0430\u0440\u043e\u0430\u043c\u0438\u0440\u043e\u0432\u043e"
    ],
    "name:tat_x_preferred":[
        "\u0418\u0441\u043a\u0435 \u04d8\u043c\u0438\u0440"
    ],
    "wof:name":"Staroamirovo",
    "wof:placetype":"locality"
},
  "geometry": {"coordinates":[54.6674,54.6616],"type":"Point"}
}