{
  "type": "Feature",
  "properties": {
    "gn:admin1_code":"8",
    "gn:asciiname":"Staroamirovo",
    "gn:country_code":"RU",
    "gn:dem":123,
    "gn:feature_class":"P",
    "gn:feature_code":"PPL",
    "gn:name":"Staroamirovo",
    "gn:population":0,
    "gn:timezone":"Asia/Yekaterinburg",
    "iso:country":"RU",
    "name:rus_x_preferred":[
        "\u0421\u0442\u0430\u0440\u043e\u0430\u043c\u0438\u0440\u043e\u0432\u043e"
    ],
    "name:und_x_variant":[
        "\u0421\u0442\u0430\u0440\u043e\u0430\u043c\u0438\u0440\u043e\u0432\u043e"
    ],
    "wof:name":"Staroamirovo",
    "wof:placetype":"locality"
},
  "geometry": {"coordinates":[54.6674,54.6616],"type":"Point"}
}