{
  "type": "Feature",
  "properties": {
    "gn:admin1_code":"33",
    "gn:asciiname":"Kanayevshchina",
    "gn:country_code":"RU",
    "gn:dem":176,
    "gn:feature_class":"P",
    "gn:feature_code":"PPL",
    "gn:name":"Kanayevshchina",
    "gn:population":0,
    "gn:timezone":"Europe/Kirov",
    "iso:country":"RU",
    "name:rus_x_preferred":[
        "\u041a\u0430\u043d\u0430\u0435\u0432\u0449\u0438\u043d\u0430"
    ],
    "wof:name":"Kanayevshchina",
    "wof:placetype":"locality"
},
  "geometry": {"coordinates":[48.49153,58.72471],"type":"Point"}
}