{
  "type": "Feature",
  "properties": {
    "gn:admin1_code":"16",
    "gn:asciiname":"Korovino",
    "gn:country_code":"RU",
    "gn:dem":174,
    "gn:feature_class":"P",
    "gn:feature_code":"PPL",
    "gn:name":"Korovino",
    "gn:population":0,
    "gn:timezone":"Europe/Moscow",
    "iso:country":"RU",
    "name:rus_x_preferred":[
        "\u041a\u043e\u0440\u043e\u0432\u0438\u043d\u043e"
    ],
    "name:und_x_variant":[
        "\u041a\u043e\u0440\u043e\u0432\u0438\u043d\u043e"
    ],
    "wof:name":"Korovino",
    "wof:placetype":"locality"
},
  "geometry": {"coordinates":[46.08167,55.17806],"type":"Point"}
}