{
  "type": "Feature",
  "properties": {
    "gn:admin1_code":"64",
    "gn:asciiname":"Slava",
    "gn:country_code":"RU",
    "gn:dem":73,
    "gn:feature_class":"P",
    "gn:feature_code":"PPL",
    "gn:name":"Slava",
    "gn:population":0,
    "gn:timezone":"Asia/Sakhalin",
    "iso:country":"RU",
    "name:eng_x_preferred":[
        "Slava"
    ],
    "name:nor_x_preferred":[
        "Slava"
    ],
    "name:rus_x_preferred":[
        "\u0421\u043b\u0430\u0432\u0430"
    ],
    "name:und_x_variant":[
        "Slavo",
        "Slyavo",
        "\u0421\u043b\u0430\u0432\u0430",
        "Slava"
    ],
    "wof:name":"Slava",
    "wof:placetype":"locality"
},
  "geometry": {"coordinates":[142.63491999999999,51.03623],"type":"Point"}
}