{
  "type": "Feature",
  "properties": {
    "gn:admin1_code":"64",
    "gn:asciiname":"Slava",
    "gn:country_code":"RU",
    "gn:dem":73,
    "gn:feature_class":"P",
    "gn:feature_code":"PPL",
    "gn:name":"Slava",
    "gn:population":0,
    "gn:timezone":"Asia/Sakhalin",
    "iso:country":"RU",
    "name:ara_x_preferred":[
        "\u0633\u0644\u0627\u0641\u0627"
    ],
    "name:bos_x_preferred":[
        "Slava"
    ],
    "name:bul_x_preferred":[
        "\u0421\u043b\u0430\u0432\u0430"
    ],
    "name:cat_x_preferred":[
        "Slava"
    ],
    "name:deu_x_preferred":[
        "Slava"
    ],
    "name:ell_x_preferred":[
        "\u03a3\u03bb\u03ac\u03b2\u03b1"
    ],
    "name:eng_x_preferred":[
        "Slava"
    ],
    "name:fra_x_preferred":[
        "Slava"
    ],
    "name:hrv_x_preferred":[
        "Krsna slava"
    ],
    "name:hye_x_preferred":[
        "\u054d\u056c\u0561\u057e\u0561"
    ],
    "name:jpn_x_preferred":[
        "\u30b9\u30e9\u30f4\u30a1"
    ],
    "name:mkd_x_preferred":[
        "\u0421\u043b\u0430\u0432\u0430"
    ],
    "name:nor_x_preferred":[
        "Slava"
    ],
    "name:pol_x_preferred":[
        "Slava"
    ],
    "name:por_x_preferred":[
        "Slava"
    ],
    "name:rus_x_preferred":[
        "\u0421\u043b\u0430\u0432\u0430"
    ],
    "name:spa_x_preferred":[
        "Slava"
    ],
    "name:srp_x_preferred":[
        "\u0421\u043b\u0430\u0432\u0430"
    ],
    "name:swe_x_preferred":[
        "Slava"
    ],
    "name:ukr_x_preferred":[
        "\u0421\u043b\u0430\u0432\u0430"
    ],
    "name:und_x_variant":[
        "Slavo",
        "Slyavo",
        "\u0421\u043b\u0430\u0432\u0430",
        "Slava"
    ],
    "name:zho_x_preferred":[
        "\u65af\u62c9\u74e6\u8282"
    ],
    "wof:name":"Slava",
    "wof:placetype":"locality"
},
  "geometry": {"coordinates":[142.63491999999999,51.03623],"type":"Point"}
}