{
  "type": "Feature",
  "properties": {
    "gn:admin1_code":"63",
    "gn:asciiname":"Nimgerkan",
    "gn:country_code":"RU",
    "gn:dem":756,
    "gn:feature_class":"P",
    "gn:feature_code":"PPL",
    "gn:name":"Nimgerkan",
    "gn:population":0,
    "gn:timezone":"Asia/Yakutsk",
    "iso:country":"RU",
    "name:eng_x_preferred":[
        "Nimgerkan"
    ],
    "name:nor_x_preferred":[
        "Nimgerkan"
    ],
    "name:rus_x_preferred":[
        "\u041d\u0438\u043c\u0433\u0435\u0440\u043a\u0430\u043d"
    ],
    "name:und_x_variant":[
        "Levyy Nimnyrkan",
        "Levyy Nimgerkan"
    ],
    "wof:name":"Nimgerkan",
    "wof:placetype":"locality"
},
  "geometry": {"coordinates":[125.05195000000001,58.36241999999999],"type":"Point"}
}