{
  "type": "Feature",
  "properties": {
    "gn:admin1_code":"69",
    "gn:asciiname":"Morachevo",
    "gn:country_code":"RU",
    "gn:dem":209,
    "gn:feature_class":"P",
    "gn:feature_code":"PPL",
    "gn:name":"Morach\u00ebvo",
    "gn:population":0,
    "gn:timezone":"Europe/Moscow",
    "iso:country":"RU",
    "name:rus_x_preferred":[
        "\u041c\u043e\u0440\u0430\u0447\u0451\u0432\u043e"
    ],
    "name:und_x_variant":[
        "Khutora Morochevo",
        "Moroch\u00ebvo",
        "Morach\u00ebvo"
    ],
    "wof:name":"Morachevo",
    "wof:placetype":"locality"
},
  "geometry": {"coordinates":[32.02718,54.4805],"type":"Point"}
}