{
  "type": "Feature",
  "properties": {
    "gn:admin1_code":"60",
    "gn:asciiname":"Gubanovo",
    "gn:country_code":"RU",
    "gn:dem":111,
    "gn:feature_class":"P",
    "gn:feature_code":"PPL",
    "gn:name":"Gubanovo",
    "gn:population":0,
    "gn:timezone":"Europe/Moscow",
    "iso:country":"RU",
    "name:rus_x_preferred":[
        "\u0413\u0443\u0431\u0430\u043d\u043e\u0432\u043e"
    ],
    "wof:name":"Gubanovo",
    "wof:placetype":"locality"
},
  "geometry": {"coordinates":[28.84769,56.84703],"type":"Point"}
}