{
  "type": "Feature",
  "properties": {
    "gn:admin1_code":"8.0",
    "gn:asciiname":"Fayzullino",
    "gn:country_code":"RU",
    "gn:dem":474,
    "gn:feature_class":"P",
    "gn:feature_code":"PPL",
    "gn:name":"Fayzullino",
    "gn:population":0,
    "gn:timezone":"Asia/Yekaterinburg",
    "iso:country":"RU",
    "name:rus_x_preferred":[
        "\u0424\u0430\u0439\u0437\u0443\u043b\u043b\u0438\u043d\u043e"
    ],
    "name:und_x_variant":[
        "Fayzullina",
        "Fayzulina",
        "Fayzulino",
        "Fayzullino"
    ],
    "wof:name":"Fayzullino",
    "wof:placetype":"locality"
},
  "geometry": {"coordinates":[58.44611,52.58694000000001],"type":"Point"}
}