{
  "type": "Feature",
  "properties": {
    "gn:admin1_code":"73",
    "gn:asciiname":"Batyr",
    "gn:country_code":"RU",
    "gn:dem":147,
    "gn:feature_class":"P",
    "gn:feature_code":"PPL",
    "gn:name":"Batyr",
    "gn:population":0,
    "gn:timezone":"Europe/Moscow",
    "iso:country":"RU",
    "name:rus_x_preferred":[
        "\u0411\u0430\u0442\u044b\u0440"
    ],
    "name:und_x_variant":[
        "\u0411\u0430\u0442\u044b\u0440"
    ],
    "wof:name":"Batyr",
    "wof:placetype":"locality"
},
  "geometry": {"coordinates":[50.9636,54.7813],"type":"Point"}
}