{
  "type": "Feature",
  "properties": {
    "gn:admin1_code":"83.0",
    "gn:asciiname":"Voronino",
    "gn:country_code":"RU",
    "gn:dem":129,
    "gn:feature_class":"P",
    "gn:feature_code":"PPL",
    "gn:name":"Voronino",
    "gn:population":232,
    "gn:timezone":"Europe/Moscow",
    "iso:country":"RU",
    "wof:name":"Voronino",
    "wof:placetype":"locality",
    "wof:population":232
},
  "geometry": {"coordinates":[41.9912,56.16147],"type":"Point"}
}