{
  "type": "Feature",
  "properties": {
    "gn:admin1_code":"80.0",
    "gn:asciiname":"Makary",
    "gn:country_code":"RU",
    "gn:dem":235,
    "gn:feature_class":"P",
    "gn:feature_code":"PPL",
    "gn:name":"Makary",
    "gn:population":0,
    "gn:timezone":"Europe/Samara",
    "iso:country":"RU",
    "name:rus_x_preferred":[
        "\u041c\u0430\u043a\u0430\u0440\u044b"
    ],
    "wof:name":"Makary",
    "wof:placetype":"locality"
},
  "geometry": {"coordinates":[53.5126,58.2256],"type":"Point"}
}