{
  "type": "Feature",
  "properties": {
    "gn:admin1_code":"49",
    "gn:asciiname":"Lesozavodskiy",
    "gn:country_code":"RU",
    "gn:dem":6,
    "gn:feature_class":"P",
    "gn:feature_code":"PPL",
    "gn:name":"Lesozavodskiy",
    "gn:population":0,
    "gn:timezone":"Europe/Moscow",
    "iso:country":"RU",
    "name:che_x_preferred":[
        "\u041b\u0435\u0441\u043e\u0437\u0430\u0432\u043e\u0434\u0441\u043a\u0438"
    ],
    "name:eng_x_preferred":[
        "Lesozavodskiy"
    ],
    "name:fin_x_preferred":[
        "Lesozavodski"
    ],
    "name:hye_x_preferred":[
        "\u053c\u0565\u057d\u0578\u0566\u0561\u057e\u0578\u0564\u057d\u056f\u056b"
    ],
    "name:nor_x_preferred":[
        "Lesozavodskij"
    ],
    "name:rus_x_preferred":[
        "\u041b\u0435\u0441\u043e\u0437\u0430\u0432\u043e\u0434\u0441\u043a\u0438\u0439"
    ],
    "name:und_x_variant":[
        "Lesozavod Nomer Sed\u2019moy"
    ],
    "wof:name":"Lesozavodskiy",
    "wof:placetype":"locality"
},
  "geometry": {"coordinates":[32.83891,66.72991999999999],"type":"Point"}
}