{
  "type": "Feature",
  "properties": {
    "gn:country":"RU",
    "gn:fcode":"PPL",
    "gn:population":4711,
    "iso:country":"RU",
    "name:fin_x_preferred":[
        "Venn\u00e4in-Vuissakka"
    ],
    "name:nor_x_preferred":[
        "Russko-Vysotskoje"
    ],
    "name:rus_x_preferred":[
        "\u0420\u0443\u0441\u0441\u043a\u043e-\u0412\u044b\u0441\u043e\u0446\u043a\u043e\u0435"
    ],
    "name:und_x_variant":[
        "Vysotskoye"
    ],
    "qs:name":"Russko-Vysotskoye",
    "qs:name_adm0":"Russia",
    "qs:name_adm1":"Leningrad Oblast",
    "qs:photos_9k":1,
    "qs:photos_9r":1,
    "qs:photos_all":2,
    "qs:photos_sr":0,
    "qs:placetype":"Town",
    "qs:pop_sr":"4",
    "wof:name":"Russko-Vysotskoye",
    "wof:placetype":"locality",
    "wof:population":4711
},
  "geometry": {"coordinates":[29.94404,59.69963],"type":"Point"}
}