{
  "type": "Feature",
  "properties": {
    "gn:admin1_code":"41.0",
    "gn:asciiname":"Degtyarnoye",
    "gn:country_code":"RU",
    "gn:dem":232,
    "gn:feature_class":"P",
    "gn:feature_code":"PPL",
    "gn:name":"Degtyarnoye",
    "gn:population":0,
    "gn:timezone":"Europe/Moscow",
    "iso:country":"RU",
    "name:rus_x_preferred":[
        "\u0414\u0435\u0433\u0442\u044f\u0440\u043d\u043e\u0435"
    ],
    "name:und_x_variant":[
        "Degtyarnaya",
        "Degtyarnoye"
    ],
    "wof:name":"Degtyarnoye",
    "wof:placetype":"locality"
},
  "geometry": {"coordinates":[37.5345,51.5599],"type":"Point"}
}