{
  "type": "Feature",
  "properties": {
    "gn:admin1_code":"77",
    "gn:asciiname":"Zubikhino",
    "gn:cc2":"RU",
    "gn:country_code":"RU",
    "gn:dem":291,
    "gn:feature_class":"P",
    "gn:feature_code":"PPL",
    "gn:name":"Zubikhino",
    "gn:population":0,
    "gn:timezone":"Europe/Moscow",
    "iso:country":"RU",
    "name:und_x_variant":[
        "Zubishki",
        "Zubikhino"
    ],
    "wof:name":"Zubikhino",
    "wof:placetype":"locality"
},
  "geometry": {"coordinates":[31.71667,56.93333000000001],"type":"Point"}
}