{
  "type": "Feature",
  "properties": {
    "gn:admin1_code":"42",
    "gn:asciiname":"Vorontsovo",
    "gn:cc2":"RU",
    "gn:country_code":"RU",
    "gn:dem":125,
    "gn:feature_class":"P",
    "gn:feature_code":"PPL",
    "gn:name":"Vorontsovo",
    "gn:population":0,
    "gn:timezone":"Europe/Moscow",
    "iso:country":"RU",
    "name:fin_x_preferred":[
        "Karvala"
    ],
    "wof:name":"Vorontsovo",
    "wof:placetype":"locality"
},
  "geometry": {"coordinates":[29.85878,60.2954],"type":"Point"}
}