{
  "type": "Feature",
  "properties": {
    "gn:admin1_code":"34",
    "gn:asciiname":"Petropavlovskiy",
    "gn:country_code":"RU",
    "gn:dem":189,
    "gn:feature_class":"P",
    "gn:feature_code":"PPL",
    "gn:name":"Petropavlovskiy",
    "gn:population":0,
    "gn:timezone":"Europe/Moscow",
    "iso:country":"RU",
    "name:rus_x_preferred":[
        "\u041f\u0435\u0442\u0440\u043e\u043f\u0430\u0432\u043b\u043e\u0432\u0441\u043a\u0438\u0439"
    ],
    "wof:name":"Petropavlovskiy",
    "wof:placetype":"locality"
},
  "geometry": {"coordinates":[49.35,59.53333000000001],"type":"Point"}
}