{
  "type": "Feature",
  "properties": {
    "gn:admin1_code":"69",
    "gn:asciiname":"Staryye Rovni",
    "gn:country_code":"RU",
    "gn:dem":200,
    "gn:feature_class":"P",
    "gn:feature_code":"PPL",
    "gn:name":"Staryye Rovni",
    "gn:population":0,
    "gn:timezone":"Europe/Moscow",
    "iso:country":"RU",
    "name:rus_x_preferred":[
        "\u0421\u0442\u0430\u0440\u044b\u0435 \u0420\u043e\u0432\u043d\u0438"
    ],
    "wof:name":"Staryye Rovni",
    "wof:placetype":"locality"
},
  "geometry": {"coordinates":[32.5631,55.5281],"type":"Point"}
}