{
  "type": "Feature",
  "properties": {
    "gn:admin1_code":"42",
    "gn:asciiname":"Veymarn",
    "gn:country_code":"RU",
    "gn:dem":76,
    "gn:feature_class":"P",
    "gn:feature_code":"PPL",
    "gn:name":"Veymarn",
    "gn:population":0,
    "gn:timezone":"Europe/Moscow",
    "iso:country":"RU",
    "name:rus_x_preferred":[
        "\u0412\u0435\u0439\u043c\u0430\u0440\u043d"
    ],
    "name:und_x_variant":[
        "Wernern",
        "Veinarn",
        "Weinern",
        "Weymarn",
        "Veymarn"
    ],
    "wof:name":"Veymarn",
    "wof:placetype":"locality"
},
  "geometry": {"coordinates":[28.84558,59.39458000000001],"type":"Point"}
}