{
  "type": "Feature",
  "properties": {
    "gn:admin1_code":"33.0",
    "gn:asciiname":"Batalovo",
    "gn:country_code":"RU",
    "gn:dem":194,
    "gn:feature_class":"P",
    "gn:feature_code":"PPL",
    "gn:name":"Batalovo",
    "gn:population":0,
    "gn:timezone":"Europe/Kirov",
    "iso:country":"RU",
    "name:eng_x_preferred":[
        "Batalovo"
    ],
    "name:nor_x_preferred":[
        "Batalovo"
    ],
    "name:rus_x_preferred":[
        "\u0411\u0430\u0442\u0430\u043b\u043e\u0432\u043e"
    ],
    "wof:name":"Batalovo",
    "wof:placetype":"locality"
},
  "geometry": {"coordinates":[52.54716,59.66667],"type":"Point"}
}