{
  "type": "Feature",
  "properties": {
    "gn:admin1_code":"46",
    "gn:asciiname":"Yezhovka",
    "gn:country_code":"RU",
    "gn:dem":192,
    "gn:feature_class":"P",
    "gn:feature_code":"PPL",
    "gn:name":"Yezhovka",
    "gn:population":0,
    "gn:timezone":"Europe/Moscow",
    "iso:country":"RU",
    "name:rus_x_preferred":[
        "\u0415\u0436\u043e\u0432\u043a\u0430"
    ],
    "name:und_x_variant":[
        "\u0415\u0436\u043e\u0432\u043a\u0430"
    ],
    "wof:name":"Yezhovka",
    "wof:placetype":"locality"
},
  "geometry": {"coordinates":[45.6803,54.8948],"type":"Point"}
}