{
  "type": "Feature",
  "properties": {
    "gn:admin1_code":"23",
    "gn:asciiname":"Komsomol'sk",
    "gn:country_code":"RU",
    "gn:dem":23,
    "gn:feature_class":"P",
    "gn:feature_code":"PPL",
    "gn:name":"Komsomol\u2019sk",
    "gn:population":0,
    "gn:timezone":"Europe/Kaliningrad",
    "iso:country":"RU",
    "name:eng_x_preferred":[
        "Komsomol'sk"
    ],
    "name:nor_x_preferred":[
        "Komsomolsk"
    ],
    "name:rus_x_preferred":[
        "\u041a\u043e\u043c\u0441\u043e\u043c\u043e\u043b\u044c\u0441\u043a"
    ],
    "name:und_x_variant":[
        "Levenkhagen",
        "L\u00f6wenhagen",
        "\u041a\u043e\u043c\u0441\u043e\u043c\u043e\u043b\u044c\u0441\u043a",
        "Komsomol\u2019sk"
    ],
    "wof:name":"Komsomol'sk",
    "wof:placetype":"locality"
},
  "geometry": {"coordinates":[20.75369,54.62805],"type":"Point"}
}