{
  "type": "Feature",
  "properties": {
    "gn:admin1_code":"11",
    "gn:asciiname":"Tayshikhino",
    "gn:cc2":"RU",
    "gn:country_code":"RU",
    "gn:dem":538,
    "gn:feature_class":"P",
    "gn:feature_code":"PPL",
    "gn:name":"Tayshikhino",
    "gn:population":0,
    "gn:timezone":"Asia/Irkutsk",
    "iso:country":"RU",
    "name:und_x_variant":[
        "Tayshilchino",
        "Tayshikhino"
    ],
    "wof:name":"Tayshikhino",
    "wof:placetype":"locality"
},
  "geometry": {"coordinates":[107.41667,51.83333],"type":"Point"}
}