{
  "type": "Feature",
  "properties": {
    "gn:admin1_code":"67.0",
    "gn:asciiname":"Danilovka",
    "gn:country_code":"RU",
    "gn:dem":88,
    "gn:feature_class":"P",
    "gn:feature_code":"PPL",
    "gn:name":"Danilovka",
    "gn:population":0,
    "gn:timezone":"Europe/Saratov",
    "iso:country":"RU",
    "name:rus_x_preferred":[
        "\u0414\u0430\u043d\u0438\u043b\u043e\u0432\u043a\u0430"
    ],
    "name:und_x_variant":[
        "\u0414\u0430\u043d\u0438\u043b\u043e\u0432\u043a\u0430"
    ],
    "wof:name":"Danilovka",
    "wof:placetype":"locality"
},
  "geometry": {"coordinates":[49.9349,52.0688],"type":"Point"}
}