{
  "type": "Feature",
  "properties": {
    "gn:admin1_code":"88.0",
    "gn:asciiname":"Pochinok",
    "gn:country_code":"RU",
    "gn:dem":174,
    "gn:feature_class":"P",
    "gn:feature_code":"PPL",
    "gn:name":"Pochinok",
    "gn:population":0,
    "gn:timezone":"Europe/Moscow",
    "iso:country":"RU",
    "name:fin_x_preferred":[
        "Pot\u0161inok"
    ],
    "name:rus_x_preferred":[
        "\u041f\u043e\u0447\u0438\u043d\u043e\u043a"
    ],
    "name:tat_x_preferred":[
        "\u041f\u043e\u0447\u0438\u043d\u043e\u043a"
    ],
    "name:ukr_x_preferred":[
        "\u041f\u043e\u0447\u0438\u043d\u043e\u043a"
    ],
    "wof:name":"Pochinok",
    "wof:placetype":"locality"
},
  "geometry": {"coordinates":[40.16111,58.08024],"type":"Point"}
}