{
  "type": "Feature",
  "properties": {
    "gn:country":"RU",
    "gn:fcode":"PPL",
    "gn:pop":6236,
    "iso:country":"RU",
    "name:rus_x_preferred":[
        "\u041a\u043e\u0440\u0435\u043d\u0435\u0432\u043e"
    ],
    "name:rus_x_variant":[
        "\u041a\u043e\u0440\u0435\u043d\u0451\u0432\u043e"
    ],
    "name:unk_x_variant":[
        "Korenewo"
    ],
    "qs:name":"Koren\u00ebvo",
    "qs:photos_9r":0,
    "qs:photos_sr":0,
    "qs:pop_sr":"5",
    "wd:wordcount":130,
    "wof:name":"Koren\u00ebvo",
    "wof:placetype":"locality",
    "wof:population":6236
},
  "geometry": {"coordinates":[34.908,51.4119],"type":"Point"}
}