{
  "type": "Feature",
  "properties": {
    "gn:admin1_code":"25",
    "gn:asciiname":"Fitinino",
    "gn:country_code":"RU",
    "gn:dem":211,
    "gn:feature_class":"P",
    "gn:feature_code":"PPL",
    "gn:name":"Fitinino",
    "gn:population":0,
    "gn:timezone":"Europe/Moscow",
    "iso:country":"RU",
    "name:rus_x_preferred":[
        "\u0424\u0438\u0442\u0438\u043d\u0438\u043d\u043e"
    ],
    "name:rus_x_variant":[
        "\u0424\u0435\u0442\u0438\u043d\u044c\u0438\u043d\u043e"
    ],
    "name:und_x_variant":[
        "Fetin\u2019ino",
        "Fitinino"
    ],
    "wof:name":"Fitinino",
    "wof:placetype":"locality"
},
  "geometry": {"coordinates":[36.51799000000001,54.5474],"type":"Point"}
}