{
  "type": "Feature",
  "properties": {
    "gn:admin1_code":"73",
    "gn:asciiname":"Bol'shiye Saltyki",
    "gn:country_code":"RU",
    "gn:dem":108,
    "gn:feature_class":"P",
    "gn:feature_code":"PPL",
    "gn:name":"Bol\u2019shiye Saltyki",
    "gn:population":0,
    "gn:timezone":"Europe/Moscow",
    "iso:country":"RU",
    "name:rus_x_preferred":[
        "\u0411\u043e\u043b\u044c\u0448\u0438\u0435 \u0421\u0430\u043b\u0442\u044b\u043a\u0438"
    ],
    "name:und_x_variant":[
        "Bol\u2019shiye Saltyki"
    ],
    "wof:name":"Bol'shiye Saltyki",
    "wof:placetype":"locality"
},
  "geometry": {"coordinates":[49.0731,55.2605],"type":"Point"}
}