{
  "type": "Feature",
  "properties": {
    "gn:admin1_code":"33",
    "gn:asciiname":"Grigor'yevo",
    "gn:country_code":"RU",
    "gn:dem":113,
    "gn:feature_class":"P",
    "gn:feature_code":"PPL",
    "gn:name":"Grigor\u2019yevo",
    "gn:population":0,
    "gn:timezone":"Europe/Kirov",
    "iso:country":"RU",
    "name:rus_x_preferred":[
        "\u0413\u0440\u0438\u0433\u043e\u0440\u044c\u0435\u0432\u043e"
    ],
    "name:und_x_variant":[
        "Grigor\u2019yevo"
    ],
    "wof:name":"Grigor'yevo",
    "wof:placetype":"locality"
},
  "geometry": {"coordinates":[47.8426,57.8841],"type":"Point"}
}