{
  "type": "Feature",
  "properties": {
    "gn:admin1_code":"65",
    "gn:asciiname":"Makar'yevka",
    "gn:country_code":"RU",
    "gn:dem":51,
    "gn:feature_class":"P",
    "gn:feature_code":"PPL",
    "gn:name":"Makar\u2019yevka",
    "gn:population":0,
    "gn:timezone":"Europe/Samara",
    "iso:country":"RU",
    "name:eng_x_preferred":[
        "Makar'yevka"
    ],
    "name:nor_x_preferred":[
        "Makarjevka"
    ],
    "name:rus_x_preferred":[
        "\u041c\u0430\u043a\u0430\u0440\u044c\u0435\u0432\u043a\u0430"
    ],
    "name:und_x_variant":[
        "Makar\u2019yevskiy",
        "Makar\u2019yevskoye",
        "\u041c\u0430\u043a\u0430\u0440\u044c\u0435\u0432\u043a\u0430",
        "Makar\u2019yevka"
    ],
    "wof:name":"Makar'yevka",
    "wof:placetype":"locality"
},
  "geometry": {"coordinates":[48.97722,52.84721999999999],"type":"Point"}
}