{
  "type": "Feature",
  "properties": {
    "gn:admin1_code":"33.0",
    "gn:asciiname":"Inda",
    "gn:country_code":"RU",
    "gn:dem":122,
    "gn:feature_class":"P",
    "gn:feature_code":"PPL",
    "gn:name":"Inda",
    "gn:population":0,
    "gn:timezone":"Europe/Kirov",
    "iso:country":"RU",
    "name:ceb_x_preferred":[
        "Inda"
    ],
    "name:deu_x_preferred":[
        "Inda"
    ],
    "name:rus_x_preferred":[
        "\u0418\u043d\u0434\u0430"
    ],
    "name:swe_x_preferred":[
        "Inda"
    ],
    "name:und_x_variant":[
        "Bol\u2019shaya Idna",
        "Bol\u2019shaya Inda",
        "Inda"
    ],
    "wof:name":"Inda",
    "wof:placetype":"locality"
},
  "geometry": {"coordinates":[47.7105,57.339],"type":"Point"}
}