{
  "type": "Feature",
  "properties": {
    "gn:admin1_code":"71",
    "gn:asciiname":"Sokolova",
    "gn:country_code":"RU",
    "gn:dem":96,
    "gn:feature_class":"P",
    "gn:feature_code":"PPL",
    "gn:name":"Sokolova",
    "gn:population":0,
    "gn:timezone":"Asia/Yekaterinburg",
    "iso:country":"RU",
    "name:rus_x_preferred":[
        "\u0421\u043e\u043a\u043e\u043b\u043e\u0432\u0430"
    ],
    "name:und_x_variant":[
        "Sokolovo",
        "Sokolova"
    ],
    "wof:name":"Sokolova",
    "wof:placetype":"locality"
},
  "geometry": {"coordinates":[63.6447,57.35527],"type":"Point"}
}