{
  "type": "Feature",
  "properties": {
    "gn:admin1_code":"47",
    "gn:asciiname":"Staroye Bobrenevo",
    "gn:country_code":"RU",
    "gn:dem":109,
    "gn:feature_class":"P",
    "gn:feature_code":"PPL",
    "gn:name":"Staroye Bobrenevo",
    "gn:population":228,
    "gn:timezone":"Europe/Moscow",
    "iso:country":"RU",
    "name:rus_x_preferred":[
        "\u0421\u0442\u0430\u0440\u043e\u0435 \u0411\u043e\u0431\u0440\u0435\u043d\u0435\u0432\u043e"
    ],
    "name:und_x_variant":[
        "\u0421\u0442\u0430\u0440\u043e\u0435 \u0411\u043e\u0431\u0440\u0435\u043d\u0435\u0432\u043e"
    ],
    "wof:name":"Staroye Bobrenevo",
    "wof:placetype":"locality",
    "wof:population":228
},
  "geometry": {"coordinates":[38.7606,55.12021],"type":"Point"}
}