{
  "type": "Feature",
  "properties": {
    "gn:admin1_code":"84",
    "gn:asciiname":"Imeni Vtoroy Pyatiletki",
    "gn:country_code":"RU",
    "gn:dem":21,
    "gn:feature_class":"P",
    "gn:feature_code":"PPL",
    "gn:name":"Imeni Vtoroy Pyatiletki",
    "gn:population":0,
    "gn:timezone":"Europe/Volgograd",
    "iso:country":"RU",
    "name:rus_x_preferred":[
        "\u0418\u043c\u0435\u043d\u0438 \u0412\u0442\u043e\u0440\u043e\u0439 \u041f\u044f\u0442\u0438\u043b\u0435\u0442\u043a\u0438"
    ],
    "name:und_x_variant":[
        "\u0418\u043c\u0435\u043d\u0438 \u0412\u0442\u043e\u0440\u043e\u0439 \u041f\u044f\u0442\u0438\u043b\u0435\u0442\u043a\u0438"
    ],
    "wof:name":"Imeni Vtoroy Pyatiletki",
    "wof:placetype":"locality"
},
  "geometry": {"coordinates":[45.14778,48.95056],"type":"Point"}
}