{
  "type": "Feature",
  "properties": {
    "gn:admin1_code":"40",
    "gn:asciiname":"Trebushinnoye",
    "gn:cc2":"RU",
    "gn:country_code":"RU",
    "gn:dem":135,
    "gn:feature_class":"P",
    "gn:feature_code":"PPL",
    "gn:name":"Trebushinnoye",
    "gn:population":0,
    "gn:timezone":"Asia/Yekaterinburg",
    "iso:country":"RU",
    "name:eng_x_preferred":[
        "Trebushinnoye"
    ],
    "name:nor_x_preferred":[
        "Trebusjinnoje"
    ],
    "name:rus_x_preferred":[
        "\u0422\u0440\u0435\u0431\u0443\u0448\u0438\u043d\u043d\u043e\u0435"
    ],
    "name:und_x_variant":[
        "Trebushinoye",
        "Trebushinnoye"
    ],
    "wof:name":"Trebushinnoye",
    "wof:placetype":"locality"
},
  "geometry": {"coordinates":[66.86721999999999,55.04861],"type":"Point"}
}