{
  "type": "Feature",
  "properties": {
    "gn:admin1_code":"8.0",
    "gn:asciiname":"Chatovo",
    "gn:country_code":"RU",
    "gn:dem":86,
    "gn:feature_class":"P",
    "gn:feature_code":"PPL",
    "gn:name":"Chatovo",
    "gn:population":0,
    "gn:timezone":"Asia/Yekaterinburg",
    "iso:country":"RU",
    "name:rus_x_preferred":[
        "\u0427\u0430\u0442\u043e\u0432\u043e"
    ],
    "wof:name":"Chatovo",
    "wof:placetype":"locality"
},
  "geometry": {"coordinates":[55.25,55.28333000000001],"type":"Point"}
}