{
  "type": "Feature",
  "properties": {
    "gn:admin1_code":"61.0",
    "gn:asciiname":"Budarki",
    "gn:cc2":"RU",
    "gn:country_code":"RU",
    "gn:dem":126,
    "gn:feature_class":"P",
    "gn:feature_code":"PPL",
    "gn:name":"Budarki",
    "gn:population":0,
    "gn:timezone":"Europe/Moscow",
    "iso:country":"RU",
    "name:rus_x_preferred":[
        "\u0411\u0443\u0434\u0430\u0440\u043a\u0438"
    ],
    "name:und_x_variant":[
        "Budarka",
        "Budarki"
    ],
    "wof:name":"Budarki",
    "wof:placetype":"locality"
},
  "geometry": {"coordinates":[41.92917,48.27361],"type":"Point"}
}