{
  "type": "Feature",
  "properties": {
    "gn:admin1_code":"55",
    "gn:asciiname":"Grafskiy",
    "gn:country_code":"RU",
    "gn:dem":165,
    "gn:feature_class":"P",
    "gn:feature_code":"PPL",
    "gn:name":"Grafskiy",
    "gn:population":0,
    "gn:timezone":"Asia/Yekaterinburg",
    "iso:country":"RU",
    "name:rus_x_preferred":[
        "\u0413\u0440\u0430\u0444\u0441\u043a\u0438\u0439"
    ],
    "wof:name":"Grafskiy",
    "wof:placetype":"locality"
},
  "geometry": {"coordinates":[53.46666999999999,53.13333000000001],"type":"Point"}
}