{
  "type": "Feature",
  "properties": {
    "gn:admin1_code":"53",
    "gn:asciiname":"Malinovskiy",
    "gn:country_code":"RU",
    "gn:dem":140,
    "gn:feature_class":"P",
    "gn:feature_code":"PPL",
    "gn:name":"Malinovskiy",
    "gn:population":0,
    "gn:timezone":"Asia/Novosibirsk",
    "iso:country":"RU",
    "name:eng_x_preferred":[
        "Malinovskiy"
    ],
    "name:nor_x_preferred":[
        "Malinovskij"
    ],
    "name:rus_x_preferred":[
        "\u041c\u0430\u043b\u0438\u043d\u043e\u0432\u0441\u043a\u0438\u0439"
    ],
    "name:und_x_variant":[
        "\u041c\u0430\u043b\u0438\u043d\u043e\u0432\u0441\u043a\u0438\u0439",
        "Malinovskiy"
    ],
    "wof:name":"Malinovskiy",
    "wof:placetype":"locality"
},
  "geometry": {"coordinates":[80.91667,54.83333],"type":"Point"}
}