{
  "type": "Feature",
  "properties": {
    "gn:admin1_code":"47",
    "gn:asciiname":"Pirochi",
    "gn:country_code":"RU",
    "gn:dem":112,
    "gn:feature_class":"P",
    "gn:feature_code":"PPL",
    "gn:name":"Pirochi",
    "gn:population":0,
    "gn:timezone":"Europe/Moscow",
    "iso:country":"RU",
    "name:eng_x_preferred":[
        "Pirochi"
    ],
    "name:nor_x_preferred":[
        "Pirotsji"
    ],
    "name:rus_x_preferred":[
        "\u041f\u0438\u0440\u043e\u0447\u0438"
    ],
    "name:und_x_variant":[
        "\u041f\u0438\u0440\u043e\u0447\u0438",
        "Pirochi"
    ],
    "wof:name":"Pirochi",
    "wof:placetype":"locality"
},
  "geometry": {"coordinates":[38.94684,55.07241],"type":"Point"}
}