{
  "type": "Feature",
  "properties": {
    "gn:admin1_code":"71",
    "gn:asciiname":"Verkhnyaya Sysert'",
    "gn:country_code":"RU",
    "gn:dem":248,
    "gn:feature_class":"P",
    "gn:feature_code":"PPL",
    "gn:name":"Verkhnyaya Sysert\u2019",
    "gn:population":1115,
    "gn:timezone":"Asia/Yekaterinburg",
    "iso:country":"RU",
    "name:nor_x_preferred":[
        "Verkhnjaja Sysert"
    ],
    "name:rus_x_preferred":[
        "\u0412\u0435\u0440\u0445\u043d\u044f\u044f \u0421\u044b\u0441\u0435\u0440\u0442\u044c"
    ],
    "name:und_x_variant":[
        "Verkhne Sysertskiy",
        "Verkhnyaya Sysert\u2019"
    ],
    "wof:name":"Verkhnyaya Sysert'",
    "wof:placetype":"locality",
    "wof:population":1115
},
  "geometry": {"coordinates":[60.75563,56.44011999999999],"type":"Point"}
}