{
  "type": "Feature",
  "properties": {
    "gn:admin1_code":"23",
    "gn:asciiname":"Kanash",
    "gn:country_code":"RU",
    "gn:dem":21,
    "gn:feature_class":"P",
    "gn:feature_code":"PPL",
    "gn:name":"Kanash",
    "gn:population":0,
    "gn:timezone":"Europe/Kaliningrad",
    "iso:country":"RU",
    "name:eng_x_preferred":[
        "Kanash"
    ],
    "name:nor_x_preferred":[
        "Kanasj"
    ],
    "name:rus_x_preferred":[
        "\u041a\u0430\u043d\u0430\u0448"
    ],
    "name:und_x_variant":[
        "K\u00f6nigskirch",
        "Yurgaytshen",
        "Jurgaitschen",
        "Kana\u0161",
        "\u041a\u0430\u043d\u0430\u0448",
        "Kanash"
    ],
    "wof:name":"Kanash",
    "wof:placetype":"locality"
},
  "geometry": {"coordinates":[21.82881,54.95512],"type":"Point"}
}