{
  "type": "Feature",
  "properties": {
    "gn:admin1_code":"62",
    "gn:asciiname":"Sin'",
    "gn:country_code":"RU",
    "gn:dem":162,
    "gn:feature_class":"P",
    "gn:feature_code":"PPL",
    "gn:name":"Sin\u2019",
    "gn:population":0,
    "gn:timezone":"Europe/Moscow",
    "iso:country":"RU",
    "name:rus_x_preferred":[
        "\u0421\u0438\u043d\u044c"
    ],
    "name:und_x_variant":[
        "Semenovskiy",
        "Sin\u2019",
        "\u0421\u0438\u043d\u044c",
        "Sovkhoz Imeni Kotovskogo"
    ],
    "wof:name":"Sin'",
    "wof:placetype":"locality"
},
  "geometry": {"coordinates":[39.49294,53.9905],"type":"Point"}
}