{
  "type": "Feature",
  "properties": {
    "gn:admin1_code":"80",
    "gn:asciiname":"Aleksandrovo",
    "gn:country_code":"RU",
    "gn:dem":162,
    "gn:feature_class":"P",
    "gn:feature_code":"PPL",
    "gn:name":"Aleksandrovo",
    "gn:population":0,
    "gn:timezone":"Europe/Samara",
    "iso:country":"RU",
    "name:nor_x_preferred":[
        "Aleksandrovo"
    ],
    "name:rus_x_preferred":[
        "\u0410\u043b\u0435\u043a\u0441\u0430\u043d\u0434\u0440\u043e\u0432\u043e"
    ],
    "name:und_x_variant":[
        "Petukhovo",
        "Aleksandrovskaya",
        "Aleksandrovo"
    ],
    "wof:name":"Aleksandrovo",
    "wof:placetype":"locality"
},
  "geometry": {"coordinates":[52.35791,56.31857],"type":"Point"}
}