{
  "type": "Feature",
  "properties": {
    "gn:admin1_code":"71",
    "gn:asciiname":"Gazeta",
    "gn:country_code":"RU",
    "gn:dem":248,
    "gn:feature_class":"P",
    "gn:feature_code":"PPL",
    "gn:name":"Gazeta",
    "gn:population":0,
    "gn:timezone":"Asia/Yekaterinburg",
    "iso:country":"RU",
    "name:eus_x_preferred":[
        "Gazeta"
    ],
    "name:fra_x_preferred":[
        "Gazeta"
    ],
    "name:por_x_preferred":[
        "Gazeta"
    ],
    "name:rus_x_preferred":[
        "\u0413\u0430\u0437\u0435\u0442\u0430"
    ],
    "wof:name":"Gazeta",
    "wof:placetype":"locality"
},
  "geometry": {"coordinates":[61.1084,56.4611],"type":"Point"}
}