{
  "type": "Feature",
  "properties": {
    "gn:admin1_code":"42",
    "gn:asciiname":"Krasnoostrovskiy",
    "gn:country_code":"RU",
    "gn:dem":1,
    "gn:feature_class":"P",
    "gn:feature_code":"PPL",
    "gn:name":"Krasnoostrovskiy",
    "gn:population":0,
    "gn:timezone":"Europe/Moscow",
    "iso:country":"RU",
    "name:fin_x_preferred":[
        "Saarenp\u00e4\u00e4"
    ],
    "name:rus_x_preferred":[
        "\u041a\u0440\u0430\u0441\u043d\u043e\u043e\u0441\u0442\u0440\u043e\u0432\u0441\u043a\u0438\u0439"
    ],
    "name:und_x_variant":[
        "Sarenpya",
        "B\u2019yerkskiy",
        "Sarenpi",
        "Saarenpyaya",
        "Saarenpya",
        "Krasnoostrovskiy"
    ],
    "wof:name":"Krasnoostrovskiy",
    "wof:placetype":"locality"
},
  "geometry": {"coordinates":[28.66807,60.29553000000001],"type":"Point"}
}