{
  "type": "Feature",
  "properties": {
    "gn:admin1_code":"76",
    "gn:asciiname":"Skuratovo",
    "gn:country_code":"RU",
    "gn:dem":245,
    "gn:feature_class":"P",
    "gn:feature_code":"PPL",
    "gn:name":"Skuratovo",
    "gn:population":0,
    "gn:timezone":"Europe/Moscow",
    "iso:country":"RU",
    "name:rus_x_preferred":[
        "\u0421\u043a\u0443\u0440\u0430\u0442\u043e\u0432\u043e"
    ],
    "wof:name":"Skuratovo",
    "wof:placetype":"locality"
},
  "geometry": {"coordinates":[37.03556,53.56721999999999],"type":"Point"}
}