{
  "type": "Feature",
  "properties": {
    "gn:admin1_code":"77",
    "gn:asciiname":"Dubrovki",
    "gn:country_code":"RU",
    "gn:dem":148,
    "gn:feature_class":"P",
    "gn:feature_code":"PPL",
    "gn:name":"Dubrovki",
    "gn:population":0,
    "gn:timezone":"Europe/Moscow",
    "iso:country":"RU",
    "name:nor_x_preferred":[
        "Dubrovki"
    ],
    "name:rus_x_preferred":[
        "\u0414\u0443\u0431\u0440\u043e\u0432\u043a\u0438"
    ],
    "name:und_x_variant":[
        "Dubrovka",
        "Dubrovki"
    ],
    "wof:name":"Dubrovki",
    "wof:placetype":"locality"
},
  "geometry": {"coordinates":[35.53511,56.73112],"type":"Point"}
}