{
  "type": "Feature",
  "properties": {
    "gn:admin1_code":"47.0",
    "gn:asciiname":"Andriyankovo",
    "gn:country_code":"RU",
    "gn:dem":193,
    "gn:feature_class":"P",
    "gn:feature_code":"PPL",
    "gn:name":"Andriyankovo",
    "gn:population":0,
    "gn:timezone":"Europe/Moscow",
    "iso:country":"RU",
    "name:nor_x_preferred":[
        "Andrijankovo"
    ],
    "name:rus_x_preferred":[
        "\u0410\u043d\u0434\u0440\u0438\u044f\u043d\u043a\u043e\u0432\u043e"
    ],
    "wof:name":"Andriyankovo",
    "wof:placetype":"locality"
},
  "geometry": {"coordinates":[36.67365,55.74471],"type":"Point"}
}