{
  "type": "Feature",
  "properties": {
    "gn:admin1_code":"42",
    "gn:asciiname":"Malli",
    "gn:country_code":"RU",
    "gn:dem":59,
    "gn:feature_class":"P",
    "gn:feature_code":"PPL",
    "gn:name":"Malli",
    "gn:population":0,
    "gn:timezone":"Europe/Moscow",
    "iso:country":"RU",
    "name:rus_x_preferred":[
        "\u041c\u0430\u043b\u043b\u0438"
    ],
    "name:und_x_variant":[
        "\u041c\u0430\u043b\u043b\u0438"
    ],
    "wof:name":"Malli",
    "wof:placetype":"locality"
},
  "geometry": {"coordinates":[28.78333,59.46666999999999],"type":"Point"}
}