{
  "type": "Feature",
  "properties": {
    "gn:admin1_code":"24.0",
    "gn:asciiname":"Kol'kta",
    "gn:country_code":"RU",
    "gn:dem":-7,
    "gn:feature_class":"P",
    "gn:feature_code":"PPL",
    "gn:name":"Kol\u2019kta",
    "gn:population":0,
    "gn:timezone":"Europe/Volgograd",
    "iso:country":"RU",
    "name:rus_x_preferred":[
        "\u041a\u043e\u043b\u044c\u043a\u0442\u0430"
    ],
    "name:und_x_variant":[
        "Kol\u2019kta"
    ],
    "wof:name":"Kol'kta",
    "wof:placetype":"locality"
},
  "geometry": {"coordinates":[46.73778,47.51806],"type":"Point"}
}