{
  "type": "Feature",
  "properties": {
    "gn:admin1_code":"37.0",
    "gn:asciiname":"Pyrino Vtoroye",
    "gn:country_code":"RU",
    "gn:dem":155,
    "gn:feature_class":"P",
    "gn:feature_code":"PPL",
    "gn:name":"Pyrino Vtoroye",
    "gn:population":0,
    "gn:timezone":"Europe/Moscow",
    "iso:country":"RU",
    "name:und_x_variant":[
        "Pyrino",
        "Pyrino Vtoroye"
    ],
    "wof:name":"Pyrino Vtoroye",
    "wof:placetype":"locality"
},
  "geometry": {"coordinates":[41.41676,58.11925],"type":"Point"}
}