{
  "type": "Feature",
  "properties": {
    "gn:admin1_code":"41",
    "gn:asciiname":"Redkiye Dubki",
    "gn:country_code":"RU",
    "gn:dem":176,
    "gn:feature_class":"P",
    "gn:feature_code":"PPL",
    "gn:name":"Redkiye Dubki",
    "gn:population":0,
    "gn:timezone":"Europe/Moscow",
    "iso:country":"RU",
    "name:rus_x_preferred":[
        "\u0420\u0435\u0434\u043a\u0438\u0435 \u0414\u0443\u0431\u043a\u0438"
    ],
    "wof:name":"Redkiye Dubki",
    "wof:placetype":"locality"
},
  "geometry": {"coordinates":[34.6422,51.9694],"type":"Point"}
}