{
  "type": "Feature",
  "properties": {
    "gn:admin1_code":"69",
    "gn:asciiname":"Abakumovka",
    "gn:country_code":"RU",
    "gn:dem":208,
    "gn:feature_class":"P",
    "gn:feature_code":"PPL",
    "gn:name":"Abakumovka",
    "gn:population":0,
    "gn:timezone":"Europe/Moscow",
    "iso:country":"RU",
    "name:che_x_preferred":[
        "\u0410\u0431\u0430\u043a\u0443\u043c\u043e\u0432\u043a\u0430"
    ],
    "name:rus_x_preferred":[
        "\u0410\u0431\u0430\u043a\u0443\u043c\u043e\u0432\u043a\u0430"
    ],
    "wof:name":"Abakumovka",
    "wof:placetype":"locality"
},
  "geometry": {"coordinates":[32.28269,54.02406],"type":"Point"}
}