{
  "type": "Feature",
  "properties": {
    "gn:admin1_code":"20",
    "gn:asciiname":"Khakharey",
    "gn:country_code":"RU",
    "gn:dem":516,
    "gn:feature_class":"P",
    "gn:feature_code":"PPL",
    "gn:name":"Khakharey",
    "gn:population":0,
    "gn:timezone":"Asia/Irkutsk",
    "iso:country":"RU",
    "name:eng_x_preferred":[
        "Khakharey"
    ],
    "name:nor_x_preferred":[
        "Khakharej"
    ],
    "name:rus_x_preferred":[
        "\u0425\u0430\u0445\u0430\u0440\u0435\u0439"
    ],
    "name:und_x_variant":[
        "\u0425\u0430\u0445\u0430\u0440\u0435\u0439",
        "Khakharey"
    ],
    "wof:name":"Khakharey",
    "wof:placetype":"locality"
},
  "geometry": {"coordinates":[101.31571,55.25534],"type":"Point"}
}