{
  "type": "Feature",
  "properties": {
    "gn:admin1_code":"6.0",
    "gn:asciiname":"Kurgomen",
    "gn:country_code":"RU",
    "gn:dem":20,
    "gn:feature_class":"P",
    "gn:feature_code":"PPL",
    "gn:name":"Kurgomen",
    "gn:population":0,
    "gn:timezone":"Europe/Moscow",
    "iso:country":"RU",
    "name:eng_x_historical":[
        "Kurgomin"
    ],
    "name:eng_x_preferred":[
        "Kurgomin"
    ],
    "wof:name":"Kurgomen",
    "wof:placetype":"locality"
},
  "geometry": {"coordinates":[43.5183,62.63806999999999],"type":"Point"}
}