{
  "type": "Feature",
  "properties": {
    "gn:admin1_code":"41",
    "gn:asciiname":"Bezhentsev",
    "gn:country_code":"RU",
    "gn:dem":186,
    "gn:feature_class":"P",
    "gn:feature_code":"PPL",
    "gn:name":"Bezhentsev",
    "gn:population":0,
    "gn:timezone":"Europe/Moscow",
    "iso:country":"RU",
    "name:rus_x_preferred":[
        "\u0411\u0435\u0436\u0435\u043d\u0446\u0435\u0432"
    ],
    "wof:name":"Bezhentsev",
    "wof:placetype":"locality"
},
  "geometry": {"coordinates":[35.2361,51.5535],"type":"Point"}
}