{
  "type": "Feature",
  "properties": {
    "gn:admin1_code":"51.0",
    "gn:asciiname":"Podrezovo",
    "gn:country_code":"RU",
    "gn:dem":89,
    "gn:feature_class":"P",
    "gn:feature_code":"PPL",
    "gn:name":"Podrezovo",
    "gn:population":0,
    "gn:timezone":"Europe/Moscow",
    "iso:country":"RU",
    "name:rus_x_preferred":[
        "\u041f\u043e\u0434\u0440\u0435\u0437\u043e\u0432\u043e"
    ],
    "wof:name":"Podrezovo",
    "wof:placetype":"locality"
},
  "geometry": {"coordinates":[44.05959,56.52989],"type":"Point"}
}