{
  "type": "Feature",
  "properties": {
    "gn:admin1_code":"62.0",
    "gn:asciiname":"Aglomazovo",
    "gn:country_code":"RU",
    "gn:dem":105,
    "gn:feature_class":"P",
    "gn:feature_code":"PPL",
    "gn:name":"Aglomazovo",
    "gn:population":0,
    "gn:timezone":"Europe/Moscow",
    "iso:country":"RU",
    "name:nor_x_preferred":[
        "Aglomazovo"
    ],
    "name:rus_x_preferred":[
        "\u0410\u0433\u043b\u043e\u043c\u0430\u0437\u043e\u0432\u043e"
    ],
    "name:und_x_variant":[
        "Aglomasovo",
        "Aglomazovo"
    ],
    "wof:name":"Aglomazovo",
    "wof:placetype":"locality"
},
  "geometry": {"coordinates":[40.2665,54.4862],"type":"Point"}
}