{
  "type": "Feature",
  "properties": {
    "gn:admin1_code":"84",
    "gn:asciiname":"Topolevskiy",
    "gn:country_code":"RU",
    "gn:dem":79,
    "gn:feature_class":"P",
    "gn:feature_code":"PPL",
    "gn:name":"Topolevskiy",
    "gn:population":0,
    "gn:timezone":"Europe/Volgograd",
    "iso:country":"RU",
    "name:rus_x_preferred":[
        "\u0422\u043e\u043f\u043e\u043b\u0435\u0432\u0441\u043a\u0438\u0439"
    ],
    "wof:name":"Topolevskiy",
    "wof:placetype":"locality"
},
  "geometry": {"coordinates":[41.8158,50.86600000000001],"type":"Point"}
}