{
  "type": "Feature",
  "properties": {
    "gn:admin1_code":"20",
    "gn:asciiname":"Yarma",
    "gn:country_code":"RU",
    "gn:dem":572,
    "gn:feature_class":"P",
    "gn:feature_code":"PPL",
    "gn:name":"Yarma",
    "gn:population":0,
    "gn:timezone":"Asia/Irkutsk",
    "iso:country":"RU",
    "wof:name":"Yarma",
    "wof:placetype":"locality"
},
  "geometry": {"coordinates":[98.83568,54.39729000000001],"type":"Point"}
}