{
  "type": "Feature",
  "properties": {
    "gn:admin1_code":"90",
    "gn:asciiname":"Shakva",
    "gn:country_code":"RU",
    "gn:dem":118,
    "gn:feature_class":"P",
    "gn:feature_code":"PPL",
    "gn:name":"Shakva",
    "gn:population":0,
    "gn:timezone":"Asia/Yekaterinburg",
    "iso:country":"RU",
    "name:che_x_preferred":[
        "\u0428\u0430\u043a\u0432\u0430"
    ],
    "name:rus_x_preferred":[
        "\u0428\u0430\u043a\u0432\u0430"
    ],
    "wof:name":"Shakva",
    "wof:placetype":"locality"
},
  "geometry": {"coordinates":[56.9423,57.4577],"type":"Point"}
}