{
  "type": "Feature",
  "properties": {
    "gn:admin1_code":"77",
    "gn:asciiname":"Khotoshino",
    "gn:country_code":"RU",
    "gn:dem":209,
    "gn:feature_class":"P",
    "gn:feature_code":"PPL",
    "gn:name":"Khotoshino",
    "gn:population":0,
    "gn:timezone":"Europe/Moscow",
    "iso:country":"RU",
    "name:rus_x_preferred":[
        "\u0425\u043e\u0442\u043e\u0448\u0438\u043d\u043e"
    ],
    "wof:name":"Khotoshino",
    "wof:placetype":"locality"
},
  "geometry": {"coordinates":[33.29307,56.90354],"type":"Point"}
}