{
  "type": "Feature",
  "properties": {
    "gn:admin1_code":"72",
    "gn:asciiname":"Ranneye Utro",
    "gn:country_code":"RU",
    "gn:dem":151,
    "gn:feature_class":"P",
    "gn:feature_code":"PPL",
    "gn:name":"Ranneye Utro",
    "gn:population":0,
    "gn:timezone":"Europe/Moscow",
    "iso:country":"RU",
    "name:rus_x_preferred":[
        "\u0420\u0430\u043d\u043d\u0435\u0435 \u0423\u0442\u0440\u043e"
    ],
    "name:und_x_variant":[
        "Ranneyeuvo",
        "Ranneye Utro",
        "\u0420\u0430\u043d\u043d\u0435\u0435 \u0423\u0442\u0440\u043e"
    ],
    "wof:name":"Ranneye Utro",
    "wof:placetype":"locality"
},
  "geometry": {"coordinates":[41.67585,53.75216],"type":"Point"}
}