{
  "type": "Feature",
  "properties": {
    "gn:admin1_code":"71",
    "gn:asciiname":"Zobnina",
    "gn:country_code":"RU",
    "gn:dem":112,
    "gn:feature_class":"P",
    "gn:feature_code":"PPL",
    "gn:name":"Zobnina",
    "gn:population":0,
    "gn:timezone":"Asia/Yekaterinburg",
    "iso:country":"RU",
    "name:eng_x_preferred":[
        "Zobnina"
    ],
    "name:nor_x_preferred":[
        "Zobnina"
    ],
    "name:rus_x_preferred":[
        "\u0417\u043e\u0431\u043d\u0438\u043d\u0430"
    ],
    "wof:name":"Zobnina",
    "wof:placetype":"locality"
},
  "geometry": {"coordinates":[64.04857,57.22723000000001],"type":"Point"}
}