{
  "type": "Feature",
  "properties": {
    "gn:admin1_code":"10",
    "gn:asciiname":"Dvortsovaya Pushcha",
    "gn:country_code":"RU",
    "gn:dem":196,
    "gn:feature_class":"P",
    "gn:feature_code":"PPL",
    "gn:name":"Dvortsovaya Pushcha",
    "gn:population":0,
    "gn:timezone":"Europe/Moscow",
    "iso:country":"RU",
    "name:rus_x_preferred":[
        "\u0414\u0432\u043e\u0440\u0446\u043e\u0432\u0430\u044f \u041f\u0443\u0449\u0430"
    ],
    "name:und_x_variant":[
        "\u0414\u0432\u043e\u0440\u0446\u043e\u0432\u0430\u044f \u041f\u0443\u0449\u0430"
    ],
    "wof:name":"Dvortsovaya Pushcha",
    "wof:placetype":"locality"
},
  "geometry": {"coordinates":[33.70278,52.78417],"type":"Point"}
}