{
  "type": "Feature",
  "properties": {
    "gn:admin1_code":"91",
    "gn:asciiname":"Svatkovo",
    "gn:cc2":"RU",
    "gn:country_code":"RU",
    "gn:dem":176,
    "gn:feature_class":"P",
    "gn:feature_code":"PPL",
    "gn:name":"Svatkovo",
    "gn:population":0,
    "gn:timezone":"Asia/Krasnoyarsk",
    "iso:country":"RU",
    "name:und_x_variant":[
        "Svatkova",
        "Svatkovo"
    ],
    "wof:name":"Svatkovo",
    "wof:placetype":"locality"
},
  "geometry": {"coordinates":[94.46666999999999,57.16667],"type":"Point"}
}