{
  "type": "Feature",
  "properties": {
    "gn:admin1_code":"90",
    "gn:asciiname":"Uvaryazh",
    "gn:country_code":"RU",
    "gn:dem":275,
    "gn:feature_class":"P",
    "gn:feature_code":"PPL",
    "gn:name":"Uvaryazh",
    "gn:population":0,
    "gn:timezone":"Asia/Yekaterinburg",
    "iso:country":"RU",
    "name:und_x_variant":[
        "Uvaryash",
        "Uvaryazh"
    ],
    "wof:name":"Uvaryazh",
    "wof:placetype":"locality"
},
  "geometry": {"coordinates":[57.05676,56.28714],"type":"Point"}
}