{
  "type": "Feature",
  "properties": {
    "gn:admin1_code":"16",
    "gn:asciiname":"Savatkino",
    "gn:country_code":"RU",
    "gn:dem":142,
    "gn:feature_class":"P",
    "gn:feature_code":"PPL",
    "gn:name":"Savatkino",
    "gn:population":0,
    "gn:timezone":"Europe/Moscow",
    "iso:country":"RU",
    "name:rus_x_preferred":[
        "\u0421\u0430\u0432\u0430\u0442\u043a\u0438\u043d\u043e"
    ],
    "name:und_x_variant":[
        "\u0421\u0430\u0432\u0430\u0442\u043a\u0438\u043d\u043e"
    ],
    "wof:name":"Savatkino",
    "wof:placetype":"locality"
},
  "geometry": {"coordinates":[46.50587,55.99318],"type":"Point"}
}