{
  "type": "Feature",
  "properties": {
    "gn:admin1_code":"83.0",
    "gn:asciiname":"Plokhovo",
    "gn:country_code":"RU",
    "gn:dem":120,
    "gn:feature_class":"P",
    "gn:feature_code":"PPL",
    "gn:name":"Plokhovo",
    "gn:population":0,
    "gn:timezone":"Europe/Moscow",
    "iso:country":"RU",
    "name:rus_x_preferred":[
        "\u041f\u043b\u043e\u0445\u043e\u0432\u043e"
    ],
    "name:und_x_variant":[
        "\u041f\u043b\u043e\u0445\u043e\u0432\u043e"
    ],
    "wof:name":"Plokhovo",
    "wof:placetype":"locality"
},
  "geometry": {"coordinates":[41.62678,56.20216],"type":"Point"}
}