{
  "type": "Feature",
  "properties": {
    "gn:admin1_code":"65",
    "gn:asciiname":"Gorskiy",
    "gn:country_code":"RU",
    "gn:dem":71,
    "gn:feature_class":"P",
    "gn:feature_code":"PPL",
    "gn:name":"Gorskiy",
    "gn:population":0,
    "gn:timezone":"Europe/Samara",
    "iso:country":"RU",
    "name:rus_x_preferred":[
        "\u0413\u043e\u0440\u0441\u043a\u0438\u0439"
    ],
    "name:und_x_variant":[
        "\u0413\u043e\u0440\u0441\u043a\u0438\u0439"
    ],
    "wof:name":"Gorskiy",
    "wof:placetype":"locality"
},
  "geometry": {"coordinates":[51.0614,53.0238],"type":"Point"}
}