{
  "type": "Feature",
  "properties": {
    "gn:admin1_code":"60",
    "gn:asciiname":"Sergeykovo",
    "gn:country_code":"RU",
    "gn:dem":216,
    "gn:feature_class":"P",
    "gn:feature_code":"PPL",
    "gn:name":"Sergeykovo",
    "gn:population":0,
    "gn:timezone":"Europe/Moscow",
    "iso:country":"RU",
    "name:rus_x_preferred":[
        "\u0421\u0435\u0440\u0433\u0435\u0439\u043a\u043e\u0432\u043e"
    ],
    "name:und_x_variant":[
        "\u0421\u0435\u0440\u0433\u0435\u0439\u043a\u043e\u0432\u043e"
    ],
    "wof:name":"Sergeykovo",
    "wof:placetype":"locality"
},
  "geometry": {"coordinates":[29.7373,56.399],"type":"Point"}
}