{
  "type": "Feature",
  "properties": {
    "gn:admin1_code":"77",
    "gn:asciiname":"Vasnevo",
    "gn:country_code":"RU",
    "gn:dem":157,
    "gn:feature_class":"P",
    "gn:feature_code":"PPL",
    "gn:name":"Vasnevo",
    "gn:population":0,
    "gn:timezone":"Europe/Moscow",
    "iso:country":"RU",
    "name:rus_x_preferred":[
        "\u0412\u0430\u0441\u043d\u0435\u0432\u043e"
    ],
    "name:und_x_variant":[
        "\u0412\u0430\u0441\u043d\u0435\u0432\u043e"
    ],
    "wof:name":"Vasnevo",
    "wof:placetype":"locality"
},
  "geometry": {"coordinates":[37.6679,57.4123],"type":"Point"}
}