{
  "type": "Feature",
  "properties": {
    "gn:admin1_code":"33",
    "gn:asciiname":"Studenovo",
    "gn:country_code":"RU",
    "gn:dem":144,
    "gn:feature_class":"P",
    "gn:feature_code":"PPL",
    "gn:name":"Stud\u00ebnovo",
    "gn:population":0,
    "gn:timezone":"Europe/Kirov",
    "iso:country":"RU",
    "name:eng_x_preferred":[
        "Stud\u00ebnovo"
    ],
    "name:nor_x_preferred":[
        "Studenovo"
    ],
    "name:rus_x_preferred":[
        "\u0421\u0442\u0443\u0434\u0435\u043d\u043e\u0432\u043e"
    ],
    "name:rus_x_variant":[
        "\u0421\u0442\u0443\u0434\u0451\u043d\u043e\u0432\u043e"
    ],
    "wof:name":"Studenovo",
    "wof:placetype":"locality"
},
  "geometry": {"coordinates":[47.59713,57.17481],"type":"Point"}
}