{
  "type": "Feature",
  "properties": {
    "gn:admin1_code":"52",
    "gn:asciiname":"Isadi",
    "gn:country_code":"RU",
    "gn:dem":142,
    "gn:feature_class":"P",
    "gn:feature_code":"PPL",
    "gn:name":"Isadi",
    "gn:population":0,
    "gn:timezone":"Europe/Moscow",
    "iso:country":"RU",
    "name:rus_x_preferred":[
        "\u0418\u0441\u0430\u0434\u0438"
    ],
    "name:und_x_variant":[
        "\u0418\u0441\u0430\u0434\u0438"
    ],
    "wof:name":"Isadi",
    "wof:placetype":"locality"
},
  "geometry": {"coordinates":[34.53592,58.37915],"type":"Point"}
}