{
  "type": "Feature",
  "properties": {
    "gn:country":"RU",
    "gn:fcode":"PPL",
    "gn:pop":4239,
    "iso:country":"RU",
    "name:arm_x_preferred":[
        "\u0544\u0561\u0574\u0561"
    ],
    "name:dut_x_preferred":[
        "Mama"
    ],
    "name:eng_x_preferred":[
        "Mama"
    ],
    "name:fre_x_preferred":[
        "Mama"
    ],
    "name:ger_x_preferred":[
        "Mama"
    ],
    "name:hun_x_preferred":[
        "Mama"
    ],
    "name:ita_x_preferred":[
        "Mama"
    ],
    "name:jpn_x_preferred":[
        "\u30de\u30de"
    ],
    "name:lit_x_preferred":[
        "Mama"
    ],
    "name:nob_x_preferred":[
        "Mama"
    ],
    "name:nor_x_preferred":[
        "Mama"
    ],
    "name:pol_x_preferred":[
        "Mama"
    ],
    "name:rus_x_preferred":[
        "\u041c\u0430\u043c\u0430"
    ],
    "name:sah_x_preferred":[
        "\u041c\u0430\u043c\u0430"
    ],
    "name:unk_x_variant":[
        "\u041c\u0430\u043c\u0430"
    ],
    "qs:name":"Mama",
    "qs:photos_9r":0,
    "qs:photos_sr":0,
    "qs:pop_sr":"4",
    "wd:wordcount":662,
    "wof:name":"Mama",
    "wof:placetype":"locality",
    "wof:population":4239
},
  "geometry": {"coordinates":[112.89861000000001,58.31056],"type":"Point"}
}