{
  "type": "Feature",
  "properties": {
    "gn:admin1_code":"90",
    "gn:asciiname":"Grigor'yevskoye",
    "gn:country_code":"RU",
    "gn:dem":124,
    "gn:feature_class":"P",
    "gn:feature_code":"PPL",
    "gn:name":"Grigor\u2019yevskoye",
    "gn:population":0,
    "gn:timezone":"Asia/Yekaterinburg",
    "iso:country":"RU",
    "name:eng_x_preferred":[
        "Grigor'yevskoye"
    ],
    "name:nor_x_preferred":[
        "Grigorjevskoje"
    ],
    "name:rus_x_preferred":[
        "\u0413\u0440\u0438\u0433\u043e\u0440\u044c\u0435\u0432\u0441\u043a\u043e\u0435"
    ],
    "name:und_x_variant":[
        "Grigor\u2019yevskaya",
        "Grigor\u2019yevskoye",
        "\u0413\u0440\u0438\u0433\u043e\u0440\u044c\u0435\u0432\u0441\u043a\u043e\u0435"
    ],
    "wof:name":"Grigor'yevskoye",
    "wof:placetype":"locality"
},
  "geometry": {"coordinates":[55.3826,58.2183],"type":"Point"}
}