{
  "type": "Feature",
  "properties": {
    "gn:admin1_code":"78",
    "gn:asciiname":"Chernyy Yar",
    "gn:cc2":"RU",
    "gn:country_code":"RU",
    "gn:dem":35,
    "gn:feature_class":"P",
    "gn:feature_code":"PPL",
    "gn:name":"Ch\u00ebrnyy Yar",
    "gn:population":0,
    "gn:timezone":"Asia/Yekaterinburg",
    "iso:country":"RU",
    "name:rus_x_preferred":[
        "\u0427\u0451\u0440\u043d\u044b\u0439 \u042f\u0440"
    ],
    "name:und_x_variant":[
        "Cherny Yar",
        "Ch\u00ebrnyy Yar"
    ],
    "wof:name":"Chernyy Yar",
    "wof:placetype":"locality"
},
  "geometry": {"coordinates":[69.46666999999999,59.68333000000001],"type":"Point"}
}