{
  "type": "Feature",
  "properties": {
    "gn:admin1_code":"65",
    "gn:asciiname":"Tauzakovo",
    "gn:cc2":"RU",
    "gn:country_code":"RU",
    "gn:dem":139,
    "gn:feature_class":"P",
    "gn:feature_code":"PPL",
    "gn:name":"Tauzakovo",
    "gn:population":0,
    "gn:timezone":"Europe/Samara",
    "iso:country":"RU",
    "name:und_x_variant":[
        "Touzakovo",
        "Tauzakovo"
    ],
    "wof:name":"Tauzakovo",
    "wof:placetype":"locality"
},
  "geometry": {"coordinates":[51.16667,54.23333],"type":"Point"}
}