{
  "type": "Feature",
  "properties": {
    "gn:admin1_code":"20",
    "gn:asciiname":"Zerma",
    "gn:country_code":"RU",
    "gn:dem":450,
    "gn:feature_class":"P",
    "gn:feature_code":"PPL",
    "gn:name":"Zerma",
    "gn:population":0,
    "gn:timezone":"Asia/Irkutsk",
    "iso:country":"RU",
    "wof:name":"Zerma",
    "wof:placetype":"locality"
},
  "geometry": {"coordinates":[103.06667,55.76667],"type":"Point"}
}