{
  "type": "Feature",
  "properties": {
    "gn:admin1_code":"12",
    "gn:asciiname":"Kurdyukovskaya",
    "gn:country_code":"RU",
    "gn:dem":1,
    "gn:feature_class":"P",
    "gn:feature_code":"PPL",
    "gn:name":"Kurdyukovskaya",
    "gn:population":0,
    "gn:timezone":"Europe/Moscow",
    "iso:country":"RU",
    "name:che_x_preferred":[
        "Kurdyukovski"
    ],
    "name:che_x_variant":[
        "\u041a\u0443\u0440\u0434\u044e\u043a\u043e\u0432\u0441\u043a\u0438"
    ],
    "name:eng_x_preferred":[
        "Kurdyukovskaya"
    ],
    "name:nor_x_preferred":[
        "Kurdjukovskaja"
    ],
    "name:rus_x_preferred":[
        "\u041a\u0443\u0440\u0434\u044e\u043a\u043e\u0432\u0441\u043a\u0430\u044f"
    ],
    "name:und_x_variant":[
        "Kurdjukovskaja",
        "Kurdyukovskaya"
    ],
    "wof:name":"Kurdyukovskaya",
    "wof:placetype":"locality"
},
  "geometry": {"coordinates":[46.45106,43.69266],"type":"Point"}
}