{
  "type": "Feature",
  "properties": {
    "gn:admin1_code":"10.0",
    "gn:asciiname":"Bobrets",
    "gn:country_code":"RU",
    "gn:dem":191,
    "gn:feature_class":"P",
    "gn:feature_code":"PPL",
    "gn:name":"Bobrets",
    "gn:population":0,
    "gn:timezone":"Europe/Moscow",
    "iso:country":"RU",
    "name:rus_x_preferred":[
        "\u0411\u043e\u0431\u0440\u0435\u0446"
    ],
    "name:und_x_variant":[
        "\u0411\u043e\u0431\u0440\u0435\u0446"
    ],
    "wof:name":"Bobrets",
    "wof:placetype":"locality"
},
  "geometry": {"coordinates":[32.96524,53.1534],"type":"Point"}
}