{
  "type": "Feature",
  "properties": {
    "gn:admin1_code":"88.0",
    "gn:asciiname":"Khokhlovo",
    "gn:country_code":"RU",
    "gn:dem":96,
    "gn:feature_class":"P",
    "gn:feature_code":"PPL",
    "gn:name":"Khokhlovo",
    "gn:population":0,
    "gn:timezone":"Europe/Moscow",
    "iso:country":"RU",
    "name:rus_x_preferred":[
        "\u0425\u043e\u0445\u043b\u043e\u0432\u043e"
    ],
    "wof:name":"Khokhlovo",
    "wof:placetype":"locality"
},
  "geometry": {"coordinates":[40.45067,58.01396999999999],"type":"Point"}
}