{
  "type": "Feature",
  "properties": {
    "gn:admin1_code":"60",
    "gn:asciiname":"Novaya Berezovka",
    "gn:country_code":"RU",
    "gn:dem":91,
    "gn:feature_class":"P",
    "gn:feature_code":"PPL",
    "gn:name":"Novaya Ber\u00ebzovka",
    "gn:population":0,
    "gn:timezone":"Europe/Moscow",
    "iso:country":"RU",
    "name:rus_x_preferred":[
        "\u041d\u043e\u0432\u0430\u044f \u0411\u0435\u0440\u0451\u0437\u043e\u0432\u043a\u0430"
    ],
    "name:und_x_variant":[
        "Novaya Ber\u00ebzovka"
    ],
    "wof:name":"Novaya Berezovka",
    "wof:placetype":"locality"
},
  "geometry": {"coordinates":[28.83331,57.02806],"type":"Point"}
}