{
  "type": "Feature",
  "properties": {
    "gn:admin1_code":"54",
    "gn:asciiname":"Il'chebaga",
    "gn:country_code":"RU",
    "gn:dem":57,
    "gn:feature_class":"P",
    "gn:feature_code":"PPL",
    "gn:name":"Il\u2019chebaga",
    "gn:population":0,
    "gn:timezone":"Asia/Omsk",
    "iso:country":"RU",
    "name:eng_x_preferred":[
        "Il'chibaga"
    ],
    "name:nor_x_preferred":[
        "Iltsjebaga"
    ],
    "name:rus_x_preferred":[
        "\u0418\u043b\u044c\u0447\u0435\u0431\u0430\u0433\u0430"
    ],
    "name:und_x_variant":[
        "Il\u2019chibag",
        "Il\u2019chibaga",
        "Il\u2019chebaga"
    ],
    "wof:name":"Il'chebaga",
    "wof:placetype":"locality"
},
  "geometry": {"coordinates":[71.544,57.6165],"type":"Point"}
}