{
  "type": "Feature",
  "properties": {
    "gn:admin1_code":"71",
    "gn:asciiname":"Borovushka",
    "gn:country_code":"RU",
    "gn:dem":98,
    "gn:feature_class":"P",
    "gn:feature_code":"PPL",
    "gn:name":"Borovushka",
    "gn:population":0,
    "gn:timezone":"Asia/Yekaterinburg",
    "iso:country":"RU",
    "name:rus_x_preferred":[
        "\u0411\u043e\u0440\u043e\u0432\u0443\u0448\u043a\u0430"
    ],
    "wof:name":"Borovushka",
    "wof:placetype":"locality"
},
  "geometry": {"coordinates":[63.78505,56.75516999999999],"type":"Point"}
}