{
  "type": "Feature",
  "properties": {
    "gn:admin1_code":"20",
    "gn:asciiname":"Bel'sk",
    "gn:country_code":"RU",
    "gn:dem":430,
    "gn:feature_class":"P",
    "gn:feature_code":"PPL",
    "gn:name":"Bel\u2019sk",
    "gn:population":0,
    "gn:timezone":"Asia/Irkutsk",
    "iso:country":"RU",
    "name:eng_x_preferred":[
        "Bel'sk"
    ],
    "name:nor_x_preferred":[
        "Belsk"
    ],
    "name:rus_x_preferred":[
        "\u0411\u0435\u043b\u044c\u0441\u043a"
    ],
    "name:und_x_variant":[
        "\u0411\u0435\u043b\u044c\u0441\u043a",
        "Bel\u2019sk"
    ],
    "wof:name":"Bel'sk",
    "wof:placetype":"locality"
},
  "geometry": {"coordinates":[103.0795,52.8698],"type":"Point"}
}