{
  "type": "Feature",
  "properties": {
    "gn:admin1_code":"38.0",
    "gn:asciiname":"Mirskoy",
    "gn:country_code":"RU",
    "gn:dem":153,
    "gn:feature_class":"P",
    "gn:feature_code":"PPL",
    "gn:name":"Mirskoy",
    "gn:population":0,
    "gn:timezone":"Europe/Moscow",
    "iso:country":"RU",
    "name:rus_x_preferred":[
        "\u041c\u0438\u0440\u0441\u043a\u043e\u0439"
    ],
    "name:und_x_variant":[
        "\u041c\u0438\u0440\u0441\u043a\u043e\u0439"
    ],
    "wof:name":"Mirskoy",
    "wof:placetype":"locality"
},
  "geometry": {"coordinates":[40.85333,45.15972],"type":"Point"}
}