{
  "type": "Feature",
  "properties": {
    "gn:admin1_code":"56",
    "gn:asciiname":"Zubarevka",
    "gn:country_code":"RU",
    "gn:dem":209,
    "gn:feature_class":"P",
    "gn:feature_code":"PPL",
    "gn:name":"Zubar\u00ebvka",
    "gn:population":0,
    "gn:timezone":"Europe/Moscow",
    "iso:country":"RU",
    "name:rus_x_preferred":[
        "\u0417\u0443\u0431\u0430\u0440\u0451\u0432\u043a\u0430"
    ],
    "name:und_x_variant":[
        "Zubar\u00ebvka",
        "\u0417\u0443\u0431\u0430\u0440\u0451\u0432\u043a\u0430"
    ],
    "wof:name":"Zubarevka",
    "wof:placetype":"locality"
},
  "geometry": {"coordinates":[36.83829,52.21187000000001],"type":"Point"}
}