{
  "type": "Feature",
  "properties": {
    "gn:admin1_code":"61.0",
    "gn:asciiname":"Yelenovka",
    "gn:country_code":"RU",
    "gn:dem":183,
    "gn:feature_class":"P",
    "gn:feature_code":"PPL",
    "gn:name":"Yelenovka",
    "gn:population":0,
    "gn:timezone":"Europe/Moscow",
    "iso:country":"RU",
    "name:aze_x_preferred":[
        "Yelenovka"
    ],
    "wof:name":"Yelenovka",
    "wof:placetype":"locality"
},
  "geometry": {"coordinates":[40.47884000000001,49.0431],"type":"Point"}
}