{
  "type": "Feature",
  "properties": {
    "gn:admin1_code":"69",
    "gn:asciiname":"Barshchevshchina",
    "gn:country_code":"RU",
    "gn:dem":224,
    "gn:feature_class":"P",
    "gn:feature_code":"PPL",
    "gn:name":"Barshchevshchina",
    "gn:population":0,
    "gn:timezone":"Europe/Moscow",
    "iso:country":"RU",
    "name:nor_x_preferred":[
        "Barsjtsjevsjtsjina"
    ],
    "name:rus_x_preferred":[
        "\u0411\u0430\u0440\u0449\u0435\u0432\u0449\u0438\u043d\u0430"
    ],
    "wof:name":"Barshchevshchina",
    "wof:placetype":"locality"
},
  "geometry": {"coordinates":[32.20869,54.69718],"type":"Point"}
}