{
  "type": "Feature",
  "properties": {
    "gn:admin1_code":"4",
    "gn:asciiname":"Chernigovka",
    "gn:cc2":"RU",
    "gn:country_code":"RU",
    "gn:dem":120,
    "gn:feature_class":"P",
    "gn:feature_code":"PPL",
    "gn:name":"Chernigovka",
    "gn:population":0,
    "gn:timezone":"Asia/Barnaul",
    "iso:country":"RU",
    "name:rus_x_preferred":[
        "\u0427\u0435\u0440\u043d\u0438\u0433\u043e\u0432\u043a\u0430"
    ],
    "name:und_x_variant":[
        "Chernigovskiy",
        "Chernigovka",
        "\u0427\u0435\u0440\u043d\u0438\u0433\u043e\u0432\u043a\u0430"
    ],
    "wof:name":"Chernigovka",
    "wof:placetype":"locality"
},
  "geometry": {"coordinates":[80.08333,52.75],"type":"Point"}
}