{
  "type": "Feature",
  "properties": {
    "gn:admin1_code":"84",
    "gn:asciiname":"Nariman",
    "gn:country_code":"RU",
    "gn:dem":81,
    "gn:feature_class":"P",
    "gn:feature_code":"PPL",
    "gn:name":"Nariman",
    "gn:population":0,
    "gn:timezone":"Europe/Volgograd",
    "iso:country":"RU",
    "name:aze_x_preferred":[
        "N\u0259riman"
    ],
    "name:deu_x_preferred":[
        "Nariman"
    ],
    "name:eng_x_preferred":[
        "Nariman"
    ],
    "name:fas_x_preferred":[
        "\u0646\u0631\u06cc\u0645\u0627\u0646"
    ],
    "name:hye_x_preferred":[
        "\u0546\u0561\u0580\u056b\u0574\u0561\u0576"
    ],
    "name:nor_x_preferred":[
        "Nariman"
    ],
    "name:rus_x_preferred":[
        "\u041d\u0430\u0440\u0438\u043c\u0430\u043d"
    ],
    "name:und_x_variant":[
        "Plantator",
        "Nariman"
    ],
    "wof:name":"Nariman",
    "wof:placetype":"locality"
},
  "geometry": {"coordinates":[44.20348,48.47959],"type":"Point"}
}