{
  "type": "Feature",
  "properties": {
    "gn:admin1_code":"28",
    "gn:asciiname":"Mikkilyan",
    "gn:country_code":"RU",
    "gn:dem":199,
    "gn:feature_class":"P",
    "gn:feature_code":"PPL",
    "gn:name":"Mikkilyan",
    "gn:population":0,
    "gn:timezone":"Europe/Moscow",
    "iso:country":"RU",
    "name:fin_x_preferred":[
        "Korkeavaara"
    ],
    "name:rus_x_preferred":[
        "\u041c\u0438\u043a\u043a\u0438\u043b\u044f\u043d"
    ],
    "name:und_x_variant":[
        "\u041c\u0438\u043a\u043a\u0438\u043b\u044f\u043d"
    ],
    "wof:name":"Mikkilyan",
    "wof:placetype":"locality"
},
  "geometry": {"coordinates":[32.23333,62.73333],"type":"Point"}
}