{
  "type": "Feature",
  "properties": {
    "gn:admin1_code":"78",
    "gn:asciiname":"Ryumikha",
    "gn:country_code":"RU",
    "gn:dem":93,
    "gn:feature_class":"P",
    "gn:feature_code":"PPL",
    "gn:name":"Ryumikha",
    "gn:population":0,
    "gn:timezone":"Asia/Yekaterinburg",
    "iso:country":"RU",
    "name:rus_x_preferred":[
        "\u0420\u044e\u043c\u0438\u0445\u0430"
    ],
    "name:und_x_variant":[
        "\u0420\u044e\u043c\u0438\u0445\u0430"
    ],
    "wof:name":"Ryumikha",
    "wof:placetype":"locality"
},
  "geometry": {"coordinates":[70.1751,56.5964],"type":"Point"}
}