{
  "type": "Feature",
  "properties": {
    "gn:admin1_code":"65",
    "gn:asciiname":"Kuybyshevskiy",
    "gn:country_code":"RU",
    "gn:dem":97,
    "gn:feature_class":"P",
    "gn:feature_code":"PPL",
    "gn:name":"Kuybyshevskiy",
    "gn:population":0,
    "gn:timezone":"Europe/Samara",
    "iso:country":"RU",
    "name:eng_x_preferred":[
        "Kuybyshevskiy"
    ],
    "name:nor_x_preferred":[
        "Kujbysjevskij"
    ],
    "name:rus_x_preferred":[
        "\u041a\u0443\u0439\u0431\u044b\u0448\u0435\u0432\u0441\u043a\u0438\u0439"
    ],
    "name:und_x_variant":[
        "Imeni Kuybysheva"
    ],
    "wof:name":"Kuybyshevskiy",
    "wof:placetype":"locality"
},
  "geometry": {"coordinates":[49.6041,52.6483],"type":"Point"}
}