{
  "type": "Feature",
  "properties": {
    "gn:admin1_code":"65",
    "gn:asciiname":"Kuybyshevskiy",
    "gn:country_code":"RU",
    "gn:dem":97,
    "gn:feature_class":"P",
    "gn:feature_code":"PPL",
    "gn:name":"Kuybyshevskiy",
    "gn:population":0,
    "gn:timezone":"Europe/Samara",
    "iso:country":"RU",
    "name:ara_x_preferred":[
        "\u0643\u0648\u064a\u0628\u064a\u0634\u064a\u0641\u0633\u0643\u064a"
    ],
    "name:ben_x_preferred":[
        "\u0995\u09c1\u09df\u09be\u09ac\u09be\u0987\u09b6\u09c7\u09ad\u09b8\u09cd\u0995\u09bf"
    ],
    "name:deu_x_preferred":[
        "Kuybyshevskiy"
    ],
    "name:ell_x_preferred":[
        "\u039a\u03bf\u03c5\u03ca\u03bc\u03c0\u03b9\u03c3\u03ba\u03ad\u03b2\u03c3\u03ba\u03b9\u03b9"
    ],
    "name:eng_x_preferred":[
        "Kuybyshevskiy"
    ],
    "name:fas_x_preferred":[
        "\u06a9\u0648\u06cc\u0628\u06cc\u0634\u0641\u0633\u06a9\u06cc"
    ],
    "name:fra_x_preferred":[
        "Kuybyshev"
    ],
    "name:heb_x_preferred":[
        "\u05e7\u05d5\u05d9\u05d1\u05d9\u05e9\u05d1\u05e1\u05e7\u05d9"
    ],
    "name:hin_x_preferred":[
        "\u0915\u093e\u092f\u092c\u093e\u092f\u0936\u0947\u0935\u0938\u094d\u0915\u0940"
    ],
    "name:hun_x_preferred":[
        "Kuybyshevskiy"
    ],
    "name:ind_x_preferred":[
        "Kuybyshevskiy"
    ],
    "name:ita_x_preferred":[
        "Kuybyshevskiy"
    ],
    "name:jpn_x_preferred":[
        "\u30af\u30a4\u30d3\u30b7\u30a7\u30d6\u30b9\u30ad\u30fc"
    ],
    "name:kor_x_preferred":[
        "\ucfe0\uc774\ube44\uc170\ud504\uc2a4\ud0a4"
    ],
    "name:nor_x_preferred":[
        "Kujbysjevskij"
    ],
    "name:por_x_preferred":[
        "Kuybyshevsky"
    ],
    "name:rus_x_preferred":[
        "\u041a\u0443\u0439\u0431\u044b\u0448\u0435\u0432\u0441\u043a\u0438\u0439"
    ],
    "name:spa_x_preferred":[
        "Kuybyshevskiy"
    ],
    "name:swe_x_preferred":[
        "Kuybyshevskiy"
    ],
    "name:tur_x_preferred":[
        "Kuybyshevskiy"
    ],
    "name:ukr_x_preferred":[
        "\u041a\u0443\u0439\u0431\u0438\u0448\u0435\u0432\u0441\u044c\u043a\u0438\u0439"
    ],
    "name:und_x_variant":[
        "Imeni Kuybysheva"
    ],
    "name:urd_x_preferred":[
        "\u06a9\u0648\u0628\u0627\u0626\u06d2\u0634\u06cc\u0648\u0633\u06a9\u06cc"
    ],
    "name:vie_x_preferred":[
        "Kuybyshevskiy"
    ],
    "name:zho_cn_x_preferred":[
        "\u53e4\u6bd4\u96ea\u592b\u65af\u57fa"
    ],
    "name:zho_tw_x_preferred":[
        "\u53e4\u6bd4\u96ea\u592b\u65af\u57fa"
    ],
    "wof:name":"Kuybyshevskiy",
    "wof:placetype":"locality"
},
  "geometry": {"coordinates":[49.6041,52.6483],"type":"Point"}
}