{
  "type": "Feature",
  "properties": {
    "gn:admin1_code":"33",
    "gn:asciiname":"Dvoryane",
    "gn:country_code":"RU",
    "gn:dem":118,
    "gn:feature_class":"P",
    "gn:feature_code":"PPL",
    "gn:name":"Dvoryane",
    "gn:population":0,
    "gn:timezone":"Europe/Kirov",
    "iso:country":"RU",
    "name:rus_x_preferred":[
        "\u0414\u0432\u043e\u0440\u044f\u043d\u0435"
    ],
    "wof:name":"Dvoryane",
    "wof:placetype":"locality"
},
  "geometry": {"coordinates":[47.9686,57.3496],"type":"Point"}
}