{
  "type": "Feature",
  "properties": {
    "gn:admin1_code":"61",
    "gn:asciiname":"Millerovo",
    "gn:country_code":"RU",
    "gn:dem":121,
    "gn:feature_class":"P",
    "gn:feature_code":"PPL",
    "gn:name":"Millerovo",
    "gn:population":0,
    "gn:timezone":"Europe/Moscow",
    "iso:country":"RU",
    "name:rus_x_preferred":[
        "\u041c\u0438\u043b\u043b\u0435\u0440\u043e\u0432\u043e"
    ],
    "name:und_x_variant":[
        "\u041c\u0438\u043b\u043b\u0435\u0440\u043e\u0432\u043e"
    ],
    "wof:name":"Millerovo",
    "wof:placetype":"locality"
},
  "geometry": {"coordinates":[39.24996,47.82898],"type":"Point"}
}