{
  "type": "Feature",
  "properties": {
    "gn:admin1_code":"25",
    "gn:asciiname":"Mochalki",
    "gn:country_code":"RU",
    "gn:dem":182,
    "gn:feature_class":"P",
    "gn:feature_code":"PPL",
    "gn:name":"Mochalki",
    "gn:population":0,
    "gn:timezone":"Europe/Moscow",
    "iso:country":"RU",
    "name:rus_x_preferred":[
        "\u041c\u043e\u0447\u0430\u043b\u043a\u0438"
    ],
    "name:und_x_variant":[
        "\u041c\u043e\u0447\u0430\u043b\u043a\u0438"
    ],
    "wof:name":"Mochalki",
    "wof:placetype":"locality"
},
  "geometry": {"coordinates":[35.34167,54.85222],"type":"Point"}
}