{
  "type": "Feature",
  "properties": {
    "gn:admin1_code":"33.0",
    "gn:asciiname":"Chudovo",
    "gn:country_code":"RU",
    "gn:dem":168,
    "gn:feature_class":"P",
    "gn:feature_code":"PPL",
    "gn:name":"Chudovo",
    "gn:population":0,
    "gn:timezone":"Europe/Kirov",
    "iso:country":"RU",
    "name:rus_x_preferred":[
        "\u0427\u0443\u0434\u043e\u0432\u043e"
    ],
    "name:und_x_variant":[
        "\u0427\u0443\u0434\u043e\u0432\u043e"
    ],
    "wof:name":"Chudovo",
    "wof:placetype":"locality"
},
  "geometry": {"coordinates":[52.03333,59.45],"type":"Point"}
}