{
  "type": "Feature",
  "properties": {
    "gn:admin1_code":"77",
    "gn:asciiname":"Podsosenka",
    "gn:country_code":"RU",
    "gn:dem":205,
    "gn:feature_class":"P",
    "gn:feature_code":"PPL",
    "gn:name":"Podsosenka",
    "gn:population":0,
    "gn:timezone":"Europe/Moscow",
    "iso:country":"RU",
    "name:rus_x_preferred":[
        "\u041f\u043e\u0434\u0441\u043e\u0441\u0435\u043d\u043a\u0430"
    ],
    "wof:name":"Podsosenka",
    "wof:placetype":"locality"
},
  "geometry": {"coordinates":[32.43173,56.20129],"type":"Point"}
}