{
  "type": "Feature",
  "properties": {
    "gn:admin1_code":"38",
    "gn:asciiname":"Borisovskiy",
    "gn:country_code":"RU",
    "gn:dem":8,
    "gn:feature_class":"P",
    "gn:feature_code":"PPL",
    "gn:name":"Borisovskiy",
    "gn:population":0,
    "gn:timezone":"Europe/Moscow",
    "iso:country":"RU",
    "name:rus_x_preferred":[
        "\u0411\u043e\u0440\u0438\u0441\u043e\u0432\u0441\u043a\u0438\u0439"
    ],
    "wof:name":"Borisovskiy",
    "wof:placetype":"locality"
},
  "geometry": {"coordinates":[37.9225,45.0412],"type":"Point"}
}