{
  "type": "Feature",
  "properties": {
    "gn:admin1_code":"52",
    "gn:asciiname":"Novo-Nikolayevskaya Koloniya",
    "gn:country_code":"RU",
    "gn:dem":26,
    "gn:feature_class":"P",
    "gn:feature_code":"PPL",
    "gn:name":"Novo-Nikolayevskaya Koloniya",
    "gn:population":0,
    "gn:timezone":"Europe/Moscow",
    "iso:country":"RU",
    "name:rus_x_preferred":[
        "\u041d\u043e\u0432\u043e-\u041d\u0438\u043a\u043e\u043b\u0430\u0435\u0432\u0441\u043a\u0430\u044f \u041a\u043e\u043b\u043e\u043d\u0438\u044f"
    ],
    "name:und_x_variant":[
        "\u041d\u043e\u0432\u043e-\u041d\u0438\u043a\u043e\u043b\u0430\u0435\u0432\u0441\u043a\u0430\u044f \u041a\u043e\u043b\u043e\u043d\u0438\u044f"
    ],
    "wof:name":"Novo-Nikolayevskaya Koloniya",
    "wof:placetype":"locality"
},
  "geometry": {"coordinates":[31.42889000000001,58.59656],"type":"Point"}
}