{
  "type": "Feature",
  "properties": {
    "gn:admin1_code":"85",
    "gn:asciiname":"Koporgino",
    "gn:cc2":"RU",
    "gn:country_code":"RU",
    "gn:dem":142,
    "gn:feature_class":"P",
    "gn:feature_code":"PPL",
    "gn:name":"Koporgino",
    "gn:population":0,
    "gn:timezone":"Europe/Moscow",
    "iso:country":"RU",
    "name:und_x_variant":[
        "Koporchino"
    ],
    "wof:name":"Koporgino",
    "wof:placetype":"locality"
},
  "geometry": {"coordinates":[42.86,60.05194],"type":"Point"}
}