{
  "type": "Feature",
  "properties": {
    "gn:admin1_code":"65",
    "gn:asciiname":"Subbotinskiy",
    "gn:country_code":"RU",
    "gn:dem":170,
    "gn:feature_class":"P",
    "gn:feature_code":"PPL",
    "gn:name":"Subbotinskiy",
    "gn:population":0,
    "gn:timezone":"Europe/Samara",
    "iso:country":"RU",
    "name:rus_x_preferred":[
        "\u0421\u0443\u0431\u0431\u043e\u0442\u0438\u043d\u0441\u043a\u0438\u0439"
    ],
    "name:und_x_variant":[
        "\u0421\u0443\u0431\u0431\u043e\u0442\u0438\u043d\u0441\u043a\u0438\u0439"
    ],
    "wof:name":"Subbotinskiy",
    "wof:placetype":"locality"
},
  "geometry": {"coordinates":[51.427,52.6015],"type":"Point"}
}