{
  "type": "Feature",
  "properties": {
    "gn:admin1_code":"20",
    "gn:asciiname":"Inela",
    "gn:country_code":"RU",
    "gn:dem":393,
    "gn:feature_class":"P",
    "gn:feature_code":"PPL",
    "gn:name":"Inela",
    "gn:population":0,
    "gn:timezone":"Asia/Irkutsk",
    "iso:country":"RU",
    "name:rus_x_preferred":[
        "\u0418\u043d\u0435\u043b\u0430"
    ],
    "wof:name":"Inela",
    "wof:placetype":"locality"
},
  "geometry": {"coordinates":[109.33333,59.88333000000001],"type":"Point"}
}