{
  "type": "Feature",
  "properties": {
    "gn:admin1_code":"12",
    "gn:asciiname":"Alkhan-Churtskiy",
    "gn:country_code":"RU",
    "gn:dem":127,
    "gn:feature_class":"P",
    "gn:feature_code":"PPL",
    "gn:name":"Alkhan-Churtskiy",
    "gn:population":0,
    "gn:timezone":"Europe/Moscow",
    "iso:country":"RU",
    "name:nor_x_preferred":[
        "Alkhaj-Tsjurtskij"
    ],
    "name:rus_x_preferred":[
        "\u0410\u043b\u0445\u0430\u043d-\u0427\u0443\u0440\u0442\u0441\u043a\u0438\u0439"
    ],
    "name:und_x_variant":[
        "Alkhay-Churtskiy",
        "Alkhan-Churt"
    ],
    "wof:name":"Alkhan-Churtskiy",
    "wof:placetype":"locality"
},
  "geometry": {"coordinates":[45.72021,43.36889],"type":"Point"}
}