{
  "type": "Feature",
  "properties": {
    "gn:admin1_code":"85.0",
    "gn:asciiname":"Akin'khovskaya",
    "gn:country_code":"RU",
    "gn:dem":164,
    "gn:feature_class":"P",
    "gn:feature_code":"PPL",
    "gn:name":"Akin\u2019khovskaya",
    "gn:population":0,
    "gn:timezone":"Europe/Moscow",
    "iso:country":"RU",
    "name:nor_x_preferred":[
        "Akinkhovskaja"
    ],
    "name:rus_x_preferred":[
        "\u0410\u043a\u0438\u043d\u044c\u0445\u043e\u0432\u0441\u043a\u0430\u044f"
    ],
    "name:und_x_variant":[
        "Akin\u2019khovskaya"
    ],
    "wof:name":"Akin'khovskaya",
    "wof:placetype":"locality"
},
  "geometry": {"coordinates":[41.85274,60.3624],"type":"Point"}
}