{
  "type": "Feature",
  "properties": {
    "gn:admin1_code":"60.0",
    "gn:asciiname":"Alol'",
    "gn:country_code":"RU",
    "gn:dem":208,
    "gn:feature_class":"P",
    "gn:feature_code":"PPL",
    "gn:name":"Alol\u2019",
    "gn:population":0,
    "gn:timezone":"Europe/Moscow",
    "iso:country":"RU",
    "name:nor_x_preferred":[
        "Alol"
    ],
    "name:rus_x_preferred":[
        "\u0410\u043b\u043e\u043b\u044c"
    ],
    "name:und_x_variant":[
        "Alol\u2019"
    ],
    "wof:name":"Alol'",
    "wof:placetype":"locality"
},
  "geometry": {"coordinates":[29.34589,56.75242],"type":"Point"}
}