{
  "type": "Feature",
  "properties": {
    "gn:admin1_code":"24",
    "gn:asciiname":"Mayskiy",
    "gn:country_code":"RU",
    "gn:dem":28,
    "gn:feature_class":"P",
    "gn:feature_code":"PPL",
    "gn:name":"Mayskiy",
    "gn:population":0,
    "gn:timezone":"Europe/Moscow",
    "iso:country":"RU",
    "name:eng_x_preferred":[
        "Mayskiy"
    ],
    "name:nor_x_preferred":[
        "Majskij"
    ],
    "name:rus_x_preferred":[
        "\u041c\u0430\u0439\u0441\u043a\u0438\u0439"
    ],
    "name:und_x_variant":[
        "\u041c\u0430\u0439\u0441\u043a\u0438\u0439",
        "Mayskiy"
    ],
    "wof:name":"Mayskiy",
    "wof:placetype":"locality"
},
  "geometry": {"coordinates":[44.7748,46.5835],"type":"Point"}
}