{
  "type": "Feature",
  "properties": {
    "gn:admin1_code":"10.0",
    "gn:asciiname":"Baklan'",
    "gn:country_code":"RU",
    "gn:dem":172,
    "gn:feature_class":"P",
    "gn:feature_code":"PPL",
    "gn:name":"Baklan\u2019",
    "gn:population":0,
    "gn:timezone":"Europe/Moscow",
    "iso:country":"RU",
    "name:eng_x_preferred":[
        "Baklan'"
    ],
    "name:nor_x_preferred":[
        "Baklan"
    ],
    "name:rus_x_preferred":[
        "\u0411\u0430\u043a\u043b\u0430\u043d\u044c"
    ],
    "name:und_x_variant":[
        "\u0411\u0430\u043a\u043b\u0430\u043d\u044c",
        "Baklan\u2019"
    ],
    "wof:name":"Baklan'",
    "wof:placetype":"locality"
},
  "geometry": {"coordinates":[33.25041,52.73792],"type":"Point"}
}