{
  "type": "Feature",
  "properties": {
    "gn:admin1_code":"23",
    "gn:asciiname":"Sal'skoye",
    "gn:country_code":"RU",
    "gn:dem":53,
    "gn:feature_class":"P",
    "gn:feature_code":"PPL",
    "gn:name":"Sal\u2019skoye",
    "gn:population":0,
    "gn:timezone":"Europe/Kaliningrad",
    "iso:country":"RU",
    "name:rus_x_preferred":[
        "\u0421\u0430\u043b\u044c\u0441\u043a\u043e\u0435"
    ],
    "name:und_x_variant":[
        "Sal\u2019skoye",
        "\u0421\u0430\u043b\u044c\u0441\u043a\u043e\u0435"
    ],
    "wof:name":"Sal'skoye",
    "wof:placetype":"locality"
},
  "geometry": {"coordinates":[20.16425,54.91318],"type":"Point"}
}