{
  "type": "Feature",
  "properties": {
    "gn:admin1_code":"33.0",
    "gn:asciiname":"Ognenki",
    "gn:country_code":"RU",
    "gn:dem":170,
    "gn:feature_class":"P",
    "gn:feature_code":"PPL",
    "gn:name":"Ognenki",
    "gn:population":0,
    "gn:timezone":"Europe/Kirov",
    "iso:country":"RU",
    "name:rus_x_preferred":[
        "\u041e\u0433\u043d\u0435\u043d\u043a\u0438"
    ],
    "name:und_x_variant":[
        "\u041e\u0433\u043d\u0435\u043d\u043a\u0438"
    ],
    "wof:name":"Ognenki",
    "wof:placetype":"locality"
},
  "geometry": {"coordinates":[50.96444,59.32278],"type":"Point"}
}