{
  "type": "Feature",
  "properties": {
    "gn:admin1_code":"41",
    "gn:asciiname":"Bochanka",
    "gn:country_code":"RU",
    "gn:dem":177,
    "gn:feature_class":"P",
    "gn:feature_code":"PPL",
    "gn:name":"Bochanka",
    "gn:population":0,
    "gn:timezone":"Europe/Moscow",
    "iso:country":"RU",
    "name:rus_x_preferred":[
        "\u0411\u043e\u0447\u0430\u043d\u043a\u0430"
    ],
    "wof:name":"Bochanka",
    "wof:placetype":"locality"
},
  "geometry": {"coordinates":[35.4423,51.37300000000001],"type":"Point"}
}