{
  "type": "Feature",
  "properties": {
    "gn:admin1_code":"62.0",
    "gn:asciiname":"Chernavskiye Vyselki",
    "gn:country_code":"RU",
    "gn:dem":201,
    "gn:feature_class":"P",
    "gn:feature_code":"PPL",
    "gn:name":"Chernavskiye Vyselki",
    "gn:population":0,
    "gn:timezone":"Europe/Moscow",
    "iso:country":"RU",
    "name:rus_x_preferred":[
        "\u0427\u0435\u0440\u043d\u0430\u0432\u0441\u043a\u0438\u0435 \u0412\u044b\u0441\u0435\u043b\u043a\u0438"
    ],
    "name:und_x_variant":[
        "Chernavo-Vyselki",
        "Chernavskiye Vyselki",
        "\u0427\u0435\u0440\u043d\u0430\u0432\u0441\u043a\u0438\u0435 \u0412\u044b\u0441\u0435\u043b\u043a\u0438"
    ],
    "wof:name":"Chernavskiye Vyselki",
    "wof:placetype":"locality"
},
  "geometry": {"coordinates":[39.10533,53.62809],"type":"Point"}
}