{
  "type": "Feature",
  "properties": {
    "gn:admin1_code":"25",
    "gn:asciiname":"Ivashkovichi",
    "gn:country_code":"RU",
    "gn:dem":142,
    "gn:feature_class":"P",
    "gn:feature_code":"PPL",
    "gn:name":"Ivashkovichi",
    "gn:population":0,
    "gn:timezone":"Europe/Moscow",
    "iso:country":"RU",
    "name:nor_x_preferred":[
        "Ivasjkovitsji"
    ],
    "name:rus_x_preferred":[
        "\u0418\u0432\u0430\u0448\u043a\u043e\u0432\u0438\u0447\u0438"
    ],
    "wof:name":"Ivashkovichi",
    "wof:placetype":"locality"
},
  "geometry": {"coordinates":[36.69788,54.98505],"type":"Point"}
}