{
  "type": "Feature",
  "properties": {
    "gn:admin1_code":"60",
    "gn:asciiname":"Sitki",
    "gn:country_code":"RU",
    "gn:dem":55,
    "gn:feature_class":"P",
    "gn:feature_code":"PPL",
    "gn:name":"Sitki",
    "gn:population":0,
    "gn:timezone":"Europe/Moscow",
    "iso:country":"RU",
    "name:rus_x_preferred":[
        "\u0421\u0438\u0442\u043a\u0438"
    ],
    "name:und_x_variant":[
        "Silki",
        "Sitki"
    ],
    "wof:name":"Sitki",
    "wof:placetype":"locality"
},
  "geometry": {"coordinates":[28.04662,57.32475],"type":"Point"}
}