{
  "type": "Feature",
  "properties": {
    "gn:admin1_code":"77.0",
    "gn:asciiname":"Detkovo",
    "gn:country_code":"RU",
    "gn:dem":184,
    "gn:feature_class":"P",
    "gn:feature_code":"PPL",
    "gn:name":"Detkovo",
    "gn:population":0,
    "gn:timezone":"Europe/Moscow",
    "iso:country":"RU",
    "name:rus_x_preferred":[
        "\u0414\u0435\u0442\u043a\u043e\u0432\u043e"
    ],
    "name:und_x_variant":[
        "\u0414\u0435\u0442\u043a\u043e\u0432\u043e"
    ],
    "wof:name":"Detkovo",
    "wof:placetype":"locality"
},
  "geometry": {"coordinates":[34.69549,57.09533],"type":"Point"}
}