{
  "type": "Feature",
  "properties": {
    "gn:admin1_code":"64",
    "gn:asciiname":"Kambuzev",
    "gn:cc2":"RU",
    "gn:country_code":"RU",
    "gn:dem":-9999,
    "gn:feature_class":"P",
    "gn:feature_code":"PPL",
    "gn:name":"Kambuzev",
    "gn:population":0,
    "gn:timezone":"Asia/Sakhalin",
    "iso:country":"RU",
    "name:rus_x_preferred":[
        "\u041a\u0430\u043c\u0431\u0443\u0437\u0435\u0432"
    ],
    "name:und_x_variant":[
        "Kanbuzev",
        "Kambuzev"
    ],
    "wof:name":"Kambuzev",
    "wof:placetype":"locality"
},
  "geometry": {"coordinates":[141.88333,52.98333],"type":"Point"}
}