{
  "type": "Feature",
  "properties": {
    "gn:admin1_code":"10",
    "gn:asciiname":"Zhensk",
    "gn:country_code":"RU",
    "gn:dem":164,
    "gn:feature_class":"P",
    "gn:feature_code":"PPL",
    "gn:name":"Zhensk",
    "gn:population":0,
    "gn:timezone":"Europe/Moscow",
    "iso:country":"RU",
    "name:rus_x_preferred":[
        "\u0416\u0435\u043d\u0441\u043a"
    ],
    "wof:name":"Zhensk",
    "wof:placetype":"locality"
},
  "geometry": {"coordinates":[33.61195,53.23446],"type":"Point"}
}