{
  "type": "Feature",
  "properties": {
    "gn:admin1_code":"60.0",
    "gn:asciiname":"Chervishchi",
    "gn:country_code":"RU",
    "gn:dem":72,
    "gn:feature_class":"P",
    "gn:feature_code":"PPL",
    "gn:name":"Chervishchi",
    "gn:population":0,
    "gn:timezone":"Europe/Moscow",
    "iso:country":"RU",
    "name:rus_x_preferred":[
        "\u0427\u0435\u0440\u0432\u0438\u0449\u0438"
    ],
    "name:und_x_variant":[
        "Cherevishchi",
        "Chervishchi"
    ],
    "wof:name":"Chervishchi",
    "wof:placetype":"locality"
},
  "geometry": {"coordinates":[29.53512000000001,58.0301],"type":"Point"}
}