{
  "type": "Feature",
  "properties": {
    "gn:admin1_code":"60",
    "gn:asciiname":"Karzuli",
    "gn:country_code":"RU",
    "gn:dem":49,
    "gn:feature_class":"P",
    "gn:feature_code":"PPL",
    "gn:name":"Karzuli",
    "gn:population":0,
    "gn:timezone":"Europe/Moscow",
    "iso:country":"RU",
    "name:rus_x_preferred":[
        "\u041a\u0430\u0440\u0437\u0443\u043b\u0438"
    ],
    "wof:name":"Karzuli",
    "wof:placetype":"locality"
},
  "geometry": {"coordinates":[28.55148,57.64991],"type":"Point"}
}