{
  "type": "Feature",
  "properties": {
    "gn:admin1_code":"6.0",
    "gn:asciiname":"Il'inskiy Ostrov",
    "gn:country_code":"RU",
    "gn:dem":80,
    "gn:feature_class":"P",
    "gn:feature_code":"PPL",
    "gn:name":"Il\u2019inskiy Ostrov",
    "gn:population":0,
    "gn:timezone":"Europe/Moscow",
    "iso:country":"RU",
    "name:rus_x_preferred":[
        "\u0418\u043b\u044c\u0438\u043d\u0441\u043a\u0438\u0439 \u041e\u0441\u0442\u0440\u043e\u0432"
    ],
    "name:und_x_variant":[
        "Il\u2019inskiy Ostrov"
    ],
    "wof:name":"Il'inskiy Ostrov",
    "wof:placetype":"locality"
},
  "geometry": {"coordinates":[40.9274,61.7404],"type":"Point"}
}