{
  "type": "Feature",
  "properties": {
    "gn:admin1_code":"85",
    "gn:asciiname":"Prisukhonskaya",
    "gn:country_code":"RU",
    "gn:dem":109,
    "gn:feature_class":"P",
    "gn:feature_code":"PPL",
    "gn:name":"Prisukhonskaya",
    "gn:population":0,
    "gn:timezone":"Europe/Moscow",
    "iso:country":"RU",
    "name:rus_x_preferred":[
        "\u041f\u0440\u0438\u0441\u0443\u0445\u043e\u043d\u0441\u043a\u0430\u044f"
    ],
    "name:und_x_variant":[
        "Bol\u2019she-Glukhaya",
        "Glukhaya",
        "Prisukhonskaya"
    ],
    "wof:name":"Prisukhonskaya",
    "wof:placetype":"locality"
},
  "geometry": {"coordinates":[41.62014,59.43062],"type":"Point"}
}