{
  "type": "Feature",
  "properties": {
    "gn:country":"RU",
    "gn:fcode":"PPL",
    "gn:pop":0,
    "iso:country":"RU",
    "name:rus_x_preferred":[
        "\u041b\u0435\u0432\u043e\u0448\u0435\u0432\u043e"
    ],
    "name:unk_x_variant":[
        "Levoshevo"
    ],
    "qs:name":"Vorshevo",
    "qs:name_adm0":"Russia",
    "qs:name_adm1":"Ryazan Oblast",
    "qs:photos_9r":0,
    "qs:photos_sr":0,
    "qs:placetype":"Town",
    "qs:pop_sr":"0",
    "wof:name":"Vorshevo",
    "wof:placetype":"locality",
    "wof:population":0
},
  "geometry": {"coordinates":[39.49252,55.58044],"type":"Point"}
}