{
  "type": "Feature",
  "properties": {
    "gn:admin1_code":"55.0",
    "gn:asciiname":"Aul Nomer Vtoroy",
    "gn:country_code":"RU",
    "gn:dem":98,
    "gn:feature_class":"P",
    "gn:feature_code":"PPL",
    "gn:name":"Aul Nomer Vtoroy",
    "gn:population":0,
    "gn:timezone":"Asia/Yekaterinburg",
    "iso:country":"RU",
    "name:nor_x_preferred":[
        "Aul Nomer Vtoroj"
    ],
    "name:rus_x_preferred":[
        "\u0410\u0443\u043b \u041d\u043e\u043c\u0435\u0440 \u0412\u0442\u043e\u0440\u043e\u0439"
    ],
    "name:und_x_variant":[
        "Aul Vtoroy",
        "Aul Nomer Vtoroy"
    ],
    "wof:name":"Aul Nomer Vtoroy",
    "wof:placetype":"locality"
},
  "geometry": {"coordinates":[55.48333,51.71667],"type":"Point"}
}