{
  "type": "Feature",
  "properties": {
    "gn:admin1_code":"60",
    "gn:asciiname":"Rykshino",
    "gn:country_code":"RU",
    "gn:dem":224,
    "gn:feature_class":"P",
    "gn:feature_code":"PPL",
    "gn:name":"Rykshino",
    "gn:population":0,
    "gn:timezone":"Europe/Moscow",
    "iso:country":"RU",
    "name:eng_x_preferred":[
        "Rykshchino"
    ],
    "name:nor_x_preferred":[
        "Ryksjino"
    ],
    "name:rus_x_preferred":[
        "\u0420\u044b\u043a\u0448\u0438\u043d\u043e"
    ],
    "wof:name":"Rykshino",
    "wof:placetype":"locality"
},
  "geometry": {"coordinates":[29.92859,56.4494],"type":"Point"}
}