{
  "type": "Feature",
  "properties": {
    "gn:admin1_code":"69.0",
    "gn:asciiname":"Buda",
    "gn:cc2":"RU",
    "gn:country_code":"RU",
    "gn:dem":221,
    "gn:feature_class":"P",
    "gn:feature_code":"PPL",
    "gn:name":"Buda",
    "gn:population":0,
    "gn:timezone":"Europe/Moscow",
    "iso:country":"RU",
    "name:rus_x_preferred":[
        "\u0411\u0443\u0434\u0430"
    ],
    "name:und_x_variant":[
        "Pil\u2019n",
        "Buda",
        "\u0411\u0443\u0434\u0430"
    ],
    "wof:name":"Buda",
    "wof:placetype":"locality"
},
  "geometry": {"coordinates":[34.37528,54.54833000000001],"type":"Point"}
}