{
  "type": "Feature",
  "properties": {
    "gn:admin1_code":"25",
    "gn:asciiname":"Kornevo",
    "gn:cc2":"RU",
    "gn:country_code":"RU",
    "gn:dem":155,
    "gn:feature_class":"P",
    "gn:feature_code":"PPL",
    "gn:name":"Korn\u00ebvo",
    "gn:population":0,
    "gn:timezone":"Europe/Moscow",
    "iso:country":"RU",
    "name:rus_x_preferred":[
        "\u041a\u043e\u0440\u043d\u0451\u0432\u043e"
    ],
    "name:und_x_variant":[
        "Protychino",
        "Pritycheno",
        "Korn\u00ebvo",
        "\u041a\u043e\u0440\u043d\u0451\u0432\u043e"
    ],
    "wof:name":"Kornevo",
    "wof:placetype":"locality"
},
  "geometry": {"coordinates":[35.34028,53.89083],"type":"Point"}
}