{
  "type": "Feature",
  "properties": {
    "gn:admin1_code":"29",
    "gn:asciiname":"Sredniy Yedinis",
    "gn:country_code":"RU",
    "gn:dem":271,
    "gn:feature_class":"P",
    "gn:feature_code":"PPL",
    "gn:name":"Sredniy Yedinis",
    "gn:population":0,
    "gn:timezone":"Asia/Novokuznetsk",
    "iso:country":"RU",
    "name:rus_x_preferred":[
        "\u0421\u0440\u0435\u0434\u043d\u0438\u0439 \u0415\u0434\u0438\u043d\u0438\u0441"
    ],
    "wof:name":"Sredniy Yedinis",
    "wof:placetype":"locality"
},
  "geometry": {"coordinates":[86.81667,55.66667],"type":"Point"}
}