{
  "type": "Feature",
  "properties": {
    "gn:admin1_code":"33",
    "gn:asciiname":"Nizhniy Puziner'",
    "gn:country_code":"RU",
    "gn:dem":127,
    "gn:feature_class":"P",
    "gn:feature_code":"PPL",
    "gn:name":"Nizhniy Puziner\u2019",
    "gn:population":0,
    "gn:timezone":"Europe/Kirov",
    "iso:country":"RU",
    "name:rus_x_preferred":[
        "\u041d\u0438\u0436\u043d\u0438\u0439 \u041f\u0443\u0437\u0438\u043d\u0435\u0440\u044c"
    ],
    "name:und_x_variant":[
        "Puziner\u2019",
        "Nizhniy Puziner\u2019"
    ],
    "wof:name":"Nizhniy Puziner'",
    "wof:placetype":"locality"
},
  "geometry": {"coordinates":[49.2645,57.0839],"type":"Point"}
}