{
  "type": "Feature",
  "properties": {
    "gn:admin1_code":"60",
    "gn:asciiname":"Strady",
    "gn:country_code":"RU",
    "gn:dem":76,
    "gn:feature_class":"P",
    "gn:feature_code":"PPL",
    "gn:name":"Strady",
    "gn:population":0,
    "gn:timezone":"Europe/Moscow",
    "iso:country":"RU",
    "name:rus_x_preferred":[
        "\u0421\u0442\u0440\u0430\u0434\u044b"
    ],
    "wof:name":"Strady",
    "wof:placetype":"locality"
},
  "geometry": {"coordinates":[28.11364,57.01368000000001],"type":"Point"}
}