{
  "type": "Feature",
  "properties": {
    "gn:admin1_code":"34",
    "gn:asciiname":"Kyltovo",
    "gn:country_code":"RU",
    "gn:dem":113,
    "gn:feature_class":"P",
    "gn:feature_code":"PPL",
    "gn:name":"Kyltovo",
    "gn:population":42,
    "gn:timezone":"Europe/Moscow",
    "iso:country":"RU",
    "name:eng_x_preferred":[
        "Kyltovo"
    ],
    "name:nor_x_preferred":[
        "Kyltovo"
    ],
    "name:rus_x_preferred":[
        "\u041a\u044b\u043b\u0442\u043e\u0432\u043e"
    ],
    "wof:name":"Kyltovo",
    "wof:placetype":"locality",
    "wof:population":42
},
  "geometry": {"coordinates":[50.98281,62.33316],"type":"Point"}
}