{
  "type": "Feature",
  "properties": {
    "gn:admin1_code":"88",
    "gn:asciiname":"Pirogovo",
    "gn:country_code":"RU",
    "gn:dem":122,
    "gn:feature_class":"P",
    "gn:feature_code":"PPL",
    "gn:name":"Pirogovo",
    "gn:population":0,
    "gn:timezone":"Europe/Moscow",
    "iso:country":"RU",
    "name:eng_x_preferred":[
        "Pirogovo"
    ],
    "name:nor_x_preferred":[
        "Pirogovo"
    ],
    "name:rus_x_preferred":[
        "\u041f\u0438\u0440\u043e\u0433\u043e\u0432\u043e"
    ],
    "name:und_x_variant":[
        "Pirogova"
    ],
    "wof:name":"Pirogovo",
    "wof:placetype":"locality"
},
  "geometry": {"coordinates":[40.8257,58.43501],"type":"Point"}
}