{
  "type": "Feature",
  "properties": {
    "gn:admin1_code":"28",
    "gn:asciiname":"Polya",
    "gn:country_code":"RU",
    "gn:dem":43,
    "gn:feature_class":"P",
    "gn:feature_code":"PPL",
    "gn:name":"Polya",
    "gn:population":0,
    "gn:timezone":"Europe/Moscow",
    "iso:country":"RU",
    "name:eng_x_preferred":[
        "Polya"
    ],
    "name:fin_x_preferred":[
        "Pola"
    ],
    "name:nor_x_preferred":[
        "Polja"
    ],
    "name:rus_x_preferred":[
        "\u041f\u043e\u043b\u044f"
    ],
    "name:und_x_variant":[
        "\u041f\u043e\u043b\u044f",
        "Polya"
    ],
    "wof:name":"Polya",
    "wof:placetype":"locality"
},
  "geometry": {"coordinates":[35.29702,62.30864],"type":"Point"}
}