{
  "type": "Feature",
  "properties": {
    "gn:admin1_code":"05",
    "gn:asciiname":"Irmakit",
    "gn:cc2":"RU",
    "gn:country_code":"RU",
    "gn:dem":346,
    "gn:feature_class":"P",
    "gn:feature_code":"PPL",
    "gn:name":"Irmakit",
    "gn:population":0,
    "gn:timezone":"Asia/Yakutsk",
    "iso:country":"RU",
    "name:rus_x_preferred":[
        "\u0418\u0440\u043c\u0430\u043a\u0438\u0442"
    ],
    "name:und_x_variant":[
        "Priisk Chitova",
        "Irmakit Camp",
        "Irmakit",
        "\u0418\u0440\u043c\u0430\u043a\u0438\u0442"
    ],
    "wof:name":"Irmakit",
    "wof:placetype":"locality"
},
  "geometry": {"coordinates":[125.21666999999999,53.93333000000001],"type":"Point"}
}