{
  "type": "Feature",
  "properties": {
    "gn:admin1_code":"56",
    "gn:asciiname":"Komari",
    "gn:country_code":"RU",
    "gn:dem":238,
    "gn:feature_class":"P",
    "gn:feature_code":"PPL",
    "gn:name":"Komari",
    "gn:population":0,
    "gn:timezone":"Europe/Moscow",
    "iso:country":"RU",
    "name:rus_x_preferred":[
        "\u041a\u043e\u043c\u0430\u0440\u0438"
    ],
    "wof:name":"Komari",
    "wof:placetype":"locality"
},
  "geometry": {"coordinates":[36.11667,53.28333000000001],"type":"Point"}
}