{
  "type": "Feature",
  "properties": {
    "gn:admin1_code":"88",
    "gn:asciiname":"Oshcherikha",
    "gn:country_code":"RU",
    "gn:dem":149,
    "gn:feature_class":"P",
    "gn:feature_code":"PPL",
    "gn:name":"Oshcherikha",
    "gn:population":0,
    "gn:timezone":"Europe/Moscow",
    "iso:country":"RU",
    "name:rus_x_preferred":[
        "\u041e\u0449\u0435\u0440\u0438\u0445\u0430"
    ],
    "wof:name":"Oshcherikha",
    "wof:placetype":"locality"
},
  "geometry": {"coordinates":[40.15,57.28333000000001],"type":"Point"}
}