{
  "type": "Feature",
  "properties": {
    "gn:admin1_code":"75",
    "gn:asciiname":"Krasnoyarskiy Reid",
    "gn:country_code":"RU",
    "gn:dem":101,
    "gn:feature_class":"P",
    "gn:feature_code":"PPL",
    "gn:name":"Krasnoyarskiy Reid",
    "gn:population":0,
    "gn:timezone":"Asia/Tomsk",
    "iso:country":"RU",
    "name:eng_x_preferred":[
        "Krasnoyarskiy Reid"
    ],
    "name:nor_x_preferred":[
        "Krasnojarskij Rejd"
    ],
    "name:rus_x_preferred":[
        "\u041a\u0440\u0430\u0441\u043d\u043e\u044f\u0440\u0441\u043a\u0438\u0439 \u0420\u0435\u0439\u0434"
    ],
    "name:rus_x_variant":[
        "\u041a\u0440\u0430\u0441\u043d\u043e\u044f\u0440\u0441\u043a\u0438\u0439 \u0420\u0435\u0438\u0434"
    ],
    "name:und_x_variant":[
        "\u041a\u0440\u0430\u0441\u043d\u043e\u044f\u0440\u0441\u043a\u0438\u0439 \u0420\u0435\u0438\u0434"
    ],
    "wof:name":"Krasnoyarskiy Reid",
    "wof:placetype":"locality"
},
  "geometry": {"coordinates":[86.79693,56.85124],"type":"Point"}
}