{
  "type": "Feature",
  "properties": {
    "gn:admin1_code":"55",
    "gn:asciiname":"Novyy",
    "gn:country_code":"RU",
    "gn:dem":191,
    "gn:feature_class":"P",
    "gn:feature_code":"PPL",
    "gn:name":"Novyy",
    "gn:population":0,
    "gn:timezone":"Asia/Yekaterinburg",
    "iso:country":"RU",
    "name:eng_x_preferred":[
        "Novyy"
    ],
    "name:nor_x_preferred":[
        "Novyj"
    ],
    "name:rus_x_preferred":[
        "\u041d\u043e\u0432\u044b\u0439"
    ],
    "wof:name":"Novyy",
    "wof:placetype":"locality"
},
  "geometry": {"coordinates":[57.2933,51.0372],"type":"Point"}
}