{
  "type": "Feature",
  "properties": {
    "gn:admin1_code":"10.0",
    "gn:asciiname":"Bol'shoy Krupets",
    "gn:country_code":"RU",
    "gn:dem":167,
    "gn:feature_class":"P",
    "gn:feature_code":"PPL",
    "gn:name":"Bol\u2019shoy Krupets",
    "gn:population":0,
    "gn:timezone":"Europe/Moscow",
    "iso:country":"RU",
    "name:rus_x_preferred":[
        "\u0411\u043e\u043b\u044c\u0448\u043e\u0439 \u041a\u0440\u0443\u043f\u0435\u0446"
    ],
    "name:und_x_variant":[
        "Bol\u2019shoy Krupets"
    ],
    "wof:name":"Bol'shoy Krupets",
    "wof:placetype":"locality"
},
  "geometry": {"coordinates":[33.7641,53.1276],"type":"Point"}
}