{
  "type": "Feature",
  "properties": {
    "gn:admin1_code":"61.0",
    "gn:asciiname":"Berkuta",
    "gn:country_code":"RU",
    "gn:dem":-1,
    "gn:feature_class":"P",
    "gn:feature_code":"PPL",
    "gn:name":"Berkuta",
    "gn:population":0,
    "gn:timezone":"Europe/Moscow",
    "iso:country":"RU",
    "name:nor_x_preferred":[
        "Berkuta"
    ],
    "name:rus_x_preferred":[
        "\u0411\u0435\u0440\u043a\u0443\u0442\u0430"
    ],
    "wof:name":"Berkuta",
    "wof:placetype":"locality"
},
  "geometry": {"coordinates":[39.25,47.16667],"type":"Point"}
}