{
  "type": "Feature",
  "properties": {
    "gn:admin1_code":"52.0",
    "gn:asciiname":"Chuprovo",
    "gn:country_code":"RU",
    "gn:dem":152,
    "gn:feature_class":"P",
    "gn:feature_code":"PPL",
    "gn:name":"Chuprovo",
    "gn:population":0,
    "gn:timezone":"Europe/Moscow",
    "iso:country":"RU",
    "name:nor_x_preferred":[
        "Tsjuprovo"
    ],
    "name:rus_x_preferred":[
        "\u0427\u0443\u043f\u0440\u043e\u0432\u043e"
    ],
    "wof:name":"Chuprovo",
    "wof:placetype":"locality"
},
  "geometry": {"coordinates":[33.6854,58.36564],"type":"Point"}
}