{
  "type": "Feature",
  "properties": {
    "gn:admin1_code":"19",
    "gn:asciiname":"Sovetskiy",
    "gn:country_code":"RU",
    "gn:dem":490,
    "gn:feature_class":"P",
    "gn:feature_code":"PPL",
    "gn:name":"Sovetskiy",
    "gn:population":0,
    "gn:timezone":"Europe/Moscow",
    "iso:country":"RU",
    "name:rus_x_preferred":[
        "\u0421\u043e\u0432\u0435\u0442\u0441\u043a\u0438\u0439"
    ],
    "wof:name":"Sovetskiy",
    "wof:placetype":"locality"
},
  "geometry": {"coordinates":[44.61667,43.55],"type":"Point"}
}