{
  "type": "Feature",
  "properties": {
    "gn:admin1_code":"90.0",
    "gn:asciiname":"Tupitca",
    "gn:country_code":"RU",
    "gn:dem":119,
    "gn:feature_class":"P",
    "gn:feature_code":"PPL",
    "gn:name":"Tupitca",
    "gn:population":0,
    "gn:timezone":"Asia/Yekaterinburg",
    "iso:country":"RU",
    "name:rus_x_preferred":[
        "\u0422\u0443\u043f\u0438\u0446\u0430"
    ],
    "wof:name":"Tupitca",
    "wof:placetype":"locality"
},
  "geometry": {"coordinates":[56.32605,58.18672],"type":"Point"}
}