{
  "type": "Feature",
  "properties": {
    "gn:admin1_code":"80",
    "gn:asciiname":"Selyanur",
    "gn:country_code":"RU",
    "gn:dem":90,
    "gn:feature_class":"P",
    "gn:feature_code":"PPL",
    "gn:name":"Selyanur",
    "gn:population":0,
    "gn:timezone":"Europe/Samara",
    "iso:country":"RU",
    "name:rus_x_preferred":[
        "\u0421\u0435\u043b\u044f\u043d\u0443\u0440"
    ],
    "name:und_x_variant":[
        "Solyanur",
        "Selyanur",
        "\u0421\u0435\u043b\u044f\u043d\u0443\u0440"
    ],
    "wof:name":"Selyanur",
    "wof:placetype":"locality"
},
  "geometry": {"coordinates":[51.72639,56.05147],"type":"Point"}
}