{
  "type": "Feature",
  "properties": {
    "gn:admin1_code":"69.0",
    "gn:asciiname":"Chachina",
    "gn:country_code":"RU",
    "gn:dem":185,
    "gn:feature_class":"P",
    "gn:feature_code":"PPL",
    "gn:name":"Chachina",
    "gn:population":0,
    "gn:timezone":"Europe/Moscow",
    "iso:country":"RU",
    "name:rus_x_preferred":[
        "\u0427\u0430\u0447\u0438\u043d\u0430"
    ],
    "name:und_x_variant":[
        "\u0427\u0430\u0447\u0438\u043d\u0430"
    ],
    "wof:name":"Chachina",
    "wof:placetype":"locality"
},
  "geometry": {"coordinates":[31.79871,55.08527],"type":"Point"}
}