{
  "type": "Feature",
  "properties": {
    "gn:admin1_code":"90.0",
    "gn:asciiname":"Kharenki",
    "gn:country_code":"RU",
    "gn:dem":126,
    "gn:feature_class":"P",
    "gn:feature_code":"PPL",
    "gn:name":"Kharenki",
    "gn:population":0,
    "gn:timezone":"Asia/Yekaterinburg",
    "iso:country":"RU",
    "name:rus_x_preferred":[
        "\u0425\u0430\u0440\u0435\u043d\u043a\u0438"
    ],
    "wof:name":"Kharenki",
    "wof:placetype":"locality"
},
  "geometry": {"coordinates":[56.4862,59.6359],"type":"Point"}
}