{
  "type": "Feature",
  "properties": {
    "gn:admin1_code":"88",
    "gn:asciiname":"Zakotoros'ye",
    "gn:country_code":"RU",
    "gn:dem":127,
    "gn:feature_class":"P",
    "gn:feature_code":"PPL",
    "gn:name":"Zakotoros\u2019ye",
    "gn:population":0,
    "gn:timezone":"Europe/Moscow",
    "iso:country":"RU",
    "name:rus_x_preferred":[
        "\u0417\u0430\u043a\u043e\u0442\u0440\u043e\u0441\u044c\u0435"
    ],
    "name:und_x_variant":[
        "Zakotoros\u2019ye"
    ],
    "wof:name":"Zakotoros'ye",
    "wof:placetype":"locality"
},
  "geometry": {"coordinates":[39.33368,57.61799],"type":"Point"}
}