{
  "type": "Feature",
  "properties": {
    "gn:admin1_code":"40",
    "gn:asciiname":"Dan'kovo",
    "gn:country_code":"RU",
    "gn:dem":146,
    "gn:feature_class":"P",
    "gn:feature_code":"PPL",
    "gn:name":"Dan\u2019kovo",
    "gn:population":0,
    "gn:timezone":"Asia/Yekaterinburg",
    "iso:country":"RU",
    "name:eng_x_preferred":[
        "Dan'kovo"
    ],
    "name:nor_x_preferred":[
        "Dankovo"
    ],
    "name:rus_x_preferred":[
        "\u0414\u0430\u043d\u044c\u043a\u043e\u0432\u043e"
    ],
    "name:und_x_variant":[
        "Dan\u2019kovo"
    ],
    "wof:name":"Dan'kovo",
    "wof:placetype":"locality"
},
  "geometry": {"coordinates":[62.6874,55.1017],"type":"Point"}
}