{
  "type": "Feature",
  "properties": {
    "gn:admin1_code":"85",
    "gn:asciiname":"Mostovitsa",
    "gn:country_code":"RU",
    "gn:dem":160,
    "gn:feature_class":"P",
    "gn:feature_code":"PPL",
    "gn:name":"Mostovitsa",
    "gn:population":0,
    "gn:timezone":"Europe/Moscow",
    "iso:country":"RU",
    "name:eng_x_preferred":[
        "Mostovitsa"
    ],
    "name:nor_x_preferred":[
        "Mostovitsa"
    ],
    "name:rus_x_preferred":[
        "\u041c\u043e\u0441\u0442\u043e\u0432\u0438\u0446\u0430"
    ],
    "name:und_x_variant":[
        "\u041c\u043e\u0441\u0442\u043e\u0432\u0438\u0446\u0430",
        "Mostovitsa"
    ],
    "wof:name":"Mostovitsa",
    "wof:placetype":"locality"
},
  "geometry": {"coordinates":[44.89066,60.16601],"type":"Point"}
}