{
  "type": "Feature",
  "properties": {
    "gn:admin1_code":"25.0",
    "gn:asciiname":"Vostok",
    "gn:country_code":"RU",
    "gn:dem":207,
    "gn:feature_class":"P",
    "gn:feature_code":"PPL",
    "gn:name":"Vostok",
    "gn:population":0,
    "gn:timezone":"Europe/Moscow",
    "iso:country":"RU",
    "name:rus_x_preferred":[
        "\u0412\u043e\u0441\u0442\u043e\u043a"
    ],
    "wof:name":"Vostok",
    "wof:placetype":"locality"
},
  "geometry": {"coordinates":[34.61940999999999,54.20084],"type":"Point"}
}