{
  "type": "Feature",
  "properties": {
    "gn:admin1_code":"37",
    "gn:asciiname":"Kapustino",
    "gn:country_code":"RU",
    "gn:dem":165,
    "gn:feature_class":"P",
    "gn:feature_code":"PPL",
    "gn:name":"Kapustino",
    "gn:population":0,
    "gn:timezone":"Europe/Moscow",
    "iso:country":"RU",
    "name:rus_x_preferred":[
        "\u041a\u0430\u043f\u0443\u0441\u0442\u0438\u043d\u043e"
    ],
    "name:und_x_variant":[
        "\u041a\u0430\u043f\u0443\u0441\u0442\u0438\u043d\u043e"
    ],
    "wof:name":"Kapustino",
    "wof:placetype":"locality"
},
  "geometry": {"coordinates":[43.0495,58.6928],"type":"Point"}
}