{
  "type": "Feature",
  "properties": {
    "gn:admin1_code":"10.0",
    "gn:asciiname":"Desyatiny",
    "gn:country_code":"RU",
    "gn:dem":171,
    "gn:feature_class":"P",
    "gn:feature_code":"PPL",
    "gn:name":"Desyatiny",
    "gn:population":0,
    "gn:timezone":"Europe/Moscow",
    "iso:country":"RU",
    "name:rus_x_preferred":[
        "\u0414\u0435\u0441\u044f\u0442\u0438\u043d\u044b"
    ],
    "name:und_x_variant":[
        "\u0414\u0435\u0441\u044f\u0442\u0438\u043d\u044b",
        "Desyatina"
    ],
    "wof:name":"Desyatiny",
    "wof:placetype":"locality"
},
  "geometry": {"coordinates":[32.09217,52.31868],"type":"Point"}
}