{
  "type": "Feature",
  "properties": {
    "gn:admin1_code":"84.0",
    "gn:asciiname":"Demidov",
    "gn:country_code":"RU",
    "gn:dem":23,
    "gn:feature_class":"P",
    "gn:feature_code":"PPL",
    "gn:name":"Demidov",
    "gn:population":0,
    "gn:timezone":"Europe/Volgograd",
    "iso:country":"RU",
    "name:ara_x_preferred":[
        "\u062f\u0645\u064a\u062f\u0648\u0641"
    ],
    "name:aze_x_preferred":[
        "Demidovlar"
    ],
    "name:deu_x_preferred":[
        "Demidow"
    ],
    "name:epo_x_preferred":[
        "Demidov"
    ],
    "name:est_x_preferred":[
        "Demidov"
    ],
    "name:fin_x_preferred":[
        "Demidov"
    ],
    "name:fra_x_preferred":[
        "Famille Demidoff"
    ],
    "name:hun_x_preferred":[
        "Gyemidov csal\u00e1d"
    ],
    "name:ita_x_preferred":[
        "Demidov"
    ],
    "name:jpn_x_preferred":[
        "\u30c7\u30df\u30c9\u30d5\u5bb6"
    ],
    "name:nld_x_preferred":[
        "Demidov"
    ],
    "name:rus_x_preferred":[
        "\u0414\u0435\u043c\u0438\u0434\u043e\u0432"
    ],
    "name:rus_x_variant":[
        "\u0414\u0435\u043c\u0438\u0434\u043e\u0432\u044b"
    ],
    "name:spa_x_preferred":[
        "Dem\u00eddov"
    ],
    "name:ukr_x_preferred":[
        "\u0414\u0435\u043c\u0438\u0434\u043e\u0432\u0438"
    ],
    "wof:name":"Demidov",
    "wof:placetype":"locality"
},
  "geometry": {"coordinates":[45.96667,49.55],"type":"Point"}
}