{
  "type": "Feature",
  "properties": {
    "gn:admin1_code":"29",
    "gn:asciiname":"Biryulya",
    "gn:country_code":"RU",
    "gn:dem":277,
    "gn:feature_class":"P",
    "gn:feature_code":"PPL",
    "gn:name":"Biryulya",
    "gn:population":0,
    "gn:timezone":"Asia/Novokuznetsk",
    "iso:country":"RU",
    "name:ceb_x_preferred":[
        "Biryulya"
    ],
    "name:che_x_preferred":[
        "\u0411\u0438\u0440\u044e\u043b\u044f"
    ],
    "name:eng_x_preferred":[
        "Biryulya"
    ],
    "name:nor_x_preferred":[
        "Birjulja"
    ],
    "name:rus_x_preferred":[
        "\u0411\u0438\u0440\u044e\u043b\u044f"
    ],
    "name:tat_x_preferred":[
        "\u0411\u0438\u0440\u044e\u043b\u044f"
    ],
    "name:ukr_x_preferred":[
        "\u0411\u0456\u0440\u044e\u043b\u044f"
    ],
    "name:und_x_variant":[
        "Biryulinskiy",
        "\u0411\u0438\u0440\u044e\u043b\u044f",
        "Biryulya"
    ],
    "wof:name":"Biryulya",
    "wof:placetype":"locality"
},
  "geometry": {"coordinates":[85.4859,54.3343],"type":"Point"}
}