{
  "type": "Feature",
  "properties": {
    "gn:admin1_code":"43",
    "gn:asciiname":"Nikol'skiye Vyselki",
    "gn:country_code":"RU",
    "gn:dem":165,
    "gn:feature_class":"P",
    "gn:feature_code":"PPL",
    "gn:name":"Nikol\u2019skiye Vyselki",
    "gn:population":0,
    "gn:timezone":"Europe/Moscow",
    "iso:country":"RU",
    "name:rus_x_preferred":[
        "\u041d\u0438\u043a\u043e\u043b\u044c\u0441\u043a\u0438\u0435 \u0412\u044b\u0441\u0435\u043b\u043a\u0438"
    ],
    "name:und_x_variant":[
        "Nikol\u2019skiy",
        "Nikol\u2019skiy Byselki",
        "Nikol\u2019skiye Vyselki"
    ],
    "wof:name":"Nikol'skiye Vyselki",
    "wof:placetype":"locality"
},
  "geometry": {"coordinates":[39.78297,51.95121],"type":"Point"}
}