{
  "type": "Feature",
  "properties": {
    "gn:admin1_code":"88",
    "gn:asciiname":"Lychentsy",
    "gn:country_code":"RU",
    "gn:dem":164,
    "gn:feature_class":"P",
    "gn:feature_code":"PPL",
    "gn:name":"Lychentsy",
    "gn:population":0,
    "gn:timezone":"Europe/Moscow",
    "iso:country":"RU",
    "name:eng_x_preferred":[
        "Lychentsy"
    ],
    "name:nor_x_preferred":[
        "Lytsjentsy"
    ],
    "name:rus_x_preferred":[
        "\u041b\u044b\u0447\u0435\u043d\u0446\u044b"
    ],
    "name:und_x_variant":[
        "\u041b\u044b\u0447\u0435\u043d\u0446\u044b",
        "Lychentsy"
    ],
    "wof:name":"Lychentsy",
    "wof:placetype":"locality"
},
  "geometry": {"coordinates":[38.81604,56.95379000000001],"type":"Point"}
}