{
  "type": "Feature",
  "properties": {
    "gn:admin1_code":"85",
    "gn:asciiname":"Yelovino",
    "gn:country_code":"RU",
    "gn:dem":167,
    "gn:feature_class":"P",
    "gn:feature_code":"PPL",
    "gn:name":"Yelovino",
    "gn:population":0,
    "gn:timezone":"Europe/Moscow",
    "iso:country":"RU",
    "name:eng_x_preferred":[
        "Yelovino"
    ],
    "name:nor_x_preferred":[
        "Jelovino"
    ],
    "name:rus_x_preferred":[
        "\u0415\u043b\u043e\u0432\u0438\u043d\u043e"
    ],
    "name:und_x_variant":[
        "Yelovinskoye"
    ],
    "wof:name":"Yelovino",
    "wof:placetype":"locality"
},
  "geometry": {"coordinates":[45.83515,59.80258000000001],"type":"Point"}
}