{
  "type": "Feature",
  "properties": {
    "gn:admin1_code":"83",
    "gn:asciiname":"Kryuki",
    "gn:country_code":"RU",
    "gn:dem":154,
    "gn:feature_class":"P",
    "gn:feature_code":"PPL",
    "gn:name":"Kryuki",
    "gn:population":0,
    "gn:timezone":"Europe/Moscow",
    "iso:country":"RU",
    "name:rus_x_preferred":[
        "\u041a\u0440\u044e\u043a\u0438"
    ],
    "wof:name":"Kryuki",
    "wof:placetype":"locality"
},
  "geometry": {"coordinates":[39.31356,56.09106],"type":"Point"}
}