{
  "type": "Feature",
  "properties": {
    "gn:admin1_code":"21.0",
    "gn:asciiname":"Maksimovskoye",
    "gn:country_code":"RU",
    "gn:dem":117,
    "gn:feature_class":"P",
    "gn:feature_code":"PPL",
    "gn:name":"Maksimovskoye",
    "gn:population":0,
    "gn:timezone":"Europe/Moscow",
    "iso:country":"RU",
    "name:rus_x_preferred":[
        "\u041c\u0430\u043a\u0441\u0438\u043c\u043e\u0432\u0441\u043a\u043e\u0435"
    ],
    "name:und_x_variant":[
        "\u041c\u0430\u043a\u0441\u0438\u043c\u043e\u0432\u0441\u043a\u043e\u0435"
    ],
    "wof:name":"Maksimovskoye",
    "wof:placetype":"locality"
},
  "geometry": {"coordinates":[41.68223,57.14853000000001],"type":"Point"}
}