{
  "type": "Feature",
  "properties": {
    "gn:admin1_code":"40",
    "gn:asciiname":"Ozhogino",
    "gn:country_code":"RU",
    "gn:dem":129,
    "gn:feature_class":"P",
    "gn:feature_code":"PPL",
    "gn:name":"Ozhogino",
    "gn:population":0,
    "gn:timezone":"Asia/Yekaterinburg",
    "iso:country":"RU",
    "name:eng_x_preferred":[
        "Ozhogino"
    ],
    "name:nor_x_preferred":[
        "Ozjogino"
    ],
    "name:rus_x_preferred":[
        "\u041e\u0436\u043e\u0433\u0438\u043d\u043e"
    ],
    "wof:name":"Ozhogino",
    "wof:placetype":"locality"
},
  "geometry": {"coordinates":[64.52549999999999,56.3991],"type":"Point"}
}