{
  "type": "Feature",
  "properties": {
    "gn:admin1_code":"47",
    "gn:asciiname":"Spas-Kamenka",
    "gn:country_code":"RU",
    "gn:dem":199,
    "gn:feature_class":"P",
    "gn:feature_code":"PPL",
    "gn:name":"Spas-Kamenka",
    "gn:population":0,
    "gn:timezone":"Europe/Moscow",
    "iso:country":"RU",
    "name:rus_x_preferred":[
        "\u0421\u043f\u0430\u0441-\u041a\u0430\u043c\u0435\u043d\u043a\u0430"
    ],
    "wof:name":"Spas-Kamenka",
    "wof:placetype":"locality"
},
  "geometry": {"coordinates":[37.45535,56.15016],"type":"Point"}
}