{
  "type": "Feature",
  "properties": {
    "gn:admin1_code":"52",
    "gn:asciiname":"Veret'ye",
    "gn:country_code":"RU",
    "gn:dem":68,
    "gn:feature_class":"P",
    "gn:feature_code":"PPL",
    "gn:name":"Veret\u2019y\u00eb",
    "gn:population":0,
    "gn:timezone":"Europe/Moscow",
    "iso:country":"RU",
    "name:rus_x_preferred":[
        "\u0412\u0435\u0440\u0435\u0442\u044c\u00eb"
    ],
    "name:und_x_variant":[
        "Veret\u2019y\u00eb"
    ],
    "wof:name":"Veret'ye",
    "wof:placetype":"locality"
},
  "geometry": {"coordinates":[30.91184,57.96774],"type":"Point"}
}