{
  "type": "Feature",
  "properties": {
    "gn:country":"RU",
    "gn:fcode":"PPL",
    "gn:population":0,
    "iso:country":"RU",
    "name:ceb_x_preferred":[
        "Khiitola"
    ],
    "name:che_x_preferred":[
        "\u0425\u0438\u0439\u0442\u043e\u043b\u0430"
    ],
    "name:dan_x_preferred":[
        "Hiitola"
    ],
    "name:deu_x_preferred":[
        "Hiitola"
    ],
    "name:ell_x_preferred":[
        "\u03a7\u03b9\u03af\u03c4\u03bf\u03bb\u03b1"
    ],
    "name:eng_x_preferred":[
        "Khiitola"
    ],
    "name:eng_x_variant":[
        "Khiytola"
    ],
    "name:epo_x_preferred":[
        "Hiitola"
    ],
    "name:est_x_preferred":[
        "Hiitola"
    ],
    "name:fin_x_preferred":[
        "Hiitola"
    ],
    "name:fra_x_preferred":[
        "Hiitola"
    ],
    "name:hye_x_preferred":[
        "\u053d\u056b\u0575\u057f\u0578\u056c\u0561"
    ],
    "name:ita_x_preferred":[
        "Chijtola"
    ],
    "name:jpn_x_preferred":[
        "\u30d2\u30fc\u30c8\u30e9"
    ],
    "name:nld_x_preferred":[
        "Khiytola"
    ],
    "name:nob_x_preferred":[
        "Khijtola"
    ],
    "name:nor_x_preferred":[
        "Khijtola"
    ],
    "name:olo_x_preferred":[
        "Hiitola"
    ],
    "name:por_x_preferred":[
        "Hiitola"
    ],
    "name:rus_x_preferred":[
        "\u0425\u0438\u0439\u0442\u043e\u043b\u0430"
    ],
    "name:rus_x_variant":[
        "\u0425\u0438\u0438\u0442\u043e\u043b\u0430",
        "\u0413\u0440\u0443\u0437\u0438\u043d\u043e"
    ],
    "name:swe_x_preferred":[
        "Hiitola"
    ],
    "name:und_x_variant":[
        "Hitola"
    ],
    "name:zho_x_preferred":[
        "\u5e0c\u6258\u62c9"
    ],
    "qs:name":"Khiitola",
    "qs:name_adm0":"Russia",
    "qs:name_adm1":"Karelia Republic",
    "qs:photos_9k":1,
    "qs:photos_9r":1,
    "qs:photos_all":21,
    "qs:photos_sr":0,
    "qs:placetype":"Town",
    "qs:pop_sr":"0",
    "wof:name":"Khiitola",
    "wof:placetype":"locality",
    "wof:population":0
},
  "geometry": {"coordinates":[29.69067,61.23927],"type":"Point"}
}