{
  "type": "Feature",
  "properties": {
    "gn:admin1_code":"42",
    "gn:asciiname":"Krasnyye Gory",
    "gn:country_code":"RU",
    "gn:dem":65,
    "gn:feature_class":"P",
    "gn:feature_code":"PPL",
    "gn:name":"Krasnyye Gory",
    "gn:population":0,
    "gn:timezone":"Europe/Moscow",
    "iso:country":"RU",
    "name:rus_x_preferred":[
        "\u041a\u0440\u0430\u0441\u043d\u044b\u0435 \u0413\u043e\u0440\u044b"
    ],
    "wof:name":"Krasnyye Gory",
    "wof:placetype":"locality"
},
  "geometry": {"coordinates":[29.63588,58.94933],"type":"Point"}
}