{
  "type": "Feature",
  "properties": {
    "gn:admin1_code":"84",
    "gn:asciiname":"Krasnaya Derevnya",
    "gn:country_code":"RU",
    "gn:dem":22,
    "gn:feature_class":"P",
    "gn:feature_code":"PPL",
    "gn:name":"Krasnaya Derevnya",
    "gn:population":0,
    "gn:timezone":"Europe/Volgograd",
    "iso:country":"RU",
    "name:eng_x_preferred":[
        "Krasnaya Derevnya"
    ],
    "name:nor_x_preferred":[
        "Krasnaja Derevnja"
    ],
    "name:rus_x_preferred":[
        "\u041a\u0440\u0430\u0441\u043d\u0430\u044f \u0414\u0435\u0440\u0435\u0432\u043d\u044f"
    ],
    "wof:name":"Krasnaya Derevnya",
    "wof:placetype":"locality"
},
  "geometry": {"coordinates":[46.4863,49.13272],"type":"Point"}
}