{
  "type": "Feature",
  "properties": {
    "gn:admin1_code":"17",
    "gn:admin2_code":"Charodinskiy Rayon",
    "gn:asciiname":"Sachada",
    "gn:country_code":"RU",
    "gn:dem":1919,
    "gn:feature_class":"P",
    "gn:feature_code":"PPL",
    "gn:name":"Sachada",
    "gn:population":0,
    "gn:timezone":"Europe/Moscow",
    "iso:country":"RU",
    "name:rus_x_preferred":[
        "\u0421\u0430\u0447\u0430\u0434\u0430"
    ],
    "name:und_x_variant":[
        "Sochada",
        "Sachada"
    ],
    "wof:name":"Sachada",
    "wof:placetype":"locality"
},
  "geometry": {"coordinates":[46.69864000000001,42.25928],"type":"Point"}
}