{
  "type": "Feature",
  "properties": {
    "gn:country":"RU",
    "gn:fcode":"PPL",
    "gn:population":0,
    "iso:country":"RU",
    "name:eng_x_preferred":[
        "Kubina"
    ],
    "name:nor_x_preferred":[
        "Kubina"
    ],
    "name:rus_x_preferred":[
        "\u041a\u0443\u0431\u0438\u043d\u0430"
    ],
    "qs:name":"Kubina",
    "qs:name_adm0":"Russia",
    "qs:name_adm1":"Karachay-Cherkessia Republic",
    "qs:photos_9r":0,
    "qs:photos_sr":0,
    "qs:placetype":"Town",
    "qs:pop_sr":"0",
    "wof:name":"Kubina",
    "wof:placetype":"locality",
    "wof:population":0
},
  "geometry": {"coordinates":[41.9517,44.0555],"type":"Point"}
}