{
  "type": "Feature",
  "properties": {
    "gn:admin1_code":"77",
    "gn:asciiname":"Mashutino",
    "gn:country_code":"RU",
    "gn:dem":140,
    "gn:feature_class":"P",
    "gn:feature_code":"PPL",
    "gn:name":"Mashutino",
    "gn:population":0,
    "gn:timezone":"Europe/Moscow",
    "iso:country":"RU",
    "name:rus_x_preferred":[
        "\u041c\u0430\u0448\u0443\u0442\u0438\u043d\u043e"
    ],
    "wof:name":"Mashutino",
    "wof:placetype":"locality"
},
  "geometry": {"coordinates":[38.269,57.3152],"type":"Point"}
}