{
  "type": "Feature",
  "properties": {
    "gn:admin1_code":"88.0",
    "gn:asciiname":"Bogorodskoye",
    "gn:country_code":"RU",
    "gn:dem":135,
    "gn:feature_class":"P",
    "gn:feature_code":"PPL",
    "gn:name":"Bogorodskoye",
    "gn:population":0,
    "gn:timezone":"Europe/Moscow",
    "iso:country":"RU",
    "name:eng_x_preferred":[
        "Bogorodskoye"
    ],
    "name:nor_x_preferred":[
        "Bogorodskoje"
    ],
    "name:rus_x_preferred":[
        "\u0411\u043e\u0433\u043e\u0440\u043e\u0434\u0441\u043a\u043e\u0435"
    ],
    "name:und_x_variant":[
        "\u0411\u043e\u0433\u043e\u0440\u043e\u0434\u0441\u043a\u043e\u0435",
        "Bogorodskoye"
    ],
    "wof:name":"Bogorodskoye",
    "wof:placetype":"locality"
},
  "geometry": {"coordinates":[37.76667,57.66667],"type":"Point"}
}