{
  "type": "Feature",
  "properties": {
    "gn:admin1_code":"37.0",
    "gn:asciiname":"Dmitriyevskoye",
    "gn:country_code":"RU",
    "gn:dem":130,
    "gn:feature_class":"P",
    "gn:feature_code":"PPL",
    "gn:name":"Dmitriyevskoye",
    "gn:population":0,
    "gn:timezone":"Europe/Moscow",
    "iso:country":"RU",
    "wof:name":"Dmitriyevskoye",
    "wof:placetype":"locality"
},
  "geometry": {"coordinates":[41.30853,58.48398],"type":"Point"}
}