{
  "type": "Feature",
  "properties": {
    "gn:admin1_code":"72",
    "gn:asciiname":"Kalinovka",
    "gn:country_code":"RU",
    "gn:dem":133,
    "gn:feature_class":"P",
    "gn:feature_code":"PPL",
    "gn:name":"Kalinovka",
    "gn:population":0,
    "gn:timezone":"Europe/Moscow",
    "iso:country":"RU",
    "name:rus_x_preferred":[
        "\u041a\u0430\u043b\u0438\u043d\u043e\u0432\u043a\u0430"
    ],
    "name:und_x_variant":[
        "\u041a\u0430\u043b\u0438\u043d\u043e\u0432\u043a\u0430"
    ],
    "wof:name":"Kalinovka",
    "wof:placetype":"locality"
},
  "geometry": {"coordinates":[41.39165,53.0542],"type":"Point"}
}