{
  "type": "Feature",
  "properties": {
    "gn:admin1_code":"84",
    "gn:asciiname":"Morets",
    "gn:country_code":"RU",
    "gn:dem":130,
    "gn:feature_class":"P",
    "gn:feature_code":"PPL",
    "gn:name":"Morets",
    "gn:population":0,
    "gn:timezone":"Europe/Volgograd",
    "iso:country":"RU",
    "name:eng_x_preferred":[
        "Morets"
    ],
    "name:nor_x_preferred":[
        "Morets"
    ],
    "name:rus_x_preferred":[
        "\u041c\u043e\u0440\u0435\u0446"
    ],
    "name:und_x_variant":[
        "Moretskiy",
        "\u041c\u043e\u0440\u0435\u0446",
        "Morets"
    ],
    "wof:name":"Morets",
    "wof:placetype":"locality"
},
  "geometry": {"coordinates":[44.042,51.0251],"type":"Point"}
}