{
  "type": "Feature",
  "properties": {
    "gn:admin1_code":"91",
    "gn:asciiname":"Kirel'-Okler",
    "gn:country_code":"RU",
    "gn:dem":402,
    "gn:feature_class":"P",
    "gn:feature_code":"PPL",
    "gn:name":"Kirel\u2019-Okler",
    "gn:population":0,
    "gn:timezone":"Asia/Krasnoyarsk",
    "iso:country":"RU",
    "name:rus_x_preferred":[
        "\u041a\u0438\u0440\u0435\u043b\u044c-\u041e\u043a\u043b\u0435\u0440"
    ],
    "name:und_x_variant":[
        "Kirel\u2019-Okler"
    ],
    "wof:name":"Kirel'-Okler",
    "wof:placetype":"locality"
},
  "geometry": {"coordinates":[95.01667,55.05],"type":"Point"}
}