{
  "type": "Feature",
  "properties": {
    "gn:admin1_code":"91",
    "gn:asciiname":"Il'inka",
    "gn:country_code":"RU",
    "gn:dem":313,
    "gn:feature_class":"P",
    "gn:feature_code":"PPL",
    "gn:name":"Il\u2019inka",
    "gn:population":0,
    "gn:timezone":"Asia/Krasnoyarsk",
    "iso:country":"RU",
    "name:rus_x_preferred":[
        "\u0418\u043b\u044c\u0438\u043d\u043a\u0430"
    ],
    "name:und_x_variant":[
        "Il\u2019inka"
    ],
    "wof:name":"Il'inka",
    "wof:placetype":"locality"
},
  "geometry": {"coordinates":[92.40000000000001,56.38333000000001],"type":"Point"}
}