{
  "type": "Feature",
  "properties": {
    "gn:admin1_code":"37.0",
    "gn:asciiname":"Dor",
    "gn:country_code":"RU",
    "gn:dem":129,
    "gn:feature_class":"P",
    "gn:feature_code":"PPL",
    "gn:name":"Dor",
    "gn:population":0,
    "gn:timezone":"Europe/Moscow",
    "iso:country":"RU",
    "name:eng_x_preferred":[
        "Dor"
    ],
    "name:nor_x_preferred":[
        "Dor"
    ],
    "name:rus_x_preferred":[
        "\u0414\u043e\u0440"
    ],
    "name:und_x_variant":[
        "\u0414\u043e\u0440",
        "Dor"
    ],
    "wof:name":"Dor",
    "wof:placetype":"locality"
},
  "geometry": {"coordinates":[41.2076,58.385],"type":"Point"}
}