{
  "type": "Feature",
  "properties": {
    "gn:admin1_code":"1",
    "gn:asciiname":"Petrov",
    "gn:country_code":"RU",
    "gn:dem":48,
    "gn:feature_class":"P",
    "gn:feature_code":"PPL",
    "gn:name":"Petrov",
    "gn:population":0,
    "gn:timezone":"Europe/Moscow",
    "iso:country":"RU",
    "name:bul_x_preferred":[
        "\u041f\u0435\u0442\u0440\u043e\u0432"
    ],
    "name:ceb_x_preferred":[
        "Petrov"
    ],
    "name:ces_x_preferred":[
        "Petrov"
    ],
    "name:deu_x_preferred":[
        "Petrov"
    ],
    "name:epo_x_preferred":[
        "Petrov"
    ],
    "name:fin_x_preferred":[
        "Petrov"
    ],
    "name:fra_x_preferred":[
        "Petrov"
    ],
    "name:heb_x_preferred":[
        "\u05e4\u05d8\u05e8\u05d5\u05d1"
    ],
    "name:ita_x_preferred":[
        "Petrov"
    ],
    "name:jpn_x_preferred":[
        "\u30da\u30c8\u30ed\u30d5"
    ],
    "name:lav_x_preferred":[
        "Petrovs"
    ],
    "name:nld_x_preferred":[
        "Petrov"
    ],
    "name:pol_x_preferred":[
        "Petrov"
    ],
    "name:por_x_preferred":[
        "Petrov"
    ],
    "name:rus_x_preferred":[
        "\u041f\u0435\u0442\u0440\u043e\u0432"
    ],
    "name:slk_x_preferred":[
        "Petrov"
    ],
    "name:spa_x_preferred":[
        "Petrov"
    ],
    "name:srp_x_preferred":[
        "\u041f\u0435\u0442\u0440\u043e\u0432"
    ],
    "name:swe_x_preferred":[
        "Petrov"
    ],
    "name:und_x_variant":[
        "\u041f\u0435\u0442\u0440\u043e\u0432"
    ],
    "wof:name":"Petrov",
    "wof:placetype":"locality"
},
  "geometry": {"coordinates":[39.50516,44.93322],"type":"Point"}
}