{
  "type": "Feature",
  "properties": {
    "gn:admin1_code":"85",
    "gn:asciiname":"Matyukhovo",
    "gn:country_code":"RU",
    "gn:dem":125,
    "gn:feature_class":"P",
    "gn:feature_code":"PPL",
    "gn:name":"Matyukhovo",
    "gn:population":0,
    "gn:timezone":"Europe/Moscow",
    "iso:country":"RU",
    "name:rus_x_preferred":[
        "\u041c\u0430\u0442\u044e\u0445\u043e\u0432\u043e"
    ],
    "name:und_x_variant":[
        "\u041c\u0430\u0442\u044e\u0445\u043e\u0432\u043e"
    ],
    "wof:name":"Matyukhovo",
    "wof:placetype":"locality"
},
  "geometry": {"coordinates":[38.33668,59.16806],"type":"Point"}
}