{
  "type": "Feature",
  "properties": {
    "gn:admin1_code":"42",
    "gn:admin2_code":"472350",
    "gn:asciiname":"Volgovo",
    "gn:country_code":"RU",
    "gn:dem":143,
    "gn:feature_class":"P",
    "gn:feature_code":"PPL",
    "gn:name":"Volgovo",
    "gn:population":0,
    "gn:timezone":"Europe/Moscow",
    "iso:country":"RU",
    "name:eng_x_preferred":[
        "Volgovo"
    ],
    "name:nor_x_preferred":[
        "Volgovo"
    ],
    "name:rus_x_preferred":[
        "\u0412\u043e\u043b\u0433\u043e\u0432\u043e"
    ],
    "wof:name":"Volgovo",
    "wof:placetype":"locality"
},
  "geometry": {"coordinates":[29.59712,59.56124000000001],"type":"Point"}
}