{
  "type": "Feature",
  "properties": {
    "gn:admin1_code":"21",
    "gn:asciiname":"Mukhortovo",
    "gn:country_code":"RU",
    "gn:dem":123,
    "gn:feature_class":"P",
    "gn:feature_code":"PPL",
    "gn:name":"Mukhortovo",
    "gn:population":0,
    "gn:timezone":"Europe/Moscow",
    "iso:country":"RU",
    "name:rus_x_preferred":[
        "\u041c\u0443\u0445\u043e\u0440\u0442\u043e\u0432\u043e"
    ],
    "name:und_x_variant":[
        "\u041c\u0443\u0445\u043e\u0440\u0442\u043e\u0432\u043e"
    ],
    "wof:name":"Mukhortovo",
    "wof:placetype":"locality"
},
  "geometry": {"coordinates":[42.48238,57.4028],"type":"Point"}
}