{
  "type": "Feature",
  "properties": {
    "gn:admin1_code":"60",
    "gn:asciiname":"Posolodino",
    "gn:country_code":"RU",
    "gn:dem":78,
    "gn:feature_class":"P",
    "gn:feature_code":"PPL",
    "gn:name":"Posolodino",
    "gn:population":0,
    "gn:timezone":"Europe/Moscow",
    "iso:country":"RU",
    "name:rus_x_preferred":[
        "\u041f\u043e\u0441\u043e\u043b\u043e\u0434\u0438\u043d\u043e"
    ],
    "name:und_x_variant":[
        "\u041f\u043e\u0441\u043e\u043b\u043e\u0434\u0438\u043d\u043e"
    ],
    "wof:name":"Posolodino",
    "wof:placetype":"locality"
},
  "geometry": {"coordinates":[29.16016,58.47107],"type":"Point"}
}