{
  "type": "Feature",
  "properties": {
    "gn:admin1_code":"52",
    "gn:asciiname":"Yablon'ka",
    "gn:country_code":"RU",
    "gn:dem":158,
    "gn:feature_class":"P",
    "gn:feature_code":"PPL",
    "gn:name":"Yablon\u2019ka",
    "gn:population":0,
    "gn:timezone":"Europe/Moscow",
    "iso:country":"RU",
    "name:rus_x_preferred":[
        "\u042f\u0431\u043b\u043e\u043d\u044c\u043a\u0430"
    ],
    "name:und_x_variant":[
        "Yablon\u2019ka"
    ],
    "wof:name":"Yablon'ka",
    "wof:placetype":"locality"
},
  "geometry": {"coordinates":[32.69003,57.9206],"type":"Point"}
}