{
  "type": "Feature",
  "properties": {
    "gn:admin1_code":"86",
    "gn:asciiname":"Solontsy",
    "gn:country_code":"RU",
    "gn:dem":107,
    "gn:feature_class":"P",
    "gn:feature_code":"PPL",
    "gn:name":"Solontsy",
    "gn:population":0,
    "gn:timezone":"Europe/Moscow",
    "iso:country":"RU",
    "name:rus_x_preferred":[
        "\u0421\u043e\u043b\u043e\u043d\u0446\u044b"
    ],
    "wof:name":"Solontsy",
    "wof:placetype":"locality"
},
  "geometry": {"coordinates":[39.44707,51.30882],"type":"Point"}
}