{
  "type": "Feature",
  "properties": {
    "gn:admin1_code":"25",
    "gn:asciiname":"Kashino",
    "gn:country_code":"RU",
    "gn:dem":166,
    "gn:feature_class":"P",
    "gn:feature_code":"PPL",
    "gn:name":"Kashino",
    "gn:population":0,
    "gn:timezone":"Europe/Moscow",
    "iso:country":"RU",
    "name:rus_x_preferred":[
        "\u041a\u0430\u0448\u0438\u043d\u043e"
    ],
    "name:und_x_variant":[
        "\u041a\u0430\u0448\u0438\u043d\u043e"
    ],
    "wof:name":"Kashino",
    "wof:placetype":"locality"
},
  "geometry": {"coordinates":[35.4075,54.63639000000001],"type":"Point"}
}