{
  "type": "Feature",
  "properties": {
    "gn:admin1_code":"80",
    "gn:asciiname":"Kochetla",
    "gn:country_code":"RU",
    "gn:dem":93,
    "gn:feature_class":"P",
    "gn:feature_code":"PPL",
    "gn:name":"Kochetla",
    "gn:population":0,
    "gn:timezone":"Europe/Samara",
    "iso:country":"RU",
    "name:rus_x_preferred":[
        "\u041a\u043e\u0447\u0435\u0442\u043b\u0430"
    ],
    "name:und_x_variant":[
        "\u041a\u043e\u0447\u0435\u0442\u043b\u0430"
    ],
    "wof:name":"Kochetla",
    "wof:placetype":"locality"
},
  "geometry": {"coordinates":[51.47073,56.23331],"type":"Point"}
}