{
  "type": "Feature",
  "properties": {
    "gn:admin1_code":"56",
    "gn:asciiname":"Chistopol'ye",
    "gn:country_code":"RU",
    "gn:dem":216,
    "gn:feature_class":"P",
    "gn:feature_code":"PPL",
    "gn:name":"Chistopol\u2019ye",
    "gn:population":0,
    "gn:timezone":"Europe/Moscow",
    "iso:country":"RU",
    "name:rus_x_preferred":[
        "\u0427\u0438\u0441\u0442\u043e\u043f\u043e\u043b\u044c\u0435"
    ],
    "name:und_x_variant":[
        "Chistopol\u2019ye",
        "\u0427\u0438\u0441\u0442\u043e\u043f\u043e\u043b\u044c\u0435"
    ],
    "wof:name":"Chistopol'ye",
    "wof:placetype":"locality"
},
  "geometry": {"coordinates":[35.2326,52.80814],"type":"Point"}
}