{
  "type": "Feature",
  "properties": {
    "gn:admin1_code":"77",
    "gn:asciiname":"Kamino",
    "gn:country_code":"RU",
    "gn:dem":198,
    "gn:feature_class":"P",
    "gn:feature_code":"PPL",
    "gn:name":"Kamino",
    "gn:population":0,
    "gn:timezone":"Europe/Moscow",
    "iso:country":"RU",
    "name:rus_x_preferred":[
        "\u041a\u0430\u043c\u0438\u043d\u043e"
    ],
    "name:und_x_variant":[
        "\u041a\u0430\u043c\u0438\u043d\u043e"
    ],
    "wof:name":"Kamino",
    "wof:placetype":"locality"
},
  "geometry": {"coordinates":[31.68333,55.86666999999999],"type":"Point"}
}