{
  "type": "Feature",
  "properties": {
    "gn:admin1_code":"77",
    "gn:asciiname":"Tsitsyno",
    "gn:country_code":"RU",
    "gn:dem":230,
    "gn:feature_class":"P",
    "gn:feature_code":"PPL",
    "gn:name":"Tsitsyno",
    "gn:population":0,
    "gn:timezone":"Europe/Moscow",
    "iso:country":"RU",
    "name:rus_x_preferred":[
        "\u0426\u0438\u0446\u044b\u043d\u043e"
    ],
    "name:und_x_variant":[
        "\u0426\u0438\u0446\u044b\u043d\u043e",
        "Tsitsina"
    ],
    "wof:name":"Tsitsyno",
    "wof:placetype":"locality"
},
  "geometry": {"coordinates":[32.87806,55.76167],"type":"Point"}
}