{
  "type": "Feature",
  "properties": {
    "gn:admin1_code":"20.0",
    "gn:asciiname":"Kalinovka",
    "gn:country_code":"RU",
    "gn:dem":436,
    "gn:feature_class":"P",
    "gn:feature_code":"PPL",
    "gn:name":"Kalinovka",
    "gn:population":0,
    "gn:timezone":"Asia/Irkutsk",
    "iso:country":"RU",
    "wof:name":"Kalinovka",
    "wof:placetype":"locality"
},
  "geometry": {"coordinates":[103.65678,52.46928000000001],"type":"Point"}
}