{
  "type": "Feature",
  "properties": {
    "gn:country":"RU",
    "gn:fcode":"PPL",
    "gn:population":2409,
    "iso:country":"RU",
    "name:eng_x_preferred":[
        "Khulimsunt"
    ],
    "name:nor_x_preferred":[
        "Khulimsunt"
    ],
    "name:rus_x_preferred":[
        "\u0425\u0443\u043b\u0438\u043c\u0441\u0443\u043d\u0442"
    ],
    "name:und_x_variant":[
        "Khulyum-Sunt"
    ],
    "qs:name":"Khulimsunt",
    "qs:photos_9r":0,
    "qs:photos_sr":0,
    "qs:pop_sr":"4",
    "wof:name":"Khulimsunt",
    "wof:placetype":"locality",
    "wof:population":2409
},
  "geometry": {"coordinates":[61.64361,62.86333],"type":"Point"}
}