{
  "type": "Feature",
  "properties": {
    "gn:admin1_code":"63",
    "gn:asciiname":"Mungurdakh",
    "gn:country_code":"RU",
    "gn:dem":92,
    "gn:feature_class":"P",
    "gn:feature_code":"PPL",
    "gn:name":"Mungurdakh",
    "gn:population":0,
    "gn:timezone":"Asia/Vladivostok",
    "iso:country":"RU",
    "name:rus_x_preferred":[
        "\u041c\u0443\u043d\u0433\u0443\u0440\u0434\u0430\u0445"
    ],
    "name:und_x_variant":[
        "Murdakh",
        "Mugurdkah",
        "Muurdakh",
        "Mungurdakh",
        "\u041c\u0443\u043d\u0433\u0443\u0440\u0434\u0430\u0445"
    ],
    "wof:name":"Mungurdakh",
    "wof:placetype":"locality"
},
  "geometry": {"coordinates":[134.76886000000002,68.50439],"type":"Point"}
}