{
  "type": "Feature",
  "properties": {
    "gn:admin1_code":"56",
    "gn:asciiname":"Rzhanoye",
    "gn:country_code":"RU",
    "gn:dem":257,
    "gn:feature_class":"P",
    "gn:feature_code":"PPL",
    "gn:name":"Rzhanoye",
    "gn:population":0,
    "gn:timezone":"Europe/Moscow",
    "iso:country":"RU",
    "name:rus_x_preferred":[
        "\u0420\u0436\u0430\u043d\u043e\u0435"
    ],
    "name:und_x_variant":[
        "Arzhanoye",
        "Rzhanoye"
    ],
    "wof:name":"Rzhanoye",
    "wof:placetype":"locality"
},
  "geometry": {"coordinates":[36.61355,52.91001],"type":"Point"}
}