{
  "type": "Feature",
  "properties": {
    "gn:country":"RU",
    "gn:fcode":"PPL",
    "gn:pop":0,
    "iso:country":"RU",
    "name:rus_x_preferred":[
        "\u041f\u044f\u0442\u0438\u043b\u0435\u0442\u043a\u0430"
    ],
    "name:unk_x_variant":[
        "Dobrunskiye Vyselki"
    ],
    "qs:name":"Pyatiletka",
    "qs:name_adm0":"Russia",
    "qs:name_adm1":"Bryansk Oblast",
    "qs:photos_9r":0,
    "qs:photos_sr":0,
    "qs:placetype":"Town",
    "qs:pop_sr":"0",
    "wof:name":"Pyatiletka",
    "wof:placetype":"locality",
    "wof:population":0
},
  "geometry": {"coordinates":[34.30883,53.15905],"type":"Point"}
}