{
  "type": "Feature",
  "properties": {
    "gn:gn_country":"RU",
    "gn:gn_fcode":"PPL",
    "gn:gn_pop":9451,
    "gn:population":9451,
    "iso:country":"RU",
    "name:eng_x_preferred":[
        "Ugleural'skiy"
    ],
    "name:nor_x_preferred":[
        "Ugleuralskij"
    ],
    "name:rus_x_preferred":[
        "\u0423\u0433\u043b\u0435\u0443\u0440\u0430\u043b\u044c\u0441\u043a\u0438\u0439"
    ],
    "name:unk_x_variant":[
        "Ugeural\u2019skiy"
    ],
    "qs_pg:aaroncc":"RU",
    "qs_pg:gn_country":"RU",
    "qs_pg:gn_fcode":"PPL",
    "qs_pg:gn_pop":9451,
    "qs_pg:name":"Ugleural\u2019skiy",
    "qs_pg:photos_9r":0,
    "qs_pg:photos_sr":0,
    "qs_pg:pop_sr":5,
    "qs_pg:qs_pg_placetype":"locality",
    "wof:name":"Ugleural\u2019skiy",
    "wof:placetype":"locality",
    "wof:population":9451
},
  "geometry": {"coordinates":[57.5937,58.9443],"type":"Point"}
}