{
  "type": "Feature",
  "properties": {
    "gn:admin1_code":"40",
    "gn:asciiname":"Ozernoye",
    "gn:country_code":"RU",
    "gn:dem":179,
    "gn:feature_class":"P",
    "gn:feature_code":"PPL",
    "gn:name":"Oz\u00ebrnoye",
    "gn:population":0,
    "gn:timezone":"Asia/Yekaterinburg",
    "iso:country":"RU",
    "name:rus_x_preferred":[
        "\u041e\u0437\u0451\u0440\u043d\u043e\u0435"
    ],
    "name:und_x_variant":[
        "Oz\u00ebrnoye",
        "\u041e\u0437\u0451\u0440\u043d\u043e\u0435"
    ],
    "wof:name":"Ozernoye",
    "wof:placetype":"locality"
},
  "geometry": {"coordinates":[62.97971999999999,54.82389000000001],"type":"Point"}
}