{
  "type": "Feature",
  "properties": {
    "gn:admin1_code":"10",
    "gn:asciiname":"Sekach",
    "gn:country_code":"RU",
    "gn:dem":209,
    "gn:feature_class":"P",
    "gn:feature_code":"PPL",
    "gn:name":"Sekach",
    "gn:population":0,
    "gn:timezone":"Europe/Moscow",
    "iso:country":"RU",
    "name:rus_x_preferred":[
        "\u0421\u0435\u043a\u0430\u0447"
    ],
    "name:und_x_variant":[
        "\u0421\u0435\u043a\u0430\u0447"
    ],
    "wof:name":"Sekach",
    "wof:placetype":"locality"
},
  "geometry": {"coordinates":[33.51,53.95083],"type":"Point"}
}