{
  "type": "Feature",
  "properties": {
    "gn:admin1_code":"64",
    "gn:asciiname":"Orlovo",
    "gn:country_code":"RU",
    "gn:dem":10,
    "gn:feature_class":"P",
    "gn:feature_code":"PPL",
    "gn:name":"Orlovo",
    "gn:population":0,
    "gn:timezone":"Asia/Sakhalin",
    "iso:country":"RU",
    "name:eng_x_preferred":[
        "Orlovo"
    ],
    "name:nor_x_preferred":[
        "Orlovo"
    ],
    "name:rus_x_preferred":[
        "\u041e\u0440\u043b\u043e\u0432\u043e"
    ],
    "name:und_x_variant":[
        "Ushiyoro",
        "Usiioro",
        "Usiro",
        "Unari",
        "Ushiro",
        "\u041e\u0440\u043b\u043e\u0432\u043e",
        "Orlovo"
    ],
    "wof:name":"Orlovo",
    "wof:placetype":"locality"
},
  "geometry": {"coordinates":[141.95113000000001,48.8479],"type":"Point"}
}