{
  "type": "Feature",
  "properties": {
    "gn:admin1_code":"83.0",
    "gn:asciiname":"Anis'kino",
    "gn:country_code":"RU",
    "gn:dem":132,
    "gn:feature_class":"P",
    "gn:feature_code":"PPL",
    "gn:name":"Anis\u2019kino",
    "gn:population":0,
    "gn:timezone":"Europe/Moscow",
    "iso:country":"RU",
    "name:nor_x_preferred":[
        "Aniskino"
    ],
    "name:rus_x_preferred":[
        "\u0410\u043d\u0438\u0441\u044c\u043a\u0438\u043d\u043e"
    ],
    "name:und_x_variant":[
        "Anis\u2019kino"
    ],
    "wof:name":"Anis'kino",
    "wof:placetype":"locality"
},
  "geometry": {"coordinates":[39.15528,55.94849],"type":"Point"}
}