{
  "type": "Feature",
  "properties": {
    "gn:admin1_code":"72",
    "gn:asciiname":"Mar'inskiye Vyselki",
    "gn:country_code":"RU",
    "gn:dem":134,
    "gn:feature_class":"P",
    "gn:feature_code":"PPL",
    "gn:name":"Mar\u2019inskiye Vyselki",
    "gn:population":0,
    "gn:timezone":"Europe/Moscow",
    "iso:country":"RU",
    "name:rus_x_preferred":[
        "\u041c\u0430\u0440\u044c\u0438\u043d\u0441\u043a\u0438\u0435 \u0412\u044b\u0441\u0435\u043b\u043a\u0438"
    ],
    "name:und_x_variant":[
        "Mar\u2019inskiye Vyselki"
    ],
    "wof:name":"Mar'inskiye Vyselki",
    "wof:placetype":"locality"
},
  "geometry": {"coordinates":[41.45,52.03333],"type":"Point"}
}