{
  "type": "Feature",
  "properties": {
    "gn:admin1_code":"85",
    "gn:asciiname":"Merezha",
    "gn:country_code":"RU",
    "gn:dem":114,
    "gn:feature_class":"P",
    "gn:feature_code":"PPL",
    "gn:name":"Mer\u00ebzha",
    "gn:population":0,
    "gn:timezone":"Europe/Moscow",
    "iso:country":"RU",
    "name:eng_x_preferred":[
        "Mer\u00ebzha"
    ],
    "name:nor_x_preferred":[
        "Merezja"
    ],
    "name:rus_x_preferred":[
        "\u041c\u0435\u0440\u0435\u0436\u0430"
    ],
    "name:rus_x_variant":[
        "\u041c\u0435\u0440\u0451\u0436\u0430"
    ],
    "name:und_x_variant":[
        "Mer\u00ebzha",
        "\u041c\u0435\u0440\u0451\u0436\u0430"
    ],
    "wof:name":"Merezha",
    "wof:placetype":"locality"
},
  "geometry": {"coordinates":[36.3963,59.0286],"type":"Point"}
}