{
  "type": "Feature",
  "properties": {
    "gn:admin1_code":"69",
    "gn:asciiname":"Korshunovo",
    "gn:country_code":"RU",
    "gn:dem":201,
    "gn:feature_class":"P",
    "gn:feature_code":"PPL",
    "gn:name":"Korshunovo",
    "gn:population":0,
    "gn:timezone":"Europe/Moscow",
    "iso:country":"RU",
    "name:rus_x_preferred":[
        "\u041a\u043e\u0440\u0448\u0443\u043d\u043e\u0432\u043e"
    ],
    "wof:name":"Korshunovo",
    "wof:placetype":"locality"
},
  "geometry": {"coordinates":[32.28979,55.66824],"type":"Point"}
}