{
  "type": "Feature",
  "properties": {
    "gn:admin1_code":"8",
    "gn:asciiname":"Staryye Kandry",
    "gn:country_code":"RU",
    "gn:dem":153,
    "gn:feature_class":"P",
    "gn:feature_code":"PPL",
    "gn:name":"Staryye Kandry",
    "gn:population":0,
    "gn:timezone":"Asia/Yekaterinburg",
    "iso:country":"RU",
    "name:eng_x_preferred":[
        "Starokandry"
    ],
    "name:nor_x_preferred":[
        "Kandry"
    ],
    "name:rus_x_preferred":[
        "\u041a\u0430\u043d\u0434\u0440\u044b"
    ],
    "name:rus_x_variant":[
        "\u0421\u0442\u0430\u0440\u044b\u0435 \u041a\u0430\u043d\u0434\u0440\u044b"
    ],
    "name:und_x_variant":[
        "Staryye Kandry"
    ],
    "wof:name":"Staryye Kandry",
    "wof:placetype":"locality"
},
  "geometry": {"coordinates":[54.05,54.53333000000001],"type":"Point"}
}