{
  "type": "Feature",
  "properties": {
    "gn:admin1_code":"6",
    "gn:admin2_code":"549751",
    "gn:asciiname":"Rechka",
    "gn:country_code":"RU",
    "gn:dem":31,
    "gn:feature_class":"P",
    "gn:feature_code":"PPL",
    "gn:name":"Rechka",
    "gn:population":0,
    "gn:timezone":"Europe/Moscow",
    "iso:country":"RU",
    "name:rus_x_preferred":[
        "\u0420\u0435\u0447\u043a\u0430"
    ],
    "name:und_x_variant":[
        "\u0420\u0435\u0447\u043a\u0430"
    ],
    "wof:name":"Rechka",
    "wof:placetype":"locality"
},
  "geometry": {"coordinates":[41.56371,63.8077],"type":"Point"}
}