{
  "type": "Feature",
  "properties": {
    "gn:admin1_code":"88.0",
    "gn:asciiname":"Ivshino",
    "gn:country_code":"RU",
    "gn:dem":97,
    "gn:feature_class":"P",
    "gn:feature_code":"PPL",
    "gn:name":"Ivshino",
    "gn:population":0,
    "gn:timezone":"Europe/Moscow",
    "iso:country":"RU",
    "name:rus_x_preferred":[
        "\u0418\u0432\u0448\u0438\u043d\u043e"
    ],
    "wof:name":"Ivshino",
    "wof:placetype":"locality"
},
  "geometry": {"coordinates":[40.65318,58.0436],"type":"Point"}
}