{
  "type": "Feature",
  "properties": {
    "gn:admin1_code":"77",
    "gn:asciiname":"Yugskiy",
    "gn:country_code":"RU",
    "gn:dem":148,
    "gn:feature_class":"P",
    "gn:feature_code":"PPL",
    "gn:name":"Yugskiy",
    "gn:population":0,
    "gn:timezone":"Europe/Moscow",
    "iso:country":"RU",
    "name:rus_x_preferred":[
        "\u042e\u0433\u0441\u043a\u0438\u0439"
    ],
    "name:und_x_variant":[
        "\u042e\u0433\u0441\u043a\u0438\u0439"
    ],
    "wof:name":"Yugskiy",
    "wof:placetype":"locality"
},
  "geometry": {"coordinates":[36.1319,58.438],"type":"Point"}
}