{
  "type": "Feature",
  "properties": {
    "gn:admin1_code":"56",
    "gn:asciiname":"Khal'zevo",
    "gn:country_code":"RU",
    "gn:dem":228,
    "gn:feature_class":"P",
    "gn:feature_code":"PPL",
    "gn:name":"Khal\u2019z\u00ebvo",
    "gn:population":0,
    "gn:timezone":"Europe/Moscow",
    "iso:country":"RU",
    "name:eng_x_preferred":[
        "Khal'z\u00ebvo"
    ],
    "name:nor_x_preferred":[
        "Khalzevo"
    ],
    "name:rus_x_preferred":[
        "\u0425\u0430\u043b\u044c\u0437\u0435\u0432\u043e"
    ],
    "name:rus_x_variant":[
        "\u0425\u0430\u043b\u044c\u0437\u0451\u0432\u043e"
    ],
    "name:und_x_variant":[
        "Khal\u2019yeyeva",
        "Khal\u2019zeyeva",
        "Khal\u2019z\u00ebvo",
        "\u0425\u0430\u043b\u044c\u0437\u0451\u0432\u043e"
    ],
    "wof:name":"Khal'zevo",
    "wof:placetype":"locality"
},
  "geometry": {"coordinates":[35.3939,52.4558],"type":"Point"}
}