{
  "type": "Feature",
  "properties": {
    "gn:admin1_code":"43.0",
    "gn:asciiname":"Cherkassy",
    "gn:country_code":"RU",
    "gn:dem":118,
    "gn:feature_class":"P",
    "gn:feature_code":"PPL",
    "gn:name":"Cherkassy",
    "gn:population":0,
    "gn:timezone":"Europe/Moscow",
    "iso:country":"RU",
    "name:eng_x_preferred":[
        "Cherkassy"
    ],
    "name:nor_x_preferred":[
        "Tsjerkassy"
    ],
    "name:rus_x_preferred":[
        "\u0427\u0435\u0440\u043a\u0430\u0441\u0441\u044b"
    ],
    "name:und_x_variant":[
        "Cherkasy"
    ],
    "wof:name":"Cherkassy",
    "wof:placetype":"locality"
},
  "geometry": {"coordinates":[38.72615,52.69593],"type":"Point"}
}