{
  "type": "Feature",
  "properties": {
    "gn:admin1_code":"52",
    "gn:asciiname":"Utushkino",
    "gn:country_code":"RU",
    "gn:dem":32,
    "gn:feature_class":"P",
    "gn:feature_code":"PPL",
    "gn:name":"Utushkino",
    "gn:population":0,
    "gn:timezone":"Europe/Moscow",
    "iso:country":"RU",
    "name:eng_x_preferred":[
        "Utushkino"
    ],
    "name:nor_x_preferred":[
        "Utusjkino"
    ],
    "name:rus_x_preferred":[
        "\u0423\u0442\u0443\u0448\u043a\u0438\u043d\u043e"
    ],
    "name:und_x_variant":[
        "Utoshkino",
        "Utushkino",
        "\u0423\u0442\u0443\u0448\u043a\u0438\u043d\u043e"
    ],
    "wof:name":"Utushkino",
    "wof:placetype":"locality"
},
  "geometry": {"coordinates":[31.2885,57.9146],"type":"Point"}
}