{
  "type": "Feature",
  "properties": {
    "gn:admin1_code":"33.0",
    "gn:asciiname":"Malyye Skurikhiny",
    "gn:country_code":"RU",
    "gn:dem":110,
    "gn:feature_class":"P",
    "gn:feature_code":"PPL",
    "gn:name":"Malyye Skurikhiny",
    "gn:population":0,
    "gn:timezone":"Europe/Kirov",
    "iso:country":"RU",
    "name:rus_x_preferred":[
        "\u041c\u0430\u043b\u044b\u0435 \u0421\u043a\u0443\u0440\u0438\u0445\u0438\u043d\u044b"
    ],
    "name:und_x_variant":[
        "\u041c\u0430\u043b\u044b\u0435 \u0421\u043a\u0443\u0440\u0438\u0445\u0438\u043d\u044b"
    ],
    "wof:name":"Malyye Skurikhiny",
    "wof:placetype":"locality"
},
  "geometry": {"coordinates":[48.6039,58.55277],"type":"Point"}
}