{
  "type": "Feature",
  "properties": {
    "gn:admin1_code":"56",
    "gn:asciiname":"Uspenskiy",
    "gn:country_code":"RU",
    "gn:dem":255,
    "gn:feature_class":"P",
    "gn:feature_code":"PPL",
    "gn:name":"Uspenskiy",
    "gn:population":0,
    "gn:timezone":"Europe/Moscow",
    "iso:country":"RU",
    "name:rus_x_preferred":[
        "\u0423\u0441\u043f\u0435\u043d\u0441\u043a\u0438\u0439"
    ],
    "wof:name":"Uspenskiy",
    "wof:placetype":"locality"
},
  "geometry": {"coordinates":[35.3563,52.4669],"type":"Point"}
}