{
  "type": "Feature",
  "properties": {
    "gn:admin1_code":"29",
    "gn:asciiname":"Gladkovka",
    "gn:cc2":"RU",
    "gn:country_code":"RU",
    "gn:dem":218,
    "gn:feature_class":"P",
    "gn:feature_code":"PPL",
    "gn:name":"Gladkovka",
    "gn:population":0,
    "gn:timezone":"Asia/Novokuznetsk",
    "iso:country":"RU",
    "name:eng_x_preferred":[
        "Gladkovka"
    ],
    "name:nor_x_preferred":[
        "Gladkova"
    ],
    "name:rus_x_preferred":[
        "\u0413\u043b\u0430\u0434\u043a\u043e\u0432\u0430"
    ],
    "name:rus_x_variant":[
        "\u0413\u043b\u0430\u0434\u043a\u043e\u0432\u043a\u0430"
    ],
    "name:und_x_variant":[
        "Gladkovskaya",
        "Gladkova",
        "Gladkovka",
        "\u0413\u043b\u0430\u0434\u043a\u043e\u0432\u043a\u0430"
    ],
    "wof:name":"Gladkovka",
    "wof:placetype":"locality"
},
  "geometry": {"coordinates":[87.16667,54.51667],"type":"Point"}
}