{
  "type": "Feature",
  "properties": {
    "gn:admin1_code":"77",
    "gn:asciiname":"Bashkino",
    "gn:country_code":"RU",
    "gn:dem":158,
    "gn:feature_class":"P",
    "gn:feature_code":"PPL",
    "gn:name":"Bashkino",
    "gn:population":0,
    "gn:timezone":"Europe/Moscow",
    "iso:country":"RU",
    "name:rus_x_preferred":[
        "\u0411\u0430\u0448\u043a\u0438\u043d\u043e"
    ],
    "wof:name":"Bashkino",
    "wof:placetype":"locality"
},
  "geometry": {"coordinates":[37.3388,58.4325],"type":"Point"}
}