{
  "type": "Feature",
  "properties": {
    "gn:admin1_code":"46",
    "gn:asciiname":"Gavayevo",
    "gn:country_code":"RU",
    "gn:dem":213,
    "gn:feature_class":"P",
    "gn:feature_code":"PPL",
    "gn:name":"Gavayevo",
    "gn:population":0,
    "gn:timezone":"Europe/Moscow",
    "iso:country":"RU",
    "name:rus_x_preferred":[
        "\u0413\u0430\u0432\u0430\u0435\u0432\u043e"
    ],
    "wof:name":"Gavayevo",
    "wof:placetype":"locality"
},
  "geometry": {"coordinates":[45.6649,54.6184],"type":"Point"}
}