{
  "type": "Feature",
  "properties": {
    "gn:admin1_code":"23",
    "gn:asciiname":"Zaytsevo",
    "gn:country_code":"RU",
    "gn:dem":37,
    "gn:feature_class":"P",
    "gn:feature_code":"PPL",
    "gn:name":"Zaytsevo",
    "gn:population":0,
    "gn:timezone":"Europe/Kaliningrad",
    "iso:country":"RU",
    "name:deu_x_historical":[
        "Stockheim"
    ],
    "name:deu_x_preferred":[
        "Stockheim"
    ],
    "wof:name":"Zaytsevo",
    "wof:placetype":"locality"
},
  "geometry": {"coordinates":[20.87695,54.47451],"type":"Point"}
}