{
  "type": "Feature",
  "properties": {
    "gn:admin1_code":"45.0",
    "gn:asciiname":"Karabayevo",
    "gn:country_code":"RU",
    "gn:dem":168,
    "gn:feature_class":"P",
    "gn:feature_code":"PPL",
    "gn:name":"Karabayevo",
    "gn:population":0,
    "gn:timezone":"Europe/Moscow",
    "iso:country":"RU",
    "name:bak_x_preferred":[
        "\u04a0\u0430\u0440\u0430\u0431\u0430\u0439"
    ],
    "name:che_x_preferred":[
        "\u041a\u0430\u0440\u0430\u0431\u0430\u0435\u0432\u043e"
    ],
    "name:hye_x_preferred":[
        "\u053f\u0561\u0580\u0561\u0562\u0561\u0587\u0578"
    ],
    "name:kaz_x_preferred":[
        "\u041a\u0430\u0440\u0430\u0431\u0430"
    ],
    "name:kir_x_preferred":[
        "\u041a\u0430\u0440\u0430\u0431\u0430"
    ],
    "name:rus_x_preferred":[
        "\u041a\u0430\u0440\u0430\u0431\u0430\u0435\u0432\u043e"
    ],
    "name:tat_x_preferred":[
        "\u041a\u0430\u0440\u0430\u0431\u0430\u0439"
    ],
    "wof:name":"Karabayevo",
    "wof:placetype":"locality"
},
  "geometry": {"coordinates":[48.82889,56.76028],"type":"Point"}
}