{
  "type": "Feature",
  "properties": {
    "gn:admin1_code":"60",
    "gn:asciiname":"Dul'by",
    "gn:country_code":"RU",
    "gn:dem":66,
    "gn:feature_class":"P",
    "gn:feature_code":"PPL",
    "gn:name":"Dul\u2019by",
    "gn:population":0,
    "gn:timezone":"Europe/Moscow",
    "iso:country":"RU",
    "name:rus_x_preferred":[
        "\u0414\u0443\u043b\u044c\u0431\u044b"
    ],
    "name:und_x_variant":[
        "Dul\u2019by"
    ],
    "wof:name":"Dul'by",
    "wof:placetype":"locality"
},
  "geometry": {"coordinates":[28.02031,57.21279000000001],"type":"Point"}
}