{
  "type": "Feature",
  "properties": {
    "gn:admin1_code":"90",
    "gn:asciiname":"Saya",
    "gn:country_code":"RU",
    "gn:dem":184,
    "gn:feature_class":"P",
    "gn:feature_code":"PPL",
    "gn:name":"Saya",
    "gn:population":0,
    "gn:timezone":"Asia/Yekaterinburg",
    "iso:country":"RU",
    "name:rus_x_preferred":[
        "\u0421\u0430\u044f"
    ],
    "name:und_x_variant":[
        "\u0421\u0430\u044f"
    ],
    "wof:name":"Saya",
    "wof:placetype":"locality"
},
  "geometry": {"coordinates":[57.6662,57.7353],"type":"Point"}
}