{
  "type": "Feature",
  "properties": {
    "gn:admin1_code":"16.0",
    "gn:asciiname":"Burunduki",
    "gn:country_code":"RU",
    "gn:dem":144,
    "gn:feature_class":"P",
    "gn:feature_code":"PPL",
    "gn:name":"Burunduki",
    "gn:population":0,
    "gn:timezone":"Europe/Moscow",
    "iso:country":"RU",
    "name:rus_x_preferred":[
        "\u0411\u0443\u0440\u0443\u043d\u0434\u0443\u043a\u0438"
    ],
    "wof:name":"Burunduki",
    "wof:placetype":"locality"
},
  "geometry": {"coordinates":[46.98242,55.80889000000001],"type":"Point"}
}