{
  "type": "Feature",
  "properties": {
    "gn:admin1_code":"60",
    "gn:asciiname":"Ovchino Maloye",
    "gn:country_code":"RU",
    "gn:dem":179,
    "gn:feature_class":"P",
    "gn:feature_code":"PPL",
    "gn:name":"Ovchino Maloye",
    "gn:population":0,
    "gn:timezone":"Europe/Moscow",
    "iso:country":"RU",
    "name:rus_x_preferred":[
        "\u041e\u0432\u0447\u0438\u043d\u043e \u041c\u0430\u043b\u043e\u0435"
    ],
    "name:und_x_variant":[
        "Maloye Ovchino",
        "Ovchino Maloye"
    ],
    "wof:name":"Ovchino Maloye",
    "wof:placetype":"locality"
},
  "geometry": {"coordinates":[29.65524000000001,56.06601],"type":"Point"}
}