{
  "type": "Feature",
  "properties": {
    "gn:admin1_code":"86",
    "gn:asciiname":"Kolovatovka",
    "gn:country_code":"RU",
    "gn:dem":90,
    "gn:feature_class":"P",
    "gn:feature_code":"PPL",
    "gn:name":"Kolovatovka",
    "gn:population":0,
    "gn:timezone":"Europe/Moscow",
    "iso:country":"RU",
    "name:rus_x_preferred":[
        "\u041a\u043e\u043b\u043e\u0432\u0430\u0442\u043e\u0432\u043a\u0430"
    ],
    "wof:name":"Kolovatovka",
    "wof:placetype":"locality"
},
  "geometry": {"coordinates":[38.886,50.7486],"type":"Point"}
}