{
  "type": "Feature",
  "properties": {
    "gn:admin1_code":"80.0",
    "gn:asciiname":"Pirekovo",
    "gn:country_code":"RU",
    "gn:dem":200,
    "gn:feature_class":"P",
    "gn:feature_code":"PPL",
    "gn:name":"Pirekovo",
    "gn:population":0,
    "gn:timezone":"Europe/Samara",
    "iso:country":"RU",
    "name:rus_x_preferred":[
        "\u041f\u0438\u0440\u0435\u043a\u043e\u0432\u043e"
    ],
    "wof:name":"Pirekovo",
    "wof:placetype":"locality"
},
  "geometry": {"coordinates":[52.7651,57.8859],"type":"Point"}
}