{
  "type": "Feature",
  "properties": {
    "gn:admin1_code":"75",
    "gn:asciiname":"Chernyshevka",
    "gn:country_code":"RU",
    "gn:dem":129,
    "gn:feature_class":"P",
    "gn:feature_code":"PPL",
    "gn:name":"Chernyshevka",
    "gn:population":0,
    "gn:timezone":"Asia/Tomsk",
    "iso:country":"RU",
    "name:eng_x_preferred":[
        "Chernyshevskiy"
    ],
    "name:rus_x_preferred":[
        "\u0427\u0435\u0440\u043d\u044b\u0448\u0435\u0432\u043a\u0430"
    ],
    "name:rus_x_variant":[
        "\u0427\u0435\u0440\u043d\u044b\u0448\u0435\u0432\u043aa"
    ],
    "name:und_x_variant":[
        "Chernyshevskiy",
        "Chernyshevka",
        "\u0427\u0435\u0440\u043d\u044b\u0448\u0435\u0432\u043aa"
    ],
    "wof:name":"Chernyshevka",
    "wof:placetype":"locality"
},
  "geometry": {"coordinates":[84.35694000000002,56.53972],"type":"Point"}
}