{
  "type": "Feature",
  "properties": {
    "gn:admin1_code":"12",
    "gn:asciiname":"Malyye Shuani",
    "gn:country_code":"RU",
    "gn:dem":545,
    "gn:feature_class":"P",
    "gn:feature_code":"PPL",
    "gn:name":"Malyye Shuani",
    "gn:population":0,
    "gn:timezone":"Europe/Moscow",
    "iso:country":"RU",
    "name:che_x_preferred":[
        "\u00c7ari-Moxk"
    ],
    "name:che_x_variant":[
        "Malaya \u015eagada",
        "\u00c7arayn-Moxk",
        "Ther\u00e7a-\u015e\u00f6na",
        "\u0422\u0406\u0435\u0440\u0447\u0430-\u0428\u043e\u044c\u043d\u0430",
        "\u0427\u0430\u0440\u0430\u0439\u043d-\u041c\u043e\u0445\u043a",
        "\u041c\u0430\u043b\u0430\u044f \u0428\u0430\u0433\u0430\u0434\u0430",
        "\u0427\u0430\u0440\u0438-\u041c\u043e\u0445\u043a"
    ],
    "name:rus_x_preferred":[
        "\u041c\u0430\u043b\u044b\u0435 \u0428\u0443\u0430\u043d\u0438"
    ],
    "name:rus_x_variant":[
        "Malye \u0160uani"
    ],
    "name:und_x_variant":[
        "Chari-Mokhk",
        "Malaya Shagada",
        "Malyye Shuany",
        "Malyye Shuani"
    ],
    "wof:name":"Malyye Shuani",
    "wof:placetype":"locality"
},
  "geometry": {"coordinates":[46.22142,43.07882],"type":"Point"}
}