{
  "type": "Feature",
  "properties": {
    "gn:admin1_code":"85",
    "gn:asciiname":"Kozhevnikovo",
    "gn:country_code":"RU",
    "gn:dem":208,
    "gn:feature_class":"P",
    "gn:feature_code":"PPL",
    "gn:name":"Kozhevnikovo",
    "gn:population":0,
    "gn:timezone":"Europe/Moscow",
    "iso:country":"RU",
    "name:rus_x_preferred":[
        "\u041a\u043e\u0436\u0435\u0432\u0438\u043a\u043e\u0432\u043e"
    ],
    "wof:name":"Kozhevnikovo",
    "wof:placetype":"locality"
},
  "geometry": {"coordinates":[38.99788,59.10475],"type":"Point"}
}