{
  "type": "Feature",
  "properties": {
    "gn:country":"RU",
    "gn:fcode":"PPL",
    "gn:pop":0,
    "iso:country":"RU",
    "name:rus_x_preferred":[
        "\u041e\u0441\u0435\u0447\u0435\u043d\u043a\u0438"
    ],
    "name:unk_x_variant":[
        "\u041e\u0441\u0435\u0447\u0435\u043d\u043a\u0438"
    ],
    "qs:name":"Osechenki",
    "qs:name_adm0":"Russia",
    "qs:name_adm1":"Moscow Oblast",
    "qs:photos_9r":0,
    "qs:photos_sr":0,
    "qs:placetype":"Town",
    "qs:pop_sr":"0",
    "wof:name":"Osechenki",
    "wof:placetype":"locality",
    "wof:population":0
},
  "geometry": {"coordinates":[38.1317,55.65723],"type":"Point"}
}