{
  "type": "Feature",
  "properties": {
    "gn:admin1_code":"54",
    "gn:asciiname":"Bol'she-Mogil'noye",
    "gn:country_code":"RU",
    "gn:dem":117,
    "gn:feature_class":"P",
    "gn:feature_code":"PPL",
    "gn:name":"Bol\u2019she-Mogil\u2019noye",
    "gn:population":0,
    "gn:timezone":"Asia/Omsk",
    "iso:country":"RU",
    "name:eng_x_preferred":[
        "Bol'she-Mogil'noye"
    ],
    "name:nor_x_preferred":[
        "Bolsjemogilnoje"
    ],
    "name:rus_x_preferred":[
        "\u0411\u043e\u043b\u044c\u0448\u0435\u043c\u043e\u0433\u0438\u043b\u044c\u043d\u043e\u0435"
    ],
    "name:und_x_variant":[
        "Mogil\u2019noye",
        "Bol\u2019shoye Mogil\u2019skoye",
        "Bol\u2019she-Mogil\u2019noye",
        "\u0411\u043e\u043b\u044c\u0448\u0435\u043c\u043e\u0433\u0438\u043b\u044c\u043d\u043e\u0435"
    ],
    "wof:name":"Bol'she-Mogil'noye",
    "wof:placetype":"locality"
},
  "geometry": {"coordinates":[72.62161,55.39826],"type":"Point"}
}