{
  "type": "Feature",
  "properties": {
    "gn:admin1_code":"93",
    "gn:asciiname":"Yavlenka",
    "gn:country_code":"RU",
    "gn:dem":606,
    "gn:feature_class":"P",
    "gn:feature_code":"PPL",
    "gn:name":"Yavlenka",
    "gn:population":0,
    "gn:timezone":"Asia/Chita",
    "iso:country":"RU",
    "name:eng_x_preferred":[
        "Yavlenka"
    ],
    "name:nor_x_preferred":[
        "Javlenka"
    ],
    "name:rus_x_preferred":[
        "\u042f\u0432\u043b\u0435\u043d\u043a\u0430"
    ],
    "name:und_x_variant":[
        "Yavlensk",
        "Yavlenka"
    ],
    "wof:name":"Yavlenka",
    "wof:placetype":"locality"
},
  "geometry": {"coordinates":[119.08204000000001,51.03695],"type":"Point"}
}