{
  "type": "Feature",
  "properties": {
    "gn:admin1_code":"22",
    "gn:asciiname":"Verkhniy Chegem",
    "gn:country_code":"RU",
    "gn:dem":1612,
    "gn:feature_class":"P",
    "gn:feature_code":"PPL",
    "gn:name":"Verkhniy Chegem",
    "gn:population":0,
    "gn:timezone":"Europe/Moscow",
    "iso:country":"RU",
    "name:eng_x_preferred":[
        "Verkhniy Chegem"
    ],
    "name:nor_x_preferred":[
        "Verkhnij Tsjegem"
    ],
    "name:rus_x_preferred":[
        "\u0412\u0435\u0440\u0445\u043d\u0438\u0439 \u0427\u0435\u0433\u0435\u043c"
    ],
    "name:und_x_variant":[
        "Bulungu"
    ],
    "wof:name":"Verkhniy Chegem",
    "wof:placetype":"locality"
},
  "geometry": {"coordinates":[43.13231,43.24034],"type":"Point"}
}