{
  "type": "Feature",
  "properties": {
    "gn:admin1_code":"60",
    "gn:asciiname":"Kor'khovo",
    "gn:country_code":"RU",
    "gn:dem":75,
    "gn:feature_class":"P",
    "gn:feature_code":"PPL",
    "gn:name":"Kor\u2019khovo",
    "gn:population":0,
    "gn:timezone":"Europe/Moscow",
    "iso:country":"RU",
    "name:eng_x_preferred":[
        "Kor'khovo"
    ],
    "name:nor_x_preferred":[
        "Korkhovo"
    ],
    "name:rus_x_preferred":[
        "\u041a\u043e\u0440\u044c\u0445\u043e\u0432\u043e"
    ],
    "name:und_x_variant":[
        "Novaya Kar\u2019khova",
        "Kor\u2019khovo"
    ],
    "wof:name":"Kor'khovo",
    "wof:placetype":"locality"
},
  "geometry": {"coordinates":[30.14286,57.79208000000001],"type":"Point"}
}