{
  "type": "Feature",
  "properties": {
    "gn:admin1_code":"60",
    "gn:asciiname":"Zaslyuzh'ye",
    "gn:country_code":"RU",
    "gn:dem":78,
    "gn:feature_class":"P",
    "gn:feature_code":"PPL",
    "gn:name":"Zaslyuzh\u2019ye",
    "gn:population":0,
    "gn:timezone":"Europe/Moscow",
    "iso:country":"RU",
    "name:rus_x_preferred":[
        "\u0417\u0430\u0441\u043b\u044e\u0436\u044c\u0435"
    ],
    "name:und_x_variant":[
        "Zaslyuzh\u2019ye"
    ],
    "wof:name":"Zaslyuzh'ye",
    "wof:placetype":"locality"
},
  "geometry": {"coordinates":[28.69586,57.27345],"type":"Point"}
}