{
  "type": "Feature",
  "properties": {
    "gn:admin1_code":"51",
    "gn:asciiname":"Karga",
    "gn:country_code":"RU",
    "gn:dem":112,
    "gn:feature_class":"P",
    "gn:feature_code":"PPL",
    "gn:name":"Karga",
    "gn:population":0,
    "gn:timezone":"Europe/Moscow",
    "iso:country":"RU",
    "name:rus_x_preferred":[
        "\u041a\u0430\u0440\u0433\u0430"
    ],
    "name:und_x_variant":[
        "\u041a\u0430\u0440\u0433\u0430"
    ],
    "wof:name":"Karga",
    "wof:placetype":"locality"
},
  "geometry": {"coordinates":[45.41454,55.41435],"type":"Point"}
}