{
  "type": "Feature",
  "properties": {
    "gn:admin1_code":"6",
    "gn:asciiname":"Romanovo",
    "gn:cc2":"RU",
    "gn:country_code":"RU",
    "gn:dem":71,
    "gn:feature_class":"P",
    "gn:feature_code":"PPL",
    "gn:name":"Romanovo",
    "gn:population":0,
    "gn:timezone":"Europe/Moscow",
    "iso:country":"RU",
    "name:rus_x_preferred":[
        "\u0420\u043e\u043c\u0430\u043d\u043e\u0432\u043e"
    ],
    "name:und_x_variant":[
        "Sloboda Romanovo",
        "Romanovo"
    ],
    "wof:name":"Romanovo",
    "wof:placetype":"locality"
},
  "geometry": {"coordinates":[46.46667,61.03333000000001],"type":"Point"}
}