{
  "type": "Feature",
  "properties": {
    "gn:admin1_code":"37",
    "gn:asciiname":"Samet'",
    "gn:country_code":"RU",
    "gn:dem":86,
    "gn:feature_class":"P",
    "gn:feature_code":"PPL",
    "gn:name":"Samet\u2019",
    "gn:population":0,
    "gn:timezone":"Europe/Moscow",
    "iso:country":"RU",
    "name:eng_x_preferred":[
        "Samet'"
    ],
    "name:nor_x_preferred":[
        "Samet"
    ],
    "name:rus_x_preferred":[
        "\u0421\u0430\u043c\u0435\u0442\u044c"
    ],
    "name:und_x_variant":[
        "Samet\u2019"
    ],
    "wof:name":"Samet'",
    "wof:placetype":"locality"
},
  "geometry": {"coordinates":[40.7259,57.8061],"type":"Point"}
}