{
  "type": "Feature",
  "properties": {
    "gn:admin1_code":"33",
    "gn:asciiname":"Gorbunovo",
    "gn:country_code":"RU",
    "gn:dem":118,
    "gn:feature_class":"P",
    "gn:feature_code":"PPL",
    "gn:name":"Gorbunovo",
    "gn:population":0,
    "gn:timezone":"Europe/Kirov",
    "iso:country":"RU",
    "name:rus_x_preferred":[
        "\u0413\u043e\u0440\u0431\u0443\u043d\u043e\u0432\u043e"
    ],
    "wof:name":"Gorbunovo",
    "wof:placetype":"locality"
},
  "geometry": {"coordinates":[50.2674,57.9318],"type":"Point"}
}