{
  "type": "Feature",
  "properties": {
    "gn:admin1_code":"11",
    "gn:asciiname":"Karmadun",
    "gn:cc2":"RU",
    "gn:country_code":"RU",
    "gn:dem":508,
    "gn:feature_class":"P",
    "gn:feature_code":"PPL",
    "gn:name":"Karmadun",
    "gn:population":0,
    "gn:timezone":"Asia/Irkutsk",
    "iso:country":"RU",
    "name:rus_x_preferred":[
        "\u041a\u0430\u0440\u043c\u0430\u0434\u0443\u043d"
    ],
    "name:und_x_variant":[
        "Zimovoye Karmadun",
        "Karmadun"
    ],
    "wof:name":"Karmadun",
    "wof:placetype":"locality"
},
  "geometry": {"coordinates":[110.51667,54.15],"type":"Point"}
}