{
  "type": "Feature",
  "properties": {
    "gn:admin1_code":"76",
    "gn:asciiname":"Staraya V'yevka",
    "gn:country_code":"RU",
    "gn:dem":180,
    "gn:feature_class":"P",
    "gn:feature_code":"PPL",
    "gn:name":"Staraya V\u2019y\u00ebvka",
    "gn:population":0,
    "gn:timezone":"Europe/Moscow",
    "iso:country":"RU",
    "wof:name":"Staraya V'yevka",
    "wof:placetype":"locality"
},
  "geometry": {"coordinates":[37.80544,54.09636],"type":"Point"}
}