{
  "type": "Feature",
  "properties": {
    "gn:admin1_code":"33",
    "gn:asciiname":"Zykintsy",
    "gn:country_code":"RU",
    "gn:dem":203,
    "gn:feature_class":"P",
    "gn:feature_code":"PPL",
    "gn:name":"Zykintsy",
    "gn:population":0,
    "gn:timezone":"Europe/Kirov",
    "iso:country":"RU",
    "wof:name":"Zykintsy",
    "wof:placetype":"locality"
},
  "geometry": {"coordinates":[50.48333,58.15],"type":"Point"}
}