{
  "type": "Feature",
  "properties": {
    "gn:admin1_code":"05",
    "gn:asciiname":"Ayak",
    "gn:country_code":"RU",
    "gn:dem":200,
    "gn:feature_class":"P",
    "gn:feature_code":"PPL",
    "gn:name":"Ayak",
    "gn:population":0,
    "gn:timezone":"Asia/Yakutsk",
    "iso:country":"RU",
    "name:nor_x_preferred":[
        "Ajak"
    ],
    "name:rus_x_preferred":[
        "\u0410\u044f\u043a"
    ],
    "wof:name":"Ayak",
    "wof:placetype":"locality"
},
  "geometry": {"coordinates":[127.78051000000001,52.79991999999999],"type":"Point"}
}