{
  "type": "Feature",
  "properties": {
    "gn:admin1_code":"69",
    "gn:asciiname":"Nadva",
    "gn:country_code":"RU",
    "gn:dem":211,
    "gn:feature_class":"P",
    "gn:feature_code":"PPL",
    "gn:name":"Nadva",
    "gn:population":0,
    "gn:timezone":"Europe/Moscow",
    "iso:country":"RU",
    "name:rus_x_preferred":[
        "\u041d\u0430\u0434\u0432\u0430"
    ],
    "name:und_x_variant":[
        "\u041d\u0430\u0434\u0432\u0430"
    ],
    "wof:name":"Nadva",
    "wof:placetype":"locality"
},
  "geometry": {"coordinates":[31.49135,54.83909],"type":"Point"}
}