{
  "type": "Feature",
  "properties": {
    "gn:admin1_code":"38",
    "gn:asciiname":"Magri",
    "gn:country_code":"RU",
    "gn:dem":44,
    "gn:feature_class":"P",
    "gn:feature_code":"PPL",
    "gn:name":"Magri",
    "gn:population":0,
    "gn:timezone":"Europe/Moscow",
    "iso:country":"RU",
    "name:rus_x_preferred":[
        "\u041c\u0430\u0433\u0440\u0438"
    ],
    "name:und_x_variant":[
        "\u041c\u0430\u0433\u0440\u0438"
    ],
    "wof:name":"Magri",
    "wof:placetype":"locality"
},
  "geometry": {"coordinates":[39.1627,44.0187],"type":"Point"}
}