{
  "type": "Feature",
  "properties": {
    "gn:admin1_code":"77",
    "gn:asciiname":"Milyatino",
    "gn:country_code":"RU",
    "gn:dem":193,
    "gn:feature_class":"P",
    "gn:feature_code":"PPL",
    "gn:name":"Milyatino",
    "gn:population":0,
    "gn:timezone":"Europe/Moscow",
    "iso:country":"RU",
    "name:rus_x_preferred":[
        "\u041c\u0438\u043b\u044f\u0442\u0438\u043d\u043e"
    ],
    "wof:name":"Milyatino",
    "wof:placetype":"locality"
},
  "geometry": {"coordinates":[31.66667,56.08333],"type":"Point"}
}