{
  "type": "Feature",
  "properties": {
    "gn:admin1_code":"77",
    "gn:asciiname":"Merluga",
    "gn:country_code":"RU",
    "gn:dem":155,
    "gn:feature_class":"P",
    "gn:feature_code":"PPL",
    "gn:name":"Merluga",
    "gn:population":0,
    "gn:timezone":"Europe/Moscow",
    "iso:country":"RU",
    "name:rus_x_preferred":[
        "\u041c\u0435\u0440\u043b\u0443\u0433\u0430"
    ],
    "name:und_x_variant":[
        "\u041c\u0435\u0440\u043b\u0443\u0433\u0430"
    ],
    "wof:name":"Merluga",
    "wof:placetype":"locality"
},
  "geometry": {"coordinates":[36.3757,57.33],"type":"Point"}
}