{
  "type": "Feature",
  "properties": {
    "gn:admin1_code":"73",
    "gn:asciiname":"Zubairovo",
    "gn:country_code":"RU",
    "gn:dem":80,
    "gn:feature_class":"P",
    "gn:feature_code":"PPL",
    "gn:name":"Zubairovo",
    "gn:population":0,
    "gn:timezone":"Europe/Moscow",
    "iso:country":"RU",
    "name:eng_x_preferred":[
        "Zubairovo"
    ],
    "name:nor_x_preferred":[
        "Zubairovo"
    ],
    "name:rus_x_preferred":[
        "\u0417\u0443\u0431\u0430\u0438\u0440\u043e\u0432\u043e"
    ],
    "name:und_x_variant":[
        "Zyubairovo",
        "Zyubayrovo"
    ],
    "wof:name":"Zubairovo",
    "wof:placetype":"locality"
},
  "geometry": {"coordinates":[53.55781999999999,55.57697],"type":"Point"}
}