{
  "type": "Feature",
  "properties": {
    "gn:admin1_code":"52",
    "gn:asciiname":"Zhestyanaya Gorka",
    "gn:country_code":"RU",
    "gn:dem":53,
    "gn:feature_class":"P",
    "gn:feature_code":"PPL",
    "gn:name":"Zhestyanaya Gorka",
    "gn:population":0,
    "gn:timezone":"Europe/Moscow",
    "iso:country":"RU",
    "wof:name":"Zhestyanaya Gorka",
    "wof:placetype":"locality"
},
  "geometry": {"coordinates":[30.77074,58.64386],"type":"Point"}
}