{
  "type": "Feature",
  "properties": {
    "gn:admin1_code":"76",
    "gn:asciiname":"Kozhanka",
    "gn:country_code":"RU",
    "gn:dem":256,
    "gn:feature_class":"P",
    "gn:feature_code":"PPL",
    "gn:name":"Kozhanka",
    "gn:population":0,
    "gn:timezone":"Europe/Moscow",
    "iso:country":"RU",
    "name:eng_x_preferred":[
        "Kozhanka"
    ],
    "name:nor_x_preferred":[
        "Kozjenka"
    ],
    "name:rus_x_preferred":[
        "\u041a\u043e\u0436\u0435\u043d\u043a\u0430"
    ],
    "name:rus_x_variant":[
        "\u041a\u043e\u0436\u0430\u043d\u043a\u0430"
    ],
    "name:ukr_x_preferred":[
        "\u041a\u043e\u0436\u0430\u043d\u043a\u0430"
    ],
    "name:und_x_variant":[
        "Kozhinka",
        "Kozhenka"
    ],
    "wof:name":"Kozhanka",
    "wof:placetype":"locality"
},
  "geometry": {"coordinates":[36.9945,53.39578],"type":"Point"}
}