{
  "type": "Feature",
  "properties": {
    "gn:admin1_code":"90.0",
    "gn:asciiname":"Zakamennaya",
    "gn:country_code":"RU",
    "gn:dem":147,
    "gn:feature_class":"P",
    "gn:feature_code":"PPL",
    "gn:name":"Zakamennaya",
    "gn:population":0,
    "gn:timezone":"Asia/Yekaterinburg",
    "iso:country":"RU",
    "name:rus_x_preferred":[
        "\u0417\u0430\u043a\u0430\u043c\u0435\u043d\u043d\u0430\u044f"
    ],
    "wof:name":"Zakamennaya",
    "wof:placetype":"locality"
},
  "geometry": {"coordinates":[56.8944,59.1116],"type":"Point"}
}