{
  "type": "Feature",
  "properties": {
    "gn:admin1_code":"52",
    "gn:asciiname":"Gubino",
    "gn:country_code":"RU",
    "gn:dem":70,
    "gn:feature_class":"P",
    "gn:feature_code":"PPL",
    "gn:name":"Gubino",
    "gn:population":0,
    "gn:timezone":"Europe/Moscow",
    "iso:country":"RU",
    "name:rus_x_preferred":[
        "\u0413\u0443\u0431\u0438\u043d\u043e"
    ],
    "wof:name":"Gubino",
    "wof:placetype":"locality"
},
  "geometry": {"coordinates":[31.37584,57.36261999999999],"type":"Point"}
}