{
  "type": "Feature",
  "properties": {
    "gn:admin1_code":"37.0",
    "gn:asciiname":"Barintsevo",
    "gn:country_code":"RU",
    "gn:dem":146,
    "gn:feature_class":"P",
    "gn:feature_code":"PPL",
    "gn:name":"Barintsevo",
    "gn:population":0,
    "gn:timezone":"Europe/Moscow",
    "iso:country":"RU",
    "name:nor_x_preferred":[
        "Barintsevo"
    ],
    "name:rus_x_preferred":[
        "\u0411\u0430\u0440\u0438\u043d\u0446\u0435\u0432\u043e"
    ],
    "name:und_x_variant":[
        "Barintseva",
        "Barintsevo"
    ],
    "wof:name":"Barintsevo",
    "wof:placetype":"locality"
},
  "geometry": {"coordinates":[41.45172,57.63797],"type":"Point"}
}