{
  "type": "Feature",
  "properties": {
    "gn:admin1_code":"33.0",
    "gn:asciiname":"Borovkovo",
    "gn:country_code":"RU",
    "gn:dem":140,
    "gn:feature_class":"P",
    "gn:feature_code":"PPL",
    "gn:name":"Borovkovo",
    "gn:population":0,
    "gn:timezone":"Europe/Kirov",
    "iso:country":"RU",
    "name:eng_x_preferred":[
        "Borovkovo"
    ],
    "name:nor_x_preferred":[
        "Borovkovo"
    ],
    "name:rus_x_preferred":[
        "\u0411\u043e\u0440\u043e\u0432\u043a\u043e\u0432\u043e"
    ],
    "name:und_x_variant":[
        "\u0411\u043e\u0440\u043e\u0432\u043a\u043e\u0432\u043e",
        "Borovkovo"
    ],
    "wof:name":"Borovkovo",
    "wof:placetype":"locality"
},
  "geometry": {"coordinates":[49.32916,57.4218],"type":"Point"}
}