{
  "type": "Feature",
  "properties": {
    "gn:admin1_code":"34.0",
    "gn:asciiname":"Ydzhid-Yag",
    "gn:country_code":"RU",
    "gn:dem":140,
    "gn:feature_class":"P",
    "gn:feature_code":"PPL",
    "gn:name":"Ydzhid-Yag",
    "gn:population":0,
    "gn:timezone":"Europe/Moscow",
    "iso:country":"RU",
    "name:rus_x_preferred":[
        "\u042b\u0434\u0436\u0438\u0434-\u042f\u0433"
    ],
    "wof:name":"Ydzhid-Yag",
    "wof:placetype":"locality"
},
  "geometry": {"coordinates":[52.76288,63.33808000000001],"type":"Point"}
}