{
  "type": "Feature",
  "properties": {
    "gn:admin1_code":"73",
    "gn:asciiname":"Kzyl-Mayak",
    "gn:country_code":"RU",
    "gn:dem":158,
    "gn:feature_class":"P",
    "gn:feature_code":"PPL",
    "gn:name":"Kzyl-Mayak",
    "gn:population":0,
    "gn:timezone":"Europe/Moscow",
    "iso:country":"RU",
    "name:rus_x_preferred":[
        "\u041a\u0437\u044b\u043b-\u041c\u0430\u044f\u043a"
    ],
    "name:und_x_variant":[
        "\u041a\u0437\u044b\u043b-\u041c\u0430\u044f\u043a"
    ],
    "wof:name":"Kzyl-Mayak",
    "wof:placetype":"locality"
},
  "geometry": {"coordinates":[50.42401,55.19694000000001],"type":"Point"}
}