{
  "type": "Feature",
  "properties": {
    "gn:admin1_code":"88",
    "gn:asciiname":"Staroye Merzleyevo",
    "gn:country_code":"RU",
    "gn:dem":132,
    "gn:feature_class":"P",
    "gn:feature_code":"PPL",
    "gn:name":"Staroye Merzleyevo",
    "gn:population":0,
    "gn:timezone":"Europe/Moscow",
    "iso:country":"RU",
    "name:rus_x_preferred":[
        "\u0421\u0442\u0430\u0440\u043e\u0435 \u041c\u0435\u0440\u0437\u043b\u0435\u0435\u0432\u043e"
    ],
    "wof:name":"Staroye Merzleyevo",
    "wof:placetype":"locality"
},
  "geometry": {"coordinates":[37.8491,58.2128],"type":"Point"}
}