{
  "type": "Feature",
  "properties": {
    "gn:admin1_code":"86.0",
    "gn:asciiname":"Sviridovo",
    "gn:country_code":"RU",
    "gn:dem":167,
    "gn:feature_class":"P",
    "gn:feature_code":"PPL",
    "gn:name":"Sviridovo",
    "gn:population":0,
    "gn:timezone":"Europe/Moscow",
    "iso:country":"RU",
    "wof:name":"Sviridovo",
    "wof:placetype":"locality"
},
  "geometry": {"coordinates":[42.03917,51.65417],"type":"Point"}
}