{
  "type": "Feature",
  "properties": {
    "gn:admin1_code":"12",
    "gn:asciiname":"Keymekhki",
    "gn:country_code":"RU",
    "gn:dem":1814,
    "gn:feature_class":"P",
    "gn:feature_code":"PPL",
    "gn:name":"Keymekhki",
    "gn:population":0,
    "gn:timezone":"Europe/Moscow",
    "iso:country":"RU",
    "name:rus_x_preferred":[
        "\u041a\u0435\u0439\u043c\u0435\u0445\u043a\u0438"
    ],
    "wof:name":"Keymekhki",
    "wof:placetype":"locality"
},
  "geometry": {"coordinates":[45.22417,42.8225],"type":"Point"}
}