{
  "type": "Feature",
  "properties": {
    "gn:admin1_code":"77",
    "gn:asciiname":"Kostino",
    "gn:country_code":"RU",
    "gn:dem":134,
    "gn:feature_class":"P",
    "gn:feature_code":"PPL",
    "gn:name":"Kostino",
    "gn:population":0,
    "gn:timezone":"Europe/Moscow",
    "iso:country":"RU",
    "name:ceb_x_preferred":[
        "Kostino"
    ],
    "name:deu_x_preferred":[
        "Kostino"
    ],
    "name:hye_x_preferred":[
        "\u053f\u0578\u057d\u057f\u056b\u0576\u0578"
    ],
    "name:nld_x_preferred":[
        "Kostino"
    ],
    "name:rus_x_preferred":[
        "\u041a\u043e\u0441\u0442\u0438\u043d\u043e"
    ],
    "name:swe_x_preferred":[
        "Kostino"
    ],
    "name:ukr_x_preferred":[
        "\u041a\u043e\u0441\u0442\u0456\u043d\u043e"
    ],
    "name:und_x_variant":[
        "\u041a\u043e\u0441\u0442\u0438\u043d\u043e"
    ],
    "wof:name":"Kostino",
    "wof:placetype":"locality"
},
  "geometry": {"coordinates":[37.0287,57.1332],"type":"Point"}
}