{
  "type": "Feature",
  "properties": {
    "gn:admin1_code":"33",
    "gn:asciiname":"Tarasovo Russkoye",
    "gn:country_code":"RU",
    "gn:dem":112,
    "gn:feature_class":"P",
    "gn:feature_code":"PPL",
    "gn:name":"Tarasovo Russkoye",
    "gn:population":0,
    "gn:timezone":"Europe/Kirov",
    "iso:country":"RU",
    "name:rus_x_preferred":[
        "\u0422\u0430\u0440\u0430\u0441\u043e\u0432\u043e \u0420\u0443\u0441\u0441\u043a\u043e\u0435"
    ],
    "wof:name":"Tarasovo Russkoye",
    "wof:placetype":"locality"
},
  "geometry": {"coordinates":[47.08611,57.02972],"type":"Point"}
}