{
  "type": "Feature",
  "properties": {
    "gn:admin1_code":"33.0",
    "gn:asciiname":"Golovizniny",
    "gn:country_code":"RU",
    "gn:dem":144,
    "gn:feature_class":"P",
    "gn:feature_code":"PPL",
    "gn:name":"Golovizniny",
    "gn:population":0,
    "gn:timezone":"Europe/Kirov",
    "iso:country":"RU",
    "name:rus_x_preferred":[
        "\u0413\u043e\u043b\u043e\u0432\u0438\u0437\u043d\u0438\u043d\u044b"
    ],
    "name:und_x_variant":[
        "Golovizino",
        "Golovizniny"
    ],
    "wof:name":"Golovizniny",
    "wof:placetype":"locality"
},
  "geometry": {"coordinates":[49.88351,58.61066],"type":"Point"}
}