{
  "type": "Feature",
  "properties": {
    "gn:admin1_code":"72.0",
    "gn:asciiname":"Bol'shaya Akhtyrka",
    "gn:country_code":"RU",
    "gn:dem":169,
    "gn:feature_class":"P",
    "gn:feature_code":"PPL",
    "gn:name":"Bol\u2019shaya Akhtyrka",
    "gn:population":0,
    "gn:timezone":"Europe/Moscow",
    "iso:country":"RU",
    "name:rus_x_preferred":[
        "\u0411\u043e\u043b\u044c\u0448\u0430\u044f \u0410\u0445\u0442\u044b\u0440\u043a\u0430"
    ],
    "name:und_x_variant":[
        "Bol\u2019shaya Akhtyrka",
        "\u0411\u043e\u043b\u044c\u0448\u0430\u044f \u0410\u0445\u0442\u044b\u0440\u043a\u0430"
    ],
    "wof:name":"Bol'shaya Akhtyrka",
    "wof:placetype":"locality"
},
  "geometry": {"coordinates":[41.63472,52.54667],"type":"Point"}
}