{
  "type": "Feature",
  "properties": {
    "gn:admin1_code":"21",
    "gn:asciiname":"Vorsino",
    "gn:country_code":"RU",
    "gn:dem":103,
    "gn:feature_class":"P",
    "gn:feature_code":"PPL",
    "gn:name":"Vorsino",
    "gn:population":0,
    "gn:timezone":"Europe/Moscow",
    "iso:country":"RU",
    "name:eng_x_preferred":[
        "Vorsino"
    ],
    "name:nor_x_preferred":[
        "Vorsino"
    ],
    "name:rus_x_preferred":[
        "\u0412\u043e\u0440\u0441\u0438\u043d\u043e"
    ],
    "wof:name":"Vorsino",
    "wof:placetype":"locality"
},
  "geometry": {"coordinates":[42.23256,57.06661],"type":"Point"}
}