{
  "type": "Feature",
  "properties": {
    "gn:admin1_code":"56",
    "gn:asciiname":"Ol'shany",
    "gn:country_code":"RU",
    "gn:dem":154,
    "gn:feature_class":"P",
    "gn:feature_code":"PPL",
    "gn:name":"Ol\u2019shany",
    "gn:population":0,
    "gn:timezone":"Europe/Moscow",
    "iso:country":"RU",
    "name:rus_x_preferred":[
        "\u041e\u043b\u044c\u0448\u0430\u043d\u044b"
    ],
    "name:und_x_variant":[
        "Ol\u2019shany",
        "\u041e\u043b\u044c\u0448\u0430\u043d\u044b"
    ],
    "wof:name":"Ol'shany",
    "wof:placetype":"locality"
},
  "geometry": {"coordinates":[35.94722,52.84861],"type":"Point"}
}