{
  "type": "Feature",
  "properties": {
    "gn:admin1_code":"37",
    "gn:asciiname":"Noz'ma",
    "gn:country_code":"RU",
    "gn:dem":133,
    "gn:feature_class":"P",
    "gn:feature_code":"PPL",
    "gn:name":"Noz\u2019ma",
    "gn:population":0,
    "gn:timezone":"Europe/Moscow",
    "iso:country":"RU",
    "name:rus_x_preferred":[
        "\u041d\u043e\u0437\u044c\u043c\u0430"
    ],
    "name:und_x_variant":[
        "Noz\u2019ma"
    ],
    "wof:name":"Noz'ma",
    "wof:placetype":"locality"
},
  "geometry": {"coordinates":[43.3699,58.3501],"type":"Point"}
}