{
  "type": "Feature",
  "properties": {
    "gn:admin1_code":"69",
    "gn:asciiname":"Pleshivtsevo",
    "gn:country_code":"RU",
    "gn:dem":265,
    "gn:feature_class":"P",
    "gn:feature_code":"PPL",
    "gn:name":"Pleshivtsevo",
    "gn:population":0,
    "gn:timezone":"Europe/Moscow",
    "iso:country":"RU",
    "name:rus_x_preferred":[
        "\u041f\u043b\u0435\u0448\u0438\u0432\u0446\u0435\u0432\u043e"
    ],
    "wof:name":"Pleshivtsevo",
    "wof:placetype":"locality"
},
  "geometry": {"coordinates":[33.28333,54.75],"type":"Point"}
}