{
  "type": "Feature",
  "properties": {
    "gn:admin1_code":"33",
    "gn:asciiname":"Ushkinskaya",
    "gn:country_code":"RU",
    "gn:dem":116,
    "gn:feature_class":"P",
    "gn:feature_code":"PPL",
    "gn:name":"Ushkinskaya",
    "gn:population":0,
    "gn:timezone":"Europe/Kirov",
    "iso:country":"RU",
    "name:eng_x_preferred":[
        "Ushkinskaya"
    ],
    "name:nor_x_preferred":[
        "Usjkinskaja"
    ],
    "name:rus_x_preferred":[
        "\u0423\u0448\u043a\u0438\u043d\u0441\u043a\u0430\u044f"
    ],
    "name:rus_x_variant":[
        "\u0423\u0448\u043a\u0438\u043d\u0441\u043aa\u044f"
    ],
    "name:und_x_variant":[
        "Uga",
        "Ushkinskaya"
    ],
    "wof:name":"Ushkinskaya",
    "wof:placetype":"locality"
},
  "geometry": {"coordinates":[48.3239,60.39297],"type":"Point"}
}