{
  "type": "Feature",
  "properties": {
    "gn:admin1_code":"21.0",
    "gn:asciiname":"Odelevo",
    "gn:country_code":"RU",
    "gn:dem":127,
    "gn:feature_class":"P",
    "gn:feature_code":"PPL",
    "gn:name":"Odelevo",
    "gn:population":0,
    "gn:timezone":"Europe/Moscow",
    "iso:country":"RU",
    "name:rus_x_preferred":[
        "\u041e\u0434\u0435\u043b\u0435\u0432\u043e"
    ],
    "name:und_x_variant":[
        "\u041e\u0434\u0435\u043b\u0435\u0432\u043e"
    ],
    "wof:name":"Odelevo",
    "wof:placetype":"locality"
},
  "geometry": {"coordinates":[41.4707,57.24748],"type":"Point"}
}