{
  "type": "Feature",
  "properties": {
    "gn:admin1_code":"81.0",
    "gn:asciiname":"Aristovka",
    "gn:country_code":"RU",
    "gn:dem":180,
    "gn:feature_class":"P",
    "gn:feature_code":"PPL",
    "gn:name":"Aristovka",
    "gn:population":0,
    "gn:timezone":"Europe/Ulyanovsk",
    "iso:country":"RU",
    "name:eng_x_preferred":[
        "Aristovka"
    ],
    "name:nor_x_preferred":[
        "Aristovka"
    ],
    "name:rus_x_preferred":[
        "\u0410\u0440\u0438\u0441\u0442\u043e\u0432\u043a\u0430"
    ],
    "name:und_x_variant":[
        "\u0410\u0440\u0438\u0441\u0442\u043e\u0432\u043a\u0430",
        "Aristovka"
    ],
    "wof:name":"Aristovka",
    "wof:placetype":"locality"
},
  "geometry": {"coordinates":[46.55397,53.62872],"type":"Point"}
}