{
  "type": "Feature",
  "properties": {
    "gn:admin1_code":"85",
    "gn:asciiname":"Shelkovo",
    "gn:country_code":"RU",
    "gn:dem":170,
    "gn:feature_class":"P",
    "gn:feature_code":"PPL",
    "gn:name":"Sh\u00eblkovo",
    "gn:population":0,
    "gn:timezone":"Europe/Moscow",
    "iso:country":"RU",
    "name:rus_x_preferred":[
        "\u0428\u0451\u043b\u043a\u043e\u0432\u043e"
    ],
    "name:und_x_variant":[
        "Sh\u00eblkovo"
    ],
    "wof:name":"Shelkovo",
    "wof:placetype":"locality"
},
  "geometry": {"coordinates":[38.38704,58.98152],"type":"Point"}
}