{
  "type": "Feature",
  "properties": {
    "gn:admin1_code":"90.0",
    "gn:asciiname":"Pochasher",
    "gn:country_code":"RU",
    "gn:dem":170,
    "gn:feature_class":"P",
    "gn:feature_code":"PPL",
    "gn:name":"Pochasher",
    "gn:population":0,
    "gn:timezone":"Asia/Yekaterinburg",
    "iso:country":"RU",
    "name:rus_x_preferred":[
        "\u041f\u043e\u0447\u0430\u0448\u0435\u0440"
    ],
    "wof:name":"Pochasher",
    "wof:placetype":"locality"
},
  "geometry": {"coordinates":[54.9675,58.9403],"type":"Point"}
}