{
  "type": "Feature",
  "properties": {
    "gn:admin1_code":"47.0",
    "gn:asciiname":"Arapovo",
    "gn:country_code":"RU",
    "gn:dem":256,
    "gn:feature_class":"P",
    "gn:feature_code":"PPL",
    "gn:name":"Arapovo",
    "gn:population":0,
    "gn:timezone":"Europe/Moscow",
    "iso:country":"RU",
    "name:nor_x_preferred":[
        "Arapovo"
    ],
    "name:rus_x_preferred":[
        "\u0410\u0440\u0430\u043f\u043e\u0432\u043e"
    ],
    "wof:name":"Arapovo",
    "wof:placetype":"locality"
},
  "geometry": {"coordinates":[35.41667,55.33333],"type":"Point"}
}