{
  "type": "Feature",
  "properties": {
    "gn:admin1_code":"10.0",
    "gn:asciiname":"Zhukovshchina",
    "gn:country_code":"RU",
    "gn:dem":190,
    "gn:feature_class":"P",
    "gn:feature_code":"PPL",
    "gn:name":"Zhukovshchina",
    "gn:population":0,
    "gn:timezone":"Europe/Moscow",
    "iso:country":"RU",
    "name:rus_x_preferred":[
        "\u0416\u0443\u043a\u043e\u0432\u0449\u0438\u043d\u0430"
    ],
    "wof:name":"Zhukovshchina",
    "wof:placetype":"locality"
},
  "geometry": {"coordinates":[33.3828,53.5772],"type":"Point"}
}