{
  "type": "Feature",
  "properties": {
    "gn:admin1_code":"85",
    "gn:asciiname":"Grifonikha",
    "gn:country_code":"RU",
    "gn:dem":148,
    "gn:feature_class":"P",
    "gn:feature_code":"PPL",
    "gn:name":"Grifonikha",
    "gn:population":0,
    "gn:timezone":"Europe/Moscow",
    "iso:country":"RU",
    "name:rus_x_preferred":[
        "\u0413\u0440\u0438\u0444\u043e\u043d\u0438\u0445\u0430"
    ],
    "name:und_x_variant":[
        "\u0413\u0440\u0438\u0444\u043e\u043d\u0438\u0445\u0430"
    ],
    "wof:name":"Grifonikha",
    "wof:placetype":"locality"
},
  "geometry": {"coordinates":[39.622,59.8776],"type":"Point"}
}