{
  "type": "Feature",
  "properties": {
    "gn:admin1_code":"77",
    "gn:asciiname":"Skornevo",
    "gn:country_code":"RU",
    "gn:dem":163,
    "gn:feature_class":"P",
    "gn:feature_code":"PPL",
    "gn:name":"Skorn\u00ebvo",
    "gn:population":0,
    "gn:timezone":"Europe/Moscow",
    "iso:country":"RU",
    "name:eng_x_preferred":[
        "Skorn\u00ebva"
    ],
    "name:nor_x_preferred":[
        "Skornevo"
    ],
    "name:rus_x_preferred":[
        "\u0421\u043a\u043e\u0440\u043d\u0435\u0432\u043e"
    ],
    "name:rus_x_variant":[
        "\u0421\u043a\u043e\u0440\u043d\u0451\u0432\u043e"
    ],
    "name:und_x_variant":[
        "Okorneva",
        "Skorn\u00ebvo"
    ],
    "wof:name":"Skornevo",
    "wof:placetype":"locality"
},
  "geometry": {"coordinates":[36.03849,57.95208],"type":"Point"}
}