{
  "type": "Feature",
  "properties": {
    "gn:admin1_code":"72",
    "gn:asciiname":"Bakovka",
    "gn:country_code":"RU",
    "gn:dem":144,
    "gn:feature_class":"P",
    "gn:feature_code":"PPL",
    "gn:name":"Bakovka",
    "gn:population":0,
    "gn:timezone":"Europe/Moscow",
    "iso:country":"RU",
    "name:nor_x_preferred":[
        "Bakovka"
    ],
    "name:rus_x_preferred":[
        "\u0411\u0430\u043a\u043e\u0432\u043a\u0430"
    ],
    "wof:name":"Bakovka",
    "wof:placetype":"locality"
},
  "geometry": {"coordinates":[40.70889,52.32556],"type":"Point"}
}