{
  "type": "Feature",
  "properties": {
    "gn:admin1_code":"47.0",
    "gn:asciiname":"Alachkovo",
    "gn:country_code":"RU",
    "gn:dem":187,
    "gn:feature_class":"P",
    "gn:feature_code":"PPL",
    "gn:name":"Alachkovo",
    "gn:population":0,
    "gn:timezone":"Europe/Moscow",
    "iso:country":"RU",
    "name:nor_x_preferred":[
        "Alatsjkovo"
    ],
    "name:rus_x_preferred":[
        "\u0410\u043b\u0430\u0447\u043a\u043e\u0432\u043e"
    ],
    "wof:name":"Alachkovo",
    "wof:placetype":"locality"
},
  "geometry": {"coordinates":[37.56294000000001,55.20757],"type":"Point"}
}