{
  "type": "Feature",
  "properties": {
    "gn:admin1_code":"62",
    "gn:asciiname":"Mosolovo",
    "gn:country_code":"RU",
    "gn:dem":134,
    "gn:feature_class":"P",
    "gn:feature_code":"PPL",
    "gn:name":"Mosolovo",
    "gn:population":0,
    "gn:timezone":"Europe/Moscow",
    "iso:country":"RU",
    "name:rus_x_preferred":[
        "\u041c\u043e\u0441\u043e\u043b\u043e\u0432\u043e"
    ],
    "name:und_x_variant":[
        "\u041c\u043e\u0441\u043e\u043b\u043e\u0432\u043e"
    ],
    "wof:name":"Mosolovo",
    "wof:placetype":"locality"
},
  "geometry": {"coordinates":[40.0143,54.4163],"type":"Point"}
}