{
  "type": "Feature",
  "properties": {
    "gn:admin1_code":"89.0",
    "gn:asciiname":"Ol'gokhta",
    "gn:country_code":"RU",
    "gn:dem":45,
    "gn:feature_class":"P",
    "gn:feature_code":"PPL",
    "gn:name":"Ol\u2019gokhta",
    "gn:population":0,
    "gn:timezone":"Asia/Vladivostok",
    "iso:country":"RU",
    "name:rus_x_preferred":[
        "\u041e\u043b\u044c\u0433\u043e\u0445\u0442\u0430"
    ],
    "name:und_x_variant":[
        "Ol\u2019gokhta"
    ],
    "wof:name":"Ol'gokhta",
    "wof:placetype":"locality"
},
  "geometry": {"coordinates":[134.15722,48.60959],"type":"Point"}
}