{
  "type": "Feature",
  "properties": {
    "gn:admin1_code":"38",
    "gn:asciiname":"Podgornaya-Sinyukha",
    "gn:country_code":"RU",
    "gn:dem":626,
    "gn:feature_class":"P",
    "gn:feature_code":"PPL",
    "gn:name":"Podgornaya-Sinyukha",
    "gn:population":0,
    "gn:timezone":"Europe/Moscow",
    "iso:country":"RU",
    "name:eng_x_preferred":[
        "Podgornaya-Sinyukha"
    ],
    "name:nor_x_preferred":[
        "Podgornaja Sinjukha"
    ],
    "name:rus_x_preferred":[
        "\u041f\u043e\u0434\u0433\u043e\u0440\u043d\u0430\u044f \u0421\u0438\u043d\u044e\u0445\u0430"
    ],
    "name:rus_x_variant":[
        "\u041f\u043e\u0434\u0433\u043e\u0440\u043d\u0430\u044f-\u0421\u0438\u043d\u044e\u0445\u0430"
    ],
    "name:und_x_variant":[
        "Podgorno-Sinyukhinskiy",
        "Podgornaya-Sinyukha",
        "\u041f\u043e\u0434\u0433\u043e\u0440\u043d\u0430\u044f-\u0421\u0438\u043d\u044e\u0445\u0430"
    ],
    "wof:name":"Podgornaya-Sinyukha",
    "wof:placetype":"locality"
},
  "geometry": {"coordinates":[41.2169,44.3774],"type":"Point"}
}