{
  "type": "Feature",
  "properties": {
    "gn:admin1_code":"78",
    "gn:asciiname":"Gagarina",
    "gn:cc2":"RU",
    "gn:country_code":"RU",
    "gn:dem":121,
    "gn:feature_class":"P",
    "gn:feature_code":"PPL",
    "gn:name":"Gagarina",
    "gn:population":0,
    "gn:timezone":"Asia/Yekaterinburg",
    "iso:country":"RU",
    "name:eng_x_preferred":[
        "Gagarina"
    ],
    "name:nor_x_preferred":[
        "Gagarina"
    ],
    "name:rus_x_preferred":[
        "\u0413\u0430\u0433\u0430\u0440\u0438\u043d\u0430"
    ],
    "name:und_x_variant":[
        "Gagarino"
    ],
    "wof:name":"Gagarina",
    "wof:placetype":"locality"
},
  "geometry": {"coordinates":[68.2375,55.79056],"type":"Point"}
}