{
  "type": "Feature",
  "properties": {
    "gn:admin1_code":"57",
    "gn:asciiname":"Zhmakino",
    "gn:country_code":"RU",
    "gn:dem":154,
    "gn:feature_class":"P",
    "gn:feature_code":"PPL",
    "gn:name":"Zhmakino",
    "gn:population":0,
    "gn:timezone":"Europe/Moscow",
    "iso:country":"RU",
    "name:rus_x_preferred":[
        "\u0416\u043c\u0430\u043a\u0438\u043d\u043e"
    ],
    "name:und_x_variant":[
        "Zhmakino Pervoye",
        "Zhmakino"
    ],
    "wof:name":"Zhmakino",
    "wof:placetype":"locality"
},
  "geometry": {"coordinates":[44.34383,52.65337],"type":"Point"}
}