{
  "type": "Feature",
  "properties": {
    "gn:admin1_code":"16",
    "gn:asciiname":"Khumushi",
    "gn:country_code":"RU",
    "gn:dem":96,
    "gn:feature_class":"P",
    "gn:feature_code":"PPL",
    "gn:name":"Khumushi",
    "gn:population":0,
    "gn:timezone":"Europe/Moscow",
    "iso:country":"RU",
    "name:rus_x_preferred":[
        "\u0425\u0443\u043c\u0443\u0448\u0438"
    ],
    "wof:name":"Khumushi",
    "wof:placetype":"locality"
},
  "geometry": {"coordinates":[46.87398,55.64199],"type":"Point"}
}