{
  "type": "Feature",
  "properties": {
    "gn:admin1_code":"12",
    "gn:asciiname":"Mekhkishty",
    "gn:country_code":"RU",
    "gn:dem":645,
    "gn:feature_class":"P",
    "gn:feature_code":"PPL",
    "gn:name":"Mekhkishty",
    "gn:population":0,
    "gn:timezone":"Europe/Moscow",
    "iso:country":"RU",
    "name:che_x_preferred":[
        "Mexka\u015f-The\u1e8ba"
    ],
    "name:che_x_variant":[
        "\u041c\u0435\u0445\u043a\u0430\u0448-\u0422\u0406\u0435\u0445\u044c\u0430",
        "\u041c\u0435\u0445\u043a\u0435\u0448\u0442\u044b"
    ],
    "name:rus_x_preferred":[
        "\u041c\u0435\u0445\u043a\u0438\u0448\u0442\u044b"
    ],
    "name:rus_x_variant":[
        "Mehki\u0161ty",
        "\u041c\u0435\u0445\u043a\u0435\u0441\u0442\u044b"
    ],
    "name:und_x_variant":[
        "Mekhkeshty",
        "Mehkesty",
        "Mekhkishty"
    ],
    "wof:name":"Mekhkishty",
    "wof:placetype":"locality"
},
  "geometry": {"coordinates":[46.39089,43.05755],"type":"Point"}
}