{
  "type": "Feature",
  "properties": {
    "gn:admin1_code":"16",
    "gn:asciiname":"Yamashevo",
    "gn:country_code":"RU",
    "gn:dem":149,
    "gn:feature_class":"P",
    "gn:feature_code":"PPL",
    "gn:name":"Yamash\u00ebvo",
    "gn:population":0,
    "gn:timezone":"Europe/Moscow",
    "iso:country":"RU",
    "name:eng_x_preferred":[
        "Yamash\u00ebvo"
    ],
    "name:nor_x_preferred":[
        "Jamasjevo"
    ],
    "name:rus_x_preferred":[
        "\u042f\u043c\u0430\u0448\u0435\u0432\u043e"
    ],
    "name:rus_x_variant":[
        "\u042f\u043c\u0430\u0448\u0451\u0432\u043e"
    ],
    "wof:name":"Yamashevo",
    "wof:placetype":"locality"
},
  "geometry": {"coordinates":[47.2241,55.5965],"type":"Point"}
}