{
  "type": "Feature",
  "properties": {
    "gn:admin1_code":"20",
    "gn:asciiname":"Eligey",
    "gn:cc2":"RU",
    "gn:country_code":"RU",
    "gn:dem":499,
    "gn:feature_class":"P",
    "gn:feature_code":"PPL",
    "gn:name":"Eligey",
    "gn:population":0,
    "gn:timezone":"Asia/Irkutsk",
    "iso:country":"RU",
    "name:rus_x_preferred":[
        "\u042d\u043b\u0438\u0433\u0435\u0439"
    ],
    "name:und_x_variant":[
        "Eligei",
        "Eligey"
    ],
    "wof:name":"Eligey",
    "wof:placetype":"locality"
},
  "geometry": {"coordinates":[107.76667,53.73333],"type":"Point"}
}