{
  "type": "Feature",
  "properties": {
    "gn:admin1_code":"45.0",
    "gn:asciiname":"Izotkino",
    "gn:country_code":"RU",
    "gn:dem":101,
    "gn:feature_class":"P",
    "gn:feature_code":"PPL",
    "gn:name":"Izotkino",
    "gn:population":0,
    "gn:timezone":"Europe/Moscow",
    "iso:country":"RU",
    "name:rus_x_preferred":[
        "\u0418\u0437\u043e\u0442\u043a\u0438\u043d\u043e"
    ],
    "name:und_x_variant":[
        "\u0418\u0437\u043e\u0442\u043a\u0438\u043d\u043e"
    ],
    "wof:name":"Izotkino",
    "wof:placetype":"locality"
},
  "geometry": {"coordinates":[48.17083,56.14833],"type":"Point"}
}