{
  "type": "Feature",
  "properties": {
    "gn:admin1_code":"21",
    "gn:asciiname":"Yakovino",
    "gn:country_code":"RU",
    "gn:dem":146,
    "gn:feature_class":"P",
    "gn:feature_code":"PPL",
    "gn:name":"Yakovino",
    "gn:population":0,
    "gn:timezone":"Europe/Moscow",
    "iso:country":"RU",
    "name:rus_x_preferred":[
        "\u042f\u043a\u043e\u0432\u0438\u043d\u043e"
    ],
    "wof:name":"Yakovino",
    "wof:placetype":"locality"
},
  "geometry": {"coordinates":[40.54865,56.70814],"type":"Point"}
}