{
  "type": "Feature",
  "properties": {
    "gn:admin1_code":"54",
    "gn:asciiname":"Rakitinka",
    "gn:country_code":"RU",
    "gn:dem":116,
    "gn:feature_class":"P",
    "gn:feature_code":"PPL",
    "gn:name":"Rakitinka",
    "gn:population":0,
    "gn:timezone":"Asia/Omsk",
    "iso:country":"RU",
    "name:rus_x_preferred":[
        "\u0420\u0430\u043a\u0438\u0442\u0438\u043d\u043a\u0430"
    ],
    "wof:name":"Rakitinka",
    "wof:placetype":"locality"
},
  "geometry": {"coordinates":[73.52141,54.89838],"type":"Point"}
}