{
  "type": "Feature",
  "properties": {
    "gn:admin1_code":"8",
    "gn:asciiname":"Muldakayevo",
    "gn:country_code":"RU",
    "gn:dem":405,
    "gn:feature_class":"P",
    "gn:feature_code":"PPL",
    "gn:name":"Muldakayevo",
    "gn:population":0,
    "gn:timezone":"Asia/Yekaterinburg",
    "iso:country":"RU",
    "name:bak_x_preferred":[
        "\u041c\u0443\u043b\u0434\u0430\u04a1\u0430\u0439"
    ],
    "name:che_x_preferred":[
        "\u041c\u0443\u043b\u0434\u0430\u043a\u0430\u0435\u0432\u043e"
    ],
    "name:hye_x_preferred":[
        "\u0544\u0578\u0582\u056c\u0564\u0561\u056f\u0561\u0587\u0578"
    ],
    "name:kat_x_preferred":[
        "\u10db\u10e3\u10da\u10d3\u10d0\u10d9\u10d0\u10d4\u10d5\u10dd(\u10d1\u10d4\u10da\u10dd\u10e0\u10d4\u10ea\u10d9\u10d8\u10e1 \u10e0\u10d0\u10d8\u10dd\u10dc\u10d8)"
    ],
    "name:kaz_x_preferred":[
        "\u041c\u0443\u043b\u0434\u0430\u043a\u0430"
    ],
    "name:rus_x_preferred":[
        "\u041c\u0443\u043b\u0434\u0430\u043a\u0430\u0435\u0432\u043e"
    ],
    "name:tat_x_preferred":[
        "\u041c\u0443\u043b\u0434\u0430\u043a\u0430\u0439"
    ],
    "name:ukr_x_preferred":[
        "\u041c\u0443\u043b\u0434\u0430\u043a\u0430\u0454\u0432\u043e"
    ],
    "name:und_x_variant":[
        "Muldakayeva",
        "Muldakayevo"
    ],
    "wof:name":"Muldakayevo",
    "wof:placetype":"locality"
},
  "geometry": {"coordinates":[59.8182,54.7648],"type":"Point"}
}