{
  "type": "Feature",
  "properties": {
    "gn:admin1_code":"8",
    "gn:asciiname":"Muldakayevo",
    "gn:country_code":"RU",
    "gn:dem":405,
    "gn:feature_class":"P",
    "gn:feature_code":"PPL",
    "gn:name":"Muldakayevo",
    "gn:population":0,
    "gn:timezone":"Asia/Yekaterinburg",
    "iso:country":"RU",
    "name:rus_x_preferred":[
        "\u041c\u0443\u043b\u0434\u0430\u043a\u0430\u0435\u0432\u043e"
    ],
    "name:und_x_variant":[
        "Muldakayeva",
        "Muldakayevo",
        "\u041c\u0443\u043b\u0434\u0430\u043a\u0430\u0435\u0432\u043e"
    ],
    "wof:name":"Muldakayevo",
    "wof:placetype":"locality"
},
  "geometry": {"coordinates":[59.8182,54.7648],"type":"Point"}
}