{
  "type": "Feature",
  "properties": {
    "gn:admin1_code":"63",
    "gn:asciiname":"Burkhalinskiy",
    "gn:country_code":"RU",
    "gn:dem":1181,
    "gn:feature_class":"P",
    "gn:feature_code":"PPL",
    "gn:name":"Burkhalinskiy",
    "gn:population":0,
    "gn:timezone":"Asia/Vladivostok",
    "iso:country":"RU",
    "name:eng_x_preferred":[
        "Burkhalinskiy"
    ],
    "name:nor_x_preferred":[
        "Burkhalinskij"
    ],
    "name:rus_x_preferred":[
        "\u0411\u0443\u0440\u0445\u0430\u043b\u0438\u043d\u0441\u043a\u0438\u0439"
    ],
    "name:und_x_variant":[
        "Burkhala"
    ],
    "wof:name":"Burkhalinskiy",
    "wof:placetype":"locality"
},
  "geometry": {"coordinates":[138.19978,61.67828000000001],"type":"Point"}
}