{
  "type": "Feature",
  "properties": {
    "gn:admin1_code":"33",
    "gn:asciiname":"Prokoshevo",
    "gn:country_code":"RU",
    "gn:dem":125,
    "gn:feature_class":"P",
    "gn:feature_code":"PPL",
    "gn:name":"Prokoshevo",
    "gn:population":0,
    "gn:timezone":"Europe/Kirov",
    "iso:country":"RU",
    "name:rus_x_preferred":[
        "\u041f\u0440\u043e\u043a\u043e\u0448\u0435\u0432\u043e"
    ],
    "wof:name":"Prokoshevo",
    "wof:placetype":"locality"
},
  "geometry": {"coordinates":[50.38800000000001,57.4956],"type":"Point"}
}