{
  "type": "Feature",
  "properties": {
    "gn:admin1_code":"55",
    "gn:asciiname":"Lyashevo",
    "gn:country_code":"RU",
    "gn:dem":46,
    "gn:feature_class":"P",
    "gn:feature_code":"PPL",
    "gn:name":"Lyashevo",
    "gn:population":0,
    "gn:timezone":"Asia/Yekaterinburg",
    "iso:country":"RU",
    "name:rus_x_preferred":[
        "\u041b\u044f\u0448\u0435\u0432\u043e"
    ],
    "name:und_x_variant":[
        "\u041b\u044f\u0448\u0435\u0432\u043e"
    ],
    "wof:name":"Lyashevo",
    "wof:placetype":"locality"
},
  "geometry": {"coordinates":[51.46667,51.81667],"type":"Point"}
}