{
  "type": "Feature",
  "properties": {
    "gn:admin1_code":"80",
    "gn:asciiname":"Kadilovo",
    "gn:country_code":"RU",
    "gn:dem":228,
    "gn:feature_class":"P",
    "gn:feature_code":"PPL",
    "gn:name":"Kadilovo",
    "gn:population":0,
    "gn:timezone":"Europe/Samara",
    "iso:country":"RU",
    "name:rus_x_preferred":[
        "\u041a\u0430\u0434\u0438\u043b\u043e\u0432\u043e"
    ],
    "name:und_x_variant":[
        "Kodilovo",
        "Kadilovo",
        "\u041a\u0430\u0434\u0438\u043b\u043e\u0432\u043e"
    ],
    "wof:name":"Kadilovo",
    "wof:placetype":"locality"
},
  "geometry": {"coordinates":[53.37581,57.32146],"type":"Point"}
}