{
  "type": "Feature",
  "properties": {
    "gn:admin1_code":"68",
    "gn:asciiname":"Mayskiy",
    "gn:cc2":"RU",
    "gn:country_code":"RU",
    "gn:dem":382,
    "gn:feature_class":"P",
    "gn:feature_code":"PPL",
    "gn:name":"Mayskiy",
    "gn:population":0,
    "gn:timezone":"Europe/Moscow",
    "iso:country":"RU",
    "name:rus_x_preferred":[
        "\u041c\u0430\u0439\u0441\u043a\u0438\u0439"
    ],
    "name:und_x_variant":[
        "Chuipalova",
        "Mayskiy",
        "\u041c\u0430\u0439\u0441\u043a\u0438\u0439"
    ],
    "wof:name":"Mayskiy",
    "wof:placetype":"locality"
},
  "geometry": {"coordinates":[44.81972,43.5625],"type":"Point"}
}