{
  "type": "Feature",
  "properties": {
    "gn:admin1_code":"60",
    "gn:asciiname":"Lavreshkovo",
    "gn:country_code":"RU",
    "gn:dem":181,
    "gn:feature_class":"P",
    "gn:feature_code":"PPL",
    "gn:name":"Lavreshkovo",
    "gn:population":0,
    "gn:timezone":"Europe/Moscow",
    "iso:country":"RU",
    "name:rus_x_preferred":[
        "\u041b\u0430\u0432\u0440\u0435\u0448\u043a\u043e\u0432\u043e"
    ],
    "name:und_x_variant":[
        "\u041b\u0430\u0432\u0440\u0435\u0448\u043a\u043e\u0432\u043e"
    ],
    "wof:name":"Lavreshkovo",
    "wof:placetype":"locality"
},
  "geometry": {"coordinates":[31.13333,56.25],"type":"Point"}
}