{
  "type": "Feature",
  "properties": {
    "gn:admin1_code":"9.0",
    "gn:asciiname":"Dolgiy",
    "gn:country_code":"RU",
    "gn:dem":227,
    "gn:feature_class":"P",
    "gn:feature_code":"PPL",
    "gn:name":"Dolgiy",
    "gn:population":0,
    "gn:timezone":"Europe/Moscow",
    "iso:country":"RU",
    "name:rus_x_preferred":[
        "\u0414\u043e\u043b\u0433\u0438\u0439"
    ],
    "wof:name":"Dolgiy",
    "wof:placetype":"locality"
},
  "geometry": {"coordinates":[36.86481,50.99254000000001],"type":"Point"}
}