{
  "type": "Feature",
  "properties": {
    "gn:admin1_code":"43",
    "gn:asciiname":"Korovino",
    "gn:country_code":"RU",
    "gn:dem":131,
    "gn:feature_class":"P",
    "gn:feature_code":"PPL",
    "gn:name":"Korovino",
    "gn:population":0,
    "gn:timezone":"Europe/Moscow",
    "iso:country":"RU",
    "name:est_x_preferred":[
        "Korovino"
    ],
    "name:hye_x_preferred":[
        "\u053f\u0578\u0580\u0578\u057e\u056b\u0576\u0578"
    ],
    "name:rus_x_preferred":[
        "\u041a\u043e\u0440\u043e\u0432\u0438\u043d\u043e"
    ],
    "name:ukr_x_preferred":[
        "\u041a\u043e\u0440\u043e\u0432\u0438\u043d\u043e"
    ],
    "name:und_x_variant":[
        "\u041a\u043e\u0440\u043e\u0432\u0438\u043d\u043e"
    ],
    "wof:name":"Korovino",
    "wof:placetype":"locality"
},
  "geometry": {"coordinates":[39.5571,52.5815],"type":"Point"}
}