{
  "type": "Feature",
  "properties": {
    "gn:admin1_code":"88",
    "gn:asciiname":"Malinovka",
    "gn:country_code":"RU",
    "gn:dem":167,
    "gn:feature_class":"P",
    "gn:feature_code":"PPL",
    "gn:name":"Malinovka",
    "gn:population":0,
    "gn:timezone":"Europe/Moscow",
    "iso:country":"RU",
    "name:rus_x_preferred":[
        "\u041c\u0430\u043b\u0438\u043d\u043e\u0432\u043a\u0430"
    ],
    "name:und_x_variant":[
        "\u041c\u0430\u043b\u0438\u043d\u043e\u0432\u043a\u0430"
    ],
    "wof:name":"Malinovka",
    "wof:placetype":"locality"
},
  "geometry": {"coordinates":[37.681,58.11946999999999],"type":"Point"}
}