{
  "type": "Feature",
  "properties": {
    "gn:admin1_code":"13",
    "gn:asciiname":"Sak-Elginskiy",
    "gn:country_code":"RU",
    "gn:dem":307,
    "gn:feature_class":"P",
    "gn:feature_code":"PPL",
    "gn:name":"Sak-Elginskiy",
    "gn:population":0,
    "gn:timezone":"Asia/Yekaterinburg",
    "iso:country":"RU",
    "wof:name":"Sak-Elginskiy",
    "wof:placetype":"locality"
},
  "geometry": {"coordinates":[60.21666999999999,55.45],"type":"Point"}
}