{
  "type": "Feature",
  "properties": {
    "gn:admin1_code":"42",
    "gn:asciiname":"Memino",
    "gn:country_code":"RU",
    "gn:dem":41,
    "gn:feature_class":"P",
    "gn:feature_code":"PPL",
    "gn:name":"Memino",
    "gn:population":0,
    "gn:timezone":"Europe/Moscow",
    "iso:country":"RU",
    "name:eng_x_preferred":[
        "Memino"
    ],
    "name:nor_x_preferred":[
        "Memino"
    ],
    "name:rus_x_preferred":[
        "\u041c\u0435\u043c\u0438\u043d\u043e"
    ],
    "wof:name":"Memino",
    "wof:placetype":"locality"
},
  "geometry": {"coordinates":[31.96598,59.73679],"type":"Point"}
}