{
  "type": "Feature",
  "properties": {
    "gn:admin1_code":"77",
    "gn:asciiname":"Gorka",
    "gn:country_code":"RU",
    "gn:dem":76,
    "gn:feature_class":"P",
    "gn:feature_code":"PPL",
    "gn:name":"Gorka",
    "gn:population":0,
    "gn:timezone":"Europe/Moscow",
    "iso:country":"RU",
    "name:rus_x_preferred":[
        "\u0413\u043e\u0440\u043a\u0430"
    ],
    "name:und_x_variant":[
        "\u0413\u043e\u0440\u043a\u0430"
    ],
    "wof:name":"Gorka",
    "wof:placetype":"locality"
},
  "geometry": {"coordinates":[30.9816,56.8782],"type":"Point"}
}