{
  "type": "Feature",
  "properties": {
    "gn:admin1_code":"60",
    "gn:asciiname":"Grit'kovo",
    "gn:country_code":"RU",
    "gn:dem":141,
    "gn:feature_class":"P",
    "gn:feature_code":"PPL",
    "gn:name":"Grit\u2019kovo",
    "gn:population":0,
    "gn:timezone":"Europe/Moscow",
    "iso:country":"RU",
    "name:rus_x_preferred":[
        "\u0413\u0440\u0438\u0442\u044c\u043a\u043e\u0432\u043e"
    ],
    "name:und_x_variant":[
        "Grit\u2019kovo"
    ],
    "wof:name":"Grit'kovo",
    "wof:placetype":"locality"
},
  "geometry": {"coordinates":[29.0865,56.2513],"type":"Point"}
}