{
  "type": "Feature",
  "properties": {
    "gn:admin1_code":"67",
    "gn:asciiname":"Morozov",
    "gn:country_code":"RU",
    "gn:dem":31,
    "gn:feature_class":"P",
    "gn:feature_code":"PPL",
    "gn:name":"Morozov",
    "gn:population":0,
    "gn:timezone":"Europe/Saratov",
    "iso:country":"RU",
    "name:eng_x_preferred":[
        "Morozov"
    ],
    "name:nor_x_preferred":[
        "Morozov"
    ],
    "name:rus_x_preferred":[
        "\u041c\u043e\u0440\u043e\u0437\u043e\u0432"
    ],
    "name:und_x_variant":[
        "\u041c\u043e\u0440\u043e\u0437\u043e\u0432",
        "Morozov"
    ],
    "wof:name":"Morozov",
    "wof:placetype":"locality"
},
  "geometry": {"coordinates":[48.4811,50.47193],"type":"Point"}
}