{
  "type": "Feature",
  "properties": {
    "gn:admin1_code":"91.0",
    "gn:asciiname":"Krasnopolyansk",
    "gn:country_code":"RU",
    "gn:dem":222,
    "gn:feature_class":"P",
    "gn:feature_code":"PPL",
    "gn:name":"Krasnopolyansk",
    "gn:population":0,
    "gn:timezone":"Asia/Krasnoyarsk",
    "iso:country":"RU",
    "name:rus_x_preferred":[
        "\u041a\u0440\u0430\u0441\u043d\u043e\u043f\u043e\u043b\u044f\u043d\u0441\u043a"
    ],
    "wof:name":"Krasnopolyansk",
    "wof:placetype":"locality"
},
  "geometry": {"coordinates":[95.56806,56.17778000000001],"type":"Point"}
}