{
  "type": "Feature",
  "properties": {
    "gn:admin1_code":"60",
    "gn:asciiname":"Morkovo",
    "gn:country_code":"RU",
    "gn:dem":212,
    "gn:feature_class":"P",
    "gn:feature_code":"PPL",
    "gn:name":"Morkovo",
    "gn:population":0,
    "gn:timezone":"Europe/Moscow",
    "iso:country":"RU",
    "name:rus_x_preferred":[
        "\u041c\u043e\u0440\u043a\u043e\u0432\u043e"
    ],
    "wof:name":"Morkovo",
    "wof:placetype":"locality"
},
  "geometry": {"coordinates":[29.6591,56.422],"type":"Point"}
}