{
  "type": "Feature",
  "properties": {
    "gn:admin1_code":"9.0",
    "gn:asciiname":"Kuleshovka",
    "gn:country_code":"RU",
    "gn:dem":153,
    "gn:feature_class":"P",
    "gn:feature_code":"PPL",
    "gn:name":"Kuleshovka",
    "gn:population":0,
    "gn:timezone":"Europe/Moscow",
    "iso:country":"RU",
    "name:rus_x_preferred":[
        "\u041a\u0443\u043b\u0435\u0448\u043e\u0432\u043a\u0430"
    ],
    "name:und_x_variant":[
        "\u041a\u0443\u043b\u0435\u0448\u043e\u0432\u043a\u0430"
    ],
    "wof:name":"Kuleshovka",
    "wof:placetype":"locality"
},
  "geometry": {"coordinates":[36.09102,50.55302],"type":"Point"}
}