{
  "type": "Feature",
  "properties": {
    "gn:admin1_code":"19.0",
    "gn:asciiname":"Morch",
    "gn:country_code":"RU",
    "gn:dem":1482,
    "gn:feature_class":"P",
    "gn:feature_code":"PPL",
    "gn:name":"Morch",
    "gn:population":0,
    "gn:timezone":"Europe/Moscow",
    "iso:country":"RU",
    "wof:name":"Morch",
    "wof:placetype":"locality"
},
  "geometry": {"coordinates":[44.75472,42.81444000000001],"type":"Point"}
}