{
  "type": "Feature",
  "properties": {
    "gn:admin1_code":"52",
    "gn:asciiname":"Vadosy",
    "gn:country_code":"RU",
    "gn:dem":44,
    "gn:feature_class":"P",
    "gn:feature_code":"PPL",
    "gn:name":"Vadosy",
    "gn:population":0,
    "gn:timezone":"Europe/Moscow",
    "iso:country":"RU",
    "name:und_x_variant":[
        "Vadossy",
        "Vadosy"
    ],
    "wof:name":"Vadosy",
    "wof:placetype":"locality"
},
  "geometry": {"coordinates":[30.2278,58.26096],"type":"Point"}
}