{
  "type": "Feature",
  "properties": {
    "gn:admin1_code":"20",
    "gn:asciiname":"Zagatuy",
    "gn:country_code":"RU",
    "gn:dem":579,
    "gn:feature_class":"P",
    "gn:feature_code":"PPL",
    "gn:name":"Zagatuy",
    "gn:population":0,
    "gn:timezone":"Asia/Irkutsk",
    "iso:country":"RU",
    "name:eng_x_preferred":[
        "Zagatuy"
    ],
    "name:nor_x_preferred":[
        "Zagatuj"
    ],
    "name:rus_x_preferred":[
        "\u0417\u0430\u0433\u0430\u0442\u0443\u0439"
    ],
    "wof:name":"Zagatuy",
    "wof:placetype":"locality"
},
  "geometry": {"coordinates":[105.34869999999999,52.8911],"type":"Point"}
}