{
  "type": "Feature",
  "properties": {
    "gn:admin1_code":"64",
    "gn:asciiname":"Sladkoye Ozero",
    "gn:country_code":"RU",
    "gn:dem":4,
    "gn:feature_class":"P",
    "gn:feature_code":"PPL",
    "gn:name":"Sladkoye Ozero",
    "gn:population":0,
    "gn:timezone":"Asia/Sakhalin",
    "iso:country":"RU",
    "name:rus_x_preferred":[
        "\u0421\u043b\u0430\u0434\u043a\u043e\u0435 \u041e\u0437\u0435\u0440\u043e"
    ],
    "name:und_x_variant":[
        "\u0421\u043b\u0430\u0434\u043a\u043e\u0435 \u041e\u0437\u0435\u0440\u043e"
    ],
    "wof:name":"Sladkoye Ozero",
    "wof:placetype":"locality"
},
  "geometry": {"coordinates":[141.94999999999999,53.41667],"type":"Point"}
}