{
  "type": "Feature",
  "properties": {
    "gn:admin1_code":"30",
    "gn:asciiname":"Padali",
    "gn:country_code":"RU",
    "gn:dem":64,
    "gn:feature_class":"P",
    "gn:feature_code":"PPL",
    "gn:name":"Padali",
    "gn:population":0,
    "gn:timezone":"Asia/Vladivostok",
    "iso:country":"RU",
    "name:eng_x_preferred":[
        "Padali"
    ],
    "name:nor_x_preferred":[
        "Padali"
    ],
    "name:rus_x_preferred":[
        "\u041f\u0430\u0434\u0430\u043b\u0438"
    ],
    "name:und_x_variant":[
        "\u041f\u0430\u0434\u0430\u043b\u0438",
        "Padali"
    ],
    "wof:name":"Padali",
    "wof:placetype":"locality"
},
  "geometry": {"coordinates":[136.65018000000001,50.21748],"type":"Point"}
}