{
  "type": "Feature",
  "properties": {
    "gn:admin1_code":"69",
    "gn:asciiname":"Drobushevo",
    "gn:country_code":"RU",
    "gn:dem":202,
    "gn:feature_class":"P",
    "gn:feature_code":"PPL",
    "gn:name":"Drobushevo",
    "gn:population":0,
    "gn:timezone":"Europe/Moscow",
    "iso:country":"RU",
    "name:rus_x_preferred":[
        "\u0414\u0440\u043e\u0431\u0443\u0448\u0435\u0432\u043e"
    ],
    "wof:name":"Drobushevo",
    "wof:placetype":"locality"
},
  "geometry": {"coordinates":[33.06778,54.94722],"type":"Point"}
}