{
  "type": "Feature",
  "properties": {
    "gn:admin1_code":"41",
    "gn:asciiname":"Kapitonovka",
    "gn:country_code":"RU",
    "gn:dem":216,
    "gn:feature_class":"P",
    "gn:feature_code":"PPL",
    "gn:name":"Kapitonovka",
    "gn:population":0,
    "gn:timezone":"Europe/Moscow",
    "iso:country":"RU",
    "name:rus_x_preferred":[
        "\u041a\u0430\u043f\u0438\u0442\u043e\u043d\u043e\u0432\u043a\u0430"
    ],
    "name:und_x_variant":[
        "Kapitanovka",
        "Kapitonovka",
        "\u041a\u0430\u043f\u0438\u0442\u043e\u043d\u043e\u0432\u043a\u0430"
    ],
    "wof:name":"Kapitonovka",
    "wof:placetype":"locality"
},
  "geometry": {"coordinates":[36.86011,52.09675],"type":"Point"}
}