{
  "type": "Feature",
  "properties": {
    "gn:admin1_code":"8",
    "gn:asciiname":"Pen'kozavod",
    "gn:country_code":"RU",
    "gn:dem":104,
    "gn:feature_class":"P",
    "gn:feature_code":"PPL",
    "gn:name":"Pen\u2019kozavod",
    "gn:population":0,
    "gn:timezone":"Asia/Yekaterinburg",
    "iso:country":"RU",
    "name:rus_x_preferred":[
        "\u041f\u0435\u043d\u044c\u043a\u043e\u0437\u0430\u0432\u043e\u0434"
    ],
    "name:und_x_variant":[
        "Pen\u2019kozavod"
    ],
    "wof:name":"Pen'kozavod",
    "wof:placetype":"locality"
},
  "geometry": {"coordinates":[53.6997,55.0921],"type":"Point"}
}