{
  "type": "Feature",
  "properties": {
    "gn:admin1_code":"10.0",
    "gn:asciiname":"Dobrik",
    "gn:country_code":"RU",
    "gn:dem":198,
    "gn:feature_class":"P",
    "gn:feature_code":"PPL",
    "gn:name":"Dobrik",
    "gn:population":0,
    "gn:timezone":"Europe/Moscow",
    "iso:country":"RU",
    "name:eng_x_preferred":[
        "Dobrik"
    ],
    "name:nor_x_preferred":[
        "Dobrik"
    ],
    "name:rus_x_preferred":[
        "\u0414\u043e\u0431\u0440\u0438\u043a"
    ],
    "name:und_x_variant":[
        "\u0414\u043e\u0431\u0440\u0438\u043a",
        "Dobrik"
    ],
    "wof:name":"Dobrik",
    "wof:placetype":"locality"
},
  "geometry": {"coordinates":[34.75097,52.70591999999999],"type":"Point"}
}