{
  "type": "Feature",
  "properties": {
    "gn:admin1_code":"69",
    "gn:asciiname":"Filino",
    "gn:country_code":"RU",
    "gn:dem":254,
    "gn:feature_class":"P",
    "gn:feature_code":"PPL",
    "gn:name":"Filino",
    "gn:population":0,
    "gn:timezone":"Europe/Moscow",
    "iso:country":"RU",
    "name:rus_x_preferred":[
        "\u0424\u0438\u043b\u0438\u043d\u043e"
    ],
    "name:und_x_variant":[
        "\u0424\u0438\u043b\u0438\u043d\u043e"
    ],
    "wof:name":"Filino",
    "wof:placetype":"locality"
},
  "geometry": {"coordinates":[33.95139,55.31583000000001],"type":"Point"}
}