{
  "type": "Feature",
  "properties": {
    "gn:admin1_code":"73",
    "gn:asciiname":"Staroye Russkoye-Mamatkozino",
    "gn:country_code":"RU",
    "gn:dem":106,
    "gn:feature_class":"P",
    "gn:feature_code":"PPL",
    "gn:name":"Staroye Russkoye-Mamatkozino",
    "gn:population":0,
    "gn:timezone":"Europe/Moscow",
    "iso:country":"RU",
    "name:rus_x_preferred":[
        "\u0421\u0442\u0430\u0440\u043e\u0435 \u0420\u0443\u0441\u0441\u043a\u043e\u0435 \u041c\u0430\u043c\u0430\u0442\u043a\u043e\u0437\u0438\u043d\u043e"
    ],
    "name:und_x_variant":[
        "Krasnoye Mamatkozino",
        "Russkoye Mamatkozino",
        "Staroye Russkoye-Mamatkozino"
    ],
    "wof:name":"Staroye Russkoye-Mamatkozino",
    "wof:placetype":"locality"
},
  "geometry": {"coordinates":[48.78967,55.56124000000001],"type":"Point"}
}