{
  "type": "Feature",
  "properties": {
    "gn:admin1_code":"37",
    "gn:asciiname":"Kladovitsa",
    "gn:country_code":"RU",
    "gn:dem":189,
    "gn:feature_class":"P",
    "gn:feature_code":"PPL",
    "gn:name":"Kladovitsa",
    "gn:population":0,
    "gn:timezone":"Europe/Moscow",
    "iso:country":"RU",
    "name:rus_x_preferred":[
        "\u041a\u043b\u0430\u0434\u043e\u0432\u0438\u0446\u0430"
    ],
    "name:und_x_variant":[
        "\u041a\u043b\u0430\u0434\u043e\u0432\u0438\u0446\u0430"
    ],
    "wof:name":"Kladovitsa",
    "wof:placetype":"locality"
},
  "geometry": {"coordinates":[46.0547,59.0511],"type":"Point"}
}