{
  "type": "Feature",
  "properties": {
    "gn:admin1_code":"33",
    "gn:asciiname":"Letovtsy",
    "gn:country_code":"RU",
    "gn:dem":170,
    "gn:feature_class":"P",
    "gn:feature_code":"PPL",
    "gn:name":"Letovtsy",
    "gn:population":0,
    "gn:timezone":"Europe/Kirov",
    "iso:country":"RU",
    "name:rus_x_preferred":[
        "\u041b\u0435\u0442\u043e\u0432\u0446\u044b"
    ],
    "name:und_x_variant":[
        "Letovo",
        "Letovtsy",
        "\u041b\u0435\u0442\u043e\u0432\u0446\u044b"
    ],
    "wof:name":"Letovtsy",
    "wof:placetype":"locality"
},
  "geometry": {"coordinates":[50.34473,58.3409],"type":"Point"}
}