{
  "type": "Feature",
  "properties": {
    "gn:admin1_code":"7.0",
    "gn:asciiname":"Khaton Yargis",
    "gn:country_code":"RU",
    "gn:dem":-23,
    "gn:feature_class":"P",
    "gn:feature_code":"PPL",
    "gn:name":"Khaton Yargis",
    "gn:population":0,
    "gn:timezone":"Europe/Astrakhan",
    "iso:country":"RU",
    "name:rus_x_preferred":[
        "\u0425\u0430\u0442\u043e\u043d \u042f\u0440\u0433\u0438\u0441"
    ],
    "wof:name":"Khaton Yargis",
    "wof:placetype":"locality"
},
  "geometry": {"coordinates":[47.62028,46.97722],"type":"Point"}
}