{
  "type": "Feature",
  "properties": {
    "gn:admin1_code":"70.0",
    "gn:asciiname":"Krasnaya Polyana",
    "gn:country_code":"RU",
    "gn:dem":270,
    "gn:feature_class":"P",
    "gn:feature_code":"PPL",
    "gn:name":"Krasnaya Polyana",
    "gn:population":0,
    "gn:timezone":"Europe/Moscow",
    "iso:country":"RU",
    "wof:name":"Krasnaya Polyana",
    "wof:placetype":"locality"
},
  "geometry": {"coordinates":[42.29667,45.18056],"type":"Point"}
}