{
  "type": "Feature",
  "properties": {
    "gn:admin1_code":"76",
    "gn:asciiname":"Shakhta Nomer Trinadtsat'",
    "gn:country_code":"RU",
    "gn:dem":183,
    "gn:feature_class":"P",
    "gn:feature_code":"PPL",
    "gn:name":"Shakhta Nomer Trinadtsat\u2019",
    "gn:population":0,
    "gn:timezone":"Europe/Moscow",
    "iso:country":"RU",
    "name:rus_x_preferred":[
        "\u0428\u0430\u0445\u0442\u0430 \u041d\u043e\u043c\u0435\u0440 \u0422\u0440\u0438\u043d\u0430\u0434\u0446\u0430\u0442\u044c"
    ],
    "name:und_x_variant":[
        "Shakhta Nomer Trinadtsat\u2019",
        "\u0428\u0430\u0445\u0442\u0430 \u041d\u043e\u043c\u0435\u0440 \u0422\u0440\u0438\u043d\u0430\u0434\u0446\u0430\u0442\u044c"
    ],
    "wof:name":"Shakhta Nomer Trinadtsat'",
    "wof:placetype":"locality"
},
  "geometry": {"coordinates":[38.3672,53.9968],"type":"Point"}
}