{
  "type": "Feature",
  "properties": {
    "gn:admin1_code":"61",
    "gn:asciiname":"Krasnopartizanskiy",
    "gn:country_code":"RU",
    "gn:dem":36,
    "gn:feature_class":"P",
    "gn:feature_code":"PPL",
    "gn:name":"Krasnopartizanskiy",
    "gn:population":0,
    "gn:timezone":"Europe/Moscow",
    "iso:country":"RU",
    "name:eng_x_preferred":[
        "Krasnopartizanskiy"
    ],
    "name:nor_x_preferred":[
        "Krasnopartizanskij"
    ],
    "name:rus_x_preferred":[
        "\u041a\u0440\u0430\u0441\u043d\u043e\u043f\u0430\u0440\u0442\u0438\u0437\u0430\u043d\u0441\u043a\u0438\u0439"
    ],
    "name:und_x_variant":[
        "Krasnyy Partizan",
        "\u041a\u0440\u0430\u0441\u043d\u043e\u043f\u0430\u0440\u0442\u0438\u0437\u0430\u043d\u0441\u043a\u0438\u0439",
        "Krasnopartizanskiy"
    ],
    "wof:name":"Krasnopartizanskiy",
    "wof:placetype":"locality"
},
  "geometry": {"coordinates":[43.1515,46.3421],"type":"Point"}
}