{
  "type": "Feature",
  "properties": {
    "gn:admin1_code":"52",
    "gn:asciiname":"Mitrokhnovo",
    "gn:country_code":"RU",
    "gn:dem":77,
    "gn:feature_class":"P",
    "gn:feature_code":"PPL",
    "gn:name":"Mitrokhnovo",
    "gn:population":0,
    "gn:timezone":"Europe/Moscow",
    "iso:country":"RU",
    "name:rus_x_preferred":[
        "\u041c\u0438\u0442\u0440\u043e\u0445\u043d\u043e\u0432\u043e"
    ],
    "wof:name":"Mitrokhnovo",
    "wof:placetype":"locality"
},
  "geometry": {"coordinates":[30.41667,58.68333000000001],"type":"Point"}
}