{
  "type": "Feature",
  "properties": {
    "gn:admin1_code":"85.0",
    "gn:asciiname":"Sboyevskaya",
    "gn:country_code":"RU",
    "gn:dem":108,
    "gn:feature_class":"P",
    "gn:feature_code":"PPL",
    "gn:name":"Sboyevskaya",
    "gn:population":0,
    "gn:timezone":"Europe/Moscow",
    "iso:country":"RU",
    "name:rus_x_preferred":[
        "\u0421\u0431\u043e\u0435\u0432\u0441\u043a\u0430\u044f"
    ],
    "wof:name":"Sboyevskaya",
    "wof:placetype":"locality"
},
  "geometry": {"coordinates":[41.684,60.8059],"type":"Point"}
}