{
  "type": "Feature",
  "properties": {
    "gn:admin1_code":"47.0",
    "gn:asciiname":"Chichevo",
    "gn:country_code":"RU",
    "gn:dem":126,
    "gn:feature_class":"P",
    "gn:feature_code":"PPL",
    "gn:name":"Chichevo",
    "gn:population":0,
    "gn:timezone":"Europe/Moscow",
    "iso:country":"RU",
    "name:rus_x_preferred":[
        "\u0427\u0438\u0447\u0435\u0432\u043e"
    ],
    "name:und_x_variant":[
        "Chitsova",
        "Chichevo",
        "\u0427\u0438\u0447\u0435\u0432\u043e"
    ],
    "wof:name":"Chichevo",
    "wof:placetype":"locality"
},
  "geometry": {"coordinates":[38.90225,55.42685],"type":"Point"}
}