{
  "type": "Feature",
  "properties": {
    "gn:admin1_code":"29",
    "gn:asciiname":"Igaza",
    "gn:country_code":"RU",
    "gn:dem":271,
    "gn:feature_class":"P",
    "gn:feature_code":"PPL",
    "gn:name":"Igaza",
    "gn:population":0,
    "gn:timezone":"Asia/Novokuznetsk",
    "iso:country":"RU",
    "name:rus_x_preferred":[
        "\u0418\u0433\u0430\u0437\u0430"
    ],
    "wof:name":"Igaza",
    "wof:placetype":"locality"
},
  "geometry": {"coordinates":[87.6726,53.7117],"type":"Point"}
}