{
  "type": "Feature",
  "properties": {
    "gn:admin1_code":"61.0",
    "gn:asciiname":"Krinichnyy",
    "gn:country_code":"RU",
    "gn:dem":28,
    "gn:feature_class":"P",
    "gn:feature_code":"PPL",
    "gn:name":"Krinichnyy",
    "gn:population":0,
    "gn:timezone":"Europe/Moscow",
    "iso:country":"RU",
    "name:rus_x_preferred":[
        "\u041a\u0440\u0438\u043d\u0438\u0447\u043d\u044b\u0439"
    ],
    "name:und_x_variant":[
        "Krinichyy",
        "Krinichnyy"
    ],
    "wof:name":"Krinichnyy",
    "wof:placetype":"locality"
},
  "geometry": {"coordinates":[38.96389,47.62982],"type":"Point"}
}