{
  "type": "Feature",
  "properties": {
    "gn:admin1_code":"42",
    "gn:asciiname":"Komsomol'skoye",
    "gn:country_code":"RU",
    "gn:dem":18,
    "gn:feature_class":"P",
    "gn:feature_code":"PPL",
    "gn:name":"Komsomol\u2019skoye",
    "gn:population":0,
    "gn:timezone":"Europe/Moscow",
    "iso:country":"RU",
    "name:eng_x_preferred":[
        "Komsomol'skoye"
    ],
    "name:fin_x_preferred":[
        "Kilpeenjoki"
    ],
    "name:nor_x_preferred":[
        "Komsomolskoje"
    ],
    "name:rus_x_preferred":[
        "\u041a\u043e\u043c\u0441\u043e\u043c\u043e\u043b\u044c\u0441\u043a\u043e\u0435"
    ],
    "name:und_x_variant":[
        "Komsomol\u2019skoye",
        "Kilpenyoki"
    ],
    "wof:name":"Komsomol'skoye",
    "wof:placetype":"locality"
},
  "geometry": {"coordinates":[28.80509,60.87232],"type":"Point"}
}