{
  "type": "Feature",
  "properties": {
    "gn:admin1_code":"57",
    "gn:asciiname":"Novoye Porzovo",
    "gn:cc2":"RU",
    "gn:country_code":"RU",
    "gn:dem":204,
    "gn:feature_class":"P",
    "gn:feature_code":"PPL",
    "gn:name":"Novoye Porzovo",
    "gn:population":0,
    "gn:timezone":"Europe/Moscow",
    "iso:country":"RU",
    "name:rus_x_preferred":[
        "\u041d\u043e\u0432\u043e\u0435 \u041f\u043e\u0440\u0437\u043e\u0432\u043e"
    ],
    "name:und_x_variant":[
        "Novaya Porzovka",
        "Novoye Porzovo"
    ],
    "wof:name":"Novoye Porzovo",
    "wof:placetype":"locality"
},
  "geometry": {"coordinates":[46.03333,52.63333000000001],"type":"Point"}
}