{
  "type": "Feature",
  "properties": {
    "gn:admin1_code":"37",
    "gn:asciiname":"Sergeyevskaya",
    "gn:country_code":"RU",
    "gn:dem":103,
    "gn:feature_class":"P",
    "gn:feature_code":"PPL",
    "gn:name":"Sergeyevskaya",
    "gn:population":0,
    "gn:timezone":"Europe/Moscow",
    "iso:country":"RU",
    "name:rus_x_preferred":[
        "\u0421\u0435\u0440\u0433\u0435\u0435\u0432\u0441\u043a\u0430\u044f"
    ],
    "name:und_x_variant":[
        "Sergiyevskaya",
        "Sergeyevskaya",
        "\u0421\u0435\u0440\u0433\u0435\u0435\u0432\u0441\u043a\u0430\u044f"
    ],
    "wof:name":"Sergeyevskaya",
    "wof:placetype":"locality"
},
  "geometry": {"coordinates":[42.83045,57.41794],"type":"Point"}
}