{
  "type": "Feature",
  "properties": {
    "gn:admin1_code":"69",
    "gn:asciiname":"Peshchiki",
    "gn:country_code":"RU",
    "gn:dem":195,
    "gn:feature_class":"P",
    "gn:feature_code":"PPL",
    "gn:name":"Peshchiki",
    "gn:population":0,
    "gn:timezone":"Europe/Moscow",
    "iso:country":"RU",
    "name:eng_x_preferred":[
        "Peshchiki"
    ],
    "name:nor_x_preferred":[
        "Pesjtsjiki"
    ],
    "name:rus_x_preferred":[
        "\u041f\u0435\u0449\u0438\u043a\u0438"
    ],
    "name:und_x_variant":[
        "Peshchik"
    ],
    "wof:name":"Peshchiki",
    "wof:placetype":"locality"
},
  "geometry": {"coordinates":[32.927,54.0488],"type":"Point"}
}