{
  "type": "Feature",
  "properties": {
    "gn:admin1_code":"86.0",
    "gn:asciiname":"Afonovka",
    "gn:country_code":"RU",
    "gn:dem":136,
    "gn:feature_class":"P",
    "gn:feature_code":"PPL",
    "gn:name":"Afonovka",
    "gn:population":0,
    "gn:timezone":"Europe/Moscow",
    "iso:country":"RU",
    "name:nor_x_preferred":[
        "Afonovka"
    ],
    "name:rus_x_preferred":[
        "\u0410\u0444\u043e\u043d\u043e\u0432\u043a\u0430"
    ],
    "wof:name":"Afonovka",
    "wof:placetype":"locality"
},
  "geometry": {"coordinates":[40.78528,51.3725],"type":"Point"}
}