{
  "type": "Feature",
  "properties": {
    "gn:admin1_code":"52",
    "gn:asciiname":"Laptevo",
    "gn:cc2":"RU",
    "gn:country_code":"RU",
    "gn:dem":226,
    "gn:feature_class":"P",
    "gn:feature_code":"PPL",
    "gn:name":"Lapt\u00ebvo",
    "gn:population":0,
    "gn:timezone":"Europe/Moscow",
    "iso:country":"RU",
    "name:rus_x_preferred":[
        "\u041b\u0430\u043f\u0442\u0451\u0432\u043e"
    ],
    "name:und_x_variant":[
        "Lapteva",
        "Lapt\u00ebvo",
        "\u041b\u0430\u043f\u0442\u0451\u0432\u043e"
    ],
    "wof:name":"Laptevo",
    "wof:placetype":"locality"
},
  "geometry": {"coordinates":[32.18333,57.21666999999999],"type":"Point"}
}