{
  "type": "Feature",
  "properties": {
    "gn:admin1_code":"38",
    "gn:asciiname":"Novopovlovskiy",
    "gn:country_code":"RU",
    "gn:dem":113,
    "gn:feature_class":"P",
    "gn:feature_code":"PPL",
    "gn:name":"Novopovlovskiy",
    "gn:population":0,
    "gn:timezone":"Europe/Moscow",
    "iso:country":"RU",
    "name:rus_x_preferred":[
        "\u041d\u043e\u0432\u043e\u043f\u043e\u0432\u043b\u043e\u0432\u0441\u043a\u0438\u0439"
    ],
    "name:und_x_variant":[
        "\u041d\u043e\u0432\u043e\u043f\u043e\u0432\u043b\u043e\u0432\u0441\u043a\u0438\u0439"
    ],
    "wof:name":"Novopovlovskiy",
    "wof:placetype":"locality"
},
  "geometry": {"coordinates":[40.71472,45.245],"type":"Point"}
}