{
  "type": "Feature",
  "properties": {
    "gn:admin1_code":"25",
    "gn:asciiname":"Kurilovo",
    "gn:country_code":"RU",
    "gn:dem":168,
    "gn:feature_class":"P",
    "gn:feature_code":"PPL",
    "gn:name":"Kurilovo",
    "gn:population":0,
    "gn:timezone":"Europe/Moscow",
    "iso:country":"RU",
    "name:rus_x_preferred":[
        "\u041a\u0443\u0440\u0438\u043b\u043e\u0432\u043e"
    ],
    "name:rus_x_variant":[
        "\u0421\u0435\u0440\u043f\u0443\u0445\u043e\u0432-15"
    ],
    "name:und_x_variant":[
        "\u041a\u0443\u0440\u0438\u043b\u043e\u0432\u043e"
    ],
    "wof:name":"Kurilovo",
    "wof:placetype":"locality"
},
  "geometry": {"coordinates":[37.01694000000001,55.08917],"type":"Point"}
}