{
  "type": "Feature",
  "properties": {
    "gn:admin1_code":"11",
    "gn:asciiname":"Gakhan",
    "gn:country_code":"RU",
    "gn:dem":536,
    "gn:feature_class":"P",
    "gn:feature_code":"PPL",
    "gn:name":"Gakhan",
    "gn:population":0,
    "gn:timezone":"Asia/Irkutsk",
    "iso:country":"RU",
    "name:rus_x_preferred":[
        "\u0413\u0430\u0445\u0430\u043d"
    ],
    "name:und_x_variant":[
        "Ulus Gakhan",
        "Gakhan",
        "\u0413\u0430\u0445\u0430\u043d"
    ],
    "wof:name":"Gakhan",
    "wof:placetype":"locality"
},
  "geometry": {"coordinates":[110.852,54.70117],"type":"Point"}
}