{
  "type": "Feature",
  "properties": {
    "gn:admin1_code":"60",
    "gn:asciiname":"Sredneye",
    "gn:country_code":"RU",
    "gn:dem":94,
    "gn:feature_class":"P",
    "gn:feature_code":"PPL",
    "gn:name":"Sredneye",
    "gn:population":0,
    "gn:timezone":"Europe/Moscow",
    "iso:country":"RU",
    "name:rus_x_preferred":[
        "\u0421\u0440\u0435\u0434\u043d\u0435\u0435"
    ],
    "name:und_x_variant":[
        "\u0421\u0440\u0435\u0434\u043d\u0435\u0435"
    ],
    "wof:name":"Sredneye",
    "wof:placetype":"locality"
},
  "geometry": {"coordinates":[30.46163,56.86104],"type":"Point"}
}