{
  "type": "Feature",
  "properties": {
    "gn:admin1_code":"53",
    "gn:asciiname":"Rozhdestvenskiy",
    "gn:country_code":"RU",
    "gn:dem":114,
    "gn:feature_class":"P",
    "gn:feature_code":"PPL",
    "gn:name":"Rozhdestvenskiy",
    "gn:population":0,
    "gn:timezone":"Asia/Novosibirsk",
    "iso:country":"RU",
    "name:eng_x_preferred":[
        "Rozhdestvenskiy"
    ],
    "name:nor_x_preferred":[
        "Rozjdestvenskij"
    ],
    "name:rus_x_preferred":[
        "\u0420\u043e\u0436\u0434\u0435\u0441\u0442\u0432\u0435\u043d\u0441\u043a\u0438\u0439"
    ],
    "wof:name":"Rozhdestvenskiy",
    "wof:placetype":"locality"
},
  "geometry": {"coordinates":[78.57944000000001,54.10189],"type":"Point"}
}