{
  "type": "Feature",
  "properties": {
    "gn:admin1_code":"67",
    "gn:asciiname":"Slantsevyy Rudnik",
    "gn:country_code":"RU",
    "gn:dem":93,
    "gn:feature_class":"P",
    "gn:feature_code":"PPL",
    "gn:name":"Slantsevyy Rudnik",
    "gn:population":0,
    "gn:timezone":"Europe/Saratov",
    "iso:country":"RU",
    "name:eng_x_preferred":[
        "Slantsevyy Rudnik"
    ],
    "name:nor_x_preferred":[
        "Slantsevyj Rudnik"
    ],
    "name:rus_x_preferred":[
        "\u0421\u043b\u0430\u043d\u0446\u0435\u0432\u044b\u0439 \u0420\u0443\u0434\u043d\u0438\u043a"
    ],
    "name:und_x_variant":[
        "\u0421\u043b\u0430\u043d\u0446\u0435\u0432\u044b\u0439 \u0420\u0443\u0434\u043d\u0438\u043a",
        "Slantsevyy Rudnik"
    ],
    "wof:name":"Slantsevyy Rudnik",
    "wof:placetype":"locality"
},
  "geometry": {"coordinates":[49.6427,51.1642],"type":"Point"}
}