{
  "type": "Feature",
  "properties": {
    "gn:admin1_code":"05",
    "gn:asciiname":"Pervyye Vybory v Verkhovnyy Sovet",
    "gn:country_code":"RU",
    "gn:dem":607,
    "gn:feature_class":"P",
    "gn:feature_code":"PPL",
    "gn:name":"Pervyye Vybory v Verkhovnyy Sovet",
    "gn:population":0,
    "gn:timezone":"Asia/Yakutsk",
    "iso:country":"RU",
    "name:rus_x_preferred":[
        "\u041f\u0435\u0440\u0432\u044b\u0435 \u0412\u044b\u0431\u043e\u0440\u044b \u0432 \u0412\u0435\u0440\u0445\u043e\u0432\u043d\u044b\u0439 \u0421\u043e\u0432\u0435\u0442"
    ],
    "name:und_x_variant":[
        "\u041f\u0435\u0440\u0432\u044b\u0435 \u0412\u044b\u0431\u043e\u0440\u044b \u0432 \u0412\u0435\u0440\u0445\u043e\u0432\u043d\u044b\u0439 \u0421\u043e\u0432\u0435\u0442"
    ],
    "wof:name":"Pervyye Vybory v Verkhovnyy Sovet",
    "wof:placetype":"locality"
},
  "geometry": {"coordinates":[121.06667,56.88333000000001],"type":"Point"}
}