{
  "type": "Feature",
  "properties": {
    "gn:admin1_code":"25.0",
    "gn:asciiname":"Domantsevo",
    "gn:country_code":"RU",
    "gn:dem":216,
    "gn:feature_class":"P",
    "gn:feature_code":"PPL",
    "gn:name":"Domantsevo",
    "gn:population":0,
    "gn:timezone":"Europe/Moscow",
    "iso:country":"RU",
    "name:rus_x_preferred":[
        "\u0414\u043e\u043c\u0430\u043d\u0446\u0435\u0432\u043e"
    ],
    "name:und_x_variant":[
        "Damantseva",
        "Domashnevo",
        "Domantsevo",
        "\u0414\u043e\u043c\u0430\u043d\u0446\u0435\u0432\u043e"
    ],
    "wof:name":"Domantsevo",
    "wof:placetype":"locality"
},
  "geometry": {"coordinates":[35.54155,54.98979],"type":"Point"}
}