{
  "type": "Feature",
  "properties": {
    "gn:admin1_code":"86.0",
    "gn:asciiname":"Beshchiy",
    "gn:country_code":"RU",
    "gn:dem":174,
    "gn:feature_class":"P",
    "gn:feature_code":"PPL",
    "gn:name":"Beshchiy",
    "gn:population":0,
    "gn:timezone":"Europe/Moscow",
    "iso:country":"RU",
    "name:nor_x_preferred":[
        "Besjtsjij"
    ],
    "name:rus_x_preferred":[
        "\u0411\u0435\u0449\u0438\u0439"
    ],
    "wof:name":"Beshchiy",
    "wof:placetype":"locality"
},
  "geometry": {"coordinates":[39.51238,50.28987],"type":"Point"}
}