{
  "type": "Feature",
  "properties": {
    "gn:admin1_code":"45",
    "gn:asciiname":"Kuzhnur",
    "gn:country_code":"RU",
    "gn:dem":150,
    "gn:feature_class":"P",
    "gn:feature_code":"PPL",
    "gn:name":"Kuzhnur",
    "gn:population":0,
    "gn:timezone":"Europe/Moscow",
    "iso:country":"RU",
    "name:rus_x_preferred":[
        "\u041a\u0443\u0436\u043d\u0443\u0440"
    ],
    "name:und_x_variant":[
        "\u041a\u0443\u0436\u043d\u0443\u0440"
    ],
    "wof:name":"Kuzhnur",
    "wof:placetype":"locality"
},
  "geometry": {"coordinates":[48.6933,57.0469],"type":"Point"}
}