{
  "type": "Feature",
  "properties": {
    "gn:admin1_code":"57",
    "gn:asciiname":"Skvorechnoye",
    "gn:country_code":"RU",
    "gn:dem":159,
    "gn:feature_class":"P",
    "gn:feature_code":"PPL",
    "gn:name":"Skvorechnoye",
    "gn:population":0,
    "gn:timezone":"Europe/Moscow",
    "iso:country":"RU",
    "name:eng_x_preferred":[
        "Skvorechnoye"
    ],
    "name:nor_x_preferred":[
        "Skvoretsjnoje"
    ],
    "name:rus_x_preferred":[
        "\u0421\u043a\u0432\u043e\u0440\u0435\u0447\u043d\u043e\u0435"
    ],
    "wof:name":"Skvorechnoye",
    "wof:placetype":"locality"
},
  "geometry": {"coordinates":[43.94444,53.35028000000001],"type":"Point"}
}