{
  "type": "Feature",
  "properties": {
    "gn:admin1_code":"77",
    "gn:asciiname":"Pogorelka",
    "gn:country_code":"RU",
    "gn:dem":186,
    "gn:feature_class":"P",
    "gn:feature_code":"PPL",
    "gn:name":"Pogorelka",
    "gn:population":0,
    "gn:timezone":"Europe/Moscow",
    "iso:country":"RU",
    "name:rus_x_preferred":[
        "\u041f\u043e\u0433\u043e\u0440\u0435\u043b\u043a\u0430"
    ],
    "wof:name":"Pogorelka",
    "wof:placetype":"locality"
},
  "geometry": {"coordinates":[35.41667,58.03333000000001],"type":"Point"}
}