{
  "type": "Feature",
  "properties": {
    "gn:admin1_code":"84",
    "gn:asciiname":"Yaryzhenskiy",
    "gn:country_code":"RU",
    "gn:dem":82,
    "gn:feature_class":"P",
    "gn:feature_code":"PPL",
    "gn:name":"Yaryzhenskiy",
    "gn:population":0,
    "gn:timezone":"Europe/Volgograd",
    "iso:country":"RU",
    "name:eng_x_preferred":[
        "Yaryzhenskiy"
    ],
    "name:nor_x_preferred":[
        "Jaryzjenskij"
    ],
    "name:rus_x_preferred":[
        "\u042f\u0440\u044b\u0436\u0435\u043d\u0441\u043a\u0438\u0439"
    ],
    "wof:name":"Yaryzhenskiy",
    "wof:placetype":"locality"
},
  "geometry": {"coordinates":[42.4723,50.5146],"type":"Point"}
}