{
  "type": "Feature",
  "properties": {
    "gn:admin1_code":"52",
    "gn:asciiname":"Sivokha",
    "gn:country_code":"RU",
    "gn:dem":41,
    "gn:feature_class":"P",
    "gn:feature_code":"PPL",
    "gn:name":"Sivokha",
    "gn:population":0,
    "gn:timezone":"Europe/Moscow",
    "iso:country":"RU",
    "name:rus_x_preferred":[
        "\u0421\u0438\u0432\u043e\u0445\u0430"
    ],
    "name:und_x_variant":[
        "\u0421\u0438\u0432\u043e\u0445\u0430"
    ],
    "wof:name":"Sivokha",
    "wof:placetype":"locality"
},
  "geometry": {"coordinates":[30.21667,58.05],"type":"Point"}
}