{
  "type": "Feature",
  "properties": {
    "gn:admin1_code":"52",
    "gn:asciiname":"Khoromy",
    "gn:country_code":"RU",
    "gn:dem":105,
    "gn:feature_class":"P",
    "gn:feature_code":"PPL",
    "gn:name":"Khoromy",
    "gn:population":0,
    "gn:timezone":"Europe/Moscow",
    "iso:country":"RU",
    "name:nor_x_preferred":[
        "Khoromy"
    ],
    "name:rus_x_preferred":[
        "\u0425\u043e\u0440\u043e\u043c\u044b"
    ],
    "wof:name":"Khoromy",
    "wof:placetype":"locality"
},
  "geometry": {"coordinates":[33.78161,58.38781],"type":"Point"}
}