{
  "type": "Feature",
  "properties": {
    "gn:admin1_code":"85",
    "gn:asciiname":"Lomok",
    "gn:country_code":"RU",
    "gn:dem":156,
    "gn:feature_class":"P",
    "gn:feature_code":"PPL",
    "gn:name":"Lomok",
    "gn:population":0,
    "gn:timezone":"Europe/Moscow",
    "iso:country":"RU",
    "name:rus_x_preferred":[
        "\u041b\u043e\u043c\u043e\u043a"
    ],
    "name:und_x_variant":[
        "\u041b\u043e\u043c\u043e\u043a"
    ],
    "wof:name":"Lomok",
    "wof:placetype":"locality"
},
  "geometry": {"coordinates":[39.96281,59.01436],"type":"Point"}
}