{
  "type": "Feature",
  "properties": {
    "gn:admin1_code":"17",
    "gn:asciiname":"Tsmur",
    "gn:country_code":"RU",
    "gn:dem":649,
    "gn:feature_class":"P",
    "gn:feature_code":"PPL",
    "gn:name":"Tsmur",
    "gn:population":0,
    "gn:timezone":"Europe/Moscow",
    "iso:country":"RU",
    "name:eng_x_preferred":[
        "Tsmur"
    ],
    "name:nor_x_preferred":[
        "Tsmur"
    ],
    "name:rus_x_preferred":[
        "\u0426\u043c\u0443\u0440"
    ],
    "wof:name":"Tsmur",
    "wof:placetype":"locality"
},
  "geometry": {"coordinates":[48.05438,41.68363],"type":"Point"}
}