{
  "type": "Feature",
  "properties": {
    "gn:country":"RU",
    "gn:fcode":"PPL",
    "gn:pop":10833,
    "iso:country":"RU",
    "name:ara_x_preferred":[
        "\u0633\u0648\u064a\u0627\u0631\u0641\u064a"
    ],
    "name:azb_x_preferred":[
        "\u0633\u0648\u06cc\u0627\u0631\u0648\u06cc"
    ],
    "name:bel_x_preferred":[
        "\u0421\u0443\u0430\u044f\u0440\u0432\u0456"
    ],
    "name:che_x_preferred":[
        "\u0421\u0443\u043e\u044f\u0440\u0432\u0438"
    ],
    "name:chi_x_preferred":[
        "\u8607\u5967\u8036\u723e\u7dad"
    ],
    "name:dut_x_preferred":[
        "Soeojarvi"
    ],
    "name:eng_x_preferred":[
        "Suoyarvi"
    ],
    "name:epo_x_preferred":[
        "Suojarvi"
    ],
    "name:est_x_preferred":[
        "Suoj\u00e4rvi"
    ],
    "name:fin_x_preferred":[
        "Suoj\u00e4rvi"
    ],
    "name:fin_x_variant":[
        "Suvilahti"
    ],
    "name:fre_x_preferred":[
        "Souo\u00efarvi"
    ],
    "name:ger_x_preferred":[
        "Suojarwi"
    ],
    "name:hsb_x_preferred":[
        "Suojarwi"
    ],
    "name:ita_x_preferred":[
        "Suojarvi"
    ],
    "name:jpn_x_preferred":[
        "\u30b9\u30fc\u30aa\u30e4\u30eb\u30f4\u30a3"
    ],
    "name:krl_x_preferred":[
        "Suoj\u00e4rvi"
    ],
    "name:krl_x_variant":[
        "\u0160uoj\u00e4rvi"
    ],
    "name:lav_x_preferred":[
        "Suojarvi"
    ],
    "name:nno_x_preferred":[
        "Suojarvi"
    ],
    "name:nob_x_preferred":[
        "Suojarvi"
    ],
    "name:nor_x_preferred":[
        "Suojarvi"
    ],
    "name:olo_x_preferred":[
        "Suoj\u00e4rvi"
    ],
    "name:per_x_preferred":[
        "\u0633\u0648\u06cc\u0627\u0631\u0648\u06cc"
    ],
    "name:pol_x_preferred":[
        "Suojarwi"
    ],
    "name:rus_x_preferred":[
        "\u0421\u0443\u043e\u044f\u0440\u0432\u0438"
    ],
    "name:sco_x_preferred":[
        "Suoyarvi"
    ],
    "name:srp_x_preferred":[
        "\u0421\u0443\u043e\u0458\u0430\u0440\u0432\u0438"
    ],
    "name:swe_x_preferred":[
        "Suoj\u00e4rvi"
    ],
    "name:tat_x_preferred":[
        "\u0421\u0443\u043e\u044f\u0440\u0432\u0438"
    ],
    "name:tgl_x_preferred":[
        "Suoyarvi"
    ],
    "name:tur_x_preferred":[
        "Suoyarvi"
    ],
    "name:ukr_x_preferred":[
        "\u0421\u0443\u043e\u044f\u0440\u0432\u0456"
    ],
    "name:unk_x_variant":[
        "Suvilakhta"
    ],
    "name:vep_x_preferred":[
        "Soj\u00e4rv"
    ],
    "name:war_x_preferred":[
        "Suoyarvi"
    ],
    "qs:name":"Suoyarvi",
    "qs:photos_9r":0,
    "qs:photos_sr":0,
    "qs:pop_sr":"6",
    "wd:wordcount":1071,
    "wof:name":"Suoyarvi",
    "wof:placetype":"locality",
    "wof:population":10833
},
  "geometry": {"coordinates":[32.35,62.08333],"type":"Point"}
}