{
  "type": "Feature",
  "properties": {
    "gn:admin1_code":"60",
    "gn:asciiname":"Mochalkovo",
    "gn:country_code":"RU",
    "gn:dem":111,
    "gn:feature_class":"P",
    "gn:feature_code":"PPL",
    "gn:name":"Mochalkovo",
    "gn:population":0,
    "gn:timezone":"Europe/Moscow",
    "iso:country":"RU",
    "name:rus_x_preferred":[
        "\u041c\u043e\u0447\u0430\u043b\u043a\u043e\u0432\u043e"
    ],
    "wof:name":"Mochalkovo",
    "wof:placetype":"locality"
},
  "geometry": {"coordinates":[28.7981,56.5302],"type":"Point"}
}