{
  "type": "Feature",
  "properties": {
    "gn:admin1_code":"56",
    "gn:asciiname":"Ovechiy Verkhniy",
    "gn:country_code":"RU",
    "gn:dem":216,
    "gn:feature_class":"P",
    "gn:feature_code":"PPL",
    "gn:name":"Ovechiy Verkhniy",
    "gn:population":0,
    "gn:timezone":"Europe/Moscow",
    "iso:country":"RU",
    "name:rus_x_preferred":[
        "\u041e\u0432\u0435\u0447\u0438\u0439 \u0412\u0435\u0440\u0445\u043d\u0438\u0439"
    ],
    "wof:name":"Ovechiy Verkhniy",
    "wof:placetype":"locality"
},
  "geometry": {"coordinates":[37.53091,52.28317],"type":"Point"}
}