{
  "type": "Feature",
  "properties": {
    "gn:admin1_code":"41.0",
    "gn:asciiname":"Berezovo-Kolodez'",
    "gn:country_code":"RU",
    "gn:dem":217,
    "gn:feature_class":"P",
    "gn:feature_code":"PPL",
    "gn:name":"Ber\u00ebzovo-Kolodez\u2019",
    "gn:population":0,
    "gn:timezone":"Europe/Moscow",
    "iso:country":"RU",
    "name:nor_x_preferred":[
        "Berjozovo-Kolodez"
    ],
    "name:rus_x_preferred":[
        "\u0411\u0435\u0440\u0451\u0437\u043e\u0432\u043e-\u041a\u043e\u043b\u043e\u0434\u0435\u0437\u044c"
    ],
    "name:und_x_variant":[
        "Ber\u00ebzovo-Kolodez\u2019"
    ],
    "wof:name":"Berezovo-Kolodez'",
    "wof:placetype":"locality"
},
  "geometry": {"coordinates":[38.2458,51.4188],"type":"Point"}
}