{
  "type": "Feature",
  "properties": {
    "gn:country":"RU",
    "gn:fcode":"PPL",
    "gn:pop":0,
    "iso:country":"RU",
    "name:eng_x_preferred":[
        "Gorodishchi"
    ],
    "name:nor_x_preferred":[
        "Gorodisjtsji"
    ],
    "name:rus_x_preferred":[
        "\u0413\u043e\u0440\u043e\u0434\u0438\u0449\u0438"
    ],
    "name:unk_x_variant":[
        "\u0413\u043e\u0440\u043e\u0434\u0438\u0449\u0438"
    ],
    "qs:name":"Gorodishchi",
    "qs:name_adm0":"Russia",
    "qs:name_adm1":"Vladimir Oblast",
    "qs:photos_9k":1,
    "qs:photos_9r":1,
    "qs:photos_all":1,
    "qs:photos_sr":0,
    "qs:placetype":"Town",
    "qs:pop_sr":"0",
    "wof:name":"Gorodishchi",
    "wof:placetype":"locality",
    "wof:population":0
},
  "geometry": {"coordinates":[39.08457,55.86765],"type":"Point"}
}