{
  "type": "Feature",
  "properties": {
    "gn:admin1_code":"42",
    "gn:asciiname":"Voypola",
    "gn:country_code":"RU",
    "gn:dem":45,
    "gn:feature_class":"P",
    "gn:feature_code":"PPL",
    "gn:name":"Voypola",
    "gn:population":0,
    "gn:timezone":"Europe/Moscow",
    "iso:country":"RU",
    "name:fin_x_preferred":[
        "Voipakkola"
    ],
    "wof:name":"Voypola",
    "wof:placetype":"locality"
},
  "geometry": {"coordinates":[31.69086,59.8723],"type":"Point"}
}