{
  "type": "Feature",
  "properties": {
    "gn:admin1_code":"10",
    "gn:asciiname":"Boyevik",
    "gn:country_code":"RU",
    "gn:dem":157,
    "gn:feature_class":"P",
    "gn:feature_code":"PPL",
    "gn:name":"Boyevik",
    "gn:population":0,
    "gn:timezone":"Europe/Moscow",
    "iso:country":"RU",
    "name:rus_x_preferred":[
        "\u0411\u043e\u0435\u0432\u0438\u043a"
    ],
    "wof:name":"Boyevik",
    "wof:placetype":"locality"
},
  "geometry": {"coordinates":[33.1253,52.3429],"type":"Point"}
}