{
  "type": "Feature",
  "properties": {
    "gn:admin1_code":"37",
    "gn:asciiname":"Reutikha",
    "gn:country_code":"RU",
    "gn:dem":143,
    "gn:feature_class":"P",
    "gn:feature_code":"PPL",
    "gn:name":"Reutikha",
    "gn:population":0,
    "gn:timezone":"Europe/Moscow",
    "iso:country":"RU",
    "name:rus_x_preferred":[
        "\u0420\u0435\u0443\u0442\u0438\u0445\u0430"
    ],
    "wof:name":"Reutikha",
    "wof:placetype":"locality"
},
  "geometry": {"coordinates":[45.6953,58.9425],"type":"Point"}
}