{
  "type": "Feature",
  "properties": {
    "gn:admin1_code":"77",
    "gn:asciiname":"Perlevo",
    "gn:country_code":"RU",
    "gn:dem":254,
    "gn:feature_class":"P",
    "gn:feature_code":"PPL",
    "gn:name":"Perlevo",
    "gn:population":0,
    "gn:timezone":"Europe/Moscow",
    "iso:country":"RU",
    "name:eng_x_preferred":[
        "Perlevo"
    ],
    "name:nor_x_preferred":[
        "Perlevo"
    ],
    "name:rus_x_preferred":[
        "\u041f\u0435\u0440\u043b\u0435\u0432\u043e"
    ],
    "wof:name":"Perlevo",
    "wof:placetype":"locality"
},
  "geometry": {"coordinates":[34.34029,56.77297],"type":"Point"}
}