{
  "type": "Feature",
  "properties": {
    "gn:admin1_code":"85",
    "gn:asciiname":"L'govo",
    "gn:country_code":"RU",
    "gn:dem":139,
    "gn:feature_class":"P",
    "gn:feature_code":"PPL",
    "gn:name":"L\u2019govo",
    "gn:population":0,
    "gn:timezone":"Europe/Moscow",
    "iso:country":"RU",
    "name:rus_x_preferred":[
        "\u041b\u044c\u0433\u043e\u0432\u043e"
    ],
    "name:und_x_variant":[
        "L\u2019govo",
        "\u041b\u044c\u0433\u043e\u0432\u043e"
    ],
    "wof:name":"L'govo",
    "wof:placetype":"locality"
},
  "geometry": {"coordinates":[38.4168,59.3472],"type":"Point"}
}