{
  "type": "Feature",
  "properties": {
    "gn:admin1_code":"81",
    "gn:asciiname":"Malaya Tsil'na",
    "gn:country_code":"RU",
    "gn:dem":138,
    "gn:feature_class":"P",
    "gn:feature_code":"PPL",
    "gn:name":"Malaya Tsil\u2019na",
    "gn:population":0,
    "gn:timezone":"Europe/Ulyanovsk",
    "iso:country":"RU",
    "name:rus_x_preferred":[
        "\u041c\u0430\u043b\u0430\u044f \u0426\u0438\u043b\u044c\u043d\u0430"
    ],
    "name:und_x_variant":[
        "Malaya Tsil\u2019na"
    ],
    "wof:name":"Malaya Tsil'na",
    "wof:placetype":"locality"
},
  "geometry": {"coordinates":[47.9844,54.664],"type":"Point"}
}