{
  "type": "Feature",
  "properties": {
    "gn:admin1_code":"16",
    "gn:asciiname":"Maloye Yanikovo",
    "gn:country_code":"RU",
    "gn:dem":145,
    "gn:feature_class":"P",
    "gn:feature_code":"PPL",
    "gn:name":"Maloye Yanikovo",
    "gn:population":0,
    "gn:timezone":"Europe/Moscow",
    "iso:country":"RU",
    "name:rus_x_preferred":[
        "\u041c\u0430\u043b\u043e\u0435 \u042f\u043d\u0438\u043a\u043e\u0432\u043e"
    ],
    "name:und_x_variant":[
        "Malo-Yanikovo",
        "Maloye Yanikovo",
        "\u041c\u0430\u043b\u043e\u0435 \u042f\u043d\u0438\u043a\u043e\u0432\u043e"
    ],
    "wof:name":"Maloye Yanikovo",
    "wof:placetype":"locality"
},
  "geometry": {"coordinates":[47.76781,55.69308],"type":"Point"}
}