{
  "type": "Feature",
  "properties": {
    "gn:country":"RU",
    "gn:fcode":"PPL",
    "gn:pop":0,
    "iso:country":"RU",
    "name:cat_x_preferred":[
        "Bogdanovka"
    ],
    "name:deu_x_preferred":[
        "Bogdanowka"
    ],
    "name:heb_x_preferred":[
        "\u05d1\u05d5\u05d2\u05d3\u05e0\u05d5\u05d1\u05e7\u05d4"
    ],
    "name:ind_x_preferred":[
        "Bogdanovka"
    ],
    "name:nor_x_preferred":[
        "Bogdanovka"
    ],
    "name:rus_x_preferred":[
        "\u0411\u043e\u0433\u0434\u0430\u043d\u043e\u0432\u043a\u0430"
    ],
    "name:spa_x_preferred":[
        "Bogdanovka"
    ],
    "qs:name":"Bogdanovka",
    "qs:name_adm0":"Russia",
    "qs:name_adm1":"Kaluga Oblast",
    "qs:photos_9r":0,
    "qs:photos_sr":0,
    "qs:placetype":"Town",
    "qs:pop_sr":"0",
    "wd:wordcount":316,
    "wof:name":"Bogdanovka",
    "wof:placetype":"locality",
    "wof:population":0
},
  "geometry": {"coordinates":[36.45596,54.57016],"type":"Point"}
}