{
  "type": "Feature",
  "properties": {
    "gn:admin1_code":"51",
    "gn:asciiname":"Maloye Panfilovo",
    "gn:country_code":"RU",
    "gn:dem":136,
    "gn:feature_class":"P",
    "gn:feature_code":"PPL",
    "gn:name":"Maloye Panfilovo",
    "gn:population":0,
    "gn:timezone":"Europe/Moscow",
    "iso:country":"RU",
    "name:rus_x_preferred":[
        "\u041c\u0430\u043b\u043e\u0435 \u041f\u0430\u043d\u0444\u0438\u043b\u043e\u0432\u043e"
    ],
    "wof:name":"Maloye Panfilovo",
    "wof:placetype":"locality"
},
  "geometry": {"coordinates":[45.7512,57.5915],"type":"Point"}
}