{
  "type": "Feature",
  "properties": {
    "gn:admin1_code":"88",
    "gn:asciiname":"Falyukovo",
    "gn:country_code":"RU",
    "gn:dem":113,
    "gn:feature_class":"P",
    "gn:feature_code":"PPL",
    "gn:name":"Falyukovo",
    "gn:population":0,
    "gn:timezone":"Europe/Moscow",
    "iso:country":"RU",
    "name:rus_x_preferred":[
        "\u0424\u0430\u043b\u044e\u043a\u043e\u0432\u043e"
    ],
    "wof:name":"Falyukovo",
    "wof:placetype":"locality"
},
  "geometry": {"coordinates":[38.4696,57.6076],"type":"Point"}
}