{
  "type": "Feature",
  "properties": {
    "gn:admin1_code":"29",
    "gn:asciiname":"Burovaya Razvedka",
    "gn:country_code":"RU",
    "gn:dem":357,
    "gn:feature_class":"P",
    "gn:feature_code":"PPL",
    "gn:name":"Burovaya Razvedka",
    "gn:population":0,
    "gn:timezone":"Asia/Novokuznetsk",
    "iso:country":"RU",
    "name:rus_x_preferred":[
        "\u0411\u0443\u0440\u043e\u0432\u0430\u044f \u0420\u0430\u0437\u0432\u0435\u0434\u043a\u0430"
    ],
    "wof:name":"Burovaya Razvedka",
    "wof:placetype":"locality"
},
  "geometry": {"coordinates":[87.4298,53.4668],"type":"Point"}
}