{
  "type": "Feature",
  "properties": {
    "gn:admin1_code":"33",
    "gn:asciiname":"Nizovskoye",
    "gn:country_code":"RU",
    "gn:dem":84,
    "gn:feature_class":"P",
    "gn:feature_code":"PPL",
    "gn:name":"Nizovskoye",
    "gn:population":0,
    "gn:timezone":"Europe/Kirov",
    "iso:country":"RU",
    "name:rus_x_preferred":[
        "\u041d\u0438\u0437\u043e\u0432\u0441\u043a\u043e\u0435"
    ],
    "wof:name":"Nizovskoye",
    "wof:placetype":"locality"
},
  "geometry": {"coordinates":[46.9816,60.2349],"type":"Point"}
}