{
  "type": "Feature",
  "properties": {
    "gn:admin1_code":"69.0",
    "gn:asciiname":"Domakhi",
    "gn:country_code":"RU",
    "gn:dem":220,
    "gn:feature_class":"P",
    "gn:feature_code":"PPL",
    "gn:name":"Domakhi",
    "gn:population":0,
    "gn:timezone":"Europe/Moscow",
    "iso:country":"RU",
    "name:rus_x_preferred":[
        "\u0414\u043e\u043c\u0430\u0445\u0438"
    ],
    "name:und_x_variant":[
        "\u0414\u043e\u043c\u0430\u0445\u0438"
    ],
    "wof:name":"Domakhi",
    "wof:placetype":"locality"
},
  "geometry": {"coordinates":[33.91583,56.04971999999999],"type":"Point"}
}