{
  "type": "Feature",
  "properties": {
    "gn:admin1_code":"60",
    "gn:asciiname":"Ladygovshchina",
    "gn:country_code":"RU",
    "gn:dem":49,
    "gn:feature_class":"P",
    "gn:feature_code":"PPL",
    "gn:name":"Ladygovshchina",
    "gn:population":0,
    "gn:timezone":"Europe/Moscow",
    "iso:country":"RU",
    "name:rus_x_preferred":[
        "\u041b\u0430\u0434\u044b\u0433\u043e\u0432\u0449\u0438\u043d\u0430"
    ],
    "wof:name":"Ladygovshchina",
    "wof:placetype":"locality"
},
  "geometry": {"coordinates":[28.2224,57.9656],"type":"Point"}
}