{
  "type": "Feature",
  "properties": {
    "gn:admin1_code":"8",
    "gn:asciiname":"Kosobachevo",
    "gn:country_code":"RU",
    "gn:dem":259,
    "gn:feature_class":"P",
    "gn:feature_code":"PPL",
    "gn:name":"Kosobachevo",
    "gn:population":0,
    "gn:timezone":"Asia/Yekaterinburg",
    "iso:country":"RU",
    "name:rus_x_preferred":[
        "\u041a\u043e\u0441\u043e\u0431\u0430\u0447\u0435\u0432\u043e"
    ],
    "name:und_x_variant":[
        "\u041a\u043e\u0441\u043e\u0431\u0430\u0447\u0435\u0432\u043e"
    ],
    "wof:name":"Kosobachevo",
    "wof:placetype":"locality"
},
  "geometry": {"coordinates":[56.65,56.05],"type":"Point"}
}