{
  "type": "Feature",
  "properties": {
    "gn:admin1_code":"90",
    "gn:asciiname":"Mokhovo",
    "gn:country_code":"RU",
    "gn:dem":178,
    "gn:feature_class":"P",
    "gn:feature_code":"PPL",
    "gn:name":"Mokhovo",
    "gn:population":0,
    "gn:timezone":"Asia/Yekaterinburg",
    "iso:country":"RU",
    "name:che_x_preferred":[
        "\u041c\u043e\u0445\u043e\u0432\u043e"
    ],
    "name:nor_x_preferred":[
        "Mokhovo"
    ],
    "name:rus_x_preferred":[
        "\u041c\u043e\u0445\u043e\u0432\u043e"
    ],
    "wof:name":"Mokhovo",
    "wof:placetype":"locality"
},
  "geometry": {"coordinates":[56.3597,58.3163],"type":"Point"}
}