{
  "type": "Feature",
  "properties": {
    "gn:admin1_code":"91",
    "gn:asciiname":"Yepishino",
    "gn:country_code":"RU",
    "gn:dem":88,
    "gn:feature_class":"P",
    "gn:feature_code":"PPL",
    "gn:name":"Yepishino",
    "gn:population":0,
    "gn:timezone":"Asia/Krasnoyarsk",
    "iso:country":"RU",
    "name:eng_x_preferred":[
        "Yepishino"
    ],
    "name:nor_x_preferred":[
        "Jepisjino"
    ],
    "name:rus_x_preferred":[
        "\u0415\u043f\u0438\u0448\u0438\u043d\u043e"
    ],
    "name:und_x_variant":[
        "Nifant\u2019yeva",
        "Yepishina"
    ],
    "wof:name":"Yepishino",
    "wof:placetype":"locality"
},
  "geometry": {"coordinates":[92.2354,58.4816],"type":"Point"}
}