{
  "type": "Feature",
  "properties": {
    "gn:admin1_code":"42.0",
    "gn:asciiname":"Gnilenka",
    "gn:country_code":"RU",
    "gn:dem":68,
    "gn:feature_class":"P",
    "gn:feature_code":"PPL",
    "gn:name":"Gnilenka",
    "gn:population":0,
    "gn:timezone":"Europe/Moscow",
    "iso:country":"RU",
    "name:rus_x_preferred":[
        "\u0413\u043d\u0438\u043b\u0435\u043d\u043a\u0430"
    ],
    "name:und_x_variant":[
        "Gnilinka",
        "Gnilenka",
        "\u0413\u043d\u0438\u043b\u0435\u043d\u043a\u0430"
    ],
    "wof:name":"Gnilenka",
    "wof:placetype":"locality"
},
  "geometry": {"coordinates":[28.75631,58.8812],"type":"Point"}
}