{
  "type": "Feature",
  "properties": {
    "gn:admin1_code":"41",
    "gn:asciiname":"Nizhnyaya Grunya",
    "gn:country_code":"RU",
    "gn:dem":163,
    "gn:feature_class":"P",
    "gn:feature_code":"PPL",
    "gn:name":"Nizhnyaya Grunya",
    "gn:population":0,
    "gn:timezone":"Europe/Moscow",
    "iso:country":"RU",
    "name:eng_x_preferred":[
        "Nizhnyaya Grunya"
    ],
    "name:nor_x_preferred":[
        "Nizjnjaja Grunja"
    ],
    "name:rus_x_preferred":[
        "\u041d\u0438\u0436\u043d\u044f\u044f \u0413\u0440\u0443\u043d\u044f"
    ],
    "name:und_x_variant":[
        "Nizhnyaya Grun\u2019"
    ],
    "wof:name":"Nizhnyaya Grunya",
    "wof:placetype":"locality"
},
  "geometry": {"coordinates":[34.9695,51.5338],"type":"Point"}
}