{
  "type": "Feature",
  "properties": {
    "gn:admin1_code":"16",
    "gn:asciiname":"Nizhniye Tatmyshi",
    "gn:country_code":"RU",
    "gn:dem":121,
    "gn:feature_class":"P",
    "gn:feature_code":"PPL",
    "gn:name":"Nizhniye Tatmyshi",
    "gn:population":0,
    "gn:timezone":"Europe/Moscow",
    "iso:country":"RU",
    "name:rus_x_preferred":[
        "\u041d\u0438\u0436\u043d\u0438\u0435 \u0422\u0430\u0442\u043c\u044b\u0448\u0438"
    ],
    "wof:name":"Nizhniye Tatmyshi",
    "wof:placetype":"locality"
},
  "geometry": {"coordinates":[47.23837,55.46119],"type":"Point"}
}