{
  "type": "Feature",
  "properties": {
    "gn:admin1_code":"60",
    "gn:asciiname":"Yashutino",
    "gn:country_code":"RU",
    "gn:dem":87,
    "gn:feature_class":"P",
    "gn:feature_code":"PPL",
    "gn:name":"Yashutino",
    "gn:population":0,
    "gn:timezone":"Europe/Moscow",
    "iso:country":"RU",
    "name:und_x_variant":[
        "Ja\u0161utina",
        "Yashutina",
        "Yashutino"
    ],
    "wof:name":"Yashutino",
    "wof:placetype":"locality"
},
  "geometry": {"coordinates":[27.92886,56.95889],"type":"Point"}
}