{
  "type": "Feature",
  "properties": {
    "gn:admin1_code":"37",
    "gn:asciiname":"Odintsovo",
    "gn:country_code":"RU",
    "gn:dem":193,
    "gn:feature_class":"P",
    "gn:feature_code":"PPL",
    "gn:name":"Odintsovo",
    "gn:population":0,
    "gn:timezone":"Europe/Moscow",
    "iso:country":"RU",
    "name:rus_x_preferred":[
        "\u041e\u0434\u0438\u043d\u0446\u043e\u0432\u043e"
    ],
    "name:und_x_variant":[
        "\u041e\u0434\u0438\u043d\u0446\u043e\u0432\u043e"
    ],
    "wof:name":"Odintsovo",
    "wof:placetype":"locality"
},
  "geometry": {"coordinates":[42.8648,58.8899],"type":"Point"}
}