{
  "type": "Feature",
  "properties": {
    "gn:admin1_code":"41",
    "gn:asciiname":"Ostapovo",
    "gn:country_code":"RU",
    "gn:dem":165,
    "gn:feature_class":"P",
    "gn:feature_code":"PPL",
    "gn:name":"Ostapovo",
    "gn:population":0,
    "gn:timezone":"Europe/Moscow",
    "iso:country":"RU",
    "name:eng_x_preferred":[
        "Ostapovo"
    ],
    "name:nor_x_preferred":[
        "Ostapovo"
    ],
    "name:rus_x_preferred":[
        "\u041e\u0441\u0442\u0430\u043f\u043e\u0432\u043e"
    ],
    "name:und_x_variant":[
        "Ostapova"
    ],
    "wof:name":"Ostapovo",
    "wof:placetype":"locality"
},
  "geometry": {"coordinates":[35.4477,52.2625],"type":"Point"}
}