{
  "type": "Feature",
  "properties": {
    "gn:admin1_code":"30",
    "gn:asciiname":"Pereprava",
    "gn:country_code":"RU",
    "gn:dem":45,
    "gn:feature_class":"P",
    "gn:feature_code":"PPL",
    "gn:name":"Pereprava",
    "gn:population":0,
    "gn:timezone":"Asia/Vladivostok",
    "iso:country":"RU",
    "name:eng_x_preferred":[
        "Pereprava"
    ],
    "name:nor_x_preferred":[
        "Pereprava"
    ],
    "name:rus_x_preferred":[
        "\u041f\u0435\u0440\u0435\u043f\u0440\u0430\u0432\u0430"
    ],
    "name:und_x_variant":[
        "\u041f\u0435\u0440\u0435\u043f\u0440\u0430\u0432\u0430",
        "Pereprava"
    ],
    "wof:name":"Pereprava",
    "wof:placetype":"locality"
},
  "geometry": {"coordinates":[134.40000000000001,48.75],"type":"Point"}
}