{
  "type": "Feature",
  "properties": {
    "gn:admin1_code":"5.0",
    "gn:asciiname":"Dzhatva",
    "gn:country_code":"RU",
    "gn:dem":219,
    "gn:feature_class":"P",
    "gn:feature_code":"PPL",
    "gn:name":"Dzhatva",
    "gn:population":0,
    "gn:timezone":"Asia/Yakutsk",
    "iso:country":"RU",
    "name:che_x_preferred":[
        "\u0414\u0436\u0430\u0442\u0432\u0430"
    ],
    "name:rus_x_preferred":[
        "\u0414\u0436\u0430\u0442\u0432\u0430"
    ],
    "wof:name":"Dzhatva",
    "wof:placetype":"locality"
},
  "geometry": {"coordinates":[128.00745000000001,51.82775],"type":"Point"}
}