{
  "type": "Feature",
  "properties": {
    "gn:admin1_code":"20",
    "gn:asciiname":"Boloto",
    "gn:country_code":"RU",
    "gn:dem":575,
    "gn:feature_class":"P",
    "gn:feature_code":"PPL",
    "gn:name":"Boloto",
    "gn:population":0,
    "gn:timezone":"Asia/Irkutsk",
    "iso:country":"RU",
    "name:che_x_preferred":[
        "\u0411\u043e\u043b\u043e\u0442\u043e"
    ],
    "name:eng_x_preferred":[
        "Boloto"
    ],
    "name:nor_x_preferred":[
        "Boloto"
    ],
    "name:rus_x_preferred":[
        "\u0411\u043e\u043b\u043e\u0442\u043e"
    ],
    "name:und_x_variant":[
        "\u0411\u043e\u043b\u043e\u0442\u043e",
        "Boloto"
    ],
    "wof:name":"Boloto",
    "wof:placetype":"locality"
},
  "geometry": {"coordinates":[106.39583,53.91944],"type":"Point"}
}