{
  "type": "Feature",
  "properties": {
    "gn:admin1_code":"34",
    "gn:asciiname":"Lebyazhsk",
    "gn:country_code":"RU",
    "gn:dem":96,
    "gn:feature_class":"P",
    "gn:feature_code":"PPL",
    "gn:name":"Lebyazhsk",
    "gn:population":0,
    "gn:timezone":"Europe/Moscow",
    "iso:country":"RU",
    "name:eng_x_preferred":[
        "Lebyazhsk"
    ],
    "name:nor_x_preferred":[
        "Lebjazjsk"
    ],
    "name:rus_x_preferred":[
        "\u041b\u0435\u0431\u044f\u0436\u0441\u043a"
    ],
    "name:und_x_variant":[
        "Lebyazhskoye"
    ],
    "wof:name":"Lebyazhsk",
    "wof:placetype":"locality"
},
  "geometry": {"coordinates":[57.16769,63.84505],"type":"Point"}
}