{
  "type": "Feature",
  "properties": {
    "gn:admin1_code":"51",
    "gn:asciiname":"Arbinskiy",
    "gn:country_code":"RU",
    "gn:dem":117,
    "gn:feature_class":"P",
    "gn:feature_code":"PPL",
    "gn:name":"Arbinskiy",
    "gn:population":0,
    "gn:timezone":"Europe/Moscow",
    "iso:country":"RU",
    "name:rus_x_preferred":[
        "\u0410\u0440\u0431\u0438\u043d\u0441\u043a\u0438\u0439"
    ],
    "wof:name":"Arbinskiy",
    "wof:placetype":"locality"
},
  "geometry": {"coordinates":[47.2715,57.6309],"type":"Point"}
}