{
  "type": "Feature",
  "properties": {
    "gn:admin1_code":"67",
    "gn:asciiname":"Pindeyev",
    "gn:country_code":"RU",
    "gn:dem":46,
    "gn:feature_class":"P",
    "gn:feature_code":"PPL",
    "gn:name":"Pindeyev",
    "gn:population":0,
    "gn:timezone":"Europe/Saratov",
    "iso:country":"RU",
    "name:rus_x_preferred":[
        "\u041f\u0438\u043d\u0434\u0435\u0435\u0432"
    ],
    "wof:name":"Pindeyev",
    "wof:placetype":"locality"
},
  "geometry": {"coordinates":[49.3414,50.8455],"type":"Point"}
}