{
  "type": "Feature",
  "properties": {
    "gn:admin1_code":"83.0",
    "gn:asciiname":"Ryabinnitsy",
    "gn:country_code":"RU",
    "gn:dem":120,
    "gn:feature_class":"P",
    "gn:feature_code":"PPL",
    "gn:name":"Ryabinnitsy",
    "gn:population":0,
    "gn:timezone":"Europe/Moscow",
    "iso:country":"RU",
    "name:rus_x_preferred":[
        "\u0420\u044f\u0431\u0438\u043d\u043d\u0438\u0446\u044b"
    ],
    "name:und_x_variant":[
        "\u0420\u044f\u0431\u0438\u043d\u043d\u0438\u0446\u044b"
    ],
    "wof:name":"Ryabinnitsy",
    "wof:placetype":"locality"
},
  "geometry": {"coordinates":[41.68549,56.40635],"type":"Point"}
}