{
  "type": "Feature",
  "properties": {
    "gn:admin1_code":"61.0",
    "gn:asciiname":"Dubrovyy",
    "gn:cc2":"RU",
    "gn:country_code":"RU",
    "gn:dem":211,
    "gn:feature_class":"P",
    "gn:feature_code":"PPL",
    "gn:name":"Dubrovyy",
    "gn:population":0,
    "gn:timezone":"Europe/Moscow",
    "iso:country":"RU",
    "name:rus_x_preferred":[
        "\u0414\u0443\u0431\u0440\u043e\u0432\u044b\u0439"
    ],
    "name:und_x_variant":[
        "Pervyy Shirokiy",
        "Dubrovyy",
        "\u0414\u0443\u0431\u0440\u043e\u0432\u044b\u0439"
    ],
    "wof:name":"Dubrovyy",
    "wof:placetype":"locality"
},
  "geometry": {"coordinates":[40.20972,49.5525],"type":"Point"}
}