{
  "type": "Feature",
  "properties": {
    "gn:country":"RU",
    "gn:fcode":"PPL",
    "gn:population":0,
    "iso:country":"RU",
    "name:rus_x_preferred":[
        "\u0413\u0440\u043e\u043c\u043e\u0432\u043e"
    ],
    "name:rus_x_variant":[
        "\u041d\u043e\u0432\u043e\u0433\u0440\u043e\u043c\u043e\u0432\u043e"
    ],
    "name:und_x_variant":[
        "Gromovo"
    ],
    "qs:name":"Novogromovo",
    "qs:name_adm0":"Russia",
    "qs:name_adm1":"Moscow Oblast",
    "qs:photos_9k":1,
    "qs:photos_9r":1,
    "qs:photos_all":3,
    "qs:photos_sr":0,
    "qs:placetype":"Town",
    "qs:pop_sr":"0",
    "wof:name":"Novogromovo",
    "wof:placetype":"locality",
    "wof:population":0
},
  "geometry": {"coordinates":[37.24583,55.29722],"type":"Point"}
}