{
  "type": "Feature",
  "properties": {
    "gn:admin1_code":"37",
    "gn:asciiname":"Selo Zaingir'",
    "gn:country_code":"RU",
    "gn:dem":130,
    "gn:feature_class":"P",
    "gn:feature_code":"PPL",
    "gn:name":"Selo Zaingir\u2019",
    "gn:population":0,
    "gn:timezone":"Europe/Moscow",
    "iso:country":"RU",
    "name:rus_x_preferred":[
        "\u0421\u0435\u043b\u043e \u0417\u0430\u0438\u043d\u0433\u0438\u0440\u044c"
    ],
    "name:und_x_variant":[
        "Selo Zaingir\u2019",
        "\u0421\u0435\u043b\u043e \u0417\u0430\u0438\u043d\u0433\u0438\u0440\u044c"
    ],
    "wof:name":"Selo Zaingir'",
    "wof:placetype":"locality"
},
  "geometry": {"coordinates":[43.9654,58.4487],"type":"Point"}
}