{
  "type": "Feature",
  "properties": {
    "gn:admin1_code":"77",
    "gn:asciiname":"Ter Gora",
    "gn:country_code":"RU",
    "gn:dem":303,
    "gn:feature_class":"P",
    "gn:feature_code":"PPL",
    "gn:name":"Ter Gora",
    "gn:population":0,
    "gn:timezone":"Europe/Moscow",
    "iso:country":"RU",
    "wof:name":"Ter Gora",
    "wof:placetype":"locality"
},
  "geometry": {"coordinates":[33.36237,56.44976],"type":"Point"}
}