{
  "type": "Feature",
  "properties": {
    "gn:admin1_code":"41",
    "gn:asciiname":"Svyatozerka",
    "gn:country_code":"RU",
    "gn:dem":183,
    "gn:feature_class":"P",
    "gn:feature_code":"PPL",
    "gn:name":"Svyatoz\u00ebrka",
    "gn:population":0,
    "gn:timezone":"Europe/Moscow",
    "iso:country":"RU",
    "name:rus_x_preferred":[
        "\u0421\u0432\u044f\u0442\u043e\u0437\u0451\u0440\u043a\u0430"
    ],
    "name:und_x_variant":[
        "Svyatoz\u00ebrka"
    ],
    "wof:name":"Svyatozerka",
    "wof:placetype":"locality"
},
  "geometry": {"coordinates":[34.6559,52.048],"type":"Point"}
}