{
  "type": "Feature",
  "properties": {
    "gn:admin1_code":"23",
    "gn:asciiname":"Rostovskoye",
    "gn:country_code":"RU",
    "gn:dem":25,
    "gn:feature_class":"P",
    "gn:feature_code":"PPL",
    "gn:name":"Rostovskoye",
    "gn:population":0,
    "gn:timezone":"Europe/Kaliningrad",
    "iso:country":"RU",
    "name:rus_x_preferred":[
        "\u0420\u043e\u0441\u0442\u043e\u0432\u0441\u043a\u043e\u0435"
    ],
    "wof:name":"Rostovskoye",
    "wof:placetype":"locality"
},
  "geometry": {"coordinates":[21.47917,54.67333000000001],"type":"Point"}
}