{
  "type": "Feature",
  "properties": {
    "gn:admin1_code":"78",
    "gn:asciiname":"Iyevlevo",
    "gn:country_code":"RU",
    "gn:dem":50,
    "gn:feature_class":"P",
    "gn:feature_code":"PPL",
    "gn:name":"Iyevlevo",
    "gn:population":0,
    "gn:timezone":"Asia/Yekaterinburg",
    "iso:country":"RU",
    "name:eng_x_preferred":[
        "Iyevlevo"
    ],
    "name:nor_x_preferred":[
        "Ijevlevo"
    ],
    "name:rus_x_preferred":[
        "\u0418\u0435\u0432\u043b\u0435\u0432\u043e"
    ],
    "wof:name":"Iyevlevo",
    "wof:placetype":"locality"
},
  "geometry": {"coordinates":[67.15111,57.57639],"type":"Point"}
}