{
  "type": "Feature",
  "properties": {
    "gn:admin1_code":"78",
    "gn:asciiname":"Staraya Maslyanka",
    "gn:country_code":"RU",
    "gn:dem":78,
    "gn:feature_class":"P",
    "gn:feature_code":"PPL",
    "gn:name":"Staraya Maslyanka",
    "gn:population":0,
    "gn:timezone":"Asia/Yekaterinburg",
    "iso:country":"RU",
    "name:rus_x_preferred":[
        "\u0421\u0442\u0430\u0440\u0430\u044f \u041c\u0430\u0441\u043b\u044f\u043d\u043a\u0430"
    ],
    "name:und_x_variant":[
        "Maslyanskoye",
        "Staromaslyanskoye",
        "Staraya Maslyanka"
    ],
    "wof:name":"Staraya Maslyanka",
    "wof:placetype":"locality"
},
  "geometry": {"coordinates":[70.10809999999999,56.08727],"type":"Point"}
}