{
  "type": "Feature",
  "properties": {
    "gn:admin1_code":"73.0",
    "gn:asciiname":"Akhtuba",
    "gn:country_code":"RU",
    "gn:dem":107,
    "gn:feature_class":"P",
    "gn:feature_code":"PPL",
    "gn:name":"Akhtuba",
    "gn:population":0,
    "gn:timezone":"Europe/Moscow",
    "iso:country":"RU",
    "name:nor_x_preferred":[
        "Akhtuba"
    ],
    "name:rus_x_preferred":[
        "\u0410\u0445\u0442\u0443\u0431\u0430"
    ],
    "wof:name":"Akhtuba",
    "wof:placetype":"locality"
},
  "geometry": {"coordinates":[51.82508,55.62298000000001],"type":"Point"}
}