{
  "type": "Feature",
  "properties": {
    "gn:admin1_code":"30",
    "gn:asciiname":"Snezhnyy",
    "gn:country_code":"RU",
    "gn:dem":149,
    "gn:feature_class":"P",
    "gn:feature_code":"PPL",
    "gn:name":"Snezhnyy",
    "gn:population":0,
    "gn:timezone":"Asia/Vladivostok",
    "iso:country":"RU",
    "name:nor_x_preferred":[
        "Snezjnyj"
    ],
    "name:rus_x_preferred":[
        "\u0421\u043d\u0435\u0436\u043d\u044b\u0439"
    ],
    "wof:name":"Snezhnyy",
    "wof:placetype":"locality"
},
  "geometry": {"coordinates":[137.94628,50.26600000000001],"type":"Point"}
}