{
  "type": "Feature",
  "properties": {
    "gn:admin1_code":"34.0",
    "gn:asciiname":"Chernogorskaya",
    "gn:country_code":"RU",
    "gn:dem":77,
    "gn:feature_class":"P",
    "gn:feature_code":"PPL",
    "gn:name":"Chernogorskaya",
    "gn:population":0,
    "gn:timezone":"Europe/Moscow",
    "iso:country":"RU",
    "name:eng_x_preferred":[
        "Chernogorskaya"
    ],
    "name:nor_x_preferred":[
        "Tsjernogorskaja"
    ],
    "name:rus_x_preferred":[
        "\u0427\u0435\u0440\u043d\u043e\u0433\u043e\u0440\u0441\u043a\u0430\u044f"
    ],
    "name:und_x_variant":[
        "\u0427\u0435\u0440\u043d\u043e\u0433\u043e\u0440\u0441\u043a\u0430\u044f",
        "Chernogorskaya"
    ],
    "wof:name":"Chernogorskaya",
    "wof:placetype":"locality"
},
  "geometry": {"coordinates":[52.3155,65.02025999999999],"type":"Point"}
}