{
  "type": "Feature",
  "properties": {
    "gn:admin1_code":"63",
    "gn:asciiname":"Neryuktyayinsk Pervyy",
    "gn:cc2":"RU",
    "gn:country_code":"RU",
    "gn:dem":141,
    "gn:feature_class":"P",
    "gn:feature_code":"PPL",
    "gn:name":"Neryuktyayinsk Pervyy",
    "gn:population":0,
    "gn:timezone":"Asia/Yakutsk",
    "iso:country":"RU",
    "name:rus_x_preferred":[
        "\u041d\u0435\u0440\u044e\u043a\u0442\u044f\u0439\u0438\u043d\u0441\u043a \u041f\u0435\u0440\u0432\u044b\u0439"
    ],
    "name:und_x_variant":[
        "N\u00ebryuktey Pervyy",
        "N\u00ebryuktey",
        "Neryuktyayinsk Pervyy"
    ],
    "wof:name":"Neryuktyayinsk Pervyy",
    "wof:placetype":"locality"
},
  "geometry": {"coordinates":[119.66249999999999,60.25917],"type":"Point"}
}