{
  "type": "Feature",
  "properties": {
    "gn:admin1_code":"29",
    "gn:asciiname":"Bezymyanka",
    "gn:country_code":"RU",
    "gn:dem":583,
    "gn:feature_class":"P",
    "gn:feature_code":"PPL",
    "gn:name":"Bezymyanka",
    "gn:population":0,
    "gn:timezone":"Asia/Novokuznetsk",
    "iso:country":"RU",
    "name:ceb_x_preferred":[
        "Bezymyanka"
    ],
    "name:deu_x_preferred":[
        "Besymjanka"
    ],
    "name:hye_x_preferred":[
        "\u0532\u0565\u0566\u056b\u0574\u0575\u0561\u0576\u056f\u0561"
    ],
    "name:nor_x_preferred":[
        "Bezymjanka"
    ],
    "name:rus_x_preferred":[
        "\u0411\u0435\u0437\u044b\u043c\u044f\u043d\u043a\u0430"
    ],
    "name:swe_x_preferred":[
        "Bezymyanka"
    ],
    "name:ukr_x_preferred":[
        "\u0411\u0435\u0437\u0456\u043c'\u044f\u043d\u043a\u0430"
    ],
    "wof:name":"Bezymyanka",
    "wof:placetype":"locality"
},
  "geometry": {"coordinates":[88.36667,54.91667],"type":"Point"}
}