{
  "type": "Feature",
  "properties": {
    "gn:admin1_code":"83",
    "gn:asciiname":"Novobarsukovo",
    "gn:country_code":"RU",
    "gn:dem":107,
    "gn:feature_class":"P",
    "gn:feature_code":"PPL",
    "gn:name":"Novobarsukovo",
    "gn:population":0,
    "gn:timezone":"Europe/Moscow",
    "iso:country":"RU",
    "name:rus_x_preferred":[
        "\u041d\u043e\u0432\u043e\u0431\u0430\u0440\u0441\u0443\u043a\u043e\u0432\u043e"
    ],
    "name:und_x_variant":[
        "Novo-Barsukovka",
        "Novobarsukovo"
    ],
    "wof:name":"Novobarsukovo",
    "wof:placetype":"locality"
},
  "geometry": {"coordinates":[41.7922,55.5848],"type":"Point"}
}