{
  "type": "Feature",
  "properties": {
    "gn:admin1_code":"73",
    "gn:asciiname":"Kuyanovo",
    "gn:country_code":"RU",
    "gn:dem":74,
    "gn:feature_class":"P",
    "gn:feature_code":"PPL",
    "gn:name":"Kuyanovo",
    "gn:population":0,
    "gn:timezone":"Europe/Moscow",
    "iso:country":"RU",
    "name:rus_x_preferred":[
        "\u041a\u0443\u044f\u043d\u043e\u0432\u043e"
    ],
    "name:und_x_variant":[
        "\u041a\u0443\u044f\u043d\u043e\u0432\u043e"
    ],
    "wof:name":"Kuyanovo",
    "wof:placetype":"locality"
},
  "geometry": {"coordinates":[53.34913,55.62774],"type":"Point"}
}