{
  "type": "Feature",
  "properties": {
    "gn:admin1_code":"60",
    "gn:asciiname":"Korosteli",
    "gn:country_code":"RU",
    "gn:dem":191,
    "gn:feature_class":"P",
    "gn:feature_code":"PPL",
    "gn:name":"Korosteli",
    "gn:population":0,
    "gn:timezone":"Europe/Moscow",
    "iso:country":"RU",
    "name:rus_x_preferred":[
        "\u041a\u043e\u0440\u043e\u0441\u0442\u0435\u043b\u0438"
    ],
    "wof:name":"Korosteli",
    "wof:placetype":"locality"
},
  "geometry": {"coordinates":[29.83807,56.58038000000001],"type":"Point"}
}