{
  "type": "Feature",
  "properties": {
    "gn:admin1_code":"33",
    "gn:asciiname":"Kruglovo",
    "gn:country_code":"RU",
    "gn:dem":155,
    "gn:feature_class":"P",
    "gn:feature_code":"PPL",
    "gn:name":"Kruglovo",
    "gn:population":0,
    "gn:timezone":"Europe/Kirov",
    "iso:country":"RU",
    "name:rus_x_preferred":[
        "\u041a\u0440\u0443\u0433\u043b\u043e\u0432\u043e"
    ],
    "wof:name":"Kruglovo",
    "wof:placetype":"locality"
},
  "geometry": {"coordinates":[50.37278,58.64111],"type":"Point"}
}