{
  "type": "Feature",
  "properties": {
    "gn:admin1_code":"60",
    "gn:asciiname":"Muldovo",
    "gn:country_code":"RU",
    "gn:dem":97,
    "gn:feature_class":"P",
    "gn:feature_code":"PPL",
    "gn:name":"Muldovo",
    "gn:population":0,
    "gn:timezone":"Europe/Moscow",
    "iso:country":"RU",
    "name:rus_x_preferred":[
        "\u041c\u0443\u043b\u0434\u043e\u0432\u043e"
    ],
    "name:und_x_variant":[
        "Mudlovo",
        "Muldovo"
    ],
    "wof:name":"Muldovo",
    "wof:placetype":"locality"
},
  "geometry": {"coordinates":[28.12027,56.8228],"type":"Point"}
}