{
  "type": "Feature",
  "properties": {
    "gn:admin1_code":"88",
    "gn:asciiname":"Dreplevo",
    "gn:country_code":"RU",
    "gn:dem":138,
    "gn:feature_class":"P",
    "gn:feature_code":"PPL",
    "gn:name":"Drepl\u00ebvo",
    "gn:population":0,
    "gn:timezone":"Europe/Moscow",
    "iso:country":"RU",
    "name:rus_x_preferred":[
        "\u0414\u0440\u0435\u043f\u043b\u0451\u0432\u043e"
    ],
    "name:und_x_variant":[
        "Drepl\u00ebvo",
        "\u0414\u0440\u0435\u043f\u043b\u0451\u0432\u043e"
    ],
    "wof:name":"Dreplevo",
    "wof:placetype":"locality"
},
  "geometry": {"coordinates":[38.2528,57.1102],"type":"Point"}
}