{
  "type": "Feature",
  "properties": {
    "gn:admin1_code":"10",
    "gn:asciiname":"Tovbozino",
    "gn:country_code":"RU",
    "gn:dem":179,
    "gn:feature_class":"P",
    "gn:feature_code":"PPL",
    "gn:name":"Tovbozino",
    "gn:population":0,
    "gn:timezone":"Europe/Moscow",
    "iso:country":"RU",
    "name:rus_x_preferred":[
        "\u0422\u043e\u0432\u0431\u043e\u0437\u0438\u043d\u043e"
    ],
    "name:und_x_variant":[
        "Tovbozina"
    ],
    "wof:name":"Tovbozino",
    "wof:placetype":"locality"
},
  "geometry": {"coordinates":[33.15518,52.83734000000001],"type":"Point"}
}