{
  "type": "Feature",
  "properties": {
    "gn:admin1_code":"90",
    "gn:asciiname":"Shalgina",
    "gn:country_code":"RU",
    "gn:dem":208,
    "gn:feature_class":"P",
    "gn:feature_code":"PPL",
    "gn:name":"Shalgina",
    "gn:population":0,
    "gn:timezone":"Asia/Yekaterinburg",
    "iso:country":"RU",
    "name:rus_x_preferred":[
        "\u0428\u0430\u043b\u0433\u0438\u043d\u0430"
    ],
    "name:und_x_variant":[
        "\u0428\u0430\u043b\u0433\u0438\u043d\u0430"
    ],
    "wof:name":"Shalgina",
    "wof:placetype":"locality"
},
  "geometry": {"coordinates":[54.0079,59.2659],"type":"Point"}
}