{
  "type": "Feature",
  "properties": {
    "gn:admin1_code":"8",
    "gn:asciiname":"Sokolki",
    "gn:country_code":"RU",
    "gn:dem":244,
    "gn:feature_class":"P",
    "gn:feature_code":"PPL",
    "gn:name":"Sokolki",
    "gn:population":0,
    "gn:timezone":"Asia/Yekaterinburg",
    "iso:country":"RU",
    "name:eng_x_preferred":[
        "Sokolki"
    ],
    "name:nor_x_preferred":[
        "Sokolki"
    ],
    "name:rus_x_preferred":[
        "\u0421\u043e\u043a\u043e\u043b\u043a\u0438"
    ],
    "name:und_x_variant":[
        "\u0421\u043e\u043a\u043e\u043b\u043a\u0438",
        "Sokolki"
    ],
    "wof:name":"Sokolki",
    "wof:placetype":"locality"
},
  "geometry": {"coordinates":[58.88639000000001,55.73667],"type":"Point"}
}