{
  "type": "Feature",
  "properties": {
    "gn:admin1_code":"61",
    "gn:asciiname":"Yanovo-Grushevskiy",
    "gn:country_code":"RU",
    "gn:dem":12,
    "gn:feature_class":"P",
    "gn:feature_code":"PPL",
    "gn:name":"Yanovo-Grushevskiy",
    "gn:population":0,
    "gn:timezone":"Europe/Moscow",
    "iso:country":"RU",
    "name:eng_x_preferred":[
        "Yanovo-Grushevskiy"
    ],
    "name:nor_x_preferred":[
        "Janovo-Grusjevskij"
    ],
    "name:rus_x_preferred":[
        "\u042f\u043d\u043e\u0432\u043e-\u0413\u0440\u0443\u0448\u0435\u0432\u0441\u043a\u0438\u0439"
    ],
    "wof:name":"Yanovo-Grushevskiy",
    "wof:placetype":"locality"
},
  "geometry": {"coordinates":[40.04085,47.48999],"type":"Point"}
}