{
  "type": "Feature",
  "properties": {
    "gn:admin1_code":"77",
    "gn:asciiname":"Krasnodub'ye",
    "gn:country_code":"RU",
    "gn:dem":170,
    "gn:feature_class":"P",
    "gn:feature_code":"PPL",
    "gn:name":"Krasnodub\u2019ye",
    "gn:population":0,
    "gn:timezone":"Europe/Moscow",
    "iso:country":"RU",
    "name:rus_x_preferred":[
        "\u041a\u0440\u0430\u0441\u043d\u043e\u0434\u0443\u0431\u044c\u0435"
    ],
    "name:und_x_variant":[
        "Krasnodub\u2019ye",
        "\u041a\u0440\u0430\u0441\u043d\u043e\u0434\u0443\u0431\u044c\u0435"
    ],
    "wof:name":"Krasnodub'ye",
    "wof:placetype":"locality"
},
  "geometry": {"coordinates":[31.41667,55.98333],"type":"Point"}
}