{
  "type": "Feature",
  "properties": {
    "gn:admin1_code":"47",
    "gn:asciiname":"Ivanishchevo",
    "gn:country_code":"RU",
    "gn:dem":128,
    "gn:feature_class":"P",
    "gn:feature_code":"PPL",
    "gn:name":"Ivanishchevo",
    "gn:population":0,
    "gn:timezone":"Europe/Moscow",
    "iso:country":"RU",
    "name:rus_x_preferred":[
        "\u0418\u0432\u0430\u043d\u0438\u0449\u0435\u0432\u043e"
    ],
    "name:und_x_variant":[
        "Ivanishcheva",
        "Ivanishchevo"
    ],
    "wof:name":"Ivanishchevo",
    "wof:placetype":"locality"
},
  "geometry": {"coordinates":[38.99538,55.46901],"type":"Point"}
}