{
  "type": "Feature",
  "properties": {
    "gn:admin1_code":"67.0",
    "gn:asciiname":"Dorogovinovka",
    "gn:country_code":"RU",
    "gn:dem":37,
    "gn:feature_class":"P",
    "gn:feature_code":"PPL",
    "gn:name":"Dorogovinovka",
    "gn:population":0,
    "gn:timezone":"Europe/Saratov",
    "iso:country":"RU",
    "name:eng_x_preferred":[
        "Dorogovinovka"
    ],
    "name:nor_x_preferred":[
        "Dorogovinovka"
    ],
    "name:rus_x_preferred":[
        "\u0414\u043e\u0440\u043e\u0433\u043e\u0432\u0438\u043d\u043e\u0432\u043a\u0430"
    ],
    "name:und_x_variant":[
        "\u0414\u043e\u0440\u043e\u0433\u043e\u0432\u0438\u043d\u043e\u0432\u043a\u0430",
        "Dorogovinovka"
    ],
    "wof:name":"Dorogovinovka",
    "wof:placetype":"locality"
},
  "geometry": {"coordinates":[48.8197,52.2468],"type":"Point"}
}