{
  "type": "Feature",
  "properties": {
    "gn:admin1_code":"21.0",
    "gn:asciiname":"Bol'shoye Brusovo",
    "gn:country_code":"RU",
    "gn:dem":116,
    "gn:feature_class":"P",
    "gn:feature_code":"PPL",
    "gn:name":"Bol\u2019shoye Brusovo",
    "gn:population":0,
    "gn:timezone":"Europe/Moscow",
    "iso:country":"RU",
    "name:und_x_variant":[
        "Brusovo-Bol\u2019shoye",
        "Bol\u2019shoye Brusovo"
    ],
    "wof:name":"Bol'shoye Brusovo",
    "wof:placetype":"locality"
},
  "geometry": {"coordinates":[42.50583,56.90521],"type":"Point"}
}