{
  "type": "Feature",
  "properties": {
    "gn:admin1_code":"1.0",
    "gn:asciiname":"Bogursukov",
    "gn:country_code":"RU",
    "gn:dem":50,
    "gn:feature_class":"P",
    "gn:feature_code":"PPL",
    "gn:name":"Bogursukov",
    "gn:population":0,
    "gn:timezone":"Europe/Moscow",
    "iso:country":"RU",
    "name:cat_x_preferred":[
        "Bogursukov"
    ],
    "name:che_x_preferred":[
        "\u0411\u043e\u0433\u0443\u0440\u0441\u0443\u043a\u043e\u0432"
    ],
    "name:rus_x_preferred":[
        "\u0411\u043e\u0433\u0443\u0440\u0441\u0443\u043a\u043e\u0432"
    ],
    "name:spa_x_preferred":[
        "Bogursukov"
    ],
    "name:ukr_x_preferred":[
        "\u0411\u043e\u0433\u0443\u0440\u0441\u0443\u043a\u043e\u0432"
    ],
    "name:und_x_variant":[
        "Bogorsukov",
        "Bogursukov",
        "\u0411\u043e\u0433\u0443\u0440\u0441\u0443\u043a\u043e\u0432"
    ],
    "wof:name":"Bogursukov",
    "wof:placetype":"locality"
},
  "geometry": {"coordinates":[39.7043,45.04119],"type":"Point"}
}