{
  "type": "Feature",
  "properties": {
    "gn:admin1_code":"65",
    "gn:asciiname":"Gremyachka",
    "gn:country_code":"RU",
    "gn:dem":73,
    "gn:feature_class":"P",
    "gn:feature_code":"PPL",
    "gn:name":"Gremyachka",
    "gn:population":0,
    "gn:timezone":"Europe/Samara",
    "iso:country":"RU",
    "name:rus_x_preferred":[
        "\u0413\u0440\u0435\u043c\u044f\u0447\u043a\u0430"
    ],
    "name:und_x_variant":[
        "Novaya Gremyachka"
    ],
    "wof:name":"Gremyachka",
    "wof:placetype":"locality"
},
  "geometry": {"coordinates":[49.0108,52.6986],"type":"Point"}
}