{
  "type": "Feature",
  "properties": {
    "gn:admin1_code":"77",
    "gn:asciiname":"Sentyurino",
    "gn:country_code":"RU",
    "gn:dem":156,
    "gn:feature_class":"P",
    "gn:feature_code":"PPL",
    "gn:name":"Sentyurino",
    "gn:population":0,
    "gn:timezone":"Europe/Moscow",
    "iso:country":"RU",
    "name:rus_x_preferred":[
        "\u0421\u0435\u043d\u0442\u044e\u0440\u0438\u043d\u043e"
    ],
    "name:und_x_variant":[
        "\u0421\u0435\u043d\u0442\u044e\u0440\u0438\u043d\u043e"
    ],
    "wof:name":"Sentyurino",
    "wof:placetype":"locality"
},
  "geometry": {"coordinates":[36.1866,56.723],"type":"Point"}
}