{
  "type": "Feature",
  "properties": {
    "gn:admin1_code":"76",
    "gn:asciiname":"Kazarinovo",
    "gn:country_code":"RU",
    "gn:dem":157,
    "gn:feature_class":"P",
    "gn:feature_code":"PPL",
    "gn:name":"Kazarinovo",
    "gn:population":0,
    "gn:timezone":"Europe/Moscow",
    "iso:country":"RU",
    "name:rus_x_preferred":[
        "\u041a\u0430\u0437\u0430\u0440\u0438\u043d\u043e\u0432\u043e"
    ],
    "name:und_x_variant":[
        "\u041a\u0430\u0437\u0430\u0440\u0438\u043d\u043e\u0432\u043e"
    ],
    "wof:name":"Kazarinovo",
    "wof:placetype":"locality"
},
  "geometry": {"coordinates":[38.0005,54.68294],"type":"Point"}
}