{
  "type": "Feature",
  "properties": {
    "gn:admin1_code":"47.0",
    "gn:asciiname":"Aleksino-Tugoles",
    "gn:country_code":"RU",
    "gn:dem":132,
    "gn:feature_class":"P",
    "gn:feature_code":"PPL",
    "gn:name":"Aleksino-Tugoles",
    "gn:population":0,
    "gn:timezone":"Europe/Moscow",
    "iso:country":"RU",
    "name:nor_x_preferred":[
        "Aleksino-Tugoles"
    ],
    "name:rus_x_preferred":[
        "\u0410\u043b\u0435\u043a\u0441\u0438\u043d\u043e-\u0422\u0443\u0433\u043e\u043b\u0435\u0441"
    ],
    "name:und_x_variant":[
        "Aleksino-Tugoless"
    ],
    "wof:name":"Aleksino-Tugoles",
    "wof:placetype":"locality"
},
  "geometry": {"coordinates":[39.74351,55.55221],"type":"Point"}
}