{
  "type": "Feature",
  "properties": {
    "gn:admin1_code":"72",
    "gn:asciiname":"Koz'minka",
    "gn:country_code":"RU",
    "gn:dem":156,
    "gn:feature_class":"P",
    "gn:feature_code":"PPL",
    "gn:name":"Koz\u2019minka",
    "gn:population":0,
    "gn:timezone":"Europe/Moscow",
    "iso:country":"RU",
    "name:rus_x_preferred":[
        "Koz\u2019minka"
    ],
    "name:rus_x_variant":[
        "\u041a\u043e\u0437\u044c\u043c\u0438\u043d\u043a\u0430",
        "Kaz\u2019minka"
    ],
    "name:und_x_variant":[
        "Kazminovka"
    ],
    "wof:name":"Koz'minka",
    "wof:placetype":"locality"
},
  "geometry": {"coordinates":[40.8968,52.0245],"type":"Point"}
}