{
  "type": "Feature",
  "properties": {
    "gn:admin1_code":"9.0",
    "gn:asciiname":"Novokazatskoye",
    "gn:country_code":"RU",
    "gn:dem":88,
    "gn:feature_class":"P",
    "gn:feature_code":"PPL",
    "gn:name":"Novokazatskoye",
    "gn:population":0,
    "gn:timezone":"Europe/Moscow",
    "iso:country":"RU",
    "name:rus_x_preferred":[
        "\u041d\u043e\u0432\u043e\u043a\u0430\u0437\u0430\u0446\u043a\u043e\u0435"
    ],
    "wof:name":"Novokazatskoye",
    "wof:placetype":"locality"
},
  "geometry": {"coordinates":[38.1452,50.2112],"type":"Point"}
}