{
  "type": "Feature",
  "properties": {
    "gn:admin1_code":"16",
    "gn:asciiname":"Armankasy",
    "gn:country_code":"RU",
    "gn:dem":139,
    "gn:feature_class":"P",
    "gn:feature_code":"PPL",
    "gn:name":"Armankasy",
    "gn:population":0,
    "gn:timezone":"Europe/Moscow",
    "iso:country":"RU",
    "name:nor_x_preferred":[
        "Armankasy"
    ],
    "name:rus_x_preferred":[
        "\u0410\u0440\u043c\u0430\u043d\u043a\u0430\u0441\u044b"
    ],
    "wof:name":"Armankasy",
    "wof:placetype":"locality"
},
  "geometry": {"coordinates":[47.33192,56.07242],"type":"Point"}
}