{
  "type": "Feature",
  "properties": {
    "gn:admin1_code":"83",
    "gn:asciiname":"Pogost-Bykovo",
    "gn:country_code":"RU",
    "gn:dem":114,
    "gn:feature_class":"P",
    "gn:feature_code":"PPL",
    "gn:name":"Pogost-Bykovo",
    "gn:population":0,
    "gn:timezone":"Europe/Moscow",
    "iso:country":"RU",
    "name:rus_x_preferred":[
        "\u041f\u043e\u0433\u043e\u0441\u0442-\u0411\u044b\u043a\u043e\u0432\u043e"
    ],
    "wof:name":"Pogost-Bykovo",
    "wof:placetype":"locality"
},
  "geometry": {"coordinates":[40.56087,56.46883],"type":"Point"}
}