{
  "type": "Feature",
  "properties": {
    "gn:admin1_code":"46",
    "gn:asciiname":"Kulisheyka",
    "gn:country_code":"RU",
    "gn:dem":190,
    "gn:feature_class":"P",
    "gn:feature_code":"PPL",
    "gn:name":"Kulisheyka",
    "gn:population":0,
    "gn:timezone":"Europe/Moscow",
    "iso:country":"RU",
    "name:rus_x_preferred":[
        "\u041a\u0443\u043b\u0438\u0448\u0435\u0439\u043a\u0430"
    ],
    "wof:name":"Kulisheyka",
    "wof:placetype":"locality"
},
  "geometry": {"coordinates":[44.64312,54.03836],"type":"Point"}
}