{
  "type": "Feature",
  "properties": {
    "gn:admin1_code":"29",
    "gn:asciiname":"Degtyarevka",
    "gn:country_code":"RU",
    "gn:dem":198,
    "gn:feature_class":"P",
    "gn:feature_code":"PPL",
    "gn:name":"Degtyar\u00ebvka",
    "gn:population":0,
    "gn:timezone":"Asia/Novokuznetsk",
    "iso:country":"RU",
    "name:rus_x_preferred":[
        "\u0414\u0435\u0433\u0442\u044f\u0440\u0451\u0432\u043a\u0430"
    ],
    "name:und_x_variant":[
        "Degtyar\u00ebvka"
    ],
    "wof:name":"Degtyarevka",
    "wof:placetype":"locality"
},
  "geometry": {"coordinates":[85.87309999999999,54.4557],"type":"Point"}
}