{
  "type": "Feature",
  "properties": {
    "gn:admin1_code":"42",
    "gn:asciiname":"Soginskiy Pogost",
    "gn:country_code":"RU",
    "gn:dem":102,
    "gn:feature_class":"P",
    "gn:feature_code":"PPL",
    "gn:name":"Soginskiy Pogost",
    "gn:population":0,
    "gn:timezone":"Europe/Moscow",
    "iso:country":"RU",
    "name:rus_x_preferred":[
        "\u0421\u043e\u0433\u0438\u043d\u0441\u043a\u0438\u0439 \u041f\u043e\u0433\u043e\u0441\u0442"
    ],
    "name:und_x_variant":[
        "\u0421\u043e\u0433\u0438\u043d\u0441\u043a\u0438\u0439 \u041f\u043e\u0433\u043e\u0441\u0442"
    ],
    "wof:name":"Soginskiy Pogost",
    "wof:placetype":"locality"
},
  "geometry": {"coordinates":[34.15,61.08333],"type":"Point"}
}