{
  "type": "Feature",
  "properties": {
    "gn:admin1_code":"8",
    "gn:asciiname":"Kuyazbash",
    "gn:country_code":"RU",
    "gn:dem":141,
    "gn:feature_class":"P",
    "gn:feature_code":"PPL",
    "gn:name":"Kuyazbash",
    "gn:population":0,
    "gn:timezone":"Asia/Yekaterinburg",
    "iso:country":"RU",
    "name:rus_x_preferred":[
        "\u041a\u0443\u044f\u0437\u0431\u0430\u0448"
    ],
    "name:und_x_variant":[
        "\u041a\u0443\u044f\u0437\u0431\u0430\u0448"
    ],
    "wof:name":"Kuyazbash",
    "wof:placetype":"locality"
},
  "geometry": {"coordinates":[54.89583,55.59139],"type":"Point"}
}