{
  "type": "Feature",
  "properties": {
    "gn:admin1_code":"52.0",
    "gn:asciiname":"Borisovo",
    "gn:country_code":"RU",
    "gn:dem":71,
    "gn:feature_class":"P",
    "gn:feature_code":"PPL",
    "gn:name":"Borisovo",
    "gn:population":0,
    "gn:timezone":"Europe/Moscow",
    "iso:country":"RU",
    "name:rus_x_preferred":[
        "\u0411\u043e\u0440\u0438\u0441\u043e\u0432\u043e"
    ],
    "name:und_x_variant":[
        "\u0411\u043e\u0440\u0438\u0441\u043e\u0432\u043e"
    ],
    "wof:name":"Borisovo",
    "wof:placetype":"locality"
},
  "geometry": {"coordinates":[31.22912,57.11561],"type":"Point"}
}