{
  "type": "Feature",
  "properties": {
    "gn:admin1_code":"88",
    "gn:asciiname":"Ivantsevo-Marikovo",
    "gn:country_code":"RU",
    "gn:dem":218,
    "gn:feature_class":"P",
    "gn:feature_code":"PPL",
    "gn:name":"Ivants\u00ebvo-Marikovo",
    "gn:population":0,
    "gn:timezone":"Europe/Moscow",
    "iso:country":"RU",
    "name:rus_x_preferred":[
        "\u0418\u0432\u0430\u043d\u0446\u0451\u0432\u043e-\u041c\u0430\u0440\u0438\u043a\u043e\u0432\u043e"
    ],
    "name:und_x_variant":[
        "Ivants\u00ebvo-Marikovo"
    ],
    "wof:name":"Ivantsevo-Marikovo",
    "wof:placetype":"locality"
},
  "geometry": {"coordinates":[38.7097,57.0679],"type":"Point"}
}