{
  "type": "Feature",
  "properties": {
    "gn:admin1_code":"65",
    "gn:asciiname":"Novaya Kamenka",
    "gn:country_code":"RU",
    "gn:dem":97,
    "gn:feature_class":"P",
    "gn:feature_code":"PPL",
    "gn:name":"Novaya Kamenka",
    "gn:population":0,
    "gn:timezone":"Europe/Samara",
    "iso:country":"RU",
    "name:rus_x_preferred":[
        "\u041d\u043e\u0432\u0430\u044f \u041a\u0430\u043c\u0435\u043d\u043a\u0430"
    ],
    "name:und_x_variant":[
        "\u041d\u043e\u0432\u0430\u044f \u041a\u0430\u043c\u0435\u043d\u043a\u0430"
    ],
    "wof:name":"Novaya Kamenka",
    "wof:placetype":"locality"
},
  "geometry": {"coordinates":[50.36667,53.66667],"type":"Point"}
}