{
  "type": "Feature",
  "properties": {
    "gn:admin1_code":"55",
    "gn:asciiname":"Gran'",
    "gn:country_code":"RU",
    "gn:dem":191,
    "gn:feature_class":"P",
    "gn:feature_code":"PPL",
    "gn:name":"Gran\u2019",
    "gn:population":0,
    "gn:timezone":"Asia/Yekaterinburg",
    "iso:country":"RU",
    "name:rus_x_preferred":[
        "\u0413\u0440\u0430\u043d\u044c"
    ],
    "name:und_x_variant":[
        "Gran\u2019",
        "\u0413\u0440\u0430\u043d\u044c"
    ],
    "wof:name":"Gran'",
    "wof:placetype":"locality"
},
  "geometry": {"coordinates":[53.93333000000001,52.06667],"type":"Point"}
}