{
  "type": "Feature",
  "properties": {
    "gn:admin1_code":"33",
    "gn:asciiname":"Mashiny",
    "gn:country_code":"RU",
    "gn:dem":150,
    "gn:feature_class":"P",
    "gn:feature_code":"PPL",
    "gn:name":"Mashiny",
    "gn:population":0,
    "gn:timezone":"Europe/Kirov",
    "iso:country":"RU",
    "name:rus_x_preferred":[
        "\u041c\u0430\u0448\u0438\u043d\u044b"
    ],
    "wof:name":"Mashiny",
    "wof:placetype":"locality"
},
  "geometry": {"coordinates":[49.3548,57.5252],"type":"Point"}
}