{
  "type": "Feature",
  "properties": {
    "gn:admin1_code":"38",
    "gn:asciiname":"Kubanskaya",
    "gn:country_code":"RU",
    "gn:dem":158,
    "gn:feature_class":"P",
    "gn:feature_code":"PPL",
    "gn:name":"Kubanskaya",
    "gn:population":0,
    "gn:timezone":"Europe/Moscow",
    "iso:country":"RU",
    "name:eng_x_preferred":[
        "Kubanskaya"
    ],
    "name:nor_x_preferred":[
        "Kubanskaja"
    ],
    "name:rus_x_preferred":[
        "\u041a\u0443\u0431\u0430\u043d\u0441\u043a\u0430\u044f"
    ],
    "name:und_x_variant":[
        "Kubanskaya Pervaya"
    ],
    "wof:name":"Kubanskaya",
    "wof:placetype":"locality"
},
  "geometry": {"coordinates":[39.71361,44.60472],"type":"Point"}
}