{
  "type": "Feature",
  "properties": {
    "gn:admin1_code":"61",
    "gn:asciiname":"Shtokolov",
    "gn:country_code":"RU",
    "gn:dem":92,
    "gn:feature_class":"P",
    "gn:feature_code":"PPL",
    "gn:name":"Shtokolov",
    "gn:population":0,
    "gn:timezone":"Europe/Moscow",
    "iso:country":"RU",
    "name:rus_x_preferred":[
        "\u0428\u0442\u043e\u043a\u043e\u043b\u043e\u0432"
    ],
    "wof:name":"Shtokolov",
    "wof:placetype":"locality"
},
  "geometry": {"coordinates":[40.4248,48.6018],"type":"Point"}
}