{
  "type": "Feature",
  "properties": {
    "gn:admin1_code":"JA",
    "gn:asciiname":"Zalivnaya",
    "gn:cc2":"RU",
    "gn:country_code":"RU",
    "gn:dem":6,
    "gn:feature_class":"P",
    "gn:feature_code":"PPL",
    "gn:name":"Zalivnaya",
    "gn:population":0,
    "gn:timezone":"Asia/Magadan",
    "iso:country":"RU",
    "name:und_x_variant":[
        "Rebausugyoj\u014d",
        "Rebausu",
        "Rebaushi",
        "Reb\u014dsu"
    ],
    "wof:name":"Zalivnaya",
    "wof:placetype":"locality"
},
  "geometry": {"coordinates":[146.05000000000001,44.41667],"type":"Point"}
}