{
  "type": "Feature",
  "properties": {
    "gn:admin1_code":"93",
    "gn:asciiname":"Nizhniy Stan",
    "gn:country_code":"RU",
    "gn:dem":885,
    "gn:feature_class":"P",
    "gn:feature_code":"PPL",
    "gn:name":"Nizhniy Stan",
    "gn:population":0,
    "gn:timezone":"Asia/Chita",
    "iso:country":"RU",
    "name:rus_x_preferred":[
        "\u041d\u0438\u0436\u043d\u0438\u0439 \u0421\u0442\u0430\u043d"
    ],
    "wof:name":"Nizhniy Stan",
    "wof:placetype":"locality"
},
  "geometry": {"coordinates":[112.52752,49.75635],"type":"Point"}
}