{
  "type": "Feature",
  "properties": {
    "gn:admin1_code":"85",
    "gn:asciiname":"Uspenskoye",
    "gn:country_code":"RU",
    "gn:dem":125,
    "gn:feature_class":"P",
    "gn:feature_code":"PPL",
    "gn:name":"Uspenskoye",
    "gn:population":0,
    "gn:timezone":"Europe/Moscow",
    "iso:country":"RU",
    "name:rus_x_preferred":[
        "\u0423\u0441\u043f\u0435\u043d\u0441\u043a\u043e\u0435"
    ],
    "name:und_x_variant":[
        "\u0423\u0441\u043f\u0435\u043d\u0441\u043a\u043e\u0435"
    ],
    "wof:name":"Uspenskoye",
    "wof:placetype":"locality"
},
  "geometry": {"coordinates":[36.6143,59.4995],"type":"Point"}
}