{
  "type": "Feature",
  "properties": {
    "gn:admin1_code":"28",
    "gn:asciiname":"Sikopokh'ya",
    "gn:country_code":"RU",
    "gn:dem":100,
    "gn:feature_class":"P",
    "gn:feature_code":"PPL",
    "gn:name":"Sikopokh\u2019ya",
    "gn:population":0,
    "gn:timezone":"Europe/Moscow",
    "iso:country":"RU",
    "name:eng_x_preferred":[
        "Sikopokh'ya"
    ],
    "name:fin_x_preferred":[
        "Sikopohja"
    ],
    "name:nor_x_preferred":[
        "Sukopokhja"
    ],
    "name:rus_x_preferred":[
        "\u0421\u0443\u043a\u043e\u043f\u043e\u0445\u044c\u044f"
    ],
    "name:rus_x_variant":[
        "\u0421\u0438\u043a\u043e\u043f\u043e\u0445\u044c\u044f"
    ],
    "name:und_x_variant":[
        "Sikopokh\u2019ya"
    ],
    "wof:name":"Sikopokh'ya",
    "wof:placetype":"locality"
},
  "geometry": {"coordinates":[30.01667,61.65],"type":"Point"}
}