{
  "type": "Feature",
  "properties": {
    "gn:admin1_code":"86",
    "gn:asciiname":"Osinki",
    "gn:country_code":"RU",
    "gn:dem":122,
    "gn:feature_class":"P",
    "gn:feature_code":"PPL",
    "gn:name":"Osinki",
    "gn:population":0,
    "gn:timezone":"Europe/Moscow",
    "iso:country":"RU",
    "name:fra_x_preferred":[
        "Osinki"
    ],
    "name:lit_x_preferred":[
        "Osinkai"
    ],
    "name:pol_x_preferred":[
        "Osinki"
    ],
    "name:rus_x_preferred":[
        "\u041e\u0441\u0438\u043d\u043a\u0438"
    ],
    "name:ukr_x_preferred":[
        "\u041e\u0441\u0456\u043d\u043a\u0456"
    ],
    "wof:name":"Osinki",
    "wof:placetype":"locality"
},
  "geometry": {"coordinates":[41.0736,51.1558],"type":"Point"}
}