{
  "type": "Feature",
  "properties": {
    "gn:admin1_code":"90",
    "gn:asciiname":"Sretenskoye",
    "gn:country_code":"RU",
    "gn:dem":115,
    "gn:feature_class":"P",
    "gn:feature_code":"PPL",
    "gn:name":"Sretenskoye",
    "gn:population":0,
    "gn:timezone":"Asia/Yekaterinburg",
    "iso:country":"RU",
    "name:eng_x_preferred":[
        "Sretenskoye"
    ],
    "name:nor_x_preferred":[
        "Sretenskoje"
    ],
    "name:rus_x_preferred":[
        "\u0421\u0440\u0435\u0442\u0435\u043d\u0441\u043a\u043e\u0435"
    ],
    "name:und_x_variant":[
        "Stretenskoye"
    ],
    "wof:name":"Sretenskoye",
    "wof:placetype":"locality"
},
  "geometry": {"coordinates":[55.55528,58.60194],"type":"Point"}
}