{
  "type": "Feature",
  "properties": {
    "gn:admin1_code":"77",
    "gn:asciiname":"Pen'ye",
    "gn:country_code":"RU",
    "gn:dem":141,
    "gn:feature_class":"P",
    "gn:feature_code":"PPL",
    "gn:name":"Pen\u2019ye",
    "gn:population":0,
    "gn:timezone":"Europe/Moscow",
    "iso:country":"RU",
    "name:rus_x_preferred":[
        "\u041f\u0435\u043d\u044c\u0435"
    ],
    "name:und_x_variant":[
        "Pen\u2019ye"
    ],
    "wof:name":"Pen'ye",
    "wof:placetype":"locality"
},
  "geometry": {"coordinates":[36.7277,57.2785],"type":"Point"}
}