{
  "type": "Feature",
  "properties": {
    "gn:admin1_code":"20",
    "gn:asciiname":"Spolokh",
    "gn:country_code":"RU",
    "gn:dem":251,
    "gn:feature_class":"P",
    "gn:feature_code":"PPL",
    "gn:name":"Spolokh",
    "gn:population":0,
    "gn:timezone":"Asia/Irkutsk",
    "iso:country":"RU",
    "name:rus_x_preferred":[
        "\u0421\u043f\u043e\u043b\u043e\u0445"
    ],
    "wof:name":"Spolokh",
    "wof:placetype":"locality"
},
  "geometry": {"coordinates":[97.7706,55.9591],"type":"Point"}
}