{
  "type": "Feature",
  "properties": {
    "gn:admin1_code":"83.0",
    "gn:asciiname":"Batyyevo",
    "gn:country_code":"RU",
    "gn:dem":123,
    "gn:feature_class":"P",
    "gn:feature_code":"PPL",
    "gn:name":"Batyyevo",
    "gn:population":0,
    "gn:timezone":"Europe/Moscow",
    "iso:country":"RU",
    "name:rus_x_preferred":[
        "\u0411\u0430\u0442\u044b\u0435\u0432\u043e"
    ],
    "wof:name":"Batyyevo",
    "wof:placetype":"locality"
},
  "geometry": {"coordinates":[40.47857,56.28999],"type":"Point"}
}