{
  "type": "Feature",
  "properties": {
    "gn:admin1_code":"55",
    "gn:asciiname":"Khersonovka",
    "gn:country_code":"RU",
    "gn:dem":178,
    "gn:feature_class":"P",
    "gn:feature_code":"PPL",
    "gn:name":"Khersonovka",
    "gn:population":0,
    "gn:timezone":"Asia/Yekaterinburg",
    "iso:country":"RU",
    "name:rus_x_preferred":[
        "\u0425\u0435\u0440\u0441\u043e\u043d\u043e\u0432\u043a\u0430"
    ],
    "name:und_x_variant":[
        "\u0425\u0435\u0440\u0441\u043e\u043d\u043e\u0432\u043a\u0430"
    ],
    "wof:name":"Khersonovka",
    "wof:placetype":"locality"
},
  "geometry": {"coordinates":[53.55,53.05],"type":"Point"}
}