{
  "type": "Feature",
  "properties": {
    "gn:admin1_code":"59",
    "gn:asciiname":"Zavetnoye",
    "gn:country_code":"RU",
    "gn:dem":272,
    "gn:feature_class":"P",
    "gn:feature_code":"PPL",
    "gn:name":"Zavetnoye",
    "gn:population":0,
    "gn:timezone":"Asia/Vladivostok",
    "iso:country":"RU",
    "name:eng_x_preferred":[
        "Zavetnoye"
    ],
    "name:nor_x_preferred":[
        "Zavetnoje"
    ],
    "name:rus_x_preferred":[
        "\u0417\u0430\u0432\u0435\u0442\u043d\u043e\u0435"
    ],
    "name:und_x_variant":[
        "Shabanova"
    ],
    "wof:name":"Zavetnoye",
    "wof:placetype":"locality"
},
  "geometry": {"coordinates":[134.69644,44.70914000000001],"type":"Point"}
}