{
  "type": "Feature",
  "properties": {
    "gn:admin1_code":"8.0",
    "gn:asciiname":"Dergachevka",
    "gn:country_code":"RU",
    "gn:dem":225,
    "gn:feature_class":"P",
    "gn:feature_code":"PPL",
    "gn:name":"Dergach\u00ebvka",
    "gn:population":0,
    "gn:timezone":"Asia/Yekaterinburg",
    "iso:country":"RU",
    "name:eng_x_preferred":[
        "Dergach\u00ebvka"
    ],
    "name:nor_x_preferred":[
        "Dergatsjevka"
    ],
    "name:rus_x_preferred":[
        "\u0414\u0435\u0440\u0433\u0430\u0447\u0435\u0432\u043a\u0430"
    ],
    "name:rus_x_variant":[
        "\u0414\u0435\u0440\u0433\u0430\u0447\u0451\u0432\u043a\u0430"
    ],
    "wof:name":"Dergachevka",
    "wof:placetype":"locality"
},
  "geometry": {"coordinates":[55.51667,53.8424],"type":"Point"}
}