{
  "type": "Feature",
  "properties": {
    "gn:admin1_code":"84",
    "gn:asciiname":"Kravtsy",
    "gn:country_code":"RU",
    "gn:dem":26,
    "gn:feature_class":"P",
    "gn:feature_code":"PPL",
    "gn:name":"Kravtsy",
    "gn:population":0,
    "gn:timezone":"Europe/Volgograd",
    "iso:country":"RU",
    "name:rus_x_preferred":[
        "\u041a\u0440\u0430\u0432\u0446\u044b"
    ],
    "name:und_x_variant":[
        "\u041a\u0440\u0430\u0432\u0446\u044b"
    ],
    "wof:name":"Kravtsy",
    "wof:placetype":"locality"
},
  "geometry": {"coordinates":[46.34908,49.71715],"type":"Point"}
}