{
  "type": "Feature",
  "properties": {
    "gn:admin1_code":"28",
    "gn:asciiname":"Parandovo",
    "gn:country_code":"RU",
    "gn:dem":55,
    "gn:feature_class":"P",
    "gn:feature_code":"PPL",
    "gn:name":"Parandovo",
    "gn:population":0,
    "gn:timezone":"Europe/Moscow",
    "iso:country":"RU",
    "name:rus_x_preferred":[
        "\u041f\u0430\u0440\u0430\u043d\u0434\u043e\u0432\u043e"
    ],
    "wof:name":"Parandovo",
    "wof:placetype":"locality"
},
  "geometry": {"coordinates":[34.25983,64.01501999999999],"type":"Point"}
}