{
  "type": "Feature",
  "properties": {
    "gn:admin1_code":"89",
    "gn:asciiname":"Kazanskiy",
    "gn:country_code":"RU",
    "gn:dem":327,
    "gn:feature_class":"P",
    "gn:feature_code":"PPL",
    "gn:name":"Kazanskiy",
    "gn:population":0,
    "gn:timezone":"Asia/Vladivostok",
    "iso:country":"RU",
    "name:rus_x_preferred":[
        "\u041a\u0430\u0437\u0430\u043d\u0441\u043a\u0438\u0439"
    ],
    "wof:name":"Kazanskiy",
    "wof:placetype":"locality"
},
  "geometry": {"coordinates":[131.25,48.73333],"type":"Point"}
}