{
  "type": "Feature",
  "properties": {
    "gn:admin1_code":"57",
    "gn:asciiname":"Novyy Machim",
    "gn:country_code":"RU",
    "gn:dem":227,
    "gn:feature_class":"P",
    "gn:feature_code":"PPL",
    "gn:name":"Novyy Machim",
    "gn:population":0,
    "gn:timezone":"Europe/Moscow",
    "iso:country":"RU",
    "name:eng_x_preferred":[
        "Novyy Machim"
    ],
    "name:nor_x_preferred":[
        "Nov.Matsjim"
    ],
    "name:rus_x_preferred":[
        "\u041d\u043e\u0432.\u041c\u0430\u0447\u0438\u043c"
    ],
    "name:rus_x_variant":[
        "\u041d\u043e\u0432\u044b\u0439 \u041c\u0430\u0447\u0438\u043c"
    ],
    "wof:name":"Novyy Machim",
    "wof:placetype":"locality"
},
  "geometry": {"coordinates":[45.74204,52.93314],"type":"Point"}
}