{
  "type": "Feature",
  "properties": {
    "gn:admin1_code":"40",
    "gn:asciiname":"Kozyrevka",
    "gn:country_code":"RU",
    "gn:dem":171,
    "gn:feature_class":"P",
    "gn:feature_code":"PPL",
    "gn:name":"Kozyrevka",
    "gn:population":0,
    "gn:timezone":"Asia/Yekaterinburg",
    "iso:country":"RU",
    "name:rus_x_preferred":[
        "\u041a\u043e\u0437\u044b\u0440\u0435\u0432\u043a\u0430"
    ],
    "name:und_x_variant":[
        "\u041a\u043e\u0437\u044b\u0440\u0435\u0432\u043a\u0430"
    ],
    "wof:name":"Kozyrevka",
    "wof:placetype":"locality"
},
  "geometry": {"coordinates":[63.49278,54.66417],"type":"Point"}
}