{
  "type": "Feature",
  "properties": {
    "gn:admin1_code":"85.0",
    "gn:asciiname":"Filinskaya",
    "gn:country_code":"RU",
    "gn:dem":127,
    "gn:feature_class":"P",
    "gn:feature_code":"PPL",
    "gn:name":"Filinskaya",
    "gn:population":0,
    "gn:timezone":"Europe/Moscow",
    "iso:country":"RU",
    "name:eng_x_preferred":[
        "Filinskaya"
    ],
    "name:nor_x_preferred":[
        "Filinskaja"
    ],
    "name:rus_x_preferred":[
        "\u0424\u0438\u043b\u0438\u043d\u0441\u043a\u0430\u044f"
    ],
    "name:und_x_variant":[
        "\u0424\u0438\u043b\u0438\u043d\u0441\u043a\u0430\u044f",
        "Filinskaya"
    ],
    "wof:name":"Filinskaya",
    "wof:placetype":"locality"
},
  "geometry": {"coordinates":[42.06657,60.68999],"type":"Point"}
}