{
  "type": "Feature",
  "properties": {
    "gn:admin1_code":"76",
    "gn:asciiname":"Rakhleyevo",
    "gn:country_code":"RU",
    "gn:dem":202,
    "gn:feature_class":"P",
    "gn:feature_code":"PPL",
    "gn:name":"Rakhleyevo",
    "gn:population":0,
    "gn:timezone":"Europe/Moscow",
    "iso:country":"RU",
    "name:eng_x_preferred":[
        "Rakhleyevo"
    ],
    "name:nor_x_preferred":[
        "Rakhlejevo"
    ],
    "name:rus_x_preferred":[
        "\u0420\u0430\u0445\u043b\u0435\u0435\u0432\u043e"
    ],
    "name:und_x_variant":[
        "Rakhleyeva",
        "Rakhlyeevo",
        "\u0420\u0430\u0445\u043b\u0435\u0435\u0432\u043e",
        "Rakhleyevo"
    ],
    "wof:name":"Rakhleyevo",
    "wof:placetype":"locality"
},
  "geometry": {"coordinates":[36.57166,53.76414000000001],"type":"Point"}
}