{
  "type": "Feature",
  "properties": {
    "gn:admin1_code":"41",
    "gn:asciiname":"Tishino",
    "gn:country_code":"RU",
    "gn:dem":183,
    "gn:feature_class":"P",
    "gn:feature_code":"PPL",
    "gn:name":"Tishino",
    "gn:population":0,
    "gn:timezone":"Europe/Moscow",
    "iso:country":"RU",
    "name:rus_x_preferred":[
        "\u0422\u0438\u0448\u0438\u043d\u043e"
    ],
    "name:und_x_variant":[
        "\u0422\u0438\u0448\u0438\u043d\u043e"
    ],
    "wof:name":"Tishino",
    "wof:placetype":"locality"
},
  "geometry": {"coordinates":[36.38417000000001,52.09882],"type":"Point"}
}