{
  "type": "Feature",
  "properties": {
    "gn:admin1_code":"77",
    "gn:asciiname":"Kunichikha",
    "gn:country_code":"RU",
    "gn:dem":143,
    "gn:feature_class":"P",
    "gn:feature_code":"PPL",
    "gn:name":"Kunichikha",
    "gn:population":0,
    "gn:timezone":"Europe/Moscow",
    "iso:country":"RU",
    "name:rus_x_preferred":[
        "\u041a\u0443\u043d\u0438\u0447\u0438\u0445\u0430"
    ],
    "wof:name":"Kunichikha",
    "wof:placetype":"locality"
},
  "geometry": {"coordinates":[35.52333,57.87889000000001],"type":"Point"}
}