{
  "type": "Feature",
  "properties": {
    "gn:admin1_code":"10",
    "gn:asciiname":"Vereshchovka",
    "gn:country_code":"RU",
    "gn:dem":188,
    "gn:feature_class":"P",
    "gn:feature_code":"PPL",
    "gn:name":"Vereshchovka",
    "gn:population":0,
    "gn:timezone":"Europe/Moscow",
    "iso:country":"RU",
    "name:eng_x_preferred":[
        "Vereshchovka"
    ],
    "name:nor_x_preferred":[
        "Veresjtsjevka"
    ],
    "name:rus_x_preferred":[
        "\u0412\u0435\u0440\u0435\u0449\u0435\u0432\u043a\u0430"
    ],
    "name:und_x_variant":[
        "Vereshch\u00ebvka",
        "Vereshchovka"
    ],
    "wof:name":"Vereshchovka",
    "wof:placetype":"locality"
},
  "geometry": {"coordinates":[34.37342,53.66466],"type":"Point"}
}