{
  "type": "Feature",
  "properties": {
    "gn:admin1_code":"62",
    "gn:asciiname":"Obreznoy",
    "gn:country_code":"RU",
    "gn:dem":150,
    "gn:feature_class":"P",
    "gn:feature_code":"PPL",
    "gn:name":"Obreznoy",
    "gn:population":0,
    "gn:timezone":"Europe/Moscow",
    "iso:country":"RU",
    "name:rus_x_preferred":[
        "\u041e\u0431\u0440\u0435\u0437\u043d\u043e\u0439"
    ],
    "wof:name":"Obreznoy",
    "wof:placetype":"locality"
},
  "geometry": {"coordinates":[39.2275,53.8491],"type":"Point"}
}