{
  "type": "Feature",
  "properties": {
    "gn:admin1_code":"60",
    "gn:asciiname":"Vishnyaki",
    "gn:country_code":"RU",
    "gn:dem":70,
    "gn:feature_class":"P",
    "gn:feature_code":"PPL",
    "gn:name":"Vishnyaki",
    "gn:population":0,
    "gn:timezone":"Europe/Moscow",
    "iso:country":"RU",
    "name:rus_x_preferred":[
        "\u0412\u0438\u0448\u043d\u044f\u043a\u0438"
    ],
    "wof:name":"Vishnyaki",
    "wof:placetype":"locality"
},
  "geometry": {"coordinates":[28.61037,57.3353],"type":"Point"}
}