{
  "type": "Feature",
  "properties": {
    "gn:country":"RU",
    "gn:fcode":"PPL",
    "gn:population":4214,
    "iso:country":"RU",
    "name:ara_x_preferred":[
        "\u064a\u064a\u0631\u0645\u064a\u0643\u064a\u064a\u0641\u0648"
    ],
    "name:bak_x_preferred":[
        "\u0419\u04d9\u0440\u043c\u04d9\u043a\u04d9\u0439"
    ],
    "name:ceb_x_preferred":[
        "Yermekeyevo"
    ],
    "name:eng_x_preferred":[
        "Yermekeyevo"
    ],
    "name:hun_x_preferred":[
        "Jermekejevo"
    ],
    "name:hye_x_preferred":[
        "\u0535\u0580\u0574\u0565\u056f\u0565\u0587\u0578"
    ],
    "name:nld_x_preferred":[
        "Yermekeyevo"
    ],
    "name:pol_x_preferred":[
        "Jermiekiejewo"
    ],
    "name:rus_x_preferred":[
        "\u0415\u0440\u043c\u0435\u043d\u0435\u0435\u0432\u043e"
    ],
    "name:rus_x_variant":[
        "\u0415\u0440\u043c\u0435\u043a\u0435\u0435\u0432\u043e"
    ],
    "name:tat_x_preferred":[
        "\u042f\u0440\u043c\u04d9\u043a\u04d9\u0439"
    ],
    "name:ukr_x_preferred":[
        "\u0404\u0440\u043c\u0435\u043a\u0435\u0454\u0432\u043e"
    ],
    "name:und_x_variant":[
        "Yermikeyevo"
    ],
    "qs:name":"Yermekeyevo",
    "qs:photos_9r":0,
    "qs:photos_sr":0,
    "qs:pop_sr":"4",
    "wd:wordcount":169,
    "wof:name":"Yermekeyevo",
    "wof:placetype":"locality",
    "wof:population":4214
},
  "geometry": {"coordinates":[53.67125,54.07614],"type":"Point"}
}