{
  "type": "Feature",
  "properties": {
    "gn:admin1_code":"33.0",
    "gn:asciiname":"Chetay",
    "gn:country_code":"RU",
    "gn:dem":119,
    "gn:feature_class":"P",
    "gn:feature_code":"PPL",
    "gn:name":"Chetay",
    "gn:population":0,
    "gn:timezone":"Europe/Kirov",
    "iso:country":"RU",
    "name:eng_x_preferred":[
        "Chetay"
    ],
    "name:nor_x_preferred":[
        "Tsjetaj"
    ],
    "name:rus_x_preferred":[
        "\u0427\u0435\u0442\u0430\u0439"
    ],
    "wof:name":"Chetay",
    "wof:placetype":"locality"
},
  "geometry": {"coordinates":[50.97053,57.12004],"type":"Point"}
}