{
  "type": "Feature",
  "properties": {
    "gn:admin1_code":"33.0",
    "gn:asciiname":"Glukhovshchina",
    "gn:country_code":"RU",
    "gn:dem":168,
    "gn:feature_class":"P",
    "gn:feature_code":"PPL",
    "gn:name":"Glukhovshchina",
    "gn:population":0,
    "gn:timezone":"Europe/Kirov",
    "iso:country":"RU",
    "name:rus_x_preferred":[
        "\u0413\u043b\u0443\u0445\u043e\u0432\u0449\u0438\u043d\u0430"
    ],
    "name:und_x_variant":[
        "\u0413\u043b\u0443\u0445\u043e\u0432\u0449\u0438\u043d\u0430"
    ],
    "wof:name":"Glukhovshchina",
    "wof:placetype":"locality"
},
  "geometry": {"coordinates":[50.98745,56.68665],"type":"Point"}
}