{
  "type": "Feature",
  "properties": {
    "gn:admin1_code":"60",
    "gn:asciiname":"Shelyapy",
    "gn:country_code":"RU",
    "gn:dem":171,
    "gn:feature_class":"P",
    "gn:feature_code":"PPL",
    "gn:name":"Shelyapy",
    "gn:population":0,
    "gn:timezone":"Europe/Moscow",
    "iso:country":"RU",
    "name:rus_x_preferred":[
        "\u0428\u0435\u043b\u044f\u043f\u044b"
    ],
    "name:und_x_variant":[
        "Shelyaty",
        "\u0428\u0435\u043b\u044f\u043f\u044b"
    ],
    "wof:name":"Shelyapy",
    "wof:placetype":"locality"
},
  "geometry": {"coordinates":[31.25278,56.12701],"type":"Point"}
}