{
  "type": "Feature",
  "properties": {
    "gn:admin1_code":"60",
    "gn:asciiname":"Korov'ye Selo",
    "gn:country_code":"RU",
    "gn:dem":50,
    "gn:feature_class":"P",
    "gn:feature_code":"PPL",
    "gn:name":"Korov\u2019ye Selo",
    "gn:population":0,
    "gn:timezone":"Europe/Moscow",
    "iso:country":"RU",
    "name:rus_x_preferred":[
        "\u041a\u043e\u0440\u043e\u0432\u044c\u0435 \u0421\u0435\u043b\u043e"
    ],
    "name:und_x_variant":[
        "Korov\u2019ye Selo"
    ],
    "wof:name":"Korov'ye Selo",
    "wof:placetype":"locality"
},
  "geometry": {"coordinates":[28.33549,57.61564],"type":"Point"}
}