{
  "type": "Feature",
  "properties": {
    "gn:admin1_code":"11",
    "gn:asciiname":"Uladyy",
    "gn:country_code":"RU",
    "gn:dem":921,
    "gn:feature_class":"P",
    "gn:feature_code":"PPL",
    "gn:name":"Uladyy",
    "gn:population":0,
    "gn:timezone":"Asia/Irkutsk",
    "iso:country":"RU",
    "name:eng_x_preferred":[
        "Uladyy"
    ],
    "name:nor_x_preferred":[
        "Uladyj"
    ],
    "name:rus_x_preferred":[
        "\u0423\u043b\u0430\u0434\u044b\u0439"
    ],
    "name:und_x_variant":[
        "Ulady",
        "Uladi",
        "Uladyy"
    ],
    "wof:name":"Uladyy",
    "wof:placetype":"locality"
},
  "geometry": {"coordinates":[107.64267,50.17432],"type":"Point"}
}