{
  "type": "Feature",
  "properties": {
    "gn:admin1_code":"62",
    "gn:asciiname":"Rudnevo",
    "gn:country_code":"RU",
    "gn:dem":168,
    "gn:feature_class":"P",
    "gn:feature_code":"PPL",
    "gn:name":"Rudn\u00ebvo",
    "gn:population":0,
    "gn:timezone":"Europe/Moscow",
    "iso:country":"RU",
    "name:eng_x_preferred":[
        "Rudn\u00ebvo"
    ],
    "name:nor_x_preferred":[
        "Rudnevo"
    ],
    "name:rus_x_preferred":[
        "\u0420\u0443\u0434\u043d\u0435\u0432\u043e"
    ],
    "name:rus_x_variant":[
        "\u0420\u0443\u0434\u043d\u0451\u0432\u043e"
    ],
    "name:und_x_variant":[
        "Rudn\u00ebvo",
        "\u0420\u0443\u0434\u043d\u0451\u0432\u043e"
    ],
    "wof:name":"Rudnevo",
    "wof:placetype":"locality"
},
  "geometry": {"coordinates":[39.4861,54.1337],"type":"Point"}
}