{
  "type": "Feature",
  "properties": {
    "gn:admin1_code":"51.0",
    "gn:asciiname":"Torchilovo",
    "gn:country_code":"RU",
    "gn:dem":71,
    "gn:feature_class":"P",
    "gn:feature_code":"PPL",
    "gn:name":"Torchilovo",
    "gn:population":0,
    "gn:timezone":"Europe/Moscow",
    "iso:country":"RU",
    "wof:name":"Torchilovo",
    "wof:placetype":"locality"
},
  "geometry": {"coordinates":[44.37454,56.21016],"type":"Point"}
}