{
  "type": "Feature",
  "properties": {
    "gn:admin1_code":"4",
    "gn:asciiname":"Novopokrovka",
    "gn:country_code":"RU",
    "gn:dem":180,
    "gn:feature_class":"P",
    "gn:feature_code":"PPL",
    "gn:name":"Novopokrovka",
    "gn:population":700,
    "gn:timezone":"Asia/Barnaul",
    "iso:country":"RU",
    "name:eng_x_preferred":[
        "Novopokrovka"
    ],
    "name:nor_x_preferred":[
        "Novopokrovskoje"
    ],
    "name:rus_x_preferred":[
        "\u041d\u043e\u0432\u043e\u043f\u043e\u043a\u0440\u043e\u0432\u0441\u043a\u043e\u0435"
    ],
    "name:rus_x_variant":[
        "\u041d\u043e\u0432\u043e\u043f\u043e\u043a\u0440\u043e\u0432\u043a\u0430"
    ],
    "name:und_x_variant":[
        "Novopokrovskoye"
    ],
    "wof:name":"Novopokrovka",
    "wof:placetype":"locality",
    "wof:population":700
},
  "geometry": {"coordinates":[84.4353,52.2221],"type":"Point"}
}