{
  "type": "Feature",
  "properties": {
    "gn:admin1_code":"4",
    "gn:asciiname":"Mokhovoye",
    "gn:country_code":"RU",
    "gn:dem":182,
    "gn:feature_class":"P",
    "gn:feature_code":"PPL",
    "gn:name":"Mokhovoye",
    "gn:population":0,
    "gn:timezone":"Asia/Barnaul",
    "iso:country":"RU",
    "name:rus_x_preferred":[
        "\u041c\u043e\u0445\u043e\u0432\u043e\u0435"
    ],
    "name:und_x_variant":[
        "Mokhovoy",
        "Mokhovoye"
    ],
    "wof:name":"Mokhovoye",
    "wof:placetype":"locality"
},
  "geometry": {"coordinates":[83.45860999999999,53.25056],"type":"Point"}
}