{
  "type": "Feature",
  "properties": {
    "gn:admin1_code":"24.0",
    "gn:asciiname":"Bor Khuduk",
    "gn:country_code":"RU",
    "gn:dem":1,
    "gn:feature_class":"P",
    "gn:feature_code":"PPL",
    "gn:name":"Bor Khuduk",
    "gn:population":0,
    "gn:timezone":"Europe/Moscow",
    "iso:country":"RU",
    "name:rus_x_preferred":[
        "\u0411\u043e\u0440 \u0425\u0443\u0434\u0443\u043a"
    ],
    "wof:name":"Bor Khuduk",
    "wof:placetype":"locality"
},
  "geometry": {"coordinates":[45.68872,47.53909],"type":"Point"}
}