{
  "type": "Feature",
  "properties": {
    "gn:admin1_code":"8",
    "gn:asciiname":"Barsuan",
    "gn:country_code":"RU",
    "gn:dem":187,
    "gn:feature_class":"P",
    "gn:feature_code":"PPL",
    "gn:name":"Barsuan",
    "gn:population":0,
    "gn:timezone":"Asia/Yekaterinburg",
    "iso:country":"RU",
    "name:bak_x_preferred":[
        "\u0411\u04d9\u0440\u04ab\u0435\u04af\u04d9\u043d"
    ],
    "name:che_x_preferred":[
        "\u0411\u0430\u0440\u0441\u0443\u0430\u043d"
    ],
    "name:hye_x_preferred":[
        "\u0532\u0561\u0580\u057d\u0578\u0582\u0561\u0576"
    ],
    "name:kaz_x_preferred":[
        "\u0411\u0430\u0440\u0441\u0443\u0430\u043d"
    ],
    "name:kir_x_preferred":[
        "\u0411\u0430\u0440\u0441\u0443\u0430\u043d"
    ],
    "name:rus_x_preferred":[
        "\u0411\u0430\u0440\u0441\u0443\u0430\u043d"
    ],
    "name:tat_x_preferred":[
        "\u0411\u04d9\u0440\u0441\u04af\u04d9\u043d"
    ],
    "name:und_x_variant":[
        "\u0411\u0430\u0440\u0441\u0443\u0430\u043d"
    ],
    "wof:name":"Barsuan",
    "wof:placetype":"locality"
},
  "geometry": {"coordinates":[55.1215,54.6198],"type":"Point"}
}