{
  "type": "Feature",
  "properties": {
    "gn:admin1_code":"8",
    "gn:asciiname":"Barsuan",
    "gn:country_code":"RU",
    "gn:dem":187,
    "gn:feature_class":"P",
    "gn:feature_code":"PPL",
    "gn:name":"Barsuan",
    "gn:population":0,
    "gn:timezone":"Asia/Yekaterinburg",
    "iso:country":"RU",
    "name:rus_x_preferred":[
        "\u0411\u0430\u0440\u0441\u0443\u0430\u043d"
    ],
    "name:und_x_variant":[
        "\u0411\u0430\u0440\u0441\u0443\u0430\u043d"
    ],
    "wof:name":"Barsuan",
    "wof:placetype":"locality"
},
  "geometry": {"coordinates":[55.1215,54.6198],"type":"Point"}
}