{
  "type": "Feature",
  "properties": {
    "gn:admin1_code":"90.0",
    "gn:asciiname":"Aterskiy",
    "gn:country_code":"RU",
    "gn:dem":240,
    "gn:feature_class":"P",
    "gn:feature_code":"PPL",
    "gn:name":"Aterskiy",
    "gn:population":0,
    "gn:timezone":"Asia/Yekaterinburg",
    "iso:country":"RU",
    "name:rus_x_preferred":[
        "\u0410\u0442\u0435\u0440\u0441\u043a\u0438\u0439"
    ],
    "wof:name":"Aterskiy",
    "wof:placetype":"locality"
},
  "geometry": {"coordinates":[56.80092,56.47898000000001],"type":"Point"}
}