{
  "type": "Feature",
  "properties": {
    "gn:admin1_code":"4",
    "gn:asciiname":"Oskolkovo",
    "gn:country_code":"RU",
    "gn:dem":185,
    "gn:feature_class":"P",
    "gn:feature_code":"PPL",
    "gn:name":"Oskolkovo",
    "gn:population":0,
    "gn:timezone":"Asia/Barnaul",
    "iso:country":"RU",
    "name:che_x_preferred":[
        "\u041e\u0441\u043a\u043e\u043b\u043a\u043e\u0432\u043e"
    ],
    "name:eng_x_preferred":[
        "Oskolkovo"
    ],
    "name:ita_x_preferred":[
        "Oskolkovo"
    ],
    "name:nor_x_preferred":[
        "Oskolkovo"
    ],
    "name:rus_x_preferred":[
        "\u041e\u0441\u043a\u043e\u043b\u043a\u043e\u0432\u043e"
    ],
    "name:und_x_variant":[
        "Oskolovo",
        "Oskolovskoye"
    ],
    "wof:name":"Oskolkovo",
    "wof:placetype":"locality"
},
  "geometry": {"coordinates":[83.1639,52.3205],"type":"Point"}
}