{
  "type": "Feature",
  "properties": {
    "gn:admin1_code":"72",
    "gn:asciiname":"Put'",
    "gn:country_code":"RU",
    "gn:dem":154,
    "gn:feature_class":"P",
    "gn:feature_code":"PPL",
    "gn:name":"Put\u2019",
    "gn:population":0,
    "gn:timezone":"Europe/Moscow",
    "iso:country":"RU",
    "name:rus_x_preferred":[
        "\u041f\u0443\u0442\u044c"
    ],
    "name:und_x_variant":[
        "Put\u2019"
    ],
    "wof:name":"Put'",
    "wof:placetype":"locality"
},
  "geometry": {"coordinates":[43.01667,52.55],"type":"Point"}
}