{
  "type": "Feature",
  "properties": {
    "gn:admin1_code":"54",
    "gn:asciiname":"Chernigovka",
    "gn:country_code":"RU",
    "gn:dem":95,
    "gn:feature_class":"P",
    "gn:feature_code":"PPL",
    "gn:name":"Chernigovka",
    "gn:population":0,
    "gn:timezone":"Asia/Omsk",
    "iso:country":"RU",
    "name:rus_x_preferred":[
        "\u0427\u0435\u0440\u043d\u0438\u0433\u043e\u0432\u043a\u0430"
    ],
    "wof:name":"Chernigovka",
    "wof:placetype":"locality"
},
  "geometry": {"coordinates":[73.48295,54.58827],"type":"Point"}
}