{
  "type": "Feature",
  "properties": {
    "gn:admin1_code":"69",
    "gn:asciiname":"Tomashevka",
    "gn:country_code":"RU",
    "gn:dem":214,
    "gn:feature_class":"P",
    "gn:feature_code":"PPL",
    "gn:name":"Tomash\u00ebvka",
    "gn:population":0,
    "gn:timezone":"Europe/Moscow",
    "iso:country":"RU",
    "name:rus_x_preferred":[
        "\u0422\u043e\u043c\u0430\u0448\u0451\u0432\u043a\u0430"
    ],
    "name:und_x_variant":[
        "Tomash\u00ebvka"
    ],
    "wof:name":"Tomashevka",
    "wof:placetype":"locality"
},
  "geometry": {"coordinates":[32.12295,54.68145],"type":"Point"}
}