{
  "type": "Feature",
  "properties": {
    "gn:admin1_code":"65",
    "gn:asciiname":"Dolinovka",
    "gn:country_code":"RU",
    "gn:dem":71,
    "gn:feature_class":"P",
    "gn:feature_code":"PPL",
    "gn:name":"Dolinovka",
    "gn:population":0,
    "gn:timezone":"Europe/Samara",
    "iso:country":"RU",
    "name:rus_x_preferred":[
        "\u0414\u043e\u043b\u0438\u043d\u043e\u0432\u043a\u0430"
    ],
    "wof:name":"Dolinovka",
    "wof:placetype":"locality"
},
  "geometry": {"coordinates":[50.5183,54.2294],"type":"Point"}
}