{
  "type": "Feature",
  "properties": {
    "gn:admin1_code":"83",
    "gn:asciiname":"Zagryazhskoye",
    "gn:country_code":"RU",
    "gn:dem":112,
    "gn:feature_class":"P",
    "gn:feature_code":"PPL",
    "gn:name":"Zagryazhskoye",
    "gn:population":0,
    "gn:timezone":"Europe/Moscow",
    "iso:country":"RU",
    "name:rus_x_preferred":[
        "\u0417\u0430\u0433\u0440\u044f\u0436\u0441\u043a\u043e\u0435"
    ],
    "wof:name":"Zagryazhskoye",
    "wof:placetype":"locality"
},
  "geometry": {"coordinates":[42.035,55.495],"type":"Point"}
}