{
  "type": "Feature",
  "properties": {
    "gn:admin1_code":"77",
    "gn:asciiname":"Pologi",
    "gn:country_code":"RU",
    "gn:dem":146,
    "gn:feature_class":"P",
    "gn:feature_code":"PPL",
    "gn:name":"Pologi",
    "gn:population":0,
    "gn:timezone":"Europe/Moscow",
    "iso:country":"RU",
    "name:rus_x_preferred":[
        "\u041f\u043e\u043b\u043e\u0433\u0438"
    ],
    "wof:name":"Pologi",
    "wof:placetype":"locality"
},
  "geometry": {"coordinates":[36.6825,58.0648],"type":"Point"}
}