{
  "type": "Feature",
  "properties": {
    "gn:country":"RU",
    "gn:fcode":"PPL",
    "gn:pop":0,
    "iso:country":"RU",
    "name:eng_x_preferred":[
        "Oktyabr'skiy"
    ],
    "name:nor_x_preferred":[
        "Oktjabrskij"
    ],
    "name:rus_x_preferred":[
        "Oktyabr\u2019skiy"
    ],
    "name:rus_x_variant":[
        "\u041e\u043a\u0442\u044f\u0431\u0440\u044c\u0441\u043a\u0438\u0439"
    ],
    "name:unk_x_variant":[
        "\u041e\u043a\u0442\u044f\u0431\u0440\u044c\u0441\u043a\u0438\u0439"
    ],
    "qs:name":"Oktyabr'skij",
    "qs:name_adm0":"Russia",
    "qs:name_adm1":"Tatarstan Republic",
    "qs:photos_9k":1,
    "qs:photos_9r":1,
    "qs:photos_all":12,
    "qs:photos_sr":0,
    "qs:placetype":"Town",
    "qs:pop_sr":"0",
    "wof:name":"Oktyabr'skij",
    "wof:placetype":"locality",
    "wof:population":0
},
  "geometry": {"coordinates":[48.79837,55.83236],"type":"Point"}
}