{
  "type": "Feature",
  "properties": {
    "gn:admin1_code":"54",
    "gn:asciiname":"Yasnaya Polyana",
    "gn:country_code":"RU",
    "gn:dem":116,
    "gn:feature_class":"P",
    "gn:feature_code":"PPL",
    "gn:name":"Yasnaya Polyana",
    "gn:population":0,
    "gn:timezone":"Asia/Omsk",
    "iso:country":"RU",
    "wof:name":"Yasnaya Polyana",
    "wof:placetype":"locality"
},
  "geometry": {"coordinates":[71.68947,54.79361],"type":"Point"}
}