{
  "type": "Feature",
  "properties": {
    "gn:admin1_code":"16",
    "gn:asciiname":"Korak-Churachiki",
    "gn:country_code":"RU",
    "gn:dem":141,
    "gn:feature_class":"P",
    "gn:feature_code":"PPL",
    "gn:name":"Korak-Churachiki",
    "gn:population":0,
    "gn:timezone":"Europe/Moscow",
    "iso:country":"RU",
    "name:rus_x_preferred":[
        "\u041a\u043e\u0440\u0430\u043a-\u0427\u0443\u0440\u0430\u0447\u0438\u043a\u0438"
    ],
    "name:und_x_variant":[
        "Korak-Churatchiki",
        "Korak-Churachiki"
    ],
    "wof:name":"Korak-Churachiki",
    "wof:placetype":"locality"
},
  "geometry": {"coordinates":[46.94561,55.99732],"type":"Point"}
}