{
  "type": "Feature",
  "properties": {
    "gn:admin1_code":"9",
    "gn:asciiname":"Khmyzovka",
    "gn:country_code":"RU",
    "gn:dem":99,
    "gn:feature_class":"P",
    "gn:feature_code":"PPL",
    "gn:name":"Khmyzovka",
    "gn:population":0,
    "gn:timezone":"Europe/Moscow",
    "iso:country":"RU",
    "name:rus_x_preferred":[
        "\u0425\u043c\u044b\u0437\u043e\u0432\u043a\u0430"
    ],
    "wof:name":"Khmyzovka",
    "wof:placetype":"locality"
},
  "geometry": {"coordinates":[38.9596,50.3334],"type":"Point"}
}