{
  "type": "Feature",
  "properties": {
    "gn:admin1_code":"88",
    "gn:asciiname":"Tret'yakovka",
    "gn:country_code":"RU",
    "gn:dem":120,
    "gn:feature_class":"P",
    "gn:feature_code":"PPL",
    "gn:name":"Tret\u2019yakovka",
    "gn:population":0,
    "gn:timezone":"Europe/Moscow",
    "iso:country":"RU",
    "name:rus_x_preferred":[
        "\u0422\u0440\u0435\u0442\u044c\u044f\u043a\u043e\u0432\u043a\u0430"
    ],
    "name:und_x_variant":[
        "Tret\u2019yakovka",
        "\u0422\u0440\u0435\u0442\u044c\u044f\u043a\u043e\u0432\u043a\u0430"
    ],
    "wof:name":"Tret'yakovka",
    "wof:placetype":"locality"
},
  "geometry": {"coordinates":[38.45413,57.85568000000001],"type":"Point"}
}