{
  "type": "Feature",
  "properties": {
    "gn:admin1_code":"8",
    "gn:asciiname":"Nur",
    "gn:country_code":"RU",
    "gn:dem":124,
    "gn:feature_class":"P",
    "gn:feature_code":"PPL",
    "gn:name":"Nur",
    "gn:population":0,
    "gn:timezone":"Asia/Yekaterinburg",
    "iso:country":"RU",
    "name:rus_x_preferred":[
        "\u041d\u0443\u0440"
    ],
    "name:und_x_variant":[
        "\u041d\u0443\u0440"
    ],
    "wof:name":"Nur",
    "wof:placetype":"locality"
},
  "geometry": {"coordinates":[56.93458,55.15779000000001],"type":"Point"}
}