{
  "type": "Feature",
  "properties": {
    "gn:admin1_code":"1.0",
    "gn:asciiname":"Derevskiy",
    "gn:country_code":"RU",
    "gn:dem":163,
    "gn:feature_class":"P",
    "gn:feature_code":"PPL",
    "gn:name":"Derevskiy",
    "gn:population":0,
    "gn:timezone":"Europe/Moscow",
    "iso:country":"RU",
    "name:rus_x_preferred":[
        "\u0414\u0435\u0440\u0435\u0432\u0441\u043a\u0438\u0439"
    ],
    "wof:name":"Derevskiy",
    "wof:placetype":"locality"
},
  "geometry": {"coordinates":[40.46972,44.83417],"type":"Point"}
}