{
  "type": "Feature",
  "properties": {
    "gn:admin1_code":"28",
    "gn:asciiname":"Megrozero",
    "gn:country_code":"RU",
    "gn:dem":92,
    "gn:feature_class":"P",
    "gn:feature_code":"PPL",
    "gn:name":"Megrozero",
    "gn:population":0,
    "gn:timezone":"Europe/Moscow",
    "iso:country":"RU",
    "name:eng_x_preferred":[
        "Megrozero"
    ],
    "name:fin_x_preferred":[
        "M\u00e4gr\u00e4tj\u00e4rvi"
    ],
    "name:nor_x_preferred":[
        "Megrozero"
    ],
    "name:und_x_variant":[
        "\u041c\u0435\u0433\u0440\u043e\u0437\u0435\u0440\u043e",
        "Megrozero"
    ],
    "wof:name":"Megrozero",
    "wof:placetype":"locality"
},
  "geometry": {"coordinates":[33.48976,61.03335],"type":"Point"}
}