{
  "type": "Feature",
  "properties": {
    "gn:admin1_code":"59",
    "gn:asciiname":"Zvezdochka",
    "gn:cc2":"RU",
    "gn:country_code":"RU",
    "gn:dem":129,
    "gn:feature_class":"P",
    "gn:feature_code":"PPL",
    "gn:name":"Zv\u00ebzdochka",
    "gn:population":0,
    "gn:timezone":"Asia/Vladivostok",
    "iso:country":"RU",
    "name:und_x_variant":[
        "Zuezdochka",
        "Zv\u00ebzdochka"
    ],
    "wof:name":"Zvezdochka",
    "wof:placetype":"locality"
},
  "geometry": {"coordinates":[133.71666999999999,42.98333],"type":"Point"}
}