{
  "type": "Feature",
  "properties": {
    "gn:admin1_code":"6",
    "gn:asciiname":"Komsomol'skiy",
    "gn:cc2":"RU",
    "gn:country_code":"RU",
    "gn:dem":67,
    "gn:feature_class":"P",
    "gn:feature_code":"PPL",
    "gn:name":"Komsomol'skiy",
    "gn:population":0,
    "gn:timezone":"Europe/Moscow",
    "iso:country":"RU",
    "name:und_x_variant":[
        "Oktyabr'skiy"
    ],
    "wof:name":"Komsomol'skiy",
    "wof:placetype":"locality"
},
  "geometry": {"coordinates":[42.13333,61.08333],"type":"Point"}
}