{
  "type": "Feature",
  "properties": {
    "gn:admin1_code":"8",
    "gn:asciiname":"Lyubovka",
    "gn:country_code":"RU",
    "gn:dem":247,
    "gn:feature_class":"P",
    "gn:feature_code":"PPL",
    "gn:name":"Lyubovka",
    "gn:population":0,
    "gn:timezone":"Asia/Yekaterinburg",
    "iso:country":"RU",
    "name:bul_x_preferred":[
        "\u041b\u044e\u0431\u043e\u0432\u043a\u0430"
    ],
    "name:fas_x_preferred":[
        "\u0644\u06cc\u0648\u0628\u0648\u0648\u06a9\u0627"
    ],
    "name:kaz_x_preferred":[
        "\u041b\u044e\u0431\u043e\u0432\u043a\u0430"
    ],
    "name:mkd_x_preferred":[
        "\u0409\u0443\u0431\u043e\u0432\u043a\u0430"
    ],
    "name:pol_x_preferred":[
        "Lubowka"
    ],
    "name:ron_x_preferred":[
        "Liubovka"
    ],
    "name:rus_x_preferred":[
        "\u041b\u044e\u0431\u043e\u0432\u043a\u0430"
    ],
    "name:ukr_x_preferred":[
        "\u041b\u044e\u0431\u043e\u0432\u043a\u0430"
    ],
    "name:und_x_variant":[
        "\u041b\u044e\u0431\u043e\u0432\u043a\u0430"
    ],
    "wof:name":"Lyubovka",
    "wof:placetype":"locality"
},
  "geometry": {"coordinates":[55.76667,53.01667],"type":"Point"}
}