{
  "type": "Feature",
  "properties": {
    "gn:admin1_code":"38",
    "gn:asciiname":"Prorvenskiy",
    "gn:country_code":"RU",
    "gn:dem":0,
    "gn:feature_class":"P",
    "gn:feature_code":"PPL",
    "gn:name":"Prorvenskiy",
    "gn:population":0,
    "gn:timezone":"Europe/Moscow",
    "iso:country":"RU",
    "name:eng_x_preferred":[
        "Prorvenskiy"
    ],
    "name:nor_x_preferred":[
        "Prorvenskij"
    ],
    "name:rus_x_preferred":[
        "\u041f\u0440\u043e\u0440\u0432\u0435\u043d\u0441\u043a\u0438\u0439"
    ],
    "name:und_x_variant":[
        "Prorva",
        "\u041f\u0440\u043e\u0440\u0432\u0435\u043d\u0441\u043a\u0438\u0439",
        "Prorvenskiy"
    ],
    "wof:name":"Prorvenskiy",
    "wof:placetype":"locality"
},
  "geometry": {"coordinates":[37.70415,45.53129000000001],"type":"Point"}
}