{
  "type": "Feature",
  "properties": {
    "gn:admin1_code":"10",
    "gn:asciiname":"Rudnya-Terekhovka",
    "gn:country_code":"RU",
    "gn:dem":151,
    "gn:feature_class":"P",
    "gn:feature_code":"PPL",
    "gn:name":"Rudnya-Terekhovka",
    "gn:population":0,
    "gn:timezone":"Europe/Moscow",
    "iso:country":"RU",
    "name:rus_x_preferred":[
        "\u0420\u0443\u0434\u043d\u044f-\u0422\u0435\u0440\u0435\u0445\u043e\u0432\u043a\u0430"
    ],
    "wof:name":"Rudnya-Terekhovka",
    "wof:placetype":"locality"
},
  "geometry": {"coordinates":[32.33600999999999,52.83504],"type":"Point"}
}