{
  "type": "Feature",
  "properties": {
    "gn:admin1_code":"85",
    "gn:asciiname":"Pryadino",
    "gn:country_code":"RU",
    "gn:dem":148,
    "gn:feature_class":"P",
    "gn:feature_code":"PPL",
    "gn:name":"Pryadino",
    "gn:population":0,
    "gn:timezone":"Europe/Moscow",
    "iso:country":"RU",
    "name:rus_x_preferred":[
        "\u041f\u0440\u044f\u0434\u0438\u043d\u043e"
    ],
    "wof:name":"Pryadino",
    "wof:placetype":"locality"
},
  "geometry": {"coordinates":[38.6513,59.4168],"type":"Point"}
}