{
  "type": "Feature",
  "properties": {
    "gn:admin1_code":"51",
    "gn:asciiname":"Zhuravli",
    "gn:country_code":"RU",
    "gn:dem":150,
    "gn:feature_class":"P",
    "gn:feature_code":"PPL",
    "gn:name":"Zhuravli",
    "gn:population":0,
    "gn:timezone":"Europe/Moscow",
    "iso:country":"RU",
    "name:ara_x_preferred":[
        "\u0642\u0635\u064a\u062f\u0629 \u0627\u0644\u0644\u0642\u0627\u0644\u0642"
    ],
    "name:ava_x_preferred":[
        "\u0425\u044a\u0430\u0445\u04c0\u0430\u043b \u043a\u044a\u0443\u043d\u043a\u044a\u0440\u0430\u0431\u0438"
    ],
    "name:eng_x_preferred":[
        "Zhuravli"
    ],
    "name:fin_x_preferred":[
        "Kurjet"
    ],
    "name:fra_x_preferred":[
        "Jouravli"
    ],
    "name:glg_x_preferred":[
        "Zhuravli"
    ],
    "name:ita_x_preferred":[
        "\u017duravli"
    ],
    "name:nld_x_preferred":[
        "Zjoeravli"
    ],
    "name:nor_x_preferred":[
        "Zjuravli"
    ],
    "name:rus_x_preferred":[
        "\u0416\u0443\u0440\u0430\u0432\u043b\u0438"
    ],
    "name:srp_x_preferred":[
        "\u0416\u0443\u0440\u0430\u0432\u043b\u0438"
    ],
    "name:swe_x_preferred":[
        "Zjuravli"
    ],
    "name:tur_x_preferred":[
        "Juravli"
    ],
    "name:und_x_variant":[
        "Murav\u2019yevskaya",
        "Zhuravli",
        "\u0416\u0443\u0440\u0430\u0432\u043b\u0438"
    ],
    "name:vie_x_preferred":[
        "\u0110\u00e0n s\u1ebfu"
    ],
    "wof:name":"Zhuravli",
    "wof:placetype":"locality"
},
  "geometry": {"coordinates":[46.65849,57.87181999999999],"type":"Point"}
}