{
  "type": "Feature",
  "properties": {
    "gn:admin1_code":"51",
    "gn:asciiname":"Zhuravli",
    "gn:country_code":"RU",
    "gn:dem":150,
    "gn:feature_class":"P",
    "gn:feature_code":"PPL",
    "gn:name":"Zhuravli",
    "gn:population":0,
    "gn:timezone":"Europe/Moscow",
    "iso:country":"RU",
    "name:eng_x_preferred":[
        "Zhuravli"
    ],
    "name:nor_x_preferred":[
        "Zjuravli"
    ],
    "name:rus_x_preferred":[
        "\u0416\u0443\u0440\u0430\u0432\u043b\u0438"
    ],
    "name:und_x_variant":[
        "Murav\u2019yevskaya",
        "Zhuravli",
        "\u0416\u0443\u0440\u0430\u0432\u043b\u0438"
    ],
    "wof:name":"Zhuravli",
    "wof:placetype":"locality"
},
  "geometry": {"coordinates":[46.65849,57.87181999999999],"type":"Point"}
}