{
  "type": "Feature",
  "properties": {
    "gn:admin1_code":"60",
    "gn:asciiname":"Bol'shaya Zhaduanka",
    "gn:country_code":"RU",
    "gn:dem":44,
    "gn:feature_class":"P",
    "gn:feature_code":"PPL",
    "gn:name":"Bol\u2019shaya Zhaduanka",
    "gn:population":0,
    "gn:timezone":"Europe/Moscow",
    "iso:country":"RU",
    "name:rus_x_preferred":[
        "\u0411\u043e\u043b\u044c\u0448\u0430\u044f \u0416\u0430\u0434\u0443\u0430\u043d\u043a\u0430"
    ],
    "name:und_x_variant":[
        "Bol\u2019shaya Zhadunka",
        "Bol\u2019shaya Zhaduanka"
    ],
    "wof:name":"Bol'shaya Zhaduanka",
    "wof:placetype":"locality"
},
  "geometry": {"coordinates":[28.5246,57.7241],"type":"Point"}
}