{
  "type": "Feature",
  "properties": {
    "gn:admin1_code":"73",
    "gn:asciiname":"Vostochnaya Zvezda",
    "gn:country_code":"RU",
    "gn:dem":148,
    "gn:feature_class":"P",
    "gn:feature_code":"PPL",
    "gn:name":"Vostochnaya Zvezda",
    "gn:population":0,
    "gn:timezone":"Europe/Moscow",
    "iso:country":"RU",
    "name:rus_x_preferred":[
        "\u0412\u043e\u0441\u0442\u043e\u0447\u043d\u0430\u044f \u0417\u0432\u0435\u0437\u0434\u0430"
    ],
    "name:rus_x_variant":[
        "Zv\u00ebzdochka"
    ],
    "wof:name":"Vostochnaya Zvezda",
    "wof:placetype":"locality"
},
  "geometry": {"coordinates":[48.7688,55.771],"type":"Point"}
}