{
  "type": "Feature",
  "properties": {
    "gn:admin1_code":"20",
    "gn:asciiname":"Savvateyevka",
    "gn:cc2":"RU",
    "gn:country_code":"RU",
    "gn:dem":456,
    "gn:feature_class":"P",
    "gn:feature_code":"PPL",
    "gn:name":"Savvateyevka",
    "gn:population":0,
    "gn:timezone":"Asia/Irkutsk",
    "iso:country":"RU",
    "name:eng_x_preferred":[
        "Savvateyevka"
    ],
    "name:nor_x_preferred":[
        "Savvatejevka"
    ],
    "name:rus_x_preferred":[
        "\u0421\u0430\u0432\u0432\u0430\u0442\u0435\u0435\u0432\u043a\u0430"
    ],
    "name:und_x_variant":[
        "Savvatayevka",
        "Savateyevka",
        "\u0421\u0430\u0432\u0432\u0430\u0442\u0435\u0435\u0432\u043a\u0430",
        "Savvateyevka"
    ],
    "wof:name":"Savvateyevka",
    "wof:placetype":"locality"
},
  "geometry": {"coordinates":[103.64,52.33333],"type":"Point"}
}