{
  "type": "Feature",
  "properties": {
    "gn:admin1_code":"60",
    "gn:asciiname":"Zaol'khov'ye",
    "gn:country_code":"RU",
    "gn:dem":89,
    "gn:feature_class":"P",
    "gn:feature_code":"PPL",
    "gn:name":"Zaol\u2019khov\u2019ye",
    "gn:population":0,
    "gn:timezone":"Europe/Moscow",
    "iso:country":"RU",
    "name:rus_x_preferred":[
        "\u0417\u0430\u043e\u043b\u044c\u0445\u043e\u0432\u044c\u0435"
    ],
    "name:und_x_variant":[
        "Zaol\u2019khov\u2019ye",
        "\u0417\u0430\u043e\u043b\u044c\u0445\u043e\u0432\u044c\u0435"
    ],
    "wof:name":"Zaol'khov'ye",
    "wof:placetype":"locality"
},
  "geometry": {"coordinates":[30.4847,57.80907],"type":"Point"}
}