{
  "type": "Feature",
  "properties": {
    "gn:admin1_code":"37",
    "gn:asciiname":"Severyanka",
    "gn:country_code":"RU",
    "gn:dem":173,
    "gn:feature_class":"P",
    "gn:feature_code":"PPL",
    "gn:name":"Severyanka",
    "gn:population":0,
    "gn:timezone":"Europe/Moscow",
    "iso:country":"RU",
    "name:eng_x_preferred":[
        "Severyanka"
    ],
    "name:nor_x_preferred":[
        "Severjanka"
    ],
    "name:rus_x_preferred":[
        "\u0421\u0435\u0432\u0435\u0440\u044f\u043d\u043a\u0430"
    ],
    "wof:name":"Severyanka",
    "wof:placetype":"locality"
},
  "geometry": {"coordinates":[46.39342,59.24596999999999],"type":"Point"}
}