{
  "type": "Feature",
  "properties": {
    "gn:admin1_code":"17.0",
    "gn:asciiname":"Staroterechnoye",
    "gn:country_code":"RU",
    "gn:dem":-26,
    "gn:feature_class":"P",
    "gn:feature_code":"PPL",
    "gn:name":"Staroterechnoye",
    "gn:population":0,
    "gn:timezone":"Europe/Moscow",
    "iso:country":"RU",
    "name:eng_x_preferred":[
        "Staroterechnoye"
    ],
    "name:nor_x_preferred":[
        "Staroteretsjnoje"
    ],
    "name:rus_x_preferred":[
        "\u0421\u0442\u0430\u0440\u043e\u0442\u0435\u0440\u0435\u0447\u043d\u043e\u0435"
    ],
    "name:und_x_variant":[
        "Staroterennyy",
        "\u0421\u0442\u0430\u0440\u043e\u0442\u0435\u0440\u0435\u0447\u043d\u043e\u0435",
        "Staroterechnoye"
    ],
    "wof:name":"Staroterechnoye",
    "wof:placetype":"locality"
},
  "geometry": {"coordinates":[47.46163,43.85585],"type":"Point"}
}