{
  "type": "Feature",
  "properties": {
    "gn:admin1_code":"10",
    "gn:asciiname":"Novoye Zaduben'ye",
    "gn:country_code":"RU",
    "gn:dem":188,
    "gn:feature_class":"P",
    "gn:feature_code":"PPL",
    "gn:name":"Novoye Zaduben\u2019ye",
    "gn:population":0,
    "gn:timezone":"Europe/Moscow",
    "iso:country":"RU",
    "name:rus_x_preferred":[
        "\u041d\u043e\u0432\u043e\u0435 \u0417\u0430\u0434\u0443\u0431\u0435\u043d\u044c\u0435"
    ],
    "name:und_x_variant":[
        "Novoye Zaduben\u2019ye",
        "\u041d\u043e\u0432\u043e\u0435 \u0417\u0430\u0434\u0443\u0431\u0435\u043d\u044c\u0435"
    ],
    "wof:name":"Novoye Zaduben'ye",
    "wof:placetype":"locality"
},
  "geometry": {"coordinates":[33.03879000000001,52.81036999999999],"type":"Point"}
}