{
  "type": "Feature",
  "properties": {
    "gn:admin1_code":"20",
    "gn:asciiname":"Bratskiy Bor",
    "gn:country_code":"RU",
    "gn:dem":356,
    "gn:feature_class":"P",
    "gn:feature_code":"PPL",
    "gn:name":"Bratskiy Bor",
    "gn:population":0,
    "gn:timezone":"Asia/Irkutsk",
    "iso:country":"RU",
    "name:rus_x_preferred":[
        "\u0411\u0440\u0430\u0442\u0441\u043a\u0438\u0439 \u0411\u043e\u0440"
    ],
    "wof:name":"Bratskiy Bor",
    "wof:placetype":"locality"
},
  "geometry": {"coordinates":[99.3558,55.1137],"type":"Point"}
}