{
  "type": "Feature",
  "properties": {
    "gn:admin1_code":"69.0",
    "gn:asciiname":"Bogoroditskoye",
    "gn:country_code":"RU",
    "gn:dem":230,
    "gn:feature_class":"P",
    "gn:feature_code":"PPL",
    "gn:name":"Bogoroditskoye",
    "gn:population":0,
    "gn:timezone":"Europe/Moscow",
    "iso:country":"RU",
    "name:eng_x_preferred":[
        "Bogoroditskoye"
    ],
    "name:nor_x_preferred":[
        "Bogoroditskoje"
    ],
    "name:rus_x_preferred":[
        "\u0411\u043e\u0433\u043e\u0440\u043e\u0434\u0438\u0446\u043a\u043e\u0435"
    ],
    "name:rus_x_variant":[
        "\u0411\u043e\u0433\u043e\u0440\u043e\u0434\u0438\u0442\u0441\u043a\u043e\u0435"
    ],
    "name:und_x_variant":[
        "\u0411\u043e\u0433\u043e\u0440\u043e\u0434\u0438\u0442\u0441\u043a\u043e\u0435"
    ],
    "wof:name":"Bogoroditskoye",
    "wof:placetype":"locality"
},
  "geometry": {"coordinates":[33.29322,54.65926],"type":"Point"}
}