{
  "type": "Feature",
  "properties": {
    "gn:admin1_code":"3",
    "gn:asciiname":"Sugul",
    "gn:cc2":"RU",
    "gn:country_code":"RU",
    "gn:dem":392,
    "gn:feature_class":"P",
    "gn:feature_code":"PPL",
    "gn:name":"Sugul",
    "gn:population":0,
    "gn:timezone":"Asia/Omsk",
    "iso:country":"RU",
    "name:che_x_preferred":[
        "\u0421\u0443\u0433\u0443\u043b"
    ],
    "name:eng_x_preferred":[
        "Sugul"
    ],
    "name:nor_x_preferred":[
        "Sugul"
    ],
    "name:rus_x_preferred":[
        "\u0421\u0443\u0433\u0443\u043b"
    ],
    "name:tat_x_preferred":[
        "\u0421\u0443\u0433\u0443\u043b"
    ],
    "name:ukr_x_preferred":[
        "\u0421\u0443\u0433\u0443\u043b"
    ],
    "name:und_x_variant":[
        "Verkhniy Sugul"
    ],
    "wof:name":"Sugul",
    "wof:placetype":"locality"
},
  "geometry": {"coordinates":[86.27139,51.94556],"type":"Point"}
}