{
  "type": "Feature",
  "properties": {
    "gn:admin1_code":"80",
    "gn:asciiname":"Sharshada",
    "gn:country_code":"RU",
    "gn:dem":157,
    "gn:feature_class":"P",
    "gn:feature_code":"PPL",
    "gn:name":"Sharshada",
    "gn:population":0,
    "gn:timezone":"Europe/Samara",
    "iso:country":"RU",
    "name:rus_x_preferred":[
        "\u0428\u0430\u0440\u0448\u0430\u0434\u0430"
    ],
    "name:und_x_variant":[
        "\u0428\u0430\u0440\u0448\u0430\u0434\u0430"
    ],
    "wof:name":"Sharshada",
    "wof:placetype":"locality"
},
  "geometry": {"coordinates":[52.41038,56.24141],"type":"Point"}
}