{
  "type": "Feature",
  "properties": {
    "gn:admin1_code":"8",
    "gn:asciiname":"Isyangazino",
    "gn:country_code":"RU",
    "gn:dem":351,
    "gn:feature_class":"P",
    "gn:feature_code":"PPL",
    "gn:name":"Isyangazino",
    "gn:population":0,
    "gn:timezone":"Asia/Yekaterinburg",
    "iso:country":"RU",
    "name:eng_x_preferred":[
        "Isyangazino"
    ],
    "name:nor_x_preferred":[
        "Isiangazino"
    ],
    "name:rus_x_preferred":[
        "\u0418\u0441\u044f\u043d\u0433\u0430\u0437\u0438\u043d\u043e"
    ],
    "name:und_x_variant":[
        "\u0418\u0441\u044f\u043d\u0433\u0430\u0437\u0438\u043d\u043e",
        "Isyangazino"
    ],
    "wof:name":"Isyangazino",
    "wof:placetype":"locality"
},
  "geometry": {"coordinates":[57.4467,52.9509],"type":"Point"}
}