{
  "type": "Feature",
  "properties": {
    "gn:admin1_code":"8",
    "gn:asciiname":"Orlovka",
    "gn:country_code":"RU",
    "gn:dem":157,
    "gn:feature_class":"P",
    "gn:feature_code":"PPL",
    "gn:name":"Orlovka",
    "gn:population":0,
    "gn:timezone":"Asia/Yekaterinburg",
    "iso:country":"RU",
    "name:rus_x_preferred":[
        "\u041e\u0440\u043b\u043e\u0432\u043a\u0430"
    ],
    "wof:name":"Orlovka",
    "wof:placetype":"locality"
},
  "geometry": {"coordinates":[55.37035,53.77541],"type":"Point"}
}