{
  "type": "Feature",
  "properties": {
    "gn:admin1_code":"37",
    "gn:asciiname":"Pritykino",
    "gn:country_code":"RU",
    "gn:dem":112,
    "gn:feature_class":"P",
    "gn:feature_code":"PPL",
    "gn:name":"Pritykino",
    "gn:population":0,
    "gn:timezone":"Europe/Moscow",
    "iso:country":"RU",
    "name:rus_x_preferred":[
        "\u041f\u0440\u0438\u0442\u044b\u043a\u0438\u043d\u043e"
    ],
    "name:und_x_variant":[
        "\u041f\u0440\u0438\u0442\u044b\u043a\u0438\u043d\u043e"
    ],
    "wof:name":"Pritykino",
    "wof:placetype":"locality"
},
  "geometry": {"coordinates":[45.4265,58.5107],"type":"Point"}
}