{
  "type": "Feature",
  "properties": {
    "gn:admin1_code":"8",
    "gn:asciiname":"Tarkhan",
    "gn:country_code":"RU",
    "gn:dem":167,
    "gn:feature_class":"P",
    "gn:feature_code":"PPL",
    "gn:name":"Tarkhan",
    "gn:population":0,
    "gn:timezone":"Asia/Yekaterinburg",
    "iso:country":"RU",
    "name:rus_x_preferred":[
        "\u0422\u0430\u0440\u0445\u0430\u043d"
    ],
    "name:und_x_variant":[
        "\u0422\u0430\u0440\u0445\u0430\u043d"
    ],
    "wof:name":"Tarkhan",
    "wof:placetype":"locality"
},
  "geometry": {"coordinates":[54.05,54.76667],"type":"Point"}
}