{
  "type": "Feature",
  "properties": {
    "gn:admin1_code":"8",
    "gn:asciiname":"Tarkhan",
    "gn:country_code":"RU",
    "gn:dem":167,
    "gn:feature_class":"P",
    "gn:feature_code":"PPL",
    "gn:name":"Tarkhan",
    "gn:population":0,
    "gn:timezone":"Asia/Yekaterinburg",
    "iso:country":"RU",
    "name:aze_x_preferred":[
        "Tarxan"
    ],
    "name:bak_x_preferred":[
        "\u0422\u0430\u0440\u0445\u0430\u043d"
    ],
    "name:bul_x_preferred":[
        "\u0422\u0430\u0440\u043a\u0430\u043d"
    ],
    "name:deu_x_preferred":[
        "Tarkhan"
    ],
    "name:fas_x_preferred":[
        "\u062a\u0631\u062e\u0627\u0646"
    ],
    "name:fra_x_preferred":[
        "Darkhan"
    ],
    "name:heb_x_preferred":[
        "\u05d8\u05d0\u05e8\u05e7\u05d0\u05e0\u05d9\u05dd"
    ],
    "name:hun_x_preferred":[
        "Tarkan"
    ],
    "name:jpn_x_preferred":[
        "\u30bf\u30eb\u30ab\u30f3"
    ],
    "name:kat_x_preferred":[
        "\u10d7\u10d0\u10e0\u10ee\u10d0\u10dc\u10d8"
    ],
    "name:kaz_x_preferred":[
        "\u0422\u0430\u0440\u0445\u0430\u043d"
    ],
    "name:kir_x_preferred":[
        "\u0422\u0430\u0440\u0445\u0430\u043d"
    ],
    "name:lav_x_preferred":[
        "Tarhans"
    ],
    "name:ron_x_preferred":[
        "Tarcani"
    ],
    "name:rus_x_preferred":[
        "\u0422\u0430\u0440\u0445\u0430\u043d"
    ],
    "name:snd_x_preferred":[
        "\u062a\u0631\u062e\u0627\u0646"
    ],
    "name:spa_x_preferred":[
        "Tarjan"
    ],
    "name:tam_x_preferred":[
        "\u0ba4\u0bb0\u0bcd\u0b95\u0ba9\u0bcd"
    ],
    "name:tat_x_preferred":[
        "\u0422\u0430\u0440\u0445\u0430\u043d"
    ],
    "name:ukr_x_preferred":[
        "\u0422\u0430\u0440\u0445\u0430\u043d"
    ],
    "name:urd_x_preferred":[
        "\u062a\u0631\u062e\u0627\u0646"
    ],
    "name:zho_x_preferred":[
        "\u7b54\u524c\u7f55"
    ],
    "wof:name":"Tarkhan",
    "wof:placetype":"locality"
},
  "geometry": {"coordinates":[54.05,54.76667],"type":"Point"}
}