{
  "type": "Feature",
  "properties": {
    "gn:admin1_code":"77",
    "gn:asciiname":"Vasnevo",
    "gn:country_code":"RU",
    "gn:dem":205,
    "gn:feature_class":"P",
    "gn:feature_code":"PPL",
    "gn:name":"Vasnevo",
    "gn:population":0,
    "gn:timezone":"Europe/Moscow",
    "iso:country":"RU",
    "name:rus_x_preferred":[
        "\u0412\u0430\u0441\u043d\u0435\u0432\u043e"
    ],
    "wof:name":"Vasnevo",
    "wof:placetype":"locality"
},
  "geometry": {"coordinates":[32.96717,55.80999],"type":"Point"}
}