{
  "type": "Feature",
  "properties": {
    "gn:admin1_code":"55.0",
    "gn:asciiname":"Burkinka",
    "gn:country_code":"RU",
    "gn:dem":268,
    "gn:feature_class":"P",
    "gn:feature_code":"PPL",
    "gn:name":"Burkinka",
    "gn:population":0,
    "gn:timezone":"Asia/Yekaterinburg",
    "iso:country":"RU",
    "name:rus_x_preferred":[
        "\u0411\u0443\u0440\u043a\u0438\u043d\u043a\u0430"
    ],
    "wof:name":"Burkinka",
    "wof:placetype":"locality"
},
  "geometry": {"coordinates":[56.06667,52.23333],"type":"Point"}
}