{
  "type": "Feature",
  "properties": {
    "gn:admin1_code":"24.0",
    "gn:asciiname":"Sharva",
    "gn:country_code":"RU",
    "gn:dem":-5,
    "gn:feature_class":"P",
    "gn:feature_code":"PPL",
    "gn:name":"Sharva",
    "gn:population":0,
    "gn:timezone":"Europe/Moscow",
    "iso:country":"RU",
    "name:rus_x_preferred":[
        "\u0428\u0430\u0440\u0432\u0430"
    ],
    "wof:name":"Sharva",
    "wof:placetype":"locality"
},
  "geometry": {"coordinates":[45.0696,46.7357],"type":"Point"}
}