{
  "type": "Feature",
  "properties": {
    "gn:admin1_code":"7",
    "gn:asciiname":"Chistyy Yar",
    "gn:country_code":"RU",
    "gn:dem":-24,
    "gn:feature_class":"P",
    "gn:feature_code":"PPL",
    "gn:name":"Chistyy Yar",
    "gn:population":0,
    "gn:timezone":"Europe/Astrakhan",
    "iso:country":"RU",
    "name:rus_x_preferred":[
        "\u0427\u0438\u0441\u0442\u044b\u0439 \u042f\u0440"
    ],
    "wof:name":"Chistyy Yar",
    "wof:placetype":"locality"
},
  "geometry": {"coordinates":[48.2807,46.59073],"type":"Point"}
}