{
  "type": "Feature",
  "properties": {
    "gn:admin1_code":"11",
    "gn:asciiname":"Malyy Amalat",
    "gn:cc2":"RU",
    "gn:country_code":"RU",
    "gn:dem":909,
    "gn:feature_class":"P",
    "gn:feature_code":"PPL",
    "gn:name":"Malyy Amalat",
    "gn:population":0,
    "gn:timezone":"Asia/Irkutsk",
    "iso:country":"RU",
    "name:eng_x_preferred":[
        "Malyy Amalat"
    ],
    "name:nor_x_preferred":[
        "Mal.Amalat"
    ],
    "name:rus_x_preferred":[
        "\u041c\u0430\u043b.\u0410\u043c\u0430\u043b\u0430\u0442"
    ],
    "name:rus_x_variant":[
        "\u041c\u0430\u043b\u044b\u0439 \u0410\u043c\u0430\u043b\u0430\u0442"
    ],
    "name:und_x_variant":[
        "Maloye Amalatskoye",
        "Malyy Amalat",
        "\u041c\u0430\u043b\u044b\u0439 \u0410\u043c\u0430\u043b\u0430\u0442"
    ],
    "wof:name":"Malyy Amalat",
    "wof:placetype":"locality"
},
  "geometry": {"coordinates":[113.40000000000001,54.31667],"type":"Point"}
}