{
  "type": "Feature",
  "properties": {
    "gn:admin1_code":"65.0",
    "gn:asciiname":"Dolgoozerskiy",
    "gn:cc2":"RU",
    "gn:country_code":"RU",
    "gn:dem":52,
    "gn:feature_class":"P",
    "gn:feature_code":"PPL",
    "gn:name":"Dolgooz\u00ebrskiy",
    "gn:population":0,
    "gn:timezone":"Europe/Samara",
    "iso:country":"RU",
    "name:rus_x_preferred":[
        "\u0414\u043e\u043b\u0433\u043e\u043e\u0437\u0451\u0440\u0441\u043a\u0438\u0439"
    ],
    "name:und_x_variant":[
        "Dolgoye Ozero",
        "Dolgooz\u00ebrskiy",
        "\u0414\u043e\u043b\u0433\u043e\u043e\u0437\u0451\u0440\u0441\u043a\u0438\u0439"
    ],
    "wof:name":"Dolgoozerskiy",
    "wof:placetype":"locality"
},
  "geometry": {"coordinates":[51.23333,52.88333000000001],"type":"Point"}
}