{
  "type": "Feature",
  "properties": {
    "gn:admin1_code":"57",
    "gn:asciiname":"Kera",
    "gn:country_code":"RU",
    "gn:dem":207,
    "gn:feature_class":"P",
    "gn:feature_code":"PPL",
    "gn:name":"Kera",
    "gn:population":0,
    "gn:timezone":"Europe/Moscow",
    "iso:country":"RU",
    "name:ceb_x_preferred":[
        "Kera"
    ],
    "name:ita_x_preferred":[
        "Kera"
    ],
    "name:lav_x_preferred":[
        "Kera"
    ],
    "name:rus_x_preferred":[
        "\u041a\u0435\u0440\u0430"
    ],
    "name:swe_x_preferred":[
        "Kera"
    ],
    "wof:name":"Kera",
    "wof:placetype":"locality"
},
  "geometry": {"coordinates":[44.3373,53.3487],"type":"Point"}
}