{
  "type": "Feature",
  "properties": {
    "gn:admin1_code":"73",
    "gn:asciiname":"Tabar-Cherki",
    "gn:country_code":"RU",
    "gn:dem":139,
    "gn:feature_class":"P",
    "gn:feature_code":"PPL",
    "gn:name":"Tabar-Cherki",
    "gn:population":0,
    "gn:timezone":"Europe/Moscow",
    "iso:country":"RU",
    "name:und_x_variant":[
        "Tadyr",
        "Tabar-Chirki",
        "Tabar-Cherki"
    ],
    "wof:name":"Tabar-Cherki",
    "wof:placetype":"locality"
},
  "geometry": {"coordinates":[48.44971,55.15826],"type":"Point"}
}