{
  "type": "Feature",
  "properties": {
    "gn:admin1_code":"8",
    "gn:asciiname":"Taymeyevo",
    "gn:country_code":"RU",
    "gn:dem":272,
    "gn:feature_class":"P",
    "gn:feature_code":"PPL",
    "gn:name":"Taymeyevo",
    "gn:population":0,
    "gn:timezone":"Asia/Yekaterinburg",
    "iso:country":"RU",
    "name:eng_x_preferred":[
        "Taymeyevo"
    ],
    "name:nor_x_preferred":[
        "Tajmejevo"
    ],
    "name:rus_x_preferred":[
        "\u0422\u0430\u0439\u043c\u0435\u0435\u0432\u043e"
    ],
    "wof:name":"Taymeyevo",
    "wof:placetype":"locality"
},
  "geometry": {"coordinates":[57.8575,55.4725],"type":"Point"}
}