{
  "type": "Feature",
  "properties": {
    "gn:admin1_code":"37.0",
    "gn:asciiname":"Belikovo",
    "gn:country_code":"RU",
    "gn:dem":148,
    "gn:feature_class":"P",
    "gn:feature_code":"PPL",
    "gn:name":"Belikovo",
    "gn:population":0,
    "gn:timezone":"Europe/Moscow",
    "iso:country":"RU",
    "name:nor_x_preferred":[
        "Belikovo"
    ],
    "name:rus_x_preferred":[
        "\u0411\u0435\u043b\u0438\u043a\u043e\u0432\u043e"
    ],
    "wof:name":"Belikovo",
    "wof:placetype":"locality"
},
  "geometry": {"coordinates":[43.23635,58.44924],"type":"Point"}
}