{
  "type": "Feature",
  "properties": {
    "gn:admin1_code":"23",
    "gn:asciiname":"Barkasovo",
    "gn:country_code":"RU",
    "gn:dem":48,
    "gn:feature_class":"P",
    "gn:feature_code":"PPL",
    "gn:name":"Barkasovo",
    "gn:population":0,
    "gn:timezone":"Europe/Kaliningrad",
    "iso:country":"RU",
    "name:nor_x_preferred":[
        "Barkasovo"
    ],
    "name:rus_x_preferred":[
        "\u0411\u0430\u0440\u043a\u0430\u0441\u043e\u0432\u043e"
    ],
    "name:und_x_variant":[
        "Neu Katzheim",
        "Staroye Barkasovo"
    ],
    "wof:name":"Barkasovo",
    "wof:placetype":"locality"
},
  "geometry": {"coordinates":[20.02926,54.91775],"type":"Point"}
}