{
  "type": "Feature",
  "properties": {
    "gn:admin1_code":"76.0",
    "gn:asciiname":"Shul'gino",
    "gn:country_code":"RU",
    "gn:dem":240,
    "gn:feature_class":"P",
    "gn:feature_code":"PPL",
    "gn:name":"Shul\u2019gino",
    "gn:population":0,
    "gn:timezone":"Europe/Moscow",
    "iso:country":"RU",
    "name:eng_x_preferred":[
        "Shul'gino"
    ],
    "name:rus_x_preferred":[
        "\u0428\u0443\u043b\u044c\u0433\u0438\u043d\u043e"
    ],
    "wof:name":"Shul'gino",
    "wof:placetype":"locality"
},
  "geometry": {"coordinates":[37.59243,54.57437],"type":"Point"}
}