{
  "type": "Feature",
  "properties": {
    "gn:admin1_code":"56",
    "gn:asciiname":"Magovka",
    "gn:country_code":"RU",
    "gn:dem":213,
    "gn:feature_class":"P",
    "gn:feature_code":"PPL",
    "gn:name":"Magovka",
    "gn:population":0,
    "gn:timezone":"Europe/Moscow",
    "iso:country":"RU",
    "name:rus_x_preferred":[
        "\u041c\u0430\u0433\u043e\u0432\u043a\u0430"
    ],
    "wof:name":"Magovka",
    "wof:placetype":"locality"
},
  "geometry": {"coordinates":[35.29002,52.90655],"type":"Point"}
}