{
  "type": "Feature",
  "properties": {
    "gn:admin1_code":"6.0",
    "gn:asciiname":"Voyepala",
    "gn:country_code":"RU",
    "gn:dem":16,
    "gn:feature_class":"P",
    "gn:feature_code":"PPL",
    "gn:name":"Voyepala",
    "gn:population":0,
    "gn:timezone":"Europe/Moscow",
    "iso:country":"RU",
    "name:rus_x_preferred":[
        "\u0412\u043e\u0435\u043f\u0430\u043b\u0430"
    ],
    "wof:name":"Voyepala",
    "wof:placetype":"locality"
},
  "geometry": {"coordinates":[43.409,64.7206],"type":"Point"}
}