{
  "type": "Feature",
  "properties": {
    "gn:admin1_code":"63",
    "gn:asciiname":"Promyshlennyy",
    "gn:country_code":"RU",
    "gn:dem":82,
    "gn:feature_class":"P",
    "gn:feature_code":"PPL",
    "gn:name":"Promyshlennyy",
    "gn:population":0,
    "gn:timezone":"Asia/Yakutsk",
    "iso:country":"RU",
    "name:eng_x_preferred":[
        "Promyshlennyy"
    ],
    "name:nor_x_preferred":[
        "Promysjlennyj"
    ],
    "name:rus_x_preferred":[
        "\u041f\u0440\u043e\u043c\u044b\u0448\u043b\u0435\u043d\u043d\u044b\u0439"
    ],
    "name:und_x_variant":[
        "Sobo-Khaya"
    ],
    "wof:name":"Promyshlennyy",
    "wof:placetype":"locality"
},
  "geometry": {"coordinates":[126.40501999999999,64.20018],"type":"Point"}
}