{
  "type": "Feature",
  "properties": {
    "gn:admin1_code":"28",
    "gn:asciiname":"Kaksinaynen",
    "gn:cc2":"RU",
    "gn:country_code":"RU",
    "gn:dem":158,
    "gn:feature_class":"P",
    "gn:feature_code":"PPL",
    "gn:name":"Kaksinaynen",
    "gn:population":0,
    "gn:timezone":"Europe/Moscow",
    "iso:country":"RU",
    "name:fin_x_preferred":[
        "Kaksinainen"
    ],
    "name:rus_x_preferred":[
        "\u041a\u0430\u043a\u0441\u0438\u043d\u0430\u0439\u043d\u0435\u043d"
    ],
    "name:und_x_variant":[
        "\u041a\u0430\u043a\u0441\u0438\u043d\u0430\u0439\u043d\u0435\u043d"
    ],
    "wof:name":"Kaksinaynen",
    "wof:placetype":"locality"
},
  "geometry": {"coordinates":[32.53333,62.18333000000001],"type":"Point"}
}