{
  "type": "Feature",
  "properties": {
    "gn:admin1_code":"90",
    "gn:asciiname":"Makhneva",
    "gn:country_code":"RU",
    "gn:dem":223,
    "gn:feature_class":"P",
    "gn:feature_code":"PPL",
    "gn:name":"Makhn\u00ebva",
    "gn:population":0,
    "gn:timezone":"Asia/Yekaterinburg",
    "iso:country":"RU",
    "name:eng_x_preferred":[
        "Makhn\u00ebva"
    ],
    "name:nor_x_preferred":[
        "Makhneva"
    ],
    "name:rus_x_preferred":[
        "\u041c\u0430\u0445\u043d\u0435\u0432\u0430"
    ],
    "name:rus_x_variant":[
        "\u041c\u0430\u0445\u043d\u0451\u0432\u0430"
    ],
    "name:und_x_variant":[
        "Makhn\u00ebvo",
        "Makhn\u00ebva",
        "\u041c\u0430\u0445\u043d\u0451\u0432\u0430"
    ],
    "wof:name":"Makhneva",
    "wof:placetype":"locality"
},
  "geometry": {"coordinates":[57.6753,59.4556],"type":"Point"}
}