{
  "type": "Feature",
  "properties": {
    "gn:admin1_code":"77",
    "gn:asciiname":"Osheyevo",
    "gn:country_code":"RU",
    "gn:dem":158,
    "gn:feature_class":"P",
    "gn:feature_code":"PPL",
    "gn:name":"Osheyevo",
    "gn:population":0,
    "gn:timezone":"Europe/Moscow",
    "iso:country":"RU",
    "name:rus_x_preferred":[
        "\u041e\u0448\u0435\u0435\u0432\u043e"
    ],
    "wof:name":"Osheyevo",
    "wof:placetype":"locality"
},
  "geometry": {"coordinates":[35.47976,58.2928],"type":"Point"}
}