{
  "type": "Feature",
  "properties": {
    "gn:country":"RU",
    "gn:fcode":"PPL",
    "gn:pop":3843,
    "iso:country":"RU",
    "name:deu_x_preferred":[
        "Witim"
    ],
    "name:eng_x_preferred":[
        "Vitim"
    ],
    "name:fin_x_preferred":[
        "Vitim"
    ],
    "name:hye_x_preferred":[
        "\u054e\u056b\u057f\u056b\u0574"
    ],
    "name:ita_x_preferred":[
        "Vitim"
    ],
    "name:lit_x_preferred":[
        "Vitimas"
    ],
    "name:nld_x_preferred":[
        "Vitim"
    ],
    "name:nor_x_preferred":[
        "Vitim"
    ],
    "name:rus_x_preferred":[
        "\u0412\u0438\u0442\u0438\u043c"
    ],
    "name:sah_x_preferred":[
        "\u0412\u0438\u0442\u0438\u043c"
    ],
    "ne:ADM0CAP":0.0,
    "ne:ADM0NAME":"Russia",
    "ne:ADM0_A3":"RUS",
    "ne:ADM1NAME":"Sakha (Yakutia)",
    "ne:ADMIN1_COD":63,
    "ne:CAPALT":0,
    "ne:CHANGED":1,
    "ne:CHECKME":0,
    "ne:COMPARE":1,
    "ne:DIFFASCII":0,
    "ne:DIFFNOTE":"Added place. Population from GeoNames.",
    "ne:ELEVATION":0.0,
    "ne:FEATURECLA":"Populated place",
    "ne:FEATURE_CL":"P",
    "ne:FEATURE_CO":"PPL",
    "ne:GEONAMEID":2013375,
    "ne:GEONAMESNO":"Geonames ascii name + lat.d + long.d matching.",
    "ne:GN_ASCII":"Vitim",
    "ne:GN_POP":3843,
    "ne:GTOPO30":197.0,
    "ne:ISO_A2":"RU",
    "ne:LABELRANK":2,
    "ne:LATITUDE":59.451499,
    "ne:LONGITUDE":112.557822,
    "ne:LS_MATCH":2,
    "ne:MAX_AREAKM":0.0,
    "ne:MAX_AREAMI":0.0,
    "ne:MAX_BBXMAX":0.0,
    "ne:MAX_BBXMIN":0.0,
    "ne:MAX_BBYMAX":0.0,
    "ne:MAX_BBYMIN":0.0,
    "ne:MAX_NATSCA":0.0,
    "ne:MAX_PERKM":0.0,
    "ne:MAX_PERMI":0.0,
    "ne:MAX_POP10":0,
    "ne:MAX_POP20":0,
    "ne:MAX_POP300":0,
    "ne:MAX_POP310":0,
    "ne:MAX_POP50":0,
    "ne:MEAN_BBXC":0.0,
    "ne:MEAN_BBYC":0.0,
    "ne:MEGACITY":0,
    "ne:MIN_AREAKM":0.0,
    "ne:MIN_AREAMI":0.0,
    "ne:MIN_BBXMAX":0.0,
    "ne:MIN_BBXMIN":0.0,
    "ne:MIN_BBYMAX":0.0,
    "ne:MIN_BBYMIN":0.0,
    "ne:MIN_PERKM":0.0,
    "ne:MIN_PERMI":0.0,
    "ne:NAME":"Vitim",
    "ne:NAMEASCII":"Vitim",
    "ne:NAMEDIFF":1,
    "ne:NATSCALE":20,
    "ne:POP1950":0,
    "ne:POP1955":0,
    "ne:POP1960":0,
    "ne:POP1965":0,
    "ne:POP1970":0,
    "ne:POP1975":0,
    "ne:POP1980":0,
    "ne:POP1985":0,
    "ne:POP1990":0,
    "ne:POP1995":0,
    "ne:POP2000":0,
    "ne:POP2005":0,
    "ne:POP2010":0,
    "ne:POP2015":0,
    "ne:POP2020":0,
    "ne:POP2025":0,
    "ne:POP2050":0,
    "ne:POP_MAX":3843,
    "ne:POP_MIN":3843,
    "ne:POP_OTHER":0,
    "ne:RANK_MAX":4,
    "ne:RANK_MIN":4,
    "ne:SCALERANK":7,
    "ne:SOV0NAME":"Russia",
    "ne:SOV_A3":"RUS",
    "ne:TIMEZONE":"Asia/Yakutsk",
    "ne:UN_FID":0,
    "ne:UN_LAT":0.0,
    "ne:UN_LONG":0.0,
    "ne:WORLDCITY":0,
    "qs:name":"Vitim",
    "qs:photos_9r":0,
    "qs:photos_sr":0,
    "qs:pop_sr":"4",
    "wd:wordcount":110,
    "wof:name":"Vitim",
    "wof:placetype":"locality",
    "wof:population":3843
},
  "geometry": {"coordinates":[112.56993,59.44326],"type":"Point"}
}