{
  "type": "Feature",
  "properties": {
    "gn:admin1_code":"53.0",
    "gn:asciiname":"Lomovskaya Dacha",
    "gn:country_code":"RU",
    "gn:dem":131,
    "gn:feature_class":"P",
    "gn:feature_code":"PPL",
    "gn:name":"Lomovskaya Dacha",
    "gn:population":0,
    "gn:timezone":"Asia/Novosibirsk",
    "iso:country":"RU",
    "name:rus_x_preferred":[
        "\u041b\u043e\u043c\u043e\u0432\u0441\u043a\u0430\u044f \u0414\u0430\u0447\u0430"
    ],
    "wof:name":"Lomovskaya Dacha",
    "wof:placetype":"locality"
},
  "geometry": {"coordinates":[82.9504,55.2121],"type":"Point"}
}