{
  "type": "Feature",
  "properties": {
    "gn:admin1_code":"28",
    "gn:asciiname":"Kerkkaelae",
    "gn:cc2":"RU",
    "gn:country_code":"RU",
    "gn:dem":130,
    "gn:feature_class":"P",
    "gn:feature_code":"PPL",
    "gn:name":"Kerkk\u00e4l\u00e4",
    "gn:population":0,
    "gn:timezone":"Europe/Moscow",
    "iso:country":"RU",
    "name:rus_x_preferred":[
        "\u041a\u0435\u0440\u043a\u043a\u044f\u043b\u044f"
    ],
    "name:und_x_variant":[
        "Kerkk\u00e4l\u00e4",
        "Kerkkyalya"
    ],
    "wof:name":"Kerkkaelae",
    "wof:placetype":"locality"
},
  "geometry": {"coordinates":[29.80007,66.26243000000001],"type":"Point"}
}