{
  "type": "Feature",
  "properties": {
    "gn:admin1_code":"90.0",
    "gn:asciiname":"Akchim",
    "gn:country_code":"RU",
    "gn:dem":152,
    "gn:feature_class":"P",
    "gn:feature_code":"PPL",
    "gn:name":"Akchim",
    "gn:population":0,
    "gn:timezone":"Asia/Yekaterinburg",
    "iso:country":"RU",
    "name:che_x_preferred":[
        "\u0410\u043a\u0447\u0438\u043c"
    ],
    "name:eng_x_preferred":[
        "Akchim"
    ],
    "name:nor_x_preferred":[
        "Aktsjim"
    ],
    "name:rus_x_preferred":[
        "\u0410\u043a\u0447\u0438\u043c"
    ],
    "wof:name":"Akchim",
    "wof:placetype":"locality"
},
  "geometry": {"coordinates":[58.04778,60.47566],"type":"Point"}
}