{
  "type": "Feature",
  "properties": {
    "gn:admin1_code":"90.0",
    "gn:asciiname":"Bikbarda",
    "gn:country_code":"RU",
    "gn:dem":131,
    "gn:feature_class":"P",
    "gn:feature_code":"PPL",
    "gn:name":"Bikbarda",
    "gn:population":0,
    "gn:timezone":"Asia/Yekaterinburg",
    "iso:country":"RU",
    "name:rus_x_preferred":[
        "\u0411\u0438\u043a\u0431\u0430\u0440\u0434\u0430"
    ],
    "wof:name":"Bikbarda",
    "wof:placetype":"locality"
},
  "geometry": {"coordinates":[55.7244,56.477],"type":"Point"}
}