{
  "type": "Feature",
  "properties": {
    "gn:admin1_code":"4",
    "gn:asciiname":"Topol'noye",
    "gn:country_code":"RU",
    "gn:dem":251,
    "gn:feature_class":"P",
    "gn:feature_code":"PPL",
    "gn:name":"Topol\u2019noye",
    "gn:population":0,
    "gn:timezone":"Asia/Barnaul",
    "iso:country":"RU",
    "name:eng_x_preferred":[
        "Topol'noye"
    ],
    "name:nor_x_preferred":[
        "Topolnoje"
    ],
    "name:rus_x_preferred":[
        "\u0422\u043e\u043f\u043e\u043b\u044c\u043d\u043e\u0435"
    ],
    "name:und_x_variant":[
        "Topol\u2019noye"
    ],
    "wof:name":"Topol'noye",
    "wof:placetype":"locality"
},
  "geometry": {"coordinates":[80.10424,50.93763],"type":"Point"}
}