{
  "type": "Feature",
  "properties": {
    "gn:admin1_code":"51",
    "gn:asciiname":"Novoyedelevo",
    "gn:country_code":"RU",
    "gn:dem":108,
    "gn:feature_class":"P",
    "gn:feature_code":"PPL",
    "gn:name":"Novoyedel\u00ebvo",
    "gn:population":0,
    "gn:timezone":"Europe/Moscow",
    "iso:country":"RU",
    "name:rus_x_preferred":[
        "\u041d\u043e\u0432\u043e\u0435\u0434\u0435\u043b\u0451\u0432\u043e"
    ],
    "name:und_x_variant":[
        "Novoyedel\u00ebvo",
        "\u041d\u043e\u0432\u043e\u0435\u0434\u0435\u043b\u0451\u0432\u043e"
    ],
    "wof:name":"Novoyedelevo",
    "wof:placetype":"locality"
},
  "geometry": {"coordinates":[44.83809,55.37056],"type":"Point"}
}