{
  "type": "Feature",
  "properties": {
    "gn:admin1_code":"90",
    "gn:asciiname":"Balandino",
    "gn:country_code":"RU",
    "gn:dem":123,
    "gn:feature_class":"P",
    "gn:feature_code":"PPL",
    "gn:name":"Balandino",
    "gn:population":0,
    "gn:timezone":"Asia/Yekaterinburg",
    "iso:country":"RU",
    "name:nor_x_preferred":[
        "Balandino"
    ],
    "name:rus_x_preferred":[
        "\u0411\u0430\u043b\u0430\u043d\u0434\u0438\u043d\u043e"
    ],
    "wof:name":"Balandino",
    "wof:placetype":"locality"
},
  "geometry": {"coordinates":[56.3618,57.8302],"type":"Point"}
}