{
  "type": "Feature",
  "properties": {
    "gn:admin1_code":"13",
    "gn:asciiname":"Berezovyy Most",
    "gn:country_code":"RU",
    "gn:dem":460,
    "gn:feature_class":"P",
    "gn:feature_code":"PPL",
    "gn:name":"Ber\u00ebzovyy Most",
    "gn:population":0,
    "gn:timezone":"Asia/Yekaterinburg",
    "iso:country":"RU",
    "name:nor_x_preferred":[
        "Berjozovyj Most"
    ],
    "name:rus_x_preferred":[
        "\u0411\u0435\u0440\u0451\u0437\u043e\u0432\u044b\u0439 \u041c\u043e\u0441\u0442"
    ],
    "name:und_x_variant":[
        "Ber\u00ebzovyy Most"
    ],
    "wof:name":"Berezovyy Most",
    "wof:placetype":"locality"
},
  "geometry": {"coordinates":[59.1507,55.0628],"type":"Point"}
}