{
  "type": "Feature",
  "properties": {
    "gn:admin1_code":"83",
    "gn:asciiname":"Staryye Petushki",
    "gn:country_code":"RU",
    "gn:dem":138,
    "gn:feature_class":"P",
    "gn:feature_code":"PPL",
    "gn:name":"Staryye Petushki",
    "gn:population":0,
    "gn:timezone":"Europe/Moscow",
    "iso:country":"RU",
    "name:rus_x_preferred":[
        "\u0421\u0442\u0430\u0440\u044b\u0435 \u041f\u0435\u0442\u0443\u0448\u043a\u0438"
    ],
    "name:und_x_variant":[
        "Petushki",
        "Staryye Petushki",
        "\u0421\u0442\u0430\u0440\u044b\u0435 \u041f\u0435\u0442\u0443\u0448\u043a\u0438"
    ],
    "wof:name":"Staryye Petushki",
    "wof:placetype":"locality"
},
  "geometry": {"coordinates":[39.48847,55.94264],"type":"Point"}
}