{
  "type": "Feature",
  "properties": {
    "gn:admin1_code":"75",
    "gn:asciiname":"Astrakhantsevo",
    "gn:country_code":"RU",
    "gn:dem":79,
    "gn:feature_class":"P",
    "gn:feature_code":"PPL",
    "gn:name":"Astrakhantsevo",
    "gn:population":0,
    "gn:timezone":"Asia/Tomsk",
    "iso:country":"RU",
    "name:eng_x_preferred":[
        "Astrakhantseva"
    ],
    "name:rus_x_preferred":[
        "\u0410\u0441\u0442\u0440\u0430\u0445\u0430\u043d\u0446\u0435\u0432\u043e"
    ],
    "name:rus_x_variant":[
        "\u0410\u0441\u0442\u0440\u0430\u0445\u0430\u043d\u0446\u0435\u0432o"
    ],
    "name:und_x_variant":[
        "Astrakhantsevo"
    ],
    "wof:name":"Astrakhantsevo",
    "wof:placetype":"locality"
},
  "geometry": {"coordinates":[84.12056,56.45667],"type":"Point"}
}