{
  "type": "Feature",
  "properties": {
    "gn:admin1_code":"86.0",
    "gn:asciiname":"Otradnoye",
    "gn:country_code":"RU",
    "gn:dem":123,
    "gn:feature_class":"P",
    "gn:feature_code":"PPL",
    "gn:name":"Otradnoye",
    "gn:population":0,
    "gn:timezone":"Europe/Moscow",
    "iso:country":"RU",
    "name:rus_x_preferred":[
        "\u041e\u0442\u0440\u0430\u0434\u043d\u043e\u0435"
    ],
    "name:und_x_variant":[
        "Otradnyy"
    ],
    "wof:name":"Otradnoye",
    "wof:placetype":"locality"
},
  "geometry": {"coordinates":[40.5751,50.8817],"type":"Point"}
}