{
  "type": "Feature",
  "properties": {
    "gn:admin1_code":"63",
    "gn:asciiname":"Sordongnookh",
    "gn:cc2":"RU",
    "gn:country_code":"RU",
    "gn:dem":51,
    "gn:feature_class":"P",
    "gn:feature_code":"PPL",
    "gn:name":"Sordongnookh",
    "gn:population":0,
    "gn:timezone":"Asia/Magadan",
    "iso:country":"RU",
    "name:rus_x_preferred":[
        "\u0421\u043e\u0440\u0434\u043e\u043d\u0433\u043d\u043e\u043e\u0445"
    ],
    "name:und_x_variant":[
        "Povarnya Sordonakh",
        "Sordongnookh"
    ],
    "wof:name":"Sordongnookh",
    "wof:placetype":"locality"
},
  "geometry": {"coordinates":[145.88333,70.75],"type":"Point"}
}