{
  "type": "Feature",
  "properties": {
    "gn:admin1_code":"41",
    "gn:asciiname":"Zaverkh",
    "gn:country_code":"RU",
    "gn:dem":249,
    "gn:feature_class":"P",
    "gn:feature_code":"PPL",
    "gn:name":"Zaverkh",
    "gn:population":0,
    "gn:timezone":"Europe/Moscow",
    "iso:country":"RU",
    "name:rus_x_preferred":[
        "\u0417\u0430\u0432\u0435\u0440\u0445"
    ],
    "wof:name":"Zaverkh",
    "wof:placetype":"locality"
},
  "geometry": {"coordinates":[38.3823,51.7818],"type":"Point"}
}