{
  "type": "Feature",
  "properties": {
    "gn:admin1_code":"65",
    "gn:asciiname":"Poplavskiy",
    "gn:country_code":"RU",
    "gn:dem":39,
    "gn:feature_class":"P",
    "gn:feature_code":"PPL",
    "gn:name":"Poplavskiy",
    "gn:population":0,
    "gn:timezone":"Europe/Samara",
    "iso:country":"RU",
    "name:rus_x_preferred":[
        "\u041f\u043e\u043f\u043b\u0430\u0432\u0441\u043a\u0438\u0439"
    ],
    "wof:name":"Poplavskiy",
    "wof:placetype":"locality"
},
  "geometry": {"coordinates":[50.83365,52.97938000000001],"type":"Point"}
}