{
  "type": "Feature",
  "properties": {
    "gn:admin1_code":"56",
    "gn:asciiname":"Bol'shaya Chernava",
    "gn:country_code":"RU",
    "gn:dem":209,
    "gn:feature_class":"P",
    "gn:feature_code":"PPL",
    "gn:name":"Bol\u2019shaya Chernava",
    "gn:population":0,
    "gn:timezone":"Europe/Moscow",
    "iso:country":"RU",
    "name:rus_x_preferred":[
        "\u0411\u043e\u043b\u044c\u0448\u0430\u044f \u0427\u0435\u0440\u043d\u0430\u0432\u0430"
    ],
    "name:und_x_variant":[
        "Leski",
        "Bol\u2019shaya Chernava",
        "\u0411\u043e\u043b\u044c\u0448\u0430\u044f \u0427\u0435\u0440\u043d\u0430\u0432\u0430"
    ],
    "wof:name":"Bol'shaya Chernava",
    "wof:placetype":"locality"
},
  "geometry": {"coordinates":[37.68378,52.71581],"type":"Point"}
}