{
  "type": "Feature",
  "properties": {
    "gn:admin1_code":"20",
    "gn:asciiname":"Mandagay",
    "gn:country_code":"RU",
    "gn:dem":489,
    "gn:feature_class":"P",
    "gn:feature_code":"PPL",
    "gn:name":"Mandagay",
    "gn:population":0,
    "gn:timezone":"Asia/Irkutsk",
    "iso:country":"RU",
    "name:rus_x_preferred":[
        "\u041c\u0430\u043d\u0434\u0430\u0433\u0430\u0439"
    ],
    "name:und_x_variant":[
        "\u041c\u0430\u043d\u0434\u0430\u0433\u0430\u0439"
    ],
    "wof:name":"Mandagay",
    "wof:placetype":"locality"
},
  "geometry": {"coordinates":[102.28111,52.965],"type":"Point"}
}