{
  "type": "Feature",
  "properties": {
    "gn:admin1_code":"53",
    "gn:asciiname":"Nizhniy Chulym",
    "gn:country_code":"RU",
    "gn:dem":108,
    "gn:feature_class":"P",
    "gn:feature_code":"PPL",
    "gn:name":"Nizhniy Chulym",
    "gn:population":0,
    "gn:timezone":"Asia/Novosibirsk",
    "iso:country":"RU",
    "name:eng_x_preferred":[
        "Nizhniy Chulym"
    ],
    "name:nor_x_preferred":[
        "Nizj.Tsjulym"
    ],
    "name:rus_x_preferred":[
        "\u041d\u0438\u0436.\u0427\u0443\u043b\u044b\u043c"
    ],
    "name:rus_x_variant":[
        "\u041d\u0438\u0436\u043d\u0438\u0439 \u0427\u0443\u043b\u044b\u043c"
    ],
    "name:und_x_variant":[
        "Sarapulovo",
        "Chulymskoye"
    ],
    "wof:name":"Nizhniy Chulym",
    "wof:placetype":"locality"
},
  "geometry": {"coordinates":[78.94,54.61346999999999],"type":"Point"}
}