{
  "type": "Feature",
  "properties": {
    "gn:admin1_code":"69",
    "gn:asciiname":"Achmashnyo",
    "gn:country_code":"RU",
    "gn:dem":191,
    "gn:feature_class":"P",
    "gn:feature_code":"PPL",
    "gn:name":"Achmashnyo",
    "gn:population":0,
    "gn:timezone":"Europe/Moscow",
    "iso:country":"RU",
    "name:nor_x_preferred":[
        "Atsjmasjnyo"
    ],
    "name:rus_x_preferred":[
        "\u0410\u0447\u043c\u0430\u0448\u043d\u044b\u043e"
    ],
    "wof:name":"Achmashnyo",
    "wof:placetype":"locality"
},
  "geometry": {"coordinates":[34.16833,55.65083000000001],"type":"Point"}
}