{
  "type": "Feature",
  "properties": {
    "gn:admin1_code":"60",
    "gn:asciiname":"Vanino",
    "gn:country_code":"RU",
    "gn:dem":55,
    "gn:feature_class":"P",
    "gn:feature_code":"PPL",
    "gn:name":"Vanino",
    "gn:population":0,
    "gn:timezone":"Europe/Moscow",
    "iso:country":"RU",
    "name:rus_x_preferred":[
        "\u0412\u0430\u043d\u0438\u043d\u043e"
    ],
    "wof:name":"Vanino",
    "wof:placetype":"locality"
},
  "geometry": {"coordinates":[28.16826,57.41067],"type":"Point"}
}