{
  "type": "Feature",
  "properties": {
    "gn:admin1_code":"60",
    "gn:asciiname":"Vanino",
    "gn:country_code":"RU",
    "gn:dem":55,
    "gn:feature_class":"P",
    "gn:feature_code":"PPL",
    "gn:name":"Vanino",
    "gn:population":0,
    "gn:timezone":"Europe/Moscow",
    "iso:country":"RU",
    "name:ben_x_preferred":[
        "\u09ad\u09cd\u09af\u09be\u09a8\u09bf\u09a8\u09cb"
    ],
    "name:ell_x_preferred":[
        "\u0392\u03b1\u03bd\u03af\u03bd\u03bf"
    ],
    "name:fas_x_preferred":[
        "\u0648\u0627\u0646\u06cc\u0646\u0648"
    ],
    "name:hin_x_preferred":[
        "\u0935\u0948\u0928\u093f\u0928\u094b"
    ],
    "name:ind_x_preferred":[
        "Vanino"
    ],
    "name:ita_x_preferred":[
        "Vanino"
    ],
    "name:por_x_preferred":[
        "Vanino"
    ],
    "name:rus_x_preferred":[
        "\u0412\u0430\u043d\u0438\u043d\u043e"
    ],
    "name:spa_x_preferred":[
        "Vanino"
    ],
    "name:swe_x_preferred":[
        "Vanino"
    ],
    "name:tur_x_preferred":[
        "Vanino"
    ],
    "name:urd_x_preferred":[
        "\u0648\u0646\u06cc\u0646\u0648"
    ],
    "name:vie_x_preferred":[
        "Vanino"
    ],
    "wof:name":"Vanino",
    "wof:placetype":"locality"
},
  "geometry": {"coordinates":[28.16826,57.41067],"type":"Point"}
}