{
  "type": "Feature",
  "properties": {
    "gn:admin1_code":"86.0",
    "gn:asciiname":"Begichevo",
    "gn:country_code":"RU",
    "gn:dem":147,
    "gn:feature_class":"P",
    "gn:feature_code":"PPL",
    "gn:name":"Begichevo",
    "gn:population":0,
    "gn:timezone":"Europe/Moscow",
    "iso:country":"RU",
    "name:rus_x_preferred":[
        "\u0411\u0435\u0433\u0438\u0447\u0435\u0432\u043e"
    ],
    "name:und_x_variant":[
        "Bigich\u00ebvo"
    ],
    "wof:name":"Begichevo",
    "wof:placetype":"locality"
},
  "geometry": {"coordinates":[40.94444,51.71389],"type":"Point"}
}