{
  "type": "Feature",
  "properties": {
    "gn:admin1_code":"77",
    "gn:asciiname":"Simonov Gorodok",
    "gn:country_code":"RU",
    "gn:dem":133,
    "gn:feature_class":"P",
    "gn:feature_code":"PPL",
    "gn:name":"Simonov Gorodok",
    "gn:population":0,
    "gn:timezone":"Europe/Moscow",
    "iso:country":"RU",
    "name:rus_x_preferred":[
        "\u0421\u0438\u043c\u043e\u043d\u043e\u0432 \u0413\u043e\u0440\u043e\u0434\u043e\u043a"
    ],
    "wof:name":"Simonov Gorodok",
    "wof:placetype":"locality"
},
  "geometry": {"coordinates":[36.3978,58.0052],"type":"Point"}
}