{
  "type": "Feature",
  "properties": {
    "gn:admin1_code":"69",
    "gn:asciiname":"Golubovichi",
    "gn:country_code":"RU",
    "gn:dem":218,
    "gn:feature_class":"P",
    "gn:feature_code":"PPL",
    "gn:name":"Golubovichi",
    "gn:population":0,
    "gn:timezone":"Europe/Moscow",
    "iso:country":"RU",
    "name:rus_x_preferred":[
        "\u0413\u043e\u043b\u0443\u0431\u043e\u0432\u0438\u0447\u0438"
    ],
    "name:und_x_variant":[
        "\u0413\u043e\u043b\u0443\u0431\u043e\u0432\u0438\u0447\u0438"
    ],
    "wof:name":"Golubovichi",
    "wof:placetype":"locality"
},
  "geometry": {"coordinates":[31.68333,54.46666999999999],"type":"Point"}
}