{
  "type": "Feature",
  "properties": {
    "gn:admin1_code":"10",
    "gn:asciiname":"Petryatinka",
    "gn:country_code":"RU",
    "gn:dem":145,
    "gn:feature_class":"P",
    "gn:feature_code":"PPL",
    "gn:name":"Petryatinka",
    "gn:population":301,
    "gn:timezone":"Europe/Moscow",
    "iso:country":"RU",
    "name:rus_x_preferred":[
        "\u041f\u0435\u0442\u0440\u044f\u0442\u0438\u043d\u043a\u0430"
    ],
    "name:und_x_variant":[
        "Osinovka",
        "Petryapinni",
        "Petryatinka",
        "Petryatinki"
    ],
    "wof:name":"Petryatinka",
    "wof:placetype":"locality",
    "wof:population":301
},
  "geometry": {"coordinates":[31.8584,52.2495],"type":"Point"}
}