{
  "type": "Feature",
  "properties": {
    "gn:admin1_code":"60",
    "gn:asciiname":"Koklino",
    "gn:country_code":"RU",
    "gn:dem":162,
    "gn:feature_class":"P",
    "gn:feature_code":"PPL",
    "gn:name":"Koklino",
    "gn:population":0,
    "gn:timezone":"Europe/Moscow",
    "iso:country":"RU",
    "name:rus_x_preferred":[
        "\u041a\u043e\u043a\u043b\u0438\u043d\u043e"
    ],
    "name:und_x_variant":[
        "\u041a\u043e\u043a\u043b\u0438\u043d\u043e"
    ],
    "wof:name":"Koklino",
    "wof:placetype":"locality"
},
  "geometry": {"coordinates":[29.2651,56.3113],"type":"Point"}
}