{
  "type": "Feature",
  "properties": {
    "gn:admin1_code":"76",
    "gn:asciiname":"Stolbovo",
    "gn:country_code":"RU",
    "gn:dem":222,
    "gn:feature_class":"P",
    "gn:feature_code":"PPL",
    "gn:name":"Stolbovo",
    "gn:population":0,
    "gn:timezone":"Europe/Moscow",
    "iso:country":"RU",
    "name:rus_x_preferred":[
        "\u0421\u0442\u043e\u043b\u0431\u043e\u0432\u043e"
    ],
    "name:rus_x_variant":[
        "\u0421\u0442\u043e\u043b\u0431\u043e\u0432\u0430"
    ],
    "name:und_x_variant":[
        "Stolbova",
        "Stolbovo"
    ],
    "wof:name":"Stolbovo",
    "wof:placetype":"locality"
},
  "geometry": {"coordinates":[36.85154,54.27608000000001],"type":"Point"}
}