{
  "type": "Feature",
  "properties": {
    "gn:admin1_code":"37",
    "gn:asciiname":"Khrulevo",
    "gn:country_code":"RU",
    "gn:dem":194,
    "gn:feature_class":"P",
    "gn:feature_code":"PPL",
    "gn:name":"Khrul\u00ebvo",
    "gn:population":0,
    "gn:timezone":"Europe/Moscow",
    "iso:country":"RU",
    "name:rus_x_preferred":[
        "\u0425\u0440\u0443\u043b\u0451\u0432\u043e"
    ],
    "name:und_x_variant":[
        "Khrul\u00ebvo",
        "\u0425\u0440\u0443\u043b\u0451\u0432\u043e"
    ],
    "wof:name":"Khrulevo",
    "wof:placetype":"locality"
},
  "geometry": {"coordinates":[42.8164,58.304],"type":"Point"}
}