{
  "type": "Feature",
  "properties": {
    "gn:admin1_code":"90.0",
    "gn:asciiname":"Kaz'myashka",
    "gn:country_code":"RU",
    "gn:dem":160,
    "gn:feature_class":"P",
    "gn:feature_code":"PPL",
    "gn:name":"Kaz\u2019myashka",
    "gn:population":0,
    "gn:timezone":"Asia/Yekaterinburg",
    "iso:country":"RU",
    "name:rus_x_preferred":[
        "\u041a\u0430\u0437\u044c\u043c\u044f\u0448\u043a\u0430"
    ],
    "name:und_x_variant":[
        "Kaz\u2019myashka"
    ],
    "wof:name":"Kaz'myashka",
    "wof:placetype":"locality"
},
  "geometry": {"coordinates":[56.72378000000001,56.825],"type":"Point"}
}