{
  "type": "Feature",
  "properties": {
    "gn:admin1_code":"83.0",
    "gn:asciiname":"Babarino",
    "gn:country_code":"RU",
    "gn:dem":105,
    "gn:feature_class":"P",
    "gn:feature_code":"PPL",
    "gn:name":"Babarino",
    "gn:population":0,
    "gn:timezone":"Europe/Moscow",
    "iso:country":"RU",
    "name:nor_x_preferred":[
        "Babarino"
    ],
    "name:rus_x_preferred":[
        "\u0411\u0430\u0431\u0430\u0440\u0438\u043d\u043e"
    ],
    "wof:name":"Babarino",
    "wof:placetype":"locality"
},
  "geometry": {"coordinates":[40.5715,56.3841],"type":"Point"}
}