{
  "type": "Feature",
  "properties": {
    "gn:admin1_code":"23",
    "gn:asciiname":"Lozovoye",
    "gn:country_code":"RU",
    "gn:dem":23,
    "gn:feature_class":"P",
    "gn:feature_code":"PPL",
    "gn:name":"Lozovoye",
    "gn:population":0,
    "gn:timezone":"Europe/Kaliningrad",
    "iso:country":"RU",
    "name:deu_x_historical":[
        "Kremitten",
        "K\u00f6niglich Kremitten"
    ],
    "name:deu_x_preferred":[
        "Kremitten"
    ],
    "name:deu_x_variant":[
        "K\u00f6niglich Kremitten"
    ],
    "name:rus_x_preferred":[
        "\u041b\u043e\u0437\u043e\u0432\u043e\u0435"
    ],
    "name:und_x_variant":[
        "Podollen",
        "Lozovoye"
    ],
    "wof:name":"Lozovoye",
    "wof:placetype":"locality"
},
  "geometry": {"coordinates":[20.94526,54.65426],"type":"Point"}
}