{
  "type": "Feature",
  "properties": {
    "gn:admin1_code":"63",
    "gn:asciiname":"Eyakit-Terde",
    "gn:cc2":"RU",
    "gn:country_code":"RU",
    "gn:dem":238,
    "gn:feature_class":"P",
    "gn:feature_code":"PPL",
    "gn:name":"Eyakit-T\u00ebrd\u00eb",
    "gn:population":0,
    "gn:timezone":"Asia/Yakutsk",
    "iso:country":"RU",
    "name:rus_x_preferred":[
        "\u042d\u044f\u043a\u0438\u0442-\u0422\u0451\u0440\u0434\u0451"
    ],
    "name:und_x_variant":[
        "Eykit-Terde",
        "Eyakit-T\u00ebrd\u00eb",
        "\u042d\u044f\u043a\u0438\u0442-\u0422\u0451\u0440\u0434\u0451"
    ],
    "wof:name":"Eyakit-Terde",
    "wof:placetype":"locality"
},
  "geometry": {"coordinates":[114.09999999999999,66.38333],"type":"Point"}
}