{
  "type": "Feature",
  "properties": {
    "gn:admin1_code":"8",
    "gn:asciiname":"Novobalakovo",
    "gn:country_code":"RU",
    "gn:dem":258,
    "gn:feature_class":"P",
    "gn:feature_code":"PPL",
    "gn:name":"Novobalakovo",
    "gn:population":0,
    "gn:timezone":"Asia/Yekaterinburg",
    "iso:country":"RU",
    "name:rus_x_preferred":[
        "\u041d\u043e\u0432\u043e\u0431\u0430\u043b\u0430\u043a\u043e\u0432\u043e"
    ],
    "name:und_x_variant":[
        "\u041d\u043e\u0432\u043e\u0431\u0430\u043b\u0430\u043a\u043e\u0432\u043e"
    ],
    "wof:name":"Novobalakovo",
    "wof:placetype":"locality"
},
  "geometry": {"coordinates":[54.25,55.13333000000001],"type":"Point"}
}