{
  "type": "Feature",
  "properties": {
    "gn:admin1_code":"56",
    "gn:asciiname":"Alisovo",
    "gn:country_code":"RU",
    "gn:dem":223,
    "gn:feature_class":"P",
    "gn:feature_code":"PPL",
    "gn:name":"Alisovo",
    "gn:population":0,
    "gn:timezone":"Europe/Moscow",
    "iso:country":"RU",
    "name:rus_x_preferred":[
        "\u0410\u043b\u0438\u0441\u043e\u0432\u043e"
    ],
    "name:und_x_variant":[
        "\u0410\u043b\u0438\u0441\u043e\u0432\u043e"
    ],
    "wof:name":"Alisovo",
    "wof:placetype":"locality"
},
  "geometry": {"coordinates":[36.4426,52.3531],"type":"Point"}
}