{
  "type": "Feature",
  "properties": {
    "gn:admin1_code":"17",
    "gn:asciiname":"Surgiya",
    "gn:country_code":"RU",
    "gn:dem":1126,
    "gn:feature_class":"P",
    "gn:feature_code":"PPL",
    "gn:name":"Surgiya",
    "gn:population":0,
    "gn:timezone":"Europe/Moscow",
    "iso:country":"RU",
    "name:rus_x_preferred":[
        "\u0421\u0443\u0440\u0433\u0438\u044f"
    ],
    "name:und_x_variant":[
        "Syuragi",
        "Surgiya",
        "\u0421\u0443\u0440\u0433\u0438\u044f"
    ],
    "wof:name":"Surgiya",
    "wof:placetype":"locality"
},
  "geometry": {"coordinates":[47.72097,42.0768],"type":"Point"}
}