{
  "type": "Feature",
  "properties": {
    "gn:admin1_code":"9",
    "gn:asciiname":"Kandaurovo",
    "gn:country_code":"RU",
    "gn:dem":174,
    "gn:feature_class":"P",
    "gn:feature_code":"PPL",
    "gn:name":"Kandaurovo",
    "gn:population":0,
    "gn:timezone":"Europe/Moscow",
    "iso:country":"RU",
    "name:rus_x_preferred":[
        "\u041a\u0430\u043d\u0434\u0430\u0443\u0440\u043e\u0432\u043e"
    ],
    "name:und_x_variant":[
        "Kandaurovka"
    ],
    "wof:name":"Kandaurovo",
    "wof:placetype":"locality"
},
  "geometry": {"coordinates":[37.445,51.2522],"type":"Point"}
}