{
  "type": "Feature",
  "properties": {
    "gn:admin1_code":"20",
    "gn:asciiname":"Yelga",
    "gn:country_code":"RU",
    "gn:dem":504,
    "gn:feature_class":"P",
    "gn:feature_code":"PPL",
    "gn:name":"Yelga",
    "gn:population":0,
    "gn:timezone":"Asia/Irkutsk",
    "iso:country":"RU",
    "name:eng_x_preferred":[
        "Yelga"
    ],
    "name:nor_x_preferred":[
        "Jelga"
    ],
    "name:rus_x_preferred":[
        "\u0415\u043b\u0433\u0430"
    ],
    "name:und_x_variant":[
        "Yalga",
        "Yelgay",
        "Yelga"
    ],
    "wof:name":"Yelga",
    "wof:placetype":"locality"
},
  "geometry": {"coordinates":[107.18498999999998,53.13878],"type":"Point"}
}