{
  "type": "Feature",
  "properties": {
    "gn:admin1_code":"33",
    "gn:asciiname":"Shikhirevskaya",
    "gn:country_code":"RU",
    "gn:dem":156,
    "gn:feature_class":"P",
    "gn:feature_code":"PPL",
    "gn:name":"Shikhirevskaya",
    "gn:population":0,
    "gn:timezone":"Europe/Kirov",
    "iso:country":"RU",
    "name:rus_x_preferred":[
        "\u0428\u0438\u0445\u0438\u0440\u0435\u0432\u0441\u043a\u0430\u044f"
    ],
    "wof:name":"Shikhirevskaya",
    "wof:placetype":"locality"
},
  "geometry": {"coordinates":[50.0335,57.7812],"type":"Point"}
}