{
  "type": "Feature",
  "properties": {
    "gn:admin1_code":"53",
    "gn:asciiname":"Artamonovo",
    "gn:country_code":"RU",
    "gn:dem":206,
    "gn:feature_class":"P",
    "gn:feature_code":"PPL",
    "gn:name":"Artamonovo",
    "gn:population":0,
    "gn:timezone":"Asia/Novosibirsk",
    "iso:country":"RU",
    "name:che_x_preferred":[
        "\u0410\u0440\u0442\u0430\u043c\u043e\u043d\u043e\u0432\u043e"
    ],
    "name:eng_x_preferred":[
        "Artamonovo"
    ],
    "name:nor_x_preferred":[
        "Artamonovo"
    ],
    "name:rus_x_preferred":[
        "\u0410\u0440\u0442\u0430\u043c\u043e\u043d\u043e\u0432\u043e"
    ],
    "name:und_x_variant":[
        "Artamonova"
    ],
    "wof:name":"Artamonovo",
    "wof:placetype":"locality"
},
  "geometry": {"coordinates":[82.13290000000001,54.1852],"type":"Point"}
}