{
  "type": "Feature",
  "properties": {
    "gn:admin1_code":"78",
    "gn:asciiname":"Baykalovo",
    "gn:country_code":"RU",
    "gn:dem":51,
    "gn:feature_class":"P",
    "gn:feature_code":"PPL",
    "gn:name":"Baykalovo",
    "gn:population":0,
    "gn:timezone":"Asia/Yekaterinburg",
    "iso:country":"RU",
    "name:eng_x_preferred":[
        "Baykalovo"
    ],
    "name:nor_x_preferred":[
        "Bajkalovo"
    ],
    "name:rus_x_preferred":[
        "\u0411\u0430\u0439\u043a\u0430\u043b\u043e\u0432\u043e"
    ],
    "name:und_x_variant":[
        "\u0411\u0430\u0439\u043a\u0430\u043b\u043e\u0432\u043e",
        "Baykalovo"
    ],
    "wof:name":"Baykalovo",
    "wof:placetype":"locality"
},
  "geometry": {"coordinates":[67.66667,57.75],"type":"Point"}
}