{
  "type": "Feature",
  "properties": {
    "gn:admin1_code":"59",
    "gn:asciiname":"Nizhniye Luzhki",
    "gn:country_code":"RU",
    "gn:dem":345,
    "gn:feature_class":"P",
    "gn:feature_code":"PPL",
    "gn:name":"Nizhniye Luzhki",
    "gn:population":0,
    "gn:timezone":"Asia/Vladivostok",
    "iso:country":"RU",
    "name:eng_x_preferred":[
        "Nizhniye Luzhki"
    ],
    "name:nor_x_preferred":[
        "Nizjnije Luki"
    ],
    "name:rus_x_preferred":[
        "\u041d\u0438\u0436\u043d\u0438\u0435 \u041b\u0443\u043a\u0438"
    ],
    "name:rus_x_variant":[
        "\u041d\u0438\u0436\u043d\u0438\u0435 \u041b\u0443\u0436\u043a\u0438"
    ],
    "name:und_x_variant":[
        "Nizhniye Lizhki",
        "Nizhniye Luzhki",
        "\u041d\u0438\u0436\u043d\u0438\u0435 \u041b\u0443\u0436\u043a\u0438"
    ],
    "wof:name":"Nizhniye Luzhki",
    "wof:placetype":"locality"
},
  "geometry": {"coordinates":[134.75582,44.29575],"type":"Point"}
}