{
  "type": "Feature",
  "properties": {
    "gn:admin1_code":"20",
    "gn:asciiname":"Surkova",
    "gn:country_code":"RU",
    "gn:dem":593,
    "gn:feature_class":"P",
    "gn:feature_code":"PPL",
    "gn:name":"Surkova",
    "gn:population":0,
    "gn:timezone":"Asia/Irkutsk",
    "iso:country":"RU",
    "name:rus_x_preferred":[
        "\u0421\u0443\u0440\u043a\u043e\u0432\u0430"
    ],
    "name:und_x_variant":[
        "\u0421\u0443\u0440\u043a\u043e\u0432\u0430"
    ],
    "wof:name":"Surkova",
    "wof:placetype":"locality"
},
  "geometry": {"coordinates":[103.86667,52.93333000000001],"type":"Point"}
}