{
  "type": "Feature",
  "properties": {
    "gn:admin1_code":"62",
    "gn:asciiname":"Myshenkova",
    "gn:country_code":"RU",
    "gn:dem":154,
    "gn:feature_class":"P",
    "gn:feature_code":"PPL",
    "gn:name":"Mysh\u00ebnkova",
    "gn:population":0,
    "gn:timezone":"Europe/Moscow",
    "iso:country":"RU",
    "name:rus_x_preferred":[
        "\u041c\u044b\u0448\u0451\u043d\u043a\u043e\u0432\u0430"
    ],
    "name:und_x_variant":[
        "Mysh\u00ebnkova"
    ],
    "wof:name":"Myshenkova",
    "wof:placetype":"locality"
},
  "geometry": {"coordinates":[41.47727,54.01476],"type":"Point"}
}