{
  "type": "Feature",
  "properties": {
    "gn:admin1_code":"73",
    "gn:asciiname":"Novoye Safarovo",
    "gn:country_code":"RU",
    "gn:dem":188,
    "gn:feature_class":"P",
    "gn:feature_code":"PPL",
    "gn:name":"Novoye Safarovo",
    "gn:population":0,
    "gn:timezone":"Europe/Moscow",
    "iso:country":"RU",
    "name:rus_x_preferred":[
        "\u041d\u043e\u0432\u043e\u0435 \u0421\u0430\u0444\u0430\u0440\u043e\u0432\u043e"
    ],
    "name:und_x_variant":[
        "\u041d\u043e\u0432\u043e\u0435 \u0421\u0430\u0444\u0430\u0440\u043e\u0432\u043e"
    ],
    "wof:name":"Novoye Safarovo",
    "wof:placetype":"locality"
},
  "geometry": {"coordinates":[53.5232,55.2361],"type":"Point"}
}