{
  "type": "Feature",
  "properties": {
    "gn:admin1_code":"85",
    "gn:asciiname":"Izbnaya",
    "gn:country_code":"RU",
    "gn:dem":202,
    "gn:feature_class":"P",
    "gn:feature_code":"PPL",
    "gn:name":"Izbnaya",
    "gn:population":0,
    "gn:timezone":"Europe/Moscow",
    "iso:country":"RU",
    "name:rus_x_preferred":[
        "\u0418\u0437\u0431\u043d\u0430\u044f"
    ],
    "name:und_x_variant":[
        "\u0418\u0437\u0431\u043d\u0430\u044f"
    ],
    "wof:name":"Izbnaya",
    "wof:placetype":"locality"
},
  "geometry": {"coordinates":[38.87816,58.79595],"type":"Point"}
}