{
  "type": "Feature",
  "properties": {
    "gn:admin1_code":"62",
    "gn:asciiname":"Spass-Nekrasovo",
    "gn:country_code":"RU",
    "gn:dem":185,
    "gn:feature_class":"P",
    "gn:feature_code":"PPL",
    "gn:name":"Spass-Nekrasovo",
    "gn:population":0,
    "gn:timezone":"Europe/Moscow",
    "iso:country":"RU",
    "name:rus_x_preferred":[
        "\u0421\u043f\u0430\u0441\u0441-\u041d\u0435\u043a\u0440\u0430\u0441\u043e\u0432\u043e"
    ],
    "name:und_x_variant":[
        "Spas-Nekrasovo"
    ],
    "wof:name":"Spass-Nekrasovo",
    "wof:placetype":"locality"
},
  "geometry": {"coordinates":[38.79371,54.20822],"type":"Point"}
}