{
  "type": "Feature",
  "properties": {
    "gn:admin1_code":"9",
    "gn:asciiname":"Nizhniy Ol'shanets",
    "gn:country_code":"RU",
    "gn:dem":119,
    "gn:feature_class":"P",
    "gn:feature_code":"PPL",
    "gn:name":"Nizhniy Ol\u2019shanets",
    "gn:population":0,
    "gn:timezone":"Europe/Moscow",
    "iso:country":"RU",
    "name:rus_x_preferred":[
        "\u041d\u0438\u0436\u043d\u0438\u0439 \u041e\u043b\u044c\u0448\u0430\u043d\u0435\u0446"
    ],
    "name:und_x_variant":[
        "Nizhniy Ol\u2019shanets"
    ],
    "wof:name":"Nizhniy Ol'shanets",
    "wof:placetype":"locality"
},
  "geometry": {"coordinates":[36.6807,50.49299],"type":"Point"}
}