{
  "type": "Feature",
  "properties": {
    "gn:admin1_code":"76.0",
    "gn:asciiname":"Fursovo",
    "gn:country_code":"RU",
    "gn:dem":167,
    "gn:feature_class":"P",
    "gn:feature_code":"PPL",
    "gn:name":"Fursovo",
    "gn:population":0,
    "gn:timezone":"Europe/Moscow",
    "iso:country":"RU",
    "name:rus_x_preferred":[
        "\u0424\u0443\u0440\u0441\u043e\u0432\u043e"
    ],
    "name:und_x_variant":[
        "\u0424\u0443\u0440\u0441\u043e\u0432\u043e"
    ],
    "wof:name":"Fursovo",
    "wof:placetype":"locality"
},
  "geometry": {"coordinates":[36.35164,53.55354000000001],"type":"Point"}
}