{
  "type": "Feature",
  "properties": {
    "gn:admin1_code":"6",
    "gn:asciiname":"Kuliga",
    "gn:country_code":"RU",
    "gn:dem":86,
    "gn:feature_class":"P",
    "gn:feature_code":"PPL",
    "gn:name":"Kuliga",
    "gn:population":0,
    "gn:timezone":"Europe/Moscow",
    "iso:country":"RU",
    "name:che_x_preferred":[
        "\u041a\u0443\u043b\u0438\u0433\u0430"
    ],
    "name:eng_x_preferred":[
        "Kuliga"
    ],
    "name:nor_x_preferred":[
        "Kuliga"
    ],
    "name:rus_x_preferred":[
        "\u041a\u0443\u043b\u0438\u0433\u0430"
    ],
    "name:tgk_x_preferred":[
        "\u041a\u0443\u043b\u0438\u0433\u0430"
    ],
    "wof:name":"Kuliga",
    "wof:placetype":"locality"
},
  "geometry": {"coordinates":[48.06572,61.62116],"type":"Point"}
}