{
  "type": "Feature",
  "properties": {
    "gn:admin1_code":"77",
    "gn:asciiname":"Zelenyy Bor",
    "gn:country_code":"RU",
    "gn:dem":236,
    "gn:feature_class":"P",
    "gn:feature_code":"PPL",
    "gn:name":"Zel\u00ebnyy Bor",
    "gn:population":0,
    "gn:timezone":"Europe/Moscow",
    "iso:country":"RU",
    "name:rus_x_preferred":[
        "\u0417\u0435\u043b\u00eb\u043d\u044b\u0439 \u0411\u043e\u0440"
    ],
    "name:und_x_variant":[
        "Zel\u00ebnyy Bor"
    ],
    "wof:name":"Zelenyy Bor",
    "wof:placetype":"locality"
},
  "geometry": {"coordinates":[31.51692,56.84435],"type":"Point"}
}