{
  "type": "Feature",
  "properties": {
    "gn:admin1_code":"33",
    "gn:asciiname":"Chupanovskaya",
    "gn:country_code":"RU",
    "gn:dem":174,
    "gn:feature_class":"P",
    "gn:feature_code":"PPL",
    "gn:name":"Chupanovskaya",
    "gn:population":0,
    "gn:timezone":"Europe/Kirov",
    "iso:country":"RU",
    "name:rus_x_preferred":[
        "\u0427\u0443\u043f\u0430\u043d\u043e\u0432\u0441\u043a\u0430\u044f"
    ],
    "wof:name":"Chupanovskaya",
    "wof:placetype":"locality"
},
  "geometry": {"coordinates":[47.85405,59.5872],"type":"Point"}
}