{
  "type": "Feature",
  "properties": {
    "gn:admin1_code":"84.0",
    "gn:asciiname":"Bol'shaya Donshchinka",
    "gn:country_code":"RU",
    "gn:dem":116,
    "gn:feature_class":"P",
    "gn:feature_code":"PPL",
    "gn:name":"Bol\u2019shaya Donshchinka",
    "gn:population":0,
    "gn:timezone":"Europe/Volgograd",
    "iso:country":"RU",
    "name:rus_x_preferred":[
        "\u0411\u043e\u043b\u044c\u0448\u0430\u044f \u0414\u043e\u043d\u0449\u0438\u043d\u043a\u0430"
    ],
    "name:und_x_variant":[
        "Bolshe Donshchinskoi",
        "Bol\u2019she-Donshchinskiy",
        "Bol\u2019shiye Donshchinskiy",
        "Bol\u2019shaya Donshchinka"
    ],
    "wof:name":"Bol'shaya Donshchinka",
    "wof:placetype":"locality"
},
  "geometry": {"coordinates":[42.43663,49.14386],"type":"Point"}
}