{
  "type": "Feature",
  "properties": {
    "gn:admin1_code":"77",
    "gn:asciiname":"Sukhoryane",
    "gn:country_code":"RU",
    "gn:dem":166,
    "gn:feature_class":"P",
    "gn:feature_code":"PPL",
    "gn:name":"Sukhoryane",
    "gn:population":0,
    "gn:timezone":"Europe/Moscow",
    "iso:country":"RU",
    "name:rus_x_preferred":[
        "\u0421\u0443\u0445\u043e\u0440\u044f\u043d\u0435"
    ],
    "name:und_x_variant":[
        "\u0421\u0443\u0445\u043e\u0440\u044f\u043d\u0435"
    ],
    "wof:name":"Sukhoryane",
    "wof:placetype":"locality"
},
  "geometry": {"coordinates":[31.32275,56.70283000000001],"type":"Point"}
}