{
  "type": "Feature",
  "properties": {
    "gn:admin1_code":"61",
    "gn:asciiname":"Mashnev",
    "gn:country_code":"RU",
    "gn:dem":187,
    "gn:feature_class":"P",
    "gn:feature_code":"PPL",
    "gn:name":"Mashnev",
    "gn:population":0,
    "gn:timezone":"Europe/Moscow",
    "iso:country":"RU",
    "name:rus_x_preferred":[
        "\u041c\u0430\u0448\u043d\u0435\u0432"
    ],
    "wof:name":"Mashnev",
    "wof:placetype":"locality"
},
  "geometry": {"coordinates":[40.54056,49.48444],"type":"Point"}
}