{
  "type": "Feature",
  "properties": {
    "gn:admin1_code":"50",
    "gn:asciiname":"Poylova",
    "gn:country_code":"RU",
    "gn:dem":3,
    "gn:feature_class":"P",
    "gn:feature_code":"PPL",
    "gn:name":"Poylova",
    "gn:population":0,
    "gn:timezone":"Europe/Moscow",
    "iso:country":"RU",
    "name:rus_x_preferred":[
        "\u041f\u043e\u0439\u043b\u043e\u0432\u0430"
    ],
    "name:und_x_variant":[
        "\u041f\u043e\u0439\u043b\u043e\u0432\u0430"
    ],
    "wof:name":"Poylova",
    "wof:placetype":"locality"
},
  "geometry": {"coordinates":[53.33333,67.84999999999999],"type":"Point"}
}