{
  "type": "Feature",
  "properties": {
    "gn:admin1_code":"85",
    "gn:asciiname":"Popovkino",
    "gn:country_code":"RU",
    "gn:dem":189,
    "gn:feature_class":"P",
    "gn:feature_code":"PPL",
    "gn:name":"Popovkino",
    "gn:population":0,
    "gn:timezone":"Europe/Moscow",
    "iso:country":"RU",
    "name:eng_x_preferred":[
        "Popovkino"
    ],
    "name:nor_x_preferred":[
        "Popovkino"
    ],
    "name:rus_x_preferred":[
        "\u041f\u043e\u043f\u043e\u0432\u043a\u0438\u043d\u043e"
    ],
    "wof:name":"Popovkino",
    "wof:placetype":"locality"
},
  "geometry": {"coordinates":[40.38048,58.67969],"type":"Point"}
}