{
  "type": "Feature",
  "properties": {
    "gn:admin1_code":"69.0",
    "gn:asciiname":"Burtakino",
    "gn:country_code":"RU",
    "gn:dem":196,
    "gn:feature_class":"P",
    "gn:feature_code":"PPL",
    "gn:name":"Burtakino",
    "gn:population":0,
    "gn:timezone":"Europe/Moscow",
    "iso:country":"RU",
    "name:rus_x_preferred":[
        "\u0411\u0443\u0440\u0442\u0430\u043a\u0438\u043d\u043e"
    ],
    "name:und_x_variant":[
        "\u0411\u0443\u0440\u0442\u0430\u043a\u0438\u043d\u043e"
    ],
    "wof:name":"Burtakino",
    "wof:placetype":"locality"
},
  "geometry": {"coordinates":[34.08278,54.76917],"type":"Point"}
}