{
  "type": "Feature",
  "properties": {
    "gn:admin1_code":"60",
    "gn:asciiname":"Bol'shiye Gvozdy",
    "gn:country_code":"RU",
    "gn:dem":133,
    "gn:feature_class":"P",
    "gn:feature_code":"PPL",
    "gn:name":"Bol\u2019shiye Gvozdy",
    "gn:population":0,
    "gn:timezone":"Europe/Moscow",
    "iso:country":"RU",
    "name:rus_x_preferred":[
        "\u0411\u043e\u043b\u044c\u0448\u0438\u0435 \u0413\u0432\u043e\u0437\u0434\u044b"
    ],
    "name:und_x_variant":[
        "Bol\u2019shiye Gvozdy"
    ],
    "wof:name":"Bol'shiye Gvozdy",
    "wof:placetype":"locality"
},
  "geometry": {"coordinates":[28.9933,56.3485],"type":"Point"}
}