{
  "type": "Feature",
  "properties": {
    "gn:admin1_code":"67",
    "gn:asciiname":"Yekaterinovka",
    "gn:country_code":"RU",
    "gn:dem":209,
    "gn:feature_class":"P",
    "gn:feature_code":"PPL",
    "gn:name":"Yekaterinovka",
    "gn:population":0,
    "gn:timezone":"Europe/Saratov",
    "iso:country":"RU",
    "wof:name":"Yekaterinovka",
    "wof:placetype":"locality"
},
  "geometry": {"coordinates":[45.96667,52.25],"type":"Point"}
}