{
  "type": "Feature",
  "properties": {
    "gn:admin1_code":"45.0",
    "gn:asciiname":"Miziner",
    "gn:country_code":"RU",
    "gn:dem":165,
    "gn:feature_class":"P",
    "gn:feature_code":"PPL",
    "gn:name":"Miziner",
    "gn:population":0,
    "gn:timezone":"Europe/Moscow",
    "iso:country":"RU",
    "name:rus_x_preferred":[
        "\u041c\u0438\u0437\u0438\u043d\u0435\u0440"
    ],
    "wof:name":"Miziner",
    "wof:placetype":"locality"
},
  "geometry": {"coordinates":[48.74139,56.40722],"type":"Point"}
}