{
  "type": "Feature",
  "properties": {
    "gn:admin1_code":"53",
    "gn:asciiname":"Novoitkul'skoye",
    "gn:country_code":"RU",
    "gn:dem":144,
    "gn:feature_class":"P",
    "gn:feature_code":"PPL",
    "gn:name":"Novoitkul\u2019skoye",
    "gn:population":0,
    "gn:timezone":"Asia/Novosibirsk",
    "iso:country":"RU",
    "name:eng_x_preferred":[
        "Novoitkul'skoye"
    ],
    "name:nor_x_preferred":[
        "Novoitkulskoje"
    ],
    "name:rus_x_preferred":[
        "\u041d\u043e\u0432\u043e\u0438\u0442\u043a\u0443\u043b\u044c\u0441\u043a\u043e\u0435"
    ],
    "name:und_x_variant":[
        "Sovkhoz Itkul\u2019skiy",
        "Novoitkul\u2019skoye"
    ],
    "wof:name":"Novoitkul'skoye",
    "wof:placetype":"locality"
},
  "geometry": {"coordinates":[81.0615,55.0494],"type":"Point"}
}