{
  "type": "Feature",
  "properties": {
    "gn:admin1_code":"77",
    "gn:asciiname":"Tarakanovo",
    "gn:country_code":"RU",
    "gn:dem":225,
    "gn:feature_class":"P",
    "gn:feature_code":"PPL",
    "gn:name":"Tarakanovo",
    "gn:population":0,
    "gn:timezone":"Europe/Moscow",
    "iso:country":"RU",
    "name:rus_x_preferred":[
        "\u0422\u0430\u0440\u0430\u043a\u0430\u043d\u043e\u0432\u043e"
    ],
    "wof:name":"Tarakanovo",
    "wof:placetype":"locality"
},
  "geometry": {"coordinates":[32.9844,55.7612],"type":"Point"}
}