{
  "type": "Feature",
  "properties": {
    "gn:admin1_code":"84.0",
    "gn:asciiname":"Dubovskoy",
    "gn:country_code":"RU",
    "gn:dem":127,
    "gn:feature_class":"P",
    "gn:feature_code":"PPL",
    "gn:name":"Dubovskoy",
    "gn:population":0,
    "gn:timezone":"Europe/Volgograd",
    "iso:country":"RU",
    "name:rus_x_preferred":[
        "\u0414\u0443\u0431\u043e\u0432\u0441\u043a\u043e\u0439"
    ],
    "name:und_x_variant":[
        "Khutor Dubovskoy",
        "Dubrovskiy",
        "Dubovskoy"
    ],
    "wof:name":"Dubovskoy",
    "wof:placetype":"locality"
},
  "geometry": {"coordinates":[42.0561,49.8163],"type":"Point"}
}