{
  "type": "Feature",
  "properties": {
    "gn:admin1_code":"88.0",
    "gn:asciiname":"Larino",
    "gn:country_code":"RU",
    "gn:dem":116,
    "gn:feature_class":"P",
    "gn:feature_code":"PPL",
    "gn:name":"Larino",
    "gn:population":0,
    "gn:timezone":"Europe/Moscow",
    "iso:country":"RU",
    "name:rus_x_preferred":[
        "\u041b\u0430\u0440\u0438\u043d\u043e"
    ],
    "name:und_x_variant":[
        "\u041b\u0430\u0440\u0438\u043d\u043e"
    ],
    "wof:name":"Larino",
    "wof:placetype":"locality"
},
  "geometry": {"coordinates":[40.68701,58.21235],"type":"Point"}
}