{
  "type": "Feature",
  "properties": {
    "gn:admin1_code":"70",
    "gn:asciiname":"Krasnyy Oktyabr'",
    "gn:country_code":"RU",
    "gn:dem":98,
    "gn:feature_class":"P",
    "gn:feature_code":"PPL",
    "gn:name":"Krasnyy Oktyabr'",
    "gn:population":0,
    "gn:timezone":"Europe/Moscow",
    "iso:country":"RU",
    "wof:name":"Krasnyy Oktyabr'",
    "wof:placetype":"locality"
},
  "geometry": {"coordinates":[41.41333,45.68167],"type":"Point"}
}