{
  "type": "Feature",
  "properties": {
    "gn:admin1_code":"20",
    "gn:asciiname":"Shadrina",
    "gn:cc2":"RU",
    "gn:country_code":"RU",
    "gn:dem":578,
    "gn:feature_class":"P",
    "gn:feature_code":"PPL",
    "gn:name":"Shadrina",
    "gn:population":0,
    "gn:timezone":"Asia/Irkutsk",
    "iso:country":"RU",
    "name:und_x_variant":[
        "Zimnik Shadrina",
        "Shadrina"
    ],
    "wof:name":"Shadrina",
    "wof:placetype":"locality"
},
  "geometry": {"coordinates":[103.08222000000001,53.17694],"type":"Point"}
}