{
  "type": "Feature",
  "properties": {
    "gn:country":"RU",
    "gn:fcode":"PPL",
    "gn:population":0,
    "iso:country":"RU",
    "name:nor_x_preferred":[
        "Bjokhovo"
    ],
    "name:rus_x_preferred":[
        "\u0411\u0451\u0445\u043e\u0432\u043e"
    ],
    "name:und_x_variant":[
        "B\u00ebkhovo"
    ],
    "qs:name":"Bekhovo",
    "qs:name_adm0":"Russia",
    "qs:name_adm1":"Tula Oblast",
    "qs:photos_9r":0,
    "qs:photos_sr":0,
    "qs:placetype":"Town",
    "qs:pop_sr":"0",
    "wof:name":"Bekhovo",
    "wof:placetype":"locality",
    "wof:population":0
},
  "geometry": {"coordinates":[37.24938,54.76022],"type":"Point"}
}