{
  "type": "Feature",
  "properties": {
    "gn:admin1_code":"77",
    "gn:asciiname":"Kornilovka",
    "gn:cc2":"RU",
    "gn:country_code":"RU",
    "gn:dem":223,
    "gn:feature_class":"P",
    "gn:feature_code":"PPL",
    "gn:name":"Kornilovka",
    "gn:population":0,
    "gn:timezone":"Europe/Moscow",
    "iso:country":"RU",
    "name:eng_x_preferred":[
        "Kornilovka"
    ],
    "name:nor_x_preferred":[
        "Kozlovo"
    ],
    "name:rus_x_preferred":[
        "\u041a\u043e\u0437\u043b\u043e\u0432\u043e"
    ],
    "name:rus_x_variant":[
        "\u041a\u043e\u0440\u043d\u0438\u043b\u043e\u0432\u043a\u0430"
    ],
    "name:und_x_variant":[
        "Kornilova"
    ],
    "wof:name":"Kornilovka",
    "wof:placetype":"locality"
},
  "geometry": {"coordinates":[32.28333,56.56667],"type":"Point"}
}