{
  "type": "Feature",
  "properties": {
    "gn:admin1_code":"53",
    "gn:asciiname":"Yelovyy Padun",
    "gn:cc2":"RU",
    "gn:country_code":"RU",
    "gn:dem":155,
    "gn:feature_class":"P",
    "gn:feature_code":"PPL",
    "gn:name":"Yelovyy Padun",
    "gn:population":0,
    "gn:timezone":"Asia/Novosibirsk",
    "iso:country":"RU",
    "name:und_x_variant":[
        "Butyrskiy",
        "Yelovyy Padun"
    ],
    "wof:name":"Yelovyy Padun",
    "wof:placetype":"locality"
},
  "geometry": {"coordinates":[84.31667,55.75],"type":"Point"}
}