{
  "type": "Feature",
  "properties": {
    "gn:admin1_code":"85",
    "gn:asciiname":"Tretnitsa",
    "gn:country_code":"RU",
    "gn:dem":172,
    "gn:feature_class":"P",
    "gn:feature_code":"PPL",
    "gn:name":"Tretnitsa",
    "gn:population":0,
    "gn:timezone":"Europe/Moscow",
    "iso:country":"RU",
    "name:eng_x_preferred":[
        "Tretnitsa"
    ],
    "name:nor_x_preferred":[
        "Tretnitsa"
    ],
    "name:rus_x_preferred":[
        "\u0422\u0440\u0435\u0442\u043d\u0438\u0446\u0430"
    ],
    "name:und_x_variant":[
        "Gretniskiy",
        "Tretnitskiy",
        "Gretnitskiy"
    ],
    "wof:name":"Tretnitsa",
    "wof:placetype":"locality"
},
  "geometry": {"coordinates":[44.44843,60.00207],"type":"Point"}
}