{
  "type": "Feature",
  "properties": {
    "gn:admin1_code":"6",
    "gn:asciiname":"Pantyy",
    "gn:country_code":"RU",
    "gn:dem":124,
    "gn:feature_class":"P",
    "gn:feature_code":"PPL",
    "gn:name":"Pantyy",
    "gn:population":0,
    "gn:timezone":"Europe/Moscow",
    "iso:country":"RU",
    "name:eng_x_preferred":[
        "Pantyy"
    ],
    "name:nor_x_preferred":[
        "Pantyj"
    ],
    "name:rus_x_preferred":[
        "\u041f\u0430\u043d\u0442\u044b\u0439"
    ],
    "wof:name":"Pantyy",
    "wof:placetype":"locality"
},
  "geometry": {"coordinates":[48.88081,62.46658000000001],"type":"Point"}
}