{
  "type": "Feature",
  "properties": {
    "gn:admin1_code":"76",
    "gn:asciiname":"Strakhovo",
    "gn:country_code":"RU",
    "gn:dem":212,
    "gn:feature_class":"P",
    "gn:feature_code":"PPL",
    "gn:name":"Strakhovo",
    "gn:population":0,
    "gn:timezone":"Europe/Moscow",
    "iso:country":"RU",
    "name:und_x_variant":[
        "Strakova"
    ],
    "wof:name":"Strakhovo",
    "wof:placetype":"locality"
},
  "geometry": {"coordinates":[37.74276,54.3203],"type":"Point"}
}