{
  "type": "Feature",
  "properties": {
    "gn:admin1_code":"60",
    "gn:asciiname":"Moshki",
    "gn:country_code":"RU",
    "gn:dem":157,
    "gn:feature_class":"P",
    "gn:feature_code":"PPL",
    "gn:name":"Moshki",
    "gn:population":0,
    "gn:timezone":"Europe/Moscow",
    "iso:country":"RU",
    "name:rus_x_preferred":[
        "\u041c\u043e\u0448\u043a\u0438"
    ],
    "wof:name":"Moshki",
    "wof:placetype":"locality"
},
  "geometry": {"coordinates":[29.1183,56.5731],"type":"Point"}
}