{
  "type": "Feature",
  "properties": {
    "gn:admin1_code":"05",
    "gn:asciiname":"Kurgan",
    "gn:country_code":"RU",
    "gn:dem":213,
    "gn:feature_class":"P",
    "gn:feature_code":"PPL",
    "gn:name":"Kurgan",
    "gn:population":0,
    "gn:timezone":"Asia/Yakutsk",
    "iso:country":"RU",
    "name:eng_x_preferred":[
        "Kurgan"
    ],
    "name:nor_x_preferred":[
        "Kurgan"
    ],
    "name:rus_x_preferred":[
        "\u041a\u0443\u0440\u0433\u0430\u043d"
    ],
    "name:und_x_variant":[
        "Klyuchevskoye",
        "\u041a\u0443\u0440\u0433\u0430\u043d",
        "Kurgan"
    ],
    "wof:name":"Kurgan",
    "wof:placetype":"locality"
},
  "geometry": {"coordinates":[128.10628,51.74531],"type":"Point"}
}