{
  "type": "Feature",
  "properties": {
    "gn:admin1_code":"45.0",
    "gn:asciiname":"Chuksola",
    "gn:country_code":"RU",
    "gn:dem":125,
    "gn:feature_class":"P",
    "gn:feature_code":"PPL",
    "gn:name":"Chuksola",
    "gn:population":0,
    "gn:timezone":"Europe/Moscow",
    "iso:country":"RU",
    "name:rus_x_preferred":[
        "\u0427\u0443\u043a\u0441\u043e\u043b\u0430"
    ],
    "wof:name":"Chuksola",
    "wof:placetype":"locality"
},
  "geometry": {"coordinates":[48.77,57.00444],"type":"Point"}
}