{
  "type": "Feature",
  "properties": {
    "gn:admin1_code":"33",
    "gn:asciiname":"Sharanitsa",
    "gn:country_code":"RU",
    "gn:dem":131,
    "gn:feature_class":"P",
    "gn:feature_code":"PPL",
    "gn:name":"Sharanitsa",
    "gn:population":0,
    "gn:timezone":"Europe/Kirov",
    "iso:country":"RU",
    "name:eng_x_preferred":[
        "Sharanitsa"
    ],
    "name:nor_x_preferred":[
        "Sjaranitsa"
    ],
    "name:rus_x_preferred":[
        "\u0428\u0430\u0440\u0430\u043d\u0438\u0446\u0430"
    ],
    "name:und_x_variant":[
        "\u0428\u0430\u0440\u0430\u043d\u0438\u0446\u0430",
        "Sharanitsa"
    ],
    "wof:name":"Sharanitsa",
    "wof:placetype":"locality"
},
  "geometry": {"coordinates":[48.63213,57.80727],"type":"Point"}
}