{
  "type": "Feature",
  "properties": {
    "gn:admin1_code":"33.0",
    "gn:asciiname":"Zolotukhino",
    "gn:country_code":"RU",
    "gn:dem":173,
    "gn:feature_class":"P",
    "gn:feature_code":"PPL",
    "gn:name":"Zolotukhino",
    "gn:population":0,
    "gn:timezone":"Europe/Kirov",
    "iso:country":"RU",
    "name:rus_x_preferred":[
        "\u0417\u043e\u043b\u043e\u0442\u0443\u0445\u0438\u043d\u043e"
    ],
    "wof:name":"Zolotukhino",
    "wof:placetype":"locality"
},
  "geometry": {"coordinates":[50.16323,58.37216],"type":"Point"}
}