{
  "type": "Feature",
  "properties": {
    "gn:admin1_code":"43",
    "gn:asciiname":"Sukhaya Lubna",
    "gn:country_code":"RU",
    "gn:dem":181,
    "gn:feature_class":"P",
    "gn:feature_code":"PPL",
    "gn:name":"Sukhaya Lubna",
    "gn:population":0,
    "gn:timezone":"Europe/Moscow",
    "iso:country":"RU",
    "name:eng_x_preferred":[
        "Sukhaya Lubna"
    ],
    "name:nor_x_preferred":[
        "Sukhaja Lubna"
    ],
    "name:rus_x_preferred":[
        "\u0421\u0443\u0445\u0430\u044f \u041b\u0443\u0431\u043d\u0430"
    ],
    "name:und_x_variant":[
        "Lubny",
        "\u0421\u0443\u0445\u0430\u044f \u041b\u0443\u0431\u043d\u0430",
        "Sukhaya Lubna"
    ],
    "wof:name":"Sukhaya Lubna",
    "wof:placetype":"locality"
},
  "geometry": {"coordinates":[39.3426,52.8004],"type":"Point"}
}