{
  "type": "Feature",
  "properties": {
    "gn:admin1_code":"12.0",
    "gn:asciiname":"Ioka-Erbel'",
    "gn:country_code":"RU",
    "gn:dem":1637,
    "gn:feature_class":"P",
    "gn:feature_code":"PPL",
    "gn:name":"Ioka-Erbel\u2019",
    "gn:population":0,
    "gn:timezone":"Europe/Moscow",
    "iso:country":"RU",
    "wof:name":"Ioka-Erbel'",
    "wof:placetype":"locality"
},
  "geometry": {"coordinates":[45.27389,42.96],"type":"Point"}
}