{
  "type": "Feature",
  "properties": {
    "gn:admin1_code":"90",
    "gn:asciiname":"Samozvanka",
    "gn:country_code":"RU",
    "gn:dem":220,
    "gn:feature_class":"P",
    "gn:feature_code":"PPL",
    "gn:name":"Samozvanka",
    "gn:population":0,
    "gn:timezone":"Asia/Yekaterinburg",
    "iso:country":"RU",
    "name:eng_x_preferred":[
        "Samozvanka"
    ],
    "name:nor_x_preferred":[
        "Samozvanka"
    ],
    "name:rus_x_preferred":[
        "\u0421\u0430\u043c\u043e\u0437\u0432\u0430\u043d\u043a\u0430"
    ],
    "name:und_x_variant":[
        "\u0421\u0430\u043c\u043e\u0437\u0432\u0430\u043d\u043a\u0430"
    ],
    "wof:name":"Samozvanka",
    "wof:placetype":"locality"
},
  "geometry": {"coordinates":[53.8679,58.6349],"type":"Point"}
}