{
  "type": "Feature",
  "properties": {
    "gn:admin1_code":"20",
    "gn:asciiname":"Baklan'",
    "gn:country_code":"RU",
    "gn:dem":479,
    "gn:feature_class":"P",
    "gn:feature_code":"PPL",
    "gn:name":"Baklan\u2019",
    "gn:population":0,
    "gn:timezone":"Asia/Irkutsk",
    "iso:country":"RU",
    "name:rus_x_preferred":[
        "\u0411\u0430\u043a\u043b\u0430\u043d\u044c"
    ],
    "name:und_x_variant":[
        "Baklan\u2019"
    ],
    "wof:name":"Baklan'",
    "wof:placetype":"locality"
},
  "geometry": {"coordinates":[104.0945,51.7606],"type":"Point"}
}