{
  "type": "Feature",
  "properties": {
    "gn:admin1_code":"77",
    "gn:asciiname":"Russkiye Ploski",
    "gn:country_code":"RU",
    "gn:dem":146,
    "gn:feature_class":"P",
    "gn:feature_code":"PPL",
    "gn:name":"Russkiye Ploski",
    "gn:population":0,
    "gn:timezone":"Europe/Moscow",
    "iso:country":"RU",
    "name:rus_x_preferred":[
        "\u0420\u0443\u0441\u0441\u043a\u0438\u0435 \u041f\u043b\u043e\u0441\u043a\u0438"
    ],
    "name:und_x_variant":[
        "Ploski",
        "Russkiye Ploski"
    ],
    "wof:name":"Russkiye Ploski",
    "wof:placetype":"locality"
},
  "geometry": {"coordinates":[35.62328,57.67576],"type":"Point"}
}