{
  "type": "Feature",
  "properties": {
    "gn:admin1_code":"64",
    "gn:asciiname":"Seinotsu",
    "gn:country_code":"RU",
    "gn:dem":10,
    "gn:feature_class":"P",
    "gn:feature_code":"PPL",
    "gn:name":"Seinotsu",
    "gn:population":0,
    "gn:timezone":"Asia/Tokyo",
    "iso:country":"RU",
    "name:rus_x_preferred":[
        "\u041d\u043e\u0432\u044c"
    ],
    "name:und_x_variant":[
        "Nov\u2019"
    ],
    "wof:name":"Seinotsu",
    "wof:placetype":"locality"
},
  "geometry": {"coordinates":[147.43333000000001,44.76667],"type":"Point"}
}