{
  "type": "Feature",
  "properties": {
    "gn:admin1_code":"93",
    "gn:asciiname":"Korabl'",
    "gn:country_code":"RU",
    "gn:dem":693,
    "gn:feature_class":"P",
    "gn:feature_code":"PPL",
    "gn:name":"Korabl\u2019",
    "gn:population":0,
    "gn:timezone":"Asia/Chita",
    "iso:country":"RU",
    "name:eng_x_preferred":[
        "Korabl'"
    ],
    "name:nor_x_preferred":[
        "Korabl"
    ],
    "name:rus_x_preferred":[
        "\u041a\u043e\u0440\u0430\u0431\u043b\u044c"
    ],
    "name:und_x_variant":[
        "Korabl\u2019"
    ],
    "wof:name":"Korabl'",
    "wof:placetype":"locality"
},
  "geometry": {"coordinates":[118.29046,51.52866],"type":"Point"}
}