{
  "type": "Feature",
  "properties": {
    "gn:admin1_code":"63",
    "gn:asciiname":"Verkhoyanskaya",
    "gn:country_code":"RU",
    "gn:dem":179,
    "gn:feature_class":"P",
    "gn:feature_code":"PPL",
    "gn:name":"Verkhoyanskaya",
    "gn:population":0,
    "gn:timezone":"Asia/Yakutsk",
    "iso:country":"RU",
    "wof:name":"Verkhoyanskaya",
    "wof:placetype":"locality"
},
  "geometry": {"coordinates":[130.59999999999999,63.61666999999999],"type":"Point"}
}