{
  "type": "Feature",
  "properties": {
    "gn:admin1_code":"62",
    "gn:asciiname":"Yesakovo",
    "gn:country_code":"RU",
    "gn:dem":114,
    "gn:feature_class":"P",
    "gn:feature_code":"PPL",
    "gn:name":"Yesakovo",
    "gn:population":0,
    "gn:timezone":"Europe/Moscow",
    "iso:country":"RU",
    "name:rus_x_preferred":[
        "\u0415\u0441\u0430\u043a\u043e\u0432\u043e"
    ],
    "wof:name":"Yesakovo",
    "wof:placetype":"locality"
},
  "geometry": {"coordinates":[39.76919,53.60175],"type":"Point"}
}