{
  "type": "Feature",
  "properties": {
    "gn:admin1_code":"60",
    "gn:asciiname":"Repino",
    "gn:country_code":"RU",
    "gn:dem":80,
    "gn:feature_class":"P",
    "gn:feature_code":"PPL",
    "gn:name":"Repino",
    "gn:population":0,
    "gn:timezone":"Europe/Moscow",
    "iso:country":"RU",
    "name:rus_x_preferred":[
        "\u0420\u0435\u043f\u0438\u043d\u043e"
    ],
    "wof:name":"Repino",
    "wof:placetype":"locality"
},
  "geometry": {"coordinates":[28.60354,57.01788000000001],"type":"Point"}
}