{
  "type": "Feature",
  "properties": {
    "gn:admin1_code":"69",
    "gn:asciiname":"Rozhdestvo",
    "gn:country_code":"RU",
    "gn:dem":226,
    "gn:feature_class":"P",
    "gn:feature_code":"PPL",
    "gn:name":"Rozhdestvo",
    "gn:population":0,
    "gn:timezone":"Europe/Moscow",
    "iso:country":"RU",
    "name:rus_x_preferred":[
        "\u0420\u043e\u0436\u0434\u0435\u0441\u0442\u0432\u043e"
    ],
    "name:und_x_variant":[
        "Staroye Rozhdestvo",
        "Rozhdestvo"
    ],
    "wof:name":"Rozhdestvo",
    "wof:placetype":"locality"
},
  "geometry": {"coordinates":[33.12761,54.72033],"type":"Point"}
}