{
  "type": "Feature",
  "properties": {
    "gn:admin1_code":"8",
    "gn:asciiname":"Novosarayevo",
    "gn:country_code":"RU",
    "gn:dem":400,
    "gn:feature_class":"P",
    "gn:feature_code":"PPL",
    "gn:name":"Novosarayevo",
    "gn:population":0,
    "gn:timezone":"Asia/Yekaterinburg",
    "iso:country":"RU",
    "name:rus_x_preferred":[
        "\u041d\u043e\u0432\u043e\u0441\u0430\u0440\u0430\u0435\u0432\u043e"
    ],
    "name:und_x_variant":[
        "\u041d\u043e\u0432\u043e\u0441\u0430\u0440\u0430\u0435\u0432\u043e"
    ],
    "wof:name":"Novosarayevo",
    "wof:placetype":"locality"
},
  "geometry": {"coordinates":[54.4457,54.0703],"type":"Point"}
}