{
  "type": "Feature",
  "properties": {
    "gn:admin1_code":"8",
    "gn:asciiname":"Novosarayevo",
    "gn:country_code":"RU",
    "gn:dem":400,
    "gn:feature_class":"P",
    "gn:feature_code":"PPL",
    "gn:name":"Novosarayevo",
    "gn:population":0,
    "gn:timezone":"Asia/Yekaterinburg",
    "iso:country":"RU",
    "name:bak_x_preferred":[
        "\u042f\u04a3\u044b \u04ba\u0430\u0440\u0430\u0439"
    ],
    "name:che_x_preferred":[
        "\u041d\u043e\u0432\u043e\u0441\u0430\u0440\u0430\u0435\u0432\u043e"
    ],
    "name:hye_x_preferred":[
        "\u0546\u0578\u057e\u0578\u057d\u0561\u0580\u0561\u0587\u0578"
    ],
    "name:kaz_x_preferred":[
        "\u0416\u0430\u04a3\u0430 \u0441\u0430\u0440\u0430"
    ],
    "name:kir_x_preferred":[
        "\u0416\u0430\u04a3\u044b \u0441\u0430\u0440\u0430"
    ],
    "name:rus_x_preferred":[
        "\u041d\u043e\u0432\u043e\u0441\u0430\u0440\u0430\u0435\u0432\u043e"
    ],
    "name:tat_x_preferred":[
        "\u042f\u04a3\u0430 \u0421\u0430\u0440\u0430\u0439"
    ],
    "name:ukr_x_preferred":[
        "\u041d\u043e\u0432\u043e\u0441\u0430\u0440\u0430\u0454\u0432\u043e"
    ],
    "wof:name":"Novosarayevo",
    "wof:placetype":"locality"
},
  "geometry": {"coordinates":[54.4457,54.0703],"type":"Point"}
}