{
  "type": "Feature",
  "properties": {
    "gn:admin1_code":"60",
    "gn:asciiname":"Staryy Yamm",
    "gn:country_code":"RU",
    "gn:dem":85,
    "gn:feature_class":"P",
    "gn:feature_code":"PPL",
    "gn:name":"Staryy Yamm",
    "gn:population":0,
    "gn:timezone":"Europe/Moscow",
    "iso:country":"RU",
    "name:rus_x_preferred":[
        "\u0421\u0442\u0430\u0440\u044b\u0439 \u042f\u043c\u043c"
    ],
    "wof:name":"Staryy Yamm",
    "wof:placetype":"locality"
},
  "geometry": {"coordinates":[28.9723,57.8413],"type":"Point"}
}