{
  "type": "Feature",
  "properties": {
    "gn:admin1_code":"53",
    "gn:asciiname":"Mosinskiy",
    "gn:country_code":"RU",
    "gn:dem":220,
    "gn:feature_class":"P",
    "gn:feature_code":"PPL",
    "gn:name":"Mosinskiy",
    "gn:population":0,
    "gn:timezone":"Asia/Novosibirsk",
    "iso:country":"RU",
    "name:rus_x_preferred":[
        "\u041c\u043e\u0441\u0438\u043d\u0441\u043a\u0438\u0439"
    ],
    "wof:name":"Mosinskiy",
    "wof:placetype":"locality"
},
  "geometry": {"coordinates":[83.26666999999998,54.88333000000001],"type":"Point"}
}