{
  "type": "Feature",
  "properties": {
    "gn:admin1_code":"43",
    "gn:asciiname":"Nalivkino",
    "gn:country_code":"RU",
    "gn:dem":152,
    "gn:feature_class":"P",
    "gn:feature_code":"PPL",
    "gn:name":"Nalivkino",
    "gn:population":0,
    "gn:timezone":"Europe/Moscow",
    "iso:country":"RU",
    "name:rus_x_preferred":[
        "\u041d\u0430\u043b\u0438\u0432\u043a\u0438\u043d\u043e"
    ],
    "name:und_x_variant":[
        "Nalivchino",
        "Nalivkino"
    ],
    "wof:name":"Nalivkino",
    "wof:placetype":"locality"
},
  "geometry": {"coordinates":[40.5376,52.1468],"type":"Point"}
}