{
  "type": "Feature",
  "properties": {
    "gn:admin1_code":"91",
    "gn:asciiname":"Buzunovo",
    "gn:cc2":"RU",
    "gn:country_code":"RU",
    "gn:dem":272,
    "gn:feature_class":"P",
    "gn:feature_code":"PPL",
    "gn:name":"Buzunovo",
    "gn:population":0,
    "gn:timezone":"Asia/Krasnoyarsk",
    "iso:country":"RU",
    "name:rus_x_preferred":[
        "\u0411\u0443\u0437\u0443\u043d\u043e\u0432\u043e"
    ],
    "name:und_x_variant":[
        "Bezunovo",
        "Buzunova",
        "Buzunovo"
    ],
    "wof:name":"Buzunovo",
    "wof:placetype":"locality"
},
  "geometry": {"coordinates":[91.61667,54.05],"type":"Point"}
}