{
  "type": "Feature",
  "properties": {
    "gn:admin1_code":"62.0",
    "gn:asciiname":"Bol'shoye Lyakhovo",
    "gn:country_code":"RU",
    "gn:dem":160,
    "gn:feature_class":"P",
    "gn:feature_code":"PPL",
    "gn:name":"Bol\u2019shoye Lyakhovo",
    "gn:population":0,
    "gn:timezone":"Europe/Moscow",
    "iso:country":"RU",
    "name:rus_x_preferred":[
        "Bol\u2019shoye Lyakhovo"
    ],
    "name:rus_x_variant":[
        "\u0411\u043e\u043b\u044c\u0448\u043e\u0435 \u041b\u044f\u0445\u043e\u0432\u043e"
    ],
    "name:und_x_variant":[
        "Lyakhovo"
    ],
    "wof:name":"Bol'shoye Lyakhovo",
    "wof:placetype":"locality"
},
  "geometry": {"coordinates":[42.1166,54.6461],"type":"Point"}
}