{
  "type": "Feature",
  "properties": {
    "gn:admin1_code":"69",
    "gn:asciiname":"Maklok",
    "gn:country_code":"RU",
    "gn:dem":174,
    "gn:feature_class":"P",
    "gn:feature_code":"PPL",
    "gn:name":"Maklok",
    "gn:population":0,
    "gn:timezone":"Europe/Moscow",
    "iso:country":"RU",
    "name:eng_x_preferred":[
        "Maklok"
    ],
    "name:nor_x_preferred":[
        "Maklok"
    ],
    "name:rus_x_preferred":[
        "\u041c\u0430\u043a\u043b\u043e\u043a"
    ],
    "name:und_x_variant":[
        "\u041c\u0430\u043a\u043b\u043e\u043a",
        "Maklok"
    ],
    "wof:name":"Maklok",
    "wof:placetype":"locality"
},
  "geometry": {"coordinates":[31.36762,55.68791],"type":"Point"}
}