{
  "type": "Feature",
  "properties": {
    "gn:admin1_code":"90.0",
    "gn:asciiname":"Yukshur",
    "gn:country_code":"RU",
    "gn:dem":144,
    "gn:feature_class":"P",
    "gn:feature_code":"PPL",
    "gn:name":"Yukshur",
    "gn:population":0,
    "gn:timezone":"Asia/Yekaterinburg",
    "iso:country":"RU",
    "name:rus_x_preferred":[
        "\u042e\u043a\u0448\u0443\u0440"
    ],
    "wof:name":"Yukshur",
    "wof:placetype":"locality"
},
  "geometry": {"coordinates":[55.3358,56.9917],"type":"Point"}
}