{
  "type": "Feature",
  "properties": {
    "gn:admin1_code":"59",
    "gn:asciiname":"Lagonesht",
    "gn:cc2":"RU",
    "gn:country_code":"RU",
    "gn:dem":21,
    "gn:feature_class":"P",
    "gn:feature_code":"PPL",
    "gn:name":"Lagonesht",
    "gn:population":0,
    "gn:timezone":"Asia/Vladivostok",
    "iso:country":"RU",
    "name:und_x_variant":[
        "Lagoneshty"
    ],
    "wof:name":"Lagonesht",
    "wof:placetype":"locality"
},
  "geometry": {"coordinates":[132.80000000000001,42.86667],"type":"Point"}
}