{
  "type": "Feature",
  "properties": {
    "gn:admin1_code":"91",
    "gn:asciiname":"Tortun",
    "gn:country_code":"RU",
    "gn:dem":367,
    "gn:feature_class":"P",
    "gn:feature_code":"PPL",
    "gn:name":"Tortun",
    "gn:population":0,
    "gn:timezone":"Asia/Krasnoyarsk",
    "iso:country":"RU",
    "wof:name":"Tortun",
    "wof:placetype":"locality"
},
  "geometry": {"coordinates":[93.18333,55.76667],"type":"Point"}
}