{
  "type": "Feature",
  "properties": {
    "gn:admin1_code":"77",
    "gn:asciiname":"Aferovo",
    "gn:country_code":"RU",
    "gn:dem":154,
    "gn:feature_class":"P",
    "gn:feature_code":"PPL",
    "gn:name":"Af\u00ebrovo",
    "gn:population":0,
    "gn:timezone":"Europe/Moscow",
    "iso:country":"RU",
    "name:rus_x_preferred":[
        "\u0410\u0444\u0451\u0440\u043e\u0432\u043e"
    ],
    "name:und_x_variant":[
        "Af\u00ebrovo",
        "\u0410\u0444\u0451\u0440\u043e\u0432\u043e"
    ],
    "wof:name":"Aferovo",
    "wof:placetype":"locality"
},
  "geometry": {"coordinates":[38.1285,57.1799],"type":"Point"}
}