{
  "type": "Feature",
  "properties": {
    "gn:admin1_code":"77",
    "gn:asciiname":"Plaskusha",
    "gn:country_code":"RU",
    "gn:dem":228,
    "gn:feature_class":"P",
    "gn:feature_code":"PPL",
    "gn:name":"Plaskusha",
    "gn:population":0,
    "gn:timezone":"Europe/Moscow",
    "iso:country":"RU",
    "name:rus_x_preferred":[
        "\u041f\u043b\u0430\u0441\u043a\u0443\u0448\u0430"
    ],
    "name:und_x_variant":[
        "Ploskusha",
        "Plaskusha",
        "\u041f\u043b\u0430\u0441\u043a\u0443\u0448\u0430"
    ],
    "wof:name":"Plaskusha",
    "wof:placetype":"locality"
},
  "geometry": {"coordinates":[33.34173,56.29662],"type":"Point"}
}