{
  "type": "Feature",
  "properties": {
    "gn:admin1_code":"8",
    "gn:asciiname":"Tara",
    "gn:country_code":"RU",
    "gn:dem":511,
    "gn:feature_class":"P",
    "gn:feature_code":"PPL",
    "gn:name":"Tara",
    "gn:population":0,
    "gn:timezone":"Asia/Yekaterinburg",
    "iso:country":"RU",
    "name:eng_x_preferred":[
        "Tara"
    ],
    "name:nor_x_preferred":[
        "Tara"
    ],
    "name:rus_x_preferred":[
        "\u0422\u0430\u0440\u0430"
    ],
    "name:und_x_variant":[
        "Tarskiy",
        "Tara"
    ],
    "wof:name":"Tara",
    "wof:placetype":"locality"
},
  "geometry": {"coordinates":[57.3716,53.7327],"type":"Point"}
}