{
  "type": "Feature",
  "properties": {
    "gn:admin1_code":"77",
    "gn:asciiname":"Pekishevo",
    "gn:country_code":"RU",
    "gn:dem":246,
    "gn:feature_class":"P",
    "gn:feature_code":"PPL",
    "gn:name":"Pekishevo",
    "gn:population":0,
    "gn:timezone":"Europe/Moscow",
    "iso:country":"RU",
    "name:rus_x_preferred":[
        "\u041f\u0435\u043a\u0438\u0448\u0435\u0432\u043e"
    ],
    "wof:name":"Pekishevo",
    "wof:placetype":"locality"
},
  "geometry": {"coordinates":[34.33375,56.89791999999999],"type":"Point"}
}