{
  "type": "Feature",
  "properties": {
    "gn:admin1_code":"44",
    "gn:asciiname":"Armanskiy",
    "gn:country_code":"RU",
    "gn:dem":6,
    "gn:feature_class":"P",
    "gn:feature_code":"PPL",
    "gn:name":"Armanskiy",
    "gn:population":0,
    "gn:timezone":"Asia/Magadan",
    "iso:country":"RU",
    "name:nor_x_preferred":[
        "Armanskij"
    ],
    "name:rus_x_preferred":[
        "\u0410\u0440\u043c\u0430\u043d\u0441\u043a\u0438\u0439"
    ],
    "wof:name":"Armanskiy",
    "wof:placetype":"locality"
},
  "geometry": {"coordinates":[149.86871000000005,59.72649000000001],"type":"Point"}
}