{
  "type": "Feature",
  "properties": {
    "gn:admin1_code":"33",
    "gn:asciiname":"Sempanur",
    "gn:country_code":"RU",
    "gn:dem":117,
    "gn:feature_class":"P",
    "gn:feature_code":"PPL",
    "gn:name":"Sempanur",
    "gn:population":0,
    "gn:timezone":"Europe/Kirov",
    "iso:country":"RU",
    "name:rus_x_preferred":[
        "\u0421\u0435\u043c\u043f\u0430\u043d\u0443\u0440"
    ],
    "wof:name":"Sempanur",
    "wof:placetype":"locality"
},
  "geometry": {"coordinates":[48.48333,57.48333],"type":"Point"}
}