{
  "type": "Feature",
  "properties": {
    "gn:admin1_code":"25",
    "gn:asciiname":"Krasnikovo",
    "gn:country_code":"RU",
    "gn:dem":201,
    "gn:feature_class":"P",
    "gn:feature_code":"PPL",
    "gn:name":"Krasnikovo",
    "gn:population":0,
    "gn:timezone":"Europe/Moscow",
    "iso:country":"RU",
    "name:rus_x_preferred":[
        "\u041a\u0440\u0430\u0441\u043d\u0438\u043a\u043e\u0432\u043e"
    ],
    "wof:name":"Krasnikovo",
    "wof:placetype":"locality"
},
  "geometry": {"coordinates":[33.96889,54.03833],"type":"Point"}
}