{
  "type": "Feature",
  "properties": {
    "gn:admin1_code":"77",
    "gn:asciiname":"Syvorotkino",
    "gn:country_code":"RU",
    "gn:dem":150,
    "gn:feature_class":"P",
    "gn:feature_code":"PPL",
    "gn:name":"Syvorotkino",
    "gn:population":0,
    "gn:timezone":"Europe/Moscow",
    "iso:country":"RU",
    "name:rus_x_preferred":[
        "\u0421\u044b\u0432\u043e\u0440\u043e\u0442\u043a\u0438\u043d\u043e"
    ],
    "name:und_x_variant":[
        "\u0421\u044b\u0432\u043e\u0440\u043e\u0442\u043a\u0438\u043d\u043e"
    ],
    "wof:name":"Syvorotkino",
    "wof:placetype":"locality"
},
  "geometry": {"coordinates":[37.4912,57.6385],"type":"Point"}
}