{
  "type": "Feature",
  "properties": {
    "gn:admin1_code":"90",
    "gn:asciiname":"Vaya",
    "gn:country_code":"RU",
    "gn:dem":161,
    "gn:feature_class":"P",
    "gn:feature_code":"PPL",
    "gn:name":"Vaya",
    "gn:population":0,
    "gn:timezone":"Asia/Yekaterinburg",
    "iso:country":"RU",
    "name:ceb_x_preferred":[
        "Vaya"
    ],
    "name:fra_x_preferred":[
        "Vaya"
    ],
    "name:swe_x_preferred":[
        "Vaya"
    ],
    "wof:name":"Vaya",
    "wof:placetype":"locality"
},
  "geometry": {"coordinates":[58.38069,60.59009],"type":"Point"}
}