{
  "type": "Feature",
  "properties": {
    "gn:admin1_code":"88",
    "gn:asciiname":"Glazki",
    "gn:country_code":"RU",
    "gn:dem":130,
    "gn:feature_class":"P",
    "gn:feature_code":"PPL",
    "gn:name":"Glazki",
    "gn:population":0,
    "gn:timezone":"Europe/Moscow",
    "iso:country":"RU",
    "name:rus_x_preferred":[
        "\u0413\u043b\u0430\u0437\u043a\u0438"
    ],
    "name:und_x_variant":[
        "\u0413\u043b\u0430\u0437\u043a\u0438"
    ],
    "wof:name":"Glazki",
    "wof:placetype":"locality"
},
  "geometry": {"coordinates":[38.1802,57.9207],"type":"Point"}
}