{
  "type": "Feature",
  "properties": {
    "gn:admin1_code":"88",
    "gn:asciiname":"Urakovo",
    "gn:country_code":"RU",
    "gn:dem":127,
    "gn:feature_class":"P",
    "gn:feature_code":"PPL",
    "gn:name":"Urakovo",
    "gn:population":0,
    "gn:timezone":"Europe/Moscow",
    "iso:country":"RU",
    "name:bak_x_preferred":[
        "\u0423\u0440\u0430\u04a1"
    ],
    "name:che_x_preferred":[
        "\u0423\u0440\u0430\u043a\u043e\u0432\u043e"
    ],
    "name:hye_x_preferred":[
        "\u0548\u0582\u0580\u0561\u056f\u0578\u057e\u0578"
    ],
    "name:kat_x_preferred":[
        "\u10e3\u10e0\u10d0\u10d9\u10dd\u10d5\u10dd"
    ],
    "name:rus_x_preferred":[
        "\u0423\u0440\u0430\u043a\u043e\u0432\u043e"
    ],
    "name:tat_x_preferred":[
        "\u0423\u0440\u0430\u043a"
    ],
    "name:und_x_variant":[
        "\u0423\u0440\u0430\u043a\u043e\u0432\u043e"
    ],
    "wof:name":"Urakovo",
    "wof:placetype":"locality"
},
  "geometry": {"coordinates":[38.374,57.5023],"type":"Point"}
}