{
  "type": "Feature",
  "properties": {
    "gn:admin1_code":"47.0",
    "gn:asciiname":"Akri",
    "gn:country_code":"RU",
    "gn:dem":165,
    "gn:feature_class":"P",
    "gn:feature_code":"PPL",
    "gn:name":"Akri",
    "gn:population":0,
    "gn:timezone":"Europe/Moscow",
    "iso:country":"RU",
    "name:nor_x_preferred":[
        "Akri"
    ],
    "name:rus_x_preferred":[
        "\u0410\u043a\u0440\u0438"
    ],
    "wof:name":"Akri",
    "wof:placetype":"locality"
},
  "geometry": {"coordinates":[38.12377,54.87546],"type":"Point"}
}