{
  "type": "Feature",
  "properties": {
    "gn:admin1_code":"70.0",
    "gn:asciiname":"Mengish-Kui",
    "gn:country_code":"RU",
    "gn:dem":77,
    "gn:feature_class":"P",
    "gn:feature_code":"PPL",
    "gn:name":"Mengish-Kui",
    "gn:population":0,
    "gn:timezone":"Europe/Moscow",
    "iso:country":"RU",
    "wof:name":"Mengish-Kui",
    "wof:placetype":"locality"
},
  "geometry": {"coordinates":[45.0775,44.36306],"type":"Point"}
}