{
  "type": "Feature",
  "properties": {
    "gn:admin1_code":"60",
    "gn:asciiname":"Prudishche",
    "gn:country_code":"RU",
    "gn:dem":153,
    "gn:feature_class":"P",
    "gn:feature_code":"PPL",
    "gn:name":"Prudishche",
    "gn:population":0,
    "gn:timezone":"Europe/Moscow",
    "iso:country":"RU",
    "name:rus_x_preferred":[
        "\u041f\u0440\u0443\u0434\u0438\u0449\u0435"
    ],
    "wof:name":"Prudishche",
    "wof:placetype":"locality"
},
  "geometry": {"coordinates":[30.68803,55.77206],"type":"Point"}
}