{
  "type": "Feature",
  "properties": {
    "gn:admin1_code":"54",
    "gn:asciiname":"Uval'naya Bitiya",
    "gn:country_code":"RU",
    "gn:dem":83,
    "gn:feature_class":"P",
    "gn:feature_code":"PPL",
    "gn:name":"Uval\u2019naya Bitiya",
    "gn:population":0,
    "gn:timezone":"Asia/Omsk",
    "iso:country":"RU",
    "name:eng_x_preferred":[
        "Uval'naya Bitiya"
    ],
    "name:nor_x_preferred":[
        "Uvalnaja-Bitia"
    ],
    "name:rus_x_preferred":[
        "\u0423\u0432\u0430\u043b\u044c\u043d\u0430\u044f-\u0411\u0438\u0442\u0438\u044f"
    ],
    "name:rus_x_variant":[
        "\u0423\u0432\u0430\u043b\u044c\u043d\u0430\u044f \u0411\u0438\u0442\u0438\u044f"
    ],
    "name:und_x_variant":[
        "Uval\u2019naya Bitiya"
    ],
    "wof:name":"Uval'naya Bitiya",
    "wof:placetype":"locality"
},
  "geometry": {"coordinates":[73.34031,55.49511],"type":"Point"}
}