{
  "type": "Feature",
  "properties": {
    "gn:admin1_code":"6",
    "gn:asciiname":"Ust'-Mekhren'ga",
    "gn:country_code":"RU",
    "gn:dem":17,
    "gn:feature_class":"P",
    "gn:feature_code":"PPL",
    "gn:name":"Ust\u2019-Mekhren\u2019ga",
    "gn:population":0,
    "gn:timezone":"Europe/Moscow",
    "iso:country":"RU",
    "name:eng_x_preferred":[
        "Ust'-Mekhren'ga"
    ],
    "name:nor_x_preferred":[
        "Ust-Mekhrenga"
    ],
    "name:rus_x_preferred":[
        "\u0423\u0441\u0442\u044c-\u041c\u0435\u0445\u0440\u0435\u043d\u044c\u0433\u0430"
    ],
    "name:und_x_variant":[
        "Ust\u2019-Mekhren\u2019ga"
    ],
    "wof:name":"Ust'-Mekhren'ga",
    "wof:placetype":"locality"
},
  "geometry": {"coordinates":[41.37167,63.25748000000001],"type":"Point"}
}