{
  "type": "Feature",
  "properties": {
    "gn:admin1_code":"51",
    "gn:asciiname":"Kodochigi",
    "gn:country_code":"RU",
    "gn:dem":151,
    "gn:feature_class":"P",
    "gn:feature_code":"PPL",
    "gn:name":"Kodochigi",
    "gn:population":0,
    "gn:timezone":"Europe/Moscow",
    "iso:country":"RU",
    "name:rus_x_preferred":[
        "\u041a\u043e\u0434\u043e\u0447\u0438\u0433\u0438"
    ],
    "name:und_x_variant":[
        "\u041a\u043e\u0434\u043e\u0447\u0438\u0433\u0438"
    ],
    "wof:name":"Kodochigi",
    "wof:placetype":"locality"
},
  "geometry": {"coordinates":[46.66651,57.3767],"type":"Point"}
}