{
  "type": "Feature",
  "properties": {
    "gn:admin1_code":"88",
    "gn:asciiname":"Bol'shiye Zalomy",
    "gn:country_code":"RU",
    "gn:dem":117,
    "gn:feature_class":"P",
    "gn:feature_code":"PPL",
    "gn:name":"Bol\u2019shiye Zalomy",
    "gn:population":0,
    "gn:timezone":"Europe/Moscow",
    "iso:country":"RU",
    "name:rus_x_preferred":[
        "\u0411\u043e\u043b\u044c\u0448\u0438\u0435 \u0417\u0430\u043b\u043e\u043c\u044b"
    ],
    "name:und_x_variant":[
        "Bol\u2019shiye Zalomy",
        "\u0411\u043e\u043b\u044c\u0448\u0438\u0435 \u0417\u0430\u043b\u043e\u043c\u044b"
    ],
    "wof:name":"Bol'shiye Zalomy",
    "wof:placetype":"locality"
},
  "geometry": {"coordinates":[38.222,58.08033],"type":"Point"}
}