{
  "type": "Feature",
  "properties": {
    "gn:admin1_code":"38.0",
    "gn:asciiname":"Fortshtadt",
    "gn:country_code":"RU",
    "gn:dem":248,
    "gn:feature_class":"P",
    "gn:feature_code":"PPL",
    "gn:name":"Fortshtadt",
    "gn:population":0,
    "gn:timezone":"Europe/Moscow",
    "iso:country":"RU",
    "name:rus_x_preferred":[
        "\u0424\u043e\u0440\u0448\u0442\u0430\u0434\u0442"
    ],
    "wof:name":"Fortshtadt",
    "wof:placetype":"locality"
},
  "geometry": {"coordinates":[41.1422,45.0319],"type":"Point"}
}