{
  "type": "Feature",
  "properties": {
    "gn:admin1_code":"88",
    "gn:asciiname":"Myakishevo",
    "gn:country_code":"RU",
    "gn:dem":128,
    "gn:feature_class":"P",
    "gn:feature_code":"PPL",
    "gn:name":"Myakishevo",
    "gn:population":0,
    "gn:timezone":"Europe/Moscow",
    "iso:country":"RU",
    "name:rus_x_preferred":[
        "\u041c\u044f\u043a\u0438\u0448\u0435\u0432\u043e"
    ],
    "wof:name":"Myakishevo",
    "wof:placetype":"locality"
},
  "geometry": {"coordinates":[37.9294,57.5799],"type":"Point"}
}