{
  "type": "Feature",
  "properties": {
    "gn:admin1_code":"55",
    "gn:asciiname":"Liman",
    "gn:country_code":"RU",
    "gn:dem":293,
    "gn:feature_class":"P",
    "gn:feature_code":"PPL",
    "gn:name":"Liman",
    "gn:population":0,
    "gn:timezone":"Asia/Yekaterinburg",
    "iso:country":"RU",
    "name:rus_x_preferred":[
        "\u041b\u0438\u043c\u0430\u043d"
    ],
    "name:und_x_variant":[
        "\u041b\u0438\u043c\u0430\u043d"
    ],
    "wof:name":"Liman",
    "wof:placetype":"locality"
},
  "geometry": {"coordinates":[58.88333000000001,51.61667],"type":"Point"}
}