{
  "type": "Feature",
  "properties": {
    "gn:admin1_code":"72",
    "gn:asciiname":"Novonikol'skoye",
    "gn:country_code":"RU",
    "gn:dem":165,
    "gn:feature_class":"P",
    "gn:feature_code":"PPL",
    "gn:name":"Novonikol\u2019skoye",
    "gn:population":0,
    "gn:timezone":"Europe/Moscow",
    "iso:country":"RU",
    "name:rus_x_preferred":[
        "Novonikol\u2019skoye"
    ],
    "name:rus_x_variant":[
        "\u041d\u043e\u0432\u043e\u043d\u0438\u043a\u043e\u043b\u044c\u0441\u043a\u043e\u0435"
    ],
    "name:und_x_variant":[
        "Vasyukovo"
    ],
    "wof:name":"Novonikol'skoye",
    "wof:placetype":"locality"
},
  "geometry": {"coordinates":[40.9644,52.4397],"type":"Point"}
}