{
  "type": "Feature",
  "properties": {
    "gn:admin1_code":"32",
    "gn:asciiname":"Nyaksimvol'",
    "gn:country_code":"RU",
    "gn:dem":44,
    "gn:feature_class":"P",
    "gn:feature_code":"PPL",
    "gn:name":"Nyaksimvol\u2019",
    "gn:population":0,
    "gn:timezone":"Asia/Yekaterinburg",
    "iso:country":"RU",
    "name:che_x_preferred":[
        "\u041d\u044f\u043a\u0441\u0438\u043c\u0432\u043e\u043b\u044c"
    ],
    "name:eng_x_preferred":[
        "Nyaksimvol'"
    ],
    "name:epo_x_preferred":[
        "Njaksimvol"
    ],
    "name:hye_x_preferred":[
        "\u0546\u0575\u0561\u056f\u057d\u056b\u0574\u057e\u0578\u056c"
    ],
    "name:nor_x_preferred":[
        "Njaksimvol"
    ],
    "name:pol_x_preferred":[
        "Niaksimwol"
    ],
    "name:rus_x_preferred":[
        "\u041d\u044f\u043a\u0441\u0438\u043c\u0432\u043e\u043b\u044c"
    ],
    "name:tat_x_preferred":[
        "\u041d\u044f\u043a\u0441\u0438\u043c\u0432\u043e\u043b\u044c"
    ],
    "name:ukr_x_preferred":[
        "\u041d\u044f\u043a\u0441\u0456\u043c\u0432\u043e\u043b\u044c"
    ],
    "name:und_x_variant":[
        "Nyaksimvol\u2019"
    ],
    "wof:name":"Nyaksimvol'",
    "wof:placetype":"locality"
},
  "geometry": {"coordinates":[60.86434000000001,62.42686],"type":"Point"}
}