{
  "type": "Feature",
  "properties": {
    "gn:admin1_code":"69",
    "gn:asciiname":"Zagustino",
    "gn:country_code":"RU",
    "gn:dem":208,
    "gn:feature_class":"P",
    "gn:feature_code":"PPL",
    "gn:name":"Zagustino",
    "gn:population":0,
    "gn:timezone":"Europe/Moscow",
    "iso:country":"RU",
    "name:eng_x_preferred":[
        "Zagustino"
    ],
    "name:nor_x_preferred":[
        "Zagustino"
    ],
    "name:rus_x_preferred":[
        "\u0417\u0430\u0433\u0443\u0441\u0442\u0438\u043d\u043e"
    ],
    "wof:name":"Zagustino",
    "wof:placetype":"locality"
},
  "geometry": {"coordinates":[32.21570999999999,53.93413],"type":"Point"}
}