{
  "type": "Feature",
  "properties": {
    "gn:admin1_code":"42",
    "gn:asciiname":"Novinka",
    "gn:country_code":"RU",
    "gn:dem":53,
    "gn:feature_class":"P",
    "gn:feature_code":"PPL",
    "gn:name":"Novinka",
    "gn:population":0,
    "gn:timezone":"Europe/Moscow",
    "iso:country":"RU",
    "name:rus_x_preferred":[
        "\u041d\u043e\u0432\u0438\u043d\u043a\u0430"
    ],
    "name:und_x_variant":[
        "\u041d\u043e\u0432\u0438\u043d\u043a\u0430"
    ],
    "wof:name":"Novinka",
    "wof:placetype":"locality"
},
  "geometry": {"coordinates":[31.25,59.46666999999999],"type":"Point"}
}