{
  "type": "Feature",
  "properties": {
    "gn:country":"RU",
    "gn:fcode":"PPL",
    "gn:population":0,
    "iso:country":"RU",
    "name:eng_x_preferred":[
        "Sosnitsy"
    ],
    "name:nor_x_preferred":[
        "Sosnitsy"
    ],
    "name:rus_x_preferred":[
        "\u0421\u043e\u0441\u043d\u0438\u0446\u044b"
    ],
    "qs:name":"Sosnitsy",
    "qs:name_adm0":"Russia",
    "qs:name_adm1":"Leningrad Oblast",
    "qs:photos_9r":0,
    "qs:photos_sr":0,
    "qs:placetype":"Town",
    "qs:pop_sr":"0",
    "wof:name":"Sosnitsy",
    "wof:placetype":"locality",
    "wof:population":0
},
  "geometry": {"coordinates":[29.54298,59.28336],"type":"Point"}
}