{
  "type": "Feature",
  "properties": {
    "gn:admin1_code":"37",
    "gn:asciiname":"Pozdnyakovo",
    "gn:country_code":"RU",
    "gn:dem":162,
    "gn:feature_class":"P",
    "gn:feature_code":"PPL",
    "gn:name":"Pozdnyakovo",
    "gn:population":0,
    "gn:timezone":"Europe/Moscow",
    "iso:country":"RU",
    "name:rus_x_preferred":[
        "\u041f\u043e\u0437\u0434\u043d\u044f\u043a\u043e\u0432\u043e"
    ],
    "name:und_x_variant":[
        "\u041f\u043e\u0437\u0434\u043d\u044f\u043a\u043e\u0432\u043e",
        "Pozdyakovo"
    ],
    "wof:name":"Pozdnyakovo",
    "wof:placetype":"locality"
},
  "geometry": {"coordinates":[46.7672,59.122],"type":"Point"}
}