{
  "type": "Feature",
  "properties": {
    "gn:admin1_code":"77",
    "gn:asciiname":"Palkino",
    "gn:country_code":"RU",
    "gn:dem":179,
    "gn:feature_class":"P",
    "gn:feature_code":"PPL",
    "gn:name":"Palkino",
    "gn:population":0,
    "gn:timezone":"Europe/Moscow",
    "iso:country":"RU",
    "name:rus_x_preferred":[
        "\u041f\u0430\u043b\u043a\u0438\u043d\u043e"
    ],
    "name:und_x_variant":[
        "\u041f\u0430\u043b\u043a\u0438\u043d\u043e"
    ],
    "wof:name":"Palkino",
    "wof:placetype":"locality"
},
  "geometry": {"coordinates":[37.0241,57.7287],"type":"Point"}
}