{
  "type": "Feature",
  "properties": {
    "gn:admin1_code":"77",
    "gn:asciiname":"Zolotilovo",
    "gn:country_code":"RU",
    "gn:dem":146,
    "gn:feature_class":"P",
    "gn:feature_code":"PPL",
    "gn:name":"Zolotilovo",
    "gn:population":0,
    "gn:timezone":"Europe/Moscow",
    "iso:country":"RU",
    "name:rus_x_preferred":[
        "\u0417\u043e\u043b\u043e\u0442\u0438\u043b\u043e\u0432\u043e"
    ],
    "name:und_x_variant":[
        "\u0417\u043e\u043b\u043e\u0442\u0438\u043b\u043e\u0432\u043e"
    ],
    "wof:name":"Zolotilovo",
    "wof:placetype":"locality"
},
  "geometry": {"coordinates":[37.5079,57.2885],"type":"Point"}
}