{
  "type": "Feature",
  "properties": {
    "gn:admin1_code":"53",
    "gn:asciiname":"Turnayevo",
    "gn:country_code":"RU",
    "gn:dem":176,
    "gn:feature_class":"P",
    "gn:feature_code":"PPL",
    "gn:name":"Turnayevo",
    "gn:population":311,
    "gn:timezone":"Asia/Novosibirsk",
    "iso:country":"RU",
    "name:eng_x_preferred":[
        "Turnayevo"
    ],
    "name:nor_x_preferred":[
        "Turnajevo"
    ],
    "name:rus_x_preferred":[
        "\u0422\u0443\u0440\u043d\u0430\u0435\u0432\u043e"
    ],
    "wof:name":"Turnayevo",
    "wof:placetype":"locality",
    "wof:population":311
},
  "geometry": {"coordinates":[84.51444000000002,55.77389],"type":"Point"}
}