{
  "type": "Feature",
  "properties": {
    "gn:admin1_code":"46",
    "gn:asciiname":"Sarga",
    "gn:country_code":"RU",
    "gn:dem":178,
    "gn:feature_class":"P",
    "gn:feature_code":"PPL",
    "gn:name":"Sarga",
    "gn:population":0,
    "gn:timezone":"Europe/Moscow",
    "iso:country":"RU",
    "name:rus_x_preferred":[
        "\u0421\u0430\u0440\u0433\u0430"
    ],
    "wof:name":"Sarga",
    "wof:placetype":"locality"
},
  "geometry": {"coordinates":[44.48765,54.37232],"type":"Point"}
}