{
  "type": "Feature",
  "properties": {
    "gn:admin1_code":"81.0",
    "gn:asciiname":"Aybashi",
    "gn:country_code":"RU",
    "gn:dem":63,
    "gn:feature_class":"P",
    "gn:feature_code":"PPL",
    "gn:name":"Aybashi",
    "gn:population":0,
    "gn:timezone":"Europe/Ulyanovsk",
    "iso:country":"RU",
    "name:nor_x_preferred":[
        "Ajbasji"
    ],
    "name:rus_x_preferred":[
        "\u0410\u0439\u0431\u0430\u0448\u0438"
    ],
    "wof:name":"Aybashi",
    "wof:placetype":"locality"
},
  "geometry": {"coordinates":[49.23333,54.71666999999999],"type":"Point"}
}