{
  "type": "Feature",
  "properties": {
    "gn:admin1_code":"61",
    "gn:asciiname":"Dvadtsat' Pyat' Let Voyenkonezavoda",
    "gn:country_code":"RU",
    "gn:dem":61,
    "gn:feature_class":"P",
    "gn:feature_code":"PPL",
    "gn:name":"Dvadtsat\u2019 Pyat\u2019 Let Voyenkonezavoda",
    "gn:population":0,
    "gn:timezone":"Europe/Moscow",
    "iso:country":"RU",
    "name:rus_x_preferred":[
        "\u0414\u0432\u0430\u0434\u0446\u0430\u0442\u044c \u041f\u044f\u0442\u044c \u041b\u0435\u0442 \u0412\u043e\u0435\u043d\u043a\u043e\u043d\u0435\u0437\u0430\u0432\u043e\u0434\u0430"
    ],
    "name:und_x_variant":[
        "Dvadtsat\u2019 Pyat\u2019 Let Voyenkonezavoda",
        "\u0414\u0432\u0430\u0434\u0446\u0430\u0442\u044c \u041f\u044f\u0442\u044c \u041b\u0435\u0442 \u0412\u043e\u0435\u043d\u043a\u043e\u043d\u0435\u0437\u0430\u0432\u043e\u0434\u0430"
    ],
    "wof:name":"Dvadtsat' Pyat' Let Voyenkonezavoda",
    "wof:placetype":"locality"
},
  "geometry": {"coordinates":[41.4824,46.6254],"type":"Point"}
}