{
  "type": "Feature",
  "properties": {
    "gn:admin1_code":"33",
    "gn:asciiname":"Loban'",
    "gn:country_code":"RU",
    "gn:dem":135,
    "gn:feature_class":"P",
    "gn:feature_code":"PPL",
    "gn:name":"Loban\u2019",
    "gn:population":0,
    "gn:timezone":"Europe/Kirov",
    "iso:country":"RU",
    "name:eng_x_preferred":[
        "Loban'"
    ],
    "name:nor_x_preferred":[
        "Loban"
    ],
    "name:rus_x_preferred":[
        "\u041b\u043e\u0431\u0430\u043d\u044c"
    ],
    "name:und_x_variant":[
        "\u041b\u043e\u0431\u0430\u043d\u044c",
        "Loban\u2019"
    ],
    "wof:name":"Loban'",
    "wof:placetype":"locality"
},
  "geometry": {"coordinates":[50.67743,57.64813],"type":"Point"}
}