{
  "type": "Feature",
  "properties": {
    "gn:admin1_code":"13",
    "gn:asciiname":"Poletayevo Pervoye",
    "gn:country_code":"RU",
    "gn:dem":230,
    "gn:feature_class":"P",
    "gn:feature_code":"PPL",
    "gn:name":"Poletayevo Pervoye",
    "gn:population":0,
    "gn:timezone":"Asia/Yekaterinburg",
    "iso:country":"RU",
    "name:rus_x_preferred":[
        "\u041f\u043e\u043b\u0435\u0442\u0430\u0435\u0432\u043e \u041f\u0435\u0440\u0432\u043e\u0435"
    ],
    "name:und_x_variant":[
        "Poletayevskiy Pervyy",
        "Poletayevo Pervoye",
        "\u041f\u043e\u043b\u0435\u0442\u0430\u0435\u0432\u043e \u041f\u0435\u0440\u0432\u043e\u0435"
    ],
    "wof:name":"Poletayevo Pervoye",
    "wof:placetype":"locality"
},
  "geometry": {"coordinates":[61.1089,55.0669],"type":"Point"}
}