{
  "type": "Feature",
  "properties": {
    "gn:admin1_code":"83.0",
    "gn:asciiname":"Ramezhki",
    "gn:country_code":"RU",
    "gn:dem":117,
    "gn:feature_class":"P",
    "gn:feature_code":"PPL",
    "gn:name":"Ramezhki",
    "gn:population":0,
    "gn:timezone":"Europe/Moscow",
    "iso:country":"RU",
    "name:rus_x_preferred":[
        "\u0420\u0430\u043c\u0435\u0436\u043a\u0438"
    ],
    "wof:name":"Ramezhki",
    "wof:placetype":"locality"
},
  "geometry": {"coordinates":[40.79523,56.06689],"type":"Point"}
}