{
  "type": "Feature",
  "properties": {
    "gn:admin1_code":"33",
    "gn:asciiname":"Staryy Burets",
    "gn:country_code":"RU",
    "gn:dem":69,
    "gn:feature_class":"P",
    "gn:feature_code":"PPL",
    "gn:name":"Staryy Burets",
    "gn:population":0,
    "gn:timezone":"Europe/Kirov",
    "iso:country":"RU",
    "name:rus_x_preferred":[
        "\u0421\u0442\u0430\u0440\u044b\u0439 \u0411\u0443\u0440\u0435\u0446"
    ],
    "wof:name":"Staryy Burets",
    "wof:placetype":"locality"
},
  "geometry": {"coordinates":[50.898,56.3855],"type":"Point"}
}