{
  "type": "Feature",
  "properties": {
    "gn:admin1_code":"10",
    "gn:asciiname":"Gudovo",
    "gn:country_code":"RU",
    "gn:dem":201,
    "gn:feature_class":"P",
    "gn:feature_code":"PPL",
    "gn:name":"Gudovo",
    "gn:population":0,
    "gn:timezone":"Europe/Moscow",
    "iso:country":"RU",
    "name:rus_x_preferred":[
        "\u0413\u0443\u0434\u043e\u0432\u043e"
    ],
    "wof:name":"Gudovo",
    "wof:placetype":"locality"
},
  "geometry": {"coordinates":[32.91932,52.79364],"type":"Point"}
}