{
  "type": "Feature",
  "properties": {
    "gn:admin1_code":"10",
    "gn:asciiname":"Never'",
    "gn:country_code":"RU",
    "gn:dem":182,
    "gn:feature_class":"P",
    "gn:feature_code":"PPL",
    "gn:name":"Never\u2019",
    "gn:population":0,
    "gn:timezone":"Europe/Moscow",
    "iso:country":"RU",
    "name:rus_x_preferred":[
        "\u041d\u0435\u0432\u0435\u0440\u044c"
    ],
    "name:und_x_variant":[
        "Never\u2019",
        "\u041d\u0435\u0432\u0435\u0440\u044c"
    ],
    "wof:name":"Never'",
    "wof:placetype":"locality"
},
  "geometry": {"coordinates":[34.39525,53.52967],"type":"Point"}
}