{
  "type": "Feature",
  "properties": {
    "gn:admin1_code":"4",
    "gn:asciiname":"Novousol'tsevo",
    "gn:country_code":"RU",
    "gn:dem":207,
    "gn:feature_class":"P",
    "gn:feature_code":"PPL",
    "gn:name":"Novousol\u2019tsevo",
    "gn:population":0,
    "gn:timezone":"Asia/Barnaul",
    "iso:country":"RU",
    "name:eng_x_preferred":[
        "Novousol'tsevo"
    ],
    "name:nor_x_preferred":[
        "Novousoltsevo"
    ],
    "name:rus_x_preferred":[
        "\u041d\u043e\u0432\u043e\u0443\u0441\u043e\u043b\u044c\u0446\u0435\u0432\u043e"
    ],
    "name:und_x_variant":[
        "\u041d\u043e\u0432\u043e\u0443\u0441\u043e\u043b\u044c\u0446\u0435\u0432\u043e",
        "Novousol\u2019tsevo"
    ],
    "wof:name":"Novousol'tsevo",
    "wof:placetype":"locality"
},
  "geometry": {"coordinates":[84.57040000000001,53.6995],"type":"Point"}
}