{
  "type": "Feature",
  "properties": {
    "gn:admin1_code":"37",
    "gn:asciiname":"Kitarikha",
    "gn:country_code":"RU",
    "gn:dem":132,
    "gn:feature_class":"P",
    "gn:feature_code":"PPL",
    "gn:name":"Kitarikha",
    "gn:population":0,
    "gn:timezone":"Europe/Moscow",
    "iso:country":"RU",
    "name:rus_x_preferred":[
        "\u041a\u0438\u0442\u0430\u0440\u0438\u0445\u0430"
    ],
    "wof:name":"Kitarikha",
    "wof:placetype":"locality"
},
  "geometry": {"coordinates":[41.00056,57.82528000000001],"type":"Point"}
}