{
  "type": "Feature",
  "properties": {
    "gn:admin1_code":"47",
    "gn:asciiname":"Gorstkino",
    "gn:country_code":"RU",
    "gn:dem":156,
    "gn:feature_class":"P",
    "gn:feature_code":"PPL",
    "gn:name":"Gorstkino",
    "gn:population":0,
    "gn:timezone":"Europe/Moscow",
    "iso:country":"RU",
    "name:nor_x_preferred":[
        "Gorstkino"
    ],
    "name:rus_x_preferred":[
        "\u0413\u043e\u0440\u0441\u0442\u043a\u0438\u043d\u043e"
    ],
    "wof:name":"Gorstkino",
    "wof:placetype":"locality"
},
  "geometry": {"coordinates":[35.63936,56.17745],"type":"Point"}
}