{
  "type": "Feature",
  "properties": {
    "gn:admin1_code":"8.0",
    "gn:asciiname":"Balykly",
    "gn:country_code":"RU",
    "gn:dem":222,
    "gn:feature_class":"P",
    "gn:feature_code":"PPL",
    "gn:name":"Balykly",
    "gn:population":0,
    "gn:timezone":"Asia/Yekaterinburg",
    "iso:country":"RU",
    "name:eng_x_preferred":[
        "Balykly"
    ],
    "name:nor_x_preferred":[
        "Balykly"
    ],
    "name:rus_x_preferred":[
        "\u0411\u0430\u043b\u044b\u043a\u043b\u044b"
    ],
    "wof:name":"Balykly",
    "wof:placetype":"locality"
},
  "geometry": {"coordinates":[55.3068,53.0959],"type":"Point"}
}