{
  "type": "Feature",
  "properties": {
    "gn:admin1_code":"93",
    "gn:asciiname":"Verkhniy Kokuy",
    "gn:country_code":"RU",
    "gn:dem":612,
    "gn:feature_class":"P",
    "gn:feature_code":"PPL",
    "gn:name":"Verkhniy Kokuy",
    "gn:population":0,
    "gn:timezone":"Asia/Chita",
    "iso:country":"RU",
    "name:und_x_variant":[
        "Verkhniye Kokui",
        "Verkhniy Kokuy"
    ],
    "wof:name":"Verkhniy Kokuy",
    "wof:placetype":"locality"
},
  "geometry": {"coordinates":[116.86215,51.65689],"type":"Point"}
}