{
  "type": "Feature",
  "properties": {
    "gn:admin1_code":"52.0",
    "gn:asciiname":"Glupaya Gorka",
    "gn:country_code":"RU",
    "gn:dem":190,
    "gn:feature_class":"P",
    "gn:feature_code":"PPL",
    "gn:name":"Glupaya Gorka",
    "gn:population":0,
    "gn:timezone":"Europe/Moscow",
    "iso:country":"RU",
    "name:rus_x_preferred":[
        "\u0413\u043b\u0443\u043f\u0430\u044f \u0413\u043e\u0440\u043a\u0430"
    ],
    "wof:name":"Glupaya Gorka",
    "wof:placetype":"locality"
},
  "geometry": {"coordinates":[32.89167,58.41001],"type":"Point"}
}