{
  "type": "Feature",
  "properties": {
    "gn:admin1_code":"21",
    "gn:asciiname":"Vareyevo",
    "gn:country_code":"RU",
    "gn:dem":113,
    "gn:feature_class":"P",
    "gn:feature_code":"PPL",
    "gn:name":"Vareyevo",
    "gn:population":0,
    "gn:timezone":"Europe/Moscow",
    "iso:country":"RU",
    "wof:name":"Vareyevo",
    "wof:placetype":"locality"
},
  "geometry": {"coordinates":[42.03672,56.88114],"type":"Point"}
}