{
  "type": "Feature",
  "properties": {
    "gn:admin1_code":"85",
    "gn:asciiname":"Kostyay",
    "gn:country_code":"RU",
    "gn:dem":118,
    "gn:feature_class":"P",
    "gn:feature_code":"PPL",
    "gn:name":"Kostyay",
    "gn:population":0,
    "gn:timezone":"Europe/Moscow",
    "iso:country":"RU",
    "name:rus_x_preferred":[
        "\u041a\u043e\u0441\u0442\u044f\u0439"
    ],
    "wof:name":"Kostyay",
    "wof:placetype":"locality"
},
  "geometry": {"coordinates":[36.0413,59.1733],"type":"Point"}
}