{
  "type": "Feature",
  "properties": {
    "gn:admin1_code":"33",
    "gn:asciiname":"Gol'tsovo",
    "gn:country_code":"RU",
    "gn:dem":117,
    "gn:feature_class":"P",
    "gn:feature_code":"PPL",
    "gn:name":"Gol\u2019tsovo",
    "gn:population":0,
    "gn:timezone":"Europe/Kirov",
    "iso:country":"RU",
    "name:rus_x_preferred":[
        "\u0413\u043e\u043b\u044c\u0446\u043e\u0432\u043e"
    ],
    "name:und_x_variant":[
        "Gol\u2019tsovo",
        "\u0413\u043e\u043b\u044c\u0446\u043e\u0432\u043e"
    ],
    "wof:name":"Gol'tsovo",
    "wof:placetype":"locality"
},
  "geometry": {"coordinates":[47.85,60.63333000000001],"type":"Point"}
}