{
  "type": "Feature",
  "properties": {
    "gn:admin1_code":"46.0",
    "gn:asciiname":"Vindrey",
    "gn:country_code":"RU",
    "gn:dem":128,
    "gn:feature_class":"P",
    "gn:feature_code":"PPL",
    "gn:name":"Vindrey",
    "gn:population":0,
    "gn:timezone":"Europe/Moscow",
    "iso:country":"RU",
    "name:che_x_preferred":[
        "\u0412\u0438\u043d\u0434\u0440\u0435\u0439"
    ],
    "name:ita_x_preferred":[
        "Vindrej"
    ],
    "name:mdf_x_preferred":[
        "\u0412\u0438\u043d\u0434\u0440\u0435\u0439"
    ],
    "name:myv_x_preferred":[
        "\u0412\u0438\u043d\u0434\u0440\u0435\u0439"
    ],
    "name:rus_x_preferred":[
        "\u0412\u0438\u043d\u0434\u0440\u0435\u0439"
    ],
    "wof:name":"Vindrey",
    "wof:placetype":"locality"
},
  "geometry": {"coordinates":[43.01237,54.25165],"type":"Point"}
}