{
  "type": "Feature",
  "properties": {
    "gn:admin1_code":"62.0",
    "gn:asciiname":"Galinka",
    "gn:country_code":"RU",
    "gn:dem":149,
    "gn:feature_class":"P",
    "gn:feature_code":"PPL",
    "gn:name":"Galinka",
    "gn:population":0,
    "gn:timezone":"Europe/Moscow",
    "iso:country":"RU",
    "name:rus_x_preferred":[
        "\u0413\u0430\u043b\u0438\u043d\u043a\u0430"
    ],
    "name:und_x_variant":[
        "\u0413\u0430\u043b\u0438\u043d\u043a\u0430"
    ],
    "wof:name":"Galinka",
    "wof:placetype":"locality"
},
  "geometry": {"coordinates":[40.9215,53.6773],"type":"Point"}
}