{
  "type": "Feature",
  "properties": {
    "gn:admin1_code":"89",
    "gn:asciiname":"Volochayevka Pervaya",
    "gn:country_code":"RU",
    "gn:dem":44,
    "gn:feature_class":"P",
    "gn:feature_code":"PPL",
    "gn:name":"Volochayevka Pervaya",
    "gn:population":0,
    "gn:timezone":"Asia/Vladivostok",
    "iso:country":"RU",
    "name:rus_x_preferred":[
        "\u0412\u043e\u043b\u043e\u0447\u0430\u0435\u0432\u043a\u0430 \u041f\u0435\u0440\u0432\u0430\u044f"
    ],
    "name:und_x_variant":[
        "Volochayevka",
        "Volochayevka Pervaya"
    ],
    "wof:name":"Volochayevka Pervaya",
    "wof:placetype":"locality"
},
  "geometry": {"coordinates":[134.48374999999999,48.56518],"type":"Point"}
}