{
  "type": "Feature",
  "properties": {
    "gn:admin1_code":"46.0",
    "gn:asciiname":"Ogarevka",
    "gn:country_code":"RU",
    "gn:dem":163,
    "gn:feature_class":"P",
    "gn:feature_code":"PPL",
    "gn:name":"Ogar\u00ebvka",
    "gn:population":0,
    "gn:timezone":"Europe/Moscow",
    "iso:country":"RU",
    "name:rus_x_preferred":[
        "\u041e\u0433\u0430\u0440\u0451\u0432\u043a\u0430"
    ],
    "name:und_x_variant":[
        "Ogar\u00ebvka"
    ],
    "wof:name":"Ogarevka",
    "wof:placetype":"locality"
},
  "geometry": {"coordinates":[45.6247,54.3877],"type":"Point"}
}