{
  "type": "Feature",
  "properties": {
    "gn:admin1_code":"63.0",
    "gn:asciiname":"Staraya Tabaga",
    "gn:country_code":"RU",
    "gn:dem":70,
    "gn:feature_class":"P",
    "gn:feature_code":"PPL",
    "gn:name":"Staraya Tabaga",
    "gn:population":692,
    "gn:timezone":"Asia/Yakutsk",
    "iso:country":"RU",
    "name:eng_x_preferred":[
        "Staraya Tabaga"
    ],
    "name:nld_x_preferred":[
        "Staraja Tabaga"
    ],
    "name:rus_x_historical":[
        "\u0422\u0430\u0431\u0430\u0433\u0430"
    ],
    "name:rus_x_preferred":[
        "\u0421\u0442\u0430\u0440\u0430\u044f \u0422\u0430\u0431\u0430\u0433\u0430"
    ],
    "name:rus_x_variant":[
        "\u0422\u0430\u0431\u0430\u0433\u0430"
    ],
    "name:sah_x_preferred":[
        "\u042d\u0440\u0433\u044d \u0422\u0430\u0431\u0430\u0495\u0430"
    ],
    "wof:name":"Staraya Tabaga",
    "wof:placetype":"locality",
    "wof:population":692
},
  "geometry": {"coordinates":[129.63387,61.82107],"type":"Point"}
}