{
  "type": "Feature",
  "properties": {
    "gn:admin1_code":"12.0",
    "gn:asciiname":"Dekhesty",
    "gn:country_code":"RU",
    "gn:dem":801,
    "gn:feature_class":"P",
    "gn:feature_code":"PPL",
    "gn:name":"Dekhesty",
    "gn:population":0,
    "gn:timezone":"Europe/Moscow",
    "iso:country":"RU",
    "name:che_x_preferred":[
        "Dixa-Isti"
    ],
    "name:che_x_variant":[
        "\u0414\u0438\u0445\u0430-\u0418\u0441\u0442\u0438"
    ],
    "name:rus_x_preferred":[
        "\u0414\u0435\u0445\u0435\u0441\u0442\u044b"
    ],
    "name:und_x_variant":[
        "Dikha-Isti",
        "Dekhesty",
        "Dehesty"
    ],
    "wof:name":"Dekhesty",
    "wof:placetype":"locality"
},
  "geometry": {"coordinates":[45.73256,42.8371],"type":"Point"}
}