{
  "type": "Feature",
  "properties": {
    "gn:admin1_code":"20",
    "gn:asciiname":"Zagvozdina",
    "gn:cc2":"RU",
    "gn:country_code":"RU",
    "gn:dem":587,
    "gn:feature_class":"P",
    "gn:feature_code":"PPL",
    "gn:name":"Zagvozdina",
    "gn:population":0,
    "gn:timezone":"Asia/Irkutsk",
    "iso:country":"RU",
    "name:und_x_variant":[
        "Zimnik Zagvozdina",
        "Zagvozdina"
    ],
    "wof:name":"Zagvozdina",
    "wof:placetype":"locality"
},
  "geometry": {"coordinates":[103.15000000000001,53.25],"type":"Point"}
}