{
  "type": "Feature",
  "properties": {
    "gn:admin1_code":"34",
    "gn:asciiname":"Ivan-Yel'",
    "gn:country_code":"RU",
    "gn:dem":108,
    "gn:feature_class":"P",
    "gn:feature_code":"PPL",
    "gn:name":"Ivan-Y\u00ebl\u2019",
    "gn:population":0,
    "gn:timezone":"Europe/Moscow",
    "iso:country":"RU",
    "name:rus_x_preferred":[
        "\u0418\u0432\u0430\u043d-\u0401\u043b\u044c"
    ],
    "name:und_x_variant":[
        "Ivan-Y\u00ebl\u2019",
        "\u0418\u0432\u0430\u043d-\u0401\u043b\u044c"
    ],
    "wof:name":"Ivan-Yel'",
    "wof:placetype":"locality"
},
  "geometry": {"coordinates":[54.38116,63.35521],"type":"Point"}
}