{
  "type": "Feature",
  "properties": {
    "gn:admin1_code":"77",
    "gn:asciiname":"Rostan'",
    "gn:country_code":"RU",
    "gn:dem":162,
    "gn:feature_class":"P",
    "gn:feature_code":"PPL",
    "gn:name":"Rostan\u2019",
    "gn:population":0,
    "gn:timezone":"Europe/Moscow",
    "iso:country":"RU",
    "name:rus_x_preferred":[
        "\u0420\u043e\u0441\u0442\u0430\u043d\u044c"
    ],
    "name:und_x_variant":[
        "Rostan\u2019",
        "\u0420\u043e\u0441\u0442\u0430\u043d\u044c"
    ],
    "wof:name":"Rostan'",
    "wof:placetype":"locality"
},
  "geometry": {"coordinates":[34.42408,58.03895],"type":"Point"}
}