{
  "type": "Feature",
  "properties": {
    "gn:admin1_code":"91",
    "gn:asciiname":"Yelan'",
    "gn:country_code":"RU",
    "gn:dem":188,
    "gn:feature_class":"P",
    "gn:feature_code":"PPL",
    "gn:name":"Yelan\u2019",
    "gn:population":0,
    "gn:timezone":"Asia/Krasnoyarsk",
    "iso:country":"RU",
    "name:und_x_variant":[
        "Ulus Yelanskiy",
        "Yelanskiy",
        "Yelan\u2019"
    ],
    "wof:name":"Yelan'",
    "wof:placetype":"locality"
},
  "geometry": {"coordinates":[90.45,57.01667],"type":"Point"}
}