{
  "type": "Feature",
  "properties": {
    "gn:admin1_code":"43",
    "gn:asciiname":"Tyutchevo",
    "gn:country_code":"RU",
    "gn:dem":134,
    "gn:feature_class":"P",
    "gn:feature_code":"PPL",
    "gn:name":"Tyutchevo",
    "gn:population":0,
    "gn:timezone":"Europe/Moscow",
    "iso:country":"RU",
    "name:rus_x_preferred":[
        "\u0422\u044e\u0442\u0447\u0435\u0432\u043e"
    ],
    "name:und_x_variant":[
        "\u0422\u044e\u0442\u0447\u0435\u0432\u043e"
    ],
    "wof:name":"Tyutchevo",
    "wof:placetype":"locality"
},
  "geometry": {"coordinates":[39.03851,52.92446],"type":"Point"}
}