{
  "type": "Feature",
  "properties": {
    "gn:admin1_code":"8",
    "gn:asciiname":"Sayranovo",
    "gn:country_code":"RU",
    "gn:dem":221,
    "gn:feature_class":"P",
    "gn:feature_code":"PPL",
    "gn:name":"Sayranovo",
    "gn:population":0,
    "gn:timezone":"Asia/Yekaterinburg",
    "iso:country":"RU",
    "name:eng_x_preferred":[
        "Sayranovo"
    ],
    "name:nor_x_preferred":[
        "Sajranovo"
    ],
    "name:rus_x_preferred":[
        "\u0421\u0430\u0439\u0440\u0430\u043d\u043e\u0432\u043e"
    ],
    "wof:name":"Sayranovo",
    "wof:placetype":"locality"
},
  "geometry": {"coordinates":[56.39346999999999,53.44661],"type":"Point"}
}