{
  "type": "Feature",
  "properties": {
    "gn:admin1_code":"57",
    "gn:asciiname":"Rayevka",
    "gn:country_code":"RU",
    "gn:dem":179,
    "gn:feature_class":"P",
    "gn:feature_code":"PPL",
    "gn:name":"Ray\u00ebvka",
    "gn:population":0,
    "gn:timezone":"Europe/Moscow",
    "iso:country":"RU",
    "name:rus_x_preferred":[
        "\u0420\u0430\u0451\u0432\u043a\u0430"
    ],
    "name:und_x_variant":[
        "Ray\u00ebvka"
    ],
    "wof:name":"Rayevka",
    "wof:placetype":"locality"
},
  "geometry": {"coordinates":[44.5426,52.8569],"type":"Point"}
}