{
  "type": "Feature",
  "properties": {
    "gn:country":"RU",
    "gn:fcode":"PPL",
    "gn:population":484,
    "iso:country":"RU",
    "name:azb_x_preferred":[
        "\u06cc\u0644\u06cc\u0645\u0627\u062e"
    ],
    "name:ceb_x_preferred":[
        "Yllymakh"
    ],
    "name:che_x_preferred":[
        "\u042b\u043b\u043b\u044b\u043c\u0430\u0445"
    ],
    "name:eng_x_preferred":[
        "Yllymakh"
    ],
    "name:hye_x_preferred":[
        "\u053b\u056c\u056b\u0574\u0561\u056d"
    ],
    "name:nld_x_preferred":[
        "Yllymach"
    ],
    "name:nno_x_preferred":[
        "Yllymakh"
    ],
    "name:nob_x_preferred":[
        "Yllymakh"
    ],
    "name:nor_x_preferred":[
        "Yllymakh"
    ],
    "name:rus_x_preferred":[
        "\u042b\u043b\u043b\u044b\u043c\u0430\u0445"
    ],
    "name:sqi_x_preferred":[
        "Yllymah"
    ],
    "name:ukr_x_preferred":[
        "\u0418\u043b\u043b\u0438\u043c\u0430\u0445"
    ],
    "qs:name":"Yllymakh",
    "qs:photos_9r":0,
    "qs:photos_sr":0,
    "qs:pop_sr":"2",
    "wd:wordcount":440,
    "wof:name":"Yllymakh",
    "wof:placetype":"locality",
    "wof:population":484
},
  "geometry": {"coordinates":[126.68877000000001,58.58028],"type":"Point"}
}