{
  "type": "Feature",
  "properties": {
    "gn:admin1_code":"21.0",
    "gn:asciiname":"Gnezdilovo",
    "gn:country_code":"RU",
    "gn:dem":122,
    "gn:feature_class":"P",
    "gn:feature_code":"PPL",
    "gn:name":"Gnezdilovo",
    "gn:population":0,
    "gn:timezone":"Europe/Moscow",
    "iso:country":"RU",
    "name:rus_x_preferred":[
        "\u0413\u043d\u0435\u0437\u0434\u0438\u043b\u043e\u0432\u043e"
    ],
    "name:und_x_variant":[
        "\u0413\u043d\u0435\u0437\u0434\u0438\u043b\u043e\u0432\u043e"
    ],
    "wof:name":"Gnezdilovo",
    "wof:placetype":"locality"
},
  "geometry": {"coordinates":[41.20556,56.73994],"type":"Point"}
}