{
  "type": "Feature",
  "properties": {
    "gn:admin1_code":"72",
    "gn:asciiname":"Krutoye",
    "gn:country_code":"RU",
    "gn:dem":138,
    "gn:feature_class":"P",
    "gn:feature_code":"PPL",
    "gn:name":"Krutoye",
    "gn:population":0,
    "gn:timezone":"Europe/Moscow",
    "iso:country":"RU",
    "name:rus_x_preferred":[
        "\u041a\u0440\u0443\u0442\u043e\u0435"
    ],
    "name:und_x_variant":[
        "\u041a\u0440\u0443\u0442\u043e\u0435"
    ],
    "wof:name":"Krutoye",
    "wof:placetype":"locality"
},
  "geometry": {"coordinates":[41.48594,53.60928000000001],"type":"Point"}
}