{
  "type": "Feature",
  "properties": {
    "gn:country":"RU",
    "gn:fcode":"PPL",
    "gn:pop":3780,
    "iso:country":"RU",
    "name:eng_x_preferred":[
        "Primorka"
    ],
    "name:nor_x_preferred":[
        "Primorka"
    ],
    "name:rus_x_preferred":[
        "\u041f\u0440\u0438\u043c\u043e\u0440\u043a\u0430"
    ],
    "name:unk_x_variant":[
        "Kosa Kuryacha"
    ],
    "qs:name":"Primorka",
    "qs:name_adm0":"Russia",
    "qs:name_adm1":"Rostov Oblast",
    "qs:photos_9k":1,
    "qs:photos_9r":4,
    "qs:photos_all":189,
    "qs:photos_sr":0,
    "qs:placetype":"Town",
    "qs:pop_sr":"4",
    "wof:name":"Primorka",
    "wof:placetype":"locality",
    "wof:population":3780
},
  "geometry": {"coordinates":[39.06408,47.28395],"type":"Point"}
}