{
  "type": "Feature",
  "properties": {
    "gn:admin1_code":"81",
    "gn:asciiname":"Shalkino",
    "gn:country_code":"RU",
    "gn:dem":205,
    "gn:feature_class":"P",
    "gn:feature_code":"PPL",
    "gn:name":"Shalkino",
    "gn:population":0,
    "gn:timezone":"Europe/Ulyanovsk",
    "iso:country":"RU",
    "name:eng_x_preferred":[
        "Shalkino"
    ],
    "name:nor_x_preferred":[
        "Sjalkino"
    ],
    "name:rus_x_preferred":[
        "\u0428\u0430\u043b\u043a\u0438\u043d\u043e"
    ],
    "name:und_x_variant":[
        "Shalkino Vtoroye",
        "Shalkino"
    ],
    "wof:name":"Shalkino",
    "wof:placetype":"locality"
},
  "geometry": {"coordinates":[47.05646,52.62574],"type":"Point"}
}