{
  "type": "Feature",
  "properties": {
    "gn:admin1_code":"65.0",
    "gn:asciiname":"Chuvashskiye Lipyagi",
    "gn:country_code":"RU",
    "gn:dem":44,
    "gn:feature_class":"P",
    "gn:feature_code":"PPL",
    "gn:name":"Chuvashskiye Lipyagi",
    "gn:population":0,
    "gn:timezone":"Europe/Samara",
    "iso:country":"RU",
    "name:rus_x_preferred":[
        "\u0427\u0443\u0432\u0430\u0448\u0441\u043a\u0438\u0435 \u041b\u0438\u043f\u044f\u0433\u0438"
    ],
    "name:und_x_variant":[
        "Lipyagi Chuvashskiye",
        "Chuvashskiye Lipyagi",
        "\u0427\u0443\u0432\u0430\u0448\u0441\u043a\u0438\u0435 \u041b\u0438\u043f\u044f\u0433\u0438"
    ],
    "wof:name":"Chuvashskiye Lipyagi",
    "wof:placetype":"locality"
},
  "geometry": {"coordinates":[49.8891,53.1161],"type":"Point"}
}