{
  "type": "Feature",
  "properties": {
    "gn:admin1_code":"37",
    "gn:asciiname":"Petrikovo",
    "gn:country_code":"RU",
    "gn:dem":126,
    "gn:feature_class":"P",
    "gn:feature_code":"PPL",
    "gn:name":"Petrikovo",
    "gn:population":0,
    "gn:timezone":"Europe/Moscow",
    "iso:country":"RU",
    "name:und_x_variant":[
        "Petrikova",
        "Petrikovo"
    ],
    "wof:name":"Petrikovo",
    "wof:placetype":"locality"
},
  "geometry": {"coordinates":[41.85144,58.98353],"type":"Point"}
}