{
  "type": "Feature",
  "properties": {
    "gn:admin1_code":"84",
    "gn:asciiname":"Krasnyanskiy",
    "gn:country_code":"RU",
    "gn:dem":88,
    "gn:feature_class":"P",
    "gn:feature_code":"PPL",
    "gn:name":"Krasnyanskiy",
    "gn:population":0,
    "gn:timezone":"Europe/Volgograd",
    "iso:country":"RU",
    "name:eng_x_preferred":[
        "Krasnyanskiy"
    ],
    "name:nor_x_preferred":[
        "Krasnjanskij"
    ],
    "name:rus_x_preferred":[
        "\u041a\u0440\u0430\u0441\u043d\u044f\u043d\u0441\u043a\u0438\u0439"
    ],
    "name:und_x_variant":[
        "\u041a\u0440\u0430\u0441\u043d\u044f\u043d\u0441\u043a\u0438\u0439",
        "Krasnyanskiy"
    ],
    "wof:name":"Krasnyanskiy",
    "wof:placetype":"locality"
},
  "geometry": {"coordinates":[42.0601,50.9647],"type":"Point"}
}