{
  "type": "Feature",
  "properties": {
    "gn:admin1_code":"88",
    "gn:asciiname":"Lomki",
    "gn:country_code":"RU",
    "gn:dem":114,
    "gn:feature_class":"P",
    "gn:feature_code":"PPL",
    "gn:name":"Lomki",
    "gn:population":0,
    "gn:timezone":"Europe/Moscow",
    "iso:country":"RU",
    "name:rus_x_preferred":[
        "\u041b\u043e\u043c\u043a\u0438"
    ],
    "name:und_x_variant":[
        "\u041b\u043e\u043c\u043a\u0438"
    ],
    "wof:name":"Lomki",
    "wof:placetype":"locality"
},
  "geometry": {"coordinates":[38.5368,57.8388],"type":"Point"}
}