{
  "type": "Feature",
  "properties": {
    "gn:admin1_code":"54",
    "gn:asciiname":"Platonovka",
    "gn:country_code":"RU",
    "gn:dem":105,
    "gn:feature_class":"P",
    "gn:feature_code":"PPL",
    "gn:name":"Platonovka",
    "gn:population":0,
    "gn:timezone":"Asia/Omsk",
    "iso:country":"RU",
    "name:eng_x_preferred":[
        "Platonovka"
    ],
    "name:nor_x_preferred":[
        "Platonovka"
    ],
    "name:rus_x_preferred":[
        "\u041f\u043b\u0430\u0442\u043e\u043d\u043e\u0432\u043a\u0430"
    ],
    "name:und_x_variant":[
        "\u041f\u043b\u0430\u0442\u043e\u043d\u043e\u0432\u043a\u0430",
        "Platonovka"
    ],
    "wof:name":"Platonovka",
    "wof:placetype":"locality"
},
  "geometry": {"coordinates":[74.67444,53.88],"type":"Point"}
}