{
  "type": "Feature",
  "properties": {
    "gn:admin1_code":"1",
    "gn:asciiname":"Kochkin",
    "gn:country_code":"RU",
    "gn:dem":57,
    "gn:feature_class":"P",
    "gn:feature_code":"PPL",
    "gn:name":"Kochkin",
    "gn:population":0,
    "gn:timezone":"Europe/Moscow",
    "iso:country":"RU",
    "name:rus_x_preferred":[
        "\u041a\u043e\u0447\u043a\u0438\u043d"
    ],
    "name:und_x_variant":[
        "\u041a\u043e\u0447\u043a\u0438\u043d"
    ],
    "wof:name":"Kochkin",
    "wof:placetype":"locality"
},
  "geometry": {"coordinates":[39.37463,44.83328],"type":"Point"}
}