{
  "type": "Feature",
  "properties": {
    "gn:admin1_code":"8",
    "gn:asciiname":"Zhilino",
    "gn:country_code":"RU",
    "gn:dem":92,
    "gn:feature_class":"P",
    "gn:feature_code":"PPL",
    "gn:name":"Zhilino",
    "gn:population":0,
    "gn:timezone":"Asia/Yekaterinburg",
    "iso:country":"RU",
    "name:rus_x_preferred":[
        "\u0416\u0438\u043b\u0438\u043d\u043e"
    ],
    "name:und_x_variant":[
        "\u0416\u0438\u043b\u0438\u043d\u043e",
        "Zhilina"
    ],
    "wof:name":"Zhilino",
    "wof:placetype":"locality"
},
  "geometry": {"coordinates":[56.06564,54.65781],"type":"Point"}
}