{
  "type": "Feature",
  "properties": {
    "gn:admin1_code":"38.0",
    "gn:asciiname":"Kosyakin",
    "gn:country_code":"RU",
    "gn:dem":108,
    "gn:feature_class":"P",
    "gn:feature_code":"PPL",
    "gn:name":"Kosyakin",
    "gn:population":0,
    "gn:timezone":"Europe/Moscow",
    "iso:country":"RU",
    "name:rus_x_preferred":[
        "\u041a\u043e\u0441\u044f\u043a\u0438\u043d"
    ],
    "wof:name":"Kosyakin",
    "wof:placetype":"locality"
},
  "geometry": {"coordinates":[40.54889,45.23611],"type":"Point"}
}