{
  "type": "Feature",
  "properties": {
    "gn:country":"RU",
    "gn:fcode":"PPL",
    "gn:population":5314,
    "iso:country":"RU",
    "name:ara_x_preferred":[
        "\u062f\u062c\u0648\u0628\u063a\u0627"
    ],
    "name:azb_x_preferred":[
        "\u062f\u0698\u0648\u0628\u0642\u0627"
    ],
    "name:bel_x_preferred":[
        "\u0414\u0436\u0443\u0431\u0433\u0430"
    ],
    "name:bul_x_preferred":[
        "\u0414\u0436\u0443\u0431\u0433\u0430"
    ],
    "name:cat_x_preferred":[
        "Djubga"
    ],
    "name:ceb_x_preferred":[
        "Dzhubga"
    ],
    "name:che_x_preferred":[
        "\u0414\u0436\u0443\u0431\u0433\u0430"
    ],
    "name:crh_x_preferred":[
        "Cubga"
    ],
    "name:eng_x_preferred":[
        "Dzhubga"
    ],
    "name:hye_x_preferred":[
        "\u054b\u0578\u0582\u0562\u0563\u0561"
    ],
    "name:ita_x_preferred":[
        "D\u017eubga"
    ],
    "name:jpn_x_preferred":[
        "\u30b8\u30e5\u30fc\u30d6\u30ac"
    ],
    "name:lit_x_preferred":[
        "D\u017eiugbra"
    ],
    "name:nld_x_preferred":[
        "Dzhubga"
    ],
    "name:nor_x_preferred":[
        "Dzjubga"
    ],
    "name:oss_x_preferred":[
        "\u0414\u0436\u0443\u0431\u0433\u00e6"
    ],
    "name:pol_x_preferred":[
        "D\u017cubga"
    ],
    "name:rus_x_preferred":[
        "\u0414\u0436\u0443\u0431\u0433\u0430"
    ],
    "name:spa_x_preferred":[
        "Dzhubga"
    ],
    "name:srp_x_preferred":[
        "\u040f\u0443\u0431\u0433\u0430"
    ],
    "name:ukr_x_preferred":[
        "\u0414\u0436\u0443\u0431\u0433\u0430"
    ],
    "name:und_x_variant":[
        "Dshubga"
    ],
    "name:zho_x_preferred":[
        "\u6731\u5e03\u52a0"
    ],
    "qs:name":"Dzhubga",
    "qs:name_adm0":"Russia",
    "qs:name_adm1":"Krasnodar Krai",
    "qs:photos_9k":1,
    "qs:photos_9r":1,
    "qs:photos_all":6,
    "qs:photos_sr":0,
    "qs:placetype":"Town",
    "qs:pop_sr":"5",
    "wd:wordcount":172,
    "wof:name":"Dzhubga",
    "wof:placetype":"locality",
    "wof:population":5314
},
  "geometry": {"coordinates":[38.7073,44.3211],"type":"Point"}
}