{
  "type": "Feature",
  "properties": {
    "gn:admin1_code":"47",
    "gn:asciiname":"Vorob'yevo",
    "gn:country_code":"RU",
    "gn:dem":154,
    "gn:feature_class":"P",
    "gn:feature_code":"PPL",
    "gn:name":"Vorob\u2019y\u00ebvo",
    "gn:population":0,
    "gn:timezone":"Europe/Moscow",
    "iso:country":"RU",
    "name:und_x_variant":[
        "Meshcherskoye",
        "Vorob\u2019y\u00ebvo"
    ],
    "wof:name":"Vorob'yevo",
    "wof:placetype":"locality"
},
  "geometry": {"coordinates":[35.74282,56.1841],"type":"Point"}
}