{
  "type": "Feature",
  "properties": {
    "gn:admin1_code":"38.0",
    "gn:asciiname":"Alekseyevka",
    "gn:country_code":"RU",
    "gn:dem":196,
    "gn:feature_class":"P",
    "gn:feature_code":"PPL",
    "gn:name":"Alekseyevka",
    "gn:population":0,
    "gn:timezone":"Europe/Moscow",
    "iso:country":"RU",
    "name:rus_x_preferred":[
        "(( \u0410\u043b\u0435\u043a\u0441\u0435\u0435\u0432\u043a\u0430 ))"
    ],
    "wof:name":"Alekseyevka",
    "wof:placetype":"locality"
},
  "geometry": {"coordinates":[39.23,44.19],"type":"Point"}
}