{
  "type": "Feature",
  "properties": {
    "gn:admin1_code":"38",
    "gn:asciiname":"Pokrovskiy",
    "gn:country_code":"RU",
    "gn:dem":443,
    "gn:feature_class":"P",
    "gn:feature_code":"PPL",
    "gn:name":"Pokrovskiy",
    "gn:population":0,
    "gn:timezone":"Europe/Moscow",
    "iso:country":"RU",
    "wof:name":"Pokrovskiy",
    "wof:placetype":"locality"
},
  "geometry": {"coordinates":[41.53306,44.40528],"type":"Point"}
}