{
  "type": "Feature",
  "properties": {
    "gn:admin1_code":"77",
    "gn:asciiname":"Ludilovo",
    "gn:country_code":"RU",
    "gn:dem":69,
    "gn:feature_class":"P",
    "gn:feature_code":"PPL",
    "gn:name":"Ludilovo",
    "gn:population":0,
    "gn:timezone":"Europe/Moscow",
    "iso:country":"RU",
    "name:rus_x_preferred":[
        "\u041b\u0443\u0434\u0438\u043b\u043e\u0432\u043e"
    ],
    "name:und_x_variant":[
        "\u041b\u0443\u0434\u0438\u043b\u043e\u0432\u043e"
    ],
    "wof:name":"Ludilovo",
    "wof:placetype":"locality"
},
  "geometry": {"coordinates":[30.9791,56.8967],"type":"Point"}
}