{
  "type": "Feature",
  "properties": {
    "gn:admin1_code":"77",
    "gn:asciiname":"Urevy",
    "gn:country_code":"RU",
    "gn:dem":207,
    "gn:feature_class":"P",
    "gn:feature_code":"PPL",
    "gn:name":"Urevy",
    "gn:population":0,
    "gn:timezone":"Europe/Moscow",
    "iso:country":"RU",
    "wof:name":"Urevy",
    "wof:placetype":"locality"
},
  "geometry": {"coordinates":[33.31462,56.98806],"type":"Point"}
}