{
  "type": "Feature",
  "properties": {
    "gn:country":"RU",
    "gn:fcode":"PPL",
    "gn:pop":5880,
    "iso:country":"RU",
    "name:eng_x_preferred":[
        "Divnomorskoye"
    ],
    "name:nor_x_preferred":[
        "Divnomorskoje"
    ],
    "name:rus_x_preferred":[
        "\u0414\u0438\u0432\u043d\u043e\u043c\u043e\u0440\u0441\u043a\u043e\u0435"
    ],
    "name:unk_x_variant":[
        "Fal\u2019shivyy Gelendzhik"
    ],
    "qs:name":"Divnomorskoye",
    "qs:name_adm0":"Russia",
    "qs:name_adm1":"Krasnodar Krai",
    "qs:photos":124,
    "qs:photos_1k":25,
    "qs:photos_9k":1,
    "qs:photos_9r":3,
    "qs:photos_all":124,
    "qs:photos_sr":3,
    "qs:placetype":"Town",
    "qs:pop_sr":"5",
    "wof:name":"Divnomorskoye",
    "wof:placetype":"locality",
    "wof:population":5880
},
  "geometry": {"coordinates":[38.1342,44.5017],"type":"Point"}
}