{
  "type": "Feature",
  "properties": {
    "gn:admin1_code":"91",
    "gn:asciiname":"Konovshchina",
    "gn:cc2":"RU",
    "gn:country_code":"RU",
    "gn:dem":96,
    "gn:feature_class":"P",
    "gn:feature_code":"PPL",
    "gn:name":"Konovshchina",
    "gn:population":0,
    "gn:timezone":"Asia/Krasnoyarsk",
    "iso:country":"RU",
    "name:rus_x_preferred":[
        "\u041a\u043e\u043d\u043e\u0432\u0449\u0438\u043d\u0430"
    ],
    "name:und_x_variant":[
        "Kopnovskaya",
        "Konovshchina"
    ],
    "wof:name":"Konovshchina",
    "wof:placetype":"locality"
},
  "geometry": {"coordinates":[92.99972,58.06],"type":"Point"}
}