{
  "type": "Feature",
  "properties": {
    "gn:admin1_code":"77",
    "gn:asciiname":"Svirka",
    "gn:country_code":"RU",
    "gn:dem":162,
    "gn:feature_class":"P",
    "gn:feature_code":"PPL",
    "gn:name":"Svirka",
    "gn:population":0,
    "gn:timezone":"Europe/Moscow",
    "iso:country":"RU",
    "name:che_x_preferred":[
        "\u0421\u0432\u0438\u0440\u043a\u0430"
    ],
    "name:rus_x_preferred":[
        "\u0421\u0432\u0438\u0440\u043a\u0430"
    ],
    "wof:name":"Svirka",
    "wof:placetype":"locality"
},
  "geometry": {"coordinates":[34.58393,58.02038],"type":"Point"}
}