{
  "type": "Feature",
  "properties": {
    "gn:admin1_code":"42",
    "gn:asciiname":"Rabochiy Poselok Nomer Tretiy",
    "gn:cc2":"RU",
    "gn:country_code":"RU",
    "gn:dem":63,
    "gn:feature_class":"P",
    "gn:feature_code":"PPL",
    "gn:name":"Rabochiy Pos\u00eblok Nomer Tretiy",
    "gn:population":0,
    "gn:timezone":"Europe/Moscow",
    "iso:country":"RU",
    "name:rus_x_preferred":[
        "\u0420\u0430\u0431\u043e\u0447\u0438\u0439 \u041f\u043e\u0441\u0451\u043b\u043e\u043a \u041d\u043e\u043c\u0435\u0440 \u0422\u0440\u0435\u0442\u0438\u0439"
    ],
    "name:und_x_variant":[
        "Rabochiy Pos\u00eblok",
        "Rabochiy Pos\u00eblok Nomer Tretiy",
        "\u0420\u0430\u0431\u043e\u0447\u0438\u0439 \u041f\u043e\u0441\u0451\u043b\u043e\u043a \u041d\u043e\u043c\u0435\u0440 \u0422\u0440\u0435\u0442\u0438\u0439"
    ],
    "wof:name":"Rabochiy Poselok Nomer Tretiy",
    "wof:placetype":"locality"
},
  "geometry": {"coordinates":[31.66667,59.76667],"type":"Point"}
}