{
  "type": "Feature",
  "properties": {
    "gn:admin1_code":"77",
    "gn:asciiname":"Korovkino",
    "gn:country_code":"RU",
    "gn:dem":230,
    "gn:feature_class":"P",
    "gn:feature_code":"PPL",
    "gn:name":"Korovkino",
    "gn:population":0,
    "gn:timezone":"Europe/Moscow",
    "iso:country":"RU",
    "name:rus_x_preferred":[
        "\u041a\u043e\u0440\u043e\u0432\u043a\u0438\u043d\u043e"
    ],
    "wof:name":"Korovkino",
    "wof:placetype":"locality"
},
  "geometry": {"coordinates":[34.21513,56.73084],"type":"Point"}
}