{
  "type": "Feature",
  "properties": {
    "gn:admin1_code":"90",
    "gn:asciiname":"Zapoleno",
    "gn:country_code":"RU",
    "gn:dem":175,
    "gn:feature_class":"P",
    "gn:feature_code":"PPL",
    "gn:name":"Zapoleno",
    "gn:population":0,
    "gn:timezone":"Asia/Yekaterinburg",
    "iso:country":"RU",
    "name:rus_x_preferred":[
        "\u0417\u0430\u043f\u043e\u043b\u0435\u043d\u043e"
    ],
    "wof:name":"Zapoleno",
    "wof:placetype":"locality"
},
  "geometry": {"coordinates":[57.32899999999999,57.3527],"type":"Point"}
}