{
  "type": "Feature",
  "properties": {
    "gn:admin1_code":"85",
    "gn:asciiname":"Bol'shaya Shormanga",
    "gn:country_code":"RU",
    "gn:dem":190,
    "gn:feature_class":"P",
    "gn:feature_code":"PPL",
    "gn:name":"Bol\u2019shaya Shormanga",
    "gn:population":0,
    "gn:timezone":"Europe/Moscow",
    "iso:country":"RU",
    "name:rus_x_preferred":[
        "\u0411\u043e\u043b\u044c\u0448\u0430\u044f \u0428\u043e\u0440\u043c\u0430\u043d\u0433\u0430"
    ],
    "name:und_x_variant":[
        "Bol\u2019shaya Shormanga"
    ],
    "wof:name":"Bol'shaya Shormanga",
    "wof:placetype":"locality"
},
  "geometry": {"coordinates":[38.50196,59.00021],"type":"Point"}
}