{
  "type": "Feature",
  "properties": {
    "gn:admin1_code":"21.0",
    "gn:asciiname":"Seredkino",
    "gn:country_code":"RU",
    "gn:dem":108,
    "gn:feature_class":"P",
    "gn:feature_code":"PPL",
    "gn:name":"Ser\u00ebdkino",
    "gn:population":0,
    "gn:timezone":"Europe/Moscow",
    "iso:country":"RU",
    "name:rus_x_preferred":[
        "\u0421\u0435\u0440\u0451\u0434\u043a\u0438\u043d\u043e"
    ],
    "name:und_x_variant":[
        "Ser\u00ebdkino",
        "\u0421\u0435\u0440\u0451\u0434\u043a\u0438\u043d\u043e"
    ],
    "wof:name":"Seredkino",
    "wof:placetype":"locality"
},
  "geometry": {"coordinates":[42.76509,57.35116],"type":"Point"}
}