{
  "type": "Feature",
  "properties": {
    "gn:admin1_code":"45.0",
    "gn:asciiname":"Poselok Gai",
    "gn:country_code":"RU",
    "gn:dem":117,
    "gn:feature_class":"P",
    "gn:feature_code":"PPL",
    "gn:name":"Pos\u00eblok Gai",
    "gn:population":0,
    "gn:timezone":"Europe/Moscow",
    "iso:country":"RU",
    "name:rus_x_preferred":[
        "\u041f\u043e\u0441\u0451\u043b\u043e\u043a \u0413\u0430\u0438"
    ],
    "name:und_x_variant":[
        "Pos\u00eblok Gai",
        "\u041f\u043e\u0441\u0451\u043b\u043e\u043a \u0413\u0430\u0438"
    ],
    "wof:name":"Poselok Gai",
    "wof:placetype":"locality"
},
  "geometry": {"coordinates":[48.04361,56.4925],"type":"Point"}
}