{
  "type": "Feature",
  "properties": {
    "gn:admin1_code":"28",
    "gn:asciiname":"Chkalovskiy",
    "gn:country_code":"RU",
    "gn:dem":18,
    "gn:feature_class":"P",
    "gn:feature_code":"PPL",
    "gn:name":"Chkalovskiy",
    "gn:population":0,
    "gn:timezone":"Europe/Moscow",
    "iso:country":"RU",
    "name:eng_x_preferred":[
        "Chkalovskiy"
    ],
    "name:fin_x_preferred":[
        "Savinansaha"
    ],
    "name:nor_x_preferred":[
        "Tsjkalovskij"
    ],
    "name:rus_x_preferred":[
        "\u0427\u043a\u0430\u043b\u043e\u0432\u0441\u043a\u0438\u0439"
    ],
    "name:und_x_variant":[
        "Samoylovichi",
        "Pos\u00eblok Rudnika Imeni Chkalova",
        "Imeni Chkalova",
        "Samoilovitsi",
        "Chkalovskiy",
        "\u0427\u043a\u0430\u043b\u043e\u0432\u0441\u043a\u0438\u0439"
    ],
    "wof:name":"Chkalovskiy",
    "wof:placetype":"locality"
},
  "geometry": {"coordinates":[33.39741,66.29829000000001],"type":"Point"}
}