{
  "type": "Feature",
  "properties": {
    "gn:admin1_code":"60",
    "gn:asciiname":"Podvor'ye",
    "gn:country_code":"RU",
    "gn:dem":162,
    "gn:feature_class":"P",
    "gn:feature_code":"PPL",
    "gn:name":"Podvor\u2019ye",
    "gn:population":0,
    "gn:timezone":"Europe/Moscow",
    "iso:country":"RU",
    "name:rus_x_preferred":[
        "\u041f\u043e\u0434\u0432\u043e\u0440\u044c\u0435"
    ],
    "name:und_x_variant":[
        "Podvor\u2019ye"
    ],
    "wof:name":"Podvor'ye",
    "wof:placetype":"locality"
},
  "geometry": {"coordinates":[30.95,56.05],"type":"Point"}
}