{
  "type": "Feature",
  "properties": {
    "gn:admin1_code":"17",
    "gn:asciiname":"Naskent",
    "gn:country_code":"RU",
    "gn:dem":1348,
    "gn:feature_class":"P",
    "gn:feature_code":"PPL",
    "gn:name":"Naskent",
    "gn:population":0,
    "gn:timezone":"Europe/Moscow",
    "iso:country":"RU",
    "name:rus_x_preferred":[
        "\u041d\u0430\u0441\u043a\u0435\u043d\u0442"
    ],
    "wof:name":"Naskent",
    "wof:placetype":"locality"
},
  "geometry": {"coordinates":[47.33624,42.38093],"type":"Point"}
}