{
  "type": "Feature",
  "properties": {
    "gn:admin1_code":"8",
    "gn:asciiname":"Shafeyevka",
    "gn:country_code":"RU",
    "gn:dem":280,
    "gn:feature_class":"P",
    "gn:feature_code":"PPL",
    "gn:name":"Shafeyevka",
    "gn:population":0,
    "gn:timezone":"Asia/Yekaterinburg",
    "iso:country":"RU",
    "name:rus_x_preferred":[
        "\u0428\u0430\u0444\u0435\u0435\u0432\u043a\u0430"
    ],
    "wof:name":"Shafeyevka",
    "wof:placetype":"locality"
},
  "geometry": {"coordinates":[54.2347,53.9821],"type":"Point"}
}