{
  "type": "Feature",
  "properties": {
    "gn:admin1_code":"77",
    "gn:asciiname":"Testovo",
    "gn:country_code":"RU",
    "gn:dem":142,
    "gn:feature_class":"P",
    "gn:feature_code":"PPL",
    "gn:name":"Testovo",
    "gn:population":0,
    "gn:timezone":"Europe/Moscow",
    "iso:country":"RU",
    "name:rus_x_preferred":[
        "\u0422\u0435\u0441\u0442\u043e\u0432\u043e"
    ],
    "wof:name":"Testovo",
    "wof:placetype":"locality"
},
  "geometry": {"coordinates":[36.6736,58.0348],"type":"Point"}
}