{
  "type": "Feature",
  "properties": {
    "gn:admin1_code":"77",
    "gn:asciiname":"Terpigorevo",
    "gn:country_code":"RU",
    "gn:dem":159,
    "gn:feature_class":"P",
    "gn:feature_code":"PPL",
    "gn:name":"Terpigorevo",
    "gn:population":0,
    "gn:timezone":"Europe/Moscow",
    "iso:country":"RU",
    "name:und_x_variant":[
        "Terpigor\u2019ye",
        "Terpigorevo"
    ],
    "wof:name":"Terpigorevo",
    "wof:placetype":"locality"
},
  "geometry": {"coordinates":[34.47473,57.68661],"type":"Point"}
}