{
  "type": "Feature",
  "properties": {
    "gn:admin1_code":"77",
    "gn:asciiname":"Karmanikha",
    "gn:country_code":"RU",
    "gn:dem":236,
    "gn:feature_class":"P",
    "gn:feature_code":"PPL",
    "gn:name":"Karmanikha",
    "gn:population":0,
    "gn:timezone":"Europe/Moscow",
    "iso:country":"RU",
    "name:rus_x_preferred":[
        "\u041a\u0430\u0440\u043c\u0430\u043d\u0438\u0445\u0430"
    ],
    "name:und_x_variant":[
        "\u041a\u0430\u0440\u043c\u0430\u043d\u0438\u0445\u0430"
    ],
    "wof:name":"Karmanikha",
    "wof:placetype":"locality"
},
  "geometry": {"coordinates":[33.99694,56.81165],"type":"Point"}
}