{
  "type": "Feature",
  "properties": {
    "gn:admin1_code":"73.0",
    "gn:asciiname":"Un'ba",
    "gn:country_code":"RU",
    "gn:dem":85,
    "gn:feature_class":"P",
    "gn:feature_code":"PPL",
    "gn:name":"Un\u2019ba",
    "gn:population":0,
    "gn:timezone":"Europe/Moscow",
    "iso:country":"RU",
    "name:rus_x_preferred":[
        "\u0423\u043d\u044c\u0431\u0430"
    ],
    "name:und_x_variant":[
        "Un\u2019ba"
    ],
    "wof:name":"Un'ba",
    "wof:placetype":"locality"
},
  "geometry": {"coordinates":[49.487,56.0834],"type":"Point"}
}