{
  "type": "Feature",
  "properties": {
    "gn:admin1_code":"63",
    "gn:admin2_code":"Verkhoyansky District (undefined)",
    "gn:asciiname":"Myngay",
    "gn:country_code":"RU",
    "gn:dem":138,
    "gn:feature_class":"P",
    "gn:feature_code":"PPL",
    "gn:name":"Myngay",
    "gn:population":0,
    "gn:timezone":"Asia/Vladivostok",
    "iso:country":"RU",
    "name:eng_x_preferred":[
        "Myngay"
    ],
    "name:nor_x_preferred":[
        "Myngaj"
    ],
    "name:rus_x_preferred":[
        "\u041c\u044b\u043d\u0433\u0430\u0439"
    ],
    "name:und_x_variant":[
        "\u041c\u044b\u043d\u0433\u0430\u0439",
        "Myngay"
    ],
    "wof:name":"Myngay",
    "wof:placetype":"locality"
},
  "geometry": {"coordinates":[134.2876,67.61936999999999],"type":"Point"}
}