{
  "type": "Feature",
  "properties": {
    "gn:country":"RU",
    "gn:fcode":"PPL",
    "gn:pop":0,
    "iso:country":"RU",
    "name:eng_x_preferred":[
        "Maloye Polpino"
    ],
    "name:nor_x_preferred":[
        "Maloje Polpino"
    ],
    "name:rus_x_preferred":[
        "\u041c\u0430\u043b\u043e\u0435 \u041f\u043e\u043b\u043f\u0438\u043d\u043e"
    ],
    "name:unk_x_variant":[
        "\u041c\u0430\u043b\u043e\u0435 \u041f\u043e\u043b\u043f\u0438\u043d\u043e"
    ],
    "qs:name":"Maloye Polpino",
    "qs:name_adm0":"Russia",
    "qs:name_adm1":"Bryansk Oblast",
    "qs:photos_9k":1,
    "qs:photos_9r":1,
    "qs:photos_all":4,
    "qs:photos_sr":0,
    "qs:placetype":"Town",
    "qs:pop_sr":"0",
    "wof:name":"Maloye Polpino",
    "wof:placetype":"locality",
    "wof:population":0
},
  "geometry": {"coordinates":[34.62262,53.27633],"type":"Point"}
}