{
  "type": "Feature",
  "properties": {
    "gn:admin1_code":"53",
    "gn:asciiname":"Apolikha",
    "gn:country_code":"RU",
    "gn:dem":108,
    "gn:feature_class":"P",
    "gn:feature_code":"PPL",
    "gn:name":"Apolikha",
    "gn:population":0,
    "gn:timezone":"Asia/Novosibirsk",
    "iso:country":"RU",
    "name:eng_x_preferred":[
        "Apolikha"
    ],
    "name:nor_x_preferred":[
        "Apolikha"
    ],
    "name:rus_x_preferred":[
        "\u0410\u043f\u043e\u043b\u0438\u0445\u0430"
    ],
    "name:und_x_variant":[
        "Opalikha",
        "Arolikha",
        "Apolikha"
    ],
    "wof:name":"Apolikha",
    "wof:placetype":"locality"
},
  "geometry": {"coordinates":[77.18031999999999,54.07014],"type":"Point"}
}