{
  "type": "Feature",
  "properties": {
    "gn:admin1_code":"05",
    "gn:asciiname":"Nizhniye Chembuki",
    "gn:country_code":"RU",
    "gn:dem":245,
    "gn:feature_class":"P",
    "gn:feature_code":"PPL",
    "gn:name":"Nizhniye Chembuki",
    "gn:population":0,
    "gn:timezone":"Asia/Yakutsk",
    "iso:country":"RU",
    "name:rus_x_preferred":[
        "\u041d\u0438\u0436\u043d\u0438\u0435 \u0427\u0435\u043c\u0431\u0443\u043a\u0438"
    ],
    "wof:name":"Nizhniye Chembuki",
    "wof:placetype":"locality"
},
  "geometry": {"coordinates":[127.93333,52.35],"type":"Point"}
}