{
  "type": "Feature",
  "properties": {
    "gn:admin1_code":"85",
    "gn:asciiname":"Shchepinskaya",
    "gn:country_code":"RU",
    "gn:dem":174,
    "gn:feature_class":"P",
    "gn:feature_code":"PPL",
    "gn:name":"Shchepinskaya",
    "gn:population":0,
    "gn:timezone":"Europe/Moscow",
    "iso:country":"RU",
    "name:rus_x_preferred":[
        "\u0429\u0435\u043f\u0438\u043d\u0441\u043a\u0430\u044f"
    ],
    "wof:name":"Shchepinskaya",
    "wof:placetype":"locality"
},
  "geometry": {"coordinates":[40.21548,60.60134],"type":"Point"}
}