{
  "type": "Feature",
  "properties": {
    "gn:admin1_code":"55",
    "gn:asciiname":"Karabator",
    "gn:country_code":"RU",
    "gn:dem":122,
    "gn:feature_class":"P",
    "gn:feature_code":"PPL",
    "gn:name":"Karabator",
    "gn:population":0,
    "gn:timezone":"Asia/Yekaterinburg",
    "iso:country":"RU",
    "name:rus_x_preferred":[
        "\u041a\u0430\u0440\u0430\u0431\u0430\u0442\u043e\u0440"
    ],
    "name:und_x_variant":[
        "\u041a\u0430\u0440\u0430\u0431\u0430\u0442\u043e\u0440"
    ],
    "wof:name":"Karabator",
    "wof:placetype":"locality"
},
  "geometry": {"coordinates":[55.93333000000001,51.95],"type":"Point"}
}