{
  "type": "Feature",
  "properties": {
    "gn:admin1_code":"77",
    "gn:asciiname":"Zarodovichi",
    "gn:country_code":"RU",
    "gn:dem":161,
    "gn:feature_class":"P",
    "gn:feature_code":"PPL",
    "gn:name":"Zarodovichi",
    "gn:population":0,
    "gn:timezone":"Europe/Moscow",
    "iso:country":"RU",
    "name:rus_x_preferred":[
        "\u0417\u0430\u0440\u043e\u0434\u043e\u0432\u0438\u0447\u0438"
    ],
    "wof:name":"Zarodovichi",
    "wof:placetype":"locality"
},
  "geometry": {"coordinates":[35.83462,58.00973000000001],"type":"Point"}
}