{
  "type": "Feature",
  "properties": {
    "gn:admin1_code":"56",
    "gn:asciiname":"Pervoye Uderevo",
    "gn:country_code":"RU",
    "gn:dem":149,
    "gn:feature_class":"P",
    "gn:feature_code":"PPL",
    "gn:name":"Pervoye Uder\u00ebvo",
    "gn:population":0,
    "gn:timezone":"Europe/Moscow",
    "iso:country":"RU",
    "name:rus_x_preferred":[
        "\u041f\u0435\u0440\u0432\u043e\u0435 \u0423\u0434\u0435\u0440\u0451\u0432\u043e"
    ],
    "name:und_x_variant":[
        "Pervoye Uder\u00ebvo",
        "\u041f\u0435\u0440\u0432\u043e\u0435 \u0423\u0434\u0435\u0440\u0451\u0432\u043e"
    ],
    "wof:name":"Pervoye Uderevo",
    "wof:placetype":"locality"
},
  "geometry": {"coordinates":[37.14962,52.23188],"type":"Point"}
}