{
  "type": "Feature",
  "properties": {
    "gn:admin1_code":"51",
    "gn:asciiname":"Parfenovo",
    "gn:country_code":"RU",
    "gn:dem":103,
    "gn:feature_class":"P",
    "gn:feature_code":"PPL",
    "gn:name":"Parfenovo",
    "gn:population":0,
    "gn:timezone":"Europe/Volgograd",
    "iso:country":"RU",
    "name:rus_x_preferred":[
        "\u041f\u0430\u0440\u0444\u0451\u043d\u043e\u0432\u043e"
    ],
    "wof:name":"Parfenovo",
    "wof:placetype":"locality"
},
  "geometry": {"coordinates":[47.55958,57.76671999999999],"type":"Point"}
}