{
  "type": "Feature",
  "properties": {
    "gn:country":"RU",
    "gn:fcode":"PPL",
    "gn:population":2877,
    "iso:country":"RU",
    "name:eng_x_preferred":[
        "Novyye Gorki"
    ],
    "name:rus_x_preferred":[
        "\u041d\u043e\u0432.\u0413\u043e\u0440\u043a\u0438"
    ],
    "name:rus_x_variant":[
        "\u041d\u043e\u0432\u044b\u0435 \u0413\u043e\u0440\u043a\u0438"
    ],
    "qs:name":"Novyye Gorki",
    "qs:name_adm0":"Russia",
    "qs:name_adm1":"Ivanovo Oblast",
    "qs:photos_9r":0,
    "qs:photos_sr":0,
    "qs:placetype":"Town",
    "qs:pop_sr":"4",
    "wof:name":"Novyye Gorki",
    "wof:placetype":"locality",
    "wof:population":2877
},
  "geometry": {"coordinates":[41.06014,56.72535],"type":"Point"}
}