{
  "type": "Feature",
  "properties": {
    "gn:admin1_code":"46",
    "gn:asciiname":"Novonikol'skoye",
    "gn:country_code":"RU",
    "gn:dem":147,
    "gn:feature_class":"P",
    "gn:feature_code":"PPL",
    "gn:name":"Novonikol\u2019skoye",
    "gn:population":0,
    "gn:timezone":"Europe/Moscow",
    "iso:country":"RU",
    "name:eng_x_preferred":[
        "Novo-Nikol'skoye"
    ],
    "name:nor_x_preferred":[
        "Novonikolskoje"
    ],
    "name:rus_x_preferred":[
        "\u041d\u043e\u0432\u043e\u043d\u0438\u043a\u043e\u043b\u044c\u0441\u043a\u043e\u0435"
    ],
    "name:und_x_variant":[
        "Novoye Nikol\u2019skoye",
        "Novonikol\u2019skoye"
    ],
    "wof:name":"Novonikol'skoye",
    "wof:placetype":"locality"
},
  "geometry": {"coordinates":[44.03604,54.67913000000001],"type":"Point"}
}