{
  "type": "Feature",
  "properties": {
    "gn:admin1_code":"56",
    "gn:asciiname":"Malaya Fominka",
    "gn:country_code":"RU",
    "gn:dem":164,
    "gn:feature_class":"P",
    "gn:feature_code":"PPL",
    "gn:name":"Malaya Fominka",
    "gn:population":0,
    "gn:timezone":"Europe/Moscow",
    "iso:country":"RU",
    "name:rus_x_preferred":[
        "\u041c\u0430\u043b\u0430\u044f \u0424\u043e\u043c\u0438\u043d\u043a\u0430"
    ],
    "wof:name":"Malaya Fominka",
    "wof:placetype":"locality"
},
  "geometry": {"coordinates":[35.99556,52.86156999999999],"type":"Point"}
}