{
  "type": "Feature",
  "properties": {
    "gn:admin1_code":"63",
    "gn:asciiname":"Tyugene",
    "gn:country_code":"RU",
    "gn:dem":270,
    "gn:feature_class":"P",
    "gn:feature_code":"PPL",
    "gn:name":"Tyugene",
    "gn:population":0,
    "gn:timezone":"Asia/Yakutsk",
    "iso:country":"RU",
    "name:eng_x_preferred":[
        "Tyugene"
    ],
    "name:rus_x_preferred":[
        "\u0410\u0431\u0430\u0440\u0430\u043d\u0433\u0434\u0430"
    ],
    "name:rus_x_variant":[
        "\u0422\u044e\u0433\u0435\u043d\u0435"
    ],
    "name:und_x_variant":[
        "Abarangda",
        "Tyugene"
    ],
    "wof:name":"Tyugene",
    "wof:placetype":"locality"
},
  "geometry": {"coordinates":[125.91656,62.41802],"type":"Point"}
}