{
  "type": "Feature",
  "properties": {
    "gn:admin1_code":"42.0",
    "gn:asciiname":"Frolovskoye",
    "gn:country_code":"RU",
    "gn:dem":57,
    "gn:feature_class":"P",
    "gn:feature_code":"PPL",
    "gn:name":"Frolovskoye",
    "gn:population":0,
    "gn:timezone":"Europe/Moscow",
    "iso:country":"RU",
    "name:rus_x_preferred":[
        "\u0424\u0440\u043e\u043b\u043e\u0432\u0441\u043a\u043e\u0435"
    ],
    "wof:name":"Frolovskoye",
    "wof:placetype":"locality"
},
  "geometry": {"coordinates":[30.73333,58.93333000000001],"type":"Point"}
}