{
  "type": "Feature",
  "properties": {
    "gn:admin1_code":"85",
    "gn:asciiname":"Mysovskaya",
    "gn:country_code":"RU",
    "gn:dem":179,
    "gn:feature_class":"P",
    "gn:feature_code":"PPL",
    "gn:name":"Mysovskaya",
    "gn:population":0,
    "gn:timezone":"Europe/Moscow",
    "iso:country":"RU",
    "name:rus_x_preferred":[
        "\u041c\u044b\u0441\u043e\u0432\u0441\u043a\u0430\u044f"
    ],
    "wof:name":"Mysovskaya",
    "wof:placetype":"locality"
},
  "geometry": {"coordinates":[41.6402,60.51894],"type":"Point"}
}