{
  "type": "Feature",
  "properties": {
    "gn:admin1_code":"60",
    "gn:asciiname":"Kustari",
    "gn:country_code":"RU",
    "gn:dem":67,
    "gn:feature_class":"P",
    "gn:feature_code":"PPL",
    "gn:name":"Kustari",
    "gn:population":0,
    "gn:timezone":"Europe/Moscow",
    "iso:country":"RU",
    "name:rus_x_preferred":[
        "\u041a\u0443\u0441\u0442\u0430\u0440\u0438"
    ],
    "name:und_x_variant":[
        "Kustara",
        "Kustari"
    ],
    "wof:name":"Kustari",
    "wof:placetype":"locality"
},
  "geometry": {"coordinates":[28.47323,57.16161999999999],"type":"Point"}
}