{
  "type": "Feature",
  "properties": {
    "gn:admin1_code":"65",
    "gn:asciiname":"Kirillovka",
    "gn:country_code":"RU",
    "gn:dem":124,
    "gn:feature_class":"P",
    "gn:feature_code":"PPL",
    "gn:name":"Kirillovka",
    "gn:population":0,
    "gn:timezone":"Europe/Samara",
    "iso:country":"RU",
    "name:eng_x_preferred":[
        "Kirillovka"
    ],
    "name:nor_x_preferred":[
        "Kirillovka"
    ],
    "name:rus_x_preferred":[
        "\u041a\u0438\u0440\u0438\u043b\u043b\u043e\u0432\u043a\u0430"
    ],
    "name:und_x_variant":[
        "\u041a\u0438\u0440\u0438\u043b\u043b\u043e\u0432\u043a\u0430",
        "Kirillovka"
    ],
    "wof:name":"Kirillovka",
    "wof:placetype":"locality"
},
  "geometry": {"coordinates":[49.80611,53.85722],"type":"Point"}
}