{
  "type": "Feature",
  "properties": {
    "gn:admin1_code":"51",
    "gn:asciiname":"Baranikha",
    "gn:country_code":"RU",
    "gn:dem":117,
    "gn:feature_class":"P",
    "gn:feature_code":"PPL",
    "gn:name":"Baranikha",
    "gn:population":0,
    "gn:timezone":"Europe/Moscow",
    "iso:country":"RU",
    "name:rus_x_preferred":[
        "\u0411\u0430\u0440\u0430\u043d\u0438\u0445\u0430"
    ],
    "name:und_x_variant":[
        "\u0411\u0430\u0440\u0430\u043d\u0438\u0445\u0430"
    ],
    "wof:name":"Baranikha",
    "wof:placetype":"locality"
},
  "geometry": {"coordinates":[45.2447,57.7118],"type":"Point"}
}