{
  "type": "Feature",
  "properties": {
    "gn:admin1_code":"78",
    "gn:asciiname":"Balandina",
    "gn:country_code":"RU",
    "gn:dem":90,
    "gn:feature_class":"P",
    "gn:feature_code":"PPL",
    "gn:name":"Balandina",
    "gn:population":0,
    "gn:timezone":"Asia/Yekaterinburg",
    "iso:country":"RU",
    "name:eng_x_preferred":[
        "Balandina"
    ],
    "name:nor_x_preferred":[
        "Balandina"
    ],
    "name:rus_x_preferred":[
        "\u0411\u0430\u043b\u0430\u043d\u0434\u0438\u043d\u0430"
    ],
    "name:und_x_variant":[
        "Balandino",
        "\u0411\u0430\u043b\u0430\u043d\u0434\u0438\u043d\u0430",
        "Balandina"
    ],
    "wof:name":"Balandina",
    "wof:placetype":"locality"
},
  "geometry": {"coordinates":[69.34196,55.48686],"type":"Point"}
}