{
  "type": "Feature",
  "properties": {
    "gn:admin1_code":"23",
    "gn:asciiname":"Zhigulevo",
    "gn:country_code":"RU",
    "gn:dem":132,
    "gn:feature_class":"P",
    "gn:feature_code":"PPL",
    "gn:name":"Zhigul\u00ebvo",
    "gn:population":0,
    "gn:timezone":"Europe/Kaliningrad",
    "iso:country":"RU",
    "wof:name":"Zhigulevo",
    "wof:placetype":"locality"
},
  "geometry": {"coordinates":[21.80226,54.36155],"type":"Point"}
}