{
  "type": "Feature",
  "properties": {
    "gn:admin1_code":"69",
    "gn:asciiname":"Sherovichi",
    "gn:country_code":"RU",
    "gn:dem":213,
    "gn:feature_class":"P",
    "gn:feature_code":"PPL",
    "gn:name":"Sherovichi",
    "gn:population":0,
    "gn:timezone":"Europe/Moscow",
    "iso:country":"RU",
    "name:eng_x_preferred":[
        "Sherovichi"
    ],
    "name:nor_x_preferred":[
        "Sjerovitsji"
    ],
    "name:rus_x_preferred":[
        "\u0428\u0435\u0440\u043e\u0432\u0438\u0447\u0438"
    ],
    "name:und_x_variant":[
        "Shirevichi",
        "\u0428\u0435\u0440\u043e\u0432\u0438\u0447\u0438",
        "Sherovichi"
    ],
    "wof:name":"Sherovichi",
    "wof:placetype":"locality"
},
  "geometry": {"coordinates":[31.14258,54.93563],"type":"Point"}
}