{
  "type": "Feature",
  "properties": {
    "gn:admin1_code":"71",
    "gn:asciiname":"Novoye Shishkino",
    "gn:country_code":"RU",
    "gn:dem":68,
    "gn:feature_class":"P",
    "gn:feature_code":"PPL",
    "gn:name":"Novoye Shishkino",
    "gn:population":0,
    "gn:timezone":"Asia/Yekaterinburg",
    "iso:country":"RU",
    "name:rus_x_preferred":[
        "\u041d\u043e\u0432\u043e\u0435 \u0428\u0438\u0448\u043a\u0438\u043d\u043e"
    ],
    "name:und_x_variant":[
        "Novaya Shishkina",
        "Novoshishkina",
        "Novoye Shishkino"
    ],
    "wof:name":"Novoye Shishkino",
    "wof:placetype":"locality"
},
  "geometry": {"coordinates":[63.16029,58.16287],"type":"Point"}
}