{
  "type": "Feature",
  "properties": {
    "gn:admin1_code":"37",
    "gn:asciiname":"Chertanovo",
    "gn:country_code":"RU",
    "gn:dem":186,
    "gn:feature_class":"P",
    "gn:feature_code":"PPL",
    "gn:name":"Chertanovo",
    "gn:population":0,
    "gn:timezone":"Europe/Moscow",
    "iso:country":"RU",
    "name:rus_x_preferred":[
        "\u0427\u0435\u0440\u0442\u0430\u043d\u043e\u0432\u043e"
    ],
    "name:und_x_variant":[
        "\u0427\u0435\u0440\u0442\u0430\u043d\u043e\u0432\u043e"
    ],
    "wof:name":"Chertanovo",
    "wof:placetype":"locality"
},
  "geometry": {"coordinates":[42.6332,58.3158],"type":"Point"}
}