{
  "type": "Feature",
  "properties": {
    "gn:admin1_code":"56",
    "gn:asciiname":"Obydenki",
    "gn:country_code":"RU",
    "gn:dem":212,
    "gn:feature_class":"P",
    "gn:feature_code":"PPL",
    "gn:name":"Obydenki",
    "gn:population":0,
    "gn:timezone":"Europe/Moscow",
    "iso:country":"RU",
    "name:rus_x_preferred":[
        "\u041e\u0431\u044b\u0434\u0435\u043d\u043a\u0438"
    ],
    "name:und_x_variant":[
        "Obydenki-Buzova"
    ],
    "wof:name":"Obydenki",
    "wof:placetype":"locality"
},
  "geometry": {"coordinates":[35.8844,52.3743],"type":"Point"}
}