{
  "type": "Feature",
  "properties": {
    "gn:admin1_code":"91",
    "gn:asciiname":"Koy",
    "gn:country_code":"RU",
    "gn:dem":476,
    "gn:feature_class":"P",
    "gn:feature_code":"PPL",
    "gn:name":"Koy",
    "gn:population":0,
    "gn:timezone":"Asia/Krasnoyarsk",
    "iso:country":"RU",
    "name:eng_x_preferred":[
        "Koy"
    ],
    "name:nor_x_preferred":[
        "Koj"
    ],
    "name:rus_x_preferred":[
        "\u041a\u043e\u0439"
    ],
    "wof:name":"Koy",
    "wof:placetype":"locality"
},
  "geometry": {"coordinates":[94.0641,55.0954],"type":"Point"}
}