{
  "type": "Feature",
  "properties": {
    "gn:admin1_code":"85",
    "gn:asciiname":"Simanikha",
    "gn:country_code":"RU",
    "gn:dem":152,
    "gn:feature_class":"P",
    "gn:feature_code":"PPL",
    "gn:name":"Simanikha",
    "gn:population":0,
    "gn:timezone":"Europe/Moscow",
    "iso:country":"RU",
    "name:rus_x_preferred":[
        "\u0421\u0438\u043c\u0430\u043d\u0438\u0445\u0430"
    ],
    "name:und_x_variant":[
        "\u0421\u0438\u043c\u0430\u043d\u0438\u0445\u0430"
    ],
    "wof:name":"Simanikha",
    "wof:placetype":"locality"
},
  "geometry": {"coordinates":[35.55,58.91667],"type":"Point"}
}