{
  "type": "Feature",
  "properties": {
    "gn:admin1_code":"77",
    "gn:asciiname":"Ovintsevo",
    "gn:country_code":"RU",
    "gn:dem":294,
    "gn:feature_class":"P",
    "gn:feature_code":"PPL",
    "gn:name":"Ovintsevo",
    "gn:population":0,
    "gn:timezone":"Europe/Moscow",
    "iso:country":"RU",
    "name:eng_x_preferred":[
        "Ovintsevo"
    ],
    "name:nor_x_preferred":[
        "Ovintsevo"
    ],
    "name:rus_x_preferred":[
        "\u041e\u0432\u0438\u043d\u0446\u0435\u0432\u043e"
    ],
    "name:und_x_variant":[
        "\u041e\u0432\u0438\u043d\u0446\u0435\u0432\u043e",
        "Ovintsevo"
    ],
    "wof:name":"Ovintsevo",
    "wof:placetype":"locality"
},
  "geometry": {"coordinates":[33.97626,57.238],"type":"Point"}
}