{
  "type": "Feature",
  "properties": {
    "gn:admin1_code":"33.0",
    "gn:asciiname":"Georgiyevo",
    "gn:country_code":"RU",
    "gn:dem":270,
    "gn:feature_class":"P",
    "gn:feature_code":"PPL",
    "gn:name":"Georgiyevo",
    "gn:population":0,
    "gn:timezone":"Europe/Kirov",
    "iso:country":"RU",
    "name:eng_x_preferred":[
        "Georgiyevo"
    ],
    "name:nor_x_preferred":[
        "Georgijevo"
    ],
    "name:rus_x_preferred":[
        "\u0413\u0435\u043e\u0440\u0433\u0438\u0435\u0432\u043e"
    ],
    "name:und_x_variant":[
        "Georgiyevskoye",
        "\u0413\u0435\u043e\u0440\u0433\u0438\u0435\u0432\u043e",
        "Georgiyevo"
    ],
    "wof:name":"Georgiyevo",
    "wof:placetype":"locality"
},
  "geometry": {"coordinates":[53.17909,59.14443000000001],"type":"Point"}
}