{
  "type": "Feature",
  "properties": {
    "gn:admin1_code":"83",
    "gn:asciiname":"Kamenovo",
    "gn:country_code":"RU",
    "gn:dem":111,
    "gn:feature_class":"P",
    "gn:feature_code":"PPL",
    "gn:name":"Kamenovo",
    "gn:population":0,
    "gn:timezone":"Europe/Moscow",
    "iso:country":"RU",
    "name:ceb_x_preferred":[
        "Kamenovo"
    ],
    "name:eng_x_preferred":[
        "Kamenevo"
    ],
    "name:fra_x_preferred":[
        "Kamenovo"
    ],
    "name:msa_x_preferred":[
        "Kamenovo"
    ],
    "name:nor_x_preferred":[
        "Kamenovo"
    ],
    "name:por_x_preferred":[
        "Kamenovo"
    ],
    "name:rus_x_preferred":[
        "\u041a\u0430\u043c\u0435\u043d\u043e\u0432\u043e"
    ],
    "name:rus_x_variant":[
        "\u041a\u0430\u043c\u0435\u043do\u0432\u043e"
    ],
    "name:slv_x_preferred":[
        "Kamenovo"
    ],
    "name:srp_x_preferred":[
        "\u041a\u0430\u043c\u0435\u043d\u043e\u0432\u043e"
    ],
    "name:und_x_variant":[
        "Kamenevo",
        "Kamenovo"
    ],
    "wof:name":"Kamenovo",
    "wof:placetype":"locality"
},
  "geometry": {"coordinates":[40.97587,56.39798],"type":"Point"}
}