{
  "type": "Feature",
  "properties": {
    "gn:admin1_code":"84",
    "gn:asciiname":"Karagichevskiy",
    "gn:country_code":"RU",
    "gn:dem":138,
    "gn:feature_class":"P",
    "gn:feature_code":"PPL",
    "gn:name":"Karagichevskiy",
    "gn:population":0,
    "gn:timezone":"Europe/Volgograd",
    "iso:country":"RU",
    "name:eng_x_preferred":[
        "Karagichev"
    ],
    "name:nor_x_preferred":[
        "Karagitsjevskij"
    ],
    "name:rus_x_preferred":[
        "\u041a\u0430\u0440\u0430\u0433\u0438\u0447\u0435\u0432\u0441\u043a\u0438\u0439"
    ],
    "name:und_x_variant":[
        "Karaichev",
        "Karachev",
        "Karagichev",
        "Karagichevskiy"
    ],
    "wof:name":"Karagichevskiy",
    "wof:placetype":"locality"
},
  "geometry": {"coordinates":[42.8991,50.1604],"type":"Point"}
}