{
  "type": "Feature",
  "properties": {
    "gn:admin1_code":"69",
    "gn:asciiname":"Novaya Borovka",
    "gn:country_code":"RU",
    "gn:dem":186,
    "gn:feature_class":"P",
    "gn:feature_code":"PPL",
    "gn:name":"Novaya Borovka",
    "gn:population":0,
    "gn:timezone":"Europe/Moscow",
    "iso:country":"RU",
    "name:rus_x_preferred":[
        "\u041d\u043e\u0432\u0430\u044f \u0411\u043e\u0440\u043e\u0432\u043a\u0430"
    ],
    "wof:name":"Novaya Borovka",
    "wof:placetype":"locality"
},
  "geometry": {"coordinates":[32.8306,54.84558000000001],"type":"Point"}
}