{
  "type": "Feature",
  "properties": {
    "gn:admin1_code":"91",
    "gn:asciiname":"Seledkovo",
    "gn:cc2":"RU",
    "gn:country_code":"RU",
    "gn:dem":255,
    "gn:feature_class":"P",
    "gn:feature_code":"PPL",
    "gn:name":"Seledkovo",
    "gn:population":0,
    "gn:timezone":"Asia/Krasnoyarsk",
    "iso:country":"RU",
    "name:eng_x_preferred":[
        "Seledkovo"
    ],
    "name:nor_x_preferred":[
        "Seledkovo"
    ],
    "name:rus_x_preferred":[
        "\u0421\u0435\u043b\u0435\u0434\u043a\u043e\u0432\u043e"
    ],
    "name:und_x_variant":[
        "Selednovskaya",
        "Seledkovo"
    ],
    "wof:name":"Seledkovo",
    "wof:placetype":"locality"
},
  "geometry": {"coordinates":[91.03667,55.89389],"type":"Point"}
}