{
  "type": "Feature",
  "properties": {
    "gn:admin1_code":"52",
    "gn:asciiname":"Borikhino",
    "gn:country_code":"RU",
    "gn:dem":139,
    "gn:feature_class":"P",
    "gn:feature_code":"PPL",
    "gn:name":"Borikhino",
    "gn:population":0,
    "gn:timezone":"Europe/Moscow",
    "iso:country":"RU",
    "name:rus_x_preferred":[
        "\u0411\u043e\u0440\u0438\u0445\u0438\u043d\u043e"
    ],
    "name:und_x_variant":[
        "\u0411\u043e\u0440\u0438\u0445\u0438\u043d\u043e"
    ],
    "wof:name":"Borikhino",
    "wof:placetype":"locality"
},
  "geometry": {"coordinates":[35.81927,58.48589000000001],"type":"Point"}
}