{
  "type": "Feature",
  "properties": {
    "gn:admin1_code":"28",
    "gn:asciiname":"Lukhtala",
    "gn:cc2":"RU",
    "gn:country_code":"RU",
    "gn:dem":148,
    "gn:feature_class":"P",
    "gn:feature_code":"PPL",
    "gn:name":"Lukhtala",
    "gn:population":0,
    "gn:timezone":"Europe/Moscow",
    "iso:country":"RU",
    "name:fin_x_preferred":[
        "Luhtala"
    ],
    "name:rus_x_preferred":[
        "\u041b\u0443\u0445\u0442\u0430\u043b\u0430"
    ],
    "name:und_x_variant":[
        "\u041b\u0443\u0445\u0442\u0430\u043b\u0430"
    ],
    "wof:name":"Lukhtala",
    "wof:placetype":"locality"
},
  "geometry": {"coordinates":[32.56667,62.25],"type":"Point"}
}