{
  "type": "Feature",
  "properties": {
    "gn:admin1_code":"17.0",
    "gn:asciiname":"Una",
    "gn:country_code":"RU",
    "gn:dem":2091,
    "gn:feature_class":"P",
    "gn:feature_code":"PPL",
    "gn:name":"Una",
    "gn:population":0,
    "gn:timezone":"Europe/Moscow",
    "iso:country":"RU",
    "name:bel_x_preferred":[
        "\u0423\u043d\u0430"
    ],
    "name:ceb_x_preferred":[
        "Una"
    ],
    "name:deu_x_preferred":[
        "Una"
    ],
    "name:fin_x_preferred":[
        "Una"
    ],
    "name:fra_x_preferred":[
        "Una"
    ],
    "name:heb_x_preferred":[
        "\u05d0\u05d5\u05e0\u05d4"
    ],
    "name:hrv_x_preferred":[
        "Una"
    ],
    "name:lat_x_preferred":[
        "Una"
    ],
    "name:mlg_x_preferred":[
        "Una"
    ],
    "name:nld_x_preferred":[
        "Una"
    ],
    "name:nor_x_preferred":[
        "Una"
    ],
    "name:pol_x_preferred":[
        "Una"
    ],
    "name:por_x_preferred":[
        "Una"
    ],
    "name:rus_x_preferred":[
        "\u0440\u0435\u043a\u0430 \u0423\u043d\u0430"
    ],
    "name:rus_x_variant":[
        "\u0423\u043d\u0430"
    ],
    "name:slv_x_preferred":[
        "Una"
    ],
    "name:spa_x_preferred":[
        "Una"
    ],
    "name:srp_x_preferred":[
        "\u0423\u043d\u0430"
    ],
    "name:swe_x_preferred":[
        "Una"
    ],
    "name:tur_x_preferred":[
        "Una"
    ],
    "name:ukr_x_preferred":[
        "\u0423\u043d\u0430"
    ],
    "name:urd_x_preferred":[
        "\u0627\u0648\u0646\u0627"
    ],
    "name:vie_x_preferred":[
        "S\u00f4ng Una"
    ],
    "name:zho_cn_x_preferred":[
        "\u5c24\u7eb3\u6cb3"
    ],
    "name:zho_tw_x_preferred":[
        "\u70cf\u90a3\u6cb3"
    ],
    "wof:name":"Una",
    "wof:placetype":"locality"
},
  "geometry": {"coordinates":[47.40355,41.66715],"type":"Point"}
}