{
  "type": "Feature",
  "properties": {
    "gn:admin1_code":"17.0",
    "gn:asciiname":"Una",
    "gn:country_code":"RU",
    "gn:dem":2091,
    "gn:feature_class":"P",
    "gn:feature_code":"PPL",
    "gn:name":"Una",
    "gn:population":0,
    "gn:timezone":"Europe/Moscow",
    "iso:country":"RU",
    "name:rus_x_preferred":[
        "\u0423\u043d\u0430"
    ],
    "wof:name":"Una",
    "wof:placetype":"locality"
},
  "geometry": {"coordinates":[47.40355,41.66715],"type":"Point"}
}