{
  "type": "Feature",
  "properties": {
    "gn:admin1_code":"28",
    "gn:asciiname":"Padany",
    "gn:country_code":"RU",
    "gn:dem":128,
    "gn:feature_class":"P",
    "gn:feature_code":"PPL",
    "gn:name":"Padany",
    "gn:population":0,
    "gn:timezone":"Europe/Moscow",
    "iso:country":"RU",
    "name:eng_x_preferred":[
        "Padany"
    ],
    "name:fin_x_preferred":[
        "Paatene"
    ],
    "name:nor_x_preferred":[
        "Padany"
    ],
    "name:olo_x_preferred":[
        "Puatane"
    ],
    "name:rus_x_preferred":[
        "\u041f\u0430\u0434\u0430\u043d\u044b"
    ],
    "name:und_x_variant":[
        "Padanje"
    ],
    "wof:name":"Padany",
    "wof:placetype":"locality"
},
  "geometry": {"coordinates":[33.41465,63.28717],"type":"Point"}
}