{
  "type": "Feature",
  "properties": {
    "gn:admin1_code":"6",
    "gn:asciiname":"Lychnoye",
    "gn:country_code":"RU",
    "gn:dem":201,
    "gn:feature_class":"P",
    "gn:feature_code":"PPL",
    "gn:name":"Lychnoye",
    "gn:population":0,
    "gn:timezone":"Europe/Moscow",
    "iso:country":"RU",
    "name:eng_x_preferred":[
        "Lychnoye"
    ],
    "name:nor_x_preferred":[
        "Lytsjnoje"
    ],
    "name:rus_x_preferred":[
        "\u041b\u044b\u0447\u043d\u043e\u0435"
    ],
    "name:und_x_variant":[
        "Lychno-Borovskaya",
        "\u041b\u044b\u0447\u043d\u043e\u0435",
        "Lychnoye"
    ],
    "wof:name":"Lychnoye",
    "wof:placetype":"locality"
},
  "geometry": {"coordinates":[41.1831,60.7412],"type":"Point"}
}