{
  "type": "Feature",
  "properties": {
    "gn:admin1_code":"41",
    "gn:asciiname":"Pravda",
    "gn:country_code":"RU",
    "gn:dem":148,
    "gn:feature_class":"P",
    "gn:feature_code":"PPL",
    "gn:name":"Pravda",
    "gn:population":0,
    "gn:timezone":"Europe/Moscow",
    "iso:country":"RU",
    "name:rus_x_preferred":[
        "\u041f\u0440\u0430\u0432\u0434\u0430"
    ],
    "wof:name":"Pravda",
    "wof:placetype":"locality"
},
  "geometry": {"coordinates":[35.313,51.2784],"type":"Point"}
}