{
  "type": "Feature",
  "properties": {
    "gn:admin1_code":"73",
    "gn:asciiname":"Klyancheyevo",
    "gn:country_code":"RU",
    "gn:dem":118,
    "gn:feature_class":"P",
    "gn:feature_code":"PPL",
    "gn:name":"Klyancheyevo",
    "gn:population":0,
    "gn:timezone":"Europe/Moscow",
    "iso:country":"RU",
    "name:rus_x_preferred":[
        "\u041a\u043b\u044f\u043d\u0447\u0435\u0435\u0432\u043e"
    ],
    "name:und_x_variant":[
        "Klyanchevo",
        "Klyancheyevo"
    ],
    "wof:name":"Klyancheyevo",
    "wof:placetype":"locality"
},
  "geometry": {"coordinates":[48.85,55.21806],"type":"Point"}
}