{
  "type": "Feature",
  "properties": {
    "gn:admin1_code":"76",
    "gn:asciiname":"Lapotkovo",
    "gn:country_code":"RU",
    "gn:dem":248,
    "gn:feature_class":"P",
    "gn:feature_code":"PPL",
    "gn:name":"Lapotkovo",
    "gn:population":0,
    "gn:timezone":"Europe/Moscow",
    "iso:country":"RU",
    "name:eng_x_preferred":[
        "Lapotkovo"
    ],
    "name:nor_x_preferred":[
        "Lapotkovo"
    ],
    "name:rus_x_preferred":[
        "\u041b\u0430\u043f\u043e\u0442\u043a\u043e\u0432\u043e"
    ],
    "name:und_x_variant":[
        "\u041b\u0430\u043f\u043e\u0442\u043a\u043e\u0432\u043e",
        "Lapotkovo"
    ],
    "wof:name":"Lapotkovo",
    "wof:placetype":"locality"
},
  "geometry": {"coordinates":[37.41677,53.83854],"type":"Point"}
}