{
  "type": "Feature",
  "properties": {
    "gn:admin1_code":"37",
    "gn:asciiname":"Kotkishevo",
    "gn:country_code":"RU",
    "gn:dem":146,
    "gn:feature_class":"P",
    "gn:feature_code":"PPL",
    "gn:name":"Kotkishevo",
    "gn:population":0,
    "gn:timezone":"Europe/Moscow",
    "iso:country":"RU",
    "name:eng_x_preferred":[
        "Kotkishevo"
    ],
    "name:nor_x_preferred":[
        "Kotkisjevo"
    ],
    "name:rus_x_preferred":[
        "\u041a\u043e\u0442\u043a\u0438\u0448\u0435\u0432\u043e"
    ],
    "wof:name":"Kotkishevo",
    "wof:placetype":"locality"
},
  "geometry": {"coordinates":[43.76422,58.25989000000001],"type":"Point"}
}