{
  "type": "Feature",
  "properties": {
    "gn:admin1_code":"8",
    "gn:asciiname":"Vedenovka",
    "gn:country_code":"RU",
    "gn:dem":142,
    "gn:feature_class":"P",
    "gn:feature_code":"PPL",
    "gn:name":"Vedenovka",
    "gn:population":0,
    "gn:timezone":"Asia/Yekaterinburg",
    "iso:country":"RU",
    "name:rus_x_preferred":[
        "\u0412\u0435\u0434\u0435\u043d\u043e\u0432\u043a\u0430"
    ],
    "wof:name":"Vedenovka",
    "wof:placetype":"locality"
},
  "geometry": {"coordinates":[55.75151,53.43946],"type":"Point"}
}