{
  "type": "Feature",
  "properties": {
    "gn:admin1_code":"57",
    "gn:asciiname":"Teryayevka",
    "gn:country_code":"RU",
    "gn:dem":205,
    "gn:feature_class":"P",
    "gn:feature_code":"PPL",
    "gn:name":"Teryayevka",
    "gn:population":0,
    "gn:timezone":"Europe/Moscow",
    "iso:country":"RU",
    "name:und_x_variant":[
        "Isikeyevo",
        "Teryayevka"
    ],
    "wof:name":"Teryayevka",
    "wof:placetype":"locality"
},
  "geometry": {"coordinates":[46.53361,52.84222],"type":"Point"}
}