{
  "type": "Feature",
  "properties": {
    "gn:admin1_code":"63",
    "gn:asciiname":"Nyachyky",
    "gn:country_code":"RU",
    "gn:dem":277,
    "gn:feature_class":"P",
    "gn:feature_code":"PPL",
    "gn:name":"Nyachyky",
    "gn:population":0,
    "gn:timezone":"Asia/Vladivostok",
    "iso:country":"RU",
    "name:rus_x_preferred":[
        "\u041d\u044f\u0447\u044b\u043a\u044b"
    ],
    "name:und_x_variant":[
        "N\u2019aachyky",
        "Nyachyky"
    ],
    "wof:name":"Nyachyky",
    "wof:placetype":"locality"
},
  "geometry": {"coordinates":[137.40268999999998,67.14605999999999],"type":"Point"}
}