{
  "type": "Feature",
  "properties": {
    "gn:admin1_code":"85",
    "gn:asciiname":"Sumarokovo",
    "gn:country_code":"RU",
    "gn:dem":126,
    "gn:feature_class":"P",
    "gn:feature_code":"PPL",
    "gn:name":"Sumarokovo",
    "gn:population":0,
    "gn:timezone":"Europe/Moscow",
    "iso:country":"RU",
    "name:rus_x_preferred":[
        "\u0421\u0443\u043c\u0430\u0440\u043e\u043a\u043e\u0432\u043e"
    ],
    "name:und_x_variant":[
        "\u0421\u0443\u043c\u0430\u0440\u043e\u043a\u043e\u0432\u043e"
    ],
    "wof:name":"Sumarokovo",
    "wof:placetype":"locality"
},
  "geometry": {"coordinates":[39.71151,59.42124],"type":"Point"}
}