{
  "type": "Feature",
  "properties": {
    "gn:admin1_code":"4",
    "gn:asciiname":"Semenovka",
    "gn:cc2":"RU",
    "gn:country_code":"RU",
    "gn:dem":399,
    "gn:feature_class":"P",
    "gn:feature_code":"PPL",
    "gn:name":"Semenovka",
    "gn:population":0,
    "gn:timezone":"Asia/Barnaul",
    "iso:country":"RU",
    "name:eng_x_preferred":[
        "Semenovka"
    ],
    "name:nor_x_preferred":[
        "Semenovka"
    ],
    "name:rus_x_preferred":[
        "\u0421\u0435\u043c\u0435\u043d\u043e\u0432\u043a\u0430"
    ],
    "name:und_x_variant":[
        "Sem\u00ebnovskoye",
        "Semenovskaya",
        "\u0421\u0435\u043c\u0435\u043d\u043e\u0432\u043a\u0430",
        "Semenovka"
    ],
    "wof:name":"Semenovka",
    "wof:placetype":"locality"
},
  "geometry": {"coordinates":[82.46916999999998,50.95861],"type":"Point"}
}