{
  "type": "Feature",
  "properties": {
    "gn:admin1_code":"86.0",
    "gn:asciiname":"Churikovo",
    "gn:country_code":"RU",
    "gn:dem":129,
    "gn:feature_class":"P",
    "gn:feature_code":"PPL",
    "gn:name":"Churikovo",
    "gn:population":0,
    "gn:timezone":"Europe/Moscow",
    "iso:country":"RU",
    "name:rus_x_preferred":[
        "\u0427\u0443\u0440\u0438\u043a\u043e\u0432\u043e"
    ],
    "wof:name":"Churikovo",
    "wof:placetype":"locality"
},
  "geometry": {"coordinates":[38.94417,51.99472],"type":"Point"}
}