{
  "type": "Feature",
  "properties": {
    "gn:admin1_code":"33.0",
    "gn:asciiname":"Adovshchina",
    "gn:country_code":"RU",
    "gn:dem":151,
    "gn:feature_class":"P",
    "gn:feature_code":"PPL",
    "gn:name":"Adovshchina",
    "gn:population":0,
    "gn:timezone":"Europe/Kirov",
    "iso:country":"RU",
    "name:nor_x_preferred":[
        "Adovsjtsjina"
    ],
    "name:rus_x_preferred":[
        "\u0410\u0434\u043e\u0432\u0449\u0438\u043d\u0430"
    ],
    "wof:name":"Adovshchina",
    "wof:placetype":"locality"
},
  "geometry": {"coordinates":[47.5051,58.31415],"type":"Point"}
}