{
  "type": "Feature",
  "properties": {
    "gn:admin1_code":"25",
    "gn:asciiname":"Ganilovo",
    "gn:country_code":"RU",
    "gn:dem":204,
    "gn:feature_class":"P",
    "gn:feature_code":"PPL",
    "gn:name":"Ganilovo",
    "gn:population":0,
    "gn:timezone":"Europe/Moscow",
    "iso:country":"RU",
    "name:rus_x_preferred":[
        "\u0413\u0430\u043d\u0438\u043b\u043e\u0432\u043e"
    ],
    "name:und_x_variant":[
        "\u0413\u0430\u043d\u0438\u043b\u043e\u0432\u043e"
    ],
    "wof:name":"Ganilovo",
    "wof:placetype":"locality"
},
  "geometry": {"coordinates":[35.94778,53.90778],"type":"Point"}
}