{
  "type": "Feature",
  "properties": {
    "gn:admin1_code":"54",
    "gn:asciiname":"Sarakhanovo",
    "gn:country_code":"RU",
    "gn:dem":78,
    "gn:feature_class":"P",
    "gn:feature_code":"PPL",
    "gn:name":"Sarakhanovo",
    "gn:population":0,
    "gn:timezone":"Asia/Omsk",
    "iso:country":"RU",
    "name:eng_x_preferred":[
        "Sarakhanovo"
    ],
    "name:nor_x_preferred":[
        "Sarakhanovo"
    ],
    "name:rus_x_preferred":[
        "\u0421\u0430\u0440\u0430\u0445\u0430\u043d\u043e\u0432\u043e"
    ],
    "name:und_x_variant":[
        "\u0421\u0430\u0440\u0430\u0445\u0430\u043d\u043e\u0432\u043e",
        "Sarakhanovo"
    ],
    "wof:name":"Sarakhanovo",
    "wof:placetype":"locality"
},
  "geometry": {"coordinates":[73.86358,56.79529],"type":"Point"}
}