{
  "type": "Feature",
  "properties": {
    "gn:admin1_code":"37",
    "gn:asciiname":"Kuz'minskaya",
    "gn:country_code":"RU",
    "gn:dem":191,
    "gn:feature_class":"P",
    "gn:feature_code":"PPL",
    "gn:name":"Kuz\u2019minskaya",
    "gn:population":0,
    "gn:timezone":"Europe/Moscow",
    "iso:country":"RU",
    "name:eng_x_preferred":[
        "Kuz'minskaya"
    ],
    "name:nor_x_preferred":[
        "Kuzminskaja"
    ],
    "name:rus_x_preferred":[
        "\u041a\u0443\u0437\u044c\u043c\u0438\u043d\u0441\u043a\u0430\u044f"
    ],
    "name:und_x_variant":[
        "Kuz\u2019minskaya"
    ],
    "wof:name":"Kuz'minskaya",
    "wof:placetype":"locality"
},
  "geometry": {"coordinates":[46.52915,59.01884],"type":"Point"}
}