{
  "type": "Feature",
  "properties": {
    "iso:country":"RU",
    "name:rus_x_preferred":[
        "\u041c\u0438\u0445\u0430\u0439\u043b\u043e\u0432\u043e-\u042f\u0440\u0446\u0435\u0432\u0441\u043a\u043e\u0435"
    ],
    "wof:name":"Mikhaylovo-Yartsevskoye",
    "wof:placetype":"neighbourhood"
},
  "geometry": {"coordinates":[37.1432368826321,55.40153419990284],"type":"Point"}
}