{
  "type": "Feature",
  "properties": {
    "gn:admin1_code":"77",
    "gn:asciiname":"Alekhino",
    "gn:country_code":"RU",
    "gn:dem":129,
    "gn:feature_class":"P",
    "gn:feature_code":"PPL",
    "gn:name":"Al\u00ebkhino",
    "gn:population":0,
    "gn:timezone":"Europe/Moscow",
    "iso:country":"RU",
    "name:rus_x_preferred":[
        "\u0410\u043b\u0451\u0445\u0438\u043d\u043e"
    ],
    "name:und_x_variant":[
        "Al\u00ebkhino"
    ],
    "wof:name":"Alekhino",
    "wof:placetype":"locality"
},
  "geometry": {"coordinates":[37.5861,57.2977],"type":"Point"}
}