{
  "type": "Feature",
  "properties": {
    "gn:admin1_code":"54",
    "gn:asciiname":"Fominovka Vtoraya",
    "gn:country_code":"RU",
    "gn:dem":114,
    "gn:feature_class":"P",
    "gn:feature_code":"PPL",
    "gn:name":"Fominovka Vtoraya",
    "gn:population":0,
    "gn:timezone":"Asia/Omsk",
    "iso:country":"RU",
    "name:rus_x_preferred":[
        "\u0424\u043e\u043c\u0438\u043d\u043e\u0432\u043a\u0430 \u0412\u0442\u043e\u0440\u0430\u044f"
    ],
    "name:und_x_variant":[
        "\u0424\u043e\u043c\u0438\u043d\u043e\u0432\u043a\u0430 \u0412\u0442\u043e\u0440\u0430\u044f"
    ],
    "wof:name":"Fominovka Vtoraya",
    "wof:placetype":"locality"
},
  "geometry": {"coordinates":[74.2684,54.8029],"type":"Point"}
}