{
  "type": "Feature",
  "properties": {
    "gn:admin1_code":"77",
    "gn:asciiname":"Komary",
    "gn:country_code":"RU",
    "gn:dem":228,
    "gn:feature_class":"P",
    "gn:feature_code":"PPL",
    "gn:name":"Komary",
    "gn:population":0,
    "gn:timezone":"Europe/Moscow",
    "iso:country":"RU",
    "name:eng_x_preferred":[
        "Komary"
    ],
    "name:nor_x_preferred":[
        "Komary"
    ],
    "name:rus_x_preferred":[
        "\u041a\u043e\u043c\u0430\u0440\u044b"
    ],
    "name:und_x_variant":[
        "\u041a\u043e\u043c\u0430\u0440\u044b",
        "Komary"
    ],
    "wof:name":"Komary",
    "wof:placetype":"locality"
},
  "geometry": {"coordinates":[33.17269,55.71735],"type":"Point"}
}