{
  "type": "Feature",
  "properties": {
    "gn:admin1_code":"91",
    "gn:asciiname":"Ivanov Kamen'",
    "gn:country_code":"RU",
    "gn:dem":139,
    "gn:feature_class":"P",
    "gn:feature_code":"PPL",
    "gn:name":"Ivanov Kamen\u2019",
    "gn:population":0,
    "gn:timezone":"Asia/Krasnoyarsk",
    "iso:country":"RU",
    "name:rus_x_preferred":[
        "\u0418\u0432\u0430\u043d\u043e\u0432 \u041a\u0430\u043c\u0435\u043d\u044c"
    ],
    "name:und_x_variant":[
        "Ivanov Kamen\u2019"
    ],
    "wof:name":"Ivanov Kamen'",
    "wof:placetype":"locality"
},
  "geometry": {"coordinates":[94.21666999999999,57.98333],"type":"Point"}
}