{
  "type": "Feature",
  "properties": {
    "gn:admin1_code":"88",
    "gn:asciiname":"Chentsy",
    "gn:country_code":"RU",
    "gn:dem":159,
    "gn:feature_class":"P",
    "gn:feature_code":"PPL",
    "gn:name":"Chentsy",
    "gn:population":0,
    "gn:timezone":"Europe/Moscow",
    "iso:country":"RU",
    "name:rus_x_preferred":[
        "\u0427\u0435\u043d\u0446\u044b"
    ],
    "name:und_x_variant":[
        "\u0427\u0435\u043d\u0446\u044b",
        "Nentsy"
    ],
    "wof:name":"Chentsy",
    "wof:placetype":"locality"
},
  "geometry": {"coordinates":[38.9913,57.6552],"type":"Point"}
}