{
  "type": "Feature",
  "properties": {
    "gn:admin1_code":"85",
    "gn:asciiname":"Kon'-Gora",
    "gn:country_code":"RU",
    "gn:dem":189,
    "gn:feature_class":"P",
    "gn:feature_code":"PPL",
    "gn:name":"Kon\u2019-Gora",
    "gn:population":0,
    "gn:timezone":"Europe/Moscow",
    "iso:country":"RU",
    "name:eng_x_preferred":[
        "Kon'-Gora"
    ],
    "name:nor_x_preferred":[
        "Kon-Gora"
    ],
    "name:rus_x_preferred":[
        "\u041a\u043e\u043d\u044c-\u0413\u043e\u0440\u0430"
    ],
    "name:und_x_variant":[
        "Kon\u2019-Gora"
    ],
    "wof:name":"Kon'-Gora",
    "wof:placetype":"locality"
},
  "geometry": {"coordinates":[39.4627,60.0366],"type":"Point"}
}