{
  "type": "Feature",
  "properties": {
    "gn:admin1_code":"69.0",
    "gn:asciiname":"Barantsevo",
    "gn:country_code":"RU",
    "gn:dem":240,
    "gn:feature_class":"P",
    "gn:feature_code":"PPL",
    "gn:name":"Barantsevo",
    "gn:population":0,
    "gn:timezone":"Europe/Moscow",
    "iso:country":"RU",
    "name:bak_x_preferred":[
        "\u0411\u0430\u0440\u0430\u043d\u0446\u0435\u0432"
    ],
    "name:che_x_preferred":[
        "\u0411\u0430\u0440\u0430\u043d\u0446\u0435\u0432\u043e"
    ],
    "name:hye_x_preferred":[
        "\u0532\u0561\u0580\u0561\u0576\u0581\u0587\u0578"
    ],
    "name:kaz_x_preferred":[
        "\u0411\u0430\u0440\u0430\u043d\u0446"
    ],
    "name:kir_x_preferred":[
        "\u0411\u0430\u0440\u0430\u043d\u0446"
    ],
    "name:nor_x_preferred":[
        "Barantsevo"
    ],
    "name:rus_x_preferred":[
        "\u0411\u0430\u0440\u0430\u043d\u0446\u0435\u0432\u043e"
    ],
    "name:tat_x_preferred":[
        "\u0411\u0430\u0440\u0430\u043d\u0446\u0435\u0432\u043e"
    ],
    "name:ukr_x_preferred":[
        "\u0411\u0430\u0440\u0430\u043d\u0446\u0435\u0432\u043e"
    ],
    "wof:name":"Barantsevo",
    "wof:placetype":"locality"
},
  "geometry": {"coordinates":[34.55,55.31667],"type":"Point"}
}