{
  "type": "Feature",
  "properties": {
    "gn:admin1_code":"13",
    "gn:asciiname":"Aeroport Pervyy",
    "gn:country_code":"RU",
    "gn:dem":220,
    "gn:feature_class":"P",
    "gn:feature_code":"PPL",
    "gn:name":"Aeroport Pervyy",
    "gn:population":0,
    "gn:timezone":"Asia/Yekaterinburg",
    "iso:country":"RU",
    "name:rus_x_preferred":[
        "\u0410\u044d\u0440\u043e\u043f\u043e\u0440\u0442 \u041f\u0435\u0440\u0432\u044b\u0439"
    ],
    "wof:name":"Aeroport Pervyy",
    "wof:placetype":"locality"
},
  "geometry": {"coordinates":[61.51813000000001,55.28921999999999],"type":"Point"}
}