{
  "type": "Feature",
  "properties": {
    "gn:admin1_code":"52",
    "gn:asciiname":"Russkaya Bolotnitsa",
    "gn:country_code":"RU",
    "gn:dem":81,
    "gn:feature_class":"P",
    "gn:feature_code":"PPL",
    "gn:name":"Russkaya Bolotnitsa",
    "gn:population":0,
    "gn:timezone":"Europe/Moscow",
    "iso:country":"RU",
    "name:eng_x_preferred":[
        "Russkaya Bolotnitsa"
    ],
    "name:nor_x_preferred":[
        "Russkaja Bolotnitsa"
    ],
    "name:rus_x_preferred":[
        "\u0420\u0443\u0441\u0441\u043a\u0430\u044f \u0411\u043e\u043b\u043e\u0442\u043d\u0438\u0446\u0430"
    ],
    "name:und_x_variant":[
        "\u0420\u0443\u0441\u0441\u043a\u0430\u044f \u0411\u043e\u043b\u043e\u0442\u043d\u0438\u0446\u0430",
        "Russkaya Bolotnitsa"
    ],
    "wof:name":"Russkaya Bolotnitsa",
    "wof:placetype":"locality"
},
  "geometry": {"coordinates":[32.20684,58.0733],"type":"Point"}
}