{
  "type": "Feature",
  "properties": {
    "gn:admin1_code":"77",
    "gn:asciiname":"Roven' Mosty",
    "gn:country_code":"RU",
    "gn:dem":245,
    "gn:feature_class":"P",
    "gn:feature_code":"PPL",
    "gn:name":"Roven\u2019 Mosty",
    "gn:population":0,
    "gn:timezone":"Europe/Moscow",
    "iso:country":"RU",
    "name:rus_x_preferred":[
        "\u0420\u043e\u0432\u0435\u043d\u044c \u041c\u043e\u0441\u0442\u044b"
    ],
    "name:und_x_variant":[
        "Roven\u2019",
        "Roven\u2019 Mosty"
    ],
    "wof:name":"Roven' Mosty",
    "wof:placetype":"locality"
},
  "geometry": {"coordinates":[32.78953,57.40948],"type":"Point"}
}