{
  "type": "Feature",
  "properties": {
    "gn:admin1_code":"72",
    "gn:asciiname":"Kim",
    "gn:country_code":"RU",
    "gn:dem":167,
    "gn:feature_class":"P",
    "gn:feature_code":"PPL",
    "gn:name":"Kim",
    "gn:population":0,
    "gn:timezone":"Europe/Moscow",
    "iso:country":"RU",
    "name:und_x_variant":[
        "Sovkhoz Imeni KIM",
        "Sovkhoz Imeni Kommunisticheskogo Internatsionala Molod\u00ebzhi",
        "Kim"
    ],
    "wof:name":"Kim",
    "wof:placetype":"locality"
},
  "geometry": {"coordinates":[40.99933,52.92179],"type":"Point"}
}