{
  "type": "Feature",
  "properties": {
    "gn:admin1_code":"16",
    "gn:asciiname":"Enekhmet'",
    "gn:country_code":"RU",
    "gn:dem":190,
    "gn:feature_class":"P",
    "gn:feature_code":"PPL",
    "gn:name":"Enekhmet\u2019",
    "gn:population":0,
    "gn:timezone":"Europe/Moscow",
    "iso:country":"RU",
    "name:rus_x_preferred":[
        "\u042d\u043d\u0435\u0445\u043c\u0435\u0442\u044c"
    ],
    "name:und_x_variant":[
        "Enekhmet\u2019"
    ],
    "wof:name":"Enekhmet'",
    "wof:placetype":"locality"
},
  "geometry": {"coordinates":[46.89281,55.82453],"type":"Point"}
}