{
  "type": "Feature",
  "properties": {
    "gn:admin1_code":"71",
    "gn:asciiname":"Verkhniy Talman",
    "gn:country_code":"RU",
    "gn:dem":123,
    "gn:feature_class":"P",
    "gn:feature_code":"PPL",
    "gn:name":"Verkhniy Talman",
    "gn:population":0,
    "gn:timezone":"Asia/Yekaterinburg",
    "iso:country":"RU",
    "name:eng_x_preferred":[
        "Verkhniy Talman"
    ],
    "name:rus_x_preferred":[
        "\u0412\u0435\u0440\u0445.\u0442\u0430\u043b\u043c\u0430\u043d"
    ],
    "name:rus_x_variant":[
        "\u0412\u0435\u0440\u0445.\u0422\u0430\u043b\u043c\u0430\u043d",
        "\u0412\u0435\u0440\u0445\u043d\u0438\u0439 \u0422\u0430\u043b\u043c\u0430\u043d"
    ],
    "name:und_x_variant":[
        "Verkhniy Tolman"
    ],
    "wof:name":"Verkhniy Talman",
    "wof:placetype":"locality"
},
  "geometry": {"coordinates":[64.18089999999999,57.16013],"type":"Point"}
}