{
  "type": "Feature",
  "properties": {
    "gn:admin1_code":"8",
    "gn:asciiname":"Osorgino",
    "gn:country_code":"RU",
    "gn:dem":119,
    "gn:feature_class":"P",
    "gn:feature_code":"PPL",
    "gn:name":"Osorgino",
    "gn:population":0,
    "gn:timezone":"Asia/Yekaterinburg",
    "iso:country":"RU",
    "name:rus_x_preferred":[
        "\u041e\u0441\u043e\u0440\u0433\u0438\u043d\u043e"
    ],
    "name:und_x_variant":[
        "\u041e\u0441\u043e\u0440\u0433\u0438\u043d\u043e"
    ],
    "wof:name":"Osorgino",
    "wof:placetype":"locality"
},
  "geometry": {"coordinates":[55.75535,54.54649000000001],"type":"Point"}
}