{
  "type": "Feature",
  "properties": {
    "gn:admin1_code":"8",
    "gn:asciiname":"Osorgino",
    "gn:country_code":"RU",
    "gn:dem":119,
    "gn:feature_class":"P",
    "gn:feature_code":"PPL",
    "gn:name":"Osorgino",
    "gn:population":0,
    "gn:timezone":"Asia/Yekaterinburg",
    "iso:country":"RU",
    "name:bak_x_preferred":[
        "\u041e\u0441\u043e\u0440\u0433\u0438\u043d"
    ],
    "name:che_x_preferred":[
        "\u041e\u0441\u043e\u0440\u0433\u0438\u043d\u043e"
    ],
    "name:hye_x_preferred":[
        "\u0555\u057d\u0578\u0580\u0563\u056b\u0576\u0578"
    ],
    "name:kat_x_preferred":[
        "\u10dd\u10e1\u10dd\u10e0\u10d2\u10d8\u10dc\u10dd"
    ],
    "name:kaz_x_preferred":[
        "\u041e\u0441\u043e\u0440\u0433\u0438\u043d\u043e"
    ],
    "name:kir_x_preferred":[
        "\u041e\u0441\u043e\u0440\u0433\u0438\u043d\u043e"
    ],
    "name:rus_x_preferred":[
        "\u041e\u0441\u043e\u0440\u0433\u0438\u043d\u043e"
    ],
    "name:tat_x_preferred":[
        "\u041e\u0441\u043e\u0440\u0433\u0438\u043d\u043e"
    ],
    "name:ukr_x_preferred":[
        "\u041e\u0441\u043e\u0440\u0433\u0456\u043d\u043e"
    ],
    "name:und_x_variant":[
        "\u041e\u0441\u043e\u0440\u0433\u0438\u043d\u043e"
    ],
    "wof:name":"Osorgino",
    "wof:placetype":"locality"
},
  "geometry": {"coordinates":[55.75535,54.54649000000001],"type":"Point"}
}