{
  "type": "Feature",
  "properties": {
    "gn:admin1_code":"63",
    "gn:asciiname":"Ogyustakh-Oyumte",
    "gn:country_code":"RU",
    "gn:dem":207,
    "gn:feature_class":"P",
    "gn:feature_code":"PPL",
    "gn:name":"Ogyustakh-Oyumte",
    "gn:population":0,
    "gn:timezone":"Asia/Magadan",
    "iso:country":"RU",
    "name:rus_x_preferred":[
        "\u041e\u0433\u044e\u0441\u0442\u0430\u0445-\u041e\u044e\u043c\u0442\u0435"
    ],
    "wof:name":"Ogyustakh-Oyumte",
    "wof:placetype":"locality"
},
  "geometry": {"coordinates":[142.80000000000001,66.40000000000001],"type":"Point"}
}