{
  "type": "Feature",
  "properties": {
    "gn:country":"RU",
    "gn:fcode":"PPL",
    "gn:pop":4298,
    "iso:country":"RU",
    "name:eng_x_preferred":[
        "Shelabolikha"
    ],
    "name:nor_x_preferred":[
        "Sjelabolikha"
    ],
    "name:rus_x_preferred":[
        "\u0428\u0435\u043b\u0430\u0431\u043e\u043b\u0438\u0445\u0430"
    ],
    "name:unk_x_variant":[
        "\u0428\u0435\u043b\u0430\u0431\u043e\u043b\u0438\u0445\u0430"
    ],
    "qs:name":"Shelabolikha",
    "qs:photos_9r":0,
    "qs:photos_sr":0,
    "qs:pop_sr":"4",
    "wd:wordcount":741,
    "wof:name":"Shelabolikha",
    "wof:placetype":"locality",
    "wof:population":4298
},
  "geometry": {"coordinates":[82.61669999999999,53.4131],"type":"Point"}
}