{
  "type": "Feature",
  "properties": {
    "gn:country":"RU",
    "gn:fcode":"PPL",
    "gn:population":4298,
    "iso:country":"RU",
    "name:ceb_x_preferred":[
        "Shelabolikhinskiy Rayon"
    ],
    "name:che_x_preferred":[
        "\u0428\u0435\u043b\u0430\u0431\u043e\u043b\u0438\u0445\u0430\u043d \u043a\u04c0\u043e\u0448\u0442"
    ],
    "name:deu_x_preferred":[
        "Schelabolichinski rajon"
    ],
    "name:eng_x_preferred":[
        "Shelabolikha"
    ],
    "name:eng_x_variant":[
        "Shelabolikhinsky District"
    ],
    "name:hun_x_preferred":[
        "Selabolihai j\u00e1r\u00e1s"
    ],
    "name:hye_x_preferred":[
        "\u0547\u0565\u056c\u0561\u0562\u0578\u056c\u056b\u056d\u056b\u0576\u057d\u056f\u056b \u0577\u0580\u057b\u0561\u0576"
    ],
    "name:ita_x_preferred":[
        "\u0160elabolichinskij rajon"
    ],
    "name:nld_x_preferred":[
        "Sjelabolichinskiy rayon"
    ],
    "name:nor_x_preferred":[
        "Sjelabolikha"
    ],
    "name:rus_x_preferred":[
        "\u0428\u0435\u043b\u0430\u0431\u043e\u043b\u0438\u0445\u0430"
    ],
    "name:rus_x_variant":[
        "\u0428\u0435\u043b\u0430\u0431\u043e\u043b\u0438\u0445\u0438\u043d\u0441\u043a\u0438\u0439 \u0440\u0430\u0439\u043e\u043d"
    ],
    "name:vie_x_preferred":[
        "Shelabolikhinsky"
    ],
    "name:zho_x_preferred":[
        "\u820d\u62c9\u535a\u5229\u6b23\u65af\u57fa\u5340"
    ],
    "qs:name":"Shelabolikha",
    "qs:photos_9r":0,
    "qs:photos_sr":0,
    "qs:pop_sr":"4",
    "wd:wordcount":741,
    "wof:name":"Shelabolikha",
    "wof:placetype":"locality",
    "wof:population":4298
},
  "geometry": {"coordinates":[82.61669999999999,53.4131],"type":"Point"}
}