{
  "type": "Feature",
  "properties": {
    "gn:admin1_code":"90",
    "gn:asciiname":"Snegiri",
    "gn:country_code":"RU",
    "gn:dem":153,
    "gn:feature_class":"P",
    "gn:feature_code":"PPL",
    "gn:name":"Snegiri",
    "gn:population":0,
    "gn:timezone":"Asia/Yekaterinburg",
    "iso:country":"RU",
    "name:rus_x_preferred":[
        "\u0421\u043d\u0435\u0433\u0438\u0440\u0438"
    ],
    "name:rus_x_variant":[
        "Snigir\u00ebvo",
        "Snegir\u00ebvo"
    ],
    "name:und_x_variant":[
        "Snegir\u00ebvo",
        "Snigir\u00ebvo",
        "Snegiri",
        "\u0421\u043d\u0435\u0433\u0438\u0440\u0438"
    ],
    "wof:name":"Snegiri",
    "wof:placetype":"locality"
},
  "geometry": {"coordinates":[56.8042,57.5563],"type":"Point"}
}