{
  "type": "Feature",
  "properties": {
    "gn:admin1_code":"21.0",
    "gn:asciiname":"Perepelino",
    "gn:country_code":"RU",
    "gn:dem":112,
    "gn:feature_class":"P",
    "gn:feature_code":"PPL",
    "gn:name":"Perepelino",
    "gn:population":0,
    "gn:timezone":"Europe/Moscow",
    "iso:country":"RU",
    "name:nor_x_preferred":[
        "Perepelino"
    ],
    "name:rus_x_preferred":[
        "\u041f\u0435\u0440\u0435\u043f\u0435\u043b\u0438\u043d\u043e"
    ],
    "wof:name":"Perepelino",
    "wof:placetype":"locality"
},
  "geometry": {"coordinates":[42.61139,56.83302],"type":"Point"}
}