{
  "type": "Feature",
  "properties": {
    "gn:admin1_code":"6",
    "gn:asciiname":"Pustynskoye",
    "gn:country_code":"RU",
    "gn:dem":83,
    "gn:feature_class":"P",
    "gn:feature_code":"PPL",
    "gn:name":"Pustynskoye",
    "gn:population":0,
    "gn:timezone":"Europe/Moscow",
    "iso:country":"RU",
    "name:rus_x_preferred":[
        "\u041f\u0443\u0441\u0442\u044b\u043d\u0441\u043a\u043e\u0435"
    ],
    "name:und_x_variant":[
        "Pustynskaya",
        "Pustynskoye"
    ],
    "wof:name":"Pustynskoye",
    "wof:placetype":"locality"
},
  "geometry": {"coordinates":[48.4928,64.50700999999999],"type":"Point"}
}