{
  "type": "Feature",
  "properties": {
    "gn:admin1_code":"62",
    "gn:asciiname":"Kudashevo",
    "gn:country_code":"RU",
    "gn:dem":146,
    "gn:feature_class":"P",
    "gn:feature_code":"PPL",
    "gn:name":"Kudashevo",
    "gn:population":0,
    "gn:timezone":"Europe/Moscow",
    "iso:country":"RU",
    "name:bak_x_preferred":[
        "\u04a0\u043e\u0499\u0430\u0448"
    ],
    "name:che_x_preferred":[
        "\u041a\u0443\u0434\u0430\u0448\u0435\u0432\u043e"
    ],
    "name:hye_x_preferred":[
        "\u053f\u0578\u0582\u0564\u0561\u0577\u0587\u0578"
    ],
    "name:kaz_x_preferred":[
        "\u041a\u0443\u0434\u0430\u0448"
    ],
    "name:kir_x_preferred":[
        "\u041a\u0443\u0434\u0430\u0448"
    ],
    "name:rus_x_preferred":[
        "\u041a\u0443\u0434\u0430\u0448\u0435\u0432\u043e"
    ],
    "name:tat_x_preferred":[
        "\u041a\u043e\u0434\u0430\u0448"
    ],
    "wof:name":"Kudashevo",
    "wof:placetype":"locality"
},
  "geometry": {"coordinates":[39.67496,54.83283],"type":"Point"}
}