{
  "type": "Feature",
  "properties": {
    "gn:admin1_code":"62",
    "gn:asciiname":"Kudashevo",
    "gn:country_code":"RU",
    "gn:dem":146,
    "gn:feature_class":"P",
    "gn:feature_code":"PPL",
    "gn:name":"Kudashevo",
    "gn:population":0,
    "gn:timezone":"Europe/Moscow",
    "iso:country":"RU",
    "name:rus_x_preferred":[
        "\u041a\u0443\u0434\u0430\u0448\u0435\u0432\u043e"
    ],
    "name:und_x_variant":[
        "\u041a\u0443\u0434\u0430\u0448\u0435\u0432\u043e"
    ],
    "wof:name":"Kudashevo",
    "wof:placetype":"locality"
},
  "geometry": {"coordinates":[39.67496,54.83283],"type":"Point"}
}