{
  "type": "Feature",
  "properties": {
    "gn:admin1_code":"54",
    "gn:asciiname":"Stoletovka",
    "gn:country_code":"RU",
    "gn:dem":112,
    "gn:feature_class":"P",
    "gn:feature_code":"PPL",
    "gn:name":"Stoletovka",
    "gn:population":0,
    "gn:timezone":"Asia/Omsk",
    "iso:country":"RU",
    "name:rus_x_preferred":[
        "\u0421\u0442\u043e\u043b\u0435\u0442\u043e\u0432\u043a\u0430"
    ],
    "wof:name":"Stoletovka",
    "wof:placetype":"locality"
},
  "geometry": {"coordinates":[74.95,54.76667],"type":"Point"}
}