{
  "type": "Feature",
  "properties": {
    "gn:admin1_code":"45.0",
    "gn:asciiname":"Maloye Akashevo",
    "gn:country_code":"RU",
    "gn:dem":112,
    "gn:feature_class":"P",
    "gn:feature_code":"PPL",
    "gn:name":"Maloye Akashevo",
    "gn:population":0,
    "gn:timezone":"Europe/Moscow",
    "iso:country":"RU",
    "name:rus_x_preferred":[
        "\u041c\u0430\u043b\u043e\u0435 \u0410\u043a\u0430\u0448\u0435\u0432\u043e"
    ],
    "wof:name":"Maloye Akashevo",
    "wof:placetype":"locality"
},
  "geometry": {"coordinates":[48.16472,56.77611],"type":"Point"}
}