{
  "type": "Feature",
  "properties": {
    "gn:admin1_code":"32",
    "gn:asciiname":"Vostokina P.",
    "gn:cc2":"RU",
    "gn:country_code":"RU",
    "gn:dem":57,
    "gn:feature_class":"P",
    "gn:feature_code":"PPL",
    "gn:name":"Vostokina P.",
    "gn:population":0,
    "gn:timezone":"Asia/Yekaterinburg",
    "iso:country":"RU",
    "name:und_x_variant":[
        "Vostokina N.",
        "Vostokina P."
    ],
    "wof:name":"Vostokina P.",
    "wof:placetype":"locality"
},
  "geometry": {"coordinates":[72.38333,61.68333000000001],"type":"Point"}
}