{
  "type": "Feature",
  "properties": {
    "gn:admin1_code":"81",
    "gn:asciiname":"Karanino",
    "gn:country_code":"RU",
    "gn:dem":132,
    "gn:feature_class":"P",
    "gn:feature_code":"PPL",
    "gn:name":"Karanino",
    "gn:population":0,
    "gn:timezone":"Europe/Ulyanovsk",
    "iso:country":"RU",
    "name:rus_x_preferred":[
        "\u041a\u0430\u0440\u0430\u043d\u0438\u043d\u043e"
    ],
    "wof:name":"Karanino",
    "wof:placetype":"locality"
},
  "geometry": {"coordinates":[47.26445,53.29079],"type":"Point"}
}