{
  "type": "Feature",
  "properties": {
    "gn:admin1_code":"17.0",
    "gn:asciiname":"Rybnyy Promysel Nomer Shest'desyat Dva",
    "gn:country_code":"RU",
    "gn:dem":-25,
    "gn:feature_class":"P",
    "gn:feature_code":"PPL",
    "gn:name":"Rybnyy Promysel Nomer Shest\u2019desyat Dva",
    "gn:population":0,
    "gn:timezone":"Europe/Moscow",
    "iso:country":"RU",
    "wof:name":"Rybnyy Promysel Nomer Shest'desyat Dva",
    "wof:placetype":"locality"
},
  "geometry": {"coordinates":[48.42333,41.91778],"type":"Point"}
}