{
  "type": "Feature",
  "properties": {
    "gn:admin1_code":"77",
    "gn:asciiname":"Bulyki",
    "gn:country_code":"RU",
    "gn:dem":178,
    "gn:feature_class":"P",
    "gn:feature_code":"PPL",
    "gn:name":"Bulyki",
    "gn:population":0,
    "gn:timezone":"Europe/Moscow",
    "iso:country":"RU",
    "name:rus_x_preferred":[
        "\u0411\u0443\u043b\u044b\u043a\u0438"
    ],
    "wof:name":"Bulyki",
    "wof:placetype":"locality"
},
  "geometry": {"coordinates":[32.1894,55.7102],"type":"Point"}
}