{
  "type": "Feature",
  "properties": {
    "gn:admin1_code":"86",
    "gn:asciiname":"Novitchenko",
    "gn:country_code":"RU",
    "gn:dem":98,
    "gn:feature_class":"P",
    "gn:feature_code":"PPL",
    "gn:name":"Novitchenko",
    "gn:population":0,
    "gn:timezone":"Europe/Moscow",
    "iso:country":"RU",
    "name:rus_x_preferred":[
        "\u041d\u043e\u0432\u0438\u0442\u0447\u0435\u043d\u043a\u043e"
    ],
    "name:und_x_variant":[
        "Navitchenko",
        "Novitchenko"
    ],
    "wof:name":"Novitchenko",
    "wof:placetype":"locality"
},
  "geometry": {"coordinates":[41.1196,51.1848],"type":"Point"}
}