{
  "type": "Feature",
  "properties": {
    "gn:admin1_code":"88.0",
    "gn:asciiname":"Dobrilovo",
    "gn:country_code":"RU",
    "gn:dem":186,
    "gn:feature_class":"P",
    "gn:feature_code":"PPL",
    "gn:name":"Dobrilovo",
    "gn:population":0,
    "gn:timezone":"Europe/Moscow",
    "iso:country":"RU",
    "name:rus_x_preferred":[
        "\u0414\u043e\u0431\u0440\u0438\u043b\u043e\u0432\u043e"
    ],
    "name:und_x_variant":[
        "\u0414\u043e\u0431\u0440\u0438\u043b\u043e\u0432\u043e"
    ],
    "wof:name":"Dobrilovo",
    "wof:placetype":"locality"
},
  "geometry": {"coordinates":[38.90175,56.66817],"type":"Point"}
}