{
  "type": "Feature",
  "properties": {
    "gn:admin1_code":"71",
    "gn:asciiname":"Trud Otdykh",
    "gn:country_code":"RU",
    "gn:dem":231,
    "gn:feature_class":"P",
    "gn:feature_code":"PPL",
    "gn:name":"Trud Otdykh",
    "gn:population":0,
    "gn:timezone":"Asia/Yekaterinburg",
    "iso:country":"RU",
    "wof:name":"Trud Otdykh",
    "wof:placetype":"locality"
},
  "geometry": {"coordinates":[61.46666999999999,56.96666999999999],"type":"Point"}
}