{
  "type": "Feature",
  "properties": {
    "gn:admin1_code":"80",
    "gn:asciiname":"Maragino",
    "gn:country_code":"RU",
    "gn:dem":89,
    "gn:feature_class":"P",
    "gn:feature_code":"PPL",
    "gn:name":"Maragino",
    "gn:population":0,
    "gn:timezone":"Europe/Samara",
    "iso:country":"RU",
    "name:nor_x_preferred":[
        "Maragino"
    ],
    "name:rus_x_preferred":[
        "\u041c\u0430\u0440\u0430\u0433\u0438\u043d\u043e"
    ],
    "wof:name":"Maragino",
    "wof:placetype":"locality"
},
  "geometry": {"coordinates":[53.65792,56.03245],"type":"Point"}
}