{
  "type": "Feature",
  "properties": {
    "gn:admin1_code":"8.0",
    "gn:asciiname":"Absalyamovo",
    "gn:country_code":"RU",
    "gn:dem":454,
    "gn:feature_class":"P",
    "gn:feature_code":"PPL",
    "gn:name":"Absalyamovo",
    "gn:population":0,
    "gn:timezone":"Asia/Yekaterinburg",
    "iso:country":"RU",
    "name:nor_x_preferred":[
        "Absaljamovo"
    ],
    "name:rus_x_preferred":[
        "\u0410\u0431\u0441\u0430\u043b\u044f\u043c\u043e\u0432\u043e"
    ],
    "name:und_x_variant":[
        "Apsalyamova",
        "Absalyamova",
        "Absalyamovo"
    ],
    "wof:name":"Absalyamovo",
    "wof:placetype":"locality"
},
  "geometry": {"coordinates":[59.5271,54.6355],"type":"Point"}
}