{
  "type": "Feature",
  "properties": {
    "gn:admin1_code":"6.0",
    "gn:asciiname":"Bryukhanovskoya",
    "gn:cc2":"RU",
    "gn:country_code":"RU",
    "gn:dem":83,
    "gn:feature_class":"P",
    "gn:feature_code":"PPL",
    "gn:name":"Bryukhanovskoya",
    "gn:population":0,
    "gn:timezone":"Europe/Moscow",
    "iso:country":"RU",
    "name:und_x_variant":[
        "Bryukanovskaya"
    ],
    "wof:name":"Bryukhanovskoya",
    "wof:placetype":"locality"
},
  "geometry": {"coordinates":[42.48333,61.33333],"type":"Point"}
}