{
  "type": "Feature",
  "properties": {
    "gn:admin1_code":"72",
    "gn:asciiname":"Protasovo",
    "gn:country_code":"RU",
    "gn:dem":171,
    "gn:feature_class":"P",
    "gn:feature_code":"PPL",
    "gn:name":"Protasovo",
    "gn:population":0,
    "gn:timezone":"Europe/Moscow",
    "iso:country":"RU",
    "name:che_x_preferred":[
        "\u041f\u0440\u043e\u0442\u0430\u0441\u043e\u0432\u043e"
    ],
    "name:eng_x_preferred":[
        "Protasovo"
    ],
    "name:nor_x_preferred":[
        "Protasovo"
    ],
    "name:rus_x_preferred":[
        "\u041f\u0440\u043e\u0442\u0430\u0441\u043e\u0432\u043e"
    ],
    "name:und_x_variant":[
        "Protasovka"
    ],
    "wof:name":"Protasovo",
    "wof:placetype":"locality"
},
  "geometry": {"coordinates":[41.73888,52.12908],"type":"Point"}
}