{
  "type": "Feature",
  "properties": {
    "gn:admin1_code":"7",
    "gn:asciiname":"Kamnev",
    "gn:country_code":"RU",
    "gn:dem":-14,
    "gn:feature_class":"P",
    "gn:feature_code":"PPL",
    "gn:name":"Kamnev",
    "gn:population":0,
    "gn:timezone":"Europe/Astrakhan",
    "iso:country":"RU",
    "name:che_x_preferred":[
        "\u041a\u0430\u043c\u043d\u0435\u0432"
    ],
    "name:rus_x_preferred":[
        "\u041a\u0430\u043c\u043d\u0435\u0432"
    ],
    "name:tgk_x_preferred":[
        "\u041a\u0430\u043c\u043d\u0435\u0432"
    ],
    "wof:name":"Kamnev",
    "wof:placetype":"locality"
},
  "geometry": {"coordinates":[45.45056,48.49781],"type":"Point"}
}