{
  "type": "Feature",
  "properties": {
    "gn:admin1_code":"80",
    "gn:asciiname":"Pol'ko",
    "gn:country_code":"RU",
    "gn:dem":151,
    "gn:feature_class":"P",
    "gn:feature_code":"PPL",
    "gn:name":"Pol\u2019ko",
    "gn:population":0,
    "gn:timezone":"Europe/Samara",
    "iso:country":"RU",
    "name:rus_x_preferred":[
        "\u041f\u043e\u043b\u044c\u043a\u043e"
    ],
    "name:und_x_variant":[
        "Pol\u2019ko"
    ],
    "wof:name":"Pol'ko",
    "wof:placetype":"locality"
},
  "geometry": {"coordinates":[51.65341,56.58345],"type":"Point"}
}