{
  "type": "Feature",
  "properties": {
    "gn:admin1_code":"69",
    "gn:asciiname":"Nikitino",
    "gn:country_code":"RU",
    "gn:dem":187,
    "gn:feature_class":"P",
    "gn:feature_code":"PPL",
    "gn:name":"Nikitino",
    "gn:population":0,
    "gn:timezone":"Europe/Moscow",
    "iso:country":"RU",
    "name:eng_x_preferred":[
        "Nikitino"
    ],
    "name:nor_x_preferred":[
        "Nikitino"
    ],
    "name:rus_x_preferred":[
        "\u041d\u0438\u043a\u0438\u0442\u0438\u043d\u043e"
    ],
    "wof:name":"Nikitino",
    "wof:placetype":"locality"
},
  "geometry": {"coordinates":[34.41807,55.8128],"type":"Point"}
}