{
  "type": "Feature",
  "properties": {
    "gn:admin1_code":"40",
    "gn:asciiname":"Kamyshi",
    "gn:country_code":"RU",
    "gn:dem":80,
    "gn:feature_class":"P",
    "gn:feature_code":"PPL",
    "gn:name":"Kamyshi",
    "gn:population":0,
    "gn:timezone":"Asia/Yekaterinburg",
    "iso:country":"RU",
    "name:che_x_preferred":[
        "\u041a\u0430\u043c\u044b\u0448\u0438"
    ],
    "name:eng_x_preferred":[
        "Kamyshi"
    ],
    "name:nor_x_preferred":[
        "Kamysji"
    ],
    "name:rus_x_preferred":[
        "\u041a\u0430\u043c\u044b\u0448\u0438"
    ],
    "name:und_x_variant":[
        "\u041a\u0430\u043c\u044b\u0448\u0438",
        "Kamyshi"
    ],
    "wof:name":"Kamyshi",
    "wof:placetype":"locality"
},
  "geometry": {"coordinates":[64.91417,55.02639],"type":"Point"}
}