{
  "type": "Feature",
  "properties": {
    "gn:admin1_code":"24",
    "gn:asciiname":"Naryn Khuduk",
    "gn:cc2":"RU",
    "gn:country_code":"RU",
    "gn:dem":-18,
    "gn:feature_class":"P",
    "gn:feature_code":"PPL",
    "gn:name":"Naryn Khuduk",
    "gn:population":0,
    "gn:timezone":"Europe/Moscow",
    "iso:country":"RU",
    "name:eng_x_preferred":[
        "Naryn Khuduk"
    ],
    "name:nor_x_preferred":[
        "Naryn-Khuduk"
    ],
    "name:rus_x_preferred":[
        "\u041d\u0430\u0440\u044b\u043d-\u0425\u0443\u0434\u0443\u043a"
    ],
    "name:rus_x_variant":[
        "\u041d\u0430\u0440\u044b\u043d \u0425\u0443\u0434\u0443\u043a"
    ],
    "name:und_x_variant":[
        "Chernozemel\u2019skoye",
        "Naryn Khuduk",
        "\u041d\u0430\u0440\u044b\u043d \u0425\u0443\u0434\u0443\u043a"
    ],
    "wof:name":"Naryn Khuduk",
    "wof:placetype":"locality"
},
  "geometry": {"coordinates":[46.54361,45.43139],"type":"Point"}
}