{
  "type": "Feature",
  "properties": {
    "gn:admin1_code":"60",
    "gn:asciiname":"Tarasy",
    "gn:country_code":"RU",
    "gn:dem":102,
    "gn:feature_class":"P",
    "gn:feature_code":"PPL",
    "gn:name":"Tarasy",
    "gn:population":0,
    "gn:timezone":"Europe/Moscow",
    "iso:country":"RU",
    "name:rus_x_preferred":[
        "\u0422\u0430\u0440\u0430\u0441\u044b"
    ],
    "name:und_x_variant":[
        "\u0422\u0430\u0440\u0430\u0441\u044b"
    ],
    "wof:name":"Tarasy",
    "wof:placetype":"locality"
},
  "geometry": {"coordinates":[30.95587,56.52522],"type":"Point"}
}