{
  "type": "Feature",
  "properties": {
    "gn:admin1_code":"84",
    "gn:asciiname":"Savinskiy",
    "gn:country_code":"RU",
    "gn:dem":66,
    "gn:feature_class":"P",
    "gn:feature_code":"PPL",
    "gn:name":"Savinskiy",
    "gn:population":0,
    "gn:timezone":"Europe/Volgograd",
    "iso:country":"RU",
    "name:eng_x_preferred":[
        "Savinskiy"
    ],
    "name:nor_x_preferred":[
        "Savinskij"
    ],
    "name:rus_x_preferred":[
        "\u0421\u0430\u0432\u0438\u043d\u0441\u043a\u0438\u0439"
    ],
    "name:und_x_variant":[
        "Savin",
        "\u0421\u0430\u0432\u0438\u043d\u0441\u043a\u0438\u0439",
        "Savinskiy"
    ],
    "wof:name":"Savinskiy",
    "wof:placetype":"locality"
},
  "geometry": {"coordinates":[42.98278,48.74462],"type":"Point"}
}