{
  "type": "Feature",
  "properties": {
    "gn:admin1_code":"52.0",
    "gn:asciiname":"Baryshevo",
    "gn:country_code":"RU",
    "gn:dem":143,
    "gn:feature_class":"P",
    "gn:feature_code":"PPL",
    "gn:name":"Baryshevo",
    "gn:population":0,
    "gn:timezone":"Europe/Moscow",
    "iso:country":"RU",
    "name:eng_x_preferred":[
        "Baryshevo"
    ],
    "name:hye_x_preferred":[
        "\u0532\u0561\u0580\u056b\u0577\u0587\u0578"
    ],
    "name:nor_x_preferred":[
        "Barysjevo"
    ],
    "name:rus_x_preferred":[
        "\u0411\u0430\u0440\u044b\u0448\u0435\u0432\u043e"
    ],
    "name:sco_x_preferred":[
        "Baryshevo"
    ],
    "wof:name":"Baryshevo",
    "wof:placetype":"locality"
},
  "geometry": {"coordinates":[34.67815,58.30574],"type":"Point"}
}