{
  "type": "Feature",
  "properties": {
    "gn:admin1_code":"77",
    "gn:asciiname":"Dyagilevo",
    "gn:country_code":"RU",
    "gn:dem":142,
    "gn:feature_class":"P",
    "gn:feature_code":"PPL",
    "gn:name":"Dyagilevo",
    "gn:population":0,
    "gn:timezone":"Europe/Moscow",
    "iso:country":"RU",
    "name:rus_x_preferred":[
        "\u0414\u044f\u0433\u0438\u043b\u0435\u0432\u043e"
    ],
    "name:und_x_variant":[
        "\u0414\u044f\u0433\u0438\u043b\u0435\u0432\u043e"
    ],
    "wof:name":"Dyagilevo",
    "wof:placetype":"locality"
},
  "geometry": {"coordinates":[36.614,56.919],"type":"Point"}
}