{
  "type": "Feature",
  "properties": {
    "gn:admin1_code":"4",
    "gn:asciiname":"Vostochnaya Zarya",
    "gn:country_code":"RU",
    "gn:dem":169,
    "gn:feature_class":"P",
    "gn:feature_code":"PPL",
    "gn:name":"Vostochnaya Zarya",
    "gn:population":0,
    "gn:timezone":"Asia/Barnaul",
    "iso:country":"RU",
    "name:rus_x_preferred":[
        "\u0412\u043e\u0441\u0442\u043e\u0447\u043d\u043d\u0430\u044f \u0417\u0430\u0440\u044f"
    ],
    "name:und_x_variant":[
        "\u0412\u043e\u0441\u0442\u043e\u0447\u043d\u043d\u0430\u044f \u0417\u0430\u0440\u044f"
    ],
    "wof:name":"Vostochnaya Zarya",
    "wof:placetype":"locality"
},
  "geometry": {"coordinates":[79.5483,53.3012],"type":"Point"}
}