{
  "type": "Feature",
  "properties": {
    "gn:admin1_code":"86",
    "gn:asciiname":"Yevdakovo",
    "gn:country_code":"RU",
    "gn:dem":194,
    "gn:feature_class":"P",
    "gn:feature_code":"PPL",
    "gn:name":"Yevdakovo",
    "gn:population":0,
    "gn:timezone":"Europe/Moscow",
    "iso:country":"RU",
    "name:eng_x_preferred":[
        "Yevdakovo"
    ],
    "name:nor_x_preferred":[
        "Jevdakovo"
    ],
    "name:rus_x_preferred":[
        "\u0415\u0432\u0434\u0430\u043a\u043e\u0432\u043e"
    ],
    "name:und_x_variant":[
        "Evdakovo"
    ],
    "wof:name":"Yevdakovo",
    "wof:placetype":"locality"
},
  "geometry": {"coordinates":[39.39628,50.75139],"type":"Point"}
}