{
  "type": "Feature",
  "properties": {
    "gn:admin1_code":"91",
    "gn:asciiname":"Smorodinka",
    "gn:country_code":"RU",
    "gn:dem":84,
    "gn:feature_class":"P",
    "gn:feature_code":"PPL",
    "gn:name":"Smorodinka",
    "gn:population":0,
    "gn:timezone":"Asia/Krasnoyarsk",
    "iso:country":"RU",
    "name:eng_x_preferred":[
        "Smorodinka"
    ],
    "name:nor_x_preferred":[
        "Smorodinka"
    ],
    "name:rus_x_preferred":[
        "\u0421\u043c\u043e\u0440\u043e\u0434\u0438\u043d\u043a\u0430"
    ],
    "name:und_x_variant":[
        "Popovshchina"
    ],
    "wof:name":"Smorodinka",
    "wof:placetype":"locality"
},
  "geometry": {"coordinates":[92.82259999999999,58.1332],"type":"Point"}
}