{
  "type": "Feature",
  "properties": {
    "gn:admin1_code":"41",
    "gn:asciiname":"Zabuzhevka",
    "gn:country_code":"RU",
    "gn:dem":179,
    "gn:feature_class":"P",
    "gn:feature_code":"PPL",
    "gn:name":"Zabuzhevka",
    "gn:population":0,
    "gn:timezone":"Europe/Moscow",
    "iso:country":"RU",
    "name:eng_x_preferred":[
        "Zabuzhevka"
    ],
    "name:nor_x_preferred":[
        "Zabuzjevka"
    ],
    "name:rus_x_preferred":[
        "\u0417\u0430\u0431\u0443\u0436\u0435\u0432\u043a\u0430"
    ],
    "wof:name":"Zabuzhevka",
    "wof:placetype":"locality"
},
  "geometry": {"coordinates":[35.4856,50.9633],"type":"Point"}
}