{
  "type": "Feature",
  "properties": {
    "gn:admin1_code":"53",
    "gn:asciiname":"Novotroitsk",
    "gn:country_code":"RU",
    "gn:dem":106,
    "gn:feature_class":"P",
    "gn:feature_code":"PPL",
    "gn:name":"Novotroitsk",
    "gn:population":0,
    "gn:timezone":"Asia/Novosibirsk",
    "iso:country":"RU",
    "name:rus_x_preferred":[
        "\u041d\u043e\u0432\u043e\u0442\u0440\u043e\u0438\u0446\u043a"
    ],
    "name:und_x_variant":[
        "Pervaya Novotroitskaya",
        "Novo-Toroitskaya",
        "Novaya Troitskaya Pervaya",
        "Novotroitskaya Pervaya",
        "Novotroitsk",
        "Sapozhki"
    ],
    "wof:name":"Novotroitsk",
    "wof:placetype":"locality"
},
  "geometry": {"coordinates":[75.68635999999999,55.00184],"type":"Point"}
}