{
  "type": "Feature",
  "properties": {
    "gn:admin1_code":"33",
    "gn:asciiname":"Vtoroy Lastik",
    "gn:country_code":"RU",
    "gn:dem":150,
    "gn:feature_class":"P",
    "gn:feature_code":"PPL",
    "gn:name":"Vtoroy Lastik",
    "gn:population":0,
    "gn:timezone":"Europe/Kirov",
    "iso:country":"RU",
    "name:rus_x_preferred":[
        "\u0412\u0442\u043e\u0440\u043e\u0439 \u041b\u0430\u0441\u0442\u0438\u043a"
    ],
    "name:und_x_variant":[
        "Lastik Vtoroy",
        "Vtoroy Lastik"
    ],
    "wof:name":"Vtoroy Lastik",
    "wof:placetype":"locality"
},
  "geometry": {"coordinates":[48.4466,57.3145],"type":"Point"}
}