{
  "type": "Feature",
  "properties": {
    "gn:admin1_code":"27",
    "gn:asciiname":"Kart-Dzhurt",
    "gn:country_code":"RU",
    "gn:dem":1291,
    "gn:feature_class":"P",
    "gn:feature_code":"PPL",
    "gn:name":"Kart-Dzhurt",
    "gn:population":0,
    "gn:timezone":"Europe/Moscow",
    "iso:country":"RU",
    "name:eng_x_preferred":[
        "Kart-Dzhurt"
    ],
    "name:nor_x_preferred":[
        "Kart-Dzjurt"
    ],
    "name:rus_x_preferred":[
        "\u041a\u0430\u0440\u0442-\u0414\u0436\u0443\u0440\u0442"
    ],
    "name:und_x_variant":[
        "Gart-Dchiurti",
        "Mtisdziri",
        "Kardzhyurt",
        "Kartdzhyurt"
    ],
    "wof:name":"Kart-Dzhurt",
    "wof:placetype":"locality"
},
  "geometry": {"coordinates":[42.11386,43.50583],"type":"Point"}
}