{
  "type": "Feature",
  "properties": {
    "gn:admin1_code":"60",
    "gn:asciiname":"Sopki",
    "gn:country_code":"RU",
    "gn:dem":207,
    "gn:feature_class":"P",
    "gn:feature_code":"PPL",
    "gn:name":"Sopki",
    "gn:population":0,
    "gn:timezone":"Europe/Moscow",
    "iso:country":"RU",
    "name:rus_x_preferred":[
        "\u0421\u043e\u043f\u043a\u0438"
    ],
    "wof:name":"Sopki",
    "wof:placetype":"locality"
},
  "geometry": {"coordinates":[29.621,56.542],"type":"Point"}
}