{
  "type": "Feature",
  "properties": {
    "gn:admin1_code":"77",
    "gn:asciiname":"Kolotovo",
    "gn:country_code":"RU",
    "gn:dem":178,
    "gn:feature_class":"P",
    "gn:feature_code":"PPL",
    "gn:name":"Kolotovo",
    "gn:population":0,
    "gn:timezone":"Europe/Moscow",
    "iso:country":"RU",
    "name:eng_x_preferred":[
        "Kolotovo"
    ],
    "name:nor_x_preferred":[
        "Zjilotkovo"
    ],
    "name:rus_x_preferred":[
        "\u0416\u0438\u043b\u043e\u0442\u043a\u043e\u0432\u043e"
    ],
    "name:rus_x_variant":[
        "\u041a\u043e\u043b\u043e\u0442\u043e\u0432\u043e"
    ],
    "name:und_x_variant":[
        "\u041a\u043e\u043b\u043e\u0442\u043e\u0432\u043e"
    ],
    "wof:name":"Kolotovo",
    "wof:placetype":"locality"
},
  "geometry": {"coordinates":[34.20941,57.55154],"type":"Point"}
}