{
  "type": "Feature",
  "properties": {
    "gn:admin1_code":"05",
    "gn:asciiname":"Serebryanka",
    "gn:country_code":"RU",
    "gn:dem":232,
    "gn:feature_class":"P",
    "gn:feature_code":"PPL",
    "gn:name":"Serebryanka",
    "gn:population":0,
    "gn:timezone":"Asia/Yakutsk",
    "iso:country":"RU",
    "name:eng_x_preferred":[
        "Serebryanka"
    ],
    "name:nor_x_preferred":[
        "Serebrjanka"
    ],
    "name:rus_x_preferred":[
        "\u0421\u0435\u0440\u0435\u0431\u0440\u044f\u043d\u043a\u0430"
    ],
    "wof:name":"Serebryanka",
    "wof:placetype":"locality"
},
  "geometry": {"coordinates":[127.77786999999999,51.36629],"type":"Point"}
}