{
  "type": "Feature",
  "properties": {
    "gn:admin1_code":"52.0",
    "gn:asciiname":"Glukhoy Berezhok",
    "gn:country_code":"RU",
    "gn:dem":55,
    "gn:feature_class":"P",
    "gn:feature_code":"PPL",
    "gn:name":"Glukhoy Berezhok",
    "gn:population":0,
    "gn:timezone":"Europe/Moscow",
    "iso:country":"RU",
    "name:rus_x_preferred":[
        "\u0413\u043b\u0443\u0445\u043e\u0439 \u0411\u0435\u0440\u0435\u0436\u043e\u043a"
    ],
    "wof:name":"Glukhoy Berezhok",
    "wof:placetype":"locality"
},
  "geometry": {"coordinates":[30.39354,58.47539],"type":"Point"}
}