{
  "type": "Feature",
  "properties": {
    "gn:admin1_code":"77",
    "gn:asciiname":"Gaysma",
    "gn:country_code":"RU",
    "gn:dem":189,
    "gn:feature_class":"P",
    "gn:feature_code":"PPL",
    "gn:name":"Gaysma",
    "gn:population":0,
    "gn:timezone":"Europe/Moscow",
    "iso:country":"RU",
    "name:und_x_variant":[
        "Yakovlevo"
    ],
    "wof:name":"Gaysma",
    "wof:placetype":"locality"
},
  "geometry": {"coordinates":[31.58226,56.26857],"type":"Point"}
}