{
  "type": "Feature",
  "properties": {
    "gn:admin1_code":"33",
    "gn:asciiname":"Zhirnovo",
    "gn:country_code":"RU",
    "gn:dem":124,
    "gn:feature_class":"P",
    "gn:feature_code":"PPL",
    "gn:name":"Zhirnovo",
    "gn:population":0,
    "gn:timezone":"Europe/Kirov",
    "iso:country":"RU",
    "name:eng_x_preferred":[
        "Zhirnovo"
    ],
    "name:nor_x_preferred":[
        "Zjirnovo"
    ],
    "name:rus_x_preferred":[
        "\u0416\u0438\u0440\u043d\u043e\u0432\u043e"
    ],
    "name:und_x_variant":[
        "Bol\u2019shoye Zhirnovo"
    ],
    "wof:name":"Zhirnovo",
    "wof:placetype":"locality"
},
  "geometry": {"coordinates":[51.2351,56.87664],"type":"Point"}
}