{
  "type": "Feature",
  "properties": {
    "gn:admin1_code":"10",
    "gn:asciiname":"Zarech'ye",
    "gn:country_code":"RU",
    "gn:dem":165,
    "gn:feature_class":"P",
    "gn:feature_code":"PPL",
    "gn:name":"Zarech\u2019ye",
    "gn:population":0,
    "gn:timezone":"Europe/Moscow",
    "iso:country":"RU",
    "name:rus_x_preferred":[
        "\u0417\u0430\u0440\u0435\u0447\u044c\u0435"
    ],
    "name:und_x_variant":[
        "Zarech\u2019ye"
    ],
    "wof:name":"Zarech'ye",
    "wof:placetype":"locality"
},
  "geometry": {"coordinates":[33.42879,53.08421],"type":"Point"}
}