{
  "type": "Feature",
  "properties": {
    "gn:admin1_code":"77",
    "gn:asciiname":"Burachikha",
    "gn:country_code":"RU",
    "gn:dem":156,
    "gn:feature_class":"P",
    "gn:feature_code":"PPL",
    "gn:name":"Burachikha",
    "gn:population":0,
    "gn:timezone":"Europe/Moscow",
    "iso:country":"RU",
    "name:rus_x_preferred":[
        "\u0411\u0443\u0440\u0430\u0447\u0438\u0445\u0430"
    ],
    "wof:name":"Burachikha",
    "wof:placetype":"locality"
},
  "geometry": {"coordinates":[36.0484,57.7125],"type":"Point"}
}