{
  "type": "Feature",
  "properties": {
    "gn:country":"RU",
    "gn:fcode":"PPL",
    "gn:pop":3243,
    "iso:country":"RU",
    "name:eng_x_preferred":[
        "Krasnyy Kurgan"
    ],
    "name:nor_x_preferred":[
        "Krasnyj Kurgan"
    ],
    "name:rus_x_preferred":[
        "\u041a\u0440\u0430\u0441\u043d\u044b\u0439 \u041a\u0443\u0440\u0433\u0430\u043d"
    ],
    "name:unk_x_variant":[
        "\u041a\u0440\u0430\u0441\u043d\u044b\u0439 \u041a\u0443\u0440\u0433\u0430\u043d"
    ],
    "qs:name":"Krasnyy Kurgan",
    "qs:photos_9r":0,
    "qs:photos_sr":0,
    "qs:pop_sr":"4",
    "wof:name":"Krasnyy Kurgan",
    "wof:placetype":"locality",
    "wof:population":3243
},
  "geometry": {"coordinates":[42.61083,43.94222],"type":"Point"}
}