{
  "type": "Feature",
  "properties": {
    "gn:admin1_code":"72.0",
    "gn:asciiname":"Savino",
    "gn:country_code":"RU",
    "gn:dem":101,
    "gn:feature_class":"P",
    "gn:feature_code":"PPL",
    "gn:name":"Savino",
    "gn:population":0,
    "gn:timezone":"Europe/Moscow",
    "iso:country":"RU",
    "wof:name":"Savino",
    "wof:placetype":"locality"
},
  "geometry": {"coordinates":[42.3468,51.75377],"type":"Point"}
}