{
  "type": "Feature",
  "properties": {
    "gn:admin1_code":"83",
    "gn:asciiname":"Lesnaya",
    "gn:country_code":"RU",
    "gn:dem":141,
    "gn:feature_class":"P",
    "gn:feature_code":"PPL",
    "gn:name":"Lesnaya",
    "gn:population":0,
    "gn:timezone":"Europe/Moscow",
    "iso:country":"RU",
    "name:rus_x_preferred":[
        "\u041b\u0435\u0441\u043d\u0430\u044f"
    ],
    "name:und_x_variant":[
        "Tryapilovo",
        "Trapilova",
        "Lesnaya",
        "\u041b\u0435\u0441\u043d\u0430\u044f"
    ],
    "wof:name":"Lesnaya",
    "wof:placetype":"locality"
},
  "geometry": {"coordinates":[40.55767,55.72952],"type":"Point"}
}