{
  "type": "Feature",
  "properties": {
    "gn:admin1_code":"73",
    "gn:asciiname":"Naumovo",
    "gn:country_code":"RU",
    "gn:dem":82,
    "gn:feature_class":"P",
    "gn:feature_code":"PPL",
    "gn:name":"Naumovo",
    "gn:population":0,
    "gn:timezone":"Europe/Moscow",
    "iso:country":"RU",
    "name:rus_x_preferred":[
        "\u041d\u0430\u0443\u043c\u043e\u0432\u043e"
    ],
    "wof:name":"Naumovo",
    "wof:placetype":"locality"
},
  "geometry": {"coordinates":[49.90328,55.58],"type":"Point"}
}