{
  "type": "Feature",
  "properties": {
    "gn:admin1_code":"76",
    "gn:asciiname":"Gremyachka",
    "gn:country_code":"RU",
    "gn:dem":207,
    "gn:feature_class":"P",
    "gn:feature_code":"PPL",
    "gn:name":"Gremyachka",
    "gn:population":0,
    "gn:timezone":"Europe/Moscow",
    "iso:country":"RU",
    "name:rus_x_preferred":[
        "\u0413\u0440\u0435\u043c\u044f\u0447\u043a\u0430"
    ],
    "name:und_x_variant":[
        "\u0413\u0440\u0435\u043c\u044f\u0447\u043a\u0430"
    ],
    "wof:name":"Gremyachka",
    "wof:placetype":"locality"
},
  "geometry": {"coordinates":[36.57207,53.55721],"type":"Point"}
}