{
  "type": "Feature",
  "properties": {
    "gn:admin1_code":"67",
    "gn:asciiname":"Trekh-Georgiyevskiy",
    "gn:country_code":"RU",
    "gn:dem":44,
    "gn:feature_class":"P",
    "gn:feature_code":"PPL",
    "gn:name":"Tr\u00ebkh-Georgiyevskiy",
    "gn:population":0,
    "gn:timezone":"Europe/Saratov",
    "iso:country":"RU",
    "wof:name":"Trekh-Georgiyevskiy",
    "wof:placetype":"locality"
},
  "geometry": {"coordinates":[48.23333,52.06667],"type":"Point"}
}