{
  "type": "Feature",
  "properties": {
    "gn:admin1_code":"16.0",
    "gn:asciiname":"Chemercheyevo Pervoye",
    "gn:country_code":"RU",
    "gn:dem":88,
    "gn:feature_class":"P",
    "gn:feature_code":"PPL",
    "gn:name":"Chemercheyevo Pervoye",
    "gn:population":0,
    "gn:timezone":"Europe/Moscow",
    "iso:country":"RU",
    "name:rus_x_preferred":[
        "\u0427\u0435\u043c\u0435\u0440\u0447\u0435\u0435\u0432\u043e \u041f\u0435\u0440\u0432\u043e\u0435"
    ],
    "name:und_x_variant":[
        "Pervoye Chimercheyevo",
        "Chimircheyevo Pervoye",
        "Pervoye Chemercheyevo",
        "Chimircheyevo",
        "Chemercheyevo",
        "Chemercheyevo Pervoye"
    ],
    "wof:name":"Chemercheyevo Pervoye",
    "wof:placetype":"locality"
},
  "geometry": {"coordinates":[47.44843,55.78425],"type":"Point"}
}