{
  "type": "Feature",
  "properties": {
    "gn:admin1_code":"52",
    "gn:asciiname":"Vzvad",
    "gn:country_code":"RU",
    "gn:dem":25,
    "gn:feature_class":"P",
    "gn:feature_code":"PPL",
    "gn:name":"Vzvad",
    "gn:population":0,
    "gn:timezone":"Europe/Moscow",
    "iso:country":"RU",
    "name:eng_x_preferred":[
        "Vzvad"
    ],
    "name:nor_x_preferred":[
        "Vzvad"
    ],
    "name:rus_x_preferred":[
        "\u0412\u0437\u0432\u0430\u0434"
    ],
    "name:und_x_variant":[
        "Vzad",
        "Vzvad"
    ],
    "wof:name":"Vzvad",
    "wof:placetype":"locality"
},
  "geometry": {"coordinates":[31.47146,58.15955],"type":"Point"}
}