{
  "type": "Feature",
  "properties": {
    "gn:admin1_code":"34",
    "gn:asciiname":"Povorot",
    "gn:country_code":"RU",
    "gn:dem":150,
    "gn:feature_class":"P",
    "gn:feature_code":"PPL",
    "gn:name":"Povorot",
    "gn:population":0,
    "gn:timezone":"Europe/Moscow",
    "iso:country":"RU",
    "name:eng_x_preferred":[
        "Povorot"
    ],
    "name:nor_x_preferred":[
        "Povorot"
    ],
    "name:rus_x_preferred":[
        "\u041f\u043e\u0432\u043e\u0440\u043e\u0442"
    ],
    "wof:name":"Povorot",
    "wof:placetype":"locality"
},
  "geometry": {"coordinates":[51.02897,61.0654],"type":"Point"}
}