{
  "type": "Feature",
  "properties": {
    "gn:admin1_code":"4",
    "gn:asciiname":"Svetlyy Luch",
    "gn:country_code":"RU",
    "gn:dem":376,
    "gn:feature_class":"P",
    "gn:feature_code":"PPL",
    "gn:name":"Svetlyy Luch",
    "gn:population":0,
    "gn:timezone":"Asia/Barnaul",
    "iso:country":"RU",
    "wof:name":"Svetlyy Luch",
    "wof:placetype":"locality"
},
  "geometry": {"coordinates":[85.61667,51.95],"type":"Point"}
}