{
  "type": "Feature",
  "properties": {
    "gn:admin1_code":"65",
    "gn:asciiname":"Bereznyaki",
    "gn:country_code":"RU",
    "gn:dem":73,
    "gn:feature_class":"P",
    "gn:feature_code":"PPL",
    "gn:name":"Bereznyaki",
    "gn:population":0,
    "gn:timezone":"Asia/Yekaterinburg",
    "iso:country":"RU",
    "name:rus_x_preferred":[
        "\u0411\u0435\u0440\u0435\u0437\u043d\u044f\u043a\u0438"
    ],
    "name:und_x_variant":[
        "\u0411\u0435\u0440\u0435\u0437\u043d\u044f\u043a\u0438"
    ],
    "wof:name":"Bereznyaki",
    "wof:placetype":"locality"
},
  "geometry": {"coordinates":[52.125,53.4345],"type":"Point"}
}