{
  "type": "Feature",
  "properties": {
    "gn:admin1_code":"40",
    "gn:asciiname":"Gvardeyskaya",
    "gn:country_code":"RU",
    "gn:dem":133,
    "gn:feature_class":"P",
    "gn:feature_code":"PPL",
    "gn:name":"Gvardeyskaya",
    "gn:population":0,
    "gn:timezone":"Asia/Yekaterinburg",
    "iso:country":"RU",
    "name:rus_x_preferred":[
        "\u0413\u0432\u0430\u0440\u0434\u0435\u0439\u0441\u043a\u0430\u044f"
    ],
    "wof:name":"Gvardeyskaya",
    "wof:placetype":"locality"
},
  "geometry": {"coordinates":[67.59472,55.21722],"type":"Point"}
}