{
  "type": "Feature",
  "properties": {
    "gn:admin1_code":"61.0",
    "gn:asciiname":"Karaichev",
    "gn:country_code":"RU",
    "gn:dem":64,
    "gn:feature_class":"P",
    "gn:feature_code":"PPL",
    "gn:name":"Karaichev",
    "gn:population":0,
    "gn:timezone":"Europe/Moscow",
    "iso:country":"RU",
    "name:rus_x_preferred":[
        "\u041a\u0430\u0440\u0430\u0438\u0447\u0435\u0432"
    ],
    "name:und_x_variant":[
        "\u041a\u0430\u0440\u0430\u0438\u0447\u0435\u0432"
    ],
    "wof:name":"Karaichev",
    "wof:placetype":"locality"
},
  "geometry": {"coordinates":[41.51611,48.55944],"type":"Point"}
}