{
  "type": "Feature",
  "properties": {
    "gn:admin1_code":"55",
    "gn:asciiname":"Novaya Volyn'",
    "gn:country_code":"RU",
    "gn:dem":88,
    "gn:feature_class":"P",
    "gn:feature_code":"PPL",
    "gn:name":"Novaya Volyn\u2019",
    "gn:population":0,
    "gn:timezone":"Asia/Yekaterinburg",
    "iso:country":"RU",
    "name:rus_x_preferred":[
        "\u041d\u043e\u0432\u0430\u044f \u0412\u043e\u043b\u044b\u043d\u044c"
    ],
    "name:und_x_variant":[
        "Novaya Volyn\u2019",
        "Volyn\u2019"
    ],
    "wof:name":"Novaya Volyn'",
    "wof:placetype":"locality"
},
  "geometry": {"coordinates":[52.4658,53.4011],"type":"Point"}
}