{
  "type": "Feature",
  "properties": {
    "gn:admin1_code":"28",
    "gn:asciiname":"Pul'cheyla",
    "gn:country_code":"RU",
    "gn:dem":71,
    "gn:feature_class":"P",
    "gn:feature_code":"PPL",
    "gn:name":"Pul\u2019cheyla",
    "gn:population":0,
    "gn:timezone":"Europe/Moscow",
    "iso:country":"RU",
    "name:fin_x_preferred":[
        "Pultsoila"
    ],
    "name:rus_x_preferred":[
        "\u041f\u0443\u043b\u044c\u0447\u0435\u0439\u043b\u0430"
    ],
    "name:und_x_variant":[
        "Pul\u2019cheylo",
        "Pul\u2019cheyla"
    ],
    "wof:name":"Pul'cheyla",
    "wof:placetype":"locality"
},
  "geometry": {"coordinates":[32.49602,61.48736],"type":"Point"}
}