{
  "type": "Feature",
  "properties": {
    "gn:admin1_code":"54",
    "gn:asciiname":"Novotsaritsyno",
    "gn:country_code":"RU",
    "gn:dem":96,
    "gn:feature_class":"P",
    "gn:feature_code":"PPL",
    "gn:name":"Novotsaritsyno",
    "gn:population":0,
    "gn:timezone":"Asia/Omsk",
    "iso:country":"RU",
    "name:eng_x_preferred":[
        "Novotsaritsyno"
    ],
    "name:nor_x_preferred":[
        "Novotsaritsyno"
    ],
    "name:rus_x_preferred":[
        "\u041d\u043e\u0432\u043e\u0446\u0430\u0440\u0438\u0446\u044b\u043d\u043e"
    ],
    "name:und_x_variant":[
        "Novoye Tsaritsyno",
        "Novotsaritsino",
        "\u041d\u043e\u0432\u043e\u0446\u0430\u0440\u0438\u0446\u044b\u043d\u043e",
        "Novotsaritsyno"
    ],
    "wof:name":"Novotsaritsyno",
    "wof:placetype":"locality"
},
  "geometry": {"coordinates":[71.94218000000002,54.66325],"type":"Point"}
}