{
  "type": "Feature",
  "properties": {
    "gn:admin1_code":"73.0",
    "gn:asciiname":"Azyakul'",
    "gn:country_code":"RU",
    "gn:dem":64,
    "gn:feature_class":"P",
    "gn:feature_code":"PPL",
    "gn:name":"Azyakul\u2019",
    "gn:population":0,
    "gn:timezone":"Europe/Moscow",
    "iso:country":"RU",
    "name:nor_x_preferred":[
        "Aziakul"
    ],
    "name:rus_x_preferred":[
        "\u0410\u0437\u044f\u043a\u0443\u043b\u044c"
    ],
    "name:und_x_variant":[
        "Azyakul\u2019"
    ],
    "wof:name":"Azyakul'",
    "wof:placetype":"locality"
},
  "geometry": {"coordinates":[54.01806,55.75149],"type":"Point"}
}