{
  "type": "Feature",
  "properties": {
    "gn:admin1_code":"16",
    "gn:asciiname":"Osinovo",
    "gn:country_code":"RU",
    "gn:dem":141,
    "gn:feature_class":"P",
    "gn:feature_code":"PPL",
    "gn:name":"Osinovo",
    "gn:population":0,
    "gn:timezone":"Europe/Moscow",
    "iso:country":"RU",
    "name:rus_x_preferred":[
        "\u041e\u0441\u0438\u043d\u043e\u0432\u043e"
    ],
    "wof:name":"Osinovo",
    "wof:placetype":"locality"
},
  "geometry": {"coordinates":[46.14265,55.74618],"type":"Point"}
}