{
  "type": "Feature",
  "properties": {
    "gn:admin1_code":"37.0",
    "gn:asciiname":"Bol'shoye Ivashovo",
    "gn:country_code":"RU",
    "gn:dem":149,
    "gn:feature_class":"P",
    "gn:feature_code":"PPL",
    "gn:name":"Bol\u2019shoye Ivashovo",
    "gn:population":0,
    "gn:timezone":"Europe/Moscow",
    "iso:country":"RU",
    "name:rus_x_preferred":[
        "\u0411\u043e\u043b\u044c\u0448\u043e\u0435 \u0418\u0432\u0430\u0448\u043e\u0432\u043e"
    ],
    "name:und_x_variant":[
        "Bol\u2019shoye Ivashovo"
    ],
    "wof:name":"Bol'shoye Ivashovo",
    "wof:placetype":"locality"
},
  "geometry": {"coordinates":[43.00366,58.25455],"type":"Point"}
}