{
  "type": "Feature",
  "properties": {
    "gn:admin1_code":"8",
    "gn:asciiname":"Lomonosovo",
    "gn:country_code":"RU",
    "gn:dem":159,
    "gn:feature_class":"P",
    "gn:feature_code":"PPL",
    "gn:name":"Lomonosovo",
    "gn:population":0,
    "gn:timezone":"Asia/Yekaterinburg",
    "iso:country":"RU",
    "name:rus_x_preferred":[
        "\u041b\u043e\u043c\u043e\u043d\u043e\u0441\u043e\u0432\u043e"
    ],
    "name:sco_x_preferred":[
        "Lomonosovo"
    ],
    "name:und_x_variant":[
        "Lomonosovskoye",
        "Lomonosovka"
    ],
    "wof:name":"Lomonosovo",
    "wof:placetype":"locality"
},
  "geometry": {"coordinates":[55.66937,54.44565],"type":"Point"}
}