{
  "type": "Feature",
  "properties": {
    "gn:admin1_code":"69",
    "gn:asciiname":"Bol'shiye Chaitsy",
    "gn:country_code":"RU",
    "gn:dem":210,
    "gn:feature_class":"P",
    "gn:feature_code":"PPL",
    "gn:name":"Bol\u2019shiye Chaitsy",
    "gn:population":0,
    "gn:timezone":"Europe/Moscow",
    "iso:country":"RU",
    "name:rus_x_preferred":[
        "\u0411\u043e\u043b\u044c\u0448\u0438\u0435 \u0427\u0430\u0438\u0446\u044b"
    ],
    "name:und_x_variant":[
        "Bol\u2019shiye Chaitsy",
        "\u0411\u043e\u043b\u044c\u0448\u0438\u0435 \u0427\u0430\u0438\u0446\u044b"
    ],
    "wof:name":"Bol'shiye Chaitsy",
    "wof:placetype":"locality"
},
  "geometry": {"coordinates":[32.23778,55.36028],"type":"Point"}
}