{
  "type": "Feature",
  "properties": {
    "gn:admin1_code":"83.0",
    "gn:asciiname":"Azikovo",
    "gn:country_code":"RU",
    "gn:dem":154,
    "gn:feature_class":"P",
    "gn:feature_code":"PPL",
    "gn:name":"Azikovo",
    "gn:population":0,
    "gn:timezone":"Europe/Moscow",
    "iso:country":"RU",
    "name:rus_x_preferred":[
        "\u0410\u0437\u0438\u043a\u043e\u0432\u043e"
    ],
    "wof:name":"Azikovo",
    "wof:placetype":"locality"
},
  "geometry": {"coordinates":[40.1319,56.16802],"type":"Point"}
}