{
  "type": "Feature",
  "properties": {
    "gn:admin1_code":"88",
    "gn:asciiname":"Vlasovskaya",
    "gn:country_code":"RU",
    "gn:dem":126,
    "gn:feature_class":"P",
    "gn:feature_code":"PPL",
    "gn:name":"Vlasovskaya",
    "gn:population":0,
    "gn:timezone":"Europe/Moscow",
    "iso:country":"RU",
    "name:rus_x_preferred":[
        "\u0412\u043b\u0430\u0441\u043e\u0432\u0441\u043a\u0430\u044f"
    ],
    "wof:name":"Vlasovskaya",
    "wof:placetype":"locality"
},
  "geometry": {"coordinates":[38.3098,57.8689],"type":"Point"}
}