{
  "type": "Feature",
  "properties": {
    "gn:admin1_code":"71",
    "gn:asciiname":"Pristan'",
    "gn:country_code":"RU",
    "gn:dem":225,
    "gn:feature_class":"P",
    "gn:feature_code":"PPL",
    "gn:name":"Pristan\u2019",
    "gn:population":0,
    "gn:timezone":"Asia/Yekaterinburg",
    "iso:country":"RU",
    "name:eng_x_preferred":[
        "Pristan'"
    ],
    "name:nor_x_preferred":[
        "Pristan"
    ],
    "name:rus_x_preferred":[
        "\u041f\u0440\u0438\u0441\u0442\u0430\u043d\u044c"
    ],
    "name:und_x_variant":[
        "Pristan\u2019"
    ],
    "wof:name":"Pristan'",
    "wof:placetype":"locality"
},
  "geometry": {"coordinates":[58.55726,56.45192],"type":"Point"}
}