{
  "type": "Feature",
  "properties": {
    "gn:admin1_code":"4",
    "gn:asciiname":"Shebalino",
    "gn:country_code":"RU",
    "gn:dem":224,
    "gn:feature_class":"P",
    "gn:feature_code":"PPL",
    "gn:name":"Shebalino",
    "gn:population":0,
    "gn:timezone":"Asia/Barnaul",
    "iso:country":"RU",
    "name:eng_x_preferred":[
        "Shebalino"
    ],
    "name:nor_x_preferred":[
        "Sjebalino"
    ],
    "name:rus_x_preferred":[
        "\u0428\u0435\u0431\u0430\u043b\u0438\u043d\u043e"
    ],
    "name:und_x_variant":[
        "Shabalino",
        "Shebolina"
    ],
    "wof:name":"Shebalino",
    "wof:placetype":"locality"
},
  "geometry": {"coordinates":[85.78921,52.7166],"type":"Point"}
}