{
  "type": "Feature",
  "properties": {
    "gn:admin1_code":"88",
    "gn:asciiname":"Mukhanovo",
    "gn:country_code":"RU",
    "gn:dem":133,
    "gn:feature_class":"P",
    "gn:feature_code":"PPL",
    "gn:name":"Mukhanovo",
    "gn:population":0,
    "gn:timezone":"Europe/Moscow",
    "iso:country":"RU",
    "name:rus_x_preferred":[
        "\u041c\u0443\u0445\u0430\u043d\u043e\u0432\u043e"
    ],
    "wof:name":"Mukhanovo",
    "wof:placetype":"locality"
},
  "geometry": {"coordinates":[37.9733,57.7575],"type":"Point"}
}