{
  "type": "Feature",
  "properties": {
    "gn:admin1_code":"16",
    "gn:asciiname":"Verkhniye Khyrkasy",
    "gn:country_code":"RU",
    "gn:dem":93,
    "gn:feature_class":"P",
    "gn:feature_code":"PPL",
    "gn:name":"Verkhniye Khyrkasy",
    "gn:population":0,
    "gn:timezone":"Europe/Moscow",
    "iso:country":"RU",
    "name:eng_x_preferred":[
        "Verkhniye Khyrkasy"
    ],
    "name:nor_x_preferred":[
        "Verkhn.Khyrkasy"
    ],
    "name:rus_x_preferred":[
        "\u0412\u0435\u0440\u0445\u043d.\u0425\u044b\u0440\u043a\u0430\u0441\u044b"
    ],
    "name:rus_x_variant":[
        "\u0412\u0435\u0440\u0445\u043d\u0438\u0435 \u0425\u044b\u0440\u043a\u0430\u0441\u044b"
    ],
    "name:und_x_variant":[
        "Khyr-Kasy",
        "Verkhniye Khyrkasy"
    ],
    "wof:name":"Verkhniye Khyrkasy",
    "wof:placetype":"locality"
},
  "geometry": {"coordinates":[47.29763,55.86583],"type":"Point"}
}