{
  "type": "Feature",
  "properties": {
    "gn:admin1_code":"88.0",
    "gn:asciiname":"Karganovo",
    "gn:country_code":"RU",
    "gn:dem":97,
    "gn:feature_class":"P",
    "gn:feature_code":"PPL",
    "gn:name":"Karganovo",
    "gn:population":0,
    "gn:timezone":"Europe/Moscow",
    "iso:country":"RU",
    "name:rus_x_preferred":[
        "\u041a\u0430\u0440\u0433\u0430\u043d\u043e\u0432\u043e"
    ],
    "name:und_x_variant":[
        "Karaganovo",
        "Karganovo"
    ],
    "wof:name":"Karganovo",
    "wof:placetype":"locality"
},
  "geometry": {"coordinates":[40.95378,58.24714],"type":"Point"}
}