{
  "type": "Feature",
  "properties": {
    "gn:admin1_code":"47",
    "gn:asciiname":"Medvezh'i Ozera",
    "gn:country_code":"RU",
    "gn:dem":154,
    "gn:feature_class":"P",
    "gn:feature_code":"PPL",
    "gn:name":"Medvezh\u2019i Oz\u00ebra",
    "gn:population":2278,
    "gn:timezone":"Europe/Moscow",
    "iso:country":"RU",
    "name:rus_x_preferred":[
        "\u041c\u0435\u0434\u0432\u0435\u0436\u044c\u0438 \u041e\u0437\u0451\u0440\u0430"
    ],
    "name:und_x_variant":[
        "Medvezh\u2019l Ozera",
        "Medvezh\u2019i Oz\u00ebra",
        "\u041c\u0435\u0434\u0432\u0435\u0436\u044c\u0438 \u041e\u0437\u0451\u0440\u0430"
    ],
    "wof:name":"Medvezh'i Ozera",
    "wof:placetype":"locality",
    "wof:population":2278
},
  "geometry": {"coordinates":[37.98613,55.86935],"type":"Point"}
}