{
  "type": "Feature",
  "properties": {
    "gn:admin1_code":"37.0",
    "gn:asciiname":"Bedrino",
    "gn:country_code":"RU",
    "gn:dem":123,
    "gn:feature_class":"P",
    "gn:feature_code":"PPL",
    "gn:name":"Bedrino",
    "gn:population":0,
    "gn:timezone":"Europe/Moscow",
    "iso:country":"RU",
    "name:nor_x_preferred":[
        "Bedrino"
    ],
    "name:rus_x_preferred":[
        "\u0411\u0435\u0434\u0440\u0438\u043d\u043e"
    ],
    "wof:name":"Bedrino",
    "wof:placetype":"locality"
},
  "geometry": {"coordinates":[41.01417,57.85639000000001],"type":"Point"}
}