{
  "type": "Feature",
  "properties": {
    "gn:admin1_code":"70.0",
    "gn:asciiname":"Trekhkopanskiy",
    "gn:country_code":"RU",
    "gn:dem":176,
    "gn:feature_class":"P",
    "gn:feature_code":"PPL",
    "gn:name":"Trekhkopanskiy",
    "gn:population":0,
    "gn:timezone":"Europe/Moscow",
    "iso:country":"RU",
    "wof:name":"Trekhkopanskiy",
    "wof:placetype":"locality"
},
  "geometry": {"coordinates":[44.54194,44.4275],"type":"Point"}
}