{
  "type": "Feature",
  "properties": {
    "gn:admin1_code":"20",
    "gn:asciiname":"Tutay",
    "gn:country_code":"RU",
    "gn:dem":462,
    "gn:feature_class":"P",
    "gn:feature_code":"PPL",
    "gn:name":"Tutay",
    "gn:population":0,
    "gn:timezone":"Asia/Irkutsk",
    "iso:country":"RU",
    "name:und_x_variant":[
        "Tetay",
        "Tutay"
    ],
    "wof:name":"Tutay",
    "wof:placetype":"locality"
},
  "geometry": {"coordinates":[106.89381000000002,52.99262],"type":"Point"}
}