{
  "type": "Feature",
  "properties": {
    "gn:admin1_code":"77",
    "gn:asciiname":"Shkutki",
    "gn:country_code":"RU",
    "gn:dem":180,
    "gn:feature_class":"P",
    "gn:feature_code":"PPL",
    "gn:name":"Shkutki",
    "gn:population":0,
    "gn:timezone":"Europe/Moscow",
    "iso:country":"RU",
    "name:rus_x_preferred":[
        "\u0428\u043a\u0443\u0442\u043a\u0438"
    ],
    "wof:name":"Shkutki",
    "wof:placetype":"locality"
},
  "geometry": {"coordinates":[32.578,55.7616],"type":"Point"}
}