{
  "type": "Feature",
  "properties": {
    "gn:admin1_code":"67",
    "gn:asciiname":"Novyy Svet",
    "gn:cc2":"RU",
    "gn:country_code":"RU",
    "gn:dem":28,
    "gn:feature_class":"P",
    "gn:feature_code":"PPL",
    "gn:name":"Novyy Svet",
    "gn:population":0,
    "gn:timezone":"Europe/Saratov",
    "iso:country":"RU",
    "name:nor_x_preferred":[
        "Novyj Svet"
    ],
    "name:rus_x_preferred":[
        "\u041d\u043e\u0432\u044b\u0439 \u0421\u0432\u0435\u0442"
    ],
    "name:und_x_variant":[
        "Nizhny Svet",
        "\u041d\u043e\u0432\u044b\u0439 \u0421\u0432\u0435\u0442",
        "Novyy Svet"
    ],
    "wof:name":"Novyy Svet",
    "wof:placetype":"locality"
},
  "geometry": {"coordinates":[49.06667,52.06667],"type":"Point"}
}