{
  "type": "Feature",
  "properties": {
    "gn:admin1_code":"80",
    "gn:asciiname":"Korshevikhino",
    "gn:country_code":"RU",
    "gn:dem":210,
    "gn:feature_class":"P",
    "gn:feature_code":"PPL",
    "gn:name":"Korshevikhino",
    "gn:population":0,
    "gn:timezone":"Europe/Samara",
    "iso:country":"RU",
    "name:rus_x_preferred":[
        "\u041a\u043e\u0440\u0448\u0435\u0432\u0438\u0445\u0438\u043d\u043e"
    ],
    "name:und_x_variant":[
        "Karshevikhino"
    ],
    "wof:name":"Korshevikhino",
    "wof:placetype":"locality"
},
  "geometry": {"coordinates":[52.8681,58.2252],"type":"Point"}
}