{
  "type": "Feature",
  "properties": {
    "gn:admin1_code":"17.0",
    "gn:asciiname":"Novokokhanovskoye",
    "gn:country_code":"RU",
    "gn:dem":-9,
    "gn:feature_class":"P",
    "gn:feature_code":"PPL",
    "gn:name":"Novokokhanovskoye",
    "gn:population":0,
    "gn:timezone":"Europe/Moscow",
    "iso:country":"RU",
    "name:rus_x_preferred":[
        "\u041d\u043e\u0432\u043e\u043a\u043e\u0445\u0430\u043d\u043e\u0432\u0441\u043a\u043e\u0435"
    ],
    "name:und_x_variant":[
        "Novokokhanovskiy",
        "Novokokhanovskoye"
    ],
    "wof:name":"Novokokhanovskoye",
    "wof:placetype":"locality"
},
  "geometry": {"coordinates":[46.65047,43.86405],"type":"Point"}
}