{
  "type": "Feature",
  "properties": {
    "gn:admin1_code":"60",
    "gn:asciiname":"Zhukovo",
    "gn:country_code":"RU",
    "gn:dem":170,
    "gn:feature_class":"P",
    "gn:feature_code":"PPL",
    "gn:name":"Zhukovo",
    "gn:population":0,
    "gn:timezone":"Europe/Moscow",
    "iso:country":"RU",
    "name:rus_x_preferred":[
        "\u0416\u0443\u043a\u043e\u0432\u043e"
    ],
    "wof:name":"Zhukovo",
    "wof:placetype":"locality"
},
  "geometry": {"coordinates":[29.6988,56.1289],"type":"Point"}
}