{
  "type": "Feature",
  "properties": {
    "gn:admin1_code":"85.0",
    "gn:asciiname":"Dereven'ka",
    "gn:country_code":"RU",
    "gn:dem":183,
    "gn:feature_class":"P",
    "gn:feature_code":"PPL",
    "gn:name":"Dereven\u2019ka",
    "gn:population":0,
    "gn:timezone":"Europe/Moscow",
    "iso:country":"RU",
    "name:eng_x_preferred":[
        "Dereven'ka"
    ],
    "name:nor_x_preferred":[
        "Derevenka"
    ],
    "name:rus_x_preferred":[
        "\u0414\u0435\u0440\u0435\u0432\u0435\u043d\u044c\u043a\u0430"
    ],
    "name:und_x_variant":[
        "Dereven\u2019ka"
    ],
    "wof:name":"Dereven'ka",
    "wof:placetype":"locality"
},
  "geometry": {"coordinates":[40.95593,60.48362],"type":"Point"}
}