{
  "type": "Feature",
  "properties": {
    "gn:admin1_code":"21.0",
    "gn:asciiname":"Brodki",
    "gn:country_code":"RU",
    "gn:dem":126,
    "gn:feature_class":"P",
    "gn:feature_code":"PPL",
    "gn:name":"Brodki",
    "gn:population":0,
    "gn:timezone":"Europe/Moscow",
    "iso:country":"RU",
    "name:rus_x_preferred":[
        "\u0411\u0440\u043e\u0434\u043a\u0438"
    ],
    "name:und_x_variant":[
        "\u0411\u0440\u043e\u0434\u043a\u0438"
    ],
    "wof:name":"Brodki",
    "wof:placetype":"locality"
},
  "geometry": {"coordinates":[41.45445,57.29398000000001],"type":"Point"}
}