{
  "type": "Feature",
  "properties": {
    "gn:admin1_code":"7",
    "gn:asciiname":"Poselok Fridrikha Engel'sa",
    "gn:country_code":"RU",
    "gn:dem":-25,
    "gn:feature_class":"P",
    "gn:feature_code":"PPL",
    "gn:name":"Pos\u00eblok Fridrikha Engel\u2019sa",
    "gn:population":0,
    "gn:timezone":"Europe/Astrakhan",
    "iso:country":"RU",
    "name:rus_x_preferred":[
        "\u041f\u043e\u0441\u0451\u043b\u043e\u043a \u0424\u0440\u0438\u0434\u0440\u0438\u0445\u0430 \u042d\u043d\u0433\u0435\u043b\u044c\u0441\u0430"
    ],
    "name:und_x_variant":[
        "Engel\u2019sa",
        "Pos\u00eblok Fridrikha Engel\u2019sa",
        "\u041f\u043e\u0441\u0451\u043b\u043e\u043a \u0424\u0440\u0438\u0434\u0440\u0438\u0445\u0430 \u042d\u043d\u0433\u0435\u043b\u044c\u0441\u0430"
    ],
    "wof:name":"Poselok Fridrikha Engel'sa",
    "wof:placetype":"locality"
},
  "geometry": {"coordinates":[48.11667,46.33333],"type":"Point"}
}