{
  "type": "Feature",
  "properties": {
    "gn:admin1_code":"51",
    "gn:asciiname":"Antsifrovo",
    "gn:country_code":"RU",
    "gn:dem":80,
    "gn:feature_class":"P",
    "gn:feature_code":"PPL",
    "gn:name":"Antsifrovo",
    "gn:population":0,
    "gn:timezone":"Europe/Moscow",
    "iso:country":"RU",
    "name:rus_x_preferred":[
        "\u0410\u043d\u0446\u0438\u0444\u0440\u043e\u0432\u043e"
    ],
    "wof:name":"Antsifrovo",
    "wof:placetype":"locality"
},
  "geometry": {"coordinates":[42.2347,55.6281],"type":"Point"}
}