{
  "type": "Feature",
  "properties": {
    "gn:admin1_code":"25",
    "gn:asciiname":"Poselok Kaluzhskoy Opytnoy Sel'skokhozyaystvennoy Stantsii",
    "gn:country_code":"RU",
    "gn:dem":162,
    "gn:feature_class":"P",
    "gn:feature_code":"PPL",
    "gn:name":"Pos\u00eblok Kaluzhskoy Opytnoy Sel\u2019skokhozyaystvennoy Stantsii",
    "gn:population":0,
    "gn:timezone":"Europe/Moscow",
    "iso:country":"RU",
    "name:nor_x_preferred":[
        "Kaluzjskaja Opytnaja Stantsia"
    ],
    "name:rus_x_preferred":[
        "\u041a\u0430\u043b\u0443\u0436\u0441\u043a\u0430\u044f \u041e\u043f\u044b\u0442\u043d\u0430\u044f \u0421\u0442\u0430\u043d\u0446\u0438\u044f"
    ],
    "name:und_x_variant":[
        "Kaluzhskaya Opytnaya Stantsiya",
        "Opytnoye Pole",
        "Pos\u00eblok Kaluzhskoy Opytnoy Sel\u2019skokhozyaystvennoy Stantsii"
    ],
    "wof:name":"Poselok Kaluzhskoy Opytnoy Sel'skokhozyaystvennoy Stantsii",
    "wof:placetype":"locality"
},
  "geometry": {"coordinates":[36.08692,54.41943000000001],"type":"Point"}
}