{
  "type": "Feature",
  "properties": {
    "gn:country":"RU",
    "gn:fcode":"PPL",
    "gn:pop":200,
    "iso:country":"RU",
    "name:eng_x_preferred":[
        "Sem\u00ebnovka"
    ],
    "name:nor_x_preferred":[
        "Semenovka"
    ],
    "name:rus_x_preferred":[
        "\u0421\u0435\u043c\u0435\u043d\u043e\u0432\u043a\u0430"
    ],
    "name:rus_x_variant":[
        "\u0421\u0435\u043c\u0451\u043d\u043e\u0432\u043a\u0430"
    ],
    "name:sco_x_preferred":[
        "Semyonovka"
    ],
    "name:unk_x_variant":[
        "Semenovskoye"
    ],
    "qs:name":"Sem\u00ebnovka",
    "qs:photos_9r":0,
    "qs:photos_sr":0,
    "qs:pop_sr":"1",
    "wd:wordcount":64,
    "wof:name":"Sem\u00ebnovka",
    "wof:placetype":"locality",
    "wof:population":200
},
  "geometry": {"coordinates":[86.28645,56.87149],"type":"Point"}
}