{
  "type": "Feature",
  "properties": {
    "gn:admin1_code":"73",
    "gn:asciiname":"Khutorskoy",
    "gn:country_code":"RU",
    "gn:dem":301,
    "gn:feature_class":"P",
    "gn:feature_code":"PPL",
    "gn:name":"Khutorskoy",
    "gn:population":0,
    "gn:timezone":"Europe/Moscow",
    "iso:country":"RU",
    "name:rus_x_preferred":[
        "\u0425\u0443\u0442\u043e\u0440\u0441\u043a\u043e\u0439"
    ],
    "wof:name":"Khutorskoy",
    "wof:placetype":"locality"
},
  "geometry": {"coordinates":[52.95,54.65],"type":"Point"}
}