{
  "type": "Feature",
  "properties": {
    "gn:admin1_code":"90",
    "gn:asciiname":"Lopvador",
    "gn:country_code":"RU",
    "gn:dem":172,
    "gn:feature_class":"P",
    "gn:feature_code":"PPL",
    "gn:name":"Lopvador",
    "gn:population":0,
    "gn:timezone":"Asia/Yekaterinburg",
    "iso:country":"RU",
    "name:che_x_preferred":[
        "\u041b\u043e\u043f\u0432\u0430\u0434\u043e\u0440"
    ],
    "name:koi_x_preferred":[
        "\u0412\u043e\u043f\u0430\u0434\u043e\u0440"
    ],
    "name:rus_x_preferred":[
        "\u041b\u043e\u043f\u0432\u0430\u0434\u043e\u0440"
    ],
    "name:und_x_variant":[
        "Lepva-Dor",
        "Lopvador"
    ],
    "wof:name":"Lopvador",
    "wof:placetype":"locality"
},
  "geometry": {"coordinates":[54.3576,59.1335],"type":"Point"}
}