{
  "type": "Feature",
  "properties": {
    "gn:admin1_code":"88",
    "gn:asciiname":"Aleksandrovka Pustyn'",
    "gn:country_code":"RU",
    "gn:dem":134,
    "gn:feature_class":"P",
    "gn:feature_code":"PPL",
    "gn:name":"Aleksandrovka Pustyn\u2019",
    "gn:population":0,
    "gn:timezone":"Europe/Moscow",
    "iso:country":"RU",
    "name:rus_x_preferred":[
        "\u0410\u043b\u0435\u043a\u0441\u0430\u043d\u0434\u0440\u043e\u0432\u043a\u0430 \u041f\u0443\u0441\u0442\u044b\u043d\u044c"
    ],
    "name:und_x_variant":[
        "Aleksandrovka Pustyn\u2019",
        "\u0410\u043b\u0435\u043a\u0441\u0430\u043d\u0434\u0440\u043e\u0432\u043a\u0430 \u041f\u0443\u0441\u0442\u044b\u043d\u044c"
    ],
    "wof:name":"Aleksandrovka Pustyn'",
    "wof:placetype":"locality"
},
  "geometry": {"coordinates":[38.9948,57.8529],"type":"Point"}
}