{
  "type": "Feature",
  "properties": {
    "gn:admin1_code":"91",
    "gn:asciiname":"Dolgovo",
    "gn:country_code":"RU",
    "gn:dem":146,
    "gn:feature_class":"P",
    "gn:feature_code":"PPL",
    "gn:name":"Dolgovo",
    "gn:population":0,
    "gn:timezone":"Asia/Krasnoyarsk",
    "iso:country":"RU",
    "name:eng_x_preferred":[
        "Dolgovo"
    ],
    "name:nor_x_preferred":[
        "Dolgovo"
    ],
    "name:rus_x_preferred":[
        "\u0414\u043e\u043b\u0433\u043e\u0432\u043e"
    ],
    "wof:name":"Dolgovo",
    "wof:placetype":"locality"
},
  "geometry": {"coordinates":[92.3087,57.7278],"type":"Point"}
}