{
  "type": "Feature",
  "properties": {
    "gn:admin1_code":"68.0",
    "gn:asciiname":"Tsalyk",
    "gn:country_code":"RU",
    "gn:dem":470,
    "gn:feature_class":"P",
    "gn:feature_code":"PPL",
    "gn:name":"Tsalyk",
    "gn:population":0,
    "gn:timezone":"Europe/Moscow",
    "iso:country":"RU",
    "name:rus_x_preferred":[
        "\u0426\u0430\u043b\u044b\u043a"
    ],
    "wof:name":"Tsalyk",
    "wof:placetype":"locality"
},
  "geometry": {"coordinates":[44.49081,43.31254000000001],"type":"Point"}
}