{
  "type": "Feature",
  "properties": {
    "gn:admin1_code":"69",
    "gn:asciiname":"Gravatovo",
    "gn:country_code":"RU",
    "gn:dem":236,
    "gn:feature_class":"P",
    "gn:feature_code":"PPL",
    "gn:name":"Gravatovo",
    "gn:population":0,
    "gn:timezone":"Europe/Moscow",
    "iso:country":"RU",
    "name:rus_x_preferred":[
        "\u0413\u0440\u0430\u0432\u0430\u0442\u043e\u0432\u043e"
    ],
    "name:und_x_variant":[
        "\u0413\u0440\u0430\u0432\u0430\u0442\u043e\u0432\u043e"
    ],
    "wof:name":"Gravatovo",
    "wof:placetype":"locality"
},
  "geometry": {"coordinates":[35.26825,55.7946],"type":"Point"}
}