{
  "type": "Feature",
  "properties": {
    "gn:admin1_code":"63",
    "gn:asciiname":"Ugun-Selyay",
    "gn:cc2":"RU",
    "gn:country_code":"RU",
    "gn:dem":11,
    "gn:feature_class":"P",
    "gn:feature_code":"PPL",
    "gn:name":"Ugun-Selyay",
    "gn:population":0,
    "gn:timezone":"Asia/Magadan",
    "iso:country":"RU",
    "name:und_x_variant":[
        "Povarnya Ugun-Selyay",
        "Ugun-Selyay"
    ],
    "wof:name":"Ugun-Selyay",
    "wof:placetype":"locality"
},
  "geometry": {"coordinates":[144.80000000000001,71.06667],"type":"Point"}
}