{
  "type": "Feature",
  "properties": {
    "gn:admin1_code":"88.0",
    "gn:asciiname":"Bol'shiye Chentsy",
    "gn:country_code":"RU",
    "gn:dem":116,
    "gn:feature_class":"P",
    "gn:feature_code":"PPL",
    "gn:name":"Bol\u2019shiye Chentsy",
    "gn:population":0,
    "gn:timezone":"Europe/Moscow",
    "iso:country":"RU",
    "name:rus_x_preferred":[
        "\u0411\u043e\u043b\u044c\u0448\u0438\u0435 \u0427\u0435\u043d\u0446\u044b"
    ],
    "name:und_x_variant":[
        "Bol\u2019shiye Chentsy",
        "Bol\u2019shoye Cheptsovo"
    ],
    "wof:name":"Bol'shiye Chentsy",
    "wof:placetype":"locality"
},
  "geometry": {"coordinates":[38.19201,58.06795],"type":"Point"}
}