{
  "type": "Feature",
  "properties": {
    "gn:admin1_code":"47",
    "gn:asciiname":"Yegor'yevskoye",
    "gn:country_code":"RU",
    "gn:dem":206,
    "gn:feature_class":"P",
    "gn:feature_code":"PPL",
    "gn:name":"Yegor\u2019yevskoye",
    "gn:population":0,
    "gn:timezone":"Europe/Moscow",
    "iso:country":"RU",
    "name:rus_x_preferred":[
        "\u0415\u0433\u043e\u0440\u044c\u0435\u0432\u0441\u043a\u043e\u0435"
    ],
    "name:und_x_variant":[
        "Yegor\u2019yevskoye",
        "\u0415\u0433\u043e\u0440\u044c\u0435\u0432\u0441\u043a\u043e\u0435"
    ],
    "wof:name":"Yegor'yevskoye",
    "wof:placetype":"locality"
},
  "geometry": {"coordinates":[36.5738,56.0874],"type":"Point"}
}