{
  "type": "Feature",
  "properties": {
    "gn:admin1_code":"62",
    "gn:asciiname":"Yefremovo",
    "gn:country_code":"RU",
    "gn:dem":131,
    "gn:feature_class":"P",
    "gn:feature_code":"PPL",
    "gn:name":"Yefremovo",
    "gn:population":0,
    "gn:timezone":"Europe/Moscow",
    "iso:country":"RU",
    "name:rus_x_preferred":[
        "\u0415\u0444\u0440\u0435\u043c\u043e\u0432\u043e"
    ],
    "wof:name":"Yefremovo",
    "wof:placetype":"locality"
},
  "geometry": {"coordinates":[40.1003,54.1147],"type":"Point"}
}