{
  "type": "Feature",
  "properties": {
    "gn:admin1_code":"8",
    "gn:asciiname":"Verovka",
    "gn:country_code":"RU",
    "gn:dem":345,
    "gn:feature_class":"P",
    "gn:feature_code":"PPL",
    "gn:name":"Verovka",
    "gn:population":0,
    "gn:timezone":"Asia/Yekaterinburg",
    "iso:country":"RU",
    "name:eng_x_preferred":[
        "Verovka"
    ],
    "name:nor_x_preferred":[
        "Verovka"
    ],
    "name:rus_x_preferred":[
        "\u0412\u0435\u0440\u043e\u0432\u043a\u0430"
    ],
    "name:und_x_variant":[
        "\u0412\u0435\u0440\u043e\u0432\u043a\u0430"
    ],
    "wof:name":"Verovka",
    "wof:placetype":"locality"
},
  "geometry": {"coordinates":[54.53333000000001,54.16667],"type":"Point"}
}