{
  "type": "Feature",
  "properties": {
    "gn:admin1_code":"62",
    "gn:asciiname":"Pashkino",
    "gn:country_code":"RU",
    "gn:dem":105,
    "gn:feature_class":"P",
    "gn:feature_code":"PPL",
    "gn:name":"Pashkino",
    "gn:population":0,
    "gn:timezone":"Europe/Moscow",
    "iso:country":"RU",
    "name:rus_x_preferred":[
        "\u041f\u0430\u0448\u043a\u0438\u043d\u043e"
    ],
    "wof:name":"Pashkino",
    "wof:placetype":"locality"
},
  "geometry": {"coordinates":[40.9406,54.1456],"type":"Point"}
}