{
  "type": "Feature",
  "properties": {
    "gn:admin1_code":"12.0",
    "gn:asciiname":"Gezenchu",
    "gn:country_code":"RU",
    "gn:dem":610,
    "gn:feature_class":"P",
    "gn:feature_code":"PPL",
    "gn:name":"Gezenchu",
    "gn:population":0,
    "gn:timezone":"Europe/Moscow",
    "iso:country":"RU",
    "name:che_x_preferred":[
        "Gezen\u00e7u"
    ],
    "name:rus_x_preferred":[
        "\u0413\u0435\u0437\u0435\u043d\u0447\u0443"
    ],
    "name:und_x_variant":[
        "Gezinchu",
        "Gezenchu"
    ],
    "wof:name":"Gezenchu",
    "wof:placetype":"locality"
},
  "geometry": {"coordinates":[46.16908,43.05215],"type":"Point"}
}