{
  "type": "Feature",
  "properties": {
    "gn:admin1_code":"24.0",
    "gn:asciiname":"Godzhur",
    "gn:country_code":"RU",
    "gn:dem":67,
    "gn:feature_class":"P",
    "gn:feature_code":"PPL",
    "gn:name":"Godzhur",
    "gn:population":0,
    "gn:timezone":"Europe/Moscow",
    "iso:country":"RU",
    "name:rus_x_preferred":[
        "\u0413\u043e\u0434\u0436\u0443\u0440"
    ],
    "wof:name":"Godzhur",
    "wof:placetype":"locality"
},
  "geometry": {"coordinates":[44.49361,46.65333],"type":"Point"}
}