{
  "type": "Feature",
  "properties": {
    "gn:admin1_code":"10",
    "gn:asciiname":"Pokhval'nyy",
    "gn:country_code":"RU",
    "gn:dem":159,
    "gn:feature_class":"P",
    "gn:feature_code":"PPL",
    "gn:name":"Pokhval\u2019nyy",
    "gn:population":0,
    "gn:timezone":"Europe/Moscow",
    "iso:country":"RU",
    "name:rus_x_preferred":[
        "\u041f\u043e\u0445\u0432\u0430\u043b\u044c\u043d\u044b\u0439"
    ],
    "name:und_x_variant":[
        "Pokhval\u2019nyy"
    ],
    "wof:name":"Pokhval'nyy",
    "wof:placetype":"locality"
},
  "geometry": {"coordinates":[33.7439,53.477],"type":"Point"}
}