{
  "type": "Feature",
  "properties": {
    "gn:admin1_code":"33.0",
    "gn:asciiname":"Krayukhi",
    "gn:country_code":"RU",
    "gn:dem":153,
    "gn:feature_class":"P",
    "gn:feature_code":"PPL",
    "gn:name":"Krayukhi",
    "gn:population":0,
    "gn:timezone":"Europe/Kirov",
    "iso:country":"RU",
    "name:rus_x_preferred":[
        "\u041a\u0440\u0430\u044e\u0445\u0438"
    ],
    "wof:name":"Krayukhi",
    "wof:placetype":"locality"
},
  "geometry": {"coordinates":[50.54641,58.19276],"type":"Point"}
}