{
  "type": "Feature",
  "properties": {
    "gn:admin1_code":"52.0",
    "gn:asciiname":"Avdeyevo",
    "gn:country_code":"RU",
    "gn:dem":165,
    "gn:feature_class":"P",
    "gn:feature_code":"PPL",
    "gn:name":"Avdeyevo",
    "gn:population":0,
    "gn:timezone":"Europe/Moscow",
    "iso:country":"RU",
    "name:nor_x_preferred":[
        "Avdejevo"
    ],
    "name:rus_x_preferred":[
        "\u0410\u0432\u0434\u0435\u0435\u0432\u043e"
    ],
    "name:ukr_x_preferred":[
        "\u0410\u0432\u0434\u0456\u0457\u0432\u043e"
    ],
    "wof:name":"Avdeyevo",
    "wof:placetype":"locality"
},
  "geometry": {"coordinates":[33.27559,58.24879],"type":"Point"}
}