{
  "type": "Feature",
  "properties": {
    "gn:admin1_code":"55.0",
    "gn:asciiname":"Dobropol'ye",
    "gn:country_code":"RU",
    "gn:dem":285,
    "gn:feature_class":"P",
    "gn:feature_code":"PPL",
    "gn:name":"Dobropol\u2019ye",
    "gn:population":0,
    "gn:timezone":"Asia/Yekaterinburg",
    "iso:country":"RU",
    "name:rus_x_preferred":[
        "\u0414\u043e\u0431\u0440\u043e\u043f\u043e\u043b\u044c\u0435"
    ],
    "name:und_x_variant":[
        "Dobropol\u2019ye"
    ],
    "wof:name":"Dobropol'ye",
    "wof:placetype":"locality"
},
  "geometry": {"coordinates":[59.71666999999999,52.08333],"type":"Point"}
}