{
  "type": "Feature",
  "properties": {
    "gn:admin1_code":"81.0",
    "gn:asciiname":"Bol'shaya Kandarat'",
    "gn:country_code":"RU",
    "gn:dem":145,
    "gn:feature_class":"P",
    "gn:feature_code":"PPL",
    "gn:name":"Bol\u2019shaya Kandarat\u2019",
    "gn:population":0,
    "gn:timezone":"Europe/Ulyanovsk",
    "iso:country":"RU",
    "name:rus_x_preferred":[
        "\u0411\u043e\u043b\u044c\u0448\u0430\u044f \u041a\u0430\u043d\u0434\u0430\u0440\u0430\u0442\u044c"
    ],
    "name:und_x_variant":[
        "Bol\u2019shaya Kondorat\u2019",
        "Bol\u2019shaya Kandarat\u2019"
    ],
    "wof:name":"Bol'shaya Kandarat'",
    "wof:placetype":"locality"
},
  "geometry": {"coordinates":[46.97761,54.39907],"type":"Point"}
}