{
  "type": "Feature",
  "properties": {
    "gn:admin1_code":"47",
    "gn:asciiname":"Avdulovo Vtoroye",
    "gn:country_code":"RU",
    "gn:dem":162,
    "gn:feature_class":"P",
    "gn:feature_code":"PPL",
    "gn:name":"Avdulovo Vtoroye",
    "gn:population":0,
    "gn:timezone":"Europe/Moscow",
    "iso:country":"RU",
    "name:nor_x_preferred":[
        "Avdulovo Vtoroje"
    ],
    "name:rus_x_preferred":[
        "\u0410\u0432\u0434\u0443\u043b\u043e\u0432\u043e \u0412\u0442\u043e\u0440\u043e\u0435"
    ],
    "wof:name":"Avdulovo Vtoroye",
    "wof:placetype":"locality"
},
  "geometry": {"coordinates":[38.26766,55.08048],"type":"Point"}
}