{
  "type": "Feature",
  "properties": {
    "gn:admin1_code":"54",
    "gn:asciiname":"Bernyazhka",
    "gn:country_code":"RU",
    "gn:dem":70,
    "gn:feature_class":"P",
    "gn:feature_code":"PPL",
    "gn:name":"Bernyazhka",
    "gn:population":0,
    "gn:timezone":"Asia/Omsk",
    "iso:country":"RU",
    "name:eng_x_preferred":[
        "Bernyazhka"
    ],
    "name:nor_x_preferred":[
        "Bernjazjka"
    ],
    "name:rus_x_preferred":[
        "\u0411\u0435\u0440\u043d\u044f\u0436\u043a\u0430"
    ],
    "wof:name":"Bernyazhka",
    "wof:placetype":"locality"
},
  "geometry": {"coordinates":[74.57460999999998,56.62277],"type":"Point"}
}