{
  "type": "Feature",
  "properties": {
    "gn:admin1_code":"77",
    "gn:asciiname":"Kortsovo",
    "gn:country_code":"RU",
    "gn:dem":205,
    "gn:feature_class":"P",
    "gn:feature_code":"PPL",
    "gn:name":"Kortsovo",
    "gn:population":0,
    "gn:timezone":"Europe/Moscow",
    "iso:country":"RU",
    "name:rus_x_preferred":[
        "\u041a\u043e\u0440\u0446\u043e\u0432\u043e"
    ],
    "name:und_x_variant":[
        "Kartsovo",
        "Kortsovo"
    ],
    "wof:name":"Kortsovo",
    "wof:placetype":"locality"
},
  "geometry": {"coordinates":[34.64183,56.98806999999999],"type":"Point"}
}