{
  "type": "Feature",
  "properties": {
    "gn:admin1_code":"32",
    "gn:asciiname":"Bobrovka",
    "gn:country_code":"RU",
    "gn:dem":45,
    "gn:feature_class":"P",
    "gn:feature_code":"PPL",
    "gn:name":"Bobrovka",
    "gn:population":0,
    "gn:timezone":"Asia/Yekaterinburg",
    "iso:country":"RU",
    "name:rus_x_preferred":[
        "\u0411\u043e\u0431\u0440\u043e\u0432\u043a\u0430"
    ],
    "name:und_x_variant":[
        "\u0411\u043e\u0431\u0440\u043e\u0432\u043a\u0430"
    ],
    "wof:name":"Bobrovka",
    "wof:placetype":"locality"
},
  "geometry": {"coordinates":[69.93333,60.03333000000001],"type":"Point"}
}