{
  "type": "Feature",
  "properties": {
    "gn:admin1_code":"41",
    "gn:asciiname":"Rzhava",
    "gn:cc2":"RU",
    "gn:country_code":"RU",
    "gn:dem":144,
    "gn:feature_class":"P",
    "gn:feature_code":"PPL",
    "gn:name":"Rzhava",
    "gn:population":0,
    "gn:timezone":"Europe/Moscow",
    "iso:country":"RU",
    "name:rus_x_preferred":[
        "\u0420\u0436\u0430\u0432\u0430"
    ],
    "name:und_x_variant":[
        "Rzhavo",
        "Rzhava"
    ],
    "wof:name":"Rzhava",
    "wof:placetype":"locality"
},
  "geometry": {"coordinates":[34.66417,51.40278],"type":"Point"}
}