{
  "type": "Feature",
  "properties": {
    "gn:admin1_code":"59",
    "gn:asciiname":"Belembe",
    "gn:country_code":"RU",
    "gn:dem":1,
    "gn:feature_class":"P",
    "gn:feature_code":"PPL",
    "gn:name":"Belembe",
    "gn:population":0,
    "gn:timezone":"Asia/Vladivostok",
    "iso:country":"RU",
    "name:rus_x_preferred":[
        "\u0411\u0435\u043b\u0435\u043c\u0431\u0435"
    ],
    "wof:name":"Belembe",
    "wof:placetype":"locality"
},
  "geometry": {"coordinates":[136.96556000000001,45.28833],"type":"Point"}
}