{
  "type": "Feature",
  "properties": {
    "gn:admin1_code":"61",
    "gn:asciiname":"Rubashkin",
    "gn:cc2":"RU",
    "gn:country_code":"RU",
    "gn:dem":156,
    "gn:feature_class":"P",
    "gn:feature_code":"PPL",
    "gn:name":"Rubashkin",
    "gn:population":0,
    "gn:timezone":"Europe/Moscow",
    "iso:country":"RU",
    "name:rus_x_preferred":[
        "\u0420\u0443\u0431\u0430\u0448\u043a\u0438\u043d"
    ],
    "name:und_x_variant":[
        "Khutor Rubashkin",
        "Rubashkin",
        "\u0420\u0443\u0431\u0430\u0448\u043a\u0438\u043d"
    ],
    "wof:name":"Rubashkin",
    "wof:placetype":"locality"
},
  "geometry": {"coordinates":[41.70361,49.04],"type":"Point"}
}