{
  "type": "Feature",
  "properties": {
    "gn:admin1_code":"60",
    "gn:asciiname":"Bor-Gudanovo",
    "gn:country_code":"RU",
    "gn:dem":72,
    "gn:feature_class":"P",
    "gn:feature_code":"PPL",
    "gn:name":"Bor-Gudanovo",
    "gn:population":0,
    "gn:timezone":"Europe/Moscow",
    "iso:country":"RU",
    "name:rus_x_preferred":[
        "\u0411\u043e\u0440-\u0413\u0443\u0434\u0430\u043d\u043e\u0432\u043e"
    ],
    "wof:name":"Bor-Gudanovo",
    "wof:placetype":"locality"
},
  "geometry": {"coordinates":[28.9722,57.12571],"type":"Point"}
}