{
  "type": "Feature",
  "properties": {
    "gn:admin1_code":"33.0",
    "gn:asciiname":"Lesouchastok Dvadtsat' Dva Kilometr",
    "gn:country_code":"RU",
    "gn:dem":260,
    "gn:feature_class":"P",
    "gn:feature_code":"PPL",
    "gn:name":"Lesouchastok Dvadtsat\u2019 Dva Kilometr",
    "gn:population":0,
    "gn:timezone":"Europe/Kirov",
    "iso:country":"RU",
    "name:rus_x_preferred":[
        "\u041b\u0435\u0441\u043e\u0443\u0447\u0430\u0441\u0442\u043e\u043a \u0414\u0432\u0430\u0434\u0446\u0430\u0442\u044c \u0414\u0432\u0430 \u041a\u0438\u043b\u043e\u043c\u0435\u0442\u0440"
    ],
    "name:und_x_variant":[
        "Lesouchastok Dvadtsat\u2019 Dva Kilometr"
    ],
    "wof:name":"Lesouchastok Dvadtsat' Dva Kilometr",
    "wof:placetype":"locality"
},
  "geometry": {"coordinates":[51.878,58.6459],"type":"Point"}
}