{
  "type": "Feature",
  "properties": {
    "gn:admin1_code":"42",
    "gn:asciiname":"Goyanshchina",
    "gn:country_code":"RU",
    "gn:dem":90,
    "gn:feature_class":"P",
    "gn:feature_code":"PPL",
    "gn:name":"Goyanshchina",
    "gn:population":0,
    "gn:timezone":"Europe/Moscow",
    "iso:country":"RU",
    "name:rus_x_preferred":[
        "\u0413\u043e\u044f\u043d\u0449\u0438\u043d\u0430"
    ],
    "wof:name":"Goyanshchina",
    "wof:placetype":"locality"
},
  "geometry": {"coordinates":[28.37966,59.01075],"type":"Point"}
}