{
  "type": "Feature",
  "properties": {
    "gn:admin1_code":"84",
    "gn:asciiname":"Pavlenko",
    "gn:country_code":"RU",
    "gn:dem":26,
    "gn:feature_class":"P",
    "gn:feature_code":"PPL",
    "gn:name":"Pavlenko",
    "gn:population":0,
    "gn:timezone":"Europe/Volgograd",
    "iso:country":"RU",
    "name:rus_x_preferred":[
        "\u041f\u0430\u0432\u043b\u0435\u043d\u043a\u043e"
    ],
    "name:und_x_variant":[
        "\u041f\u0430\u0432\u043b\u0435\u043d\u043a\u043e"
    ],
    "wof:name":"Pavlenko",
    "wof:placetype":"locality"
},
  "geometry": {"coordinates":[45.86667,49.66667],"type":"Point"}
}