{
  "type": "Feature",
  "properties": {
    "gn:admin1_code":"81.0",
    "gn:asciiname":"Dmitriyevo-Pomryaskino",
    "gn:country_code":"RU",
    "gn:dem":68,
    "gn:feature_class":"P",
    "gn:feature_code":"PPL",
    "gn:name":"Dmitriyevo-Pomryaskino",
    "gn:population":0,
    "gn:timezone":"Europe/Ulyanovsk",
    "iso:country":"RU",
    "name:eng_x_preferred":[
        "Dmitriyevo-Pomryaskino"
    ],
    "name:nor_x_preferred":[
        "Dmitrijevo-Pomrjaskino"
    ],
    "name:rus_x_preferred":[
        "\u0414\u043c\u0438\u0442\u0440\u0438\u0435\u0432\u043e-\u041f\u043e\u043c\u0440\u044f\u0441\u043a\u0438\u043d\u043e"
    ],
    "wof:name":"Dmitriyevo-Pomryaskino",
    "wof:placetype":"locality"
},
  "geometry": {"coordinates":[48.92789000000001,54.43697],"type":"Point"}
}