{
  "type": "Feature",
  "properties": {
    "gn:admin1_code":"10",
    "gn:asciiname":"Verebsk",
    "gn:country_code":"RU",
    "gn:dem":206,
    "gn:feature_class":"P",
    "gn:feature_code":"PPL",
    "gn:name":"Verebsk",
    "gn:population":0,
    "gn:timezone":"Europe/Moscow",
    "iso:country":"RU",
    "name:eng_x_preferred":[
        "Verebsk"
    ],
    "name:nor_x_preferred":[
        "Verebskoje"
    ],
    "name:rus_x_preferred":[
        "\u0412\u0435\u0440\u0435\u0431\u0441\u043a\u043e\u0435"
    ],
    "name:und_x_variant":[
        "Verebskoye",
        "Verebskiy"
    ],
    "wof:name":"Verebsk",
    "wof:placetype":"locality"
},
  "geometry": {"coordinates":[34.93834,52.66811],"type":"Point"}
}