{
  "type": "Feature",
  "properties": {
    "gn:admin1_code":"8.0",
    "gn:asciiname":"Davletkulovo",
    "gn:country_code":"RU",
    "gn:dem":180,
    "gn:feature_class":"P",
    "gn:feature_code":"PPL",
    "gn:name":"Davletkulovo",
    "gn:population":0,
    "gn:timezone":"Asia/Yekaterinburg",
    "iso:country":"RU",
    "name:rus_x_preferred":[
        "\u0414\u0430\u0432\u043b\u0435\u0442\u043a\u0443\u043b\u043e\u0432\u043e"
    ],
    "wof:name":"Davletkulovo",
    "wof:placetype":"locality"
},
  "geometry": {"coordinates":[55.7626,53.287],"type":"Point"}
}