{
  "type": "Feature",
  "properties": {
    "gn:admin1_code":"73",
    "gn:asciiname":"Novaya Tura",
    "gn:country_code":"RU",
    "gn:dem":97,
    "gn:feature_class":"P",
    "gn:feature_code":"PPL",
    "gn:name":"Novaya Tura",
    "gn:population":0,
    "gn:timezone":"Europe/Moscow",
    "iso:country":"RU",
    "name:rus_x_preferred":[
        "\u041d\u043e\u0432\u0430\u044f \u0422\u0443\u0440\u0430"
    ],
    "name:und_x_variant":[
        "Tura",
        "Novaya Tura",
        "\u041d\u043e\u0432\u0430\u044f \u0422\u0443\u0440\u0430"
    ],
    "wof:name":"Novaya Tura",
    "wof:placetype":"locality"
},
  "geometry": {"coordinates":[48.84354,55.86901999999999],"type":"Point"}
}