{
  "type": "Feature",
  "properties": {
    "gn:admin1_code":"05",
    "gn:asciiname":"Busse",
    "gn:country_code":"RU",
    "gn:dem":159,
    "gn:feature_class":"P",
    "gn:feature_code":"PPL",
    "gn:name":"Busse",
    "gn:population":0,
    "gn:timezone":"Asia/Yakutsk",
    "iso:country":"RU",
    "name:deu_x_preferred":[
        "Busse"
    ],
    "name:eng_x_preferred":[
        "Busse"
    ],
    "name:epo_x_preferred":[
        "Busse"
    ],
    "name:nor_x_preferred":[
        "Busse"
    ],
    "name:rus_x_preferred":[
        "\u0411\u0443\u0441\u0441\u0435"
    ],
    "wof:name":"Busse",
    "wof:placetype":"locality"
},
  "geometry": {"coordinates":[126.92104999999999,51.22636],"type":"Point"}
}