{
  "type": "Feature",
  "properties": {
    "gn:admin1_code":"67.0",
    "gn:asciiname":"Malaya Topolevka",
    "gn:country_code":"RU",
    "gn:dem":18,
    "gn:feature_class":"P",
    "gn:feature_code":"PPL",
    "gn:name":"Malaya Topol\u00ebvka",
    "gn:population":0,
    "gn:timezone":"Europe/Saratov",
    "iso:country":"RU",
    "wof:name":"Malaya Topolevka",
    "wof:placetype":"locality"
},
  "geometry": {"coordinates":[46.2914,51.57212],"type":"Point"}
}