{
  "type": "Feature",
  "properties": {
    "gn:admin1_code":"33",
    "gn:asciiname":"Zakharovskiy Vystavok",
    "gn:country_code":"RU",
    "gn:dem":145,
    "gn:feature_class":"P",
    "gn:feature_code":"PPL",
    "gn:name":"Zakharovskiy Vystavok",
    "gn:population":0,
    "gn:timezone":"Europe/Kirov",
    "iso:country":"RU",
    "name:rus_x_preferred":[
        "\u0417\u0430\u0445\u0430\u0440\u043e\u0432\u0441\u043a\u0438\u0439 \u0412\u044b\u0441\u0442\u0430\u0432\u043e\u043a"
    ],
    "wof:name":"Zakharovskiy Vystavok",
    "wof:placetype":"locality"
},
  "geometry": {"coordinates":[48.40412,60.38236],"type":"Point"}
}