{
  "type": "Feature",
  "properties": {
    "gn:admin1_code":"53",
    "gn:asciiname":"Kochkovatyy",
    "gn:country_code":"RU",
    "gn:dem":109,
    "gn:feature_class":"P",
    "gn:feature_code":"PPL",
    "gn:name":"Kochkovatyy",
    "gn:population":0,
    "gn:timezone":"Asia/Novosibirsk",
    "iso:country":"RU",
    "name:rus_x_preferred":[
        "\u041a\u043e\u0447\u043a\u043e\u0432\u0430\u0442\u044b\u0439"
    ],
    "name:und_x_variant":[
        "\u041a\u043e\u0447\u043a\u043e\u0432\u0430\u0442\u044b\u0439"
    ],
    "wof:name":"Kochkovatyy",
    "wof:placetype":"locality"
},
  "geometry": {"coordinates":[76.66667,55.41667],"type":"Point"}
}