{
  "type": "Feature",
  "properties": {
    "gn:admin1_code":"20",
    "gn:asciiname":"Turgenevka",
    "gn:country_code":"RU",
    "gn:dem":755,
    "gn:feature_class":"P",
    "gn:feature_code":"PPL",
    "gn:name":"Turgenevka",
    "gn:population":0,
    "gn:timezone":"Asia/Irkutsk",
    "iso:country":"RU",
    "name:eng_x_preferred":[
        "Turgenevka"
    ],
    "name:nor_x_preferred":[
        "Turgenevka"
    ],
    "name:rus_x_preferred":[
        "\u0422\u0443\u0440\u0433\u0435\u043d\u0435\u0432\u043a\u0430"
    ],
    "name:und_x_variant":[
        "Turgeneva",
        "Turgenevka",
        "\u0422\u0443\u0440\u0433\u0435\u043d\u0435\u0432\u043a\u0430"
    ],
    "wof:name":"Turgenevka",
    "wof:placetype":"locality"
},
  "geometry": {"coordinates":[105.67417,53.0275],"type":"Point"}
}