{
  "type": "Feature",
  "properties": {
    "gn:admin1_code":"45.0",
    "gn:asciiname":"Kamichi",
    "gn:country_code":"RU",
    "gn:dem":138,
    "gn:feature_class":"P",
    "gn:feature_code":"PPL",
    "gn:name":"Kamichi",
    "gn:population":0,
    "gn:timezone":"Europe/Moscow",
    "iso:country":"RU",
    "name:cat_x_preferred":[
        "Kamichi"
    ],
    "name:rus_x_preferred":[
        "\u041a\u0430\u043c\u0438\u0447\u0438"
    ],
    "wof:name":"Kamichi",
    "wof:placetype":"locality"
},
  "geometry": {"coordinates":[48.5407,57.0977],"type":"Point"}
}