{
  "type": "Feature",
  "properties": {
    "gn:admin1_code":"51",
    "gn:asciiname":"Krasnyy Kirpichnik",
    "gn:country_code":"RU",
    "gn:dem":165,
    "gn:feature_class":"P",
    "gn:feature_code":"PPL",
    "gn:name":"Krasnyy Kirpichnik",
    "gn:population":0,
    "gn:timezone":"Europe/Moscow",
    "iso:country":"RU",
    "name:rus_x_preferred":[
        "\u041a\u0440\u0430\u0441\u043d\u044b\u0439 \u041a\u0438\u0440\u043f\u0438\u0447\u043d\u0438\u043a"
    ],
    "name:und_x_variant":[
        "\u041a\u0440\u0430\u0441\u043d\u044b\u0439 \u041a\u0438\u0440\u043f\u0438\u0447\u043d\u0438\u043a"
    ],
    "wof:name":"Krasnyy Kirpichnik",
    "wof:placetype":"locality"
},
  "geometry": {"coordinates":[46.6716,57.6552],"type":"Point"}
}