{
  "type": "Feature",
  "properties": {
    "gn:admin1_code":"81.0",
    "gn:asciiname":"Akhmetley",
    "gn:country_code":"RU",
    "gn:dem":217,
    "gn:feature_class":"P",
    "gn:feature_code":"PPL",
    "gn:name":"Akhmetley",
    "gn:population":0,
    "gn:timezone":"Europe/Ulyanovsk",
    "iso:country":"RU",
    "name:eng_x_preferred":[
        "Akhmetley"
    ],
    "name:nor_x_preferred":[
        "Akhmetlej"
    ],
    "name:rus_x_preferred":[
        "\u0410\u0445\u043c\u0435\u0442\u043b\u0435\u0439"
    ],
    "name:und_x_variant":[
        "\u0410\u0445\u043c\u0435\u0442\u043b\u0435\u0439",
        "Akhmetley"
    ],
    "wof:name":"Akhmetley",
    "wof:placetype":"locality"
},
  "geometry": {"coordinates":[46.98793,53.23839],"type":"Point"}
}