{
  "type": "Feature",
  "properties": {
    "gn:admin1_code":"16",
    "gn:asciiname":"Shinary",
    "gn:country_code":"RU",
    "gn:dem":130,
    "gn:feature_class":"P",
    "gn:feature_code":"PPL",
    "gn:name":"Shinary",
    "gn:population":0,
    "gn:timezone":"Europe/Moscow",
    "iso:country":"RU",
    "name:rus_x_preferred":[
        "\u0428\u0438\u043d\u0430\u0440\u044b"
    ],
    "name:und_x_variant":[
        "Shinery",
        "Shinary",
        "\u0428\u0438\u043d\u0430\u0440\u044b"
    ],
    "wof:name":"Shinary",
    "wof:placetype":"locality"
},
  "geometry": {"coordinates":[47.19482,55.84219],"type":"Point"}
}