{
  "type": "Feature",
  "properties": {
    "gn:admin1_code":"16",
    "gn:asciiname":"Murzakasy",
    "gn:country_code":"RU",
    "gn:dem":169,
    "gn:feature_class":"P",
    "gn:feature_code":"PPL",
    "gn:name":"Murzakasy",
    "gn:population":0,
    "gn:timezone":"Europe/Moscow",
    "iso:country":"RU",
    "name:rus_x_preferred":[
        "\u041c\u0443\u0440\u0437\u0430\u043a\u0430\u0441\u044b"
    ],
    "wof:name":"Murzakasy",
    "wof:placetype":"locality"
},
  "geometry": {"coordinates":[46.49246,55.99223000000001],"type":"Point"}
}