{
  "type": "Feature",
  "properties": {
    "gn:admin1_code":"54",
    "gn:asciiname":"Tavrichanka",
    "gn:country_code":"RU",
    "gn:dem":110,
    "gn:feature_class":"P",
    "gn:feature_code":"PPL",
    "gn:name":"Tavrichanka",
    "gn:population":0,
    "gn:timezone":"Asia/Omsk",
    "iso:country":"RU",
    "name:che_x_preferred":[
        "\u0422\u0430\u0432\u0440\u0438\u0447\u0430\u043d\u043a\u0430"
    ],
    "name:eng_x_preferred":[
        "Tavrichanka"
    ],
    "name:nor_x_preferred":[
        "Tavritsjanka"
    ],
    "name:rus_x_preferred":[
        "\u0422\u0430\u0432\u0440\u0438\u0447\u0430\u043d\u043a\u0430"
    ],
    "name:und_x_variant":[
        "\u0422\u0430\u0432\u0440\u0438\u0447\u0430\u043d\u043a\u0430"
    ],
    "wof:name":"Tavrichanka",
    "wof:placetype":"locality"
},
  "geometry": {"coordinates":[72.76989,55.45716],"type":"Point"}
}