{
  "type": "Feature",
  "properties": {
    "gn:admin1_code":"91",
    "gn:asciiname":"Stalino",
    "gn:country_code":"RU",
    "gn:dem":196,
    "gn:feature_class":"P",
    "gn:feature_code":"PPL",
    "gn:name":"Stalino",
    "gn:population":0,
    "gn:timezone":"Asia/Krasnoyarsk",
    "iso:country":"RU",
    "name:rus_x_preferred":[
        "\u0421\u0442\u0430\u043b\u0438\u043d\u043e"
    ],
    "wof:name":"Stalino",
    "wof:placetype":"locality"
},
  "geometry": {"coordinates":[98.33333,60.38333000000001],"type":"Point"}
}