{
  "type": "Feature",
  "properties": {
    "gn:admin1_code":"90",
    "gn:asciiname":"Sgorki",
    "gn:cc2":"RU",
    "gn:country_code":"RU",
    "gn:dem":155,
    "gn:feature_class":"P",
    "gn:feature_code":"PPL",
    "gn:name":"Sgorki",
    "gn:population":0,
    "gn:timezone":"Asia/Yekaterinburg",
    "iso:country":"RU",
    "name:nor_x_preferred":[
        "Sgorki"
    ],
    "name:rus_x_preferred":[
        "\u0421\u0433\u043e\u0440\u043a\u0438"
    ],
    "name:und_x_variant":[
        "Sgorky",
        "Sgorki"
    ],
    "wof:name":"Sgorki",
    "wof:placetype":"locality"
},
  "geometry": {"coordinates":[56.73333,58.95],"type":"Point"}
}