{
  "type": "Feature",
  "properties": {
    "gn:admin1_code":"33",
    "gn:asciiname":"Khozikha",
    "gn:country_code":"RU",
    "gn:dem":203,
    "gn:feature_class":"P",
    "gn:feature_code":"PPL",
    "gn:name":"Khozikha",
    "gn:population":0,
    "gn:timezone":"Europe/Kirov",
    "iso:country":"RU",
    "name:rus_x_preferred":[
        "\u0425\u043e\u0437\u0438\u0445\u0430"
    ],
    "wof:name":"Khozikha",
    "wof:placetype":"locality"
},
  "geometry": {"coordinates":[49.7133,57.8565],"type":"Point"}
}