{
  "type": "Feature",
  "properties": {
    "gn:admin1_code":"05",
    "gn:asciiname":"Kivdo-Tyukan",
    "gn:country_code":"RU",
    "gn:dem":148,
    "gn:feature_class":"P",
    "gn:feature_code":"PPL",
    "gn:name":"Kivdo-Tyukan",
    "gn:population":0,
    "gn:timezone":"Asia/Yakutsk",
    "iso:country":"RU",
    "name:che_x_preferred":[
        "\u041a\u0438\u0432\u0434\u043e-\u0422\u044e\u043a\u0430\u043d"
    ],
    "name:eng_x_preferred":[
        "Kivdo-Tyukan"
    ],
    "name:nor_x_preferred":[
        "Kivda-Tjukan"
    ],
    "name:rus_x_preferred":[
        "\u041a\u0438\u0432\u0434\u0430-\u0422\u044e\u043a\u0430\u043d"
    ],
    "name:rus_x_variant":[
        "\u041a\u0438\u0432\u0434\u043e-\u0422\u044e\u043a\u0430\u043d"
    ],
    "name:tgk_x_preferred":[
        "\u041a\u0438\u0432\u0434\u043e-\u0422\u044e\u043a\u0430\u043d"
    ],
    "name:und_x_variant":[
        "Pravyy Tyukan",
        "Kivdo-Tyukan"
    ],
    "wof:name":"Kivdo-Tyukan",
    "wof:placetype":"locality"
},
  "geometry": {"coordinates":[129.68211000000002,49.84855],"type":"Point"}
}