{
  "type": "Feature",
  "properties": {
    "gn:admin1_code":"62",
    "gn:asciiname":"Ibredskiy",
    "gn:country_code":"RU",
    "gn:dem":119,
    "gn:feature_class":"P",
    "gn:feature_code":"PPL",
    "gn:name":"Ibredskiy",
    "gn:population":0,
    "gn:timezone":"Europe/Moscow",
    "iso:country":"RU",
    "name:eng_x_preferred":[
        "Iberdskiy"
    ],
    "name:nor_x_preferred":[
        "Iberdskij"
    ],
    "name:rus_x_preferred":[
        "\u0418\u0431\u0440\u0435\u0434\u0441\u043a\u0438\u0439"
    ],
    "name:und_x_variant":[
        "Iberdskiy",
        "Ibredskiy"
    ],
    "wof:name":"Ibredskiy",
    "wof:placetype":"locality"
},
  "geometry": {"coordinates":[40.2362,53.8597],"type":"Point"}
}