{
  "type": "Feature",
  "properties": {
    "gn:admin1_code":"69",
    "gn:asciiname":"Kharinka",
    "gn:country_code":"RU",
    "gn:dem":227,
    "gn:feature_class":"P",
    "gn:feature_code":"PPL",
    "gn:name":"Kharinka",
    "gn:population":0,
    "gn:timezone":"Europe/Moscow",
    "iso:country":"RU",
    "name:rus_x_preferred":[
        "\u0425\u0430\u0440\u0438\u043d\u043aa"
    ],
    "name:und_x_variant":[
        "Kharinki",
        "Kharinka"
    ],
    "wof:name":"Kharinka",
    "wof:placetype":"locality"
},
  "geometry": {"coordinates":[32.33434,54.57522],"type":"Point"}
}