{
  "type": "Feature",
  "properties": {
    "gn:admin1_code":"28",
    "gn:asciiname":"Lad-Vara",
    "gn:country_code":"RU",
    "gn:dem":204,
    "gn:feature_class":"P",
    "gn:feature_code":"PPL",
    "gn:name":"Lad-Vara",
    "gn:population":0,
    "gn:timezone":"Europe/Moscow",
    "iso:country":"RU",
    "name:fin_x_preferred":[
        "Lautavaara"
    ],
    "name:rus_x_preferred":[
        "\u041b\u0430\u0434-\u0412\u0430\u0440\u0430"
    ],
    "wof:name":"Lad-Vara",
    "wof:placetype":"locality"
},
  "geometry": {"coordinates":[31.93333,63.05],"type":"Point"}
}