{
  "type": "Feature",
  "properties": {
    "gn:admin1_code":"4",
    "gn:asciiname":"Solyanoozernoye",
    "gn:cc2":"RU",
    "gn:country_code":"RU",
    "gn:dem":161,
    "gn:feature_class":"P",
    "gn:feature_code":"PPL",
    "gn:name":"Solyanooz\u00ebrnoye",
    "gn:population":0,
    "gn:timezone":"Asia/Barnaul",
    "iso:country":"RU",
    "name:rus_x_preferred":[
        "\u0421\u043e\u043b\u044f\u043d\u043e\u043e\u0437\u0451\u0440\u043d\u043e\u0435"
    ],
    "name:und_x_variant":[
        "Soleno-Ozerny",
        "Solenoozernoye",
        "Solyanooz\u00ebrnoye"
    ],
    "wof:name":"Solyanoozernoye",
    "wof:placetype":"locality"
},
  "geometry": {"coordinates":[79.58333,51.68333],"type":"Point"}
}