{
  "type": "Feature",
  "properties": {
    "gn:admin1_code":"77",
    "gn:asciiname":"Merloshki",
    "gn:country_code":"RU",
    "gn:dem":286,
    "gn:feature_class":"P",
    "gn:feature_code":"PPL",
    "gn:name":"Merloshki",
    "gn:population":0,
    "gn:timezone":"Europe/Moscow",
    "iso:country":"RU",
    "wof:name":"Merloshki",
    "wof:placetype":"locality"
},
  "geometry": {"coordinates":[33.569,56.28436],"type":"Point"}
}