{
  "type": "Feature",
  "properties": {
    "gn:admin1_code":"10",
    "gn:asciiname":"Zhdanovo",
    "gn:country_code":"RU",
    "gn:dem":152,
    "gn:feature_class":"P",
    "gn:feature_code":"PPL",
    "gn:name":"Zhdanovo",
    "gn:population":0,
    "gn:timezone":"Europe/Moscow",
    "iso:country":"RU",
    "name:rus_x_preferred":[
        "\u0414\u043e\u0440\u043a\u043e\u0432"
    ],
    "name:rus_x_variant":[
        "\u0416\u0434\u0430\u043d\u043e\u0432\u043e"
    ],
    "name:und_x_variant":[
        "Dorkov",
        "\u0414\u043e\u0440\u043a\u043e\u0432",
        "Zhdanovo"
    ],
    "wof:name":"Zhdanovo",
    "wof:placetype":"locality"
},
  "geometry": {"coordinates":[34.10722,52.76333],"type":"Point"}
}