{
  "type": "Feature",
  "properties": {
    "gn:admin1_code":"69",
    "gn:asciiname":"Volkovichi",
    "gn:country_code":"RU",
    "gn:dem":190,
    "gn:feature_class":"P",
    "gn:feature_code":"PPL",
    "gn:name":"Volkovichi",
    "gn:population":0,
    "gn:timezone":"Europe/Moscow",
    "iso:country":"RU",
    "name:rus_x_preferred":[
        "\u0412\u043e\u043b\u043a\u043e\u0432\u0438\u0447\u0438"
    ],
    "name:und_x_variant":[
        "\u0412\u043e\u043b\u043a\u043e\u0432\u0438\u0447\u0438"
    ],
    "wof:name":"Volkovichi",
    "wof:placetype":"locality"
},
  "geometry": {"coordinates":[33.03667,53.89556],"type":"Point"}
}