{
  "type": "Feature",
  "properties": {
    "gn:admin1_code":"85",
    "gn:asciiname":"Nefedovo",
    "gn:country_code":"RU",
    "gn:dem":129,
    "gn:feature_class":"P",
    "gn:feature_code":"PPL",
    "gn:name":"Nef\u00ebdovo",
    "gn:population":0,
    "gn:timezone":"Europe/Moscow",
    "iso:country":"RU",
    "name:rus_x_preferred":[
        "\u041d\u0435\u0444\u0451\u0434\u043e\u0432\u043e"
    ],
    "name:und_x_variant":[
        "Nef\u00ebdovo"
    ],
    "wof:name":"Nefedovo",
    "wof:placetype":"locality"
},
  "geometry": {"coordinates":[40.79609,58.85219],"type":"Point"}
}