{
  "type": "Feature",
  "properties": {
    "gn:admin1_code":"77.0",
    "gn:asciiname":"Galtnikha",
    "gn:country_code":"RU",
    "gn:dem":172,
    "gn:feature_class":"P",
    "gn:feature_code":"PPL",
    "gn:name":"Galtnikha",
    "gn:population":0,
    "gn:timezone":"Europe/Moscow",
    "iso:country":"RU",
    "name:rus_x_preferred":[
        "\u0413\u0430\u043b\u0442\u043d\u0438\u0445\u0430"
    ],
    "wof:name":"Galtnikha",
    "wof:placetype":"locality"
},
  "geometry": {"coordinates":[35.08333,58.08333],"type":"Point"}
}