{
  "type": "Feature",
  "properties": {
    "gn:admin1_code":"84.0",
    "gn:asciiname":"Budarin",
    "gn:country_code":"RU",
    "gn:dem":23,
    "gn:feature_class":"P",
    "gn:feature_code":"PPL",
    "gn:name":"Budarin",
    "gn:population":0,
    "gn:timezone":"Europe/Volgograd",
    "iso:country":"RU",
    "name:rus_x_preferred":[
        "\u0411\u0443\u0434\u0430\u0440\u0438\u043d"
    ],
    "name:und_x_variant":[
        "\u0411\u0443\u0434\u0430\u0440\u0438\u043d"
    ],
    "wof:name":"Budarin",
    "wof:placetype":"locality"
},
  "geometry": {"coordinates":[45.46667,49.18333],"type":"Point"}
}