{
  "type": "Feature",
  "properties": {
    "gn:admin1_code":"65",
    "gn:asciiname":"Srednyaya Orlyanka",
    "gn:country_code":"RU",
    "gn:dem":71,
    "gn:feature_class":"P",
    "gn:feature_code":"PPL",
    "gn:name":"Srednyaya Orlyanka",
    "gn:population":0,
    "gn:timezone":"Europe/Samara",
    "iso:country":"RU",
    "name:eng_x_preferred":[
        "Srednyaya Orlyanka"
    ],
    "name:nor_x_preferred":[
        "Srednjaja Orljanka"
    ],
    "name:rus_x_preferred":[
        "\u0421\u0440\u0435\u0434\u043d\u044f\u044f \u041e\u0440\u043b\u044f\u043d\u043a\u0430"
    ],
    "wof:name":"Srednyaya Orlyanka",
    "wof:placetype":"locality"
},
  "geometry": {"coordinates":[50.9764,53.77956999999999],"type":"Point"}
}