{
  "type": "Feature",
  "properties": {
    "gn:admin1_code":"25",
    "gn:asciiname":"Uspekh",
    "gn:country_code":"RU",
    "gn:dem":207,
    "gn:feature_class":"P",
    "gn:feature_code":"PPL",
    "gn:name":"Uspekh",
    "gn:population":0,
    "gn:timezone":"Europe/Moscow",
    "iso:country":"RU",
    "name:che_x_preferred":[
        "\u0423\u0441\u043f\u0435\u0445"
    ],
    "name:rus_x_preferred":[
        "\u0423\u0441\u043f\u0435\u0445"
    ],
    "name:tgk_x_preferred":[
        "\u0423\u0441\u043f\u0435\u0445"
    ],
    "wof:name":"Uspekh",
    "wof:placetype":"locality"
},
  "geometry": {"coordinates":[33.79991,54.4649],"type":"Point"}
}