{
  "type": "Feature",
  "properties": {
    "gn:admin1_code":"33",
    "gn:asciiname":"Urzhum",
    "gn:country_code":"RU",
    "gn:dem":120,
    "gn:feature_class":"P",
    "gn:feature_code":"PPL",
    "gn:name":"Urzhum",
    "gn:population":0,
    "gn:timezone":"Europe/Kirov",
    "iso:country":"RU",
    "name:rus_x_preferred":[
        "\u0423\u0440\u0436\u0443\u043c"
    ],
    "name:und_x_variant":[
        "\u0423\u0440\u0436\u0443\u043c"
    ],
    "wof:name":"Urzhum",
    "wof:placetype":"locality"
},
  "geometry": {"coordinates":[46.9676,57.1177],"type":"Point"}
}