{
  "type": "Feature",
  "properties": {
    "gn:admin1_code":"42.0",
    "gn:asciiname":"Protasovka",
    "gn:country_code":"RU",
    "gn:dem":91,
    "gn:feature_class":"P",
    "gn:feature_code":"PPL",
    "gn:name":"Protasovka",
    "gn:population":0,
    "gn:timezone":"Europe/Moscow",
    "iso:country":"RU",
    "name:rus_x_preferred":[
        "\u041f\u0440\u043e\u0442\u0430\u0441\u043e\u0432\u043a\u0430"
    ],
    "name:und_x_variant":[
        "\u041f\u0440\u043e\u0442\u0430\u0441\u043e\u0432\u043a\u0430"
    ],
    "wof:name":"Protasovka",
    "wof:placetype":"locality"
},
  "geometry": {"coordinates":[30.1125,59.30722],"type":"Point"}
}