{
  "type": "Feature",
  "properties": {
    "gn:admin1_code":"76",
    "gn:asciiname":"Lupishki",
    "gn:country_code":"RU",
    "gn:dem":157,
    "gn:feature_class":"P",
    "gn:feature_code":"PPL",
    "gn:name":"Lupishki",
    "gn:population":0,
    "gn:timezone":"Europe/Moscow",
    "iso:country":"RU",
    "name:rus_x_preferred":[
        "\u041b\u0443\u043f\u0438\u0448\u043a\u0438"
    ],
    "name:und_x_variant":[
        "\u041b\u0443\u043f\u0438\u0448\u043a\u0438"
    ],
    "wof:name":"Lupishki",
    "wof:placetype":"locality"
},
  "geometry": {"coordinates":[38.49800000000001,53.87217],"type":"Point"}
}