{
  "type": "Feature",
  "properties": {
    "gn:admin1_code":"60.0",
    "gn:asciiname":"Gorokhovo",
    "gn:country_code":"RU",
    "gn:dem":96,
    "gn:feature_class":"P",
    "gn:feature_code":"PPL",
    "gn:name":"Gorokhovo",
    "gn:population":0,
    "gn:timezone":"Europe/Moscow",
    "iso:country":"RU",
    "name:rus_x_preferred":[
        "\u0413\u043e\u0440\u043e\u0445\u043e\u0432\u043e"
    ],
    "wof:name":"Gorokhovo",
    "wof:placetype":"locality"
},
  "geometry": {"coordinates":[28.59182,56.7138],"type":"Point"}
}