{
  "type": "Feature",
  "properties": {
    "gn:admin1_code":"8",
    "gn:asciiname":"Ozerki",
    "gn:country_code":"RU",
    "gn:dem":238,
    "gn:feature_class":"P",
    "gn:feature_code":"PPL",
    "gn:name":"Ozerki",
    "gn:population":0,
    "gn:timezone":"Asia/Yekaterinburg",
    "iso:country":"RU",
    "name:rus_x_preferred":[
        "\u041e\u0437\u0435\u0440\u043a\u0438"
    ],
    "name:und_x_variant":[
        "\u041e\u0437\u0435\u0440\u043a\u0438"
    ],
    "wof:name":"Ozerki",
    "wof:placetype":"locality"
},
  "geometry": {"coordinates":[55.78333000000001,52.91667],"type":"Point"}
}