{
  "type": "Feature",
  "properties": {
    "gn:admin1_code":"88.0",
    "gn:asciiname":"Shchekoldino",
    "gn:country_code":"RU",
    "gn:dem":140,
    "gn:feature_class":"P",
    "gn:feature_code":"PPL",
    "gn:name":"Shchekoldino",
    "gn:population":0,
    "gn:timezone":"Europe/Moscow",
    "iso:country":"RU",
    "name:rus_x_preferred":[
        "\u0429\u0435\u043a\u043e\u043b\u0434\u0438\u043d\u043e"
    ],
    "name:und_x_variant":[
        "\u0429\u0435\u043a\u043e\u043b\u0434\u0438\u043d\u043e"
    ],
    "wof:name":"Shchekoldino",
    "wof:placetype":"locality"
},
  "geometry": {"coordinates":[40.23028,58.42511999999999],"type":"Point"}
}