{
  "type": "Feature",
  "properties": {
    "gn:admin1_code":"47",
    "gn:asciiname":"Shiryayevo",
    "gn:country_code":"RU",
    "gn:dem":134,
    "gn:feature_class":"P",
    "gn:feature_code":"PPL",
    "gn:name":"Shiryayevo",
    "gn:population":0,
    "gn:timezone":"Europe/Moscow",
    "iso:country":"RU",
    "name:rus_x_preferred":[
        "\u0428\u0438\u0440\u044f\u0435\u0432\u043e"
    ],
    "name:und_x_variant":[
        "\u0428\u0438\u0440\u044f\u0435\u0432\u043e"
    ],
    "wof:name":"Shiryayevo",
    "wof:placetype":"locality"
},
  "geometry": {"coordinates":[39.73503,55.31171],"type":"Point"}
}