{
  "type": "Feature",
  "properties": {
    "gn:admin1_code":"33.0",
    "gn:asciiname":"Krysy",
    "gn:country_code":"RU",
    "gn:dem":175,
    "gn:feature_class":"P",
    "gn:feature_code":"PPL",
    "gn:name":"Krysy",
    "gn:population":0,
    "gn:timezone":"Europe/Kirov",
    "iso:country":"RU",
    "name:rus_x_preferred":[
        "\u041a\u0440\u044b\u0441\u044b"
    ],
    "name:und_x_variant":[
        "\u041a\u0440\u044b\u0441\u044b"
    ],
    "wof:name":"Krysy",
    "wof:placetype":"locality"
},
  "geometry": {"coordinates":[48.34,59.17639000000001],"type":"Point"}
}