{
  "type": "Feature",
  "properties": {
    "gn:admin1_code":"77",
    "gn:asciiname":"Glintsovo",
    "gn:country_code":"RU",
    "gn:dem":137,
    "gn:feature_class":"P",
    "gn:feature_code":"PPL",
    "gn:name":"Glintsovo",
    "gn:population":0,
    "gn:timezone":"Europe/Moscow",
    "iso:country":"RU",
    "name:rus_x_preferred":[
        "\u0413\u043b\u0438\u043d\u0446\u043e\u0432\u043e"
    ],
    "name:und_x_variant":[
        "\u0413\u043b\u0438\u043d\u0446\u043e\u0432\u043e"
    ],
    "wof:name":"Glintsovo",
    "wof:placetype":"locality"
},
  "geometry": {"coordinates":[36.9266,57.0314],"type":"Point"}
}