{
  "type": "Feature",
  "properties": {
    "gn:admin1_code":"88",
    "gn:asciiname":"Likharevo",
    "gn:country_code":"RU",
    "gn:dem":134,
    "gn:feature_class":"P",
    "gn:feature_code":"PPL",
    "gn:name":"Likhar\u00ebvo",
    "gn:population":0,
    "gn:timezone":"Europe/Moscow",
    "iso:country":"RU",
    "name:eng_x_preferred":[
        "Likhar\u00ebvo"
    ],
    "name:nor_x_preferred":[
        "Likharevo"
    ],
    "name:rus_x_preferred":[
        "\u041b\u0438\u0445\u0430\u0440\u0435\u0432\u043e"
    ],
    "name:rus_x_variant":[
        "\u041b\u0438\u0445\u0430\u0440\u0451\u0432\u043e"
    ],
    "name:und_x_variant":[
        "Likhar\u00ebvo",
        "\u041b\u0438\u0445\u0430\u0440\u0451\u0432\u043e"
    ],
    "wof:name":"Likharevo",
    "wof:placetype":"locality"
},
  "geometry": {"coordinates":[38.23333,56.96666999999999],"type":"Point"}
}