{
  "type": "Feature",
  "properties": {
    "gn:admin1_code":"62",
    "gn:asciiname":"Sobakino",
    "gn:country_code":"RU",
    "gn:dem":160,
    "gn:feature_class":"P",
    "gn:feature_code":"PPL",
    "gn:name":"Sobakino",
    "gn:population":0,
    "gn:timezone":"Europe/Moscow",
    "iso:country":"RU",
    "name:rus_x_preferred":[
        "\u0421\u043e\u0431\u0430\u043a\u0438\u043d\u043e"
    ],
    "name:und_x_variant":[
        "\u0421\u043e\u0431\u0430\u043a\u0438\u043d\u043e"
    ],
    "wof:name":"Sobakino",
    "wof:placetype":"locality"
},
  "geometry": {"coordinates":[41.55232,54.93953000000001],"type":"Point"}
}