{
  "type": "Feature",
  "properties": {
    "gn:admin1_code":"76",
    "gn:asciiname":"Dar'inka",
    "gn:country_code":"RU",
    "gn:dem":199,
    "gn:feature_class":"P",
    "gn:feature_code":"PPL",
    "gn:name":"Dar\u2019inka",
    "gn:population":0,
    "gn:timezone":"Europe/Moscow",
    "iso:country":"RU",
    "name:rus_x_preferred":[
        "\u0414\u0430\u0440\u044c\u0438\u043d\u043a\u0430"
    ],
    "name:und_x_variant":[
        "Dar\u2019inka",
        "\u0414\u0430\u0440\u044c\u0438\u043d\u043a\u0430"
    ],
    "wof:name":"Dar'inka",
    "wof:placetype":"locality"
},
  "geometry": {"coordinates":[36.92972,53.76667],"type":"Point"}
}