{
  "type": "Feature",
  "properties": {
    "gn:country":"RU",
    "gn:fcode":"PPL",
    "gn:pop":5184,
    "iso:country":"RU",
    "name:arm_x_preferred":[
        "\u053f\u0561\u0580\u0561\u056b\u0564\u0565\u056c"
    ],
    "name:bak_x_preferred":[
        "\u04a0\u0430\u0440\u0438\u0499\u0435\u043b"
    ],
    "name:dut_x_preferred":[
        "Karaidel"
    ],
    "name:eng_x_preferred":[
        "Karaidel'"
    ],
    "name:gre_x_preferred":[
        "\u039a\u03b1\u03c1\u03b1\u03ca\u03bd\u03c4\u03ad\u03bb"
    ],
    "name:nor_x_preferred":[
        "Karaidel"
    ],
    "name:rus_x_preferred":[
        "\u041a\u0430\u0440\u0430\u0438\u0434\u0435\u043b\u044c"
    ],
    "name:tat_x_preferred":[
        "\u041a\u0430\u0440\u0430\u0438\u0434\u0435\u043b"
    ],
    "name:unk_x_variant":[
        "\u041a\u0430\u0440\u0430\u0438\u0434\u0435\u043b\u044c"
    ],
    "qs:name":"Karaidel'",
    "qs:name_adm0":"Russia",
    "qs:name_adm1":"Bashkortostan Republic",
    "qs:photos_9k":1,
    "qs:photos_9r":1,
    "qs:photos_all":4,
    "qs:photos_sr":0,
    "qs:placetype":"Town",
    "qs:pop_sr":"5",
    "wd:wordcount":1083,
    "wof:name":"Karaidel'",
    "wof:placetype":"locality",
    "wof:population":5184
},
  "geometry": {"coordinates":[56.90692,55.83372],"type":"Point"}
}