{
  "type": "Feature",
  "properties": {
    "gn:admin1_code":"85",
    "gn:asciiname":"Tepen'kino",
    "gn:country_code":"RU",
    "gn:dem":113,
    "gn:feature_class":"P",
    "gn:feature_code":"PPL",
    "gn:name":"Tepen\u2019kino",
    "gn:population":0,
    "gn:timezone":"Europe/Moscow",
    "iso:country":"RU",
    "name:rus_x_preferred":[
        "\u0422\u0435\u0440\u0435\u043d\u044c\u043a\u0438\u043d\u043e"
    ],
    "name:und_x_variant":[
        "Tepen\u2019kino"
    ],
    "wof:name":"Tepen'kino",
    "wof:placetype":"locality"
},
  "geometry": {"coordinates":[39.9611,59.2217],"type":"Point"}
}