{
  "type": "Feature",
  "properties": {
    "gn:admin1_code":"38",
    "gn:asciiname":"Verkhne Yurt",
    "gn:country_code":"RU",
    "gn:dem":39,
    "gn:feature_class":"P",
    "gn:feature_code":"PPL",
    "gn:name":"Verkhne Yurt",
    "gn:population":0,
    "gn:timezone":"Europe/Moscow",
    "iso:country":"RU",
    "name:und_x_variant":[
        "Razdol\u2019noye",
        "Verkhne Yurt"
    ],
    "wof:name":"Verkhne Yurt",
    "wof:placetype":"locality"
},
  "geometry": {"coordinates":[39.74813,43.63634],"type":"Point"}
}