{
  "type": "Feature",
  "properties": {
    "gn:admin1_code":"42.0",
    "gn:asciiname":"Desyatskoye",
    "gn:country_code":"RU",
    "gn:dem":116,
    "gn:feature_class":"P",
    "gn:feature_code":"PPL",
    "gn:name":"Desyatskoye",
    "gn:population":0,
    "gn:timezone":"Europe/Moscow",
    "iso:country":"RU",
    "name:rus_x_preferred":[
        "\u0414\u0435\u0441\u044f\u0442\u0441\u043a\u043e\u0435"
    ],
    "name:und_x_variant":[
        "\u0414\u0435\u0441\u044f\u0442\u0441\u043a\u043e\u0435"
    ],
    "wof:name":"Desyatskoye",
    "wof:placetype":"locality"
},
  "geometry": {"coordinates":[29.41667,59.75],"type":"Point"}
}