{
  "type": "Feature",
  "properties": {
    "gn:admin1_code":"12.0",
    "gn:asciiname":"Baskhoy",
    "gn:country_code":"RU",
    "gn:dem":1940,
    "gn:feature_class":"P",
    "gn:feature_code":"PPL",
    "gn:name":"Baskhoy",
    "gn:population":0,
    "gn:timezone":"Europe/Moscow",
    "iso:country":"RU",
    "name:nor_x_preferred":[
        "Baskhoj"
    ],
    "name:rus_x_preferred":[
        "\u0411\u0430\u0441\u0445\u043e\u0439"
    ],
    "wof:name":"Baskhoy",
    "wof:placetype":"locality"
},
  "geometry": {"coordinates":[45.97917,42.71222],"type":"Point"}
}