{
  "type": "Feature",
  "properties": {
    "gn:admin1_code":"62.0",
    "gn:asciiname":"Pobedinka",
    "gn:country_code":"RU",
    "gn:dem":189,
    "gn:feature_class":"P",
    "gn:feature_code":"PPL",
    "gn:name":"Pobedinka",
    "gn:population":0,
    "gn:timezone":"Europe/Moscow",
    "iso:country":"RU",
    "name:che_x_preferred":[
        "\u041f\u043e\u0431\u0435\u0434\u0438\u043d\u043a\u0430"
    ],
    "name:hye_x_preferred":[
        "\u054a\u0578\u0562\u0565\u0564\u056b\u0576\u056f\u0561"
    ],
    "name:rus_x_preferred":[
        "\u041f\u043e\u0431\u0435\u0434\u0438\u043d\u043a\u0430"
    ],
    "name:und_x_variant":[
        "Pobedinskiy"
    ],
    "wof:name":"Pobedinka",
    "wof:placetype":"locality"
},
  "geometry": {"coordinates":[39.5642,53.7112],"type":"Point"}
}