{
  "type": "Feature",
  "properties": {
    "gn:admin1_code":"76",
    "gn:asciiname":"Man'shino",
    "gn:country_code":"RU",
    "gn:dem":209,
    "gn:feature_class":"P",
    "gn:feature_code":"PPL",
    "gn:name":"Man\u2019shino",
    "gn:population":0,
    "gn:timezone":"Europe/Moscow",
    "iso:country":"RU",
    "name:rus_x_preferred":[
        "\u041c\u0430\u043d\u044c\u0448\u0438\u043d\u043e"
    ],
    "name:und_x_variant":[
        "Man\u2019shino",
        "\u041c\u0430\u043d\u044c\u0448\u0438\u043d\u043e",
        "Manyshino"
    ],
    "wof:name":"Man'shino",
    "wof:placetype":"locality"
},
  "geometry": {"coordinates":[37.25765,54.4431],"type":"Point"}
}