{
  "type": "Feature",
  "properties": {
    "gn:admin1_code":"80.0",
    "gn:asciiname":"Gan'kina",
    "gn:country_code":"RU",
    "gn:dem":151,
    "gn:feature_class":"P",
    "gn:feature_code":"PPL",
    "gn:name":"Gan\u2019kina",
    "gn:population":0,
    "gn:timezone":"Europe/Samara",
    "iso:country":"RU",
    "name:rus_x_preferred":[
        "\u0413\u0430\u043d\u044c\u043a\u0438\u043d\u0430"
    ],
    "name:und_x_variant":[
        "Gan\u2019kina",
        "\u0413\u0430\u043d\u044c\u043a\u0438\u043d\u0430"
    ],
    "wof:name":"Gan'kina",
    "wof:placetype":"locality"
},
  "geometry": {"coordinates":[53.71666999999999,56.08333],"type":"Point"}
}