{
  "type": "Feature",
  "properties": {
    "gn:admin1_code":"72.0",
    "gn:asciiname":"Devyatka",
    "gn:country_code":"RU",
    "gn:dem":166,
    "gn:feature_class":"P",
    "gn:feature_code":"PPL",
    "gn:name":"Devyatka",
    "gn:population":0,
    "gn:timezone":"Europe/Moscow",
    "iso:country":"RU",
    "name:rus_x_preferred":[
        "\u0414\u0435\u0432\u044f\u0442\u043a\u0430"
    ],
    "wof:name":"Devyatka",
    "wof:placetype":"locality"
},
  "geometry": {"coordinates":[41.11654,51.86304000000001],"type":"Point"}
}