{
  "type": "Feature",
  "properties": {
    "gn:admin1_code":"61.0",
    "gn:asciiname":"Nazarov",
    "gn:country_code":"RU",
    "gn:dem":88,
    "gn:feature_class":"P",
    "gn:feature_code":"PPL",
    "gn:name":"Nazarov",
    "gn:population":0,
    "gn:timezone":"Europe/Moscow",
    "iso:country":"RU",
    "name:rus_x_preferred":[
        "\u041d\u0430\u0437\u0430\u0440\u043e\u0432"
    ],
    "wof:name":"Nazarov",
    "wof:placetype":"locality"
},
  "geometry": {"coordinates":[42.4792,47.4702],"type":"Point"}
}