{
  "type": "Feature",
  "properties": {
    "gn:admin1_code":"93",
    "gn:asciiname":"Chigiteyevo",
    "gn:country_code":"RU",
    "gn:dem":800,
    "gn:feature_class":"P",
    "gn:feature_code":"PPL",
    "gn:name":"Chigiteyevo",
    "gn:population":0,
    "gn:timezone":"Asia/Chita",
    "iso:country":"RU",
    "name:rus_x_preferred":[
        "\u0427\u0438\u0433\u0438\u0442\u0435\u0435\u0432\u043e"
    ],
    "name:und_x_variant":[
        "Chigitey",
        "Chigiteyevo",
        "\u0427\u0438\u0433\u0438\u0442\u0435\u0435\u0432\u043e"
    ],
    "wof:name":"Chigiteyevo",
    "wof:placetype":"locality"
},
  "geometry": {"coordinates":[113.16667,50.23333],"type":"Point"}
}