{
  "type": "Feature",
  "properties": {
    "gn:admin1_code":"63",
    "gn:asciiname":"Yuyettyakh",
    "gn:country_code":"RU",
    "gn:dem":153,
    "gn:feature_class":"P",
    "gn:feature_code":"PPL",
    "gn:name":"Yuyettyakh",
    "gn:population":0,
    "gn:timezone":"Asia/Vladivostok",
    "iso:country":"RU",
    "name:eng_x_preferred":[
        "Yuyettyakh"
    ],
    "name:nor_x_preferred":[
        "Jujettjakh"
    ],
    "name:rus_x_preferred":[
        "\u042e\u0435\u0442\u0442\u044f\u0445"
    ],
    "wof:name":"Yuyettyakh",
    "wof:placetype":"locality"
},
  "geometry": {"coordinates":[132.74238,66.97806],"type":"Point"}
}