{
  "type": "Feature",
  "properties": {
    "gn:admin1_code":"28",
    "gn:asciiname":"Kashalambi",
    "gn:country_code":"RU",
    "gn:dem":153,
    "gn:feature_class":"P",
    "gn:feature_code":"PPL",
    "gn:name":"Kashalambi",
    "gn:population":0,
    "gn:timezone":"Europe/Moscow",
    "iso:country":"RU",
    "name:fin_x_preferred":[
        "Kassanlampi"
    ],
    "name:rus_x_preferred":[
        "\u041a\u0430\u0448\u0430\u043b\u0430\u043c\u0431\u0438"
    ],
    "wof:name":"Kashalambi",
    "wof:placetype":"locality"
},
  "geometry": {"coordinates":[32.84105,61.96672],"type":"Point"}
}