{
  "type": "Feature",
  "properties": {
    "gn:admin1_code":"73",
    "gn:asciiname":"Sardek",
    "gn:country_code":"RU",
    "gn:dem":126,
    "gn:feature_class":"P",
    "gn:feature_code":"PPL",
    "gn:name":"Sardek",
    "gn:population":0,
    "gn:timezone":"Europe/Moscow",
    "iso:country":"RU",
    "name:rus_x_preferred":[
        "\u0421\u0430\u0440\u0434\u0435\u043a"
    ],
    "name:und_x_variant":[
        "Sardyk",
        "Sardek",
        "\u0421\u0430\u0440\u0434\u0435\u043a"
    ],
    "wof:name":"Sardek",
    "wof:placetype":"locality"
},
  "geometry": {"coordinates":[50.3209,56.6087],"type":"Point"}
}