{
  "type": "Feature",
  "properties": {
    "gn:admin1_code":"9",
    "gn:asciiname":"Krasnaya Polyana",
    "gn:country_code":"RU",
    "gn:dem":223,
    "gn:feature_class":"P",
    "gn:feature_code":"PPL",
    "gn:name":"Krasnaya Polyana",
    "gn:population":0,
    "gn:timezone":"Europe/Moscow",
    "iso:country":"RU",
    "name:bel_x_preferred":[
        "\u041a\u0440\u0430\u0441\u043d\u0430\u044f \u041f\u0430\u043b\u044f\u043d\u0430"
    ],
    "name:deu_x_preferred":[
        "Krasnaja Poljana"
    ],
    "name:hun_x_preferred":[
        "Krasznaja Poljana"
    ],
    "name:hye_x_preferred":[
        "\u053f\u0580\u0561\u057d\u0576\u0561\u0575\u0561 \u054a\u0578\u056c\u0575\u0561\u0576\u0561"
    ],
    "name:ita_x_preferred":[
        "Krasnaja Poljana"
    ],
    "name:kaz_x_preferred":[
        "\u041a\u0440\u0430\u0441\u043d\u0430\u044f \u041f\u043e\u043b\u044f\u043d\u0430"
    ],
    "name:nld_x_preferred":[
        "Krasnaja Poljana"
    ],
    "name:rus_x_preferred":[
        "\u041a\u0440\u0430\u0441\u043d\u0430\u044f \u041f\u043e\u043b\u044f\u043d\u0430"
    ],
    "name:sco_x_preferred":[
        "Krasnaya Polyana"
    ],
    "name:spa_x_preferred":[
        "Kr\u00e1snaya Poliana"
    ],
    "name:tat_x_preferred":[
        "\u041a\u0440\u0430\u0441\u043d\u0430\u044f \u041f\u043e\u043b\u044f\u043d\u0430"
    ],
    "name:ukr_x_preferred":[
        "\u041a\u0440\u0430\u0441\u043d\u0430 \u041f\u043e\u043b\u044f\u043d\u0430"
    ],
    "name:und_x_variant":[
        "Krasinaya Polyana"
    ],
    "wof:name":"Krasnaya Polyana",
    "wof:placetype":"locality"
},
  "geometry": {"coordinates":[37.55662,50.97972],"type":"Point"}
}