{
  "type": "Feature",
  "properties": {
    "gn:admin1_code":"9",
    "gn:asciiname":"Krasnaya Polyana",
    "gn:country_code":"RU",
    "gn:dem":223,
    "gn:feature_class":"P",
    "gn:feature_code":"PPL",
    "gn:name":"Krasnaya Polyana",
    "gn:population":0,
    "gn:timezone":"Europe/Moscow",
    "iso:country":"RU",
    "name:rus_x_preferred":[
        "\u041a\u0440\u0430\u0441\u043d\u0430\u044f \u041f\u043e\u043b\u044f\u043d\u0430"
    ],
    "name:und_x_variant":[
        "Krasinaya Polyana",
        "Krasnaya Polyana"
    ],
    "wof:name":"Krasnaya Polyana",
    "wof:placetype":"locality"
},
  "geometry": {"coordinates":[37.55662,50.97972],"type":"Point"}
}