{
  "type": "Feature",
  "properties": {
    "gn:admin1_code":"77",
    "gn:asciiname":"Lakhnevo",
    "gn:country_code":"RU",
    "gn:dem":154,
    "gn:feature_class":"P",
    "gn:feature_code":"PPL",
    "gn:name":"Lakhnevo",
    "gn:population":0,
    "gn:timezone":"Europe/Moscow",
    "iso:country":"RU",
    "name:rus_x_preferred":[
        "\u041b\u0430\u0445\u043d\u0435\u0432\u043e"
    ],
    "name:und_x_variant":[
        "\u041b\u0430\u0445\u043d\u0435\u0432\u043e"
    ],
    "wof:name":"Lakhnevo",
    "wof:placetype":"locality"
},
  "geometry": {"coordinates":[36.51139000000001,58.10705],"type":"Point"}
}