{
  "type": "Feature",
  "properties": {
    "gn:admin1_code":"91",
    "gn:asciiname":"Miroyedikha",
    "gn:cc2":"RU",
    "gn:country_code":"RU",
    "gn:dem":96,
    "gn:feature_class":"P",
    "gn:feature_code":"PPL",
    "gn:name":"Miroyedikha",
    "gn:population":0,
    "gn:timezone":"Asia/Krasnoyarsk",
    "iso:country":"RU",
    "name:eng_x_preferred":[
        "Miroyedikha"
    ],
    "name:nor_x_preferred":[
        "Mirojedikha"
    ],
    "name:rus_x_preferred":[
        "\u041c\u0438\u0440\u043e\u0435\u0434\u0438\u0445\u0430"
    ],
    "name:und_x_variant":[
        "Stanitsa Miroyedikha"
    ],
    "wof:name":"Miroyedikha",
    "wof:placetype":"locality"
},
  "geometry": {"coordinates":[88.09999999999999,65.63333],"type":"Point"}
}