{
  "type": "Feature",
  "properties": {
    "gn:admin1_code":"69",
    "gn:asciiname":"Gorby",
    "gn:country_code":"RU",
    "gn:dem":234,
    "gn:feature_class":"P",
    "gn:feature_code":"PPL",
    "gn:name":"Gorby",
    "gn:population":0,
    "gn:timezone":"Europe/Moscow",
    "iso:country":"RU",
    "name:rus_x_preferred":[
        "\u0413\u043e\u0440\u0431\u044b"
    ],
    "name:und_x_variant":[
        "\u0413\u043e\u0440\u0431\u044b"
    ],
    "wof:name":"Gorby",
    "wof:placetype":"locality"
},
  "geometry": {"coordinates":[32.78861,54.76333],"type":"Point"}
}