{
  "type": "Feature",
  "properties": {
    "gn:admin1_code":"73",
    "gn:asciiname":"Bakcha-Saray",
    "gn:country_code":"RU",
    "gn:dem":178,
    "gn:feature_class":"P",
    "gn:feature_code":"PPL",
    "gn:name":"Bakcha-Saray",
    "gn:population":0,
    "gn:timezone":"Europe/Moscow",
    "iso:country":"RU",
    "name:rus_x_preferred":[
        "\u0411\u0430\u043a\u0447\u0430-\u0421\u0430\u0440\u0430\u0439"
    ],
    "name:und_x_variant":[
        "\u0411\u0430\u043a\u0447\u0430-\u0421\u0430\u0440\u0430\u0439"
    ],
    "wof:name":"Bakcha-Saray",
    "wof:placetype":"locality"
},
  "geometry": {"coordinates":[52.08600000000001,55.5528],"type":"Point"}
}