{
  "type": "Feature",
  "properties": {
    "gn:admin1_code":"10",
    "gn:asciiname":"Staryye Khaleyevichi",
    "gn:country_code":"RU",
    "gn:dem":195,
    "gn:feature_class":"P",
    "gn:feature_code":"PPL",
    "gn:name":"Staryye Khaleyevichi",
    "gn:population":0,
    "gn:timezone":"Europe/Moscow",
    "iso:country":"RU",
    "name:rus_x_preferred":[
        "\u0421\u0442\u0430\u0440\u044b\u0435 \u0425\u0430\u043b\u0435\u0435\u0432\u0438\u0447\u0438"
    ],
    "name:und_x_variant":[
        "Khaleyevichi",
        "Staryye Khalevichi",
        "Khalevichi",
        "Staryye Khaleyevichi",
        "\u0421\u0442\u0430\u0440\u044b\u0435 \u0425\u0430\u043b\u0435\u0435\u0432\u0438\u0447\u0438"
    ],
    "wof:name":"Staryye Khaleyevichi",
    "wof:placetype":"locality"
},
  "geometry": {"coordinates":[32.54994,52.65051999999999],"type":"Point"}
}