{
  "type": "Feature",
  "properties": {
    "gn:admin1_code":"84.0",
    "gn:asciiname":"Golubirka",
    "gn:country_code":"RU",
    "gn:dem":80,
    "gn:feature_class":"P",
    "gn:feature_code":"PPL",
    "gn:name":"Golubirka",
    "gn:population":0,
    "gn:timezone":"Europe/Moscow",
    "iso:country":"RU",
    "name:rus_x_preferred":[
        "\u0413\u043e\u043b\u0443\u0431\u0438\u0440\u043a\u0430"
    ],
    "name:und_x_variant":[
        "\u0413\u043e\u043b\u0443\u0431\u0438\u0440\u043a\u0430"
    ],
    "wof:name":"Golubirka",
    "wof:placetype":"locality"
},
  "geometry": {"coordinates":[42.48972,49.00694],"type":"Point"}
}