{
  "type": "Feature",
  "properties": {
    "gn:admin1_code":"9.0",
    "gn:asciiname":"Dal'niy Dotzhik",
    "gn:country_code":"RU",
    "gn:dem":233,
    "gn:feature_class":"P",
    "gn:feature_code":"PPL",
    "gn:name":"Dal\u2019niy Dotzhik",
    "gn:population":0,
    "gn:timezone":"Europe/Moscow",
    "iso:country":"RU",
    "name:rus_x_preferred":[
        "\u0414\u0430\u043b\u044c\u043d\u0438\u0439 \u0414\u043e\u0442\u0436\u0438\u043a"
    ],
    "name:und_x_variant":[
        "Dal\u2019niy Dotzhik",
        "\u0414\u0430\u043b\u044c\u043d\u0438\u0439 \u0414\u043e\u0442\u0436\u0438\u043a"
    ],
    "wof:name":"Dal'niy Dotzhik",
    "wof:placetype":"locality"
},
  "geometry": {"coordinates":[36.80194,50.95806],"type":"Point"}
}