{
  "type": "Feature",
  "properties": {
    "gn:admin1_code":"40",
    "gn:asciiname":"Oshurkovo",
    "gn:country_code":"RU",
    "gn:dem":83,
    "gn:feature_class":"P",
    "gn:feature_code":"PPL",
    "gn:name":"Oshurkovo",
    "gn:population":0,
    "gn:timezone":"Asia/Yekaterinburg",
    "iso:country":"RU",
    "name:eng_x_preferred":[
        "Oshurkovo"
    ],
    "name:nor_x_preferred":[
        "Osjurkovo"
    ],
    "name:rus_x_preferred":[
        "\u041e\u0448\u0443\u0440\u043a\u043e\u0432\u043e"
    ],
    "wof:name":"Oshurkovo",
    "wof:placetype":"locality"
},
  "geometry": {"coordinates":[66.17444,55.96194000000001],"type":"Point"}
}