{
  "type": "Feature",
  "properties": {
    "gn:admin1_code":"33",
    "gn:asciiname":"Osetry",
    "gn:country_code":"RU",
    "gn:dem":123,
    "gn:feature_class":"P",
    "gn:feature_code":"PPL",
    "gn:name":"Osetry",
    "gn:population":0,
    "gn:timezone":"Europe/Kirov",
    "iso:country":"RU",
    "name:rus_x_preferred":[
        "\u041e\u0441\u0435\u0442\u0440\u044b"
    ],
    "wof:name":"Osetry",
    "wof:placetype":"locality"
},
  "geometry": {"coordinates":[50.1981,57.8138],"type":"Point"}
}