{
  "type": "Feature",
  "properties": {
    "gn:admin1_code":"55",
    "gn:asciiname":"Otrada",
    "gn:country_code":"RU",
    "gn:dem":185,
    "gn:feature_class":"P",
    "gn:feature_code":"PPL",
    "gn:name":"Otrada",
    "gn:population":0,
    "gn:timezone":"Asia/Yekaterinburg",
    "iso:country":"RU",
    "name:bak_x_preferred":[
        "\u041e\u0442\u0440\u0430\u0434\u0430"
    ],
    "name:che_x_preferred":[
        "\u041e\u0442\u0440\u0430\u0434\u0430"
    ],
    "name:hye_x_preferred":[
        "\u0555\u057f\u0580\u0561\u0564\u0561"
    ],
    "name:kat_x_preferred":[
        "\u10dd\u10e2\u10e0\u10d0\u10d3\u10d0"
    ],
    "name:kaz_x_preferred":[
        "\u041e\u0442\u0440\u0430\u0434\u0430"
    ],
    "name:kir_x_preferred":[
        "\u041e\u0442\u0440\u0430\u0434\u0430"
    ],
    "name:rus_x_preferred":[
        "\u041e\u0442\u0440\u0430\u0434\u0430"
    ],
    "name:tat_x_preferred":[
        "\u041e\u0442\u0440\u0430\u0434\u0430"
    ],
    "name:ukr_x_preferred":[
        "\u041e\u0442\u0440\u0430\u0434\u0430"
    ],
    "wof:name":"Otrada",
    "wof:placetype":"locality"
},
  "geometry": {"coordinates":[53.41667,52.05],"type":"Point"}
}