{
  "type": "Feature",
  "properties": {
    "gn:admin1_code":"51.0",
    "gn:asciiname":"Sakony",
    "gn:country_code":"RU",
    "gn:dem":150,
    "gn:feature_class":"P",
    "gn:feature_code":"PPL",
    "gn:name":"Sakony",
    "gn:population":0,
    "gn:timezone":"Europe/Moscow",
    "iso:country":"RU",
    "name:rus_x_preferred":[
        "\u0421\u0430\u043a\u043e\u043d\u044b"
    ],
    "wof:name":"Sakony",
    "wof:placetype":"locality"
},
  "geometry": {"coordinates":[43.09762,55.48399000000001],"type":"Point"}
}