{
  "type": "Feature",
  "properties": {
    "gn:admin1_code":"3",
    "gn:asciiname":"Verkhnyaya Talda",
    "gn:country_code":"RU",
    "gn:dem":1081,
    "gn:feature_class":"P",
    "gn:feature_code":"PPL",
    "gn:name":"Verkhnyaya Talda",
    "gn:population":0,
    "gn:timezone":"Asia/Omsk",
    "iso:country":"RU",
    "wof:name":"Verkhnyaya Talda",
    "wof:placetype":"locality"
},
  "geometry": {"coordinates":[85.88333,50.93333],"type":"Point"}
}