{
  "type": "Feature",
  "properties": {
    "gn:admin1_code":"16",
    "gn:asciiname":"Sin'yaly",
    "gn:country_code":"RU",
    "gn:dem":132,
    "gn:feature_class":"P",
    "gn:feature_code":"PPL",
    "gn:name":"Sin\u2019yaly",
    "gn:population":0,
    "gn:timezone":"Europe/Moscow",
    "iso:country":"RU",
    "name:rus_x_preferred":[
        "\u0421\u0438\u043d\u044c\u044f\u043b\u044b"
    ],
    "name:und_x_variant":[
        "Sin\u2019yaly",
        "\u0421\u0438\u043d\u044c\u044f\u043b\u044b"
    ],
    "wof:name":"Sin'yaly",
    "wof:placetype":"locality"
},
  "geometry": {"coordinates":[46.82752,55.63076],"type":"Point"}
}