{
  "type": "Feature",
  "properties": {
    "gn:admin1_code":"62",
    "gn:asciiname":"Mityakino",
    "gn:country_code":"RU",
    "gn:dem":203,
    "gn:feature_class":"P",
    "gn:feature_code":"PPL",
    "gn:name":"Mityakino",
    "gn:population":0,
    "gn:timezone":"Europe/Moscow",
    "iso:country":"RU",
    "name:rus_x_preferred":[
        "\u041c\u0438\u0442\u044f\u043a\u0438\u043d\u043e"
    ],
    "wof:name":"Mityakino",
    "wof:placetype":"locality"
},
  "geometry": {"coordinates":[38.7273,54.0914],"type":"Point"}
}