{
  "type": "Feature",
  "properties": {
    "gn:admin1_code":"53",
    "gn:asciiname":"Verkh-Mil'tyushi",
    "gn:country_code":"RU",
    "gn:dem":246,
    "gn:feature_class":"P",
    "gn:feature_code":"PPL",
    "gn:name":"Verkh-Mil\u2019tyushi",
    "gn:population":0,
    "gn:timezone":"Asia/Novosibirsk",
    "iso:country":"RU",
    "name:eng_x_preferred":[
        "Verkh-Mil'tyushi"
    ],
    "name:nor_x_preferred":[
        "Verkh-Miltjusji"
    ],
    "name:rus_x_preferred":[
        "\u0412\u0435\u0440\u0445-\u041c\u0438\u043b\u044c\u0442\u044e\u0448\u0438"
    ],
    "name:und_x_variant":[
        "Verkhniye Mil\u2019tyushi",
        "Verkhniy Mil\u2019tyush",
        "Verkh-Mil\u2019tyushi"
    ],
    "wof:name":"Verkh-Mil'tyushi",
    "wof:placetype":"locality"
},
  "geometry": {"coordinates":[82.9057,54.2986],"type":"Point"}
}