{
  "type": "Feature",
  "properties": {
    "gn:admin1_code":"85",
    "gn:asciiname":"Nagorskoye",
    "gn:country_code":"RU",
    "gn:dem":130,
    "gn:feature_class":"P",
    "gn:feature_code":"PPL",
    "gn:name":"Nagorskoye",
    "gn:population":0,
    "gn:timezone":"Europe/Moscow",
    "iso:country":"RU",
    "name:rus_x_preferred":[
        "\u041d\u0430\u0433\u043e\u0440\u0441\u043a\u043e\u0435"
    ],
    "name:und_x_variant":[
        "\u041d\u0430\u0433\u043e\u0440\u0441\u043a\u043e\u0435"
    ],
    "wof:name":"Nagorskoye",
    "wof:placetype":"locality"
},
  "geometry": {"coordinates":[39.7783,59.2762],"type":"Point"}
}