{
  "type": "Feature",
  "properties": {
    "gn:admin1_code":"84",
    "gn:asciiname":"Rodionovskiy",
    "gn:country_code":"RU",
    "gn:dem":66,
    "gn:feature_class":"P",
    "gn:feature_code":"PPL",
    "gn:name":"Rodionovskiy",
    "gn:population":0,
    "gn:timezone":"Europe/Volgograd",
    "iso:country":"RU",
    "name:rus_x_preferred":[
        "\u0420\u043e\u0434\u0438\u043e\u043d\u043e\u0432\u0441\u043a\u0438\u0439"
    ],
    "name:und_x_variant":[
        "Radionovskiy",
        "Rodionovskiy"
    ],
    "wof:name":"Rodionovskiy",
    "wof:placetype":"locality"
},
  "geometry": {"coordinates":[42.5805,49.9482],"type":"Point"}
}