{
  "type": "Feature",
  "properties": {
    "gn:admin1_code":"84",
    "gn:asciiname":"Varlamovka",
    "gn:cc2":"RU",
    "gn:country_code":"RU",
    "gn:dem":52,
    "gn:feature_class":"P",
    "gn:feature_code":"PPL",
    "gn:name":"Varlamovka",
    "gn:population":0,
    "gn:timezone":"Europe/Volgograd",
    "iso:country":"RU",
    "name:und_x_variant":[
        "Sredne-Tsaritsynskiy",
        "Varlallovka",
        "Varlamov",
        "Varlamovka"
    ],
    "wof:name":"Varlamovka",
    "wof:placetype":"locality"
},
  "geometry": {"coordinates":[43.80917,48.59361],"type":"Point"}
}