{
  "type": "Feature",
  "properties": {
    "gn:admin1_code":"32",
    "gn:asciiname":"Bagras",
    "gn:country_code":"RU",
    "gn:dem":15,
    "gn:feature_class":"P",
    "gn:feature_code":"PPL",
    "gn:name":"Bagras",
    "gn:population":0,
    "gn:timezone":"Asia/Yekaterinburg",
    "iso:country":"RU",
    "name:nor_x_preferred":[
        "Bagras"
    ],
    "name:rus_x_preferred":[
        "\u0411\u0430\u0433\u0440\u0430\u0441"
    ],
    "wof:name":"Bagras",
    "wof:placetype":"locality"
},
  "geometry": {"coordinates":[76.3219,60.9206],"type":"Point"}
}