{
  "type": "Feature",
  "properties": {
    "gn:admin1_code":"85",
    "gn:asciiname":"Toloknyanitsa",
    "gn:country_code":"RU",
    "gn:dem":146,
    "gn:feature_class":"P",
    "gn:feature_code":"PPL",
    "gn:name":"Toloknyanitsa",
    "gn:population":0,
    "gn:timezone":"Europe/Moscow",
    "iso:country":"RU",
    "name:rus_x_preferred":[
        "\u0422\u043e\u043b\u043e\u043a\u043d\u044f\u043d\u0438\u0446\u0430"
    ],
    "wof:name":"Toloknyanitsa",
    "wof:placetype":"locality"
},
  "geometry": {"coordinates":[38.8248,59.8006],"type":"Point"}
}