{
  "type": "Feature",
  "properties": {
    "gn:admin1_code":"55",
    "gn:asciiname":"Novoaleksandrovka",
    "gn:cc2":"RU",
    "gn:country_code":"RU",
    "gn:dem":157,
    "gn:feature_class":"P",
    "gn:feature_code":"PPL",
    "gn:name":"Novoaleksandrovka",
    "gn:population":0,
    "gn:timezone":"Asia/Yekaterinburg",
    "iso:country":"RU",
    "name:rus_x_preferred":[
        "\u041d\u043e\u0432\u043e\u0430\u043b\u0435\u043a\u0441\u0430\u043d\u0434\u0440\u043e\u0432\u043a\u0430"
    ],
    "name:und_x_variant":[
        "Aleksandrovka",
        "Novoaleksandrovka"
    ],
    "wof:name":"Novoaleksandrovka",
    "wof:placetype":"locality"
},
  "geometry": {"coordinates":[55.45,51.38333],"type":"Point"}
}