{
  "type": "Feature",
  "properties": {
    "gn:admin1_code":"69",
    "gn:asciiname":"Sidorova",
    "gn:country_code":"RU",
    "gn:dem":209,
    "gn:feature_class":"P",
    "gn:feature_code":"PPL",
    "gn:name":"Sidorova",
    "gn:population":0,
    "gn:timezone":"Europe/Moscow",
    "iso:country":"RU",
    "name:rus_x_preferred":[
        "\u0421\u0438\u0434\u043e\u0440\u043e\u0432\u0430"
    ],
    "name:und_x_variant":[
        "\u0421\u0438\u0434\u043e\u0440\u043e\u0432\u0430"
    ],
    "wof:name":"Sidorova",
    "wof:placetype":"locality"
},
  "geometry": {"coordinates":[32.25,54.51667],"type":"Point"}
}