{
  "type": "Feature",
  "properties": {
    "gn:admin1_code":"8",
    "gn:asciiname":"Ishberda",
    "gn:cc2":"RU",
    "gn:country_code":"RU",
    "gn:dem":510,
    "gn:feature_class":"P",
    "gn:feature_code":"PPL",
    "gn:name":"Ishberda",
    "gn:population":0,
    "gn:timezone":"Asia/Yekaterinburg",
    "iso:country":"RU",
    "name:rus_x_preferred":[
        "\u0418\u0448\u0431\u0435\u0440\u0434\u0430"
    ],
    "name:und_x_variant":[
        "Ishberdina",
        "Ishberda",
        "\u0418\u0448\u0431\u0435\u0440\u0434\u0430"
    ],
    "wof:name":"Ishberda",
    "wof:placetype":"locality"
},
  "geometry": {"coordinates":[58.36666999999999,52.95],"type":"Point"}
}