{
  "type": "Feature",
  "properties": {
    "gn:admin1_code":"80.0",
    "gn:asciiname":"Bazhenikha",
    "gn:country_code":"RU",
    "gn:dem":68,
    "gn:feature_class":"P",
    "gn:feature_code":"PPL",
    "gn:name":"Bazhenikha",
    "gn:population":0,
    "gn:timezone":"Europe/Samara",
    "iso:country":"RU",
    "name:eng_x_preferred":[
        "Bazhenikha"
    ],
    "name:nor_x_preferred":[
        "Bazjenikha"
    ],
    "name:rus_x_preferred":[
        "\u0411\u0430\u0436\u0435\u043d\u0438\u0445\u0430"
    ],
    "name:und_x_variant":[
        "Bozhenikha"
    ],
    "wof:name":"Bazhenikha",
    "wof:placetype":"locality"
},
  "geometry": {"coordinates":[51.51145,55.96505],"type":"Point"}
}