{
  "type": "Feature",
  "properties": {
    "gn:admin1_code":"71",
    "gn:asciiname":"Tagil'tsy",
    "gn:country_code":"RU",
    "gn:dem":60,
    "gn:feature_class":"P",
    "gn:feature_code":"PPL",
    "gn:name":"Tagil\u2019tsy",
    "gn:population":0,
    "gn:timezone":"Asia/Yekaterinburg",
    "iso:country":"RU",
    "name:eng_x_preferred":[
        "Tagil'tsy"
    ],
    "name:nor_x_preferred":[
        "Tagiltsy"
    ],
    "name:rus_x_preferred":[
        "\u0422\u0430\u0433\u0438\u043b\u044c\u0446\u044b"
    ],
    "name:und_x_variant":[
        "Tagil\u2019tsy"
    ],
    "wof:name":"Tagil'tsy",
    "wof:placetype":"locality"
},
  "geometry": {"coordinates":[65.30034000000001,58.13472],"type":"Point"}
}