{
  "type": "Feature",
  "properties": {
    "gn:admin1_code":"73",
    "gn:asciiname":"Pochinok-Ponik",
    "gn:country_code":"RU",
    "gn:dem":152,
    "gn:feature_class":"P",
    "gn:feature_code":"PPL",
    "gn:name":"Pochinok-Ponik",
    "gn:population":0,
    "gn:timezone":"Europe/Moscow",
    "iso:country":"RU",
    "name:rus_x_preferred":[
        "\u041f\u043e\u0447\u0438\u043d\u043e\u043a-\u041f\u043e\u043d\u0438\u043a"
    ],
    "wof:name":"Pochinok-Ponik",
    "wof:placetype":"locality"
},
  "geometry": {"coordinates":[50.234,56.2161],"type":"Point"}
}