{
  "type": "Feature",
  "properties": {
    "gn:admin1_code":"71",
    "gn:asciiname":"Kozlovskiy",
    "gn:country_code":"RU",
    "gn:dem":274,
    "gn:feature_class":"P",
    "gn:feature_code":"PPL",
    "gn:name":"Kozlovskiy",
    "gn:population":0,
    "gn:timezone":"Asia/Yekaterinburg",
    "iso:country":"RU",
    "name:rus_x_preferred":[
        "\u041a\u043e\u0437\u043b\u043e\u0432\u0441\u043a\u0438\u0439"
    ],
    "name:und_x_variant":[
        "\u041a\u043e\u0437\u043b\u043e\u0432\u0441\u043a\u0438\u0439"
    ],
    "wof:name":"Kozlovskiy",
    "wof:placetype":"locality"
},
  "geometry": {"coordinates":[60.7005,56.971],"type":"Point"}
}