{
  "type": "Feature",
  "properties": {
    "gn:admin1_code":"52.0",
    "gn:asciiname":"Bol'shaya Kozona",
    "gn:country_code":"RU",
    "gn:dem":25,
    "gn:feature_class":"P",
    "gn:feature_code":"PPL",
    "gn:name":"Bol\u2019shaya Kozona",
    "gn:population":0,
    "gn:timezone":"Europe/Moscow",
    "iso:country":"RU",
    "name:rus_x_preferred":[
        "\u0411\u043e\u043b\u044c\u0448\u0430\u044f \u041a\u043e\u0437\u043e\u043d\u0430"
    ],
    "name:und_x_variant":[
        "Bol\u2019shaya Kozanka",
        "Bol\u2019shaya Kozona",
        "\u0411\u043e\u043b\u044c\u0448\u0430\u044f \u041a\u043e\u0437\u043e\u043d\u0430"
    ],
    "wof:name":"Bol'shaya Kozona",
    "wof:placetype":"locality"
},
  "geometry": {"coordinates":[31.35885,57.95928000000001],"type":"Point"}
}