{
  "type": "Feature",
  "properties": {
    "gn:admin1_code":"40",
    "gn:asciiname":"Bakayevo",
    "gn:country_code":"RU",
    "gn:dem":197,
    "gn:feature_class":"P",
    "gn:feature_code":"PPL",
    "gn:name":"Bakayevo",
    "gn:population":0,
    "gn:timezone":"Asia/Yekaterinburg",
    "iso:country":"RU",
    "name:bak_x_preferred":[
        "\u0411\u0430\u04a1\u0430\u0439"
    ],
    "name:eng_x_preferred":[
        "Bakayevo"
    ],
    "name:kat_x_preferred":[
        "\u10d1\u10d0\u10d9\u10d0\u10d4\u10d5\u10dd"
    ],
    "name:nor_x_preferred":[
        "Bakajevo"
    ],
    "name:rus_x_preferred":[
        "\u0411\u0430\u043a\u0430\u0435\u0432\u043e"
    ],
    "name:tat_x_preferred":[
        "\u0411\u0430\u043a\u0430\u0439"
    ],
    "name:ukr_x_preferred":[
        "\u0411\u0430\u043a\u0430\u0454\u0432\u043e"
    ],
    "name:und_x_variant":[
        "Bakayeva"
    ],
    "wof:name":"Bakayevo",
    "wof:placetype":"locality"
},
  "geometry": {"coordinates":[62.58917,54.66972],"type":"Point"}
}