{
  "type": "Feature",
  "properties": {
    "gn:admin1_code":"21.0",
    "gn:asciiname":"Rogushi",
    "gn:country_code":"RU",
    "gn:dem":143,
    "gn:feature_class":"P",
    "gn:feature_code":"PPL",
    "gn:name":"Rogushi",
    "gn:population":0,
    "gn:timezone":"Europe/Moscow",
    "iso:country":"RU",
    "name:rus_x_preferred":[
        "\u0420\u043e\u0433\u0443\u0448\u0438"
    ],
    "wof:name":"Rogushi",
    "wof:placetype":"locality"
},
  "geometry": {"coordinates":[42.23158,57.27652],"type":"Point"}
}