{
  "type": "Feature",
  "properties": {
    "gn:admin1_code":"61",
    "gn:asciiname":"Novochigirinovskiy",
    "gn:country_code":"RU",
    "gn:dem":97,
    "gn:feature_class":"P",
    "gn:feature_code":"PPL",
    "gn:name":"Novochigirinovskiy",
    "gn:population":0,
    "gn:timezone":"Europe/Moscow",
    "iso:country":"RU",
    "name:rus_x_preferred":[
        "\u041d\u043e\u0432\u043e\u0447\u0438\u0433\u0438\u0440\u0438\u043d\u043e\u0432\u0441\u043a\u0438\u0439"
    ],
    "name:und_x_variant":[
        "Shchegrinovskiy",
        "Novochizirinskiy",
        "Novochigirinskiy",
        "Novochigirinovskiy"
    ],
    "wof:name":"Novochigirinovskiy",
    "wof:placetype":"locality"
},
  "geometry": {"coordinates":[41.14617,49.18034],"type":"Point"}
}