{
  "type": "Feature",
  "properties": {
    "gn:admin1_code":"20",
    "gn:asciiname":"Bayer",
    "gn:country_code":"RU",
    "gn:dem":284,
    "gn:feature_class":"P",
    "gn:feature_code":"PPL",
    "gn:name":"Bayer",
    "gn:population":0,
    "gn:timezone":"Asia/Irkutsk",
    "iso:country":"RU",
    "name:eng_x_preferred":[
        "Bayer"
    ],
    "name:nor_x_preferred":[
        "Bajer"
    ],
    "name:rus_x_preferred":[
        "\u0411\u0430\u0435\u0440"
    ],
    "name:und_x_variant":[
        "Baer",
        "\u0411\u0430\u0435\u0440",
        "Bayer"
    ],
    "wof:name":"Bayer",
    "wof:placetype":"locality"
},
  "geometry": {"coordinates":[99.50667,55.76361],"type":"Point"}
}