{
  "type": "Feature",
  "properties": {
    "gn:admin1_code":"67",
    "gn:asciiname":"Lada",
    "gn:country_code":"RU",
    "gn:dem":187,
    "gn:feature_class":"P",
    "gn:feature_code":"PPL",
    "gn:name":"Lada",
    "gn:population":0,
    "gn:timezone":"Europe/Saratov",
    "iso:country":"RU",
    "name:rus_x_preferred":[
        "\u041b\u0430\u0434\u0430"
    ],
    "name:und_x_variant":[
        "\u041b\u0430\u0434\u0430"
    ],
    "wof:name":"Lada",
    "wof:placetype":"locality"
},
  "geometry": {"coordinates":[43.77529000000001,51.64065],"type":"Point"}
}