{
  "type": "Feature",
  "properties": {
    "gn:admin1_code":"88",
    "gn:asciiname":"Timofeykovo",
    "gn:country_code":"RU",
    "gn:dem":151,
    "gn:feature_class":"P",
    "gn:feature_code":"PPL",
    "gn:name":"Timofeykovo",
    "gn:population":0,
    "gn:timezone":"Europe/Moscow",
    "iso:country":"RU",
    "name:rus_x_preferred":[
        "\u0422\u0438\u043c\u043e\u0444\u0435\u0439\u043a\u043e\u0432\u043e"
    ],
    "name:und_x_variant":[
        "\u0422\u0438\u043c\u043e\u0444\u0435\u0439\u043a\u043e\u0432\u043e"
    ],
    "wof:name":"Timofeykovo",
    "wof:placetype":"locality"
},
  "geometry": {"coordinates":[38.7535,57.2249],"type":"Point"}
}