{
  "type": "Feature",
  "properties": {
    "gn:admin1_code":"9.0",
    "gn:asciiname":"Plotva",
    "gn:country_code":"RU",
    "gn:dem":202,
    "gn:feature_class":"P",
    "gn:feature_code":"PPL",
    "gn:name":"Plotva",
    "gn:population":0,
    "gn:timezone":"Europe/Moscow",
    "iso:country":"RU",
    "name:rus_x_preferred":[
        "\u041f\u043b\u043e\u0442\u0432\u0430"
    ],
    "wof:name":"Plotva",
    "wof:placetype":"locality"
},
  "geometry": {"coordinates":[37.9075,50.556],"type":"Point"}
}