{
  "type": "Feature",
  "properties": {
    "gn:admin1_code":"65",
    "gn:asciiname":"Korneyevka",
    "gn:country_code":"RU",
    "gn:dem":88,
    "gn:feature_class":"P",
    "gn:feature_code":"PPL",
    "gn:name":"Korneyevka",
    "gn:population":0,
    "gn:timezone":"Europe/Samara",
    "iso:country":"RU",
    "name:eng_x_preferred":[
        "Korneyevka"
    ],
    "name:nor_x_preferred":[
        "Kornejevka"
    ],
    "name:rus_x_preferred":[
        "\u041a\u043e\u0440\u043d\u0435\u0435\u0432\u043a\u0430"
    ],
    "wof:name":"Korneyevka",
    "wof:placetype":"locality"
},
  "geometry": {"coordinates":[51.3374,52.708],"type":"Point"}
}