{
  "type": "Feature",
  "properties": {
    "gn:admin1_code":"50",
    "gn:asciiname":"Sukharev",
    "gn:cc2":"RU",
    "gn:country_code":"RU",
    "gn:dem":27,
    "gn:feature_class":"P",
    "gn:feature_code":"PPL",
    "gn:name":"Sukharev",
    "gn:population":0,
    "gn:timezone":"Europe/Moscow",
    "iso:country":"RU",
    "name:rus_x_preferred":[
        "\u0421\u0443\u0445\u0430\u0440\u0435\u0432"
    ],
    "name:und_x_variant":[
        "Sukhareva",
        "Sukharev"
    ],
    "wof:name":"Sukharev",
    "wof:placetype":"locality"
},
  "geometry": {"coordinates":[46.58333,66.58333],"type":"Point"}
}