{
  "type": "Feature",
  "properties": {
    "gn:admin1_code":"72",
    "gn:asciiname":"Strelki",
    "gn:country_code":"RU",
    "gn:dem":170,
    "gn:feature_class":"P",
    "gn:feature_code":"PPL",
    "gn:name":"Strelki",
    "gn:population":0,
    "gn:timezone":"Europe/Moscow",
    "iso:country":"RU",
    "name:eng_x_preferred":[
        "Strelki"
    ],
    "name:nld_x_preferred":[
        "Strelki"
    ],
    "name:nor_x_preferred":[
        "Strelki"
    ],
    "name:rus_x_preferred":[
        "\u0421\u0442\u0440\u0435\u043b\u043a\u0438"
    ],
    "wof:name":"Strelki",
    "wof:placetype":"locality"
},
  "geometry": {"coordinates":[40.9895,53.4841],"type":"Point"}
}