{
  "type": "Feature",
  "properties": {
    "gn:admin1_code":"24.0",
    "gn:asciiname":"Balanov",
    "gn:country_code":"RU",
    "gn:dem":78,
    "gn:feature_class":"P",
    "gn:feature_code":"PPL",
    "gn:name":"Balanov",
    "gn:population":0,
    "gn:timezone":"Europe/Moscow",
    "iso:country":"RU",
    "name:nor_x_preferred":[
        "Balanov"
    ],
    "name:rus_x_preferred":[
        "\u0411\u0430\u043b\u0430\u043d\u043e\u0432"
    ],
    "wof:name":"Balanov",
    "wof:placetype":"locality"
},
  "geometry": {"coordinates":[44.37481,47.67487],"type":"Point"}
}