{
  "type": "Feature",
  "properties": {
    "gn:admin1_code":"10",
    "gn:asciiname":"Roshcha",
    "gn:country_code":"RU",
    "gn:dem":187,
    "gn:feature_class":"P",
    "gn:feature_code":"PPL",
    "gn:name":"Roshcha",
    "gn:population":0,
    "gn:timezone":"Europe/Moscow",
    "iso:country":"RU",
    "name:rus_x_preferred":[
        "\u0420\u043e\u0449\u0430"
    ],
    "name:rus_x_variant":[
        "Zel\u00ebnaya Roshcha"
    ],
    "name:und_x_variant":[
        "\u0420\u043e\u0449\u0430",
        "Zel\u00ebnaya Roshcha"
    ],
    "wof:name":"Roshcha",
    "wof:placetype":"locality"
},
  "geometry": {"coordinates":[32.25889,52.61444],"type":"Point"}
}