{
  "type": "Feature",
  "properties": {
    "gn:country":"RU",
    "gn:fcode":"PPL",
    "gn:population":0,
    "iso:country":"RU",
    "name:bak_x_preferred":[
        "\u0411\u0430\u0439\u0493\u0430\u0499\u044b"
    ],
    "name:che_x_preferred":[
        "\u0411\u0430\u0439\u0433\u0430\u0437\u0438\u043d\u043e"
    ],
    "name:eng_x_preferred":[
        "Baygil'dino"
    ],
    "name:hye_x_preferred":[
        "\u0532\u0561\u0575\u0563\u0561\u0566\u056b\u0576\u0578"
    ],
    "name:kat_x_preferred":[
        "\u10d1\u10d0\u10d8\u10d2\u10d0\u10d6\u10d8\u10dc\u10dd"
    ],
    "name:kaz_x_preferred":[
        "\u0411\u0430\u0439\u0433\u0430\u0437\u0438\u043d\u043e"
    ],
    "name:kir_x_preferred":[
        "\u0411\u0430\u0439\u0433\u0430\u0437\u0438\u043d\u043e"
    ],
    "name:nor_x_preferred":[
        "Bajgildino"
    ],
    "name:rus_x_preferred":[
        "\u0411\u0430\u0439\u0433\u0438\u043b\u044c\u0434\u0438\u043d\u043e"
    ],
    "name:rus_x_variant":[
        "\u0411\u0430\u0439\u0433\u0430\u0437\u0438\u043d\u043e"
    ],
    "name:tat_x_preferred":[
        "\u0411\u0430\u0439\u0433\u0430\u0437\u044b"
    ],
    "name:ukr_x_preferred":[
        "\u0411\u0430\u0439\u0433\u0430\u0437\u0456\u043d\u043e"
    ],
    "name:und_x_variant":[
        "Baygil\u2019dina"
    ],
    "qs:name":"Baygazino",
    "qs:name_adm0":"Russia",
    "qs:name_adm1":"Bashkortostan Republic",
    "qs:photos_9r":0,
    "qs:photos_sr":0,
    "qs:placetype":"Town",
    "qs:pop_sr":"0",
    "wof:name":"Baygazino",
    "wof:placetype":"locality",
    "wof:population":0
},
  "geometry": {"coordinates":[56.50998,54.98281],"type":"Point"}
}