{
  "type": "Feature",
  "properties": {
    "gn:country":"RU",
    "gn:fcode":"PPL",
    "gn:pop":0,
    "iso:country":"RU",
    "name:eng_x_preferred":[
        "Baygil'dino"
    ],
    "name:nor_x_preferred":[
        "Bajgildino"
    ],
    "name:rus_x_preferred":[
        "\u0411\u0430\u0439\u0433\u0438\u043b\u044c\u0434\u0438\u043d\u043e"
    ],
    "name:unk_x_variant":[
        "Baygil\u2019dina"
    ],
    "qs:name":"Baygazino",
    "qs:name_adm0":"Russia",
    "qs:name_adm1":"Bashkortostan Republic",
    "qs:photos_9r":0,
    "qs:photos_sr":0,
    "qs:placetype":"Town",
    "qs:pop_sr":"0",
    "wof:name":"Baygazino",
    "wof:placetype":"locality",
    "wof:population":0
},
  "geometry": {"coordinates":[56.50998,54.98281],"type":"Point"}
}