{
  "type": "Feature",
  "properties": {
    "gn:admin1_code":"6",
    "gn:asciiname":"Kuimka",
    "gn:country_code":"RU",
    "gn:dem":148,
    "gn:feature_class":"P",
    "gn:feature_code":"PPL",
    "gn:name":"Kuimka",
    "gn:population":0,
    "gn:timezone":"Europe/Moscow",
    "iso:country":"RU",
    "name:rus_x_preferred":[
        "\u041a\u0443\u0438\u043c\u043a\u0430"
    ],
    "name:und_x_variant":[
        "\u041a\u0443\u0438\u043c\u043a\u0430"
    ],
    "wof:name":"Kuimka",
    "wof:placetype":"locality"
},
  "geometry": {"coordinates":[47.48897,61.87749],"type":"Point"}
}