{
  "type": "Feature",
  "properties": {
    "gn:admin1_code":"83",
    "gn:asciiname":"Peremilovo",
    "gn:country_code":"RU",
    "gn:dem":147,
    "gn:feature_class":"P",
    "gn:feature_code":"PPL",
    "gn:name":"Peremilovo",
    "gn:population":0,
    "gn:timezone":"Europe/Moscow",
    "iso:country":"RU",
    "name:rus_x_preferred":[
        "\u041f\u0435\u0440\u0435\u043c\u0438\u043b\u043e\u0432\u043e"
    ],
    "wof:name":"Peremilovo",
    "wof:placetype":"locality"
},
  "geometry": {"coordinates":[39.41556,56.70362],"type":"Point"}
}