{
  "type": "Feature",
  "properties": {
    "gn:admin1_code":"51.0",
    "gn:asciiname":"Begichevo",
    "gn:country_code":"RU",
    "gn:dem":122,
    "gn:feature_class":"P",
    "gn:feature_code":"PPL",
    "gn:name":"Begich\u00ebvo",
    "gn:population":0,
    "gn:timezone":"Europe/Moscow",
    "iso:country":"RU",
    "name:nor_x_preferred":[
        "Begitsjovo"
    ],
    "name:rus_x_preferred":[
        "\u0411\u0435\u0433\u0438\u0447\u0451\u0432\u043e"
    ],
    "name:und_x_variant":[
        "Begich\u00ebvo"
    ],
    "wof:name":"Begichevo",
    "wof:placetype":"locality"
},
  "geometry": {"coordinates":[46.20374,55.31099],"type":"Point"}
}