{
  "type": "Feature",
  "properties": {
    "gn:admin1_code":"33.0",
    "gn:asciiname":"Arkhipenki",
    "gn:country_code":"RU",
    "gn:dem":140,
    "gn:feature_class":"P",
    "gn:feature_code":"PPL",
    "gn:name":"Arkhipenki",
    "gn:population":0,
    "gn:timezone":"Europe/Kirov",
    "iso:country":"RU",
    "name:nor_x_preferred":[
        "Arkhipenki"
    ],
    "name:rus_x_preferred":[
        "\u0410\u0440\u0445\u0438\u043f\u0435\u043d\u043a\u0438"
    ],
    "wof:name":"Arkhipenki",
    "wof:placetype":"locality"
},
  "geometry": {"coordinates":[48.18056,58.15472],"type":"Point"}
}