{
  "type": "Feature",
  "properties": {
    "gn:admin1_code":"81",
    "gn:asciiname":"Kartsovka",
    "gn:country_code":"RU",
    "gn:dem":256,
    "gn:feature_class":"P",
    "gn:feature_code":"PPL",
    "gn:name":"Kartsovka",
    "gn:population":0,
    "gn:timezone":"Europe/Ulyanovsk",
    "iso:country":"RU",
    "name:rus_x_preferred":[
        "\u041a\u0430\u0440\u0446\u043e\u0432\u043a\u0430"
    ],
    "name:und_x_variant":[
        "Kartsevka"
    ],
    "wof:name":"Kartsovka",
    "wof:placetype":"locality"
},
  "geometry": {"coordinates":[47.5988,54.0921],"type":"Point"}
}