{
  "type": "Feature",
  "properties": {
    "gn:admin1_code":"77",
    "gn:asciiname":"Niva",
    "gn:country_code":"RU",
    "gn:dem":224,
    "gn:feature_class":"P",
    "gn:feature_code":"PPL",
    "gn:name":"Niva",
    "gn:population":0,
    "gn:timezone":"Europe/Moscow",
    "iso:country":"RU",
    "name:rus_x_preferred":[
        "\u041d\u0438\u0432\u0430"
    ],
    "name:und_x_variant":[
        "Nivy",
        "Niva"
    ],
    "wof:name":"Niva",
    "wof:placetype":"locality"
},
  "geometry": {"coordinates":[32.94928,56.40093],"type":"Point"}
}