{
  "type": "Feature",
  "properties": {
    "gn:admin1_code":"20.0",
    "gn:asciiname":"Stolbova",
    "gn:country_code":"RU",
    "gn:dem":503,
    "gn:feature_class":"P",
    "gn:feature_code":"PPL",
    "gn:name":"Stolbova",
    "gn:population":0,
    "gn:timezone":"Asia/Irkutsk",
    "iso:country":"RU",
    "name:rus_x_preferred":[
        "\u0421\u0442\u043e\u043b\u0431\u043e\u0432\u0430"
    ],
    "name:und_x_variant":[
        "Stolbovo",
        "Stolbova",
        "\u0421\u0442\u043e\u043b\u0431\u043e\u0432\u0430"
    ],
    "wof:name":"Stolbova",
    "wof:placetype":"locality"
},
  "geometry": {"coordinates":[104.22,52.42],"type":"Point"}
}