{
  "type": "Feature",
  "properties": {
    "gn:admin1_code":"90.0",
    "gn:asciiname":"Budkeyevo",
    "gn:country_code":"RU",
    "gn:dem":192,
    "gn:feature_class":"P",
    "gn:feature_code":"PPL",
    "gn:name":"Budkeyevo",
    "gn:population":0,
    "gn:timezone":"Asia/Yekaterinburg",
    "iso:country":"RU",
    "name:rus_x_preferred":[
        "\u0411\u0443\u0434\u043a\u0435\u0435\u0432\u043e"
    ],
    "wof:name":"Budkeyevo",
    "wof:placetype":"locality"
},
  "geometry": {"coordinates":[56.94626,56.57703000000001],"type":"Point"}
}