{
  "type": "Feature",
  "properties": {
    "gn:admin1_code":"69",
    "gn:asciiname":"Tupichino",
    "gn:country_code":"RU",
    "gn:dem":242,
    "gn:feature_class":"P",
    "gn:feature_code":"PPL",
    "gn:name":"Tupichino",
    "gn:population":0,
    "gn:timezone":"Europe/Moscow",
    "iso:country":"RU",
    "wof:name":"Tupichino",
    "wof:placetype":"locality"
},
  "geometry": {"coordinates":[33.60222,55.77222],"type":"Point"}
}