{
  "type": "Feature",
  "properties": {
    "gn:admin1_code":"72",
    "gn:asciiname":"Viktoriya",
    "gn:country_code":"RU",
    "gn:dem":137,
    "gn:feature_class":"P",
    "gn:feature_code":"PPL",
    "gn:name":"Viktoriya",
    "gn:population":0,
    "gn:timezone":"Europe/Moscow",
    "iso:country":"RU",
    "name:aze_x_preferred":[
        "Viktoriya"
    ],
    "wof:name":"Viktoriya",
    "wof:placetype":"locality"
},
  "geometry": {"coordinates":[41.10972,52.53361],"type":"Point"}
}