{
  "type": "Feature",
  "properties": {
    "gn:admin1_code":"54",
    "gn:asciiname":"Tambovka",
    "gn:country_code":"RU",
    "gn:dem":91,
    "gn:feature_class":"P",
    "gn:feature_code":"PPL",
    "gn:name":"Tambovka",
    "gn:population":0,
    "gn:timezone":"Asia/Omsk",
    "iso:country":"RU",
    "name:eng_x_preferred":[
        "Tambovka"
    ],
    "name:nor_x_preferred":[
        "Tambovka"
    ],
    "name:rus_x_preferred":[
        "\u0422\u0430\u043c\u0431\u043e\u0432\u043a\u0430"
    ],
    "name:und_x_variant":[
        "Ferma Nomer Chetyre Sovkhoza Sorok Shest\u2019"
    ],
    "wof:name":"Tambovka",
    "wof:placetype":"locality"
},
  "geometry": {"coordinates":[73.03532,55.47481],"type":"Point"}
}