{
  "type": "Feature",
  "properties": {
    "gn:admin1_code":"33",
    "gn:asciiname":"Pashkovy",
    "gn:country_code":"RU",
    "gn:dem":197,
    "gn:feature_class":"P",
    "gn:feature_code":"PPL",
    "gn:name":"Pashkovy",
    "gn:population":0,
    "gn:timezone":"Europe/Kirov",
    "iso:country":"RU",
    "name:rus_x_preferred":[
        "\u041f\u0430\u0448\u043a\u043e\u0432\u044b"
    ],
    "wof:name":"Pashkovy",
    "wof:placetype":"locality"
},
  "geometry": {"coordinates":[47.9915,59.114],"type":"Point"}
}