{
  "type": "Feature",
  "properties": {
    "gn:admin1_code":"12",
    "gn:asciiname":"Terkhi",
    "gn:country_code":"RU",
    "gn:dem":1228,
    "gn:feature_class":"P",
    "gn:feature_code":"PPL",
    "gn:name":"Terkhi",
    "gn:population":0,
    "gn:timezone":"Europe/Moscow",
    "iso:country":"RU",
    "wof:name":"Terkhi",
    "wof:placetype":"locality"
},
  "geometry": {"coordinates":[45.34944,42.90944],"type":"Point"}
}