{
  "type": "Feature",
  "properties": {
    "gn:admin1_code":"55",
    "gn:asciiname":"Marchenko",
    "gn:cc2":"RU",
    "gn:country_code":"RU",
    "gn:dem":394,
    "gn:feature_class":"P",
    "gn:feature_code":"PPL",
    "gn:name":"Marchenko",
    "gn:population":0,
    "gn:timezone":"Asia/Yekaterinburg",
    "iso:country":"RU",
    "name:rus_x_preferred":[
        "\u041c\u0430\u0440\u0447\u0435\u043d\u043a\u043e"
    ],
    "name:und_x_variant":[
        "Marchenkov",
        "Marchenko",
        "\u041c\u0430\u0440\u0447\u0435\u043d\u043a\u043e"
    ],
    "wof:name":"Marchenko",
    "wof:placetype":"locality"
},
  "geometry": {"coordinates":[57.95,51.51667],"type":"Point"}
}