{
  "type": "Feature",
  "properties": {
    "gn:admin1_code":"63",
    "gn:asciiname":"Kelegan",
    "gn:cc2":"RU",
    "gn:country_code":"RU",
    "gn:dem":37,
    "gn:feature_class":"P",
    "gn:feature_code":"PPL",
    "gn:name":"Kelegan",
    "gn:population":0,
    "gn:timezone":"Asia/Magadan",
    "iso:country":"RU",
    "name:rus_x_preferred":[
        "\u041a\u0435\u043b\u0435\u0433\u0430\u043d"
    ],
    "name:und_x_variant":[
        "Kolegay",
        "Kedereen",
        "Kelegkhey",
        "Kelegan",
        "\u041a\u0435\u043b\u0435\u0433\u0430\u043d"
    ],
    "wof:name":"Kelegan",
    "wof:placetype":"locality"
},
  "geometry": {"coordinates":[141.56666999999999,70.23333000000001],"type":"Point"}
}