{
  "type": "Feature",
  "properties": {
    "gn:admin1_code":"73.0",
    "gn:asciiname":"Galimovka",
    "gn:country_code":"RU",
    "gn:dem":205,
    "gn:feature_class":"P",
    "gn:feature_code":"PPL",
    "gn:name":"Galimovka",
    "gn:population":0,
    "gn:timezone":"Europe/Moscow",
    "iso:country":"RU",
    "name:rus_x_preferred":[
        "\u0413\u0430\u043b\u0438\u043c\u043e\u0432\u043a\u0430"
    ],
    "name:und_x_variant":[
        "\u0413\u0430\u043b\u0438\u043c\u043e\u0432\u043a\u0430"
    ],
    "wof:name":"Galimovka",
    "wof:placetype":"locality"
},
  "geometry": {"coordinates":[53.35,54.76667],"type":"Point"}
}