{
  "type": "Feature",
  "properties": {
    "gn:admin1_code":"60",
    "gn:asciiname":"Tokolovo",
    "gn:country_code":"RU",
    "gn:dem":131,
    "gn:feature_class":"P",
    "gn:feature_code":"PPL",
    "gn:name":"Tokolovo",
    "gn:population":0,
    "gn:timezone":"Europe/Moscow",
    "iso:country":"RU",
    "name:eng_x_preferred":[
        "Tokolovo"
    ],
    "name:nor_x_preferred":[
        "Tokolovo"
    ],
    "name:rus_x_preferred":[
        "\u0422\u043e\u043a\u043e\u043b\u043e\u0432\u043e"
    ],
    "name:und_x_variant":[
        "\u0422\u043e\u043a\u043e\u043b\u043e\u0432\u043e"
    ],
    "wof:name":"Tokolovo",
    "wof:placetype":"locality"
},
  "geometry": {"coordinates":[30.54242,56.26778],"type":"Point"}
}