{
  "type": "Feature",
  "properties": {
    "gn:admin1_code":"73",
    "gn:asciiname":"Kzyl-Bayrak",
    "gn:country_code":"RU",
    "gn:dem":191,
    "gn:feature_class":"P",
    "gn:feature_code":"PPL",
    "gn:name":"Kzyl-Bayrak",
    "gn:population":0,
    "gn:timezone":"Europe/Moscow",
    "iso:country":"RU",
    "name:rus_x_preferred":[
        "\u041a\u0437\u044b\u043b-\u0411\u0430\u0439\u0440\u0430\u043a"
    ],
    "name:und_x_variant":[
        "\u041a\u0437\u044b\u043b-\u0411\u0430\u0439\u0440\u0430\u043a"
    ],
    "wof:name":"Kzyl-Bayrak",
    "wof:placetype":"locality"
},
  "geometry": {"coordinates":[52.4504,55.4749],"type":"Point"}
}