{
  "type": "Feature",
  "properties": {
    "gn:admin1_code":"41",
    "gn:asciiname":"Vtoraya Medveditsa",
    "gn:cc2":"RU",
    "gn:country_code":"RU",
    "gn:dem":249,
    "gn:feature_class":"P",
    "gn:feature_code":"PPL",
    "gn:name":"Vtoraya Medveditsa",
    "gn:population":0,
    "gn:timezone":"Europe/Moscow",
    "iso:country":"RU",
    "name:und_x_variant":[
        "Puzanovka",
        "Vtoraya Medveditsa"
    ],
    "wof:name":"Vtoraya Medveditsa",
    "wof:placetype":"locality"
},
  "geometry": {"coordinates":[36.08333,51.85],"type":"Point"}
}