{
  "type": "Feature",
  "properties": {
    "gn:admin1_code":"17.0",
    "gn:asciiname":"Imeni Maksima Gor'kogo",
    "gn:country_code":"RU",
    "gn:dem":-15,
    "gn:feature_class":"P",
    "gn:feature_code":"PPL",
    "gn:name":"Imeni Maksima Gor\u2019kogo",
    "gn:population":0,
    "gn:timezone":"Europe/Moscow",
    "iso:country":"RU",
    "name:rus_x_preferred":[
        "\u0418\u043c\u0435\u043d\u0438 \u041c\u0430\u043a\u0441\u0438\u043c\u0430 \u0413\u043e\u0440\u044c\u043a\u043e\u0433\u043e"
    ],
    "name:und_x_variant":[
        "Maksim Gor\u2019kiy",
        "Imeni Maksima Gor\u2019kogo"
    ],
    "wof:name":"Imeni Maksima Gor'kogo",
    "wof:placetype":"locality"
},
  "geometry": {"coordinates":[46.64431,44.02744000000001],"type":"Point"}
}