{
  "type": "Feature",
  "properties": {
    "gn:admin1_code":"86.0",
    "gn:asciiname":"Shuvalov",
    "gn:country_code":"RU",
    "gn:dem":192,
    "gn:feature_class":"P",
    "gn:feature_code":"PPL",
    "gn:name":"Shuvalov",
    "gn:population":0,
    "gn:timezone":"Europe/Moscow",
    "iso:country":"RU",
    "name:bel_x_preferred":[
        "\u0420\u043e\u0434 \u0428\u0443\u0432\u0430\u043b\u0430\u0432\u044b\u0445"
    ],
    "name:fra_x_preferred":[
        "Famille Chouvalov"
    ],
    "name:jpn_x_preferred":[
        "\u30b7\u30e5\u30f4\u30a1\u30fc\u30ed\u30d5\u5bb6"
    ],
    "name:rus_x_preferred":[
        "\u0428\u0443\u0432\u0430\u043b\u043e\u0432"
    ],
    "name:rus_x_variant":[
        "\u0428\u0443\u0432\u0430\u043b\u043e\u0432\u044b"
    ],
    "wof:name":"Shuvalov",
    "wof:placetype":"locality"
},
  "geometry": {"coordinates":[40.4958,50.5123],"type":"Point"}
}