{
  "type": "Feature",
  "properties": {
    "gn:admin1_code":"86.0",
    "gn:asciiname":"Shuvalov",
    "gn:country_code":"RU",
    "gn:dem":192,
    "gn:feature_class":"P",
    "gn:feature_code":"PPL",
    "gn:name":"Shuvalov",
    "gn:population":0,
    "gn:timezone":"Europe/Moscow",
    "iso:country":"RU",
    "name:rus_x_preferred":[
        "\u0428\u0443\u0432\u0430\u043b\u043e\u0432"
    ],
    "wof:name":"Shuvalov",
    "wof:placetype":"locality"
},
  "geometry": {"coordinates":[40.4958,50.5123],"type":"Point"}
}