{
  "type": "Feature",
  "properties": {
    "gn:admin1_code":"34.0",
    "gn:asciiname":"Akis'",
    "gn:country_code":"RU",
    "gn:dem":41,
    "gn:feature_class":"P",
    "gn:feature_code":"PPL",
    "gn:name":"Akis\u2019",
    "gn:population":0,
    "gn:timezone":"Europe/Moscow",
    "iso:country":"RU",
    "name:eng_x_preferred":[
        "Akis'"
    ],
    "name:nor_x_preferred":[
        "Akis"
    ],
    "name:rus_x_preferred":[
        "\u0410\u043a\u0438\u0441\u044c"
    ],
    "name:und_x_variant":[
        "Smol\u2019nyy Materik",
        "Akichi",
        "Smol\u2019nyy",
        "Akis\u2019"
    ],
    "wof:name":"Akis'",
    "wof:placetype":"locality"
},
  "geometry": {"coordinates":[56.75631,65.8386],"type":"Point"}
}