{
  "type": "Feature",
  "properties": {
    "gn:admin1_code":"10",
    "gn:asciiname":"Korotkiye",
    "gn:country_code":"RU",
    "gn:dem":168,
    "gn:feature_class":"P",
    "gn:feature_code":"PPL",
    "gn:name":"Korotkiye",
    "gn:population":0,
    "gn:timezone":"Europe/Moscow",
    "iso:country":"RU",
    "name:rus_x_preferred":[
        "\u041a\u043e\u0440\u043e\u0442\u043a\u0438\u0435"
    ],
    "wof:name":"Korotkiye",
    "wof:placetype":"locality"
},
  "geometry": {"coordinates":[33.41898,53.10699],"type":"Point"}
}