{
  "type": "Feature",
  "properties": {
    "gn:admin1_code":"83",
    "gn:asciiname":"Ozyablitsy",
    "gn:country_code":"RU",
    "gn:dem":155,
    "gn:feature_class":"P",
    "gn:feature_code":"PPL",
    "gn:name":"Ozyablitsy",
    "gn:population":0,
    "gn:timezone":"Europe/Moscow",
    "iso:country":"RU",
    "name:rus_x_preferred":[
        "\u041e\u0437\u044f\u0431\u043b\u0438\u0446\u044b"
    ],
    "name:und_x_variant":[
        "\u041e\u0437\u044f\u0431\u043b\u0438\u0446\u044b"
    ],
    "wof:name":"Ozyablitsy",
    "wof:placetype":"locality"
},
  "geometry": {"coordinates":[41.1495,55.7722],"type":"Point"}
}