{
  "type": "Feature",
  "properties": {
    "gn:admin1_code":"20",
    "gn:asciiname":"Priboynyy",
    "gn:country_code":"RU",
    "gn:dem":408,
    "gn:feature_class":"P",
    "gn:feature_code":"PPL",
    "gn:name":"Priboynyy",
    "gn:population":0,
    "gn:timezone":"Asia/Irkutsk",
    "iso:country":"RU",
    "name:eng_x_preferred":[
        "Priboynyy"
    ],
    "name:nor_x_preferred":[
        "Pribojnyj"
    ],
    "name:rus_x_preferred":[
        "\u041f\u0440\u0438\u0431\u043e\u0439\u043d\u044b\u0439"
    ],
    "wof:name":"Priboynyy",
    "wof:placetype":"locality"
},
  "geometry": {"coordinates":[103.2273,55.6326],"type":"Point"}
}