{
  "type": "Feature",
  "properties": {
    "gn:admin1_code":"88",
    "gn:asciiname":"Basalayevo",
    "gn:country_code":"RU",
    "gn:dem":133,
    "gn:feature_class":"P",
    "gn:feature_code":"PPL",
    "gn:name":"Basalayevo",
    "gn:population":0,
    "gn:timezone":"Europe/Moscow",
    "iso:country":"RU",
    "name:rus_x_preferred":[
        "\u0411\u0430\u0441\u0430\u043b\u0430\u0435\u0432\u043e"
    ],
    "name:und_x_variant":[
        "\u0411\u0430\u0441\u0430\u043b\u0430\u0435\u0432\u043e"
    ],
    "wof:name":"Basalayevo",
    "wof:placetype":"locality"
},
  "geometry": {"coordinates":[38.849,57.8689],"type":"Point"}
}