{
  "type": "Feature",
  "properties": {
    "gn:admin1_code":"72",
    "gn:asciiname":"Peschanovka",
    "gn:country_code":"RU",
    "gn:dem":141,
    "gn:feature_class":"P",
    "gn:feature_code":"PPL",
    "gn:name":"Peschanovka",
    "gn:population":0,
    "gn:timezone":"Europe/Moscow",
    "iso:country":"RU",
    "name:rus_x_preferred":[
        "\u041f\u0435\u0441\u0447\u0430\u043d\u043e\u0432\u043a\u0430"
    ],
    "wof:name":"Peschanovka",
    "wof:placetype":"locality"
},
  "geometry": {"coordinates":[40.91778,52.12111],"type":"Point"}
}