{
  "type": "Feature",
  "properties": {
    "gn:admin1_code":"45",
    "gn:asciiname":"Kurshakovo",
    "gn:country_code":"RU",
    "gn:dem":139,
    "gn:feature_class":"P",
    "gn:feature_code":"PPL",
    "gn:name":"Kurshakovo",
    "gn:population":0,
    "gn:timezone":"Europe/Moscow",
    "iso:country":"RU",
    "name:rus_x_preferred":[
        "\u041a\u0443\u0440\u0448\u0430\u043a\u043e\u0432\u043e"
    ],
    "name:und_x_variant":[
        "Kurshanovo",
        "Kurshakovo"
    ],
    "wof:name":"Kurshakovo",
    "wof:placetype":"locality"
},
  "geometry": {"coordinates":[49.75261,56.86858],"type":"Point"}
}