{
  "type": "Feature",
  "properties": {
    "gn:admin1_code":"77",
    "gn:asciiname":"Molchanovo",
    "gn:country_code":"RU",
    "gn:dem":195,
    "gn:feature_class":"P",
    "gn:feature_code":"PPL",
    "gn:name":"Molchanovo",
    "gn:population":0,
    "gn:timezone":"Europe/Moscow",
    "iso:country":"RU",
    "name:rus_x_preferred":[
        "\u041c\u043e\u043b\u0447\u0430\u043d\u043e\u0432\u043e"
    ],
    "name:und_x_variant":[
        "\u041c\u043e\u043b\u0447\u0430\u043d\u043e\u0432\u043e"
    ],
    "wof:name":"Molchanovo",
    "wof:placetype":"locality"
},
  "geometry": {"coordinates":[33.72389,57.92389],"type":"Point"}
}