{
  "type": "Feature",
  "properties": {
    "gn:admin1_code":"37.0",
    "gn:asciiname":"Korostelevo",
    "gn:country_code":"RU",
    "gn:dem":95,
    "gn:feature_class":"P",
    "gn:feature_code":"PPL",
    "gn:name":"Korostelevo",
    "gn:population":0,
    "gn:timezone":"Europe/Moscow",
    "iso:country":"RU",
    "name:rus_x_preferred":[
        "\u041a\u043e\u0440\u043e\u0441\u0442\u0435\u043b\u0435\u0432\u043e"
    ],
    "wof:name":"Korostelevo",
    "wof:placetype":"locality"
},
  "geometry": {"coordinates":[41.04236,57.54831],"type":"Point"}
}