{
  "type": "Feature",
  "properties": {
    "gn:admin1_code":"84",
    "gn:asciiname":"Yevlampiyevskiy",
    "gn:country_code":"RU",
    "gn:dem":41,
    "gn:feature_class":"P",
    "gn:feature_code":"PPL",
    "gn:name":"Yevlampiyevskiy",
    "gn:population":0,
    "gn:timezone":"Europe/Volgograd",
    "iso:country":"RU",
    "name:rus_x_preferred":[
        "\u0415\u0432\u043b\u0430\u043c\u043f\u0438\u0435\u0432\u0441\u043a\u0438\u0439"
    ],
    "name:und_x_variant":[
        "Yelampiyevskiy",
        "Yevlampiyevskiy",
        "\u0415\u0432\u043b\u0430\u043c\u043f\u0438\u0435\u0432\u0441\u043a\u0438\u0439"
    ],
    "wof:name":"Yevlampiyevskiy",
    "wof:placetype":"locality"
},
  "geometry": {"coordinates":[43.6262,48.98876],"type":"Point"}
}