{
  "type": "Feature",
  "properties": {
    "gn:admin1_code":"71.0",
    "gn:asciiname":"Novoostrovnaya",
    "gn:country_code":"RU",
    "gn:dem":64,
    "gn:feature_class":"P",
    "gn:feature_code":"PPL",
    "gn:name":"Novoostrovnaya",
    "gn:population":0,
    "gn:timezone":"Asia/Yekaterinburg",
    "iso:country":"RU",
    "name:rus_x_preferred":[
        "\u041d\u043e\u0432\u043e\u043e\u0441\u0442\u0440\u043e\u0432\u043d\u0430\u044f"
    ],
    "wof:name":"Novoostrovnaya",
    "wof:placetype":"locality"
},
  "geometry": {"coordinates":[63.8961,57.99608000000001],"type":"Point"}
}