{
  "type": "Feature",
  "properties": {
    "gn:admin1_code":"12",
    "gn:asciiname":"Berkat-Yurt",
    "gn:country_code":"RU",
    "gn:dem":106,
    "gn:feature_class":"P",
    "gn:feature_code":"PPL",
    "gn:name":"Berkat-Yurt",
    "gn:population":0,
    "gn:timezone":"Europe/Moscow",
    "iso:country":"RU",
    "name:nor_x_preferred":[
        "Berkat-Jurt"
    ],
    "name:rus_x_preferred":[
        "\u0411\u0435\u0440\u043a\u0430\u0442-\u042e\u0440\u0442"
    ],
    "name:und_x_variant":[
        "Berkat-Jurt"
    ],
    "wof:name":"Berkat-Yurt",
    "wof:placetype":"locality"
},
  "geometry": {"coordinates":[45.82408,43.32428],"type":"Point"}
}