{
  "type": "Feature",
  "properties": {
    "gn:admin1_code":"69",
    "gn:asciiname":"Telicheno",
    "gn:country_code":"RU",
    "gn:dem":221,
    "gn:feature_class":"P",
    "gn:feature_code":"PPL",
    "gn:name":"Telicheno",
    "gn:population":0,
    "gn:timezone":"Europe/Moscow",
    "iso:country":"RU",
    "name:rus_x_preferred":[
        "\u0422\u0435\u043b\u0438\u0447\u0435\u043d\u043e"
    ],
    "wof:name":"Telicheno",
    "wof:placetype":"locality"
},
  "geometry": {"coordinates":[32.0083,54.6245],"type":"Point"}
}