{
  "type": "Feature",
  "properties": {
    "gn:admin1_code":"8",
    "gn:asciiname":"Bogomolovka",
    "gn:country_code":"RU",
    "gn:dem":102,
    "gn:feature_class":"P",
    "gn:feature_code":"PPL",
    "gn:name":"Bogomolovka",
    "gn:population":0,
    "gn:timezone":"Asia/Yekaterinburg",
    "iso:country":"RU",
    "name:rus_x_preferred":[
        "\u0411\u043e\u0433\u043e\u043c\u043e\u043b\u043e\u0432\u043a\u0430"
    ],
    "name:und_x_variant":[
        "\u0411\u043e\u0433\u043e\u043c\u043e\u043b\u043e\u0432\u043a\u0430"
    ],
    "wof:name":"Bogomolovka",
    "wof:placetype":"locality"
},
  "geometry": {"coordinates":[55.4744,54.6159],"type":"Point"}
}