{
  "type": "Feature",
  "properties": {
    "gn:admin1_code":"8.0",
    "gn:asciiname":"Butayevo",
    "gn:country_code":"RU",
    "gn:dem":428,
    "gn:feature_class":"P",
    "gn:feature_code":"PPL",
    "gn:name":"Butayevo",
    "gn:population":0,
    "gn:timezone":"Asia/Yekaterinburg",
    "iso:country":"RU",
    "name:bak_x_preferred":[
        "\u0411\u043e\u0442\u0430\u0439"
    ],
    "name:che_x_preferred":[
        "\u0411\u0443\u0442\u0430\u0435\u0432\u043e"
    ],
    "name:eng_x_preferred":[
        "Butayevo"
    ],
    "name:hye_x_preferred":[
        "\u0532\u0578\u0582\u057f\u0561\u0587\u0578"
    ],
    "name:kat_x_preferred":[
        "\u10d1\u10e3\u10e2\u10d0\u10d4\u10d5\u10dd"
    ],
    "name:kaz_x_preferred":[
        "\u0411\u0443\u0442\u0430"
    ],
    "name:nor_x_preferred":[
        "Butajevo"
    ],
    "name:rus_x_preferred":[
        "\u0411\u0443\u0442\u0430\u0435\u0432\u043e"
    ],
    "name:tat_x_preferred":[
        "\u0411\u043e\u0442\u0430\u0439"
    ],
    "name:ukr_x_preferred":[
        "\u0411\u0443\u0442\u0430\u0454\u0432\u043e"
    ],
    "name:und_x_variant":[
        "Butayeva",
        "\u0411\u0443\u0442\u0430\u0435\u0432\u043e",
        "Butayevo"
    ],
    "wof:name":"Butayevo",
    "wof:placetype":"locality"
},
  "geometry": {"coordinates":[57.2898,53.8292],"type":"Point"}
}