{
  "type": "Feature",
  "properties": {
    "gn:admin1_code":"71.0",
    "gn:asciiname":"Vyatkina",
    "gn:country_code":"RU",
    "gn:dem":65,
    "gn:feature_class":"P",
    "gn:feature_code":"PPL",
    "gn:name":"Vyatkina",
    "gn:population":0,
    "gn:timezone":"Asia/Yekaterinburg",
    "iso:country":"RU",
    "name:rus_x_preferred":[
        "\u0412\u044f\u0442\u043a\u0438\u043d\u0430"
    ],
    "wof:name":"Vyatkina",
    "wof:placetype":"locality"
},
  "geometry": {"coordinates":[63.33807,57.58788000000001],"type":"Point"}
}