{
  "type": "Feature",
  "properties": {
    "gn:admin1_code":"84",
    "gn:asciiname":"Khovanskiy",
    "gn:country_code":"RU",
    "gn:dem":62,
    "gn:feature_class":"P",
    "gn:feature_code":"PPL",
    "gn:name":"Khovanskiy",
    "gn:population":0,
    "gn:timezone":"Europe/Volgograd",
    "iso:country":"RU",
    "name:eng_x_preferred":[
        "Khovanskiy"
    ],
    "name:nor_x_preferred":[
        "Khovanskij"
    ],
    "name:rus_x_preferred":[
        "\u0425\u043e\u0432\u0430\u043d\u0441\u043a\u0438\u0439"
    ],
    "wof:name":"Khovanskiy",
    "wof:placetype":"locality"
},
  "geometry": {"coordinates":[42.548,49.5811],"type":"Point"}
}