{
  "type": "Feature",
  "properties": {
    "gn:admin1_code":"61",
    "gn:asciiname":"Kuteynikov",
    "gn:country_code":"RU",
    "gn:dem":121,
    "gn:feature_class":"P",
    "gn:feature_code":"PPL",
    "gn:name":"Kuteynikov",
    "gn:population":0,
    "gn:timezone":"Europe/Moscow",
    "iso:country":"RU",
    "name:eng_x_preferred":[
        "Kuteynikov"
    ],
    "name:nor_x_preferred":[
        "Kutejnikov"
    ],
    "name:rus_x_preferred":[
        "\u041a\u0443\u0442\u0435\u0439\u043d\u0438\u043a\u043e\u0432"
    ],
    "name:und_x_variant":[
        "Kuteynikovo"
    ],
    "wof:name":"Kuteynikov",
    "wof:placetype":"locality"
},
  "geometry": {"coordinates":[41.87589000000001,48.90564000000001],"type":"Point"}
}