{
  "type": "Feature",
  "properties": {
    "gn:admin1_code":"33",
    "gn:asciiname":"Kiselikha",
    "gn:country_code":"RU",
    "gn:dem":159,
    "gn:feature_class":"P",
    "gn:feature_code":"PPL",
    "gn:name":"Kiselikha",
    "gn:population":0,
    "gn:timezone":"Europe/Kirov",
    "iso:country":"RU",
    "name:rus_x_preferred":[
        "\u041a\u0438\u0441\u0435\u043b\u0438\u0445\u0430"
    ],
    "name:und_x_variant":[
        "Kuselikha",
        "Kiselikha"
    ],
    "wof:name":"Kiselikha",
    "wof:placetype":"locality"
},
  "geometry": {"coordinates":[50.02687,57.9883],"type":"Point"}
}