{
  "type": "Feature",
  "properties": {
    "gn:admin1_code":"51",
    "gn:asciiname":"Berdnichikha",
    "gn:country_code":"RU",
    "gn:dem":116,
    "gn:feature_class":"P",
    "gn:feature_code":"PPL",
    "gn:name":"Berdnichikha",
    "gn:population":0,
    "gn:timezone":"Europe/Moscow",
    "iso:country":"RU",
    "name:rus_x_preferred":[
        "\u0411\u0435\u0440\u0434\u043d\u0438\u0447\u0438\u0445\u0430"
    ],
    "wof:name":"Berdnichikha",
    "wof:placetype":"locality"
},
  "geometry": {"coordinates":[45.0132,57.4599],"type":"Point"}
}