{
  "type": "Feature",
  "properties": {
    "gn:admin1_code":"77",
    "gn:asciiname":"Ragozino",
    "gn:country_code":"RU",
    "gn:dem":158,
    "gn:feature_class":"P",
    "gn:feature_code":"PPL",
    "gn:name":"Ragozino",
    "gn:population":0,
    "gn:timezone":"Europe/Moscow",
    "iso:country":"RU",
    "name:rus_x_preferred":[
        "\u0420\u0430\u0433\u043e\u0437\u0438\u043d\u043e"
    ],
    "wof:name":"Ragozino",
    "wof:placetype":"locality"
},
  "geometry": {"coordinates":[34.48228,57.66781],"type":"Point"}
}