{
  "type": "Feature",
  "properties": {
    "gn:admin1_code":"90.0",
    "gn:asciiname":"Goldyrevskiy",
    "gn:country_code":"RU",
    "gn:dem":210,
    "gn:feature_class":"P",
    "gn:feature_code":"PPL",
    "gn:name":"Goldyrevskiy",
    "gn:population":0,
    "gn:timezone":"Asia/Yekaterinburg",
    "iso:country":"RU",
    "name:eng_x_preferred":[
        "Goldyrevskiy"
    ],
    "name:nor_x_preferred":[
        "Goldyrevskij"
    ],
    "name:rus_x_preferred":[
        "\u0413\u043e\u043b\u0434\u044b\u0440\u0435\u0432\u0441\u043a\u0438\u0439"
    ],
    "name:und_x_variant":[
        "\u0413\u043e\u043b\u0434\u044b\u0440\u0435\u0432\u0441\u043a\u0438\u0439"
    ],
    "wof:name":"Goldyrevskiy",
    "wof:placetype":"locality"
},
  "geometry": {"coordinates":[57.0391,57.2634],"type":"Point"}
}