{
  "type": "Feature",
  "properties": {
    "gn:admin1_code":"53",
    "gn:asciiname":"Krasnovka",
    "gn:country_code":"RU",
    "gn:dem":145,
    "gn:feature_class":"P",
    "gn:feature_code":"PPL",
    "gn:name":"Krasnovka",
    "gn:population":0,
    "gn:timezone":"Asia/Novosibirsk",
    "iso:country":"RU",
    "name:eng_x_preferred":[
        "Krasnovka"
    ],
    "name:nor_x_preferred":[
        "Krasnovka"
    ],
    "name:rus_x_preferred":[
        "\u041a\u0440\u0430\u0441\u043d\u043e\u0432\u043a\u0430"
    ],
    "name:und_x_variant":[
        "Krasnovskiy"
    ],
    "wof:name":"Krasnovka",
    "wof:placetype":"locality"
},
  "geometry": {"coordinates":[80.65889,55.19917],"type":"Point"}
}