{
  "type": "Feature",
  "properties": {
    "gn:country":"RU",
    "gn:fcode":"PPLX",
    "gn:pop":13011,
    "iso:country":"RU",
    "name:cat_x_preferred":[
        "Vostotxni"
    ],
    "name:ceb_x_preferred":[
        "\u0412\u043e\u0441\u0442\u043e\u0447\u043d\u044b\u0439"
    ],
    "name:deu_x_preferred":[
        "Wostotschny"
    ],
    "name:ita_x_preferred":[
        "Vosto\u010dnyj"
    ],
    "name:jpn_x_preferred":[
        "\u30dc\u30b9\u30c8\u30c1\u30cc\u30a4"
    ],
    "name:rus_x_preferred":[
        "\u0412\u043e\u0441\u0442\u043e\u0447\u043d\u044b\u0439"
    ],
    "name:sco_x_preferred":[
        "Vostochny"
    ],
    "name:spa_x_preferred":[
        "Vostochni"
    ],
    "name:ukr_x_preferred":[
        "\u0412\u043e\u0441\u0442\u043e\u0447\u043d\u0438\u0439"
    ],
    "name:unk_x_variant":[
        "Stalinskiy"
    ],
    "qs:name":"Vostochnyy",
    "qs:photos_9r":0,
    "qs:photos_sr":0,
    "qs:pop_sr":"6",
    "wd:wordcount":64,
    "wof:name":"Vostochnyy",
    "wof:placetype":"neighbourhood",
    "wof:population":13011
},
  "geometry": {"coordinates":[37.86667,55.81667],"type":"Point"}
}