{
  "type": "Feature",
  "properties": {
    "gn:country":"RU",
    "gn:fcode":"PPLX",
    "gn:pop":13011,
    "iso:country":"RU",
    "name:rus_x_preferred":[
        "\u0412\u043e\u0441\u0442\u043e\u0447\u043d\u044b\u0439"
    ],
    "name:unk_x_variant":[
        "Stalinskiy"
    ],
    "qs:name":"Vostochnyy",
    "qs:photos_9r":0,
    "qs:photos_sr":0,
    "qs:pop_sr":"6",
    "wd:wordcount":64,
    "wof:name":"Vostochnyy",
    "wof:placetype":"neighbourhood",
    "wof:population":13011
},
  "geometry": {"coordinates":[37.86667,55.81667],"type":"Point"}
}