{
  "type": "Feature",
  "properties": {
    "gn:admin1_code":"81",
    "gn:asciiname":"Rashtanovka",
    "gn:country_code":"RU",
    "gn:dem":279,
    "gn:feature_class":"P",
    "gn:feature_code":"PPL",
    "gn:name":"Rashtanovka",
    "gn:population":0,
    "gn:timezone":"Europe/Ulyanovsk",
    "iso:country":"RU",
    "name:rus_x_preferred":[
        "\u0420\u0430\u0448\u0442\u0430\u043d\u043e\u0432\u043a\u0430"
    ],
    "wof:name":"Rashtanovka",
    "wof:placetype":"locality"
},
  "geometry": {"coordinates":[47.23761,52.84001],"type":"Point"}
}