{
  "type": "Feature",
  "properties": {
    "gn:admin1_code":"63",
    "gn:asciiname":"Uchyugey-Kyuyel'",
    "gn:country_code":"RU",
    "gn:dem":186,
    "gn:feature_class":"P",
    "gn:feature_code":"PPL",
    "gn:name":"Uchyugey-Kyuyel\u2019",
    "gn:population":0,
    "gn:timezone":"Asia/Yakutsk",
    "iso:country":"RU",
    "name:und_x_variant":[
        "Yuchyugey-Kyuyel\u2019",
        "Uchyugey-Kyuyel\u2019"
    ],
    "wof:name":"Uchyugey-Kyuyel'",
    "wof:placetype":"locality"
},
  "geometry": {"coordinates":[133.56666999999999,61.93333000000001],"type":"Point"}
}