{
  "type": "Feature",
  "properties": {
    "gn:admin1_code":"84",
    "gn:asciiname":"Sadovoye",
    "gn:cc2":"RU",
    "gn:country_code":"RU",
    "gn:dem":22,
    "gn:feature_class":"P",
    "gn:feature_code":"PPL",
    "gn:name":"Sadovoye",
    "gn:population":0,
    "gn:timezone":"Europe/Volgograd",
    "iso:country":"RU",
    "name:rus_x_preferred":[
        "\u0421\u0430\u0434\u043e\u0432\u043e\u0435"
    ],
    "name:und_x_variant":[
        "Sadovyy",
        "Sadovoye"
    ],
    "wof:name":"Sadovoye",
    "wof:placetype":"locality"
},
  "geometry": {"coordinates":[46.16667,49.46667],"type":"Point"}
}