{
  "type": "Feature",
  "properties": {
    "gn:admin1_code":"65",
    "gn:asciiname":"Vladimirovka",
    "gn:country_code":"RU",
    "gn:dem":139,
    "gn:feature_class":"P",
    "gn:feature_code":"PPL",
    "gn:name":"Vladimirovka",
    "gn:population":0,
    "gn:timezone":"Europe/Samara",
    "iso:country":"RU",
    "name:rus_x_preferred":[
        "\u0412\u043b\u0430\u0434\u0438\u043c\u0438\u0440\u043e\u0432\u043a\u0430"
    ],
    "name:und_x_variant":[
        "\u0412\u043b\u0430\u0434\u0438\u043c\u0438\u0440\u043e\u0432\u043a\u0430"
    ],
    "wof:name":"Vladimirovka",
    "wof:placetype":"locality"
},
  "geometry": {"coordinates":[51.5224,54.1711],"type":"Point"}
}