{
  "type": "Feature",
  "properties": {
    "gn:admin1_code":"90",
    "gn:asciiname":"Verkhnyaya Urmeya",
    "gn:country_code":"RU",
    "gn:dem":229,
    "gn:feature_class":"P",
    "gn:feature_code":"PPL",
    "gn:name":"Verkhnyaya Urmeya",
    "gn:population":0,
    "gn:timezone":"Asia/Yekaterinburg",
    "iso:country":"RU",
    "name:rus_x_preferred":[
        "\u0412\u0435\u0440\u0445\u043d\u044f\u044f \u0423\u0440\u043c\u0435\u044f"
    ],
    "name:und_x_variant":[
        "Verkhnyaya Urmiya",
        "Verkhnyaya Urmeya"
    ],
    "wof:name":"Verkhnyaya Urmeya",
    "wof:placetype":"locality"
},
  "geometry": {"coordinates":[56.83894,56.19024],"type":"Point"}
}