{
  "type": "Feature",
  "properties": {
    "gn:admin1_code":"8.0",
    "gn:asciiname":"Aksaitovo",
    "gn:country_code":"RU",
    "gn:dem":127,
    "gn:feature_class":"P",
    "gn:feature_code":"PPL",
    "gn:name":"Aksaitovo",
    "gn:population":0,
    "gn:timezone":"Asia/Yekaterinburg",
    "iso:country":"RU",
    "name:eng_x_preferred":[
        "Aksaitovo"
    ],
    "name:nor_x_preferred":[
        "Aksaitovo"
    ],
    "name:rus_x_preferred":[
        "\u0410\u043a\u0441\u0430\u0438\u0442\u043e\u0432\u043e"
    ],
    "name:und_x_variant":[
        "\u0410\u043a\u0441\u0430\u0438\u0442\u043e\u0432\u043e",
        "Aksaitovo"
    ],
    "wof:name":"Aksaitovo",
    "wof:placetype":"locality"
},
  "geometry": {"coordinates":[55.598,56.3627],"type":"Point"}
}