{
  "type": "Feature",
  "properties": {
    "gn:admin1_code":"60",
    "gn:asciiname":"Maloye Grabovo",
    "gn:country_code":"RU",
    "gn:dem":94,
    "gn:feature_class":"P",
    "gn:feature_code":"PPL",
    "gn:name":"Maloye Grabovo",
    "gn:population":0,
    "gn:timezone":"Europe/Moscow",
    "iso:country":"RU",
    "name:rus_x_preferred":[
        "\u041c\u0430\u043b\u043e\u0435 \u0413\u0440\u0430\u0431\u043e\u0432\u043e"
    ],
    "wof:name":"Maloye Grabovo",
    "wof:placetype":"locality"
},
  "geometry": {"coordinates":[30.0831,57.1471],"type":"Point"}
}