{
  "type": "Feature",
  "properties": {
    "gn:admin1_code":"69",
    "gn:asciiname":"Ratkevshchina",
    "gn:country_code":"RU",
    "gn:dem":235,
    "gn:feature_class":"P",
    "gn:feature_code":"PPL",
    "gn:name":"Ratkevshchina",
    "gn:population":0,
    "gn:timezone":"Europe/Moscow",
    "iso:country":"RU",
    "name:rus_x_preferred":[
        "\u0420\u0430\u0442\u043a\u0435\u0432\u0449\u0438\u043d\u0430"
    ],
    "name:und_x_variant":[
        "\u0420\u0430\u0442\u043a\u0435\u0432\u0449\u0438\u043d\u0430"
    ],
    "wof:name":"Ratkevshchina",
    "wof:placetype":"locality"
},
  "geometry": {"coordinates":[31.94929,54.69136999999999],"type":"Point"}
}