{
  "type": "Feature",
  "properties": {
    "gn:admin1_code":"40",
    "gn:asciiname":"Adzhitarovo",
    "gn:country_code":"RU",
    "gn:dem":184,
    "gn:feature_class":"P",
    "gn:feature_code":"PPL",
    "gn:name":"Adzhitarovo",
    "gn:population":0,
    "gn:timezone":"Asia/Yekaterinburg",
    "iso:country":"RU",
    "name:eng_x_preferred":[
        "Adzhitarovo"
    ],
    "name:rus_x_preferred":[
        "\u0411\u043e\u043b.\u0410\u0434\u0436\u0438\u0442\u0430\u0440\u043e\u0432\u043e"
    ],
    "name:rus_x_variant":[
        "\u0410\u0434\u0436\u0438\u0442\u0430\u0440\u043e\u0432\u043e"
    ],
    "name:und_x_variant":[
        "Adzhikulevo"
    ],
    "wof:name":"Adzhitarovo",
    "wof:placetype":"locality"
},
  "geometry": {"coordinates":[62.1365,54.962],"type":"Point"}
}