{
  "type": "Feature",
  "properties": {
    "gn:admin1_code":"20",
    "gn:asciiname":"Ponomareva",
    "gn:country_code":"RU",
    "gn:dem":478,
    "gn:feature_class":"P",
    "gn:feature_code":"PPL",
    "gn:name":"Ponomar\u00ebva",
    "gn:population":0,
    "gn:timezone":"Asia/Irkutsk",
    "iso:country":"RU",
    "name:rus_x_preferred":[
        "\u041f\u043e\u043d\u043e\u043c\u0430\u0440\u0451\u0432\u0430"
    ],
    "name:und_x_variant":[
        "Ponomar\u00ebva"
    ],
    "wof:name":"Ponomareva",
    "wof:placetype":"locality"
},
  "geometry": {"coordinates":[103.65000000000001,52.95],"type":"Point"}
}