{
  "type": "Feature",
  "properties": {
    "gn:admin1_code":"53",
    "gn:asciiname":"Kamen'",
    "gn:country_code":"RU",
    "gn:dem":94,
    "gn:feature_class":"P",
    "gn:feature_code":"PPL",
    "gn:name":"Kamen\u2019",
    "gn:population":0,
    "gn:timezone":"Asia/Novosibirsk",
    "iso:country":"RU",
    "name:eng_x_preferred":[
        "Kamen'"
    ],
    "name:nor_x_preferred":[
        "Kamen"
    ],
    "name:rus_x_preferred":[
        "\u041a\u0430\u043c\u0435\u043d\u044c"
    ],
    "name:und_x_variant":[
        "\u041a\u0430\u043c\u0435\u043d\u044c",
        "Kamen\u2019"
    ],
    "wof:name":"Kamen'",
    "wof:placetype":"locality"
},
  "geometry": {"coordinates":[83.6703,55.6251],"type":"Point"}
}