{
  "type": "Feature",
  "properties": {
    "gn:admin1_code":"11",
    "gn:asciiname":"Komsomol'skoye",
    "gn:country_code":"RU",
    "gn:dem":862,
    "gn:feature_class":"P",
    "gn:feature_code":"PPL",
    "gn:name":"Komsomol\u2019skoye",
    "gn:population":0,
    "gn:timezone":"Asia/Irkutsk",
    "iso:country":"RU",
    "name:eng_x_preferred":[
        "Komsomol'skoye"
    ],
    "name:nor_x_preferred":[
        "Komsomolskoje"
    ],
    "name:rus_x_preferred":[
        "\u041a\u043e\u043c\u0441\u043e\u043c\u043e\u043b\u044c\u0441\u043a\u043e\u0435"
    ],
    "name:und_x_variant":[
        "Pogrominskoye",
        "Pogromnoye",
        "\u041a\u043e\u043c\u0441\u043e\u043c\u043e\u043b\u044c\u0441\u043a\u043e\u0435",
        "Komsomol\u2019skoye"
    ],
    "wof:name":"Komsomol'skoye",
    "wof:placetype":"locality"
},
  "geometry": {"coordinates":[111.08886,52.48116],"type":"Point"}
}