{
  "type": "Feature",
  "properties": {
    "gn:admin1_code":"69.0",
    "gn:asciiname":"Dedovo",
    "gn:country_code":"RU",
    "gn:dem":223,
    "gn:feature_class":"P",
    "gn:feature_code":"PPL",
    "gn:name":"Dedovo",
    "gn:population":0,
    "gn:timezone":"Europe/Moscow",
    "iso:country":"RU",
    "name:bul_x_preferred":[
        "\u0414\u0435\u0434\u043e\u0432\u043e"
    ],
    "name:fas_x_preferred":[
        "\u062f\u062f\u0648\u0648\u0648"
    ],
    "name:kaz_x_preferred":[
        "\u0414\u0435\u0434\u043e\u0432\u043e"
    ],
    "name:pol_x_preferred":[
        "Dedowo"
    ],
    "name:ron_x_preferred":[
        "Dedovo"
    ],
    "name:rus_x_preferred":[
        "\u0414\u0435\u0434\u043e\u0432\u043e"
    ],
    "name:ukr_x_preferred":[
        "\u0414\u0435\u0434\u043e\u0432\u043e"
    ],
    "name:und_x_variant":[
        "Dedova"
    ],
    "wof:name":"Dedovo",
    "wof:placetype":"locality"
},
  "geometry": {"coordinates":[32.9758,55.3202],"type":"Point"}
}