{
  "type": "Feature",
  "properties": {
    "gn:admin1_code":"85",
    "gn:asciiname":"Borodino",
    "gn:country_code":"RU",
    "gn:dem":150,
    "gn:feature_class":"P",
    "gn:feature_code":"PPL",
    "gn:name":"Borodino",
    "gn:population":0,
    "gn:timezone":"Europe/Moscow",
    "iso:country":"RU",
    "name:rus_x_preferred":[
        "\u0411\u043e\u0440\u043e\u0434\u0438\u043d\u043e"
    ],
    "name:und_x_variant":[
        "\u0411\u043e\u0440\u043e\u0434\u0438\u043d\u043e"
    ],
    "wof:name":"Borodino",
    "wof:placetype":"locality"
},
  "geometry": {"coordinates":[36.2439,58.6696],"type":"Point"}
}