{
  "type": "Feature",
  "properties": {
    "gn:admin1_code":"91",
    "gn:asciiname":"Muratovo",
    "gn:country_code":"RU",
    "gn:dem":215,
    "gn:feature_class":"P",
    "gn:feature_code":"PPL",
    "gn:name":"Muratovo",
    "gn:population":0,
    "gn:timezone":"Asia/Krasnoyarsk",
    "iso:country":"RU",
    "name:eng_x_preferred":[
        "Muratovo"
    ],
    "name:nor_x_preferred":[
        "Muratovo"
    ],
    "name:rus_x_preferred":[
        "\u041c\u0443\u0440\u0430\u0442\u043e\u0432\u043e"
    ],
    "wof:name":"Muratovo",
    "wof:placetype":"locality"
},
  "geometry": {"coordinates":[93.3043,57.1874],"type":"Point"}
}