{
  "type": "Feature",
  "properties": {
    "gn:admin1_code":"9",
    "gn:asciiname":"Meshkovoye",
    "gn:country_code":"RU",
    "gn:dem":188,
    "gn:feature_class":"P",
    "gn:feature_code":"PPL",
    "gn:name":"Meshkovoye",
    "gn:population":0,
    "gn:timezone":"Europe/Moscow",
    "iso:country":"RU",
    "name:rus_x_preferred":[
        "\u041c\u0435\u0448\u043a\u043e\u0432\u043e\u0435"
    ],
    "name:und_x_variant":[
        "\u041c\u0435\u0448\u043a\u043e\u0432\u043e\u0435"
    ],
    "wof:name":"Meshkovoye",
    "wof:placetype":"locality"
},
  "geometry": {"coordinates":[37.4291,50.4836],"type":"Point"}
}