{
  "type": "Feature",
  "properties": {
    "gn:admin1_code":"11",
    "gn:asciiname":"Dureny",
    "gn:cc2":"RU",
    "gn:country_code":"RU",
    "gn:dem":605,
    "gn:feature_class":"P",
    "gn:feature_code":"PPL",
    "gn:name":"Dureny",
    "gn:population":0,
    "gn:timezone":"Asia/Irkutsk",
    "iso:country":"RU",
    "name:eng_x_preferred":[
        "Dureny"
    ],
    "name:nor_x_preferred":[
        "Dureny"
    ],
    "name:rus_x_preferred":[
        "\u0414\u0443\u0440\u0435\u043d\u044b"
    ],
    "name:und_x_variant":[
        "Durenskaya",
        "\u0414\u0443\u0440\u0435\u043d\u044b",
        "Dureny"
    ],
    "wof:name":"Dureny",
    "wof:placetype":"locality"
},
  "geometry": {"coordinates":[106.89417,50.31861],"type":"Point"}
}