{
  "type": "Feature",
  "properties": {
    "gn:admin1_code":"73.0",
    "gn:asciiname":"Bol'shoye Tyaberdino",
    "gn:country_code":"RU",
    "gn:dem":94,
    "gn:feature_class":"P",
    "gn:feature_code":"PPL",
    "gn:name":"Bol\u2019shoye Tyaberdino",
    "gn:population":0,
    "gn:timezone":"Europe/Moscow",
    "iso:country":"RU",
    "name:rus_x_preferred":[
        "\u0411\u043e\u043b\u044c\u0448\u043e\u0435 \u0422\u044f\u0431\u0435\u0440\u0434\u0438\u043d\u043e"
    ],
    "name:und_x_variant":[
        "Bol\u2019shoye Tyaberdino"
    ],
    "wof:name":"Bol'shoye Tyaberdino",
    "wof:placetype":"locality"
},
  "geometry": {"coordinates":[47.72468,55.27444000000001],"type":"Point"}
}