{
  "type": "Feature",
  "properties": {
    "gn:admin1_code":"90.0",
    "gn:asciiname":"Parfenova",
    "gn:country_code":"RU",
    "gn:dem":187,
    "gn:feature_class":"P",
    "gn:feature_code":"PPL",
    "gn:name":"Parfenova",
    "gn:population":0,
    "gn:timezone":"Asia/Yekaterinburg",
    "iso:country":"RU",
    "name:rus_x_preferred":[
        "\u041f\u0430\u0440\u0444\u0435\u043d\u043e\u0432\u0430"
    ],
    "wof:name":"Parfenova",
    "wof:placetype":"locality"
},
  "geometry": {"coordinates":[54.2719,58.8583],"type":"Point"}
}