{
  "type": "Feature",
  "properties": {
    "gn:admin1_code":"63",
    "gn:asciiname":"Okhotskiy Perevoz",
    "gn:country_code":"RU",
    "gn:dem":138,
    "gn:feature_class":"P",
    "gn:feature_code":"PPL",
    "gn:name":"Okhotskiy Perevoz",
    "gn:population":0,
    "gn:timezone":"Asia/Vladivostok",
    "iso:country":"RU",
    "name:eng_x_preferred":[
        "Okhotskiy Perevoz"
    ],
    "name:nor_x_preferred":[
        "Okhotskij Perevoz"
    ],
    "name:rus_x_preferred":[
        "\u041e\u0445\u043e\u0442\u0441\u043a\u0438\u0439 \u041f\u0435\u0440\u0435\u0432\u043e\u0437"
    ],
    "wof:name":"Okhotskiy Perevoz",
    "wof:placetype":"locality"
},
  "geometry": {"coordinates":[135.52690000000001,61.87801],"type":"Point"}
}