{
  "type": "Feature",
  "properties": {
    "gn:admin1_code":"81",
    "gn:asciiname":"Poddubnoye",
    "gn:country_code":"RU",
    "gn:dem":165,
    "gn:feature_class":"P",
    "gn:feature_code":"PPL",
    "gn:name":"Poddubnoye",
    "gn:population":0,
    "gn:timezone":"Europe/Ulyanovsk",
    "iso:country":"RU",
    "name:rus_x_preferred":[
        "\u041f\u043e\u0434\u0434\u0443\u0431\u043d\u043e\u0435"
    ],
    "name:und_x_variant":[
        "Staraya Domoserdka",
        "Staryye Domoserdki",
        "Poddubnoye",
        "\u041f\u043e\u0434\u0434\u0443\u0431\u043d\u043e\u0435"
    ],
    "wof:name":"Poddubnoye",
    "wof:placetype":"locality"
},
  "geometry": {"coordinates":[46.45462,53.7257],"type":"Point"}
}