{
  "type": "Feature",
  "properties": {
    "gn:admin1_code":"9",
    "gn:asciiname":"Verkhneyablonovo",
    "gn:country_code":"RU",
    "gn:dem":93,
    "gn:feature_class":"P",
    "gn:feature_code":"PPL",
    "gn:name":"Verkhneyablonovo",
    "gn:population":0,
    "gn:timezone":"Europe/Moscow",
    "iso:country":"RU",
    "name:rus_x_preferred":[
        "\u0412\u0435\u0440\u0445\u043d\u0435\u044f\u0431\u043b\u043e\u043d\u043e\u0432\u043e"
    ],
    "wof:name":"Verkhneyablonovo",
    "wof:placetype":"locality"
},
  "geometry": {"coordinates":[37.8206,50.3752],"type":"Point"}
}