{
  "type": "Feature",
  "properties": {
    "gn:admin1_code":"56",
    "gn:asciiname":"Azarovo",
    "gn:country_code":"RU",
    "gn:dem":194,
    "gn:feature_class":"P",
    "gn:feature_code":"PPL",
    "gn:name":"Azarovo",
    "gn:population":0,
    "gn:timezone":"Europe/Moscow",
    "iso:country":"RU",
    "name:nor_x_preferred":[
        "Azarovo"
    ],
    "name:rus_x_preferred":[
        "\u0410\u0437\u0430\u0440\u043e\u0432\u043e"
    ],
    "wof:name":"Azarovo",
    "wof:placetype":"locality"
},
  "geometry": {"coordinates":[35.34472,53.18],"type":"Point"}
}