{
  "type": "Feature",
  "properties": {
    "gn:country":"RU",
    "gn:fcode":"PPL",
    "gn:pop":0,
    "iso:country":"RU",
    "name:rus_x_preferred":[
        "\u0422\u0440\u043e\u0438\u0446\u0430"
    ],
    "name:unk_x_variant":[
        "\u0422\u0440\u043e\u0438\u0446\u0430"
    ],
    "qs:name":"Troitsa",
    "qs:name_adm0":"Russia",
    "qs:name_adm1":"Pskov Oblast",
    "qs:photos_9r":0,
    "qs:photos_sr":0,
    "qs:placetype":"Town",
    "qs:pop_sr":"0",
    "wd:wordcount":575,
    "wof:name":"Troitsa",
    "wof:placetype":"locality",
    "wof:population":0
},
  "geometry": {"coordinates":[30.68031,56.03883],"type":"Point"}
}