{
  "type": "Feature",
  "properties": {
    "gn:admin1_code":"33",
    "gn:asciiname":"Lopanur",
    "gn:country_code":"RU",
    "gn:dem":106,
    "gn:feature_class":"P",
    "gn:feature_code":"PPL",
    "gn:name":"Lopanur",
    "gn:population":0,
    "gn:timezone":"Europe/Kirov",
    "iso:country":"RU",
    "name:rus_x_preferred":[
        "\u041b\u043e\u043f\u0430\u043d\u0443\u0440"
    ],
    "wof:name":"Lopanur",
    "wof:placetype":"locality"
},
  "geometry": {"coordinates":[46.9818,56.9747],"type":"Point"}
}