{
  "type": "Feature",
  "properties": {
    "gn:admin1_code":"63",
    "gn:asciiname":"Mon'obut",
    "gn:country_code":"RU",
    "gn:dem":191,
    "gn:feature_class":"P",
    "gn:feature_code":"PPL",
    "gn:name":"Mon\u2019obut",
    "gn:population":0,
    "gn:timezone":"Asia/Yakutsk",
    "iso:country":"RU",
    "name:rus_x_preferred":[
        "\u041c\u043e\u043d\u044c\u043e\u0431\u0443\u0442"
    ],
    "name:und_x_variant":[
        "Moonn\u2019oobut",
        "Mon\u2019obut",
        "\u041c\u043e\u043d\u044c\u043e\u0431\u0443\u0442"
    ],
    "wof:name":"Mon'obut",
    "wof:placetype":"locality"
},
  "geometry": {"coordinates":[131.33333000000002,58.93333000000001],"type":"Point"}
}