{
  "type": "Feature",
  "properties": {
    "gn:admin1_code":"84",
    "gn:asciiname":"Karaitskiy",
    "gn:country_code":"RU",
    "gn:dem":52,
    "gn:feature_class":"P",
    "gn:feature_code":"PPL",
    "gn:name":"Karaitskiy",
    "gn:population":0,
    "gn:timezone":"Europe/Volgograd",
    "iso:country":"RU",
    "name:rus_x_preferred":[
        "\u041a\u0430\u0440\u0430\u0438\u0442\u0441\u043a\u0438\u0439"
    ],
    "wof:name":"Karaitskiy",
    "wof:placetype":"locality"
},
  "geometry": {"coordinates":[43.7591,49.18295],"type":"Point"}
}