{
  "type": "Feature",
  "properties": {
    "gn:admin1_code":"76.0",
    "gn:asciiname":"Belyayevo",
    "gn:country_code":"RU",
    "gn:dem":208,
    "gn:feature_class":"P",
    "gn:feature_code":"PPL",
    "gn:name":"Belyayevo",
    "gn:population":0,
    "gn:timezone":"Europe/Moscow",
    "iso:country":"RU",
    "name:nor_x_preferred":[
        "Beljaevo"
    ],
    "name:rus_x_preferred":[
        "\u0411\u0435\u043b\u044f\u0435\u0432\u043e"
    ],
    "wof:name":"Belyayevo",
    "wof:placetype":"locality"
},
  "geometry": {"coordinates":[36.69275,54.27826999999999],"type":"Point"}
}