{
  "type": "Feature",
  "properties": {
    "gn:admin1_code":"84.0",
    "gn:asciiname":"Dinamo",
    "gn:country_code":"RU",
    "gn:dem":206,
    "gn:feature_class":"P",
    "gn:feature_code":"PPL",
    "gn:name":"Dinamo",
    "gn:population":0,
    "gn:timezone":"Europe/Volgograd",
    "iso:country":"RU",
    "name:eng_x_preferred":[
        "Dinamo"
    ],
    "name:nor_x_preferred":[
        "Dinamo"
    ],
    "name:rus_x_preferred":[
        "\u0414\u0438\u043d\u0430\u043c\u043e"
    ],
    "wof:name":"Dinamo",
    "wof:placetype":"locality"
},
  "geometry": {"coordinates":[41.65600000000001,50.2448],"type":"Point"}
}