{
  "type": "Feature",
  "properties": {
    "gn:admin1_code":"69",
    "gn:asciiname":"Korennoye",
    "gn:country_code":"RU",
    "gn:dem":248,
    "gn:feature_class":"P",
    "gn:feature_code":"PPL",
    "gn:name":"Korennoye",
    "gn:population":0,
    "gn:timezone":"Europe/Moscow",
    "iso:country":"RU",
    "name:rus_x_preferred":[
        "\u041a\u043e\u0440\u0435\u043d\u043d\u043e\u0435"
    ],
    "wof:name":"Korennoye",
    "wof:placetype":"locality"
},
  "geometry": {"coordinates":[35.25611,55.54667],"type":"Point"}
}