{
  "type": "Feature",
  "properties": {
    "gn:admin1_code":"21",
    "gn:asciiname":"Shel'bovo",
    "gn:country_code":"RU",
    "gn:dem":131,
    "gn:feature_class":"P",
    "gn:feature_code":"PPL",
    "gn:name":"Shel\u2019bovo",
    "gn:population":0,
    "gn:timezone":"Europe/Moscow",
    "iso:country":"RU",
    "name:rus_x_preferred":[
        "\u0428\u0435\u043b\u044c\u0431\u043e\u0432\u043e"
    ],
    "name:und_x_variant":[
        "Shel\u2019bovo"
    ],
    "wof:name":"Shel'bovo",
    "wof:placetype":"locality"
},
  "geometry": {"coordinates":[39.9644,56.55862],"type":"Point"}
}