{
  "type": "Feature",
  "properties": {
    "gn:admin1_code":"61",
    "gn:asciiname":"Metelev",
    "gn:country_code":"RU",
    "gn:dem":22,
    "gn:feature_class":"P",
    "gn:feature_code":"PPL",
    "gn:name":"Metel\u00ebv",
    "gn:population":0,
    "gn:timezone":"Europe/Moscow",
    "iso:country":"RU",
    "name:rus_x_preferred":[
        "\u041c\u0435\u0442\u0435\u043b\u0451\u0432"
    ],
    "name:und_x_variant":[
        "Metelov",
        "Metel\u00ebv"
    ],
    "wof:name":"Metelev",
    "wof:placetype":"locality"
},
  "geometry": {"coordinates":[39.0737,46.8822],"type":"Point"}
}