{
  "type": "Feature",
  "properties": {
    "gn:admin1_code":"61",
    "gn:asciiname":"Gorbatov",
    "gn:country_code":"RU",
    "gn:dem":114,
    "gn:feature_class":"P",
    "gn:feature_code":"PPL",
    "gn:name":"Gorbatov",
    "gn:population":0,
    "gn:timezone":"Europe/Moscow",
    "iso:country":"RU",
    "name:eng_x_preferred":[
        "Gorbatov"
    ],
    "name:nor_x_preferred":[
        "Gorbatovskij"
    ],
    "name:rus_x_preferred":[
        "\u0413\u043e\u0440\u0431\u0430\u0442\u043e\u0432\u0441\u043a\u0438\u0439"
    ],
    "name:rus_x_variant":[
        "\u0413\u043e\u0440\u0431\u0430\u0442\u043e\u0432"
    ],
    "name:und_x_variant":[
        "\u0413\u043e\u0440\u0431\u0430\u0442\u043e\u0432"
    ],
    "wof:name":"Gorbatov",
    "wof:placetype":"locality"
},
  "geometry": {"coordinates":[42.0273,49.3546],"type":"Point"}
}