{
  "type": "Feature",
  "properties": {
    "gn:country":"RU",
    "gn:fcode":"PPL",
    "gn:population":0,
    "iso:country":"RU",
    "name:che_x_preferred":[
        "\u0412\u0435\u0440\u0448\u0438\u043d\u0438\u043d\u043e"
    ],
    "name:deu_x_preferred":[
        "Werschinino"
    ],
    "name:eng_x_preferred":[
        "Vershinino"
    ],
    "name:nor_x_preferred":[
        "Versjinino"
    ],
    "name:rus_x_preferred":[
        "\u0412\u0435\u0440\u0448\u0438\u043d\u0438\u043d\u043e"
    ],
    "name:ukr_x_preferred":[
        "\u0412\u0435\u0440\u0448\u0438\u043d\u0438\u043d\u043e"
    ],
    "name:und_x_variant":[
        "Vershinina"
    ],
    "qs:name":"Vershinino",
    "qs:name_adm0":"Russia",
    "qs:name_adm1":"Tomsk Oblast",
    "qs:photos_9k":1,
    "qs:photos_9r":1,
    "qs:photos_all":2,
    "qs:photos_sr":0,
    "qs:placetype":"Town",
    "qs:pop_sr":"0",
    "wd:wordcount":201,
    "wof:name":"Vershinino",
    "wof:placetype":"locality",
    "wof:population":0
},
  "geometry": {"coordinates":[84.92551,56.22756],"type":"Point"}
}