{
  "type": "Feature",
  "properties": {
    "gn:admin1_code":"42.0",
    "gn:admin2_code":"575409",
    "gn:asciiname":"Mozolevo-2",
    "gn:country_code":"RU",
    "gn:dem":75,
    "gn:feature_class":"P",
    "gn:feature_code":"PPL",
    "gn:name":"Mozolevo-2",
    "gn:population":0,
    "gn:timezone":"Europe/Moscow",
    "iso:country":"RU",
    "name:rus_x_preferred":[
        "\u041c\u043e\u0437\u043e\u043b\u0435\u0432\u043e-2"
    ],
    "wof:name":"Mozolevo-2",
    "wof:placetype":"locality"
},
  "geometry": {"coordinates":[33.83853,59.32162],"type":"Point"}
}