{
  "type": "Feature",
  "properties": {
    "gn:admin1_code":"51.0",
    "gn:asciiname":"Filyukovo",
    "gn:country_code":"RU",
    "gn:dem":169,
    "gn:feature_class":"P",
    "gn:feature_code":"PPL",
    "gn:name":"Filyukovo",
    "gn:population":0,
    "gn:timezone":"Europe/Moscow",
    "iso:country":"RU",
    "name:eng_x_preferred":[
        "Filyukovo"
    ],
    "name:nor_x_preferred":[
        "Filjukovo"
    ],
    "name:rus_x_preferred":[
        "\u0424\u0438\u043b\u044e\u043a\u043e\u0432\u043e"
    ],
    "name:und_x_variant":[
        "\u0424\u0438\u043b\u044e\u043a\u043e\u0432\u043e",
        "Filyukovo"
    ],
    "wof:name":"Filyukovo",
    "wof:placetype":"locality"
},
  "geometry": {"coordinates":[42.9683,55.7411],"type":"Point"}
}