{
  "type": "Feature",
  "properties": {
    "gn:admin1_code":"38",
    "gn:asciiname":"Leninskiy",
    "gn:country_code":"RU",
    "gn:dem":24,
    "gn:feature_class":"P",
    "gn:feature_code":"PPL",
    "gn:name":"Leninskiy",
    "gn:population":0,
    "gn:timezone":"Europe/Moscow",
    "iso:country":"RU",
    "name:eng_x_preferred":[
        "Leninskiy"
    ],
    "name:nor_x_preferred":[
        "Leninskij"
    ],
    "name:rus_x_preferred":[
        "\u041b\u0435\u043d\u0438\u043d\u0441\u043a\u0438\u0439"
    ],
    "name:und_x_variant":[
        "Leininskiy Rashpil\u2019",
        "\u041b\u0435\u043d\u0438\u043d\u0441\u043a\u0438\u0439",
        "Leninskiy"
    ],
    "wof:name":"Leninskiy",
    "wof:placetype":"locality"
},
  "geometry": {"coordinates":[39.07334,45.4057],"type":"Point"}
}