{
  "type": "Feature",
  "properties": {
    "gn:admin1_code":"56",
    "gn:asciiname":"Khmelevaya",
    "gn:country_code":"RU",
    "gn:dem":212,
    "gn:feature_class":"P",
    "gn:feature_code":"PPL",
    "gn:name":"Khmel\u00ebvaya",
    "gn:population":0,
    "gn:timezone":"Europe/Moscow",
    "iso:country":"RU",
    "name:rus_x_preferred":[
        "\u0425\u043c\u0435\u043b\u0451\u0432\u0430\u044f"
    ],
    "name:und_x_variant":[
        "Khmel\u00ebvaya",
        "\u0425\u043c\u0435\u043b\u0451\u0432\u0430\u044f"
    ],
    "wof:name":"Khmelevaya",
    "wof:placetype":"locality"
},
  "geometry": {"coordinates":[35.44876,52.74397],"type":"Point"}
}