{
  "type": "Feature",
  "properties": {
    "gn:admin1_code":"59.0",
    "gn:asciiname":"Kedrovyy",
    "gn:country_code":"RU",
    "gn:dem":44,
    "gn:feature_class":"P",
    "gn:feature_code":"PPL",
    "gn:name":"Kedrovyy",
    "gn:population":0,
    "gn:timezone":"Asia/Vladivostok",
    "iso:country":"RU",
    "name:rus_x_preferred":[
        "\u041a\u0435\u0434\u0440\u043e\u0432\u044b\u0439"
    ],
    "wof:name":"Kedrovyy",
    "wof:placetype":"locality"
},
  "geometry": {"coordinates":[131.52611999999999,43.03761],"type":"Point"}
}