{
  "type": "Feature",
  "properties": {
    "gn:admin1_code":"73",
    "gn:asciiname":"Tatarskiye Shatrashany",
    "gn:country_code":"RU",
    "gn:dem":126,
    "gn:feature_class":"P",
    "gn:feature_code":"PPL",
    "gn:name":"Tatarskiye Shatrashany",
    "gn:population":0,
    "gn:timezone":"Europe/Moscow",
    "iso:country":"RU",
    "name:rus_x_preferred":[
        "\u0422\u0430\u0442\u0430\u0440\u0441\u043a\u0438\u0435 \u0428\u0430\u0442\u0440\u0430\u0448\u0430\u043d\u044b"
    ],
    "name:und_x_variant":[
        "Shatrashany",
        "Tatarskiye Shatrashany"
    ],
    "wof:name":"Tatarskiye Shatrashany",
    "wof:placetype":"locality"
},
  "geometry": {"coordinates":[47.3882,54.5507],"type":"Point"}
}