{
  "type": "Feature",
  "properties": {
    "gn:admin1_code":"85",
    "gn:asciiname":"Piksimovo",
    "gn:country_code":"RU",
    "gn:dem":163,
    "gn:feature_class":"P",
    "gn:feature_code":"PPL",
    "gn:name":"Piksimovo",
    "gn:population":0,
    "gn:timezone":"Europe/Moscow",
    "iso:country":"RU",
    "name:eng_x_preferred":[
        "Piksimovo"
    ],
    "name:nor_x_preferred":[
        "Piksimovo"
    ],
    "name:rus_x_preferred":[
        "\u041f\u0438\u043a\u0441\u0438\u043c\u043e\u0432\u043e"
    ],
    "wof:name":"Piksimovo",
    "wof:placetype":"locality"
},
  "geometry": {"coordinates":[37.656,60.4586],"type":"Point"}
}