{
  "type": "Feature",
  "properties": {
    "gn:admin1_code":"77",
    "gn:asciiname":"Poved'",
    "gn:country_code":"RU",
    "gn:dem":186,
    "gn:feature_class":"P",
    "gn:feature_code":"PPL",
    "gn:name":"Poved\u2019",
    "gn:population":0,
    "gn:timezone":"Europe/Moscow",
    "iso:country":"RU",
    "name:rus_x_preferred":[
        "\u041f\u043e\u0432\u0435\u0434\u044c"
    ],
    "name:und_x_variant":[
        "Poved\u2019"
    ],
    "wof:name":"Poved'",
    "wof:placetype":"locality"
},
  "geometry": {"coordinates":[34.60720999999999,57.20413000000001],"type":"Point"}
}