{
  "type": "Feature",
  "properties": {
    "gn:gn_country":"RU",
    "gn:gn_fcode":"PPL",
    "gn:gn_pop":16404,
    "gn:population":16404,
    "iso:country":"RU",
    "name:ara_x_preferred":[
        "\u064a\u064a\u0645\u0641\u0627"
    ],
    "name:azb_x_preferred":[
        "\u06cc\u0645\u0648\u0627"
    ],
    "name:aze_x_preferred":[
        "Yemva"
    ],
    "name:bel_x_preferred":[
        "\u0415\u043c\u0432\u0430"
    ],
    "name:bul_x_preferred":[
        "\u0415\u043c\u0432\u0430"
    ],
    "name:cat_x_preferred":[
        "Iemva"
    ],
    "name:ceb_x_preferred":[
        "Yemva"
    ],
    "name:ces_x_preferred":[
        "Jemva"
    ],
    "name:deu_x_preferred":[
        "Jemwa"
    ],
    "name:eng_x_preferred":[
        "Yemva"
    ],
    "name:epo_x_preferred":[
        "Jemva"
    ],
    "name:est_x_preferred":[
        "Jemva"
    ],
    "name:fas_x_preferred":[
        "\u06cc\u0645\u0648\u0627"
    ],
    "name:fin_x_preferred":[
        "Jemva"
    ],
    "name:fra_x_preferred":[
        "Iemva"
    ],
    "name:heb_x_preferred":[
        "\u05d9\u05de\u05d1\u05d4"
    ],
    "name:hsb_x_preferred":[
        "Jemwa"
    ],
    "name:hun_x_preferred":[
        "Jemva"
    ],
    "name:ita_x_preferred":[
        "Emva"
    ],
    "name:koi_x_preferred":[
        "\u0415\u043c\u0432\u0430"
    ],
    "name:kom_x_preferred":[
        "\u0415\u043c\u0432\u0430"
    ],
    "name:myv_x_preferred":[
        "\u0415\u043c\u0432\u0430 \u043e\u0448"
    ],
    "name:nld_x_preferred":[
        "Jemva"
    ],
    "name:nno_x_preferred":[
        "Jemva"
    ],
    "name:nob_x_preferred":[
        "Jemva"
    ],
    "name:nor_x_preferred":[
        "Zjeleznodorozjnyj"
    ],
    "name:pol_x_preferred":[
        "Jemwa"
    ],
    "name:rus_x_preferred":[
        "\u0416\u0435\u043b\u0435\u0437\u043d\u043e\u0434\u043e\u0440\u043e\u0436\u043d\u044b\u0439"
    ],
    "name:rus_x_variant":[
        "\u0415\u043c\u0432\u0430"
    ],
    "name:spa_x_preferred":[
        "Yemva"
    ],
    "name:srp_x_preferred":[
        "\u0408\u0435\u043c\u0432\u0430"
    ],
    "name:tat_x_preferred":[
        "\u0415\u043c\u0432\u0430"
    ],
    "name:tgk_x_preferred":[
        "\u0415\u043c\u0432\u0430"
    ],
    "name:tgl_x_preferred":[
        "Yemva"
    ],
    "name:tur_x_preferred":[
        "Yemva"
    ],
    "name:ukr_x_preferred":[
        "\u0404\u043c\u0432\u0430"
    ],
    "name:unk_x_variant":[
        "Zheleznodorozhnyy"
    ],
    "name:vep_x_preferred":[
        "Jemv"
    ],
    "name:war_x_preferred":[
        "Yemva"
    ],
    "name:xal_x_preferred":[
        "\u0415\u043c\u0432\u0430 \u0431\u0430\u043b\u04bb\u0441\u043d"
    ],
    "name:zho_x_preferred":[
        "\u8449\u59c6\u74e6"
    ],
    "qs_pg:aaroncc":"RU",
    "qs_pg:gn_country":"RU",
    "qs_pg:gn_fcode":"PPL",
    "qs_pg:gn_pop":16404,
    "qs_pg:name":"Lymva",
    "qs_pg:name_adm0":"Russia",
    "qs_pg:name_adm1":"Komi Republic",
    "qs_pg:photos_9r":0,
    "qs_pg:photos_sr":0,
    "qs_pg:pop_sr":6,
    "qs_pg:qs_pg_placetype":"locality",
    "qs_pg:qs_pg_placetype_gp":"Town",
    "qs_pg:woe_adm0":23424936,
    "woe:adm0_id":23424936,
    "woe:name_adm0":"Russia",
    "woe:name_adm1":"Komi Republic",
    "woe:placetype":"Town",
    "wof:name":"Lymva",
    "wof:placetype":"locality",
    "wof:population":16404
},
  "geometry": {"coordinates":[50.85939,62.58999],"type":"Point"}
}