{
  "type": "Feature",
  "properties": {
    "gn:admin1_code":"63",
    "gn:asciiname":"Sharabarina",
    "gn:country_code":"RU",
    "gn:dem":159,
    "gn:feature_class":"P",
    "gn:feature_code":"PPL",
    "gn:name":"Sharabarina",
    "gn:population":0,
    "gn:timezone":"Asia/Vladivostok",
    "iso:country":"RU",
    "name:rus_x_preferred":[
        "\u0428\u0430\u0440\u0430\u0431\u0430\u0440\u0438\u043d\u0430"
    ],
    "wof:name":"Sharabarina",
    "wof:placetype":"locality"
},
  "geometry": {"coordinates":[135.01667,60.58333],"type":"Point"}
}