{
  "type": "Feature",
  "properties": {
    "gn:admin1_code":"42",
    "gn:asciiname":"Shipkovo",
    "gn:cc2":"RU",
    "gn:country_code":"RU",
    "gn:dem":193,
    "gn:feature_class":"P",
    "gn:feature_code":"PPL",
    "gn:name":"Shipkovo",
    "gn:population":0,
    "gn:timezone":"Europe/Moscow",
    "iso:country":"RU",
    "name:bul_x_preferred":[
        "\u0428\u0438\u043f\u043a\u043e\u0432\u043e"
    ],
    "name:ceb_x_preferred":[
        "Shipkovo"
    ],
    "name:fas_x_preferred":[
        "\u0634\u06cc\u067e\u06a9\u0648\u0648\u0648"
    ],
    "name:kaz_x_preferred":[
        "\u0428\u0438\u043f\u043a\u043e\u0432\u043e"
    ],
    "name:pol_x_preferred":[
        "Szipkowo"
    ],
    "name:ron_x_preferred":[
        "\u0218ipkovo"
    ],
    "name:rus_x_preferred":[
        "\u0428\u0438\u043f\u043a\u043e\u0432\u043e"
    ],
    "name:swe_x_preferred":[
        "Sjipkovo"
    ],
    "name:ukr_x_preferred":[
        "\u0428\u0438\u043f\u043a\u043e\u0432\u043e"
    ],
    "name:und_x_variant":[
        "Shibkovo",
        "Shipkovo",
        "\u0428\u0438\u043f\u043a\u043e\u0432\u043e"
    ],
    "wof:name":"Shipkovo",
    "wof:placetype":"locality"
},
  "geometry": {"coordinates":[34.21667,59.48333],"type":"Point"}
}