{
  "type": "Feature",
  "properties": {
    "gn:admin1_code":"33",
    "gn:asciiname":"Vysokovo",
    "gn:country_code":"RU",
    "gn:dem":190,
    "gn:feature_class":"P",
    "gn:feature_code":"PPL",
    "gn:name":"Vysokovo",
    "gn:population":0,
    "gn:timezone":"Europe/Kirov",
    "iso:country":"RU",
    "name:eng_x_preferred":[
        "Vysokovo"
    ],
    "name:nor_x_preferred":[
        "Vysokovo"
    ],
    "name:rus_x_preferred":[
        "\u0412\u044b\u0441\u043e\u043a\u043e\u0432\u043e"
    ],
    "wof:name":"Vysokovo",
    "wof:placetype":"locality"
},
  "geometry": {"coordinates":[49.21771,59.12628],"type":"Point"}
}