{
  "type": "Feature",
  "properties": {
    "gn:admin1_code":"37",
    "gn:asciiname":"Yelegino",
    "gn:country_code":"RU",
    "gn:dem":183,
    "gn:feature_class":"P",
    "gn:feature_code":"PPL",
    "gn:name":"Yelegino",
    "gn:population":0,
    "gn:timezone":"Europe/Moscow",
    "iso:country":"RU",
    "name:eng_x_preferred":[
        "Yelegino"
    ],
    "name:nor_x_preferred":[
        "Jelegino"
    ],
    "name:rus_x_preferred":[
        "\u0415\u043b\u0435\u0433\u0438\u043d\u043e"
    ],
    "name:und_x_variant":[
        "Yelagina"
    ],
    "wof:name":"Yelegino",
    "wof:placetype":"locality"
},
  "geometry": {"coordinates":[41.91891,58.71298],"type":"Point"}
}