{
  "type": "Feature",
  "properties": {
    "gn:admin1_code":"72",
    "gn:asciiname":"Novocherkasovka",
    "gn:country_code":"RU",
    "gn:dem":169,
    "gn:feature_class":"P",
    "gn:feature_code":"PPL",
    "gn:name":"Novocherkasovka",
    "gn:population":0,
    "gn:timezone":"Europe/Moscow",
    "iso:country":"RU",
    "name:rus_x_preferred":[
        "\u041d\u043e\u0432\u043e\u0447\u0435\u0440\u043a\u0430\u0441\u043e\u0432\u043a\u0430"
    ],
    "name:und_x_variant":[
        "Novo-Cherkassy",
        "Novocherkasovka",
        "\u041d\u043e\u0432\u043e\u0447\u0435\u0440\u043a\u0430\u0441\u043e\u0432\u043a\u0430"
    ],
    "wof:name":"Novocherkasovka",
    "wof:placetype":"locality"
},
  "geometry": {"coordinates":[41.21384000000001,53.43086],"type":"Point"}
}