{
  "type": "Feature",
  "properties": {
    "gn:admin1_code":"23",
    "gn:asciiname":"Shmelevo",
    "gn:country_code":"RU",
    "gn:dem":18,
    "gn:feature_class":"P",
    "gn:feature_code":"PPL",
    "gn:name":"Shmel\u00ebvo",
    "gn:population":0,
    "gn:timezone":"Europe/Kaliningrad",
    "iso:country":"RU",
    "name:rus_x_preferred":[
        "\u0428\u043c\u0435\u043b\u0451\u0432\u043e"
    ],
    "name:und_x_variant":[
        "Shmel\u00ebvo",
        "\u0428\u043c\u0435\u043b\u0451\u0432\u043e"
    ],
    "wof:name":"Shmelevo",
    "wof:placetype":"locality"
},
  "geometry": {"coordinates":[22.10444,54.81472],"type":"Point"}
}