{
  "type": "Feature",
  "properties": {
    "gn:admin1_code":"91",
    "gn:asciiname":"Zhivotnovod",
    "gn:country_code":"RU",
    "gn:dem":124,
    "gn:feature_class":"P",
    "gn:feature_code":"PPL",
    "gn:name":"Zhivotnovod",
    "gn:population":0,
    "gn:timezone":"Asia/Krasnoyarsk",
    "iso:country":"RU",
    "wof:name":"Zhivotnovod",
    "wof:placetype":"locality"
},
  "geometry": {"coordinates":[92.46666999999999,58.13333000000001],"type":"Point"}
}