{
  "type": "Feature",
  "properties": {
    "gn:admin1_code":"40",
    "gn:asciiname":"Skaty",
    "gn:country_code":"RU",
    "gn:dem":107,
    "gn:feature_class":"P",
    "gn:feature_code":"PPL",
    "gn:name":"Skaty",
    "gn:population":0,
    "gn:timezone":"Asia/Yekaterinburg",
    "iso:country":"RU",
    "name:eng_x_preferred":[
        "Skaty"
    ],
    "name:nor_x_preferred":[
        "Skaty"
    ],
    "name:rus_x_preferred":[
        "\u0421\u043a\u0430\u0442\u044b"
    ],
    "wof:name":"Skaty",
    "wof:placetype":"locality"
},
  "geometry": {"coordinates":[65.30639000000001,55.71444],"type":"Point"}
}