{
  "type": "Feature",
  "properties": {
    "gn:admin1_code":"6",
    "gn:asciiname":"Kraskovo",
    "gn:country_code":"RU",
    "gn:dem":127,
    "gn:feature_class":"P",
    "gn:feature_code":"PPL",
    "gn:name":"Kraskovo",
    "gn:population":0,
    "gn:timezone":"Europe/Moscow",
    "iso:country":"RU",
    "name:eng_x_preferred":[
        "Kraskovo"
    ],
    "name:nor_x_preferred":[
        "Kraskovo"
    ],
    "name:rus_x_preferred":[
        "\u041a\u0440\u0430\u0441\u043a\u043e\u0432\u043e"
    ],
    "name:und_x_variant":[
        "\u041a\u0440\u0430\u0441\u043a\u043e\u0432\u043e",
        "Kraskovo"
    ],
    "wof:name":"Kraskovo",
    "wof:placetype":"locality"
},
  "geometry": {"coordinates":[39.26239,60.75688],"type":"Point"}
}