{
  "type": "Feature",
  "properties": {
    "gn:admin1_code":"8",
    "gn:asciiname":"Romanovka",
    "gn:country_code":"RU",
    "gn:dem":146,
    "gn:feature_class":"P",
    "gn:feature_code":"PPL",
    "gn:name":"Romanovka",
    "gn:population":0,
    "gn:timezone":"Asia/Yekaterinburg",
    "iso:country":"RU",
    "name:ceb_x_preferred":[
        "Romanovka"
    ],
    "name:lav_x_preferred":[
        "Romanovka"
    ],
    "name:rus_x_preferred":[
        "\u0420\u043e\u043c\u0430\u043d\u043e\u0432\u043a\u0430"
    ],
    "name:swe_x_preferred":[
        "Romanovka"
    ],
    "wof:name":"Romanovka",
    "wof:placetype":"locality"
},
  "geometry": {"coordinates":[55.487,54.33165],"type":"Point"}
}