{
  "type": "Feature",
  "properties": {
    "gn:country":"RU",
    "gn:fcode":"PPL",
    "gn:population":8117,
    "iso:country":"RU",
    "name:eng_x_preferred":[
        "Krasnokholmskiy"
    ],
    "name:nor_x_preferred":[
        "Krasnokholmskij"
    ],
    "name:rus_x_preferred":[
        "\u041a\u0440\u0430\u0441\u043d\u043e\u0445\u043e\u043b\u043c\u0441\u043a\u0438\u0439"
    ],
    "name:und_x_variant":[
        "Kranokholmskiy"
    ],
    "qs_pg:aaroncc":"RU",
    "qs_pg:gn_country":"RU",
    "qs_pg:gn_fcode":"PPL",
    "qs_pg:gn_pop":8117,
    "qs_pg:name":"Krasnokholmskiy",
    "qs_pg:photos_9r":0,
    "qs_pg:photos_sr":0,
    "qs_pg:pop_sr":5,
    "qs_pg:qs_pg_placetype":"locality",
    "wof:name":"Krasnokholmskiy",
    "wof:placetype":"locality",
    "wof:population":8117
},
  "geometry": {"coordinates":[55.04659,55.98729],"type":"Point"}
}