{
  "type": "Feature",
  "properties": {
    "gn:admin1_code":"13",
    "gn:asciiname":"Rassypukha",
    "gn:country_code":"RU",
    "gn:dem":455,
    "gn:feature_class":"P",
    "gn:feature_code":"PPL",
    "gn:name":"Rassypukha",
    "gn:population":0,
    "gn:timezone":"Asia/Yekaterinburg",
    "iso:country":"RU",
    "name:eng_x_preferred":[
        "Rassypukha"
    ],
    "name:nor_x_preferred":[
        "Rassypukha"
    ],
    "name:rus_x_preferred":[
        "\u0420\u0430\u0441\u0441\u044b\u043f\u0443\u0445\u0430"
    ],
    "name:und_x_variant":[
        "\u0420\u0430\u0441\u0441\u044b\u043f\u0443\u0445\u0430",
        "Rassypukha"
    ],
    "wof:name":"Rassypukha",
    "wof:placetype":"locality"
},
  "geometry": {"coordinates":[60.08333,55.56667],"type":"Point"}
}