{
  "type": "Feature",
  "properties": {
    "gn:admin1_code":"69",
    "gn:asciiname":"Kuprinki",
    "gn:country_code":"RU",
    "gn:dem":233,
    "gn:feature_class":"P",
    "gn:feature_code":"PPL",
    "gn:name":"Kuprinki",
    "gn:population":0,
    "gn:timezone":"Europe/Moscow",
    "iso:country":"RU",
    "name:rus_x_preferred":[
        "\u041a\u0443\u043f\u0440\u0438\u043d\u043a\u0438"
    ],
    "wof:name":"Kuprinki",
    "wof:placetype":"locality"
},
  "geometry": {"coordinates":[32.3106,55.3781],"type":"Point"}
}