{
  "type": "Feature",
  "properties": {
    "gn:admin1_code":"52",
    "gn:asciiname":"Tyurikovo",
    "gn:country_code":"RU",
    "gn:dem":94,
    "gn:feature_class":"P",
    "gn:feature_code":"PPL",
    "gn:name":"Tyurikovo",
    "gn:population":0,
    "gn:timezone":"Europe/Moscow",
    "iso:country":"RU",
    "name:rus_x_preferred":[
        "\u0422\u044e\u0440\u0438\u043a\u043e\u0432\u043e"
    ],
    "name:und_x_variant":[
        "\u0422\u044e\u0440\u0438\u043a\u043e\u0432\u043e"
    ],
    "wof:name":"Tyurikovo",
    "wof:placetype":"locality"
},
  "geometry": {"coordinates":[30.537,57.719],"type":"Point"}
}