{
  "type": "Feature",
  "properties": {
    "gn:admin1_code":"51",
    "gn:asciiname":"Ivanchikha",
    "gn:country_code":"RU",
    "gn:dem":118,
    "gn:feature_class":"P",
    "gn:feature_code":"PPL",
    "gn:name":"Ivanchikha",
    "gn:population":0,
    "gn:timezone":"Europe/Moscow",
    "iso:country":"RU",
    "name:rus_x_preferred":[
        "\u0418\u0432\u0430\u043d\u0447\u0438\u0445\u0430"
    ],
    "name:und_x_variant":[
        "\u0418\u0432\u0430\u043d\u0447\u0438\u0445\u0430"
    ],
    "wof:name":"Ivanchikha",
    "wof:placetype":"locality"
},
  "geometry": {"coordinates":[45.2164,57.7149],"type":"Point"}
}