{
  "type": "Feature",
  "properties": {
    "gn:country":"RU",
    "gn:fcode":"PPL",
    "gn:population":0,
    "iso:country":"RU",
    "name:rus_x_preferred":[
        "\u0425\u043c\u0435\u043b\u0451\u0432\u043a\u0430"
    ],
    "name:und_x_variant":[
        "Khmel\u00ebvka"
    ],
    "qs:name":"Khmelevka",
    "qs:name_adm0":"Russia",
    "qs:name_adm1":"Saratov Oblast",
    "qs:photos_9r":0,
    "qs:photos_sr":0,
    "qs:placetype":"Town",
    "qs:pop_sr":"0",
    "wof:name":"Khmelevka",
    "wof:placetype":"locality",
    "wof:population":0
},
  "geometry": {"coordinates":[45.85528,51.37611],"type":"Point"}
}