{
  "type": "Feature",
  "properties": {
    "gn:admin1_code":"71",
    "gn:asciiname":"Kornilovskiy",
    "gn:country_code":"RU",
    "gn:dem":93,
    "gn:feature_class":"P",
    "gn:feature_code":"PPL",
    "gn:name":"Kornilovskiy",
    "gn:population":0,
    "gn:timezone":"Asia/Yekaterinburg",
    "iso:country":"RU",
    "name:rus_x_preferred":[
        "\u041a\u043e\u0440\u043d\u0438\u043b\u043e\u0432\u0441\u043a\u0438\u0439"
    ],
    "wof:name":"Kornilovskiy",
    "wof:placetype":"locality"
},
  "geometry": {"coordinates":[63.65,58.85],"type":"Point"}
}