{
  "type": "Feature",
  "properties": {
    "gn:admin1_code":"25",
    "gn:asciiname":"Rukav",
    "gn:country_code":"RU",
    "gn:dem":198,
    "gn:feature_class":"P",
    "gn:feature_code":"PPL",
    "gn:name":"Rukav",
    "gn:population":0,
    "gn:timezone":"Europe/Moscow",
    "iso:country":"RU",
    "name:rus_x_preferred":[
        "\u0420\u0443\u043a\u0430\u0432"
    ],
    "wof:name":"Rukav",
    "wof:placetype":"locality"
},
  "geometry": {"coordinates":[35.063,53.96006],"type":"Point"}
}