{
  "type": "Feature",
  "properties": {
    "gn:admin1_code":"13",
    "gn:asciiname":"Kavardina",
    "gn:country_code":"RU",
    "gn:dem":281,
    "gn:feature_class":"P",
    "gn:feature_code":"PPL",
    "gn:name":"Kavardina",
    "gn:population":0,
    "gn:timezone":"Asia/Yekaterinburg",
    "iso:country":"RU",
    "name:rus_x_preferred":[
        "\u041a\u0430\u0432\u0430\u0440\u0434\u0438\u043d\u0430"
    ],
    "wof:name":"Kavardina",
    "wof:placetype":"locality"
},
  "geometry": {"coordinates":[60.91667,54.53333000000001],"type":"Point"}
}