{
  "type": "Feature",
  "properties": {
    "gn:admin1_code":"86",
    "gn:asciiname":"Golosnovka",
    "gn:country_code":"RU",
    "gn:dem":186,
    "gn:feature_class":"P",
    "gn:feature_code":"PPL",
    "gn:name":"Golosnovka",
    "gn:population":0,
    "gn:timezone":"Europe/Moscow",
    "iso:country":"RU",
    "name:rus_x_preferred":[
        "\u0413\u043e\u043b\u043e\u0441\u043d\u043e\u0432\u043a\u0430"
    ],
    "name:und_x_variant":[
        "Golaya Snova",
        "Golosnovka",
        "\u0413\u043e\u043b\u043e\u0441\u043d\u043e\u0432\u043a\u0430"
    ],
    "wof:name":"Golosnovka",
    "wof:placetype":"locality"
},
  "geometry": {"coordinates":[38.5731,52.01337],"type":"Point"}
}