{
  "type": "Feature",
  "properties": {
    "gn:admin1_code":"51.0",
    "gn:asciiname":"Duplikha",
    "gn:country_code":"RU",
    "gn:dem":114,
    "gn:feature_class":"P",
    "gn:feature_code":"PPL",
    "gn:name":"Duplikha",
    "gn:population":0,
    "gn:timezone":"Europe/Moscow",
    "iso:country":"RU",
    "name:rus_x_preferred":[
        "\u0414\u0443\u043f\u043b\u0438\u0445\u0430"
    ],
    "name:und_x_variant":[
        "\u0414\u0443\u043f\u043b\u0438\u0445\u0430"
    ],
    "wof:name":"Duplikha",
    "wof:placetype":"locality"
},
  "geometry": {"coordinates":[45.22591,56.99715],"type":"Point"}
}