{
  "type": "Feature",
  "properties": {
    "gn:admin1_code":"8",
    "gn:asciiname":"Timofeyevka",
    "gn:country_code":"RU",
    "gn:dem":188,
    "gn:feature_class":"P",
    "gn:feature_code":"PPL",
    "gn:name":"Timofeyevka",
    "gn:population":0,
    "gn:timezone":"Asia/Yekaterinburg",
    "iso:country":"RU",
    "name:rus_x_preferred":[
        "\u0422\u0438\u043c\u043e\u0444\u0435\u0435\u0432\u043a\u0430"
    ],
    "wof:name":"Timofeyevka",
    "wof:placetype":"locality"
},
  "geometry": {"coordinates":[53.79196,54.07546],"type":"Point"}
}