{
  "type": "Feature",
  "properties": {
    "gn:admin1_code":"28",
    "gn:asciiname":"Ruskaset",
    "gn:country_code":"RU",
    "gn:dem":81,
    "gn:feature_class":"P",
    "gn:feature_code":"PPL",
    "gn:name":"Ruskaset",
    "gn:population":0,
    "gn:timezone":"Europe/Moscow",
    "iso:country":"RU",
    "name:fin_x_preferred":[
        "Ruuskaset"
    ],
    "name:rus_x_preferred":[
        "\u0420\u0443\u0441\u043a\u0430\u0441\u0435\u0442"
    ],
    "wof:name":"Ruskaset",
    "wof:placetype":"locality"
},
  "geometry": {"coordinates":[31.43017,61.68938000000001],"type":"Point"}
}