{
  "type": "Feature",
  "properties": {
    "gn:admin1_code":"77",
    "gn:asciiname":"Bredniki",
    "gn:country_code":"RU",
    "gn:dem":268,
    "gn:feature_class":"P",
    "gn:feature_code":"PPL",
    "gn:name":"Bredniki",
    "gn:population":0,
    "gn:timezone":"Europe/Moscow",
    "iso:country":"RU",
    "name:rus_x_preferred":[
        "\u0411\u0440\u0435\u0434\u043d\u0438\u043a\u0438"
    ],
    "wof:name":"Bredniki",
    "wof:placetype":"locality"
},
  "geometry": {"coordinates":[33.57833,56.44389],"type":"Point"}
}