{
  "type": "Feature",
  "properties": {
    "gn:admin1_code":"77",
    "gn:asciiname":"Dubrovo Vtoroye",
    "gn:country_code":"RU",
    "gn:dem":178,
    "gn:feature_class":"P",
    "gn:feature_code":"PPL",
    "gn:name":"Dubrovo Vtoroye",
    "gn:population":0,
    "gn:timezone":"Europe/Moscow",
    "iso:country":"RU",
    "name:rus_x_preferred":[
        "\u0414\u0443\u0431\u0440\u043e\u0432\u043e \u0412\u0442\u043e\u0440\u043e\u0435"
    ],
    "wof:name":"Dubrovo Vtoroye",
    "wof:placetype":"locality"
},
  "geometry": {"coordinates":[32.5656,55.7319],"type":"Point"}
}