{
  "type": "Feature",
  "properties": {
    "gn:admin1_code":"42.0",
    "gn:asciiname":"Poselok",
    "gn:country_code":"RU",
    "gn:dem":103,
    "gn:feature_class":"P",
    "gn:feature_code":"PPL",
    "gn:name":"Pos\u00eblok",
    "gn:population":0,
    "gn:timezone":"Europe/Moscow",
    "iso:country":"RU",
    "name:rus_x_preferred":[
        "\u041f\u043e\u0441\u0451\u043b\u043e\u043a"
    ],
    "name:und_x_variant":[
        "Pos\u00eblok",
        "\u041f\u043e\u0441\u0451\u043b\u043e\u043a"
    ],
    "wof:name":"Poselok",
    "wof:placetype":"locality"
},
  "geometry": {"coordinates":[30.19472,59.71722],"type":"Point"}
}