{
  "type": "Feature",
  "properties": {
    "gn:admin1_code":"8",
    "gn:asciiname":"Novaya Vasil'yevka",
    "gn:country_code":"RU",
    "gn:dem":158,
    "gn:feature_class":"P",
    "gn:feature_code":"PPL",
    "gn:name":"Novaya Vasil\u2019yevka",
    "gn:population":0,
    "gn:timezone":"Asia/Yekaterinburg",
    "iso:country":"RU",
    "name:rus_x_preferred":[
        "\u041d\u043e\u0432\u0430\u044f \u0412\u0430\u0441\u0438\u043b\u044c\u0435\u0432\u043a\u0430"
    ],
    "name:und_x_variant":[
        "Novaya Vasil\u2019yevka"
    ],
    "wof:name":"Novaya Vasil'yevka",
    "wof:placetype":"locality"
},
  "geometry": {"coordinates":[55.9267,53.477],"type":"Point"}
}