{
  "type": "Feature",
  "properties": {
    "gn:admin1_code":"71",
    "gn:asciiname":"Sredniy Bugalysh",
    "gn:country_code":"RU",
    "gn:dem":195,
    "gn:feature_class":"P",
    "gn:feature_code":"PPL",
    "gn:name":"Sredniy Bugalysh",
    "gn:population":0,
    "gn:timezone":"Asia/Yekaterinburg",
    "iso:country":"RU",
    "name:eng_x_preferred":[
        "Sredniy Bugalysh"
    ],
    "name:nor_x_preferred":[
        "Sred.Bugalysj"
    ],
    "name:rus_x_preferred":[
        "\u0421\u0440\u0435\u0434.\u0411\u0443\u0433\u0430\u043b\u044b\u0448"
    ],
    "name:rus_x_variant":[
        "\u0421\u0440\u0435\u0434\u043d\u0438\u0439 \u0411\u0443\u0433\u0430\u043b\u044b\u0448"
    ],
    "name:und_x_variant":[
        "\u0421\u0440\u0435\u0434\u043d\u0438\u0439 \u0411\u0443\u0433\u0430\u043b\u044b\u0448"
    ],
    "wof:name":"Sredniy Bugalysh",
    "wof:placetype":"locality"
},
  "geometry": {"coordinates":[57.99063,56.30002],"type":"Point"}
}