{
  "type": "Feature",
  "properties": {
    "gn:admin1_code":"60",
    "gn:asciiname":"Lunevshchina",
    "gn:country_code":"RU",
    "gn:dem":42,
    "gn:feature_class":"P",
    "gn:feature_code":"PPL",
    "gn:name":"Lunevshchina",
    "gn:population":0,
    "gn:timezone":"Europe/Moscow",
    "iso:country":"RU",
    "name:rus_x_preferred":[
        "\u041b\u0443\u043d\u0435\u0432\u0449\u0438\u043d\u0430"
    ],
    "name:und_x_variant":[
        "Lukevshchina",
        "Lunevshchina"
    ],
    "wof:name":"Lunevshchina",
    "wof:placetype":"locality"
},
  "geometry": {"coordinates":[27.87984,58.59745],"type":"Point"}
}