{
  "type": "Feature",
  "properties": {
    "gn:admin1_code":"6",
    "gn:asciiname":"Slobodchikovo",
    "gn:country_code":"RU",
    "gn:dem":198,
    "gn:feature_class":"P",
    "gn:feature_code":"PPL",
    "gn:name":"Slobodchikovo",
    "gn:population":0,
    "gn:timezone":"Europe/Moscow",
    "iso:country":"RU",
    "name:eng_x_preferred":[
        "Slobodchikovo"
    ],
    "name:nor_x_preferred":[
        "Slobodtsjikovo"
    ],
    "name:rus_x_preferred":[
        "\u0421\u043b\u043e\u0431\u043e\u0434\u0447\u0438\u043a\u043e\u0432\u043e"
    ],
    "name:und_x_variant":[
        "Slobodchikovskaya"
    ],
    "wof:name":"Slobodchikovo",
    "wof:placetype":"locality"
},
  "geometry": {"coordinates":[40.8182,60.747],"type":"Point"}
}