{
  "type": "Feature",
  "properties": {
    "gn:admin1_code":"4",
    "gn:asciiname":"Samarskiy",
    "gn:country_code":"RU",
    "gn:dem":122,
    "gn:feature_class":"P",
    "gn:feature_code":"PPL",
    "gn:name":"Samarskiy",
    "gn:population":0,
    "gn:timezone":"Asia/Barnaul",
    "iso:country":"RU",
    "name:rus_x_preferred":[
        "\u0421\u0430\u043c\u0430\u0440\u0441\u043a\u0438\u0439"
    ],
    "name:und_x_variant":[
        "\u0421\u0430\u043c\u0430\u0440\u0441\u043a\u0438\u0439"
    ],
    "wof:name":"Samarskiy",
    "wof:placetype":"locality"
},
  "geometry": {"coordinates":[78.86667,52.86666999999999],"type":"Point"}
}