{
  "type": "Feature",
  "properties": {
    "gn:admin1_code":"38.0",
    "gn:asciiname":"Sukhaya Kochovka",
    "gn:country_code":"RU",
    "gn:dem":306,
    "gn:feature_class":"P",
    "gn:feature_code":"PPL",
    "gn:name":"Sukhaya Kochovka",
    "gn:population":0,
    "gn:timezone":"Europe/Moscow",
    "iso:country":"RU",
    "wof:name":"Sukhaya Kochovka",
    "wof:placetype":"locality"
},
  "geometry": {"coordinates":[39.75917000000001,44.28167],"type":"Point"}
}