{
  "type": "Feature",
  "properties": {
    "gn:admin1_code":"77",
    "gn:asciiname":"Polyanka",
    "gn:country_code":"RU",
    "gn:dem":168,
    "gn:feature_class":"P",
    "gn:feature_code":"PPL",
    "gn:name":"Polyanka",
    "gn:population":0,
    "gn:timezone":"Europe/Moscow",
    "iso:country":"RU",
    "name:rus_x_preferred":[
        "\u041f\u043e\u043b\u044f\u043d\u043a\u0430"
    ],
    "name:und_x_variant":[
        "\u041f\u043e\u043b\u044f\u043d\u043a\u0430"
    ],
    "wof:name":"Polyanka",
    "wof:placetype":"locality"
},
  "geometry": {"coordinates":[36.3579,57.3736],"type":"Point"}
}