{
  "type": "Feature",
  "properties": {
    "gn:admin1_code":"51.0",
    "gn:asciiname":"Yablonnoye",
    "gn:country_code":"RU",
    "gn:dem":105,
    "gn:feature_class":"P",
    "gn:feature_code":"PPL",
    "gn:name":"Yablonnoye",
    "gn:population":0,
    "gn:timezone":"Europe/Moscow",
    "iso:country":"RU",
    "name:und_x_variant":[
        "Yablonoye",
        "Yablonnoye"
    ],
    "wof:name":"Yablonnoye",
    "wof:placetype":"locality"
},
  "geometry": {"coordinates":[43.62869,56.64553000000001],"type":"Point"}
}