{
  "type": "Feature",
  "properties": {
    "gn:admin1_code":"29.0",
    "gn:asciiname":"Rubtsovka",
    "gn:country_code":"RU",
    "gn:dem":394,
    "gn:feature_class":"P",
    "gn:feature_code":"PPL",
    "gn:name":"Rubtsovka",
    "gn:population":0,
    "gn:timezone":"Asia/Novokuznetsk",
    "iso:country":"RU",
    "name:rus_x_preferred":[
        "\u0420\u0443\u0431\u0446\u043e\u0432\u043a\u0430"
    ],
    "wof:name":"Rubtsovka",
    "wof:placetype":"locality"
},
  "geometry": {"coordinates":[86.11620000000001,54.1156],"type":"Point"}
}