{
  "type": "Feature",
  "properties": {
    "gn:admin1_code":"8",
    "gn:asciiname":"Ustyushka",
    "gn:country_code":"RU",
    "gn:dem":684,
    "gn:feature_class":"P",
    "gn:feature_code":"PPL",
    "gn:name":"Ustyushka",
    "gn:population":0,
    "gn:timezone":"Asia/Yekaterinburg",
    "iso:country":"RU",
    "wof:name":"Ustyushka",
    "wof:placetype":"locality"
},
  "geometry": {"coordinates":[58.45,54.31667],"type":"Point"}
}