{
  "type": "Feature",
  "properties": {
    "gn:admin1_code":"33.0",
    "gn:asciiname":"Agapikha",
    "gn:country_code":"RU",
    "gn:dem":137,
    "gn:feature_class":"P",
    "gn:feature_code":"PPL",
    "gn:name":"Agapikha",
    "gn:population":0,
    "gn:timezone":"Europe/Kirov",
    "iso:country":"RU",
    "name:nor_x_preferred":[
        "Agapikha"
    ],
    "name:rus_x_preferred":[
        "\u0410\u0433\u0430\u043f\u0438\u0445\u0430"
    ],
    "wof:name":"Agapikha",
    "wof:placetype":"locality"
},
  "geometry": {"coordinates":[48.93264,58.62093],"type":"Point"}
}