{
  "type": "Feature",
  "properties": {
    "gn:admin1_code":"42",
    "gn:asciiname":"Panteleyevichi",
    "gn:country_code":"RU",
    "gn:dem":61,
    "gn:feature_class":"P",
    "gn:feature_code":"PPL",
    "gn:name":"Panteleyevichi",
    "gn:population":0,
    "gn:timezone":"Europe/Moscow",
    "iso:country":"RU",
    "name:rus_x_preferred":[
        "\u041f\u0430\u043d\u0442\u0435\u043b\u0435\u0435\u0432\u0438\u0447\u0438"
    ],
    "name:und_x_variant":[
        "\u041f\u0430\u043d\u0442\u0435\u043b\u0435\u0435\u0432\u0438\u0447\u0438"
    ],
    "wof:name":"Panteleyevichi",
    "wof:placetype":"locality"
},
  "geometry": {"coordinates":[30.32439,58.81346],"type":"Point"}
}