{
  "type": "Feature",
  "properties": {
    "gn:admin1_code":"60.0",
    "gn:asciiname":"Drozdova",
    "gn:country_code":"RU",
    "gn:dem":174,
    "gn:feature_class":"P",
    "gn:feature_code":"PPL",
    "gn:name":"Drozdova",
    "gn:population":0,
    "gn:timezone":"Europe/Moscow",
    "iso:country":"RU",
    "name:rus_x_preferred":[
        "\u0414\u0440\u043e\u0437\u0434\u043e\u0432\u0430"
    ],
    "wof:name":"Drozdova",
    "wof:placetype":"locality"
},
  "geometry": {"coordinates":[29.73333,55.95],"type":"Point"}
}