{
  "type": "Feature",
  "properties": {
    "gn:admin1_code":"77",
    "gn:asciiname":"Navi",
    "gn:country_code":"RU",
    "gn:dem":157,
    "gn:feature_class":"P",
    "gn:feature_code":"PPL",
    "gn:name":"Navi",
    "gn:population":0,
    "gn:timezone":"Europe/Moscow",
    "iso:country":"RU",
    "name:cat_x_preferred":[
        "Navi"
    ],
    "name:ceb_x_preferred":[
        "Navi"
    ],
    "name:deu_x_preferred":[
        "Navi"
    ],
    "name:nld_x_preferred":[
        "Navi"
    ],
    "name:rus_x_preferred":[
        "\u041d\u0430\u0432\u0438"
    ],
    "name:spa_x_preferred":[
        "Navi"
    ],
    "name:swe_x_preferred":[
        "Navi"
    ],
    "name:und_x_variant":[
        "\u041d\u0430\u0432\u0438"
    ],
    "wof:name":"Navi",
    "wof:placetype":"locality"
},
  "geometry": {"coordinates":[37.18007,58.03349],"type":"Point"}
}