{
  "type": "Feature",
  "properties": {
    "gn:admin1_code":"37.0",
    "gn:asciiname":"Gavrilovskoye",
    "gn:country_code":"RU",
    "gn:dem":136,
    "gn:feature_class":"P",
    "gn:feature_code":"PPL",
    "gn:name":"Gavrilovskoye",
    "gn:population":0,
    "gn:timezone":"Europe/Moscow",
    "iso:country":"RU",
    "name:eng_x_preferred":[
        "Gavrilovskoye"
    ],
    "name:nor_x_preferred":[
        "Gavrilovskoje"
    ],
    "name:rus_x_preferred":[
        "\u0413\u0430\u0432\u0440\u0438\u043b\u043e\u0432\u0441\u043a\u043e\u0435"
    ],
    "wof:name":"Gavrilovskoye",
    "wof:placetype":"locality"
},
  "geometry": {"coordinates":[41.39679,58.33116],"type":"Point"}
}