{
  "type": "Feature",
  "properties": {
    "gn:admin1_code":"16",
    "gn:asciiname":"Ichiksy",
    "gn:country_code":"RU",
    "gn:dem":96,
    "gn:feature_class":"P",
    "gn:feature_code":"PPL",
    "gn:name":"Ichiksy",
    "gn:population":0,
    "gn:timezone":"Europe/Moscow",
    "iso:country":"RU",
    "name:rus_x_preferred":[
        "\u0418\u0447\u0438\u043a\u0441\u044b"
    ],
    "wof:name":"Ichiksy",
    "wof:placetype":"locality"
},
  "geometry": {"coordinates":[46.46957,54.98009],"type":"Point"}
}