{
  "type": "Feature",
  "properties": {
    "gn:admin1_code":"10",
    "gn:asciiname":"Zelenyy Rog",
    "gn:country_code":"RU",
    "gn:dem":150,
    "gn:feature_class":"P",
    "gn:feature_code":"PPL",
    "gn:name":"Zel\u00ebnyy Rog",
    "gn:population":0,
    "gn:timezone":"Europe/Moscow",
    "iso:country":"RU",
    "name:rus_x_preferred":[
        "\u0417\u0435\u043b\u0451\u043d\u044b\u0439 \u0420\u043e\u0433"
    ],
    "name:und_x_variant":[
        "Zel\u00ebnyy Rog",
        "\u0417\u0435\u043b\u0451\u043d\u044b\u0439 \u0420\u043e\u0433"
    ],
    "wof:name":"Zelenyy Rog",
    "wof:placetype":"locality"
},
  "geometry": {"coordinates":[33.5507,52.8805],"type":"Point"}
}