{
  "type": "Feature",
  "properties": {
    "gn:admin1_code":"25",
    "gn:asciiname":"Zhelny",
    "gn:country_code":"RU",
    "gn:dem":206,
    "gn:feature_class":"P",
    "gn:feature_code":"PPL",
    "gn:name":"Zh\u00eblny",
    "gn:population":0,
    "gn:timezone":"Europe/Moscow",
    "iso:country":"RU",
    "name:eng_x_preferred":[
        "Zh\u00eblny"
    ],
    "name:nor_x_preferred":[
        "Zjelny"
    ],
    "name:rus_x_preferred":[
        "\u0416\u0435\u043b\u043d\u044b"
    ],
    "name:und_x_variant":[
        "Zh\u00eblny"
    ],
    "wof:name":"Zhelny",
    "wof:placetype":"locality"
},
  "geometry": {"coordinates":[33.84806,54.21074],"type":"Point"}
}