{
  "type": "Feature",
  "properties": {
    "gn:admin1_code":"88",
    "gn:asciiname":"Bogoslov",
    "gn:country_code":"RU",
    "gn:dem":99,
    "gn:feature_class":"P",
    "gn:feature_code":"PPL",
    "gn:name":"Bogoslov",
    "gn:population":0,
    "gn:timezone":"Europe/Moscow",
    "iso:country":"RU",
    "name:bul_x_preferred":[
        "\u0411\u043e\u0433\u043e\u0441\u043b\u043e\u0432"
    ],
    "name:ceb_x_preferred":[
        "Bogoslov"
    ],
    "name:kaz_x_preferred":[
        "\u0411\u043e\u0433\u043e\u0441\u043b\u043e\u0432"
    ],
    "name:ron_x_preferred":[
        "Bogoslov"
    ],
    "name:rus_x_preferred":[
        "\u0411\u043e\u0433\u043e\u0441\u043b\u043e\u0432"
    ],
    "name:swe_x_preferred":[
        "Bogoslov"
    ],
    "name:ukr_x_preferred":[
        "\u0411\u043e\u0433\u043e\u0441\u043b\u043e\u0432"
    ],
    "wof:name":"Bogoslov",
    "wof:placetype":"locality"
},
  "geometry": {"coordinates":[39.61266,57.61366999999999],"type":"Point"}
}