{
  "type": "Feature",
  "properties": {
    "gn:admin1_code":"77",
    "gn:asciiname":"Bukino",
    "gn:country_code":"RU",
    "gn:dem":224,
    "gn:feature_class":"P",
    "gn:feature_code":"PPL",
    "gn:name":"Bukino",
    "gn:population":0,
    "gn:timezone":"Europe/Moscow",
    "iso:country":"RU",
    "name:rus_x_preferred":[
        "\u0411\u0443\u043a\u0438\u043d\u043e"
    ],
    "name:und_x_variant":[
        "\u0411\u0443\u043a\u0438\u043d\u043e"
    ],
    "wof:name":"Bukino",
    "wof:placetype":"locality"
},
  "geometry": {"coordinates":[33.48786,57.42981],"type":"Point"}
}