{
  "type": "Feature",
  "properties": {
    "gn:admin1_code":"29",
    "gn:asciiname":"Mrassu",
    "gn:cc2":"RU",
    "gn:country_code":"RU",
    "gn:dem":646,
    "gn:feature_class":"P",
    "gn:feature_code":"PPL",
    "gn:name":"Mrassu",
    "gn:population":0,
    "gn:timezone":"Asia/Novokuznetsk",
    "iso:country":"RU",
    "name:eng_x_preferred":[
        "Mrassu"
    ],
    "name:nor_x_preferred":[
        "Mrassu"
    ],
    "name:rus_x_preferred":[
        "\u041c\u0440\u0430\u0441\u0441\u0443"
    ],
    "name:und_x_variant":[
        "Tebechek"
    ],
    "wof:name":"Mrassu",
    "wof:placetype":"locality"
},
  "geometry": {"coordinates":[88.52083,52.29806],"type":"Point"}
}