{
  "type": "Feature",
  "properties": {
    "gn:admin1_code":"8",
    "gn:asciiname":"Nazargulovo",
    "gn:country_code":"RU",
    "gn:dem":193,
    "gn:feature_class":"P",
    "gn:feature_code":"PPL",
    "gn:name":"Nazargulovo",
    "gn:population":0,
    "gn:timezone":"Asia/Yekaterinburg",
    "iso:country":"RU",
    "name:rus_x_preferred":[
        "\u041d\u0430\u0437\u0430\u0440\u0433\u0443\u043b\u043e\u0432\u043e"
    ],
    "name:und_x_variant":[
        "\u041d\u0430\u0437\u0430\u0440\u0433\u0443\u043b\u043e\u0432\u043e"
    ],
    "wof:name":"Nazargulovo",
    "wof:placetype":"locality"
},
  "geometry": {"coordinates":[56.23333,52.86666999999999],"type":"Point"}
}