{
  "type": "Feature",
  "properties": {
    "gn:admin1_code":"77.0",
    "gn:asciiname":"Borzyni",
    "gn:country_code":"RU",
    "gn:dem":230,
    "gn:feature_class":"P",
    "gn:feature_code":"PPL",
    "gn:name":"Borzyni",
    "gn:population":0,
    "gn:timezone":"Europe/Moscow",
    "iso:country":"RU",
    "name:rus_x_preferred":[
        "\u0411\u043e\u0440\u0437\u044b\u043d\u0438"
    ],
    "name:und_x_variant":[
        "Borzyn\u2019",
        "Borzyni",
        "\u0411\u043e\u0440\u0437\u044b\u043d\u0438"
    ],
    "wof:name":"Borzyni",
    "wof:placetype":"locality"
},
  "geometry": {"coordinates":[34.26347,57.21415],"type":"Point"}
}