{
  "type": "Feature",
  "properties": {
    "gn:admin1_code":"52",
    "gn:asciiname":"Petukhovo",
    "gn:country_code":"RU",
    "gn:dem":163,
    "gn:feature_class":"P",
    "gn:feature_code":"PPL",
    "gn:name":"Petukhovo",
    "gn:population":0,
    "gn:timezone":"Europe/Moscow",
    "iso:country":"RU",
    "name:eng_x_preferred":[
        "Petukhovo"
    ],
    "name:nor_x_preferred":[
        "Petukhovo"
    ],
    "name:rus_x_preferred":[
        "\u041f\u0435\u0442\u0443\u0445\u043e\u0432\u043e"
    ],
    "name:und_x_variant":[
        "Petukhova"
    ],
    "wof:name":"Petukhovo",
    "wof:placetype":"locality"
},
  "geometry": {"coordinates":[34.23172,58.41916],"type":"Point"}
}