{
  "type": "Feature",
  "properties": {
    "gn:admin1_code":"63",
    "gn:asciiname":"Kyyy",
    "gn:country_code":"RU",
    "gn:dem":177,
    "gn:feature_class":"P",
    "gn:feature_code":"PPL",
    "gn:name":"Kyyy",
    "gn:population":0,
    "gn:timezone":"Asia/Yakutsk",
    "iso:country":"RU",
    "name:und_x_variant":[
        "Kyyyy",
        "Kyiy",
        "Kyyy"
    ],
    "wof:name":"Kyyy",
    "wof:placetype":"locality"
},
  "geometry": {"coordinates":[133.03198,62.11834],"type":"Point"}
}