{
  "type": "Feature",
  "properties": {
    "gn:admin1_code":"25",
    "gn:asciiname":"Mamonovka",
    "gn:country_code":"RU",
    "gn:dem":197,
    "gn:feature_class":"P",
    "gn:feature_code":"PPL",
    "gn:name":"Mamonovka",
    "gn:population":0,
    "gn:timezone":"Europe/Moscow",
    "iso:country":"RU",
    "name:rus_x_preferred":[
        "\u041c\u0430\u043c\u043e\u043d\u043e\u0432\u043a\u0430"
    ],
    "name:und_x_variant":[
        "Mamonovskiy",
        "Mamonovzhskiy",
        "Mamonovka",
        "\u041c\u0430\u043c\u043e\u043d\u043e\u0432\u043a\u0430"
    ],
    "wof:name":"Mamonovka",
    "wof:placetype":"locality"
},
  "geometry": {"coordinates":[33.6043,54.07054],"type":"Point"}
}