{
  "type": "Feature",
  "properties": {
    "gn:admin1_code":"77.0",
    "gn:asciiname":"Bolshevo",
    "gn:country_code":"RU",
    "gn:dem":158,
    "gn:feature_class":"P",
    "gn:feature_code":"PPL",
    "gn:name":"Bolsh\u00ebvo",
    "gn:population":0,
    "gn:timezone":"Europe/Moscow",
    "iso:country":"RU",
    "name:ceb_x_preferred":[
        "Bolshevo"
    ],
    "name:rus_x_preferred":[
        "\u0411\u043e\u043b\u0448\u0451\u0432\u043e"
    ],
    "name:rus_x_variant":[
        "\u0411\u043e\u043b\u0448\u0435\u0432\u043e"
    ],
    "name:und_x_variant":[
        "Bolsh\u00ebvo"
    ],
    "wof:name":"Bolshevo",
    "wof:placetype":"locality"
},
  "geometry": {"coordinates":[35.38333,56.48333],"type":"Point"}
}