{
  "type": "Feature",
  "properties": {
    "gn:admin1_code":"33",
    "gn:asciiname":"Novosely",
    "gn:country_code":"RU",
    "gn:dem":205,
    "gn:feature_class":"P",
    "gn:feature_code":"PPL",
    "gn:name":"Novos\u00ebly",
    "gn:population":0,
    "gn:timezone":"Europe/Kirov",
    "iso:country":"RU",
    "name:eng_x_preferred":[
        "Novos\u00ebly"
    ],
    "name:nor_x_preferred":[
        "Novosely"
    ],
    "name:rus_x_preferred":[
        "\u041d\u043e\u0432\u043e\u0441\u0435\u043b\u044b"
    ],
    "name:rus_x_variant":[
        "\u041d\u043e\u0432\u043e\u0441\u0451\u043b\u044b"
    ],
    "name:und_x_variant":[
        "Novosel\u2019ye"
    ],
    "wof:name":"Novosely",
    "wof:placetype":"locality"
},
  "geometry": {"coordinates":[51.26284,59.34617],"type":"Point"}
}