{
  "type": "Feature",
  "properties": {
    "gn:admin1_code":"77.0",
    "gn:asciiname":"Fofanovo",
    "gn:country_code":"RU",
    "gn:dem":193,
    "gn:feature_class":"P",
    "gn:feature_code":"PPL",
    "gn:name":"Fofanovo",
    "gn:population":0,
    "gn:timezone":"Europe/Moscow",
    "iso:country":"RU",
    "name:rus_x_preferred":[
        "\u0424\u043e\u0444\u0430\u043d\u043e\u0432\u043e"
    ],
    "wof:name":"Fofanovo",
    "wof:placetype":"locality"
},
  "geometry": {"coordinates":[32.05201,56.21264],"type":"Point"}
}