{
  "type": "Feature",
  "properties": {
    "gn:admin1_code":"51.0",
    "gn:asciiname":"Shonikha",
    "gn:country_code":"RU",
    "gn:dem":149,
    "gn:feature_class":"P",
    "gn:feature_code":"PPL",
    "gn:name":"Shonikha",
    "gn:population":0,
    "gn:timezone":"Europe/Moscow",
    "iso:country":"RU",
    "name:rus_x_preferred":[
        "\u0428\u043e\u043d\u0438\u0445\u0430"
    ],
    "wof:name":"Shonikha",
    "wof:placetype":"locality"
},
  "geometry": {"coordinates":[43.77762,55.86528000000001],"type":"Point"}
}