{
  "type": "Feature",
  "properties": {
    "gn:admin1_code":"6",
    "gn:asciiname":"Klykovo",
    "gn:country_code":"RU",
    "gn:dem":70,
    "gn:feature_class":"P",
    "gn:feature_code":"PPL",
    "gn:name":"Klykovo",
    "gn:population":0,
    "gn:timezone":"Europe/Moscow",
    "iso:country":"RU",
    "name:rus_x_preferred":[
        "\u041a\u043b\u044b\u043a\u043e\u0432\u043e"
    ],
    "wof:name":"Klykovo",
    "wof:placetype":"locality"
},
  "geometry": {"coordinates":[42.53333,62.16667],"type":"Point"}
}