{
  "type": "Feature",
  "properties": {
    "gn:admin1_code":"21",
    "gn:asciiname":"Butyrevo",
    "gn:country_code":"RU",
    "gn:dem":151,
    "gn:feature_class":"P",
    "gn:feature_code":"PPL",
    "gn:name":"Butyrevo",
    "gn:population":0,
    "gn:timezone":"Europe/Moscow",
    "iso:country":"RU",
    "name:rus_x_preferred":[
        "\u0411\u0443\u0442\u044b\u0440\u0435\u0432\u043e"
    ],
    "wof:name":"Butyrevo",
    "wof:placetype":"locality"
},
  "geometry": {"coordinates":[39.5952,57.00607],"type":"Point"}
}