{
  "type": "Feature",
  "properties": {
    "gn:admin1_code":"10",
    "gn:asciiname":"Borovka",
    "gn:country_code":"RU",
    "gn:dem":135,
    "gn:feature_class":"P",
    "gn:feature_code":"PPL",
    "gn:name":"Borovka",
    "gn:population":31,
    "gn:timezone":"Europe/Moscow",
    "iso:country":"RU",
    "name:rus_x_preferred":[
        "\u0411\u043e\u0440\u043e\u0432\u043aa"
    ],
    "name:und_x_variant":[
        "\u0411\u043e\u0440\u043e\u0432\u043aa",
        "Borovskoy"
    ],
    "wof:name":"Borovka",
    "wof:placetype":"locality",
    "wof:population":31
},
  "geometry": {"coordinates":[32.19782,52.11316],"type":"Point"}
}