{
  "type": "Feature",
  "properties": {
    "gn:admin1_code":"69.0",
    "gn:asciiname":"Bolshe-Zakhar'yevskoye",
    "gn:country_code":"RU",
    "gn:dem":181,
    "gn:feature_class":"P",
    "gn:feature_code":"PPL",
    "gn:name":"Bolshe-Zakhar\u2019yevskoye",
    "gn:population":0,
    "gn:timezone":"Europe/Moscow",
    "iso:country":"RU",
    "name:rus_x_preferred":[
        "\u0411\u043e\u043b\u0448\u0435-\u0417\u0430\u0445\u0430\u0440\u044c\u0435\u0432\u0441\u043a\u043e\u0435"
    ],
    "name:und_x_variant":[
        "Bolshe-Zakhar\u2019yevskoye",
        "\u0411\u043e\u043b\u0448\u0435-\u0417\u0430\u0445\u0430\u0440\u044c\u0435\u0432\u0441\u043a\u043e\u0435"
    ],
    "wof:name":"Bolshe-Zakhar'yevskoye",
    "wof:placetype":"locality"
},
  "geometry": {"coordinates":[33.85548,54.69624],"type":"Point"}
}