{
  "type": "Feature",
  "properties": {
    "gn:country":"RU",
    "gn:fcode":"PPL",
    "gn:population":0,
    "iso:country":"RU",
    "name:rus_x_preferred":[
        "\u041b\u0435\u0432\u043a\u043e\u0432\u043e"
    ],
    "qs:name":"Levkovo",
    "qs:name_adm0":"Russia",
    "qs:name_adm1":"Moscow Oblast",
    "qs:photos_9k":1,
    "qs:photos_9r":1,
    "qs:photos_all":5,
    "qs:photos_sr":0,
    "qs:placetype":"Town",
    "qs:pop_sr":"0",
    "wof:name":"Levkovo",
    "wof:placetype":"locality",
    "wof:population":0
},
  "geometry": {"coordinates":[37.95,56.01667],"type":"Point"}
}