{
  "type": "Feature",
  "properties": {
    "gn:admin1_code":"45.0",
    "gn:asciiname":"Pis'mener",
    "gn:country_code":"RU",
    "gn:dem":138,
    "gn:feature_class":"P",
    "gn:feature_code":"PPL",
    "gn:name":"Pis\u2019mener",
    "gn:population":0,
    "gn:timezone":"Europe/Moscow",
    "iso:country":"RU",
    "name:rus_x_preferred":[
        "\u041f\u0438\u0441\u044c\u043c\u0435\u043d\u0435\u0440"
    ],
    "name:und_x_variant":[
        "Pis\u2019mener"
    ],
    "wof:name":"Pis'mener",
    "wof:placetype":"locality"
},
  "geometry": {"coordinates":[49.60128,56.90725],"type":"Point"}
}