{
  "type": "Feature",
  "properties": {
    "gn:admin1_code":"85",
    "gn:asciiname":"Prokino",
    "gn:country_code":"RU",
    "gn:dem":171,
    "gn:feature_class":"P",
    "gn:feature_code":"PPL",
    "gn:name":"Prokino",
    "gn:population":0,
    "gn:timezone":"Europe/Moscow",
    "iso:country":"RU",
    "name:eng_x_preferred":[
        "Prokino"
    ],
    "name:nor_x_preferred":[
        "Jurotsjkino"
    ],
    "name:rus_x_preferred":[
        "\u042e\u0440\u043e\u0447\u043a\u0438\u043d\u043e"
    ],
    "name:rus_x_variant":[
        "\u041f\u0440\u043e\u043a\u0438\u043d\u043e"
    ],
    "wof:name":"Prokino",
    "wof:placetype":"locality"
},
  "geometry": {"coordinates":[38.51871,59.04226],"type":"Point"}
}