{
  "type": "Feature",
  "properties": {
    "gn:admin1_code":"37.0",
    "gn:asciiname":"Berezovets",
    "gn:country_code":"RU",
    "gn:dem":150,
    "gn:feature_class":"P",
    "gn:feature_code":"PPL",
    "gn:name":"Berezovets",
    "gn:population":0,
    "gn:timezone":"Europe/Moscow",
    "iso:country":"RU",
    "name:eng_x_preferred":[
        "Berezovets"
    ],
    "name:nor_x_preferred":[
        "Berezovets"
    ],
    "name:rus_x_preferred":[
        "\u0411\u0435\u0440\u0435\u0437\u043e\u0432\u0435\u0446"
    ],
    "name:und_x_variant":[
        "\u0411\u0435\u0440\u0435\u0437\u043e\u0432\u0435\u0446",
        "Berezovets"
    ],
    "wof:name":"Berezovets",
    "wof:placetype":"locality"
},
  "geometry": {"coordinates":[42.27229000000001,58.63797],"type":"Point"}
}