{
  "type": "Feature",
  "properties": {
    "gn:admin1_code":"5",
    "gn:asciiname":"Uralovka",
    "gn:country_code":"RU",
    "gn:dem":196,
    "gn:feature_class":"P",
    "gn:feature_code":"PPL",
    "gn:name":"Uralovka",
    "gn:population":0,
    "gn:timezone":"Asia/Yakutsk",
    "iso:country":"RU",
    "name:eng_x_preferred":[
        "Uralovka"
    ],
    "name:nor_x_preferred":[
        "Uralovka"
    ],
    "name:rus_x_preferred":[
        "\u0423\u0440\u0430\u043b\u043e\u0432\u043a\u0430"
    ],
    "wof:name":"Uralovka",
    "wof:placetype":"locality"
},
  "geometry": {"coordinates":[128.12712999999999,52.45002],"type":"Point"}
}