{
  "type": "Feature",
  "properties": {
    "gn:admin1_code":"60.0",
    "gn:asciiname":"Dolgovo",
    "gn:country_code":"RU",
    "gn:dem":131,
    "gn:feature_class":"P",
    "gn:feature_code":"PPL",
    "gn:name":"Dolgovo",
    "gn:population":0,
    "gn:timezone":"Europe/Moscow",
    "iso:country":"RU",
    "name:rus_x_preferred":[
        "\u0414\u043e\u043b\u0433\u043e\u0432\u043e"
    ],
    "wof:name":"Dolgovo",
    "wof:placetype":"locality"
},
  "geometry": {"coordinates":[28.5414,56.32084],"type":"Point"}
}