{
  "type": "Feature",
  "properties": {
    "gn:admin1_code":"67",
    "gn:asciiname":"Polchaninovka",
    "gn:country_code":"RU",
    "gn:dem":265,
    "gn:feature_class":"P",
    "gn:feature_code":"PPL",
    "gn:name":"Polchaninovka",
    "gn:population":0,
    "gn:timezone":"Europe/Saratov",
    "iso:country":"RU",
    "name:eng_x_preferred":[
        "Polchaninovka"
    ],
    "name:nor_x_preferred":[
        "Poltsjaninovka"
    ],
    "name:rus_x_preferred":[
        "\u041f\u043e\u043b\u0447\u0430\u043d\u0438\u043d\u043e\u0432\u043a\u0430"
    ],
    "name:und_x_variant":[
        "\u041f\u043e\u043b\u0447\u0430\u043d\u0438\u043d\u043e\u0432\u043a\u0430",
        "Polchaninovka"
    ],
    "wof:name":"Polchaninovka",
    "wof:placetype":"locality"
},
  "geometry": {"coordinates":[45.60194,51.85861],"type":"Point"}
}