{
  "type": "Feature",
  "properties": {
    "gn:admin1_code":"85",
    "gn:asciiname":"Kukmanino",
    "gn:country_code":"RU",
    "gn:dem":142,
    "gn:feature_class":"P",
    "gn:feature_code":"PPL",
    "gn:name":"Kukmanino",
    "gn:population":0,
    "gn:timezone":"Europe/Moscow",
    "iso:country":"RU",
    "name:rus_x_preferred":[
        "\u041a\u0443\u043a\u043c\u0430\u043d\u0438\u043d\u043e"
    ],
    "name:und_x_variant":[
        "Kikmanino"
    ],
    "wof:name":"Kukmanino",
    "wof:placetype":"locality"
},
  "geometry": {"coordinates":[38.8956,59.7202],"type":"Point"}
}