{
  "type": "Feature",
  "properties": {
    "gn:admin1_code":"47",
    "gn:asciiname":"Shvanovo",
    "gn:cc2":"RU",
    "gn:country_code":"RU",
    "gn:dem":232,
    "gn:feature_class":"P",
    "gn:feature_code":"PPL",
    "gn:name":"Shvanovo",
    "gn:population":0,
    "gn:timezone":"Europe/Moscow",
    "iso:country":"RU",
    "name:rus_x_preferred":[
        "\u0428\u0432\u0430\u043d\u043e\u0432\u043e"
    ],
    "name:und_x_variant":[
        "Shvanova",
        "Shvanovo",
        "\u0428\u0432\u0430\u043d\u043e\u0432\u043e"
    ],
    "wof:name":"Shvanovo",
    "wof:placetype":"locality"
},
  "geometry": {"coordinates":[35.51278,55.58167],"type":"Point"}
}