{
  "type": "Feature",
  "properties": {
    "gn:admin1_code":"9",
    "gn:asciiname":"Zmeyevka",
    "gn:country_code":"RU",
    "gn:dem":138,
    "gn:feature_class":"P",
    "gn:feature_code":"PPL",
    "gn:name":"Zmey\u00ebvka",
    "gn:population":0,
    "gn:timezone":"Europe/Moscow",
    "iso:country":"RU",
    "name:rus_x_preferred":[
        "\u0417\u043c\u0435\u00eb\u0432\u043a\u0430"
    ],
    "name:und_x_variant":[
        "Zmiy\u00ebvka",
        "Zmey\u00ebvka"
    ],
    "wof:name":"Zmeyevka",
    "wof:placetype":"locality"
},
  "geometry": {"coordinates":[38.2149,51.1121],"type":"Point"}
}