{
  "type": "Feature",
  "properties": {
    "gn:admin1_code":"76",
    "gn:asciiname":"Gorki",
    "gn:country_code":"RU",
    "gn:dem":155,
    "gn:feature_class":"P",
    "gn:feature_code":"PPL",
    "gn:name":"Gorki",
    "gn:population":0,
    "gn:timezone":"Europe/Moscow",
    "iso:country":"RU",
    "name:rus_x_preferred":[
        "\u0413\u043e\u0440\u043a\u0438"
    ],
    "name:und_x_variant":[
        "Gorki Pervyye",
        "Gorki",
        "\u0413\u043e\u0440\u043a\u0438"
    ],
    "wof:name":"Gorki",
    "wof:placetype":"locality"
},
  "geometry": {"coordinates":[38.53146,53.72078000000001],"type":"Point"}
}