{
  "type": "Feature",
  "properties": {
    "gn:admin1_code":"75",
    "gn:asciiname":"Poskoyevo",
    "gn:cc2":"RU",
    "gn:country_code":"RU",
    "gn:dem":81,
    "gn:feature_class":"P",
    "gn:feature_code":"PPL",
    "gn:name":"Poskoyevo",
    "gn:population":0,
    "gn:timezone":"Asia/Tomsk",
    "iso:country":"RU",
    "name:rus_x_preferred":[
        "\u041f\u043e\u0441\u043a\u043e\u0435\u0432\u043e"
    ],
    "name:und_x_variant":[
        "Poskoyeva",
        "Poskoyevo",
        "\u041f\u043e\u0441\u043a\u043e\u0435\u0432\u043e"
    ],
    "wof:name":"Poskoyevo",
    "wof:placetype":"locality"
},
  "geometry": {"coordinates":[82.51666999999998,57.88333000000001],"type":"Point"}
}