{
  "type": "Feature",
  "properties": {
    "gn:admin1_code":"77",
    "gn:asciiname":"Rozhkovo",
    "gn:cc2":"RU",
    "gn:country_code":"RU",
    "gn:dem":185,
    "gn:feature_class":"P",
    "gn:feature_code":"PPL",
    "gn:name":"Rozhkovo",
    "gn:population":0,
    "gn:timezone":"Europe/Moscow",
    "iso:country":"RU",
    "name:rus_x_preferred":[
        "\u0420\u043e\u0436\u043a\u043e\u0432\u043e"
    ],
    "name:und_x_variant":[
        "Roshcha",
        "Rozhkovo",
        "\u0420\u043e\u0436\u043a\u043e\u0432\u043e"
    ],
    "wof:name":"Rozhkovo",
    "wof:placetype":"locality"
},
  "geometry": {"coordinates":[31.76667,56.15],"type":"Point"}
}