{
  "type": "Feature",
  "properties": {
    "gn:admin1_code":"65",
    "gn:asciiname":"Oykino",
    "gn:country_code":"RU",
    "gn:dem":163,
    "gn:feature_class":"P",
    "gn:feature_code":"PPL",
    "gn:name":"Oykino",
    "gn:population":0,
    "gn:timezone":"Europe/Samara",
    "iso:country":"RU",
    "name:rus_x_preferred":[
        "\u041e\u0439\u043a\u0438\u043d\u043e"
    ],
    "name:und_x_variant":[
        "\u041e\u0439\u043a\u0438\u043d\u043e"
    ],
    "wof:name":"Oykino",
    "wof:placetype":"locality"
},
  "geometry": {"coordinates":[51.83333,54.41667],"type":"Point"}
}