{
  "type": "Feature",
  "properties": {
    "gn:admin1_code":"75",
    "gn:asciiname":"Teka",
    "gn:country_code":"RU",
    "gn:dem":123,
    "gn:feature_class":"P",
    "gn:feature_code":"PPL",
    "gn:name":"Teka",
    "gn:population":0,
    "gn:timezone":"Asia/Tomsk",
    "iso:country":"RU",
    "name:ell_x_preferred":[
        "Teka"
    ],
    "name:eng_x_preferred":[
        "Teka"
    ],
    "name:eus_x_preferred":[
        "Teka"
    ],
    "name:fas_x_preferred":[
        "\u062a\u06a9\u0627"
    ],
    "name:fra_x_preferred":[
        "Teka"
    ],
    "name:ind_x_preferred":[
        "Teka"
    ],
    "name:nor_x_preferred":[
        "Teka"
    ],
    "name:por_x_preferred":[
        "Teka"
    ],
    "name:rus_x_preferred":[
        "\u0422\u0435\u043a\u0430"
    ],
    "name:spa_x_preferred":[
        "Teka"
    ],
    "name:ukr_x_preferred":[
        "Teka"
    ],
    "name:zho_x_preferred":[
        "\u5fb7\u683c\u96c6\u5718"
    ],
    "wof:name":"Teka",
    "wof:placetype":"locality"
},
  "geometry": {"coordinates":[83.75658,56.18431999999999],"type":"Point"}
}