{
  "type": "Feature",
  "properties": {
    "gn:admin1_code":"33.0",
    "gn:asciiname":"Bol'shiye Pervushi",
    "gn:country_code":"RU",
    "gn:dem":144,
    "gn:feature_class":"P",
    "gn:feature_code":"PPL",
    "gn:name":"Bol\u2019shiye Pervushi",
    "gn:population":0,
    "gn:timezone":"Europe/Kirov",
    "iso:country":"RU",
    "name:rus_x_preferred":[
        "\u0411\u043e\u043b\u044c\u0448\u0438\u0435 \u041f\u0435\u0440\u0432\u0443\u0448\u0438"
    ],
    "name:und_x_variant":[
        "Bol\u2019shiye Pervushi"
    ],
    "wof:name":"Bol'shiye Pervushi",
    "wof:placetype":"locality"
},
  "geometry": {"coordinates":[46.69537,58.35667],"type":"Point"}
}