{
  "type": "Feature",
  "properties": {
    "gn:admin1_code":"90.0",
    "gn:asciiname":"Denisyata",
    "gn:country_code":"RU",
    "gn:dem":127,
    "gn:feature_class":"P",
    "gn:feature_code":"PPL",
    "gn:name":"Denisyata",
    "gn:population":0,
    "gn:timezone":"Asia/Yekaterinburg",
    "iso:country":"RU",
    "name:che_x_preferred":[
        "\u0414\u0435\u043d\u0438\u0441\u044f\u0442\u0430"
    ],
    "name:rus_x_preferred":[
        "\u0414\u0435\u043d\u0438\u0441\u044f\u0442\u0430"
    ],
    "wof:name":"Denisyata",
    "wof:placetype":"locality"
},
  "geometry": {"coordinates":[55.8444,57.9339],"type":"Point"}
}