{
  "type": "Feature",
  "properties": {
    "gn:admin1_code":"85",
    "gn:asciiname":"Orinodory",
    "gn:country_code":"RU",
    "gn:dem":148,
    "gn:feature_class":"P",
    "gn:feature_code":"PPL",
    "gn:name":"Orinodory",
    "gn:population":0,
    "gn:timezone":"Europe/Moscow",
    "iso:country":"RU",
    "name:eng_x_preferred":[
        "Orinodory"
    ],
    "name:nor_x_preferred":[
        "Orinodory"
    ],
    "name:rus_x_preferred":[
        "\u041e\u0440\u0438\u043d\u043e\u0434\u043e\u0440\u044b"
    ],
    "name:und_x_variant":[
        "Orinodorskaya",
        "\u041e\u0440\u0438\u043d\u043e\u0434\u043e\u0440\u044b",
        "Orinodory"
    ],
    "wof:name":"Orinodory",
    "wof:placetype":"locality"
},
  "geometry": {"coordinates":[42.52603,60.46364000000001],"type":"Point"}
}