{
  "type": "Feature",
  "properties": {
    "gn:admin1_code":"54",
    "gn:asciiname":"Babaylovka",
    "gn:country_code":"RU",
    "gn:dem":113,
    "gn:feature_class":"P",
    "gn:feature_code":"PPL",
    "gn:name":"Babaylovka",
    "gn:population":0,
    "gn:timezone":"Asia/Omsk",
    "iso:country":"RU",
    "name:rus_x_preferred":[
        "\u0411\u0430\u0431\u0430\u0439\u043b\u043e\u0432\u043a\u0430"
    ],
    "wof:name":"Babaylovka",
    "wof:placetype":"locality"
},
  "geometry": {"coordinates":[72.6127,55.2276],"type":"Point"}
}