{
  "type": "Feature",
  "properties": {
    "gn:admin1_code":"16",
    "gn:asciiname":"Kadyshi",
    "gn:country_code":"RU",
    "gn:dem":103,
    "gn:feature_class":"P",
    "gn:feature_code":"PPL",
    "gn:name":"Kadyshi",
    "gn:population":0,
    "gn:timezone":"Europe/Moscow",
    "iso:country":"RU",
    "name:rus_x_preferred":[
        "\u041a\u0430\u0434\u044b\u0448\u0438"
    ],
    "name:und_x_variant":[
        "\u041a\u0430\u0434\u044b\u0448\u0438"
    ],
    "wof:name":"Kadyshi",
    "wof:placetype":"locality"
},
  "geometry": {"coordinates":[46.84802,55.56482],"type":"Point"}
}