{
  "type": "Feature",
  "properties": {
    "gn:admin1_code":"8",
    "gn:asciiname":"Kulushevo",
    "gn:country_code":"RU",
    "gn:dem":95,
    "gn:feature_class":"P",
    "gn:feature_code":"PPL",
    "gn:name":"Kulush\u00ebvo",
    "gn:population":0,
    "gn:timezone":"Asia/Yekaterinburg",
    "iso:country":"RU",
    "name:rus_x_preferred":[
        "\u041a\u0443\u043b\u0443\u0448\u0451\u0432\u043e"
    ],
    "name:und_x_variant":[
        "Kulushovo",
        "Kulush\u00ebvo"
    ],
    "wof:name":"Kulushevo",
    "wof:placetype":"locality"
},
  "geometry": {"coordinates":[56.18899999999999,54.4987],"type":"Point"}
}