{
  "type": "Feature",
  "properties": {
    "gn:admin1_code":"46",
    "gn:asciiname":"Novaya Kar'ga",
    "gn:country_code":"RU",
    "gn:dem":158,
    "gn:feature_class":"P",
    "gn:feature_code":"PPL",
    "gn:name":"Novaya Kar\u2019ga",
    "gn:population":0,
    "gn:timezone":"Europe/Moscow",
    "iso:country":"RU",
    "name:nor_x_preferred":[
        "Novaja Karga"
    ],
    "name:rus_x_preferred":[
        "\u041d\u043e\u0432\u0430\u044f \u041a\u0430\u0440\u044c\u0433\u0430"
    ],
    "name:und_x_variant":[
        "Novaya Kar\u2019ga"
    ],
    "wof:name":"Novaya Kar'ga",
    "wof:placetype":"locality"
},
  "geometry": {"coordinates":[43.37749,54.40801],"type":"Point"}
}