{
  "type": "Feature",
  "properties": {
    "gn:admin1_code":"47",
    "gn:asciiname":"Voskresenki",
    "gn:country_code":"RU",
    "gn:dem":196,
    "gn:feature_class":"P",
    "gn:feature_code":"PPL",
    "gn:name":"Voskresenki",
    "gn:population":0,
    "gn:timezone":"Europe/Moscow",
    "iso:country":"RU",
    "name:und_x_variant":[
        "Voskresensk",
        "Voskresenki"
    ],
    "wof:name":"Voskresenki",
    "wof:placetype":"locality"
},
  "geometry": {"coordinates":[36.63196,55.84154],"type":"Point"}
}