{
  "type": "Feature",
  "properties": {
    "gn:admin1_code":"77",
    "gn:asciiname":"Chistyaki",
    "gn:country_code":"RU",
    "gn:dem":264,
    "gn:feature_class":"P",
    "gn:feature_code":"PPL",
    "gn:name":"Chistyaki",
    "gn:population":0,
    "gn:timezone":"Europe/Moscow",
    "iso:country":"RU",
    "name:rus_x_preferred":[
        "\u0427\u0438\u0441\u0442\u044f\u043a\u0438"
    ],
    "wof:name":"Chistyaki",
    "wof:placetype":"locality"
},
  "geometry": {"coordinates":[34.25013,57.30064],"type":"Point"}
}