{
  "type": "Feature",
  "properties": {
    "gn:admin1_code":"51",
    "gn:asciiname":"Gusevskiy",
    "gn:country_code":"RU",
    "gn:dem":155,
    "gn:feature_class":"P",
    "gn:feature_code":"PPL",
    "gn:name":"Gusevskiy",
    "gn:population":0,
    "gn:timezone":"Europe/Moscow",
    "iso:country":"RU",
    "name:rus_x_preferred":[
        "\u0413\u0443\u0441\u0435\u0432\u0441\u043a\u0438\u0439"
    ],
    "wof:name":"Gusevskiy",
    "wof:placetype":"locality"
},
  "geometry": {"coordinates":[46.7604,57.7804],"type":"Point"}
}