{
  "type": "Feature",
  "properties": {
    "gn:admin1_code":"77",
    "gn:asciiname":"Raslovka",
    "gn:country_code":"RU",
    "gn:dem":132,
    "gn:feature_class":"P",
    "gn:feature_code":"PPL",
    "gn:name":"Raslovka",
    "gn:population":0,
    "gn:timezone":"Europe/Moscow",
    "iso:country":"RU",
    "name:rus_x_preferred":[
        "\u0420\u0430\u0441\u043b\u043e\u0432\u043a\u0430"
    ],
    "wof:name":"Raslovka",
    "wof:placetype":"locality"
},
  "geometry": {"coordinates":[38.1642,57.0754],"type":"Point"}
}