{
  "type": "Feature",
  "properties": {
    "gn:admin1_code":"8",
    "gn:asciiname":"Syuren'",
    "gn:country_code":"RU",
    "gn:dem":295,
    "gn:feature_class":"P",
    "gn:feature_code":"PPL",
    "gn:name":"Syuren\u2019",
    "gn:population":0,
    "gn:timezone":"Asia/Yekaterinburg",
    "iso:country":"RU",
    "name:eng_x_preferred":[
        "Syuren'"
    ],
    "name:nor_x_preferred":[
        "Siuren"
    ],
    "name:rus_x_preferred":[
        "\u0421\u044e\u0440\u0435\u043d\u044c"
    ],
    "name:und_x_variant":[
        "Stepanovka",
        "Syuren\u2019"
    ],
    "wof:name":"Syuren'",
    "wof:placetype":"locality"
},
  "geometry": {"coordinates":[56.91707,52.79438],"type":"Point"}
}