{
  "type": "Feature",
  "properties": {
    "gn:admin1_code":"93",
    "gn:asciiname":"Verkhniy Aleur",
    "gn:country_code":"RU",
    "gn:dem":473,
    "gn:feature_class":"P",
    "gn:feature_code":"PPL",
    "gn:name":"Verkhniy Aleur",
    "gn:population":0,
    "gn:timezone":"Asia/Chita",
    "iso:country":"RU",
    "wof:name":"Verkhniy Aleur",
    "wof:placetype":"locality"
},
  "geometry": {"coordinates":[116.58333,51.96667],"type":"Point"}
}