{
  "type": "Feature",
  "properties": {
    "iso:country":"RU",
    "name:ben_x_preferred":[
        "\u0987\u09b8\u09bf\u0995\u09c1\u09b2"
    ],
    "name:ell_x_preferred":[
        "\u0399\u03c3\u03b9\u03ba\u03bf\u03cd\u03bb"
    ],
    "name:hin_x_preferred":[
        "\u0907\u0938\u093f\u0915\u0941\u0932"
    ],
    "name:ind_x_preferred":[
        "Isikul"
    ],
    "name:spa_x_preferred":[
        "Isikul"
    ],
    "name:swe_x_preferred":[
        "Isikul"
    ],
    "name:urd_x_preferred":[
        "\u0622\u0626\u06cc\u0633\u06cc\u06a9\u0648\u0644"
    ],
    "ne:ADM0CAP":0.0,
    "ne:ADM0NAME":"Russia",
    "ne:ADM0_A3":"RUS",
    "ne:ADM1NAME":"Omsk",
    "ne:ADMIN1_COD":0,
    "ne:CAPALT":0,
    "ne:CHANGED":0,
    "ne:CHECKME":0,
    "ne:COMPARE":0,
    "ne:DIFFASCII":0,
    "ne:ELEVATION":0.0,
    "ne:FEATURECLA":"Populated place",
    "ne:GEONAMEID":-1,
    "ne:GEONAMESNO":"No GeoNames match due to small population, not in GeoNames, or poor NEV placement.",
    "ne:GN_POP":0,
    "ne:GTOPO30":0.0,
    "ne:ISO_A2":"RU",
    "ne:LABELRANK":2,
    "ne:LATITUDE":54.9287,
    "ne:LONGITUDE":71.268249,
    "ne:LS_MATCH":1,
    "ne:LS_NAME":"Isikul",
    "ne:MAX_AREAKM":18.0,
    "ne:MAX_AREAMI":7.0,
    "ne:MAX_BBXMAX":71.316667,
    "ne:MAX_BBXMIN":71.241667,
    "ne:MAX_BBYMAX":54.941667,
    "ne:MAX_BBYMIN":54.875,
    "ne:MAX_NATSCA":20.0,
    "ne:MAX_PERKM":32.0,
    "ne:MAX_PERMI":20.0,
    "ne:MAX_POP10":21136,
    "ne:MAX_POP20":21136,
    "ne:MAX_POP300":0,
    "ne:MAX_POP310":0,
    "ne:MAX_POP50":0,
    "ne:MEAN_BBXC":71.271284,
    "ne:MEAN_BBYC":54.908221,
    "ne:MEGACITY":0,
    "ne:MIN_AREAKM":18.0,
    "ne:MIN_AREAMI":7.0,
    "ne:MIN_BBXMAX":71.316667,
    "ne:MIN_BBXMIN":71.241667,
    "ne:MIN_BBYMAX":54.941667,
    "ne:MIN_BBYMIN":54.875,
    "ne:MIN_PERKM":32.0,
    "ne:MIN_PERMI":20.0,
    "ne:NAME":"Isikul",
    "ne:NAMEASCII":"Isikul",
    "ne:NAMEDIFF":0,
    "ne:NATSCALE":20,
    "ne:POP1950":0,
    "ne:POP1955":0,
    "ne:POP1960":0,
    "ne:POP1965":0,
    "ne:POP1970":0,
    "ne:POP1975":0,
    "ne:POP1980":0,
    "ne:POP1985":0,
    "ne:POP1990":0,
    "ne:POP1995":0,
    "ne:POP2000":0,
    "ne:POP2005":0,
    "ne:POP2010":0,
    "ne:POP2015":0,
    "ne:POP2020":0,
    "ne:POP2025":0,
    "ne:POP2050":0,
    "ne:POP_MAX":21136,
    "ne:POP_MIN":21136,
    "ne:POP_OTHER":18655,
    "ne:RANK_MAX":7,
    "ne:RANK_MIN":7,
    "ne:SCALERANK":7,
    "ne:SOV0NAME":"Russia",
    "ne:SOV_A3":"RUS",
    "ne:UN_FID":0,
    "ne:UN_LAT":0.0,
    "ne:UN_LONG":0.0,
    "ne:WORLDCITY":0,
    "ne:min_zoom":6.1,
    "wof:name":"Isikul",
    "wof:placetype":"locality"
},
  "geometry": {"coordinates":[71.268249,54.9287],"type":"Point"}
}