{
  "type": "Feature",
  "properties": {
    "gn:admin1_code":"69",
    "gn:asciiname":"Matyushino",
    "gn:country_code":"RU",
    "gn:dem":242,
    "gn:feature_class":"P",
    "gn:feature_code":"PPL",
    "gn:name":"Matyushino",
    "gn:population":0,
    "gn:timezone":"Europe/Moscow",
    "iso:country":"RU",
    "name:rus_x_preferred":[
        "\u041c\u0430\u0442\u044e\u0448\u0438\u043d\u043e"
    ],
    "name:und_x_variant":[
        "\u041c\u0430\u0442\u044e\u0448\u0438\u043d\u043e"
    ],
    "wof:name":"Matyushino",
    "wof:placetype":"locality"
},
  "geometry": {"coordinates":[34.13564,54.91363000000001],"type":"Point"}
}