{
  "type": "Feature",
  "properties": {
    "gn:admin1_code":"21",
    "gn:asciiname":"Novovasilevo",
    "gn:country_code":"RU",
    "gn:dem":132,
    "gn:feature_class":"P",
    "gn:feature_code":"PPL",
    "gn:name":"Novovasilevo",
    "gn:population":0,
    "gn:timezone":"Europe/Moscow",
    "iso:country":"RU",
    "name:rus_x_preferred":[
        "\u041d\u043e\u0432\u043e\u0432\u0430\u0441\u0438\u043b\u0435\u0432\u043e"
    ],
    "name:und_x_variant":[
        "Vasil\u2019yeva",
        "Novovasilevo"
    ],
    "wof:name":"Novovasilevo",
    "wof:placetype":"locality"
},
  "geometry": {"coordinates":[40.39467,56.91555],"type":"Point"}
}