{
  "type": "Feature",
  "properties": {
    "gn:admin1_code":"47.0",
    "gn:asciiname":"Belyye Kolodezi",
    "gn:country_code":"RU",
    "gn:dem":118,
    "gn:feature_class":"P",
    "gn:feature_code":"PPL",
    "gn:name":"Belyye Kolodezi",
    "gn:population":0,
    "gn:timezone":"Europe/Moscow",
    "iso:country":"RU",
    "name:eng_x_preferred":[
        "Belyye Kolodezi"
    ],
    "name:nor_x_preferred":[
        "Belye Kolodezi"
    ],
    "name:rus_x_preferred":[
        "\u0411\u0435\u043b\u044b\u0435 \u041a\u043e\u043b\u043e\u0434\u0435\u0437\u0438"
    ],
    "wof:name":"Belyye Kolodezi",
    "wof:placetype":"locality"
},
  "geometry": {"coordinates":[38.69799,54.91954000000001],"type":"Point"}
}