{
  "type": "Feature",
  "properties": {
    "gn:admin1_code":"8",
    "gn:asciiname":"Saitkulovo",
    "gn:country_code":"RU",
    "gn:dem":215,
    "gn:feature_class":"P",
    "gn:feature_code":"PPL",
    "gn:name":"Saitkulovo",
    "gn:population":0,
    "gn:timezone":"Asia/Yekaterinburg",
    "iso:country":"RU",
    "name:aze_x_preferred":[
        "H\u0259yetkol"
    ],
    "name:bak_x_preferred":[
        "\u04ba\u04d9\u0439\u0435\u0442\u04a1\u043e\u043b"
    ],
    "name:che_x_preferred":[
        "\u0421\u0430\u0438\u0442\u043a\u0443\u043b\u043e\u0432\u043e"
    ],
    "name:hye_x_preferred":[
        "\u054d\u0561\u056b\u057f\u056f\u0578\u0582\u056c\u0578\u057e\u0578"
    ],
    "name:kat_x_preferred":[
        "\u10e1\u10d0\u10d8\u10e2\u10d9\u10e3\u10da\u10dd\u10d5\u10dd"
    ],
    "name:kaz_x_preferred":[
        "\u0421\u0430\u0439\u044b\u0442\u043a\u0443\u043b"
    ],
    "name:kir_x_preferred":[
        "\u0421\u0430\u0439\u044b\u0442\u043a\u0443\u043b"
    ],
    "name:rus_x_preferred":[
        "\u0421\u0430\u0438\u0442\u043a\u0443\u043b\u043e\u0432\u043e"
    ],
    "name:tat_x_preferred":[
        "\u0421\u04d9\u0435\u0442\u043a\u043e\u043b"
    ],
    "name:ukr_x_preferred":[
        "\u0421\u0430\u0457\u0442\u043a\u0443\u043b\u043e\u0432\u043e"
    ],
    "wof:name":"Saitkulovo",
    "wof:placetype":"locality"
},
  "geometry": {"coordinates":[56.53074,52.60206],"type":"Point"}
}