{
  "type": "Feature",
  "properties": {
    "gn:admin1_code":"8",
    "gn:asciiname":"Saitkulovo",
    "gn:country_code":"RU",
    "gn:dem":215,
    "gn:feature_class":"P",
    "gn:feature_code":"PPL",
    "gn:name":"Saitkulovo",
    "gn:population":0,
    "gn:timezone":"Asia/Yekaterinburg",
    "iso:country":"RU",
    "name:rus_x_preferred":[
        "\u0421\u0430\u0438\u0442\u043a\u0443\u043b\u043e\u0432\u043e"
    ],
    "name:und_x_variant":[
        "\u0421\u0430\u0438\u0442\u043a\u0443\u043b\u043e\u0432\u043e"
    ],
    "wof:name":"Saitkulovo",
    "wof:placetype":"locality"
},
  "geometry": {"coordinates":[56.53074,52.60206],"type":"Point"}
}