{
  "type": "Feature",
  "properties": {
    "gn:admin1_code":"20",
    "gn:asciiname":"Kokorina",
    "gn:country_code":"RU",
    "gn:dem":732,
    "gn:feature_class":"P",
    "gn:feature_code":"PPL",
    "gn:name":"Kokorina",
    "gn:population":0,
    "gn:timezone":"Asia/Irkutsk",
    "iso:country":"RU",
    "name:bos_x_preferred":[
        "Kokorina"
    ],
    "name:ell_x_preferred":[
        "\u039a\u03bf\u03ba\u03cc\u03c1\u03b9\u03bd\u03b1"
    ],
    "name:fra_x_preferred":[
        "Kokorina"
    ],
    "name:hrv_x_preferred":[
        "Kokorina"
    ],
    "name:rus_x_preferred":[
        "\u041a\u043e\u043a\u043e\u0440\u0438\u043d\u0430"
    ],
    "name:srp_x_preferred":[
        "\u041a\u043e\u043a\u043e\u0440\u0438\u043d\u0430"
    ],
    "name:und_x_variant":[
        "Markelovka",
        "Kokorine",
        "Kokorino"
    ],
    "wof:name":"Kokorina",
    "wof:placetype":"locality"
},
  "geometry": {"coordinates":[105.16278,53.08583],"type":"Point"}
}