{
  "type": "Feature",
  "properties": {
    "gn:admin1_code":"77",
    "gn:asciiname":"Goreli",
    "gn:country_code":"RU",
    "gn:dem":151,
    "gn:feature_class":"P",
    "gn:feature_code":"PPL",
    "gn:name":"Goreli",
    "gn:population":0,
    "gn:timezone":"Europe/Moscow",
    "iso:country":"RU",
    "name:rus_x_preferred":[
        "\u0413\u043e\u0440\u0435\u043b\u0438"
    ],
    "name:und_x_variant":[
        "\u0413\u043e\u0440\u0435\u043b\u0438"
    ],
    "wof:name":"Goreli",
    "wof:placetype":"locality"
},
  "geometry": {"coordinates":[38.287,57.2871],"type":"Point"}
}