{
  "type": "Feature",
  "properties": {
    "gn:admin1_code":"33",
    "gn:asciiname":"Shabardenki",
    "gn:country_code":"RU",
    "gn:dem":153,
    "gn:feature_class":"P",
    "gn:feature_code":"PPL",
    "gn:name":"Shabardenki",
    "gn:population":0,
    "gn:timezone":"Europe/Kirov",
    "iso:country":"RU",
    "name:eng_x_preferred":[
        "Shabardenki"
    ],
    "name:nor_x_preferred":[
        "Sjabardenki"
    ],
    "name:rus_x_preferred":[
        "\u0428\u0430\u0431\u0430\u0440\u0434\u0435\u043d\u043a\u0438"
    ],
    "name:und_x_variant":[
        "\u0428\u0430\u0431\u0430\u0440\u0434\u0435\u043d\u043a\u0438",
        "Shabardenki"
    ],
    "wof:name":"Shabardenki",
    "wof:placetype":"locality"
},
  "geometry": {"coordinates":[49.40146,58.31251999999999],"type":"Point"}
}