{
  "type": "Feature",
  "properties": {
    "gn:admin1_code":"77",
    "gn:asciiname":"Petraki",
    "gn:country_code":"RU",
    "gn:dem":210,
    "gn:feature_class":"P",
    "gn:feature_code":"PPL",
    "gn:name":"Petraki",
    "gn:population":0,
    "gn:timezone":"Europe/Moscow",
    "iso:country":"RU",
    "name:eng_x_preferred":[
        "Petraki"
    ],
    "name:nor_x_preferred":[
        "Petraki"
    ],
    "name:rus_x_preferred":[
        "\u041f\u0435\u0442\u0440\u0430\u043a\u0438"
    ],
    "wof:name":"Petraki",
    "wof:placetype":"locality"
},
  "geometry": {"coordinates":[31.3204,56.51038000000001],"type":"Point"}
}