{
  "type": "Feature",
  "properties": {
    "gn:admin1_code":"63",
    "gn:asciiname":"Moy-Yuryakh",
    "gn:country_code":"RU",
    "gn:dem":397,
    "gn:feature_class":"P",
    "gn:feature_code":"PPL",
    "gn:name":"Moy-Yuryakh",
    "gn:population":0,
    "gn:timezone":"Asia/Vladivostok",
    "iso:country":"RU",
    "name:rus_x_preferred":[
        "\u041c\u043e\u0439-\u042e\u0440\u044f\u0445"
    ],
    "name:und_x_variant":[
        "Moiskaya",
        "Moi Yuryakh",
        "Moy-Yurikh",
        "Mooy-Yurekh",
        "Moy-Yuryakh"
    ],
    "wof:name":"Moy-Yuryakh",
    "wof:placetype":"locality"
},
  "geometry": {"coordinates":[131.71953999999999,65.94105999999999],"type":"Point"}
}