{
  "type": "Feature",
  "properties": {
    "gn:admin1_code":"5.0",
    "gn:asciiname":"Polyanoye",
    "gn:country_code":"RU",
    "gn:dem":190,
    "gn:feature_class":"P",
    "gn:feature_code":"PPL",
    "gn:name":"Polyanoye",
    "gn:population":0,
    "gn:timezone":"Asia/Yakutsk",
    "iso:country":"RU",
    "name:che_x_preferred":[
        "\u041f\u043e\u043b\u044f\u043d\u0438"
    ],
    "name:rus_x_preferred":[
        "\u041f\u043e\u043b\u044f\u043d\u043e\u0435"
    ],
    "name:tgk_x_preferred":[
        "\u041f\u043e\u043b\u044f\u043d\u043e\u0435"
    ],
    "name:und_x_variant":[
        "Voyenkhoz Nomer Odinnadtsat\u2019",
        "Polyanoye"
    ],
    "wof:name":"Polyanoye",
    "wof:placetype":"locality"
},
  "geometry": {"coordinates":[128.32488000000001,50.73578],"type":"Point"}
}