{
  "type": "Feature",
  "properties": {
    "gn:admin1_code":"28",
    "gn:asciiname":"Mikrilya",
    "gn:cc2":"RU",
    "gn:country_code":"RU",
    "gn:dem":68,
    "gn:feature_class":"P",
    "gn:feature_code":"PPL",
    "gn:name":"Mikrilya",
    "gn:population":0,
    "gn:timezone":"Europe/Moscow",
    "iso:country":"RU",
    "name:fin_x_preferred":[
        "Mikril\u00e4"
    ],
    "name:rus_x_preferred":[
        "\u041c\u0438\u043a\u0440\u0438\u043b\u044f"
    ],
    "name:und_x_variant":[
        "Mikrelya",
        "Mikrilya",
        "\u041c\u0438\u043a\u0440\u0438\u043b\u044f"
    ],
    "wof:name":"Mikrilya",
    "wof:placetype":"locality"
},
  "geometry": {"coordinates":[29.8217,61.43351],"type":"Point"}
}