{
  "type": "Feature",
  "properties": {
    "gn:admin1_code":"88",
    "gn:asciiname":"Matveyevka",
    "gn:country_code":"RU",
    "gn:dem":144,
    "gn:feature_class":"P",
    "gn:feature_code":"PPL",
    "gn:name":"Matveyevka",
    "gn:population":0,
    "gn:timezone":"Europe/Moscow",
    "iso:country":"RU",
    "name:rus_x_preferred":[
        "\u041c\u0430\u0442\u0432\u0435\u0435\u0432\u043a\u0430"
    ],
    "name:und_x_variant":[
        "\u041c\u0430\u0442\u0432\u0435\u0435\u0432\u043a\u0430"
    ],
    "wof:name":"Matveyevka",
    "wof:placetype":"locality"
},
  "geometry": {"coordinates":[38.2634,57.1033],"type":"Point"}
}