{
  "type": "Feature",
  "properties": {
    "gn:admin1_code":"84",
    "gn:asciiname":"Surochinskiy",
    "gn:country_code":"RU",
    "gn:dem":143,
    "gn:feature_class":"P",
    "gn:feature_code":"PPL",
    "gn:name":"Surochinskiy",
    "gn:population":0,
    "gn:timezone":"Europe/Volgograd",
    "iso:country":"RU",
    "name:rus_x_preferred":[
        "\u0421\u0443\u0440\u043e\u0447\u0438\u043d\u0441\u043a\u0438\u0439"
    ],
    "name:und_x_variant":[
        "\u0421\u0443\u0440\u043e\u0447\u0438\u043d\u0441\u043a\u0438\u0439"
    ],
    "wof:name":"Surochinskiy",
    "wof:placetype":"locality"
},
  "geometry": {"coordinates":[41.51028,50.7025],"type":"Point"}
}