{
  "type": "Feature",
  "properties": {
    "gn:admin1_code":"17",
    "gn:admin2_code":"557977",
    "gn:asciiname":"Agada",
    "gn:country_code":"RU",
    "gn:dem":1210,
    "gn:feature_class":"P",
    "gn:feature_code":"PPL",
    "gn:name":"Agada",
    "gn:population":0,
    "gn:timezone":"Europe/Moscow",
    "iso:country":"RU",
    "name:fra_x_preferred":[
        "Agada"
    ],
    "name:hin_x_preferred":[
        "\u0905\u0917\u0926\u0924\u0902\u0924\u094d\u0930"
    ],
    "name:ita_x_preferred":[
        "Agada"
    ],
    "name:mal_x_preferred":[
        "\u0d05\u0d17\u0d26\u0d24\u0d28\u0d4d\u0d24\u0d4d\u0d30\u0d02"
    ],
    "name:nor_x_preferred":[
        "Agada"
    ],
    "name:pol_x_preferred":[
        "Agada"
    ],
    "name:rus_x_preferred":[
        "\u0410\u0433\u0430\u0434\u0430"
    ],
    "name:zho_x_preferred":[
        "\u963f\u4f3d\u9640"
    ],
    "wof:name":"Agada",
    "wof:placetype":"locality"
},
  "geometry": {"coordinates":[46.84139,42.41278],"type":"Point"}
}