{
  "type": "Feature",
  "properties": {
    "gn:admin1_code":"8",
    "gn:asciiname":"Novousmanovo",
    "gn:country_code":"RU",
    "gn:dem":459,
    "gn:feature_class":"P",
    "gn:feature_code":"PPL",
    "gn:name":"Novousmanovo",
    "gn:population":0,
    "gn:timezone":"Asia/Yekaterinburg",
    "iso:country":"RU",
    "name:bak_x_preferred":[
        "\u042f\u04a3\u044b \u0423\u04ab\u043c\u0430\u043d"
    ],
    "name:che_x_preferred":[
        "\u041d\u043e\u0432\u043e\u0443\u0441\u043c\u0430\u043d\u043e\u0432\u043e"
    ],
    "name:eng_x_preferred":[
        "Novousmanovo"
    ],
    "name:hye_x_preferred":[
        "\u0546\u0578\u057e\u0578\u0578\u0582\u057d\u0574\u0561\u0576\u0578\u057e\u0578"
    ],
    "name:kat_x_preferred":[
        "\u10dc\u10dd\u10d5\u10dd\u10e3\u10e1\u10db\u10d0\u10dc\u10dd\u10d5\u10dd"
    ],
    "name:kaz_x_preferred":[
        "\u0416\u0430\u04a3\u0430 \u0443\u0441\u043c\u0430\u043d"
    ],
    "name:kir_x_preferred":[
        "\u0416\u0430\u04a3\u044b \u0443\u0441\u043c\u0430\u043d"
    ],
    "name:nor_x_preferred":[
        "Novousmanovo"
    ],
    "name:rus_x_preferred":[
        "\u041d\u043e\u0432\u043e\u0443\u0441\u043c\u0430\u043d\u043e\u0432\u043e"
    ],
    "name:tat_x_preferred":[
        "\u042f\u04a3\u0430 \u0423\u0441\u043c\u0430\u043d"
    ],
    "name:ukr_x_preferred":[
        "\u041d\u043e\u0432\u043e\u0443\u0441\u043c\u0430\u043d\u043e\u0432\u043e"
    ],
    "wof:name":"Novousmanovo",
    "wof:placetype":"locality"
},
  "geometry": {"coordinates":[57.6535,53.067],"type":"Point"}
}