{
  "type": "Feature",
  "properties": {
    "gn:admin1_code":"63",
    "gn:asciiname":"Khalynya",
    "gn:country_code":"RU",
    "gn:dem":750,
    "gn:feature_class":"P",
    "gn:feature_code":"PPL",
    "gn:name":"Khalynya",
    "gn:population":0,
    "gn:timezone":"Asia/Yakutsk",
    "iso:country":"RU",
    "name:rus_x_preferred":[
        "\u0425\u0430\u043b\u044b\u043d\u044f"
    ],
    "name:und_x_variant":[
        "\u0425\u0430\u043b\u044b\u043d\u044f"
    ],
    "wof:name":"Khalynya",
    "wof:placetype":"locality"
},
  "geometry": {"coordinates":[129.69014999999999,67.57559000000001],"type":"Point"}
}