{
  "type": "Feature",
  "properties": {
    "gn:admin1_code":"53",
    "gn:asciiname":"Kiyevka",
    "gn:country_code":"RU",
    "gn:dem":200,
    "gn:feature_class":"P",
    "gn:feature_code":"PPL",
    "gn:name":"Kiyevka",
    "gn:population":0,
    "gn:timezone":"Asia/Novosibirsk",
    "iso:country":"RU",
    "name:rus_x_preferred":[
        "\u041a\u0438\u0435\u0432\u043a\u0430"
    ],
    "wof:name":"Kiyevka",
    "wof:placetype":"locality"
},
  "geometry": {"coordinates":[84.23194000000002,55.60556],"type":"Point"}
}