{
  "type": "Feature",
  "properties": {
    "gn:admin1_code":"9",
    "gn:asciiname":"Nizhneye Kuzkino",
    "gn:country_code":"RU",
    "gn:dem":223,
    "gn:feature_class":"P",
    "gn:feature_code":"PPL",
    "gn:name":"Nizhneye Kuzkino",
    "gn:population":0,
    "gn:timezone":"Europe/Moscow",
    "iso:country":"RU",
    "wof:name":"Nizhneye Kuzkino",
    "wof:placetype":"locality"
},
  "geometry": {"coordinates":[37.55571,50.90681],"type":"Point"}
}