{
  "type": "Feature",
  "properties": {
    "gn:admin1_code":"45.0",
    "gn:asciiname":"Mari-Leblyak",
    "gn:country_code":"RU",
    "gn:dem":161,
    "gn:feature_class":"P",
    "gn:feature_code":"PPL",
    "gn:name":"Mari-Leblyak",
    "gn:population":0,
    "gn:timezone":"Europe/Moscow",
    "iso:country":"RU",
    "name:rus_x_preferred":[
        "\u041c\u0430\u0440\u0438-\u041b\u0435\u0431\u043b\u044f\u043a"
    ],
    "name:und_x_variant":[
        "\u041c\u0430\u0440\u0438-\u041b\u0435\u0431\u043b\u044f\u043a"
    ],
    "wof:name":"Mari-Leblyak",
    "wof:placetype":"locality"
},
  "geometry": {"coordinates":[49.36444,56.74778000000001],"type":"Point"}
}