{
  "type": "Feature",
  "properties": {
    "gn:admin1_code":"47",
    "gn:asciiname":"Starogor'ye",
    "gn:country_code":"RU",
    "gn:dem":164,
    "gn:feature_class":"P",
    "gn:feature_code":"PPL",
    "gn:name":"Starogor\u2019ye",
    "gn:population":0,
    "gn:timezone":"Europe/Moscow",
    "iso:country":"RU",
    "name:rus_x_preferred":[
        "\u0421\u0442\u0430\u0440\u043e\u0433\u043e\u0440\u044c\u0435"
    ],
    "name:und_x_variant":[
        "Starogor\u2019ye",
        "\u0421\u0442\u0430\u0440\u043e\u0433\u043e\u0440\u044c\u0435"
    ],
    "wof:name":"Starogor'ye",
    "wof:placetype":"locality"
},
  "geometry": {"coordinates":[37.66667,55.98333],"type":"Point"}
}