{
  "type": "Feature",
  "properties": {
    "gn:admin1_code":"62.0",
    "gn:asciiname":"Sel'tso Gavrilovskoye",
    "gn:country_code":"RU",
    "gn:dem":133,
    "gn:feature_class":"P",
    "gn:feature_code":"PPL",
    "gn:name":"Sel\u2019tso Gavrilovskoye",
    "gn:population":0,
    "gn:timezone":"Europe/Moscow",
    "iso:country":"RU",
    "name:rus_x_preferred":[
        "\u0421\u0435\u043b\u044c\u0446\u043e \u0413\u0430\u0432\u0440\u0438\u043b\u043e\u0432\u0441\u043a\u043e\u0435"
    ],
    "name:und_x_variant":[
        "Gavrilovskoye",
        "Sel\u2019tso Gavrilovskoye"
    ],
    "wof:name":"Sel'tso Gavrilovskoye",
    "wof:placetype":"locality"
},
  "geometry": {"coordinates":[40.0906,54.4394],"type":"Point"}
}