{
  "type": "Feature",
  "properties": {
    "gn:admin1_code":"63",
    "gn:admin2_code":"Nyurbinsky District (undefined)",
    "gn:asciiname":"Chappanda",
    "gn:cc2":"RU",
    "gn:country_code":"RU",
    "gn:dem":115,
    "gn:feature_class":"P",
    "gn:feature_code":"PPL",
    "gn:name":"Chappanda",
    "gn:population":0,
    "gn:timezone":"Asia/Yakutsk",
    "iso:country":"RU",
    "name:eng_x_preferred":[
        "Chappanda"
    ],
    "name:nor_x_preferred":[
        "Tsjappanda"
    ],
    "name:rus_x_preferred":[
        "\u0427\u0430\u043f\u043f\u0430\u043d\u0434\u0430"
    ],
    "name:und_x_variant":[
        "Chapangda",
        "\u0427\u0430\u043f\u043f\u0430\u043d\u0434\u0430",
        "Chappanda"
    ],
    "wof:name":"Chappanda",
    "wof:placetype":"locality"
},
  "geometry": {"coordinates":[118.61528,63.42278],"type":"Point"}
}