{
  "type": "Feature",
  "properties": {
    "gn:admin1_code":"77.0",
    "gn:asciiname":"Glinskoye",
    "gn:country_code":"RU",
    "gn:dem":174,
    "gn:feature_class":"P",
    "gn:feature_code":"PPL",
    "gn:name":"Glinskoye",
    "gn:population":0,
    "gn:timezone":"Europe/Moscow",
    "iso:country":"RU",
    "name:rus_x_preferred":[
        "\u0413\u043b\u0438\u043d\u0441\u043a\u043e\u0435"
    ],
    "wof:name":"Glinskoye",
    "wof:placetype":"locality"
},
  "geometry": {"coordinates":[32.03528,55.94111],"type":"Point"}
}