{
  "type": "Feature",
  "properties": {
    "gn:admin1_code":"33",
    "gn:asciiname":"Kozly-Konichi",
    "gn:country_code":"RU",
    "gn:dem":152,
    "gn:feature_class":"P",
    "gn:feature_code":"PPL",
    "gn:name":"Kozly-Konichi",
    "gn:population":0,
    "gn:timezone":"Europe/Kirov",
    "iso:country":"RU",
    "name:rus_x_preferred":[
        "\u041a\u043e\u0437\u043b\u044b-\u041a\u043e\u043d\u0438\u0447\u0438"
    ],
    "wof:name":"Kozly-Konichi",
    "wof:placetype":"locality"
},
  "geometry": {"coordinates":[47.75031,58.28223000000001],"type":"Point"}
}