{
  "type": "Feature",
  "properties": {
    "gn:admin1_code":"46",
    "gn:asciiname":"Groznaya Krepost'",
    "gn:country_code":"RU",
    "gn:dem":124,
    "gn:feature_class":"P",
    "gn:feature_code":"PPL",
    "gn:name":"Groznaya Krepost\u2019",
    "gn:population":0,
    "gn:timezone":"Europe/Moscow",
    "iso:country":"RU",
    "name:rus_x_preferred":[
        "\u0413\u0440\u043e\u0437\u043d\u0430\u044f \u041a\u0440\u0435\u043f\u043e\u0441\u0442\u044c"
    ],
    "name:und_x_variant":[
        "Groznaya Krepost\u2019",
        "\u0413\u0440\u043e\u0437\u043d\u0430\u044f \u041a\u0440\u0435\u043f\u043e\u0441\u0442\u044c"
    ],
    "wof:name":"Groznaya Krepost'",
    "wof:placetype":"locality"
},
  "geometry": {"coordinates":[45.9195,54.978],"type":"Point"}
}