{
  "type": "Feature",
  "properties": {
    "gn:admin1_code":"20",
    "gn:asciiname":"Parizhskaya Kommuna",
    "gn:country_code":"RU",
    "gn:dem":284,
    "gn:feature_class":"P",
    "gn:feature_code":"PPL",
    "gn:name":"Parizhskaya Kommuna",
    "gn:population":0,
    "gn:timezone":"Asia/Irkutsk",
    "iso:country":"RU",
    "name:rus_x_preferred":[
        "\u041f\u0430\u0440\u0438\u0436\u0441\u043a\u0430\u044f \u041a\u043e\u043c\u043c\u0443\u043d\u0430"
    ],
    "wof:name":"Parizhskaya Kommuna",
    "wof:placetype":"locality"
},
  "geometry": {"coordinates":[98.1247,55.9403],"type":"Point"}
}