{
  "type": "Feature",
  "properties": {
    "gn:admin1_code":"77",
    "gn:asciiname":"Dityatevo",
    "gn:country_code":"RU",
    "gn:dem":141,
    "gn:feature_class":"P",
    "gn:feature_code":"PPL",
    "gn:name":"Dityatevo",
    "gn:population":0,
    "gn:timezone":"Europe/Moscow",
    "iso:country":"RU",
    "name:rus_x_preferred":[
        "\u0414\u0438\u0442\u044f\u0442\u0435\u0432\u043e"
    ],
    "wof:name":"Dityatevo",
    "wof:placetype":"locality"
},
  "geometry": {"coordinates":[36.7769,57.0715],"type":"Point"}
}