{
  "type": "Feature",
  "properties": {
    "gn:admin1_code":"6",
    "gn:asciiname":"Krasnyy Poselok",
    "gn:country_code":"RU",
    "gn:dem":9,
    "gn:feature_class":"P",
    "gn:feature_code":"PPL",
    "gn:name":"Krasnyy Poselok",
    "gn:population":0,
    "gn:timezone":"Europe/Moscow",
    "iso:country":"RU",
    "name:rus_x_preferred":[
        "\u041a\u0440\u0430\u0441\u043d\u044b\u0439 \u041f\u043e\u0441\u0435\u043b\u043e\u043a"
    ],
    "wof:name":"Krasnyy Poselok",
    "wof:placetype":"locality"
},
  "geometry": {"coordinates":[40.45,64.63333],"type":"Point"}
}