{
  "type": "Feature",
  "properties": {
    "gn:admin1_code":"55",
    "gn:asciiname":"Mamalayevka",
    "gn:country_code":"RU",
    "gn:dem":156,
    "gn:feature_class":"P",
    "gn:feature_code":"PPL",
    "gn:name":"Mamalayevka",
    "gn:population":0,
    "gn:timezone":"Asia/Yekaterinburg",
    "iso:country":"RU",
    "name:eng_x_preferred":[
        "Mamalayevka"
    ],
    "name:nor_x_preferred":[
        "Mamalajevka"
    ],
    "name:rus_x_preferred":[
        "\u041c\u0430\u043c\u0430\u043b\u0430\u0435\u0432\u043a\u0430"
    ],
    "name:und_x_variant":[
        "Mamalayevskaya",
        "\u041c\u0430\u043c\u0430\u043b\u0430\u0435\u0432\u043a\u0430",
        "Mamalayevka"
    ],
    "wof:name":"Mamalayevka",
    "wof:placetype":"locality"
},
  "geometry": {"coordinates":[54.0521,51.92582],"type":"Point"}
}