{
  "type": "Feature",
  "properties": {
    "gn:admin1_code":"60",
    "gn:asciiname":"Novgorodka",
    "gn:country_code":"RU",
    "gn:dem":78,
    "gn:feature_class":"P",
    "gn:feature_code":"PPL",
    "gn:name":"Novgorodka",
    "gn:population":0,
    "gn:timezone":"Europe/Moscow",
    "iso:country":"RU",
    "name:eng_x_preferred":[
        "Novgorodka"
    ],
    "name:nor_x_preferred":[
        "Novgorodka"
    ],
    "name:rus_x_preferred":[
        "\u041d\u043e\u0432\u0433\u043e\u0440\u043e\u0434\u043a\u0430"
    ],
    "wof:name":"Novgorodka",
    "wof:placetype":"locality"
},
  "geometry": {"coordinates":[28.57981,57.05304],"type":"Point"}
}