{
  "type": "Feature",
  "properties": {
    "gn:admin1_code":"33.0",
    "gn:asciiname":"Nizhniye Yaryiginy",
    "gn:country_code":"RU",
    "gn:dem":104,
    "gn:feature_class":"P",
    "gn:feature_code":"PPL",
    "gn:name":"Nizhniye Yaryiginy",
    "gn:population":0,
    "gn:timezone":"Europe/Kirov",
    "iso:country":"RU",
    "name:rus_x_preferred":[
        "\u041d\u0438\u0436\u043d\u0438\u0435 \u042f\u0440\u044b\u0433\u0438\u043d\u044b"
    ],
    "wof:name":"Nizhniye Yaryiginy",
    "wof:placetype":"locality"
},
  "geometry": {"coordinates":[48.77035,58.4147],"type":"Point"}
}