{
  "type": "Feature",
  "properties": {
    "gn:admin1_code":"73",
    "gn:asciiname":"Bernovyye Kovali",
    "gn:country_code":"RU",
    "gn:dem":98,
    "gn:feature_class":"P",
    "gn:feature_code":"PPL",
    "gn:name":"Bernovyye Kovali",
    "gn:population":0,
    "gn:timezone":"Europe/Moscow",
    "iso:country":"RU",
    "name:rus_x_preferred":[
        "\u0411\u0435\u0440\u043d\u043e\u0432\u044b\u0435 \u041a\u043e\u0432\u0430\u043b\u0438"
    ],
    "wof:name":"Bernovyye Kovali",
    "wof:placetype":"locality"
},
  "geometry": {"coordinates":[49.04157,55.98676999999999],"type":"Point"}
}