{
  "type": "Feature",
  "properties": {
    "gn:admin1_code":"75",
    "gn:asciiname":"Kolbikha",
    "gn:country_code":"RU",
    "gn:dem":243,
    "gn:feature_class":"P",
    "gn:feature_code":"PPL",
    "gn:name":"Kolbikha",
    "gn:population":0,
    "gn:timezone":"Asia/Tomsk",
    "iso:country":"RU",
    "name:rus_x_preferred":[
        "\u041a\u043e\u043b\u0431\u0438\u0445\u0430"
    ],
    "name:und_x_variant":[
        "\u041a\u043e\u043b\u0431\u0438\u0445\u0430"
    ],
    "wof:name":"Kolbikha",
    "wof:placetype":"locality"
},
  "geometry": {"coordinates":[85.58333,56.51667],"type":"Point"}
}