{
  "type": "Feature",
  "properties": {
    "gn:admin1_code":"90.0",
    "gn:asciiname":"Garevaya",
    "gn:country_code":"RU",
    "gn:dem":105,
    "gn:feature_class":"P",
    "gn:feature_code":"PPL",
    "gn:name":"Garevaya",
    "gn:population":0,
    "gn:timezone":"Asia/Yekaterinburg",
    "iso:country":"RU",
    "name:eng_x_preferred":[
        "Garevaya"
    ],
    "name:nor_x_preferred":[
        "Garevaja"
    ],
    "name:rus_x_preferred":[
        "\u0413\u0430\u0440\u0435\u0432\u0430\u044f"
    ],
    "name:und_x_variant":[
        "\u0413\u0430\u0440\u0435\u0432\u0430\u044f"
    ],
    "wof:name":"Garevaya",
    "wof:placetype":"locality"
},
  "geometry": {"coordinates":[54.29543,56.71316],"type":"Point"}
}