{
  "type": "Feature",
  "properties": {
    "gn:admin1_code":"60",
    "gn:asciiname":"Batalovo",
    "gn:country_code":"RU",
    "gn:dem":71,
    "gn:feature_class":"P",
    "gn:feature_code":"PPL",
    "gn:name":"Batalovo",
    "gn:population":0,
    "gn:timezone":"Europe/Moscow",
    "iso:country":"RU",
    "name:rus_x_preferred":[
        "\u0411\u0430\u0442\u0430\u043b\u043e\u0432\u043e"
    ],
    "wof:name":"Batalovo",
    "wof:placetype":"locality"
},
  "geometry": {"coordinates":[28.18789,57.06059000000001],"type":"Point"}
}