{
  "type": "Feature",
  "properties": {
    "gn:admin1_code":"45",
    "gn:asciiname":"Shereganovo",
    "gn:country_code":"RU",
    "gn:dem":180,
    "gn:feature_class":"P",
    "gn:feature_code":"PPL",
    "gn:name":"Shereganovo",
    "gn:population":0,
    "gn:timezone":"Europe/Moscow",
    "iso:country":"RU",
    "name:rus_x_preferred":[
        "\u0428\u0435\u0440\u0435\u0433\u0430\u043d\u043e\u0432\u043e"
    ],
    "name:und_x_variant":[
        "Shoragan",
        "Shereganovo"
    ],
    "wof:name":"Shereganovo",
    "wof:placetype":"locality"
},
  "geometry": {"coordinates":[48.70667,56.34222],"type":"Point"}
}