{
  "type": "Feature",
  "properties": {
    "gn:admin1_code":"69",
    "gn:asciiname":"Matyukhi",
    "gn:country_code":"RU",
    "gn:dem":156,
    "gn:feature_class":"P",
    "gn:feature_code":"PPL",
    "gn:name":"Matyukhi",
    "gn:population":0,
    "gn:timezone":"Europe/Moscow",
    "iso:country":"RU",
    "name:rus_x_preferred":[
        "\u041c\u0430\u0442\u044e\u0445\u0438"
    ],
    "name:und_x_variant":[
        "\u041c\u0430\u0442\u044e\u0445\u0438"
    ],
    "wof:name":"Matyukhi",
    "wof:placetype":"locality"
},
  "geometry": {"coordinates":[30.96013,55.46019],"type":"Point"}
}