{
  "type": "Feature",
  "properties": {
    "gn:admin1_code":"64",
    "gn:asciiname":"Rybnoye",
    "gn:country_code":"RU",
    "gn:dem":4,
    "gn:feature_class":"P",
    "gn:feature_code":"PPL",
    "gn:name":"Rybnoye",
    "gn:population":0,
    "gn:timezone":"Asia/Sakhalin",
    "iso:country":"RU",
    "name:eng_x_preferred":[
        "Rybnoye"
    ],
    "name:nor_x_preferred":[
        "Rybnoje"
    ],
    "name:rus_x_preferred":[
        "\u0420\u044b\u0431\u043d\u043e\u0435"
    ],
    "name:und_x_variant":[
        "Robnoye",
        "Rybnovsk"
    ],
    "wof:name":"Rybnoye",
    "wof:placetype":"locality"
},
  "geometry": {"coordinates":[141.84576999999999,53.41147],"type":"Point"}
}