{
  "type": "Feature",
  "properties": {
    "gn:admin1_code":"40",
    "gn:asciiname":"Mostovskoye",
    "gn:country_code":"RU",
    "gn:dem":70,
    "gn:feature_class":"P",
    "gn:feature_code":"PPL",
    "gn:name":"Mostovskoye",
    "gn:population":0,
    "gn:timezone":"Asia/Yekaterinburg",
    "iso:country":"RU",
    "name:eng_x_preferred":[
        "Mostovskoye"
    ],
    "name:nor_x_preferred":[
        "Mostovskoje"
    ],
    "name:rus_x_preferred":[
        "\u041c\u043e\u0441\u0442\u043e\u0432\u0441\u043a\u043e\u0435"
    ],
    "wof:name":"Mostovskoye",
    "wof:placetype":"locality"
},
  "geometry": {"coordinates":[65.0033,56.413],"type":"Point"}
}