{
  "type": "Feature",
  "properties": {
    "gn:admin1_code":"77",
    "gn:asciiname":"Dremukha",
    "gn:country_code":"RU",
    "gn:dem":183,
    "gn:feature_class":"P",
    "gn:feature_code":"PPL",
    "gn:name":"Dremukha",
    "gn:population":0,
    "gn:timezone":"Europe/Moscow",
    "iso:country":"RU",
    "name:rus_x_preferred":[
        "\u0414\u0440\u0435\u043c\u0443\u0445\u0430"
    ],
    "wof:name":"Dremukha",
    "wof:placetype":"locality"
},
  "geometry": {"coordinates":[34.65975,57.92415],"type":"Point"}
}