{
  "type": "Feature",
  "properties": {
    "gn:admin1_code":"88",
    "gn:asciiname":"Tchanovo",
    "gn:country_code":"RU",
    "gn:dem":131,
    "gn:feature_class":"P",
    "gn:feature_code":"PPL",
    "gn:name":"Tchanovo",
    "gn:population":0,
    "gn:timezone":"Europe/Moscow",
    "iso:country":"RU",
    "name:rus_x_preferred":[
        "\u0422\u0447\u0430\u043d\u043e\u0432\u043e"
    ],
    "wof:name":"Tchanovo",
    "wof:placetype":"locality"
},
  "geometry": {"coordinates":[38.4575,57.4427],"type":"Point"}
}