{
  "type": "Feature",
  "properties": {
    "gn:admin1_code":"55",
    "gn:asciiname":"Yefimovka",
    "gn:country_code":"RU",
    "gn:dem":94,
    "gn:feature_class":"P",
    "gn:feature_code":"PPL",
    "gn:name":"Yefimovka",
    "gn:population":0,
    "gn:timezone":"Asia/Yekaterinburg",
    "iso:country":"RU",
    "name:eng_x_preferred":[
        "Yefimovka"
    ],
    "name:nor_x_preferred":[
        "Jefimovka"
    ],
    "name:rus_x_preferred":[
        "\u0415\u0444\u0438\u043c\u043e\u0432\u043a\u0430"
    ],
    "wof:name":"Yefimovka",
    "wof:placetype":"locality"
},
  "geometry": {"coordinates":[52.0475,52.2144],"type":"Point"}
}