{
  "type": "Feature",
  "properties": {
    "gn:admin1_code":"90.0",
    "gn:asciiname":"Bol'shoye Kuznetsovo",
    "gn:country_code":"RU",
    "gn:dem":143,
    "gn:feature_class":"P",
    "gn:feature_code":"PPL",
    "gn:name":"Bol\u2019shoye Kuznetsovo",
    "gn:population":0,
    "gn:timezone":"Asia/Yekaterinburg",
    "iso:country":"RU",
    "name:rus_x_preferred":[
        "\u0411\u043e\u043b\u044c\u0448\u043e\u0435 \u041a\u0443\u0437\u043d\u0435\u0446\u043e\u0432\u043e"
    ],
    "name:und_x_variant":[
        "Bol\u2019shaya Kuznetsova",
        "Bol\u2019shoye Kuznetsovo",
        "\u0411\u043e\u043b\u044c\u0448\u043e\u0435 \u041a\u0443\u0437\u043d\u0435\u0446\u043e\u0432\u043e"
    ],
    "wof:name":"Bol'shoye Kuznetsovo",
    "wof:placetype":"locality"
},
  "geometry": {"coordinates":[55.993,59.6747],"type":"Point"}
}