{
  "type": "Feature",
  "properties": {
    "gn:admin1_code":"20",
    "gn:asciiname":"Andreyevskiy",
    "gn:country_code":"RU",
    "gn:dem":1448,
    "gn:feature_class":"P",
    "gn:feature_code":"PPL",
    "gn:name":"Andreyevskiy",
    "gn:population":0,
    "gn:timezone":"Asia/Irkutsk",
    "iso:country":"RU",
    "name:eng_x_preferred":[
        "Andreyevskiy"
    ],
    "name:nor_x_preferred":[
        "Andrejevskij"
    ],
    "name:rus_x_preferred":[
        "\u0410\u043d\u0434\u0440\u0435\u0435\u0432\u0441\u043a\u0438\u0439"
    ],
    "name:und_x_variant":[
        "\u0410\u043d\u0434\u0440\u0435\u0435\u0432\u0441\u043a\u0438\u0439",
        "Andreyevskiy"
    ],
    "wof:name":"Andreyevskiy",
    "wof:placetype":"locality"
},
  "geometry": {"coordinates":[97.40000000000001,54.01667],"type":"Point"}
}