{
  "type": "Feature",
  "properties": {
    "gn:admin1_code":"52.0",
    "gn:asciiname":"Fal'ki",
    "gn:country_code":"RU",
    "gn:dem":75,
    "gn:feature_class":"P",
    "gn:feature_code":"PPL",
    "gn:name":"Fal\u2019ki",
    "gn:population":0,
    "gn:timezone":"Europe/Moscow",
    "iso:country":"RU",
    "name:rus_x_preferred":[
        "\u0424\u0430\u043b\u044c\u043a\u0438"
    ],
    "name:und_x_variant":[
        "Fal\u2019ki"
    ],
    "wof:name":"Fal'ki",
    "wof:placetype":"locality"
},
  "geometry": {"coordinates":[30.13333,57.93333000000001],"type":"Point"}
}