{
  "type": "Feature",
  "properties": {
    "gn:admin1_code":"57",
    "gn:asciiname":"Verkhnyaya Salmovka",
    "gn:country_code":"RU",
    "gn:dem":228,
    "gn:feature_class":"P",
    "gn:feature_code":"PPL",
    "gn:name":"Verkhnyaya Salmovka",
    "gn:population":0,
    "gn:timezone":"Europe/Moscow",
    "iso:country":"RU",
    "name:rus_x_preferred":[
        "\u0412\u0435\u0440\u0445\u043d\u044f\u044f \u0421\u0430\u043b\u043c\u043e\u0432\u043a\u0430"
    ],
    "name:und_x_variant":[
        "\u0412\u0435\u0440\u0445\u043d\u044f\u044f \u0421\u0430\u043b\u043c\u043e\u0432\u043a\u0430",
        "Verkhnyaya Solmovka"
    ],
    "wof:name":"Verkhnyaya Salmovka",
    "wof:placetype":"locality"
},
  "geometry": {"coordinates":[44.68289,53.89019],"type":"Point"}
}