{
  "type": "Feature",
  "properties": {
    "gn:admin1_code":"57.0",
    "gn:asciiname":"Trushnino",
    "gn:country_code":"RU",
    "gn:dem":171,
    "gn:feature_class":"P",
    "gn:feature_code":"PPL",
    "gn:name":"Trushnino",
    "gn:population":0,
    "gn:timezone":"Europe/Moscow",
    "iso:country":"RU",
    "name:rus_x_preferred":[
        "\u0422\u0440\u0443\u0448\u043d\u0438\u043d\u043e"
    ],
    "wof:name":"Trushnino",
    "wof:placetype":"locality"
},
  "geometry": {"coordinates":[45.47152,53.11908],"type":"Point"}
}