{
  "type": "Feature",
  "properties": {
    "gn:admin1_code":"62",
    "gn:asciiname":"Demen'shchino",
    "gn:country_code":"RU",
    "gn:dem":167,
    "gn:feature_class":"P",
    "gn:feature_code":"PPL",
    "gn:name":"Demen\u2019shchino",
    "gn:population":0,
    "gn:timezone":"Europe/Moscow",
    "iso:country":"RU",
    "name:rus_x_preferred":[
        "\u0414\u0435\u043c\u0435\u043d\u044c\u0449\u0438\u043d\u043e"
    ],
    "name:und_x_variant":[
        "Demenshchina",
        "Demen\u2019shchino",
        "\u0414\u0435\u043c\u0435\u043d\u044c\u0449\u0438\u043d\u043e",
        "Demen\u2019shino"
    ],
    "wof:name":"Demen'shchino",
    "wof:placetype":"locality"
},
  "geometry": {"coordinates":[39.55945,53.93564],"type":"Point"}
}