{
  "type": "Feature",
  "properties": {
    "gn:admin1_code":"9.0",
    "gn:asciiname":"Zayarovka",
    "gn:country_code":"RU",
    "gn:dem":133,
    "gn:feature_class":"P",
    "gn:feature_code":"PPL",
    "gn:name":"Zayarovka",
    "gn:population":0,
    "gn:timezone":"Europe/Moscow",
    "iso:country":"RU",
    "name:rus_x_preferred":[
        "\u0417\u0430\u044f\u0440\u043e\u0432\u043a\u0430"
    ],
    "wof:name":"Zayarovka",
    "wof:placetype":"locality"
},
  "geometry": {"coordinates":[37.5293,50.4097],"type":"Point"}
}