{
  "type": "Feature",
  "properties": {
    "gn:admin1_code":"52.0",
    "gn:asciiname":"Chekunovo",
    "gn:country_code":"RU",
    "gn:dem":72,
    "gn:feature_class":"P",
    "gn:feature_code":"PPL",
    "gn:name":"Chekunovo",
    "gn:population":0,
    "gn:timezone":"Europe/Moscow",
    "iso:country":"RU",
    "name:rus_x_preferred":[
        "\u0427\u0435\u043a\u0443\u043d\u043e\u0432\u043e"
    ],
    "name:und_x_variant":[
        "Chikonovo",
        "Chikumovo",
        "Chikunovo",
        "Chekunovo",
        "\u0427\u0435\u043a\u0443\u043d\u043e\u0432\u043e"
    ],
    "wof:name":"Chekunovo",
    "wof:placetype":"locality"
},
  "geometry": {"coordinates":[31.13292,57.19529],"type":"Point"}
}