{
  "type": "Feature",
  "properties": {
    "gn:admin1_code":"33",
    "gn:asciiname":"Shurma-Nikol'skiy",
    "gn:country_code":"RU",
    "gn:dem":129,
    "gn:feature_class":"P",
    "gn:feature_code":"PPL",
    "gn:name":"Shurma-Nikol\u2019skiy",
    "gn:population":0,
    "gn:timezone":"Europe/Kirov",
    "iso:country":"RU",
    "name:rus_x_preferred":[
        "\u0428\u0443\u0440\u043c\u0430-\u041d\u0438\u043a\u043e\u043b\u044c\u0441\u043a\u0438\u0439"
    ],
    "name:und_x_variant":[
        "Shurma-Nikol\u2019skiy"
    ],
    "wof:name":"Shurma-Nikol'skiy",
    "wof:placetype":"locality"
},
  "geometry": {"coordinates":[50.1657,56.8939],"type":"Point"}
}