{
  "type": "Feature",
  "properties": {
    "gn:admin1_code":"42",
    "gn:admin2_code":"472711",
    "gn:asciiname":"Kirishi",
    "gn:country_code":"RU",
    "gn:dem":68,
    "gn:feature_class":"P",
    "gn:feature_code":"PPL",
    "gn:name":"Kirishi",
    "gn:population":0,
    "gn:timezone":"Europe/Moscow",
    "iso:country":"RU",
    "name:rus_x_preferred":[
        "\u041a\u0438\u0440\u0438\u0448\u0438"
    ],
    "name:und_x_variant":[
        "Kireshi",
        "Kirishi",
        "\u041a\u0438\u0440\u0438\u0448\u0438"
    ],
    "wof:name":"Kirishi",
    "wof:placetype":"locality"
},
  "geometry": {"coordinates":[32.92262,59.96136],"type":"Point"}
}