{
  "type": "Feature",
  "properties": {
    "gn:admin1_code":"42",
    "gn:admin2_code":"472711",
    "gn:asciiname":"Kirishi",
    "gn:country_code":"RU",
    "gn:dem":68,
    "gn:feature_class":"P",
    "gn:feature_code":"PPL",
    "gn:name":"Kirishi",
    "gn:population":0,
    "gn:timezone":"Europe/Moscow",
    "iso:country":"RU",
    "name:ara_x_preferred":[
        "\u0643\u064a\u0631\u064a\u0634\u064a"
    ],
    "name:azb_x_preferred":[
        "\u06a9\u06cc\u0631\u06cc\u0634\u06cc"
    ],
    "name:bel_x_preferred":[
        "\u041a\u0456\u0440\u044b\u0448\u044b"
    ],
    "name:ceb_x_preferred":[
        "Kirishi"
    ],
    "name:ces_x_preferred":[
        "Kiri\u0161i"
    ],
    "name:che_x_preferred":[
        "\u041a\u0438\u0440\u0438\u0448\u0438"
    ],
    "name:chu_x_preferred":[
        "\u041a\u0438\u0440\u0438\u0448\u0438"
    ],
    "name:chv_x_preferred":[
        "\u041a\u0438\u0440\u0438\u0448\u0438"
    ],
    "name:deu_x_preferred":[
        "Kirischi"
    ],
    "name:ell_x_preferred":[
        "\u039a\u03af\u03c1\u03b9\u03c3\u03b9"
    ],
    "name:epo_x_preferred":[
        "Kiri\u015di"
    ],
    "name:est_x_preferred":[
        "Kiri\u0161i"
    ],
    "name:fas_x_preferred":[
        "\u06a9\u06cc\u0631\u06cc\u0634\u06cc"
    ],
    "name:fin_x_preferred":[
        "Kiri\u0161i"
    ],
    "name:fra_x_preferred":[
        "Kirichi"
    ],
    "name:hsb_x_preferred":[
        "Kiri\u0161i"
    ],
    "name:ita_x_preferred":[
        "Kiri\u0161i"
    ],
    "name:kat_x_preferred":[
        "\u10d9\u10d8\u10e0\u10d8\u10e8\u10d8"
    ],
    "name:kor_x_preferred":[
        "\ud0a4\ub9ac\uc2dc"
    ],
    "name:lav_x_preferred":[
        "Kiri\u0161i"
    ],
    "name:lit_x_preferred":[
        "Kiri\u0161ai"
    ],
    "name:nld_x_preferred":[
        "Kirisji"
    ],
    "name:nno_x_preferred":[
        "Kirisji"
    ],
    "name:nor_x_preferred":[
        "Kirisji"
    ],
    "name:pnb_x_preferred":[
        "\u06a9\u06cc\u0631\u06cc\u0634\u06cc"
    ],
    "name:pol_x_preferred":[
        "Kiriszy"
    ],
    "name:por_x_preferred":[
        "Kirishi"
    ],
    "name:ron_x_preferred":[
        "Kiri\u0219i"
    ],
    "name:rus_x_preferred":[
        "\u041a\u0438\u0440\u0438\u0448\u0438"
    ],
    "name:sco_x_preferred":[
        "Kirishi"
    ],
    "name:spa_x_preferred":[
        "K\u00edrishi"
    ],
    "name:srp_x_preferred":[
        "\u041a\u0438\u0440\u0438\u0448\u0438"
    ],
    "name:tat_x_preferred":[
        "\u041a\u0438\u0440\u0438\u0448\u0438"
    ],
    "name:tgl_x_preferred":[
        "Kirishi"
    ],
    "name:tur_x_preferred":[
        "Kiri\u015fi"
    ],
    "name:ukr_x_preferred":[
        "\u041a\u0456\u0440\u0456\u0448\u0438"
    ],
    "name:und_x_variant":[
        "Kireshi",
        "Kirishi",
        "\u041a\u0438\u0440\u0438\u0448\u0438"
    ],
    "name:vep_x_preferred":[
        "Kiri\u0161i"
    ],
    "name:vie_x_preferred":[
        "Kirishi"
    ],
    "name:war_x_preferred":[
        "Kirishi"
    ],
    "name:zho_x_preferred":[
        "\u57fa\u91cc\u5e0c"
    ],
    "wof:name":"Kirishi",
    "wof:placetype":"locality"
},
  "geometry": {"coordinates":[32.92262,59.96136],"type":"Point"}
}