{
  "type": "Feature",
  "properties": {
    "gn:admin1_code":"77",
    "gn:asciiname":"Bulygino",
    "gn:country_code":"RU",
    "gn:dem":224,
    "gn:feature_class":"P",
    "gn:feature_code":"PPL",
    "gn:name":"Bulygino",
    "gn:population":0,
    "gn:timezone":"Europe/Moscow",
    "iso:country":"RU",
    "name:rus_x_preferred":[
        "\u0411\u0443\u043b\u044b\u0433\u0438\u043d\u043e"
    ],
    "wof:name":"Bulygino",
    "wof:placetype":"locality"
},
  "geometry": {"coordinates":[33.12898,55.75917],"type":"Point"}
}