{
  "type": "Feature",
  "properties": {
    "gn:admin1_code":"65",
    "gn:asciiname":"Nefteprovod",
    "gn:country_code":"RU",
    "gn:dem":83,
    "gn:feature_class":"P",
    "gn:feature_code":"PPL",
    "gn:name":"Nefteprovod",
    "gn:population":0,
    "gn:timezone":"Europe/Samara",
    "iso:country":"RU",
    "name:rus_x_preferred":[
        "\u041d\u0435\u0444\u0442\u0435\u043f\u0440\u043e\u0432\u043e\u0434"
    ],
    "wof:name":"Nefteprovod",
    "wof:placetype":"locality"
},
  "geometry": {"coordinates":[48.3671,53.2091],"type":"Point"}
}