{
  "type": "Feature",
  "properties": {
    "gn:admin1_code":"54",
    "gn:asciiname":"Tyumenka",
    "gn:country_code":"RU",
    "gn:dem":114,
    "gn:feature_class":"P",
    "gn:feature_code":"PPL",
    "gn:name":"Tyumenka",
    "gn:population":0,
    "gn:timezone":"Asia/Omsk",
    "iso:country":"RU",
    "name:rus_x_preferred":[
        "\u0422\u044e\u043c\u0435\u043d\u043a\u0430"
    ],
    "name:und_x_variant":[
        "\u0422\u044e\u043c\u0435\u043d\u043a\u0430"
    ],
    "wof:name":"Tyumenka",
    "wof:placetype":"locality"
},
  "geometry": {"coordinates":[72.31708,55.26448000000001],"type":"Point"}
}