{
  "type": "Feature",
  "properties": {
    "gn:admin1_code":"10",
    "gn:asciiname":"Strigovo",
    "gn:country_code":"RU",
    "gn:dem":188,
    "gn:feature_class":"P",
    "gn:feature_code":"PPL",
    "gn:name":"Strigovo",
    "gn:population":0,
    "gn:timezone":"Europe/Moscow",
    "iso:country":"RU",
    "name:rus_x_preferred":[
        "\u0421\u0442\u0440\u0438\u0433\u043e\u0432\u043e"
    ],
    "name:und_x_variant":[
        "\u0421\u0442\u0440\u0438\u0433\u043e\u0432\u043e"
    ],
    "wof:name":"Strigovo",
    "wof:placetype":"locality"
},
  "geometry": {"coordinates":[33.19575,52.84305],"type":"Point"}
}