{
  "type": "Feature",
  "properties": {
    "gn:admin1_code":"38",
    "gn:asciiname":"Temp",
    "gn:country_code":"RU",
    "gn:dem":64,
    "gn:feature_class":"P",
    "gn:feature_code":"PPL",
    "gn:name":"Temp",
    "gn:population":0,
    "gn:timezone":"Europe/Moscow",
    "iso:country":"RU",
    "name:dan_x_preferred":[
        "Temp"
    ],
    "name:fra_x_preferred":[
        "Temp"
    ],
    "name:kaz_x_preferred":[
        "\u0422\u0435\u043c\u043f"
    ],
    "name:rus_x_preferred":[
        "\u0422\u0435\u043c\u043f"
    ],
    "name:und_x_variant":[
        "\u0422\u0435\u043c\u043f"
    ],
    "wof:name":"Temp",
    "wof:placetype":"locality"
},
  "geometry": {"coordinates":[39.8543,46.255],"type":"Point"}
}