{
  "type": "Feature",
  "properties": {
    "gn:admin1_code":"29",
    "gn:asciiname":"Pecherkino",
    "gn:country_code":"RU",
    "gn:dem":244,
    "gn:feature_class":"P",
    "gn:feature_code":"PPL",
    "gn:name":"Pecherkino",
    "gn:population":0,
    "gn:timezone":"Asia/Novokuznetsk",
    "iso:country":"RU",
    "name:rus_x_preferred":[
        "\u041f\u0435\u0447\u0435\u0440\u043a\u0438\u043d\u043e"
    ],
    "name:und_x_variant":[
        "Pecherkina"
    ],
    "wof:name":"Pecherkino",
    "wof:placetype":"locality"
},
  "geometry": {"coordinates":[85.6878,54.4175],"type":"Point"}
}