{
  "type": "Feature",
  "properties": {
    "gn:admin1_code":"60",
    "gn:asciiname":"Klishkovichi",
    "gn:country_code":"RU",
    "gn:dem":168,
    "gn:feature_class":"P",
    "gn:feature_code":"PPL",
    "gn:name":"Klishkovichi",
    "gn:population":0,
    "gn:timezone":"Europe/Moscow",
    "iso:country":"RU",
    "name:rus_x_preferred":[
        "\u041a\u043b\u0438\u0448\u043a\u043e\u0432\u0438\u0447\u0438"
    ],
    "name:und_x_variant":[
        "\u041a\u043b\u0438\u0448\u043a\u043e\u0432\u0438\u0447\u0438"
    ],
    "wof:name":"Klishkovichi",
    "wof:placetype":"locality"
},
  "geometry": {"coordinates":[29.9172,56.8071],"type":"Point"}
}