{
  "type": "Feature",
  "properties": {
    "gn:admin1_code":"80",
    "gn:asciiname":"Karkashur",
    "gn:country_code":"RU",
    "gn:dem":197,
    "gn:feature_class":"P",
    "gn:feature_code":"PPL",
    "gn:name":"Karkashur",
    "gn:population":0,
    "gn:timezone":"Europe/Samara",
    "iso:country":"RU",
    "name:rus_x_preferred":[
        "\u041a\u0430\u0440\u043a\u0430\u0448\u0443\u0440"
    ],
    "wof:name":"Karkashur",
    "wof:placetype":"locality"
},
  "geometry": {"coordinates":[52.18333,57.76667],"type":"Point"}
}