{
  "type": "Feature",
  "properties": {
    "gn:admin1_code":"32",
    "gn:asciiname":"Kinyaminy Pervyye",
    "gn:country_code":"RU",
    "gn:dem":52,
    "gn:feature_class":"P",
    "gn:feature_code":"PPL",
    "gn:name":"Kinyaminy Pervyye",
    "gn:population":0,
    "gn:timezone":"Asia/Yekaterinburg",
    "iso:country":"RU",
    "name:rus_x_preferred":[
        "\u041a\u0438\u043d\u044f\u043c\u0438\u043d\u044b \u041f\u0435\u0440\u0432\u044b\u0435"
    ],
    "wof:name":"Kinyaminy Pervyye",
    "wof:placetype":"locality"
},
  "geometry": {"coordinates":[74.43694000000001,60.48278000000001],"type":"Point"}
}