{
  "type": "Feature",
  "properties": {
    "gn:admin1_code":"33",
    "gn:asciiname":"Vedernikovo",
    "gn:country_code":"RU",
    "gn:dem":91,
    "gn:feature_class":"P",
    "gn:feature_code":"PPL",
    "gn:name":"Vedernikovo",
    "gn:population":0,
    "gn:timezone":"Europe/Kirov",
    "iso:country":"RU",
    "name:rus_x_preferred":[
        "\u0412\u0435\u0434\u0435\u0440\u043d\u0438\u043a\u043e\u0432\u043e"
    ],
    "wof:name":"Vedernikovo",
    "wof:placetype":"locality"
},
  "geometry": {"coordinates":[47.1574,56.97865],"type":"Point"}
}