{
  "type": "Feature",
  "properties": {
    "gn:admin1_code":"54",
    "gn:asciiname":"Babezh",
    "gn:country_code":"RU",
    "gn:dem":121,
    "gn:feature_class":"P",
    "gn:feature_code":"PPL",
    "gn:name":"Babezh",
    "gn:population":0,
    "gn:timezone":"Asia/Omsk",
    "iso:country":"RU",
    "name:eng_x_preferred":[
        "Babezh"
    ],
    "name:nor_x_preferred":[
        "Babezj"
    ],
    "name:rus_x_preferred":[
        "\u0411\u0430\u0431\u0435\u0436"
    ],
    "wof:name":"Babezh",
    "wof:placetype":"locality"
},
  "geometry": {"coordinates":[72.20756999999998,54.6344],"type":"Point"}
}