{
  "type": "Feature",
  "properties": {
    "gn:admin1_code":"34",
    "gn:asciiname":"Shezhem",
    "gn:country_code":"RU",
    "gn:dem":138,
    "gn:feature_class":"P",
    "gn:feature_code":"PPL",
    "gn:name":"Shezh\u00ebm",
    "gn:population":0,
    "gn:timezone":"Europe/Moscow",
    "iso:country":"RU",
    "name:eng_x_preferred":[
        "Shezh\u00ebm"
    ],
    "name:nor_x_preferred":[
        "Sjezjam"
    ],
    "name:rus_x_preferred":[
        "\u0428\u0435\u0436\u0430\u043c"
    ],
    "name:rus_x_variant":[
        "\u0428\u0435\u0436\u0451\u043c"
    ],
    "name:und_x_variant":[
        "Shezham"
    ],
    "wof:name":"Shezhem",
    "wof:placetype":"locality"
},
  "geometry": {"coordinates":[49.96055,62.29784],"type":"Point"}
}