{
  "type": "Feature",
  "properties": {
    "gn:admin1_code":"49",
    "gn:asciiname":"Tuloma",
    "gn:country_code":"RU",
    "gn:dem":27,
    "gn:feature_class":"P",
    "gn:feature_code":"PPL",
    "gn:name":"Tuloma",
    "gn:population":0,
    "gn:timezone":"Europe/Moscow",
    "iso:country":"RU",
    "name:ara_x_preferred":[
        "\u062a\u0648\u0644\u0648\u0645\u0627"
    ],
    "name:ben_x_preferred":[
        "\u099f\u09c1\u09b2\u09cb\u09ae\u09be"
    ],
    "name:ell_x_preferred":[
        "\u03a4\u03bf\u03c5\u03bb\u03cc\u03bc\u03b1"
    ],
    "name:eng_x_preferred":[
        "Tuloma"
    ],
    "name:fas_x_preferred":[
        "\u062a\u0648\u0644\u0648\u0645\u0627"
    ],
    "name:heb_x_preferred":[
        "\u05d8\u05d5\u05dc\u05d5\u05de\u05d4"
    ],
    "name:hin_x_preferred":[
        "\u0924\u0941\u0932\u094b\u092e\u093e"
    ],
    "name:hun_x_preferred":[
        "Tuloma"
    ],
    "name:ind_x_preferred":[
        "Tuloma"
    ],
    "name:kor_x_preferred":[
        "\ud234\ub85c\ub9c8"
    ],
    "name:nor_x_preferred":[
        "Tuloma"
    ],
    "name:por_x_preferred":[
        "Tuloma"
    ],
    "name:rus_x_preferred":[
        "\u0422\u0443\u043b\u043e\u043c\u0430"
    ],
    "name:swe_x_preferred":[
        "Tuloma"
    ],
    "name:ukr_x_preferred":[
        "\u0422\u0443\u043b\u043e\u043c\u0430"
    ],
    "name:urd_x_preferred":[
        "\u0679\u0648\u0644\u0648\u0645\u0627"
    ],
    "name:vie_x_preferred":[
        "S\u00f4ng Tuloma"
    ],
    "wof:name":"Tuloma",
    "wof:placetype":"locality"
},
  "geometry": {"coordinates":[32.68724,68.81644],"type":"Point"}
}