{
  "type": "Feature",
  "properties": {
    "gn:admin1_code":"69",
    "gn:asciiname":"Fedorovo",
    "gn:country_code":"RU",
    "gn:dem":183,
    "gn:feature_class":"P",
    "gn:feature_code":"PPL",
    "gn:name":"F\u00ebdorovo",
    "gn:population":0,
    "gn:timezone":"Europe/Moscow",
    "iso:country":"RU",
    "name:rus_x_preferred":[
        "\u0424\u0451\u0434\u043e\u0440\u043e\u0432\u043e"
    ],
    "name:und_x_variant":[
        "F\u00ebdorovo"
    ],
    "wof:name":"Fedorovo",
    "wof:placetype":"locality"
},
  "geometry": {"coordinates":[32.18824,54.30011],"type":"Point"}
}