{
  "type": "Feature",
  "properties": {
    "gn:admin1_code":"69",
    "gn:asciiname":"Cherneyka",
    "gn:country_code":"RU",
    "gn:dem":191,
    "gn:feature_class":"P",
    "gn:feature_code":"PPL",
    "gn:name":"Cherneyka",
    "gn:population":0,
    "gn:timezone":"Europe/Moscow",
    "iso:country":"RU",
    "name:rus_x_preferred":[
        "\u0427\u0435\u0440\u043d\u0435\u0439\u043a\u0430"
    ],
    "name:und_x_variant":[
        "\u0427\u0435\u0440\u043d\u0435\u0439\u043a\u0430"
    ],
    "wof:name":"Cherneyka",
    "wof:placetype":"locality"
},
  "geometry": {"coordinates":[34.343,55.72709],"type":"Point"}
}