{
  "type": "Feature",
  "properties": {
    "gn:admin1_code":"86",
    "gn:asciiname":"Sal'nyy",
    "gn:country_code":"RU",
    "gn:dem":142,
    "gn:feature_class":"P",
    "gn:feature_code":"PPL",
    "gn:name":"Sal\u2019nyy",
    "gn:population":0,
    "gn:timezone":"Europe/Moscow",
    "iso:country":"RU",
    "name:rus_x_preferred":[
        "\u0421\u0430\u043b\u044c\u043d\u044b\u0439"
    ],
    "name:und_x_variant":[
        "Sal\u2019ny",
        "Pos\u00eblok Sal\u2019nyy",
        "Sal\u2019nny",
        "Sal\u2019nyy",
        "\u0421\u0430\u043b\u044c\u043d\u044b\u0439"
    ],
    "wof:name":"Sal'nyy",
    "wof:placetype":"locality"
},
  "geometry": {"coordinates":[39.77056,51.30111],"type":"Point"}
}