{
  "type": "Feature",
  "properties": {
    "gn:admin1_code":"52",
    "gn:asciiname":"Krupino",
    "gn:country_code":"RU",
    "gn:dem":182,
    "gn:feature_class":"P",
    "gn:feature_code":"PPL",
    "gn:name":"Krupino",
    "gn:population":0,
    "gn:timezone":"Europe/Moscow",
    "iso:country":"RU",
    "name:eng_x_preferred":[
        "Krupino"
    ],
    "name:nor_x_preferred":[
        "Krupino"
    ],
    "name:rus_x_preferred":[
        "\u041a\u0440\u0443\u043f\u0438\u043d\u043e"
    ],
    "name:und_x_variant":[
        "\u041a\u0440\u0443\u043f\u0438\u043d\u043e",
        "Krupino"
    ],
    "wof:name":"Krupino",
    "wof:placetype":"locality"
},
  "geometry": {"coordinates":[34.8321,58.533],"type":"Point"}
}