{
  "type": "Feature",
  "properties": {
    "gn:admin1_code":"69.0",
    "gn:asciiname":"Gluzdy",
    "gn:country_code":"RU",
    "gn:dem":162,
    "gn:feature_class":"P",
    "gn:feature_code":"PPL",
    "gn:name":"Gluzdy",
    "gn:population":0,
    "gn:timezone":"Europe/Moscow",
    "iso:country":"RU",
    "name:rus_x_preferred":[
        "\u0413\u043b\u0443\u0437\u0434\u044b"
    ],
    "wof:name":"Gluzdy",
    "wof:placetype":"locality"
},
  "geometry": {"coordinates":[31.58689,55.73333],"type":"Point"}
}