{
  "type": "Feature",
  "properties": {
    "gn:admin1_code":"52",
    "gn:asciiname":"Smolevo",
    "gn:country_code":"RU",
    "gn:dem":178,
    "gn:feature_class":"P",
    "gn:feature_code":"PPL",
    "gn:name":"Smolevo",
    "gn:population":0,
    "gn:timezone":"Europe/Moscow",
    "iso:country":"RU",
    "name:bul_x_preferred":[
        "\u0421\u043c\u043e\u043b\u0435\u0432\u043e"
    ],
    "name:ceb_x_preferred":[
        "Smolevo"
    ],
    "name:fas_x_preferred":[
        "\u0633\u0645\u0648\u0644\u0648\u0648"
    ],
    "name:kaz_x_preferred":[
        "\u0421\u043c\u043e\u043b\u0435\u0432\u043e"
    ],
    "name:mkd_x_preferred":[
        "\u0418\u043b\u0430\u043d\u0441\u043a\u043e"
    ],
    "name:ron_x_preferred":[
        "Smolevo"
    ],
    "name:rus_x_preferred":[
        "\u0421\u043c\u043e\u043b\u0435\u0432\u043e"
    ],
    "name:swe_x_preferred":[
        "Smolevo"
    ],
    "name:ukr_x_preferred":[
        "\u0421\u043c\u043e\u043b\u0435\u0432\u043e"
    ],
    "wof:name":"Smolevo",
    "wof:placetype":"locality"
},
  "geometry": {"coordinates":[33.40525,58.93286],"type":"Point"}
}