{
  "type": "Feature",
  "properties": {
    "gn:admin1_code":"88",
    "gn:asciiname":"Bud'kovo",
    "gn:country_code":"RU",
    "gn:dem":191,
    "gn:feature_class":"P",
    "gn:feature_code":"PPL",
    "gn:name":"Bud\u2019kovo",
    "gn:population":0,
    "gn:timezone":"Europe/Moscow",
    "iso:country":"RU",
    "name:rus_x_preferred":[
        "\u0411\u0443\u0434\u044c\u043a\u043e\u0432\u043e"
    ],
    "name:und_x_variant":[
        "Bud\u2019kovo",
        "\u0411\u0443\u0434\u044c\u043a\u043e\u0432\u043e"
    ],
    "wof:name":"Bud'kovo",
    "wof:placetype":"locality"
},
  "geometry": {"coordinates":[38.4099,57.1929],"type":"Point"}
}