{
  "type": "Feature",
  "properties": {
    "gn:admin1_code":"76",
    "gn:asciiname":"Maloye Kolodeznoye",
    "gn:country_code":"RU",
    "gn:dem":201,
    "gn:feature_class":"P",
    "gn:feature_code":"PPL",
    "gn:name":"Maloye Kolodeznoye",
    "gn:population":0,
    "gn:timezone":"Europe/Moscow",
    "iso:country":"RU",
    "name:rus_x_preferred":[
        "\u041c\u0430\u043b\u043e\u0435 \u041a\u043e\u043b\u043e\u0434\u0435\u0437\u043d\u043e\u0435"
    ],
    "name:und_x_variant":[
        "Malaya Kolodeznaya",
        "Maloye Kolodeznoye"
    ],
    "wof:name":"Maloye Kolodeznoye",
    "wof:placetype":"locality"
},
  "geometry": {"coordinates":[38.32579000000001,54.03716],"type":"Point"}
}