{
  "type": "Feature",
  "properties": {
    "gn:admin1_code":"60",
    "gn:asciiname":"Novoye Kratkovo",
    "gn:country_code":"RU",
    "gn:dem":75,
    "gn:feature_class":"P",
    "gn:feature_code":"PPL",
    "gn:name":"Novoye Kratkovo",
    "gn:population":0,
    "gn:timezone":"Europe/Moscow",
    "iso:country":"RU",
    "name:rus_x_preferred":[
        "\u041d\u043e\u0432\u043e\u0435 \u041a\u0440\u0430\u0442\u043a\u043e\u0432\u043e"
    ],
    "name:und_x_variant":[
        "\u041d\u043e\u0432\u043e\u0435 \u041a\u0440\u0430\u0442\u043a\u043e\u0432\u043e"
    ],
    "wof:name":"Novoye Kratkovo",
    "wof:placetype":"locality"
},
  "geometry": {"coordinates":[28.4207,58.0318],"type":"Point"}
}