{
  "type": "Feature",
  "properties": {
    "gn:admin1_code":"81.0",
    "gn:asciiname":"Bol'shaya Karamzinka",
    "gn:country_code":"RU",
    "gn:dem":131,
    "gn:feature_class":"P",
    "gn:feature_code":"PPL",
    "gn:name":"Bol\u2019shaya Karamzinka",
    "gn:population":0,
    "gn:timezone":"Europe/Ulyanovsk",
    "iso:country":"RU",
    "name:nor_x_preferred":[
        "Bolsjaja Karamzinka"
    ],
    "name:rus_x_preferred":[
        "\u0411\u043e\u043b\u044c\u0448\u0430\u044f \u041a\u0430\u0440\u0430\u043c\u0437\u0438\u043d\u043a\u0430"
    ],
    "name:und_x_variant":[
        "Bol\u2019shaya Karamzinka"
    ],
    "wof:name":"Bol'shaya Karamzinka",
    "wof:placetype":"locality"
},
  "geometry": {"coordinates":[47.98889000000001,54.05722],"type":"Point"}
}