{
  "type": "Feature",
  "properties": {
    "gn:admin1_code":"34",
    "gn:asciiname":"Zuleb",
    "gn:country_code":"RU",
    "gn:dem":92,
    "gn:feature_class":"P",
    "gn:feature_code":"PPL",
    "gn:name":"Zuleb",
    "gn:population":0,
    "gn:timezone":"Europe/Moscow",
    "iso:country":"RU",
    "name:eng_x_preferred":[
        "Zuleb"
    ],
    "name:nor_x_preferred":[
        "Zilob"
    ],
    "name:rus_x_preferred":[
        "\u0417\u0438\u043b\u043e\u0431"
    ],
    "name:und_x_variant":[
        "Zulobdin",
        "Zulob",
        "Zuleb-Din",
        "Zulobdinskaya",
        "Zuleb"
    ],
    "wof:name":"Zuleb",
    "wof:placetype":"locality"
},
  "geometry": {"coordinates":[52.46296,62.18965],"type":"Point"}
}