{
  "type": "Feature",
  "properties": {
    "gn:admin1_code":"33.0",
    "gn:asciiname":"Igoshata",
    "gn:country_code":"RU",
    "gn:dem":144,
    "gn:feature_class":"P",
    "gn:feature_code":"PPL",
    "gn:name":"Igoshata",
    "gn:population":0,
    "gn:timezone":"Europe/Kirov",
    "iso:country":"RU",
    "name:rus_x_preferred":[
        "\u0418\u0433\u043e\u0448\u0430\u0442\u0430"
    ],
    "wof:name":"Igoshata",
    "wof:placetype":"locality"
},
  "geometry": {"coordinates":[48.30186,58.57881],"type":"Point"}
}