{
  "type": "Feature",
  "properties": {
    "gn:admin1_code":"83.0",
    "gn:asciiname":"Abbakumovo",
    "gn:country_code":"RU",
    "gn:dem":116,
    "gn:feature_class":"P",
    "gn:feature_code":"PPL",
    "gn:name":"Abbakumovo",
    "gn:population":0,
    "gn:timezone":"Europe/Moscow",
    "iso:country":"RU",
    "name:nor_x_preferred":[
        "Abbakumovo"
    ],
    "name:rus_x_preferred":[
        "\u0410\u0431\u0431\u0430\u043a\u0443\u043c\u043e\u0432\u043e"
    ],
    "wof:name":"Abbakumovo",
    "wof:placetype":"locality"
},
  "geometry": {"coordinates":[39.69274,55.92316999999999],"type":"Point"}
}