{
  "type": "Feature",
  "properties": {
    "gn:admin1_code":"10",
    "gn:asciiname":"Purvinka",
    "gn:country_code":"RU",
    "gn:dem":184,
    "gn:feature_class":"P",
    "gn:feature_code":"PPL",
    "gn:name":"Purvinka",
    "gn:population":0,
    "gn:timezone":"Europe/Moscow",
    "iso:country":"RU",
    "name:rus_x_preferred":[
        "\u041f\u0443\u0440\u0432\u0438\u043d\u043a\u0430"
    ],
    "name:und_x_variant":[
        "Purvinko",
        "Purvinka"
    ],
    "wof:name":"Purvinka",
    "wof:placetype":"locality"
},
  "geometry": {"coordinates":[34.44512,52.90595],"type":"Point"}
}