{
  "type": "Feature",
  "properties": {
    "gn:admin1_code":"67.0",
    "gn:asciiname":"Bol'shaya Gusikha",
    "gn:country_code":"RU",
    "gn:dem":207,
    "gn:feature_class":"P",
    "gn:feature_code":"PPL",
    "gn:name":"Bol\u2019shaya Gusikha",
    "gn:population":0,
    "gn:timezone":"Europe/Saratov",
    "iso:country":"RU",
    "name:rus_x_preferred":[
        "\u0411\u043e\u043b\u044c\u0448\u0430\u044f \u0413\u0443\u0441\u0438\u0445\u0430"
    ],
    "name:und_x_variant":[
        "Bol\u2019shaya Gusikha"
    ],
    "wof:name":"Bol'shaya Gusikha",
    "wof:placetype":"locality"
},
  "geometry": {"coordinates":[46.29217,52.50951],"type":"Point"}
}