{
  "type": "Feature",
  "properties": {
    "gn:admin1_code":"77",
    "gn:asciiname":"Khmytyti",
    "gn:country_code":"RU",
    "gn:dem":240,
    "gn:feature_class":"P",
    "gn:feature_code":"PPL",
    "gn:name":"Khmytyti",
    "gn:population":0,
    "gn:timezone":"Europe/Moscow",
    "iso:country":"RU",
    "name:rus_x_preferred":[
        "\u0425\u043c\u044b\u0442\u044b\u0442\u0438"
    ],
    "wof:name":"Khmytyti",
    "wof:placetype":"locality"
},
  "geometry": {"coordinates":[33.3675,56.11278000000001],"type":"Point"}
}