{
  "type": "Feature",
  "properties": {
    "gn:admin1_code":"43",
    "gn:asciiname":"Kolyayevka",
    "gn:country_code":"RU",
    "gn:dem":239,
    "gn:feature_class":"P",
    "gn:feature_code":"PPL",
    "gn:name":"Kolyayevka",
    "gn:population":0,
    "gn:timezone":"Europe/Moscow",
    "iso:country":"RU",
    "name:rus_x_preferred":[
        "\u041a\u043e\u043b\u044f\u0435\u0432\u043a\u0430"
    ],
    "name:und_x_variant":[
        "\u041a\u043e\u043b\u044f\u0435\u0432\u043a\u0430"
    ],
    "wof:name":"Kolyayevka",
    "wof:placetype":"locality"
},
  "geometry": {"coordinates":[38.2578,52.9354],"type":"Point"}
}