{
  "type": "Feature",
  "properties": {
    "gn:admin1_code":"90",
    "gn:asciiname":"Vilizhnaya",
    "gn:country_code":"RU",
    "gn:dem":139,
    "gn:feature_class":"P",
    "gn:feature_code":"PPL",
    "gn:name":"Vilizhnaya",
    "gn:population":0,
    "gn:timezone":"Asia/Yekaterinburg",
    "iso:country":"RU",
    "name:rus_x_preferred":[
        "\u0412\u0438\u043b\u0438\u0436\u043d\u0430\u044f"
    ],
    "name:und_x_variant":[
        "Velizhna",
        "Vilizhna",
        "Vilizhnaya"
    ],
    "wof:name":"Vilizhnaya",
    "wof:placetype":"locality"
},
  "geometry": {"coordinates":[57.0487,58.1975],"type":"Point"}
}