{
  "type": "Feature",
  "properties": {
    "gn:admin1_code":"52",
    "gn:asciiname":"Gorneshno",
    "gn:country_code":"RU",
    "gn:dem":175,
    "gn:feature_class":"P",
    "gn:feature_code":"PPL",
    "gn:name":"Gorneshno",
    "gn:population":0,
    "gn:timezone":"Europe/Moscow",
    "iso:country":"RU",
    "name:eng_x_preferred":[
        "Gorneshno"
    ],
    "name:nor_x_preferred":[
        "Gornesjno"
    ],
    "name:rus_x_preferred":[
        "\u0413\u043e\u0440\u043d\u0435\u0448\u043d\u043e"
    ],
    "name:und_x_variant":[
        "Gorneshnoye"
    ],
    "wof:name":"Gorneshno",
    "wof:placetype":"locality"
},
  "geometry": {"coordinates":[33.23798,58.27506999999999],"type":"Point"}
}