{
  "type": "Feature",
  "properties": {
    "gn:admin1_code":"56",
    "gn:asciiname":"Mokhovoye",
    "gn:country_code":"RU",
    "gn:dem":188,
    "gn:feature_class":"P",
    "gn:feature_code":"PPL",
    "gn:name":"Mokhovoye",
    "gn:population":0,
    "gn:timezone":"Europe/Moscow",
    "iso:country":"RU",
    "name:eng_x_preferred":[
        "Mokhovoye"
    ],
    "name:nor_x_preferred":[
        "Mokhovoje"
    ],
    "name:rus_x_preferred":[
        "\u041c\u043e\u0445\u043e\u0432\u043e\u0435"
    ],
    "name:und_x_variant":[
        "\u041c\u043e\u0445\u043e\u0432\u043e\u0435",
        "Mokhovoye"
    ],
    "wof:name":"Mokhovoye",
    "wof:placetype":"locality"
},
  "geometry": {"coordinates":[35.8475,52.538],"type":"Point"}
}