{
  "type": "Feature",
  "properties": {
    "gn:admin1_code":"30",
    "gn:asciiname":"Nepomnyashchego",
    "gn:cc2":"RU",
    "gn:country_code":"RU",
    "gn:dem":284,
    "gn:feature_class":"P",
    "gn:feature_code":"PPL",
    "gn:name":"Nepomnyashchego",
    "gn:population":0,
    "gn:timezone":"Asia/Vladivostok",
    "iso:country":"RU",
    "name:rus_x_preferred":[
        "\u041d\u0435\u043f\u043e\u043c\u043d\u044f\u0449\u0435\u0433\u043e"
    ],
    "name:und_x_variant":[
        "Yudomskoye",
        "Nepomnyashchego"
    ],
    "wof:name":"Nepomnyashchego",
    "wof:placetype":"locality"
},
  "geometry": {"coordinates":[135.33333000000002,59.16667],"type":"Point"}
}