{
  "type": "Feature",
  "properties": {
    "gn:admin1_code":"71",
    "gn:asciiname":"Zvezda",
    "gn:country_code":"RU",
    "gn:dem":76,
    "gn:feature_class":"P",
    "gn:feature_code":"PPL",
    "gn:name":"Zvezda",
    "gn:population":0,
    "gn:timezone":"Asia/Yekaterinburg",
    "iso:country":"RU",
    "name:bak_x_preferred":[
        "\u0419\u043e\u043d\u0434\u043e\u0499"
    ],
    "name:bul_x_preferred":[
        "\u0417\u0432\u0435\u0437\u0434\u0430"
    ],
    "name:ceb_x_preferred":[
        "Zvezda"
    ],
    "name:eng_x_preferred":[
        "Zvezda"
    ],
    "name:est_x_preferred":[
        "Zvezda"
    ],
    "name:fin_x_preferred":[
        "Zvezda"
    ],
    "name:fra_x_preferred":[
        "Zvezda"
    ],
    "name:hye_x_preferred":[
        "\u0536\u057e\u0565\u0566\u0564\u0561"
    ],
    "name:ita_x_preferred":[
        "Zvezda"
    ],
    "name:jpn_x_preferred":[
        "\u30ba\u30f4\u30a7\u30ba\u30c0"
    ],
    "name:kor_x_preferred":[
        "\uc988\ubca0\uc988\ub2e4"
    ],
    "name:lez_x_preferred":[
        "\u0413\u044a\u0435\u0434"
    ],
    "name:lit_x_preferred":[
        "\u017dvaig\u017ed\u0117"
    ],
    "name:nld_x_preferred":[
        "Zvezda"
    ],
    "name:nor_x_preferred":[
        "Zvezda"
    ],
    "name:rus_x_preferred":[
        "\u0417\u0432\u0435\u0437\u0434\u0430"
    ],
    "name:slk_x_preferred":[
        "Hviezda"
    ],
    "name:slv_x_preferred":[
        "Zvezda"
    ],
    "name:spa_x_preferred":[
        "Zvezd\u00e1"
    ],
    "name:srp_x_preferred":[
        "\u0417\u0432\u0435\u0437\u0434\u0430"
    ],
    "name:swe_x_preferred":[
        "Zvezda"
    ],
    "name:ukr_x_preferred":[
        "\u0417\u0432\u0454\u0437\u0434\u0430"
    ],
    "wof:name":"Zvezda",
    "wof:placetype":"locality"
},
  "geometry": {"coordinates":[64.16446999999999,57.62386],"type":"Point"}
}