{
  "type": "Feature",
  "properties": {
    "gn:admin1_code":"33",
    "gn:asciiname":"Staraya Yur'ya",
    "gn:country_code":"RU",
    "gn:dem":121,
    "gn:feature_class":"P",
    "gn:feature_code":"PPL",
    "gn:name":"Staraya Yur\u2019ya",
    "gn:population":0,
    "gn:timezone":"Europe/Kirov",
    "iso:country":"RU",
    "name:rus_x_preferred":[
        "\u0421\u0442\u0430\u0440\u0430\u044f \u042e\u0440\u044c\u044f"
    ],
    "name:und_x_variant":[
        "Staraya Yur\u2019ya",
        "\u0421\u0442\u0430\u0440\u0430\u044f \u042e\u0440\u044c\u044f"
    ],
    "wof:name":"Staraya Yur'ya",
    "wof:placetype":"locality"
},
  "geometry": {"coordinates":[49.26667,59.05],"type":"Point"}
}