{
  "type": "Feature",
  "properties": {
    "gn:admin1_code":"80.0",
    "gn:asciiname":"Bol'shoy Apevay",
    "gn:country_code":"RU",
    "gn:dem":210,
    "gn:feature_class":"P",
    "gn:feature_code":"PPL",
    "gn:name":"Bol\u2019shoy Apevay",
    "gn:population":0,
    "gn:timezone":"Europe/Samara",
    "iso:country":"RU",
    "name:rus_x_preferred":[
        "\u0411\u043e\u043b\u044c\u0448\u043e\u0439 \u0410\u043f\u0435\u0432\u0430\u0439"
    ],
    "name:und_x_variant":[
        "Bol\u2019shoy Apevay"
    ],
    "wof:name":"Bol'shoy Apevay",
    "wof:placetype":"locality"
},
  "geometry": {"coordinates":[51.98849000000001,58.40097],"type":"Point"}
}