{
  "type": "Feature",
  "properties": {
    "gn:admin1_code":"85",
    "gn:asciiname":"Titovshchina",
    "gn:country_code":"RU",
    "gn:dem":110,
    "gn:feature_class":"P",
    "gn:feature_code":"PPL",
    "gn:name":"Titovshchina",
    "gn:population":0,
    "gn:timezone":"Europe/Moscow",
    "iso:country":"RU",
    "name:rus_x_preferred":[
        "\u0422\u0438\u0442\u043e\u0432\u0449\u0438\u043d\u0430"
    ],
    "name:und_x_variant":[
        "\u0422\u0438\u0442\u043e\u0432\u0449\u0438\u043d\u0430"
    ],
    "wof:name":"Titovshchina",
    "wof:placetype":"locality"
},
  "geometry": {"coordinates":[46.653,59.9626],"type":"Point"}
}