{
  "type": "Feature",
  "properties": {
    "gn:admin1_code":"25",
    "gn:asciiname":"Khmylovka",
    "gn:country_code":"RU",
    "gn:dem":188,
    "gn:feature_class":"P",
    "gn:feature_code":"PPL",
    "gn:name":"Khmylovka",
    "gn:population":0,
    "gn:timezone":"Europe/Moscow",
    "iso:country":"RU",
    "name:rus_x_preferred":[
        "\u0425\u043c\u0435\u043b\u0435\u0432\u043a\u0430"
    ],
    "name:und_x_variant":[
        "Khmel\u00ebvka"
    ],
    "wof:name":"Khmylovka",
    "wof:placetype":"locality"
},
  "geometry": {"coordinates":[35.29694,54.87639],"type":"Point"}
}