{
  "type": "Feature",
  "properties": {
    "gn:admin1_code":"84.0",
    "gn:asciiname":"Dundukov",
    "gn:country_code":"RU",
    "gn:dem":114,
    "gn:feature_class":"P",
    "gn:feature_code":"PPL",
    "gn:name":"Dundukov",
    "gn:population":0,
    "gn:timezone":"Europe/Volgograd",
    "iso:country":"RU",
    "name:rus_x_preferred":[
        "\u0414\u0443\u043d\u0434\u0443\u043a\u043e\u0432"
    ],
    "wof:name":"Dundukov",
    "wof:placetype":"locality"
},
  "geometry": {"coordinates":[44.16667,50.16667],"type":"Point"}
}