{
  "type": "Feature",
  "properties": {
    "gn:admin1_code":"81",
    "gn:asciiname":"Krasnyye Gory",
    "gn:country_code":"RU",
    "gn:dem":159,
    "gn:feature_class":"P",
    "gn:feature_code":"PPL",
    "gn:name":"Krasnyye Gory",
    "gn:population":0,
    "gn:timezone":"Europe/Ulyanovsk",
    "iso:country":"RU",
    "name:rus_x_preferred":[
        "\u041a\u0440\u0430\u0441\u043d\u044b\u0435 \u0413\u043e\u0440\u044b"
    ],
    "name:und_x_variant":[
        "Kobelevka",
        "Krasnyye Gory"
    ],
    "wof:name":"Krasnyye Gory",
    "wof:placetype":"locality"
},
  "geometry": {"coordinates":[46.98287,54.47166],"type":"Point"}
}