{
  "type": "Feature",
  "properties": {
    "gn:admin1_code":"52.0",
    "gn:asciiname":"Bereznyak Pervyy",
    "gn:country_code":"RU",
    "gn:dem":200,
    "gn:feature_class":"P",
    "gn:feature_code":"PPL",
    "gn:name":"Bereznyak Pervyy",
    "gn:population":0,
    "gn:timezone":"Europe/Moscow",
    "iso:country":"RU",
    "name:nor_x_preferred":[
        "Bereznjak Pervyj"
    ],
    "name:rus_x_preferred":[
        "\u0411\u0435\u0440\u0435\u0437\u043d\u044f\u043a \u041f\u0435\u0440\u0432\u044b\u0439"
    ],
    "wof:name":"Bereznyak Pervyy",
    "wof:placetype":"locality"
},
  "geometry": {"coordinates":[33.44253,58.88596],"type":"Point"}
}