{
  "type": "Feature",
  "properties": {
    "gn:country":"RU",
    "gn:fcode":"PPL",
    "gn:pop":93834,
    "iso:country":"RU",
    "name:ara_x_preferred":[
        "\u062c\u064a\u0644\u064a\u0632\u0646\u0648\u063a\u0648\u0631\u0633\u0643\u060c \u0643\u0631\u0627\u0633\u0646\u0648\u064a\u0627\u0631\u0633\u0643 \u0643\u0631\u0627\u064a"
    ],
    "name:azb_x_preferred":[
        "\u0698\u0627\u0644\u0632\u0646\u0648\u0642\u0648\u0631\u0633\u06a9"
    ],
    "name:bel_x_preferred":[
        "\u0416\u0430\u043b\u0435\u0437\u043d\u0430\u0433\u043e\u0440\u0441\u043a"
    ],
    "name:bos_x_preferred":[
        "\u017deleznogorsk"
    ],
    "name:bul_x_preferred":[
        "\u0416\u0435\u043b\u0435\u0437\u043d\u043e\u0433\u043e\u0440\u0441\u043a"
    ],
    "name:cat_x_preferred":[
        "Jeleznogorsk"
    ],
    "name:ces_x_preferred":[
        "\u017deleznogorsk"
    ],
    "name:deu_x_preferred":[
        "Schelesnogorsk"
    ],
    "name:eng_x_preferred":[
        "Zheleznogorsk"
    ],
    "name:epo_x_preferred":[
        "\u0134eleznogorsk"
    ],
    "name:est_x_preferred":[
        "\u017deleznogorsk"
    ],
    "name:fas_x_preferred":[
        "\u0698\u0644\u0632\u0646\u0648\u06af\u0648\u0631\u0633\u06a9\u060c \u06a9\u0631\u0627\u0633\u0646\u0648\u06cc\u0627\u0631\u0633\u06a9"
    ],
    "name:fin_x_preferred":[
        "\u017deleznogorsk"
    ],
    "name:fra_x_preferred":[
        "Jeleznogorsk"
    ],
    "name:hrv_x_preferred":[
        "\u017deleznogorsk"
    ],
    "name:hsb_x_preferred":[
        "\u017deleznogorsk"
    ],
    "name:hun_x_preferred":[
        "Zseleznogorszk"
    ],
    "name:ita_x_preferred":[
        "\u017deleznogorsk"
    ],
    "name:jpn_x_preferred":[
        "\u30b8\u30a7\u30ec\u30ba\u30ce\u30b4\u30eb\u30b9\u30af"
    ],
    "name:kor_x_preferred":[
        "\uc824\ub808\uc988\ub178\uace0\ub974\uc2a4\ud06c"
    ],
    "name:nld_x_preferred":[
        "Zjeleznogorsk"
    ],
    "name:nno_x_preferred":[
        "Zjeleznogorsk"
    ],
    "name:nob_x_preferred":[
        "Zjeleznogorsk"
    ],
    "name:nor_x_preferred":[
        "Zjeleznogorsk"
    ],
    "name:pnb_x_preferred":[
        "\u0698\u0644\u06cc\u0632\u0646\u0648\u06af\u0648\u0631\u0633\u06a9"
    ],
    "name:pol_x_preferred":[
        "\u017beleznogorsk"
    ],
    "name:rus_x_preferred":[
        "\u0416\u0435\u043b\u0435\u0437\u043d\u043e\u0433\u043e\u0440\u0441\u043a"
    ],
    "name:spa_x_preferred":[
        "Zheleznogorsk"
    ],
    "name:srp_x_preferred":[
        "\u0416\u0435\u0459\u0435\u0437\u043d\u043e\u0433\u043e\u0440\u0441\u043a"
    ],
    "name:swe_x_preferred":[
        "Zjeleznogorsk"
    ],
    "name:tat_x_preferred":[
        "\u0416\u0435\u043b\u0435\u0437\u043d\u043e\u0433\u043e\u0440\u0441\u043a"
    ],
    "name:tgl_x_preferred":[
        "Zheleznogorsk"
    ],
    "name:ukr_x_preferred":[
        "\u0416\u0435\u043b\u0454\u0437\u043d\u043e\u0433\u043e\u0440\u0441\u044c\u043a"
    ],
    "name:unk_x_variant":[
        "Atomgrad"
    ],
    "name:vep_x_preferred":[
        "\u017deleznogorsk"
    ],
    "name:vie_x_preferred":[
        "Zheleznogorsk"
    ],
    "name:war_x_preferred":[
        "Zheleznogorsk"
    ],
    "name:zho_x_preferred":[
        "\u70ed\u5217\u5179\u8bfa\u54e5\u5c14\u65af\u514b"
    ],
    "qs:name":"Zheleznogorsk",
    "qs:photos_9r":0,
    "qs:photos_sr":0,
    "qs:pop_sr":"8",
    "wd:wordcount":84,
    "wof:name":"Zheleznogorsk",
    "wof:placetype":"locality",
    "wof:population":93834
},
  "geometry": {"coordinates":[93.53194000000001,56.25111],"type":"Point"}
}