{
  "type": "Feature",
  "properties": {
    "gn:admin1_code":"71",
    "gn:asciiname":"Karelino",
    "gn:country_code":"RU",
    "gn:dem":165,
    "gn:feature_class":"P",
    "gn:feature_code":"PPL",
    "gn:name":"Karelino",
    "gn:population":0,
    "gn:timezone":"Asia/Yekaterinburg",
    "iso:country":"RU",
    "name:eng_x_preferred":[
        "Karelino"
    ],
    "name:nor_x_preferred":[
        "Karelino"
    ],
    "name:rus_x_preferred":[
        "\u041a\u0430\u0440\u0435\u043b\u0438\u043d\u043e"
    ],
    "name:und_x_variant":[
        "Korelino",
        "\u041a\u0430\u0440\u0435\u043b\u0438\u043d\u043e",
        "Karelino"
    ],
    "wof:name":"Karelino",
    "wof:placetype":"locality"
},
  "geometry": {"coordinates":[60.39848000000001,58.70648000000001],"type":"Point"}
}