{
  "type": "Feature",
  "properties": {
    "gn:country":"RU",
    "gn:fcode":"PPL",
    "gn:pop":4606,
    "iso:country":"RU",
    "name:eng_x_preferred":[
        "Yurginskoye"
    ],
    "name:nor_x_preferred":[
        "Jurginskoje"
    ],
    "name:rus_x_preferred":[
        "\u042e\u0440\u0433\u0438\u043d\u0441\u043a\u043e\u0435"
    ],
    "name:unk_x_variant":[
        "Korginskoye"
    ],
    "qs:name":"Yurginskoye",
    "qs:photos_9r":0,
    "qs:photos_sr":0,
    "qs:pop_sr":"4",
    "wd:wordcount":822,
    "wof:name":"Yurginskoye",
    "wof:placetype":"locality",
    "wof:population":4606
},
  "geometry": {"coordinates":[67.39211,56.81888],"type":"Point"}
}