{
  "type": "Feature",
  "properties": {
    "gn:country":"RU",
    "gn:fcode":"PPL",
    "gn:pop":4606,
    "iso:country":"RU",
    "name:ceb_x_preferred":[
        "Yurginskiy Rayon"
    ],
    "name:che_x_preferred":[
        "\u042e\u0440\u0433\u0438\u043d\u0441\u043a\u0430\u043d \u043a\u04c0\u043e\u0448\u0442"
    ],
    "name:deu_x_preferred":[
        "Rajon Jurginski"
    ],
    "name:eng_x_preferred":[
        "Yurginskoye"
    ],
    "name:eng_x_variant":[
        "Yurginsky District"
    ],
    "name:hun_x_preferred":[
        "Jurginszkojei j\u00e1r\u00e1s"
    ],
    "name:hye_x_preferred":[
        "\u0545\u0578\u0582\u0580\u0563\u056b\u0576\u057d\u056f\u056b \u0577\u0580\u057b\u0561\u0576"
    ],
    "name:ita_x_preferred":[
        "Jurginskij rajon"
    ],
    "name:nld_x_preferred":[
        "Yurginsky District"
    ],
    "name:nor_x_preferred":[
        "Jurginskoje"
    ],
    "name:rus_x_preferred":[
        "\u042e\u0440\u0433\u0438\u043d\u0441\u043a\u043e\u0435"
    ],
    "name:rus_x_variant":[
        "\u042e\u0440\u0433\u0438\u043d\u0441\u043a\u0438\u0439 \u0440\u0430\u0439\u043e\u043d"
    ],
    "name:tat_x_preferred":[
        "\u042e\u0440\u0433\u0430 \u0440\u0430\u0439\u043e\u043d\u044b"
    ],
    "name:unk_x_variant":[
        "Korginskoye"
    ],
    "name:zho_x_preferred":[
        "\u5c24\u723e\u91d1\u65af\u57fa\u5340"
    ],
    "qs:name":"Yurginskoye",
    "qs:photos_9r":0,
    "qs:photos_sr":0,
    "qs:pop_sr":"4",
    "wd:wordcount":822,
    "wof:name":"Yurginskoye",
    "wof:placetype":"locality",
    "wof:population":4606
},
  "geometry": {"coordinates":[67.39211,56.81888],"type":"Point"}
}