{
  "type": "Feature",
  "properties": {
    "gn:admin1_code":"53",
    "gn:asciiname":"Andreyevka",
    "gn:country_code":"RU",
    "gn:dem":109,
    "gn:feature_class":"P",
    "gn:feature_code":"PPL",
    "gn:name":"Andreyevka",
    "gn:population":0,
    "gn:timezone":"Asia/Novosibirsk",
    "iso:country":"RU",
    "name:eng_x_preferred":[
        "Andreyevka"
    ],
    "name:nor_x_preferred":[
        "Andrejevka"
    ],
    "name:rus_x_preferred":[
        "\u0410\u043d\u0434\u0440\u0435\u0435\u0432\u043a\u0430"
    ],
    "name:und_x_variant":[
        "Voskresenskoye",
        "Andreyevskoye"
    ],
    "wof:name":"Andreyevka",
    "wof:placetype":"locality"
},
  "geometry": {"coordinates":[77.44653000000002,53.84456],"type":"Point"}
}