{
  "type": "Feature",
  "properties": {
    "gn:admin1_code":"63",
    "gn:asciiname":"Kharaulakh",
    "gn:country_code":"RU",
    "gn:dem":240,
    "gn:feature_class":"P",
    "gn:feature_code":"PPL",
    "gn:name":"Kharaulakh",
    "gn:population":0,
    "gn:timezone":"Asia/Yakutsk",
    "iso:country":"RU",
    "name:rus_x_preferred":[
        "\u0425\u0430\u0440\u0430\u0443\u043b\u0430\u0445"
    ],
    "wof:name":"Kharaulakh",
    "wof:placetype":"locality"
},
  "geometry": {"coordinates":[129.75,70.46666999999999],"type":"Point"}
}