{
  "type": "Feature",
  "properties": {
    "gn:admin1_code":"85",
    "gn:asciiname":"Sosunovo",
    "gn:country_code":"RU",
    "gn:dem":130,
    "gn:feature_class":"P",
    "gn:feature_code":"PPL",
    "gn:name":"Sosunovo",
    "gn:population":0,
    "gn:timezone":"Europe/Moscow",
    "iso:country":"RU",
    "name:rus_x_preferred":[
        "\u0421\u043e\u0441\u0443\u043d\u043e\u0432\u043e"
    ],
    "wof:name":"Sosunovo",
    "wof:placetype":"locality"
},
  "geometry": {"coordinates":[38.21675,59.85155],"type":"Point"}
}