{
  "type": "Feature",
  "properties": {
    "gn:country":"RU",
    "gn:fcode":"PPL",
    "gn:pop":8279,
    "iso:country":"RU",
    "name:nor_x_preferred":[
        "Srednjaja Jeljuzan"
    ],
    "name:rus_x_preferred":[
        "\u0421\u0440\u0435\u0434\u043d\u044f\u044f \u0415\u043b\u044e\u0437\u0430\u043d\u044c"
    ],
    "name:unk_x_variant":[
        "\u0421\u0440\u0435\u0434\u043d\u044f\u044f \u0415\u043b\u044e\u0437\u0430\u043d\u044c"
    ],
    "qs:name":"Srednyaya Yelyuzan'",
    "qs:name_adm0":"Russia",
    "qs:name_adm1":"Penza Oblast",
    "qs:photos_9r":0,
    "qs:photos_sr":0,
    "qs:placetype":"Town",
    "qs:pop_sr":"5",
    "wof:name":"Srednyaya Yelyuzan'",
    "wof:placetype":"locality",
    "wof:population":8279
},
  "geometry": {"coordinates":[45.9529,53.0241],"type":"Point"}
}