{
  "type": "Feature",
  "properties": {
    "gn:admin1_code":"28",
    "gn:asciiname":"Yelovaya Gora",
    "gn:country_code":"RU",
    "gn:dem":144,
    "gn:feature_class":"P",
    "gn:feature_code":"PPL",
    "gn:name":"Yelovaya Gora",
    "gn:population":0,
    "gn:timezone":"Europe/Moscow",
    "iso:country":"RU",
    "name:fin_x_preferred":[
        "Elovaara"
    ],
    "wof:name":"Yelovaya Gora",
    "wof:placetype":"locality"
},
  "geometry": {"coordinates":[32.36667,64.18333],"type":"Point"}
}