{
  "type": "Feature",
  "properties": {
    "gn:admin1_code":"17.0",
    "gn:admin2_code":"551375",
    "gn:asciiname":"Artlukh",
    "gn:country_code":"RU",
    "gn:dem":2050,
    "gn:feature_class":"P",
    "gn:feature_code":"PPL",
    "gn:name":"Artlukh",
    "gn:population":0,
    "gn:timezone":"Europe/Moscow",
    "iso:country":"RU",
    "name:nor_x_preferred":[
        "Artlukh"
    ],
    "name:rus_x_preferred":[
        "\u0410\u0440\u0442\u043b\u0443\u0445"
    ],
    "wof:name":"Artlukh",
    "wof:placetype":"locality"
},
  "geometry": {"coordinates":[46.66942,42.86166],"type":"Point"}
}