{
  "type": "Feature",
  "properties": {
    "gn:admin1_code":"71",
    "gn:asciiname":"Pyshminskaya",
    "gn:country_code":"RU",
    "gn:dem":129,
    "gn:feature_class":"P",
    "gn:feature_code":"PPL",
    "gn:name":"Pyshminskaya",
    "gn:population":0,
    "gn:timezone":"Asia/Yekaterinburg",
    "iso:country":"RU",
    "name:rus_x_preferred":[
        "\u041f\u044b\u0448\u043c\u0438\u043d\u0441\u043a\u0430\u044f"
    ],
    "name:und_x_variant":[
        "\u041f\u044b\u0448\u043c\u0438\u043d\u0441\u043a\u0430\u044f"
    ],
    "wof:name":"Pyshminskaya",
    "wof:placetype":"locality"
},
  "geometry": {"coordinates":[62.3884,56.8066],"type":"Point"}
}