{
  "type": "Feature",
  "properties": {
    "gn:admin1_code":"15",
    "gn:asciiname":"Keniskhvin",
    "gn:cc2":"RU",
    "gn:country_code":"RU",
    "gn:dem":455,
    "gn:feature_class":"P",
    "gn:feature_code":"PPL",
    "gn:name":"Keniskhvin",
    "gn:population":0,
    "gn:timezone":"Asia/Anadyr",
    "iso:country":"RU",
    "name:rus_x_preferred":[
        "\u041a\u0435\u043d\u0438\u0441\u0445\u0432\u0438\u043d"
    ],
    "name:und_x_variant":[
        "Keneshken",
        "Keniskhvin"
    ],
    "wof:name":"Keniskhvin",
    "wof:placetype":"locality"
},
  "geometry": {"coordinates":[171.69999999999999,66.86667],"type":"Point"}
}