{
  "type": "Feature",
  "properties": {
    "gn:admin1_code":"16",
    "gn:asciiname":"Il'ina Gora",
    "gn:country_code":"RU",
    "gn:dem":117,
    "gn:feature_class":"P",
    "gn:feature_code":"PPL",
    "gn:name":"Il\u2019ina Gora",
    "gn:population":0,
    "gn:timezone":"Europe/Moscow",
    "iso:country":"RU",
    "name:eng_x_preferred":[
        "Il'ina Gora"
    ],
    "name:nor_x_preferred":[
        "Ilina Gora"
    ],
    "name:rus_x_preferred":[
        "\u0418\u043b\u044c\u0438\u043d\u0430 \u0413\u043e\u0440\u0430"
    ],
    "name:und_x_variant":[
        "\u0418\u043b\u044c\u0438\u043d\u0430 \u0413\u043e\u0440\u0430",
        "Il\u2019ina Gora"
    ],
    "wof:name":"Il'ina Gora",
    "wof:placetype":"locality"
},
  "geometry": {"coordinates":[46.12657,55.82663],"type":"Point"}
}