{
  "type": "Feature",
  "properties": {
    "gn:admin1_code":"73",
    "gn:asciiname":"Burdybash",
    "gn:country_code":"RU",
    "gn:dem":147,
    "gn:feature_class":"P",
    "gn:feature_code":"PPL",
    "gn:name":"Burdybash",
    "gn:population":0,
    "gn:timezone":"Europe/Moscow",
    "iso:country":"RU",
    "name:rus_x_preferred":[
        "\u0411\u0443\u0440\u0434\u044b\u0431\u0430\u0448"
    ],
    "name:und_x_variant":[
        "\u0411\u0443\u0440\u0434\u044b\u0431\u0430\u0448"
    ],
    "wof:name":"Burdybash",
    "wof:placetype":"locality"
},
  "geometry": {"coordinates":[52.3392,55.5127],"type":"Point"}
}