{
  "type": "Feature",
  "properties": {
    "gn:admin1_code":"33.0",
    "gn:asciiname":"Polyany",
    "gn:country_code":"RU",
    "gn:dem":138,
    "gn:feature_class":"P",
    "gn:feature_code":"PPL",
    "gn:name":"Polyany",
    "gn:population":0,
    "gn:timezone":"Europe/Kirov",
    "iso:country":"RU",
    "name:bel_x_preferred":[
        "\u041f\u0430\u043b\u044f\u043d\u044b"
    ],
    "name:rus_x_preferred":[
        "\u041f\u043e\u043b\u044f\u043d\u044b"
    ],
    "name:ukr_x_preferred":[
        "\u041f\u043e\u043b\u044f\u043d\u0438"
    ],
    "wof:name":"Polyany",
    "wof:placetype":"locality"
},
  "geometry": {"coordinates":[50.38871,58.42059],"type":"Point"}
}