{
  "type": "Feature",
  "properties": {
    "gn:admin1_code":"47",
    "gn:asciiname":"Koshcheykovo",
    "gn:country_code":"RU",
    "gn:dem":170,
    "gn:feature_class":"P",
    "gn:feature_code":"PPL",
    "gn:name":"Koshcheykovo",
    "gn:population":49,
    "gn:timezone":"Europe/Moscow",
    "iso:country":"RU",
    "name:rus_x_preferred":[
        "\u041a\u043e\u0449\u0435\u0439\u043a\u043e\u0432\u043e"
    ],
    "name:und_x_variant":[
        "\u041a\u043e\u0449\u0435\u0439\u043a\u043e\u0432\u043e"
    ],
    "wof:name":"Koshcheykovo",
    "wof:placetype":"locality",
    "wof:population":49
},
  "geometry": {"coordinates":[37.91667,56.08333],"type":"Point"}
}