{
  "type": "Feature",
  "properties": {
    "gn:admin1_code":"21.0",
    "gn:asciiname":"Borutikha",
    "gn:country_code":"RU",
    "gn:dem":119,
    "gn:feature_class":"P",
    "gn:feature_code":"PPL",
    "gn:name":"Borutikha",
    "gn:population":0,
    "gn:timezone":"Europe/Moscow",
    "iso:country":"RU",
    "name:rus_x_preferred":[
        "\u0411\u043e\u0440\u0443\u0442\u0438\u0445\u0430"
    ],
    "name:und_x_variant":[
        "\u0411\u043e\u0440\u0443\u0442\u0438\u0445\u0430"
    ],
    "wof:name":"Borutikha",
    "wof:placetype":"locality"
},
  "geometry": {"coordinates":[41.82309,57.377],"type":"Point"}
}