{
  "type": "Feature",
  "properties": {
    "gn:admin1_code":"77",
    "gn:asciiname":"Konyshkovo",
    "gn:country_code":"RU",
    "gn:dem":238,
    "gn:feature_class":"P",
    "gn:feature_code":"PPL",
    "gn:name":"Konyshkovo",
    "gn:population":0,
    "gn:timezone":"Europe/Moscow",
    "iso:country":"RU",
    "name:rus_x_preferred":[
        "\u041a\u043e\u043d\u044b\u0448\u043a\u043e\u0432\u043e"
    ],
    "name:und_x_variant":[
        "\u041a\u043e\u043d\u044b\u0448\u043a\u043e\u0432\u043e"
    ],
    "wof:name":"Konyshkovo",
    "wof:placetype":"locality"
},
  "geometry": {"coordinates":[34.48693,56.76382],"type":"Point"}
}