{
  "type": "Feature",
  "properties": {
    "gn:admin1_code":"70.0",
    "gn:asciiname":"Urakovskiy",
    "gn:country_code":"RU",
    "gn:dem":272,
    "gn:feature_class":"P",
    "gn:feature_code":"PPL",
    "gn:name":"Urakovskiy",
    "gn:population":0,
    "gn:timezone":"Europe/Moscow",
    "iso:country":"RU",
    "name:rus_x_preferred":[
        "\u0423\u0440\u0430\u043a\u043e\u0432\u0441\u043a\u0438\u0439"
    ],
    "wof:name":"Urakovskiy",
    "wof:placetype":"locality"
},
  "geometry": {"coordinates":[41.76307,44.83433],"type":"Point"}
}