{
  "type": "Feature",
  "properties": {
    "gn:admin1_code":"42",
    "gn:asciiname":"Krasnaya Gorka",
    "gn:country_code":"RU",
    "gn:dem":80,
    "gn:feature_class":"P",
    "gn:feature_code":"PPL",
    "gn:name":"Krasnaya Gorka",
    "gn:population":0,
    "gn:timezone":"Europe/Moscow",
    "iso:country":"RU",
    "name:fin_x_preferred":[
        "Rauhala"
    ],
    "name:rus_x_preferred":[
        "\u041a\u0440\u0430\u0441\u043d\u0430\u044f \u0413\u043e\u0440\u043a\u0430"
    ],
    "wof:name":"Krasnaya Gorka",
    "wof:placetype":"locality"
},
  "geometry": {"coordinates":[30.65,59.51667],"type":"Point"}
}