{
  "type": "Feature",
  "properties": {
    "gn:admin1_code":"80",
    "gn:asciiname":"Kapustino",
    "gn:country_code":"RU",
    "gn:dem":120,
    "gn:feature_class":"P",
    "gn:feature_code":"PPL",
    "gn:name":"Kapustino",
    "gn:population":0,
    "gn:timezone":"Europe/Samara",
    "iso:country":"RU",
    "name:eng_x_preferred":[
        "Kapustino"
    ],
    "name:nor_x_preferred":[
        "Kapustino"
    ],
    "name:rus_x_preferred":[
        "\u041a\u0430\u043f\u0443\u0441\u0442\u0438\u043d\u043e"
    ],
    "name:und_x_variant":[
        "Staroye Kapustino"
    ],
    "wof:name":"Kapustino",
    "wof:placetype":"locality"
},
  "geometry": {"coordinates":[52.74644,56.70121999999999],"type":"Point"}
}