{
  "type": "Feature",
  "properties": {
    "gn:country":"RU",
    "gn:fcode":"PPL",
    "gn:pop":5159,
    "iso:country":"RU",
    "name:bul_x_preferred":[
        "\u041f\u0440\u0438\u043b\u0430\u0434\u043e\u0436\u043a\u0438"
    ],
    "name:cat_x_preferred":[
        "Priladozhsky"
    ],
    "name:che_x_preferred":[
        "\u041f\u0440\u0438\u043b\u0430\u0434\u043e\u0436\u0441\u043a\u0438\u0439"
    ],
    "name:deu_x_preferred":[
        "Prilado\u017eski"
    ],
    "name:eng_x_preferred":[
        "Priladozhsky"
    ],
    "name:fin_x_preferred":[
        "Prilado\u017eski"
    ],
    "name:fra_x_preferred":[
        "Priladozhsky"
    ],
    "name:hye_x_preferred":[
        "\u054a\u0580\u056b\u056c\u0561\u0564\u0578\u056a\u057d\u056f\u056b\u0575"
    ],
    "name:ita_x_preferred":[
        "Prilado\u017eskij"
    ],
    "name:nld_x_preferred":[
        "Priladozjskiy"
    ],
    "name:nno_x_preferred":[
        "Priladozjskij"
    ],
    "name:nob_x_preferred":[
        "Priladozjskij"
    ],
    "name:nor_x_preferred":[
        "Priladozjskij"
    ],
    "name:oci_x_preferred":[
        "Priladozhsky"
    ],
    "name:rus_x_preferred":[
        "\u041f\u0440\u0438\u043b\u0430\u0434\u043e\u0436\u0441\u043a\u0438\u0439"
    ],
    "name:spa_x_preferred":[
        "Prilado\u017eskij"
    ],
    "name:srp_x_preferred":[
        "\u041f\u0440\u0438\u043b\u0430\u0434\u043e\u0448\u043a\u0438"
    ],
    "name:unk_x_variant":[
        "\u041f\u0440\u0438\u043b\u0430\u0434\u043e\u0436\u0441\u043a\u0438\u0439"
    ],
    "qs:name":"Priladozhskiy",
    "qs:name_adm0":"Russia",
    "qs:name_adm1":"Leningrad Oblast",
    "qs:photos_9k":5,
    "qs:photos_9r":7,
    "qs:photos_all":1237,
    "qs:photos_sr":0,
    "qs:placetype":"Town",
    "qs:pop_sr":"5",
    "wof:name":"Priladozhskiy",
    "wof:placetype":"locality",
    "wof:population":5159
},
  "geometry": {"coordinates":[31.48333,59.85],"type":"Point"}
}