{
  "type": "Feature",
  "properties": {
    "gn:admin1_code":"81",
    "gn:asciiname":"Yur'yevka",
    "gn:country_code":"RU",
    "gn:dem":191,
    "gn:feature_class":"P",
    "gn:feature_code":"PPL",
    "gn:name":"Yur\u2019yevka",
    "gn:population":0,
    "gn:timezone":"Europe/Ulyanovsk",
    "iso:country":"RU",
    "name:rus_x_preferred":[
        "\u042e\u0440\u044c\u0435\u0432\u043a\u0430"
    ],
    "name:und_x_variant":[
        "Yur\u2019yevka"
    ],
    "wof:name":"Yur'yevka",
    "wof:placetype":"locality"
},
  "geometry": {"coordinates":[47.84681,53.04273000000001],"type":"Point"}
}