{
  "type": "Feature",
  "properties": {
    "gn:admin1_code":"32",
    "gn:asciiname":"Sabun",
    "gn:country_code":"RU",
    "gn:dem":85,
    "gn:feature_class":"P",
    "gn:feature_code":"PPL",
    "gn:name":"Sabun",
    "gn:population":0,
    "gn:timezone":"Asia/Yekaterinburg",
    "iso:country":"RU",
    "name:rus_x_preferred":[
        "\u0421\u0430\u0431\u0443\u043d"
    ],
    "name:und_x_variant":[
        "\u0421\u0430\u0431\u0443\u043d"
    ],
    "wof:name":"Sabun",
    "wof:placetype":"locality"
},
  "geometry": {"coordinates":[81.38333,62.01667],"type":"Point"}
}