{
  "type": "Feature",
  "properties": {
    "gn:admin1_code":"91",
    "gn:asciiname":"Konzhul",
    "gn:country_code":"RU",
    "gn:dem":292,
    "gn:feature_class":"P",
    "gn:feature_code":"PPL",
    "gn:name":"Konzhul",
    "gn:population":0,
    "gn:timezone":"Asia/Krasnoyarsk",
    "iso:country":"RU",
    "name:rus_x_preferred":[
        "\u041a\u043e\u043d\u0436\u0443\u043b"
    ],
    "wof:name":"Konzhul",
    "wof:placetype":"locality"
},
  "geometry": {"coordinates":[92.56667,55.38333000000001],"type":"Point"}
}