{
  "type": "Feature",
  "properties": {
    "gn:admin1_code":"4",
    "gn:asciiname":"Karagayka",
    "gn:country_code":"RU",
    "gn:dem":252,
    "gn:feature_class":"P",
    "gn:feature_code":"PPL",
    "gn:name":"Karagayka",
    "gn:population":0,
    "gn:timezone":"Asia/Barnaul",
    "iso:country":"RU",
    "name:eng_x_preferred":[
        "Karagayka"
    ],
    "name:nor_x_preferred":[
        "Karagajka"
    ],
    "name:rus_x_preferred":[
        "\u041a\u0430\u0440\u0430\u0433\u0430\u0439\u043a\u0430"
    ],
    "wof:name":"Karagayka",
    "wof:placetype":"locality"
},
  "geometry": {"coordinates":[86.3056,52.25100000000001],"type":"Point"}
}