{
  "type": "Feature",
  "properties": {
    "gn:country":"RU",
    "gn:fcode":"PPL",
    "gn:population":4024,
    "iso:country":"RU",
    "name:nor_x_preferred":[
        "Solnetsjnoje"
    ],
    "name:rus_x_preferred":[
        "\u0421\u043e\u043b\u043d\u0435\u0447\u043d\u043e\u0435"
    ],
    "name:und_x_variant":[
        "Batashevskiy"
    ],
    "qs:name":"Solnechnoe",
    "qs:name_adm0":"Russia",
    "qs:name_adm1":"Dagestan Republic",
    "qs:photos_9r":0,
    "qs:photos_sr":0,
    "qs:placetype":"Town",
    "qs:pop_sr":"4",
    "wof:name":"Solnechnoe",
    "wof:placetype":"locality",
    "wof:population":4024
},
  "geometry": {"coordinates":[46.50697,43.276],"type":"Point"}
}