{
  "type": "Feature",
  "properties": {
    "gn:admin1_code":"77",
    "gn:asciiname":"Sukhoyedovo",
    "gn:country_code":"RU",
    "gn:dem":166,
    "gn:feature_class":"P",
    "gn:feature_code":"PPL",
    "gn:name":"Sukhoyedovo",
    "gn:population":0,
    "gn:timezone":"Europe/Moscow",
    "iso:country":"RU",
    "name:rus_x_preferred":[
        "\u0421\u0443\u0445\u043e\u0435\u0434\u043e\u0432\u043e"
    ],
    "name:und_x_variant":[
        "\u0421\u0443\u0445\u043e\u0435\u0434\u043e\u0432\u043e"
    ],
    "wof:name":"Sukhoyedovo",
    "wof:placetype":"locality"
},
  "geometry": {"coordinates":[33.93333,58.18333000000001],"type":"Point"}
}