{
  "type": "Feature",
  "properties": {
    "gn:admin1_code":"51.0",
    "gn:asciiname":"Shirmaksha",
    "gn:country_code":"RU",
    "gn:dem":96,
    "gn:feature_class":"P",
    "gn:feature_code":"PPL",
    "gn:name":"Shirmaksha",
    "gn:population":0,
    "gn:timezone":"Europe/Moscow",
    "iso:country":"RU",
    "name:nor_x_preferred":[
        "Sjirmaksja"
    ],
    "name:rus_x_preferred":[
        "\u0428\u0438\u0440\u043c\u0430\u043a\u0448\u0430"
    ],
    "wof:name":"Shirmaksha",
    "wof:placetype":"locality"
},
  "geometry": {"coordinates":[43.34448,56.9771],"type":"Point"}
}