{
  "type": "Feature",
  "properties": {
    "gn:admin1_code":"21",
    "gn:asciiname":"Lodygino",
    "gn:country_code":"RU",
    "gn:dem":123,
    "gn:feature_class":"P",
    "gn:feature_code":"PPL",
    "gn:name":"Lodygino",
    "gn:population":0,
    "gn:timezone":"Europe/Moscow",
    "iso:country":"RU",
    "name:che_x_preferred":[
        "\u041b\u043e\u0434\u044b\u0433\u0438\u043d\u043e"
    ],
    "name:rus_x_preferred":[
        "\u041b\u043e\u0434\u044b\u0433\u0438\u043d\u043e"
    ],
    "name:und_x_variant":[
        "Ladygino",
        "Lodygino"
    ],
    "wof:name":"Lodygino",
    "wof:placetype":"locality"
},
  "geometry": {"coordinates":[41.34637,57.24986],"type":"Point"}
}