{
  "type": "Feature",
  "properties": {
    "gn:admin1_code":"60",
    "gn:asciiname":"Timokhovo",
    "gn:country_code":"RU",
    "gn:dem":103,
    "gn:feature_class":"P",
    "gn:feature_code":"PPL",
    "gn:name":"Timokhovo",
    "gn:population":0,
    "gn:timezone":"Europe/Moscow",
    "iso:country":"RU",
    "name:rus_x_preferred":[
        "\u0422\u0438\u043c\u043e\u0445\u043e\u0432\u043e"
    ],
    "name:und_x_variant":[
        "Timokhova",
        "Timokhovo",
        "\u0422\u0438\u043c\u043e\u0445\u043e\u0432\u043e"
    ],
    "wof:name":"Timokhovo",
    "wof:placetype":"locality"
},
  "geometry": {"coordinates":[30.208,56.58697],"type":"Point"}
}