{
  "type": "Feature",
  "properties": {
    "gn:admin1_code":"33",
    "gn:asciiname":"Usovy",
    "gn:country_code":"RU",
    "gn:dem":151,
    "gn:feature_class":"P",
    "gn:feature_code":"PPL",
    "gn:name":"Usovy",
    "gn:population":0,
    "gn:timezone":"Europe/Kirov",
    "iso:country":"RU",
    "name:eng_x_preferred":[
        "Usovy"
    ],
    "name:nor_x_preferred":[
        "Usovy"
    ],
    "name:rus_x_preferred":[
        "\u0423\u0441\u043e\u0432\u044b"
    ],
    "wof:name":"Usovy",
    "wof:placetype":"locality"
},
  "geometry": {"coordinates":[49.25433,58.33894],"type":"Point"}
}