{
  "type": "Feature",
  "properties": {
    "gn:admin1_code":"52",
    "gn:asciiname":"Penina",
    "gn:cc2":"RU",
    "gn:country_code":"RU",
    "gn:dem":45,
    "gn:feature_class":"P",
    "gn:feature_code":"PPL",
    "gn:name":"Penina",
    "gn:population":0,
    "gn:timezone":"Europe/Moscow",
    "iso:country":"RU",
    "name:rus_x_preferred":[
        "\u041f\u0435\u043d\u0438\u043d\u0430"
    ],
    "name:und_x_variant":[
        "Penino",
        "Pekina",
        "Penina"
    ],
    "wof:name":"Penina",
    "wof:placetype":"locality"
},
  "geometry": {"coordinates":[30.16667,58.06667],"type":"Point"}
}