{
  "type": "Feature",
  "properties": {
    "gn:admin1_code":"91",
    "gn:asciiname":"Bol'shoye Ozero",
    "gn:country_code":"RU",
    "gn:dem":414,
    "gn:feature_class":"P",
    "gn:feature_code":"PPL",
    "gn:name":"Bol\u2019shoye Ozero",
    "gn:population":0,
    "gn:timezone":"Asia/Krasnoyarsk",
    "iso:country":"RU",
    "name:rus_x_preferred":[
        "\u0411\u043e\u043b\u044c\u0448\u043e\u0435 \u041e\u0437\u0435\u0440\u043e"
    ],
    "name:und_x_variant":[
        "Bozh\u2019ye-Ozero",
        "Bozh\u2019ye-Ozerskoye",
        "Bol\u2019shoye Ozero"
    ],
    "wof:name":"Bol'shoye Ozero",
    "wof:placetype":"locality"
},
  "geometry": {"coordinates":[89.31778,55.18722],"type":"Point"}
}