{
  "type": "Feature",
  "properties": {
    "gn:admin1_code":"28",
    "gn:asciiname":"Lipovaya Sel'ga",
    "gn:country_code":"RU",
    "gn:dem":138,
    "gn:feature_class":"P",
    "gn:feature_code":"PPL",
    "gn:name":"Lipovaya Sel\u2019ga",
    "gn:population":0,
    "gn:timezone":"Europe/Moscow",
    "iso:country":"RU",
    "name:rus_x_preferred":[
        "\u041b\u0438\u043f\u043e\u0432\u0430\u044f \u0421\u0435\u043b\u044c\u0433\u0430"
    ],
    "name:und_x_variant":[
        "Lipovaya Sel\u2019ga"
    ],
    "wof:name":"Lipovaya Sel'ga",
    "wof:placetype":"locality"
},
  "geometry": {"coordinates":[36.77039,61.59798000000001],"type":"Point"}
}