{
  "type": "Feature",
  "properties": {
    "gn:admin1_code":"50",
    "gn:asciiname":"Nizhnyaya Pesha",
    "gn:country_code":"RU",
    "gn:dem":10,
    "gn:feature_class":"P",
    "gn:feature_code":"PPL",
    "gn:name":"Nizhnyaya Pesha",
    "gn:population":0,
    "gn:timezone":"Europe/Moscow",
    "iso:country":"RU",
    "name:eng_x_preferred":[
        "Nizhnyaya Pesha"
    ],
    "name:nor_x_preferred":[
        "Nizj.Pesja"
    ],
    "name:rus_x_preferred":[
        "\u041d\u0438\u0436.\u041f\u0435\u0448\u0430"
    ],
    "name:rus_x_variant":[
        "\u041d\u0438\u0436\u043d\u044f\u044f \u041f\u0435\u0448\u0430"
    ],
    "name:und_x_variant":[
        "Pecha",
        "Nizh Pesha",
        "Nizhnyaya Pesha",
        "\u041d\u0438\u0436\u043d\u044f\u044f \u041f\u0435\u0448\u0430"
    ],
    "wof:name":"Nizhnyaya Pesha",
    "wof:placetype":"locality"
},
  "geometry": {"coordinates":[47.77286,66.75189],"type":"Point"}
}