{
  "type": "Feature",
  "properties": {
    "gn:admin1_code":"20",
    "gn:asciiname":"Sofronova",
    "gn:country_code":"RU",
    "gn:dem":549,
    "gn:feature_class":"P",
    "gn:feature_code":"PPL",
    "gn:name":"Sofronova",
    "gn:population":0,
    "gn:timezone":"Asia/Irkutsk",
    "iso:country":"RU",
    "wof:name":"Sofronova",
    "wof:placetype":"locality"
},
  "geometry": {"coordinates":[103.13333,53.18333000000001],"type":"Point"}
}