{
  "type": "Feature",
  "properties": {
    "gn:admin1_code":"13",
    "gn:asciiname":"Kirovskiy",
    "gn:country_code":"RU",
    "gn:dem":360,
    "gn:feature_class":"P",
    "gn:feature_code":"PPL",
    "gn:name":"Kirovskiy",
    "gn:population":0,
    "gn:timezone":"Asia/Yekaterinburg",
    "iso:country":"RU",
    "name:rus_x_preferred":[
        "\u041a\u0438\u0440\u043e\u0432\u0441\u043a\u0438\u0439"
    ],
    "name:und_x_variant":[
        "Kirovo",
        "Kirovskiy",
        "\u041a\u0438\u0440\u043e\u0432\u0441\u043a\u0438\u0439"
    ],
    "wof:name":"Kirovskiy",
    "wof:placetype":"locality"
},
  "geometry": {"coordinates":[59.5898,53.2116],"type":"Point"}
}