{
  "type": "Feature",
  "properties": {
    "gn:admin1_code":"88",
    "gn:asciiname":"Kuznechikha",
    "gn:country_code":"RU",
    "gn:dem":128,
    "gn:feature_class":"P",
    "gn:feature_code":"PPL",
    "gn:name":"Kuznechikha",
    "gn:population":0,
    "gn:timezone":"Europe/Moscow",
    "iso:country":"RU",
    "name:eng_x_preferred":[
        "Kuznechikha"
    ],
    "name:nor_x_preferred":[
        "Kuznetsjikha"
    ],
    "name:rus_x_preferred":[
        "\u041a\u0443\u0437\u043d\u0435\u0447\u0438\u0445\u0430"
    ],
    "wof:name":"Kuznechikha",
    "wof:placetype":"locality"
},
  "geometry": {"coordinates":[39.9026,57.7062],"type":"Point"}
}