{
  "type": "Feature",
  "properties": {
    "gn:admin1_code":"10",
    "gn:asciiname":"Novaya Pestrakovka",
    "gn:country_code":"RU",
    "gn:dem":183,
    "gn:feature_class":"P",
    "gn:feature_code":"PPL",
    "gn:name":"Novaya Pestrakovka",
    "gn:population":0,
    "gn:timezone":"Europe/Moscow",
    "iso:country":"RU",
    "name:rus_x_preferred":[
        "\u041d\u043e\u0432\u0430\u044f \u041f\u0435\u0441\u0442\u0440\u0430\u043a\u043e\u0432\u043a\u0430"
    ],
    "name:und_x_variant":[
        "Pestrikova",
        "Novaya Pestrakovka"
    ],
    "wof:name":"Novaya Pestrakovka",
    "wof:placetype":"locality"
},
  "geometry": {"coordinates":[33.28057,53.40241999999999],"type":"Point"}
}