{
  "type": "Feature",
  "properties": {
    "gn:admin1_code":"41",
    "gn:asciiname":"Krutyye Verkhi",
    "gn:country_code":"RU",
    "gn:dem":164,
    "gn:feature_class":"P",
    "gn:feature_code":"PPL",
    "gn:name":"Krutyye Verkhi",
    "gn:population":0,
    "gn:timezone":"Europe/Moscow",
    "iso:country":"RU",
    "name:rus_x_preferred":[
        "\u041a\u0440\u0443\u0442\u044b\u0435 \u0412\u0435\u0440\u0445\u0438"
    ],
    "wof:name":"Krutyye Verkhi",
    "wof:placetype":"locality"
},
  "geometry": {"coordinates":[37.407,51.4194],"type":"Point"}
}