{
  "type": "Feature",
  "properties": {
    "gn:country":"RU",
    "gn:fcode":"PPL",
    "gn:population":3554,
    "iso:country":"RU",
    "name:eng_x_preferred":[
        "Staropesterevo"
    ],
    "name:nor_x_preferred":[
        "Staropesterevo"
    ],
    "name:rus_x_preferred":[
        "\u0421\u0442\u0430\u0440\u043e\u043f\u0435\u0441\u0442\u0435\u0440\u0435\u0432\u043e"
    ],
    "name:und_x_variant":[
        "Stropesterovo"
    ],
    "qs:name":"Staropesterevo",
    "qs:name_adm0":"Russia",
    "qs:name_adm1":"Kemerovo Oblast",
    "qs:photos_9r":0,
    "qs:photos_sr":0,
    "qs:placetype":"Town",
    "qs:pop_sr":"4",
    "wof:name":"Staropesterevo",
    "wof:placetype":"locality",
    "wof:population":3554
},
  "geometry": {"coordinates":[86.40940000000001,54.5001],"type":"Point"}
}