{
  "type": "Feature",
  "properties": {
    "gn:admin1_code":"69",
    "gn:asciiname":"Stegrimovo",
    "gn:country_code":"RU",
    "gn:dem":204,
    "gn:feature_class":"P",
    "gn:feature_code":"PPL",
    "gn:name":"Stegrimovo",
    "gn:population":0,
    "gn:timezone":"Europe/Moscow",
    "iso:country":"RU",
    "name:eng_x_preferred":[
        "Stegrimovo"
    ],
    "name:nor_x_preferred":[
        "Stegrimovo"
    ],
    "name:rus_x_preferred":[
        "\u0421\u0442\u0435\u0433\u0440\u0438\u043c\u043e\u0432\u043e"
    ],
    "name:und_x_variant":[
        "\u0421\u0442\u0435\u0433\u0440\u0438\u043c\u043e\u0432\u043e",
        "Stegrimovo"
    ],
    "wof:name":"Stegrimovo",
    "wof:placetype":"locality"
},
  "geometry": {"coordinates":[31.9061,54.47152],"type":"Point"}
}