{
  "type": "Feature",
  "properties": {
    "gn:admin1_code":"20",
    "gn:asciiname":"Nesterova",
    "gn:country_code":"RU",
    "gn:dem":483,
    "gn:feature_class":"P",
    "gn:feature_code":"PPL",
    "gn:name":"Nesterova",
    "gn:population":0,
    "gn:timezone":"Asia/Irkutsk",
    "iso:country":"RU",
    "name:rus_x_preferred":[
        "\u041d\u0435\u0441\u0442\u0435\u0440\u043e\u0432\u0430"
    ],
    "name:und_x_variant":[
        "Zimnik Nesterova",
        "Nesterova"
    ],
    "wof:name":"Nesterova",
    "wof:placetype":"locality"
},
  "geometry": {"coordinates":[102.91667,53.33333],"type":"Point"}
}