{
  "type": "Feature",
  "properties": {
    "gn:admin1_code":"20",
    "gn:asciiname":"Ust'-Iyskaya",
    "gn:country_code":"RU",
    "gn:dem":391,
    "gn:feature_class":"P",
    "gn:feature_code":"PPL",
    "gn:name":"Ust\u2019-Iyskaya",
    "gn:population":0,
    "gn:timezone":"Asia/Irkutsk",
    "iso:country":"RU",
    "name:und_x_variant":[
        "Ust\u2019-Lyskaya",
        "Ust\u2019-Iyskaya"
    ],
    "wof:name":"Ust'-Iyskaya",
    "wof:placetype":"locality"
},
  "geometry": {"coordinates":[102.09999999999999,55.58333],"type":"Point"}
}