{
  "type": "Feature",
  "properties": {
    "gn:country":"RU",
    "gn:fcode":"PPL",
    "gn:pop":5000,
    "iso:country":"RU",
    "name:rus_x_preferred":[
        "\u0414\u0443\u0431\u0440\u043e\u0432\u0438\u0446\u044b"
    ],
    "name:unk_x_variant":[
        "\u0414\u0443\u0431\u0440\u043e\u0432\u0438\u0446\u044b"
    ],
    "qs:name":"Dubrovitsy",
    "qs:name_adm0":"Russia",
    "qs:name_adm1":"Moscow Oblast",
    "qs:photos":114,
    "qs:photos_1k":23,
    "qs:photos_9k":1,
    "qs:photos_9r":3,
    "qs:photos_all":114,
    "qs:photos_sr":3,
    "qs:placetype":"Town",
    "qs:pop_sr":"4",
    "wof:name":"Dubrovitsy",
    "wof:placetype":"locality",
    "wof:population":5000
},
  "geometry": {"coordinates":[37.4867,55.43969],"type":"Point"}
}