{
  "type": "Feature",
  "properties": {
    "gn:admin1_code":"38",
    "gn:asciiname":"Matveyev",
    "gn:country_code":"RU",
    "gn:dem":196,
    "gn:feature_class":"P",
    "gn:feature_code":"PPL",
    "gn:name":"Matveyev",
    "gn:population":0,
    "gn:timezone":"Europe/Moscow",
    "iso:country":"RU",
    "name:rus_x_preferred":[
        "\u041c\u0430\u0442\u0432\u0435\u0435\u0432"
    ],
    "name:slv_x_preferred":[
        "Matvejev"
    ],
    "wof:name":"Matveyev",
    "wof:placetype":"locality"
},
  "geometry": {"coordinates":[40.81667,44.93333],"type":"Point"}
}