{
  "type": "Feature",
  "properties": {
    "gn:admin1_code":"85",
    "gn:asciiname":"Murdruchey",
    "gn:country_code":"RU",
    "gn:dem":209,
    "gn:feature_class":"P",
    "gn:feature_code":"PPL",
    "gn:name":"Murdruchey",
    "gn:population":0,
    "gn:timezone":"Europe/Moscow",
    "iso:country":"RU",
    "name:rus_x_preferred":[
        "\u041c\u0443\u0440\u0434\u0440\u0443\u0447\u0435\u0439"
    ],
    "wof:name":"Murdruchey",
    "wof:placetype":"locality"
},
  "geometry": {"coordinates":[37.43333,61.21666999999999],"type":"Point"}
}