{
  "type": "Feature",
  "properties": {
    "gn:admin1_code":"85",
    "gn:asciiname":"Sidorovo",
    "gn:country_code":"RU",
    "gn:dem":143,
    "gn:feature_class":"P",
    "gn:feature_code":"PPL",
    "gn:name":"Sidorovo",
    "gn:population":0,
    "gn:timezone":"Europe/Moscow",
    "iso:country":"RU",
    "name:eng_x_preferred":[
        "Sidorovo"
    ],
    "name:nor_x_preferred":[
        "Sidorovo"
    ],
    "name:rus_x_preferred":[
        "\u0421\u0438\u0434\u043e\u0440\u043e\u0432\u043e"
    ],
    "name:und_x_variant":[
        "Sidorova",
        "\u0421\u0438\u0434\u043e\u0440\u043e\u0432\u043e",
        "Sidorovo"
    ],
    "wof:name":"Sidorovo",
    "wof:placetype":"locality"
},
  "geometry": {"coordinates":[40.97667,58.75722],"type":"Point"}
}