{
  "type": "Feature",
  "properties": {
    "gn:admin1_code":"43",
    "gn:asciiname":"Lysovka",
    "gn:country_code":"RU",
    "gn:dem":202,
    "gn:feature_class":"P",
    "gn:feature_code":"PPL",
    "gn:name":"Lysovka",
    "gn:population":0,
    "gn:timezone":"Europe/Moscow",
    "iso:country":"RU",
    "name:rus_x_preferred":[
        "\u041b\u044b\u0441\u043e\u0432\u043a\u0430"
    ],
    "name:und_x_variant":[
        "\u041b\u044b\u0441\u043e\u0432\u043a\u0430"
    ],
    "wof:name":"Lysovka",
    "wof:placetype":"locality"
},
  "geometry": {"coordinates":[38.69234,52.83304],"type":"Point"}
}