{
  "type": "Feature",
  "properties": {
    "gn:admin1_code":"10",
    "gn:asciiname":"Malaya Osinovka",
    "gn:country_code":"RU",
    "gn:dem":190,
    "gn:feature_class":"P",
    "gn:feature_code":"PPL",
    "gn:name":"Malaya Osinovka",
    "gn:population":0,
    "gn:timezone":"Europe/Moscow",
    "iso:country":"RU",
    "name:rus_x_preferred":[
        "\u041c\u0430\u043b\u0430\u044f \u041e\u0441\u0438\u043d\u043e\u0432\u043a\u0430"
    ],
    "name:und_x_variant":[
        "Osinovskiye Vyselki",
        "Malaya Osinovka"
    ],
    "wof:name":"Malaya Osinovka",
    "wof:placetype":"locality"
},
  "geometry": {"coordinates":[34.71334,53.0305],"type":"Point"}
}