{
  "type": "Feature",
  "properties": {
    "gn:admin1_code":"60",
    "gn:asciiname":"Ruch'yevaya",
    "gn:country_code":"RU",
    "gn:dem":87,
    "gn:feature_class":"P",
    "gn:feature_code":"PPL",
    "gn:name":"Ruch\u2019yevaya",
    "gn:population":0,
    "gn:timezone":"Europe/Moscow",
    "iso:country":"RU",
    "name:rus_x_preferred":[
        "\u0420\u0443\u0447\u044c\u0435\u0432\u0430\u044f"
    ],
    "name:und_x_variant":[
        "Ruch\u2019yevaya",
        "\u0420\u0443\u0447\u044c\u0435\u0432\u0430\u044f"
    ],
    "wof:name":"Ruch'yevaya",
    "wof:placetype":"locality"
},
  "geometry": {"coordinates":[30.342,57.48],"type":"Point"}
}