{
  "type": "Feature",
  "properties": {
    "gn:admin1_code":"85",
    "gn:asciiname":"Ponizov'ye",
    "gn:country_code":"RU",
    "gn:dem":115,
    "gn:feature_class":"P",
    "gn:feature_code":"PPL",
    "gn:name":"Ponizov\u2019ye",
    "gn:population":0,
    "gn:timezone":"Europe/Moscow",
    "iso:country":"RU",
    "name:eng_x_preferred":[
        "Ponizov'ye"
    ],
    "name:nor_x_preferred":[
        "Ponizovje"
    ],
    "name:rus_x_preferred":[
        "\u041f\u043e\u043d\u0438\u0437\u043e\u0432\u044c\u0435"
    ],
    "name:und_x_variant":[
        "Ponizov\u2019ye"
    ],
    "wof:name":"Ponizov'ye",
    "wof:placetype":"locality"
},
  "geometry": {"coordinates":[36.7363,59.0359],"type":"Point"}
}