{
  "type": "Feature",
  "properties": {
    "gn:admin1_code":"80.0",
    "gn:asciiname":"Biban'gurt",
    "gn:country_code":"RU",
    "gn:dem":224,
    "gn:feature_class":"P",
    "gn:feature_code":"PPL",
    "gn:name":"Biban\u2019gurt",
    "gn:population":0,
    "gn:timezone":"Europe/Samara",
    "iso:country":"RU",
    "name:rus_x_preferred":[
        "\u0411\u0438\u0431\u0430\u043d\u044c\u0433\u0443\u0440\u0442"
    ],
    "name:und_x_variant":[
        "Biban\u2019gurt"
    ],
    "wof:name":"Biban'gurt",
    "wof:placetype":"locality"
},
  "geometry": {"coordinates":[53.8031,57.5777],"type":"Point"}
}