{
  "type": "Feature",
  "properties": {
    "gn:admin1_code":"81",
    "gn:asciiname":"Shikovka",
    "gn:country_code":"RU",
    "gn:dem":88,
    "gn:feature_class":"P",
    "gn:feature_code":"PPL",
    "gn:name":"Shikovka",
    "gn:population":0,
    "gn:timezone":"Europe/Ulyanovsk",
    "iso:country":"RU",
    "name:eng_x_preferred":[
        "Shikovka"
    ],
    "name:nor_x_preferred":[
        "Sjikovka"
    ],
    "name:rus_x_preferred":[
        "\u0428\u0438\u043a\u043e\u0432\u043a\u0430"
    ],
    "wof:name":"Shikovka",
    "wof:placetype":"locality"
},
  "geometry": {"coordinates":[47.40197,52.60424],"type":"Point"}
}