{
  "type": "Feature",
  "properties": {
    "gn:admin1_code":"77",
    "gn:asciiname":"Krasnyy Bor",
    "gn:country_code":"RU",
    "gn:dem":133,
    "gn:feature_class":"P",
    "gn:feature_code":"PPL",
    "gn:name":"Krasnyy Bor",
    "gn:population":0,
    "gn:timezone":"Europe/Moscow",
    "iso:country":"RU",
    "name:nor_x_preferred":[
        "Krasnyj Bor"
    ],
    "name:rus_x_preferred":[
        "\u041a\u0440\u0430\u0441\u043d\u044b\u0439 \u0411\u043e\u0440"
    ],
    "name:und_x_variant":[
        "Prechistyy Bor",
        "Krasnyy Bor"
    ],
    "wof:name":"Krasnyy Bor",
    "wof:placetype":"locality"
},
  "geometry": {"coordinates":[35.68686,56.94523],"type":"Point"}
}