{
  "type": "Feature",
  "properties": {
    "gn:admin1_code":"60",
    "gn:asciiname":"Muzover",
    "gn:country_code":"RU",
    "gn:dem":74,
    "gn:feature_class":"P",
    "gn:feature_code":"PPL",
    "gn:name":"Muzover",
    "gn:population":0,
    "gn:timezone":"Europe/Moscow",
    "iso:country":"RU",
    "name:rus_x_preferred":[
        "\u041c\u0443\u0437\u043e\u0432\u0435\u0440"
    ],
    "wof:name":"Muzover",
    "wof:placetype":"locality"
},
  "geometry": {"coordinates":[28.5818,58.4981],"type":"Point"}
}