{
  "type": "Feature",
  "properties": {
    "gn:admin1_code":"60",
    "gn:asciiname":"Berezavets",
    "gn:country_code":"RU",
    "gn:dem":156,
    "gn:feature_class":"P",
    "gn:feature_code":"PPL",
    "gn:name":"Ber\u00ebzavets",
    "gn:population":0,
    "gn:timezone":"Europe/Moscow",
    "iso:country":"RU",
    "name:rus_x_preferred":[
        "\u0411\u0435\u0440\u0451\u0437a\u0432\u0435\u0446"
    ],
    "name:und_x_variant":[
        "Ber\u00ebzavets"
    ],
    "wof:name":"Berezavets",
    "wof:placetype":"locality"
},
  "geometry": {"coordinates":[28.827,56.0612],"type":"Point"}
}