{
  "type": "Feature",
  "properties": {
    "gn:admin1_code":"77",
    "gn:asciiname":"Sysoyevo",
    "gn:country_code":"RU",
    "gn:dem":239,
    "gn:feature_class":"P",
    "gn:feature_code":"PPL",
    "gn:name":"Sysoyevo",
    "gn:population":0,
    "gn:timezone":"Europe/Moscow",
    "iso:country":"RU",
    "wof:name":"Sysoyevo",
    "wof:placetype":"locality"
},
  "geometry": {"coordinates":[33.98372,56.72016],"type":"Point"}
}