{
  "type": "Feature",
  "properties": {
    "gn:admin1_code":"60",
    "gn:asciiname":"Pozolotino",
    "gn:country_code":"RU",
    "gn:dem":128,
    "gn:feature_class":"P",
    "gn:feature_code":"PPL",
    "gn:name":"Pozolotino",
    "gn:population":0,
    "gn:timezone":"Europe/Moscow",
    "iso:country":"RU",
    "name:rus_x_preferred":[
        "\u041f\u043e\u0437\u043e\u043b\u043e\u0442\u0438\u043d\u043e"
    ],
    "wof:name":"Pozolotino",
    "wof:placetype":"locality"
},
  "geometry": {"coordinates":[29.0185,56.9138],"type":"Point"}
}