{
  "type": "Feature",
  "properties": {
    "gn:admin1_code":"91",
    "gn:asciiname":"Rakitovka",
    "gn:country_code":"RU",
    "gn:dem":296,
    "gn:feature_class":"P",
    "gn:feature_code":"PPL",
    "gn:name":"Rakitovka",
    "gn:population":0,
    "gn:timezone":"Asia/Krasnoyarsk",
    "iso:country":"RU",
    "name:eng_x_preferred":[
        "Rakitovka"
    ],
    "name:nor_x_preferred":[
        "Rakitovka"
    ],
    "name:rus_x_preferred":[
        "\u0420\u0430\u043a\u0438\u0442\u043e\u0432\u043a\u0430"
    ],
    "wof:name":"Rakitovka",
    "wof:placetype":"locality"
},
  "geometry": {"coordinates":[95.3788,55.8196],"type":"Point"}
}