{
  "type": "Feature",
  "properties": {
    "gn:admin1_code":"4",
    "gn:asciiname":"Novomatveyevka",
    "gn:cc2":"RU",
    "gn:country_code":"RU",
    "gn:dem":226,
    "gn:feature_class":"P",
    "gn:feature_code":"PPL",
    "gn:name":"Novomatveyevka",
    "gn:population":0,
    "gn:timezone":"Asia/Barnaul",
    "iso:country":"RU",
    "name:eng_x_preferred":[
        "Novomatveyevka"
    ],
    "name:nor_x_preferred":[
        "Novomatvejevka"
    ],
    "name:rus_x_preferred":[
        "\u041d\u043e\u0432\u043e\u043c\u0430\u0442\u0432\u0435\u0435\u0432\u043a\u0430"
    ],
    "name:und_x_variant":[
        "Novaya Matveyevskaya"
    ],
    "wof:name":"Novomatveyevka",
    "wof:placetype":"locality"
},
  "geometry": {"coordinates":[81.21222,51.32583],"type":"Point"}
}