{
  "type": "Feature",
  "properties": {
    "gn:admin1_code":"76",
    "gn:asciiname":"Maslovo-Trukhachevo",
    "gn:country_code":"RU",
    "gn:dem":176,
    "gn:feature_class":"P",
    "gn:feature_code":"PPL",
    "gn:name":"Maslovo-Trukhach\u00ebvo",
    "gn:population":0,
    "gn:timezone":"Europe/Moscow",
    "iso:country":"RU",
    "name:rus_x_preferred":[
        "\u041c\u0430\u0441\u043b\u043e\u0432\u043e-\u0422\u0440\u0443\u0445\u0430\u0447\u0451\u0432\u043e"
    ],
    "name:und_x_variant":[
        "Maslovo-Trukhach\u00ebvo"
    ],
    "wof:name":"Maslovo-Trukhachevo",
    "wof:placetype":"locality"
},
  "geometry": {"coordinates":[38.5062,53.3283],"type":"Point"}
}