{
  "type": "Feature",
  "properties": {
    "gn:admin1_code":"38.0",
    "gn:asciiname":"Volna Revolyutsii",
    "gn:country_code":"RU",
    "gn:dem":43,
    "gn:feature_class":"P",
    "gn:feature_code":"PPL",
    "gn:name":"Volna Revolyutsii",
    "gn:population":0,
    "gn:timezone":"Europe/Moscow",
    "iso:country":"RU",
    "wof:name":"Volna Revolyutsii",
    "wof:placetype":"locality"
},
  "geometry": {"coordinates":[40.08167,45.93806],"type":"Point"}
}