{
  "type": "Feature",
  "properties": {
    "gn:admin1_code":"55",
    "gn:asciiname":"Shevchenkovskiy",
    "gn:country_code":"RU",
    "gn:dem":144,
    "gn:feature_class":"P",
    "gn:feature_code":"PPL",
    "gn:name":"Shevchenkovskiy",
    "gn:population":0,
    "gn:timezone":"Asia/Yekaterinburg",
    "iso:country":"RU",
    "name:rus_x_preferred":[
        "\u0428\u0435\u0432\u0447\u0435\u043d\u043a\u043e\u0432\u0441\u043a\u0438\u0439"
    ],
    "name:und_x_variant":[
        "Shevchenko",
        "Shevchenkovskiy",
        "\u0428\u0435\u0432\u0447\u0435\u043d\u043a\u043e\u0432\u0441\u043a\u0438\u0439"
    ],
    "wof:name":"Shevchenkovskiy",
    "wof:placetype":"locality"
},
  "geometry": {"coordinates":[55.22037,50.81671],"type":"Point"}
}