{
  "type": "Feature",
  "properties": {
    "gn:admin1_code":"52.0",
    "gn:asciiname":"Deryagino",
    "gn:country_code":"RU",
    "gn:dem":156,
    "gn:feature_class":"P",
    "gn:feature_code":"PPL",
    "gn:name":"Deryagino",
    "gn:population":0,
    "gn:timezone":"Europe/Moscow",
    "iso:country":"RU",
    "name:rus_x_preferred":[
        "\u0414\u0435\u0440\u044f\u0433\u0438\u043d\u043e"
    ],
    "name:und_x_variant":[
        "\u0414\u0435\u0440\u044f\u0433\u0438\u043d\u043e"
    ],
    "wof:name":"Deryagino",
    "wof:placetype":"locality"
},
  "geometry": {"coordinates":[34.43598,58.64934],"type":"Point"}
}