{
  "type": "Feature",
  "properties": {
    "gn:admin1_code":"42",
    "gn:asciiname":"Ragulovo",
    "gn:country_code":"RU",
    "gn:dem":95,
    "gn:feature_class":"P",
    "gn:feature_code":"PPL",
    "gn:name":"Ragulovo",
    "gn:population":0,
    "gn:timezone":"Europe/Moscow",
    "iso:country":"RU",
    "name:nor_x_preferred":[
        "Ragulovo"
    ],
    "name:rus_x_preferred":[
        "\u0420\u0430\u0433\u0443\u043b\u043e\u0432\u043e"
    ],
    "wof:name":"Ragulovo",
    "wof:placetype":"locality"
},
  "geometry": {"coordinates":[28.95987,59.38981],"type":"Point"}
}