{
  "type": "Feature",
  "properties": {
    "gn:admin1_code":"8.0",
    "gn:asciiname":"Gadel'sha",
    "gn:country_code":"RU",
    "gn:dem":444,
    "gn:feature_class":"P",
    "gn:feature_code":"PPL",
    "gn:name":"Gadel\u2019sha",
    "gn:population":0,
    "gn:timezone":"Asia/Yekaterinburg",
    "iso:country":"RU",
    "name:rus_x_preferred":[
        "\u0413\u0430\u0434\u0435\u043b\u044c\u0448\u0430"
    ],
    "name:und_x_variant":[
        "Gadel\u2019shinskiy",
        "Gadil\u2019shina",
        "Gadivshina",
        "Gadel\u2019sha"
    ],
    "wof:name":"Gadel'sha",
    "wof:placetype":"locality"
},
  "geometry": {"coordinates":[58.4675,52.77583000000001],"type":"Point"}
}