{
  "type": "Feature",
  "properties": {
    "gn:admin1_code":"76",
    "gn:asciiname":"Starukhino",
    "gn:country_code":"RU",
    "gn:dem":238,
    "gn:feature_class":"P",
    "gn:feature_code":"PPL",
    "gn:name":"Starukhino",
    "gn:population":0,
    "gn:timezone":"Europe/Moscow",
    "iso:country":"RU",
    "name:rus_x_preferred":[
        "\u0421\u0442\u0430\u0440\u0443\u0445\u0438\u043d\u043e"
    ],
    "name:und_x_variant":[
        "\u0421\u0442\u0430\u0440\u0443\u0445\u0438\u043d\u043e"
    ],
    "wof:name":"Starukhino",
    "wof:placetype":"locality"
},
  "geometry": {"coordinates":[36.71957,53.3808],"type":"Point"}
}