{
  "type": "Feature",
  "properties": {
    "gn:admin1_code":"4",
    "gn:asciiname":"Zimino",
    "gn:country_code":"RU",
    "gn:dem":154,
    "gn:feature_class":"P",
    "gn:feature_code":"PPL",
    "gn:name":"Zimino",
    "gn:population":0,
    "gn:timezone":"Asia/Barnaul",
    "iso:country":"RU",
    "name:eng_x_preferred":[
        "Zimino"
    ],
    "name:nor_x_preferred":[
        "Zimino"
    ],
    "name:rus_x_preferred":[
        "\u0417\u0438\u043c\u0438\u043d\u043e"
    ],
    "name:und_x_variant":[
        "Ziminskoye"
    ],
    "wof:name":"Zimino",
    "wof:placetype":"locality"
},
  "geometry": {"coordinates":[83.17619999999999,52.6335],"type":"Point"}
}