{
  "type": "Feature",
  "properties": {
    "gn:admin1_code":"62",
    "gn:asciiname":"Kaznacheyevka",
    "gn:country_code":"RU",
    "gn:dem":153,
    "gn:feature_class":"P",
    "gn:feature_code":"PPL",
    "gn:name":"Kaznacheyevka",
    "gn:population":0,
    "gn:timezone":"Europe/Moscow",
    "iso:country":"RU",
    "name:rus_x_preferred":[
        "\u041a\u0430\u0437\u043d\u0430\u0447\u0435\u0435\u0432\u043a\u0430"
    ],
    "wof:name":"Kaznacheyevka",
    "wof:placetype":"locality"
},
  "geometry": {"coordinates":[39.47543,53.63399999999999],"type":"Point"}
}