{
  "type": "Feature",
  "properties": {
    "gn:admin1_code":"52",
    "gn:asciiname":"Zaruchev'ye",
    "gn:country_code":"RU",
    "gn:dem":74,
    "gn:feature_class":"P",
    "gn:feature_code":"PPL",
    "gn:name":"Zaruchev\u2019ye",
    "gn:population":0,
    "gn:timezone":"Europe/Moscow",
    "iso:country":"RU",
    "name:rus_x_preferred":[
        "\u0417\u0430\u0440\u0443\u0447\u0435\u0432\u044c\u0435"
    ],
    "name:und_x_variant":[
        "Zaruchev\u2019ye"
    ],
    "wof:name":"Zaruchev'ye",
    "wof:placetype":"locality"
},
  "geometry": {"coordinates":[32.0285,57.43436],"type":"Point"}
}