{
  "type": "Feature",
  "properties": {
    "gn:admin1_code":"60.0",
    "gn:asciiname":"Bel'kava",
    "gn:country_code":"RU",
    "gn:dem":75,
    "gn:feature_class":"P",
    "gn:feature_code":"PPL",
    "gn:name":"Bel\u2019kava",
    "gn:population":0,
    "gn:timezone":"Europe/Moscow",
    "iso:country":"RU",
    "name:nor_x_preferred":[
        "Belkava"
    ],
    "name:rus_x_preferred":[
        "\u0411\u0435\u043b\u044c\u043a\u0430\u0432\u0430"
    ],
    "name:und_x_variant":[
        "Bel\u2019kava"
    ],
    "wof:name":"Bel'kava",
    "wof:placetype":"locality"
},
  "geometry": {"coordinates":[27.96629,57.30253],"type":"Point"}
}