{
  "type": "Feature",
  "properties": {
    "gn:admin1_code":"77",
    "gn:asciiname":"Duplevo",
    "gn:country_code":"RU",
    "gn:dem":142,
    "gn:feature_class":"P",
    "gn:feature_code":"PPL",
    "gn:name":"Duplevo",
    "gn:population":0,
    "gn:timezone":"Europe/Moscow",
    "iso:country":"RU",
    "name:rus_x_preferred":[
        "\u0414\u0443\u043f\u043b\u0435\u0432\u043e"
    ],
    "wof:name":"Duplevo",
    "wof:placetype":"locality"
},
  "geometry": {"coordinates":[37.3138,57.4286],"type":"Point"}
}