{
  "type": "Feature",
  "properties": {
    "gn:admin1_code":"73",
    "gn:asciiname":"Tally-Bulyak",
    "gn:country_code":"RU",
    "gn:dem":321,
    "gn:feature_class":"P",
    "gn:feature_code":"PPL",
    "gn:name":"Tally-Bulyak",
    "gn:population":0,
    "gn:timezone":"Europe/Moscow",
    "iso:country":"RU",
    "name:rus_x_preferred":[
        "\u0422\u0430\u043b\u043b\u044b-\u0411\u0443\u043b\u044f\u043a"
    ],
    "name:und_x_variant":[
        "\u0422\u0430\u043b\u043b\u044b-\u0411\u0443\u043b\u044f\u043a"
    ],
    "wof:name":"Tally-Bulyak",
    "wof:placetype":"locality"
},
  "geometry": {"coordinates":[52.727,54.5684],"type":"Point"}
}