{
  "type": "Feature",
  "properties": {
    "gn:admin1_code":"37",
    "gn:asciiname":"Orlovo",
    "gn:country_code":"RU",
    "gn:dem":93,
    "gn:feature_class":"P",
    "gn:feature_code":"PPL",
    "gn:name":"Orlovo",
    "gn:population":0,
    "gn:timezone":"Europe/Moscow",
    "iso:country":"RU",
    "name:und_x_variant":[
        "Orlova",
        "Orlovo"
    ],
    "wof:name":"Orlovo",
    "wof:placetype":"locality"
},
  "geometry": {"coordinates":[41.00829,58.25791],"type":"Point"}
}