{
  "type": "Feature",
  "properties": {
    "gn:admin1_code":"33",
    "gn:asciiname":"Zaovrag",
    "gn:country_code":"RU",
    "gn:dem":116,
    "gn:feature_class":"P",
    "gn:feature_code":"PPL",
    "gn:name":"Zaovrag",
    "gn:population":0,
    "gn:timezone":"Europe/Kirov",
    "iso:country":"RU",
    "name:rus_x_preferred":[
        "\u0417\u0430\u043e\u0432\u0440\u0430\u0433"
    ],
    "wof:name":"Zaovrag",
    "wof:placetype":"locality"
},
  "geometry": {"coordinates":[49.3232,57.4959],"type":"Point"}
}