{
  "type": "Feature",
  "properties": {
    "gn:admin1_code":"16",
    "gn:asciiname":"Khornoy",
    "gn:country_code":"RU",
    "gn:dem":153,
    "gn:feature_class":"P",
    "gn:feature_code":"PPL",
    "gn:name":"Khornoy",
    "gn:population":0,
    "gn:timezone":"Europe/Moscow",
    "iso:country":"RU",
    "name:rus_x_preferred":[
        "\u0425\u043e\u0440\u043d\u043e\u0439"
    ],
    "name:und_x_variant":[
        "\u0425\u043e\u0440\u043d\u043e\u0439"
    ],
    "wof:name":"Khornoy",
    "wof:placetype":"locality"
},
  "geometry": {"coordinates":[46.73239,55.99155],"type":"Point"}
}