{
  "type": "Feature",
  "properties": {
    "gn:admin1_code":"64",
    "gn:asciiname":"Bukhta",
    "gn:country_code":"RU",
    "gn:dem":-9999,
    "gn:feature_class":"P",
    "gn:feature_code":"PPL",
    "gn:name":"Bukhta",
    "gn:population":0,
    "gn:timezone":"Asia/Magadan",
    "iso:country":"RU",
    "name:rus_x_preferred":[
        "\u0411\u0443\u0445\u0442\u0430"
    ],
    "name:und_x_variant":[
        "Sokiya",
        "Sokitani",
        "Bukhta"
    ],
    "wof:name":"Bukhta",
    "wof:placetype":"locality"
},
  "geometry": {"coordinates":[148.48145,45.38851],"type":"Point"}
}