{
  "type": "Feature",
  "properties": {
    "gn:admin1_code":"10",
    "gn:asciiname":"Poselok Vtoroy",
    "gn:country_code":"RU",
    "gn:dem":206,
    "gn:feature_class":"P",
    "gn:feature_code":"PPL",
    "gn:name":"Pos\u00eblok Vtoroy",
    "gn:population":0,
    "gn:timezone":"Europe/Moscow",
    "iso:country":"RU",
    "name:rus_x_preferred":[
        "\u041f\u043e\u0441\u0451\u043b\u043e\u043a \u0412\u0442\u043e\u0440\u043e\u0439"
    ],
    "name:und_x_variant":[
        "Pos\u00eblok Vtoroy",
        "Pos\u00eblok Nomer Vtoroy"
    ],
    "wof:name":"Poselok Vtoroy",
    "wof:placetype":"locality"
},
  "geometry": {"coordinates":[34.3018,52.0873],"type":"Point"}
}