{
  "type": "Feature",
  "properties": {
    "gn:admin1_code":"76",
    "gn:asciiname":"Kazinki",
    "gn:country_code":"RU",
    "gn:dem":219,
    "gn:feature_class":"P",
    "gn:feature_code":"PPL",
    "gn:name":"Kazinki",
    "gn:population":0,
    "gn:timezone":"Europe/Moscow",
    "iso:country":"RU",
    "name:rus_x_preferred":[
        "\u041a\u0430\u0437\u0438\u043d\u043a\u0438"
    ],
    "name:und_x_variant":[
        "Kozinki",
        "Kazinki",
        "\u041a\u0430\u0437\u0438\u043d\u043a\u0438"
    ],
    "wof:name":"Kazinki",
    "wof:placetype":"locality"
},
  "geometry": {"coordinates":[38.62872,53.60363],"type":"Point"}
}