{
  "type": "Feature",
  "properties": {
    "gn:admin1_code":"63",
    "gn:asciiname":"Khatyngnakh",
    "gn:country_code":"RU",
    "gn:dem":249,
    "gn:feature_class":"P",
    "gn:feature_code":"PPL",
    "gn:name":"Khatyngnakh",
    "gn:population":0,
    "gn:timezone":"Asia/Vladivostok",
    "iso:country":"RU",
    "name:che_x_preferred":[
        "\u0425\u0430\u0442\u044b\u043d\u0433\u043d\u0430\u0445"
    ],
    "name:rus_x_preferred":[
        "\u0425\u0430\u0442\u044b\u043d\u0433\u043d\u0430\u0445"
    ],
    "name:und_x_variant":[
        "Khatynnakh",
        "Khatyngnakh"
    ],
    "wof:name":"Khatyngnakh",
    "wof:placetype":"locality"
},
  "geometry": {"coordinates":[131.83364,66.53041999999999],"type":"Point"}
}