{
  "type": "Feature",
  "properties": {
    "gn:admin1_code":"90",
    "gn:asciiname":"Soyuz",
    "gn:country_code":"RU",
    "gn:dem":126,
    "gn:feature_class":"P",
    "gn:feature_code":"PPL",
    "gn:name":"Soyuz",
    "gn:population":0,
    "gn:timezone":"Asia/Yekaterinburg",
    "iso:country":"RU",
    "name:rus_x_preferred":[
        "\u0421\u043e\u044e\u0437"
    ],
    "wof:name":"Soyuz",
    "wof:placetype":"locality"
},
  "geometry": {"coordinates":[55.4802,56.3622],"type":"Point"}
}