{
  "type": "Feature",
  "properties": {
    "gn:admin1_code":"90",
    "gn:asciiname":"Soyuz",
    "gn:country_code":"RU",
    "gn:dem":126,
    "gn:feature_class":"P",
    "gn:feature_code":"PPL",
    "gn:name":"Soyuz",
    "gn:population":0,
    "gn:timezone":"Asia/Yekaterinburg",
    "iso:country":"RU",
    "name:afr_x_preferred":[
        "Sojoez"
    ],
    "name:ben_x_preferred":[
        "\u09b8\u09af\u09bc\u09c1\u099c"
    ],
    "name:bul_x_preferred":[
        "\u0421\u043e\u044e\u0437"
    ],
    "name:cat_x_preferred":[
        "Soiuz"
    ],
    "name:ces_x_preferred":[
        "Sojuz"
    ],
    "name:chv_x_preferred":[
        "\u0421\u043e\u044e\u0437"
    ],
    "name:deu_x_preferred":[
        "Sojus"
    ],
    "name:epo_x_preferred":[
        "Sojuz"
    ],
    "name:est_x_preferred":[
        "Sojuz"
    ],
    "name:fas_x_preferred":[
        "\u0633\u0627\u06cc\u0648\u0632"
    ],
    "name:fin_x_preferred":[
        "Sojuz"
    ],
    "name:fra_x_preferred":[
        "Soyouz"
    ],
    "name:heb_x_preferred":[
        "\u05e1\u05d5\u05d9\u05d5\u05d6"
    ],
    "name:hun_x_preferred":[
        "Szojuz"
    ],
    "name:ind_x_preferred":[
        "Soyuz"
    ],
    "name:ita_x_preferred":[
        "Sojuz"
    ],
    "name:jpn_x_preferred":[
        "\u30bd\u30e6\u30fc\u30ba"
    ],
    "name:kor_x_preferred":[
        "\uc18c\uc720\uc2a4"
    ],
    "name:lav_x_preferred":[
        "Sojuz"
    ],
    "name:nld_x_preferred":[
        "Sojoez"
    ],
    "name:pol_x_preferred":[
        "Sojuz"
    ],
    "name:ron_x_preferred":[
        "Soiuz"
    ],
    "name:rus_x_preferred":[
        "\u0421\u043e\u044e\u0437"
    ],
    "name:slk_x_preferred":[
        "Sojuz"
    ],
    "name:spa_x_preferred":[
        "Soyuz"
    ],
    "name:srp_x_preferred":[
        "\u0421\u043e\u0458\u0443\u0437"
    ],
    "name:swe_x_preferred":[
        "Sojuz"
    ],
    "name:tha_x_preferred":[
        "\u0e42\u0e0b\u0e22\u0e38\u0e0b"
    ],
    "name:tur_x_preferred":[
        "Soyuz"
    ],
    "name:ukr_x_preferred":[
        "\u0421\u043e\u044e\u0437"
    ],
    "name:vie_x_preferred":[
        "Soyuz"
    ],
    "wof:name":"Soyuz",
    "wof:placetype":"locality"
},
  "geometry": {"coordinates":[55.4802,56.3622],"type":"Point"}
}