{
  "type": "Feature",
  "properties": {
    "gn:admin1_code":"60",
    "gn:asciiname":"Begunovo",
    "gn:country_code":"RU",
    "gn:dem":186,
    "gn:feature_class":"P",
    "gn:feature_code":"PPL",
    "gn:name":"Begunovo",
    "gn:population":0,
    "gn:timezone":"Europe/Moscow",
    "iso:country":"RU",
    "name:rus_x_preferred":[
        "\u0411\u0435\u0433\u0443\u043d\u043e\u0432\u043e"
    ],
    "name:und_x_variant":[
        "\u0411\u0435\u0433\u0443\u043d\u043e\u0432\u043e"
    ],
    "wof:name":"Begunovo",
    "wof:placetype":"locality"
},
  "geometry": {"coordinates":[29.7831,56.0957],"type":"Point"}
}