{
  "type": "Feature",
  "properties": {
    "gn:admin1_code":"20",
    "gn:asciiname":"Kholmogoy",
    "gn:country_code":"RU",
    "gn:dem":463,
    "gn:feature_class":"P",
    "gn:feature_code":"PPL",
    "gn:name":"Kholmogoy",
    "gn:population":0,
    "gn:timezone":"Asia/Irkutsk",
    "iso:country":"RU",
    "name:eng_x_preferred":[
        "Kholmogoy"
    ],
    "name:nor_x_preferred":[
        "Kholmogoj"
    ],
    "name:rus_x_preferred":[
        "\u0425\u043e\u043b\u043c\u043e\u0433\u043e\u0439"
    ],
    "wof:name":"Kholmogoy",
    "wof:placetype":"locality"
},
  "geometry": {"coordinates":[102.3017,53.489],"type":"Point"}
}