{
  "type": "Feature",
  "properties": {
    "gn:admin1_code":"25",
    "gn:asciiname":"Il'icehvka",
    "gn:country_code":"RU",
    "gn:dem":212,
    "gn:feature_class":"P",
    "gn:feature_code":"PPL",
    "gn:name":"Il\u2019ic\u00ebhvka",
    "gn:population":0,
    "gn:timezone":"Europe/Moscow",
    "iso:country":"RU",
    "name:nor_x_preferred":[
        "Ilitsj\u00ebvka"
    ],
    "name:rus_x_preferred":[
        "\u0418\u043b\u044c\u0438\u0447\u0451\u0432\u043a\u0430"
    ],
    "name:und_x_variant":[
        "Il\u2019ic\u00ebhvka"
    ],
    "wof:name":"Il'icehvka",
    "wof:placetype":"locality"
},
  "geometry": {"coordinates":[36.52191,54.98773000000001],"type":"Point"}
}