{
  "type": "Feature",
  "properties": {
    "gn:admin1_code":"86.0",
    "gn:asciiname":"Ushakov",
    "gn:country_code":"RU",
    "gn:dem":197,
    "gn:feature_class":"P",
    "gn:feature_code":"PPL",
    "gn:name":"Ushakov",
    "gn:population":0,
    "gn:timezone":"Europe/Moscow",
    "iso:country":"RU",
    "name:bel_x_preferred":[
        "\u0423\u0448\u0430\u043a\u043e\u045e"
    ],
    "name:deu_x_preferred":[
        "Uschakow"
    ],
    "name:fra_x_preferred":[
        "Ouchakov"
    ],
    "name:ita_x_preferred":[
        "U\u0161akov"
    ],
    "name:kat_x_preferred":[
        "\u10e3\u10e8\u10d0\u10d9\u10dd\u10d5\u10d8"
    ],
    "name:lav_x_preferred":[
        "U\u0161akovs"
    ],
    "name:por_x_preferred":[
        "Ushakov"
    ],
    "name:rus_x_preferred":[
        "\u0423\u0448\u0430\u043a\u043e\u0432"
    ],
    "name:ukr_x_preferred":[
        "\u0423\u0448\u0430\u043a\u043e\u0432"
    ],
    "name:und_x_variant":[
        "Usbakov"
    ],
    "wof:name":"Ushakov",
    "wof:placetype":"locality"
},
  "geometry": {"coordinates":[38.971,50.9265],"type":"Point"}
}