{
  "type": "Feature",
  "properties": {
    "gn:admin1_code":"91",
    "gn:asciiname":"Mokino",
    "gn:country_code":"RU",
    "gn:dem":432,
    "gn:feature_class":"P",
    "gn:feature_code":"PPL",
    "gn:name":"Mokino",
    "gn:population":0,
    "gn:timezone":"Asia/Krasnoyarsk",
    "iso:country":"RU",
    "name:rus_x_preferred":[
        "\u041c\u043e\u043a\u0438\u043d\u043e"
    ],
    "wof:name":"Mokino",
    "wof:placetype":"locality"
},
  "geometry": {"coordinates":[92.95,54.16667],"type":"Point"}
}