{
  "type": "Feature",
  "properties": {
    "gn:admin1_code":"80.0",
    "gn:asciiname":"Oboi",
    "gn:country_code":"RU",
    "gn:dem":256,
    "gn:feature_class":"P",
    "gn:feature_code":"PPL",
    "gn:name":"Oboi",
    "gn:population":0,
    "gn:timezone":"Asia/Yekaterinburg",
    "iso:country":"RU",
    "name:rus_x_preferred":[
        "\u041e\u0431\u043e\u0438"
    ],
    "wof:name":"Oboi",
    "wof:placetype":"locality"
},
  "geometry": {"coordinates":[53.9336,58.1454],"type":"Point"}
}