{
  "type": "Feature",
  "properties": {
    "gn:admin1_code":"80.0",
    "gn:asciiname":"Oboi",
    "gn:country_code":"RU",
    "gn:dem":256,
    "gn:feature_class":"P",
    "gn:feature_code":"PPL",
    "gn:name":"Oboi",
    "gn:population":0,
    "gn:timezone":"Asia/Yekaterinburg",
    "iso:country":"RU",
    "name:fra_x_preferred":[
        "Oboi"
    ],
    "name:ind_x_preferred":[
        "Aobai"
    ],
    "name:jpn_x_preferred":[
        "\u30aa\u30dc\u30a4"
    ],
    "name:kor_x_preferred":[
        "\uad6c\uc648\uac38 \uc624\ubcf4\uc774"
    ],
    "name:nor_x_preferred":[
        "Oboi"
    ],
    "name:rus_x_preferred":[
        "\u041e\u0431\u043e\u0438"
    ],
    "name:swe_x_preferred":[
        "Oboi"
    ],
    "name:tha_x_preferred":[
        "\u0e40\u0e2d\u0e4b\u0e32\u0e44\u0e1b\u0e49"
    ],
    "name:vie_x_preferred":[
        "Ngao B\u00e1i"
    ],
    "wof:name":"Oboi",
    "wof:placetype":"locality"
},
  "geometry": {"coordinates":[53.9336,58.1454],"type":"Point"}
}