{
  "type": "Feature",
  "properties": {
    "gn:admin1_code":"60",
    "gn:asciiname":"Ostrovshchina",
    "gn:country_code":"RU",
    "gn:dem":124,
    "gn:feature_class":"P",
    "gn:feature_code":"PPL",
    "gn:name":"Ostrovshchina",
    "gn:population":0,
    "gn:timezone":"Europe/Moscow",
    "iso:country":"RU",
    "name:rus_x_preferred":[
        "\u041e\u0441\u0442\u0440\u043e\u0432\u0449\u0438\u043d\u0430"
    ],
    "name:und_x_variant":[
        "\u041e\u0441\u0442\u0440\u043e\u0432\u0449\u0438\u043d\u0430"
    ],
    "wof:name":"Ostrovshchina",
    "wof:placetype":"locality"
},
  "geometry": {"coordinates":[30.8421,56.5341],"type":"Point"}
}