{
  "type": "Feature",
  "properties": {
    "gn:admin1_code":"41",
    "gn:asciiname":"Klishino",
    "gn:country_code":"RU",
    "gn:dem":178,
    "gn:feature_class":"P",
    "gn:feature_code":"PPL",
    "gn:name":"Klishino",
    "gn:population":0,
    "gn:timezone":"Europe/Moscow",
    "iso:country":"RU",
    "name:eng_x_preferred":[
        "Klishino"
    ],
    "name:nor_x_preferred":[
        "Klisjino"
    ],
    "name:rus_x_preferred":[
        "\u041a\u043b\u0438\u0448\u0438\u043d\u043e"
    ],
    "name:und_x_variant":[
        "Klishina",
        "\u041a\u043b\u0438\u0448\u0438\u043d\u043e",
        "Klishino"
    ],
    "wof:name":"Klishino",
    "wof:placetype":"locality"
},
  "geometry": {"coordinates":[35.2202,52.2628],"type":"Point"}
}