{
  "type": "Feature",
  "properties": {
    "gn:admin1_code":"61",
    "gn:asciiname":"Novokuznetsov",
    "gn:country_code":"RU",
    "gn:dem":74,
    "gn:feature_class":"P",
    "gn:feature_code":"PPL",
    "gn:name":"Novokuznetsov",
    "gn:population":0,
    "gn:timezone":"Europe/Moscow",
    "iso:country":"RU",
    "name:rus_x_preferred":[
        "\u041d\u043e\u0432\u043e\u043a\u0443\u0437\u043d\u0435\u0446\u043e\u0432"
    ],
    "name:und_x_variant":[
        "Kuznetsov",
        "Novokuznetsov",
        "\u041d\u043e\u0432\u043e\u043a\u0443\u0437\u043d\u0435\u0446\u043e\u0432"
    ],
    "wof:name":"Novokuznetsov",
    "wof:placetype":"locality"
},
  "geometry": {"coordinates":[41.64102000000001,48.60782],"type":"Point"}
}