{
  "type": "Feature",
  "properties": {
    "gn:admin1_code":"81",
    "gn:asciiname":"Semenovskiy",
    "gn:cc2":"RU",
    "gn:country_code":"RU",
    "gn:dem":60,
    "gn:feature_class":"P",
    "gn:feature_code":"PPL",
    "gn:name":"Sem\u00ebnovskiy",
    "gn:population":0,
    "gn:timezone":"Europe/Ulyanovsk",
    "iso:country":"RU",
    "name:rus_x_preferred":[
        "\u0421\u0435\u043c\u0451\u043d\u043e\u0432\u0441\u043a\u0438\u0439"
    ],
    "name:und_x_variant":[
        "Semenovka",
        "Sem\u00ebnovskiy",
        "\u0421\u0435\u043c\u0451\u043d\u043e\u0432\u0441\u043a\u0438\u0439"
    ],
    "wof:name":"Semenovskiy",
    "wof:placetype":"locality"
},
  "geometry": {"coordinates":[49.43333,53.88333000000001],"type":"Point"}
}