{
  "type": "Feature",
  "properties": {
    "gn:admin1_code":"12",
    "gn:asciiname":"Tsentora-Yurt",
    "gn:country_code":"RU",
    "gn:dem":109,
    "gn:feature_class":"P",
    "gn:feature_code":"PPL",
    "gn:name":"Tsentora-Yurt",
    "gn:population":0,
    "gn:timezone":"Europe/Moscow",
    "iso:country":"RU",
    "name:rus_x_preferred":[
        "\u0426\u0435\u043d\u0442\u043e\u0440\u0430-\u042e\u0440\u0442"
    ],
    "name:und_x_variant":[
        "Novyy Tsentoroy"
    ],
    "wof:name":"Tsentora-Yurt",
    "wof:placetype":"locality"
},
  "geometry": {"coordinates":[45.82963,43.31653],"type":"Point"}
}