{
  "type": "Feature",
  "properties": {
    "gn:admin1_code":"8",
    "gn:asciiname":"Staryy Burungut",
    "gn:country_code":"RU",
    "gn:dem":134,
    "gn:feature_class":"P",
    "gn:feature_code":"PPL",
    "gn:name":"Staryy Burungut",
    "gn:population":0,
    "gn:timezone":"Asia/Yekaterinburg",
    "iso:country":"RU",
    "name:rus_x_preferred":[
        "\u0421\u0442\u0430\u0440\u044b\u0439 \u0411\u0443\u0440\u0443\u043d\u0433\u0443\u0442"
    ],
    "name:und_x_variant":[
        "\u0421\u0442\u0430\u0440\u044b\u0439 \u0411\u0443\u0440\u0443\u043d\u0433\u0443\u0442"
    ],
    "wof:name":"Staryy Burungut",
    "wof:placetype":"locality"
},
  "geometry": {"coordinates":[56.96666999999999,55.68333000000001],"type":"Point"}
}