{
  "type": "Feature",
  "properties": {
    "gn:admin1_code":"60.0",
    "gn:asciiname":"Boronovalovo",
    "gn:country_code":"RU",
    "gn:dem":166,
    "gn:feature_class":"P",
    "gn:feature_code":"PPL",
    "gn:name":"Boronovalovo",
    "gn:population":0,
    "gn:timezone":"Europe/Moscow",
    "iso:country":"RU",
    "name:rus_x_preferred":[
        "\u0411\u043e\u0440\u043e\u043d\u043e\u0432\u0430\u043b\u043e\u0432\u043e"
    ],
    "name:und_x_variant":[
        "Bornovalovo",
        "Boronovalovo",
        "\u0411\u043e\u0440\u043e\u043d\u043e\u0432\u0430\u043b\u043e\u0432\u043e"
    ],
    "wof:name":"Boronovalovo",
    "wof:placetype":"locality"
},
  "geometry": {"coordinates":[30.63195,55.76071999999999],"type":"Point"}
}