{
  "type": "Feature",
  "properties": {
    "gn:admin1_code":"85",
    "gn:asciiname":"Chernitsyno",
    "gn:country_code":"RU",
    "gn:dem":150,
    "gn:feature_class":"P",
    "gn:feature_code":"PPL",
    "gn:name":"Chernitsyno",
    "gn:population":0,
    "gn:timezone":"Europe/Moscow",
    "iso:country":"RU",
    "name:rus_x_preferred":[
        "\u0427\u0435\u0440\u043d\u0438\u0446\u044b\u043d\u043e"
    ],
    "wof:name":"Chernitsyno",
    "wof:placetype":"locality"
},
  "geometry": {"coordinates":[38.8448,59.6257],"type":"Point"}
}