{
  "type": "Feature",
  "properties": {
    "gn:admin1_code":"53",
    "gn:asciiname":"Novovoskresenka",
    "gn:country_code":"RU",
    "gn:dem":208,
    "gn:feature_class":"P",
    "gn:feature_code":"PPL",
    "gn:name":"Novovoskresenka",
    "gn:population":0,
    "gn:timezone":"Asia/Novosibirsk",
    "iso:country":"RU",
    "name:eng_x_preferred":[
        "Novovoskresenka"
    ],
    "name:nor_x_preferred":[
        "Novovoskresenka"
    ],
    "name:rus_x_preferred":[
        "\u041d\u043e\u0432\u043e\u0432\u043e\u0441\u043a\u0440\u0435\u0441\u0435\u043d\u043a\u0430"
    ],
    "name:und_x_variant":[
        "Novo-Voskresenskaya"
    ],
    "wof:name":"Novovoskresenka",
    "wof:placetype":"locality"
},
  "geometry": {"coordinates":[83.0549,54.0928],"type":"Point"}
}