{
  "type": "Feature",
  "properties": {
    "gn:admin1_code":"10",
    "gn:asciiname":"Pchela-Kommuna",
    "gn:country_code":"RU",
    "gn:dem":174,
    "gn:feature_class":"P",
    "gn:feature_code":"PPL",
    "gn:name":"Pchela-Kommuna",
    "gn:population":0,
    "gn:timezone":"Europe/Moscow",
    "iso:country":"RU",
    "name:rus_x_preferred":[
        "\u041f\u0447\u0435\u043b\u0430-\u041a\u043e\u043c\u043c\u0443\u043d\u0430"
    ],
    "name:und_x_variant":[
        "Pchela",
        "Pchela-Kommuna",
        "\u041f\u0447\u0435\u043b\u0430-\u041a\u043e\u043c\u043c\u0443\u043d\u0430"
    ],
    "wof:name":"Pchela-Kommuna",
    "wof:placetype":"locality"
},
  "geometry": {"coordinates":[34.47588,52.5297],"type":"Point"}
}