{
  "type": "Feature",
  "properties": {
    "gn:admin1_code":"51.0",
    "gn:asciiname":"Marmyzhevo",
    "gn:country_code":"RU",
    "gn:dem":97,
    "gn:feature_class":"P",
    "gn:feature_code":"PPL",
    "gn:name":"Marmyzhevo",
    "gn:population":0,
    "gn:timezone":"Europe/Moscow",
    "iso:country":"RU",
    "name:nor_x_preferred":[
        "Marmyzjevo"
    ],
    "name:rus_x_preferred":[
        "\u041c\u0430\u0440\u043c\u044b\u0436\u0435\u0432\u043e"
    ],
    "wof:name":"Marmyzhevo",
    "wof:placetype":"locality"
},
  "geometry": {"coordinates":[43.37266,56.93845],"type":"Point"}
}