{
  "type": "Feature",
  "properties": {
    "gn:admin1_code":"28",
    "gn:asciiname":"Krasnaya Rechka",
    "gn:cc2":"RU",
    "gn:country_code":"RU",
    "gn:dem":49,
    "gn:feature_class":"P",
    "gn:feature_code":"PPL",
    "gn:name":"Krasnaya Rechka",
    "gn:population":0,
    "gn:timezone":"Europe/Moscow",
    "iso:country":"RU",
    "name:fin_x_preferred":[
        "Sakarvaoja"
    ],
    "name:rus_x_preferred":[
        "\u041a\u0440\u0430\u0441\u043d\u0430\u044f \u0420\u0435\u0447\u043a\u0430"
    ],
    "name:und_x_variant":[
        "Krasnaya Rachka",
        "Krasnyy Pakhar",
        "Krasnaya Rechka",
        "\u041a\u0440\u0430\u0441\u043d\u0430\u044f \u0420\u0435\u0447\u043a\u0430"
    ],
    "wof:name":"Krasnaya Rechka",
    "wof:placetype":"locality"
},
  "geometry": {"coordinates":[33.75,62.43333000000001],"type":"Point"}
}