{
  "type": "Feature",
  "properties": {
    "gn:admin1_code":"6",
    "gn:asciiname":"Isakovskaya",
    "gn:country_code":"RU",
    "gn:dem":40,
    "gn:feature_class":"P",
    "gn:feature_code":"PPL",
    "gn:name":"Isakovskaya",
    "gn:population":0,
    "gn:timezone":"Europe/Moscow",
    "iso:country":"RU",
    "name:eng_x_preferred":[
        "Isakovskaya"
    ],
    "name:nor_x_preferred":[
        "Isakovskaja"
    ],
    "name:rus_x_preferred":[
        "\u0418\u0441\u0430\u043a\u043e\u0432\u0441\u043a\u0430\u044f"
    ],
    "name:tgk_x_preferred":[
        "\u0418\u0441\u0430\u043a\u043e\u0432\u0441\u043a\u0430\u044f"
    ],
    "name:und_x_variant":[
        "\u0418\u0441\u0430\u043a\u043e\u0432\u0441\u043a\u0430\u044f",
        "Isakovskaya"
    ],
    "wof:name":"Isakovskaya",
    "wof:placetype":"locality"
},
  "geometry": {"coordinates":[44.7711,62.255],"type":"Point"}
}