{
  "type": "Feature",
  "properties": {
    "gn:admin1_code":"88.0",
    "gn:asciiname":"Sluda",
    "gn:country_code":"RU",
    "gn:dem":161,
    "gn:feature_class":"P",
    "gn:feature_code":"PPL",
    "gn:name":"Sluda",
    "gn:population":0,
    "gn:timezone":"Europe/Moscow",
    "iso:country":"RU",
    "name:rus_x_preferred":[
        "\u0421\u043b\u0443\u0434\u0430"
    ],
    "name:und_x_variant":[
        "\u0421\u043b\u0443\u0434\u0430"
    ],
    "wof:name":"Sluda",
    "wof:placetype":"locality"
},
  "geometry": {"coordinates":[40.1903,58.5215],"type":"Point"}
}