{
  "type": "Feature",
  "properties": {
    "gn:admin1_code":"8.0",
    "gn:asciiname":"Abdrakhimovo",
    "gn:country_code":"RU",
    "gn:dem":197,
    "gn:feature_class":"P",
    "gn:feature_code":"PPL",
    "gn:name":"Abdrakhimovo",
    "gn:population":0,
    "gn:timezone":"Asia/Yekaterinburg",
    "iso:country":"RU",
    "name:bak_x_preferred":[
        "\u04d8\u0431\u0434\u0440\u04d9\u0445\u0438\u043c"
    ],
    "name:che_x_preferred":[
        "\u0410\u0431\u0434\u0440\u0430\u0445\u0438\u043c\u043e\u0432\u043e"
    ],
    "name:chv_x_preferred":[
        "\u0410\u0431\u0434\u0440\u0430\u0445\u0438\u043c"
    ],
    "name:eng_x_preferred":[
        "Abdrakhimovo"
    ],
    "name:hye_x_preferred":[
        "\u0531\u0562\u0564\u0580\u0561\u056d\u056b\u0574\u0578\u057e\u0578"
    ],
    "name:kaz_x_preferred":[
        "\u04d8\u0431\u0434\u0440\u0430\u0445\u0438\u043c"
    ],
    "name:kir_x_preferred":[
        "\u0410\u0431\u0434\u0440\u0430\u0445\u0438\u043c"
    ],
    "name:nor_x_preferred":[
        "Abdrakhimovo"
    ],
    "name:rus_x_preferred":[
        "\u0410\u0431\u0434\u0440\u0430\u0445\u0438\u043c\u043e\u0432\u043e"
    ],
    "name:tat_x_preferred":[
        "\u0413\u0430\u0431\u0434\u0440\u04d9\u0445\u0438\u043c"
    ],
    "name:ukr_x_preferred":[
        "\u0410\u0431\u0434\u0440\u0430\u0445\u0438\u043c\u043e\u0432\u0435"
    ],
    "name:und_x_variant":[
        "Abdrakhimova",
        "\u0410\u0431\u0434\u0440\u0430\u0445\u0438\u043c\u043e\u0432\u043e",
        "Abdrakhimovo"
    ],
    "wof:name":"Abdrakhimovo",
    "wof:placetype":"locality"
},
  "geometry": {"coordinates":[58.32167,55.82583],"type":"Point"}
}