{
  "type": "Feature",
  "properties": {
    "gn:admin1_code":"8.0",
    "gn:asciiname":"Biginyayevo",
    "gn:country_code":"RU",
    "gn:dem":128,
    "gn:feature_class":"P",
    "gn:feature_code":"PPL",
    "gn:name":"Biginyayevo",
    "gn:population":0,
    "gn:timezone":"Asia/Yekaterinburg",
    "iso:country":"RU",
    "name:bak_x_preferred":[
        "\u0411\u0438\u0433\u04d9\u043d\u04d9\u0439"
    ],
    "name:che_x_preferred":[
        "\u0411\u0438\u0433\u0438\u043d\u044f\u0435\u0432\u043e"
    ],
    "name:hye_x_preferred":[
        "\u0532\u056b\u0563\u056b\u0576\u0575\u0561\u0587\u0578"
    ],
    "name:kaz_x_preferred":[
        "\u0411\u0438\u0433\u0438\u043d\u044f"
    ],
    "name:kir_x_preferred":[
        "\u0411\u0438\u0433\u0438\u043d\u044f"
    ],
    "name:rus_x_preferred":[
        "\u0411\u0438\u0433\u0438\u043d\u044f\u0435\u0432\u043e"
    ],
    "name:tat_x_preferred":[
        "\u0411\u0438\u0433\u04d9\u043d\u04d9\u0439"
    ],
    "name:und_x_variant":[
        "Biganey",
        "Biginyayevo"
    ],
    "wof:name":"Biginyayevo",
    "wof:placetype":"locality"
},
  "geometry": {"coordinates":[55.14443000000001,55.75824],"type":"Point"}
}