{
  "type": "Feature",
  "properties": {
    "gn:admin1_code":"29",
    "gn:asciiname":"Staryy Tyazhin",
    "gn:country_code":"RU",
    "gn:dem":181,
    "gn:feature_class":"P",
    "gn:feature_code":"PPL",
    "gn:name":"Staryy Tyazhin",
    "gn:population":0,
    "gn:timezone":"Asia/Novokuznetsk",
    "iso:country":"RU",
    "name:eng_x_preferred":[
        "Staryy Tyazhin"
    ],
    "name:nor_x_preferred":[
        "Star.Tjazjin"
    ],
    "name:rus_x_preferred":[
        "\u0421\u0442\u0430\u0440.\u0422\u044f\u0436\u0438\u043d"
    ],
    "name:rus_x_variant":[
        "\u0421\u0442\u0430\u0440\u044b\u0439 \u0422\u044f\u0436\u0438\u043d"
    ],
    "wof:name":"Staryy Tyazhin",
    "wof:placetype":"locality"
},
  "geometry": {"coordinates":[88.57028000000003,56.13746],"type":"Point"}
}