{
  "type": "Feature",
  "properties": {
    "gn:admin1_code":"52",
    "gn:asciiname":"Klenka",
    "gn:country_code":"RU",
    "gn:dem":60,
    "gn:feature_class":"P",
    "gn:feature_code":"PPL",
    "gn:name":"Klenka",
    "gn:population":0,
    "gn:timezone":"Europe/Moscow",
    "iso:country":"RU",
    "name:rus_x_preferred":[
        "\u041a\u043b\u0435\u043d\u043a\u0430"
    ],
    "wof:name":"Klenka",
    "wof:placetype":"locality"
},
  "geometry": {"coordinates":[32.1462,57.6773],"type":"Point"}
}