{
  "type": "Feature",
  "properties": {
    "gn:admin1_code":"52",
    "gn:asciiname":"Pokrovka",
    "gn:country_code":"RU",
    "gn:dem":95,
    "gn:feature_class":"P",
    "gn:feature_code":"PPL",
    "gn:name":"Pokrovka",
    "gn:population":0,
    "gn:timezone":"Europe/Moscow",
    "iso:country":"RU",
    "name:rus_x_preferred":[
        "\u041f\u043e\u043a\u0440\u043e\u0432\u043a\u0430"
    ],
    "wof:name":"Pokrovka",
    "wof:placetype":"locality"
},
  "geometry": {"coordinates":[32.54034,57.61887],"type":"Point"}
}