{
  "type": "Feature",
  "properties": {
    "gn:admin1_code":"42",
    "gn:asciiname":"Krasnoarmeyskoye",
    "gn:country_code":"RU",
    "gn:dem":30,
    "gn:feature_class":"P",
    "gn:feature_code":"PPL",
    "gn:name":"Krasnoarmeyskoye",
    "gn:population":0,
    "gn:timezone":"Europe/Moscow",
    "iso:country":"RU",
    "name:fin_x_preferred":[
        "Tiitua"
    ],
    "name:rus_x_preferred":[
        "\u041a\u0440\u0430\u0441\u043d\u043e\u0430\u0440\u043c\u0435\u0439\u0441\u043a\u043e\u0435"
    ],
    "name:und_x_variant":[
        "Tiytua",
        "Krasnoarmeyskoye",
        "\u041a\u0440\u0430\u0441\u043d\u043e\u0430\u0440\u043c\u0435\u0439\u0441\u043a\u043e\u0435"
    ],
    "wof:name":"Krasnoarmeyskoye",
    "wof:placetype":"locality"
},
  "geometry": {"coordinates":[30.05637,60.75433],"type":"Point"}
}