{
  "type": "Feature",
  "properties": {
    "gn:admin1_code":"37",
    "gn:asciiname":"Zhilotovo",
    "gn:country_code":"RU",
    "gn:dem":180,
    "gn:feature_class":"P",
    "gn:feature_code":"PPL",
    "gn:name":"Zhilotovo",
    "gn:population":0,
    "gn:timezone":"Europe/Moscow",
    "iso:country":"RU",
    "name:rus_x_preferred":[
        "\u0416\u0438\u043b\u043e\u0442\u043e\u0432\u043e"
    ],
    "wof:name":"Zhilotovo",
    "wof:placetype":"locality"
},
  "geometry": {"coordinates":[42.401,58.3412],"type":"Point"}
}