{
  "type": "Feature",
  "properties": {
    "gn:admin1_code":"25",
    "gn:asciiname":"Kudinovo",
    "gn:country_code":"RU",
    "gn:dem":193,
    "gn:feature_class":"P",
    "gn:feature_code":"PPL",
    "gn:name":"Kudinovo",
    "gn:population":0,
    "gn:timezone":"Europe/Moscow",
    "iso:country":"RU",
    "name:nor_x_preferred":[
        "Kudinovo"
    ],
    "name:rus_x_preferred":[
        "\u041a\u0443\u0434\u0438\u043d\u043e\u0432\u043e"
    ],
    "wof:name":"Kudinovo",
    "wof:placetype":"locality"
},
  "geometry": {"coordinates":[36.63773,54.81763],"type":"Point"}
}