{
  "type": "Feature",
  "properties": {
    "gn:admin1_code":"42",
    "gn:asciiname":"Gukkalovo",
    "gn:country_code":"RU",
    "gn:dem":71,
    "gn:feature_class":"P",
    "gn:feature_code":"PPL",
    "gn:name":"Gukkalovo",
    "gn:population":0,
    "gn:timezone":"Europe/Moscow",
    "iso:country":"RU",
    "name:rus_x_preferred":[
        "\u0413\u0443\u043a\u043a\u0430\u043b\u043e\u0432\u043e"
    ],
    "wof:name":"Gukkalovo",
    "wof:placetype":"locality"
},
  "geometry": {"coordinates":[30.35,59.66667],"type":"Point"}
}