{
  "type": "Feature",
  "properties": {
    "gn:admin1_code":"80",
    "gn:asciiname":"Kamennyy Klyuch",
    "gn:country_code":"RU",
    "gn:dem":181,
    "gn:feature_class":"P",
    "gn:feature_code":"PPL",
    "gn:name":"Kamennyy Klyuch",
    "gn:population":0,
    "gn:timezone":"Europe/Samara",
    "iso:country":"RU",
    "name:rus_x_preferred":[
        "\u041a\u0430\u043c\u0435\u043d\u043d\u044b\u0439 \u041a\u043b\u044e\u0447"
    ],
    "name:und_x_variant":[
        "Zyazlud-Kaksya",
        "Kamennyy Klyuch"
    ],
    "wof:name":"Kamennyy Klyuch",
    "wof:placetype":"locality"
},
  "geometry": {"coordinates":[52.17133,56.81921],"type":"Point"}
}