{
  "type": "Feature",
  "properties": {
    "gn:admin1_code":"53",
    "gn:asciiname":"Novopokrovskiy",
    "gn:cc2":"RU",
    "gn:country_code":"RU",
    "gn:dem":283,
    "gn:feature_class":"P",
    "gn:feature_code":"PPL",
    "gn:name":"Novopokrovskiy",
    "gn:population":0,
    "gn:timezone":"Asia/Novosibirsk",
    "iso:country":"RU",
    "name:rus_x_preferred":[
        "\u041d\u043e\u0432\u043e\u043f\u043e\u043a\u0440\u043e\u0432\u0441\u043a\u0438\u0439"
    ],
    "name:und_x_variant":[
        "Pokrovskiy",
        "Novopokrovskiy",
        "\u041d\u043e\u0432\u043e\u043f\u043e\u043a\u0440\u043e\u0432\u0441\u043a\u0438\u0439"
    ],
    "wof:name":"Novopokrovskiy",
    "wof:placetype":"locality"
},
  "geometry": {"coordinates":[82.68333,54.28333000000001],"type":"Point"}
}