{
  "type": "Feature",
  "properties": {
    "gn:admin1_code":"10",
    "gn:asciiname":"Zelikiny",
    "gn:country_code":"RU",
    "gn:dem":200,
    "gn:feature_class":"P",
    "gn:feature_code":"PPL",
    "gn:name":"Zelikiny",
    "gn:population":0,
    "gn:timezone":"Europe/Moscow",
    "iso:country":"RU",
    "wof:name":"Zelikiny",
    "wof:placetype":"locality"
},
  "geometry": {"coordinates":[33.48305999999999,53.47472],"type":"Point"}
}