{
  "type": "Feature",
  "properties": {
    "gn:admin1_code":"85",
    "gn:asciiname":"Yaskino",
    "gn:country_code":"RU",
    "gn:dem":165,
    "gn:feature_class":"P",
    "gn:feature_code":"PPL",
    "gn:name":"Yaskino",
    "gn:population":0,
    "gn:timezone":"Europe/Moscow",
    "iso:country":"RU",
    "name:rus_x_preferred":[
        "\u042f\u0441\u043a\u0438\u043d\u043e"
    ],
    "wof:name":"Yaskino",
    "wof:placetype":"locality"
},
  "geometry": {"coordinates":[39.35993,59.16816],"type":"Point"}
}