{
  "type": "Feature",
  "properties": {
    "gn:admin1_code":"51.0",
    "gn:asciiname":"Borkovka",
    "gn:country_code":"RU",
    "gn:dem":103,
    "gn:feature_class":"P",
    "gn:feature_code":"PPL",
    "gn:name":"Borkovka",
    "gn:population":0,
    "gn:timezone":"Europe/Moscow",
    "iso:country":"RU",
    "name:nor_x_preferred":[
        "Barkovka"
    ],
    "name:rus_x_preferred":[
        "\u0411\u043e\u0440\u043a\u043e\u0432\u043a\u0430"
    ],
    "name:und_x_variant":[
        "Barkovka",
        "Borkovka"
    ],
    "wof:name":"Borkovka",
    "wof:placetype":"locality"
},
  "geometry": {"coordinates":[42.1074,55.303],"type":"Point"}
}