{
  "type": "Feature",
  "properties": {
    "gn:admin1_code":"4",
    "gn:asciiname":"Sadovyy",
    "gn:country_code":"RU",
    "gn:dem":318,
    "gn:feature_class":"P",
    "gn:feature_code":"PPL",
    "gn:name":"Sadovyy",
    "gn:population":0,
    "gn:timezone":"Asia/Barnaul",
    "iso:country":"RU",
    "name:eng_x_preferred":[
        "Sadovyy"
    ],
    "name:nor_x_preferred":[
        "Sadovyj"
    ],
    "name:rus_x_preferred":[
        "\u0421\u0430\u0434\u043e\u0432\u044b\u0439"
    ],
    "name:und_x_variant":[
        "\u0421\u0430\u0434\u043e\u0432\u044b\u0439",
        "Sadovyy"
    ],
    "wof:name":"Sadovyy",
    "wof:placetype":"locality"
},
  "geometry": {"coordinates":[81.92028000000001,50.98278],"type":"Point"}
}