{
  "type": "Feature",
  "properties": {
    "gn:admin1_code":"33.0",
    "gn:asciiname":"Bezdenezhnyye",
    "gn:country_code":"RU",
    "gn:dem":118,
    "gn:feature_class":"P",
    "gn:feature_code":"PPL",
    "gn:name":"Bezdenezhnyye",
    "gn:population":0,
    "gn:timezone":"Europe/Kirov",
    "iso:country":"RU",
    "name:nor_x_preferred":[
        "Bezdenezjnye"
    ],
    "name:rus_x_preferred":[
        "\u0411\u0435\u0437\u0434\u0435\u043d\u0435\u0436\u043d\u044b\u0435"
    ],
    "wof:name":"Bezdenezhnyye",
    "wof:placetype":"locality"
},
  "geometry": {"coordinates":[48.28355,58.05463],"type":"Point"}
}