{
  "type": "Feature",
  "properties": {
    "gn:admin1_code":"33.0",
    "gn:asciiname":"Osart",
    "gn:country_code":"RU",
    "gn:dem":128,
    "gn:feature_class":"P",
    "gn:feature_code":"PPL",
    "gn:name":"Osart",
    "gn:population":0,
    "gn:timezone":"Europe/Kirov",
    "iso:country":"RU",
    "name:rus_x_preferred":[
        "\u041e\u0441\u0430\u0440\u0442"
    ],
    "name:und_x_variant":[
        "\u041e\u0441\u0430\u0440\u0442"
    ],
    "wof:name":"Osart",
    "wof:placetype":"locality"
},
  "geometry": {"coordinates":[49.95291,59.12635],"type":"Point"}
}