{
  "type": "Feature",
  "properties": {
    "gn:admin1_code":"78",
    "gn:asciiname":"Yelovka",
    "gn:country_code":"RU",
    "gn:dem":82,
    "gn:feature_class":"P",
    "gn:feature_code":"PPL",
    "gn:name":"Yelovka",
    "gn:population":0,
    "gn:timezone":"Asia/Yekaterinburg",
    "iso:country":"RU",
    "name:eng_x_preferred":[
        "Yelovka"
    ],
    "name:nor_x_preferred":[
        "Jelovka"
    ],
    "name:rus_x_preferred":[
        "\u0415\u043b\u043e\u0432\u043a\u0430"
    ],
    "wof:name":"Yelovka",
    "wof:placetype":"locality"
},
  "geometry": {"coordinates":[70.92270000000001,57.2222],"type":"Point"}
}