{
  "type": "Feature",
  "properties": {
    "gn:admin1_code":"52",
    "gn:asciiname":"Shlino",
    "gn:country_code":"RU",
    "gn:dem":186,
    "gn:feature_class":"P",
    "gn:feature_code":"PPL",
    "gn:name":"Shlino",
    "gn:population":0,
    "gn:timezone":"Europe/Moscow",
    "iso:country":"RU",
    "name:rus_x_preferred":[
        "\u0428\u043b\u0438\u043d\u043e"
    ],
    "wof:name":"Shlino",
    "wof:placetype":"locality"
},
  "geometry": {"coordinates":[33.11667,58.23333],"type":"Point"}
}