{
  "type": "Feature",
  "properties": {
    "gn:admin1_code":"73",
    "gn:asciiname":"Zmeyevo",
    "gn:country_code":"RU",
    "gn:dem":94,
    "gn:feature_class":"P",
    "gn:feature_code":"PPL",
    "gn:name":"Zmeyevo",
    "gn:population":0,
    "gn:timezone":"Europe/Moscow",
    "iso:country":"RU",
    "name:rus_x_preferred":[
        "\u0417\u043c\u0435\u0435\u0432\u043e"
    ],
    "name:und_x_variant":[
        "Zmiyevo",
        "Zmeyevo"
    ],
    "wof:name":"Zmeyevo",
    "wof:placetype":"locality"
},
  "geometry": {"coordinates":[50.7249,55.39578],"type":"Point"}
}