{
  "type": "Feature",
  "properties": {
    "gn:admin1_code":"72",
    "gn:asciiname":"Serebryakovka",
    "gn:country_code":"RU",
    "gn:dem":126,
    "gn:feature_class":"P",
    "gn:feature_code":"PPL",
    "gn:name":"Serebryakovka",
    "gn:population":0,
    "gn:timezone":"Europe/Moscow",
    "iso:country":"RU",
    "name:rus_x_preferred":[
        "\u0421\u0435\u0440\u0435\u0431\u0440\u044f\u043a\u043e\u0432\u043a\u0430"
    ],
    "name:und_x_variant":[
        "Serebryakovo",
        "Serebryakoyka",
        "Serebryaki",
        "Serebryakovka"
    ],
    "wof:name":"Serebryakovka",
    "wof:placetype":"locality"
},
  "geometry": {"coordinates":[41.32399,52.52244],"type":"Point"}
}