{
  "type": "Feature",
  "properties": {
    "gn:admin1_code":"88.0",
    "gn:asciiname":"Dor-Lukonino",
    "gn:country_code":"RU",
    "gn:dem":126,
    "gn:feature_class":"P",
    "gn:feature_code":"PPL",
    "gn:name":"Dor-Lukonino",
    "gn:population":0,
    "gn:timezone":"Europe/Moscow",
    "iso:country":"RU",
    "name:rus_x_preferred":[
        "\u0414\u043e\u0440-\u041b\u0443\u043a\u043e\u043d\u0438\u043d\u043e"
    ],
    "wof:name":"Dor-Lukonino",
    "wof:placetype":"locality"
},
  "geometry": {"coordinates":[40.29949000000001,58.36124],"type":"Point"}
}