{
  "type": "Feature",
  "properties": {
    "gn:admin1_code":"60",
    "gn:asciiname":"Peskovo",
    "gn:country_code":"RU",
    "gn:dem":71,
    "gn:feature_class":"P",
    "gn:feature_code":"PPL",
    "gn:name":"Peskovo",
    "gn:population":0,
    "gn:timezone":"Europe/Moscow",
    "iso:country":"RU",
    "name:rus_x_preferred":[
        "\u041f\u0435\u0441\u043a\u043e\u0432\u043e"
    ],
    "wof:name":"Peskovo",
    "wof:placetype":"locality"
},
  "geometry": {"coordinates":[28.10997,57.16739000000001],"type":"Point"}
}