{
  "type": "Feature",
  "properties": {
    "gn:admin1_code":"63",
    "gn:asciiname":"Yekyuchchyu",
    "gn:country_code":"RU",
    "gn:dem":205,
    "gn:feature_class":"P",
    "gn:feature_code":"PPL",
    "gn:name":"Yekyuchchyu",
    "gn:population":0,
    "gn:timezone":"Asia/Vladivostok",
    "iso:country":"RU",
    "name:eng_x_preferred":[
        "Yekyuchchyu"
    ],
    "name:nor_x_preferred":[
        "Okjutsjtsju"
    ],
    "name:rus_x_preferred":[
        "\u041e\u043a\u044e\u0447\u0447\u044e"
    ],
    "name:und_x_variant":[
        "Khonu-Okyuchchu",
        "Khonu"
    ],
    "wof:name":"Yekyuchchyu",
    "wof:placetype":"locality"
},
  "geometry": {"coordinates":[131.62472,66.76606],"type":"Point"}
}