{
  "type": "Feature",
  "properties": {
    "gn:admin1_code":"33.0",
    "gn:asciiname":"Kuliga",
    "gn:country_code":"RU",
    "gn:dem":145,
    "gn:feature_class":"P",
    "gn:feature_code":"PPL",
    "gn:name":"Kuliga",
    "gn:population":0,
    "gn:timezone":"Europe/Kirov",
    "iso:country":"RU",
    "name:rus_x_preferred":[
        "\u041a\u0443\u043b\u0438\u0433\u0430"
    ],
    "name:und_x_variant":[
        "\u041a\u0443\u043b\u0438\u0433\u0430"
    ],
    "wof:name":"Kuliga",
    "wof:placetype":"locality"
},
  "geometry": {"coordinates":[50.1787,58.9709],"type":"Point"}
}