{
  "type": "Feature",
  "properties": {
    "gn:admin1_code":"84",
    "gn:asciiname":"Yegorovskiy",
    "gn:country_code":"RU",
    "gn:dem":104,
    "gn:feature_class":"P",
    "gn:feature_code":"PPL",
    "gn:name":"Yegorovskiy",
    "gn:population":0,
    "gn:timezone":"Europe/Volgograd",
    "iso:country":"RU",
    "name:rus_x_preferred":[
        "\u0415\u0433\u043e\u0440\u043e\u0432\u0441\u043a\u0438\u0439"
    ],
    "wof:name":"Yegorovskiy",
    "wof:placetype":"locality"
},
  "geometry": {"coordinates":[41.7386,50.8549],"type":"Point"}
}