{
  "type": "Feature",
  "properties": {
    "gn:admin1_code":"24.0",
    "gn:asciiname":"Burgusta",
    "gn:country_code":"RU",
    "gn:dem":129,
    "gn:feature_class":"P",
    "gn:feature_code":"PPL",
    "gn:name":"Burgusta",
    "gn:population":0,
    "gn:timezone":"Europe/Moscow",
    "iso:country":"RU",
    "name:rus_x_preferred":[
        "\u0411\u0443\u0440\u0433\u0443\u0441\u0442\u0430"
    ],
    "name:und_x_variant":[
        "Lozovoy",
        "Khutora Burgustinskiye",
        "Burgusta"
    ],
    "wof:name":"Burgusta",
    "wof:placetype":"locality"
},
  "geometry": {"coordinates":[44.0647,46.2914],"type":"Point"}
}