{
  "type": "Feature",
  "properties": {
    "gn:admin1_code":"62",
    "gn:asciiname":"Mar'inka",
    "gn:country_code":"RU",
    "gn:dem":168,
    "gn:feature_class":"P",
    "gn:feature_code":"PPL",
    "gn:name":"Mar\u2019inka",
    "gn:population":0,
    "gn:timezone":"Europe/Moscow",
    "iso:country":"RU",
    "name:rus_x_preferred":[
        "\u041c\u0430\u0440\u044c\u0438\u043d\u043a\u0430"
    ],
    "name:und_x_variant":[
        "Mar\u2019inka",
        "\u041c\u0430\u0440\u044c\u0438\u043d\u043a\u0430"
    ],
    "wof:name":"Mar'inka",
    "wof:placetype":"locality"
},
  "geometry": {"coordinates":[40.41667,53.41667],"type":"Point"}
}