{
  "type": "Feature",
  "properties": {
    "gn:admin1_code":"60",
    "gn:asciiname":"Khoroshaya",
    "gn:country_code":"RU",
    "gn:dem":73,
    "gn:feature_class":"P",
    "gn:feature_code":"PPL",
    "gn:name":"Khoroshaya",
    "gn:population":0,
    "gn:timezone":"Europe/Moscow",
    "iso:country":"RU",
    "name:rus_x_preferred":[
        "\u0425\u043e\u0440\u043e\u0448\u0430\u044f"
    ],
    "wof:name":"Khoroshaya",
    "wof:placetype":"locality"
},
  "geometry": {"coordinates":[28.749,57.32289],"type":"Point"}
}