{
  "type": "Feature",
  "properties": {
    "gn:admin1_code":"29",
    "gn:asciiname":"Morkovkino",
    "gn:country_code":"RU",
    "gn:dem":121,
    "gn:feature_class":"P",
    "gn:feature_code":"PPL",
    "gn:name":"Morkovkino",
    "gn:population":0,
    "gn:timezone":"Asia/Novokuznetsk",
    "iso:country":"RU",
    "name:rus_x_preferred":[
        "\u041c\u043e\u0440\u043a\u043e\u0432\u043a\u0438\u043d\u043e"
    ],
    "wof:name":"Morkovkino",
    "wof:placetype":"locality"
},
  "geometry": {"coordinates":[85.6174,55.7089],"type":"Point"}
}