{
  "type": "Feature",
  "properties": {
    "gn:admin1_code":"67.0",
    "gn:asciiname":"Gagarino",
    "gn:country_code":"RU",
    "gn:dem":212,
    "gn:feature_class":"P",
    "gn:feature_code":"PPL",
    "gn:name":"Gagarino",
    "gn:population":0,
    "gn:timezone":"Europe/Saratov",
    "iso:country":"RU",
    "name:eng_x_preferred":[
        "Gagarino"
    ],
    "name:nor_x_preferred":[
        "Gagarino"
    ],
    "name:rus_x_preferred":[
        "\u0413\u0430\u0433\u0430\u0440\u0438\u043d\u043e"
    ],
    "name:und_x_variant":[
        "\u0413\u0430\u0433\u0430\u0440\u0438\u043d\u043e",
        "Gagarino"
    ],
    "wof:name":"Gagarino",
    "wof:placetype":"locality"
},
  "geometry": {"coordinates":[43.92491,52.00082],"type":"Point"}
}