{
  "type": "Feature",
  "properties": {
    "gn:admin1_code":"47",
    "gn:asciiname":"Maloye Krutoye",
    "gn:country_code":"RU",
    "gn:dem":249,
    "gn:feature_class":"P",
    "gn:feature_code":"PPL",
    "gn:name":"Maloye Krutoye",
    "gn:population":0,
    "gn:timezone":"Europe/Moscow",
    "iso:country":"RU",
    "name:eng_x_preferred":[
        "Maloye Krutoye"
    ],
    "name:nor_x_preferred":[
        "Maloje Krutoje"
    ],
    "name:rus_x_preferred":[
        "\u041c\u0430\u043b\u043e\u0435 \u041a\u0440\u0443\u0442\u043e\u0435"
    ],
    "wof:name":"Maloye Krutoye",
    "wof:placetype":"locality"
},
  "geometry": {"coordinates":[35.25316,55.88053000000001],"type":"Point"}
}