{
  "type": "Feature",
  "properties": {
    "gn:admin1_code":"41",
    "gn:asciiname":"Skrylevka",
    "gn:country_code":"RU",
    "gn:dem":176,
    "gn:feature_class":"P",
    "gn:feature_code":"PPL",
    "gn:name":"Skryl\u00ebvka",
    "gn:population":0,
    "gn:timezone":"Europe/Moscow",
    "iso:country":"RU",
    "name:rus_x_preferred":[
        "\u0421\u043a\u0440\u044b\u043b\u0451\u0432\u043a\u0430"
    ],
    "name:und_x_variant":[
        "Skryl\u00ebvka",
        "\u0421\u043a\u0440\u044b\u043b\u0451\u0432\u043a\u0430"
    ],
    "wof:name":"Skrylevka",
    "wof:placetype":"locality"
},
  "geometry": {"coordinates":[35.1342,51.4462],"type":"Point"}
}