{
  "type": "Feature",
  "properties": {
    "gn:admin1_code":"30",
    "gn:asciiname":"Pachi",
    "gn:country_code":"RU",
    "gn:dem":2,
    "gn:feature_class":"P",
    "gn:feature_code":"PPL",
    "gn:name":"Pachi",
    "gn:population":0,
    "gn:timezone":"Asia/Vladivostok",
    "iso:country":"RU",
    "name:ceb_x_preferred":[
        "Pachi"
    ],
    "name:rus_x_preferred":[
        "\u041f\u0430\u0447\u0438"
    ],
    "name:swe_x_preferred":[
        "Pachi"
    ],
    "name:und_x_variant":[
        "\u041f\u0430\u0447\u0438"
    ],
    "wof:name":"Pachi",
    "wof:placetype":"locality"
},
  "geometry": {"coordinates":[139.90000000000001,53.25],"type":"Point"}
}