{
  "type": "Feature",
  "properties": {
    "gn:admin1_code":"42.0",
    "gn:asciiname":"Gavrilovskaya",
    "gn:country_code":"RU",
    "gn:dem":100,
    "gn:feature_class":"P",
    "gn:feature_code":"PPL",
    "gn:name":"Gavrilovskaya",
    "gn:population":0,
    "gn:timezone":"Europe/Moscow",
    "iso:country":"RU",
    "name:rus_x_preferred":[
        "\u0413\u0430\u0432\u0440\u0438\u043b\u043e\u0432\u0441\u043a\u0430\u044f"
    ],
    "name:und_x_variant":[
        "\u0413\u0430\u0432\u0440\u0438\u043b\u043e\u0432\u0441\u043a\u0430\u044f"
    ],
    "wof:name":"Gavrilovskaya",
    "wof:placetype":"locality"
},
  "geometry": {"coordinates":[34.83333,60.81667],"type":"Point"}
}