{
  "type": "Feature",
  "properties": {
    "gn:admin1_code":"67",
    "gn:asciiname":"Yeremino",
    "gn:country_code":"RU",
    "gn:dem":37,
    "gn:feature_class":"P",
    "gn:feature_code":"PPL",
    "gn:name":"Yer\u00ebmino",
    "gn:population":0,
    "gn:timezone":"Europe/Saratov",
    "iso:country":"RU",
    "name:rus_x_preferred":[
        "Yer\u00ebmino"
    ],
    "name:rus_x_variant":[
        "\u0415\u0440\u00eb\u043c\u0438\u043d\u043e"
    ],
    "wof:name":"Yeremino",
    "wof:placetype":"locality"
},
  "geometry": {"coordinates":[49.6619,51.7702],"type":"Point"}
}