{
  "type": "Feature",
  "properties": {
    "gn:admin1_code":"69",
    "gn:asciiname":"Shiryaikha",
    "gn:country_code":"RU",
    "gn:dem":198,
    "gn:feature_class":"P",
    "gn:feature_code":"PPL",
    "gn:name":"Shiryaikha",
    "gn:population":0,
    "gn:timezone":"Europe/Moscow",
    "iso:country":"RU",
    "name:che_x_preferred":[
        "\u0428\u0438\u0440\u044f\u0438\u0445\u0430"
    ],
    "name:ita_x_preferred":[
        "\u0160irjaicha"
    ],
    "name:rus_x_preferred":[
        "\u0428\u0438\u0440\u044f\u0438\u0445\u0430"
    ],
    "wof:name":"Shiryaikha",
    "wof:placetype":"locality"
},
  "geometry": {"coordinates":[34.72037,55.57385],"type":"Point"}
}