{
  "type": "Feature",
  "properties": {
    "gn:country":"RU",
    "gn:fcode":"PPL",
    "gn:pop":3278,
    "iso:country":"RU",
    "name:nor_x_preferred":[
        "Nizjnij Tsasutsjej"
    ],
    "name:rus_x_preferred":[
        "\u041d\u0438\u0436\u043d\u0438\u0439 \u0426\u0430\u0441\u0443\u0447\u0435\u0439"
    ],
    "name:unk_x_variant":[
        "\u041d\u0438\u0436\u043d\u0438\u0439 \u0426\u0430\u0441\u0443\u0447\u0435\u0439"
    ],
    "qs:name":"Nizhniy Tsasuchey",
    "qs:photos_9r":0,
    "qs:photos_sr":0,
    "qs:pop_sr":"4",
    "wof:name":"Nizhniy Tsasuchey",
    "wof:placetype":"locality",
    "wof:population":3278
},
  "geometry": {"coordinates":[115.13333,50.51667],"type":"Point"}
}