{
  "type": "Feature",
  "properties": {
    "gn:admin1_code":"71",
    "gn:asciiname":"Nalimovo",
    "gn:country_code":"RU",
    "gn:dem":150,
    "gn:feature_class":"P",
    "gn:feature_code":"PPL",
    "gn:name":"Nalimovo",
    "gn:population":0,
    "gn:timezone":"Asia/Yekaterinburg",
    "iso:country":"RU",
    "name:rus_x_preferred":[
        "\u041d\u0430\u043b\u0438\u043c\u043e\u0432\u043e"
    ],
    "name:und_x_variant":[
        "Kalinova",
        "Nalimova",
        "Nalimovo"
    ],
    "wof:name":"Nalimovo",
    "wof:placetype":"locality"
},
  "geometry": {"coordinates":[61.93734,57.43357],"type":"Point"}
}