{
  "type": "Feature",
  "properties": {
    "gn:admin1_code":"80.0",
    "gn:asciiname":"Tsyp'ya",
    "gn:country_code":"RU",
    "gn:dem":211,
    "gn:feature_class":"P",
    "gn:feature_code":"PPL",
    "gn:name":"Tsyp\u2019ya",
    "gn:population":0,
    "gn:timezone":"Europe/Samara",
    "iso:country":"RU",
    "name:rus_x_preferred":[
        "\u0426\u044b\u043f\u044c\u044f"
    ],
    "name:und_x_variant":[
        "Tsyp\u2019ya"
    ],
    "wof:name":"Tsyp'ya",
    "wof:placetype":"locality"
},
  "geometry": {"coordinates":[52.2554,58.338],"type":"Point"}
}