{
  "type": "Feature",
  "properties": {
    "gn:admin1_code":"44",
    "gn:asciiname":"Surovaya",
    "gn:country_code":"RU",
    "gn:dem":701,
    "gn:feature_class":"P",
    "gn:feature_code":"PPL",
    "gn:name":"Surovaya",
    "gn:population":0,
    "gn:timezone":"Asia/Magadan",
    "iso:country":"RU",
    "name:rus_x_preferred":[
        "\u0421\u0443\u0440\u043e\u0432\u0430\u044f"
    ],
    "wof:name":"Surovaya",
    "wof:placetype":"locality"
},
  "geometry": {"coordinates":[148.23333,62.85],"type":"Point"}
}