{
  "type": "Feature",
  "properties": {
    "gn:admin1_code":"54",
    "gn:asciiname":"Novoseletsk",
    "gn:country_code":"RU",
    "gn:dem":95,
    "gn:feature_class":"P",
    "gn:feature_code":"PPL",
    "gn:name":"Novoseletsk",
    "gn:population":0,
    "gn:timezone":"Asia/Omsk",
    "iso:country":"RU",
    "name:eng_x_preferred":[
        "Novoseletsk"
    ],
    "name:nor_x_preferred":[
        "Novoseletsk"
    ],
    "name:rus_x_preferred":[
        "\u041d\u043e\u0432\u043e\u0441\u0435\u043b\u0435\u0446\u043a"
    ],
    "wof:name":"Novoseletsk",
    "wof:placetype":"locality"
},
  "geometry": {"coordinates":[73.52034999999999,54.6517],"type":"Point"}
}