{
  "type": "Feature",
  "properties": {
    "gn:admin1_code":"54",
    "gn:asciiname":"Subbotinka",
    "gn:country_code":"RU",
    "gn:dem":114,
    "gn:feature_class":"P",
    "gn:feature_code":"PPL",
    "gn:name":"Subbotinka",
    "gn:population":0,
    "gn:timezone":"Asia/Omsk",
    "iso:country":"RU",
    "name:rus_x_preferred":[
        "\u0421\u0443\u0431\u0431\u043e\u0442\u0438\u043d\u043a\u0430"
    ],
    "name:und_x_variant":[
        "\u0421\u0443\u0431\u0431\u043e\u0442\u0438\u043d\u043a\u0430"
    ],
    "wof:name":"Subbotinka",
    "wof:placetype":"locality"
},
  "geometry": {"coordinates":[72.4063,55.3723],"type":"Point"}
}