{
  "type": "Feature",
  "properties": {
    "gn:admin1_code":"77.0",
    "gn:asciiname":"Valuyki",
    "gn:country_code":"RU",
    "gn:dem":139,
    "gn:feature_class":"P",
    "gn:feature_code":"PPL",
    "gn:name":"Valuyki",
    "gn:population":0,
    "gn:timezone":"Europe/Moscow",
    "iso:country":"RU",
    "name:nor_x_preferred":[
        "Valujki"
    ],
    "name:rus_x_preferred":[
        "\u0412\u0430\u043b\u0443\u0439\u043a\u0438"
    ],
    "name:und_x_variant":[
        "Bol\u2019shiye Valuyki",
        "Valuyki"
    ],
    "wof:name":"Valuyki",
    "wof:placetype":"locality"
},
  "geometry": {"coordinates":[35.13987,56.5817],"type":"Point"}
}