{
  "type": "Feature",
  "properties": {
    "gn:admin1_code":"77.0",
    "gn:asciiname":"Valuyki",
    "gn:country_code":"RU",
    "gn:dem":139,
    "gn:feature_class":"P",
    "gn:feature_code":"PPL",
    "gn:name":"Valuyki",
    "gn:population":0,
    "gn:timezone":"Europe/Moscow",
    "iso:country":"RU",
    "name:ben_x_preferred":[
        "\u09ad\u09be\u09b2\u09c1\u0987\u0995\u09bf"
    ],
    "name:ell_x_preferred":[
        "\u0392\u03b1\u03bb\u03bf\u03cd\u03b9\u03ba\u03b9"
    ],
    "name:hin_x_preferred":[
        "\u0935\u093e\u0932\u0941\u092f\u094d\u0915\u0940"
    ],
    "name:ind_x_preferred":[
        "Valuyki"
    ],
    "name:jpn_x_preferred":[
        "\u30f4\u30a1\u30eb\u30a4\u30ad"
    ],
    "name:nor_x_preferred":[
        "Valujki"
    ],
    "name:rus_x_preferred":[
        "\u0412\u0430\u043b\u0443\u0439\u043a\u0438"
    ],
    "name:swe_x_preferred":[
        "Valujki"
    ],
    "name:und_x_variant":[
        "Bol\u2019shiye Valuyki",
        "Valuyki"
    ],
    "name:urd_x_preferred":[
        "\u0648\u0627\u0644\u06cc\u0648\u06a9\u06cc"
    ],
    "wof:name":"Valuyki",
    "wof:placetype":"locality"
},
  "geometry": {"coordinates":[35.13987,56.5817],"type":"Point"}
}