{
  "type": "Feature",
  "properties": {
    "gn:admin1_code":"51.0",
    "gn:asciiname":"Massalki",
    "gn:country_code":"RU",
    "gn:dem":116,
    "gn:feature_class":"P",
    "gn:feature_code":"PPL",
    "gn:name":"Massalki",
    "gn:population":0,
    "gn:timezone":"Europe/Moscow",
    "iso:country":"RU",
    "name:rus_x_preferred":[
        "\u041c\u0430\u0441\u0441\u0430\u043b\u043a\u0438"
    ],
    "wof:name":"Massalki",
    "wof:placetype":"locality"
},
  "geometry": {"coordinates":[44.72242,54.79933000000001],"type":"Point"}
}