{
  "type": "Feature",
  "properties": {
    "gn:admin1_code":"63",
    "gn:asciiname":"Dogdogur",
    "gn:country_code":"RU",
    "gn:dem":41,
    "gn:feature_class":"P",
    "gn:feature_code":"PPL",
    "gn:name":"Dogdogur",
    "gn:population":0,
    "gn:timezone":"Asia/Magadan",
    "iso:country":"RU",
    "name:rus_x_preferred":[
        "\u0414\u043e\u0433\u0434\u043e\u0433\u0443\u0440"
    ],
    "wof:name":"Dogdogur",
    "wof:placetype":"locality"
},
  "geometry": {"coordinates":[144.88333,68.26666999999999],"type":"Point"}
}