{
  "type": "Feature",
  "properties": {
    "gn:admin1_code":"40",
    "gn:asciiname":"Maksimovka",
    "gn:country_code":"RU",
    "gn:dem":163,
    "gn:feature_class":"P",
    "gn:feature_code":"PPL",
    "gn:name":"Maksimovka",
    "gn:population":0,
    "gn:timezone":"Asia/Yekaterinburg",
    "iso:country":"RU",
    "name:lav_x_preferred":[
        "Maksimovka"
    ],
    "name:rus_x_preferred":[
        "\u041c\u0430\u043a\u0441\u0438\u043c\u043e\u0432\u043a\u0430"
    ],
    "name:ukr_x_preferred":[
        "\u041c\u0430\u043a\u0441\u0438\u043c\u043e\u0432\u043a\u0430"
    ],
    "name:und_x_variant":[
        "\u041c\u0430\u043a\u0441\u0438\u043c\u043e\u0432\u043a\u0430"
    ],
    "wof:name":"Maksimovka",
    "wof:placetype":"locality"
},
  "geometry": {"coordinates":[62.7023,54.9299],"type":"Point"}
}