{
  "type": "Feature",
  "properties": {
    "gn:admin1_code":"80",
    "gn:asciiname":"Lagunovo",
    "gn:country_code":"RU",
    "gn:dem":97,
    "gn:feature_class":"P",
    "gn:feature_code":"PPL",
    "gn:name":"Lagunovo",
    "gn:population":0,
    "gn:timezone":"Europe/Samara",
    "iso:country":"RU",
    "name:eng_x_preferred":[
        "Lagunovo"
    ],
    "name:nor_x_preferred":[
        "Lagunovo"
    ],
    "name:rus_x_preferred":[
        "\u041b\u0430\u0433\u0443\u043d\u043e\u0432\u043e"
    ],
    "name:und_x_variant":[
        "\u041b\u0430\u0433\u0443\u043d\u043e\u0432\u043e",
        "Lagunovo"
    ],
    "wof:name":"Lagunovo",
    "wof:placetype":"locality"
},
  "geometry": {"coordinates":[53.61102,56.61638000000001],"type":"Point"}
}