{
  "type": "Feature",
  "properties": {
    "gn:admin1_code":"17.0",
    "gn:asciiname":"Achi-Kol'",
    "gn:country_code":"RU",
    "gn:dem":11,
    "gn:feature_class":"P",
    "gn:feature_code":"PPL",
    "gn:name":"Achi-Kol\u2019",
    "gn:population":0,
    "gn:timezone":"Europe/Moscow",
    "iso:country":"RU",
    "name:nor_x_preferred":[
        "Atsji-Kol"
    ],
    "name:rus_x_preferred":[
        "\u0410\u0447\u0438-\u041a\u043e\u043b\u044c"
    ],
    "name:und_x_variant":[
        "Achi-Kol\u2019"
    ],
    "wof:name":"Achi-Kol'",
    "wof:placetype":"locality"
},
  "geometry": {"coordinates":[45.64944000000001,44.66111],"type":"Point"}
}