{
  "type": "Feature",
  "properties": {
    "gn:admin1_code":"62.0",
    "gn:asciiname":"Bol'shaya Yekaterinovka",
    "gn:country_code":"RU",
    "gn:dem":131,
    "gn:feature_class":"P",
    "gn:feature_code":"PPL",
    "gn:name":"Bol\u2019shaya Yekaterinovka",
    "gn:population":0,
    "gn:timezone":"Europe/Moscow",
    "iso:country":"RU",
    "name:rus_x_preferred":[
        "\u0411\u043e\u043b\u044c\u0448\u0430\u044f \u0415\u043a\u0430\u0442\u0435\u0440\u0438\u043d\u043e\u0432\u043a\u0430"
    ],
    "name:und_x_variant":[
        "Bol\u2019shaya Yekaterinovka"
    ],
    "wof:name":"Bol'shaya Yekaterinovka",
    "wof:placetype":"locality"
},
  "geometry": {"coordinates":[41.40691,54.03584],"type":"Point"}
}