{
  "type": "Feature",
  "properties": {
    "gn:admin1_code":"77",
    "gn:asciiname":"Shirokusha",
    "gn:country_code":"RU",
    "gn:dem":162,
    "gn:feature_class":"P",
    "gn:feature_code":"PPL",
    "gn:name":"Shirokusha",
    "gn:population":0,
    "gn:timezone":"Europe/Moscow",
    "iso:country":"RU",
    "name:rus_x_preferred":[
        "\u0428\u0438\u0440\u043e\u043a\u0443\u0448\u0430"
    ],
    "wof:name":"Shirokusha",
    "wof:placetype":"locality"
},
  "geometry": {"coordinates":[37.2718,57.7327],"type":"Point"}
}