{
  "type": "Feature",
  "properties": {
    "gn:admin1_code":"77",
    "gn:asciiname":"Kuzlovo",
    "gn:country_code":"RU",
    "gn:dem":268,
    "gn:feature_class":"P",
    "gn:feature_code":"PPL",
    "gn:name":"Kuzlovo",
    "gn:population":0,
    "gn:timezone":"Europe/Moscow",
    "iso:country":"RU",
    "name:rus_x_preferred":[
        "\u041a\u0443\u0437\u043b\u043e\u0432\u043e"
    ],
    "name:und_x_variant":[
        "\u041a\u0443\u0437\u043b\u043e\u0432\u043e"
    ],
    "wof:name":"Kuzlovo",
    "wof:placetype":"locality"
},
  "geometry": {"coordinates":[34.3618,57.30418],"type":"Point"}
}