{
  "type": "Feature",
  "properties": {
    "gn:admin1_code":"59",
    "gn:asciiname":"Astrakhanka",
    "gn:country_code":"RU",
    "gn:dem":97,
    "gn:feature_class":"P",
    "gn:feature_code":"PPL",
    "gn:name":"Astrakhanka",
    "gn:population":0,
    "gn:timezone":"Asia/Vladivostok",
    "iso:country":"RU",
    "name:eng_x_preferred":[
        "Astrakhanka"
    ],
    "name:nor_x_preferred":[
        "Astrakhanka"
    ],
    "name:rus_x_preferred":[
        "\u0410\u0441\u0442\u0440\u0430\u0445\u0430\u043d\u043a\u0430"
    ],
    "name:und_x_variant":[
        "\u0410\u0441\u0442\u0440\u0430\u0445\u0430\u043d\u043a\u0430",
        "Astrakhanka"
    ],
    "wof:name":"Astrakhanka",
    "wof:placetype":"locality"
},
  "geometry": {"coordinates":[132.05170000000001,44.7259],"type":"Point"}
}