{
  "type": "Feature",
  "properties": {
    "gn:admin1_code":"88",
    "gn:asciiname":"Oparino",
    "gn:country_code":"RU",
    "gn:dem":132,
    "gn:feature_class":"P",
    "gn:feature_code":"PPL",
    "gn:name":"Oparino",
    "gn:population":0,
    "gn:timezone":"Europe/Moscow",
    "iso:country":"RU",
    "name:deu_x_preferred":[
        "Oparino"
    ],
    "name:rus_x_preferred":[
        "\u041e\u043f\u0430\u0440\u0438\u043d\u043e"
    ],
    "wof:name":"Oparino",
    "wof:placetype":"locality"
},
  "geometry": {"coordinates":[39.82457,57.47046],"type":"Point"}
}