{
  "type": "Feature",
  "properties": {
    "gn:admin1_code":"53",
    "gn:asciiname":"Lotoshnoye",
    "gn:country_code":"RU",
    "gn:dem":113,
    "gn:feature_class":"P",
    "gn:feature_code":"PPL",
    "gn:name":"Lotoshnoye",
    "gn:population":0,
    "gn:timezone":"Asia/Novosibirsk",
    "iso:country":"RU",
    "name:eng_x_preferred":[
        "Lotoshnoye"
    ],
    "name:nor_x_preferred":[
        "Lotosjnoje"
    ],
    "name:rus_x_preferred":[
        "\u041b\u043e\u0442\u043e\u0448\u043d\u043e\u0435"
    ],
    "name:und_x_variant":[
        "\u041b\u043e\u0442\u043e\u0448\u043d\u043e\u0435",
        "Lotoshnoye"
    ],
    "wof:name":"Lotoshnoye",
    "wof:placetype":"locality"
},
  "geometry": {"coordinates":[78.78607,54.13936999999999],"type":"Point"}
}