{
  "type": "Feature",
  "properties": {
    "gn:admin1_code":"28",
    "gn:asciiname":"Tsipringa",
    "gn:cc2":"RU",
    "gn:country_code":"RU",
    "gn:dem":107,
    "gn:feature_class":"P",
    "gn:feature_code":"PPL",
    "gn:name":"Tsipringa",
    "gn:population":0,
    "gn:timezone":"Europe/Moscow",
    "iso:country":"RU",
    "name:fin_x_preferred":[
        "Ukonniemi"
    ],
    "name:und_x_variant":[
        "Chipringa",
        "Ukkoniyemi",
        "Tsipringa"
    ],
    "wof:name":"Tsipringa",
    "wof:placetype":"locality"
},
  "geometry": {"coordinates":[30.75897,66.324],"type":"Point"}
}