{
  "type": "Feature",
  "properties": {
    "gn:admin1_code":"93",
    "gn:asciiname":"Il'inka",
    "gn:country_code":"RU",
    "gn:dem":771,
    "gn:feature_class":"P",
    "gn:feature_code":"PPL",
    "gn:name":"Il\u2019inka",
    "gn:population":0,
    "gn:timezone":"Asia/Chita",
    "iso:country":"RU",
    "name:eng_x_preferred":[
        "Il'inka"
    ],
    "name:nor_x_preferred":[
        "Glinka"
    ],
    "name:rus_x_preferred":[
        "\u0413\u043b\u0438\u043d\u043a\u0430"
    ],
    "name:rus_x_variant":[
        "\u0418\u043b\u044c\u0438\u043d\u043a\u0430"
    ],
    "name:und_x_variant":[
        "Il\u2019inka"
    ],
    "wof:name":"Il'inka",
    "wof:placetype":"locality"
},
  "geometry": {"coordinates":[110.0157,51.3863],"type":"Point"}
}