{
  "type": "Feature",
  "properties": {
    "gn:admin1_code":"71.0",
    "gn:asciiname":"Cherkasova",
    "gn:country_code":"RU",
    "gn:dem":224,
    "gn:feature_class":"P",
    "gn:feature_code":"PPL",
    "gn:name":"Cherkasova",
    "gn:population":0,
    "gn:timezone":"Asia/Yekaterinburg",
    "iso:country":"RU",
    "name:rus_x_preferred":[
        "\u0427\u0435\u0440\u043a\u0430\u0441\u043e\u0432\u0430"
    ],
    "name:und_x_variant":[
        "\u0427\u0435\u0440\u043a\u0430\u0441\u043e\u0432\u0430"
    ],
    "wof:name":"Cherkasova",
    "wof:placetype":"locality"
},
  "geometry": {"coordinates":[57.75238,56.52381999999999],"type":"Point"}
}