{
  "type": "Feature",
  "properties": {
    "gn:admin1_code":"45",
    "gn:asciiname":"Murzanayevo",
    "gn:country_code":"RU",
    "gn:dem":136,
    "gn:feature_class":"P",
    "gn:feature_code":"PPL",
    "gn:name":"Murzanayevo",
    "gn:population":0,
    "gn:timezone":"Europe/Moscow",
    "iso:country":"RU",
    "name:rus_x_preferred":[
        "\u041c\u0443\u0440\u0437\u0430\u043d\u0430\u0435\u0432\u043e"
    ],
    "wof:name":"Murzanayevo",
    "wof:placetype":"locality"
},
  "geometry": {"coordinates":[49.015,57.1362],"type":"Point"}
}