{
  "type": "Feature",
  "properties": {
    "gn:admin1_code":"69",
    "gn:asciiname":"Kurchebovo",
    "gn:country_code":"RU",
    "gn:dem":219,
    "gn:feature_class":"P",
    "gn:feature_code":"PPL",
    "gn:name":"Kurchebovo",
    "gn:population":0,
    "gn:timezone":"Europe/Moscow",
    "iso:country":"RU",
    "name:rus_x_preferred":[
        "\u041a\u0443\u0440\u0447\u0435\u0431\u043e\u0432\u043e"
    ],
    "wof:name":"Kurchebovo",
    "wof:placetype":"locality"
},
  "geometry": {"coordinates":[33.32556,55.24306],"type":"Point"}
}