{
  "type": "Feature",
  "properties": {
    "gn:admin1_code":"76",
    "gn:asciiname":"Khitrovshchina",
    "gn:country_code":"RU",
    "gn:dem":178,
    "gn:feature_class":"P",
    "gn:feature_code":"PPL",
    "gn:name":"Khitrovshchina",
    "gn:population":0,
    "gn:timezone":"Europe/Moscow",
    "iso:country":"RU",
    "name:rus_x_preferred":[
        "\u0425\u0438\u0442\u0440\u043e\u0432\u0449\u0438\u043d\u0430"
    ],
    "name:und_x_variant":[
        "Bogoyavlenovskoye",
        "Khitrovshchino",
        "Khitrovshchina"
    ],
    "wof:name":"Khitrovshchina",
    "wof:placetype":"locality"
},
  "geometry": {"coordinates":[38.79182,53.95681],"type":"Point"}
}