{
  "type": "Feature",
  "properties": {
    "gn:admin1_code":"80.0",
    "gn:asciiname":"Karakulino",
    "gn:country_code":"RU",
    "gn:dem":213,
    "gn:feature_class":"P",
    "gn:feature_code":"PPL",
    "gn:name":"Karakulino",
    "gn:population":0,
    "gn:timezone":"Europe/Samara",
    "iso:country":"RU",
    "name:rus_x_preferred":[
        "\u041a\u0430\u0440\u0430\u043a\u0443\u043b\u0438\u043d\u043e"
    ],
    "wof:name":"Karakulino",
    "wof:placetype":"locality"
},
  "geometry": {"coordinates":[53.8298,57.9005],"type":"Point"}
}