{
  "type": "Feature",
  "properties": {
    "gn:admin1_code":"90",
    "gn:asciiname":"Machino",
    "gn:country_code":"RU",
    "gn:dem":171,
    "gn:feature_class":"P",
    "gn:feature_code":"PPL",
    "gn:name":"Machino",
    "gn:population":0,
    "gn:timezone":"Asia/Yekaterinburg",
    "iso:country":"RU",
    "name:rus_x_preferred":[
        "\u041c\u0430\u0447\u0438\u043d\u043e"
    ],
    "wof:name":"Machino",
    "wof:placetype":"locality"
},
  "geometry": {"coordinates":[57.3832,57.6075],"type":"Point"}
}