{
  "type": "Feature",
  "properties": {
    "gn:admin1_code":"60",
    "gn:asciiname":"Dubnovo",
    "gn:country_code":"RU",
    "gn:dem":75,
    "gn:feature_class":"P",
    "gn:feature_code":"PPL",
    "gn:name":"Dubnovo",
    "gn:population":0,
    "gn:timezone":"Europe/Moscow",
    "iso:country":"RU",
    "name:rus_x_preferred":[
        "\u0414\u0443\u0431\u043d\u043e\u0432\u043e"
    ],
    "wof:name":"Dubnovo",
    "wof:placetype":"locality"
},
  "geometry": {"coordinates":[28.02315,57.14234],"type":"Point"}
}