{
  "type": "Feature",
  "properties": {
    "gn:admin1_code":"85",
    "gn:asciiname":"Vysokovo",
    "gn:country_code":"RU",
    "gn:dem":151,
    "gn:feature_class":"P",
    "gn:feature_code":"PPL",
    "gn:name":"Vysokovo",
    "gn:population":0,
    "gn:timezone":"Europe/Moscow",
    "iso:country":"RU",
    "name:rus_x_preferred":[
        "\u0412\u044b\u0441\u043e\u043a\u043e\u0432\u043e"
    ],
    "name:und_x_variant":[
        "\u0412\u044b\u0441\u043e\u043a\u043e\u0432\u043e"
    ],
    "wof:name":"Vysokovo",
    "wof:placetype":"locality"
},
  "geometry": {"coordinates":[46.84757000000001,60.556],"type":"Point"}
}