{
  "type": "Feature",
  "properties": {
    "gn:admin1_code":"10",
    "gn:asciiname":"Lochinok-Aleshok",
    "gn:country_code":"RU",
    "gn:dem":187,
    "gn:feature_class":"P",
    "gn:feature_code":"PPL",
    "gn:name":"Lochinok-Aleshok",
    "gn:population":0,
    "gn:timezone":"Europe/Moscow",
    "iso:country":"RU",
    "name:rus_x_preferred":[
        "\u041f\u043e\u0447\u0438\u043d\u043e\u043a-\u0410\u043b\u0435\u0448\u043e\u043a"
    ],
    "name:und_x_variant":[
        "Pochinok-Aleshok",
        "Lochinok-Aleshok"
    ],
    "wof:name":"Lochinok-Aleshok",
    "wof:placetype":"locality"
},
  "geometry": {"coordinates":[34.77306,52.26861],"type":"Point"}
}