{
  "type": "Feature",
  "properties": {
    "gn:admin1_code":"81",
    "gn:asciiname":"Novoye Tomyshevo",
    "gn:country_code":"RU",
    "gn:dem":73,
    "gn:feature_class":"P",
    "gn:feature_code":"PPL",
    "gn:name":"Novoye Tomyshevo",
    "gn:population":0,
    "gn:timezone":"Europe/Ulyanovsk",
    "iso:country":"RU",
    "name:eng_x_preferred":[
        "Novoye Tomyshevo"
    ],
    "name:nor_x_preferred":[
        "Nov.Tomysjevo"
    ],
    "name:rus_x_preferred":[
        "\u041d\u043e\u0432.\u0422\u043e\u043c\u044b\u0448\u0435\u0432\u043e"
    ],
    "name:rus_x_variant":[
        "\u041d\u043e\u0432\u043e\u0435 \u0422\u043e\u043c\u044b\u0448\u0435\u0432\u043e"
    ],
    "name:und_x_variant":[
        "Tomyshevskiye Vyselki",
        "Novo-Tomyshevo",
        "Novoye Tomyshevo",
        "\u041d\u043e\u0432\u043e\u0435 \u0422\u043e\u043c\u044b\u0448\u0435\u0432\u043e"
    ],
    "wof:name":"Novoye Tomyshevo",
    "wof:placetype":"locality"
},
  "geometry": {"coordinates":[47.9009,53.14973000000001],"type":"Point"}
}