{
  "type": "Feature",
  "properties": {
    "gn:admin1_code":"4",
    "gn:asciiname":"Yagodnoye",
    "gn:country_code":"RU",
    "gn:dem":222,
    "gn:feature_class":"P",
    "gn:feature_code":"PPL",
    "gn:name":"Yagodnoye",
    "gn:population":0,
    "gn:timezone":"Asia/Barnaul",
    "iso:country":"RU",
    "name:rus_x_preferred":[
        "\u042f\u0433\u043e\u0434\u043d\u043e\u0435"
    ],
    "name:und_x_variant":[
        "Yagodnyy",
        "Yagodnoye"
    ],
    "wof:name":"Yagodnoye",
    "wof:placetype":"locality"
},
  "geometry": {"coordinates":[83.6185,53.2294],"type":"Point"}
}