{
  "type": "Feature",
  "properties": {
    "gn:admin1_code":"51",
    "gn:asciiname":"Semenovo",
    "gn:country_code":"RU",
    "gn:dem":121,
    "gn:feature_class":"P",
    "gn:feature_code":"PPL",
    "gn:name":"Sem\u00ebnovo",
    "gn:population":0,
    "gn:timezone":"Europe/Moscow",
    "iso:country":"RU",
    "name:rus_x_preferred":[
        "\u0421\u0435\u043c\u0451\u043d\u043e\u0432\u043e"
    ],
    "name:und_x_variant":[
        "Kriselok",
        "Sem\u00ebnovo",
        "\u0421\u0435\u043c\u0451\u043d\u043e\u0432\u043e"
    ],
    "wof:name":"Semenovo",
    "wof:placetype":"locality"
},
  "geometry": {"coordinates":[43.54258,55.36663000000001],"type":"Point"}
}