{
  "type": "Feature",
  "properties": {
    "gn:admin1_code":"60",
    "gn:asciiname":"Bogdashi",
    "gn:country_code":"RU",
    "gn:dem":71,
    "gn:feature_class":"P",
    "gn:feature_code":"PPL",
    "gn:name":"Bogdashi",
    "gn:population":0,
    "gn:timezone":"Europe/Moscow",
    "iso:country":"RU",
    "name:rus_x_preferred":[
        "\u0411\u043e\u0433\u0434\u0430\u0448\u0438"
    ],
    "wof:name":"Bogdashi",
    "wof:placetype":"locality"
},
  "geometry": {"coordinates":[28.13189,57.46089],"type":"Point"}
}