{
  "type": "Feature",
  "properties": {
    "gn:admin1_code":"52",
    "gn:asciiname":"Ol'khi",
    "gn:country_code":"RU",
    "gn:dem":67,
    "gn:feature_class":"P",
    "gn:feature_code":"PPL",
    "gn:name":"Ol\u2019khi",
    "gn:population":0,
    "gn:timezone":"Europe/Moscow",
    "iso:country":"RU",
    "name:rus_x_preferred":[
        "\u041e\u043b\u044c\u0445\u0438"
    ],
    "name:und_x_variant":[
        "Ol\u2019khi",
        "\u041e\u043b\u044c\u0445\u0438"
    ],
    "wof:name":"Ol'khi",
    "wof:placetype":"locality"
},
  "geometry": {"coordinates":[31.35,57.56667],"type":"Point"}
}