{
  "type": "Feature",
  "properties": {
    "gn:admin1_code":"33",
    "gn:asciiname":"Pashki",
    "gn:country_code":"RU",
    "gn:dem":127,
    "gn:feature_class":"P",
    "gn:feature_code":"PPL",
    "gn:name":"Pashki",
    "gn:population":0,
    "gn:timezone":"Europe/Kirov",
    "iso:country":"RU",
    "name:rus_x_preferred":[
        "\u041f\u0430\u0448\u043a\u0438"
    ],
    "name:und_x_variant":[
        "\u041f\u0430\u0448\u043a\u0438"
    ],
    "wof:name":"Pashki",
    "wof:placetype":"locality"
},
  "geometry": {"coordinates":[48.58333,57.73333],"type":"Point"}
}