{
  "type": "Feature",
  "properties": {
    "gn:admin1_code":"33",
    "gn:asciiname":"Tereshenki",
    "gn:country_code":"RU",
    "gn:dem":154,
    "gn:feature_class":"P",
    "gn:feature_code":"PPL",
    "gn:name":"Tereshenki",
    "gn:population":0,
    "gn:timezone":"Europe/Kirov",
    "iso:country":"RU",
    "wof:name":"Tereshenki",
    "wof:placetype":"locality"
},
  "geometry": {"coordinates":[48.32361,58.92778000000001],"type":"Point"}
}