{
  "type": "Feature",
  "properties": {
    "gn:admin1_code":"33.0",
    "gn:asciiname":"Gradoboy",
    "gn:country_code":"RU",
    "gn:dem":149,
    "gn:feature_class":"P",
    "gn:feature_code":"PPL",
    "gn:name":"Gradoboy",
    "gn:population":0,
    "gn:timezone":"Europe/Kirov",
    "iso:country":"RU",
    "name:rus_x_preferred":[
        "\u0413\u0440\u0430\u0434\u043e\u0431\u043e\u0438"
    ],
    "name:und_x_variant":[
        "Gradoboi"
    ],
    "wof:name":"Gradoboy",
    "wof:placetype":"locality"
},
  "geometry": {"coordinates":[50.87807,58.49726],"type":"Point"}
}