{
  "type": "Feature",
  "properties": {
    "gn:admin1_code":"52.0",
    "gn:asciiname":"Finev Lug",
    "gn:cc2":"RU",
    "gn:country_code":"RU",
    "gn:dem":61,
    "gn:feature_class":"P",
    "gn:feature_code":"PPL",
    "gn:name":"Finev Lug",
    "gn:population":0,
    "gn:timezone":"Europe/Moscow",
    "iso:country":"RU",
    "name:rus_x_preferred":[
        "\u0424\u0438\u043d\u0435\u0432 \u041b\u0443\u0433"
    ],
    "name:und_x_variant":[
        "Fenev-Lug",
        "Finev Lug",
        "\u0424\u0438\u043d\u0435\u0432 \u041b\u0443\u0433"
    ],
    "wof:name":"Finev Lug",
    "wof:placetype":"locality"
},
  "geometry": {"coordinates":[31.08333,58.95],"type":"Point"}
}