{
  "type": "Feature",
  "properties": {
    "gn:admin1_code":"42",
    "gn:asciiname":"Klimova",
    "gn:country_code":"RU",
    "gn:dem":85,
    "gn:feature_class":"P",
    "gn:feature_code":"PPL",
    "gn:name":"Klimova",
    "gn:population":0,
    "gn:timezone":"Europe/Moscow",
    "iso:country":"RU",
    "name:rus_x_preferred":[
        "\u041a\u043e\u043d\u0434\u0443\u0448\u0438-\u041a\u043b\u0438\u043c\u043e\u0432\u0430"
    ],
    "name:und_x_variant":[
        "Kondushi-Klimova",
        "\u041a\u043e\u043d\u0434\u0443\u0448\u0438-\u041a\u043b\u0438\u043c\u043e\u0432\u0430"
    ],
    "wof:name":"Klimova",
    "wof:placetype":"locality"
},
  "geometry": {"coordinates":[33.41045,60.86782],"type":"Point"}
}