{
  "type": "Feature",
  "properties": {
    "gn:admin1_code":"75",
    "gn:asciiname":"Tashlpir",
    "gn:country_code":"RU",
    "gn:dem":121,
    "gn:feature_class":"P",
    "gn:feature_code":"PPL",
    "gn:name":"Tashlpir",
    "gn:population":0,
    "gn:timezone":"Asia/Tomsk",
    "iso:country":"RU",
    "wof:name":"Tashlpir",
    "wof:placetype":"locality"
},
  "geometry": {"coordinates":[84.26666999999998,56.26667],"type":"Point"}
}