{
  "type": "Feature",
  "properties": {
    "gn:admin1_code":"91",
    "gn:asciiname":"Kirikovo",
    "gn:country_code":"RU",
    "gn:dem":187,
    "gn:feature_class":"P",
    "gn:feature_code":"PPL",
    "gn:name":"Kirikovo",
    "gn:population":0,
    "gn:timezone":"Asia/Krasnoyarsk",
    "iso:country":"RU",
    "name:eng_x_preferred":[
        "Kirikovo"
    ],
    "name:nor_x_preferred":[
        "Kirikovo"
    ],
    "name:rus_x_preferred":[
        "\u041a\u0438\u0440\u0438\u043a\u043e\u0432\u043e"
    ],
    "name:und_x_variant":[
        "Kirikovskiy"
    ],
    "wof:name":"Kirikovo",
    "wof:placetype":"locality"
},
  "geometry": {"coordinates":[92.4746,57.5752],"type":"Point"}
}