{
  "type": "Feature",
  "properties": {
    "gn:admin1_code":"21",
    "gn:asciiname":"Afanasovka",
    "gn:country_code":"RU",
    "gn:dem":142,
    "gn:feature_class":"P",
    "gn:feature_code":"PPL",
    "gn:name":"Afanasovka",
    "gn:population":0,
    "gn:timezone":"Europe/Moscow",
    "iso:country":"RU",
    "name:rus_x_preferred":[
        "\u0410\u0444\u0430\u043d\u0430\u0441\u043e\u0432\u043a\u0430"
    ],
    "wof:name":"Afanasovka",
    "wof:placetype":"locality"
},
  "geometry": {"coordinates":[40.15362,56.9312],"type":"Point"}
}