{
  "type": "Feature",
  "properties": {
    "gn:admin1_code":"75",
    "gn:asciiname":"Berlinka",
    "gn:country_code":"RU",
    "gn:dem":106,
    "gn:feature_class":"P",
    "gn:feature_code":"PPL",
    "gn:name":"Berlinka",
    "gn:population":0,
    "gn:timezone":"Asia/Tomsk",
    "iso:country":"RU",
    "name:eng_x_preferred":[
        "Berlinka"
    ],
    "name:nor_x_preferred":[
        "Berlinka"
    ],
    "name:rus_x_preferred":[
        "\u0411\u0435\u0440\u043b\u0438\u043d\u043a\u0430"
    ],
    "name:und_x_variant":[
        "Belinka",
        "\u0411\u0435\u0440\u043b\u0438\u043d\u043a\u0430",
        "Berlinka"
    ],
    "wof:name":"Berlinka",
    "wof:placetype":"locality"
},
  "geometry": {"coordinates":[86.55247,56.83231],"type":"Point"}
}