{
  "type": "Feature",
  "properties": {
    "gn:admin1_code":"10",
    "gn:asciiname":"Shamordino",
    "gn:country_code":"RU",
    "gn:dem":198,
    "gn:feature_class":"P",
    "gn:feature_code":"PPL",
    "gn:name":"Shamordino",
    "gn:population":0,
    "gn:timezone":"Europe/Moscow",
    "iso:country":"RU",
    "name:rus_x_preferred":[
        "\u0428\u0430\u043c\u043e\u0440\u0434\u0438\u043d\u043e"
    ],
    "wof:name":"Shamordino",
    "wof:placetype":"locality"
},
  "geometry": {"coordinates":[33.77008,53.38744000000001],"type":"Point"}
}