{
  "type": "Feature",
  "properties": {
    "gn:admin1_code":"77",
    "gn:asciiname":"Osinka",
    "gn:country_code":"RU",
    "gn:dem":209,
    "gn:feature_class":"P",
    "gn:feature_code":"PPL",
    "gn:name":"Osinka",
    "gn:population":0,
    "gn:timezone":"Europe/Moscow",
    "iso:country":"RU",
    "name:rus_x_preferred":[
        "\u041e\u0441\u0438\u043d\u043a\u0430"
    ],
    "name:und_x_variant":[
        "\u041e\u0441\u0438\u043d\u043a\u0430"
    ],
    "wof:name":"Osinka",
    "wof:placetype":"locality"
},
  "geometry": {"coordinates":[33.03165,57.39167],"type":"Point"}
}