{
  "type": "Feature",
  "properties": {
    "gn:admin1_code":"80",
    "gn:asciiname":"Sada",
    "gn:country_code":"RU",
    "gn:dem":136,
    "gn:feature_class":"P",
    "gn:feature_code":"PPL",
    "gn:name":"Sada",
    "gn:population":0,
    "gn:timezone":"Europe/Samara",
    "iso:country":"RU",
    "name:cat_x_preferred":[
        "Sada"
    ],
    "name:ceb_x_preferred":[
        "Sada"
    ],
    "name:che_x_preferred":[
        "\u0421\u0430\u0434\u0430"
    ],
    "name:deu_x_preferred":[
        "Sada"
    ],
    "name:eng_x_preferred":[
        "Sada"
    ],
    "name:eus_x_preferred":[
        "Sada"
    ],
    "name:fra_x_preferred":[
        "Sada"
    ],
    "name:glg_x_preferred":[
        "Sada"
    ],
    "name:hrv_x_preferred":[
        "Sada"
    ],
    "name:hun_x_preferred":[
        "Sada"
    ],
    "name:hye_x_preferred":[
        "\u054d\u0561\u0564\u0561"
    ],
    "name:ita_x_preferred":[
        "Sada"
    ],
    "name:lit_x_preferred":[
        "Sada"
    ],
    "name:msa_x_preferred":[
        "Sada"
    ],
    "name:nld_x_preferred":[
        "Sada"
    ],
    "name:nor_x_preferred":[
        "Rus.Sada"
    ],
    "name:oci_x_preferred":[
        "Sada"
    ],
    "name:pol_x_preferred":[
        "Sada"
    ],
    "name:por_x_preferred":[
        "Sada"
    ],
    "name:rus_x_preferred":[
        "\u0420\u0443\u0441.\u0421\u0430\u0434\u0430"
    ],
    "name:rus_x_variant":[
        "\u0421\u0430\u0434\u0430"
    ],
    "name:scn_x_preferred":[
        "Sada"
    ],
    "name:slk_x_preferred":[
        "Sada"
    ],
    "name:spa_x_preferred":[
        "Sada"
    ],
    "name:swe_x_preferred":[
        "Sada"
    ],
    "name:tur_x_preferred":[
        "Sada"
    ],
    "name:ukr_x_preferred":[
        "\u0421\u0430\u0434\u0430"
    ],
    "name:uzb_x_preferred":[
        "Sada"
    ],
    "name:vie_x_preferred":[
        "Sada"
    ],
    "name:war_x_preferred":[
        "Sada"
    ],
    "wof:name":"Sada",
    "wof:placetype":"locality"
},
  "geometry": {"coordinates":[51.82358,58.28648000000001],"type":"Point"}
}