{
  "type": "Feature",
  "properties": {
    "gn:admin1_code":"80",
    "gn:asciiname":"Sada",
    "gn:country_code":"RU",
    "gn:dem":136,
    "gn:feature_class":"P",
    "gn:feature_code":"PPL",
    "gn:name":"Sada",
    "gn:population":0,
    "gn:timezone":"Europe/Samara",
    "iso:country":"RU",
    "name:eng_x_preferred":[
        "Sada"
    ],
    "name:nor_x_preferred":[
        "Rus.Sada"
    ],
    "name:rus_x_preferred":[
        "\u0420\u0443\u0441.\u0421\u0430\u0434\u0430"
    ],
    "name:rus_x_variant":[
        "\u0421\u0430\u0434\u0430"
    ],
    "wof:name":"Sada",
    "wof:placetype":"locality"
},
  "geometry": {"coordinates":[51.82358,58.28648000000001],"type":"Point"}
}