{
  "type": "Feature",
  "properties": {
    "gn:admin1_code":"40",
    "gn:asciiname":"Batyrevo",
    "gn:country_code":"RU",
    "gn:dem":149,
    "gn:feature_class":"P",
    "gn:feature_code":"PPL",
    "gn:name":"Batyrevo",
    "gn:population":0,
    "gn:timezone":"Asia/Yekaterinburg",
    "iso:country":"RU",
    "name:nor_x_preferred":[
        "Batyrevo"
    ],
    "name:rus_x_preferred":[
        "\u0411\u0430\u0442\u044b\u0440\u0435\u0432\u043e"
    ],
    "wof:name":"Batyrevo",
    "wof:placetype":"locality"
},
  "geometry": {"coordinates":[66.36028,54.88806],"type":"Point"}
}