{
  "type": "Feature",
  "properties": {
    "gn:admin1_code":"6.0",
    "gn:asciiname":"Lomovoye",
    "gn:country_code":"RU",
    "gn:dem":107,
    "gn:feature_class":"P",
    "gn:feature_code":"PPL",
    "gn:name":"Lomovoye",
    "gn:population":0,
    "gn:timezone":"Europe/Moscow",
    "iso:country":"RU",
    "name:rus_x_preferred":[
        "\u041b\u043e\u043c\u043e\u0432\u043e\u0435"
    ],
    "name:und_x_variant":[
        "\u041b\u043e\u043c\u043e\u0432\u043e\u0435"
    ],
    "wof:name":"Lomovoye",
    "wof:placetype":"locality"
},
  "geometry": {"coordinates":[40.659,64.0074],"type":"Point"}
}