{
  "type": "Feature",
  "properties": {
    "gn:admin1_code":"69",
    "gn:asciiname":"Malyy Ray",
    "gn:country_code":"RU",
    "gn:dem":189,
    "gn:feature_class":"P",
    "gn:feature_code":"PPL",
    "gn:name":"Malyy Ray",
    "gn:population":0,
    "gn:timezone":"Europe/Moscow",
    "iso:country":"RU",
    "name:rus_x_preferred":[
        "\u041c\u0430\u043b\u044b\u0439 \u0420\u0430\u0439"
    ],
    "name:und_x_variant":[
        "Maly Ray",
        "Malyy Ray"
    ],
    "wof:name":"Malyy Ray",
    "wof:placetype":"locality"
},
  "geometry": {"coordinates":[31.52732,54.1643],"type":"Point"}
}