{
  "type": "Feature",
  "properties": {
    "gn:admin1_code":"33.0",
    "gn:asciiname":"Mokretsy",
    "gn:country_code":"RU",
    "gn:dem":134,
    "gn:feature_class":"P",
    "gn:feature_code":"PPL",
    "gn:name":"Mokretsy",
    "gn:population":0,
    "gn:timezone":"Europe/Kirov",
    "iso:country":"RU",
    "name:rus_x_preferred":[
        "\u041c\u043e\u043a\u0440\u0435\u0446\u044b"
    ],
    "name:und_x_variant":[
        "\u041c\u043e\u043a\u0440\u0435\u0446\u044b"
    ],
    "wof:name":"Mokretsy",
    "wof:placetype":"locality"
},
  "geometry": {"coordinates":[49.67447,58.48984],"type":"Point"}
}