{
  "type": "Feature",
  "properties": {
    "gn:admin1_code":"37",
    "gn:asciiname":"Darovitsa",
    "gn:country_code":"RU",
    "gn:dem":190,
    "gn:feature_class":"P",
    "gn:feature_code":"PPL",
    "gn:name":"Darovitsa",
    "gn:population":0,
    "gn:timezone":"Europe/Moscow",
    "iso:country":"RU",
    "name:rus_x_preferred":[
        "\u0414\u0430\u0440\u043e\u0432\u0438\u0446\u0430"
    ],
    "wof:name":"Darovitsa",
    "wof:placetype":"locality"
},
  "geometry": {"coordinates":[43.7841,58.6139],"type":"Point"}
}