{
  "type": "Feature",
  "properties": {
    "gn:admin1_code":"45.0",
    "gn:asciiname":"Kundushumbal",
    "gn:country_code":"RU",
    "gn:dem":133,
    "gn:feature_class":"P",
    "gn:feature_code":"PPL",
    "gn:name":"Kundushumbal",
    "gn:population":0,
    "gn:timezone":"Europe/Moscow",
    "iso:country":"RU",
    "name:rus_x_preferred":[
        "\u041a\u0443\u043d\u0434\u0443\u0448\u0443\u043c\u0431\u0430\u043b"
    ],
    "wof:name":"Kundushumbal",
    "wof:placetype":"locality"
},
  "geometry": {"coordinates":[48.64417,56.72639],"type":"Point"}
}