{
  "type": "Feature",
  "properties": {
    "gn:admin1_code":"38",
    "gn:asciiname":"Kazachiy",
    "gn:country_code":"RU",
    "gn:dem":-4,
    "gn:feature_class":"P",
    "gn:feature_code":"PPL",
    "gn:name":"Kazachiy",
    "gn:population":0,
    "gn:timezone":"Europe/Moscow",
    "iso:country":"RU",
    "name:rus_x_preferred":[
        "\u041a\u0430\u0437\u0430\u0447\u0438\u0439"
    ],
    "name:und_x_variant":[
        "\u041a\u0430\u0437\u0430\u0447\u0438\u0439"
    ],
    "wof:name":"Kazachiy",
    "wof:placetype":"locality"
},
  "geometry": {"coordinates":[38.66667,45.98333],"type":"Point"}
}