{
  "type": "Feature",
  "properties": {
    "gn:admin1_code":"63",
    "gn:asciiname":"Zhirkova",
    "gn:country_code":"RU",
    "gn:dem":15,
    "gn:feature_class":"P",
    "gn:feature_code":"PPL",
    "gn:name":"Zhirkova",
    "gn:population":0,
    "gn:timezone":"Asia/Magadan",
    "iso:country":"RU",
    "name:und_x_variant":[
        "Zhirkovo",
        "Zhirnova",
        "Zhirkova"
    ],
    "wof:name":"Zhirkova",
    "wof:placetype":"locality"
},
  "geometry": {"coordinates":[155.79336999999995,67.56813000000001],"type":"Point"}
}