{
  "type": "Feature",
  "properties": {
    "gn:admin1_code":"17",
    "gn:asciiname":"Novonadezhdovka",
    "gn:country_code":"RU",
    "gn:dem":-12,
    "gn:feature_class":"P",
    "gn:feature_code":"PPL",
    "gn:name":"Novonadezhdovka",
    "gn:population":0,
    "gn:timezone":"Europe/Moscow",
    "iso:country":"RU",
    "name:rus_x_preferred":[
        "\u041d\u043e\u0432\u043e\u043d\u0430\u0434\u0435\u0436\u0434\u043e\u0432\u043a\u0430"
    ],
    "wof:name":"Novonadezhdovka",
    "wof:placetype":"locality"
},
  "geometry": {"coordinates":[46.93295,43.83556],"type":"Point"}
}