{
  "type": "Feature",
  "properties": {
    "gn:admin1_code":"44",
    "gn:asciiname":"Suchaynyy",
    "gn:country_code":"RU",
    "gn:dem":557,
    "gn:feature_class":"P",
    "gn:feature_code":"PPL",
    "gn:name":"Suchaynyy",
    "gn:population":0,
    "gn:timezone":"Asia/Magadan",
    "iso:country":"RU",
    "name:rus_x_preferred":[
        "\u0421\u0443\u0447\u0430\u0439\u043d\u044b\u0439"
    ],
    "wof:name":"Suchaynyy",
    "wof:placetype":"locality"
},
  "geometry": {"coordinates":[151.56666999999999,62.41667],"type":"Point"}
}