{
  "type": "Feature",
  "properties": {
    "gn:admin1_code":"71",
    "gn:asciiname":"Vakhtovyy",
    "gn:country_code":"RU",
    "gn:dem":212,
    "gn:feature_class":"P",
    "gn:feature_code":"PPL",
    "gn:name":"Vakhtovyy",
    "gn:population":0,
    "gn:timezone":"Asia/Yekaterinburg",
    "iso:country":"RU",
    "name:rus_x_preferred":[
        "\u0412\u0430\u0445\u0442\u043e\u0432\u044b\u0439"
    ],
    "wof:name":"Vakhtovyy",
    "wof:placetype":"locality"
},
  "geometry": {"coordinates":[58.0461,57.1103],"type":"Point"}
}