{
  "type": "Feature",
  "properties": {
    "gn:admin1_code":"21",
    "gn:asciiname":"Koshcheyevo",
    "gn:country_code":"RU",
    "gn:dem":110,
    "gn:feature_class":"P",
    "gn:feature_code":"PPL",
    "gn:name":"Koshcheyevo",
    "gn:population":0,
    "gn:timezone":"Europe/Moscow",
    "iso:country":"RU",
    "name:rus_x_preferred":[
        "\u041a\u043e\u0449\u0435\u0435\u0432\u043e"
    ],
    "name:und_x_variant":[
        "Koshchayevo",
        "Koshcheyevo",
        "\u041a\u043e\u0449\u0435\u0435\u0432\u043e"
    ],
    "wof:name":"Koshcheyevo",
    "wof:placetype":"locality"
},
  "geometry": {"coordinates":[41.52146,57.152],"type":"Point"}
}