{
  "type": "Feature",
  "properties": {
    "gn:admin1_code":"90",
    "gn:asciiname":"Nizhnyaya Kiga",
    "gn:country_code":"RU",
    "gn:dem":137,
    "gn:feature_class":"P",
    "gn:feature_code":"PPL",
    "gn:name":"Nizhnyaya Kiga",
    "gn:population":0,
    "gn:timezone":"Asia/Yekaterinburg",
    "iso:country":"RU",
    "name:rus_x_preferred":[
        "\u041d\u0438\u0436\u043d\u044f\u044f \u041a\u0438\u0433\u0430"
    ],
    "wof:name":"Nizhnyaya Kiga",
    "wof:placetype":"locality"
},
  "geometry": {"coordinates":[55.98333,56.46666999999999],"type":"Point"}
}