{
  "type": "Feature",
  "properties": {
    "gn:admin1_code":"40",
    "gn:asciiname":"Peschanotavolzhanskoye",
    "gn:country_code":"RU",
    "gn:dem":139,
    "gn:feature_class":"P",
    "gn:feature_code":"PPL",
    "gn:name":"Peschanotavolzhanskoye",
    "gn:population":0,
    "gn:timezone":"Asia/Yekaterinburg",
    "iso:country":"RU",
    "name:eng_x_preferred":[
        "Peschanotavolzhanskoye"
    ],
    "name:nor_x_preferred":[
        "Pestsjanotavolzjanskoje"
    ],
    "name:rus_x_preferred":[
        "\u041f\u0435\u0441\u0447\u0430\u043d\u043e\u0442\u0430\u0432\u043e\u043b\u0436\u0430\u043d\u0441\u043a\u043e\u0435"
    ],
    "wof:name":"Peschanotavolzhanskoye",
    "wof:placetype":"locality"
},
  "geometry": {"coordinates":[63.31806,55.7275],"type":"Point"}
}