{
  "type": "Feature",
  "properties": {
    "gn:admin1_code":"61.0",
    "gn:asciiname":"Fedorovskoye",
    "gn:cc2":"RU",
    "gn:country_code":"RU",
    "gn:dem":93,
    "gn:feature_class":"P",
    "gn:feature_code":"PPL",
    "gn:name":"F\u00ebdorovskoye",
    "gn:population":0,
    "gn:timezone":"Europe/Moscow",
    "iso:country":"RU",
    "name:rus_x_preferred":[
        "\u0424\u0451\u0434\u043e\u0440\u043e\u0432\u0441\u043a\u043e\u0435"
    ],
    "name:und_x_variant":[
        "Fedorovskiy",
        "F\u00ebdorovskoye",
        "\u0424\u0451\u0434\u043e\u0440\u043e\u0432\u0441\u043a\u043e\u0435"
    ],
    "wof:name":"Fedorovskoye",
    "wof:placetype":"locality"
},
  "geometry": {"coordinates":[41.41111,48.96028],"type":"Point"}
}