{
  "type": "Feature",
  "properties": {
    "gn:admin1_code":"88",
    "gn:asciiname":"Kupanskoye",
    "gn:cc2":"RU",
    "gn:country_code":"RU",
    "gn:dem":141,
    "gn:feature_class":"P",
    "gn:feature_code":"PPL",
    "gn:name":"Kupanskoye",
    "gn:population":0,
    "gn:timezone":"Europe/Moscow",
    "iso:country":"RU",
    "name:eng_x_preferred":[
        "Kupanskoye"
    ],
    "name:nor_x_preferred":[
        "Kupanskoje"
    ],
    "name:rus_x_preferred":[
        "\u041a\u0443\u043f\u0430\u043d\u0441\u043a\u043e\u0435"
    ],
    "name:und_x_variant":[
        "Usol\u2019ye",
        "Kupanskiy"
    ],
    "wof:name":"Kupanskoye",
    "wof:placetype":"locality"
},
  "geometry": {"coordinates":[38.67167,56.81667],"type":"Point"}
}