{
  "type": "Feature",
  "properties": {
    "gn:country":"RU",
    "gn:fcode":"PPL",
    "gn:population":0,
    "iso:country":"RU",
    "name:eng_x_preferred":[
        "Prishib"
    ],
    "name:nor_x_preferred":[
        "Prisjib"
    ],
    "name:rus_x_preferred":[
        "\u041f\u0440\u0438\u0448\u0438\u0431"
    ],
    "qs:name":"Prishib",
    "qs:name_adm0":"Russia",
    "qs:name_adm1":"Omsk Oblast",
    "qs:photos_9r":0,
    "qs:photos_sr":0,
    "qs:placetype":"Town",
    "qs:pop_sr":"0",
    "wd:wordcount":139,
    "wof:name":"Prishib",
    "wof:placetype":"locality",
    "wof:population":0
},
  "geometry": {"coordinates":[73.06381,54.43194],"type":"Point"}
}