{
  "type": "Feature",
  "properties": {
    "gn:admin1_code":"85.0",
    "gn:asciiname":"Bol'shoye Zaymishche",
    "gn:country_code":"RU",
    "gn:dem":146,
    "gn:feature_class":"P",
    "gn:feature_code":"PPL",
    "gn:name":"Bol\u2019shoye Zaymishche",
    "gn:population":0,
    "gn:timezone":"Europe/Moscow",
    "iso:country":"RU",
    "name:rus_x_preferred":[
        "\u0411\u043e\u043b\u044c\u0448\u043e\u0435 \u0417\u0430\u0439\u043c\u0438\u0449\u0435"
    ],
    "name:und_x_variant":[
        "Bol\u2019she-Zaymishche",
        "Bol\u2019shoye Zaymishche",
        "\u0411\u043e\u043b\u044c\u0448\u043e\u0435 \u0417\u0430\u0439\u043c\u0438\u0449\u0435"
    ],
    "wof:name":"Bol'shoye Zaymishche",
    "wof:placetype":"locality"
},
  "geometry": {"coordinates":[40.51095,58.92914],"type":"Point"}
}