{
  "type": "Feature",
  "properties": {
    "gn:admin1_code":"65.0",
    "gn:asciiname":"Bogdanovka",
    "gn:country_code":"RU",
    "gn:dem":70,
    "gn:feature_class":"P",
    "gn:feature_code":"PPL",
    "gn:name":"Bogdanovka",
    "gn:population":0,
    "gn:timezone":"Europe/Samara",
    "iso:country":"RU",
    "name:eng_x_preferred":[
        "Bogdanovka"
    ],
    "name:nor_x_preferred":[
        "Bogdanovka"
    ],
    "name:rus_x_preferred":[
        "\u0411\u043e\u0433\u0434\u0430\u043d\u043e\u0432\u043a\u0430"
    ],
    "name:und_x_variant":[
        "\u0411\u043e\u0433\u0434\u0430\u043d\u043e\u0432\u043a\u0430",
        "Bogdanovka"
    ],
    "wof:name":"Bogdanovka",
    "wof:placetype":"locality"
},
  "geometry": {"coordinates":[51.56473,53.20355],"type":"Point"}
}