{
  "type": "Feature",
  "properties": {
    "gn:admin1_code":"69",
    "gn:asciiname":"Solov'yevka",
    "gn:country_code":"RU",
    "gn:dem":191,
    "gn:feature_class":"P",
    "gn:feature_code":"PPL",
    "gn:name":"Solov\u2019y\u00ebvka",
    "gn:population":0,
    "gn:timezone":"Europe/Moscow",
    "iso:country":"RU",
    "name:rus_x_preferred":[
        "\u0421\u043e\u043b\u043e\u0432\u044c\u0451\u0432\u043a\u0430"
    ],
    "name:und_x_variant":[
        "Solov\u2019y\u00ebvka"
    ],
    "wof:name":"Solov'yevka",
    "wof:placetype":"locality"
},
  "geometry": {"coordinates":[32.1041,54.38],"type":"Point"}
}