{
  "type": "Feature",
  "properties": {
    "gn:admin1_code":"69",
    "gn:asciiname":"Bulokhovo",
    "gn:country_code":"RU",
    "gn:dem":170,
    "gn:feature_class":"P",
    "gn:feature_code":"PPL",
    "gn:name":"Bulokhovo",
    "gn:population":0,
    "gn:timezone":"Europe/Moscow",
    "iso:country":"RU",
    "name:rus_x_preferred":[
        "\u0411\u0443\u043b\u043e\u0445\u043e\u0432\u043e"
    ],
    "name:und_x_variant":[
        "\u0411\u0443\u043b\u043e\u0445\u043e\u0432\u043e"
    ],
    "wof:name":"Bulokhovo",
    "wof:placetype":"locality"
},
  "geometry": {"coordinates":[30.98028,55.26944],"type":"Point"}
}