{
  "type": "Feature",
  "properties": {
    "gn:admin1_code":"62",
    "gn:asciiname":"Aleshina",
    "gn:country_code":"RU",
    "gn:dem":108,
    "gn:feature_class":"P",
    "gn:feature_code":"PPL",
    "gn:name":"Aleshina",
    "gn:population":0,
    "gn:timezone":"Europe/Moscow",
    "iso:country":"RU",
    "name:nor_x_preferred":[
        "Alesjina"
    ],
    "name:rus_x_preferred":[
        "\u0410\u043b\u0435\u0448\u0438\u043d\u0430"
    ],
    "wof:name":"Aleshina",
    "wof:placetype":"locality"
},
  "geometry": {"coordinates":[41.07444,53.84278000000001],"type":"Point"}
}