{
  "type": "Feature",
  "properties": {
    "gn:admin1_code":"61",
    "gn:asciiname":"Kucherovka",
    "gn:country_code":"RU",
    "gn:dem":20,
    "gn:feature_class":"P",
    "gn:feature_code":"PPL",
    "gn:name":"Kucherovka",
    "gn:population":0,
    "gn:timezone":"Europe/Moscow",
    "iso:country":"RU",
    "name:rus_x_preferred":[
        "\u041a\u0443\u0447\u0435\u0440\u043e\u0432\u043a\u0430"
    ],
    "name:und_x_variant":[
        "Kucherovo",
        "Kucherovka"
    ],
    "wof:name":"Kucherovka",
    "wof:placetype":"locality"
},
  "geometry": {"coordinates":[38.88569,47.67628],"type":"Point"}
}