{
  "type": "Feature",
  "properties": {
    "gn:admin1_code":"73",
    "gn:asciiname":"Toygil'dy",
    "gn:country_code":"RU",
    "gn:dem":127,
    "gn:feature_class":"P",
    "gn:feature_code":"PPL",
    "gn:name":"Toygil\u2019dy",
    "gn:population":0,
    "gn:timezone":"Europe/Moscow",
    "iso:country":"RU",
    "name:und_x_variant":[
        "Toygildino",
        "Toygil\u2019dy"
    ],
    "wof:name":"Toygil'dy",
    "wof:placetype":"locality"
},
  "geometry": {"coordinates":[48.05358,55.05035],"type":"Point"}
}