{
  "type": "Feature",
  "properties": {
    "gn:admin1_code":"4",
    "gn:asciiname":"Vershina Bashchelaka",
    "gn:country_code":"RU",
    "gn:dem":855,
    "gn:feature_class":"P",
    "gn:feature_code":"PPL",
    "gn:name":"Vershina Bashchelaka",
    "gn:population":0,
    "gn:timezone":"Asia/Barnaul",
    "iso:country":"RU",
    "wof:name":"Vershina Bashchelaka",
    "wof:placetype":"locality"
},
  "geometry": {"coordinates":[84.13333,51.38333],"type":"Point"}
}