{
  "type": "Feature",
  "properties": {
    "gn:admin1_code":"25",
    "gn:asciiname":"Bogat'kovo",
    "gn:country_code":"RU",
    "gn:dem":229,
    "gn:feature_class":"P",
    "gn:feature_code":"PPL",
    "gn:name":"\u0411\u043e\u0433\u0430\u0442\u044c\u043a\u043e\u0432\u043e",
    "gn:population":0,
    "gn:timezone":"Europe/Moscow",
    "iso:country":"RU",
    "name:rus_x_preferred":[
        "\u0411\u043e\u0433\u0430\u0442\u044c\u043a\u043e\u0432\u043e"
    ],
    "name:und_x_variant":[
        "Bogat\u2019kovo"
    ],
    "wof:name":"Bogat'kovo",
    "wof:placetype":"locality"
},
  "geometry": {"coordinates":[35.33685,54.01677],"type":"Point"}
}