{
  "type": "Feature",
  "properties": {
    "gn:admin1_code":"90.0",
    "gn:asciiname":"Beloborodovo",
    "gn:country_code":"RU",
    "gn:dem":156,
    "gn:feature_class":"P",
    "gn:feature_code":"PPL",
    "gn:name":"Beloborodovo",
    "gn:population":0,
    "gn:timezone":"Asia/Yekaterinburg",
    "iso:country":"RU",
    "name:rus_x_preferred":[
        "\u0411\u0435\u043b\u043e\u0431\u043e\u0440\u043e\u0434\u043e\u0432\u043e"
    ],
    "wof:name":"Beloborodovo",
    "wof:placetype":"locality"
},
  "geometry": {"coordinates":[54.72026999999999,57.83763],"type":"Point"}
}