{
  "type": "Feature",
  "properties": {
    "gn:admin1_code":"9",
    "gn:asciiname":"Lugi",
    "gn:country_code":"RU",
    "gn:dem":137,
    "gn:feature_class":"P",
    "gn:feature_code":"PPL",
    "gn:name":"Lugi",
    "gn:population":0,
    "gn:timezone":"Europe/Moscow",
    "iso:country":"RU",
    "name:rus_x_preferred":[
        "\u041b\u0443\u0433\u0438"
    ],
    "name:und_x_variant":[
        "\u041b\u0443\u0433\u0438"
    ],
    "wof:name":"Lugi",
    "wof:placetype":"locality"
},
  "geometry": {"coordinates":[37.76667,51.38333],"type":"Point"}
}