{
  "type": "Feature",
  "properties": {
    "gn:admin1_code":"69",
    "gn:asciiname":"Khateyevka",
    "gn:cc2":"RU",
    "gn:country_code":"RU",
    "gn:dem":203,
    "gn:feature_class":"P",
    "gn:feature_code":"PPL",
    "gn:name":"Khateyevka",
    "gn:population":0,
    "gn:timezone":"Europe/Moscow",
    "iso:country":"RU",
    "name:rus_x_preferred":[
        "\u0425\u0430\u0442\u0435\u0435\u0432\u043a\u0430"
    ],
    "name:und_x_variant":[
        "Khoteyevka",
        "Khateyevka",
        "\u0425\u0430\u0442\u0435\u0435\u0432\u043a\u0430"
    ],
    "wof:name":"Khateyevka",
    "wof:placetype":"locality"
},
  "geometry": {"coordinates":[32.98333,54.11666999999999],"type":"Point"}
}