{
  "type": "Feature",
  "properties": {
    "gn:admin1_code":"21.0",
    "gn:asciiname":"Pleshakovo",
    "gn:country_code":"RU",
    "gn:dem":121,
    "gn:feature_class":"P",
    "gn:feature_code":"PPL",
    "gn:name":"Pleshakovo",
    "gn:population":0,
    "gn:timezone":"Europe/Moscow",
    "iso:country":"RU",
    "name:nor_x_preferred":[
        "Plesjakovo"
    ],
    "name:rus_x_preferred":[
        "\u041f\u043b\u0435\u0448\u0430\u043a\u043e\u0432\u043e"
    ],
    "wof:name":"Pleshakovo",
    "wof:placetype":"locality"
},
  "geometry": {"coordinates":[42.96643,56.86424],"type":"Point"}
}