{
  "type": "Feature",
  "properties": {
    "gn:admin1_code":"17.0",
    "gn:asciiname":"Shimere-Ulyuk",
    "gn:country_code":"RU",
    "gn:dem":-3,
    "gn:feature_class":"P",
    "gn:feature_code":"PPL",
    "gn:name":"Shimere-Ulyuk",
    "gn:population":0,
    "gn:timezone":"Europe/Moscow",
    "iso:country":"RU",
    "wof:name":"Shimere-Ulyuk",
    "wof:placetype":"locality"
},
  "geometry": {"coordinates":[45.96444,44.55028],"type":"Point"}
}