{
  "type": "Feature",
  "properties": {
    "gn:admin1_code":"90.0",
    "gn:asciiname":"Pal'nik",
    "gn:country_code":"RU",
    "gn:dem":153,
    "gn:feature_class":"P",
    "gn:feature_code":"PPL",
    "gn:name":"Pal\u2019nik",
    "gn:population":0,
    "gn:timezone":"Asia/Yekaterinburg",
    "iso:country":"RU",
    "name:rus_x_preferred":[
        "\u041f\u0430\u043b\u044c\u043d\u0438\u043a"
    ],
    "name:und_x_variant":[
        "Pal\u2019nik"
    ],
    "wof:name":"Pal'nik",
    "wof:placetype":"locality"
},
  "geometry": {"coordinates":[56.2795,59.9182],"type":"Point"}
}