{
  "type": "Feature",
  "properties": {
    "gn:admin1_code":"88",
    "gn:asciiname":"Svobodnoye",
    "gn:country_code":"RU",
    "gn:dem":223,
    "gn:feature_class":"P",
    "gn:feature_code":"PPL",
    "gn:name":"Svobodnoye",
    "gn:population":0,
    "gn:timezone":"Europe/Moscow",
    "iso:country":"RU",
    "name:rus_x_preferred":[
        "\u0421\u0432\u043e\u0431\u043e\u0434\u043d\u043e\u0435"
    ],
    "name:und_x_variant":[
        "Nikol\u2019skoye",
        "Svobodnoye"
    ],
    "wof:name":"Svobodnoye",
    "wof:placetype":"locality"
},
  "geometry": {"coordinates":[38.53333,57.13333000000001],"type":"Point"}
}