{
  "type": "Feature",
  "properties": {
    "gn:admin1_code":"8",
    "gn:asciiname":"Simbirskiy",
    "gn:country_code":"RU",
    "gn:dem":180,
    "gn:feature_class":"P",
    "gn:feature_code":"PPL",
    "gn:name":"Simbirskiy",
    "gn:population":0,
    "gn:timezone":"Asia/Yekaterinburg",
    "iso:country":"RU",
    "name:rus_x_preferred":[
        "\u0421\u0438\u043c\u0431\u0438\u0440\u0441\u043a\u0438\u0439"
    ],
    "wof:name":"Simbirskiy",
    "wof:placetype":"locality"
},
  "geometry": {"coordinates":[56.55174,52.2564],"type":"Point"}
}