{
  "type": "Feature",
  "properties": {
    "gn:admin1_code":"77",
    "gn:asciiname":"Zhiroma",
    "gn:country_code":"RU",
    "gn:dem":234,
    "gn:feature_class":"P",
    "gn:feature_code":"PPL",
    "gn:name":"Zhiroma",
    "gn:population":0,
    "gn:timezone":"Europe/Moscow",
    "iso:country":"RU",
    "name:rus_x_preferred":[
        "\u0416\u0438\u0440\u043e\u043c\u0430"
    ],
    "name:und_x_variant":[
        "Zhiromo",
        "Zhiroma"
    ],
    "wof:name":"Zhiroma",
    "wof:placetype":"locality"
},
  "geometry": {"coordinates":[32.70342,57.30016],"type":"Point"}
}