{
  "type": "Feature",
  "properties": {
    "gn:admin1_code":"85.0",
    "gn:asciiname":"Abanino",
    "gn:country_code":"RU",
    "gn:dem":187,
    "gn:feature_class":"P",
    "gn:feature_code":"PPL",
    "gn:name":"Abanino",
    "gn:population":0,
    "gn:timezone":"Europe/Moscow",
    "iso:country":"RU",
    "name:che_x_preferred":[
        "\u0410\u0431\u0430\u043d\u0438\u043d\u043e"
    ],
    "name:nor_x_preferred":[
        "Abanino"
    ],
    "name:rus_x_preferred":[
        "\u0410\u0431\u0430\u043d\u0438\u043d\u043e"
    ],
    "wof:name":"Abanino",
    "wof:placetype":"locality"
},
  "geometry": {"coordinates":[40.31711,58.70324],"type":"Point"}
}