{
  "type": "Feature",
  "properties": {
    "gn:admin1_code":"37",
    "gn:asciiname":"Ozhegino",
    "gn:country_code":"RU",
    "gn:dem":131,
    "gn:feature_class":"P",
    "gn:feature_code":"PPL",
    "gn:name":"Ozhegino",
    "gn:population":0,
    "gn:timezone":"Europe/Moscow",
    "iso:country":"RU",
    "name:rus_x_preferred":[
        "\u041e\u0436\u0435\u0433\u0438\u043d\u043e"
    ],
    "name:und_x_variant":[
        "Ozhogino"
    ],
    "wof:name":"Ozhegino",
    "wof:placetype":"locality"
},
  "geometry": {"coordinates":[42.06992,58.48498000000001],"type":"Point"}
}