{
  "type": "Feature",
  "properties": {
    "gn:admin1_code":"25",
    "gn:asciiname":"Lutkino",
    "gn:country_code":"RU",
    "gn:dem":215,
    "gn:feature_class":"P",
    "gn:feature_code":"PPL",
    "gn:name":"Lutkino",
    "gn:population":0,
    "gn:timezone":"Europe/Moscow",
    "iso:country":"RU",
    "name:rus_x_preferred":[
        "\u041b\u0443\u0442\u043a\u0438\u043d\u043e"
    ],
    "name:und_x_variant":[
        "Lutkina",
        "Lutkino",
        "\u041b\u0443\u0442\u043a\u0438\u043d\u043e"
    ],
    "wof:name":"Lutkino",
    "wof:placetype":"locality"
},
  "geometry": {"coordinates":[35.42547000000001,55.06614],"type":"Point"}
}