{
  "type": "Feature",
  "properties": {
    "gn:admin1_code":"80",
    "gn:asciiname":"Verkhniy Bemyzh",
    "gn:country_code":"RU",
    "gn:dem":150,
    "gn:feature_class":"P",
    "gn:feature_code":"PPL",
    "gn:name":"Verkhniy Bemyzh",
    "gn:population":0,
    "gn:timezone":"Europe/Samara",
    "iso:country":"RU",
    "name:eng_x_preferred":[
        "Verkhniy Bemyzh"
    ],
    "name:nor_x_preferred":[
        "Verkh.Bemyzj"
    ],
    "name:rus_x_preferred":[
        "\u0412\u0435\u0440\u0445.\u0411\u0435\u043c\u044b\u0436"
    ],
    "wof:name":"Verkhniy Bemyzh",
    "wof:placetype":"locality"
},
  "geometry": {"coordinates":[51.71529,56.22755],"type":"Point"}
}