{
  "type": "Feature",
  "properties": {
    "gn:admin1_code":"59",
    "gn:asciiname":"Severnaya",
    "gn:country_code":"RU",
    "gn:dem":402,
    "gn:feature_class":"P",
    "gn:feature_code":"PPL",
    "gn:name":"Severnaya",
    "gn:population":0,
    "gn:timezone":"Asia/Vladivostok",
    "iso:country":"RU",
    "name:rus_x_preferred":[
        "\u0421\u0435\u0432\u0435\u0440\u043d\u0430\u044f"
    ],
    "name:und_x_variant":[
        "\u0421\u0435\u0432\u0435\u0440\u043d\u0430\u044f"
    ],
    "wof:name":"Severnaya",
    "wof:placetype":"locality"
},
  "geometry": {"coordinates":[131.68333000000001,45.05],"type":"Point"}
}