{
  "type": "Feature",
  "properties": {
    "gn:admin1_code":"85",
    "gn:asciiname":"Kholka",
    "gn:country_code":"RU",
    "gn:dem":164,
    "gn:feature_class":"P",
    "gn:feature_code":"PPL",
    "gn:name":"Kholka",
    "gn:population":0,
    "gn:timezone":"Europe/Moscow",
    "iso:country":"RU",
    "name:rus_x_preferred":[
        "\u0425\u043e\u043b\u043a\u0430"
    ],
    "name:und_x_variant":[
        "\u0425\u043e\u043b\u043a\u0430"
    ],
    "wof:name":"Kholka",
    "wof:placetype":"locality"
},
  "geometry": {"coordinates":[45.54905,60.10025],"type":"Point"}
}