{
  "type": "Feature",
  "properties": {
    "gn:admin1_code":"52",
    "gn:asciiname":"Kolomino",
    "gn:country_code":"RU",
    "gn:dem":177,
    "gn:feature_class":"P",
    "gn:feature_code":"PPL",
    "gn:name":"Kolomino",
    "gn:population":0,
    "gn:timezone":"Europe/Moscow",
    "iso:country":"RU",
    "name:rus_x_preferred":[
        "\u041a\u043e\u043b\u043e\u043c\u0438\u043d\u043e"
    ],
    "name:und_x_variant":[
        "\u041a\u043e\u043b\u043e\u043c\u0438\u043d\u043e"
    ],
    "wof:name":"Kolomino",
    "wof:placetype":"locality"
},
  "geometry": {"coordinates":[35.13333,58.75],"type":"Point"}
}