{
  "type": "Feature",
  "properties": {
    "gn:admin1_code":"77",
    "gn:asciiname":"Podberez'ye",
    "gn:country_code":"RU",
    "gn:dem":152,
    "gn:feature_class":"P",
    "gn:feature_code":"PPL",
    "gn:name":"Podberez\u2019ye",
    "gn:population":0,
    "gn:timezone":"Europe/Moscow",
    "iso:country":"RU",
    "name:rus_x_preferred":[
        "\u041f\u043e\u0434\u0431\u0435\u0440\u0435\u0437\u044c\u0435"
    ],
    "name:und_x_variant":[
        "Podberez\u2019ye",
        "\u041f\u043e\u0434\u0431\u0435\u0440\u0435\u0437\u044c\u0435"
    ],
    "wof:name":"Podberez'ye",
    "wof:placetype":"locality"
},
  "geometry": {"coordinates":[37.0077,57.3515],"type":"Point"}
}