{
  "type": "Feature",
  "properties": {
    "gn:admin1_code":"47.0",
    "gn:asciiname":"Nemchinovo",
    "gn:country_code":"RU",
    "gn:dem":157,
    "gn:feature_class":"P",
    "gn:feature_code":"PPL",
    "gn:name":"Nemchinovo",
    "gn:population":0,
    "gn:timezone":"Europe/Moscow",
    "iso:country":"RU",
    "name:rus_x_preferred":[
        "\u041d\u0435\u043c\u0447\u0438\u043d\u043e\u0432\u043e"
    ],
    "name:und_x_variant":[
        "\u041d\u0435\u043c\u0447\u0438\u043d\u043e\u0432\u043e"
    ],
    "wof:name":"Nemchinovo",
    "wof:placetype":"locality"
},
  "geometry": {"coordinates":[37.36207,55.67859],"type":"Point"}
}