{
  "type": "Feature",
  "properties": {
    "gn:admin1_code":"28",
    "gn:asciiname":"Yan'gozero",
    "gn:country_code":"RU",
    "gn:dem":156,
    "gn:feature_class":"P",
    "gn:feature_code":"PPL",
    "gn:name":"Yan\u2019gozero",
    "gn:population":0,
    "gn:timezone":"Europe/Moscow",
    "iso:country":"RU",
    "name:eng_x_preferred":[
        "Yan'gozero"
    ],
    "name:nor_x_preferred":[
        "Jangozero"
    ],
    "name:rus_x_preferred":[
        "\u042f\u043d\u0433\u043e\u0437\u0435\u0440\u043e"
    ],
    "name:und_x_variant":[
        "Jankijarvi",
        "Yan\u2019gozero"
    ],
    "wof:name":"Yan'gozero",
    "wof:placetype":"locality"
},
  "geometry": {"coordinates":[36.54368,62.62466],"type":"Point"}
}