{
  "type": "Feature",
  "properties": {
    "gn:admin1_code":"88",
    "gn:asciiname":"Novyy Pokrovok",
    "gn:country_code":"RU",
    "gn:dem":133,
    "gn:feature_class":"P",
    "gn:feature_code":"PPL",
    "gn:name":"Novyy Pokrovok",
    "gn:population":0,
    "gn:timezone":"Europe/Moscow",
    "iso:country":"RU",
    "name:rus_x_preferred":[
        "\u041d\u043e\u0432\u044b\u0439 \u041f\u043e\u043a\u0440\u043e\u0432\u043e\u043a"
    ],
    "wof:name":"Novyy Pokrovok",
    "wof:placetype":"locality"
},
  "geometry": {"coordinates":[37.7764,58.3355],"type":"Point"}
}