{
  "type": "Feature",
  "properties": {
    "gn:admin1_code":"65.0",
    "gn:asciiname":"Ust'-Kinel'skiy",
    "gn:country_code":"RU",
    "gn:dem":53,
    "gn:feature_class":"P",
    "gn:feature_code":"PPL",
    "gn:name":"Ust\u2019-Kinel\u2019skiy",
    "gn:population":0,
    "gn:timezone":"Europe/Samara",
    "iso:country":"RU",
    "name:rus_x_preferred":[
        "\u0423\u0441\u0442\u044c-\u041a\u0438\u043d\u0435\u043b\u044c\u0441\u043a\u0438\u0439"
    ],
    "name:und_x_variant":[
        "Ust\u2019-Kinel\u2019skiy"
    ],
    "wof:name":"Ust'-Kinel'skiy",
    "wof:placetype":"locality"
},
  "geometry": {"coordinates":[50.57815,53.2682],"type":"Point"}
}