{
  "type": "Feature",
  "properties": {
    "gn:country":"RU",
    "gn:fcode":"PPL",
    "gn:population":0,
    "iso:country":"RU",
    "name:rus_x_preferred":[
        "\u0418\u043b\u044c\u0447\u0435\u043d\u043a\u043e"
    ],
    "name:und_x_variant":[
        "Il\u2019chenko"
    ],
    "qs:name":"Il'chenko",
    "qs:name_adm0":"Russia",
    "qs:name_adm1":"Tver Oblast",
    "qs:photos":6,
    "qs:photos_1k":1,
    "qs:photos_9k":1,
    "qs:photos_9r":1,
    "qs:photos_all":6,
    "qs:photos_sr":1,
    "qs:placetype":"Suburb",
    "qs:pop_sr":"0",
    "wof:name":"Il'chenko",
    "wof:placetype":"neighbourhood",
    "wof:population":0
},
  "geometry": {"coordinates":[34.33333,56.25],"type":"Point"}
}