{
  "type": "Feature",
  "properties": {
    "gn:admin1_code":"6.0",
    "gn:asciiname":"Borovskaya",
    "gn:country_code":"RU",
    "gn:dem":177,
    "gn:feature_class":"P",
    "gn:feature_code":"PPL",
    "gn:name":"Borovskaya",
    "gn:population":0,
    "gn:timezone":"Europe/Moscow",
    "iso:country":"RU",
    "name:rus_x_preferred":[
        "\u0411\u043e\u0440\u043e\u0432\u0441\u043a\u0430\u044f"
    ],
    "name:und_x_variant":[
        "\u0411\u043e\u0440\u043e\u0432\u0441\u043a\u0430\u044f"
    ],
    "wof:name":"Borovskaya",
    "wof:placetype":"locality"
},
  "geometry": {"coordinates":[41.01667,60.83333],"type":"Point"}
}