{
  "type": "Feature",
  "properties": {
    "gn:admin1_code":"61",
    "gn:asciiname":"Pavlov",
    "gn:country_code":"RU",
    "gn:dem":75,
    "gn:feature_class":"P",
    "gn:feature_code":"PPL",
    "gn:name":"Pavlov",
    "gn:population":0,
    "gn:timezone":"Europe/Moscow",
    "iso:country":"RU",
    "name:bel_x_preferred":[
        "\u041f\u0430\u045e\u043b\u0430\u045e"
    ],
    "name:bul_x_preferred":[
        "\u041f\u0430\u0432\u043b\u043e\u0432"
    ],
    "name:ceb_x_preferred":[
        "Pavlov"
    ],
    "name:ces_x_preferred":[
        "Pavlov"
    ],
    "name:chv_x_preferred":[
        "\u041f\u0430\u0432\u043b\u043e\u0432"
    ],
    "name:deu_x_preferred":[
        "Pavlov"
    ],
    "name:epo_x_preferred":[
        "Pavlov"
    ],
    "name:fin_x_preferred":[
        "Pavlov"
    ],
    "name:fra_x_preferred":[
        "Pavlov"
    ],
    "name:heb_x_preferred":[
        "\u05e4\u05d1\u05dc\u05d5\u05d1"
    ],
    "name:hye_x_preferred":[
        "\u054a\u0561\u057e\u056c\u0578\u057e"
    ],
    "name:ita_x_preferred":[
        "Pavlov"
    ],
    "name:jpn_x_preferred":[
        "\u30d1\u30f4\u30ed\u30d5"
    ],
    "name:lav_x_preferred":[
        "Pavlovs"
    ],
    "name:nld_x_preferred":[
        "Pavlov"
    ],
    "name:nor_x_preferred":[
        "Pavlov"
    ],
    "name:pol_x_preferred":[
        "Pavlov"
    ],
    "name:por_x_preferred":[
        "Pavlov"
    ],
    "name:rus_x_preferred":[
        "\u041f\u0430\u0432\u043b\u043e\u0432"
    ],
    "name:slk_x_preferred":[
        "Pavlov"
    ],
    "name:slv_x_preferred":[
        "Pavlov"
    ],
    "name:spa_x_preferred":[
        "Pavlov"
    ],
    "name:srp_x_preferred":[
        "\u041f\u0430\u0432\u043b\u043e\u0432"
    ],
    "name:tat_x_preferred":[
        "\u041f\u0430\u0432\u043b\u043e\u0432"
    ],
    "name:ukr_x_preferred":[
        "\u041f\u0430\u0432\u043b\u043e\u0432"
    ],
    "wof:name":"Pavlov",
    "wof:placetype":"locality"
},
  "geometry": {"coordinates":[40.73017,49.1403],"type":"Point"}
}