{
  "type": "Feature",
  "properties": {
    "gn:admin1_code":"83",
    "gn:asciiname":"Saulovo",
    "gn:country_code":"RU",
    "gn:dem":114,
    "gn:feature_class":"P",
    "gn:feature_code":"PPL",
    "gn:name":"Saulovo",
    "gn:population":0,
    "gn:timezone":"Europe/Moscow",
    "iso:country":"RU",
    "name:rus_x_preferred":[
        "\u0421\u0430\u0443\u043b\u043e\u0432\u043e"
    ],
    "wof:name":"Saulovo",
    "wof:placetype":"locality"
},
  "geometry": {"coordinates":[40.79658,56.40913000000001],"type":"Point"}
}