{
  "type": "Feature",
  "properties": {
    "gn:admin1_code":"42",
    "gn:admin2_code":"575409",
    "gn:asciiname":"Moshnya",
    "gn:country_code":"RU",
    "gn:dem":77,
    "gn:feature_class":"P",
    "gn:feature_code":"PPL",
    "gn:name":"Moshnya",
    "gn:population":0,
    "gn:timezone":"Europe/Moscow",
    "iso:country":"RU",
    "name:rus_x_preferred":[
        "\u041c\u043e\u0448\u043d\u044f"
    ],
    "wof:name":"Moshnya",
    "wof:placetype":"locality"
},
  "geometry": {"coordinates":[33.77889,59.40011],"type":"Point"}
}