{
  "type": "Feature",
  "properties": {
    "gn:admin1_code":"6",
    "gn:asciiname":"Krechetovo",
    "gn:country_code":"RU",
    "gn:dem":148,
    "gn:feature_class":"P",
    "gn:feature_code":"PPL",
    "gn:name":"Krechetovo",
    "gn:population":0,
    "gn:timezone":"Europe/Moscow",
    "iso:country":"RU",
    "name:eng_x_preferred":[
        "Krechetovo"
    ],
    "name:nor_x_preferred":[
        "Kretsjetovo"
    ],
    "name:rus_x_preferred":[
        "\u041a\u0440\u0435\u0447\u0435\u0442\u043e\u0432\u043e"
    ],
    "name:und_x_variant":[
        "\u041a\u0440\u0435\u0447\u0435\u0442\u043e\u0432\u043e",
        "Krechetovo"
    ],
    "wof:name":"Krechetovo",
    "wof:placetype":"locality"
},
  "geometry": {"coordinates":[38.51185,60.94864000000001],"type":"Point"}
}