{
  "type": "Feature",
  "properties": {
    "gn:admin1_code":"63",
    "gn:asciiname":"Ulu-Togo",
    "gn:country_code":"RU",
    "gn:dem":214,
    "gn:feature_class":"P",
    "gn:feature_code":"PPL",
    "gn:name":"Ulu-Togo",
    "gn:population":0,
    "gn:timezone":"Asia/Yakutsk",
    "iso:country":"RU",
    "name:eng_x_preferred":[
        "Ulu-Togo"
    ],
    "name:nor_x_preferred":[
        "Ulu-Togoj"
    ],
    "name:rus_x_preferred":[
        "\u0423\u043b\u0443-\u0422\u043e\u0433\u043e\u0439"
    ],
    "wof:name":"Ulu-Togo",
    "wof:placetype":"locality"
},
  "geometry": {"coordinates":[113.20303,62.97191],"type":"Point"}
}