{
  "type": "Feature",
  "properties": {
    "gn:admin1_code":"47",
    "gn:asciiname":"Kolychevo",
    "gn:country_code":"RU",
    "gn:dem":141,
    "gn:feature_class":"P",
    "gn:feature_code":"PPL",
    "gn:name":"Kolych\u00ebvo",
    "gn:population":0,
    "gn:timezone":"Europe/Moscow",
    "iso:country":"RU",
    "name:rus_x_preferred":[
        "\u041a\u043e\u043b\u044b\u0447\u0451\u0432\u043e"
    ],
    "name:und_x_variant":[
        "Kolych\u00ebvo",
        "\u041a\u043e\u043b\u044b\u0447\u0451\u0432\u043e"
    ],
    "wof:name":"Kolychevo",
    "wof:placetype":"locality"
},
  "geometry": {"coordinates":[37.85811,55.49177],"type":"Point"}
}