{
  "type": "Feature",
  "properties": {
    "gn:admin1_code":"85",
    "gn:asciiname":"Vanomozero",
    "gn:country_code":"RU",
    "gn:dem":140,
    "gn:feature_class":"P",
    "gn:feature_code":"PPL",
    "gn:name":"Vanomozero",
    "gn:population":0,
    "gn:timezone":"Europe/Moscow",
    "iso:country":"RU",
    "name:rus_x_preferred":[
        "\u0412\u0430\u043d\u043e\u043c\u043e\u0437\u0435\u0440\u043e"
    ],
    "wof:name":"Vanomozero",
    "wof:placetype":"locality"
},
  "geometry": {"coordinates":[38.0301,60.4064],"type":"Point"}
}