{
  "type": "Feature",
  "properties": {
    "gn:admin1_code":"63",
    "gn:asciiname":"Tas-Tumus",
    "gn:country_code":"RU",
    "gn:dem":110,
    "gn:feature_class":"P",
    "gn:feature_code":"PPL",
    "gn:name":"Tas-Tumus",
    "gn:population":0,
    "gn:timezone":"Asia/Yakutsk",
    "iso:country":"RU",
    "name:eng_x_preferred":[
        "Tas-Tumus"
    ],
    "name:nor_x_preferred":[
        "Tas-Tumus"
    ],
    "name:rus_x_preferred":[
        "\u0422\u0430\u0441-\u0422\u0443\u043c\u0443\u0441"
    ],
    "wof:name":"Tas-Tumus",
    "wof:placetype":"locality"
},
  "geometry": {"coordinates":[126.68322000000001,64.182],"type":"Point"}
}