{
  "type": "Feature",
  "properties": {
    "gn:admin1_code":"20",
    "gn:asciiname":"Kas'yanovka",
    "gn:country_code":"RU",
    "gn:dem":474,
    "gn:feature_class":"P",
    "gn:feature_code":"PPL",
    "gn:name":"Kas\u2019yanovka",
    "gn:population":0,
    "gn:timezone":"Asia/Irkutsk",
    "iso:country":"RU",
    "name:rus_x_preferred":[
        "\u041a\u0430\u0441\u044c\u044f\u043d\u043e\u0432\u043a\u0430"
    ],
    "name:und_x_variant":[
        "Kas\u2019yanovka"
    ],
    "wof:name":"Kas'yanovka",
    "wof:placetype":"locality"
},
  "geometry": {"coordinates":[103.58333,56.63333000000001],"type":"Point"}
}