{
  "type": "Feature",
  "properties": {
    "gn:admin1_code":"28",
    "gn:asciiname":"Valday",
    "gn:country_code":"RU",
    "gn:dem":90,
    "gn:feature_class":"P",
    "gn:feature_code":"PPL",
    "gn:name":"Valday",
    "gn:population":0,
    "gn:timezone":"Europe/Moscow",
    "iso:country":"RU",
    "name:chv_x_preferred":[
        "\u0412\u0430\u043b\u0434\u0430\u0439"
    ],
    "name:cym_x_preferred":[
        "Valdai"
    ],
    "name:deu_x_preferred":[
        "Valdai"
    ],
    "name:eng_x_preferred":[
        "Valday"
    ],
    "name:fin_x_preferred":[
        "Uikuj\u00e4rvi"
    ],
    "name:fin_x_variant":[
        "Valdai"
    ],
    "name:ita_x_preferred":[
        "Valdaj"
    ],
    "name:jpn_x_preferred":[
        "\u30f4\u30a1\u30eb\u30c0\u30a4"
    ],
    "name:nor_x_preferred":[
        "Valdaj"
    ],
    "name:pol_x_preferred":[
        "Wa\u0142daj"
    ],
    "name:rus_x_preferred":[
        "\u0412\u0430\u043b\u0434\u0430\u0439"
    ],
    "name:spa_x_preferred":[
        "Vald\u00e1i"
    ],
    "name:ukr_x_preferred":[
        "\u0412\u0430\u043b\u0434\u0430\u0439"
    ],
    "wof:name":"Valday",
    "wof:placetype":"locality"
},
  "geometry": {"coordinates":[35.51291,63.42898],"type":"Point"}
}