{
  "type": "Feature",
  "properties": {
    "gn:admin1_code":"57.0",
    "gn:asciiname":"Smychka",
    "gn:country_code":"RU",
    "gn:dem":238,
    "gn:feature_class":"P",
    "gn:feature_code":"PPL",
    "gn:name":"Smychka",
    "gn:population":0,
    "gn:timezone":"Europe/Moscow",
    "iso:country":"RU",
    "name:rus_x_preferred":[
        "\u0421\u043c\u044b\u0447\u043a\u0430"
    ],
    "wof:name":"Smychka",
    "wof:placetype":"locality"
},
  "geometry": {"coordinates":[45.8428,53.03106999999999],"type":"Point"}
}