{
  "type": "Feature",
  "properties": {
    "gn:admin1_code":"28",
    "gn:asciiname":"Torppa",
    "gn:country_code":"RU",
    "gn:dem":32,
    "gn:feature_class":"P",
    "gn:feature_code":"PPL",
    "gn:name":"Torppa",
    "gn:population":0,
    "gn:timezone":"Europe/Moscow",
    "iso:country":"RU",
    "name:fin_x_preferred":[
        "Puolam\u00e4ki"
    ],
    "wof:name":"Torppa",
    "wof:placetype":"locality"
},
  "geometry": {"coordinates":[30.86609,61.75379],"type":"Point"}
}