{
  "type": "Feature",
  "properties": {
    "gn:admin1_code":"69.0",
    "gn:asciiname":"Afonino",
    "gn:country_code":"RU",
    "gn:dem":206,
    "gn:feature_class":"P",
    "gn:feature_code":"PPL",
    "gn:name":"Afonino",
    "gn:population":0,
    "gn:timezone":"Europe/Moscow",
    "iso:country":"RU",
    "name:nor_x_preferred":[
        "Afonino"
    ],
    "name:rus_x_preferred":[
        "\u0410\u0444\u043e\u043d\u0438\u043d\u043e"
    ],
    "wof:name":"Afonino",
    "wof:placetype":"locality"
},
  "geometry": {"coordinates":[33.71145,54.81983],"type":"Point"}
}