{
  "type": "Feature",
  "properties": {
    "gn:admin1_code":"73",
    "gn:asciiname":"Naratly-Kichu",
    "gn:country_code":"RU",
    "gn:dem":76,
    "gn:feature_class":"P",
    "gn:feature_code":"PPL",
    "gn:name":"Naratly-Kichu",
    "gn:population":0,
    "gn:timezone":"Europe/Moscow",
    "iso:country":"RU",
    "name:eng_x_preferred":[
        "Naratly-Kichu"
    ],
    "name:nor_x_preferred":[
        "Naratly-Kitsju"
    ],
    "name:rus_x_preferred":[
        "\u041d\u0430\u0440\u0430\u0442\u043b\u044b-\u041a\u0438\u0447\u0443"
    ],
    "wof:name":"Naratly-Kichu",
    "wof:placetype":"locality"
},
  "geometry": {"coordinates":[52.84475,55.56625],"type":"Point"}
}