{
  "type": "Feature",
  "properties": {
    "gn:admin1_code":"13",
    "gn:asciiname":"Novovoroninskiy",
    "gn:country_code":"RU",
    "gn:dem":402,
    "gn:feature_class":"P",
    "gn:feature_code":"PPL",
    "gn:name":"Novovoroninskiy",
    "gn:population":0,
    "gn:timezone":"Asia/Yekaterinburg",
    "iso:country":"RU",
    "name:eng_x_preferred":[
        "Novovoroninskiy"
    ],
    "name:nor_x_preferred":[
        "Novovoroninskij"
    ],
    "name:rus_x_preferred":[
        "\u041d\u043e\u0432\u043e\u0432\u043e\u0440\u043e\u043d\u0438\u043d\u0441\u043a\u0438\u0439"
    ],
    "name:und_x_variant":[
        "Novo-Veroninskiy",
        "\u041d\u043e\u0432\u043e\u0432\u043e\u0440\u043e\u043d\u0438\u043d\u0441\u043a\u0438\u0439",
        "Novovoroninskiy"
    ],
    "wof:name":"Novovoroninskiy",
    "wof:placetype":"locality"
},
  "geometry": {"coordinates":[59.3025,53.75583],"type":"Point"}
}