{
  "type": "Feature",
  "properties": {
    "gn:admin1_code":"49",
    "gn:asciiname":"Pitkul'",
    "gn:country_code":"RU",
    "gn:dem":148,
    "gn:feature_class":"P",
    "gn:feature_code":"PPL",
    "gn:name":"Pitkul\u2019",
    "gn:population":0,
    "gn:timezone":"Europe/Moscow",
    "iso:country":"RU",
    "name:eng_x_preferred":[
        "Pitkul'"
    ],
    "name:fin_x_preferred":[
        "Pitkuljoki"
    ],
    "name:nor_x_preferred":[
        "Pitkul"
    ],
    "name:rus_x_preferred":[
        "\u041f\u0438\u0442\u043a\u0443\u043b\u044c"
    ],
    "name:und_x_variant":[
        "Pos\u00eblok Pitkul\u2019",
        "Okhtokanda",
        "Pilkulj Siirtola",
        "\u041f\u0438\u0442\u043a\u0443\u043b\u044c"
    ],
    "wof:name":"Pitkul'",
    "wof:placetype":"locality"
},
  "geometry": {"coordinates":[33.18798,67.46163],"type":"Point"}
}