{
  "type": "Feature",
  "properties": {
    "gn:admin1_code":"88",
    "gn:asciiname":"Priimkovo",
    "gn:country_code":"RU",
    "gn:dem":103,
    "gn:feature_class":"P",
    "gn:feature_code":"PPL",
    "gn:name":"Priimkovo",
    "gn:population":0,
    "gn:timezone":"Europe/Moscow",
    "iso:country":"RU",
    "name:rus_x_preferred":[
        "\u041f\u0440\u0438\u0438\u043c\u043a\u043e\u0432\u043e"
    ],
    "wof:name":"Priimkovo",
    "wof:placetype":"locality"
},
  "geometry": {"coordinates":[39.61526,57.27502],"type":"Point"}
}