{
  "type": "Feature",
  "properties": {
    "gn:admin1_code":"70",
    "gn:asciiname":"Konnyy",
    "gn:country_code":"RU",
    "gn:dem":299,
    "gn:feature_class":"P",
    "gn:feature_code":"PPL",
    "gn:name":"Konnyy",
    "gn:population":0,
    "gn:timezone":"Europe/Moscow",
    "iso:country":"RU",
    "name:rus_x_preferred":[
        "\u041a\u043e\u043d\u043d\u044b\u0439"
    ],
    "wof:name":"Konnyy",
    "wof:placetype":"locality"
},
  "geometry": {"coordinates":[43.01472,44.53083],"type":"Point"}
}