{
  "type": "Feature",
  "properties": {
    "gn:admin1_code":"9.0",
    "gn:asciiname":"Yendovino",
    "gn:country_code":"RU",
    "gn:dem":217,
    "gn:feature_class":"P",
    "gn:feature_code":"PPL",
    "gn:name":"Yendovino",
    "gn:population":0,
    "gn:timezone":"Europe/Moscow",
    "iso:country":"RU",
    "name:rus_x_preferred":[
        "\u0415\u043d\u0434\u043e\u0432\u0438\u043d\u043e"
    ],
    "name:und_x_variant":[
        "Yendovinovo"
    ],
    "wof:name":"Yendovino",
    "wof:placetype":"locality"
},
  "geometry": {"coordinates":[37.6724,50.67448],"type":"Point"}
}