{
  "type": "Feature",
  "properties": {
    "gn:admin1_code":"41.0",
    "gn:asciiname":"Cheremoshki",
    "gn:country_code":"RU",
    "gn:dem":171,
    "gn:feature_class":"P",
    "gn:feature_code":"PPL",
    "gn:name":"Cher\u00ebmoshki",
    "gn:population":0,
    "gn:timezone":"Europe/Moscow",
    "iso:country":"RU",
    "name:eng_x_preferred":[
        "Cher\u00ebmoshka"
    ],
    "name:nor_x_preferred":[
        "Tsjeremosjki"
    ],
    "name:rus_x_preferred":[
        "\u0427\u0435\u0440\u0435\u043c\u043e\u0448\u043a\u0438"
    ],
    "name:rus_x_variant":[
        "\u0427\u0435\u0440\u0451\u043c\u043e\u0448\u043a\u0438"
    ],
    "name:und_x_variant":[
        "Cher\u00ebmoshki",
        "Cher\u00ebmoshka"
    ],
    "wof:name":"Cheremoshki",
    "wof:placetype":"locality"
},
  "geometry": {"coordinates":[35.27361,51.52056],"type":"Point"}
}