{
  "type": "Feature",
  "properties": {
    "gn:admin1_code":"55.0",
    "gn:asciiname":"Baygorovka",
    "gn:country_code":"RU",
    "gn:dem":107,
    "gn:feature_class":"P",
    "gn:feature_code":"PPL",
    "gn:name":"Baygorovka",
    "gn:population":0,
    "gn:timezone":"Asia/Yekaterinburg",
    "iso:country":"RU",
    "name:nor_x_preferred":[
        "Bajgorovka"
    ],
    "name:rus_x_preferred":[
        "\u0411\u0430\u0439\u0433\u043e\u0440\u043e\u0432\u043a\u0430"
    ],
    "wof:name":"Baygorovka",
    "wof:placetype":"locality"
},
  "geometry": {"coordinates":[51.9508,52.2968],"type":"Point"}
}