{
  "type": "Feature",
  "properties": {
    "gn:admin1_code":"33.0",
    "gn:asciiname":"Chernyad'yevy",
    "gn:country_code":"RU",
    "gn:dem":135,
    "gn:feature_class":"P",
    "gn:feature_code":"PPL",
    "gn:name":"Chernyad\u2019yevy",
    "gn:population":0,
    "gn:timezone":"Europe/Kirov",
    "iso:country":"RU",
    "name:rus_x_preferred":[
        "\u0427\u0435\u0440\u043d\u044f\u0434\u044c\u0435\u0432\u044b"
    ],
    "name:und_x_variant":[
        "Chernyad\u2019yevy",
        "\u0427\u0435\u0440\u043d\u044f\u0434\u044c\u0435\u0432\u044b"
    ],
    "wof:name":"Chernyad'yevy",
    "wof:placetype":"locality"
},
  "geometry": {"coordinates":[49.4423,58.54371999999999],"type":"Point"}
}