{
  "type": "Feature",
  "properties": {
    "gn:admin1_code":"61.0",
    "gn:asciiname":"Chapura",
    "gn:country_code":"RU",
    "gn:dem":140,
    "gn:feature_class":"P",
    "gn:feature_code":"PPL",
    "gn:name":"Chapura",
    "gn:population":0,
    "gn:timezone":"Europe/Moscow",
    "iso:country":"RU",
    "name:rus_x_preferred":[
        "\u0427\u0430\u043f\u0443\u0440\u0430"
    ],
    "wof:name":"Chapura",
    "wof:placetype":"locality"
},
  "geometry": {"coordinates":[41.92169000000001,48.45038],"type":"Point"}
}