{
  "type": "Feature",
  "properties": {
    "gn:admin1_code":"51",
    "gn:asciiname":"Turbenevo",
    "gn:country_code":"RU",
    "gn:dem":168,
    "gn:feature_class":"P",
    "gn:feature_code":"PPL",
    "gn:name":"Turbenevo",
    "gn:population":0,
    "gn:timezone":"Europe/Moscow",
    "iso:country":"RU",
    "name:rus_x_preferred":[
        "\u0422\u0443\u0440\u0431\u0435\u043d\u0435\u0432\u043e"
    ],
    "name:und_x_variant":[
        "Tyurbeneva",
        "Turbenevo"
    ],
    "wof:name":"Turbenevo",
    "wof:placetype":"locality"
},
  "geometry": {"coordinates":[42.88333,55.85139],"type":"Point"}
}