{
  "type": "Feature",
  "properties": {
    "gn:admin1_code":"77",
    "gn:asciiname":"Pechnikovo",
    "gn:country_code":"RU",
    "gn:dem":241,
    "gn:feature_class":"P",
    "gn:feature_code":"PPL",
    "gn:name":"Pechnikovo",
    "gn:population":0,
    "gn:timezone":"Europe/Moscow",
    "iso:country":"RU",
    "name:rus_x_preferred":[
        "\u041f\u0435\u0447\u043d\u0438\u043a\u043e\u0432\u043e"
    ],
    "name:und_x_variant":[
        "\u041f\u0435\u0447\u043d\u0438\u043a\u043e\u0432\u043e"
    ],
    "wof:name":"Pechnikovo",
    "wof:placetype":"locality"
},
  "geometry": {"coordinates":[34.20677,57.24149],"type":"Point"}
}