{
  "type": "Feature",
  "properties": {
    "gn:admin1_code":"45",
    "gn:asciiname":"Tumer",
    "gn:country_code":"RU",
    "gn:dem":125,
    "gn:feature_class":"P",
    "gn:feature_code":"PPL",
    "gn:name":"Tumer",
    "gn:population":0,
    "gn:timezone":"Europe/Moscow",
    "iso:country":"RU",
    "name:rus_x_preferred":[
        "\u0422\u0443\u043c\u0435\u0440"
    ],
    "name:und_x_variant":[
        "Tumersola",
        "Tumer"
    ],
    "wof:name":"Tumer",
    "wof:placetype":"locality"
},
  "geometry": {"coordinates":[47.76882,56.82011],"type":"Point"}
}