{
  "type": "Feature",
  "properties": {
    "gn:admin1_code":"80",
    "gn:asciiname":"Kib'ya",
    "gn:country_code":"RU",
    "gn:dem":131,
    "gn:feature_class":"P",
    "gn:feature_code":"PPL",
    "gn:name":"Kib\u2019ya",
    "gn:population":0,
    "gn:timezone":"Europe/Samara",
    "iso:country":"RU",
    "name:eng_x_preferred":[
        "Kib'ya"
    ],
    "name:nor_x_preferred":[
        "Kibja"
    ],
    "name:rus_x_preferred":[
        "\u041a\u0438\u0431\u044c\u044f"
    ],
    "name:und_x_variant":[
        "Kib\u2019ya"
    ],
    "wof:name":"Kib'ya",
    "wof:placetype":"locality"
},
  "geometry": {"coordinates":[51.41037,56.41274],"type":"Point"}
}