{
  "type": "Feature",
  "properties": {
    "gn:admin1_code":"85",
    "gn:asciiname":"Novoye Domozerovo",
    "gn:country_code":"RU",
    "gn:dem":115,
    "gn:feature_class":"P",
    "gn:feature_code":"PPL",
    "gn:name":"Novoye Domozerovo",
    "gn:population":0,
    "gn:timezone":"Europe/Moscow",
    "iso:country":"RU",
    "name:eng_x_preferred":[
        "Novoye Domozerovo"
    ],
    "name:nor_x_preferred":[
        "Nov.Domozerovo"
    ],
    "name:rus_x_preferred":[
        "\u041d\u043e\u0432.\u0414\u043e\u043c\u043e\u0437\u0435\u0440\u043e\u0432\u043e"
    ],
    "name:rus_x_variant":[
        "\u041d\u043e\u0432\u043e\u0435 \u0414\u043e\u043c\u043e\u0437\u0435\u0440\u043e\u0432\u043e"
    ],
    "name:und_x_variant":[
        "\u041d\u043e\u0432\u043e\u0435 \u0414\u043e\u043c\u043e\u0437\u0435\u0440\u043e\u0432\u043e"
    ],
    "wof:name":"Novoye Domozerovo",
    "wof:placetype":"locality"
},
  "geometry": {"coordinates":[38.16255,59.03782],"type":"Point"}
}