{
  "type": "Feature",
  "properties": {
    "gn:admin1_code":"47.0",
    "gn:asciiname":"Antropovo",
    "gn:country_code":"RU",
    "gn:dem":166,
    "gn:feature_class":"P",
    "gn:feature_code":"PPL",
    "gn:name":"Antropovo",
    "gn:population":0,
    "gn:timezone":"Europe/Moscow",
    "iso:country":"RU",
    "name:nor_x_preferred":[
        "Antropovo"
    ],
    "name:rus_x_preferred":[
        "\u0410\u043d\u0442\u0440\u043e\u043f\u043e\u0432\u043e"
    ],
    "wof:name":"Antropovo",
    "wof:placetype":"locality"
},
  "geometry": {"coordinates":[37.64806,55.24886],"type":"Point"}
}