{
  "type": "Feature",
  "properties": {
    "gn:admin1_code":"61",
    "gn:asciiname":"Lugan'",
    "gn:country_code":"RU",
    "gn:dem":16,
    "gn:feature_class":"P",
    "gn:feature_code":"PPL",
    "gn:name":"Lugan\u2019",
    "gn:population":0,
    "gn:timezone":"Europe/Moscow",
    "iso:country":"RU",
    "name:rus_x_preferred":[
        "\u041b\u0443\u0433\u0430\u043d\u044c"
    ],
    "name:und_x_variant":[
        "Lugan\u2019"
    ],
    "wof:name":"Lugan'",
    "wof:placetype":"locality"
},
  "geometry": {"coordinates":[39.90661,46.88106],"type":"Point"}
}