{
  "type": "Feature",
  "properties": {
    "gn:admin1_code":"52",
    "gn:asciiname":"Shumilovo",
    "gn:country_code":"RU",
    "gn:dem":46,
    "gn:feature_class":"P",
    "gn:feature_code":"PPL",
    "gn:name":"Shumilovo",
    "gn:population":0,
    "gn:timezone":"Europe/Moscow",
    "iso:country":"RU",
    "name:rus_x_preferred":[
        "\u0428\u0443\u043c\u0438\u043b\u043e\u0432o"
    ],
    "wof:name":"Shumilovo",
    "wof:placetype":"locality"
},
  "geometry": {"coordinates":[32.2332,57.7109],"type":"Point"}
}