{
  "type": "Feature",
  "properties": {
    "gn:admin1_code":"45",
    "gn:asciiname":"Maydan",
    "gn:country_code":"RU",
    "gn:dem":65,
    "gn:feature_class":"P",
    "gn:feature_code":"PPL",
    "gn:name":"Maydan",
    "gn:population":0,
    "gn:timezone":"Europe/Moscow",
    "iso:country":"RU",
    "name:eng_x_preferred":[
        "Maydan"
    ],
    "name:nor_x_preferred":[
        "Majdan"
    ],
    "name:rus_x_preferred":[
        "\u041c\u0430\u0439\u0434\u0430\u043d"
    ],
    "name:und_x_variant":[
        "\u041c\u0430\u0439\u0434\u0430\u043d",
        "Maydan"
    ],
    "wof:name":"Maydan",
    "wof:placetype":"locality"
},
  "geometry": {"coordinates":[46.22582,56.27885],"type":"Point"}
}