{
  "type": "Feature",
  "properties": {
    "gn:admin1_code":"16",
    "gn:asciiname":"Staroye Yansitovo",
    "gn:country_code":"RU",
    "gn:dem":100,
    "gn:feature_class":"P",
    "gn:feature_code":"PPL",
    "gn:name":"Staroye Yansitovo",
    "gn:population":0,
    "gn:timezone":"Europe/Moscow",
    "iso:country":"RU",
    "name:rus_x_preferred":[
        "\u0421\u0442\u0430\u0440\u043e\u0435 \u042f\u043d\u0441\u0438\u0442\u043e\u0432\u043e"
    ],
    "name:und_x_variant":[
        "Verkhniye Kinchery",
        "Staroye Yansitovo",
        "\u0421\u0442\u0430\u0440\u043e\u0435 \u042f\u043d\u0441\u0438\u0442\u043e\u0432\u043e"
    ],
    "wof:name":"Staroye Yansitovo",
    "wof:placetype":"locality"
},
  "geometry": {"coordinates":[47.91887,55.79167],"type":"Point"}
}