{
  "type": "Feature",
  "properties": {
    "gn:admin1_code":"7",
    "gn:asciiname":"Rychinskiy",
    "gn:country_code":"RU",
    "gn:dem":-25,
    "gn:feature_class":"P",
    "gn:feature_code":"PPL",
    "gn:name":"Rychinskiy",
    "gn:population":0,
    "gn:timezone":"Europe/Astrakhan",
    "iso:country":"RU",
    "name:rus_x_preferred":[
        "\u0420\u044b\u0447\u0438\u043d\u0441\u043a\u0438\u0439"
    ],
    "wof:name":"Rychinskiy",
    "wof:placetype":"locality"
},
  "geometry": {"coordinates":[48.08555,46.52506],"type":"Point"}
}