{
  "type": "Feature",
  "properties": {
    "gn:admin1_code":"17.0",
    "gn:asciiname":"Kubra",
    "gn:country_code":"RU",
    "gn:dem":1809,
    "gn:feature_class":"P",
    "gn:feature_code":"PPL",
    "gn:name":"Kubra",
    "gn:population":0,
    "gn:timezone":"Europe/Moscow",
    "iso:country":"RU",
    "name:rus_x_preferred":[
        "\u041a\u0443\u0431\u0440\u0430"
    ],
    "name:und_x_variant":[
        "\u041a\u0443\u0431\u0440\u0430"
    ],
    "wof:name":"Kubra",
    "wof:placetype":"locality"
},
  "geometry": {"coordinates":[47.08175,42.14373],"type":"Point"}
}