{
  "type": "Feature",
  "properties": {
    "gn:admin1_code":"42",
    "gn:asciiname":"Zadnevo",
    "gn:country_code":"RU",
    "gn:dem":39,
    "gn:feature_class":"P",
    "gn:feature_code":"PPL",
    "gn:name":"Zadnevo",
    "gn:population":0,
    "gn:timezone":"Europe/Moscow",
    "iso:country":"RU",
    "wof:name":"Zadnevo",
    "wof:placetype":"locality"
},
  "geometry": {"coordinates":[32.55907,59.90653],"type":"Point"}
}