{
  "type": "Feature",
  "properties": {
    "gn:admin1_code":"05",
    "gn:asciiname":"Krasnyy Ugolok",
    "gn:cc2":"RU",
    "gn:country_code":"RU",
    "gn:dem":277,
    "gn:feature_class":"P",
    "gn:feature_code":"PPL",
    "gn:name":"Krasnyy Ugolok",
    "gn:population":0,
    "gn:timezone":"Asia/Yakutsk",
    "iso:country":"RU",
    "name:rus_x_preferred":[
        "\u041a\u0440\u0430\u0441\u043d\u044b\u0439 \u0423\u0433\u043e\u043b\u043e\u043a"
    ],
    "name:und_x_variant":[
        "Krasnyy Utolok",
        "Krasnyy Ugolok"
    ],
    "wof:name":"Krasnyy Ugolok",
    "wof:placetype":"locality"
},
  "geometry": {"coordinates":[127.01667,52.71666999999999],"type":"Point"}
}