{
  "type": "Feature",
  "properties": {
    "gn:admin1_code":"83",
    "gn:asciiname":"Ivachi",
    "gn:country_code":"RU",
    "gn:dem":159,
    "gn:feature_class":"P",
    "gn:feature_code":"PPL",
    "gn:name":"Ivachi",
    "gn:population":0,
    "gn:timezone":"Europe/Moscow",
    "iso:country":"RU",
    "name:rus_x_preferred":[
        "\u0418\u0432\u0430\u0447\u0438"
    ],
    "wof:name":"Ivachi",
    "wof:placetype":"locality"
},
  "geometry": {"coordinates":[39.43333,56.03333000000001],"type":"Point"}
}