{
  "type": "Feature",
  "properties": {
    "gn:country":"RU",
    "gn:fcode":"PPL",
    "gn:pop":0,
    "iso:country":"RU",
    "name:fin_x_preferred":[
        "Kopittala"
    ],
    "name:rus_x_preferred":[
        "\u041a\u0430\u043f\u0438\u0442\u043e\u043b\u043e\u0432\u043e"
    ],
    "name:unk_x_variant":[
        "\u041a\u0430\u043f\u0438\u0442\u043e\u043b\u043e\u0432\u043e"
    ],
    "qs:name":"Kapitolovo",
    "qs:name_adm0":"Russia",
    "qs:name_adm1":"Leningrad Oblast",
    "qs:photos_9r":0,
    "qs:photos_sr":0,
    "qs:placetype":"Town",
    "qs:pop_sr":"0",
    "wof:name":"Kapitolovo",
    "wof:placetype":"locality",
    "wof:population":0
},
  "geometry": {"coordinates":[30.48463,60.09535],"type":"Point"}
}