{
  "type": "Feature",
  "properties": {
    "gn:admin1_code":"6",
    "gn:asciiname":"Zabelinskaya",
    "gn:country_code":"RU",
    "gn:dem":40,
    "gn:feature_class":"P",
    "gn:feature_code":"PPL",
    "gn:name":"Zabelinskaya",
    "gn:population":0,
    "gn:timezone":"Europe/Moscow",
    "iso:country":"RU",
    "wof:name":"Zabelinskaya",
    "wof:placetype":"locality"
},
  "geometry": {"coordinates":[46.26667,61.41667],"type":"Point"}
}