{
  "type": "Feature",
  "properties": {
    "gn:admin1_code":"20",
    "gn:asciiname":"Lidinskaya",
    "gn:country_code":"RU",
    "gn:dem":723,
    "gn:feature_class":"P",
    "gn:feature_code":"PPL",
    "gn:name":"Lidinskaya",
    "gn:population":0,
    "gn:timezone":"Asia/Irkutsk",
    "iso:country":"RU",
    "name:eng_x_preferred":[
        "Lidinskaya"
    ],
    "name:nor_x_preferred":[
        "Lidinskaja"
    ],
    "name:rus_x_preferred":[
        "\u041b\u0438\u0434\u0438\u043d\u0441\u043a\u0430\u044f"
    ],
    "wof:name":"Lidinskaya",
    "wof:placetype":"locality"
},
  "geometry": {"coordinates":[105.8199,53.0844],"type":"Point"}
}