{
  "type": "Feature",
  "properties": {
    "gn:admin1_code":"70.0",
    "gn:asciiname":"Novaya Kugul'ta",
    "gn:country_code":"RU",
    "gn:dem":89,
    "gn:feature_class":"P",
    "gn:feature_code":"PPL",
    "gn:name":"Novaya Kugul\u2019ta",
    "gn:population":0,
    "gn:timezone":"Europe/Moscow",
    "iso:country":"RU",
    "name:eng_x_preferred":[
        "Novaya Kugulta"
    ],
    "name:nor_x_preferred":[
        "Malaja Kugulta"
    ],
    "name:rus_x_preferred":[
        "\u041c\u0430\u043b\u0430\u044f \u041a\u0443\u0433\u0443\u043b\u044c\u0442\u0430"
    ],
    "name:rus_x_variant":[
        "\u041d\u043e\u0432\u0430\u044f \u041a\u0443\u0433\u0443\u043b\u044c\u0442\u0430"
    ],
    "name:und_x_variant":[
        "Malaya Kugul\u2019ta",
        "Novokugul\u2019tinskoye",
        "Novaya Kugul\u2019ta",
        "\u041d\u043e\u0432\u0430\u044f \u041a\u0443\u0433\u0443\u043b\u044c\u0442\u0430"
    ],
    "wof:name":"Novaya Kugul'ta",
    "wof:placetype":"locality"
},
  "geometry": {"coordinates":[42.11389000000001,45.67139],"type":"Point"}
}