{
  "type": "Feature",
  "properties": {
    "gn:admin1_code":"53",
    "gn:asciiname":"Blinkovo",
    "gn:country_code":"RU",
    "gn:dem":115,
    "gn:feature_class":"P",
    "gn:feature_code":"PPL",
    "gn:name":"Blinkovo",
    "gn:population":0,
    "gn:timezone":"Asia/Novosibirsk",
    "iso:country":"RU",
    "name:eng_x_preferred":[
        "Blinkovo"
    ],
    "name:nor_x_preferred":[
        "Blinkovo"
    ],
    "name:rus_x_preferred":[
        "\u0411\u043b\u0438\u043d\u043a\u043e\u0432\u043e"
    ],
    "name:und_x_variant":[
        "Blinkovskiy"
    ],
    "wof:name":"Blinkovo",
    "wof:placetype":"locality"
},
  "geometry": {"coordinates":[77.1656,55.76708000000001],"type":"Point"}
}