{
  "type": "Feature",
  "properties": {
    "gn:admin1_code":"53",
    "gn:asciiname":"Khayryuzovka",
    "gn:country_code":"RU",
    "gn:dem":279,
    "gn:feature_class":"P",
    "gn:feature_code":"PPL",
    "gn:name":"Khayryuzovka",
    "gn:population":0,
    "gn:timezone":"Asia/Novosibirsk",
    "iso:country":"RU",
    "name:rus_x_preferred":[
        "\u0425\u0430\u0439\u0440\u044e\u0437\u043e\u0432\u043a\u0430"
    ],
    "wof:name":"Khayryuzovka",
    "wof:placetype":"locality"
},
  "geometry": {"coordinates":[84.45,54.15],"type":"Point"}
}