{
  "type": "Feature",
  "properties": {
    "gn:admin1_code":"85.0",
    "gn:asciiname":"Kameshnik",
    "gn:country_code":"RU",
    "gn:dem":165,
    "gn:feature_class":"P",
    "gn:feature_code":"PPL",
    "gn:name":"Kameshnik",
    "gn:population":0,
    "gn:timezone":"Europe/Moscow",
    "iso:country":"RU",
    "name:che_x_preferred":[
        "\u041a\u0430\u043c\u0435\u0448\u043d\u0438\u043a"
    ],
    "name:rus_x_preferred":[
        "\u041a\u0430\u043c\u0435\u0448\u043d\u0438\u043a"
    ],
    "wof:name":"Kameshnik",
    "wof:placetype":"locality"
},
  "geometry": {"coordinates":[40.23864,58.93023],"type":"Point"}
}