{
  "type": "Feature",
  "properties": {
    "gn:admin1_code":"13",
    "gn:asciiname":"Bannikovo",
    "gn:country_code":"RU",
    "gn:dem":176,
    "gn:feature_class":"P",
    "gn:feature_code":"PPL",
    "gn:name":"Bannikovo",
    "gn:population":0,
    "gn:timezone":"Asia/Yekaterinburg",
    "iso:country":"RU",
    "name:nor_x_preferred":[
        "Bannikovo"
    ],
    "name:rus_x_preferred":[
        "\u0411\u0430\u043d\u043d\u0438\u043a\u043e\u0432\u043e"
    ],
    "wof:name":"Bannikovo",
    "wof:placetype":"locality"
},
  "geometry": {"coordinates":[63.08167,54.67833],"type":"Point"}
}