{
  "type": "Feature",
  "properties": {
    "gn:admin1_code":"87",
    "gn:asciiname":"Napalkovo",
    "gn:cc2":"RU",
    "gn:country_code":"RU",
    "gn:dem":-9999,
    "gn:feature_class":"P",
    "gn:feature_code":"PPL",
    "gn:name":"Napalkovo",
    "gn:population":0,
    "gn:timezone":"Asia/Yekaterinburg",
    "iso:country":"RU",
    "name:eng_x_preferred":[
        "Napalkovo"
    ],
    "name:nor_x_preferred":[
        "Napalkovo"
    ],
    "name:rus_x_preferred":[
        "\u041d\u0430\u043f\u0430\u043b\u043a\u043e\u0432\u043e"
    ],
    "name:und_x_variant":[
        "Faktoriya Napalkovo",
        "Faktoriya Abkay-Sede"
    ],
    "wof:name":"Napalkovo",
    "wof:placetype":"locality"
},
  "geometry": {"coordinates":[73.77972,70.04528000000001],"type":"Point"}
}