{
  "type": "Feature",
  "properties": {
    "gn:admin1_code":"52",
    "gn:asciiname":"Gorushka",
    "gn:country_code":"RU",
    "gn:dem":219,
    "gn:feature_class":"P",
    "gn:feature_code":"PPL",
    "gn:name":"Gorushka",
    "gn:population":0,
    "gn:timezone":"Europe/Moscow",
    "iso:country":"RU",
    "name:nor_x_preferred":[
        "Gorusjka"
    ],
    "name:rus_x_preferred":[
        "\u0413\u043e\u0440\u0443\u0448\u043a\u0430"
    ],
    "wof:name":"Gorushka",
    "wof:placetype":"locality"
},
  "geometry": {"coordinates":[33.30602,58.17834000000001],"type":"Point"}
}