{
  "type": "Feature",
  "properties": {
    "gn:admin1_code":"8",
    "gn:asciiname":"Staroturayevo",
    "gn:country_code":"RU",
    "gn:dem":119,
    "gn:feature_class":"P",
    "gn:feature_code":"PPL",
    "gn:name":"Staroturayevo",
    "gn:population":0,
    "gn:timezone":"Asia/Yekaterinburg",
    "iso:country":"RU",
    "name:eng_x_preferred":[
        "Staroturayevo"
    ],
    "name:nor_x_preferred":[
        "Staroturajevo"
    ],
    "name:rus_x_preferred":[
        "\u0421\u0442\u0430\u0440\u043e\u0442\u0443\u0440\u0430\u0435\u0432\u043e"
    ],
    "name:und_x_variant":[
        "Staroye Turayevo",
        "\u0421\u0442\u0430\u0440\u043e\u0442\u0443\u0440\u0430\u0435\u0432\u043e",
        "Staroturayevo"
    ],
    "wof:name":"Staroturayevo",
    "wof:placetype":"locality"
},
  "geometry": {"coordinates":[53.49345,54.27754],"type":"Point"}
}