{
  "type": "Feature",
  "properties": {
    "gn:admin1_code":"8",
    "gn:asciiname":"Staroturayevo",
    "gn:country_code":"RU",
    "gn:dem":119,
    "gn:feature_class":"P",
    "gn:feature_code":"PPL",
    "gn:name":"Staroturayevo",
    "gn:population":0,
    "gn:timezone":"Asia/Yekaterinburg",
    "iso:country":"RU",
    "name:bak_x_preferred":[
        "\u0418\u04ab\u043a\u0435 \u0422\u0443\u0440\u0430\u0439"
    ],
    "name:che_x_preferred":[
        "\u0421\u0442\u0430\u0440\u043e\u0442\u0443\u0440\u0430\u0435\u0432\u043e"
    ],
    "name:eng_x_preferred":[
        "Staroturayevo"
    ],
    "name:hye_x_preferred":[
        "\u054d\u057f\u0561\u0580\u0578\u057f\u0578\u0582\u0580\u0561\u0587\u0578"
    ],
    "name:kaz_x_preferred":[
        "\u0415\u0441\u043a\u0456 \u0442\u0443\u0440\u0430"
    ],
    "name:kir_x_preferred":[
        "\u042d\u0441\u043a\u0438 \u0442\u0443\u0440\u0430"
    ],
    "name:nor_x_preferred":[
        "Staroturajevo"
    ],
    "name:rus_x_preferred":[
        "\u0421\u0442\u0430\u0440\u043e\u0442\u0443\u0440\u0430\u0435\u0432\u043e"
    ],
    "name:tat_x_preferred":[
        "\u0418\u0441\u043a\u0435 \u0422\u0443\u0440\u0430\u0439"
    ],
    "name:ukr_x_preferred":[
        "\u0421\u0442\u0430\u0440\u043e\u0442\u0443\u0440\u0430\u0454\u0432\u043e"
    ],
    "name:und_x_variant":[
        "Staroye Turayevo"
    ],
    "wof:name":"Staroturayevo",
    "wof:placetype":"locality"
},
  "geometry": {"coordinates":[53.49345,54.27754],"type":"Point"}
}