{
  "type": "Feature",
  "properties": {
    "gn:admin1_code":"69.0",
    "gn:asciiname":"Drozhzhino",
    "gn:country_code":"RU",
    "gn:dem":193,
    "gn:feature_class":"P",
    "gn:feature_code":"PPL",
    "gn:name":"Drozhzhino",
    "gn:population":0,
    "gn:timezone":"Europe/Moscow",
    "iso:country":"RU",
    "name:rus_x_preferred":[
        "\u0414\u0440\u043e\u0436\u0436\u0438\u043d\u043e"
    ],
    "name:und_x_variant":[
        "\u0414\u0440\u043e\u0436\u0436\u0438\u043d\u043e"
    ],
    "wof:name":"Drozhzhino",
    "wof:placetype":"locality"
},
  "geometry": {"coordinates":[34.62521,55.00666],"type":"Point"}
}