{
  "type": "Feature",
  "properties": {
    "gn:admin1_code":"17.0",
    "gn:admin2_code":"Tlyaratinskiy Rayon",
    "gn:asciiname":"Charakh",
    "gn:country_code":"RU",
    "gn:dem":1907,
    "gn:feature_class":"P",
    "gn:feature_code":"PPL",
    "gn:name":"Charakh",
    "gn:population":0,
    "gn:timezone":"Europe/Moscow",
    "iso:country":"RU",
    "name:rus_x_preferred":[
        "\u0427\u0430\u0440\u0430\u0445"
    ],
    "name:und_x_variant":[
        "Cherakh",
        "Charakh"
    ],
    "wof:name":"Charakh",
    "wof:placetype":"locality"
},
  "geometry": {"coordinates":[46.35589,42.3057],"type":"Point"}
}