{
  "type": "Feature",
  "properties": {
    "gn:admin1_code":"61.0",
    "gn:asciiname":"Tokmatskiy",
    "gn:country_code":"RU",
    "gn:dem":58,
    "gn:feature_class":"P",
    "gn:feature_code":"PPL",
    "gn:name":"Tokmatskiy",
    "gn:population":0,
    "gn:timezone":"Europe/Moscow",
    "iso:country":"RU",
    "name:rus_x_preferred":[
        "\u0422\u043e\u043a\u043c\u0430\u0446\u043a\u0438\u0439"
    ],
    "wof:name":"Tokmatskiy",
    "wof:placetype":"locality"
},
  "geometry": {"coordinates":[42.229,47.0032],"type":"Point"}
}