{
  "type": "Feature",
  "properties": {
    "gn:admin1_code":"63",
    "gn:asciiname":"Khara-Yuryakh",
    "gn:country_code":"RU",
    "gn:dem":756,
    "gn:feature_class":"P",
    "gn:feature_code":"PPL",
    "gn:name":"Khara-Yuryakh",
    "gn:population":0,
    "gn:timezone":"Asia/Magadan",
    "iso:country":"RU",
    "name:rus_x_preferred":[
        "\u0425\u0430\u0440\u0430-\u042e\u0440\u044f\u0445"
    ],
    "wof:name":"Khara-Yuryakh",
    "wof:placetype":"locality"
},
  "geometry": {"coordinates":[145.16666999999995,64.25],"type":"Point"}
}