{
  "type": "Feature",
  "properties": {
    "gn:admin1_code":"91",
    "gn:asciiname":"Tumakovo",
    "gn:country_code":"RU",
    "gn:dem":330,
    "gn:feature_class":"P",
    "gn:feature_code":"PPL",
    "gn:name":"Tumakovo",
    "gn:population":0,
    "gn:timezone":"Asia/Krasnoyarsk",
    "iso:country":"RU",
    "name:eng_x_preferred":[
        "Tumakovo"
    ],
    "name:nor_x_preferred":[
        "Tumakovo"
    ],
    "name:rus_x_preferred":[
        "\u0422\u0443\u043c\u0430\u043a\u043e\u0432\u043e"
    ],
    "name:und_x_variant":[
        "Tumakova"
    ],
    "wof:name":"Tumakovo",
    "wof:placetype":"locality"
},
  "geometry": {"coordinates":[95.5641,55.7928],"type":"Point"}
}