{
  "type": "Feature",
  "properties": {
    "gn:admin1_code":"69",
    "gn:asciiname":"Shchitniki",
    "gn:country_code":"RU",
    "gn:dem":221,
    "gn:feature_class":"P",
    "gn:feature_code":"PPL",
    "gn:name":"Shchitniki",
    "gn:population":0,
    "gn:timezone":"Europe/Moscow",
    "iso:country":"RU",
    "name:rus_x_preferred":[
        "\u0429\u0438\u0442\u043d\u0438\u043a\u0438"
    ],
    "wof:name":"Shchitniki",
    "wof:placetype":"locality"
},
  "geometry": {"coordinates":[32.05328,54.9266],"type":"Point"}
}