{
  "type": "Feature",
  "properties": {
    "gn:admin1_code":"77",
    "gn:asciiname":"Pryazhino",
    "gn:country_code":"RU",
    "gn:dem":127,
    "gn:feature_class":"P",
    "gn:feature_code":"PPL",
    "gn:name":"Pryazhino",
    "gn:population":0,
    "gn:timezone":"Europe/Moscow",
    "iso:country":"RU",
    "name:rus_x_preferred":[
        "\u041f\u0440\u044f\u0436\u0438\u043d\u043e"
    ],
    "name:und_x_variant":[
        "Pryazhina",
        "Pryazhino"
    ],
    "wof:name":"Pryazhino",
    "wof:placetype":"locality"
},
  "geometry": {"coordinates":[37.91667,57.13333000000001],"type":"Point"}
}