{
  "type": "Feature",
  "properties": {
    "gn:admin1_code":"72.0",
    "gn:asciiname":"Chicherino",
    "gn:country_code":"RU",
    "gn:dem":142,
    "gn:feature_class":"P",
    "gn:feature_code":"PPL",
    "gn:name":"Chich\u00ebrino",
    "gn:population":0,
    "gn:timezone":"Europe/Moscow",
    "iso:country":"RU",
    "name:rus_x_preferred":[
        "Chich\u00ebrino"
    ],
    "name:rus_x_variant":[
        "\u0427\u0438\u0447\u0451\u0440\u0438\u043d\u043e"
    ],
    "name:und_x_variant":[
        "Chich\u00ebrino",
        "\u0427\u0438\u0447\u0451\u0440\u0438\u043d\u043e"
    ],
    "wof:name":"Chicherino",
    "wof:placetype":"locality"
},
  "geometry": {"coordinates":[40.6627,52.382],"type":"Point"}
}