{
  "type": "Feature",
  "properties": {
    "gn:admin1_code":"60",
    "gn:asciiname":"Prokshina",
    "gn:country_code":"RU",
    "gn:dem":161,
    "gn:feature_class":"P",
    "gn:feature_code":"PPL",
    "gn:name":"Prokshina",
    "gn:population":0,
    "gn:timezone":"Europe/Moscow",
    "iso:country":"RU",
    "name:rus_x_preferred":[
        "\u041f\u0440\u043e\u043a\u0448\u0438\u043d\u0430"
    ],
    "wof:name":"Prokshina",
    "wof:placetype":"locality"
},
  "geometry": {"coordinates":[29.53333,57.31667],"type":"Point"}
}