{
  "type": "Feature",
  "properties": {
    "gn:admin1_code":"90.0",
    "gn:asciiname":"Gorodnichata",
    "gn:country_code":"RU",
    "gn:dem":119,
    "gn:feature_class":"P",
    "gn:feature_code":"PPL",
    "gn:name":"Gorodnichata",
    "gn:population":0,
    "gn:timezone":"Asia/Yekaterinburg",
    "iso:country":"RU",
    "name:rus_x_preferred":[
        "\u0413\u043e\u0440\u043e\u0434\u043d\u0438\u0447\u0430\u0442\u0430"
    ],
    "wof:name":"Gorodnichata",
    "wof:placetype":"locality"
},
  "geometry": {"coordinates":[55.2006,58.0268],"type":"Point"}
}