{
  "type": "Feature",
  "properties": {
    "gn:admin1_code":"7",
    "gn:asciiname":"Verblyuzhiy",
    "gn:country_code":"RU",
    "gn:dem":-3,
    "gn:feature_class":"P",
    "gn:feature_code":"PPL",
    "gn:name":"Verblyuzhiy",
    "gn:population":0,
    "gn:timezone":"Europe/Astrakhan",
    "iso:country":"RU",
    "name:eng_x_preferred":[
        "Verblyuzhiy"
    ],
    "name:nor_x_preferred":[
        "Verbljuzjij"
    ],
    "name:rus_x_preferred":[
        "\u0412\u0435\u0440\u0431\u043b\u044e\u0436\u0438\u0439"
    ],
    "wof:name":"Verblyuzhiy",
    "wof:placetype":"locality"
},
  "geometry": {"coordinates":[46.8806,47.723],"type":"Point"}
}