{
  "type": "Feature",
  "properties": {
    "gn:admin1_code":"81",
    "gn:asciiname":"Pokrovskaya Reshetka",
    "gn:country_code":"RU",
    "gn:dem":232,
    "gn:feature_class":"P",
    "gn:feature_code":"PPL",
    "gn:name":"Pokrovskaya Resh\u00ebtka",
    "gn:population":0,
    "gn:timezone":"Europe/Ulyanovsk",
    "iso:country":"RU",
    "name:rus_x_preferred":[
        "\u041f\u043e\u043a\u0440\u043e\u0432\u0441\u043a\u0430\u044f \u0420\u0435\u0448\u0451\u0442\u043a\u0430"
    ],
    "name:und_x_variant":[
        "Pokrovskaya Resh\u00ebtka"
    ],
    "wof:name":"Pokrovskaya Reshetka",
    "wof:placetype":"locality"
},
  "geometry": {"coordinates":[46.93126,53.67849],"type":"Point"}
}