{
  "type": "Feature",
  "properties": {
    "gn:admin1_code":"51",
    "gn:asciiname":"Trufanovo",
    "gn:country_code":"RU",
    "gn:dem":98,
    "gn:feature_class":"P",
    "gn:feature_code":"PPL",
    "gn:name":"Trufanovo",
    "gn:population":0,
    "gn:timezone":"Europe/Moscow",
    "iso:country":"RU",
    "name:rus_x_preferred":[
        "\u0422\u0440\u0443\u0444\u0430\u043d\u043e\u0432\u043e"
    ],
    "name:und_x_variant":[
        "\u0422\u0440\u0443\u0444\u0430\u043d\u043e\u0432\u043e"
    ],
    "wof:name":"Trufanovo",
    "wof:placetype":"locality"
},
  "geometry": {"coordinates":[45.0386,57.246],"type":"Point"}
}