{
  "type": "Feature",
  "properties": {
    "gn:admin1_code":"55.0",
    "gn:asciiname":"Cheremushki",
    "gn:cc2":"RU",
    "gn:country_code":"RU",
    "gn:dem":170,
    "gn:feature_class":"P",
    "gn:feature_code":"PPL",
    "gn:name":"Cher\u00ebmushki",
    "gn:population":0,
    "gn:timezone":"Asia/Yekaterinburg",
    "iso:country":"RU",
    "name:rus_x_preferred":[
        "\u0427\u0435\u0440\u0451\u043c\u0443\u0448\u043a\u0438"
    ],
    "name:und_x_variant":[
        "Pavlovka",
        "Cher\u00ebmushki"
    ],
    "wof:name":"Cheremushki",
    "wof:placetype":"locality"
},
  "geometry": {"coordinates":[53.95,53.45],"type":"Point"}
}