{
  "type": "Feature",
  "properties": {
    "gn:admin1_code":"88",
    "gn:asciiname":"Ploski",
    "gn:country_code":"RU",
    "gn:dem":130,
    "gn:feature_class":"P",
    "gn:feature_code":"PPL",
    "gn:name":"Ploski",
    "gn:population":0,
    "gn:timezone":"Europe/Moscow",
    "iso:country":"RU",
    "name:eng_x_preferred":[
        "Ploski"
    ],
    "name:nor_x_preferred":[
        "Ploski"
    ],
    "name:rus_x_preferred":[
        "\u041f\u043b\u043e\u0441\u043a\u0438"
    ],
    "name:und_x_variant":[
        "\u041f\u043b\u043e\u0441\u043a\u0438",
        "Ploski"
    ],
    "wof:name":"Ploski",
    "wof:placetype":"locality"
},
  "geometry": {"coordinates":[37.93028,57.4425],"type":"Point"}
}