{
  "type": "Feature",
  "properties": {
    "gn:admin1_code":"88",
    "gn:asciiname":"Ploski",
    "gn:country_code":"RU",
    "gn:dem":130,
    "gn:feature_class":"P",
    "gn:feature_code":"PPL",
    "gn:name":"Ploski",
    "gn:population":0,
    "gn:timezone":"Europe/Moscow",
    "iso:country":"RU",
    "name:azb_x_preferred":[
        "\u067e\u0644\u0648\u0633\u06a9\u06cc"
    ],
    "name:eng_x_preferred":[
        "Ploski"
    ],
    "name:fas_x_preferred":[
        "\u067e\u0644\u0648\u0633\u06a9\u06cc"
    ],
    "name:fra_x_preferred":[
        "Ploski"
    ],
    "name:lit_x_preferred":[
        "Ploskai"
    ],
    "name:nor_x_preferred":[
        "Ploski"
    ],
    "name:pol_x_preferred":[
        "Ploski"
    ],
    "name:rus_x_preferred":[
        "\u041f\u043b\u043e\u0441\u043a\u0438"
    ],
    "name:ukr_x_preferred":[
        "\u041f\u043b\u044c\u043e\u0441\u043a\u0456"
    ],
    "wof:name":"Ploski",
    "wof:placetype":"locality"
},
  "geometry": {"coordinates":[37.93028,57.4425],"type":"Point"}
}