{
  "type": "Feature",
  "properties": {
    "gn:admin1_code":"22",
    "gn:asciiname":"Tashly-Tala",
    "gn:country_code":"RU",
    "gn:dem":1140,
    "gn:feature_class":"P",
    "gn:feature_code":"PPL",
    "gn:name":"Tashly-Tala",
    "gn:population":0,
    "gn:timezone":"Europe/Moscow",
    "iso:country":"RU",
    "name:eng_x_preferred":[
        "Tashly-Tala"
    ],
    "name:nor_x_preferred":[
        "Tasjly-Tala"
    ],
    "name:rus_x_preferred":[
        "\u0422\u0430\u0448\u043b\u044b-\u0422\u0430\u043b\u0430"
    ],
    "wof:name":"Tashly-Tala",
    "wof:placetype":"locality"
},
  "geometry": {"coordinates":[43.69443,43.14525],"type":"Point"}
}