{
  "type": "Feature",
  "properties": {
    "gn:admin1_code":"62",
    "gn:asciiname":"Tsentral'naya",
    "gn:country_code":"RU",
    "gn:dem":161,
    "gn:feature_class":"P",
    "gn:feature_code":"PPL",
    "gn:name":"Tsentral\u2019naya",
    "gn:population":0,
    "gn:timezone":"Europe/Moscow",
    "iso:country":"RU",
    "wof:name":"Tsentral'naya",
    "wof:placetype":"locality"
},
  "geometry": {"coordinates":[41.07442,53.5364],"type":"Point"}
}