{
  "type": "Feature",
  "properties": {
    "gn:admin1_code":"45",
    "gn:asciiname":"Sredniy Ruyal",
    "gn:country_code":"RU",
    "gn:dem":121,
    "gn:feature_class":"P",
    "gn:feature_code":"PPL",
    "gn:name":"Sredniy Ruyal",
    "gn:population":0,
    "gn:timezone":"Europe/Moscow",
    "iso:country":"RU",
    "name:rus_x_preferred":[
        "\u0421\u0440\u0435\u0434\u043d\u0438\u0439 \u0420\u0443\u044f\u043b"
    ],
    "wof:name":"Sredniy Ruyal",
    "wof:placetype":"locality"
},
  "geometry": {"coordinates":[49.6458,57.0238],"type":"Point"}
}