{
  "type": "Feature",
  "properties": {
    "gn:admin1_code":"8",
    "gn:asciiname":"Ishalina",
    "gn:country_code":"RU",
    "gn:dem":229,
    "gn:feature_class":"P",
    "gn:feature_code":"PPL",
    "gn:name":"Ishalina",
    "gn:population":0,
    "gn:timezone":"Asia/Yekaterinburg",
    "iso:country":"RU",
    "name:eng_x_preferred":[
        "Ishalina"
    ],
    "name:nor_x_preferred":[
        "Isjalino"
    ],
    "name:rus_x_preferred":[
        "\u0418\u0448\u0430\u043b\u0438\u043d\u043e"
    ],
    "name:rus_x_variant":[
        "\u0418\u0448\u0430\u043b\u0438\u043d\u0430"
    ],
    "name:und_x_variant":[
        "\u0418\u0448\u0430\u043b\u0438\u043d\u0430"
    ],
    "wof:name":"Ishalina",
    "wof:placetype":"locality"
},
  "geometry": {"coordinates":[58.55116999999999,56.00879000000001],"type":"Point"}
}