{
  "type": "Feature",
  "properties": {
    "gn:admin1_code":"33.0",
    "gn:asciiname":"Bol'shoy Kityak",
    "gn:country_code":"RU",
    "gn:dem":86,
    "gn:feature_class":"P",
    "gn:feature_code":"PPL",
    "gn:name":"Bol\u2019shoy Kityak",
    "gn:population":0,
    "gn:timezone":"Europe/Kirov",
    "iso:country":"RU",
    "name:rus_x_preferred":[
        "\u0411\u043e\u043b\u044c\u0448\u043e\u0439 \u041a\u0438\u0442\u044f\u043a"
    ],
    "name:und_x_variant":[
        "Bol\u2019shoy Kityak"
    ],
    "wof:name":"Bol'shoy Kityak",
    "wof:placetype":"locality"
},
  "geometry": {"coordinates":[50.753,56.3384],"type":"Point"}
}