{
  "type": "Feature",
  "properties": {
    "gn:admin1_code":"93",
    "gn:asciiname":"Khada-Bulak",
    "gn:country_code":"RU",
    "gn:dem":806,
    "gn:feature_class":"P",
    "gn:feature_code":"PPL",
    "gn:name":"Khada-Bulak",
    "gn:population":0,
    "gn:timezone":"Asia/Chita",
    "iso:country":"RU",
    "name:eng_x_preferred":[
        "Khada-Bulak"
    ],
    "name:nor_x_preferred":[
        "Khada-Bulak"
    ],
    "name:rus_x_preferred":[
        "\u0425\u0430\u0434\u0430-\u0411\u0443\u043b\u0430\u043a"
    ],
    "name:und_x_variant":[
        "Khadabulanskoye",
        "Khadabulakskoye",
        "\u0425\u0430\u0434\u0430-\u0411\u0443\u043b\u0430\u043a",
        "Khada-Bulak"
    ],
    "wof:name":"Khada-Bulak",
    "wof:placetype":"locality"
},
  "geometry": {"coordinates":[116.55,50.61667],"type":"Point"}
}