{
  "type": "Feature",
  "properties": {
    "gn:admin1_code":"55.0",
    "gn:asciiname":"Berezovyy",
    "gn:country_code":"RU",
    "gn:dem":97,
    "gn:feature_class":"P",
    "gn:feature_code":"PPL",
    "gn:name":"Ber\u00ebzovyy",
    "gn:population":0,
    "gn:timezone":"Asia/Yekaterinburg",
    "iso:country":"RU",
    "name:nor_x_preferred":[
        "Berjozovyj"
    ],
    "name:rus_x_preferred":[
        "\u0411\u0435\u0440\u0451\u0437\u043e\u0432\u044b\u0439"
    ],
    "name:und_x_variant":[
        "Berezovskiy",
        "Ber\u00ebzovyy"
    ],
    "wof:name":"Berezovyy",
    "wof:placetype":"locality"
},
  "geometry": {"coordinates":[52.46666999999999,53.36666999999999],"type":"Point"}
}