{
  "type": "Feature",
  "properties": {
    "gn:admin1_code":"47.0",
    "gn:asciiname":"Barantsevo",
    "gn:country_code":"RU",
    "gn:dem":198,
    "gn:feature_class":"P",
    "gn:feature_code":"PPL",
    "gn:name":"Barantsevo",
    "gn:population":0,
    "gn:timezone":"Europe/Moscow",
    "iso:country":"RU",
    "wof:name":"Barantsevo",
    "wof:placetype":"locality"
},
  "geometry": {"coordinates":[37.11833,55.95583000000001],"type":"Point"}
}