{
  "type": "Feature",
  "properties": {
    "gn:admin1_code":"41",
    "gn:asciiname":"Gryaznoye",
    "gn:country_code":"RU",
    "gn:dem":198,
    "gn:feature_class":"P",
    "gn:feature_code":"PPL",
    "gn:name":"Gryaznoye",
    "gn:population":0,
    "gn:timezone":"Europe/Moscow",
    "iso:country":"RU",
    "name:rus_x_preferred":[
        "\u0413\u0440\u044f\u0437\u043d\u043e\u0435"
    ],
    "wof:name":"Gryaznoye",
    "wof:placetype":"locality"
},
  "geometry": {"coordinates":[36.75778,51.98472],"type":"Point"}
}