{
  "type": "Feature",
  "properties": {
    "gn:admin1_code":"21",
    "gn:asciiname":"Osokovo",
    "gn:country_code":"RU",
    "gn:dem":129,
    "gn:feature_class":"P",
    "gn:feature_code":"PPL",
    "gn:name":"Osokovo",
    "gn:population":0,
    "gn:timezone":"Europe/Moscow",
    "iso:country":"RU",
    "name:eng_x_preferred":[
        "Osokovo"
    ],
    "name:nor_x_preferred":[
        "Osokovo"
    ],
    "name:rus_x_preferred":[
        "\u041e\u0441\u043e\u043a\u043e\u0432\u043e"
    ],
    "wof:name":"Osokovo",
    "wof:placetype":"locality"
},
  "geometry": {"coordinates":[42.53043,56.97086],"type":"Point"}
}