{
  "type": "Feature",
  "properties": {
    "gn:country":"RU",
    "gn:fcode":"PPL",
    "gn:population":3318,
    "iso:country":"RU",
    "name:ceb_x_preferred":[
        "Burmakino"
    ],
    "name:che_x_preferred":[
        "\u0411\u0443\u0440\u043c\u0430\u043a\u0438\u043d\u043e"
    ],
    "name:eng_x_preferred":[
        "Burmakino"
    ],
    "name:hye_x_preferred":[
        "\u0532\u0578\u0582\u0580\u0574\u0561\u056f\u056b\u0576\u0578"
    ],
    "name:ita_x_preferred":[
        "Burmakino"
    ],
    "name:nld_x_preferred":[
        "Burmakino"
    ],
    "name:nor_x_preferred":[
        "Burmakino"
    ],
    "name:rus_x_preferred":[
        "\u0411\u0443\u0440\u043c\u0430\u043a\u0438\u043d\u043e"
    ],
    "name:und_x_variant":[
        "Burmikino"
    ],
    "name:zho_x_preferred":[
        "\u5e03\u5c14\u9a6c\u57fa\u8bfa"
    ],
    "qs:name":"Burmakino",
    "qs:photos_9r":0,
    "qs:photos_sr":0,
    "qs:pop_sr":"4",
    "wof:name":"Burmakino",
    "wof:placetype":"locality",
    "wof:population":3318
},
  "geometry": {"coordinates":[40.23688,57.41664],"type":"Point"}
}