{
  "type": "Feature",
  "properties": {
    "gn:admin1_code":"44",
    "gn:asciiname":"Orlinaya",
    "gn:country_code":"RU",
    "gn:dem":835,
    "gn:feature_class":"P",
    "gn:feature_code":"PPL",
    "gn:name":"Orlinaya",
    "gn:population":0,
    "gn:timezone":"Asia/Magadan",
    "iso:country":"RU",
    "name:rus_x_preferred":[
        "\u041e\u0440\u043b\u0438\u043d\u0430\u044f"
    ],
    "wof:name":"Orlinaya",
    "wof:placetype":"locality"
},
  "geometry": {"coordinates":[145.80000000000001,63.76667],"type":"Point"}
}