{
  "type": "Feature",
  "properties": {
    "gn:admin1_code":"38",
    "gn:asciiname":"Plancheskaya Shchel'",
    "gn:country_code":"RU",
    "gn:dem":121,
    "gn:feature_class":"P",
    "gn:feature_code":"PPL",
    "gn:name":"Plancheskaya Shchel\u2019",
    "gn:population":0,
    "gn:timezone":"Europe/Moscow",
    "iso:country":"RU",
    "name:eng_x_preferred":[
        "Plancheskaya Shchel'"
    ],
    "name:nor_x_preferred":[
        "Plantsjeskaja-Sjtsjel"
    ],
    "name:rus_x_preferred":[
        "\u041f\u043b\u0430\u043d\u0447\u0435\u0441\u043a\u0430\u044f-\u0429\u0435\u043b\u044c"
    ],
    "name:rus_x_variant":[
        "\u041f\u043b\u0430\u043d\u0447\u0435\u0441\u043a\u0430\u044f \u0429\u0435\u043b\u044c"
    ],
    "name:und_x_variant":[
        "Plancheskaya Shchel\u2019"
    ],
    "wof:name":"Plancheskaya Shchel'",
    "wof:placetype":"locality"
},
  "geometry": {"coordinates":[38.6146,44.6352],"type":"Point"}
}