{
  "type": "Feature",
  "properties": {
    "gn:admin1_code":"17",
    "gn:admin2_code":"Shamil'skiy Rayon",
    "gn:asciiname":"Nizhniy Batlukh",
    "gn:country_code":"RU",
    "gn:dem":1520,
    "gn:feature_class":"P",
    "gn:feature_code":"PPL",
    "gn:name":"Nizhniy Batlukh",
    "gn:population":0,
    "gn:timezone":"Europe/Moscow",
    "iso:country":"RU",
    "name:rus_x_preferred":[
        "\u041d\u0438\u0436\u043d\u0438\u0439 \u0411\u0430\u0442\u043b\u0443\u0445"
    ],
    "name:und_x_variant":[
        "Nizhniy Baktlukh",
        "Nizhniy Baklukh",
        "Nizhniy Batlukh",
        "\u041d\u0438\u0436\u043d\u0438\u0439 \u0411\u0430\u0442\u043b\u0443\u0445"
    ],
    "wof:name":"Nizhniy Batlukh",
    "wof:placetype":"locality"
},
  "geometry": {"coordinates":[46.52246,42.48833],"type":"Point"}
}