{
  "type": "Feature",
  "properties": {
    "gn:admin1_code":"69.0",
    "gn:asciiname":"Cherepy-Kachenskiye",
    "gn:cc2":"RU",
    "gn:country_code":"RU",
    "gn:dem":193,
    "gn:feature_class":"P",
    "gn:feature_code":"PPL",
    "gn:name":"Cherepy-Kachenskiye",
    "gn:population":0,
    "gn:timezone":"Europe/Moscow",
    "iso:country":"RU",
    "name:rus_x_preferred":[
        "\u0427\u0435\u0440\u0435\u043f\u044b-\u041a\u0430\u0447\u0435\u043d\u0441\u043a\u0438\u0435"
    ],
    "name:und_x_variant":[
        "Cherepy",
        "Cherepy-Kachenskiye"
    ],
    "wof:name":"Cherepy-Kachenskiye",
    "wof:placetype":"locality"
},
  "geometry": {"coordinates":[34.53444,55.80722],"type":"Point"}
}