{
  "type": "Feature",
  "properties": {
    "gn:admin1_code":"84",
    "gn:asciiname":"Kraptsovskiy",
    "gn:country_code":"RU",
    "gn:dem":68,
    "gn:feature_class":"P",
    "gn:feature_code":"PPL",
    "gn:name":"Kraptsovskiy",
    "gn:population":0,
    "gn:timezone":"Europe/Volgograd",
    "iso:country":"RU",
    "name:rus_x_preferred":[
        "\u041a\u0440\u0430\u043f\u0446\u043e\u0432\u0441\u043a\u0438\u0439"
    ],
    "name:und_x_variant":[
        "\u041a\u0440\u0430\u043f\u0446\u043e\u0432\u0441\u043a\u0438\u0439"
    ],
    "wof:name":"Kraptsovskiy",
    "wof:placetype":"locality"
},
  "geometry": {"coordinates":[42.6132,49.966],"type":"Point"}
}