{
  "type": "Feature",
  "properties": {
    "gn:admin1_code":"85",
    "gn:asciiname":"Viktorovo",
    "gn:country_code":"RU",
    "gn:dem":161,
    "gn:feature_class":"P",
    "gn:feature_code":"PPL",
    "gn:name":"Viktorovo",
    "gn:population":0,
    "gn:timezone":"Europe/Moscow",
    "iso:country":"RU",
    "name:eng_x_preferred":[
        "Viktorovo"
    ],
    "name:nor_x_preferred":[
        "Viktorovo"
    ],
    "name:rus_x_preferred":[
        "\u0412\u0438\u043a\u0442\u043e\u0440\u043e\u0432\u043e"
    ],
    "wof:name":"Viktorovo",
    "wof:placetype":"locality"
},
  "geometry": {"coordinates":[46.9716,60.59727],"type":"Point"}
}