{
  "type": "Feature",
  "properties": {
    "gn:admin1_code":"4",
    "gn:asciiname":"Bol'shaya Rechka",
    "gn:country_code":"RU",
    "gn:dem":215,
    "gn:feature_class":"P",
    "gn:feature_code":"PPL",
    "gn:name":"Bol\u2019shaya Rechka",
    "gn:population":0,
    "gn:timezone":"Asia/Barnaul",
    "iso:country":"RU",
    "name:rus_x_preferred":[
        "\u0411\u043e\u043b\u044c\u0448\u0430\u044f \u0420\u0435\u0447\u043a\u0430"
    ],
    "name:und_x_variant":[
        "Troitskiy",
        "Bol\u2019shaya Rechka",
        "\u0411\u043e\u043b\u044c\u0448\u0430\u044f \u0420\u0435\u0447\u043a\u0430"
    ],
    "wof:name":"Bol'shaya Rechka",
    "wof:placetype":"locality"
},
  "geometry": {"coordinates":[84.79056,53.02694],"type":"Point"}
}