{
  "type": "Feature",
  "properties": {
    "gn:admin1_code":"45.0",
    "gn:asciiname":"Nurmuchash",
    "gn:country_code":"RU",
    "gn:dem":197,
    "gn:feature_class":"P",
    "gn:feature_code":"PPL",
    "gn:name":"Nurmuchash",
    "gn:population":0,
    "gn:timezone":"Europe/Moscow",
    "iso:country":"RU",
    "name:rus_x_preferred":[
        "\u041d\u0443\u0440\u043c\u0443\u0447\u0430\u0448"
    ],
    "wof:name":"Nurmuchash",
    "wof:placetype":"locality"
},
  "geometry": {"coordinates":[48.74472,56.92556],"type":"Point"}
}