{
  "type": "Feature",
  "properties": {
    "gn:admin1_code":"69",
    "gn:asciiname":"Nikitinka",
    "gn:country_code":"RU",
    "gn:dem":255,
    "gn:feature_class":"P",
    "gn:feature_code":"PPL",
    "gn:name":"Nikitinka",
    "gn:population":0,
    "gn:timezone":"Europe/Moscow",
    "iso:country":"RU",
    "name:bak_x_preferred":[
        "\u041d\u0438\u043a\u0438\u0442\u0438\u043d\u043a\u0430"
    ],
    "name:che_x_preferred":[
        "\u041d\u0438\u043a\u0438\u0442\u0438\u043d\u043a\u0430"
    ],
    "name:chv_x_preferred":[
        "\u041d\u0438\u043a\u0438\u0442\u0438\u043d\u043a\u0430"
    ],
    "name:hye_x_preferred":[
        "\u0546\u056b\u056f\u056b\u057f\u056b\u0576\u056f\u0561"
    ],
    "name:kaz_x_preferred":[
        "\u041d\u0438\u043a\u0438\u0442\u0438\u043d\u043a\u0430"
    ],
    "name:kir_x_preferred":[
        "\u041d\u0438\u043a\u0438\u0442\u0438\u043d\u043a\u0430"
    ],
    "name:rus_x_preferred":[
        "\u041d\u0438\u043a\u0438\u0442\u0438\u043d\u043a\u0430"
    ],
    "name:tat_x_preferred":[
        "\u041d\u0438\u043a\u0438\u0442\u0438\u043d\u043a\u0430"
    ],
    "name:ukr_x_preferred":[
        "\u041d\u0456\u043a\u0456\u0442\u0456\u043d\u043a\u0430"
    ],
    "wof:name":"Nikitinka",
    "wof:placetype":"locality"
},
  "geometry": {"coordinates":[33.46944000000001,55.595],"type":"Point"}
}