{
  "type": "Feature",
  "properties": {
    "gn:admin1_code":"69",
    "gn:asciiname":"Nikitinka",
    "gn:country_code":"RU",
    "gn:dem":255,
    "gn:feature_class":"P",
    "gn:feature_code":"PPL",
    "gn:name":"Nikitinka",
    "gn:population":0,
    "gn:timezone":"Europe/Moscow",
    "iso:country":"RU",
    "wof:name":"Nikitinka",
    "wof:placetype":"locality"
},
  "geometry": {"coordinates":[33.46944000000001,55.595],"type":"Point"}
}