{
  "type": "Feature",
  "properties": {
    "gn:admin1_code":"52",
    "gn:asciiname":"Narotovo",
    "gn:country_code":"RU",
    "gn:dem":184,
    "gn:feature_class":"P",
    "gn:feature_code":"PPL",
    "gn:name":"Narotovo",
    "gn:population":0,
    "gn:timezone":"Europe/Moscow",
    "iso:country":"RU",
    "name:rus_x_preferred":[
        "\u041d\u0430\u0440\u043e\u0442\u043e\u0432\u043e"
    ],
    "name:und_x_variant":[
        "\u041d\u0430\u0440\u043e\u0442\u043e\u0432\u043e"
    ],
    "wof:name":"Narotovo",
    "wof:placetype":"locality"
},
  "geometry": {"coordinates":[34.18333,58.85],"type":"Point"}
}