{
  "type": "Feature",
  "properties": {
    "gn:admin1_code":"42",
    "gn:admin2_code":"575409",
    "gn:asciiname":"Kozhakovo",
    "gn:country_code":"RU",
    "gn:dem":162,
    "gn:feature_class":"P",
    "gn:feature_code":"PPL",
    "gn:name":"Kozhakovo",
    "gn:population":0,
    "gn:timezone":"Europe/Moscow",
    "iso:country":"RU",
    "name:rus_x_preferred":[
        "\u041a\u043e\u0436\u0430\u043a\u043e\u0432\u043e"
    ],
    "name:und_x_variant":[
        "\u041a\u043e\u0436\u0430\u043a\u043e\u0432\u043e"
    ],
    "wof:name":"Kozhakovo",
    "wof:placetype":"locality"
},
  "geometry": {"coordinates":[34.80389,59.39],"type":"Point"}
}