{
  "type": "Feature",
  "properties": {
    "gn:admin1_code":"60",
    "gn:asciiname":"Malaya Budnitsa",
    "gn:country_code":"RU",
    "gn:dem":187,
    "gn:feature_class":"P",
    "gn:feature_code":"PPL",
    "gn:name":"Malaya Budnitsa",
    "gn:population":0,
    "gn:timezone":"Europe/Moscow",
    "iso:country":"RU",
    "name:rus_x_preferred":[
        "\u041c\u0430\u043b\u0430\u044f \u0411\u0443\u0434\u043d\u0438\u0446\u0430"
    ],
    "wof:name":"Malaya Budnitsa",
    "wof:placetype":"locality"
},
  "geometry": {"coordinates":[30.29027,55.88345],"type":"Point"}
}