{
  "type": "Feature",
  "properties": {
    "gn:admin1_code":"20",
    "gn:asciiname":"Chichek",
    "gn:country_code":"RU",
    "gn:dem":470,
    "gn:feature_class":"P",
    "gn:feature_code":"PPL",
    "gn:name":"Chichek",
    "gn:population":0,
    "gn:timezone":"Asia/Irkutsk",
    "iso:country":"RU",
    "name:eng_x_preferred":[
        "Chichek"
    ],
    "name:nor_x_preferred":[
        "Tsjitsjek"
    ],
    "name:rus_x_preferred":[
        "\u0427\u0438\u0447\u0435\u043a"
    ],
    "name:und_x_variant":[
        "Chichekovskaya",
        "Chachek",
        "\u0427\u0438\u0447\u0435\u043a",
        "Chichek"
    ],
    "wof:name":"Chichek",
    "wof:placetype":"locality"
},
  "geometry": {"coordinates":[104.79640000000001,54.5285],"type":"Point"}
}