{
  "type": "Feature",
  "properties": {
    "gn:admin1_code":"47.0",
    "gn:asciiname":"Babkino",
    "gn:country_code":"RU",
    "gn:dem":192,
    "gn:feature_class":"P",
    "gn:feature_code":"PPL",
    "gn:name":"Babkino",
    "gn:population":0,
    "gn:timezone":"Europe/Moscow",
    "iso:country":"RU",
    "name:nor_x_preferred":[
        "Babkino"
    ],
    "name:rus_x_preferred":[
        "\u0411\u0430\u0431\u043a\u0438\u043d\u043e"
    ],
    "wof:name":"Babkino",
    "wof:placetype":"locality"
},
  "geometry": {"coordinates":[36.83333,55.95],"type":"Point"}
}