{
  "type": "Feature",
  "properties": {
    "gn:admin1_code":"80",
    "gn:asciiname":"Shud'ya",
    "gn:country_code":"RU",
    "gn:dem":126,
    "gn:feature_class":"P",
    "gn:feature_code":"PPL",
    "gn:name":"Shud\u2019ya",
    "gn:population":0,
    "gn:timezone":"Europe/Samara",
    "iso:country":"RU",
    "name:nor_x_preferred":[
        "Sjudja"
    ],
    "name:rus_x_preferred":[
        "\u0428\u0443\u0434\u044c\u044f"
    ],
    "name:und_x_variant":[
        "Shudzya",
        "Shud\u2019ya"
    ],
    "wof:name":"Shud'ya",
    "wof:placetype":"locality"
},
  "geometry": {"coordinates":[53.07076,56.78586],"type":"Point"}
}