{
  "type": "Feature",
  "properties": {
    "gn:admin1_code":"64",
    "gn:asciiname":"Prirechnoye",
    "gn:cc2":"RU",
    "gn:country_code":"RU",
    "gn:dem":230,
    "gn:feature_class":"P",
    "gn:feature_code":"PPL",
    "gn:name":"Prirechnoye",
    "gn:population":0,
    "gn:timezone":"Asia/Sakhalin",
    "iso:country":"RU",
    "name:rus_x_preferred":[
        "\u041f\u0440\u0438\u0440\u0435\u0447\u043d\u043e\u0435"
    ],
    "name:und_x_variant":[
        "Amagi",
        "Prirechnoye",
        "\u041f\u0440\u0438\u0440\u0435\u0447\u043d\u043e\u0435"
    ],
    "wof:name":"Prirechnoye",
    "wof:placetype":"locality"
},
  "geometry": {"coordinates":[142.30000000000001,46.95],"type":"Point"}
}