{
  "type": "Feature",
  "properties": {
    "gn:admin1_code":"67",
    "gn:asciiname":"Nizhnyaya Chernavka",
    "gn:country_code":"RU",
    "gn:dem":55,
    "gn:feature_class":"P",
    "gn:feature_code":"PPL",
    "gn:name":"Nizhnyaya Chernavka",
    "gn:population":0,
    "gn:timezone":"Europe/Saratov",
    "iso:country":"RU",
    "name:rus_x_preferred":[
        "\u041d\u0438\u0436\u043d\u044f\u044f \u0427\u0435\u0440\u043d\u0430\u0432\u043a\u0430"
    ],
    "wof:name":"Nizhnyaya Chernavka",
    "wof:placetype":"locality"
},
  "geometry": {"coordinates":[47.22838,52.28153],"type":"Point"}
}