{
  "type": "Feature",
  "properties": {
    "gn:admin1_code":"4",
    "gn:asciiname":"Borovoy Forpost",
    "gn:cc2":"RU",
    "gn:country_code":"RU",
    "gn:dem":178,
    "gn:feature_class":"P",
    "gn:feature_code":"PPL",
    "gn:name":"Borovoy Forpost",
    "gn:population":0,
    "gn:timezone":"Asia/Barnaul",
    "iso:country":"RU",
    "name:eng_x_preferred":[
        "Borovoy Forpost"
    ],
    "name:nor_x_preferred":[
        "Bor Forpost"
    ],
    "name:rus_x_preferred":[
        "\u0411\u043e\u0440-\u0424\u043e\u0440\u043f\u043e\u0441\u0442"
    ],
    "name:rus_x_variant":[
        "\u0411\u043e\u0440\u043e\u0432\u043e\u0439 \u0424\u043e\u0440\u043f\u043e\u0441\u0442"
    ],
    "name:und_x_variant":[
        "Borovoi-Forpost\u2019",
        "Borovoy Fortpost"
    ],
    "wof:name":"Borovoy Forpost",
    "wof:placetype":"locality"
},
  "geometry": {"coordinates":[80.15000000000001,51.88333],"type":"Point"}
}