{
  "type": "Feature",
  "properties": {
    "gn:admin1_code":"43.0",
    "gn:asciiname":"Alekseyevka",
    "gn:country_code":"RU",
    "gn:dem":198,
    "gn:feature_class":"P",
    "gn:feature_code":"PPL",
    "gn:name":"Alekseyevka",
    "gn:population":0,
    "gn:timezone":"Europe/Moscow",
    "iso:country":"RU",
    "name:nor_x_preferred":[
        "Aleksejevka"
    ],
    "name:rus_x_preferred":[
        "\u0410\u043b\u0435\u043a\u0441\u0435\u0435\u0432\u043a\u0430"
    ],
    "name:und_x_variant":[
        "Alekseyevskiy Pos\u00eblok",
        "Alekseyevskiy",
        "Alekseyevka"
    ],
    "wof:name":"Alekseyevka",
    "wof:placetype":"locality"
},
  "geometry": {"coordinates":[39.53194000000001,53.40472],"type":"Point"}
}