{
  "type": "Feature",
  "properties": {
    "gn:admin1_code":"85",
    "gn:asciiname":"Trestenka",
    "gn:country_code":"RU",
    "gn:dem":141,
    "gn:feature_class":"P",
    "gn:feature_code":"PPL",
    "gn:name":"Trestenka",
    "gn:population":0,
    "gn:timezone":"Europe/Moscow",
    "iso:country":"RU",
    "name:rus_x_preferred":[
        "\u0422\u0440\u0435\u0441\u0442\u0435\u043d\u043a\u0430"
    ],
    "name:und_x_variant":[
        "\u0422\u0440\u0435\u0441\u0442\u0435\u043d\u043a\u0430"
    ],
    "wof:name":"Trestenka",
    "wof:placetype":"locality"
},
  "geometry": {"coordinates":[36.4217,58.7249],"type":"Point"}
}