{
  "type": "Feature",
  "properties": {
    "gn:admin1_code":"51",
    "gn:asciiname":"Usta",
    "gn:country_code":"RU",
    "gn:dem":126,
    "gn:feature_class":"P",
    "gn:feature_code":"PPL",
    "gn:name":"Usta",
    "gn:population":0,
    "gn:timezone":"Europe/Moscow",
    "iso:country":"RU",
    "name:aze_x_preferred":[
        "Usta"
    ],
    "name:deu_x_preferred":[
        "Usta"
    ],
    "name:nor_x_preferred":[
        "Usta"
    ],
    "name:rus_x_preferred":[
        "\u0423\u0441\u0442\u0430"
    ],
    "name:swe_x_preferred":[
        "Usta"
    ],
    "wof:name":"Usta",
    "wof:placetype":"locality"
},
  "geometry": {"coordinates":[46.3504,57.219],"type":"Point"}
}