{
  "type": "Feature",
  "properties": {
    "gn:admin1_code":"73",
    "gn:asciiname":"Malyye Yurty",
    "gn:country_code":"RU",
    "gn:dem":87,
    "gn:feature_class":"P",
    "gn:feature_code":"PPL",
    "gn:name":"Malyye Yurty",
    "gn:population":0,
    "gn:timezone":"Europe/Moscow",
    "iso:country":"RU",
    "name:rus_x_preferred":[
        "\u041c\u0430\u043b\u044b\u0435 \u042e\u0440\u0442\u044b"
    ],
    "wof:name":"Malyye Yurty",
    "wof:placetype":"locality"
},
  "geometry": {"coordinates":[48.4323,55.7812],"type":"Point"}
}