{
  "type": "Feature",
  "properties": {
    "gn:admin1_code":"69",
    "gn:asciiname":"Kobylino",
    "gn:country_code":"RU",
    "gn:dem":216,
    "gn:feature_class":"P",
    "gn:feature_code":"PPL",
    "gn:name":"Kobylino",
    "gn:population":0,
    "gn:timezone":"Europe/Moscow",
    "iso:country":"RU",
    "name:rus_x_preferred":[
        "\u041a\u043e\u0431\u044b\u043b\u0438\u043d\u043e"
    ],
    "wof:name":"Kobylino",
    "wof:placetype":"locality"
},
  "geometry": {"coordinates":[33.71611,55.61389000000001],"type":"Point"}
}