{
  "type": "Feature",
  "properties": {
    "gn:admin1_code":"34",
    "gn:asciiname":"Staryy Chukhlem",
    "gn:country_code":"RU",
    "gn:dem":110,
    "gn:feature_class":"P",
    "gn:feature_code":"PPL",
    "gn:name":"Staryy Chukhlem",
    "gn:population":0,
    "gn:timezone":"Europe/Moscow",
    "iso:country":"RU",
    "name:eng_x_preferred":[
        "Staryy Chukhlem"
    ],
    "name:nor_x_preferred":[
        "Star.Tsjukhlem"
    ],
    "name:rus_x_preferred":[
        "\u0421\u0442\u0430\u0440.\u0427\u0443\u0445\u043b\u044d\u043c"
    ],
    "name:rus_x_variant":[
        "\u0421\u0442\u0430\u0440\u044b\u0439 \u0427\u0443\u0445\u043b\u0435\u043c"
    ],
    "name:und_x_variant":[
        "Staryy Chukhlom"
    ],
    "wof:name":"Staryy Chukhlem",
    "wof:placetype":"locality"
},
  "geometry": {"coordinates":[50.17686,61.23758],"type":"Point"}
}