{
  "type": "Feature",
  "properties": {
    "gn:admin1_code":"52",
    "gn:asciiname":"Istrubishche",
    "gn:country_code":"RU",
    "gn:dem":103,
    "gn:feature_class":"P",
    "gn:feature_code":"PPL",
    "gn:name":"Istrubishche",
    "gn:population":0,
    "gn:timezone":"Europe/Moscow",
    "iso:country":"RU",
    "name:eng_x_preferred":[
        "Istrubishche"
    ],
    "name:nor_x_preferred":[
        "Istrubisjtsje"
    ],
    "name:rus_x_preferred":[
        "\u0418\u0441\u0442\u0440\u0443\u0431\u0438\u0449\u0435"
    ],
    "name:und_x_variant":[
        "Istrubishchi",
        "\u0418\u0441\u0442\u0440\u0443\u0431\u0438\u0449\u0435",
        "Istrubishche"
    ],
    "wof:name":"Istrubishche",
    "wof:placetype":"locality"
},
  "geometry": {"coordinates":[31.64944,57.21083],"type":"Point"}
}