{
  "type": "Feature",
  "properties": {
    "gn:admin1_code":"55",
    "gn:asciiname":"Kalikino",
    "gn:country_code":"RU",
    "gn:dem":174,
    "gn:feature_class":"P",
    "gn:feature_code":"PPL",
    "gn:name":"Kalikino",
    "gn:population":0,
    "gn:timezone":"Asia/Yekaterinburg",
    "iso:country":"RU",
    "name:eng_x_preferred":[
        "Kalikino"
    ],
    "name:nor_x_preferred":[
        "Kalikino"
    ],
    "name:rus_x_preferred":[
        "\u041a\u0430\u043b\u0438\u043a\u0438\u043d\u043e"
    ],
    "wof:name":"Kalikino",
    "wof:placetype":"locality"
},
  "geometry": {"coordinates":[54.08333,52.91667],"type":"Point"}
}