{
  "type": "Feature",
  "properties": {
    "gn:admin1_code":"67.0",
    "gn:asciiname":"Almazov",
    "gn:country_code":"RU",
    "gn:dem":132,
    "gn:feature_class":"P",
    "gn:feature_code":"PPL",
    "gn:name":"Almazov",
    "gn:population":0,
    "gn:timezone":"Europe/Saratov",
    "iso:country":"RU",
    "name:nor_x_preferred":[
        "Almazov"
    ],
    "name:rus_x_preferred":[
        "\u0410\u043b\u043c\u0430\u0437\u043e\u0432"
    ],
    "wof:name":"Almazov",
    "wof:placetype":"locality"
},
  "geometry": {"coordinates":[43.24861,51.28417],"type":"Point"}
}