{
  "type": "Feature",
  "properties": {
    "gn:admin1_code":"54",
    "gn:asciiname":"Zaton",
    "gn:country_code":"RU",
    "gn:dem":53,
    "gn:feature_class":"P",
    "gn:feature_code":"PPL",
    "gn:name":"Zaton",
    "gn:population":0,
    "gn:timezone":"Asia/Omsk",
    "iso:country":"RU",
    "name:rus_x_preferred":[
        "\u0417\u0430\u0442\u043e\u043d"
    ],
    "name:und_x_variant":[
        "\u0417\u0430\u0442\u043e\u043d"
    ],
    "wof:name":"Zaton",
    "wof:placetype":"locality"
},
  "geometry": {"coordinates":[70.91240000000001,57.7507],"type":"Point"}
}