{
  "type": "Feature",
  "properties": {
    "gn:admin1_code":"28.0",
    "gn:asciiname":"Dubovo",
    "gn:cc2":"RU",
    "gn:country_code":"RU",
    "gn:dem":129,
    "gn:feature_class":"P",
    "gn:feature_code":"PPL",
    "gn:name":"Dubovo",
    "gn:population":0,
    "gn:timezone":"Europe/Moscow",
    "iso:country":"RU",
    "name:rus_x_preferred":[
        "\u0414\u0443\u0431\u043e\u0432\u043e"
    ],
    "name:und_x_variant":[
        "Dubova",
        "Dubovo",
        "\u0414\u0443\u0431\u043e\u0432\u043e"
    ],
    "wof:name":"Dubovo",
    "wof:placetype":"locality"
},
  "geometry": {"coordinates":[37.73333,61.76667],"type":"Point"}
}