{
  "type": "Feature",
  "properties": {
    "gn:admin1_code":"52",
    "gn:asciiname":"Klin",
    "gn:country_code":"RU",
    "gn:dem":124,
    "gn:feature_class":"P",
    "gn:feature_code":"PPL",
    "gn:name":"Klin",
    "gn:population":0,
    "gn:timezone":"Europe/Moscow",
    "iso:country":"RU",
    "name:bul_x_preferred":[
        "\u041a\u043b\u0438\u043d"
    ],
    "name:ceb_x_preferred":[
        "Klin"
    ],
    "name:ces_x_preferred":[
        "Kl\u00edn"
    ],
    "name:deu_x_preferred":[
        "Klin"
    ],
    "name:epo_x_preferred":[
        "Klin"
    ],
    "name:fra_x_preferred":[
        "Klin"
    ],
    "name:ita_x_preferred":[
        "Klin"
    ],
    "name:nld_x_preferred":[
        "Klin"
    ],
    "name:pol_x_preferred":[
        "Klin"
    ],
    "name:rus_x_preferred":[
        "\u041a\u043b\u0438\u043d"
    ],
    "name:slk_x_preferred":[
        "Klin"
    ],
    "name:srp_x_preferred":[
        "\u041a\u043b\u0438\u043d"
    ],
    "name:swe_x_preferred":[
        "Klin"
    ],
    "name:ukr_x_preferred":[
        "\u041a\u043b\u0438\u043d"
    ],
    "wof:name":"Klin",
    "wof:placetype":"locality"
},
  "geometry": {"coordinates":[33.67542,58.59879],"type":"Point"}
}