{
  "type": "Feature",
  "properties": {
    "gn:admin1_code":"53",
    "gn:asciiname":"Kushagi",
    "gn:country_code":"RU",
    "gn:dem":111,
    "gn:feature_class":"P",
    "gn:feature_code":"PPL",
    "gn:name":"Kushagi",
    "gn:population":0,
    "gn:timezone":"Asia/Novosibirsk",
    "iso:country":"RU",
    "name:eng_x_preferred":[
        "Kushagi"
    ],
    "name:nor_x_preferred":[
        "Kusjagi"
    ],
    "name:rus_x_preferred":[
        "\u041a\u0443\u0448\u0430\u0433\u0438"
    ],
    "name:und_x_variant":[
        "Kushagovskoye",
        "\u041a\u0443\u0448\u0430\u0433\u0438",
        "Kushagi"
    ],
    "wof:name":"Kushagi",
    "wof:placetype":"locality"
},
  "geometry": {"coordinates":[75.75213000000002,55.67446],"type":"Point"}
}