{
  "type": "Feature",
  "properties": {
    "gn:admin1_code":"10",
    "gn:asciiname":"Kalinin",
    "gn:country_code":"RU",
    "gn:dem":180,
    "gn:feature_class":"P",
    "gn:feature_code":"PPL",
    "gn:name":"Kalinin",
    "gn:population":101,
    "gn:timezone":"Europe/Moscow",
    "iso:country":"RU",
    "name:rus_x_preferred":[
        "\u041a\u0430\u043b\u0438\u043d\u0438\u043d"
    ],
    "name:und_x_variant":[
        "Kalichin",
        "Kalinino",
        "Kalinin",
        "\u041a\u0430\u043b\u0438\u043d\u0438\u043d"
    ],
    "wof:name":"Kalinin",
    "wof:placetype":"locality",
    "wof:population":101
},
  "geometry": {"coordinates":[32.17521,52.64218],"type":"Point"}
}