{
  "type": "Feature",
  "properties": {
    "gn:admin1_code":"4",
    "gn:asciiname":"Verkh-Kamyshenka",
    "gn:country_code":"RU",
    "gn:dem":199,
    "gn:feature_class":"P",
    "gn:feature_code":"PPL",
    "gn:name":"Verkh-Kamyshenka",
    "gn:population":0,
    "gn:timezone":"Asia/Barnaul",
    "iso:country":"RU",
    "name:eng_x_preferred":[
        "Verkhnyaya Kamyshenka"
    ],
    "name:nor_x_preferred":[
        "Verkh-Kamysjenka"
    ],
    "name:rus_x_preferred":[
        "\u0412\u0435\u0440\u0445-\u041a\u0430\u043c\u044b\u0448\u0435\u043d\u043a\u0430"
    ],
    "name:und_x_variant":[
        "Verkhne Kamyshenka",
        "Verkhneye Kamyshenskoye",
        "Verkh-Kamyshenka",
        "Verkhnyaya-Kamyshinka"
    ],
    "wof:name":"Verkh-Kamyshenka",
    "wof:placetype":"locality"
},
  "geometry": {"coordinates":[84.80419999999999,53.5961],"type":"Point"}
}