{
  "type": "Feature",
  "properties": {
    "gn:admin1_code":"77.0",
    "gn:asciiname":"Fedotkovo",
    "gn:country_code":"RU",
    "gn:dem":151,
    "gn:feature_class":"P",
    "gn:feature_code":"PPL",
    "gn:name":"Fedotkovo",
    "gn:population":0,
    "gn:timezone":"Europe/Moscow",
    "iso:country":"RU",
    "name:rus_x_preferred":[
        "\u0424\u0435\u0434\u043e\u0442\u043a\u043e\u0432\u043e"
    ],
    "name:und_x_variant":[
        "\u0424\u0435\u0434\u043e\u0442\u043a\u043e\u0432\u043e"
    ],
    "wof:name":"Fedotkovo",
    "wof:placetype":"locality"
},
  "geometry": {"coordinates":[35.44929000000001,58.14603],"type":"Point"}
}