{
  "type": "Feature",
  "properties": {
    "gn:admin1_code":"90.0",
    "gn:asciiname":"Zhak-Klyuch",
    "gn:country_code":"RU",
    "gn:dem":186,
    "gn:feature_class":"P",
    "gn:feature_code":"PPL",
    "gn:name":"Zhak-Klyuch",
    "gn:population":0,
    "gn:timezone":"Asia/Yekaterinburg",
    "iso:country":"RU",
    "name:che_x_preferred":[
        "\u0416\u0430\u043a-\u041a\u043b\u044e\u0447"
    ],
    "name:koi_x_preferred":[
        "\u0416\u0430\u043a\u043a\u043b\u044e\u0447"
    ],
    "name:rus_x_preferred":[
        "\u0416\u0430\u043a-\u041a\u043b\u044e\u0447"
    ],
    "wof:name":"Zhak-Klyuch",
    "wof:placetype":"locality"
},
  "geometry": {"coordinates":[54.5682,58.83],"type":"Point"}
}