{
  "type": "Feature",
  "properties": {
    "gn:admin1_code":"21",
    "gn:asciiname":"Zobnino",
    "gn:country_code":"RU",
    "gn:dem":106,
    "gn:feature_class":"P",
    "gn:feature_code":"PPL",
    "gn:name":"Zobnino",
    "gn:population":0,
    "gn:timezone":"Europe/Moscow",
    "iso:country":"RU",
    "name:eng_x_preferred":[
        "Zobnino"
    ],
    "name:nor_x_preferred":[
        "Zobnino"
    ],
    "name:rus_x_preferred":[
        "\u0417\u043e\u0431\u043d\u0438\u043d\u043e"
    ],
    "name:und_x_variant":[
        "Zobninskoye",
        "Zobnino"
    ],
    "wof:name":"Zobnino",
    "wof:placetype":"locality"
},
  "geometry": {"coordinates":[42.60255,57.20088000000001],"type":"Point"}
}