{
  "type": "Feature",
  "properties": {
    "gn:admin1_code":"88",
    "gn:asciiname":"Korotylevo",
    "gn:country_code":"RU",
    "gn:dem":141,
    "gn:feature_class":"P",
    "gn:feature_code":"PPL",
    "gn:name":"Korotylevo",
    "gn:population":0,
    "gn:timezone":"Europe/Moscow",
    "iso:country":"RU",
    "name:rus_x_preferred":[
        "\u041a\u043e\u0440\u043e\u0442\u044b\u043b\u0435\u0432\u043e"
    ],
    "name:und_x_variant":[
        "\u041a\u043e\u0440\u043e\u0442\u044b\u043b\u0435\u0432\u043e",
        "Korotelevo"
    ],
    "wof:name":"Korotylevo",
    "wof:placetype":"locality"
},
  "geometry": {"coordinates":[38.9775,57.3289],"type":"Point"}
}