{
  "type": "Feature",
  "properties": {
    "gn:admin1_code":"77",
    "gn:asciiname":"Sytino",
    "gn:cc2":"RU",
    "gn:country_code":"RU",
    "gn:dem":178,
    "gn:feature_class":"P",
    "gn:feature_code":"PPL",
    "gn:name":"Sytino",
    "gn:population":0,
    "gn:timezone":"Europe/Moscow",
    "iso:country":"RU",
    "name:und_x_variant":[
        "Satino",
        "Sytino"
    ],
    "wof:name":"Sytino",
    "wof:placetype":"locality"
},
  "geometry": {"coordinates":[35.335,57.97917],"type":"Point"}
}