{
  "type": "Feature",
  "properties": {
    "gn:admin1_code":"21.0",
    "gn:asciiname":"Pigarevo",
    "gn:country_code":"RU",
    "gn:dem":120,
    "gn:feature_class":"P",
    "gn:feature_code":"PPL",
    "gn:name":"Pigar\u00ebvo",
    "gn:population":0,
    "gn:timezone":"Europe/Moscow",
    "iso:country":"RU",
    "name:rus_x_preferred":[
        "\u041f\u0438\u0433\u0430\u0440\u0451\u0432\u043e"
    ],
    "name:und_x_variant":[
        "Pigar\u00ebvo",
        "\u041f\u0438\u0433\u0430\u0440\u0451\u0432\u043e"
    ],
    "wof:name":"Pigarevo",
    "wof:placetype":"locality"
},
  "geometry": {"coordinates":[42.96738,57.30259],"type":"Point"}
}