{
  "type": "Feature",
  "properties": {
    "gn:admin1_code":"62.0",
    "gn:asciiname":"Fedino",
    "gn:country_code":"RU",
    "gn:dem":128,
    "gn:feature_class":"P",
    "gn:feature_code":"PPL",
    "gn:name":"Fedino",
    "gn:population":0,
    "gn:timezone":"Europe/Moscow",
    "iso:country":"RU",
    "name:rus_x_preferred":[
        "\u0424\u0435\u0434\u0438\u043d\u043e"
    ],
    "name:und_x_variant":[
        "\u0424\u0435\u0434\u0438\u043d\u043e"
    ],
    "wof:name":"Fedino",
    "wof:placetype":"locality"
},
  "geometry": {"coordinates":[40.4421,55.07673000000001],"type":"Point"}
}