{
  "type": "Feature",
  "properties": {
    "gn:admin1_code":"21.0",
    "gn:asciiname":"Skoba",
    "gn:country_code":"RU",
    "gn:dem":114,
    "gn:feature_class":"P",
    "gn:feature_code":"PPL",
    "gn:name":"Skoba",
    "gn:population":0,
    "gn:timezone":"Europe/Moscow",
    "iso:country":"RU",
    "name:nor_x_preferred":[
        "Skoba"
    ],
    "name:rus_x_preferred":[
        "\u0421\u043a\u043e\u0431\u0430"
    ],
    "wof:name":"Skoba",
    "wof:placetype":"locality"
},
  "geometry": {"coordinates":[42.70022,56.7056],"type":"Point"}
}