{
  "type": "Feature",
  "properties": {
    "gn:admin1_code":"85",
    "gn:asciiname":"Konovalovo",
    "gn:country_code":"RU",
    "gn:dem":140,
    "gn:feature_class":"P",
    "gn:feature_code":"PPL",
    "gn:name":"Konovalovo",
    "gn:population":0,
    "gn:timezone":"Europe/Moscow",
    "iso:country":"RU",
    "name:eng_x_preferred":[
        "Konovalovo"
    ],
    "name:nor_x_preferred":[
        "Konovalovo"
    ],
    "name:rus_x_preferred":[
        "\u041a\u043e\u043d\u043e\u0432\u0430\u043b\u043e\u0432\u043e"
    ],
    "wof:name":"Konovalovo",
    "wof:placetype":"locality"
},
  "geometry": {"coordinates":[36.6634,60.4736],"type":"Point"}
}