{
  "type": "Feature",
  "properties": {
    "gn:admin1_code":"10",
    "gn:asciiname":"Dolotnya",
    "gn:country_code":"RU",
    "gn:dem":157,
    "gn:feature_class":"P",
    "gn:feature_code":"PPL",
    "gn:name":"Dolotnya",
    "gn:population":0,
    "gn:timezone":"Europe/Moscow",
    "iso:country":"RU",
    "name:rus_x_preferred":[
        "\u0414\u043e\u043b\u043e\u0442\u043d\u044f"
    ],
    "name:und_x_variant":[
        "\u0414\u043e\u043b\u043e\u0442\u043d\u044f"
    ],
    "wof:name":"Dolotnya",
    "wof:placetype":"locality"
},
  "geometry": {"coordinates":[32.70052,53.26094000000001],"type":"Point"}
}