{
  "type": "Feature",
  "properties": {
    "gn:admin1_code":"90",
    "gn:asciiname":"Voskresensk",
    "gn:country_code":"RU",
    "gn:dem":124,
    "gn:feature_class":"P",
    "gn:feature_code":"PPL",
    "gn:name":"Voskresensk",
    "gn:population":0,
    "gn:timezone":"Asia/Yekaterinburg",
    "iso:country":"RU",
    "name:eng_x_preferred":[
        "Voskresensk"
    ],
    "name:nor_x_preferred":[
        "Voskresensk"
    ],
    "name:rus_x_preferred":[
        "\u0412\u043e\u0441\u043a\u0440\u0435\u0441\u0435\u043d\u0441\u043a"
    ],
    "name:swe_x_preferred":[
        "Voskresensk"
    ],
    "name:und_x_variant":[
        "Voskresenskoye",
        "Voskresensk"
    ],
    "wof:name":"Voskresensk",
    "wof:placetype":"locality"
},
  "geometry": {"coordinates":[55.2302,58.5839],"type":"Point"}
}