{
  "type": "Feature",
  "properties": {
    "gn:admin1_code":"55",
    "gn:asciiname":"Krasnoural'skiy",
    "gn:country_code":"RU",
    "gn:dem":143,
    "gn:feature_class":"P",
    "gn:feature_code":"PPL",
    "gn:name":"Krasnoural\u2019skiy",
    "gn:population":0,
    "gn:timezone":"Asia/Yekaterinburg",
    "iso:country":"RU",
    "name:eng_x_preferred":[
        "Krasnoural'skiy"
    ],
    "name:nor_x_preferred":[
        "Krasnouralsk"
    ],
    "name:rus_x_preferred":[
        "\u041a\u0440\u0430\u0441\u043d\u043e\u0443\u0440\u0430\u043b\u044c\u0441\u043a"
    ],
    "name:rus_x_variant":[
        "\u041a\u0440\u0430\u0441\u043d\u043e\u0443\u0440\u0430\u043b\u044c\u0441\u043a\u0438\u0439"
    ],
    "name:und_x_variant":[
        "Krasnoural\u2019skiy"
    ],
    "wof:name":"Krasnoural'skiy",
    "wof:placetype":"locality"
},
  "geometry": {"coordinates":[56.88333000000001,51.34986],"type":"Point"}
}