{
  "type": "Feature",
  "properties": {
    "gn:admin1_code":"05",
    "gn:asciiname":"Neklya",
    "gn:cc2":"RU",
    "gn:country_code":"RU",
    "gn:dem":253,
    "gn:feature_class":"P",
    "gn:feature_code":"PPL",
    "gn:name":"Neklya",
    "gn:population":0,
    "gn:timezone":"Asia/Yakutsk",
    "iso:country":"RU",
    "name:rus_x_preferred":[
        "\u041d\u0435\u043a\u043b\u044f"
    ],
    "name:und_x_variant":[
        "Nekaya",
        "Neklya"
    ],
    "wof:name":"Neklya",
    "wof:placetype":"locality"
},
  "geometry": {"coordinates":[129.58333000000002,52.28333],"type":"Point"}
}