{
  "type": "Feature",
  "properties": {
    "gn:admin1_code":"65",
    "gn:asciiname":"Stepnaya",
    "gn:country_code":"RU",
    "gn:dem":135,
    "gn:feature_class":"P",
    "gn:feature_code":"PPL",
    "gn:name":"Stepnaya",
    "gn:population":0,
    "gn:timezone":"Europe/Samara",
    "iso:country":"RU",
    "name:rus_x_preferred":[
        "\u0421\u0442\u0435\u043f\u043d\u0430\u044f"
    ],
    "wof:name":"Stepnaya",
    "wof:placetype":"locality"
},
  "geometry": {"coordinates":[49.9375,52.9933],"type":"Point"}
}