{
  "type": "Feature",
  "properties": {
    "gn:admin1_code":"33",
    "gn:asciiname":"Bol'shaya Verkhovskaya",
    "gn:country_code":"RU",
    "gn:dem":144,
    "gn:feature_class":"P",
    "gn:feature_code":"PPL",
    "gn:name":"Bol\u2019shaya Verkhovskaya",
    "gn:population":0,
    "gn:timezone":"Europe/Kirov",
    "iso:country":"RU",
    "name:rus_x_preferred":[
        "\u0411\u043e\u043b\u044c\u0448\u0430\u044f \u0412\u0435\u0440\u0445\u043e\u0432\u0441\u043a\u0430\u044f"
    ],
    "name:und_x_variant":[
        "Bol\u2019shaya Verkhovskaya",
        "\u0411\u043e\u043b\u044c\u0448\u0430\u044f \u0412\u0435\u0440\u0445\u043e\u0432\u0441\u043a\u0430\u044f"
    ],
    "wof:name":"Bol'shaya Verkhovskaya",
    "wof:placetype":"locality"
},
  "geometry": {"coordinates":[47.90413,59.22883],"type":"Point"}
}