{
  "type": "Feature",
  "properties": {
    "gn:admin1_code":"41",
    "gn:asciiname":"Uyutnyy Ugolok",
    "gn:country_code":"RU",
    "gn:dem":199,
    "gn:feature_class":"P",
    "gn:feature_code":"PPL",
    "gn:name":"Uyutnyy Ugolok",
    "gn:population":0,
    "gn:timezone":"Europe/Moscow",
    "iso:country":"RU",
    "name:rus_x_preferred":[
        "\u0423\u044e\u0442\u043d\u044b\u0439 \u0423\u0433\u043e\u043b\u043e\u043a"
    ],
    "wof:name":"Uyutnyy Ugolok",
    "wof:placetype":"locality"
},
  "geometry": {"coordinates":[34.8288,51.9074],"type":"Point"}
}