{
  "type": "Feature",
  "properties": {
    "gn:admin1_code":"37",
    "gn:asciiname":"Kovalevo",
    "gn:country_code":"RU",
    "gn:dem":144,
    "gn:feature_class":"P",
    "gn:feature_code":"PPL",
    "gn:name":"Koval\u00ebvo",
    "gn:population":0,
    "gn:timezone":"Europe/Moscow",
    "iso:country":"RU",
    "name:rus_x_preferred":[
        "\u041a\u043e\u0432\u0430\u043b\u0451\u0432\u043e"
    ],
    "name:und_x_variant":[
        "Koval\u00ebvo"
    ],
    "wof:name":"Kovalevo",
    "wof:placetype":"locality"
},
  "geometry": {"coordinates":[41.58333,57.91667],"type":"Point"}
}