{
  "type": "Feature",
  "properties": {
    "gn:admin1_code":"51",
    "gn:asciiname":"Malaya Poldnevaya",
    "gn:country_code":"RU",
    "gn:dem":131,
    "gn:feature_class":"P",
    "gn:feature_code":"PPL",
    "gn:name":"Malaya Poldnevaya",
    "gn:population":0,
    "gn:timezone":"Europe/Moscow",
    "iso:country":"RU",
    "name:rus_x_preferred":[
        "\u041c\u0430\u043b\u0430\u044f \u041f\u043e\u043b\u0434\u043d\u0435\u0432\u0430\u044f"
    ],
    "wof:name":"Malaya Poldnevaya",
    "wof:placetype":"locality"
},
  "geometry": {"coordinates":[46.4159,57.63673000000001],"type":"Point"}
}