{
  "type": "Feature",
  "properties": {
    "gn:admin1_code":"4",
    "gn:asciiname":"Ozerno-Kuznetsovo",
    "gn:country_code":"RU",
    "gn:dem":204,
    "gn:feature_class":"P",
    "gn:feature_code":"PPL",
    "gn:name":"Ozerno-Kuznetsovo",
    "gn:population":0,
    "gn:timezone":"Asia/Barnaul",
    "iso:country":"RU",
    "name:eng_x_preferred":[
        "Ozerno-Kuznetsovo"
    ],
    "name:nor_x_preferred":[
        "Ozerno-Kuznetsovo"
    ],
    "name:rus_x_preferred":[
        "\u041e\u0437\u0435\u0440\u043d\u043e-\u041a\u0443\u0437\u043d\u0435\u0446\u043e\u0432\u043e"
    ],
    "wof:name":"Ozerno-Kuznetsovo",
    "wof:placetype":"locality"
},
  "geometry": {"coordinates":[80.35720000000001,51.5128],"type":"Point"}
}