{
  "type": "Feature",
  "properties": {
    "gn:admin1_code":"46",
    "gn:asciiname":"Purkayevo",
    "gn:country_code":"RU",
    "gn:dem":153,
    "gn:feature_class":"P",
    "gn:feature_code":"PPL",
    "gn:name":"Purkayevo",
    "gn:population":0,
    "gn:timezone":"Europe/Moscow",
    "iso:country":"RU",
    "name:eng_x_preferred":[
        "Purkayevo"
    ],
    "name:nor_x_preferred":[
        "Purkajevo"
    ],
    "name:rus_x_preferred":[
        "\u041f\u0443\u0440\u043a\u0430\u0435\u0432\u043e"
    ],
    "name:und_x_variant":[
        "Nalitovo"
    ],
    "wof:name":"Purkayevo",
    "wof:placetype":"locality"
},
  "geometry": {"coordinates":[46.63525,54.37557],"type":"Point"}
}