{
  "type": "Feature",
  "properties": {
    "gn:admin1_code":"75",
    "gn:asciiname":"Alandino",
    "gn:country_code":"RU",
    "gn:dem":103,
    "gn:feature_class":"P",
    "gn:feature_code":"PPL",
    "gn:name":"Alandino",
    "gn:population":0,
    "gn:timezone":"Asia/Tomsk",
    "iso:country":"RU",
    "name:nor_x_preferred":[
        "Alandino"
    ],
    "name:rus_x_preferred":[
        "\u0410\u043b\u0430\u043d\u0434\u0438\u043d\u043e"
    ],
    "wof:name":"Alandino",
    "wof:placetype":"locality"
},
  "geometry": {"coordinates":[82.26666999999998,57.13333000000001],"type":"Point"}
}