{
  "type": "Feature",
  "properties": {
    "gn:admin1_code":"78",
    "gn:asciiname":"Sipailov",
    "gn:country_code":"RU",
    "gn:dem":49,
    "gn:feature_class":"P",
    "gn:feature_code":"PPL",
    "gn:name":"Sipailov",
    "gn:population":0,
    "gn:timezone":"Asia/Yekaterinburg",
    "iso:country":"RU",
    "name:rus_x_preferred":[
        "\u0421\u0438\u043f\u0430\u0438\u043b\u043e\u0432"
    ],
    "name:und_x_variant":[
        "Sipaylov",
        "Sipailov"
    ],
    "wof:name":"Sipailov",
    "wof:placetype":"locality"
},
  "geometry": {"coordinates":[70.9633,59.47776],"type":"Point"}
}