{
  "type": "Feature",
  "properties": {
    "gn:admin1_code":"90.0",
    "gn:asciiname":"Poletayenki",
    "gn:country_code":"RU",
    "gn:dem":138,
    "gn:feature_class":"P",
    "gn:feature_code":"PPL",
    "gn:name":"Poletayenki",
    "gn:population":0,
    "gn:timezone":"Asia/Yekaterinburg",
    "iso:country":"RU",
    "name:rus_x_preferred":[
        "\u041f\u043e\u043b\u0435\u0442\u0430\u0435\u043d\u043a\u0438"
    ],
    "name:und_x_variant":[
        "Poletainki",
        "Poletayenki"
    ],
    "wof:name":"Poletayenki",
    "wof:placetype":"locality"
},
  "geometry": {"coordinates":[56.9798,58.6586],"type":"Point"}
}