{
  "type": "Feature",
  "properties": {
    "gn:admin1_code":"28",
    "gn:asciiname":"Leppyasenakho",
    "gn:cc2":"RU",
    "gn:country_code":"RU",
    "gn:dem":212,
    "gn:feature_class":"P",
    "gn:feature_code":"PPL",
    "gn:name":"Leppyasenakho",
    "gn:population":0,
    "gn:timezone":"Europe/Moscow",
    "iso:country":"RU",
    "name:fin_x_preferred":[
        "Lepp\u00e4senaho"
    ],
    "name:rus_x_preferred":[
        "\u041b\u0435\u043f\u043f\u044f\u0441\u0435\u043d\u0430\u0445\u043e"
    ],
    "wof:name":"Leppyasenakho",
    "wof:placetype":"locality"
},
  "geometry": {"coordinates":[32.11667,62.68333000000001],"type":"Point"}
}