{
  "type": "Feature",
  "properties": {
    "gn:admin1_code":"38.0",
    "gn:asciiname":"Paylidi",
    "gn:country_code":"RU",
    "gn:dem":78,
    "gn:feature_class":"P",
    "gn:feature_code":"PPL",
    "gn:name":"Paylidi",
    "gn:population":0,
    "gn:timezone":"Europe/Moscow",
    "iso:country":"RU",
    "wof:name":"Paylidi",
    "wof:placetype":"locality"
},
  "geometry": {"coordinates":[37.43528,44.79694],"type":"Point"}
}