{
  "type": "Feature",
  "properties": {
    "gn:admin1_code":"20",
    "gn:asciiname":"Ongosor",
    "gn:country_code":"RU",
    "gn:dem":464,
    "gn:feature_class":"P",
    "gn:feature_code":"PPL",
    "gn:name":"Ongosor",
    "gn:population":0,
    "gn:timezone":"Asia/Irkutsk",
    "iso:country":"RU",
    "name:eng_x_preferred":[
        "Ongosor"
    ],
    "name:nor_x_preferred":[
        "Ongosor"
    ],
    "name:rus_x_preferred":[
        "\u041e\u043d\u0433\u043e\u0441\u043e\u0440"
    ],
    "name:und_x_variant":[
        "Anchasorski",
        "Anchasorskiy",
        "Angosar",
        "Angasor",
        "Angosorskiy",
        "Ongosor",
        "\u041e\u043d\u0433\u043e\u0441\u043e\u0440"
    ],
    "wof:name":"Ongosor",
    "wof:placetype":"locality"
},
  "geometry": {"coordinates":[104.2478,53.3928],"type":"Point"}
}