{
  "type": "Feature",
  "properties": {
    "gn:admin1_code":"80",
    "gn:asciiname":"Nizhniy Ukan",
    "gn:country_code":"RU",
    "gn:dem":148,
    "gn:feature_class":"P",
    "gn:feature_code":"PPL",
    "gn:name":"Nizhniy Ukan",
    "gn:population":0,
    "gn:timezone":"Europe/Samara",
    "iso:country":"RU",
    "name:eng_x_preferred":[
        "Nizhniy Ukan"
    ],
    "name:nor_x_preferred":[
        "Nizj.Ukan"
    ],
    "name:rus_x_preferred":[
        "\u041d\u0438\u0436.\u0423\u043a\u0430\u043d"
    ],
    "name:rus_x_variant":[
        "\u041d\u0438\u0436\u043d\u0438\u0439 \u0423\u043a\u0430\u043d"
    ],
    "name:und_x_variant":[
        "\u041d\u0438\u0436\u043d\u0438\u0439 \u0423\u043a\u0430\u043d"
    ],
    "wof:name":"Nizhniy Ukan",
    "wof:placetype":"locality"
},
  "geometry": {"coordinates":[52.0182,58.1578],"type":"Point"}
}