{
  "type": "Feature",
  "properties": {
    "gn:admin1_code":"73",
    "gn:asciiname":"Sekines'",
    "gn:country_code":"RU",
    "gn:dem":82,
    "gn:feature_class":"P",
    "gn:feature_code":"PPL",
    "gn:name":"Sekines\u2019",
    "gn:population":0,
    "gn:timezone":"Europe/Moscow",
    "iso:country":"RU",
    "name:eng_x_preferred":[
        "Sekines'"
    ],
    "name:nor_x_preferred":[
        "Sekines"
    ],
    "name:rus_x_preferred":[
        "\u0421\u0435\u043a\u0438\u043d\u0435\u0441\u044c"
    ],
    "name:und_x_variant":[
        "Sekines\u2019"
    ],
    "wof:name":"Sekines'",
    "wof:placetype":"locality"
},
  "geometry": {"coordinates":[51.30864,55.5496],"type":"Point"}
}