{
  "type": "Feature",
  "properties": {
    "gn:admin1_code":"67.0",
    "gn:asciiname":"Annin Verkh",
    "gn:country_code":"RU",
    "gn:dem":43,
    "gn:feature_class":"P",
    "gn:feature_code":"PPL",
    "gn:name":"Annin Verkh",
    "gn:population":0,
    "gn:timezone":"Europe/Saratov",
    "iso:country":"RU",
    "name:eng_x_preferred":[
        "Annin Verkh"
    ],
    "name:rus_x_preferred":[
        "\u0410\u043d\u043d\u0438\u043d-\u0412\u0435\u0440\u0445"
    ],
    "name:rus_x_variant":[
        "\u0410\u043d\u043d\u0438\u043d \u0412\u0435\u0440\u0445"
    ],
    "name:und_x_variant":[
        "Annin Verkhniy",
        "Annin Verkh"
    ],
    "wof:name":"Annin Verkh",
    "wof:placetype":"locality"
},
  "geometry": {"coordinates":[49.7386,52.0185],"type":"Point"}
}