{
  "type": "Feature",
  "properties": {
    "gn:admin1_code":"16",
    "gn:asciiname":"Zavodskoye",
    "gn:country_code":"RU",
    "gn:dem":85,
    "gn:feature_class":"P",
    "gn:feature_code":"PPL",
    "gn:name":"Zavodskoye",
    "gn:population":0,
    "gn:timezone":"Europe/Moscow",
    "iso:country":"RU",
    "name:rus_x_preferred":[
        "\u0417\u0430\u0432\u043e\u0434\u0441\u043a\u043e\u0435"
    ],
    "name:und_x_variant":[
        "Protopikha",
        "Protopikhi",
        "Zavodskoye"
    ],
    "wof:name":"Zavodskoye",
    "wof:placetype":"locality"
},
  "geometry": {"coordinates":[47.1958,56.1284],"type":"Point"}
}