{
  "type": "Feature",
  "properties": {
    "gn:admin1_code":"51",
    "gn:asciiname":"Kondrykino",
    "gn:country_code":"RU",
    "gn:dem":229,
    "gn:feature_class":"P",
    "gn:feature_code":"PPL",
    "gn:name":"Kondrykino",
    "gn:population":0,
    "gn:timezone":"Europe/Moscow",
    "iso:country":"RU",
    "name:eng_x_preferred":[
        "Kandyrkino"
    ],
    "name:nor_x_preferred":[
        "Kondrykino"
    ],
    "name:rus_x_preferred":[
        "\u041a\u043e\u043d\u0434\u0440\u044b\u043a\u0438\u043d\u043e"
    ],
    "wof:name":"Kondrykino",
    "wof:placetype":"locality"
},
  "geometry": {"coordinates":[45.03997,54.92066],"type":"Point"}
}