{
  "type": "Feature",
  "properties": {
    "gn:admin1_code":"25",
    "gn:asciiname":"Sorochenka",
    "gn:country_code":"RU",
    "gn:dem":186,
    "gn:feature_class":"P",
    "gn:feature_code":"PPL",
    "gn:name":"Sorochenka",
    "gn:population":0,
    "gn:timezone":"Europe/Moscow",
    "iso:country":"RU",
    "name:rus_x_preferred":[
        "\u0421\u043e\u0440\u043e\u0447\u0435\u043d\u043a\u0430"
    ],
    "name:und_x_variant":[
        "Sorochinka",
        "Sorochenka"
    ],
    "wof:name":"Sorochenka",
    "wof:placetype":"locality"
},
  "geometry": {"coordinates":[35.06139,54.35611],"type":"Point"}
}