{
  "type": "Feature",
  "properties": {
    "gn:admin1_code":"40",
    "gn:asciiname":"Udarnik",
    "gn:country_code":"RU",
    "gn:dem":128,
    "gn:feature_class":"P",
    "gn:feature_code":"PPL",
    "gn:name":"Udarnik",
    "gn:population":0,
    "gn:timezone":"Asia/Yekaterinburg",
    "iso:country":"RU",
    "name:eng_x_preferred":[
        "Udarnik"
    ],
    "name:nor_x_preferred":[
        "Udarnik"
    ],
    "name:rus_x_preferred":[
        "\u0423\u0434\u0430\u0440\u043d\u0438\u043a"
    ],
    "name:und_x_variant":[
        "Chistovskoye",
        "Udarnik"
    ],
    "wof:name":"Udarnik",
    "wof:placetype":"locality"
},
  "geometry": {"coordinates":[67.22845,55.33918000000001],"type":"Point"}
}