{
  "type": "Feature",
  "properties": {
    "gn:admin1_code":"20",
    "gn:asciiname":"Brikachan",
    "gn:country_code":"RU",
    "gn:dem":432,
    "gn:feature_class":"P",
    "gn:feature_code":"PPL",
    "gn:name":"Brikachan",
    "gn:population":0,
    "gn:timezone":"Asia/Irkutsk",
    "iso:country":"RU",
    "wof:name":"Brikachan",
    "wof:placetype":"locality"
},
  "geometry": {"coordinates":[107.76667,56.45],"type":"Point"}
}