{
  "type": "Feature",
  "properties": {
    "gn:admin1_code":"17.0",
    "gn:asciiname":"Ameterkmakhi",
    "gn:country_code":"RU",
    "gn:dem":1032,
    "gn:feature_class":"P",
    "gn:feature_code":"PPL",
    "gn:name":"Ameterkmakhi",
    "gn:population":0,
    "gn:timezone":"Europe/Moscow",
    "iso:country":"RU",
    "name:rus_x_preferred":[
        "\u0410\u043c\u0435\u0442\u0435\u0440\u043a\u043c\u0430\u0445\u0438"
    ],
    "wof:name":"Ameterkmakhi",
    "wof:placetype":"locality"
},
  "geometry": {"coordinates":[47.15778,42.34333],"type":"Point"}
}