{
  "type": "Feature",
  "properties": {
    "gn:admin1_code":"75",
    "gn:asciiname":"Poludenovka",
    "gn:cc2":"RU",
    "gn:country_code":"RU",
    "gn:dem":80,
    "gn:feature_class":"P",
    "gn:feature_code":"PPL",
    "gn:name":"Polud\u00ebnovka",
    "gn:population":0,
    "gn:timezone":"Asia/Tomsk",
    "iso:country":"RU",
    "name:eng_x_preferred":[
        "Polud\u00ebnovka"
    ],
    "name:nor_x_preferred":[
        "Poludenovka"
    ],
    "name:rus_x_preferred":[
        "\u041f\u043e\u043b\u0443\u0434\u0435\u043d\u043e\u0432\u043a\u0430"
    ],
    "name:rus_x_variant":[
        "\u041f\u043e\u043b\u0443\u0434\u0451\u043d\u043e\u0432\u043a\u0430"
    ],
    "name:und_x_variant":[
        "Poludenovskiy",
        "Polud\u00ebnovka",
        "\u041f\u043e\u043b\u0443\u0434\u0451\u043d\u043e\u0432\u043a\u0430"
    ],
    "wof:name":"Poludenovka",
    "wof:placetype":"locality"
},
  "geometry": {"coordinates":[84.94333,58.44361],"type":"Point"}
}