{
  "type": "Feature",
  "properties": {
    "gn:admin1_code":"60",
    "gn:asciiname":"Cherepyagino",
    "gn:country_code":"RU",
    "gn:dem":69,
    "gn:feature_class":"P",
    "gn:feature_code":"PPL",
    "gn:name":"Cherepyagino",
    "gn:population":0,
    "gn:timezone":"Europe/Moscow",
    "iso:country":"RU",
    "name:rus_x_preferred":[
        "\u0427\u0435\u0440\u0435\u043f\u044f\u0433\u0438\u043d\u043e"
    ],
    "wof:name":"Cherepyagino",
    "wof:placetype":"locality"
},
  "geometry": {"coordinates":[28.41669000000001,57.26497],"type":"Point"}
}