{
  "type": "Feature",
  "properties": {
    "gn:admin1_code":"52",
    "gn:asciiname":"Retno",
    "gn:country_code":"RU",
    "gn:dem":66,
    "gn:feature_class":"P",
    "gn:feature_code":"PPL",
    "gn:name":"Retno",
    "gn:population":0,
    "gn:timezone":"Europe/Moscow",
    "iso:country":"RU",
    "name:eng_x_preferred":[
        "Retno"
    ],
    "name:fra_x_preferred":[
        "Retno"
    ],
    "name:nor_x_preferred":[
        "Retno"
    ],
    "name:pol_x_preferred":[
        "Retno"
    ],
    "name:rus_x_preferred":[
        "\u0420\u0435\u0442\u043d\u043e"
    ],
    "name:ukr_x_preferred":[
        "\u0420\u0435\u0442\u043d\u043e"
    ],
    "name:und_x_variant":[
        "Retnya"
    ],
    "wof:name":"Retno",
    "wof:placetype":"locality"
},
  "geometry": {"coordinates":[30.20764,57.99101],"type":"Point"}
}