{
  "type": "Feature",
  "properties": {
    "gn:admin1_code":"41",
    "gn:asciiname":"Bocharovka",
    "gn:country_code":"RU",
    "gn:dem":180,
    "gn:feature_class":"P",
    "gn:feature_code":"PPL",
    "gn:name":"Bocharovka",
    "gn:population":0,
    "gn:timezone":"Europe/Moscow",
    "iso:country":"RU",
    "name:rus_x_preferred":[
        "\u0411\u043e\u0447\u0430\u0440\u043e\u0432\u043a\u0430"
    ],
    "wof:name":"Bocharovka",
    "wof:placetype":"locality"
},
  "geometry": {"coordinates":[37.0659,51.3498],"type":"Point"}
}