{
  "type": "Feature",
  "properties": {
    "gn:admin1_code":"47",
    "gn:asciiname":"Kharitonovo",
    "gn:country_code":"RU",
    "gn:dem":161,
    "gn:feature_class":"P",
    "gn:feature_code":"PPL",
    "gn:name":"Kharitonovo",
    "gn:population":0,
    "gn:timezone":"Europe/Moscow",
    "iso:country":"RU",
    "name:rus_x_preferred":[
        "\u0425\u0430\u0440\u0438\u0442\u043e\u043d\u043e\u0432\u043e"
    ],
    "name:und_x_variant":[
        "\u0425\u0430\u0440\u0438\u0442\u043e\u043d\u043e\u0432\u043e"
    ],
    "wof:name":"Kharitonovo",
    "wof:placetype":"locality"
},
  "geometry": {"coordinates":[35.53333,56.15],"type":"Point"}
}