{
  "type": "Feature",
  "properties": {
    "gn:admin1_code":"76.0",
    "gn:asciiname":"Bogorodskoye",
    "gn:country_code":"RU",
    "gn:dem":190,
    "gn:feature_class":"P",
    "gn:feature_code":"PPL",
    "gn:name":"Bogorodskoye",
    "gn:population":0,
    "gn:timezone":"Europe/Moscow",
    "iso:country":"RU",
    "name:rus_x_preferred":[
        "\u0411\u043e\u0433\u043e\u0440\u043e\u0434\u0441\u043a\u043e\u0435"
    ],
    "wof:name":"Bogorodskoye",
    "wof:placetype":"locality"
},
  "geometry": {"coordinates":[36.91314000000001,53.32539000000001],"type":"Point"}
}