{
  "type": "Feature",
  "properties": {
    "gn:admin1_code":"70.0",
    "gn:asciiname":"Blyumenfel'd",
    "gn:country_code":"RU",
    "gn:dem":410,
    "gn:feature_class":"P",
    "gn:feature_code":"PPL",
    "gn:name":"Blyumenfel'd",
    "gn:population":0,
    "gn:timezone":"Europe/Moscow",
    "iso:country":"RU",
    "wof:name":"Blyumenfel'd",
    "wof:placetype":"locality"
},
  "geometry": {"coordinates":[43.205,44.11444],"type":"Point"}
}