{
  "type": "Feature",
  "properties": {
    "gn:admin1_code":"57",
    "gn:asciiname":"Kurganovka",
    "gn:country_code":"RU",
    "gn:dem":202,
    "gn:feature_class":"P",
    "gn:feature_code":"PPL",
    "gn:name":"Kurganovka",
    "gn:population":0,
    "gn:timezone":"Europe/Moscow",
    "iso:country":"RU",
    "name:rus_x_preferred":[
        "\u041a\u0443\u0440\u0433\u0430\u043d\u043e\u0432\u043a\u0430"
    ],
    "name:und_x_variant":[
        "\u041a\u0443\u0440\u0433\u0430\u043d\u043e\u0432\u043a\u0430"
    ],
    "wof:name":"Kurganovka",
    "wof:placetype":"locality"
},
  "geometry": {"coordinates":[44.2446,53.1036],"type":"Point"}
}