{
  "type": "Feature",
  "properties": {
    "gn:admin1_code":"47",
    "gn:asciiname":"Sandarovo",
    "gn:country_code":"RU",
    "gn:dem":182,
    "gn:feature_class":"P",
    "gn:feature_code":"PPL",
    "gn:name":"Sandarovo",
    "gn:population":0,
    "gn:timezone":"Europe/Moscow",
    "iso:country":"RU",
    "name:rus_x_preferred":[
        "\u0421\u0430\u043d\u0434\u0430\u0440\u043e\u0432\u043e"
    ],
    "name:und_x_variant":[
        "\u0421\u0430\u043d\u0434\u0430\u0440\u043e\u0432\u043e"
    ],
    "wof:name":"Sandarovo",
    "wof:placetype":"locality"
},
  "geometry": {"coordinates":[37.45179,55.2503],"type":"Point"}
}