{
  "type": "Feature",
  "properties": {
    "gn:admin1_code":"83",
    "gn:asciiname":"Krutoyak",
    "gn:country_code":"RU",
    "gn:dem":109,
    "gn:feature_class":"P",
    "gn:feature_code":"PPL",
    "gn:name":"Krutoyak",
    "gn:population":0,
    "gn:timezone":"Europe/Moscow",
    "iso:country":"RU",
    "name:rus_x_preferred":[
        "\u041a\u0440\u0443\u0442\u043e\u044f\u043a"
    ],
    "name:und_x_variant":[
        "\u041a\u0440\u0443\u0442\u043e\u044f\u043a"
    ],
    "wof:name":"Krutoyak",
    "wof:placetype":"locality"
},
  "geometry": {"coordinates":[39.98474,55.94304],"type":"Point"}
}