{
  "type": "Feature",
  "properties": {
    "gn:admin1_code":"37.0",
    "gn:asciiname":"Popad'ino",
    "gn:country_code":"RU",
    "gn:dem":185,
    "gn:feature_class":"P",
    "gn:feature_code":"PPL",
    "gn:name":"Popad\u2019ino",
    "gn:population":0,
    "gn:timezone":"Europe/Moscow",
    "iso:country":"RU",
    "name:rus_x_preferred":[
        "\u041f\u043e\u043f\u0430\u0434\u044c\u0438\u043d\u043e"
    ],
    "name:und_x_variant":[
        "Popad\u2019ino"
    ],
    "wof:name":"Popad'ino",
    "wof:placetype":"locality"
},
  "geometry": {"coordinates":[41.72971,57.78274],"type":"Point"}
}