{
  "type": "Feature",
  "properties": {
    "gn:admin1_code":"48",
    "gn:admin2_code":"8520892",
    "gn:asciiname":"Starosyrovo",
    "gn:country_code":"RU",
    "gn:dem":161,
    "gn:feature_class":"P",
    "gn:feature_code":"PPL",
    "gn:name":"Starosyrovo",
    "gn:population":0,
    "gn:timezone":"Europe/Moscow",
    "iso:country":"RU",
    "name:rus_x_preferred":[
        "\u0421\u0442\u0430\u0440\u043e\u0441\u044b\u0440\u043e\u0432\u043e"
    ],
    "name:und_x_variant":[
        "Staroye Syrovo",
        "Syrovo",
        "Starosyrovo",
        "\u0421\u0442\u0430\u0440\u043e\u0441\u044b\u0440\u043e\u0432\u043e"
    ],
    "wof:name":"Starosyrovo",
    "wof:placetype":"locality"
},
  "geometry": {"coordinates":[37.53604,55.48604],"type":"Point"}
}