{
  "type": "Feature",
  "properties": {
    "gn:admin1_code":"73",
    "gn:asciiname":"Novyye Chechkaby",
    "gn:country_code":"RU",
    "gn:dem":97,
    "gn:feature_class":"P",
    "gn:feature_code":"PPL",
    "gn:name":"Novyye Chechkaby",
    "gn:population":0,
    "gn:timezone":"Europe/Moscow",
    "iso:country":"RU",
    "name:eng_x_preferred":[
        "Novyye Chechkaby"
    ],
    "name:nor_x_preferred":[
        "Novye Tsjetsjkaby"
    ],
    "name:rus_x_preferred":[
        "\u041d\u043e\u0432\u044b\u0435 \u0427\u0435\u0447\u043a\u0430\u0431\u044b"
    ],
    "name:und_x_variant":[
        "\u041d\u043e\u0432\u044b\u0435 \u0427\u0435\u0447\u043a\u0430\u0431\u044b",
        "Novyye Chechkaby"
    ],
    "wof:name":"Novyye Chechkaby",
    "wof:placetype":"locality"
},
  "geometry": {"coordinates":[48.13372,55.07188000000001],"type":"Point"}
}