{
  "type": "Feature",
  "properties": {
    "gn:admin1_code":"41.0",
    "gn:asciiname":"Don-Semitsa",
    "gn:country_code":"RU",
    "gn:dem":173,
    "gn:feature_class":"P",
    "gn:feature_code":"PPL",
    "gn:name":"Don-Semitsa",
    "gn:population":0,
    "gn:timezone":"Europe/Moscow",
    "iso:country":"RU",
    "name:rus_x_preferred":[
        "\u0414\u043e\u043d-\u0421\u0435\u043c\u0438\u0446\u0430"
    ],
    "wof:name":"Don-Semitsa",
    "wof:placetype":"locality"
},
  "geometry": {"coordinates":[36.86667,51.35],"type":"Point"}
}