{
  "type": "Feature",
  "properties": {
    "gn:admin1_code":"21.0",
    "gn:asciiname":"Orlikha",
    "gn:country_code":"RU",
    "gn:dem":109,
    "gn:feature_class":"P",
    "gn:feature_code":"PPL",
    "gn:name":"Orlikha",
    "gn:population":0,
    "gn:timezone":"Europe/Moscow",
    "iso:country":"RU",
    "name:rus_x_preferred":[
        "\u041e\u0440\u043b\u0438\u0445\u0430"
    ],
    "name:und_x_variant":[
        "\u041e\u0440\u043b\u0438\u0445\u0430"
    ],
    "wof:name":"Orlikha",
    "wof:placetype":"locality"
},
  "geometry": {"coordinates":[41.52314000000001,56.96171999999999],"type":"Point"}
}