{
  "type": "Feature",
  "properties": {
    "gn:admin1_code":"8",
    "gn:asciiname":"Nizhneidrisovo",
    "gn:country_code":"RU",
    "gn:dem":534,
    "gn:feature_class":"P",
    "gn:feature_code":"PPL",
    "gn:name":"Nizhneidrisovo",
    "gn:population":0,
    "gn:timezone":"Asia/Yekaterinburg",
    "iso:country":"RU",
    "name:aze_x_preferred":[
        "A\u015fa\u011f\u0131 \u0130zris"
    ],
    "name:bak_x_preferred":[
        "\u0422\u04af\u0431\u04d9\u043d\u0433\u0435 \u0418\u0499\u0440\u0438\u0441"
    ],
    "name:che_x_preferred":[
        "\u041d\u0438\u0436\u043d\u0435\u0438\u0434\u0440\u0438\u0441\u043e\u0432\u043e"
    ],
    "name:eng_x_preferred":[
        "Nizhneidrisovo"
    ],
    "name:hye_x_preferred":[
        "\u0546\u056b\u056a\u0576\u0565\u056b\u0564\u0580\u056b\u057d\u0578\u057e\u0578"
    ],
    "name:kaz_x_preferred":[
        "\u0422\u04e9\u043c\u0435\u043d\u0433\u0456 \u0438\u0434\u0440\u0438\u0441"
    ],
    "name:kir_x_preferred":[
        "\u0422\u04e9\u043c\u04e9\u043d\u043a\u04af \u0438\u0434\u0440\u0438\u0441"
    ],
    "name:nor_x_preferred":[
        "Verkhneidrisovo"
    ],
    "name:rus_x_preferred":[
        "\u0412\u0435\u0440\u0445\u043d\u0435\u0438\u0434\u0440\u0438\u0441\u043e\u0432\u043e"
    ],
    "name:rus_x_variant":[
        "\u041d\u0438\u0436\u043d\u0435\u0438\u0434\u0440\u0438\u0441\u043e\u0432\u043e"
    ],
    "name:tat_x_preferred":[
        "\u0422\u04af\u0431\u04d9\u043d \u0418\u0434\u0440\u0438\u0441"
    ],
    "name:ukr_x_preferred":[
        "\u041d\u0438\u0436\u043d\u044c\u043e\u0456\u0434\u0440\u0456\u0441\u043e\u0432\u043e"
    ],
    "name:und_x_variant":[
        "Nizhneye Idrisovo"
    ],
    "wof:name":"Nizhneidrisovo",
    "wof:placetype":"locality"
},
  "geometry": {"coordinates":[58.07944000000001,52.94028],"type":"Point"}
}