{
  "type": "Feature",
  "properties": {
    "gn:admin1_code":"8",
    "gn:asciiname":"Nizhneidrisovo",
    "gn:country_code":"RU",
    "gn:dem":534,
    "gn:feature_class":"P",
    "gn:feature_code":"PPL",
    "gn:name":"Nizhneidrisovo",
    "gn:population":0,
    "gn:timezone":"Asia/Yekaterinburg",
    "iso:country":"RU",
    "name:eng_x_preferred":[
        "Nizhneidrisovo"
    ],
    "name:nor_x_preferred":[
        "Verkhneidrisovo"
    ],
    "name:rus_x_preferred":[
        "\u0412\u0435\u0440\u0445\u043d\u0435\u0438\u0434\u0440\u0438\u0441\u043e\u0432\u043e"
    ],
    "name:rus_x_variant":[
        "\u041d\u0438\u0436\u043d\u0435\u0438\u0434\u0440\u0438\u0441\u043e\u0432\u043e"
    ],
    "name:und_x_variant":[
        "Nizhneye Idrisovo",
        "Nizhneidrisovo",
        "\u041d\u0438\u0436\u043d\u0435\u0438\u0434\u0440\u0438\u0441\u043e\u0432\u043e"
    ],
    "wof:name":"Nizhneidrisovo",
    "wof:placetype":"locality"
},
  "geometry": {"coordinates":[58.07944000000001,52.94028],"type":"Point"}
}