{
  "type": "Feature",
  "properties": {
    "gn:admin1_code":"37",
    "gn:asciiname":"Rakitikha",
    "gn:country_code":"RU",
    "gn:dem":145,
    "gn:feature_class":"P",
    "gn:feature_code":"PPL",
    "gn:name":"Rakitikha",
    "gn:population":0,
    "gn:timezone":"Europe/Moscow",
    "iso:country":"RU",
    "name:rus_x_preferred":[
        "\u0420\u0430\u043a\u0438\u0442\u0438\u0445\u0430"
    ],
    "wof:name":"Rakitikha",
    "wof:placetype":"locality"
},
  "geometry": {"coordinates":[45.7057,58.1154],"type":"Point"}
}