{
  "type": "Feature",
  "properties": {
    "gn:admin1_code":"80",
    "gn:asciiname":"Verkhniye Alnashi",
    "gn:country_code":"RU",
    "gn:dem":132,
    "gn:feature_class":"P",
    "gn:feature_code":"PPL",
    "gn:name":"Verkhniye Alnashi",
    "gn:population":0,
    "gn:timezone":"Europe/Samara",
    "iso:country":"RU",
    "name:und_x_variant":[
        "Verkhneye Alnashi",
        "Verkhniye Alnashi"
    ],
    "wof:name":"Verkhniye Alnashi",
    "wof:placetype":"locality"
},
  "geometry": {"coordinates":[52.41322,56.20741],"type":"Point"}
}