{
  "type": "Feature",
  "properties": {
    "gn:admin1_code":"91.0",
    "gn:asciiname":"Kan",
    "gn:country_code":"RU",
    "gn:dem":348,
    "gn:feature_class":"P",
    "gn:feature_code":"PPL",
    "gn:name":"Kan",
    "gn:population":0,
    "gn:timezone":"Asia/Krasnoyarsk",
    "iso:country":"RU",
    "name:rus_x_preferred":[
        "\u041a\u0430\u043d"
    ],
    "wof:name":"Kan",
    "wof:placetype":"locality"
},
  "geometry": {"coordinates":[95.1337,55.1597],"type":"Point"}
}