{
  "type": "Feature",
  "properties": {
    "gn:admin1_code":"52.0",
    "gn:asciiname":"Chauni",
    "gn:country_code":"RU",
    "gn:dem":62,
    "gn:feature_class":"P",
    "gn:feature_code":"PPL",
    "gn:name":"Chauni",
    "gn:population":0,
    "gn:timezone":"Europe/Moscow",
    "iso:country":"RU",
    "name:rus_x_preferred":[
        "\u0427\u0430\u0443\u043d\u0438"
    ],
    "wof:name":"Chauni",
    "wof:placetype":"locality"
},
  "geometry": {"coordinates":[31.05,58.88333000000001],"type":"Point"}
}