{
  "type": "Feature",
  "properties": {
    "gn:admin1_code":"88.0",
    "gn:asciiname":"Filimonovo",
    "gn:country_code":"RU",
    "gn:dem":162,
    "gn:feature_class":"P",
    "gn:feature_code":"PPL",
    "gn:name":"Filimonovo",
    "gn:population":0,
    "gn:timezone":"Europe/Moscow",
    "iso:country":"RU",
    "name:eng_x_preferred":[
        "Filimonovo"
    ],
    "name:nor_x_preferred":[
        "Koskovo"
    ],
    "name:rus_x_preferred":[
        "\u041a\u043e\u0441\u043a\u043e\u0432\u043e"
    ],
    "name:rus_x_variant":[
        "\u0424\u0438\u043b\u0438\u043c\u043e\u043d\u043e\u0432\u043e"
    ],
    "wof:name":"Filimonovo",
    "wof:placetype":"locality"
},
  "geometry": {"coordinates":[37.54674,58.26864000000001],"type":"Point"}
}