{
  "type": "Feature",
  "properties": {
    "gn:admin1_code":"73",
    "gn:asciiname":"Novochershilinskiy",
    "gn:country_code":"RU",
    "gn:dem":240,
    "gn:feature_class":"P",
    "gn:feature_code":"PPL",
    "gn:name":"Novochershilinskiy",
    "gn:population":0,
    "gn:timezone":"Europe/Moscow",
    "iso:country":"RU",
    "name:rus_x_preferred":[
        "\u041d\u043e\u0432\u043e\u0447\u0435\u0440\u0448\u0438\u043b\u0438\u043d\u0441\u043a\u0438\u0439"
    ],
    "wof:name":"Novochershilinskiy",
    "wof:placetype":"locality"
},
  "geometry": {"coordinates":[52.3872,54.6404],"type":"Point"}
}