{
  "type": "Feature",
  "properties": {
    "gn:country":"RU",
    "gn:fcode":"PPL",
    "gn:population":0,
    "iso:country":"RU",
    "name:eng_x_preferred":[
        "Taraskovo"
    ],
    "name:nor_x_preferred":[
        "Taraskovo"
    ],
    "name:rus_x_preferred":[
        "\u0422\u0430\u0440\u0430\u0441\u043a\u043e\u0432\u043e"
    ],
    "qs:name":"Taraskovo",
    "qs:name_adm0":"Russia",
    "qs:name_adm1":"Moscow Oblast",
    "qs:photos_9k":1,
    "qs:photos_9r":4,
    "qs:photos_all":185,
    "qs:photos_sr":0,
    "qs:placetype":"Town",
    "qs:pop_sr":"0",
    "wof:name":"Taraskovo",
    "wof:placetype":"locality",
    "wof:population":0
},
  "geometry": {"coordinates":[38.02039,54.81691],"type":"Point"}
}