{
  "type": "Feature",
  "properties": {
    "gn:admin1_code":"38.0",
    "gn:asciiname":"Borets Truda",
    "gn:country_code":"RU",
    "gn:dem":29,
    "gn:feature_class":"P",
    "gn:feature_code":"PPL",
    "gn:name":"Borets Truda",
    "gn:population":0,
    "gn:timezone":"Europe/Moscow",
    "iso:country":"RU",
    "name:rus_x_preferred":[
        "\u0411\u043e\u0440\u0435\u0446 \u0422\u0440\u0443\u0434\u0430"
    ],
    "wof:name":"Borets Truda",
    "wof:placetype":"locality"
},
  "geometry": {"coordinates":[38.83864000000001,46.22565],"type":"Point"}
}