{
  "type": "Feature",
  "properties": {
    "gn:admin1_code":"45",
    "gn:asciiname":"Yemelevo",
    "gn:country_code":"RU",
    "gn:dem":173,
    "gn:feature_class":"P",
    "gn:feature_code":"PPL",
    "gn:name":"Yemelevo",
    "gn:population":0,
    "gn:timezone":"Europe/Moscow",
    "iso:country":"RU",
    "name:eng_x_preferred":[
        "Yemelevo"
    ],
    "name:nor_x_preferred":[
        "Jemelevo"
    ],
    "name:rus_x_preferred":[
        "\u0415\u043c\u0435\u043b\u0435\u0432\u043e"
    ],
    "name:und_x_variant":[
        "\u0415\u043c\u0435\u043b\u0435\u0432\u043e"
    ],
    "wof:name":"Yemelevo",
    "wof:placetype":"locality"
},
  "geometry": {"coordinates":[46.3893,56.14147],"type":"Point"}
}