{
  "type": "Feature",
  "properties": {
    "gn:admin1_code":"77.0",
    "gn:asciiname":"Zalezh'ye",
    "gn:country_code":"RU",
    "gn:dem":232,
    "gn:feature_class":"P",
    "gn:feature_code":"PPL",
    "gn:name":"Zalezh\u2019ye",
    "gn:population":0,
    "gn:timezone":"Europe/Moscow",
    "iso:country":"RU",
    "name:rus_x_preferred":[
        "\u0417\u0430\u043b\u0435\u0436\u044c\u0435"
    ],
    "name:und_x_variant":[
        "Zalezh\u2019ye",
        "\u0417\u0430\u043b\u0435\u0436\u044c\u0435",
        "Bol\u2019shoye Zalezh\u2019ye"
    ],
    "wof:name":"Zalezh'ye",
    "wof:placetype":"locality"
},
  "geometry": {"coordinates":[31.62514,56.75028],"type":"Point"}
}