{
  "type": "Feature",
  "properties": {
    "gn:admin1_code":"69",
    "gn:asciiname":"Dyadishchevo",
    "gn:country_code":"RU",
    "gn:dem":198,
    "gn:feature_class":"P",
    "gn:feature_code":"PPL",
    "gn:name":"Dyadishchevo",
    "gn:population":0,
    "gn:timezone":"Europe/Moscow",
    "iso:country":"RU",
    "name:rus_x_preferred":[
        "\u0414\u044f\u0434\u0438\u0449\u0435\u0432\u043e"
    ],
    "name:und_x_variant":[
        "\u0414\u044f\u0434\u0438\u0449\u0435\u0432\u043e"
    ],
    "wof:name":"Dyadishchevo",
    "wof:placetype":"locality"
},
  "geometry": {"coordinates":[33.38024,54.64366],"type":"Point"}
}