{
  "type": "Feature",
  "properties": {
    "gn:admin1_code":"65.0",
    "gn:asciiname":"Annino",
    "gn:country_code":"RU",
    "gn:dem":40,
    "gn:feature_class":"P",
    "gn:feature_code":"PPL",
    "gn:name":"Annino",
    "gn:population":0,
    "gn:timezone":"Europe/Samara",
    "iso:country":"RU",
    "name:ceb_x_preferred":[
        "Annino"
    ],
    "name:nor_x_preferred":[
        "Annino"
    ],
    "name:rus_x_preferred":[
        "\u0410\u043d\u043d\u0438\u043d\u043e"
    ],
    "name:swe_x_preferred":[
        "Annino"
    ],
    "wof:name":"Annino",
    "wof:placetype":"locality"
},
  "geometry": {"coordinates":[48.5815,52.844],"type":"Point"}
}