{
  "type": "Feature",
  "properties": {
    "gn:admin1_code":"85",
    "gn:asciiname":"Sholomovo",
    "gn:country_code":"RU",
    "gn:dem":144,
    "gn:feature_class":"P",
    "gn:feature_code":"PPL",
    "gn:name":"Sholomovo",
    "gn:population":0,
    "gn:timezone":"Europe/Moscow",
    "iso:country":"RU",
    "name:rus_x_preferred":[
        "\u0428\u043e\u043b\u043e\u043c\u043e\u0432\u043e"
    ],
    "name:und_x_variant":[
        "\u0428\u043e\u043b\u043e\u043c\u043e\u0432\u043e"
    ],
    "wof:name":"Sholomovo",
    "wof:placetype":"locality"
},
  "geometry": {"coordinates":[39.67039000000001,59.20967],"type":"Point"}
}