{
  "type": "Feature",
  "properties": {
    "gn:admin1_code":"73.0",
    "gn:asciiname":"Selo-Chura",
    "gn:country_code":"RU",
    "gn:dem":156,
    "gn:feature_class":"P",
    "gn:feature_code":"PPL",
    "gn:name":"Selo-Chura",
    "gn:population":0,
    "gn:timezone":"Europe/Moscow",
    "iso:country":"RU",
    "name:rus_x_preferred":[
        "\u0421\u0435\u043b\u043e-\u0427\u0443\u0440\u0430"
    ],
    "name:und_x_variant":[
        "Chura",
        "Selo-Chura",
        "\u0421\u0435\u043b\u043e-\u0427\u0443\u0440\u0430"
    ],
    "wof:name":"Selo-Chura",
    "wof:placetype":"locality"
},
  "geometry": {"coordinates":[50.4794,56.2653],"type":"Point"}
}