{
  "type": "Feature",
  "properties": {
    "gn:admin1_code":"61",
    "gn:asciiname":"Il'ichev",
    "gn:country_code":"RU",
    "gn:dem":69,
    "gn:feature_class":"P",
    "gn:feature_code":"PPL",
    "gn:name":"Il\u2019ich\u00ebv",
    "gn:population":0,
    "gn:timezone":"Europe/Moscow",
    "iso:country":"RU",
    "name:eng_x_preferred":[
        "Il'ich\u00ebv"
    ],
    "name:nor_x_preferred":[
        "Ilitsjev"
    ],
    "name:rus_x_preferred":[
        "\u0418\u043b\u044c\u0438\u0447\u0435\u0432"
    ],
    "name:rus_x_variant":[
        "\u0418\u043b\u044c\u0438\u0447\u0451\u0432"
    ],
    "name:und_x_variant":[
        "Ternovski",
        "Il\u2019ichev-Ternovskiy",
        "Ternovskiy",
        "Il\u2019ich\u00ebv",
        "\u0418\u043b\u044c\u0438\u0447\u0451\u0432"
    ],
    "wof:name":"Il'ichev",
    "wof:placetype":"locality"
},
  "geometry": {"coordinates":[42.6875,47.1365],"type":"Point"}
}