{
  "type": "Feature",
  "properties": {
    "gn:admin1_code":"78",
    "gn:asciiname":"Sokolovka",
    "gn:country_code":"RU",
    "gn:dem":91,
    "gn:feature_class":"P",
    "gn:feature_code":"PPL",
    "gn:name":"Sokolovka",
    "gn:population":0,
    "gn:timezone":"Asia/Yekaterinburg",
    "iso:country":"RU",
    "name:eng_x_preferred":[
        "Sokolovka"
    ],
    "name:nor_x_preferred":[
        "Sokolovka"
    ],
    "name:rus_x_preferred":[
        "\u0421\u043e\u043a\u043e\u043b\u043e\u0432\u043a\u0430"
    ],
    "name:und_x_variant":[
        "\u0421\u043e\u043a\u043e\u043b\u043e\u0432\u043a\u0430",
        "Sokolovka"
    ],
    "wof:name":"Sokolovka",
    "wof:placetype":"locality"
},
  "geometry": {"coordinates":[65.68245999999999,57.72212],"type":"Point"}
}