{
  "type": "Feature",
  "properties": {
    "gn:admin1_code":"52.0",
    "gn:asciiname":"Bol'shiye Udrai",
    "gn:country_code":"RU",
    "gn:dem":60,
    "gn:feature_class":"P",
    "gn:feature_code":"PPL",
    "gn:name":"Bol\u2019shiye Udrai",
    "gn:population":0,
    "gn:timezone":"Europe/Moscow",
    "iso:country":"RU",
    "name:rus_x_preferred":[
        "\u0411\u043e\u043b\u044c\u0448\u0438\u0435 \u0423\u0434\u0440\u0430\u0438"
    ],
    "name:und_x_variant":[
        "Bol\u2019shiye Udrai"
    ],
    "wof:name":"Bol'shiye Udrai",
    "wof:placetype":"locality"
},
  "geometry": {"coordinates":[30.16552,58.65298000000001],"type":"Point"}
}