{
  "type": "Feature",
  "properties": {
    "gn:admin1_code":"52",
    "gn:asciiname":"Kiverovo",
    "gn:country_code":"RU",
    "gn:dem":141,
    "gn:feature_class":"P",
    "gn:feature_code":"PPL",
    "gn:name":"Kiverovo",
    "gn:population":0,
    "gn:timezone":"Europe/Moscow",
    "iso:country":"RU",
    "name:rus_x_preferred":[
        "\u041a\u0438\u0432\u0435\u0440\u043e\u0432\u043e"
    ],
    "wof:name":"Kiverovo",
    "wof:placetype":"locality"
},
  "geometry": {"coordinates":[34.65819,58.2958],"type":"Point"}
}