{
  "type": "Feature",
  "properties": {
    "gn:admin1_code":"10",
    "gn:asciiname":"Velikogayskiy",
    "gn:country_code":"RU",
    "gn:dem":176,
    "gn:feature_class":"P",
    "gn:feature_code":"PPL",
    "gn:name":"Velikogayskiy",
    "gn:population":0,
    "gn:timezone":"Europe/Moscow",
    "iso:country":"RU",
    "name:rus_x_preferred":[
        "\u0412\u0435\u043b\u0438\u043a\u043e\u0433\u0430\u0439\u0441\u043a\u0438\u0439"
    ],
    "wof:name":"Velikogayskiy",
    "wof:placetype":"locality"
},
  "geometry": {"coordinates":[32.221,52.4672],"type":"Point"}
}