{
  "type": "Feature",
  "properties": {
    "gn:admin1_code":"76",
    "gn:asciiname":"Krasnyye Buytsy",
    "gn:country_code":"RU",
    "gn:dem":204,
    "gn:feature_class":"P",
    "gn:feature_code":"PPL",
    "gn:name":"Krasnyye Buytsy",
    "gn:population":0,
    "gn:timezone":"Europe/Moscow",
    "iso:country":"RU",
    "name:rus_x_preferred":[
        "\u041a\u0440\u0430\u0441\u043d\u044b\u0435 \u0411\u0443\u0439\u0446\u044b"
    ],
    "name:und_x_variant":[
        "Krasnye Buytsy",
        "Krasnyye Buytsy",
        "\u041a\u0440\u0430\u0441\u043d\u044b\u0435 \u0411\u0443\u0439\u0446\u044b"
    ],
    "wof:name":"Krasnyye Buytsy",
    "wof:placetype":"locality"
},
  "geometry": {"coordinates":[38.50852,53.64992],"type":"Point"}
}