{
  "type": "Feature",
  "properties": {
    "gn:admin1_code":"61",
    "gn:asciiname":"Zherebkovskiy",
    "gn:country_code":"RU",
    "gn:dem":64,
    "gn:feature_class":"P",
    "gn:feature_code":"PPL",
    "gn:name":"Zherebkovskiy",
    "gn:population":0,
    "gn:timezone":"Europe/Moscow",
    "iso:country":"RU",
    "name:rus_x_preferred":[
        "\u0416\u0435\u0440\u0435\u0431\u043a\u043e\u0432\u0441\u043a\u0438\u0439"
    ],
    "wof:name":"Zherebkovskiy",
    "wof:placetype":"locality"
},
  "geometry": {"coordinates":[40.0875,48.9202],"type":"Point"}
}