{
  "type": "Feature",
  "properties": {
    "gn:admin1_code":"10",
    "gn:asciiname":"Strugovka",
    "gn:country_code":"RU",
    "gn:dem":152,
    "gn:feature_class":"P",
    "gn:feature_code":"PPL",
    "gn:name":"Strugovka",
    "gn:population":0,
    "gn:timezone":"Europe/Moscow",
    "iso:country":"RU",
    "name:rus_x_preferred":[
        "\u0421\u0442\u0440\u0443\u0433\u043e\u0432\u043a\u0430"
    ],
    "wof:name":"Strugovka",
    "wof:placetype":"locality"
},
  "geometry": {"coordinates":[32.07152,53.01516],"type":"Point"}
}