{
  "type": "Feature",
  "properties": {
    "gn:admin1_code":"71",
    "gn:asciiname":"Makhtyli",
    "gn:country_code":"RU",
    "gn:dem":67,
    "gn:feature_class":"P",
    "gn:feature_code":"PPL",
    "gn:name":"Makhtyli",
    "gn:population":0,
    "gn:timezone":"Asia/Yekaterinburg",
    "iso:country":"RU",
    "name:eng_x_preferred":[
        "Makhtyli"
    ],
    "name:nor_x_preferred":[
        "Makhtyli"
    ],
    "name:rus_x_preferred":[
        "\u041c\u0430\u0445\u0442\u044b\u043b\u0438"
    ],
    "wof:name":"Makhtyli",
    "wof:placetype":"locality"
},
  "geometry": {"coordinates":[62.11447,59.24061999999999],"type":"Point"}
}