{
  "type": "Feature",
  "properties": {
    "gn:admin1_code":"9",
    "gn:asciiname":"Krasnaya Livada",
    "gn:country_code":"RU",
    "gn:dem":191,
    "gn:feature_class":"P",
    "gn:feature_code":"PPL",
    "gn:name":"Krasnaya Livada",
    "gn:population":0,
    "gn:timezone":"Europe/Moscow",
    "iso:country":"RU",
    "name:rus_x_preferred":[
        "\u041a\u0440\u0430\u0441\u043d\u0430\u044f \u041b\u0438\u0432\u0430\u0434\u0430"
    ],
    "name:und_x_variant":[
        "Krasnoye",
        "Krasnaya Livada",
        "\u041a\u0440\u0430\u0441\u043d\u0430\u044f \u041b\u0438\u0432\u0430\u0434\u0430"
    ],
    "wof:name":"Krasnaya Livada",
    "wof:placetype":"locality"
},
  "geometry": {"coordinates":[38.7075,50.9961],"type":"Point"}
}