{
  "type": "Feature",
  "properties": {
    "gn:country":"RU",
    "gn:fcode":"PPL",
    "gn:pop":10183,
    "iso:country":"RU",
    "name:che_x_historical":[
        "\u00c7axker-Yurt",
        "\u015ea\u1e8bgiri-Evl",
        "\u015ea\u1e8b-Giriyn-Evla",
        "Se\u1e8ba Ata\u0121a"
    ],
    "name:che_x_preferred":[
        "\u00c7axker-Yurt"
    ],
    "name:che_x_variant":[
        "\u015ea\u1e8bgiri-Evl",
        "\u015ea\u1e8b-Giriyn-Evla",
        "Se\u1e8ba Ata\u0121a",
        "\u0421\u0435\u0445\u044c\u0430 \u0410\u0442\u0430\u0433\u0406\u0430",
        "\u0427\u0430\u0445\u043a\u0435\u0440-\u042e\u0440\u0442",
        "\u0428\u0430\u0445\u044c-\u0413\u0438\u0440\u0438\u0439\u043d-\u042d\u0432\u043b\u0430",
        "\u0428\u0430\u0445\u044c\u0433\u0438\u0440\u0438-\u042d\u0432\u043b",
        "\u0419\u043e\u043a\u043a\u0445\u0430-\u0410\u0442\u0430\u0433l\u0430",
        "\u0419\u043e\u043a\u043a\u0445\u0430-\u0410\u0442\u0430\u0433I\u0430"
    ],
    "name:deu_x_preferred":[
        "Staryje Atagi"
    ],
    "name:eng_x_preferred":[
        "Starye Atagi"
    ],
    "name:jpn_x_preferred":[
        "\u30b9\u30bf\u30fc\u30eb\u30a3\u30a8\u30fb\u30a2\u30bf\u30ae"
    ],
    "name:nld_x_preferred":[
        "Starye Atagi"
    ],
    "name:nor_x_preferred":[
        "Starye Atagi"
    ],
    "name:rus_x_historical":[
        "Vozdvi\u017eenskaja",
        "Vozdvi\u017eenskoe ukreplenie",
        "\u0412\u043e\u0437\u0434\u0432\u0438\u0436\u0435\u043d\u0441\u043a\u0430\u044f",
        "\u0412\u043e\u0437\u0434\u0432\u0438\u0436\u0435\u043d\u0441\u043a\u043e\u0435 \u0443\u043a\u0440\u0435\u043f\u043b\u0435\u043d\u0438\u0435",
        "\u041f\u0440\u0435\u0434\u0433\u043e\u0440\u043d\u043e\u0435"
    ],
    "name:rus_x_preferred":[
        "\u0421\u0442\u0430\u0440\u044b\u0435 \u0410\u0442\u0430\u0433\u0438"
    ],
    "name:rus_x_variant":[
        "Vozdvi\u017eenskaja",
        "Vozdvi\u017eenskoe ukreplenie",
        "\u0412\u043e\u0437\u0434\u0432\u0438\u0436\u0435\u043d\u0441\u043a\u0430\u044f",
        "\u0412\u043e\u0437\u0434\u0432\u0438\u0436\u0435\u043d\u0441\u043a\u043e\u0435 \u0443\u043a\u0440\u0435\u043f\u043b\u0435\u043d\u0438\u0435",
        "\u041f\u0440\u0435\u0434\u0433\u043e\u0440\u043d\u043e\u0435",
        "\u0421\u0442\u0430\u0440\u044b\u0435 \u041e\u0442\u0430\u0433\u0438"
    ],
    "name:sco_x_preferred":[
        "Starye Atagi"
    ],
    "name:unk_x_variant":[
        "Vozdvizhenskaya"
    ],
    "qs:name":"Staryye Atagi",
    "qs:name_adm0":"Russia",
    "qs:name_adm1":"Chechnya Republic",
    "qs:photos_9r":0,
    "qs:photos_sr":0,
    "qs:placetype":"Town",
    "qs:pop_sr":"6",
    "wof:name":"Staryye Atagi",
    "wof:placetype":"locality",
    "wof:population":10183
},
  "geometry": {"coordinates":[45.74056,43.12028],"type":"Point"}
}