{
  "type": "Feature",
  "properties": {
    "gn:admin1_code":"62",
    "gn:asciiname":"Serskoye",
    "gn:country_code":"RU",
    "gn:dem":113,
    "gn:feature_class":"P",
    "gn:feature_code":"PPL",
    "gn:name":"Serskoye",
    "gn:population":0,
    "gn:timezone":"Europe/Moscow",
    "iso:country":"RU",
    "name:rus_x_preferred":[
        "\u0421\u0435\u0440\u0441\u043a\u043e\u0435"
    ],
    "wof:name":"Serskoye",
    "wof:placetype":"locality"
},
  "geometry": {"coordinates":[41.92402,54.21665],"type":"Point"}
}