{
  "type": "Feature",
  "properties": {
    "gn:admin1_code":"12.0",
    "gn:asciiname":"Dzharkhoy",
    "gn:country_code":"RU",
    "gn:dem":1948,
    "gn:feature_class":"P",
    "gn:feature_code":"PPL",
    "gn:name":"Dzharkhoy",
    "gn:population":0,
    "gn:timezone":"Europe/Moscow",
    "iso:country":"RU",
    "name:rus_x_preferred":[
        "\u0414\u0436\u0430\u0440\u0445\u043e\u0439"
    ],
    "wof:name":"Dzharkhoy",
    "wof:placetype":"locality"
},
  "geometry": {"coordinates":[45.23889000000001,42.70833],"type":"Point"}
}