{
  "type": "Feature",
  "properties": {
    "gn:admin1_code":"88",
    "gn:asciiname":"Stanovishche",
    "gn:country_code":"RU",
    "gn:dem":110,
    "gn:feature_class":"P",
    "gn:feature_code":"PPL",
    "gn:name":"Stanovishche",
    "gn:population":0,
    "gn:timezone":"Europe/Moscow",
    "iso:country":"RU",
    "name:rus_x_preferred":[
        "\u0421\u0442\u0430\u043d\u043e\u0432\u0438\u0449\u0435"
    ],
    "name:und_x_variant":[
        "\u0421\u0442\u0430\u043d\u043e\u0432\u0438\u0449\u0435"
    ],
    "wof:name":"Stanovishche",
    "wof:placetype":"locality"
},
  "geometry": {"coordinates":[38.4864,57.6176],"type":"Point"}
}