{
  "type": "Feature",
  "properties": {
    "gn:admin1_code":"55",
    "gn:asciiname":"Put' Stalina",
    "gn:country_code":"RU",
    "gn:dem":60,
    "gn:feature_class":"P",
    "gn:feature_code":"PPL",
    "gn:name":"Put\u2019 Stalina",
    "gn:population":0,
    "gn:timezone":"Asia/Yekaterinburg",
    "iso:country":"RU",
    "name:rus_x_preferred":[
        "\u041f\u0443\u0442\u044c \u0421\u0442\u0430\u043b\u0438\u043d\u0430"
    ],
    "name:und_x_variant":[
        "Put\u2019 Stalina"
    ],
    "wof:name":"Put' Stalina",
    "wof:placetype":"locality"
},
  "geometry": {"coordinates":[53.53333000000001,51.55],"type":"Point"}
}