{
  "type": "Feature",
  "properties": {
    "gn:admin1_code":"69",
    "gn:asciiname":"Staraya Vorob'yevka",
    "gn:country_code":"RU",
    "gn:dem":162,
    "gn:feature_class":"P",
    "gn:feature_code":"PPL",
    "gn:name":"Staraya Vorob\u2019yevka",
    "gn:population":0,
    "gn:timezone":"Europe/Moscow",
    "iso:country":"RU",
    "name:rus_x_preferred":[
        "\u0421\u0442\u0430\u0440\u0430\u044f \u0412\u043e\u0440\u043e\u0431\u044c\u0435\u0432\u043a\u0430"
    ],
    "name:und_x_variant":[
        "Staraya Vorob\u2019yevka"
    ],
    "wof:name":"Staraya Vorob'yevka",
    "wof:placetype":"locality"
},
  "geometry": {"coordinates":[32.19684,54.18304000000001],"type":"Point"}
}