{
  "type": "Feature",
  "properties": {
    "gn:country":"RU",
    "gn:fcode":"PPL",
    "gn:population":0,
    "iso:country":"RU",
    "name:deu_x_preferred":[
        "Doni"
    ],
    "name:fin_x_preferred":[
        "Tonnila"
    ],
    "name:fra_x_preferred":[
        "Doni"
    ],
    "name:ita_x_preferred":[
        "Doni"
    ],
    "name:nld_x_preferred":[
        "Doni"
    ],
    "name:por_x_preferred":[
        "Doni"
    ],
    "name:rus_x_preferred":[
        "\u0414\u043e\u043d\u0438"
    ],
    "name:vie_x_preferred":[
        "Doni"
    ],
    "qs:name":"Doni",
    "qs:name_adm0":"Russia",
    "qs:name_adm1":"Leningrad Oblast",
    "qs:photos_9r":0,
    "qs:photos_sr":0,
    "qs:placetype":"Town",
    "qs:pop_sr":"0",
    "wd:wordcount":106,
    "wof:name":"Doni",
    "wof:placetype":"locality",
    "wof:population":0
},
  "geometry": {"coordinates":[30.23083,59.66833],"type":"Point"}
}