{
  "type": "Feature",
  "properties": {
    "gn:admin1_code":"7",
    "gn:asciiname":"Kul'pa",
    "gn:country_code":"RU",
    "gn:dem":-25,
    "gn:feature_class":"P",
    "gn:feature_code":"PPL",
    "gn:name":"Kul\u2019pa",
    "gn:population":0,
    "gn:timezone":"Europe/Astrakhan",
    "iso:country":"RU",
    "name:eng_x_preferred":[
        "Kul'pa"
    ],
    "name:nor_x_preferred":[
        "Kulpa"
    ],
    "name:rus_x_preferred":[
        "\u041a\u0443\u043b\u044c\u043f\u0430"
    ],
    "name:und_x_variant":[
        "Kul\u2019pa"
    ],
    "wof:name":"Kul'pa",
    "wof:placetype":"locality"
},
  "geometry": {"coordinates":[48.34711,46.2942],"type":"Point"}
}