{
  "type": "Feature",
  "properties": {
    "gn:admin1_code":"77",
    "gn:asciiname":"Akulovo",
    "gn:country_code":"RU",
    "gn:dem":154,
    "gn:feature_class":"P",
    "gn:feature_code":"PPL",
    "gn:name":"Akulovo",
    "gn:population":0,
    "gn:timezone":"Europe/Moscow",
    "iso:country":"RU",
    "name:rus_x_preferred":[
        "\u0410\u043a\u0443\u043b\u043e\u0432\u043e"
    ],
    "name:und_x_variant":[
        "\u0410\u043a\u0443\u043b\u043e\u0432\u043e"
    ],
    "wof:name":"Akulovo",
    "wof:placetype":"locality"
},
  "geometry": {"coordinates":[36.5534,57.3311],"type":"Point"}
}