{
  "type": "Feature",
  "properties": {
    "gn:admin1_code":"73",
    "gn:asciiname":"Karamyshevo",
    "gn:country_code":"RU",
    "gn:dem":102,
    "gn:feature_class":"P",
    "gn:feature_code":"PPL",
    "gn:name":"Karamyshevo",
    "gn:population":0,
    "gn:timezone":"Europe/Moscow",
    "iso:country":"RU",
    "name:eng_x_preferred":[
        "Karamyshevo"
    ],
    "name:nor_x_preferred":[
        "Karamysjevo"
    ],
    "name:rus_x_preferred":[
        "\u041a\u0430\u0440\u0430\u043c\u044b\u0448\u0435\u0432\u043e"
    ],
    "name:sco_x_preferred":[
        "Karamyshevo"
    ],
    "name:und_x_variant":[
        "\u041a\u0430\u0440\u0430\u043c\u044b\u0448\u0435\u0432\u043e",
        "Karamyshevo"
    ],
    "wof:name":"Karamyshevo",
    "wof:placetype":"locality"
},
  "geometry": {"coordinates":[51.43529,54.90216],"type":"Point"}
}