{
  "type": "Feature",
  "properties": {
    "gn:country":"RU",
    "gn:fcode":"PPL",
    "gn:population":1351,
    "iso:country":"RU",
    "name:eng_x_preferred":[
        "Teryayevo"
    ],
    "name:nor_x_preferred":[
        "Terjaevo"
    ],
    "name:rus_x_preferred":[
        "\u0422\u0435\u0440\u044f\u0435\u0432\u043e"
    ],
    "name:ukr_x_preferred":[
        "\u0422\u0435\u0440\u044f\u0454\u0432\u043e"
    ],
    "name:und_x_variant":[
        "Teryayeva Sloboda"
    ],
    "qs:name":"Teryayevo",
    "qs:name_adm0":"Russia",
    "qs:name_adm1":"Moscow Oblast",
    "qs:photos_9k":1,
    "qs:photos_9r":1,
    "qs:photos_all":1,
    "qs:photos_sr":0,
    "qs:placetype":"Town",
    "qs:pop_sr":"3",
    "wd:wordcount":122,
    "wof:name":"Teryayevo",
    "wof:placetype":"locality",
    "wof:population":1351
},
  "geometry": {"coordinates":[36.12545,56.16974],"type":"Point"}
}