{
  "type": "Feature",
  "properties": {
    "gn:admin1_code":"52",
    "gn:asciiname":"Polutino",
    "gn:country_code":"RU",
    "gn:dem":176,
    "gn:feature_class":"P",
    "gn:feature_code":"PPL",
    "gn:name":"Polutino",
    "gn:population":0,
    "gn:timezone":"Europe/Moscow",
    "iso:country":"RU",
    "name:rus_x_preferred":[
        "\u041f\u043e\u043b\u0443\u0442\u0438\u043d\u043e"
    ],
    "wof:name":"Polutino",
    "wof:placetype":"locality"
},
  "geometry": {"coordinates":[34.90056,58.47745],"type":"Point"}
}