{
  "type": "Feature",
  "properties": {
    "gn:admin1_code":"60",
    "gn:asciiname":"Balsovo",
    "gn:country_code":"RU",
    "gn:dem":46,
    "gn:feature_class":"P",
    "gn:feature_code":"PPL",
    "gn:name":"Balsovo",
    "gn:population":0,
    "gn:timezone":"Europe/Moscow",
    "iso:country":"RU",
    "name:rus_x_preferred":[
        "\u0411\u0430\u043b\u0441\u043e\u0432\u043e"
    ],
    "wof:name":"Balsovo",
    "wof:placetype":"locality"
},
  "geometry": {"coordinates":[28.1444,57.8289],"type":"Point"}
}