{
  "type": "Feature",
  "properties": {
    "gn:admin1_code":"52",
    "gn:asciiname":"Ostashevo",
    "gn:country_code":"RU",
    "gn:dem":167,
    "gn:feature_class":"P",
    "gn:feature_code":"PPL",
    "gn:name":"Ostash\u00ebvo",
    "gn:population":0,
    "gn:timezone":"Europe/Moscow",
    "iso:country":"RU",
    "name:eng_x_preferred":[
        "Ostash\u00ebvo"
    ],
    "name:nor_x_preferred":[
        "Ostasjevo"
    ],
    "name:rus_x_preferred":[
        "\u041e\u0441\u0442\u0430\u0448\u0435\u0432\u043e"
    ],
    "name:rus_x_variant":[
        "\u041e\u0441\u0442\u0430\u0448\u0451\u0432\u043e"
    ],
    "name:und_x_variant":[
        "Ostash\u00ebvo",
        "\u041e\u0441\u0442\u0430\u0448\u0451\u0432\u043e"
    ],
    "wof:name":"Ostashevo",
    "wof:placetype":"locality"
},
  "geometry": {"coordinates":[34.41446,58.55042],"type":"Point"}
}