{
  "type": "Feature",
  "properties": {
    "gn:admin1_code":"25",
    "gn:asciiname":"Sliznevo",
    "gn:country_code":"RU",
    "gn:dem":220,
    "gn:feature_class":"P",
    "gn:feature_code":"PPL",
    "gn:name":"Slizn\u00ebvo",
    "gn:population":0,
    "gn:timezone":"Europe/Moscow",
    "iso:country":"RU",
    "name:rus_x_preferred":[
        "\u0421\u043b\u0438\u0437\u043d\u0451\u0432\u043e"
    ],
    "name:und_x_variant":[
        "Slizn\u00ebvo",
        "\u0421\u043b\u0438\u0437\u043d\u0451\u0432\u043e"
    ],
    "wof:name":"Sliznevo",
    "wof:placetype":"locality"
},
  "geometry": {"coordinates":[35.04716,54.12212],"type":"Point"}
}