{
  "type": "Feature",
  "properties": {
    "gn:admin1_code":"8",
    "gn:asciiname":"Taishevo",
    "gn:country_code":"RU",
    "gn:dem":215,
    "gn:feature_class":"P",
    "gn:feature_code":"PPL",
    "gn:name":"Taishevo",
    "gn:population":0,
    "gn:timezone":"Asia/Yekaterinburg",
    "iso:country":"RU",
    "name:bak_x_preferred":[
        "\u0422\u0430\u0439\u044b\u0448"
    ],
    "name:che_x_preferred":[
        "\u0422\u0430\u0438\u0448\u0435\u0432\u043e"
    ],
    "name:eng_x_preferred":[
        "Taishevo"
    ],
    "name:hye_x_preferred":[
        "\u054f\u0561\u056b\u0577\u0587\u0578"
    ],
    "name:kaz_x_preferred":[
        "\u0422\u0430\u0439\u044b\u0448"
    ],
    "name:kir_x_preferred":[
        "\u0422\u0430\u0439\u044b\u0448"
    ],
    "name:nor_x_preferred":[
        "Taisjevo"
    ],
    "name:rus_x_preferred":[
        "\u0422\u0430\u0438\u0448\u0435\u0432\u043e"
    ],
    "name:tat_x_preferred":[
        "\u0422\u0430\u0435\u0448"
    ],
    "name:ukr_x_preferred":[
        "\u0422\u0430\u0457\u0448\u0435\u0432\u043e"
    ],
    "name:und_x_variant":[
        "Taisheva",
        "Taishevo"
    ],
    "wof:name":"Taishevo",
    "wof:placetype":"locality"
},
  "geometry": {"coordinates":[58.45333,55.76083000000001],"type":"Point"}
}