{
  "type": "Feature",
  "properties": {
    "gn:admin1_code":"88",
    "gn:asciiname":"Skokovo",
    "gn:country_code":"RU",
    "gn:dem":155,
    "gn:feature_class":"P",
    "gn:feature_code":"PPL",
    "gn:name":"Skokovo",
    "gn:population":0,
    "gn:timezone":"Europe/Moscow",
    "iso:country":"RU",
    "name:rus_x_preferred":[
        "\u0421\u043a\u043e\u043a\u043e\u0432\u043e"
    ],
    "name:und_x_variant":[
        "\u0421\u043a\u043e\u043a\u043e\u0432\u043e"
    ],
    "wof:name":"Skokovo",
    "wof:placetype":"locality"
},
  "geometry": {"coordinates":[38.4125,57.3381],"type":"Point"}
}