{
  "type": "Feature",
  "properties": {
    "gn:admin1_code":"43",
    "gn:asciiname":"Kuznetskaya Sloboda",
    "gn:cc2":"RU",
    "gn:country_code":"RU",
    "gn:dem":176,
    "gn:feature_class":"P",
    "gn:feature_code":"PPL",
    "gn:name":"Kuznetskaya Sloboda",
    "gn:population":0,
    "gn:timezone":"Europe/Moscow",
    "iso:country":"RU",
    "name:rus_x_preferred":[
        "\u041a\u0443\u0437\u043d\u0435\u0442\u0441\u043a\u0430\u044f \u0421\u043b\u043e\u0431\u043e\u0434\u0430"
    ],
    "name:und_x_variant":[
        "Kuznetsy",
        "Kuznetskaya Sloboda"
    ],
    "wof:name":"Kuznetskaya Sloboda",
    "wof:placetype":"locality"
},
  "geometry": {"coordinates":[39.11417,53.02361],"type":"Point"}
}