{
  "type": "Feature",
  "properties": {
    "gn:admin1_code":"84",
    "gn:asciiname":"Soldatsko-Stepnoye",
    "gn:country_code":"RU",
    "gn:dem":27,
    "gn:feature_class":"P",
    "gn:feature_code":"PPL",
    "gn:name":"Soldatsko-Stepnoye",
    "gn:population":0,
    "gn:timezone":"Europe/Volgograd",
    "iso:country":"RU",
    "name:eng_x_preferred":[
        "Soldatsko-Stepnoye"
    ],
    "name:nor_x_preferred":[
        "Soldatsko-Stepnoje"
    ],
    "name:rus_x_preferred":[
        "\u0421\u043e\u043b\u0434\u0430\u0442\u0441\u043a\u043e-\u0421\u0442\u0435\u043f\u043d\u043e\u0435"
    ],
    "wof:name":"Soldatsko-Stepnoye",
    "wof:placetype":"locality"
},
  "geometry": {"coordinates":[45.5087,49.52511],"type":"Point"}
}