{
  "type": "Feature",
  "properties": {
    "gn:admin1_code":"62.0",
    "gn:asciiname":"Chulkovo-Likharevo",
    "gn:country_code":"RU",
    "gn:dem":128,
    "gn:feature_class":"P",
    "gn:feature_code":"PPL",
    "gn:name":"Chulkovo-Likhar\u00ebvo",
    "gn:population":0,
    "gn:timezone":"Europe/Moscow",
    "iso:country":"RU",
    "name:rus_x_preferred":[
        "\u0427\u0443\u043b\u043a\u043e\u0432\u043e-\u041b\u0438\u0445\u0430\u0440\u0451\u0432\u043e"
    ],
    "name:und_x_variant":[
        "Chulkovo-Likhar\u00ebvo"
    ],
    "wof:name":"Chulkovo-Likharevo",
    "wof:placetype":"locality"
},
  "geometry": {"coordinates":[39.55,53.75],"type":"Point"}
}