{
  "type": "Feature",
  "properties": {
    "gn:admin1_code":"83",
    "gn:asciiname":"Stepan'kovo",
    "gn:country_code":"RU",
    "gn:dem":104,
    "gn:feature_class":"P",
    "gn:feature_code":"PPL",
    "gn:name":"Stepan\u2019kovo",
    "gn:population":0,
    "gn:timezone":"Europe/Moscow",
    "iso:country":"RU",
    "name:rus_x_preferred":[
        "\u0421\u0442\u0435\u043f\u0430\u043d\u044c\u043a\u043e\u0432\u043e"
    ],
    "name:und_x_variant":[
        "Stepan\u2019kovo",
        "\u0421\u0442\u0435\u043f\u0430\u043d\u044c\u043a\u043e\u0432\u043e",
        "Spepan\u2019kovo"
    ],
    "wof:name":"Stepan'kovo",
    "wof:placetype":"locality"
},
  "geometry": {"coordinates":[41.8847,55.3704],"type":"Point"}
}