{
  "type": "Feature",
  "properties": {
    "gn:admin1_code":"33",
    "gn:asciiname":"Votchinskiy Kuner",
    "gn:country_code":"RU",
    "gn:dem":129,
    "gn:feature_class":"P",
    "gn:feature_code":"PPL",
    "gn:name":"Votchinskiy Kuner",
    "gn:population":0,
    "gn:timezone":"Europe/Kirov",
    "iso:country":"RU",
    "name:rus_x_preferred":[
        "\u0412\u043e\u0442\u0447\u0438\u043d\u0441\u043a\u0438\u0439 \u041a\u0443\u043d\u0435\u0440"
    ],
    "name:und_x_variant":[
        "Votchinskiy"
    ],
    "wof:name":"Votchinskiy Kuner",
    "wof:placetype":"locality"
},
  "geometry": {"coordinates":[47.50843,56.98532],"type":"Point"}
}