{
  "type": "Feature",
  "properties": {
    "gn:admin1_code":"17",
    "gn:asciiname":"Dzhugut",
    "gn:country_code":"RU",
    "gn:dem":-10,
    "gn:feature_class":"P",
    "gn:feature_code":"PPL",
    "gn:name":"Dzhugut",
    "gn:population":0,
    "gn:timezone":"Europe/Moscow",
    "iso:country":"RU",
    "name:rus_x_preferred":[
        "\u0414\u0436\u0443\u0433\u0443\u0442"
    ],
    "name:rus_x_variant":[
        "\u0414\u0436\u0443\u0442\u043a\u0443\u0442\u0430\u043d"
    ],
    "name:und_x_variant":[
        "Dzhutkutan",
        "Dzhugut"
    ],
    "wof:name":"Dzhugut",
    "wof:placetype":"locality"
},
  "geometry": {"coordinates":[46.86498,43.70835],"type":"Point"}
}