{
  "type": "Feature",
  "properties": {
    "gn:admin1_code":"62",
    "gn:asciiname":"Khirino",
    "gn:country_code":"RU",
    "gn:dem":165,
    "gn:feature_class":"P",
    "gn:feature_code":"PPL",
    "gn:name":"Khirino",
    "gn:population":0,
    "gn:timezone":"Europe/Moscow",
    "iso:country":"RU",
    "name:rus_x_preferred":[
        "\u0425\u0438\u0440\u0438\u043d\u043e"
    ],
    "wof:name":"Khirino",
    "wof:placetype":"locality"
},
  "geometry": {"coordinates":[40.8124,53.6572],"type":"Point"}
}