{
  "type": "Feature",
  "properties": {
    "gn:admin1_code":"11",
    "gn:asciiname":"Katun'",
    "gn:country_code":"RU",
    "gn:dem":459,
    "gn:feature_class":"P",
    "gn:feature_code":"PPL",
    "gn:name":"Katun\u2019",
    "gn:population":0,
    "gn:timezone":"Asia/Irkutsk",
    "iso:country":"RU",
    "name:eng_x_preferred":[
        "Katun'"
    ],
    "name:nor_x_preferred":[
        "Katun"
    ],
    "name:rus_x_preferred":[
        "\u041a\u0430\u0442\u0443\u043d\u044c"
    ],
    "name:und_x_variant":[
        "\u041a\u0430\u0442\u0443\u043d\u044c",
        "Katun\u2019"
    ],
    "wof:name":"Katun'",
    "wof:placetype":"locality"
},
  "geometry": {"coordinates":[109.02717,53.68204],"type":"Point"}
}