{
  "type": "Feature",
  "properties": {
    "gn:admin1_code":"54",
    "gn:asciiname":"Vinogradovka",
    "gn:country_code":"RU",
    "gn:dem":119,
    "gn:feature_class":"P",
    "gn:feature_code":"PPL",
    "gn:name":"Vinogradovka",
    "gn:population":0,
    "gn:timezone":"Asia/Omsk",
    "iso:country":"RU",
    "name:che_x_preferred":[
        "\u0412\u0438\u043d\u043e\u0433\u0440\u0430\u0434\u043e\u0432\u043a\u0430"
    ],
    "name:rus_x_preferred":[
        "\u0412\u0438\u043d\u043e\u0433\u0440\u0430\u0434\u043e\u0432\u043a\u0430"
    ],
    "name:tgk_x_preferred":[
        "\u0412\u0438\u043d\u043e\u0433\u0440\u0430\u0434\u043e\u0432\u043a\u0430"
    ],
    "wof:name":"Vinogradovka",
    "wof:placetype":"locality"
},
  "geometry": {"coordinates":[71.91800000000001,55.083],"type":"Point"}
}