{
  "type": "Feature",
  "properties": {
    "gn:country":"RU",
    "gn:fcode":"PPL",
    "gn:pop":41500,
    "iso:country":"RU",
    "name:ara_x_preferred":[
        "\u0628\u064a\u062a-\u064a\u0627\u062e"
    ],
    "name:azb_x_preferred":[
        "\u067e\u06cc\u062a-\u06cc\u0627\u062e"
    ],
    "name:aze_x_preferred":[
        "P\u0131t-Yax"
    ],
    "name:bel_x_preferred":[
        "\u041f\u044b\u0446\u044c-\u042f\u0445"
    ],
    "name:bul_x_preferred":[
        "\u041f\u0438\u0442 \u042f\u0445"
    ],
    "name:chi_x_preferred":[
        "\u4f69\u8482\u4e9e\u8d6b"
    ],
    "name:dut_x_preferred":[
        "Pyt-Jach"
    ],
    "name:eng_x_preferred":[
        "Pyt-Yakh"
    ],
    "name:epo_x_preferred":[
        "Pitj-Ja\u0125"
    ],
    "name:est_x_preferred":[
        "P\u00f5t-Jahh"
    ],
    "name:fin_x_preferred":[
        "Pyt-Jah"
    ],
    "name:fre_x_preferred":[
        "Pyt-Iakh"
    ],
    "name:ger_x_preferred":[
        "Pyt-Jach"
    ],
    "name:hsb_x_preferred":[
        "Pyt-Jach"
    ],
    "name:ita_x_preferred":[
        "Pyt'-Jach"
    ],
    "name:nno_x_preferred":[
        "Pyt-Jakh"
    ],
    "name:nob_x_preferred":[
        "Pyt-Jakh"
    ],
    "name:per_x_preferred":[
        "\u067e\u06cc\u062a-\u06cc\u0627\u062e"
    ],
    "name:pol_x_preferred":[
        "Pyt-Jach"
    ],
    "name:rus_x_preferred":[
        "\u041f\u044b\u0442\u044c-\u042f\u0445"
    ],
    "name:srp_x_preferred":[
        "\u041f\u0438\u0442-\u0408\u0430\u0445"
    ],
    "name:tat_x_preferred":[
        "\u041f\u044b\u0442\u044c-\u042f\u0445"
    ],
    "name:tgk_x_preferred":[
        "\u041f\u0438\u0442-\u042f\u0445"
    ],
    "name:tgl_x_preferred":[
        "Pyt-Yakh"
    ],
    "name:vie_x_preferred":[
        "Pyt-Yakh"
    ],
    "name:war_x_preferred":[
        "Pyt-Yakh"
    ],
    "qs:name":"Pyt-Yakh",
    "qs:photos_9r":0,
    "qs:photos_sr":0,
    "qs:pop_sr":"7",
    "wd:population":41005,
    "wd:wordcount":815,
    "wof:name":"Pyt-Yakh",
    "wof:placetype":"locality",
    "wof:population":41005
},
  "geometry": {"coordinates":[72.85824,60.74985],"type":"Point"}
}