{
  "type": "Feature",
  "properties": {
    "gn:admin1_code":"51.0",
    "gn:asciiname":"Pobegayki",
    "gn:country_code":"RU",
    "gn:dem":82,
    "gn:feature_class":"P",
    "gn:feature_code":"PPL",
    "gn:name":"Pobegayki",
    "gn:population":0,
    "gn:timezone":"Europe/Moscow",
    "iso:country":"RU",
    "name:rus_x_preferred":[
        "\u041f\u043e\u0431\u0435\u0433\u0430\u0439\u043a\u0438"
    ],
    "wof:name":"Pobegayki",
    "wof:placetype":"locality"
},
  "geometry": {"coordinates":[44.24666,56.44538000000001],"type":"Point"}
}