{
  "type": "Feature",
  "properties": {
    "gn:admin1_code":"78",
    "gn:asciiname":"Byzova",
    "gn:country_code":"RU",
    "gn:dem":64,
    "gn:feature_class":"P",
    "gn:feature_code":"PPL",
    "gn:name":"Byzova",
    "gn:population":0,
    "gn:timezone":"Asia/Yekaterinburg",
    "iso:country":"RU",
    "name:eng_x_preferred":[
        "Byzova"
    ],
    "name:nor_x_preferred":[
        "Byzovo"
    ],
    "name:rus_x_preferred":[
        "\u0411\u044b\u0437\u043e\u0432\u043e"
    ],
    "name:rus_x_variant":[
        "\u0411\u044b\u0437\u043e\u0432\u0430"
    ],
    "name:und_x_variant":[
        "\u0411\u044b\u0437\u043e\u0432\u0430"
    ],
    "wof:name":"Byzova",
    "wof:placetype":"locality"
},
  "geometry": {"coordinates":[66.19464000000001,56.30369],"type":"Point"}
}