{
  "type": "Feature",
  "properties": {
    "gn:admin1_code":"69",
    "gn:asciiname":"Ostashkovo",
    "gn:country_code":"RU",
    "gn:dem":222,
    "gn:feature_class":"P",
    "gn:feature_code":"PPL",
    "gn:name":"Ostashkovo",
    "gn:population":0,
    "gn:timezone":"Europe/Moscow",
    "iso:country":"RU",
    "name:rus_x_preferred":[
        "\u041e\u0441\u0442\u0430\u0448\u043a\u043e\u0432\u043e"
    ],
    "name:und_x_variant":[
        "\u041e\u0441\u0442\u0430\u0448\u043a\u043e\u0432\u043e"
    ],
    "wof:name":"Ostashkovo",
    "wof:placetype":"locality"
},
  "geometry": {"coordinates":[33.80417,55.26278000000001],"type":"Point"}
}