{
  "type": "Feature",
  "properties": {
    "gn:admin1_code":"17.0",
    "gn:asciiname":"Furdag",
    "gn:country_code":"RU",
    "gn:dem":1214,
    "gn:feature_class":"P",
    "gn:feature_code":"PPL",
    "gn:name":"Furdag",
    "gn:population":0,
    "gn:timezone":"Europe/Moscow",
    "iso:country":"RU",
    "name:rus_x_preferred":[
        "\u0424\u0443\u0440\u0434\u0430\u0433"
    ],
    "wof:name":"Furdag",
    "wof:placetype":"locality"
},
  "geometry": {"coordinates":[47.86215,41.86348],"type":"Point"}
}