{
  "type": "Feature",
  "properties": {
    "gn:admin1_code":"76",
    "gn:asciiname":"Odintsovo",
    "gn:country_code":"RU",
    "gn:dem":162,
    "gn:feature_class":"P",
    "gn:feature_code":"PPL",
    "gn:name":"Odintsovo",
    "gn:population":0,
    "gn:timezone":"Europe/Moscow",
    "iso:country":"RU",
    "name:rus_x_preferred":[
        "\u041e\u0434\u0438\u043d\u0446\u043e\u0432\u043e"
    ],
    "wof:name":"Odintsovo",
    "wof:placetype":"locality"
},
  "geometry": {"coordinates":[37.99435,54.66561],"type":"Point"}
}