{
  "type": "Feature",
  "properties": {
    "gn:admin1_code":"23",
    "gn:asciiname":"Maloye Belozernoye",
    "gn:country_code":"RU",
    "gn:dem":174,
    "gn:feature_class":"P",
    "gn:feature_code":"PPL",
    "gn:name":"Maloye Beloz\u00ebrnoye",
    "gn:population":0,
    "gn:timezone":"Europe/Kaliningrad",
    "iso:country":"RU",
    "name:rus_x_preferred":[
        "\u041c\u0430\u043b\u043e\u0435 \u0411\u0435\u043b\u043e\u0437\u0451\u0440\u043d\u043e\u0435"
    ],
    "name:und_x_variant":[
        "Maloye Beloz\u00ebrnoye",
        "\u041c\u0430\u043b\u043e\u0435 \u0411\u0435\u043b\u043e\u0437\u0451\u0440\u043d\u043e\u0435"
    ],
    "wof:name":"Maloye Belozernoye",
    "wof:placetype":"locality"
},
  "geometry": {"coordinates":[22.69889,54.45194],"type":"Point"}
}