{
  "type": "Feature",
  "properties": {
    "gn:admin1_code":"33",
    "gn:asciiname":"Kul'ma",
    "gn:country_code":"RU",
    "gn:dem":126,
    "gn:feature_class":"P",
    "gn:feature_code":"PPL",
    "gn:name":"Kul\u2019ma",
    "gn:population":0,
    "gn:timezone":"Europe/Kirov",
    "iso:country":"RU",
    "name:eng_x_preferred":[
        "Kul'ma"
    ],
    "name:nor_x_preferred":[
        "Kulma"
    ],
    "name:rus_x_preferred":[
        "\u041a\u0443\u043b\u044c\u043c\u0430"
    ],
    "name:und_x_variant":[
        "Kul\u2019ma"
    ],
    "wof:name":"Kul'ma",
    "wof:placetype":"locality"
},
  "geometry": {"coordinates":[50.80231,57.24235],"type":"Point"}
}