{
  "type": "Feature",
  "properties": {
    "gn:admin1_code":"52",
    "gn:asciiname":"Podbelo",
    "gn:country_code":"RU",
    "gn:dem":26,
    "gn:feature_class":"P",
    "gn:feature_code":"PPL",
    "gn:name":"Podbelo",
    "gn:population":0,
    "gn:timezone":"Europe/Moscow",
    "iso:country":"RU",
    "name:rus_x_preferred":[
        "\u041f\u043e\u0434\u0431\u0435\u043b\u043e"
    ],
    "wof:name":"Podbelo",
    "wof:placetype":"locality"
},
  "geometry": {"coordinates":[31.88333,57.88333000000001],"type":"Point"}
}