{
  "type": "Feature",
  "properties": {
    "gn:admin1_code":"88",
    "gn:asciiname":"Il'kino",
    "gn:country_code":"RU",
    "gn:dem":157,
    "gn:feature_class":"P",
    "gn:feature_code":"PPL",
    "gn:name":"Il\u2019kino",
    "gn:population":0,
    "gn:timezone":"Europe/Moscow",
    "iso:country":"RU",
    "name:rus_x_preferred":[
        "\u0418\u043b\u044c\u043a\u0438\u043d\u043e"
    ],
    "name:und_x_variant":[
        "Il\u2019kino"
    ],
    "wof:name":"Il'kino",
    "wof:placetype":"locality"
},
  "geometry": {"coordinates":[39.3656,57.7985],"type":"Point"}
}