{
  "type": "Feature",
  "properties": {
    "gn:admin1_code":"51",
    "gn:asciiname":"Paraguzikha",
    "gn:country_code":"RU",
    "gn:dem":104,
    "gn:feature_class":"P",
    "gn:feature_code":"PPL",
    "gn:name":"Paraguzikha",
    "gn:population":0,
    "gn:timezone":"Europe/Moscow",
    "iso:country":"RU",
    "name:rus_x_preferred":[
        "\u041f\u0430\u0440\u0430\u0433\u0443\u0437\u0438\u0445\u0430"
    ],
    "name:und_x_variant":[
        "\u041f\u0430\u0440\u0430\u0433\u0443\u0437\u0438\u0445\u0430"
    ],
    "wof:name":"Paraguzikha",
    "wof:placetype":"locality"
},
  "geometry": {"coordinates":[45.1081,57.6608],"type":"Point"}
}