{
  "type": "Feature",
  "properties": {
    "gn:admin1_code":"9",
    "gn:asciiname":"Vodyanoye",
    "gn:country_code":"RU",
    "gn:dem":212,
    "gn:feature_class":"P",
    "gn:feature_code":"PPL",
    "gn:name":"Vodyanoye",
    "gn:population":0,
    "gn:timezone":"Europe/Moscow",
    "iso:country":"RU",
    "name:rus_x_preferred":[
        "\u0412\u043e\u0434\u044f\u043d\u043e\u0435"
    ],
    "name:und_x_variant":[
        "Vodyanoy"
    ],
    "wof:name":"Vodyanoye",
    "wof:placetype":"locality"
},
  "geometry": {"coordinates":[37.48358,50.9627],"type":"Point"}
}