{
  "type": "Feature",
  "properties": {
    "gn:admin1_code":"77",
    "gn:asciiname":"Shestino",
    "gn:country_code":"RU",
    "gn:dem":138,
    "gn:feature_class":"P",
    "gn:feature_code":"PPL",
    "gn:name":"Shestino",
    "gn:population":0,
    "gn:timezone":"Europe/Moscow",
    "iso:country":"RU",
    "name:rus_x_preferred":[
        "\u0428\u0435\u0441\u0442\u0438\u043d\u043e"
    ],
    "name:und_x_variant":[
        "\u0428\u0435\u0441\u0442\u0438\u043d\u043e"
    ],
    "wof:name":"Shestino",
    "wof:placetype":"locality"
},
  "geometry": {"coordinates":[36.19183,56.91208],"type":"Point"}
}