{
  "type": "Feature",
  "properties": {
    "gn:admin1_code":"4",
    "gn:asciiname":"Yelbanka",
    "gn:country_code":"RU",
    "gn:dem":155,
    "gn:feature_class":"P",
    "gn:feature_code":"PPL",
    "gn:name":"Yelbanka",
    "gn:population":0,
    "gn:timezone":"Asia/Barnaul",
    "iso:country":"RU",
    "name:eng_x_preferred":[
        "Yelbanka"
    ],
    "name:nor_x_preferred":[
        "Jelbanka"
    ],
    "name:rus_x_preferred":[
        "\u0415\u043b\u0431\u0430\u043d\u043a\u0430"
    ],
    "name:und_x_variant":[
        "Yelbanskoye"
    ],
    "wof:name":"Yelbanka",
    "wof:placetype":"locality"
},
  "geometry": {"coordinates":[83.60890000000001,52.2286],"type":"Point"}
}