{
  "type": "Feature",
  "properties": {
    "gn:admin1_code":"8",
    "gn:asciiname":"Tan",
    "gn:country_code":"RU",
    "gn:dem":208,
    "gn:feature_class":"P",
    "gn:feature_code":"PPL",
    "gn:name":"Tan",
    "gn:population":0,
    "gn:timezone":"Asia/Yekaterinburg",
    "iso:country":"RU",
    "name:eng_x_preferred":[
        "Tan"
    ],
    "name:nor_x_preferred":[
        "Tan"
    ],
    "name:rus_x_preferred":[
        "\u0422\u0430\u043d"
    ],
    "name:und_x_variant":[
        "\u0422\u0430\u043d"
    ],
    "wof:name":"Tan",
    "wof:placetype":"locality"
},
  "geometry": {"coordinates":[55.002,54.8237],"type":"Point"}
}