{
  "type": "Feature",
  "properties": {
    "gn:admin1_code":"60",
    "gn:asciiname":"Goristo",
    "gn:country_code":"RU",
    "gn:dem":95,
    "gn:feature_class":"P",
    "gn:feature_code":"PPL",
    "gn:name":"Goristo",
    "gn:population":0,
    "gn:timezone":"Europe/Moscow",
    "iso:country":"RU",
    "name:rus_x_preferred":[
        "\u0413\u043e\u0440\u0438\u0441\u0442\u043e"
    ],
    "name:und_x_variant":[
        "Gorista",
        "Goristo"
    ],
    "wof:name":"Goristo",
    "wof:placetype":"locality"
},
  "geometry": {"coordinates":[29.07982,58.02526],"type":"Point"}
}