{
  "type": "Feature",
  "properties": {
    "gn:admin1_code":"76",
    "gn:asciiname":"Podosinki-Kozhino",
    "gn:country_code":"RU",
    "gn:dem":212,
    "gn:feature_class":"P",
    "gn:feature_code":"PPL",
    "gn:name":"Podosinki-Kozhino",
    "gn:population":0,
    "gn:timezone":"Europe/Moscow",
    "iso:country":"RU",
    "name:rus_x_preferred":[
        "\u041f\u043e\u0434\u043e\u0441\u0438\u043d\u043a\u0438-\u041a\u043e\u0436\u0438\u043d\u043e"
    ],
    "name:und_x_variant":[
        "Podosinki",
        "Podosinki-Kozhino",
        "\u041f\u043e\u0434\u043e\u0441\u0438\u043d\u043a\u0438-\u041a\u043e\u0436\u0438\u043d\u043e"
    ],
    "wof:name":"Podosinki-Kozhino",
    "wof:placetype":"locality"
},
  "geometry": {"coordinates":[38.53345,54.19911],"type":"Point"}
}