{
  "type": "Feature",
  "properties": {
    "gn:admin1_code":"40",
    "gn:asciiname":"Dubrovnoye",
    "gn:cc2":"RU",
    "gn:country_code":"RU",
    "gn:dem":154,
    "gn:feature_class":"P",
    "gn:feature_code":"PPL",
    "gn:name":"Dubrovnoye",
    "gn:population":0,
    "gn:timezone":"Asia/Yekaterinburg",
    "iso:country":"RU",
    "name:eng_x_preferred":[
        "Dubrovnoye"
    ],
    "name:nor_x_preferred":[
        "Dubrovnoje"
    ],
    "name:rus_x_preferred":[
        "\u0414\u0443\u0431\u0440\u043e\u0432\u043d\u043e\u0435"
    ],
    "name:und_x_variant":[
        "Dubrovskoye"
    ],
    "wof:name":"Dubrovnoye",
    "wof:placetype":"locality"
},
  "geometry": {"coordinates":[65.87166999999999,55.25694],"type":"Point"}
}