{
  "type": "Feature",
  "properties": {
    "gn:admin1_code":"8",
    "gn:asciiname":"Novyy Susadybash",
    "gn:country_code":"RU",
    "gn:dem":194,
    "gn:feature_class":"P",
    "gn:feature_code":"PPL",
    "gn:name":"Novyy Susadybash",
    "gn:population":0,
    "gn:timezone":"Asia/Yekaterinburg",
    "iso:country":"RU",
    "name:rus_x_preferred":[
        "\u041d\u043e\u0432\u044b\u0439 \u0421\u0443\u0441\u0430\u0434\u044b\u0431\u0430\u0448"
    ],
    "wof:name":"Novyy Susadybash",
    "wof:placetype":"locality"
},
  "geometry": {"coordinates":[54.8521,56.1004],"type":"Point"}
}