{
  "type": "Feature",
  "properties": {
    "gn:admin1_code":"69",
    "gn:asciiname":"Ilovnya",
    "gn:country_code":"RU",
    "gn:dem":187,
    "gn:feature_class":"P",
    "gn:feature_code":"PPL",
    "gn:name":"Ilovnya",
    "gn:population":0,
    "gn:timezone":"Europe/Moscow",
    "iso:country":"RU",
    "name:rus_x_preferred":[
        "\u0418\u043b\u043e\u0432\u043d\u044f"
    ],
    "wof:name":"Ilovnya",
    "wof:placetype":"locality"
},
  "geometry": {"coordinates":[32.26372,54.00675],"type":"Point"}
}