{
  "type": "Feature",
  "properties": {
    "gn:admin1_code":"52",
    "gn:asciiname":"Stari",
    "gn:country_code":"RU",
    "gn:dem":163,
    "gn:feature_class":"P",
    "gn:feature_code":"PPL",
    "gn:name":"Stari",
    "gn:population":0,
    "gn:timezone":"Europe/Moscow",
    "iso:country":"RU",
    "name:und_x_variant":[
        "Staroye",
        "Stari"
    ],
    "wof:name":"Stari",
    "wof:placetype":"locality"
},
  "geometry": {"coordinates":[33.09389,58.34056],"type":"Point"}
}