{
  "type": "Feature",
  "properties": {
    "gn:admin1_code":"4",
    "gn:asciiname":"Iskra",
    "gn:country_code":"RU",
    "gn:dem":152,
    "gn:feature_class":"P",
    "gn:feature_code":"PPL",
    "gn:name":"Iskra",
    "gn:population":0,
    "gn:timezone":"Asia/Barnaul",
    "iso:country":"RU",
    "name:ara_x_preferred":[
        "\u0625\u0633\u0643\u0631\u0627"
    ],
    "name:aze_x_preferred":[
        "\u0130skra"
    ],
    "name:cat_x_preferred":[
        "Iskra"
    ],
    "name:deu_x_preferred":[
        "Iskra"
    ],
    "name:ell_x_preferred":[
        "\u038a\u03c3\u03ba\u03c1\u03b1"
    ],
    "name:fin_x_preferred":[
        "Iskra"
    ],
    "name:fra_x_preferred":[
        "Iskra"
    ],
    "name:glg_x_preferred":[
        "Iskra"
    ],
    "name:heb_x_preferred":[
        "\u05d0\u05d9\u05e1\u05e7\u05e8\u05d4"
    ],
    "name:hin_x_preferred":[
        "\u0907\u0938\u094d\u0915\u094d\u0930\u093e"
    ],
    "name:hun_x_preferred":[
        "Iszkra"
    ],
    "name:hye_x_preferred":[
        "\u053b\u057d\u056f\u0580\u0561"
    ],
    "name:ind_x_preferred":[
        "Iskra"
    ],
    "name:ita_x_preferred":[
        "Iskra"
    ],
    "name:jpn_x_preferred":[
        "\u30a4\u30b9\u30af\u30e9"
    ],
    "name:nld_x_preferred":[
        "Iskra"
    ],
    "name:nor_x_preferred":[
        "Iskra"
    ],
    "name:pan_x_preferred":[
        "\u0a07\u0a38\u0a15\u0a30\u0a3e"
    ],
    "name:pnb_x_preferred":[
        "\u0627\u0650\u0633\u06a9\u0631\u0627"
    ],
    "name:pol_x_preferred":[
        "Iskra"
    ],
    "name:por_x_preferred":[
        "Iskra"
    ],
    "name:ron_x_preferred":[
        "Iskra"
    ],
    "name:rus_x_preferred":[
        "\u0418\u0441\u043a\u0440\u0430"
    ],
    "name:spa_x_preferred":[
        "Iskra"
    ],
    "name:swe_x_preferred":[
        "Iskra"
    ],
    "name:tur_x_preferred":[
        "\u0130skra"
    ],
    "name:ukr_x_preferred":[
        "\u0418\u0441\u043a\u0440\u0430"
    ],
    "name:und_x_variant":[
        "\u0418\u0441\u043a\u0440\u0430"
    ],
    "name:zho_x_preferred":[
        "\u706b\u661f\u62a5"
    ],
    "wof:name":"Iskra",
    "wof:placetype":"locality"
},
  "geometry": {"coordinates":[79.61667,53.55],"type":"Point"}
}