{
  "type": "Feature",
  "properties": {
    "gn:admin1_code":"32",
    "gn:asciiname":"Lugovoy",
    "gn:country_code":"RU",
    "gn:dem":25,
    "gn:feature_class":"P",
    "gn:feature_code":"PPL",
    "gn:name":"Lugovoy",
    "gn:population":0,
    "gn:timezone":"Asia/Yekaterinburg",
    "iso:country":"RU",
    "name:deu_x_preferred":[
        "Lugowoi"
    ],
    "name:eng_x_preferred":[
        "Lugovoy"
    ],
    "name:hye_x_preferred":[
        "\u053c\u0578\u0582\u0563\u0578\u057e\u0578\u0575"
    ],
    "name:nor_x_preferred":[
        "Lugovoje"
    ],
    "name:pol_x_preferred":[
        "\u0141ugowoj"
    ],
    "name:rus_x_preferred":[
        "\u041b\u0443\u0433\u043e\u0432\u043e\u0435"
    ],
    "name:rus_x_variant":[
        "\u041b\u0443\u0433\u043e\u0432\u043e\u0439"
    ],
    "name:ukr_x_preferred":[
        "\u041b\u0443\u0433\u043e\u0432\u0438\u0439"
    ],
    "wof:name":"Lugovoy",
    "wof:placetype":"locality"
},
  "geometry": {"coordinates":[68.46666999999999,61.06667],"type":"Point"}
}