{
  "type": "Feature",
  "properties": {
    "gn:admin1_code":"47",
    "gn:asciiname":"Maloye Kropotovo",
    "gn:country_code":"RU",
    "gn:dem":180,
    "gn:feature_class":"P",
    "gn:feature_code":"PPL",
    "gn:name":"Maloye Kropotovo",
    "gn:population":0,
    "gn:timezone":"Europe/Moscow",
    "iso:country":"RU",
    "name:rus_x_preferred":[
        "\u041c\u0430\u043b\u043e\u0435 \u041a\u0440\u043e\u043f\u043e\u0442\u043e\u0432\u043e"
    ],
    "name:und_x_variant":[
        "\u041c\u0430\u043b\u043e\u0435 \u041a\u0440\u043e\u043f\u043e\u0442\u043e\u0432\u043e"
    ],
    "wof:name":"Maloye Kropotovo",
    "wof:placetype":"locality"
},
  "geometry": {"coordinates":[38.33333,54.85],"type":"Point"}
}