{
  "type": "Feature",
  "properties": {
    "gn:admin1_code":"91",
    "gn:asciiname":"Dvinka",
    "gn:country_code":"RU",
    "gn:dem":190,
    "gn:feature_class":"P",
    "gn:feature_code":"PPL",
    "gn:name":"Dvinka",
    "gn:population":0,
    "gn:timezone":"Asia/Krasnoyarsk",
    "iso:country":"RU",
    "name:eng_x_preferred":[
        "Dvinka"
    ],
    "name:nor_x_preferred":[
        "Dvinka"
    ],
    "name:rus_x_preferred":[
        "\u0414\u0432\u0438\u043d\u043a\u0430"
    ],
    "name:und_x_variant":[
        "Dvinskiy",
        "Dvinka"
    ],
    "wof:name":"Dvinka",
    "wof:placetype":"locality"
},
  "geometry": {"coordinates":[88.97301,56.48465],"type":"Point"}
}