{
  "type": "Feature",
  "properties": {
    "gn:admin1_code":"46",
    "gn:asciiname":"Pashino",
    "gn:country_code":"RU",
    "gn:dem":220,
    "gn:feature_class":"P",
    "gn:feature_code":"PPL",
    "gn:name":"Pashino",
    "gn:population":0,
    "gn:timezone":"Europe/Moscow",
    "iso:country":"RU",
    "name:rus_x_preferred":[
        "\u041f\u0430\u0448\u0438\u043d\u043e"
    ],
    "name:und_x_variant":[
        "\u041f\u0430\u0448\u0438\u043d\u043e"
    ],
    "wof:name":"Pashino",
    "wof:placetype":"locality"
},
  "geometry": {"coordinates":[46.2346,54.5115],"type":"Point"}
}