{
  "type": "Feature",
  "properties": {
    "gn:admin1_code":"78",
    "gn:asciiname":"Lovtsovo",
    "gn:country_code":"RU",
    "gn:dem":132,
    "gn:feature_class":"P",
    "gn:feature_code":"PPL",
    "gn:name":"Lovtsovo",
    "gn:population":0,
    "gn:timezone":"Asia/Yekaterinburg",
    "iso:country":"RU",
    "name:eng_x_preferred":[
        "Lovtsovo"
    ],
    "name:nor_x_preferred":[
        "Lovtsovo"
    ],
    "name:rus_x_preferred":[
        "\u041b\u043e\u0432\u0446\u043e\u0432\u043e"
    ],
    "wof:name":"Lovtsovo",
    "wof:placetype":"locality"
},
  "geometry": {"coordinates":[70.28198,55.63626],"type":"Point"}
}