{
  "type": "Feature",
  "properties": {
    "gn:admin1_code":"4",
    "gn:asciiname":"Dobrovolets",
    "gn:country_code":"RU",
    "gn:dem":479,
    "gn:feature_class":"P",
    "gn:feature_code":"PPL",
    "gn:name":"Dobrovolets",
    "gn:population":0,
    "gn:timezone":"Asia/Barnaul",
    "iso:country":"RU",
    "name:rus_x_preferred":[
        "\u0414\u043e\u0431\u0440\u043e\u0432\u043e\u043b\u0435\u0446"
    ],
    "wof:name":"Dobrovolets",
    "wof:placetype":"locality"
},
  "geometry": {"coordinates":[82.16500000000001,50.74972],"type":"Point"}
}