{
  "type": "Feature",
  "properties": {
    "gn:admin1_code":"6",
    "gn:asciiname":"Yemen'ga",
    "gn:country_code":"RU",
    "gn:dem":162,
    "gn:feature_class":"P",
    "gn:feature_code":"PPL",
    "gn:name":"Yemen\u2019ga",
    "gn:population":0,
    "gn:timezone":"Europe/Moscow",
    "iso:country":"RU",
    "name:eng_x_preferred":[
        "Yemen'ga"
    ],
    "name:nor_x_preferred":[
        "Jemenga"
    ],
    "name:rus_x_preferred":[
        "\u0415\u043c\u0435\u043d\u044c\u0433\u0430"
    ],
    "name:und_x_variant":[
        "Yemen\u2019ga"
    ],
    "wof:name":"Yemen'ga",
    "wof:placetype":"locality"
},
  "geometry": {"coordinates":[41.2142,61.5008],"type":"Point"}
}