{
  "type": "Feature",
  "properties": {
    "gn:admin1_code":"85",
    "gn:asciiname":"Shastovo",
    "gn:country_code":"RU",
    "gn:dem":74,
    "gn:feature_class":"P",
    "gn:feature_code":"PPL",
    "gn:name":"Shastovo",
    "gn:population":0,
    "gn:timezone":"Europe/Moscow",
    "iso:country":"RU",
    "name:eng_x_preferred":[
        "Shastovo"
    ],
    "name:nor_x_preferred":[
        "Sjastovo"
    ],
    "name:rus_x_preferred":[
        "\u0428\u0430\u0441\u0442\u043e\u0432\u043e"
    ],
    "name:und_x_variant":[
        "\u0428\u0430\u0441\u0442\u043e\u0432\u043e",
        "Shastovo"
    ],
    "wof:name":"Shastovo",
    "wof:placetype":"locality"
},
  "geometry": {"coordinates":[46.56179,60.59547],"type":"Point"}
}