{
  "type": "Feature",
  "properties": {
    "gn:admin1_code":"72.0",
    "gn:asciiname":"Chicherino",
    "gn:country_code":"RU",
    "gn:dem":166,
    "gn:feature_class":"P",
    "gn:feature_code":"PPL",
    "gn:name":"Chicherino",
    "gn:population":0,
    "gn:timezone":"Europe/Moscow",
    "iso:country":"RU",
    "name:rus_x_preferred":[
        "\u0427\u0438\u0447\u0435\u0440\u0438\u043d\u043e"
    ],
    "name:und_x_variant":[
        "\u0427\u0438\u0447\u0435\u0440\u0438\u043d\u043e",
        "Chichereno"
    ],
    "wof:name":"Chicherino",
    "wof:placetype":"locality"
},
  "geometry": {"coordinates":[41.01485,52.48763],"type":"Point"}
}