{
  "type": "Feature",
  "properties": {
    "gn:admin1_code":"52.0",
    "gn:asciiname":"Bol'shiye Tal'tsy",
    "gn:country_code":"RU",
    "gn:dem":82,
    "gn:feature_class":"P",
    "gn:feature_code":"PPL",
    "gn:name":"Bol\u2019shiye Tal\u2019tsy",
    "gn:population":0,
    "gn:timezone":"Europe/Moscow",
    "iso:country":"RU",
    "name:rus_x_preferred":[
        "\u0411\u043e\u043b\u044c\u0448\u0438\u0435 \u0422\u0430\u043b\u044c\u0446\u044b"
    ],
    "name:und_x_variant":[
        "Talets",
        "Bol\u2019shoy Tal\u2019tsy",
        "Bol\u2019shoy Talets",
        "Bol\u2019shiye Tal\u2019tsy",
        "\u0411\u043e\u043b\u044c\u0448\u0438\u0435 \u0422\u0430\u043b\u044c\u0446\u044b"
    ],
    "wof:name":"Bol'shiye Tal'tsy",
    "wof:placetype":"locality"
},
  "geometry": {"coordinates":[32.99879,59.18945],"type":"Point"}
}