{
  "type": "Feature",
  "properties": {
    "gn:admin1_code":"05",
    "gn:asciiname":"Morozovka",
    "gn:country_code":"RU",
    "gn:dem":203,
    "gn:feature_class":"P",
    "gn:feature_code":"PPL",
    "gn:name":"Morozovka",
    "gn:population":0,
    "gn:timezone":"Asia/Yakutsk",
    "iso:country":"RU",
    "name:eng_x_preferred":[
        "Morozovka"
    ],
    "name:nor_x_preferred":[
        "Morozovka"
    ],
    "name:rus_x_preferred":[
        "\u041c\u043e\u0440\u043e\u0437\u043e\u0432\u043a\u0430"
    ],
    "name:und_x_variant":[
        "Morozovskiy",
        "\u041c\u043e\u0440\u043e\u0437\u043e\u0432\u043a\u0430",
        "Morozovka"
    ],
    "wof:name":"Morozovka",
    "wof:placetype":"locality"
},
  "geometry": {"coordinates":[129.21947,51.3751],"type":"Point"}
}