{
  "type": "Feature",
  "properties": {
    "gn:country":"RU",
    "gn:fcode":"PPL",
    "gn:population":13903,
    "iso:country":"RU",
    "name:ara_x_preferred":[
        "\u0641\u064a\u0631\u0643\u0646\u064a\u062f\u0646\u064a\u0628\u0631\u0648\u0641\u0633\u0643\u064a\u064a\u060c \u0633\u0645\u0648\u0644\u064a\u0646\u0633\u0643"
    ],
    "name:ara_x_variant":[
        "\u0641\u064a\u0631\u0643\u0646\u064a\u062f\u0646\u064a\u0628\u0631\u0648\u0641\u0633\u0643\u064a\u064a"
    ],
    "name:ceb_x_preferred":[
        "Verkhnedneprovskiy"
    ],
    "name:che_x_preferred":[
        "\u0412\u0435\u0440\u0445\u043d\u0435\u0434\u043d\u0435\u043f\u0440\u043e\u0432\u0441\u043a\u0438\u0439"
    ],
    "name:deu_x_preferred":[
        "Werchnedneprowski"
    ],
    "name:eng_x_preferred":[
        "Verkhnedneprovskiy"
    ],
    "name:fin_x_preferred":[
        "Verhnedneprovski"
    ],
    "name:nld_x_preferred":[
        "Verchnedneprovskiy"
    ],
    "name:nor_x_preferred":[
        "Verkhnedneprovskij"
    ],
    "name:pol_x_preferred":[
        "Wierchniednieprowskij"
    ],
    "name:rus_x_preferred":[
        "\u0412\u0435\u0440\u0445\u043d\u0435\u0434\u043d\u0435\u043f\u0440\u043e\u0432\u0441\u043a\u0438\u0439"
    ],
    "name:srp_x_preferred":[
        "\u0412\u0435\u0440\u0445\u045a\u0435\u0434\u045a\u0435\u043f\u0440\u043e\u0432\u0441\u043a\u0438"
    ],
    "name:ukr_x_preferred":[
        "\u0412\u0435\u0440\u0445\u043d\u044c\u043e\u0434\u043d\u0456\u043f\u0440\u043e\u0432\u0441\u044c\u043a\u0438\u0439"
    ],
    "qs:name":"Verkhnedneprovskiy",
    "qs:name_adm0":"Russia",
    "qs:name_adm1":"Smolensk Oblast",
    "qs:photos_9k":1,
    "qs:photos_9r":1,
    "qs:photos_all":3,
    "qs:photos_sr":0,
    "qs:placetype":"Town",
    "qs:pop_sr":"6",
    "wof:name":"Verkhnedneprovskiy",
    "wof:placetype":"locality",
    "wof:population":13903
},
  "geometry": {"coordinates":[33.34573,54.98131],"type":"Point"}
}