{
  "type": "Feature",
  "properties": {
    "gn:admin1_code":"30",
    "gn:asciiname":"Khaperka",
    "gn:country_code":"RU",
    "gn:dem":57,
    "gn:feature_class":"P",
    "gn:feature_code":"PPL",
    "gn:name":"Khap\u00ebrka",
    "gn:population":0,
    "gn:timezone":"Asia/Vladivostok",
    "iso:country":"RU",
    "name:und_x_variant":[
        "Khop\u00ebrka",
        "Khoperskoye",
        "Khopersnoye"
    ],
    "wof:name":"Khaperka",
    "wof:placetype":"locality"
},
  "geometry": {"coordinates":[135.01333,48.36139],"type":"Point"}
}