{
  "type": "Feature",
  "properties": {
    "gn:admin1_code":"8",
    "gn:asciiname":"Kalmiyabash",
    "gn:country_code":"RU",
    "gn:dem":121,
    "gn:feature_class":"P",
    "gn:feature_code":"PPL",
    "gn:name":"Kalmiyabash",
    "gn:population":0,
    "gn:timezone":"Asia/Yekaterinburg",
    "iso:country":"RU",
    "name:eng_x_preferred":[
        "Kalmiyabash"
    ],
    "name:nor_x_preferred":[
        "Kalmijabasj"
    ],
    "name:rus_x_preferred":[
        "\u041a\u0430\u043b\u043c\u0438\u044f\u0431\u0430\u0448"
    ],
    "name:und_x_variant":[
        "\u041a\u0430\u043b\u043c\u0438\u044f\u0431\u0430\u0448",
        "Kalmiyabash"
    ],
    "wof:name":"Kalmiyabash",
    "wof:placetype":"locality"
},
  "geometry": {"coordinates":[54.93611,55.89673000000001],"type":"Point"}
}