{
  "type": "Feature",
  "properties": {
    "gn:admin1_code":"33.0",
    "gn:asciiname":"Suyevalovy",
    "gn:country_code":"RU",
    "gn:dem":148,
    "gn:feature_class":"P",
    "gn:feature_code":"PPL",
    "gn:name":"Suyevalovy",
    "gn:population":0,
    "gn:timezone":"Europe/Kirov",
    "iso:country":"RU",
    "name:rus_x_preferred":[
        "\u0421\u0443\u0435\u0432\u0430\u043b\u043e\u0432\u044b"
    ],
    "name:und_x_variant":[
        "Suyevalovo",
        "Suyevalovy"
    ],
    "wof:name":"Suyevalovy",
    "wof:placetype":"locality"
},
  "geometry": {"coordinates":[48.0273,58.81688000000001],"type":"Point"}
}