{
  "type": "Feature",
  "properties": {
    "gn:admin1_code":"69",
    "gn:asciiname":"Klokovo",
    "gn:country_code":"RU",
    "gn:dem":223,
    "gn:feature_class":"P",
    "gn:feature_code":"PPL",
    "gn:name":"Klokovo",
    "gn:population":0,
    "gn:timezone":"Europe/Moscow",
    "iso:country":"RU",
    "name:fas_x_preferred":[
        "\u06a9\u0644\u0648\u06a9\u0641"
    ],
    "name:rus_x_preferred":[
        "\u041a\u043b\u043e\u043a\u043e\u0432\u043e"
    ],
    "wof:name":"Klokovo",
    "wof:placetype":"locality"
},
  "geometry": {"coordinates":[32.84026,54.66576],"type":"Point"}
}