{
  "type": "Feature",
  "properties": {
    "gn:admin1_code":"61",
    "gn:asciiname":"Koltykanov",
    "gn:country_code":"RU",
    "gn:dem":52,
    "gn:feature_class":"P",
    "gn:feature_code":"PPL",
    "gn:name":"Koltykanov",
    "gn:population":0,
    "gn:timezone":"Europe/Moscow",
    "iso:country":"RU",
    "name:rus_x_preferred":[
        "\u041a\u043e\u043b\u0442\u044b\u043a\u0430\u043d\u043e\u0432"
    ],
    "wof:name":"Koltykanov",
    "wof:placetype":"locality"
},
  "geometry": {"coordinates":[43.11667,47.06667],"type":"Point"}
}