{
  "type": "Feature",
  "properties": {
    "gn:admin1_code":"40",
    "gn:asciiname":"Sorokino",
    "gn:country_code":"RU",
    "gn:dem":134,
    "gn:feature_class":"P",
    "gn:feature_code":"PPL",
    "gn:name":"Sorokino",
    "gn:population":0,
    "gn:timezone":"Asia/Yekaterinburg",
    "iso:country":"RU",
    "name:rus_x_preferred":[
        "\u0421\u043e\u0440\u043e\u043a\u0438\u043d\u043e"
    ],
    "wof:name":"Sorokino",
    "wof:placetype":"locality"
},
  "geometry": {"coordinates":[64.20583000000001,54.95639],"type":"Point"}
}