{
  "type": "Feature",
  "properties": {
    "gn:admin1_code":"77",
    "gn:asciiname":"Maloye Korobino",
    "gn:country_code":"RU",
    "gn:dem":195,
    "gn:feature_class":"P",
    "gn:feature_code":"PPL",
    "gn:name":"Maloye Korobino",
    "gn:population":0,
    "gn:timezone":"Europe/Moscow",
    "iso:country":"RU",
    "name:rus_x_preferred":[
        "\u041c\u0430\u043b\u043e\u0435 \u041a\u043e\u0440\u043e\u0431\u0438\u043d\u043e"
    ],
    "wof:name":"Maloye Korobino",
    "wof:placetype":"locality"
},
  "geometry": {"coordinates":[34.57680999999999,56.11774000000001],"type":"Point"}
}