{
  "type": "Feature",
  "properties": {
    "gn:admin1_code":"52",
    "gn:asciiname":"Komel'",
    "gn:country_code":"RU",
    "gn:dem":131,
    "gn:feature_class":"P",
    "gn:feature_code":"PPL",
    "gn:name":"Komel\u2019",
    "gn:population":0,
    "gn:timezone":"Europe/Moscow",
    "iso:country":"RU",
    "name:rus_x_preferred":[
        "\u041a\u043e\u043c\u0435\u043b\u044c"
    ],
    "name:und_x_variant":[
        "Komel\u2019"
    ],
    "wof:name":"Komel'",
    "wof:placetype":"locality"
},
  "geometry": {"coordinates":[32.91725,58.73794],"type":"Point"}
}