{
  "type": "Feature",
  "properties": {
    "gn:admin1_code":"34.0",
    "gn:asciiname":"Filippovo",
    "gn:country_code":"RU",
    "gn:dem":43,
    "gn:feature_class":"P",
    "gn:feature_code":"PPL",
    "gn:name":"Filippovo",
    "gn:population":0,
    "gn:timezone":"Europe/Moscow",
    "iso:country":"RU",
    "name:eng_x_preferred":[
        "Filippovo"
    ],
    "name:nor_x_preferred":[
        "Filippovo"
    ],
    "name:rus_x_preferred":[
        "\u0424\u0438\u043b\u0438\u043f\u043f\u043e\u0432\u043e"
    ],
    "wof:name":"Filippovo",
    "wof:placetype":"locality"
},
  "geometry": {"coordinates":[51.10369,65.435],"type":"Point"}
}