{
  "type": "Feature",
  "properties": {
    "gn:admin1_code":"41",
    "gn:asciiname":"Ryzhevka",
    "gn:country_code":"RU",
    "gn:dem":157,
    "gn:feature_class":"P",
    "gn:feature_code":"PPL",
    "gn:name":"Ryzhevka",
    "gn:population":0,
    "gn:timezone":"Europe/Moscow",
    "iso:country":"RU",
    "name:rus_x_preferred":[
        "\u0420\u044b\u0436\u0435\u0432\u043a\u0430"
    ],
    "name:und_x_variant":[
        "Ryzhovka",
        "Ryzhevka",
        "\u0420\u044b\u0436\u0435\u0432\u043a\u0430"
    ],
    "wof:name":"Ryzhevka",
    "wof:placetype":"locality"
},
  "geometry": {"coordinates":[34.3126,51.6491],"type":"Point"}
}