{
  "type": "Feature",
  "properties": {
    "gn:admin1_code":"88.0",
    "gn:asciiname":"Abramovo",
    "gn:country_code":"RU",
    "gn:dem":134,
    "gn:feature_class":"P",
    "gn:feature_code":"PPL",
    "gn:name":"Abramovo",
    "gn:population":0,
    "gn:timezone":"Europe/Moscow",
    "iso:country":"RU",
    "name:nor_x_preferred":[
        "Abramovo"
    ],
    "name:rus_x_preferred":[
        "\u0410\u0431\u0440\u0430\u043c\u043e\u0432\u043e"
    ],
    "wof:name":"Abramovo",
    "wof:placetype":"locality"
},
  "geometry": {"coordinates":[40.37502,58.04711],"type":"Point"}
}