{
  "type": "Feature",
  "properties": {
    "gn:admin1_code":"8",
    "gn:asciiname":"Sarlak",
    "gn:country_code":"RU",
    "gn:dem":187,
    "gn:feature_class":"P",
    "gn:feature_code":"PPL",
    "gn:name":"Sarlak",
    "gn:population":0,
    "gn:timezone":"Asia/Yekaterinburg",
    "iso:country":"RU",
    "name:ara_x_preferred":[
        "\u0633\u0631\u0644\u0643"
    ],
    "name:ceb_x_preferred":[
        "Sarlak"
    ],
    "name:fas_x_preferred":[
        "\u0633\u0631\u0644\u06a9"
    ],
    "name:rus_x_preferred":[
        "\u0421\u0430\u0440\u043b\u0430\u043a"
    ],
    "name:swe_x_preferred":[
        "Sarlak"
    ],
    "wof:name":"Sarlak",
    "wof:placetype":"locality"
},
  "geometry": {"coordinates":[55.9242,52.9972],"type":"Point"}
}