{
  "type": "Feature",
  "properties": {
    "gn:admin1_code":"51",
    "gn:asciiname":"Markusha",
    "gn:country_code":"RU",
    "gn:dem":133,
    "gn:feature_class":"P",
    "gn:feature_code":"PPL",
    "gn:name":"Markusha",
    "gn:population":0,
    "gn:timezone":"Europe/Moscow",
    "iso:country":"RU",
    "name:rus_x_preferred":[
        "\u041c\u0430\u0440\u043a\u0443\u0448\u0430"
    ],
    "name:und_x_variant":[
        "\u041c\u0430\u0440\u043a\u0443\u0448\u0430"
    ],
    "wof:name":"Markusha",
    "wof:placetype":"locality"
},
  "geometry": {"coordinates":[45.8603,57.8725],"type":"Point"}
}