{
  "type": "Feature",
  "properties": {
    "gn:admin1_code":"47",
    "gn:asciiname":"Krekhtino",
    "gn:country_code":"RU",
    "gn:dem":136,
    "gn:feature_class":"P",
    "gn:feature_code":"PPL",
    "gn:name":"Krekhtino",
    "gn:population":0,
    "gn:timezone":"Europe/Moscow",
    "iso:country":"RU",
    "name:rus_x_preferred":[
        "\u041a\u0440\u0435\u0445\u0442\u0438\u043d\u043e"
    ],
    "wof:name":"Krekhtino",
    "wof:placetype":"locality"
},
  "geometry": {"coordinates":[39.42149000000001,55.27506],"type":"Point"}
}