{
  "type": "Feature",
  "properties": {
    "gn:admin1_code":"60",
    "gn:asciiname":"Chernicheno",
    "gn:country_code":"RU",
    "gn:dem":205,
    "gn:feature_class":"P",
    "gn:feature_code":"PPL",
    "gn:name":"Chernicheno",
    "gn:population":0,
    "gn:timezone":"Europe/Moscow",
    "iso:country":"RU",
    "name:rus_x_preferred":[
        "\u0427\u0435\u0440\u043d\u0438\u0447\u0435\u043d\u043e"
    ],
    "name:und_x_variant":[
        "\u0427\u0435\u0440\u043d\u0438\u0447\u0435\u043d\u043e"
    ],
    "wof:name":"Chernicheno",
    "wof:placetype":"locality"
},
  "geometry": {"coordinates":[29.8936,56.339],"type":"Point"}
}