{
  "type": "Feature",
  "properties": {
    "gn:country":"RU",
    "gn:fcode":"PPL",
    "gn:pop":9712,
    "iso:country":"RU",
    "name:eng_x_preferred":[
        "Shatki"
    ],
    "name:nor_x_preferred":[
        "Sjatki"
    ],
    "name:rus_x_preferred":[
        "\u0428\u0430\u0442\u043a\u0438"
    ],
    "name:unk_x_variant":[
        "\u0428\u0430\u0442\u043a\u0438"
    ],
    "qs:name":"Shatki",
    "qs:photos_9r":0,
    "qs:photos_sr":0,
    "qs:pop_sr":"5",
    "wd:wordcount":45,
    "wof:name":"Shatki",
    "wof:placetype":"locality",
    "wof:population":9712
},
  "geometry": {"coordinates":[44.12486,55.18874],"type":"Point"}
}