{
  "type": "Feature",
  "properties": {
    "gn:admin1_code":"90.0",
    "gn:asciiname":"Zelenyata",
    "gn:country_code":"RU",
    "gn:dem":114,
    "gn:feature_class":"P",
    "gn:feature_code":"PPL",
    "gn:name":"Zelenyata",
    "gn:population":0,
    "gn:timezone":"Asia/Yekaterinburg",
    "iso:country":"RU",
    "name:rus_x_preferred":[
        "\u0417\u0435\u043b\u0435\u043d\u044f\u0442\u0430"
    ],
    "wof:name":"Zelenyata",
    "wof:placetype":"locality"
},
  "geometry": {"coordinates":[55.0183,58.0171],"type":"Point"}
}