{
  "type": "Feature",
  "properties": {
    "gn:admin1_code":"77",
    "gn:asciiname":"Yazovitsy",
    "gn:country_code":"RU",
    "gn:dem":184,
    "gn:feature_class":"P",
    "gn:feature_code":"PPL",
    "gn:name":"Yazovitsy",
    "gn:population":0,
    "gn:timezone":"Europe/Moscow",
    "iso:country":"RU",
    "name:rus_x_preferred":[
        "\u042f\u0437\u043e\u0432\u0438\u0446\u044b"
    ],
    "wof:name":"Yazovitsy",
    "wof:placetype":"locality"
},
  "geometry": {"coordinates":[35.24438,58.206],"type":"Point"}
}