{
  "type": "Feature",
  "properties": {
    "gn:admin1_code":"84.0",
    "gn:asciiname":"Buyeratskiy",
    "gn:country_code":"RU",
    "gn:dem":96,
    "gn:feature_class":"P",
    "gn:feature_code":"PPL",
    "gn:name":"Buyeratskiy",
    "gn:population":0,
    "gn:timezone":"Europe/Volgograd",
    "iso:country":"RU",
    "name:rus_x_preferred":[
        "\u0411\u0443\u0435\u0440\u0430\u0442\u0441\u043a\u0438\u0439"
    ],
    "wof:name":"Buyeratskiy",
    "wof:placetype":"locality"
},
  "geometry": {"coordinates":[42.96667,49.88333],"type":"Point"}
}