{
  "type": "Feature",
  "properties": {
    "gn:admin1_code":"77",
    "gn:asciiname":"Kozhuritsa",
    "gn:country_code":"RU",
    "gn:dem":211,
    "gn:feature_class":"P",
    "gn:feature_code":"PPL",
    "gn:name":"Kozhuritsa",
    "gn:population":0,
    "gn:timezone":"Europe/Moscow",
    "iso:country":"RU",
    "name:rus_x_preferred":[
        "\u041a\u043e\u0436\u0443\u0440\u0438\u0446\u0430"
    ],
    "wof:name":"Kozhuritsa",
    "wof:placetype":"locality"
},
  "geometry": {"coordinates":[32.6191,57.15584000000001],"type":"Point"}
}