{
  "type": "Feature",
  "properties": {
    "gn:admin1_code":"91",
    "gn:asciiname":"Ul'ye",
    "gn:country_code":"RU",
    "gn:dem":465,
    "gn:feature_class":"P",
    "gn:feature_code":"PPL",
    "gn:name":"Ul\u2019ye",
    "gn:population":0,
    "gn:timezone":"Asia/Krasnoyarsk",
    "iso:country":"RU",
    "wof:name":"Ul'ye",
    "wof:placetype":"locality"
},
  "geometry": {"coordinates":[95.09999999999999,54.95],"type":"Point"}
}