{
  "type": "Feature",
  "properties": {
    "gn:admin1_code":"77.0",
    "gn:asciiname":"Bezgachevo",
    "gn:country_code":"RU",
    "gn:dem":204,
    "gn:feature_class":"P",
    "gn:feature_code":"PPL",
    "gn:name":"Bezgachevo",
    "gn:population":0,
    "gn:timezone":"Europe/Moscow",
    "iso:country":"RU",
    "name:nor_x_preferred":[
        "Bezgatsjevo"
    ],
    "name:rus_x_preferred":[
        "\u0411\u0435\u0437\u0433\u0430\u0447\u0435\u0432\u043e"
    ],
    "name:und_x_variant":[
        "Bezgacheva",
        "Bezgachevo"
    ],
    "wof:name":"Bezgachevo",
    "wof:placetype":"locality"
},
  "geometry": {"coordinates":[34.52863,56.26564000000001],"type":"Point"}
}