{
  "type": "Feature",
  "properties": {
    "gn:admin1_code":"85",
    "gn:asciiname":"Murdinskaya",
    "gn:country_code":"RU",
    "gn:dem":126,
    "gn:feature_class":"P",
    "gn:feature_code":"PPL",
    "gn:name":"Murdinskaya",
    "gn:population":0,
    "gn:timezone":"Europe/Moscow",
    "iso:country":"RU",
    "name:rus_x_preferred":[
        "\u041c\u0443\u0440\u0434\u0438\u043d\u0441\u043a\u0430\u044f"
    ],
    "name:und_x_variant":[
        "\u041c\u0443\u0440\u0434\u0438\u043d\u0441\u043a\u0430\u044f"
    ],
    "wof:name":"Murdinskaya",
    "wof:placetype":"locality"
},
  "geometry": {"coordinates":[46.3124,60.407],"type":"Point"}
}