{
  "type": "Feature",
  "properties": {
    "gn:admin1_code":"60.0",
    "gn:asciiname":"Arestovo",
    "gn:country_code":"RU",
    "gn:dem":166,
    "gn:feature_class":"P",
    "gn:feature_code":"PPL",
    "gn:name":"Arestovo",
    "gn:population":0,
    "gn:timezone":"Europe/Moscow",
    "iso:country":"RU",
    "name:nor_x_preferred":[
        "Arestovo"
    ],
    "name:rus_x_preferred":[
        "\u0410\u0440\u0435\u0441\u0442\u043e\u0432\u043e"
    ],
    "wof:name":"Arestovo",
    "wof:placetype":"locality"
},
  "geometry": {"coordinates":[31.26667,56.15],"type":"Point"}
}