{
  "type": "Feature",
  "properties": {
    "gn:admin1_code":"38",
    "gn:asciiname":"Paskhatidi",
    "gn:country_code":"RU",
    "gn:dem":289,
    "gn:feature_class":"P",
    "gn:feature_code":"PPL",
    "gn:name":"Paskhatidi",
    "gn:population":0,
    "gn:timezone":"Europe/Moscow",
    "iso:country":"RU",
    "name:rus_x_preferred":[
        "\u041f\u0430\u0441\u0445\u0430\u0442\u0438\u0434\u0438"
    ],
    "wof:name":"Paskhatidi",
    "wof:placetype":"locality"
},
  "geometry": {"coordinates":[38.53333,44.45],"type":"Point"}
}