{
  "type": "Feature",
  "properties": {
    "gn:admin1_code":"88",
    "gn:asciiname":"Kharapushki",
    "gn:country_code":"RU",
    "gn:dem":121,
    "gn:feature_class":"P",
    "gn:feature_code":"PPL",
    "gn:name":"Kharapushki",
    "gn:population":0,
    "gn:timezone":"Europe/Moscow",
    "iso:country":"RU",
    "name:rus_x_preferred":[
        "\u0425\u0430\u0440\u0430\u043f\u0443\u0448\u043a\u0438"
    ],
    "wof:name":"Kharapushki",
    "wof:placetype":"locality"
},
  "geometry": {"coordinates":[38.2064,57.5245],"type":"Point"}
}