{
  "type": "Feature",
  "properties": {
    "gn:admin1_code":"59.0",
    "gn:asciiname":"Lastochka",
    "gn:country_code":"RU",
    "gn:dem":78,
    "gn:feature_class":"P",
    "gn:feature_code":"PPL",
    "gn:name":"Lastochka",
    "gn:population":0,
    "gn:timezone":"Asia/Vladivostok",
    "iso:country":"RU",
    "name:bel_x_preferred":[
        "\u041b\u0430\u0441\u0442\u0430\u045e\u043a\u0430"
    ],
    "name:epo_x_preferred":[
        "Lasto\u0109ka"
    ],
    "name:hun_x_preferred":[
        "Lasztocska"
    ],
    "name:jpn_x_preferred":[
        "\u30e9\u30fc\u30b9\u30bf\u30c1\u30ab"
    ],
    "name:nor_x_preferred":[
        "Lastotsjka"
    ],
    "name:rus_x_preferred":[
        "\u041b\u0430\u0441\u0442\u043e\u0447\u043a\u0430"
    ],
    "wof:name":"Lastochka",
    "wof:placetype":"locality"
},
  "geometry": {"coordinates":[134.12112999999999,46.39775],"type":"Point"}
}