{
  "type": "Feature",
  "properties": {
    "gn:admin1_code":"60",
    "gn:asciiname":"Belokhrebtovo",
    "gn:country_code":"RU",
    "gn:dem":183,
    "gn:feature_class":"P",
    "gn:feature_code":"PPL",
    "gn:name":"Belokhrebtovo",
    "gn:population":0,
    "gn:timezone":"Europe/Moscow",
    "iso:country":"RU",
    "name:rus_x_preferred":[
        "\u0411\u0435\u043b\u043e\u0445\u0440\u0435\u0431\u0442\u043e\u0432\u043e"
    ],
    "wof:name":"Belokhrebtovo",
    "wof:placetype":"locality"
},
  "geometry": {"coordinates":[29.1349,56.6882],"type":"Point"}
}