{
  "type": "Feature",
  "properties": {
    "gn:admin1_code":"77",
    "gn:asciiname":"Yelmanova-Gorka",
    "gn:cc2":"RU",
    "gn:country_code":"RU",
    "gn:dem":165,
    "gn:feature_class":"P",
    "gn:feature_code":"PPL",
    "gn:name":"Yelmanova-Gorka",
    "gn:population":0,
    "gn:timezone":"Europe/Moscow",
    "iso:country":"RU",
    "name:und_x_variant":[
        "Gelmanova Gorka",
        "Yelmanova-Gorka"
    ],
    "wof:name":"Yelmanova-Gorka",
    "wof:placetype":"locality"
},
  "geometry": {"coordinates":[34.9775,57.83528],"type":"Point"}
}