{
  "type": "Feature",
  "properties": {
    "gn:admin1_code":"4.0",
    "gn:asciiname":"Ikonnikovo",
    "gn:country_code":"RU",
    "gn:dem":165,
    "gn:feature_class":"P",
    "gn:feature_code":"PPL",
    "gn:name":"Ikonnikovo",
    "gn:population":75,
    "gn:timezone":"Asia/Barnaul",
    "iso:country":"RU",
    "wof:name":"Ikonnikovo",
    "wof:placetype":"locality",
    "wof:population":75
},
  "geometry": {"coordinates":[85.09215,52.43193],"type":"Point"}
}