{
  "type": "Feature",
  "properties": {
    "gn:admin1_code":"90.0",
    "gn:asciiname":"Chernaya",
    "gn:country_code":"RU",
    "gn:dem":119,
    "gn:feature_class":"P",
    "gn:feature_code":"PPL",
    "gn:name":"Ch\u00ebrnaya",
    "gn:population":0,
    "gn:timezone":"Asia/Yekaterinburg",
    "iso:country":"RU",
    "name:rus_x_preferred":[
        "\u0427\u0451\u0440\u043d\u0430\u044f"
    ],
    "name:und_x_variant":[
        "Ch\u00ebrnaya",
        "\u0427\u0451\u0440\u043d\u0430\u044f"
    ],
    "wof:name":"Chernaya",
    "wof:placetype":"locality"
},
  "geometry": {"coordinates":[55.7359,58.1404],"type":"Point"}
}