{
  "type": "Feature",
  "properties": {
    "gn:admin1_code":"56",
    "gn:asciiname":"Aseyeva",
    "gn:country_code":"RU",
    "gn:dem":201,
    "gn:feature_class":"P",
    "gn:feature_code":"PPL",
    "gn:name":"Aseyeva",
    "gn:population":0,
    "gn:timezone":"Europe/Moscow",
    "iso:country":"RU",
    "name:nor_x_preferred":[
        "Asejeva"
    ],
    "name:rus_x_preferred":[
        "\u0410\u0441\u0435\u0435\u0432\u0430"
    ],
    "name:und_x_variant":[
        "Aseyevo",
        "Aseyeva"
    ],
    "wof:name":"Aseyeva",
    "wof:placetype":"locality"
},
  "geometry": {"coordinates":[35.81930999999999,53.47857],"type":"Point"}
}