{
  "type": "Feature",
  "properties": {
    "gn:admin1_code":"37",
    "gn:asciiname":"Prudovka",
    "gn:country_code":"RU",
    "gn:dem":144,
    "gn:feature_class":"P",
    "gn:feature_code":"PPL",
    "gn:name":"Prudovka",
    "gn:population":0,
    "gn:timezone":"Europe/Moscow",
    "iso:country":"RU",
    "name:rus_x_preferred":[
        "\u041f\u0440\u0443\u0434\u043e\u0432\u043a\u0430"
    ],
    "name:und_x_variant":[
        "\u041f\u0440\u0443\u0434\u043e\u0432\u043a\u0430"
    ],
    "wof:name":"Prudovka",
    "wof:placetype":"locality"
},
  "geometry": {"coordinates":[45.6121,58.0262],"type":"Point"}
}