{
  "type": "Feature",
  "properties": {
    "gn:admin1_code":"52",
    "gn:asciiname":"Sutoka",
    "gn:country_code":"RU",
    "gn:dem":84,
    "gn:feature_class":"P",
    "gn:feature_code":"PPL",
    "gn:name":"Sutoka",
    "gn:population":0,
    "gn:timezone":"Europe/Moscow",
    "iso:country":"RU",
    "name:und_x_variant":[
        "Sutoki",
        "Sutoka"
    ],
    "wof:name":"Sutoka",
    "wof:placetype":"locality"
},
  "geometry": {"coordinates":[33.14806,58.72778],"type":"Point"}
}