{
  "type": "Feature",
  "properties": {
    "gn:admin1_code":"93",
    "gn:asciiname":"Verkhniy Tergen'",
    "gn:country_code":"RU",
    "gn:dem":658,
    "gn:feature_class":"P",
    "gn:feature_code":"PPL",
    "gn:name":"Verkhniy Tergen\u2019",
    "gn:population":0,
    "gn:timezone":"Asia/Chita",
    "iso:country":"RU",
    "name:eng_x_preferred":[
        "Verkhniy Tergen'"
    ],
    "name:nor_x_preferred":[
        "Verkh.Tergen"
    ],
    "name:rus_x_preferred":[
        "\u0412\u0435\u0440\u0445.\u0422\u0435\u0440\u0433\u0435\u043d\u044c"
    ],
    "name:rus_x_variant":[
        "\u0412\u0435\u0440\u0445\u043d\u0438\u0439 \u0422\u0435\u0440\u0433\u0435\u043d\u044c"
    ],
    "name:und_x_variant":[
        "Verkhneye Terch\u2019ye",
        "Verkhne Terch\u2019ye",
        "Verkhniy Tergen\u2019"
    ],
    "wof:name":"Verkhniy Tergen'",
    "wof:placetype":"locality"
},
  "geometry": {"coordinates":[117.35232999999999,51.7369],"type":"Point"}
}