{
  "type": "Feature",
  "properties": {
    "gn:admin1_code":"91",
    "gn:asciiname":"Moskovka",
    "gn:country_code":"RU",
    "gn:dem":348,
    "gn:feature_class":"P",
    "gn:feature_code":"PPL",
    "gn:name":"Moskovka",
    "gn:population":0,
    "gn:timezone":"Asia/Krasnoyarsk",
    "iso:country":"RU",
    "name:eng_x_preferred":[
        "Moskovka"
    ],
    "name:nor_x_preferred":[
        "Moskovka"
    ],
    "name:rus_x_preferred":[
        "\u041c\u043e\u0441\u043a\u043e\u0432\u043a\u0430"
    ],
    "wof:name":"Moskovka",
    "wof:placetype":"locality"
},
  "geometry": {"coordinates":[90.57917,55.63139],"type":"Point"}
}