{
  "type": "Feature",
  "properties": {
    "gn:admin1_code":"6.0",
    "gn:asciiname":"Lysitsa",
    "gn:country_code":"RU",
    "gn:dem":10,
    "gn:feature_class":"P",
    "gn:feature_code":"PPL",
    "gn:name":"Lysitsa",
    "gn:population":0,
    "gn:timezone":"Europe/Moscow",
    "iso:country":"RU",
    "name:rus_x_preferred":[
        "\u041b\u044b\u0441\u0438\u0446\u0430"
    ],
    "wof:name":"Lysitsa",
    "wof:placetype":"locality"
},
  "geometry": {"coordinates":[41.7651,63.5945],"type":"Point"}
}