{
  "type": "Feature",
  "properties": {
    "gn:country":"RU",
    "gn:fcode":"PPL",
    "gn:pop":0,
    "iso:country":"RU",
    "name:rus_x_preferred":[
        "\u0422\u0438\u043c\u043e\u043d\u0438\u043d\u043e"
    ],
    "name:unk_x_variant":[
        "\u0422\u0438\u043c\u043e\u043d\u0438\u043d\u043e"
    ],
    "qs:name":"Timonino",
    "qs:name_adm0":"Russia",
    "qs:name_adm1":"Moscow Oblast",
    "qs:photos_9k":1,
    "qs:photos_9r":1,
    "qs:photos_all":1,
    "qs:photos_sr":0,
    "qs:placetype":"Town",
    "qs:pop_sr":"0",
    "wof:name":"Timonino",
    "wof:placetype":"locality",
    "wof:population":0
},
  "geometry": {"coordinates":[36.5869,56.3326],"type":"Point"}
}