{
  "type": "Feature",
  "properties": {
    "gn:admin1_code":"78",
    "gn:asciiname":"Teterkino",
    "gn:country_code":"RU",
    "gn:dem":136,
    "gn:feature_class":"P",
    "gn:feature_code":"PPL",
    "gn:name":"Tet\u00ebrkino",
    "gn:population":0,
    "gn:timezone":"Asia/Yekaterinburg",
    "iso:country":"RU",
    "name:eng_x_preferred":[
        "Tet\u00ebrkino"
    ],
    "name:nor_x_preferred":[
        "Teterkina"
    ],
    "name:rus_x_preferred":[
        "\u0422\u0435\u0442\u0435\u0440\u043a\u0438\u043d\u0430"
    ],
    "name:und_x_variant":[
        "Tet\u00ebrkino"
    ],
    "wof:name":"Teterkino",
    "wof:placetype":"locality"
},
  "geometry": {"coordinates":[67.63934,56.17215],"type":"Point"}
}