{
  "type": "Feature",
  "properties": {
    "gn:admin1_code":"33",
    "gn:asciiname":"Yushki",
    "gn:country_code":"RU",
    "gn:dem":123,
    "gn:feature_class":"P",
    "gn:feature_code":"PPL",
    "gn:name":"Yushki",
    "gn:population":0,
    "gn:timezone":"Europe/Kirov",
    "iso:country":"RU",
    "name:rus_x_preferred":[
        "\u042e\u0448\u043a\u0438"
    ],
    "wof:name":"Yushki",
    "wof:placetype":"locality"
},
  "geometry": {"coordinates":[50.45498,57.69911999999999],"type":"Point"}
}