{
  "type": "Feature",
  "properties": {
    "gn:admin1_code":"83.0",
    "gn:asciiname":"Ruchkino",
    "gn:country_code":"RU",
    "gn:dem":94,
    "gn:feature_class":"P",
    "gn:feature_code":"PPL",
    "gn:name":"Ruchkino",
    "gn:population":0,
    "gn:timezone":"Europe/Moscow",
    "iso:country":"RU",
    "name:rus_x_preferred":[
        "\u0420\u0443\u0447\u043a\u0438\u043d\u043e"
    ],
    "wof:name":"Ruchkino",
    "wof:placetype":"locality"
},
  "geometry": {"coordinates":[41.03718,56.47156999999999],"type":"Point"}
}