{
  "type": "Feature",
  "properties": {
    "gn:admin1_code":"89",
    "gn:asciiname":"Sagdy-Bira",
    "gn:country_code":"RU",
    "gn:dem":122,
    "gn:feature_class":"P",
    "gn:feature_code":"PPL",
    "gn:name":"Sagdy-Bira",
    "gn:population":0,
    "gn:timezone":"Asia/Vladivostok",
    "iso:country":"RU",
    "name:eng_x_preferred":[
        "Sagdy-Bira"
    ],
    "name:nor_x_preferred":[
        "Sagdy-Bira"
    ],
    "name:rus_x_preferred":[
        "\u0421\u0430\u0433\u0434\u044b-\u0411\u0438\u0440\u0430"
    ],
    "wof:name":"Sagdy-Bira",
    "wof:placetype":"locality"
},
  "geometry": {"coordinates":[132.66493,48.92952],"type":"Point"}
}