{
  "type": "Feature",
  "properties": {
    "gn:admin1_code":"31",
    "gn:asciiname":"Shipilinsk",
    "gn:country_code":"RU",
    "gn:dem":1162,
    "gn:feature_class":"P",
    "gn:feature_code":"PPL",
    "gn:name":"Shipilinsk",
    "gn:population":0,
    "gn:timezone":"Asia/Krasnoyarsk",
    "iso:country":"RU",
    "name:eng_x_preferred":[
        "Shipilinsk"
    ],
    "name:nor_x_preferred":[
        "Sjipilinsk"
    ],
    "name:rus_x_preferred":[
        "\u0428\u0438\u043f\u0438\u043b\u0438\u043d\u0441\u043a"
    ],
    "wof:name":"Shipilinsk",
    "wof:placetype":"locality"
},
  "geometry": {"coordinates":[89.21666999999999,54.36666999999999],"type":"Point"}
}