{
  "type": "Feature",
  "properties": {
    "gn:admin1_code":"16",
    "gn:asciiname":"Sovkhoznyy",
    "gn:country_code":"RU",
    "gn:dem":166,
    "gn:feature_class":"P",
    "gn:feature_code":"PPL",
    "gn:name":"Sovkhoznyy",
    "gn:population":0,
    "gn:timezone":"Europe/Moscow",
    "iso:country":"RU",
    "name:rus_x_preferred":[
        "\u0421\u043e\u0432\u0445\u043e\u0437\u043d\u044b\u0439"
    ],
    "name:und_x_variant":[
        "\u0421\u043e\u0432\u0445\u043e\u0437\u043d\u044b\u0439"
    ],
    "wof:name":"Sovkhoznyy",
    "wof:placetype":"locality"
},
  "geometry": {"coordinates":[46.2805,56.0415],"type":"Point"}
}