{
  "type": "Feature",
  "properties": {
    "gn:admin1_code":"52",
    "gn:asciiname":"Legot Malyy",
    "gn:country_code":"RU",
    "gn:dem":82,
    "gn:feature_class":"P",
    "gn:feature_code":"PPL",
    "gn:name":"Legot Malyy",
    "gn:population":0,
    "gn:timezone":"Europe/Moscow",
    "iso:country":"RU",
    "name:rus_x_preferred":[
        "\u041b\u0435\u0433\u043e\u0442 \u041c\u0430\u043b\u044b\u0439"
    ],
    "name:und_x_variant":[
        "\u041b\u0435\u0433\u043e\u0442 \u041c\u0430\u043b\u044b\u0439"
    ],
    "wof:name":"Legot Malyy",
    "wof:placetype":"locality"
},
  "geometry": {"coordinates":[30.76667,56.91667],"type":"Point"}
}