{
  "type": "Feature",
  "properties": {
    "gn:admin1_code":"53",
    "gn:asciiname":"Nizhnyaya Matrenka",
    "gn:country_code":"RU",
    "gn:dem":314,
    "gn:feature_class":"P",
    "gn:feature_code":"PPL",
    "gn:name":"Nizhnyaya Matr\u00ebnka",
    "gn:population":0,
    "gn:timezone":"Asia/Novosibirsk",
    "iso:country":"RU",
    "name:rus_x_preferred":[
        "\u041d\u0438\u0436\u043d\u044f\u044f \u041c\u0430\u0442\u0440\u0451\u043d\u043a\u0430"
    ],
    "name:rus_x_variant":[
        "\u041d\u0438\u0436\u043d\u044f\u044f \u041c\u0430\u0442\u0440\u0435\u043d\u043a\u0430"
    ],
    "name:und_x_variant":[
        "Nizhnyaya Matr\u00ebnka",
        "\u041d\u0438\u0436\u043d\u044f\u044f \u041c\u0430\u0442\u0440\u0451\u043d\u043a\u0430"
    ],
    "wof:name":"Nizhnyaya Matrenka",
    "wof:placetype":"locality"
},
  "geometry": {"coordinates":[84.76416999999999,54.46333000000001],"type":"Point"}
}