{
  "type": "Feature",
  "properties": {
    "gn:admin1_code":"76",
    "gn:asciiname":"Kopenkino",
    "gn:country_code":"RU",
    "gn:dem":212,
    "gn:feature_class":"P",
    "gn:feature_code":"PPL",
    "gn:name":"Kop\u00ebnkino",
    "gn:population":0,
    "gn:timezone":"Europe/Moscow",
    "iso:country":"RU",
    "name:rus_x_preferred":[
        "\u041a\u043e\u043f\u0451\u043d\u043a\u0438\u043d\u043e"
    ],
    "name:und_x_variant":[
        "Koponkino",
        "Kop\u00ebnkino"
    ],
    "wof:name":"Kopenkino",
    "wof:placetype":"locality"
},
  "geometry": {"coordinates":[37.97767,54.61699],"type":"Point"}
}