{
  "type": "Feature",
  "properties": {
    "gn:admin1_code":"33",
    "gn:asciiname":"Prudki",
    "gn:country_code":"RU",
    "gn:dem":149,
    "gn:feature_class":"P",
    "gn:feature_code":"PPL",
    "gn:name":"Prudki",
    "gn:population":0,
    "gn:timezone":"Europe/Kirov",
    "iso:country":"RU",
    "name:rus_x_preferred":[
        "\u041f\u0440\u0443\u0434\u043a\u0438"
    ],
    "name:und_x_variant":[
        "Prutki"
    ],
    "wof:name":"Prudki",
    "wof:placetype":"locality"
},
  "geometry": {"coordinates":[47.9672,57.0775],"type":"Point"}
}