{
  "type": "Feature",
  "properties": {
    "gn:admin1_code":"34.0",
    "gn:asciiname":"Borovo",
    "gn:country_code":"RU",
    "gn:dem":121,
    "gn:feature_class":"P",
    "gn:feature_code":"PPL",
    "gn:name":"Borovo",
    "gn:population":0,
    "gn:timezone":"Europe/Moscow",
    "iso:country":"RU",
    "name:bos_x_preferred":[
        "Borovo"
    ],
    "name:bul_x_preferred":[
        "\u0411\u043e\u0440\u043e\u0432\u043e"
    ],
    "name:ceb_x_preferred":[
        "Borovo"
    ],
    "name:eng_x_preferred":[
        "Borovo"
    ],
    "name:fra_x_preferred":[
        "Borovo"
    ],
    "name:hrv_x_preferred":[
        "Borovo"
    ],
    "name:mkd_x_preferred":[
        "\u0411\u043e\u0440\u043e\u0432\u043e"
    ],
    "name:nld_x_preferred":[
        "Borovo"
    ],
    "name:nor_x_preferred":[
        "Borovo"
    ],
    "name:por_x_preferred":[
        "Borovo"
    ],
    "name:ron_x_preferred":[
        "Borovo"
    ],
    "name:rus_x_preferred":[
        "\u0411\u043e\u0440\u043e\u0432\u043e"
    ],
    "name:slv_x_preferred":[
        "Borovo"
    ],
    "name:spa_x_preferred":[
        "Borovo"
    ],
    "name:srp_x_preferred":[
        "\u0411\u043e\u0440\u043e\u0432\u043e"
    ],
    "name:swe_x_preferred":[
        "Borovo"
    ],
    "name:ukr_x_preferred":[
        "\u0411\u043e\u0440\u043e\u0432\u043e"
    ],
    "name:und_x_variant":[
        "Borovskaya"
    ],
    "wof:name":"Borovo",
    "wof:placetype":"locality"
},
  "geometry": {"coordinates":[49.52174,63.53546],"type":"Point"}
}