{
  "type": "Feature",
  "properties": {
    "gn:admin1_code":"34.0",
    "gn:asciiname":"Borovo",
    "gn:country_code":"RU",
    "gn:dem":121,
    "gn:feature_class":"P",
    "gn:feature_code":"PPL",
    "gn:name":"Borovo",
    "gn:population":0,
    "gn:timezone":"Europe/Moscow",
    "iso:country":"RU",
    "name:eng_x_preferred":[
        "Borovo"
    ],
    "name:nor_x_preferred":[
        "Borovo"
    ],
    "name:rus_x_preferred":[
        "\u0411\u043e\u0440\u043e\u0432\u043e"
    ],
    "name:und_x_variant":[
        "Borovskaya",
        "\u0411\u043e\u0440\u043e\u0432\u043e",
        "Borovo"
    ],
    "wof:name":"Borovo",
    "wof:placetype":"locality"
},
  "geometry": {"coordinates":[49.52174,63.53546],"type":"Point"}
}