{
  "type": "Feature",
  "properties": {
    "gn:admin1_code":"4",
    "gn:asciiname":"Shestakovskiy",
    "gn:country_code":"RU",
    "gn:dem":286,
    "gn:feature_class":"P",
    "gn:feature_code":"PPL",
    "gn:name":"Shestakovskiy",
    "gn:population":0,
    "gn:timezone":"Asia/Barnaul",
    "iso:country":"RU",
    "name:rus_x_preferred":[
        "\u0428\u0435\u0441\u0442\u0430\u043a\u043e\u0432\u0441\u043a\u0438\u0439"
    ],
    "wof:name":"Shestakovskiy",
    "wof:placetype":"locality"
},
  "geometry": {"coordinates":[81.34999999999999,51.36667],"type":"Point"}
}