{
  "type": "Feature",
  "properties": {
    "gn:admin1_code":"84",
    "gn:asciiname":"Klyuchi",
    "gn:country_code":"RU",
    "gn:dem":59,
    "gn:feature_class":"P",
    "gn:feature_code":"PPL",
    "gn:name":"Klyuchi",
    "gn:population":0,
    "gn:timezone":"Europe/Volgograd",
    "iso:country":"RU",
    "name:bel_x_preferred":[
        "\u041a\u043b\u044e\u0447\u044b"
    ],
    "name:ceb_x_preferred":[
        "\u041a\u043b\u044e\u0447\u0438"
    ],
    "name:ces_x_preferred":[
        "Klju\u010di"
    ],
    "name:deu_x_preferred":[
        "Kljutschi"
    ],
    "name:kor_x_preferred":[
        "\ud074\ub958\uce58"
    ],
    "name:rus_x_preferred":[
        "\u041a\u043b\u044e\u0447\u0438"
    ],
    "name:tat_x_preferred":[
        "\u041a\u043b\u044e\u0447\u0438"
    ],
    "name:ukr_x_preferred":[
        "\u041a\u043b\u044e\u0447\u0456"
    ],
    "wof:name":"Klyuchi",
    "wof:placetype":"locality"
},
  "geometry": {"coordinates":[42.5902,49.8275],"type":"Point"}
}