{
  "type": "Feature",
  "properties": {
    "gn:admin1_code":"85.0",
    "gn:asciiname":"Dil'skiye",
    "gn:country_code":"RU",
    "gn:dem":126,
    "gn:feature_class":"P",
    "gn:feature_code":"PPL",
    "gn:name":"Dil\u2019skiye",
    "gn:population":0,
    "gn:timezone":"Europe/Moscow",
    "iso:country":"RU",
    "name:eng_x_preferred":[
        "Dil'skoye"
    ],
    "name:nor_x_preferred":[
        "Dilskije"
    ],
    "name:rus_x_preferred":[
        "\u0414\u0438\u043b\u044c\u0441\u043a\u0438\u0435"
    ],
    "name:und_x_variant":[
        "Dil\u2019skoye",
        "Dil\u2019skiye",
        "\u0414\u0438\u043b\u044c\u0441\u043a\u0438\u0435"
    ],
    "wof:name":"Dil'skiye",
    "wof:placetype":"locality"
},
  "geometry": {"coordinates":[36.6187,59.4349],"type":"Point"}
}