{
  "type": "Feature",
  "properties": {
    "gn:admin1_code":"42",
    "gn:admin2_code":"472711",
    "gn:asciiname":"Vel'tsa",
    "gn:country_code":"RU",
    "gn:dem":27,
    "gn:feature_class":"P",
    "gn:feature_code":"PPL",
    "gn:name":"Vel\u2019tsa",
    "gn:population":0,
    "gn:timezone":"Europe/Moscow",
    "iso:country":"RU",
    "name:rus_x_preferred":[
        "\u0412\u0435\u043b\u044c\u0446\u0430"
    ],
    "name:und_x_variant":[
        "Bel\u2019sy",
        "Vel\u2019sy",
        "Vel\u2019tsa"
    ],
    "wof:name":"Vel'tsa",
    "wof:placetype":"locality"
},
  "geometry": {"coordinates":[32.3618,59.83456],"type":"Point"}
}