{
  "type": "Feature",
  "properties": {
    "gn:admin1_code":"10.0",
    "gn:asciiname":"Zhukovo",
    "gn:country_code":"RU",
    "gn:dem":227,
    "gn:feature_class":"P",
    "gn:feature_code":"PPL",
    "gn:name":"Zhukovo",
    "gn:population":0,
    "gn:timezone":"Europe/Moscow",
    "iso:country":"RU",
    "name:rus_x_preferred":[
        "\u0416\u0443\u043a\u043e\u0432\u043e"
    ],
    "name:und_x_variant":[
        "Zhukova",
        "Zhukovo"
    ],
    "wof:name":"Zhukovo",
    "wof:placetype":"locality"
},
  "geometry": {"coordinates":[33.43879,53.6127],"type":"Point"}
}