{
  "type": "Feature",
  "properties": {
    "gn:admin1_code":"63",
    "gn:asciiname":"Suorattakh",
    "gn:country_code":"RU",
    "gn:dem":128,
    "gn:feature_class":"P",
    "gn:feature_code":"PPL",
    "gn:name":"Suorattakh",
    "gn:population":0,
    "gn:timezone":"Asia/Yakutsk",
    "iso:country":"RU",
    "name:rus_x_preferred":[
        "\u0421\u0443\u043e\u0440\u0430\u0442\u0442\u0430\u0445"
    ],
    "wof:name":"Suorattakh",
    "wof:placetype":"locality"
},
  "geometry": {"coordinates":[117.88333,63.05],"type":"Point"}
}