{
  "type": "Feature",
  "properties": {
    "gn:admin1_code":"23",
    "gn:asciiname":"Kruglovka",
    "gn:country_code":"RU",
    "gn:dem":14,
    "gn:feature_class":"P",
    "gn:feature_code":"PPL",
    "gn:name":"Kruglovka",
    "gn:population":0,
    "gn:timezone":"Europe/Kaliningrad",
    "iso:country":"RU",
    "name:rus_x_preferred":[
        "\u041a\u0440\u0443\u0433\u043b\u043e\u0432\u043a\u0430"
    ],
    "name:und_x_variant":[
        "\u041a\u0440\u0443\u0433\u043b\u043e\u0432\u043a\u0430"
    ],
    "wof:name":"Kruglovka",
    "wof:placetype":"locality"
},
  "geometry": {"coordinates":[21.04389,54.6925],"type":"Point"}
}