{
  "type": "Feature",
  "properties": {
    "gn:admin1_code":"6",
    "gn:asciiname":"Priluk",
    "gn:country_code":"RU",
    "gn:dem":16,
    "gn:feature_class":"P",
    "gn:feature_code":"PPL",
    "gn:name":"Priluk",
    "gn:population":0,
    "gn:timezone":"Europe/Moscow",
    "iso:country":"RU",
    "name:eng_x_preferred":[
        "Priluki"
    ],
    "name:nor_x_preferred":[
        "Priluk"
    ],
    "name:rus_x_preferred":[
        "\u041f\u0440\u0438\u043b\u0443\u043a"
    ],
    "wof:name":"Priluk",
    "wof:placetype":"locality"
},
  "geometry": {"coordinates":[42.9928,62.8149],"type":"Point"}
}