{
  "type": "Feature",
  "properties": {
    "gn:admin1_code":"32",
    "gn:asciiname":"Votman-Kurt",
    "gn:country_code":"RU",
    "gn:dem":22,
    "gn:feature_class":"P",
    "gn:feature_code":"PPL",
    "gn:name":"Votman-Kurt",
    "gn:population":0,
    "gn:timezone":"Asia/Yekaterinburg",
    "iso:country":"RU",
    "wof:name":"Votman-Kurt",
    "wof:placetype":"locality"
},
  "geometry": {"coordinates":[66.48994999999999,64.15106],"type":"Point"}
}