{
  "type": "Feature",
  "properties": {
    "gn:admin1_code":"91",
    "gn:asciiname":"Kamennyy",
    "gn:country_code":"RU",
    "gn:dem":475,
    "gn:feature_class":"P",
    "gn:feature_code":"PPL",
    "gn:name":"Kamennyy",
    "gn:population":0,
    "gn:timezone":"Asia/Krasnoyarsk",
    "iso:country":"RU",
    "name:rus_x_preferred":[
        "\u041a\u0430\u043c\u0435\u043d\u043d\u044b\u0439"
    ],
    "wof:name":"Kamennyy",
    "wof:placetype":"locality"
},
  "geometry": {"coordinates":[93.96666999999999,56.73333],"type":"Point"}
}