{
  "type": "Feature",
  "properties": {
    "gn:admin1_code":"10",
    "gn:asciiname":"Setka",
    "gn:country_code":"RU",
    "gn:dem":186,
    "gn:feature_class":"P",
    "gn:feature_code":"PPL",
    "gn:name":"Setka",
    "gn:population":0,
    "gn:timezone":"Europe/Moscow",
    "iso:country":"RU",
    "name:rus_x_preferred":[
        "\u0421\u0435\u0442\u043a\u0430"
    ],
    "name:und_x_variant":[
        "\u0421\u0435\u0442\u043a\u0430"
    ],
    "wof:name":"Setka",
    "wof:placetype":"locality"
},
  "geometry": {"coordinates":[33.16111,53.64083],"type":"Point"}
}