{
  "type": "Feature",
  "properties": {
    "gn:admin1_code":"88",
    "gn:asciiname":"Budovskoye",
    "gn:country_code":"RU",
    "gn:dem":159,
    "gn:feature_class":"P",
    "gn:feature_code":"PPL",
    "gn:name":"Budovskoye",
    "gn:population":0,
    "gn:timezone":"Europe/Moscow",
    "iso:country":"RU",
    "name:rus_x_preferred":[
        "\u0411\u0443\u0434\u043e\u0432\u0441\u043a\u043e\u0435"
    ],
    "wof:name":"Budovskoye",
    "wof:placetype":"locality"
},
  "geometry": {"coordinates":[39.2342,56.69],"type":"Point"}
}