{
  "type": "Feature",
  "properties": {
    "gn:admin1_code":"51",
    "gn:asciiname":"Zhaysk",
    "gn:country_code":"RU",
    "gn:dem":169,
    "gn:feature_class":"P",
    "gn:feature_code":"PPL",
    "gn:name":"Zhaysk",
    "gn:population":0,
    "gn:timezone":"Europe/Moscow",
    "iso:country":"RU",
    "name:eng_x_preferred":[
        "Zhaysk"
    ],
    "name:nor_x_preferred":[
        "Zjajsk"
    ],
    "name:rus_x_preferred":[
        "\u0416\u0430\u0439\u0441\u043a"
    ],
    "name:und_x_variant":[
        "Zhayskoye"
    ],
    "wof:name":"Zhaysk",
    "wof:placetype":"locality"
},
  "geometry": {"coordinates":[42.5454,55.9013],"type":"Point"}
}