{
  "type": "Feature",
  "properties": {
    "gn:admin1_code":"88",
    "gn:asciiname":"Matrenino",
    "gn:country_code":"RU",
    "gn:dem":116,
    "gn:feature_class":"P",
    "gn:feature_code":"PPL",
    "gn:name":"Matrenino",
    "gn:population":0,
    "gn:timezone":"Europe/Moscow",
    "iso:country":"RU",
    "name:rus_x_preferred":[
        "\u041c\u0430\u0442\u0440\u0435\u043d\u0438\u043d\u043e"
    ],
    "wof:name":"Matrenino",
    "wof:placetype":"locality"
},
  "geometry": {"coordinates":[39.98882,57.70976999999999],"type":"Point"}
}