{
  "type": "Feature",
  "properties": {
    "gn:admin1_code":"8",
    "gn:asciiname":"Verkhniye Lemezy",
    "gn:country_code":"RU",
    "gn:dem":158,
    "gn:feature_class":"P",
    "gn:feature_code":"PPL",
    "gn:name":"Verkhniye Lemezy",
    "gn:population":0,
    "gn:timezone":"Asia/Yekaterinburg",
    "iso:country":"RU",
    "name:eng_x_preferred":[
        "Verkhnelemezy"
    ],
    "name:nor_x_preferred":[
        "Verkh.Lemezy"
    ],
    "name:rus_x_preferred":[
        "\u0412\u0435\u0440\u0445.\u041b\u0435\u043c\u0435\u0437\u044b"
    ],
    "name:rus_x_variant":[
        "\u0412\u0435\u0440\u0445\u043d\u0438\u0435 \u041b\u0435\u043c\u0435\u0437\u044b"
    ],
    "name:und_x_variant":[
        "Verkhnyaya Lemeza",
        "Verkhniye Lemezy",
        "Verkhnelemezy"
    ],
    "wof:name":"Verkhniye Lemezy",
    "wof:placetype":"locality"
},
  "geometry": {"coordinates":[57.1943,54.6184],"type":"Point"}
}