{
  "type": "Feature",
  "properties": {
    "gn:admin1_code":"8",
    "gn:asciiname":"Verkhniye Lemezy",
    "gn:country_code":"RU",
    "gn:dem":158,
    "gn:feature_class":"P",
    "gn:feature_code":"PPL",
    "gn:name":"Verkhniye Lemezy",
    "gn:population":0,
    "gn:timezone":"Asia/Yekaterinburg",
    "iso:country":"RU",
    "name:aze_x_preferred":[
        "Yuxar\u0131 L\u0259m\u0259z"
    ],
    "name:bak_x_preferred":[
        "\u04ae\u0440\u0433\u0435 \u041b\u04d9\u043c\u04d9\u0499"
    ],
    "name:che_x_preferred":[
        "\u0412\u0435\u0440\u0445\u043d\u0438 \u041b\u0435\u043c\u0435\u0437\u044b"
    ],
    "name:eng_x_preferred":[
        "Verkhnelemezy"
    ],
    "name:hye_x_preferred":[
        "\u054e\u0565\u0580\u056d\u0576\u056b\u0565 \u053c\u0565\u0574\u0565\u0566\u056b"
    ],
    "name:kat_x_preferred":[
        "\u10d5\u10d4\u10e0\u10ee\u10dc\u10d8\u10d4-\u10da\u10d4\u10db\u10d4\u10d6\u10d8"
    ],
    "name:kaz_x_preferred":[
        "\u0416\u043e\u0493\u0430\u0440\u0493\u044b \u041b\u0435\u043c\u0435\u0437"
    ],
    "name:kir_x_preferred":[
        "\u0416\u043e\u0433\u043e\u0440\u043a\u0443 \u041b\u0435\u043c\u0435\u0437\u044b"
    ],
    "name:nor_x_preferred":[
        "Verkh.Lemezy"
    ],
    "name:rus_x_preferred":[
        "\u0412\u0435\u0440\u0445.\u041b\u0435\u043c\u0435\u0437\u044b"
    ],
    "name:rus_x_variant":[
        "\u0412\u0435\u0440\u0445\u043d\u0438\u0435 \u041b\u0435\u043c\u0435\u0437\u044b"
    ],
    "name:tat_x_preferred":[
        "\u042e\u0433\u0430\u0440\u044b \u041b\u04d9\u043c\u04d9\u0437"
    ],
    "name:ukr_x_preferred":[
        "\u0412\u0435\u0440\u0445\u043d\u0456 \u041b\u0435\u043c\u0435\u0437\u0438"
    ],
    "name:und_x_variant":[
        "Verkhnyaya Lemeza",
        "Verkhniye Lemezy",
        "Verkhnelemezy"
    ],
    "wof:name":"Verkhniye Lemezy",
    "wof:placetype":"locality"
},
  "geometry": {"coordinates":[57.1943,54.6184],"type":"Point"}
}