{
  "type": "Feature",
  "properties": {
    "gn:admin1_code":"71",
    "gn:asciiname":"Turutina",
    "gn:country_code":"RU",
    "gn:dem":79,
    "gn:feature_class":"P",
    "gn:feature_code":"PPL",
    "gn:name":"Turutina",
    "gn:population":0,
    "gn:timezone":"Asia/Yekaterinburg",
    "iso:country":"RU",
    "name:rus_x_preferred":[
        "\u0422\u0443\u0440\u0443\u0442\u0438\u043d\u0430"
    ],
    "name:und_x_variant":[
        "\u0422\u0443\u0440\u0443\u0442\u0438\u043d\u0430"
    ],
    "wof:name":"Turutina",
    "wof:placetype":"locality"
},
  "geometry": {"coordinates":[61.95192,58.46103000000001],"type":"Point"}
}