{
  "type": "Feature",
  "properties": {
    "gn:admin1_code":"56",
    "gn:asciiname":"Rassoshnoye",
    "gn:country_code":"RU",
    "gn:dem":223,
    "gn:feature_class":"P",
    "gn:feature_code":"PPL",
    "gn:name":"Rassoshnoye",
    "gn:population":0,
    "gn:timezone":"Europe/Moscow",
    "iso:country":"RU",
    "name:rus_x_preferred":[
        "\u0420\u0430\u0441\u0441\u043e\u0448\u043d\u043e\u0435"
    ],
    "name:und_x_variant":[
        "Rososhnoye",
        "Rossoshnoye",
        "Rassoshnoye",
        "\u0420\u0430\u0441\u0441\u043e\u0448\u043d\u043e\u0435"
    ],
    "wof:name":"Rassoshnoye",
    "wof:placetype":"locality"
},
  "geometry": {"coordinates":[37.69261,52.78454],"type":"Point"}
}