{
  "type": "Feature",
  "properties": {
    "gn:admin1_code":"56",
    "gn:asciiname":"Paramonovo",
    "gn:country_code":"RU",
    "gn:dem":246,
    "gn:feature_class":"P",
    "gn:feature_code":"PPL",
    "gn:name":"Paramonovo",
    "gn:population":0,
    "gn:timezone":"Europe/Moscow",
    "iso:country":"RU",
    "name:eng_x_preferred":[
        "Paramonovo"
    ],
    "name:nor_x_preferred":[
        "Paramonovo"
    ],
    "name:rus_x_preferred":[
        "\u041f\u0430\u0440\u0430\u043c\u043e\u043d\u043e\u0432\u043e"
    ],
    "wof:name":"Paramonovo",
    "wof:placetype":"locality"
},
  "geometry": {"coordinates":[37.38219,53.16382],"type":"Point"}
}