{
  "type": "Feature",
  "properties": {
    "gn:admin1_code":"38",
    "gn:asciiname":"Botanika",
    "gn:country_code":"RU",
    "gn:dem":136,
    "gn:feature_class":"P",
    "gn:feature_code":"PPL",
    "gn:name":"Botanika",
    "gn:population":0,
    "gn:timezone":"Europe/Moscow",
    "iso:country":"RU",
    "name:rus_x_preferred":[
        "\u0411\u043e\u0442\u0430\u043d\u0438\u043a\u0430"
    ],
    "name:und_x_variant":[
        "\u0411\u043e\u0442\u0430\u043d\u0438\u043a\u0430"
    ],
    "wof:name":"Botanika",
    "wof:placetype":"locality"
},
  "geometry": {"coordinates":[40.795,45.21472],"type":"Point"}
}