{
  "type": "Feature",
  "properties": {
    "gn:admin1_code":"77",
    "gn:asciiname":"Ulanovo",
    "gn:country_code":"RU",
    "gn:dem":135,
    "gn:feature_class":"P",
    "gn:feature_code":"PPL",
    "gn:name":"Ulanovo",
    "gn:population":0,
    "gn:timezone":"Europe/Moscow",
    "iso:country":"RU",
    "name:rus_x_preferred":[
        "\u0423\u043b\u0430\u043d\u043e\u0432\u043e"
    ],
    "name:und_x_variant":[
        "\u0423\u043b\u0430\u043d\u043e\u0432\u043e"
    ],
    "wof:name":"Ulanovo",
    "wof:placetype":"locality"
},
  "geometry": {"coordinates":[38.15389,57.26056],"type":"Point"}
}