{
  "type": "Feature",
  "properties": {
    "gn:admin1_code":"25.0",
    "gn:asciiname":"Ferzikovo",
    "gn:country_code":"RU",
    "gn:dem":206,
    "gn:feature_class":"P",
    "gn:feature_code":"PPL",
    "gn:name":"Ferzikovo",
    "gn:population":0,
    "gn:timezone":"Europe/Moscow",
    "iso:country":"RU",
    "name:ceb_x_preferred":[
        "Ferzikovo"
    ],
    "name:che_x_preferred":[
        "\u0424\u0435\u0440\u0437\u0438\u043a\u043e\u0432\u043e"
    ],
    "name:deu_x_preferred":[
        "Fersikowo"
    ],
    "name:hye_x_preferred":[
        "\u0556\u0565\u0580\u0566\u056b\u056f\u0578\u057e\u0578"
    ],
    "name:nor_x_preferred":[
        "Ferzikovo"
    ],
    "name:pol_x_preferred":[
        "Fierzikowo"
    ],
    "name:rus_x_preferred":[
        "\u0424\u0435\u0440\u0437\u0438\u043a\u043e\u0432\u043e"
    ],
    "name:ukr_x_preferred":[
        "\u0424\u0435\u0440\u0437\u0438\u043a\u043e\u0432\u0435"
    ],
    "wof:name":"Ferzikovo",
    "wof:placetype":"locality"
},
  "geometry": {"coordinates":[36.74423,54.5441],"type":"Point"}
}