{
  "type": "Feature",
  "properties": {
    "gn:admin1_code":"85",
    "gn:asciiname":"Vashki",
    "gn:country_code":"RU",
    "gn:dem":137,
    "gn:feature_class":"P",
    "gn:feature_code":"PPL",
    "gn:name":"Vashki",
    "gn:population":0,
    "gn:timezone":"Europe/Moscow",
    "iso:country":"RU",
    "name:eng_x_preferred":[
        "Vashki"
    ],
    "name:nor_x_preferred":[
        "Vasjki"
    ],
    "name:rus_x_preferred":[
        "\u0412\u0430\u0448\u043a\u0438"
    ],
    "name:sco_x_preferred":[
        "Vashki"
    ],
    "wof:name":"Vashki",
    "wof:placetype":"locality"
},
  "geometry": {"coordinates":[37.9536,60.3058],"type":"Point"}
}