{
  "type": "Feature",
  "properties": {
    "gn:admin1_code":"71",
    "gn:asciiname":"Kosari",
    "gn:country_code":"RU",
    "gn:dem":66,
    "gn:feature_class":"P",
    "gn:feature_code":"PPL",
    "gn:name":"Kosari",
    "gn:population":0,
    "gn:timezone":"Asia/Yekaterinburg",
    "iso:country":"RU",
    "name:rus_x_preferred":[
        "\u041a\u043e\u0441\u0430\u0440\u0438"
    ],
    "name:und_x_variant":[
        "Kosar\u00ebva",
        "Kosari"
    ],
    "wof:name":"Kosari",
    "wof:placetype":"locality"
},
  "geometry": {"coordinates":[63.11847,57.73748000000001],"type":"Point"}
}