{
  "type": "Feature",
  "properties": {
    "gn:admin1_code":"53",
    "gn:asciiname":"Iskra",
    "gn:country_code":"RU",
    "gn:dem":116,
    "gn:feature_class":"P",
    "gn:feature_code":"PPL",
    "gn:name":"Iskra",
    "gn:population":0,
    "gn:timezone":"Asia/Novosibirsk",
    "iso:country":"RU",
    "name:rus_x_preferred":[
        "\u0418\u0441\u043a\u0440\u0430"
    ],
    "wof:name":"Iskra",
    "wof:placetype":"locality"
},
  "geometry": {"coordinates":[77.42775,54.43026],"type":"Point"}
}