{
  "type": "Feature",
  "properties": {
    "gn:admin1_code":"85",
    "gn:asciiname":"Mochalovo",
    "gn:country_code":"RU",
    "gn:dem":115,
    "gn:feature_class":"P",
    "gn:feature_code":"PPL",
    "gn:name":"Mochalovo",
    "gn:population":0,
    "gn:timezone":"Europe/Moscow",
    "iso:country":"RU",
    "name:rus_x_preferred":[
        "\u041c\u043e\u0447\u0430\u043b\u043e\u0432\u043e"
    ],
    "name:und_x_variant":[
        "\u041c\u043e\u0447\u0430\u043b\u043e\u0432\u043e"
    ],
    "wof:name":"Mochalovo",
    "wof:placetype":"locality"
},
  "geometry": {"coordinates":[39.9241,59.5806],"type":"Point"}
}