{
  "type": "Feature",
  "properties": {
    "gn:admin1_code":"41",
    "gn:asciiname":"Koz'minka",
    "gn:country_code":"RU",
    "gn:dem":174,
    "gn:feature_class":"P",
    "gn:feature_code":"PPL",
    "gn:name":"Koz\u2019minka",
    "gn:population":0,
    "gn:timezone":"Europe/Moscow",
    "iso:country":"RU",
    "name:rus_x_preferred":[
        "\u041a\u043e\u0437\u044c\u043c\u0438\u043d\u043a\u0430"
    ],
    "name:und_x_variant":[
        "Koz\u2019minka"
    ],
    "wof:name":"Koz'minka",
    "wof:placetype":"locality"
},
  "geometry": {"coordinates":[36.38902,51.97811],"type":"Point"}
}