{
  "type": "Feature",
  "properties": {
    "gn:admin1_code":"83.0",
    "gn:asciiname":"Fryazino",
    "gn:country_code":"RU",
    "gn:dem":96,
    "gn:feature_class":"P",
    "gn:feature_code":"PPL",
    "gn:name":"Fryazino",
    "gn:population":0,
    "gn:timezone":"Europe/Moscow",
    "iso:country":"RU",
    "name:rus_x_preferred":[
        "\u0424\u0440\u044f\u0437\u0438\u043d\u043e"
    ],
    "wof:name":"Fryazino",
    "wof:placetype":"locality"
},
  "geometry": {"coordinates":[40.30217,56.03646],"type":"Point"}
}