{
  "type": "Feature",
  "properties": {
    "gn:admin1_code":"25",
    "gn:asciiname":"Maloye Litashevo",
    "gn:country_code":"RU",
    "gn:dem":191,
    "gn:feature_class":"P",
    "gn:feature_code":"PPL",
    "gn:name":"Maloye Litash\u00ebvo",
    "gn:population":0,
    "gn:timezone":"Europe/Moscow",
    "iso:country":"RU",
    "name:rus_x_preferred":[
        "\u041c\u0430\u043b\u043e\u0435 \u041b\u0438\u0442\u0430\u0448\u0451\u0432\u043e"
    ],
    "name:und_x_variant":[
        "Maloye Litash\u00ebvo",
        "\u041c\u0430\u043b\u043e\u0435 \u041b\u0438\u0442\u0430\u0448\u0451\u0432\u043e"
    ],
    "wof:name":"Maloye Litashevo",
    "wof:placetype":"locality"
},
  "geometry": {"coordinates":[36.88333,55.08333],"type":"Point"}
}