{
  "type": "Feature",
  "properties": {
    "gn:admin1_code":"91",
    "gn:asciiname":"Momotovo",
    "gn:country_code":"RU",
    "gn:dem":93,
    "gn:feature_class":"P",
    "gn:feature_code":"PPL",
    "gn:name":"Momotovo",
    "gn:population":0,
    "gn:timezone":"Asia/Krasnoyarsk",
    "iso:country":"RU",
    "name:eng_x_preferred":[
        "Momotovo"
    ],
    "name:nor_x_preferred":[
        "Momotovo"
    ],
    "name:rus_x_preferred":[
        "\u041c\u043e\u043c\u043e\u0442\u043e\u0432\u043e"
    ],
    "name:und_x_variant":[
        "Mamotovo",
        "Mamotova",
        "Momotovo"
    ],
    "wof:name":"Momotovo",
    "wof:placetype":"locality"
},
  "geometry": {"coordinates":[93.3223,57.629],"type":"Point"}
}