{
  "type": "Feature",
  "properties": {
    "gn:admin1_code":"8.0",
    "gn:asciiname":"Bikkulovo",
    "gn:country_code":"RU",
    "gn:dem":433,
    "gn:feature_class":"P",
    "gn:feature_code":"PPL",
    "gn:name":"Bikkulovo",
    "gn:population":0,
    "gn:timezone":"Asia/Yekaterinburg",
    "iso:country":"RU",
    "name:rus_x_preferred":[
        "\u0411\u0438\u043a\u043a\u0443\u043b\u043e\u0432\u043e"
    ],
    "name:und_x_variant":[
        "\u0411\u0438\u043a\u043a\u0443\u043b\u043e\u0432\u043e"
    ],
    "wof:name":"Bikkulovo",
    "wof:placetype":"locality"
},
  "geometry": {"coordinates":[58.6985,53.6563],"type":"Point"}
}