{
  "type": "Feature",
  "properties": {
    "gn:admin1_code":"47.0",
    "gn:asciiname":"Rudakovo",
    "gn:country_code":"RU",
    "gn:dem":136,
    "gn:feature_class":"P",
    "gn:feature_code":"PPL",
    "gn:name":"Rudakovo",
    "gn:population":0,
    "gn:timezone":"Europe/Moscow",
    "iso:country":"RU",
    "name:rus_x_preferred":[
        "\u0420\u0443\u0434\u0430\u043a\u043e\u0432\u043e"
    ],
    "wof:name":"Rudakovo",
    "wof:placetype":"locality"
},
  "geometry": {"coordinates":[37.15528,55.056],"type":"Point"}
}