{
  "type": "Feature",
  "properties": {
    "gn:admin1_code":"76",
    "gn:asciiname":"Osinovka",
    "gn:cc2":"RU",
    "gn:country_code":"RU",
    "gn:dem":202,
    "gn:feature_class":"P",
    "gn:feature_code":"PPL",
    "gn:name":"Osinovka",
    "gn:population":0,
    "gn:timezone":"Europe/Moscow",
    "iso:country":"RU",
    "name:ceb_x_preferred":[
        "Osinovka"
    ],
    "name:lav_x_preferred":[
        "Osinovka"
    ],
    "name:rus_x_preferred":[
        "\u041e\u0441\u0438\u043d\u043e\u0432\u043a\u0430"
    ],
    "name:swe_x_preferred":[
        "Osinovka"
    ],
    "name:und_x_variant":[
        "Zakhlebovka",
        "Zekhlebovka",
        "Osinovka",
        "\u041e\u0441\u0438\u043d\u043e\u0432\u043a\u0430"
    ],
    "wof:name":"Osinovka",
    "wof:placetype":"locality"
},
  "geometry": {"coordinates":[37.25,53.51667],"type":"Point"}
}