{
  "type": "Feature",
  "properties": {
    "gn:admin1_code":"51.0",
    "gn:asciiname":"Chuvakhley",
    "gn:country_code":"RU",
    "gn:dem":139,
    "gn:feature_class":"P",
    "gn:feature_code":"PPL",
    "gn:name":"Chuvakhley",
    "gn:population":0,
    "gn:timezone":"Europe/Moscow",
    "iso:country":"RU",
    "name:rus_x_preferred":[
        "\u0427\u0443\u0432\u0430\u0445\u043b\u0435\u0439"
    ],
    "name:und_x_variant":[
        "Chuvakhla",
        "Chuvakhley"
    ],
    "wof:name":"Chuvakhley",
    "wof:placetype":"locality"
},
  "geometry": {"coordinates":[44.13943,55.4939],"type":"Point"}
}