{
  "type": "Feature",
  "properties": {
    "gn:admin1_code":"33",
    "gn:asciiname":"Nikishichi",
    "gn:country_code":"RU",
    "gn:dem":198,
    "gn:feature_class":"P",
    "gn:feature_code":"PPL",
    "gn:name":"Nikishichi",
    "gn:population":0,
    "gn:timezone":"Europe/Kirov",
    "iso:country":"RU",
    "name:eng_x_preferred":[
        "Nikishichi"
    ],
    "name:nor_x_preferred":[
        "Nikisjitsji"
    ],
    "name:rus_x_preferred":[
        "\u041d\u0438\u043a\u0438\u0448\u0438\u0447\u0438"
    ],
    "wof:name":"Nikishichi",
    "wof:placetype":"locality"
},
  "geometry": {"coordinates":[49.03479,59.35602],"type":"Point"}
}