{
  "type": "Feature",
  "properties": {
    "gn:country":"RU",
    "gn:fcode":"PPL",
    "gn:population":1855,
    "iso:country":"RU",
    "name:bel_x_preferred":[
        "\u041c\u0435\u0436\u0434\u0443\u0440\u044d\u0447\u0430\u043d\u0441\u043a"
    ],
    "name:bul_x_preferred":[
        "\u041c\u0435\u0436\u0434\u0443\u0440\u0435\u0447\u0435\u043d\u0441\u043a"
    ],
    "name:eng_x_preferred":[
        "Mezhdurechensk"
    ],
    "name:fin_x_preferred":[
        "Me\u017eduret\u0161ensk"
    ],
    "name:hye_x_preferred":[
        "\u0544\u0565\u056a\u0564\u0578\u0582\u0580\u0565\u0579\u0565\u0576\u057d\u056f"
    ],
    "name:kom_x_preferred":[
        "\u041c\u0435\u0436\u0434\u0443\u0440\u0435\u0447\u0435\u043d\u0441\u043a"
    ],
    "name:nld_x_preferred":[
        "Mezjdoeretsjensk"
    ],
    "name:nno_x_preferred":[
        "Mezjduretsjensk"
    ],
    "name:nob_x_preferred":[
        "Mezjduretsjensk"
    ],
    "name:pol_x_preferred":[
        "Mie\u017cdurieczensk"
    ],
    "name:rus_x_preferred":[
        "\u041c\u0435\u0436\u0434\u0443\u0440\u0435\u0447\u0435\u043d\u0441\u043a"
    ],
    "qs:name":"Mezhdurechensk",
    "qs:photos_9r":0,
    "qs:photos_sr":0,
    "qs:pop_sr":"3",
    "wd:wordcount":85,
    "wof:name":"Mezhdurechensk",
    "wof:placetype":"locality",
    "wof:population":1855
},
  "geometry": {"coordinates":[48.55333,63.24556],"type":"Point"}
}