{
  "type": "Feature",
  "properties": {
    "gn:admin1_code":"57",
    "gn:asciiname":"Sulyayevka",
    "gn:country_code":"RU",
    "gn:dem":217,
    "gn:feature_class":"P",
    "gn:feature_code":"PPL",
    "gn:name":"Sulyayevka",
    "gn:population":0,
    "gn:timezone":"Europe/Moscow",
    "iso:country":"RU",
    "name:eng_x_preferred":[
        "Sulyayevka"
    ],
    "name:nor_x_preferred":[
        "Suljaevka"
    ],
    "name:rus_x_preferred":[
        "\u0421\u0443\u043b\u044f\u0435\u0432\u043a\u0430"
    ],
    "wof:name":"Sulyayevka",
    "wof:placetype":"locality"
},
  "geometry": {"coordinates":[45.91559,52.64728],"type":"Point"}
}