{
  "type": "Feature",
  "properties": {
    "gn:admin1_code":"45.0",
    "gn:asciiname":"Druzhba",
    "gn:country_code":"RU",
    "gn:dem":93,
    "gn:feature_class":"P",
    "gn:feature_code":"PPL",
    "gn:name":"Druzhba",
    "gn:population":0,
    "gn:timezone":"Europe/Moscow",
    "iso:country":"RU",
    "name:rus_x_preferred":[
        "\u0414\u0440\u0443\u0436\u0431\u0430"
    ],
    "name:und_x_variant":[
        "\u0414\u0440\u0443\u0436\u0431\u0430"
    ],
    "wof:name":"Druzhba",
    "wof:placetype":"locality"
},
  "geometry": {"coordinates":[48.03194000000001,56.1475],"type":"Point"}
}