{
  "type": "Feature",
  "properties": {
    "gn:admin1_code":"17.0",
    "gn:asciiname":"Khodzha-Kazmalyar",
    "gn:country_code":"RU",
    "gn:dem":194,
    "gn:feature_class":"P",
    "gn:feature_code":"PPL",
    "gn:name":"Khodzha-Kazmalyar",
    "gn:population":0,
    "gn:timezone":"Europe/Moscow",
    "iso:country":"RU",
    "name:rus_x_preferred":[
        "\u0425\u043e\u0434\u0436\u0430-\u041a\u0430\u0437\u043c\u0430\u043b\u044f\u0440"
    ],
    "wof:name":"Khodzha-Kazmalyar",
    "wof:placetype":"locality"
},
  "geometry": {"coordinates":[48.438,41.72534],"type":"Point"}
}