{
  "type": "Feature",
  "properties": {
    "gn:admin1_code":"63",
    "gn:asciiname":"Zhdanovo",
    "gn:country_code":"RU",
    "gn:dem":164,
    "gn:feature_class":"P",
    "gn:feature_code":"PPL",
    "gn:name":"Zhdanovo",
    "gn:population":0,
    "gn:timezone":"Asia/Yakutsk",
    "iso:country":"RU",
    "name:eng_x_preferred":[
        "Zhdanovo"
    ],
    "name:nor_x_preferred":[
        "Zjdanovo"
    ],
    "name:rus_x_preferred":[
        "\u0416\u0434\u0430\u043d\u043e\u0432\u043e"
    ],
    "wof:name":"Zhdanovo",
    "wof:placetype":"locality"
},
  "geometry": {"coordinates":[122.41533,64.46313000000001],"type":"Point"}
}