{
  "type": "Feature",
  "properties": {
    "gn:admin1_code":"47",
    "gn:asciiname":"Khmelevki",
    "gn:country_code":"RU",
    "gn:dem":152,
    "gn:feature_class":"P",
    "gn:feature_code":"PPL",
    "gn:name":"Khmel\u00ebvki",
    "gn:population":0,
    "gn:timezone":"Europe/Moscow",
    "iso:country":"RU",
    "name:nor_x_preferred":[
        "Khmeljovki"
    ],
    "name:rus_x_preferred":[
        "\u0425\u043c\u0435\u043b\u0451\u0432\u043a\u0438"
    ],
    "name:und_x_variant":[
        "Khmel\u00ebvki"
    ],
    "wof:name":"Khmelevki",
    "wof:placetype":"locality"
},
  "geometry": {"coordinates":[35.69773,56.3264],"type":"Point"}
}