{
  "type": "Feature",
  "properties": {
    "gn:admin1_code":"51.0",
    "gn:asciiname":"Svobodnoye",
    "gn:country_code":"RU",
    "gn:dem":150,
    "gn:feature_class":"P",
    "gn:feature_code":"PPL",
    "gn:name":"Svobodnoye",
    "gn:population":0,
    "gn:timezone":"Europe/Moscow",
    "iso:country":"RU",
    "name:und_x_variant":[
        "Svobodnaya",
        "Svobodnoye"
    ],
    "wof:name":"Svobodnoye",
    "wof:placetype":"locality"
},
  "geometry": {"coordinates":[43.5525,55.45816],"type":"Point"}
}