{
  "type": "Feature",
  "properties": {
    "gn:admin1_code":"52",
    "gn:asciiname":"Luskarevo",
    "gn:country_code":"RU",
    "gn:dem":66,
    "gn:feature_class":"P",
    "gn:feature_code":"PPL",
    "gn:name":"Luskarevo",
    "gn:population":0,
    "gn:timezone":"Europe/Moscow",
    "iso:country":"RU",
    "name:rus_x_preferred":[
        "\u041b\u0443\u0441\u043a\u0430\u0440\u0435\u0432\u043e"
    ],
    "wof:name":"Luskarevo",
    "wof:placetype":"locality"
},
  "geometry": {"coordinates":[31.1606,57.6117],"type":"Point"}
}