{
  "type": "Feature",
  "properties": {
    "gn:admin1_code":"61.0",
    "gn:asciiname":"Danilov",
    "gn:country_code":"RU",
    "gn:dem":153,
    "gn:feature_class":"P",
    "gn:feature_code":"PPL",
    "gn:name":"Danilov",
    "gn:population":0,
    "gn:timezone":"Europe/Moscow",
    "iso:country":"RU",
    "name:eng_x_preferred":[
        "Danilov"
    ],
    "name:nor_x_preferred":[
        "Danilov"
    ],
    "name:rus_x_preferred":[
        "\u0414\u0430\u043d\u0438\u043b\u043e\u0432"
    ],
    "name:und_x_variant":[
        "\u0414\u0430\u043d\u0438\u043b\u043e\u0432",
        "Danilov"
    ],
    "wof:name":"Danilov",
    "wof:placetype":"locality"
},
  "geometry": {"coordinates":[40.81482000000001,48.49557],"type":"Point"}
}