{
  "type": "Feature",
  "properties": {
    "gn:admin1_code":"46",
    "gn:asciiname":"Kuchkayevo",
    "gn:country_code":"RU",
    "gn:dem":199,
    "gn:feature_class":"P",
    "gn:feature_code":"PPL",
    "gn:name":"Kuchkayevo",
    "gn:population":0,
    "gn:timezone":"Europe/Moscow",
    "iso:country":"RU",
    "name:rus_x_preferred":[
        "\u041a\u0443\u0447\u043a\u0430\u0435\u0432\u043e"
    ],
    "name:und_x_variant":[
        "\u041a\u0443\u0447\u043a\u0430\u0435\u0432\u043e"
    ],
    "wof:name":"Kuchkayevo",
    "wof:placetype":"locality"
},
  "geometry": {"coordinates":[45.68459,55.03039],"type":"Point"}
}