{
  "type": "Feature",
  "properties": {
    "gn:admin1_code":"63",
    "gn:asciiname":"Kester",
    "gn:country_code":"RU",
    "gn:dem":642,
    "gn:feature_class":"P",
    "gn:feature_code":"PPL",
    "gn:name":"K\u00ebster",
    "gn:population":0,
    "gn:timezone":"Asia/Vladivostok",
    "iso:country":"RU",
    "name:rus_x_preferred":[
        "\u041a\u0451\u0441\u0442\u0435\u0440"
    ],
    "name:und_x_variant":[
        "K\u00ebster",
        "\u041a\u0451\u0441\u0442\u0435\u0440"
    ],
    "wof:name":"Kester",
    "wof:placetype":"locality"
},
  "geometry": {"coordinates":[134.26317,67.24989000000001],"type":"Point"}
}