{
  "type": "Feature",
  "properties": {
    "gn:admin1_code":"10",
    "gn:asciiname":"Kolech'ye",
    "gn:country_code":"RU",
    "gn:dem":137,
    "gn:feature_class":"P",
    "gn:feature_code":"PPL",
    "gn:name":"Kolech\u2019ye",
    "gn:population":0,
    "gn:timezone":"Europe/Moscow",
    "iso:country":"RU",
    "name:rus_x_preferred":[
        "\u041ao\u043b\u0435\u0447\u044c\u0435"
    ],
    "name:rus_x_variant":[
        "Kolech\u2019ye"
    ],
    "name:und_x_variant":[
        "Kolech\u2019ye",
        "\u041ao\u043b\u0435\u0447\u044c\u0435",
        "Kaleche"
    ],
    "wof:name":"Kolech'ye",
    "wof:placetype":"locality"
},
  "geometry": {"coordinates":[32.30145,52.16631],"type":"Point"}
}