{
  "type": "Feature",
  "properties": {
    "gn:admin1_code":"90.0",
    "gn:asciiname":"Balkachi",
    "gn:country_code":"RU",
    "gn:dem":169,
    "gn:feature_class":"P",
    "gn:feature_code":"PPL",
    "gn:name":"Balkachi",
    "gn:population":0,
    "gn:timezone":"Asia/Yekaterinburg",
    "iso:country":"RU",
    "name:che_x_preferred":[
        "\u0411\u0430\u043b\u043a\u0430\u0447\u0438"
    ],
    "name:rus_x_preferred":[
        "\u0411\u0430\u043b\u043a\u0430\u0447\u0438"
    ],
    "wof:name":"Balkachi",
    "wof:placetype":"locality"
},
  "geometry": {"coordinates":[54.713,58.7045],"type":"Point"}
}