{
  "type": "Feature",
  "properties": {
    "gn:admin1_code":"71",
    "gn:asciiname":"Golysheva",
    "gn:country_code":"RU",
    "gn:dem":66,
    "gn:feature_class":"P",
    "gn:feature_code":"PPL",
    "gn:name":"Golysh\u00ebva",
    "gn:population":0,
    "gn:timezone":"Asia/Yekaterinburg",
    "iso:country":"RU",
    "name:rus_x_preferred":[
        "\u0413\u043e\u043b\u044b\u0448\u0451\u0432\u0430"
    ],
    "name:und_x_variant":[
        "Golysh\u00ebva"
    ],
    "wof:name":"Golysheva",
    "wof:placetype":"locality"
},
  "geometry": {"coordinates":[63.8834,58.01575],"type":"Point"}
}