{
  "type": "Feature",
  "properties": {
    "gn:admin1_code":"28",
    "gn:asciiname":"Peypposenkyulya",
    "gn:country_code":"RU",
    "gn:dem":6,
    "gn:feature_class":"P",
    "gn:feature_code":"PPL",
    "gn:name":"Peypposenkyulya",
    "gn:population":0,
    "gn:timezone":"Europe/Moscow",
    "iso:country":"RU",
    "name:fin_x_preferred":[
        "Peipposenkyl\u00e4"
    ],
    "name:rus_x_preferred":[
        "\u041f\u0435\u0439\u043f\u043f\u043e\u0441\u0435\u043d\u043a\u044e\u043b\u044f"
    ],
    "name:und_x_variant":[
        "\u041f\u0435\u0439\u043f\u043f\u043e\u0441\u0435\u043d\u043a\u044e\u043b\u044f"
    ],
    "wof:name":"Peypposenkyulya",
    "wof:placetype":"locality"
},
  "geometry": {"coordinates":[31.54896,61.35725],"type":"Point"}
}