{
  "type": "Feature",
  "properties": {
    "gn:admin1_code":"47",
    "gn:asciiname":"Borzetsovo",
    "gn:country_code":"RU",
    "gn:dem":186,
    "gn:feature_class":"P",
    "gn:feature_code":"PPL",
    "gn:name":"Borzetsovo",
    "gn:population":0,
    "gn:timezone":"Europe/Moscow",
    "iso:country":"RU",
    "name:rus_x_preferred":[
        "\u0411\u043e\u0440\u0437\u0435\u0446\u043e\u0432\u043e"
    ],
    "wof:name":"Borzetsovo",
    "wof:placetype":"locality"
},
  "geometry": {"coordinates":[36.23361,55.82694],"type":"Point"}
}