{
  "type": "Feature",
  "properties": {
    "gn:admin1_code":"71",
    "gn:asciiname":"Staraya Galisheva",
    "gn:country_code":"RU",
    "gn:dem":78,
    "gn:feature_class":"P",
    "gn:feature_code":"PPL",
    "gn:name":"Staraya Galish\u00ebva",
    "gn:population":0,
    "gn:timezone":"Asia/Yekaterinburg",
    "iso:country":"RU",
    "name:rus_x_preferred":[
        "\u0421\u0442\u0430\u0440\u0430\u044f \u0413\u0430\u043b\u0438\u0448\u0451\u0432\u0430"
    ],
    "name:und_x_variant":[
        "Staraya Galish\u00ebva"
    ],
    "wof:name":"Staraya Galisheva",
    "wof:placetype":"locality"
},
  "geometry": {"coordinates":[63.15,57.48333],"type":"Point"}
}