{
  "type": "Feature",
  "properties": {
    "gn:admin1_code":"69",
    "gn:asciiname":"Roshchino",
    "gn:country_code":"RU",
    "gn:dem":201,
    "gn:feature_class":"P",
    "gn:feature_code":"PPL",
    "gn:name":"Roshchino",
    "gn:population":0,
    "gn:timezone":"Europe/Moscow",
    "iso:country":"RU",
    "name:rus_x_preferred":[
        "\u0420\u043e\u0449\u0438\u043d\u043e"
    ],
    "name:und_x_variant":[
        "\u0420\u043e\u0449\u0438\u043d\u043e"
    ],
    "wof:name":"Roshchino",
    "wof:placetype":"locality"
},
  "geometry": {"coordinates":[34.85174,55.84266],"type":"Point"}
}