{
  "type": "Feature",
  "properties": {
    "gn:admin1_code":"51",
    "gn:asciiname":"Malaya Yel'nya",
    "gn:country_code":"RU",
    "gn:dem":91,
    "gn:feature_class":"P",
    "gn:feature_code":"PPL",
    "gn:name":"Malaya Yel\u2019nya",
    "gn:population":0,
    "gn:timezone":"Europe/Moscow",
    "iso:country":"RU",
    "name:rus_x_preferred":[
        "\u041c\u0430\u043b\u0430\u044f \u0415\u043b\u044c\u043d\u044f"
    ],
    "name:und_x_variant":[
        "Malaya Yel\u2019nya",
        "\u041c\u0430\u043b\u0430\u044f \u0415\u043b\u044c\u043d\u044f"
    ],
    "wof:name":"Malaya Yel'nya",
    "wof:placetype":"locality"
},
  "geometry": {"coordinates":[44.14641,56.21001999999999],"type":"Point"}
}