{
  "type": "Feature",
  "properties": {
    "gn:admin1_code":"10",
    "gn:asciiname":"Kartashovo",
    "gn:country_code":"RU",
    "gn:dem":148,
    "gn:feature_class":"P",
    "gn:feature_code":"PPL",
    "gn:name":"Kartashovo",
    "gn:population":0,
    "gn:timezone":"Europe/Moscow",
    "iso:country":"RU",
    "name:rus_x_preferred":[
        "\u041a\u0430\u0440\u0442\u0430\u0448\u043e\u0432\u043e"
    ],
    "name:und_x_variant":[
        "Kartashova",
        "Kartashovo",
        "\u041a\u0430\u0440\u0442\u0430\u0448\u043e\u0432\u043e"
    ],
    "wof:name":"Kartashovo",
    "wof:placetype":"locality"
},
  "geometry": {"coordinates":[33.657,52.59705],"type":"Point"}
}