{
  "type": "Feature",
  "properties": {
    "gn:admin1_code":"61",
    "gn:asciiname":"Sibirki",
    "gn:country_code":"RU",
    "gn:dem":78,
    "gn:feature_class":"P",
    "gn:feature_code":"PPL",
    "gn:name":"Sibirki",
    "gn:population":0,
    "gn:timezone":"Europe/Moscow",
    "iso:country":"RU",
    "name:rus_x_preferred":[
        "\u0421\u0438\u0431\u0438\u0440\u043a\u0438"
    ],
    "name:und_x_variant":[
        "Bibirki",
        "Sibirki",
        "\u0421\u0438\u0431\u0438\u0440\u043a\u0438"
    ],
    "wof:name":"Sibirki",
    "wof:placetype":"locality"
},
  "geometry": {"coordinates":[41.71601,48.30134],"type":"Point"}
}