{
  "type": "Feature",
  "properties": {
    "gn:admin1_code":"17.0",
    "gn:asciiname":"Chalits",
    "gn:country_code":"RU",
    "gn:dem":1953,
    "gn:feature_class":"P",
    "gn:feature_code":"PPL",
    "gn:name":"Chalits",
    "gn:population":0,
    "gn:timezone":"Europe/Moscow",
    "iso:country":"RU",
    "wof:name":"Chalits",
    "wof:placetype":"locality"
},
  "geometry": {"coordinates":[47.3775,42.03194000000001],"type":"Point"}
}