{
  "type": "Feature",
  "properties": {
    "gn:admin1_code":"33.0",
    "gn:asciiname":"Bol'shiye Sharomovy",
    "gn:country_code":"RU",
    "gn:dem":152,
    "gn:feature_class":"P",
    "gn:feature_code":"PPL",
    "gn:name":"Bol\u2019shiye Sharomovy",
    "gn:population":0,
    "gn:timezone":"Europe/Kirov",
    "iso:country":"RU",
    "name:rus_x_preferred":[
        "\u0411\u043e\u043b\u044c\u0448\u0438\u0435 \u0428\u0430\u0440\u043e\u043c\u043e\u0432\u044b"
    ],
    "name:und_x_variant":[
        "Bol\u2019shiye Sharomovy",
        "\u0411\u043e\u043b\u044c\u0448\u0438\u0435 \u0428\u0430\u0440\u043e\u043c\u043e\u0432\u044b"
    ],
    "wof:name":"Bol'shiye Sharomovy",
    "wof:placetype":"locality"
},
  "geometry": {"coordinates":[50.04583,58.68028],"type":"Point"}
}