{
  "type": "Feature",
  "properties": {
    "gn:admin1_code":"84",
    "gn:asciiname":"Lapin",
    "gn:country_code":"RU",
    "gn:dem":95,
    "gn:feature_class":"P",
    "gn:feature_code":"PPL",
    "gn:name":"Lapin",
    "gn:population":0,
    "gn:timezone":"Europe/Volgograd",
    "iso:country":"RU",
    "name:rus_x_preferred":[
        "\u041b\u0430\u043f\u0438\u043d"
    ],
    "wof:name":"Lapin",
    "wof:placetype":"locality"
},
  "geometry": {"coordinates":[42.9741,50.7458],"type":"Point"}
}