{
  "type": "Feature",
  "properties": {
    "gn:admin1_code":"8",
    "gn:asciiname":"Tangatarovo",
    "gn:country_code":"RU",
    "gn:dem":82,
    "gn:feature_class":"P",
    "gn:feature_code":"PPL",
    "gn:name":"Tangatarovo",
    "gn:population":0,
    "gn:timezone":"Asia/Yekaterinburg",
    "iso:country":"RU",
    "name:bak_x_preferred":[
        "\u0422\u0430\u04a3\u0430\u0442\u0430\u0440"
    ],
    "name:che_x_preferred":[
        "\u0422\u0430\u043d\u0433\u0430\u0442\u0430\u0440\u043e\u0432\u043e"
    ],
    "name:eng_x_preferred":[
        "Tangatarovo"
    ],
    "name:hye_x_preferred":[
        "\u054f\u0561\u0576\u0563\u0561\u057f\u0561\u0580\u0578\u057e\u0578"
    ],
    "name:kaz_x_preferred":[
        "\u0422\u0430\u043d\u043e\u0432\u0433\u0430\u0442\u0430\u0440"
    ],
    "name:kir_x_preferred":[
        "\u0422\u0430\u043d\u043e\u0432\u0433\u0430\u0442\u0430\u0440"
    ],
    "name:nor_x_preferred":[
        "Tangatarovo"
    ],
    "name:rus_x_preferred":[
        "\u0422\u0430\u043d\u0433\u0430\u0442\u0430\u0440\u043e\u0432\u043e"
    ],
    "name:tat_x_preferred":[
        "\u0422\u0430\u04a3\u0430\u0442\u0430\u0440"
    ],
    "wof:name":"Tangatarovo",
    "wof:placetype":"locality"
},
  "geometry": {"coordinates":[54.95224,55.78745],"type":"Point"}
}