{
  "type": "Feature",
  "properties": {
    "gn:admin1_code":"60",
    "gn:asciiname":"Lyutyye Bolota",
    "gn:country_code":"RU",
    "gn:dem":102,
    "gn:feature_class":"P",
    "gn:feature_code":"PPL",
    "gn:name":"Lyutyye Bolota",
    "gn:population":0,
    "gn:timezone":"Europe/Moscow",
    "iso:country":"RU",
    "name:rus_x_preferred":[
        "\u041b\u044e\u0442\u044b\u0435 \u0411\u043e\u043b\u043e\u0442\u0430"
    ],
    "name:und_x_variant":[
        "\u041b\u044e\u0442\u044b\u0435 \u0411\u043e\u043b\u043e\u0442\u0430"
    ],
    "wof:name":"Lyutyye Bolota",
    "wof:placetype":"locality"
},
  "geometry": {"coordinates":[29.16235,57.55939],"type":"Point"}
}