{
  "type": "Feature",
  "properties": {
    "gn:admin1_code":"77",
    "gn:asciiname":"Monchalovo",
    "gn:country_code":"RU",
    "gn:dem":206,
    "gn:feature_class":"P",
    "gn:feature_code":"PPL",
    "gn:name":"Monchalovo",
    "gn:population":0,
    "gn:timezone":"Europe/Moscow",
    "iso:country":"RU",
    "name:eng_x_preferred":[
        "Monchalovo"
    ],
    "name:nor_x_preferred":[
        "Mantsjalovo"
    ],
    "name:rus_x_preferred":[
        "\u041c\u0430\u043d\u0447\u0430\u043b\u043e\u0432\u043e"
    ],
    "name:rus_x_variant":[
        "\u041c\u043e\u043d\u0447\u0430\u043b\u043e\u0432\u043e"
    ],
    "name:und_x_variant":[
        "Manchalovo"
    ],
    "wof:name":"Monchalovo",
    "wof:placetype":"locality"
},
  "geometry": {"coordinates":[34.11878,56.23043000000001],"type":"Point"}
}