{
  "type": "Feature",
  "properties": {
    "iso:country":"RU",
    "name:rus_x_preferred":[
        "\u0411\u0438\u0440\u044e\u043b\u0451\u0432\u043e \u0417\u0430\u0301\u043f\u0430\u0434\u043d\u043e\u0435"
    ],
    "wof:name":"Biryulyovo Zapadnoye",
    "wof:placetype":"neighbourhood"
},
  "geometry": {"coordinates":[37.63549043383811,55.58761734376552],"type":"Point"}
}