{
  "type": "Feature",
  "properties": {
    "gn:admin1_code":"37.0",
    "gn:asciiname":"Adishchevo",
    "gn:country_code":"RU",
    "gn:dem":105,
    "gn:feature_class":"P",
    "gn:feature_code":"PPL",
    "gn:name":"Adishchevo",
    "gn:population":0,
    "gn:timezone":"Europe/Moscow",
    "iso:country":"RU",
    "name:che_x_preferred":[
        "\u0410\u0434\u0438\u0449\u0435\u0432\u043e"
    ],
    "name:eng_x_preferred":[
        "Adishchevo"
    ],
    "name:nor_x_preferred":[
        "Adisjtsjevo"
    ],
    "name:rus_x_preferred":[
        "\u0410\u0434\u0438\u0449\u0435\u0432\u043e"
    ],
    "wof:name":"Adishchevo",
    "wof:placetype":"locality"
},
  "geometry": {"coordinates":[42.1382,57.66356999999999],"type":"Point"}
}