{
  "type": "Feature",
  "properties": {
    "gn:admin1_code":"13",
    "gn:asciiname":"Obruchevka",
    "gn:country_code":"RU",
    "gn:dem":319,
    "gn:feature_class":"P",
    "gn:feature_code":"PPL",
    "gn:name":"Obruch\u00ebvka",
    "gn:population":0,
    "gn:timezone":"Asia/Yekaterinburg",
    "iso:country":"RU",
    "name:eng_x_preferred":[
        "Obruch\u00ebvaka"
    ],
    "name:nor_x_preferred":[
        "Obrutsjevka"
    ],
    "name:rus_x_preferred":[
        "\u041e\u0431\u0440\u0443\u0447\u0435\u0432\u043a\u0430"
    ],
    "name:rus_x_variant":[
        "\u041e\u0431\u0440\u0443\u0447\u0451\u0432\u043a\u0430"
    ],
    "name:und_x_variant":[
        "Obruchevski",
        "Obruch\u00ebvaka",
        "Obruch\u00ebvka",
        "\u041e\u0431\u0440\u0443\u0447\u0451\u0432\u043a\u0430"
    ],
    "wof:name":"Obruchevka",
    "wof:placetype":"locality"
},
  "geometry": {"coordinates":[59.20806,52.76778],"type":"Point"}
}