{
  "type": "Feature",
  "properties": {
    "gn:admin1_code":"30",
    "gn:asciiname":"Sergeyevka",
    "gn:country_code":"RU",
    "gn:dem":36,
    "gn:feature_class":"P",
    "gn:feature_code":"PPL",
    "gn:name":"Sergeyevka",
    "gn:population":0,
    "gn:timezone":"Asia/Vladivostok",
    "iso:country":"RU",
    "name:rus_x_preferred":[
        "\u0421\u0435\u0440\u0433\u0435\u0435\u0432\u043a\u0430"
    ],
    "name:und_x_variant":[
        "Licha",
        "Sergeyevskoye",
        "Litya",
        "Sergiyevskoye",
        "Sergeyevka",
        "\u0421\u0435\u0440\u0433\u0435\u0435\u0432\u043a\u0430"
    ],
    "wof:name":"Sergeyevka",
    "wof:placetype":"locality"
},
  "geometry": {"coordinates":[140.66165000000001,53.14708],"type":"Point"}
}