{
  "type": "Feature",
  "properties": {
    "gn:admin1_code":"75",
    "gn:asciiname":"Vilkiny",
    "gn:cc2":"RU",
    "gn:country_code":"RU",
    "gn:dem":92,
    "gn:feature_class":"P",
    "gn:feature_code":"PPL",
    "gn:name":"Vilkiny",
    "gn:population":0,
    "gn:timezone":"Asia/Tomsk",
    "iso:country":"RU",
    "name:und_x_variant":[
        "Yurty Vilkiny",
        "Vilkiny"
    ],
    "wof:name":"Vilkiny",
    "wof:placetype":"locality"
},
  "geometry": {"coordinates":[76.26666999999998,57.71666999999999],"type":"Point"}
}