{
  "type": "Feature",
  "properties": {
    "gn:admin1_code":"6",
    "gn:asciiname":"Pavyatinskaya",
    "gn:cc2":"RU",
    "gn:country_code":"RU",
    "gn:dem":17,
    "gn:feature_class":"P",
    "gn:feature_code":"PPL",
    "gn:name":"Pavyatinskaya",
    "gn:population":0,
    "gn:timezone":"Europe/Moscow",
    "iso:country":"RU",
    "name:rus_x_preferred":[
        "\u041f\u0430\u0432\u044f\u0442\u0438\u043d\u0441\u043a\u0430\u044f"
    ],
    "name:und_x_variant":[
        "Pavyaginskaya",
        "Pavyatinskaya",
        "\u041f\u0430\u0432\u044f\u0442\u0438\u043d\u0441\u043a\u0430\u044f"
    ],
    "wof:name":"Pavyatinskaya",
    "wof:placetype":"locality"
},
  "geometry": {"coordinates":[42.05,63.08333],"type":"Point"}
}