{
  "type": "Feature",
  "properties": {
    "gn:admin1_code":"45",
    "gn:asciiname":"Mazikino",
    "gn:country_code":"RU",
    "gn:dem":73,
    "gn:feature_class":"P",
    "gn:feature_code":"PPL",
    "gn:name":"Mazikino",
    "gn:population":0,
    "gn:timezone":"Europe/Moscow",
    "iso:country":"RU",
    "name:rus_x_preferred":[
        "\u041c\u0430\u0437\u0438\u043a\u0438\u043d\u043e"
    ],
    "name:und_x_variant":[
        "\u041c\u0430\u0437\u0438\u043a\u0438\u043d\u043e"
    ],
    "wof:name":"Mazikino",
    "wof:placetype":"locality"
},
  "geometry": {"coordinates":[46.7396,56.4054],"type":"Point"}
}