{
  "type": "Feature",
  "properties": {
    "gn:admin1_code":"91",
    "gn:asciiname":"Topol",
    "gn:country_code":"RU",
    "gn:dem":176,
    "gn:feature_class":"P",
    "gn:feature_code":"PPL",
    "gn:name":"Topol",
    "gn:population":0,
    "gn:timezone":"Asia/Krasnoyarsk",
    "iso:country":"RU",
    "name:bos_x_preferred":[
        "Topol"
    ],
    "name:ceb_x_preferred":[
        "Topol"
    ],
    "name:ces_x_preferred":[
        "Topol"
    ],
    "name:deu_x_preferred":[
        "Topol"
    ],
    "name:eng_x_preferred":[
        "Topol"
    ],
    "name:epo_x_preferred":[
        "Topol"
    ],
    "name:heb_x_preferred":[
        "\u05d8\u05d5\u05e4\u05d5\u05dc"
    ],
    "name:hrv_x_preferred":[
        "Topol"
    ],
    "name:hun_x_preferred":[
        "Topol"
    ],
    "name:nld_x_preferred":[
        "Topol"
    ],
    "name:nor_x_preferred":[
        "Topol"
    ],
    "name:pol_x_preferred":[
        "Topol"
    ],
    "name:rus_x_preferred":[
        "\u0422\u043e\u043f\u043e\u043b"
    ],
    "name:rus_x_variant":[
        "\u0422\u043e\u043f\u043e\u043b\u044c"
    ],
    "name:slv_x_preferred":[
        "Topol"
    ],
    "name:spa_x_preferred":[
        "Topol"
    ],
    "wof:name":"Topol",
    "wof:placetype":"locality"
},
  "geometry": {"coordinates":[95.11944,56.9425],"type":"Point"}
}