{
  "type": "Feature",
  "properties": {
    "gn:admin1_code":"91",
    "gn:asciiname":"Topol",
    "gn:country_code":"RU",
    "gn:dem":176,
    "gn:feature_class":"P",
    "gn:feature_code":"PPL",
    "gn:name":"Topol",
    "gn:population":0,
    "gn:timezone":"Asia/Krasnoyarsk",
    "iso:country":"RU",
    "name:eng_x_preferred":[
        "Topol"
    ],
    "name:nor_x_preferred":[
        "Topol"
    ],
    "name:rus_x_preferred":[
        "\u0422\u043e\u043f\u043e\u043b"
    ],
    "wof:name":"Topol",
    "wof:placetype":"locality"
},
  "geometry": {"coordinates":[95.11944,56.9425],"type":"Point"}
}