{
  "type": "Feature",
  "properties": {
    "gn:admin1_code":"93",
    "gn:asciiname":"Srednyaya Borzya",
    "gn:country_code":"RU",
    "gn:dem":501,
    "gn:feature_class":"P",
    "gn:feature_code":"PPL",
    "gn:name":"Srednyaya Borzya",
    "gn:population":0,
    "gn:timezone":"Asia/Chita",
    "iso:country":"RU",
    "name:rus_x_preferred":[
        "\u0421\u0440\u0435\u0434\u043d\u044f\u044f \u0411\u043e\u0440\u0437\u044f"
    ],
    "name:und_x_variant":[
        "Sredne Borzinskoye",
        "Srednyaya Borzya",
        "\u0421\u0440\u0435\u0434\u043d\u044f\u044f \u0411\u043e\u0440\u0437\u044f"
    ],
    "wof:name":"Srednyaya Borzya",
    "wof:placetype":"locality"
},
  "geometry": {"coordinates":[119.4866,50.91151],"type":"Point"}
}