{
  "type": "Feature",
  "properties": {
    "gn:admin1_code":"33.0",
    "gn:asciiname":"Salychi",
    "gn:country_code":"RU",
    "gn:dem":144,
    "gn:feature_class":"P",
    "gn:feature_code":"PPL",
    "gn:name":"Salychi",
    "gn:population":0,
    "gn:timezone":"Europe/Kirov",
    "iso:country":"RU",
    "name:rus_x_preferred":[
        "\u0421\u0430\u043b\u044b\u0447\u0438"
    ],
    "name:und_x_variant":[
        "\u0421\u0430\u043b\u044b\u0447\u0438"
    ],
    "wof:name":"Salychi",
    "wof:placetype":"locality"
},
  "geometry": {"coordinates":[48.05556,58.38721999999999],"type":"Point"}
}