{
  "type": "Feature",
  "properties": {
    "gn:admin1_code":"37",
    "gn:asciiname":"Neronovo",
    "gn:country_code":"RU",
    "gn:dem":185,
    "gn:feature_class":"P",
    "gn:feature_code":"PPL",
    "gn:name":"Neronovo",
    "gn:population":0,
    "gn:timezone":"Europe/Moscow",
    "iso:country":"RU",
    "name:rus_x_preferred":[
        "\u041d\u0435\u0440\u043e\u043d\u043e\u0432\u043e"
    ],
    "name:und_x_variant":[
        "\u041d\u0435\u0440\u043e\u043d\u043e\u0432\u043e"
    ],
    "wof:name":"Neronovo",
    "wof:placetype":"locality"
},
  "geometry": {"coordinates":[42.4437,58.8431],"type":"Point"}
}