{
  "type": "Feature",
  "properties": {
    "gn:admin1_code":"20",
    "gn:asciiname":"Zaslavskaya",
    "gn:country_code":"RU",
    "gn:dem":451,
    "gn:feature_class":"P",
    "gn:feature_code":"PPL",
    "gn:name":"Zaslavskaya",
    "gn:population":0,
    "gn:timezone":"Asia/Irkutsk",
    "iso:country":"RU",
    "name:eng_x_preferred":[
        "Zaslavskaya"
    ],
    "name:nor_x_preferred":[
        "Zaslavskaja"
    ],
    "name:rus_x_preferred":[
        "\u0417\u0430\u0441\u043b\u0430\u0432\u0441\u043a\u0430\u044f"
    ],
    "wof:name":"Zaslavskaya",
    "wof:placetype":"locality"
},
  "geometry": {"coordinates":[102.96980000000001,54.2188],"type":"Point"}
}