{
  "type": "Feature",
  "properties": {
    "gn:admin1_code":"65",
    "gn:asciiname":"Ol'gino",
    "gn:country_code":"RU",
    "gn:dem":54,
    "gn:feature_class":"P",
    "gn:feature_code":"PPL",
    "gn:name":"Ol\u2019gino",
    "gn:population":0,
    "gn:timezone":"Europe/Samara",
    "iso:country":"RU",
    "name:eng_x_preferred":[
        "Ol'gino"
    ],
    "name:nor_x_preferred":[
        "Olgino"
    ],
    "name:rus_x_preferred":[
        "Ol\u2019gino"
    ],
    "name:rus_x_variant":[
        "\u041e\u043b\u044c\u0433\u0438\u043d\u043e"
    ],
    "name:und_x_variant":[
        "\u041e\u043b\u044c\u0433\u0438\u043d\u043e",
        "Ol\u2019gino"
    ],
    "wof:name":"Ol'gino",
    "wof:placetype":"locality"
},
  "geometry": {"coordinates":[49.1184,52.8761],"type":"Point"}
}