{
  "type": "Feature",
  "properties": {
    "gn:admin1_code":"77.0",
    "gn:asciiname":"Belavino",
    "gn:country_code":"RU",
    "gn:dem":182,
    "gn:feature_class":"P",
    "gn:feature_code":"PPL",
    "gn:name":"Belavino",
    "gn:population":0,
    "gn:timezone":"Europe/Moscow",
    "iso:country":"RU",
    "name:eng_x_preferred":[
        "Belavino"
    ],
    "name:nor_x_preferred":[
        "Belavino"
    ],
    "name:rus_x_preferred":[
        "\u0411\u0435\u043b\u0430\u0432\u0438\u043d\u043e"
    ],
    "name:und_x_variant":[
        "Belavina"
    ],
    "wof:name":"Belavino",
    "wof:placetype":"locality"
},
  "geometry": {"coordinates":[34.87747,57.71339],"type":"Point"}
}