{
  "type": "Feature",
  "properties": {
    "gn:admin1_code":"86.0",
    "gn:asciiname":"Konnoye",
    "gn:country_code":"RU",
    "gn:dem":183,
    "gn:feature_class":"P",
    "gn:feature_code":"PPL",
    "gn:name":"Konnoye",
    "gn:population":0,
    "gn:timezone":"Europe/Moscow",
    "iso:country":"RU",
    "name:rus_x_preferred":[
        "\u041a\u043e\u043d\u043d\u043e\u0435"
    ],
    "wof:name":"Konnoye",
    "wof:placetype":"locality"
},
  "geometry": {"coordinates":[39.18886,50.16318],"type":"Point"}
}