{
  "type": "Feature",
  "properties": {
    "gn:admin1_code":"65",
    "gn:asciiname":"Grekovka",
    "gn:country_code":"RU",
    "gn:dem":71,
    "gn:feature_class":"P",
    "gn:feature_code":"PPL",
    "gn:name":"Grekovka",
    "gn:population":0,
    "gn:timezone":"Europe/Samara",
    "iso:country":"RU",
    "name:rus_x_preferred":[
        "\u0413\u0440\u0435\u043a\u043e\u0432\u043a\u0430"
    ],
    "wof:name":"Grekovka",
    "wof:placetype":"locality"
},
  "geometry": {"coordinates":[51.2477,52.6477],"type":"Point"}
}