{
  "type": "Feature",
  "properties": {
    "gn:admin1_code":"33.0",
    "gn:asciiname":"Uskovy",
    "gn:country_code":"RU",
    "gn:dem":125,
    "gn:feature_class":"P",
    "gn:feature_code":"PPL",
    "gn:name":"Uskovy",
    "gn:population":0,
    "gn:timezone":"Europe/Kirov",
    "iso:country":"RU",
    "name:rus_x_preferred":[
        "\u0423\u0441\u043a\u043e\u0432\u044b"
    ],
    "wof:name":"Uskovy",
    "wof:placetype":"locality"
},
  "geometry": {"coordinates":[48.92679,58.56664],"type":"Point"}
}