{
  "type": "Feature",
  "properties": {
    "gn:admin1_code":"38",
    "gn:asciiname":"Tarusin",
    "gn:country_code":"RU",
    "gn:dem":13,
    "gn:feature_class":"P",
    "gn:feature_code":"PPL",
    "gn:name":"Tarusin",
    "gn:population":0,
    "gn:timezone":"Europe/Moscow",
    "iso:country":"RU",
    "name:rus_x_preferred":[
        "\u0422\u0430\u0440\u0443\u0441\u0438\u043d"
    ],
    "wof:name":"Tarusin",
    "wof:placetype":"locality"
},
  "geometry": {"coordinates":[37.44466,44.89988],"type":"Point"}
}