{
  "type": "Feature",
  "properties": {
    "gn:admin1_code":"8",
    "gn:asciiname":"Imeni Kuybysheva",
    "gn:country_code":"RU",
    "gn:dem":251,
    "gn:feature_class":"P",
    "gn:feature_code":"PPL",
    "gn:name":"Imeni Kuybysheva",
    "gn:population":0,
    "gn:timezone":"Asia/Yekaterinburg",
    "iso:country":"RU",
    "name:rus_x_preferred":[
        "\u0418\u043c\u0435\u043d\u0438 \u041a\u0443\u0439\u0431\u044b\u0448\u0435\u0432\u0430"
    ],
    "wof:name":"Imeni Kuybysheva",
    "wof:placetype":"locality"
},
  "geometry": {"coordinates":[57.08333,54.38333000000001],"type":"Point"}
}