{
  "type": "Feature",
  "properties": {
    "gn:admin1_code":"71",
    "gn:asciiname":"Sarga",
    "gn:country_code":"RU",
    "gn:dem":229,
    "gn:feature_class":"P",
    "gn:feature_code":"PPL",
    "gn:name":"Sarga",
    "gn:population":0,
    "gn:timezone":"Asia/Yekaterinburg",
    "iso:country":"RU",
    "name:rus_x_preferred":[
        "\u0421\u0430\u0440\u0433\u0430"
    ],
    "name:und_x_variant":[
        "Syraya Sarga",
        "Grachi"
    ],
    "wof:name":"Sarga",
    "wof:placetype":"locality"
},
  "geometry": {"coordinates":[58.164,56.8096],"type":"Point"}
}