{
  "type": "Feature",
  "properties": {
    "gn:admin1_code":"19.0",
    "gn:asciiname":"Bashni",
    "gn:country_code":"RU",
    "gn:dem":765,
    "gn:feature_class":"P",
    "gn:feature_code":"PPL",
    "gn:name":"Bashni",
    "gn:population":0,
    "gn:timezone":"Europe/Moscow",
    "iso:country":"RU",
    "name:nor_x_preferred":[
        "Basjni"
    ],
    "name:rus_x_preferred":[
        "\u0411\u0430\u0448\u043d\u0438"
    ],
    "name:rus_x_variant":[
        "\u0421\u0442\u043e\u043b\u0431\u043e\u0432\u044b\u0435 \u0448\u0430\u0448\u043a\u0438"
    ],
    "name:zho_x_preferred":[
        "\u4fc4\u7f85\u65af\u758a\u8df3\u68cb"
    ],
    "wof:name":"Bashni",
    "wof:placetype":"locality"
},
  "geometry": {"coordinates":[45.01972,42.9575],"type":"Point"}
}