{
  "type": "Feature",
  "properties": {
    "gn:admin1_code":"19.0",
    "gn:asciiname":"Bashni",
    "gn:country_code":"RU",
    "gn:dem":765,
    "gn:feature_class":"P",
    "gn:feature_code":"PPL",
    "gn:name":"Bashni",
    "gn:population":0,
    "gn:timezone":"Europe/Moscow",
    "iso:country":"RU",
    "name:nor_x_preferred":[
        "Basjni"
    ],
    "name:rus_x_preferred":[
        "\u0411\u0430\u0448\u043d\u0438"
    ],
    "wof:name":"Bashni",
    "wof:placetype":"locality"
},
  "geometry": {"coordinates":[45.01972,42.9575],"type":"Point"}
}