{
  "type": "Feature",
  "properties": {
    "gn:admin1_code":"38",
    "gn:asciiname":"Sirotino",
    "gn:country_code":"RU",
    "gn:dem":64,
    "gn:feature_class":"P",
    "gn:feature_code":"PPL",
    "gn:name":"Sirotino",
    "gn:population":0,
    "gn:timezone":"Europe/Moscow",
    "iso:country":"RU",
    "name:rus_x_preferred":[
        "\u0421\u0438\u0440\u043e\u0442\u0438\u043d\u043e"
    ],
    "name:und_x_variant":[
        "\u0421\u0438\u0440\u043e\u0442\u0438\u043d\u043e"
    ],
    "wof:name":"Sirotino",
    "wof:placetype":"locality"
},
  "geometry": {"coordinates":[40.22368,46.48024],"type":"Point"}
}