{
  "type": "Feature",
  "properties": {
    "gn:admin1_code":"40",
    "gn:asciiname":"Verkhniye Peski",
    "gn:country_code":"RU",
    "gn:dem":150,
    "gn:feature_class":"P",
    "gn:feature_code":"PPL",
    "gn:name":"Verkhniye Peski",
    "gn:population":0,
    "gn:timezone":"Asia/Yekaterinburg",
    "iso:country":"RU",
    "name:rus_x_preferred":[
        "\u0412\u0435\u0440\u0445\u043d\u0438\u0435 \u041f\u0435\u0441\u043a\u0438"
    ],
    "name:und_x_variant":[
        "Peski",
        "Peskovskoye",
        "Verkhniye Peski"
    ],
    "wof:name":"Verkhniye Peski",
    "wof:placetype":"locality"
},
  "geometry": {"coordinates":[62.6009,56.1823],"type":"Point"}
}