{
  "type": "Feature",
  "properties": {
    "gn:admin1_code":"77",
    "gn:asciiname":"Novoselovo",
    "gn:country_code":"RU",
    "gn:dem":191,
    "gn:feature_class":"P",
    "gn:feature_code":"PPL",
    "gn:name":"Novos\u00eblovo",
    "gn:population":0,
    "gn:timezone":"Europe/Moscow",
    "iso:country":"RU",
    "name:rus_x_preferred":[
        "\u041d\u043e\u0432\u043e\u0441\u0451\u043b\u043e\u0432\u043e"
    ],
    "name:und_x_variant":[
        "Novos\u00eblovo",
        "\u041d\u043e\u0432\u043e\u0441\u0451\u043b\u043e\u0432\u043e"
    ],
    "wof:name":"Novoselovo",
    "wof:placetype":"locality"
},
  "geometry": {"coordinates":[34.47831,56.00614],"type":"Point"}
}