{
  "type": "Feature",
  "properties": {
    "gn:admin1_code":"23",
    "gn:asciiname":"Zhemchuzhnoye",
    "gn:country_code":"RU",
    "gn:dem":6,
    "gn:feature_class":"P",
    "gn:feature_code":"PPL",
    "gn:name":"Zhemchuzhnoye",
    "gn:population":0,
    "gn:timezone":"Europe/Kaliningrad",
    "iso:country":"RU",
    "name:deu_x_historical":[
        "Kirchschaaken"
    ],
    "name:deu_x_preferred":[
        "Kirchschaaken"
    ],
    "wof:name":"Zhemchuzhnoye",
    "wof:placetype":"locality"
},
  "geometry": {"coordinates":[20.68679,54.89709000000001],"type":"Point"}
}