{
  "type": "Feature",
  "properties": {
    "gn:admin1_code":"88",
    "gn:asciiname":"Pishchal'nikovo",
    "gn:country_code":"RU",
    "gn:dem":108,
    "gn:feature_class":"P",
    "gn:feature_code":"PPL",
    "gn:name":"Pishchal\u2019nikovo",
    "gn:population":0,
    "gn:timezone":"Europe/Moscow",
    "iso:country":"RU",
    "name:rus_x_preferred":[
        "\u041f\u0438\u0449\u0430\u043b\u044c\u043d\u0438\u043a\u043e\u0432\u043e"
    ],
    "name:und_x_variant":[
        "Pishchal\u2019nikovo"
    ],
    "wof:name":"Pishchal'nikovo",
    "wof:placetype":"locality"
},
  "geometry": {"coordinates":[40.38333,57.68333000000001],"type":"Point"}
}