{
  "type": "Feature",
  "properties": {
    "gn:admin1_code":"20",
    "gn:asciiname":"Tolmachevo",
    "gn:country_code":"RU",
    "gn:dem":488,
    "gn:feature_class":"P",
    "gn:feature_code":"PPL",
    "gn:name":"Tolmach\u00ebvo",
    "gn:population":0,
    "gn:timezone":"Asia/Irkutsk",
    "iso:country":"RU",
    "name:eng_x_preferred":[
        "Tolmach\u00ebvo"
    ],
    "name:nor_x_preferred":[
        "Tolmatsjeva"
    ],
    "name:rus_x_preferred":[
        "\u0422\u043e\u043b\u043c\u0430\u0447\u0435\u0432\u0430"
    ],
    "name:und_x_variant":[
        "Tolmacheva"
    ],
    "wof:name":"Tolmachevo",
    "wof:placetype":"locality"
},
  "geometry": {"coordinates":[105.53706,54.09724],"type":"Point"}
}