{
  "type": "Feature",
  "properties": {
    "gn:admin1_code":"60",
    "gn:asciiname":"Brod",
    "gn:country_code":"RU",
    "gn:dem":153,
    "gn:feature_class":"P",
    "gn:feature_code":"PPL",
    "gn:name":"Brod",
    "gn:population":0,
    "gn:timezone":"Europe/Moscow",
    "iso:country":"RU",
    "name:rus_x_preferred":[
        "\u0411\u0440\u043e\u0434"
    ],
    "name:und_x_variant":[
        "\u0411\u0440\u043e\u0434"
    ],
    "wof:name":"Brod",
    "wof:placetype":"locality"
},
  "geometry": {"coordinates":[30.6844,56.0641],"type":"Point"}
}