{
  "type": "Feature",
  "properties": {
    "gn:admin1_code":"67",
    "gn:asciiname":"Nizovka",
    "gn:country_code":"RU",
    "gn:dem":126,
    "gn:feature_class":"P",
    "gn:feature_code":"PPL",
    "gn:name":"Nizovka",
    "gn:population":0,
    "gn:timezone":"Europe/Saratov",
    "iso:country":"RU",
    "name:eng_x_preferred":[
        "Nizovka"
    ],
    "name:nor_x_preferred":[
        "Nizovka"
    ],
    "name:rus_x_preferred":[
        "\u041d\u0438\u0437\u043e\u0432\u043a\u0430"
    ],
    "name:und_x_variant":[
        "\u041d\u0438\u0437\u043e\u0432\u043a\u0430",
        "Nizovka"
    ],
    "wof:name":"Nizovka",
    "wof:placetype":"locality"
},
  "geometry": {"coordinates":[43.4843,51.1363],"type":"Point"}
}