{
  "type": "Feature",
  "properties": {
    "gn:admin1_code":"37",
    "gn:asciiname":"Il'inskoye",
    "gn:country_code":"RU",
    "gn:dem":213,
    "gn:feature_class":"P",
    "gn:feature_code":"PPL",
    "gn:name":"Il\u2019inskoye",
    "gn:population":0,
    "gn:timezone":"Europe/Moscow",
    "iso:country":"RU",
    "name:rus_x_preferred":[
        "\u0418\u043b\u044c\u0438\u043d\u0441\u043a\u043e\u0435"
    ],
    "name:und_x_variant":[
        "Il\u2019inskoye",
        "\u0418\u043b\u044c\u0438\u043d\u0441\u043a\u043e\u0435"
    ],
    "wof:name":"Il'inskoye",
    "wof:placetype":"locality"
},
  "geometry": {"coordinates":[42.76667,59.13333000000001],"type":"Point"}
}