{
  "type": "Feature",
  "properties": {
    "gn:admin1_code":"11",
    "gn:asciiname":"Bon",
    "gn:country_code":"RU",
    "gn:dem":820,
    "gn:feature_class":"P",
    "gn:feature_code":"PPL",
    "gn:name":"Bon",
    "gn:population":0,
    "gn:timezone":"Asia/Irkutsk",
    "iso:country":"RU",
    "wof:name":"Bon",
    "wof:placetype":"locality"
},
  "geometry": {"coordinates":[105.06222,50.6125],"type":"Point"}
}