{
  "type": "Feature",
  "properties": {
    "gn:admin1_code":"11",
    "gn:asciiname":"Bon",
    "gn:country_code":"RU",
    "gn:dem":820,
    "gn:feature_class":"P",
    "gn:feature_code":"PPL",
    "gn:name":"Bon",
    "gn:population":0,
    "gn:timezone":"Asia/Irkutsk",
    "iso:country":"RU",
    "name:ben_x_preferred":[
        "\u09ac\u09a8"
    ],
    "name:bod_x_preferred":[
        "\u0f56\u0f7c\u0f53\u0f0d"
    ],
    "name:bul_x_preferred":[
        "\u0411\u043e\u043d"
    ],
    "name:bxr_x_preferred":[
        "\u0411\u043e\u043c\u0431\u043e"
    ],
    "name:cat_x_preferred":[
        "Bon"
    ],
    "name:ces_x_preferred":[
        "B\u00f6n"
    ],
    "name:dan_x_preferred":[
        "B\u00f6n-religionen"
    ],
    "name:deu_x_preferred":[
        "B\u00f6n"
    ],
    "name:dzo_x_preferred":[
        "\u0f56\u0f7c\u0f53\u0f0d"
    ],
    "name:ell_x_preferred":[
        "\u039c\u03c0\u03bf\u03bd"
    ],
    "name:est_x_preferred":[
        "B\u00f6n"
    ],
    "name:eus_x_preferred":[
        "Bon"
    ],
    "name:fin_x_preferred":[
        "B\u00f6n"
    ],
    "name:fra_x_preferred":[
        "B\u00f6n"
    ],
    "name:hin_x_preferred":[
        "\u092c\u094b\u0928 \u0927\u0930\u094d\u092e"
    ],
    "name:hun_x_preferred":[
        "Bon"
    ],
    "name:ind_x_preferred":[
        "Bon"
    ],
    "name:ita_x_preferred":[
        "B\u00f6n"
    ],
    "name:jpn_x_preferred":[
        "\u30dc\u30f3\u6559"
    ],
    "name:kat_x_preferred":[
        "\u10d1\u10dd\u10dc\u10d8"
    ],
    "name:lit_x_preferred":[
        "Bonas"
    ],
    "name:mal_x_preferred":[
        "\u0d2c\u0d4b\u0d7a \u0d2e\u0d24\u0d02"
    ],
    "name:nep_x_preferred":[
        "\u092c\u094b\u0928 \u0927\u0930\u094d\u092e"
    ],
    "name:nld_x_preferred":[
        "B\u00f6n"
    ],
    "name:nno_x_preferred":[
        "B\u00f6n"
    ],
    "name:nor_x_preferred":[
        "B\u00f8n"
    ],
    "name:pnb_x_preferred":[
        "\u0628\u0648\u0646 \u062f\u06be\u0631\u0645"
    ],
    "name:pol_x_preferred":[
        "B\u00f6n"
    ],
    "name:por_x_preferred":[
        "B\u00f6n"
    ],
    "name:ron_x_preferred":[
        "Bon"
    ],
    "name:rus_x_preferred":[
        "\u0411\u043e\u043d"
    ],
    "name:sat_x_preferred":[
        "\u1c75\u1c5a\u1c71 \u1c6b\u1c77\u1c5a\u1c68\u1c5a\u1c62"
    ],
    "name:slk_x_preferred":[
        "B\u00f6nizmus"
    ],
    "name:spa_x_preferred":[
        "B\u00f6n"
    ],
    "name:swe_x_preferred":[
        "Bon"
    ],
    "name:tam_x_preferred":[
        "\u0baa\u0bcb\u0ba9\u0bcd \u0baa\u0bcc\u0ba4\u0bcd\u0ba4\u0bae\u0bcd"
    ],
    "name:tur_x_preferred":[
        "B\u00f6n"
    ],
    "name:tyv_x_preferred":[
        "\u0411\u043e\u043d"
    ],
    "name:ukr_x_preferred":[
        "\u0411\u043e\u043d"
    ],
    "name:urd_x_preferred":[
        "\u0628\u0648\u0646"
    ],
    "wof:name":"Bon",
    "wof:placetype":"locality"
},
  "geometry": {"coordinates":[105.06222,50.6125],"type":"Point"}
}