{
  "type": "Feature",
  "properties": {
    "gn:admin1_code":"10",
    "gn:asciiname":"Nikolayevka",
    "gn:country_code":"RU",
    "gn:dem":169,
    "gn:feature_class":"P",
    "gn:feature_code":"PPL",
    "gn:name":"Nikolayevka",
    "gn:population":0,
    "gn:timezone":"Europe/Moscow",
    "iso:country":"RU",
    "name:eng_x_preferred":[
        "Nikolayevka"
    ],
    "name:nor_x_preferred":[
        "Nikolajevka"
    ],
    "name:rus_x_preferred":[
        "\u041d\u0438\u043a\u043e\u043b\u0430\u0435\u0432\u043a\u0430"
    ],
    "name:und_x_variant":[
        "\u041d\u0438\u043a\u043e\u043b\u0430\u0435\u0432\u043a\u0430",
        "Nikolayevka"
    ],
    "wof:name":"Nikolayevka",
    "wof:placetype":"locality"
},
  "geometry": {"coordinates":[31.4398,53.1916],"type":"Point"}
}