{
  "type": "Feature",
  "properties": {
    "gn:admin1_code":"8",
    "gn:asciiname":"Novyy Kichkinyash",
    "gn:country_code":"RU",
    "gn:dem":241,
    "gn:feature_class":"P",
    "gn:feature_code":"PPL",
    "gn:name":"Novyy Kichkinyash",
    "gn:population":0,
    "gn:timezone":"Asia/Yekaterinburg",
    "iso:country":"RU",
    "name:rus_x_preferred":[
        "\u041d\u043e\u0432\u044b\u0439 \u041a\u0438\u0447\u043a\u0438\u043d\u044f\u0448"
    ],
    "wof:name":"Novyy Kichkinyash",
    "wof:placetype":"locality"
},
  "geometry": {"coordinates":[54.0306,54.8987],"type":"Point"}
}