{
  "type": "Feature",
  "properties": {
    "gn:admin1_code":"25",
    "gn:asciiname":"Zhiletovo",
    "gn:country_code":"RU",
    "gn:dem":184,
    "gn:feature_class":"P",
    "gn:feature_code":"PPL",
    "gn:name":"Zhiletovo",
    "gn:population":0,
    "gn:timezone":"Europe/Moscow",
    "iso:country":"RU",
    "name:und_x_variant":[
        "Zheletovo",
        "Zhiletovo"
    ],
    "wof:name":"Zhiletovo",
    "wof:placetype":"locality"
},
  "geometry": {"coordinates":[35.28167,54.57306],"type":"Point"}
}