{
  "type": "Feature",
  "properties": {
    "gn:admin1_code":"51.0",
    "gn:asciiname":"Anosovo",
    "gn:country_code":"RU",
    "gn:dem":160,
    "gn:feature_class":"P",
    "gn:feature_code":"PPL",
    "gn:name":"Anosovo",
    "gn:population":0,
    "gn:timezone":"Europe/Moscow",
    "iso:country":"RU",
    "name:eng_x_preferred":[
        "Anosovo"
    ],
    "name:nor_x_preferred":[
        "Anosovo"
    ],
    "name:rus_x_preferred":[
        "\u0410\u043d\u043e\u0441\u043e\u0432\u043e"
    ],
    "name:und_x_variant":[
        "\u0410\u043d\u043e\u0441\u043e\u0432\u043e",
        "Anosovo"
    ],
    "wof:name":"Anosovo",
    "wof:placetype":"locality"
},
  "geometry": {"coordinates":[45.29273,55.06811999999999],"type":"Point"}
}