{
  "type": "Feature",
  "properties": {
    "gn:admin1_code":"6",
    "gn:asciiname":"Shamanikha",
    "gn:country_code":"RU",
    "gn:dem":98,
    "gn:feature_class":"P",
    "gn:feature_code":"PPL",
    "gn:name":"Shamanikha",
    "gn:population":0,
    "gn:timezone":"Europe/Moscow",
    "iso:country":"RU",
    "name:rus_x_preferred":[
        "\u0428\u0430\u043c\u0430\u043d\u0438\u0445\u0430"
    ],
    "wof:name":"Shamanikha",
    "wof:placetype":"locality"
},
  "geometry": {"coordinates":[48.1478,61.0892],"type":"Point"}
}