{
  "type": "Feature",
  "properties": {
    "gn:admin1_code":"51.0",
    "gn:asciiname":"Dyrino",
    "gn:country_code":"RU",
    "gn:dem":118,
    "gn:feature_class":"P",
    "gn:feature_code":"PPL",
    "gn:name":"Dyrino",
    "gn:population":0,
    "gn:timezone":"Europe/Moscow",
    "iso:country":"RU",
    "name:und_x_variant":[
        "Durino",
        "Cher\u00ebmushki",
        "Dyrino"
    ],
    "wof:name":"Dyrino",
    "wof:placetype":"locality"
},
  "geometry": {"coordinates":[43.79358,56.755],"type":"Point"}
}