{
  "type": "Feature",
  "properties": {
    "gn:admin1_code":"77",
    "gn:asciiname":"Zavidovo",
    "gn:country_code":"RU",
    "gn:dem":143,
    "gn:feature_class":"P",
    "gn:feature_code":"PPL",
    "gn:name":"Zavidovo",
    "gn:population":0,
    "gn:timezone":"Europe/Moscow",
    "iso:country":"RU",
    "name:ceb_x_preferred":[
        "Zavidovo"
    ],
    "name:che_x_preferred":[
        "\u0417\u0430\u0432\u0438\u0434\u043e\u0432\u043e"
    ],
    "name:epo_x_preferred":[
        "Zavidovo"
    ],
    "name:fin_x_preferred":[
        "Zavidovo"
    ],
    "name:hye_x_preferred":[
        "\u0536\u0561\u057e\u056b\u0564\u0578\u057e\u0578"
    ],
    "name:rus_x_preferred":[
        "\u0417\u0430\u0432\u0438\u0434\u043e\u0432\u043e"
    ],
    "name:und_x_variant":[
        "\u0417\u0430\u0432\u0438\u0434\u043e\u0432\u043e"
    ],
    "name:zho_x_preferred":[
        "\u624e\u7ef4\u591a\u6c83"
    ],
    "wof:name":"Zavidovo",
    "wof:placetype":"locality"
},
  "geometry": {"coordinates":[36.9402,56.9378],"type":"Point"}
}