{
  "type": "Feature",
  "properties": {
    "gn:admin1_code":"65.0",
    "gn:asciiname":"Nizhnyaya Tuarma",
    "gn:country_code":"RU",
    "gn:dem":129,
    "gn:feature_class":"P",
    "gn:feature_code":"PPL",
    "gn:name":"Nizhnyaya Tuarma",
    "gn:population":0,
    "gn:timezone":"Europe/Samara",
    "iso:country":"RU",
    "name:rus_x_preferred":[
        "\u041d\u0438\u0436\u043d\u044f\u044f \u0422\u0443\u0430\u0440\u043c\u0430"
    ],
    "wof:name":"Nizhnyaya Tuarma",
    "wof:placetype":"locality"
},
  "geometry": {"coordinates":[51.6487,54.5373],"type":"Point"}
}