{
  "type": "Feature",
  "properties": {
    "gn:admin1_code":"57",
    "gn:asciiname":"Rostok",
    "gn:country_code":"RU",
    "gn:dem":204,
    "gn:feature_class":"P",
    "gn:feature_code":"PPL",
    "gn:name":"Rostok",
    "gn:population":0,
    "gn:timezone":"Europe/Moscow",
    "iso:country":"RU",
    "name:rus_x_preferred":[
        "\u0420\u043e\u0441\u0442\u043e\u043a"
    ],
    "name:und_x_variant":[
        "\u0420\u043e\u0441\u0442\u043e\u043a"
    ],
    "wof:name":"Rostok",
    "wof:placetype":"locality"
},
  "geometry": {"coordinates":[44.0208,53.2846],"type":"Point"}
}