{
  "type": "Feature",
  "properties": {
    "gn:admin1_code":"75",
    "gn:asciiname":"Uzen'",
    "gn:country_code":"RU",
    "gn:dem":122,
    "gn:feature_class":"P",
    "gn:feature_code":"PPL",
    "gn:name":"Uzen\u2019",
    "gn:population":0,
    "gn:timezone":"Asia/Tomsk",
    "iso:country":"RU",
    "name:eng_x_preferred":[
        "Uzen'"
    ],
    "name:nor_x_preferred":[
        "Uzen"
    ],
    "name:rus_x_preferred":[
        "\u0423\u0437\u0435\u043d\u044c"
    ],
    "name:und_x_variant":[
        "Uzen\u2019"
    ],
    "wof:name":"Uzen'",
    "wof:placetype":"locality"
},
  "geometry": {"coordinates":[86.22150000000001,57.297],"type":"Point"}
}