{
  "type": "Feature",
  "properties": {
    "gn:admin1_code":"51",
    "gn:asciiname":"Kudreshki",
    "gn:country_code":"RU",
    "gn:dem":122,
    "gn:feature_class":"P",
    "gn:feature_code":"PPL",
    "gn:name":"Kudreshki",
    "gn:population":0,
    "gn:timezone":"Europe/Moscow",
    "iso:country":"RU",
    "name:nor_x_preferred":[
        "Kudresjki"
    ],
    "name:rus_x_preferred":[
        "\u041a\u0443\u0434\u0440\u0435\u0448\u043a\u0438"
    ],
    "wof:name":"Kudreshki",
    "wof:placetype":"locality"
},
  "geometry": {"coordinates":[43.35791,56.05096],"type":"Point"}
}