{
  "type": "Feature",
  "properties": {
    "gn:admin1_code":"4",
    "gn:asciiname":"Podsnezhnoye",
    "gn:country_code":"RU",
    "gn:dem":136,
    "gn:feature_class":"P",
    "gn:feature_code":"PPL",
    "gn:name":"Podsnezhnoye",
    "gn:population":0,
    "gn:timezone":"Asia/Barnaul",
    "iso:country":"RU",
    "name:rus_x_preferred":[
        "\u041f\u043e\u0434\u0441\u043d\u0435\u0436\u043d\u043e\u0435"
    ],
    "wof:name":"Podsnezhnoye",
    "wof:placetype":"locality"
},
  "geometry": {"coordinates":[79.01666999999998,53.31667],"type":"Point"}
}