{
  "type": "Feature",
  "properties": {
    "gn:admin1_code":"89",
    "gn:asciiname":"Danilovka",
    "gn:country_code":"RU",
    "gn:dem":42,
    "gn:feature_class":"P",
    "gn:feature_code":"PPL",
    "gn:name":"Danilovka",
    "gn:population":0,
    "gn:timezone":"Asia/Vladivostok",
    "iso:country":"RU",
    "name:eng_x_preferred":[
        "Danilovka"
    ],
    "name:nor_x_preferred":[
        "Danilovka"
    ],
    "name:rus_x_preferred":[
        "\u0414\u0430\u043d\u0438\u043b\u043e\u0432\u043a\u0430"
    ],
    "name:und_x_variant":[
        "Danilovskoye"
    ],
    "wof:name":"Danilovka",
    "wof:placetype":"locality"
},
  "geometry": {"coordinates":[134.60807,48.59242],"type":"Point"}
}