{
  "type": "Feature",
  "properties": {
    "gn:admin1_code":"27",
    "gn:asciiname":"Nizhnyaya Teberda",
    "gn:country_code":"RU",
    "gn:dem":1035,
    "gn:feature_class":"P",
    "gn:feature_code":"PPL",
    "gn:name":"Nizhnyaya Teberda",
    "gn:population":0,
    "gn:timezone":"Europe/Moscow",
    "iso:country":"RU",
    "name:eng_x_preferred":[
        "Nizhnyaya Teberda"
    ],
    "name:nor_x_preferred":[
        "Nizjnjaja Teberda"
    ],
    "name:rus_x_preferred":[
        "\u041d\u0438\u0436\u043d\u044f\u044f \u0422\u0435\u0431\u0435\u0440\u0434\u0430"
    ],
    "name:und_x_variant":[
        "Mzisa",
        "Nizhne-Teberdinskiy",
        "Nizhniy Teberda"
    ],
    "wof:name":"Nizhnyaya Teberda",
    "wof:placetype":"locality"
},
  "geometry": {"coordinates":[41.87728,43.63772],"type":"Point"}
}