{
  "type": "Feature",
  "properties": {
    "gn:admin1_code":"51",
    "gn:asciiname":"Kodochigi",
    "gn:country_code":"RU",
    "gn:dem":114,
    "gn:feature_class":"P",
    "gn:feature_code":"PPL",
    "gn:name":"Kodochigi",
    "gn:population":0,
    "gn:timezone":"Europe/Moscow",
    "iso:country":"RU",
    "name:und_x_variant":[
        "Kodychigi",
        "Kodochigi"
    ],
    "wof:name":"Kodochigi",
    "wof:placetype":"locality"
},
  "geometry": {"coordinates":[42.92878,56.74789000000001],"type":"Point"}
}