{
  "type": "Feature",
  "properties": {
    "gn:admin1_code":"86.0",
    "gn:asciiname":"Brazhnikovo",
    "gn:country_code":"RU",
    "gn:dem":207,
    "gn:feature_class":"P",
    "gn:feature_code":"PPL",
    "gn:name":"Brazhnikovo",
    "gn:population":0,
    "gn:timezone":"Europe/Moscow",
    "iso:country":"RU",
    "name:rus_x_preferred":[
        "\u0411\u0440\u0430\u0436\u043d\u0438\u043a\u043e\u0432\u043e"
    ],
    "wof:name":"Brazhnikovo",
    "wof:placetype":"locality"
},
  "geometry": {"coordinates":[40.8999,50.9186],"type":"Point"}
}