{
  "type": "Feature",
  "properties": {
    "gn:admin1_code":"59",
    "gn:asciiname":"Kustanay",
    "gn:cc2":"RU",
    "gn:country_code":"RU",
    "gn:dem":118,
    "gn:feature_class":"P",
    "gn:feature_code":"PPL",
    "gn:name":"Kustanay",
    "gn:population":0,
    "gn:timezone":"Asia/Vladivostok",
    "iso:country":"RU",
    "name:rus_x_preferred":[
        "\u041a\u0443\u0441\u0442\u0430\u043d\u0430\u0439"
    ],
    "name:und_x_variant":[
        "Kusutanai",
        "Kustanay"
    ],
    "wof:name":"Kustanay",
    "wof:placetype":"locality"
},
  "geometry": {"coordinates":[134.68333000000001,45.81667],"type":"Point"}
}