{
  "type": "Feature",
  "properties": {
    "gn:admin1_code":"69",
    "gn:asciiname":"Mamyrkino",
    "gn:country_code":"RU",
    "gn:dem":184,
    "gn:feature_class":"P",
    "gn:feature_code":"PPL",
    "gn:name":"Mamyrkino",
    "gn:population":0,
    "gn:timezone":"Europe/Moscow",
    "iso:country":"RU",
    "wof:name":"Mamyrkino",
    "wof:placetype":"locality"
},
  "geometry": {"coordinates":[33.34262,54.93532],"type":"Point"}
}