{
  "type": "Feature",
  "properties": {
    "gn:admin1_code":"7",
    "gn:asciiname":"Nizhnelebyazh'ye",
    "gn:country_code":"RU",
    "gn:dem":-24,
    "gn:feature_class":"P",
    "gn:feature_code":"PPL",
    "gn:name":"Nizhnelebyazh\u2019ye",
    "gn:population":0,
    "gn:timezone":"Europe/Astrakhan",
    "iso:country":"RU",
    "name:eng_x_preferred":[
        "Nizhne-Lebyazh'ye"
    ],
    "name:nor_x_preferred":[
        "Nizjnelebjazje"
    ],
    "name:rus_x_preferred":[
        "\u041d\u0438\u0436\u043d\u0435\u043b\u0435\u0431\u044f\u0436\u044c\u0435"
    ],
    "name:und_x_variant":[
        "Nizhnelebyazh\u2019ye",
        "Nizhneye Lebyazh\u2019ye"
    ],
    "wof:name":"Nizhnelebyazh'ye",
    "wof:placetype":"locality"
},
  "geometry": {"coordinates":[47.8839,46.6902],"type":"Point"}
}