{
  "type": "Feature",
  "properties": {
    "gn:admin1_code":"55",
    "gn:asciiname":"Kyzyl-Dzhar",
    "gn:country_code":"RU",
    "gn:dem":258,
    "gn:feature_class":"P",
    "gn:feature_code":"PPL",
    "gn:name":"Kyzyl-Dzhar",
    "gn:population":0,
    "gn:timezone":"Asia/Yekaterinburg",
    "iso:country":"RU",
    "wof:name":"Kyzyl-Dzhar",
    "wof:placetype":"locality"
},
  "geometry": {"coordinates":[59.56667,50.83333],"type":"Point"}
}