{
  "type": "Feature",
  "properties": {
    "gn:admin1_code":"55",
    "gn:asciiname":"Khersonka",
    "gn:country_code":"RU",
    "gn:dem":374,
    "gn:feature_class":"P",
    "gn:feature_code":"PPL",
    "gn:name":"Khersonka",
    "gn:population":0,
    "gn:timezone":"Asia/Yekaterinburg",
    "iso:country":"RU",
    "name:rus_x_preferred":[
        "\u0425\u0435\u0440\u0441\u043e\u043d\u043a\u0430"
    ],
    "name:und_x_variant":[
        "Novo-Nikolayevskiy",
        "Khersonka"
    ],
    "wof:name":"Khersonka",
    "wof:placetype":"locality"
},
  "geometry": {"coordinates":[57.6709,51.4324],"type":"Point"}
}