{
  "type": "Feature",
  "properties": {
    "gn:admin1_code":"77",
    "gn:asciiname":"Shiryatino",
    "gn:country_code":"RU",
    "gn:dem":193,
    "gn:feature_class":"P",
    "gn:feature_code":"PPL",
    "gn:name":"Shiryatino",
    "gn:population":0,
    "gn:timezone":"Europe/Moscow",
    "iso:country":"RU",
    "name:rus_x_preferred":[
        "\u0428\u0438\u0440\u044f\u0442\u0438\u043d\u043e"
    ],
    "name:und_x_variant":[
        "\u0428\u0438\u0440\u044f\u0442\u0438\u043d\u043e"
    ],
    "wof:name":"Shiryatino",
    "wof:placetype":"locality"
},
  "geometry": {"coordinates":[37.1619,57.6167],"type":"Point"}
}