{
  "type": "Feature",
  "properties": {
    "gn:admin1_code":"33.0",
    "gn:asciiname":"Yugunur",
    "gn:country_code":"RU",
    "gn:dem":120,
    "gn:feature_class":"P",
    "gn:feature_code":"PPL",
    "gn:name":"Yugunur",
    "gn:population":0,
    "gn:timezone":"Europe/Kirov",
    "iso:country":"RU",
    "name:rus_x_preferred":[
        "\u042e\u0433\u0443\u043d\u0443\u0440"
    ],
    "wof:name":"Yugunur",
    "wof:placetype":"locality"
},
  "geometry": {"coordinates":[47.893,57.463],"type":"Point"}
}