{
  "type": "Feature",
  "properties": {
    "gn:admin1_code":"62",
    "gn:asciiname":"Poselok Svobody",
    "gn:country_code":"RU",
    "gn:dem":179,
    "gn:feature_class":"P",
    "gn:feature_code":"PPL",
    "gn:name":"Pos\u00eblok Svobody",
    "gn:population":0,
    "gn:timezone":"Europe/Moscow",
    "iso:country":"RU",
    "name:rus_x_preferred":[
        "\u041f\u043e\u0441\u0451\u043b\u043e\u043a \u0421\u0432\u043e\u0431\u043e\u0434\u044b"
    ],
    "name:und_x_variant":[
        "Pos\u00eblok Svobody"
    ],
    "wof:name":"Poselok Svobody",
    "wof:placetype":"locality"
},
  "geometry": {"coordinates":[39.7289,54.4428],"type":"Point"}
}