{
  "type": "Feature",
  "properties": {
    "gn:admin1_code":"8",
    "gn:asciiname":"Staryy Ashit",
    "gn:country_code":"RU",
    "gn:dem":147,
    "gn:feature_class":"P",
    "gn:feature_code":"PPL",
    "gn:name":"Staryy Ashit",
    "gn:population":0,
    "gn:timezone":"Asia/Yekaterinburg",
    "iso:country":"RU",
    "name:rus_x_preferred":[
        "\u0421\u0442\u0430\u0440\u044b\u0439 \u0410\u0448\u0438\u0442"
    ],
    "name:und_x_variant":[
        "Staroashitovo",
        "Staryy Ashit",
        "\u0421\u0442\u0430\u0440\u044b\u0439 \u0410\u0448\u0438\u0442"
    ],
    "wof:name":"Staryy Ashit",
    "wof:placetype":"locality"
},
  "geometry": {"coordinates":[54.64885,55.89006],"type":"Point"}
}