{
  "type": "Feature",
  "properties": {
    "gn:admin1_code":"6",
    "gn:asciiname":"Safonovo",
    "gn:country_code":"RU",
    "gn:dem":50,
    "gn:feature_class":"P",
    "gn:feature_code":"PPL",
    "gn:name":"Safonovo",
    "gn:population":0,
    "gn:timezone":"Europe/Moscow",
    "iso:country":"RU",
    "name:bel_x_preferred":[
        "\u0421\u0430\u0444\u043e\u043d\u0430\u0432\u0430"
    ],
    "name:ceb_x_preferred":[
        "Safonovo"
    ],
    "name:ces_x_preferred":[
        "Safonovo"
    ],
    "name:deu_x_preferred":[
        "Safonowo"
    ],
    "name:eng_x_preferred":[
        "Safonovo"
    ],
    "name:ita_x_preferred":[
        "Safonovo"
    ],
    "name:nld_x_preferred":[
        "Safonovo"
    ],
    "name:nor_x_preferred":[
        "Safonovo"
    ],
    "name:rus_x_preferred":[
        "\u0421\u0430\u0444\u043e\u043d\u043e\u0432\u043e"
    ],
    "name:tat_x_preferred":[
        "\u0421\u0430\u0444\u043e\u043d\u043e\u0432\u043e"
    ],
    "name:und_x_variant":[
        "\u0421\u0430\u0444\u043e\u043d\u043e\u0432\u043e",
        "Safonovo"
    ],
    "wof:name":"Safonovo",
    "wof:placetype":"locality"
},
  "geometry": {"coordinates":[47.6921,65.66889999999999],"type":"Point"}
}