{
  "type": "Feature",
  "properties": {
    "gn:admin1_code":"57",
    "gn:asciiname":"Russkaya Muromka",
    "gn:country_code":"RU",
    "gn:dem":201,
    "gn:feature_class":"P",
    "gn:feature_code":"PPL",
    "gn:name":"Russkaya Muromka",
    "gn:population":0,
    "gn:timezone":"Europe/Moscow",
    "iso:country":"RU",
    "name:rus_x_preferred":[
        "\u0420\u0443\u0441\u0441\u043a\u0430\u044f \u041c\u0443\u0440\u043e\u043c\u043a\u0430"
    ],
    "name:und_x_variant":[
        "\u0420\u0443\u0441\u0441\u043a\u0430\u044f \u041c\u0443\u0440\u043e\u043c\u043a\u0430"
    ],
    "wof:name":"Russkaya Muromka",
    "wof:placetype":"locality"
},
  "geometry": {"coordinates":[43.68139,53.425],"type":"Point"}
}