{
  "type": "Feature",
  "properties": {
    "gn:admin1_code":"47",
    "gn:asciiname":"Pavleyevo",
    "gn:country_code":"RU",
    "gn:dem":147,
    "gn:feature_class":"P",
    "gn:feature_code":"PPL",
    "gn:name":"Pavleyevo",
    "gn:population":0,
    "gn:timezone":"Europe/Moscow",
    "iso:country":"RU",
    "name:rus_x_preferred":[
        "\u041f\u0430\u0432\u043b\u0435\u0435\u0432\u043e"
    ],
    "name:und_x_variant":[
        "\u041f\u0430\u0432\u043b\u0435\u0435\u0432\u043e"
    ],
    "wof:name":"Pavleyevo",
    "wof:placetype":"locality"
},
  "geometry": {"coordinates":[38.54628,55.08077],"type":"Point"}
}