{
  "type": "Feature",
  "properties": {
    "gn:admin1_code":"51",
    "gn:asciiname":"Martyushikha",
    "gn:country_code":"RU",
    "gn:dem":115,
    "gn:feature_class":"P",
    "gn:feature_code":"PPL",
    "gn:name":"Martyushikha",
    "gn:population":0,
    "gn:timezone":"Europe/Moscow",
    "iso:country":"RU",
    "name:rus_x_preferred":[
        "\u041c\u0430\u0440\u0442\u044e\u0448\u0438\u0445\u0430"
    ],
    "name:und_x_variant":[
        "Matyusnikha",
        "Martyushikha",
        "\u041c\u0430\u0440\u0442\u044e\u0448\u0438\u0445\u0430"
    ],
    "wof:name":"Martyushikha",
    "wof:placetype":"locality"
},
  "geometry": {"coordinates":[42.3986,55.7042],"type":"Point"}
}