{
  "type": "Feature",
  "properties": {
    "gn:admin1_code":"33.0",
    "gn:asciiname":"Mal'shchukovy",
    "gn:country_code":"RU",
    "gn:dem":126,
    "gn:feature_class":"P",
    "gn:feature_code":"PPL",
    "gn:name":"Mal\u2019shchukovy",
    "gn:population":0,
    "gn:timezone":"Europe/Kirov",
    "iso:country":"RU",
    "name:rus_x_preferred":[
        "\u041c\u0430\u043b\u044c\u0449\u0443\u043a\u043e\u0432\u044b"
    ],
    "name:und_x_variant":[
        "Mal\u2019shchukovy",
        "\u041c\u0430\u043b\u044c\u0449\u0443\u043a\u043e\u0432\u044b"
    ],
    "wof:name":"Mal'shchukovy",
    "wof:placetype":"locality"
},
  "geometry": {"coordinates":[48.6959,58.5863],"type":"Point"}
}