{
  "type": "Feature",
  "properties": {
    "gn:admin1_code":"86",
    "gn:asciiname":"Tumanovka",
    "gn:country_code":"RU",
    "gn:dem":178,
    "gn:feature_class":"P",
    "gn:feature_code":"PPL",
    "gn:name":"Tumanovka",
    "gn:population":0,
    "gn:timezone":"Europe/Moscow",
    "iso:country":"RU",
    "name:rus_x_preferred":[
        "\u0422\u0443\u043c\u0430\u043d\u043e\u0432\u043a\u0430"
    ],
    "name:und_x_variant":[
        "Tamanovka",
        "Tomanovka",
        "Tumanovka"
    ],
    "wof:name":"Tumanovka",
    "wof:placetype":"locality"
},
  "geometry": {"coordinates":[40.2675,50.7368],"type":"Point"}
}