{
  "type": "Feature",
  "properties": {
    "gn:admin1_code":"7",
    "gn:asciiname":"Latanov",
    "gn:country_code":"RU",
    "gn:dem":18,
    "gn:feature_class":"P",
    "gn:feature_code":"PPL",
    "gn:name":"Latanov",
    "gn:population":0,
    "gn:timezone":"Europe/Astrakhan",
    "iso:country":"RU",
    "name:rus_x_preferred":[
        "\u041b\u0430\u0442\u0430\u043d\u043e\u0432"
    ],
    "name:und_x_variant":[
        "\u041b\u0430\u0442\u0430\u043d\u043e\u0432"
    ],
    "wof:name":"Latanov",
    "wof:placetype":"locality"
},
  "geometry": {"coordinates":[46.11667,48.81667],"type":"Point"}
}