{
  "type": "Feature",
  "properties": {
    "gn:admin1_code":"70.0",
    "gn:asciiname":"Staro-Izrail'skiy",
    "gn:country_code":"RU",
    "gn:dem":139,
    "gn:feature_class":"P",
    "gn:feature_code":"PPL",
    "gn:name":"Staro-Izrail\u2019skiy",
    "gn:population":0,
    "gn:timezone":"Europe/Moscow",
    "iso:country":"RU",
    "wof:name":"Staro-Izrail'skiy",
    "wof:placetype":"locality"
},
  "geometry": {"coordinates":[44.60111,44.43083],"type":"Point"}
}