{
  "type": "Feature",
  "properties": {
    "gn:admin1_code":"28",
    "gn:asciiname":"Yukko-Guba",
    "gn:country_code":"RU",
    "gn:dem":131,
    "gn:feature_class":"P",
    "gn:feature_code":"PPL",
    "gn:name":"Yukko-Guba",
    "gn:population":0,
    "gn:timezone":"Europe/Moscow",
    "iso:country":"RU",
    "name:eng_x_preferred":[
        "Yukko-Guba"
    ],
    "name:fin_x_preferred":[
        "Jukkolahti"
    ],
    "name:nor_x_preferred":[
        "Jukkoguba"
    ],
    "name:rus_x_preferred":[
        "\u042e\u043a\u043a\u043e\u0433\u0443\u0431\u0430"
    ],
    "name:und_x_variant":[
        "Rabochaya Sila",
        "Yukka-Guba",
        "Yukno-Guba",
        "Yukko-Guba"
    ],
    "wof:name":"Yukko-Guba",
    "wof:placetype":"locality"
},
  "geometry": {"coordinates":[33.09046,63.4049],"type":"Point"}
}