{
  "type": "Feature",
  "properties": {
    "gn:admin1_code":"56",
    "gn:asciiname":"Nizhnyaya Shkava",
    "gn:country_code":"RU",
    "gn:dem":187,
    "gn:feature_class":"P",
    "gn:feature_code":"PPL",
    "gn:name":"Nizhnyaya Shkava",
    "gn:population":0,
    "gn:timezone":"Europe/Moscow",
    "iso:country":"RU",
    "name:rus_x_preferred":[
        "\u041d\u0438\u0436\u043d\u044f\u044f \u0428\u043a\u0430\u0432\u0430"
    ],
    "wof:name":"Nizhnyaya Shkava",
    "wof:placetype":"locality"
},
  "geometry": {"coordinates":[35.44029000000001,53.3522],"type":"Point"}
}