{
  "type": "Feature",
  "properties": {
    "gn:admin1_code":"10",
    "gn:asciiname":"Vshchizh",
    "gn:country_code":"RU",
    "gn:dem":195,
    "gn:feature_class":"P",
    "gn:feature_code":"PPL",
    "gn:name":"Vshchizh",
    "gn:population":0,
    "gn:timezone":"Europe/Moscow",
    "iso:country":"RU",
    "name:che_x_preferred":[
        "\u0412\u0449\u0438\u0436"
    ],
    "name:hye_x_preferred":[
        "\u054e\u0577\u0579\u056b\u056a"
    ],
    "name:ita_x_preferred":[
        "V\u0161\u010di\u017e"
    ],
    "name:jpn_x_preferred":[
        "\u30d5\u30b7\u30c1\u30a4\u30b7\u30e5"
    ],
    "name:rus_x_preferred":[
        "\u0412\u0449\u0438\u0436"
    ],
    "name:ukr_x_preferred":[
        "\u0412\u0449\u0438\u0436"
    ],
    "name:und_x_variant":[
        "Vshchikh",
        "Vshchizh"
    ],
    "wof:name":"Vshchizh",
    "wof:placetype":"locality"
},
  "geometry": {"coordinates":[33.82809,53.41862],"type":"Point"}
}