{
  "type": "Feature",
  "properties": {
    "gn:admin1_code":"6.0",
    "gn:asciiname":"Bol'shaya Korzikha",
    "gn:country_code":"RU",
    "gn:dem":7,
    "gn:feature_class":"P",
    "gn:feature_code":"PPL",
    "gn:name":"Bol\u2019shaya Korzikha",
    "gn:population":0,
    "gn:timezone":"Europe/Moscow",
    "iso:country":"RU",
    "name:rus_x_preferred":[
        "\u0411\u043e\u043b\u044c\u0448\u0430\u044f \u041a\u043e\u0440\u0437\u0438\u0445\u0430"
    ],
    "name:und_x_variant":[
        "Bol\u2019shaya Korzikha"
    ],
    "wof:name":"Bol'shaya Korzikha",
    "wof:placetype":"locality"
},
  "geometry": {"coordinates":[40.58864000000001,64.4866],"type":"Point"}
}