{
  "type": "Feature",
  "properties": {
    "gn:admin1_code":"60",
    "gn:asciiname":"Sergeykovo",
    "gn:country_code":"RU",
    "gn:dem":124,
    "gn:feature_class":"P",
    "gn:feature_code":"PPL",
    "gn:name":"Sergeykovo",
    "gn:population":0,
    "gn:timezone":"Europe/Moscow",
    "iso:country":"RU",
    "name:rus_x_preferred":[
        "\u0421\u0435\u0440\u0433\u0435\u0439\u043a\u043e\u0432\u043e"
    ],
    "wof:name":"Sergeykovo",
    "wof:placetype":"locality"
},
  "geometry": {"coordinates":[28.78514,56.60223000000001],"type":"Point"}
}