{
  "type": "Feature",
  "properties": {
    "gn:admin1_code":"93",
    "gn:asciiname":"Baytsetuy",
    "gn:country_code":"RU",
    "gn:dem":668,
    "gn:feature_class":"P",
    "gn:feature_code":"PPL",
    "gn:name":"Baytsetuy",
    "gn:population":0,
    "gn:timezone":"Asia/Chita",
    "iso:country":"RU",
    "name:nor_x_preferred":[
        "Bajtsetuj"
    ],
    "name:rus_x_preferred":[
        "\u0411\u0430\u0439\u0446\u0435\u0442\u0443\u0439"
    ],
    "name:und_x_variant":[
        "Baitsatui",
        "Baysetuy",
        "Baytsatuy",
        "Baytsetun",
        "Baytsetuy"
    ],
    "wof:name":"Baytsetuy",
    "wof:placetype":"locality"
},
  "geometry": {"coordinates":[115.32201999999999,51.89882],"type":"Point"}
}