{
  "type": "Feature",
  "properties": {
    "gn:admin1_code":"33.0",
    "gn:asciiname":"Bulyzhino",
    "gn:country_code":"RU",
    "gn:dem":219,
    "gn:feature_class":"P",
    "gn:feature_code":"PPL",
    "gn:name":"Bulyzhino",
    "gn:population":0,
    "gn:timezone":"Europe/Kirov",
    "iso:country":"RU",
    "name:rus_x_preferred":[
        "\u0411\u0443\u043b\u044b\u0436\u0438\u043d\u043e"
    ],
    "wof:name":"Bulyzhino",
    "wof:placetype":"locality"
},
  "geometry": {"coordinates":[53.5602,58.5368],"type":"Point"}
}