{
  "type": "Feature",
  "properties": {
    "gn:admin1_code":"53",
    "gn:asciiname":"Mil'tyush",
    "gn:country_code":"RU",
    "gn:dem":106,
    "gn:feature_class":"P",
    "gn:feature_code":"PPL",
    "gn:name":"Mil\u2019tyush",
    "gn:population":0,
    "gn:timezone":"Asia/Novosibirsk",
    "iso:country":"RU",
    "name:rus_x_preferred":[
        "\u041c\u0438\u043b\u044c\u0442\u044e\u0448"
    ],
    "name:und_x_variant":[
        "Mil\u2019tyush"
    ],
    "wof:name":"Mil'tyush",
    "wof:placetype":"locality"
},
  "geometry": {"coordinates":[82.90000000000001,54.68333000000001],"type":"Point"}
}