{
  "type": "Feature",
  "properties": {
    "gn:admin1_code":"55",
    "gn:asciiname":"Chistyy",
    "gn:country_code":"RU",
    "gn:dem":122,
    "gn:feature_class":"P",
    "gn:feature_code":"PPL",
    "gn:name":"Chistyy",
    "gn:population":0,
    "gn:timezone":"Asia/Yekaterinburg",
    "iso:country":"RU",
    "name:rus_x_preferred":[
        "\u0427\u0438\u0441\u0442\u044b\u0439"
    ],
    "wof:name":"Chistyy",
    "wof:placetype":"locality"
},
  "geometry": {"coordinates":[55.04737,51.63811],"type":"Point"}
}