{
  "type": "Feature",
  "properties": {
    "gn:admin1_code":"33.0",
    "gn:asciiname":"Chupiny",
    "gn:country_code":"RU",
    "gn:dem":185,
    "gn:feature_class":"P",
    "gn:feature_code":"PPL",
    "gn:name":"Chupiny",
    "gn:population":0,
    "gn:timezone":"Europe/Kirov",
    "iso:country":"RU",
    "name:rus_x_preferred":[
        "\u0427\u0443\u043f\u0438\u043d\u044b"
    ],
    "name:und_x_variant":[
        "\u0427\u0443\u043f\u0438\u043d\u044b"
    ],
    "wof:name":"Chupiny",
    "wof:placetype":"locality"
},
  "geometry": {"coordinates":[48.58359,58.73508],"type":"Point"}
}