{
  "type": "Feature",
  "properties": {
    "gn:admin1_code":"72",
    "gn:asciiname":"Inozemnaya Dukhovka",
    "gn:country_code":"RU",
    "gn:dem":127,
    "gn:feature_class":"P",
    "gn:feature_code":"PPL",
    "gn:name":"Inozemnaya Dukhovka",
    "gn:population":0,
    "gn:timezone":"Europe/Moscow",
    "iso:country":"RU",
    "name:rus_x_preferred":[
        "\u0418\u043d\u043e\u0437\u0435\u043c\u043d\u0430\u044f \u0414\u0443\u0445\u043e\u0432\u043a\u0430"
    ],
    "wof:name":"Inozemnaya Dukhovka",
    "wof:placetype":"locality"
},
  "geometry": {"coordinates":[41.4298,52.91899],"type":"Point"}
}