{
  "type": "Feature",
  "properties": {
    "gn:admin1_code":"51",
    "gn:asciiname":"Novoye Laptevo",
    "gn:country_code":"RU",
    "gn:dem":133,
    "gn:feature_class":"P",
    "gn:feature_code":"PPL",
    "gn:name":"Novoye Lapt\u00ebvo",
    "gn:population":0,
    "gn:timezone":"Europe/Moscow",
    "iso:country":"RU",
    "name:rus_x_preferred":[
        "\u041d\u043e\u0432\u043e\u0435 \u041b\u0430\u043f\u0442\u0451\u0432\u043e"
    ],
    "name:und_x_variant":[
        "Novoye Lapt\u00ebvo"
    ],
    "wof:name":"Novoye Laptevo",
    "wof:placetype":"locality"
},
  "geometry": {"coordinates":[46.7542,57.4555],"type":"Point"}
}