{
  "type": "Feature",
  "properties": {
    "gn:admin1_code":"88",
    "gn:asciiname":"Shul'gino",
    "gn:country_code":"RU",
    "gn:dem":153,
    "gn:feature_class":"P",
    "gn:feature_code":"PPL",
    "gn:name":"Shul\u2019gino",
    "gn:population":0,
    "gn:timezone":"Europe/Moscow",
    "iso:country":"RU",
    "name:rus_x_preferred":[
        "\u0428\u0443\u043b\u044c\u0433\u0438\u043d\u043e"
    ],
    "name:und_x_variant":[
        "Shul\u2019tino",
        "Shul\u2019gino"
    ],
    "wof:name":"Shul'gino",
    "wof:placetype":"locality"
},
  "geometry": {"coordinates":[39.17078,57.74299],"type":"Point"}
}