{
  "type": "Feature",
  "properties": {
    "gn:admin1_code":"50",
    "gn:asciiname":"Smekalovka",
    "gn:cc2":"RU",
    "gn:country_code":"RU",
    "gn:dem":19,
    "gn:feature_class":"P",
    "gn:feature_code":"PPL",
    "gn:name":"Smekalovka",
    "gn:population":0,
    "gn:timezone":"Europe/Moscow",
    "iso:country":"RU",
    "name:rus_x_preferred":[
        "\u0421\u043c\u0435\u043a\u0430\u043b\u043e\u0432\u043a\u0430"
    ],
    "name:und_x_variant":[
        "Smekalkina",
        "Smekalovka",
        "\u0421\u043c\u0435\u043a\u0430\u043b\u043e\u0432\u043a\u0430"
    ],
    "wof:name":"Smekalovka",
    "wof:placetype":"locality"
},
  "geometry": {"coordinates":[52.25,67.46666999999999],"type":"Point"}
}