{
  "type": "Feature",
  "properties": {
    "gn:admin1_code":"37",
    "gn:asciiname":"Krutets",
    "gn:country_code":"RU",
    "gn:dem":118,
    "gn:feature_class":"P",
    "gn:feature_code":"PPL",
    "gn:name":"Krutets",
    "gn:population":0,
    "gn:timezone":"Europe/Moscow",
    "iso:country":"RU",
    "name:rus_x_preferred":[
        "\u041a\u0440\u0443\u0442\u0435\u0446"
    ],
    "name:und_x_variant":[
        "\u041a\u0440\u0443\u0442\u0435\u0446"
    ],
    "wof:name":"Krutets",
    "wof:placetype":"locality"
},
  "geometry": {"coordinates":[42.39768,57.80633],"type":"Point"}
}