{
  "type": "Feature",
  "properties": {
    "gn:admin1_code":"37.0",
    "gn:asciiname":"Demidkovo",
    "gn:country_code":"RU",
    "gn:dem":141,
    "gn:feature_class":"P",
    "gn:feature_code":"PPL",
    "gn:name":"Demidkovo",
    "gn:population":0,
    "gn:timezone":"Europe/Moscow",
    "iso:country":"RU",
    "name:rus_x_preferred":[
        "\u0414\u0435\u043c\u0438\u0434\u043a\u043e\u0432\u043e"
    ],
    "name:und_x_variant":[
        "\u0414\u0435\u043c\u0438\u0434\u043a\u043e\u0432\u043e"
    ],
    "wof:name":"Demidkovo",
    "wof:placetype":"locality"
},
  "geometry": {"coordinates":[41.17083,57.69051999999999],"type":"Point"}
}