{
  "type": "Feature",
  "properties": {
    "gn:admin1_code":"60",
    "gn:asciiname":"Priozernyy",
    "gn:country_code":"RU",
    "gn:dem":93,
    "gn:feature_class":"P",
    "gn:feature_code":"PPL",
    "gn:name":"Prioz\u00ebrnyy",
    "gn:population":0,
    "gn:timezone":"Europe/Moscow",
    "iso:country":"RU",
    "name:rus_x_preferred":[
        "\u041f\u0440\u0438\u043e\u0437\u0451\u0440\u043d\u044b\u0439"
    ],
    "name:und_x_variant":[
        "Prioz\u00ebrnyy"
    ],
    "wof:name":"Priozernyy",
    "wof:placetype":"locality"
},
  "geometry": {"coordinates":[28.63733,56.79071],"type":"Point"}
}