{
  "type": "Feature",
  "properties": {
    "gn:admin1_code":"69",
    "gn:asciiname":"Levina",
    "gn:country_code":"RU",
    "gn:dem":241,
    "gn:feature_class":"P",
    "gn:feature_code":"PPL",
    "gn:name":"Levina",
    "gn:population":0,
    "gn:timezone":"Europe/Moscow",
    "iso:country":"RU",
    "name:rus_x_preferred":[
        "\u041b\u0435\u0432\u0438\u043d\u0430"
    ],
    "name:und_x_variant":[
        "Levino",
        "Levina",
        "\u041b\u0435\u0432\u0438\u043d\u0430"
    ],
    "wof:name":"Levina",
    "wof:placetype":"locality"
},
  "geometry": {"coordinates":[33.19863,55.62146],"type":"Point"}
}