{
  "type": "Feature",
  "properties": {
    "gn:admin1_code":"71",
    "gn:asciiname":"Vyazovka",
    "gn:country_code":"RU",
    "gn:dem":68,
    "gn:feature_class":"P",
    "gn:feature_code":"PPL",
    "gn:name":"Vyazovka",
    "gn:population":0,
    "gn:timezone":"Asia/Yekaterinburg",
    "iso:country":"RU",
    "name:aze_x_preferred":[
        "Vyazovka"
    ],
    "name:bak_x_preferred":[
        "\u0412\u044f\u0437\u043e\u0432\u043a\u0430"
    ],
    "name:che_x_preferred":[
        "\u0412\u044f\u0437\u043e\u0432\u043a\u0430"
    ],
    "name:chv_x_preferred":[
        "\u0412\u044f\u0437\u043e\u0432\u043a\u0430"
    ],
    "name:eng_x_preferred":[
        "Vyazovka"
    ],
    "name:hye_x_preferred":[
        "\u054e\u0575\u0561\u0566\u0578\u057e\u056f\u0561"
    ],
    "name:kaz_x_preferred":[
        "\u0412\u044f\u0437\u043e\u0432\u043a\u0430"
    ],
    "name:kir_x_preferred":[
        "\u0412\u044f\u0437\u043e\u0432\u043a\u0430"
    ],
    "name:nor_x_preferred":[
        "Vjazovka"
    ],
    "name:rus_x_preferred":[
        "\u0412\u044f\u0437\u043e\u0432\u043a\u0430"
    ],
    "name:tat_x_preferred":[
        "\u0412\u044f\u0437\u043e\u0432\u043a\u0430"
    ],
    "name:ukr_x_preferred":[
        "\u0412'\u044f\u0437\u043e\u0432\u043a\u0430"
    ],
    "wof:name":"Vyazovka",
    "wof:placetype":"locality"
},
  "geometry": {"coordinates":[63.8653,57.50257],"type":"Point"}
}