{
  "type": "Feature",
  "properties": {
    "gn:admin1_code":"28",
    "gn:asciiname":"Yakkima",
    "gn:cc2":"RU",
    "gn:country_code":"RU",
    "gn:dem":42,
    "gn:feature_class":"P",
    "gn:feature_code":"PPL",
    "gn:name":"Yakkima",
    "gn:population":0,
    "gn:timezone":"Europe/Moscow",
    "iso:country":"RU",
    "name:fin_x_preferred":[
        "Jaakkima"
    ],
    "wof:name":"Yakkima",
    "wof:placetype":"locality"
},
  "geometry": {"coordinates":[30.17035,61.52523000000001],"type":"Point"}
}