{
  "type": "Feature",
  "properties": {
    "gn:admin1_code":"70",
    "gn:asciiname":"Peschanyy",
    "gn:country_code":"RU",
    "gn:dem":76,
    "gn:feature_class":"P",
    "gn:feature_code":"PPL",
    "gn:name":"Peschanyy",
    "gn:population":0,
    "gn:timezone":"Europe/Moscow",
    "iso:country":"RU",
    "name:eng_x_preferred":[
        "Peschanyy"
    ],
    "name:nor_x_preferred":[
        "Pestsjanyj"
    ],
    "name:rus_x_preferred":[
        "\u041f\u0435\u0441\u0447\u0430\u043d\u044b\u0439"
    ],
    "wof:name":"Peschanyy",
    "wof:placetype":"locality"
},
  "geometry": {"coordinates":[45.42556,44.14361],"type":"Point"}
}