{
  "type": "Feature",
  "properties": {
    "gn:admin1_code":"67",
    "gn:asciiname":"Shalinka",
    "gn:country_code":"RU",
    "gn:dem":208,
    "gn:feature_class":"P",
    "gn:feature_code":"PPL",
    "gn:name":"Shalinka",
    "gn:population":0,
    "gn:timezone":"Europe/Saratov",
    "iso:country":"RU",
    "name:rus_x_preferred":[
        "\u0428\u0430\u043b\u0438\u043d\u043a\u0430"
    ],
    "name:und_x_variant":[
        "\u0428\u0430\u043b\u0438\u043d\u043a\u0430"
    ],
    "wof:name":"Shalinka",
    "wof:placetype":"locality"
},
  "geometry": {"coordinates":[44.28441,51.65831],"type":"Point"}
}