{
  "type": "Feature",
  "properties": {
    "gn:admin1_code":"70",
    "gn:asciiname":"Shvedino",
    "gn:country_code":"RU",
    "gn:dem":165,
    "gn:feature_class":"P",
    "gn:feature_code":"PPL",
    "gn:name":"Shvedino",
    "gn:population":0,
    "gn:timezone":"Europe/Moscow",
    "iso:country":"RU",
    "name:eng_x_preferred":[
        "Shvedino"
    ],
    "name:nor_x_preferred":[
        "Sjvedino"
    ],
    "name:rus_x_preferred":[
        "\u0428\u0432\u0435\u0434\u0438\u043d\u043e"
    ],
    "wof:name":"Shvedino",
    "wof:placetype":"locality"
},
  "geometry": {"coordinates":[42.8925,45.41083],"type":"Point"}
}