{
  "type": "Feature",
  "properties": {
    "gn:admin1_code":"37",
    "gn:asciiname":"Kharitonovo",
    "gn:country_code":"RU",
    "gn:dem":119,
    "gn:feature_class":"P",
    "gn:feature_code":"PPL",
    "gn:name":"Kharitonovo",
    "gn:population":0,
    "gn:timezone":"Europe/Moscow",
    "iso:country":"RU",
    "name:che_x_preferred":[
        "\u0425\u0430\u0440\u0438\u0442\u043e\u043d\u043e\u0432\u043e"
    ],
    "name:eng_x_preferred":[
        "Kharitonovo"
    ],
    "name:nor_x_preferred":[
        "Kharitonovo"
    ],
    "name:rus_x_preferred":[
        "\u0425\u0430\u0440\u0438\u0442\u043e\u043d\u043e\u0432\u043e"
    ],
    "name:und_x_variant":[
        "\u0425\u0430\u0440\u0438\u0442\u043e\u043d\u043e\u0432\u043e",
        "Kharitonovo"
    ],
    "wof:name":"Kharitonovo",
    "wof:placetype":"locality"
},
  "geometry": {"coordinates":[41.2325,57.62266999999999],"type":"Point"}
}