{
  "type": "Feature",
  "properties": {
    "gn:admin1_code":"77",
    "gn:asciiname":"Nikolo-Malitsa",
    "gn:country_code":"RU",
    "gn:dem":137,
    "gn:feature_class":"P",
    "gn:feature_code":"PPL",
    "gn:name":"Nikolo-Malitsa",
    "gn:population":0,
    "gn:timezone":"Europe/Moscow",
    "iso:country":"RU",
    "name:nor_x_preferred":[
        "Nikolo-Malitsa"
    ],
    "name:rus_x_preferred":[
        "\u041d\u0438\u043a\u043e\u043b\u043e-\u041c\u0430\u043b\u0438\u0446\u0430"
    ],
    "name:und_x_variant":[
        "Malitsa",
        "Nikola-Malitsa",
        "Nikolo-Malitsa"
    ],
    "wof:name":"Nikolo-Malitsa",
    "wof:placetype":"locality"
},
  "geometry": {"coordinates":[35.79676,56.87582],"type":"Point"}
}