{
  "type": "Feature",
  "properties": {
    "gn:admin1_code":"51.0",
    "gn:asciiname":"Mochal'noye",
    "gn:country_code":"RU",
    "gn:dem":100,
    "gn:feature_class":"P",
    "gn:feature_code":"PPL",
    "gn:name":"Mochal\u2019noye",
    "gn:population":0,
    "gn:timezone":"Europe/Moscow",
    "iso:country":"RU",
    "name:nor_x_preferred":[
        "Motsjalnoje"
    ],
    "name:rus_x_preferred":[
        "\u041c\u043e\u0447\u0430\u043b\u044c\u043d\u043e\u0435"
    ],
    "name:und_x_variant":[
        "Mochal\u2019noye"
    ],
    "wof:name":"Mochal'noye",
    "wof:placetype":"locality"
},
  "geometry": {"coordinates":[43.65309,56.83098],"type":"Point"}
}