{
  "type": "Feature",
  "properties": {
    "gn:admin1_code":"57.0",
    "gn:asciiname":"Cherkassk",
    "gn:country_code":"RU",
    "gn:dem":161,
    "gn:feature_class":"P",
    "gn:feature_code":"PPL",
    "gn:name":"Cherkassk",
    "gn:population":0,
    "gn:timezone":"Europe/Moscow",
    "iso:country":"RU",
    "name:rus_x_preferred":[
        "\u0427\u0435\u0440\u043a\u0430\u0441\u0441\u043a"
    ],
    "name:und_x_variant":[
        "Cherkasskoye",
        "Cherkassk"
    ],
    "wof:name":"Cherkassk",
    "wof:placetype":"locality"
},
  "geometry": {"coordinates":[44.4235,52.7526],"type":"Point"}
}