{
  "type": "Feature",
  "properties": {
    "gn:admin1_code":"67",
    "gn:asciiname":"Sorokin",
    "gn:country_code":"RU",
    "gn:dem":22,
    "gn:feature_class":"P",
    "gn:feature_code":"PPL",
    "gn:name":"Sorokin",
    "gn:population":0,
    "gn:timezone":"Europe/Saratov",
    "iso:country":"RU",
    "name:bul_x_preferred":[
        "\u0421\u043e\u0440\u043e\u043a\u0438\u043d"
    ],
    "name:ces_x_preferred":[
        "Sorokin"
    ],
    "name:fra_x_preferred":[
        "Sorokine"
    ],
    "name:pol_x_preferred":[
        "Sorokin"
    ],
    "name:rus_x_preferred":[
        "\u0421\u043e\u0440\u043e\u043a\u0438\u043d"
    ],
    "name:slv_x_preferred":[
        "Sorokin"
    ],
    "wof:name":"Sorokin",
    "wof:placetype":"locality"
},
  "geometry": {"coordinates":[48.59392,50.38628],"type":"Point"}
}