{
  "type": "Feature",
  "properties": {
    "gn:admin1_code":"73",
    "gn:asciiname":"Votkin",
    "gn:country_code":"RU",
    "gn:dem":221,
    "gn:feature_class":"P",
    "gn:feature_code":"PPL",
    "gn:name":"Votkin",
    "gn:population":0,
    "gn:timezone":"Europe/Moscow",
    "iso:country":"RU",
    "name:rus_x_preferred":[
        "\u0412\u043e\u0442\u043a\u0438\u043d"
    ],
    "name:und_x_variant":[
        "\u0412\u043e\u0442\u043a\u0438\u043d"
    ],
    "wof:name":"Votkin",
    "wof:placetype":"locality"
},
  "geometry": {"coordinates":[53.2144,54.344],"type":"Point"}
}