{
  "type": "Feature",
  "properties": {
    "gn:admin1_code":"10.0",
    "gn:asciiname":"Bul'shevo",
    "gn:country_code":"RU",
    "gn:dem":185,
    "gn:feature_class":"P",
    "gn:feature_code":"PPL",
    "gn:name":"Bul\u2019shevo",
    "gn:population":0,
    "gn:timezone":"Europe/Moscow",
    "iso:country":"RU",
    "name:rus_x_preferred":[
        "\u0411\u0443\u043b\u044c\u0448\u0435\u0432\u043e"
    ],
    "name:und_x_variant":[
        "Bul\u2019shovo Korshevo",
        "Bul\u2019shovo",
        "Bul\u2019shevo"
    ],
    "wof:name":"Bul'shevo",
    "wof:placetype":"locality"
},
  "geometry": {"coordinates":[33.2606,53.2152],"type":"Point"}
}