{
  "type": "Feature",
  "properties": {
    "gn:admin1_code":"17",
    "gn:asciiname":"Kusur",
    "gn:country_code":"RU",
    "gn:dem":2118,
    "gn:feature_class":"P",
    "gn:feature_code":"PPL",
    "gn:name":"Kusur",
    "gn:population":0,
    "gn:timezone":"Europe/Moscow",
    "iso:country":"RU",
    "name:eng_x_preferred":[
        "Kusur"
    ],
    "name:nor_x_preferred":[
        "Kusur"
    ],
    "name:rus_x_preferred":[
        "\u041a\u0443\u0441\u0443\u0440"
    ],
    "wof:name":"Kusur",
    "wof:placetype":"locality"
},
  "geometry": {"coordinates":[46.94925,41.78265],"type":"Point"}
}