{
  "type": "Feature",
  "properties": {
    "gn:admin1_code":"80.0",
    "gn:asciiname":"Barmino",
    "gn:country_code":"RU",
    "gn:dem":106,
    "gn:feature_class":"P",
    "gn:feature_code":"PPL",
    "gn:name":"Barmino",
    "gn:population":0,
    "gn:timezone":"Europe/Samara",
    "iso:country":"RU",
    "name:nor_x_preferred":[
        "Barmino"
    ],
    "name:rus_x_preferred":[
        "\u0411\u0430\u0440\u043c\u0438\u043d\u043e"
    ],
    "wof:name":"Barmino",
    "wof:placetype":"locality"
},
  "geometry": {"coordinates":[52.16659,56.69841],"type":"Point"}
}