{
  "type": "Feature",
  "properties": {
    "gn:admin1_code":"88",
    "gn:asciiname":"Dumino",
    "gn:country_code":"RU",
    "gn:dem":110,
    "gn:feature_class":"P",
    "gn:feature_code":"PPL",
    "gn:name":"Dumino",
    "gn:population":0,
    "gn:timezone":"Europe/Moscow",
    "iso:country":"RU",
    "name:rus_x_preferred":[
        "\u0414\u0443\u043c\u0438\u043d\u043e"
    ],
    "wof:name":"Dumino",
    "wof:placetype":"locality"
},
  "geometry": {"coordinates":[39.9956,57.7014],"type":"Point"}
}