{
  "type": "Feature",
  "properties": {
    "gn:admin1_code":"21.0",
    "gn:asciiname":"Ivakovo",
    "gn:country_code":"RU",
    "gn:dem":101,
    "gn:feature_class":"P",
    "gn:feature_code":"PPL",
    "gn:name":"Ivakovo",
    "gn:population":0,
    "gn:timezone":"Europe/Moscow",
    "iso:country":"RU",
    "wof:name":"Ivakovo",
    "wof:placetype":"locality"
},
  "geometry": {"coordinates":[41.345,56.92306],"type":"Point"}
}