{
  "type": "Feature",
  "properties": {
    "gn:admin1_code":"90",
    "gn:asciiname":"Kar'yer Izvestnyak",
    "gn:country_code":"RU",
    "gn:dem":176,
    "gn:feature_class":"P",
    "gn:feature_code":"PPL",
    "gn:name":"Kar\u2019yer Izvestnyak",
    "gn:population":0,
    "gn:timezone":"Asia/Yekaterinburg",
    "iso:country":"RU",
    "name:eng_x_preferred":[
        "Kar'yer Izvestnyak"
    ],
    "name:nor_x_preferred":[
        "Karjer Izvestnjaka"
    ],
    "name:rus_x_preferred":[
        "\u041a\u0430\u0440\u044c\u0435\u0440 \u0418\u0437\u0432\u0435\u0441\u0442\u043d\u044f\u043a\u0430"
    ],
    "name:rus_x_variant":[
        "\u041a\u0430\u0440\u044c\u0435\u0440 \u0418\u0437\u0432\u0435\u0441\u0442\u043d\u044f\u043a"
    ],
    "name:und_x_variant":[
        "Kar\u2019yer",
        "Kar\u2019yer Izvestnyak",
        "Kar\u2019yer Izvestnyaka"
    ],
    "wof:name":"Kar'yer Izvestnyak",
    "wof:placetype":"locality"
},
  "geometry": {"coordinates":[57.4782,59.1912],"type":"Point"}
}