{
  "type": "Feature",
  "properties": {
    "gn:country":"RU",
    "gn:fcode":"PPL",
    "gn:pop":1865,
    "iso:country":"RU",
    "name:eng_x_preferred":[
        "Yamkino"
    ],
    "name:nor_x_preferred":[
        "Jamkino"
    ],
    "name:rus_x_preferred":[
        "\u042f\u043c\u043a\u0438\u043d\u043e"
    ],
    "qs:name":"Yamkino",
    "qs:name_adm0":"Russia",
    "qs:name_adm1":"Moscow Oblast",
    "qs:photos_9k":1,
    "qs:photos_9r":2,
    "qs:photos_all":34,
    "qs:photos_sr":0,
    "qs:placetype":"Town",
    "qs:pop_sr":"3",
    "wof:name":"Yamkino",
    "wof:placetype":"locality",
    "wof:population":1865
},
  "geometry": {"coordinates":[38.40417,55.92088],"type":"Point"}
}