{
  "type": "Feature",
  "properties": {
    "gn:admin1_code":"60",
    "gn:asciiname":"Lezhovka",
    "gn:country_code":"RU",
    "gn:dem":117,
    "gn:feature_class":"P",
    "gn:feature_code":"PPL",
    "gn:name":"Lezhovka",
    "gn:population":0,
    "gn:timezone":"Europe/Moscow",
    "iso:country":"RU",
    "name:rus_x_preferred":[
        "\u041b\u0435\u0436\u043e\u0432\u043a\u0430"
    ],
    "wof:name":"Lezhovka",
    "wof:placetype":"locality"
},
  "geometry": {"coordinates":[28.92591,56.72255],"type":"Point"}
}