{
  "type": "Feature",
  "properties": {
    "gn:admin1_code":"90",
    "gn:asciiname":"Verkhnyaya Lys'va",
    "gn:country_code":"RU",
    "gn:dem":211,
    "gn:feature_class":"P",
    "gn:feature_code":"PPL",
    "gn:name":"Verkhnyaya Lys\u2019va",
    "gn:population":0,
    "gn:timezone":"Asia/Yekaterinburg",
    "iso:country":"RU",
    "name:eng_x_preferred":[
        "Verkh-Lys'va"
    ],
    "name:nor_x_preferred":[
        "Verkh-Lysva"
    ],
    "name:rus_x_preferred":[
        "\u0412\u0435\u0440\u0445-\u041b\u044b\u0441\u044c\u0432\u0430"
    ],
    "name:rus_x_variant":[
        "\u0412\u0435\u0440\u0445\u043d\u044f\u044f \u041b\u044b\u0441\u044c\u0432\u0430"
    ],
    "name:und_x_variant":[
        "Verkhne-Lys\u2019venskiy",
        "Verkhniy Lys\u2019venskiy",
        "Verkh-Lys\u2019va",
        "Verkhnyaya Lys\u2019va"
    ],
    "wof:name":"Verkhnyaya Lys'va",
    "wof:placetype":"locality"
},
  "geometry": {"coordinates":[57.9052,57.9801],"type":"Point"}
}