{
  "type": "Feature",
  "properties": {
    "gn:admin1_code":"55.0",
    "gn:asciiname":"Drygin Sad",
    "gn:country_code":"RU",
    "gn:dem":135,
    "gn:feature_class":"P",
    "gn:feature_code":"PPL",
    "gn:name":"Drygin Sad",
    "gn:population":0,
    "gn:timezone":"Asia/Yekaterinburg",
    "iso:country":"RU",
    "name:eng_x_preferred":[
        "Drygin Sad"
    ],
    "name:nor_x_preferred":[
        "Drygin-Sad"
    ],
    "name:rus_x_preferred":[
        "\u0414\u0440\u044b\u0433\u0438\u043d-\u0421\u0430\u0434"
    ],
    "name:rus_x_variant":[
        "\u0414\u0440\u044b\u0433\u0438\u043d \u0421\u0430\u0434"
    ],
    "name:und_x_variant":[
        "Dryyein Sad",
        "Drygin Sad",
        "\u0414\u0440\u044b\u0433\u0438\u043d \u0421\u0430\u0434"
    ],
    "wof:name":"Drygin Sad",
    "wof:placetype":"locality"
},
  "geometry": {"coordinates":[53.45,52.73333],"type":"Point"}
}