{
  "type": "Feature",
  "properties": {
    "gn:admin1_code":"37",
    "gn:asciiname":"Osinniki",
    "gn:country_code":"RU",
    "gn:dem":172,
    "gn:feature_class":"P",
    "gn:feature_code":"PPL",
    "gn:name":"Osinniki",
    "gn:population":0,
    "gn:timezone":"Europe/Moscow",
    "iso:country":"RU",
    "name:rus_x_preferred":[
        "\u041e\u0441\u0438\u043d\u043d\u0438\u043a\u0438"
    ],
    "name:und_x_variant":[
        "\u041e\u0441\u0438\u043d\u043d\u0438\u043a\u0438"
    ],
    "wof:name":"Osinniki",
    "wof:placetype":"locality"
},
  "geometry": {"coordinates":[45.81667,58.95],"type":"Point"}
}