{
  "type": "Feature",
  "properties": {
    "gn:admin1_code":"37",
    "gn:asciiname":"Osinniki",
    "gn:country_code":"RU",
    "gn:dem":172,
    "gn:feature_class":"P",
    "gn:feature_code":"PPL",
    "gn:name":"Osinniki",
    "gn:population":0,
    "gn:timezone":"Europe/Moscow",
    "iso:country":"RU",
    "name:ara_x_preferred":[
        "\u0623\u0648\u0633\u064a\u0646\u064a\u0643\u064a"
    ],
    "name:azb_x_preferred":[
        "\u0627\u0648\u0633\u06cc\u0646\u06cc\u06a9\u06cc"
    ],
    "name:bel_x_preferred":[
        "\u0410\u0441\u0456\u043d\u043d\u0456\u043a\u0456"
    ],
    "name:bul_x_preferred":[
        "\u041e\u0441\u0438\u043d\u043d\u0438\u043a\u0438"
    ],
    "name:ceb_x_preferred":[
        "Osinniki"
    ],
    "name:ces_x_preferred":[
        "Osinniki"
    ],
    "name:che_x_preferred":[
        "\u041e\u0441\u0438\u043d\u043d\u0438\u043a\u0438"
    ],
    "name:deu_x_preferred":[
        "Ossinniki"
    ],
    "name:epo_x_preferred":[
        "Osinniki"
    ],
    "name:est_x_preferred":[
        "Ossinniki"
    ],
    "name:fas_x_preferred":[
        "\u0627\u0648\u0633\u06cc\u0646\u06cc\u06a9\u06cc"
    ],
    "name:fin_x_preferred":[
        "Osinniki"
    ],
    "name:fra_x_preferred":[
        "Ossinniki"
    ],
    "name:hsb_x_preferred":[
        "Osinniki"
    ],
    "name:ita_x_preferred":[
        "Osinniki"
    ],
    "name:nno_x_preferred":[
        "Osinniki"
    ],
    "name:nor_x_preferred":[
        "Osinniki"
    ],
    "name:pnb_x_preferred":[
        "\u0627\u0648\u0633\u06cc\u0646\u06cc\u06a9\u06cc"
    ],
    "name:pol_x_preferred":[
        "Osinniki"
    ],
    "name:por_x_preferred":[
        "Osinniki"
    ],
    "name:ron_x_preferred":[
        "Osinniki"
    ],
    "name:rus_x_preferred":[
        "\u041e\u0441\u0438\u043d\u043d\u0438\u043a\u0438"
    ],
    "name:slk_x_preferred":[
        "Osinniki"
    ],
    "name:srp_x_preferred":[
        "\u041e\u0441\u0438\u043d\u0438\u043a\u0438"
    ],
    "name:tat_x_preferred":[
        "\u041e\u0441\u0438\u043d\u043d\u0438\u043a\u0438"
    ],
    "name:tgl_x_preferred":[
        "Osinniki"
    ],
    "name:tur_x_preferred":[
        "Osinniki"
    ],
    "name:und_x_variant":[
        "\u041e\u0441\u0438\u043d\u043d\u0438\u043a\u0438"
    ],
    "name:vep_x_preferred":[
        "Osinniki"
    ],
    "name:vie_x_preferred":[
        "Osinniki"
    ],
    "name:war_x_preferred":[
        "Osinniki"
    ],
    "name:zho_x_preferred":[
        "\u5967\u8f9b\u5c3c\u57fa"
    ],
    "wof:name":"Osinniki",
    "wof:placetype":"locality"
},
  "geometry": {"coordinates":[45.81667,58.95],"type":"Point"}
}