{
  "type": "Feature",
  "properties": {
    "gn:admin1_code":"6",
    "gn:asciiname":"Verkhneye Chazhestrovo",
    "gn:country_code":"RU",
    "gn:dem":19,
    "gn:feature_class":"P",
    "gn:feature_code":"PPL",
    "gn:name":"Verkhneye Chazhestrovo",
    "gn:population":0,
    "gn:timezone":"Europe/Moscow",
    "iso:country":"RU",
    "name:rus_x_preferred":[
        "\u0412\u0435\u0440\u0445\u043d\u0435\u0435 \u0427\u0430\u0436\u0435\u0441\u0442\u0440\u043e\u0432\u043e"
    ],
    "name:und_x_variant":[
        "Verkhneye Chuzhestrovo"
    ],
    "wof:name":"Verkhneye Chazhestrovo",
    "wof:placetype":"locality"
},
  "geometry": {"coordinates":[42.6502,62.8711],"type":"Point"}
}