{
  "type": "Feature",
  "properties": {
    "gn:admin1_code":"59",
    "gn:asciiname":"Yelenovka",
    "gn:country_code":"RU",
    "gn:dem":102,
    "gn:feature_class":"P",
    "gn:feature_code":"PPL",
    "gn:name":"Yel\u00ebnovka",
    "gn:population":0,
    "gn:timezone":"Asia/Vladivostok",
    "iso:country":"RU",
    "name:aze_x_preferred":[
        "Yelenovka"
    ],
    "name:eng_x_preferred":[
        "Yel\u00ebnovka"
    ],
    "name:nor_x_preferred":[
        "Jelenovka"
    ],
    "name:rus_x_preferred":[
        "\u0415\u043b\u0435\u043d\u043e\u0432\u043a\u0430"
    ],
    "name:und_x_variant":[
        "Yel\u00ebnovka"
    ],
    "wof:name":"Yelenovka",
    "wof:placetype":"locality"
},
  "geometry": {"coordinates":[133.67196000000001,45.17088],"type":"Point"}
}