{
  "type": "Feature",
  "properties": {
    "gn:admin1_code":"63",
    "gn:asciiname":"Kombayn",
    "gn:country_code":"RU",
    "gn:dem":152,
    "gn:feature_class":"P",
    "gn:feature_code":"PPL",
    "gn:name":"Kombayn",
    "gn:population":0,
    "gn:timezone":"Asia/Yakutsk",
    "iso:country":"RU",
    "name:rus_x_preferred":[
        "\u041a\u043e\u043c\u0431\u0430\u0439\u043d"
    ],
    "wof:name":"Kombayn",
    "wof:placetype":"locality"
},
  "geometry": {"coordinates":[132.43333000000001,61.08333],"type":"Point"}
}