{
  "type": "Feature",
  "properties": {
    "gn:admin1_code":"77",
    "gn:asciiname":"Moshnaya Gora",
    "gn:country_code":"RU",
    "gn:dem":169,
    "gn:feature_class":"P",
    "gn:feature_code":"PPL",
    "gn:name":"Moshnaya Gora",
    "gn:population":0,
    "gn:timezone":"Europe/Moscow",
    "iso:country":"RU",
    "name:rus_x_preferred":[
        "\u041c\u043e\u0448\u043d\u0430\u044f \u0413\u043e\u0440\u0430"
    ],
    "wof:name":"Moshnaya Gora",
    "wof:placetype":"locality"
},
  "geometry": {"coordinates":[34.99778,57.96944000000001],"type":"Point"}
}