{
  "type": "Feature",
  "properties": {
    "gn:admin1_code":"75",
    "gn:asciiname":"Udarnyy",
    "gn:country_code":"RU",
    "gn:dem":117,
    "gn:feature_class":"P",
    "gn:feature_code":"PPL",
    "gn:name":"Udarnyy",
    "gn:population":0,
    "gn:timezone":"Asia/Tomsk",
    "iso:country":"RU",
    "wof:name":"Udarnyy",
    "wof:placetype":"locality"
},
  "geometry": {"coordinates":[82.88333,57.85],"type":"Point"}
}