{
  "type": "Feature",
  "properties": {
    "gn:admin1_code":"41.0",
    "gn:asciiname":"Gir'i",
    "gn:country_code":"RU",
    "gn:dem":152,
    "gn:feature_class":"P",
    "gn:feature_code":"PPL",
    "gn:name":"Gir\u2019i",
    "gn:population":0,
    "gn:timezone":"Europe/Moscow",
    "iso:country":"RU",
    "name:eng_x_preferred":[
        "Gir'i"
    ],
    "name:nor_x_preferred":[
        "Giri"
    ],
    "name:rus_x_preferred":[
        "\u0413\u0438\u0440\u044c\u0438"
    ],
    "name:und_x_variant":[
        "Gir\u2019l",
        "Gir\u2019i"
    ],
    "wof:name":"Gir'i",
    "wof:placetype":"locality"
},
  "geometry": {"coordinates":[35.57611,51.08667],"type":"Point"}
}