{
  "type": "Feature",
  "properties": {
    "gn:admin1_code":"60",
    "gn:asciiname":"Andreykovo",
    "gn:country_code":"RU",
    "gn:dem":174,
    "gn:feature_class":"P",
    "gn:feature_code":"PPL",
    "gn:name":"Andreykovo",
    "gn:population":0,
    "gn:timezone":"Europe/Moscow",
    "iso:country":"RU",
    "name:rus_x_preferred":[
        "\u0410\u043d\u0434\u0440\u0435\u0439\u043a\u043e\u0432\u043e"
    ],
    "wof:name":"Andreykovo",
    "wof:placetype":"locality"
},
  "geometry": {"coordinates":[30.0249,56.4088],"type":"Point"}
}