{
  "type": "Feature",
  "properties": {
    "gn:admin1_code":"20",
    "gn:asciiname":"Alygdzher",
    "gn:country_code":"RU",
    "gn:dem":915,
    "gn:feature_class":"P",
    "gn:feature_code":"PPL",
    "gn:name":"Alygdzher",
    "gn:population":0,
    "gn:timezone":"Asia/Irkutsk",
    "iso:country":"RU",
    "name:eng_x_preferred":[
        "Alygdzher"
    ],
    "name:nor_x_preferred":[
        "Alygdzjer"
    ],
    "name:rus_x_preferred":[
        "\u0410\u043b\u044b\u0433\u0434\u0436\u0435\u0440"
    ],
    "name:und_x_variant":[
        "Kul\u2019tbaza Alygdzher",
        "Alygjer"
    ],
    "wof:name":"Alygdzher",
    "wof:placetype":"locality"
},
  "geometry": {"coordinates":[98.21829,53.63965],"type":"Point"}
}