{
  "type": "Feature",
  "properties": {
    "gn:admin1_code":"76",
    "gn:asciiname":"Butyrovka",
    "gn:country_code":"RU",
    "gn:dem":176,
    "gn:feature_class":"P",
    "gn:feature_code":"PPL",
    "gn:name":"Butyrovka",
    "gn:population":0,
    "gn:timezone":"Europe/Moscow",
    "iso:country":"RU",
    "name:rus_x_preferred":[
        "\u0411\u0443\u0442\u044b\u0440\u043e\u0432\u043a\u0430"
    ],
    "wof:name":"Butyrovka",
    "wof:placetype":"locality"
},
  "geometry": {"coordinates":[38.8988,53.7217],"type":"Point"}
}