{
  "type": "Feature",
  "properties": {
    "gn:admin1_code":"73",
    "gn:asciiname":"Gordeyevo",
    "gn:country_code":"RU",
    "gn:dem":101,
    "gn:feature_class":"P",
    "gn:feature_code":"PPL",
    "gn:name":"Gordeyevo",
    "gn:population":0,
    "gn:timezone":"Europe/Moscow",
    "iso:country":"RU",
    "name:che_x_preferred":[
        "\u0413\u043e\u0440\u0434\u0435\u0435\u0432\u043e"
    ],
    "name:rus_x_preferred":[
        "\u0413\u043e\u0440\u0434\u0435\u0435\u0432\u043e"
    ],
    "name:und_x_variant":[
        "Gordoyevo",
        "Gordeyevo"
    ],
    "wof:name":"Gordeyevo",
    "wof:placetype":"locality"
},
  "geometry": {"coordinates":[48.29083,55.48426],"type":"Point"}
}