{
  "type": "Feature",
  "properties": {
    "gn:admin1_code":"88.0",
    "gn:asciiname":"Byl'tsyno",
    "gn:country_code":"RU",
    "gn:dem":152,
    "gn:feature_class":"P",
    "gn:feature_code":"PPL",
    "gn:name":"Byl\u2019tsyno",
    "gn:population":0,
    "gn:timezone":"Europe/Moscow",
    "iso:country":"RU",
    "name:rus_x_preferred":[
        "\u0411\u044b\u043b\u044c\u0446\u044b\u043d\u043e"
    ],
    "name:und_x_variant":[
        "Byl\u2019tsino",
        "Byl\u2019tsyno",
        "\u0411\u044b\u043b\u044c\u0446\u044b\u043d\u043e"
    ],
    "wof:name":"Byl'tsyno",
    "wof:placetype":"locality"
},
  "geometry": {"coordinates":[38.55583,57.49833],"type":"Point"}
}