{
  "type": "Feature",
  "properties": {
    "gn:admin1_code":"37",
    "gn:asciiname":"Shatunovo",
    "gn:country_code":"RU",
    "gn:dem":178,
    "gn:feature_class":"P",
    "gn:feature_code":"PPL",
    "gn:name":"Shatunovo",
    "gn:population":0,
    "gn:timezone":"Europe/Moscow",
    "iso:country":"RU",
    "name:rus_x_preferred":[
        "\u0428\u0430\u0442\u0443\u043d\u043e\u0432\u043e"
    ],
    "name:und_x_variant":[
        "\u0428\u0430\u0442\u0443\u043d\u043e\u0432\u043e"
    ],
    "wof:name":"Shatunovo",
    "wof:placetype":"locality"
},
  "geometry": {"coordinates":[42.78333,58.63333000000001],"type":"Point"}
}