{
  "type": "Feature",
  "properties": {
    "gn:country":"RU",
    "gn:fcode":"PPL",
    "gn:pop":0,
    "iso:country":"RU",
    "name:rus_x_preferred":[
        "\u041a\u0430\u043c\u0435\u043d\u043a\u0430"
    ],
    "name:unk_x_variant":[
        "\u041a\u0430\u043c\u0435\u043d\u043a\u0430"
    ],
    "qs:name":"Kamenka",
    "qs:name_adm0":"Russia",
    "qs:name_adm1":"Lipetsk Oblast",
    "qs:photos_9r":0,
    "qs:photos_sr":0,
    "qs:placetype":"Town",
    "qs:pop_sr":"0",
    "wd:wordcount":157,
    "wof:name":"Kamenka",
    "wof:placetype":"locality",
    "wof:population":0
},
  "geometry": {"coordinates":[38.7672,52.3767],"type":"Point"}
}