{
  "type": "Feature",
  "properties": {
    "gn:admin1_code":"77",
    "gn:asciiname":"Klypino",
    "gn:country_code":"RU",
    "gn:dem":237,
    "gn:feature_class":"P",
    "gn:feature_code":"PPL",
    "gn:name":"Klypino",
    "gn:population":0,
    "gn:timezone":"Europe/Moscow",
    "iso:country":"RU",
    "name:rus_x_preferred":[
        "\u041a\u043b\u044b\u043f\u0438\u043d\u043e"
    ],
    "name:und_x_variant":[
        "\u041a\u043b\u044b\u043f\u0438\u043d\u043e"
    ],
    "wof:name":"Klypino",
    "wof:placetype":"locality"
},
  "geometry": {"coordinates":[33.76787,56.61767],"type":"Point"}
}