{
  "type": "Feature",
  "properties": {
    "gn:admin1_code":"53.0",
    "gn:asciiname":"Koshevo",
    "gn:country_code":"RU",
    "gn:dem":226,
    "gn:feature_class":"P",
    "gn:feature_code":"PPL",
    "gn:name":"Koshevo",
    "gn:population":0,
    "gn:timezone":"Asia/Novosibirsk",
    "iso:country":"RU",
    "name:rus_x_preferred":[
        "\u041a\u043e\u0448\u0435\u0432\u043e"
    ],
    "name:und_x_variant":[
        "\u041a\u043e\u0448\u0435\u0432\u043e"
    ],
    "wof:name":"Koshevo",
    "wof:placetype":"locality"
},
  "geometry": {"coordinates":[83.49679999999999,55.2539],"type":"Point"}
}