{
  "type": "Feature",
  "properties": {
    "gn:admin1_code":"83",
    "gn:asciiname":"Monakovo",
    "gn:country_code":"RU",
    "gn:dem":124,
    "gn:feature_class":"P",
    "gn:feature_code":"PPL",
    "gn:name":"Monakovo",
    "gn:population":0,
    "gn:timezone":"Europe/Moscow",
    "iso:country":"RU",
    "name:rus_x_preferred":[
        "\u041c\u043e\u043d\u0430\u043a\u043e\u0432\u043e"
    ],
    "wof:name":"Monakovo",
    "wof:placetype":"locality"
},
  "geometry": {"coordinates":[39.98103,56.13596],"type":"Point"}
}