{
  "type": "Feature",
  "properties": {
    "gn:admin1_code":"21",
    "gn:asciiname":"Natalikha",
    "gn:country_code":"RU",
    "gn:dem":133,
    "gn:feature_class":"P",
    "gn:feature_code":"PPL",
    "gn:name":"Natalikha",
    "gn:population":0,
    "gn:timezone":"Europe/Moscow",
    "iso:country":"RU",
    "name:rus_x_preferred":[
        "\u041d\u0430\u0442\u0430\u043b\u0438\u0445\u0430"
    ],
    "wof:name":"Natalikha",
    "wof:placetype":"locality"
},
  "geometry": {"coordinates":[39.91742,56.63936999999999],"type":"Point"}
}