{
  "type": "Feature",
  "properties": {
    "gn:admin1_code":"33",
    "gn:asciiname":"Tatarnik",
    "gn:country_code":"RU",
    "gn:dem":174,
    "gn:feature_class":"P",
    "gn:feature_code":"PPL",
    "gn:name":"Tatarnik",
    "gn:population":0,
    "gn:timezone":"Europe/Kirov",
    "iso:country":"RU",
    "name:rus_x_preferred":[
        "\u0422\u0430\u0442\u0430\u0440\u043d\u0438\u043a"
    ],
    "wof:name":"Tatarnik",
    "wof:placetype":"locality"
},
  "geometry": {"coordinates":[49.4193,58.2051],"type":"Point"}
}