{
  "type": "Feature",
  "properties": {
    "gn:admin1_code":"13",
    "gn:asciiname":"Osikovka",
    "gn:country_code":"RU",
    "gn:dem":280,
    "gn:feature_class":"P",
    "gn:feature_code":"PPL",
    "gn:name":"Osikovka",
    "gn:population":0,
    "gn:timezone":"Asia/Yekaterinburg",
    "iso:country":"RU",
    "name:rus_x_preferred":[
        "\u041e\u0441\u0438\u043a\u043e\u0432\u043a\u0430"
    ],
    "name:und_x_variant":[
        "\u041e\u0441\u0438\u043a\u043e\u0432\u043a\u0430"
    ],
    "wof:name":"Osikovka",
    "wof:placetype":"locality"
},
  "geometry": {"coordinates":[60.81667,54.28333000000001],"type":"Point"}
}