{
  "type": "Feature",
  "properties": {
    "gn:admin1_code":"8",
    "gn:asciiname":"Mysovtsevo",
    "gn:country_code":"RU",
    "gn:dem":102,
    "gn:feature_class":"P",
    "gn:feature_code":"PPL",
    "gn:name":"Mysovtsevo",
    "gn:population":0,
    "gn:timezone":"Asia/Yekaterinburg",
    "iso:country":"RU",
    "name:rus_x_preferred":[
        "\u041c\u044b\u0441\u043e\u0432\u0446\u0435\u0432\u043e"
    ],
    "name:und_x_variant":[
        "Mysovtseva",
        "Mysovtsevo"
    ],
    "wof:name":"Mysovtsevo",
    "wof:placetype":"locality"
},
  "geometry": {"coordinates":[55.7415,54.64325],"type":"Point"}
}