{
  "type": "Feature",
  "properties": {
    "gn:admin1_code":"28",
    "gn:asciiname":"Nizhniye Vidany",
    "gn:country_code":"RU",
    "gn:dem":39,
    "gn:feature_class":"P",
    "gn:feature_code":"PPL",
    "gn:name":"Nizhniye Vidany",
    "gn:population":0,
    "gn:timezone":"Europe/Moscow",
    "iso:country":"RU",
    "name:fin_x_preferred":[
        "Ala-Viitana"
    ],
    "name:rus_x_preferred":[
        "\u041d\u0438\u0436\u043d\u0438\u0435 \u0412\u0438\u0434\u0430\u043d\u044b"
    ],
    "name:und_x_variant":[
        "\u041d\u0438\u0436\u043d\u0438\u0435 \u0412\u0438\u0434\u0430\u043d\u044b"
    ],
    "wof:name":"Nizhniye Vidany",
    "wof:placetype":"locality"
},
  "geometry": {"coordinates":[34.05,61.86666999999999],"type":"Point"}
}