{
  "type": "Feature",
  "properties": {
    "gn:admin1_code":"91",
    "gn:asciiname":"Innokent'yevskiy",
    "gn:country_code":"RU",
    "gn:dem":186,
    "gn:feature_class":"P",
    "gn:feature_code":"PPL",
    "gn:name":"Innokent\u2019yevskiy",
    "gn:population":0,
    "gn:timezone":"Asia/Krasnoyarsk",
    "iso:country":"RU",
    "name:rus_x_preferred":[
        "\u0418\u043d\u043d\u043e\u043a\u0435\u043d\u0442\u044c\u0435\u0432\u0441\u043a\u0438\u0439"
    ],
    "name:und_x_variant":[
        "Innokent\u2019yevskiy"
    ],
    "wof:name":"Innokent'yevskiy",
    "wof:placetype":"locality"
},
  "geometry": {"coordinates":[92.93619,56.04753],"type":"Point"}
}