{
  "type": "Feature",
  "properties": {
    "gn:admin1_code":"46",
    "gn:asciiname":"Tarkhanovo",
    "gn:country_code":"RU",
    "gn:dem":104,
    "gn:feature_class":"P",
    "gn:feature_code":"PPL",
    "gn:name":"Tarkhanovo",
    "gn:population":0,
    "gn:timezone":"Europe/Moscow",
    "iso:country":"RU",
    "name:eng_x_preferred":[
        "Tarkhanovo"
    ],
    "name:nor_x_preferred":[
        "Tarkhanovo"
    ],
    "name:rus_x_preferred":[
        "\u0422\u0430\u0440\u0445\u0430\u043d\u043e\u0432\u043e"
    ],
    "wof:name":"Tarkhanovo",
    "wof:placetype":"locality"
},
  "geometry": {"coordinates":[45.66198,54.76153000000001],"type":"Point"}
}