{
  "type": "Feature",
  "properties": {
    "gn:admin1_code":"38",
    "gn:asciiname":"Lozinskogo",
    "gn:country_code":"RU",
    "gn:dem":266,
    "gn:feature_class":"P",
    "gn:feature_code":"PPL",
    "gn:name":"Lozinskogo",
    "gn:population":0,
    "gn:timezone":"Europe/Moscow",
    "iso:country":"RU",
    "name:rus_x_preferred":[
        "\u041b\u043e\u0437\u0438\u043d\u0441\u043a\u043e\u0433\u043e"
    ],
    "name:und_x_variant":[
        "\u041b\u043e\u0437\u0438\u043d\u0441\u043a\u043e\u0433\u043e"
    ],
    "wof:name":"Lozinskogo",
    "wof:placetype":"locality"
},
  "geometry": {"coordinates":[38.93333,44.46667],"type":"Point"}
}