{
  "type": "Feature",
  "properties": {
    "gn:admin1_code":"8.0",
    "gn:asciiname":"Blyumental'",
    "gn:country_code":"RU",
    "gn:dem":287,
    "gn:feature_class":"P",
    "gn:feature_code":"PPL",
    "gn:name":"Blyumental\u2019",
    "gn:population":0,
    "gn:timezone":"Asia/Yekaterinburg",
    "iso:country":"RU",
    "name:rus_x_preferred":[
        "\u0411\u043b\u044e\u043c\u0435\u043d\u0442\u0430\u043b\u044c"
    ],
    "name:und_x_variant":[
        "Blyumental\u2019",
        "\u0411\u043b\u044e\u043c\u0435\u043d\u0442\u0430\u043b\u044c"
    ],
    "wof:name":"Blyumental'",
    "wof:placetype":"locality"
},
  "geometry": {"coordinates":[55.18333000000001,53.73333],"type":"Point"}
}