{
  "type": "Feature",
  "properties": {
    "gn:admin1_code":"19.0",
    "gn:asciiname":"Barsuki",
    "gn:country_code":"RU",
    "gn:dem":514,
    "gn:feature_class":"P",
    "gn:feature_code":"PPL",
    "gn:name":"Barsuki",
    "gn:population":0,
    "gn:timezone":"Europe/Moscow",
    "iso:country":"RU",
    "wof:name":"Barsuki",
    "wof:placetype":"locality"
},
  "geometry": {"coordinates":[44.80989,43.26021],"type":"Point"}
}