{
  "type": "Feature",
  "properties": {
    "gn:admin1_code":"37",
    "gn:asciiname":"Nogino",
    "gn:country_code":"RU",
    "gn:dem":178,
    "gn:feature_class":"P",
    "gn:feature_code":"PPL",
    "gn:name":"Nogino",
    "gn:population":0,
    "gn:timezone":"Europe/Moscow",
    "iso:country":"RU",
    "name:und_x_variant":[
        "Nogina",
        "Nogino"
    ],
    "wof:name":"Nogino",
    "wof:placetype":"locality"
},
  "geometry": {"coordinates":[41.82307,58.29015],"type":"Point"}
}