{
  "type": "Feature",
  "properties": {
    "gn:admin1_code":"69",
    "gn:asciiname":"Molevo",
    "gn:country_code":"RU",
    "gn:dem":194,
    "gn:feature_class":"P",
    "gn:feature_code":"PPL",
    "gn:name":"Mol\u00ebvo",
    "gn:population":0,
    "gn:timezone":"Europe/Moscow",
    "iso:country":"RU",
    "name:rus_x_preferred":[
        "\u041c\u043e\u043b\u0451\u0432\u043e"
    ],
    "name:und_x_variant":[
        "Mol\u00ebvo Boloto",
        "Mol\u00ebvo",
        "\u041c\u043e\u043b\u0451\u0432\u043e"
    ],
    "wof:name":"Molevo",
    "wof:placetype":"locality"
},
  "geometry": {"coordinates":[31.33204000000001,54.93976],"type":"Point"}
}