{
  "type": "Feature",
  "properties": {
    "gn:admin1_code":"83",
    "gn:asciiname":"Kalday",
    "gn:country_code":"RU",
    "gn:dem":127,
    "gn:feature_class":"P",
    "gn:feature_code":"PPL",
    "gn:name":"Kalday",
    "gn:population":0,
    "gn:timezone":"Europe/Moscow",
    "iso:country":"RU",
    "name:rus_x_preferred":[
        "\u041a\u0430\u043b\u0434\u0430\u0439"
    ],
    "name:und_x_variant":[
        "\u041a\u0430\u043b\u0434\u0430\u0439"
    ],
    "wof:name":"Kalday",
    "wof:placetype":"locality"
},
  "geometry": {"coordinates":[40.59129,55.352],"type":"Point"}
}