{
  "type": "Feature",
  "properties": {
    "gn:admin1_code":"42.0",
    "gn:asciiname":"Pustoshka",
    "gn:country_code":"RU",
    "gn:dem":80,
    "gn:feature_class":"P",
    "gn:feature_code":"PPL",
    "gn:name":"Pustoshka",
    "gn:population":0,
    "gn:timezone":"Europe/Moscow",
    "iso:country":"RU",
    "name:bel_x_preferred":[
        "\u041f\u0443\u0441\u0442\u043e\u0448\u043a\u0430"
    ],
    "name:fin_x_preferred":[
        "Kankaankyl\u00e4"
    ],
    "name:rus_x_preferred":[
        "\u041f\u0443\u0441\u0442\u043e\u0448\u043a\u0430"
    ],
    "name:ukr_x_preferred":[
        "\u041f\u0443\u0441\u0442\u043e\u0448\u043a\u0430"
    ],
    "name:und_x_variant":[
        "\u041f\u0443\u0441\u0442\u043e\u0448\u043a\u0430"
    ],
    "wof:name":"Pustoshka",
    "wof:placetype":"locality"
},
  "geometry": {"coordinates":[30.21167,59.51111],"type":"Point"}
}