{
  "type": "Feature",
  "properties": {
    "gn:admin1_code":"42",
    "gn:asciiname":"Korkino",
    "gn:country_code":"RU",
    "gn:dem":51,
    "gn:feature_class":"P",
    "gn:feature_code":"PPL",
    "gn:name":"Korkino",
    "gn:population":0,
    "gn:timezone":"Europe/Moscow",
    "iso:country":"RU",
    "name:fin_x_preferred":[
        "Korkkina"
    ],
    "name:rus_x_preferred":[
        "\u041a\u043e\u0440\u043a\u0438\u043d\u043e"
    ],
    "name:und_x_variant":[
        "\u041a\u043e\u0440\u043a\u0438\u043d\u043e"
    ],
    "wof:name":"Korkino",
    "wof:placetype":"locality"
},
  "geometry": {"coordinates":[30.7175,59.93056],"type":"Point"}
}