{
  "type": "Feature",
  "properties": {
    "gn:admin1_code":"17",
    "gn:asciiname":"Sur-Surbachi",
    "gn:country_code":"RU",
    "gn:dem":1897,
    "gn:feature_class":"P",
    "gn:feature_code":"PPL",
    "gn:name":"Sur-Surbachi",
    "gn:population":0,
    "gn:timezone":"Europe/Moscow",
    "iso:country":"RU",
    "name:und_x_variant":[
        "Sorsorbachi-Makhi",
        "Sursabachi",
        "Sur-Surbachi"
    ],
    "wof:name":"Sur-Surbachi",
    "wof:placetype":"locality"
},
  "geometry": {"coordinates":[47.49156,42.02698],"type":"Point"}
}