{
  "type": "Feature",
  "properties": {
    "gn:admin1_code":"83",
    "gn:asciiname":"Kikino",
    "gn:country_code":"RU",
    "gn:dem":150,
    "gn:feature_class":"P",
    "gn:feature_code":"PPL",
    "gn:name":"Kikino",
    "gn:population":0,
    "gn:timezone":"Europe/Moscow",
    "iso:country":"RU",
    "name:rus_x_preferred":[
        "\u041a\u0438\u043a\u0438\u043d\u043e"
    ],
    "wof:name":"Kikino",
    "wof:placetype":"locality"
},
  "geometry": {"coordinates":[39.18964,56.11202],"type":"Point"}
}