{
  "type": "Feature",
  "properties": {
    "gn:admin1_code":"76.0",
    "gn:asciiname":"Bashino",
    "gn:country_code":"RU",
    "gn:dem":211,
    "gn:feature_class":"P",
    "gn:feature_code":"PPL",
    "gn:name":"Bashino",
    "gn:population":0,
    "gn:timezone":"Europe/Moscow",
    "iso:country":"RU",
    "name:nor_x_preferred":[
        "Basjino"
    ],
    "name:rus_x_preferred":[
        "\u0411\u0430\u0448\u0438\u043d\u043e"
    ],
    "wof:name":"Bashino",
    "wof:placetype":"locality"
},
  "geometry": {"coordinates":[37.92886,54.70676],"type":"Point"}
}