{
  "type": "Feature",
  "properties": {
    "gn:admin1_code":"93",
    "gn:asciiname":"Mangiday",
    "gn:country_code":"RU",
    "gn:dem":422,
    "gn:feature_class":"P",
    "gn:feature_code":"PPL",
    "gn:name":"Mangiday",
    "gn:population":0,
    "gn:timezone":"Asia/Chita",
    "iso:country":"RU",
    "name:eng_x_preferred":[
        "Mangiday"
    ],
    "name:nor_x_preferred":[
        "Mangidaj"
    ],
    "name:rus_x_preferred":[
        "\u041c\u0430\u043d\u0433\u0438\u0434\u0430\u0439"
    ],
    "name:und_x_variant":[
        "\u041c\u0430\u043d\u0433\u0438\u0434\u0430\u0439",
        "Mangiday"
    ],
    "wof:name":"Mangiday",
    "wof:placetype":"locality"
},
  "geometry": {"coordinates":[118.51188999999999,52.37739000000001],"type":"Point"}
}