{
  "type": "Feature",
  "properties": {
    "gn:admin1_code":"55",
    "gn:asciiname":"Rabochiy Poselok",
    "gn:country_code":"RU",
    "gn:dem":185,
    "gn:feature_class":"P",
    "gn:feature_code":"PPL",
    "gn:name":"Rabochiy Pos\u00eblok",
    "gn:population":0,
    "gn:timezone":"Asia/Yekaterinburg",
    "iso:country":"RU",
    "name:rus_x_preferred":[
        "\u0420\u0430\u0431\u043e\u0447\u0438\u0439 \u041f\u043e\u0441\u0451\u043b\u043e\u043a"
    ],
    "name:und_x_variant":[
        "Rabochiy Pos\u00eblok"
    ],
    "wof:name":"Rabochiy Poselok",
    "wof:placetype":"locality"
},
  "geometry": {"coordinates":[51.859,52.746],"type":"Point"}
}