{
  "type": "Feature",
  "properties": {
    "gn:admin1_code":"45",
    "gn:asciiname":"Shimvazh",
    "gn:country_code":"RU",
    "gn:dem":158,
    "gn:feature_class":"P",
    "gn:feature_code":"PPL",
    "gn:name":"Shimvazh",
    "gn:population":0,
    "gn:timezone":"Europe/Moscow",
    "iso:country":"RU",
    "name:rus_x_preferred":[
        "\u0428\u0438\u043c\u0432\u0430\u0436"
    ],
    "name:und_x_variant":[
        "\u0428\u0438\u043c\u0432\u0430\u0436"
    ],
    "wof:name":"Shimvazh",
    "wof:placetype":"locality"
},
  "geometry": {"coordinates":[46.1785,56.0903],"type":"Point"}
}