{
  "type": "Feature",
  "properties": {
    "gn:admin1_code":"8",
    "gn:asciiname":"Sakatovo",
    "gn:country_code":"RU",
    "gn:dem":106,
    "gn:feature_class":"P",
    "gn:feature_code":"PPL",
    "gn:name":"Sakatovo",
    "gn:population":0,
    "gn:timezone":"Asia/Yekaterinburg",
    "iso:country":"RU",
    "name:aze_x_preferred":[
        "Sakat"
    ],
    "name:bak_x_preferred":[
        "\u0421\u0430\u04a1\u0430\u0442"
    ],
    "name:che_x_preferred":[
        "\u0421\u0430\u043a\u0430\u0442\u043e\u0432\u043e"
    ],
    "name:hye_x_preferred":[
        "\u054d\u0561\u056f\u0561\u057f\u0578\u057e\u0578"
    ],
    "name:kaz_x_preferred":[
        "\u0421\u0430\u043a\u0430\u0442"
    ],
    "name:kir_x_preferred":[
        "\u0421\u0430\u043a\u0430\u0442"
    ],
    "name:rus_x_preferred":[
        "\u0421\u0430\u043a\u0430\u0442\u043e\u0432\u043e"
    ],
    "name:tat_x_preferred":[
        "\u0427\u04d9\u043a\u04d9\u0442"
    ],
    "name:und_x_variant":[
        "Sokatova",
        "Sanatovo",
        "Sakatovo"
    ],
    "wof:name":"Sakatovo",
    "wof:placetype":"locality"
},
  "geometry": {"coordinates":[53.69889000000001,55.03806],"type":"Point"}
}