{
  "type": "Feature",
  "properties": {
    "gn:admin1_code":"8",
    "gn:asciiname":"Sakatovo",
    "gn:country_code":"RU",
    "gn:dem":106,
    "gn:feature_class":"P",
    "gn:feature_code":"PPL",
    "gn:name":"Sakatovo",
    "gn:population":0,
    "gn:timezone":"Asia/Yekaterinburg",
    "iso:country":"RU",
    "name:rus_x_preferred":[
        "\u0421\u0430\u043a\u0430\u0442\u043e\u0432\u043e"
    ],
    "name:und_x_variant":[
        "Sokatova",
        "Sanatovo",
        "Sakatovo",
        "\u0421\u0430\u043a\u0430\u0442\u043e\u0432\u043e"
    ],
    "wof:name":"Sakatovo",
    "wof:placetype":"locality"
},
  "geometry": {"coordinates":[53.69889000000001,55.03806],"type":"Point"}
}