{
  "type": "Feature",
  "properties": {
    "gn:admin1_code":"10",
    "gn:asciiname":"Goshch'",
    "gn:country_code":"RU",
    "gn:dem":188,
    "gn:feature_class":"P",
    "gn:feature_code":"PPL",
    "gn:name":"Goshch\u2019",
    "gn:population":0,
    "gn:timezone":"Europe/Moscow",
    "iso:country":"RU",
    "name:rus_x_preferred":[
        "\u0413\u043e\u0449\u044c"
    ],
    "name:und_x_variant":[
        "Goshch\u2019",
        "\u0413\u043e\u0449\u044c"
    ],
    "wof:name":"Goshch'",
    "wof:placetype":"locality"
},
  "geometry": {"coordinates":[34.65022,53.02042],"type":"Point"}
}