{
  "type": "Feature",
  "properties": {
    "gn:admin1_code":"37",
    "gn:asciiname":"Pechikhino",
    "gn:country_code":"RU",
    "gn:dem":257,
    "gn:feature_class":"P",
    "gn:feature_code":"PPL",
    "gn:name":"Pechikhino",
    "gn:population":0,
    "gn:timezone":"Europe/Moscow",
    "iso:country":"RU",
    "name:rus_x_preferred":[
        "\u041f\u0435\u0447\u0438\u0445\u0438\u043d\u043e"
    ],
    "name:und_x_variant":[
        "\u041f\u0435\u0447\u0438\u0445\u0438\u043d\u043e"
    ],
    "wof:name":"Pechikhino",
    "wof:placetype":"locality"
},
  "geometry": {"coordinates":[42.1519,58.8454],"type":"Point"}
}