{
  "type": "Feature",
  "properties": {
    "gn:admin1_code":"16.0",
    "gn:asciiname":"Chuteyevo",
    "gn:country_code":"RU",
    "gn:dem":120,
    "gn:feature_class":"P",
    "gn:feature_code":"PPL",
    "gn:name":"Chuteyevo",
    "gn:population":0,
    "gn:timezone":"Europe/Moscow",
    "iso:country":"RU",
    "name:eng_x_preferred":[
        "Chuteyevo"
    ],
    "name:nor_x_preferred":[
        "Tsjutejevo"
    ],
    "name:rus_x_preferred":[
        "\u0427\u0443\u0442\u0435\u0435\u0432\u043e"
    ],
    "name:und_x_variant":[
        "\u0427\u0443\u0442\u0435\u0435\u0432\u043e",
        "Chuteyevo"
    ],
    "wof:name":"Chuteyevo",
    "wof:placetype":"locality"
},
  "geometry": {"coordinates":[47.8301,55.39231],"type":"Point"}
}