{
  "type": "Feature",
  "properties": {
    "gn:admin1_code":"85",
    "gn:asciiname":"Kalinovo",
    "gn:country_code":"RU",
    "gn:dem":116,
    "gn:feature_class":"P",
    "gn:feature_code":"PPL",
    "gn:name":"Kalinovo",
    "gn:population":0,
    "gn:timezone":"Europe/Moscow",
    "iso:country":"RU",
    "name:rus_x_preferred":[
        "\u041a\u0430\u043b\u0438\u043d\u043e\u0432\u043e"
    ],
    "name:und_x_variant":[
        "\u041a\u0430\u043b\u0438\u043d\u043e\u0432\u043e"
    ],
    "wof:name":"Kalinovo",
    "wof:placetype":"locality"
},
  "geometry": {"coordinates":[39.88645,59.51373],"type":"Point"}
}