{
  "type": "Feature",
  "properties": {
    "gn:admin1_code":"85",
    "gn:asciiname":"Kalinovo",
    "gn:country_code":"RU",
    "gn:dem":116,
    "gn:feature_class":"P",
    "gn:feature_code":"PPL",
    "gn:name":"Kalinovo",
    "gn:population":0,
    "gn:timezone":"Europe/Moscow",
    "iso:country":"RU",
    "name:cat_x_preferred":[
        "Kalinovo"
    ],
    "name:ces_x_preferred":[
        "Kalinovo"
    ],
    "name:deu_x_preferred":[
        "Kalinovo"
    ],
    "name:epo_x_preferred":[
        "Kalinovo"
    ],
    "name:eus_x_preferred":[
        "Kalinovo"
    ],
    "name:fra_x_preferred":[
        "Kalinovo"
    ],
    "name:hun_x_preferred":[
        "K\u00e1ln\u00f3"
    ],
    "name:ita_x_preferred":[
        "Kalinovo"
    ],
    "name:msa_x_preferred":[
        "Kalinovo"
    ],
    "name:nld_x_preferred":[
        "Kalinovo"
    ],
    "name:pol_x_preferred":[
        "Kalinovo"
    ],
    "name:ron_x_preferred":[
        "Kalinovo"
    ],
    "name:rus_x_preferred":[
        "\u041a\u0430\u043b\u0438\u043d\u043e\u0432\u043e"
    ],
    "name:slk_x_preferred":[
        "Kalinovo"
    ],
    "name:spa_x_preferred":[
        "Kalinovo"
    ],
    "name:srp_x_preferred":[
        "\u041a\u0430\u043b\u0438\u043d\u043e\u0432\u043e"
    ],
    "name:ukr_x_preferred":[
        "\u041a\u0430\u043b\u0456\u043d\u043e\u0432\u043e"
    ],
    "name:war_x_preferred":[
        "Kalinovo"
    ],
    "wof:name":"Kalinovo",
    "wof:placetype":"locality"
},
  "geometry": {"coordinates":[39.88645,59.51373],"type":"Point"}
}