{
  "type": "Feature",
  "properties": {
    "gn:admin1_code":"88",
    "gn:asciiname":"Zvernitsy",
    "gn:country_code":"RU",
    "gn:dem":89,
    "gn:feature_class":"P",
    "gn:feature_code":"PPL",
    "gn:name":"Zvernitsy",
    "gn:population":0,
    "gn:timezone":"Europe/Moscow",
    "iso:country":"RU",
    "name:rus_x_preferred":[
        "\u0417\u0432\u0435\u0440\u043d\u0438\u0446\u044b"
    ],
    "wof:name":"Zvernitsy",
    "wof:placetype":"locality"
},
  "geometry": {"coordinates":[39.76525,57.63265],"type":"Point"}
}