{
  "type": "Feature",
  "properties": {
    "gn:admin1_code":"41",
    "gn:asciiname":"Kachanov",
    "gn:country_code":"RU",
    "gn:dem":151,
    "gn:feature_class":"P",
    "gn:feature_code":"PPL",
    "gn:name":"Kachanov",
    "gn:population":0,
    "gn:timezone":"Europe/Moscow",
    "iso:country":"RU",
    "name:rus_x_preferred":[
        "\u041a\u0430\u0447\u0430\u043d\u043e\u0432"
    ],
    "wof:name":"Kachanov",
    "wof:placetype":"locality"
},
  "geometry": {"coordinates":[34.2938,51.6548],"type":"Point"}
}