{
  "type": "Feature",
  "properties": {
    "gn:admin1_code":"51.0",
    "gn:asciiname":"Astashikha",
    "gn:country_code":"RU",
    "gn:dem":110,
    "gn:feature_class":"P",
    "gn:feature_code":"PPL",
    "gn:name":"Astashikha",
    "gn:population":0,
    "gn:timezone":"Europe/Moscow",
    "iso:country":"RU",
    "name:che_x_preferred":[
        "\u0410\u0441\u0442\u0430\u0448\u0438\u0445\u0430"
    ],
    "name:nor_x_preferred":[
        "Astasjikha"
    ],
    "name:rus_x_preferred":[
        "\u0410\u0441\u0442\u0430\u0448\u0438\u0445\u0430"
    ],
    "name:tgk_x_preferred":[
        "\u0410\u0441\u0442\u0430\u0448\u0438\u0445\u0430"
    ],
    "wof:name":"Astashikha",
    "wof:placetype":"locality"
},
  "geometry": {"coordinates":[45.32818,56.92324],"type":"Point"}
}