{
  "type": "Feature",
  "properties": {
    "gn:admin1_code":"83.0",
    "gn:asciiname":"Fedurniki",
    "gn:country_code":"RU",
    "gn:dem":115,
    "gn:feature_class":"P",
    "gn:feature_code":"PPL",
    "gn:name":"Fedurniki",
    "gn:population":0,
    "gn:timezone":"Europe/Moscow",
    "iso:country":"RU",
    "name:rus_x_preferred":[
        "\u0424\u0435\u0434\u0443\u0440\u043d\u0438\u043a\u0438"
    ],
    "name:und_x_variant":[
        "\u0424\u0435\u0434\u0443\u0440\u043d\u0438\u043a\u0438"
    ],
    "wof:name":"Fedurniki",
    "wof:placetype":"locality"
},
  "geometry": {"coordinates":[42.23333,56.21666999999999],"type":"Point"}
}