{
  "type": "Feature",
  "properties": {
    "gn:admin1_code":"67",
    "gn:asciiname":"Malyy Vyazok",
    "gn:country_code":"RU",
    "gn:dem":39,
    "gn:feature_class":"P",
    "gn:feature_code":"PPL",
    "gn:name":"Malyy Vyazok",
    "gn:population":0,
    "gn:timezone":"Europe/Saratov",
    "iso:country":"RU",
    "name:rus_x_preferred":[
        "\u041c\u0430\u043b\u044b\u0439 \u0412\u044f\u0437\u043e\u043a"
    ],
    "wof:name":"Malyy Vyazok",
    "wof:placetype":"locality"
},
  "geometry": {"coordinates":[48.0824,50.7887],"type":"Point"}
}