{
  "type": "Feature",
  "properties": {
    "gn:admin1_code":"70",
    "gn:asciiname":"Nevdakhin",
    "gn:country_code":"RU",
    "gn:dem":99,
    "gn:feature_class":"P",
    "gn:feature_code":"PPL",
    "gn:name":"Nevdakhin",
    "gn:population":0,
    "gn:timezone":"Europe/Moscow",
    "iso:country":"RU",
    "name:rus_x_preferred":[
        "\u041d\u0435\u0432\u0434\u0430\u0445\u0438\u043d"
    ],
    "name:und_x_variant":[
        "Nevdakhina",
        "Nevsakhin",
        "Nevdakhin",
        "\u041d\u0435\u0432\u0434\u0430\u0445\u0438\u043d"
    ],
    "wof:name":"Nevdakhin",
    "wof:placetype":"locality"
},
  "geometry": {"coordinates":[41.97381,45.5248],"type":"Point"}
}