{
  "type": "Feature",
  "properties": {
    "gn:admin1_code":"60",
    "gn:asciiname":"Zaborovo",
    "gn:country_code":"RU",
    "gn:dem":73,
    "gn:feature_class":"P",
    "gn:feature_code":"PPL",
    "gn:name":"Zaborovo",
    "gn:population":0,
    "gn:timezone":"Europe/Moscow",
    "iso:country":"RU",
    "name:rus_x_preferred":[
        "\u0417\u0430\u0431\u043e\u0440\u043e\u0432\u043e"
    ],
    "wof:name":"Zaborovo",
    "wof:placetype":"locality"
},
  "geometry": {"coordinates":[28.81936,57.08597],"type":"Point"}
}