{
  "type": "Feature",
  "properties": {
    "gn:admin1_code":"77",
    "gn:asciiname":"Shcherbaki",
    "gn:country_code":"RU",
    "gn:dem":164,
    "gn:feature_class":"P",
    "gn:feature_code":"PPL",
    "gn:name":"Shcherbaki",
    "gn:population":0,
    "gn:timezone":"Europe/Moscow",
    "iso:country":"RU",
    "name:rus_x_preferred":[
        "\u0429\u0435\u0440\u0431\u0430\u043a\u0438"
    ],
    "wof:name":"Shcherbaki",
    "wof:placetype":"locality"
},
  "geometry": {"coordinates":[35.41601,58.02667],"type":"Point"}
}