{
  "type": "Feature",
  "properties": {
    "gn:admin1_code":"60",
    "gn:asciiname":"Korentsy",
    "gn:country_code":"RU",
    "gn:dem":50,
    "gn:feature_class":"P",
    "gn:feature_code":"PPL",
    "gn:name":"Korentsy",
    "gn:population":0,
    "gn:timezone":"Europe/Moscow",
    "iso:country":"RU",
    "name:rus_x_preferred":[
        "\u041a\u043e\u0440\u0435\u043d\u0446\u044b"
    ],
    "wof:name":"Korentsy",
    "wof:placetype":"locality"
},
  "geometry": {"coordinates":[28.3929,57.8532],"type":"Point"}
}