{
  "type": "Feature",
  "properties": {
    "gn:admin1_code":"63",
    "gn:asciiname":"Taloye",
    "gn:country_code":"RU",
    "gn:dem":473,
    "gn:feature_class":"P",
    "gn:feature_code":"PPL",
    "gn:name":"Taloye",
    "gn:population":0,
    "gn:timezone":"Asia/Yakutsk",
    "iso:country":"RU",
    "wof:name":"Taloye",
    "wof:placetype":"locality"
},
  "geometry": {"coordinates":[127.65000000000001,60.48333],"type":"Point"}
}