{
  "type": "Feature",
  "properties": {
    "gn:admin1_code":"53",
    "gn:asciiname":"Novorozhdestvenskiy",
    "gn:cc2":"RU",
    "gn:country_code":"RU",
    "gn:dem":125,
    "gn:feature_class":"P",
    "gn:feature_code":"PPL",
    "gn:name":"Novorozhdestvenskiy",
    "gn:population":0,
    "gn:timezone":"Asia/Novosibirsk",
    "iso:country":"RU",
    "name:rus_x_preferred":[
        "\u041d\u043e\u0432\u043e\u0440\u043e\u0436\u0434\u0435\u0441\u0442\u0432\u0435\u043d\u0441\u043a\u0438\u0439"
    ],
    "name:und_x_variant":[
        "Rozhdestvenskiy",
        "Novorozhdestvenskiy",
        "\u041d\u043e\u0432\u043e\u0440\u043e\u0436\u0434\u0435\u0441\u0442\u0432\u0435\u043d\u0441\u043a\u0438\u0439"
    ],
    "wof:name":"Novorozhdestvenskiy",
    "wof:placetype":"locality"
},
  "geometry": {"coordinates":[79.51666999999998,55.53333000000001],"type":"Point"}
}