{
  "type": "Feature",
  "properties": {
    "gn:admin1_code":"90.0",
    "gn:asciiname":"Doynaya",
    "gn:country_code":"RU",
    "gn:dem":160,
    "gn:feature_class":"P",
    "gn:feature_code":"PPL",
    "gn:name":"Doynaya",
    "gn:population":0,
    "gn:timezone":"Asia/Yekaterinburg",
    "iso:country":"RU",
    "name:rus_x_preferred":[
        "\u0414\u043e\u0439\u043d\u0430\u044f"
    ],
    "wof:name":"Doynaya",
    "wof:placetype":"locality"
},
  "geometry": {"coordinates":[55.0273,56.67100000000001],"type":"Point"}
}