{
  "type": "Feature",
  "properties": {
    "gn:admin1_code":"42",
    "gn:asciiname":"Sokolov Ruchey",
    "gn:country_code":"RU",
    "gn:dem":54,
    "gn:feature_class":"P",
    "gn:feature_code":"PPL",
    "gn:name":"Sokolov Ruchey",
    "gn:population":0,
    "gn:timezone":"Europe/Moscow",
    "iso:country":"RU",
    "name:rus_x_preferred":[
        "\u0421\u043e\u043a\u043e\u043b\u043e\u0432 \u0420\u0443\u0447\u0435\u0439"
    ],
    "wof:name":"Sokolov Ruchey",
    "wof:placetype":"locality"
},
  "geometry": {"coordinates":[31.11667000000001,59.38333000000001],"type":"Point"}
}