{
  "type": "Feature",
  "properties": {
    "gn:admin1_code":"51.0",
    "gn:asciiname":"Mishino",
    "gn:country_code":"RU",
    "gn:dem":112,
    "gn:feature_class":"P",
    "gn:feature_code":"PPL",
    "gn:name":"Mishino",
    "gn:population":0,
    "gn:timezone":"Europe/Moscow",
    "iso:country":"RU",
    "name:nor_x_preferred":[
        "Misjino"
    ],
    "name:rus_x_preferred":[
        "\u041c\u0438\u0448\u0438\u043d\u043e"
    ],
    "wof:name":"Mishino",
    "wof:placetype":"locality"
},
  "geometry": {"coordinates":[42.9448,56.70545],"type":"Point"}
}