{
  "type": "Feature",
  "properties": {
    "gn:admin1_code":"77",
    "gn:asciiname":"Pyatnitskoye",
    "gn:country_code":"RU",
    "gn:dem":199,
    "gn:feature_class":"P",
    "gn:feature_code":"PPL",
    "gn:name":"Pyatnitskoye",
    "gn:population":0,
    "gn:timezone":"Europe/Moscow",
    "iso:country":"RU",
    "name:rus_x_preferred":[
        "\u041f\u044f\u0442\u043d\u0438\u0442\u0441\u043a\u043e\u0435"
    ],
    "name:und_x_variant":[
        "Pavlyuki",
        "Pyatnitskoye",
        "\u041f\u044f\u0442\u043d\u0438\u0442\u0441\u043a\u043e\u0435"
    ],
    "wof:name":"Pyatnitskoye",
    "wof:placetype":"locality"
},
  "geometry": {"coordinates":[34.01873,56.09497],"type":"Point"}
}