{
  "type": "Feature",
  "properties": {
    "gn:admin1_code":"38",
    "gn:asciiname":"Livonskoye",
    "gn:country_code":"RU",
    "gn:dem":327,
    "gn:feature_class":"P",
    "gn:feature_code":"PPL",
    "gn:name":"Livonskoye",
    "gn:population":0,
    "gn:timezone":"Europe/Moscow",
    "iso:country":"RU",
    "wof:name":"Livonskoye",
    "wof:placetype":"locality"
},
  "geometry": {"coordinates":[41.34639,44.64444],"type":"Point"}
}