{
  "type": "Feature",
  "properties": {
    "gn:admin1_code":"13",
    "gn:asciiname":"Uysko-Sanarskiy",
    "gn:country_code":"RU",
    "gn:dem":190,
    "gn:feature_class":"P",
    "gn:feature_code":"PPL",
    "gn:name":"Uysko-Sanarskiy",
    "gn:population":0,
    "gn:timezone":"Asia/Yekaterinburg",
    "iso:country":"RU",
    "name:rus_x_preferred":[
        "\u0423\u0439\u0441\u043a\u043e-\u0421\u0430\u043d\u0430\u0440\u0441\u043a\u0438\u0439"
    ],
    "wof:name":"Uysko-Sanarskiy",
    "wof:placetype":"locality"
},
  "geometry": {"coordinates":[61.1822,54.0863],"type":"Point"}
}