{
  "type": "Feature",
  "properties": {
    "gn:admin1_code":"25",
    "gn:asciiname":"Zharikov",
    "gn:country_code":"RU",
    "gn:dem":216,
    "gn:feature_class":"P",
    "gn:feature_code":"PPL",
    "gn:name":"Zharikov",
    "gn:population":0,
    "gn:timezone":"Europe/Moscow",
    "iso:country":"RU",
    "name:und_x_variant":[
        "Zharikova",
        "Zharikov"
    ],
    "wof:name":"Zharikov",
    "wof:placetype":"locality"
},
  "geometry": {"coordinates":[34.53568,54.17916999999999],"type":"Point"}
}