{
  "type": "Feature",
  "properties": {
    "gn:admin1_code":"90",
    "gn:asciiname":"Oshib",
    "gn:country_code":"RU",
    "gn:dem":159,
    "gn:feature_class":"P",
    "gn:feature_code":"PPL",
    "gn:name":"Oshib",
    "gn:population":0,
    "gn:timezone":"Asia/Yekaterinburg",
    "iso:country":"RU",
    "name:rus_x_preferred":[
        "\u041e\u0448\u0438\u0431"
    ],
    "name:und_x_variant":[
        "\u041e\u0448\u0438\u0431"
    ],
    "wof:name":"Oshib",
    "wof:placetype":"locality"
},
  "geometry": {"coordinates":[54.87694000000001,59.22],"type":"Point"}
}