{
  "type": "Feature",
  "properties": {
    "iso:country":"RU",
    "name:rus_x_preferred":[
        "\u0421\u0435\u0432\u0435\u0440\u043e-\u041f\u0440\u0438\u043c\u043e\u0440\u0441\u043a\u0430\u044f \u0447\u0430\u0441\u0442\u044c"
    ],
    "wof:name":"Severo-Primorskaja chast",
    "wof:placetype":"neighbourhood"
},
  "geometry": {"coordinates":[30.21531425722787,60.00169604521118],"type":"Point"}
}