{
  "type": "Feature",
  "properties": {
    "gn:admin1_code":"73",
    "gn:asciiname":"Isleytar",
    "gn:cc2":"RU",
    "gn:country_code":"RU",
    "gn:dem":209,
    "gn:feature_class":"P",
    "gn:feature_code":"PPL",
    "gn:name":"Isleytar",
    "gn:population":0,
    "gn:timezone":"Europe/Moscow",
    "iso:country":"RU",
    "name:eng_x_preferred":[
        "Isleytar"
    ],
    "name:nor_x_preferred":[
        "Islejtar"
    ],
    "name:rus_x_preferred":[
        "\u0418\u0441\u043b\u0435\u0439\u0442\u0430\u0440"
    ],
    "name:und_x_variant":[
        "Isletar",
        "\u0418\u0441\u043b\u0435\u0439\u0442\u0430\u0440",
        "Isleytar"
    ],
    "wof:name":"Isleytar",
    "wof:placetype":"locality"
},
  "geometry": {"coordinates":[49.15861,56.32471999999999],"type":"Point"}
}