{
  "type": "Feature",
  "properties": {
    "gn:admin1_code":"88.0",
    "gn:asciiname":"Krutik",
    "gn:country_code":"RU",
    "gn:dem":93,
    "gn:feature_class":"P",
    "gn:feature_code":"PPL",
    "gn:name":"Krutik",
    "gn:population":0,
    "gn:timezone":"Europe/Moscow",
    "iso:country":"RU",
    "name:rus_x_preferred":[
        "\u041a\u0440\u0443\u0442\u0438\u043a"
    ],
    "wof:name":"Krutik",
    "wof:placetype":"locality"
},
  "geometry": {"coordinates":[40.77555,58.08379],"type":"Point"}
}