{
  "type": "Feature",
  "properties": {
    "gn:admin1_code":"38.0",
    "gn:asciiname":"Dubinin",
    "gn:country_code":"RU",
    "gn:dem":165,
    "gn:feature_class":"P",
    "gn:feature_code":"PPL",
    "gn:name":"Dubinin",
    "gn:population":0,
    "gn:timezone":"Europe/Moscow",
    "iso:country":"RU",
    "name:slv_x_preferred":[
        "Dubinin"
    ],
    "wof:name":"Dubinin",
    "wof:placetype":"locality"
},
  "geometry": {"coordinates":[39.01667,44.63306],"type":"Point"}
}