{
  "type": "Feature",
  "properties": {
    "gn:admin1_code":"55",
    "gn:asciiname":"Kamyshevka",
    "gn:country_code":"RU",
    "gn:dem":170,
    "gn:feature_class":"P",
    "gn:feature_code":"PPL",
    "gn:name":"Kamyshevka",
    "gn:population":0,
    "gn:timezone":"Asia/Yekaterinburg",
    "iso:country":"RU",
    "name:eng_x_preferred":[
        "Kamyshevka"
    ],
    "name:nor_x_preferred":[
        "Kamysjevka"
    ],
    "name:rus_x_preferred":[
        "\u041a\u0430\u043c\u044b\u0448\u0435\u0432\u043a\u0430"
    ],
    "name:und_x_variant":[
        "\u041a\u0430\u043c\u044b\u0448\u0435\u0432\u043a\u0430",
        "Kamyshevka",
        "Kamyshovka"
    ],
    "wof:name":"Kamyshevka",
    "wof:placetype":"locality"
},
  "geometry": {"coordinates":[54.38333000000001,52.23333],"type":"Point"}
}