{
  "type": "Feature",
  "properties": {
    "gn:admin1_code":"93",
    "gn:asciiname":"Orsuk",
    "gn:country_code":"RU",
    "gn:dem":709,
    "gn:feature_class":"P",
    "gn:feature_code":"PPL",
    "gn:name":"Orsuk",
    "gn:population":0,
    "gn:timezone":"Asia/Chita",
    "iso:country":"RU",
    "name:eng_x_preferred":[
        "Orsuk"
    ],
    "name:nor_x_preferred":[
        "Orsuk"
    ],
    "name:rus_x_preferred":[
        "\u041e\u0440\u0441\u0443\u043a"
    ],
    "name:und_x_variant":[
        "Orsun",
        "Ozhuk\u2019",
        "\u041e\u0440\u0441\u0443\u043a",
        "Orsuk"
    ],
    "wof:name":"Orsuk",
    "wof:placetype":"locality"
},
  "geometry": {"coordinates":[108.8115,50.957],"type":"Point"}
}