{
  "type": "Feature",
  "properties": {
    "gn:admin1_code":"38",
    "gn:asciiname":"Kalinino",
    "gn:country_code":"RU",
    "gn:dem":28,
    "gn:feature_class":"P",
    "gn:feature_code":"PPL",
    "gn:name":"Kalinino",
    "gn:population":0,
    "gn:timezone":"Europe/Moscow",
    "iso:country":"RU",
    "name:ceb_x_preferred":[
        "Kalinino"
    ],
    "name:deu_x_preferred":[
        "Kalinino"
    ],
    "name:eng_x_preferred":[
        "Kalinino"
    ],
    "name:kat_x_preferred":[
        "\u10d9\u10d0\u10da\u10d8\u10dc\u10d8\u10dc\u10dd"
    ],
    "name:nor_x_preferred":[
        "Kalinino"
    ],
    "name:rus_x_preferred":[
        "\u041a\u0430\u043b\u0438\u043d\u0438\u043d\u043e"
    ],
    "name:swe_x_preferred":[
        "Kalinino"
    ],
    "wof:name":"Kalinino",
    "wof:placetype":"locality"
},
  "geometry": {"coordinates":[38.93929,45.1084],"type":"Point"}
}