{
  "type": "Feature",
  "properties": {
    "gn:admin1_code":"42",
    "gn:asciiname":"Rekhkolovo",
    "gn:country_code":"RU",
    "gn:dem":72,
    "gn:feature_class":"P",
    "gn:feature_code":"PPL",
    "gn:name":"Rekhkolovo",
    "gn:population":0,
    "gn:timezone":"Europe/Moscow",
    "iso:country":"RU",
    "name:fin_x_preferred":[
        "Kapasi"
    ],
    "name:rus_x_preferred":[
        "\u0420\u0435\u0445\u043a\u043e\u043b\u043e\u0432\u043e"
    ],
    "wof:name":"Rekhkolovo",
    "wof:placetype":"locality"
},
  "geometry": {"coordinates":[30.30703,59.73438],"type":"Point"}
}