{
  "type": "Feature",
  "properties": {
    "gn:admin1_code":"10",
    "gn:asciiname":"Kryzhino",
    "gn:country_code":"RU",
    "gn:dem":203,
    "gn:feature_class":"P",
    "gn:feature_code":"PPL",
    "gn:name":"Kryzhino",
    "gn:population":0,
    "gn:timezone":"Europe/Moscow",
    "iso:country":"RU",
    "name:rus_x_preferred":[
        "\u041a\u0440\u044b\u0436\u0438\u043d\u043e"
    ],
    "name:und_x_variant":[
        "Kkyzhino",
        "Kryzheno",
        "Kryzhino"
    ],
    "wof:name":"Kryzhino",
    "wof:placetype":"locality"
},
  "geometry": {"coordinates":[33.69538,53.37028000000001],"type":"Point"}
}