{
  "type": "Feature",
  "properties": {
    "gn:admin1_code":"51",
    "gn:asciiname":"Begovatovo",
    "gn:country_code":"RU",
    "gn:dem":122,
    "gn:feature_class":"P",
    "gn:feature_code":"PPL",
    "gn:name":"Begovatovo",
    "gn:population":0,
    "gn:timezone":"Europe/Moscow",
    "iso:country":"RU",
    "name:rus_x_preferred":[
        "\u0411\u0435\u0433\u043e\u0432\u0430\u0442\u043e\u0432\u043e"
    ],
    "wof:name":"Begovatovo",
    "wof:placetype":"locality"
},
  "geometry": {"coordinates":[42.7124,54.8256],"type":"Point"}
}