{
  "type": "Feature",
  "properties": {
    "gn:admin1_code":"60",
    "gn:asciiname":"Bereznitsa",
    "gn:country_code":"RU",
    "gn:dem":91,
    "gn:feature_class":"P",
    "gn:feature_code":"PPL",
    "gn:name":"Bereznitsa",
    "gn:population":0,
    "gn:timezone":"Europe/Moscow",
    "iso:country":"RU",
    "name:rus_x_preferred":[
        "\u0411\u0435\u0440e\u0437\u043d\u0438\u0446\u0430"
    ],
    "wof:name":"Bereznitsa",
    "wof:placetype":"locality"
},
  "geometry": {"coordinates":[28.33192,56.77231],"type":"Point"}
}