{
  "type": "Feature",
  "properties": {
    "gn:admin1_code":"53",
    "gn:asciiname":"Chaymaki",
    "gn:country_code":"RU",
    "gn:dem":112,
    "gn:feature_class":"P",
    "gn:feature_code":"PPL",
    "gn:name":"Chaymaki",
    "gn:population":0,
    "gn:timezone":"Asia/Novosibirsk",
    "iso:country":"RU",
    "name:rus_x_preferred":[
        "\u0427\u0430\u0439\u043c\u0430\u043a\u0438"
    ],
    "name:und_x_variant":[
        "\u0427\u0430\u0439\u043c\u0430\u043a\u0438"
    ],
    "wof:name":"Chaymaki",
    "wof:placetype":"locality"
},
  "geometry": {"coordinates":[77.08333,56.15],"type":"Point"}
}