{
  "type": "Feature",
  "properties": {
    "gn:admin1_code":"4",
    "gn:asciiname":"Omutskoye",
    "gn:country_code":"RU",
    "gn:dem":122,
    "gn:feature_class":"P",
    "gn:feature_code":"PPL",
    "gn:name":"Omutskoye",
    "gn:population":0,
    "gn:timezone":"Asia/Barnaul",
    "iso:country":"RU",
    "name:eng_x_preferred":[
        "Omutskoye"
    ],
    "name:nor_x_preferred":[
        "Omutskoje"
    ],
    "name:rus_x_preferred":[
        "\u041e\u043c\u0443\u0442\u0441\u043a\u043e\u0435"
    ],
    "name:und_x_variant":[
        "Omutskaya"
    ],
    "wof:name":"Omutskoye",
    "wof:placetype":"locality"
},
  "geometry": {"coordinates":[82.21799999999998,53.4855],"type":"Point"}
}