{
  "type": "Feature",
  "properties": {
    "gn:admin1_code":"71",
    "gn:asciiname":"Rassvet",
    "gn:country_code":"RU",
    "gn:dem":146,
    "gn:feature_class":"P",
    "gn:feature_code":"PPL",
    "gn:name":"Rassvet",
    "gn:population":0,
    "gn:timezone":"Asia/Yekaterinburg",
    "iso:country":"RU",
    "name:rus_x_preferred":[
        "\u0420\u0430\u0441\u0441\u0432\u0435\u0442"
    ],
    "wof:name":"Rassvet",
    "wof:placetype":"locality"
},
  "geometry": {"coordinates":[62.6095,56.9958],"type":"Point"}
}