{
  "type": "Feature",
  "properties": {
    "gn:admin1_code":"62",
    "gn:asciiname":"Maloye Pirogovo",
    "gn:country_code":"RU",
    "gn:dem":98,
    "gn:feature_class":"P",
    "gn:feature_code":"PPL",
    "gn:name":"Maloye Pirogovo",
    "gn:population":0,
    "gn:timezone":"Europe/Moscow",
    "iso:country":"RU",
    "name:rus_x_preferred":[
        "\u041c\u0430\u043b\u043e\u0435 \u041f\u0438\u0440\u043e\u0433\u043e\u0432\u043e"
    ],
    "name:und_x_variant":[
        "Malyye Pirogi",
        "Maloye Pirogovo"
    ],
    "wof:name":"Maloye Pirogovo",
    "wof:placetype":"locality"
},
  "geometry": {"coordinates":[40.2668,54.2279],"type":"Point"}
}