{
  "type": "Feature",
  "properties": {
    "gn:admin1_code":"4",
    "gn:asciiname":"Suvorovka",
    "gn:country_code":"RU",
    "gn:dem":105,
    "gn:feature_class":"P",
    "gn:feature_code":"PPL",
    "gn:name":"Suvorovka",
    "gn:population":0,
    "gn:timezone":"Asia/Barnaul",
    "iso:country":"RU",
    "wof:name":"Suvorovka",
    "wof:placetype":"locality"
},
  "geometry": {"coordinates":[78.25,53.18333000000001],"type":"Point"}
}