{
  "type": "Feature",
  "properties": {
    "gn:admin1_code":"51",
    "gn:asciiname":"Steshikha",
    "gn:country_code":"RU",
    "gn:dem":162,
    "gn:feature_class":"P",
    "gn:feature_code":"PPL",
    "gn:name":"Steshikha",
    "gn:population":0,
    "gn:timezone":"Europe/Moscow",
    "iso:country":"RU",
    "name:eng_x_preferred":[
        "Steshikha"
    ],
    "name:nor_x_preferred":[
        "Stesjikha"
    ],
    "name:rus_x_preferred":[
        "\u0421\u0442\u0435\u0448\u0438\u0445\u0430"
    ],
    "wof:name":"Steshikha",
    "wof:placetype":"locality"
},
  "geometry": {"coordinates":[46.0547,57.73317],"type":"Point"}
}