{
  "type": "Feature",
  "properties": {
    "gn:admin1_code":"77",
    "gn:asciiname":"Prokhorovo",
    "gn:country_code":"RU",
    "gn:dem":169,
    "gn:feature_class":"P",
    "gn:feature_code":"PPL",
    "gn:name":"Prokhorovo",
    "gn:population":0,
    "gn:timezone":"Europe/Moscow",
    "iso:country":"RU",
    "name:rus_x_preferred":[
        "\u041f\u0440\u043e\u0445\u043e\u0440\u043e\u0432\u043e"
    ],
    "name:und_x_variant":[
        "\u041f\u0440\u043e\u0445\u043e\u0440\u043e\u0432\u043e"
    ],
    "wof:name":"Prokhorovo",
    "wof:placetype":"locality"
},
  "geometry": {"coordinates":[34.82995,57.71226],"type":"Point"}
}