{
  "type": "Feature",
  "properties": {
    "gn:admin1_code":"60",
    "gn:asciiname":"Torchilovo",
    "gn:country_code":"RU",
    "gn:dem":154,
    "gn:feature_class":"P",
    "gn:feature_code":"PPL",
    "gn:name":"Torchilovo",
    "gn:population":0,
    "gn:timezone":"Europe/Moscow",
    "iso:country":"RU",
    "name:rus_x_preferred":[
        "\u0422\u043e\u0440\u0447\u0438\u043b\u043e\u0432\u043e"
    ],
    "wof:name":"Torchilovo",
    "wof:placetype":"locality"
},
  "geometry": {"coordinates":[29.19,56.2779],"type":"Point"}
}