{
  "type": "Feature",
  "properties": {
    "gn:admin1_code":"57",
    "gn:asciiname":"Shelemis",
    "gn:country_code":"RU",
    "gn:dem":226,
    "gn:feature_class":"P",
    "gn:feature_code":"PPL",
    "gn:name":"Shelemis",
    "gn:population":0,
    "gn:timezone":"Europe/Moscow",
    "iso:country":"RU",
    "name:rus_x_preferred":[
        "\u0428\u0435\u043b\u0435\u043c\u0438\u0441"
    ],
    "wof:name":"Shelemis",
    "wof:placetype":"locality"
},
  "geometry": {"coordinates":[46.64843,53.26184],"type":"Point"}
}