{
  "type": "Feature",
  "properties": {
    "gn:admin1_code":"60",
    "gn:asciiname":"Svetloye",
    "gn:country_code":"RU",
    "gn:dem":232,
    "gn:feature_class":"P",
    "gn:feature_code":"PPL",
    "gn:name":"Svetloye",
    "gn:population":0,
    "gn:timezone":"Europe/Moscow",
    "iso:country":"RU",
    "name:rus_x_preferred":[
        "\u0421\u0432\u0435\u0442\u043b\u043e\u0435"
    ],
    "name:und_x_variant":[
        "\u0421\u0432\u0435\u0442\u043b\u043e\u0435"
    ],
    "wof:name":"Svetloye",
    "wof:placetype":"locality"
},
  "geometry": {"coordinates":[29.8876,56.1954],"type":"Point"}
}