{
  "type": "Feature",
  "properties": {
    "gn:admin1_code":"29",
    "gn:asciiname":"Kolkhoznyy Gorodok",
    "gn:country_code":"RU",
    "gn:dem":221,
    "gn:feature_class":"P",
    "gn:feature_code":"PPL",
    "gn:name":"Kolkhoznyy Gorodok",
    "gn:population":0,
    "gn:timezone":"Asia/Novokuznetsk",
    "iso:country":"RU",
    "name:rus_x_preferred":[
        "\u041a\u043e\u043b\u0445\u043e\u0437\u043d\u044b\u0439 \u0413\u043e\u0440\u043e\u0434\u043e\u043a"
    ],
    "wof:name":"Kolkhoznyy Gorodok",
    "wof:placetype":"locality"
},
  "geometry": {"coordinates":[87.10720000000001,53.8108],"type":"Point"}
}