{
  "type": "Feature",
  "properties": {
    "gn:admin1_code":"69.0",
    "gn:asciiname":"Dedenki",
    "gn:country_code":"RU",
    "gn:dem":190,
    "gn:feature_class":"P",
    "gn:feature_code":"PPL",
    "gn:name":"Ded\u00ebnki",
    "gn:population":0,
    "gn:timezone":"Europe/Moscow",
    "iso:country":"RU",
    "name:rus_x_preferred":[
        "\u0414\u0435\u0434\u0451\u043d\u043a\u0438"
    ],
    "name:und_x_variant":[
        "Ded\u00ebnki"
    ],
    "wof:name":"Dedenki",
    "wof:placetype":"locality"
},
  "geometry": {"coordinates":[31.49545,55.14141],"type":"Point"}
}