{
  "type": "Feature",
  "properties": {
    "gn:admin1_code":"51",
    "gn:asciiname":"Vetoshkino",
    "gn:country_code":"RU",
    "gn:dem":151,
    "gn:feature_class":"P",
    "gn:feature_code":"PPL",
    "gn:name":"Vetoshkino",
    "gn:population":0,
    "gn:timezone":"Europe/Moscow",
    "iso:country":"RU",
    "name:eng_x_preferred":[
        "Vetoshkino"
    ],
    "name:nor_x_preferred":[
        "Vetosjkino"
    ],
    "name:rus_x_preferred":[
        "\u0412\u0435\u0442\u043e\u0448\u043a\u0438\u043d\u043e"
    ],
    "name:und_x_variant":[
        "Yetoshkino",
        "Vetoshkino"
    ],
    "wof:name":"Vetoshkino",
    "wof:placetype":"locality"
},
  "geometry": {"coordinates":[45.05918,55.29233000000001],"type":"Point"}
}