{
  "type": "Feature",
  "properties": {
    "gn:admin1_code":"69",
    "gn:asciiname":"Ryabtsevo",
    "gn:country_code":"RU",
    "gn:dem":188,
    "gn:feature_class":"P",
    "gn:feature_code":"PPL",
    "gn:name":"Ryabtsevo",
    "gn:population":0,
    "gn:timezone":"Europe/Moscow",
    "iso:country":"RU",
    "name:rus_x_preferred":[
        "\u0420\u044f\u0431\u0446\u0435\u0432\u043e"
    ],
    "name:und_x_variant":[
        "Ryabtsova",
        "Ryabtsevo"
    ],
    "wof:name":"Ryabtsevo",
    "wof:placetype":"locality"
},
  "geometry": {"coordinates":[32.35002,54.63973000000001],"type":"Point"}
}