{
  "type": "Feature",
  "properties": {
    "gn:admin1_code":"52",
    "gn:asciiname":"Berezovaya Izba",
    "gn:country_code":"RU",
    "gn:dem":133,
    "gn:feature_class":"P",
    "gn:feature_code":"PPL",
    "gn:name":"Ber\u00ebzovaya Izba",
    "gn:population":0,
    "gn:timezone":"Europe/Moscow",
    "iso:country":"RU",
    "name:rus_x_preferred":[
        "\u0411\u0435\u0440\u0451\u0437\u043e\u0432\u0430\u044f \u0418\u0437\u0431\u0430"
    ],
    "name:und_x_variant":[
        "Ber\u00ebzovaya Izba"
    ],
    "wof:name":"Berezovaya Izba",
    "wof:placetype":"locality"
},
  "geometry": {"coordinates":[31.8331,57.1879],"type":"Point"}
}