{
  "type": "Feature",
  "properties": {
    "gn:admin1_code":"67",
    "gn:asciiname":"Pichurino",
    "gn:country_code":"RU",
    "gn:dem":147,
    "gn:feature_class":"P",
    "gn:feature_code":"PPL",
    "gn:name":"Pichurino",
    "gn:population":0,
    "gn:timezone":"Europe/Saratov",
    "iso:country":"RU",
    "name:eng_x_preferred":[
        "Pichurino"
    ],
    "name:nor_x_preferred":[
        "Pitsjurino"
    ],
    "name:rus_x_preferred":[
        "\u041f\u0438\u0447\u0443\u0440\u0438\u043d\u043e"
    ],
    "name:und_x_variant":[
        "\u041f\u0438\u0447\u0443\u0440\u0438\u043d\u043e",
        "Pichurino"
    ],
    "wof:name":"Pichurino",
    "wof:placetype":"locality"
},
  "geometry": {"coordinates":[43.0991,51.2269],"type":"Point"}
}