{
  "type": "Feature",
  "properties": {
    "gn:admin1_code":"45",
    "gn:asciiname":"Vakhrushevo",
    "gn:country_code":"RU",
    "gn:dem":118,
    "gn:feature_class":"P",
    "gn:feature_code":"PPL",
    "gn:name":"Vakhrushevo",
    "gn:population":0,
    "gn:timezone":"Europe/Volgograd",
    "iso:country":"RU",
    "name:rus_x_preferred":[
        "\u0412\u0430\u0445\u0440\u0443\u0448\u0435\u0432\u043e"
    ],
    "wof:name":"Vakhrushevo",
    "wof:placetype":"locality"
},
  "geometry": {"coordinates":[49.1678,57.207],"type":"Point"}
}