{
  "type": "Feature",
  "properties": {
    "gn:admin1_code":"60",
    "gn:asciiname":"Bryukashi",
    "gn:country_code":"RU",
    "gn:dem":66,
    "gn:feature_class":"P",
    "gn:feature_code":"PPL",
    "gn:name":"Bryukashi",
    "gn:population":0,
    "gn:timezone":"Europe/Moscow",
    "iso:country":"RU",
    "name:rus_x_preferred":[
        "\u0411\u0440\u044e\u043a\u0430\u0448\u0438"
    ],
    "wof:name":"Bryukashi",
    "wof:placetype":"locality"
},
  "geometry": {"coordinates":[28.18377000000001,57.17378000000001],"type":"Point"}
}