{
  "type": "Feature",
  "properties": {
    "gn:admin1_code":"73",
    "gn:asciiname":"Mariyskoye Tekashevo",
    "gn:country_code":"RU",
    "gn:dem":153,
    "gn:feature_class":"P",
    "gn:feature_code":"PPL",
    "gn:name":"Mariyskoye Tekashevo",
    "gn:population":0,
    "gn:timezone":"Europe/Moscow",
    "iso:country":"RU",
    "name:rus_x_preferred":[
        "\u041c\u0430\u0440\u0438\u0439\u0441\u043a\u043e\u0435 \u0422\u0435\u043a\u0430\u0448\u0435\u0432\u043e"
    ],
    "wof:name":"Mariyskoye Tekashevo",
    "wof:placetype":"locality"
},
  "geometry": {"coordinates":[52.422,55.97],"type":"Point"}
}