{
  "type": "Feature",
  "properties": {
    "gn:admin1_code":"73",
    "gn:asciiname":"Novyy Pochinok",
    "gn:country_code":"RU",
    "gn:dem":120,
    "gn:feature_class":"P",
    "gn:feature_code":"PPL",
    "gn:name":"Novyy Pochinok",
    "gn:population":0,
    "gn:timezone":"Europe/Moscow",
    "iso:country":"RU",
    "name:rus_x_preferred":[
        "\u041d\u043e\u0432\u044b\u0439 \u041f\u043e\u0447\u0438\u043d\u043e\u043a"
    ],
    "name:und_x_variant":[
        "Pochinok",
        "Novyy Pochinok",
        "\u041d\u043e\u0432\u044b\u0439 \u041f\u043e\u0447\u0438\u043d\u043e\u043a"
    ],
    "wof:name":"Novyy Pochinok",
    "wof:placetype":"locality"
},
  "geometry": {"coordinates":[50.14433,55.62395],"type":"Point"}
}