{
  "type": "Feature",
  "properties": {
    "gn:admin1_code":"65",
    "gn:asciiname":"Teneyevo",
    "gn:country_code":"RU",
    "gn:dem":79,
    "gn:feature_class":"P",
    "gn:feature_code":"PPL",
    "gn:name":"Teneyevo",
    "gn:population":0,
    "gn:timezone":"Europe/Samara",
    "iso:country":"RU",
    "name:rus_x_preferred":[
        "\u0422\u0435\u043d\u0435\u0435\u0432\u043e"
    ],
    "name:und_x_variant":[
        "Staroye Teneyevo",
        "Teneyevo"
    ],
    "wof:name":"Teneyevo",
    "wof:placetype":"locality"
},
  "geometry": {"coordinates":[50.63203,54.32359],"type":"Point"}
}