{
  "type": "Feature",
  "properties": {
    "gn:admin1_code":"42",
    "gn:asciiname":"Medjanka",
    "gn:cc2":"RU",
    "gn:country_code":"RU",
    "gn:dem":1,
    "gn:feature_class":"P",
    "gn:feature_code":"PPL",
    "gn:name":"Medjanka",
    "gn:population":0,
    "gn:timezone":"Europe/Moscow",
    "iso:country":"RU",
    "name:fin_x_preferred":[
        "Niemel\u00e4"
    ],
    "name:rus_x_preferred":[
        "\u041d\u0438\u0435\u043c\u0435\u043b\u044f"
    ],
    "name:und_x_variant":[
        "Ninula",
        "Niyemelya"
    ],
    "wof:name":"Medjanka",
    "wof:placetype":"locality"
},
  "geometry": {"coordinates":[28.67844,60.59186],"type":"Point"}
}