{
  "type": "Feature",
  "properties": {
    "gn:admin1_code":"56",
    "gn:asciiname":"Zinov'yevka",
    "gn:country_code":"RU",
    "gn:dem":221,
    "gn:feature_class":"P",
    "gn:feature_code":"PPL",
    "gn:name":"Zinov\u2019yevka",
    "gn:population":0,
    "gn:timezone":"Europe/Moscow",
    "iso:country":"RU",
    "name:rus_x_preferred":[
        "\u0417\u0438\u043d\u043e\u0432\u044c\u0435\u0432\u043a\u0430"
    ],
    "name:und_x_variant":[
        "Zeno\u2019yevka",
        "Zinov\u2019yevka",
        "Zenov\u2019yevka",
        "Zenov\u2019yevka Pervaya",
        "Zenov\u2019yevka Vtoraya"
    ],
    "wof:name":"Zinov'yevka",
    "wof:placetype":"locality"
},
  "geometry": {"coordinates":[36.94589000000001,52.536],"type":"Point"}
}