{
  "type": "Feature",
  "properties": {
    "gn:admin1_code":"88",
    "gn:asciiname":"Gribanikha",
    "gn:country_code":"RU",
    "gn:dem":125,
    "gn:feature_class":"P",
    "gn:feature_code":"PPL",
    "gn:name":"Gribanikha",
    "gn:population":0,
    "gn:timezone":"Europe/Moscow",
    "iso:country":"RU",
    "name:rus_x_preferred":[
        "\u0413\u0440\u0438\u0431\u0430\u043d\u0438\u0445\u0430"
    ],
    "wof:name":"Gribanikha",
    "wof:placetype":"locality"
},
  "geometry": {"coordinates":[38.34808,57.83633],"type":"Point"}
}