{
  "type": "Feature",
  "properties": {
    "gn:admin1_code":"47.0",
    "gn:asciiname":"Aleyevo",
    "gn:country_code":"RU",
    "gn:dem":167,
    "gn:feature_class":"P",
    "gn:feature_code":"PPL",
    "gn:name":"Aleyevo",
    "gn:population":0,
    "gn:timezone":"Europe/Moscow",
    "iso:country":"RU",
    "name:nor_x_preferred":[
        "Alejevo"
    ],
    "name:rus_x_preferred":[
        "\u0410\u043b\u0435\u0435\u0432\u043e"
    ],
    "wof:name":"Aleyevo",
    "wof:placetype":"locality"
},
  "geometry": {"coordinates":[38.02064,54.94428000000001],"type":"Point"}
}