{
  "type": "Feature",
  "properties": {
    "gn:admin1_code":"60",
    "gn:asciiname":"Usmyn'",
    "gn:country_code":"RU",
    "gn:dem":163,
    "gn:feature_class":"P",
    "gn:feature_code":"PPL",
    "gn:name":"Usmyn\u2019",
    "gn:population":0,
    "gn:timezone":"Europe/Moscow",
    "iso:country":"RU",
    "name:eng_x_preferred":[
        "Usmyn'"
    ],
    "name:nor_x_preferred":[
        "Usmyn"
    ],
    "name:rus_x_preferred":[
        "\u0423\u0441\u043c\u044b\u043d\u044c"
    ],
    "name:und_x_variant":[
        "Usmyn\u2019"
    ],
    "wof:name":"Usmyn'",
    "wof:placetype":"locality"
},
  "geometry": {"coordinates":[31.16693,55.85641],"type":"Point"}
}