{
  "type": "Feature",
  "properties": {
    "gn:admin1_code":"86",
    "gn:asciiname":"Medvezh'ya Polyana",
    "gn:country_code":"RU",
    "gn:dem":185,
    "gn:feature_class":"P",
    "gn:feature_code":"PPL",
    "gn:name":"Medvezh\u2019ya Polyana",
    "gn:population":0,
    "gn:timezone":"Europe/Moscow",
    "iso:country":"RU",
    "name:rus_x_preferred":[
        "\u041c\u0435\u0434\u0432\u0435\u0436\u044c\u044f \u041f\u043e\u043b\u044f\u043d\u0430"
    ],
    "name:und_x_variant":[
        "Medvezh\u2019ya Polyana",
        "\u041c\u0435\u0434\u0432\u0435\u0436\u044c\u044f \u041f\u043e\u043b\u044f\u043d\u0430"
    ],
    "wof:name":"Medvezh'ya Polyana",
    "wof:placetype":"locality"
},
  "geometry": {"coordinates":[39.00361,50.93417],"type":"Point"}
}