{
  "type": "Feature",
  "properties": {
    "gn:admin1_code":"16",
    "gn:asciiname":"Khirlukasy",
    "gn:country_code":"RU",
    "gn:dem":122,
    "gn:feature_class":"P",
    "gn:feature_code":"PPL",
    "gn:name":"Khirlukasy",
    "gn:population":0,
    "gn:timezone":"Europe/Moscow",
    "iso:country":"RU",
    "name:rus_x_preferred":[
        "\u0425\u0438\u0440\u043b\u0443\u043a\u0430\u0441\u044b"
    ],
    "name:und_x_variant":[
        "Khyrlukasy",
        "Khirlukasy",
        "\u0425\u0438\u0440\u043b\u0443\u043a\u0430\u0441\u044b"
    ],
    "wof:name":"Khirlukasy",
    "wof:placetype":"locality"
},
  "geometry": {"coordinates":[46.14731,55.75535],"type":"Point"}
}