{
  "type": "Feature",
  "properties": {
    "gn:admin1_code":"3",
    "gn:asciiname":"Ust'-Kumir",
    "gn:country_code":"RU",
    "gn:dem":729,
    "gn:feature_class":"P",
    "gn:feature_code":"PPL",
    "gn:name":"Ust\u2019-Kumir",
    "gn:population":0,
    "gn:timezone":"Asia/Omsk",
    "iso:country":"RU",
    "name:eng_x_preferred":[
        "Ust'-Kumir"
    ],
    "name:nor_x_preferred":[
        "Ust-Kumir"
    ],
    "name:rus_x_preferred":[
        "\u0423\u0441\u0442\u044c-\u041a\u0443\u043c\u0438\u0440"
    ],
    "name:und_x_variant":[
        "Ust\u2019-Kumir"
    ],
    "wof:name":"Ust'-Kumir",
    "wof:placetype":"locality"
},
  "geometry": {"coordinates":[84.28360000000001,51.0316],"type":"Point"}
}