{
  "type": "Feature",
  "properties": {
    "gn:admin1_code":"54",
    "gn:asciiname":"Bakalinskiy",
    "gn:country_code":"RU",
    "gn:dem":109,
    "gn:feature_class":"P",
    "gn:feature_code":"PPL",
    "gn:name":"Bakalinskiy",
    "gn:population":0,
    "gn:timezone":"Asia/Omsk",
    "iso:country":"RU",
    "name:nor_x_preferred":[
        "Bakalinskij"
    ],
    "name:rus_x_preferred":[
        "\u0411\u0430\u043a\u0430\u043b\u0438\u043d\u0441\u043a\u0438\u0439"
    ],
    "wof:name":"Bakalinskiy",
    "wof:placetype":"locality"
},
  "geometry": {"coordinates":[72.78333000000001,55.63333000000001],"type":"Point"}
}