{
  "type": "Feature",
  "properties": {
    "gn:admin1_code":"5",
    "gn:asciiname":"Verkhne-Blagoveshchenskoye",
    "gn:country_code":"RU",
    "gn:dem":132,
    "gn:feature_class":"P",
    "gn:feature_code":"PPL",
    "gn:name":"Verkhne-Blagoveshchenskoye",
    "gn:population":0,
    "gn:timezone":"Asia/Yakutsk",
    "iso:country":"RU",
    "name:rus_x_preferred":[
        "\u0412\u0435\u0440\u0445\u043d\u0435-\u0411\u043b\u0430\u0433\u043e\u0432\u0435\u0449\u0435\u043d\u0441\u043a\u043e\u0435"
    ],
    "name:und_x_variant":[
        "Verkhne-Blagoveshchensk",
        "Verkhne-Blagoveshchenskiy",
        "Verkhne-Blagoveshchenskoye"
    ],
    "wof:name":"Verkhne-Blagoveshchenskoye",
    "wof:placetype":"locality"
},
  "geometry": {"coordinates":[127.40652,50.28405],"type":"Point"}
}