{
  "type": "Feature",
  "properties": {
    "gn:admin1_code":"69",
    "gn:asciiname":"Trukhanovo",
    "gn:country_code":"RU",
    "gn:dem":222,
    "gn:feature_class":"P",
    "gn:feature_code":"PPL",
    "gn:name":"Trukhanovo",
    "gn:population":0,
    "gn:timezone":"Europe/Moscow",
    "iso:country":"RU",
    "name:rus_x_preferred":[
        "\u0422\u0440\u0443\u0445\u0430\u043d\u043e\u0432\u043e"
    ],
    "name:und_x_variant":[
        "Trukhonovo",
        "Trukhanovo"
    ],
    "wof:name":"Trukhanovo",
    "wof:placetype":"locality"
},
  "geometry": {"coordinates":[32.41929,54.59008000000001],"type":"Point"}
}