{
  "type": "Feature",
  "properties": {
    "gn:admin1_code":"83",
    "gn:asciiname":"Turab'yevo",
    "gn:country_code":"RU",
    "gn:dem":183,
    "gn:feature_class":"P",
    "gn:feature_code":"PPL",
    "gn:name":"Turab\u2019yevo",
    "gn:population":0,
    "gn:timezone":"Europe/Moscow",
    "iso:country":"RU",
    "name:rus_x_preferred":[
        "\u0422\u0443\u0440\u0430\u0431\u044c\u0435\u0432\u043e"
    ],
    "name:und_x_variant":[
        "Turab\u2019yevo"
    ],
    "wof:name":"Turab'yevo",
    "wof:placetype":"locality"
},
  "geometry": {"coordinates":[39.86466,56.57694],"type":"Point"}
}