{
  "type": "Feature",
  "properties": {
    "gn:admin1_code":"37",
    "gn:asciiname":"Vladimirovo",
    "gn:country_code":"RU",
    "gn:dem":172,
    "gn:feature_class":"P",
    "gn:feature_code":"PPL",
    "gn:name":"Vladimirovo",
    "gn:population":0,
    "gn:timezone":"Europe/Moscow",
    "iso:country":"RU",
    "name:rus_x_preferred":[
        "\u0412\u043b\u0430\u0434\u0438\u043c\u0438\u0440\u043e\u0432\u043e"
    ],
    "name:und_x_variant":[
        "\u0412\u043b\u0430\u0434\u0438\u043c\u0438\u0440\u043e\u0432\u043e"
    ],
    "wof:name":"Vladimirovo",
    "wof:placetype":"locality"
},
  "geometry": {"coordinates":[45.0835,58.7258],"type":"Point"}
}