{
  "type": "Feature",
  "properties": {
    "gn:admin1_code":"33",
    "gn:asciiname":"Kopotyagi",
    "gn:country_code":"RU",
    "gn:dem":162,
    "gn:feature_class":"P",
    "gn:feature_code":"PPL",
    "gn:name":"Kopotyagi",
    "gn:population":0,
    "gn:timezone":"Europe/Kirov",
    "iso:country":"RU",
    "name:eng_x_preferred":[
        "Kopotyagi"
    ],
    "name:nor_x_preferred":[
        "Kopotjagi"
    ],
    "name:rus_x_preferred":[
        "\u041a\u043e\u043f\u043e\u0442\u044f\u0433\u0438"
    ],
    "name:und_x_variant":[
        "\u041a\u043e\u043f\u043e\u0442\u044f\u0433\u0438",
        "Kopotyagi"
    ],
    "wof:name":"Kopotyagi",
    "wof:placetype":"locality"
},
  "geometry": {"coordinates":[49.36977,58.10651],"type":"Point"}
}