{
  "type": "Feature",
  "properties": {
    "gn:admin1_code":"28.0",
    "gn:asciiname":"Batovo",
    "gn:country_code":"RU",
    "gn:dem":38,
    "gn:feature_class":"P",
    "gn:feature_code":"PPL",
    "gn:name":"Batovo",
    "gn:population":0,
    "gn:timezone":"Europe/Moscow",
    "iso:country":"RU",
    "name:ceb_x_preferred":[
        "Batovo"
    ],
    "name:fra_x_preferred":[
        "Batovo"
    ],
    "name:hrv_x_preferred":[
        "Batovo"
    ],
    "name:nor_x_preferred":[
        "Batovo"
    ],
    "name:rus_x_preferred":[
        "\u0411\u0430\u0442\u043e\u0432\u043e"
    ],
    "name:srp_x_preferred":[
        "\u0411\u0430\u0442\u043e\u0432\u043e"
    ],
    "name:swe_x_preferred":[
        "Batovo"
    ],
    "wof:name":"Batovo",
    "wof:placetype":"locality"
},
  "geometry": {"coordinates":[35.06582,62.54848000000001],"type":"Point"}
}