{
  "type": "Feature",
  "properties": {
    "gn:admin1_code":"85.0",
    "gn:asciiname":"Osiyevskaya",
    "gn:country_code":"RU",
    "gn:dem":166,
    "gn:feature_class":"P",
    "gn:feature_code":"PPL",
    "gn:name":"Osiyevskaya",
    "gn:population":0,
    "gn:timezone":"Europe/Moscow",
    "iso:country":"RU",
    "name:rus_x_preferred":[
        "\u041e\u0441\u0438\u0435\u0432\u0441\u043a\u0430\u044f"
    ],
    "wof:name":"Osiyevskaya",
    "wof:placetype":"locality"
},
  "geometry": {"coordinates":[38.5364,60.2685],"type":"Point"}
}