{
  "type": "Feature",
  "properties": {
    "gn:admin1_code":"43",
    "gn:asciiname":"Lobanovka",
    "gn:country_code":"RU",
    "gn:dem":187,
    "gn:feature_class":"P",
    "gn:feature_code":"PPL",
    "gn:name":"Lobanovka",
    "gn:population":0,
    "gn:timezone":"Europe/Moscow",
    "iso:country":"RU",
    "name:rus_x_preferred":[
        "\u041b\u043e\u0431\u0430\u043d\u043e\u0432\u043a\u0430"
    ],
    "wof:name":"Lobanovka",
    "wof:placetype":"locality"
},
  "geometry": {"coordinates":[38.1991,52.107],"type":"Point"}
}