{
  "type": "Feature",
  "properties": {
    "gn:admin1_code":"12",
    "gn:asciiname":"Dolinskiy",
    "gn:country_code":"RU",
    "gn:dem":220,
    "gn:feature_class":"P",
    "gn:feature_code":"PPL",
    "gn:name":"Dolinskiy",
    "gn:population":0,
    "gn:timezone":"Europe/Moscow",
    "iso:country":"RU",
    "name:rus_x_preferred":[
        "\u0414\u043e\u043b\u0438\u043d\u0441\u043a\u0438\u0439"
    ],
    "wof:name":"Dolinskiy",
    "wof:placetype":"locality"
},
  "geometry": {"coordinates":[45.38459,43.40509],"type":"Point"}
}