{
  "type": "Feature",
  "properties": {
    "gn:admin1_code":"25.0",
    "gn:asciiname":"Alekino",
    "gn:country_code":"RU",
    "gn:dem":179,
    "gn:feature_class":"P",
    "gn:feature_code":"PPL",
    "gn:name":"Al\u00ebkino",
    "gn:population":0,
    "gn:timezone":"Europe/Moscow",
    "iso:country":"RU",
    "name:nor_x_preferred":[
        "Aljokino"
    ],
    "name:rus_x_preferred":[
        "\u0410\u043b\u0451\u043a\u0438\u043d\u043e"
    ],
    "name:und_x_variant":[
        "Aleksino",
        "Al\u00ebkino"
    ],
    "wof:name":"Alekino",
    "wof:placetype":"locality"
},
  "geometry": {"coordinates":[37.17309,54.66163],"type":"Point"}
}