{
  "type": "Feature",
  "properties": {
    "gn:admin1_code":"70",
    "gn:asciiname":"Krasnyy Oktyabr'",
    "gn:cc2":"RU",
    "gn:country_code":"RU",
    "gn:dem":274,
    "gn:feature_class":"P",
    "gn:feature_code":"PPL",
    "gn:name":"Krasnyy Oktyabr'",
    "gn:population":0,
    "gn:timezone":"Europe/Moscow",
    "iso:country":"RU",
    "name:und_x_variant":[
        "Ugol'nyye"
    ],
    "wof:name":"Krasnyy Oktyabr'",
    "wof:placetype":"locality"
},
  "geometry": {"coordinates":[42.81667,45.01667],"type":"Point"}
}