{
  "type": "Feature",
  "properties": {
    "gn:admin1_code":"52",
    "gn:asciiname":"Zador'ye",
    "gn:country_code":"RU",
    "gn:dem":118,
    "gn:feature_class":"P",
    "gn:feature_code":"PPL",
    "gn:name":"Zador\u2019ye",
    "gn:population":0,
    "gn:timezone":"Europe/Moscow",
    "iso:country":"RU",
    "name:und_x_variant":[
        "Sadore",
        "Zador\u2019ye"
    ],
    "wof:name":"Zador'ye",
    "wof:placetype":"locality"
},
  "geometry": {"coordinates":[33.07889,58.77222],"type":"Point"}
}