{
  "type": "Feature",
  "properties": {
    "gn:admin1_code":"34",
    "gn:asciiname":"Nizhniy Syuzya-Ib",
    "gn:country_code":"RU",
    "gn:dem":97,
    "gn:feature_class":"P",
    "gn:feature_code":"PPL",
    "gn:name":"Nizhniy Syuzya-Ib",
    "gn:population":0,
    "gn:timezone":"Europe/Moscow",
    "iso:country":"RU",
    "name:rus_x_preferred":[
        "\u041d\u0438\u0436\u043d\u0438\u0439 \u0421\u044e\u0437\u044f-\u0418\u0431"
    ],
    "wof:name":"Nizhniy Syuzya-Ib",
    "wof:placetype":"locality"
},
  "geometry": {"coordinates":[52.47606,62.22441],"type":"Point"}
}