{
  "type": "Feature",
  "properties": {
    "gn:gn_country":"RU",
    "gn:gn_fcode":"PPL",
    "gn:gn_pop":296,
    "gn:population":296,
    "iso:country":"RU",
    "name:ara_x_preferred":[
        "\u0623\u0641\u0633\u064a\u0648\u0646\u064a\u0646\u0648"
    ],
    "name:cat_x_preferred":[
        "Al\u00b7lakh-Iun"
    ],
    "name:deu_x_preferred":[
        "Allach-Jun"
    ],
    "name:eng_x_preferred":[
        "Allakh-Yun'"
    ],
    "name:hye_x_preferred":[
        "\u0531\u056c\u0561\u056d-\u0545\u0578\u0582\u0576"
    ],
    "name:lit_x_preferred":[
        "Alach Junis"
    ],
    "name:nld_x_preferred":[
        "Allach-Jun"
    ],
    "name:rus_x_preferred":[
        "\u0410\u043b\u043b\u0430\u0445-\u042e\u043d\u044c"
    ],
    "name:sah_x_preferred":[
        "\u0410\u0430\u043b\u043b\u0430\u0430\u0445 \u04ae\u04af\u043d"
    ],
    "name:unk_x_variant":[
        "Allakh"
    ],
    "name:zho_x_preferred":[
        "\u963f\u62c9\u8d6b\u96f2"
    ],
    "qs_pg:aaroncc":"RU",
    "qs_pg:gn_country":"RU",
    "qs_pg:gn_fcode":"PPL",
    "qs_pg:gn_pop":296,
    "qs_pg:name":"Allakh-Yun\u2019",
    "qs_pg:photos_9r":0,
    "qs_pg:photos_sr":0,
    "qs_pg:pop_sr":2,
    "qs_pg:qs_pg_placetype":"locality",
    "wof:name":"Allakh-Yun\u2019",
    "wof:placetype":"locality",
    "wof:population":296
},
  "geometry": {"coordinates":[138.04893000000001,61.13356],"type":"Point"}
}