{
  "type": "Feature",
  "properties": {
    "gn:admin1_code":"92",
    "gn:asciiname":"Glinka",
    "gn:country_code":"RU",
    "gn:dem":8,
    "gn:feature_class":"P",
    "gn:feature_code":"PPL",
    "gn:name":"Glinka",
    "gn:population":0,
    "gn:timezone":"Asia/Kamchatka",
    "iso:country":"RU",
    "name:bel_x_preferred":[
        "\u0413\u043b\u0456\u043d\u043a\u0430"
    ],
    "name:bul_x_preferred":[
        "\u0413\u043b\u0438\u043d\u043a\u0430"
    ],
    "name:ceb_x_preferred":[
        "\u0413\u043b\u0438\u043d\u043a\u0430"
    ],
    "name:deu_x_preferred":[
        "Glinka"
    ],
    "name:fra_x_preferred":[
        "Glinka"
    ],
    "name:hun_x_preferred":[
        "Glinka"
    ],
    "name:hye_x_preferred":[
        "\u0533\u056c\u056b\u0576\u056f\u0561"
    ],
    "name:ita_x_preferred":[
        "Glinka"
    ],
    "name:nld_x_preferred":[
        "Glinka"
    ],
    "name:pol_x_preferred":[
        "Glinka"
    ],
    "name:rus_x_preferred":[
        "\u0413\u043b\u0438\u043d\u043a\u0430"
    ],
    "name:swe_x_preferred":[
        "Glinka"
    ],
    "name:ukr_x_preferred":[
        "\u0490\u043b\u0456\u043d\u043a\u0430"
    ],
    "wof:name":"Glinka",
    "wof:placetype":"locality"
},
  "geometry": {"coordinates":[167.96222,54.58393],"type":"Point"}
}