{
  "type": "Feature",
  "properties": {
    "gn:admin1_code":"92",
    "gn:asciiname":"Glinka",
    "gn:country_code":"RU",
    "gn:dem":8,
    "gn:feature_class":"P",
    "gn:feature_code":"PPL",
    "gn:name":"Glinka",
    "gn:population":0,
    "gn:timezone":"Asia/Kamchatka",
    "iso:country":"RU",
    "name:rus_x_preferred":[
        "\u0413\u043b\u0438\u043d\u043a\u0430"
    ],
    "name:und_x_variant":[
        "\u0413\u043b\u0438\u043d\u043a\u0430"
    ],
    "wof:name":"Glinka",
    "wof:placetype":"locality"
},
  "geometry": {"coordinates":[167.96222,54.58393],"type":"Point"}
}