{
  "type": "Feature",
  "properties": {
    "gn:admin1_code":"76",
    "gn:asciiname":"Podgorskoye",
    "gn:country_code":"RU",
    "gn:dem":180,
    "gn:feature_class":"P",
    "gn:feature_code":"PPL",
    "gn:name":"Podgorskoye",
    "gn:population":0,
    "gn:timezone":"Europe/Moscow",
    "iso:country":"RU",
    "name:rus_x_preferred":[
        "\u041f\u043e\u0434\u0433\u043e\u0440\u0441\u043a\u043e\u0435"
    ],
    "name:und_x_variant":[
        "\u041f\u043e\u0434\u0433\u043e\u0440\u0441\u043a\u043e\u0435"
    ],
    "wof:name":"Podgorskoye",
    "wof:placetype":"locality"
},
  "geometry": {"coordinates":[38.4257,53.5542],"type":"Point"}
}