{
  "type": "Feature",
  "properties": {
    "gn:admin1_code":"29",
    "gn:asciiname":"Kutonovo",
    "gn:country_code":"RU",
    "gn:dem":264,
    "gn:feature_class":"P",
    "gn:feature_code":"PPL",
    "gn:name":"Kutonovo",
    "gn:population":0,
    "gn:timezone":"Asia/Novokuznetsk",
    "iso:country":"RU",
    "name:rus_x_preferred":[
        "\u041a\u0443\u0442\u043e\u043d\u043e\u0432\u043e"
    ],
    "wof:name":"Kutonovo",
    "wof:placetype":"locality"
},
  "geometry": {"coordinates":[86.68819999999999,54.0933],"type":"Point"}
}