{
  "type": "Feature",
  "properties": {
    "gn:admin1_code":"6",
    "gn:asciiname":"Shestnikovskaya",
    "gn:country_code":"RU",
    "gn:dem":96,
    "gn:feature_class":"P",
    "gn:feature_code":"PPL",
    "gn:name":"Shestnikovskaya",
    "gn:population":0,
    "gn:timezone":"Europe/Moscow",
    "iso:country":"RU",
    "name:eng_x_preferred":[
        "Shestnikovskaya"
    ],
    "name:nor_x_preferred":[
        "Sjestnikovskaja"
    ],
    "name:rus_x_preferred":[
        "\u0428\u0435\u0441\u0442\u043d\u0438\u043a\u043e\u0432\u0441\u043a\u0430\u044f"
    ],
    "wof:name":"Shestnikovskaya",
    "wof:placetype":"locality"
},
  "geometry": {"coordinates":[42.47099,60.82026],"type":"Point"}
}