{
  "type": "Feature",
  "properties": {
    "gn:admin1_code":"84",
    "gn:asciiname":"Ranovskiy",
    "gn:country_code":"RU",
    "gn:dem":44,
    "gn:feature_class":"P",
    "gn:feature_code":"PPL",
    "gn:name":"Ranovskiy",
    "gn:population":0,
    "gn:timezone":"Europe/Volgograd",
    "iso:country":"RU",
    "name:rus_x_preferred":[
        "\u0420\u0430\u043d\u043e\u0432\u0441\u043a\u0438\u0439"
    ],
    "wof:name":"Ranovskiy",
    "wof:placetype":"locality"
},
  "geometry": {"coordinates":[43.6357,49.3817],"type":"Point"}
}