{
  "type": "Feature",
  "properties": {
    "gn:admin1_code":"51.0",
    "gn:asciiname":"Bochikha",
    "gn:country_code":"RU",
    "gn:dem":180,
    "gn:feature_class":"P",
    "gn:feature_code":"PPL",
    "gn:name":"Bochikha",
    "gn:population":0,
    "gn:timezone":"Europe/Moscow",
    "iso:country":"RU",
    "name:eng_x_preferred":[
        "Bochikha"
    ],
    "name:nor_x_preferred":[
        "Botsjikha"
    ],
    "name:rus_x_preferred":[
        "\u0411\u043e\u0447\u0438\u0445\u0430"
    ],
    "name:und_x_variant":[
        "\u0411\u043e\u0447\u0438\u0445\u0430",
        "Bochikha"
    ],
    "wof:name":"Bochikha",
    "wof:placetype":"locality"
},
  "geometry": {"coordinates":[43.41838,55.73024],"type":"Point"}
}