{
  "type": "Feature",
  "properties": {
    "gn:admin1_code":"6.0",
    "gn:asciiname":"Chasovenskaya",
    "gn:country_code":"RU",
    "gn:dem":3,
    "gn:feature_class":"P",
    "gn:feature_code":"PPL",
    "gn:name":"Chasovenskaya",
    "gn:population":0,
    "gn:timezone":"Europe/Moscow",
    "iso:country":"RU",
    "name:rus_x_preferred":[
        "\u0427\u0430\u0441\u043e\u0432\u0435\u043d\u0441\u043a\u0430\u044f"
    ],
    "name:und_x_variant":[
        "Chasovenskoye",
        "Chasovnya"
    ],
    "wof:name":"Chasovenskaya",
    "wof:placetype":"locality"
},
  "geometry": {"coordinates":[41.5191,63.8109],"type":"Point"}
}