{
  "type": "Feature",
  "properties": {
    "gn:admin1_code":"37",
    "gn:asciiname":"Olekhovo",
    "gn:country_code":"RU",
    "gn:dem":169,
    "gn:feature_class":"P",
    "gn:feature_code":"PPL",
    "gn:name":"Ol\u00ebkhovo",
    "gn:population":0,
    "gn:timezone":"Europe/Moscow",
    "iso:country":"RU",
    "name:rus_x_preferred":[
        "\u041e\u043b\u0451\u0445\u043e\u0432\u043e"
    ],
    "name:und_x_variant":[
        "Ol\u00ebkhovo"
    ],
    "wof:name":"Olekhovo",
    "wof:placetype":"locality"
},
  "geometry": {"coordinates":[43.1075,58.5334],"type":"Point"}
}