{
  "type": "Feature",
  "properties": {
    "gn:admin1_code":"62",
    "gn:asciiname":"Roditel'skoye",
    "gn:country_code":"RU",
    "gn:dem":94,
    "gn:feature_class":"P",
    "gn:feature_code":"PPL",
    "gn:name":"Roditel\u2019skoye",
    "gn:population":0,
    "gn:timezone":"Europe/Moscow",
    "iso:country":"RU",
    "name:rus_x_preferred":[
        "\u0420\u043e\u0434\u0438\u0442\u0435\u043b\u044c\u0441\u043a\u043e\u0435"
    ],
    "name:und_x_variant":[
        "Roditel\u2019skoye"
    ],
    "wof:name":"Roditel'skoye",
    "wof:placetype":"locality"
},
  "geometry": {"coordinates":[42.4927,54.5083],"type":"Point"}
}