{
  "type": "Feature",
  "properties": {
    "gn:admin1_code":"41.0",
    "gn:asciiname":"Cheremoshnoye",
    "gn:country_code":"RU",
    "gn:dem":193,
    "gn:feature_class":"P",
    "gn:feature_code":"PPL",
    "gn:name":"Cheremoshnoye",
    "gn:population":0,
    "gn:timezone":"Europe/Moscow",
    "iso:country":"RU",
    "name:eng_x_preferred":[
        "Cheremoshnoye"
    ],
    "name:nor_x_preferred":[
        "Tsjermosjnoje"
    ],
    "name:rus_x_preferred":[
        "\u0427\u0435\u0440\u043c\u043e\u0448\u043d\u043e\u0435"
    ],
    "name:rus_x_variant":[
        "\u0427\u0435\u0440\u0435\u043c\u043e\u0448\u043d\u043e\u0435"
    ],
    "name:und_x_variant":[
        "Novoye Cheremoshnoye",
        "Chermoshnoye",
        "Cheremoshnoye",
        "\u0427\u0435\u0440\u0435\u043c\u043e\u0448\u043d\u043e\u0435"
    ],
    "wof:name":"Cheremoshnoye",
    "wof:placetype":"locality"
},
  "geometry": {"coordinates":[36.19276,51.4515],"type":"Point"}
}