{
  "type": "Feature",
  "properties": {
    "gn:admin1_code":"8",
    "gn:asciiname":"Suvanyak",
    "gn:country_code":"RU",
    "gn:dem":657,
    "gn:feature_class":"P",
    "gn:feature_code":"PPL",
    "gn:name":"Suvanyak",
    "gn:population":0,
    "gn:timezone":"Asia/Yekaterinburg",
    "iso:country":"RU",
    "name:rus_x_preferred":[
        "\u0421\u0443\u0432\u0430\u043d\u044f\u043a"
    ],
    "wof:name":"Suvanyak",
    "wof:placetype":"locality"
},
  "geometry": {"coordinates":[57.9645,53.0862],"type":"Point"}
}