{
  "type": "Feature",
  "properties": {
    "gn:admin1_code":"81",
    "gn:asciiname":"Stogovka",
    "gn:country_code":"RU",
    "gn:dem":118,
    "gn:feature_class":"P",
    "gn:feature_code":"PPL",
    "gn:name":"Stogovka",
    "gn:population":0,
    "gn:timezone":"Europe/Ulyanovsk",
    "iso:country":"RU",
    "name:eng_x_preferred":[
        "Stogovka"
    ],
    "name:nor_x_preferred":[
        "Stogovka"
    ],
    "name:rus_x_preferred":[
        "\u0421\u0442\u043e\u0433\u043e\u0432\u043a\u0430"
    ],
    "name:und_x_variant":[
        "Lukino",
        "\u0421\u0442\u043e\u0433\u043e\u0432\u043a\u0430",
        "Stogovka"
    ],
    "wof:name":"Stogovka",
    "wof:placetype":"locality"
},
  "geometry": {"coordinates":[48.0174,53.9729],"type":"Point"}
}