{
  "type": "Feature",
  "properties": {
    "gn:admin1_code":"85",
    "gn:asciiname":"Kosarovo",
    "gn:country_code":"RU",
    "gn:dem":141,
    "gn:feature_class":"P",
    "gn:feature_code":"PPL",
    "gn:name":"Kosarovo",
    "gn:population":0,
    "gn:timezone":"Europe/Moscow",
    "iso:country":"RU",
    "name:rus_x_preferred":[
        "\u041a\u043e\u0441\u0430\u0440\u043e\u0432\u043e"
    ],
    "name:und_x_variant":[
        "\u041a\u043e\u0441\u0430\u0440\u043e\u0432\u043e"
    ],
    "wof:name":"Kosarovo",
    "wof:placetype":"locality"
},
  "geometry": {"coordinates":[40.45,58.98611],"type":"Point"}
}