{
  "type": "Feature",
  "properties": {
    "gn:admin1_code":"85",
    "gn:asciiname":"Lant'yevo",
    "gn:country_code":"RU",
    "gn:dem":166,
    "gn:feature_class":"P",
    "gn:feature_code":"PPL",
    "gn:name":"Lant\u2019yevo",
    "gn:population":0,
    "gn:timezone":"Europe/Moscow",
    "iso:country":"RU",
    "name:rus_x_preferred":[
        "\u041b\u0430\u043d\u0442\u044c\u0435\u0432\u043e"
    ],
    "name:und_x_variant":[
        "Lant\u2019yevo"
    ],
    "wof:name":"Lant'yevo",
    "wof:placetype":"locality"
},
  "geometry": {"coordinates":[39.57561,59.13438000000001],"type":"Point"}
}