{
  "type": "Feature",
  "properties": {
    "gn:admin1_code":"21.0",
    "gn:asciiname":"Alekseyevskoye Staroye",
    "gn:country_code":"RU",
    "gn:dem":153,
    "gn:feature_class":"P",
    "gn:feature_code":"PPL",
    "gn:name":"Alekseyevskoye Staroye",
    "gn:population":0,
    "gn:timezone":"Europe/Moscow",
    "iso:country":"RU",
    "name:nor_x_preferred":[
        "Aleksejevskoje Staroje"
    ],
    "name:rus_x_preferred":[
        "\u0410\u043b\u0435\u043a\u0441\u0435\u0435\u0432\u0441\u043a\u043e\u0435 \u0421\u0442\u0430\u0440\u043e\u0435"
    ],
    "name:und_x_variant":[
        "Alekseyevskoye",
        "Alekseyevskoye Staroye"
    ],
    "wof:name":"Alekseyevskoye Staroye",
    "wof:placetype":"locality"
},
  "geometry": {"coordinates":[41.10478,57.3612],"type":"Point"}
}