{
  "type": "Feature",
  "properties": {
    "gn:admin1_code":"29",
    "gn:asciiname":"Trekhrech'ye",
    "gn:country_code":"RU",
    "gn:dem":421,
    "gn:feature_class":"P",
    "gn:feature_code":"PPL",
    "gn:name":"Tr\u00ebkhrech\u2019ye",
    "gn:population":0,
    "gn:timezone":"Asia/Novokuznetsk",
    "iso:country":"RU",
    "name:eng_x_preferred":[
        "Tr\u00ebkhrech'ye"
    ],
    "name:nor_x_preferred":[
        "Trekhretsje"
    ],
    "name:rus_x_preferred":[
        "\u0422\u0440\u0435\u0445\u0440\u0435\u0447\u044c\u0435"
    ],
    "name:und_x_variant":[
        "Tr\u00ebkhrech\u2019ye"
    ],
    "wof:name":"Trekhrech'ye",
    "wof:placetype":"locality"
},
  "geometry": {"coordinates":[88.59676999999998,53.2074],"type":"Point"}
}