{
  "type": "Feature",
  "properties": {
    "gn:admin1_code":"61",
    "gn:asciiname":"Kasenovka",
    "gn:country_code":"RU",
    "gn:dem":16,
    "gn:feature_class":"P",
    "gn:feature_code":"PPL",
    "gn:name":"Kasenovka",
    "gn:population":0,
    "gn:timezone":"Europe/Moscow",
    "iso:country":"RU",
    "name:rus_x_preferred":[
        "\u041a\u0430\u0441\u0435\u043d\u043e\u0432\u043a\u0430"
    ],
    "wof:name":"Kasenovka",
    "wof:placetype":"locality"
},
  "geometry": {"coordinates":[41.40611,46.87583],"type":"Point"}
}