{
  "type": "Feature",
  "properties": {
    "gn:admin1_code":"52.0",
    "gn:asciiname":"Baluyevo",
    "gn:country_code":"RU",
    "gn:dem":217,
    "gn:feature_class":"P",
    "gn:feature_code":"PPL",
    "gn:name":"Baluyevo",
    "gn:population":0,
    "gn:timezone":"Europe/Moscow",
    "iso:country":"RU",
    "name:nor_x_preferred":[
        "Balujevo"
    ],
    "name:rus_x_preferred":[
        "\u0411\u0430\u043b\u0443\u0435\u0432\u043e"
    ],
    "wof:name":"Baluyevo",
    "wof:placetype":"locality"
},
  "geometry": {"coordinates":[33.05536,57.69156],"type":"Point"}
}