{
  "type": "Feature",
  "properties": {
    "gn:admin1_code":"65",
    "gn:asciiname":"Ryazanka",
    "gn:country_code":"RU",
    "gn:dem":91,
    "gn:feature_class":"P",
    "gn:feature_code":"PPL",
    "gn:name":"Ryazanka",
    "gn:population":0,
    "gn:timezone":"Europe/Samara",
    "iso:country":"RU",
    "name:rus_x_preferred":[
        "\u0420\u044f\u0437\u0430\u043d\u043a\u0430"
    ],
    "name:und_x_variant":[
        "\u0420\u044f\u0437\u0430\u043d\u043a\u0430"
    ],
    "wof:name":"Ryazanka",
    "wof:placetype":"locality"
},
  "geometry": {"coordinates":[50.76667,53.58333],"type":"Point"}
}