{
  "type": "Feature",
  "properties": {
    "gn:admin1_code":"30",
    "gn:asciiname":"Lugovaya",
    "gn:country_code":"RU",
    "gn:dem":3,
    "gn:feature_class":"P",
    "gn:feature_code":"PPL",
    "gn:name":"Lugovaya",
    "gn:population":0,
    "gn:timezone":"Asia/Vladivostok",
    "iso:country":"RU",
    "name:eng_x_preferred":[
        "Lugovaya"
    ],
    "name:nor_x_preferred":[
        "Lugovaja"
    ],
    "name:rus_x_preferred":[
        "\u041b\u0443\u0433\u043e\u0432\u0430\u044f"
    ],
    "name:und_x_variant":[
        "Lugovoye",
        "\u041b\u0443\u0433\u043e\u0432\u0430\u044f",
        "Lugovaya"
    ],
    "wof:name":"Lugovaya",
    "wof:placetype":"locality"
},
  "geometry": {"coordinates":[139.19606000000002,47.68793],"type":"Point"}
}