{
  "type": "Feature",
  "properties": {
    "gn:admin1_code":"86",
    "gn:asciiname":"Il'inskiy",
    "gn:country_code":"RU",
    "gn:dem":86,
    "gn:feature_class":"P",
    "gn:feature_code":"PPL",
    "gn:name":"Il\u2019inskiy",
    "gn:population":0,
    "gn:timezone":"Europe/Moscow",
    "iso:country":"RU",
    "name:rus_x_preferred":[
        "\u0418\u043b\u044c\u0438\u043d\u0441\u043a\u0438\u0439"
    ],
    "name:und_x_variant":[
        "Il\u2019inskiy",
        "\u0418\u043b\u044c\u0438\u043d\u0441\u043a\u0438\u0439"
    ],
    "wof:name":"Il'inskiy",
    "wof:placetype":"locality"
},
  "geometry": {"coordinates":[41.78,51.33861],"type":"Point"}
}