{
  "type": "Feature",
  "properties": {
    "gn:admin1_code":"47",
    "gn:asciiname":"Berezenki",
    "gn:country_code":"RU",
    "gn:dem":164,
    "gn:feature_class":"P",
    "gn:feature_code":"PPL",
    "gn:name":"\u0411\u0435\u0440\u0435\u0437\u0435\u043d\u043a\u0438",
    "gn:population":0,
    "gn:timezone":"Europe/Moscow",
    "iso:country":"RU",
    "name:rus_x_preferred":[
        "\u0411\u0435\u0440\u0435\u0437\u0435\u043d\u043a\u0438"
    ],
    "name:und_x_variant":[
        "Berez\u00ebnki",
        "\u0411\u0435\u0440\u0435\u0437\u0435\u043d\u043a\u0438"
    ],
    "wof:name":"Berezenki",
    "wof:placetype":"locality"
},
  "geometry": {"coordinates":[37.22839000000001,55.07155],"type":"Point"}
}