{
  "type": "Feature",
  "properties": {
    "gn:admin1_code":"84",
    "gn:asciiname":"Karasev",
    "gn:country_code":"RU",
    "gn:dem":102,
    "gn:feature_class":"P",
    "gn:feature_code":"PPL",
    "gn:name":"Karasev",
    "gn:population":0,
    "gn:timezone":"Europe/Volgograd",
    "iso:country":"RU",
    "name:rus_x_preferred":[
        "\u041a\u0430\u0440\u0430\u0441\u0435\u0432"
    ],
    "wof:name":"Karasev",
    "wof:placetype":"locality"
},
  "geometry": {"coordinates":[42.27342,49.24986],"type":"Point"}
}