{
  "type": "Feature",
  "properties": {
    "gn:admin1_code":"89",
    "gn:asciiname":"Bashurovo",
    "gn:country_code":"RU",
    "gn:dem":98,
    "gn:feature_class":"P",
    "gn:feature_code":"PPL",
    "gn:name":"Bashurovo",
    "gn:population":0,
    "gn:timezone":"Asia/Vladivostok",
    "iso:country":"RU",
    "name:eng_x_preferred":[
        "Bashurovo"
    ],
    "name:nor_x_preferred":[
        "Basjurovo"
    ],
    "name:rus_x_preferred":[
        "\u0411\u0430\u0448\u0443\u0440\u043e\u0432\u043e"
    ],
    "name:und_x_variant":[
        "Bashurova",
        "Baturovo",
        "Boshurovo"
    ],
    "wof:name":"Bashurovo",
    "wof:placetype":"locality"
},
  "geometry": {"coordinates":[130.59683000000001,48.69887],"type":"Point"}
}