{
  "type": "Feature",
  "properties": {
    "gn:admin1_code":"20",
    "gn:asciiname":"Pushchina",
    "gn:cc2":"RU",
    "gn:country_code":"RU",
    "gn:dem":234,
    "gn:feature_class":"P",
    "gn:feature_code":"PPL",
    "gn:name":"Pushchina",
    "gn:population":0,
    "gn:timezone":"Asia/Irkutsk",
    "iso:country":"RU",
    "name:eng_x_preferred":[
        "Pushchina"
    ],
    "name:nor_x_preferred":[
        "Pusjtsjina"
    ],
    "name:rus_x_preferred":[
        "\u041f\u0443\u0449\u0438\u043d\u0430"
    ],
    "name:und_x_variant":[
        "Pushchino"
    ],
    "wof:name":"Pushchina",
    "wof:placetype":"locality"
},
  "geometry": {"coordinates":[109.30944,58.19],"type":"Point"}
}