{
  "type": "Feature",
  "properties": {
    "gn:country":"RU",
    "gn:fcode":"PPL",
    "gn:pop":500,
    "iso:country":"RU",
    "name:rus_x_preferred":[
        "\u041b\u0435\u0442\u043e\u0432\u043e"
    ],
    "name:unk_x_variant":[
        "\u041b\u0435\u0442\u043e\u0432\u043e"
    ],
    "qs:name":"Letovo",
    "qs:name_adm0":"Russia",
    "qs:name_adm1":"Moscow Oblast",
    "qs:photos_9r":0,
    "qs:photos_sr":0,
    "qs:placetype":"Town",
    "qs:pop_sr":"2",
    "wof:name":"Letovo",
    "wof:placetype":"locality",
    "wof:population":500
},
  "geometry": {"coordinates":[37.39867,55.56267],"type":"Point"}
}