{
  "type": "Feature",
  "properties": {
    "gn:admin1_code":"21.0",
    "gn:asciiname":"Klimovo",
    "gn:country_code":"RU",
    "gn:dem":135,
    "gn:feature_class":"P",
    "gn:feature_code":"PPL",
    "gn:name":"Klimovo",
    "gn:population":0,
    "gn:timezone":"Europe/Moscow",
    "iso:country":"RU",
    "name:rus_x_preferred":[
        "\u041a\u043b\u0438\u043c\u043e\u0432\u043e"
    ],
    "wof:name":"Klimovo",
    "wof:placetype":"locality"
},
  "geometry": {"coordinates":[41.09579,57.17149000000001],"type":"Point"}
}