{
  "type": "Feature",
  "properties": {
    "gn:admin1_code":"93",
    "gn:asciiname":"Kontorka",
    "gn:country_code":"RU",
    "gn:dem":1022,
    "gn:feature_class":"P",
    "gn:feature_code":"PPL",
    "gn:name":"Kontorka",
    "gn:population":0,
    "gn:timezone":"Asia/Chita",
    "iso:country":"RU",
    "name:rus_x_preferred":[
        "\u041a\u043e\u043d\u0442\u043e\u0440\u043a\u0430"
    ],
    "name:und_x_variant":[
        "\u041a\u043e\u043d\u0442\u043e\u0440\u043a\u0430"
    ],
    "wof:name":"Kontorka",
    "wof:placetype":"locality"
},
  "geometry": {"coordinates":[110.28333000000001,50.83333],"type":"Point"}
}