{
  "type": "Feature",
  "properties": {
    "gn:admin1_code":"21",
    "gn:asciiname":"Gorbovo",
    "gn:country_code":"RU",
    "gn:dem":139,
    "gn:feature_class":"P",
    "gn:feature_code":"PPL",
    "gn:name":"Gorbovo",
    "gn:population":0,
    "gn:timezone":"Europe/Moscow",
    "iso:country":"RU",
    "name:rus_x_preferred":[
        "\u0413\u043e\u0440\u0431\u043e\u0432\u043e"
    ],
    "wof:name":"Gorbovo",
    "wof:placetype":"locality"
},
  "geometry": {"coordinates":[39.68625,57.00075],"type":"Point"}
}