{
  "type": "Feature",
  "properties": {
    "gn:admin1_code":"85",
    "gn:asciiname":"Lavrushino",
    "gn:country_code":"RU",
    "gn:dem":136,
    "gn:feature_class":"P",
    "gn:feature_code":"PPL",
    "gn:name":"Lavrushino",
    "gn:population":0,
    "gn:timezone":"Europe/Moscow",
    "iso:country":"RU",
    "name:rus_x_preferred":[
        "\u041b\u0430\u0432\u0440\u0443\u0448\u0438\u043d\u043e"
    ],
    "name:und_x_variant":[
        "Lavrushin",
        "Lavrushino"
    ],
    "wof:name":"Lavrushino",
    "wof:placetype":"locality"
},
  "geometry": {"coordinates":[36.9155,60.1904],"type":"Point"}
}