{
  "type": "Feature",
  "properties": {
    "gn:admin1_code":"73",
    "gn:asciiname":"Utyamishevo",
    "gn:country_code":"RU",
    "gn:dem":62,
    "gn:feature_class":"P",
    "gn:feature_code":"PPL",
    "gn:name":"Utyamishevo",
    "gn:population":0,
    "gn:timezone":"Europe/Moscow",
    "iso:country":"RU",
    "name:und_x_variant":[
        "Utyamyshevo",
        "Utyamishevo"
    ],
    "wof:name":"Utyamishevo",
    "wof:placetype":"locality"
},
  "geometry": {"coordinates":[48.53155,55.32044000000001],"type":"Point"}
}