{
  "type": "Feature",
  "properties": {
    "gn:admin1_code":"42",
    "gn:asciiname":"Kemka",
    "gn:country_code":"RU",
    "gn:dem":59,
    "gn:feature_class":"P",
    "gn:feature_code":"PPL",
    "gn:name":"Kemka",
    "gn:population":0,
    "gn:timezone":"Europe/Moscow",
    "iso:country":"RU",
    "name:rus_x_preferred":[
        "\u041a\u0435\u043c\u043a\u0430"
    ],
    "wof:name":"Kemka",
    "wof:placetype":"locality"
},
  "geometry": {"coordinates":[29.81678,58.93794000000001],"type":"Point"}
}