{
  "type": "Feature",
  "properties": {
    "gn:admin1_code":"69",
    "gn:asciiname":"Morozovka",
    "gn:country_code":"RU",
    "gn:dem":234,
    "gn:feature_class":"P",
    "gn:feature_code":"PPL",
    "gn:name":"Morozovka",
    "gn:population":0,
    "gn:timezone":"Europe/Moscow",
    "iso:country":"RU",
    "name:che_x_preferred":[
        "\u041c\u043e\u0440\u043e\u0437\u043e\u0432\u043a\u0430"
    ],
    "name:rus_x_preferred":[
        "\u041c\u043e\u0440\u043e\u0437\u043e\u0432\u043a\u0430"
    ],
    "wof:name":"Morozovka",
    "wof:placetype":"locality"
},
  "geometry": {"coordinates":[33.15345,54.11768000000001],"type":"Point"}
}