{
  "type": "Feature",
  "properties": {
    "gn:admin1_code":"16",
    "gn:asciiname":"Chapayevka",
    "gn:country_code":"RU",
    "gn:dem":165,
    "gn:feature_class":"P",
    "gn:feature_code":"PPL",
    "gn:name":"Chapayevka",
    "gn:population":0,
    "gn:timezone":"Europe/Moscow",
    "iso:country":"RU",
    "name:ceb_x_preferred":[
        "Chapayevka"
    ],
    "name:deu_x_preferred":[
        "Tschapajewka"
    ],
    "name:hye_x_preferred":[
        "\u0549\u0561\u057a\u0561\u0587\u056f\u0561"
    ],
    "name:rus_x_preferred":[
        "\u0427\u0430\u043f\u0430\u0435\u0432\u043a\u0430"
    ],
    "name:ukr_x_preferred":[
        "\u0427\u0430\u043f\u0430\u0454\u0432\u043a\u0430"
    ],
    "wof:name":"Chapayevka",
    "wof:placetype":"locality"
},
  "geometry": {"coordinates":[47.0211,54.9146],"type":"Point"}
}