{
  "type": "Feature",
  "properties": {
    "gn:admin1_code":"91",
    "gn:asciiname":"Rechka",
    "gn:country_code":"RU",
    "gn:dem":264,
    "gn:feature_class":"P",
    "gn:feature_code":"PPL",
    "gn:name":"Rechka",
    "gn:population":0,
    "gn:timezone":"Asia/Krasnoyarsk",
    "iso:country":"RU",
    "name:eng_x_preferred":[
        "Rechka"
    ],
    "name:nor_x_preferred":[
        "Retsjka"
    ],
    "name:rus_x_preferred":[
        "\u0420\u0435\u0447\u043a\u0430"
    ],
    "wof:name":"Rechka",
    "wof:placetype":"locality"
},
  "geometry": {"coordinates":[94.06583000000001,56.02916999999999],"type":"Point"}
}