{
  "type": "Feature",
  "properties": {
    "gn:admin1_code":"51.0",
    "gn:asciiname":"Sukhonoska",
    "gn:country_code":"RU",
    "gn:dem":119,
    "gn:feature_class":"P",
    "gn:feature_code":"PPL",
    "gn:name":"Sukhonoska",
    "gn:population":0,
    "gn:timezone":"Europe/Moscow",
    "iso:country":"RU",
    "name:nor_x_preferred":[
        "Sukhonoska"
    ],
    "name:rus_x_preferred":[
        "\u0421\u0443\u0445\u043e\u043d\u043e\u0441\u043a\u0430"
    ],
    "wof:name":"Sukhonoska",
    "wof:placetype":"locality"
},
  "geometry": {"coordinates":[43.77926,57.02417],"type":"Point"}
}