{
  "type": "Feature",
  "properties": {
    "gn:country":"RU",
    "gn:fcode":"PPL",
    "gn:population":1077,
    "iso:country":"RU",
    "name:eng_x_preferred":[
        "Kaltay"
    ],
    "name:nor_x_preferred":[
        "Kaltaj"
    ],
    "name:rus_x_preferred":[
        "\u041a\u0430\u043b\u0442\u0430\u0439"
    ],
    "name:und_x_variant":[
        "Kadtay"
    ],
    "qs:name":"Kaltay",
    "qs:photos_9r":0,
    "qs:photos_sr":0,
    "qs:pop_sr":"3",
    "wof:name":"Kaltay",
    "wof:placetype":"locality",
    "wof:population":1077
},
  "geometry": {"coordinates":[84.87860999999999,56.27917],"type":"Point"}
}