{
  "type": "Feature",
  "properties": {
    "gn:admin1_code":"73",
    "gn:asciiname":"Kil'debyak",
    "gn:country_code":"RU",
    "gn:dem":157,
    "gn:feature_class":"P",
    "gn:feature_code":"PPL",
    "gn:name":"Kil\u2019debyak",
    "gn:population":0,
    "gn:timezone":"Europe/Moscow",
    "iso:country":"RU",
    "name:eng_x_preferred":[
        "Kil'debyak"
    ],
    "name:nor_x_preferred":[
        "Kildebjak"
    ],
    "name:rus_x_preferred":[
        "\u041a\u0438\u043b\u044c\u0434\u0435\u0431\u044f\u043a"
    ],
    "name:und_x_variant":[
        "Kil\u2019debyak"
    ],
    "wof:name":"Kil'debyak",
    "wof:placetype":"locality"
},
  "geometry": {"coordinates":[50.5667,56.023],"type":"Point"}
}