{
  "type": "Feature",
  "properties": {
    "gn:admin1_code":"41",
    "gn:asciiname":"Makeyev",
    "gn:country_code":"RU",
    "gn:dem":174,
    "gn:feature_class":"P",
    "gn:feature_code":"PPL",
    "gn:name":"Makeyev",
    "gn:population":0,
    "gn:timezone":"Europe/Moscow",
    "iso:country":"RU",
    "name:rus_x_preferred":[
        "\u041c\u0430\u043a\u0435\u0435\u0432"
    ],
    "name:ukr_x_preferred":[
        "\u041c\u0430\u043a\u0435\u0454\u0432"
    ],
    "wof:name":"Makeyev",
    "wof:placetype":"locality"
},
  "geometry": {"coordinates":[35.4754,51.8805],"type":"Point"}
}