{
  "type": "Feature",
  "properties": {
    "gn:admin1_code":"80",
    "gn:asciiname":"Malaya Kopka",
    "gn:country_code":"RU",
    "gn:dem":158,
    "gn:feature_class":"P",
    "gn:feature_code":"PPL",
    "gn:name":"Malaya Kopka",
    "gn:population":0,
    "gn:timezone":"Europe/Samara",
    "iso:country":"RU",
    "name:rus_x_preferred":[
        "\u041c\u0430\u043b\u0430\u044f \u041a\u043e\u043f\u043a\u0430"
    ],
    "name:und_x_variant":[
        "Malyye Kopki",
        "Malaya Kopka"
    ],
    "wof:name":"Malaya Kopka",
    "wof:placetype":"locality"
},
  "geometry": {"coordinates":[52.15519000000001,56.50144],"type":"Point"}
}