{
  "type": "Feature",
  "properties": {
    "gn:admin1_code":"33.0",
    "gn:asciiname":"Bad'iny",
    "gn:country_code":"RU",
    "gn:dem":159,
    "gn:feature_class":"P",
    "gn:feature_code":"PPL",
    "gn:name":"Bad\u2019iny",
    "gn:population":0,
    "gn:timezone":"Europe/Kirov",
    "iso:country":"RU",
    "name:nor_x_preferred":[
        "Badiny"
    ],
    "name:rus_x_preferred":[
        "\u0411\u0430\u0434\u044c\u0438\u043d\u044b"
    ],
    "name:und_x_variant":[
        "Bad\u2019iny"
    ],
    "wof:name":"Bad'iny",
    "wof:placetype":"locality"
},
  "geometry": {"coordinates":[48.86278,58.55042],"type":"Point"}
}