{
  "type": "Feature",
  "properties": {
    "gn:admin1_code":"85",
    "gn:asciiname":"Konstantinovskiye Porogi",
    "gn:cc2":"RU",
    "gn:country_code":"RU",
    "gn:dem":80,
    "gn:feature_class":"P",
    "gn:feature_code":"PPL",
    "gn:name":"Konstantinovskiye Porogi",
    "gn:population":0,
    "gn:timezone":"Europe/Moscow",
    "iso:country":"RU",
    "name:rus_x_preferred":[
        "\u041a\u043e\u043d\u0441\u0442\u0430\u043d\u0442\u0438\u043d\u043e\u0432\u0441\u043a\u0438\u0435 \u041f\u043e\u0440\u043e\u0433\u0438"
    ],
    "name:und_x_variant":[
        "Porogi",
        "Konstantinovskoye",
        "Konstantinovskiye Porogi"
    ],
    "wof:name":"Konstantinovskiye Porogi",
    "wof:placetype":"locality"
},
  "geometry": {"coordinates":[37.15,60.56667],"type":"Point"}
}