{
  "type": "Feature",
  "properties": {
    "gn:admin1_code":"56",
    "gn:asciiname":"Korolevka",
    "gn:country_code":"RU",
    "gn:dem":214,
    "gn:feature_class":"P",
    "gn:feature_code":"PPL",
    "gn:name":"Korol\u00ebvka",
    "gn:population":0,
    "gn:timezone":"Europe/Moscow",
    "iso:country":"RU",
    "name:rus_x_preferred":[
        "\u041a\u043e\u0440\u043e\u043b\u0451\u0432\u043a\u0430"
    ],
    "name:und_x_variant":[
        "Korol\u00ebvka",
        "\u041a\u043e\u0440\u043e\u043b\u0451\u0432\u043a\u0430"
    ],
    "wof:name":"Korolevka",
    "wof:placetype":"locality"
},
  "geometry": {"coordinates":[36.19002,53.37974000000001],"type":"Point"}
}