{
  "type": "Feature",
  "properties": {
    "gn:country":"RU",
    "gn:fcode":"PPLX",
    "gn:population":17836,
    "iso:country":"RU",
    "name:eng_x_preferred":[
        "Kosaya Gora"
    ],
    "name:nor_x_preferred":[
        "Kosaja Gora"
    ],
    "name:rus_x_preferred":[
        "\u041a\u043e\u0441\u0430\u044f \u0413\u043e\u0440\u0430"
    ],
    "qs_pg:aaroncc":"RU",
    "qs_pg:gn_country":"RU",
    "qs_pg:gn_fcode":"PPLX",
    "qs_pg:gn_pop":17836,
    "qs_pg:name":"Kosaya Gora",
    "qs_pg:photos_9r":0,
    "qs_pg:photos_sr":0,
    "qs_pg:pop_sr":6,
    "qs_pg:qs_pg_placetype":"neighbourhood",
    "wof:name":"Kosaya Gora",
    "wof:placetype":"neighbourhood",
    "wof:population":17836
},
  "geometry": {"coordinates":[37.54459,54.11896],"type":"Point"}
}