{
  "type": "Feature",
  "properties": {
    "gn:admin1_code":"88",
    "gn:asciiname":"Zvyagino",
    "gn:country_code":"RU",
    "gn:dem":148,
    "gn:feature_class":"P",
    "gn:feature_code":"PPL",
    "gn:name":"Zvyagino",
    "gn:population":0,
    "gn:timezone":"Europe/Moscow",
    "iso:country":"RU",
    "name:rus_x_preferred":[
        "\u0417\u0432\u044f\u0433\u0438\u043d\u043e"
    ],
    "name:und_x_variant":[
        "\u0417\u0432\u044f\u0433\u0438\u043d\u043e"
    ],
    "wof:name":"Zvyagino",
    "wof:placetype":"locality"
},
  "geometry": {"coordinates":[38.9132,57.3079],"type":"Point"}
}