{
  "type": "Feature",
  "properties": {
    "gn:admin1_code":"91",
    "gn:asciiname":"Daurskoye",
    "gn:country_code":"RU",
    "gn:dem":329,
    "gn:feature_class":"P",
    "gn:feature_code":"PPL",
    "gn:name":"Daurskoye",
    "gn:population":0,
    "gn:timezone":"Asia/Krasnoyarsk",
    "iso:country":"RU",
    "name:eng_x_preferred":[
        "Daurskoye"
    ],
    "name:nor_x_preferred":[
        "Daurskoje"
    ],
    "name:rus_x_preferred":[
        "\u0414\u0430\u0443\u0440\u0441\u043a\u043e\u0435"
    ],
    "wof:name":"Daurskoye",
    "wof:placetype":"locality"
},
  "geometry": {"coordinates":[91.95917,55.22694],"type":"Point"}
}