{
  "type": "Feature",
  "properties": {
    "gn:admin1_code":"71",
    "gn:asciiname":"Polovinnyy",
    "gn:country_code":"RU",
    "gn:dem":318,
    "gn:feature_class":"P",
    "gn:feature_code":"PPL",
    "gn:name":"Polovinnyy",
    "gn:population":0,
    "gn:timezone":"Asia/Yekaterinburg",
    "iso:country":"RU",
    "name:eng_x_preferred":[
        "Polovinnyy"
    ],
    "name:nor_x_preferred":[
        "Polovinnyj"
    ],
    "name:rus_x_preferred":[
        "\u041f\u043e\u043b\u043e\u0432\u0438\u043d\u043d\u044b\u0439"
    ],
    "name:und_x_variant":[
        "\u041f\u043e\u043b\u043e\u0432\u0438\u043d\u043d\u044b\u0439",
        "Polovinnyy"
    ],
    "wof:name":"Polovinnyy",
    "wof:placetype":"locality"
},
  "geometry": {"coordinates":[59.8907,57.31368000000001],"type":"Point"}
}