{
  "type": "Feature",
  "properties": {
    "gn:admin1_code":"25",
    "gn:asciiname":"Melekhovo",
    "gn:country_code":"RU",
    "gn:dem":167,
    "gn:feature_class":"P",
    "gn:feature_code":"PPL",
    "gn:name":"Melekhovo",
    "gn:population":0,
    "gn:timezone":"Europe/Moscow",
    "iso:country":"RU",
    "name:eng_x_preferred":[
        "Melekhovo"
    ],
    "name:nor_x_preferred":[
        "Melekhovo"
    ],
    "name:rus_x_preferred":[
        "\u041c\u0435\u043b\u0435\u0445\u043e\u0432\u043e"
    ],
    "name:und_x_variant":[
        "Melekhova"
    ],
    "wof:name":"Melekhovo",
    "wof:placetype":"locality"
},
  "geometry": {"coordinates":[35.60431,53.60126999999999],"type":"Point"}
}