{
  "type": "Feature",
  "properties": {
    "gn:admin1_code":"10",
    "gn:asciiname":"Verkhopol'ye",
    "gn:country_code":"RU",
    "gn:dem":188,
    "gn:feature_class":"P",
    "gn:feature_code":"PPL",
    "gn:name":"Verkhopol\u2019ye",
    "gn:population":0,
    "gn:timezone":"Europe/Moscow",
    "iso:country":"RU",
    "name:eng_x_preferred":[
        "Verkhopol'ye"
    ],
    "name:nor_x_preferred":[
        "Verkhopolje"
    ],
    "name:rus_x_preferred":[
        "\u0412\u0435\u0440\u0445\u043e\u043f\u043e\u043b\u044c\u0435"
    ],
    "name:und_x_variant":[
        "Verkhopol\u2019ye"
    ],
    "wof:name":"Verkhopol'ye",
    "wof:placetype":"locality"
},
  "geometry": {"coordinates":[34.64258,53.0753],"type":"Point"}
}