{
  "type": "Feature",
  "properties": {
    "gn:admin1_code":"16",
    "gn:asciiname":"Vtoryye Yaldry",
    "gn:country_code":"RU",
    "gn:dem":140,
    "gn:feature_class":"P",
    "gn:feature_code":"PPL",
    "gn:name":"Vtoryye Yaldry",
    "gn:population":0,
    "gn:timezone":"Europe/Moscow",
    "iso:country":"RU",
    "name:rus_x_preferred":[
        "\u0412\u0442\u043e\u0440\u044b\u0435 \u042f\u043b\u0434\u0440\u044b"
    ],
    "name:und_x_variant":[
        "Yaldry Vtoryye",
        "Vtoryye Yaldry"
    ],
    "wof:name":"Vtoryye Yaldry",
    "wof:placetype":"locality"
},
  "geometry": {"coordinates":[46.68161,55.62623000000001],"type":"Point"}
}