{
  "type": "Feature",
  "properties": {
    "gn:admin1_code":"73.0",
    "gn:asciiname":"Bol'shaya Shukhota",
    "gn:country_code":"RU",
    "gn:dem":137,
    "gn:feature_class":"P",
    "gn:feature_code":"PPL",
    "gn:name":"Bol\u2019shaya Shukhota",
    "gn:population":0,
    "gn:timezone":"Europe/Moscow",
    "iso:country":"RU",
    "name:rus_x_preferred":[
        "\u0411\u043e\u043b\u044c\u0448\u0430\u044f \u0428\u0443\u0445\u043e\u0442\u0430"
    ],
    "name:und_x_variant":[
        "Bol\u2019shaya Shukhota",
        "Bol\u2019shaya Shukhata"
    ],
    "wof:name":"Bol'shaya Shukhota",
    "wof:placetype":"locality"
},
  "geometry": {"coordinates":[49.31639000000001,56.21111],"type":"Point"}
}