{
  "type": "Feature",
  "properties": {
    "gn:admin1_code":"55",
    "gn:asciiname":"Zadorozhnyy",
    "gn:country_code":"RU",
    "gn:dem":129,
    "gn:feature_class":"P",
    "gn:feature_code":"PPL",
    "gn:name":"Zadorozhnyy",
    "gn:population":0,
    "gn:timezone":"Asia/Yekaterinburg",
    "iso:country":"RU",
    "name:rus_x_preferred":[
        "\u0417\u0430\u0434\u043e\u0440\u043e\u0436\u043d\u044b\u0439"
    ],
    "name:und_x_variant":[
        "\u0417\u0430\u0434\u043e\u0440\u043e\u0436\u043d\u044b\u0439"
    ],
    "wof:name":"Zadorozhnyy",
    "wof:placetype":"locality"
},
  "geometry": {"coordinates":[52.4565,52.1094],"type":"Point"}
}