{
  "type": "Feature",
  "properties": {
    "gn:admin1_code":"93",
    "gn:asciiname":"Semiozer'ye",
    "gn:country_code":"RU",
    "gn:dem":1177,
    "gn:feature_class":"P",
    "gn:feature_code":"PPL",
    "gn:name":"Semioz\u00ebr\u2019ye",
    "gn:population":0,
    "gn:timezone":"Asia/Chita",
    "iso:country":"RU",
    "name:eng_x_preferred":[
        "Semiozer'ye"
    ],
    "name:nor_x_preferred":[
        "Semiozerje"
    ],
    "name:rus_x_preferred":[
        "\u0421\u0435\u043c\u0438\u043e\u0437\u0451\u0440\u044c\u0435"
    ],
    "name:und_x_variant":[
        "Semiozerskiy",
        "Semioz\u00ebr\u2019ye"
    ],
    "wof:name":"Semiozer'ye",
    "wof:placetype":"locality"
},
  "geometry": {"coordinates":[110.44701999999999,49.81961],"type":"Point"}
}