{
  "type": "Feature",
  "properties": {
    "gn:admin1_code":"77",
    "gn:asciiname":"Borilovo",
    "gn:country_code":"RU",
    "gn:dem":180,
    "gn:feature_class":"P",
    "gn:feature_code":"PPL",
    "gn:name":"Borilovo",
    "gn:population":0,
    "gn:timezone":"Europe/Moscow",
    "iso:country":"RU",
    "name:rus_x_preferred":[
        "\u0411\u043e\u0440\u0438\u043b\u043e\u0432\u043e"
    ],
    "wof:name":"Borilovo",
    "wof:placetype":"locality"
},
  "geometry": {"coordinates":[34.77539,57.36923],"type":"Point"}
}