{
  "type": "Feature",
  "properties": {
    "gn:admin1_code":"60",
    "gn:asciiname":"Krasino",
    "gn:country_code":"RU",
    "gn:dem":56,
    "gn:feature_class":"P",
    "gn:feature_code":"PPL",
    "gn:name":"Krasino",
    "gn:population":0,
    "gn:timezone":"Europe/Moscow",
    "iso:country":"RU",
    "name:bul_x_preferred":[
        "\u041a\u0440\u0430\u0441\u0438\u043d\u043e"
    ],
    "name:ceb_x_preferred":[
        "Krasino"
    ],
    "name:kaz_x_preferred":[
        "\u041a\u0440\u0430\u0441\u0438\u043d\u043e"
    ],
    "name:ron_x_preferred":[
        "Krasino"
    ],
    "name:rus_x_preferred":[
        "\u041a\u0440\u0430\u0441\u0438\u043d\u043e"
    ],
    "name:swe_x_preferred":[
        "Krasino"
    ],
    "name:ukr_x_preferred":[
        "\u041a\u0440\u0430\u0441\u0438\u043d\u043e"
    ],
    "wof:name":"Krasino",
    "wof:placetype":"locality"
},
  "geometry": {"coordinates":[28.27732,57.55367],"type":"Point"}
}