{
  "type": "Feature",
  "properties": {
    "gn:admin1_code":"77",
    "gn:asciiname":"Zastrov'ye",
    "gn:country_code":"RU",
    "gn:dem":162,
    "gn:feature_class":"P",
    "gn:feature_code":"PPL",
    "gn:name":"Zastrov\u2019ye",
    "gn:population":0,
    "gn:timezone":"Europe/Moscow",
    "iso:country":"RU",
    "name:rus_x_preferred":[
        "\u0417\u0430\u0441\u0442\u0440\u043e\u0432\u044c\u0435"
    ],
    "name:und_x_variant":[
        "Zastrov\u2019ye",
        "Zaostrov\u2019ye"
    ],
    "wof:name":"Zastrov'ye",
    "wof:placetype":"locality"
},
  "geometry": {"coordinates":[35.46763,58.32422],"type":"Point"}
}