{
  "type": "Feature",
  "properties": {
    "gn:admin1_code":"61",
    "gn:asciiname":"Verkhniy Verkholomov",
    "gn:cc2":"RU",
    "gn:country_code":"RU",
    "gn:dem":71,
    "gn:feature_class":"P",
    "gn:feature_code":"PPL",
    "gn:name":"Verkhniy Verkholomov",
    "gn:population":0,
    "gn:timezone":"Europe/Moscow",
    "iso:country":"RU",
    "name:und_x_variant":[
        "Verkhne-Verkholomov",
        "Verkhniy Verkholomov"
    ],
    "wof:name":"Verkhniy Verkholomov",
    "wof:placetype":"locality"
},
  "geometry": {"coordinates":[42.33167,46.87083],"type":"Point"}
}