{
  "type": "Feature",
  "properties": {
    "gn:admin1_code":"75",
    "gn:asciiname":"Igrekovo",
    "gn:country_code":"RU",
    "gn:dem":63,
    "gn:feature_class":"P",
    "gn:feature_code":"PPL",
    "gn:name":"Igrekovo",
    "gn:population":0,
    "gn:timezone":"Asia/Tomsk",
    "iso:country":"RU",
    "name:eng_x_preferred":[
        "Igrekovo"
    ],
    "name:nor_x_preferred":[
        "Igrekovo"
    ],
    "name:rus_x_preferred":[
        "\u0418\u0433\u0440\u0435\u043a\u043e\u0432\u043e"
    ],
    "wof:name":"Igrekovo",
    "wof:placetype":"locality"
},
  "geometry": {"coordinates":[83.78639,57.73583000000001],"type":"Point"}
}