{
  "type": "Feature",
  "properties": {
    "gn:admin1_code":"10",
    "gn:asciiname":"Rekord",
    "gn:country_code":"RU",
    "gn:dem":191,
    "gn:feature_class":"P",
    "gn:feature_code":"PPL",
    "gn:name":"Rekord",
    "gn:population":0,
    "gn:timezone":"Europe/Moscow",
    "iso:country":"RU",
    "name:rus_x_preferred":[
        "\u0420\u0435\u043a\u043e\u0440\u0434"
    ],
    "wof:name":"Rekord",
    "wof:placetype":"locality"
},
  "geometry": {"coordinates":[34.8913,52.3194],"type":"Point"}
}