{
  "type": "Feature",
  "properties": {
    "gn:admin1_code":"21",
    "gn:asciiname":"Sokol'skoye",
    "gn:country_code":"RU",
    "gn:dem":108,
    "gn:feature_class":"P",
    "gn:feature_code":"PPL",
    "gn:name":"Sokol\u2019skoye",
    "gn:population":0,
    "gn:timezone":"Europe/Moscow",
    "iso:country":"RU",
    "name:eng_x_preferred":[
        "Sokol'skoye"
    ],
    "name:nor_x_preferred":[
        "Sokolskoje"
    ],
    "name:rus_x_preferred":[
        "\u0421\u043e\u043a\u043e\u043b\u044c\u0441\u043a\u043e\u0435"
    ],
    "name:und_x_variant":[
        "\u0421\u043e\u043a\u043e\u043b\u044c\u0441\u043a\u043e\u0435",
        "Sokol\u2019skoye"
    ],
    "wof:name":"Sokol'skoye",
    "wof:placetype":"locality"
},
  "geometry": {"coordinates":[42.26225,57.09004],"type":"Point"}
}