{
  "type": "Feature",
  "properties": {
    "gn:admin1_code":"70",
    "gn:asciiname":"Verkhneyegorlykskiy",
    "gn:country_code":"RU",
    "gn:dem":302,
    "gn:feature_class":"P",
    "gn:feature_code":"PPL",
    "gn:name":"Verkhneyegorlykskiy",
    "gn:population":0,
    "gn:timezone":"Europe/Moscow",
    "iso:country":"RU",
    "name:eng_x_preferred":[
        "Verkhneyegorlykskiy"
    ],
    "name:nor_x_preferred":[
        "Verkhnejegorlykskij"
    ],
    "name:rus_x_preferred":[
        "\u0412\u0435\u0440\u0445\u043d\u0435\u0435\u0433\u043e\u0440\u043b\u044b\u043a\u0441\u043a\u0438\u0439"
    ],
    "wof:name":"Verkhneyegorlykskiy",
    "wof:placetype":"locality"
},
  "geometry": {"coordinates":[41.8629,44.9186],"type":"Point"}
}