{
  "type": "Feature",
  "properties": {
    "gn:admin1_code":"57",
    "gn:asciiname":"Mokryye Ovrazhki",
    "gn:country_code":"RU",
    "gn:dem":254,
    "gn:feature_class":"P",
    "gn:feature_code":"PPL",
    "gn:name":"Mokryye Ovrazhki",
    "gn:population":0,
    "gn:timezone":"Europe/Moscow",
    "iso:country":"RU",
    "name:rus_x_preferred":[
        "\u041c\u043e\u043a\u0440\u044b\u0435 \u041e\u0432\u0440\u0430\u0436\u043a\u0438"
    ],
    "name:und_x_variant":[
        "Mokryye Vrazhki"
    ],
    "wof:name":"Mokryye Ovrazhki",
    "wof:placetype":"locality"
},
  "geometry": {"coordinates":[44.4819,53.2975],"type":"Point"}
}