{
  "type": "Feature",
  "properties": {
    "gn:admin1_code":"38",
    "gn:asciiname":"Makushin",
    "gn:cc2":"RU",
    "gn:country_code":"RU",
    "gn:dem":53,
    "gn:feature_class":"P",
    "gn:feature_code":"PPL",
    "gn:name":"Makushin",
    "gn:population":0,
    "gn:timezone":"Europe/Moscow",
    "iso:country":"RU",
    "name:rus_x_preferred":[
        "\u041c\u0430\u043a\u0443\u0448\u0438\u043d"
    ],
    "name:und_x_variant":[
        "Makushin Balka",
        "Makushina Balka",
        "Makushin",
        "\u041c\u0430\u043a\u0443\u0448\u0438\u043d"
    ],
    "wof:name":"Makushin",
    "wof:placetype":"locality"
},
  "geometry": {"coordinates":[39.96667,46.43333],"type":"Point"}
}