{
  "type": "Feature",
  "properties": {
    "gn:admin1_code":"54",
    "gn:asciiname":"Kaydaul",
    "gn:country_code":"RU",
    "gn:dem":115,
    "gn:feature_class":"P",
    "gn:feature_code":"PPL",
    "gn:name":"Kaydaul",
    "gn:population":0,
    "gn:timezone":"Asia/Omsk",
    "iso:country":"RU",
    "name:eng_x_preferred":[
        "Kaydaul"
    ],
    "name:nor_x_preferred":[
        "Kajdaul"
    ],
    "name:rus_x_preferred":[
        "\u041a\u0430\u0439\u0434\u0430\u0443\u043b"
    ],
    "wof:name":"Kaydaul",
    "wof:placetype":"locality"
},
  "geometry": {"coordinates":[73.7867,54.1359],"type":"Point"}
}