{
  "type": "Feature",
  "properties": {
    "gn:admin1_code":"85",
    "gn:asciiname":"Shepyakovo",
    "gn:country_code":"RU",
    "gn:dem":115,
    "gn:feature_class":"P",
    "gn:feature_code":"PPL",
    "gn:name":"Shepyakovo",
    "gn:population":0,
    "gn:timezone":"Europe/Moscow",
    "iso:country":"RU",
    "name:rus_x_preferred":[
        "\u0428\u0435\u043f\u044f\u043a\u043e\u0432\u043e"
    ],
    "name:und_x_variant":[
        "\u0428\u0435\u043f\u044f\u043a\u043e\u0432\u043e"
    ],
    "wof:name":"Shepyakovo",
    "wof:placetype":"locality"
},
  "geometry": {"coordinates":[40.26667,59.05],"type":"Point"}
}