{
  "type": "Feature",
  "properties": {
    "gn:admin1_code":"76",
    "gn:asciiname":"Babushkino",
    "gn:country_code":"RU",
    "gn:dem":212,
    "gn:feature_class":"P",
    "gn:feature_code":"PPL",
    "gn:name":"Babushkino",
    "gn:population":0,
    "gn:timezone":"Europe/Moscow",
    "iso:country":"RU",
    "name:nor_x_preferred":[
        "Babusjkino"
    ],
    "name:rus_x_preferred":[
        "\u0411\u0430\u0431\u0443\u0448\u043a\u0438\u043d\u043e"
    ],
    "wof:name":"Babushkino",
    "wof:placetype":"locality"
},
  "geometry": {"coordinates":[37.42362,53.88059000000001],"type":"Point"}
}