{
  "type": "Feature",
  "properties": {
    "gn:admin1_code":"57.0",
    "gn:asciiname":"Ulanovka",
    "gn:country_code":"RU",
    "gn:dem":220,
    "gn:feature_class":"P",
    "gn:feature_code":"PPL",
    "gn:name":"Ulanovka",
    "gn:population":0,
    "gn:timezone":"Europe/Moscow",
    "iso:country":"RU",
    "name:rus_x_preferred":[
        "\u0423\u043b\u0430\u043d\u043e\u0432\u043a\u0430"
    ],
    "wof:name":"Ulanovka",
    "wof:placetype":"locality"
},
  "geometry": {"coordinates":[44.7532,52.9206],"type":"Point"}
}