{
  "type": "Feature",
  "properties": {
    "gn:admin1_code":"21.0",
    "gn:asciiname":"Isayevskoye",
    "gn:country_code":"RU",
    "gn:dem":126,
    "gn:feature_class":"P",
    "gn:feature_code":"PPL",
    "gn:name":"Isayevskoye",
    "gn:population":0,
    "gn:timezone":"Europe/Moscow",
    "iso:country":"RU",
    "name:rus_x_preferred":[
        "\u0418\u0441\u0430\u0435\u0432\u0441\u043a\u043e\u0435"
    ],
    "name:und_x_variant":[
        "\u0418\u0441\u0430\u0435\u0432\u0441\u043a\u043e\u0435"
    ],
    "wof:name":"Isayevskoye",
    "wof:placetype":"locality"
},
  "geometry": {"coordinates":[41.09544,57.21058000000001],"type":"Point"}
}