{
  "type": "Feature",
  "properties": {
    "gn:admin1_code":"46",
    "gn:asciiname":"Ivanova Polyana",
    "gn:country_code":"RU",
    "gn:dem":173,
    "gn:feature_class":"P",
    "gn:feature_code":"PPL",
    "gn:name":"Ivanova Polyana",
    "gn:population":0,
    "gn:timezone":"Europe/Moscow",
    "iso:country":"RU",
    "name:rus_x_preferred":[
        "\u0418\u0432\u0430\u043d\u043e\u0432\u0430 \u041f\u043e\u043b\u044f\u043d\u0430"
    ],
    "name:und_x_variant":[
        "\u0418\u0432\u0430\u043d\u043e\u0432\u0430 \u041f\u043e\u043b\u044f\u043d\u0430"
    ],
    "wof:name":"Ivanova Polyana",
    "wof:placetype":"locality"
},
  "geometry": {"coordinates":[45.8051,54.3522],"type":"Point"}
}