{
  "type": "Feature",
  "properties": {
    "gn:admin1_code":"88",
    "gn:asciiname":"Tret'yachikha",
    "gn:country_code":"RU",
    "gn:dem":134,
    "gn:feature_class":"P",
    "gn:feature_code":"PPL",
    "gn:name":"Tret\u2019yachikha",
    "gn:population":0,
    "gn:timezone":"Europe/Moscow",
    "iso:country":"RU",
    "name:rus_x_preferred":[
        "\u0422\u0440\u0435\u0442\u044c\u044f\u0447\u0438\u0445\u0430"
    ],
    "name:und_x_variant":[
        "Tret\u2019yachikha",
        "\u0422\u0440\u0435\u0442\u044c\u044f\u0447\u0438\u0445\u0430"
    ],
    "wof:name":"Tret'yachikha",
    "wof:placetype":"locality"
},
  "geometry": {"coordinates":[37.5229,58.3771],"type":"Point"}
}