{
  "type": "Feature",
  "properties": {
    "gn:admin1_code":"57",
    "gn:asciiname":"Zalapino",
    "gn:country_code":"RU",
    "gn:dem":258,
    "gn:feature_class":"P",
    "gn:feature_code":"PPL",
    "gn:name":"Zalapino",
    "gn:population":0,
    "gn:timezone":"Europe/Moscow",
    "iso:country":"RU",
    "name:und_x_variant":[
        "Zolotino",
        "Zalapino"
    ],
    "wof:name":"Zalapino",
    "wof:placetype":"locality"
},
  "geometry": {"coordinates":[46.54732,52.70766],"type":"Point"}
}