{
  "type": "Feature",
  "properties": {
    "gn:admin1_code":"81.0",
    "gn:asciiname":"Akshuat",
    "gn:country_code":"RU",
    "gn:dem":214,
    "gn:feature_class":"P",
    "gn:feature_code":"PPL",
    "gn:name":"Akshuat",
    "gn:population":0,
    "gn:timezone":"Europe/Ulyanovsk",
    "iso:country":"RU",
    "name:eng_x_preferred":[
        "Akshuat"
    ],
    "name:nor_x_preferred":[
        "Aksjuat"
    ],
    "name:rus_x_preferred":[
        "\u0410\u043a\u0448\u0443\u0430\u0442"
    ],
    "wof:name":"Akshuat",
    "wof:placetype":"locality"
},
  "geometry": {"coordinates":[47.43977,53.67652],"type":"Point"}
}