{
  "type": "Feature",
  "properties": {
    "gn:admin1_code":"83",
    "gn:asciiname":"Koshirino",
    "gn:country_code":"RU",
    "gn:dem":168,
    "gn:feature_class":"P",
    "gn:feature_code":"PPL",
    "gn:name":"Koshirino",
    "gn:population":0,
    "gn:timezone":"Europe/Moscow",
    "iso:country":"RU",
    "name:und_x_variant":[
        "Kashirino",
        "Koshirino"
    ],
    "wof:name":"Koshirino",
    "wof:placetype":"locality"
},
  "geometry": {"coordinates":[42.32096,56.22489],"type":"Point"}
}