{
  "type": "Feature",
  "properties": {
    "gn:admin1_code":"6",
    "gn:asciiname":"Kolokolovskaya",
    "gn:country_code":"RU",
    "gn:dem":103,
    "gn:feature_class":"P",
    "gn:feature_code":"PPL",
    "gn:name":"Kolokolovskaya",
    "gn:population":0,
    "gn:timezone":"Europe/Moscow",
    "iso:country":"RU",
    "name:che_x_preferred":[
        "\u041a\u043e\u043b\u043e\u043a\u043e\u043b\u043e\u0432\u0441\u043a\u0438"
    ],
    "name:eng_x_preferred":[
        "Kolokolovskaya"
    ],
    "name:nor_x_preferred":[
        "Kolokolovskaja"
    ],
    "name:rus_x_preferred":[
        "\u041a\u043e\u043b\u043e\u043a\u043e\u043b\u043e\u0432\u0441\u043a\u0430\u044f"
    ],
    "name:tat_x_preferred":[
        "\u041a\u043e\u043b\u043e\u043a\u043e\u043b\u043e\u0432\u0441\u043a\u0430\u044f"
    ],
    "name:tgk_x_preferred":[
        "\u041a\u043e\u043b\u043e\u043a\u043e\u043b\u043e\u0432\u0441\u043a\u0430\u044f"
    ],
    "wof:name":"Kolokolovskaya",
    "wof:placetype":"locality"
},
  "geometry": {"coordinates":[41.5307,61.5341],"type":"Point"}
}