{
  "type": "Feature",
  "properties": {
    "gn:admin1_code":"67",
    "gn:asciiname":"Ust'-Karaman",
    "gn:country_code":"RU",
    "gn:dem":26,
    "gn:feature_class":"P",
    "gn:feature_code":"PPL",
    "gn:name":"Ust\u2019-Karaman",
    "gn:population":0,
    "gn:timezone":"Europe/Saratov",
    "iso:country":"RU",
    "name:und_x_variant":[
        "Enders",
        "Ust\u2019-Karman",
        "Ust\u2019-Karaman"
    ],
    "wof:name":"Ust'-Karaman",
    "wof:placetype":"locality"
},
  "geometry": {"coordinates":[46.55389,51.65917],"type":"Point"}
}