{
  "type": "Feature",
  "properties": {
    "gn:admin1_code":"42",
    "gn:asciiname":"Kurkovitsy",
    "gn:country_code":"RU",
    "gn:dem":129,
    "gn:feature_class":"P",
    "gn:feature_code":"PPL",
    "gn:name":"Kurkovitsy",
    "gn:population":0,
    "gn:timezone":"Europe/Moscow",
    "iso:country":"RU",
    "name:fin_x_preferred":[
        "Kurkovitsa"
    ],
    "name:nor_x_preferred":[
        "Kurkovitsy"
    ],
    "name:rus_x_preferred":[
        "\u041a\u0443\u0440\u043a\u043e\u0432\u0438\u0446\u044b"
    ],
    "wof:name":"Kurkovitsy",
    "wof:placetype":"locality"
},
  "geometry": {"coordinates":[29.67402,59.42534000000001],"type":"Point"}
}