{
  "type": "Feature",
  "properties": {
    "gn:admin1_code":"37",
    "gn:asciiname":"Aleshunino",
    "gn:country_code":"RU",
    "gn:dem":115,
    "gn:feature_class":"P",
    "gn:feature_code":"PPL",
    "gn:name":"Al\u00ebshunino",
    "gn:population":0,
    "gn:timezone":"Europe/Moscow",
    "iso:country":"RU",
    "name:rus_x_preferred":[
        "\u0410\u043b\u0451\u0448\u0443\u043d\u0438\u043d\u043e"
    ],
    "name:und_x_variant":[
        "Al\u00ebshunino",
        "\u0410\u043b\u0451\u0448\u0443\u043d\u0438\u043d\u043e"
    ],
    "wof:name":"Aleshunino",
    "wof:placetype":"locality"
},
  "geometry": {"coordinates":[45.4993,58.3938],"type":"Point"}
}