{
  "type": "Feature",
  "properties": {
    "gn:admin1_code":"85",
    "gn:asciiname":"Yedoma",
    "gn:country_code":"RU",
    "gn:dem":115,
    "gn:feature_class":"P",
    "gn:feature_code":"PPL",
    "gn:name":"Yedoma",
    "gn:population":0,
    "gn:timezone":"Europe/Moscow",
    "iso:country":"RU",
    "name:eng_x_preferred":[
        "Yedoma"
    ],
    "name:fin_x_preferred":[
        "Jedoma"
    ],
    "name:fra_x_preferred":[
        "Yedoma"
    ],
    "name:ita_x_preferred":[
        "Jedoma"
    ],
    "name:kat_x_preferred":[
        "\u10d4\u10d3\u10dd\u10db\u10d0"
    ],
    "name:nor_x_preferred":[
        "Jedoma"
    ],
    "name:rus_x_preferred":[
        "\u0415\u0434\u043e\u043c\u0430"
    ],
    "name:und_x_variant":[
        "\u0415\u0434\u043e\u043c\u0430",
        "Yedoma"
    ],
    "wof:name":"Yedoma",
    "wof:placetype":"locality"
},
  "geometry": {"coordinates":[38.32218,59.1414],"type":"Point"}
}