{
  "type": "Feature",
  "properties": {
    "gn:admin1_code":"77",
    "gn:asciiname":"Ovsishche",
    "gn:country_code":"RU",
    "gn:dem":209,
    "gn:feature_class":"P",
    "gn:feature_code":"PPL",
    "gn:name":"Ovsishche",
    "gn:population":0,
    "gn:timezone":"Europe/Moscow",
    "iso:country":"RU",
    "name:rus_x_preferred":[
        "\u041e\u0432\u0441\u0438\u0449\u0435"
    ],
    "wof:name":"Ovsishche",
    "wof:placetype":"locality"
},
  "geometry": {"coordinates":[31.28369,56.60141],"type":"Point"}
}