{
  "type": "Feature",
  "properties": {
    "gn:admin1_code":"86",
    "gn:asciiname":"Sevost'yanovka",
    "gn:country_code":"RU",
    "gn:dem":131,
    "gn:feature_class":"P",
    "gn:feature_code":"PPL",
    "gn:name":"Sevost\u2019yanovka",
    "gn:population":0,
    "gn:timezone":"Europe/Moscow",
    "iso:country":"RU",
    "name:rus_x_preferred":[
        "\u0421\u0435\u0432\u043e\u0441\u0442\u044c\u044f\u043d\u043e\u0432\u043a\u0430"
    ],
    "name:und_x_variant":[
        "Sevast\u2019yanovka",
        "\u0421\u0435\u0432\u0430\u0441\u0442\u044c\u044f\u043d\u043e\u0432\u043a\u0430",
        "Sevost\u2019yanovka"
    ],
    "wof:name":"Sevost'yanovka",
    "wof:placetype":"locality"
},
  "geometry": {"coordinates":[38.8237,51.7661],"type":"Point"}
}