{
  "type": "Feature",
  "properties": {
    "gn:admin1_code":"42",
    "gn:admin2_code":"471099",
    "gn:asciiname":"Rokhma",
    "gn:country_code":"RU",
    "gn:dem":76,
    "gn:feature_class":"P",
    "gn:feature_code":"PPL",
    "gn:name":"Rokhma",
    "gn:population":0,
    "gn:timezone":"Europe/Moscow",
    "iso:country":"RU",
    "name:rus_x_preferred":[
        "\u0420\u043e\u0445\u043c\u0430"
    ],
    "name:und_x_variant":[
        "Rokhta",
        "Rokhma"
    ],
    "wof:name":"Rokhma",
    "wof:placetype":"locality"
},
  "geometry": {"coordinates":[30.38711,60.24978],"type":"Point"}
}