{
  "type": "Feature",
  "properties": {
    "gn:admin1_code":"65.0",
    "gn:asciiname":"Utekayevo",
    "gn:country_code":"RU",
    "gn:dem":64,
    "gn:feature_class":"P",
    "gn:feature_code":"PPL",
    "gn:name":"Utekayevo",
    "gn:population":0,
    "gn:timezone":"Europe/Samara",
    "iso:country":"RU",
    "name:nor_x_preferred":[
        "Basjkir-Vtekajevo"
    ],
    "name:rus_x_preferred":[
        "\u0423\u0442\u0435\u043a\u0430\u0435\u0432\u043e"
    ],
    "name:und_x_variant":[
        "Bashkir-Vtekayevo"
    ],
    "wof:name":"Utekayevo",
    "wof:placetype":"locality"
},
  "geometry": {"coordinates":[50.84827,52.20318],"type":"Point"}
}