{
  "type": "Feature",
  "properties": {
    "gn:admin1_code":"42",
    "gn:asciiname":"Mashino",
    "gn:country_code":"RU",
    "gn:dem":51,
    "gn:feature_class":"P",
    "gn:feature_code":"PPL",
    "gn:name":"Mashino",
    "gn:population":0,
    "gn:timezone":"Europe/Moscow",
    "iso:country":"RU",
    "name:rus_x_preferred":[
        "\u041c\u0430\u0448\u0438\u043d\u043e"
    ],
    "name:und_x_variant":[
        "\u041c\u0430\u0448\u0438\u043d\u043e"
    ],
    "wof:name":"Mashino",
    "wof:placetype":"locality"
},
  "geometry": {"coordinates":[30.75056,59.40694000000001],"type":"Point"}
}