{
  "type": "Feature",
  "properties": {
    "gn:admin1_code":"47",
    "gn:asciiname":"Malaya Il'inka",
    "gn:country_code":"RU",
    "gn:dem":111,
    "gn:feature_class":"P",
    "gn:feature_code":"PPL",
    "gn:name":"Malaya Il\u2019inka",
    "gn:population":0,
    "gn:timezone":"Europe/Moscow",
    "iso:country":"RU",
    "name:rus_x_preferred":[
        "\u041c\u0430\u043b\u0430\u044f \u0418\u043b\u044c\u0438\u043d\u043a\u0430"
    ],
    "name:und_x_variant":[
        "Malaya Il\u2019inka"
    ],
    "wof:name":"Malaya Il'inka",
    "wof:placetype":"locality"
},
  "geometry": {"coordinates":[39.46391,55.24329],"type":"Point"}
}