{
  "type": "Feature",
  "properties": {
    "gn:admin1_code":"19.0",
    "gn:asciiname":"Garbayeva",
    "gn:country_code":"RU",
    "gn:dem":571,
    "gn:feature_class":"P",
    "gn:feature_code":"PPL",
    "gn:name":"Garbayeva",
    "gn:population":0,
    "gn:timezone":"Europe/Moscow",
    "iso:country":"RU",
    "name:rus_x_preferred":[
        "\u0413\u0430\u0440\u0431\u0430\u0435\u0432\u0430"
    ],
    "wof:name":"Garbayeva",
    "wof:placetype":"locality"
},
  "geometry": {"coordinates":[44.59917,43.54028],"type":"Point"}
}