{
  "type": "Feature",
  "properties": {
    "gn:admin1_code":"85.0",
    "gn:asciiname":"Pil'yevo",
    "gn:country_code":"RU",
    "gn:dem":115,
    "gn:feature_class":"P",
    "gn:feature_code":"PPL",
    "gn:name":"Pil\u2019yevo",
    "gn:population":0,
    "gn:timezone":"Europe/Moscow",
    "iso:country":"RU",
    "name:rus_x_preferred":[
        "\u041f\u0438\u043b\u044c\u0435\u0432\u043e"
    ],
    "name:und_x_variant":[
        "Pil\u2019yevo"
    ],
    "wof:name":"Pil'yevo",
    "wof:placetype":"locality"
},
  "geometry": {"coordinates":[39.356,60.5216],"type":"Point"}
}