{
  "type": "Feature",
  "properties": {
    "gn:admin1_code":"33.0",
    "gn:asciiname":"Orekhovtsy",
    "gn:country_code":"RU",
    "gn:dem":133,
    "gn:feature_class":"P",
    "gn:feature_code":"PPL",
    "gn:name":"Orekhovtsy",
    "gn:population":0,
    "gn:timezone":"Europe/Kirov",
    "iso:country":"RU",
    "name:rus_x_preferred":[
        "\u041e\u0440\u0435\u0445\u043e\u0432\u0446\u044b"
    ],
    "name:und_x_variant":[
        "Orekhovy",
        "Orekhovtsy"
    ],
    "wof:name":"Orekhovtsy",
    "wof:placetype":"locality"
},
  "geometry": {"coordinates":[49.95877,58.51379],"type":"Point"}
}