{
  "type": "Feature",
  "properties": {
    "gn:admin1_code":"30",
    "gn:asciiname":"Innokent'yevka",
    "gn:country_code":"RU",
    "gn:dem":21,
    "gn:feature_class":"P",
    "gn:feature_code":"PPL",
    "gn:name":"Innokent\u2019yevka",
    "gn:population":0,
    "gn:timezone":"Asia/Vladivostok",
    "iso:country":"RU",
    "name:eng_x_preferred":[
        "Innokent'yevka"
    ],
    "name:nor_x_preferred":[
        "Innokentjevka"
    ],
    "name:rus_x_preferred":[
        "\u0418\u043d\u043d\u043e\u043a\u0435\u043d\u0442\u044c\u0435\u0432\u043a\u0430"
    ],
    "name:und_x_variant":[
        "\u0418\u043d\u043d\u043e\u043a\u0435\u043d\u0442\u044c\u0435\u0432\u043a\u0430",
        "Innokent\u2019yevka"
    ],
    "wof:name":"Innokent'yevka",
    "wof:placetype":"locality"
},
  "geometry": {"coordinates":[140.32217,53.23048000000001],"type":"Point"}
}