{
  "type": "Feature",
  "properties": {
    "gn:admin1_code":"59",
    "gn:asciiname":"Varpakhovka",
    "gn:country_code":"RU",
    "gn:dem":195,
    "gn:feature_class":"P",
    "gn:feature_code":"PPL",
    "gn:name":"Varpakhovka",
    "gn:population":0,
    "gn:timezone":"Asia/Vladivostok",
    "iso:country":"RU",
    "name:eng_x_preferred":[
        "Varpakhovka"
    ],
    "name:nor_x_preferred":[
        "Varpakhovka"
    ],
    "name:rus_x_preferred":[
        "\u0412\u0430\u0440\u043f\u0430\u0445\u043e\u0432\u043a\u0430"
    ],
    "name:und_x_variant":[
        "Varpanovka",
        "Varpakhovka"
    ],
    "wof:name":"Varpakhovka",
    "wof:placetype":"locality"
},
  "geometry": {"coordinates":[134.03826999999998,44.4087],"type":"Point"}
}