{
  "type": "Feature",
  "properties": {
    "gn:admin1_code":"34.0",
    "gn:asciiname":"Varysh",
    "gn:country_code":"RU",
    "gn:dem":144,
    "gn:feature_class":"P",
    "gn:feature_code":"PPL",
    "gn:name":"Varysh",
    "gn:population":0,
    "gn:timezone":"Europe/Moscow",
    "iso:country":"RU",
    "name:che_x_preferred":[
        "\u0412\u0430\u0440\u044b\u0448"
    ],
    "name:koi_x_preferred":[
        "\u0412\u0430\u0440\u044b\u0448"
    ],
    "name:rus_x_preferred":[
        "\u0412\u0430\u0440\u044b\u0448"
    ],
    "wof:name":"Varysh",
    "wof:placetype":"locality"
},
  "geometry": {"coordinates":[48.79733,59.94088000000001],"type":"Point"}
}