{
  "type": "Feature",
  "properties": {
    "gn:admin1_code":"8",
    "gn:asciiname":"Zhelannyy",
    "gn:country_code":"RU",
    "gn:dem":141,
    "gn:feature_class":"P",
    "gn:feature_code":"PPL",
    "gn:name":"Zhelannyy",
    "gn:population":0,
    "gn:timezone":"Asia/Yekaterinburg",
    "iso:country":"RU",
    "name:rus_x_preferred":[
        "\u0416\u0435\u043b\u0430\u043d\u043d\u044b\u0439"
    ],
    "wof:name":"Zhelannyy",
    "wof:placetype":"locality"
},
  "geometry": {"coordinates":[55.96051,53.33928],"type":"Point"}
}