{
  "type": "Feature",
  "properties": {
    "gn:admin1_code":"29",
    "gn:asciiname":"Maltsevo",
    "gn:cc2":"RU",
    "gn:country_code":"RU",
    "gn:dem":222,
    "gn:feature_class":"P",
    "gn:feature_code":"PPL",
    "gn:name":"Maltsevo",
    "gn:population":0,
    "gn:timezone":"Asia/Novokuznetsk",
    "iso:country":"RU",
    "name:eng_x_preferred":[
        "Maltsevo"
    ],
    "name:nor_x_preferred":[
        "Maltsevo"
    ],
    "name:rus_x_preferred":[
        "\u041c\u0430\u043b\u044c\u0446\u0435\u0432\u043e"
    ],
    "name:rus_x_variant":[
        "\u041c\u0430\u043b\u0446\u0435\u0432\u043e"
    ],
    "name:und_x_variant":[
        "Mal\u2019tseva",
        "Maltsevo",
        "\u041c\u0430\u043b\u0446\u0435\u0432\u043e"
    ],
    "wof:name":"Maltsevo",
    "wof:placetype":"locality"
},
  "geometry": {"coordinates":[87.13333,54.41667],"type":"Point"}
}