{
  "type": "Feature",
  "properties": {
    "gn:admin1_code":"73",
    "gn:asciiname":"Urazmet'yevo",
    "gn:country_code":"RU",
    "gn:dem":140,
    "gn:feature_class":"P",
    "gn:feature_code":"PPL",
    "gn:name":"Urazmet\u2019yevo",
    "gn:population":0,
    "gn:timezone":"Europe/Moscow",
    "iso:country":"RU",
    "name:eng_x_preferred":[
        "Urazmet'yevo"
    ],
    "name:nor_x_preferred":[
        "Urazmetjevo"
    ],
    "name:rus_x_preferred":[
        "\u0423\u0440\u0430\u0437\u043c\u0435\u0442\u044c\u0435\u0432\u043e"
    ],
    "name:und_x_variant":[
        "Urazmetevo",
        "Urazamet\u2019yevo",
        "Urazmet\u2019yevo"
    ],
    "wof:name":"Urazmet'yevo",
    "wof:placetype":"locality"
},
  "geometry": {"coordinates":[53.60695,55.39542],"type":"Point"}
}