{
  "type": "Feature",
  "properties": {
    "gn:admin1_code":"13",
    "gn:asciiname":"Koryazhnyy",
    "gn:cc2":"RU",
    "gn:country_code":"RU",
    "gn:dem":370,
    "gn:feature_class":"P",
    "gn:feature_code":"PPL",
    "gn:name":"Koryazhnyy",
    "gn:population":0,
    "gn:timezone":"Asia/Yekaterinburg",
    "iso:country":"RU",
    "name:rus_x_preferred":[
        "\u041a\u043e\u0440\u044f\u0436\u043d\u044b\u0439"
    ],
    "name:und_x_variant":[
        "Karyazhinskiy",
        "Koryazhnyy",
        "\u041a\u043e\u0440\u044f\u0436\u043d\u044b\u0439"
    ],
    "wof:name":"Koryazhnyy",
    "wof:placetype":"locality"
},
  "geometry": {"coordinates":[60.19416999999999,52.28306],"type":"Point"}
}