{
  "type": "Feature",
  "properties": {
    "gn:admin1_code":"44",
    "gn:asciiname":"Pestraya Dresva",
    "gn:country_code":"RU",
    "gn:dem":167,
    "gn:feature_class":"P",
    "gn:feature_code":"PPL",
    "gn:name":"P\u00ebstraya Dresva",
    "gn:population":0,
    "gn:timezone":"Asia/Magadan",
    "iso:country":"RU",
    "name:rus_x_preferred":[
        "\u041f\u0451\u0441\u0442\u0440\u0430\u044f \u0414\u0440\u0435\u0441\u0432\u0430"
    ],
    "name:und_x_variant":[
        "P\u00ebstraya Dresva"
    ],
    "wof:name":"Pestraya Dresva",
    "wof:placetype":"locality"
},
  "geometry": {"coordinates":[156.68333000000001,61.56667],"type":"Point"}
}