{
  "type": "Feature",
  "properties": {
    "gn:admin1_code":"85.0",
    "gn:asciiname":"Agafonovskaya",
    "gn:country_code":"RU",
    "gn:dem":185,
    "gn:feature_class":"P",
    "gn:feature_code":"PPL",
    "gn:name":"Agafonovskaya",
    "gn:population":0,
    "gn:timezone":"Europe/Moscow",
    "iso:country":"RU",
    "name:che_x_preferred":[
        "\u0410\u0433\u0430\u0444\u043e\u043d\u043e\u0432\u0441\u043a\u0438"
    ],
    "name:nor_x_preferred":[
        "Agafonovskaja"
    ],
    "name:rus_x_preferred":[
        "\u0410\u0433\u0430\u0444\u043e\u043d\u043e\u0432\u0441\u043a\u0430\u044f"
    ],
    "name:und_x_variant":[
        "Agafonovskaja",
        "Agafonovskaya"
    ],
    "wof:name":"Agafonovskaya",
    "wof:placetype":"locality"
},
  "geometry": {"coordinates":[37.93333,60.76667],"type":"Point"}
}