{
  "type": "Feature",
  "properties": {
    "gn:admin1_code":"55.0",
    "gn:asciiname":"Chkalov",
    "gn:country_code":"RU",
    "gn:dem":101,
    "gn:feature_class":"P",
    "gn:feature_code":"PPL",
    "gn:name":"Chkalov",
    "gn:population":0,
    "gn:timezone":"Asia/Yekaterinburg",
    "iso:country":"RU",
    "name:eng_x_preferred":[
        "Chkalov"
    ],
    "name:nor_x_preferred":[
        "Tsjkalov"
    ],
    "name:rus_x_preferred":[
        "\u0427\u043a\u0430\u043b\u043e\u0432"
    ],
    "wof:name":"Chkalov",
    "wof:placetype":"locality"
},
  "geometry": {"coordinates":[55.3637,51.7227],"type":"Point"}
}