{
  "type": "Feature",
  "properties": {
    "gn:admin1_code":"60",
    "gn:asciiname":"Shelukhi",
    "gn:country_code":"RU",
    "gn:dem":147,
    "gn:feature_class":"P",
    "gn:feature_code":"PPL",
    "gn:name":"Shelukhi",
    "gn:population":0,
    "gn:timezone":"Europe/Moscow",
    "iso:country":"RU",
    "name:rus_x_preferred":[
        "\u0428\u0435\u043b\u0443\u0445\u0438"
    ],
    "wof:name":"Shelukhi",
    "wof:placetype":"locality"
},
  "geometry": {"coordinates":[28.9278,56.524],"type":"Point"}
}