{
  "type": "Feature",
  "properties": {
    "gn:admin1_code":"16",
    "gn:asciiname":"Malaya Yerykla",
    "gn:country_code":"RU",
    "gn:dem":135,
    "gn:feature_class":"P",
    "gn:feature_code":"PPL",
    "gn:name":"Malaya Yerykla",
    "gn:population":0,
    "gn:timezone":"Europe/Moscow",
    "iso:country":"RU",
    "name:rus_x_preferred":[
        "\u041c\u0430\u043b\u0430\u044f \u0415\u0440\u044b\u043a\u043b\u0430"
    ],
    "wof:name":"Malaya Yerykla",
    "wof:placetype":"locality"
},
  "geometry": {"coordinates":[47.91104,55.18376],"type":"Point"}
}