{
  "type": "Feature",
  "properties": {
    "gn:admin1_code":"61.0",
    "gn:asciiname":"Denisovo-Alekseyevka",
    "gn:country_code":"RU",
    "gn:dem":84,
    "gn:feature_class":"P",
    "gn:feature_code":"PPL",
    "gn:name":"Denisovo-Alekseyevka",
    "gn:population":0,
    "gn:timezone":"Europe/Moscow",
    "iso:country":"RU",
    "name:rus_x_preferred":[
        "\u0414\u0435\u043d\u0438\u0441\u043e\u0432\u043e-\u0410\u043b\u0435\u043a\u0441\u0435\u0435\u0432\u043a\u0430"
    ],
    "name:ukr_x_preferred":[
        "Denisovo-Aleksyeyevka"
    ],
    "name:und_x_variant":[
        "Denisovo-Alekseyevskiy",
        "Denisovo-Alekseyevka",
        "\u0414\u0435\u043d\u0438\u0441\u043e\u0432\u043e-\u0410\u043b\u0435\u043a\u0441\u0435\u0435\u0432\u043a\u0430"
    ],
    "wof:name":"Denisovo-Alekseyevka",
    "wof:placetype":"locality"
},
  "geometry": {"coordinates":[39.32139,47.79741],"type":"Point"}
}