{
  "type": "Feature",
  "properties": {
    "gn:admin1_code":"60",
    "gn:asciiname":"Gribul'ski",
    "gn:country_code":"RU",
    "gn:dem":83,
    "gn:feature_class":"P",
    "gn:feature_code":"PPL",
    "gn:name":"Gribul\u2019ski",
    "gn:population":0,
    "gn:timezone":"Europe/Moscow",
    "iso:country":"RU",
    "name:rus_x_preferred":[
        "\u0413\u0440\u0438\u0431\u0443\u043b\u044c\u0441\u043a\u0438"
    ],
    "name:und_x_variant":[
        "Gribul\u2019ski"
    ],
    "wof:name":"Gribul'ski",
    "wof:placetype":"locality"
},
  "geometry": {"coordinates":[27.8386,57.46292],"type":"Point"}
}