{
  "type": "Feature",
  "properties": {
    "gn:admin1_code":"52",
    "gn:asciiname":"Bokovo",
    "gn:country_code":"RU",
    "gn:dem":127,
    "gn:feature_class":"P",
    "gn:feature_code":"PPL",
    "gn:name":"Bokovo",
    "gn:population":0,
    "gn:timezone":"Europe/Moscow",
    "iso:country":"RU",
    "name:rus_x_preferred":[
        "\u0411\u043e\u043a\u043e\u0432\u043e"
    ],
    "wof:name":"Bokovo",
    "wof:placetype":"locality"
},
  "geometry": {"coordinates":[32.4641,57.38775],"type":"Point"}
}