{
  "type": "Feature",
  "properties": {
    "gn:admin1_code":"60.0",
    "gn:asciiname":"Gnutiki",
    "gn:country_code":"RU",
    "gn:dem":208,
    "gn:feature_class":"P",
    "gn:feature_code":"PPL",
    "gn:name":"Gnutiki",
    "gn:population":0,
    "gn:timezone":"Europe/Moscow",
    "iso:country":"RU",
    "name:rus_x_preferred":[
        "\u0413\u043d\u0443\u0442\u0438\u043a\u0438"
    ],
    "name:und_x_variant":[
        "\u0413\u043d\u0443\u0442\u0438\u043a\u0438"
    ],
    "wof:name":"Gnutiki",
    "wof:placetype":"locality"
},
  "geometry": {"coordinates":[29.2183,56.6979],"type":"Point"}
}