{
  "type": "Feature",
  "properties": {
    "gn:country":"RU",
    "gn:fcode":"PPL",
    "gn:pop":6803,
    "iso:country":"RU",
    "name:arm_x_preferred":[
        "\u0544\u0561\u056c\u0561\u0575\u0561 \u054a\u0578\u0582\u0580\u0563\u0561"
    ],
    "name:che_x_preferred":[
        "\u041c\u0430\u043b\u0430\u044f \u041f\u0443\u0440\u0433\u0430"
    ],
    "name:dut_x_preferred":[
        "Malaja Poerga"
    ],
    "name:eng_x_preferred":[
        "Malaya Purga"
    ],
    "name:fin_x_preferred":[
        "Malaja Purga"
    ],
    "name:hun_x_preferred":[
        "Malaja Purga"
    ],
    "name:rus_x_preferred":[
        "\u041c\u0430\u043b\u0430\u044f \u041f\u0443\u0440\u0433\u0430"
    ],
    "name:udm_x_preferred":[
        "\u041f\u0438\u0447\u0438 \u041f\u0443\u0440\u0433\u0430"
    ],
    "name:ukr_x_preferred":[
        "\u041c\u0430\u043b\u0430 \u041f\u0443\u0440\u0433\u0430"
    ],
    "name:unk_x_variant":[
        "Malaya Purga"
    ],
    "qs:name":"Mal. Purga",
    "qs:name_adm0":"Russia",
    "qs:name_adm1":"Udmurtia Republic",
    "qs:photos_9r":0,
    "qs:photos_sr":0,
    "qs:placetype":"Town",
    "qs:pop_sr":"5",
    "wof:name":"Mal. Purga",
    "wof:placetype":"locality",
    "wof:population":6803
},
  "geometry": {"coordinates":[53.00434,56.55666],"type":"Point"}
}