{
  "type": "Feature",
  "properties": {
    "gn:admin1_code":"8",
    "gn:asciiname":"Ishmenevo",
    "gn:country_code":"RU",
    "gn:dem":151,
    "gn:feature_class":"P",
    "gn:feature_code":"PPL",
    "gn:name":"Ishmenevo",
    "gn:population":0,
    "gn:timezone":"Asia/Yekaterinburg",
    "iso:country":"RU",
    "name:bak_x_preferred":[
        "\u0418\u0448\u043c\u04d9\u043d"
    ],
    "name:che_x_preferred":[
        "\u0418\u0448\u043c\u0435\u043d\u0435\u0432\u043e"
    ],
    "name:hye_x_preferred":[
        "\u053b\u0577\u0574\u0565\u0576\u0587\u0578"
    ],
    "name:kaz_x_preferred":[
        "\u0418\u0448\u043c\u0435\u043d"
    ],
    "name:kir_x_preferred":[
        "\u0418\u0448\u043c\u0435\u043d"
    ],
    "name:rus_x_preferred":[
        "\u0418\u0448\u043c\u0435\u043d\u0435\u0432\u043e"
    ],
    "name:tat_x_preferred":[
        "\u0418\u0448\u043c\u04d9\u043d"
    ],
    "name:und_x_variant":[
        "\u0418\u0448\u043c\u0435\u043d\u0435\u0432\u043e"
    ],
    "wof:name":"Ishmenevo",
    "wof:placetype":"locality"
},
  "geometry": {"coordinates":[54.5299,54.6914],"type":"Point"}
}