{
  "type": "Feature",
  "properties": {
    "gn:admin1_code":"33.0",
    "gn:asciiname":"Salmaki",
    "gn:country_code":"RU",
    "gn:dem":135,
    "gn:feature_class":"P",
    "gn:feature_code":"PPL",
    "gn:name":"Salmaki",
    "gn:population":0,
    "gn:timezone":"Europe/Kirov",
    "iso:country":"RU",
    "name:rus_x_preferred":[
        "\u0421\u0430\u043b\u043c\u0430\u043a\u0438"
    ],
    "wof:name":"Salmaki",
    "wof:placetype":"locality"
},
  "geometry": {"coordinates":[49.13516,58.51813000000001],"type":"Point"}
}