{
  "type": "Feature",
  "properties": {
    "gn:admin1_code":"05",
    "gn:asciiname":"Sokhatino",
    "gn:country_code":"RU",
    "gn:dem":162,
    "gn:feature_class":"P",
    "gn:feature_code":"PPL",
    "gn:name":"Sokhatino",
    "gn:population":0,
    "gn:timezone":"Asia/Yakutsk",
    "iso:country":"RU",
    "name:eng_x_preferred":[
        "Sokhatino"
    ],
    "name:nor_x_preferred":[
        "Sokhatino"
    ],
    "name:rus_x_preferred":[
        "\u0421\u043e\u0445\u0430\u0442\u0438\u043d\u043e"
    ],
    "name:und_x_variant":[
        "Sakhatino",
        "Sokhanino",
        "Sokhatino"
    ],
    "wof:name":"Sokhatino",
    "wof:placetype":"locality"
},
  "geometry": {"coordinates":[128.85008999999999,51.68061],"type":"Point"}
}