{
  "type": "Feature",
  "properties": {
    "gn:admin1_code":"72",
    "gn:asciiname":"Ivano-Verdereyevka",
    "gn:country_code":"RU",
    "gn:dem":140,
    "gn:feature_class":"P",
    "gn:feature_code":"PPL",
    "gn:name":"Ivano-Verdereyevka",
    "gn:population":0,
    "gn:timezone":"Europe/Moscow",
    "iso:country":"RU",
    "name:rus_x_preferred":[
        "\u0418\u0432\u0430\u043d\u043e-\u0412\u0435\u0440\u0434\u0435\u0440\u0435\u0435\u0432\u043a\u0430"
    ],
    "wof:name":"Ivano-Verdereyevka",
    "wof:placetype":"locality"
},
  "geometry": {"coordinates":[40.655,53.2187],"type":"Point"}
}