{
  "type": "Feature",
  "properties": {
    "gn:admin1_code":"17",
    "gn:asciiname":"Khoymi",
    "gn:country_code":"RU",
    "gn:dem":1676,
    "gn:feature_class":"P",
    "gn:feature_code":"PPL",
    "gn:name":"Khoymi",
    "gn:population":0,
    "gn:timezone":"Europe/Moscow",
    "iso:country":"RU",
    "name:rus_x_preferred":[
        "\u0425\u043e\u0439\u043c\u0438"
    ],
    "name:und_x_variant":[
        "Keymi",
        "Khoymi",
        "\u0425\u043e\u0439\u043c\u0438"
    ],
    "wof:name":"Khoymi",
    "wof:placetype":"locality"
},
  "geometry": {"coordinates":[47.20822,42.09367],"type":"Point"}
}