{
  "type": "Feature",
  "properties": {
    "gn:admin1_code":"93",
    "gn:asciiname":"Arshan",
    "gn:country_code":"RU",
    "gn:dem":864,
    "gn:feature_class":"P",
    "gn:feature_code":"PPL",
    "gn:name":"Arshan",
    "gn:population":0,
    "gn:timezone":"Asia/Chita",
    "iso:country":"RU",
    "name:nor_x_preferred":[
        "Arsjan"
    ],
    "name:rus_x_preferred":[
        "\u0410\u0440\u0448\u0430\u043d"
    ],
    "wof:name":"Arshan",
    "wof:placetype":"locality"
},
  "geometry": {"coordinates":[110.15000000000001,51.38333],"type":"Point"}
}