{
  "type": "Feature",
  "properties": {
    "gn:admin1_code":"83",
    "gn:asciiname":"Prechistino",
    "gn:country_code":"RU",
    "gn:dem":194,
    "gn:feature_class":"P",
    "gn:feature_code":"PPL",
    "gn:name":"Prechistino",
    "gn:population":0,
    "gn:timezone":"Europe/Moscow",
    "iso:country":"RU",
    "name:rus_x_preferred":[
        "\u041f\u0440\u0435\u0447\u0438\u0441\u0442\u0438\u043d\u043e"
    ],
    "wof:name":"Prechistino",
    "wof:placetype":"locality"
},
  "geometry": {"coordinates":[39.0152,56.48967],"type":"Point"}
}