{
  "type": "Feature",
  "properties": {
    "gn:admin1_code":"88",
    "gn:asciiname":"Poselok Zubarevo",
    "gn:country_code":"RU",
    "gn:dem":106,
    "gn:feature_class":"P",
    "gn:feature_code":"PPL",
    "gn:name":"Pos\u00eblok Zubar\u00ebvo",
    "gn:population":0,
    "gn:timezone":"Europe/Moscow",
    "iso:country":"RU",
    "name:rus_x_preferred":[
        "\u041f\u043e\u0441\u0451\u043b\u043e\u043a \u0417\u0443\u0431\u0430\u0440\u0451\u0432\u043e"
    ],
    "name:und_x_variant":[
        "Pos\u00eblok Zubar\u00ebvo",
        "\u041f\u043e\u0441\u0451\u043b\u043e\u043a \u0417\u0443\u0431\u0430\u0440\u0451\u0432\u043e"
    ],
    "wof:name":"Poselok Zubarevo",
    "wof:placetype":"locality"
},
  "geometry": {"coordinates":[38.98013,58.48872],"type":"Point"}
}