{
  "type": "Feature",
  "properties": {
    "gn:admin1_code":"88.0",
    "gn:asciiname":"Novoivanovskoye",
    "gn:country_code":"RU",
    "gn:dem":163,
    "gn:feature_class":"P",
    "gn:feature_code":"PPL",
    "gn:name":"Novoivanovskoye",
    "gn:population":0,
    "gn:timezone":"Europe/Moscow",
    "iso:country":"RU",
    "name:che_x_preferred":[
        "\u041d\u043e\u0432\u043e\u0438\u0432\u0430\u043d\u043e\u0432\u0441\u043a\u0438"
    ],
    "name:hye_x_preferred":[
        "\u0546\u0578\u057e\u0578\u056b\u057e\u0561\u0576\u0578\u057e\u057d\u056f\u0578\u0565"
    ],
    "name:rus_x_preferred":[
        "\u041d\u043e\u0432\u043e\u0438\u0432\u0430\u043d\u043e\u0432\u0441\u043a\u043e\u0435"
    ],
    "wof:name":"Novoivanovskoye",
    "wof:placetype":"locality"
},
  "geometry": {"coordinates":[40.10358,58.19585],"type":"Point"}
}