{
  "type": "Feature",
  "properties": {
    "gn:admin1_code":"25",
    "gn:asciiname":"Kolosovo",
    "gn:country_code":"RU",
    "gn:dem":167,
    "gn:feature_class":"P",
    "gn:feature_code":"PPL",
    "gn:name":"Kolosovo",
    "gn:population":0,
    "gn:timezone":"Europe/Moscow",
    "iso:country":"RU",
    "name:rus_x_preferred":[
        "\u041a\u043e\u043b\u043e\u0441\u043e\u0432\u043e"
    ],
    "name:und_x_variant":[
        "Kolosova",
        "Kolosovo",
        "\u041a\u043e\u043b\u043e\u0441\u043e\u0432\u043e"
    ],
    "wof:name":"Kolosovo",
    "wof:placetype":"locality"
},
  "geometry": {"coordinates":[35.58685999999999,53.85289],"type":"Point"}
}