{
  "type": "Feature",
  "properties": {
    "gn:admin1_code":"33",
    "gn:asciiname":"Prokoshevy",
    "gn:country_code":"RU",
    "gn:dem":128,
    "gn:feature_class":"P",
    "gn:feature_code":"PPL",
    "gn:name":"Prokoshevy",
    "gn:population":0,
    "gn:timezone":"Europe/Kirov",
    "iso:country":"RU",
    "name:rus_x_preferred":[
        "\u041f\u0440\u043e\u043a\u043e\u0448\u0435\u0432\u044b"
    ],
    "wof:name":"Prokoshevy",
    "wof:placetype":"locality"
},
  "geometry": {"coordinates":[49.959,58.5281],"type":"Point"}
}