{
  "type": "Feature",
  "properties": {
    "gn:admin1_code":"83.0",
    "gn:asciiname":"Okatovo",
    "gn:country_code":"RU",
    "gn:dem":124,
    "gn:feature_class":"P",
    "gn:feature_code":"PPL",
    "gn:name":"Okatovo",
    "gn:population":0,
    "gn:timezone":"Europe/Moscow",
    "iso:country":"RU",
    "name:rus_x_preferred":[
        "\u041e\u043a\u0430\u0442\u043e\u0432\u043e"
    ],
    "wof:name":"Okatovo",
    "wof:placetype":"locality"
},
  "geometry": {"coordinates":[41.94354000000001,56.07443000000001],"type":"Point"}
}