{
  "type": "Feature",
  "properties": {
    "gn:admin1_code":"88",
    "gn:asciiname":"Baskachevo",
    "gn:country_code":"RU",
    "gn:dem":127,
    "gn:feature_class":"P",
    "gn:feature_code":"PPL",
    "gn:name":"Baskach\u00ebvo",
    "gn:population":0,
    "gn:timezone":"Europe/Moscow",
    "iso:country":"RU",
    "name:rus_x_preferred":[
        "\u0411\u0430\u0441\u043a\u0430\u0447\u0451\u0432\u043e"
    ],
    "name:und_x_variant":[
        "Baskach\u00ebvo"
    ],
    "wof:name":"Baskachevo",
    "wof:placetype":"locality"
},
  "geometry": {"coordinates":[38.2152,57.4896],"type":"Point"}
}