{
  "type": "Feature",
  "properties": {
    "gn:admin1_code":"17.0",
    "gn:asciiname":"Chankurbe",
    "gn:country_code":"RU",
    "gn:dem":896,
    "gn:feature_class":"P",
    "gn:feature_code":"PPL",
    "gn:name":"Chankurbe",
    "gn:population":0,
    "gn:timezone":"Europe/Moscow",
    "iso:country":"RU",
    "name:rus_x_preferred":[
        "\u0427\u0430\u043d\u043a\u0443\u0440\u0431\u0435"
    ],
    "name:und_x_variant":[
        "\u0427\u0430\u043d\u043a\u0443\u0440\u0431\u0435"
    ],
    "wof:name":"Chankurbe",
    "wof:placetype":"locality"
},
  "geometry": {"coordinates":[47.30963,42.6298],"type":"Point"}
}