{
  "type": "Feature",
  "properties": {
    "gn:admin1_code":"51.0",
    "gn:asciiname":"Pesochnoye",
    "gn:country_code":"RU",
    "gn:dem":113,
    "gn:feature_class":"P",
    "gn:feature_code":"PPL",
    "gn:name":"Pesochnoye",
    "gn:population":0,
    "gn:timezone":"Europe/Moscow",
    "iso:country":"RU",
    "name:rus_x_preferred":[
        "\u041f\u0435\u0441\u043e\u0447\u043d\u043e\u0435"
    ],
    "name:und_x_variant":[
        "\u041f\u0435\u0441\u043e\u0447\u043d\u043e\u0435"
    ],
    "wof:name":"Pesochnoye",
    "wof:placetype":"locality"
},
  "geometry": {"coordinates":[44.30708,56.77361],"type":"Point"}
}