{
  "type": "Feature",
  "properties": {
    "gn:admin1_code":"77",
    "gn:asciiname":"Pereter'ye",
    "gn:country_code":"RU",
    "gn:dem":142,
    "gn:feature_class":"P",
    "gn:feature_code":"PPL",
    "gn:name":"Pereter\u2019y\u00eb",
    "gn:population":0,
    "gn:timezone":"Europe/Moscow",
    "iso:country":"RU",
    "name:rus_x_preferred":[
        "\u041f\u0435\u0440\u0435\u0442\u0435\u0440\u044c\u0451"
    ],
    "name:und_x_variant":[
        "Kobylino",
        "Pereter\u2019y\u00eb",
        "\u041f\u0435\u0440\u0435\u0442\u0435\u0440\u044c\u0451"
    ],
    "wof:name":"Pereter'ye",
    "wof:placetype":"locality"
},
  "geometry": {"coordinates":[37.46079,57.73151],"type":"Point"}
}