{
  "type": "Feature",
  "properties": {
    "gn:admin1_code":"37",
    "gn:asciiname":"Borisyata",
    "gn:country_code":"RU",
    "gn:dem":138,
    "gn:feature_class":"P",
    "gn:feature_code":"PPL",
    "gn:name":"Borisyata",
    "gn:population":0,
    "gn:timezone":"Europe/Moscow",
    "iso:country":"RU",
    "name:rus_x_preferred":[
        "\u0411\u043e\u0440\u0438\u0441\u044f\u0442\u0430"
    ],
    "wof:name":"Borisyata",
    "wof:placetype":"locality"
},
  "geometry": {"coordinates":[46.5122,58.8756],"type":"Point"}
}