{
  "type": "Feature",
  "properties": {
    "gn:admin1_code":"21",
    "gn:asciiname":"Novinki",
    "gn:country_code":"RU",
    "gn:dem":161,
    "gn:feature_class":"P",
    "gn:feature_code":"PPL",
    "gn:name":"Novinki",
    "gn:population":0,
    "gn:timezone":"Europe/Moscow",
    "iso:country":"RU",
    "name:und_x_variant":[
        "Novinka",
        "Novinki"
    ],
    "wof:name":"Novinki",
    "wof:placetype":"locality"
},
  "geometry": {"coordinates":[40.94097,57.2457],"type":"Point"}
}