{
  "type": "Feature",
  "properties": {
    "gn:admin1_code":"20.0",
    "gn:asciiname":"Traktovaya",
    "gn:country_code":"RU",
    "gn:dem":514,
    "gn:feature_class":"P",
    "gn:feature_code":"PPL",
    "gn:name":"Traktovaya",
    "gn:population":0,
    "gn:timezone":"Asia/Irkutsk",
    "iso:country":"RU",
    "name:rus_x_preferred":[
        "\u0422\u0440\u0430\u043a\u0442\u043e\u0432\u0430\u044f"
    ],
    "wof:name":"Traktovaya",
    "wof:placetype":"locality"
},
  "geometry": {"coordinates":[102.92610000000001,53.2196],"type":"Point"}
}