{
  "type": "Feature",
  "properties": {
    "gn:admin1_code":"33",
    "gn:asciiname":"Kozly",
    "gn:country_code":"RU",
    "gn:dem":186,
    "gn:feature_class":"P",
    "gn:feature_code":"PPL",
    "gn:name":"Kozly",
    "gn:population":0,
    "gn:timezone":"Europe/Kirov",
    "iso:country":"RU",
    "name:rus_x_preferred":[
        "\u041a\u043e\u0437\u043b\u044b"
    ],
    "name:und_x_variant":[
        "\u041a\u043e\u0437\u043b\u044b"
    ],
    "wof:name":"Kozly",
    "wof:placetype":"locality"
},
  "geometry": {"coordinates":[50.70833,59.20222],"type":"Point"}
}