{
  "type": "Feature",
  "properties": {
    "gn:admin1_code":"90",
    "gn:asciiname":"Petukhova",
    "gn:country_code":"RU",
    "gn:dem":150,
    "gn:feature_class":"P",
    "gn:feature_code":"PPL",
    "gn:name":"Petukhova",
    "gn:population":0,
    "gn:timezone":"Asia/Yekaterinburg",
    "iso:country":"RU",
    "name:che_x_preferred":[
        "\u041f\u0435\u0442\u0443\u0445\u043e\u0432\u0430"
    ],
    "name:koi_x_preferred":[
        "\u041f\u0435\u0442\u0443\u043a"
    ],
    "name:rus_x_preferred":[
        "\u041f\u0435\u0442\u0443\u0445\u043e\u0432\u0430"
    ],
    "wof:name":"Petukhova",
    "wof:placetype":"locality"
},
  "geometry": {"coordinates":[54.93889,59.24444],"type":"Point"}
}