{
  "type": "Feature",
  "properties": {
    "gn:admin1_code":"43",
    "gn:asciiname":"Khleborob",
    "gn:country_code":"RU",
    "gn:dem":155,
    "gn:feature_class":"P",
    "gn:feature_code":"PPL",
    "gn:name":"Khleborob",
    "gn:population":0,
    "gn:timezone":"Europe/Moscow",
    "iso:country":"RU",
    "name:rus_x_preferred":[
        "\u0425\u043b\u0435\u0431\u043e\u0440\u043e\u0431"
    ],
    "name:und_x_variant":[
        "Khleboroby"
    ],
    "wof:name":"Khleborob",
    "wof:placetype":"locality"
},
  "geometry": {"coordinates":[39.81728,52.31983],"type":"Point"}
}