{
  "type": "Feature",
  "properties": {
    "gn:admin1_code":"42.0",
    "gn:asciiname":"Bol'shiye Vleshkovichi",
    "gn:country_code":"RU",
    "gn:dem":51,
    "gn:feature_class":"P",
    "gn:feature_code":"PPL",
    "gn:name":"Bol\u2019shiye Vleshkovichi",
    "gn:population":0,
    "gn:timezone":"Europe/Moscow",
    "iso:country":"RU",
    "name:rus_x_preferred":[
        "\u0411\u043e\u043b\u044c\u0448\u0438\u0435 \u0412\u043b\u0435\u0448\u043a\u043e\u0432\u0438\u0447\u0438"
    ],
    "name:und_x_variant":[
        "Bol\u2019shiye Vleshkovichi",
        "\u0411\u043e\u043b\u044c\u0448\u0438\u0435 \u0412\u043b\u0435\u0448\u043a\u043e\u0432\u0438\u0447\u0438"
    ],
    "wof:name":"Bol'shiye Vleshkovichi",
    "wof:placetype":"locality"
},
  "geometry": {"coordinates":[30.26047,58.77286],"type":"Point"}
}