{
  "type": "Feature",
  "properties": {
    "gn:admin1_code":"67",
    "gn:asciiname":"Sysoyev",
    "gn:country_code":"RU",
    "gn:dem":22,
    "gn:feature_class":"P",
    "gn:feature_code":"PPL",
    "gn:name":"Sysoyev",
    "gn:population":0,
    "gn:timezone":"Europe/Saratov",
    "iso:country":"RU",
    "name:eng_x_preferred":[
        "Sysoyev"
    ],
    "name:nor_x_preferred":[
        "Sysojev"
    ],
    "name:rus_x_preferred":[
        "\u0421\u044b\u0441\u043e\u0435\u0432"
    ],
    "wof:name":"Sysoyev",
    "wof:placetype":"locality"
},
  "geometry": {"coordinates":[48.35114,50.09038],"type":"Point"}
}