{
  "type": "Feature",
  "properties": {
    "gn:admin1_code":"73",
    "gn:asciiname":"Sredniy Shander",
    "gn:country_code":"RU",
    "gn:dem":98,
    "gn:feature_class":"P",
    "gn:feature_code":"PPL",
    "gn:name":"Sredniy Shander",
    "gn:population":0,
    "gn:timezone":"Europe/Moscow",
    "iso:country":"RU",
    "name:rus_x_preferred":[
        "\u0421\u0440\u0435\u0434\u043d\u0438\u0439 \u0428\u0430\u043d\u0434\u0435\u0440"
    ],
    "name:und_x_variant":[
        "\u0421\u0440\u0435\u0434\u043d\u0438\u0439 \u0428\u0430\u043d\u0434\u0435\u0440"
    ],
    "wof:name":"Sredniy Shander",
    "wof:placetype":"locality"
},
  "geometry": {"coordinates":[51.2915,55.9585],"type":"Point"}
}