{
  "type": "Feature",
  "properties": {
    "gn:admin1_code":"38",
    "gn:asciiname":"Shepeleva",
    "gn:cc2":"RU",
    "gn:country_code":"RU",
    "gn:dem":21,
    "gn:feature_class":"P",
    "gn:feature_code":"PPL",
    "gn:name":"Shepel\u00ebva",
    "gn:population":0,
    "gn:timezone":"Europe/Moscow",
    "iso:country":"RU",
    "name:rus_x_preferred":[
        "\u0428\u0435\u043f\u0435\u043b\u0451\u0432\u0430"
    ],
    "name:und_x_variant":[
        "Khutor Shepeleva",
        "Shepel\u00ebva",
        "\u0428\u0435\u043f\u0435\u043b\u0451\u0432\u0430"
    ],
    "wof:name":"Shepeleva",
    "wof:placetype":"locality"
},
  "geometry": {"coordinates":[38.66056,44.31889],"type":"Point"}
}