{
  "type": "Feature",
  "properties": {
    "gn:admin1_code":"37",
    "gn:asciiname":"Vasyutino",
    "gn:country_code":"RU",
    "gn:dem":151,
    "gn:feature_class":"P",
    "gn:feature_code":"PPL",
    "gn:name":"Vasyutino",
    "gn:population":0,
    "gn:timezone":"Europe/Moscow",
    "iso:country":"RU",
    "name:rus_x_preferred":[
        "\u0412\u0430\u0441\u044e\u0442\u0438\u043d\u043e"
    ],
    "name:und_x_variant":[
        "\u0412\u0430\u0441\u044e\u0442\u0438\u043d\u043e"
    ],
    "wof:name":"Vasyutino",
    "wof:placetype":"locality"
},
  "geometry": {"coordinates":[42.1162,58.0548],"type":"Point"}
}