{
  "type": "Feature",
  "properties": {
    "gn:admin1_code":"73",
    "gn:asciiname":"Mokraya Savaleyevka",
    "gn:country_code":"RU",
    "gn:dem":95,
    "gn:feature_class":"P",
    "gn:feature_code":"PPL",
    "gn:name":"Mokraya Savaleyevka",
    "gn:population":0,
    "gn:timezone":"Europe/Moscow",
    "iso:country":"RU",
    "wof:name":"Mokraya Savaleyevka",
    "wof:placetype":"locality"
},
  "geometry": {"coordinates":[48.00211,54.93849],"type":"Point"}
}