{
  "type": "Feature",
  "properties": {
    "gn:admin1_code":"8",
    "gn:asciiname":"Rodionovka",
    "gn:country_code":"RU",
    "gn:dem":295,
    "gn:feature_class":"P",
    "gn:feature_code":"PPL",
    "gn:name":"Rodionovka",
    "gn:population":0,
    "gn:timezone":"Asia/Yekaterinburg",
    "iso:country":"RU",
    "name:che_x_preferred":[
        "\u0420\u043e\u0434\u0438\u043e\u043d\u043e\u0432\u043a\u0430"
    ],
    "name:rus_x_preferred":[
        "\u0420\u043e\u0434\u0438\u043e\u043d\u043e\u0432\u043a\u0430"
    ],
    "name:tgk_x_preferred":[
        "\u0420\u043e\u0434\u0438\u043e\u043d\u043e\u0432\u043a\u0430"
    ],
    "wof:name":"Rodionovka",
    "wof:placetype":"locality"
},
  "geometry": {"coordinates":[55.07192,53.41543000000001],"type":"Point"}
}