{
  "type": "Feature",
  "properties": {
    "gn:admin1_code":"62",
    "gn:asciiname":"Lesnaya Polyana",
    "gn:country_code":"RU",
    "gn:dem":132,
    "gn:feature_class":"P",
    "gn:feature_code":"PPL",
    "gn:name":"Lesnaya Polyana",
    "gn:population":0,
    "gn:timezone":"Europe/Moscow",
    "iso:country":"RU",
    "name:che_x_preferred":[
        "\u041b\u0435\u0441\u043d\u0438 \u041f\u043e\u043b\u044f\u043d\u0430"
    ],
    "name:hye_x_preferred":[
        "\u053c\u0565\u057d\u0576\u0561\u0575\u0561 \u054a\u0578\u056c\u0575\u0561\u0576\u0561"
    ],
    "name:ita_x_preferred":[
        "Lesnaja Poljana"
    ],
    "name:rus_x_preferred":[
        "\u041b\u0435\u0441\u043d\u0430\u044f \u041f\u043e\u043b\u044f\u043d\u0430"
    ],
    "name:und_x_variant":[
        "\u041b\u0435\u0441\u043d\u0430\u044f \u041f\u043e\u043b\u044f\u043d\u0430"
    ],
    "wof:name":"Lesnaya Polyana",
    "wof:placetype":"locality"
},
  "geometry": {"coordinates":[41.23505,54.25696],"type":"Point"}
}