{
  "type": "Feature",
  "properties": {
    "gn:admin1_code":"55",
    "gn:asciiname":"Otrozhnyy",
    "gn:country_code":"RU",
    "gn:dem":154,
    "gn:feature_class":"P",
    "gn:feature_code":"PPL",
    "gn:name":"Otrozhnyy",
    "gn:population":0,
    "gn:timezone":"Asia/Yekaterinburg",
    "iso:country":"RU",
    "name:rus_x_preferred":[
        "\u041e\u0442\u0440\u043e\u0436\u043d\u044b\u0439"
    ],
    "name:und_x_variant":[
        "\u041e\u0442\u0440\u043e\u0436\u043d\u044b\u0439"
    ],
    "wof:name":"Otrozhnyy",
    "wof:placetype":"locality"
},
  "geometry": {"coordinates":[54.01667,52.56667],"type":"Point"}
}