{
  "type": "Feature",
  "properties": {
    "gn:admin1_code":"91.0",
    "gn:asciiname":"Tayga",
    "gn:country_code":"RU",
    "gn:dem":296,
    "gn:feature_class":"P",
    "gn:feature_code":"PPL",
    "gn:name":"Tayga",
    "gn:population":0,
    "gn:timezone":"Asia/Krasnoyarsk",
    "iso:country":"RU",
    "name:rus_x_preferred":[
        "\u0422\u0430\u0439\u0433\u0430"
    ],
    "wof:name":"Tayga",
    "wof:placetype":"locality"
},
  "geometry": {"coordinates":[91.46792000000001,56.21775],"type":"Point"}
}