{
  "type": "Feature",
  "properties": {
    "gn:admin1_code":"85",
    "gn:asciiname":"Khudyakovskaya",
    "gn:country_code":"RU",
    "gn:dem":160,
    "gn:feature_class":"P",
    "gn:feature_code":"PPL",
    "gn:name":"Khudyakovskaya",
    "gn:population":0,
    "gn:timezone":"Europe/Moscow",
    "iso:country":"RU",
    "name:rus_x_preferred":[
        "\u0425\u0443\u0434\u044f\u043a\u043e\u0432\u0441\u043a\u0430\u044f"
    ],
    "name:und_x_variant":[
        "\u0425\u0443\u0434\u044f\u043a\u043e\u0432\u0441\u043a\u0430\u044f"
    ],
    "wof:name":"Khudyakovskaya",
    "wof:placetype":"locality"
},
  "geometry": {"coordinates":[41.03333,60.21666999999999],"type":"Point"}
}