{
  "type": "Feature",
  "properties": {
    "gn:admin1_code":"55",
    "gn:asciiname":"Vertima",
    "gn:country_code":"RU",
    "gn:dem":239,
    "gn:feature_class":"P",
    "gn:feature_code":"PPL",
    "gn:name":"Vertima",
    "gn:population":0,
    "gn:timezone":"Asia/Yekaterinburg",
    "iso:country":"RU",
    "name:rus_x_preferred":[
        "\u0412\u0435\u0440\u0442\u0438\u043c\u0430"
    ],
    "wof:name":"Vertima",
    "wof:placetype":"locality"
},
  "geometry": {"coordinates":[52.6848,54.2398],"type":"Point"}
}