{
  "type": "Feature",
  "properties": {
    "gn:admin1_code":"23",
    "gn:asciiname":"Bakalino",
    "gn:country_code":"RU",
    "gn:dem":35,
    "gn:feature_class":"P",
    "gn:feature_code":"PPL",
    "gn:name":"Bakalino",
    "gn:population":0,
    "gn:timezone":"Europe/Kaliningrad",
    "iso:country":"RU",
    "name:nor_x_preferred":[
        "Bakalino"
    ],
    "name:rus_x_preferred":[
        "\u0411\u0430\u043a\u0430\u043b\u0438\u043d\u043e"
    ],
    "wof:name":"Bakalino",
    "wof:placetype":"locality"
},
  "geometry": {"coordinates":[19.95056,54.92389],"type":"Point"}
}