{
  "type": "Feature",
  "properties": {
    "gn:admin1_code":"85",
    "gn:asciiname":"Sobolevo",
    "gn:country_code":"RU",
    "gn:dem":124,
    "gn:feature_class":"P",
    "gn:feature_code":"PPL",
    "gn:name":"Sobolevo",
    "gn:population":0,
    "gn:timezone":"Europe/Moscow",
    "iso:country":"RU",
    "name:eng_x_preferred":[
        "Sobolevo"
    ],
    "name:nor_x_preferred":[
        "Sobolevo"
    ],
    "name:rus_x_preferred":[
        "\u0421\u043e\u0431\u043e\u043b\u0435\u0432\u043e"
    ],
    "wof:name":"Sobolevo",
    "wof:placetype":"locality"
},
  "geometry": {"coordinates":[36.5454,58.8285],"type":"Point"}
}