{
  "type": "Feature",
  "properties": {
    "gn:admin1_code":"56",
    "gn:asciiname":"Korsun'",
    "gn:country_code":"RU",
    "gn:dem":220,
    "gn:feature_class":"P",
    "gn:feature_code":"PPL",
    "gn:name":"Korsun\u2019",
    "gn:population":0,
    "gn:timezone":"Europe/Moscow",
    "iso:country":"RU",
    "name:rus_x_preferred":[
        "\u041a\u043e\u0440\u0441\u0443\u043d\u044c"
    ],
    "name:und_x_variant":[
        "Kersun\u2019",
        "Korsunskaya",
        "Korsun\u2019"
    ],
    "wof:name":"Korsun'",
    "wof:placetype":"locality"
},
  "geometry": {"coordinates":[37.00788,52.72291],"type":"Point"}
}