{
  "type": "Feature",
  "properties": {
    "gn:admin1_code":"10",
    "gn:asciiname":"Guta-Koretskaya",
    "gn:country_code":"RU",
    "gn:dem":147,
    "gn:feature_class":"P",
    "gn:feature_code":"PPL",
    "gn:name":"Guta-Koretskaya",
    "gn:population":0,
    "gn:timezone":"Europe/Moscow",
    "iso:country":"RU",
    "name:rus_x_preferred":[
        "\u0413\u0443\u0442\u0430-\u041a\u043e\u0440\u0435\u0446\u043a\u0430\u044f"
    ],
    "wof:name":"Guta-Koretskaya",
    "wof:placetype":"locality"
},
  "geometry": {"coordinates":[32.02995,52.84485],"type":"Point"}
}