{
  "type": "Feature",
  "properties": {
    "gn:admin1_code":"91",
    "gn:asciiname":"Klimovka",
    "gn:country_code":"RU",
    "gn:dem":333,
    "gn:feature_class":"P",
    "gn:feature_code":"PPL",
    "gn:name":"Klimovka",
    "gn:population":0,
    "gn:timezone":"Asia/Krasnoyarsk",
    "iso:country":"RU",
    "name:rus_x_preferred":[
        "\u041a\u043b\u0438\u043c\u043e\u0432\u043a\u0430"
    ],
    "wof:name":"Klimovka",
    "wof:placetype":"locality"
},
  "geometry": {"coordinates":[93.12944,54.00528000000001],"type":"Point"}
}