{
  "type": "Feature",
  "properties": {
    "gn:admin1_code":"85",
    "gn:asciiname":"Solomatino",
    "gn:country_code":"RU",
    "gn:dem":126,
    "gn:feature_class":"P",
    "gn:feature_code":"PPL",
    "gn:name":"Solomatino",
    "gn:population":0,
    "gn:timezone":"Europe/Moscow",
    "iso:country":"RU",
    "name:rus_x_preferred":[
        "\u0421\u043e\u043b\u043e\u043c\u0430\u0442\u0438\u043d\u043e"
    ],
    "name:und_x_variant":[
        "Salamatino",
        "Solomatino"
    ],
    "wof:name":"Solomatino",
    "wof:placetype":"locality"
},
  "geometry": {"coordinates":[39.2688,60.0169],"type":"Point"}
}