{
  "type": "Feature",
  "properties": {
    "gn:admin1_code":"8.0",
    "gn:asciiname":"Akhmerovo",
    "gn:country_code":"RU",
    "gn:dem":398,
    "gn:feature_class":"P",
    "gn:feature_code":"PPL",
    "gn:name":"Akhmerovo",
    "gn:population":0,
    "gn:timezone":"Asia/Yekaterinburg",
    "iso:country":"RU",
    "name:aze_x_preferred":[
        "\u018fxm\u0259r"
    ],
    "name:bak_x_preferred":[
        "\u04d8\u0445\u043c\u04d9\u0440"
    ],
    "name:che_x_preferred":[
        "\u0410\u0445\u043c\u0435\u0440\u043e\u0432\u043e"
    ],
    "name:eng_x_preferred":[
        "Akhmerovo"
    ],
    "name:hye_x_preferred":[
        "\u0531\u056d\u0574\u0565\u0580\u0578\u057e\u0578"
    ],
    "name:kat_x_preferred":[
        "\u10d0\u10ee\u10db\u10d4\u10e0\u10dd\u10d5\u10dd"
    ],
    "name:kaz_x_preferred":[
        "\u0410\u0445\u043c\u0435\u0440"
    ],
    "name:kir_x_preferred":[
        "\u0410\u0445\u043c\u0435\u0440"
    ],
    "name:nor_x_preferred":[
        "Akhmerovo"
    ],
    "name:rus_x_preferred":[
        "\u0410\u0445\u043c\u0435\u0440\u043e\u0432\u043e"
    ],
    "name:tat_x_preferred":[
        "\u04d8\u0445\u043c\u04d9\u0440"
    ],
    "name:ukr_x_preferred":[
        "\u0410\u0445\u043c\u0435\u0440\u043e\u0432\u043e"
    ],
    "name:und_x_variant":[
        "\u0410\u0445\u043c\u0435\u0440\u043e\u0432\u043e",
        "Akhmerovo"
    ],
    "wof:name":"Akhmerovo",
    "wof:placetype":"locality"
},
  "geometry": {"coordinates":[58.52778000000001,52.83221999999999],"type":"Point"}
}