{
  "type": "Feature",
  "properties": {
    "gn:admin1_code":"8.0",
    "gn:asciiname":"Akhmerovo",
    "gn:country_code":"RU",
    "gn:dem":398,
    "gn:feature_class":"P",
    "gn:feature_code":"PPL",
    "gn:name":"Akhmerovo",
    "gn:population":0,
    "gn:timezone":"Asia/Yekaterinburg",
    "iso:country":"RU",
    "name:eng_x_preferred":[
        "Akhmerovo"
    ],
    "name:nor_x_preferred":[
        "Akhmerovo"
    ],
    "name:rus_x_preferred":[
        "\u0410\u0445\u043c\u0435\u0440\u043e\u0432\u043e"
    ],
    "name:und_x_variant":[
        "\u0410\u0445\u043c\u0435\u0440\u043e\u0432\u043e",
        "Akhmerovo"
    ],
    "wof:name":"Akhmerovo",
    "wof:placetype":"locality"
},
  "geometry": {"coordinates":[58.52778000000001,52.83221999999999],"type":"Point"}
}