{
  "type": "Feature",
  "properties": {
    "gn:admin1_code":"8",
    "gn:asciiname":"Kuselyarovo",
    "gn:country_code":"RU",
    "gn:dem":232,
    "gn:feature_class":"P",
    "gn:feature_code":"PPL",
    "gn:name":"Kuselyarovo",
    "gn:population":0,
    "gn:timezone":"Asia/Yekaterinburg",
    "iso:country":"RU",
    "name:rus_x_preferred":[
        "\u041a\u0443\u0441\u0435\u043b\u044f\u0440\u043e\u0432\u043e"
    ],
    "name:und_x_variant":[
        "Kuselyarova",
        "Kuselyarovo"
    ],
    "wof:name":"Kuselyarovo",
    "wof:placetype":"locality"
},
  "geometry": {"coordinates":[57.88247,55.39782],"type":"Point"}
}