{
  "type": "Feature",
  "properties": {
    "gn:admin1_code":"33.0",
    "gn:asciiname":"Chiklyanovo",
    "gn:country_code":"RU",
    "gn:dem":159,
    "gn:feature_class":"P",
    "gn:feature_code":"PPL",
    "gn:name":"Chiklyanovo",
    "gn:population":0,
    "gn:timezone":"Europe/Kirov",
    "iso:country":"RU",
    "name:rus_x_preferred":[
        "\u0427\u0438\u043a\u043b\u044f\u043d\u043e\u0432\u043e"
    ],
    "name:und_x_variant":[
        "Chiklanovo",
        "Chiklyanovo"
    ],
    "wof:name":"Chiklyanovo",
    "wof:placetype":"locality"
},
  "geometry": {"coordinates":[48.59,57.1684],"type":"Point"}
}