{
  "type": "Feature",
  "properties": {
    "gn:admin1_code":"21",
    "gn:asciiname":"Marfino",
    "gn:country_code":"RU",
    "gn:dem":114,
    "gn:feature_class":"P",
    "gn:feature_code":"PPL",
    "gn:name":"Marfino",
    "gn:population":0,
    "gn:timezone":"Europe/Moscow",
    "iso:country":"RU",
    "name:rus_x_preferred":[
        "\u041c\u0430\u0440\u0444\u0438\u043d\u043e"
    ],
    "name:und_x_variant":[
        "\u041c\u0430\u0440\u0444\u0438\u043d\u043e"
    ],
    "wof:name":"Marfino",
    "wof:placetype":"locality"
},
  "geometry": {"coordinates":[41.91354000000001,57.27888000000001],"type":"Point"}
}