{
  "type": "Feature",
  "properties": {
    "gn:admin1_code":"86",
    "gn:asciiname":"Zaytsevka",
    "gn:country_code":"RU",
    "gn:dem":139,
    "gn:feature_class":"P",
    "gn:feature_code":"PPL",
    "gn:name":"Zaytsevka",
    "gn:population":0,
    "gn:timezone":"Europe/Moscow",
    "iso:country":"RU",
    "name:rus_x_preferred":[
        "\u0417\u0430\u0439\u0446\u0435\u0432\u043a\u0430"
    ],
    "wof:name":"Zaytsevka",
    "wof:placetype":"locality"
},
  "geometry": {"coordinates":[39.97259,49.6943],"type":"Point"}
}