{
  "type": "Feature",
  "properties": {
    "gn:admin1_code":"20.0",
    "gn:asciiname":"Subbotina",
    "gn:country_code":"RU",
    "gn:dem":503,
    "gn:feature_class":"P",
    "gn:feature_code":"PPL",
    "gn:name":"Subbotina",
    "gn:population":0,
    "gn:timezone":"Asia/Irkutsk",
    "iso:country":"RU",
    "name:rus_x_preferred":[
        "\u0421\u0443\u0431\u0431\u043e\u0442\u0438\u043d\u0430"
    ],
    "wof:name":"Subbotina",
    "wof:placetype":"locality"
},
  "geometry": {"coordinates":[103.29819999999999,52.94300000000001],"type":"Point"}
}