{
  "type": "Feature",
  "properties": {
    "gn:admin1_code":"90",
    "gn:asciiname":"Parkany",
    "gn:country_code":"RU",
    "gn:dem":209,
    "gn:feature_class":"P",
    "gn:feature_code":"PPL",
    "gn:name":"Parkany",
    "gn:population":0,
    "gn:timezone":"Asia/Yekaterinburg",
    "iso:country":"RU",
    "name:rus_x_preferred":[
        "\u041f\u0430\u0440\u043a\u0430\u043d\u044b"
    ],
    "name:und_x_variant":[
        "\u041f\u0430\u0440\u043a\u0430\u043d\u044b"
    ],
    "wof:name":"Parkany",
    "wof:placetype":"locality"
},
  "geometry": {"coordinates":[57.8698,57.7989],"type":"Point"}
}