{
  "type": "Feature",
  "properties": {
    "gn:admin1_code":"37",
    "gn:asciiname":"Zikeyevo",
    "gn:country_code":"RU",
    "gn:dem":162,
    "gn:feature_class":"P",
    "gn:feature_code":"PPL",
    "gn:name":"Zikeyevo",
    "gn:population":0,
    "gn:timezone":"Europe/Moscow",
    "iso:country":"RU",
    "name:rus_x_preferred":[
        "\u0417\u0438\u043a\u0435\u0435\u0432\u043e"
    ],
    "wof:name":"Zikeyevo",
    "wof:placetype":"locality"
},
  "geometry": {"coordinates":[42.9311,58.7292],"type":"Point"}
}