{
  "type": "Feature",
  "properties": {
    "gn:admin1_code":"73",
    "gn:asciiname":"Yanalif",
    "gn:country_code":"RU",
    "gn:dem":242,
    "gn:feature_class":"P",
    "gn:feature_code":"PPL",
    "gn:name":"Yanalif",
    "gn:population":0,
    "gn:timezone":"Europe/Moscow",
    "iso:country":"RU",
    "name:rus_x_preferred":[
        "\u042f\u043d\u0430\u043b\u0438\u0444"
    ],
    "name:und_x_variant":[
        "\u042f\u043d\u0430\u043b\u0438\u0444"
    ],
    "wof:name":"Yanalif",
    "wof:placetype":"locality"
},
  "geometry": {"coordinates":[52.7096,54.4186],"type":"Point"}
}