{
  "type": "Feature",
  "properties": {
    "gn:admin1_code":"77",
    "gn:asciiname":"Sukhaya Niva",
    "gn:country_code":"RU",
    "gn:dem":248,
    "gn:feature_class":"P",
    "gn:feature_code":"PPL",
    "gn:name":"Sukhaya Niva",
    "gn:population":0,
    "gn:timezone":"Europe/Moscow",
    "iso:country":"RU",
    "name:rus_x_preferred":[
        "\u0421\u0443\u0445\u0430\u044f \u041d\u0438\u0432\u0430"
    ],
    "name:und_x_variant":[
        "\u0421\u0443\u0445\u0430\u044f \u041d\u0438\u0432\u0430"
    ],
    "wof:name":"Sukhaya Niva",
    "wof:placetype":"locality"
},
  "geometry": {"coordinates":[33.35657,57.40898000000001],"type":"Point"}
}