{
  "type": "Feature",
  "properties": {
    "gn:admin1_code":"56",
    "gn:asciiname":"Merkulovskiye Dvoriki",
    "gn:country_code":"RU",
    "gn:dem":250,
    "gn:feature_class":"P",
    "gn:feature_code":"PPL",
    "gn:name":"Merkulovskiye Dvoriki",
    "gn:population":0,
    "gn:timezone":"Europe/Moscow",
    "iso:country":"RU",
    "wof:name":"Merkulovskiye Dvoriki",
    "wof:placetype":"locality"
},
  "geometry": {"coordinates":[37.14139,53.19722],"type":"Point"}
}