{
  "type": "Feature",
  "properties": {
    "gn:admin1_code":"71",
    "gn:asciiname":"Lugovaya",
    "gn:country_code":"RU",
    "gn:dem":232,
    "gn:feature_class":"P",
    "gn:feature_code":"PPL",
    "gn:name":"Lugovaya",
    "gn:population":0,
    "gn:timezone":"Asia/Yekaterinburg",
    "iso:country":"RU",
    "name:bel_x_preferred":[
        "\u041b\u0443\u0433\u0430\u0432\u0430\u044f"
    ],
    "name:ceb_x_preferred":[
        "Lugovaya"
    ],
    "name:rus_x_preferred":[
        "\u041b\u0443\u0433\u043e\u0432\u0430\u044f"
    ],
    "name:swe_x_preferred":[
        "Lugovaya"
    ],
    "name:tat_x_preferred":[
        "\u041b\u0443\u0433\u043e\u0432\u0430\u044f"
    ],
    "name:ukr_x_preferred":[
        "\u041b\u0443\u0433\u043e\u0432\u0430"
    ],
    "name:und_x_variant":[
        "Kopchik",
        "Lugovaya",
        "\u041b\u0443\u0433\u043e\u0432\u0430\u044f"
    ],
    "wof:name":"Lugovaya",
    "wof:placetype":"locality"
},
  "geometry": {"coordinates":[58.66481,57.9819],"type":"Point"}
}