{
  "type": "Feature",
  "properties": {
    "gn:admin1_code":"50",
    "gn:asciiname":"Staraya Yazhma Russkaya",
    "gn:cc2":"RU",
    "gn:country_code":"RU",
    "gn:dem":15,
    "gn:feature_class":"P",
    "gn:feature_code":"PPL",
    "gn:name":"Staraya Yazhma Russkaya",
    "gn:population":0,
    "gn:timezone":"Europe/Moscow",
    "iso:country":"RU",
    "name:rus_x_preferred":[
        "\u0421\u0442\u0430\u0440\u0430\u044f \u042f\u0436\u043c\u0430 \u0420\u0443\u0441\u0441\u043a\u0430\u044f"
    ],
    "name:und_x_variant":[
        "Staraya Yamzha Russkaya",
        "Staraya Yazhma Russkaya",
        "\u0421\u0442\u0430\u0440\u0430\u044f \u042f\u0436\u043c\u0430 \u0420\u0443\u0441\u0441\u043a\u0430\u044f"
    ],
    "wof:name":"Staraya Yazhma Russkaya",
    "wof:placetype":"locality"
},
  "geometry": {"coordinates":[44.65,66.78333000000001],"type":"Point"}
}