{
  "type": "Feature",
  "properties": {
    "gn:admin1_code":"17",
    "gn:admin2_code":"571887",
    "gn:asciiname":"Gunkha",
    "gn:country_code":"RU",
    "gn:dem":1590,
    "gn:feature_class":"P",
    "gn:feature_code":"PPL",
    "gn:name":"Gunkha",
    "gn:population":0,
    "gn:timezone":"Europe/Moscow",
    "iso:country":"RU",
    "name:rus_x_preferred":[
        "\u0413\u0443\u043d\u0445\u0430"
    ],
    "name:und_x_variant":[
        "Khunkho",
        "Gunkha"
    ],
    "wof:name":"Gunkha",
    "wof:placetype":"locality"
},
  "geometry": {"coordinates":[46.28275,42.78968],"type":"Point"}
}