{
  "type": "Feature",
  "properties": {
    "gn:admin1_code":"38",
    "gn:asciiname":"Malyy Raznokol",
    "gn:country_code":"RU",
    "gn:dem":10,
    "gn:feature_class":"P",
    "gn:feature_code":"PPL",
    "gn:name":"Malyy Raznokol",
    "gn:population":0,
    "gn:timezone":"Europe/Moscow",
    "iso:country":"RU",
    "name:rus_x_preferred":[
        "\u041c\u0430\u043b\u044b\u0439 \u0420\u0430\u0437\u043d\u043e\u043a\u043e\u043b"
    ],
    "name:und_x_variant":[
        "Maly Raznokol",
        "Malyy Raznokol"
    ],
    "wof:name":"Malyy Raznokol",
    "wof:placetype":"locality"
},
  "geometry": {"coordinates":[37.44148,45.14905],"type":"Point"}
}