{
  "type": "Feature",
  "properties": {
    "gn:country":"RU",
    "gn:fcode":"PPL",
    "gn:population":0,
    "iso:country":"RU",
    "name:rus_x_preferred":[
        "\u041c\u0435\u0449\u0435\u0440\u0438\u043d\u043e"
    ],
    "name:und_x_variant":[
        "Sovkhoz Meshcherino"
    ],
    "qs:name":"Meshcherino",
    "qs:name_adm0":"Russia",
    "qs:name_adm1":"Moscow Oblast",
    "qs:photos_9r":0,
    "qs:photos_sr":0,
    "qs:placetype":"Town",
    "qs:pop_sr":"0",
    "wof:name":"Meshcherino",
    "wof:placetype":"locality",
    "wof:population":0
},
  "geometry": {"coordinates":[37.83481,55.48824],"type":"Point"}
}