{
  "type": "Feature",
  "properties": {
    "gn:admin1_code":"84",
    "gn:asciiname":"Rubezhnyy",
    "gn:country_code":"RU",
    "gn:dem":135,
    "gn:feature_class":"P",
    "gn:feature_code":"PPL",
    "gn:name":"Rubezhnyy",
    "gn:population":0,
    "gn:timezone":"Europe/Volgograd",
    "iso:country":"RU",
    "name:eng_x_preferred":[
        "Rubezhnyy"
    ],
    "name:nor_x_preferred":[
        "Rubezjnyj"
    ],
    "name:rus_x_preferred":[
        "\u0420\u0443\u0431\u0435\u0436\u043d\u044b\u0439"
    ],
    "wof:name":"Rubezhnyy",
    "wof:placetype":"locality"
},
  "geometry": {"coordinates":[44.0515,49.81808],"type":"Point"}
}