{
  "type": "Feature",
  "properties": {
    "gn:admin1_code":"77",
    "gn:asciiname":"Zhitinki",
    "gn:country_code":"RU",
    "gn:dem":199,
    "gn:feature_class":"P",
    "gn:feature_code":"PPL",
    "gn:name":"Zhitinki",
    "gn:population":0,
    "gn:timezone":"Europe/Moscow",
    "iso:country":"RU",
    "name:und_x_variant":[
        "Mutyachino",
        "Zhitinki"
    ],
    "wof:name":"Zhitinki",
    "wof:placetype":"locality"
},
  "geometry": {"coordinates":[34.54708,56.30629],"type":"Point"}
}