{
  "type": "Feature",
  "properties": {
    "gn:admin1_code":"6.0",
    "gn:asciiname":"Kashino",
    "gn:country_code":"RU",
    "gn:dem":12,
    "gn:feature_class":"P",
    "gn:feature_code":"PPL",
    "gn:name":"Kashino",
    "gn:population":0,
    "gn:timezone":"Europe/Moscow",
    "iso:country":"RU",
    "name:che_x_preferred":[
        "\u041a\u0430\u0448\u0438\u043d\u043e"
    ],
    "name:rus_x_preferred":[
        "\u041a\u0430\u0448\u0438\u043d\u043e"
    ],
    "wof:name":"Kashino",
    "wof:placetype":"locality"
},
  "geometry": {"coordinates":[41.728,64.2972],"type":"Point"}
}