{
  "type": "Feature",
  "properties": {
    "gn:admin1_code":"85",
    "gn:asciiname":"Ananino",
    "gn:country_code":"RU",
    "gn:dem":174,
    "gn:feature_class":"P",
    "gn:feature_code":"PPL",
    "gn:name":"Ananino",
    "gn:population":0,
    "gn:timezone":"Europe/Moscow",
    "iso:country":"RU",
    "name:rus_x_preferred":[
        "\u0410\u043d\u0430\u043d\u0438\u043d\u043e"
    ],
    "name:und_x_variant":[
        "\u0410\u043d\u0430\u043d\u0438\u043d\u043e"
    ],
    "wof:name":"Ananino",
    "wof:placetype":"locality"
},
  "geometry": {"coordinates":[36.1307,59.9969],"type":"Point"}
}