{
  "type": "Feature",
  "properties": {
    "gn:admin1_code":"16",
    "gn:asciiname":"Kachikasy",
    "gn:country_code":"RU",
    "gn:dem":118,
    "gn:feature_class":"P",
    "gn:feature_code":"PPL",
    "gn:name":"Kachikasy",
    "gn:population":0,
    "gn:timezone":"Europe/Moscow",
    "iso:country":"RU",
    "name:rus_x_preferred":[
        "\u041a\u0430\u0447\u0438\u043a\u0430\u0441\u044b"
    ],
    "name:und_x_variant":[
        "\u041a\u0430\u0447\u0438\u043a\u0430\u0441\u044b"
    ],
    "wof:name":"Kachikasy",
    "wof:placetype":"locality"
},
  "geometry": {"coordinates":[46.46849,55.85014],"type":"Point"}
}