{
  "type": "Feature",
  "properties": {
    "gn:admin1_code":"25.0",
    "gn:asciiname":"Shatrishchi",
    "gn:country_code":"RU",
    "gn:dem":211,
    "gn:feature_class":"P",
    "gn:feature_code":"PPL",
    "gn:name":"Shatrishchi",
    "gn:population":0,
    "gn:timezone":"Europe/Moscow",
    "iso:country":"RU",
    "name:rus_x_preferred":[
        "\u0428\u0430\u0442\u0440\u0438\u0449\u0438"
    ],
    "wof:name":"Shatrishchi",
    "wof:placetype":"locality"
},
  "geometry": {"coordinates":[35.27,54.97],"type":"Point"}
}