{
  "type": "Feature",
  "properties": {
    "gn:admin1_code":"43",
    "gn:asciiname":"Zashevo",
    "gn:country_code":"RU",
    "gn:dem":209,
    "gn:feature_class":"P",
    "gn:feature_code":"PPL",
    "gn:name":"Zashevo",
    "gn:population":0,
    "gn:timezone":"Europe/Moscow",
    "iso:country":"RU",
    "name:rus_x_preferred":[
        "\u0417\u0430\u0448\u0435\u0432\u043e"
    ],
    "wof:name":"Zashevo",
    "wof:placetype":"locality"
},
  "geometry": {"coordinates":[38.9857,53.1825],"type":"Point"}
}