{
  "type": "Feature",
  "properties": {
    "gn:admin1_code":"54",
    "gn:asciiname":"Lebyazh'ye",
    "gn:country_code":"RU",
    "gn:dem":131,
    "gn:feature_class":"P",
    "gn:feature_code":"PPL",
    "gn:name":"Lebyazh\u2019ye",
    "gn:population":0,
    "gn:timezone":"Asia/Omsk",
    "iso:country":"RU",
    "name:eng_x_preferred":[
        "Lebyazh'ye"
    ],
    "name:nor_x_preferred":[
        "Lebjazje"
    ],
    "name:rus_x_preferred":[
        "\u041b\u0435\u0431\u044f\u0436\u044c\u0435"
    ],
    "name:und_x_variant":[
        "\u041b\u0435\u0431\u044f\u0436\u044c\u0435",
        "Lebyazh\u2019ye"
    ],
    "wof:name":"Lebyazh'ye",
    "wof:placetype":"locality"
},
  "geometry": {"coordinates":[71.01405,55.23321],"type":"Point"}
}