{
  "type": "Feature",
  "properties": {
    "gn:admin1_code":"9",
    "gn:asciiname":"Krutoy Log",
    "gn:country_code":"RU",
    "gn:dem":173,
    "gn:feature_class":"P",
    "gn:feature_code":"PPL",
    "gn:name":"Krutoy Log",
    "gn:population":0,
    "gn:timezone":"Europe/Moscow",
    "iso:country":"RU",
    "name:eng_x_preferred":[
        "Krutoy Log"
    ],
    "name:nor_x_preferred":[
        "Krutoj Log"
    ],
    "name:rus_x_preferred":[
        "\u041a\u0440\u0443\u0442\u043e\u0439 \u041b\u043e\u0433"
    ],
    "wof:name":"Krutoy Log",
    "wof:placetype":"locality"
},
  "geometry": {"coordinates":[36.74204,50.5215],"type":"Point"}
}