{
  "type": "Feature",
  "properties": {
    "gn:admin1_code":"88",
    "gn:asciiname":"Mikhal'tsevo",
    "gn:country_code":"RU",
    "gn:dem":121,
    "gn:feature_class":"P",
    "gn:feature_code":"PPL",
    "gn:name":"Mikhal\u2019tsevo",
    "gn:population":0,
    "gn:timezone":"Europe/Moscow",
    "iso:country":"RU",
    "name:rus_x_preferred":[
        "\u041c\u0438\u0445\u0430\u043b\u044c\u0446\u0435\u0432\u043e"
    ],
    "name:und_x_variant":[
        "Mikhal\u2019tsevo"
    ],
    "wof:name":"Mikhal'tsevo",
    "wof:placetype":"locality"
},
  "geometry": {"coordinates":[40.34874,58.02608000000001],"type":"Point"}
}