{
  "type": "Feature",
  "properties": {
    "gn:admin1_code":"93",
    "gn:asciiname":"Ust'-Atsa",
    "gn:country_code":"RU",
    "gn:dem":817,
    "gn:feature_class":"P",
    "gn:feature_code":"PPL",
    "gn:name":"Ust\u2019-Atsa",
    "gn:population":0,
    "gn:timezone":"Asia/Chita",
    "iso:country":"RU",
    "name:rus_x_preferred":[
        "\u0423\u0441\u0442\u044c-\u0410\u0446\u0430"
    ],
    "name:und_x_variant":[
        "Ust\u2019-Atsa"
    ],
    "wof:name":"Ust'-Atsa",
    "wof:placetype":"locality"
},
  "geometry": {"coordinates":[109.49928,50.53403],"type":"Point"}
}