{
  "type": "Feature",
  "properties": {
    "gn:admin1_code":"88",
    "gn:asciiname":"Khokhlovka",
    "gn:country_code":"RU",
    "gn:dem":119,
    "gn:feature_class":"P",
    "gn:feature_code":"PPL",
    "gn:name":"Khokhlovka",
    "gn:population":0,
    "gn:timezone":"Europe/Moscow",
    "iso:country":"RU",
    "name:deu_x_preferred":[
        "Chochlowka"
    ],
    "name:nor_x_preferred":[
        "Khokhlovka friluftsmuseum"
    ],
    "name:rus_x_preferred":[
        "\u0425\u043e\u0445\u043b\u043e\u0432\u043a\u0430"
    ],
    "wof:name":"Khokhlovka",
    "wof:placetype":"locality"
},
  "geometry": {"coordinates":[38.4575,57.892],"type":"Point"}
}