{
  "type": "Feature",
  "properties": {
    "gn:admin1_code":"10",
    "gn:asciiname":"Gulevka",
    "gn:country_code":"RU",
    "gn:dem":186,
    "gn:feature_class":"P",
    "gn:feature_code":"PPL",
    "gn:name":"Gulevka",
    "gn:population":799,
    "gn:timezone":"Europe/Moscow",
    "iso:country":"RU",
    "name:rus_x_preferred":[
        "\u0413\u0443\u043b\u0435\u0432\u043a\u0430"
    ],
    "wof:name":"Gulevka",
    "wof:placetype":"locality",
    "wof:population":799
},
  "geometry": {"coordinates":[32.22719,52.60979],"type":"Point"}
}