{
  "type": "Feature",
  "properties": {
    "gn:admin1_code":"17",
    "gn:admin2_code":"Tlyaratinskiy Rayon",
    "gn:asciiname":"Nachada",
    "gn:country_code":"RU",
    "gn:dem":2058,
    "gn:feature_class":"P",
    "gn:feature_code":"PPL",
    "gn:name":"Nachada",
    "gn:population":0,
    "gn:timezone":"Europe/Moscow",
    "iso:country":"RU",
    "name:rus_x_preferred":[
        "\u041d\u0430\u0447\u0430\u0434\u0430"
    ],
    "wof:name":"Nachada",
    "wof:placetype":"locality"
},
  "geometry": {"coordinates":[46.45358,42.19842],"type":"Point"}
}