{
  "type": "Feature",
  "properties": {
    "gn:admin1_code":"91",
    "gn:asciiname":"Novonikol'sk",
    "gn:country_code":"RU",
    "gn:dem":424,
    "gn:feature_class":"P",
    "gn:feature_code":"PPL",
    "gn:name":"Novonikol\u2019sk",
    "gn:population":0,
    "gn:timezone":"Asia/Krasnoyarsk",
    "iso:country":"RU",
    "name:eng_x_preferred":[
        "Novonikol'sk"
    ],
    "name:rus_x_preferred":[
        "\u041d\u043e\u0432\u043e\u043d\u0438\u043a\u043e\u043b\u044c\u0441\u043a"
    ],
    "name:rus_x_variant":[
        "\u041d\u043e\u0432\u043e\u0441\u0435\u043b\u044c\u0441\u043a"
    ],
    "name:und_x_variant":[
        "Novo-Nikol\u2019skoye",
        "Novyy Nikol\u2019sk",
        "Novosel\u2019sk",
        "Novonikol\u2019sk"
    ],
    "wof:name":"Novonikol'sk",
    "wof:placetype":"locality"
},
  "geometry": {"coordinates":[93.6109,55.7846],"type":"Point"}
}