{
  "type": "Feature",
  "properties": {
    "gn:admin1_code":"73",
    "gn:asciiname":"Malyy Oshnyak",
    "gn:country_code":"RU",
    "gn:dem":75,
    "gn:feature_class":"P",
    "gn:feature_code":"PPL",
    "gn:name":"Malyy Oshnyak",
    "gn:population":0,
    "gn:timezone":"Europe/Moscow",
    "iso:country":"RU",
    "name:rus_x_preferred":[
        "\u041c\u0430\u043b\u044b\u0439 \u041e\u0448\u043d\u044f\u043a"
    ],
    "name:und_x_variant":[
        "Maly Oshnyak",
        "Malyy Oshnyak"
    ],
    "wof:name":"Malyy Oshnyak",
    "wof:placetype":"locality"
},
  "geometry": {"coordinates":[49.98524000000001,55.51864000000001],"type":"Point"}
}