{
  "type": "Feature",
  "properties": {
    "gn:admin1_code":"77",
    "gn:asciiname":"Krasnopolets",
    "gn:country_code":"RU",
    "gn:dem":178,
    "gn:feature_class":"P",
    "gn:feature_code":"PPL",
    "gn:name":"Krasnopolets",
    "gn:population":0,
    "gn:timezone":"Europe/Moscow",
    "iso:country":"RU",
    "name:eng_x_preferred":[
        "Krasnopolets"
    ],
    "name:nor_x_preferred":[
        "Krasnopolets"
    ],
    "name:rus_x_preferred":[
        "\u041a\u0440\u0430\u0441\u043d\u043e\u043f\u043e\u043b\u0435\u0446"
    ],
    "wof:name":"Krasnopolets",
    "wof:placetype":"locality"
},
  "geometry": {"coordinates":[31.35949,56.8356],"type":"Point"}
}