{
  "type": "Feature",
  "properties": {
    "gn:admin1_code":"56",
    "gn:asciiname":"Avdeyevo",
    "gn:country_code":"RU",
    "gn:dem":211,
    "gn:feature_class":"P",
    "gn:feature_code":"PPL",
    "gn:name":"Avdeyevo",
    "gn:population":0,
    "gn:timezone":"Europe/Moscow",
    "iso:country":"RU",
    "name:nor_x_preferred":[
        "Avdejevo"
    ],
    "name:rus_x_preferred":[
        "\u0410\u0432\u0434\u0435\u0435\u0432\u043e"
    ],
    "wof:name":"Avdeyevo",
    "wof:placetype":"locality"
},
  "geometry": {"coordinates":[37.21556,53.24166999999999],"type":"Point"}
}