{
  "type": "Feature",
  "properties": {
    "gn:country":"RU",
    "gn:fcode":"PPL",
    "gn:population":21833,
    "iso:country":"RU",
    "name:azb_x_preferred":[
        "\u0644\u0648\u0686\u0642\u0648\u0631\u0632\u06a9"
    ],
    "name:bel_x_preferred":[
        "\u041b\u0443\u0447\u0430\u0433\u043e\u0440\u0441\u043a"
    ],
    "name:bul_x_preferred":[
        "\u041b\u0443\u0447\u0435\u0433\u043e\u0440\u0441\u043a"
    ],
    "name:cat_x_preferred":[
        "Lutxegorsk"
    ],
    "name:ceb_x_preferred":[
        "Luchegorsk"
    ],
    "name:crh_x_preferred":[
        "Lu\u00e7egorsk"
    ],
    "name:deu_x_preferred":[
        "Lutschegorsk"
    ],
    "name:eng_x_preferred":[
        "Luchegorsk"
    ],
    "name:eus_x_preferred":[
        "Lutxegorsk"
    ],
    "name:heb_x_preferred":[
        "\u05dc\u05d5\u05e6'\u05d2\u05d5\u05e8\u05e1\u05e7"
    ],
    "name:hun_x_preferred":[
        "Lucsegorszk"
    ],
    "name:ita_x_preferred":[
        "Lu\u010degorsk"
    ],
    "name:jpn_x_preferred":[
        "\u30eb\u30c1\u30a7\u30b4\u30eb\u30b9\u30af"
    ],
    "name:nld_x_preferred":[
        "Loetsjegorsk"
    ],
    "name:nob_x_preferred":[
        "Lutsjegorsk"
    ],
    "name:nor_x_preferred":[
        "Lutsjegorsk"
    ],
    "name:pol_x_preferred":[
        "\u0141uczegorsk"
    ],
    "name:rus_x_preferred":[
        "\u041b\u0443\u0447\u0435\u0433\u043e\u0440\u0441\u043a"
    ],
    "name:swe_x_preferred":[
        "Lutjegorsk"
    ],
    "name:ukr_x_preferred":[
        "\u041b\u0443\u0447\u0435\u0433\u043e\u0440\u0441\u044c\u043a"
    ],
    "name:zho_x_preferred":[
        "\u76e7\u5207\u6208\u723e\u65af\u514b"
    ],
    "qs:name":"Luchegorsk",
    "qs:photos_9r":0,
    "qs:photos_sr":0,
    "qs:pop_sr":"7",
    "wd:wordcount":361,
    "wof:name":"Luchegorsk",
    "wof:placetype":"locality",
    "wof:population":21833
},
  "geometry": {"coordinates":[134.19532000000001,46.47656],"type":"Point"}
}