{
  "type": "Feature",
  "properties": {
    "gn:country":"RU",
    "gn:fcode":"PPL",
    "gn:pop":21833,
    "iso:country":"RU",
    "name:bul_x_preferred":[
        "\u041b\u0443\u0447\u0435\u0433\u043e\u0440\u0441\u043a"
    ],
    "name:chi_x_preferred":[
        "\u76e7\u5207\u6208\u723e\u65af\u514b"
    ],
    "name:deu_x_preferred":[
        "Lutschegorsk"
    ],
    "name:dut_x_preferred":[
        "Loetsjegorsk"
    ],
    "name:eng_x_preferred":[
        "Luchegorsk"
    ],
    "name:ger_x_preferred":[
        "Lutschegorsk"
    ],
    "name:ita_x_preferred":[
        "Lu\u010degorsk"
    ],
    "name:jpn_x_preferred":[
        "\u30eb\u30c1\u30a7\u30b4\u30eb\u30b9\u30af"
    ],
    "name:nob_x_preferred":[
        "Lutsjegorsk"
    ],
    "name:nor_x_preferred":[
        "Lutsjegorsk"
    ],
    "name:rus_x_preferred":[
        "\u041b\u0443\u0447\u0435\u0433\u043e\u0440\u0441\u043a"
    ],
    "name:ukr_x_preferred":[
        "\u041b\u0443\u0447\u0435\u0433\u043e\u0440\u0441\u044c\u043a"
    ],
    "name:unk_x_variant":[
        "\u041b\u0443\u0447\u0435\u0433\u043e\u0440\u0441\u043a"
    ],
    "name:zho_x_preferred":[
        "\u76e7\u5207\u6208\u723e\u65af\u514b"
    ],
    "qs:name":"Luchegorsk",
    "qs:photos_9r":0,
    "qs:photos_sr":0,
    "qs:pop_sr":"7",
    "wd:wordcount":361,
    "wof:name":"Luchegorsk",
    "wof:placetype":"locality",
    "wof:population":21833
},
  "geometry": {"coordinates":[134.19532000000001,46.47656],"type":"Point"}
}