{
  "type": "Feature",
  "properties": {
    "gn:admin1_code":"56",
    "gn:asciiname":"Yablonovskiy",
    "gn:country_code":"RU",
    "gn:dem":242,
    "gn:feature_class":"P",
    "gn:feature_code":"PPL",
    "gn:name":"Yablonovskiy",
    "gn:population":0,
    "gn:timezone":"Europe/Moscow",
    "iso:country":"RU",
    "name:rus_x_preferred":[
        "\u042f\u0431\u043b\u043e\u043d\u043e\u0432\u0441\u043a\u0438\u0439"
    ],
    "wof:name":"Yablonovskiy",
    "wof:placetype":"locality"
},
  "geometry": {"coordinates":[35.1073,52.3885],"type":"Point"}
}