{
  "type": "Feature",
  "properties": {
    "gn:admin1_code":"69",
    "gn:asciiname":"Kholm",
    "gn:country_code":"RU",
    "gn:dem":219,
    "gn:feature_class":"P",
    "gn:feature_code":"PPL",
    "gn:name":"Kholm",
    "gn:population":0,
    "gn:timezone":"Europe/Moscow",
    "iso:country":"RU",
    "name:rus_x_preferred":[
        "\u0425\u043e\u043b\u043c"
    ],
    "name:und_x_variant":[
        "\u0425\u043e\u043b\u043c"
    ],
    "wof:name":"Kholm",
    "wof:placetype":"locality"
},
  "geometry": {"coordinates":[33.88565,54.82281],"type":"Point"}
}