{
  "type": "Feature",
  "properties": {
    "gn:admin1_code":"22",
    "gn:asciiname":"Prishibskaya",
    "gn:country_code":"RU",
    "gn:dem":204,
    "gn:feature_class":"P",
    "gn:feature_code":"PPL",
    "gn:name":"Prishibskaya",
    "gn:population":0,
    "gn:timezone":"Europe/Moscow",
    "iso:country":"RU",
    "name:rus_x_preferred":[
        "\u041f\u0440\u0438\u0448\u0438\u0431\u0441\u043a\u0430\u044f"
    ],
    "wof:name":"Prishibskaya",
    "wof:placetype":"locality"
},
  "geometry": {"coordinates":[44.08639,43.65444],"type":"Point"}
}