{
  "type": "Feature",
  "properties": {
    "gn:admin1_code":"84.0",
    "gn:asciiname":"Chugunov",
    "gn:country_code":"RU",
    "gn:dem":26,
    "gn:feature_class":"P",
    "gn:feature_code":"PPL",
    "gn:name":"Chugunov",
    "gn:population":0,
    "gn:timezone":"Europe/Volgograd",
    "iso:country":"RU",
    "name:deu_x_preferred":[
        "Tschugunow"
    ],
    "name:rus_x_preferred":[
        "\u0427\u0443\u0433\u0443\u043d\u043e\u0432"
    ],
    "wof:name":"Chugunov",
    "wof:placetype":"locality"
},
  "geometry": {"coordinates":[45.96667,49.48333],"type":"Point"}
}