{
  "type": "Feature",
  "properties": {
    "gn:admin1_code":"84",
    "gn:asciiname":"Vishnevka",
    "gn:country_code":"RU",
    "gn:dem":25,
    "gn:feature_class":"P",
    "gn:feature_code":"PPL",
    "gn:name":"Vishn\u00ebvka",
    "gn:population":0,
    "gn:timezone":"Europe/Volgograd",
    "iso:country":"RU",
    "name:eng_x_preferred":[
        "Vishn\u00ebvka"
    ],
    "name:nor_x_preferred":[
        "Visjnevka"
    ],
    "name:rus_x_preferred":[
        "\u0412\u0438\u0448\u043d\u0435\u0432\u043a\u0430"
    ],
    "wof:name":"Vishnevka",
    "wof:placetype":"locality"
},
  "geometry": {"coordinates":[46.77261,49.42872],"type":"Point"}
}