{
  "type": "Feature",
  "properties": {
    "gn:admin1_code":"33",
    "gn:asciiname":"Peschanyy Polom",
    "gn:cc2":"RU",
    "gn:country_code":"RU",
    "gn:dem":137,
    "gn:feature_class":"P",
    "gn:feature_code":"PPL",
    "gn:name":"Peschanyy Polom",
    "gn:population":0,
    "gn:timezone":"Europe/Kirov",
    "iso:country":"RU",
    "name:rus_x_preferred":[
        "\u041f\u0435\u0441\u0447\u0430\u043d\u044b\u0439 \u041f\u043e\u043b\u043e\u043c"
    ],
    "name:und_x_variant":[
        "Peschanny Polom",
        "Peschanyy Polom"
    ],
    "wof:name":"Peschanyy Polom",
    "wof:placetype":"locality"
},
  "geometry": {"coordinates":[50.26667,57.43333000000001],"type":"Point"}
}