{
  "type": "Feature",
  "properties": {
    "gn:admin1_code":"91",
    "gn:asciiname":"Krasnyy Khleborob",
    "gn:country_code":"RU",
    "gn:dem":261,
    "gn:feature_class":"P",
    "gn:feature_code":"PPL",
    "gn:name":"Krasnyy Khleborob",
    "gn:population":0,
    "gn:timezone":"Asia/Krasnoyarsk",
    "iso:country":"RU",
    "name:eng_x_preferred":[
        "Krasnyy Khleborob"
    ],
    "name:nor_x_preferred":[
        "Krasnyj Khleborob"
    ],
    "name:rus_x_preferred":[
        "\u041a\u0440\u0430\u0441\u043d\u044b\u0439 \u0425\u043b\u0435\u0431\u043e\u0440\u043e\u0431"
    ],
    "wof:name":"Krasnyy Khleborob",
    "wof:placetype":"locality"
},
  "geometry": {"coordinates":[96.0273,56.2897],"type":"Point"}
}