{
  "type": "Feature",
  "properties": {
    "gn:admin1_code":"46.0",
    "gn:asciiname":"Bol'shaya Taneyevka",
    "gn:country_code":"RU",
    "gn:dem":142,
    "gn:feature_class":"P",
    "gn:feature_code":"PPL",
    "gn:name":"Bol\u2019shaya Taneyevka",
    "gn:population":0,
    "gn:timezone":"Europe/Moscow",
    "iso:country":"RU",
    "name:rus_x_preferred":[
        "\u0411\u043e\u043b\u044c\u0448\u0430\u044f \u0422\u0430\u043d\u0435\u0435\u0432\u043a\u0430"
    ],
    "name:und_x_variant":[
        "Bol\u2019shaya Taneyevka",
        "\u0411\u043e\u043b\u044c\u0448\u0430\u044f \u0422\u0430\u043d\u0435\u0435\u0432\u043a\u0430"
    ],
    "wof:name":"Bol'shaya Taneyevka",
    "wof:placetype":"locality"
},
  "geometry": {"coordinates":[45.1595,54.0599],"type":"Point"}
}