{
  "type": "Feature",
  "properties": {
    "gn:admin1_code":"76",
    "gn:asciiname":"Yegnyshevka",
    "gn:country_code":"RU",
    "gn:dem":162,
    "gn:feature_class":"P",
    "gn:feature_code":"PPL",
    "gn:name":"Yegnysh\u00ebvka",
    "gn:population":0,
    "gn:timezone":"Europe/Moscow",
    "iso:country":"RU",
    "name:eng_x_preferred":[
        "Yegnysh\u00ebvka"
    ],
    "name:nor_x_preferred":[
        "Jegnysjevka"
    ],
    "name:rus_x_preferred":[
        "\u0415\u0433\u043d\u044b\u0448\u0435\u0432\u043a\u0430"
    ],
    "wof:name":"Yegnyshevka",
    "wof:placetype":"locality"
},
  "geometry": {"coordinates":[37.20209000000001,54.63609],"type":"Point"}
}