{
  "type": "Feature",
  "properties": {
    "gn:admin1_code":"47.0",
    "gn:asciiname":"Didyakovo",
    "gn:country_code":"RU",
    "gn:dem":165,
    "gn:feature_class":"P",
    "gn:feature_code":"PPL",
    "gn:name":"Didyakovo",
    "gn:population":0,
    "gn:timezone":"Europe/Moscow",
    "iso:country":"RU",
    "name:rus_x_preferred":[
        "\u0414\u0438\u0434\u044f\u043a\u043e\u0432\u043e"
    ],
    "name:und_x_variant":[
        "Dedyakovo",
        "Didyakovo",
        "\u0414\u0438\u0434\u044f\u043a\u043e\u0432\u043e"
    ],
    "wof:name":"Didyakovo",
    "wof:placetype":"locality"
},
  "geometry": {"coordinates":[37.5373,55.06551999999999],"type":"Point"}
}