{
  "type": "Feature",
  "properties": {
    "gn:admin1_code":"91",
    "gn:asciiname":"Kulizhnikovo",
    "gn:country_code":"RU",
    "gn:dem":428,
    "gn:feature_class":"P",
    "gn:feature_code":"PPL",
    "gn:name":"Kulizhnikovo",
    "gn:population":0,
    "gn:timezone":"Asia/Krasnoyarsk",
    "iso:country":"RU",
    "name:eng_x_preferred":[
        "Kulizhnikovo"
    ],
    "name:nor_x_preferred":[
        "Kulizjnikovo"
    ],
    "name:rus_x_preferred":[
        "\u041a\u0443\u043b\u0438\u0436\u043d\u0438\u043a\u043e\u0432\u043e"
    ],
    "name:und_x_variant":[
        "Kulizhnikova"
    ],
    "wof:name":"Kulizhnikovo",
    "wof:placetype":"locality"
},
  "geometry": {"coordinates":[94.6837,55.2762],"type":"Point"}
}