{
  "type": "Feature",
  "properties": {
    "gn:admin1_code":"28.0",
    "gn:asciiname":"Otsanlahti",
    "gn:country_code":"RU",
    "gn:dem":21,
    "gn:feature_class":"P",
    "gn:feature_code":"PPL",
    "gn:name":"Otsanlahti",
    "gn:population":0,
    "gn:timezone":"Europe/Moscow",
    "iso:country":"RU",
    "wof:name":"Otsanlahti",
    "wof:placetype":"locality"
},
  "geometry": {"coordinates":[29.9441,61.32028],"type":"Point"}
}