{
  "type": "Feature",
  "properties": {
    "gn:admin1_code":"69",
    "gn:asciiname":"Ptakhino",
    "gn:country_code":"RU",
    "gn:dem":220,
    "gn:feature_class":"P",
    "gn:feature_code":"PPL",
    "gn:name":"Ptakhino",
    "gn:population":0,
    "gn:timezone":"Europe/Moscow",
    "iso:country":"RU",
    "name:rus_x_preferred":[
        "\u041f\u0442\u0430\u0445\u0438\u043d\u043e"
    ],
    "wof:name":"Ptakhino",
    "wof:placetype":"locality"
},
  "geometry": {"coordinates":[32.49131,54.57626],"type":"Point"}
}