{
  "type": "Feature",
  "properties": {
    "gn:admin1_code":"62",
    "gn:asciiname":"Kupchaya",
    "gn:country_code":"RU",
    "gn:dem":184,
    "gn:feature_class":"P",
    "gn:feature_code":"PPL",
    "gn:name":"Kupchaya",
    "gn:population":0,
    "gn:timezone":"Europe/Moscow",
    "iso:country":"RU",
    "name:rus_x_preferred":[
        "\u041a\u0443\u043f\u0447\u0430\u044f"
    ],
    "wof:name":"Kupchaya",
    "wof:placetype":"locality"
},
  "geometry": {"coordinates":[38.8344,53.82544],"type":"Point"}
}