{
  "type": "Feature",
  "properties": {
    "gn:admin1_code":"1.0",
    "gn:asciiname":"Kurskiy",
    "gn:country_code":"RU",
    "gn:dem":166,
    "gn:feature_class":"P",
    "gn:feature_code":"PPL",
    "gn:name":"Kurskiy",
    "gn:population":0,
    "gn:timezone":"Europe/Moscow",
    "iso:country":"RU",
    "name:rus_x_preferred":[
        "\u041a\u0443\u0440\u0441\u043a\u0438\u0439"
    ],
    "wof:name":"Kurskiy",
    "wof:placetype":"locality"
},
  "geometry": {"coordinates":[40.36889,44.77972000000001],"type":"Point"}
}