{
  "type": "Feature",
  "properties": {
    "gn:admin1_code":"10",
    "gn:asciiname":"Gben'",
    "gn:country_code":"RU",
    "gn:dem":202,
    "gn:feature_class":"P",
    "gn:feature_code":"PPL",
    "gn:name":"Gben\u2019",
    "gn:population":0,
    "gn:timezone":"Europe/Moscow",
    "iso:country":"RU",
    "name:rus_x_preferred":[
        "\u0413\u0431\u0435\u043d\u044c"
    ],
    "name:und_x_variant":[
        "Gben\u2019",
        "\u0413\u0431\u0435\u043d\u044c"
    ],
    "wof:name":"Gben'",
    "wof:placetype":"locality"
},
  "geometry": {"coordinates":[34.66972,52.67389],"type":"Point"}
}