{
  "type": "Feature",
  "properties": {
    "gn:admin1_code":"29",
    "gn:asciiname":"Shushtulep",
    "gn:country_code":"RU",
    "gn:dem":214,
    "gn:feature_class":"P",
    "gn:feature_code":"PPL",
    "gn:name":"Shushtulep",
    "gn:population":0,
    "gn:timezone":"Asia/Novokuznetsk",
    "iso:country":"RU",
    "name:rus_x_preferred":[
        "\u0428\u0443\u0448\u0442\u0443\u043b\u0435\u043f"
    ],
    "name:und_x_variant":[
        "\u0428\u0443\u0448\u0442\u0443\u043b\u0435\u043f"
    ],
    "wof:name":"Shushtulep",
    "wof:placetype":"locality"
},
  "geometry": {"coordinates":[87.28060000000001,53.5673],"type":"Point"}
}