{
  "type": "Feature",
  "properties": {
    "gn:admin1_code":"20",
    "gn:asciiname":"Kurkat",
    "gn:country_code":"RU",
    "gn:dem":479,
    "gn:feature_class":"P",
    "gn:feature_code":"PPL",
    "gn:name":"Kurkat",
    "gn:population":0,
    "gn:timezone":"Asia/Irkutsk",
    "iso:country":"RU",
    "name:eng_x_preferred":[
        "Kurkat"
    ],
    "name:fas_x_preferred":[
        "\u06a9\u0648\u0631\u06a9\u062a"
    ],
    "name:msa_x_preferred":[
        "Kurkat"
    ],
    "name:nor_x_preferred":[
        "Kurkat"
    ],
    "name:rus_x_preferred":[
        "\u041a\u0443\u0440\u043a\u0430\u0442"
    ],
    "name:urd_x_preferred":[
        "\u06a9\u0648\u0631\u06a9\u062a"
    ],
    "wof:name":"Kurkat",
    "wof:placetype":"locality"
},
  "geometry": {"coordinates":[102.42639,53.17471999999999],"type":"Point"}
}