{
  "type": "Feature",
  "properties": {
    "gn:admin1_code":"78",
    "gn:asciiname":"Meteleva",
    "gn:country_code":"RU",
    "gn:dem":81,
    "gn:feature_class":"P",
    "gn:feature_code":"PPL",
    "gn:name":"Meteleva",
    "gn:population":0,
    "gn:timezone":"Asia/Yekaterinburg",
    "iso:country":"RU",
    "name:rus_x_preferred":[
        "\u041c\u0435\u0442\u0435\u043b\u0435\u0432\u0430"
    ],
    "wof:name":"Meteleva",
    "wof:placetype":"locality"
},
  "geometry": {"coordinates":[65.4259,57.213],"type":"Point"}
}