{
  "type": "Feature",
  "properties": {
    "gn:admin1_code":"81",
    "gn:asciiname":"Malaya Khomuter'",
    "gn:country_code":"RU",
    "gn:dem":170,
    "gn:feature_class":"P",
    "gn:feature_code":"PPL",
    "gn:name":"Malaya Khomuter\u2019",
    "gn:population":0,
    "gn:timezone":"Europe/Ulyanovsk",
    "iso:country":"RU",
    "name:eng_x_preferred":[
        "Malaya Khomuter'"
    ],
    "name:nor_x_preferred":[
        "Mal.Khomuter"
    ],
    "name:rus_x_preferred":[
        "\u041c\u0430\u043b.\u0425\u043e\u043c\u0443\u0442\u0435\u0440\u044c"
    ],
    "name:rus_x_variant":[
        "\u041c\u0430\u043b\u0430\u044f \u0425\u043e\u043c\u0443\u0442\u0435\u0440\u044c"
    ],
    "name:und_x_variant":[
        "Malaya Khomuter\u2019",
        "\u041c\u0430\u043b\u0430\u044f \u0425\u043e\u043c\u0443\u0442\u0435\u0440\u044c"
    ],
    "wof:name":"Malaya Khomuter'",
    "wof:placetype":"locality"
},
  "geometry": {"coordinates":[47.07429000000001,53.75919],"type":"Point"}
}