{
  "type": "Feature",
  "properties": {
    "gn:country":"RU",
    "gn:fcode":"ADM4",
    "gn:population":0,
    "iso:country":"RU",
    "name:und_x_variant":[
        "Lyuksemburgskiy Rayon"
    ],
    "qs:name":"Krasnogvardeyskiy Rayon",
    "qs:photos_9r":0,
    "qs:photos_sr":0,
    "qs:pop_sr":"0",
    "wof:name":"Krasnogvardeyskiy Rayon",
    "wof:placetype":"localadmin",
    "wof:population":0
},
  "geometry": {"coordinates":[53.41667,52.75],"type":"Point"}
}