{
  "type": "Feature",
  "properties": {
    "gn:admin1_code":"29",
    "gn:asciiname":"Pontryazhka",
    "gn:country_code":"RU",
    "gn:dem":252,
    "gn:feature_class":"P",
    "gn:feature_code":"PPL",
    "gn:name":"Pontryazhka",
    "gn:population":0,
    "gn:timezone":"Asia/Novokuznetsk",
    "iso:country":"RU",
    "name:rus_x_preferred":[
        "\u041f\u043e\u043d\u0442\u0440\u044f\u0436\u043a\u0430"
    ],
    "name:und_x_variant":[
        "Pantryazhka"
    ],
    "wof:name":"Pontryazhka",
    "wof:placetype":"locality"
},
  "geometry": {"coordinates":[85.5757,54.3964],"type":"Point"}
}