{
  "type": "Feature",
  "properties": {
    "gn:admin1_code":"21",
    "gn:asciiname":"Seleznevo",
    "gn:country_code":"RU",
    "gn:dem":149,
    "gn:feature_class":"P",
    "gn:feature_code":"PPL",
    "gn:name":"Selezn\u00ebvo",
    "gn:population":0,
    "gn:timezone":"Europe/Moscow",
    "iso:country":"RU",
    "name:und_x_variant":[
        "Selezen\u00ebvo",
        "Selezn\u00ebvo"
    ],
    "wof:name":"Seleznevo",
    "wof:placetype":"locality"
},
  "geometry": {"coordinates":[40.50778,57.14223000000001],"type":"Point"}
}