{
  "type": "Feature",
  "properties": {
    "gn:admin1_code":"90.0",
    "gn:asciiname":"Burunduk",
    "gn:country_code":"RU",
    "gn:dem":210,
    "gn:feature_class":"P",
    "gn:feature_code":"PPL",
    "gn:name":"Burunduk",
    "gn:population":0,
    "gn:timezone":"Asia/Yekaterinburg",
    "iso:country":"RU",
    "name:eng_x_preferred":[
        "Burunduk"
    ],
    "name:nor_x_preferred":[
        "Burunduk"
    ],
    "name:rus_x_preferred":[
        "\u0411\u0443\u0440\u0443\u043d\u0434\u0443\u043a"
    ],
    "wof:name":"Burunduk",
    "wof:placetype":"locality"
},
  "geometry": {"coordinates":[58.1144,60.79626],"type":"Point"}
}