{
  "type": "Feature",
  "properties": {
    "gn:admin1_code":"46.0",
    "gn:admin2_code":"482117",
    "gn:asciiname":"Mazilug",
    "gn:country_code":"RU",
    "gn:dem":184,
    "gn:feature_class":"P",
    "gn:feature_code":"PPL",
    "gn:name":"Mazilug",
    "gn:population":0,
    "gn:timezone":"Europe/Moscow",
    "iso:country":"RU",
    "wof:name":"Mazilug",
    "wof:placetype":"locality"
},
  "geometry": {"coordinates":[43.20819,54.08882],"type":"Point"}
}