{
  "type": "Feature",
  "properties": {
    "gn:admin1_code":"33.0",
    "gn:asciiname":"Lipichi",
    "gn:country_code":"RU",
    "gn:dem":108,
    "gn:feature_class":"P",
    "gn:feature_code":"PPL",
    "gn:name":"Lipichi",
    "gn:population":0,
    "gn:timezone":"Europe/Kirov",
    "iso:country":"RU",
    "name:rus_x_preferred":[
        "\u041b\u0438\u043f\u0438\u0447\u0438"
    ],
    "wof:name":"Lipichi",
    "wof:placetype":"locality"
},
  "geometry": {"coordinates":[48.47778,58.37371],"type":"Point"}
}