{
  "type": "Feature",
  "properties": {
    "gn:admin1_code":"81",
    "gn:asciiname":"Konnyy Oboz",
    "gn:country_code":"RU",
    "gn:dem":209,
    "gn:feature_class":"P",
    "gn:feature_code":"PPL",
    "gn:name":"Konnyy Oboz",
    "gn:population":0,
    "gn:timezone":"Europe/Ulyanovsk",
    "iso:country":"RU",
    "name:rus_x_preferred":[
        "\u041a\u043e\u043d\u043d\u044b\u0439 \u041e\u0431\u043e\u0437"
    ],
    "wof:name":"Konnyy Oboz",
    "wof:placetype":"locality"
},
  "geometry": {"coordinates":[48.3366,53.9189],"type":"Point"}
}