{
  "type": "Feature",
  "properties": {
    "gn:admin1_code":"91",
    "gn:asciiname":"Krasnyy Khutor",
    "gn:cc2":"RU",
    "gn:country_code":"RU",
    "gn:dem":305,
    "gn:feature_class":"P",
    "gn:feature_code":"PPL",
    "gn:name":"Krasnyy Khutor",
    "gn:population":0,
    "gn:timezone":"Asia/Krasnoyarsk",
    "iso:country":"RU",
    "name:eng_x_preferred":[
        "Krasnyy Khutor"
    ],
    "name:nor_x_preferred":[
        "Krasnyj Khutor"
    ],
    "name:rus_x_preferred":[
        "\u041a\u0440\u0430\u0441\u043d\u044b\u0439 \u0425\u0443\u0442\u043e\u0440"
    ],
    "name:und_x_variant":[
        "Kraxny Khutor",
        "Krasnyy Khutor"
    ],
    "wof:name":"Krasnyy Khutor",
    "wof:placetype":"locality"
},
  "geometry": {"coordinates":[91.45722000000001,53.03917],"type":"Point"}
}