{
  "type": "Feature",
  "properties": {
    "gn:admin1_code":"8",
    "gn:asciiname":"Kendektamak",
    "gn:country_code":"RU",
    "gn:dem":119,
    "gn:feature_class":"P",
    "gn:feature_code":"PPL",
    "gn:name":"Kendektamak",
    "gn:population":0,
    "gn:timezone":"Asia/Yekaterinburg",
    "iso:country":"RU",
    "name:rus_x_preferred":[
        "\u041a\u0435\u043d\u0434\u0435\u043a\u0442\u0430\u043c\u0430\u043a"
    ],
    "name:und_x_variant":[
        "Kendy-Tamak",
        "Kendektamak",
        "\u041a\u0435\u043d\u0434\u0435\u043a\u0442\u0430\u043c\u0430\u043a"
    ],
    "wof:name":"Kendektamak",
    "wof:placetype":"locality"
},
  "geometry": {"coordinates":[53.9235,54.4771],"type":"Point"}
}