{
  "type": "Feature",
  "properties": {
    "gn:admin1_code":"69",
    "gn:asciiname":"Konoplyanka",
    "gn:country_code":"RU",
    "gn:dem":194,
    "gn:feature_class":"P",
    "gn:feature_code":"PPL",
    "gn:name":"Konoplyanka",
    "gn:population":0,
    "gn:timezone":"Europe/Moscow",
    "iso:country":"RU",
    "name:rus_x_preferred":[
        "\u041a\u043e\u043d\u043e\u043f\u043b\u044f\u043d\u043a\u0430"
    ],
    "wof:name":"Konoplyanka",
    "wof:placetype":"locality"
},
  "geometry": {"coordinates":[35.07333,55.12472],"type":"Point"}
}