{
  "type": "Feature",
  "properties": {
    "gn:country":"RU",
    "gn:fcode":"PPL",
    "gn:population":0,
    "iso:country":"RU",
    "name:rus_x_preferred":[
        "\u041d\u0438\u043a\u043e\u043b\u043e-\u0423\u0440\u044e\u043f\u0438\u043d\u043e"
    ],
    "name:und_x_variant":[
        "Uryupino"
    ],
    "qs:name":"Nikol'skoye-Uryupino",
    "qs:name_adm0":"Russia",
    "qs:name_adm1":"Moscow Oblast",
    "qs:photos_9k":1,
    "qs:photos_9r":1,
    "qs:photos_all":5,
    "qs:photos_sr":0,
    "qs:placetype":"Town",
    "qs:pop_sr":"0",
    "wof:name":"Nikol'skoye-Uryupino",
    "wof:placetype":"locality",
    "wof:population":0
},
  "geometry": {"coordinates":[37.20793,55.80378],"type":"Point"}
}