{
  "type": "Feature",
  "properties": {
    "gn:admin1_code":"83",
    "gn:asciiname":"Barykino",
    "gn:country_code":"RU",
    "gn:dem":160,
    "gn:feature_class":"P",
    "gn:feature_code":"PPL",
    "gn:name":"Barykino",
    "gn:population":0,
    "gn:timezone":"Europe/Moscow",
    "iso:country":"RU",
    "name:rus_x_preferred":[
        "\u0411\u0430\u0440\u044b\u043a\u0438\u043d\u043e"
    ],
    "wof:name":"Barykino",
    "wof:placetype":"locality"
},
  "geometry": {"coordinates":[39.45876,56.29695],"type":"Point"}
}