{
  "type": "Feature",
  "properties": {
    "gn:admin1_code":"63",
    "gn:asciiname":"Balyktakh",
    "gn:country_code":"RU",
    "gn:dem":140,
    "gn:feature_class":"P",
    "gn:feature_code":"PPL",
    "gn:name":"Balyktakh",
    "gn:population":0,
    "gn:timezone":"Asia/Yakutsk",
    "iso:country":"RU",
    "name:nor_x_preferred":[
        "Balyktakh"
    ],
    "name:rus_x_preferred":[
        "\u0411\u0430\u043b\u044b\u043a\u0442\u0430\u0445"
    ],
    "wof:name":"Balyktakh",
    "wof:placetype":"locality"
},
  "geometry": {"coordinates":[130.90953000000002,62.51552],"type":"Point"}
}