{
  "type": "Feature",
  "properties": {
    "gn:admin1_code":"90.0",
    "gn:asciiname":"Chukyleva",
    "gn:country_code":"RU",
    "gn:dem":158,
    "gn:feature_class":"P",
    "gn:feature_code":"PPL",
    "gn:name":"Chukyleva",
    "gn:population":0,
    "gn:timezone":"Asia/Yekaterinburg",
    "iso:country":"RU",
    "name:rus_x_preferred":[
        "\u0427\u0443\u043a\u044b\u043b\u0435\u0432\u0430"
    ],
    "wof:name":"Chukyleva",
    "wof:placetype":"locality"
},
  "geometry": {"coordinates":[54.7205,59.1778],"type":"Point"}
}