{
  "type": "Feature",
  "properties": {
    "gn:admin1_code":"78",
    "gn:asciiname":"Tobolovo",
    "gn:country_code":"RU",
    "gn:dem":99,
    "gn:feature_class":"P",
    "gn:feature_code":"PPL",
    "gn:name":"Tobolovo",
    "gn:population":0,
    "gn:timezone":"Asia/Yekaterinburg",
    "iso:country":"RU",
    "name:eng_x_preferred":[
        "Tobolovo"
    ],
    "name:nor_x_preferred":[
        "Tobolovo"
    ],
    "name:rus_x_preferred":[
        "\u0422\u043e\u0431\u043e\u043b\u043e\u0432\u043e"
    ],
    "wof:name":"Tobolovo",
    "wof:placetype":"locality"
},
  "geometry": {"coordinates":[69.13665999999999,56.20548],"type":"Point"}
}