{
  "type": "Feature",
  "properties": {
    "gn:admin1_code":"29.0",
    "gn:asciiname":"Zenkovskiy Uklon",
    "gn:country_code":"RU",
    "gn:dem":307,
    "gn:feature_class":"P",
    "gn:feature_code":"PPL",
    "gn:name":"Zenkovskiy Uklon",
    "gn:population":0,
    "gn:timezone":"Asia/Novokuznetsk",
    "iso:country":"RU",
    "name:rus_x_preferred":[
        "\u0417\u0435\u043d\u043a\u043e\u0432\u0441\u043a\u0438\u0439 \u0423\u043a\u043b\u043e\u043d"
    ],
    "wof:name":"Zenkovskiy Uklon",
    "wof:placetype":"locality"
},
  "geometry": {"coordinates":[86.7285,53.8178],"type":"Point"}
}