{
  "type": "Feature",
  "properties": {
    "gn:admin1_code":"17",
    "gn:asciiname":"Manasaul",
    "gn:country_code":"RU",
    "gn:dem":838,
    "gn:feature_class":"P",
    "gn:feature_code":"PPL",
    "gn:name":"Manasaul",
    "gn:population":0,
    "gn:timezone":"Europe/Moscow",
    "iso:country":"RU",
    "name:eng_x_preferred":[
        "Manasaul"
    ],
    "name:nor_x_preferred":[
        "Manas-Aul"
    ],
    "name:rus_x_preferred":[
        "\u041c\u0430\u043d\u0430\u0441-\u0410\u0443\u043b"
    ],
    "name:rus_x_variant":[
        "\u041c\u0430\u043d\u0430\u0441\u0430\u0443\u043b"
    ],
    "name:und_x_variant":[
        "Manas"
    ],
    "wof:name":"Manasaul",
    "wof:placetype":"locality"
},
  "geometry": {"coordinates":[47.03827,42.75741],"type":"Point"}
}