{
  "type": "Feature",
  "properties": {
    "gn:admin1_code":"34.0",
    "gn:asciiname":"Adz'vavom",
    "gn:country_code":"RU",
    "gn:dem":55,
    "gn:feature_class":"P",
    "gn:feature_code":"PPL",
    "gn:name":"Adz\u2019vavom",
    "gn:population":0,
    "gn:timezone":"Europe/Moscow",
    "iso:country":"RU",
    "name:eng_x_preferred":[
        "Adz'vavom"
    ],
    "name:nor_x_preferred":[
        "Adzvavom"
    ],
    "name:rus_x_preferred":[
        "\u0410\u0434\u0437\u044c\u0432\u0430\u0432\u043e\u043c"
    ],
    "name:und_x_variant":[
        "Soveta",
        "Adz\u2019vavom"
    ],
    "wof:name":"Adz'vavom",
    "wof:placetype":"locality"
},
  "geometry": {"coordinates":[59.29541999999999,66.59168000000001],"type":"Point"}
}