{
  "type": "Feature",
  "properties": {
    "gn:admin1_code":"73",
    "gn:asciiname":"Verkhniy Takermen",
    "gn:country_code":"RU",
    "gn:dem":118,
    "gn:feature_class":"P",
    "gn:feature_code":"PPL",
    "gn:name":"Verkhniy Takermen",
    "gn:population":0,
    "gn:timezone":"Europe/Moscow",
    "iso:country":"RU",
    "name:eng_x_preferred":[
        "Verkhniy Takermen"
    ],
    "name:nor_x_preferred":[
        "Verkhnij Takermen"
    ],
    "name:rus_x_preferred":[
        "\u0412\u0435\u0440\u0445\u043d\u0438\u0439 \u0422\u0430\u043a\u0435\u0440\u043c\u0435\u043d"
    ],
    "name:und_x_variant":[
        "Verkhniy Takirmen",
        "Verkhniy Takermen",
        "\u0412\u0435\u0440\u0445\u043d\u0438\u0439 \u0422\u0430\u043a\u0435\u0440\u043c\u0435\u043d"
    ],
    "wof:name":"Verkhniy Takermen",
    "wof:placetype":"locality"
},
  "geometry": {"coordinates":[52.69321,55.65305],"type":"Point"}
}