{
  "type": "Feature",
  "properties": {
    "gn:admin1_code":"61",
    "gn:asciiname":"Karpovskiy",
    "gn:country_code":"RU",
    "gn:dem":43,
    "gn:feature_class":"P",
    "gn:feature_code":"PPL",
    "gn:name":"Karpovskiy",
    "gn:population":0,
    "gn:timezone":"Europe/Moscow",
    "iso:country":"RU",
    "name:rus_x_preferred":[
        "\u041a\u0430\u0440\u043f\u043e\u0432\u0441\u043a\u0438\u0439"
    ],
    "name:und_x_variant":[
        "Karpovskaya",
        "Karpovskiy",
        "\u041a\u0430\u0440\u043f\u043e\u0432\u0441\u043a\u0438\u0439"
    ],
    "wof:name":"Karpovskiy",
    "wof:placetype":"locality"
},
  "geometry": {"coordinates":[42.20089,48.00695],"type":"Point"}
}