{
  "type": "Feature",
  "properties": {
    "gn:admin1_code":"45.0",
    "gn:asciiname":"Arzebelyak",
    "gn:country_code":"RU",
    "gn:dem":58,
    "gn:feature_class":"P",
    "gn:feature_code":"PPL",
    "gn:name":"Arzebelyak",
    "gn:population":0,
    "gn:timezone":"Europe/Moscow",
    "iso:country":"RU",
    "name:nor_x_preferred":[
        "Arzebeljak"
    ],
    "name:rus_x_preferred":[
        "\u0410\u0440\u0437\u0435\u0431\u0435\u043b\u044f\u043a"
    ],
    "name:und_x_variant":[
        "Arza-Belyak",
        "Arzebelyak"
    ],
    "wof:name":"Arzebelyak",
    "wof:placetype":"locality"
},
  "geometry": {"coordinates":[48.00056,56.07111],"type":"Point"}
}