{
  "type": "Feature",
  "properties": {
    "gn:admin1_code":"4",
    "gn:asciiname":"Kruzhalo",
    "gn:country_code":"RU",
    "gn:dem":258,
    "gn:feature_class":"P",
    "gn:feature_code":"PPL",
    "gn:name":"Kruzhalo",
    "gn:population":0,
    "gn:timezone":"Asia/Barnaul",
    "iso:country":"RU",
    "name:rus_x_preferred":[
        "\u041a\u0440\u0443\u0436\u0430\u043b\u043e"
    ],
    "wof:name":"Kruzhalo",
    "wof:placetype":"locality"
},
  "geometry": {"coordinates":[85.76609999999999,53.7615],"type":"Point"}
}