{
  "type": "Feature",
  "properties": {
    "gn:admin1_code":"88",
    "gn:asciiname":"Yudino",
    "gn:country_code":"RU",
    "gn:dem":137,
    "gn:feature_class":"P",
    "gn:feature_code":"PPL",
    "gn:name":"Yudino",
    "gn:population":0,
    "gn:timezone":"Europe/Moscow",
    "iso:country":"RU",
    "name:eng_x_preferred":[
        "Yudino"
    ],
    "name:nor_x_preferred":[
        "Judino"
    ],
    "name:rus_x_preferred":[
        "\u042e\u0434\u0438\u043d\u043e"
    ],
    "wof:name":"Yudino",
    "wof:placetype":"locality"
},
  "geometry": {"coordinates":[39.30173,58.70829000000001],"type":"Point"}
}