{
  "type": "Feature",
  "properties": {
    "gn:admin1_code":"88",
    "gn:asciiname":"Gridenino",
    "gn:country_code":"RU",
    "gn:dem":129,
    "gn:feature_class":"P",
    "gn:feature_code":"PPL",
    "gn:name":"Gridenino",
    "gn:population":0,
    "gn:timezone":"Europe/Moscow",
    "iso:country":"RU",
    "name:rus_x_preferred":[
        "\u0413\u0440\u0438\u0434\u0435\u043d\u0438\u043d\u043e"
    ],
    "name:und_x_variant":[
        "Gredenino",
        "Gridenino",
        "\u0413\u0440\u0438\u0434\u0435\u043d\u0438\u043d\u043e"
    ],
    "wof:name":"Gridenino",
    "wof:placetype":"locality"
},
  "geometry": {"coordinates":[40.53589,58.06785],"type":"Point"}
}