{
  "type": "Feature",
  "properties": {
    "gn:admin1_code":"33.0",
    "gn:asciiname":"Bol'shoy Volmanovskiy",
    "gn:country_code":"RU",
    "gn:dem":163,
    "gn:feature_class":"P",
    "gn:feature_code":"PPL",
    "gn:name":"Bol'shoy Volmanovskiy",
    "gn:population":0,
    "gn:timezone":"Europe/Kirov",
    "iso:country":"RU",
    "wof:name":"Bol'shoy Volmanovskiy",
    "wof:placetype":"locality"
},
  "geometry": {"coordinates":[47.43333,59.43333000000001],"type":"Point"}
}