{
  "type": "Feature",
  "properties": {
    "gn:admin1_code":"61",
    "gn:asciiname":"Rusichi",
    "gn:country_code":"RU",
    "gn:dem":70,
    "gn:feature_class":"P",
    "gn:feature_code":"PPL",
    "gn:name":"Rusichi",
    "gn:population":0,
    "gn:timezone":"Europe/Moscow",
    "iso:country":"RU",
    "name:rus_x_preferred":[
        "\u0420\u0443\u0441\u0438\u0447\u0438"
    ],
    "wof:name":"Rusichi",
    "wof:placetype":"locality"
},
  "geometry": {"coordinates":[40.5885,48.2347],"type":"Point"}
}