{
  "type": "Feature",
  "properties": {
    "gn:admin1_code":"75",
    "gn:asciiname":"Kuchumovka",
    "gn:cc2":"RU",
    "gn:country_code":"RU",
    "gn:dem":113,
    "gn:feature_class":"P",
    "gn:feature_code":"PPL",
    "gn:name":"Kuchumovka",
    "gn:population":0,
    "gn:timezone":"Asia/Tomsk",
    "iso:country":"RU",
    "name:rus_x_preferred":[
        "\u041a\u0443\u0447\u0443\u043c\u043e\u0432\u043a\u0430"
    ],
    "name:und_x_variant":[
        "Kuchumova",
        "Kuchumovka",
        "\u041a\u0443\u0447\u0443\u043c\u043e\u0432\u043a\u0430"
    ],
    "wof:name":"Kuchumovka",
    "wof:placetype":"locality"
},
  "geometry": {"coordinates":[80.90000000000001,56.86666999999999],"type":"Point"}
}