{
  "type": "Feature",
  "properties": {
    "gn:admin1_code":"33",
    "gn:asciiname":"Kostenki",
    "gn:country_code":"RU",
    "gn:dem":119,
    "gn:feature_class":"P",
    "gn:feature_code":"PPL",
    "gn:name":"Kostenki",
    "gn:population":0,
    "gn:timezone":"Europe/Kirov",
    "iso:country":"RU",
    "name:rus_x_preferred":[
        "\u041a\u043e\u0441\u0442\u0435\u043d\u043a\u0438"
    ],
    "wof:name":"Kostenki",
    "wof:placetype":"locality"
},
  "geometry": {"coordinates":[48.29444,59.04221999999999],"type":"Point"}
}