{
  "type": "Feature",
  "properties": {
    "gn:admin1_code":"77",
    "gn:asciiname":"Lisovo",
    "gn:country_code":"RU",
    "gn:dem":275,
    "gn:feature_class":"P",
    "gn:feature_code":"PPL",
    "gn:name":"Lisovo",
    "gn:population":0,
    "gn:timezone":"Europe/Moscow",
    "iso:country":"RU",
    "name:bul_x_preferred":[
        "\u041b\u0438\u0441\u043e\u0432\u043e"
    ],
    "name:eng_x_preferred":[
        "Lisovo"
    ],
    "name:fas_x_preferred":[
        "\u0644\u06cc\u0633\u0648\u0648\u0648"
    ],
    "name:kaz_x_preferred":[
        "\u041b\u0438\u0441\u043e\u0432\u043e"
    ],
    "name:nor_x_preferred":[
        "Lisovo"
    ],
    "name:pol_x_preferred":[
        "Lisowo"
    ],
    "name:ron_x_preferred":[
        "Lisovo"
    ],
    "name:rus_x_preferred":[
        "\u041b\u0438\u0441\u043e\u0432\u043e"
    ],
    "name:ukr_x_preferred":[
        "\u041b\u0438\u0441\u043e\u0432\u043e"
    ],
    "name:und_x_variant":[
        "Lisevo",
        "\u041b\u0438\u0441\u043e\u0432\u043e",
        "Lisovo"
    ],
    "wof:name":"Lisovo",
    "wof:placetype":"locality"
},
  "geometry": {"coordinates":[33.95587,56.96744],"type":"Point"}
}