{
  "type": "Feature",
  "properties": {
    "gn:admin1_code":"05",
    "gn:asciiname":"Bakhirevo",
    "gn:country_code":"RU",
    "gn:dem":132,
    "gn:feature_class":"P",
    "gn:feature_code":"PPL",
    "gn:name":"Bakhir\u00ebvo",
    "gn:population":0,
    "gn:timezone":"Asia/Yakutsk",
    "iso:country":"RU",
    "name:eng_x_preferred":[
        "Bakhir\u00ebvo"
    ],
    "name:rus_x_preferred":[
        "\u0411\u0430\u0445\u0438\u0440\u0435\u0432\u043e"
    ],
    "name:rus_x_variant":[
        "\u0411\u0430\u0445\u0438\u0440\u0451\u0432\u043e"
    ],
    "name:und_x_variant":[
        "Bakhirevka",
        "Bakhireva"
    ],
    "wof:name":"Bakhirevo",
    "wof:placetype":"locality"
},
  "geometry": {"coordinates":[130.00124,50.04013],"type":"Point"}
}