{
  "type": "Feature",
  "properties": {
    "gn:admin1_code":"77.0",
    "gn:asciiname":"Bridino",
    "gn:country_code":"RU",
    "gn:dem":190,
    "gn:feature_class":"P",
    "gn:feature_code":"PPL",
    "gn:name":"Bridino",
    "gn:population":0,
    "gn:timezone":"Europe/Moscow",
    "iso:country":"RU",
    "name:eng_x_preferred":[
        "Bridino"
    ],
    "name:nor_x_preferred":[
        "Bridino"
    ],
    "name:rus_x_preferred":[
        "\u0411\u0440\u0438\u0434\u0438\u043d\u043e"
    ],
    "name:und_x_variant":[
        "\u0411\u0440\u0438\u0434\u0438\u043d\u043e",
        "Bridino"
    ],
    "wof:name":"Bridino",
    "wof:placetype":"locality"
},
  "geometry": {"coordinates":[31.73333,56.43333000000001],"type":"Point"}
}