{
  "type": "Feature",
  "properties": {
    "gn:admin1_code":"56",
    "gn:asciiname":"Vyazki",
    "gn:country_code":"RU",
    "gn:dem":156,
    "gn:feature_class":"P",
    "gn:feature_code":"PPL",
    "gn:name":"Vyazki",
    "gn:population":0,
    "gn:timezone":"Europe/Moscow",
    "iso:country":"RU",
    "name:und_x_variant":[
        "Vyazhovskiy",
        "Vyazki"
    ],
    "wof:name":"Vyazki",
    "wof:placetype":"locality"
},
  "geometry": {"coordinates":[36.15708,53.06983],"type":"Point"}
}