{
  "type": "Feature",
  "properties": {
    "gn:admin1_code":"83",
    "gn:asciiname":"Malyshkino",
    "gn:country_code":"RU",
    "gn:dem":110,
    "gn:feature_class":"P",
    "gn:feature_code":"PPL",
    "gn:name":"Malyshkino",
    "gn:population":0,
    "gn:timezone":"Europe/Moscow",
    "iso:country":"RU",
    "name:eng_x_preferred":[
        "Malyshkino"
    ],
    "name:nor_x_preferred":[
        "Velikodvorskij"
    ],
    "name:rus_x_preferred":[
        "\u0412\u0435\u043b\u0438\u043a\u043e\u0434\u0432\u043e\u0440\u0441\u043a\u0438\u0439"
    ],
    "name:rus_x_variant":[
        "\u041c\u0430\u043b\u044b\u0448\u043a\u0438\u043d\u043e"
    ],
    "name:und_x_variant":[
        "Velikodvor\u2019ye"
    ],
    "wof:name":"Malyshkino",
    "wof:placetype":"locality"
},
  "geometry": {"coordinates":[40.71273,55.23497],"type":"Point"}
}