{
  "type": "Feature",
  "properties": {
    "gn:admin1_code":"33",
    "gn:asciiname":"Gorevshchina",
    "gn:country_code":"RU",
    "gn:dem":176,
    "gn:feature_class":"P",
    "gn:feature_code":"PPL",
    "gn:name":"Gorevshchina",
    "gn:population":0,
    "gn:timezone":"Europe/Kirov",
    "iso:country":"RU",
    "name:rus_x_preferred":[
        "\u0413\u043e\u0440\u0435\u0432\u0449\u0438\u043d\u0430"
    ],
    "name:und_x_variant":[
        "\u0413\u043e\u0440\u0435\u0432\u0449\u0438\u043d\u0430"
    ],
    "wof:name":"Gorevshchina",
    "wof:placetype":"locality"
},
  "geometry": {"coordinates":[48.45111,59.13833],"type":"Point"}
}