{
  "type": "Feature",
  "properties": {
    "gn:admin1_code":"77",
    "gn:asciiname":"Maykovo",
    "gn:country_code":"RU",
    "gn:dem":164,
    "gn:feature_class":"P",
    "gn:feature_code":"PPL",
    "gn:name":"Maykovo",
    "gn:population":0,
    "gn:timezone":"Europe/Moscow",
    "iso:country":"RU",
    "name:rus_x_preferred":[
        "\u041c\u0430\u0439\u043a\u043e\u0432\u043e"
    ],
    "name:und_x_variant":[
        "\u041c\u0430\u0439\u043a\u043e\u0432\u043e"
    ],
    "wof:name":"Maykovo",
    "wof:placetype":"locality"
},
  "geometry": {"coordinates":[36.7168,57.1972],"type":"Point"}
}