{
  "type": "Feature",
  "properties": {
    "gn:admin1_code":"52",
    "gn:asciiname":"Nikolayevka",
    "gn:country_code":"RU",
    "gn:dem":69,
    "gn:feature_class":"P",
    "gn:feature_code":"PPL",
    "gn:name":"Nikolayevka",
    "gn:population":0,
    "gn:timezone":"Europe/Moscow",
    "iso:country":"RU",
    "wof:name":"Nikolayevka",
    "wof:placetype":"locality"
},
  "geometry": {"coordinates":[33.42992,58.8358],"type":"Point"}
}