{
  "type": "Feature",
  "properties": {
    "gn:country":"RU",
    "gn:fcode":"PPL",
    "gn:pop":0,
    "iso:country":"RU",
    "name:rus_x_preferred":[
        "\u041c\u0430\u0440\u044c\u0438\u043d\u0430 \u0420\u043e\u0449\u0430"
    ],
    "name:unk_x_variant":[
        "Mar\u2019ina Roshcha"
    ],
    "qs:name":"Mar'ina Roshcha",
    "qs:name_adm0":"Russia",
    "qs:name_adm1":"Krasnodar Krai",
    "qs:photos":45,
    "qs:photos_1k":9,
    "qs:photos_9k":1,
    "qs:photos_9r":2,
    "qs:photos_all":45,
    "qs:photos_sr":2,
    "qs:placetype":"Town",
    "qs:pop_sr":"0",
    "wof:name":"Mar'ina Roshcha",
    "wof:placetype":"locality",
    "wof:population":0
},
  "geometry": {"coordinates":[38.0324,44.6194],"type":"Point"}
}