{
  "type": "Feature",
  "properties": {
    "gn:admin1_code":"37",
    "gn:asciiname":"Gashevo",
    "gn:country_code":"RU",
    "gn:dem":159,
    "gn:feature_class":"P",
    "gn:feature_code":"PPL",
    "gn:name":"Gashevo",
    "gn:population":0,
    "gn:timezone":"Europe/Moscow",
    "iso:country":"RU",
    "name:rus_x_preferred":[
        "\u0413\u0430\u0448\u0435\u0432\u043e"
    ],
    "wof:name":"Gashevo",
    "wof:placetype":"locality"
},
  "geometry": {"coordinates":[43.1301,58.5521],"type":"Point"}
}