{
  "type": "Feature",
  "properties": {
    "gn:admin1_code":"8.0",
    "gn:asciiname":"Baimovo",
    "gn:country_code":"RU",
    "gn:dem":408,
    "gn:feature_class":"P",
    "gn:feature_code":"PPL",
    "gn:name":"Baimovo",
    "gn:population":0,
    "gn:timezone":"Asia/Yekaterinburg",
    "iso:country":"RU",
    "name:eng_x_preferred":[
        "Baimovo"
    ],
    "name:nor_x_preferred":[
        "Baimovo"
    ],
    "name:rus_x_preferred":[
        "\u0411\u0430\u0438\u043c\u043e\u0432\u043e"
    ],
    "name:und_x_variant":[
        "Baymova",
        "Bailova",
        "\u0411\u0430\u0438\u043c\u043e\u0432\u043e",
        "Baimovo"
    ],
    "wof:name":"Baimovo",
    "wof:placetype":"locality"
},
  "geometry": {"coordinates":[58.84472,53.72944],"type":"Point"}
}