{
  "type": "Feature",
  "properties": {
    "gn:admin1_code":"61",
    "gn:asciiname":"Karasenko",
    "gn:country_code":"RU",
    "gn:dem":84,
    "gn:feature_class":"P",
    "gn:feature_code":"PPL",
    "gn:name":"Karasenko",
    "gn:population":0,
    "gn:timezone":"Europe/Moscow",
    "iso:country":"RU",
    "name:rus_x_preferred":[
        "\u041a\u0430\u0440\u0430\u0441\u0435\u043d\u043a\u043e"
    ],
    "name:und_x_variant":[
        "\u041a\u0430\u0440\u0430\u0441\u0435\u043d\u043a\u043e"
    ],
    "wof:name":"Karasenko",
    "wof:placetype":"locality"
},
  "geometry": {"coordinates":[38.73333,47.46667],"type":"Point"}
}