{
  "type": "Feature",
  "properties": {
    "gn:admin1_code":"84",
    "gn:asciiname":"Laptev",
    "gn:country_code":"RU",
    "gn:dem":160,
    "gn:feature_class":"P",
    "gn:feature_code":"PPL",
    "gn:name":"Laptev",
    "gn:population":0,
    "gn:timezone":"Europe/Volgograd",
    "iso:country":"RU",
    "name:bel_x_preferred":[
        "\u041b\u0430\u043f\u0446\u0435\u045e"
    ],
    "name:deu_x_preferred":[
        "Laptew"
    ],
    "name:fra_x_preferred":[
        "Laptev"
    ],
    "name:heb_x_preferred":[
        "\u05dc\u05d0\u05e4\u05d8\u05d1"
    ],
    "name:hun_x_preferred":[
        "Laptyev"
    ],
    "name:rus_x_preferred":[
        "\u041b\u0430\u043f\u0442\u0435\u0432"
    ],
    "name:swe_x_preferred":[
        "Laptev"
    ],
    "name:ukr_x_preferred":[
        "\u041b\u0430\u043f\u0442\u0454\u0432"
    ],
    "name:und_x_variant":[
        "\u041b\u0430\u043f\u0442\u0435\u0432"
    ],
    "wof:name":"Laptev",
    "wof:placetype":"locality"
},
  "geometry": {"coordinates":[43.66667,49.06667],"type":"Point"}
}