{
  "type": "Feature",
  "properties": {
    "gn:admin1_code":"7",
    "gn:asciiname":"Volzhskiy",
    "gn:country_code":"RU",
    "gn:dem":-23,
    "gn:feature_class":"P",
    "gn:feature_code":"PPL",
    "gn:name":"Volzhskiy",
    "gn:population":0,
    "gn:timezone":"Europe/Astrakhan",
    "iso:country":"RU",
    "name:eng_x_preferred":[
        "Volzhskiy"
    ],
    "name:nor_x_preferred":[
        "Volzjskij"
    ],
    "name:rus_x_preferred":[
        "\u0412\u043e\u043b\u0436\u0441\u043a\u0438\u0439"
    ],
    "name:und_x_variant":[
        "Schambai",
        "Shambay",
        "\u0412\u043e\u043b\u0436\u0441\u043a\u0438\u0439",
        "Volzhskiy"
    ],
    "wof:name":"Volzhskiy",
    "wof:placetype":"locality"
},
  "geometry": {"coordinates":[47.5519,46.9685],"type":"Point"}
}