{
  "type": "Feature",
  "properties": {
    "gn:admin1_code":"4",
    "gn:asciiname":"Ust'-Volchikha",
    "gn:country_code":"RU",
    "gn:dem":181,
    "gn:feature_class":"P",
    "gn:feature_code":"PPL",
    "gn:name":"Ust\u2019-Volchikha",
    "gn:population":0,
    "gn:timezone":"Asia/Barnaul",
    "iso:country":"RU",
    "name:eng_x_preferred":[
        "Ust'-Volchikha"
    ],
    "name:nor_x_preferred":[
        "Ust-Voltsjikha"
    ],
    "name:rus_x_preferred":[
        "\u0423\u0441\u0442\u044c-\u0412\u043e\u043b\u0447\u0438\u0445\u0430"
    ],
    "name:und_x_variant":[
        "Ust\u2019-Volchikha"
    ],
    "wof:name":"Ust'-Volchikha",
    "wof:placetype":"locality"
},
  "geometry": {"coordinates":[80.25409999999999,51.8949],"type":"Point"}
}