{
  "type": "Feature",
  "properties": {
    "gn:admin1_code":"52",
    "gn:asciiname":"Malaya Lukovnitsa",
    "gn:country_code":"RU",
    "gn:dem":36,
    "gn:feature_class":"P",
    "gn:feature_code":"PPL",
    "gn:name":"Malaya Lukovnitsa",
    "gn:population":0,
    "gn:timezone":"Europe/Moscow",
    "iso:country":"RU",
    "name:rus_x_preferred":[
        "\u041c\u0430\u043b\u0430\u044f \u041b\u0443\u043a\u043e\u0432\u043d\u0438\u0446\u0430"
    ],
    "wof:name":"Malaya Lukovnitsa",
    "wof:placetype":"locality"
},
  "geometry": {"coordinates":[31.06667,58.51667],"type":"Point"}
}