{
  "type": "Feature",
  "properties": {
    "gn:admin1_code":"86",
    "gn:asciiname":"Il'ich",
    "gn:country_code":"RU",
    "gn:dem":142,
    "gn:feature_class":"P",
    "gn:feature_code":"PPL",
    "gn:name":"Il\u2019ich",
    "gn:population":0,
    "gn:timezone":"Europe/Moscow",
    "iso:country":"RU",
    "name:rus_x_preferred":[
        "\u0418\u043b\u044c\u0438\u0447"
    ],
    "name:und_x_variant":[
        "Il\u2019ich"
    ],
    "wof:name":"Il'ich",
    "wof:placetype":"locality"
},
  "geometry": {"coordinates":[39.70031,51.21442],"type":"Point"}
}