{
  "type": "Feature",
  "properties": {
    "gn:admin1_code":"45.0",
    "gn:asciiname":"Nagorino",
    "gn:country_code":"RU",
    "gn:dem":134,
    "gn:feature_class":"P",
    "gn:feature_code":"PPL",
    "gn:name":"Nagorino",
    "gn:population":0,
    "gn:timezone":"Europe/Moscow",
    "iso:country":"RU",
    "name:rus_x_preferred":[
        "\u041d\u0430\u0433\u043e\u0440\u0438\u043d\u043e"
    ],
    "name:und_x_variant":[
        "\u041d\u0430\u0433\u043e\u0440\u0438\u043d\u043e"
    ],
    "wof:name":"Nagorino",
    "wof:placetype":"locality"
},
  "geometry": {"coordinates":[48.65639,56.06694],"type":"Point"}
}