{
  "type": "Feature",
  "properties": {
    "gn:admin1_code":"77",
    "gn:asciiname":"Kun'ye",
    "gn:country_code":"RU",
    "gn:dem":134,
    "gn:feature_class":"P",
    "gn:feature_code":"PPL",
    "gn:name":"Kun\u2019ye",
    "gn:population":0,
    "gn:timezone":"Europe/Moscow",
    "iso:country":"RU",
    "name:rus_x_preferred":[
        "\u041a\u0443\u043d\u044c\u0435"
    ],
    "name:und_x_variant":[
        "Kun\u2019ye",
        "\u041a\u0443\u043d\u044c\u0435"
    ],
    "wof:name":"Kun'ye",
    "wof:placetype":"locality"
},
  "geometry": {"coordinates":[36.2881,57.9712],"type":"Point"}
}