{
  "type": "Feature",
  "properties": {
    "gn:admin1_code":"44",
    "gn:asciiname":"Brokhova",
    "gn:country_code":"RU",
    "gn:dem":7,
    "gn:feature_class":"P",
    "gn:feature_code":"PPL",
    "gn:name":"Brokhova",
    "gn:population":0,
    "gn:timezone":"Asia/Magadan",
    "iso:country":"RU",
    "name:eng_x_preferred":[
        "Brokhova"
    ],
    "name:nor_x_preferred":[
        "Brokhovo"
    ],
    "name:rus_x_preferred":[
        "\u0411\u0440\u043e\u0445\u043e\u0432\u043e"
    ],
    "name:rus_x_variant":[
        "\u0411\u0440\u043e\u0445\u043e\u0432\u0430"
    ],
    "wof:name":"Brokhova",
    "wof:placetype":"locality"
},
  "geometry": {"coordinates":[154.30024,59.63822],"type":"Point"}
}