{
  "type": "Feature",
  "properties": {
    "gn:admin1_code":"53",
    "gn:asciiname":"Sedova Zaimka",
    "gn:country_code":"RU",
    "gn:dem":119,
    "gn:feature_class":"P",
    "gn:feature_code":"PPL",
    "gn:name":"Sedova Zaimka",
    "gn:population":0,
    "gn:timezone":"Asia/Novosibirsk",
    "iso:country":"RU",
    "name:rus_x_preferred":[
        "\u0421\u0435\u0434\u043e\u0432\u0430 \u0417\u0430\u0438\u043c\u043a\u0430"
    ],
    "name:und_x_variant":[
        "Sedovo",
        "Sedova Zaimka",
        "\u0421\u0435\u0434\u043e\u0432\u0430 \u0417\u0430\u0438\u043c\u043a\u0430",
        "Dachi Sedovo"
    ],
    "wof:name":"Sedova Zaimka",
    "wof:placetype":"locality"
},
  "geometry": {"coordinates":[82.85209999999999,55.3659],"type":"Point"}
}