{
  "type": "Feature",
  "properties": {
    "gn:admin1_code":"4",
    "gn:asciiname":"Toptushka",
    "gn:country_code":"RU",
    "gn:dem":374,
    "gn:feature_class":"P",
    "gn:feature_code":"PPL",
    "gn:name":"Toptushka",
    "gn:population":0,
    "gn:timezone":"Asia/Barnaul",
    "iso:country":"RU",
    "name:ceb_x_preferred":[
        "Toptushka"
    ],
    "name:che_x_preferred":[
        "\u0422\u043e\u043f\u0442\u0443\u0448\u043a\u0430"
    ],
    "name:hye_x_preferred":[
        "\u054f\u0578\u057a\u057f\u0578\u0582\u0577\u056f\u0561"
    ],
    "name:rus_x_preferred":[
        "\u0422\u043e\u043f\u0442\u0443\u0448\u043a\u0430"
    ],
    "wof:name":"Toptushka",
    "wof:placetype":"locality"
},
  "geometry": {"coordinates":[86.58333,53.46666999999999],"type":"Point"}
}