{
  "type": "Feature",
  "properties": {
    "gn:admin1_code":"62",
    "gn:asciiname":"Shigayevo",
    "gn:country_code":"RU",
    "gn:dem":111,
    "gn:feature_class":"P",
    "gn:feature_code":"PPL",
    "gn:name":"Shigayevo",
    "gn:population":0,
    "gn:timezone":"Europe/Moscow",
    "iso:country":"RU",
    "name:rus_x_preferred":[
        "\u0428\u0438\u0433\u0430\u0435\u0432\u043e"
    ],
    "name:und_x_variant":[
        "\u0428\u0438\u0433\u0430\u0435\u0432\u043e"
    ],
    "wof:name":"Shigayevo",
    "wof:placetype":"locality"
},
  "geometry": {"coordinates":[41.31667,54.15],"type":"Point"}
}