{
  "type": "Feature",
  "properties": {
    "gn:admin1_code":"62",
    "gn:asciiname":"Shigayevo",
    "gn:country_code":"RU",
    "gn:dem":111,
    "gn:feature_class":"P",
    "gn:feature_code":"PPL",
    "gn:name":"Shigayevo",
    "gn:population":0,
    "gn:timezone":"Europe/Moscow",
    "iso:country":"RU",
    "name:bak_x_preferred":[
        "\u0428\u044b\u0493\u0430\u0439"
    ],
    "name:che_x_preferred":[
        "\u0428\u0438\u0433\u0430\u0435\u0432\u043e"
    ],
    "name:hye_x_preferred":[
        "\u0547\u056b\u0563\u0561\u0587\u0578"
    ],
    "name:kat_x_preferred":[
        "\u10e8\u10d8\u10d2\u10d0\u10d4\u10d5\u10dd"
    ],
    "name:kaz_x_preferred":[
        "\u0428\u0438\u0433\u0430"
    ],
    "name:rus_x_preferred":[
        "\u0428\u0438\u0433\u0430\u0435\u0432\u043e"
    ],
    "name:tat_x_preferred":[
        "\u0428\u044b\u0433\u0430\u0439"
    ],
    "name:ukr_x_preferred":[
        "\u0428\u0438\u0433\u0430\u0454\u0432\u043e"
    ],
    "wof:name":"Shigayevo",
    "wof:placetype":"locality"
},
  "geometry": {"coordinates":[41.31667,54.15],"type":"Point"}
}