{
  "type": "Feature",
  "properties": {
    "gn:admin1_code":"38",
    "gn:asciiname":"Plavstroy",
    "gn:country_code":"RU",
    "gn:dem":4,
    "gn:feature_class":"P",
    "gn:feature_code":"PPL",
    "gn:name":"Plavstroy",
    "gn:population":0,
    "gn:timezone":"Europe/Moscow",
    "iso:country":"RU",
    "name:rus_x_preferred":[
        "\u041f\u043b\u0430\u0432\u0441\u0442\u0440\u043e\u0439"
    ],
    "wof:name":"Plavstroy",
    "wof:placetype":"locality"
},
  "geometry": {"coordinates":[38.01667,45.33333],"type":"Point"}
}