{
  "type": "Feature",
  "properties": {
    "gn:admin1_code":"51.0",
    "gn:asciiname":"Skipino",
    "gn:country_code":"RU",
    "gn:dem":95,
    "gn:feature_class":"P",
    "gn:feature_code":"PPL",
    "gn:name":"Skipino",
    "gn:population":0,
    "gn:timezone":"Europe/Moscow",
    "iso:country":"RU",
    "name:nor_x_preferred":[
        "Skipino"
    ],
    "name:rus_x_preferred":[
        "\u0421\u043a\u0438\u043f\u0438\u043d\u043e"
    ],
    "wof:name":"Skipino",
    "wof:placetype":"locality"
},
  "geometry": {"coordinates":[43.37378,56.71496],"type":"Point"}
}