{
  "type": "Feature",
  "properties": {
    "gn:admin1_code":"16.0",
    "gn:asciiname":"Aleshkino",
    "gn:country_code":"RU",
    "gn:dem":151,
    "gn:feature_class":"P",
    "gn:feature_code":"PPL",
    "gn:name":"Al\u00ebshkino",
    "gn:population":0,
    "gn:timezone":"Europe/Moscow",
    "iso:country":"RU",
    "name:nor_x_preferred":[
        "Aljosjkino"
    ],
    "name:rus_x_preferred":[
        "\u0410\u043b\u0451\u0448\u043a\u0438\u043d\u043e"
    ],
    "name:und_x_variant":[
        "Al\u00ebshkino"
    ],
    "wof:name":"Aleshkino",
    "wof:placetype":"locality"
},
  "geometry": {"coordinates":[46.39137,55.82571],"type":"Point"}
}