{
  "type": "Feature",
  "properties": {
    "gn:admin1_code":"41",
    "gn:asciiname":"Novyy Poselok",
    "gn:cc2":"RU",
    "gn:country_code":"RU",
    "gn:dem":183,
    "gn:feature_class":"P",
    "gn:feature_code":"PPL",
    "gn:name":"Novyy Pos\u00eblok",
    "gn:population":0,
    "gn:timezone":"Europe/Moscow",
    "iso:country":"RU",
    "name:rus_x_preferred":[
        "\u041d\u043e\u0432\u044b\u0439 \u041f\u043e\u0441\u0451\u043b\u043e\u043a"
    ],
    "name:und_x_variant":[
        "Novy Poselok",
        "Novyy Pos\u00eblok"
    ],
    "wof:name":"Novyy Poselok",
    "wof:placetype":"locality"
},
  "geometry": {"coordinates":[37.05,51.88333],"type":"Point"}
}