{
  "type": "Feature",
  "properties": {
    "gn:admin1_code":"57.0",
    "gn:asciiname":"Lyubovka",
    "gn:country_code":"RU",
    "gn:dem":161,
    "gn:feature_class":"P",
    "gn:feature_code":"PPL",
    "gn:name":"Lyubovka",
    "gn:population":0,
    "gn:timezone":"Europe/Moscow",
    "iso:country":"RU",
    "name:rus_x_preferred":[
        "\u041b\u044e\u0431\u043e\u0432\u043a\u0430"
    ],
    "wof:name":"Lyubovka",
    "wof:placetype":"locality"
},
  "geometry": {"coordinates":[44.4141,52.7469],"type":"Point"}
}