{
  "type": "Feature",
  "properties": {
    "gn:admin1_code":"77",
    "gn:asciiname":"Uzgovo",
    "gn:country_code":"RU",
    "gn:dem":213,
    "gn:feature_class":"P",
    "gn:feature_code":"PPL",
    "gn:name":"Uzgovo",
    "gn:population":0,
    "gn:timezone":"Europe/Moscow",
    "iso:country":"RU",
    "name:rus_x_preferred":[
        "\u0423\u0437\u0433\u043e\u0432\u043e"
    ],
    "wof:name":"Uzgovo",
    "wof:placetype":"locality"
},
  "geometry": {"coordinates":[32.6027,57.214],"type":"Point"}
}