{
  "type": "Feature",
  "properties": {
    "gn:admin1_code":"65.0",
    "gn:asciiname":"Chemerichnyy",
    "gn:country_code":"RU",
    "gn:dem":42,
    "gn:feature_class":"P",
    "gn:feature_code":"PPL",
    "gn:name":"Chemerichnyy",
    "gn:population":0,
    "gn:timezone":"Europe/Samara",
    "iso:country":"RU",
    "name:rus_x_preferred":[
        "\u0427\u0435\u043c\u0435\u0440\u0438\u0447\u043d\u044b\u0439"
    ],
    "name:und_x_variant":[
        "Chemerichny",
        "Chemerichnyy"
    ],
    "wof:name":"Chemerichnyy",
    "wof:placetype":"locality"
},
  "geometry": {"coordinates":[50.8464,53.79053],"type":"Point"}
}