{
  "type": "Feature",
  "properties": {
    "gn:admin1_code":"8",
    "gn:asciiname":"Yandyganovo",
    "gn:country_code":"RU",
    "gn:dem":110,
    "gn:feature_class":"P",
    "gn:feature_code":"PPL",
    "gn:name":"Yandyganovo",
    "gn:population":0,
    "gn:timezone":"Asia/Yekaterinburg",
    "iso:country":"RU",
    "name:eng_x_preferred":[
        "Yandyganovo"
    ],
    "name:nor_x_preferred":[
        "Jandyganovo"
    ],
    "name:rus_x_preferred":[
        "\u042f\u043d\u0434\u044b\u0433\u0430\u043d\u043e\u0432\u043e"
    ],
    "wof:name":"Yandyganovo",
    "wof:placetype":"locality"
},
  "geometry": {"coordinates":[55.97032,55.4128],"type":"Point"}
}