{
  "type": "Feature",
  "properties": {
    "gn:admin1_code":"55",
    "gn:asciiname":"Tally",
    "gn:country_code":"RU",
    "gn:dem":167,
    "gn:feature_class":"P",
    "gn:feature_code":"PPL",
    "gn:name":"Tally",
    "gn:population":0,
    "gn:timezone":"Asia/Yekaterinburg",
    "iso:country":"RU",
    "name:deu_x_preferred":[
        "Tally"
    ],
    "name:eng_x_preferred":[
        "Tally"
    ],
    "name:nor_x_preferred":[
        "Tally"
    ],
    "name:rus_x_preferred":[
        "\u0422\u0430\u043b\u043b\u044b"
    ],
    "name:rus_x_variant":[
        "\u0422\u044d\u043b\u043b\u0438"
    ],
    "name:und_x_variant":[
        "\u0422\u0430\u043b\u043b\u044b"
    ],
    "wof:name":"Tally",
    "wof:placetype":"locality"
},
  "geometry": {"coordinates":[53.06667,53.13333000000001],"type":"Point"}
}