{
  "type": "Feature",
  "properties": {
    "gn:admin1_code":"54",
    "gn:asciiname":"Kaysy",
    "gn:country_code":"RU",
    "gn:dem":54,
    "gn:feature_class":"P",
    "gn:feature_code":"PPL",
    "gn:name":"Kaysy",
    "gn:population":0,
    "gn:timezone":"Asia/Omsk",
    "iso:country":"RU",
    "name:eng_x_preferred":[
        "Kaysy"
    ],
    "name:nor_x_preferred":[
        "Kajsy"
    ],
    "name:rus_x_preferred":[
        "\u041a\u0430\u0439\u0441\u044b"
    ],
    "name:und_x_variant":[
        "\u041a\u0430\u0439\u0441\u044b",
        "Kaysy"
    ],
    "wof:name":"Kaysy",
    "wof:placetype":"locality"
},
  "geometry": {"coordinates":[71.69880000000001,57.6578],"type":"Point"}
}