{
  "type": "Feature",
  "properties": {
    "gn:admin1_code":"83.0",
    "gn:asciiname":"Bol'shiye Yelovki",
    "gn:country_code":"RU",
    "gn:dem":202,
    "gn:feature_class":"P",
    "gn:feature_code":"PPL",
    "gn:name":"Bol\u2019shiye Yelovki",
    "gn:population":0,
    "gn:timezone":"Europe/Moscow",
    "iso:country":"RU",
    "name:rus_x_preferred":[
        "\u0411\u043e\u043b\u044c\u0448\u0438\u0435 \u0415\u043b\u043e\u0432\u043a\u0438"
    ],
    "name:und_x_variant":[
        "Yelovka",
        "Bol\u2019shiye Yelovki"
    ],
    "wof:name":"Bol'shiye Yelovki",
    "wof:placetype":"locality"
},
  "geometry": {"coordinates":[38.98659,56.50025],"type":"Point"}
}