{
  "type": "Feature",
  "properties": {
    "gn:admin1_code":"7",
    "gn:asciiname":"Tal'nikovyy",
    "gn:country_code":"RU",
    "gn:dem":-27,
    "gn:feature_class":"P",
    "gn:feature_code":"PPL",
    "gn:name":"Tal\u2019nikovyy",
    "gn:population":0,
    "gn:timezone":"Europe/Astrakhan",
    "iso:country":"RU",
    "wof:name":"Tal'nikovyy",
    "wof:placetype":"locality"
},
  "geometry": {"coordinates":[48.03333,46.73333],"type":"Point"}
}