{
  "type": "Feature",
  "properties": {
    "gn:admin1_code":"16",
    "gn:asciiname":"Vurmankasy",
    "gn:country_code":"RU",
    "gn:dem":166,
    "gn:feature_class":"P",
    "gn:feature_code":"PPL",
    "gn:name":"Vurmankasy",
    "gn:population":0,
    "gn:timezone":"Europe/Moscow",
    "iso:country":"RU",
    "name:rus_x_preferred":[
        "\u0412\u0443\u0440\u043c\u0430\u043d\u043a\u0430\u0441\u044b"
    ],
    "wof:name":"Vurmankasy",
    "wof:placetype":"locality"
},
  "geometry": {"coordinates":[47.01262,56.11415],"type":"Point"}
}