{
  "type": "Feature",
  "properties": {
    "gn:admin1_code":"91",
    "gn:asciiname":"Tuzlukovka",
    "gn:country_code":"RU",
    "gn:dem":253,
    "gn:feature_class":"P",
    "gn:feature_code":"PPL",
    "gn:name":"Tuzlukovka",
    "gn:population":0,
    "gn:timezone":"Asia/Krasnoyarsk",
    "iso:country":"RU",
    "name:eng_x_preferred":[
        "Tuzlukovka"
    ],
    "name:nor_x_preferred":[
        "Tuzlukovka"
    ],
    "name:rus_x_preferred":[
        "\u0422\u0443\u0437\u043b\u0443\u043a\u043e\u0432\u043a\u0430"
    ],
    "name:und_x_variant":[
        "Tuzlukovskiy"
    ],
    "wof:name":"Tuzlukovka",
    "wof:placetype":"locality"
},
  "geometry": {"coordinates":[89.19757,56.19795],"type":"Point"}
}