{
  "type": "Feature",
  "properties": {
    "gn:admin1_code":"37",
    "gn:asciiname":"Petryayevo",
    "gn:country_code":"RU",
    "gn:dem":163,
    "gn:feature_class":"P",
    "gn:feature_code":"PPL",
    "gn:name":"Petryayevo",
    "gn:population":0,
    "gn:timezone":"Europe/Moscow",
    "iso:country":"RU",
    "name:rus_x_preferred":[
        "\u041f\u0435\u0442\u0440\u044f\u0435\u0432\u043e"
    ],
    "name:und_x_variant":[
        "\u041f\u0435\u0442\u0440\u044f\u0435\u0432\u043e"
    ],
    "wof:name":"Petryayevo",
    "wof:placetype":"locality"
},
  "geometry": {"coordinates":[42.91667,59.06667],"type":"Point"}
}