{
  "type": "Feature",
  "properties": {
    "gn:admin1_code":"25",
    "gn:asciiname":"Medovniki",
    "gn:cc2":"RU",
    "gn:country_code":"RU",
    "gn:dem":173,
    "gn:feature_class":"P",
    "gn:feature_code":"PPL",
    "gn:name":"Medovniki",
    "gn:population":0,
    "gn:timezone":"Europe/Moscow",
    "iso:country":"RU",
    "name:rus_x_preferred":[
        "\u041c\u0435\u0434\u043e\u0432\u043d\u0438\u043a\u0438"
    ],
    "name:und_x_variant":[
        "Medowniki",
        "Medovniki"
    ],
    "wof:name":"Medovniki",
    "wof:placetype":"locality"
},
  "geometry": {"coordinates":[36.22028,55.17944],"type":"Point"}
}