{
  "type": "Feature",
  "properties": {
    "gn:admin1_code":"75",
    "gn:asciiname":"Charfo",
    "gn:country_code":"RU",
    "gn:dem":105,
    "gn:feature_class":"P",
    "gn:feature_code":"PPL",
    "gn:name":"Charfo",
    "gn:population":0,
    "gn:timezone":"Asia/Tomsk",
    "iso:country":"RU",
    "name:eng_x_preferred":[
        "Charfo"
    ],
    "name:nor_x_preferred":[
        "Tsjarfa"
    ],
    "name:rus_x_preferred":[
        "\u0427\u0430\u0440\u0444\u0430"
    ],
    "name:rus_x_variant":[
        "\u0427\u0430\u0440\u0444\u043e"
    ],
    "name:und_x_variant":[
        "\u0427\u0430\u0440\u0444\u043e"
    ],
    "wof:name":"Charfo",
    "wof:placetype":"locality"
},
  "geometry": {"coordinates":[79.21597,57.45953000000001],"type":"Point"}
}