{
  "type": "Feature",
  "properties": {
    "gn:admin1_code":"91",
    "gn:asciiname":"Gusevka",
    "gn:country_code":"RU",
    "gn:dem":172,
    "gn:feature_class":"P",
    "gn:feature_code":"PPL",
    "gn:name":"Gusevka",
    "gn:population":0,
    "gn:timezone":"Asia/Krasnoyarsk",
    "iso:country":"RU",
    "name:rus_x_preferred":[
        "\u0413\u0443\u0441\u0435\u0432\u043a\u0430"
    ],
    "wof:name":"Gusevka",
    "wof:placetype":"locality"
},
  "geometry": {"coordinates":[100.63333,58.68333000000001],"type":"Point"}
}