{
  "type": "Feature",
  "properties": {
    "gn:admin1_code":"85",
    "gn:asciiname":"Pustynka",
    "gn:country_code":"RU",
    "gn:dem":250,
    "gn:feature_class":"P",
    "gn:feature_code":"PPL",
    "gn:name":"Pustynka",
    "gn:population":0,
    "gn:timezone":"Europe/Moscow",
    "iso:country":"RU",
    "name:eng_x_preferred":[
        "Pustynka"
    ],
    "name:fin_x_preferred":[
        "Puusta"
    ],
    "name:nor_x_preferred":[
        "Pustynka"
    ],
    "name:pol_x_preferred":[
        "Pustynka"
    ],
    "name:rus_x_preferred":[
        "\u041f\u0443\u0441\u0442\u044b\u043d\u043a\u0430"
    ],
    "name:und_x_variant":[
        "Pustyrka",
        "\u041f\u0443\u0441\u0442\u044b\u043d\u043a\u0430",
        "Pustynka"
    ],
    "wof:name":"Pustynka",
    "wof:placetype":"locality"
},
  "geometry": {"coordinates":[35.88816,60.45387],"type":"Point"}
}