{
  "type": "Feature",
  "properties": {
    "gn:admin1_code":"40",
    "gn:asciiname":"Kokorevo",
    "gn:cc2":"RU",
    "gn:country_code":"RU",
    "gn:dem":104,
    "gn:feature_class":"P",
    "gn:feature_code":"PPL",
    "gn:name":"Kokorevo",
    "gn:population":0,
    "gn:timezone":"Asia/Yekaterinburg",
    "iso:country":"RU",
    "name:eng_x_preferred":[
        "Kokorevo"
    ],
    "name:nor_x_preferred":[
        "Kokarevo"
    ],
    "name:rus_x_preferred":[
        "\u041a\u043e\u043a\u0430\u0440\u0435\u0432\u043e"
    ],
    "name:rus_x_variant":[
        "\u041a\u043e\u043a\u043e\u0440\u0435\u0432\u043e"
    ],
    "name:und_x_variant":[
        "Kokoreva"
    ],
    "wof:name":"Kokorevo",
    "wof:placetype":"locality"
},
  "geometry": {"coordinates":[66.70833,55.8725],"type":"Point"}
}