{
  "type": "Feature",
  "properties": {
    "gn:admin1_code":"53",
    "gn:asciiname":"Musy",
    "gn:cc2":"RU",
    "gn:country_code":"RU",
    "gn:dem":141,
    "gn:feature_class":"P",
    "gn:feature_code":"PPL",
    "gn:name":"Musy",
    "gn:population":0,
    "gn:timezone":"Asia/Novosibirsk",
    "iso:country":"RU",
    "name:eng_x_preferred":[
        "Musy"
    ],
    "name:nor_x_preferred":[
        "Musy"
    ],
    "name:rus_x_preferred":[
        "\u041c\u0443\u0441\u044b"
    ],
    "name:und_x_variant":[
        "Musinskiy",
        "Musa"
    ],
    "wof:name":"Musy",
    "wof:placetype":"locality"
},
  "geometry": {"coordinates":[80.42971999999997,55.46],"type":"Point"}
}