{
  "type": "Feature",
  "properties": {
    "gn:admin1_code":"91",
    "gn:asciiname":"Ogon'ki",
    "gn:country_code":"RU",
    "gn:dem":366,
    "gn:feature_class":"P",
    "gn:feature_code":"PPL",
    "gn:name":"Ogon\u2019ki",
    "gn:population":0,
    "gn:timezone":"Asia/Krasnoyarsk",
    "iso:country":"RU",
    "name:eng_x_preferred":[
        "Ogon'ki"
    ],
    "name:nor_x_preferred":[
        "Ogonki"
    ],
    "name:rus_x_preferred":[
        "\u041e\u0433\u043e\u043d\u044c\u043a\u0438"
    ],
    "name:und_x_variant":[
        "Ogon\u2019ki"
    ],
    "wof:name":"Ogon'ki",
    "wof:placetype":"locality"
},
  "geometry": {"coordinates":[91.84472,55.46639],"type":"Point"}
}