{
  "type": "Feature",
  "properties": {
    "gn:admin1_code":"73",
    "gn:asciiname":"Murtaza",
    "gn:country_code":"RU",
    "gn:dem":130,
    "gn:feature_class":"P",
    "gn:feature_code":"PPL",
    "gn:name":"Murtaza",
    "gn:population":0,
    "gn:timezone":"Europe/Moscow",
    "iso:country":"RU",
    "name:eng_x_preferred":[
        "Murtaza"
    ],
    "name:jpn_x_preferred":[
        "\u30e2\u30eb\u30c6\u30b6\u30fc"
    ],
    "name:nor_x_preferred":[
        "Murtaza"
    ],
    "name:rus_x_preferred":[
        "\u041c\u0443\u0440\u0442\u0430\u0437\u0430"
    ],
    "name:und_x_variant":[
        "Murtava",
        "\u041c\u0443\u0440\u0442\u0430\u0437\u0430",
        "Murtaza"
    ],
    "wof:name":"Murtaza",
    "wof:placetype":"locality"
},
  "geometry": {"coordinates":[53.12289000000001,54.47536],"type":"Point"}
}