{
  "type": "Feature",
  "properties": {
    "gn:admin1_code":"84",
    "gn:asciiname":"Kuzhnoy",
    "gn:country_code":"RU",
    "gn:dem":26,
    "gn:feature_class":"P",
    "gn:feature_code":"PPL",
    "gn:name":"Kuzhnoy",
    "gn:population":0,
    "gn:timezone":"Europe/Volgograd",
    "iso:country":"RU",
    "name:rus_x_preferred":[
        "\u041a\u0443\u0436\u043d\u043e\u0439"
    ],
    "name:und_x_variant":[
        "\u041a\u0443\u0436\u043d\u043e\u0439"
    ],
    "wof:name":"Kuzhnoy",
    "wof:placetype":"locality"
},
  "geometry": {"coordinates":[45.24003,49.25027],"type":"Point"}
}