{
  "type": "Feature",
  "properties": {
    "gn:admin1_code":"54",
    "gn:asciiname":"Dubrovka",
    "gn:country_code":"RU",
    "gn:dem":110,
    "gn:feature_class":"P",
    "gn:feature_code":"PPL",
    "gn:name":"Dubrovka",
    "gn:population":0,
    "gn:timezone":"Asia/Omsk",
    "iso:country":"RU",
    "name:eng_x_preferred":[
        "Dubrovka"
    ],
    "name:nor_x_preferred":[
        "Dubrovka"
    ],
    "name:rus_x_preferred":[
        "\u0414\u0443\u0431\u0440\u043e\u0432\u043a\u0430"
    ],
    "name:und_x_variant":[
        "\u0414\u0443\u0431\u0440\u043e\u0432\u043a\u0430",
        "Dubrovka"
    ],
    "wof:name":"Dubrovka",
    "wof:placetype":"locality"
},
  "geometry": {"coordinates":[73.96764,55.14744],"type":"Point"}
}