{
  "type": "Feature",
  "properties": {
    "gn:country":"RU",
    "gn:fcode":"PPL",
    "gn:population":2100,
    "iso:country":"RU",
    "name:epo_x_preferred":[
        "Obuxovskoje"
    ],
    "name:rus_x_preferred":[
        "\u041e\u0431\u0443\u0445\u043e\u0432\u0441\u043a\u043e\u0435"
    ],
    "name:rus_x_variant":[
        "\u041e\u0431\u0443\u0445\u043e\u0432\u0441\u043a\u0438\u0439"
    ],
    "qs:name":"Obukhovskoye",
    "qs:name_adm0":"Russia",
    "qs:name_adm1":"Sverdlovsk Oblast",
    "qs:photos_9k":1,
    "qs:photos_9r":2,
    "qs:photos_all":69,
    "qs:photos_sr":0,
    "qs:placetype":"Town",
    "qs:pop_sr":"4",
    "wd:wordcount":99,
    "wof:name":"Obukhovskoye",
    "wof:placetype":"locality",
    "wof:population":2100
},
  "geometry": {"coordinates":[62.612,56.8345],"type":"Point"}
}