{
  "type": "Feature",
  "properties": {
    "gn:admin1_code":"33.0",
    "gn:asciiname":"Pozdnyaki",
    "gn:country_code":"RU",
    "gn:dem":108,
    "gn:feature_class":"P",
    "gn:feature_code":"PPL",
    "gn:name":"Pozdnyaki",
    "gn:population":0,
    "gn:timezone":"Europe/Kirov",
    "iso:country":"RU",
    "name:rus_x_preferred":[
        "\u041f\u043e\u0437\u0434\u043d\u044f\u043a\u0438"
    ],
    "wof:name":"Pozdnyaki",
    "wof:placetype":"locality"
},
  "geometry": {"coordinates":[48.3035,57.9844],"type":"Point"}
}