{
  "type": "Feature",
  "properties": {
    "gn:admin1_code":"17.0",
    "gn:asciiname":"Adzhidada",
    "gn:country_code":"RU",
    "gn:dem":-12,
    "gn:feature_class":"P",
    "gn:feature_code":"PPL",
    "gn:name":"Adzhidada",
    "gn:population":0,
    "gn:timezone":"Europe/Moscow",
    "iso:country":"RU",
    "name:eng_x_preferred":[
        "Adzhidada"
    ],
    "name:nor_x_preferred":[
        "Adzjidada"
    ],
    "name:rus_x_preferred":[
        "\u0410\u0434\u0436\u0438\u0434\u0430\u0434\u0430"
    ],
    "wof:name":"Adzhidada",
    "wof:placetype":"locality"
},
  "geometry": {"coordinates":[47.07583,43.28542],"type":"Point"}
}