{
  "type": "Feature",
  "properties": {
    "gn:admin1_code":"52.0",
    "gn:asciiname":"Bereznyak Vtoroy",
    "gn:country_code":"RU",
    "gn:dem":208,
    "gn:feature_class":"P",
    "gn:feature_code":"PPL",
    "gn:name":"Bereznyak Vtoroy",
    "gn:population":0,
    "gn:timezone":"Europe/Moscow",
    "iso:country":"RU",
    "name:nor_x_preferred":[
        "Bereznjak Vtoroj"
    ],
    "name:rus_x_preferred":[
        "\u0411\u0435\u0440\u0435\u0437\u043d\u044f\u043a \u0412\u0442\u043e\u0440\u043e\u0439"
    ],
    "name:und_x_variant":[
        "Bereznyak",
        "Bereznyak Vtoroy"
    ],
    "wof:name":"Bereznyak Vtoroy",
    "wof:placetype":"locality"
},
  "geometry": {"coordinates":[33.45952,58.88303000000001],"type":"Point"}
}