{
  "type": "Feature",
  "properties": {
    "gn:admin1_code":"45",
    "gn:asciiname":"Shikhmamat",
    "gn:country_code":"RU",
    "gn:dem":94,
    "gn:feature_class":"P",
    "gn:feature_code":"PPL",
    "gn:name":"Shikhmamat",
    "gn:population":0,
    "gn:timezone":"Europe/Moscow",
    "iso:country":"RU",
    "name:rus_x_preferred":[
        "\u0428\u0438\u0445\u043c\u0430\u043c\u0430\u0442"
    ],
    "name:und_x_variant":[
        "\u0428\u0438\u0445\u043c\u0430\u043c\u0430\u0442"
    ],
    "wof:name":"Shikhmamat",
    "wof:placetype":"locality"
},
  "geometry": {"coordinates":[47.84671,56.71401],"type":"Point"}
}