{
  "type": "Feature",
  "properties": {
    "gn:admin1_code":"33",
    "gn:asciiname":"Kozlovo",
    "gn:country_code":"RU",
    "gn:dem":130,
    "gn:feature_class":"P",
    "gn:feature_code":"PPL",
    "gn:name":"Kozlovo",
    "gn:population":0,
    "gn:timezone":"Europe/Kirov",
    "iso:country":"RU",
    "name:eng_x_preferred":[
        "Kozlovo"
    ],
    "name:nor_x_preferred":[
        "Kozlovo"
    ],
    "name:rus_x_preferred":[
        "\u041a\u043e\u0437\u043b\u043e\u0432\u043e"
    ],
    "name:und_x_variant":[
        "\u041a\u043e\u0437\u043b\u043e\u0432\u043e",
        "Kozlovo"
    ],
    "wof:name":"Kozlovo",
    "wof:placetype":"locality"
},
  "geometry": {"coordinates":[49.44637,58.82436],"type":"Point"}
}