{
  "type": "Feature",
  "properties": {
    "gn:country":"RU",
    "gn:fcode":"PPL",
    "gn:population":854,
    "iso:country":"RU",
    "name:ara_x_preferred":[
        "\u062f\u064a\u0628\u064a\u0646"
    ],
    "name:ceb_x_preferred":[
        "Debin"
    ],
    "name:che_x_preferred":[
        "\u0414\u0435\u0431\u0438\u043d"
    ],
    "name:deu_x_preferred":[
        "Debin"
    ],
    "name:eng_x_preferred":[
        "Debin"
    ],
    "name:hun_x_preferred":[
        "Debin"
    ],
    "name:hye_x_preferred":[
        "\u0534\u0565\u0562\u056b\u0576"
    ],
    "name:ita_x_preferred":[
        "Debin"
    ],
    "name:lit_x_preferred":[
        "Debinas"
    ],
    "name:nor_x_preferred":[
        "Debin"
    ],
    "name:pol_x_preferred":[
        "Debin"
    ],
    "name:rus_x_preferred":[
        "\u0414\u0435\u0431\u0438\u043d"
    ],
    "name:swe_x_preferred":[
        "Debin"
    ],
    "name:tgl_x_preferred":[
        "Debin"
    ],
    "name:ukr_x_preferred":[
        "\u0414\u0435\u0431\u0456\u043d"
    ],
    "name:und_x_variant":[
        "Rybnoye"
    ],
    "qs:name":"Debin",
    "qs:photos_9r":0,
    "qs:photos_sr":0,
    "qs:pop_sr":"2",
    "wd:wordcount":464,
    "wof:name":"Debin",
    "wof:placetype":"locality",
    "wof:population":854
},
  "geometry": {"coordinates":[150.75745000000001,62.34198],"type":"Point"}
}