{
  "type": "Feature",
  "properties": {
    "gn:admin1_code":"51",
    "gn:asciiname":"Zubovo",
    "gn:country_code":"RU",
    "gn:dem":147,
    "gn:feature_class":"P",
    "gn:feature_code":"PPL",
    "gn:name":"Zubovo",
    "gn:population":0,
    "gn:timezone":"Europe/Moscow",
    "iso:country":"RU",
    "name:rus_x_preferred":[
        "\u0417\u0443\u0431\u043e\u0432\u043e"
    ],
    "name:und_x_variant":[
        "\u0417\u0443\u0431\u043e\u0432\u043e"
    ],
    "wof:name":"Zubovo",
    "wof:placetype":"locality"
},
  "geometry": {"coordinates":[45.7906,57.6604],"type":"Point"}
}