{
  "type": "Feature",
  "properties": {
    "gn:admin1_code":"20",
    "gn:asciiname":"Cheremnova",
    "gn:country_code":"RU",
    "gn:dem":291,
    "gn:feature_class":"P",
    "gn:feature_code":"PPL",
    "gn:name":"Cheremnova",
    "gn:population":0,
    "gn:timezone":"Asia/Irkutsk",
    "iso:country":"RU",
    "name:che_x_preferred":[
        "\u0427\u0435\u0440\u0435\u043c\u043d\u043e\u0432\u0430"
    ],
    "name:koi_x_preferred":[
        "\u0427\u0435\u0440\u04e7\u043c\u043d\u04e7\u0439"
    ],
    "name:rus_x_preferred":[
        "\u0427\u0435\u0440\u0435\u043c\u043d\u043e\u0432\u0430"
    ],
    "wof:name":"Cheremnova",
    "wof:placetype":"locality"
},
  "geometry": {"coordinates":[103.26667,57.16667],"type":"Point"}
}