{
  "type": "Feature",
  "properties": {
    "gn:admin1_code":"77",
    "gn:asciiname":"Zaruch'ye",
    "gn:country_code":"RU",
    "gn:dem":132,
    "gn:feature_class":"P",
    "gn:feature_code":"PPL",
    "gn:name":"Zaruch\u2019ye",
    "gn:population":0,
    "gn:timezone":"Europe/Moscow",
    "iso:country":"RU",
    "name:rus_x_preferred":[
        "\u0417\u0430\u0440\u0443\u0447\u044c\u0435"
    ],
    "name:und_x_variant":[
        "Zaruch\u2019ye",
        "\u0417\u0430\u0440\u0443\u0447\u044c\u0435"
    ],
    "wof:name":"Zaruch'ye",
    "wof:placetype":"locality"
},
  "geometry": {"coordinates":[36.6175,57.9234],"type":"Point"}
}