{
  "type": "Feature",
  "properties": {
    "gn:admin1_code":"28",
    "gn:asciiname":"Khallasel'kya",
    "gn:country_code":"RU",
    "gn:dem":141,
    "gn:feature_class":"P",
    "gn:feature_code":"PPL",
    "gn:name":"Khallasel\u2019kya",
    "gn:population":0,
    "gn:timezone":"Europe/Moscow",
    "iso:country":"RU",
    "name:fin_x_preferred":[
        "Hallaselk\u00e4"
    ],
    "name:rus_x_preferred":[
        "\u0425\u0430\u043b\u043b\u0430\u0441\u0435\u043b\u044c\u043a\u044f"
    ],
    "name:und_x_variant":[
        "Khallasel\u2019kya"
    ],
    "wof:name":"Khallasel'kya",
    "wof:placetype":"locality"
},
  "geometry": {"coordinates":[32.52193,62.19226],"type":"Point"}
}