{
  "type": "Feature",
  "properties": {
    "gn:admin1_code":"6.0",
    "gn:asciiname":"Navolok",
    "gn:country_code":"RU",
    "gn:dem":60,
    "gn:feature_class":"P",
    "gn:feature_code":"PPL",
    "gn:name":"Navolok",
    "gn:population":0,
    "gn:timezone":"Europe/Moscow",
    "iso:country":"RU",
    "name:eng_x_preferred":[
        "Navolok"
    ],
    "name:nor_x_preferred":[
        "Navolok"
    ],
    "name:rus_x_preferred":[
        "\u041d\u0430\u0432\u043e\u043b\u043e\u043a"
    ],
    "name:und_x_variant":[
        "\u041d\u0430\u0432\u043e\u043b\u043e\u043a",
        "Navolok"
    ],
    "wof:name":"Navolok",
    "wof:placetype":"locality"
},
  "geometry": {"coordinates":[41.19917,62.81015],"type":"Point"}
}