{
  "type": "Feature",
  "properties": {
    "gn:admin1_code":"8",
    "gn:asciiname":"Il'chibay",
    "gn:country_code":"RU",
    "gn:dem":147,
    "gn:feature_class":"P",
    "gn:feature_code":"PPL",
    "gn:name":"Il\u2019chibay",
    "gn:population":0,
    "gn:timezone":"Asia/Yekaterinburg",
    "iso:country":"RU",
    "name:rus_x_preferred":[
        "\u0418\u043b\u044c\u0447\u0438\u0431\u0430\u0439"
    ],
    "name:und_x_variant":[
        "Ilchibayevo",
        "Il\u2019chibay"
    ],
    "wof:name":"Il'chibay",
    "wof:placetype":"locality"
},
  "geometry": {"coordinates":[54.6675,56.0091],"type":"Point"}
}