{
  "type": "Feature",
  "properties": {
    "gn:admin1_code":"71",
    "gn:asciiname":"Beloyarka",
    "gn:country_code":"RU",
    "gn:dem":76,
    "gn:feature_class":"P",
    "gn:feature_code":"PPL",
    "gn:name":"Beloyarka",
    "gn:population":0,
    "gn:timezone":"Asia/Yekaterinburg",
    "iso:country":"RU",
    "name:eng_x_preferred":[
        "Beloyarka"
    ],
    "name:nor_x_preferred":[
        "Belojarka"
    ],
    "name:rus_x_preferred":[
        "\u0411\u0435\u043b\u043e\u044f\u0440\u043a\u0430"
    ],
    "wof:name":"Beloyarka",
    "wof:placetype":"locality"
},
  "geometry": {"coordinates":[64.93799,58.22514],"type":"Point"}
}