{
  "type": "Feature",
  "properties": {
    "gn:admin1_code":"54",
    "gn:asciiname":"Staryy Bazarbay",
    "gn:country_code":"RU",
    "gn:dem":115,
    "gn:feature_class":"P",
    "gn:feature_code":"PPL",
    "gn:name":"Staryy Bazarbay",
    "gn:population":0,
    "gn:timezone":"Asia/Omsk",
    "iso:country":"RU",
    "name:rus_x_preferred":[
        "\u0421\u0442\u0430\u0440\u044b\u0439 \u0411\u0430\u0437\u0430\u0440\u0431\u0430\u0439"
    ],
    "name:und_x_variant":[
        "\u0421\u0442\u0430\u0440\u044b\u0439 \u0411\u0430\u0437\u0430\u0440\u0431\u0430\u0439"
    ],
    "wof:name":"Staryy Bazarbay",
    "wof:placetype":"locality"
},
  "geometry": {"coordinates":[72.05,54.71666999999999],"type":"Point"}
}