{
  "type": "Feature",
  "properties": {
    "gn:country":"RU",
    "gn:fcode":"PPL",
    "gn:pop":1722,
    "iso:country":"RU",
    "name:rus_x_preferred":[
        "\u041a\u0443\u0441\u0430\u043a"
    ],
    "name:unk_x_variant":[
        "\u041a\u0443\u0441\u0430\u043a"
    ],
    "qs:name":"Kusak",
    "qs:photos_9r":0,
    "qs:photos_sr":0,
    "qs:pop_sr":"3",
    "wof:name":"Kusak",
    "wof:placetype":"locality",
    "wof:population":1722
},
  "geometry": {"coordinates":[78.9337,53.2238],"type":"Point"}
}