{
  "type": "Feature",
  "properties": {
    "gn:admin1_code":"33",
    "gn:asciiname":"Verdyukovskaya",
    "gn:country_code":"RU",
    "gn:dem":149,
    "gn:feature_class":"P",
    "gn:feature_code":"PPL",
    "gn:name":"Verdyukovskaya",
    "gn:population":0,
    "gn:timezone":"Europe/Kirov",
    "iso:country":"RU",
    "name:rus_x_preferred":[
        "\u0412\u0435\u0440\u0434\u044e\u043a\u043e\u0432\u0441\u043a\u0430\u044f"
    ],
    "wof:name":"Verdyukovskaya",
    "wof:placetype":"locality"
},
  "geometry": {"coordinates":[48.1569,60.43451999999999],"type":"Point"}
}