{
  "type": "Feature",
  "properties": {
    "gn:admin1_code":"56",
    "gn:asciiname":"Kofanova",
    "gn:country_code":"RU",
    "gn:dem":207,
    "gn:feature_class":"P",
    "gn:feature_code":"PPL",
    "gn:name":"Kofanova",
    "gn:population":0,
    "gn:timezone":"Europe/Moscow",
    "iso:country":"RU",
    "name:rus_x_preferred":[
        "\u041a\u043e\u0444\u0430\u043d\u043e\u0432\u0430"
    ],
    "name:und_x_variant":[
        "Kofanovo",
        "Kofanova",
        "\u041a\u043e\u0444\u0430\u043d\u043e\u0432\u0430"
    ],
    "wof:name":"Kofanova",
    "wof:placetype":"locality"
},
  "geometry": {"coordinates":[35.64383,53.19609000000001],"type":"Point"}
}