{
  "type": "Feature",
  "properties": {
    "gn:admin1_code":"12",
    "gn:admin2_code":"Itum-Kalinskiy Rayon",
    "gn:asciiname":"Bacharkhe",
    "gn:country_code":"RU",
    "gn:dem":1658,
    "gn:feature_class":"P",
    "gn:feature_code":"PPL",
    "gn:name":"Bacharkhe",
    "gn:population":0,
    "gn:timezone":"Europe/Moscow",
    "iso:country":"RU",
    "name:nor_x_preferred":[
        "Batsjarkhe"
    ],
    "name:rus_x_preferred":[
        "\u0411\u0430\u0447\u0430\u0440\u0445\u0435"
    ],
    "wof:name":"Bacharkhe",
    "wof:placetype":"locality"
},
  "geometry": {"coordinates":[45.92861,42.63806],"type":"Point"}
}