{
  "type": "Feature",
  "properties": {
    "gn:admin1_code":"52",
    "gn:asciiname":"Zelenaya Dubrova",
    "gn:country_code":"RU",
    "gn:dem":71,
    "gn:feature_class":"P",
    "gn:feature_code":"PPL",
    "gn:name":"Zel\u00ebnaya Dubrova",
    "gn:population":0,
    "gn:timezone":"Europe/Moscow",
    "iso:country":"RU",
    "name:rus_x_preferred":[
        "\u0417\u0435\u043b\u00eb\u043d\u0430\u044f \u0414\u0443\u0431\u0440\u043e\u0432\u0430"
    ],
    "name:und_x_variant":[
        "Zel\u00ebnaya Dubrova"
    ],
    "wof:name":"Zelenaya Dubrova",
    "wof:placetype":"locality"
},
  "geometry": {"coordinates":[30.9727,57.8782],"type":"Point"}
}