{
  "type": "Feature",
  "properties": {
    "gn:admin1_code":"88",
    "gn:asciiname":"Khovory",
    "gn:country_code":"RU",
    "gn:dem":169,
    "gn:feature_class":"P",
    "gn:feature_code":"PPL",
    "gn:name":"Khovory",
    "gn:population":0,
    "gn:timezone":"Europe/Moscow",
    "iso:country":"RU",
    "name:rus_x_preferred":[
        "\u0425\u043e\u0432\u043e\u0440\u044b"
    ],
    "wof:name":"Khovory",
    "wof:placetype":"locality"
},
  "geometry": {"coordinates":[38.6623,57.2312],"type":"Point"}
}