{
  "type": "Feature",
  "properties": {
    "gn:admin1_code":"70",
    "gn:asciiname":"Kolontay",
    "gn:country_code":"RU",
    "gn:dem":83,
    "gn:feature_class":"P",
    "gn:feature_code":"PPL",
    "gn:name":"Kolontay",
    "gn:population":0,
    "gn:timezone":"Europe/Moscow",
    "iso:country":"RU",
    "name:rus_x_preferred":[
        "\u041a\u043e\u043b\u043e\u043d\u0442\u0430\u0439"
    ],
    "name:und_x_variant":[
        "\u041a\u043e\u043b\u043e\u043d\u0442\u0430\u0439"
    ],
    "wof:name":"Kolontay",
    "wof:placetype":"locality"
},
  "geometry": {"coordinates":[45.44167,43.94194],"type":"Point"}
}