{
  "type": "Feature",
  "properties": {
    "gn:admin1_code":"55",
    "gn:asciiname":"Mayachnyy",
    "gn:country_code":"RU",
    "gn:dem":195,
    "gn:feature_class":"P",
    "gn:feature_code":"PPL",
    "gn:name":"Mayachnyy",
    "gn:population":0,
    "gn:timezone":"Asia/Yekaterinburg",
    "iso:country":"RU",
    "name:eng_x_preferred":[
        "Mayachnyy"
    ],
    "name:nor_x_preferred":[
        "Majatsjnyj"
    ],
    "name:rus_x_preferred":[
        "\u041c\u0430\u044f\u0447\u043d\u044b\u0439"
    ],
    "name:und_x_variant":[
        "Myachnyy",
        "\u041c\u0430\u044f\u0447\u043d\u044b\u0439",
        "Mayachnyy"
    ],
    "wof:name":"Mayachnyy",
    "wof:placetype":"locality"
},
  "geometry": {"coordinates":[57.5098,51.0937],"type":"Point"}
}