{
  "type": "Feature",
  "properties": {
    "gn:admin1_code":"85",
    "gn:asciiname":"Staryy Ruchey",
    "gn:country_code":"RU",
    "gn:dem":232,
    "gn:feature_class":"P",
    "gn:feature_code":"PPL",
    "gn:name":"Staryy Ruchey",
    "gn:population":0,
    "gn:timezone":"Europe/Moscow",
    "iso:country":"RU",
    "wof:name":"Staryy Ruchey",
    "wof:placetype":"locality"
},
  "geometry": {"coordinates":[35.38417000000001,60.49444],"type":"Point"}
}