{
  "type": "Feature",
  "properties": {
    "gn:admin1_code":"13",
    "gn:asciiname":"Suleymanovo",
    "gn:country_code":"RU",
    "gn:dem":197,
    "gn:feature_class":"P",
    "gn:feature_code":"PPL",
    "gn:name":"Suleymanovo",
    "gn:population":0,
    "gn:timezone":"Asia/Yekaterinburg",
    "iso:country":"RU",
    "name:aze_x_preferred":[
        "S\u00fcleyman"
    ],
    "name:bak_x_preferred":[
        "\u0421\u04e9\u043b\u04d9\u0439\u043c\u04d9\u043d"
    ],
    "name:che_x_preferred":[
        "\u0421\u0443\u043b\u0435\u0439\u043c\u0430\u043d\u043e\u0432\u043e"
    ],
    "name:hye_x_preferred":[
        "\u054d\u0578\u0582\u056c\u0565\u0575\u0574\u0561\u0576\u0578\u057e\u0578"
    ],
    "name:kaz_x_preferred":[
        "\u0421\u0443\u043b\u0435\u0439\u043c\u0430\u043d"
    ],
    "name:kir_x_preferred":[
        "\u0421\u0443\u043b\u0435\u0439\u043c\u0430\u043d"
    ],
    "name:rus_x_preferred":[
        "\u0421\u0443\u043b\u0435\u0439\u043c\u0430\u043d\u043e\u0432\u043e"
    ],
    "name:tat_x_preferred":[
        "\u0421\u04e9\u043b\u04d9\u0439\u043c\u0430\u043d"
    ],
    "name:ukr_x_preferred":[
        "\u0421\u0443\u043b\u0435\u0439\u043c\u0430\u043d\u043e\u0432\u043e"
    ],
    "name:und_x_variant":[
        "Suleymanova",
        "Suleymanovo"
    ],
    "wof:name":"Suleymanovo",
    "wof:placetype":"locality"
},
  "geometry": {"coordinates":[61.2687,55.6767],"type":"Point"}
}