{
  "type": "Feature",
  "properties": {
    "gn:admin1_code":"73",
    "gn:asciiname":"Yenovka",
    "gn:country_code":"RU",
    "gn:dem":237,
    "gn:feature_class":"P",
    "gn:feature_code":"PPL",
    "gn:name":"Yenovka",
    "gn:population":0,
    "gn:timezone":"Europe/Moscow",
    "iso:country":"RU",
    "name:rus_x_preferred":[
        "\u0415\u043d\u043e\u0432\u043a\u0430"
    ],
    "name:und_x_variant":[
        "\u0415\u043d\u043e\u0432\u043a\u0430",
        "Yanovka"
    ],
    "wof:name":"Yenovka",
    "wof:placetype":"locality"
},
  "geometry": {"coordinates":[53.16289,54.59591],"type":"Point"}
}