{
  "type": "Feature",
  "properties": {
    "gn:admin1_code":"46",
    "gn:asciiname":"Kaymar",
    "gn:country_code":"RU",
    "gn:dem":174,
    "gn:feature_class":"P",
    "gn:feature_code":"PPL",
    "gn:name":"Kaymar",
    "gn:population":0,
    "gn:timezone":"Europe/Moscow",
    "iso:country":"RU",
    "name:eng_x_preferred":[
        "Kaymar"
    ],
    "name:nor_x_preferred":[
        "Kajmar"
    ],
    "name:rus_x_preferred":[
        "\u041a\u0430\u0439\u043c\u0430\u0440"
    ],
    "wof:name":"Kaymar",
    "wof:placetype":"locality"
},
  "geometry": {"coordinates":[44.23375,54.43373],"type":"Point"}
}