{
  "type": "Feature",
  "properties": {
    "gn:admin1_code":"56",
    "gn:asciiname":"Paponovka",
    "gn:cc2":"RU",
    "gn:country_code":"RU",
    "gn:dem":237,
    "gn:feature_class":"P",
    "gn:feature_code":"PPL",
    "gn:name":"Paponovka",
    "gn:population":0,
    "gn:timezone":"Europe/Moscow",
    "iso:country":"RU",
    "name:rus_x_preferred":[
        "\u041f\u0430\u043f\u043e\u043d\u043e\u0432\u043a\u0430"
    ],
    "name:und_x_variant":[
        "Papanovka",
        "Paponovka",
        "\u041f\u0430\u043f\u043e\u043d\u043e\u0432\u043a\u0430"
    ],
    "wof:name":"Paponovka",
    "wof:placetype":"locality"
},
  "geometry": {"coordinates":[37.63333,52.95],"type":"Point"}
}