{
  "type": "Feature",
  "properties": {
    "gn:admin1_code":"17",
    "gn:asciiname":"Shadni",
    "gn:country_code":"RU",
    "gn:dem":1356,
    "gn:feature_class":"P",
    "gn:feature_code":"PPL",
    "gn:name":"Shadni",
    "gn:population":0,
    "gn:timezone":"Europe/Moscow",
    "iso:country":"RU",
    "name:rus_x_preferred":[
        "\u0428\u0430\u0434\u043d\u0438"
    ],
    "wof:name":"Shadni",
    "wof:placetype":"locality"
},
  "geometry": {"coordinates":[47.64603,42.19372],"type":"Point"}
}