{
  "type": "Feature",
  "properties": {
    "gn:admin1_code":"77",
    "gn:asciiname":"Kholop'ya",
    "gn:country_code":"RU",
    "gn:dem":184,
    "gn:feature_class":"P",
    "gn:feature_code":"PPL",
    "gn:name":"Kholop\u2019ya",
    "gn:population":0,
    "gn:timezone":"Europe/Moscow",
    "iso:country":"RU",
    "name:rus_x_preferred":[
        "\u0425\u043e\u043b\u043e\u043f\u044c\u044f"
    ],
    "name:und_x_variant":[
        "Kholop\u2019ye",
        "Kholop\u2019ya",
        "\u0425\u043e\u043b\u043e\u043f\u044c\u044f"
    ],
    "wof:name":"Kholop'ya",
    "wof:placetype":"locality"
},
  "geometry": {"coordinates":[34.88333,56.16667],"type":"Point"}
}