{
  "type": "Feature",
  "properties": {
    "gn:admin1_code":"51",
    "gn:asciiname":"Zmeyka",
    "gn:country_code":"RU",
    "gn:dem":95,
    "gn:feature_class":"P",
    "gn:feature_code":"PPL",
    "gn:name":"Zmeyka",
    "gn:population":0,
    "gn:timezone":"Europe/Moscow",
    "iso:country":"RU",
    "name:rus_x_preferred":[
        "\u0417\u043c\u0435\u0439\u043a\u0430"
    ],
    "wof:name":"Zmeyka",
    "wof:placetype":"locality"
},
  "geometry": {"coordinates":[42.1679,55.4197],"type":"Point"}
}