{
  "type": "Feature",
  "properties": {
    "gn:country":"RU",
    "gn:fcode":"PPL",
    "gn:population":265,
    "iso:country":"RU",
    "name:cat_x_preferred":[
        "Beloretxka"
    ],
    "name:ceb_x_preferred":[
        "Belorechka"
    ],
    "name:che_x_preferred":[
        "\u0411\u0435\u043b\u043e\u0440\u0435\u0447\u043a\u0430"
    ],
    "name:eng_x_preferred":[
        "Belorechka"
    ],
    "name:rus_x_preferred":[
        "\u0411\u0435\u043b\u043e\u0440\u0435\u0447\u043a\u0430"
    ],
    "name:tat_x_preferred":[
        "\u0411\u0435\u043b\u043e\u0440\u0435\u0447\u043a\u0430"
    ],
    "name:tgk_x_preferred":[
        "\u0411\u0435\u043b\u0430\u044f \u0440\u0435\u0447\u043a\u0430"
    ],
    "name:ukr_x_preferred":[
        "\u0411\u0456\u043b\u043e\u0440\u0456\u0447\u043a\u0430"
    ],
    "qs:name":"Belorechka",
    "qs:name_adm0":"Russia",
    "qs:name_adm1":"Sverdlovsk Oblast",
    "qs:photos_9r":0,
    "qs:photos_sr":0,
    "qs:placetype":"Town",
    "qs:pop_sr":"2",
    "wof:name":"Belorechka",
    "wof:placetype":"locality",
    "wof:population":265
},
  "geometry": {"coordinates":[60.03472,57.33194],"type":"Point"}
}