{
  "type": "Feature",
  "properties": {
    "gn:admin1_code":"72",
    "gn:asciiname":"Koptevo",
    "gn:country_code":"RU",
    "gn:dem":149,
    "gn:feature_class":"P",
    "gn:feature_code":"PPL",
    "gn:name":"Kopt\u00ebvo",
    "gn:population":0,
    "gn:timezone":"Europe/Moscow",
    "iso:country":"RU",
    "name:bel_x_preferred":[
        "\u041a\u043e\u043f\u0446\u0435\u0432\u0430"
    ],
    "name:eng_x_preferred":[
        "Kopt\u00ebvo"
    ],
    "name:nld_x_preferred":[
        "Koptevo"
    ],
    "name:nor_x_preferred":[
        "Koptevo"
    ],
    "name:rus_x_preferred":[
        "\u041a\u043e\u043f\u0442\u0435\u0432\u043e"
    ],
    "name:rus_x_variant":[
        "\u041a\u043e\u043f\u0442\u0451\u0432\u043e"
    ],
    "name:und_x_variant":[
        "Kopt\u00ebvo"
    ],
    "wof:name":"Koptevo",
    "wof:placetype":"locality"
},
  "geometry": {"coordinates":[41.71985,52.47994],"type":"Point"}
}