{
  "type": "Feature",
  "properties": {
    "gn:admin1_code":"37",
    "gn:asciiname":"Bragino",
    "gn:country_code":"RU",
    "gn:dem":135,
    "gn:feature_class":"P",
    "gn:feature_code":"PPL",
    "gn:name":"Bragino",
    "gn:population":0,
    "gn:timezone":"Europe/Moscow",
    "iso:country":"RU",
    "name:rus_x_preferred":[
        "\u0411\u0440\u0430\u0433\u0438\u043d\u043e"
    ],
    "name:und_x_variant":[
        "\u0411\u0440\u0430\u0433\u0438\u043d\u043e"
    ],
    "wof:name":"Bragino",
    "wof:placetype":"locality"
},
  "geometry": {"coordinates":[43.4722,58.4255],"type":"Point"}
}