{
  "type": "Feature",
  "properties": {
    "gn:admin1_code":"46",
    "gn:asciiname":"Mordovskoye Kolomasovo",
    "gn:country_code":"RU",
    "gn:dem":174,
    "gn:feature_class":"P",
    "gn:feature_code":"PPL",
    "gn:name":"Mordovskoye Kolomasovo",
    "gn:population":0,
    "gn:timezone":"Europe/Moscow",
    "iso:country":"RU",
    "name:rus_x_preferred":[
        "\u041c\u043e\u0440\u0434\u043e\u0432\u0441\u043a\u043e\u0435 \u041a\u043e\u043b\u043e\u043c\u0430\u0441\u043e\u0432\u043e"
    ],
    "name:und_x_variant":[
        "\u041c\u043e\u0440\u0434\u043e\u0432\u0441\u043a\u043e\u0435 \u041a\u043e\u043b\u043e\u043c\u0430\u0441\u043e\u0432\u043e"
    ],
    "wof:name":"Mordovskoye Kolomasovo",
    "wof:placetype":"locality"
},
  "geometry": {"coordinates":[44.13599,53.9626],"type":"Point"}
}