{
  "type": "Feature",
  "properties": {
    "gn:admin1_code":"20.0",
    "gn:asciiname":"Kaduy",
    "gn:country_code":"RU",
    "gn:dem":567,
    "gn:feature_class":"P",
    "gn:feature_code":"PPL",
    "gn:name":"Kaduy",
    "gn:population":0,
    "gn:timezone":"Asia/Irkutsk",
    "iso:country":"RU",
    "name:rus_x_preferred":[
        "\u041a\u0430\u0434\u0443\u0439"
    ],
    "wof:name":"Kaduy",
    "wof:placetype":"locality"
},
  "geometry": {"coordinates":[99.4926,54.7447],"type":"Point"}
}