{
  "type": "Feature",
  "properties": {
    "gn:admin1_code":"6",
    "gn:asciiname":"Kyarostrov",
    "gn:country_code":"RU",
    "gn:dem":4,
    "gn:feature_class":"P",
    "gn:feature_code":"PPL",
    "gn:name":"Kyarostrov",
    "gn:population":0,
    "gn:timezone":"Europe/Moscow",
    "iso:country":"RU",
    "name:rus_x_preferred":[
        "\u041a\u044f\u0440\u043e\u0441\u0442\u0440\u043e\u0432"
    ],
    "name:und_x_variant":[
        "Karostrovo",
        "Kyarostrov"
    ],
    "wof:name":"Kyarostrov",
    "wof:placetype":"locality"
},
  "geometry": {"coordinates":[40.4286,64.5394],"type":"Point"}
}