{
  "type": "Feature",
  "properties": {
    "gn:admin1_code":"47",
    "gn:asciiname":"Skorodnya",
    "gn:country_code":"RU",
    "gn:dem":140,
    "gn:feature_class":"P",
    "gn:feature_code":"PPL",
    "gn:name":"Skorodnya",
    "gn:population":0,
    "gn:timezone":"Europe/Moscow",
    "iso:country":"RU",
    "name:rus_x_preferred":[
        "\u0421\u043a\u043e\u0440\u043e\u0434\u043d\u044f"
    ],
    "wof:name":"Skorodnya",
    "wof:placetype":"locality"
},
  "geometry": {"coordinates":[38.4834,54.4633],"type":"Point"}
}