{
  "type": "Feature",
  "properties": {
    "gn:admin1_code":"65",
    "gn:asciiname":"Sokskiy",
    "gn:country_code":"RU",
    "gn:dem":100,
    "gn:feature_class":"P",
    "gn:feature_code":"PPL",
    "gn:name":"Sokskiy",
    "gn:population":0,
    "gn:timezone":"Europe/Samara",
    "iso:country":"RU",
    "name:rus_x_preferred":[
        "\u0421\u043e\u043a\u0441\u043a\u0438\u0439"
    ],
    "name:und_x_variant":[
        "\u0421\u043e\u043a\u0441\u043a\u0438\u0439",
        "Sovkhoz Rassvet"
    ],
    "wof:name":"Sokskiy",
    "wof:placetype":"locality"
},
  "geometry": {"coordinates":[51.8641,54.0668],"type":"Point"}
}