{
  "type": "Feature",
  "properties": {
    "gn:admin1_code":"56",
    "gn:asciiname":"Zubkovo",
    "gn:country_code":"RU",
    "gn:dem":220,
    "gn:feature_class":"P",
    "gn:feature_code":"PPL",
    "gn:name":"Zubkovo",
    "gn:population":0,
    "gn:timezone":"Europe/Moscow",
    "iso:country":"RU",
    "name:rus_x_preferred":[
        "\u0417\u0443\u0431\u043a\u043e\u0432\u043e"
    ],
    "wof:name":"Zubkovo",
    "wof:placetype":"locality"
},
  "geometry": {"coordinates":[36.84282,52.5927],"type":"Point"}
}