{
  "type": "Feature",
  "properties": {
    "gn:admin1_code":"37.0",
    "gn:asciiname":"Voskresen'ye-Glazunovo",
    "gn:country_code":"RU",
    "gn:dem":225,
    "gn:feature_class":"P",
    "gn:feature_code":"PPL",
    "gn:name":"Voskresen\u2019ye-Glazunovo",
    "gn:population":0,
    "gn:timezone":"Europe/Moscow",
    "iso:country":"RU",
    "name:rus_x_preferred":[
        "\u0412\u043e\u0441\u043a\u0440\u0435\u0441\u0435\u043d\u044c\u0435-\u0413\u043b\u0430\u0437\u0443\u043d\u043e\u0432\u043e"
    ],
    "name:und_x_variant":[
        "Voskreseniye-Glazunovo",
        "Voskreseniye",
        "Voskresen\u2019ye-Glazunovo",
        "Glazunovo",
        "Vysokoye-Glazunovo"
    ],
    "wof:name":"Voskresen'ye-Glazunovo",
    "wof:placetype":"locality"
},
  "geometry": {"coordinates":[42.61899,58.6035],"type":"Point"}
}