{
  "type": "Feature",
  "properties": {
    "gn:admin1_code":"56",
    "gn:asciiname":"Neplyuyevo",
    "gn:country_code":"RU",
    "gn:dem":240,
    "gn:feature_class":"P",
    "gn:feature_code":"PPL",
    "gn:name":"Neplyuyevo",
    "gn:population":0,
    "gn:timezone":"Europe/Moscow",
    "iso:country":"RU",
    "name:eng_x_preferred":[
        "Neplyuyevo"
    ],
    "name:nor_x_preferred":[
        "Nepljuevo"
    ],
    "name:rus_x_preferred":[
        "\u041d\u0435\u043f\u043b\u044e\u0435\u0432\u043e"
    ],
    "name:und_x_variant":[
        "Peplyuyevo"
    ],
    "wof:name":"Neplyuyevo",
    "wof:placetype":"locality"
},
  "geometry": {"coordinates":[36.46974,52.87099],"type":"Point"}
}