{
  "type": "Feature",
  "properties": {
    "gn:admin1_code":"56.0",
    "gn:asciiname":"Fironovka",
    "gn:country_code":"RU",
    "gn:dem":187,
    "gn:feature_class":"P",
    "gn:feature_code":"PPL",
    "gn:name":"Fironovka",
    "gn:population":0,
    "gn:timezone":"Europe/Moscow",
    "iso:country":"RU",
    "name:rus_x_preferred":[
        "\u0424\u0438\u0440\u043e\u043d\u043e\u0432\u043a\u0430"
    ],
    "name:und_x_variant":[
        "Feronovka",
        "Fironovka",
        "\u0424\u0438\u0440\u043e\u043d\u043e\u0432\u043a\u0430"
    ],
    "wof:name":"Fironovka",
    "wof:placetype":"locality"
},
  "geometry": {"coordinates":[37.21043,53.10195],"type":"Point"}
}