{
  "type": "Feature",
  "properties": {
    "gn:admin1_code":"38.0",
    "gn:asciiname":"Otrub Sed'moy",
    "gn:country_code":"RU",
    "gn:dem":-1,
    "gn:feature_class":"P",
    "gn:feature_code":"PPL",
    "gn:name":"Otrub Sed\u2019moy",
    "gn:population":0,
    "gn:timezone":"Europe/Moscow",
    "iso:country":"RU",
    "wof:name":"Otrub Sed'moy",
    "wof:placetype":"locality"
},
  "geometry": {"coordinates":[37.7075,45.22111],"type":"Point"}
}