{
  "type": "Feature",
  "properties": {
    "gn:admin1_code":"63",
    "gn:asciiname":"Dalyr",
    "gn:country_code":"RU",
    "gn:dem":169,
    "gn:feature_class":"P",
    "gn:feature_code":"PPL",
    "gn:name":"Dalyr",
    "gn:population":0,
    "gn:timezone":"Asia/Yakutsk",
    "iso:country":"RU",
    "name:eng_x_preferred":[
        "Dalyr"
    ],
    "name:nor_x_preferred":[
        "Dalyr"
    ],
    "name:rus_x_preferred":[
        "\u0414\u0430\u043b\u044b\u0440"
    ],
    "name:und_x_variant":[
        "\u0414\u0430\u043b\u044b\u0440",
        "Dalyr"
    ],
    "wof:name":"Dalyr",
    "wof:placetype":"locality"
},
  "geometry": {"coordinates":[120.25189,63.86487],"type":"Point"}
}