{
  "type": "Feature",
  "properties": {
    "gn:admin1_code":"51",
    "gn:asciiname":"Zharnava",
    "gn:country_code":"RU",
    "gn:dem":123,
    "gn:feature_class":"P",
    "gn:feature_code":"PPL",
    "gn:name":"Zharnava",
    "gn:population":0,
    "gn:timezone":"Europe/Moscow",
    "iso:country":"RU",
    "name:rus_x_preferred":[
        "\u0416\u0430\u0440\u043d\u0430\u0432\u0430"
    ],
    "name:und_x_variant":[
        "\u0416\u0430\u0440\u043d\u0430\u0432\u0430"
    ],
    "wof:name":"Zharnava",
    "wof:placetype":"locality"
},
  "geometry": {"coordinates":[45.2719,57.7236],"type":"Point"}
}