{
  "type": "Feature",
  "properties": {
    "gn:admin1_code":"6.0",
    "gn:asciiname":"Safronovskaya",
    "gn:country_code":"RU",
    "gn:dem":17,
    "gn:feature_class":"P",
    "gn:feature_code":"PPL",
    "gn:name":"Safronovskaya",
    "gn:population":0,
    "gn:timezone":"Europe/Moscow",
    "iso:country":"RU",
    "name:rus_x_preferred":[
        "\u0421\u0430\u0444\u0440\u043e\u043d\u043e\u0432\u0441\u043a\u0430\u044f"
    ],
    "wof:name":"Safronovskaya",
    "wof:placetype":"locality"
},
  "geometry": {"coordinates":[43.2696,62.7531],"type":"Point"}
}