{
  "type": "Feature",
  "properties": {
    "gn:admin1_code":"53",
    "gn:asciiname":"Putevodnaya Zvezda",
    "gn:country_code":"RU",
    "gn:dem":188,
    "gn:feature_class":"P",
    "gn:feature_code":"PPL",
    "gn:name":"Putevodnaya Zvezda",
    "gn:population":0,
    "gn:timezone":"Asia/Novosibirsk",
    "iso:country":"RU",
    "name:rus_x_preferred":[
        "\u041f\u0443\u0442\u0435\u0432\u043e\u0434\u043d\u0430\u044f \u0417\u0432\u0435\u0437\u0434\u0430"
    ],
    "wof:name":"Putevodnaya Zvezda",
    "wof:placetype":"locality"
},
  "geometry": {"coordinates":[83.76666999999998,54.73333],"type":"Point"}
}