{
  "type": "Feature",
  "properties": {
    "gn:admin1_code":"44",
    "gn:asciiname":"Khatynnakh",
    "gn:country_code":"RU",
    "gn:dem":565,
    "gn:feature_class":"P",
    "gn:feature_code":"PPL",
    "gn:name":"Khatynnakh",
    "gn:population":0,
    "gn:timezone":"Asia/Magadan",
    "iso:country":"RU",
    "name:eng_x_preferred":[
        "Khatynnakh"
    ],
    "name:nor_x_preferred":[
        "Khatyngnakh"
    ],
    "name:rus_x_preferred":[
        "\u0425\u0430\u0442\u044b\u043d\u0433\u043d\u0430\u0445"
    ],
    "name:rus_x_variant":[
        "\u0425\u0430\u0442\u044b\u043d\u043d\u0430\u0445"
    ],
    "name:und_x_variant":[
        "Khat\u00f6nnakh",
        "Khatyngnakh",
        "Khatynnakh",
        "\u0425\u0430\u0442\u044b\u043d\u043d\u0430\u0445"
    ],
    "wof:name":"Khatynnakh",
    "wof:placetype":"locality"
},
  "geometry": {"coordinates":[150.01437000000001,62.72009],"type":"Point"}
}