{
  "type": "Feature",
  "properties": {
    "gn:admin1_code":"90.0",
    "gn:asciiname":"Mitronino",
    "gn:country_code":"RU",
    "gn:dem":147,
    "gn:feature_class":"P",
    "gn:feature_code":"PPL",
    "gn:name":"Mitronino",
    "gn:population":0,
    "gn:timezone":"Asia/Yekaterinburg",
    "iso:country":"RU",
    "name:rus_x_preferred":[
        "\u041c\u0438\u0442\u0440\u043e\u043d\u0438\u043d\u043e"
    ],
    "wof:name":"Mitronino",
    "wof:placetype":"locality"
},
  "geometry": {"coordinates":[55.1823,58.3728],"type":"Point"}
}