{
  "type": "Feature",
  "properties": {
    "gn:admin1_code":"42",
    "gn:asciiname":"Voloshovo",
    "gn:country_code":"RU",
    "gn:dem":66,
    "gn:feature_class":"P",
    "gn:feature_code":"PPL",
    "gn:name":"Voloshovo",
    "gn:population":0,
    "gn:timezone":"Europe/Moscow",
    "iso:country":"RU",
    "name:eng_x_preferred":[
        "Voloshovo"
    ],
    "name:nor_x_preferred":[
        "Volosjovo"
    ],
    "name:rus_x_preferred":[
        "\u0412\u043e\u043b\u043e\u0448\u043e\u0432\u043e"
    ],
    "wof:name":"Voloshovo",
    "wof:placetype":"locality"
},
  "geometry": {"coordinates":[29.30418,58.73274],"type":"Point"}
}