{
  "type": "Feature",
  "properties": {
    "gn:admin1_code":"77",
    "gn:asciiname":"Maloye Ushakovo",
    "gn:country_code":"RU",
    "gn:dem":168,
    "gn:feature_class":"P",
    "gn:feature_code":"PPL",
    "gn:name":"Maloye Ushakovo",
    "gn:population":0,
    "gn:timezone":"Europe/Moscow",
    "iso:country":"RU",
    "name:rus_x_preferred":[
        "\u041c\u0430\u043b\u043e\u0435 \u0423\u0448\u0430\u043a\u043e\u0432\u043e"
    ],
    "wof:name":"Maloye Ushakovo",
    "wof:placetype":"locality"
},
  "geometry": {"coordinates":[35.06667,57.23333],"type":"Point"}
}