{
  "type": "Feature",
  "properties": {
    "gn:admin1_code":"1.0",
    "gn:asciiname":"Sennoy",
    "gn:country_code":"RU",
    "gn:dem":1193,
    "gn:feature_class":"P",
    "gn:feature_code":"PPL",
    "gn:name":"Sennoy",
    "gn:population":0,
    "gn:timezone":"Europe/Moscow",
    "iso:country":"RU",
    "wof:name":"Sennoy",
    "wof:placetype":"locality"
},
  "geometry": {"coordinates":[40.34937,43.87606],"type":"Point"}
}