{
  "type": "Feature",
  "properties": {
    "gn:admin1_code":"55",
    "gn:asciiname":"Poltavskiy",
    "gn:country_code":"RU",
    "gn:dem":134,
    "gn:feature_class":"P",
    "gn:feature_code":"PPL",
    "gn:name":"Poltavskiy",
    "gn:population":0,
    "gn:timezone":"Asia/Yekaterinburg",
    "iso:country":"RU",
    "name:rus_x_preferred":[
        "\u041f\u043e\u043b\u0442\u0430\u0432\u0441\u043a\u0438\u0439"
    ],
    "name:und_x_variant":[
        "\u041f\u043e\u043b\u0442\u0430\u0432\u0441\u043a\u0438\u0439"
    ],
    "wof:name":"Poltavskiy",
    "wof:placetype":"locality"
},
  "geometry": {"coordinates":[53.68333000000001,51.83333],"type":"Point"}
}