{
  "type": "Feature",
  "properties": {
    "gn:admin1_code":"51",
    "gn:asciiname":"Chukhlomka",
    "gn:country_code":"RU",
    "gn:dem":85,
    "gn:feature_class":"P",
    "gn:feature_code":"PPL",
    "gn:name":"Chukhlomka",
    "gn:population":0,
    "gn:timezone":"Europe/Moscow",
    "iso:country":"RU",
    "name:rus_x_preferred":[
        "\u0427\u0443\u0445\u043b\u043e\u043c\u043a\u0430"
    ],
    "wof:name":"Chukhlomka",
    "wof:placetype":"locality"
},
  "geometry": {"coordinates":[45.39792,56.82104],"type":"Point"}
}