{
  "type": "Feature",
  "properties": {
    "gn:admin1_code":"33.0",
    "gn:asciiname":"Bovykiny",
    "gn:country_code":"RU",
    "gn:dem":187,
    "gn:feature_class":"P",
    "gn:feature_code":"PPL",
    "gn:name":"Bovykiny",
    "gn:population":0,
    "gn:timezone":"Europe/Kirov",
    "iso:country":"RU",
    "name:rus_x_preferred":[
        "\u0411\u043e\u0432\u044b\u043a\u0438\u043d\u044b"
    ],
    "name:und_x_variant":[
        "\u0411\u043e\u0432\u044b\u043a\u0438\u043d\u044b"
    ],
    "wof:name":"Bovykiny",
    "wof:placetype":"locality"
},
  "geometry": {"coordinates":[48.45972,59.25722],"type":"Point"}
}