{
  "type": "Feature",
  "properties": {
    "gn:admin1_code":"8",
    "gn:asciiname":"Tan",
    "gn:country_code":"RU",
    "gn:dem":222,
    "gn:feature_class":"P",
    "gn:feature_code":"PPL",
    "gn:name":"Tan",
    "gn:population":0,
    "gn:timezone":"Asia/Yekaterinburg",
    "iso:country":"RU",
    "name:bul_x_preferred":[
        "\u0422\u0430\u043d"
    ],
    "name:ceb_x_preferred":[
        "Tan"
    ],
    "name:ces_x_preferred":[
        "Tan"
    ],
    "name:deu_x_preferred":[
        "Tan"
    ],
    "name:fin_x_preferred":[
        "Tan"
    ],
    "name:frr_x_preferred":[
        "Tan"
    ],
    "name:nld_x_preferred":[
        "Tan"
    ],
    "name:nno_x_preferred":[
        "Tan"
    ],
    "name:nor_x_preferred":[
        "Tan"
    ],
    "name:pol_x_preferred":[
        "Tan"
    ],
    "name:rus_x_preferred":[
        "\u0422\u0430\u043d"
    ],
    "name:swe_x_preferred":[
        "Tan"
    ],
    "name:tur_x_preferred":[
        "Tan"
    ],
    "name:ukr_x_preferred":[
        "\u0422\u0430\u043d"
    ],
    "wof:name":"Tan",
    "wof:placetype":"locality"
},
  "geometry": {"coordinates":[53.8692,54.7142],"type":"Point"}
}