{
  "type": "Feature",
  "properties": {
    "gn:admin1_code":"33.0",
    "gn:asciiname":"Borodiny",
    "gn:country_code":"RU",
    "gn:dem":130,
    "gn:feature_class":"P",
    "gn:feature_code":"PPL",
    "gn:name":"Borodiny",
    "gn:population":0,
    "gn:timezone":"Europe/Kirov",
    "iso:country":"RU",
    "name:rus_x_preferred":[
        "\u0411\u043e\u0440\u043e\u0434\u0438\u043d\u044b"
    ],
    "name:und_x_variant":[
        "\u0411\u043e\u0440\u043e\u0434\u0438\u043d\u044b"
    ],
    "wof:name":"Borodiny",
    "wof:placetype":"locality"
},
  "geometry": {"coordinates":[48.31941,58.33279],"type":"Point"}
}