{
  "type": "Feature",
  "properties": {
    "gn:admin1_code":"62",
    "gn:asciiname":"Kurbatovka",
    "gn:country_code":"RU",
    "gn:dem":146,
    "gn:feature_class":"P",
    "gn:feature_code":"PPL",
    "gn:name":"Kurbatovka",
    "gn:population":0,
    "gn:timezone":"Europe/Moscow",
    "iso:country":"RU",
    "name:rus_x_preferred":[
        "\u041a\u0443\u0440\u0431\u0430\u0442\u043e\u0432\u043a\u0430"
    ],
    "wof:name":"Kurbatovka",
    "wof:placetype":"locality"
},
  "geometry": {"coordinates":[40.6501,53.8377],"type":"Point"}
}