{
  "type": "Feature",
  "properties": {
    "gn:admin1_code":"44",
    "gn:asciiname":"Khatyngnakh",
    "gn:country_code":"RU",
    "gn:dem":497,
    "gn:feature_class":"P",
    "gn:feature_code":"PPL",
    "gn:name":"Khatyngnakh",
    "gn:population":0,
    "gn:timezone":"Asia/Magadan",
    "iso:country":"RU",
    "name:che_x_preferred":[
        "\u0425\u0430\u0442\u044b\u043d\u0433\u043d\u0430\u0445"
    ],
    "name:eng_x_preferred":[
        "Khatyngnakh"
    ],
    "name:nor_x_preferred":[
        "Khatynnakh"
    ],
    "name:rus_x_preferred":[
        "\u0425\u0430\u0442\u044b\u043d\u043d\u0430\u0445"
    ],
    "name:rus_x_variant":[
        "\u0425\u0430\u0442\u044b\u043d\u0433\u043d\u0430\u0445"
    ],
    "name:und_x_variant":[
        "Khatynnakh",
        "Khatyngnakh",
        "\u0425\u0430\u0442\u044b\u043d\u0433\u043d\u0430\u0445"
    ],
    "wof:name":"Khatyngnakh",
    "wof:placetype":"locality"
},
  "geometry": {"coordinates":[148.14826000000005,62.03178000000001],"type":"Point"}
}