{
  "type": "Feature",
  "properties": {
    "gn:admin1_code":"68.0",
    "gn:asciiname":"Tli",
    "gn:country_code":"RU",
    "gn:dem":1891,
    "gn:feature_class":"P",
    "gn:feature_code":"PPL",
    "gn:name":"Tli",
    "gn:population":0,
    "gn:timezone":"Europe/Moscow",
    "iso:country":"RU",
    "wof:name":"Tli",
    "wof:placetype":"locality"
},
  "geometry": {"coordinates":[43.8954,42.66511],"type":"Point"}
}