{
  "type": "Feature",
  "properties": {
    "gn:admin1_code":"60",
    "gn:asciiname":"Shumenets",
    "gn:country_code":"RU",
    "gn:dem":188,
    "gn:feature_class":"P",
    "gn:feature_code":"PPL",
    "gn:name":"Shumenets",
    "gn:population":0,
    "gn:timezone":"Europe/Moscow",
    "iso:country":"RU",
    "name:rus_x_preferred":[
        "\u0428\u0443\u043c\u0435\u043d\u0435\u0446"
    ],
    "name:und_x_variant":[
        "\u0428\u0443\u043c\u0435\u043d\u0435\u0446"
    ],
    "wof:name":"Shumenets",
    "wof:placetype":"locality"
},
  "geometry": {"coordinates":[29.4194,56.4018],"type":"Point"}
}