{
  "type": "Feature",
  "properties": {
    "gn:admin1_code":"37",
    "gn:asciiname":"Koshkino",
    "gn:country_code":"RU",
    "gn:dem":192,
    "gn:feature_class":"P",
    "gn:feature_code":"PPL",
    "gn:name":"Koshkino",
    "gn:population":0,
    "gn:timezone":"Europe/Moscow",
    "iso:country":"RU",
    "name:rus_x_preferred":[
        "\u041a\u043e\u0448\u043a\u0438\u043d\u043e"
    ],
    "wof:name":"Koshkino",
    "wof:placetype":"locality"
},
  "geometry": {"coordinates":[43.6281,58.6894],"type":"Point"}
}