{
  "type": "Feature",
  "properties": {
    "gn:admin1_code":"90",
    "gn:asciiname":"Odina",
    "gn:country_code":"RU",
    "gn:dem":92,
    "gn:feature_class":"P",
    "gn:feature_code":"PPL",
    "gn:name":"Odina",
    "gn:population":0,
    "gn:timezone":"Asia/Yekaterinburg",
    "iso:country":"RU",
    "name:ceb_x_preferred":[
        "Odina"
    ],
    "name:nld_x_preferred":[
        "Odina"
    ],
    "name:nor_x_preferred":[
        "Odina"
    ],
    "name:rus_x_preferred":[
        "\u041e\u0434\u0438\u043d\u0430"
    ],
    "name:swe_x_preferred":[
        "Odina"
    ],
    "name:vie_x_preferred":[
        "Odina"
    ],
    "name:war_x_preferred":[
        "Odina"
    ],
    "wof:name":"Odina",
    "wof:placetype":"locality"
},
  "geometry": {"coordinates":[55.6803,58.0222],"type":"Point"}
}