{
  "type": "Feature",
  "properties": {
    "gn:admin1_code":"37",
    "gn:asciiname":"Lukina Gora",
    "gn:country_code":"RU",
    "gn:dem":171,
    "gn:feature_class":"P",
    "gn:feature_code":"PPL",
    "gn:name":"Lukina Gora",
    "gn:population":0,
    "gn:timezone":"Europe/Moscow",
    "iso:country":"RU",
    "name:rus_x_preferred":[
        "\u041b\u0443\u043a\u0438\u043d\u0430 \u0413\u043e\u0440\u0430"
    ],
    "wof:name":"Lukina Gora",
    "wof:placetype":"locality"
},
  "geometry": {"coordinates":[46.2309,58.941],"type":"Point"}
}