{
  "type": "Feature",
  "properties": {
    "gn:admin1_code":"85.0",
    "gn:asciiname":"Gerasimovo",
    "gn:country_code":"RU",
    "gn:dem":168,
    "gn:feature_class":"P",
    "gn:feature_code":"PPL",
    "gn:name":"Gerasimovo",
    "gn:population":0,
    "gn:timezone":"Europe/Moscow",
    "iso:country":"RU",
    "name:rus_x_preferred":[
        "\u0413\u0435\u0440\u0430\u0441\u0438\u043c\u043e\u0432\u043e"
    ],
    "wof:name":"Gerasimovo",
    "wof:placetype":"locality"
},
  "geometry": {"coordinates":[40.78022,58.78701],"type":"Point"}
}