{
  "type": "Feature",
  "properties": {
    "gn:admin1_code":"67",
    "gn:asciiname":"Oroshayemyy",
    "gn:country_code":"RU",
    "gn:dem":33,
    "gn:feature_class":"P",
    "gn:feature_code":"PPL",
    "gn:name":"Oroshayemyy",
    "gn:population":0,
    "gn:timezone":"Europe/Saratov",
    "iso:country":"RU",
    "name:rus_x_preferred":[
        "\u041e\u0440\u043e\u0448\u0430\u0435\u043c\u044b\u0439"
    ],
    "wof:name":"Oroshayemyy",
    "wof:placetype":"locality"
},
  "geometry": {"coordinates":[49.3245,52.0921],"type":"Point"}
}