{
  "type": "Feature",
  "properties": {
    "gn:admin1_code":"77.0",
    "gn:asciiname":"Bystri",
    "gn:country_code":"RU",
    "gn:dem":235,
    "gn:feature_class":"P",
    "gn:feature_code":"PPL",
    "gn:name":"Bystri",
    "gn:population":0,
    "gn:timezone":"Europe/Moscow",
    "iso:country":"RU",
    "name:eng_x_preferred":[
        "Bystri"
    ],
    "name:nor_x_preferred":[
        "Bystri"
    ],
    "name:rus_x_preferred":[
        "\u0411\u044b\u0441\u0442\u0440\u0438"
    ],
    "wof:name":"Bystri",
    "wof:placetype":"locality"
},
  "geometry": {"coordinates":[32.10766,56.8428],"type":"Point"}
}