{
  "type": "Feature",
  "properties": {
    "gn:admin1_code":"71",
    "gn:asciiname":"Simonyata",
    "gn:country_code":"RU",
    "gn:dem":268,
    "gn:feature_class":"P",
    "gn:feature_code":"PPL",
    "gn:name":"Simonyata",
    "gn:population":0,
    "gn:timezone":"Asia/Yekaterinburg",
    "iso:country":"RU",
    "name:eng_x_preferred":[
        "Simonyata"
    ],
    "name:nor_x_preferred":[
        "Simonjata"
    ],
    "name:rus_x_preferred":[
        "\u0421\u0438\u043c\u043e\u043d\u044f\u0442\u0430"
    ],
    "name:und_x_variant":[
        "Rechka",
        "\u0421\u0438\u043c\u043e\u043d\u044f\u0442\u0430",
        "Simonyata"
    ],
    "wof:name":"Simonyata",
    "wof:placetype":"locality"
},
  "geometry": {"coordinates":[58.24584,57.52291999999999],"type":"Point"}
}