{
  "type": "Feature",
  "properties": {
    "gn:admin1_code":"77",
    "gn:asciiname":"Zoby",
    "gn:country_code":"RU",
    "gn:dem":139,
    "gn:feature_class":"P",
    "gn:feature_code":"PPL",
    "gn:name":"Zoby",
    "gn:population":0,
    "gn:timezone":"Europe/Moscow",
    "iso:country":"RU",
    "name:rus_x_preferred":[
        "\u0417\u043e\u0431\u044b"
    ],
    "wof:name":"Zoby",
    "wof:placetype":"locality"
},
  "geometry": {"coordinates":[36.7149,57.7343],"type":"Point"}
}