{
  "type": "Feature",
  "properties": {
    "gn:admin1_code":"60",
    "gn:asciiname":"Vlaskovo",
    "gn:country_code":"RU",
    "gn:dem":247,
    "gn:feature_class":"P",
    "gn:feature_code":"PPL",
    "gn:name":"Vlaskovo",
    "gn:population":0,
    "gn:timezone":"Europe/Moscow",
    "iso:country":"RU",
    "name:rus_x_preferred":[
        "\u0412\u043b\u0430\u0441\u043a\u043e\u0432\u043e"
    ],
    "wof:name":"Vlaskovo",
    "wof:placetype":"locality"
},
  "geometry": {"coordinates":[29.4187,56.8505],"type":"Point"}
}