{
  "type": "Feature",
  "properties": {
    "gn:admin1_code":"69",
    "gn:asciiname":"Salova",
    "gn:country_code":"RU",
    "gn:dem":210,
    "gn:feature_class":"P",
    "gn:feature_code":"PPL",
    "gn:name":"Salova",
    "gn:population":0,
    "gn:timezone":"Europe/Moscow",
    "iso:country":"RU",
    "name:rus_x_preferred":[
        "\u0421\u0430\u043b\u043e\u0432\u0430"
    ],
    "wof:name":"Salova",
    "wof:placetype":"locality"
},
  "geometry": {"coordinates":[32.94722,53.84861],"type":"Point"}
}