{
  "type": "Feature",
  "properties": {
    "gn:admin1_code":"56",
    "gn:asciiname":"Lobanovo",
    "gn:country_code":"RU",
    "gn:dem":217,
    "gn:feature_class":"P",
    "gn:feature_code":"PPL",
    "gn:name":"Lobanovo",
    "gn:population":0,
    "gn:timezone":"Europe/Moscow",
    "iso:country":"RU",
    "name:rus_x_preferred":[
        "\u041b\u043e\u0431\u0430\u043d\u043e\u0432\u043e"
    ],
    "name:und_x_variant":[
        "\u041b\u043e\u0431\u0430\u043d\u043e\u0432\u043e"
    ],
    "wof:name":"Lobanovo",
    "wof:placetype":"locality"
},
  "geometry": {"coordinates":[35.35,52.38333],"type":"Point"}
}