{
  "type": "Feature",
  "properties": {
    "gn:admin1_code":"33.0",
    "gn:asciiname":"Shchennikovy",
    "gn:country_code":"RU",
    "gn:dem":145,
    "gn:feature_class":"P",
    "gn:feature_code":"PPL",
    "gn:name":"Shchennikovy",
    "gn:population":0,
    "gn:timezone":"Europe/Kirov",
    "iso:country":"RU",
    "name:rus_x_preferred":[
        "\u0429\u0435\u043d\u043d\u0438\u043a\u043e\u0432\u044b"
    ],
    "name:und_x_variant":[
        "\u0429\u0435\u043d\u043d\u0438\u043a\u043e\u0432\u044b"
    ],
    "wof:name":"Shchennikovy",
    "wof:placetype":"locality"
},
  "geometry": {"coordinates":[48.21888,58.43373],"type":"Point"}
}