{
  "type": "Feature",
  "properties": {
    "gn:admin1_code":"78",
    "gn:asciiname":"Yevsino",
    "gn:country_code":"RU",
    "gn:dem":97,
    "gn:feature_class":"P",
    "gn:feature_code":"PPL",
    "gn:name":"Yevsino",
    "gn:population":0,
    "gn:timezone":"Asia/Yekaterinburg",
    "iso:country":"RU",
    "name:eng_x_preferred":[
        "Yevsino"
    ],
    "name:nor_x_preferred":[
        "Jevsino"
    ],
    "name:rus_x_preferred":[
        "\u0415\u0432\u0441\u0438\u043d\u043e"
    ],
    "wof:name":"Yevsino",
    "wof:placetype":"locality"
},
  "geometry": {"coordinates":[68.28825000000001,56.70607],"type":"Point"}
}