{
  "type": "Feature",
  "properties": {
    "gn:admin1_code":"77",
    "gn:asciiname":"Kolyubeyevo",
    "gn:country_code":"RU",
    "gn:dem":125,
    "gn:feature_class":"P",
    "gn:feature_code":"PPL",
    "gn:name":"Kolyubeyevo",
    "gn:population":0,
    "gn:timezone":"Europe/Moscow",
    "iso:country":"RU",
    "name:rus_x_preferred":[
        "\u041a\u043e\u043b\u044e\u0431\u0435\u0435\u0432\u043e"
    ],
    "wof:name":"Kolyubeyevo",
    "wof:placetype":"locality"
},
  "geometry": {"coordinates":[37.0089,57.2823],"type":"Point"}
}