{
  "type": "Feature",
  "properties": {
    "gn:admin1_code":"25.0",
    "gn:asciiname":"Timofeyevka",
    "gn:country_code":"RU",
    "gn:dem":174,
    "gn:feature_class":"P",
    "gn:feature_code":"PPL",
    "gn:name":"Timofeyevka",
    "gn:population":0,
    "gn:timezone":"Europe/Moscow",
    "iso:country":"RU",
    "wof:name":"Timofeyevka",
    "wof:placetype":"locality"
},
  "geometry": {"coordinates":[36.6032,54.43426],"type":"Point"}
}