{
  "type": "Feature",
  "properties": {
    "gn:admin1_code":"9.0",
    "gn:asciiname":"Kugutki",
    "gn:country_code":"RU",
    "gn:dem":200,
    "gn:feature_class":"P",
    "gn:feature_code":"PPL",
    "gn:name":"Kugutki",
    "gn:population":0,
    "gn:timezone":"Europe/Moscow",
    "iso:country":"RU",
    "name:rus_x_preferred":[
        "\u041a\u0443\u0433\u0443\u0442\u043a\u0438"
    ],
    "name:und_x_variant":[
        "\u041a\u0443\u0433\u0443\u0442\u043a\u0438"
    ],
    "wof:name":"Kugutki",
    "wof:placetype":"locality"
},
  "geometry": {"coordinates":[37.1229,50.94115],"type":"Point"}
}