{
  "type": "Feature",
  "properties": {
    "gn:admin1_code":"33.0",
    "gn:asciiname":"Shishkari",
    "gn:country_code":"RU",
    "gn:dem":193,
    "gn:feature_class":"P",
    "gn:feature_code":"PPL",
    "gn:name":"Shishkari",
    "gn:population":0,
    "gn:timezone":"Europe/Kirov",
    "iso:country":"RU",
    "name:rus_x_preferred":[
        "\u0428\u0438\u0448\u043a\u0430\u0440\u0438"
    ],
    "name:und_x_variant":[
        "\u0428\u0438\u0448\u043a\u0430\u0440\u0438"
    ],
    "wof:name":"Shishkari",
    "wof:placetype":"locality"
},
  "geometry": {"coordinates":[49.01321,59.34767],"type":"Point"}
}