{
  "type": "Feature",
  "properties": {
    "gn:admin1_code":"43",
    "gn:asciiname":"Put' Pakharya",
    "gn:country_code":"RU",
    "gn:dem":105,
    "gn:feature_class":"P",
    "gn:feature_code":"PPL",
    "gn:name":"Put\u2019 Pakharya",
    "gn:population":0,
    "gn:timezone":"Europe/Moscow",
    "iso:country":"RU",
    "name:rus_x_preferred":[
        "\u041f\u0443\u0442\u044c \u041f\u0430\u0445\u0430\u0440\u044f"
    ],
    "name:und_x_variant":[
        "Put\u2019 Pakharya",
        "\u041f\u0443\u0442\u044c \u041f\u0430\u0445\u0430\u0440\u044f"
    ],
    "wof:name":"Put' Pakharya",
    "wof:placetype":"locality"
},
  "geometry": {"coordinates":[39.76667,52.58333],"type":"Point"}
}