{
  "type": "Feature",
  "properties": {
    "gn:admin1_code":"55",
    "gn:asciiname":"Vlasovka",
    "gn:country_code":"RU",
    "gn:dem":276,
    "gn:feature_class":"P",
    "gn:feature_code":"PPL",
    "gn:name":"Vlasovka",
    "gn:population":0,
    "gn:timezone":"Asia/Yekaterinburg",
    "iso:country":"RU",
    "name:rus_x_preferred":[
        "\u0412\u043b\u0430\u0441\u043e\u0432\u043a\u0430"
    ],
    "wof:name":"Vlasovka",
    "wof:placetype":"locality"
},
  "geometry": {"coordinates":[54.26667,52.05],"type":"Point"}
}