{
  "type": "Feature",
  "properties": {
    "gn:admin1_code":"37",
    "gn:asciiname":"Babino",
    "gn:country_code":"RU",
    "gn:dem":156,
    "gn:feature_class":"P",
    "gn:feature_code":"PPL",
    "gn:name":"Babino",
    "gn:population":0,
    "gn:timezone":"Europe/Moscow",
    "iso:country":"RU",
    "name:rus_x_preferred":[
        "\u0411\u0430\u0431\u0438\u043d\u043e"
    ],
    "name:und_x_variant":[
        "\u0411\u0430\u0431\u0438\u043d\u043e"
    ],
    "wof:name":"Babino",
    "wof:placetype":"locality"
},
  "geometry": {"coordinates":[43.6556,58.0794],"type":"Point"}
}