{
  "type": "Feature",
  "properties": {
    "gn:admin1_code":"57",
    "gn:asciiname":"Pleshcheyevka",
    "gn:country_code":"RU",
    "gn:dem":162,
    "gn:feature_class":"P",
    "gn:feature_code":"PPL",
    "gn:name":"Pleshcheyevka",
    "gn:population":0,
    "gn:timezone":"Europe/Moscow",
    "iso:country":"RU",
    "name:eng_x_preferred":[
        "Pleshch\u00ebvka"
    ],
    "name:nor_x_preferred":[
        "Plesjtsjejevka"
    ],
    "name:rus_x_preferred":[
        "\u041f\u043b\u0435\u0449\u0435\u0435\u0432\u043a\u0430"
    ],
    "name:und_x_variant":[
        "Pleshcheyevka"
    ],
    "wof:name":"Pleshcheyevka",
    "wof:placetype":"locality"
},
  "geometry": {"coordinates":[44.41225,52.66654000000001],"type":"Point"}
}