{
  "type": "Feature",
  "properties": {
    "gn:admin1_code":"69",
    "gn:asciiname":"Mignovichi",
    "gn:country_code":"RU",
    "gn:dem":170,
    "gn:feature_class":"P",
    "gn:feature_code":"PPL",
    "gn:name":"Mignovichi",
    "gn:population":0,
    "gn:timezone":"Europe/Moscow",
    "iso:country":"RU",
    "name:rus_x_preferred":[
        "\u041c\u0438\u0433\u043d\u043e\u0432\u0438\u0447\u0438"
    ],
    "wof:name":"Mignovichi",
    "wof:placetype":"locality"
},
  "geometry": {"coordinates":[31.56778,54.26221999999999],"type":"Point"}
}