{
  "type": "Feature",
  "properties": {
    "gn:admin1_code":"45.0",
    "gn:asciiname":"Yel'sukovo",
    "gn:country_code":"RU",
    "gn:dem":142,
    "gn:feature_class":"P",
    "gn:feature_code":"PPL",
    "gn:name":"Yel\u2019sukovo",
    "gn:population":0,
    "gn:timezone":"Europe/Moscow",
    "iso:country":"RU",
    "name:rus_x_preferred":[
        "\u0415\u043b\u044c\u0441\u0443\u043a\u043e\u0432\u043e"
    ],
    "name:und_x_variant":[
        "Yel\u2019sukovo"
    ],
    "wof:name":"Yel'sukovo",
    "wof:placetype":"locality"
},
  "geometry": {"coordinates":[49.73326,56.70292],"type":"Point"}
}