{
  "type": "Feature",
  "properties": {
    "gn:admin1_code":"47",
    "gn:asciiname":"Dedovo-Talyzino",
    "gn:country_code":"RU",
    "gn:dem":226,
    "gn:feature_class":"P",
    "gn:feature_code":"PPL",
    "gn:name":"Dedovo-Talyzino",
    "gn:population":0,
    "gn:timezone":"Europe/Moscow",
    "iso:country":"RU",
    "name:rus_x_preferred":[
        "\u0414\u0435\u0434\u043e\u0432\u043e"
    ],
    "name:und_x_variant":[
        "Dedovo",
        "\u0414\u0435\u0434\u043e\u0432\u043e",
        "Dedovo-Talyzino"
    ],
    "wof:name":"Dedovo-Talyzino",
    "wof:placetype":"locality"
},
  "geometry": {"coordinates":[37.09444000000001,55.91911999999999],"type":"Point"}
}