{
  "type": "Feature",
  "properties": {
    "gn:admin1_code":"91",
    "gn:asciiname":"Kochenyata",
    "gn:cc2":"RU",
    "gn:country_code":"RU",
    "gn:dem":486,
    "gn:feature_class":"P",
    "gn:feature_code":"PPL",
    "gn:name":"Kochenyata",
    "gn:population":0,
    "gn:timezone":"Asia/Krasnoyarsk",
    "iso:country":"RU",
    "name:rus_x_preferred":[
        "\u041a\u043e\u0447\u0435\u043d\u044f\u0442\u0430"
    ],
    "name:und_x_variant":[
        "Kochemyata",
        "Kochenyata"
    ],
    "wof:name":"Kochenyata",
    "wof:placetype":"locality"
},
  "geometry": {"coordinates":[94.18333,61.85],"type":"Point"}
}