{
  "type": "Feature",
  "properties": {
    "gn:admin1_code":"75",
    "gn:asciiname":"Orlovka",
    "gn:country_code":"RU",
    "gn:dem":76,
    "gn:feature_class":"P",
    "gn:feature_code":"PPL",
    "gn:name":"Orlovka",
    "gn:population":0,
    "gn:timezone":"Asia/Tomsk",
    "iso:country":"RU",
    "name:eng_x_preferred":[
        "Orlovka"
    ],
    "name:nor_x_preferred":[
        "Orlovka"
    ],
    "name:rus_x_preferred":[
        "\u041e\u0440\u043b\u043e\u0432\u043a\u0430"
    ],
    "wof:name":"Orlovka",
    "wof:placetype":"locality"
},
  "geometry": {"coordinates":[84.64725,56.81291],"type":"Point"}
}