{
  "type": "Feature",
  "properties": {
    "gn:admin1_code":"33.0",
    "gn:asciiname":"Rublevo",
    "gn:country_code":"RU",
    "gn:dem":146,
    "gn:feature_class":"P",
    "gn:feature_code":"PPL",
    "gn:name":"Rubl\u00ebvo",
    "gn:population":0,
    "gn:timezone":"Europe/Kirov",
    "iso:country":"RU",
    "name:rus_x_preferred":[
        "\u0420\u0443\u0431\u043b\u0451\u0432\u043e"
    ],
    "name:und_x_variant":[
        "Rubl\u00ebvo"
    ],
    "wof:name":"Rublevo",
    "wof:placetype":"locality"
},
  "geometry": {"coordinates":[49.43789,58.48964],"type":"Point"}
}