{
  "type": "Feature",
  "properties": {
    "gn:admin1_code":"81.0",
    "gn:asciiname":"Bol'shoye Zherebyatnikovo",
    "gn:country_code":"RU",
    "gn:dem":218,
    "gn:feature_class":"P",
    "gn:feature_code":"PPL",
    "gn:name":"Bol\u2019shoye Zherebyatnikovo",
    "gn:population":0,
    "gn:timezone":"Europe/Ulyanovsk",
    "iso:country":"RU",
    "name:rus_x_preferred":[
        "\u0411\u043e\u043b\u044c\u0448\u043e\u0435 \u0416\u0435\u0440\u0435\u0431\u044f\u0442\u043d\u0438\u043a\u043e\u0432\u043e"
    ],
    "name:und_x_variant":[
        "Bol\u2019shoye Zherebyatnikovo",
        "\u0411\u043e\u043b\u044c\u0448\u043e\u0435 \u0416\u0435\u0440\u0435\u0431\u044f\u0442\u043d\u0438\u043a\u043e\u0432\u043e"
    ],
    "wof:name":"Bol'shoye Zherebyatnikovo",
    "wof:placetype":"locality"
},
  "geometry": {"coordinates":[47.529,54.1644],"type":"Point"}
}