{
  "type": "Feature",
  "properties": {
    "gn:admin1_code":"10",
    "gn:asciiname":"Klinok",
    "gn:country_code":"RU",
    "gn:dem":165,
    "gn:feature_class":"P",
    "gn:feature_code":"PPL",
    "gn:name":"Klinok",
    "gn:population":0,
    "gn:timezone":"Europe/Moscow",
    "iso:country":"RU",
    "name:rus_x_preferred":[
        "\u041a\u043b\u0438\u043d\u043e\u043a"
    ],
    "name:und_x_variant":[
        "\u041a\u043b\u0438\u043d\u043e\u043a"
    ],
    "wof:name":"Klinok",
    "wof:placetype":"locality"
},
  "geometry": {"coordinates":[34.0838,53.12067],"type":"Point"}
}