{
  "type": "Feature",
  "properties": {
    "gn:admin1_code":"41.0",
    "gn:asciiname":"Chaplygino",
    "gn:country_code":"RU",
    "gn:dem":178,
    "gn:feature_class":"P",
    "gn:feature_code":"PPL",
    "gn:name":"Chaplygino",
    "gn:population":0,
    "gn:timezone":"Europe/Moscow",
    "iso:country":"RU",
    "name:rus_x_preferred":[
        "\u0427\u0430\u043f\u043b\u044b\u0433\u0438\u043d\u043e"
    ],
    "wof:name":"Chaplygino",
    "wof:placetype":"locality"
},
  "geometry": {"coordinates":[35.83333,52.08333],"type":"Point"}
}