{
  "type": "Feature",
  "properties": {
    "gn:admin1_code":"60",
    "gn:asciiname":"Tomsino",
    "gn:country_code":"RU",
    "gn:dem":143,
    "gn:feature_class":"P",
    "gn:feature_code":"PPL",
    "gn:name":"Tomsino",
    "gn:population":0,
    "gn:timezone":"Europe/Moscow",
    "iso:country":"RU",
    "name:rus_x_preferred":[
        "\u0422\u043e\u043c\u0441\u0438\u043d\u043e"
    ],
    "wof:name":"Tomsino",
    "wof:placetype":"locality"
},
  "geometry": {"coordinates":[28.7057,56.0547],"type":"Point"}
}