{
  "type": "Feature",
  "properties": {
    "gn:admin1_code":"17",
    "gn:asciiname":"Orada Chugli",
    "gn:country_code":"RU",
    "gn:dem":1539,
    "gn:feature_class":"P",
    "gn:feature_code":"PPL",
    "gn:name":"Orada Chugli",
    "gn:population":0,
    "gn:timezone":"Europe/Moscow",
    "iso:country":"RU",
    "name:rus_x_preferred":[
        "\u041e\u0440\u0430\u0434\u0430 \u0427\u0443\u0433\u043b\u0438"
    ],
    "name:und_x_variant":[
        "Chogly",
        "Chugli",
        "Orada Chugli"
    ],
    "wof:name":"Orada Chugli",
    "wof:placetype":"locality"
},
  "geometry": {"coordinates":[47.22264000000001,42.49384000000001],"type":"Point"}
}