{
  "type": "Feature",
  "properties": {
    "gn:admin1_code":"9",
    "gn:asciiname":"Oktyabr'skaya Gotnya",
    "gn:country_code":"RU",
    "gn:dem":155,
    "gn:feature_class":"P",
    "gn:feature_code":"PPL",
    "gn:name":"Oktyabr\u2019skaya Gotnya",
    "gn:population":0,
    "gn:timezone":"Europe/Moscow",
    "iso:country":"RU",
    "name:rus_x_preferred":[
        "\u041e\u043a\u0442\u044f\u0431\u0440\u044c\u0441\u043a\u0430\u044f \u0413\u043e\u0442\u043d\u044f"
    ],
    "name:und_x_variant":[
        "Monastyrskaya Gotnya",
        "Oktyabr\u2019skaya",
        "Oktyabr\u2019skaya Gotnya",
        "\u041e\u043a\u0442\u044f\u0431\u0440\u044c\u0441\u043a\u0430\u044f \u0413\u043e\u0442\u043d\u044f",
        "Gotnya"
    ],
    "wof:name":"Oktyabr'skaya Gotnya",
    "wof:placetype":"locality"
},
  "geometry": {"coordinates":[35.89944000000001,50.65611],"type":"Point"}
}