{
  "type": "Feature",
  "properties": {
    "gn:admin1_code":"73",
    "gn:asciiname":"Malalla",
    "gn:country_code":"RU",
    "gn:dem":54,
    "gn:feature_class":"P",
    "gn:feature_code":"PPL",
    "gn:name":"Malalla",
    "gn:population":0,
    "gn:timezone":"Europe/Moscow",
    "iso:country":"RU",
    "name:rus_x_preferred":[
        "\u041c\u0430\u043b\u0430\u043b\u043b\u0430"
    ],
    "wof:name":"Malalla",
    "wof:placetype":"locality"
},
  "geometry": {"coordinates":[48.5405,55.4393],"type":"Point"}
}