{
  "type": "Feature",
  "properties": {
    "gn:admin1_code":"72.0",
    "gn:asciiname":"Antsifrovo",
    "gn:country_code":"RU",
    "gn:dem":138,
    "gn:feature_class":"P",
    "gn:feature_code":"PPL",
    "gn:name":"Antsifrovo",
    "gn:population":0,
    "gn:timezone":"Europe/Moscow",
    "iso:country":"RU",
    "name:nor_x_preferred":[
        "Antsifrovo"
    ],
    "name:rus_x_preferred":[
        "\u0410\u043d\u0446\u0438\u0444\u0440\u043e\u0432\u043e"
    ],
    "name:und_x_variant":[
        "Antsiforovo"
    ],
    "wof:name":"Antsifrovo",
    "wof:placetype":"locality"
},
  "geometry": {"coordinates":[40.65083,52.54389000000001],"type":"Point"}
}