{
  "type": "Feature",
  "properties": {
    "gn:admin1_code":"73",
    "gn:asciiname":"Kanash",
    "gn:country_code":"RU",
    "gn:dem":123,
    "gn:feature_class":"P",
    "gn:feature_code":"PPL",
    "gn:name":"Kanash",
    "gn:population":0,
    "gn:timezone":"Europe/Moscow",
    "iso:country":"RU",
    "name:rus_x_preferred":[
        "\u041a\u0430\u043d\u0430\u0448"
    ],
    "name:und_x_variant":[
        "Karmalka",
        "\u041a\u0430\u043d\u0430\u0448"
    ],
    "wof:name":"Kanash",
    "wof:placetype":"locality"
},
  "geometry": {"coordinates":[51.85278,55.2055],"type":"Point"}
}