{
  "type": "Feature",
  "properties": {
    "gn:admin1_code":"73",
    "gn:asciiname":"Kanash",
    "gn:country_code":"RU",
    "gn:dem":123,
    "gn:feature_class":"P",
    "gn:feature_code":"PPL",
    "gn:name":"Kanash",
    "gn:population":0,
    "gn:timezone":"Europe/Moscow",
    "iso:country":"RU",
    "name:ara_x_preferred":[
        "\u0643\u0627\u0646\u0627\u0634"
    ],
    "name:azb_x_preferred":[
        "\u06a9\u0627\u0646\u0627\u0634"
    ],
    "name:bel_x_preferred":[
        "\u041a\u0430\u043d\u0430\u0448"
    ],
    "name:bul_x_preferred":[
        "\u041a\u0430\u043d\u0430\u0448"
    ],
    "name:ceb_x_preferred":[
        "Kanash"
    ],
    "name:ces_x_preferred":[
        "Kana\u0161"
    ],
    "name:chv_x_preferred":[
        "\u041a\u0430\u043d\u0430\u0448"
    ],
    "name:deu_x_preferred":[
        "Kanasch"
    ],
    "name:epo_x_preferred":[
        "Kana\u015d"
    ],
    "name:est_x_preferred":[
        "Kana\u0161"
    ],
    "name:eus_x_preferred":[
        "Kanax"
    ],
    "name:fas_x_preferred":[
        "\u06a9\u0627\u0646\u0627\u0634"
    ],
    "name:fin_x_preferred":[
        "Kana\u0161"
    ],
    "name:fra_x_preferred":[
        "Kanach"
    ],
    "name:hrv_x_preferred":[
        "Kana\u0161"
    ],
    "name:hsb_x_preferred":[
        "Kana\u0161"
    ],
    "name:ita_x_preferred":[
        "Kana\u0161"
    ],
    "name:kor_x_preferred":[
        "\uce74\ub098\uc2dc"
    ],
    "name:mhr_x_preferred":[
        "\u041a\u0430\u04a5\u0430\u0448"
    ],
    "name:myv_x_preferred":[
        "\u041a\u0430\u043d\u0430\u0448 \u043e\u0448"
    ],
    "name:nld_x_preferred":[
        "Kanasj"
    ],
    "name:nno_x_preferred":[
        "Kanasj"
    ],
    "name:nor_x_preferred":[
        "Kanasj"
    ],
    "name:oss_x_preferred":[
        "\u041a\u0430\u043d\u0430\u0448"
    ],
    "name:pnb_x_preferred":[
        "\u06a9\u0627\u0646\u0627\u0634"
    ],
    "name:pol_x_preferred":[
        "Kanasz"
    ],
    "name:ron_x_preferred":[
        "Kanash"
    ],
    "name:rus_x_preferred":[
        "\u041a\u0430\u043d\u0430\u0448"
    ],
    "name:srp_x_preferred":[
        "\u041a\u0430\u043d\u0430\u0448"
    ],
    "name:swe_x_preferred":[
        "Kanasj"
    ],
    "name:tat_x_preferred":[
        "\u041a\u0430\u043d\u0430\u0448"
    ],
    "name:tgl_x_preferred":[
        "Kanash"
    ],
    "name:tur_x_preferred":[
        "Kana\u015f"
    ],
    "name:ukr_x_preferred":[
        "\u041a\u0430\u043d\u0430\u0448"
    ],
    "name:und_x_variant":[
        "Karmalka"
    ],
    "name:vep_x_preferred":[
        "Kana\u0161"
    ],
    "name:vie_x_preferred":[
        "Kanash"
    ],
    "name:war_x_preferred":[
        "Kanash"
    ],
    "name:zho_x_preferred":[
        "\u5361\u7d0d\u4ec0"
    ],
    "wof:name":"Kanash",
    "wof:placetype":"locality"
},
  "geometry": {"coordinates":[51.85278,55.2055],"type":"Point"}
}