{
  "type": "Feature",
  "properties": {
    "gn:admin1_code":"59",
    "gn:asciiname":"Krasnyy Yar",
    "gn:country_code":"RU",
    "gn:dem":138,
    "gn:feature_class":"P",
    "gn:feature_code":"PPL",
    "gn:name":"Krasnyy Yar",
    "gn:population":0,
    "gn:timezone":"Asia/Vladivostok",
    "iso:country":"RU",
    "name:eng_x_preferred":[
        "Krasnyy Yar"
    ],
    "name:nor_x_preferred":[
        "Krasnyj Jar"
    ],
    "name:rus_x_preferred":[
        "\u041a\u0440\u0430\u0441\u043d\u044b\u0439 \u042f\u0440"
    ],
    "wof:name":"Krasnyy Yar",
    "wof:placetype":"locality"
},
  "geometry": {"coordinates":[135.36099999999999,46.54139],"type":"Point"}
}