{
  "type": "Feature",
  "properties": {
    "gn:admin1_code":"77",
    "gn:asciiname":"Mogilki",
    "gn:country_code":"RU",
    "gn:dem":160,
    "gn:feature_class":"P",
    "gn:feature_code":"PPL",
    "gn:name":"Mogilki",
    "gn:population":0,
    "gn:timezone":"Europe/Moscow",
    "iso:country":"RU",
    "name:rus_x_preferred":[
        "\u041c\u043e\u0433\u0438\u043b\u043a\u0438"
    ],
    "name:und_x_variant":[
        "\u041c\u043e\u0433\u0438\u043b\u043a\u0438"
    ],
    "wof:name":"Mogilki",
    "wof:placetype":"locality"
},
  "geometry": {"coordinates":[35.88344,57.33127],"type":"Point"}
}