{
  "type": "Feature",
  "properties": {
    "gn:admin1_code":"32",
    "gn:asciiname":"Nyagyn'",
    "gn:country_code":"RU",
    "gn:dem":36,
    "gn:feature_class":"P",
    "gn:feature_code":"PPL",
    "gn:name":"Nyagyn\u2019",
    "gn:population":0,
    "gn:timezone":"Asia/Yekaterinburg",
    "iso:country":"RU",
    "name:rus_x_preferred":[
        "\u041d\u044f\u0433\u044b\u043d\u044c"
    ],
    "name:und_x_variant":[
        "Nyagyn\u2019",
        "\u041d\u044f\u0433\u044b\u043d\u044c"
    ],
    "wof:name":"Nyagyn'",
    "wof:placetype":"locality"
},
  "geometry": {"coordinates":[65.47528,62.15221999999999],"type":"Point"}
}