{
  "type": "Feature",
  "properties": {
    "gn:admin1_code":"33",
    "gn:asciiname":"Bol'shoye Pavlovo",
    "gn:country_code":"RU",
    "gn:dem":133,
    "gn:feature_class":"P",
    "gn:feature_code":"PPL",
    "gn:name":"Bol\u2019shoye Pavlovo",
    "gn:population":0,
    "gn:timezone":"Europe/Kirov",
    "iso:country":"RU",
    "name:rus_x_preferred":[
        "\u0411\u043e\u043b\u044c\u0448\u043e\u0435 \u041f\u0430\u0432\u043b\u043e\u0432\u043e"
    ],
    "name:und_x_variant":[
        "Pavlovo",
        "Bol\u2019shoye Pavlovo",
        "\u0411\u043e\u043b\u044c\u0448\u043e\u0435 \u041f\u0430\u0432\u043b\u043e\u0432\u043e"
    ],
    "wof:name":"Bol'shoye Pavlovo",
    "wof:placetype":"locality"
},
  "geometry": {"coordinates":[47.48268,56.95069],"type":"Point"}
}