{
  "type": "Feature",
  "properties": {
    "gn:admin1_code":"61.0",
    "gn:asciiname":"Grekovo-Petrovskiy",
    "gn:country_code":"RU",
    "gn:dem":82,
    "gn:feature_class":"P",
    "gn:feature_code":"PPL",
    "gn:name":"Grekovo-Petrovskiy",
    "gn:population":0,
    "gn:timezone":"Europe/Moscow",
    "iso:country":"RU",
    "name:rus_x_preferred":[
        "\u0413\u0440\u0435\u043a\u043e\u0432\u043e-\u041f\u0435\u0442\u0440\u043e\u0432\u0441\u043a\u0438\u0439"
    ],
    "name:und_x_variant":[
        "\u0413\u0440\u0435\u043a\u043e\u0432\u043e-\u041f\u0435\u0442\u0440\u043e\u0432\u0441\u043a\u0438\u0439",
        "Grekovo-Petrovkiy",
        "Grekovo"
    ],
    "wof:name":"Grekovo-Petrovskiy",
    "wof:placetype":"locality"
},
  "geometry": {"coordinates":[40.37389,48.83597],"type":"Point"}
}