{
  "type": "Feature",
  "properties": {
    "gn:admin1_code":"81.0",
    "gn:asciiname":"Boltayevka",
    "gn:country_code":"RU",
    "gn:dem":97,
    "gn:feature_class":"P",
    "gn:feature_code":"PPL",
    "gn:name":"Boltayevka",
    "gn:population":0,
    "gn:timezone":"Europe/Ulyanovsk",
    "iso:country":"RU",
    "name:rus_x_preferred":[
        "\u0411\u043e\u043b\u0442\u0430\u0435\u0432\u043a\u0430"
    ],
    "wof:name":"Boltayevka",
    "wof:placetype":"locality"
},
  "geometry": {"coordinates":[46.76117,54.40468000000001],"type":"Point"}
}