{
  "type": "Feature",
  "properties": {
    "gn:admin1_code":"55",
    "gn:asciiname":"Kameykino",
    "gn:country_code":"RU",
    "gn:dem":333,
    "gn:feature_class":"P",
    "gn:feature_code":"PPL",
    "gn:name":"Kameykino",
    "gn:population":0,
    "gn:timezone":"Asia/Yekaterinburg",
    "iso:country":"RU",
    "name:eng_x_preferred":[
        "Kameykino"
    ],
    "name:nor_x_preferred":[
        "Kamejkino"
    ],
    "name:rus_x_preferred":[
        "\u041a\u0430\u043c\u0435\u0439\u043a\u0438\u043d\u043e"
    ],
    "wof:name":"Kameykino",
    "wof:placetype":"locality"
},
  "geometry": {"coordinates":[58.43222,51.50889],"type":"Point"}
}