{
  "type": "Feature",
  "properties": {
    "gn:admin1_code":"77.0",
    "gn:asciiname":"Glubokoye",
    "gn:country_code":"RU",
    "gn:dem":198,
    "gn:feature_class":"P",
    "gn:feature_code":"PPL",
    "gn:name":"Glubokoye",
    "gn:population":0,
    "gn:timezone":"Europe/Moscow",
    "iso:country":"RU",
    "name:rus_x_preferred":[
        "\u0413\u043b\u0443\u0431\u043e\u043a\u043e\u0435"
    ],
    "name:und_x_variant":[
        "Glubokaya",
        "Glubokoye"
    ],
    "wof:name":"Glubokoye",
    "wof:placetype":"locality"
},
  "geometry": {"coordinates":[31.67785,56.77611],"type":"Point"}
}