{
  "type": "Feature",
  "properties": {
    "gn:admin1_code":"8.0",
    "gn:asciiname":"Akbulatovo",
    "gn:country_code":"RU",
    "gn:dem":301,
    "gn:feature_class":"P",
    "gn:feature_code":"PPL",
    "gn:name":"Akbulatovo",
    "gn:population":0,
    "gn:timezone":"Asia/Yekaterinburg",
    "iso:country":"RU",
    "name:bak_x_preferred":[
        "\u0410\u04a1\u0431\u0443\u043b\u0430\u0442"
    ],
    "name:che_x_preferred":[
        "\u0410\u043a\u0431\u0443\u043b\u0430\u0442\u043e\u0432\u043e"
    ],
    "name:hye_x_preferred":[
        "\u0531\u056f\u0562\u0578\u0582\u056c\u0561\u057f\u0578\u057e\u0578"
    ],
    "name:kat_x_preferred":[
        "\u10d0\u10d9\u10d1\u10e3\u10da\u10d0\u10e2\u10dd\u10d5\u10dd"
    ],
    "name:kaz_x_preferred":[
        "\u0410\u043a\u0431\u0443\u043b\u0430\u0442"
    ],
    "name:kir_x_preferred":[
        "\u0410\u043a\u0431\u0443\u043b\u0430\u0442"
    ],
    "name:nor_x_preferred":[
        "Akbulatova"
    ],
    "name:rus_x_preferred":[
        "\u0410\u043a\u0431\u0443\u043b\u0430\u0442\u043e\u0432\u043e"
    ],
    "name:tat_x_preferred":[
        "\u0410\u043a\u0431\u0443\u043b\u0430\u0442"
    ],
    "name:ukr_x_preferred":[
        "\u0410\u043a\u0431\u0443\u043b\u0430\u0442\u043e\u0432\u043e"
    ],
    "name:und_x_variant":[
        "Akbulat",
        "Akbulatovo"
    ],
    "wof:name":"Akbulatovo",
    "wof:placetype":"locality"
},
  "geometry": {"coordinates":[55.1401,53.1496],"type":"Point"}
}