{
  "type": "Feature",
  "properties": {
    "gn:admin1_code":"8.0",
    "gn:asciiname":"Akbulatovo",
    "gn:country_code":"RU",
    "gn:dem":301,
    "gn:feature_class":"P",
    "gn:feature_code":"PPL",
    "gn:name":"Akbulatovo",
    "gn:population":0,
    "gn:timezone":"Asia/Yekaterinburg",
    "iso:country":"RU",
    "name:nor_x_preferred":[
        "Akbulatova"
    ],
    "name:rus_x_preferred":[
        "\u0410\u043a\u0431\u0443\u043b\u0430\u0442\u043e\u0432\u043e"
    ],
    "name:und_x_variant":[
        "Akbulat",
        "Akbulatova",
        "Akbulatovo"
    ],
    "wof:name":"Akbulatovo",
    "wof:placetype":"locality"
},
  "geometry": {"coordinates":[55.1401,53.1496],"type":"Point"}
}