{
  "type": "Feature",
  "properties": {
    "gn:admin1_code":"71",
    "gn:asciiname":"Malakhova",
    "gn:country_code":"RU",
    "gn:dem":67,
    "gn:feature_class":"P",
    "gn:feature_code":"PPL",
    "gn:name":"Malakhova",
    "gn:population":0,
    "gn:timezone":"Asia/Yekaterinburg",
    "iso:country":"RU",
    "name:eng_x_preferred":[
        "Malakhova"
    ],
    "name:nor_x_preferred":[
        "Tsjernovskoje"
    ],
    "name:rus_x_preferred":[
        "\u0427\u0435\u0440\u043d\u043e\u0432\u0441\u043a\u043e\u0435"
    ],
    "name:rus_x_variant":[
        "\u041c\u0430\u043b\u0430\u0445\u043e\u0432\u0430"
    ],
    "name:und_x_variant":[
        "Chernovo",
        "Malakhova"
    ],
    "wof:name":"Malakhova",
    "wof:placetype":"locality"
},
  "geometry": {"coordinates":[63.40261,57.60933000000001],"type":"Point"}
}