{
  "type": "Feature",
  "properties": {
    "gn:admin1_code":"20.0",
    "gn:asciiname":"Kulunkun",
    "gn:country_code":"RU",
    "gn:dem":554,
    "gn:feature_class":"P",
    "gn:feature_code":"PPL",
    "gn:name":"Kulunkun",
    "gn:population":0,
    "gn:timezone":"Asia/Irkutsk",
    "iso:country":"RU",
    "name:rus_x_preferred":[
        "\u041a\u0443\u043b\u0443\u043d\u043a\u0443\u043d"
    ],
    "name:und_x_variant":[
        "Ata",
        "Kulunkun"
    ],
    "wof:name":"Kulunkun",
    "wof:placetype":"locality"
},
  "geometry": {"coordinates":[104.68277999999999,52.84056],"type":"Point"}
}