{
  "type": "Feature",
  "properties": {
    "iso:country":"RU",
    "name:rus_x_preferred":[
        "\u041a\u043e\u0436\u0443\u0445\u043e\u0432\u043e"
    ],
    "wof:name":"Kozhukhovo",
    "wof:placetype":"neighbourhood"
},
  "geometry": {"coordinates":[37.89075102980227,55.71469301790262],"type":"Point"}
}