{
  "type": "Feature",
  "properties": {
    "gn:admin1_code":"10",
    "gn:asciiname":"Lyshchichi",
    "gn:country_code":"RU",
    "gn:dem":180,
    "gn:feature_class":"P",
    "gn:feature_code":"PPL",
    "gn:name":"Lyshchichi",
    "gn:population":0,
    "gn:timezone":"Europe/Moscow",
    "iso:country":"RU",
    "name:eng_x_preferred":[
        "Lyshchichi"
    ],
    "name:nor_x_preferred":[
        "Lysjtsjiki"
    ],
    "name:rus_x_preferred":[
        "\u041b\u044b\u0449\u0438\u043a\u0438"
    ],
    "name:rus_x_variant":[
        "\u041b\u044b\u0449\u0438\u0447\u0438"
    ],
    "name:und_x_variant":[
        "Lyschtschitschi"
    ],
    "wof:name":"Lyshchichi",
    "wof:placetype":"locality"
},
  "geometry": {"coordinates":[32.56853,52.73735],"type":"Point"}
}