{
  "type": "Feature",
  "properties": {
    "gn:admin1_code":"85",
    "gn:asciiname":"Svoroba",
    "gn:country_code":"RU",
    "gn:dem":130,
    "gn:feature_class":"P",
    "gn:feature_code":"PPL",
    "gn:name":"Svoroba",
    "gn:population":0,
    "gn:timezone":"Europe/Moscow",
    "iso:country":"RU",
    "name:rus_x_preferred":[
        "\u0421\u0432\u043e\u0440\u043e\u0431\u0430"
    ],
    "wof:name":"Svoroba",
    "wof:placetype":"locality"
},
  "geometry": {"coordinates":[35.94023,58.96099],"type":"Point"}
}