{
  "type": "Feature",
  "properties": {
    "gn:admin1_code":"16",
    "gn:asciiname":"Atmen'",
    "gn:country_code":"RU",
    "gn:dem":162,
    "gn:feature_class":"P",
    "gn:feature_code":"PPL",
    "gn:name":"Atmen\u2019",
    "gn:population":0,
    "gn:timezone":"Europe/Moscow",
    "iso:country":"RU",
    "name:nor_x_preferred":[
        "Atmen"
    ],
    "name:rus_x_preferred":[
        "\u0410\u0442\u043c\u0435\u043d\u044c"
    ],
    "name:und_x_variant":[
        "Atmen\u2019"
    ],
    "wof:name":"Atmen'",
    "wof:placetype":"locality"
},
  "geometry": {"coordinates":[46.55792,55.80369],"type":"Point"}
}