{
  "type": "Feature",
  "properties": {
    "gn:admin1_code":"85",
    "gn:asciiname":"Yershovo",
    "gn:country_code":"RU",
    "gn:dem":149,
    "gn:feature_class":"P",
    "gn:feature_code":"PPL",
    "gn:name":"Yershovo",
    "gn:population":0,
    "gn:timezone":"Europe/Moscow",
    "iso:country":"RU",
    "name:eng_x_preferred":[
        "Yershovo"
    ],
    "name:nor_x_preferred":[
        "Jersjovo"
    ],
    "name:rus_x_preferred":[
        "\u0415\u0440\u0448\u043e\u0432\u043e"
    ],
    "wof:name":"Yershovo",
    "wof:placetype":"locality"
},
  "geometry": {"coordinates":[38.4082,59.3603],"type":"Point"}
}