{
  "type": "Feature",
  "properties": {
    "gn:admin1_code":"69",
    "gn:asciiname":"Niklyudy",
    "gn:country_code":"RU",
    "gn:dem":195,
    "gn:feature_class":"P",
    "gn:feature_code":"PPL",
    "gn:name":"Niklyudy",
    "gn:population":0,
    "gn:timezone":"Europe/Moscow",
    "iso:country":"RU",
    "name:rus_x_preferred":[
        "\u041d\u0438\u043a\u043b\u044e\u0434\u044b"
    ],
    "wof:name":"Niklyudy",
    "wof:placetype":"locality"
},
  "geometry": {"coordinates":[31.81667,54.88333000000001],"type":"Point"}
}