{
  "type": "Feature",
  "properties": {
    "gn:admin1_code":"76",
    "gn:asciiname":"Zhitovo-Dedovo",
    "gn:country_code":"RU",
    "gn:dem":179,
    "gn:feature_class":"P",
    "gn:feature_code":"PPL",
    "gn:name":"Zhitovo-Dedovo",
    "gn:population":0,
    "gn:timezone":"Europe/Moscow",
    "iso:country":"RU",
    "name:und_x_variant":[
        "Zhitovo",
        "Zhitovo-Dedovo"
    ],
    "wof:name":"Zhitovo-Dedovo",
    "wof:placetype":"locality"
},
  "geometry": {"coordinates":[37.50129,53.94273000000001],"type":"Point"}
}