{
  "type": "Feature",
  "properties": {
    "gn:admin1_code":"7",
    "gn:asciiname":"Yar-Bazar",
    "gn:country_code":"RU",
    "gn:dem":-16,
    "gn:feature_class":"P",
    "gn:feature_code":"PPL",
    "gn:name":"Yar-Bazar",
    "gn:population":0,
    "gn:timezone":"Europe/Astrakhan",
    "iso:country":"RU",
    "name:che_x_preferred":[
        "\u042f\u0440-\u0411\u0430\u0437\u0430\u0440"
    ],
    "name:eng_x_preferred":[
        "Yar-Bazar"
    ],
    "name:nor_x_preferred":[
        "Jar-Bazar"
    ],
    "name:rus_x_preferred":[
        "\u042f\u0440-\u0411\u0430\u0437\u0430\u0440"
    ],
    "name:tgk_x_preferred":[
        "\u042f\u0440-\u0411\u0430\u0437\u0430\u0440"
    ],
    "wof:name":"Yar-Bazar",
    "wof:placetype":"locality"
},
  "geometry": {"coordinates":[47.49386,45.95923],"type":"Point"}
}