{
  "type": "Feature",
  "properties": {
    "gn:admin1_code":"32",
    "gn:asciiname":"Usanovy",
    "gn:country_code":"RU",
    "gn:dem":60,
    "gn:feature_class":"P",
    "gn:feature_code":"PPL",
    "gn:name":"Usanovy",
    "gn:population":0,
    "gn:timezone":"Asia/Yekaterinburg",
    "iso:country":"RU",
    "name:rus_x_preferred":[
        "\u0423\u0441\u0430\u043d\u043e\u0432\u044b"
    ],
    "wof:name":"Usanovy",
    "wof:placetype":"locality"
},
  "geometry": {"coordinates":[73.3766,59.442],"type":"Point"}
}