{
  "type": "Feature",
  "properties": {
    "gn:admin1_code":"61",
    "gn:asciiname":"Zhirnyy",
    "gn:country_code":"RU",
    "gn:dem":46,
    "gn:feature_class":"P",
    "gn:feature_code":"PPL",
    "gn:name":"Zhirnyy",
    "gn:population":0,
    "gn:timezone":"Europe/Moscow",
    "iso:country":"RU",
    "name:rus_x_preferred":[
        "\u0416\u0438\u0440\u043d\u044b\u0439"
    ],
    "name:und_x_variant":[
        "Zhirnny",
        "Zhirnyy"
    ],
    "wof:name":"Zhirnyy",
    "wof:placetype":"locality"
},
  "geometry": {"coordinates":[42.1581,47.1214],"type":"Point"}
}