{
  "type": "Feature",
  "properties": {
    "gn:admin1_code":"33",
    "gn:asciiname":"Novaya Ukazna",
    "gn:country_code":"RU",
    "gn:dem":147,
    "gn:feature_class":"P",
    "gn:feature_code":"PPL",
    "gn:name":"Novaya Ukazna",
    "gn:population":0,
    "gn:timezone":"Europe/Kirov",
    "iso:country":"RU",
    "name:eng_x_preferred":[
        "Novaya Ukazna"
    ],
    "name:nor_x_preferred":[
        "Nov.Ukazna"
    ],
    "name:rus_x_preferred":[
        "\u041d\u043e\u0432.\u0423\u043a\u0430\u0437\u043d\u0430"
    ],
    "name:rus_x_variant":[
        "\u041d\u043e\u0432\u0430\u044f \u0423\u043a\u0430\u0437\u043d\u0430"
    ],
    "wof:name":"Novaya Ukazna",
    "wof:placetype":"locality"
},
  "geometry": {"coordinates":[46.81322,58.27094],"type":"Point"}
}