{
  "type": "Feature",
  "properties": {
    "gn:admin1_code":"73",
    "gn:asciiname":"Yakty-Kul'",
    "gn:country_code":"RU",
    "gn:dem":162,
    "gn:feature_class":"P",
    "gn:feature_code":"PPL",
    "gn:name":"Yakty-Kul\u2019",
    "gn:population":0,
    "gn:timezone":"Europe/Moscow",
    "iso:country":"RU",
    "name:rus_x_preferred":[
        "\u042f\u043a\u0442\u044b-\u041a\u0443\u043b\u044c"
    ],
    "name:und_x_variant":[
        "Yakty-Kul\u2019",
        "Yaktykul\u2019"
    ],
    "wof:name":"Yakty-Kul'",
    "wof:placetype":"locality"
},
  "geometry": {"coordinates":[53.31667,54.95],"type":"Point"}
}