{
  "type": "Feature",
  "properties": {
    "gn:admin1_code":"60",
    "gn:asciiname":"Obruby",
    "gn:country_code":"RU",
    "gn:dem":105,
    "gn:feature_class":"P",
    "gn:feature_code":"PPL",
    "gn:name":"Obruby",
    "gn:population":0,
    "gn:timezone":"Europe/Moscow",
    "iso:country":"RU",
    "name:azb_x_preferred":[
        "\u0627\u0648\u0628\u0631\u0648\u0628\u06cc"
    ],
    "name:ceb_x_preferred":[
        "Obruby"
    ],
    "name:ces_x_preferred":[
        "Obruby"
    ],
    "name:eus_x_preferred":[
        "Obruby"
    ],
    "name:fas_x_preferred":[
        "\u0627\u0648\u0628\u0631\u0648\u0628\u06cc"
    ],
    "name:fra_x_preferred":[
        "Obruby"
    ],
    "name:hun_x_preferred":[
        "Obruby"
    ],
    "name:ita_x_preferred":[
        "Obruby"
    ],
    "name:msa_x_preferred":[
        "Obruby"
    ],
    "name:nld_x_preferred":[
        "Obruby"
    ],
    "name:pol_x_preferred":[
        "Obruby"
    ],
    "name:por_x_preferred":[
        "Obruby"
    ],
    "name:rus_x_preferred":[
        "\u041e\u0431\u0440\u0443\u0431\u044b"
    ],
    "name:rus_x_variant":[
        "\u041e\u0431\u0440\u0443\u0431\u0438"
    ],
    "name:slk_x_preferred":[
        "Obruby"
    ],
    "name:spa_x_preferred":[
        "Obruby"
    ],
    "name:srp_x_preferred":[
        "\u041e\u0431\u0440\u0443\u0431\u0438"
    ],
    "name:swe_x_preferred":[
        "Obruby"
    ],
    "name:vie_x_preferred":[
        "Obruby"
    ],
    "wof:name":"Obruby",
    "wof:placetype":"locality"
},
  "geometry": {"coordinates":[28.92331,57.24083],"type":"Point"}
}