{
  "type": "Feature",
  "properties": {
    "gn:admin1_code":"52.0",
    "gn:asciiname":"Balogizha",
    "gn:country_code":"RU",
    "gn:dem":23,
    "gn:feature_class":"P",
    "gn:feature_code":"PPL",
    "gn:name":"Balogizha",
    "gn:population":0,
    "gn:timezone":"Europe/Moscow",
    "iso:country":"RU",
    "name:nor_x_preferred":[
        "Balogizja"
    ],
    "name:rus_x_preferred":[
        "\u0411\u0430\u043b\u043e\u0433\u0438\u0436\u0430"
    ],
    "name:und_x_variant":[
        "Bologizha",
        "Balogizha"
    ],
    "wof:name":"Balogizha",
    "wof:placetype":"locality"
},
  "geometry": {"coordinates":[31.32908,58.05656],"type":"Point"}
}