{
  "type": "Feature",
  "properties": {
    "gn:admin1_code":"8",
    "gn:asciiname":"Tyuryushevo",
    "gn:country_code":"RU",
    "gn:dem":240,
    "gn:feature_class":"P",
    "gn:feature_code":"PPL",
    "gn:name":"Tyuryushevo",
    "gn:population":0,
    "gn:timezone":"Asia/Yekaterinburg",
    "iso:country":"RU",
    "name:eng_x_preferred":[
        "Tyuryushevo"
    ],
    "name:nor_x_preferred":[
        "Tjurjusjevo"
    ],
    "name:rus_x_preferred":[
        "\u0422\u044e\u0440\u044e\u0448\u0435\u0432\u043e"
    ],
    "name:und_x_variant":[
        "Tyuryush-Shuymayeva",
        "Tyuryush",
        "Tyuryushevo",
        "\u0422\u044e\u0440\u044e\u0448\u0435\u0432\u043e"
    ],
    "wof:name":"Tyuryushevo",
    "wof:placetype":"locality"
},
  "geometry": {"coordinates":[54.58333,54.93333000000001],"type":"Point"}
}