{
  "type": "Feature",
  "properties": {
    "gn:admin1_code":"43",
    "gn:asciiname":"Svishchevka",
    "gn:country_code":"RU",
    "gn:dem":167,
    "gn:feature_class":"P",
    "gn:feature_code":"PPL",
    "gn:name":"Svishch\u00ebvka",
    "gn:population":0,
    "gn:timezone":"Europe/Moscow",
    "iso:country":"RU",
    "name:rus_x_preferred":[
        "\u0421\u0432\u0438\u0449\u00eb\u0432\u043a\u0430"
    ],
    "name:und_x_variant":[
        "Seishchovka",
        "Svishchovka",
        "Svishch\u00ebvka"
    ],
    "wof:name":"Svishchevka",
    "wof:placetype":"locality"
},
  "geometry": {"coordinates":[39.45324,53.28673000000001],"type":"Point"}
}