{
  "type": "Feature",
  "properties": {
    "gn:admin1_code":"60.0",
    "gn:asciiname":"Filiptsevo",
    "gn:country_code":"RU",
    "gn:dem":187,
    "gn:feature_class":"P",
    "gn:feature_code":"PPL",
    "gn:name":"Filiptsevo",
    "gn:population":0,
    "gn:timezone":"Europe/Moscow",
    "iso:country":"RU",
    "name:rus_x_preferred":[
        "\u0424\u0438\u043b\u0438\u043f\u0446\u0435\u0432\u043e"
    ],
    "name:und_x_variant":[
        "\u0424\u0438\u043b\u0438\u043f\u0446\u0435\u0432\u043e"
    ],
    "wof:name":"Filiptsevo",
    "wof:placetype":"locality"
},
  "geometry": {"coordinates":[31.02652,56.33122],"type":"Point"}
}