{
  "type": "Feature",
  "properties": {
    "gn:admin1_code":"62.0",
    "gn:asciiname":"Abakumovo",
    "gn:country_code":"RU",
    "gn:dem":165,
    "gn:feature_class":"P",
    "gn:feature_code":"PPL",
    "gn:name":"Abakumovo",
    "gn:population":0,
    "gn:timezone":"Europe/Moscow",
    "iso:country":"RU",
    "name:nor_x_preferred":[
        "Abakumovo"
    ],
    "name:rus_x_preferred":[
        "\u0410\u0431\u0430\u043a\u0443\u043c\u043e\u0432\u043e"
    ],
    "wof:name":"Abakumovo",
    "wof:placetype":"locality"
},
  "geometry": {"coordinates":[39.5846,54.2587],"type":"Point"}
}