{
  "type": "Feature",
  "properties": {
    "gn:admin1_code":"71",
    "gn:asciiname":"Panteleykovo",
    "gn:country_code":"RU",
    "gn:dem":245,
    "gn:feature_class":"P",
    "gn:feature_code":"PPL",
    "gn:name":"Panteleykovo",
    "gn:population":0,
    "gn:timezone":"Asia/Yekaterinburg",
    "iso:country":"RU",
    "name:eng_x_preferred":[
        "Panteleykovo"
    ],
    "name:nor_x_preferred":[
        "Pantelejkovo"
    ],
    "name:rus_x_preferred":[
        "\u041f\u0430\u043d\u0442\u0435\u043b\u0435\u0439\u043a\u043e\u0432\u043e"
    ],
    "name:und_x_variant":[
        "Panteleyevka",
        "\u041f\u0430\u043d\u0442\u0435\u043b\u0435\u0439\u043a\u043e\u0432\u043e",
        "Panteleykovo"
    ],
    "wof:name":"Panteleykovo",
    "wof:placetype":"locality"
},
  "geometry": {"coordinates":[58.5662,56.36773],"type":"Point"}
}