{
  "type": "Feature",
  "properties": {
    "gn:admin1_code":"6",
    "gn:asciiname":"Prokoptsevskaya",
    "gn:country_code":"RU",
    "gn:dem":64,
    "gn:feature_class":"P",
    "gn:feature_code":"PPL",
    "gn:name":"Prokoptsevskaya",
    "gn:population":0,
    "gn:timezone":"Europe/Moscow",
    "iso:country":"RU",
    "name:rus_x_preferred":[
        "\u041f\u0440\u043e\u043a\u043e\u043f\u0446\u0435\u0432\u0441\u043a\u0430\u044f"
    ],
    "name:und_x_variant":[
        "Zaslonovo",
        "Prokoptsenskaya",
        "Prokoptsevskaya"
    ],
    "wof:name":"Prokoptsevskaya",
    "wof:placetype":"locality"
},
  "geometry": {"coordinates":[43.11517,61.09339],"type":"Point"}
}