{
  "type": "Feature",
  "properties": {
    "gn:admin1_code":"76",
    "gn:asciiname":"Verkhneye Red'kino",
    "gn:country_code":"RU",
    "gn:dem":212,
    "gn:feature_class":"P",
    "gn:feature_code":"PPL",
    "gn:name":"Verkhneye Red\u2019kino",
    "gn:population":0,
    "gn:timezone":"Europe/Moscow",
    "iso:country":"RU",
    "name:rus_x_preferred":[
        "\u0412\u0435\u0440\u0445\u043d\u0435\u0435 \u0420\u0435\u0434\u044c\u043a\u0438\u043d\u043e"
    ],
    "name:und_x_variant":[
        "Verkhneye Red\u2019kino"
    ],
    "wof:name":"Verkhneye Red'kino",
    "wof:placetype":"locality"
},
  "geometry": {"coordinates":[38.0947,54.6372],"type":"Point"}
}