{
  "type": "Feature",
  "properties": {
    "gn:admin1_code":"53",
    "gn:asciiname":"Osinovka",
    "gn:country_code":"RU",
    "gn:dem":190,
    "gn:feature_class":"P",
    "gn:feature_code":"PPL",
    "gn:name":"Osinovka",
    "gn:population":0,
    "gn:timezone":"Asia/Novosibirsk",
    "iso:country":"RU",
    "name:ceb_x_preferred":[
        "Osinovka"
    ],
    "name:eng_x_preferred":[
        "Osinovka"
    ],
    "name:lav_x_preferred":[
        "Osinovka"
    ],
    "name:nor_x_preferred":[
        "Osinovka"
    ],
    "name:rus_x_preferred":[
        "\u041e\u0441\u0438\u043d\u043e\u0432\u043a\u0430"
    ],
    "name:swe_x_preferred":[
        "Osinovka"
    ],
    "name:und_x_variant":[
        "\u041e\u0441\u0438\u043d\u043e\u0432\u043a\u0430",
        "Osinovka"
    ],
    "wof:name":"Osinovka",
    "wof:placetype":"locality"
},
  "geometry": {"coordinates":[84.66944000000002,55.32083000000001],"type":"Point"}
}