{
  "type": "Feature",
  "properties": {
    "gn:admin1_code":"69",
    "gn:asciiname":"Skotinina",
    "gn:country_code":"RU",
    "gn:dem":191,
    "gn:feature_class":"P",
    "gn:feature_code":"PPL",
    "gn:name":"Skotinina",
    "gn:population":0,
    "gn:timezone":"Europe/Moscow",
    "iso:country":"RU",
    "name:rus_x_preferred":[
        "\u0421\u043a\u043e\u0442\u0438\u043d\u0438\u043d\u0430"
    ],
    "wof:name":"Skotinina",
    "wof:placetype":"locality"
},
  "geometry": {"coordinates":[32.50360999999999,54.33139],"type":"Point"}
}