{
  "type": "Feature",
  "properties": {
    "gn:admin1_code":"38",
    "gn:asciiname":"Nezaymanovskiy",
    "gn:country_code":"RU",
    "gn:dem":33,
    "gn:feature_class":"P",
    "gn:feature_code":"PPL",
    "gn:name":"Nezaymanovskiy",
    "gn:population":0,
    "gn:timezone":"Europe/Moscow",
    "iso:country":"RU",
    "name:eng_x_preferred":[
        "Nezaymanovskiy"
    ],
    "name:nor_x_preferred":[
        "Nezajmanovskij"
    ],
    "name:rus_x_preferred":[
        "\u041d\u0435\u0437\u0430\u0439\u043c\u0430\u043d\u043e\u0432\u0441\u043a\u0438\u0439"
    ],
    "name:und_x_variant":[
        "Nezaymanskiy"
    ],
    "wof:name":"Nezaymanovskiy",
    "wof:placetype":"locality"
},
  "geometry": {"coordinates":[39.30632,45.71812],"type":"Point"}
}