{
  "type": "Feature",
  "properties": {
    "gn:admin1_code":"77",
    "gn:asciiname":"Kadnoye",
    "gn:country_code":"RU",
    "gn:dem":174,
    "gn:feature_class":"P",
    "gn:feature_code":"PPL",
    "gn:name":"Kadnoye",
    "gn:population":0,
    "gn:timezone":"Europe/Moscow",
    "iso:country":"RU",
    "name:rus_x_preferred":[
        "\u041a\u0430\u0434\u043d\u043e\u0435"
    ],
    "wof:name":"Kadnoye",
    "wof:placetype":"locality"
},
  "geometry": {"coordinates":[36.0282,57.3741],"type":"Point"}
}