{
  "type": "Feature",
  "properties": {
    "gn:admin1_code":"33.0",
    "gn:asciiname":"Korshunikha",
    "gn:country_code":"RU",
    "gn:dem":118,
    "gn:feature_class":"P",
    "gn:feature_code":"PPL",
    "gn:name":"Korshunikha",
    "gn:population":0,
    "gn:timezone":"Europe/Kirov",
    "iso:country":"RU",
    "name:rus_x_preferred":[
        "\u041a\u043e\u0440\u0448\u0443\u043d\u0438\u0445\u0430"
    ],
    "name:und_x_variant":[
        "\u041a\u043e\u0440\u0448\u0443\u043d\u0438\u0445\u0430"
    ],
    "wof:name":"Korshunikha",
    "wof:placetype":"locality"
},
  "geometry": {"coordinates":[50.46814000000001,58.45424000000001],"type":"Point"}
}