{
  "type": "Feature",
  "properties": {
    "gn:admin1_code":"63",
    "gn:asciiname":"Khaptanga",
    "gn:country_code":"RU",
    "gn:dem":134,
    "gn:feature_class":"P",
    "gn:feature_code":"PPL",
    "gn:name":"Khaptanga",
    "gn:population":0,
    "gn:timezone":"Asia/Yakutsk",
    "iso:country":"RU",
    "name:eng_x_preferred":[
        "Khaptanga"
    ],
    "name:nor_x_preferred":[
        "Khaptanga"
    ],
    "name:rus_x_preferred":[
        "\u0425\u0430\u043f\u0442\u0430\u043d\u0433\u0430"
    ],
    "wof:name":"Khaptanga",
    "wof:placetype":"locality"
},
  "geometry": {"coordinates":[131.18109999999999,62.78153],"type":"Point"}
}