{
  "type": "Feature",
  "properties": {
    "gn:admin1_code":"51",
    "gn:asciiname":"Orekhovo",
    "gn:country_code":"RU",
    "gn:dem":74,
    "gn:feature_class":"P",
    "gn:feature_code":"PPL",
    "gn:name":"Orekhovo",
    "gn:population":0,
    "gn:timezone":"Europe/Moscow",
    "iso:country":"RU",
    "name:rus_x_preferred":[
        "\u041e\u0440\u0435\u0445\u043e\u0432\u043e"
    ],
    "name:und_x_variant":[
        "\u041e\u0440\u0435\u0445\u043e\u0432\u043e"
    ],
    "wof:name":"Orekhovo",
    "wof:placetype":"locality"
},
  "geometry": {"coordinates":[44.32232,56.22632],"type":"Point"}
}