{
  "type": "Feature",
  "properties": {
    "gn:admin1_code":"85",
    "gn:asciiname":"Liminskiy",
    "gn:country_code":"RU",
    "gn:dem":122,
    "gn:feature_class":"P",
    "gn:feature_code":"PPL",
    "gn:name":"Liminskiy",
    "gn:population":0,
    "gn:timezone":"Europe/Moscow",
    "iso:country":"RU",
    "name:rus_x_preferred":[
        "\u041b\u0438\u043c\u0438\u043d\u0441\u043a\u0438\u0439"
    ],
    "name:und_x_variant":[
        "\u041b\u0438\u043c\u0438\u043d\u0441\u043a\u0438\u0439"
    ],
    "wof:name":"Liminskiy",
    "wof:placetype":"locality"
},
  "geometry": {"coordinates":[39.88333,59.21666999999999],"type":"Point"}
}