{
  "type": "Feature",
  "properties": {
    "gn:admin1_code":"28",
    "gn:asciiname":"Suysar'",
    "gn:country_code":"RU",
    "gn:dem":23,
    "gn:feature_class":"P",
    "gn:feature_code":"PPL",
    "gn:name":"Suysar\u2019",
    "gn:population":0,
    "gn:timezone":"Europe/Moscow",
    "iso:country":"RU",
    "name:eng_x_preferred":[
        "Suysar'"
    ],
    "name:fin_x_preferred":[
        "Suisaari"
    ],
    "name:nor_x_preferred":[
        "Sujsar"
    ],
    "name:rus_x_preferred":[
        "\u0421\u0443\u0439\u0441\u0430\u0440\u044c"
    ],
    "name:und_x_variant":[
        "Suysari",
        "Suysaari",
        "Suysar\u2019"
    ],
    "wof:name":"Suysar'",
    "wof:placetype":"locality"
},
  "geometry": {"coordinates":[34.55578,61.97543],"type":"Point"}
}