{
  "type": "Feature",
  "properties": {
    "gn:admin1_code":"33",
    "gn:asciiname":"Ivanovskaya",
    "gn:country_code":"RU",
    "gn:dem":236,
    "gn:feature_class":"P",
    "gn:feature_code":"PPL",
    "gn:name":"Ivanovskaya",
    "gn:population":0,
    "gn:timezone":"Europe/Kirov",
    "iso:country":"RU",
    "name:nor_x_preferred":[
        "Ivanovskaja"
    ],
    "name:rus_x_preferred":[
        "\u0418\u0432\u0430\u043d\u043e\u0432\u0441\u043a\u0430\u044f"
    ],
    "name:und_x_variant":[
        "Ivanovskaya Pervaya",
        "\u0418\u0432\u0430\u043d\u043e\u0432\u0441\u043a\u0430\u044f",
        "Ivanovskaya"
    ],
    "wof:name":"Ivanovskaya",
    "wof:placetype":"locality"
},
  "geometry": {"coordinates":[53.67536,58.87008],"type":"Point"}
}