{
  "type": "Feature",
  "properties": {
    "gn:admin1_code":"44",
    "gn:asciiname":"Labaznaya",
    "gn:country_code":"RU",
    "gn:dem":691,
    "gn:feature_class":"P",
    "gn:feature_code":"PPL",
    "gn:name":"Labaznaya",
    "gn:population":0,
    "gn:timezone":"Asia/Magadan",
    "iso:country":"RU",
    "name:rus_x_preferred":[
        "\u041b\u0430\u0431\u0430\u0437\u043d\u0430\u044f"
    ],
    "name:und_x_variant":[
        "\u041b\u0430\u0431\u0430\u0437\u043d\u0430\u044f"
    ],
    "wof:name":"Labaznaya",
    "wof:placetype":"locality"
},
  "geometry": {"coordinates":[158.45421999999999,63.31912],"type":"Point"}
}