{
  "type": "Feature",
  "properties": {
    "gn:admin1_code":"53",
    "gn:asciiname":"Padun",
    "gn:country_code":"RU",
    "gn:dem":270,
    "gn:feature_class":"P",
    "gn:feature_code":"PPL",
    "gn:name":"Padun",
    "gn:population":0,
    "gn:timezone":"Asia/Novosibirsk",
    "iso:country":"RU",
    "name:eng_x_preferred":[
        "Padun"
    ],
    "name:nor_x_preferred":[
        "Padun"
    ],
    "name:rus_x_preferred":[
        "\u041f\u0430\u0434\u0443\u043d"
    ],
    "name:und_x_variant":[
        "\u041f\u0430\u0434\u0443\u043d",
        "Padun"
    ],
    "wof:name":"Padun",
    "wof:placetype":"locality"
},
  "geometry": {"coordinates":[83.61499999999999,54.3438],"type":"Point"}
}