{
  "type": "Feature",
  "properties": {
    "gn:admin1_code":"10.0",
    "gn:asciiname":"Berezovshchina",
    "gn:country_code":"RU",
    "gn:dem":186,
    "gn:feature_class":"P",
    "gn:feature_code":"PPL",
    "gn:name":"Berezovshchina",
    "gn:population":0,
    "gn:timezone":"Europe/Moscow",
    "iso:country":"RU",
    "name:nor_x_preferred":[
        "Berezovsjtsjina"
    ],
    "name:rus_x_preferred":[
        "\u0411\u0435\u0440\u0435\u0437\u043e\u0432\u0449\u0438\u043d\u0430"
    ],
    "wof:name":"Berezovshchina",
    "wof:placetype":"locality"
},
  "geometry": {"coordinates":[33.03346,52.44153000000001],"type":"Point"}
}