{
  "type": "Feature",
  "properties": {
    "gn:admin1_code":"91",
    "gn:asciiname":"Glinnyy",
    "gn:country_code":"RU",
    "gn:dem":221,
    "gn:feature_class":"P",
    "gn:feature_code":"PPL",
    "gn:name":"Glinnyy",
    "gn:population":0,
    "gn:timezone":"Asia/Krasnoyarsk",
    "iso:country":"RU",
    "name:eng_x_preferred":[
        "Glinnyy"
    ],
    "name:rus_x_preferred":[
        "\u0413\u043b\u0438\u043d\u043d\u044b\u0439"
    ],
    "name:rus_x_variant":[
        "\u0413\u043b\u0438\u043d\u043a\u0430"
    ],
    "wof:name":"Glinnyy",
    "wof:placetype":"locality"
},
  "geometry": {"coordinates":[97.7116,56.7818],"type":"Point"}
}