{
  "type": "Feature",
  "properties": {
    "gn:country":"RU",
    "gn:fcode":"PPL",
    "gn:pop":0,
    "iso:country":"RU",
    "name:eng_x_preferred":[
        "Molokovo"
    ],
    "name:rus_x_preferred":[
        "\u041c\u043e\u043b\u043e\u043a\u043e\u0432\u043e"
    ],
    "name:unk_x_variant":[
        "Irininskoye"
    ],
    "qs:name":"Molokovo",
    "qs:name_adm0":"Russia",
    "qs:name_adm1":"Moscow Oblast",
    "qs:photos_9r":0,
    "qs:photos_sr":0,
    "qs:placetype":"Town",
    "qs:pop_sr":"0",
    "wd:wordcount":284,
    "wof:name":"Molokovo",
    "wof:placetype":"locality",
    "wof:population":0
},
  "geometry": {"coordinates":[37.86492,55.56186],"type":"Point"}
}