{
  "type": "Feature",
  "properties": {
    "gn:admin1_code":"40",
    "gn:asciiname":"Pervomayskaya",
    "gn:country_code":"RU",
    "gn:dem":138,
    "gn:feature_class":"P",
    "gn:feature_code":"PPL",
    "gn:name":"Pervomayskaya",
    "gn:population":0,
    "gn:timezone":"Asia/Yekaterinburg",
    "iso:country":"RU",
    "name:rus_x_preferred":[
        "\u041f\u0435\u0440\u0432\u043e\u043c\u0430\u0439\u0441\u043a\u0430\u044f"
    ],
    "name:und_x_variant":[
        "\u041f\u0435\u0440\u0432\u043e\u043c\u0430\u0439\u0441\u043a\u0430\u044f"
    ],
    "wof:name":"Pervomayskaya",
    "wof:placetype":"locality"
},
  "geometry": {"coordinates":[67.92278,55.02389],"type":"Point"}
}