{
  "type": "Feature",
  "properties": {
    "gn:admin1_code":"28",
    "gn:asciiname":"Mogil'niki",
    "gn:country_code":"RU",
    "gn:dem":80,
    "gn:feature_class":"P",
    "gn:feature_code":"PPL",
    "gn:name":"Mogil\u2019niki",
    "gn:population":0,
    "gn:timezone":"Europe/Moscow",
    "iso:country":"RU",
    "name:rus_x_preferred":[
        "\u041c\u043e\u0433\u0438\u043b\u044c\u043d\u0438\u043a\u0438"
    ],
    "name:und_x_variant":[
        "Mogil\u2019niki",
        "\u041c\u043e\u0433\u0438\u043b\u044c\u043d\u0438\u043a\u0438"
    ],
    "wof:name":"Mogil'niki",
    "wof:placetype":"locality"
},
  "geometry": {"coordinates":[34.30218,62.62201],"type":"Point"}
}