{
  "type": "Feature",
  "properties": {
    "gn:admin1_code":"10",
    "gn:asciiname":"Poselok Nomer Tretiy",
    "gn:cc2":"RU",
    "gn:country_code":"RU",
    "gn:dem":195,
    "gn:feature_class":"P",
    "gn:feature_code":"PPL",
    "gn:name":"Pos\u00eblok Nomer Tretiy",
    "gn:population":0,
    "gn:timezone":"Europe/Moscow",
    "iso:country":"RU",
    "name:rus_x_preferred":[
        "\u041f\u043e\u0441\u0451\u043b\u043e\u043a \u041d\u043e\u043c\u0435\u0440 \u0422\u0440\u0435\u0442\u0438\u0439"
    ],
    "name:und_x_variant":[
        "Pos\u00eblok Tretiy",
        "Pos\u00eblok Nomer Tretiy"
    ],
    "wof:name":"Poselok Nomer Tretiy",
    "wof:placetype":"locality"
},
  "geometry": {"coordinates":[34.33333,52.08333],"type":"Point"}
}