{
  "type": "Feature",
  "properties": {
    "gn:admin1_code":"91",
    "gn:asciiname":"Menzot",
    "gn:country_code":"RU",
    "gn:dem":329,
    "gn:feature_class":"P",
    "gn:feature_code":"PPL",
    "gn:name":"Menzot",
    "gn:population":0,
    "gn:timezone":"Asia/Krasnoyarsk",
    "iso:country":"RU",
    "name:rus_x_preferred":[
        "\u041c\u0435\u043d\u0437\u043e\u0442"
    ],
    "wof:name":"Menzot",
    "wof:placetype":"locality"
},
  "geometry": {"coordinates":[92.23833,54.56056],"type":"Point"}
}