{
  "type": "Feature",
  "properties": {
    "gn:admin1_code":"10",
    "gn:asciiname":"Gannovka",
    "gn:country_code":"RU",
    "gn:dem":148,
    "gn:feature_class":"P",
    "gn:feature_code":"PPL",
    "gn:name":"Gannovka",
    "gn:population":0,
    "gn:timezone":"Europe/Moscow",
    "iso:country":"RU",
    "name:rus_x_preferred":[
        "\u0413\u0430\u043d\u043d\u043e\u0432\u043a\u0430"
    ],
    "wof:name":"Gannovka",
    "wof:placetype":"locality"
},
  "geometry": {"coordinates":[32.065,52.86816],"type":"Point"}
}