{
  "type": "Feature",
  "properties": {
    "gn:admin1_code":"88",
    "gn:asciiname":"Balobanovo",
    "gn:country_code":"RU",
    "gn:dem":109,
    "gn:feature_class":"P",
    "gn:feature_code":"PPL",
    "gn:name":"Balobanovo",
    "gn:population":0,
    "gn:timezone":"Europe/Moscow",
    "iso:country":"RU",
    "name:rus_x_preferred":[
        "\u0411\u0430\u043b\u043e\u0431\u0430\u043d\u043e\u0432\u043e"
    ],
    "name:und_x_variant":[
        "\u0411\u0430\u043b\u043e\u0431\u0430\u043d\u043e\u0432\u043e"
    ],
    "wof:name":"Balobanovo",
    "wof:placetype":"locality"
},
  "geometry": {"coordinates":[38.66184000000001,58.10518],"type":"Point"}
}