{
  "type": "Feature",
  "properties": {
    "gn:admin1_code":"33.0",
    "gn:asciiname":"Kovrovy",
    "gn:country_code":"RU",
    "gn:dem":136,
    "gn:feature_class":"P",
    "gn:feature_code":"PPL",
    "gn:name":"Kovrovy",
    "gn:population":0,
    "gn:timezone":"Europe/Kirov",
    "iso:country":"RU",
    "name:rus_x_preferred":[
        "\u041a\u043e\u0432\u0440\u043e\u0432\u044b"
    ],
    "wof:name":"Kovrovy",
    "wof:placetype":"locality"
},
  "geometry": {"coordinates":[48.45167,58.33711],"type":"Point"}
}