{
  "type": "Feature",
  "properties": {
    "gn:admin1_code":"73",
    "gn:asciiname":"Suyk-Chishma",
    "gn:country_code":"RU",
    "gn:dem":157,
    "gn:feature_class":"P",
    "gn:feature_code":"PPL",
    "gn:name":"Suyk-Chishma",
    "gn:population":0,
    "gn:timezone":"Europe/Moscow",
    "iso:country":"RU",
    "name:rus_x_preferred":[
        "\u0421\u0443\u044b\u043a-\u0427\u0438\u0448\u043c\u0430"
    ],
    "wof:name":"Suyk-Chishma",
    "wof:placetype":"locality"
},
  "geometry": {"coordinates":[52.9437,54.3373],"type":"Point"}
}