{
  "type": "Feature",
  "properties": {
    "gn:admin1_code":"10",
    "gn:asciiname":"Malyy Krupets",
    "gn:country_code":"RU",
    "gn:dem":181,
    "gn:feature_class":"P",
    "gn:feature_code":"PPL",
    "gn:name":"Malyy Krupets",
    "gn:population":0,
    "gn:timezone":"Europe/Moscow",
    "iso:country":"RU",
    "name:rus_x_preferred":[
        "\u041c\u0430\u043b\u044b\u0439 \u041a\u0440\u0443\u043f\u0435\u0446"
    ],
    "wof:name":"Malyy Krupets",
    "wof:placetype":"locality"
},
  "geometry": {"coordinates":[33.86555,53.15884000000001],"type":"Point"}
}