{
  "type": "Feature",
  "properties": {
    "gn:admin1_code":"64",
    "gn:asciiname":"Beregovyye Langry",
    "gn:country_code":"RU",
    "gn:dem":3,
    "gn:feature_class":"P",
    "gn:feature_code":"PPL",
    "gn:name":"Beregovyye Langry",
    "gn:population":0,
    "gn:timezone":"Asia/Sakhalin",
    "iso:country":"RU",
    "name:eng_x_preferred":[
        "Beregovyye Langry"
    ],
    "name:nor_x_preferred":[
        "Beregovye Langry"
    ],
    "name:rus_x_preferred":[
        "\u0411\u0435\u0440\u0435\u0433\u043e\u0432\u044b\u0435 \u041b\u0430\u043d\u0433\u0440\u044b"
    ],
    "wof:name":"Beregovyye Langry",
    "wof:placetype":"locality"
},
  "geometry": {"coordinates":[141.92939999999999,53.04893000000001],"type":"Point"}
}