{
  "type": "Feature",
  "properties": {
    "gn:admin1_code":"73",
    "gn:asciiname":"Novoselki",
    "gn:country_code":"RU",
    "gn:dem":87,
    "gn:feature_class":"P",
    "gn:feature_code":"PPL",
    "gn:name":"Novos\u00eblki",
    "gn:population":0,
    "gn:timezone":"Europe/Moscow",
    "iso:country":"RU",
    "name:lav_x_preferred":[
        "Novoselki"
    ],
    "wof:name":"Novoselki",
    "wof:placetype":"locality"
},
  "geometry": {"coordinates":[48.17676,54.73647],"type":"Point"}
}