{
  "type": "Feature",
  "properties": {
    "gn:admin1_code":"20",
    "gn:asciiname":"Kurgatey",
    "gn:country_code":"RU",
    "gn:dem":544,
    "gn:feature_class":"P",
    "gn:feature_code":"PPL",
    "gn:name":"Kurgatey",
    "gn:population":0,
    "gn:timezone":"Asia/Irkutsk",
    "iso:country":"RU",
    "name:eng_x_preferred":[
        "Kurgatey"
    ],
    "name:nor_x_preferred":[
        "Kurgatej"
    ],
    "name:rus_x_preferred":[
        "\u041a\u0443\u0440\u0433\u0430\u0442\u0435\u0439"
    ],
    "name:und_x_variant":[
        "Kurgatyy",
        "Kurgaty"
    ],
    "wof:name":"Kurgatey",
    "wof:placetype":"locality"
},
  "geometry": {"coordinates":[99.43089999999999,54.3775],"type":"Point"}
}