{
  "type": "Feature",
  "properties": {
    "gn:admin1_code":"77",
    "gn:asciiname":"Staroye Malinovo",
    "gn:country_code":"RU",
    "gn:dem":210,
    "gn:feature_class":"P",
    "gn:feature_code":"PPL",
    "gn:name":"Staroye Malinovo",
    "gn:population":0,
    "gn:timezone":"Europe/Moscow",
    "iso:country":"RU",
    "name:rus_x_preferred":[
        "\u0421\u0442\u0430\u0440\u043e\u0435 \u041c\u0430\u043b\u0438\u043d\u043e\u0432\u043e"
    ],
    "wof:name":"Staroye Malinovo",
    "wof:placetype":"locality"
},
  "geometry": {"coordinates":[34.51892,57.14858],"type":"Point"}
}