{
  "type": "Feature",
  "properties": {
    "gn:admin1_code":"45",
    "gn:asciiname":"Sukma",
    "gn:country_code":"RU",
    "gn:dem":128,
    "gn:feature_class":"P",
    "gn:feature_code":"PPL",
    "gn:name":"Sukma",
    "gn:population":0,
    "gn:timezone":"Europe/Moscow",
    "iso:country":"RU",
    "name:deu_x_preferred":[
        "Sukma"
    ],
    "name:fra_x_preferred":[
        "Sukma"
    ],
    "name:hin_x_preferred":[
        "\u0938\u0941\u0915\u092e\u093e"
    ],
    "name:ori_x_preferred":[
        "\u0b38\u0b41\u0b15\u0b2e\u0b3e \u0b1c\u0b3f\u0b32\u0b4d\u0b32\u0b3e"
    ],
    "name:rus_x_preferred":[
        "\u0421\u0443\u043a\u043c\u0430"
    ],
    "name:und_x_variant":[
        "\u0421\u0443\u043a\u043c\u0430"
    ],
    "name:urd_x_preferred":[
        "\u0633\u0648\u06a9\u0645\u0627"
    ],
    "wof:name":"Sukma",
    "wof:placetype":"locality"
},
  "geometry": {"coordinates":[49.80139000000001,56.64335],"type":"Point"}
}