{
  "type": "Feature",
  "properties": {
    "iso:country":"RU",
    "name:bel_x_preferred":[
        "\u041a\u0430\u043b\u0456\u043d\u043a\u0430"
    ],
    "name:bel_x_variant":[
        "\u041a\u0430\u043b\u0456\u043d\u043a\u0430"
    ],
    "name:deu_x_preferred":[
        "Kalinka"
    ],
    "name:eng_x_preferred":[
        "Kalinka"
    ],
    "name:ind_x_preferred":[
        "Kalinka"
    ],
    "name:jpn_x_preferred":[
        "\u30ab\u30ea\u30f3\u30ab"
    ],
    "name:mkd_x_preferred":[
        "\u041a\u0430\u043b\u0438\u043d\u043a\u0430"
    ],
    "name:rus_x_preferred":[
        "\u041a\u0430\u043b\u0438\u043d\u043a\u0430"
    ],
    "name:ukr_x_preferred":[
        "\u041a\u0430\u043b\u0438\u043d\u043a\u0430"
    ],
    "name:unk_x_variant":[
        "\u041a\u0430\u043b\u0438\u043d\u043a\u0430",
        "Kalinka"
    ],
    "qs:gn_fcode":"PPL",
    "qs:gn_local":0,
    "qs:gn_namadm1":"30",
    "qs:gn_name":"Kalinka",
    "qs:local_max":314,
    "qs:local_sum":314,
    "qs:localhoods":1,
    "qs:name":"Kalinka",
    "qs:name_adm0":"Russia",
    "qs:name_adm1":"Khabarovsk Krai",
    "qs:name_adm2":"Khabarovskiy Raion",
    "qs:name_local":"Khabarovskiy Raion",
    "qs:photo_max":84,
    "qs:photo_sum":314,
    "qs:placetype":"Suburb",
    "qs:quad_count":32,
    "qs:woe_adm0":23424936,
    "qs:woe_adm1":2346883,
    "qs:woe_adm2":12597743,
    "qs:woe_lau":0,
    "qs:woe_local":12597743,
    "qs:woe_ver":"7.10.0",
    "wd:wordcount":98,
    "wof:lang":[
        "eng"
    ],
    "wof:name":"Kalinka",
    "wof:placetype":"neighbourhood"
},
  "geometry": {"coordinates":[135.123154,48.4189],"type":"Point"}
}