{
  "type": "Feature",
  "properties": {
    "gn:admin1_code":"61",
    "gn:asciiname":"Dudarevskiy",
    "gn:country_code":"RU",
    "gn:dem":112,
    "gn:feature_class":"P",
    "gn:feature_code":"PPL",
    "gn:name":"Dudar\u00ebvskiy",
    "gn:population":0,
    "gn:timezone":"Europe/Moscow",
    "iso:country":"RU",
    "name:eng_x_preferred":[
        "Dudar\u00ebvskiy"
    ],
    "name:nor_x_preferred":[
        "Verkhnedudarevskij"
    ],
    "name:rus_x_preferred":[
        "\u0412\u0435\u0440\u0445\u043d\u0435\u0434\u0443\u0434\u0430\u0440\u0435\u0432\u0441\u043a\u0438\u0439"
    ],
    "name:rus_x_variant":[
        "\u0414\u0443\u0434\u0430\u0440\u0451\u0432\u0441\u043a\u0438\u0439"
    ],
    "name:und_x_variant":[
        "Verkhnyaya Dudar\u00ebvka",
        "Dudarevka",
        "Verkhnedudar\u00ebvskiy",
        "Dudar\u00ebvskiy",
        "\u0414\u0443\u0434\u0430\u0440\u0451\u0432\u0441\u043a\u0438\u0439"
    ],
    "wof:name":"Dudarevskiy",
    "wof:placetype":"locality"
},
  "geometry": {"coordinates":[41.65103,49.88696],"type":"Point"}
}