{
  "type": "Feature",
  "properties": {
    "gn:admin1_code":"89",
    "gn:asciiname":"Tselinnoye",
    "gn:country_code":"RU",
    "gn:dem":75,
    "gn:feature_class":"P",
    "gn:feature_code":"PPL",
    "gn:name":"Tselinnoye",
    "gn:population":0,
    "gn:timezone":"Asia/Vladivostok",
    "iso:country":"RU",
    "name:eng_x_preferred":[
        "Tselinnoye"
    ],
    "name:nor_x_preferred":[
        "Tselinnoje"
    ],
    "name:rus_x_preferred":[
        "\u0426\u0435\u043b\u0438\u043d\u043d\u043e\u0435"
    ],
    "wof:name":"Tselinnoye",
    "wof:placetype":"locality"
},
  "geometry": {"coordinates":[132.4092,48.12266],"type":"Point"}
}