{
  "type": "Feature",
  "properties": {
    "gn:admin1_code":"1",
    "gn:asciiname":"Apostolidi",
    "gn:country_code":"RU",
    "gn:dem":26,
    "gn:feature_class":"P",
    "gn:feature_code":"PPL",
    "gn:name":"Apostolidi",
    "gn:population":0,
    "gn:timezone":"Europe/Moscow",
    "iso:country":"RU",
    "name:cat_x_preferred":[
        "Apostolidi"
    ],
    "name:che_x_preferred":[
        "\u0410\u043f\u043e\u0441\u0442\u043e\u043b\u0438\u0434\u0438"
    ],
    "name:nor_x_preferred":[
        "Apostolidi"
    ],
    "name:rus_x_preferred":[
        "\u0410\u043f\u043e\u0441\u0442\u043e\u043b\u0438\u0434\u0438"
    ],
    "name:spa_x_preferred":[
        "Apostolidi"
    ],
    "name:ukr_x_preferred":[
        "\u0410\u043f\u043e\u0441\u0442\u043e\u043b\u0456\u0434\u0456"
    ],
    "wof:name":"Apostolidi",
    "wof:placetype":"locality"
},
  "geometry": {"coordinates":[38.96569,44.89552],"type":"Point"}
}