{
  "type": "Feature",
  "properties": {
    "gn:admin1_code":"76",
    "gn:asciiname":"Teploye",
    "gn:country_code":"RU",
    "gn:dem":186,
    "gn:feature_class":"P",
    "gn:feature_code":"PPL",
    "gn:name":"Teploye",
    "gn:population":0,
    "gn:timezone":"Europe/Moscow",
    "iso:country":"RU",
    "name:rus_x_preferred":[
        "\u0422\u0451\u043f\u043b\u043e\u0435"
    ],
    "wof:name":"Teploye",
    "wof:placetype":"locality"
},
  "geometry": {"coordinates":[38.20029,54.27378],"type":"Point"}
}