{
  "type": "Feature",
  "properties": {
    "gn:admin1_code":"73",
    "gn:asciiname":"Novoye Isakovo",
    "gn:country_code":"RU",
    "gn:dem":160,
    "gn:feature_class":"P",
    "gn:feature_code":"PPL",
    "gn:name":"Novoye Isakovo",
    "gn:population":0,
    "gn:timezone":"Europe/Moscow",
    "iso:country":"RU",
    "name:rus_x_preferred":[
        "\u041d\u043e\u0432\u043e\u0435 \u0418\u0441\u0430\u043a\u043e\u0432\u043e"
    ],
    "name:und_x_variant":[
        "\u041d\u043e\u0432\u043e\u0435 \u0418\u0441\u0430\u043a\u043e\u0432\u043e"
    ],
    "wof:name":"Novoye Isakovo",
    "wof:placetype":"locality"
},
  "geometry": {"coordinates":[53.0417,54.4494],"type":"Point"}
}