{
  "type": "Feature",
  "properties": {
    "gn:admin1_code":"33",
    "gn:asciiname":"Lipovoye",
    "gn:country_code":"RU",
    "gn:dem":154,
    "gn:feature_class":"P",
    "gn:feature_code":"PPL",
    "gn:name":"Lipovoye",
    "gn:population":0,
    "gn:timezone":"Europe/Kirov",
    "iso:country":"RU",
    "name:eng_x_preferred":[
        "Lipovoye"
    ],
    "name:nor_x_preferred":[
        "Lipovoje"
    ],
    "name:rus_x_preferred":[
        "\u041b\u0438\u043f\u043e\u0432\u043e\u0435"
    ],
    "name:und_x_variant":[
        "\u041b\u0438\u043f\u043e\u0432\u043e\u0435",
        "Lipovoye"
    ],
    "wof:name":"Lipovoye",
    "wof:placetype":"locality"
},
  "geometry": {"coordinates":[51.01318,59.27737],"type":"Point"}
}