{
  "type": "Feature",
  "properties": {
    "gn:admin1_code":"67",
    "gn:asciiname":"Rasskazovka",
    "gn:country_code":"RU",
    "gn:dem":205,
    "gn:feature_class":"P",
    "gn:feature_code":"PPL",
    "gn:name":"Rasskazovka",
    "gn:population":0,
    "gn:timezone":"Europe/Saratov",
    "iso:country":"RU",
    "name:rus_x_preferred":[
        "\u0420\u0430\u0441\u0441\u043a\u0430\u0437\u043e\u0432\u043a\u0430"
    ],
    "name:und_x_variant":[
        "\u0420\u0430\u0441\u0441\u043a\u0430\u0437\u043e\u0432\u043a\u0430"
    ],
    "wof:name":"Rasskazovka",
    "wof:placetype":"locality"
},
  "geometry": {"coordinates":[45.23333,52.36667],"type":"Point"}
}