{
  "type": "Feature",
  "properties": {
    "gn:admin1_code":"67",
    "gn:asciiname":"Rasskazovka",
    "gn:country_code":"RU",
    "gn:dem":205,
    "gn:feature_class":"P",
    "gn:feature_code":"PPL",
    "gn:name":"Rasskazovka",
    "gn:population":0,
    "gn:timezone":"Europe/Saratov",
    "iso:country":"RU",
    "name:bel_x_preferred":[
        "\u0420\u0430\u0441\u043a\u0430\u0437\u0430\u045e\u043a\u0430"
    ],
    "name:kat_x_preferred":[
        "\u10e0\u10d0\u10e1\u10d9\u10d0\u10d6\u10dd\u10d5\u10d9\u10d0"
    ],
    "name:kor_x_preferred":[
        "\ub77c\uc2a4\uce74\uc881\uce74 \uc5ed"
    ],
    "name:nld_x_preferred":[
        "Rasskazovka"
    ],
    "name:rus_x_preferred":[
        "\u0420\u0430\u0441\u0441\u043a\u0430\u0437\u043e\u0432\u043a\u0430"
    ],
    "name:ukr_x_preferred":[
        "\u0420\u0430\u0441\u0441\u043a\u0430\u0437\u043e\u0432\u043a\u0430"
    ],
    "name:zho_x_preferred":[
        "\u62c9\u65af\u5361\u4f50\u592b\u5361\u7ad9"
    ],
    "wof:name":"Rasskazovka",
    "wof:placetype":"locality"
},
  "geometry": {"coordinates":[45.23333,52.36667],"type":"Point"}
}