{
  "type": "Feature",
  "properties": {
    "gn:admin1_code":"71",
    "gn:asciiname":"Pervomayskiy",
    "gn:country_code":"RU",
    "gn:dem":261,
    "gn:feature_class":"P",
    "gn:feature_code":"PPL",
    "gn:name":"Pervomayskiy",
    "gn:population":0,
    "gn:timezone":"Asia/Yekaterinburg",
    "iso:country":"RU",
    "name:eng_x_preferred":[
        "Pervomayskiy"
    ],
    "name:nor_x_preferred":[
        "Pervomajskij"
    ],
    "name:rus_x_preferred":[
        "\u041f\u0435\u0440\u0432\u043e\u043c\u0430\u0439\u0441\u043a\u0438\u0439"
    ],
    "name:und_x_variant":[
        "Pervomayskoye",
        "\u041f\u0435\u0440\u0432\u043e\u043c\u0430\u0439\u0441\u043a\u0438\u0439",
        "Pervomayskiy"
    ],
    "wof:name":"Pervomayskiy",
    "wof:placetype":"locality"
},
  "geometry": {"coordinates":[58.855,56.9585],"type":"Point"}
}