{
  "type": "Feature",
  "properties": {
    "gn:admin1_code":"10",
    "gn:asciiname":"Gromovka",
    "gn:country_code":"RU",
    "gn:dem":172,
    "gn:feature_class":"P",
    "gn:feature_code":"PPL",
    "gn:name":"Gromovka",
    "gn:population":0,
    "gn:timezone":"Europe/Moscow",
    "iso:country":"RU",
    "name:rus_x_preferred":[
        "\u0413\u0440\u043e\u043c\u043e\u0432\u043a\u0430"
    ],
    "name:und_x_variant":[
        "\u0413\u0440\u043e\u043c\u043e\u0432\u043a\u0430"
    ],
    "wof:name":"Gromovka",
    "wof:placetype":"locality"
},
  "geometry": {"coordinates":[32.77611,52.51416999999999],"type":"Point"}
}