{
  "type": "Feature",
  "properties": {
    "gn:admin1_code":"77",
    "gn:asciiname":"Zadniy Bor",
    "gn:country_code":"RU",
    "gn:dem":234,
    "gn:feature_class":"P",
    "gn:feature_code":"PPL",
    "gn:name":"Zadniy Bor",
    "gn:population":0,
    "gn:timezone":"Europe/Moscow",
    "iso:country":"RU",
    "wof:name":"Zadniy Bor",
    "wof:placetype":"locality"
},
  "geometry": {"coordinates":[32.99083,56.73583000000001],"type":"Point"}
}