{
  "type": "Feature",
  "properties": {
    "gn:admin1_code":"21",
    "gn:asciiname":"Reshma",
    "gn:country_code":"RU",
    "gn:dem":111,
    "gn:feature_class":"P",
    "gn:feature_code":"PPL",
    "gn:name":"Reshma",
    "gn:population":0,
    "gn:timezone":"Europe/Moscow",
    "iso:country":"RU",
    "name:eng_x_preferred":[
        "Reshma"
    ],
    "name:nor_x_preferred":[
        "Resjma"
    ],
    "name:rus_x_preferred":[
        "\u0420\u0435\u0448\u043c\u0430"
    ],
    "name:und_x_variant":[
        "\u0420\u0435\u0448\u043c\u0430",
        "Reshma"
    ],
    "wof:name":"Reshma",
    "wof:placetype":"locality"
},
  "geometry": {"coordinates":[42.55676,57.40851],"type":"Point"}
}