{
  "type": "Feature",
  "properties": {
    "gn:admin1_code":"21",
    "gn:asciiname":"Reshma",
    "gn:country_code":"RU",
    "gn:dem":111,
    "gn:feature_class":"P",
    "gn:feature_code":"PPL",
    "gn:name":"Reshma",
    "gn:population":0,
    "gn:timezone":"Europe/Moscow",
    "iso:country":"RU",
    "name:ara_x_preferred":[
        "\u0631\u064a\u0634\u0645\u0627"
    ],
    "name:azb_x_preferred":[
        "\u0631\u06cc\u0634\u0645\u0627"
    ],
    "name:eng_x_preferred":[
        "Reshma"
    ],
    "name:hin_x_preferred":[
        "\u0930\u0947\u0936\u092e\u093e"
    ],
    "name:mal_x_preferred":[
        "\u0d30\u0d47\u0d37\u0d4d\u0d2e"
    ],
    "name:nor_x_preferred":[
        "Resjma"
    ],
    "name:pan_x_preferred":[
        "\u0a30\u0a47\u0a38\u0a3c\u0a2e\u0a3e"
    ],
    "name:pnb_x_preferred":[
        "\u0631\u06cc\u0634\u0645\u0627\u06ba"
    ],
    "name:rus_x_preferred":[
        "\u0420\u0435\u0448\u043c\u0430"
    ],
    "name:tam_x_preferred":[
        "\u0bb0\u0bc7\u0bb7\u0bcd\u0bae\u0bbe"
    ],
    "name:tel_x_preferred":[
        "\u0c30\u0c47\u0c37\u0c4d\u0c2e\u0c3e"
    ],
    "name:und_x_variant":[
        "\u0420\u0435\u0448\u043c\u0430",
        "Reshma"
    ],
    "name:urd_x_preferred":[
        "\u0631\u06cc\u0634\u0645\u0627\u06ba"
    ],
    "wof:name":"Reshma",
    "wof:placetype":"locality"
},
  "geometry": {"coordinates":[42.55676,57.40851],"type":"Point"}
}