{
  "type": "Feature",
  "properties": {
    "gn:admin1_code":"60",
    "gn:asciiname":"Medvedkovo",
    "gn:country_code":"RU",
    "gn:dem":98,
    "gn:feature_class":"P",
    "gn:feature_code":"PPL",
    "gn:name":"Medvedkovo",
    "gn:population":0,
    "gn:timezone":"Europe/Moscow",
    "iso:country":"RU",
    "name:rus_x_preferred":[
        "\u041c\u0435\u0434\u0432\u0435\u0434\u043a\u043e\u0432\u043e"
    ],
    "name:und_x_variant":[
        "Medvedovka",
        "Medvedkovo"
    ],
    "wof:name":"Medvedkovo",
    "wof:placetype":"locality"
},
  "geometry": {"coordinates":[30.62592,56.37843],"type":"Point"}
}