{
  "type": "Feature",
  "properties": {
    "gn:admin1_code":"90.0",
    "gn:asciiname":"Barkhatova",
    "gn:country_code":"RU",
    "gn:dem":96,
    "gn:feature_class":"P",
    "gn:feature_code":"PPL",
    "gn:name":"Barkhatova",
    "gn:population":0,
    "gn:timezone":"Asia/Yekaterinburg",
    "iso:country":"RU",
    "name:nor_x_preferred":[
        "Barkhatova"
    ],
    "name:rus_x_preferred":[
        "\u0411\u0430\u0440\u0445\u0430\u0442\u043e\u0432\u0430"
    ],
    "wof:name":"Barkhatova",
    "wof:placetype":"locality"
},
  "geometry": {"coordinates":[55.5287,57.2324],"type":"Point"}
}