{
  "type": "Feature",
  "properties": {
    "gn:admin1_code":"05",
    "gn:asciiname":"Bazisnaya",
    "gn:country_code":"RU",
    "gn:dem":294,
    "gn:feature_class":"P",
    "gn:feature_code":"PPL",
    "gn:name":"Bazisnaya",
    "gn:population":0,
    "gn:timezone":"Asia/Yakutsk",
    "iso:country":"RU",
    "name:eng_x_preferred":[
        "Bazisnaya"
    ],
    "name:rus_x_preferred":[
        "\u0411\u0430\u0437\u0438\u0441\u043d\u043e\u0435"
    ],
    "name:rus_x_variant":[
        "\u0411\u0430\u0437\u0438\u0441\u043d\u0430\u044f"
    ],
    "name:und_x_variant":[
        "Bazisniy",
        "Baziskoye"
    ],
    "wof:name":"Bazisnaya",
    "wof:placetype":"locality"
},
  "geometry": {"coordinates":[127.67479,52.13888],"type":"Point"}
}