{
  "type": "Feature",
  "properties": {
    "gn:admin1_code":"85",
    "gn:asciiname":"Natsepino",
    "gn:country_code":"RU",
    "gn:dem":107,
    "gn:feature_class":"P",
    "gn:feature_code":"PPL",
    "gn:name":"Natsepino",
    "gn:population":0,
    "gn:timezone":"Europe/Moscow",
    "iso:country":"RU",
    "name:rus_x_preferred":[
        "\u041d\u0430\u0446\u0435\u043f\u0438\u043d\u043e"
    ],
    "name:und_x_variant":[
        "\u041d\u0430\u0446\u0435\u043f\u0438\u043d\u043e"
    ],
    "wof:name":"Natsepino",
    "wof:placetype":"locality"
},
  "geometry": {"coordinates":[46.73334000000001,60.50317],"type":"Point"}
}