{
  "type": "Feature",
  "properties": {
    "gn:admin1_code":"77.0",
    "gn:asciiname":"Gavril'tsevo",
    "gn:country_code":"RU",
    "gn:dem":209,
    "gn:feature_class":"P",
    "gn:feature_code":"PPL",
    "gn:name":"Gavril\u2019tsevo",
    "gn:population":0,
    "gn:timezone":"Europe/Moscow",
    "iso:country":"RU",
    "name:rus_x_preferred":[
        "\u0413\u0430\u0432\u0440\u0438\u043b\u044c\u0446\u0435\u0432\u043e"
    ],
    "name:und_x_variant":[
        "Gavril\u2019tsevo",
        "\u0413\u0430\u0432\u0440\u0438\u043b\u044c\u0446\u0435\u0432\u043e"
    ],
    "wof:name":"Gavril'tsevo",
    "wof:placetype":"locality"
},
  "geometry": {"coordinates":[35.01153,58.15083000000001],"type":"Point"}
}