{
  "type": "Feature",
  "properties": {
    "gn:admin1_code":"28",
    "gn:asciiname":"Kyulyusel'ga",
    "gn:country_code":"RU",
    "gn:dem":122,
    "gn:feature_class":"P",
    "gn:feature_code":"PPL",
    "gn:name":"Kyulyusel\u2019ga",
    "gn:population":0,
    "gn:timezone":"Europe/Moscow",
    "iso:country":"RU",
    "name:fin_x_preferred":[
        "Kylyselk\u00e4"
    ],
    "name:und_x_variant":[
        "Kyulyusel\u2019ga"
    ],
    "wof:name":"Kyulyusel'ga",
    "wof:placetype":"locality"
},
  "geometry": {"coordinates":[32.98333,61.88333000000001],"type":"Point"}
}