{
  "type": "Feature",
  "properties": {
    "gn:admin1_code":"90",
    "gn:asciiname":"Rezka",
    "gn:country_code":"RU",
    "gn:dem":147,
    "gn:feature_class":"P",
    "gn:feature_code":"PPL",
    "gn:name":"Rezka",
    "gn:population":0,
    "gn:timezone":"Asia/Yekaterinburg",
    "iso:country":"RU",
    "name:rus_x_preferred":[
        "\u0420\u0435\u0437\u043a\u0430"
    ],
    "name:und_x_variant":[
        "Bol\u2019shaya Rezka",
        "Rezka",
        "\u0420\u0435\u0437\u043a\u0430"
    ],
    "wof:name":"Rezka",
    "wof:placetype":"locality"
},
  "geometry": {"coordinates":[54.7637,58.43959],"type":"Point"}
}