{
  "type": "Feature",
  "properties": {
    "gn:admin1_code":"77",
    "gn:asciiname":"Bakharevo",
    "gn:country_code":"RU",
    "gn:dem":174,
    "gn:feature_class":"P",
    "gn:feature_code":"PPL",
    "gn:name":"Bakhar\u00ebvo",
    "gn:population":0,
    "gn:timezone":"Europe/Moscow",
    "iso:country":"RU",
    "name:rus_x_preferred":[
        "\u0411\u0430\u0445\u0430\u0440\u0451\u0432\u043e"
    ],
    "name:und_x_variant":[
        "Bakhar\u00ebvo",
        "\u0411\u0430\u0445\u0430\u0440\u0451\u0432\u043e"
    ],
    "wof:name":"Bakharevo",
    "wof:placetype":"locality"
},
  "geometry": {"coordinates":[36.5512,57.3923],"type":"Point"}
}