{
  "type": "Feature",
  "properties": {
    "gn:admin1_code":"69",
    "gn:asciiname":"Valukhovo",
    "gn:cc2":"RU",
    "gn:country_code":"RU",
    "gn:dem":175,
    "gn:feature_class":"P",
    "gn:feature_code":"PPL",
    "gn:name":"Valukhovo",
    "gn:population":0,
    "gn:timezone":"Europe/Moscow",
    "iso:country":"RU",
    "name:und_x_variant":[
        "Valulova",
        "Valukhovo"
    ],
    "wof:name":"Valukhovo",
    "wof:placetype":"locality"
},
  "geometry": {"coordinates":[34.98472,54.97917],"type":"Point"}
}