{
  "type": "Feature",
  "properties": {
    "gn:admin1_code":"52",
    "gn:asciiname":"Zapolek",
    "gn:country_code":"RU",
    "gn:dem":73,
    "gn:feature_class":"P",
    "gn:feature_code":"PPL",
    "gn:name":"Zapolek",
    "gn:population":0,
    "gn:timezone":"Europe/Moscow",
    "iso:country":"RU",
    "name:und_x_variant":[
        "Zapol\u2019ka",
        "Zapolek"
    ],
    "wof:name":"Zapolek",
    "wof:placetype":"locality"
},
  "geometry": {"coordinates":[33.785,58.4875],"type":"Point"}
}