{
  "type": "Feature",
  "properties": {
    "gn:admin1_code":"52",
    "gn:asciiname":"Kolotilovo",
    "gn:country_code":"RU",
    "gn:dem":96,
    "gn:feature_class":"P",
    "gn:feature_code":"PPL",
    "gn:name":"Kolotilovo",
    "gn:population":0,
    "gn:timezone":"Europe/Moscow",
    "iso:country":"RU",
    "name:rus_x_preferred":[
        "\u041a\u043e\u043b\u043e\u0442\u0438\u043b\u043e\u0432\u043e"
    ],
    "wof:name":"Kolotilovo",
    "wof:placetype":"locality"
},
  "geometry": {"coordinates":[30.6633,57.7986],"type":"Point"}
}