{
  "type": "Feature",
  "properties": {
    "gn:admin1_code":"29",
    "gn:asciiname":"Berezovo",
    "gn:country_code":"RU",
    "gn:dem":121,
    "gn:feature_class":"P",
    "gn:feature_code":"PPL",
    "gn:name":"Ber\u00ebzovo",
    "gn:population":0,
    "gn:timezone":"Asia/Novokuznetsk",
    "iso:country":"RU",
    "name:ceb_x_preferred":[
        "Berezovo"
    ],
    "name:deu_x_preferred":[
        "Berjosowo"
    ],
    "name:eng_x_preferred":[
        "Ber\u00ebzovo"
    ],
    "name:hye_x_preferred":[
        "\u0532\u0565\u0580\u0575\u0578\u0566\u0578\u057e\u0578"
    ],
    "name:rus_x_preferred":[
        "\u0411\u0435\u0440\u0435\u0437\u043e\u0432\u043e"
    ],
    "name:rus_x_variant":[
        "\u0411\u0435\u0440\u0451\u0437\u043e\u0432\u043e"
    ],
    "name:tgk_x_preferred":[
        "\u0411\u0435\u0440\u0435\u0437\u043e\u0432\u043e"
    ],
    "name:ukr_x_preferred":[
        "\u0411\u0435\u0440\u0435\u0437\u043e\u0432\u043e"
    ],
    "name:und_x_variant":[
        "Berezovaya",
        "Berezova",
        "Berezovka",
        "Ber\u00ebzovo"
    ],
    "wof:name":"Berezovo",
    "wof:placetype":"locality"
},
  "geometry": {"coordinates":[86.25,55.23333],"type":"Point"}
}