{
  "type": "Feature",
  "properties": {
    "gn:admin1_code":"57",
    "gn:asciiname":"Sinodskoye",
    "gn:country_code":"RU",
    "gn:dem":232,
    "gn:feature_class":"P",
    "gn:feature_code":"PPL",
    "gn:name":"Sinodskoye",
    "gn:population":0,
    "gn:timezone":"Europe/Moscow",
    "iso:country":"RU",
    "name:eng_x_preferred":[
        "Sinodskoye"
    ],
    "name:nor_x_preferred":[
        "Sinodskoje"
    ],
    "name:rus_x_preferred":[
        "\u0421\u0438\u043d\u043e\u0434\u0441\u043a\u043e\u0435"
    ],
    "wof:name":"Sinodskoye",
    "wof:placetype":"locality"
},
  "geometry": {"coordinates":[45.40786,52.68329],"type":"Point"}
}