{
  "type": "Feature",
  "properties": {
    "gn:admin1_code":"54",
    "gn:asciiname":"Yeremeyevka",
    "gn:country_code":"RU",
    "gn:dem":119,
    "gn:feature_class":"P",
    "gn:feature_code":"PPL",
    "gn:name":"Yeremeyevka",
    "gn:population":0,
    "gn:timezone":"Asia/Omsk",
    "iso:country":"RU",
    "name:eng_x_preferred":[
        "Yeremeyevka"
    ],
    "name:nor_x_preferred":[
        "Jeremejevka"
    ],
    "name:rus_x_preferred":[
        "\u0415\u0440\u0435\u043c\u0435\u0435\u0432\u043a\u0430"
    ],
    "name:und_x_variant":[
        "\u0415\u0440\u0435\u043c\u0435\u0435\u0432\u043a\u0430"
    ],
    "wof:name":"Yeremeyevka",
    "wof:placetype":"locality"
},
  "geometry": {"coordinates":[72.04649999999999,54.2808],"type":"Point"}
}