{
  "type": "Feature",
  "properties": {
    "gn:admin1_code":"23",
    "gn:asciiname":"Kozhedubovo",
    "gn:country_code":"RU",
    "gn:dem":-3,
    "gn:feature_class":"P",
    "gn:feature_code":"PPL",
    "gn:name":"Kozhedubovo",
    "gn:population":0,
    "gn:timezone":"Europe/Kaliningrad",
    "iso:country":"RU",
    "name:rus_x_preferred":[
        "\u041a\u043e\u0436\u0435\u0434\u0443\u0431\u043e\u0432\u043e"
    ],
    "name:und_x_variant":[
        "\u041a\u043e\u0436\u0435\u0434\u0443\u0431\u043e\u0432\u043e"
    ],
    "wof:name":"Kozhedubovo",
    "wof:placetype":"locality"
},
  "geometry": {"coordinates":[21.58931,55.00845],"type":"Point"}
}