{
  "type": "Feature",
  "properties": {
    "gn:admin1_code":"68",
    "gn:asciiname":"Sel'khoztekhnika",
    "gn:country_code":"RU",
    "gn:dem":444,
    "gn:feature_class":"P",
    "gn:feature_code":"PPL",
    "gn:name":"Sel\u2019khoztekhnika",
    "gn:population":0,
    "gn:timezone":"Europe/Moscow",
    "iso:country":"RU",
    "name:rus_x_preferred":[
        "\u0421\u0435\u043b\u044c\u0445\u043e\u0437\u0442\u0435\u0445\u043d\u0438\u043a\u0430"
    ],
    "name:und_x_variant":[
        "Sel\u2019khoztekhnika"
    ],
    "wof:name":"Sel'khoztekhnika",
    "wof:placetype":"locality"
},
  "geometry": {"coordinates":[44.4852,43.25242],"type":"Point"}
}