{
  "type": "Feature",
  "properties": {
    "gn:admin1_code":"71",
    "gn:asciiname":"Zhiryakova",
    "gn:country_code":"RU",
    "gn:dem":63,
    "gn:feature_class":"P",
    "gn:feature_code":"PPL",
    "gn:name":"Zhiryakova",
    "gn:population":0,
    "gn:timezone":"Asia/Yekaterinburg",
    "iso:country":"RU",
    "name:rus_x_preferred":[
        "\u0416\u0438\u0440\u044f\u043a\u043e\u0432\u0430"
    ],
    "name:und_x_variant":[
        "Zhiryakovo",
        "Zhiryakova",
        "\u0416\u0438\u0440\u044f\u043a\u043e\u0432\u0430"
    ],
    "wof:name":"Zhiryakova",
    "wof:placetype":"locality"
},
  "geometry": {"coordinates":[64.55856999999999,57.50075],"type":"Point"}
}