{
  "type": "Feature",
  "properties": {
    "gn:admin1_code":"11",
    "gn:asciiname":"Domna",
    "gn:country_code":"RU",
    "gn:dem":965,
    "gn:feature_class":"P",
    "gn:feature_code":"PPL",
    "gn:name":"Domna",
    "gn:population":0,
    "gn:timezone":"Asia/Irkutsk",
    "iso:country":"RU",
    "name:ceb_x_preferred":[
        "Domna"
    ],
    "name:deu_x_preferred":[
        "Domna"
    ],
    "name:rus_x_preferred":[
        "\u0414\u043e\u043c\u043d\u0430"
    ],
    "name:und_x_variant":[
        "Sobolka",
        "Domna"
    ],
    "wof:name":"Domna",
    "wof:placetype":"locality"
},
  "geometry": {"coordinates":[111.71447999999999,52.56207],"type":"Point"}
}