{
  "type": "Feature",
  "properties": {
    "gn:admin1_code":"77",
    "gn:asciiname":"V'yugovo",
    "gn:country_code":"RU",
    "gn:dem":145,
    "gn:feature_class":"P",
    "gn:feature_code":"PPL",
    "gn:name":"V\u2019yugovo",
    "gn:population":0,
    "gn:timezone":"Europe/Moscow",
    "iso:country":"RU",
    "name:rus_x_preferred":[
        "\u0412\u044c\u044e\u0433\u043e\u0432\u043e"
    ],
    "name:und_x_variant":[
        "V\u2019yugovo",
        "\u0412\u044c\u044e\u0433\u043e\u0432\u043e"
    ],
    "wof:name":"V'yugovo",
    "wof:placetype":"locality"
},
  "geometry": {"coordinates":[36.7942,57.8022],"type":"Point"}
}