{
  "type": "Feature",
  "properties": {
    "gn:admin1_code":"24",
    "gn:asciiname":"Zernovoye",
    "gn:country_code":"RU",
    "gn:dem":67,
    "gn:feature_class":"P",
    "gn:feature_code":"PPL",
    "gn:name":"Zernovoye",
    "gn:population":0,
    "gn:timezone":"Europe/Moscow",
    "iso:country":"RU",
    "name:eng_x_preferred":[
        "Zernovoye"
    ],
    "name:nor_x_preferred":[
        "Zernovoje"
    ],
    "name:rus_x_preferred":[
        "\u0417\u0435\u0440\u043d\u043e\u0432\u043e\u0435"
    ],
    "name:und_x_variant":[
        "Menguta",
        "Zernovoye"
    ],
    "wof:name":"Zernovoye",
    "wof:placetype":"locality"
},
  "geometry": {"coordinates":[42.3764,46.1395],"type":"Point"}
}