{
  "type": "Feature",
  "properties": {
    "gn:admin1_code":"10",
    "gn:asciiname":"Khot'yanovka",
    "gn:country_code":"RU",
    "gn:dem":187,
    "gn:feature_class":"P",
    "gn:feature_code":"PPL",
    "gn:name":"Khot\u2019yanovka",
    "gn:population":0,
    "gn:timezone":"Europe/Moscow",
    "iso:country":"RU",
    "name:rus_x_preferred":[
        "\u0425\u043e\u0442\u044c\u044f\u043d\u043e\u0432\u043a\u0430"
    ],
    "name:rus_x_variant":[
        "Khot\u2019yanovka"
    ],
    "wof:name":"Khot'yanovka",
    "wof:placetype":"locality"
},
  "geometry": {"coordinates":[33.55069,52.54691999999999],"type":"Point"}
}