{
  "type": "Feature",
  "properties": {
    "gn:admin1_code":"6",
    "gn:asciiname":"Zaboloto",
    "gn:country_code":"RU",
    "gn:dem":189,
    "gn:feature_class":"P",
    "gn:feature_code":"PPL",
    "gn:name":"Zaboloto",
    "gn:population":0,
    "gn:timezone":"Europe/Moscow",
    "iso:country":"RU",
    "name:rus_x_preferred":[
        "\u0417\u0430\u0431\u043e\u043b\u043e\u0442\u043e"
    ],
    "name:und_x_variant":[
        "Zabolotnaya",
        "Zaboloto"
    ],
    "wof:name":"Zaboloto",
    "wof:placetype":"locality"
},
  "geometry": {"coordinates":[40.8022,60.7529],"type":"Point"}
}