{
  "type": "Feature",
  "properties": {
    "gn:admin1_code":"88",
    "gn:asciiname":"Rodyukino",
    "gn:country_code":"RU",
    "gn:dem":127,
    "gn:feature_class":"P",
    "gn:feature_code":"PPL",
    "gn:name":"Rodyukino",
    "gn:population":0,
    "gn:timezone":"Europe/Moscow",
    "iso:country":"RU",
    "name:und_x_variant":[
        "Radyukino",
        "Rodyukino"
    ],
    "wof:name":"Rodyukino",
    "wof:placetype":"locality"
},
  "geometry": {"coordinates":[40.24323,57.48405],"type":"Point"}
}