{
  "type": "Feature",
  "properties": {
    "gn:admin1_code":"8.0",
    "gn:asciiname":"Abdrakhmanovo",
    "gn:country_code":"RU",
    "gn:dem":365,
    "gn:feature_class":"P",
    "gn:feature_code":"PPL",
    "gn:name":"Abdrakhmanovo",
    "gn:population":0,
    "gn:timezone":"Asia/Yekaterinburg",
    "iso:country":"RU",
    "name:nor_x_preferred":[
        "Abdrakhmanovo"
    ],
    "name:rus_x_preferred":[
        "\u0410\u0431\u0434\u0440\u0430\u0445\u043c\u0430\u043d\u043e\u0432\u043e"
    ],
    "name:und_x_variant":[
        "Abdurakhmanovo",
        "Abdurakhmanova",
        "Abdrakhmanovo"
    ],
    "wof:name":"Abdrakhmanovo",
    "wof:placetype":"locality"
},
  "geometry": {"coordinates":[58.625,52.55639],"type":"Point"}
}