{
  "type": "Feature",
  "properties": {
    "gn:country":"RU",
    "gn:fcode":"PPL",
    "gn:population":0,
    "iso:country":"RU",
    "name:rus_x_preferred":[
        "\u041b\u044b\u0449\u0435\u0432\u043e"
    ],
    "qs:name":"Lyshchevo",
    "qs:name_adm0":"Russia",
    "qs:name_adm1":"Kostroma Oblast",
    "qs:photos_9r":0,
    "qs:photos_sr":0,
    "qs:placetype":"Town",
    "qs:pop_sr":"0",
    "wof:name":"Lyshchevo",
    "wof:placetype":"locality",
    "wof:population":0
},
  "geometry": {"coordinates":[41.06074,57.5928],"type":"Point"}
}