{
  "type": "Feature",
  "properties": {
    "gn:admin1_code":"13",
    "gn:asciiname":"Astaf'yevskiy",
    "gn:country_code":"RU",
    "gn:dem":365,
    "gn:feature_class":"P",
    "gn:feature_code":"PPL",
    "gn:name":"Astaf\u2019yevskiy",
    "gn:population":0,
    "gn:timezone":"Asia/Yekaterinburg",
    "iso:country":"RU",
    "name:eng_x_preferred":[
        "Astaf'yevskiy"
    ],
    "name:rus_x_preferred":[
        "\u0410\u0441\u0442\u0430\u0444\u044c\u0435\u0432\u043a\u0430"
    ],
    "name:rus_x_variant":[
        "\u0410\u0441\u0442\u0430\u0444\u044c\u0435\u0432\u0441\u043a\u0438\u0439"
    ],
    "name:und_x_variant":[
        "Astaf\u2019yevskiy"
    ],
    "wof:name":"Astaf'yevskiy",
    "wof:placetype":"locality"
},
  "geometry": {"coordinates":[60.07028,53.47600000000001],"type":"Point"}
}