{
  "type": "Feature",
  "properties": {
    "gn:admin1_code":"30",
    "gn:asciiname":"Vesenniy",
    "gn:cc2":"RU",
    "gn:country_code":"RU",
    "gn:dem":166,
    "gn:feature_class":"P",
    "gn:feature_code":"PPL",
    "gn:name":"Vesenniy",
    "gn:population":0,
    "gn:timezone":"Asia/Vladivostok",
    "iso:country":"RU",
    "name:und_x_variant":[
        "Orogo",
        "Ivanovskaya",
        "Vesenniy"
    ],
    "wof:name":"Vesenniy",
    "wof:placetype":"locality"
},
  "geometry": {"coordinates":[135.88333,52.35],"type":"Point"}
}