{
  "type": "Feature",
  "properties": {
    "gn:admin1_code":"37",
    "gn:asciiname":"Shalabino",
    "gn:country_code":"RU",
    "gn:dem":162,
    "gn:feature_class":"P",
    "gn:feature_code":"PPL",
    "gn:name":"Shalabino",
    "gn:population":0,
    "gn:timezone":"Europe/Moscow",
    "iso:country":"RU",
    "name:rus_x_preferred":[
        "\u0428\u0430\u043b\u0430\u0431\u0438\u043d\u043e"
    ],
    "name:und_x_variant":[
        "\u0428\u0430\u043b\u0430\u0431\u0438\u043d\u043e"
    ],
    "wof:name":"Shalabino",
    "wof:placetype":"locality"
},
  "geometry": {"coordinates":[42.1855,58.3606],"type":"Point"}
}