{
  "type": "Feature",
  "properties": {
    "gn:admin1_code":"55",
    "gn:asciiname":"Karpovka",
    "gn:country_code":"RU",
    "gn:dem":167,
    "gn:feature_class":"P",
    "gn:feature_code":"PPL",
    "gn:name":"Karpovka",
    "gn:population":0,
    "gn:timezone":"Asia/Yekaterinburg",
    "iso:country":"RU",
    "name:eng_x_preferred":[
        "Karpovka"
    ],
    "name:nor_x_preferred":[
        "Karpovka"
    ],
    "name:rus_x_preferred":[
        "\u041a\u0430\u0440\u043f\u043e\u0432\u043a\u0430"
    ],
    "name:und_x_variant":[
        "Karpovskiy",
        "\u041a\u0430\u0440\u043f\u043e\u0432\u043a\u0430",
        "Karpovka"
    ],
    "wof:name":"Karpovka",
    "wof:placetype":"locality"
},
  "geometry": {"coordinates":[56.055,51.11712],"type":"Point"}
}