{
  "type": "Feature",
  "properties": {
    "gn:admin1_code":"91",
    "gn:asciiname":"Novyy Put'",
    "gn:country_code":"RU",
    "gn:dem":152,
    "gn:feature_class":"P",
    "gn:feature_code":"PPL",
    "gn:name":"Novyy Put\u2019",
    "gn:population":0,
    "gn:timezone":"Asia/Krasnoyarsk",
    "iso:country":"RU",
    "name:eng_x_preferred":[
        "Novyy Put'"
    ],
    "name:nor_x_preferred":[
        "Nov.Put"
    ],
    "name:rus_x_preferred":[
        "\u041d\u043e\u0432.\u041f\u0443\u0442\u044c"
    ],
    "name:rus_x_variant":[
        "\u041d\u043e\u0432\u044b\u0439 \u041f\u0443\u0442\u044c"
    ],
    "name:und_x_variant":[
        "Novyy Put\u2019"
    ],
    "wof:name":"Novyy Put'",
    "wof:placetype":"locality"
},
  "geometry": {"coordinates":[93.46693999999999,56.16361],"type":"Point"}
}