{
  "type": "Feature",
  "properties": {
    "gn:admin1_code":"28",
    "gn:asciiname":"Syurga",
    "gn:country_code":"RU",
    "gn:dem":90,
    "gn:feature_class":"P",
    "gn:feature_code":"PPL",
    "gn:name":"Syurga",
    "gn:population":0,
    "gn:timezone":"Europe/Moscow",
    "iso:country":"RU",
    "name:fin_x_preferred":[
        "Syrj\u00e4"
    ],
    "name:vep_x_preferred":[
        "S\u00fcrd\u2019"
    ],
    "wof:name":"Syurga",
    "wof:placetype":"locality"
},
  "geometry": {"coordinates":[35.06667,61.43333000000001],"type":"Point"}
}