{
  "type": "Feature",
  "properties": {
    "gn:admin1_code":"69",
    "gn:asciiname":"Khitrova",
    "gn:country_code":"RU",
    "gn:dem":194,
    "gn:feature_class":"P",
    "gn:feature_code":"PPL",
    "gn:name":"Khitrova",
    "gn:population":0,
    "gn:timezone":"Europe/Moscow",
    "iso:country":"RU",
    "name:rus_x_preferred":[
        "\u0425\u0438\u0442\u0440\u043e\u0432\u0430"
    ],
    "name:und_x_variant":[
        "\u0425\u0438\u0442\u0440\u043e\u0432\u0430"
    ],
    "wof:name":"Khitrova",
    "wof:placetype":"locality"
},
  "geometry": {"coordinates":[33.59917,55.3225],"type":"Point"}
}