{
  "type": "Feature",
  "properties": {
    "gn:admin1_code":"91.0",
    "gn:asciiname":"Vorob'yevka",
    "gn:country_code":"RU",
    "gn:dem":231,
    "gn:feature_class":"P",
    "gn:feature_code":"PPL",
    "gn:name":"Vorob\u2019y\u00ebvka",
    "gn:population":0,
    "gn:timezone":"Asia/Krasnoyarsk",
    "iso:country":"RU",
    "name:rus_x_preferred":[
        "\u0412\u043e\u0440\u043e\u0431\u044c\u00eb\u0432\u043a\u0430"
    ],
    "name:und_x_variant":[
        "Vorob\u2019y\u00ebvka"
    ],
    "wof:name":"Vorob'yevka",
    "wof:placetype":"locality"
},
  "geometry": {"coordinates":[96.03228,56.7231],"type":"Point"}
}