{
  "type": "Feature",
  "properties": {
    "gn:admin1_code":"25",
    "gn:asciiname":"Komola",
    "gn:country_code":"RU",
    "gn:dem":214,
    "gn:feature_class":"P",
    "gn:feature_code":"PPL",
    "gn:name":"Komola",
    "gn:population":0,
    "gn:timezone":"Europe/Moscow",
    "iso:country":"RU",
    "name:nor_x_preferred":[
        "Komola"
    ],
    "name:rus_x_preferred":[
        "\u041a\u043e\u043c\u043e\u043b\u0430"
    ],
    "wof:name":"Komola",
    "wof:placetype":"locality"
},
  "geometry": {"coordinates":[36.65107,54.50971],"type":"Point"}
}