{
  "type": "Feature",
  "properties": {
    "gn:admin1_code":"21",
    "gn:asciiname":"Roshma",
    "gn:country_code":"RU",
    "gn:dem":123,
    "gn:feature_class":"P",
    "gn:feature_code":"PPL",
    "gn:name":"Roshma",
    "gn:population":0,
    "gn:timezone":"Europe/Moscow",
    "iso:country":"RU",
    "name:rus_x_preferred":[
        "\u0420\u043e\u0448\u043c\u0430"
    ],
    "wof:name":"Roshma",
    "wof:placetype":"locality"
},
  "geometry": {"coordinates":[41.83516,57.26797],"type":"Point"}
}