{
  "type": "Feature",
  "properties": {
    "gn:admin1_code":"44",
    "gn:asciiname":"Gerba",
    "gn:country_code":"RU",
    "gn:dem":696,
    "gn:feature_class":"P",
    "gn:feature_code":"PPL",
    "gn:name":"Gerba",
    "gn:population":0,
    "gn:timezone":"Asia/Magadan",
    "iso:country":"RU",
    "name:ceb_x_preferred":[
        "Gerba"
    ],
    "name:fra_x_preferred":[
        "Gerba"
    ],
    "name:ita_x_preferred":[
        "Gerba"
    ],
    "name:rus_x_preferred":[
        "\u0413\u0435\u0440\u0431\u0430"
    ],
    "name:spa_x_preferred":[
        "Gerba"
    ],
    "wof:name":"Gerba",
    "wof:placetype":"locality"
},
  "geometry": {"coordinates":[152.11667,61.95],"type":"Point"}
}