{
  "type": "Feature",
  "properties": {
    "gn:admin1_code":"53",
    "gn:asciiname":"Novokandakovo",
    "gn:country_code":"RU",
    "gn:dem":106,
    "gn:feature_class":"P",
    "gn:feature_code":"PPL",
    "gn:name":"Novokandakovo",
    "gn:population":0,
    "gn:timezone":"Asia/Novosibirsk",
    "iso:country":"RU",
    "name:rus_x_preferred":[
        "\u041d\u043e\u0432\u043e\u043a\u0430\u043d\u0434\u0430\u043a\u043e\u0432\u043e"
    ],
    "name:und_x_variant":[
        "Novo-Kandakova",
        "Novokandakovo",
        "\u041d\u043e\u0432\u043e\u043a\u0430\u043d\u0434\u0430\u043a\u043e\u0432\u043e"
    ],
    "wof:name":"Novokandakovo",
    "wof:placetype":"locality"
},
  "geometry": {"coordinates":[77.60287,55.44893],"type":"Point"}
}