{
  "type": "Feature",
  "properties": {
    "gn:admin1_code":"42",
    "gn:asciiname":"Karasevka",
    "gn:country_code":"RU",
    "gn:dem":17,
    "gn:feature_class":"P",
    "gn:feature_code":"PPL",
    "gn:name":"Karas\u00ebvka",
    "gn:population":0,
    "gn:timezone":"Europe/Moscow",
    "iso:country":"RU",
    "name:fin_x_preferred":[
        "Penttil\u00e4"
    ],
    "name:rus_x_preferred":[
        "\u041a\u0430\u0440\u0430\u0441\u0451\u0432\u043a\u0430"
    ],
    "name:und_x_variant":[
        "Penttilya",
        "Pentilia",
        "Pentilya",
        "Karas\u00ebvka"
    ],
    "wof:name":"Karasevka",
    "wof:placetype":"locality"
},
  "geometry": {"coordinates":[28.67876,60.34709],"type":"Point"}
}