{
  "type": "Feature",
  "properties": {
    "gn:admin1_code":"47",
    "gn:asciiname":"Terent'yevo",
    "gn:country_code":"RU",
    "gn:dem":183,
    "gn:feature_class":"P",
    "gn:feature_code":"PPL",
    "gn:name":"Terent\u2019yevo",
    "gn:population":0,
    "gn:timezone":"Europe/Moscow",
    "iso:country":"RU",
    "name:und_x_variant":[
        "Tevent\u2019yevo",
        "Terent\u2019yevo"
    ],
    "wof:name":"Terent'yevo",
    "wof:placetype":"locality"
},
  "geometry": {"coordinates":[35.885,55.98917],"type":"Point"}
}