{
  "type": "Feature",
  "properties": {
    "gn:admin1_code":"83",
    "gn:asciiname":"Nepeytsyno",
    "gn:country_code":"RU",
    "gn:dem":139,
    "gn:feature_class":"P",
    "gn:feature_code":"PPL",
    "gn:name":"Nepeytsyno",
    "gn:population":0,
    "gn:timezone":"Europe/Moscow",
    "iso:country":"RU",
    "name:rus_x_preferred":[
        "\u041d\u0435\u043f\u0435\u0439\u0446\u044b\u043d\u043e"
    ],
    "name:und_x_variant":[
        "Nepeytsino",
        "Nepeytsyno",
        "\u041d\u0435\u043f\u0435\u0439\u0446\u044b\u043d\u043e"
    ],
    "wof:name":"Nepeytsyno",
    "wof:placetype":"locality"
},
  "geometry": {"coordinates":[41.053,55.9858],"type":"Point"}
}