{
  "type": "Feature",
  "properties": {
    "gn:admin1_code":"76",
    "gn:asciiname":"Seleznevo",
    "gn:country_code":"RU",
    "gn:dem":242,
    "gn:feature_class":"P",
    "gn:feature_code":"PPL",
    "gn:name":"Selezn\u00ebvo",
    "gn:population":0,
    "gn:timezone":"Europe/Moscow",
    "iso:country":"RU",
    "name:eng_x_preferred":[
        "Selezn\u00ebvo"
    ],
    "name:nor_x_preferred":[
        "Seleznevo"
    ],
    "name:rus_x_preferred":[
        "\u0421\u0435\u043b\u0435\u0437\u043d\u0435\u0432\u043e"
    ],
    "name:rus_x_variant":[
        "\u0421\u0435\u043b\u0435\u0437\u043d\u0451\u0432\u043e"
    ],
    "name:und_x_variant":[
        "Seleznev Kolodez\u2019",
        "Selezn\u00ebvo",
        "\u0421\u0435\u043b\u0435\u0437\u043d\u0451\u0432\u043e"
    ],
    "wof:name":"Seleznevo",
    "wof:placetype":"locality"
},
  "geometry": {"coordinates":[37.11975,53.61189],"type":"Point"}
}