{
  "type": "Feature",
  "properties": {
    "gn:admin1_code":"42",
    "gn:asciiname":"Vartemyagi",
    "gn:country_code":"RU",
    "gn:dem":55,
    "gn:feature_class":"P",
    "gn:feature_code":"PPL",
    "gn:name":"Vartemyagi",
    "gn:population":0,
    "gn:timezone":"Europe/Moscow",
    "iso:country":"RU",
    "name:eng_x_preferred":[
        "Vartemyagi"
    ],
    "name:fin_x_preferred":[
        "Vartiom\u00e4ki"
    ],
    "name:nor_x_preferred":[
        "Vartemjagi"
    ],
    "name:rus_x_preferred":[
        "\u0412\u0430\u0440\u0442\u0435\u043c\u044f\u0433\u0438"
    ],
    "name:und_x_variant":[
        "Vartemyaki",
        "Vartemyagi"
    ],
    "wof:name":"Vartemyagi",
    "wof:placetype":"locality"
},
  "geometry": {"coordinates":[30.33214000000001,60.17738000000001],"type":"Point"}
}