{
  "type": "Feature",
  "properties": {
    "gn:admin1_code":"42",
    "gn:asciiname":"Nakol",
    "gn:country_code":"RU",
    "gn:dem":63,
    "gn:feature_class":"P",
    "gn:feature_code":"PPL",
    "gn:name":"Nakol",
    "gn:population":0,
    "gn:timezone":"Europe/Moscow",
    "iso:country":"RU",
    "name:nor_x_preferred":[
        "Nakol"
    ],
    "name:pol_x_preferred":[
        "Nakol"
    ],
    "name:rus_x_preferred":[
        "\u041d\u0430\u043a\u043e\u043b"
    ],
    "name:ukr_x_preferred":[
        "\u041d\u0430\u043a\u043e\u043b\u044c"
    ],
    "wof:name":"Nakol",
    "wof:placetype":"locality"
},
  "geometry": {"coordinates":[29.50361,59.04847],"type":"Point"}
}