{
  "type": "Feature",
  "properties": {
    "gn:admin1_code":"38",
    "gn:asciiname":"Svobodnyy",
    "gn:country_code":"RU",
    "gn:dem":57,
    "gn:feature_class":"P",
    "gn:feature_code":"PPL",
    "gn:name":"Svobodnyy",
    "gn:population":0,
    "gn:timezone":"Europe/Moscow",
    "iso:country":"RU",
    "name:rus_x_preferred":[
        "\u0421\u0432\u043e\u0431\u043e\u0434\u043d\u044b\u0439"
    ],
    "name:und_x_variant":[
        "Svobodny",
        "Svobodnyy"
    ],
    "wof:name":"Svobodnyy",
    "wof:placetype":"locality"
},
  "geometry": {"coordinates":[39.53245,45.35018],"type":"Point"}
}