{
  "type": "Feature",
  "properties": {
    "gn:admin1_code":"42",
    "gn:asciiname":"Vyskatka",
    "gn:country_code":"RU",
    "gn:dem":65,
    "gn:feature_class":"P",
    "gn:feature_code":"PPL",
    "gn:name":"Vyskatka",
    "gn:population":0,
    "gn:timezone":"Europe/Moscow",
    "iso:country":"RU",
    "name:eng_x_preferred":[
        "Vyskatka"
    ],
    "name:nor_x_preferred":[
        "Vyskatka"
    ],
    "name:rus_x_preferred":[
        "\u0412\u044b\u0441\u043a\u0430\u0442\u043a\u0430"
    ],
    "wof:name":"Vyskatka",
    "wof:placetype":"locality"
},
  "geometry": {"coordinates":[28.18172,59.02144000000001],"type":"Point"}
}