{
  "type": "Feature",
  "properties": {
    "gn:admin1_code":"88",
    "gn:asciiname":"Sedel'nitsy",
    "gn:country_code":"RU",
    "gn:dem":125,
    "gn:feature_class":"P",
    "gn:feature_code":"PPL",
    "gn:name":"Sedel\u2019nitsy",
    "gn:population":0,
    "gn:timezone":"Europe/Moscow",
    "iso:country":"RU",
    "name:rus_x_preferred":[
        "\u0421\u0435\u0434\u0435\u043b\u044c\u043d\u0438\u0446\u044b"
    ],
    "name:und_x_variant":[
        "Sedel\u2019nitsy"
    ],
    "wof:name":"Sedel'nitsy",
    "wof:placetype":"locality"
},
  "geometry": {"coordinates":[39.31325,57.62746],"type":"Point"}
}