{
  "type": "Feature",
  "properties": {
    "gn:country":"RU",
    "gn:fcode":"PPL",
    "gn:pop":7666,
    "iso:country":"RU",
    "name:che_x_preferred":[
        "Alxan-\u00c7urtskii"
    ],
    "name:che_x_variant":[
        "\u0410\u043b\u0445\u0430\u043d-\u0427\u0443\u0440\u0442\u0441\u043a\u0438\u0439"
    ],
    "name:nor_x_preferred":[
        "Alkhan-Tsjurt"
    ],
    "name:rus_x_preferred":[
        "\u0410\u043b\u0445\u0430\u043d-\u0427\u0443\u0440\u0442"
    ],
    "name:rus_x_variant":[
        "Alhan-\u010curt"
    ],
    "qs:name":"Alkhan-Churt",
    "qs:photos_9r":0,
    "qs:photos_sr":0,
    "qs:pop_sr":"5",
    "wof:name":"Alkhan-Churt",
    "wof:placetype":"locality",
    "wof:population":7666
},
  "geometry": {"coordinates":[44.78694,43.35194],"type":"Point"}
}