{
  "type": "Feature",
  "properties": {
    "gn:admin1_code":"79",
    "gn:asciiname":"Seserlig",
    "gn:cc2":"RU",
    "gn:country_code":"RU",
    "gn:dem":1103,
    "gn:feature_class":"P",
    "gn:feature_code":"PPL",
    "gn:name":"Seserlig",
    "gn:population":0,
    "gn:timezone":"Asia/Krasnoyarsk",
    "iso:country":"RU",
    "name:eng_x_preferred":[
        "Seserlig"
    ],
    "name:nor_x_preferred":[
        "Seserlig"
    ],
    "name:rus_x_preferred":[
        "\u0421\u0435\u0441\u0435\u0440\u043b\u0438\u0433"
    ],
    "name:und_x_variant":[
        "Germanovka",
        "Germeneska"
    ],
    "wof:name":"Seserlig",
    "wof:placetype":"locality"
},
  "geometry": {"coordinates":[94.16667,51.83333],"type":"Point"}
}