{
  "type": "Feature",
  "properties": {
    "gn:admin1_code":"73",
    "gn:asciiname":"Islyaykino",
    "gn:country_code":"RU",
    "gn:dem":84,
    "gn:feature_class":"P",
    "gn:feature_code":"PPL",
    "gn:name":"Islyaykino",
    "gn:population":0,
    "gn:timezone":"Europe/Moscow",
    "iso:country":"RU",
    "name:eng_x_preferred":[
        "Islyaykino"
    ],
    "name:nor_x_preferred":[
        "Isljajkino"
    ],
    "name:rus_x_preferred":[
        "\u0418\u0441\u043b\u044f\u0439\u043a\u0438\u043d\u043e"
    ],
    "name:und_x_variant":[
        "\u0418\u0441\u043b\u044f\u0439\u043a\u0438\u043d\u043e",
        "Islyaykino"
    ],
    "wof:name":"Islyaykino",
    "wof:placetype":"locality"
},
  "geometry": {"coordinates":[50.97548,55.28932],"type":"Point"}
}