{
  "type": "Feature",
  "properties": {
    "gn:admin1_code":"80.0",
    "gn:asciiname":"Belyayevskoye",
    "gn:country_code":"RU",
    "gn:dem":174,
    "gn:feature_class":"P",
    "gn:feature_code":"PPL",
    "gn:name":"Belyayevskoye",
    "gn:population":0,
    "gn:timezone":"Europe/Samara",
    "iso:country":"RU",
    "name:rus_x_preferred":[
        "\u0411\u0435\u043b\u044f\u0435\u0432\u0441\u043a\u043e\u0435"
    ],
    "wof:name":"Belyayevskoye",
    "wof:placetype":"locality"
},
  "geometry": {"coordinates":[53.4633,57.522],"type":"Point"}
}