{
  "type": "Feature",
  "properties": {
    "gn:admin1_code":"65",
    "gn:asciiname":"Klyuchi",
    "gn:country_code":"RU",
    "gn:dem":98,
    "gn:feature_class":"P",
    "gn:feature_code":"PPL",
    "gn:name":"Klyuchi",
    "gn:population":0,
    "gn:timezone":"Europe/Samara",
    "iso:country":"RU",
    "name:eng_x_preferred":[
        "Klyuchi"
    ],
    "name:nor_x_preferred":[
        "Kljutsji"
    ],
    "name:rus_x_preferred":[
        "\u041a\u043b\u044e\u0447\u0438"
    ],
    "name:und_x_variant":[
        "\u041a\u043b\u044e\u0447\u0438",
        "Klyuchi"
    ],
    "wof:name":"Klyuchi",
    "wof:placetype":"locality"
},
  "geometry": {"coordinates":[51.43333,54.15],"type":"Point"}
}