{
  "type": "Feature",
  "properties": {
    "gn:admin1_code":"75",
    "gn:asciiname":"Starochernovo",
    "gn:cc2":"RU",
    "gn:country_code":"RU",
    "gn:dem":114,
    "gn:feature_class":"P",
    "gn:feature_code":"PPL",
    "gn:name":"Starochernovo",
    "gn:population":0,
    "gn:timezone":"Asia/Tomsk",
    "iso:country":"RU",
    "name:eng_x_preferred":[
        "Starochernovo"
    ],
    "name:nor_x_preferred":[
        "Starotsjernovo"
    ],
    "name:rus_x_preferred":[
        "\u0421\u0442\u0430\u0440\u043e\u0447\u0435\u0440\u043d\u043e\u0432\u043e"
    ],
    "name:und_x_variant":[
        "Staroye Chernovo",
        "Staro-Chernova",
        "\u0421\u0442\u0430\u0440\u043e\u0447\u0435\u0440\u043d\u043e\u0432\u043e",
        "Starochernovo"
    ],
    "wof:name":"Starochernovo",
    "wof:placetype":"locality"
},
  "geometry": {"coordinates":[83.43333,56.325],"type":"Point"}
}