{
  "type": "Feature",
  "properties": {
    "gn:admin1_code":"16.0",
    "gn:asciiname":"Bol'shiye Yal'chiki",
    "gn:country_code":"RU",
    "gn:dem":135,
    "gn:feature_class":"P",
    "gn:feature_code":"PPL",
    "gn:name":"Bol\u2019shiye Yal\u2019chiki",
    "gn:population":0,
    "gn:timezone":"Europe/Moscow",
    "iso:country":"RU",
    "name:eng_x_preferred":[
        "Bol'shiye Yal'chiki"
    ],
    "name:nor_x_preferred":[
        "Bolsjije Jaltsjiki"
    ],
    "name:rus_x_preferred":[
        "\u0411\u043e\u043b\u044c\u0448\u0438\u0435 \u042f\u043b\u044c\u0447\u0438\u043a\u0438"
    ],
    "name:und_x_variant":[
        "\u0411\u043e\u043b\u044c\u0448\u0438\u0435 \u042f\u043b\u044c\u0447\u0438\u043a\u0438",
        "Bol\u2019shiye Yal\u2019chiki"
    ],
    "wof:name":"Bol'shiye Yal'chiki",
    "wof:placetype":"locality"
},
  "geometry": {"coordinates":[48.06176,55.17269],"type":"Point"}
}