{
  "type": "Feature",
  "properties": {
    "gn:admin1_code":"57.0",
    "gn:asciiname":"Pereleski",
    "gn:country_code":"RU",
    "gn:dem":179,
    "gn:feature_class":"P",
    "gn:feature_code":"PPL",
    "gn:name":"Pereleski",
    "gn:population":0,
    "gn:timezone":"Europe/Moscow",
    "iso:country":"RU",
    "name:rus_x_preferred":[
        "\u041f\u0435\u0440\u0435\u043b\u0435\u0441\u043a\u0438"
    ],
    "wof:name":"Pereleski",
    "wof:placetype":"locality"
},
  "geometry": {"coordinates":[45.65163,53.13077],"type":"Point"}
}