{
  "type": "Feature",
  "properties": {
    "gn:admin1_code":"77",
    "gn:asciiname":"Lebedevo",
    "gn:country_code":"RU",
    "gn:dem":138,
    "gn:feature_class":"P",
    "gn:feature_code":"PPL",
    "gn:name":"Lebedevo",
    "gn:population":0,
    "gn:timezone":"Europe/Moscow",
    "iso:country":"RU",
    "name:rus_x_preferred":[
        "\u041b\u0435\u0431\u0435\u0434\u0435\u0432\u043e"
    ],
    "name:und_x_variant":[
        "Lebedeva",
        "Lebedevo",
        "\u041b\u0435\u0431\u0435\u0434\u0435\u0432\u043e"
    ],
    "wof:name":"Lebedevo",
    "wof:placetype":"locality"
},
  "geometry": {"coordinates":[35.87627,58.05416],"type":"Point"}
}