{
  "type": "Feature",
  "properties": {
    "gn:admin1_code":"90",
    "gn:asciiname":"Ovinovo",
    "gn:country_code":"RU",
    "gn:dem":127,
    "gn:feature_class":"P",
    "gn:feature_code":"PPL",
    "gn:name":"Ovinovo",
    "gn:population":0,
    "gn:timezone":"Asia/Yekaterinburg",
    "iso:country":"RU",
    "name:rus_x_preferred":[
        "\u041e\u0432\u0438\u043d\u043e\u0432\u043e"
    ],
    "name:und_x_variant":[
        "Ovinova",
        "Ovinovo"
    ],
    "wof:name":"Ovinovo",
    "wof:placetype":"locality"
},
  "geometry": {"coordinates":[56.3232,59.5298],"type":"Point"}
}