{
  "type": "Feature",
  "properties": {
    "gn:admin1_code":"43",
    "gn:asciiname":"Laukhino",
    "gn:country_code":"RU",
    "gn:dem":244,
    "gn:feature_class":"P",
    "gn:feature_code":"PPL",
    "gn:name":"Laukhino",
    "gn:population":0,
    "gn:timezone":"Europe/Moscow",
    "iso:country":"RU",
    "name:rus_x_preferred":[
        "\u041b\u0430\u0443\u0445\u0438\u043d\u043e"
    ],
    "wof:name":"Laukhino",
    "wof:placetype":"locality"
},
  "geometry": {"coordinates":[38.19829,52.84032],"type":"Point"}
}