{
  "type": "Feature",
  "properties": {
    "gn:admin1_code":"53",
    "gn:asciiname":"Sizevo",
    "gn:country_code":"RU",
    "gn:dem":113,
    "gn:feature_class":"P",
    "gn:feature_code":"PPL",
    "gn:name":"Sizevo",
    "gn:population":0,
    "gn:timezone":"Asia/Novosibirsk",
    "iso:country":"RU",
    "name:eng_x_preferred":[
        "Sizevo"
    ],
    "name:nor_x_preferred":[
        "Sizevo"
    ],
    "name:rus_x_preferred":[
        "\u0421\u0438\u0437\u0435\u0432\u043e"
    ],
    "name:und_x_variant":[
        "Sizeva",
        "\u0421\u0438\u0437\u0435\u0432\u043e",
        "Sizevo"
    ],
    "wof:name":"Sizevo",
    "wof:placetype":"locality"
},
  "geometry": {"coordinates":[78.27264,54.89665],"type":"Point"}
}