{
  "type": "Feature",
  "properties": {
    "gn:admin1_code":"51",
    "gn:asciiname":"Tikhonovo",
    "gn:country_code":"RU",
    "gn:dem":130,
    "gn:feature_class":"P",
    "gn:feature_code":"PPL",
    "gn:name":"Tikhonovo",
    "gn:population":0,
    "gn:timezone":"Europe/Moscow",
    "iso:country":"RU",
    "name:und_x_variant":[
        "Tikhanovo",
        "Tikhonovo"
    ],
    "wof:name":"Tikhonovo",
    "wof:placetype":"locality"
},
  "geometry": {"coordinates":[43.74594,57.14965],"type":"Point"}
}