{
  "type": "Feature",
  "properties": {
    "gn:admin1_code":"91",
    "gn:asciiname":"Kazyr",
    "gn:country_code":"RU",
    "gn:dem":428,
    "gn:feature_class":"P",
    "gn:feature_code":"PPL",
    "gn:name":"Kazyr",
    "gn:population":0,
    "gn:timezone":"Asia/Krasnoyarsk",
    "iso:country":"RU",
    "name:rus_x_preferred":[
        "\u041a\u0430\u0437\u044b\u0440"
    ],
    "name:und_x_variant":[
        "Verkhne-Kazyrskaya"
    ],
    "wof:name":"Kazyr",
    "wof:placetype":"locality"
},
  "geometry": {"coordinates":[94.2033,53.6843],"type":"Point"}
}