{
  "type": "Feature",
  "properties": {
    "gn:country":"RU",
    "gn:fcode":"PPL",
    "gn:pop":0,
    "iso:country":"RU",
    "name:aze_x_preferred":[
        "Petrovka"
    ],
    "name:bel_x_preferred":[
        "\u041f\u044f\u0442\u0440\u043e\u045e\u043a\u0430"
    ],
    "name:ceb_x_preferred":[
        "\u041f\u0435\u0442\u0440\u043e\u0432\u043a\u0430"
    ],
    "name:ces_x_preferred":[
        "Petrovka"
    ],
    "name:chv_x_preferred":[
        "\u041f\u0435\u0442\u0440\u043e\u0432\u043a\u0430"
    ],
    "name:deu_x_preferred":[
        "Petrowka"
    ],
    "name:eng_x_preferred":[
        "Petrovskiy"
    ],
    "name:fra_x_preferred":[
        "Petrovka"
    ],
    "name:hye_x_preferred":[
        "\u054a\u0565\u057f\u0580\u0578\u057e\u056f\u0561"
    ],
    "name:ita_x_preferred":[
        "Petrovka"
    ],
    "name:kaz_x_preferred":[
        "\u041f\u0435\u0442\u0440\u043e\u0432\u043a\u0430"
    ],
    "name:lav_x_preferred":[
        "Petrovka"
    ],
    "name:myv_x_preferred":[
        "\u041f\u0435\u0442\u0440\u043e\u0432\u043a\u0430"
    ],
    "name:nor_x_preferred":[
        "Petrovka"
    ],
    "name:rus_x_preferred":[
        "\u041f\u0435\u0442\u0440\u043e\u0432\u043a\u0430"
    ],
    "name:slk_x_preferred":[
        "Petrovka"
    ],
    "name:tat_x_preferred":[
        "\u041f\u0435\u0442\u0440\u043e\u0432\u043a\u0430"
    ],
    "name:ukr_x_preferred":[
        "\u041f\u0435\u0442\u0440\u043e\u0432\u043a\u0430"
    ],
    "name:unk_x_variant":[
        "Petrovskiy"
    ],
    "qs:name":"Petrovka",
    "qs:name_adm0":"Russia",
    "qs:name_adm1":"Omsk Oblast",
    "qs:photos_9k":1,
    "qs:photos_9r":1,
    "qs:photos_all":10,
    "qs:photos_sr":0,
    "qs:placetype":"Town",
    "qs:pop_sr":"0",
    "wd:wordcount":60,
    "wof:name":"Petrovka",
    "wof:placetype":"locality",
    "wof:population":0
},
  "geometry": {"coordinates":[73.54451,55.25828],"type":"Point"}
}