{
  "type": "Feature",
  "properties": {
    "gn:admin1_code":"53",
    "gn:asciiname":"Orlovskiy",
    "gn:country_code":"RU",
    "gn:dem":163,
    "gn:feature_class":"P",
    "gn:feature_code":"PPL",
    "gn:name":"Orlovskiy",
    "gn:population":0,
    "gn:timezone":"Asia/Novosibirsk",
    "iso:country":"RU",
    "name:eng_x_preferred":[
        "Orlovskiy"
    ],
    "name:nor_x_preferred":[
        "Orlovskij"
    ],
    "name:rus_x_preferred":[
        "\u041e\u0440\u043b\u043e\u0432\u0441\u043a\u0438\u0439"
    ],
    "name:und_x_variant":[
        "Orlovka"
    ],
    "wof:name":"Orlovskiy",
    "wof:placetype":"locality"
},
  "geometry": {"coordinates":[81.4346,54.9174],"type":"Point"}
}