{
  "type": "Feature",
  "properties": {
    "gn:admin1_code":"8",
    "gn:asciiname":"Kirgizovo",
    "gn:country_code":"RU",
    "gn:dem":70,
    "gn:feature_class":"P",
    "gn:feature_code":"PPL",
    "gn:name":"Kirgizovo",
    "gn:population":0,
    "gn:timezone":"Asia/Yekaterinburg",
    "iso:country":"RU",
    "name:rus_x_preferred":[
        "\u041a\u0438\u0440\u0433\u0438\u0437\u043e\u0432\u043e"
    ],
    "wof:name":"Kirgizovo",
    "wof:placetype":"locality"
},
  "geometry": {"coordinates":[54.36032,55.78585],"type":"Point"}
}