{
  "type": "Feature",
  "properties": {
    "gn:admin1_code":"76",
    "gn:asciiname":"Shakhterskiy",
    "gn:country_code":"RU",
    "gn:dem":232,
    "gn:feature_class":"P",
    "gn:feature_code":"PPL",
    "gn:name":"Shakht\u00ebrskiy",
    "gn:population":0,
    "gn:timezone":"Europe/Moscow",
    "iso:country":"RU",
    "name:eng_x_preferred":[
        "Shakht\u00ebrskiy"
    ],
    "name:nor_x_preferred":[
        "Sjakhterskij"
    ],
    "name:rus_x_preferred":[
        "\u0428\u0430\u0445\u0442\u0435\u0440\u0441\u043a\u0438\u0439"
    ],
    "name:rus_x_variant":[
        "\u0428\u0430\u0445\u0442\u0451\u0440\u0441\u043a\u0438\u0439"
    ],
    "name:und_x_variant":[
        "Yegor\u2019yevskoye",
        "Shakht\u00ebrskiy",
        "\u0428\u0430\u0445\u0442\u0451\u0440\u0441\u043a\u0438\u0439"
    ],
    "wof:name":"Shakhterskiy",
    "wof:placetype":"locality"
},
  "geometry": {"coordinates":[38.3044,53.92178000000001],"type":"Point"}
}