{
  "type": "Feature",
  "properties": {
    "gn:admin1_code":"30",
    "gn:asciiname":"Kadi",
    "gn:country_code":"RU",
    "gn:dem":23,
    "gn:feature_class":"P",
    "gn:feature_code":"PPL",
    "gn:name":"Kadi",
    "gn:population":0,
    "gn:timezone":"Asia/Vladivostok",
    "iso:country":"RU",
    "name:ceb_x_preferred":[
        "Kadi"
    ],
    "name:ces_x_preferred":[
        "Kadi"
    ],
    "name:deu_x_preferred":[
        "Kadi"
    ],
    "name:fas_x_preferred":[
        "\u0642\u0627\u0636\u06cc"
    ],
    "name:fra_x_preferred":[
        "Kadi"
    ],
    "name:ita_x_preferred":[
        "Kadi"
    ],
    "name:nld_x_preferred":[
        "Kadi"
    ],
    "name:rus_x_preferred":[
        "\u041a\u0430\u0434\u0438"
    ],
    "name:swe_x_preferred":[
        "Kadi"
    ],
    "wof:name":"Kadi",
    "wof:placetype":"locality"
},
  "geometry": {"coordinates":[140.39598000000001,51.8814],"type":"Point"}
}