{
  "type": "Feature",
  "properties": {
    "gn:admin1_code":"30",
    "gn:asciiname":"Kadi",
    "gn:country_code":"RU",
    "gn:dem":23,
    "gn:feature_class":"P",
    "gn:feature_code":"PPL",
    "gn:name":"Kadi",
    "gn:population":0,
    "gn:timezone":"Asia/Vladivostok",
    "iso:country":"RU",
    "name:rus_x_preferred":[
        "\u041a\u0430\u0434\u0438"
    ],
    "name:und_x_variant":[
        "\u041a\u0430\u0434\u0438"
    ],
    "wof:name":"Kadi",
    "wof:placetype":"locality"
},
  "geometry": {"coordinates":[140.39598000000001,51.8814],"type":"Point"}
}