{
  "type": "Feature",
  "properties": {
    "gn:admin1_code":"30",
    "gn:asciiname":"Malyushino",
    "gn:country_code":"RU",
    "gn:dem":407,
    "gn:feature_class":"P",
    "gn:feature_code":"PPL",
    "gn:name":"Malyushino",
    "gn:population":0,
    "gn:timezone":"Asia/Vladivostok",
    "iso:country":"RU",
    "name:rus_x_preferred":[
        "\u041c\u0430\u043b\u044e\u0448\u0438\u043d\u043e"
    ],
    "wof:name":"Malyushino",
    "wof:placetype":"locality"
},
  "geometry": {"coordinates":[137.91666999999998,54.85],"type":"Point"}
}