{
  "type": "Feature",
  "properties": {
    "gn:admin1_code":"33.0",
    "gn:asciiname":"Metelikha",
    "gn:country_code":"RU",
    "gn:dem":145,
    "gn:feature_class":"P",
    "gn:feature_code":"PPL",
    "gn:name":"Metelikha",
    "gn:population":0,
    "gn:timezone":"Europe/Kirov",
    "iso:country":"RU",
    "name:rus_x_preferred":[
        "\u041c\u0435\u0442\u0435\u043b\u0438\u0445\u0430"
    ],
    "name:und_x_variant":[
        "Melelikha",
        "Metelikha"
    ],
    "wof:name":"Metelikha",
    "wof:placetype":"locality"
},
  "geometry": {"coordinates":[48.87281,58.62131],"type":"Point"}
}