{
  "type": "Feature",
  "properties": {
    "gn:country":"RU",
    "gn:fcode":"PPL",
    "gn:pop":11081,
    "iso:country":"RU",
    "name:ceb_x_preferred":[
        "\u0422\u0440\u043e\u0438\u0446\u043a\u0438\u0439"
    ],
    "name:deu_x_preferred":[
        "Troizki"
    ],
    "name:eng_x_preferred":[
        "Troitskiy"
    ],
    "name:est_x_preferred":[
        "Troitski"
    ],
    "name:hye_x_preferred":[
        "\u054f\u0580\u0578\u056b\u0581\u056f\u056b"
    ],
    "name:nld_x_preferred":[
        "Troitski"
    ],
    "name:nor_x_preferred":[
        "Troitskij"
    ],
    "name:rus_x_preferred":[
        "\u0422\u0440\u043e\u0438\u0446\u043a\u0438\u0439"
    ],
    "name:spa_x_preferred":[
        "Troitski"
    ],
    "name:ukr_x_preferred":[
        "\u0422\u0440\u043e\u0457\u0446\u044c\u043a\u0438\u0439"
    ],
    "name:unk_x_variant":[
        "\u0422\u0440\u043e\u0438\u0446\u043a\u0438\u0439"
    ],
    "qs:name":"Troitskiy",
    "qs:photos_9r":0,
    "qs:photos_sr":0,
    "qs:pop_sr":"6",
    "wd:wordcount":95,
    "wof:name":"Troitskiy",
    "wof:placetype":"locality",
    "wof:population":11081
},
  "geometry": {"coordinates":[63.74811,57.06028],"type":"Point"}
}