{
  "type": "Feature",
  "properties": {
    "gn:admin1_code":"20",
    "gn:asciiname":"Pokrovka",
    "gn:country_code":"RU",
    "gn:dem":662,
    "gn:feature_class":"P",
    "gn:feature_code":"PPL",
    "gn:name":"Pokrovka",
    "gn:population":0,
    "gn:timezone":"Asia/Irkutsk",
    "iso:country":"RU",
    "wof:name":"Pokrovka",
    "wof:placetype":"locality"
},
  "geometry": {"coordinates":[105.53333000000001,53.08333],"type":"Point"}
}