{
  "type": "Feature",
  "properties": {
    "gn:admin1_code":"77",
    "gn:asciiname":"Krapivkino",
    "gn:country_code":"RU",
    "gn:dem":218,
    "gn:feature_class":"P",
    "gn:feature_code":"PPL",
    "gn:name":"Krapivkino",
    "gn:population":0,
    "gn:timezone":"Europe/Moscow",
    "iso:country":"RU",
    "name:rus_x_preferred":[
        "\u041a\u0440\u0430\u043f\u0438\u0432\u043a\u0438\u043d\u043e"
    ],
    "name:und_x_variant":[
        "\u041a\u0440\u0430\u043f\u0438\u0432\u043a\u0438\u043d\u043e"
    ],
    "wof:name":"Krapivkino",
    "wof:placetype":"locality"
},
  "geometry": {"coordinates":[37.3184,58.338],"type":"Point"}
}