{
  "type": "Feature",
  "properties": {
    "gn:admin1_code":"47",
    "gn:asciiname":"Parshino",
    "gn:country_code":"RU",
    "gn:dem":241,
    "gn:feature_class":"P",
    "gn:feature_code":"PPL",
    "gn:name":"Parshino",
    "gn:population":0,
    "gn:timezone":"Europe/Moscow",
    "iso:country":"RU",
    "name:rus_x_preferred":[
        "\u041f\u0430\u0440\u0448\u0438\u043d\u043e"
    ],
    "wof:name":"Parshino",
    "wof:placetype":"locality"
},
  "geometry": {"coordinates":[35.44663,55.99217],"type":"Point"}
}