{
  "type": "Feature",
  "properties": {
    "gn:admin1_code":"52",
    "gn:asciiname":"Meglets",
    "gn:country_code":"RU",
    "gn:dem":57,
    "gn:feature_class":"P",
    "gn:feature_code":"PPL",
    "gn:name":"Meglets",
    "gn:population":0,
    "gn:timezone":"Europe/Moscow",
    "iso:country":"RU",
    "name:rus_x_preferred":[
        "\u041c\u0435\u0433\u043b\u0435\u0446"
    ],
    "name:und_x_variant":[
        "\u041c\u0435\u0433\u043b\u0435\u0446"
    ],
    "wof:name":"Meglets",
    "wof:placetype":"locality"
},
  "geometry": {"coordinates":[31.23333,57.58333],"type":"Point"}
}