{
  "type": "Feature",
  "properties": {
    "gn:admin1_code":"69",
    "gn:asciiname":"Ivkovka",
    "gn:country_code":"RU",
    "gn:dem":235,
    "gn:feature_class":"P",
    "gn:feature_code":"PPL",
    "gn:name":"Ivkovka",
    "gn:population":0,
    "gn:timezone":"Europe/Moscow",
    "iso:country":"RU",
    "name:rus_x_preferred":[
        "\u0418\u0432\u043a\u043e\u0432\u043a\u0430"
    ],
    "wof:name":"Ivkovka",
    "wof:placetype":"locality"
},
  "geometry": {"coordinates":[32.94833,54.30611],"type":"Point"}
}