{
  "type": "Feature",
  "properties": {
    "gn:admin1_code":"43.0",
    "gn:asciiname":"Patriarshaya",
    "gn:country_code":"RU",
    "gn:dem":194,
    "gn:feature_class":"P",
    "gn:feature_code":"PPL",
    "gn:name":"Patriarshaya",
    "gn:population":0,
    "gn:timezone":"Europe/Moscow",
    "iso:country":"RU",
    "name:rus_x_preferred":[
        "\u041f\u0430\u0442\u0440\u0438\u0430\u0440\u0448\u0430\u044f"
    ],
    "wof:name":"Patriarshaya",
    "wof:placetype":"locality"
},
  "geometry": {"coordinates":[39.0647,52.6533],"type":"Point"}
}