{
  "type": "Feature",
  "properties": {
    "gn:admin1_code":"15",
    "gn:asciiname":"Staryy Mayn",
    "gn:cc2":"RU",
    "gn:country_code":"RU",
    "gn:dem":20,
    "gn:feature_class":"P",
    "gn:feature_code":"PPL",
    "gn:name":"Staryy Mayn",
    "gn:population":0,
    "gn:timezone":"Asia/Anadyr",
    "iso:country":"RU",
    "name:rus_x_preferred":[
        "\u0421\u0442\u0430\u0440\u044b\u0439 \u041c\u0430\u0439\u043d"
    ],
    "name:und_x_variant":[
        "Stantsiya Mayn",
        "Staryy Mayn",
        "\u0421\u0442\u0430\u0440\u044b\u0439 \u041c\u0430\u0439\u043d"
    ],
    "wof:name":"Staryy Mayn",
    "wof:placetype":"locality"
},
  "geometry": {"coordinates":[171.19999999999999,64.51666999999999],"type":"Point"}
}