{
  "type": "Feature",
  "properties": {
    "gn:admin1_code":"90",
    "gn:asciiname":"Yergach",
    "gn:country_code":"RU",
    "gn:dem":156,
    "gn:feature_class":"P",
    "gn:feature_code":"PPL",
    "gn:name":"Yergach",
    "gn:population":0,
    "gn:timezone":"Asia/Yekaterinburg",
    "iso:country":"RU",
    "name:rus_x_preferred":[
        "\u0415\u0440\u0433\u0430\u0447"
    ],
    "wof:name":"Yergach",
    "wof:placetype":"locality"
},
  "geometry": {"coordinates":[56.6155,57.5054],"type":"Point"}
}