{
  "type": "Feature",
  "properties": {
    "gn:admin1_code":"4",
    "gn:asciiname":"Cherepenino",
    "gn:cc2":"RU",
    "gn:country_code":"RU",
    "gn:dem":116,
    "gn:feature_class":"P",
    "gn:feature_code":"PPL",
    "gn:name":"Cherepenino",
    "gn:population":0,
    "gn:timezone":"Asia/Barnaul",
    "iso:country":"RU",
    "name:rus_x_preferred":[
        "\u0427\u0435\u0440\u0435\u043f\u0435\u043d\u0438\u043d\u043e"
    ],
    "name:und_x_variant":[
        "Cherepenina",
        "Cherepenino",
        "\u0427\u0435\u0440\u0435\u043f\u0435\u043d\u0438\u043d\u043e"
    ],
    "wof:name":"Cherepenino",
    "wof:placetype":"locality"
},
  "geometry": {"coordinates":[81.61667,53.78333000000001],"type":"Point"}
}