{
  "type": "Feature",
  "properties": {
    "gn:admin1_code":"4",
    "gn:asciiname":"Tyakhta",
    "gn:country_code":"RU",
    "gn:dem":188,
    "gn:feature_class":"P",
    "gn:feature_code":"PPL",
    "gn:name":"Tyakhta",
    "gn:population":0,
    "gn:timezone":"Asia/Barnaul",
    "iso:country":"RU",
    "name:eng_x_preferred":[
        "Tyakhta"
    ],
    "name:nor_x_preferred":[
        "Tjakhta"
    ],
    "name:rus_x_preferred":[
        "\u0422\u044f\u0445\u0442\u0430"
    ],
    "wof:name":"Tyakhta",
    "wof:placetype":"locality"
},
  "geometry": {"coordinates":[85.4727,53.5774],"type":"Point"}
}