{
  "type": "Feature",
  "properties": {
    "gn:admin1_code":"37",
    "gn:asciiname":"Yagodino",
    "gn:country_code":"RU",
    "gn:dem":145,
    "gn:feature_class":"P",
    "gn:feature_code":"PPL",
    "gn:name":"Yagodino",
    "gn:population":0,
    "gn:timezone":"Europe/Moscow",
    "iso:country":"RU",
    "name:und_x_variant":[
        "Yagodina",
        "Yagodino"
    ],
    "wof:name":"Yagodino",
    "wof:placetype":"locality"
},
  "geometry": {"coordinates":[42.16839,59.109],"type":"Point"}
}