{
  "type": "Feature",
  "properties": {
    "gn:admin1_code":"69.0",
    "gn:asciiname":"Budnevka",
    "gn:cc2":"RU",
    "gn:country_code":"RU",
    "gn:dem":200,
    "gn:feature_class":"P",
    "gn:feature_code":"PPL",
    "gn:name":"Budn\u00ebvka",
    "gn:population":0,
    "gn:timezone":"Europe/Moscow",
    "iso:country":"RU",
    "name:rus_x_preferred":[
        "\u0411\u0443\u0434\u043d\u0451\u0432\u043a\u0430"
    ],
    "name:und_x_variant":[
        "Budhevka",
        "Budn\u00ebvka"
    ],
    "wof:name":"Budnevka",
    "wof:placetype":"locality"
},
  "geometry": {"coordinates":[34.41861,54.76778],"type":"Point"}
}