{
  "type": "Feature",
  "properties": {
    "gn:admin1_code":"37",
    "gn:asciiname":"Gol'tsovo",
    "gn:country_code":"RU",
    "gn:dem":170,
    "gn:feature_class":"P",
    "gn:feature_code":"PPL",
    "gn:name":"Gol\u2019tsovo",
    "gn:population":0,
    "gn:timezone":"Europe/Moscow",
    "iso:country":"RU",
    "name:nor_x_preferred":[
        "Goltsovo"
    ],
    "name:rus_x_preferred":[
        "\u0413\u043e\u043b\u044c\u0446\u043e\u0432\u043e"
    ],
    "name:und_x_variant":[
        "Gol\u2019tsova",
        "Gol\u2019tsovo"
    ],
    "wof:name":"Gol'tsovo",
    "wof:placetype":"locality"
},
  "geometry": {"coordinates":[41.662,58.26923000000001],"type":"Point"}
}