{
  "type": "Feature",
  "properties": {
    "gn:admin1_code":"71",
    "gn:asciiname":"Borisovskiy",
    "gn:country_code":"RU",
    "gn:dem":212,
    "gn:feature_class":"P",
    "gn:feature_code":"PPL",
    "gn:name":"Borisovskiy",
    "gn:population":0,
    "gn:timezone":"Asia/Yekaterinburg",
    "iso:country":"RU",
    "name:rus_x_preferred":[
        "\u0411\u043e\u0440\u0438\u0441\u043e\u0432\u0441\u043a\u0438\u0439"
    ],
    "name:und_x_variant":[
        "\u0411\u043e\u0440\u0438\u0441\u043e\u0432\u0441\u043a\u0438\u0439"
    ],
    "wof:name":"Borisovskiy",
    "wof:placetype":"locality"
},
  "geometry": {"coordinates":[59.4909,58.8628],"type":"Point"}
}