{
  "type": "Feature",
  "properties": {
    "gn:admin1_code":"61",
    "gn:asciiname":"Latyshev",
    "gn:country_code":"RU",
    "gn:dem":130,
    "gn:feature_class":"P",
    "gn:feature_code":"PPL",
    "gn:name":"Latysh\u00ebv",
    "gn:population":0,
    "gn:timezone":"Europe/Moscow",
    "iso:country":"RU",
    "name:rus_x_preferred":[
        "\u041b\u0430\u0442\u044b\u0448\u0451\u0432"
    ],
    "name:und_x_variant":[
        "Latysh\u00ebv"
    ],
    "wof:name":"Latyshev",
    "wof:placetype":"locality"
},
  "geometry": {"coordinates":[41.78583,47.99056],"type":"Point"}
}