{
  "type": "Feature",
  "properties": {
    "gn:admin1_code":"60",
    "gn:asciiname":"Pushkovo",
    "gn:country_code":"RU",
    "gn:dem":67,
    "gn:feature_class":"P",
    "gn:feature_code":"PPL",
    "gn:name":"Pushkovo",
    "gn:population":0,
    "gn:timezone":"Europe/Moscow",
    "iso:country":"RU",
    "name:rus_x_preferred":[
        "\u041f\u0443\u0448\u043a\u043e\u0432\u043e"
    ],
    "wof:name":"Pushkovo",
    "wof:placetype":"locality"
},
  "geometry": {"coordinates":[28.53665,57.30062],"type":"Point"}
}