{
  "type": "Feature",
  "properties": {
    "gn:admin1_code":"85",
    "gn:asciiname":"Tsarikha",
    "gn:country_code":"RU",
    "gn:dem":149,
    "gn:feature_class":"P",
    "gn:feature_code":"PPL",
    "gn:name":"Tsarikha",
    "gn:population":0,
    "gn:timezone":"Europe/Moscow",
    "iso:country":"RU",
    "name:eng_x_preferred":[
        "Tsarikha"
    ],
    "name:nor_x_preferred":[
        "Tsarikha"
    ],
    "name:rus_x_preferred":[
        "\u0426\u0430\u0440\u0438\u0445\u0430"
    ],
    "wof:name":"Tsarikha",
    "wof:placetype":"locality"
},
  "geometry": {"coordinates":[39.676,60.1772],"type":"Point"}
}