{
  "type": "Feature",
  "properties": {
    "gn:admin1_code":"65.0",
    "gn:asciiname":"Kondurchinskiy",
    "gn:country_code":"RU",
    "gn:dem":34,
    "gn:feature_class":"P",
    "gn:feature_code":"PPL",
    "gn:name":"Kondurchinskiy",
    "gn:population":0,
    "gn:timezone":"Europe/Samara",
    "iso:country":"RU",
    "name:rus_x_preferred":[
        "\u041a\u043e\u043d\u0434\u0443\u0440\u0447\u0438\u043d\u0441\u043a\u0438\u0439"
    ],
    "wof:name":"Kondurchinskiy",
    "wof:placetype":"locality"
},
  "geometry": {"coordinates":[50.35513,53.52432],"type":"Point"}
}