{
  "type": "Feature",
  "properties": {
    "gn:admin1_code":"43.0",
    "gn:asciiname":"Bykovka",
    "gn:country_code":"RU",
    "gn:dem":171,
    "gn:feature_class":"P",
    "gn:feature_code":"PPL",
    "gn:name":"Bykovka",
    "gn:population":0,
    "gn:timezone":"Europe/Moscow",
    "iso:country":"RU",
    "name:che_x_preferred":[
        "\u0411\u044b\u043a\u043e\u0432\u043a\u0430"
    ],
    "name:rus_x_preferred":[
        "\u0411\u044b\u043a\u043e\u0432\u043a\u0430"
    ],
    "name:und_x_variant":[
        "\u0411\u044b\u043a\u043e\u0432\u043a\u0430"
    ],
    "wof:name":"Bykovka",
    "wof:placetype":"locality"
},
  "geometry": {"coordinates":[38.5055,52.53056],"type":"Point"}
}