{
  "type": "Feature",
  "properties": {
    "gn:admin1_code":"33.0",
    "gn:asciiname":"Arkul'",
    "gn:country_code":"RU",
    "gn:dem":109,
    "gn:feature_class":"P",
    "gn:feature_code":"PPL",
    "gn:name":"Arkul\u2019",
    "gn:population":0,
    "gn:timezone":"Europe/Kirov",
    "iso:country":"RU",
    "name:rus_x_preferred":[
        "\u0410\u0440\u043a\u0443\u043b\u044c"
    ],
    "name:und_x_variant":[
        "Arkul\u2019"
    ],
    "wof:name":"Arkul'",
    "wof:placetype":"locality"
},
  "geometry": {"coordinates":[50.7631,56.9355],"type":"Point"}
}