{
  "type": "Feature",
  "properties": {
    "gn:admin1_code":"85",
    "gn:asciiname":"Olekhovskaya",
    "gn:country_code":"RU",
    "gn:dem":168,
    "gn:feature_class":"P",
    "gn:feature_code":"PPL",
    "gn:name":"Ol\u00ebkhovskaya",
    "gn:population":0,
    "gn:timezone":"Europe/Moscow",
    "iso:country":"RU",
    "name:rus_x_preferred":[
        "\u041e\u043b\u0451\u0445\u043e\u0432\u0441\u043a\u0430\u044f"
    ],
    "name:und_x_variant":[
        "Ol\u00ebkhovskaya",
        "\u041e\u043b\u0451\u0445\u043e\u0432\u0441\u043a\u0430\u044f"
    ],
    "wof:name":"Olekhovskaya",
    "wof:placetype":"locality"
},
  "geometry": {"coordinates":[41.0009,60.02955],"type":"Point"}
}