{
  "type": "Feature",
  "properties": {
    "gn:admin1_code":"65",
    "gn:asciiname":"Malorossiyskiy",
    "gn:country_code":"RU",
    "gn:dem":86,
    "gn:feature_class":"P",
    "gn:feature_code":"PPL",
    "gn:name":"Malorossiyskiy",
    "gn:population":0,
    "gn:timezone":"Europe/Samara",
    "iso:country":"RU",
    "name:eng_x_preferred":[
        "Malorossiyskiy"
    ],
    "name:nor_x_preferred":[
        "Malorossijskij"
    ],
    "name:rus_x_preferred":[
        "\u041c\u0430\u043b\u043e\u0440\u043e\u0441\u0441\u0438\u0439\u0441\u043a\u0438\u0439"
    ],
    "wof:name":"Malorossiyskiy",
    "wof:placetype":"locality"
},
  "geometry": {"coordinates":[50.9868,52.35202],"type":"Point"}
}