{
  "type": "Feature",
  "properties": {
    "gn:admin1_code":"45.0",
    "gn:asciiname":"Chavaynur",
    "gn:country_code":"RU",
    "gn:dem":208,
    "gn:feature_class":"P",
    "gn:feature_code":"PPL",
    "gn:name":"Chavaynur",
    "gn:population":0,
    "gn:timezone":"Europe/Moscow",
    "iso:country":"RU",
    "name:rus_x_preferred":[
        "\u0427\u0430\u0432\u0430\u0439\u043d\u0443\u0440"
    ],
    "name:und_x_variant":[
        "\u0427\u0430\u0432\u0430\u0439\u043d\u0443\u0440"
    ],
    "wof:name":"Chavaynur",
    "wof:placetype":"locality"
},
  "geometry": {"coordinates":[48.8625,56.33111],"type":"Point"}
}