{
  "type": "Feature",
  "properties": {
    "gn:admin1_code":"62",
    "gn:asciiname":"Maloye Samarino",
    "gn:country_code":"RU",
    "gn:dem":106,
    "gn:feature_class":"P",
    "gn:feature_code":"PPL",
    "gn:name":"Maloye Samarino",
    "gn:population":0,
    "gn:timezone":"Europe/Moscow",
    "iso:country":"RU",
    "name:rus_x_preferred":[
        "\u041c\u0430\u043b\u043e\u0435 \u0421\u0430\u043c\u0430\u0440\u0438\u043d\u043e"
    ],
    "name:und_x_variant":[
        "Samarino",
        "Maloye Samarino"
    ],
    "wof:name":"Maloye Samarino",
    "wof:placetype":"locality"
},
  "geometry": {"coordinates":[40.1995,53.8409],"type":"Point"}
}