{
  "type": "Feature",
  "properties": {
    "gn:admin1_code":"10",
    "gn:asciiname":"Kuznetsy",
    "gn:country_code":"RU",
    "gn:dem":169,
    "gn:feature_class":"P",
    "gn:feature_code":"PPL",
    "gn:name":"Kuznetsy",
    "gn:population":0,
    "gn:timezone":"Europe/Moscow",
    "iso:country":"RU",
    "name:rus_x_preferred":[
        "\u041a\u0443\u0437\u043d\u0435\u0446\u044b"
    ],
    "wof:name":"Kuznetsy",
    "wof:placetype":"locality"
},
  "geometry": {"coordinates":[33.32945,52.9987],"type":"Point"}
}