{
  "type": "Feature",
  "properties": {
    "gn:admin1_code":"38.0",
    "gn:asciiname":"Ashe",
    "gn:country_code":"RU",
    "gn:dem":126,
    "gn:feature_class":"P",
    "gn:feature_code":"PPL",
    "gn:name":"Ashe",
    "gn:population":1000,
    "gn:timezone":"Europe/Moscow",
    "iso:country":"RU",
    "name:nor_x_preferred":[
        "Asje"
    ],
    "name:rus_x_preferred":[
        "\u0410\u0448\u0435"
    ],
    "wof:name":"Ashe",
    "wof:placetype":"locality",
    "wof:population":1000
},
  "geometry": {"coordinates":[39.27911,43.95668],"type":"Point"}
}