{
  "type": "Feature",
  "properties": {
    "gn:admin1_code":"33",
    "gn:asciiname":"Vanichi",
    "gn:country_code":"RU",
    "gn:dem":204,
    "gn:feature_class":"P",
    "gn:feature_code":"PPL",
    "gn:name":"Vanichi",
    "gn:population":0,
    "gn:timezone":"Europe/Kirov",
    "iso:country":"RU",
    "name:rus_x_preferred":[
        "\u0412\u0430\u043d\u0438\u0447\u0438"
    ],
    "wof:name":"Vanichi",
    "wof:placetype":"locality"
},
  "geometry": {"coordinates":[49.1999,57.4538],"type":"Point"}
}