{
  "type": "Feature",
  "properties": {
    "gn:admin1_code":"60",
    "gn:asciiname":"Zaguz'ye",
    "gn:country_code":"RU",
    "gn:dem":89,
    "gn:feature_class":"P",
    "gn:feature_code":"PPL",
    "gn:name":"Zaguz\u2019ye",
    "gn:population":0,
    "gn:timezone":"Europe/Moscow",
    "iso:country":"RU",
    "name:rus_x_preferred":[
        "\u0417\u0430\u0433\u0443\u0437\u044c\u0435"
    ],
    "name:und_x_variant":[
        "Zaguz\u2019ye",
        "\u0417\u0430\u0433\u0443\u0437\u044c\u0435"
    ],
    "wof:name":"Zaguz'ye",
    "wof:placetype":"locality"
},
  "geometry": {"coordinates":[30.241,57.7015],"type":"Point"}
}