{
  "type": "Feature",
  "properties": {
    "gn:admin1_code":"67",
    "gn:asciiname":"Taly",
    "gn:country_code":"RU",
    "gn:dem":187,
    "gn:feature_class":"P",
    "gn:feature_code":"PPL",
    "gn:name":"Taly",
    "gn:population":0,
    "gn:timezone":"Europe/Saratov",
    "iso:country":"RU",
    "name:che_x_preferred":[
        "\u0422\u0430\u043b\u0438"
    ],
    "name:rus_x_preferred":[
        "\u0422\u0430\u043b\u044b\u0439"
    ],
    "wof:name":"Taly",
    "wof:placetype":"locality"
},
  "geometry": {"coordinates":[43.08401,52.21876],"type":"Point"}
}