{
  "type": "Feature",
  "properties": {
    "gn:admin1_code":"45",
    "gn:asciiname":"Khlebnikovo",
    "gn:country_code":"RU",
    "gn:dem":146,
    "gn:feature_class":"P",
    "gn:feature_code":"PPL",
    "gn:name":"Khlebnikovo",
    "gn:population":0,
    "gn:timezone":"Europe/Moscow",
    "iso:country":"RU",
    "name:eng_x_preferred":[
        "Khlebnikovo"
    ],
    "name:nor_x_preferred":[
        "Khlebnikovo"
    ],
    "name:rus_x_preferred":[
        "\u0425\u043b\u0435\u0431\u043d\u0438\u043a\u043e\u0432\u043e"
    ],
    "name:und_x_variant":[
        "\u0425\u043b\u0435\u0431\u043d\u0438\u043a\u043e\u0432\u043e",
        "Khlebnikovo"
    ],
    "wof:name":"Khlebnikovo",
    "wof:placetype":"locality"
},
  "geometry": {"coordinates":[49.94129,56.64664000000001],"type":"Point"}
}