{
  "type": "Feature",
  "properties": {
    "gn:admin1_code":"51.0",
    "gn:asciiname":"Novaya Sloboda",
    "gn:country_code":"RU",
    "gn:dem":164,
    "gn:feature_class":"P",
    "gn:feature_code":"PPL",
    "gn:name":"Novaya Sloboda",
    "gn:population":0,
    "gn:timezone":"Europe/Moscow",
    "iso:country":"RU",
    "name:rus_x_preferred":[
        "\u041d\u043e\u0432\u0430\u044f \u0421\u043b\u043e\u0431\u043e\u0434\u0430"
    ],
    "name:und_x_variant":[
        "\u041d\u043e\u0432\u0430\u044f \u0421\u043b\u043e\u0431\u043e\u0434\u0430"
    ],
    "wof:name":"Novaya Sloboda",
    "wof:placetype":"locality"
},
  "geometry": {"coordinates":[43.65781,55.48038],"type":"Point"}
}