{
  "type": "Feature",
  "properties": {
    "gn:admin1_code":"42.0",
    "gn:asciiname":"Bol'shevo",
    "gn:country_code":"RU",
    "gn:dem":112,
    "gn:feature_class":"P",
    "gn:feature_code":"PPL",
    "gn:name":"Bol\u2019sh\u00ebvo",
    "gn:population":0,
    "gn:timezone":"Europe/Moscow",
    "iso:country":"RU",
    "name:fin_x_preferred":[
        "Polssova"
    ],
    "name:rus_x_preferred":[
        "\u0411\u043e\u043b\u044c\u0448\u0451\u0432\u043e"
    ],
    "name:und_x_variant":[
        "Bol\u2019sh\u00ebvo"
    ],
    "wof:name":"Bol'shevo",
    "wof:placetype":"locality"
},
  "geometry": {"coordinates":[30.04,59.32722],"type":"Point"}
}