{
  "type": "Feature",
  "properties": {
    "gn:admin1_code":"88.0",
    "gn:asciiname":"Barkino",
    "gn:country_code":"RU",
    "gn:dem":132,
    "gn:feature_class":"P",
    "gn:feature_code":"PPL",
    "gn:name":"Barkino",
    "gn:population":0,
    "gn:timezone":"Europe/Moscow",
    "iso:country":"RU",
    "name:eng_x_preferred":[
        "Barkino"
    ],
    "name:nor_x_preferred":[
        "Barkino"
    ],
    "name:rus_x_preferred":[
        "\u0411\u0430\u0440\u043a\u0438\u043d\u043e"
    ],
    "name:und_x_variant":[
        "\u0411\u0430\u0440\u043a\u0438\u043d\u043e",
        "Barkino"
    ],
    "wof:name":"Barkino",
    "wof:placetype":"locality"
},
  "geometry": {"coordinates":[38.77686,58.58726],"type":"Point"}
}