{
  "type": "Feature",
  "properties": {
    "gn:admin1_code":"84",
    "gn:asciiname":"Krasnyy Buksir",
    "gn:country_code":"RU",
    "gn:dem":-4,
    "gn:feature_class":"P",
    "gn:feature_code":"PPL",
    "gn:name":"Krasnyy Buksir",
    "gn:population":0,
    "gn:timezone":"Europe/Volgograd",
    "iso:country":"RU",
    "name:rus_x_preferred":[
        "\u041a\u0440\u0430\u0441\u043d\u044b\u0439 \u0411\u0443\u043a\u0441\u0438\u0440"
    ],
    "name:und_x_variant":[
        "Krasny Buksir",
        "Krasnyy Buksir"
    ],
    "wof:name":"Krasnyy Buksir",
    "wof:placetype":"locality"
},
  "geometry": {"coordinates":[44.70942,48.72361],"type":"Point"}
}