{
  "type": "Feature",
  "properties": {
    "gn:admin1_code":"47",
    "gn:asciiname":"Malyn'",
    "gn:country_code":"RU",
    "gn:dem":188,
    "gn:feature_class":"P",
    "gn:feature_code":"PPL",
    "gn:name":"Malyn\u2019",
    "gn:population":0,
    "gn:timezone":"Europe/Moscow",
    "iso:country":"RU",
    "name:eng_x_preferred":[
        "Malyn'"
    ],
    "name:nor_x_preferred":[
        "Malyn"
    ],
    "name:rus_x_preferred":[
        "\u041c\u0430\u043b\u044b\u043d\u044c"
    ],
    "name:und_x_variant":[
        "Malyn\u2019"
    ],
    "wof:name":"Malyn'",
    "wof:placetype":"locality"
},
  "geometry": {"coordinates":[38.66199,54.60987],"type":"Point"}
}