{
  "type": "Feature",
  "properties": {
    "gn:admin1_code":"8",
    "gn:asciiname":"Petukhovka",
    "gn:country_code":"RU",
    "gn:dem":300,
    "gn:feature_class":"P",
    "gn:feature_code":"PPL",
    "gn:name":"Petukhovka",
    "gn:population":0,
    "gn:timezone":"Asia/Yekaterinburg",
    "iso:country":"RU",
    "name:rus_x_preferred":[
        "\u041f\u0435\u0442\u0443\u0445\u043e\u0432\u043a\u0430"
    ],
    "name:und_x_variant":[
        "\u041f\u0435\u0442\u0443\u0445\u043e\u0432\u043a\u0430"
    ],
    "wof:name":"Petukhovka",
    "wof:placetype":"locality"
},
  "geometry": {"coordinates":[57.58333,55.55],"type":"Point"}
}