{
  "type": "Feature",
  "properties": {
    "gn:admin1_code":"86",
    "gn:asciiname":"Krasyukovskiy",
    "gn:country_code":"RU",
    "gn:dem":106,
    "gn:feature_class":"P",
    "gn:feature_code":"PPL",
    "gn:name":"Krasyukovskiy",
    "gn:population":0,
    "gn:timezone":"Europe/Moscow",
    "iso:country":"RU",
    "name:rus_x_preferred":[
        "\u041a\u0440\u0430\u0441\u044e\u043a\u043e\u0432\u0441\u043a\u0438\u0439"
    ],
    "wof:name":"Krasyukovskiy",
    "wof:placetype":"locality"
},
  "geometry": {"coordinates":[39.64824,50.5082],"type":"Point"}
}