{
  "type": "Feature",
  "properties": {
    "gn:admin1_code":"13",
    "gn:asciiname":"Slikisha",
    "gn:country_code":"RU",
    "gn:dem":400,
    "gn:feature_class":"P",
    "gn:feature_code":"PPL",
    "gn:name":"Slikisha",
    "gn:population":0,
    "gn:timezone":"Asia/Yekaterinburg",
    "iso:country":"RU",
    "name:rus_x_preferred":[
        "\u0421\u043b\u0438\u043a\u0438\u0448\u0430"
    ],
    "wof:name":"Slikisha",
    "wof:placetype":"locality"
},
  "geometry": {"coordinates":[60.08333,55.61666999999999],"type":"Point"}
}