{
  "type": "Feature",
  "properties": {
    "gn:admin1_code":"61.0",
    "gn:asciiname":"Gayevka",
    "gn:country_code":"RU",
    "gn:dem":27,
    "gn:feature_class":"P",
    "gn:feature_code":"PPL",
    "gn:name":"Gayevka",
    "gn:population":0,
    "gn:timezone":"Europe/Moscow",
    "iso:country":"RU",
    "name:rus_x_preferred":[
        "\u0413\u0430\u0435\u0432\u043a\u0430"
    ],
    "wof:name":"Gayevka",
    "wof:placetype":"locality"
},
  "geometry": {"coordinates":[38.83963,47.27505],"type":"Point"}
}