{
  "type": "Feature",
  "properties": {
    "gn:admin1_code":"9",
    "gn:asciiname":"Kholodnoye",
    "gn:country_code":"RU",
    "gn:dem":220,
    "gn:feature_class":"P",
    "gn:feature_code":"PPL",
    "gn:name":"Kholodnoye",
    "gn:population":0,
    "gn:timezone":"Europe/Moscow",
    "iso:country":"RU",
    "name:eng_x_preferred":[
        "Kholodnoye"
    ],
    "name:nor_x_preferred":[
        "Kholodnoje"
    ],
    "name:rus_x_preferred":[
        "\u0425\u043e\u043b\u043e\u0434\u043d\u043e\u0435"
    ],
    "name:und_x_variant":[
        "\u0425\u043e\u043b\u043e\u0434\u043d\u043e\u0435",
        "Kholodnoye"
    ],
    "wof:name":"Kholodnoye",
    "wof:placetype":"locality"
},
  "geometry": {"coordinates":[37.10306,51.00693],"type":"Point"}
}