{
  "type": "Feature",
  "properties": {
    "gn:admin1_code":"67.0",
    "gn:asciiname":"Aleksandrovka Tret'ya",
    "gn:country_code":"RU",
    "gn:dem":171,
    "gn:feature_class":"P",
    "gn:feature_code":"PPL",
    "gn:name":"Aleksandrovka Tret\u2019ya",
    "gn:population":0,
    "gn:timezone":"Europe/Saratov",
    "iso:country":"RU",
    "name:nor_x_preferred":[
        "Aleksandrovka Tretja"
    ],
    "name:rus_x_preferred":[
        "\u0410\u043b\u0435\u043a\u0441\u0430\u043d\u0434\u0440\u043e\u0432\u043a\u0430 \u0422\u0440\u0435\u0442\u044c\u044f"
    ],
    "name:und_x_variant":[
        "Aleksandrovka",
        "Aleksandrovka Tret\u2019ya"
    ],
    "wof:name":"Aleksandrovka Tret'ya",
    "wof:placetype":"locality"
},
  "geometry": {"coordinates":[44.15169,51.68151],"type":"Point"}
}