{
  "type": "Feature",
  "properties": {
    "gn:admin1_code":"29",
    "gn:asciiname":"Ust'-Munzha",
    "gn:country_code":"RU",
    "gn:dem":431,
    "gn:feature_class":"P",
    "gn:feature_code":"PPL",
    "gn:name":"Ust\u2019-Munzha",
    "gn:population":0,
    "gn:timezone":"Asia/Novokuznetsk",
    "iso:country":"RU",
    "name:eng_x_preferred":[
        "Ust'-Munzha"
    ],
    "name:nor_x_preferred":[
        "Ust-Munzja"
    ],
    "name:rus_x_preferred":[
        "\u0423\u0441\u0442\u044c-\u041c\u0443\u043d\u0436\u0430"
    ],
    "name:und_x_variant":[
        "Munzha",
        "Ulus Munzha",
        "Ust\u2019-Munzha"
    ],
    "wof:name":"Ust'-Munzha",
    "wof:placetype":"locality"
},
  "geometry": {"coordinates":[87.48333000000002,52.65],"type":"Point"}
}