{
  "type": "Feature",
  "properties": {
    "gn:admin1_code":"21",
    "gn:asciiname":"Klyginskaya",
    "gn:country_code":"RU",
    "gn:dem":129,
    "gn:feature_class":"P",
    "gn:feature_code":"PPL",
    "gn:name":"Klyginskaya",
    "gn:population":0,
    "gn:timezone":"Europe/Moscow",
    "iso:country":"RU",
    "name:rus_x_preferred":[
        "\u041a\u043b\u044b\u0433\u0438\u043d\u0441\u043a\u0430\u044f"
    ],
    "wof:name":"Klyginskaya",
    "wof:placetype":"locality"
},
  "geometry": {"coordinates":[41.98459,57.25615],"type":"Point"}
}