{
  "type": "Feature",
  "properties": {
    "gn:admin1_code":"67",
    "gn:asciiname":"Peredovoy",
    "gn:country_code":"RU",
    "gn:dem":18,
    "gn:feature_class":"P",
    "gn:feature_code":"PPL",
    "gn:name":"Peredovoy",
    "gn:population":0,
    "gn:timezone":"Europe/Saratov",
    "iso:country":"RU",
    "name:eng_x_preferred":[
        "Peredovoy"
    ],
    "name:nor_x_preferred":[
        "Peredovoj"
    ],
    "name:rus_x_preferred":[
        "\u041f\u0435\u0440\u0435\u0434\u043e\u0432\u043e\u0439"
    ],
    "name:und_x_variant":[
        "Peredovoye",
        "\u041f\u0435\u0440\u0435\u0434\u043e\u0432\u043e\u0439",
        "Peredovoy"
    ],
    "wof:name":"Peredovoy",
    "wof:placetype":"locality"
},
  "geometry": {"coordinates":[48.81597,50.09459],"type":"Point"}
}