{
  "type": "Feature",
  "properties": {
    "gn:admin1_code":"56",
    "gn:asciiname":"Orlyanka",
    "gn:country_code":"RU",
    "gn:dem":213,
    "gn:feature_class":"P",
    "gn:feature_code":"PPL",
    "gn:name":"Orlyanka",
    "gn:population":0,
    "gn:timezone":"Europe/Moscow",
    "iso:country":"RU",
    "name:rus_x_preferred":[
        "\u041e\u0440\u043b\u044f\u043d\u043a\u0430"
    ],
    "name:und_x_variant":[
        "Oriyunka",
        "Orlyanka",
        "\u041e\u0440\u043b\u044f\u043d\u043a\u0430"
    ],
    "wof:name":"Orlyanka",
    "wof:placetype":"locality"
},
  "geometry": {"coordinates":[36.48484000000001,52.33552],"type":"Point"}
}