{
  "type": "Feature",
  "properties": {
    "gn:admin1_code":"33",
    "gn:asciiname":"Yelanka",
    "gn:country_code":"RU",
    "gn:dem":210,
    "gn:feature_class":"P",
    "gn:feature_code":"PPL",
    "gn:name":"Yelanka",
    "gn:population":0,
    "gn:timezone":"Europe/Kirov",
    "iso:country":"RU",
    "name:che_x_preferred":[
        "\u0415\u043b\u0430\u043d\u043a\u0430"
    ],
    "name:sah_x_preferred":[
        "\u0415\u043b\u0430\u043d\u043a\u0430"
    ],
    "wof:name":"Yelanka",
    "wof:placetype":"locality"
},
  "geometry": {"coordinates":[49.95,57.71666999999999],"type":"Point"}
}