{
  "type": "Feature",
  "properties": {
    "gn:admin1_code":"67",
    "gn:asciiname":"Undol'shchino",
    "gn:country_code":"RU",
    "gn:dem":168,
    "gn:feature_class":"P",
    "gn:feature_code":"PPL",
    "gn:name":"Undol\u2019shchino",
    "gn:population":0,
    "gn:timezone":"Europe/Saratov",
    "iso:country":"RU",
    "wof:name":"Undol'shchino",
    "wof:placetype":"locality"
},
  "geometry": {"coordinates":[43.48371,52.11526],"type":"Point"}
}