{
  "type": "Feature",
  "properties": {
    "gn:admin1_code":"47",
    "gn:asciiname":"Staromoygory",
    "gn:country_code":"RU",
    "gn:dem":173,
    "gn:feature_class":"P",
    "gn:feature_code":"PPL",
    "gn:name":"Staromoygory",
    "gn:population":0,
    "gn:timezone":"Europe/Moscow",
    "iso:country":"RU",
    "name:rus_x_preferred":[
        "\u0421\u0442\u0430\u0440\u043e\u043c\u043e\u0439\u0433\u043e\u0440\u044b"
    ],
    "name:und_x_variant":[
        "Staraya Moygora",
        "Staromoygory"
    ],
    "wof:name":"Staromoygory",
    "wof:placetype":"locality"
},
  "geometry": {"coordinates":[38.49968,54.47981],"type":"Point"}
}