{
  "type": "Feature",
  "properties": {
    "gn:admin1_code":"90.0",
    "gn:asciiname":"Chernaya",
    "gn:country_code":"RU",
    "gn:dem":129,
    "gn:feature_class":"P",
    "gn:feature_code":"PPL",
    "gn:name":"Ch\u00ebrnaya",
    "gn:population":0,
    "gn:timezone":"Asia/Yekaterinburg",
    "iso:country":"RU",
    "name:eng_x_preferred":[
        "Ch\u00ebrnaya"
    ],
    "name:nor_x_preferred":[
        "Tsjernaja"
    ],
    "name:rus_x_preferred":[
        "\u0427\u0435\u0440\u043d\u0430\u044f"
    ],
    "name:rus_x_variant":[
        "\u0427\u0451\u0440\u043d\u0430\u044f"
    ],
    "name:und_x_variant":[
        "\u0427\u0451\u0440\u043d\u0430\u044f",
        "Ch\u00ebrnaya"
    ],
    "wof:name":"Chernaya",
    "wof:placetype":"locality"
},
  "geometry": {"coordinates":[55.73094,58.14241],"type":"Point"}
}