{
  "type": "Feature",
  "properties": {
    "gn:admin1_code":"88",
    "gn:asciiname":"Sel'tsy",
    "gn:country_code":"RU",
    "gn:dem":132,
    "gn:feature_class":"P",
    "gn:feature_code":"PPL",
    "gn:name":"Sel\u2019tsy",
    "gn:population":0,
    "gn:timezone":"Europe/Moscow",
    "iso:country":"RU",
    "name:rus_x_preferred":[
        "\u0421\u0435\u043b\u044c\u0446\u044b"
    ],
    "name:und_x_variant":[
        "Sel\u2019tsy"
    ],
    "wof:name":"Sel'tsy",
    "wof:placetype":"locality"
},
  "geometry": {"coordinates":[38.1018,57.5122],"type":"Point"}
}