{
  "type": "Feature",
  "properties": {
    "gn:admin1_code":"77",
    "gn:asciiname":"Kharovichi",
    "gn:country_code":"RU",
    "gn:dem":183,
    "gn:feature_class":"P",
    "gn:feature_code":"PPL",
    "gn:name":"Kharovichi",
    "gn:population":0,
    "gn:timezone":"Europe/Moscow",
    "iso:country":"RU",
    "name:rus_x_preferred":[
        "\u0425\u0430\u0440\u043e\u0432\u0438\u0447\u0438"
    ],
    "wof:name":"Kharovichi",
    "wof:placetype":"locality"
},
  "geometry": {"coordinates":[36.2629,58.4858],"type":"Point"}
}