{
  "type": "Feature",
  "properties": {
    "gn:admin1_code":"56",
    "gn:asciiname":"Kikino",
    "gn:country_code":"RU",
    "gn:dem":147,
    "gn:feature_class":"P",
    "gn:feature_code":"PPL",
    "gn:name":"Kikino",
    "gn:population":0,
    "gn:timezone":"Europe/Moscow",
    "iso:country":"RU",
    "name:rus_x_preferred":[
        "\u041a\u0438\u043a\u0438\u043d\u043e"
    ],
    "name:und_x_variant":[
        "Krupyatskoye",
        "Kikino"
    ],
    "wof:name":"Kikino",
    "wof:placetype":"locality"
},
  "geometry": {"coordinates":[36.31367,53.18353000000001],"type":"Point"}
}