{
  "type": "Feature",
  "properties": {
    "gn:admin1_code":"60.0",
    "gn:asciiname":"Gachki",
    "gn:country_code":"RU",
    "gn:dem":75,
    "gn:feature_class":"P",
    "gn:feature_code":"PPL",
    "gn:name":"Gachki",
    "gn:population":0,
    "gn:timezone":"Europe/Moscow",
    "iso:country":"RU",
    "name:rus_x_preferred":[
        "\u0413\u0430\u0447\u043a\u0438"
    ],
    "name:und_x_variant":[
        "\u0413\u0430\u0447\u043a\u0438"
    ],
    "wof:name":"Gachki",
    "wof:placetype":"locality"
},
  "geometry": {"coordinates":[30.14344,57.88786999999999],"type":"Point"}
}