{
  "type": "Feature",
  "properties": {
    "gn:admin1_code":"33",
    "gn:asciiname":"Maksaki",
    "gn:country_code":"RU",
    "gn:dem":190,
    "gn:feature_class":"P",
    "gn:feature_code":"PPL",
    "gn:name":"Maksaki",
    "gn:population":0,
    "gn:timezone":"Europe/Kirov",
    "iso:country":"RU",
    "name:eng_x_preferred":[
        "Maksaki"
    ],
    "name:nor_x_preferred":[
        "Maksaki"
    ],
    "name:rus_x_preferred":[
        "\u041c\u0430\u043a\u0441\u0430\u043a\u0438"
    ],
    "name:und_x_variant":[
        "\u041c\u0430\u043a\u0441\u0430\u043a\u0438",
        "Maksaki"
    ],
    "wof:name":"Maksaki",
    "wof:placetype":"locality"
},
  "geometry": {"coordinates":[49.15692,57.91112],"type":"Point"}
}