{
  "type": "Feature",
  "properties": {
    "gn:admin1_code":"63",
    "gn:asciiname":"Yendeyyer",
    "gn:country_code":"RU",
    "gn:dem":273,
    "gn:feature_class":"P",
    "gn:feature_code":"PPL",
    "gn:name":"Yend\u00ebyy\u00ebr",
    "gn:population":0,
    "gn:timezone":"Asia/Yakutsk",
    "iso:country":"RU",
    "name:eng_x_preferred":[
        "Yend\u00ebyy\u00ebr"
    ],
    "name:nor_x_preferred":[
        "Jendejer"
    ],
    "name:rus_x_preferred":[
        "\u0415\u043d\u0434\u0435\u0439\u0435\u0440"
    ],
    "wof:name":"Yendeyyer",
    "wof:placetype":"locality"
},
  "geometry": {"coordinates":[131.86001000000002,61.44851],"type":"Point"}
}