{
  "type": "Feature",
  "properties": {
    "gn:admin1_code":"56.0",
    "gn:asciiname":"Bakino",
    "gn:country_code":"RU",
    "gn:dem":177,
    "gn:feature_class":"P",
    "gn:feature_code":"PPL",
    "gn:name":"Bakino",
    "gn:population":0,
    "gn:timezone":"Europe/Moscow",
    "iso:country":"RU",
    "name:nor_x_preferred":[
        "Bakinskij"
    ],
    "name:rus_x_preferred":[
        "\u0411\u0430\u043a\u0438\u043d\u043e"
    ],
    "name:und_x_variant":[
        "\u0411\u0430\u043a\u0438\u043d\u043e",
        "Bakinskiy"
    ],
    "wof:name":"Bakino",
    "wof:placetype":"locality"
},
  "geometry": {"coordinates":[36.28122000000001,52.91079000000001],"type":"Point"}
}