{
  "type": "Feature",
  "properties": {
    "gn:admin1_code":"76.0",
    "gn:asciiname":"Bugrovka-Klyuchevaya",
    "gn:country_code":"RU",
    "gn:dem":198,
    "gn:feature_class":"P",
    "gn:feature_code":"PPL",
    "gn:name":"Bugrovka-Klyuchevaya",
    "gn:population":0,
    "gn:timezone":"Europe/Moscow",
    "iso:country":"RU",
    "name:rus_x_preferred":[
        "\u0411\u0443\u0433\u0440\u043e\u0432\u043a\u0430-\u041a\u043b\u044e\u0447\u0435\u0432\u0430\u044f"
    ],
    "name:und_x_variant":[
        "Bugrovka"
    ],
    "wof:name":"Bugrovka-Klyuchevaya",
    "wof:placetype":"locality"
},
  "geometry": {"coordinates":[38.82145,53.80407],"type":"Point"}
}