{
  "type": "Feature",
  "properties": {
    "gn:admin1_code":"54",
    "gn:asciiname":"Nayman",
    "gn:country_code":"RU",
    "gn:dem":106,
    "gn:feature_class":"P",
    "gn:feature_code":"PPL",
    "gn:name":"Nayman",
    "gn:population":0,
    "gn:timezone":"Asia/Omsk",
    "iso:country":"RU",
    "name:ceb_x_preferred":[
        "Nayman"
    ],
    "name:kir_x_preferred":[
        "\u041d\u0430\u0439\u043c\u0430\u043d"
    ],
    "name:rus_x_preferred":[
        "\u041d\u0430\u0439\u043c\u0430\u043d"
    ],
    "name:swe_x_preferred":[
        "Nayman"
    ],
    "name:ukr_x_preferred":[
        "\u041d\u0430\u0439\u043c\u0430\u043d"
    ],
    "name:und_x_variant":[
        "\u041d\u0430\u0439\u043c\u0430\u043d"
    ],
    "name:uzb_x_preferred":[
        "Nayman"
    ],
    "wof:name":"Nayman",
    "wof:placetype":"locality"
},
  "geometry": {"coordinates":[72.55,54.53333000000001],"type":"Point"}
}