{
  "type": "Feature",
  "properties": {
    "gn:admin1_code":"67.0",
    "gn:asciiname":"Akhmat",
    "gn:country_code":"RU",
    "gn:dem":36,
    "gn:feature_class":"P",
    "gn:feature_code":"PPL",
    "gn:name":"Akhmat",
    "gn:population":0,
    "gn:timezone":"Europe/Saratov",
    "iso:country":"RU",
    "name:nor_x_preferred":[
        "Akhmat"
    ],
    "name:rus_x_preferred":[
        "\u0410\u0445\u043c\u0430\u0442"
    ],
    "wof:name":"Akhmat",
    "wof:placetype":"locality"
},
  "geometry": {"coordinates":[46.93333,50.76667],"type":"Point"}
}