{
  "type": "Feature",
  "properties": {
    "gn:admin1_code":"69",
    "gn:asciiname":"Pleshchitsy",
    "gn:country_code":"RU",
    "gn:dem":190,
    "gn:feature_class":"P",
    "gn:feature_code":"PPL",
    "gn:name":"Pleshchitsy",
    "gn:population":0,
    "gn:timezone":"Europe/Moscow",
    "iso:country":"RU",
    "name:rus_x_preferred":[
        "\u041f\u043b\u0435\u0449\u0438\u0446\u044b"
    ],
    "name:und_x_variant":[
        "Pleshchitsa",
        "Pleshchitsy"
    ],
    "wof:name":"Pleshchitsy",
    "wof:placetype":"locality"
},
  "geometry": {"coordinates":[32.0811,54.07368],"type":"Point"}
}