{
  "type": "Feature",
  "properties": {
    "gn:admin1_code":"84",
    "gn:asciiname":"Titovskiy",
    "gn:country_code":"RU",
    "gn:dem":101,
    "gn:feature_class":"P",
    "gn:feature_code":"PPL",
    "gn:name":"Titovskiy",
    "gn:population":0,
    "gn:timezone":"Europe/Volgograd",
    "iso:country":"RU",
    "name:rus_x_preferred":[
        "\u0422\u0438\u0442\u043e\u0432\u0441\u043a\u0438\u0439"
    ],
    "name:und_x_variant":[
        "Titov"
    ],
    "wof:name":"Titovskiy",
    "wof:placetype":"locality"
},
  "geometry": {"coordinates":[42.803,50.5159],"type":"Point"}
}