{
  "type": "Feature",
  "properties": {
    "gn:admin1_code":"80",
    "gn:asciiname":"Pyshket",
    "gn:country_code":"RU",
    "gn:dem":201,
    "gn:feature_class":"P",
    "gn:feature_code":"PPL",
    "gn:name":"Pyshket",
    "gn:population":0,
    "gn:timezone":"Europe/Samara",
    "iso:country":"RU",
    "name:eng_x_preferred":[
        "Pyshket"
    ],
    "name:nor_x_preferred":[
        "Pysjket"
    ],
    "name:rus_x_preferred":[
        "\u041f\u044b\u0448\u043a\u0435\u0442"
    ],
    "name:und_x_variant":[
        "\u041f\u044b\u0448\u043a\u0435\u0442",
        "Pyshket"
    ],
    "wof:name":"Pyshket",
    "wof:placetype":"locality"
},
  "geometry": {"coordinates":[51.9524,57.8966],"type":"Point"}
}