{
  "type": "Feature",
  "properties": {
    "gn:admin1_code":"77",
    "gn:asciiname":"Gribovo",
    "gn:cc2":"RU",
    "gn:country_code":"RU",
    "gn:dem":140,
    "gn:feature_class":"P",
    "gn:feature_code":"PPL",
    "gn:name":"Gribovo",
    "gn:population":0,
    "gn:timezone":"Europe/Moscow",
    "iso:country":"RU",
    "name:rus_x_preferred":[
        "\u0413\u0440\u0438\u0431\u043e\u0432\u043e"
    ],
    "name:und_x_variant":[
        "Gatbovo",
        "Gribovo",
        "\u0413\u0440\u0438\u0431\u043e\u0432\u043e"
    ],
    "wof:name":"Gribovo",
    "wof:placetype":"locality"
},
  "geometry": {"coordinates":[35.65,56.93333000000001],"type":"Point"}
}