{
  "type": "Feature",
  "properties": {
    "gn:admin1_code":"53",
    "gn:asciiname":"Klubnichnyy",
    "gn:country_code":"RU",
    "gn:dem":139,
    "gn:feature_class":"P",
    "gn:feature_code":"PPL",
    "gn:name":"Klubnichnyy",
    "gn:population":0,
    "gn:timezone":"Asia/Novosibirsk",
    "iso:country":"RU",
    "name:rus_x_preferred":[
        "\u041a\u043b\u0443\u0431\u043d\u0438\u0447\u043d\u044b\u0439"
    ],
    "name:und_x_variant":[
        "\u041a\u043b\u0443\u0431\u043d\u0438\u0447\u043d\u044b\u0439"
    ],
    "wof:name":"Klubnichnyy",
    "wof:placetype":"locality"
},
  "geometry": {"coordinates":[79.35214000000001,55.33071],"type":"Point"}
}