{
  "type": "Feature",
  "properties": {
    "gn:admin1_code":"83",
    "gn:asciiname":"Fedos'ino",
    "gn:country_code":"RU",
    "gn:dem":184,
    "gn:feature_class":"P",
    "gn:feature_code":"PPL",
    "gn:name":"Fedos\u2019ino",
    "gn:population":0,
    "gn:timezone":"Europe/Moscow",
    "iso:country":"RU",
    "name:rus_x_preferred":[
        "\u0424\u0435\u0434\u043e\u0441\u044c\u0438\u043d\u043e"
    ],
    "name:und_x_variant":[
        "Fedos\u2019ino"
    ],
    "wof:name":"Fedos'ino",
    "wof:placetype":"locality"
},
  "geometry": {"coordinates":[39.6598,56.55529],"type":"Point"}
}