{
  "type": "Feature",
  "properties": {
    "gn:admin1_code":"8",
    "gn:asciiname":"Katayka",
    "gn:country_code":"RU",
    "gn:dem":538,
    "gn:feature_class":"P",
    "gn:feature_code":"PPL",
    "gn:name":"Katayka",
    "gn:population":0,
    "gn:timezone":"Asia/Yekaterinburg",
    "iso:country":"RU",
    "name:bak_x_preferred":[
        "\u04a0\u0430\u0442\u0430\u0439"
    ],
    "name:che_x_preferred":[
        "\u041a\u0430\u0442\u0430\u0439\u043a\u0430"
    ],
    "name:eng_x_preferred":[
        "Katayka"
    ],
    "name:hye_x_preferred":[
        "\u053f\u0561\u057f\u0561\u0575\u056f\u0561"
    ],
    "name:kat_x_preferred":[
        "\u10d9\u10d0\u10e2\u10d0\u10d8\u10d9\u10d0"
    ],
    "name:kaz_x_preferred":[
        "\u041a\u0430\u0442\u0430\u0439\u043a\u0430"
    ],
    "name:nor_x_preferred":[
        "Katajka"
    ],
    "name:rus_x_preferred":[
        "\u041a\u0430\u0442\u0430\u0439\u043a\u0430"
    ],
    "name:tat_x_preferred":[
        "\u041a\u0430\u0442\u0430\u0439"
    ],
    "name:ukr_x_preferred":[
        "\u041a\u0430\u0442\u0430\u0439\u043a\u0430"
    ],
    "name:und_x_variant":[
        "\u041a\u0430\u0442\u0430\u0439\u043a\u0430",
        "Katayka"
    ],
    "wof:name":"Katayka",
    "wof:placetype":"locality"
},
  "geometry": {"coordinates":[58.424,54.0427],"type":"Point"}
}