{
  "type": "Feature",
  "properties": {
    "gn:admin1_code":"63",
    "gn:asciiname":"Setan'ya",
    "gn:country_code":"RU",
    "gn:dem":629,
    "gn:feature_class":"P",
    "gn:feature_code":"PPL",
    "gn:name":"Setan\u2019ya",
    "gn:population":0,
    "gn:timezone":"Asia/Vladivostok",
    "iso:country":"RU",
    "name:rus_x_preferred":[
        "\u0421\u0435\u0442\u0430\u043d\u044c\u044f"
    ],
    "name:und_x_variant":[
        "Setan\u2019ya",
        "\u0421\u0435\u0442\u0430\u043d\u044c\u044f"
    ],
    "wof:name":"Setan'ya",
    "wof:placetype":"locality"
},
  "geometry": {"coordinates":[137.73333,61.36666999999999],"type":"Point"}
}