{
  "type": "Feature",
  "properties": {
    "gn:admin1_code":"17",
    "gn:asciiname":"Tulizma",
    "gn:country_code":"RU",
    "gn:dem":1913,
    "gn:feature_class":"P",
    "gn:feature_code":"PPL",
    "gn:name":"Tulizma",
    "gn:population":0,
    "gn:timezone":"Europe/Moscow",
    "iso:country":"RU",
    "wof:name":"Tulizma",
    "wof:placetype":"locality"
},
  "geometry": {"coordinates":[47.09214,42.11722],"type":"Point"}
}