{
  "type": "Feature",
  "properties": {
    "gn:admin1_code":"11",
    "gn:asciiname":"Urinskiy Istochnik",
    "gn:country_code":"RU",
    "gn:dem":1218,
    "gn:feature_class":"P",
    "gn:feature_code":"PPL",
    "gn:name":"Urinskiy Istochnik",
    "gn:population":0,
    "gn:timezone":"Asia/Irkutsk",
    "iso:country":"RU",
    "wof:name":"Urinskiy Istochnik",
    "wof:placetype":"locality"
},
  "geometry": {"coordinates":[110.08333,53.43333000000001],"type":"Point"}
}