{
  "type": "Feature",
  "properties": {
    "gn:admin1_code":"33",
    "gn:asciiname":"Sosnovka",
    "gn:country_code":"RU",
    "gn:dem":113,
    "gn:feature_class":"P",
    "gn:feature_code":"PPL",
    "gn:name":"Sosnovka",
    "gn:population":0,
    "gn:timezone":"Europe/Kirov",
    "iso:country":"RU",
    "name:rus_x_preferred":[
        "\u0421\u043e\u0441\u043d\u043e\u0432\u043a\u0430"
    ],
    "wof:name":"Sosnovka",
    "wof:placetype":"locality"
},
  "geometry": {"coordinates":[47.8845,57.2657],"type":"Point"}
}