{
  "type": "Feature",
  "properties": {
    "gn:admin1_code":"73",
    "gn:admin2_code":"862917",
    "gn:asciiname":"Urgancha",
    "gn:country_code":"RU",
    "gn:dem":96,
    "gn:feature_class":"P",
    "gn:feature_code":"PPL",
    "gn:name":"Urgancha",
    "gn:population":0,
    "gn:timezone":"Europe/Moscow",
    "iso:country":"RU",
    "name:rus_x_preferred":[
        "\u0423\u0440\u0433\u0430\u043d\u0441\u0430"
    ],
    "wof:name":"Urgancha",
    "wof:placetype":"locality"
},
  "geometry": {"coordinates":[51.4672,55.2323],"type":"Point"}
}