{
  "type": "Feature",
  "properties": {
    "gn:admin1_code":"33",
    "gn:asciiname":"Sredneivkino",
    "gn:country_code":"RU",
    "gn:dem":177,
    "gn:feature_class":"P",
    "gn:feature_code":"PPL",
    "gn:name":"Sredneivkino",
    "gn:population":0,
    "gn:timezone":"Europe/Kirov",
    "iso:country":"RU",
    "name:eng_x_preferred":[
        "Sredneivkino"
    ],
    "name:nor_x_preferred":[
        "Sredneivkino"
    ],
    "name:rus_x_preferred":[
        "\u0421\u0440\u0435\u0434\u043d\u0435\u0438\u0432\u043a\u0438\u043d\u043e"
    ],
    "name:und_x_variant":[
        "Sredneye Ivkino"
    ],
    "wof:name":"Sredneivkino",
    "wof:placetype":"locality"
},
  "geometry": {"coordinates":[49.42946,58.00202],"type":"Point"}
}