{
  "type": "Feature",
  "properties": {
    "gn:admin1_code":"60",
    "gn:asciiname":"Spitsina",
    "gn:country_code":"RU",
    "gn:dem":157,
    "gn:feature_class":"P",
    "gn:feature_code":"PPL",
    "gn:name":"Spitsina",
    "gn:population":0,
    "gn:timezone":"Europe/Moscow",
    "iso:country":"RU",
    "name:rus_x_preferred":[
        "\u0421\u043f\u0438\u0446\u0438\u043d\u0430"
    ],
    "name:und_x_variant":[
        "Spitsyna",
        "Spitsina"
    ],
    "wof:name":"Spitsina",
    "wof:placetype":"locality"
},
  "geometry": {"coordinates":[30.97145,56.01925],"type":"Point"}
}