{
  "type": "Feature",
  "properties": {
    "gn:admin1_code":"8.0",
    "gn:asciiname":"Dautlarovo",
    "gn:country_code":"RU",
    "gn:dem":133,
    "gn:feature_class":"P",
    "gn:feature_code":"PPL",
    "gn:name":"Dautlarovo",
    "gn:population":0,
    "gn:timezone":"Asia/Yekaterinburg",
    "iso:country":"RU",
    "name:bak_x_preferred":[
        "\u0414\u0430\u0443\u044b\u0442\u043b\u0430\u0440"
    ],
    "name:che_x_preferred":[
        "\u0414\u0430\u0443\u0442\u043b\u0430\u0440\u043e\u0432\u043e"
    ],
    "name:eng_x_preferred":[
        "Dautlarovo"
    ],
    "name:hye_x_preferred":[
        "\u0534\u0561\u0578\u0582\u057f\u056c\u0561\u0580\u0578\u057e\u0578"
    ],
    "name:kaz_x_preferred":[
        "\u0414\u0430\u0443\u0442\u043b\u0430\u0440"
    ],
    "name:kir_x_preferred":[
        "\u0414\u0430\u0443\u0442\u043b\u0430\u0440"
    ],
    "name:nor_x_preferred":[
        "Dautlarovo"
    ],
    "name:rus_x_preferred":[
        "\u0414\u0430\u0443\u0442\u043b\u0430\u0440\u043e\u0432\u043e"
    ],
    "name:tat_x_preferred":[
        "\u0414\u0430\u0432\u044b\u0442\u043b\u0430\u0440"
    ],
    "name:und_x_variant":[
        "\u0414\u0430\u0443\u0442\u043b\u0430\u0440\u043e\u0432\u043e",
        "Dautlarovo"
    ],
    "wof:name":"Dautlarovo",
    "wof:placetype":"locality"
},
  "geometry": {"coordinates":[55.71354,55.77063],"type":"Point"}
}