{
  "type": "Feature",
  "properties": {
    "gn:admin1_code":"49.0",
    "gn:asciiname":"Gabrish",
    "gn:cc2":"RU",
    "gn:country_code":"RU",
    "gn:dem":35,
    "gn:feature_class":"P",
    "gn:feature_code":"PPL",
    "gn:name":"Gabrish",
    "gn:population":0,
    "gn:timezone":"Europe/Moscow",
    "iso:country":"RU",
    "name:fin_x_preferred":[
        "Kaprit\u0161a"
    ],
    "name:rus_x_preferred":[
        "\u0413\u0430\u0431\u0440\u0438\u0448"
    ],
    "name:und_x_variant":[
        "Gabrezh",
        "Gabrish"
    ],
    "wof:name":"Gabrish",
    "wof:placetype":"locality"
},
  "geometry": {"coordinates":[31.86667000000001,66.81667],"type":"Point"}
}