{
  "type": "Feature",
  "properties": {
    "gn:admin1_code":"54",
    "gn:asciiname":"Kaban'ye",
    "gn:country_code":"RU",
    "gn:dem":106,
    "gn:feature_class":"P",
    "gn:feature_code":"PPL",
    "gn:name":"Kaban\u2019ye",
    "gn:population":0,
    "gn:timezone":"Asia/Omsk",
    "iso:country":"RU",
    "name:eng_x_preferred":[
        "Kaban'ye"
    ],
    "name:nor_x_preferred":[
        "Kabanje"
    ],
    "name:rus_x_preferred":[
        "\u041a\u0430\u0431\u0430\u043d\u044c\u0435"
    ],
    "name:und_x_variant":[
        "Kaban\u2019ya",
        "Kaban\u2019ye"
    ],
    "wof:name":"Kaban'ye",
    "wof:placetype":"locality"
},
  "geometry": {"coordinates":[75.20484999999999,54.99326],"type":"Point"}
}