{
  "type": "Feature",
  "properties": {
    "gn:admin1_code":"83",
    "gn:asciiname":"Krylovo",
    "gn:country_code":"RU",
    "gn:dem":77,
    "gn:feature_class":"P",
    "gn:feature_code":"PPL",
    "gn:name":"Krylovo",
    "gn:population":0,
    "gn:timezone":"Europe/Moscow",
    "iso:country":"RU",
    "name:und_x_variant":[
        "Krylova",
        "Krylovo"
    ],
    "wof:name":"Krylovo",
    "wof:placetype":"locality"
},
  "geometry": {"coordinates":[42.89547,56.16991],"type":"Point"}
}