{
  "type": "Feature",
  "properties": {
    "gn:admin1_code":"67",
    "gn:asciiname":"Novaya Il'inka",
    "gn:country_code":"RU",
    "gn:dem":167,
    "gn:feature_class":"P",
    "gn:feature_code":"PPL",
    "gn:name":"Novaya Il\u2019inka",
    "gn:population":0,
    "gn:timezone":"Europe/Saratov",
    "iso:country":"RU",
    "name:rus_x_preferred":[
        "\u041d\u043e\u0432\u0430\u044f \u0418\u043b\u044c\u0438\u043d\u043a\u0430"
    ],
    "name:und_x_variant":[
        "Novaya Il\u2019inka",
        "\u041d\u043e\u0432\u0430\u044f \u0418\u043b\u044c\u0438\u043d\u043a\u0430"
    ],
    "wof:name":"Novaya Il'inka",
    "wof:placetype":"locality"
},
  "geometry": {"coordinates":[43.37556,51.54889],"type":"Point"}
}