{
  "type": "Feature",
  "properties": {
    "gn:admin1_code":"69.0",
    "gn:asciiname":"Dudkino",
    "gn:country_code":"RU",
    "gn:dem":241,
    "gn:feature_class":"P",
    "gn:feature_code":"PPL",
    "gn:name":"Dudkino",
    "gn:population":0,
    "gn:timezone":"Europe/Moscow",
    "iso:country":"RU",
    "name:rus_x_preferred":[
        "\u0414\u0443\u0434\u043a\u0438\u043d\u043e"
    ],
    "wof:name":"Dudkino",
    "wof:placetype":"locality"
},
  "geometry": {"coordinates":[33.71291,55.88856],"type":"Point"}
}