{
  "type": "Feature",
  "properties": {
    "gn:admin1_code":"52",
    "gn:asciiname":"Melichazha",
    "gn:country_code":"RU",
    "gn:dem":52,
    "gn:feature_class":"P",
    "gn:feature_code":"PPL",
    "gn:name":"Melichazha",
    "gn:population":0,
    "gn:timezone":"Europe/Moscow",
    "iso:country":"RU",
    "name:rus_x_preferred":[
        "\u041c\u0435\u043b\u0438\u0447\u0430\u0436\u0430"
    ],
    "wof:name":"Melichazha",
    "wof:placetype":"locality"
},
  "geometry": {"coordinates":[30.85,58.75],"type":"Point"}
}