{
  "type": "Feature",
  "properties": {
    "gn:admin1_code":"56",
    "gn:asciiname":"Payusovo",
    "gn:country_code":"RU",
    "gn:dem":180,
    "gn:feature_class":"P",
    "gn:feature_code":"PPL",
    "gn:name":"Payusovo",
    "gn:population":0,
    "gn:timezone":"Europe/Moscow",
    "iso:country":"RU",
    "name:rus_x_preferred":[
        "\u041f\u0430\u044e\u0441\u043e\u0432\u043e"
    ],
    "name:und_x_variant":[
        "\u041f\u0430\u044e\u0441\u043e\u0432\u043e"
    ],
    "wof:name":"Payusovo",
    "wof:placetype":"locality"
},
  "geometry": {"coordinates":[35.99105,53.16871],"type":"Point"}
}