{
  "type": "Feature",
  "properties": {
    "gn:admin1_code":"8",
    "gn:asciiname":"Mukhametrakhimovo",
    "gn:cc2":"RU",
    "gn:country_code":"RU",
    "gn:dem":379,
    "gn:feature_class":"P",
    "gn:feature_code":"PPL",
    "gn:name":"Mukhametrakhimovo",
    "gn:population":0,
    "gn:timezone":"Asia/Yekaterinburg",
    "iso:country":"RU",
    "name:rus_x_preferred":[
        "\u041c\u0443\u0445\u0430\u043c\u0435\u0442\u0440\u0430\u0445\u0438\u043c\u043e\u0432\u043e"
    ],
    "name:und_x_variant":[
        "Mukhametrakhimova",
        "Mukhametrakhimovo"
    ],
    "wof:name":"Mukhametrakhimovo",
    "wof:placetype":"locality"
},
  "geometry": {"coordinates":[58.08333,52.15],"type":"Point"}
}