{
  "type": "Feature",
  "properties": {
    "gn:admin1_code":"8.0",
    "gn:asciiname":"Tazeyevo",
    "gn:country_code":"RU",
    "gn:dem":75,
    "gn:feature_class":"P",
    "gn:feature_code":"PPL",
    "gn:name":"Tazeyevo",
    "gn:population":0,
    "gn:timezone":"Asia/Yekaterinburg",
    "iso:country":"RU",
    "name:eng_x_preferred":[
        "Tazeyevo"
    ],
    "name:nor_x_preferred":[
        "Tazejevo"
    ],
    "name:rus_x_preferred":[
        "\u0422\u0430\u0437\u0435\u0435\u0432\u043e"
    ],
    "name:und_x_variant":[
        "Bol\u2019shoye Tazeyevo",
        "Tazeyevo"
    ],
    "wof:name":"Tazeyevo",
    "wof:placetype":"locality"
},
  "geometry": {"coordinates":[54.55886,55.60715],"type":"Point"}
}