{
  "type": "Feature",
  "properties": {
    "gn:admin1_code":"54",
    "gn:asciiname":"Andreyevskiy",
    "gn:country_code":"RU",
    "gn:dem":111,
    "gn:feature_class":"P",
    "gn:feature_code":"PPL",
    "gn:name":"Andreyevskiy",
    "gn:population":0,
    "gn:timezone":"Asia/Omsk",
    "iso:country":"RU",
    "name:rus_x_preferred":[
        "\u0410\u043d\u0434\u0440\u0435\u0435\u0432\u0441\u043a\u0438\u0439"
    ],
    "wof:name":"Andreyevskiy",
    "wof:placetype":"locality"
},
  "geometry": {"coordinates":[73.712,55.0928],"type":"Point"}
}