{
  "type": "Feature",
  "properties": {
    "gn:admin1_code":"51",
    "gn:asciiname":"Gorokhovo",
    "gn:country_code":"RU",
    "gn:dem":107,
    "gn:feature_class":"P",
    "gn:feature_code":"PPL",
    "gn:name":"Gorokhovo",
    "gn:population":0,
    "gn:timezone":"Europe/Moscow",
    "iso:country":"RU",
    "name:rus_x_preferred":[
        "\u0413\u043e\u0440\u043e\u0445\u043e\u0432\u043e"
    ],
    "name:und_x_variant":[
        "\u0413\u043e\u0440\u043e\u0445\u043e\u0432\u043e"
    ],
    "wof:name":"Gorokhovo",
    "wof:placetype":"locality"
},
  "geometry": {"coordinates":[43.3675,57.36448000000001],"type":"Point"}
}