{
  "type": "Feature",
  "properties": {
    "gn:admin1_code":"75",
    "gn:asciiname":"Novoil'inka",
    "gn:country_code":"RU",
    "gn:dem":105,
    "gn:feature_class":"P",
    "gn:feature_code":"PPL",
    "gn:name":"Novoil\u2019inka",
    "gn:population":0,
    "gn:timezone":"Asia/Tomsk",
    "iso:country":"RU",
    "name:eng_x_preferred":[
        "Novoil'inka"
    ],
    "name:nor_x_preferred":[
        "Novoilinka"
    ],
    "name:rus_x_preferred":[
        "\u041d\u043e\u0432\u043e\u0438\u043b\u044c\u0438\u043d\u043a\u0430"
    ],
    "name:und_x_variant":[
        "Novoil\u2019inka"
    ],
    "wof:name":"Novoil'inka",
    "wof:placetype":"locality"
},
  "geometry": {"coordinates":[84.09179,56.98711],"type":"Point"}
}