{
  "type": "Feature",
  "properties": {
    "gn:admin1_code":"55",
    "gn:asciiname":"Roshchepkino",
    "gn:country_code":"RU",
    "gn:dem":156,
    "gn:feature_class":"P",
    "gn:feature_code":"PPL",
    "gn:name":"Roshchepkino",
    "gn:population":0,
    "gn:timezone":"Asia/Yekaterinburg",
    "iso:country":"RU",
    "name:rus_x_preferred":[
        "\u0420\u043e\u0449\u0435\u043f\u043a\u0438\u043d\u043e"
    ],
    "name:und_x_variant":[
        "Malyye Gorki",
        "Roshchepkino"
    ],
    "wof:name":"Roshchepkino",
    "wof:placetype":"locality"
},
  "geometry": {"coordinates":[54.41667,52.68333000000001],"type":"Point"}
}