{
  "type": "Feature",
  "properties": {
    "gn:admin1_code":"24",
    "gn:asciiname":"Verkhniy Sal",
    "gn:country_code":"RU",
    "gn:dem":74,
    "gn:feature_class":"P",
    "gn:feature_code":"PPL",
    "gn:name":"Verkhniy Sal",
    "gn:population":0,
    "gn:timezone":"Europe/Moscow",
    "iso:country":"RU",
    "name:eng_x_preferred":[
        "Verkhniy Sal"
    ],
    "name:nor_x_preferred":[
        "Verkhnij Sal"
    ],
    "name:rus_x_preferred":[
        "\u0412\u0435\u0440\u0445\u043d\u0438\u0439 \u0421\u0430\u043b"
    ],
    "name:und_x_variant":[
        "Sarpinskiy",
        "Baga-Zorgakin",
        "Vershin-Sal",
        "Verkhne-Sal\u2019sk",
        "Verkhniy Sal\u2019sk",
        "Verkhne Sal\u2019skiy"
    ],
    "wof:name":"Verkhniy Sal",
    "wof:placetype":"locality"
},
  "geometry": {"coordinates":[43.87059,47.50193],"type":"Point"}
}