{
  "type": "Feature",
  "properties": {
    "gn:admin1_code":"60",
    "gn:asciiname":"Sakirino",
    "gn:country_code":"RU",
    "gn:dem":71,
    "gn:feature_class":"P",
    "gn:feature_code":"PPL",
    "gn:name":"Sakirino",
    "gn:population":0,
    "gn:timezone":"Europe/Moscow",
    "iso:country":"RU",
    "name:rus_x_preferred":[
        "\u0421\u0430\u043a\u0438\u0440\u0438\u043d\u043e"
    ],
    "wof:name":"Sakirino",
    "wof:placetype":"locality"
},
  "geometry": {"coordinates":[28.90397,57.47905],"type":"Point"}
}