{
  "type": "Feature",
  "properties": {
    "gn:admin1_code":"54",
    "gn:asciiname":"Sik",
    "gn:country_code":"RU",
    "gn:dem":101,
    "gn:feature_class":"P",
    "gn:feature_code":"PPL",
    "gn:name":"Sik",
    "gn:population":0,
    "gn:timezone":"Asia/Omsk",
    "iso:country":"RU",
    "name:rus_x_preferred":[
        "\u0421\u0438\u043a"
    ],
    "wof:name":"Sik",
    "wof:placetype":"locality"
},
  "geometry": {"coordinates":[73.38333,57.63333000000001],"type":"Point"}
}