{
  "type": "Feature",
  "properties": {
    "gn:admin1_code":"90.0",
    "gn:asciiname":"Igatka",
    "gn:country_code":"RU",
    "gn:dem":191,
    "gn:feature_class":"P",
    "gn:feature_code":"PPL",
    "gn:name":"Igatka",
    "gn:population":0,
    "gn:timezone":"Asia/Yekaterinburg",
    "iso:country":"RU",
    "name:rus_x_preferred":[
        "\u0418\u0433\u0430\u0442\u043a\u0430"
    ],
    "wof:name":"Igatka",
    "wof:placetype":"locality"
},
  "geometry": {"coordinates":[55.8753,56.7984],"type":"Point"}
}