{
  "type": "Feature",
  "properties": {
    "gn:admin1_code":"9.0",
    "gn:asciiname":"Kalinichenkovo",
    "gn:country_code":"RU",
    "gn:dem":178,
    "gn:feature_class":"P",
    "gn:feature_code":"PPL",
    "gn:name":"Kalinichenkovo",
    "gn:population":0,
    "gn:timezone":"Europe/Moscow",
    "iso:country":"RU",
    "name:rus_x_preferred":[
        "\u041a\u0430\u043b\u0438\u043d\u0438\u0447\u0435\u043d\u043a\u043e\u0432\u043e"
    ],
    "wof:name":"Kalinichenkovo",
    "wof:placetype":"locality"
},
  "geometry": {"coordinates":[38.9909,50.1869],"type":"Point"}
}