{
  "type": "Feature",
  "properties": {
    "gn:admin1_code":"41.0",
    "gn:asciiname":"Tsukanov",
    "gn:country_code":"RU",
    "gn:dem":212,
    "gn:feature_class":"P",
    "gn:feature_code":"PPL",
    "gn:name":"Tsukanov",
    "gn:population":0,
    "gn:timezone":"Europe/Moscow",
    "iso:country":"RU",
    "name:rus_x_preferred":[
        "\u0426\u0443\u043a\u0430\u043d\u043e\u0432"
    ],
    "wof:name":"Tsukanov",
    "wof:placetype":"locality"
},
  "geometry": {"coordinates":[34.6237,51.769],"type":"Point"}
}