{
  "type": "Feature",
  "properties": {
    "gn:admin1_code":"8",
    "gn:asciiname":"Kolokol'tsevo",
    "gn:country_code":"RU",
    "gn:dem":161,
    "gn:feature_class":"P",
    "gn:feature_code":"PPL",
    "gn:name":"Kolokol\u2019tsevo",
    "gn:population":0,
    "gn:timezone":"Asia/Yekaterinburg",
    "iso:country":"RU",
    "name:rus_x_preferred":[
        "\u041a\u043e\u043b\u043e\u043a\u043e\u043b\u044c\u0446\u0435\u0432\u043e"
    ],
    "name:und_x_variant":[
        "Kolokol\u2019tsevo"
    ],
    "wof:name":"Kolokol'tsevo",
    "wof:placetype":"locality"
},
  "geometry": {"coordinates":[55.6529,54.7681],"type":"Point"}
}