{
  "type": "Feature",
  "properties": {
    "gn:admin1_code":"65",
    "gn:asciiname":"Pokrovskaya Ploshchadka",
    "gn:country_code":"RU",
    "gn:dem":47,
    "gn:feature_class":"P",
    "gn:feature_code":"PPL",
    "gn:name":"Pokrovskaya Ploshchadka",
    "gn:population":0,
    "gn:timezone":"Europe/Samara",
    "iso:country":"RU",
    "name:rus_x_preferred":[
        "\u041f\u043e\u043a\u0440\u043e\u0432\u0441\u043a\u0430\u044f \u041f\u043b\u043e\u0449\u0430\u0434\u043a\u0430"
    ],
    "wof:name":"Pokrovskaya Ploshchadka",
    "wof:placetype":"locality"
},
  "geometry": {"coordinates":[49.5905,52.8898],"type":"Point"}
}