{
  "type": "Feature",
  "properties": {
    "gn:admin1_code":"60",
    "gn:asciiname":"Velebetskoye",
    "gn:country_code":"RU",
    "gn:dem":138,
    "gn:feature_class":"P",
    "gn:feature_code":"PPL",
    "gn:name":"Velebetskoye",
    "gn:population":0,
    "gn:timezone":"Europe/Moscow",
    "iso:country":"RU",
    "name:rus_x_preferred":[
        "\u0412\u0435\u043b\u0435\u0431\u0435\u0446\u043a\u043e\u0435"
    ],
    "wof:name":"Velebetskoye",
    "wof:placetype":"locality"
},
  "geometry": {"coordinates":[30.4455,56.3237],"type":"Point"}
}