{
  "type": "Feature",
  "properties": {
    "gn:admin1_code":"89",
    "gn:asciiname":"Mikhaylo-Arkhangel'skoye",
    "gn:country_code":"RU",
    "gn:dem":92,
    "gn:feature_class":"P",
    "gn:feature_code":"PPL",
    "gn:name":"Mikhaylo-Arkhangel\u2019skoye",
    "gn:population":0,
    "gn:timezone":"Asia/Vladivostok",
    "iso:country":"RU",
    "name:rus_x_preferred":[
        "\u041c\u0438\u0445\u0430\u0439\u043b\u043e-\u0410\u0440\u0445\u0430\u043d\u0433\u0435\u043b\u044c\u0441\u043a\u043e\u0435"
    ],
    "name:und_x_variant":[
        "Mikhaylo-Arhangel\u2019skoye",
        "Mikhaylo-Arkhangel\u2019skoye",
        "\u041c\u0438\u0445\u0430\u0439\u043b\u043e-\u0410\u0440\u0445\u0430\u043d\u0433\u0435\u043b\u044c\u0441\u043a\u043e\u0435"
    ],
    "wof:name":"Mikhaylo-Arkhangel'skoye",
    "wof:placetype":"locality"
},
  "geometry": {"coordinates":[132.59999999999999,48.33333],"type":"Point"}
}