{
  "type": "Feature",
  "properties": {
    "gn:admin1_code":"60",
    "gn:asciiname":"Brakulino",
    "gn:country_code":"RU",
    "gn:dem":167,
    "gn:feature_class":"P",
    "gn:feature_code":"PPL",
    "gn:name":"Brakulino",
    "gn:population":0,
    "gn:timezone":"Europe/Moscow",
    "iso:country":"RU",
    "name:rus_x_preferred":[
        "\u0411\u0440\u0430\u043a\u0443\u043b\u0438\u043d\u043e"
    ],
    "name:und_x_variant":[
        "\u0411\u0440\u0430\u043a\u0443\u043b\u0438\u043d\u043e"
    ],
    "wof:name":"Brakulino",
    "wof:placetype":"locality"
},
  "geometry": {"coordinates":[30.1568,56.5041],"type":"Point"}
}