{
  "type": "Feature",
  "properties": {
    "gn:admin1_code":"47.0",
    "gn:asciiname":"Gorodishche",
    "gn:country_code":"RU",
    "gn:dem":154,
    "gn:feature_class":"P",
    "gn:feature_code":"PPL",
    "gn:name":"Gorodishche",
    "gn:population":0,
    "gn:timezone":"Europe/Moscow",
    "iso:country":"RU",
    "name:ceb_x_preferred":[
        "Gorodishche"
    ],
    "name:tgl_x_preferred":[
        "Gorodishche"
    ],
    "name:zho_x_preferred":[
        "\u6208\u7f85\u5b63\u8b1d"
    ],
    "wof:name":"Gorodishche",
    "wof:placetype":"locality"
},
  "geometry": {"coordinates":[37.43357,55.53477],"type":"Point"}
}