{
  "type": "Feature",
  "properties": {
    "gn:admin1_code":"93",
    "gn:asciiname":"Cheremkhovo",
    "gn:country_code":"RU",
    "gn:dem":717,
    "gn:feature_class":"P",
    "gn:feature_code":"PPL",
    "gn:name":"Cheremkhovo",
    "gn:population":0,
    "gn:timezone":"Asia/Chita",
    "iso:country":"RU",
    "name:ara_x_preferred":[
        "\u062a\u0634\u064a\u0631\u064a\u0645\u062e\u0648\u0641\u0648"
    ],
    "name:azb_x_preferred":[
        "\u0686\u0627\u0631\u0645\u06a9\u0647\u0648\u0648\u0648"
    ],
    "name:aze_x_preferred":[
        "\u00c7eremxovo"
    ],
    "name:bel_x_preferred":[
        "\u0427\u0430\u0440\u0430\u043c\u0445\u043e\u0432\u0430"
    ],
    "name:cat_x_preferred":[
        "Txeremkhovo"
    ],
    "name:ceb_x_preferred":[
        "Cheremkhovo"
    ],
    "name:ces_x_preferred":[
        "\u010ceremchovo"
    ],
    "name:che_x_preferred":[
        "\u0427\u0435\u0440\u0435\u043c\u0445\u043e\u0432\u043e"
    ],
    "name:dan_x_preferred":[
        "Tjeremkhovo"
    ],
    "name:deu_x_preferred":[
        "Tscheremchowo"
    ],
    "name:eng_x_preferred":[
        "Cheremkhovo"
    ],
    "name:epo_x_preferred":[
        "\u0108erem\u0125ovo"
    ],
    "name:est_x_preferred":[
        "T\u0161eremhovo"
    ],
    "name:fas_x_preferred":[
        "\u0686\u0631\u0645\u062e\u0648\u0641\u0648"
    ],
    "name:fin_x_preferred":[
        "T\u0161eremhovo"
    ],
    "name:fra_x_preferred":[
        "Tcheremkhovo"
    ],
    "name:hsb_x_preferred":[
        "\u010cerjemchowo"
    ],
    "name:hun_x_preferred":[
        "Cseremhovo"
    ],
    "name:ita_x_preferred":[
        "\u010ceremchovo"
    ],
    "name:kor_x_preferred":[
        "\uccb4\ub818\ud638\ubcf4"
    ],
    "name:lit_x_preferred":[
        "\u010ceremchovas"
    ],
    "name:nld_x_preferred":[
        "Tsjeremchovo"
    ],
    "name:nno_x_preferred":[
        "Tsjeremkhovo"
    ],
    "name:nor_x_preferred":[
        "Tsjeremkhovo"
    ],
    "name:pnb_x_preferred":[
        "\u0686\u06cc\u0631\u06cc\u0645\u062e\u0648\u0641\u0648"
    ],
    "name:pol_x_preferred":[
        "Czeremchowo"
    ],
    "name:ron_x_preferred":[
        "Ceremhovo"
    ],
    "name:rus_x_preferred":[
        "\u0427\u0435\u0440\u0435\u043c\u0445\u043e\u0432\u043e"
    ],
    "name:spa_x_preferred":[
        "Cheremjovo"
    ],
    "name:srp_x_preferred":[
        "\u0427\u0435\u0440\u0435\u043c\u0445\u043e\u0432\u043e"
    ],
    "name:tat_x_preferred":[
        "\u0427\u0435\u0440\u0435\u043c\u0445\u043e\u0432\u043e"
    ],
    "name:tgk_x_preferred":[
        "\u0427\u0435\u0440\u0435\u043c\u0445\u043e\u0432\u043e"
    ],
    "name:tgl_x_preferred":[
        "Cheremkhovo"
    ],
    "name:tur_x_preferred":[
        "\u00c7eremhovo"
    ],
    "name:ukr_x_preferred":[
        "\u0427\u0435\u0440\u0435\u043c\u0445\u043e\u0432\u043e"
    ],
    "name:vep_x_preferred":[
        "\u010cer\u00f6mhovo"
    ],
    "name:vie_x_preferred":[
        "Cheremkhovo"
    ],
    "name:war_x_preferred":[
        "Cheremkhovo"
    ],
    "name:zho_x_preferred":[
        "\u5207\u5217\u59c6\u970d\u6c83"
    ],
    "wof:name":"Cheremkhovo",
    "wof:placetype":"locality"
},
  "geometry": {"coordinates":[112.72499000000001,51.45885],"type":"Point"}
}