{
  "type": "Feature",
  "properties": {
    "gn:admin1_code":"90",
    "gn:asciiname":"Khutarikha",
    "gn:country_code":"RU",
    "gn:dem":227,
    "gn:feature_class":"P",
    "gn:feature_code":"PPL",
    "gn:name":"Khutarikha",
    "gn:population":0,
    "gn:timezone":"Asia/Yekaterinburg",
    "iso:country":"RU",
    "name:rus_x_preferred":[
        "\u0425\u0443\u0442\u0430\u0440\u0438\u0445\u0430"
    ],
    "name:und_x_variant":[
        "\u0425\u0443\u0442\u0430\u0440\u0438\u0445\u0430"
    ],
    "wof:name":"Khutarikha",
    "wof:placetype":"locality"
},
  "geometry": {"coordinates":[57.03333000000001,57.85],"type":"Point"}
}