{
  "type": "Feature",
  "properties": {
    "gn:admin1_code":"28",
    "gn:asciiname":"Lubosalma",
    "gn:country_code":"RU",
    "gn:dem":167,
    "gn:feature_class":"P",
    "gn:feature_code":"PPL",
    "gn:name":"Lubosalma",
    "gn:population":0,
    "gn:timezone":"Europe/Moscow",
    "iso:country":"RU",
    "name:eng_x_preferred":[
        "Lubosalma"
    ],
    "name:fin_x_preferred":[
        "Lupasalmi"
    ],
    "name:nor_x_preferred":[
        "Lubosalma"
    ],
    "name:rus_x_preferred":[
        "\u041b\u0443\u0431\u043e\u0441\u0430\u043b\u043c\u0430"
    ],
    "name:und_x_variant":[
        "Luba-Salma",
        "\u041b\u0443\u0431\u043e\u0441\u0430\u043b\u043c\u0430",
        "Lubosalma"
    ],
    "wof:name":"Lubosalma",
    "wof:placetype":"locality"
},
  "geometry": {"coordinates":[31.75906,63.05689],"type":"Point"}
}