{
  "type": "Feature",
  "properties": {
    "gn:admin1_code":"52",
    "gn:asciiname":"Kozlovo",
    "gn:country_code":"RU",
    "gn:dem":46,
    "gn:feature_class":"P",
    "gn:feature_code":"PPL",
    "gn:name":"Kozlovo",
    "gn:population":0,
    "gn:timezone":"Europe/Moscow",
    "iso:country":"RU",
    "name:rus_x_preferred":[
        "\u041a\u043e\u0437\u043b\u043e\u0432\u043e"
    ],
    "name:und_x_variant":[
        "\u041a\u043e\u0437\u043b\u043e\u0432\u043e"
    ],
    "wof:name":"Kozlovo",
    "wof:placetype":"locality"
},
  "geometry": {"coordinates":[31.35928,57.66208],"type":"Point"}
}