{
  "type": "Feature",
  "properties": {
    "gn:admin1_code":"59",
    "gn:asciiname":"Sofiyevka",
    "gn:cc2":"RU",
    "gn:country_code":"RU",
    "gn:dem":98,
    "gn:feature_class":"P",
    "gn:feature_code":"PPL",
    "gn:name":"Sofiyevka",
    "gn:population":0,
    "gn:timezone":"Asia/Vladivostok",
    "iso:country":"RU",
    "name:rus_x_preferred":[
        "\u0421\u043e\u0444\u0438\u0435\u0432\u043a\u0430"
    ],
    "name:und_x_variant":[
        "Sofugefuka",
        "Sof\u2019yevka",
        "Sofiyevka"
    ],
    "wof:name":"Sofiyevka",
    "wof:placetype":"locality"
},
  "geometry": {"coordinates":[134.19999999999999,46.05],"type":"Point"}
}