{
  "type": "Feature",
  "properties": {
    "gn:admin1_code":"61",
    "gn:asciiname":"Mityakinskaya",
    "gn:country_code":"RU",
    "gn:dem":37,
    "gn:feature_class":"P",
    "gn:feature_code":"PPL",
    "gn:name":"Mityakinskaya",
    "gn:population":0,
    "gn:timezone":"Europe/Moscow",
    "iso:country":"RU",
    "name:eng_x_preferred":[
        "Mityakinskaya"
    ],
    "name:nor_x_preferred":[
        "Mitjakinskaja"
    ],
    "name:rus_x_preferred":[
        "\u041c\u0438\u0442\u044f\u043a\u0438\u043d\u0441\u043a\u0430\u044f"
    ],
    "name:und_x_variant":[
        "\u041c\u0438\u0442\u044f\u043a\u0438\u043d\u0441\u043a\u0430\u044f",
        "Mityakinskaya"
    ],
    "wof:name":"Mityakinskaya",
    "wof:placetype":"locality"
},
  "geometry": {"coordinates":[39.7831,48.6104],"type":"Point"}
}