{
  "type": "Feature",
  "properties": {
    "gn:admin1_code":"4.0",
    "gn:asciiname":"Karasuk",
    "gn:country_code":"RU",
    "gn:dem":193,
    "gn:feature_class":"P",
    "gn:feature_code":"PPL",
    "gn:name":"Karasuk",
    "gn:population":0,
    "gn:timezone":"Asia/Barnaul",
    "iso:country":"RU",
    "name:bel_x_preferred":[
        "\u041a\u0430\u0440\u0430\u0441\u0443\u043a"
    ],
    "name:ben_x_preferred":[
        "\u0995\u09be\u09b0\u09be\u09b8\u09c1\u0995"
    ],
    "name:ceb_x_preferred":[
        "Karasuk"
    ],
    "name:deu_x_preferred":[
        "Karassuk"
    ],
    "name:ell_x_preferred":[
        "\u039a\u03b1\u03c1\u03b1\u03c3\u03bf\u03cd\u03ba"
    ],
    "name:fra_x_preferred":[
        "Karassouk"
    ],
    "name:heb_x_preferred":[
        "\u05e7\u05d0\u05e8\u05d0\u05e1\u05d5\u05e7"
    ],
    "name:hin_x_preferred":[
        "\u0915\u0930\u093e\u0938\u0941\u0915"
    ],
    "name:ind_x_preferred":[
        "Karasuk"
    ],
    "name:ita_x_preferred":[
        "Karasuk"
    ],
    "name:jpn_x_preferred":[
        "\u30ab\u30e9\u30b9\u30af"
    ],
    "name:kor_x_preferred":[
        "\uac00\ub77c\uc219"
    ],
    "name:nor_x_preferred":[
        "Karasuk"
    ],
    "name:rus_x_preferred":[
        "\u041a\u0430\u0440\u0430\u0441\u0443\u043a"
    ],
    "name:spa_x_preferred":[
        "Karasuk"
    ],
    "name:swe_x_preferred":[
        "Karasuk"
    ],
    "name:urd_x_preferred":[
        "\u06a9\u0627\u0631\u0627\u0633\u06a9"
    ],
    "name:vie_x_preferred":[
        "Karasuk"
    ],
    "wof:name":"Karasuk",
    "wof:placetype":"locality"
},
  "geometry": {"coordinates":[85.59004,52.38548],"type":"Point"}
}