{
  "type": "Feature",
  "properties": {
    "gn:admin1_code":"69",
    "gn:asciiname":"Staryye Vereshkovichi",
    "gn:country_code":"RU",
    "gn:dem":224,
    "gn:feature_class":"P",
    "gn:feature_code":"PPL",
    "gn:name":"Staryye Vereshkovichi",
    "gn:population":0,
    "gn:timezone":"Europe/Moscow",
    "iso:country":"RU",
    "name:rus_x_preferred":[
        "\u0421\u0442\u0430\u0440\u044b\u0435 \u0412\u0435\u0440\u0435\u0448\u043a\u043e\u0432\u0438\u0447\u0438"
    ],
    "wof:name":"Staryye Vereshkovichi",
    "wof:placetype":"locality"
},
  "geometry": {"coordinates":[32.4253,55.4758],"type":"Point"}
}