{
  "type": "Feature",
  "properties": {
    "gn:admin1_code":"16.0",
    "gn:asciiname":"Chernorechenskiy",
    "gn:country_code":"RU",
    "gn:dem":156,
    "gn:feature_class":"P",
    "gn:feature_code":"PPL",
    "gn:name":"Chernorechenskiy",
    "gn:population":0,
    "gn:timezone":"Europe/Moscow",
    "iso:country":"RU",
    "name:rus_x_preferred":[
        "\u0427\u0435\u0440\u043d\u043e\u0440\u0435\u0447\u0435\u043d\u0441\u043a\u0438\u0439"
    ],
    "name:und_x_variant":[
        "\u0427\u0435\u0440\u043d\u043e\u0440\u0435\u0447\u0435\u043d\u0441\u043a\u0438\u0439"
    ],
    "wof:name":"Chernorechenskiy",
    "wof:placetype":"locality"
},
  "geometry": {"coordinates":[47.03333,55.31667],"type":"Point"}
}