{
  "type": "Feature",
  "properties": {
    "gn:admin1_code":"23",
    "gn:asciiname":"Demidovka",
    "gn:country_code":"RU",
    "gn:dem":109,
    "gn:feature_class":"P",
    "gn:feature_code":"PPL",
    "gn:name":"Demidovka",
    "gn:population":0,
    "gn:timezone":"Europe/Kaliningrad",
    "iso:country":"RU",
    "name:che_x_preferred":[
        "\u0414\u0435\u043c\u0438\u0434\u043e\u0432\u043a\u0430"
    ],
    "name:rus_x_preferred":[
        "\u0414\u0435\u043c\u0438\u0434\u043e\u0432\u043a\u0430"
    ],
    "wof:name":"Demidovka",
    "wof:placetype":"locality"
},
  "geometry": {"coordinates":[21.79273,54.39227],"type":"Point"}
}