{
  "type": "Feature",
  "properties": {
    "gn:admin1_code":"32",
    "gn:asciiname":"Lyankh-Uriy-Pugol",
    "gn:country_code":"RU",
    "gn:dem":52,
    "gn:feature_class":"P",
    "gn:feature_code":"PPL",
    "gn:name":"Lyankh-Uriy-Pugol",
    "gn:population":0,
    "gn:timezone":"Asia/Yekaterinburg",
    "iso:country":"RU",
    "name:rus_x_preferred":[
        "\u041b\u044f\u043d\u0445-\u0423\u0440\u0438\u0439-\u041f\u0443\u0433\u043e\u043b"
    ],
    "name:und_x_variant":[
        "\u041b\u044f\u043d\u0445-\u0423\u0440\u0438\u0439-\u041f\u0443\u0433\u043e\u043b"
    ],
    "wof:name":"Lyankh-Uriy-Pugol",
    "wof:placetype":"locality"
},
  "geometry": {"coordinates":[74.41667,61.83333],"type":"Point"}
}