{
  "type": "Feature",
  "properties": {
    "gn:admin1_code":"61.0",
    "gn:asciiname":"Chernetsov",
    "gn:country_code":"RU",
    "gn:dem":72,
    "gn:feature_class":"P",
    "gn:feature_code":"PPL",
    "gn:name":"Chernetsov",
    "gn:population":0,
    "gn:timezone":"Europe/Moscow",
    "iso:country":"RU",
    "name:eng_x_preferred":[
        "Chernetsovka"
    ],
    "name:nor_x_preferred":[
        "Tsjernetsov"
    ],
    "name:rus_x_preferred":[
        "\u0427\u0435\u0440\u043d\u0435\u0446\u043e\u0432"
    ],
    "name:und_x_variant":[
        "Chernitsovka",
        "\u0427\u0435\u0440\u043d\u0435\u0446\u043e\u0432",
        "Chernetsov",
        "Chernetsovka"
    ],
    "wof:name":"Chernetsov",
    "wof:placetype":"locality"
},
  "geometry": {"coordinates":[40.47381,48.11114],"type":"Point"}
}