{
  "type": "Feature",
  "properties": {
    "gn:admin1_code":"8",
    "gn:asciiname":"Kalu-Ayry",
    "gn:country_code":"RU",
    "gn:dem":492,
    "gn:feature_class":"P",
    "gn:feature_code":"PPL",
    "gn:name":"Kalu-Ayry",
    "gn:population":0,
    "gn:timezone":"Asia/Yekaterinburg",
    "iso:country":"RU",
    "name:eng_x_preferred":[
        "Kaluayry"
    ],
    "name:nor_x_preferred":[
        "Kalu-Ajry"
    ],
    "name:rus_x_preferred":[
        "\u041a\u0430\u043b\u0443-\u0410\u0439\u0440\u044b"
    ],
    "name:und_x_variant":[
        "Kuly-Ayry",
        "Kalu-Ayry",
        "\u041a\u0430\u043b\u0443-\u0410\u0439\u0440\u044b"
    ],
    "wof:name":"Kalu-Ayry",
    "wof:placetype":"locality"
},
  "geometry": {"coordinates":[56.95268000000001,53.53198],"type":"Point"}
}