{
  "type": "Feature",
  "properties": {
    "gn:admin1_code":"71",
    "gn:asciiname":"Golyakova",
    "gn:country_code":"RU",
    "gn:dem":74,
    "gn:feature_class":"P",
    "gn:feature_code":"PPL",
    "gn:name":"Golyakova",
    "gn:population":0,
    "gn:timezone":"Asia/Yekaterinburg",
    "iso:country":"RU",
    "name:eng_x_preferred":[
        "Golyakova"
    ],
    "name:nor_x_preferred":[
        "Goljakova"
    ],
    "name:rus_x_preferred":[
        "\u0413\u043e\u043b\u044f\u043a\u043e\u0432\u0430"
    ],
    "name:und_x_variant":[
        "\u0413\u043e\u043b\u044f\u043a\u043e\u0432\u0430",
        "Golyakova"
    ],
    "wof:name":"Golyakova",
    "wof:placetype":"locality"
},
  "geometry": {"coordinates":[64.41374,57.44538000000001],"type":"Point"}
}