{
  "type": "Feature",
  "properties": {
    "gn:admin1_code":"8",
    "gn:asciiname":"Yarmukhametova",
    "gn:cc2":"RU",
    "gn:country_code":"RU",
    "gn:dem":306,
    "gn:feature_class":"P",
    "gn:feature_code":"PPL",
    "gn:name":"Yarmukhametova",
    "gn:population":0,
    "gn:timezone":"Asia/Yekaterinburg",
    "iso:country":"RU",
    "name:und_x_variant":[
        "Yarmukhametovo",
        "Yarmukhametova"
    ],
    "wof:name":"Yarmukhametova",
    "wof:placetype":"locality"
},
  "geometry": {"coordinates":[57.38333000000001,53.05],"type":"Point"}
}