{
  "type": "Feature",
  "properties": {
    "gn:admin1_code":"76",
    "gn:asciiname":"Bol'shaya Khatunka",
    "gn:country_code":"RU",
    "gn:dem":167,
    "gn:feature_class":"P",
    "gn:feature_code":"PPL",
    "gn:name":"Bol\u2019shaya Khatunka",
    "gn:population":0,
    "gn:timezone":"Europe/Moscow",
    "iso:country":"RU",
    "name:rus_x_preferred":[
        "\u0411\u043e\u043b\u044c\u0448\u0430\u044f \u0425\u0430\u0442\u0443\u043d\u043a\u0430"
    ],
    "name:und_x_variant":[
        "Bol\u2019shaya Khatunka",
        "Khatunka"
    ],
    "wof:name":"Bol'shaya Khatunka",
    "wof:placetype":"locality"
},
  "geometry": {"coordinates":[37.33311,54.01569],"type":"Point"}
}