{
  "type": "Feature",
  "properties": {
    "gn:admin1_code":"69.0",
    "gn:asciiname":"Bobrovo Pervoye",
    "gn:country_code":"RU",
    "gn:dem":241,
    "gn:feature_class":"P",
    "gn:feature_code":"PPL",
    "gn:name":"Bobrovo Pervoye",
    "gn:population":0,
    "gn:timezone":"Europe/Moscow",
    "iso:country":"RU",
    "name:rus_x_preferred":[
        "\u0411\u043e\u0431\u0440\u043e\u0432\u043e \u041f\u0435\u0440\u0432\u043e\u0435"
    ],
    "name:und_x_variant":[
        "\u0411\u043e\u0431\u0440\u043e\u0432\u043e \u041f\u0435\u0440\u0432\u043e\u0435"
    ],
    "wof:name":"Bobrovo Pervoye",
    "wof:placetype":"locality"
},
  "geometry": {"coordinates":[33.01667,54.76667],"type":"Point"}
}