{
  "type": "Feature",
  "properties": {
    "gn:admin1_code":"55",
    "gn:asciiname":"Novokul'sharilovo",
    "gn:country_code":"RU",
    "gn:dem":108,
    "gn:feature_class":"P",
    "gn:feature_code":"PPL",
    "gn:name":"Novokul\u2019sharilovo",
    "gn:population":0,
    "gn:timezone":"Asia/Yekaterinburg",
    "iso:country":"RU",
    "name:rus_x_preferred":[
        "\u041d\u043e\u0432\u043e\u043a\u0443\u043b\u044c\u0448\u0430\u0440\u0438\u043b\u043e\u0432\u043e"
    ],
    "name:und_x_variant":[
        "Novokul\u2019sharilovo",
        "\u041d\u043e\u0432\u043e\u043a\u0443\u043b\u044c\u0448\u0430\u0440\u0438\u043b\u043e\u0432\u043e"
    ],
    "wof:name":"Novokul'sharilovo",
    "wof:placetype":"locality"
},
  "geometry": {"coordinates":[52.9429,53.4438],"type":"Point"}
}