{
  "type": "Feature",
  "properties": {
    "gn:admin1_code":"83",
    "gn:asciiname":"Ileykino",
    "gn:country_code":"RU",
    "gn:dem":141,
    "gn:feature_class":"P",
    "gn:feature_code":"PPL",
    "gn:name":"Ileykino",
    "gn:population":0,
    "gn:timezone":"Europe/Moscow",
    "iso:country":"RU",
    "name:rus_x_preferred":[
        "\u0418\u043b\u0435\u0439\u043a\u0438\u043d\u043e"
    ],
    "name:und_x_variant":[
        "\u0418\u043b\u0435\u0439\u043a\u0438\u043d\u043e"
    ],
    "wof:name":"Ileykino",
    "wof:placetype":"locality"
},
  "geometry": {"coordinates":[38.85789000000001,56.07359],"type":"Point"}
}