{
  "type": "Feature",
  "properties": {
    "gn:admin1_code":"62",
    "gn:asciiname":"Samodurovka",
    "gn:country_code":"RU",
    "gn:dem":93,
    "gn:feature_class":"P",
    "gn:feature_code":"PPL",
    "gn:name":"Samodurovka",
    "gn:population":0,
    "gn:timezone":"Europe/Moscow",
    "iso:country":"RU",
    "name:bak_x_preferred":[
        "\u0421\u0430\u043c\u043e\u0434\u0443\u0440\u043e\u0432\u043a\u0430"
    ],
    "name:che_x_preferred":[
        "\u0421\u0430\u043c\u043e\u0434\u0443\u0440\u043e\u0432\u043a\u0430"
    ],
    "name:hye_x_preferred":[
        "\u054d\u0561\u0574\u0578\u0564\u0578\u0582\u0580\u0578\u057e\u056f\u0561"
    ],
    "name:kat_x_preferred":[
        "\u10e1\u10d0\u10db\u10dd\u10d3\u10e3\u10e0\u10dd\u10d5\u10d9\u10d0"
    ],
    "name:kaz_x_preferred":[
        "\u0421\u0430\u043c\u043e\u0434\u0443\u0440\u043e\u0432\u043a\u0430"
    ],
    "name:kir_x_preferred":[
        "\u0421\u0430\u043c\u043e\u0434\u0443\u0440\u043e\u0432\u043a\u0430"
    ],
    "name:rus_x_preferred":[
        "\u0421\u0430\u043c\u043e\u0434\u0443\u0440\u043e\u0432\u043a\u0430"
    ],
    "name:tat_x_preferred":[
        "\u0421\u0430\u043c\u043e\u0434\u0443\u0440\u043e\u0432\u043a\u0430"
    ],
    "name:ukr_x_preferred":[
        "\u0421\u0430\u043c\u043e\u0434\u0443\u0440\u043e\u0432\u043a\u0430"
    ],
    "name:und_x_variant":[
        "\u0421\u0430\u043c\u043e\u0434\u0443\u0440\u043e\u0432\u043a\u0430"
    ],
    "wof:name":"Samodurovka",
    "wof:placetype":"locality"
},
  "geometry": {"coordinates":[40.91667,54.18333000000001],"type":"Point"}
}