{
  "type": "Feature",
  "properties": {
    "gn:admin1_code":"62",
    "gn:asciiname":"Samodurovka",
    "gn:country_code":"RU",
    "gn:dem":93,
    "gn:feature_class":"P",
    "gn:feature_code":"PPL",
    "gn:name":"Samodurovka",
    "gn:population":0,
    "gn:timezone":"Europe/Moscow",
    "iso:country":"RU",
    "name:rus_x_preferred":[
        "\u0421\u0430\u043c\u043e\u0434\u0443\u0440\u043e\u0432\u043a\u0430"
    ],
    "name:und_x_variant":[
        "\u0421\u0430\u043c\u043e\u0434\u0443\u0440\u043e\u0432\u043a\u0430"
    ],
    "wof:name":"Samodurovka",
    "wof:placetype":"locality"
},
  "geometry": {"coordinates":[40.91667,54.18333000000001],"type":"Point"}
}