{
  "type": "Feature",
  "properties": {
    "gn:admin1_code":"41",
    "gn:asciiname":"Lebedin",
    "gn:country_code":"RU",
    "gn:dem":166,
    "gn:feature_class":"P",
    "gn:feature_code":"PPL",
    "gn:name":"Lebedin",
    "gn:population":0,
    "gn:timezone":"Europe/Moscow",
    "iso:country":"RU",
    "name:rus_x_preferred":[
        "\u041b\u0435\u0431\u0435\u0434\u0438\u043d"
    ],
    "wof:name":"Lebedin",
    "wof:placetype":"locality"
},
  "geometry": {"coordinates":[35.96667,51.54083],"type":"Point"}
}