{
  "type": "Feature",
  "properties": {
    "gn:admin1_code":"29",
    "gn:asciiname":"Yashkinskiy",
    "gn:country_code":"RU",
    "gn:dem":247,
    "gn:feature_class":"P",
    "gn:feature_code":"PPL",
    "gn:name":"Yashkinskiy",
    "gn:population":0,
    "gn:timezone":"Asia/Novokuznetsk",
    "iso:country":"RU",
    "name:rus_x_preferred":[
        "\u042f\u0448\u043a\u0438\u043d\u0441\u043a\u0438\u0439"
    ],
    "wof:name":"Yashkinskiy",
    "wof:placetype":"locality"
},
  "geometry": {"coordinates":[85.4059,55.8733],"type":"Point"}
}