{
  "type": "Feature",
  "properties": {
    "gn:admin1_code":"4",
    "gn:asciiname":"Kizikha",
    "gn:country_code":"RU",
    "gn:dem":216,
    "gn:feature_class":"P",
    "gn:feature_code":"PPL",
    "gn:name":"Kizikha",
    "gn:population":0,
    "gn:timezone":"Asia/Barnaul",
    "iso:country":"RU",
    "name:rus_x_preferred":[
        "\u041a\u0438\u0437\u0438\u0445\u0430"
    ],
    "wof:name":"Kizikha",
    "wof:placetype":"locality"
},
  "geometry": {"coordinates":[81.66667,51.66667],"type":"Point"}
}