{
  "type": "Feature",
  "properties": {
    "gn:admin1_code":"53",
    "gn:asciiname":"Bogatikha",
    "gn:country_code":"RU",
    "gn:dem":110,
    "gn:feature_class":"P",
    "gn:feature_code":"PPL",
    "gn:name":"Bogatikha",
    "gn:population":0,
    "gn:timezone":"Asia/Novosibirsk",
    "iso:country":"RU",
    "name:eng_x_preferred":[
        "Bogatikha"
    ],
    "name:nor_x_preferred":[
        "Bogatikha"
    ],
    "name:rus_x_preferred":[
        "\u0411\u043e\u0433\u0430\u0442\u0438\u0445\u0430"
    ],
    "name:und_x_variant":[
        "Bogatskaya"
    ],
    "wof:name":"Bogatikha",
    "wof:placetype":"locality"
},
  "geometry": {"coordinates":[77.82534,54.7116],"type":"Point"}
}