{
  "type": "Feature",
  "properties": {
    "gn:admin1_code":"85",
    "gn:asciiname":"Timoshkino",
    "gn:country_code":"RU",
    "gn:dem":162,
    "gn:feature_class":"P",
    "gn:feature_code":"PPL",
    "gn:name":"Timoshkino",
    "gn:population":0,
    "gn:timezone":"Europe/Moscow",
    "iso:country":"RU",
    "name:rus_x_preferred":[
        "\u0422\u0438\u043c\u043e\u0448\u043a\u0438\u043d\u043e"
    ],
    "wof:name":"Timoshkino",
    "wof:placetype":"locality"
},
  "geometry": {"coordinates":[39.5878,60.5165],"type":"Point"}
}