{
  "type": "Feature",
  "properties": {
    "gn:admin1_code":"69",
    "gn:asciiname":"Budishche",
    "gn:country_code":"RU",
    "gn:dem":179,
    "gn:feature_class":"P",
    "gn:feature_code":"PPL",
    "gn:name":"Budishche",
    "gn:population":0,
    "gn:timezone":"Europe/Moscow",
    "iso:country":"RU",
    "name:rus_x_preferred":[
        "\u0411\u0443\u0434\u0438\u0449\u0435"
    ],
    "name:und_x_variant":[
        "\u0411\u0443\u0434\u0438\u0449\u0435"
    ],
    "wof:name":"Budishche",
    "wof:placetype":"locality"
},
  "geometry": {"coordinates":[32.70556,53.51194],"type":"Point"}
}