{
  "type": "Feature",
  "properties": {
    "gn:admin1_code":"38.0",
    "gn:asciiname":"Al'tmets",
    "gn:country_code":"RU",
    "gn:dem":113,
    "gn:feature_class":"P",
    "gn:feature_code":"PPL",
    "gn:name":"Al\u2019tmets",
    "gn:population":0,
    "gn:timezone":"Europe/Moscow",
    "iso:country":"RU",
    "name:nor_x_preferred":[
        "Altmets"
    ],
    "name:rus_x_preferred":[
        "\u0410\u043b\u044c\u0442\u043c\u0435\u0446"
    ],
    "name:und_x_variant":[
        "Al\u2019tmets"
    ],
    "wof:name":"Al'tmets",
    "wof:placetype":"locality"
},
  "geometry": {"coordinates":[39.67592,43.72231],"type":"Point"}
}