{
  "type": "Feature",
  "properties": {
    "gn:admin1_code":"85",
    "gn:asciiname":"Nesterikha",
    "gn:country_code":"RU",
    "gn:dem":157,
    "gn:feature_class":"P",
    "gn:feature_code":"PPL",
    "gn:name":"Nesterikha",
    "gn:population":0,
    "gn:timezone":"Europe/Moscow",
    "iso:country":"RU",
    "name:rus_x_preferred":[
        "\u041d\u0435\u0441\u0442\u0435\u0440\u0438\u0445\u0430"
    ],
    "wof:name":"Nesterikha",
    "wof:placetype":"locality"
},
  "geometry": {"coordinates":[40.97465,60.01707],"type":"Point"}
}