{
  "type": "Feature",
  "properties": {
    "gn:admin1_code":"72.0",
    "gn:asciiname":"Chetvertaya Alekseyevka",
    "gn:country_code":"RU",
    "gn:dem":168,
    "gn:feature_class":"P",
    "gn:feature_code":"PPL",
    "gn:name":"Chetv\u00ebrtaya Alekseyevka",
    "gn:population":0,
    "gn:timezone":"Europe/Moscow",
    "iso:country":"RU",
    "name:rus_x_preferred":[
        "\u0427\u0435\u0442\u0432\u0451\u0440\u0442\u0430\u044f \u0410\u043b\u0435\u043a\u0441\u0435\u0435\u0432\u043a\u0430"
    ],
    "name:und_x_variant":[
        "Chetv\u00ebrtaya Alekseyevka",
        "\u0427\u0435\u0442\u0432\u0451\u0440\u0442\u0430\u044f \u0410\u043b\u0435\u043a\u0441\u0435\u0435\u0432\u043a\u0430"
    ],
    "wof:name":"Chetvertaya Alekseyevka",
    "wof:placetype":"locality"
},
  "geometry": {"coordinates":[41.15,52.45],"type":"Point"}
}