{
  "type": "Feature",
  "properties": {
    "gn:admin1_code":"52",
    "gn:asciiname":"Staro",
    "gn:country_code":"RU",
    "gn:dem":89,
    "gn:feature_class":"P",
    "gn:feature_code":"PPL",
    "gn:name":"Staro",
    "gn:population":0,
    "gn:timezone":"Europe/Moscow",
    "iso:country":"RU",
    "name:rus_x_preferred":[
        "\u0421\u0442\u0430\u0440\u043e"
    ],
    "name:und_x_variant":[
        "Staroye",
        "Staraya",
        "Staro",
        "\u0421\u0442\u0430\u0440\u043e"
    ],
    "wof:name":"Staro",
    "wof:placetype":"locality"
},
  "geometry": {"coordinates":[30.77143,57.75686],"type":"Point"}
}