{
  "type": "Feature",
  "properties": {
    "gn:admin1_code":"70.0",
    "gn:asciiname":"Bratskiy",
    "gn:country_code":"RU",
    "gn:dem":207,
    "gn:feature_class":"P",
    "gn:feature_code":"PPL",
    "gn:name":"Bratskiy",
    "gn:population":0,
    "gn:timezone":"Europe/Moscow",
    "iso:country":"RU",
    "name:rus_x_preferred":[
        "\u0411\u0440\u0430\u0442\u0441\u043a\u0438\u0439"
    ],
    "wof:name":"Bratskiy",
    "wof:placetype":"locality"
},
  "geometry": {"coordinates":[44.25889,44.11611],"type":"Point"}
}