{
  "type": "Feature",
  "properties": {
    "gn:admin1_code":"90",
    "gn:asciiname":"Zotino",
    "gn:country_code":"RU",
    "gn:dem":197,
    "gn:feature_class":"P",
    "gn:feature_code":"PPL",
    "gn:name":"Zotino",
    "gn:population":0,
    "gn:timezone":"Asia/Yekaterinburg",
    "iso:country":"RU",
    "name:eng_x_preferred":[
        "Zotino"
    ],
    "name:nor_x_preferred":[
        "Zotino"
    ],
    "name:rus_x_preferred":[
        "\u0417\u043e\u0442\u0438\u043d\u043e"
    ],
    "wof:name":"Zotino",
    "wof:placetype":"locality"
},
  "geometry": {"coordinates":[53.868,58.4151],"type":"Point"}
}