{
  "type": "Feature",
  "properties": {
    "gn:admin1_code":"9",
    "gn:asciiname":"Novyy Khutor",
    "gn:country_code":"RU",
    "gn:dem":142,
    "gn:feature_class":"P",
    "gn:feature_code":"PPL",
    "gn:name":"Novyy Khutor",
    "gn:population":0,
    "gn:timezone":"Europe/Moscow",
    "iso:country":"RU",
    "name:rus_x_preferred":[
        "\u041d\u043e\u0432\u044b\u0439 \u0425\u0443\u0442\u043e\u0440"
    ],
    "wof:name":"Novyy Khutor",
    "wof:placetype":"locality"
},
  "geometry": {"coordinates":[37.55722,50.37806],"type":"Point"}
}