{
  "type": "Feature",
  "properties": {
    "gn:admin1_code":"54",
    "gn:asciiname":"Roshchinskiy",
    "gn:country_code":"RU",
    "gn:dem":108,
    "gn:feature_class":"P",
    "gn:feature_code":"PPL",
    "gn:name":"Roshchinskiy",
    "gn:population":0,
    "gn:timezone":"Asia/Omsk",
    "iso:country":"RU",
    "name:nor_x_preferred":[
        "Rosjtsjinskij"
    ],
    "name:rus_x_preferred":[
        "\u0420\u043e\u0449\u0438\u043d\u0441\u043a\u0438\u0439"
    ],
    "name:und_x_variant":[
        "\u0420\u043e\u0449\u0438\u043d\u0441\u043a\u0438\u0439",
        "Roshchinskiy"
    ],
    "wof:name":"Roshchinskiy",
    "wof:placetype":"locality"
},
  "geometry": {"coordinates":[74.13240999999999,55.10516],"type":"Point"}
}