{
  "type": "Feature",
  "properties": {
    "gn:admin1_code":"42",
    "gn:asciiname":"Vybor",
    "gn:country_code":"RU",
    "gn:dem":68,
    "gn:feature_class":"P",
    "gn:feature_code":"PPL",
    "gn:name":"Vybor",
    "gn:population":0,
    "gn:timezone":"Europe/Moscow",
    "iso:country":"RU",
    "wof:name":"Vybor",
    "wof:placetype":"locality"
},
  "geometry": {"coordinates":[30.10436,58.69725],"type":"Point"}
}