{
  "type": "Feature",
  "properties": {
    "gn:admin1_code":"51.0",
    "gn:asciiname":"Aksel'skiye Vyselki",
    "gn:country_code":"RU",
    "gn:dem":159,
    "gn:feature_class":"P",
    "gn:feature_code":"PPL",
    "gn:name":"Aksel\u2019skiye Vyselki",
    "gn:population":0,
    "gn:timezone":"Europe/Moscow",
    "iso:country":"RU",
    "name:nor_x_preferred":[
        "Akselskije Vyselki"
    ],
    "name:rus_x_preferred":[
        "\u0410\u043a\u0441\u0435\u043b\u044c\u0441\u043a\u0438\u0435 \u0412\u044b\u0441\u0435\u043b\u043a\u0438"
    ],
    "name:und_x_variant":[
        "Aksel\u2019skiy Vyselok",
        "Alsel\u2019skiy Vyselok",
        "Aksel\u2019skiye Vyselki"
    ],
    "wof:name":"Aksel'skiye Vyselki",
    "wof:placetype":"locality"
},
  "geometry": {"coordinates":[43.83333,54.83333],"type":"Point"}
}