{
  "type": "Feature",
  "properties": {
    "gn:admin1_code":"10",
    "gn:asciiname":"Volovnya",
    "gn:country_code":"RU",
    "gn:dem":181,
    "gn:feature_class":"P",
    "gn:feature_code":"PPL",
    "gn:name":"Volovnya",
    "gn:population":0,
    "gn:timezone":"Europe/Moscow",
    "iso:country":"RU",
    "name:rus_x_preferred":[
        "\u0412\u043e\u043b\u043e\u0432\u043d\u044f"
    ],
    "name:und_x_variant":[
        "\u0412\u043e\u043b\u043e\u0432\u043d\u044f"
    ],
    "wof:name":"Volovnya",
    "wof:placetype":"locality"
},
  "geometry": {"coordinates":[33.65743,52.9512],"type":"Point"}
}