{
  "type": "Feature",
  "properties": {
    "gn:admin1_code":"77",
    "gn:asciiname":"Vypolzovo",
    "gn:country_code":"RU",
    "gn:dem":248,
    "gn:feature_class":"P",
    "gn:feature_code":"PPL",
    "gn:name":"Vypolzovo",
    "gn:population":0,
    "gn:timezone":"Europe/Moscow",
    "iso:country":"RU",
    "name:rus_x_preferred":[
        "\u0412\u044b\u043f\u043e\u043b\u0437\u043e\u0432\u043e"
    ],
    "name:tgk_x_preferred":[
        "\u0412\u0438\u043f\u043e\u043b\u0437\u043e\u0432\u043e"
    ],
    "name:und_x_variant":[
        "Vypolzova",
        "Vypolzoro",
        "Vypolzovo",
        "\u0412\u044b\u043f\u043e\u043b\u0437\u043e\u0432\u043e"
    ],
    "wof:name":"Vypolzovo",
    "wof:placetype":"locality"
},
  "geometry": {"coordinates":[31.94795,56.86388],"type":"Point"}
}