{
  "type": "Feature",
  "properties": {
    "gn:admin1_code":"47.0",
    "gn:asciiname":"Oshenevo",
    "gn:country_code":"RU",
    "gn:dem":159,
    "gn:feature_class":"P",
    "gn:feature_code":"PPL",
    "gn:name":"Oshenevo",
    "gn:population":0,
    "gn:timezone":"Europe/Moscow",
    "iso:country":"RU",
    "name:eng_x_preferred":[
        "Oshenevo"
    ],
    "name:rus_x_preferred":[
        "\u041e\u0448\u0435\u043d\u0435\u0432\u043e"
    ],
    "wof:name":"Oshenevo",
    "wof:placetype":"locality"
},
  "geometry": {"coordinates":[35.64427,56.27503000000001],"type":"Point"}
}