{
  "type": "Feature",
  "properties": {
    "gn:country":"RU",
    "gn:fcode":"PPL",
    "gn:population":6928,
    "iso:country":"RU",
    "name:ara_x_preferred":[
        "\u063a\u0627\u0644\u0627\u0634\u0643\u064a"
    ],
    "name:ceb_x_preferred":[
        "Galashki"
    ],
    "name:che_x_preferred":[
        "\u0413\u0430\u043b\u0430\u0448\u043a\u0438\u0435"
    ],
    "name:deu_x_preferred":[
        "Galaschki"
    ],
    "name:eng_x_preferred":[
        "Galashki"
    ],
    "name:epo_x_preferred":[
        "Gala\u015dko"
    ],
    "name:hye_x_preferred":[
        "\u0533\u0561\u056c\u0561\u0577\u056f\u056b"
    ],
    "name:inh_x_preferred":[
        "\u0413\u0430\u043b\u0430\u0448\u043a\u0435"
    ],
    "name:nld_x_preferred":[
        "Galasjki"
    ],
    "name:nor_x_preferred":[
        "Galasjki"
    ],
    "name:oss_x_preferred":[
        "\u0413\u0430\u043b\u0430\u0448\u043a\u0438"
    ],
    "name:rus_x_preferred":[
        "\u0413\u0430\u043b\u0430\u0448\u043a\u0438"
    ],
    "qs:name":"Galashki",
    "qs:photos_9r":0,
    "qs:photos_sr":0,
    "qs:pop_sr":"5",
    "wd:wordcount":97,
    "wof:name":"Galashki",
    "wof:placetype":"locality",
    "wof:population":6928
},
  "geometry": {"coordinates":[44.99055,43.1174],"type":"Point"}
}