{
  "type": "Feature",
  "properties": {
    "gn:admin1_code":"12.0",
    "gn:asciiname":"Gezekhoy",
    "gn:cc2":"RU",
    "gn:country_code":"RU",
    "gn:dem":1513,
    "gn:feature_class":"P",
    "gn:feature_code":"PPL",
    "gn:name":"Gezekhoy",
    "gn:population":0,
    "gn:timezone":"Europe/Moscow",
    "iso:country":"RU",
    "name:rus_x_preferred":[
        "\u0413\u0435\u0437\u0435\u0445\u043e\u0439"
    ],
    "name:und_x_variant":[
        "Gezakhoy",
        "Gezekhoy"
    ],
    "wof:name":"Gezekhoy",
    "wof:placetype":"locality"
},
  "geometry": {"coordinates":[45.44167,42.73361],"type":"Point"}
}