{
  "type": "Feature",
  "properties": {
    "gn:admin1_code":"38",
    "gn:asciiname":"Novyy",
    "gn:country_code":"RU",
    "gn:dem":20,
    "gn:feature_class":"P",
    "gn:feature_code":"PPL",
    "gn:name":"Novyy",
    "gn:population":0,
    "gn:timezone":"Europe/Moscow",
    "iso:country":"RU",
    "name:rus_x_preferred":[
        "\u041d\u043e\u0432\u044b\u0439"
    ],
    "name:und_x_variant":[
        "Novy",
        "Novyy"
    ],
    "wof:name":"Novyy",
    "wof:placetype":"locality"
},
  "geometry": {"coordinates":[38.80967,45.15687],"type":"Point"}
}