{
  "type": "Feature",
  "properties": {
    "gn:admin1_code":"77",
    "gn:asciiname":"Zaluch'ye",
    "gn:country_code":"RU",
    "gn:dem":215,
    "gn:feature_class":"P",
    "gn:feature_code":"PPL",
    "gn:name":"Zaluch\u2019ye",
    "gn:population":0,
    "gn:timezone":"Europe/Moscow",
    "iso:country":"RU",
    "name:eng_x_preferred":[
        "Zaluch'ye"
    ],
    "name:nor_x_preferred":[
        "Zalutsje"
    ],
    "name:rus_x_preferred":[
        "\u0417\u0430\u043b\u0443\u0447\u044c\u0435"
    ],
    "name:und_x_variant":[
        "Zaluch\u2019ye"
    ],
    "wof:name":"Zaluch'ye",
    "wof:placetype":"locality"
},
  "geometry": {"coordinates":[32.78118,57.31326],"type":"Point"}
}