{
  "type": "Feature",
  "properties": {
    "gn:admin1_code":"85",
    "gn:asciiname":"Nizhneye Isakovo",
    "gn:country_code":"RU",
    "gn:dem":101,
    "gn:feature_class":"P",
    "gn:feature_code":"PPL",
    "gn:name":"Nizhneye Isakovo",
    "gn:population":0,
    "gn:timezone":"Europe/Moscow",
    "iso:country":"RU",
    "name:rus_x_preferred":[
        "\u041d\u0438\u0436\u043d\u0435\u0435 \u0418\u0441\u0430\u043a\u043e\u0432\u043e"
    ],
    "name:und_x_variant":[
        "\u041d\u0438\u0436\u043d\u0435\u0435 \u0418\u0441\u0430\u043a\u043e\u0432\u043e"
    ],
    "wof:name":"Nizhneye Isakovo",
    "wof:placetype":"locality"
},
  "geometry": {"coordinates":[46.6167,60.0113],"type":"Point"}
}