{
  "type": "Feature",
  "properties": {
    "gn:admin1_code":"77",
    "gn:asciiname":"Narachino",
    "gn:country_code":"RU",
    "gn:dem":190,
    "gn:feature_class":"P",
    "gn:feature_code":"PPL",
    "gn:name":"Narachino",
    "gn:population":0,
    "gn:timezone":"Europe/Moscow",
    "iso:country":"RU",
    "name:rus_x_preferred":[
        "\u041d\u0430\u0440\u0430\u0447\u0438\u043d\u043e"
    ],
    "name:und_x_variant":[
        "\u041d\u0430\u0440\u0430\u0447\u0438\u043d\u043e"
    ],
    "wof:name":"Narachino",
    "wof:placetype":"locality"
},
  "geometry": {"coordinates":[33.79972,57.8775],"type":"Point"}
}