{
  "type": "Feature",
  "properties": {
    "gn:admin1_code":"76",
    "gn:asciiname":"Sadovaya",
    "gn:country_code":"RU",
    "gn:dem":160,
    "gn:feature_class":"P",
    "gn:feature_code":"PPL",
    "gn:name":"Sadovaya",
    "gn:population":0,
    "gn:timezone":"Europe/Moscow",
    "iso:country":"RU",
    "name:rus_x_preferred":[
        "\u0421\u0430\u0434\u043e\u0432\u0430\u044f"
    ],
    "name:und_x_variant":[
        "Sobakino",
        "Sadovaya",
        "\u0421\u0430\u0434\u043e\u0432\u0430\u044f"
    ],
    "wof:name":"Sadovaya",
    "wof:placetype":"locality"
},
  "geometry": {"coordinates":[36.12757,53.73306],"type":"Point"}
}