{
  "type": "Feature",
  "properties": {
    "gn:admin1_code":"60",
    "gn:asciiname":"Shcheglyn'",
    "gn:country_code":"RU",
    "gn:dem":72,
    "gn:feature_class":"P",
    "gn:feature_code":"PPL",
    "gn:name":"Shcheglyn\u2019",
    "gn:population":0,
    "gn:timezone":"Europe/Moscow",
    "iso:country":"RU",
    "name:rus_x_preferred":[
        "\u0429\u0435\u0433\u043b\u044b\u043d\u044c"
    ],
    "name:und_x_variant":[
        "Shcheglyn\u2019"
    ],
    "wof:name":"Shcheglyn'",
    "wof:placetype":"locality"
},
  "geometry": {"coordinates":[28.73938,57.12986],"type":"Point"}
}