{
  "type": "Feature",
  "properties": {
    "gn:admin1_code":"63",
    "gn:asciiname":"Kamukovo",
    "gn:cc2":"RU",
    "gn:country_code":"RU",
    "gn:dem":17,
    "gn:feature_class":"P",
    "gn:feature_code":"PPL",
    "gn:name":"Kamukovo",
    "gn:population":0,
    "gn:timezone":"Asia/Magadan",
    "iso:country":"RU",
    "name:rus_x_preferred":[
        "\u041a\u0430\u043c\u0443\u043a\u043e\u0432\u043e"
    ],
    "name:und_x_variant":[
        "Kamukova",
        "Kamukovo",
        "\u041a\u0430\u043c\u0443\u043a\u043e\u0432\u043e"
    ],
    "wof:name":"Kamukovo",
    "wof:placetype":"locality"
},
  "geometry": {"coordinates":[147.36667,69.36667],"type":"Point"}
}