{
  "type": "Feature",
  "properties": {
    "gn:admin1_code":"41.0",
    "gn:asciiname":"Rovenka",
    "gn:country_code":"RU",
    "gn:dem":167,
    "gn:feature_class":"P",
    "gn:feature_code":"PPL",
    "gn:name":"Rovenka",
    "gn:population":0,
    "gn:timezone":"Europe/Moscow",
    "iso:country":"RU",
    "name:rus_x_preferred":[
        "\u0420\u043e\u0432\u0435\u043d\u043a\u0430"
    ],
    "name:und_x_variant":[
        "\u0420\u043e\u0432\u0435\u043d\u043a\u0430"
    ],
    "wof:name":"Rovenka",
    "wof:placetype":"locality"
},
  "geometry": {"coordinates":[38.033,51.4245],"type":"Point"}
}