{
  "type": "Feature",
  "properties": {
    "gn:admin1_code":"42",
    "gn:asciiname":"Staryye Raglitsy",
    "gn:country_code":"RU",
    "gn:dem":118,
    "gn:feature_class":"P",
    "gn:feature_code":"PPL",
    "gn:name":"Staryye Raglitsy",
    "gn:population":0,
    "gn:timezone":"Europe/Moscow",
    "iso:country":"RU",
    "name:fin_x_preferred":[
        "Vanha-Raaklitsa"
    ],
    "name:nor_x_preferred":[
        "Starye Raglitsy"
    ],
    "name:rus_x_preferred":[
        "\u0421\u0442\u0430\u0440\u044b\u0435 \u0420\u0430\u0433\u043b\u0438\u0446\u044b"
    ],
    "wof:name":"Staryye Raglitsy",
    "wof:placetype":"locality"
},
  "geometry": {"coordinates":[29.66422,59.40353],"type":"Point"}
}