{
  "type": "Feature",
  "properties": {
    "gn:admin1_code":"83",
    "gn:asciiname":"Povalikhino",
    "gn:country_code":"RU",
    "gn:dem":77,
    "gn:feature_class":"P",
    "gn:feature_code":"PPL",
    "gn:name":"Povalikhino",
    "gn:population":0,
    "gn:timezone":"Europe/Moscow",
    "iso:country":"RU",
    "name:rus_x_preferred":[
        "\u041f\u043e\u0432\u0430\u043b\u0438\u0445\u0438\u043d\u043e"
    ],
    "name:und_x_variant":[
        "Pavalikhino"
    ],
    "wof:name":"Povalikhino",
    "wof:placetype":"locality"
},
  "geometry": {"coordinates":[42.5577,55.9896],"type":"Point"}
}