{
  "type": "Feature",
  "properties": {
    "gn:admin1_code":"33.0",
    "gn:asciiname":"Kazakovshchina",
    "gn:country_code":"RU",
    "gn:dem":198,
    "gn:feature_class":"P",
    "gn:feature_code":"PPL",
    "gn:name":"Kazakovshchina",
    "gn:population":0,
    "gn:timezone":"Europe/Kirov",
    "iso:country":"RU",
    "name:rus_x_preferred":[
        "\u041a\u0430\u0437\u0430\u043a\u043e\u0432\u0449\u0438\u043d\u0430"
    ],
    "wof:name":"Kazakovshchina",
    "wof:placetype":"locality"
},
  "geometry": {"coordinates":[48.45583,59.08611],"type":"Point"}
}