{
  "type": "Feature",
  "properties": {
    "gn:admin1_code":"63",
    "gn:asciiname":"Amginskoye",
    "gn:country_code":"RU",
    "gn:dem":187,
    "gn:feature_class":"P",
    "gn:feature_code":"PPL",
    "gn:name":"Amginskoye",
    "gn:population":0,
    "gn:timezone":"Asia/Yakutsk",
    "iso:country":"RU",
    "name:nor_x_preferred":[
        "Amginskoje"
    ],
    "name:rus_x_preferred":[
        "\u0410\u043c\u0433\u0438\u043d\u0441\u043a\u043e\u0435"
    ],
    "name:und_x_variant":[
        "Amginskaya",
        "Amginskoye"
    ],
    "wof:name":"Amginskoye",
    "wof:placetype":"locality"
},
  "geometry": {"coordinates":[133.56666999999999,61.75],"type":"Point"}
}