{
  "type": "Feature",
  "properties": {
    "gn:admin1_code":"51",
    "gn:asciiname":"Piter",
    "gn:country_code":"RU",
    "gn:dem":139,
    "gn:feature_class":"P",
    "gn:feature_code":"PPL",
    "gn:name":"Piter",
    "gn:population":0,
    "gn:timezone":"Europe/Moscow",
    "iso:country":"RU",
    "name:rus_x_preferred":[
        "\u041f\u0438\u0442\u0435\u0440"
    ],
    "wof:name":"Piter",
    "wof:placetype":"locality"
},
  "geometry": {"coordinates":[47.1818,57.789],"type":"Point"}
}