{
  "type": "Feature",
  "properties": {
    "gn:admin1_code":"71",
    "gn:asciiname":"Yalunina",
    "gn:country_code":"RU",
    "gn:dem":193,
    "gn:feature_class":"P",
    "gn:feature_code":"PPL",
    "gn:name":"Yalunina",
    "gn:population":0,
    "gn:timezone":"Asia/Yekaterinburg",
    "iso:country":"RU",
    "name:rus_x_preferred":[
        "\u042f\u043b\u0443\u043d\u0438\u043d\u0430"
    ],
    "wof:name":"Yalunina",
    "wof:placetype":"locality"
},
  "geometry": {"coordinates":[61.4524,56.8116],"type":"Point"}
}