{
  "type": "Feature",
  "properties": {
    "gn:admin1_code":"8",
    "gn:asciiname":"Grafskoye",
    "gn:country_code":"RU",
    "gn:dem":125,
    "gn:feature_class":"P",
    "gn:feature_code":"PPL",
    "gn:name":"Grafskoye",
    "gn:population":0,
    "gn:timezone":"Asia/Yekaterinburg",
    "iso:country":"RU",
    "name:rus_x_preferred":[
        "\u0413\u0440\u0430\u0444\u0441\u043a\u043e\u0435"
    ],
    "name:und_x_variant":[
        "\u0413\u0440\u0430\u0444\u0441\u043a\u043e\u0435"
    ],
    "wof:name":"Grafskoye",
    "wof:placetype":"locality"
},
  "geometry": {"coordinates":[54.4533,55.92698000000001],"type":"Point"}
}