{
  "type": "Feature",
  "properties": {
    "gn:admin1_code":"54",
    "gn:asciiname":"Pyatiletka",
    "gn:country_code":"RU",
    "gn:dem":108,
    "gn:feature_class":"P",
    "gn:feature_code":"PPL",
    "gn:name":"Pyatiletka",
    "gn:population":0,
    "gn:timezone":"Asia/Omsk",
    "iso:country":"RU",
    "name:rus_x_preferred":[
        "\u041f\u044f\u0442\u0438\u043b\u0435\u0442\u043a\u0430"
    ],
    "wof:name":"Pyatiletka",
    "wof:placetype":"locality"
},
  "geometry": {"coordinates":[72.93479000000001,54.93706],"type":"Point"}
}