{
  "type": "Feature",
  "properties": {
    "gn:admin1_code":"30",
    "gn:asciiname":"Uyega",
    "gn:country_code":"RU",
    "gn:dem":389,
    "gn:feature_class":"P",
    "gn:feature_code":"PPL",
    "gn:name":"Uyega",
    "gn:population":0,
    "gn:timezone":"Asia/Vladivostok",
    "iso:country":"RU",
    "name:eng_x_preferred":[
        "Uyega"
    ],
    "name:nor_x_preferred":[
        "Ujega"
    ],
    "name:rus_x_preferred":[
        "\u0423\u0435\u0433\u0430"
    ],
    "name:und_x_variant":[
        "Uega",
        "Uvga"
    ],
    "wof:name":"Uyega",
    "wof:placetype":"locality"
},
  "geometry": {"coordinates":[142.76188999999999,60.72201],"type":"Point"}
}