{
  "type": "Feature",
  "properties": {
    "gn:admin1_code":"84",
    "gn:asciiname":"Krasnogorskiy",
    "gn:country_code":"RU",
    "gn:dem":127,
    "gn:feature_class":"P",
    "gn:feature_code":"PPL",
    "gn:name":"Krasnogorskiy",
    "gn:population":0,
    "gn:timezone":"Europe/Volgograd",
    "iso:country":"RU",
    "name:rus_x_preferred":[
        "\u041a\u0440\u0430\u0441\u043d\u043e\u0433\u043e\u0440\u0441\u043a\u0438\u0439"
    ],
    "wof:name":"Krasnogorskiy",
    "wof:placetype":"locality"
},
  "geometry": {"coordinates":[42.8238,50.4204],"type":"Point"}
}