{
  "type": "Feature",
  "properties": {
    "gn:admin1_code":"76",
    "gn:asciiname":"Vosemskoye",
    "gn:country_code":"RU",
    "gn:dem":137,
    "gn:feature_class":"P",
    "gn:feature_code":"PPL",
    "gn:name":"Vosemskoye",
    "gn:population":0,
    "gn:timezone":"Europe/Moscow",
    "iso:country":"RU",
    "name:und_x_variant":[
        "Vos\u2019ma",
        "Vosemskoye"
    ],
    "wof:name":"Vosemskoye",
    "wof:placetype":"locality"
},
  "geometry": {"coordinates":[37.93618,54.75983000000001],"type":"Point"}
}