{
  "type": "Feature",
  "properties": {
    "gn:admin1_code":"86",
    "gn:asciiname":"Shcherbakovo",
    "gn:country_code":"RU",
    "gn:dem":182,
    "gn:feature_class":"P",
    "gn:feature_code":"PPL",
    "gn:name":"Shcherbakovo",
    "gn:population":0,
    "gn:timezone":"Europe/Moscow",
    "iso:country":"RU",
    "name:rus_x_preferred":[
        "\u0429\u0435\u0440\u0431\u0430\u043a\u043e\u0432\u043e"
    ],
    "name:und_x_variant":[
        "Shcherbakova",
        "Shcherbakovo"
    ],
    "wof:name":"Shcherbakovo",
    "wof:placetype":"locality"
},
  "geometry": {"coordinates":[39.35188,50.80507],"type":"Point"}
}