{
  "type": "Feature",
  "properties": {
    "gn:admin1_code":"56.0",
    "gn:asciiname":"Bukreyevskiy",
    "gn:country_code":"RU",
    "gn:dem":216,
    "gn:feature_class":"P",
    "gn:feature_code":"PPL",
    "gn:name":"Bukreyevskiy",
    "gn:population":0,
    "gn:timezone":"Europe/Moscow",
    "iso:country":"RU",
    "name:rus_x_preferred":[
        "\u0411\u0443\u043a\u0440\u0435\u0435\u0432\u0441\u043a\u0438\u0439"
    ],
    "name:und_x_variant":[
        "\u0411\u0443\u043a\u0440\u0435\u0435\u0432\u0441\u043a\u0438\u0439"
    ],
    "wof:name":"Bukreyevskiy",
    "wof:placetype":"locality"
},
  "geometry": {"coordinates":[35.88333,52.61666999999999],"type":"Point"}
}