{
  "type": "Feature",
  "properties": {
    "gn:admin1_code":"46",
    "gn:asciiname":"Russkaya Payevka",
    "gn:country_code":"RU",
    "gn:dem":158,
    "gn:feature_class":"P",
    "gn:feature_code":"PPL",
    "gn:name":"Russkaya Pay\u00ebvka",
    "gn:population":0,
    "gn:timezone":"Europe/Moscow",
    "iso:country":"RU",
    "name:rus_x_preferred":[
        "\u0420\u0443\u0441\u0441\u043a\u0430\u044f \u041f\u0430\u0451\u0432\u043a\u0430"
    ],
    "name:und_x_variant":[
        "Pay\u00ebvka",
        "Russkaya Pay\u00ebvka",
        "\u0420\u0443\u0441\u0441\u043a\u0430\u044f \u041f\u0430\u0451\u0432\u043a\u0430"
    ],
    "wof:name":"Russkaya Payevka",
    "wof:placetype":"locality"
},
  "geometry": {"coordinates":[44.31002,53.90153000000001],"type":"Point"}
}