{
  "type": "Feature",
  "properties": {
    "gn:admin1_code":"33.0",
    "gn:asciiname":"Ishimovy",
    "gn:country_code":"RU",
    "gn:dem":142,
    "gn:feature_class":"P",
    "gn:feature_code":"PPL",
    "gn:name":"Ishimovy",
    "gn:population":0,
    "gn:timezone":"Europe/Kirov",
    "iso:country":"RU",
    "name:rus_x_preferred":[
        "\u0418\u0448\u0438\u043c\u043e\u0432\u044b"
    ],
    "wof:name":"Ishimovy",
    "wof:placetype":"locality"
},
  "geometry": {"coordinates":[48.88405,58.32111],"type":"Point"}
}