{
  "type": "Feature",
  "properties": {
    "gn:country":"RU",
    "gn:fcode":"PPL",
    "gn:population":0,
    "iso:country":"RU",
    "name:fin_x_preferred":[
        "Mistola"
    ],
    "name:rus_x_preferred":[
        "\u041c\u0438\u0441\u0442\u043e\u043b\u043e\u0432\u043e"
    ],
    "qs:name":"Mistolovo",
    "qs:name_adm0":"Russia",
    "qs:name_adm1":"Leningrad Oblast",
    "qs:photos_9r":0,
    "qs:photos_sr":0,
    "qs:placetype":"Town",
    "qs:pop_sr":"0",
    "wof:name":"Mistolovo",
    "wof:placetype":"locality",
    "wof:population":0
},
  "geometry": {"coordinates":[30.40562,60.12043],"type":"Point"}
}