{
  "type": "Feature",
  "properties": {
    "gn:admin1_code":"63",
    "gn:asciiname":"Kysyl",
    "gn:country_code":"RU",
    "gn:dem":232,
    "gn:feature_class":"P",
    "gn:feature_code":"PPL",
    "gn:name":"Kysyl",
    "gn:population":0,
    "gn:timezone":"Asia/Yakutsk",
    "iso:country":"RU",
    "name:eng_x_preferred":[
        "Kysyl"
    ],
    "name:nor_x_preferred":[
        "Kysyl"
    ],
    "name:rus_x_preferred":[
        "\u041a\u044b\u0441\u044b\u043b"
    ],
    "wof:name":"Kysyl",
    "wof:placetype":"locality"
},
  "geometry": {"coordinates":[126.59986000000001,62.10291],"type":"Point"}
}