{
  "type": "Feature",
  "properties": {
    "gn:admin1_code":"23",
    "gn:asciiname":"Timiryazevo",
    "gn:country_code":"RU",
    "gn:dem":3,
    "gn:feature_class":"P",
    "gn:feature_code":"PPL",
    "gn:name":"Timiryazevo",
    "gn:population":0,
    "gn:timezone":"Europe/Kaliningrad",
    "iso:country":"RU",
    "name:eng_x_preferred":[
        "Timiryazevo"
    ],
    "name:nor_x_preferred":[
        "Timirjazevo"
    ],
    "name:rus_x_preferred":[
        "\u0422\u0438\u043c\u0438\u0440\u044f\u0437\u0435\u0432\u043e"
    ],
    "name:und_x_variant":[
        "Noykirkh",
        "Timirjazevo",
        "Neukirch",
        "Neukirkh",
        "Timiryazevo"
    ],
    "wof:name":"Timiryazevo",
    "wof:placetype":"locality"
},
  "geometry": {"coordinates":[21.6107,55.08338000000001],"type":"Point"}
}