{
  "type": "Feature",
  "properties": {
    "gn:admin1_code":"68",
    "gn:asciiname":"Yelgona",
    "gn:country_code":"RU",
    "gn:dem":1908,
    "gn:feature_class":"P",
    "gn:feature_code":"PPL",
    "gn:name":"Yelgona",
    "gn:population":0,
    "gn:timezone":"Europe/Moscow",
    "iso:country":"RU",
    "name:rus_x_preferred":[
        "\u0415\u043b\u0433\u043e\u043d\u0430"
    ],
    "wof:name":"Yelgona",
    "wof:placetype":"locality"
},
  "geometry": {"coordinates":[44.05883,42.67939000000001],"type":"Point"}
}