{
  "type": "Feature",
  "properties": {
    "gn:admin1_code":"33",
    "gn:asciiname":"Paryug",
    "gn:country_code":"RU",
    "gn:dem":147,
    "gn:feature_class":"P",
    "gn:feature_code":"PPL",
    "gn:name":"Paryug",
    "gn:population":0,
    "gn:timezone":"Europe/Kirov",
    "iso:country":"RU",
    "name:eng_x_preferred":[
        "Paryug"
    ],
    "name:nor_x_preferred":[
        "Parjug"
    ],
    "name:rus_x_preferred":[
        "\u041f\u0430\u0440\u044e\u0433"
    ],
    "wof:name":"Paryug",
    "wof:placetype":"locality"
},
  "geometry": {"coordinates":[47.93011,58.60444],"type":"Point"}
}