{
  "type": "Feature",
  "properties": {
    "gn:admin1_code":"60",
    "gn:asciiname":"Kononovo",
    "gn:country_code":"RU",
    "gn:dem":66,
    "gn:feature_class":"P",
    "gn:feature_code":"PPL",
    "gn:name":"Kononovo",
    "gn:population":0,
    "gn:timezone":"Europe/Moscow",
    "iso:country":"RU",
    "name:che_x_preferred":[
        "\u041a\u043e\u043d\u043e\u043d\u043e\u0432\u043e"
    ],
    "name:rus_x_preferred":[
        "\u041a\u043e\u043d\u043e\u043d\u043e\u0432\u043e"
    ],
    "wof:name":"Kononovo",
    "wof:placetype":"locality"
},
  "geometry": {"coordinates":[28.03329,57.4938],"type":"Point"}
}