{
  "type": "Feature",
  "properties": {
    "gn:admin1_code":"51",
    "gn:asciiname":"Sharonovka",
    "gn:country_code":"RU",
    "gn:dem":125,
    "gn:feature_class":"P",
    "gn:feature_code":"PPL",
    "gn:name":"Sharonovka",
    "gn:population":0,
    "gn:timezone":"Europe/Moscow",
    "iso:country":"RU",
    "name:rus_x_preferred":[
        "\u0428\u0430\u0440\u043e\u043d\u043e\u0432\u043a\u0430"
    ],
    "name:und_x_variant":[
        "\u0428\u0430\u0440\u043e\u043d\u043e\u0432\u043a\u0430"
    ],
    "wof:name":"Sharonovka",
    "wof:placetype":"locality"
},
  "geometry": {"coordinates":[46.0959,57.4158],"type":"Point"}
}