{
  "type": "Feature",
  "properties": {
    "gn:admin1_code":"80.0",
    "gn:asciiname":"Davkino",
    "gn:country_code":"RU",
    "gn:dem":151,
    "gn:feature_class":"P",
    "gn:feature_code":"PPL",
    "gn:name":"Davkino",
    "gn:population":0,
    "gn:timezone":"Europe/Samara",
    "iso:country":"RU",
    "name:rus_x_preferred":[
        "\u0414\u0430\u0432\u043a\u0438\u043d\u043e"
    ],
    "name:und_x_variant":[
        "\u0414\u0430\u0432\u043a\u0438\u043d\u043e"
    ],
    "wof:name":"Davkino",
    "wof:placetype":"locality"
},
  "geometry": {"coordinates":[51.91234,56.2408],"type":"Point"}
}