{
  "type": "Feature",
  "properties": {
    "gn:admin1_code":"61.0",
    "gn:asciiname":"Boguny",
    "gn:country_code":"RU",
    "gn:dem":172,
    "gn:feature_class":"P",
    "gn:feature_code":"PPL",
    "gn:name":"Boguny",
    "gn:population":0,
    "gn:timezone":"Europe/Moscow",
    "iso:country":"RU",
    "name:rus_x_preferred":[
        "\u0411\u043e\u0433\u0443\u043d\u044b"
    ],
    "name:und_x_variant":[
        "Buguny",
        "Bogunov",
        "Boguny"
    ],
    "wof:name":"Boguny",
    "wof:placetype":"locality"
},
  "geometry": {"coordinates":[40.84289,49.48215],"type":"Point"}
}