{
  "type": "Feature",
  "properties": {
    "gn:admin1_code":"61",
    "gn:asciiname":"Zelenkovskiy Lastivyanov",
    "gn:country_code":"RU",
    "gn:dem":89,
    "gn:feature_class":"P",
    "gn:feature_code":"PPL",
    "gn:name":"Zelenkovskiy Lastivyanov",
    "gn:population":0,
    "gn:timezone":"Europe/Moscow",
    "iso:country":"RU",
    "wof:name":"Zelenkovskiy Lastivyanov",
    "wof:placetype":"locality"
},
  "geometry": {"coordinates":[40.76086,49.27448],"type":"Point"}
}