{
  "type": "Feature",
  "properties": {
    "gn:admin1_code":"52",
    "gn:asciiname":"Dedova Luka",
    "gn:country_code":"RU",
    "gn:dem":36,
    "gn:feature_class":"P",
    "gn:feature_code":"PPL",
    "gn:name":"Dedova Luka",
    "gn:population":0,
    "gn:timezone":"Europe/Moscow",
    "iso:country":"RU",
    "name:rus_x_preferred":[
        "\u0414\u0435\u0434\u043e\u0432\u0430 \u041b\u0443\u043a\u0430"
    ],
    "name:und_x_variant":[
        "\u0414\u0435\u0434\u043e\u0432\u0430 \u041b\u0443\u043a\u0430"
    ],
    "wof:name":"Dedova Luka",
    "wof:placetype":"locality"
},
  "geometry": {"coordinates":[31.1473,57.9226],"type":"Point"}
}