{
  "type": "Feature",
  "properties": {
    "gn:admin1_code":"76",
    "gn:asciiname":"Pyatilovka",
    "gn:country_code":"RU",
    "gn:dem":158,
    "gn:feature_class":"P",
    "gn:feature_code":"PPL",
    "gn:name":"Pyatilovka",
    "gn:population":0,
    "gn:timezone":"Europe/Moscow",
    "iso:country":"RU",
    "name:rus_x_preferred":[
        "\u041f\u044f\u0442\u0438\u043b\u043e\u0432\u043a\u0430"
    ],
    "wof:name":"Pyatilovka",
    "wof:placetype":"locality"
},
  "geometry": {"coordinates":[38.52614000000001,53.60732],"type":"Point"}
}