{
  "type": "Feature",
  "properties": {
    "gn:admin1_code":"37.0",
    "gn:asciiname":"Slobodishchevo",
    "gn:country_code":"RU",
    "gn:dem":90,
    "gn:feature_class":"P",
    "gn:feature_code":"PPL",
    "gn:name":"Slobodishchevo",
    "gn:population":0,
    "gn:timezone":"Europe/Moscow",
    "iso:country":"RU",
    "name:rus_x_preferred":[
        "\u0421\u043b\u043e\u0431\u043e\u0434\u0438\u0449\u0435\u0432\u043e"
    ],
    "wof:name":"Slobodishchevo",
    "wof:placetype":"locality"
},
  "geometry": {"coordinates":[41.1175,57.62995],"type":"Point"}
}