{
  "type": "Feature",
  "properties": {
    "gn:admin1_code":"91",
    "gn:asciiname":"Malyy Kanaray",
    "gn:cc2":"RU",
    "gn:country_code":"RU",
    "gn:dem":263,
    "gn:feature_class":"P",
    "gn:feature_code":"PPL",
    "gn:name":"Malyy Kanaray",
    "gn:population":0,
    "gn:timezone":"Asia/Krasnoyarsk",
    "iso:country":"RU",
    "name:und_x_variant":[
        "Orekhovaya"
    ],
    "wof:name":"Malyy Kanaray",
    "wof:placetype":"locality"
},
  "geometry": {"coordinates":[94.43556,56.93556],"type":"Point"}
}