{
  "type": "Feature",
  "properties": {
    "gn:admin1_code":"54",
    "gn:asciiname":"Severnoye",
    "gn:country_code":"RU",
    "gn:dem":106,
    "gn:feature_class":"P",
    "gn:feature_code":"PPL",
    "gn:name":"Severnoye",
    "gn:population":0,
    "gn:timezone":"Asia/Omsk",
    "iso:country":"RU",
    "name:eng_x_preferred":[
        "Severnoye"
    ],
    "name:nor_x_preferred":[
        "Severnoje"
    ],
    "name:rus_x_preferred":[
        "\u0421\u0435\u0432\u0435\u0440\u043d\u043e\u0435"
    ],
    "name:und_x_variant":[
        "\u0421\u0435\u0432\u0435\u0440\u043d\u043e\u0435",
        "Severnoye"
    ],
    "wof:name":"Severnoye",
    "wof:placetype":"locality"
},
  "geometry": {"coordinates":[74.76661999999997,54.50583],"type":"Point"}
}