{
  "type": "Feature",
  "properties": {
    "gn:admin1_code":"60",
    "gn:asciiname":"Solonovo",
    "gn:country_code":"RU",
    "gn:dem":56,
    "gn:feature_class":"P",
    "gn:feature_code":"PPL",
    "gn:name":"Solonovo",
    "gn:population":0,
    "gn:timezone":"Europe/Moscow",
    "iso:country":"RU",
    "name:rus_x_preferred":[
        "\u0421\u043e\u043b\u043e\u043d\u043e\u0432\u043e"
    ],
    "wof:name":"Solonovo",
    "wof:placetype":"locality"
},
  "geometry": {"coordinates":[28.2831,57.8634],"type":"Point"}
}