{
  "type": "Feature",
  "properties": {
    "gn:admin1_code":"60.0",
    "gn:asciiname":"Fedyaki",
    "gn:country_code":"RU",
    "gn:dem":73,
    "gn:feature_class":"P",
    "gn:feature_code":"PPL",
    "gn:name":"Fedyaki",
    "gn:population":0,
    "gn:timezone":"Europe/Moscow",
    "iso:country":"RU",
    "name:rus_x_preferred":[
        "\u0424\u0435\u0434\u044f\u043a\u0438"
    ],
    "wof:name":"Fedyaki",
    "wof:placetype":"locality"
},
  "geometry": {"coordinates":[30.88743,56.93583],"type":"Point"}
}