{
  "type": "Feature",
  "properties": {
    "gn:admin1_code":"41",
    "gn:asciiname":"Mikhaylovskiy",
    "gn:country_code":"RU",
    "gn:dem":178,
    "gn:feature_class":"P",
    "gn:feature_code":"PPL",
    "gn:name":"Mikhaylovskiy",
    "gn:population":0,
    "gn:timezone":"Europe/Moscow",
    "iso:country":"RU",
    "name:rus_x_preferred":[
        "\u041c\u0438\u0445\u0430\u0439\u043b\u043e\u0432\u0441\u043a\u0438\u0439"
    ],
    "wof:name":"Mikhaylovskiy",
    "wof:placetype":"locality"
},
  "geometry": {"coordinates":[35.4395,52.3507],"type":"Point"}
}