{
  "type": "Feature",
  "properties": {
    "gn:admin1_code":"61.0",
    "gn:asciiname":"Millerovo",
    "gn:country_code":"RU",
    "gn:dem":142,
    "gn:feature_class":"P",
    "gn:feature_code":"PPL",
    "gn:name":"Millerovo",
    "gn:population":0,
    "gn:timezone":"Europe/Moscow",
    "iso:country":"RU",
    "name:ben_x_preferred":[
        "\u09ae\u09bf\u09b2\u09cd\u09b2\u09c7\u09b0\u09cb\u09ad\u09cb"
    ],
    "name:ell_x_preferred":[
        "\u039c\u03b9\u03bb\u03bb\u03ad\u03c1\u03bf\u03b2\u03b9"
    ],
    "name:eng_x_preferred":[
        "Millerovo"
    ],
    "name:hin_x_preferred":[
        "\u092e\u093f\u0932\u0947\u0930\u094b\u0935\u094b"
    ],
    "name:ind_x_preferred":[
        "Millerovo"
    ],
    "name:nor_x_preferred":[
        "Millerovo"
    ],
    "name:por_x_preferred":[
        "Millerovo"
    ],
    "name:rus_x_preferred":[
        "\u041c\u0438\u043b\u043b\u0435\u0440\u043e\u0432\u043e"
    ],
    "name:spa_x_preferred":[
        "Millerovo"
    ],
    "name:swe_x_preferred":[
        "Millerovo"
    ],
    "name:urd_x_preferred":[
        "\u0645\u06cc\u0644\u06cc\u0631\u0648\u0648"
    ],
    "wof:name":"Millerovo",
    "wof:placetype":"locality"
},
  "geometry": {"coordinates":[39.28028,47.84722],"type":"Point"}
}