{
  "type": "Feature",
  "properties": {
    "gn:admin1_code":"7",
    "gn:asciiname":"Yamnoye",
    "gn:country_code":"RU",
    "gn:dem":-20,
    "gn:feature_class":"P",
    "gn:feature_code":"PPL",
    "gn:name":"Yamnoye",
    "gn:population":0,
    "gn:timezone":"Europe/Astrakhan",
    "iso:country":"RU",
    "name:eng_x_preferred":[
        "Yamnoye"
    ],
    "name:nor_x_preferred":[
        "Jamnoje"
    ],
    "name:rus_x_preferred":[
        "\u042f\u043c\u043d\u043e\u0435"
    ],
    "wof:name":"Yamnoye",
    "wof:placetype":"locality"
},
  "geometry": {"coordinates":[47.7041,45.98848],"type":"Point"}
}