{
  "type": "Feature",
  "properties": {
    "gn:admin1_code":"7",
    "gn:asciiname":"Malaya Solyanka",
    "gn:country_code":"RU",
    "gn:dem":1,
    "gn:feature_class":"P",
    "gn:feature_code":"PPL",
    "gn:name":"Malaya Solyanka",
    "gn:population":0,
    "gn:timezone":"Europe/Astrakhan",
    "iso:country":"RU",
    "name:rus_x_preferred":[
        "\u041c\u0430\u043b\u0430\u044f \u0421\u043e\u043b\u044f\u043d\u043a\u0430"
    ],
    "wof:name":"Malaya Solyanka",
    "wof:placetype":"locality"
},
  "geometry": {"coordinates":[45.91139,48.49444],"type":"Point"}
}