{
  "type": "Feature",
  "properties": {
    "gn:admin1_code":"8",
    "gn:asciiname":"Osipovka",
    "gn:country_code":"RU",
    "gn:dem":264,
    "gn:feature_class":"P",
    "gn:feature_code":"PPL",
    "gn:name":"Osipovka",
    "gn:population":0,
    "gn:timezone":"Asia/Yekaterinburg",
    "iso:country":"RU",
    "name:rus_x_preferred":[
        "\u041e\u0441\u0438\u043f\u043e\u0432\u043a\u0430"
    ],
    "name:und_x_variant":[
        "\u041e\u0441\u0438\u043f\u043e\u0432\u043a\u0430"
    ],
    "wof:name":"Osipovka",
    "wof:placetype":"locality"
},
  "geometry": {"coordinates":[56.3446,55.46089],"type":"Point"}
}