{
  "type": "Feature",
  "properties": {
    "gn:admin1_code":"41",
    "gn:asciiname":"Sukhotinovka",
    "gn:country_code":"RU",
    "gn:dem":185,
    "gn:feature_class":"P",
    "gn:feature_code":"PPL",
    "gn:name":"Sukhotinovka",
    "gn:population":0,
    "gn:timezone":"Europe/Moscow",
    "iso:country":"RU",
    "name:rus_x_preferred":[
        "\u0421\u0443\u0445\u043e\u0442\u0438\u043d\u043e\u0432\u043a\u0430"
    ],
    "wof:name":"Sukhotinovka",
    "wof:placetype":"locality"
},
  "geometry": {"coordinates":[37.5058,51.8226],"type":"Point"}
}