{
  "type": "Feature",
  "properties": {
    "gn:admin1_code":"17",
    "gn:asciiname":"Aynikab",
    "gn:country_code":"RU",
    "gn:dem":1577,
    "gn:feature_class":"P",
    "gn:feature_code":"PPL",
    "gn:name":"Aynikab",
    "gn:population":0,
    "gn:timezone":"Europe/Moscow",
    "iso:country":"RU",
    "name:nor_x_preferred":[
        "Ajnikab"
    ],
    "name:rus_x_preferred":[
        "\u0410\u0439\u043d\u0438\u043a\u0430\u0431"
    ],
    "wof:name":"Aynikab",
    "wof:placetype":"locality"
},
  "geometry": {"coordinates":[47.21678,42.36941],"type":"Point"}
}