{
  "type": "Feature",
  "properties": {
    "gn:admin1_code":"85",
    "gn:asciiname":"Dargun",
    "gn:country_code":"RU",
    "gn:dem":107,
    "gn:feature_class":"P",
    "gn:feature_code":"PPL",
    "gn:name":"Dargun",
    "gn:population":0,
    "gn:timezone":"Europe/Moscow",
    "iso:country":"RU",
    "name:ara_x_preferred":[
        "\u062f\u0627\u0631\u063a\u0648\u0646"
    ],
    "name:azb_x_preferred":[
        "\u062f\u0627\u0631\u0642\u0648\u0646"
    ],
    "name:ceb_x_preferred":[
        "Dargun"
    ],
    "name:dan_x_preferred":[
        "Dargun"
    ],
    "name:deu_x_preferred":[
        "Dargun"
    ],
    "name:epo_x_preferred":[
        "Dargun"
    ],
    "name:fas_x_preferred":[
        "\u062f\u0627\u0631\u06af\u0648\u0646"
    ],
    "name:fra_x_preferred":[
        "Dargun"
    ],
    "name:hun_x_preferred":[
        "Dargun"
    ],
    "name:ita_x_preferred":[
        "Dargun"
    ],
    "name:kaz_x_preferred":[
        "\u0414\u0430\u0440\u0433\u0443\u043d"
    ],
    "name:kir_x_preferred":[
        "\u0414\u0430\u0440\u0433\u0443\u043d"
    ],
    "name:lav_x_preferred":[
        "Darguna"
    ],
    "name:mkd_x_preferred":[
        "\u0414\u0430\u0440\u0433\u0443\u043d"
    ],
    "name:msa_x_preferred":[
        "Dargun"
    ],
    "name:nld_x_preferred":[
        "Dargun"
    ],
    "name:pol_x_preferred":[
        "Dargun"
    ],
    "name:ron_x_preferred":[
        "Dargun"
    ],
    "name:rus_x_preferred":[
        "\u0414\u0430\u0440\u0433\u0443\u043d"
    ],
    "name:spa_x_preferred":[
        "Dargun"
    ],
    "name:srp_x_preferred":[
        "\u0414\u0430\u0440\u0433\u0443\u043d"
    ],
    "name:swe_x_preferred":[
        "Dargun"
    ],
    "name:tur_x_preferred":[
        "Dargun"
    ],
    "name:ukr_x_preferred":[
        "\u0414\u0430\u0440\u0433\u0443\u043d"
    ],
    "name:und_x_variant":[
        "\u0414\u0430\u0440\u0433\u0443\u043d"
    ],
    "name:vie_x_preferred":[
        "Dargun"
    ],
    "name:vol_x_preferred":[
        "Dargun"
    ],
    "name:war_x_preferred":[
        "Dargun"
    ],
    "name:zho_x_preferred":[
        "\u8fbe\u5c14\u8d21"
    ],
    "wof:name":"Dargun",
    "wof:placetype":"locality"
},
  "geometry": {"coordinates":[38.2374,59.08215],"type":"Point"}
}