{
  "type": "Feature",
  "properties": {
    "gn:admin1_code":"85",
    "gn:asciiname":"Dargun",
    "gn:country_code":"RU",
    "gn:dem":107,
    "gn:feature_class":"P",
    "gn:feature_code":"PPL",
    "gn:name":"Dargun",
    "gn:population":0,
    "gn:timezone":"Europe/Moscow",
    "iso:country":"RU",
    "name:rus_x_preferred":[
        "\u0414\u0430\u0440\u0433\u0443\u043d"
    ],
    "name:und_x_variant":[
        "\u0414\u0430\u0440\u0433\u0443\u043d"
    ],
    "wof:name":"Dargun",
    "wof:placetype":"locality"
},
  "geometry": {"coordinates":[38.2374,59.08215],"type":"Point"}
}