{
  "type": "Feature",
  "properties": {
    "gn:admin1_code":"38",
    "gn:asciiname":"Buzinovskaya",
    "gn:country_code":"RU",
    "gn:dem":32,
    "gn:feature_class":"P",
    "gn:feature_code":"PPL",
    "gn:name":"Buzinovskaya",
    "gn:population":0,
    "gn:timezone":"Europe/Moscow",
    "iso:country":"RU",
    "name:eng_x_preferred":[
        "Buzinovskaya"
    ],
    "name:nor_x_preferred":[
        "Buzinovskaja"
    ],
    "name:rus_x_preferred":[
        "\u0411\u0443\u0437\u0438\u043d\u043e\u0432\u0441\u043a\u0430\u044f"
    ],
    "name:und_x_variant":[
        "\u0411\u0443\u0437\u0438\u043d\u043e\u0432\u0441\u043a\u0430\u044f",
        "Buzinovskaya"
    ],
    "wof:name":"Buzinovskaya",
    "wof:placetype":"locality"
},
  "geometry": {"coordinates":[39.79016,45.63976],"type":"Point"}
}