{
  "type": "Feature",
  "properties": {
    "gn:admin1_code":"47",
    "gn:asciiname":"Pushkino",
    "gn:country_code":"RU",
    "gn:dem":149,
    "gn:feature_class":"P",
    "gn:feature_code":"PPL",
    "gn:name":"Pushkino",
    "gn:population":0,
    "gn:timezone":"Europe/Moscow",
    "iso:country":"RU",
    "name:ceb_x_preferred":[
        "Pushkino"
    ],
    "name:sco_x_preferred":[
        "Pushkino"
    ],
    "name:swe_x_preferred":[
        "Pushkino"
    ],
    "wof:name":"Pushkino",
    "wof:placetype":"locality"
},
  "geometry": {"coordinates":[37.85306,55.37111],"type":"Point"}
}