{
  "type": "Feature",
  "properties": {
    "gn:admin1_code":"75",
    "gn:asciiname":"Stalinka",
    "gn:country_code":"RU",
    "gn:dem":84,
    "gn:feature_class":"P",
    "gn:feature_code":"PPL",
    "gn:name":"Stalinka",
    "gn:population":0,
    "gn:timezone":"Asia/Tomsk",
    "iso:country":"RU",
    "name:rus_x_preferred":[
        "\u0421\u0442\u0430\u043b\u0438\u043d\u043a\u0430"
    ],
    "name:und_x_variant":[
        "\u0421\u0442\u0430\u043b\u0438\u043d\u043a\u0430"
    ],
    "wof:name":"Stalinka",
    "wof:placetype":"locality"
},
  "geometry": {"coordinates":[77.66667,59.15],"type":"Point"}
}