{
  "type": "Feature",
  "properties": {
    "gn:admin1_code":"63",
    "gn:asciiname":"Khayyr",
    "gn:country_code":"RU",
    "gn:dem":14,
    "gn:feature_class":"P",
    "gn:feature_code":"PPL",
    "gn:name":"Khayyr",
    "gn:population":0,
    "gn:timezone":"Asia/Vladivostok",
    "iso:country":"RU",
    "name:eng_x_preferred":[
        "Khayyr"
    ],
    "name:nor_x_preferred":[
        "Khajyr"
    ],
    "name:rus_x_preferred":[
        "\u0425\u0430\u0439\u044b\u0440"
    ],
    "name:und_x_variant":[
        "Khair",
        "\u0425\u0430\u0439\u044b\u0440",
        "Khayyr"
    ],
    "wof:name":"Khayyr",
    "wof:placetype":"locality"
},
  "geometry": {"coordinates":[133.49997999999999,70.81376],"type":"Point"}
}