{
  "type": "Feature",
  "properties": {
    "gn:admin1_code":"76",
    "gn:asciiname":"Salamatovka",
    "gn:country_code":"RU",
    "gn:dem":205,
    "gn:feature_class":"P",
    "gn:feature_code":"PPL",
    "gn:name":"Salamatovka",
    "gn:population":0,
    "gn:timezone":"Europe/Moscow",
    "iso:country":"RU",
    "name:eng_x_preferred":[
        "Salamatovka"
    ],
    "name:nor_x_preferred":[
        "Salamatovka"
    ],
    "name:rus_x_preferred":[
        "\u0421\u0430\u043b\u0430\u043c\u0430\u0442\u043e\u0432\u043a\u0430"
    ],
    "wof:name":"Salamatovka",
    "wof:placetype":"locality"
},
  "geometry": {"coordinates":[38.71152,53.82674],"type":"Point"}
}