{
  "type": "Feature",
  "properties": {
    "gn:admin1_code":"63",
    "gn:asciiname":"Gidaybit",
    "gn:country_code":"RU",
    "gn:dem":155,
    "gn:feature_class":"P",
    "gn:feature_code":"PPL",
    "gn:name":"Gidaybit",
    "gn:population":0,
    "gn:timezone":"Asia/Yakutsk",
    "iso:country":"RU",
    "name:rus_x_preferred":[
        "\u0413\u0438\u0434\u0430\u0439\u0431\u0438\u0442"
    ],
    "wof:name":"Gidaybit",
    "wof:placetype":"locality"
},
  "geometry": {"coordinates":[118.40000000000001,63.71666999999999],"type":"Point"}
}