{
  "type": "Feature",
  "properties": {
    "gn:admin1_code":"16",
    "gn:asciiname":"Novoye Bakhtiyarovo",
    "gn:country_code":"RU",
    "gn:dem":93,
    "gn:feature_class":"P",
    "gn:feature_code":"PPL",
    "gn:name":"Novoye Bakhtiyarovo",
    "gn:population":0,
    "gn:timezone":"Europe/Moscow",
    "iso:country":"RU",
    "name:rus_x_preferred":[
        "\u041d\u043e\u0432\u043e\u0435 \u0411\u0430\u0445\u0442\u0438\u044f\u0440\u043e\u0432\u043e"
    ],
    "name:und_x_variant":[
        "\u041d\u043e\u0432\u043e\u0435 \u0411\u0430\u0445\u0442\u0438\u044f\u0440\u043e\u0432\u043e"
    ],
    "wof:name":"Novoye Bakhtiyarovo",
    "wof:placetype":"locality"
},
  "geometry": {"coordinates":[47.74778,55.08375],"type":"Point"}
}