{
  "type": "Feature",
  "properties": {
    "gn:admin1_code":"33",
    "gn:asciiname":"Zarechnyy",
    "gn:country_code":"RU",
    "gn:dem":83,
    "gn:feature_class":"P",
    "gn:feature_code":"PPL",
    "gn:name":"Zarechnyy",
    "gn:population":0,
    "gn:timezone":"Europe/Kirov",
    "iso:country":"RU",
    "name:eng_x_preferred":[
        "Zarechnyy"
    ],
    "name:nor_x_preferred":[
        "Zaretsjnyj"
    ],
    "name:rus_x_preferred":[
        "\u0417\u0430\u0440\u0435\u0447\u043d\u044b\u0439"
    ],
    "name:und_x_variant":[
        "Tsepochkinskiy Lesouchastok",
        "Zarechnyy"
    ],
    "wof:name":"Zarechnyy",
    "wof:placetype":"locality"
},
  "geometry": {"coordinates":[50.15102,57.19688000000001],"type":"Point"}
}