{
  "type": "Feature",
  "properties": {
    "gn:admin1_code":"28",
    "gn:asciiname":"Pirttipokh'ya",
    "gn:country_code":"RU",
    "gn:dem":95,
    "gn:feature_class":"P",
    "gn:feature_code":"PPL",
    "gn:name":"Pirttipokh\u2019ya",
    "gn:population":0,
    "gn:timezone":"Europe/Moscow",
    "iso:country":"RU",
    "name:fin_x_preferred":[
        "Pirttipohja"
    ],
    "name:rus_x_preferred":[
        "\u041f\u0438\u0440\u0442\u0442\u0438\u043f\u043e\u0445\u044c\u044f"
    ],
    "name:und_x_variant":[
        "Pirttipokh\u2019ya"
    ],
    "wof:name":"Pirttipokh'ya",
    "wof:placetype":"locality"
},
  "geometry": {"coordinates":[30.69752,61.96204],"type":"Point"}
}