{
  "type": "Feature",
  "properties": {
    "gn:admin1_code":"75",
    "gn:asciiname":"Bol'shoy Tatosh",
    "gn:country_code":"RU",
    "gn:dem":85,
    "gn:feature_class":"P",
    "gn:feature_code":"PPL",
    "gn:name":"Bol\u2019shoy Tatosh",
    "gn:population":0,
    "gn:timezone":"Asia/Tomsk",
    "iso:country":"RU",
    "name:rus_x_preferred":[
        "\u0411\u043e\u043b\u044c\u0448\u043e\u0439 \u0422\u0430\u0442\u043e\u0448"
    ],
    "name:und_x_variant":[
        "Bol\u2019shoy Tatosh"
    ],
    "wof:name":"Bol'shoy Tatosh",
    "wof:placetype":"locality"
},
  "geometry": {"coordinates":[83.46666999999999,57.61666999999999],"type":"Point"}
}