{
  "type": "Feature",
  "properties": {
    "gn:admin1_code":"8",
    "gn:asciiname":"Karamaly-Gubeyevo",
    "gn:country_code":"RU",
    "gn:dem":146,
    "gn:feature_class":"P",
    "gn:feature_code":"PPL",
    "gn:name":"Karamaly-Gubeyevo",
    "gn:population":0,
    "gn:timezone":"Asia/Yekaterinburg",
    "iso:country":"RU",
    "name:eng_x_preferred":[
        "Karamaly-Gubeyevo"
    ],
    "name:nor_x_preferred":[
        "Karamaly-Gubejevo"
    ],
    "name:rus_x_preferred":[
        "\u041a\u0430\u0440\u0430\u043c\u0430\u043b\u044b-\u0413\u0443\u0431\u0435\u0435\u0432\u043e"
    ],
    "name:und_x_variant":[
        "\u041a\u0430\u0440\u0430\u043c\u0430\u043b\u044b-\u0413\u0443\u0431\u0435\u0435\u0432\u043e",
        "Karamaly-Gubeyevo"
    ],
    "wof:name":"Karamaly-Gubeyevo",
    "wof:placetype":"locality"
},
  "geometry": {"coordinates":[54.06667,54.35],"type":"Point"}
}