{
  "type": "Feature",
  "properties": {
    "gn:admin1_code":"8",
    "gn:asciiname":"Safargulovo",
    "gn:country_code":"RU",
    "gn:dem":253,
    "gn:feature_class":"P",
    "gn:feature_code":"PPL",
    "gn:name":"Safargulovo",
    "gn:population":0,
    "gn:timezone":"Asia/Yekaterinburg",
    "iso:country":"RU",
    "name:bak_x_preferred":[
        "\u0421\u04d9\u0444\u04d9\u0440\u0493\u043e\u043b"
    ],
    "name:che_x_preferred":[
        "\u0421\u0430\u0444\u0430\u0440\u0433\u0443\u043b\u043e\u0432\u043e"
    ],
    "name:hye_x_preferred":[
        "\u054d\u0561\u0586\u0561\u0580\u0563\u0578\u0582\u056c\u0578\u057e\u0578"
    ],
    "name:kat_x_preferred":[
        "\u10e1\u10d0\u10e4\u10d0\u10e0\u10d2\u10e3\u10da\u10dd\u10d5\u10dd"
    ],
    "name:kaz_x_preferred":[
        "\u0421\u0430\u0444\u0430\u0440\u0433\u04af\u043b"
    ],
    "name:rus_x_preferred":[
        "\u0421\u0430\u0444\u0430\u0440\u0433\u0443\u043b\u043e\u0432\u043e"
    ],
    "name:tat_x_preferred":[
        "\u0421\u04d9\u0444\u04d9\u0440\u0433\u043e\u043b"
    ],
    "name:ukr_x_preferred":[
        "\u0421\u0430\u0444\u0430\u0440\u0433\u0443\u043b\u043e\u0432\u043e"
    ],
    "name:und_x_variant":[
        "\u0421\u0430\u0444\u0430\u0440\u0433\u0443\u043b\u043e\u0432\u043e"
    ],
    "wof:name":"Safargulovo",
    "wof:placetype":"locality"
},
  "geometry": {"coordinates":[57.6128,54.2464],"type":"Point"}
}