{
  "type": "Feature",
  "properties": {
    "gn:admin1_code":"8",
    "gn:asciiname":"Safargulovo",
    "gn:country_code":"RU",
    "gn:dem":253,
    "gn:feature_class":"P",
    "gn:feature_code":"PPL",
    "gn:name":"Safargulovo",
    "gn:population":0,
    "gn:timezone":"Asia/Yekaterinburg",
    "iso:country":"RU",
    "name:rus_x_preferred":[
        "\u0421\u0430\u0444\u0430\u0440\u0433\u0443\u043b\u043e\u0432\u043e"
    ],
    "name:und_x_variant":[
        "\u0421\u0430\u0444\u0430\u0440\u0433\u0443\u043b\u043e\u0432\u043e"
    ],
    "wof:name":"Safargulovo",
    "wof:placetype":"locality"
},
  "geometry": {"coordinates":[57.6128,54.2464],"type":"Point"}
}