{
  "type": "Feature",
  "properties": {
    "gn:country":"RU",
    "gn:fcode":"PPL",
    "gn:pop":491,
    "iso:country":"RU",
    "name:ceb_x_preferred":[
        "Baykal"
    ],
    "name:che_x_preferred":[
        "\u0411\u0430\u0439\u043a\u0430\u043b"
    ],
    "name:deu_x_preferred":[
        "Baikal"
    ],
    "name:eng_x_preferred":[
        "Baykal"
    ],
    "name:eng_x_variant":[
        "Baikal"
    ],
    "name:hye_x_preferred":[
        "\u0532\u0561\u0575\u056f\u0561\u056c"
    ],
    "name:ita_x_preferred":[
        "Bajkal"
    ],
    "name:lit_x_preferred":[
        "Baikalas"
    ],
    "name:nld_x_preferred":[
        "Baykal"
    ],
    "name:pol_x_preferred":[
        "Bajka\u0142"
    ],
    "name:rus_x_preferred":[
        "\u0411\u0430\u0439\u043a\u0430\u043b"
    ],
    "name:tgk_x_preferred":[
        "\u0411\u0430\u0439\u043a\u0430\u043b"
    ],
    "name:unk_x_variant":[
        "Baikal"
    ],
    "qs:name":"Baykal",
    "qs:photos_9r":0,
    "qs:photos_sr":0,
    "qs:pop_sr":"2",
    "wof:name":"Baykal",
    "wof:placetype":"locality",
    "wof:population":491
},
  "geometry": {"coordinates":[104.7894,51.8792],"type":"Point"}
}