{
  "type": "Feature",
  "properties": {
    "gn:admin1_code":"33.0",
    "gn:asciiname":"Shipitsyny",
    "gn:country_code":"RU",
    "gn:dem":111,
    "gn:feature_class":"P",
    "gn:feature_code":"PPL",
    "gn:name":"Shipitsyny",
    "gn:population":0,
    "gn:timezone":"Europe/Kirov",
    "iso:country":"RU",
    "name:rus_x_preferred":[
        "\u0428\u0438\u043f\u0438\u0446\u044b\u043d\u044b"
    ],
    "name:und_x_variant":[
        "Shipitsiny",
        "Shipitsyny",
        "\u0428\u0438\u043f\u0438\u0446\u044b\u043d\u044b"
    ],
    "wof:name":"Shipitsyny",
    "wof:placetype":"locality"
},
  "geometry": {"coordinates":[49.23339,58.47475],"type":"Point"}
}