{
  "type": "Feature",
  "properties": {
    "gn:admin1_code":"41.0",
    "gn:asciiname":"Krasnaya Step'",
    "gn:country_code":"RU",
    "gn:dem":181,
    "gn:feature_class":"P",
    "gn:feature_code":"PPL",
    "gn:name":"Krasnaya Step\u2019",
    "gn:population":0,
    "gn:timezone":"Europe/Moscow",
    "iso:country":"RU",
    "name:rus_x_preferred":[
        "\u041a\u0440\u0430\u0441\u043d\u0430\u044f \u0421\u0442\u0435\u043f\u044c"
    ],
    "name:und_x_variant":[
        "Krasnaya Step\u2019"
    ],
    "wof:name":"Krasnaya Step'",
    "wof:placetype":"locality"
},
  "geometry": {"coordinates":[36.73778,51.31389],"type":"Point"}
}