{
  "type": "Feature",
  "properties": {
    "gn:admin1_code":"56",
    "gn:asciiname":"Glinishche",
    "gn:country_code":"RU",
    "gn:dem":259,
    "gn:feature_class":"P",
    "gn:feature_code":"PPL",
    "gn:name":"Glinishche",
    "gn:population":0,
    "gn:timezone":"Europe/Moscow",
    "iso:country":"RU",
    "name:rus_x_preferred":[
        "\u0413\u043b\u0438\u043d\u0438\u0449\u0435"
    ],
    "name:und_x_variant":[
        "\u0413\u043b\u0438\u043d\u0438\u0449\u0435"
    ],
    "wof:name":"Glinishche",
    "wof:placetype":"locality"
},
  "geometry": {"coordinates":[37.12358,53.22479000000001],"type":"Point"}
}