{
  "type": "Feature",
  "properties": {
    "gn:admin1_code":"72",
    "gn:asciiname":"Shmarovka",
    "gn:country_code":"RU",
    "gn:dem":125,
    "gn:feature_class":"P",
    "gn:feature_code":"PPL",
    "gn:name":"Shmarovka",
    "gn:population":0,
    "gn:timezone":"Europe/Moscow",
    "iso:country":"RU",
    "name:rus_x_preferred":[
        "\u0428\u043c\u0430\u0440\u043e\u0432\u043a\u0430"
    ],
    "name:und_x_variant":[
        "\u0428\u043c\u0430\u0440\u043e\u0432\u043a\u0430"
    ],
    "wof:name":"Shmarovka",
    "wof:placetype":"locality"
},
  "geometry": {"coordinates":[40.6363,52.0271],"type":"Point"}
}