{
  "type": "Feature",
  "properties": {
    "gn:admin1_code":"83",
    "gn:asciiname":"Lepeshkino",
    "gn:country_code":"RU",
    "gn:dem":116,
    "gn:feature_class":"P",
    "gn:feature_code":"PPL",
    "gn:name":"Lep\u00ebshkino",
    "gn:population":0,
    "gn:timezone":"Europe/Moscow",
    "iso:country":"RU",
    "name:rus_x_preferred":[
        "\u041b\u0435\u043f\u0451\u0448\u043a\u0438\u043d\u043e"
    ],
    "name:und_x_variant":[
        "Lep\u00ebshkino",
        "\u041b\u0435\u043f\u0451\u0448\u043a\u0438\u043d\u043e"
    ],
    "wof:name":"Lepeshkino",
    "wof:placetype":"locality"
},
  "geometry": {"coordinates":[41.71048,56.26693],"type":"Point"}
}