{
  "type": "Feature",
  "properties": {
    "gn:admin1_code":"77",
    "gn:asciiname":"Kholmovo",
    "gn:country_code":"RU",
    "gn:dem":228,
    "gn:feature_class":"P",
    "gn:feature_code":"PPL",
    "gn:name":"Kholmovo",
    "gn:population":0,
    "gn:timezone":"Europe/Moscow",
    "iso:country":"RU",
    "name:rus_x_preferred":[
        "\u0425\u043e\u043b\u043c\u043e\u0432\u043e"
    ],
    "wof:name":"Kholmovo",
    "wof:placetype":"locality"
},
  "geometry": {"coordinates":[33.9582,56.51981],"type":"Point"}
}