{
  "type": "Feature",
  "properties": {
    "gn:admin1_code":"92",
    "gn:asciiname":"Moroshechnoye",
    "gn:country_code":"RU",
    "gn:dem":12,
    "gn:feature_class":"P",
    "gn:feature_code":"PPL",
    "gn:name":"Moroshechnoye",
    "gn:population":0,
    "gn:timezone":"Asia/Kamchatka",
    "iso:country":"RU",
    "name:eng_x_preferred":[
        "Moroshechnoye"
    ],
    "name:nor_x_preferred":[
        "Morosjetsjnoje"
    ],
    "name:rus_x_preferred":[
        "\u041c\u043e\u0440\u043e\u0448\u0435\u0447\u043d\u043e\u0435"
    ],
    "name:und_x_variant":[
        "Moroshechnoe",
        "Moroshechnoye",
        "\u041c\u043e\u0440\u043e\u0448\u0435\u0447\u043d\u043e\u0435"
    ],
    "wof:name":"Moroshechnoye",
    "wof:placetype":"locality"
},
  "geometry": {"coordinates":[156.22415000000001,56.3656],"type":"Point"}
}