{
  "type": "Feature",
  "properties": {
    "gn:admin1_code":"10",
    "gn:asciiname":"Nizhnyaya Zlobinka",
    "gn:country_code":"RU",
    "gn:dem":163,
    "gn:feature_class":"P",
    "gn:feature_code":"PPL",
    "gn:name":"Nizhnyaya Zlobinka",
    "gn:population":0,
    "gn:timezone":"Europe/Moscow",
    "iso:country":"RU",
    "name:rus_x_preferred":[
        "\u041d\u0438\u0436\u043d\u044f\u044f \u0417\u043b\u043e\u0431\u0438\u043d\u043a\u0430"
    ],
    "wof:name":"Nizhnyaya Zlobinka",
    "wof:placetype":"locality"
},
  "geometry": {"coordinates":[33.3511,52.8944],"type":"Point"}
}