{
  "type": "Feature",
  "properties": {
    "gn:admin1_code":"76",
    "gn:asciiname":"Ryazantsevo",
    "gn:country_code":"RU",
    "gn:dem":216,
    "gn:feature_class":"P",
    "gn:feature_code":"PPL",
    "gn:name":"Ryazantsevo",
    "gn:population":0,
    "gn:timezone":"Europe/Moscow",
    "iso:country":"RU",
    "name:rus_x_preferred":[
        "\u0420\u044f\u0437\u0430\u043d\u0446\u0435\u0432\u043e"
    ],
    "wof:name":"Ryazantsevo",
    "wof:placetype":"locality"
},
  "geometry": {"coordinates":[36.74959000000001,53.76606],"type":"Point"}
}