{
  "type": "Feature",
  "properties": {
    "gn:admin1_code":"71",
    "gn:asciiname":"Lesozavod",
    "gn:country_code":"RU",
    "gn:dem":193,
    "gn:feature_class":"P",
    "gn:feature_code":"PPL",
    "gn:name":"Lesozavod",
    "gn:population":0,
    "gn:timezone":"Asia/Yekaterinburg",
    "iso:country":"RU",
    "name:rus_x_preferred":[
        "\u041b\u0435\u0441\u043e\u0437\u0430\u0432\u043e\u0434"
    ],
    "wof:name":"Lesozavod",
    "wof:placetype":"locality"
},
  "geometry": {"coordinates":[61.4655,57.0731],"type":"Point"}
}