{
  "type": "Feature",
  "properties": {
    "gn:admin1_code":"42",
    "gn:admin2_code":"575409",
    "gn:asciiname":"Peregoroda",
    "gn:country_code":"RU",
    "gn:dem":172,
    "gn:feature_class":"P",
    "gn:feature_code":"PPL",
    "gn:name":"Peregoroda",
    "gn:population":0,
    "gn:timezone":"Europe/Moscow",
    "iso:country":"RU",
    "name:rus_x_preferred":[
        "\u041f\u0435\u0440\u0435\u0433\u043e\u0440\u043e\u0434\u0430"
    ],
    "name:und_x_variant":[
        "Peregorody",
        "Peregoroda"
    ],
    "wof:name":"Peregoroda",
    "wof:placetype":"locality"
},
  "geometry": {"coordinates":[35.3971,59.70399999999999],"type":"Point"}
}