{
  "type": "Feature",
  "properties": {
    "gn:admin1_code":"12.0",
    "gn:asciiname":"Bast-Khaykhi",
    "gn:country_code":"RU",
    "gn:dem":1323,
    "gn:feature_class":"P",
    "gn:feature_code":"PPL",
    "gn:name":"Bast-Khaykhi",
    "gn:population":0,
    "gn:timezone":"Europe/Moscow",
    "iso:country":"RU",
    "name:nor_x_preferred":[
        "Bast-Khajkhi"
    ],
    "name:rus_x_preferred":[
        "\u0411\u0430\u0441\u0442-\u0425\u0430\u0439\u0445\u0438"
    ],
    "wof:name":"Bast-Khaykhi",
    "wof:placetype":"locality"
},
  "geometry": {"coordinates":[45.41417,42.72056],"type":"Point"}
}