{
  "type": "Feature",
  "properties": {
    "gn:admin1_code":"12",
    "gn:asciiname":"Savel'yevskaya",
    "gn:country_code":"RU",
    "gn:dem":79,
    "gn:feature_class":"P",
    "gn:feature_code":"PPL",
    "gn:name":"Savel\u2019yevskaya",
    "gn:population":0,
    "gn:timezone":"Europe/Moscow",
    "iso:country":"RU",
    "name:che_x_preferred":[
        "Sovelevski"
    ],
    "name:che_x_variant":[
        "\u0421\u043e\u0432\u0435\u043b\u0435\u0432\u0441\u043a\u0438"
    ],
    "name:rus_x_preferred":[
        "\u0421\u0430\u0432\u0435\u043b\u044c\u0435\u0432\u0441\u043a\u0430\u044f"
    ],
    "name:rus_x_variant":[
        "Savel\u2019evskaja",
        "Sovel\u2019evskaja",
        "\u0421\u043e\u0432\u0435\u043b\u044c\u0435\u0432\u0441\u043a\u0430\u044f"
    ],
    "name:und_x_variant":[
        "Savel\u2019yevskaya"
    ],
    "wof:name":"Savel'yevskaya",
    "wof:placetype":"locality"
},
  "geometry": {"coordinates":[45.45759,43.63389],"type":"Point"}
}