{
  "type": "Feature",
  "properties": {
    "gn:admin1_code":"3",
    "gn:asciiname":"Shiverta",
    "gn:country_code":"RU",
    "gn:dem":1298,
    "gn:feature_class":"P",
    "gn:feature_code":"PPL",
    "gn:name":"Shiverta",
    "gn:population":0,
    "gn:timezone":"Asia/Omsk",
    "iso:country":"RU",
    "name:rus_x_preferred":[
        "\u0428\u0438\u0432\u0435\u0440\u0442\u0430"
    ],
    "name:und_x_variant":[
        "\u0428\u0438\u0432\u0435\u0440\u0442\u0430"
    ],
    "wof:name":"Shiverta",
    "wof:placetype":"locality"
},
  "geometry": {"coordinates":[84.90000000000001,50.75],"type":"Point"}
}