{
  "type": "Feature",
  "properties": {
    "gn:admin1_code":"4",
    "gn:asciiname":"Petrov Log",
    "gn:country_code":"RU",
    "gn:dem":225,
    "gn:feature_class":"P",
    "gn:feature_code":"PPL",
    "gn:name":"Petrov Log",
    "gn:population":0,
    "gn:timezone":"Asia/Barnaul",
    "iso:country":"RU",
    "name:rus_x_preferred":[
        "\u041f\u0435\u0442\u0440\u043e\u0432 \u041b\u043e\u0433"
    ],
    "wof:name":"Petrov Log",
    "wof:placetype":"locality"
},
  "geometry": {"coordinates":[83.1969,53.0762],"type":"Point"}
}