{
  "type": "Feature",
  "properties": {
    "gn:admin1_code":"83",
    "gn:asciiname":"Trushino",
    "gn:country_code":"RU",
    "gn:dem":117,
    "gn:feature_class":"P",
    "gn:feature_code":"PPL",
    "gn:name":"Trushino",
    "gn:population":0,
    "gn:timezone":"Europe/Moscow",
    "iso:country":"RU",
    "name:bak_x_preferred":[
        "\u0422\u0440\u0443\u0448\u0438\u043d"
    ],
    "name:che_x_preferred":[
        "\u0422\u0440\u0443\u0448\u0438\u043d\u043e"
    ],
    "name:hye_x_preferred":[
        "\u054f\u0580\u0578\u0582\u0577\u056b\u0576\u0578"
    ],
    "name:kaz_x_preferred":[
        "\u0422\u0440\u0443\u0448\u0438\u043d\u043e"
    ],
    "name:kir_x_preferred":[
        "\u0422\u0440\u0443\u0448\u0438\u043d\u043e"
    ],
    "name:rus_x_preferred":[
        "\u0422\u0440\u0443\u0448\u0438\u043d\u043e"
    ],
    "name:tat_x_preferred":[
        "\u0422\u0440\u0443\u0448\u0438\u043d\u043e"
    ],
    "name:ukr_x_preferred":[
        "\u0422\u0440\u0443\u0448\u0438\u043d\u043e"
    ],
    "wof:name":"Trushino",
    "wof:placetype":"locality"
},
  "geometry": {"coordinates":[40.71874,55.30991],"type":"Point"}
}