{
  "type": "Feature",
  "properties": {
    "gn:admin1_code":"20",
    "gn:asciiname":"Lyury",
    "gn:country_code":"RU",
    "gn:dem":618,
    "gn:feature_class":"P",
    "gn:feature_code":"PPL",
    "gn:name":"Lyury",
    "gn:population":0,
    "gn:timezone":"Asia/Irkutsk",
    "iso:country":"RU",
    "name:eng_x_preferred":[
        "Lyury"
    ],
    "name:nor_x_preferred":[
        "Ljury"
    ],
    "name:rus_x_preferred":[
        "\u041b\u044e\u0440\u044b"
    ],
    "wof:name":"Lyury",
    "wof:placetype":"locality"
},
  "geometry": {"coordinates":[105.4661,52.9996],"type":"Point"}
}