{
  "type": "Feature",
  "properties": {
    "gn:admin1_code":"4",
    "gn:asciiname":"Cherepanovskiy",
    "gn:cc2":"RU",
    "gn:country_code":"RU",
    "gn:dem":412,
    "gn:feature_class":"P",
    "gn:feature_code":"PPL",
    "gn:name":"Cherepanovskiy",
    "gn:population":0,
    "gn:timezone":"Asia/Barnaul",
    "iso:country":"RU",
    "name:eng_x_preferred":[
        "Cherepanovskiy"
    ],
    "name:nor_x_preferred":[
        "Tsjerepanovskij"
    ],
    "name:rus_x_preferred":[
        "\u0427\u0435\u0440\u0435\u043f\u0430\u043d\u043e\u0432\u0441\u043a\u0438\u0439"
    ],
    "name:und_x_variant":[
        "Cherepanovskoe",
        "Cherepanovka",
        "\u0427\u0435\u0440\u0435\u043f\u0430\u043d\u043e\u0432\u0441\u043a\u0438\u0439",
        "Cherepanovskiy"
    ],
    "wof:name":"Cherepanovskiy",
    "wof:placetype":"locality"
},
  "geometry": {"coordinates":[82.30806,51.19306],"type":"Point"}
}