{
  "type": "Feature",
  "properties": {
    "gn:admin1_code":"8",
    "gn:asciiname":"Ozerovka",
    "gn:country_code":"RU",
    "gn:dem":282,
    "gn:feature_class":"P",
    "gn:feature_code":"PPL",
    "gn:name":"Oz\u00ebrovka",
    "gn:population":0,
    "gn:timezone":"Asia/Yekaterinburg",
    "iso:country":"RU",
    "name:rus_x_preferred":[
        "\u041e\u0437\u0451\u0440\u043e\u0432\u043a\u0430"
    ],
    "name:und_x_variant":[
        "Oz\u00ebrovka",
        "\u041e\u0437\u0451\u0440\u043e\u0432\u043a\u0430"
    ],
    "wof:name":"Ozerovka",
    "wof:placetype":"locality"
},
  "geometry": {"coordinates":[54.05,53.78333000000001],"type":"Point"}
}