{
  "type": "Feature",
  "properties": {
    "gn:admin1_code":"85",
    "gn:asciiname":"Goncharka",
    "gn:country_code":"RU",
    "gn:dem":130,
    "gn:feature_class":"P",
    "gn:feature_code":"PPL",
    "gn:name":"Goncharka",
    "gn:population":0,
    "gn:timezone":"Europe/Moscow",
    "iso:country":"RU",
    "name:cat_x_preferred":[
        "Gontxarka"
    ],
    "name:che_x_preferred":[
        "\u0413\u043e\u043d\u0447\u0430\u0440\u043a\u0430"
    ],
    "name:hye_x_preferred":[
        "\u0533\u0578\u0576\u0579\u0561\u0580\u056f\u0561"
    ],
    "name:rus_x_preferred":[
        "\u0413\u043e\u043d\u0447\u0430\u0440\u043a\u0430"
    ],
    "name:spa_x_preferred":[
        "Goncharka"
    ],
    "name:ukr_x_preferred":[
        "\u0413\u043e\u043d\u0447\u0430\u0440\u043a\u0430"
    ],
    "name:und_x_variant":[
        "\u0413\u043e\u043d\u0447\u0430\u0440\u043a\u0430",
        "Roncharka"
    ],
    "wof:name":"Goncharka",
    "wof:placetype":"locality"
},
  "geometry": {"coordinates":[39.5201,59.3126],"type":"Point"}
}