{
  "type": "Feature",
  "properties": {
    "gn:admin1_code":"88",
    "gn:asciiname":"Kliny",
    "gn:country_code":"RU",
    "gn:dem":87,
    "gn:feature_class":"P",
    "gn:feature_code":"PPL",
    "gn:name":"Kliny",
    "gn:population":0,
    "gn:timezone":"Europe/Moscow",
    "iso:country":"RU",
    "name:fra_x_preferred":[
        "Kliny"
    ],
    "name:nor_x_preferred":[
        "Kliny"
    ],
    "name:pol_x_preferred":[
        "Kliny"
    ],
    "name:rus_x_preferred":[
        "\u041a\u043b\u0438\u043d\u044b"
    ],
    "name:srp_x_preferred":[
        "\u041a\u043b\u0438\u043d\u0438"
    ],
    "name:ukr_x_preferred":[
        "\u041a\u043b\u0456\u043d\u0438"
    ],
    "name:und_x_variant":[
        "Klin"
    ],
    "wof:name":"Kliny",
    "wof:placetype":"locality"
},
  "geometry": {"coordinates":[40.35016,57.86043000000001],"type":"Point"}
}