{
  "type": "Feature",
  "properties": {
    "gn:admin1_code":"63",
    "gn:asciiname":"Mooy-Bystybyt",
    "gn:cc2":"RU",
    "gn:country_code":"RU",
    "gn:dem":74,
    "gn:feature_class":"P",
    "gn:feature_code":"PPL",
    "gn:name":"Mooy-Bystybyt",
    "gn:population":0,
    "gn:timezone":"Asia/Vladivostok",
    "iso:country":"RU",
    "name:rus_x_preferred":[
        "\u041c\u043e\u043e\u0439-\u0411\u044b\u0441\u0442\u044b\u0431\u044b\u0442"
    ],
    "name:und_x_variant":[
        "Moy-Bysyta",
        "Moi Bysta",
        "Moy-Bysta",
        "Mooy-Bystybyt",
        "\u041c\u043e\u043e\u0439-\u0411\u044b\u0441\u0442\u044b\u0431\u044b\u0442"
    ],
    "wof:name":"Mooy-Bystybyt",
    "wof:placetype":"locality"
},
  "geometry": {"coordinates":[133.19999999999999,70.66667],"type":"Point"}
}