{
  "type": "Feature",
  "properties": {
    "gn:admin1_code":"8",
    "gn:asciiname":"Nizhniy Chat",
    "gn:country_code":"RU",
    "gn:dem":117,
    "gn:feature_class":"P",
    "gn:feature_code":"PPL",
    "gn:name":"Nizhniy Chat",
    "gn:population":0,
    "gn:timezone":"Asia/Yekaterinburg",
    "iso:country":"RU",
    "name:rus_x_preferred":[
        "\u041d\u0438\u0436\u043d\u0438\u0439 \u0427\u0430\u0442"
    ],
    "name:und_x_variant":[
        "Nizhneye Chatovo",
        "Nizhniy Chat"
    ],
    "wof:name":"Nizhniy Chat",
    "wof:placetype":"locality"
},
  "geometry": {"coordinates":[55.41059,56.0833],"type":"Point"}
}