{
  "type": "Feature",
  "properties": {
    "gn:admin1_code":"55",
    "gn:asciiname":"Saga",
    "gn:country_code":"RU",
    "gn:dem":227,
    "gn:feature_class":"P",
    "gn:feature_code":"PPL",
    "gn:name":"Saga",
    "gn:population":0,
    "gn:timezone":"Asia/Yekaterinburg",
    "iso:country":"RU",
    "name:rus_x_preferred":[
        "\u0421\u0430\u0433\u0430"
    ],
    "name:und_x_variant":[
        "\u0421\u0430\u0433\u0430"
    ],
    "wof:name":"Saga",
    "wof:placetype":"locality"
},
  "geometry": {"coordinates":[59.25,50.96667],"type":"Point"}
}