{
  "type": "Feature",
  "properties": {
    "gn:admin1_code":"37",
    "gn:asciiname":"Rubtsovo",
    "gn:country_code":"RU",
    "gn:dem":226,
    "gn:feature_class":"P",
    "gn:feature_code":"PPL",
    "gn:name":"Rubtsovo",
    "gn:population":0,
    "gn:timezone":"Europe/Moscow",
    "iso:country":"RU",
    "name:rus_x_preferred":[
        "\u0420\u0443\u0431\u0446\u043e\u0432\u043e"
    ],
    "name:und_x_variant":[
        "\u0420\u0443\u0431\u0446\u043e\u0432\u043e"
    ],
    "wof:name":"Rubtsovo",
    "wof:placetype":"locality"
},
  "geometry": {"coordinates":[43.43333,58.85],"type":"Point"}
}