{
  "type": "Feature",
  "properties": {
    "gn:admin1_code":"77.0",
    "gn:asciiname":"Chamerovo",
    "gn:country_code":"RU",
    "gn:dem":120,
    "gn:feature_class":"P",
    "gn:feature_code":"PPL",
    "gn:name":"Chamerovo",
    "gn:population":0,
    "gn:timezone":"Europe/Moscow",
    "iso:country":"RU",
    "name:eng_x_preferred":[
        "Chamerovo"
    ],
    "name:nor_x_preferred":[
        "Tsjamerovo"
    ],
    "name:rus_x_preferred":[
        "\u0427\u0430\u043c\u0435\u0440\u043e\u0432\u043e"
    ],
    "name:und_x_variant":[
        "Chamarovo",
        "\u0427\u0430\u043c\u0435\u0440\u043e\u0432\u043e",
        "Chamerovo"
    ],
    "wof:name":"Chamerovo",
    "wof:placetype":"locality"
},
  "geometry": {"coordinates":[37.37432,58.46653000000001],"type":"Point"}
}