{
  "type": "Feature",
  "properties": {
    "gn:admin1_code":"88",
    "gn:asciiname":"Pakhomovo",
    "gn:country_code":"RU",
    "gn:dem":140,
    "gn:feature_class":"P",
    "gn:feature_code":"PPL",
    "gn:name":"Pakhomovo",
    "gn:population":0,
    "gn:timezone":"Europe/Moscow",
    "iso:country":"RU",
    "name:rus_x_preferred":[
        "\u041f\u0430\u0445\u043e\u043c\u043e\u0432\u043e"
    ],
    "wof:name":"Pakhomovo",
    "wof:placetype":"locality"
},
  "geometry": {"coordinates":[39.09939,57.48737],"type":"Point"}
}