{
  "type": "Feature",
  "properties": {
    "gn:admin1_code":"33.0",
    "gn:asciiname":"Chigili",
    "gn:country_code":"RU",
    "gn:dem":124,
    "gn:feature_class":"P",
    "gn:feature_code":"PPL",
    "gn:name":"Chigili",
    "gn:population":0,
    "gn:timezone":"Europe/Kirov",
    "iso:country":"RU",
    "name:rus_x_preferred":[
        "\u0427\u0438\u0433\u0438\u043b\u0438"
    ],
    "name:und_x_variant":[
        "\u0427\u0438\u0433\u0438\u043b\u0438"
    ],
    "wof:name":"Chigili",
    "wof:placetype":"locality"
},
  "geometry": {"coordinates":[48.70083,58.30833000000001],"type":"Point"}
}