{
  "type": "Feature",
  "properties": {
    "gn:admin1_code":"45.0",
    "gn:asciiname":"Dubovaya",
    "gn:country_code":"RU",
    "gn:dem":145,
    "gn:feature_class":"P",
    "gn:feature_code":"PPL",
    "gn:name":"Dubovaya",
    "gn:population":0,
    "gn:timezone":"Europe/Moscow",
    "iso:country":"RU",
    "name:che_x_preferred":[
        "\u0414\u0443\u0431\u043e\u0432\u0438"
    ],
    "name:rus_x_preferred":[
        "\u0414\u0443\u0431\u043e\u0432\u0430\u044f"
    ],
    "name:und_x_variant":[
        "\u0414\u0443\u0431\u043e\u0432\u0430\u044f"
    ],
    "wof:name":"Dubovaya",
    "wof:placetype":"locality"
},
  "geometry": {"coordinates":[48.49389,56.26306],"type":"Point"}
}