{
  "type": "Feature",
  "properties": {
    "gn:admin1_code":"3",
    "gn:asciiname":"Terebety",
    "gn:country_code":"RU",
    "gn:dem":744,
    "gn:feature_class":"P",
    "gn:feature_code":"PPL",
    "gn:name":"Terebety",
    "gn:population":0,
    "gn:timezone":"Asia/Omsk",
    "iso:country":"RU",
    "wof:name":"Terebety",
    "wof:placetype":"locality"
},
  "geometry": {"coordinates":[86.68869000000002,50.34428],"type":"Point"}
}