{
  "type": "Feature",
  "properties": {
    "gn:admin1_code":"38",
    "gn:asciiname":"Novoselovskiy",
    "gn:country_code":"RU",
    "gn:dem":559,
    "gn:feature_class":"P",
    "gn:feature_code":"PPL",
    "gn:name":"Novos\u00eblovskiy",
    "gn:population":0,
    "gn:timezone":"Europe/Moscow",
    "iso:country":"RU",
    "wof:name":"Novoselovskiy",
    "wof:placetype":"locality"
},
  "geometry": {"coordinates":[41.29167,44.45333],"type":"Point"}
}