{
  "type": "Feature",
  "properties": {
    "gn:admin1_code":"34",
    "gn:asciiname":"Bol'shoye Noskovo",
    "gn:country_code":"RU",
    "gn:dem":111,
    "gn:feature_class":"P",
    "gn:feature_code":"PPL",
    "gn:name":"Bol\u2019shoye Noskovo",
    "gn:population":0,
    "gn:timezone":"Europe/Moscow",
    "iso:country":"RU",
    "name:rus_x_preferred":[
        "\u0411\u043e\u043b\u044c\u0448\u043ee \u041d\u043e\u0441\u043a\u043e\u0432\u043e"
    ],
    "name:und_x_variant":[
        "Bol\u2019shoye Noskovo",
        "\u0411\u043e\u043b\u044c\u0448\u043ee \u041d\u043e\u0441\u043a\u043e\u0432\u043e"
    ],
    "wof:name":"Bol'shoye Noskovo",
    "wof:placetype":"locality"
},
  "geometry": {"coordinates":[49.9862,61.0402],"type":"Point"}
}