{
  "type": "Feature",
  "properties": {
    "gn:admin1_code":"56",
    "gn:asciiname":"Massali",
    "gn:country_code":"RU",
    "gn:dem":185,
    "gn:feature_class":"P",
    "gn:feature_code":"PPL",
    "gn:name":"Massali",
    "gn:population":0,
    "gn:timezone":"Europe/Moscow",
    "iso:country":"RU",
    "name:rus_x_preferred":[
        "\u041c\u0430\u0441\u0441\u0430\u043b\u0438"
    ],
    "name:und_x_variant":[
        "Masali",
        "Massali",
        "\u041c\u0430\u0441\u0441\u0430\u043b\u0438"
    ],
    "wof:name":"Massali",
    "wof:placetype":"locality"
},
  "geometry": {"coordinates":[37.43652,52.79453],"type":"Point"}
}