{
  "type": "Feature",
  "properties": {
    "gn:admin1_code":"47",
    "gn:asciiname":"Lazarevo",
    "gn:country_code":"RU",
    "gn:dem":114,
    "gn:feature_class":"P",
    "gn:feature_code":"PPL",
    "gn:name":"Lazarevo",
    "gn:population":0,
    "gn:timezone":"Europe/Moscow",
    "iso:country":"RU",
    "name:rus_x_preferred":[
        "\u041b\u0430\u0437\u0430\u0440\u0435\u0432\u043e"
    ],
    "name:und_x_variant":[
        "\u041b\u0430\u0437\u0430\u0440\u0435\u0432\u043e"
    ],
    "wof:name":"Lazarevo",
    "wof:placetype":"locality"
},
  "geometry": {"coordinates":[39.30711,55.19003000000001],"type":"Point"}
}