{
  "type": "Feature",
  "properties": {
    "gn:admin1_code":"67.0",
    "gn:asciiname":"Chirikovo",
    "gn:country_code":"RU",
    "gn:dem":172,
    "gn:feature_class":"P",
    "gn:feature_code":"PPL",
    "gn:name":"Chirikovo",
    "gn:population":0,
    "gn:timezone":"Europe/Saratov",
    "iso:country":"RU",
    "name:rus_x_preferred":[
        "\u0427\u0438\u0440\u0438\u043a\u043e\u0432\u043e"
    ],
    "name:und_x_variant":[
        "Chirkovo",
        "Chirikovo"
    ],
    "wof:name":"Chirikovo",
    "wof:placetype":"locality"
},
  "geometry": {"coordinates":[43.2806,52.09882],"type":"Point"}
}