{
  "type": "Feature",
  "properties": {
    "gn:admin1_code":"69",
    "gn:asciiname":"Izborovo",
    "gn:country_code":"RU",
    "gn:dem":227,
    "gn:feature_class":"P",
    "gn:feature_code":"PPL",
    "gn:name":"Izborovo",
    "gn:population":0,
    "gn:timezone":"Europe/Moscow",
    "iso:country":"RU",
    "name:rus_x_preferred":[
        "\u0418\u0437\u0431\u043e\u0440\u043e\u0432\u043e"
    ],
    "wof:name":"Izborovo",
    "wof:placetype":"locality"
},
  "geometry": {"coordinates":[33.87748,55.06811999999999],"type":"Point"}
}