{
  "type": "Feature",
  "properties": {
    "gn:admin1_code":"05",
    "gn:asciiname":"Markuchi",
    "gn:country_code":"RU",
    "gn:dem":218,
    "gn:feature_class":"P",
    "gn:feature_code":"PPL",
    "gn:name":"Markuchi",
    "gn:population":0,
    "gn:timezone":"Asia/Yakutsk",
    "iso:country":"RU",
    "name:che_x_preferred":[
        "\u041c\u0430\u0440\u043a\u0443\u0447\u0438"
    ],
    "name:eng_x_preferred":[
        "Markuchi"
    ],
    "name:nor_x_preferred":[
        "Markutsji"
    ],
    "name:rus_x_preferred":[
        "\u041c\u0430\u0440\u043a\u0443\u0447\u0438"
    ],
    "name:und_x_variant":[
        "Markuchin",
        "Markuchi"
    ],
    "wof:name":"Markuchi",
    "wof:placetype":"locality"
},
  "geometry": {"coordinates":[127.70605,51.57614],"type":"Point"}
}