{
  "type": "Feature",
  "properties": {
    "gn:admin1_code":"24",
    "gn:asciiname":"Pervomayskoye",
    "gn:cc2":"RU",
    "gn:country_code":"RU",
    "gn:dem":60,
    "gn:feature_class":"P",
    "gn:feature_code":"PPL",
    "gn:name":"Pervomayskoye",
    "gn:population":0,
    "gn:timezone":"Europe/Moscow",
    "iso:country":"RU",
    "name:rus_x_preferred":[
        "\u041f\u0435\u0440\u0432\u043e\u043c\u0430\u0439\u0441\u043a\u043e\u0435"
    ],
    "name:und_x_variant":[
        "Abganery",
        "Pervomayskiy",
        "Pervomayskoye"
    ],
    "wof:name":"Pervomayskoye",
    "wof:placetype":"locality"
},
  "geometry": {"coordinates":[41.90167,46.10944],"type":"Point"}
}