{
  "type": "Feature",
  "properties": {
    "gn:admin1_code":"90",
    "gn:asciiname":"Pyzh'yanovo",
    "gn:country_code":"RU",
    "gn:dem":138,
    "gn:feature_class":"P",
    "gn:feature_code":"PPL",
    "gn:name":"Pyzh\u2019yanovo",
    "gn:population":0,
    "gn:timezone":"Asia/Yekaterinburg",
    "iso:country":"RU",
    "name:rus_x_preferred":[
        "\u041f\u044b\u0436\u044c\u044f\u043d\u043e\u0432\u043e"
    ],
    "name:und_x_variant":[
        "Pyzh\u2019yanovo"
    ],
    "wof:name":"Pyzh'yanovo",
    "wof:placetype":"locality"
},
  "geometry": {"coordinates":[57.506,57.3589],"type":"Point"}
}