{
  "type": "Feature",
  "properties": {
    "gn:admin1_code":"46",
    "gn:asciiname":"Kushki",
    "gn:country_code":"RU",
    "gn:dem":160,
    "gn:feature_class":"P",
    "gn:feature_code":"PPL",
    "gn:name":"Kushki",
    "gn:population":0,
    "gn:timezone":"Europe/Moscow",
    "iso:country":"RU",
    "name:eng_x_preferred":[
        "Kushki"
    ],
    "name:nor_x_preferred":[
        "Kusjki"
    ],
    "name:rus_x_preferred":[
        "\u041a\u0443\u0448\u043a\u0438"
    ],
    "wof:name":"Kushki",
    "wof:placetype":"locality"
},
  "geometry": {"coordinates":[43.27378,54.5014],"type":"Point"}
}