{
  "type": "Feature",
  "properties": {
    "gn:admin1_code":"4",
    "gn:asciiname":"Inyushevo",
    "gn:country_code":"RU",
    "gn:dem":148,
    "gn:feature_class":"P",
    "gn:feature_code":"PPL",
    "gn:name":"Inyushevo",
    "gn:population":0,
    "gn:timezone":"Asia/Barnaul",
    "iso:country":"RU",
    "name:eng_x_preferred":[
        "Inyushevo"
    ],
    "name:nor_x_preferred":[
        "Injusjevo"
    ],
    "name:rus_x_preferred":[
        "\u0418\u043d\u044e\u0448\u0435\u0432\u043e"
    ],
    "name:und_x_variant":[
        "\u0418\u043d\u044e\u0448\u0435\u0432\u043e",
        "Inyushevo"
    ],
    "wof:name":"Inyushevo",
    "wof:placetype":"locality"
},
  "geometry": {"coordinates":[83.89960000000001,53.9289],"type":"Point"}
}