{
  "type": "Feature",
  "properties": {
    "gn:admin1_code":"33",
    "gn:asciiname":"Slobodino",
    "gn:country_code":"RU",
    "gn:dem":131,
    "gn:feature_class":"P",
    "gn:feature_code":"PPL",
    "gn:name":"Slobodino",
    "gn:population":0,
    "gn:timezone":"Europe/Kirov",
    "iso:country":"RU",
    "name:eng_x_preferred":[
        "Slobodino"
    ],
    "name:nor_x_preferred":[
        "Slobodino"
    ],
    "name:rus_x_preferred":[
        "\u0421\u043b\u043e\u0431\u043e\u0434\u0438\u043d\u043e"
    ],
    "name:und_x_variant":[
        "Slobodina"
    ],
    "wof:name":"Slobodino",
    "wof:placetype":"locality"
},
  "geometry": {"coordinates":[49.55878,58.74916999999999],"type":"Point"}
}