{
  "type": "Feature",
  "properties": {
    "gn:admin1_code":"56",
    "gn:asciiname":"Yegurnovo",
    "gn:country_code":"RU",
    "gn:dem":172,
    "gn:feature_class":"P",
    "gn:feature_code":"PPL",
    "gn:name":"Yegurnovo",
    "gn:population":0,
    "gn:timezone":"Europe/Moscow",
    "iso:country":"RU",
    "name:rus_x_preferred":[
        "\u0415\u0433\u0443\u0440\u043d\u043e\u0432\u043e"
    ],
    "name:und_x_variant":[
        "\u0415\u0433\u0443\u0440\u043d\u043e\u0432\u043e"
    ],
    "wof:name":"Yegurnovo",
    "wof:placetype":"locality"
},
  "geometry": {"coordinates":[36.6764,52.3039],"type":"Point"}
}