{
  "type": "Feature",
  "properties": {
    "gn:admin1_code":"38",
    "gn:asciiname":"Kara-Kuban'",
    "gn:country_code":"RU",
    "gn:dem":0,
    "gn:feature_class":"P",
    "gn:feature_code":"PPL",
    "gn:name":"Kara-Kuban\u2019",
    "gn:population":0,
    "gn:timezone":"Europe/Moscow",
    "iso:country":"RU",
    "name:rus_x_preferred":[
        "\u041a\u0430\u0440\u0430-\u041a\u0443\u0431\u0430\u043d\u044c"
    ],
    "name:und_x_variant":[
        "Kara-Kuban\u2019",
        "\u041a\u0430\u0440\u0430-\u041a\u0443\u0431\u0430\u043d\u044c"
    ],
    "wof:name":"Kara-Kuban'",
    "wof:placetype":"locality"
},
  "geometry": {"coordinates":[38.1525,45.59361],"type":"Point"}
}