{
  "type": "Feature",
  "properties": {
    "gn:admin1_code":"70",
    "gn:asciiname":"Krupsko-Ul'yanovskiy",
    "gn:country_code":"RU",
    "gn:dem":295,
    "gn:feature_class":"P",
    "gn:feature_code":"PPL",
    "gn:name":"Krupsko-Ul\u2019yanovskiy",
    "gn:population":0,
    "gn:timezone":"Europe/Moscow",
    "iso:country":"RU",
    "name:rus_x_preferred":[
        "\u041a\u0440\u0443\u043f\u0441\u043a\u043e-\u0423\u043b\u044c\u044f\u043d\u043e\u0432\u0441\u043a\u0438\u0439"
    ],
    "name:und_x_variant":[
        "Krupsko-Ul\u2019yanovskiy"
    ],
    "wof:name":"Krupsko-Ul'yanovskiy",
    "wof:placetype":"locality"
},
  "geometry": {"coordinates":[43.71639,43.83722],"type":"Point"}
}