{
  "type": "Feature",
  "properties": {
    "gn:admin1_code":"38",
    "gn:asciiname":"Korzhevskiy",
    "gn:cc2":"RU",
    "gn:country_code":"RU",
    "gn:dem":12,
    "gn:feature_class":"P",
    "gn:feature_code":"PPL",
    "gn:name":"Korzhevskiy",
    "gn:population":0,
    "gn:timezone":"Europe/Moscow",
    "iso:country":"RU",
    "name:rus_x_preferred":[
        "\u041a\u043e\u0440\u0436\u0435\u0432\u0441\u043a\u0438\u0439"
    ],
    "name:und_x_variant":[
        "Novo-Korzhevskiye",
        "Korzhevskiy",
        "\u041a\u043e\u0440\u0436\u0435\u0432\u0441\u043a\u0438\u0439"
    ],
    "wof:name":"Korzhevskiy",
    "wof:placetype":"locality"
},
  "geometry": {"coordinates":[38.66667,45.36667],"type":"Point"}
}