{
  "type": "Feature",
  "properties": {
    "gn:admin1_code":"88",
    "gn:asciiname":"Pavlovo",
    "gn:country_code":"RU",
    "gn:dem":150,
    "gn:feature_class":"P",
    "gn:feature_code":"PPL",
    "gn:name":"Pavlovo",
    "gn:population":0,
    "gn:timezone":"Europe/Moscow",
    "iso:country":"RU",
    "name:rus_x_preferred":[
        "\u041f\u0430\u0432\u043b\u043e\u0432\u043e"
    ],
    "wof:name":"Pavlovo",
    "wof:placetype":"locality"
},
  "geometry": {"coordinates":[39.05677,57.2813],"type":"Point"}
}