{
  "type": "Feature",
  "properties": {
    "gn:admin1_code":"90.0",
    "gn:asciiname":"Chernukhi",
    "gn:country_code":"RU",
    "gn:dem":152,
    "gn:feature_class":"P",
    "gn:feature_code":"PPL",
    "gn:name":"Chernukhi",
    "gn:population":0,
    "gn:timezone":"Asia/Yekaterinburg",
    "iso:country":"RU",
    "name:eng_x_preferred":[
        "Chernukhi"
    ],
    "name:nor_x_preferred":[
        "Tsjernukhi"
    ],
    "name:rus_x_preferred":[
        "\u0427\u0435\u0440\u043d\u0443\u0445\u0438"
    ],
    "wof:name":"Chernukhi",
    "wof:placetype":"locality"
},
  "geometry": {"coordinates":[54.57945,57.29136999999999],"type":"Point"}
}