{
  "type": "Feature",
  "properties": {
    "gn:admin1_code":"86",
    "gn:asciiname":"Serdyuki",
    "gn:country_code":"RU",
    "gn:dem":115,
    "gn:feature_class":"P",
    "gn:feature_code":"PPL",
    "gn:name":"Serdyuki",
    "gn:population":0,
    "gn:timezone":"Europe/Moscow",
    "iso:country":"RU",
    "name:bak_x_preferred":[
        "\u0421\u0435\u0440\u0434\u044e\u043a\u0438"
    ],
    "name:che_x_preferred":[
        "\u0421\u0435\u0440\u0434\u044e\u043a\u0438"
    ],
    "name:hye_x_preferred":[
        "\u054d\u0565\u0580\u0564\u0575\u0578\u0582\u056f\u056b"
    ],
    "name:kaz_x_preferred":[
        "\u0421\u0435\u0440\u0434\u044e\u043a\u0438"
    ],
    "name:kir_x_preferred":[
        "\u0421\u0435\u0440\u0434\u044e\u043a\u0438"
    ],
    "name:rus_x_preferred":[
        "\u0421\u0435\u0440\u0434\u044e\u043a\u0438"
    ],
    "name:tat_x_preferred":[
        "\u0421\u0435\u0440\u0434\u044e\u043a\u0438"
    ],
    "name:ukr_x_preferred":[
        "\u0421\u0435\u0440\u0434\u044e\u043a\u0438"
    ],
    "wof:name":"Serdyuki",
    "wof:placetype":"locality"
},
  "geometry": {"coordinates":[38.64,51.042],"type":"Point"}
}