{
  "type": "Feature",
  "properties": {
    "gn:admin1_code":"91",
    "gn:asciiname":"Kononovskiy",
    "gn:country_code":"RU",
    "gn:dem":59,
    "gn:feature_class":"P",
    "gn:feature_code":"PPL",
    "gn:name":"Kononovskiy",
    "gn:population":0,
    "gn:timezone":"Asia/Krasnoyarsk",
    "iso:country":"RU",
    "name:rus_x_preferred":[
        "\u041a\u043e\u043d\u043e\u043d\u043e\u0432\u0441\u043a\u0438\u0439"
    ],
    "wof:name":"Kononovskiy",
    "wof:placetype":"locality"
},
  "geometry": {"coordinates":[100.83333,71.73333000000002],"type":"Point"}
}