{
  "type": "Feature",
  "properties": {
    "gn:admin1_code":"64",
    "gn:asciiname":"Mitsulevka",
    "gn:country_code":"RU",
    "gn:dem":12,
    "gn:feature_class":"P",
    "gn:feature_code":"PPL",
    "gn:name":"Mitsulevka",
    "gn:population":0,
    "gn:timezone":"Asia/Sakhalin",
    "iso:country":"RU",
    "name:eng_x_preferred":[
        "Mitsulevka"
    ],
    "name:nor_x_preferred":[
        "Mitsulevka"
    ],
    "name:rus_x_preferred":[
        "\u041c\u0438\u0446\u0443\u043b\u0435\u0432\u043a\u0430"
    ],
    "name:und_x_variant":[
        "Nakazato",
        "Mitsuriyofuka",
        "Mitsrevka",
        "Nakasata",
        "Nakasato"
    ],
    "wof:name":"Mitsulevka",
    "wof:placetype":"locality"
},
  "geometry": {"coordinates":[142.73369,46.80442],"type":"Point"}
}