{
  "type": "Feature",
  "properties": {
    "gn:asciiname":"Velikusha",
    "gn:country_code":"RU",
    "gn:dem":45,
    "gn:feature_class":"P",
    "gn:feature_code":"PPL",
    "gn:name":"Velikusha",
    "gn:population":0,
    "gn:timezone":"Europe/Moscow",
    "iso:country":"RU",
    "wof:name":"Velikusha",
    "wof:placetype":"locality"
},
  "geometry": {"coordinates":[27.81584,58.35131],"type":"Point"}
}