{
  "type": "Feature",
  "properties": {
    "gn:admin1_code":"56",
    "gn:asciiname":"Verkhniy Stish'",
    "gn:country_code":"RU",
    "gn:dem":196,
    "gn:feature_class":"P",
    "gn:feature_code":"PPL",
    "gn:name":"Verkhniy Stish\u2019",
    "gn:population":0,
    "gn:timezone":"Europe/Moscow",
    "iso:country":"RU",
    "name:rus_x_preferred":[
        "\u0412\u0435\u0440\u0445\u043d\u0438\u0439 \u0421\u0442\u0438\u0448\u044c"
    ],
    "name:und_x_variant":[
        "Verkhniy Stish\u2019",
        "\u0412\u0435\u0440\u0445\u043d\u0438\u0439 \u0421\u0442\u0438\u0448\u044c"
    ],
    "wof:name":"Verkhniy Stish'",
    "wof:placetype":"locality"
},
  "geometry": {"coordinates":[36.14825,52.81908000000001],"type":"Point"}
}