{
  "type": "Feature",
  "properties": {
    "gn:admin1_code":"21",
    "gn:asciiname":"Koromyslovo",
    "gn:country_code":"RU",
    "gn:dem":147,
    "gn:feature_class":"P",
    "gn:feature_code":"PPL",
    "gn:name":"Koromyslovo",
    "gn:population":0,
    "gn:timezone":"Europe/Moscow",
    "iso:country":"RU",
    "name:nor_x_preferred":[
        "Koromyslovo"
    ],
    "name:rus_x_preferred":[
        "\u041a\u043e\u0440\u043e\u043c\u044b\u0441\u043b\u043e\u0432\u043e"
    ],
    "wof:name":"Koromyslovo",
    "wof:placetype":"locality"
},
  "geometry": {"coordinates":[40.33113,57.20913],"type":"Point"}
}