{
  "type": "Feature",
  "properties": {
    "gn:admin1_code":"43",
    "gn:asciiname":"Panikovets",
    "gn:country_code":"RU",
    "gn:dem":144,
    "gn:feature_class":"P",
    "gn:feature_code":"PPL",
    "gn:name":"Panikovets",
    "gn:population":0,
    "gn:timezone":"Europe/Moscow",
    "iso:country":"RU",
    "name:eng_x_preferred":[
        "Panikovets"
    ],
    "name:nor_x_preferred":[
        "Panikovets"
    ],
    "name:rus_x_preferred":[
        "\u041f\u0430\u043d\u0438\u043a\u043e\u0432\u0435\u0446"
    ],
    "wof:name":"Panikovets",
    "wof:placetype":"locality"
},
  "geometry": {"coordinates":[38.36465,52.46862],"type":"Point"}
}