{
  "type": "Feature",
  "properties": {
    "gn:admin1_code":"77",
    "gn:asciiname":"Perekhozheye",
    "gn:country_code":"RU",
    "gn:dem":147,
    "gn:feature_class":"P",
    "gn:feature_code":"PPL",
    "gn:name":"Perekhozheye",
    "gn:population":0,
    "gn:timezone":"Europe/Moscow",
    "iso:country":"RU",
    "name:nor_x_preferred":[
        "Perekhozjeje"
    ],
    "name:rus_x_preferred":[
        "\u041f\u0435\u0440\u0435\u0445\u043e\u0436\u0435\u0435"
    ],
    "name:und_x_variant":[
        "Perekhozhaya",
        "Perekhozheye"
    ],
    "wof:name":"Perekhozheye",
    "wof:placetype":"locality"
},
  "geometry": {"coordinates":[35.38239,56.89539],"type":"Point"}
}