{
  "type": "Feature",
  "properties": {
    "gn:admin1_code":"61.0",
    "gn:asciiname":"Baklanovskaya",
    "gn:country_code":"RU",
    "gn:dem":73,
    "gn:feature_class":"P",
    "gn:feature_code":"PPL",
    "gn:name":"Baklanovskaya",
    "gn:population":0,
    "gn:timezone":"Europe/Moscow",
    "iso:country":"RU",
    "name:eng_x_preferred":[
        "Baklanovskaya"
    ],
    "name:nor_x_preferred":[
        "Baklanovskaja"
    ],
    "name:rus_x_preferred":[
        "\u0411\u0430\u043a\u043b\u0430\u043d\u043e\u0432\u0441\u043a\u0430\u044f"
    ],
    "name:und_x_variant":[
        "\u0411\u0430\u043a\u043b\u0430\u043d\u043e\u0432\u0441\u043a\u0430\u044f",
        "Baklanovskaya"
    ],
    "wof:name":"Baklanovskaya",
    "wof:placetype":"locality"
},
  "geometry": {"coordinates":[42.5827,47.6277],"type":"Point"}
}