{
  "type": "Feature",
  "properties": {
    "gn:admin1_code":"75",
    "gn:asciiname":"Ponomarevo",
    "gn:country_code":"RU",
    "gn:dem":141,
    "gn:feature_class":"P",
    "gn:feature_code":"PPL",
    "gn:name":"Ponomar\u00ebvo",
    "gn:population":0,
    "gn:timezone":"Asia/Tomsk",
    "iso:country":"RU",
    "name:rus_x_preferred":[
        "\u041f\u043e\u043d\u043e\u043c\u0430\u0440\u0451\u0432\u043e"
    ],
    "name:und_x_variant":[
        "Ponomar\u00ebvo",
        "\u041f\u043e\u043d\u043e\u043c\u0430\u0440\u0451\u0432\u043e"
    ],
    "wof:name":"Ponomarevo",
    "wof:placetype":"locality"
},
  "geometry": {"coordinates":[79.71666999999999,57.31667],"type":"Point"}
}