{
  "type": "Feature",
  "properties": {
    "gn:admin1_code":"45",
    "gn:asciiname":"Apshak-Pelyak",
    "gn:country_code":"RU",
    "gn:dem":141,
    "gn:feature_class":"P",
    "gn:feature_code":"PPL",
    "gn:name":"Apshak-Pelyak",
    "gn:population":0,
    "gn:timezone":"Europe/Moscow",
    "iso:country":"RU",
    "name:rus_x_preferred":[
        "\u0410\u043f\u0448\u0430\u043a-\u041f\u0435\u043b\u044f\u043a"
    ],
    "name:und_x_variant":[
        "\u0410\u043f\u0448\u0430\u043a-\u041f\u0435\u043b\u044f\u043a"
    ],
    "wof:name":"Apshak-Pelyak",
    "wof:placetype":"locality"
},
  "geometry": {"coordinates":[46.7034,56.177],"type":"Point"}
}