{
  "type": "Feature",
  "properties": {
    "gn:admin1_code":"52",
    "gn:asciiname":"Pakhino",
    "gn:country_code":"RU",
    "gn:dem":72,
    "gn:feature_class":"P",
    "gn:feature_code":"PPL",
    "gn:name":"Pakhino",
    "gn:population":0,
    "gn:timezone":"Europe/Moscow",
    "iso:country":"RU",
    "name:rus_x_preferred":[
        "\u041f\u0430\u0445\u0438\u043d\u043e"
    ],
    "wof:name":"Pakhino",
    "wof:placetype":"locality"
},
  "geometry": {"coordinates":[32.1151,57.6605],"type":"Point"}
}