{
  "type": "Feature",
  "properties": {
    "gn:admin1_code":"51",
    "gn:asciiname":"Kruglaya",
    "gn:country_code":"RU",
    "gn:dem":130,
    "gn:feature_class":"P",
    "gn:feature_code":"PPL",
    "gn:name":"Kruglaya",
    "gn:population":0,
    "gn:timezone":"Europe/Moscow",
    "iso:country":"RU",
    "name:rus_x_preferred":[
        "\u041a\u0440\u0443\u0433\u043b\u0430\u044f"
    ],
    "wof:name":"Kruglaya",
    "wof:placetype":"locality"
},
  "geometry": {"coordinates":[45.3334,57.9462],"type":"Point"}
}