{
  "type": "Feature",
  "properties": {
    "gn:admin1_code":"16",
    "gn:asciiname":"Novyye Vyselki",
    "gn:country_code":"RU",
    "gn:dem":174,
    "gn:feature_class":"P",
    "gn:feature_code":"PPL",
    "gn:name":"Novyye Vyselki",
    "gn:population":0,
    "gn:timezone":"Europe/Moscow",
    "iso:country":"RU",
    "name:rus_x_preferred":[
        "\u041d\u043e\u0432\u044b\u0435 \u0412\u044b\u0441\u0435\u043b\u043a\u0438"
    ],
    "wof:name":"Novyye Vyselki",
    "wof:placetype":"locality"
},
  "geometry": {"coordinates":[47.11418,54.9862],"type":"Point"}
}