{
  "type": "Feature",
  "properties": {
    "gn:admin1_code":"85",
    "gn:asciiname":"Rodionovo",
    "gn:country_code":"RU",
    "gn:dem":135,
    "gn:feature_class":"P",
    "gn:feature_code":"PPL",
    "gn:name":"Rodionovo",
    "gn:population":0,
    "gn:timezone":"Europe/Moscow",
    "iso:country":"RU",
    "name:rus_x_preferred":[
        "\u0420\u043e\u0434\u0438\u043e\u043d\u043e\u0432\u043e"
    ],
    "wof:name":"Rodionovo",
    "wof:placetype":"locality"
},
  "geometry": {"coordinates":[39.3421,59.8525],"type":"Point"}
}