{
  "type": "Feature",
  "properties": {
    "gn:admin1_code":"42",
    "gn:asciiname":"Osiyevshchina",
    "gn:country_code":"RU",
    "gn:dem":38,
    "gn:feature_class":"P",
    "gn:feature_code":"PPL",
    "gn:name":"Osiyevshchina",
    "gn:population":0,
    "gn:timezone":"Europe/Moscow",
    "iso:country":"RU",
    "name:rus_x_preferred":[
        "\u041e\u0441\u0438\u0435\u0432\u0449\u0438\u043d\u0430"
    ],
    "wof:name":"Osiyevshchina",
    "wof:placetype":"locality"
},
  "geometry": {"coordinates":[33.91667,60.98333],"type":"Point"}
}