{
  "type": "Feature",
  "properties": {
    "gn:admin1_code":"76",
    "gn:asciiname":"Naberezhnoye",
    "gn:country_code":"RU",
    "gn:dem":167,
    "gn:feature_class":"P",
    "gn:feature_code":"PPL",
    "gn:name":"Naberezhnoye",
    "gn:population":0,
    "gn:timezone":"Europe/Moscow",
    "iso:country":"RU",
    "name:rus_x_preferred":[
        "\u041d\u0430\u0431\u0435\u0440\u0435\u0436\u043d\u043e\u0435"
    ],
    "name:und_x_variant":[
        "Naberezhnaya",
        "Naberezhnoye"
    ],
    "wof:name":"Naberezhnoye",
    "wof:placetype":"locality"
},
  "geometry": {"coordinates":[38.43485,53.56184],"type":"Point"}
}