{
  "type": "Feature",
  "properties": {
    "gn:admin1_code":"8",
    "gn:asciiname":"Il'ich",
    "gn:country_code":"RU",
    "gn:dem":305,
    "gn:feature_class":"P",
    "gn:feature_code":"PPL",
    "gn:name":"Il\u2019ich",
    "gn:population":0,
    "gn:timezone":"Asia/Yekaterinburg",
    "iso:country":"RU",
    "name:rus_x_preferred":[
        "\u0418\u043b\u044c\u0438\u0447"
    ],
    "name:und_x_variant":[
        "Il\u2019ich"
    ],
    "wof:name":"Il'ich",
    "wof:placetype":"locality"
},
  "geometry": {"coordinates":[54.63333000000001,53.48333],"type":"Point"}
}