{
  "type": "Feature",
  "properties": {
    "gn:country":"RU",
    "gn:fcode":"PPL",
    "gn:pop":2973,
    "iso:country":"RU",
    "name:che_x_preferred":[
        "\u0418\u043b\u044c\u0438\u043d\u0441\u043a\u043e-\u041f\u043e\u0434\u043e\u043c\u0441\u043a\u043e\u0435"
    ],
    "name:dut_x_preferred":[
        "Ilinsko-Podomskoe"
    ],
    "name:eng_x_preferred":[
        "Il'insko-Podomskoye"
    ],
    "name:fin_x_preferred":[
        "Iljinsko-Podomskoje"
    ],
    "name:ger_x_preferred":[
        "Iljinsko-Podomskoje"
    ],
    "name:hun_x_preferred":[
        "Iljinszko-Podomszkoje"
    ],
    "name:ita_x_preferred":[
        "Il'insko-Podomskoe"
    ],
    "name:nno_x_preferred":[
        "Ilinsko-Podomskoje"
    ],
    "name:nob_x_preferred":[
        "Ilinsko-Podomskoje"
    ],
    "name:nor_x_preferred":[
        "Ilinsko-Podomskoje"
    ],
    "name:rus_x_preferred":[
        "\u0418\u043b\u044c\u0438\u043d\u0441\u043a\u043e-\u041f\u043e\u0434\u043e\u043c\u0441\u043a\u043e\u0435"
    ],
    "name:tgk_x_preferred":[
        "\u0418\u043b\u0438\u043d\u0441\u043a\u043e-\u041f\u043e\u0434\u043e\u043c\u0441\u043a\u043e\u0435"
    ],
    "name:unk_x_variant":[
        "Il\u2019inskoye"
    ],
    "qs:name":"Il\u2019insko-Podomskoye",
    "qs:photos_9r":0,
    "qs:photos_sr":0,
    "qs:pop_sr":"4",
    "wof:name":"Il\u2019insko-Podomskoye",
    "wof:placetype":"locality",
    "wof:population":2973
},
  "geometry": {"coordinates":[47.97861,61.11444],"type":"Point"}
}