{
  "type": "Feature",
  "properties": {
    "gn:admin1_code":"77",
    "gn:asciiname":"Rashkino",
    "gn:country_code":"RU",
    "gn:dem":209,
    "gn:feature_class":"P",
    "gn:feature_code":"PPL",
    "gn:name":"Rashkino",
    "gn:population":0,
    "gn:timezone":"Europe/Moscow",
    "iso:country":"RU",
    "name:rus_x_preferred":[
        "\u0420\u0430\u0448\u043a\u0438\u043d\u043e"
    ],
    "name:und_x_variant":[
        "\u0420\u0430\u0448\u043a\u0438\u043d\u043e"
    ],
    "wof:name":"Rashkino",
    "wof:placetype":"locality"
},
  "geometry": {"coordinates":[34.64928,56.99274000000001],"type":"Point"}
}