{
  "type": "Feature",
  "properties": {
    "gn:admin1_code":"20",
    "gn:asciiname":"Zarechnoye",
    "gn:country_code":"RU",
    "gn:dem":530,
    "gn:feature_class":"P",
    "gn:feature_code":"PPL",
    "gn:name":"Zarechnoye",
    "gn:population":0,
    "gn:timezone":"Asia/Irkutsk",
    "iso:country":"RU",
    "name:rus_x_preferred":[
        "\u0417\u0430\u0440\u0435\u0447\u043d\u043e\u0435"
    ],
    "name:und_x_variant":[
        "Zarechnyy",
        "Zarechnoye"
    ],
    "wof:name":"Zarechnoye",
    "wof:placetype":"locality"
},
  "geometry": {"coordinates":[102.6377,53.1657],"type":"Point"}
}