{
  "type": "Feature",
  "properties": {
    "gn:admin1_code":"52.0",
    "gn:asciiname":"Desyatiny",
    "gn:country_code":"RU",
    "gn:dem":26,
    "gn:feature_class":"P",
    "gn:feature_code":"PPL",
    "gn:name":"Desyatiny",
    "gn:population":0,
    "gn:timezone":"Europe/Moscow",
    "iso:country":"RU",
    "name:rus_x_preferred":[
        "\u0414\u0435\u0441\u044f\u0442\u0438\u043d\u044b"
    ],
    "wof:name":"Desyatiny",
    "wof:placetype":"locality"
},
  "geometry": {"coordinates":[31.16409,58.36435],"type":"Point"}
}