{
  "type": "Feature",
  "properties": {
    "gn:admin1_code":"56",
    "gn:asciiname":"Plotavka",
    "gn:country_code":"RU",
    "gn:dem":177,
    "gn:feature_class":"P",
    "gn:feature_code":"PPL",
    "gn:name":"Plotavka",
    "gn:population":0,
    "gn:timezone":"Europe/Moscow",
    "iso:country":"RU",
    "name:rus_x_preferred":[
        "\u041f\u043b\u043e\u0442\u0430\u0432\u043a\u0430"
    ],
    "wof:name":"Plotavka",
    "wof:placetype":"locality"
},
  "geometry": {"coordinates":[37.44481,52.79357],"type":"Point"}
}