{
  "type": "Feature",
  "properties": {
    "gn:admin1_code":"33",
    "gn:asciiname":"Dymkovo",
    "gn:country_code":"RU",
    "gn:dem":112,
    "gn:feature_class":"P",
    "gn:feature_code":"PPL",
    "gn:name":"Dymkovo",
    "gn:population":0,
    "gn:timezone":"Europe/Kirov",
    "iso:country":"RU",
    "name:rus_x_preferred":[
        "\u0414\u044b\u043c\u043a\u043e\u0432\u043e"
    ],
    "wof:name":"Dymkovo",
    "wof:placetype":"locality"
},
  "geometry": {"coordinates":[50.3962,57.6392],"type":"Point"}
}