{
  "type": "Feature",
  "properties": {
    "gn:admin1_code":"77",
    "gn:asciiname":"Gorbylevka",
    "gn:cc2":"RU",
    "gn:country_code":"RU",
    "gn:dem":201,
    "gn:feature_class":"P",
    "gn:feature_code":"PPL",
    "gn:name":"Gorbyl\u00ebvka",
    "gn:population":0,
    "gn:timezone":"Europe/Moscow",
    "iso:country":"RU",
    "name:rus_x_preferred":[
        "\u0413\u043e\u0440\u0431\u044b\u043b\u0451\u0432\u043a\u0430"
    ],
    "name:und_x_variant":[
        "Gorbylevo",
        "Gorbyl\u00ebvka"
    ],
    "wof:name":"Gorbylevka",
    "wof:placetype":"locality"
},
  "geometry": {"coordinates":[33.02333,56.01639],"type":"Point"}
}