{
  "type": "Feature",
  "properties": {
    "gn:admin1_code":"77",
    "gn:asciiname":"Baranovka",
    "gn:country_code":"RU",
    "gn:dem":186,
    "gn:feature_class":"P",
    "gn:feature_code":"PPL",
    "gn:name":"Baranovka",
    "gn:population":0,
    "gn:timezone":"Europe/Moscow",
    "iso:country":"RU",
    "name:eng_x_preferred":[
        "Baranovka"
    ],
    "name:nor_x_preferred":[
        "Baranovka"
    ],
    "name:rus_x_preferred":[
        "\u0411\u0430\u0440\u0430\u043d\u043e\u0432\u043a\u0430"
    ],
    "name:und_x_variant":[
        "\u0411\u0430\u0440\u0430\u043d\u043e\u0432\u043a\u0430",
        "Baranovka"
    ],
    "wof:name":"Baranovka",
    "wof:placetype":"locality"
},
  "geometry": {"coordinates":[35.33580999999999,57.2053],"type":"Point"}
}