{
  "type": "Feature",
  "properties": {
    "gn:admin1_code":"43.0",
    "gn:asciiname":"Bol'shiye Butyrki",
    "gn:country_code":"RU",
    "gn:dem":201,
    "gn:feature_class":"P",
    "gn:feature_code":"PPL",
    "gn:name":"Bol\u2019shiye Butyrki",
    "gn:population":0,
    "gn:timezone":"Europe/Moscow",
    "iso:country":"RU",
    "name:rus_x_preferred":[
        "\u0411\u043e\u043b\u044c\u0448\u0438\u0435 \u0411\u0443\u0442\u044b\u0440\u043a\u0438"
    ],
    "name:und_x_variant":[
        "Bol\u2019shiye Butyrki"
    ],
    "wof:name":"Bol'shiye Butyrki",
    "wof:placetype":"locality"
},
  "geometry": {"coordinates":[37.96556,52.94556],"type":"Point"}
}