{
  "type": "Feature",
  "properties": {
    "gn:admin1_code":"77.0",
    "gn:asciiname":"Bol'shoye Yakshino",
    "gn:country_code":"RU",
    "gn:dem":232,
    "gn:feature_class":"P",
    "gn:feature_code":"PPL",
    "gn:name":"Bol\u2019shoye Yakshino",
    "gn:population":0,
    "gn:timezone":"Europe/Moscow",
    "iso:country":"RU",
    "name:rus_x_preferred":[
        "\u0411\u043e\u043b\u044c\u0448\u043e\u0435 \u042f\u043a\u0448\u0438\u043d\u043e"
    ],
    "name:und_x_variant":[
        "Bol\u2019shoye Yakshino"
    ],
    "wof:name":"Bol'shoye Yakshino",
    "wof:placetype":"locality"
},
  "geometry": {"coordinates":[33.39045,56.6746],"type":"Point"}
}