{
  "type": "Feature",
  "properties": {
    "gn:admin1_code":"88.0",
    "gn:asciiname":"Pochinok-Usanov",
    "gn:country_code":"RU",
    "gn:dem":93,
    "gn:feature_class":"P",
    "gn:feature_code":"PPL",
    "gn:name":"Pochinok-Usanov",
    "gn:population":0,
    "gn:timezone":"Europe/Moscow",
    "iso:country":"RU",
    "name:rus_x_preferred":[
        "\u041f\u043e\u0447\u0438\u043d\u043e\u043a-\u0423\u0441\u0430\u043d\u043e\u0432"
    ],
    "name:und_x_variant":[
        "\u041f\u043e\u0447\u0438\u043d\u043e\u043a-\u0423\u0441\u0430\u043d\u043e\u0432"
    ],
    "wof:name":"Pochinok-Usanov",
    "wof:placetype":"locality"
},
  "geometry": {"coordinates":[40.89838,58.19985],"type":"Point"}
}