{
  "type": "Feature",
  "properties": {
    "gn:admin1_code":"55.0",
    "gn:asciiname":"Aul",
    "gn:country_code":"RU",
    "gn:dem":219,
    "gn:feature_class":"P",
    "gn:feature_code":"PPL",
    "gn:name":"Aul",
    "gn:population":0,
    "gn:timezone":"Asia/Yekaterinburg",
    "iso:country":"RU",
    "name:nor_x_preferred":[
        "Aul"
    ],
    "name:rus_x_preferred":[
        "\u0410\u0443\u043b"
    ],
    "wof:name":"Aul",
    "wof:placetype":"locality"
},
  "geometry": {"coordinates":[55.91667,51.06667],"type":"Point"}
}