{
  "type": "Feature",
  "properties": {
    "gn:admin1_code":"90",
    "gn:asciiname":"Mikhanyata",
    "gn:country_code":"RU",
    "gn:dem":258,
    "gn:feature_class":"P",
    "gn:feature_code":"PPL",
    "gn:name":"Mikhanyata",
    "gn:population":0,
    "gn:timezone":"Asia/Yekaterinburg",
    "iso:country":"RU",
    "name:rus_x_preferred":[
        "\u041c\u0438\u0445\u0430\u043d\u044f\u0442\u0430"
    ],
    "name:und_x_variant":[
        "\u041c\u0438\u0445\u0430\u043d\u044f\u0442\u0430"
    ],
    "wof:name":"Mikhanyata",
    "wof:placetype":"locality"
},
  "geometry": {"coordinates":[57.1251,57.1508],"type":"Point"}
}