{
  "type": "Feature",
  "properties": {
    "gn:admin1_code":"63",
    "gn:asciiname":"Khara-Sele-Terde",
    "gn:country_code":"RU",
    "gn:dem":531,
    "gn:feature_class":"P",
    "gn:feature_code":"PPL",
    "gn:name":"Khara-Sele-Terde",
    "gn:population":0,
    "gn:timezone":"Asia/Vladivostok",
    "iso:country":"RU",
    "name:rus_x_preferred":[
        "\u0425\u0430\u0440\u0430-\u0421\u0435\u043b\u0435-\u0422\u0435\u0440\u0434\u0435"
    ],
    "name:und_x_variant":[
        "\u0425\u0430\u0440\u0430-\u0421\u0435\u043b\u0435-\u0422\u0435\u0440\u0434\u0435"
    ],
    "wof:name":"Khara-Sele-Terde",
    "wof:placetype":"locality"
},
  "geometry": {"coordinates":[138.03333000000001,66.78333000000001],"type":"Point"}
}