{
  "type": "Feature",
  "properties": {
    "gn:admin1_code":"61",
    "gn:asciiname":"Kuzhnoy",
    "gn:country_code":"RU",
    "gn:dem":83,
    "gn:feature_class":"P",
    "gn:feature_code":"PPL",
    "gn:name":"Kuzhnoy",
    "gn:population":0,
    "gn:timezone":"Europe/Moscow",
    "iso:country":"RU",
    "name:rus_x_preferred":[
        "\u041a\u0443\u0436\u043d\u043e\u0439"
    ],
    "wof:name":"Kuzhnoy",
    "wof:placetype":"locality"
},
  "geometry": {"coordinates":[41.97611,49.17028],"type":"Point"}
}