{
  "type": "Feature",
  "properties": {
    "gn:admin1_code":"90",
    "gn:asciiname":"Kostoryata",
    "gn:country_code":"RU",
    "gn:dem":126,
    "gn:feature_class":"P",
    "gn:feature_code":"PPL",
    "gn:name":"Kostoryata",
    "gn:population":0,
    "gn:timezone":"Asia/Yekaterinburg",
    "iso:country":"RU",
    "name:rus_x_preferred":[
        "\u041a\u043e\u0441\u0442\u043e\u0440\u044f\u0442\u0430"
    ],
    "name:und_x_variant":[
        "\u041a\u043e\u0441\u0442\u043e\u0440\u044f\u0442\u0430"
    ],
    "wof:name":"Kostoryata",
    "wof:placetype":"locality"
},
  "geometry": {"coordinates":[56.333,57.9165],"type":"Point"}
}