{
  "type": "Feature",
  "properties": {
    "gn:admin1_code":"33",
    "gn:asciiname":"Udel'noye",
    "gn:country_code":"RU",
    "gn:dem":95,
    "gn:feature_class":"P",
    "gn:feature_code":"PPL",
    "gn:name":"Udel\u2019noye",
    "gn:population":0,
    "gn:timezone":"Europe/Kirov",
    "iso:country":"RU",
    "name:rus_x_preferred":[
        "\u0423\u0434\u0435\u043b\u044c\u043d\u043e\u0435"
    ],
    "name:und_x_variant":[
        "Udel\u2019noye"
    ],
    "wof:name":"Udel'noye",
    "wof:placetype":"locality"
},
  "geometry": {"coordinates":[49.6394,57.5247],"type":"Point"}
}