{
  "type": "Feature",
  "properties": {
    "gn:admin1_code":"90",
    "gn:asciiname":"Kolvinets",
    "gn:country_code":"RU",
    "gn:dem":218,
    "gn:feature_class":"P",
    "gn:feature_code":"PPL",
    "gn:name":"Kolvinets",
    "gn:population":0,
    "gn:timezone":"Asia/Yekaterinburg",
    "iso:country":"RU",
    "name:eng_x_preferred":[
        "Kolvinets"
    ],
    "name:nor_x_preferred":[
        "Kolvinets"
    ],
    "name:rus_x_preferred":[
        "\u041a\u043e\u043b\u0432\u0438\u043d\u0435\u0446"
    ],
    "name:und_x_variant":[
        "\u041a\u043e\u043b\u0432\u0438\u043d\u0435\u0446"
    ],
    "wof:name":"Kolvinets",
    "wof:placetype":"locality"
},
  "geometry": {"coordinates":[56.79398000000001,60.727],"type":"Point"}
}