{
  "type": "Feature",
  "properties": {
    "gn:admin1_code":"49.0",
    "gn:asciiname":"Chudz'yavr",
    "gn:country_code":"RU",
    "gn:dem":200,
    "gn:feature_class":"P",
    "gn:feature_code":"PPL",
    "gn:name":"Chudz\u2019yavr",
    "gn:population":0,
    "gn:timezone":"Europe/Moscow",
    "iso:country":"RU",
    "name:rus_x_preferred":[
        "\u0427\u0443\u0434\u0437\u044c\u044f\u0432\u0440"
    ],
    "name:und_x_variant":[
        "Chudz\u2019yarvi",
        "Chudz\u2019yavr"
    ],
    "wof:name":"Chudz'yavr",
    "wof:placetype":"locality"
},
  "geometry": {"coordinates":[34.33333,68.26666999999999],"type":"Point"}
}