{
  "type": "Feature",
  "properties": {
    "gn:admin1_code":"6",
    "gn:asciiname":"Samsonovskaya Pravyy Bereg",
    "gn:country_code":"RU",
    "gn:dem":73,
    "gn:feature_class":"P",
    "gn:feature_code":"PPL",
    "gn:name":"Samsonovskaya Pravyy Bereg",
    "gn:population":0,
    "gn:timezone":"Europe/Moscow",
    "iso:country":"RU",
    "name:rus_x_preferred":[
        "\u0421\u0430\u043c\u0441\u043e\u043d\u043e\u0432\u0441\u043a\u0430\u044f \u041f\u0440\u0430\u0432\u044b\u0439 \u0411\u0435\u0440\u0435\u0433"
    ],
    "wof:name":"Samsonovskaya Pravyy Bereg",
    "wof:placetype":"locality"
},
  "geometry": {"coordinates":[42.76221,61.31739],"type":"Point"}
}