{
  "type": "Feature",
  "properties": {
    "gn:admin1_code":"91",
    "gn:asciiname":"Malyy Ungut",
    "gn:country_code":"RU",
    "gn:dem":345,
    "gn:feature_class":"P",
    "gn:feature_code":"PPL",
    "gn:name":"Malyy Ungut",
    "gn:population":0,
    "gn:timezone":"Asia/Krasnoyarsk",
    "iso:country":"RU",
    "name:eng_x_preferred":[
        "Malyy Ungut"
    ],
    "name:nor_x_preferred":[
        "Mal.Ungut"
    ],
    "name:rus_x_preferred":[
        "\u041c\u0430\u043b.\u0423\u043d\u0433\u0443\u0442"
    ],
    "name:rus_x_variant":[
        "\u041c\u0430\u043b\u044b\u0439 \u0423\u043d\u0433\u0443\u0442"
    ],
    "wof:name":"Malyy Ungut",
    "wof:placetype":"locality"
},
  "geometry": {"coordinates":[93.3575,55.4417],"type":"Point"}
}