{
  "type": "Feature",
  "properties": {
    "gn:admin1_code":"25.0",
    "gn:asciiname":"Bebelevo",
    "gn:country_code":"RU",
    "gn:dem":194,
    "gn:feature_class":"P",
    "gn:feature_code":"PPL",
    "gn:name":"Bebelevo",
    "gn:population":0,
    "gn:timezone":"Europe/Moscow",
    "iso:country":"RU",
    "name:nor_x_preferred":[
        "Bebelevo"
    ],
    "name:rus_x_preferred":[
        "\u0411\u0435\u0431\u0435\u043b\u0435\u0432\u043e"
    ],
    "name:und_x_variant":[
        "Bobrovo",
        "Bebelovo"
    ],
    "wof:name":"Bebelevo",
    "wof:placetype":"locality"
},
  "geometry": {"coordinates":[36.4969,54.53187],"type":"Point"}
}