{
  "type": "Feature",
  "properties": {
    "gn:admin1_code":"77",
    "gn:asciiname":"Berezovskiy Ryadok",
    "gn:country_code":"RU",
    "gn:dem":212,
    "gn:feature_class":"P",
    "gn:feature_code":"PPL",
    "gn:name":"Ber\u00ebzovskiy Ryadok",
    "gn:population":0,
    "gn:timezone":"Europe/Moscow",
    "iso:country":"RU",
    "name:rus_x_preferred":[
        "\u0411\u0435\u0440\u0451\u0437\u043e\u0432\u0441\u043a\u0438\u0439 \u0420\u044f\u0434\u043e\u043a"
    ],
    "name:und_x_variant":[
        "Ber\u00ebzovskiy Ryadok"
    ],
    "wof:name":"Berezovskiy Ryadok",
    "wof:placetype":"locality"
},
  "geometry": {"coordinates":[32.79793,57.30653],"type":"Point"}
}