{
  "type": "Feature",
  "properties": {
    "gn:admin1_code":"25",
    "gn:asciiname":"Pechenkino",
    "gn:country_code":"RU",
    "gn:dem":197,
    "gn:feature_class":"P",
    "gn:feature_code":"PPL",
    "gn:name":"Pech\u00ebnkino",
    "gn:population":0,
    "gn:timezone":"Europe/Moscow",
    "iso:country":"RU",
    "name:rus_x_preferred":[
        "\u041f\u0435\u0447\u0451\u043d\u043a\u0438\u043d\u043e"
    ],
    "name:und_x_variant":[
        "Pech\u00ebnkino",
        "\u041f\u0435\u0447\u0451\u043d\u043a\u0438\u043d\u043e"
    ],
    "wof:name":"Pechenkino",
    "wof:placetype":"locality"
},
  "geometry": {"coordinates":[35.24674,54.05396999999999],"type":"Point"}
}