{
  "type": "Feature",
  "properties": {
    "gn:admin1_code":"88",
    "gn:asciiname":"Golubkovo",
    "gn:country_code":"RU",
    "gn:dem":160,
    "gn:feature_class":"P",
    "gn:feature_code":"PPL",
    "gn:name":"Golubkovo",
    "gn:population":0,
    "gn:timezone":"Europe/Moscow",
    "iso:country":"RU",
    "name:rus_x_preferred":[
        "\u0413\u043e\u043b\u0443\u0431\u043a\u043e\u0432\u043e"
    ],
    "wof:name":"Golubkovo",
    "wof:placetype":"locality"
},
  "geometry": {"coordinates":[39.57363,57.46677],"type":"Point"}
}