{
  "type": "Feature",
  "properties": {
    "gn:admin1_code":"13",
    "gn:asciiname":"Tabuska",
    "gn:country_code":"RU",
    "gn:dem":368,
    "gn:feature_class":"P",
    "gn:feature_code":"PPL",
    "gn:name":"Tabuska",
    "gn:population":0,
    "gn:timezone":"Asia/Yekaterinburg",
    "iso:country":"RU",
    "name:eng_x_preferred":[
        "Tabuska"
    ],
    "name:nor_x_preferred":[
        "Tabuska"
    ],
    "name:rus_x_preferred":[
        "\u0422\u0430\u0431\u0443\u0441\u043a\u0430"
    ],
    "wof:name":"Tabuska",
    "wof:placetype":"locality"
},
  "geometry": {"coordinates":[59.4325,56.10917],"type":"Point"}
}