{
  "type": "Feature",
  "properties": {
    "gn:admin1_code":"8",
    "gn:asciiname":"Novonikolayevka",
    "gn:country_code":"RU",
    "gn:dem":170,
    "gn:feature_class":"P",
    "gn:feature_code":"PPL",
    "gn:name":"Novonikolayevka",
    "gn:population":0,
    "gn:timezone":"Asia/Yekaterinburg",
    "iso:country":"RU",
    "name:ceb_x_preferred":[
        "Novonikolayevka"
    ],
    "name:ces_x_preferred":[
        "Novomykolajivka"
    ],
    "name:deu_x_preferred":[
        "Nowomykolajiwka"
    ],
    "name:hun_x_preferred":[
        "Novonyikolajevka"
    ],
    "name:hye_x_preferred":[
        "\u0546\u0578\u057e\u0578\u0576\u056b\u056f\u0578\u056c\u0561\u0587\u056f\u0561"
    ],
    "name:pol_x_preferred":[
        "Nowomyko\u0142ajiwka"
    ],
    "name:rus_x_preferred":[
        "\u041d\u043e\u0432\u043e\u043d\u0438\u043a\u043e\u043b\u0430\u0435\u0432\u043a\u0430"
    ],
    "name:spa_x_preferred":[
        "Novonikol\u00e1yevka"
    ],
    "name:ukr_x_preferred":[
        "\u041d\u043e\u0432\u043e\u043c\u0438\u043a\u043e\u043b\u0430\u0457\u0432\u043a\u0430"
    ],
    "wof:name":"Novonikolayevka",
    "wof:placetype":"locality"
},
  "geometry": {"coordinates":[53.72663000000001,54.05721],"type":"Point"}
}