{
  "type": "Feature",
  "properties": {
    "gn:admin1_code":"62",
    "gn:asciiname":"Tolstyye",
    "gn:country_code":"RU",
    "gn:dem":180,
    "gn:feature_class":"P",
    "gn:feature_code":"PPL",
    "gn:name":"Tolstyye",
    "gn:population":0,
    "gn:timezone":"Europe/Moscow",
    "iso:country":"RU",
    "name:rus_x_preferred":[
        "\u0422\u043e\u043b\u0441\u0442\u044b\u0435"
    ],
    "name:und_x_variant":[
        "\u0422\u043e\u043b\u0441\u0442\u044b\u0435"
    ],
    "wof:name":"Tolstyye",
    "wof:placetype":"locality"
},
  "geometry": {"coordinates":[39.10938,53.54293000000001],"type":"Point"}
}