{
  "type": "Feature",
  "properties": {
    "gn:admin1_code":"8.0",
    "gn:asciiname":"Nizhnyaya Akberda",
    "gn:country_code":"RU",
    "gn:dem":206,
    "gn:feature_class":"P",
    "gn:feature_code":"PPL",
    "gn:name":"Nizhnyaya Akberda",
    "gn:population":0,
    "gn:timezone":"Asia/Yekaterinburg",
    "iso:country":"RU",
    "name:bak_x_preferred":[
        "\u0422\u04af\u0431\u04d9\u043d\u0433\u0435 \u0410\u04a1\u0431\u0438\u0440\u0499\u0435"
    ],
    "name:che_x_preferred":[
        "\u041d\u0438\u0436\u043d\u0438 \u0410\u043a\u0431\u0435\u0440\u0434\u0430"
    ],
    "name:hye_x_preferred":[
        "\u0546\u056b\u056a\u0576\u0575\u0561\u0575\u0561 \u0531\u056f\u0562\u0565\u0580\u0564\u0561"
    ],
    "name:kaz_x_preferred":[
        "\u0422\u04e9\u043c\u0435\u043d\u0433\u0456 \u0410\u043a\u0431\u0435\u0440\u0434\u0430"
    ],
    "name:kir_x_preferred":[
        "\u0422\u04e9\u043c\u04e9\u043d\u043a\u04af \u0410\u043a\u0431\u0435\u0440\u0434\u0430"
    ],
    "name:rus_x_preferred":[
        "\u041d\u0438\u0436\u043d\u044f\u044f \u0410\u043a\u0431\u0435\u0440\u0434\u0430"
    ],
    "name:tat_x_preferred":[
        "\u0422\u04af\u0431\u04d9\u043d \u0410\u043a\u0431\u0438\u0440\u0434\u0435"
    ],
    "name:ukr_x_preferred":[
        "\u041d\u0438\u0436\u043d\u044f \u0410\u043a\u0431\u0435\u0440\u0434\u0430"
    ],
    "name:und_x_variant":[
        "Akberda",
        "Nizhnyaya Akberda",
        "\u041d\u0438\u0436\u043d\u044f\u044f \u0410\u043a\u0431\u0435\u0440\u0434\u0430"
    ],
    "wof:name":"Nizhnyaya Akberda",
    "wof:placetype":"locality"
},
  "geometry": {"coordinates":[56.76303000000001,51.99524],"type":"Point"}
}