{
  "type": "Feature",
  "properties": {
    "gn:admin1_code":"8.0",
    "gn:asciiname":"Nizhnyaya Akberda",
    "gn:country_code":"RU",
    "gn:dem":206,
    "gn:feature_class":"P",
    "gn:feature_code":"PPL",
    "gn:name":"Nizhnyaya Akberda",
    "gn:population":0,
    "gn:timezone":"Asia/Yekaterinburg",
    "iso:country":"RU",
    "name:rus_x_preferred":[
        "\u041d\u0438\u0436\u043d\u044f\u044f \u0410\u043a\u0431\u0435\u0440\u0434\u0430"
    ],
    "name:und_x_variant":[
        "Akberda",
        "Nizhnyaya Akberda",
        "\u041d\u0438\u0436\u043d\u044f\u044f \u0410\u043a\u0431\u0435\u0440\u0434\u0430"
    ],
    "wof:name":"Nizhnyaya Akberda",
    "wof:placetype":"locality"
},
  "geometry": {"coordinates":[56.76303000000001,51.99524],"type":"Point"}
}