{
  "type": "Feature",
  "properties": {
    "gn:admin1_code":"62",
    "gn:asciiname":"Prosech'ye",
    "gn:country_code":"RU",
    "gn:dem":159,
    "gn:feature_class":"P",
    "gn:feature_code":"PPL",
    "gn:name":"Prosech\u2019ye",
    "gn:population":0,
    "gn:timezone":"Europe/Moscow",
    "iso:country":"RU",
    "name:eng_x_preferred":[
        "Prosech'ye"
    ],
    "name:nor_x_preferred":[
        "Prosetsje"
    ],
    "name:rus_x_preferred":[
        "\u041f\u0440\u043e\u0441\u0435\u0447\u044c\u0435"
    ],
    "name:und_x_variant":[
        "Prosech\u2019ye"
    ],
    "wof:name":"Prosech'ye",
    "wof:placetype":"locality"
},
  "geometry": {"coordinates":[40.3792,53.4927],"type":"Point"}
}