{
  "type": "Feature",
  "properties": {
    "gn:admin1_code":"77",
    "gn:asciiname":"Borok",
    "gn:country_code":"RU",
    "gn:dem":141,
    "gn:feature_class":"P",
    "gn:feature_code":"PPL",
    "gn:name":"Borok",
    "gn:population":0,
    "gn:timezone":"Europe/Moscow",
    "iso:country":"RU",
    "name:rus_x_preferred":[
        "\u0411\u043e\u0440\u043e\u043a"
    ],
    "name:und_x_variant":[
        "\u0411\u043e\u0440\u043e\u043a"
    ],
    "wof:name":"Borok",
    "wof:placetype":"locality"
},
  "geometry": {"coordinates":[36.6139,58.131],"type":"Point"}
}