{
  "type": "Feature",
  "properties": {
    "gn:admin1_code":"11",
    "gn:asciiname":"Modonkul'",
    "gn:country_code":"RU",
    "gn:dem":1049,
    "gn:feature_class":"P",
    "gn:feature_code":"PPL",
    "gn:name":"Modonkul\u2019",
    "gn:population":0,
    "gn:timezone":"Asia/Irkutsk",
    "iso:country":"RU",
    "name:rus_x_preferred":[
        "\u041c\u043e\u0434\u043e\u043d\u043a\u0443\u043b\u044c"
    ],
    "name:und_x_variant":[
        "Karaul Modonkul\u2019skiy",
        "Modenkul\u2019",
        "Poselok Modonkul\u2019",
        "Modanku",
        "Modonkul\u2019"
    ],
    "wof:name":"Modonkul'",
    "wof:placetype":"locality"
},
  "geometry": {"coordinates":[103.31667,50.43333],"type":"Point"}
}