{
  "type": "Feature",
  "properties": {
    "gn:admin1_code":"29",
    "gn:asciiname":"Abyshevo",
    "gn:country_code":"RU",
    "gn:dem":157,
    "gn:feature_class":"P",
    "gn:feature_code":"PPL",
    "gn:name":"Abyshevo",
    "gn:population":0,
    "gn:timezone":"Asia/Novokuznetsk",
    "iso:country":"RU",
    "name:eng_x_preferred":[
        "Abyshevo"
    ],
    "name:nor_x_preferred":[
        "Abysjevo"
    ],
    "name:rus_x_preferred":[
        "\u0410\u0431\u044b\u0448\u0435\u0432\u043e"
    ],
    "name:und_x_variant":[
        "Abysheva"
    ],
    "wof:name":"Abyshevo",
    "wof:placetype":"locality"
},
  "geometry": {"coordinates":[84.99028,55.06694],"type":"Point"}
}