{
  "type": "Feature",
  "properties": {
    "gn:admin1_code":"4",
    "gn:asciiname":"Uksunay",
    "gn:country_code":"RU",
    "gn:dem":200,
    "gn:feature_class":"P",
    "gn:feature_code":"PPL",
    "gn:name":"Uksunay",
    "gn:population":0,
    "gn:timezone":"Asia/Barnaul",
    "iso:country":"RU",
    "name:eng_x_preferred":[
        "Uksunay"
    ],
    "name:nor_x_preferred":[
        "Uksunaj"
    ],
    "name:rus_x_preferred":[
        "\u0423\u043a\u0441\u0443\u043d\u0430\u0439"
    ],
    "name:und_x_variant":[
        "Uksunayskaya",
        "Uksunai"
    ],
    "wof:name":"Uksunay",
    "wof:placetype":"locality"
},
  "geometry": {"coordinates":[86.0129,53.4958],"type":"Point"}
}