{
  "type": "Feature",
  "properties": {
    "gn:admin1_code":"20",
    "gn:asciiname":"Tyrgur",
    "gn:country_code":"RU",
    "gn:dem":508,
    "gn:feature_class":"P",
    "gn:feature_code":"PPL",
    "gn:name":"Tyrgur",
    "gn:population":0,
    "gn:timezone":"Asia/Irkutsk",
    "iso:country":"RU",
    "name:rus_x_preferred":[
        "\u0422\u044b\u0440\u0433\u0443\u0440"
    ],
    "wof:name":"Tyrgur",
    "wof:placetype":"locality"
},
  "geometry": {"coordinates":[103.5129,53.121],"type":"Point"}
}