{
  "type": "Feature",
  "properties": {
    "gn:admin1_code":"13",
    "gn:asciiname":"Tatarskaya Karabolka",
    "gn:country_code":"RU",
    "gn:dem":209,
    "gn:feature_class":"P",
    "gn:feature_code":"PPL",
    "gn:name":"Tatarskaya Karabolka",
    "gn:population":0,
    "gn:timezone":"Asia/Yekaterinburg",
    "iso:country":"RU",
    "name:eng_x_preferred":[
        "Tatarskaya Karabolka"
    ],
    "name:rus_x_preferred":[
        "\u0422\u0430\u0442.\u041a\u0430\u0440\u0430\u0431\u043e\u043b\u043a\u0430"
    ],
    "name:rus_x_variant":[
        "\u0422\u0430\u0442.\u043a\u0430\u0440\u0430\u0431\u043e\u043b\u043a\u0430",
        "\u0422\u0430\u0442\u0430\u0440\u0441\u043a\u0430\u044f \u041a\u0430\u0440\u0430\u0431\u043e\u043b\u043a\u0430"
    ],
    "name:und_x_variant":[
        "Karabolka"
    ],
    "wof:name":"Tatarskaya Karabolka",
    "wof:placetype":"locality"
},
  "geometry": {"coordinates":[61.184,55.9464],"type":"Point"}
}