{
  "type": "Feature",
  "properties": {
    "gn:admin1_code":"40",
    "gn:asciiname":"Novaya Zatobol'naya",
    "gn:country_code":"RU",
    "gn:dem":89,
    "gn:feature_class":"P",
    "gn:feature_code":"PPL",
    "gn:name":"Novaya Zatobol\u2019naya",
    "gn:population":0,
    "gn:timezone":"Asia/Yekaterinburg",
    "iso:country":"RU",
    "name:rus_x_preferred":[
        "\u041d\u043e\u0432\u0430\u044f \u0417\u0430\u0442\u043e\u0431\u043e\u043b\u044c\u043d\u0430\u044f"
    ],
    "name:und_x_variant":[
        "Vorob\u2019y\u00ebvka",
        "Novaya Zatobol\u2019naya"
    ],
    "wof:name":"Novaya Zatobol'naya",
    "wof:placetype":"locality"
},
  "geometry": {"coordinates":[65.21972,55.22333],"type":"Point"}
}