{
  "type": "Feature",
  "properties": {
    "gn:admin1_code":"37.0",
    "gn:asciiname":"Mikhal'tsy",
    "gn:country_code":"RU",
    "gn:dem":93,
    "gn:feature_class":"P",
    "gn:feature_code":"PPL",
    "gn:name":"Mikhal\u2019tsy",
    "gn:population":0,
    "gn:timezone":"Europe/Moscow",
    "iso:country":"RU",
    "name:rus_x_preferred":[
        "\u041c\u0438\u0445\u0430\u043b\u044c\u0446\u044b"
    ],
    "name:und_x_variant":[
        "Mikhal\u2019tsy",
        "\u041c\u0438\u0445\u0430\u043b\u044c\u0446\u044b"
    ],
    "wof:name":"Mikhal'tsy",
    "wof:placetype":"locality"
},
  "geometry": {"coordinates":[42.83234,57.44813000000001],"type":"Point"}
}