{
  "type": "Feature",
  "properties": {
    "gn:admin1_code":"56",
    "gn:asciiname":"Novyy Svet",
    "gn:cc2":"RU",
    "gn:country_code":"RU",
    "gn:dem":238,
    "gn:feature_class":"P",
    "gn:feature_code":"PPL",
    "gn:name":"Novyy Svet",
    "gn:population":0,
    "gn:timezone":"Europe/Moscow",
    "iso:country":"RU",
    "name:rus_x_preferred":[
        "\u041d\u043e\u0432\u044b\u0439 \u0421\u0432\u0435\u0442"
    ],
    "name:und_x_variant":[
        "Novy Svet",
        "Novyy Svet"
    ],
    "wof:name":"Novyy Svet",
    "wof:placetype":"locality"
},
  "geometry": {"coordinates":[35.58139,52.43861],"type":"Point"}
}