{
  "type": "Feature",
  "properties": {
    "gn:admin1_code":"78",
    "gn:asciiname":"Porotnikova",
    "gn:country_code":"RU",
    "gn:dem":69,
    "gn:feature_class":"P",
    "gn:feature_code":"PPL",
    "gn:name":"Porotnikova",
    "gn:population":0,
    "gn:timezone":"Asia/Yekaterinburg",
    "iso:country":"RU",
    "name:eng_x_preferred":[
        "Porotnikovo"
    ],
    "name:nor_x_preferred":[
        "Porotnikova"
    ],
    "name:rus_x_preferred":[
        "\u041f\u043e\u0440\u043e\u0442\u043d\u0438\u043a\u043e\u0432\u0430"
    ],
    "wof:name":"Porotnikova",
    "wof:placetype":"locality"
},
  "geometry": {"coordinates":[70.7128,56.34189],"type":"Point"}
}