{
  "type": "Feature",
  "properties": {
    "gn:admin1_code":"30",
    "gn:asciiname":"Aim",
    "gn:country_code":"RU",
    "gn:dem":228,
    "gn:feature_class":"P",
    "gn:feature_code":"PPL",
    "gn:name":"Aim",
    "gn:population":0,
    "gn:timezone":"Asia/Vladivostok",
    "iso:country":"RU",
    "name:eng_x_preferred":[
        "Aim"
    ],
    "name:nor_x_preferred":[
        "Aim"
    ],
    "name:rus_x_preferred":[
        "\u0410\u0438\u043c"
    ],
    "wof:name":"Aim",
    "wof:placetype":"locality"
},
  "geometry": {"coordinates":[134.25403,58.77421],"type":"Point"}
}