{
  "type": "Feature",
  "properties": {
    "gn:admin1_code":"81",
    "gn:asciiname":"Staraya Savaderka",
    "gn:country_code":"RU",
    "gn:dem":206,
    "gn:feature_class":"P",
    "gn:feature_code":"PPL",
    "gn:name":"Staraya Savaderka",
    "gn:population":0,
    "gn:timezone":"Europe/Ulyanovsk",
    "iso:country":"RU",
    "name:rus_x_preferred":[
        "\u0421\u0442\u0430\u0440\u0430\u044f \u0421\u0430\u0432\u0430\u0434\u0435\u0440\u043a\u0430"
    ],
    "wof:name":"Staraya Savaderka",
    "wof:placetype":"locality"
},
  "geometry": {"coordinates":[46.9869,53.7562],"type":"Point"}
}