{
  "type": "Feature",
  "properties": {
    "gn:admin1_code":"28",
    "gn:asciiname":"Gumarino",
    "gn:country_code":"RU",
    "gn:dem":147,
    "gn:feature_class":"P",
    "gn:feature_code":"PPL",
    "gn:name":"Gumarino",
    "gn:population":0,
    "gn:timezone":"Europe/Moscow",
    "iso:country":"RU",
    "name:eng_x_preferred":[
        "Gumarino"
    ],
    "name:nor_x_preferred":[
        "Gumarino"
    ],
    "name:rus_x_preferred":[
        "\u0413\u0443\u043c\u0430\u0440\u0438\u043d\u043e"
    ],
    "wof:name":"Gumarino",
    "wof:placetype":"locality"
},
  "geometry": {"coordinates":[33.11605,62.96354],"type":"Point"}
}