{
  "type": "Feature",
  "properties": {
    "gn:admin1_code":"47",
    "gn:asciiname":"Cherepovo",
    "gn:country_code":"RU",
    "gn:dem":160,
    "gn:feature_class":"P",
    "gn:feature_code":"PPL",
    "gn:name":"Cherepovo",
    "gn:population":0,
    "gn:timezone":"Europe/Moscow",
    "iso:country":"RU",
    "name:bul_x_preferred":[
        "\u0427\u0435\u0440\u0435\u043f\u043e\u0432\u043e"
    ],
    "name:ceb_x_preferred":[
        "Cherepovo"
    ],
    "name:fas_x_preferred":[
        "\u0686\u0631\u067e\u0648\u0648\u0648"
    ],
    "name:kaz_x_preferred":[
        "\u0427\u0435\u0440\u0435\u043f\u043e\u0432\u043e"
    ],
    "name:pol_x_preferred":[
        "Czerepowo"
    ],
    "name:ron_x_preferred":[
        "Cerepovo"
    ],
    "name:rus_x_preferred":[
        "\u0427\u0435\u0440\u0435\u043f\u043e\u0432\u043e"
    ],
    "name:swe_x_preferred":[
        "Tjerepovo"
    ],
    "name:ukr_x_preferred":[
        "\u0427\u0435\u0440\u0435\u043f\u043e\u0432\u043e"
    ],
    "name:und_x_variant":[
        "\u0427\u0435\u0440\u0435\u043f\u043e\u0432\u043e",
        "Cherepovo"
    ],
    "wof:name":"Cherepovo",
    "wof:placetype":"locality"
},
  "geometry": {"coordinates":[37.39806,55.48972],"type":"Point"}
}