{
  "type": "Feature",
  "properties": {
    "gn:admin1_code":"53",
    "gn:asciiname":"Krotovo",
    "gn:country_code":"RU",
    "gn:dem":120,
    "gn:feature_class":"P",
    "gn:feature_code":"PPL",
    "gn:name":"Krotovo",
    "gn:population":0,
    "gn:timezone":"Asia/Novosibirsk",
    "iso:country":"RU",
    "name:eng_x_preferred":[
        "Krotovo"
    ],
    "name:nor_x_preferred":[
        "Krotovo"
    ],
    "name:rus_x_preferred":[
        "\u041a\u0440\u043e\u0442\u043e\u0432\u043e"
    ],
    "name:und_x_variant":[
        "Krotova"
    ],
    "wof:name":"Krotovo",
    "wof:placetype":"locality"
},
  "geometry": {"coordinates":[82.4644,53.5439],"type":"Point"}
}