{
  "type": "Feature",
  "properties": {
    "gn:admin1_code":"90.0",
    "gn:asciiname":"Abakshata",
    "gn:country_code":"RU",
    "gn:dem":149,
    "gn:feature_class":"P",
    "gn:feature_code":"PPL",
    "gn:name":"Abakshata",
    "gn:population":0,
    "gn:timezone":"Asia/Yekaterinburg",
    "iso:country":"RU",
    "name:eng_x_preferred":[
        "Abakshata"
    ],
    "name:nor_x_preferred":[
        "Abaksjata"
    ],
    "name:rus_x_preferred":[
        "\u0410\u0431\u0430\u043a\u0448\u0430\u0442\u0430"
    ],
    "name:und_x_variant":[
        "\u0410\u0431\u0430\u043a\u0448\u0430\u0442\u0430"
    ],
    "wof:name":"Abakshata",
    "wof:placetype":"locality"
},
  "geometry": {"coordinates":[55.8419,58.1857],"type":"Point"}
}