{
  "type": "Feature",
  "properties": {
    "gn:admin1_code":"91",
    "gn:asciiname":"Malyy Telek",
    "gn:country_code":"RU",
    "gn:dem":286,
    "gn:feature_class":"P",
    "gn:feature_code":"PPL",
    "gn:name":"Malyy Telek",
    "gn:population":0,
    "gn:timezone":"Asia/Krasnoyarsk",
    "iso:country":"RU",
    "name:rus_x_preferred":[
        "\u041c\u0430\u043b\u044b\u0439 \u0422\u0435\u043b\u0435\u043a"
    ],
    "wof:name":"Malyy Telek",
    "wof:placetype":"locality"
},
  "geometry": {"coordinates":[91.93861,54.33221999999999],"type":"Point"}
}