{
  "type": "Feature",
  "properties": {
    "gn:admin1_code":"8",
    "gn:asciiname":"Naryshevo",
    "gn:country_code":"RU",
    "gn:dem":149,
    "gn:feature_class":"P",
    "gn:feature_code":"PPL",
    "gn:name":"Naryshevo",
    "gn:population":0,
    "gn:timezone":"Asia/Yekaterinburg",
    "iso:country":"RU",
    "name:bak_x_preferred":[
        "\u041d\u0430\u0440\u044b\u0448"
    ],
    "name:che_x_preferred":[
        "\u041d\u0430\u0440\u044b\u0448\u0435\u0432\u043e"
    ],
    "name:hye_x_preferred":[
        "\u0546\u0561\u0580\u056b\u0577\u0587\u0578"
    ],
    "name:kaz_x_preferred":[
        "\u041d\u0430\u0440\u044b\u0448"
    ],
    "name:kir_x_preferred":[
        "\u041d\u0430\u0440\u044b\u0448"
    ],
    "name:rus_x_preferred":[
        "\u041d\u0430\u0440\u044b\u0448\u0435\u0432\u043e"
    ],
    "name:tat_x_preferred":[
        "\u041d\u0430\u0440\u044b\u0448"
    ],
    "name:und_x_variant":[
        "Narysheva",
        "Naryshevo"
    ],
    "wof:name":"Naryshevo",
    "wof:placetype":"locality"
},
  "geometry": {"coordinates":[53.5152,54.50777],"type":"Point"}
}