{
  "type": "Feature",
  "properties": {
    "gn:admin1_code":"73",
    "gn:asciiname":"Sarmash-Bash",
    "gn:country_code":"RU",
    "gn:dem":176,
    "gn:feature_class":"P",
    "gn:feature_code":"PPL",
    "gn:name":"Sarmash-Bash",
    "gn:population":0,
    "gn:timezone":"Europe/Moscow",
    "iso:country":"RU",
    "name:eng_x_preferred":[
        "Sarmash-Bash"
    ],
    "name:nor_x_preferred":[
        "Sarmasj-Basj"
    ],
    "name:rus_x_preferred":[
        "\u0421\u0430\u0440\u043c\u0430\u0448-\u0411\u0430\u0448"
    ],
    "wof:name":"Sarmash-Bash",
    "wof:placetype":"locality"
},
  "geometry": {"coordinates":[52.34782,55.22306],"type":"Point"}
}