{
  "type": "Feature",
  "properties": {
    "gn:admin1_code":"77",
    "gn:asciiname":"Selishche",
    "gn:country_code":"RU",
    "gn:dem":120,
    "gn:feature_class":"P",
    "gn:feature_code":"PPL",
    "gn:name":"Selishche",
    "gn:population":0,
    "gn:timezone":"Europe/Moscow",
    "iso:country":"RU",
    "name:eng_x_preferred":[
        "Selishche"
    ],
    "name:nor_x_preferred":[
        "Selisjtsje"
    ],
    "name:rus_x_preferred":[
        "\u0421\u0435\u043b\u0438\u0449\u0435"
    ],
    "name:und_x_variant":[
        "Novyye Selishchi",
        "Selishche Pervoye",
        "Selishche Vtoroye"
    ],
    "wof:name":"Selishche",
    "wof:placetype":"locality"
},
  "geometry": {"coordinates":[37.42694,57.01056],"type":"Point"}
}