{
  "type": "Feature",
  "properties": {
    "gn:admin1_code":"42",
    "gn:asciiname":"Henttala",
    "gn:cc2":"RU",
    "gn:country_code":"RU",
    "gn:dem":20,
    "gn:feature_class":"P",
    "gn:feature_code":"PPL",
    "gn:name":"Henttala",
    "gn:population":0,
    "gn:timezone":"Europe/Moscow",
    "iso:country":"RU",
    "name:und_x_variant":[
        "Kentola",
        "Virolaynen"
    ],
    "wof:name":"Henttala",
    "wof:placetype":"locality"
},
  "geometry": {"coordinates":[28.62711,60.47795],"type":"Point"}
}