{
  "type": "Feature",
  "properties": {
    "gn:admin1_code":"90",
    "gn:asciiname":"Verkhneye Kalino",
    "gn:country_code":"RU",
    "gn:dem":121,
    "gn:feature_class":"P",
    "gn:feature_code":"PPL",
    "gn:name":"Verkhneye Kalino",
    "gn:population":0,
    "gn:timezone":"Asia/Yekaterinburg",
    "iso:country":"RU",
    "name:rus_x_preferred":[
        "\u0412\u0435\u0440\u0445\u043d\u0435\u0435 \u041a\u0430\u043b\u0438\u043d\u043e"
    ],
    "wof:name":"Verkhneye Kalino",
    "wof:placetype":"locality"
},
  "geometry": {"coordinates":[57.6596,58.3113],"type":"Point"}
}