{
  "type": "Feature",
  "properties": {
    "gn:admin1_code":"51.0",
    "gn:asciiname":"Sorimostovo",
    "gn:country_code":"RU",
    "gn:dem":94,
    "gn:feature_class":"P",
    "gn:feature_code":"PPL",
    "gn:name":"Sorimostovo",
    "gn:population":0,
    "gn:timezone":"Europe/Moscow",
    "iso:country":"RU",
    "name:nor_x_preferred":[
        "Sorimostovo"
    ],
    "name:rus_x_preferred":[
        "\u0421\u043e\u0440\u0438\u043c\u043e\u0441\u0442\u043e\u0432\u043e"
    ],
    "wof:name":"Sorimostovo",
    "wof:placetype":"locality"
},
  "geometry": {"coordinates":[43.94156,56.49693000000001],"type":"Point"}
}