{
  "type": "Feature",
  "properties": {
    "gn:admin1_code":"77",
    "gn:asciiname":"Lukino",
    "gn:country_code":"RU",
    "gn:dem":172,
    "gn:feature_class":"P",
    "gn:feature_code":"PPL",
    "gn:name":"Lukino",
    "gn:population":0,
    "gn:timezone":"Europe/Moscow",
    "iso:country":"RU",
    "name:rus_x_preferred":[
        "\u041b\u0443\u043a\u0438\u043d\u043e"
    ],
    "name:und_x_variant":[
        "\u041b\u0443\u043a\u0438\u043d\u043e"
    ],
    "wof:name":"Lukino",
    "wof:placetype":"locality"
},
  "geometry": {"coordinates":[34.95903,57.63007],"type":"Point"}
}