{
  "type": "Feature",
  "properties": {
    "gn:admin1_code":"61",
    "gn:asciiname":"Zotov",
    "gn:country_code":"RU",
    "gn:dem":181,
    "gn:feature_class":"P",
    "gn:feature_code":"PPL",
    "gn:name":"Zotov",
    "gn:population":0,
    "gn:timezone":"Europe/Moscow",
    "iso:country":"RU",
    "name:slv_x_preferred":[
        "Zotov"
    ],
    "wof:name":"Zotov",
    "wof:placetype":"locality"
},
  "geometry": {"coordinates":[40.95945,49.24169000000001],"type":"Point"}
}