{
  "type": "Feature",
  "properties": {
    "gn:admin1_code":"84.0",
    "gn:asciiname":"Belyayevskiy",
    "gn:country_code":"RU",
    "gn:dem":60,
    "gn:feature_class":"P",
    "gn:feature_code":"PPL",
    "gn:name":"Belyayevskiy",
    "gn:population":0,
    "gn:timezone":"Europe/Volgograd",
    "iso:country":"RU",
    "name:nor_x_preferred":[
        "Beljaevskij"
    ],
    "name:rus_x_preferred":[
        "\u0411\u0435\u043b\u044f\u0435\u0432\u0441\u043a\u0438\u0439"
    ],
    "wof:name":"Belyayevskiy",
    "wof:placetype":"locality"
},
  "geometry": {"coordinates":[42.7861,49.5339],"type":"Point"}
}