{
  "type": "Feature",
  "properties": {
    "gn:admin1_code":"62",
    "gn:asciiname":"Sukhovka",
    "gn:country_code":"RU",
    "gn:dem":112,
    "gn:feature_class":"P",
    "gn:feature_code":"PPL",
    "gn:name":"Sukhovka",
    "gn:population":0,
    "gn:timezone":"Europe/Moscow",
    "iso:country":"RU",
    "name:rus_x_preferred":[
        "\u0421\u0443\u0445\u043e\u0432\u043a\u0430"
    ],
    "name:und_x_variant":[
        "\u0421\u0443\u0445\u043e\u0432\u043a\u0430"
    ],
    "wof:name":"Sukhovka",
    "wof:placetype":"locality"
},
  "geometry": {"coordinates":[41.10149000000001,54.21661999999999],"type":"Point"}
}