{
  "type": "Feature",
  "properties": {
    "iso:country":"RU",
    "name:rus_x_preferred":[
        "\u0417\u0430\u043f\u0430\u0434\u043d\u043e\u0435 \u0414\u0435\u0433\u0443\u043d\u0438\u043d\u043e"
    ],
    "wof:name":"Zapadnoye Degunino",
    "wof:placetype":"neighbourhood"
},
  "geometry": {"coordinates":[37.52044864316661,55.87180254782053],"type":"Point"}
}