{
  "type": "Feature",
  "properties": {
    "gn:admin1_code":"52",
    "gn:asciiname":"Berezka",
    "gn:country_code":"RU",
    "gn:dem":60,
    "gn:feature_class":"P",
    "gn:feature_code":"PPL",
    "gn:name":"Ber\u00ebzka",
    "gn:population":0,
    "gn:timezone":"Europe/Moscow",
    "iso:country":"RU",
    "name:hun_x_preferred":[
        "Berezka"
    ],
    "name:rus_x_preferred":[
        "\u0411\u0435\u0440\u0451\u0437\u043a\u0430"
    ],
    "name:und_x_variant":[
        "Ber\u00ebzka"
    ],
    "wof:name":"Berezka",
    "wof:placetype":"locality"
},
  "geometry": {"coordinates":[31.0302,57.9633],"type":"Point"}
}