{
  "type": "Feature",
  "properties": {
    "gn:admin1_code":"12.0",
    "gn:asciiname":"Tsindoy",
    "gn:country_code":"RU",
    "gn:dem":955,
    "gn:feature_class":"P",
    "gn:feature_code":"PPL",
    "gn:name":"Tsindoy",
    "gn:population":0,
    "gn:timezone":"Europe/Moscow",
    "iso:country":"RU",
    "name:che_x_preferred":[
        "\u010aindo"
    ],
    "name:che_x_variant":[
        "\u0426\u0406\u0438\u043d\u0434\u043e"
    ],
    "name:rus_x_preferred":[
        "\u0426\u0438\u043d\u0434\u043e\u0439"
    ],
    "name:und_x_variant":[
        "Cindoj"
    ],
    "wof:name":"Tsindoy",
    "wof:placetype":"locality"
},
  "geometry": {"coordinates":[45.89043,42.75944000000001],"type":"Point"}
}