{
  "type": "Feature",
  "properties": {
    "gn:admin1_code":"33",
    "gn:asciiname":"Razboynyy Bor",
    "gn:country_code":"RU",
    "gn:dem":104,
    "gn:feature_class":"P",
    "gn:feature_code":"PPL",
    "gn:name":"Razboynyy Bor",
    "gn:population":0,
    "gn:timezone":"Europe/Kirov",
    "iso:country":"RU",
    "name:eng_x_preferred":[
        "Razboynyy Bor"
    ],
    "name:nor_x_preferred":[
        "Razbojnyj Bor"
    ],
    "name:rus_x_preferred":[
        "\u0420\u0430\u0437\u0431\u043e\u0439\u043d\u044b\u0439 \u0411\u043e\u0440"
    ],
    "wof:name":"Razboynyy Bor",
    "wof:placetype":"locality"
},
  "geometry": {"coordinates":[48.53002,58.0133],"type":"Point"}
}