{
  "type": "Feature",
  "properties": {
    "gn:admin1_code":"62",
    "gn:asciiname":"Zimarovo",
    "gn:country_code":"RU",
    "gn:dem":144,
    "gn:feature_class":"P",
    "gn:feature_code":"PPL",
    "gn:name":"Zimarovo",
    "gn:population":0,
    "gn:timezone":"Europe/Moscow",
    "iso:country":"RU",
    "name:rus_x_preferred":[
        "\u0417\u0438\u043c\u0430\u0440\u043e\u0432\u043e"
    ],
    "wof:name":"Zimarovo",
    "wof:placetype":"locality"
},
  "geometry": {"coordinates":[40.2086,53.3721],"type":"Point"}
}