{
  "type": "Feature",
  "properties": {
    "gn:admin1_code":"24",
    "gn:asciiname":"Yalmta",
    "gn:country_code":"RU",
    "gn:dem":3,
    "gn:feature_class":"P",
    "gn:feature_code":"PPL",
    "gn:name":"Yalmta",
    "gn:population":0,
    "gn:timezone":"Europe/Moscow",
    "iso:country":"RU",
    "name:eng_x_preferred":[
        "Yalmta"
    ],
    "name:nor_x_preferred":[
        "Jalmta"
    ],
    "name:rus_x_preferred":[
        "\u042f\u043b\u043c\u0442\u0430"
    ],
    "wof:name":"Yalmta",
    "wof:placetype":"locality"
},
  "geometry": {"coordinates":[44.8955,46.5384],"type":"Point"}
}