{
  "type": "Feature",
  "properties": {
    "gn:admin1_code":"62.0",
    "gn:asciiname":"Bezhtvino",
    "gn:country_code":"RU",
    "gn:dem":131,
    "gn:feature_class":"P",
    "gn:feature_code":"PPL",
    "gn:name":"Bezhtvino",
    "gn:population":0,
    "gn:timezone":"Europe/Moscow",
    "iso:country":"RU",
    "name:nor_x_preferred":[
        "Bezjtvino"
    ],
    "name:rus_x_preferred":[
        "\u0411\u0435\u0436\u0442\u0432\u0438\u043d\u043e"
    ],
    "wof:name":"Bezhtvino",
    "wof:placetype":"locality"
},
  "geometry": {"coordinates":[39.94306,54.44416999999999],"type":"Point"}
}