{
  "type": "Feature",
  "properties": {
    "gn:admin1_code":"89",
    "gn:asciiname":"Nizhnespasskoye",
    "gn:country_code":"RU",
    "gn:dem":44,
    "gn:feature_class":"P",
    "gn:feature_code":"PPL",
    "gn:name":"Nizhnespasskoye",
    "gn:population":0,
    "gn:timezone":"Asia/Vladivostok",
    "iso:country":"RU",
    "name:eng_x_preferred":[
        "Nizhnespasskoye"
    ],
    "name:nor_x_preferred":[
        "Nizjnespasskoje"
    ],
    "name:rus_x_preferred":[
        "\u041d\u0438\u0436\u043d\u0435\u0441\u043f\u0430\u0441\u0441\u043a\u043e\u0435"
    ],
    "name:und_x_variant":[
        "Nizhne-Spassk",
        "Nizhne-Spasskaya",
        "Novo-Spasskoye",
        "\u041d\u0438\u0436\u043d\u0435\u0441\u043f\u0430\u0441\u0441\u043a\u043e\u0435",
        "Nizhnespasskoye"
    ],
    "wof:name":"Nizhnespasskoye",
    "wof:placetype":"locality"
},
  "geometry": {"coordinates":[134.53001,48.43749],"type":"Point"}
}