{
  "type": "Feature",
  "properties": {
    "gn:admin1_code":"31",
    "gn:asciiname":"Davydkovo",
    "gn:cc2":"RU",
    "gn:country_code":"RU",
    "gn:dem":663,
    "gn:feature_class":"P",
    "gn:feature_code":"PPL",
    "gn:name":"Davydkovo",
    "gn:population":0,
    "gn:timezone":"Asia/Krasnoyarsk",
    "iso:country":"RU",
    "name:che_x_preferred":[
        "\u0414\u0430\u0432\u044b\u0434\u043a\u043e\u0432\u043e"
    ],
    "name:eng_x_preferred":[
        "Davydkovo"
    ],
    "name:nor_x_preferred":[
        "Davydkovo"
    ],
    "name:rus_x_preferred":[
        "\u0414\u0430\u0432\u044b\u0434\u043a\u043e\u0432\u043e"
    ],
    "name:und_x_variant":[
        "Davydkovka",
        "Davydkova",
        "\u0414\u0430\u0432\u044b\u0434\u043a\u043e\u0432\u043e",
        "Davydkovo"
    ],
    "wof:name":"Davydkovo",
    "wof:placetype":"locality"
},
  "geometry": {"coordinates":[90.50972,54.12611],"type":"Point"}
}