{
  "type": "Feature",
  "properties": {
    "gn:admin1_code":"65",
    "gn:asciiname":"Novyye Sosny",
    "gn:country_code":"RU",
    "gn:dem":174,
    "gn:feature_class":"P",
    "gn:feature_code":"PPL",
    "gn:name":"Novyye Sosny",
    "gn:population":0,
    "gn:timezone":"Europe/Samara",
    "iso:country":"RU",
    "name:eng_x_preferred":[
        "Novyye Sosny"
    ],
    "name:nor_x_preferred":[
        "Novye Sosny"
    ],
    "name:rus_x_preferred":[
        "\u041d\u043e\u0432\u044b\u0435 \u0421\u043e\u0441\u043d\u044b"
    ],
    "name:und_x_variant":[
        "Novaya Sosna",
        "\u041d\u043e\u0432\u044b\u0435 \u0421\u043e\u0441\u043d\u044b",
        "Novyye Sosny"
    ],
    "wof:name":"Novyye Sosny",
    "wof:placetype":"locality"
},
  "geometry": {"coordinates":[52.05223,54.2169],"type":"Point"}
}