{
  "type": "Feature",
  "properties": {
    "gn:admin1_code":"8",
    "gn:asciiname":"Satyyevo",
    "gn:country_code":"RU",
    "gn:dem":212,
    "gn:feature_class":"P",
    "gn:feature_code":"PPL",
    "gn:name":"Satyyevo",
    "gn:population":0,
    "gn:timezone":"Asia/Yekaterinburg",
    "iso:country":"RU",
    "name:eng_x_preferred":[
        "Satyyevo"
    ],
    "name:nor_x_preferred":[
        "Satyevo"
    ],
    "name:rus_x_preferred":[
        "\u0421\u0430\u0442\u044b\u0435\u0432\u043e"
    ],
    "name:und_x_variant":[
        "Satyyeva"
    ],
    "wof:name":"Satyyevo",
    "wof:placetype":"locality"
},
  "geometry": {"coordinates":[54.7324,53.5046],"type":"Point"}
}