{
  "type": "Feature",
  "properties": {
    "gn:admin1_code":"56",
    "gn:asciiname":"Ivanenkovo",
    "gn:country_code":"RU",
    "gn:dem":185,
    "gn:feature_class":"P",
    "gn:feature_code":"PPL",
    "gn:name":"Ivanenkovo",
    "gn:population":0,
    "gn:timezone":"Europe/Moscow",
    "iso:country":"RU",
    "name:rus_x_preferred":[
        "\u0418\u0432\u0430\u043d\u0435\u043d\u043a\u043e\u0432\u043e"
    ],
    "name:und_x_variant":[
        "\u0418\u0432\u0430\u043d\u0435\u043d\u043a\u043e\u0432\u043e"
    ],
    "wof:name":"Ivanenkovo",
    "wof:placetype":"locality"
},
  "geometry": {"coordinates":[37.24735,52.01772],"type":"Point"}
}