{
  "type": "Feature",
  "properties": {
    "gn:admin1_code":"54",
    "gn:asciiname":"Golubkovskiy",
    "gn:country_code":"RU",
    "gn:dem":116,
    "gn:feature_class":"P",
    "gn:feature_code":"PPL",
    "gn:name":"Golubkovskiy",
    "gn:population":0,
    "gn:timezone":"Asia/Omsk",
    "iso:country":"RU",
    "name:rus_x_preferred":[
        "\u0413\u043e\u043b\u0443\u0431\u043a\u043e\u0432\u0441\u043a\u0438\u0439"
    ],
    "wof:name":"Golubkovskiy",
    "wof:placetype":"locality"
},
  "geometry": {"coordinates":[72.11667,55.43333000000001],"type":"Point"}
}