{
  "type": "Feature",
  "properties": {
    "gn:admin1_code":"61",
    "gn:asciiname":"Pshenichnyy",
    "gn:cc2":"RU",
    "gn:country_code":"RU",
    "gn:dem":51,
    "gn:feature_class":"P",
    "gn:feature_code":"PPL",
    "gn:name":"Pshenichnyy",
    "gn:population":0,
    "gn:timezone":"Europe/Moscow",
    "iso:country":"RU",
    "name:rus_x_preferred":[
        "\u041f\u0448\u0435\u043d\u0438\u0447\u043d\u044b\u0439"
    ],
    "name:und_x_variant":[
        "Pshenichny",
        "Pshenichnyy",
        "\u041f\u0448\u0435\u043d\u0438\u0447\u043d\u044b\u0439"
    ],
    "wof:name":"Pshenichnyy",
    "wof:placetype":"locality"
},
  "geometry": {"coordinates":[39.23333,46.65],"type":"Point"}
}