{
  "type": "Feature",
  "properties": {
    "gn:admin1_code":"10",
    "gn:asciiname":"Vad'kovka",
    "gn:country_code":"RU",
    "gn:dem":136,
    "gn:feature_class":"P",
    "gn:feature_code":"PPL",
    "gn:name":"Vad\u2019kovka",
    "gn:population":0,
    "gn:timezone":"Europe/Moscow",
    "iso:country":"RU",
    "name:rus_x_preferred":[
        "\u0412\u0430\u0434\u044c\u043a\u043e\u0432\u043a\u0430"
    ],
    "name:rus_x_variant":[
        "Vad\u2019kovka",
        "Vat\u2019kovka"
    ],
    "name:und_x_variant":[
        "Vad\u2019kovka",
        "\u0412\u0430\u0434\u044c\u043a\u043e\u0432\u043a\u0430",
        "Vat\u2019kovka"
    ],
    "wof:name":"Vad'kovka",
    "wof:placetype":"locality"
},
  "geometry": {"coordinates":[33.31184,52.55873],"type":"Point"}
}