{
  "type": "Feature",
  "properties": {
    "gn:admin1_code":"37",
    "gn:asciiname":"Sintsovo",
    "gn:country_code":"RU",
    "gn:dem":142,
    "gn:feature_class":"P",
    "gn:feature_code":"PPL",
    "gn:name":"Sintsovo",
    "gn:population":0,
    "gn:timezone":"Europe/Moscow",
    "iso:country":"RU",
    "name:rus_x_preferred":[
        "\u0421\u0438\u043d\u0446\u043e\u0432\u043e"
    ],
    "name:und_x_variant":[
        "Sentsova",
        "Sentsovo",
        "Sintsovo"
    ],
    "wof:name":"Sintsovo",
    "wof:placetype":"locality"
},
  "geometry": {"coordinates":[41.48197,57.69129],"type":"Point"}
}