{
  "type": "Feature",
  "properties": {
    "gn:admin1_code":"54",
    "gn:asciiname":"Ilyushkino",
    "gn:country_code":"RU",
    "gn:dem":106,
    "gn:feature_class":"P",
    "gn:feature_code":"PPL",
    "gn:name":"Ilyushkino",
    "gn:population":0,
    "gn:timezone":"Asia/Omsk",
    "iso:country":"RU",
    "name:rus_x_preferred":[
        "\u0418\u043b\u044e\u0448\u043a\u0438\u043d\u043e"
    ],
    "wof:name":"Ilyushkino",
    "wof:placetype":"locality"
},
  "geometry": {"coordinates":[75.00960000000001,55.0956],"type":"Point"}
}