{
  "type": "Feature",
  "properties": {
    "gn:admin1_code":"32",
    "gn:asciiname":"Vakhsamtaukurt",
    "gn:country_code":"RU",
    "gn:dem":6,
    "gn:feature_class":"P",
    "gn:feature_code":"PPL",
    "gn:name":"Vakhsamtaukurt",
    "gn:population":0,
    "gn:timezone":"Asia/Yekaterinburg",
    "iso:country":"RU",
    "wof:name":"Vakhsamtaukurt",
    "wof:placetype":"locality"
},
  "geometry": {"coordinates":[65.66667,63.58333],"type":"Point"}
}