{
  "type": "Feature",
  "properties": {
    "gn:admin1_code":"67",
    "gn:asciiname":"Trudovoye",
    "gn:country_code":"RU",
    "gn:dem":39,
    "gn:feature_class":"P",
    "gn:feature_code":"PPL",
    "gn:name":"Trudovoye",
    "gn:population":0,
    "gn:timezone":"Europe/Saratov",
    "iso:country":"RU",
    "name:eng_x_preferred":[
        "Trudovoye"
    ],
    "name:nor_x_preferred":[
        "Trudovoje"
    ],
    "name:rus_x_preferred":[
        "\u0422\u0440\u0443\u0434\u043e\u0432\u043e\u0435"
    ],
    "wof:name":"Trudovoye",
    "wof:placetype":"locality"
},
  "geometry": {"coordinates":[48.2439,50.9292],"type":"Point"}
}