{
  "type": "Feature",
  "properties": {
    "gn:admin1_code":"60",
    "gn:asciiname":"Pukhly",
    "gn:country_code":"RU",
    "gn:dem":140,
    "gn:feature_class":"P",
    "gn:feature_code":"PPL",
    "gn:name":"Pukhly",
    "gn:population":0,
    "gn:timezone":"Europe/Moscow",
    "iso:country":"RU",
    "name:rus_x_preferred":[
        "\u041f\u0443\u0445\u043b\u044b"
    ],
    "wof:name":"Pukhly",
    "wof:placetype":"locality"
},
  "geometry": {"coordinates":[28.79,56.6448],"type":"Point"}
}