{
  "type": "Feature",
  "properties": {
    "gn:admin1_code":"77",
    "gn:asciiname":"Chalishchevo",
    "gn:country_code":"RU",
    "gn:dem":232,
    "gn:feature_class":"P",
    "gn:feature_code":"PPL",
    "gn:name":"Chalishchevo",
    "gn:population":0,
    "gn:timezone":"Europe/Moscow",
    "iso:country":"RU",
    "name:rus_x_preferred":[
        "\u0427\u0430\u043b\u0438\u0449\u0435\u0432\u043e"
    ],
    "name:und_x_variant":[
        "\u0427\u0430\u043b\u0438\u0449\u0435\u0432\u043e"
    ],
    "wof:name":"Chalishchevo",
    "wof:placetype":"locality"
},
  "geometry": {"coordinates":[32.18917,56.89528000000001],"type":"Point"}
}