{
  "type": "Feature",
  "properties": {
    "gn:admin1_code":"80",
    "gn:asciiname":"Nyaz'-Vortsy",
    "gn:country_code":"RU",
    "gn:dem":191,
    "gn:feature_class":"P",
    "gn:feature_code":"PPL",
    "gn:name":"Nyaz\u2019-Vortsy",
    "gn:population":0,
    "gn:timezone":"Europe/Samara",
    "iso:country":"RU",
    "name:rus_x_preferred":[
        "\u041d\u044f\u0437\u044c-\u0412\u043e\u0440\u0446\u044b"
    ],
    "name:und_x_variant":[
        "Nyaz\u2019-Vortsy"
    ],
    "wof:name":"Nyaz'-Vortsy",
    "wof:placetype":"locality"
},
  "geometry": {"coordinates":[53.2311,57.4173],"type":"Point"}
}