{
  "type": "Feature",
  "properties": {
    "gn:admin1_code":"33",
    "gn:asciiname":"Verkhneye Kokor'ye",
    "gn:country_code":"RU",
    "gn:dem":132,
    "gn:feature_class":"P",
    "gn:feature_code":"PPL",
    "gn:name":"Verkhneye Kokor\u2019ye",
    "gn:population":0,
    "gn:timezone":"Europe/Kirov",
    "iso:country":"RU",
    "wof:name":"Verkhneye Kokor'ye",
    "wof:placetype":"locality"
},
  "geometry": {"coordinates":[51.06667,59.23333],"type":"Point"}
}