{
  "type": "Feature",
  "properties": {
    "gn:admin1_code":"30",
    "gn:asciiname":"Susanino",
    "gn:country_code":"RU",
    "gn:dem":23,
    "gn:feature_class":"P",
    "gn:feature_code":"PPL",
    "gn:name":"Susanino",
    "gn:population":0,
    "gn:timezone":"Asia/Vladivostok",
    "iso:country":"RU",
    "name:eng_x_preferred":[
        "Susanino"
    ],
    "name:nor_x_preferred":[
        "Susanino"
    ],
    "name:rus_x_preferred":[
        "\u0421\u0443\u0441\u0430\u043d\u0438\u043d\u043e"
    ],
    "name:und_x_variant":[
        "Mkhel\u2019",
        "Mikhel\u2019"
    ],
    "wof:name":"Susanino",
    "wof:placetype":"locality"
},
  "geometry": {"coordinates":[140.08041,52.78623],"type":"Point"}
}