{
  "type": "Feature",
  "properties": {
    "gn:admin1_code":"25.0",
    "gn:asciiname":"Dolgaya",
    "gn:country_code":"RU",
    "gn:dem":181,
    "gn:feature_class":"P",
    "gn:feature_code":"PPL",
    "gn:name":"Dolgaya",
    "gn:population":0,
    "gn:timezone":"Europe/Moscow",
    "iso:country":"RU",
    "name:rus_x_preferred":[
        "\u0414\u043e\u043b\u0433\u0430\u044f"
    ],
    "wof:name":"Dolgaya",
    "wof:placetype":"locality"
},
  "geometry": {"coordinates":[35.89586,53.77448],"type":"Point"}
}