{
  "type": "Feature",
  "properties": {
    "gn:admin1_code":"57",
    "gn:asciiname":"Mikhaylovka Vtoraya",
    "gn:country_code":"RU",
    "gn:dem":130,
    "gn:feature_class":"P",
    "gn:feature_code":"PPL",
    "gn:name":"Mikhaylovka Vtoraya",
    "gn:population":0,
    "gn:timezone":"Europe/Moscow",
    "iso:country":"RU",
    "name:rus_x_preferred":[
        "\u041c\u0438\u0445\u0430\u0439\u043b\u043e\u0432\u043a\u0430 \u0412\u0442\u043e\u0440\u0430\u044f"
    ],
    "name:und_x_variant":[
        "Mikhaylovka",
        "Mikhaylovka Vtoraya"
    ],
    "wof:name":"Mikhaylovka Vtoraya",
    "wof:placetype":"locality"
},
  "geometry": {"coordinates":[42.14478,53.66354000000001],"type":"Point"}
}