{
  "type": "Feature",
  "properties": {
    "gn:admin1_code":"6.0",
    "gn:asciiname":"Tegra-Verkhnyaya",
    "gn:country_code":"RU",
    "gn:dem":31,
    "gn:feature_class":"P",
    "gn:feature_code":"PPL",
    "gn:name":"Tegra-Verkhnyaya",
    "gn:population":0,
    "gn:timezone":"Europe/Moscow",
    "iso:country":"RU",
    "name:rus_x_preferred":[
        "\u0422\u0435\u0433\u0440\u0430-\u0412\u0435\u0440\u0445\u043d\u044f\u044f"
    ],
    "wof:name":"Tegra-Verkhnyaya",
    "wof:placetype":"locality"
},
  "geometry": {"coordinates":[41.3696,63.3812],"type":"Point"}
}