{
  "type": "Feature",
  "properties": {
    "gn:admin1_code":"83",
    "gn:asciiname":"Novoselka",
    "gn:country_code":"RU",
    "gn:dem":105,
    "gn:feature_class":"P",
    "gn:feature_code":"PPL",
    "gn:name":"Novos\u00eblka",
    "gn:population":0,
    "gn:timezone":"Europe/Moscow",
    "iso:country":"RU",
    "name:rus_x_preferred":[
        "\u041d\u043e\u0432\u043e\u0441\u0451\u043b\u043a\u0430"
    ],
    "name:und_x_variant":[
        "Novos\u00eblka"
    ],
    "wof:name":"Novoselka",
    "wof:placetype":"locality"
},
  "geometry": {"coordinates":[40.5354,56.41717],"type":"Point"}
}