{
  "type": "Feature",
  "properties": {
    "gn:admin1_code":"17.0",
    "gn:asciiname":"Shovkra",
    "gn:country_code":"RU",
    "gn:dem":1615,
    "gn:feature_class":"P",
    "gn:feature_code":"PPL",
    "gn:name":"Shovkra",
    "gn:population":0,
    "gn:timezone":"Europe/Moscow",
    "iso:country":"RU",
    "name:rus_x_preferred":[
        "\u0428\u043e\u0432\u043a\u0440\u0430"
    ],
    "name:und_x_variant":[
        "Shovka",
        "Shovkra",
        "\u0428\u043e\u0432\u043a\u0440\u0430"
    ],
    "wof:name":"Shovkra",
    "wof:placetype":"locality"
},
  "geometry": {"coordinates":[47.12741,42.14008],"type":"Point"}
}