{
  "type": "Feature",
  "properties": {
    "gn:admin1_code":"61.0",
    "gn:asciiname":"Chunusovskiy",
    "gn:cc2":"RU",
    "gn:country_code":"RU",
    "gn:dem":51,
    "gn:feature_class":"P",
    "gn:feature_code":"PPL",
    "gn:name":"Chunusovskiy",
    "gn:population":0,
    "gn:timezone":"Europe/Moscow",
    "iso:country":"RU",
    "name:rus_x_preferred":[
        "\u0427\u0443\u043d\u0443\u0441\u043e\u0432\u0441\u043a\u0438\u0439"
    ],
    "name:und_x_variant":[
        "Chunusovskaya",
        "Chunusovskiy",
        "\u0427\u0443\u043d\u0443\u0441\u043e\u0432\u0441\u043a\u0438\u0439"
    ],
    "wof:name":"Chunusovskiy",
    "wof:placetype":"locality"
},
  "geometry": {"coordinates":[42.86833,47.23139000000001],"type":"Point"}
}