{
  "type": "Feature",
  "properties": {
    "gn:admin1_code":"69",
    "gn:asciiname":"Rednya",
    "gn:country_code":"RU",
    "gn:dem":214,
    "gn:feature_class":"P",
    "gn:feature_code":"PPL",
    "gn:name":"Rednya",
    "gn:population":0,
    "gn:timezone":"Europe/Moscow",
    "iso:country":"RU",
    "name:rus_x_preferred":[
        "\u0420\u0435\u0434\u043d\u044f"
    ],
    "name:und_x_variant":[
        "\u0420\u0435\u0434\u043d\u044f",
        "Rednya"
    ],
    "wof:name":"Rednya",
    "wof:placetype":"locality"
},
  "geometry": {"coordinates":[32.12027,55.08949000000001],"type":"Point"}
}