{
  "type": "Feature",
  "properties": {
    "gn:admin1_code":"69",
    "gn:asciiname":"Shishkino",
    "gn:country_code":"RU",
    "gn:dem":203,
    "gn:feature_class":"P",
    "gn:feature_code":"PPL",
    "gn:name":"Shishkino",
    "gn:population":0,
    "gn:timezone":"Europe/Moscow",
    "iso:country":"RU",
    "name:che_x_preferred":[
        "\u0428\u0438\u0448\u043a\u0438\u043d\u043e"
    ],
    "name:rus_x_preferred":[
        "\u0428\u0438\u0448\u043a\u0438\u043d\u043e"
    ],
    "wof:name":"Shishkino",
    "wof:placetype":"locality"
},
  "geometry": {"coordinates":[32.41222,54.71528000000001],"type":"Point"}
}