{
  "type": "Feature",
  "properties": {
    "gn:admin1_code":"60",
    "gn:asciiname":"Lugovka",
    "gn:country_code":"RU",
    "gn:dem":88,
    "gn:feature_class":"P",
    "gn:feature_code":"PPL",
    "gn:name":"Lugovka",
    "gn:population":0,
    "gn:timezone":"Europe/Moscow",
    "iso:country":"RU",
    "name:rus_x_preferred":[
        "\u041b\u0443\u0433\u043e\u0432\u043a\u0430"
    ],
    "name:und_x_variant":[
        "Lugovo",
        "Lugovka",
        "Lugova"
    ],
    "wof:name":"Lugovka",
    "wof:placetype":"locality"
},
  "geometry": {"coordinates":[28.90499,57.04087],"type":"Point"}
}