{
  "type": "Feature",
  "properties": {
    "gn:admin1_code":"42.0",
    "gn:asciiname":"Bereg",
    "gn:country_code":"RU",
    "gn:dem":56,
    "gn:feature_class":"P",
    "gn:feature_code":"PPL",
    "gn:name":"Bereg",
    "gn:population":0,
    "gn:timezone":"Europe/Moscow",
    "iso:country":"RU",
    "name:nor_x_preferred":[
        "Bereg"
    ],
    "name:rus_x_preferred":[
        "\u0411\u0435\u0440\u0435\u0433"
    ],
    "wof:name":"Bereg",
    "wof:placetype":"locality"
},
  "geometry": {"coordinates":[29.98333,58.68333000000001],"type":"Point"}
}