{
  "type": "Feature",
  "properties": {
    "gn:admin1_code":"72",
    "gn:asciiname":"Novokrugloye",
    "gn:country_code":"RU",
    "gn:dem":139,
    "gn:feature_class":"P",
    "gn:feature_code":"PPL",
    "gn:name":"Novokrugloye",
    "gn:population":0,
    "gn:timezone":"Europe/Moscow",
    "iso:country":"RU",
    "name:rus_x_preferred":[
        "\u041d\u043e\u0432\u043e\u043a\u0440\u0443\u0433\u043b\u043e\u0435"
    ],
    "name:und_x_variant":[
        "Novoye Krugloye",
        "Novokrugloye"
    ],
    "wof:name":"Novokrugloye",
    "wof:placetype":"locality"
},
  "geometry": {"coordinates":[40.832,53.0229],"type":"Point"}
}