{
  "type": "Feature",
  "properties": {
    "gn:admin1_code":"77",
    "gn:asciiname":"Pokrovskoye",
    "gn:country_code":"RU",
    "gn:dem":243,
    "gn:feature_class":"P",
    "gn:feature_code":"PPL",
    "gn:name":"Pokrovskoye",
    "gn:population":0,
    "gn:timezone":"Europe/Moscow",
    "iso:country":"RU",
    "name:eng_x_preferred":[
        "Pokrovskoye"
    ],
    "name:nor_x_preferred":[
        "Pokrovskoje"
    ],
    "name:rus_x_preferred":[
        "\u041f\u043e\u043a\u0440\u043e\u0432\u0441\u043a\u043e\u0435"
    ],
    "wof:name":"Pokrovskoye",
    "wof:placetype":"locality"
},
  "geometry": {"coordinates":[32.07918,56.49608000000001],"type":"Point"}
}