{
  "type": "Feature",
  "properties": {
    "gn:admin1_code":"45",
    "gn:asciiname":"Tsinglok",
    "gn:country_code":"RU",
    "gn:dem":108,
    "gn:feature_class":"P",
    "gn:feature_code":"PPL",
    "gn:name":"Tsinglok",
    "gn:population":0,
    "gn:timezone":"Europe/Moscow",
    "iso:country":"RU",
    "name:rus_x_preferred":[
        "\u0426\u0438\u043d\u0433\u043b\u043e\u043a"
    ],
    "wof:name":"Tsinglok",
    "wof:placetype":"locality"
},
  "geometry": {"coordinates":[46.7854,56.6348],"type":"Point"}
}