{
  "type": "Feature",
  "properties": {
    "gn:admin1_code":"56",
    "gn:asciiname":"Kudryayevka",
    "gn:country_code":"RU",
    "gn:dem":244,
    "gn:feature_class":"P",
    "gn:feature_code":"PPL",
    "gn:name":"Kudryayevka",
    "gn:population":0,
    "gn:timezone":"Europe/Moscow",
    "iso:country":"RU",
    "name:rus_x_preferred":[
        "\u041a\u0443\u0434\u0440\u044f\u0435\u0432\u043a\u0430"
    ],
    "name:und_x_variant":[
        "Kurdyayevka",
        "Kurdyavka",
        "Kudryayevka",
        "\u041a\u0443\u0434\u0440\u044f\u0435\u0432\u043a\u0430"
    ],
    "wof:name":"Kudryayevka",
    "wof:placetype":"locality"
},
  "geometry": {"coordinates":[37.32114,53.01037],"type":"Point"}
}