{
  "type": "Feature",
  "properties": {
    "gn:admin1_code":"71",
    "gn:asciiname":"Polevskoy Uchastok",
    "gn:country_code":"RU",
    "gn:dem":302,
    "gn:feature_class":"P",
    "gn:feature_code":"PPL",
    "gn:name":"Polevskoy Uchastok",
    "gn:population":0,
    "gn:timezone":"Asia/Yekaterinburg",
    "iso:country":"RU",
    "name:rus_x_preferred":[
        "\u041f\u043e\u043b\u0435\u0432\u0441\u043a\u043e\u0439 \u0423\u0447\u0430\u0441\u0442\u043e\u043a"
    ],
    "wof:name":"Polevskoy Uchastok",
    "wof:placetype":"locality"
},
  "geometry": {"coordinates":[60.6526,56.55174],"type":"Point"}
}