{
  "type": "Feature",
  "properties": {
    "gn:admin1_code":"40",
    "gn:asciiname":"Sosnovyy",
    "gn:country_code":"RU",
    "gn:dem":98,
    "gn:feature_class":"P",
    "gn:feature_code":"PPL",
    "gn:name":"Sosnovyy",
    "gn:population":0,
    "gn:timezone":"Asia/Yekaterinburg",
    "iso:country":"RU",
    "name:rus_x_preferred":[
        "\u0421\u043e\u0441\u043d\u043e\u0432\u044b\u0439"
    ],
    "wof:name":"Sosnovyy",
    "wof:placetype":"locality"
},
  "geometry": {"coordinates":[65.11944,54.92639000000001],"type":"Point"}
}