{
  "type": "Feature",
  "properties": {
    "gn:admin1_code":"84",
    "gn:asciiname":"Zakharovka",
    "gn:country_code":"RU",
    "gn:dem":65,
    "gn:feature_class":"P",
    "gn:feature_code":"PPL",
    "gn:name":"Zakharovka",
    "gn:population":0,
    "gn:timezone":"Europe/Volgograd",
    "iso:country":"RU",
    "name:eng_x_preferred":[
        "Zakharovka"
    ],
    "name:nor_x_preferred":[
        "Zakharovka"
    ],
    "name:rus_x_preferred":[
        "\u0417\u0430\u0445\u0430\u0440\u043e\u0432\u043a\u0430"
    ],
    "wof:name":"Zakharovka",
    "wof:placetype":"locality"
},
  "geometry": {"coordinates":[44.36353,49.71009],"type":"Point"}
}