{
  "type": "Feature",
  "properties": {
    "gn:admin1_code":"41.0",
    "gn:asciiname":"Dronyayevo",
    "gn:country_code":"RU",
    "gn:dem":157,
    "gn:feature_class":"P",
    "gn:feature_code":"PPL",
    "gn:name":"Dronyayevo",
    "gn:population":0,
    "gn:timezone":"Europe/Moscow",
    "iso:country":"RU",
    "name:eng_x_preferred":[
        "Dronyayevo"
    ],
    "name:nor_x_preferred":[
        "Dronjaevo"
    ],
    "name:rus_x_preferred":[
        "\u0414\u0440\u043e\u043d\u044f\u0435\u0432\u043e"
    ],
    "wof:name":"Dronyayevo",
    "wof:placetype":"locality"
},
  "geometry": {"coordinates":[35.6172,51.7114],"type":"Point"}
}