{
  "type": "Feature",
  "properties": {
    "gn:admin1_code":"55",
    "gn:asciiname":"Lekarevka",
    "gn:country_code":"RU",
    "gn:dem":142,
    "gn:feature_class":"P",
    "gn:feature_code":"PPL",
    "gn:name":"Lekarevka",
    "gn:population":0,
    "gn:timezone":"Asia/Yekaterinburg",
    "iso:country":"RU",
    "name:eng_x_preferred":[
        "Lekarevka"
    ],
    "name:nor_x_preferred":[
        "Lekarevka"
    ],
    "name:rus_x_preferred":[
        "\u041b\u0435\u043a\u0430\u0440\u0435\u0432\u043a\u0430"
    ],
    "wof:name":"Lekarevka",
    "wof:placetype":"locality"
},
  "geometry": {"coordinates":[52.73813000000001,53.47405],"type":"Point"}
}