{
  "type": "Feature",
  "properties": {
    "gn:admin1_code":"90.0",
    "gn:asciiname":"Dorosheva",
    "gn:country_code":"RU",
    "gn:dem":146,
    "gn:feature_class":"P",
    "gn:feature_code":"PPL",
    "gn:name":"Dorosheva",
    "gn:population":0,
    "gn:timezone":"Asia/Yekaterinburg",
    "iso:country":"RU",
    "name:nor_x_preferred":[
        "Dorosjeva"
    ],
    "name:rus_x_preferred":[
        "\u0414\u043e\u0440\u043e\u0448\u0435\u0432\u0430"
    ],
    "wof:name":"Dorosheva",
    "wof:placetype":"locality"
},
  "geometry": {"coordinates":[56.03333000000001,58.98333],"type":"Point"}
}