{
  "type": "Feature",
  "properties": {
    "gn:admin1_code":"33",
    "gn:asciiname":"Bol'shoye Saltayevo",
    "gn:country_code":"RU",
    "gn:dem":117,
    "gn:feature_class":"P",
    "gn:feature_code":"PPL",
    "gn:name":"Bol\u2019shoye Saltayevo",
    "gn:population":0,
    "gn:timezone":"Europe/Kirov",
    "iso:country":"RU",
    "name:rus_x_preferred":[
        "\u0411\u043e\u043b\u044c\u0448\u043e\u0435 \u0421\u0430\u043b\u0442\u0430\u0435\u0432\u043e"
    ],
    "name:und_x_variant":[
        "Bol\u2019shoye Saltayevo"
    ],
    "wof:name":"Bol'shoye Saltayevo",
    "wof:placetype":"locality"
},
  "geometry": {"coordinates":[47.2044,57.2367],"type":"Point"}
}