{
  "type": "Feature",
  "properties": {
    "gn:admin1_code":"20",
    "gn:asciiname":"Solyanka",
    "gn:cc2":"RU",
    "gn:country_code":"RU",
    "gn:dem":373,
    "gn:feature_class":"P",
    "gn:feature_code":"PPL",
    "gn:name":"Solyanka",
    "gn:population":0,
    "gn:timezone":"Asia/Irkutsk",
    "iso:country":"RU",
    "name:rus_x_preferred":[
        "\u0421\u043e\u043b\u044f\u043d\u043a\u0430"
    ],
    "name:und_x_variant":[
        "Solyanna",
        "Solyanka",
        "\u0421\u043e\u043b\u044f\u043d\u043a\u0430"
    ],
    "wof:name":"Solyanka",
    "wof:placetype":"locality"
},
  "geometry": {"coordinates":[111.59999999999999,59.06667],"type":"Point"}
}