{
  "type": "Feature",
  "properties": {
    "gn:admin1_code":"20",
    "gn:asciiname":"Solyanka",
    "gn:cc2":"RU",
    "gn:country_code":"RU",
    "gn:dem":373,
    "gn:feature_class":"P",
    "gn:feature_code":"PPL",
    "gn:name":"Solyanka",
    "gn:population":0,
    "gn:timezone":"Asia/Irkutsk",
    "iso:country":"RU",
    "name:bel_x_preferred":[
        "\u0421\u0430\u043b\u044f\u043d\u043a\u0430"
    ],
    "name:ces_x_preferred":[
        "Soljanka"
    ],
    "name:dan_x_preferred":[
        "Soljanka"
    ],
    "name:deu_x_preferred":[
        "Soljanka"
    ],
    "name:est_x_preferred":[
        "Seljanka"
    ],
    "name:fas_x_preferred":[
        "\u0633\u0648\u0644\u06cc\u0627\u0646\u06a9\u0627"
    ],
    "name:fin_x_preferred":[
        "Seljanka"
    ],
    "name:fra_x_preferred":[
        "Solianka"
    ],
    "name:hrv_x_preferred":[
        "Soljanka"
    ],
    "name:hun_x_preferred":[
        "Szolj\u00e1nka"
    ],
    "name:hye_x_preferred":[
        "\u054d\u0578\u056c\u0575\u0561\u0576\u056f\u0561"
    ],
    "name:ind_x_preferred":[
        "Solyanka"
    ],
    "name:jpn_x_preferred":[
        "\u30bd\u30ea\u30e3\u30f3\u30ab"
    ],
    "name:kaz_x_preferred":[
        "\u0421\u043e\u043b\u044f\u043d\u043a\u0430"
    ],
    "name:kor_x_preferred":[
        "\uc194\ub7b8\uce74"
    ],
    "name:nld_x_preferred":[
        "Soljanka"
    ],
    "name:pol_x_preferred":[
        "Solanka"
    ],
    "name:por_x_preferred":[
        "Solyanka"
    ],
    "name:rus_x_preferred":[
        "\u0421\u043e\u043b\u044f\u043d\u043a\u0430"
    ],
    "name:spa_x_preferred":[
        "Solianka"
    ],
    "name:swe_x_preferred":[
        "Soljanka"
    ],
    "name:ukr_x_preferred":[
        "\u0421\u043e\u043b\u044f\u043d\u043a\u0430"
    ],
    "name:und_x_variant":[
        "Solyanna",
        "Solyanka",
        "\u0421\u043e\u043b\u044f\u043d\u043a\u0430"
    ],
    "name:zho_x_preferred":[
        "\u96dc\u62cc\u6e6f"
    ],
    "wof:name":"Solyanka",
    "wof:placetype":"locality"
},
  "geometry": {"coordinates":[111.59999999999999,59.06667],"type":"Point"}
}