{
  "type": "Feature",
  "properties": {
    "gn:admin1_code":"77",
    "gn:asciiname":"Tartsevo",
    "gn:country_code":"RU",
    "gn:dem":130,
    "gn:feature_class":"P",
    "gn:feature_code":"PPL",
    "gn:name":"Tartsevo",
    "gn:population":0,
    "gn:timezone":"Europe/Moscow",
    "iso:country":"RU",
    "name:rus_x_preferred":[
        "\u0422\u0430\u0440\u0446\u0435\u0432\u043e"
    ],
    "name:und_x_variant":[
        "\u0422\u0430\u0440\u0446\u0435\u0432\u043e"
    ],
    "wof:name":"Tartsevo",
    "wof:placetype":"locality"
},
  "geometry": {"coordinates":[37.9643,57.1104],"type":"Point"}
}