{
  "type": "Feature",
  "properties": {
    "gn:admin1_code":"9.0",
    "gn:asciiname":"Averino",
    "gn:country_code":"RU",
    "gn:dem":240,
    "gn:feature_class":"P",
    "gn:feature_code":"PPL",
    "gn:name":"Averino",
    "gn:population":0,
    "gn:timezone":"Europe/Moscow",
    "iso:country":"RU",
    "name:nor_x_preferred":[
        "Averino"
    ],
    "name:rus_x_preferred":[
        "\u0410\u0432\u0435\u0440\u0438\u043d\u043e"
    ],
    "wof:name":"Averino",
    "wof:placetype":"locality"
},
  "geometry": {"coordinates":[37.4459,51.2904],"type":"Point"}
}