{
  "type": "Feature",
  "properties": {
    "gn:admin1_code":"92",
    "gn:asciiname":"Ketkino",
    "gn:country_code":"RU",
    "gn:dem":36,
    "gn:feature_class":"P",
    "gn:feature_code":"PPL",
    "gn:name":"Ketkino",
    "gn:population":0,
    "gn:timezone":"Asia/Kamchatka",
    "iso:country":"RU",
    "name:rus_x_preferred":[
        "\u041a\u0435\u0442\u043a\u0438\u043d\u043e"
    ],
    "wof:name":"Ketkino",
    "wof:placetype":"locality"
},
  "geometry": {"coordinates":[158.32232999999999,53.26542],"type":"Point"}
}