{
  "type": "Feature",
  "properties": {
    "gn:admin1_code":"51",
    "gn:asciiname":"Skryabino",
    "gn:country_code":"RU",
    "gn:dem":132,
    "gn:feature_class":"P",
    "gn:feature_code":"PPL",
    "gn:name":"Skryabino",
    "gn:population":0,
    "gn:timezone":"Europe/Moscow",
    "iso:country":"RU",
    "name:eng_x_preferred":[
        "Skryabino"
    ],
    "name:nor_x_preferred":[
        "Skrjabino"
    ],
    "name:rus_x_preferred":[
        "\u0421\u043a\u0440\u044f\u0431\u0438\u043d\u043e"
    ],
    "wof:name":"Skryabino",
    "wof:placetype":"locality"
},
  "geometry": {"coordinates":[45.88355,58.00435],"type":"Point"}
}