{
  "type": "Feature",
  "properties": {
    "gn:admin1_code":"33.0",
    "gn:asciiname":"Malygintsy",
    "gn:country_code":"RU",
    "gn:dem":209,
    "gn:feature_class":"P",
    "gn:feature_code":"PPL",
    "gn:name":"Malygintsy",
    "gn:population":0,
    "gn:timezone":"Europe/Kirov",
    "iso:country":"RU",
    "name:rus_x_preferred":[
        "\u041c\u0430\u043b\u044b\u0433\u0438\u043d\u0446\u044b"
    ],
    "name:und_x_variant":[
        "Molygintsy",
        "Malygintsy"
    ],
    "wof:name":"Malygintsy",
    "wof:placetype":"locality"
},
  "geometry": {"coordinates":[50.51319,59.3489],"type":"Point"}
}