{
  "type": "Feature",
  "properties": {
    "gn:admin1_code":"86",
    "gn:asciiname":"Grechishkina",
    "gn:country_code":"RU",
    "gn:dem":142,
    "gn:feature_class":"P",
    "gn:feature_code":"PPL",
    "gn:name":"Grechishkina",
    "gn:population":0,
    "gn:timezone":"Europe/Moscow",
    "iso:country":"RU",
    "name:rus_x_preferred":[
        "\u0413\u0440\u0435\u0447\u0438\u0448\u043a\u0438\u043d\u0430"
    ],
    "wof:name":"Grechishkina",
    "wof:placetype":"locality"
},
  "geometry": {"coordinates":[39.36667,51.48333],"type":"Point"}
}