{
  "type": "Feature",
  "properties": {
    "gn:admin1_code":"84",
    "gn:asciiname":"Verkhneosinovskiy",
    "gn:country_code":"RU",
    "gn:dem":70,
    "gn:feature_class":"P",
    "gn:feature_code":"PPL",
    "gn:name":"Verkhneosinovskiy",
    "gn:population":0,
    "gn:timezone":"Europe/Volgograd",
    "iso:country":"RU",
    "name:eng_x_preferred":[
        "Verkhneosinovskiy"
    ],
    "name:nor_x_preferred":[
        "Verkhneosinovskij"
    ],
    "name:rus_x_preferred":[
        "\u0412\u0435\u0440\u0445\u043d\u0435\u043e\u0441\u0438\u043d\u043e\u0432\u0441\u043a\u0438\u0439"
    ],
    "name:und_x_variant":[
        "Verkhno-Osinovka",
        "Verkhnyaya Osinovka"
    ],
    "wof:name":"Verkhneosinovskiy",
    "wof:placetype":"locality"
},
  "geometry": {"coordinates":[42.77439,48.68141],"type":"Point"}
}