{
  "type": "Feature",
  "properties": {
    "gn:admin1_code":"53",
    "gn:asciiname":"Sorochikha",
    "gn:country_code":"RU",
    "gn:dem":110,
    "gn:feature_class":"P",
    "gn:feature_code":"PPL",
    "gn:name":"Sorochikha",
    "gn:population":0,
    "gn:timezone":"Asia/Novosibirsk",
    "iso:country":"RU",
    "name:eng_x_preferred":[
        "Sorochikha"
    ],
    "name:nor_x_preferred":[
        "Sorotsjikha"
    ],
    "name:rus_x_preferred":[
        "\u0421\u043e\u0440\u043e\u0447\u0438\u0445\u0430"
    ],
    "name:und_x_variant":[
        "\u0421\u043e\u0440\u043e\u0447\u0438\u0445\u0430",
        "Sorochikha"
    ],
    "wof:name":"Sorochikha",
    "wof:placetype":"locality"
},
  "geometry": {"coordinates":[77.94832,53.73174],"type":"Point"}
}