{
  "type": "Feature",
  "properties": {
    "gn:admin1_code":"75",
    "gn:asciiname":"Novomargino",
    "gn:country_code":"RU",
    "gn:dem":47,
    "gn:feature_class":"P",
    "gn:feature_code":"PPL",
    "gn:name":"Novomargino",
    "gn:population":0,
    "gn:timezone":"Asia/Tomsk",
    "iso:country":"RU",
    "name:rus_x_preferred":[
        "\u041d\u043e\u0432\u043e\u043c\u0430\u0440\u0433\u0438\u043d\u043e"
    ],
    "name:und_x_variant":[
        "\u041d\u043e\u0432\u043e\u043c\u0430\u0440\u0433\u0438\u043d\u043e"
    ],
    "wof:name":"Novomargino",
    "wof:placetype":"locality"
},
  "geometry": {"coordinates":[80.33333,58.93333000000001],"type":"Point"}
}