{
  "type": "Feature",
  "properties": {
    "gn:admin1_code":"10",
    "gn:asciiname":"Kazanovo",
    "gn:country_code":"RU",
    "gn:dem":161,
    "gn:feature_class":"P",
    "gn:feature_code":"PPL",
    "gn:name":"Kazanovo",
    "gn:population":0,
    "gn:timezone":"Europe/Moscow",
    "iso:country":"RU",
    "name:rus_x_preferred":[
        "\u041a\u0430\u0437\u0430\u043d\u043e\u0432\u043e"
    ],
    "wof:name":"Kazanovo",
    "wof:placetype":"locality"
},
  "geometry": {"coordinates":[33.55086,53.15133],"type":"Point"}
}