{
  "type": "Feature",
  "properties": {
    "gn:admin1_code":"25.0",
    "gn:asciiname":"Dabuzha",
    "gn:country_code":"RU",
    "gn:dem":232,
    "gn:feature_class":"P",
    "gn:feature_code":"PPL",
    "gn:name":"Dabuzha",
    "gn:population":0,
    "gn:timezone":"Europe/Moscow",
    "iso:country":"RU",
    "name:rus_x_preferred":[
        "\u0414\u0430\u0431\u0443\u0436\u0430"
    ],
    "wof:name":"Dabuzha",
    "wof:placetype":"locality"
},
  "geometry": {"coordinates":[34.75039,54.22066],"type":"Point"}
}