{
  "type": "Feature",
  "properties": {
    "gn:admin1_code":"17",
    "gn:asciiname":"Maydan-Kent",
    "gn:country_code":"RU",
    "gn:dem":279,
    "gn:feature_class":"P",
    "gn:feature_code":"PPL",
    "gn:name":"Maydan-Kent",
    "gn:population":0,
    "gn:timezone":"Europe/Moscow",
    "iso:country":"RU",
    "name:rus_x_preferred":[
        "\u041c\u0430\u0439\u0434\u0430\u043d-\u041a\u0435\u043d\u0442"
    ],
    "name:und_x_variant":[
        "\u041c\u0430\u0439\u0434\u0430\u043d-\u041a\u0435\u043d\u0442"
    ],
    "wof:name":"Maydan-Kent",
    "wof:placetype":"locality"
},
  "geometry": {"coordinates":[48.06667,42.03361],"type":"Point"}
}