{
  "type": "Feature",
  "properties": {
    "gn:admin1_code":"25.0",
    "gn:asciiname":"Babayevo",
    "gn:country_code":"RU",
    "gn:dem":216,
    "gn:feature_class":"P",
    "gn:feature_code":"PPL",
    "gn:name":"Babayevo",
    "gn:population":0,
    "gn:timezone":"Europe/Moscow",
    "iso:country":"RU",
    "name:nor_x_preferred":[
        "Babajevo"
    ],
    "name:rus_x_preferred":[
        "\u0411\u0430\u0431\u0430\u0435\u0432\u043e"
    ],
    "name:und_x_variant":[
        "Bobayevo",
        "Babayevo"
    ],
    "wof:name":"Babayevo",
    "wof:placetype":"locality"
},
  "geometry": {"coordinates":[36.50321,54.73597],"type":"Point"}
}