{
  "type": "Feature",
  "properties": {
    "gn:admin1_code":"60",
    "gn:asciiname":"Mostishchi",
    "gn:country_code":"RU",
    "gn:dem":123,
    "gn:feature_class":"P",
    "gn:feature_code":"PPL",
    "gn:name":"Mostishchi",
    "gn:population":0,
    "gn:timezone":"Europe/Moscow",
    "iso:country":"RU",
    "name:rus_x_preferred":[
        "\u041c\u043e\u0441\u0442\u0438\u0449\u0438"
    ],
    "wof:name":"Mostishchi",
    "wof:placetype":"locality"
},
  "geometry": {"coordinates":[28.82578,56.62475],"type":"Point"}
}