{
  "type": "Feature",
  "properties": {
    "gn:admin1_code":"61",
    "gn:asciiname":"Tsypkin",
    "gn:country_code":"RU",
    "gn:dem":111,
    "gn:feature_class":"P",
    "gn:feature_code":"PPL",
    "gn:name":"Tsypkin",
    "gn:population":0,
    "gn:timezone":"Europe/Moscow",
    "iso:country":"RU",
    "wof:name":"Tsypkin",
    "wof:placetype":"locality"
},
  "geometry": {"coordinates":[41.41026,49.04424],"type":"Point"}
}