{
  "type": "Feature",
  "properties": {
    "gn:admin1_code":"11",
    "gn:asciiname":"Tonnel'nyy",
    "gn:country_code":"RU",
    "gn:dem":829,
    "gn:feature_class":"P",
    "gn:feature_code":"PPL",
    "gn:name":"Tonnel\u2019nyy",
    "gn:population":0,
    "gn:timezone":"Asia/Irkutsk",
    "iso:country":"RU",
    "name:eng_x_preferred":[
        "Tonnel'nyy"
    ],
    "name:nor_x_preferred":[
        "Tonnelnyj"
    ],
    "name:rus_x_preferred":[
        "\u0422\u043e\u043d\u043d\u0435\u043b\u044c\u043d\u044b\u0439"
    ],
    "name:und_x_variant":[
        "Tonnel\u2019nyy"
    ],
    "wof:name":"Tonnel'nyy",
    "wof:placetype":"locality"
},
  "geometry": {"coordinates":[113.34927,56.28738000000001],"type":"Point"}
}