{
  "type": "Feature",
  "properties": {
    "gn:admin1_code":"88.0",
    "gn:asciiname":"Fenevo",
    "gn:country_code":"RU",
    "gn:dem":126,
    "gn:feature_class":"P",
    "gn:feature_code":"PPL",
    "gn:name":"Fen\u00ebvo",
    "gn:population":0,
    "gn:timezone":"Europe/Moscow",
    "iso:country":"RU",
    "name:rus_x_preferred":[
        "\u0424\u0435\u043d\u0451\u0432\u043e"
    ],
    "name:und_x_variant":[
        "Fen\u00ebvo",
        "\u0424\u0435\u043d\u0451\u0432\u043e"
    ],
    "wof:name":"Fenevo",
    "wof:placetype":"locality"
},
  "geometry": {"coordinates":[40.059,58.43600000000001],"type":"Point"}
}