{
  "type": "Feature",
  "properties": {
    "gn:admin1_code":"88",
    "gn:asciiname":"Lyagichino",
    "gn:country_code":"RU",
    "gn:dem":154,
    "gn:feature_class":"P",
    "gn:feature_code":"PPL",
    "gn:name":"Lyagichino",
    "gn:population":0,
    "gn:timezone":"Europe/Moscow",
    "iso:country":"RU",
    "name:rus_x_preferred":[
        "\u041b\u044f\u0433\u0438\u0447\u0438\u043d\u043e"
    ],
    "wof:name":"Lyagichino",
    "wof:placetype":"locality"
},
  "geometry": {"coordinates":[39.33456,57.80061],"type":"Point"}
}