{
  "type": "Feature",
  "properties": {
    "gn:admin1_code":"88",
    "gn:asciiname":"Vasil'yevskoye",
    "gn:country_code":"RU",
    "gn:dem":83,
    "gn:feature_class":"P",
    "gn:feature_code":"PPL",
    "gn:name":"Vasil\u2019yevskoye",
    "gn:population":0,
    "gn:timezone":"Europe/Moscow",
    "iso:country":"RU",
    "name:und_x_variant":[
        "Sovkhoz Revolyutsiya",
        "Vasil\u2019yevskoye"
    ],
    "wof:name":"Vasil'yevskoye",
    "wof:placetype":"locality"
},
  "geometry": {"coordinates":[40.29843,57.78406],"type":"Point"}
}