{
  "type": "Feature",
  "properties": {
    "gn:admin1_code":"71",
    "gn:asciiname":"Sorokina",
    "gn:country_code":"RU",
    "gn:dem":59,
    "gn:feature_class":"P",
    "gn:feature_code":"PPL",
    "gn:name":"Sorokina",
    "gn:population":0,
    "gn:timezone":"Asia/Yekaterinburg",
    "iso:country":"RU",
    "name:fra_x_preferred":[
        "Sorokina"
    ],
    "name:rus_x_preferred":[
        "\u0421\u043e\u0440\u043e\u043a\u0438\u043d\u0430"
    ],
    "name:swe_x_preferred":[
        "Sorokina"
    ],
    "wof:name":"Sorokina",
    "wof:placetype":"locality"
},
  "geometry": {"coordinates":[63.76667,58.01667],"type":"Point"}
}