{
  "type": "Feature",
  "properties": {
    "gn:admin1_code":"72",
    "gn:asciiname":"Annenka",
    "gn:country_code":"RU",
    "gn:dem":135,
    "gn:feature_class":"P",
    "gn:feature_code":"PPL",
    "gn:name":"Annenka",
    "gn:population":0,
    "gn:timezone":"Europe/Moscow",
    "iso:country":"RU",
    "name:rus_x_preferred":[
        "\u0410\u043d\u043d\u0435\u043d\u043a\u0430"
    ],
    "name:und_x_variant":[
        "Shishkovo",
        "Annenka",
        "Pervaya Annenka"
    ],
    "wof:name":"Annenka",
    "wof:placetype":"locality"
},
  "geometry": {"coordinates":[40.6444,52.3957],"type":"Point"}
}