{
  "type": "Feature",
  "properties": {
    "gn:admin1_code":"38.0",
    "gn:asciiname":"Il'ichevskiy",
    "gn:country_code":"RU",
    "gn:dem":37,
    "gn:feature_class":"P",
    "gn:feature_code":"PPL",
    "gn:name":"Il\u2019ichevskiy",
    "gn:population":0,
    "gn:timezone":"Europe/Moscow",
    "iso:country":"RU",
    "name:rus_x_preferred":[
        "\u0418\u043b\u044c\u0438\u0447\u0435\u0432\u0441\u043a\u0438\u0439"
    ],
    "name:und_x_variant":[
        "Ichevskiy",
        "Il\u2019ichevskiy"
    ],
    "wof:name":"Il'ichevskiy",
    "wof:placetype":"locality"
},
  "geometry": {"coordinates":[37.79951,45.02879],"type":"Point"}
}