{
  "type": "Feature",
  "properties": {
    "gn:admin1_code":"76",
    "gn:asciiname":"Fat'yanovo",
    "gn:country_code":"RU",
    "gn:dem":143,
    "gn:feature_class":"P",
    "gn:feature_code":"PPL",
    "gn:name":"Fat\u2019yanovo",
    "gn:population":0,
    "gn:timezone":"Europe/Moscow",
    "iso:country":"RU",
    "name:rus_x_preferred":[
        "\u0424\u0430\u0442\u044c\u044f\u043d\u043e\u0432\u043e"
    ],
    "name:und_x_variant":[
        "Fat\u2019yanovo",
        "\u0424\u0430\u0442\u044c\u044f\u043d\u043e\u0432\u043e"
    ],
    "wof:name":"Fat'yanovo",
    "wof:placetype":"locality"
},
  "geometry": {"coordinates":[36.1435,53.7782],"type":"Point"}
}