{
  "type": "Feature",
  "properties": {
    "gn:admin1_code":"21",
    "gn:asciiname":"Kotovo",
    "gn:country_code":"RU",
    "gn:dem":142,
    "gn:feature_class":"P",
    "gn:feature_code":"PPL",
    "gn:name":"Kotovo",
    "gn:population":0,
    "gn:timezone":"Europe/Moscow",
    "iso:country":"RU",
    "name:rus_x_preferred":[
        "\u041a\u043e\u0442\u043e\u0432\u043e"
    ],
    "name:und_x_variant":[
        "\u041a\u043e\u0442\u043e\u0432\u043e"
    ],
    "wof:name":"Kotovo",
    "wof:placetype":"locality"
},
  "geometry": {"coordinates":[41.23959,57.17075],"type":"Point"}
}