{
  "type": "Feature",
  "properties": {
    "gn:admin1_code":"43.0",
    "gn:asciiname":"Poddubrovka",
    "gn:country_code":"RU",
    "gn:dem":153,
    "gn:feature_class":"P",
    "gn:feature_code":"PPL",
    "gn:name":"Poddubrovka",
    "gn:population":0,
    "gn:timezone":"Europe/Moscow",
    "iso:country":"RU",
    "name:rus_x_preferred":[
        "\u041f\u043e\u0434\u0434\u0443\u0431\u0440\u043e\u0432\u043a\u0430"
    ],
    "name:und_x_variant":[
        "Dubrovka",
        "Poddubrovka"
    ],
    "wof:name":"Poddubrovka",
    "wof:placetype":"locality"
},
  "geometry": {"coordinates":[40.4068,52.0833],"type":"Point"}
}