{
  "type": "Feature",
  "properties": {
    "gn:admin1_code":"11",
    "gn:asciiname":"Ganga",
    "gn:country_code":"RU",
    "gn:dem":693,
    "gn:feature_class":"P",
    "gn:feature_code":"PPL",
    "gn:name":"Ganga",
    "gn:population":0,
    "gn:timezone":"Asia/Irkutsk",
    "iso:country":"RU",
    "name:rus_x_preferred":[
        "\u0413\u0430\u043d\u0433\u0430"
    ],
    "wof:name":"Ganga",
    "wof:placetype":"locality"
},
  "geometry": {"coordinates":[110.07007,51.79404],"type":"Point"}
}