{
  "type": "Feature",
  "properties": {
    "gn:admin1_code":"69",
    "gn:asciiname":"Timoshevo",
    "gn:country_code":"RU",
    "gn:dem":193,
    "gn:feature_class":"P",
    "gn:feature_code":"PPL",
    "gn:name":"Timosh\u00ebvo",
    "gn:population":0,
    "gn:timezone":"Europe/Moscow",
    "iso:country":"RU",
    "name:rus_x_preferred":[
        "\u0422\u0438\u043c\u043e\u0448\u00eb\u0432\u043e"
    ],
    "name:und_x_variant":[
        "Timash\u00ebvo",
        "Timosh\u00ebvo"
    ],
    "wof:name":"Timoshevo",
    "wof:placetype":"locality"
},
  "geometry": {"coordinates":[32.73957,54.68581999999999],"type":"Point"}
}