{
  "type": "Feature",
  "properties": {
    "gn:admin1_code":"86",
    "gn:asciiname":"Kameno-Verkhovka",
    "gn:country_code":"RU",
    "gn:dem":94,
    "gn:feature_class":"P",
    "gn:feature_code":"PPL",
    "gn:name":"Kameno-Verkhovka",
    "gn:population":0,
    "gn:timezone":"Europe/Moscow",
    "iso:country":"RU",
    "name:rus_x_preferred":[
        "\u041a\u0430\u043c\u0435\u043d\u043d\u043e-\u0412\u0435\u0440\u0445\u043e\u0432\u043a\u0430"
    ],
    "name:und_x_variant":[
        "Kamenka-Verkhovskoye",
        "Kamenka",
        "Kamenno-Verkhovskoye",
        "Kameno-Verkhovskoye",
        "Kamenno-Verkhovka",
        "Kameno-Verkhovka"
    ],
    "wof:name":"Kameno-Verkhovka",
    "wof:placetype":"locality"
},
  "geometry": {"coordinates":[39.15106,51.35791],"type":"Point"}
}