{
  "type": "Feature",
  "properties": {
    "gn:admin1_code":"53",
    "gn:asciiname":"Akhtyrka",
    "gn:country_code":"RU",
    "gn:dem":114,
    "gn:feature_class":"P",
    "gn:feature_code":"PPL",
    "gn:name":"Akhtyrka",
    "gn:population":0,
    "gn:timezone":"Asia/Novosibirsk",
    "iso:country":"RU",
    "name:eng_x_preferred":[
        "Akhtyrka"
    ],
    "name:nor_x_preferred":[
        "Akhtyrka"
    ],
    "name:rus_x_preferred":[
        "\u0410\u0445\u0442\u044b\u0440\u043a\u0430"
    ],
    "name:und_x_variant":[
        "\u0410\u0445\u0442\u044b\u0440\u043a\u0430",
        "Akhtyrka"
    ],
    "wof:name":"Akhtyrka",
    "wof:placetype":"locality"
},
  "geometry": {"coordinates":[76.40283000000002,55.71083],"type":"Point"}
}