{
  "type": "Feature",
  "properties": {
    "gn:admin1_code":"33.0",
    "gn:asciiname":"Artekovo",
    "gn:country_code":"RU",
    "gn:dem":113,
    "gn:feature_class":"P",
    "gn:feature_code":"PPL",
    "gn:name":"Artekovo",
    "gn:population":0,
    "gn:timezone":"Europe/Kirov",
    "iso:country":"RU",
    "name:rus_x_preferred":[
        "\u0410\u0440\u0442\u0435\u043a\u043e\u0432\u043e"
    ],
    "wof:name":"Artekovo",
    "wof:placetype":"locality"
},
  "geometry": {"coordinates":[48.00405,57.47361],"type":"Point"}
}