{
  "type": "Feature",
  "properties": {
    "gn:admin1_code":"16",
    "gn:asciiname":"Yambakhtino",
    "gn:country_code":"RU",
    "gn:dem":148,
    "gn:feature_class":"P",
    "gn:feature_code":"PPL",
    "gn:name":"Yambakhtino",
    "gn:population":0,
    "gn:timezone":"Europe/Moscow",
    "iso:country":"RU",
    "name:rus_x_preferred":[
        "\u042f\u043c\u0431\u0430\u0445\u0442\u0438\u043d\u043e"
    ],
    "wof:name":"Yambakhtino",
    "wof:placetype":"locality"
},
  "geometry": {"coordinates":[47.3828,55.6874],"type":"Point"}
}