{
  "type": "Feature",
  "properties": {
    "gn:admin1_code":"49",
    "gn:asciiname":"Padun",
    "gn:cc2":"RU",
    "gn:country_code":"RU",
    "gn:dem":24,
    "gn:feature_class":"P",
    "gn:feature_code":"PPL",
    "gn:name":"Padun",
    "gn:population":0,
    "gn:timezone":"Europe/Moscow",
    "iso:country":"RU",
    "name:rus_x_preferred":[
        "\u041f\u0430\u0434\u0443\u043d"
    ],
    "name:und_x_variant":[
        "Paduny",
        "Padun"
    ],
    "wof:name":"Padun",
    "wof:placetype":"locality"
},
  "geometry": {"coordinates":[31.8401,68.60364],"type":"Point"}
}