{
  "type": "Feature",
  "properties": {
    "gn:admin1_code":"63",
    "gn:asciiname":"Kubalakh",
    "gn:country_code":"RU",
    "gn:dem":120,
    "gn:feature_class":"P",
    "gn:feature_code":"PPL",
    "gn:name":"Kubalakh",
    "gn:population":0,
    "gn:timezone":"Asia/Yakutsk",
    "iso:country":"RU",
    "name:rus_x_preferred":[
        "\u041a\u0443\u0431\u0430\u043b\u0430\u0445"
    ],
    "name:und_x_variant":[
        "\u041a\u0443\u0431\u0430\u043b\u0430\u0445"
    ],
    "wof:name":"Kubalakh",
    "wof:placetype":"locality"
},
  "geometry": {"coordinates":[118.01667,63.68333000000001],"type":"Point"}
}