{
  "type": "Feature",
  "properties": {
    "gn:admin1_code":"45",
    "gn:asciiname":"Yurdur",
    "gn:country_code":"RU",
    "gn:dem":95,
    "gn:feature_class":"P",
    "gn:feature_code":"PPL",
    "gn:name":"Yurdur",
    "gn:population":0,
    "gn:timezone":"Europe/Moscow",
    "iso:country":"RU",
    "name:rus_x_preferred":[
        "\u042e\u0440\u0434\u0443\u0440"
    ],
    "name:und_x_variant":[
        "Staryy Yurdur",
        "Yurdur"
    ],
    "wof:name":"Yurdur",
    "wof:placetype":"locality"
},
  "geometry": {"coordinates":[49.04944,56.38056],"type":"Point"}
}