{
  "type": "Feature",
  "properties": {
    "gn:admin1_code":"80",
    "gn:asciiname":"Pazhman",
    "gn:country_code":"RU",
    "gn:dem":248,
    "gn:feature_class":"P",
    "gn:feature_code":"PPL",
    "gn:name":"Pazhman",
    "gn:population":0,
    "gn:timezone":"Europe/Samara",
    "iso:country":"RU",
    "name:rus_x_preferred":[
        "\u041f\u0430\u0436\u043c\u0430\u043d"
    ],
    "name:und_x_variant":[
        "\u041f\u0430\u0436\u043c\u0430\u043d"
    ],
    "wof:name":"Pazhman",
    "wof:placetype":"locality"
},
  "geometry": {"coordinates":[53.6358,57.978],"type":"Point"}
}