{
  "type": "Feature",
  "properties": {
    "gn:admin1_code":"9",
    "gn:asciiname":"Ryabiki",
    "gn:country_code":"RU",
    "gn:dem":164,
    "gn:feature_class":"P",
    "gn:feature_code":"PPL",
    "gn:name":"Ryabiki",
    "gn:population":0,
    "gn:timezone":"Europe/Moscow",
    "iso:country":"RU",
    "name:rus_x_preferred":[
        "\u0420\u044f\u0431\u0438\u043a\u0438"
    ],
    "name:und_x_variant":[
        "Ryabikin",
        "Ryaboki",
        "Ryabiki"
    ],
    "wof:name":"Ryabiki",
    "wof:placetype":"locality"
},
  "geometry": {"coordinates":[37.7826,50.1919],"type":"Point"}
}