{
  "type": "Feature",
  "properties": {
    "gn:admin1_code":"77",
    "gn:asciiname":"Peschivitsa",
    "gn:country_code":"RU",
    "gn:dem":206,
    "gn:feature_class":"P",
    "gn:feature_code":"PPL",
    "gn:name":"Peschivitsa",
    "gn:population":0,
    "gn:timezone":"Europe/Moscow",
    "iso:country":"RU",
    "name:und_x_variant":[
        "Peshchivitsa"
    ],
    "wof:name":"Peschivitsa",
    "wof:placetype":"locality"
},
  "geometry": {"coordinates":[31.83316,56.19656],"type":"Point"}
}