{
  "type": "Feature",
  "properties": {
    "gn:admin1_code":"11",
    "gn:asciiname":"Zolotoy Klyuch",
    "gn:country_code":"RU",
    "gn:dem":491,
    "gn:feature_class":"P",
    "gn:feature_code":"PPL",
    "gn:name":"Zolotoy Klyuch",
    "gn:population":0,
    "gn:timezone":"Asia/Irkutsk",
    "iso:country":"RU",
    "name:rus_x_preferred":[
        "\u0417\u043e\u043b\u043e\u0442\u043e\u0439 \u041a\u043b\u044e\u0447"
    ],
    "wof:name":"Zolotoy Klyuch",
    "wof:placetype":"locality"
},
  "geometry": {"coordinates":[108.6546,52.9876],"type":"Point"}
}