{
  "type": "Feature",
  "properties": {
    "gn:admin1_code":"53",
    "gn:asciiname":"Razumovka",
    "gn:cc2":"RU",
    "gn:country_code":"RU",
    "gn:dem":278,
    "gn:feature_class":"P",
    "gn:feature_code":"PPL",
    "gn:name":"Razumovka",
    "gn:population":0,
    "gn:timezone":"Asia/Novosibirsk",
    "iso:country":"RU",
    "name:rus_x_preferred":[
        "\u0420\u0430\u0437\u0443\u043c\u043e\u0432\u043a\u0430"
    ],
    "name:und_x_variant":[
        "Razumovskiy",
        "Razumovka",
        "\u0420\u0430\u0437\u0443\u043c\u043e\u0432\u043a\u0430"
    ],
    "wof:name":"Razumovka",
    "wof:placetype":"locality"
},
  "geometry": {"coordinates":[83.91667,54.51667],"type":"Point"}
}