{
  "type": "Feature",
  "properties": {
    "gn:admin1_code":"85.0",
    "gn:asciiname":"Gavshino",
    "gn:country_code":"RU",
    "gn:dem":166,
    "gn:feature_class":"P",
    "gn:feature_code":"PPL",
    "gn:name":"Gavshino",
    "gn:population":0,
    "gn:timezone":"Europe/Moscow",
    "iso:country":"RU",
    "name:rus_x_preferred":[
        "\u0413\u0430\u0432\u0448\u0438\u043d\u043e"
    ],
    "name:und_x_variant":[
        "Pavshinskaya",
        "Gavshino"
    ],
    "wof:name":"Gavshino",
    "wof:placetype":"locality"
},
  "geometry": {"coordinates":[42.07621,60.35544],"type":"Point"}
}