{
  "type": "Feature",
  "properties": {
    "gn:admin1_code":"72",
    "gn:asciiname":"Mutas'yevo",
    "gn:country_code":"RU",
    "gn:dem":104,
    "gn:feature_class":"P",
    "gn:feature_code":"PPL",
    "gn:name":"Mutas\u2019yevo",
    "gn:population":0,
    "gn:timezone":"Europe/Moscow",
    "iso:country":"RU",
    "name:eng_x_preferred":[
        "Mutas'yevo"
    ],
    "name:nor_x_preferred":[
        "Mutasievo"
    ],
    "name:rus_x_preferred":[
        "\u041c\u0443\u0442\u0430\u0441\u044c\u0435\u0432\u043e"
    ],
    "name:und_x_variant":[
        "Mutas\u2019yevo"
    ],
    "wof:name":"Mutas'yevo",
    "wof:placetype":"locality"
},
  "geometry": {"coordinates":[41.85991,53.55335],"type":"Point"}
}