{
  "type": "Feature",
  "properties": {
    "gn:admin1_code":"8",
    "gn:asciiname":"Obshchina",
    "gn:country_code":"RU",
    "gn:dem":121,
    "gn:feature_class":"P",
    "gn:feature_code":"PPL",
    "gn:name":"Obshchina",
    "gn:population":0,
    "gn:timezone":"Asia/Yekaterinburg",
    "iso:country":"RU",
    "name:cat_x_preferred":[
        "Obsxina"
    ],
    "name:ces_x_preferred":[
        "Ob\u0161\u010dina"
    ],
    "name:deu_x_preferred":[
        "Mir"
    ],
    "name:fin_x_preferred":[
        "Kyl\u00e4kunta"
    ],
    "name:fra_x_preferred":[
        "Mir"
    ],
    "name:hin_x_preferred":[
        "\u0913\u092c\u094d\u0936\u094d\u091a\u0940\u0928\u093e"
    ],
    "name:ita_x_preferred":[
        "Ob\u0161\u010dina"
    ],
    "name:kor_x_preferred":[
        "\ubbf8\ub974"
    ],
    "name:nld_x_preferred":[
        "Obsjtsjina"
    ],
    "name:oci_x_preferred":[
        "Mir"
    ],
    "name:pol_x_preferred":[
        "Obszczina"
    ],
    "name:por_x_preferred":[
        "Obshchina"
    ],
    "name:ron_x_preferred":[
        "Ob\u0219cina"
    ],
    "name:rus_x_preferred":[
        "\u041e\u0431\u0449\u0438\u043d\u0430"
    ],
    "name:rus_x_variant":[
        "\u0421\u0435\u043b\u044c\u0441\u043a\u043e\u0435 \u043e\u0431\u0449\u0435\u0441\u0442\u0432\u043e"
    ],
    "name:slk_x_preferred":[
        "Ob\u010dina"
    ],
    "name:spa_x_preferred":[
        "Mir"
    ],
    "name:ukr_x_preferred":[
        "\u0421\u0456\u043b\u044c\u0441\u044c\u043a\u0435 \u0442\u043e\u0432\u0430\u0440\u0438\u0441\u0442\u0432\u043e"
    ],
    "name:und_x_variant":[
        "\u041e\u0431\u0449\u0438\u043d\u0430"
    ],
    "wof:name":"Obshchina",
    "wof:placetype":"locality"
},
  "geometry": {"coordinates":[54.6822,54.7461],"type":"Point"}
}