{
  "type": "Feature",
  "properties": {
    "gn:admin1_code":"8",
    "gn:asciiname":"Obshchina",
    "gn:country_code":"RU",
    "gn:dem":121,
    "gn:feature_class":"P",
    "gn:feature_code":"PPL",
    "gn:name":"Obshchina",
    "gn:population":0,
    "gn:timezone":"Asia/Yekaterinburg",
    "iso:country":"RU",
    "name:rus_x_preferred":[
        "\u041e\u0431\u0449\u0438\u043d\u0430"
    ],
    "name:und_x_variant":[
        "\u041e\u0431\u0449\u0438\u043d\u0430"
    ],
    "wof:name":"Obshchina",
    "wof:placetype":"locality"
},
  "geometry": {"coordinates":[54.6822,54.7461],"type":"Point"}
}