{
  "type": "Feature",
  "properties": {
    "gn:admin1_code":"64",
    "gn:admin2_code":"2128971",
    "gn:asciiname":"Kagamae",
    "gn:country_code":"RU",
    "gn:dem":8,
    "gn:feature_class":"P",
    "gn:feature_code":"PPL",
    "gn:name":"Kagamae",
    "gn:population":0,
    "gn:timezone":"Asia/Sakhalin",
    "iso:country":"RU",
    "name:jpn_x_preferred":[
        "\u91dc\u524d"
    ],
    "name:jpn_x_variant":[
        "\u304b\u304c\u307e\u3048",
        "\u30ab\u30ac\u30de\u30a8"
    ],
    "name:und_x_variant":[
        "Kamemae",
        "Kamamae",
        "Kagamae"
    ],
    "wof:name":"Kagamae",
    "wof:placetype":"locality"
},
  "geometry": {"coordinates":[146.33628000000004,43.63607],"type":"Point"}
}