{
  "type": "Feature",
  "properties": {
    "gn:admin1_code":"21.0",
    "gn:asciiname":"Bol'shaya Gar'",
    "gn:country_code":"RU",
    "gn:dem":87,
    "gn:feature_class":"P",
    "gn:feature_code":"PPL",
    "gn:name":"Bol\u2019shaya Gar\u2019",
    "gn:population":0,
    "gn:timezone":"Europe/Moscow",
    "iso:country":"RU",
    "name:und_x_variant":[
        "Gar\u2019 Bol\u2019shaya",
        "Bol\u2019shaya Gar\u2019"
    ],
    "wof:name":"Bol'shaya Gar'",
    "wof:placetype":"locality"
},
  "geometry": {"coordinates":[42.76634,57.32369],"type":"Point"}
}