{
  "type": "Feature",
  "properties": {
    "gn:admin1_code":"22.0",
    "gn:asciiname":"Batekh",
    "gn:country_code":"RU",
    "gn:dem":632,
    "gn:feature_class":"P",
    "gn:feature_code":"PPL",
    "gn:name":"Batekh",
    "gn:population":0,
    "gn:timezone":"Europe/Moscow",
    "iso:country":"RU",
    "wof:name":"Batekh",
    "wof:placetype":"locality"
},
  "geometry": {"coordinates":[43.22944,43.85417],"type":"Point"}
}