{
  "type": "Feature",
  "properties": {
    "gn:admin1_code":"20",
    "gn:asciiname":"Nagishkina",
    "gn:country_code":"RU",
    "gn:dem":492,
    "gn:feature_class":"P",
    "gn:feature_code":"PPL",
    "gn:name":"Nagishkina",
    "gn:population":0,
    "gn:timezone":"Asia/Irkutsk",
    "iso:country":"RU",
    "name:eng_x_preferred":[
        "Nagishkina"
    ],
    "name:nor_x_preferred":[
        "Nagisjkina"
    ],
    "name:rus_x_preferred":[
        "\u041d\u0430\u0433\u0438\u0448\u043a\u0438\u043d\u0430"
    ],
    "name:und_x_variant":[
        "\u041d\u0430\u0433\u0438\u0448\u043a\u0438\u043d\u0430",
        "Nagishkina"
    ],
    "wof:name":"Nagishkina",
    "wof:placetype":"locality"
},
  "geometry": {"coordinates":[102.14389,53.81528],"type":"Point"}
}