{
  "type": "Feature",
  "properties": {
    "gn:country":"RU",
    "gn:fcode":"PPL",
    "gn:pop":0,
    "iso:country":"RU",
    "name:eng_x_preferred":[
        "Aksakovo"
    ],
    "name:nor_x_preferred":[
        "Aksakovo"
    ],
    "name:rus_x_preferred":[
        "\u0410\u043a\u0441\u0430\u043a\u043e\u0432\u043e"
    ],
    "name:unk_x_variant":[
        "\u0410\u043a\u0441\u0430\u043a\u043e\u0432\u043e"
    ],
    "qs:name":"Aksakovo",
    "qs:name_adm0":"Russia",
    "qs:name_adm1":"Moscow Oblast",
    "qs:photos_9r":0,
    "qs:photos_sr":0,
    "qs:placetype":"Town",
    "qs:pop_sr":"0",
    "wd:elevation":99.0,
    "wd:wordcount":107,
    "wof:name":"Aksakovo",
    "wof:placetype":"locality",
    "wof:population":0
},
  "geometry": {"coordinates":[37.61667,56.05],"type":"Point"}
}