{
  "type": "Feature",
  "properties": {
    "gn:admin1_code":"20",
    "gn:asciiname":"Novonikol'sk",
    "gn:country_code":"RU",
    "gn:dem":487,
    "gn:feature_class":"P",
    "gn:feature_code":"PPL",
    "gn:name":"Novonikol\u2019sk",
    "gn:population":0,
    "gn:timezone":"Asia/Irkutsk",
    "iso:country":"RU",
    "name:eng_x_preferred":[
        "Novonikol'sk"
    ],
    "name:nor_x_preferred":[
        "Novonikolsk"
    ],
    "name:rus_x_preferred":[
        "\u041d\u043e\u0432\u043e\u043d\u0438\u043a\u043e\u043b\u044c\u0441\u043a"
    ],
    "name:und_x_variant":[
        "Novo-Nikol\u2019skaya",
        "Novonikol\u2019skoye",
        "\u041d\u043e\u0432\u043e\u043d\u0438\u043a\u043e\u043b\u044c\u0441\u043a",
        "Novonikol\u2019sk"
    ],
    "wof:name":"Novonikol'sk",
    "wof:placetype":"locality"
},
  "geometry": {"coordinates":[101.5296,53.7666],"type":"Point"}
}