{
  "type": "Feature",
  "properties": {
    "gn:admin1_code":"85",
    "gn:asciiname":"Zakharovskaya",
    "gn:country_code":"RU",
    "gn:dem":108,
    "gn:feature_class":"P",
    "gn:feature_code":"PPL",
    "gn:name":"Zakharovskaya",
    "gn:population":0,
    "gn:timezone":"Europe/Moscow",
    "iso:country":"RU",
    "name:eng_x_preferred":[
        "Zakharovskaya"
    ],
    "name:nor_x_preferred":[
        "Zakharovskaja"
    ],
    "name:rus_x_preferred":[
        "\u0417\u0430\u0445\u0430\u0440\u043e\u0432\u0441\u043a\u0430\u044f"
    ],
    "wof:name":"Zakharovskaya",
    "wof:placetype":"locality"
},
  "geometry": {"coordinates":[41.6899,60.8068],"type":"Point"}
}