{
  "type": "Feature",
  "properties": {
    "gn:admin1_code":"91",
    "gn:asciiname":"Petropavlovka Vtoraya",
    "gn:country_code":"RU",
    "gn:dem":337,
    "gn:feature_class":"P",
    "gn:feature_code":"PPL",
    "gn:name":"Petropavlovka Vtoraya",
    "gn:population":0,
    "gn:timezone":"Asia/Krasnoyarsk",
    "iso:country":"RU",
    "name:rus_x_preferred":[
        "\u041f\u0435\u0442\u0440\u043e\u043f\u0430\u0432\u043b\u043e\u0432\u043a\u0430 \u0412\u0442\u043e\u0440\u0430\u044f"
    ],
    "wof:name":"Petropavlovka Vtoraya",
    "wof:placetype":"locality"
},
  "geometry": {"coordinates":[95.3254,55.8926],"type":"Point"}
}