{
  "type": "Feature",
  "properties": {
    "gn:admin1_code":"86",
    "gn:asciiname":"Urochishche Oseledkovo",
    "gn:country_code":"RU",
    "gn:dem":183,
    "gn:feature_class":"P",
    "gn:feature_code":"PPL",
    "gn:name":"Urochishche Osel\u00ebdkovo",
    "gn:population":0,
    "gn:timezone":"Europe/Moscow",
    "iso:country":"RU",
    "name:rus_x_preferred":[
        "\u041e\u0441\u0435\u043b\u0435\u0434\u043a\u043e\u0432"
    ],
    "name:rus_x_variant":[
        "Urochishche Osel\u00ebdkovo",
        "\u0423\u0440\u043e\u0447\u0438\u0449\u0435 \u041e\u0441\u0435\u043b\u0451\u0434\u043a\u043e\u0432\u043e"
    ],
    "name:und_x_variant":[
        "Oselodkov",
        "Oseledkov"
    ],
    "wof:name":"Urochishche Oseledkovo",
    "wof:placetype":"locality"
},
  "geometry": {"coordinates":[40.50194000000001,50.47056],"type":"Point"}
}