{
  "type": "Feature",
  "properties": {
    "gn:admin1_code":"8",
    "gn:asciiname":"Isametovo",
    "gn:country_code":"RU",
    "gn:dem":134,
    "gn:feature_class":"P",
    "gn:feature_code":"PPL",
    "gn:name":"Isametovo",
    "gn:population":0,
    "gn:timezone":"Asia/Yekaterinburg",
    "iso:country":"RU",
    "name:rus_x_preferred":[
        "\u0418\u0441\u0430\u043c\u0435\u0442\u043e\u0432\u043e"
    ],
    "name:und_x_variant":[
        "\u0418\u0441\u0430\u043c\u0435\u0442\u043e\u0432\u043e"
    ],
    "wof:name":"Isametovo",
    "wof:placetype":"locality"
},
  "geometry": {"coordinates":[53.9118,54.8078],"type":"Point"}
}