{
  "type": "Feature",
  "properties": {
    "gn:admin1_code":"56",
    "gn:asciiname":"Yablochkovo",
    "gn:country_code":"RU",
    "gn:dem":177,
    "gn:feature_class":"P",
    "gn:feature_code":"PPL",
    "gn:name":"Yablochkovo",
    "gn:population":0,
    "gn:timezone":"Europe/Moscow",
    "iso:country":"RU",
    "name:und_x_variant":[
        "Yablochkova",
        "Yablochkovo"
    ],
    "wof:name":"Yablochkovo",
    "wof:placetype":"locality"
},
  "geometry": {"coordinates":[35.03225,52.86479],"type":"Point"}
}