{
  "type": "Feature",
  "properties": {
    "gn:admin1_code":"15",
    "gn:asciiname":"Yeropol",
    "gn:country_code":"RU",
    "gn:dem":124,
    "gn:feature_class":"P",
    "gn:feature_code":"PPL",
    "gn:name":"Yeropol",
    "gn:population":0,
    "gn:timezone":"Asia/Anadyr",
    "iso:country":"RU",
    "wof:name":"Yeropol",
    "wof:placetype":"locality"
},
  "geometry": {"coordinates":[168.66666999999995,65.25],"type":"Point"}
}