{
  "type": "Feature",
  "properties": {
    "gn:admin1_code":"67.0",
    "gn:asciiname":"Ladygin",
    "gn:country_code":"RU",
    "gn:dem":43,
    "gn:feature_class":"P",
    "gn:feature_code":"PPL",
    "gn:name":"Ladygin",
    "gn:population":0,
    "gn:timezone":"Europe/Saratov",
    "iso:country":"RU",
    "name:rus_x_preferred":[
        "\u041b\u0430\u0434\u044b\u0433\u0438\u043d"
    ],
    "name:slv_x_preferred":[
        "Ladigin"
    ],
    "name:und_x_variant":[
        "\u041b\u0430\u0434\u044b\u0433\u0438\u043d"
    ],
    "wof:name":"Ladygin",
    "wof:placetype":"locality"
},
  "geometry": {"coordinates":[46.97139,52.0863],"type":"Point"}
}