{
  "type": "Feature",
  "properties": {
    "gn:admin1_code":"30",
    "gn:asciiname":"Borisova",
    "gn:country_code":"RU",
    "gn:dem":559,
    "gn:feature_class":"P",
    "gn:feature_code":"PPL",
    "gn:name":"Borisova",
    "gn:population":0,
    "gn:timezone":"Asia/Vladivostok",
    "iso:country":"RU",
    "name:rus_x_preferred":[
        "\u0411\u043e\u0440\u0438\u0441\u043e\u0432\u0430"
    ],
    "name:und_x_variant":[
        "\u0411\u043e\u0440\u0438\u0441\u043e\u0432\u0430"
    ],
    "wof:name":"Borisova",
    "wof:placetype":"locality"
},
  "geometry": {"coordinates":[136.38333,58.28333000000001],"type":"Point"}
}