{
  "type": "Feature",
  "properties": {
    "gn:admin1_code":"90",
    "gn:asciiname":"Uyas",
    "gn:country_code":"RU",
    "gn:dem":191,
    "gn:feature_class":"P",
    "gn:feature_code":"PPL",
    "gn:name":"Uyas",
    "gn:population":0,
    "gn:timezone":"Asia/Yekaterinburg",
    "iso:country":"RU",
    "name:rus_x_preferred":[
        "\u0423\u044f\u0441"
    ],
    "wof:name":"Uyas",
    "wof:placetype":"locality"
},
  "geometry": {"coordinates":[56.74346,56.56615],"type":"Point"}
}