{
  "type": "Feature",
  "properties": {
    "gn:admin1_code":"86.0",
    "gn:asciiname":"Krivusha",
    "gn:country_code":"RU",
    "gn:dem":139,
    "gn:feature_class":"P",
    "gn:feature_code":"PPL",
    "gn:name":"Krivusha",
    "gn:population":0,
    "gn:timezone":"Europe/Moscow",
    "iso:country":"RU",
    "name:rus_x_preferred":[
        "\u041a\u0440\u0438\u0432\u0443\u0448\u0430"
    ],
    "wof:name":"Krivusha",
    "wof:placetype":"locality"
},
  "geometry": {"coordinates":[40.76806,51.58306],"type":"Point"}
}