{
  "type": "Feature",
  "properties": {
    "gn:admin1_code":"33",
    "gn:asciiname":"Gozhemyata",
    "gn:cc2":"RU",
    "gn:country_code":"RU",
    "gn:dem":292,
    "gn:feature_class":"P",
    "gn:feature_code":"PPL",
    "gn:name":"Gozhemyata",
    "gn:population":0,
    "gn:timezone":"Europe/Kirov",
    "iso:country":"RU",
    "name:eng_x_preferred":[
        "Gozhemyata"
    ],
    "name:nor_x_preferred":[
        "Gozjemjata"
    ],
    "name:rus_x_preferred":[
        "\u0413\u043e\u0436\u0435\u043c\u044f\u0442\u0430"
    ],
    "name:und_x_variant":[
        "Ves\u00eblyy Log",
        "\u0413\u043e\u0436\u0435\u043c\u044f\u0442\u0430",
        "Gozhemyata"
    ],
    "wof:name":"Gozhemyata",
    "wof:placetype":"locality"
},
  "geometry": {"coordinates":[53.37083000000001,59.02721999999999],"type":"Point"}
}