{
  "type": "Feature",
  "properties": {
    "gn:admin1_code":"43",
    "gn:asciiname":"Kamennaya Lubna",
    "gn:country_code":"RU",
    "gn:dem":162,
    "gn:feature_class":"P",
    "gn:feature_code":"PPL",
    "gn:name":"Kamennaya Lubna",
    "gn:population":0,
    "gn:timezone":"Europe/Moscow",
    "iso:country":"RU",
    "name:rus_x_preferred":[
        "\u041a\u0430\u043c\u0435\u043d\u043d\u0430\u044f \u041b\u0443\u0431\u043d\u0430"
    ],
    "wof:name":"Kamennaya Lubna",
    "wof:placetype":"locality"
},
  "geometry": {"coordinates":[39.12607,52.77295],"type":"Point"}
}