{
  "type": "Feature",
  "properties": {
    "gn:admin1_code":"13",
    "gn:asciiname":"Karino",
    "gn:country_code":"RU",
    "gn:dem":139,
    "gn:feature_class":"P",
    "gn:feature_code":"PPL",
    "gn:name":"Karino",
    "gn:population":0,
    "gn:timezone":"Asia/Yekaterinburg",
    "iso:country":"RU",
    "name:rus_x_preferred":[
        "\u041a\u0430\u0440\u0438\u043d\u043e"
    ],
    "name:und_x_variant":[
        "\u041a\u0430\u0440\u0438\u043d\u043e"
    ],
    "wof:name":"Karino",
    "wof:placetype":"locality"
},
  "geometry": {"coordinates":[61.7578,56.0727],"type":"Point"}
}