{
  "type": "Feature",
  "properties": {
    "gn:admin1_code":"69",
    "gn:asciiname":"Staryye Mamolki",
    "gn:country_code":"RU",
    "gn:dem":170,
    "gn:feature_class":"P",
    "gn:feature_code":"PPL",
    "gn:name":"Staryye Mamolki",
    "gn:population":0,
    "gn:timezone":"Europe/Moscow",
    "iso:country":"RU",
    "name:rus_x_preferred":[
        "\u0421\u0442\u0430\u0440\u044b\u0435 \u041c\u0430\u043c\u043e\u043b\u043a\u0438"
    ],
    "wof:name":"Staryye Mamolki",
    "wof:placetype":"locality"
},
  "geometry": {"coordinates":[31.73333,55.16667],"type":"Point"}
}