{
  "type": "Feature",
  "properties": {
    "gn:admin1_code":"90.0",
    "gn:asciiname":"Chernoyarskaya Odina",
    "gn:country_code":"RU",
    "gn:dem":136,
    "gn:feature_class":"P",
    "gn:feature_code":"PPL",
    "gn:name":"Chernoyarskaya Odina",
    "gn:population":0,
    "gn:timezone":"Asia/Yekaterinburg",
    "iso:country":"RU",
    "name:che_x_preferred":[
        "\u0427\u0435\u0440\u043d\u043e\u044f\u0440\u0441\u043a\u0438 \u041e\u0434\u0438\u043d\u0430"
    ],
    "name:rus_x_preferred":[
        "\u0427\u0435\u0440\u043d\u043e\u044f\u0440\u0441\u043a\u0430\u044f \u041e\u0434\u0438\u043d\u0430"
    ],
    "wof:name":"Chernoyarskaya Odina",
    "wof:placetype":"locality"
},
  "geometry": {"coordinates":[57.4423,57.2842],"type":"Point"}
}