{
  "type": "Feature",
  "properties": {
    "gn:admin1_code":"72.0",
    "gn:asciiname":"Bulgakovo",
    "gn:country_code":"RU",
    "gn:dem":157,
    "gn:feature_class":"P",
    "gn:feature_code":"PPL",
    "gn:name":"Bulgakovo",
    "gn:population":0,
    "gn:timezone":"Europe/Moscow",
    "iso:country":"RU",
    "name:rus_x_preferred":[
        "\u0411\u0443\u043b\u0433\u0430\u043a\u043e\u0432\u043e"
    ],
    "name:und_x_variant":[
        "\u0411\u0443\u043b\u0433\u0430\u043a\u043e\u0432\u043e"
    ],
    "wof:name":"Bulgakovo",
    "wof:placetype":"locality"
},
  "geometry": {"coordinates":[41.87828,51.67944],"type":"Point"}
}