{
  "type": "Feature",
  "properties": {
    "gn:admin1_code":"64",
    "gn:asciiname":"Toruvo",
    "gn:cc2":"RU",
    "gn:country_code":"RU",
    "gn:dem":2,
    "gn:feature_class":"P",
    "gn:feature_code":"PPL",
    "gn:name":"Toruvo",
    "gn:population":0,
    "gn:timezone":"Asia/Sakhalin",
    "iso:country":"RU",
    "name:und_x_variant":[
        "Goruvo",
        "Tolvo",
        "Toruvo"
    ],
    "wof:name":"Toruvo",
    "wof:placetype":"locality"
},
  "geometry": {"coordinates":[143.13333,52.36667],"type":"Point"}
}