{
  "type": "Feature",
  "properties": {
    "gn:admin1_code":"64",
    "gn:asciiname":"Ozeretskoye",
    "gn:cc2":"RU",
    "gn:country_code":"RU",
    "gn:dem":2,
    "gn:feature_class":"P",
    "gn:feature_code":"PPL",
    "gn:name":"Ozeretskoye",
    "gn:population":0,
    "gn:timezone":"Asia/Sakhalin",
    "iso:country":"RU",
    "name:rus_x_preferred":[
        "\u041e\u0437\u0435\u0440\u0435\u0442\u0441\u043a\u043e\u0435"
    ],
    "name:und_x_variant":[
        "Eura",
        "Nak\u016bbe",
        "Anivaskiy-Ozeretskiy",
        "Enoura",
        "Anivskiy-Ozeretskiy",
        "Ozeretskoye",
        "\u041e\u0437\u0435\u0440\u0435\u0442\u0441\u043a\u043e\u0435"
    ],
    "wof:name":"Ozeretskoye",
    "wof:placetype":"locality"
},
  "geometry": {"coordinates":[142.63333,46.73333],"type":"Point"}
}