{
  "type": "Feature",
  "properties": {
    "gn:admin1_code":"43.0",
    "gn:asciiname":"Matveyevka",
    "gn:country_code":"RU",
    "gn:dem":147,
    "gn:feature_class":"P",
    "gn:feature_code":"PPL",
    "gn:name":"Matveyevka",
    "gn:population":0,
    "gn:timezone":"Europe/Moscow",
    "iso:country":"RU",
    "name:rus_x_preferred":[
        "\u041c\u0430\u0442\u0432\u0435\u0435\u0432\u043a\u0430"
    ],
    "wof:name":"Matveyevka",
    "wof:placetype":"locality"
},
  "geometry": {"coordinates":[40.296,51.9746],"type":"Point"}
}