{
  "type": "Feature",
  "properties": {
    "gn:admin1_code":"1",
    "gn:asciiname":"Staromogilevskiy",
    "gn:country_code":"RU",
    "gn:dem":41,
    "gn:feature_class":"P",
    "gn:feature_code":"PPL",
    "gn:name":"Staromogil\u00ebvskiy",
    "gn:population":0,
    "gn:timezone":"Europe/Moscow",
    "iso:country":"RU",
    "name:rus_x_preferred":[
        "\u0421\u0442\u0430\u0440\u043e\u043c\u043e\u0433\u0438\u043b\u0451\u0432\u0441\u043a\u0438\u0439"
    ],
    "name:und_x_variant":[
        "Gridnev",
        "Gridnew",
        "Staromogil\u00ebvskiy",
        "\u0421\u0442\u0430\u0440\u043e\u043c\u043e\u0433\u0438\u043b\u0451\u0432\u0441\u043a\u0438\u0439"
    ],
    "wof:name":"Staromogilevskiy",
    "wof:placetype":"locality"
},
  "geometry": {"coordinates":[39.11492,44.83082],"type":"Point"}
}