{
  "type": "Feature",
  "properties": {
    "gn:admin1_code":"57",
    "gn:asciiname":"Kromshchino",
    "gn:country_code":"RU",
    "gn:dem":236,
    "gn:feature_class":"P",
    "gn:feature_code":"PPL",
    "gn:name":"Kromshchino",
    "gn:population":0,
    "gn:timezone":"Europe/Moscow",
    "iso:country":"RU",
    "name:rus_x_preferred":[
        "\u041a\u0440\u043e\u043c\u0449\u0438\u043d\u043e"
    ],
    "wof:name":"Kromshchino",
    "wof:placetype":"locality"
},
  "geometry": {"coordinates":[44.82391,52.90666],"type":"Point"}
}