{
  "type": "Feature",
  "properties": {
    "gn:admin1_code":"77",
    "gn:asciiname":"Pikhten'",
    "gn:country_code":"RU",
    "gn:dem":231,
    "gn:feature_class":"P",
    "gn:feature_code":"PPL",
    "gn:name":"Pikhten\u2019",
    "gn:population":0,
    "gn:timezone":"Europe/Moscow",
    "iso:country":"RU",
    "name:rus_x_preferred":[
        "\u041f\u0438\u0445\u0442\u0435\u043d\u044c"
    ],
    "name:und_x_variant":[
        "Pikhten\u2019"
    ],
    "wof:name":"Pikhten'",
    "wof:placetype":"locality"
},
  "geometry": {"coordinates":[32.79368,57.08975],"type":"Point"}
}