{
  "type": "Feature",
  "properties": {
    "gn:admin1_code":"77",
    "gn:asciiname":"Turbayevo",
    "gn:country_code":"RU",
    "gn:dem":193,
    "gn:feature_class":"P",
    "gn:feature_code":"PPL",
    "gn:name":"Turbayevo",
    "gn:population":0,
    "gn:timezone":"Europe/Moscow",
    "iso:country":"RU",
    "name:eng_x_preferred":[
        "Turbayevo"
    ],
    "name:nor_x_preferred":[
        "Turbajevo"
    ],
    "name:rus_x_preferred":[
        "\u0422\u0443\u0440\u0431\u0430\u0435\u0432\u043e"
    ],
    "wof:name":"Turbayevo",
    "wof:placetype":"locality"
},
  "geometry": {"coordinates":[34.35899000000001,56.20765],"type":"Point"}
}