{
  "type": "Feature",
  "properties": {
    "gn:admin1_code":"33",
    "gn:asciiname":"Bekhterevy",
    "gn:country_code":"RU",
    "gn:dem":194,
    "gn:feature_class":"P",
    "gn:feature_code":"PPL",
    "gn:name":"Bekhterevy",
    "gn:population":0,
    "gn:timezone":"Europe/Kirov",
    "iso:country":"RU",
    "name:nor_x_preferred":[
        "Bekhterevy"
    ],
    "name:rus_x_preferred":[
        "\u0411\u0435\u0445\u0442\u0435\u0440\u0435\u0432\u044b"
    ],
    "wof:name":"Bekhterevy",
    "wof:placetype":"locality"
},
  "geometry": {"coordinates":[48.40768,59.3721],"type":"Point"}
}