{
  "type": "Feature",
  "properties": {
    "gn:admin1_code":"8",
    "gn:asciiname":"Khripunovskiy",
    "gn:country_code":"RU",
    "gn:dem":117,
    "gn:feature_class":"P",
    "gn:feature_code":"PPL",
    "gn:name":"Khripunovskiy",
    "gn:population":0,
    "gn:timezone":"Asia/Yekaterinburg",
    "iso:country":"RU",
    "name:rus_x_preferred":[
        "\u0425\u0440\u0438\u043f\u0443\u043d\u043e\u0432\u0441\u043a\u0438\u0439"
    ],
    "wof:name":"Khripunovskiy",
    "wof:placetype":"locality"
},
  "geometry": {"coordinates":[56.1639,53.8242],"type":"Point"}
}