{
  "type": "Feature",
  "properties": {
    "gn:admin1_code":"16",
    "gn:asciiname":"Rungi",
    "gn:country_code":"RU",
    "gn:dem":101,
    "gn:feature_class":"P",
    "gn:feature_code":"PPL",
    "gn:name":"Rungi",
    "gn:population":0,
    "gn:timezone":"Europe/Moscow",
    "iso:country":"RU",
    "name:rus_x_preferred":[
        "\u0420\u0443\u043d\u0433\u0438"
    ],
    "name:und_x_variant":[
        "\u0420\u0443\u043d\u0433\u0438"
    ],
    "wof:name":"Rungi",
    "wof:placetype":"locality"
},
  "geometry": {"coordinates":[47.14476,55.48531],"type":"Point"}
}