{
  "type": "Feature",
  "properties": {
    "gn:admin1_code":"88",
    "gn:asciiname":"Rodiontsevo",
    "gn:country_code":"RU",
    "gn:dem":177,
    "gn:feature_class":"P",
    "gn:feature_code":"PPL",
    "gn:name":"Rodiontsevo",
    "gn:population":0,
    "gn:timezone":"Europe/Moscow",
    "iso:country":"RU",
    "name:rus_x_preferred":[
        "\u0420\u043e\u0434\u0438\u043e\u043d\u0446\u0435\u0432\u043e"
    ],
    "wof:name":"Rodiontsevo",
    "wof:placetype":"locality"
},
  "geometry": {"coordinates":[39.65037,57.86277],"type":"Point"}
}