{
  "type": "Feature",
  "properties": {
    "gn:admin1_code":"85",
    "gn:asciiname":"Kletnaya",
    "gn:country_code":"RU",
    "gn:dem":187,
    "gn:feature_class":"P",
    "gn:feature_code":"PPL",
    "gn:name":"Kletnaya",
    "gn:population":0,
    "gn:timezone":"Europe/Moscow",
    "iso:country":"RU",
    "name:rus_x_preferred":[
        "\u041a\u043b\u0435\u0442\u043d\u0430\u044f"
    ],
    "wof:name":"Kletnaya",
    "wof:placetype":"locality"
},
  "geometry": {"coordinates":[38.5743,60.4539],"type":"Point"}
}