{
  "type": "Feature",
  "properties": {
    "gn:admin1_code":"69",
    "gn:asciiname":"Sutoki",
    "gn:country_code":"RU",
    "gn:dem":169,
    "gn:feature_class":"P",
    "gn:feature_code":"PPL",
    "gn:name":"Sutoki",
    "gn:population":0,
    "gn:timezone":"Europe/Moscow",
    "iso:country":"RU",
    "name:eng_x_preferred":[
        "Sutoki"
    ],
    "name:nor_x_preferred":[
        "Sutoki"
    ],
    "name:rus_x_preferred":[
        "\u0421\u0443\u0442\u043e\u043a\u0438"
    ],
    "wof:name":"Sutoki",
    "wof:placetype":"locality"
},
  "geometry": {"coordinates":[31.23552,54.76708000000001],"type":"Point"}
}