{
  "type": "Feature",
  "properties": {
    "gn:admin1_code":"86.0",
    "gn:asciiname":"Briliantovka",
    "gn:country_code":"RU",
    "gn:dem":147,
    "gn:feature_class":"P",
    "gn:feature_code":"PPL",
    "gn:name":"Briliantovka",
    "gn:population":0,
    "gn:timezone":"Europe/Moscow",
    "iso:country":"RU",
    "name:rus_x_preferred":[
        "\u0411\u0440\u0438\u043b\u0438\u0430\u043d\u0442\u043e\u0432\u043a\u0430"
    ],
    "wof:name":"Briliantovka",
    "wof:placetype":"locality"
},
  "geometry": {"coordinates":[39.81852,51.47637],"type":"Point"}
}