{
  "type": "Feature",
  "properties": {
    "gn:admin1_code":"59",
    "gn:asciiname":"Klerk",
    "gn:cc2":"RU",
    "gn:country_code":"RU",
    "gn:dem":-9999,
    "gn:feature_class":"P",
    "gn:feature_code":"PPL",
    "gn:name":"Klerk",
    "gn:population":0,
    "gn:timezone":"Asia/Vladivostok",
    "iso:country":"RU",
    "name:rus_x_preferred":[
        "\u041a\u043b\u0435\u0440\u043a"
    ],
    "name:und_x_variant":[
        "Pansilyay",
        "Klerk"
    ],
    "wof:name":"Klerk",
    "wof:placetype":"locality"
},
  "geometry": {"coordinates":[131.36667,42.78333],"type":"Point"}
}