{
  "type": "Feature",
  "properties": {
    "gn:country":"RU",
    "gn:fcode":"PPL",
    "gn:population":0,
    "iso:country":"RU",
    "name:eng_x_preferred":[
        "Biklyan'"
    ],
    "name:nor_x_preferred":[
        "Bikljan"
    ],
    "name:rus_x_preferred":[
        "\u0411\u0438\u043a\u043b\u044f\u043d\u044c"
    ],
    "qs:name":"Biklyan'",
    "qs:name_adm0":"Russia",
    "qs:name_adm1":"Tatarstan Republic",
    "qs:photos_9k":1,
    "qs:photos_9r":1,
    "qs:photos_all":1,
    "qs:photos_sr":0,
    "qs:placetype":"Town",
    "qs:pop_sr":"0",
    "wof:name":"Biklyan'",
    "wof:placetype":"locality",
    "wof:population":0
},
  "geometry": {"coordinates":[52.14396,55.62197],"type":"Point"}
}