{
  "type": "Feature",
  "properties": {
    "gn:admin1_code":"52.0",
    "gn:asciiname":"Dedlovo",
    "gn:country_code":"RU",
    "gn:dem":121,
    "gn:feature_class":"P",
    "gn:feature_code":"PPL",
    "gn:name":"Dedlovo",
    "gn:population":0,
    "gn:timezone":"Europe/Moscow",
    "iso:country":"RU",
    "name:eng_x_preferred":[
        "Dedlovo"
    ],
    "name:nor_x_preferred":[
        "Dedlovo"
    ],
    "name:rus_x_preferred":[
        "\u0414\u0435\u0434\u043b\u043e\u0432\u043e"
    ],
    "name:und_x_variant":[
        "\u0414\u0435\u0434\u043b\u043e\u0432\u043e",
        "Dedlovo"
    ],
    "wof:name":"Dedlovo",
    "wof:placetype":"locality"
},
  "geometry": {"coordinates":[33.3537,59.09107],"type":"Point"}
}