{
  "type": "Feature",
  "properties": {
    "gn:admin1_code":"41",
    "gn:asciiname":"Konzavod-Azovskoye",
    "gn:country_code":"RU",
    "gn:dem":200,
    "gn:feature_class":"P",
    "gn:feature_code":"PPL",
    "gn:name":"Konzavod-Azovskoye",
    "gn:population":0,
    "gn:timezone":"Europe/Moscow",
    "iso:country":"RU",
    "name:rus_x_preferred":[
        "\u041a\u043e\u043d\u0437\u0430\u0432\u043e\u0434-\u0410\u0437\u043e\u0432\u0441\u043a\u043e\u0435"
    ],
    "wof:name":"Konzavod-Azovskoye",
    "wof:placetype":"locality"
},
  "geometry": {"coordinates":[37.88333,51.73333],"type":"Point"}
}