{
  "type": "Feature",
  "properties": {
    "gn:admin1_code":"90",
    "gn:asciiname":"Sosnovaya Gora",
    "gn:country_code":"RU",
    "gn:dem":147,
    "gn:feature_class":"P",
    "gn:feature_code":"PPL",
    "gn:name":"Sosnovaya Gora",
    "gn:population":0,
    "gn:timezone":"Asia/Yekaterinburg",
    "iso:country":"RU",
    "name:rus_x_preferred":[
        "\u0421\u043e\u0441\u043d\u043e\u0432\u0430\u044f \u0413\u043e\u0440\u0430"
    ],
    "wof:name":"Sosnovaya Gora",
    "wof:placetype":"locality"
},
  "geometry": {"coordinates":[57.1627,58.0376],"type":"Point"}
}