{
  "type": "Feature",
  "properties": {
    "gn:admin1_code":"53",
    "gn:asciiname":"Filimonovskiy",
    "gn:country_code":"RU",
    "gn:dem":149,
    "gn:feature_class":"P",
    "gn:feature_code":"PPL",
    "gn:name":"Filimonovskiy",
    "gn:population":0,
    "gn:timezone":"Asia/Novosibirsk",
    "iso:country":"RU",
    "name:eng_x_preferred":[
        "Filimonovskiy"
    ],
    "name:nor_x_preferred":[
        "Filimonovskij"
    ],
    "name:rus_x_preferred":[
        "\u0424\u0438\u043b\u0438\u043c\u043e\u043d\u043e\u0432\u0441\u043a\u0438\u0439"
    ],
    "name:und_x_variant":[
        "Filimonovka"
    ],
    "wof:name":"Filimonovskiy",
    "wof:placetype":"locality"
},
  "geometry": {"coordinates":[81.0692,54.9303],"type":"Point"}
}