{
  "type": "Feature",
  "properties": {
    "gn:admin1_code":"91",
    "gn:asciiname":"Nizhnyaya Agashul'",
    "gn:country_code":"RU",
    "gn:dem":390,
    "gn:feature_class":"P",
    "gn:feature_code":"PPL",
    "gn:name":"Nizhnyaya Agashul\u2019",
    "gn:population":0,
    "gn:timezone":"Asia/Krasnoyarsk",
    "iso:country":"RU",
    "name:rus_x_preferred":[
        "\u041d\u0438\u0436\u043d\u044f\u044f \u0410\u0433\u0430\u0448\u0443\u043b\u044c"
    ],
    "name:und_x_variant":[
        "Nizhniy Agashul",
        "Nizhnyaya Agashul\u2019"
    ],
    "wof:name":"Nizhnyaya Agashul'",
    "wof:placetype":"locality"
},
  "geometry": {"coordinates":[94.68333,55.48333],"type":"Point"}
}