{
  "type": "Feature",
  "properties": {
    "gn:admin1_code":"9",
    "gn:asciiname":"Kuznetsovka",
    "gn:country_code":"RU",
    "gn:dem":86,
    "gn:feature_class":"P",
    "gn:feature_code":"PPL",
    "gn:name":"Kuznetsovka",
    "gn:population":0,
    "gn:timezone":"Europe/Moscow",
    "iso:country":"RU",
    "name:rus_x_preferred":[
        "\u041a\u0443\u0437\u043d\u0435\u0446\u043e\u0432\u043a\u0430"
    ],
    "wof:name":"Kuznetsovka",
    "wof:placetype":"locality"
},
  "geometry": {"coordinates":[38.0337,50.2253],"type":"Point"}
}