{
  "type": "Feature",
  "properties": {
    "gn:admin1_code":"9",
    "gn:asciiname":"Kuznetsovka",
    "gn:country_code":"RU",
    "gn:dem":86,
    "gn:feature_class":"P",
    "gn:feature_code":"PPL",
    "gn:name":"Kuznetsovka",
    "gn:population":0,
    "gn:timezone":"Europe/Moscow",
    "iso:country":"RU",
    "name:aze_x_preferred":[
        "Kuznesovka"
    ],
    "name:bak_x_preferred":[
        "\u041a\u0443\u0437\u043d\u0435\u0446\u043e\u0432\u043a\u0430"
    ],
    "name:che_x_preferred":[
        "\u041a\u0443\u0437\u043d\u0435\u0446\u043e\u0432\u043a\u0430"
    ],
    "name:hye_x_preferred":[
        "\u053f\u0578\u0582\u0566\u0576\u0565\u0581\u0578\u057e\u056f\u0561"
    ],
    "name:kat_x_preferred":[
        "\u10d9\u10e3\u10d6\u10dc\u10d4\u10ea\u10dd\u10d5\u10d9\u10d0"
    ],
    "name:kaz_x_preferred":[
        "\u041a\u0443\u0437\u043d\u0435\u0446\u043e\u0432\u043a\u0430"
    ],
    "name:kir_x_preferred":[
        "\u041a\u0443\u0437\u043d\u0435\u0446\u043e\u0432\u043a\u0430"
    ],
    "name:rus_x_preferred":[
        "\u041a\u0443\u0437\u043d\u0435\u0446\u043e\u0432\u043a\u0430"
    ],
    "name:tat_x_preferred":[
        "\u041a\u0443\u0437\u043d\u0435\u0446\u043e\u0432\u043a\u0430"
    ],
    "name:ukr_x_preferred":[
        "\u041a\u0443\u0437\u043d\u0435\u0446\u043e\u0432\u043a\u0430"
    ],
    "wof:name":"Kuznetsovka",
    "wof:placetype":"locality"
},
  "geometry": {"coordinates":[38.0337,50.2253],"type":"Point"}
}