{
  "type": "Feature",
  "properties": {
    "gn:admin1_code":"37.0",
    "gn:asciiname":"Bogoroditskoye-Pole",
    "gn:country_code":"RU",
    "gn:dem":103,
    "gn:feature_class":"P",
    "gn:feature_code":"PPL",
    "gn:name":"Bogoroditskoye-Pole",
    "gn:population":0,
    "gn:timezone":"Europe/Moscow",
    "iso:country":"RU",
    "name:rus_x_preferred":[
        "\u0411\u043e\u0433\u043e\u0440\u043e\u0434\u0438\u0442\u0441\u043a\u043e\u0435-\u041f\u043e\u043b\u0435"
    ],
    "name:und_x_variant":[
        "\u0411\u043e\u0433\u043e\u0440\u043e\u0434\u0438\u0442\u0441\u043a\u043e\u0435-\u041f\u043e\u043b\u0435"
    ],
    "wof:name":"Bogoroditskoye-Pole",
    "wof:placetype":"locality"
},
  "geometry": {"coordinates":[41.98333,58.51667],"type":"Point"}
}