{
  "type": "Feature",
  "properties": {
    "gn:admin1_code":"77",
    "gn:asciiname":"Kostruble",
    "gn:country_code":"RU",
    "gn:dem":237,
    "gn:feature_class":"P",
    "gn:feature_code":"PPL",
    "gn:name":"Kostrubl\u00eb",
    "gn:population":0,
    "gn:timezone":"Europe/Moscow",
    "iso:country":"RU",
    "name:rus_x_preferred":[
        "\u041a\u043e\u0441\u0442\u0440\u0443\u0431\u043b\u0451"
    ],
    "name:und_x_variant":[
        "Kastrubli",
        "Kostrubli",
        "Kostrubl\u00eb"
    ],
    "wof:name":"Kostruble",
    "wof:placetype":"locality"
},
  "geometry": {"coordinates":[33.64145,57.42188],"type":"Point"}
}