{
  "type": "Feature",
  "properties": {
    "gn:admin1_code":"23",
    "gn:asciiname":"Pogranichnoye",
    "gn:country_code":"RU",
    "gn:dem":84,
    "gn:feature_class":"P",
    "gn:feature_code":"PPL",
    "gn:name":"Pogranichnoye",
    "gn:population":0,
    "gn:timezone":"Europe/Kaliningrad",
    "iso:country":"RU",
    "name:rus_x_preferred":[
        "\u041f\u043e\u0433\u0440\u0430\u043d\u0438\u0447\u043d\u043e\u0435"
    ],
    "name:und_x_variant":[
        "\u041f\u043e\u0433\u0440\u0430\u043d\u0438\u0447\u043d\u043e\u0435"
    ],
    "wof:name":"Pogranichnoye",
    "wof:placetype":"locality"
},
  "geometry": {"coordinates":[20.83083,54.38417],"type":"Point"}
}