{
  "type": "Feature",
  "properties": {
    "gn:admin1_code":"80",
    "gn:asciiname":"Zyuzino",
    "gn:country_code":"RU",
    "gn:dem":261,
    "gn:feature_class":"P",
    "gn:feature_code":"PPL",
    "gn:name":"Zyuzino",
    "gn:population":0,
    "gn:timezone":"Europe/Samara",
    "iso:country":"RU",
    "name:eng_x_preferred":[
        "Zyuzino"
    ],
    "name:nor_x_preferred":[
        "Ziuzino"
    ],
    "name:rus_x_preferred":[
        "\u0417\u044e\u0437\u0438\u043d\u043e"
    ],
    "wof:name":"Zyuzino",
    "wof:placetype":"locality"
},
  "geometry": {"coordinates":[54.02466,57.47267],"type":"Point"}
}