{
  "type": "Feature",
  "properties": {
    "gn:admin1_code":"47",
    "gn:asciiname":"Meshcherskoye",
    "gn:country_code":"RU",
    "gn:dem":173,
    "gn:feature_class":"P",
    "gn:feature_code":"PPL",
    "gn:name":"Meshcherskoye",
    "gn:population":0,
    "gn:timezone":"Europe/Moscow",
    "iso:country":"RU",
    "name:rus_x_preferred":[
        "\u041c\u0435\u0449\u0435\u0440\u0441\u043a\u043e\u0435"
    ],
    "name:und_x_variant":[
        "Meshcherskoe",
        "Meshcherskoye",
        "\u041c\u0435\u0449\u0435\u0440\u0441\u043a\u043e\u0435"
    ],
    "wof:name":"Meshcherskoye",
    "wof:placetype":"locality"
},
  "geometry": {"coordinates":[37.63072,55.279],"type":"Point"}
}