{
  "type": "Feature",
  "properties": {
    "gn:admin1_code":"80.0",
    "gn:asciiname":"Lyukvyr",
    "gn:country_code":"RU",
    "gn:dem":214,
    "gn:feature_class":"P",
    "gn:feature_code":"PPL",
    "gn:name":"Lyukvyr",
    "gn:population":0,
    "gn:timezone":"Europe/Samara",
    "iso:country":"RU",
    "name:rus_x_preferred":[
        "\u041b\u044e\u043a\u0432\u044b\u0440"
    ],
    "wof:name":"Lyukvyr",
    "wof:placetype":"locality"
},
  "geometry": {"coordinates":[53.4702,57.6283],"type":"Point"}
}