{
  "type": "Feature",
  "properties": {
    "gn:admin1_code":"90.0",
    "gn:asciiname":"Konyayevo",
    "gn:country_code":"RU",
    "gn:dem":158,
    "gn:feature_class":"P",
    "gn:feature_code":"PPL",
    "gn:name":"Konyayevo",
    "gn:population":0,
    "gn:timezone":"Asia/Yekaterinburg",
    "iso:country":"RU",
    "name:rus_x_preferred":[
        "\u041a\u043e\u043d\u044f\u0435\u0432\u043e"
    ],
    "wof:name":"Konyayevo",
    "wof:placetype":"locality"
},
  "geometry": {"coordinates":[55.5456,58.7587],"type":"Point"}
}