{
  "type": "Feature",
  "properties": {
    "gn:admin1_code":"10",
    "gn:asciiname":"Tyutcheva Sloboda",
    "gn:country_code":"RU",
    "gn:dem":198,
    "gn:feature_class":"P",
    "gn:feature_code":"PPL",
    "gn:name":"Tyutcheva Sloboda",
    "gn:population":0,
    "gn:timezone":"Europe/Moscow",
    "iso:country":"RU",
    "name:rus_x_preferred":[
        "\u0422\u044e\u0442\u0447\u0435\u0432\u0430 \u0421\u043b\u043e\u0431\u043e\u0434\u0430"
    ],
    "name:und_x_variant":[
        "Sloboda",
        "Tyutcheva Sloboda"
    ],
    "wof:name":"Tyutcheva Sloboda",
    "wof:placetype":"locality"
},
  "geometry": {"coordinates":[33.5182,53.5855],"type":"Point"}
}