{
  "type": "Feature",
  "properties": {
    "gn:admin1_code":"10",
    "gn:asciiname":"Vygonichi",
    "gn:country_code":"RU",
    "gn:dem":174,
    "gn:feature_class":"P",
    "gn:feature_code":"PPL",
    "gn:name":"Vygonichi",
    "gn:population":0,
    "gn:timezone":"Europe/Moscow",
    "iso:country":"RU",
    "name:und_x_variant":[
        "Bygenitschi",
        "Vygonichi"
    ],
    "wof:name":"Vygonichi",
    "wof:placetype":"locality"
},
  "geometry": {"coordinates":[34.09141,53.13081999999999],"type":"Point"}
}