{
  "type": "Feature",
  "properties": {
    "gn:admin1_code":"10",
    "gn:asciiname":"Vygonichi",
    "gn:country_code":"RU",
    "gn:dem":174,
    "gn:feature_class":"P",
    "gn:feature_code":"PPL",
    "gn:name":"Vygonichi",
    "gn:population":0,
    "gn:timezone":"Europe/Moscow",
    "iso:country":"RU",
    "name:ara_x_preferred":[
        "\u0641\u064a\u063a\u0648\u0646\u064a\u062a\u0634\u064a"
    ],
    "name:bel_x_preferred":[
        "\u0412\u044b\u0433\u0430\u043d\u0456\u0447\u044b"
    ],
    "name:che_x_preferred":[
        "\u0412\u044b\u0433\u043e\u043d\u0438\u0447\u0438"
    ],
    "name:deu_x_preferred":[
        "Wygonitschi"
    ],
    "name:fin_x_preferred":[
        "Vygonit\u0161i"
    ],
    "name:ita_x_preferred":[
        "Vygoni\u010di"
    ],
    "name:lav_x_preferred":[
        "Vigo\u0146i\u010di"
    ],
    "name:pol_x_preferred":[
        "Wygoniczi"
    ],
    "name:rus_x_preferred":[
        "\u0412\u044b\u0433\u043e\u043d\u0438\u0447\u0438"
    ],
    "name:ukr_x_preferred":[
        "\u0412\u0438\u0433\u043e\u043d\u0438\u0447\u0456"
    ],
    "name:und_x_variant":[
        "Bygenitschi",
        "Vygonichi"
    ],
    "wof:name":"Vygonichi",
    "wof:placetype":"locality"
},
  "geometry": {"coordinates":[34.09141,53.13081999999999],"type":"Point"}
}