{
  "type": "Feature",
  "properties": {
    "gn:admin1_code":"60",
    "gn:asciiname":"Berez'ye",
    "gn:country_code":"RU",
    "gn:dem":152,
    "gn:feature_class":"P",
    "gn:feature_code":"PPL",
    "gn:name":"Berez\u2019ye",
    "gn:population":0,
    "gn:timezone":"Europe/Moscow",
    "iso:country":"RU",
    "name:rus_x_preferred":[
        "\u0411\u0435\u0440\u0435\u0437\u044c\u0435"
    ],
    "name:und_x_variant":[
        "Berez\u2019ye",
        "\u0411\u0435\u0440\u0435\u0437\u044c\u0435"
    ],
    "wof:name":"Berez'ye",
    "wof:placetype":"locality"
},
  "geometry": {"coordinates":[30.6936,56.2098],"type":"Point"}
}