{
  "type": "Feature",
  "properties": {
    "gn:admin1_code":"10",
    "gn:asciiname":"Chistyakovo",
    "gn:country_code":"RU",
    "gn:dem":196,
    "gn:feature_class":"P",
    "gn:feature_code":"PPL",
    "gn:name":"Chistyakovo",
    "gn:population":0,
    "gn:timezone":"Europe/Moscow",
    "iso:country":"RU",
    "name:rus_x_preferred":[
        "\u0427\u0438\u0441\u0442\u044f\u043a\u043e\u0432\u043e"
    ],
    "wof:name":"Chistyakovo",
    "wof:placetype":"locality"
},
  "geometry": {"coordinates":[34.84500999999999,53.3482],"type":"Point"}
}