{
  "type": "Feature",
  "properties": {
    "gn:admin1_code":"62",
    "gn:asciiname":"Uzkovo",
    "gn:country_code":"RU",
    "gn:dem":149,
    "gn:feature_class":"P",
    "gn:feature_code":"PPL",
    "gn:name":"Uzkovo",
    "gn:population":0,
    "gn:timezone":"Europe/Moscow",
    "iso:country":"RU",
    "name:rus_x_preferred":[
        "\u0423\u0437\u043a\u043e\u0432\u043e"
    ],
    "wof:name":"Uzkovo",
    "wof:placetype":"locality"
},
  "geometry": {"coordinates":[42.1363,54.7037],"type":"Point"}
}