{
  "type": "Feature",
  "properties": {
    "gn:admin1_code":"33",
    "gn:asciiname":"Shushary",
    "gn:country_code":"RU",
    "gn:dem":130,
    "gn:feature_class":"P",
    "gn:feature_code":"PPL",
    "gn:name":"Shushary",
    "gn:population":0,
    "gn:timezone":"Europe/Kirov",
    "iso:country":"RU",
    "name:rus_x_preferred":[
        "\u0428\u0443\u0448\u0430\u0440\u044b"
    ],
    "wof:name":"Shushary",
    "wof:placetype":"locality"
},
  "geometry": {"coordinates":[50.98333,57.48333],"type":"Point"}
}