{
  "type": "Feature",
  "properties": {
    "gn:admin1_code":"84",
    "gn:asciiname":"Krutovskiy",
    "gn:country_code":"RU",
    "gn:dem":59,
    "gn:feature_class":"P",
    "gn:feature_code":"PPL",
    "gn:name":"Krutovskiy",
    "gn:population":0,
    "gn:timezone":"Europe/Volgograd",
    "iso:country":"RU",
    "name:eng_x_preferred":[
        "Krutovskiy"
    ],
    "name:nor_x_preferred":[
        "Krutovskij"
    ],
    "name:rus_x_preferred":[
        "\u041a\u0440\u0443\u0442\u043e\u0432\u0441\u043a\u0438\u0439"
    ],
    "wof:name":"Krutovskiy",
    "wof:placetype":"locality"
},
  "geometry": {"coordinates":[42.2312,49.5863],"type":"Point"}
}