{
  "type": "Feature",
  "properties": {
    "gn:admin1_code":"28",
    "gn:asciiname":"Kerisyur'ya",
    "gn:country_code":"RU",
    "gn:dem":78,
    "gn:feature_class":"P",
    "gn:feature_code":"PPL",
    "gn:name":"Kerisyur\u2019ya",
    "gn:population":0,
    "gn:timezone":"Europe/Moscow",
    "iso:country":"RU",
    "name:fin_x_preferred":[
        "Kelisyrj\u00e4"
    ],
    "name:rus_x_preferred":[
        "\u041a\u0435\u0440\u0438\u0441\u044e\u0440\u044c\u044f"
    ],
    "name:und_x_variant":[
        "Kerisyur\u2019ya"
    ],
    "wof:name":"Kerisyur'ya",
    "wof:placetype":"locality"
},
  "geometry": {"coordinates":[31.1071,61.73738],"type":"Point"}
}