{
  "type": "Feature",
  "properties": {
    "gn:admin1_code":"25",
    "gn:asciiname":"Korytnya",
    "gn:country_code":"RU",
    "gn:dem":212,
    "gn:feature_class":"P",
    "gn:feature_code":"PPL",
    "gn:name":"Korytnya",
    "gn:population":0,
    "gn:timezone":"Europe/Moscow",
    "iso:country":"RU",
    "name:rus_x_preferred":[
        "\u041a\u043e\u0440\u044b\u0442\u043d\u044f"
    ],
    "wof:name":"Korytnya",
    "wof:placetype":"locality"
},
  "geometry": {"coordinates":[36.73278,54.80333],"type":"Point"}
}