{
  "type": "Feature",
  "properties": {
    "gn:admin1_code":"47",
    "gn:asciiname":"Gornevo",
    "gn:country_code":"RU",
    "gn:dem":174,
    "gn:feature_class":"P",
    "gn:feature_code":"PPL",
    "gn:name":"Gornevo",
    "gn:population":0,
    "gn:timezone":"Europe/Moscow",
    "iso:country":"RU",
    "name:rus_x_preferred":[
        "\u0413\u043e\u0440\u043d\u0435\u0432\u043e"
    ],
    "name:und_x_variant":[
        "Gornevo"
    ],
    "wof:name":"Gornevo",
    "wof:placetype":"locality"
},
  "geometry": {"coordinates":[37.09645,55.19905],"type":"Point"}
}