{
  "type": "Feature",
  "properties": {
    "gn:admin1_code":"23",
    "gn:asciiname":"Novostroyevo",
    "gn:country_code":"RU",
    "gn:dem":89,
    "gn:feature_class":"P",
    "gn:feature_code":"PPL",
    "gn:name":"Novostroyevo",
    "gn:population":0,
    "gn:timezone":"Europe/Kaliningrad",
    "iso:country":"RU",
    "name:deu_x_preferred":[
        "Trempen"
    ],
    "name:rus_x_preferred":[
        "\u041d\u043e\u0432\u043e\u0441\u0442\u0440\u043e\u0435\u0432\u043e"
    ],
    "name:und_x_variant":[
        "\u041d\u043e\u0432\u043e\u0441\u0442\u0440\u043e\u0435\u0432\u043e",
        "Trempen"
    ],
    "wof:name":"Novostroyevo",
    "wof:placetype":"locality"
},
  "geometry": {"coordinates":[21.83275,54.44212],"type":"Point"}
}