{
  "type": "Feature",
  "properties": {
    "gn:admin1_code":"62.0",
    "gn:asciiname":"Abryutino",
    "gn:country_code":"RU",
    "gn:dem":158,
    "gn:feature_class":"P",
    "gn:feature_code":"PPL",
    "gn:name":"Abryutino",
    "gn:population":0,
    "gn:timezone":"Europe/Moscow",
    "iso:country":"RU",
    "name:nor_x_preferred":[
        "Abrjutino"
    ],
    "name:rus_x_preferred":[
        "\u0410\u0431\u0440\u044e\u0442\u0438\u043d\u043e"
    ],
    "wof:name":"Abryutino",
    "wof:placetype":"locality"
},
  "geometry": {"coordinates":[39.5577,54.547],"type":"Point"}
}