{
  "type": "Feature",
  "properties": {
    "gn:admin1_code":"52",
    "gn:asciiname":"Kislyakovo",
    "gn:country_code":"RU",
    "gn:dem":66,
    "gn:feature_class":"P",
    "gn:feature_code":"PPL",
    "gn:name":"Kislyakovo",
    "gn:population":0,
    "gn:timezone":"Europe/Moscow",
    "iso:country":"RU",
    "name:rus_x_preferred":[
        "\u041a\u0438\u0441\u043b\u044f\u043a\u043e\u0432\u043e"
    ],
    "wof:name":"Kislyakovo",
    "wof:placetype":"locality"
},
  "geometry": {"coordinates":[30.885,57.9544],"type":"Point"}
}