{
  "type": "Feature",
  "properties": {
    "gn:admin1_code":"37",
    "gn:asciiname":"Prostotino",
    "gn:country_code":"RU",
    "gn:dem":159,
    "gn:feature_class":"P",
    "gn:feature_code":"PPL",
    "gn:name":"Prostotino",
    "gn:population":0,
    "gn:timezone":"Europe/Moscow",
    "iso:country":"RU",
    "name:rus_x_preferred":[
        "\u041f\u0440\u043e\u0441\u0442\u043e\u0442\u0438\u043d\u043e"
    ],
    "name:und_x_variant":[
        "\u041f\u0440\u043e\u0441\u0442\u043e\u0442\u0438\u043d\u043e"
    ],
    "wof:name":"Prostotino",
    "wof:placetype":"locality"
},
  "geometry": {"coordinates":[42.08718,59.26116],"type":"Point"}
}