{
  "type": "Feature",
  "properties": {
    "gn:admin1_code":"41",
    "gn:asciiname":"Yefrosimovka",
    "gn:country_code":"RU",
    "gn:dem":171,
    "gn:feature_class":"P",
    "gn:feature_code":"PPL",
    "gn:name":"Yefrosimovka",
    "gn:population":0,
    "gn:timezone":"Europe/Moscow",
    "iso:country":"RU",
    "name:rus_x_preferred":[
        "\u0415\u0444\u0440\u043e\u0441\u0438\u043c\u043e\u0432\u043a\u0430"
    ],
    "wof:name":"Yefrosimovka",
    "wof:placetype":"locality"
},
  "geometry": {"coordinates":[35.6955,51.496],"type":"Point"}
}