{
  "type": "Feature",
  "properties": {
    "gn:admin1_code":"1",
    "gn:asciiname":"Novyy Sad",
    "gn:country_code":"RU",
    "gn:dem":28,
    "gn:feature_class":"P",
    "gn:feature_code":"PPL",
    "gn:name":"Novyy Sad",
    "gn:population":0,
    "gn:timezone":"Europe/Moscow",
    "iso:country":"RU",
    "name:rus_x_preferred":[
        "\u041d\u043e\u0432\u044b\u0439 \u0421\u0430\u0434"
    ],
    "name:und_x_variant":[
        "\u041d\u043e\u0432\u044b\u0439 \u0421\u0430\u0434"
    ],
    "wof:name":"Novyy Sad",
    "wof:placetype":"locality"
},
  "geometry": {"coordinates":[38.90557,44.90446],"type":"Point"}
}