{
  "type": "Feature",
  "properties": {
    "gn:admin1_code":"16",
    "gn:asciiname":"Yegorkino",
    "gn:country_code":"RU",
    "gn:dem":121,
    "gn:feature_class":"P",
    "gn:feature_code":"PPL",
    "gn:name":"Yegorkino",
    "gn:population":0,
    "gn:timezone":"Europe/Moscow",
    "iso:country":"RU",
    "name:rus_x_preferred":[
        "\u0415\u0433\u043e\u0440\u043a\u0438\u043d\u043e"
    ],
    "wof:name":"Yegorkino",
    "wof:placetype":"locality"
},
  "geometry": {"coordinates":[46.356,55.6384],"type":"Point"}
}