{
  "type": "Feature",
  "properties": {
    "gn:admin1_code":"20",
    "gn:asciiname":"Pavlovskaya",
    "gn:country_code":"RU",
    "gn:dem":618,
    "gn:feature_class":"P",
    "gn:feature_code":"PPL",
    "gn:name":"Pavlovskaya",
    "gn:population":0,
    "gn:timezone":"Asia/Irkutsk",
    "iso:country":"RU",
    "name:rus_x_preferred":[
        "\u041f\u0430\u0432\u043b\u043e\u0432\u0441\u043a\u0430\u044f"
    ],
    "name:und_x_variant":[
        "\u041f\u0430\u0432\u043b\u043e\u0432\u0441\u043a\u0430\u044f"
    ],
    "wof:name":"Pavlovskaya",
    "wof:placetype":"locality"
},
  "geometry": {"coordinates":[106.15000000000001,56.38333000000001],"type":"Point"}
}