{
  "type": "Feature",
  "properties": {
    "gn:admin1_code":"83.0",
    "gn:asciiname":"Karel'skaya Slobodka",
    "gn:country_code":"RU",
    "gn:dem":146,
    "gn:feature_class":"P",
    "gn:feature_code":"PPL",
    "gn:name":"Karel\u2019skaya Slobodka",
    "gn:population":0,
    "gn:timezone":"Europe/Moscow",
    "iso:country":"RU",
    "name:rus_x_preferred":[
        "\u041a\u0430\u0440\u0435\u043b\u044c\u0441\u043a\u0430\u044f \u0421\u043b\u043e\u0431\u043e\u0434\u043a\u0430"
    ],
    "name:und_x_variant":[
        "Karel\u2019skaya Slobodka"
    ],
    "wof:name":"Karel'skaya Slobodka",
    "wof:placetype":"locality"
},
  "geometry": {"coordinates":[40.21784,56.39397],"type":"Point"}
}