{
  "type": "Feature",
  "properties": {
    "gn:admin1_code":"23",
    "gn:asciiname":"Mezhdules'ye",
    "gn:country_code":"RU",
    "gn:dem":8,
    "gn:feature_class":"P",
    "gn:feature_code":"PPL",
    "gn:name":"Mezhdules\u2019ye",
    "gn:population":0,
    "gn:timezone":"Europe/Kaliningrad",
    "iso:country":"RU",
    "name:rus_x_preferred":[
        "\u041c\u0435\u0436\u0434\u0443\u043b\u0435\u0441\u044c\u0435"
    ],
    "name:und_x_variant":[
        "Mezhdules\u2019ye",
        "\u041c\u0435\u0436\u0434\u0443\u043b\u0435\u0441\u044c\u0435"
    ],
    "wof:name":"Mezhdules'ye",
    "wof:placetype":"locality"
},
  "geometry": {"coordinates":[21.31326,54.73461],"type":"Point"}
}