{
  "type": "Feature",
  "properties": {
    "gn:admin1_code":"13",
    "gn:asciiname":"Trudovoy",
    "gn:country_code":"RU",
    "gn:dem":178,
    "gn:feature_class":"P",
    "gn:feature_code":"PPL",
    "gn:name":"Trudovoy",
    "gn:population":0,
    "gn:timezone":"Asia/Yekaterinburg",
    "iso:country":"RU",
    "name:eng_x_preferred":[
        "Trudovoy"
    ],
    "name:nor_x_preferred":[
        "Trudovoj"
    ],
    "name:rus_x_preferred":[
        "\u0422\u0440\u0443\u0434\u043e\u0432\u043e\u0439"
    ],
    "wof:name":"Trudovoy",
    "wof:placetype":"locality"
},
  "geometry": {"coordinates":[61.7458,55.9905],"type":"Point"}
}