{
  "type": "Feature",
  "properties": {
    "gn:admin1_code":"52",
    "gn:asciiname":"Ryshevo",
    "gn:country_code":"RU",
    "gn:dem":37,
    "gn:feature_class":"P",
    "gn:feature_code":"PPL",
    "gn:name":"Ryshevo",
    "gn:population":0,
    "gn:timezone":"Europe/Moscow",
    "iso:country":"RU",
    "name:rus_x_preferred":[
        "\u0420\u044b\u0448\u0435\u0432\u043e"
    ],
    "wof:name":"Ryshevo",
    "wof:placetype":"locality"
},
  "geometry": {"coordinates":[31.80649,58.58096999999999],"type":"Point"}
}