{
  "type": "Feature",
  "properties": {
    "gn:admin1_code":"52",
    "gn:asciiname":"Berezovik",
    "gn:country_code":"RU",
    "gn:dem":187,
    "gn:feature_class":"P",
    "gn:feature_code":"PPL",
    "gn:name":"Ber\u00ebzovik",
    "gn:population":0,
    "gn:timezone":"Europe/Moscow",
    "iso:country":"RU",
    "name:rus_x_preferred":[
        "\u0411\u0435\u0440\u0451\u0437\u043e\u0432\u0438\u043a"
    ],
    "name:und_x_variant":[
        "Ber\u00ebzovik"
    ],
    "wof:name":"Berezovik",
    "wof:placetype":"locality"
},
  "geometry": {"coordinates":[36.115,58.5089],"type":"Point"}
}