{
  "type": "Feature",
  "properties": {
    "gn:admin1_code":"28",
    "gn:asciiname":"Nizhneye Kumozero",
    "gn:country_code":"RU",
    "gn:dem":80,
    "gn:feature_class":"P",
    "gn:feature_code":"PPL",
    "gn:name":"Nizhneye Kumozero",
    "gn:population":0,
    "gn:timezone":"Europe/Moscow",
    "iso:country":"RU",
    "name:fin_x_preferred":[
        "Ala-Kuusemaj\u00e4rvi"
    ],
    "name:rus_x_preferred":[
        "\u041d\u0438\u0436\u043d\u0435\u0435 \u041a\u0443\u043c\u043e\u0437\u0435\u0440\u043e"
    ],
    "name:und_x_variant":[
        "\u041d\u0438\u0436\u043d\u0435\u0435 \u041a\u0443\u043c\u043e\u0437\u0435\u0440\u043e"
    ],
    "wof:name":"Nizhneye Kumozero",
    "wof:placetype":"locality"
},
  "geometry": {"coordinates":[33.26063,65.46471],"type":"Point"}
}