{
  "type": "Feature",
  "properties": {
    "gn:admin1_code":"77",
    "gn:asciiname":"Krivkina",
    "gn:country_code":"RU",
    "gn:dem":197,
    "gn:feature_class":"P",
    "gn:feature_code":"PPL",
    "gn:name":"Krivkina",
    "gn:population":0,
    "gn:timezone":"Europe/Moscow",
    "iso:country":"RU",
    "name:rus_x_preferred":[
        "\u041a\u0440\u0438\u0432\u043a\u0438\u043d\u0430"
    ],
    "wof:name":"Krivkina",
    "wof:placetype":"locality"
},
  "geometry": {"coordinates":[31.56667,56.28333000000001],"type":"Point"}
}