{
  "type": "Feature",
  "properties": {
    "gn:admin1_code":"20",
    "gn:asciiname":"Sosna",
    "gn:country_code":"RU",
    "gn:dem":283,
    "gn:feature_class":"P",
    "gn:feature_code":"PPL",
    "gn:name":"Sosna",
    "gn:population":0,
    "gn:timezone":"Asia/Irkutsk",
    "iso:country":"RU",
    "name:rus_x_preferred":[
        "\u0421\u043e\u0441\u043d\u0430"
    ],
    "name:und_x_variant":[
        "\u0421\u043e\u0441\u043d\u0430"
    ],
    "wof:name":"Sosna",
    "wof:placetype":"locality"
},
  "geometry": {"coordinates":[106.73333,60.96666999999999],"type":"Point"}
}