{
  "type": "Feature",
  "properties": {
    "gn:admin1_code":"63",
    "gn:asciiname":"Ken-Balagan",
    "gn:country_code":"RU",
    "gn:dem":131,
    "gn:feature_class":"P",
    "gn:feature_code":"PPL",
    "gn:name":"Ken-Balagan",
    "gn:population":0,
    "gn:timezone":"Asia/Vladivostok",
    "iso:country":"RU",
    "name:rus_x_preferred":[
        "\u041a\u0435\u043d-\u0411\u0430\u043b\u0430\u0433\u0430\u043d"
    ],
    "name:und_x_variant":[
        "\u041a\u0435\u043d-\u0411\u0430\u043b\u0430\u0433\u0430\u043d"
    ],
    "wof:name":"Ken-Balagan",
    "wof:placetype":"locality"
},
  "geometry": {"coordinates":[132.59999999999999,67.46666999999999],"type":"Point"}
}