{
  "type": "Feature",
  "properties": {
    "gn:admin1_code":"55",
    "gn:asciiname":"Novodubovka",
    "gn:country_code":"RU",
    "gn:dem":120,
    "gn:feature_class":"P",
    "gn:feature_code":"PPL",
    "gn:name":"Novodubovka",
    "gn:population":0,
    "gn:timezone":"Asia/Yekaterinburg",
    "iso:country":"RU",
    "name:rus_x_preferred":[
        "\u041d\u043e\u0432\u043e\u0434\u0443\u0431\u043e\u0432\u043a\u0430"
    ],
    "wof:name":"Novodubovka",
    "wof:placetype":"locality"
},
  "geometry": {"coordinates":[51.61667,52.53333000000001],"type":"Point"}
}