{
  "type": "Feature",
  "properties": {
    "gn:admin1_code":"3",
    "gn:asciiname":"Levinka",
    "gn:cc2":"RU",
    "gn:country_code":"RU",
    "gn:dem":306,
    "gn:feature_class":"P",
    "gn:feature_code":"PPL",
    "gn:name":"Levinka",
    "gn:population":0,
    "gn:timezone":"Asia/Omsk",
    "iso:country":"RU",
    "name:eng_x_preferred":[
        "Levinka"
    ],
    "name:nor_x_preferred":[
        "Levinka"
    ],
    "name:rus_x_preferred":[
        "\u041b\u0435\u0432\u0438\u043d\u043a\u0430"
    ],
    "name:und_x_variant":[
        "Levinskoye",
        "Levinskiy",
        "Levinskii",
        "\u041b\u0435\u0432\u0438\u043d\u043a\u0430",
        "Levinka"
    ],
    "wof:name":"Levinka",
    "wof:placetype":"locality"
},
  "geometry": {"coordinates":[86.42083000000002,51.97861],"type":"Point"}
}