{
  "type": "Feature",
  "properties": {
    "gn:admin1_code":"56.0",
    "gn:asciiname":"Dorogoye",
    "gn:country_code":"RU",
    "gn:dem":191,
    "gn:feature_class":"P",
    "gn:feature_code":"PPL",
    "gn:name":"Dorogoye",
    "gn:population":0,
    "gn:timezone":"Europe/Moscow",
    "iso:country":"RU",
    "name:rus_x_preferred":[
        "\u0414\u043e\u0440\u043e\u0433\u043e\u0435"
    ],
    "wof:name":"Dorogoye",
    "wof:placetype":"locality"
},
  "geometry": {"coordinates":[36.6921,52.79536],"type":"Point"}
}