{
  "type": "Feature",
  "properties": {
    "gn:admin1_code":"69",
    "gn:asciiname":"Slizovo",
    "gn:country_code":"RU",
    "gn:dem":214,
    "gn:feature_class":"P",
    "gn:feature_code":"PPL",
    "gn:name":"Slizovo",
    "gn:population":0,
    "gn:timezone":"Europe/Moscow",
    "iso:country":"RU",
    "name:rus_x_preferred":[
        "\u0421\u043b\u0438\u0437\u043e\u0432\u043e"
    ],
    "wof:name":"Slizovo",
    "wof:placetype":"locality"
},
  "geometry": {"coordinates":[32.79083,54.77833],"type":"Point"}
}