{
  "type": "Feature",
  "properties": {
    "gn:admin1_code":"40",
    "gn:asciiname":"Mayka",
    "gn:country_code":"RU",
    "gn:dem":174,
    "gn:feature_class":"P",
    "gn:feature_code":"PPL",
    "gn:name":"Mayka",
    "gn:population":0,
    "gn:timezone":"Asia/Yekaterinburg",
    "iso:country":"RU",
    "name:rus_x_preferred":[
        "\u041c\u0430\u0439\u043a\u0430"
    ],
    "name:und_x_variant":[
        "\u041c\u0430\u0439\u043a\u0430"
    ],
    "wof:name":"Mayka",
    "wof:placetype":"locality"
},
  "geometry": {"coordinates":[62.26111,55.23472],"type":"Point"}
}