{
  "type": "Feature",
  "properties": {
    "gn:admin1_code":"33",
    "gn:asciiname":"Pozhar",
    "gn:country_code":"RU",
    "gn:dem":91,
    "gn:feature_class":"P",
    "gn:feature_code":"PPL",
    "gn:name":"Pozhar",
    "gn:population":0,
    "gn:timezone":"Europe/Kirov",
    "iso:country":"RU",
    "name:rus_x_preferred":[
        "\u041f\u043e\u0436\u0430\u0440"
    ],
    "wof:name":"Pozhar",
    "wof:placetype":"locality"
},
  "geometry": {"coordinates":[47.08058,60.3005],"type":"Point"}
}