{
  "type": "Feature",
  "properties": {
    "gn:admin1_code":"69",
    "gn:asciiname":"Sheynovka",
    "gn:country_code":"RU",
    "gn:dem":178,
    "gn:feature_class":"P",
    "gn:feature_code":"PPL",
    "gn:name":"Sheynovka",
    "gn:population":0,
    "gn:timezone":"Europe/Moscow",
    "iso:country":"RU",
    "name:rus_x_preferred":[
        "\u0428\u0435\u0439\u043d\u043e\u0432\u043a\u0430"
    ],
    "wof:name":"Sheynovka",
    "wof:placetype":"locality"
},
  "geometry": {"coordinates":[32.1119,54.80335],"type":"Point"}
}