{
  "type": "Feature",
  "properties": {
    "gn:admin1_code":"62",
    "gn:asciiname":"Svistovka",
    "gn:country_code":"RU",
    "gn:dem":135,
    "gn:feature_class":"P",
    "gn:feature_code":"PPL",
    "gn:name":"Svistovka",
    "gn:population":0,
    "gn:timezone":"Europe/Moscow",
    "iso:country":"RU",
    "name:rus_x_preferred":[
        "\u0421\u0432\u0438\u0441\u0442\u043e\u0432\u043a\u0430"
    ],
    "wof:name":"Svistovka",
    "wof:placetype":"locality"
},
  "geometry": {"coordinates":[40.0042,53.4519],"type":"Point"}
}