{
  "type": "Feature",
  "properties": {
    "gn:admin1_code":"77.0",
    "gn:asciiname":"Cheshovo",
    "gn:country_code":"RU",
    "gn:dem":166,
    "gn:feature_class":"P",
    "gn:feature_code":"PPL",
    "gn:name":"Cheshovo",
    "gn:population":0,
    "gn:timezone":"Europe/Moscow",
    "iso:country":"RU",
    "name:eng_x_preferred":[
        "Cheshovo"
    ],
    "name:nor_x_preferred":[
        "Tsjesjevo"
    ],
    "name:rus_x_preferred":[
        "\u0427\u0435\u0448\u0435\u0432\u043e"
    ],
    "name:rus_x_variant":[
        "\u0427\u0435\u0448\u043e\u0432\u043e"
    ],
    "wof:name":"Cheshovo",
    "wof:placetype":"locality"
},
  "geometry": {"coordinates":[34.282,58.00532],"type":"Point"}
}