{
  "type": "Feature",
  "properties": {
    "gn:admin1_code":"60",
    "gn:asciiname":"Sklevo",
    "gn:country_code":"RU",
    "gn:dem":78,
    "gn:feature_class":"P",
    "gn:feature_code":"PPL",
    "gn:name":"Skl\u00ebvo",
    "gn:population":0,
    "gn:timezone":"Europe/Moscow",
    "iso:country":"RU",
    "name:rus_x_preferred":[
        "\u0421\u043a\u043b\u0451\u0432\u043e"
    ],
    "name:und_x_variant":[
        "Skl\u00ebv",
        "Skl\u00ebvo",
        "\u0421\u043a\u043b\u0451\u0432\u043e"
    ],
    "wof:name":"Sklevo",
    "wof:placetype":"locality"
},
  "geometry": {"coordinates":[30.06785,57.57283],"type":"Point"}
}