{
  "type": "Feature",
  "properties": {
    "gn:admin1_code":"77.0",
    "gn:asciiname":"Dvoyna",
    "gn:country_code":"RU",
    "gn:dem":228,
    "gn:feature_class":"P",
    "gn:feature_code":"PPL",
    "gn:name":"Dvoyna",
    "gn:population":0,
    "gn:timezone":"Europe/Moscow",
    "iso:country":"RU",
    "name:rus_x_preferred":[
        "\u0414\u0432\u043e\u0439\u043d\u0430"
    ],
    "wof:name":"Dvoyna",
    "wof:placetype":"locality"
},
  "geometry": {"coordinates":[34.2345,56.48841],"type":"Point"}
}