{
  "type": "Feature",
  "properties": {
    "gn:admin1_code":"83",
    "gn:asciiname":"Pivovarovo",
    "gn:country_code":"RU",
    "gn:dem":147,
    "gn:feature_class":"P",
    "gn:feature_code":"PPL",
    "gn:name":"Pivovarovo",
    "gn:population":0,
    "gn:timezone":"Europe/Moscow",
    "iso:country":"RU",
    "name:rus_x_preferred":[
        "\u041f\u0438\u0432\u043e\u0432\u0430\u0440\u043e\u0432\u043e"
    ],
    "name:und_x_variant":[
        "\u041f\u0438\u0432\u043e\u0432\u0430\u0440\u043e\u0432\u043e"
    ],
    "wof:name":"Pivovarovo",
    "wof:placetype":"locality"
},
  "geometry": {"coordinates":[41.3002,55.8007],"type":"Point"}
}