{
  "type": "Feature",
  "properties": {
    "gn:admin1_code":"38.0",
    "gn:asciiname":"Suetkha Pervyy",
    "gn:cc2":"RU",
    "gn:country_code":"RU",
    "gn:dem":343,
    "gn:feature_class":"P",
    "gn:feature_code":"PPL",
    "gn:name":"Suetkha Pervyy",
    "gn:population":0,
    "gn:timezone":"Europe/Moscow",
    "iso:country":"RU",
    "name:und_x_variant":[
        "Suyetkh Pervyy"
    ],
    "wof:name":"Suetkha Pervyy",
    "wof:placetype":"locality"
},
  "geometry": {"coordinates":[39.5925,43.80667],"type":"Point"}
}