{
  "type": "Feature",
  "properties": {
    "gn:admin1_code":"54",
    "gn:asciiname":"Enbekshi-Kazakh",
    "gn:country_code":"RU",
    "gn:dem":122,
    "gn:feature_class":"P",
    "gn:feature_code":"PPL",
    "gn:name":"Enbekshi-Kazakh",
    "gn:population":0,
    "gn:timezone":"Asia/Omsk",
    "iso:country":"RU",
    "name:rus_x_preferred":[
        "\u042d\u043d\u0431\u0435\u043a\u0448\u0438-\u041a\u0430\u0437\u0430\u0445"
    ],
    "name:und_x_variant":[
        "\u042d\u043d\u0431\u0435\u043a\u0448\u0438-\u041a\u0430\u0437\u0430\u0445"
    ],
    "wof:name":"Enbekshi-Kazakh",
    "wof:placetype":"locality"
},
  "geometry": {"coordinates":[71.51806999999999,55.31889],"type":"Point"}
}