{
  "type": "Feature",
  "properties": {
    "gn:admin1_code":"91",
    "gn:asciiname":"Kukuy",
    "gn:country_code":"RU",
    "gn:dem":265,
    "gn:feature_class":"P",
    "gn:feature_code":"PPL",
    "gn:name":"Kukuy",
    "gn:population":0,
    "gn:timezone":"Asia/Krasnoyarsk",
    "iso:country":"RU",
    "name:rus_x_preferred":[
        "\u041a\u0443\u043a\u0443\u0439"
    ],
    "wof:name":"Kukuy",
    "wof:placetype":"locality"
},
  "geometry": {"coordinates":[92.03333000000001,62.28333000000001],"type":"Point"}
}