{
  "type": "Feature",
  "properties": {
    "gn:admin1_code":"33.0",
    "gn:asciiname":"Filenki",
    "gn:country_code":"RU",
    "gn:dem":217,
    "gn:feature_class":"P",
    "gn:feature_code":"PPL",
    "gn:name":"Filenki",
    "gn:population":0,
    "gn:timezone":"Europe/Kirov",
    "iso:country":"RU",
    "name:rus_x_preferred":[
        "\u0424\u0438\u043b\u0435\u043d\u043a\u0438"
    ],
    "wof:name":"Filenki",
    "wof:placetype":"locality"
},
  "geometry": {"coordinates":[53.593,58.5224],"type":"Point"}
}