{
  "type": "Feature",
  "properties": {
    "iso:country":"RU",
    "name:eng_x_variant":[
        "Northern Butovo"
    ],
    "name:rus_x_preferred":[
        "\u0421\u0435\u0432\u0435\u0440\u043d\u043e\u0435 \u0411\u0443\u0442\u043e\u0432\u043e"
    ],
    "wof:name":"Severnoye Butovo",
    "wof:placetype":"neighbourhood"
},
  "geometry": {"coordinates":[37.56995867021384,55.5687921787702],"type":"Point"}
}