{
  "type": "Feature",
  "properties": {
    "gn:admin1_code":"56.0",
    "gn:asciiname":"Chernod'ye",
    "gn:country_code":"RU",
    "gn:dem":204,
    "gn:feature_class":"P",
    "gn:feature_code":"PPL",
    "gn:name":"Chernod\u2019ye",
    "gn:population":0,
    "gn:timezone":"Europe/Moscow",
    "iso:country":"RU",
    "name:rus_x_preferred":[
        "\u0427\u0435\u0440\u043d\u043e\u0434\u044c\u0435"
    ],
    "name:und_x_variant":[
        "Chernod\u2019ye",
        "\u0427\u0435\u0440\u043d\u043e\u0434\u044c\u0435"
    ],
    "wof:name":"Chernod'ye",
    "wof:placetype":"locality"
},
  "geometry": {"coordinates":[35.7359,52.4791],"type":"Point"}
}