{
  "type": "Feature",
  "properties": {
    "gn:admin1_code":"90",
    "gn:asciiname":"Lobozovo",
    "gn:country_code":"RU",
    "gn:dem":172,
    "gn:feature_class":"P",
    "gn:feature_code":"PPL",
    "gn:name":"Lobozovo",
    "gn:population":0,
    "gn:timezone":"Asia/Yekaterinburg",
    "iso:country":"RU",
    "name:rus_x_preferred":[
        "\u041b\u043e\u0431\u043e\u0437\u043e\u0432\u043e"
    ],
    "name:und_x_variant":[
        "\u041b\u043e\u0431\u043e\u0437\u043e\u0432\u043e"
    ],
    "wof:name":"Lobozovo",
    "wof:placetype":"locality"
},
  "geometry": {"coordinates":[54.2194,59.5352],"type":"Point"}
}