{
  "type": "Feature",
  "properties": {
    "gn:admin1_code":"88.0",
    "gn:asciiname":"Lytino",
    "gn:country_code":"RU",
    "gn:dem":106,
    "gn:feature_class":"P",
    "gn:feature_code":"PPL",
    "gn:name":"Lytino",
    "gn:population":0,
    "gn:timezone":"Europe/Moscow",
    "iso:country":"RU",
    "name:rus_x_preferred":[
        "\u041b\u044b\u0442\u0438\u043d\u043e"
    ],
    "name:und_x_variant":[
        "\u041b\u044b\u0442\u0438\u043d\u043e"
    ],
    "wof:name":"Lytino",
    "wof:placetype":"locality"
},
  "geometry": {"coordinates":[40.47001,58.00653000000001],"type":"Point"}
}