{
  "type": "Feature",
  "properties": {
    "gn:admin1_code":"81",
    "gn:asciiname":"Ushakovka",
    "gn:country_code":"RU",
    "gn:dem":226,
    "gn:feature_class":"P",
    "gn:feature_code":"PPL",
    "gn:name":"Ushakovka",
    "gn:population":0,
    "gn:timezone":"Europe/Ulyanovsk",
    "iso:country":"RU",
    "name:che_x_preferred":[
        "\u0423\u0448\u0430\u043a\u043e\u0432\u043a\u0430"
    ],
    "name:rus_x_preferred":[
        "\u0423\u0448\u0430\u043a\u043e\u0432\u043a\u0430"
    ],
    "name:tgk_x_preferred":[
        "\u0423\u0448\u0430\u043a\u043e\u0432\u043a\u0430"
    ],
    "wof:name":"Ushakovka",
    "wof:placetype":"locality"
},
  "geometry": {"coordinates":[46.9017,53.5647],"type":"Point"}
}