{
  "type": "Feature",
  "properties": {
    "gn:admin1_code":"24.0",
    "gn:asciiname":"Ryzhkovo",
    "gn:country_code":"RU",
    "gn:dem":-21,
    "gn:feature_class":"P",
    "gn:feature_code":"PPL",
    "gn:name":"Ryzhkovo",
    "gn:population":0,
    "gn:timezone":"Europe/Moscow",
    "iso:country":"RU",
    "wof:name":"Ryzhkovo",
    "wof:placetype":"locality"
},
  "geometry": {"coordinates":[47.34028,45.44611],"type":"Point"}
}