{
  "type": "Feature",
  "properties": {
    "gn:admin1_code":"16",
    "gn:asciiname":"Tymar",
    "gn:country_code":"RU",
    "gn:dem":193,
    "gn:feature_class":"P",
    "gn:feature_code":"PPL",
    "gn:name":"Tymar",
    "gn:population":0,
    "gn:timezone":"Europe/Moscow",
    "iso:country":"RU",
    "name:rus_x_preferred":[
        "\u0422\u044b\u043c\u0430\u0440"
    ],
    "name:und_x_variant":[
        "Tymer",
        "Tymar"
    ],
    "wof:name":"Tymar",
    "wof:placetype":"locality"
},
  "geometry": {"coordinates":[47.01692,55.2713],"type":"Point"}
}