{
  "type": "Feature",
  "properties": {
    "gn:admin1_code":"34",
    "gn:asciiname":"Ust'-Un'ya",
    "gn:country_code":"RU",
    "gn:dem":139,
    "gn:feature_class":"P",
    "gn:feature_code":"PPL",
    "gn:name":"Ust\u2019-Un\u2019ya",
    "gn:population":0,
    "gn:timezone":"Europe/Moscow",
    "iso:country":"RU",
    "name:eng_x_preferred":[
        "Ust'-Un'ya"
    ],
    "name:nor_x_preferred":[
        "Ust-Unja"
    ],
    "name:rus_x_preferred":[
        "\u0423\u0441\u0442\u044c-\u0423\u043d\u044c\u044f"
    ],
    "name:und_x_variant":[
        "Ust\u2019-Un\u2019ya"
    ],
    "wof:name":"Ust'-Un'ya",
    "wof:placetype":"locality"
},
  "geometry": {"coordinates":[57.87399,61.80774],"type":"Point"}
}