{
  "type": "Feature",
  "properties": {
    "gn:admin1_code":"77",
    "gn:asciiname":"Vyselok-Il'inskoye",
    "gn:country_code":"RU",
    "gn:dem":210,
    "gn:feature_class":"P",
    "gn:feature_code":"PPL",
    "gn:name":"Vyselok-Il\u2019inskoye",
    "gn:population":0,
    "gn:timezone":"Europe/Moscow",
    "iso:country":"RU",
    "name:rus_x_preferred":[
        "\u0412\u044b\u0441\u0435\u043b\u043e\u043a-\u0418\u043b\u044c\u0438\u043d\u0441\u043a\u043e\u0435"
    ],
    "name:und_x_variant":[
        "Vyselok-Il\u2019inskoye"
    ],
    "wof:name":"Vyselok-Il'inskoye",
    "wof:placetype":"locality"
},
  "geometry": {"coordinates":[32.85632,56.95115],"type":"Point"}
}