{
  "type": "Feature",
  "properties": {
    "gn:admin1_code":"44",
    "gn:asciiname":"Talon",
    "gn:country_code":"RU",
    "gn:dem":23,
    "gn:feature_class":"P",
    "gn:feature_code":"PPL",
    "gn:name":"Talon",
    "gn:population":0,
    "gn:timezone":"Asia/Magadan",
    "iso:country":"RU",
    "name:aze_x_preferred":[
        "Talon"
    ],
    "name:ceb_x_preferred":[
        "Talon"
    ],
    "name:ces_x_preferred":[
        "Talon"
    ],
    "name:dan_x_preferred":[
        "Talon"
    ],
    "name:deu_x_preferred":[
        "Talon"
    ],
    "name:eng_x_preferred":[
        "Talon"
    ],
    "name:fra_x_preferred":[
        "Talon"
    ],
    "name:ido_x_preferred":[
        "Talono"
    ],
    "name:ita_x_preferred":[
        "Talon"
    ],
    "name:nld_x_preferred":[
        "Talon"
    ],
    "name:nor_x_preferred":[
        "Talon"
    ],
    "name:oci_x_preferred":[
        "Talon"
    ],
    "name:pol_x_preferred":[
        "Talon"
    ],
    "name:rus_x_preferred":[
        "\u0422\u0430\u043b\u043e\u043d"
    ],
    "name:tgl_x_preferred":[
        "Talon"
    ],
    "name:ukr_x_preferred":[
        "\u0422\u0430\u043b\u043e\u043d"
    ],
    "wof:name":"Talon",
    "wof:placetype":"locality"
},
  "geometry": {"coordinates":[148.65776,59.76154],"type":"Point"}
}