{
  "type": "Feature",
  "properties": {
    "gn:admin1_code":"6",
    "gn:asciiname":"Losevo",
    "gn:country_code":"RU",
    "gn:dem":46,
    "gn:feature_class":"P",
    "gn:feature_code":"PPL",
    "gn:name":"Losevo",
    "gn:population":0,
    "gn:timezone":"Europe/Moscow",
    "iso:country":"RU",
    "name:deu_x_preferred":[
        "Lossewo"
    ],
    "name:eng_x_preferred":[
        "Losevo"
    ],
    "name:nor_x_preferred":[
        "Losevo"
    ],
    "name:rus_x_preferred":[
        "\u041b\u043e\u0441\u0435\u0432\u043e"
    ],
    "name:spa_x_preferred":[
        "L\u00f3sevo"
    ],
    "name:und_x_variant":[
        "\u041b\u043e\u0441\u0435\u0432\u043e",
        "Losevo"
    ],
    "wof:name":"Losevo",
    "wof:placetype":"locality"
},
  "geometry": {"coordinates":[44.9274,63.7984],"type":"Point"}
}