{
  "type": "Feature",
  "properties": {
    "gn:admin1_code":"10",
    "gn:asciiname":"Pupkovskiy",
    "gn:country_code":"RU",
    "gn:dem":177,
    "gn:feature_class":"P",
    "gn:feature_code":"PPL",
    "gn:name":"Pupkovskiy",
    "gn:population":0,
    "gn:timezone":"Europe/Moscow",
    "iso:country":"RU",
    "name:rus_x_preferred":[
        "\u041f\u0443\u043f\u043a\u043e\u0432\u0441\u043a\u0438\u0439"
    ],
    "wof:name":"Pupkovskiy",
    "wof:placetype":"locality"
},
  "geometry": {"coordinates":[34.50833,53.52721999999999],"type":"Point"}
}