{
  "type": "Feature",
  "properties": {
    "gn:admin1_code":"62",
    "gn:asciiname":"Probuzhdeniye",
    "gn:country_code":"RU",
    "gn:dem":157,
    "gn:feature_class":"P",
    "gn:feature_code":"PPL",
    "gn:name":"Probuzhdeniye",
    "gn:population":0,
    "gn:timezone":"Europe/Moscow",
    "iso:country":"RU",
    "name:rus_x_preferred":[
        "\u041f\u0440\u043e\u0431\u0443\u0436\u0434\u0435\u043d\u0438\u0435"
    ],
    "name:und_x_variant":[
        "\u041f\u0440\u043e\u0431\u0443\u0436\u0434\u0435\u043d\u0438\u0435"
    ],
    "wof:name":"Probuzhdeniye",
    "wof:placetype":"locality"
},
  "geometry": {"coordinates":[39.5206,53.6195],"type":"Point"}
}