{
  "type": "Feature",
  "properties": {
    "gn:admin1_code":"41",
    "gn:asciiname":"Spokoyevka",
    "gn:country_code":"RU",
    "gn:dem":188,
    "gn:feature_class":"P",
    "gn:feature_code":"PPL",
    "gn:name":"Spokoyevka",
    "gn:population":0,
    "gn:timezone":"Europe/Moscow",
    "iso:country":"RU",
    "name:rus_x_preferred":[
        "\u0421\u043f\u043e\u043a\u043e\u0435\u0432\u043a\u0430"
    ],
    "wof:name":"Spokoyevka",
    "wof:placetype":"locality"
},
  "geometry": {"coordinates":[35.9775,51.5035],"type":"Point"}
}