{
  "type": "Feature",
  "properties": {
    "gn:admin1_code":"91",
    "gn:asciiname":"Yakushevo",
    "gn:country_code":"RU",
    "gn:dem":311,
    "gn:feature_class":"P",
    "gn:feature_code":"PPL",
    "gn:name":"Yakushevo",
    "gn:population":0,
    "gn:timezone":"Asia/Krasnoyarsk",
    "iso:country":"RU",
    "name:eng_x_preferred":[
        "Yakushevo"
    ],
    "name:nor_x_preferred":[
        "Jakusjevo"
    ],
    "name:rus_x_preferred":[
        "\u042f\u043a\u0443\u0448\u0435\u0432\u043e"
    ],
    "name:und_x_variant":[
        "Yakusheva"
    ],
    "wof:name":"Yakushevo",
    "wof:placetype":"locality"
},
  "geometry": {"coordinates":[91.05804999999999,55.19285],"type":"Point"}
}