{
  "type": "Feature",
  "properties": {
    "gn:admin1_code":"05",
    "gn:asciiname":"Khalan",
    "gn:country_code":"RU",
    "gn:dem":517,
    "gn:feature_class":"P",
    "gn:feature_code":"PPL",
    "gn:name":"Khalan",
    "gn:population":0,
    "gn:timezone":"Asia/Yakutsk",
    "iso:country":"RU",
    "name:ceb_x_preferred":[
        "Kh\u0101l\u0101n"
    ],
    "name:eng_x_preferred":[
        "Khalan"
    ],
    "name:fas_x_preferred":[
        "\u062e\u0627\u0644\u0627\u0646"
    ],
    "name:msa_x_preferred":[
        "Khalan"
    ],
    "name:nor_x_preferred":[
        "Khalan"
    ],
    "name:rus_x_preferred":[
        "\u0425\u0430\u043b\u0430\u043d"
    ],
    "name:swe_x_preferred":[
        "Kh\u0101l\u0101n"
    ],
    "name:und_x_variant":[
        "Kholin",
        "Kholan",
        "\u0425\u0430\u043b\u0430\u043d",
        "Khalan"
    ],
    "wof:name":"Khalan",
    "wof:placetype":"locality"
},
  "geometry": {"coordinates":[122.59815,54.06931],"type":"Point"}
}