{
  "type": "Feature",
  "properties": {
    "gn:admin1_code":"9",
    "gn:asciiname":"Roskoshnyy",
    "gn:country_code":"RU",
    "gn:dem":214,
    "gn:feature_class":"P",
    "gn:feature_code":"PPL",
    "gn:name":"Roskoshnyy",
    "gn:population":0,
    "gn:timezone":"Europe/Moscow",
    "iso:country":"RU",
    "name:rus_x_preferred":[
        "\u0420\u043e\u0441\u043a\u043e\u0448\u043d\u044b\u0439"
    ],
    "wof:name":"Roskoshnyy",
    "wof:placetype":"locality"
},
  "geometry": {"coordinates":[37.338,51.2056],"type":"Point"}
}