{
  "type": "Feature",
  "properties": {
    "gn:admin1_code":"10",
    "gn:asciiname":"Sinezerskiy",
    "gn:country_code":"RU",
    "gn:dem":173,
    "gn:feature_class":"P",
    "gn:feature_code":"PPL",
    "gn:name":"Sinez\u00ebrskiy",
    "gn:population":0,
    "gn:timezone":"Europe/Moscow",
    "iso:country":"RU",
    "name:eng_x_preferred":[
        "Sinez\u00ebrskiy"
    ],
    "name:nor_x_preferred":[
        "Sinezerki"
    ],
    "name:rus_x_preferred":[
        "\u0421\u0438\u043d\u0435\u0437\u0435\u0440\u043a\u0438"
    ],
    "name:rus_x_variant":[
        "\u0421\u0438\u043d\u0435\u0437\u0451\u0440\u0441\u043a\u0438\u0439"
    ],
    "name:und_x_variant":[
        "Sinezerka",
        "Sinez\u00ebrki",
        "Sinererki",
        "Sinez\u00ebrskiy",
        "\u0421\u0438\u043d\u0435\u0437\u0451\u0440\u0441\u043a\u0438\u0439"
    ],
    "wof:name":"Sinezerskiy",
    "wof:placetype":"locality"
},
  "geometry": {"coordinates":[34.43551,53.02563000000001],"type":"Point"}
}