{
  "type": "Feature",
  "properties": {
    "gn:admin1_code":"77",
    "gn:asciiname":"Solovki",
    "gn:country_code":"RU",
    "gn:dem":175,
    "gn:feature_class":"P",
    "gn:feature_code":"PPL",
    "gn:name":"Solovki",
    "gn:population":0,
    "gn:timezone":"Europe/Moscow",
    "iso:country":"RU",
    "name:rus_x_preferred":[
        "\u0421\u043e\u043b\u043e\u0432\u043a\u0438"
    ],
    "name:und_x_variant":[
        "\u0421\u043e\u043b\u043e\u0432\u043a\u0438"
    ],
    "wof:name":"Solovki",
    "wof:placetype":"locality"
},
  "geometry": {"coordinates":[35.36667,58.36666999999999],"type":"Point"}
}