{
  "type": "Feature",
  "properties": {
    "gn:admin1_code":"21.0",
    "gn:asciiname":"Seredukhino",
    "gn:country_code":"RU",
    "gn:dem":105,
    "gn:feature_class":"P",
    "gn:feature_code":"PPL",
    "gn:name":"Seredukhino",
    "gn:population":0,
    "gn:timezone":"Europe/Moscow",
    "iso:country":"RU",
    "name:rus_x_preferred":[
        "\u0421\u0435\u0440\u0435\u0434\u0443\u0445\u0438\u043d\u043e"
    ],
    "name:und_x_variant":[
        "\u0421\u0435\u0440\u0435\u0434\u0443\u0445\u0438\u043d\u043e"
    ],
    "wof:name":"Seredukhino",
    "wof:placetype":"locality"
},
  "geometry": {"coordinates":[42.98364,57.13869],"type":"Point"}
}