{
  "type": "Feature",
  "properties": {
    "gn:admin1_code":"80.0",
    "gn:asciiname":"Bygi",
    "gn:country_code":"RU",
    "gn:dem":139,
    "gn:feature_class":"P",
    "gn:feature_code":"PPL",
    "gn:name":"Bygi",
    "gn:population":0,
    "gn:timezone":"Europe/Samara",
    "iso:country":"RU",
    "name:rus_x_preferred":[
        "\u0411\u044b\u0433\u0438"
    ],
    "name:und_x_variant":[
        "Staryye Bygi",
        "Bygi"
    ],
    "wof:name":"Bygi",
    "wof:placetype":"locality"
},
  "geometry": {"coordinates":[53.75989000000001,57.21848000000001],"type":"Point"}
}