{
  "type": "Feature",
  "properties": {
    "gn:admin1_code":"61.0",
    "gn:asciiname":"Gerasimovka",
    "gn:country_code":"RU",
    "gn:dem":12,
    "gn:feature_class":"P",
    "gn:feature_code":"PPL",
    "gn:name":"Gerasimovka",
    "gn:population":0,
    "gn:timezone":"Europe/Moscow",
    "iso:country":"RU",
    "name:rus_x_preferred":[
        "\u0413\u0435\u0440\u0430\u0441\u0438\u043c\u043e\u0432\u043a\u0430"
    ],
    "name:und_x_variant":[
        "\u0413\u0435\u0440\u0430\u0441\u0438\u043c\u043e\u0432\u043a\u0430"
    ],
    "wof:name":"Gerasimovka",
    "wof:placetype":"locality"
},
  "geometry": {"coordinates":[38.75958,47.24047],"type":"Point"}
}