{
  "type": "Feature",
  "properties": {
    "gn:admin1_code":"53",
    "gn:asciiname":"Staryye Karachi",
    "gn:country_code":"RU",
    "gn:dem":104,
    "gn:feature_class":"P",
    "gn:feature_code":"PPL",
    "gn:name":"Staryye Karachi",
    "gn:population":0,
    "gn:timezone":"Asia/Novosibirsk",
    "iso:country":"RU",
    "name:eng_x_preferred":[
        "Staryye Karachi"
    ],
    "name:nor_x_preferred":[
        "Starye Karatsji"
    ],
    "name:rus_x_preferred":[
        "\u0421\u0442\u0430\u0440\u044b\u0435 \u041a\u0430\u0440\u0430\u0447\u0438"
    ],
    "name:und_x_variant":[
        "Starokarachi",
        "Karachinskoye"
    ],
    "wof:name":"Staryye Karachi",
    "wof:placetype":"locality"
},
  "geometry": {"coordinates":[77.04668000000002,55.49645],"type":"Point"}
}