{
  "type": "Feature",
  "properties": {
    "gn:admin1_code":"49.0",
    "gn:asciiname":"Chapoma",
    "gn:country_code":"RU",
    "gn:dem":19,
    "gn:feature_class":"P",
    "gn:feature_code":"PPL",
    "gn:name":"Chapoma",
    "gn:population":0,
    "gn:timezone":"Europe/Moscow",
    "iso:country":"RU",
    "name:eng_x_preferred":[
        "Chapoma"
    ],
    "name:nor_x_preferred":[
        "Tsjapoma"
    ],
    "name:rus_x_preferred":[
        "\u0427\u0430\u043f\u043e\u043c\u0430"
    ],
    "name:und_x_variant":[
        "Seleniye Chapoma",
        "\u0427\u0430\u043f\u043e\u043c\u0430",
        "Chapoma"
    ],
    "wof:name":"Chapoma",
    "wof:placetype":"locality"
},
  "geometry": {"coordinates":[38.86964,66.10414],"type":"Point"}
}