{
  "type": "Feature",
  "properties": {
    "gn:admin1_code":"70.0",
    "gn:asciiname":"Severnyy",
    "gn:country_code":"RU",
    "gn:dem":208,
    "gn:feature_class":"P",
    "gn:feature_code":"PPL",
    "gn:name":"Severnyy",
    "gn:population":0,
    "gn:timezone":"Europe/Moscow",
    "iso:country":"RU",
    "name:eng_x_preferred":[
        "Severnyy"
    ],
    "name:nor_x_preferred":[
        "Severnyj"
    ],
    "name:rus_x_preferred":[
        "\u0421\u0435\u0432\u0435\u0440\u043d\u044b\u0439"
    ],
    "wof:name":"Severnyy",
    "wof:placetype":"locality"
},
  "geometry": {"coordinates":[44.27222,44.15444],"type":"Point"}
}