{
  "type": "Feature",
  "properties": {
    "gn:admin1_code":"69",
    "gn:asciiname":"Pereyezd",
    "gn:country_code":"RU",
    "gn:dem":194,
    "gn:feature_class":"P",
    "gn:feature_code":"PPL",
    "gn:name":"Pereyezd",
    "gn:population":0,
    "gn:timezone":"Europe/Moscow",
    "iso:country":"RU",
    "name:rus_x_preferred":[
        "\u041f\u0435\u0440\u0435\u0435\u0437\u0434"
    ],
    "name:und_x_variant":[
        "Pereyezdovo",
        "Pereyezd"
    ],
    "wof:name":"Pereyezd",
    "wof:placetype":"locality"
},
  "geometry": {"coordinates":[31.97192,55.08841999999999],"type":"Point"}
}