{
  "type": "Feature",
  "properties": {
    "gn:admin1_code":"20.0",
    "gn:asciiname":"Zamazchikova",
    "gn:country_code":"RU",
    "gn:dem":500,
    "gn:feature_class":"P",
    "gn:feature_code":"PPL",
    "gn:name":"Zamazchikova",
    "gn:population":0,
    "gn:timezone":"Asia/Irkutsk",
    "iso:country":"RU",
    "name:rus_x_preferred":[
        "\u0417\u0430\u043c\u0430\u0437\u0447\u0438\u043a\u043e\u0432\u0430"
    ],
    "wof:name":"Zamazchikova",
    "wof:placetype":"locality"
},
  "geometry": {"coordinates":[102.1446,53.4831],"type":"Point"}
}