{
  "type": "Feature",
  "properties": {
    "gn:admin1_code":"10",
    "gn:asciiname":"Nezevayevka",
    "gn:country_code":"RU",
    "gn:dem":143,
    "gn:feature_class":"P",
    "gn:feature_code":"PPL",
    "gn:name":"Nezevayevka",
    "gn:population":0,
    "gn:timezone":"Europe/Moscow",
    "iso:country":"RU",
    "name:rus_x_preferred":[
        "\u041d\u0435\u0437\u0435\u0432\u0430\u0435\u0432\u043a\u0430"
    ],
    "wof:name":"Nezevayevka",
    "wof:placetype":"locality"
},
  "geometry": {"coordinates":[33.1032,52.6095],"type":"Point"}
}