{
  "type": "Feature",
  "properties": {
    "gn:admin1_code":"63",
    "gn:asciiname":"Oguy-Okhtubutt",
    "gn:country_code":"RU",
    "gn:dem":156,
    "gn:feature_class":"P",
    "gn:feature_code":"PPL",
    "gn:name":"Oguy-Okhtubutt",
    "gn:population":0,
    "gn:timezone":"Asia/Vladivostok",
    "iso:country":"RU",
    "name:rus_x_preferred":[
        "\u041e\u0433\u0443\u0439-\u041e\u0445\u0442\u0443\u0431\u0443\u0442\u0442"
    ],
    "wof:name":"Oguy-Okhtubutt",
    "wof:placetype":"locality"
},
  "geometry": {"coordinates":[135.34542999999999,67.23741],"type":"Point"}
}