{
  "type": "Feature",
  "properties": {
    "gn:admin1_code":"33",
    "gn:asciiname":"Khlebishino",
    "gn:country_code":"RU",
    "gn:dem":135,
    "gn:feature_class":"P",
    "gn:feature_code":"PPL",
    "gn:name":"Khlebishino",
    "gn:population":0,
    "gn:timezone":"Europe/Kirov",
    "iso:country":"RU",
    "name:rus_x_preferred":[
        "\u0425\u043b\u0435\u0431\u0438\u0448\u0438\u043d\u043e"
    ],
    "name:und_x_variant":[
        "\u0425\u043b\u0435\u0431\u0438\u0448\u0438\u043d\u043e"
    ],
    "wof:name":"Khlebishino",
    "wof:placetype":"locality"
},
  "geometry": {"coordinates":[47.33333,60.31667],"type":"Point"}
}