{
  "type": "Feature",
  "properties": {
    "gn:admin1_code":"47",
    "gn:asciiname":"Loshatovo",
    "gn:country_code":"RU",
    "gn:dem":159,
    "gn:feature_class":"P",
    "gn:feature_code":"PPL",
    "gn:name":"Loshatovo",
    "gn:population":0,
    "gn:timezone":"Europe/Moscow",
    "iso:country":"RU",
    "name:rus_x_preferred":[
        "\u041b\u043e\u0448\u0430\u0442\u043e\u0432\u043e"
    ],
    "name:und_x_variant":[
        "Bol\u2019shaya Loshatovka",
        "Loshatovo"
    ],
    "wof:name":"Loshatovo",
    "wof:placetype":"locality"
},
  "geometry": {"coordinates":[38.81401,54.57502],"type":"Point"}
}