{
  "type": "Feature",
  "properties": {
    "gn:admin1_code":"91",
    "gn:asciiname":"Shilinka",
    "gn:country_code":"RU",
    "gn:dem":236,
    "gn:feature_class":"P",
    "gn:feature_code":"PPL",
    "gn:name":"Shilinka",
    "gn:population":0,
    "gn:timezone":"Asia/Krasnoyarsk",
    "iso:country":"RU",
    "name:eng_x_preferred":[
        "Shilinka"
    ],
    "name:nor_x_preferred":[
        "Sjilinka"
    ],
    "name:rus_x_preferred":[
        "\u0428\u0438\u043b\u0438\u043d\u043a\u0430"
    ],
    "wof:name":"Shilinka",
    "wof:placetype":"locality"
},
  "geometry": {"coordinates":[92.9165,56.5361],"type":"Point"}
}