{
  "type": "Feature",
  "properties": {
    "gn:admin1_code":"91",
    "gn:asciiname":"Podgornoye",
    "gn:cc2":"RU",
    "gn:country_code":"RU",
    "gn:dem":119,
    "gn:feature_class":"P",
    "gn:feature_code":"PPL",
    "gn:name":"Podgornoye",
    "gn:population":0,
    "gn:timezone":"Asia/Krasnoyarsk",
    "iso:country":"RU",
    "name:eng_x_preferred":[
        "Podgornoye"
    ],
    "name:nor_x_preferred":[
        "Podgornoje"
    ],
    "name:rus_x_preferred":[
        "\u041f\u043e\u0434\u0433\u043e\u0440\u043d\u043e\u0435"
    ],
    "name:und_x_variant":[
        "Podgornayo",
        "Podgornaya",
        "Podgornoye"
    ],
    "wof:name":"Podgornoye",
    "wof:placetype":"locality"
},
  "geometry": {"coordinates":[91.88806,58.10944],"type":"Point"}
}