{
  "type": "Feature",
  "properties": {
    "gn:admin1_code":"33.0",
    "gn:asciiname":"Barzichi",
    "gn:country_code":"RU",
    "gn:dem":136,
    "gn:feature_class":"P",
    "gn:feature_code":"PPL",
    "gn:name":"Barzichi",
    "gn:population":0,
    "gn:timezone":"Europe/Kirov",
    "iso:country":"RU",
    "name:rus_x_preferred":[
        "\u0411\u0430\u0440\u0437\u0438\u0447\u0438"
    ],
    "name:und_x_variant":[
        "Varzichi"
    ],
    "wof:name":"Barzichi",
    "wof:placetype":"locality"
},
  "geometry": {"coordinates":[48.00056,58.8025],"type":"Point"}
}