{
  "type": "Feature",
  "properties": {
    "gn:admin1_code":"88",
    "gn:asciiname":"Krivtsovo",
    "gn:country_code":"RU",
    "gn:dem":139,
    "gn:feature_class":"P",
    "gn:feature_code":"PPL",
    "gn:name":"Krivtsovo",
    "gn:population":0,
    "gn:timezone":"Europe/Moscow",
    "iso:country":"RU",
    "name:rus_x_preferred":[
        "\u041a\u0440\u0438\u0432\u0446\u043e\u0432\u043e"
    ],
    "wof:name":"Krivtsovo",
    "wof:placetype":"locality"
},
  "geometry": {"coordinates":[37.5352,58.3654],"type":"Point"}
}