{
  "type": "Feature",
  "properties": {
    "gn:admin1_code":"33",
    "gn:asciiname":"Rychazhnoye",
    "gn:country_code":"RU",
    "gn:dem":122,
    "gn:feature_class":"P",
    "gn:feature_code":"PPL",
    "gn:name":"Rychazhnoye",
    "gn:population":0,
    "gn:timezone":"Europe/Kirov",
    "iso:country":"RU",
    "name:eng_x_preferred":[
        "Rychazhnoye"
    ],
    "name:nor_x_preferred":[
        "Rytsjazjnoje"
    ],
    "name:rus_x_preferred":[
        "\u0420\u044b\u0447\u0430\u0436\u043d\u043e\u0435"
    ],
    "wof:name":"Rychazhnoye",
    "wof:placetype":"locality"
},
  "geometry": {"coordinates":[50.2673,59.0258],"type":"Point"}
}