{
  "type": "Feature",
  "properties": {
    "gn:admin1_code":"62",
    "gn:asciiname":"Lavsya",
    "gn:country_code":"RU",
    "gn:dem":110,
    "gn:feature_class":"P",
    "gn:feature_code":"PPL",
    "gn:name":"Lavsya",
    "gn:population":0,
    "gn:timezone":"Europe/Moscow",
    "iso:country":"RU",
    "name:eng_x_preferred":[
        "Lapsya"
    ],
    "name:nor_x_preferred":[
        "Lavsia"
    ],
    "name:rus_x_preferred":[
        "\u041b\u0430\u0432\u0441\u044f"
    ],
    "name:und_x_variant":[
        "Lapsya"
    ],
    "wof:name":"Lavsya",
    "wof:placetype":"locality"
},
  "geometry": {"coordinates":[41.17515,55.20111],"type":"Point"}
}