{
  "type": "Feature",
  "properties": {
    "gn:admin1_code":"76",
    "gn:asciiname":"Grumant",
    "gn:country_code":"RU",
    "gn:dem":208,
    "gn:feature_class":"P",
    "gn:feature_code":"PPL",
    "gn:name":"Grumant",
    "gn:population":0,
    "gn:timezone":"Europe/Moscow",
    "iso:country":"RU",
    "name:und_x_variant":[
        "Ugryumy"
    ],
    "wof:name":"Grumant",
    "wof:placetype":"locality"
},
  "geometry": {"coordinates":[37.48528,54.07111],"type":"Point"}
}