{
  "type": "Feature",
  "properties": {
    "gn:admin1_code":"76",
    "gn:asciiname":"Grumant",
    "gn:country_code":"RU",
    "gn:dem":208,
    "gn:feature_class":"P",
    "gn:feature_code":"PPL",
    "gn:name":"Grumant",
    "gn:population":0,
    "gn:timezone":"Europe/Moscow",
    "iso:country":"RU",
    "name:bul_x_preferred":[
        "\u0413\u0440\u0443\u043c\u0430\u043d\u0442"
    ],
    "name:cat_x_preferred":[
        "Gr\u00famant"
    ],
    "name:dan_x_preferred":[
        "Grumantbyen"
    ],
    "name:deu_x_preferred":[
        "Grumant"
    ],
    "name:fra_x_preferred":[
        "Grumantbyen"
    ],
    "name:ita_x_preferred":[
        "Grumantbyen"
    ],
    "name:nld_x_preferred":[
        "Groemant"
    ],
    "name:nno_x_preferred":[
        "Grumantbyen"
    ],
    "name:nor_x_preferred":[
        "Grumantbyen"
    ],
    "name:rus_x_preferred":[
        "\u0413\u0440\u0443\u043c\u0430\u043d\u0442"
    ],
    "name:spa_x_preferred":[
        "Grumant"
    ],
    "name:swe_x_preferred":[
        "Grumantbyen"
    ],
    "name:ukr_x_preferred":[
        "\u0413\u0440\u0443\u043c\u0430\u043d\u0442"
    ],
    "name:und_x_variant":[
        "Ugryumy"
    ],
    "wof:name":"Grumant",
    "wof:placetype":"locality"
},
  "geometry": {"coordinates":[37.48528,54.07111],"type":"Point"}
}