{
  "type": "Feature",
  "properties": {
    "gn:admin1_code":"10.0",
    "gn:asciiname":"Byakovo",
    "gn:country_code":"RU",
    "gn:dem":171,
    "gn:feature_class":"P",
    "gn:feature_code":"PPL",
    "gn:name":"Byakovo",
    "gn:population":0,
    "gn:timezone":"Europe/Moscow",
    "iso:country":"RU",
    "name:eng_x_preferred":[
        "Byakovo"
    ],
    "name:nor_x_preferred":[
        "Bjakovo"
    ],
    "name:rus_x_preferred":[
        "\u0411\u044f\u043a\u043e\u0432\u043e"
    ],
    "name:und_x_variant":[
        "Bykhovo"
    ],
    "wof:name":"Byakovo",
    "wof:placetype":"locality"
},
  "geometry": {"coordinates":[34.55422,52.87172],"type":"Point"}
}