{
  "type": "Feature",
  "properties": {
    "gn:admin1_code":"80",
    "gn:asciiname":"Pochinki",
    "gn:country_code":"RU",
    "gn:dem":187,
    "gn:feature_class":"P",
    "gn:feature_code":"PPL",
    "gn:name":"Pochinki",
    "gn:population":0,
    "gn:timezone":"Europe/Samara",
    "iso:country":"RU",
    "name:ara_x_preferred":[
        "\u0628\u0648\u0634\u0646\u0643\u064a"
    ],
    "name:eng_x_preferred":[
        "Pochinki"
    ],
    "name:nor_x_preferred":[
        "Potsjinki"
    ],
    "name:rus_x_preferred":[
        "\u041f\u043e\u0447\u0438\u043d\u043a\u0438"
    ],
    "name:und_x_variant":[
        "Pochinochnaya",
        "\u041f\u043e\u0447\u0438\u043d\u043a\u0438",
        "Pochinki"
    ],
    "wof:name":"Pochinki",
    "wof:placetype":"locality"
},
  "geometry": {"coordinates":[52.2673,57.9544],"type":"Point"}
}