{
  "type": "Feature",
  "properties": {
    "gn:country":"RU",
    "gn:fcode":"PPL",
    "gn:population":0,
    "iso:country":"RU",
    "name:eng_x_preferred":[
        "Zav'yalovo"
    ],
    "name:nor_x_preferred":[
        "Zavjalovo"
    ],
    "name:rus_x_preferred":[
        "\u0417\u0430\u0432\u044c\u044f\u043b\u043e\u0432\u043e"
    ],
    "name:und_x_variant":[
        "Zav\u2019yalovskoye"
    ],
    "qs:name":"Zav'yalovo",
    "qs:name_adm0":"Russia",
    "qs:name_adm1":"Novosibirsk Oblast",
    "qs:photos":60,
    "qs:photos_1k":12,
    "qs:photos_9k":1,
    "qs:photos_9r":2,
    "qs:photos_all":60,
    "qs:photos_sr":2,
    "qs:placetype":"Town",
    "qs:pop_sr":"4",
    "wof:name":"Zav'yalovo",
    "wof:placetype":"locality",
    "wof:population":0
},
  "geometry": {"coordinates":[82.4508,54.5047],"type":"Point"}
}