{
  "type": "Feature",
  "properties": {
    "gn:admin1_code":"69",
    "gn:asciiname":"Yeremeno",
    "gn:cc2":"RU",
    "gn:country_code":"RU",
    "gn:dem":236,
    "gn:feature_class":"P",
    "gn:feature_code":"PPL",
    "gn:name":"Yer\u00ebmeno",
    "gn:population":0,
    "gn:timezone":"Europe/Moscow",
    "iso:country":"RU",
    "name:und_x_variant":[
        "Yeremino",
        "Yer\u00ebmeno"
    ],
    "wof:name":"Yeremeno",
    "wof:placetype":"locality"
},
  "geometry": {"coordinates":[33.80833,55.67806],"type":"Point"}
}