{
  "type": "Feature",
  "properties": {
    "gn:admin1_code":"24.0",
    "gn:asciiname":"Beglete",
    "gn:country_code":"RU",
    "gn:dem":-13,
    "gn:feature_class":"P",
    "gn:feature_code":"PPL",
    "gn:name":"Beglete",
    "gn:population":0,
    "gn:timezone":"Europe/Moscow",
    "iso:country":"RU",
    "name:rus_x_preferred":[
        "\u0411\u0435\u0433\u043b\u0435\u0442\u0435"
    ],
    "name:und_x_variant":[
        "Kuduk Beglete",
        "Beglete"
    ],
    "wof:name":"Beglete",
    "wof:placetype":"locality"
},
  "geometry": {"coordinates":[46.5276,46.4086],"type":"Point"}
}