{
  "type": "Feature",
  "properties": {
    "gn:admin1_code":"56",
    "gn:asciiname":"Pesochenskiy",
    "gn:country_code":"RU",
    "gn:dem":260,
    "gn:feature_class":"P",
    "gn:feature_code":"PPL",
    "gn:name":"Pesochenskiy",
    "gn:population":0,
    "gn:timezone":"Europe/Moscow",
    "iso:country":"RU",
    "name:rus_x_preferred":[
        "\u041f\u0435\u0441\u043e\u0447\u0435\u043d\u0441\u043a\u0438\u0439"
    ],
    "wof:name":"Pesochenskiy",
    "wof:placetype":"locality"
},
  "geometry": {"coordinates":[37.53333,52.98333],"type":"Point"}
}