{
  "type": "Feature",
  "properties": {
    "gn:admin1_code":"84",
    "gn:asciiname":"Malyy Oreshkin",
    "gn:country_code":"RU",
    "gn:dem":86,
    "gn:feature_class":"P",
    "gn:feature_code":"PPL",
    "gn:name":"Malyy Oreshkin",
    "gn:population":0,
    "gn:timezone":"Europe/Volgograd",
    "iso:country":"RU",
    "name:rus_x_preferred":[
        "\u041c\u0430\u043b\u044b\u0439 \u041e\u0440\u0435\u0448\u043a\u0438\u043d"
    ],
    "wof:name":"Malyy Oreshkin",
    "wof:placetype":"locality"
},
  "geometry": {"coordinates":[43.4069,50.169],"type":"Point"}
}