{
  "type": "Feature",
  "properties": {
    "gn:admin1_code":"71",
    "gn:asciiname":"Vantur",
    "gn:country_code":"RU",
    "gn:dem":79,
    "gn:feature_class":"P",
    "gn:feature_code":"PPL",
    "gn:name":"Vantur",
    "gn:population":0,
    "gn:timezone":"Asia/Yekaterinburg",
    "iso:country":"RU",
    "name:eng_x_preferred":[
        "Vantur"
    ],
    "name:nor_x_preferred":[
        "Vantur"
    ],
    "name:rus_x_preferred":[
        "\u0412\u0430\u043d\u0442\u0443\u0440"
    ],
    "wof:name":"Vantur",
    "wof:placetype":"locality"
},
  "geometry": {"coordinates":[62.08333,60.73333],"type":"Point"}
}