{
  "type": "Feature",
  "properties": {
    "gn:admin1_code":"6",
    "gn:asciiname":"Chizhikovo",
    "gn:country_code":"RU",
    "gn:dem":31,
    "gn:feature_class":"P",
    "gn:feature_code":"PPL",
    "gn:name":"Chizhikovo",
    "gn:population":0,
    "gn:timezone":"Europe/Moscow",
    "iso:country":"RU",
    "name:eng_x_preferred":[
        "Chizhikovo"
    ],
    "name:nor_x_preferred":[
        "Tsjizjikovo"
    ],
    "name:rus_x_preferred":[
        "\u0427\u0438\u0436\u0438\u043a\u043e\u0432\u043e"
    ],
    "name:und_x_variant":[
        "Pizhikovo",
        "\u0427\u0438\u0436\u0438\u043a\u043e\u0432\u043e",
        "Chizhikovo"
    ],
    "wof:name":"Chizhikovo",
    "wof:placetype":"locality"
},
  "geometry": {"coordinates":[38.72734000000001,63.65795],"type":"Point"}
}