{
  "type": "Feature",
  "properties": {
    "gn:country":"RU",
    "gn:fcode":"PPL",
    "gn:population":3059,
    "iso:country":"RU",
    "name:nor_x_preferred":[
        "Taremskoje"
    ],
    "name:rus_x_preferred":[
        "\u0422\u0430\u0440\u0435\u043c\u0441\u043a\u043e\u0435"
    ],
    "qs:name":"Taremskoye",
    "qs:photos_9r":0,
    "qs:photos_sr":0,
    "qs:pop_sr":"4",
    "wof:name":"Taremskoye",
    "wof:placetype":"locality",
    "wof:population":3059
},
  "geometry": {"coordinates":[43.04433,55.92889],"type":"Point"}
}