{
  "type": "Feature",
  "properties": {
    "gn:admin1_code":"8",
    "gn:asciiname":"Salikhovo",
    "gn:country_code":"RU",
    "gn:dem":165,
    "gn:feature_class":"P",
    "gn:feature_code":"PPL",
    "gn:name":"Salikhovo",
    "gn:population":0,
    "gn:timezone":"Asia/Yekaterinburg",
    "iso:country":"RU",
    "name:aze_x_preferred":[
        "S\u0259lix"
    ],
    "name:bak_x_preferred":[
        "\u0421\u04d9\u043b\u0438\u0445"
    ],
    "name:che_x_preferred":[
        "\u0421\u0430\u043b\u0438\u0445\u043e\u0432\u043e"
    ],
    "name:eng_x_preferred":[
        "Salikhovo"
    ],
    "name:hye_x_preferred":[
        "\u054d\u0561\u056c\u056b\u056d\u0578\u057e\u0578"
    ],
    "name:kaz_x_preferred":[
        "\u0421\u0430\u043b\u0438\u0445"
    ],
    "name:kir_x_preferred":[
        "\u0421\u0430\u043b\u0438\u0445"
    ],
    "name:nor_x_preferred":[
        "Salikhovo"
    ],
    "name:rus_x_preferred":[
        "\u0421\u0430\u043b\u0438\u0445\u043e\u0432\u043e"
    ],
    "name:tat_x_preferred":[
        "\u0421\u0430\u043b\u0438\u0445"
    ],
    "name:ukr_x_preferred":[
        "\u0421\u0430\u043b\u0456\u0445\u043e\u0432\u043e"
    ],
    "name:und_x_variant":[
        "\u0421\u0430\u043b\u0438\u0445\u043e\u0432\u043e",
        "Salikhovo"
    ],
    "wof:name":"Salikhovo",
    "wof:placetype":"locality"
},
  "geometry": {"coordinates":[56.22584000000001,53.51342],"type":"Point"}
}