{
  "type": "Feature",
  "properties": {
    "gn:admin1_code":"33",
    "gn:asciiname":"Utmanovo",
    "gn:country_code":"RU",
    "gn:dem":104,
    "gn:feature_class":"P",
    "gn:feature_code":"PPL",
    "gn:name":"Utmanovo",
    "gn:population":0,
    "gn:timezone":"Europe/Kirov",
    "iso:country":"RU",
    "name:eng_x_preferred":[
        "Utmanovo"
    ],
    "name:nor_x_preferred":[
        "Utmanovo"
    ],
    "name:rus_x_preferred":[
        "\u0423\u0442\u043c\u0430\u043d\u043e\u0432\u043e"
    ],
    "wof:name":"Utmanovo",
    "wof:placetype":"locality"
},
  "geometry": {"coordinates":[46.63018,60.15292],"type":"Point"}
}