{
  "type": "Feature",
  "properties": {
    "gn:admin1_code":"56",
    "gn:asciiname":"Stany",
    "gn:country_code":"RU",
    "gn:dem":234,
    "gn:feature_class":"P",
    "gn:feature_code":"PPL",
    "gn:name":"Stany",
    "gn:population":0,
    "gn:timezone":"Europe/Moscow",
    "iso:country":"RU",
    "name:fra_x_preferred":[
        "Stany"
    ],
    "name:pol_x_preferred":[
        "Stany"
    ],
    "name:rus_x_preferred":[
        "\u0421\u0442\u0430\u043d\u044b"
    ],
    "name:ukr_x_preferred":[
        "\u0421\u0442\u0430\u043d\u0438"
    ],
    "name:und_x_variant":[
        "\u0421\u0442\u0430\u043d\u044b"
    ],
    "wof:name":"Stany",
    "wof:placetype":"locality"
},
  "geometry": {"coordinates":[36.5575,52.9622],"type":"Point"}
}