{
  "type": "Feature",
  "properties": {
    "gn:admin1_code":"17.0",
    "gn:asciiname":"Rizhkhoa",
    "gn:country_code":"RU",
    "gn:dem":2869,
    "gn:feature_class":"P",
    "gn:feature_code":"PPL",
    "gn:name":"Rizhkhoa",
    "gn:population":0,
    "gn:timezone":"Europe/Moscow",
    "iso:country":"RU",
    "wof:name":"Rizhkhoa",
    "wof:placetype":"locality"
},
  "geometry": {"coordinates":[47.53444,41.42861],"type":"Point"}
}