{
  "type": "Feature",
  "properties": {
    "gn:admin1_code":"52",
    "gn:asciiname":"Malyye Myasnitsy",
    "gn:country_code":"RU",
    "gn:dem":75,
    "gn:feature_class":"P",
    "gn:feature_code":"PPL",
    "gn:name":"Malyye Myasnitsy",
    "gn:population":0,
    "gn:timezone":"Europe/Moscow",
    "iso:country":"RU",
    "name:rus_x_preferred":[
        "\u041c\u0430\u043b\u044b\u0435 \u041c\u044f\u0441\u043d\u0438\u0446\u044b"
    ],
    "wof:name":"Malyye Myasnitsy",
    "wof:placetype":"locality"
},
  "geometry": {"coordinates":[31.98333,58.08333],"type":"Point"}
}