{
  "type": "Feature",
  "properties": {
    "gn:admin1_code":"85",
    "gn:asciiname":"Nadeyevo",
    "gn:country_code":"RU",
    "gn:dem":130,
    "gn:feature_class":"P",
    "gn:feature_code":"PPL",
    "gn:name":"Nadeyevo",
    "gn:population":0,
    "gn:timezone":"Europe/Moscow",
    "iso:country":"RU",
    "name:rus_x_preferred":[
        "\u041d\u0430\u0434\u0435\u0435\u0432\u043e"
    ],
    "wof:name":"Nadeyevo",
    "wof:placetype":"locality"
},
  "geometry": {"coordinates":[40.43395,59.44494],"type":"Point"}
}