{
  "type": "Feature",
  "properties": {
    "gn:admin1_code":"13",
    "gn:asciiname":"Novyy Ural",
    "gn:country_code":"RU",
    "gn:dem":279,
    "gn:feature_class":"P",
    "gn:feature_code":"PPL",
    "gn:name":"Novyy Ural",
    "gn:population":0,
    "gn:timezone":"Asia/Yekaterinburg",
    "iso:country":"RU",
    "name:eng_x_preferred":[
        "Novyy Ural"
    ],
    "name:nor_x_preferred":[
        "Novyj Ural"
    ],
    "name:rus_x_preferred":[
        "\u041d\u043e\u0432\u044b\u0439 \u0423\u0440\u0430\u043b"
    ],
    "wof:name":"Novyy Ural",
    "wof:placetype":"locality"
},
  "geometry": {"coordinates":[60.76409,53.41174],"type":"Point"}
}