{
  "type": "Feature",
  "properties": {
    "gn:admin1_code":"33",
    "gn:asciiname":"Bol'shaya Dubrova",
    "gn:country_code":"RU",
    "gn:dem":147,
    "gn:feature_class":"P",
    "gn:feature_code":"PPL",
    "gn:name":"Bol\u2019shaya Dubrova",
    "gn:population":0,
    "gn:timezone":"Europe/Kirov",
    "iso:country":"RU",
    "name:rus_x_preferred":[
        "\u0411\u043e\u043b\u044c\u0448\u0430\u044f \u0414\u0443\u0431\u0440\u043e\u0432\u0430"
    ],
    "name:und_x_variant":[
        "Bol\u2019shaya Dubrova"
    ],
    "wof:name":"Bol'shaya Dubrova",
    "wof:placetype":"locality"
},
  "geometry": {"coordinates":[50.2493,57.6308],"type":"Point"}
}