{
  "type": "Feature",
  "properties": {
    "gn:admin1_code":"45",
    "gn:asciiname":"Koponanger",
    "gn:country_code":"RU",
    "gn:dem":118,
    "gn:feature_class":"P",
    "gn:feature_code":"PPL",
    "gn:name":"Koponanger",
    "gn:population":0,
    "gn:timezone":"Europe/Moscow",
    "iso:country":"RU",
    "name:rus_x_preferred":[
        "\u041a\u043e\u043f\u043e\u043d\u0430\u043d\u0433\u0435\u0440"
    ],
    "name:und_x_variant":[
        "\u041a\u043e\u043f\u043e\u043d\u0430\u043d\u0433\u0435\u0440"
    ],
    "wof:name":"Koponanger",
    "wof:placetype":"locality"
},
  "geometry": {"coordinates":[46.5966,56.2449],"type":"Point"}
}