{
  "type": "Feature",
  "properties": {
    "gn:admin1_code":"7",
    "gn:asciiname":"Kapitanskiye",
    "gn:country_code":"RU",
    "gn:dem":-23,
    "gn:feature_class":"P",
    "gn:feature_code":"PPL",
    "gn:name":"Kapitanskiye",
    "gn:population":0,
    "gn:timezone":"Europe/Astrakhan",
    "iso:country":"RU",
    "name:rus_x_preferred":[
        "\u041a\u0430\u043f\u0438\u0442\u0430\u043d\u0441\u043a\u0438\u0435"
    ],
    "name:und_x_variant":[
        "\u041a\u0430\u043f\u0438\u0442\u0430\u043d\u0441\u043a\u0438\u0435"
    ],
    "wof:name":"Kapitanskiye",
    "wof:placetype":"locality"
},
  "geometry": {"coordinates":[47.24528,47.17],"type":"Point"}
}