{
  "type": "Feature",
  "properties": {
    "gn:admin1_code":"90",
    "gn:asciiname":"Sordva",
    "gn:country_code":"RU",
    "gn:dem":129,
    "gn:feature_class":"P",
    "gn:feature_code":"PPL",
    "gn:name":"Sordva",
    "gn:population":0,
    "gn:timezone":"Asia/Yekaterinburg",
    "iso:country":"RU",
    "name:che_x_preferred":[
        "\u0421\u043e\u0440\u0434\u0432\u0430"
    ],
    "name:koi_x_preferred":[
        "\u0421\u043e\u0440\u0434\u0432\u0430"
    ],
    "name:rus_x_preferred":[
        "\u0421\u043e\u0440\u0434\u0432\u0430"
    ],
    "wof:name":"Sordva",
    "wof:placetype":"locality"
},
  "geometry": {"coordinates":[54.8363,59.1054],"type":"Point"}
}