{
  "type": "Feature",
  "properties": {
    "gn:admin1_code":"77",
    "gn:asciiname":"Grachnevo",
    "gn:country_code":"RU",
    "gn:dem":251,
    "gn:feature_class":"P",
    "gn:feature_code":"PPL",
    "gn:name":"Grachnevo",
    "gn:population":0,
    "gn:timezone":"Europe/Moscow",
    "iso:country":"RU",
    "name:rus_x_preferred":[
        "\u0413\u0440\u0430\u0447\u043d\u0435\u0432\u043e"
    ],
    "wof:name":"Grachnevo",
    "wof:placetype":"locality"
},
  "geometry": {"coordinates":[31.88333,56.56667],"type":"Point"}
}