{
  "type": "Feature",
  "properties": {
    "gn:admin1_code":"57",
    "gn:asciiname":"Rebrovka",
    "gn:country_code":"RU",
    "gn:dem":238,
    "gn:feature_class":"P",
    "gn:feature_code":"PPL",
    "gn:name":"Rebrovka",
    "gn:population":0,
    "gn:timezone":"Europe/Moscow",
    "iso:country":"RU",
    "name:rus_x_preferred":[
        "\u0420\u0435\u0431\u0440\u043e\u0432\u043a\u0430"
    ],
    "wof:name":"Rebrovka",
    "wof:placetype":"locality"
},
  "geometry": {"coordinates":[45.97802,53.63962],"type":"Point"}
}