{
  "type": "Feature",
  "properties": {
    "gn:admin1_code":"43",
    "gn:asciiname":"Solovoye",
    "gn:country_code":"RU",
    "gn:dem":142,
    "gn:feature_class":"P",
    "gn:feature_code":"PPL",
    "gn:name":"Solovoye",
    "gn:population":0,
    "gn:timezone":"Europe/Moscow",
    "iso:country":"RU",
    "name:eng_x_preferred":[
        "Solovyye"
    ],
    "name:nor_x_preferred":[
        "Solovoje"
    ],
    "name:rus_x_preferred":[
        "\u0421\u043e\u043b\u043e\u0432\u043e\u0435"
    ],
    "name:und_x_variant":[
        "Salovyye",
        "Solovoye"
    ],
    "wof:name":"Solovoye",
    "wof:placetype":"locality"
},
  "geometry": {"coordinates":[40.0929,53.3585],"type":"Point"}
}