{
  "type": "Feature",
  "properties": {
    "gn:admin1_code":"63",
    "gn:asciiname":"Kerdyugen",
    "gn:country_code":"RU",
    "gn:dem":153,
    "gn:feature_class":"P",
    "gn:feature_code":"PPL",
    "gn:name":"K\u00ebrdyugen",
    "gn:population":0,
    "gn:timezone":"Asia/Yakutsk",
    "iso:country":"RU",
    "name:rus_x_preferred":[
        "\u041a\u0451\u0440\u0434\u044e\u0433\u0435\u043d"
    ],
    "name:sah_x_preferred":[
        "\u041a\u04e9\u0440\u0434\u04af\u0433\u044d\u043d"
    ],
    "name:und_x_variant":[
        "K\u00ebrdyugen"
    ],
    "wof:name":"Kerdyugen",
    "wof:placetype":"locality"
},
  "geometry": {"coordinates":[131.01667,61.73333],"type":"Point"}
}