{
  "type": "Feature",
  "properties": {
    "gn:admin1_code":"69",
    "gn:asciiname":"Lomy",
    "gn:country_code":"RU",
    "gn:dem":234,
    "gn:feature_class":"P",
    "gn:feature_code":"PPL",
    "gn:name":"Lomy",
    "gn:population":0,
    "gn:timezone":"Europe/Moscow",
    "iso:country":"RU",
    "name:rus_x_preferred":[
        "\u041b\u043e\u043c\u044b"
    ],
    "name:und_x_variant":[
        "\u041b\u043e\u043c\u044b"
    ],
    "wof:name":"Lomy",
    "wof:placetype":"locality"
},
  "geometry": {"coordinates":[34.89978,55.24416],"type":"Point"}
}