{
  "type": "Feature",
  "properties": {
    "gn:admin1_code":"20",
    "gn:asciiname":"Verkhnyaya Kuyta",
    "gn:country_code":"RU",
    "gn:dem":452,
    "gn:feature_class":"P",
    "gn:feature_code":"PPL",
    "gn:name":"Verkhnyaya Kuyta",
    "gn:population":0,
    "gn:timezone":"Asia/Irkutsk",
    "iso:country":"RU",
    "wof:name":"Verkhnyaya Kuyta",
    "wof:placetype":"locality"
},
  "geometry": {"coordinates":[102.45,53.825],"type":"Point"}
}