{
  "type": "Feature",
  "properties": {
    "gn:admin1_code":"88.0",
    "gn:asciiname":"Ivanchino",
    "gn:country_code":"RU",
    "gn:dem":181,
    "gn:feature_class":"P",
    "gn:feature_code":"PPL",
    "gn:name":"Ivanchino",
    "gn:population":0,
    "gn:timezone":"Europe/Moscow",
    "iso:country":"RU",
    "name:rus_x_preferred":[
        "\u0418\u0432\u0430\u043d\u0447\u0438\u043d\u043e"
    ],
    "name:und_x_variant":[
        "\u0418\u0432\u0430\u043d\u0447\u0438\u043d\u043e"
    ],
    "wof:name":"Ivanchino",
    "wof:placetype":"locality"
},
  "geometry": {"coordinates":[40.26291,58.52944],"type":"Point"}
}