{
  "type": "Feature",
  "properties": {
    "gn:admin1_code":"75",
    "gn:asciiname":"Kuchukovo",
    "gn:cc2":"RU",
    "gn:country_code":"RU",
    "gn:dem":115,
    "gn:feature_class":"P",
    "gn:feature_code":"PPL",
    "gn:name":"Kuchukovo",
    "gn:population":0,
    "gn:timezone":"Asia/Tomsk",
    "iso:country":"RU",
    "name:eng_x_preferred":[
        "Kuchukovo"
    ],
    "name:nor_x_preferred":[
        "Kutsjukovo"
    ],
    "name:rus_x_preferred":[
        "\u041a\u0443\u0447\u0443\u043a\u043e\u0432\u043e"
    ],
    "name:und_x_variant":[
        "Kuchukova"
    ],
    "wof:name":"Kuchukovo",
    "wof:placetype":"locality"
},
  "geometry": {"coordinates":[87.02916999999999,56.96889],"type":"Point"}
}