{
  "type": "Feature",
  "properties": {
    "gn:admin1_code":"61",
    "gn:asciiname":"Sumskoy",
    "gn:country_code":"RU",
    "gn:dem":96,
    "gn:feature_class":"P",
    "gn:feature_code":"PPL",
    "gn:name":"Sumskoy",
    "gn:population":0,
    "gn:timezone":"Europe/Moscow",
    "iso:country":"RU",
    "name:rus_x_preferred":[
        "\u0421\u0443\u043c\u0441\u043a\u043e\u0439"
    ],
    "name:und_x_variant":[
        "\u0421\u0443\u043c\u0441\u043a\u043e\u0439"
    ],
    "wof:name":"Sumskoy",
    "wof:placetype":"locality"
},
  "geometry": {"coordinates":[40.78194000000001,46.66806],"type":"Point"}
}