{
  "type": "Feature",
  "properties": {
    "gn:admin1_code":"17",
    "gn:asciiname":"Mutnyy Artezian",
    "gn:country_code":"RU",
    "gn:dem":-2,
    "gn:feature_class":"P",
    "gn:feature_code":"PPL",
    "gn:name":"Mutnyy Artezian",
    "gn:population":0,
    "gn:timezone":"Europe/Moscow",
    "iso:country":"RU",
    "name:rus_x_preferred":[
        "\u041c\u0443\u0442\u043d\u044b\u0439 \u0410\u0440\u0442\u0435\u0437\u0438\u0430\u043d"
    ],
    "wof:name":"Mutnyy Artezian",
    "wof:placetype":"locality"
},
  "geometry": {"coordinates":[45.92778,44.51861],"type":"Point"}
}