{
  "type": "Feature",
  "properties": {
    "gn:country":"RU",
    "gn:fcode":"PPL",
    "gn:population":0,
    "iso:country":"RU",
    "name:che_x_preferred":[
        "Gil\u2019na"
    ],
    "name:che_x_variant":[
        "\u0423\u0440\u0438\u0431"
    ],
    "name:rus_x_preferred":[
        "\u0413\u0438\u043b\u044f\u043d\u044b"
    ],
    "name:rus_x_variant":[
        "\u0413\u0438\u043b\u044c\u043d\u0430"
    ],
    "name:und_x_variant":[
        "Urib"
    ],
    "qs:name":"Gilyanj",
    "qs:name_adm0":"Russia",
    "qs:name_adm1":"Chechnya Republic",
    "qs:photos_9r":0,
    "qs:photos_sr":0,
    "qs:placetype":"Town",
    "qs:pop_sr":"0",
    "wof:name":"Gilyanj",
    "wof:placetype":"locality",
    "wof:population":0
},
  "geometry": {"coordinates":[46.48503,43.07215],"type":"Point"}
}