{
  "type": "Feature",
  "properties": {
    "gn:admin1_code":"16",
    "gn:asciiname":"Yashkil'dino",
    "gn:country_code":"RU",
    "gn:dem":121,
    "gn:feature_class":"P",
    "gn:feature_code":"PPL",
    "gn:name":"Yashkil\u2019dino",
    "gn:population":0,
    "gn:timezone":"Europe/Moscow",
    "iso:country":"RU",
    "name:rus_x_preferred":[
        "\u042f\u0448\u043a\u0438\u043b\u044c\u0434\u0438\u043d\u043e"
    ],
    "name:und_x_variant":[
        "Yashkil\u2019dino"
    ],
    "wof:name":"Yashkil'dino",
    "wof:placetype":"locality"
},
  "geometry": {"coordinates":[47.12389,55.79528000000001],"type":"Point"}
}