{
  "type": "Feature",
  "properties": {
    "gn:admin1_code":"77",
    "gn:asciiname":"Gluntsovo",
    "gn:country_code":"RU",
    "gn:dem":160,
    "gn:feature_class":"P",
    "gn:feature_code":"PPL",
    "gn:name":"Gluntsovo",
    "gn:population":0,
    "gn:timezone":"Europe/Moscow",
    "iso:country":"RU",
    "name:rus_x_preferred":[
        "\u0413\u043b\u0443\u043d\u0446\u043e\u0432\u043e"
    ],
    "name:und_x_variant":[
        "\u0413\u043b\u0443\u043d\u0446\u043e\u0432\u043e"
    ],
    "wof:name":"Gluntsovo",
    "wof:placetype":"locality"
},
  "geometry": {"coordinates":[37.1347,58.0526],"type":"Point"}
}