{
  "type": "Feature",
  "properties": {
    "gn:admin1_code":"45.0",
    "gn:asciiname":"Gornyak",
    "gn:country_code":"RU",
    "gn:dem":240,
    "gn:feature_class":"P",
    "gn:feature_code":"PPL",
    "gn:name":"Gornyak",
    "gn:population":0,
    "gn:timezone":"Europe/Moscow",
    "iso:country":"RU",
    "name:bel_x_preferred":[
        "\u0413\u0430\u0440\u043d\u044f\u043a"
    ],
    "name:ben_x_preferred":[
        "\u0997\u09cb\u09b0\u09a8\u09be\u09df\u0995"
    ],
    "name:ceb_x_preferred":[
        "Gornyak"
    ],
    "name:deu_x_preferred":[
        "Gornjak"
    ],
    "name:ell_x_preferred":[
        "\u0393\u03ba\u03cc\u03c1\u03bd\u03b9\u03b1\u03ba"
    ],
    "name:heb_x_preferred":[
        "\u05d2\u05d5\u05e8\u05e0\u05d9\u05d0\u05e7"
    ],
    "name:hin_x_preferred":[
        "\u0917\u094b\u0930\u094d\u0928\u094d\u092f\u093e\u0915"
    ],
    "name:ind_x_preferred":[
        "Gornyak"
    ],
    "name:jpn_x_preferred":[
        "\u30b4\u30eb\u30cb\u30e3\u30af"
    ],
    "name:kor_x_preferred":[
        "\uac00\ub974\ub0d0\ud06c"
    ],
    "name:lav_x_preferred":[
        "Gor\u0146aka"
    ],
    "name:por_x_preferred":[
        "Gornyak"
    ],
    "name:rus_x_preferred":[
        "\u0413\u043e\u0440\u043d\u044f\u043a"
    ],
    "name:srp_x_preferred":[
        "\u0413\u043e\u0440\u045a\u0430\u043a"
    ],
    "name:ukr_x_preferred":[
        "\u0413\u043e\u0440\u043d\u044f\u043a"
    ],
    "name:urd_x_preferred":[
        "\u06af\u0648\u0631\u0646\u0627\u06cc\u06a9"
    ],
    "name:vie_x_preferred":[
        "Gornyak"
    ],
    "wof:name":"Gornyak",
    "wof:placetype":"locality"
},
  "geometry": {"coordinates":[49.05444,56.86056],"type":"Point"}
}