{
  "type": "Feature",
  "properties": {
    "gn:admin1_code":"45.0",
    "gn:asciiname":"Gornyak",
    "gn:country_code":"RU",
    "gn:dem":240,
    "gn:feature_class":"P",
    "gn:feature_code":"PPL",
    "gn:name":"Gornyak",
    "gn:population":0,
    "gn:timezone":"Europe/Moscow",
    "iso:country":"RU",
    "name:bel_x_preferred":[
        "\u0413\u0430\u0440\u043d\u044f\u043a"
    ],
    "name:ceb_x_preferred":[
        "Gornyak"
    ],
    "name:deu_x_preferred":[
        "Gornjak"
    ],
    "name:lav_x_preferred":[
        "Gor\u0146aka"
    ],
    "name:rus_x_preferred":[
        "\u0413\u043e\u0440\u043d\u044f\u043a"
    ],
    "name:srp_x_preferred":[
        "\u0413\u043e\u0440\u045a\u0430\u043a"
    ],
    "name:ukr_x_preferred":[
        "\u0413\u043e\u0440\u043d\u044f\u043a"
    ],
    "wof:name":"Gornyak",
    "wof:placetype":"locality"
},
  "geometry": {"coordinates":[49.05444,56.86056],"type":"Point"}
}