{
  "type": "Feature",
  "properties": {
    "gn:admin1_code":"42",
    "gn:asciiname":"Solovyovo",
    "gn:country_code":"RU",
    "gn:dem":1,
    "gn:feature_class":"P",
    "gn:feature_code":"PPL",
    "gn:name":"Solovyovo",
    "gn:population":0,
    "gn:timezone":"Europe/Moscow",
    "iso:country":"RU",
    "name:che_x_preferred":[
        "\u0421\u043e\u043b\u043e\u0432\u044c\u0435\u0432\u043e"
    ],
    "name:dan_x_preferred":[
        "Solovjovo"
    ],
    "name:fin_x_historical":[
        "Taipale"
    ],
    "name:fin_x_preferred":[
        "Taipale"
    ],
    "name:fra_x_preferred":[
        "Soloviovo"
    ],
    "name:rus_x_historical":[
        "\u0422\u0430\u0439\u043f\u0430\u043b\u0435"
    ],
    "name:rus_x_preferred":[
        "\u0421\u043e\u043b\u043e\u0432\u044c\u0451\u0432\u043e"
    ],
    "name:rus_x_variant":[
        "\u0422\u0430\u0439\u043f\u0430\u043b\u0435",
        "\u0421\u043e\u043b\u043e\u0432\u044c\u0435\u0432\u043e"
    ],
    "name:swe_x_preferred":[
        "Taipale"
    ],
    "wof:name":"Solovyovo",
    "wof:placetype":"locality"
},
  "geometry": {"coordinates":[30.51178,60.62741],"type":"Point"}
}