{
  "type": "Feature",
  "properties": {
    "gn:admin1_code":"11",
    "gn:asciiname":"Lenzoloto",
    "gn:country_code":"RU",
    "gn:dem":879,
    "gn:feature_class":"P",
    "gn:feature_code":"PPL",
    "gn:name":"Lenzoloto",
    "gn:population":0,
    "gn:timezone":"Asia/Irkutsk",
    "iso:country":"RU",
    "name:rus_x_preferred":[
        "\u041b\u0435\u043d\u0437\u043e\u043b\u043e\u0442\u043e"
    ],
    "wof:name":"Lenzoloto",
    "wof:placetype":"locality"
},
  "geometry": {"coordinates":[112.7949,53.20944],"type":"Point"}
}