{
  "type": "Feature",
  "properties": {
    "gn:admin1_code":"63",
    "gn:asciiname":"Khomustakh",
    "gn:country_code":"RU",
    "gn:dem":161,
    "gn:feature_class":"P",
    "gn:feature_code":"PPL",
    "gn:name":"Khomustakh",
    "gn:population":0,
    "gn:timezone":"Asia/Yakutsk",
    "iso:country":"RU",
    "name:rus_x_preferred":[
        "\u0425\u043e\u043c\u0443\u0441\u0442\u0430\u0445"
    ],
    "name:und_x_variant":[
        "Zimov\u2019ye Nakhu Komustakh",
        "Khomustakh",
        "\u0425\u043e\u043c\u0443\u0441\u0442\u0430\u0445"
    ],
    "wof:name":"Khomustakh",
    "wof:placetype":"locality"
},
  "geometry": {"coordinates":[134.93244999999999,61.94351999999999],"type":"Point"}
}