{
  "type": "Feature",
  "properties": {
    "gn:admin1_code":"5",
    "gn:asciiname":"Verkhnyaya Bereya",
    "gn:country_code":"RU",
    "gn:dem":289,
    "gn:feature_class":"P",
    "gn:feature_code":"PPL",
    "gn:name":"Verkhnyaya Bereya",
    "gn:population":0,
    "gn:timezone":"Asia/Yakutsk",
    "iso:country":"RU",
    "wof:name":"Verkhnyaya Bereya",
    "wof:placetype":"locality"
},
  "geometry": {"coordinates":[127.33333,52.15],"type":"Point"}
}