{
  "type": "Feature",
  "properties": {
    "gn:admin1_code":"63",
    "gn:asciiname":"Pokhodsk",
    "gn:country_code":"RU",
    "gn:dem":11,
    "gn:feature_class":"P",
    "gn:feature_code":"PPL",
    "gn:name":"Pokhodsk",
    "gn:population":0,
    "gn:timezone":"Asia/Magadan",
    "iso:country":"RU",
    "name:che_x_preferred":[
        "\u041f\u043e\u0445\u043e\u0434\u0441\u043a"
    ],
    "name:eng_x_preferred":[
        "Pokhodsk"
    ],
    "name:lit_x_preferred":[
        "Pochodskas"
    ],
    "name:nld_x_preferred":[
        "Pochodsk"
    ],
    "name:nor_x_preferred":[
        "Pokhodsk"
    ],
    "name:rus_x_preferred":[
        "\u041f\u043e\u0445\u043e\u0434\u0441\u043a"
    ],
    "name:und_x_variant":[
        "Pokhodskaya",
        "Pokhodskoye"
    ],
    "wof:name":"Pokhodsk",
    "wof:placetype":"locality"
},
  "geometry": {"coordinates":[160.96267,69.08001999999999],"type":"Point"}
}