{
  "type": "Feature",
  "properties": {
    "gn:admin1_code":"84.0",
    "gn:asciiname":"Chekunov",
    "gn:cc2":"RU",
    "gn:country_code":"RU",
    "gn:dem":111,
    "gn:feature_class":"P",
    "gn:feature_code":"PPL",
    "gn:name":"Chekunov",
    "gn:population":0,
    "gn:timezone":"Europe/Volgograd",
    "iso:country":"RU",
    "name:rus_x_preferred":[
        "\u0427\u0435\u043a\u0443\u043d\u043e\u0432"
    ],
    "name:und_x_variant":[
        "Chekunovskiy",
        "Chekunov",
        "\u0427\u0435\u043a\u0443\u043d\u043e\u0432"
    ],
    "wof:name":"Chekunov",
    "wof:placetype":"locality"
},
  "geometry": {"coordinates":[42.58333,50.36667],"type":"Point"}
}