{
  "type": "Feature",
  "properties": {
    "gn:country":"RU",
    "gn:fcode":"PPL",
    "gn:pop":3240,
    "iso:country":"RU",
    "name:eng_x_preferred":[
        "Chunoyar"
    ],
    "name:nor_x_preferred":[
        "Tsjunojar"
    ],
    "name:rus_x_preferred":[
        "\u0427\u0443\u043d\u043e\u044f\u0440"
    ],
    "qs:name":"Chunoyar",
    "qs:photos_9r":0,
    "qs:photos_sr":0,
    "qs:pop_sr":"4",
    "wof:name":"Chunoyar",
    "wof:placetype":"locality",
    "wof:population":3240
},
  "geometry": {"coordinates":[97.32859999999999,57.4483],"type":"Point"}
}