{
  "type": "Feature",
  "properties": {
    "gn:admin1_code":"8",
    "gn:asciiname":"Kozhevnya",
    "gn:country_code":"RU",
    "gn:dem":511,
    "gn:feature_class":"P",
    "gn:feature_code":"PPL",
    "gn:name":"Kozhevnya",
    "gn:population":0,
    "gn:timezone":"Asia/Yekaterinburg",
    "iso:country":"RU",
    "name:rus_x_preferred":[
        "\u041a\u043e\u0436\u0435\u0432\u043d\u044f"
    ],
    "name:und_x_variant":[
        "\u041a\u043e\u0436\u0435\u0432\u043d\u044f"
    ],
    "wof:name":"Kozhevnya",
    "wof:placetype":"locality"
},
  "geometry": {"coordinates":[57.81667,53.68333000000001],"type":"Point"}
}