{
  "type": "Feature",
  "properties": {
    "gn:admin1_code":"05",
    "gn:asciiname":"Kulikovka",
    "gn:country_code":"RU",
    "gn:dem":120,
    "gn:feature_class":"P",
    "gn:feature_code":"PPL",
    "gn:name":"Kulikovka",
    "gn:population":0,
    "gn:timezone":"Asia/Yakutsk",
    "iso:country":"RU",
    "name:eng_x_preferred":[
        "Kulikovka"
    ],
    "name:nor_x_preferred":[
        "Kulikovka"
    ],
    "name:rus_x_preferred":[
        "\u041a\u0443\u043b\u0438\u043a\u043e\u0432\u043a\u0430"
    ],
    "wof:name":"Kulikovka",
    "wof:placetype":"locality"
},
  "geometry": {"coordinates":[130.05722,49.86536],"type":"Point"}
}