{
  "type": "Feature",
  "properties": {
    "gn:admin1_code":"40.0",
    "gn:asciiname":"Mogileva",
    "gn:country_code":"RU",
    "gn:dem":72,
    "gn:feature_class":"P",
    "gn:feature_code":"PPL",
    "gn:name":"Mogil\u00ebva",
    "gn:population":0,
    "gn:timezone":"Asia/Yekaterinburg",
    "iso:country":"RU",
    "name:rus_x_preferred":[
        "\u041c\u043e\u0433\u0438\u043b\u0451\u0432\u0430"
    ],
    "name:und_x_variant":[
        "Mogil\u00ebva"
    ],
    "wof:name":"Mogileva",
    "wof:placetype":"locality"
},
  "geometry": {"coordinates":[64.3853,56.0966],"type":"Point"}
}