{
  "type": "Feature",
  "properties": {
    "gn:country":"RU",
    "gn:fcode":"PPLX",
    "gn:population":0,
    "iso:country":"RU",
    "name:ceb_x_preferred":[
        "Mitino"
    ],
    "name:deu_x_preferred":[
        "Mitino"
    ],
    "name:eng_x_preferred":[
        "Mitino District"
    ],
    "name:hye_x_preferred":[
        "\u0544\u056b\u057f\u056b\u0576\u0578"
    ],
    "name:ita_x_preferred":[
        "Mitino"
    ],
    "name:rus_x_preferred":[
        "\u041c\u0438\u0442\u0438\u043d\u043e"
    ],
    "name:sco_x_preferred":[
        "Mitino Destrict"
    ],
    "name:swe_x_preferred":[
        "Mitino"
    ],
    "name:ukr_x_preferred":[
        "\u041c\u0438\u0442\u0456\u043d\u043e"
    ],
    "qs:name":"Mitino",
    "qs:name_adm0":"Russia",
    "qs:name_adm1":"Moscow Federal City",
    "qs:photos":21,
    "qs:photos_1k":4,
    "qs:photos_9k":1,
    "qs:photos_9r":1,
    "qs:photos_all":21,
    "qs:photos_sr":1,
    "qs:placetype":"Suburb",
    "qs:pop_sr":"0",
    "wd:wordcount":9,
    "wof:name":"Mitino",
    "wof:placetype":"neighbourhood",
    "wof:population":0
},
  "geometry": {"coordinates":[37.33821,55.84769],"type":"Point"}
}