{
  "type": "Feature",
  "properties": {
    "gn:admin1_code":"77",
    "gn:asciiname":"Malaya Kamenka",
    "gn:country_code":"RU",
    "gn:dem":206,
    "gn:feature_class":"P",
    "gn:feature_code":"PPL",
    "gn:name":"Malaya Kamenka",
    "gn:population":0,
    "gn:timezone":"Europe/Moscow",
    "iso:country":"RU",
    "name:rus_x_preferred":[
        "\u041c\u0430\u043b\u0430\u044f \u041a\u0430\u043c\u0435\u043d\u043a\u0430"
    ],
    "wof:name":"Malaya Kamenka",
    "wof:placetype":"locality"
},
  "geometry": {"coordinates":[32.71667,56.25],"type":"Point"}
}