{
  "type": "Feature",
  "properties": {
    "gn:admin1_code":"55.0",
    "gn:asciiname":"Ashche-Say",
    "gn:country_code":"RU",
    "gn:dem":207,
    "gn:feature_class":"P",
    "gn:feature_code":"PPL",
    "gn:name":"Ashche-Say",
    "gn:population":0,
    "gn:timezone":"Asia/Yekaterinburg",
    "iso:country":"RU",
    "name:nor_x_preferred":[
        "Asjtsje-Saj"
    ],
    "name:rus_x_preferred":[
        "\u0410\u0449\u0435-\u0421\u0430\u0439"
    ],
    "wof:name":"Ashche-Say",
    "wof:placetype":"locality"
},
  "geometry": {"coordinates":[55.59186,50.65118],"type":"Point"}
}