{
  "type": "Feature",
  "properties": {
    "gn:admin1_code":"23",
    "gn:asciiname":"Bogatovo",
    "gn:country_code":"RU",
    "gn:dem":2,
    "gn:feature_class":"P",
    "gn:feature_code":"PPL",
    "gn:name":"Bogatovo",
    "gn:population":0,
    "gn:timezone":"Europe/Kaliningrad",
    "iso:country":"RU",
    "name:rus_x_preferred":[
        "\u0411\u043e\u0433\u0430\u0442\u043e\u0432\u043e"
    ],
    "name:und_x_variant":[
        "\u0411\u043e\u0433\u0430\u0442\u043e\u0432\u043e"
    ],
    "wof:name":"Bogatovo",
    "wof:placetype":"locality"
},
  "geometry": {"coordinates":[21.35666,54.85236],"type":"Point"}
}