{
  "type": "Feature",
  "properties": {
    "gn:admin1_code":"16.0",
    "gn:asciiname":"Buguyan",
    "gn:country_code":"RU",
    "gn:dem":145,
    "gn:feature_class":"P",
    "gn:feature_code":"PPL",
    "gn:name":"Buguyan",
    "gn:population":0,
    "gn:timezone":"Europe/Moscow",
    "iso:country":"RU",
    "name:eng_x_preferred":[
        "Buguyan"
    ],
    "name:nor_x_preferred":[
        "Bugujan"
    ],
    "name:rus_x_preferred":[
        "\u0411\u0443\u0433\u0443\u044f\u043d"
    ],
    "wof:name":"Buguyan",
    "wof:placetype":"locality"
},
  "geometry": {"coordinates":[46.79533,55.3238],"type":"Point"}
}