{
  "type": "Feature",
  "properties": {
    "gn:admin1_code":"28",
    "gn:asciiname":"Meliorativnyy",
    "gn:country_code":"RU",
    "gn:dem":37,
    "gn:feature_class":"P",
    "gn:feature_code":"PPL",
    "gn:name":"Meliorativnyy",
    "gn:population":0,
    "gn:timezone":"Europe/Moscow",
    "iso:country":"RU",
    "name:olo_x_preferred":[
        "Meliorativnoi"
    ],
    "name:rus_x_preferred":[
        "\u041c\u0435\u043b\u0438\u043e\u0440\u0430\u0442\u0438\u0432\u043d\u044b\u0439"
    ],
    "wof:name":"Meliorativnyy",
    "wof:placetype":"locality"
},
  "geometry": {"coordinates":[34.25,61.85],"type":"Point"}
}