{
  "type": "Feature",
  "properties": {
    "gn:admin1_code":"73.0",
    "gn:asciiname":"Bima",
    "gn:country_code":"RU",
    "gn:dem":66,
    "gn:feature_class":"P",
    "gn:feature_code":"PPL",
    "gn:name":"Bima",
    "gn:population":0,
    "gn:timezone":"Europe/Moscow",
    "iso:country":"RU",
    "name:rus_x_preferred":[
        "\u0411\u0438\u043c\u0430"
    ],
    "name:und_x_variant":[
        "Vol\u2019naya Bima",
        "Bima"
    ],
    "wof:name":"Bima",
    "wof:placetype":"locality"
},
  "geometry": {"coordinates":[49.49778,55.61753],"type":"Point"}
}