{
  "type": "Feature",
  "properties": {
    "gn:admin1_code":"4",
    "gn:asciiname":"Simonovo",
    "gn:country_code":"RU",
    "gn:dem":190,
    "gn:feature_class":"P",
    "gn:feature_code":"PPL",
    "gn:name":"Simonovo",
    "gn:population":0,
    "gn:timezone":"Asia/Barnaul",
    "iso:country":"RU",
    "name:eng_x_preferred":[
        "Simonovo"
    ],
    "name:nor_x_preferred":[
        "Simonovo"
    ],
    "name:rus_x_preferred":[
        "\u0421\u0438\u043c\u043e\u043d\u043e\u0432\u043e"
    ],
    "name:und_x_variant":[
        "Simonovskiy"
    ],
    "wof:name":"Simonovo",
    "wof:placetype":"locality"
},
  "geometry": {"coordinates":[80.3801,51.6863],"type":"Point"}
}