{
  "type": "Feature",
  "properties": {
    "gn:admin1_code":"42.0",
    "gn:asciiname":"Ryabizi",
    "gn:country_code":"RU",
    "gn:dem":118,
    "gn:feature_class":"P",
    "gn:feature_code":"PPL",
    "gn:name":"Ryabizi",
    "gn:population":0,
    "gn:timezone":"Europe/Moscow",
    "iso:country":"RU",
    "name:fin_x_preferred":[
        "R\u00e4\u00e4pisi"
    ],
    "wof:name":"Ryabizi",
    "wof:placetype":"locality"
},
  "geometry": {"coordinates":[29.97749,59.49568000000001],"type":"Point"}
}