{
  "type": "Feature",
  "properties": {
    "gn:admin1_code":"71",
    "gn:asciiname":"Shompa",
    "gn:country_code":"RU",
    "gn:dem":311,
    "gn:feature_class":"P",
    "gn:feature_code":"PPL",
    "gn:name":"Shompa",
    "gn:population":0,
    "gn:timezone":"Asia/Yekaterinburg",
    "iso:country":"RU",
    "name:eng_x_preferred":[
        "Shompa"
    ],
    "name:nor_x_preferred":[
        "Sjompa"
    ],
    "name:rus_x_preferred":[
        "\u0428\u043e\u043c\u043f\u0430"
    ],
    "wof:name":"Shompa",
    "wof:placetype":"locality"
},
  "geometry": {"coordinates":[59.4868,59.9956],"type":"Point"}
}