{
  "type": "Feature",
  "properties": {
    "gn:admin1_code":"80",
    "gn:asciiname":"Pazyal",
    "gn:country_code":"RU",
    "gn:dem":117,
    "gn:feature_class":"P",
    "gn:feature_code":"PPL",
    "gn:name":"Pazyal",
    "gn:population":0,
    "gn:timezone":"Europe/Samara",
    "iso:country":"RU",
    "name:eng_x_preferred":[
        "Pazyal"
    ],
    "name:nor_x_preferred":[
        "Pazal"
    ],
    "name:rus_x_preferred":[
        "\u041f\u0430\u0437\u0430\u043b"
    ],
    "name:rus_x_variant":[
        "\u041f\u0430\u0437\u044f\u043b"
    ],
    "wof:name":"Pazyal",
    "wof:placetype":"locality"
},
  "geometry": {"coordinates":[52.1806,56.62605],"type":"Point"}
}