{
  "type": "Feature",
  "properties": {
    "gn:admin1_code":"6.0",
    "gn:asciiname":"Avangard",
    "gn:country_code":"RU",
    "gn:dem":47,
    "gn:feature_class":"P",
    "gn:feature_code":"PPL",
    "gn:name":"Avangard",
    "gn:population":0,
    "gn:timezone":"Europe/Moscow",
    "iso:country":"RU",
    "name:eng_x_preferred":[
        "Avangard"
    ],
    "name:nor_x_preferred":[
        "Avangard"
    ],
    "name:rus_x_preferred":[
        "\u0410\u0432\u0430\u043d\u0433\u0430\u0440\u0434"
    ],
    "name:und_x_variant":[
        "\u0410\u0432\u0430\u043d\u0433\u0430\u0440\u0434",
        "Avangard"
    ],
    "wof:name":"Avangard",
    "wof:placetype":"locality"
},
  "geometry": {"coordinates":[40.64,63.76600000000001],"type":"Point"}
}