{
  "type": "Feature",
  "properties": {
    "gn:admin1_code":"43",
    "gn:asciiname":"Sibil'da",
    "gn:country_code":"RU",
    "gn:dem":206,
    "gn:feature_class":"P",
    "gn:feature_code":"PPL",
    "gn:name":"Sibil\u2019da",
    "gn:population":0,
    "gn:timezone":"Europe/Moscow",
    "iso:country":"RU",
    "name:rus_x_preferred":[
        "\u0421\u0438\u0431\u0438\u043b\u044c\u0434\u0430"
    ],
    "name:und_x_variant":[
        "Sibil\u2019da"
    ],
    "wof:name":"Sibil'da",
    "wof:placetype":"locality"
},
  "geometry": {"coordinates":[38.9527,53.0698],"type":"Point"}
}