{
  "type": "Feature",
  "properties": {
    "gn:admin1_code":"76",
    "gn:asciiname":"Simakovo",
    "gn:country_code":"RU",
    "gn:dem":221,
    "gn:feature_class":"P",
    "gn:feature_code":"PPL",
    "gn:name":"Simakovo",
    "gn:population":0,
    "gn:timezone":"Europe/Moscow",
    "iso:country":"RU",
    "name:rus_x_preferred":[
        "\u0421\u0438\u043c\u0430\u043a\u043e\u0432\u043e"
    ],
    "wof:name":"Simakovo",
    "wof:placetype":"locality"
},
  "geometry": {"coordinates":[38.30234,54.18587],"type":"Point"}
}