{
  "type": "Feature",
  "properties": {
    "gn:admin1_code":"71",
    "gn:asciiname":"Zhelezyanka",
    "gn:country_code":"RU",
    "gn:dem":185,
    "gn:feature_class":"P",
    "gn:feature_code":"PPL",
    "gn:name":"Zhelezyanka",
    "gn:population":0,
    "gn:timezone":"Asia/Yekaterinburg",
    "iso:country":"RU",
    "name:rus_x_preferred":[
        "\u0416\u0435\u043b\u0435\u0437\u044f\u043d\u043a\u0430"
    ],
    "name:und_x_variant":[
        "Zhelezenka",
        "Zhelezyanka"
    ],
    "wof:name":"Zhelezyanka",
    "wof:placetype":"locality"
},
  "geometry": {"coordinates":[59.89944000000001,58.58611],"type":"Point"}
}