{
  "type": "Feature",
  "properties": {
    "gn:admin1_code":"53.0",
    "gn:asciiname":"Zimovka",
    "gn:country_code":"RU",
    "gn:dem":155,
    "gn:feature_class":"P",
    "gn:feature_code":"PPL",
    "gn:name":"Zimovka",
    "gn:population":0,
    "gn:timezone":"Asia/Novosibirsk",
    "iso:country":"RU",
    "name:rus_x_preferred":[
        "\u0417\u0438\u043c\u043e\u0432\u043a\u0430"
    ],
    "wof:name":"Zimovka",
    "wof:placetype":"locality"
},
  "geometry": {"coordinates":[81.73690000000001,55.0491],"type":"Point"}
}