{
  "type": "Feature",
  "properties": {
    "gn:admin1_code":"69",
    "gn:asciiname":"Savluki",
    "gn:country_code":"RU",
    "gn:dem":175,
    "gn:feature_class":"P",
    "gn:feature_code":"PPL",
    "gn:name":"Savluki",
    "gn:population":0,
    "gn:timezone":"Europe/Moscow",
    "iso:country":"RU",
    "name:rus_x_preferred":[
        "\u0421\u0430\u0432\u043b\u0443\u043a\u0438"
    ],
    "name:und_x_variant":[
        "\u0421\u0430\u0432\u043b\u0443\u043a\u0438"
    ],
    "wof:name":"Savluki",
    "wof:placetype":"locality"
},
  "geometry": {"coordinates":[31.38333,55.26667],"type":"Point"}
}