{
  "type": "Feature",
  "properties": {
    "gn:admin1_code":"29",
    "gn:asciiname":"Tomilovo",
    "gn:country_code":"RU",
    "gn:dem":101,
    "gn:feature_class":"P",
    "gn:feature_code":"PPL",
    "gn:name":"Tomilovo",
    "gn:population":0,
    "gn:timezone":"Asia/Novokuznetsk",
    "iso:country":"RU",
    "name:eng_x_preferred":[
        "Tomilovo"
    ],
    "name:nor_x_preferred":[
        "Tomilovo"
    ],
    "name:rus_x_preferred":[
        "\u0422\u043e\u043c\u0438\u043b\u043e\u0432\u043e"
    ],
    "name:und_x_variant":[
        "Tomilova"
    ],
    "wof:name":"Tomilovo",
    "wof:placetype":"locality"
},
  "geometry": {"coordinates":[84.88460000000001,55.9919],"type":"Point"}
}