{
  "type": "Feature",
  "properties": {
    "gn:admin1_code":"20",
    "gn:asciiname":"Mayskiy",
    "gn:country_code":"RU",
    "gn:dem":472,
    "gn:feature_class":"P",
    "gn:feature_code":"PPL",
    "gn:name":"Mayskiy",
    "gn:population":0,
    "gn:timezone":"Asia/Irkutsk",
    "iso:country":"RU",
    "name:rus_x_preferred":[
        "\u041c\u0430\u0439\u0441\u043a\u0438\u0439"
    ],
    "wof:name":"Mayskiy",
    "wof:placetype":"locality"
},
  "geometry": {"coordinates":[99.0111,54.8275],"type":"Point"}
}