{
  "type": "Feature",
  "properties": {
    "gn:admin1_code":"51.0",
    "gn:asciiname":"Aktukovo",
    "gn:country_code":"RU",
    "gn:dem":108,
    "gn:feature_class":"P",
    "gn:feature_code":"PPL",
    "gn:name":"Aktukovo",
    "gn:population":0,
    "gn:timezone":"Europe/Moscow",
    "iso:country":"RU",
    "name:nor_x_preferred":[
        "Aktukovo"
    ],
    "name:rus_x_preferred":[
        "\u0410\u043a\u0442\u0443\u043a\u043e\u0432\u043e"
    ],
    "name:und_x_variant":[
        "Aktukova",
        "Aktukovo"
    ],
    "wof:name":"Aktukovo",
    "wof:placetype":"locality"
},
  "geometry": {"coordinates":[45.63676,55.3753],"type":"Point"}
}