{
  "type": "Feature",
  "properties": {
    "gn:admin1_code":"33.0",
    "gn:asciiname":"Bychkovy",
    "gn:country_code":"RU",
    "gn:dem":135,
    "gn:feature_class":"P",
    "gn:feature_code":"PPL",
    "gn:name":"Bychkovy",
    "gn:population":0,
    "gn:timezone":"Europe/Kirov",
    "iso:country":"RU",
    "name:rus_x_preferred":[
        "\u0411\u044b\u0447\u043a\u043e\u0432\u044b"
    ],
    "name:und_x_variant":[
        "Bychkovo",
        "Bychkovy"
    ],
    "wof:name":"Bychkovy",
    "wof:placetype":"locality"
},
  "geometry": {"coordinates":[48.36478,58.38441],"type":"Point"}
}