{
  "type": "Feature",
  "properties": {
    "gn:admin1_code":"85",
    "gn:asciiname":"Vorkop'",
    "gn:country_code":"RU",
    "gn:dem":128,
    "gn:feature_class":"P",
    "gn:feature_code":"PPL",
    "gn:name":"Vorkop\u2019",
    "gn:population":0,
    "gn:timezone":"Europe/Moscow",
    "iso:country":"RU",
    "name:rus_x_preferred":[
        "\u0412\u043e\u0440\u043a\u043e\u043f\u044c"
    ],
    "name:und_x_variant":[
        "Vorkop\u2019"
    ],
    "wof:name":"Vorkop'",
    "wof:placetype":"locality"
},
  "geometry": {"coordinates":[38.4285,59.3672],"type":"Point"}
}