{
  "type": "Feature",
  "properties": {
    "gn:admin1_code":"21.0",
    "gn:asciiname":"Mikhalikha",
    "gn:country_code":"RU",
    "gn:dem":106,
    "gn:feature_class":"P",
    "gn:feature_code":"PPL",
    "gn:name":"Mikhalikha",
    "gn:population":0,
    "gn:timezone":"Europe/Moscow",
    "iso:country":"RU",
    "name:rus_x_preferred":[
        "\u041c\u0438\u0445\u0430\u043b\u0438\u0445\u0430"
    ],
    "wof:name":"Mikhalikha",
    "wof:placetype":"locality"
},
  "geometry": {"coordinates":[41.24938,56.57946],"type":"Point"}
}