{
  "type": "Feature",
  "properties": {
    "gn:admin1_code":"71",
    "gn:asciiname":"Nizhniye Tavolgi",
    "gn:country_code":"RU",
    "gn:dem":233,
    "gn:feature_class":"P",
    "gn:feature_code":"PPL",
    "gn:name":"Nizhniye Tavolgi",
    "gn:population":0,
    "gn:timezone":"Asia/Yekaterinburg",
    "iso:country":"RU",
    "name:rus_x_preferred":[
        "\u041d\u0438\u0436\u043d\u0438\u0435 \u0422\u0430\u0432\u043e\u043b\u0433\u0438"
    ],
    "name:und_x_variant":[
        "\u041d\u0438\u0436\u043d\u0438\u0435 \u0422\u0430\u0432\u043e\u043b\u0433\u0438"
    ],
    "wof:name":"Nizhniye Tavolgi",
    "wof:placetype":"locality"
},
  "geometry": {"coordinates":[60.3763,57.58527],"type":"Point"}
}