{
  "type": "Feature",
  "properties": {
    "gn:admin1_code":"83",
    "gn:asciiname":"Miklyaikha",
    "gn:country_code":"RU",
    "gn:dem":203,
    "gn:feature_class":"P",
    "gn:feature_code":"PPL",
    "gn:name":"Miklyaikha",
    "gn:population":0,
    "gn:timezone":"Europe/Moscow",
    "iso:country":"RU",
    "name:rus_x_preferred":[
        "\u041c\u0438\u043a\u043b\u044f\u0438\u0445\u0430"
    ],
    "wof:name":"Miklyaikha",
    "wof:placetype":"locality"
},
  "geometry": {"coordinates":[39.39325,56.19395],"type":"Point"}
}