{
  "type": "Feature",
  "properties": {
    "gn:admin1_code":"85",
    "gn:asciiname":"Zolottslovo",
    "gn:country_code":"RU",
    "gn:dem":193,
    "gn:feature_class":"P",
    "gn:feature_code":"PPL",
    "gn:name":"Zolottslovo",
    "gn:population":0,
    "gn:timezone":"Europe/Moscow",
    "iso:country":"RU",
    "name:rus_x_preferred":[
        "\u0417\u043e\u043b\u043e\u0442\u0446\u043b\u043e\u0432\u043e"
    ],
    "name:und_x_variant":[
        "Zolotilovo"
    ],
    "wof:name":"Zolottslovo",
    "wof:placetype":"locality"
},
  "geometry": {"coordinates":[38.91895,58.83932],"type":"Point"}
}