{
  "type": "Feature",
  "properties": {
    "gn:admin1_code":"73",
    "gn:asciiname":"Verkhniy Tabyn",
    "gn:country_code":"RU",
    "gn:dem":103,
    "gn:feature_class":"P",
    "gn:feature_code":"PPL",
    "gn:name":"Verkhniy Tabyn",
    "gn:population":0,
    "gn:timezone":"Europe/Moscow",
    "iso:country":"RU",
    "name:eng_x_preferred":[
        "Verkhniy Tabyn"
    ],
    "name:nor_x_preferred":[
        "Verkhnij Tabyn"
    ],
    "name:rus_x_preferred":[
        "\u0412\u0435\u0440\u0445\u043d\u0438\u0439 \u0422\u0430\u0431\u044b\u043d"
    ],
    "name:und_x_variant":[
        "Tabyn"
    ],
    "wof:name":"Verkhniy Tabyn",
    "wof:placetype":"locality"
},
  "geometry": {"coordinates":[53.00774000000001,55.35912],"type":"Point"}
}