{
  "type": "Feature",
  "properties": {
    "gn:admin1_code":"62",
    "gn:asciiname":"Verevkin Khutor",
    "gn:country_code":"RU",
    "gn:dem":143,
    "gn:feature_class":"P",
    "gn:feature_code":"PPL",
    "gn:name":"Ver\u00ebvkin Khutor",
    "gn:population":0,
    "gn:timezone":"Europe/Moscow",
    "iso:country":"RU",
    "name:rus_x_preferred":[
        "Ver\u00ebvkin Khutor"
    ],
    "name:rus_x_variant":[
        "\u0412\u0435\u0440\u0451\u0432\u043a\u0438\u043d \u0425\u0443\u0442\u043e\u0440"
    ],
    "name:und_x_variant":[
        "Ver\u00ebvkin"
    ],
    "wof:name":"Verevkin Khutor",
    "wof:placetype":"locality"
},
  "geometry": {"coordinates":[40.344,53.8635],"type":"Point"}
}