{
  "type": "Feature",
  "properties": {
    "gn:admin1_code":"28.0",
    "gn:asciiname":"Akhvenlampi",
    "gn:country_code":"RU",
    "gn:dem":117,
    "gn:feature_class":"P",
    "gn:feature_code":"PPL",
    "gn:name":"Akhvenlampi",
    "gn:population":0,
    "gn:timezone":"Europe/Moscow",
    "iso:country":"RU",
    "name:fin_x_preferred":[
        "Ahvenlampi"
    ],
    "name:nor_x_preferred":[
        "Akhvenlampi"
    ],
    "name:rus_x_preferred":[
        "\u0410\u0445\u0432\u0435\u043d\u043b\u0430\u043c\u043f\u0438"
    ],
    "wof:name":"Akhvenlampi",
    "wof:placetype":"locality"
},
  "geometry": {"coordinates":[32.67334,61.90995],"type":"Point"}
}