{
  "type": "Feature",
  "properties": {
    "gn:admin1_code":"53",
    "gn:asciiname":"Gorevka",
    "gn:country_code":"RU",
    "gn:dem":208,
    "gn:feature_class":"P",
    "gn:feature_code":"PPL",
    "gn:name":"Gorevka",
    "gn:population":0,
    "gn:timezone":"Asia/Novosibirsk",
    "iso:country":"RU",
    "name:eng_x_preferred":[
        "Garevka"
    ],
    "name:nor_x_preferred":[
        "Gorevka"
    ],
    "name:rus_x_preferred":[
        "\u0413\u043e\u0440\u0435\u0432\u043a\u0430"
    ],
    "name:und_x_variant":[
        "Gorevskoye",
        "\u0413\u043e\u0440\u0435\u0432\u043a\u0430",
        "Garevka",
        "Gorevka"
    ],
    "wof:name":"Gorevka",
    "wof:placetype":"locality"
},
  "geometry": {"coordinates":[82.8109,54.4275],"type":"Point"}
}