{
  "type": "Feature",
  "properties": {
    "gn:admin1_code":"84",
    "gn:asciiname":"Lipologovskiy",
    "gn:country_code":"RU",
    "gn:dem":99,
    "gn:feature_class":"P",
    "gn:feature_code":"PPL",
    "gn:name":"Lipologovskiy",
    "gn:population":0,
    "gn:timezone":"Europe/Volgograd",
    "iso:country":"RU",
    "name:rus_x_preferred":[
        "\u041b\u0438\u043f\u043e\u043b\u043e\u0433\u043e\u0432\u0441\u043a\u0438\u0439"
    ],
    "wof:name":"Lipologovskiy",
    "wof:placetype":"locality"
},
  "geometry": {"coordinates":[43.36194,48.82778],"type":"Point"}
}