{
  "type": "Feature",
  "properties": {
    "gn:admin1_code":"60",
    "gn:asciiname":"Zales'ye",
    "gn:country_code":"RU",
    "gn:dem":58,
    "gn:feature_class":"P",
    "gn:feature_code":"PPL",
    "gn:name":"Zales\u2019ye",
    "gn:population":0,
    "gn:timezone":"Europe/Moscow",
    "iso:country":"RU",
    "name:rus_x_preferred":[
        "\u0417\u0430\u043b\u0435\u0441\u044c\u0435"
    ],
    "name:und_x_variant":[
        "Zales\u2019ye"
    ],
    "wof:name":"Zales'ye",
    "wof:placetype":"locality"
},
  "geometry": {"coordinates":[28.06357,58.9353],"type":"Point"}
}