{
  "type": "Feature",
  "properties": {
    "gn:admin1_code":"7.0",
    "gn:asciiname":"Davsta",
    "gn:country_code":"RU",
    "gn:dem":-27,
    "gn:feature_class":"P",
    "gn:feature_code":"PPL",
    "gn:name":"Davsta",
    "gn:population":0,
    "gn:timezone":"Europe/Astrakhan",
    "iso:country":"RU",
    "name:rus_x_preferred":[
        "\u0414\u0430\u0432\u0441\u0442\u0430"
    ],
    "wof:name":"Davsta",
    "wof:placetype":"locality"
},
  "geometry": {"coordinates":[47.51389,45.93694],"type":"Point"}
}