{
  "type": "Feature",
  "properties": {
    "gn:admin1_code":"38",
    "gn:asciiname":"Engel'sa",
    "gn:country_code":"RU",
    "gn:dem":178,
    "gn:feature_class":"P",
    "gn:feature_code":"PPL",
    "gn:name":"Engel\u2019sa",
    "gn:population":0,
    "gn:timezone":"Europe/Moscow",
    "iso:country":"RU",
    "name:rus_x_preferred":[
        "\u042d\u043d\u0433\u0435\u043b\u044c\u0441\u0430"
    ],
    "name:und_x_variant":[
        "Imeni Engel\u2019sa",
        "Engel\u2019sa"
    ],
    "wof:name":"Engel'sa",
    "wof:placetype":"locality"
},
  "geometry": {"coordinates":[40.85,45.12278],"type":"Point"}
}