{
  "type": "Feature",
  "properties": {
    "gn:admin1_code":"51.0",
    "gn:asciiname":"Rezanovo",
    "gn:country_code":"RU",
    "gn:dem":115,
    "gn:feature_class":"P",
    "gn:feature_code":"PPL",
    "gn:name":"Rezanovo",
    "gn:population":0,
    "gn:timezone":"Europe/Moscow",
    "iso:country":"RU",
    "name:nor_x_preferred":[
        "Rezanovo"
    ],
    "name:rus_x_preferred":[
        "\u0420\u0435\u0437\u0430\u043d\u043e\u0432\u043e"
    ],
    "wof:name":"Rezanovo",
    "wof:placetype":"locality"
},
  "geometry": {"coordinates":[43.30217,56.9723],"type":"Point"}
}