{
  "type": "Feature",
  "properties": {
    "gn:admin1_code":"8.0",
    "gn:asciiname":"Bekeshevo",
    "gn:country_code":"RU",
    "gn:dem":511,
    "gn:feature_class":"P",
    "gn:feature_code":"PPL",
    "gn:name":"Bekeshevo",
    "gn:population":0,
    "gn:timezone":"Asia/Yekaterinburg",
    "iso:country":"RU",
    "name:aze_x_preferred":[
        "Bike\u015f"
    ],
    "name:bak_x_preferred":[
        "\u0411\u0438\u043a\u0435\u0448"
    ],
    "name:che_x_preferred":[
        "\u0411\u0435\u043a\u0435\u0448\u0435\u0432\u043e"
    ],
    "name:eng_x_preferred":[
        "Bekeshevo"
    ],
    "name:hye_x_preferred":[
        "\u0532\u0565\u056f\u0565\u0577\u0587\u0578"
    ],
    "name:kaz_x_preferred":[
        "\u0411\u0435\u043a\u0435\u0448"
    ],
    "name:kir_x_preferred":[
        "\u0411\u0435\u043a\u0435\u0448"
    ],
    "name:nor_x_preferred":[
        "Bekesjevo"
    ],
    "name:rus_x_preferred":[
        "\u0411\u0435\u043a\u0435\u0448\u0435\u0432\u043e"
    ],
    "name:tat_x_preferred":[
        "\u0411\u0438\u043a\u0435\u0448"
    ],
    "name:ukr_x_preferred":[
        "\u0411\u0435\u043a\u0435\u0448\u0435\u0432\u043e"
    ],
    "name:und_x_variant":[
        "\u0411\u0435\u043a\u0435\u0448\u0435\u0432\u043e",
        "Bekeshevo"
    ],
    "wof:name":"Bekeshevo",
    "wof:placetype":"locality"
},
  "geometry": {"coordinates":[58.08528,52.74028000000001],"type":"Point"}
}