{
  "type": "Feature",
  "properties": {
    "gn:admin1_code":"91.0",
    "gn:asciiname":"Kuchetkan",
    "gn:country_code":"RU",
    "gn:dem":312,
    "gn:feature_class":"P",
    "gn:feature_code":"PPL",
    "gn:name":"Kuchetkan",
    "gn:population":0,
    "gn:timezone":"Asia/Krasnoyarsk",
    "iso:country":"RU",
    "name:rus_x_preferred":[
        "\u041a\u0443\u0447\u0435\u0442\u043a\u0430\u043d"
    ],
    "wof:name":"Kuchetkan",
    "wof:placetype":"locality"
},
  "geometry": {"coordinates":[97.3938,57.8555],"type":"Point"}
}