{
  "type": "Feature",
  "properties": {
    "gn:admin1_code":"4",
    "gn:asciiname":"Kamenka Vtoraya",
    "gn:cc2":"RU",
    "gn:country_code":"RU",
    "gn:dem":285,
    "gn:feature_class":"P",
    "gn:feature_code":"PPL",
    "gn:name":"Kamenka Vtoraya",
    "gn:population":0,
    "gn:timezone":"Asia/Barnaul",
    "iso:country":"RU",
    "name:eng_x_preferred":[
        "Kamenka Vtoraya"
    ],
    "name:rus_x_preferred":[
        "\u041a\u0430\u043c\u0435\u043d\u043a\u0430-2-\u044f"
    ],
    "name:rus_x_variant":[
        "\u041a\u0430\u043c\u0435\u043d\u0430 2-\u044f",
        "\u041a\u0430\u043c\u0435\u043d\u043a\u0430 \u0412\u0442\u043e\u0440\u0430\u044f"
    ],
    "name:und_x_variant":[
        "Vtoraya Kamenka",
        "Kamenskoye",
        "Kamenka",
        "Kamenka 2 (Vtoraya)",
        "Kamenka 2-ya"
    ],
    "wof:name":"Kamenka Vtoraya",
    "wof:placetype":"locality"
},
  "geometry": {"coordinates":[81.75417,51.05917],"type":"Point"}
}