{
  "type": "Feature",
  "properties": {
    "gn:admin1_code":"21.0",
    "gn:asciiname":"Pochinki",
    "gn:country_code":"RU",
    "gn:dem":126,
    "gn:feature_class":"P",
    "gn:feature_code":"PPL",
    "gn:name":"Pochinki",
    "gn:population":0,
    "gn:timezone":"Europe/Moscow",
    "iso:country":"RU",
    "name:ara_x_preferred":[
        "\u0628\u0648\u0634\u0646\u0643\u064a"
    ],
    "name:rus_x_preferred":[
        "\u041f\u043e\u0447\u0438\u043d\u043a\u0438"
    ],
    "name:und_x_variant":[
        "\u041f\u043e\u0447\u0438\u043d\u043a\u0438"
    ],
    "wof:name":"Pochinki",
    "wof:placetype":"locality"
},
  "geometry": {"coordinates":[42.91291,57.27335],"type":"Point"}
}