{
  "type": "Feature",
  "properties": {
    "gn:admin1_code":"89",
    "gn:asciiname":"Trek",
    "gn:country_code":"RU",
    "gn:dem":109,
    "gn:feature_class":"P",
    "gn:feature_code":"PPL",
    "gn:name":"Trek",
    "gn:population":0,
    "gn:timezone":"Asia/Vladivostok",
    "iso:country":"RU",
    "name:eng_x_preferred":[
        "Trek"
    ],
    "name:nor_x_preferred":[
        "St.Trek"
    ],
    "name:rus_x_preferred":[
        "\u0421\u0442.\u0422\u0440\u0435\u043a"
    ],
    "name:rus_x_variant":[
        "\u0422\u0440\u0435\u043a"
    ],
    "name:und_x_variant":[
        "Topol\u00ebvaya",
        "Trek"
    ],
    "wof:name":"Trek",
    "wof:placetype":"locality"
},
  "geometry": {"coordinates":[132.71807999999999,48.9151],"type":"Point"}
}