{
  "type": "Feature",
  "properties": {
    "gn:admin1_code":"69",
    "gn:asciiname":"Bobovo",
    "gn:country_code":"RU",
    "gn:dem":250,
    "gn:feature_class":"P",
    "gn:feature_code":"PPL",
    "gn:name":"Bobovo",
    "gn:population":0,
    "gn:timezone":"Europe/Moscow",
    "iso:country":"RU",
    "wof:name":"Bobovo",
    "wof:placetype":"locality"
},
  "geometry": {"coordinates":[34.33796,55.15868],"type":"Point"}
}