{
  "type": "Feature",
  "properties": {
    "gn:admin1_code":"88",
    "gn:asciiname":"Yadreyevo",
    "gn:country_code":"RU",
    "gn:dem":120,
    "gn:feature_class":"P",
    "gn:feature_code":"PPL",
    "gn:name":"Yadreyevo",
    "gn:population":0,
    "gn:timezone":"Europe/Moscow",
    "iso:country":"RU",
    "name:rus_x_preferred":[
        "\u042f\u0434\u0440\u0435\u0435\u0432\u043e"
    ],
    "name:und_x_variant":[
        "\u042f\u0434\u0440\u0435\u0435\u0432\u043e"
    ],
    "wof:name":"Yadreyevo",
    "wof:placetype":"locality"
},
  "geometry": {"coordinates":[38.6539,57.6281],"type":"Point"}
}