{
  "type": "Feature",
  "properties": {
    "gn:admin1_code":"34",
    "gn:asciiname":"Madmas",
    "gn:country_code":"RU",
    "gn:dem":78,
    "gn:feature_class":"P",
    "gn:feature_code":"PPL",
    "gn:name":"Madmas",
    "gn:population":0,
    "gn:timezone":"Europe/Moscow",
    "iso:country":"RU",
    "name:eng_x_preferred":[
        "Madmas"
    ],
    "name:nor_x_preferred":[
        "Madmas"
    ],
    "name:rus_x_preferred":[
        "\u041c\u0430\u0434\u043c\u0430\u0441"
    ],
    "name:und_x_variant":[
        "\u041c\u0430\u0434\u043c\u0430\u0441",
        "Madmas"
    ],
    "wof:name":"Madmas",
    "wof:placetype":"locality"
},
  "geometry": {"coordinates":[49.31937,62.02629],"type":"Point"}
}