{
  "type": "Feature",
  "properties": {
    "gn:admin1_code":"90.0",
    "gn:asciiname":"Permyakovka",
    "gn:country_code":"RU",
    "gn:dem":122,
    "gn:feature_class":"P",
    "gn:feature_code":"PPL",
    "gn:name":"Permyakovka",
    "gn:population":0,
    "gn:timezone":"Asia/Yekaterinburg",
    "iso:country":"RU",
    "name:rus_x_preferred":[
        "\u041f\u0435\u0440\u043c\u044f\u043a\u043e\u0432\u043a\u0430"
    ],
    "wof:name":"Permyakovka",
    "wof:placetype":"locality"
},
  "geometry": {"coordinates":[54.45282,57.125],"type":"Point"}
}