{
  "type": "Feature",
  "properties": {
    "gn:admin1_code":"72",
    "gn:asciiname":"Krasivka",
    "gn:country_code":"RU",
    "gn:dem":167,
    "gn:feature_class":"P",
    "gn:feature_code":"PPL",
    "gn:name":"Krasivka",
    "gn:population":0,
    "gn:timezone":"Europe/Moscow",
    "iso:country":"RU",
    "name:eng_x_preferred":[
        "Krasivka"
    ],
    "name:nor_x_preferred":[
        "Krasivka"
    ],
    "name:rus_x_preferred":[
        "\u041a\u0440\u0430\u0441\u0438\u0432\u043a\u0430"
    ],
    "name:und_x_variant":[
        "\u041a\u0440\u0430\u0441\u0438\u0432\u043a\u0430",
        "Krasivka"
    ],
    "wof:name":"Krasivka",
    "wof:placetype":"locality"
},
  "geometry": {"coordinates":[42.39657,53.23075],"type":"Point"}
}