{
  "type": "Feature",
  "properties": {
    "gn:country":"RU",
    "gn:fcode":"PPL",
    "gn:pop":486,
    "iso:country":"RU",
    "name:rus_x_preferred":[
        "\u041f\u0440\u0430\u0432\u0434\u0430"
    ],
    "name:unk_x_variant":[
        "\u041f\u0440\u0430\u0432\u0434\u0430"
    ],
    "qs:name":"Pravda",
    "qs:name_adm0":"Russia",
    "qs:name_adm1":"Altai Krai",
    "qs:photos_9r":0,
    "qs:photos_sr":0,
    "qs:placetype":"Town",
    "qs:pop_sr":"2",
    "wd:wordcount":2200,
    "wof:name":"Pravda",
    "wof:placetype":"locality",
    "wof:population":486
},
  "geometry": {"coordinates":[84.1275,53.4374],"type":"Point"}
}