{
  "type": "Feature",
  "properties": {
    "gn:admin1_code":"61",
    "gn:asciiname":"Kupyrovskiy",
    "gn:country_code":"RU",
    "gn:dem":96,
    "gn:feature_class":"P",
    "gn:feature_code":"PPL",
    "gn:name":"Kupyrovskiy",
    "gn:population":0,
    "gn:timezone":"Europe/Moscow",
    "iso:country":"RU",
    "name:rus_x_preferred":[
        "\u041a\u0443\u043f\u044b\u0440\u043e\u0432\u0441\u043a\u0438\u0439"
    ],
    "wof:name":"Kupyrovskiy",
    "wof:placetype":"locality"
},
  "geometry": {"coordinates":[40.3106,49.32932],"type":"Point"}
}