{
  "type": "Feature",
  "properties": {
    "gn:admin1_code":"12.0",
    "gn:asciiname":"Baukhoy",
    "gn:country_code":"RU",
    "gn:dem":1248,
    "gn:feature_class":"P",
    "gn:feature_code":"PPL",
    "gn:name":"Baukhoy",
    "gn:population":0,
    "gn:timezone":"Europe/Moscow",
    "iso:country":"RU",
    "name:nor_x_preferred":[
        "Baukhoj"
    ],
    "name:rus_x_preferred":[
        "\u0411\u0430\u0443\u0445\u043e\u0439"
    ],
    "wof:name":"Baukhoy",
    "wof:placetype":"locality"
},
  "geometry": {"coordinates":[45.56861,42.78806],"type":"Point"}
}