{
  "type": "Feature",
  "properties": {
    "gn:admin1_code":"53",
    "gn:asciiname":"Chumakovo",
    "gn:country_code":"RU",
    "gn:dem":123,
    "gn:feature_class":"P",
    "gn:feature_code":"PPL",
    "gn:name":"Chumakovo",
    "gn:population":0,
    "gn:timezone":"Asia/Novosibirsk",
    "iso:country":"RU",
    "name:eng_x_preferred":[
        "Chumakovo"
    ],
    "name:nor_x_preferred":[
        "Tsjumakovo"
    ],
    "name:rus_x_preferred":[
        "\u0427\u0443\u043c\u0430\u043a\u043e\u0432\u043e"
    ],
    "name:und_x_variant":[
        "\u0427\u0443\u043c\u0430\u043a\u043e\u0432\u043e",
        "Chumakovo"
    ],
    "wof:name":"Chumakovo",
    "wof:placetype":"locality"
},
  "geometry": {"coordinates":[79.0553,55.68906],"type":"Point"}
}