{
  "type": "Feature",
  "properties": {
    "gn:admin1_code":"40",
    "gn:asciiname":"Profintern",
    "gn:country_code":"RU",
    "gn:dem":137,
    "gn:feature_class":"P",
    "gn:feature_code":"PPL",
    "gn:name":"Profintern",
    "gn:population":0,
    "gn:timezone":"Asia/Yekaterinburg",
    "iso:country":"RU",
    "name:eng_x_preferred":[
        "Profintern"
    ],
    "name:nor_x_preferred":[
        "Profintern"
    ],
    "name:rus_x_preferred":[
        "\u041f\u0440\u043e\u0444\u0438\u043d\u0442\u0435\u0440\u043d"
    ],
    "name:und_x_variant":[
        "\u041f\u0440\u043e\u0444\u0438\u043d\u0442\u0435\u0440\u043d",
        "Profintern"
    ],
    "wof:name":"Profintern",
    "wof:placetype":"locality"
},
  "geometry": {"coordinates":[67.00721999999999,54.89306],"type":"Point"}
}