{
  "type": "Feature",
  "properties": {
    "gn:admin1_code":"93",
    "gn:asciiname":"Novyy Durulguy",
    "gn:country_code":"RU",
    "gn:dem":767,
    "gn:feature_class":"P",
    "gn:feature_code":"PPL",
    "gn:name":"Novyy Durulguy",
    "gn:population":0,
    "gn:timezone":"Asia/Chita",
    "iso:country":"RU",
    "name:eng_x_preferred":[
        "Novyy Durulguy"
    ],
    "name:nor_x_preferred":[
        "Nov.Durulguj"
    ],
    "name:rus_x_preferred":[
        "\u041d\u043e\u0432.\u0414\u0443\u0440\u0443\u043b\u0433\u0443\u0439"
    ],
    "name:rus_x_variant":[
        "\u041d\u043e\u0432\u044b\u0439 \u0414\u0443\u0440\u0443\u043b\u0433\u0443\u0439"
    ],
    "name:und_x_variant":[
        "Novy Durulguy",
        "Novodurulguy",
        "Nov\u00f6y Durulguy",
        "Novo-Durulgui"
    ],
    "wof:name":"Novyy Durulguy",
    "wof:placetype":"locality"
},
  "geometry": {"coordinates":[114.41667,50.33333],"type":"Point"}
}