{
  "type": "Feature",
  "properties": {
    "gn:admin1_code":"10",
    "gn:asciiname":"Mantsurovo",
    "gn:country_code":"RU",
    "gn:dem":175,
    "gn:feature_class":"P",
    "gn:feature_code":"PPL",
    "gn:name":"Mantsurovo",
    "gn:population":0,
    "gn:timezone":"Europe/Moscow",
    "iso:country":"RU",
    "name:eng_x_preferred":[
        "Mantsurovka"
    ],
    "name:nor_x_preferred":[
        "Mantsurovo"
    ],
    "name:rus_x_preferred":[
        "\u041c\u0430\u043d\u0446\u0443\u0440\u043e\u0432\u043e"
    ],
    "name:und_x_variant":[
        "\u041c\u0430\u043d\u0446\u0443\u0440\u043e\u0432\u043e",
        "Mantsurovka"
    ],
    "wof:name":"Mantsurovo",
    "wof:placetype":"locality"
},
  "geometry": {"coordinates":[33.98407,52.80299],"type":"Point"}
}