{
  "type": "Feature",
  "properties": {
    "gn:admin1_code":"57",
    "gn:asciiname":"Kerenka",
    "gn:country_code":"RU",
    "gn:dem":179,
    "gn:feature_class":"P",
    "gn:feature_code":"PPL",
    "gn:name":"Kerenka",
    "gn:population":0,
    "gn:timezone":"Europe/Moscow",
    "iso:country":"RU",
    "name:est_x_preferred":[
        "Kerenski rubla"
    ],
    "name:ron_x_preferred":[
        "Kerenka"
    ],
    "name:rus_x_preferred":[
        "\u041a\u0435\u0440\u0435\u043d\u043a\u0430"
    ],
    "wof:name":"Kerenka",
    "wof:placetype":"locality"
},
  "geometry": {"coordinates":[44.73802,53.45815],"type":"Point"}
}