{
  "type": "Feature",
  "properties": {
    "gn:admin1_code":"42",
    "gn:asciiname":"Goryatino",
    "gn:country_code":"RU",
    "gn:dem":86,
    "gn:feature_class":"P",
    "gn:feature_code":"PPL",
    "gn:name":"Goryatino",
    "gn:population":0,
    "gn:timezone":"Europe/Moscow",
    "iso:country":"RU",
    "name:rus_x_preferred":[
        "\u0413\u043e\u0440\u044f\u0442\u0438\u043d\u043e"
    ],
    "name:und_x_variant":[
        "\u0413\u043e\u0440\u044f\u0442\u0438\u043d\u043e"
    ],
    "wof:name":"Goryatino",
    "wof:placetype":"locality"
},
  "geometry": {"coordinates":[32.60402,59.26425],"type":"Point"}
}