{
  "type": "Feature",
  "properties": {
    "gn:admin1_code":"47",
    "gn:asciiname":"Smolino",
    "gn:cc2":"RU",
    "gn:country_code":"RU",
    "gn:dem":183,
    "gn:feature_class":"P",
    "gn:feature_code":"PPL",
    "gn:name":"Smolino",
    "gn:population":0,
    "gn:timezone":"Europe/Moscow",
    "iso:country":"RU",
    "name:bel_x_preferred":[
        "\u0421\u043c\u043e\u043b\u0456\u043d\u0430"
    ],
    "name:eng_x_preferred":[
        "Smolino"
    ],
    "name:fra_x_preferred":[
        "Smolino"
    ],
    "name:nor_x_preferred":[
        "Smolino"
    ],
    "name:rus_x_preferred":[
        "\u0421\u043c\u043e\u043b\u0438\u043d\u043e"
    ],
    "name:ukr_x_preferred":[
        "\u0421\u043c\u043e\u043b\u0456\u043d\u043e"
    ],
    "name:und_x_variant":[
        "Smolinskoye",
        "\u0421\u043c\u043e\u043b\u0438\u043d\u043e",
        "Smolino"
    ],
    "wof:name":"Smolino",
    "wof:placetype":"locality"
},
  "geometry": {"coordinates":[36.44222,55.35556],"type":"Point"}
}