{
  "type": "Feature",
  "properties": {
    "gn:admin1_code":"91",
    "gn:asciiname":"Vasil'yevka",
    "gn:country_code":"RU",
    "gn:dem":348,
    "gn:feature_class":"P",
    "gn:feature_code":"PPL",
    "gn:name":"Vasil\u2019yevka",
    "gn:population":0,
    "gn:timezone":"Asia/Krasnoyarsk",
    "iso:country":"RU",
    "wof:name":"Vasil'yevka",
    "wof:placetype":"locality"
},
  "geometry": {"coordinates":[92.333,54.54174],"type":"Point"}
}