{
  "type": "Feature",
  "properties": {
    "gn:admin1_code":"25",
    "gn:asciiname":"Pavlovka",
    "gn:country_code":"RU",
    "gn:dem":202,
    "gn:feature_class":"P",
    "gn:feature_code":"PPL",
    "gn:name":"Pavlovka",
    "gn:population":0,
    "gn:timezone":"Europe/Moscow",
    "iso:country":"RU",
    "name:nor_x_preferred":[
        "Pavlovka"
    ],
    "name:rus_x_preferred":[
        "\u041f\u0430\u0432\u043b\u043e\u0432\u043a\u0430"
    ],
    "wof:name":"Pavlovka",
    "wof:placetype":"locality"
},
  "geometry": {"coordinates":[36.36594,54.75036],"type":"Point"}
}