{
  "type": "Feature",
  "properties": {
    "gn:admin1_code":"71",
    "gn:asciiname":"Shpalorezka",
    "gn:country_code":"RU",
    "gn:dem":62,
    "gn:feature_class":"P",
    "gn:feature_code":"PPL",
    "gn:name":"Shpalorezka",
    "gn:population":0,
    "gn:timezone":"Asia/Yekaterinburg",
    "iso:country":"RU",
    "name:rus_x_preferred":[
        "\u0428\u043f\u0430\u043b\u043e\u0440\u0435\u0437\u043a\u0430"
    ],
    "name:und_x_variant":[
        "\u0428\u043f\u0430\u043b\u043e\u0440\u0435\u0437\u043a\u0430"
    ],
    "wof:name":"Shpalorezka",
    "wof:placetype":"locality"
},
  "geometry": {"coordinates":[64.73810999999999,58.36697],"type":"Point"}
}