{
  "type": "Feature",
  "properties": {
    "gn:admin1_code":"93",
    "gn:asciiname":"Kuti",
    "gn:country_code":"RU",
    "gn:dem":554,
    "gn:feature_class":"P",
    "gn:feature_code":"PPL",
    "gn:name":"Kuti",
    "gn:population":0,
    "gn:timezone":"Asia/Chita",
    "iso:country":"RU",
    "name:bos_x_preferred":[
        "Kuti"
    ],
    "name:ceb_x_preferred":[
        "Kuti"
    ],
    "name:deu_x_preferred":[
        "Kuti"
    ],
    "name:eng_x_preferred":[
        "Kuti"
    ],
    "name:fra_x_preferred":[
        "Kuti"
    ],
    "name:hrv_x_preferred":[
        "Kuti"
    ],
    "name:nor_x_preferred":[
        "Kuti"
    ],
    "name:pol_x_preferred":[
        "Kuti"
    ],
    "name:rus_x_preferred":[
        "\u041a\u0443\u0442\u0438"
    ],
    "name:slv_x_preferred":[
        "Kuti"
    ],
    "name:srp_x_preferred":[
        "\u041a\u0443\u0442\u0438"
    ],
    "name:swe_x_preferred":[
        "Kuti"
    ],
    "name:und_x_variant":[
        "\u041a\u0443\u0442\u0438",
        "Kuti"
    ],
    "wof:name":"Kuti",
    "wof:placetype":"locality"
},
  "geometry": {"coordinates":[119.1867,50.0898],"type":"Point"}
}