{
  "type": "Feature",
  "properties": {
    "gn:admin1_code":"67.0",
    "gn:asciiname":"Kar'yer",
    "gn:country_code":"RU",
    "gn:dem":37,
    "gn:feature_class":"P",
    "gn:feature_code":"PPL",
    "gn:name":"Kar\u2019yer",
    "gn:population":0,
    "gn:timezone":"Europe/Saratov",
    "iso:country":"RU",
    "name:rus_x_preferred":[
        "\u041a\u0430\u0440\u044c\u0435\u0440"
    ],
    "name:und_x_variant":[
        "Kar\u2019yer",
        "\u041a\u0430\u0440\u044c\u0435\u0440"
    ],
    "wof:name":"Kar'yer",
    "wof:placetype":"locality"
},
  "geometry": {"coordinates":[46.92475,52.15473],"type":"Point"}
}