{
  "type": "Feature",
  "properties": {
    "gn:admin1_code":"54",
    "gn:asciiname":"Malaya Safonikha",
    "gn:country_code":"RU",
    "gn:dem":123,
    "gn:feature_class":"P",
    "gn:feature_code":"PPL",
    "gn:name":"Malaya Safonikha",
    "gn:population":0,
    "gn:timezone":"Asia/Omsk",
    "iso:country":"RU",
    "name:rus_x_preferred":[
        "\u041c\u0430\u043b\u0430\u044f \u0421\u0430\u0444\u043e\u043d\u0438\u0445\u0430"
    ],
    "wof:name":"Malaya Safonikha",
    "wof:placetype":"locality"
},
  "geometry": {"coordinates":[71.48845,55.71705],"type":"Point"}
}