{
  "type": "Feature",
  "properties": {
    "gn:admin1_code":"76.0",
    "gn:asciiname":"Bukhtorma",
    "gn:country_code":"RU",
    "gn:dem":216,
    "gn:feature_class":"P",
    "gn:feature_code":"PPL",
    "gn:name":"Bukhtorma",
    "gn:population":0,
    "gn:timezone":"Europe/Moscow",
    "iso:country":"RU",
    "name:rus_x_preferred":[
        "\u0411\u0443\u0445\u0442\u043e\u0440\u043c\u0430"
    ],
    "name:und_x_variant":[
        "Bukhtorka",
        "Bukhtorma",
        "\u0411\u0443\u0445\u0442\u043e\u0440\u043c\u0430",
        "Bukhtorna"
    ],
    "wof:name":"Bukhtorma",
    "wof:placetype":"locality"
},
  "geometry": {"coordinates":[37.16632,54.48894],"type":"Point"}
}