{
  "type": "Feature",
  "properties": {
    "gn:admin1_code":"85",
    "gn:asciiname":"Yakovlevskoye",
    "gn:country_code":"RU",
    "gn:dem":150,
    "gn:feature_class":"P",
    "gn:feature_code":"PPL",
    "gn:name":"Yakovlevskoye",
    "gn:population":0,
    "gn:timezone":"Europe/Moscow",
    "iso:country":"RU",
    "name:rus_x_preferred":[
        "\u042f\u043a\u043e\u0432\u043b\u0435\u0432\u0441\u043a\u043e\u0435"
    ],
    "name:und_x_variant":[
        "\u042f\u043a\u043e\u0432\u043b\u0435\u0432\u0441\u043a\u043e\u0435"
    ],
    "wof:name":"Yakovlevskoye",
    "wof:placetype":"locality"
},
  "geometry": {"coordinates":[39.75096,59.35543000000001],"type":"Point"}
}