{
  "type": "Feature",
  "properties": {
    "gn:admin1_code":"80.0",
    "gn:asciiname":"Zhobshur",
    "gn:country_code":"RU",
    "gn:dem":259,
    "gn:feature_class":"P",
    "gn:feature_code":"PPL",
    "gn:name":"Zhobshur",
    "gn:population":0,
    "gn:timezone":"Europe/Samara",
    "iso:country":"RU",
    "name:rus_x_preferred":[
        "\u0416\u043e\u0431\u0448\u0443\u0440"
    ],
    "wof:name":"Zhobshur",
    "wof:placetype":"locality"
},
  "geometry": {"coordinates":[53.3512,58.1853],"type":"Point"}
}