{
  "type": "Feature",
  "properties": {
    "gn:admin1_code":"68.0",
    "gn:asciiname":"Biragzang",
    "gn:country_code":"RU",
    "gn:dem":668,
    "gn:feature_class":"P",
    "gn:feature_code":"PPL",
    "gn:name":"Biragzang",
    "gn:population":0,
    "gn:timezone":"Europe/Moscow",
    "iso:country":"RU",
    "name:eng_x_preferred":[
        "Biragzang"
    ],
    "name:nor_x_preferred":[
        "Biragzang"
    ],
    "name:rus_x_preferred":[
        "\u0411\u0438\u0440\u0430\u0433\u0437\u0430\u043d\u0433"
    ],
    "wof:name":"Biragzang",
    "wof:placetype":"locality"
},
  "geometry": {"coordinates":[44.23291,43.00829],"type":"Point"}
}