{
  "type": "Feature",
  "properties": {
    "gn:admin1_code":"54",
    "gn:asciiname":"Malyy Ayev",
    "gn:cc2":"RU",
    "gn:country_code":"RU",
    "gn:dem":94,
    "gn:feature_class":"P",
    "gn:feature_code":"PPL",
    "gn:name":"Malyy Ayev",
    "gn:population":0,
    "gn:timezone":"Asia/Omsk",
    "iso:country":"RU",
    "name:rus_x_preferred":[
        "\u041c\u0430\u043b\u044b\u0439 \u0410\u0435\u0432"
    ],
    "name:und_x_variant":[
        "Maly Ayev",
        "Malyy Ayev"
    ],
    "wof:name":"Malyy Ayev",
    "wof:placetype":"locality"
},
  "geometry": {"coordinates":[71.93333,56.91667],"type":"Point"}
}