{
  "type": "Feature",
  "properties": {
    "gn:admin1_code":"77",
    "gn:asciiname":"Rybinskoye Zaruch'ye",
    "gn:country_code":"RU",
    "gn:dem":138,
    "gn:feature_class":"P",
    "gn:feature_code":"PPL",
    "gn:name":"Rybinskoye Zaruch\u2019ye",
    "gn:population":0,
    "gn:timezone":"Europe/Moscow",
    "iso:country":"RU",
    "name:rus_x_preferred":[
        "\u0420\u044b\u0431\u0438\u043d\u0441\u043a\u043e\u0435 \u0417\u0430\u0440\u0443\u0447\u044c\u0435"
    ],
    "name:und_x_variant":[
        "Pybinskoye Zaruch\u2019ye",
        "Rybinskoye Zaruch\u2019ye",
        "\u0420\u044b\u0431\u0438\u043d\u0441\u043a\u043e\u0435 \u0417\u0430\u0440\u0443\u0447\u044c\u0435"
    ],
    "wof:name":"Rybinskoye Zaruch'ye",
    "wof:placetype":"locality"
},
  "geometry": {"coordinates":[35.98898,57.81545],"type":"Point"}
}