{
  "type": "Feature",
  "properties": {
    "gn:admin1_code":"62",
    "gn:asciiname":"Gal'tsovo",
    "gn:country_code":"RU",
    "gn:dem":147,
    "gn:feature_class":"P",
    "gn:feature_code":"PPL",
    "gn:name":"Gal\u2019tsovo",
    "gn:population":0,
    "gn:timezone":"Europe/Moscow",
    "iso:country":"RU",
    "name:rus_x_preferred":[
        "\u0413\u0430\u043b\u044c\u0446\u043e\u0432\u043e"
    ],
    "name:und_x_variant":[
        "Gal\u2019tsevo",
        "Gal\u2019tsovo"
    ],
    "wof:name":"Gal'tsovo",
    "wof:placetype":"locality"
},
  "geometry": {"coordinates":[39.81793,53.97727],"type":"Point"}
}