{
  "type": "Feature",
  "properties": {
    "gn:admin1_code":"6.0",
    "gn:asciiname":"Churkinskaya",
    "gn:country_code":"RU",
    "gn:dem":176,
    "gn:feature_class":"P",
    "gn:feature_code":"PPL",
    "gn:name":"Churkinskaya",
    "gn:population":0,
    "gn:timezone":"Europe/Moscow",
    "iso:country":"RU",
    "name:rus_x_preferred":[
        "\u0427\u0443\u0440\u043a\u0438\u043d\u0441\u043a\u0430\u044f"
    ],
    "name:und_x_variant":[
        "\u0427\u0443\u0440\u043a\u0438\u043d\u0441\u043a\u0430\u044f"
    ],
    "wof:name":"Churkinskaya",
    "wof:placetype":"locality"
},
  "geometry": {"coordinates":[41.88333,60.98333],"type":"Point"}
}