{
  "type": "Feature",
  "properties": {
    "gn:admin1_code":"33",
    "gn:asciiname":"Uspenskoye",
    "gn:country_code":"RU",
    "gn:dem":127,
    "gn:feature_class":"P",
    "gn:feature_code":"PPL",
    "gn:name":"Uspenskoye",
    "gn:population":0,
    "gn:timezone":"Europe/Kirov",
    "iso:country":"RU",
    "name:rus_x_preferred":[
        "\u0423\u0441\u043f\u0435\u043d\u0441\u043a\u043e\u0435"
    ],
    "wof:name":"Uspenskoye",
    "wof:placetype":"locality"
},
  "geometry": {"coordinates":[50.17833,58.68],"type":"Point"}
}