{
  "type": "Feature",
  "properties": {
    "gn:admin1_code":"63",
    "gn:asciiname":"Sayylyk",
    "gn:country_code":"RU",
    "gn:dem":340,
    "gn:feature_class":"P",
    "gn:feature_code":"PPL",
    "gn:name":"Sayylyk",
    "gn:population":0,
    "gn:timezone":"Asia/Vladivostok",
    "iso:country":"RU",
    "name:eng_x_preferred":[
        "Sayylyk"
    ],
    "name:nor_x_preferred":[
        "Sajylyk"
    ],
    "name:rus_x_preferred":[
        "\u0421\u0430\u0439\u044b\u043b\u044b\u043a"
    ],
    "wof:name":"Sayylyk",
    "wof:placetype":"locality"
},
  "geometry": {"coordinates":[138.41253,68.96602],"type":"Point"}
}