{
  "type": "Feature",
  "properties": {
    "gn:admin1_code":"10.0",
    "gn:asciiname":"Glyadino",
    "gn:country_code":"RU",
    "gn:dem":202,
    "gn:feature_class":"P",
    "gn:feature_code":"PPL",
    "gn:name":"Glyadino",
    "gn:population":0,
    "gn:timezone":"Europe/Moscow",
    "iso:country":"RU",
    "name:rus_x_preferred":[
        "\u0413\u043b\u044f\u0434\u0438\u043d\u043e"
    ],
    "name:und_x_variant":[
        "Shulevka",
        "Glyadino",
        "\u0413\u043b\u044f\u0434\u0438\u043d\u043e"
    ],
    "wof:name":"Glyadino",
    "wof:placetype":"locality"
},
  "geometry": {"coordinates":[34.8208,52.3559],"type":"Point"}
}