{
  "type": "Feature",
  "properties": {
    "gn:admin1_code":"23",
    "gn:asciiname":"Anichkino",
    "gn:country_code":"RU",
    "gn:dem":7,
    "gn:feature_class":"P",
    "gn:feature_code":"PPL",
    "gn:name":"Anichkino",
    "gn:population":0,
    "gn:timezone":"Europe/Kaliningrad",
    "iso:country":"RU",
    "name:nor_x_preferred":[
        "Anitsjkino"
    ],
    "name:rus_x_preferred":[
        "\u0410\u043d\u0438\u0447\u043a\u0438\u043d\u043e"
    ],
    "wof:name":"Anichkino",
    "wof:placetype":"locality"
},
  "geometry": {"coordinates":[20.86889,54.80333],"type":"Point"}
}