{
  "type": "Feature",
  "properties": {
    "gn:admin1_code":"17",
    "gn:asciiname":"Novogladovka",
    "gn:country_code":"RU",
    "gn:dem":-13,
    "gn:feature_class":"P",
    "gn:feature_code":"PPL",
    "gn:name":"Novogladovka",
    "gn:population":0,
    "gn:timezone":"Europe/Moscow",
    "iso:country":"RU",
    "name:rus_x_preferred":[
        "\u041d\u043e\u0432\u043e\u0433\u043b\u0430\u0434\u043e\u0432\u043a\u0430"
    ],
    "name:und_x_variant":[
        "Novogladkovskiy",
        "Novogladovka"
    ],
    "wof:name":"Novogladovka",
    "wof:placetype":"locality"
},
  "geometry": {"coordinates":[46.89421,43.84923],"type":"Point"}
}