{
  "type": "Feature",
  "properties": {
    "gn:admin1_code":"43.0",
    "gn:asciiname":"Aksay",
    "gn:country_code":"RU",
    "gn:dem":153,
    "gn:feature_class":"P",
    "gn:feature_code":"PPL",
    "gn:name":"Aksay",
    "gn:population":0,
    "gn:timezone":"Europe/Moscow",
    "iso:country":"RU",
    "name:ceb_x_preferred":[
        "Aksay"
    ],
    "name:nor_x_preferred":[
        "Aksaj"
    ],
    "name:rus_x_preferred":[
        "\u0410\u043a\u0441\u0430\u0439"
    ],
    "name:swe_x_preferred":[
        "Aksay"
    ],
    "name:tgl_x_preferred":[
        "Aksay"
    ],
    "wof:name":"Aksay",
    "wof:placetype":"locality"
},
  "geometry": {"coordinates":[39.72352,52.24958],"type":"Point"}
}