{
  "type": "Feature",
  "properties": {
    "gn:admin1_code":"90",
    "gn:asciiname":"Kuz'mino",
    "gn:country_code":"RU",
    "gn:dem":172,
    "gn:feature_class":"P",
    "gn:feature_code":"PPL",
    "gn:name":"Kuz\u2019mino",
    "gn:population":0,
    "gn:timezone":"Asia/Yekaterinburg",
    "iso:country":"RU",
    "name:rus_x_preferred":[
        "\u041a\u0443\u0437\u044c\u043c\u0438\u043d\u043e"
    ],
    "name:und_x_variant":[
        "Kuz\u2019mina",
        "Kuz\u2019mino"
    ],
    "wof:name":"Kuz'mino",
    "wof:placetype":"locality"
},
  "geometry": {"coordinates":[54.3499,59.707],"type":"Point"}
}