{
  "type": "Feature",
  "properties": {
    "gn:admin1_code":"88",
    "gn:asciiname":"Vorygino",
    "gn:country_code":"RU",
    "gn:dem":106,
    "gn:feature_class":"P",
    "gn:feature_code":"PPL",
    "gn:name":"Vorygino",
    "gn:population":0,
    "gn:timezone":"Europe/Moscow",
    "iso:country":"RU",
    "name:rus_x_preferred":[
        "\u0412\u043e\u0440\u044b\u0433\u0438\u043d\u043e"
    ],
    "wof:name":"Vorygino",
    "wof:placetype":"locality"
},
  "geometry": {"coordinates":[38.63276,58.08362],"type":"Point"}
}