{
  "type": "Feature",
  "properties": {
    "gn:admin1_code":"73",
    "gn:asciiname":"Bikchurayevo",
    "gn:country_code":"RU",
    "gn:dem":108,
    "gn:feature_class":"P",
    "gn:feature_code":"PPL",
    "gn:name":"Bikchurayevo",
    "gn:population":0,
    "gn:timezone":"Europe/Moscow",
    "iso:country":"RU",
    "name:rus_x_preferred":[
        "\u0411\u0438\u043a\u0447\u0443\u0440\u0430\u0435\u0432\u043e"
    ],
    "wof:name":"Bikchurayevo",
    "wof:placetype":"locality"
},
  "geometry": {"coordinates":[50.68783,55.66182],"type":"Point"}
}