{
  "type": "Feature",
  "properties": {
    "gn:admin1_code":"78",
    "gn:asciiname":"Achimovo",
    "gn:country_code":"RU",
    "gn:dem":94,
    "gn:feature_class":"P",
    "gn:feature_code":"PPL",
    "gn:name":"Achimovo",
    "gn:population":0,
    "gn:timezone":"Asia/Yekaterinburg",
    "iso:country":"RU",
    "name:eng_x_preferred":[
        "Achimovo"
    ],
    "name:nor_x_preferred":[
        "Atsjimovo"
    ],
    "name:rus_x_preferred":[
        "\u0410\u0447\u0438\u043c\u043e\u0432\u043e"
    ],
    "wof:name":"Achimovo",
    "wof:placetype":"locality"
},
  "geometry": {"coordinates":[71.34365,56.8032],"type":"Point"}
}