{
  "type": "Feature",
  "properties": {
    "gn:admin1_code":"53.0",
    "gn:asciiname":"Krasnoglinnoye",
    "gn:country_code":"RU",
    "gn:dem":106,
    "gn:feature_class":"P",
    "gn:feature_code":"PPL",
    "gn:name":"Krasnoglinnoye",
    "gn:population":0,
    "gn:timezone":"Asia/Novosibirsk",
    "iso:country":"RU",
    "name:rus_x_preferred":[
        "\u041a\u0440\u0430\u0441\u043d\u043e\u0433\u043b\u0438\u043d\u043d\u043e\u0435"
    ],
    "wof:name":"Krasnoglinnoye",
    "wof:placetype":"locality"
},
  "geometry": {"coordinates":[82.70269999999999,54.9684],"type":"Point"}
}