{
  "type": "Feature",
  "properties": {
    "gn:admin1_code":"29",
    "gn:asciiname":"Pochitanka",
    "gn:country_code":"RU",
    "gn:dem":220,
    "gn:feature_class":"P",
    "gn:feature_code":"PPL",
    "gn:name":"Pochitanka",
    "gn:population":0,
    "gn:timezone":"Asia/Novokuznetsk",
    "iso:country":"RU",
    "name:eng_x_preferred":[
        "Pochitanka"
    ],
    "name:nor_x_preferred":[
        "Potsjitanka"
    ],
    "name:rus_x_preferred":[
        "\u041f\u043e\u0447\u0438\u0442\u0430\u043d\u043a\u0430"
    ],
    "name:und_x_variant":[
        "Bol\u2019she-Pochitanskoye",
        "Verkhnyaya Pochitanka",
        "\u041f\u043e\u0447\u0438\u0442\u0430\u043d\u043a\u0430",
        "Pochitanka"
    ],
    "wof:name":"Pochitanka",
    "wof:placetype":"locality"
},
  "geometry": {"coordinates":[86.6962,56.28782],"type":"Point"}
}