{
  "type": "Feature",
  "properties": {
    "gn:admin1_code":"42",
    "gn:asciiname":"Maklakovo",
    "gn:country_code":"RU",
    "gn:dem":138,
    "gn:feature_class":"P",
    "gn:feature_code":"PPL",
    "gn:name":"Maklakovo",
    "gn:population":0,
    "gn:timezone":"Europe/Moscow",
    "iso:country":"RU",
    "name:fin_x_preferred":[
        "Maklakkova"
    ],
    "name:nor_x_preferred":[
        "Maklakovo"
    ],
    "name:rus_x_preferred":[
        "\u041c\u0430\u043a\u043b\u0430\u043a\u043e\u0432\u043e"
    ],
    "name:und_x_variant":[
        "Maklakova"
    ],
    "wof:name":"Maklakovo",
    "wof:placetype":"locality"
},
  "geometry": {"coordinates":[29.06139000000001,59.64809],"type":"Point"}
}