{
  "type": "Feature",
  "properties": {
    "gn:admin1_code":"91",
    "gn:asciiname":"Sulomay",
    "gn:cc2":"RU",
    "gn:country_code":"RU",
    "gn:dem":41,
    "gn:feature_class":"P",
    "gn:feature_code":"PPL",
    "gn:name":"Sulomay",
    "gn:population":0,
    "gn:timezone":"Asia/Krasnoyarsk",
    "iso:country":"RU",
    "name:eng_x_preferred":[
        "Sulomay"
    ],
    "name:nor_x_preferred":[
        "Sulomaj"
    ],
    "name:rus_x_preferred":[
        "\u0421\u0443\u043b\u043e\u043c\u0430\u0439"
    ],
    "name:und_x_variant":[
        "Ch\u00ebrnyy Ostrov",
        "Sulamay"
    ],
    "wof:name":"Sulomay",
    "wof:placetype":"locality"
},
  "geometry": {"coordinates":[91.18639,61.61639],"type":"Point"}
}