{
  "type": "Feature",
  "properties": {
    "gn:admin1_code":"17.0",
    "gn:asciiname":"Karaman Vtoroy",
    "gn:country_code":"RU",
    "gn:dem":-22,
    "gn:feature_class":"P",
    "gn:feature_code":"PPL",
    "gn:name":"Karaman Vtoroy",
    "gn:population":0,
    "gn:timezone":"Europe/Moscow",
    "iso:country":"RU",
    "name:rus_x_preferred":[
        "\u041a\u0430\u0440\u0430\u043c\u0430\u043d \u0412\u0442\u043e\u0440\u043e\u0439"
    ],
    "wof:name":"Karaman Vtoroy",
    "wof:placetype":"locality"
},
  "geometry": {"coordinates":[47.48111,43.17417],"type":"Point"}
}