{
  "type": "Feature",
  "properties": {
    "gn:admin1_code":"54",
    "gn:asciiname":"Kulany",
    "gn:country_code":"RU",
    "gn:dem":99,
    "gn:feature_class":"P",
    "gn:feature_code":"PPL",
    "gn:name":"Kulany",
    "gn:population":0,
    "gn:timezone":"Asia/Omsk",
    "iso:country":"RU",
    "name:ceb_x_preferred":[
        "Kulany"
    ],
    "name:fra_x_preferred":[
        "Kulany"
    ],
    "name:pol_x_preferred":[
        "Kulany"
    ],
    "name:rus_x_preferred":[
        "\u041a\u0443\u043b\u0430\u043d\u044b"
    ],
    "name:ukr_x_preferred":[
        "\u041a\u0443\u043b\u044f\u043d\u0438"
    ],
    "name:und_x_variant":[
        "\u041a\u0443\u043b\u0430\u043d\u044b"
    ],
    "wof:name":"Kulany",
    "wof:placetype":"locality"
},
  "geometry": {"coordinates":[75.26666999999998,54.38333000000001],"type":"Point"}
}