{
  "type": "Feature",
  "properties": {
    "gn:admin1_code":"33",
    "gn:asciiname":"Brod",
    "gn:country_code":"RU",
    "gn:dem":129,
    "gn:feature_class":"P",
    "gn:feature_code":"PPL",
    "gn:name":"Brod",
    "gn:population":0,
    "gn:timezone":"Europe/Kirov",
    "iso:country":"RU",
    "name:bel_x_preferred":[
        "\u0411\u0440\u043e\u0434"
    ],
    "name:bos_x_preferred":[
        "Brod"
    ],
    "name:bul_x_preferred":[
        "\u0411\u0440\u043e\u0434"
    ],
    "name:ceb_x_preferred":[
        "Brod"
    ],
    "name:ces_x_preferred":[
        "Brod"
    ],
    "name:deu_x_preferred":[
        "Brod"
    ],
    "name:fas_x_preferred":[
        "\u0628\u0631\u0627\u062f"
    ],
    "name:fra_x_preferred":[
        "Brod"
    ],
    "name:heb_x_preferred":[
        "\u05d1\u05e8\u05d5\u05d3"
    ],
    "name:hrv_x_preferred":[
        "Brod"
    ],
    "name:hun_x_preferred":[
        "Brod"
    ],
    "name:hye_x_preferred":[
        "\u0532\u0580\u0578\u0564"
    ],
    "name:ita_x_preferred":[
        "Brod"
    ],
    "name:kor_x_preferred":[
        "\ube0c\ub85c\ub4dc"
    ],
    "name:lit_x_preferred":[
        "Brodas"
    ],
    "name:mkd_x_preferred":[
        "\u0411\u0440\u043e\u0434"
    ],
    "name:nld_x_preferred":[
        "Brod"
    ],
    "name:pol_x_preferred":[
        "Brod"
    ],
    "name:por_x_preferred":[
        "Brod"
    ],
    "name:ron_x_preferred":[
        "Brod"
    ],
    "name:rue_x_preferred":[
        "\u0411\u0440\u043e\u0434"
    ],
    "name:rus_x_preferred":[
        "\u0411\u0440\u043e\u0434"
    ],
    "name:slk_x_preferred":[
        "Brod"
    ],
    "name:slv_x_preferred":[
        "Brod"
    ],
    "name:srp_x_preferred":[
        "\u0411\u0440\u043e\u0434"
    ],
    "name:swe_x_preferred":[
        "Brod"
    ],
    "name:ukr_x_preferred":[
        "\u0411\u0440\u043e\u0434"
    ],
    "wof:name":"Brod",
    "wof:placetype":"locality"
},
  "geometry": {"coordinates":[49.2396,57.0687],"type":"Point"}
}