{
  "type": "Feature",
  "properties": {
    "gn:admin1_code":"38",
    "gn:asciiname":"Dvoynoye",
    "gn:country_code":"RU",
    "gn:dem":150,
    "gn:feature_class":"P",
    "gn:feature_code":"PPL",
    "gn:name":"Dvoynoye",
    "gn:population":0,
    "gn:timezone":"Europe/Moscow",
    "iso:country":"RU",
    "name:rus_x_preferred":[
        "\u0414\u0432\u043e\u0439\u043d\u043e\u0435"
    ],
    "wof:name":"Dvoynoye",
    "wof:placetype":"locality"
},
  "geometry": {"coordinates":[40.91333,45.20722],"type":"Point"}
}