{
  "type": "Feature",
  "properties": {
    "gn:admin1_code":"8.0",
    "gn:asciiname":"Aktuganovo",
    "gn:country_code":"RU",
    "gn:dem":103,
    "gn:feature_class":"P",
    "gn:feature_code":"PPL",
    "gn:name":"Aktuganovo",
    "gn:population":0,
    "gn:timezone":"Asia/Yekaterinburg",
    "iso:country":"RU",
    "name:nor_x_preferred":[
        "Aktuganovo"
    ],
    "name:rus_x_preferred":[
        "\u0410\u043a\u0442\u0443\u0433\u0430\u043d\u043e\u0432\u043e"
    ],
    "wof:name":"Aktuganovo",
    "wof:placetype":"locality"
},
  "geometry": {"coordinates":[55.31498000000001,55.99497],"type":"Point"}
}