{
  "type": "Feature",
  "properties": {
    "gn:admin1_code":"55",
    "gn:asciiname":"Krasnaya Slobodka",
    "gn:country_code":"RU",
    "gn:dem":182,
    "gn:feature_class":"P",
    "gn:feature_code":"PPL",
    "gn:name":"Krasnaya Slobodka",
    "gn:population":0,
    "gn:timezone":"Asia/Yekaterinburg",
    "iso:country":"RU",
    "name:eng_x_preferred":[
        "Krasnaya Slobodka"
    ],
    "name:nor_x_preferred":[
        "Krasnaja Slobodka"
    ],
    "name:rus_x_preferred":[
        "\u041a\u0440\u0430\u0441\u043d\u0430\u044f \u0421\u043b\u043e\u0431\u043e\u0434\u043a\u0430"
    ],
    "name:und_x_variant":[
        "Krasnaya Sloboda"
    ],
    "wof:name":"Krasnaya Slobodka",
    "wof:placetype":"locality"
},
  "geometry": {"coordinates":[52.51989,53.22746],"type":"Point"}
}