{
  "type": "Feature",
  "properties": {
    "gn:admin1_code":"23",
    "gn:asciiname":"Kuybyshevo",
    "gn:country_code":"RU",
    "gn:dem":52,
    "gn:feature_class":"P",
    "gn:feature_code":"PPL",
    "gn:name":"Kuybyshevo",
    "gn:population":0,
    "gn:timezone":"Europe/Kaliningrad",
    "iso:country":"RU",
    "name:rus_x_preferred":[
        "\u041a\u0443\u0439\u0431\u044b\u0448\u0435\u0432\u043e"
    ],
    "name:und_x_variant":[
        "\u041a\u0443\u0439\u0431\u044b\u0448\u0435\u0432\u043e"
    ],
    "wof:name":"Kuybyshevo",
    "wof:placetype":"locality"
},
  "geometry": {"coordinates":[22.055,54.91806],"type":"Point"}
}