{
  "type": "Feature",
  "properties": {
    "gn:admin1_code":"32",
    "gn:asciiname":"Polnovat",
    "gn:cc2":"RU",
    "gn:country_code":"RU",
    "gn:dem":6,
    "gn:feature_class":"P",
    "gn:feature_code":"PPL",
    "gn:name":"Polnovat",
    "gn:population":0,
    "gn:timezone":"Asia/Yekaterinburg",
    "iso:country":"RU",
    "name:eng_x_preferred":[
        "Polnovat"
    ],
    "name:nor_x_preferred":[
        "Polnovat"
    ],
    "name:rus_x_preferred":[
        "\u041f\u043e\u043b\u043d\u043e\u0432\u0430\u0442"
    ],
    "name:und_x_variant":[
        "Polnovatskiye",
        "\u041f\u043e\u043b\u043d\u043e\u0432\u0430\u0442",
        "Polnovat"
    ],
    "wof:name":"Polnovat",
    "wof:placetype":"locality"
},
  "geometry": {"coordinates":[65.90916999999999,63.78833],"type":"Point"}
}