{
  "type": "Feature",
  "properties": {
    "gn:admin1_code":"60",
    "gn:asciiname":"Slavno",
    "gn:country_code":"RU",
    "gn:dem":206,
    "gn:feature_class":"P",
    "gn:feature_code":"PPL",
    "gn:name":"Slavno",
    "gn:population":0,
    "gn:timezone":"Europe/Moscow",
    "iso:country":"RU",
    "name:rus_x_preferred":[
        "\u0421\u043b\u0430\u0432\u043d\u043e"
    ],
    "name:und_x_variant":[
        "\u0421\u043b\u0430\u0432\u043d\u043e"
    ],
    "wof:name":"Slavno",
    "wof:placetype":"locality"
},
  "geometry": {"coordinates":[29.5214,56.8523],"type":"Point"}
}