{
  "type": "Feature",
  "properties": {
    "gn:admin1_code":"42",
    "gn:asciiname":"Svinyye Golovy",
    "gn:country_code":"RU",
    "gn:dem":73,
    "gn:feature_class":"P",
    "gn:feature_code":"PPL",
    "gn:name":"Svinyye Golovy",
    "gn:population":0,
    "gn:timezone":"Europe/Moscow",
    "iso:country":"RU",
    "wof:name":"Svinyye Golovy",
    "wof:placetype":"locality"
},
  "geometry": {"coordinates":[28.35,59.08333],"type":"Point"}
}