{
  "type": "Feature",
  "properties": {
    "gn:admin1_code":"61",
    "gn:asciiname":"Rodniki",
    "gn:country_code":"RU",
    "gn:dem":43,
    "gn:feature_class":"P",
    "gn:feature_code":"PPL",
    "gn:name":"Rodniki",
    "gn:population":0,
    "gn:timezone":"Europe/Moscow",
    "iso:country":"RU",
    "name:eng_x_preferred":[
        "Rodniki"
    ],
    "name:nor_x_preferred":[
        "Rodniki"
    ],
    "name:rus_x_preferred":[
        "\u0420\u043e\u0434\u043d\u0438\u043a\u0438"
    ],
    "name:sco_x_preferred":[
        "Rodniki"
    ],
    "wof:name":"Rodniki",
    "wof:placetype":"locality"
},
  "geometry": {"coordinates":[40.22479000000001,46.9614],"type":"Point"}
}