{
  "type": "Feature",
  "properties": {
    "gn:admin1_code":"77",
    "gn:asciiname":"Lutkovo",
    "gn:country_code":"RU",
    "gn:dem":157,
    "gn:feature_class":"P",
    "gn:feature_code":"PPL",
    "gn:name":"Lutkovo",
    "gn:population":0,
    "gn:timezone":"Europe/Moscow",
    "iso:country":"RU",
    "name:rus_x_preferred":[
        "\u041b\u0443\u0442\u043a\u043e\u0432\u043e"
    ],
    "wof:name":"Lutkovo",
    "wof:placetype":"locality"
},
  "geometry": {"coordinates":[34.51667,57.81667],"type":"Point"}
}