{
  "type": "Feature",
  "properties": {
    "gn:admin1_code":"59",
    "gn:asciiname":"Maloye-Tal'mi",
    "gn:country_code":"RU",
    "gn:dem":21,
    "gn:feature_class":"P",
    "gn:feature_code":"PPL",
    "gn:name":"Maloye-Tal'mi",
    "gn:population":0,
    "gn:timezone":"Asia/Vladivostok",
    "iso:country":"RU",
    "wof:name":"Maloye-Tal'mi",
    "wof:placetype":"locality"
},
  "geometry": {"coordinates":[130.67306000000002,42.49278],"type":"Point"}
}