{
  "type": "Feature",
  "properties": {
    "gn:admin1_code":"60",
    "gn:asciiname":"Balandino",
    "gn:country_code":"RU",
    "gn:dem":99,
    "gn:feature_class":"P",
    "gn:feature_code":"PPL",
    "gn:name":"Balandino",
    "gn:population":0,
    "gn:timezone":"Europe/Moscow",
    "iso:country":"RU",
    "name:che_x_preferred":[
        "\u0411\u0430\u043b\u0430\u043d\u0434\u0438\u043d\u043e"
    ],
    "name:rus_x_preferred":[
        "\u0411\u0430\u043b\u0430\u043d\u0434\u0438\u043d\u043e"
    ],
    "wof:name":"Balandino",
    "wof:placetype":"locality"
},
  "geometry": {"coordinates":[30.6058,56.3667],"type":"Point"}
}