{
  "type": "Feature",
  "properties": {
    "gn:admin1_code":"38",
    "gn:asciiname":"Prirechnyy",
    "gn:country_code":"RU",
    "gn:dem":134,
    "gn:feature_class":"P",
    "gn:feature_code":"PPL",
    "gn:name":"Prirechnyy",
    "gn:population":0,
    "gn:timezone":"Europe/Moscow",
    "iso:country":"RU",
    "name:rus_x_preferred":[
        "\u041f\u0440\u0438\u0440\u0435\u0447\u043d\u044b\u0439"
    ],
    "name:und_x_variant":[
        "\u041f\u0440\u0438\u0440\u0435\u0447\u043d\u044b\u0439"
    ],
    "wof:name":"Prirechnyy",
    "wof:placetype":"locality"
},
  "geometry": {"coordinates":[39.9004,44.72189],"type":"Point"}
}