{
  "type": "Feature",
  "properties": {
    "gn:admin1_code":"13.0",
    "gn:asciiname":"Aul-Butak",
    "gn:country_code":"RU",
    "gn:dem":364,
    "gn:feature_class":"P",
    "gn:feature_code":"PPL",
    "gn:name":"Aul-Butak",
    "gn:population":0,
    "gn:timezone":"Asia/Yekaterinburg",
    "iso:country":"RU",
    "name:nor_x_preferred":[
        "Aul-Butak"
    ],
    "name:rus_x_preferred":[
        "\u0410\u0443\u043b-\u0411\u0443\u0442\u0430\u043a"
    ],
    "wof:name":"Aul-Butak",
    "wof:placetype":"locality"
},
  "geometry": {"coordinates":[59.81667,52.61666999999999],"type":"Point"}
}