{
  "type": "Feature",
  "properties": {
    "gn:admin1_code":"55",
    "gn:asciiname":"Rubezhinskiy",
    "gn:cc2":"RU",
    "gn:country_code":"RU",
    "gn:dem":95,
    "gn:feature_class":"P",
    "gn:feature_code":"PPL",
    "gn:name":"Rubezhinskiy",
    "gn:population":0,
    "gn:timezone":"Asia/Yekaterinburg",
    "iso:country":"RU",
    "name:eng_x_preferred":[
        "Rubezhinskiy"
    ],
    "name:nor_x_preferred":[
        "Rubezjinskij"
    ],
    "name:rus_x_preferred":[
        "\u0420\u0443\u0431\u0435\u0436\u0438\u043d\u0441\u043a\u0438\u0439"
    ],
    "name:und_x_variant":[
        "Kargala"
    ],
    "wof:name":"Rubezhinskiy",
    "wof:placetype":"locality"
},
  "geometry": {"coordinates":[52.11972,51.74389],"type":"Point"}
}