{
  "type": "Feature",
  "properties": {
    "gn:admin1_code":"62",
    "gn:asciiname":"Mokhovoye",
    "gn:country_code":"RU",
    "gn:dem":166,
    "gn:feature_class":"P",
    "gn:feature_code":"PPL",
    "gn:name":"Mokhovoye",
    "gn:population":0,
    "gn:timezone":"Europe/Moscow",
    "iso:country":"RU",
    "name:rus_x_preferred":[
        "\u041c\u043e\u0445\u043e\u0432\u043e\u0435"
    ],
    "wof:name":"Mokhovoye",
    "wof:placetype":"locality"
},
  "geometry": {"coordinates":[39.59925,53.95611],"type":"Point"}
}