{
  "type": "Feature",
  "properties": {
    "gn:admin1_code":"65",
    "gn:asciiname":"Suponevo",
    "gn:country_code":"RU",
    "gn:dem":71,
    "gn:feature_class":"P",
    "gn:feature_code":"PPL",
    "gn:name":"Suponevo",
    "gn:population":0,
    "gn:timezone":"Europe/Samara",
    "iso:country":"RU",
    "name:eng_x_preferred":[
        "Suponevo"
    ],
    "name:nor_x_preferred":[
        "Suponevo"
    ],
    "name:rus_x_preferred":[
        "\u0421\u0443\u043f\u043e\u043d\u0435\u0432\u043e"
    ],
    "name:und_x_variant":[
        "\u0421\u0443\u043f\u043e\u043d\u0435\u0432\u043e",
        "Suponevo"
    ],
    "wof:name":"Suponevo",
    "wof:placetype":"locality"
},
  "geometry": {"coordinates":[50.56945,54.23911999999999],"type":"Point"}
}