{
  "type": "Feature",
  "properties": {
    "gn:admin1_code":"33",
    "gn:asciiname":"Nagoryany",
    "gn:country_code":"RU",
    "gn:dem":159,
    "gn:feature_class":"P",
    "gn:feature_code":"PPL",
    "gn:name":"Nagoryany",
    "gn:population":0,
    "gn:timezone":"Europe/Kirov",
    "iso:country":"RU",
    "name:rus_x_preferred":[
        "\u041d\u0430\u0433\u043e\u0440\u044f\u043d\u044b"
    ],
    "wof:name":"Nagoryany",
    "wof:placetype":"locality"
},
  "geometry": {"coordinates":[49.76667,58.68333000000001],"type":"Point"}
}