{
  "type": "Feature",
  "properties": {
    "gn:admin1_code":"8",
    "gn:asciiname":"Malyy Buzat",
    "gn:country_code":"RU",
    "gn:dem":341,
    "gn:feature_class":"P",
    "gn:feature_code":"PPL",
    "gn:name":"Malyy Buzat",
    "gn:population":0,
    "gn:timezone":"Asia/Yekaterinburg",
    "iso:country":"RU",
    "name:rus_x_preferred":[
        "\u041c\u0430\u043b\u044b\u0439 \u0411\u0443\u0437\u0430\u0442"
    ],
    "name:und_x_variant":[
        "\u041c\u0430\u043b\u044b\u0439 \u0411\u0443\u0437\u0430\u0442"
    ],
    "wof:name":"Malyy Buzat",
    "wof:placetype":"locality"
},
  "geometry": {"coordinates":[54.71666999999999,53.31667],"type":"Point"}
}