{
  "type": "Feature",
  "properties": {
    "gn:admin1_code":"90",
    "gn:asciiname":"Verkhnyaya Lop'ya",
    "gn:country_code":"RU",
    "gn:dem":185,
    "gn:feature_class":"P",
    "gn:feature_code":"PPL",
    "gn:name":"Verkhnyaya Lop\u2019ya",
    "gn:population":0,
    "gn:timezone":"Asia/Yekaterinburg",
    "iso:country":"RU",
    "wof:name":"Verkhnyaya Lop'ya",
    "wof:placetype":"locality"
},
  "geometry": {"coordinates":[55.62902,60.94859],"type":"Point"}
}