{
  "type": "Feature",
  "properties": {
    "gn:admin1_code":"85",
    "gn:asciiname":"Vysokovo Pervoye",
    "gn:country_code":"RU",
    "gn:dem":169,
    "gn:feature_class":"P",
    "gn:feature_code":"PPL",
    "gn:name":"Vysokovo Pervoye",
    "gn:population":0,
    "gn:timezone":"Europe/Moscow",
    "iso:country":"RU",
    "name:rus_x_preferred":[
        "\u0412\u044b\u0441\u043e\u043a\u043e\u0432\u043e \u041f\u0435\u0440\u0432\u043e\u0435"
    ],
    "name:und_x_variant":[
        "\u0412\u044b\u0441\u043e\u043a\u043e\u0432\u043e \u041f\u0435\u0440\u0432\u043e\u0435",
        "Vysokovo"
    ],
    "wof:name":"Vysokovo Pervoye",
    "wof:placetype":"locality"
},
  "geometry": {"coordinates":[39.1924,59.4757],"type":"Point"}
}