{
  "type": "Feature",
  "properties": {
    "gn:admin1_code":"41",
    "gn:asciiname":"Osinovyy",
    "gn:country_code":"RU",
    "gn:dem":205,
    "gn:feature_class":"P",
    "gn:feature_code":"PPL",
    "gn:name":"Osinovyy",
    "gn:population":0,
    "gn:timezone":"Europe/Moscow",
    "iso:country":"RU",
    "name:rus_x_preferred":[
        "\u041e\u0441\u0438\u043d\u043e\u0432\u044b\u0439"
    ],
    "name:und_x_variant":[
        "\u041e\u0441\u0438\u043d\u043e\u0432\u044b\u0439"
    ],
    "wof:name":"Osinovyy",
    "wof:placetype":"locality"
},
  "geometry": {"coordinates":[36.15861,52.225],"type":"Point"}
}