{
  "type": "Feature",
  "properties": {
    "gn:admin1_code":"40",
    "gn:asciiname":"Malysheva",
    "gn:country_code":"RU",
    "gn:dem":176,
    "gn:feature_class":"P",
    "gn:feature_code":"PPL",
    "gn:name":"Malysheva",
    "gn:population":0,
    "gn:timezone":"Asia/Yekaterinburg",
    "iso:country":"RU",
    "name:rus_x_preferred":[
        "\u041c\u0430\u043b\u044b\u0448\u0435\u0432\u0430"
    ],
    "wof:name":"Malysheva",
    "wof:placetype":"locality"
},
  "geometry": {"coordinates":[63.42278,54.92944],"type":"Point"}
}