{
  "type": "Feature",
  "properties": {
    "gn:admin1_code":"73",
    "gn:asciiname":"Stepnoye",
    "gn:country_code":"RU",
    "gn:dem":80,
    "gn:feature_class":"P",
    "gn:feature_code":"PPL",
    "gn:name":"Stepnoye",
    "gn:population":0,
    "gn:timezone":"Europe/Moscow",
    "iso:country":"RU",
    "name:rus_x_preferred":[
        "\u0421\u0442\u0435\u043f\u043d\u043e\u0435"
    ],
    "name:und_x_variant":[
        "Stepnoye Ozero",
        "Stepnoye",
        "\u0421\u0442\u0435\u043f\u043d\u043e\u0435"
    ],
    "wof:name":"Stepnoye",
    "wof:placetype":"locality"
},
  "geometry": {"coordinates":[50.93039,54.39214000000001],"type":"Point"}
}