{
  "type": "Feature",
  "properties": {
    "gn:admin1_code":"41.0",
    "gn:asciiname":"Kirsanovka",
    "gn:country_code":"RU",
    "gn:dem":218,
    "gn:feature_class":"P",
    "gn:feature_code":"PPL",
    "gn:name":"Kirsanovka",
    "gn:population":0,
    "gn:timezone":"Europe/Moscow",
    "iso:country":"RU",
    "name:rus_x_preferred":[
        "\u041a\u0438\u0440\u0441\u0430\u043d\u043e\u0432\u043a\u0430"
    ],
    "name:und_x_variant":[
        "\u041a\u0438\u0440\u0441\u0430\u043d\u043e\u0432\u043a\u0430"
    ],
    "wof:name":"Kirsanovka",
    "wof:placetype":"locality"
},
  "geometry": {"coordinates":[36.94194,51.95333],"type":"Point"}
}