{
  "type": "Feature",
  "properties": {
    "gn:admin1_code":"61",
    "gn:asciiname":"Nizhne-Gvozdikov",
    "gn:country_code":"RU",
    "gn:dem":95,
    "gn:feature_class":"P",
    "gn:feature_code":"PPL",
    "gn:name":"Nizhne-Gvozdikov",
    "gn:population":0,
    "gn:timezone":"Europe/Moscow",
    "iso:country":"RU",
    "name:eng_x_preferred":[
        "Ob\u201dyedin\u00ebnnyy"
    ],
    "name:nor_x_preferred":[
        "Objedinennyj"
    ],
    "name:rus_x_preferred":[
        "\u041e\u0431\u044a\u0435\u0434\u0438\u043d\u0435\u043d\u043d\u044b\u0439"
    ],
    "name:rus_x_variant":[
        "\u041e\u0431\u044a\u0435\u0434\u0438\u043d\u0451\u043d\u043d\u044b\u0439"
    ],
    "name:und_x_variant":[
        "Ob\u2019yedinenny",
        "Ob\u201dyedin\u00ebnnyy",
        "\u041e\u0431\u044a\u0435\u0434\u0438\u043d\u0451\u043d\u043d\u044b\u0439"
    ],
    "wof:name":"Nizhne-Gvozdikov",
    "wof:placetype":"locality"
},
  "geometry": {"coordinates":[40.44948,46.61168],"type":"Point"}
}