{
  "type": "Feature",
  "properties": {
    "gn:admin1_code":"8.0",
    "gn:asciiname":"Berdyash",
    "gn:country_code":"RU",
    "gn:dem":497,
    "gn:feature_class":"P",
    "gn:feature_code":"PPL",
    "gn:name":"Berdyash",
    "gn:population":0,
    "gn:timezone":"Asia/Yekaterinburg",
    "iso:country":"RU",
    "name:bak_x_preferred":[
        "\u0411\u0438\u0440\u0499\u04d9\u0448"
    ],
    "name:che_x_preferred":[
        "\u0411\u0435\u0440\u0434\u044f\u0448"
    ],
    "name:chv_x_preferred":[
        "\u041f\u0435\u0440\u0442\u0435\u0448"
    ],
    "name:eng_x_preferred":[
        "Berdyash"
    ],
    "name:hye_x_preferred":[
        "\u0532\u0565\u0580\u0564\u0575\u0561\u0577"
    ],
    "name:kat_x_preferred":[
        "\u10d1\u10d4\u10e0\u10d3\u10d8\u10d0\u10e8\u10d8"
    ],
    "name:kaz_x_preferred":[
        "\u0411\u0435\u0440\u0434\u044f\u0448"
    ],
    "name:kir_x_preferred":[
        "\u0411\u0435\u0440\u0434\u044f\u0448"
    ],
    "name:nor_x_preferred":[
        "Berdjasj"
    ],
    "name:rus_x_preferred":[
        "\u0411\u0435\u0440\u0434\u044f\u0448"
    ],
    "name:tat_x_preferred":[
        "\u0411\u0438\u0440\u0434\u04d9\u0448"
    ],
    "name:ukr_x_preferred":[
        "\u0411\u0435\u0440\u0434\u044f\u0448"
    ],
    "wof:name":"Berdyash",
    "wof:placetype":"locality"
},
  "geometry": {"coordinates":[57.2066,52.1775],"type":"Point"}
}