{
  "type": "Feature",
  "properties": {
    "gn:admin1_code":"8.0",
    "gn:asciiname":"Berdyash",
    "gn:country_code":"RU",
    "gn:dem":497,
    "gn:feature_class":"P",
    "gn:feature_code":"PPL",
    "gn:name":"Berdyash",
    "gn:population":0,
    "gn:timezone":"Asia/Yekaterinburg",
    "iso:country":"RU",
    "name:eng_x_preferred":[
        "Berdyash"
    ],
    "name:nor_x_preferred":[
        "Berdjasj"
    ],
    "name:rus_x_preferred":[
        "\u0411\u0435\u0440\u0434\u044f\u0448"
    ],
    "name:und_x_variant":[
        "\u0411\u0435\u0440\u0434\u044f\u0448",
        "Berdyash"
    ],
    "wof:name":"Berdyash",
    "wof:placetype":"locality"
},
  "geometry": {"coordinates":[57.2066,52.1775],"type":"Point"}
}