{
  "type": "Feature",
  "properties": {
    "gn:admin1_code":"45",
    "gn:asciiname":"Sautkino",
    "gn:country_code":"RU",
    "gn:dem":86,
    "gn:feature_class":"P",
    "gn:feature_code":"PPL",
    "gn:name":"Sautkino",
    "gn:population":0,
    "gn:timezone":"Europe/Moscow",
    "iso:country":"RU",
    "name:rus_x_preferred":[
        "\u0421\u0430\u0443\u0442\u043a\u0438\u043d\u043e"
    ],
    "wof:name":"Sautkino",
    "wof:placetype":"locality"
},
  "geometry": {"coordinates":[46.7364,56.1873],"type":"Point"}
}