{
  "type": "Feature",
  "properties": {
    "gn:admin1_code":"51.0",
    "gn:asciiname":"Fedoseyevo",
    "gn:country_code":"RU",
    "gn:dem":127,
    "gn:feature_class":"P",
    "gn:feature_code":"PPL",
    "gn:name":"Fedoseyevo",
    "gn:population":0,
    "gn:timezone":"Europe/Moscow",
    "iso:country":"RU",
    "name:rus_x_preferred":[
        "\u0424\u0435\u0434\u043e\u0441\u0435\u0435\u0432\u043e"
    ],
    "name:und_x_variant":[
        "\u0424\u0435\u0434\u043e\u0441\u0435\u0435\u0432\u043e"
    ],
    "wof:name":"Fedoseyevo",
    "wof:placetype":"locality"
},
  "geometry": {"coordinates":[44.42174,56.86223],"type":"Point"}
}