{
  "type": "Feature",
  "properties": {
    "gn:admin1_code":"51",
    "gn:asciiname":"Malaya Lumar'",
    "gn:country_code":"RU",
    "gn:dem":117,
    "gn:feature_class":"P",
    "gn:feature_code":"PPL",
    "gn:name":"Malaya Lumar\u2019",
    "gn:population":0,
    "gn:timezone":"Europe/Moscow",
    "iso:country":"RU",
    "name:rus_x_preferred":[
        "\u041c\u0430\u043b\u0430\u044f \u041b\u0443\u043c\u0430\u0440\u044c"
    ],
    "name:und_x_variant":[
        "Malaya Lumar\u2019"
    ],
    "wof:name":"Malaya Lumar'",
    "wof:placetype":"locality"
},
  "geometry": {"coordinates":[47.4767,57.6178],"type":"Point"}
}