{
  "type": "Feature",
  "properties": {
    "gn:admin1_code":"20",
    "gn:asciiname":"Ulus Khogoto-Tarasa",
    "gn:country_code":"RU",
    "gn:dem":515,
    "gn:feature_class":"P",
    "gn:feature_code":"PPL",
    "gn:name":"Ulus Khogoto-Tarasa",
    "gn:population":0,
    "gn:timezone":"Asia/Irkutsk",
    "iso:country":"RU",
    "name:und_x_variant":[
        "Khogota-Tarasa",
        "Khogoto-Tarasa",
        "Ulus Khogoto-Tarasa"
    ],
    "wof:name":"Ulus Khogoto-Tarasa",
    "wof:placetype":"locality"
},
  "geometry": {"coordinates":[103.90000000000001,53.05],"type":"Point"}
}