{
  "type": "Feature",
  "properties": {
    "gn:admin1_code":"51",
    "gn:asciiname":"Valki",
    "gn:country_code":"RU",
    "gn:dem":100,
    "gn:feature_class":"P",
    "gn:feature_code":"PPL",
    "gn:name":"Valki",
    "gn:population":0,
    "gn:timezone":"Europe/Moscow",
    "iso:country":"RU",
    "name:und_x_variant":[
        "Volki",
        "Valki"
    ],
    "wof:name":"Valki",
    "wof:placetype":"locality"
},
  "geometry": {"coordinates":[44.04529,56.60091],"type":"Point"}
}