{
  "type": "Feature",
  "properties": {
    "gn:admin1_code":"8",
    "gn:asciiname":"Ilyakshidy",
    "gn:country_code":"RU",
    "gn:dem":136,
    "gn:feature_class":"P",
    "gn:feature_code":"PPL",
    "gn:name":"Ilyakshidy",
    "gn:population":0,
    "gn:timezone":"Asia/Yekaterinburg",
    "iso:country":"RU",
    "name:rus_x_preferred":[
        "\u0418\u043b\u044f\u043a\u0448\u0438\u0434\u044b"
    ],
    "name:und_x_variant":[
        "\u0418\u043b\u044f\u043a\u0448\u0438\u0434\u044b"
    ],
    "wof:name":"Ilyakshidy",
    "wof:placetype":"locality"
},
  "geometry": {"coordinates":[54.59056,55.29083000000001],"type":"Point"}
}