{
  "type": "Feature",
  "properties": {
    "gn:admin1_code":"25.0",
    "gn:asciiname":"Chapayevka",
    "gn:country_code":"RU",
    "gn:dem":170,
    "gn:feature_class":"P",
    "gn:feature_code":"PPL",
    "gn:name":"Chapayevka",
    "gn:population":0,
    "gn:timezone":"Europe/Moscow",
    "iso:country":"RU",
    "name:eng_x_preferred":[
        "Chapayevka"
    ],
    "name:nor_x_preferred":[
        "Tsjapajevka"
    ],
    "name:rus_x_preferred":[
        "\u0427\u0430\u043f\u0430\u0435\u0432\u043a\u0430"
    ],
    "name:und_x_variant":[
        "Vshivka",
        "\u0427\u0430\u043f\u0430\u0435\u0432\u043a\u0430",
        "Chapayevka"
    ],
    "wof:name":"Chapayevka",
    "wof:placetype":"locality"
},
  "geometry": {"coordinates":[35.81766,54.62927],"type":"Point"}
}