{
  "type": "Feature",
  "properties": {
    "gn:admin1_code":"6",
    "gn:asciiname":"Samsonovo",
    "gn:country_code":"RU",
    "gn:dem":130,
    "gn:feature_class":"P",
    "gn:feature_code":"PPL",
    "gn:name":"Samsonovo",
    "gn:population":0,
    "gn:timezone":"Europe/Moscow",
    "iso:country":"RU",
    "name:rus_x_preferred":[
        "\u0421\u0430\u043c\u0441\u043e\u043d\u043e\u0432\u043e"
    ],
    "name:und_x_variant":[
        "\u0421\u0430\u043c\u0441\u043e\u043d\u043e\u0432\u043e"
    ],
    "wof:name":"Samsonovo",
    "wof:placetype":"locality"
},
  "geometry": {"coordinates":[38.749,61.00639],"type":"Point"}
}