{
  "type": "Feature",
  "properties": {
    "gn:admin1_code":"59",
    "gn:asciiname":"Yemel'yanovka",
    "gn:country_code":"RU",
    "gn:dem":60,
    "gn:feature_class":"P",
    "gn:feature_code":"PPL",
    "gn:name":"Yemel\u2019yanovka",
    "gn:population":0,
    "gn:timezone":"Asia/Vladivostok",
    "iso:country":"RU",
    "name:eng_x_preferred":[
        "Yemel'yanovka"
    ],
    "name:nor_x_preferred":[
        "Jemeljanovka"
    ],
    "name:rus_x_preferred":[
        "\u0415\u043c\u0435\u043b\u044c\u044f\u043d\u043e\u0432\u043a\u0430"
    ],
    "name:und_x_variant":[
        "Nemiriyanouka",
        "Yemel\u2019yanovka"
    ],
    "wof:name":"Yemel'yanovka",
    "wof:placetype":"locality"
},
  "geometry": {"coordinates":[134.04726000000002,46.36609],"type":"Point"}
}