{
  "type": "Feature",
  "properties": {
    "gn:admin1_code":"51.0",
    "gn:asciiname":"Serkovo",
    "gn:country_code":"RU",
    "gn:dem":97,
    "gn:feature_class":"P",
    "gn:feature_code":"PPL",
    "gn:name":"Serkovo",
    "gn:population":0,
    "gn:timezone":"Europe/Moscow",
    "iso:country":"RU",
    "name:nor_x_preferred":[
        "Serkovo"
    ],
    "name:rus_x_preferred":[
        "\u0421\u0435\u0440\u043a\u043e\u0432\u043e"
    ],
    "wof:name":"Serkovo",
    "wof:placetype":"locality"
},
  "geometry": {"coordinates":[43.51716,56.63043],"type":"Point"}
}