{
  "type": "Feature",
  "properties": {
    "gn:admin1_code":"47.0",
    "gn:asciiname":"Yegorovo",
    "gn:country_code":"RU",
    "gn:dem":134,
    "gn:feature_class":"P",
    "gn:feature_code":"PPL",
    "gn:name":"Yegorovo",
    "gn:population":0,
    "gn:timezone":"Europe/Moscow",
    "iso:country":"RU",
    "name:rus_x_preferred":[
        "\u0415\u0433\u043e\u0440\u043e\u0432\u043e"
    ],
    "wof:name":"Yegorovo",
    "wof:placetype":"locality"
},
  "geometry": {"coordinates":[37.94639,55.64556],"type":"Point"}
}