{
  "type": "Feature",
  "properties": {
    "gn:admin1_code":"56",
    "gn:asciiname":"Kamennyy Les",
    "gn:country_code":"RU",
    "gn:dem":202,
    "gn:feature_class":"P",
    "gn:feature_code":"PPL",
    "gn:name":"Kamennyy Les",
    "gn:population":0,
    "gn:timezone":"Europe/Moscow",
    "iso:country":"RU",
    "name:rus_x_preferred":[
        "\u041a\u0430\u043c\u0435\u043d\u043d\u044b\u0439 \u041b\u0435\u0441"
    ],
    "wof:name":"Kamennyy Les",
    "wof:placetype":"locality"
},
  "geometry": {"coordinates":[35.4229,52.5538],"type":"Point"}
}