{
  "type": "Feature",
  "properties": {
    "gn:admin1_code":"60.0",
    "gn:asciiname":"Glukhaya Gorushka",
    "gn:country_code":"RU",
    "gn:dem":87,
    "gn:feature_class":"P",
    "gn:feature_code":"PPL",
    "gn:name":"Glukhaya Gorushka",
    "gn:population":0,
    "gn:timezone":"Europe/Moscow",
    "iso:country":"RU",
    "name:eng_x_preferred":[
        "Glukhaya Gorushka"
    ],
    "name:nor_x_preferred":[
        "Glukhaja Gorusjka"
    ],
    "name:rus_x_preferred":[
        "\u0413\u043b\u0443\u0445\u0430\u044f \u0413\u043e\u0440\u0443\u0448\u043a\u0430"
    ],
    "wof:name":"Glukhaya Gorushka",
    "wof:placetype":"locality"
},
  "geometry": {"coordinates":[30.33186,57.71583],"type":"Point"}
}