{
  "type": "Feature",
  "properties": {
    "gn:admin1_code":"69",
    "gn:asciiname":"Korovniki",
    "gn:country_code":"RU",
    "gn:dem":187,
    "gn:feature_class":"P",
    "gn:feature_code":"PPL",
    "gn:name":"Korovniki",
    "gn:population":0,
    "gn:timezone":"Europe/Moscow",
    "iso:country":"RU",
    "name:rus_x_preferred":[
        "\u041a\u043e\u0440\u043e\u0432\u043d\u0438\u043a\u0438"
    ],
    "wof:name":"Korovniki",
    "wof:placetype":"locality"
},
  "geometry": {"coordinates":[32.75021,54.90978000000001],"type":"Point"}
}