{
  "type": "Feature",
  "properties": {
    "gn:admin1_code":"20",
    "gn:asciiname":"Yermaki",
    "gn:country_code":"RU",
    "gn:dem":325,
    "gn:feature_class":"P",
    "gn:feature_code":"PPL",
    "gn:name":"Yermaki",
    "gn:population":0,
    "gn:timezone":"Asia/Irkutsk",
    "iso:country":"RU",
    "name:eng_x_preferred":[
        "Yermaki"
    ],
    "name:nor_x_preferred":[
        "Jermaki"
    ],
    "name:rus_x_preferred":[
        "\u0415\u0440\u043c\u0430\u043a\u0438"
    ],
    "name:und_x_variant":[
        "Yermakovskaya"
    ],
    "wof:name":"Yermaki",
    "wof:placetype":"locality"
},
  "geometry": {"coordinates":[107.81721,56.6271],"type":"Point"}
}