{
  "type": "Feature",
  "properties": {
    "gn:admin1_code":"77",
    "gn:asciiname":"Kstinkino",
    "gn:country_code":"RU",
    "gn:dem":169,
    "gn:feature_class":"P",
    "gn:feature_code":"PPL",
    "gn:name":"Kstinkino",
    "gn:population":0,
    "gn:timezone":"Europe/Moscow",
    "iso:country":"RU",
    "name:rus_x_preferred":[
        "\u041a\u0441\u0442\u0438\u043d\u043a\u0438\u043d\u043e"
    ],
    "wof:name":"Kstinkino",
    "wof:placetype":"locality"
},
  "geometry": {"coordinates":[36.4315,58.5044],"type":"Point"}
}