{
  "type": "Feature",
  "properties": {
    "gn:admin1_code":"60",
    "gn:asciiname":"Pesenkovo",
    "gn:country_code":"RU",
    "gn:dem":156,
    "gn:feature_class":"P",
    "gn:feature_code":"PPL",
    "gn:name":"Pesenkovo",
    "gn:population":0,
    "gn:timezone":"Europe/Moscow",
    "iso:country":"RU",
    "name:rus_x_preferred":[
        "\u041f\u0435\u0441\u0435\u043d\u043a\u043e\u0432\u043e"
    ],
    "wof:name":"Pesenkovo",
    "wof:placetype":"locality"
},
  "geometry": {"coordinates":[30.7338,56.127],"type":"Point"}
}