{
  "type": "Feature",
  "properties": {
    "gn:admin1_code":"40",
    "gn:asciiname":"Stanovaya",
    "gn:cc2":"RU",
    "gn:country_code":"RU",
    "gn:dem":143,
    "gn:feature_class":"P",
    "gn:feature_code":"PPL",
    "gn:name":"Stanovaya",
    "gn:population":0,
    "gn:timezone":"Asia/Yekaterinburg",
    "iso:country":"RU",
    "name:eng_x_preferred":[
        "Stanovaya"
    ],
    "name:nor_x_preferred":[
        "Stanovaja"
    ],
    "name:rus_x_preferred":[
        "\u0421\u0442\u0430\u043d\u043e\u0432\u0430\u044f"
    ],
    "name:und_x_variant":[
        "Stanovoye",
        "\u0421\u0442\u0430\u043d\u043e\u0432\u0430\u044f",
        "Stanovaya"
    ],
    "wof:name":"Stanovaya",
    "wof:placetype":"locality"
},
  "geometry": {"coordinates":[65.48083000000001,55.2575],"type":"Point"}
}