{
  "type": "Feature",
  "properties": {
    "gn:admin1_code":"86.0",
    "gn:asciiname":"Kardail",
    "gn:country_code":"RU",
    "gn:dem":163,
    "gn:feature_class":"P",
    "gn:feature_code":"PPL",
    "gn:name":"Kardail",
    "gn:population":0,
    "gn:timezone":"Europe/Moscow",
    "iso:country":"RU",
    "name:rus_x_preferred":[
        "\u041a\u0430\u0440\u0434\u0430\u0438\u043b"
    ],
    "name:und_x_variant":[
        "\u041a\u0430\u0440\u0434\u0430\u0438\u043b"
    ],
    "wof:name":"Kardail",
    "wof:placetype":"locality"
},
  "geometry": {"coordinates":[41.84944,51.40639],"type":"Point"}
}