{
  "type": "Feature",
  "properties": {
    "gn:admin1_code":"73",
    "gn:asciiname":"Tatarskiy Sarsaz",
    "gn:country_code":"RU",
    "gn:dem":122,
    "gn:feature_class":"P",
    "gn:feature_code":"PPL",
    "gn:name":"Tatarskiy Sarsaz",
    "gn:population":0,
    "gn:timezone":"Europe/Moscow",
    "iso:country":"RU",
    "name:rus_x_preferred":[
        "\u0422\u0430\u0442\u0430\u0440\u0441\u043a\u0438\u0439 \u0421\u0430\u0440\u0441\u0430\u0437"
    ],
    "name:und_x_variant":[
        "Tatarskiye Sarsasy",
        "Tatarskiy Sarsaz",
        "\u0422\u0430\u0442\u0430\u0440\u0441\u043a\u0438\u0439 \u0421\u0430\u0440\u0441\u0430\u0437"
    ],
    "wof:name":"Tatarskiy Sarsaz",
    "wof:placetype":"locality"
},
  "geometry": {"coordinates":[50.82064,55.24663],"type":"Point"}
}