{
  "type": "Feature",
  "properties": {
    "gn:country":"RU",
    "gn:fcode":"PPL",
    "gn:population":7532,
    "iso:country":"RU",
    "name:che_x_preferred":[
        "\u041a\u0430\u0447\u0443\u0433"
    ],
    "name:eng_x_preferred":[
        "Kachug"
    ],
    "name:nor_x_preferred":[
        "Katsjug"
    ],
    "name:rus_x_preferred":[
        "\u041a\u0430\u0447\u0443\u0433"
    ],
    "name:swe_x_preferred":[
        "Katjug"
    ],
    "name:und_x_variant":[
        "Kachuga"
    ],
    "qs:name":"Kachug",
    "qs:photos_9r":0,
    "qs:photos_sr":0,
    "qs:pop_sr":"5",
    "wd:wordcount":42,
    "wof:name":"Kachug",
    "wof:placetype":"locality",
    "wof:population":7532
},
  "geometry": {"coordinates":[105.88167,53.96056],"type":"Point"}
}