{
  "type": "Feature",
  "properties": {
    "gn:admin1_code":"38",
    "gn:asciiname":"Novogeorgiyevskiy",
    "gn:country_code":"RU",
    "gn:dem":10,
    "gn:feature_class":"P",
    "gn:feature_code":"PPL",
    "gn:name":"Novogeorgiyevskiy",
    "gn:population":0,
    "gn:timezone":"Europe/Moscow",
    "iso:country":"RU",
    "name:rus_x_preferred":[
        "\u041d\u043e\u0432\u043e\u0433\u0435\u043e\u0440\u0433\u0438\u0435\u0432\u0441\u043a\u0438\u0439"
    ],
    "wof:name":"Novogeorgiyevskiy",
    "wof:placetype":"locality"
},
  "geometry": {"coordinates":[37.72222,45.10389],"type":"Point"}
}