{
  "type": "Feature",
  "properties": {
    "gn:admin1_code":"69.0",
    "gn:asciiname":"Bel'dyugino",
    "gn:country_code":"RU",
    "gn:dem":203,
    "gn:feature_class":"P",
    "gn:feature_code":"PPL",
    "gn:name":"Bel\u2019dyugino",
    "gn:population":0,
    "gn:timezone":"Europe/Moscow",
    "iso:country":"RU",
    "name:eng_x_preferred":[
        "Bel'dyugino"
    ],
    "name:nor_x_preferred":[
        "Beldjugino"
    ],
    "name:rus_x_preferred":[
        "\u0411\u0435\u043b\u044c\u0434\u044e\u0433\u0438\u043d\u043e"
    ],
    "name:und_x_variant":[
        "Bil\u2019dyugina",
        "\u0411\u0435\u043b\u044c\u0434\u044e\u0433\u0438\u043d\u043e",
        "Bel\u2019dyugino"
    ],
    "wof:name":"Bel'dyugino",
    "wof:placetype":"locality"
},
  "geometry": {"coordinates":[34.36322,54.89169],"type":"Point"}
}