{
  "type": "Feature",
  "properties": {
    "gn:admin1_code":"77",
    "gn:asciiname":"Zhabny",
    "gn:country_code":"RU",
    "gn:dem":249,
    "gn:feature_class":"P",
    "gn:feature_code":"PPL",
    "gn:name":"Zhabny",
    "gn:population":0,
    "gn:timezone":"Europe/Moscow",
    "iso:country":"RU",
    "name:eng_x_preferred":[
        "Zhabny"
    ],
    "name:nor_x_preferred":[
        "Zjabny"
    ],
    "name:rus_x_preferred":[
        "\u0416\u0430\u0431\u043d\u044b"
    ],
    "wof:name":"Zhabny",
    "wof:placetype":"locality"
},
  "geometry": {"coordinates":[33.52077,57.55181999999999],"type":"Point"}
}