{
  "type": "Feature",
  "properties": {
    "gn:admin1_code":"8.0",
    "gn:asciiname":"Tyukun'",
    "gn:country_code":"RU",
    "gn:dem":113,
    "gn:feature_class":"P",
    "gn:feature_code":"PPL",
    "gn:name":"Tyukun\u2019",
    "gn:population":0,
    "gn:timezone":"Asia/Yekaterinburg",
    "iso:country":"RU",
    "name:rus_x_preferred":[
        "\u0422\u044e\u043a\u0443\u043d\u044c"
    ],
    "name:und_x_variant":[
        "Tyukun\u2019"
    ],
    "wof:name":"Tyukun'",
    "wof:placetype":"locality"
},
  "geometry": {"coordinates":[56.3275,54.1957],"type":"Point"}
}