{
  "type": "Feature",
  "properties": {
    "gn:admin1_code":"90",
    "gn:asciiname":"Staryy Lyp",
    "gn:country_code":"RU",
    "gn:dem":124,
    "gn:feature_class":"P",
    "gn:feature_code":"PPL",
    "gn:name":"Staryy Lyp",
    "gn:population":0,
    "gn:timezone":"Asia/Yekaterinburg",
    "iso:country":"RU",
    "name:eng_x_preferred":[
        "Staryy Lyp"
    ],
    "name:nor_x_preferred":[
        "Star.Lyp"
    ],
    "name:rus_x_preferred":[
        "\u0421\u0442\u0430\u0440.\u041b\u044b\u043f"
    ],
    "name:rus_x_variant":[
        "\u0421\u0442\u0430\u0440\u044b\u0439 \u041b\u044b\u043f"
    ],
    "wof:name":"Staryy Lyp",
    "wof:placetype":"locality"
},
  "geometry": {"coordinates":[54.26733,57.37816],"type":"Point"}
}