{
  "type": "Feature",
  "properties": {
    "gn:admin1_code":"62.0",
    "gn:asciiname":"Agrafenovka",
    "gn:country_code":"RU",
    "gn:dem":104,
    "gn:feature_class":"P",
    "gn:feature_code":"PPL",
    "gn:name":"Agraf\u00ebnovka",
    "gn:population":0,
    "gn:timezone":"Europe/Moscow",
    "iso:country":"RU",
    "name:nor_x_preferred":[
        "Agrafjonovka"
    ],
    "name:rus_x_preferred":[
        "\u0410\u0433\u0440\u0430\u0444\u0451\u043d\u043e\u0432\u043a\u0430"
    ],
    "name:und_x_variant":[
        "Agraf\u00ebnovka"
    ],
    "wof:name":"Agrafenovka",
    "wof:placetype":"locality"
},
  "geometry": {"coordinates":[40.6924,54.6362],"type":"Point"}
}