{
  "type": "Feature",
  "properties": {
    "gn:admin1_code":"9.0",
    "gn:asciiname":"Orlov",
    "gn:country_code":"RU",
    "gn:dem":187,
    "gn:feature_class":"P",
    "gn:feature_code":"PPL",
    "gn:name":"Orlov",
    "gn:population":0,
    "gn:timezone":"Europe/Moscow",
    "iso:country":"RU",
    "name:bar_x_preferred":[
        "Orlov"
    ],
    "name:bel_x_preferred":[
        "\u0410\u0440\u043b\u043e\u045e"
    ],
    "name:bul_x_preferred":[
        "\u041e\u0440\u043b\u043e\u0432"
    ],
    "name:cat_x_preferred":[
        "Orlov"
    ],
    "name:ceb_x_preferred":[
        "Orlov"
    ],
    "name:ces_x_preferred":[
        "Orlov"
    ],
    "name:chv_x_preferred":[
        "\u041e\u0440\u043b\u043e\u0432"
    ],
    "name:deu_x_preferred":[
        "Orlov"
    ],
    "name:epo_x_preferred":[
        "Orlov"
    ],
    "name:fin_x_preferred":[
        "Orlov"
    ],
    "name:fra_x_preferred":[
        "Orlov"
    ],
    "name:hun_x_preferred":[
        "Orlov"
    ],
    "name:ita_x_preferred":[
        "Orlov"
    ],
    "name:jpn_x_preferred":[
        "\u30aa\u30eb\u30ed\u30d5"
    ],
    "name:lav_x_preferred":[
        "Orlovs"
    ],
    "name:pol_x_preferred":[
        "Or\u0142ow"
    ],
    "name:ron_x_preferred":[
        "Orlov"
    ],
    "name:rus_x_preferred":[
        "\u041e\u0440\u043b\u043e\u0432"
    ],
    "name:spa_x_preferred":[
        "Orlov"
    ],
    "name:srp_x_preferred":[
        "\u041e\u0440\u043b\u043e\u0432"
    ],
    "name:swe_x_preferred":[
        "Orlov"
    ],
    "name:tat_x_preferred":[
        "\u041e\u0440\u043b\u043e\u0432"
    ],
    "name:ukr_x_preferred":[
        "\u041e\u0440\u043b\u043e\u0432"
    ],
    "name:zho_x_preferred":[
        "\u5965\u5c14\u6d1b\u592b"
    ],
    "wof:name":"Orlov",
    "wof:placetype":"locality"
},
  "geometry": {"coordinates":[38.5332,50.0878],"type":"Point"}
}