{
  "type": "Feature",
  "properties": {
    "gn:admin1_code":"43",
    "gn:asciiname":"Malyye Izvaly",
    "gn:country_code":"RU",
    "gn:dem":193,
    "gn:feature_class":"P",
    "gn:feature_code":"PPL",
    "gn:name":"Malyye Izvaly",
    "gn:population":0,
    "gn:timezone":"Europe/Moscow",
    "iso:country":"RU",
    "name:rus_x_preferred":[
        "\u041c\u0430\u043b\u044b\u0435 \u0418\u0437\u0432\u0430\u043b\u044b"
    ],
    "name:und_x_variant":[
        "\u041c\u0430\u043b\u044b\u0435 \u0418\u0437\u0432\u0430\u043b\u044b"
    ],
    "wof:name":"Malyye Izvaly",
    "wof:placetype":"locality"
},
  "geometry": {"coordinates":[38.79833,52.52293],"type":"Point"}
}