{
  "type": "Feature",
  "properties": {
    "gn:admin1_code":"76.0",
    "gn:asciiname":"Brusyanovka",
    "gn:country_code":"RU",
    "gn:dem":218,
    "gn:feature_class":"P",
    "gn:feature_code":"PPL",
    "gn:name":"Brusyanovka",
    "gn:population":0,
    "gn:timezone":"Europe/Moscow",
    "iso:country":"RU",
    "name:rus_x_preferred":[
        "\u0411\u0440\u0443\u0441\u044f\u043d\u043e\u0432\u043a\u0430"
    ],
    "wof:name":"Brusyanovka",
    "wof:placetype":"locality"
},
  "geometry": {"coordinates":[37.91385,53.9064],"type":"Point"}
}