{
  "type": "Feature",
  "properties": {
    "gn:admin1_code":"51",
    "gn:asciiname":"Morchikha",
    "gn:country_code":"RU",
    "gn:dem":102,
    "gn:feature_class":"P",
    "gn:feature_code":"PPL",
    "gn:name":"Morchikha",
    "gn:population":0,
    "gn:timezone":"Europe/Moscow",
    "iso:country":"RU",
    "name:rus_x_preferred":[
        "\u041c\u043e\u0440\u0447\u0438\u0445\u0430"
    ],
    "wof:name":"Morchikha",
    "wof:placetype":"locality"
},
  "geometry": {"coordinates":[45.4671,57.8172],"type":"Point"}
}