{
  "type": "Feature",
  "properties": {
    "gn:admin1_code":"53",
    "gn:asciiname":"Sorikha",
    "gn:cc2":"RU",
    "gn:country_code":"RU",
    "gn:dem":330,
    "gn:feature_class":"P",
    "gn:feature_code":"PPL",
    "gn:name":"Sorikha",
    "gn:population":0,
    "gn:timezone":"Asia/Omsk",
    "iso:country":"RU",
    "name:rus_x_preferred":[
        "\u0421\u043e\u0440\u0438\u0445\u0430"
    ],
    "name:und_x_variant":[
        "Serikha",
        "Sorikha",
        "\u0421\u043e\u0440\u0438\u0445\u0430"
    ],
    "wof:name":"Sorikha",
    "wof:placetype":"locality"
},
  "geometry": {"coordinates":[84.76666999999998,54.36666999999999],"type":"Point"}
}