{
  "type": "Feature",
  "properties": {
    "gn:admin1_code":"76",
    "gn:asciiname":"Botashovka",
    "gn:country_code":"RU",
    "gn:dem":167,
    "gn:feature_class":"P",
    "gn:feature_code":"PPL",
    "gn:name":"Botashovka",
    "gn:population":0,
    "gn:timezone":"Europe/Moscow",
    "iso:country":"RU",
    "name:rus_x_preferred":[
        "\u0411\u043e\u0442\u0430\u0448\u043e\u0432\u043a\u0430"
    ],
    "wof:name":"Botashovka",
    "wof:placetype":"locality"
},
  "geometry": {"coordinates":[37.93758,53.32533000000001],"type":"Point"}
}