{
  "type": "Feature",
  "properties": {
    "gn:admin1_code":"41",
    "gn:asciiname":"Kolodezhi",
    "gn:country_code":"RU",
    "gn:dem":133,
    "gn:feature_class":"P",
    "gn:feature_code":"PPL",
    "gn:name":"Kolodezhi",
    "gn:population":0,
    "gn:timezone":"Europe/Moscow",
    "iso:country":"RU",
    "name:rus_x_preferred":[
        "\u041a\u043e\u043b\u043e\u0434\u0435\u0436\u0438"
    ],
    "wof:name":"Kolodezhi",
    "wof:placetype":"locality"
},
  "geometry": {"coordinates":[34.327,51.4087],"type":"Point"}
}