{
  "type": "Feature",
  "properties": {
    "gn:admin1_code":"7",
    "gn:asciiname":"Zelenyy Sad",
    "gn:country_code":"RU",
    "gn:dem":-10,
    "gn:feature_class":"P",
    "gn:feature_code":"PPL",
    "gn:name":"Zel\u00ebnyy Sad",
    "gn:population":0,
    "gn:timezone":"Europe/Astrakhan",
    "iso:country":"RU",
    "name:rus_x_preferred":[
        "\u0417\u0435\u043b\u0451\u043d\u044b\u0439 \u0421\u0430\u0434"
    ],
    "name:und_x_variant":[
        "Zel\u00ebnyy Sad"
    ],
    "wof:name":"Zelenyy Sad",
    "wof:placetype":"locality"
},
  "geometry": {"coordinates":[45.27478,48.41616],"type":"Point"}
}