{
  "type": "Feature",
  "properties": {
    "gn:admin1_code":"33",
    "gn:asciiname":"Bol'shaya Krutenka",
    "gn:country_code":"RU",
    "gn:dem":163,
    "gn:feature_class":"P",
    "gn:feature_code":"PPL",
    "gn:name":"Bol\u2019shaya Krutenka",
    "gn:population":0,
    "gn:timezone":"Europe/Kirov",
    "iso:country":"RU",
    "name:rus_x_preferred":[
        "\u0411\u043e\u043b\u044c\u0448\u0430\u044f \u041a\u0440\u0443\u0442\u0435\u043d\u043a\u0430"
    ],
    "name:und_x_variant":[
        "Bol\u2019shaya Krutenka"
    ],
    "wof:name":"Bol'shaya Krutenka",
    "wof:placetype":"locality"
},
  "geometry": {"coordinates":[46.8872,58.3363],"type":"Point"}
}