{
  "type": "Feature",
  "properties": {
    "gn:admin1_code":"89",
    "gn:asciiname":"Vladimirovka",
    "gn:country_code":"RU",
    "gn:dem":36,
    "gn:feature_class":"P",
    "gn:feature_code":"PPL",
    "gn:name":"Vladimirovka",
    "gn:population":0,
    "gn:timezone":"Asia/Vladivostok",
    "iso:country":"RU",
    "name:eng_x_preferred":[
        "Vladimirovka"
    ],
    "name:nor_x_preferred":[
        "Vladimirovka"
    ],
    "name:rus_x_preferred":[
        "\u0412\u043b\u0430\u0434\u0438\u043c\u0438\u0440\u043e\u0432\u043a\u0430"
    ],
    "name:und_x_variant":[
        "Vladymyrovka",
        "Vladimirovka"
    ],
    "wof:name":"Vladimirovka",
    "wof:placetype":"locality"
},
  "geometry": {"coordinates":[134.89626999999999,48.45604],"type":"Point"}
}