{
  "type": "Feature",
  "properties": {
    "gn:admin1_code":"33",
    "gn:asciiname":"Pogost",
    "gn:country_code":"RU",
    "gn:dem":154,
    "gn:feature_class":"P",
    "gn:feature_code":"PPL",
    "gn:name":"Pogost",
    "gn:population":0,
    "gn:timezone":"Europe/Kirov",
    "iso:country":"RU",
    "name:rus_x_preferred":[
        "\u041f\u043e\u0433\u043e\u0441\u0442"
    ],
    "name:und_x_variant":[
        "\u041f\u043e\u0433\u043e\u0441\u0442"
    ],
    "wof:name":"Pogost",
    "wof:placetype":"locality"
},
  "geometry": {"coordinates":[50.15,58.83333],"type":"Point"}
}