{
  "type": "Feature",
  "properties": {
    "gn:admin1_code":"60",
    "gn:asciiname":"Stariki",
    "gn:country_code":"RU",
    "gn:dem":102,
    "gn:feature_class":"P",
    "gn:feature_code":"PPL",
    "gn:name":"Stariki",
    "gn:population":0,
    "gn:timezone":"Europe/Moscow",
    "iso:country":"RU",
    "name:eng_x_preferred":[
        "Stariki"
    ],
    "name:nor_x_preferred":[
        "Stariki"
    ],
    "name:rus_x_preferred":[
        "\u0421\u0442\u0430\u0440\u0438\u043a\u0438"
    ],
    "name:und_x_variant":[
        "\u0421\u0442\u0430\u0440\u0438\u043a\u0438",
        "Stariki"
    ],
    "wof:name":"Stariki",
    "wof:placetype":"locality"
},
  "geometry": {"coordinates":[29.88131,57.19512],"type":"Point"}
}