{
  "type": "Feature",
  "properties": {
    "gn:admin1_code":"37.0",
    "gn:asciiname":"Bol'shaya Strelka",
    "gn:country_code":"RU",
    "gn:dem":159,
    "gn:feature_class":"P",
    "gn:feature_code":"PPL",
    "gn:name":"Bol\u2019shaya Strelka",
    "gn:population":0,
    "gn:timezone":"Europe/Moscow",
    "iso:country":"RU",
    "name:rus_x_preferred":[
        "\u0411\u043e\u043b\u044c\u0448\u0430\u044f \u0421\u0442\u0440\u0435\u043b\u043a\u0430"
    ],
    "name:und_x_variant":[
        "Bol\u2019shaya Strelka",
        "\u0411\u043e\u043b\u044c\u0448\u0430\u044f \u0421\u0442\u0440\u0435\u043b\u043a\u0430"
    ],
    "wof:name":"Bol'shaya Strelka",
    "wof:placetype":"locality"
},
  "geometry": {"coordinates":[46.77546,58.77325],"type":"Point"}
}