{
  "type": "Feature",
  "properties": {
    "gn:admin1_code":"47",
    "gn:asciiname":"Bortnikovo",
    "gn:country_code":"RU",
    "gn:dem":164,
    "gn:feature_class":"P",
    "gn:feature_code":"PPL",
    "gn:name":"Bortnikovo",
    "gn:population":0,
    "gn:timezone":"Europe/Moscow",
    "iso:country":"RU",
    "name:rus_x_preferred":[
        "\u0411\u043e\u0440\u0442\u043d\u0438\u043a\u043e\u0432\u043e"
    ],
    "name:und_x_variant":[
        "\u0411\u043e\u0440\u0442\u043d\u0438\u043a\u043e\u0432\u043e"
    ],
    "wof:name":"Bortnikovo",
    "wof:placetype":"locality"
},
  "geometry": {"coordinates":[36.7549,56.5243],"type":"Point"}
}