{
  "type": "Feature",
  "properties": {
    "gn:admin1_code":"67",
    "gn:asciiname":"Kvasnikovka",
    "gn:country_code":"RU",
    "gn:dem":20,
    "gn:feature_class":"P",
    "gn:feature_code":"PPL",
    "gn:name":"Kvasnikovka",
    "gn:population":0,
    "gn:timezone":"Europe/Saratov",
    "iso:country":"RU",
    "name:eng_x_preferred":[
        "Kvasnikovka"
    ],
    "name:nor_x_preferred":[
        "Kvasninovka"
    ],
    "name:rus_x_preferred":[
        "\u041a\u0432\u0430\u0441\u043d\u0438\u043d\u043e\u0432\u043a\u0430"
    ],
    "wof:name":"Kvasnikovka",
    "wof:placetype":"locality"
},
  "geometry": {"coordinates":[46.02806,51.38222],"type":"Point"}
}