{
  "type": "Feature",
  "properties": {
    "gn:admin1_code":"6.0",
    "gn:asciiname":"Artyushinskaya",
    "gn:country_code":"RU",
    "gn:dem":18,
    "gn:feature_class":"P",
    "gn:feature_code":"PPL",
    "gn:name":"Artyushinskaya",
    "gn:population":0,
    "gn:timezone":"Europe/Moscow",
    "iso:country":"RU",
    "name:che_x_preferred":[
        "\u0410\u0440\u0442\u044e\u0448\u0438\u043d\u0441\u043a\u0438"
    ],
    "name:nor_x_preferred":[
        "Artjusjinskaja"
    ],
    "name:rus_x_preferred":[
        "\u0410\u0440\u0442\u044e\u0448\u0438\u043d\u0441\u043a\u0430\u044f"
    ],
    "name:tgk_x_preferred":[
        "\u0410\u0440\u0442\u044e\u0448\u0438\u043d\u0441\u043a\u0430\u044f"
    ],
    "wof:name":"Artyushinskaya",
    "wof:placetype":"locality"
},
  "geometry": {"coordinates":[43.2679,62.7401],"type":"Point"}
}