{
  "type": "Feature",
  "properties": {
    "gn:admin1_code":"77.0",
    "gn:asciiname":"Bolotovo",
    "gn:country_code":"RU",
    "gn:dem":216,
    "gn:feature_class":"P",
    "gn:feature_code":"PPL",
    "gn:name":"Bolotovo",
    "gn:population":0,
    "gn:timezone":"Europe/Moscow",
    "iso:country":"RU",
    "name:rus_x_preferred":[
        "\u0411\u043e\u043b\u043e\u0442\u043e\u0432\u043e"
    ],
    "name:und_x_variant":[
        "\u0411\u043e\u043b\u043e\u0442\u043e\u0432\u043e"
    ],
    "wof:name":"Bolotovo",
    "wof:placetype":"locality"
},
  "geometry": {"coordinates":[31.72157,57.03344],"type":"Point"}
}