{
  "type": "Feature",
  "properties": {
    "gn:admin1_code":"55",
    "gn:asciiname":"Kuz'minovka",
    "gn:country_code":"RU",
    "gn:dem":271,
    "gn:feature_class":"P",
    "gn:feature_code":"PPL",
    "gn:name":"Kuz\u2019minovka",
    "gn:population":0,
    "gn:timezone":"Asia/Yekaterinburg",
    "iso:country":"RU",
    "name:rus_x_preferred":[
        "\u041a\u0443\u0437\u044c\u043c\u0438\u043d\u043e\u0432\u043a\u0430"
    ],
    "name:und_x_variant":[
        "Kuz\u2019minovka"
    ],
    "wof:name":"Kuz'minovka",
    "wof:placetype":"locality"
},
  "geometry": {"coordinates":[53.43333000000001,53.45],"type":"Point"}
}