{
  "type": "Feature",
  "properties": {
    "gn:admin1_code":"33.0",
    "gn:asciiname":"Smirnovy",
    "gn:country_code":"RU",
    "gn:dem":102,
    "gn:feature_class":"P",
    "gn:feature_code":"PPL",
    "gn:name":"Smirnovy",
    "gn:population":0,
    "gn:timezone":"Europe/Kirov",
    "iso:country":"RU",
    "name:rus_x_preferred":[
        "\u0421\u043c\u0438\u0440\u043d\u043e\u0432\u044b"
    ],
    "name:und_x_variant":[
        "\u0421\u043c\u0438\u0440\u043d\u043e\u0432\u044b"
    ],
    "wof:name":"Smirnovy",
    "wof:placetype":"locality"
},
  "geometry": {"coordinates":[48.86321,58.4197],"type":"Point"}
}