{
  "type": "Feature",
  "properties": {
    "gn:admin1_code":"84",
    "gn:asciiname":"Sestrenki",
    "gn:country_code":"RU",
    "gn:dem":60,
    "gn:feature_class":"P",
    "gn:feature_code":"PPL",
    "gn:name":"Sestr\u00ebnki",
    "gn:population":0,
    "gn:timezone":"Europe/Volgograd",
    "iso:country":"RU",
    "name:rus_x_preferred":[
        "\u0421\u0435\u0441\u0442\u0440\u0451\u043d\u043a\u0438"
    ],
    "name:und_x_variant":[
        "Sestr\u00ebnki",
        "\u0421\u0435\u0441\u0442\u0440\u0451\u043d\u043a\u0438"
    ],
    "wof:name":"Sestrenki",
    "wof:placetype":"locality"
},
  "geometry": {"coordinates":[45.33333,49.98333],"type":"Point"}
}