{
  "type": "Feature",
  "properties": {
    "gn:admin1_code":"71",
    "gn:asciiname":"Kvartal Nomer Pyat'",
    "gn:country_code":"RU",
    "gn:dem":147,
    "gn:feature_class":"P",
    "gn:feature_code":"PPL",
    "gn:name":"Kvartal Nomer Pyat\u2019",
    "gn:population":0,
    "gn:timezone":"Asia/Yekaterinburg",
    "iso:country":"RU",
    "name:rus_x_preferred":[
        "\u041a\u0432\u0430\u0440\u0442\u0430\u043b \u041d\u043e\u043c\u0435\u0440 \u041f\u044f\u0442\u044c"
    ],
    "name:und_x_variant":[
        "Kvartal Nomer Pyat\u2019"
    ],
    "wof:name":"Kvartal Nomer Pyat'",
    "wof:placetype":"locality"
},
  "geometry": {"coordinates":[62.1437,57.2905],"type":"Point"}
}