{
  "type": "Feature",
  "properties": {
    "gn:admin1_code":"85",
    "gn:asciiname":"Nikitikha",
    "gn:country_code":"RU",
    "gn:dem":125,
    "gn:feature_class":"P",
    "gn:feature_code":"PPL",
    "gn:name":"Nikitikha",
    "gn:population":0,
    "gn:timezone":"Europe/Moscow",
    "iso:country":"RU",
    "name:eng_x_preferred":[
        "Nikitikha"
    ],
    "name:nor_x_preferred":[
        "Nikitikha"
    ],
    "name:rus_x_preferred":[
        "\u041d\u0438\u043a\u0438\u0442\u0438\u0445\u0430"
    ],
    "name:und_x_variant":[
        "Nikitinskaya",
        "\u041d\u0438\u043a\u0438\u0442\u0438\u0445\u0430",
        "Nikitikha"
    ],
    "wof:name":"Nikitikha",
    "wof:placetype":"locality"
},
  "geometry": {"coordinates":[43.2941,60.42141],"type":"Point"}
}