{
  "type": "Feature",
  "properties": {
    "gn:admin1_code":"54",
    "gn:asciiname":"Chulkovo",
    "gn:country_code":"RU",
    "gn:dem":112,
    "gn:feature_class":"P",
    "gn:feature_code":"PPL",
    "gn:name":"Chulkovo",
    "gn:population":0,
    "gn:timezone":"Asia/Omsk",
    "iso:country":"RU",
    "name:eng_x_preferred":[
        "Chulkovo"
    ],
    "name:nor_x_preferred":[
        "Tsjulkovo"
    ],
    "name:rus_x_preferred":[
        "\u0427\u0443\u043b\u043a\u043e\u0432\u043e"
    ],
    "name:und_x_variant":[
        "Chulkova"
    ],
    "wof:name":"Chulkovo",
    "wof:placetype":"locality"
},
  "geometry": {"coordinates":[72.58828000000003,55.15445],"type":"Point"}
}