{
  "type": "Feature",
  "properties": {
    "gn:admin1_code":"85",
    "gn:asciiname":"Mitino",
    "gn:country_code":"RU",
    "gn:dem":122,
    "gn:feature_class":"P",
    "gn:feature_code":"PPL",
    "gn:name":"Mitino",
    "gn:population":0,
    "gn:timezone":"Europe/Moscow",
    "iso:country":"RU",
    "name:ceb_x_preferred":[
        "Mitino"
    ],
    "name:deu_x_preferred":[
        "Mitino"
    ],
    "name:hye_x_preferred":[
        "\u0544\u056b\u057f\u056b\u0576\u0578"
    ],
    "name:ita_x_preferred":[
        "Mitino"
    ],
    "name:rus_x_preferred":[
        "\u041c\u0438\u0442\u0438\u043d\u043e"
    ],
    "name:swe_x_preferred":[
        "Mitino"
    ],
    "name:ukr_x_preferred":[
        "\u041c\u0438\u0442\u0456\u043d\u043e"
    ],
    "name:und_x_variant":[
        "\u041c\u0438\u0442\u0438\u043d\u043e"
    ],
    "wof:name":"Mitino",
    "wof:placetype":"locality"
},
  "geometry": {"coordinates":[38.34601,59.82315],"type":"Point"}
}