{
  "type": "Feature",
  "properties": {
    "gn:admin1_code":"76",
    "gn:asciiname":"Khomutovka",
    "gn:country_code":"RU",
    "gn:dem":177,
    "gn:feature_class":"P",
    "gn:feature_code":"PPL",
    "gn:name":"Khomutovka",
    "gn:population":0,
    "gn:timezone":"Europe/Moscow",
    "iso:country":"RU",
    "name:rus_x_preferred":[
        "\u0425\u043e\u043c\u0443\u0442\u043e\u0432\u043a\u0430"
    ],
    "name:und_x_variant":[
        "Mikhaylovka",
        "Khomutovka"
    ],
    "wof:name":"Khomutovka",
    "wof:placetype":"locality"
},
  "geometry": {"coordinates":[38.5713,53.93459],"type":"Point"}
}