{
  "type": "Feature",
  "properties": {
    "gn:admin1_code":"53",
    "gn:asciiname":"Kalinovskiy",
    "gn:country_code":"RU",
    "gn:dem":176,
    "gn:feature_class":"P",
    "gn:feature_code":"PPL",
    "gn:name":"Kalinovskiy",
    "gn:population":0,
    "gn:timezone":"Asia/Novosibirsk",
    "iso:country":"RU",
    "name:rus_x_preferred":[
        "\u041a\u0430\u043b\u0438\u043d\u043e\u0432\u0441\u043a\u0438\u0439"
    ],
    "wof:name":"Kalinovskiy",
    "wof:placetype":"locality"
},
  "geometry": {"coordinates":[79.28653,53.76667],"type":"Point"}
}