{
  "type": "Feature",
  "properties": {
    "gn:admin1_code":"21",
    "gn:asciiname":"Petushki",
    "gn:country_code":"RU",
    "gn:dem":115,
    "gn:feature_class":"P",
    "gn:feature_code":"PPL",
    "gn:name":"Petushki",
    "gn:population":0,
    "gn:timezone":"Europe/Moscow",
    "iso:country":"RU",
    "name:nor_x_preferred":[
        "Petusjki"
    ],
    "name:rus_x_preferred":[
        "\u041f\u0435\u0442\u0443\u0448\u043a\u0438"
    ],
    "wof:name":"Petushki",
    "wof:placetype":"locality"
},
  "geometry": {"coordinates":[42.03359,56.70458000000001],"type":"Point"}
}