{
  "type": "Feature",
  "properties": {
    "gn:admin1_code":"60",
    "gn:asciiname":"Dorozhkovo",
    "gn:country_code":"RU",
    "gn:dem":163,
    "gn:feature_class":"P",
    "gn:feature_code":"PPL",
    "gn:name":"Dorozhkovo",
    "gn:population":0,
    "gn:timezone":"Europe/Moscow",
    "iso:country":"RU",
    "name:rus_x_preferred":[
        "\u0414\u043e\u0440\u043e\u0436\u043a\u043e\u0432\u043e"
    ],
    "wof:name":"Dorozhkovo",
    "wof:placetype":"locality"
},
  "geometry": {"coordinates":[29.0782,56.3925],"type":"Point"}
}