{
  "type": "Feature",
  "properties": {
    "gn:admin1_code":"25.0",
    "gn:asciiname":"Katorginka Vtoraya",
    "gn:country_code":"RU",
    "gn:dem":176,
    "gn:feature_class":"P",
    "gn:feature_code":"PPL",
    "gn:name":"Katorginka Vtoraya",
    "gn:population":0,
    "gn:timezone":"Europe/Moscow",
    "iso:country":"RU",
    "name:und_x_variant":[
        "Katarginka Vtoraya",
        "Katorginka Vtoraya"
    ],
    "wof:name":"Katorginka Vtoraya",
    "wof:placetype":"locality"
},
  "geometry": {"coordinates":[35.62709,54.11428000000001],"type":"Point"}
}