{
  "type": "Feature",
  "properties": {
    "gn:admin1_code":"42",
    "gn:asciiname":"Varvarinskaya",
    "gn:cc2":"RU",
    "gn:country_code":"RU",
    "gn:dem":129,
    "gn:feature_class":"P",
    "gn:feature_code":"PPL",
    "gn:name":"Varvarinskaya",
    "gn:population":0,
    "gn:timezone":"Europe/Moscow",
    "iso:country":"RU",
    "name:fin_x_preferred":[
        "Varvaskoi"
    ],
    "name:und_x_variant":[
        "Varvarosi",
        "Varvarinskaya"
    ],
    "wof:name":"Varvarinskaya",
    "wof:placetype":"locality"
},
  "geometry": {"coordinates":[29.5903,59.74827],"type":"Point"}
}