{
  "type": "Feature",
  "properties": {
    "gn:admin1_code":"60",
    "gn:asciiname":"Kirillovo",
    "gn:country_code":"RU",
    "gn:dem":62,
    "gn:feature_class":"P",
    "gn:feature_code":"PPL",
    "gn:name":"Kirillovo",
    "gn:population":0,
    "gn:timezone":"Europe/Moscow",
    "iso:country":"RU",
    "name:rus_x_preferred":[
        "\u041a\u0438\u0440\u0438\u043b\u043b\u043e\u0432\u043e"
    ],
    "wof:name":"Kirillovo",
    "wof:placetype":"locality"
},
  "geometry": {"coordinates":[28.98525,57.62525],"type":"Point"}
}