{
  "type": "Feature",
  "properties": {
    "gn:admin1_code":"77",
    "gn:asciiname":"Venshino",
    "gn:country_code":"RU",
    "gn:dem":237,
    "gn:feature_class":"P",
    "gn:feature_code":"PPL",
    "gn:name":"Venshino",
    "gn:population":0,
    "gn:timezone":"Europe/Moscow",
    "iso:country":"RU",
    "name:und_x_variant":[
        "Venchino",
        "Venshino"
    ],
    "wof:name":"Venshino",
    "wof:placetype":"locality"
},
  "geometry": {"coordinates":[34.13630999999999,56.47301],"type":"Point"}
}