{
  "type": "Feature",
  "properties": {
    "gn:admin1_code":"37",
    "gn:asciiname":"Strelitsa",
    "gn:country_code":"RU",
    "gn:dem":135,
    "gn:feature_class":"P",
    "gn:feature_code":"PPL",
    "gn:name":"Strelitsa",
    "gn:population":0,
    "gn:timezone":"Europe/Moscow",
    "iso:country":"RU",
    "name:che_x_preferred":[
        "\u0421\u0442\u0440\u0435\u043b\u0438\u0446\u0430"
    ],
    "name:rus_x_preferred":[
        "\u0421\u0442\u0440\u0435\u043b\u0438\u0446\u0430"
    ],
    "name:tgk_x_preferred":[
        "\u0421\u0442\u0440\u0435\u043b\u0438\u0442\u0441\u0430"
    ],
    "name:und_x_variant":[
        "\u0421\u0442\u0440\u0435\u043b\u0438\u0446\u0430"
    ],
    "wof:name":"Strelitsa",
    "wof:placetype":"locality"
},
  "geometry": {"coordinates":[43.6745,58.0281],"type":"Point"}
}