{
  "type": "Feature",
  "properties": {
    "gn:admin1_code":"88",
    "gn:asciiname":"Mitino",
    "gn:country_code":"RU",
    "gn:dem":136,
    "gn:feature_class":"P",
    "gn:feature_code":"PPL",
    "gn:name":"Mitino",
    "gn:population":0,
    "gn:timezone":"Europe/Moscow",
    "iso:country":"RU",
    "name:rus_x_preferred":[
        "\u041c\u0438\u0442\u0438\u043d\u043e"
    ],
    "name:und_x_variant":[
        "\u041c\u0438\u0442\u0438\u043d\u043e"
    ],
    "wof:name":"Mitino",
    "wof:placetype":"locality"
},
  "geometry": {"coordinates":[40.59005,58.33451],"type":"Point"}
}