{
  "type": "Feature",
  "properties": {
    "gn:admin1_code":"40",
    "gn:asciiname":"Severnaya",
    "gn:country_code":"RU",
    "gn:dem":138,
    "gn:feature_class":"P",
    "gn:feature_code":"PPL",
    "gn:name":"Severnaya",
    "gn:population":0,
    "gn:timezone":"Asia/Yekaterinburg",
    "iso:country":"RU",
    "name:eng_x_preferred":[
        "Severnaya"
    ],
    "name:nor_x_preferred":[
        "Severnaja"
    ],
    "name:rus_x_preferred":[
        "\u0421\u0435\u0432\u0435\u0440\u043d\u0430\u044f"
    ],
    "name:und_x_variant":[
        "Dolgaya"
    ],
    "wof:name":"Severnaya",
    "wof:placetype":"locality"
},
  "geometry": {"coordinates":[65.0164,56.0653],"type":"Point"}
}