{
  "type": "Feature",
  "properties": {
    "gn:admin1_code":"13",
    "gn:asciiname":"Shumakovo",
    "gn:cc2":"RU",
    "gn:country_code":"RU",
    "gn:dem":201,
    "gn:feature_class":"P",
    "gn:feature_code":"PPL",
    "gn:name":"Shumakovo",
    "gn:population":0,
    "gn:timezone":"Asia/Yekaterinburg",
    "iso:country":"RU",
    "name:rus_x_preferred":[
        "\u0428\u0443\u043c\u0430\u043a\u043e\u0432\u043e"
    ],
    "name:und_x_variant":[
        "Shumaki",
        "Shumakovo",
        "\u0428\u0443\u043c\u0430\u043a\u043e\u0432\u043e"
    ],
    "wof:name":"Shumakovo",
    "wof:placetype":"locality"
},
  "geometry": {"coordinates":[61.91667,54.71666999999999],"type":"Point"}
}