{
  "type": "Feature",
  "properties": {
    "gn:admin1_code":"32",
    "gn:asciiname":"Rynkova V.",
    "gn:country_code":"RU",
    "gn:dem":62,
    "gn:feature_class":"P",
    "gn:feature_code":"PPL",
    "gn:name":"Rynkova V.",
    "gn:population":0,
    "gn:timezone":"Asia/Yekaterinburg",
    "iso:country":"RU",
    "name:rus_x_preferred":[
        "\u0420\u044b\u043d\u043a\u043e\u0432\u0430 \u0412."
    ],
    "wof:name":"Rynkova V.",
    "wof:placetype":"locality"
},
  "geometry": {"coordinates":[73.43333,61.36666999999999],"type":"Point"}
}