{
  "type": "Feature",
  "properties": {
    "gn:admin1_code":"56",
    "gn:asciiname":"Krasnaya Rybnitsa",
    "gn:country_code":"RU",
    "gn:dem":202,
    "gn:feature_class":"P",
    "gn:feature_code":"PPL",
    "gn:name":"Krasnaya Rybnitsa",
    "gn:population":0,
    "gn:timezone":"Europe/Moscow",
    "iso:country":"RU",
    "name:rus_x_preferred":[
        "\u041a\u0440\u0430\u0441\u043d\u0430\u044f \u0420\u044b\u0431\u043d\u0438\u0446\u0430"
    ],
    "name:und_x_variant":[
        "Rybnitsa",
        "Krasnaya Rybnitsa",
        "\u041a\u0440\u0430\u0441\u043d\u0430\u044f \u0420\u044b\u0431\u043d\u0438\u0446\u0430"
    ],
    "wof:name":"Krasnaya Rybnitsa",
    "wof:placetype":"locality"
},
  "geometry": {"coordinates":[36.25652,52.58331],"type":"Point"}
}