{
  "type": "Feature",
  "properties": {
    "gn:admin1_code":"62",
    "gn:asciiname":"Simushka",
    "gn:country_code":"RU",
    "gn:dem":124,
    "gn:feature_class":"P",
    "gn:feature_code":"PPL",
    "gn:name":"Simushka",
    "gn:population":0,
    "gn:timezone":"Europe/Moscow",
    "iso:country":"RU",
    "name:rus_x_preferred":[
        "\u0421\u0438\u043c\u0443\u0448\u043a\u0430"
    ],
    "wof:name":"Simushka",
    "wof:placetype":"locality"
},
  "geometry": {"coordinates":[42.5818,54.402],"type":"Point"}
}