{
  "type": "Feature",
  "properties": {
    "gn:admin1_code":"53",
    "gn:asciiname":"Bogoslovka",
    "gn:country_code":"RU",
    "gn:dem":106,
    "gn:feature_class":"P",
    "gn:feature_code":"PPL",
    "gn:name":"Bogoslovka",
    "gn:population":0,
    "gn:timezone":"Asia/Novosibirsk",
    "iso:country":"RU",
    "name:eng_x_preferred":[
        "Bogoslovka"
    ],
    "name:nor_x_preferred":[
        "Bogoslovka"
    ],
    "name:rus_x_preferred":[
        "\u0411\u043e\u0433\u043e\u0441\u043b\u043e\u0432\u043a\u0430"
    ],
    "name:und_x_variant":[
        "Bogoslavka",
        "\u0411\u043e\u0433\u043e\u0441\u043b\u043e\u0432\u043a\u0430",
        "Bogoslovka"
    ],
    "wof:name":"Bogoslovka",
    "wof:placetype":"locality"
},
  "geometry": {"coordinates":[77.30096999999998,53.68631],"type":"Point"}
}