{
  "type": "Feature",
  "properties": {
    "gn:admin1_code":"13",
    "gn:asciiname":"Yagodnaya",
    "gn:country_code":"RU",
    "gn:dem":463,
    "gn:feature_class":"P",
    "gn:feature_code":"PPL",
    "gn:name":"Yagodnaya",
    "gn:population":0,
    "gn:timezone":"Asia/Yekaterinburg",
    "iso:country":"RU",
    "name:rus_x_preferred":[
        "\u042f\u0433\u043e\u0434\u043d\u0430\u044f"
    ],
    "wof:name":"Yagodnaya",
    "wof:placetype":"locality"
},
  "geometry": {"coordinates":[59.5454,53.6559],"type":"Point"}
}