{
  "type": "Feature",
  "properties": {
    "gn:admin1_code":"30",
    "gn:asciiname":"Tyray",
    "gn:country_code":"RU",
    "gn:dem":49,
    "gn:feature_class":"P",
    "gn:feature_code":"PPL",
    "gn:name":"Tyray",
    "gn:population":0,
    "gn:timezone":"Asia/Vladivostok",
    "iso:country":"RU",
    "name:eng_x_preferred":[
        "Tyray"
    ],
    "name:nor_x_preferred":[
        "Tyraj"
    ],
    "name:rus_x_preferred":[
        "\u0422\u044b\u0440\u0430\u0439"
    ],
    "wof:name":"Tyray",
    "wof:placetype":"locality"
},
  "geometry": {"coordinates":[142.67762999999999,59.45322],"type":"Point"}
}