{
  "type": "Feature",
  "properties": {
    "gn:admin1_code":"28",
    "gn:asciiname":"Syuskyuya",
    "gn:country_code":"RU",
    "gn:dem":37,
    "gn:feature_class":"P",
    "gn:feature_code":"PPL",
    "gn:name":"Syuskyuya",
    "gn:population":0,
    "gn:timezone":"Europe/Moscow",
    "iso:country":"RU",
    "name:fin_x_preferred":[
        "Syysky\u00e4"
    ],
    "wof:name":"Syuskyuya",
    "wof:placetype":"locality"
},
  "geometry": {"coordinates":[31.28151,61.6188],"type":"Point"}
}