{
  "type": "Feature",
  "properties": {
    "gn:admin1_code":"37",
    "gn:asciiname":"Zales'ye",
    "gn:country_code":"RU",
    "gn:dem":165,
    "gn:feature_class":"P",
    "gn:feature_code":"PPL",
    "gn:name":"Zales\u2019ye",
    "gn:population":0,
    "gn:timezone":"Europe/Moscow",
    "iso:country":"RU",
    "name:rus_x_preferred":[
        "\u0417\u0430\u043b\u0435\u0441\u044c\u0435"
    ],
    "name:und_x_variant":[
        "Zales\u2019ye",
        "\u0417\u0430\u043b\u0435\u0441\u044c\u0435"
    ],
    "wof:name":"Zales'ye",
    "wof:placetype":"locality"
},
  "geometry": {"coordinates":[43.2976,58.3763],"type":"Point"}
}