{
  "type": "Feature",
  "properties": {
    "gn:admin1_code":"8",
    "gn:asciiname":"Novotroitsk",
    "gn:country_code":"RU",
    "gn:dem":229,
    "gn:feature_class":"P",
    "gn:feature_code":"PPL",
    "gn:name":"Novotroitsk",
    "gn:population":0,
    "gn:timezone":"Asia/Yekaterinburg",
    "iso:country":"RU",
    "name:rus_x_preferred":[
        "\u041d\u043e\u0432\u043e\u0442\u0440\u043e\u0438\u0446\u043a"
    ],
    "name:und_x_variant":[
        "\u041d\u043e\u0432\u043e\u0442\u0440\u043e\u0438\u0446\u043a"
    ],
    "wof:name":"Novotroitsk",
    "wof:placetype":"locality"
},
  "geometry": {"coordinates":[56.2454,54.3203],"type":"Point"}
}