{
  "type": "Feature",
  "properties": {
    "gn:admin1_code":"8",
    "gn:asciiname":"Tashkichi",
    "gn:country_code":"RU",
    "gn:dem":103,
    "gn:feature_class":"P",
    "gn:feature_code":"PPL",
    "gn:name":"Tashkichi",
    "gn:population":0,
    "gn:timezone":"Asia/Yekaterinburg",
    "iso:country":"RU",
    "name:und_x_variant":[
        "Tatarskiye Kichi",
        "Tashkichi"
    ],
    "wof:name":"Tashkichi",
    "wof:placetype":"locality"
},
  "geometry": {"coordinates":[54.47183,55.60456],"type":"Point"}
}