{
  "type": "Feature",
  "properties": {
    "gn:admin1_code":"85",
    "gn:asciiname":"Vanda",
    "gn:country_code":"RU",
    "gn:dem":170,
    "gn:feature_class":"P",
    "gn:feature_code":"PPL",
    "gn:name":"Vanda",
    "gn:population":0,
    "gn:timezone":"Europe/Moscow",
    "iso:country":"RU",
    "name:ara_x_preferred":[
        "\u0641\u0627\u0646\u062f\u0627"
    ],
    "name:bul_x_preferred":[
        "\u0412\u0430\u043d\u0434\u0430"
    ],
    "name:cat_x_preferred":[
        "Vanda"
    ],
    "name:ceb_x_preferred":[
        "Vanda"
    ],
    "name:ces_x_preferred":[
        "Vanda"
    ],
    "name:deu_x_preferred":[
        "Vanda"
    ],
    "name:eng_x_preferred":[
        "Vanda"
    ],
    "name:epo_x_preferred":[
        "Vandao"
    ],
    "name:fin_x_preferred":[
        "Vandat"
    ],
    "name:fra_x_preferred":[
        "Vanda"
    ],
    "name:hin_x_preferred":[
        "\u0935\u093e\u0902\u0921\u093e"
    ],
    "name:hun_x_preferred":[
        "Vanda"
    ],
    "name:ita_x_preferred":[
        "Vanda"
    ],
    "name:jpn_x_preferred":[
        "\u30d2\u30b9\u30a4\u30e9\u30f3\u5c5e"
    ],
    "name:koi_x_preferred":[
        "\u0412\u0430\u043d\u0434\u0430"
    ],
    "name:kom_x_preferred":[
        "\u0412\u0430\u043d\u0434\u0430"
    ],
    "name:lit_x_preferred":[
        "Vanda"
    ],
    "name:mal_x_preferred":[
        "\u0d2e\u0d30\u0d35\u0d3e\u0d34"
    ],
    "name:mrj_x_preferred":[
        "\u0412\u0430\u043d\u0434\u0430"
    ],
    "name:nor_x_preferred":[
        "Vanda"
    ],
    "name:pnb_x_preferred":[
        "\u0648\u0627\u0646\u0688\u0627"
    ],
    "name:pol_x_preferred":[
        "Wanda"
    ],
    "name:por_x_preferred":[
        "Vanda"
    ],
    "name:rus_x_preferred":[
        "\u0412\u0430\u043d\u0434\u0430"
    ],
    "name:slk_x_preferred":[
        "Vanda"
    ],
    "name:spa_x_preferred":[
        "Vanda"
    ],
    "name:srp_x_preferred":[
        "Vanda"
    ],
    "name:swe_x_preferred":[
        "Vandasl\u00e4ktet"
    ],
    "name:tha_x_preferred":[
        "\u0e41\u0e27\u0e19\u0e14\u0e49\u0e32"
    ],
    "name:udm_x_preferred":[
        "\u0412\u0430\u043d\u0434\u0430"
    ],
    "name:ukr_x_preferred":[
        "\u0412\u0430\u043d\u0434\u0430"
    ],
    "name:und_x_variant":[
        "Vyanda"
    ],
    "name:vie_x_preferred":[
        "Vanda"
    ],
    "name:war_x_preferred":[
        "Vanda"
    ],
    "name:zho_x_preferred":[
        "\u842c\u4ee3\u862d\u5c6c"
    ],
    "wof:name":"Vanda",
    "wof:placetype":"locality"
},
  "geometry": {"coordinates":[36.05,59.6853],"type":"Point"}
}