{
  "type": "Feature",
  "properties": {
    "gn:admin1_code":"85",
    "gn:asciiname":"Vanda",
    "gn:country_code":"RU",
    "gn:dem":170,
    "gn:feature_class":"P",
    "gn:feature_code":"PPL",
    "gn:name":"Vanda",
    "gn:population":0,
    "gn:timezone":"Europe/Moscow",
    "iso:country":"RU",
    "name:eng_x_preferred":[
        "Vanda"
    ],
    "name:nor_x_preferred":[
        "Vanda"
    ],
    "name:rus_x_preferred":[
        "\u0412\u0430\u043d\u0434\u0430"
    ],
    "name:und_x_variant":[
        "\u0412\u0430\u043d\u0434\u0430",
        "Vyanda"
    ],
    "wof:name":"Vanda",
    "wof:placetype":"locality"
},
  "geometry": {"coordinates":[36.05,59.6853],"type":"Point"}
}