{
  "type": "Feature",
  "properties": {
    "gn:admin1_code":"91",
    "gn:asciiname":"Badalozhnaya",
    "gn:country_code":"RU",
    "gn:dem":346,
    "gn:feature_class":"P",
    "gn:feature_code":"PPL",
    "gn:name":"Badalozhnaya",
    "gn:population":0,
    "gn:timezone":"Asia/Krasnoyarsk",
    "iso:country":"RU",
    "name:eng_x_preferred":[
        "Badalazhnyy"
    ],
    "name:rus_x_preferred":[
        "\u0411\u0430\u0434\u0430\u043b\u043e\u0436\u043d\u0430\u044f"
    ],
    "name:rus_x_variant":[
        "\u0411\u0430\u0434\u0430\u043bo\u0436\u043d\u0430\u044f"
    ],
    "name:und_x_variant":[
        "Badalazhnyy",
        "Badalozhnaya"
    ],
    "wof:name":"Badalozhnaya",
    "wof:placetype":"locality"
},
  "geometry": {"coordinates":[91.86809,56.0757],"type":"Point"}
}