{
  "type": "Feature",
  "properties": {
    "gn:admin1_code":"28",
    "gn:asciiname":"Ust'-Reka",
    "gn:country_code":"RU",
    "gn:dem":103,
    "gn:feature_class":"P",
    "gn:feature_code":"PPL",
    "gn:name":"Ust\u2019-Reka",
    "gn:population":0,
    "gn:timezone":"Europe/Moscow",
    "iso:country":"RU",
    "name:eng_x_preferred":[
        "Ust'-Reka"
    ],
    "name:nor_x_preferred":[
        "Ust-Reka"
    ],
    "name:rus_x_preferred":[
        "\u0423\u0441\u0442\u044c-\u0420\u0435\u043a\u0430"
    ],
    "name:und_x_variant":[
        "Dorshinskaya",
        "Ust\u2019-Reka"
    ],
    "wof:name":"Ust'-Reka",
    "wof:placetype":"locality"
},
  "geometry": {"coordinates":[37.72697,61.79085],"type":"Point"}
}