{
  "type": "Feature",
  "properties": {
    "gn:admin1_code":"60",
    "gn:asciiname":"Kostelevo",
    "gn:country_code":"RU",
    "gn:dem":149,
    "gn:feature_class":"P",
    "gn:feature_code":"PPL",
    "gn:name":"Kostel\u00ebvo",
    "gn:population":0,
    "gn:timezone":"Europe/Moscow",
    "iso:country":"RU",
    "name:rus_x_preferred":[
        "\u041a\u043e\u0441\u0442\u0435\u043b\u0451\u0432\u043e"
    ],
    "name:und_x_variant":[
        "Kostel\u00ebvo",
        "\u041a\u043e\u0441\u0442\u0435\u043b\u0451\u0432\u043e"
    ],
    "wof:name":"Kostelevo",
    "wof:placetype":"locality"
},
  "geometry": {"coordinates":[30.48945,55.96204],"type":"Point"}
}