{
  "type": "Feature",
  "properties": {
    "gn:admin1_code":"33",
    "gn:asciiname":"Pashino",
    "gn:country_code":"RU",
    "gn:dem":249,
    "gn:feature_class":"P",
    "gn:feature_code":"PPL",
    "gn:name":"Pashino",
    "gn:population":0,
    "gn:timezone":"Europe/Kirov",
    "iso:country":"RU",
    "name:rus_x_preferred":[
        "\u041f\u0430\u0448\u0438\u043d\u043e"
    ],
    "name:und_x_variant":[
        "Pashinskaya",
        "Pashino",
        "\u041f\u0430\u0448\u0438\u043d\u043e"
    ],
    "wof:name":"Pashino",
    "wof:placetype":"locality"
},
  "geometry": {"coordinates":[53.33354,58.77824],"type":"Point"}
}