{
  "type": "Feature",
  "properties": {
    "gn:admin1_code":"53",
    "gn:asciiname":"Druzhinino",
    "gn:country_code":"RU",
    "gn:dem":110,
    "gn:feature_class":"P",
    "gn:feature_code":"PPL",
    "gn:name":"Druzhinino",
    "gn:population":0,
    "gn:timezone":"Asia/Novosibirsk",
    "iso:country":"RU",
    "name:ceb_x_preferred":[
        "Druzhinino"
    ],
    "name:che_x_preferred":[
        "\u0414\u0440\u0443\u0436\u0438\u043d\u0438\u043d\u043e"
    ],
    "name:eng_x_preferred":[
        "Druzhinino"
    ],
    "name:hye_x_preferred":[
        "\u0534\u0580\u0578\u0582\u056a\u056b\u0576\u056b\u0576\u0578"
    ],
    "name:nor_x_preferred":[
        "Druzjinino"
    ],
    "name:rus_x_preferred":[
        "\u0414\u0440\u0443\u0436\u0438\u043d\u0438\u043d\u043e"
    ],
    "name:tat_x_preferred":[
        "\u0414\u0440\u0443\u0436\u0438\u043d\u0438\u043d\u043e"
    ],
    "name:tgk_x_preferred":[
        "\u0414\u0440\u0443\u0436\u0438\u043d\u0438\u043d\u043e"
    ],
    "name:und_x_variant":[
        "Druzhinina"
    ],
    "wof:name":"Druzhinino",
    "wof:placetype":"locality"
},
  "geometry": {"coordinates":[77.24450999999998,54.61783000000001],"type":"Point"}
}