{
  "type": "Feature",
  "properties": {
    "gn:admin1_code":"77",
    "gn:asciiname":"Davydtsevo",
    "gn:country_code":"RU",
    "gn:dem":136,
    "gn:feature_class":"P",
    "gn:feature_code":"PPL",
    "gn:name":"Davydtsevo",
    "gn:population":0,
    "gn:timezone":"Europe/Moscow",
    "iso:country":"RU",
    "name:rus_x_preferred":[
        "\u0414\u0430\u0432\u044b\u0434\u0446\u0435\u0432\u043e"
    ],
    "wof:name":"Davydtsevo",
    "wof:placetype":"locality"
},
  "geometry": {"coordinates":[36.6013,57.94600000000001],"type":"Point"}
}