{
  "type": "Feature",
  "properties": {
    "gn:admin1_code":"60",
    "gn:asciiname":"Lekalovo",
    "gn:country_code":"RU",
    "gn:dem":173,
    "gn:feature_class":"P",
    "gn:feature_code":"PPL",
    "gn:name":"Lekalovo",
    "gn:population":0,
    "gn:timezone":"Europe/Moscow",
    "iso:country":"RU",
    "name:rus_x_preferred":[
        "\u041b\u0435\u043a\u0430\u043b\u043e\u0432\u043e"
    ],
    "name:und_x_variant":[
        "\u041b\u0435\u043a\u0430\u043b\u043e\u0432\u043e"
    ],
    "wof:name":"Lekalovo",
    "wof:placetype":"locality"
},
  "geometry": {"coordinates":[30.60894,56.05904],"type":"Point"}
}