{
  "type": "Feature",
  "properties": {
    "gn:admin1_code":"11",
    "gn:asciiname":"Dunda-Kiret'",
    "gn:country_code":"RU",
    "gn:dem":625,
    "gn:feature_class":"P",
    "gn:feature_code":"PPL",
    "gn:name":"Dunda-Kiret\u2019",
    "gn:population":0,
    "gn:timezone":"Asia/Irkutsk",
    "iso:country":"RU",
    "name:eng_x_preferred":[
        "Dunda-Kiret'"
    ],
    "name:nor_x_preferred":[
        "Dunda-Kiret"
    ],
    "name:rus_x_preferred":[
        "\u0414\u0443\u043d\u0434\u0430-\u041a\u0438\u0440\u0435\u0442\u044c"
    ],
    "name:und_x_variant":[
        "Dunda-Kiret\u2019"
    ],
    "wof:name":"Dunda-Kiret'",
    "wof:placetype":"locality"
},
  "geometry": {"coordinates":[107.45667,50.57944000000001],"type":"Point"}
}