{
  "type": "Feature",
  "properties": {
    "gn:admin1_code":"51",
    "gn:asciiname":"Trekhrech'ye",
    "gn:country_code":"RU",
    "gn:dem":157,
    "gn:feature_class":"P",
    "gn:feature_code":"PPL",
    "gn:name":"Tr\u00ebkhrech\u2019ye",
    "gn:population":0,
    "gn:timezone":"Europe/Moscow",
    "iso:country":"RU",
    "name:rus_x_preferred":[
        "\u0422\u0440\u0451\u0445\u0440\u0435\u0447\u044c\u0435"
    ],
    "name:und_x_variant":[
        "Tr\u00ebkhrech\u2019ye",
        "\u0422\u0440\u0451\u0445\u0440\u0435\u0447\u044c\u0435"
    ],
    "wof:name":"Trekhrech'ye",
    "wof:placetype":"locality"
},
  "geometry": {"coordinates":[46.8701,57.6533],"type":"Point"}
}