{
  "type": "Feature",
  "properties": {
    "gn:admin1_code":"28",
    "gn:asciiname":"Mikkolya",
    "gn:cc2":"RU",
    "gn:country_code":"RU",
    "gn:dem":131,
    "gn:feature_class":"P",
    "gn:feature_code":"PPL",
    "gn:name":"Mikkolya",
    "gn:population":0,
    "gn:timezone":"Europe/Moscow",
    "iso:country":"RU",
    "name:fin_x_preferred":[
        "Mikkola"
    ],
    "name:rus_x_preferred":[
        "\u041c\u0438\u043a\u043a\u043e\u043b\u044f"
    ],
    "wof:name":"Mikkolya",
    "wof:placetype":"locality"
},
  "geometry": {"coordinates":[31.66667,65.21666999999999],"type":"Point"}
}