{
  "type": "Feature",
  "properties": {
    "gn:admin1_code":"16",
    "gn:asciiname":"Sirma-Pos'",
    "gn:country_code":"RU",
    "gn:dem":133,
    "gn:feature_class":"P",
    "gn:feature_code":"PPL",
    "gn:name":"Sirma-Pos\u2019",
    "gn:population":0,
    "gn:timezone":"Europe/Moscow",
    "iso:country":"RU",
    "name:rus_x_preferred":[
        "\u0421\u0438\u0440\u043c\u0430-\u041f\u043e\u0441\u044c"
    ],
    "name:und_x_variant":[
        "Sirma-Pos\u2019",
        "\u0421\u0438\u0440\u043c\u0430-\u041f\u043e\u0441\u044c"
    ],
    "wof:name":"Sirma-Pos'",
    "wof:placetype":"locality"
},
  "geometry": {"coordinates":[47.13333,55.86666999999999],"type":"Point"}
}