{
  "type": "Feature",
  "properties": {
    "gn:admin1_code":"13.0",
    "gn:asciiname":"Churilovskiy Peschanyy Kar'yer",
    "gn:country_code":"RU",
    "gn:dem":199,
    "gn:feature_class":"P",
    "gn:feature_code":"PPL",
    "gn:name":"Churilovskiy Peschanyy Kar\u2019yer",
    "gn:population":0,
    "gn:timezone":"Asia/Yekaterinburg",
    "iso:country":"RU",
    "name:rus_x_preferred":[
        "\u0427\u0443\u0440\u0438\u043b\u043e\u0432\u0441\u043a\u0438\u0439 \u041f\u0435\u0441\u0447\u0430\u043d\u044b\u0439 \u041a\u0430\u0440\u044c\u0435\u0440"
    ],
    "name:und_x_variant":[
        "Churilovskiy Peschanyy Kar\u2019yer",
        "Churilovskiy Pesochnyy Kar\u2019yer"
    ],
    "wof:name":"Churilovskiy Peschanyy Kar'yer",
    "wof:placetype":"locality"
},
  "geometry": {"coordinates":[61.54686,55.22273000000001],"type":"Point"}
}