{
  "type": "Feature",
  "properties": {
    "gn:admin1_code":"64",
    "gn:asciiname":"Tret'ya Pad'",
    "gn:country_code":"RU",
    "gn:dem":47,
    "gn:feature_class":"P",
    "gn:feature_code":"PPL",
    "gn:name":"Tret\u2019ya Pad\u2019",
    "gn:population":0,
    "gn:timezone":"Asia/Sakhalin",
    "iso:country":"RU",
    "name:eng_x_preferred":[
        "Tret'ya Pad'"
    ],
    "name:nor_x_preferred":[
        "Tretja-Pad"
    ],
    "name:rus_x_preferred":[
        "\u0422\u0440\u0435\u0442\u044c\u044f-\u041f\u0430\u0434\u044c"
    ],
    "name:und_x_variant":[
        "Chitose",
        "Torechipaachi",
        "Peterpach\u2019",
        "Sannosawa",
        "Tret\u2019ya Pad\u2019"
    ],
    "wof:name":"Tret'ya Pad'",
    "wof:placetype":"locality"
},
  "geometry": {"coordinates":[142.74435,46.70434],"type":"Point"}
}