{
  "type": "Feature",
  "properties": {
    "gn:admin1_code":"85",
    "gn:asciiname":"Kostenevo",
    "gn:country_code":"RU",
    "gn:dem":179,
    "gn:feature_class":"P",
    "gn:feature_code":"PPL",
    "gn:name":"Kosten\u00ebvo",
    "gn:population":0,
    "gn:timezone":"Europe/Moscow",
    "iso:country":"RU",
    "name:eng_x_preferred":[
        "Kosten\u00ebvo"
    ],
    "name:nor_x_preferred":[
        "Kostenevo"
    ],
    "name:rus_x_preferred":[
        "\u041a\u043e\u0441\u0442\u0435\u043d\u0435\u0432\u043e"
    ],
    "name:rus_x_variant":[
        "\u041a\u043e\u0441\u0442\u0435\u043d\u0451\u0432\u043e"
    ],
    "wof:name":"Kostenevo",
    "wof:placetype":"locality"
},
  "geometry": {"coordinates":[44.65096,59.63414],"type":"Point"}
}