{
  "type": "Feature",
  "properties": {
    "gn:admin1_code":"85.0",
    "gn:asciiname":"Brusnovolovskiy Pogost",
    "gn:country_code":"RU",
    "gn:dem":140,
    "gn:feature_class":"P",
    "gn:feature_code":"PPL",
    "gn:name":"Brusnovolovskiy Pogost",
    "gn:population":0,
    "gn:timezone":"Europe/Moscow",
    "iso:country":"RU",
    "name:rus_x_preferred":[
        "\u0411\u0440\u0443\u0441\u043d\u043e\u0432\u043e\u043b\u043e\u0432\u0441\u043a\u0438\u0439 \u041f\u043e\u0433\u043e\u0441\u0442"
    ],
    "name:und_x_variant":[
        "Brusnovalovskiy Pogost",
        "Brusnovskiy Pogost",
        "Brusnovolovskiy Pogost",
        "\u0411\u0440\u0443\u0441\u043d\u043e\u0432\u043e\u043b\u043e\u0432\u0441\u043a\u0438\u0439 \u041f\u043e\u0433\u043e\u0441\u0442"
    ],
    "wof:name":"Brusnovolovskiy Pogost",
    "wof:placetype":"locality"
},
  "geometry": {"coordinates":[44.09023,60.22016],"type":"Point"}
}