{
  "type": "Feature",
  "properties": {
    "gn:admin1_code":"69",
    "gn:asciiname":"Konoplinka",
    "gn:cc2":"RU",
    "gn:country_code":"RU",
    "gn:dem":224,
    "gn:feature_class":"P",
    "gn:feature_code":"PPL",
    "gn:name":"Konoplinka",
    "gn:population":0,
    "gn:timezone":"Europe/Moscow",
    "iso:country":"RU",
    "name:rus_x_preferred":[
        "\u041a\u043e\u043d\u043e\u043f\u043b\u0438\u043d\u043a\u0430"
    ],
    "name:und_x_variant":[
        "Konoplyanka",
        "Konoplinka"
    ],
    "wof:name":"Konoplinka",
    "wof:placetype":"locality"
},
  "geometry": {"coordinates":[33.33722,54.57278],"type":"Point"}
}