{
  "type": "Feature",
  "properties": {
    "gn:admin1_code":"8",
    "gn:asciiname":"Marshanovka",
    "gn:country_code":"RU",
    "gn:dem":153,
    "gn:feature_class":"P",
    "gn:feature_code":"PPL",
    "gn:name":"Marshanovka",
    "gn:population":0,
    "gn:timezone":"Asia/Yekaterinburg",
    "iso:country":"RU",
    "name:rus_x_preferred":[
        "\u041c\u0430\u0440\u0448\u0430\u043d\u043e\u0432\u043a\u0430"
    ],
    "wof:name":"Marshanovka",
    "wof:placetype":"locality"
},
  "geometry": {"coordinates":[55.71179,53.67303],"type":"Point"}
}