{
  "type": "Feature",
  "properties": {
    "gn:admin1_code":"77",
    "gn:asciiname":"Berdovka",
    "gn:country_code":"RU",
    "gn:dem":125,
    "gn:feature_class":"P",
    "gn:feature_code":"PPL",
    "gn:name":"Berdovka",
    "gn:population":0,
    "gn:timezone":"Europe/Moscow",
    "iso:country":"RU",
    "name:rus_x_preferred":[
        "\u0411\u0435\u0440\u0434\u043e\u0432\u043a\u0430"
    ],
    "name:und_x_variant":[
        "Oberdovka"
    ],
    "wof:name":"Berdovka",
    "wof:placetype":"locality"
},
  "geometry": {"coordinates":[38.01667,57.11666999999999],"type":"Point"}
}