{
  "type": "Feature",
  "properties": {
    "gn:admin1_code":"20",
    "gn:asciiname":"Aprel'sk",
    "gn:country_code":"RU",
    "gn:dem":740,
    "gn:feature_class":"P",
    "gn:feature_code":"PPL",
    "gn:name":"Aprel\u2019sk",
    "gn:population":0,
    "gn:timezone":"Asia/Irkutsk",
    "iso:country":"RU",
    "name:che_x_preferred":[
        "\u0410\u043f\u0440\u0435\u043b\u044c\u0441\u043a"
    ],
    "name:eng_x_preferred":[
        "Aprel'sk"
    ],
    "name:lit_x_preferred":[
        "Aprelskas"
    ],
    "name:nor_x_preferred":[
        "Aprelsk"
    ],
    "name:rus_x_preferred":[
        "\u0410\u043f\u0440\u0435\u043b\u044c\u0441\u043a"
    ],
    "name:und_x_variant":[
        "\u0410\u043f\u0440\u0435\u043b\u044c\u0441\u043a",
        "Aprel\u2019sk"
    ],
    "wof:name":"Aprel'sk",
    "wof:placetype":"locality"
},
  "geometry": {"coordinates":[114.54056,58.17944],"type":"Point"}
}