{
  "type": "Feature",
  "properties": {
    "gn:country":"RU",
    "gn:fcode":"PPL",
    "gn:pop":7356,
    "iso:country":"RU",
    "name:che_x_preferred":[
        "\u0420\u0435\u0448\u0435\u0442\u0438\u0445\u0430"
    ],
    "name:eng_x_preferred":[
        "Reshetikha"
    ],
    "name:nor_x_preferred":[
        "Resjetikha"
    ],
    "name:rus_x_preferred":[
        "\u0420\u0435\u0448\u0435\u0442\u0438\u0445\u0430"
    ],
    "qs:name":"Reshetikha",
    "qs:photos_9r":0,
    "qs:photos_sr":0,
    "qs:pop_sr":"5",
    "wof:name":"Reshetikha",
    "wof:placetype":"locality",
    "wof:population":7356
},
  "geometry": {"coordinates":[43.28802,56.21566],"type":"Point"}
}