{
  "type": "Feature",
  "properties": {
    "gn:admin1_code":"56",
    "gn:asciiname":"Lesnoye",
    "gn:country_code":"RU",
    "gn:dem":255,
    "gn:feature_class":"P",
    "gn:feature_code":"PPL",
    "gn:name":"Lesnoye",
    "gn:population":0,
    "gn:timezone":"Europe/Moscow",
    "iso:country":"RU",
    "name:rus_x_preferred":[
        "\u041b\u0435\u0441\u043d\u043e\u0435"
    ],
    "name:und_x_variant":[
        "\u041b\u0435\u0441\u043d\u043e\u0435"
    ],
    "wof:name":"Lesnoye",
    "wof:placetype":"locality"
},
  "geometry": {"coordinates":[36.66667,52.85],"type":"Point"}
}