{
  "type": "Feature",
  "properties": {
    "gn:admin1_code":"73",
    "gn:asciiname":"Olimpiadovka",
    "gn:country_code":"RU",
    "gn:dem":148,
    "gn:feature_class":"P",
    "gn:feature_code":"PPL",
    "gn:name":"Olimpiadovka",
    "gn:population":0,
    "gn:timezone":"Europe/Moscow",
    "iso:country":"RU",
    "name:rus_x_preferred":[
        "\u041e\u043b\u0438\u043c\u043f\u0438\u0430\u0434\u043e\u0432\u043a\u0430"
    ],
    "wof:name":"Olimpiadovka",
    "wof:placetype":"locality"
},
  "geometry": {"coordinates":[51.64407,54.98432],"type":"Point"}
}