{
  "type": "Feature",
  "properties": {
    "gn:admin1_code":"73",
    "gn:asciiname":"Nizhnyaya Kuz'mes'",
    "gn:country_code":"RU",
    "gn:dem":103,
    "gn:feature_class":"P",
    "gn:feature_code":"PPL",
    "gn:name":"Nizhnyaya Kuz\u2019mes\u2019",
    "gn:population":0,
    "gn:timezone":"Europe/Moscow",
    "iso:country":"RU",
    "name:rus_x_preferred":[
        "\u041d\u0438\u0436\u043d\u044f\u044f \u041a\u0443\u0437\u044c\u043c\u0435\u0441\u044c"
    ],
    "name:und_x_variant":[
        "Nizhnyaya Kuz\u2019mes\u2019"
    ],
    "wof:name":"Nizhnyaya Kuz'mes'",
    "wof:placetype":"locality"
},
  "geometry": {"coordinates":[50.5697,56.2094],"type":"Point"}
}