{
  "type": "Feature",
  "properties": {
    "gn:admin1_code":"91.0",
    "gn:asciiname":"Dachi Ibryul'",
    "gn:country_code":"RU",
    "gn:dem":250,
    "gn:feature_class":"P",
    "gn:feature_code":"PPL",
    "gn:name":"Dachi Ibryul\u2019",
    "gn:population":0,
    "gn:timezone":"Asia/Krasnoyarsk",
    "iso:country":"RU",
    "name:rus_x_preferred":[
        "\u0414\u0430\u0447\u0438 \u0418\u0431\u0440\u044e\u043b\u044c"
    ],
    "name:und_x_variant":[
        "Dachi Ibryul\u2019",
        "Ibryul\u2019"
    ],
    "wof:name":"Dachi Ibryul'",
    "wof:placetype":"locality"
},
  "geometry": {"coordinates":[91.00535000000001,56.30819],"type":"Point"}
}