{
  "type": "Feature",
  "properties": {
    "gn:admin1_code":"88",
    "gn:asciiname":"Pechkino",
    "gn:country_code":"RU",
    "gn:dem":125,
    "gn:feature_class":"P",
    "gn:feature_code":"PPL",
    "gn:name":"Pechkino",
    "gn:population":0,
    "gn:timezone":"Europe/Moscow",
    "iso:country":"RU",
    "name:rus_x_preferred":[
        "\u041f\u0435\u0447\u043a\u0438\u043d\u043e"
    ],
    "name:und_x_variant":[
        "\u041f\u0435\u0447\u043a\u0438\u043d\u043e"
    ],
    "wof:name":"Pechkino",
    "wof:placetype":"locality"
},
  "geometry": {"coordinates":[38.3945,57.5262],"type":"Point"}
}