{
  "type": "Feature",
  "properties": {
    "gn:admin1_code":"55.0",
    "gn:asciiname":"Cherepanovka",
    "gn:country_code":"RU",
    "gn:dem":203,
    "gn:feature_class":"P",
    "gn:feature_code":"PPL",
    "gn:name":"Cherepanovka",
    "gn:population":0,
    "gn:timezone":"Asia/Yekaterinburg",
    "iso:country":"RU",
    "name:rus_x_preferred":[
        "\u0427\u0435\u0440\u0435\u043f\u0430\u043d\u043e\u0432\u043a\u0430"
    ],
    "name:und_x_variant":[
        "\u0427\u0435\u0440\u0435\u043f\u0430\u043d\u043e\u0432\u043a\u0430"
    ],
    "wof:name":"Cherepanovka",
    "wof:placetype":"locality"
},
  "geometry": {"coordinates":[56.3441,52.09304],"type":"Point"}
}