{
  "type": "Feature",
  "properties": {
    "gn:admin1_code":"73",
    "gn:asciiname":"Verkhnyaya Kamenka",
    "gn:country_code":"RU",
    "gn:dem":128,
    "gn:feature_class":"P",
    "gn:feature_code":"PPL",
    "gn:name":"Verkhnyaya Kamenka",
    "gn:population":0,
    "gn:timezone":"Europe/Moscow",
    "iso:country":"RU",
    "name:eng_x_preferred":[
        "Verkhnyaya Kamenka"
    ],
    "name:nor_x_preferred":[
        "Verkhnjaja Kamenka"
    ],
    "name:rus_x_preferred":[
        "\u0412\u0435\u0440\u0445\u043d\u044f\u044f \u041a\u0430\u043c\u0435\u043d\u043a\u0430"
    ],
    "name:und_x_variant":[
        "\u0412\u0435\u0440\u0445\u043d\u044f\u044f \u041a\u0430\u043c\u0435\u043d\u043a\u0430"
    ],
    "wof:name":"Verkhnyaya Kamenka",
    "wof:placetype":"locality"
},
  "geometry": {"coordinates":[51.47023,54.80538000000001],"type":"Point"}
}