{
  "type": "Feature",
  "properties": {
    "gn:admin1_code":"47",
    "gn:asciiname":"Zubovo",
    "gn:country_code":"RU",
    "gn:dem":201,
    "gn:feature_class":"P",
    "gn:feature_code":"PPL",
    "gn:name":"Zubovo",
    "gn:population":0,
    "gn:timezone":"Europe/Moscow",
    "iso:country":"RU",
    "wof:name":"Zubovo",
    "wof:placetype":"locality"
},
  "geometry": {"coordinates":[35.80551,56.02398],"type":"Point"}
}