{
  "type": "Feature",
  "properties": {
    "gn:admin1_code":"90.0",
    "gn:asciiname":"Arazayeva",
    "gn:country_code":"RU",
    "gn:dem":197,
    "gn:feature_class":"P",
    "gn:feature_code":"PPL",
    "gn:name":"Arazayeva",
    "gn:population":0,
    "gn:timezone":"Asia/Yekaterinburg",
    "iso:country":"RU",
    "name:rus_x_preferred":[
        "\u0410\u0440\u0430\u0437\u0430\u0435\u0432\u0430"
    ],
    "wof:name":"Arazayeva",
    "wof:placetype":"locality"
},
  "geometry": {"coordinates":[54.0843,58.835],"type":"Point"}
}