{
  "type": "Feature",
  "properties": {
    "gn:admin1_code":"37.0",
    "gn:asciiname":"Konishchevo",
    "gn:country_code":"RU",
    "gn:dem":150,
    "gn:feature_class":"P",
    "gn:feature_code":"PPL",
    "gn:name":"Konishchevo",
    "gn:population":0,
    "gn:timezone":"Europe/Moscow",
    "iso:country":"RU",
    "name:nor_x_preferred":[
        "Konisjtsjevo"
    ],
    "name:rus_x_preferred":[
        "\u041a\u043e\u043d\u0438\u0449\u0435\u0432\u043e"
    ],
    "wof:name":"Konishchevo",
    "wof:placetype":"locality"
},
  "geometry": {"coordinates":[41.66722,58.34],"type":"Point"}
}