{
  "type": "Feature",
  "properties": {
    "gn:admin1_code":"77",
    "gn:asciiname":"Malyye Ushany",
    "gn:country_code":"RU",
    "gn:dem":203,
    "gn:feature_class":"P",
    "gn:feature_code":"PPL",
    "gn:name":"Malyye Ushany",
    "gn:population":0,
    "gn:timezone":"Europe/Moscow",
    "iso:country":"RU",
    "name:rus_x_preferred":[
        "\u041c\u0430\u043b\u044b\u0435 \u0423\u0448\u0430\u043d\u044b"
    ],
    "name:und_x_variant":[
        "Malyye Ushchani",
        "Malyye Ushany"
    ],
    "wof:name":"Malyye Ushany",
    "wof:placetype":"locality"
},
  "geometry": {"coordinates":[32.33547,56.23302],"type":"Point"}
}