{
  "type": "Feature",
  "properties": {
    "gn:admin1_code":"80",
    "gn:asciiname":"Gol'yanskiy",
    "gn:country_code":"RU",
    "gn:dem":137,
    "gn:feature_class":"P",
    "gn:feature_code":"PPL",
    "gn:name":"Gol\u2019yanskiy",
    "gn:population":0,
    "gn:timezone":"Europe/Samara",
    "iso:country":"RU",
    "name:eng_x_preferred":[
        "Gol'yanskiy"
    ],
    "name:nor_x_preferred":[
        "Goljanskij"
    ],
    "name:rus_x_preferred":[
        "\u0413\u043e\u043b\u044c\u044f\u043d\u0441\u043a\u0438\u0439"
    ],
    "name:und_x_variant":[
        "Gol\u2019yany",
        "Gol\u2019yansk",
        "\u0413\u043e\u043b\u044c\u044f\u043d\u0441\u043a\u0438\u0439",
        "Gol\u2019yanskiy"
    ],
    "wof:name":"Gol'yanskiy",
    "wof:placetype":"locality"
},
  "geometry": {"coordinates":[53.5197,56.89686],"type":"Point"}
}