{
  "type": "Feature",
  "properties": {
    "gn:admin1_code":"88.0",
    "gn:asciiname":"Molozevo",
    "gn:country_code":"RU",
    "gn:dem":129,
    "gn:feature_class":"P",
    "gn:feature_code":"PPL",
    "gn:name":"Molozevo",
    "gn:population":0,
    "gn:timezone":"Europe/Moscow",
    "iso:country":"RU",
    "name:rus_x_preferred":[
        "\u041c\u043e\u043b\u043e\u0437\u0435\u0432\u043e"
    ],
    "name:und_x_variant":[
        "\u041c\u043e\u043b\u043e\u0437\u0435\u0432\u043e"
    ],
    "wof:name":"Molozevo",
    "wof:placetype":"locality"
},
  "geometry": {"coordinates":[40.485,58.44833000000001],"type":"Point"}
}