{
  "type": "Feature",
  "properties": {
    "gn:admin1_code":"69",
    "gn:asciiname":"Kolpenitsa",
    "gn:country_code":"RU",
    "gn:dem":201,
    "gn:feature_class":"P",
    "gn:feature_code":"PPL",
    "gn:name":"Kolpenitsa",
    "gn:population":0,
    "gn:timezone":"Europe/Moscow",
    "iso:country":"RU",
    "name:eng_x_preferred":[
        "Kolpenitsa"
    ],
    "name:nor_x_preferred":[
        "Kolpenitsa"
    ],
    "name:rus_x_preferred":[
        "\u041a\u043e\u043b\u043f\u0435\u043d\u0438\u0446\u0430"
    ],
    "name:und_x_variant":[
        "Kolpenitskiye",
        "Kolpenitsa"
    ],
    "wof:name":"Kolpenitsa",
    "wof:placetype":"locality"
},
  "geometry": {"coordinates":[32.6508,54.0267],"type":"Point"}
}