{
  "type": "Feature",
  "properties": {
    "gn:admin1_code":"91",
    "gn:asciiname":"Mazul'",
    "gn:country_code":"RU",
    "gn:dem":219,
    "gn:feature_class":"P",
    "gn:feature_code":"PPL",
    "gn:name":"Mazul\u2019",
    "gn:population":0,
    "gn:timezone":"Asia/Krasnoyarsk",
    "iso:country":"RU",
    "name:rus_x_preferred":[
        "\u041c\u0430\u0437\u0443\u043b\u044c"
    ],
    "name:und_x_variant":[
        "Mazul\u2019"
    ],
    "wof:name":"Mazul'",
    "wof:placetype":"locality"
},
  "geometry": {"coordinates":[90.47069999999999,56.2478],"type":"Point"}
}