{
  "type": "Feature",
  "properties": {
    "gn:admin1_code":"68",
    "gn:asciiname":"Kuskhomaykho",
    "gn:country_code":"RU",
    "gn:dem":701,
    "gn:feature_class":"P",
    "gn:feature_code":"PPL",
    "gn:name":"Kuskhomaykho",
    "gn:population":0,
    "gn:timezone":"Europe/Moscow",
    "iso:country":"RU",
    "name:rus_x_preferred":[
        "\u041a\u0443\u0441\u0445\u043e\u043c\u0430\u0439\u0445\u043e"
    ],
    "wof:name":"Kuskhomaykho",
    "wof:placetype":"locality"
},
  "geometry": {"coordinates":[43.91111,43.15944],"type":"Point"}
}