{
  "type": "Feature",
  "properties": {
    "gn:admin1_code":"88",
    "gn:asciiname":"Yaksayevo",
    "gn:country_code":"RU",
    "gn:dem":140,
    "gn:feature_class":"P",
    "gn:feature_code":"PPL",
    "gn:name":"Yaksayevo",
    "gn:population":0,
    "gn:timezone":"Europe/Moscow",
    "iso:country":"RU",
    "name:rus_x_preferred":[
        "\u042f\u043a\u0441\u0430\u0435\u0432\u043e"
    ],
    "wof:name":"Yaksayevo",
    "wof:placetype":"locality"
},
  "geometry": {"coordinates":[37.86861,57.8011],"type":"Point"}
}