{
  "type": "Feature",
  "properties": {
    "gn:admin1_code":"23",
    "gn:asciiname":"Putyatino",
    "gn:country_code":"RU",
    "gn:dem":68,
    "gn:feature_class":"P",
    "gn:feature_code":"PPL",
    "gn:name":"Putyatino",
    "gn:population":0,
    "gn:timezone":"Europe/Kaliningrad",
    "iso:country":"RU",
    "name:rus_x_preferred":[
        "\u041f\u0443\u0442\u044f\u0442\u0438\u043d\u043e"
    ],
    "wof:name":"Putyatino",
    "wof:placetype":"locality"
},
  "geometry": {"coordinates":[22.08083,54.49583000000001],"type":"Point"}
}