{
  "type": "Feature",
  "properties": {
    "gn:admin1_code":"63",
    "gn:asciiname":"Bayaga",
    "gn:country_code":"RU",
    "gn:dem":192,
    "gn:feature_class":"P",
    "gn:feature_code":"PPL",
    "gn:name":"Bayaga",
    "gn:population":0,
    "gn:timezone":"Asia/Yakutsk",
    "iso:country":"RU",
    "name:nor_x_preferred":[
        "Bajaga"
    ],
    "name:rus_x_preferred":[
        "\u0411\u0430\u044f\u0433\u0430"
    ],
    "wof:name":"Bayaga",
    "wof:placetype":"locality"
},
  "geometry": {"coordinates":[132.76667,62.86666999999999],"type":"Point"}
}