{
  "type": "Feature",
  "properties": {
    "gn:country":"RU",
    "gn:fcode":"PPL",
    "gn:pop":13229,
    "iso:country":"RU",
    "name:eng_x_preferred":[
        "Vetluzhskiy"
    ],
    "name:nor_x_preferred":[
        "Vetluzjskij"
    ],
    "name:rus_x_preferred":[
        "\u0412\u0435\u0442\u043b\u0443\u0436\u0441\u043a\u0438\u0439"
    ],
    "name:unk_x_variant":[
        "Golyshi"
    ],
    "qs:name":"Vetluzhskiy",
    "qs:photos_9r":0,
    "qs:photos_sr":0,
    "qs:pop_sr":"6",
    "wd:wordcount":31,
    "wof:name":"Vetluzhskiy",
    "wof:placetype":"locality",
    "wof:population":13229
},
  "geometry": {"coordinates":[45.46542,58.39016],"type":"Point"}
}