{
  "type": "Feature",
  "properties": {
    "gn:admin1_code":"21.0",
    "gn:asciiname":"Pichugino",
    "gn:country_code":"RU",
    "gn:dem":105,
    "gn:feature_class":"P",
    "gn:feature_code":"PPL",
    "gn:name":"Pichugino",
    "gn:population":0,
    "gn:timezone":"Europe/Moscow",
    "iso:country":"RU",
    "name:rus_x_preferred":[
        "\u041f\u0438\u0447\u0443\u0433\u0438\u043d\u043e"
    ],
    "name:und_x_variant":[
        "\u041f\u0438\u0447\u0443\u0433\u0438\u043d\u043e"
    ],
    "wof:name":"Pichugino",
    "wof:placetype":"locality"
},
  "geometry": {"coordinates":[42.51702,57.2292],"type":"Point"}
}