{
  "type": "Feature",
  "properties": {
    "gn:admin1_code":"61.0",
    "gn:asciiname":"Krasnoye Utro",
    "gn:country_code":"RU",
    "gn:dem":66,
    "gn:feature_class":"P",
    "gn:feature_code":"PPL",
    "gn:name":"Krasnoye Utro",
    "gn:population":0,
    "gn:timezone":"Europe/Moscow",
    "iso:country":"RU",
    "name:rus_x_preferred":[
        "\u041a\u0440\u0430\u0441\u043d\u043e\u0435 \u0423\u0442\u0440\u043e"
    ],
    "name:und_x_variant":[
        "\u041a\u0440\u0430\u0441\u043d\u043e\u0435 \u0423\u0442\u0440\u043e"
    ],
    "wof:name":"Krasnoye Utro",
    "wof:placetype":"locality"
},
  "geometry": {"coordinates":[40.70088,49.02886],"type":"Point"}
}