{
  "type": "Feature",
  "properties": {
    "gn:admin1_code":"33.0",
    "gn:asciiname":"Batashi",
    "gn:country_code":"RU",
    "gn:dem":130,
    "gn:feature_class":"P",
    "gn:feature_code":"PPL",
    "gn:name":"Batashi",
    "gn:population":0,
    "gn:timezone":"Europe/Kirov",
    "iso:country":"RU",
    "name:nor_x_preferred":[
        "Batasji"
    ],
    "name:rus_x_preferred":[
        "\u0411\u0430\u0442\u0430\u0448\u0438"
    ],
    "wof:name":"Batashi",
    "wof:placetype":"locality"
},
  "geometry": {"coordinates":[49.99039000000001,58.62024],"type":"Point"}
}