{
  "type": "Feature",
  "properties": {
    "gn:admin1_code":"52",
    "gn:asciiname":"Velikoye Selo",
    "gn:country_code":"RU",
    "gn:dem":84,
    "gn:feature_class":"P",
    "gn:feature_code":"PPL",
    "gn:name":"Velikoye Selo",
    "gn:population":0,
    "gn:timezone":"Europe/Moscow",
    "iso:country":"RU",
    "name:rus_x_preferred":[
        "\u0412\u0435\u043b\u0438\u043a\u043e\u0435 \u0421\u0435\u043b\u043e"
    ],
    "wof:name":"Velikoye Selo",
    "wof:placetype":"locality"
},
  "geometry": {"coordinates":[30.81853,57.54444],"type":"Point"}
}