{
  "type": "Feature",
  "properties": {
    "gn:admin1_code":"77",
    "gn:asciiname":"Simanovo",
    "gn:country_code":"RU",
    "gn:dem":231,
    "gn:feature_class":"P",
    "gn:feature_code":"PPL",
    "gn:name":"Simanovo",
    "gn:population":0,
    "gn:timezone":"Europe/Moscow",
    "iso:country":"RU",
    "name:rus_x_preferred":[
        "\u0421\u0438\u043c\u0430\u043d\u043e\u0432\u043e"
    ],
    "wof:name":"Simanovo",
    "wof:placetype":"locality"
},
  "geometry": {"coordinates":[31.56471,56.78894],"type":"Point"}
}