{
  "type": "Feature",
  "properties": {
    "gn:admin1_code":"88",
    "gn:asciiname":"Petrunino",
    "gn:country_code":"RU",
    "gn:dem":171,
    "gn:feature_class":"P",
    "gn:feature_code":"PPL",
    "gn:name":"Petrunino",
    "gn:population":0,
    "gn:timezone":"Europe/Moscow",
    "iso:country":"RU",
    "name:rus_x_preferred":[
        "\u041f\u0435\u0442\u0440\u0443\u043d\u0438\u043d\u043e"
    ],
    "wof:name":"Petrunino",
    "wof:placetype":"locality"
},
  "geometry": {"coordinates":[39.29897,57.55859],"type":"Point"}
}