{
  "type": "Feature",
  "properties": {
    "gn:admin1_code":"20",
    "gn:admin2_code":"2023464",
    "gn:asciiname":"Shara-Togot",
    "gn:country_code":"RU",
    "gn:dem":562,
    "gn:feature_class":"P",
    "gn:feature_code":"PPL",
    "gn:name":"Shara-Togot",
    "gn:population":375,
    "gn:timezone":"Asia/Irkutsk",
    "iso:country":"RU",
    "name:eng_x_preferred":[
        "Shara-Togot"
    ],
    "name:nor_x_preferred":[
        "Tsjernorud"
    ],
    "name:rus_x_preferred":[
        "\u0427\u0435\u0440\u043d\u043e\u0440\u0443\u0434"
    ],
    "name:rus_x_variant":[
        "\u0428\u0430\u0440\u0430-\u0422\u043e\u0433\u043e\u0442"
    ],
    "name:und_x_variant":[
        "Chernorud",
        "Shira-Togot",
        "Togot"
    ],
    "wof:name":"Shara-Togot",
    "wof:placetype":"locality",
    "wof:population":375
},
  "geometry": {"coordinates":[106.715,52.99889],"type":"Point"}
}