{
  "type": "Feature",
  "properties": {
    "gn:admin1_code":"77",
    "gn:asciiname":"Smenovo",
    "gn:cc2":"RU",
    "gn:country_code":"RU",
    "gn:dem":163,
    "gn:feature_class":"P",
    "gn:feature_code":"PPL",
    "gn:name":"Smenovo",
    "gn:population":0,
    "gn:timezone":"Europe/Moscow",
    "iso:country":"RU",
    "name:rus_x_preferred":[
        "\u0421\u043c\u0435\u043d\u043e\u0432\u043e"
    ],
    "name:und_x_variant":[
        "Smenova",
        "Smenovo"
    ],
    "wof:name":"Smenovo",
    "wof:placetype":"locality"
},
  "geometry": {"coordinates":[34.97944,57.75471999999999],"type":"Point"}
}