{
  "type": "Feature",
  "properties": {
    "gn:admin1_code":"69",
    "gn:asciiname":"Lozki",
    "gn:country_code":"RU",
    "gn:dem":203,
    "gn:feature_class":"P",
    "gn:feature_code":"PPL",
    "gn:name":"Lozki",
    "gn:population":0,
    "gn:timezone":"Europe/Moscow",
    "iso:country":"RU",
    "name:rus_x_preferred":[
        "\u041b\u043e\u0437\u043a\u0438"
    ],
    "name:und_x_variant":[
        "\u041b\u043e\u0437\u043a\u0438"
    ],
    "wof:name":"Lozki",
    "wof:placetype":"locality"
},
  "geometry": {"coordinates":[32.99333,53.86221999999999],"type":"Point"}
}