{
  "type": "Feature",
  "properties": {
    "gn:admin1_code":"33",
    "gn:asciiname":"Simanovshchina",
    "gn:country_code":"RU",
    "gn:dem":134,
    "gn:feature_class":"P",
    "gn:feature_code":"PPL",
    "gn:name":"Simanovshchina",
    "gn:population":0,
    "gn:timezone":"Europe/Kirov",
    "iso:country":"RU",
    "name:rus_x_preferred":[
        "\u0421\u0438\u043c\u0430\u043d\u043e\u0432\u0449\u0438\u043d\u0430"
    ],
    "wof:name":"Simanovshchina",
    "wof:placetype":"locality"
},
  "geometry": {"coordinates":[50.6239,57.5697],"type":"Point"}
}