{
  "type": "Feature",
  "properties": {
    "gn:admin1_code":"73.0",
    "gn:asciiname":"Staroye Bikchentayevo",
    "gn:country_code":"RU",
    "gn:dem":138,
    "gn:feature_class":"P",
    "gn:feature_code":"PPL",
    "gn:name":"Staroye Bikchentayevo",
    "gn:population":0,
    "gn:timezone":"Europe/Moscow",
    "iso:country":"RU",
    "name:rus_x_preferred":[
        "\u0421\u0442\u0430\u0440\u043e\u0435 \u0411\u0438\u043a\u0447\u0435\u043d\u0442\u0430\u0435\u0432\u043e"
    ],
    "name:und_x_variant":[
        "Bikchentayevo",
        "Staroye Bichkentayevo",
        "Staroye Bikchentayevo",
        "\u0421\u0442\u0430\u0440\u043e\u0435 \u0411\u0438\u043a\u0447\u0435\u043d\u0442\u0430\u0435\u0432\u043e"
    ],
    "wof:name":"Staroye Bikchentayevo",
    "wof:placetype":"locality"
},
  "geometry": {"coordinates":[53.68832,55.63405],"type":"Point"}
}