{
  "type": "Feature",
  "properties": {
    "gn:admin1_code":"46.0",
    "gn:asciiname":"Komarovka",
    "gn:country_code":"RU",
    "gn:dem":114,
    "gn:feature_class":"P",
    "gn:feature_code":"PPL",
    "gn:name":"Komarovka",
    "gn:population":0,
    "gn:timezone":"Europe/Moscow",
    "iso:country":"RU",
    "name:che_x_preferred":[
        "\u041a\u043e\u043c\u0430\u0440\u043e\u0432\u043a\u0430"
    ],
    "name:rus_x_preferred":[
        "\u041a\u043e\u043c\u0430\u0440\u043e\u0432\u043a\u0430"
    ],
    "name:tgk_x_preferred":[
        "\u041a\u043e\u043c\u0430\u0440\u043e\u0432\u043a\u0430"
    ],
    "wof:name":"Komarovka",
    "wof:placetype":"locality"
},
  "geometry": {"coordinates":[43.77672000000001,54.61995],"type":"Point"}
}