{
  "type": "Feature",
  "properties": {
    "gn:admin1_code":"53",
    "gn:asciiname":"Dubinkinskiy",
    "gn:country_code":"RU",
    "gn:dem":157,
    "gn:feature_class":"P",
    "gn:feature_code":"PPL",
    "gn:name":"Dubinkinskiy",
    "gn:population":0,
    "gn:timezone":"Asia/Novosibirsk",
    "iso:country":"RU",
    "name:rus_x_preferred":[
        "\u0414\u0443\u0431\u0438\u043d\u043a\u0438\u043d\u0441\u043a\u0438\u0439"
    ],
    "name:und_x_variant":[
        "\u0414\u0443\u0431\u0438\u043d\u043a\u0438\u043d\u0441\u043a\u0438\u0439"
    ],
    "wof:name":"Dubinkinskiy",
    "wof:placetype":"locality"
},
  "geometry": {"coordinates":[81.38333,54.93333000000001],"type":"Point"}
}