{
  "type": "Feature",
  "properties": {
    "gn:admin1_code":"21.0",
    "gn:asciiname":"Bol'shiye Luben'ki",
    "gn:country_code":"RU",
    "gn:dem":116,
    "gn:feature_class":"P",
    "gn:feature_code":"PPL",
    "gn:name":"Bol\u2019shiye Luben\u2019ki",
    "gn:population":0,
    "gn:timezone":"Europe/Moscow",
    "iso:country":"RU",
    "name:und_x_variant":[
        "Luben\u2019ki-Bol\u2019shiye",
        "Bol\u2019shiye Luben\u2019ki"
    ],
    "wof:name":"Bol'shiye Luben'ki",
    "wof:placetype":"locality"
},
  "geometry": {"coordinates":[42.1432,56.93069000000001],"type":"Point"}
}