{
  "type": "Feature",
  "properties": {
    "gn:admin1_code":"45.0",
    "gn:asciiname":"Lopsola",
    "gn:country_code":"RU",
    "gn:dem":184,
    "gn:feature_class":"P",
    "gn:feature_code":"PPL",
    "gn:name":"Lopsola",
    "gn:population":0,
    "gn:timezone":"Europe/Moscow",
    "iso:country":"RU",
    "name:rus_x_preferred":[
        "\u041b\u043e\u043f\u0441\u043e\u043b\u0430"
    ],
    "name:und_x_variant":[
        "Lal-Sola",
        "Lopsola",
        "Lap-Sola"
    ],
    "wof:name":"Lopsola",
    "wof:placetype":"locality"
},
  "geometry": {"coordinates":[48.73861,56.795],"type":"Point"}
}