{
  "type": "Feature",
  "properties": {
    "gn:country":"RU",
    "gn:fcode":"PPL",
    "gn:pop":6,
    "iso:country":"RU",
    "name:rus_x_preferred":[
        "\u041c\u0430\u0440\u0442\u044c\u044f\u043d\u043e\u0432\u043e"
    ],
    "name:unk_x_variant":[
        "Mart\u2019yanovo"
    ],
    "qs:name":"Mart'yanovo",
    "qs:name_adm0":"Russia",
    "qs:name_adm1":"Moscow Oblast",
    "qs:photos_9r":0,
    "qs:photos_sr":0,
    "qs:placetype":"Town",
    "qs:pop_sr":"1",
    "wof:name":"Mart'yanovo",
    "wof:placetype":"locality",
    "wof:population":6
},
  "geometry": {"coordinates":[37.55855,54.959],"type":"Point"}
}