{
  "type": "Feature",
  "properties": {
    "gn:admin1_code":"47.0",
    "gn:asciiname":"Biserovo",
    "gn:country_code":"RU",
    "gn:dem":136,
    "gn:feature_class":"P",
    "gn:feature_code":"PPL",
    "gn:name":"Biserovo",
    "gn:population":0,
    "gn:timezone":"Europe/Moscow",
    "iso:country":"RU",
    "name:rus_x_preferred":[
        "\u0411\u0438\u0441\u0435\u0440\u043e\u0432\u043e"
    ],
    "name:und_x_variant":[
        "Biserova",
        "Bisirovo",
        "Biserovo",
        "\u0411\u0438\u0441\u0435\u0440\u043e\u0432\u043e"
    ],
    "wof:name":"Biserovo",
    "wof:placetype":"locality"
},
  "geometry": {"coordinates":[38.28443,55.39751999999999],"type":"Point"}
}