{
  "type": "Feature",
  "properties": {
    "gn:admin1_code":"71.0",
    "gn:asciiname":"Komaritsa",
    "gn:country_code":"RU",
    "gn:dem":81,
    "gn:feature_class":"P",
    "gn:feature_code":"PPL",
    "gn:name":"Komaritsa",
    "gn:population":0,
    "gn:timezone":"Asia/Yekaterinburg",
    "iso:country":"RU",
    "name:rus_x_preferred":[
        "\u041a\u043e\u043c\u0430\u0440\u0438\u0446\u0430"
    ],
    "wof:name":"Komaritsa",
    "wof:placetype":"locality"
},
  "geometry": {"coordinates":[63.75919,57.36778],"type":"Point"}
}