{
  "type": "Feature",
  "properties": {
    "gn:admin1_code":"28",
    "gn:asciiname":"Koykinitsy",
    "gn:country_code":"RU",
    "gn:dem":110,
    "gn:feature_class":"P",
    "gn:feature_code":"PPL",
    "gn:name":"Koykinitsy",
    "gn:population":0,
    "gn:timezone":"Europe/Moscow",
    "iso:country":"RU",
    "name:fin_x_preferred":[
        "Koikinitsa"
    ],
    "name:rus_x_preferred":[
        "\u041a\u043e\u0439\u043a\u0438\u043d\u0438\u0446\u044b"
    ],
    "name:und_x_variant":[
        "\u041a\u043e\u0439\u043a\u0438\u043d\u0438\u0446\u044b"
    ],
    "wof:name":"Koykinitsy",
    "wof:placetype":"locality"
},
  "geometry": {"coordinates":[34.90871,63.69149],"type":"Point"}
}