{
  "type": "Feature",
  "properties": {
    "gn:admin1_code":"80",
    "gn:asciiname":"Kychino",
    "gn:country_code":"RU",
    "gn:dem":184,
    "gn:feature_class":"P",
    "gn:feature_code":"PPL",
    "gn:name":"Kychino",
    "gn:population":0,
    "gn:timezone":"Europe/Samara",
    "iso:country":"RU",
    "name:rus_x_preferred":[
        "\u041a\u044b\u0447\u0438\u043d\u043e"
    ],
    "name:und_x_variant":[
        "Kuchino",
        "Kychinovskaya",
        "Kychino"
    ],
    "wof:name":"Kychino",
    "wof:placetype":"locality"
},
  "geometry": {"coordinates":[52.0203,58.2214],"type":"Point"}
}