{
  "type": "Feature",
  "properties": {
    "gn:admin1_code":"88.0",
    "gn:asciiname":"Lilitsyno",
    "gn:country_code":"RU",
    "gn:dem":100,
    "gn:feature_class":"P",
    "gn:feature_code":"PPL",
    "gn:name":"Lilitsyno",
    "gn:population":0,
    "gn:timezone":"Europe/Moscow",
    "iso:country":"RU",
    "name:rus_x_preferred":[
        "\u041b\u0438\u043b\u0438\u0446\u044b\u043d\u043e"
    ],
    "name:und_x_variant":[
        "Lelitsino",
        "Lilitsyno",
        "\u041b\u0438\u043b\u0438\u0446\u044b\u043d\u043e"
    ],
    "wof:name":"Lilitsyno",
    "wof:placetype":"locality"
},
  "geometry": {"coordinates":[40.68515,58.05223],"type":"Point"}
}