{
  "type": "Feature",
  "properties": {
    "gn:admin1_code":"53",
    "gn:asciiname":"Veselaya",
    "gn:country_code":"RU",
    "gn:dem":112,
    "gn:feature_class":"P",
    "gn:feature_code":"PPL",
    "gn:name":"Ves\u00eblaya",
    "gn:population":0,
    "gn:timezone":"Asia/Novosibirsk",
    "iso:country":"RU",
    "name:eng_x_preferred":[
        "Ves\u00eblaya"
    ],
    "name:nor_x_preferred":[
        "Veselaja"
    ],
    "name:rus_x_preferred":[
        "\u0412\u0435\u0441\u0435\u043b\u0430\u044f"
    ],
    "wof:name":"Veselaya",
    "wof:placetype":"locality"
},
  "geometry": {"coordinates":[78.22057,56.60785],"type":"Point"}
}