{
  "type": "Feature",
  "properties": {
    "gn:admin1_code":"67",
    "gn:asciiname":"Novozizevka",
    "gn:country_code":"RU",
    "gn:dem":44,
    "gn:feature_class":"P",
    "gn:feature_code":"PPL",
    "gn:name":"Novozizevka",
    "gn:population":0,
    "gn:timezone":"Europe/Saratov",
    "iso:country":"RU",
    "name:eng_x_preferred":[
        "Novozizevka"
    ],
    "name:nor_x_preferred":[
        "Novozizevka"
    ],
    "name:rus_x_preferred":[
        "\u041d\u043e\u0432\u043e\u0437\u0438\u0437\u0435\u0432\u043a\u0430"
    ],
    "name:und_x_variant":[
        "Novo-Sisevka",
        "Novozizevskiy",
        "\u041d\u043e\u0432\u043e\u0437\u0438\u0437\u0435\u0432\u043a\u0430",
        "Novozizevka"
    ],
    "wof:name":"Novozizevka",
    "wof:placetype":"locality"
},
  "geometry": {"coordinates":[49.1236,50.8047],"type":"Point"}
}