{
  "type": "Feature",
  "properties": {
    "gn:admin1_code":"61",
    "gn:asciiname":"Talovyy",
    "gn:country_code":"RU",
    "gn:dem":135,
    "gn:feature_class":"P",
    "gn:feature_code":"PPL",
    "gn:name":"Talovyy",
    "gn:population":0,
    "gn:timezone":"Europe/Moscow",
    "iso:country":"RU",
    "name:eng_x_preferred":[
        "Talovyy"
    ],
    "name:nor_x_preferred":[
        "Talovyj"
    ],
    "name:rus_x_preferred":[
        "\u0422\u0430\u043b\u043e\u0432\u044b\u0439"
    ],
    "name:und_x_variant":[
        "Mikoyan"
    ],
    "wof:name":"Talovyy",
    "wof:placetype":"locality"
},
  "geometry": {"coordinates":[42.6822,46.7143],"type":"Point"}
}