{
  "type": "Feature",
  "properties": {
    "gn:admin1_code":"16",
    "gn:asciiname":"Toysi Pervyye",
    "gn:country_code":"RU",
    "gn:dem":91,
    "gn:feature_class":"P",
    "gn:feature_code":"PPL",
    "gn:name":"Toysi Pervyye",
    "gn:population":0,
    "gn:timezone":"Europe/Moscow",
    "iso:country":"RU",
    "name:rus_x_preferred":[
        "\u0422\u043e\u0439\u0441\u0438 \u041f\u0435\u0440\u0432\u044b\u0435"
    ],
    "name:und_x_variant":[
        "Pervyye Toysi",
        "Toysi Pervyye"
    ],
    "wof:name":"Toysi Pervyye",
    "wof:placetype":"locality"
},
  "geometry": {"coordinates":[47.7218,55.82298],"type":"Point"}
}