{
  "type": "Feature",
  "properties": {
    "gn:admin1_code":"51",
    "gn:asciiname":"Lyubimovo",
    "gn:country_code":"RU",
    "gn:dem":195,
    "gn:feature_class":"P",
    "gn:feature_code":"PPL",
    "gn:name":"Lyubimovo",
    "gn:population":0,
    "gn:timezone":"Europe/Moscow",
    "iso:country":"RU",
    "name:rus_x_preferred":[
        "\u041b\u044e\u0431\u0438\u043c\u043e\u0432\u043e"
    ],
    "wof:name":"Lyubimovo",
    "wof:placetype":"locality"
},
  "geometry": {"coordinates":[45.0353,54.533],"type":"Point"}
}