{
  "type": "Feature",
  "properties": {
    "gn:admin1_code":"7",
    "gn:asciiname":"Tri Bugra",
    "gn:country_code":"RU",
    "gn:dem":-3,
    "gn:feature_class":"P",
    "gn:feature_code":"PPL",
    "gn:name":"Tri Bugra",
    "gn:population":0,
    "gn:timezone":"Europe/Astrakhan",
    "iso:country":"RU",
    "wof:name":"Tri Bugra",
    "wof:placetype":"locality"
},
  "geometry": {"coordinates":[46.65,47.33333],"type":"Point"}
}