{
  "type": "Feature",
  "properties": {
    "gn:admin1_code":"41.0",
    "gn:asciiname":"Belachinskaya",
    "gn:country_code":"RU",
    "gn:dem":209,
    "gn:feature_class":"P",
    "gn:feature_code":"PPL",
    "gn:name":"Belachinskaya",
    "gn:population":0,
    "gn:timezone":"Europe/Moscow",
    "iso:country":"RU",
    "name:nor_x_preferred":[
        "Belatsjinskaja"
    ],
    "name:rus_x_preferred":[
        "\u0411\u0435\u043b\u0430\u0447\u0438\u043d\u0441\u043a\u0430\u044f"
    ],
    "wof:name":"Belachinskaya",
    "wof:placetype":"locality"
},
  "geometry": {"coordinates":[36.53333,51.46667],"type":"Point"}
}