{
  "type": "Feature",
  "properties": {
    "gn:admin1_code":"43",
    "gn:asciiname":"Pirogovka",
    "gn:country_code":"RU",
    "gn:dem":208,
    "gn:feature_class":"P",
    "gn:feature_code":"PPL",
    "gn:name":"Pirogovka",
    "gn:population":0,
    "gn:timezone":"Europe/Moscow",
    "iso:country":"RU",
    "name:che_x_preferred":[
        "\u041f\u0438\u0440\u043e\u0433\u043e\u0432\u043a\u0430"
    ],
    "name:rus_x_preferred":[
        "\u041f\u0438\u0440\u043e\u0433\u043e\u0432\u043a\u0430"
    ],
    "name:tgk_x_preferred":[
        "\u041f\u0438\u0440\u043e\u0433\u043e\u0432\u043a\u0430"
    ],
    "wof:name":"Pirogovka",
    "wof:placetype":"locality"
},
  "geometry": {"coordinates":[38.84889,53.48806],"type":"Point"}
}