{
  "type": "Feature",
  "properties": {
    "gn:admin1_code":"47",
    "gn:asciiname":"Pochinki",
    "gn:country_code":"RU",
    "gn:dem":144,
    "gn:feature_class":"P",
    "gn:feature_code":"PPL",
    "gn:name":"Pochinki",
    "gn:population":0,
    "gn:timezone":"Europe/Moscow",
    "iso:country":"RU",
    "name:ara_x_preferred":[
        "\u0628\u0648\u0634\u0646\u0643\u064a"
    ],
    "name:rus_x_preferred":[
        "\u041f\u043e\u0447\u0438\u043d\u043a\u0438"
    ],
    "wof:name":"Pochinki",
    "wof:placetype":"locality"
},
  "geometry": {"coordinates":[39.72262,55.48495],"type":"Point"}
}