{
  "type": "Feature",
  "properties": {
    "gn:admin1_code":"46",
    "gn:asciiname":"Polyanki",
    "gn:country_code":"RU",
    "gn:dem":155,
    "gn:feature_class":"P",
    "gn:feature_code":"PPL",
    "gn:name":"Polyanki",
    "gn:population":0,
    "gn:timezone":"Europe/Moscow",
    "iso:country":"RU",
    "name:rus_x_preferred":[
        "\u041f\u043e\u043b\u044f\u043d\u043a\u0438"
    ],
    "name:und_x_variant":[
        "\u041f\u043e\u043b\u044f\u043d\u043a\u0438"
    ],
    "wof:name":"Polyanki",
    "wof:placetype":"locality"
},
  "geometry": {"coordinates":[45.0738,54.076],"type":"Point"}
}