{
  "type": "Feature",
  "properties": {
    "gn:admin1_code":"76",
    "gn:asciiname":"Khochevo",
    "gn:country_code":"RU",
    "gn:dem":195,
    "gn:feature_class":"P",
    "gn:feature_code":"PPL",
    "gn:name":"Khochevo",
    "gn:population":0,
    "gn:timezone":"Europe/Moscow",
    "iso:country":"RU",
    "name:rus_x_preferred":[
        "\u0425\u043e\u0447\u0435\u0432\u043e"
    ],
    "name:und_x_variant":[
        "\u0425\u043e\u0447\u0435\u0432\u043e"
    ],
    "wof:name":"Khochevo",
    "wof:placetype":"locality"
},
  "geometry": {"coordinates":[36.09915,53.86473],"type":"Point"}
}