{
  "type": "Feature",
  "properties": {
    "gn:country":"RU",
    "gn:fcode":"PPL",
    "gn:pop":5521,
    "iso:country":"RU",
    "name:ara_x_preferred":[
        "\u063a\u062f\u0648\u0641"
    ],
    "name:azb_x_preferred":[
        "\u0642\u062f\u0648\u0641"
    ],
    "name:aze_x_preferred":[
        "Qdov"
    ],
    "name:bel_x_preferred":[
        "\u0413\u043e\u0440\u0430\u0434 \u0413\u0434\u043e\u045e"
    ],
    "name:bel_x_variant":[
        "\u0413\u0434\u043e\u045e"
    ],
    "name:bis_x_preferred":[
        "Gdov"
    ],
    "name:bul_x_preferred":[
        "\u0413\u0434\u043e\u0432"
    ],
    "name:ceb_x_preferred":[
        "Gdov"
    ],
    "name:ces_x_preferred":[
        "Gdov"
    ],
    "name:che_x_preferred":[
        "\u0413\u0434\u043e\u0432"
    ],
    "name:cym_x_preferred":[
        "Gdov"
    ],
    "name:dan_x_preferred":[
        "Gdov"
    ],
    "name:deu_x_preferred":[
        "Gdow"
    ],
    "name:diq_x_preferred":[
        "Gdov"
    ],
    "name:eng_x_preferred":[
        "Gdov"
    ],
    "name:epo_x_preferred":[
        "Gdov"
    ],
    "name:est_x_preferred":[
        "Oudova"
    ],
    "name:fas_x_preferred":[
        "\u06af\u062f\u0648\u0641"
    ],
    "name:fin_x_preferred":[
        "Outova"
    ],
    "name:fra_x_preferred":[
        "Gdov"
    ],
    "name:hrv_x_preferred":[
        "Gdov"
    ],
    "name:hsb_x_preferred":[
        "Gdow"
    ],
    "name:hye_x_preferred":[
        "\u0533\u0564\u0578\u057e"
    ],
    "name:ita_x_preferred":[
        "Gdov"
    ],
    "name:jpn_x_preferred":[
        "\u30b0\u30c9\u30d5"
    ],
    "name:kat_x_preferred":[
        "\u10d2\u10d3\u10dd\u10d5\u10d8"
    ],
    "name:kor_x_preferred":[
        "\uadf8\ub3c4\ud504"
    ],
    "name:lat_x_preferred":[
        "Gdovia"
    ],
    "name:lav_x_preferred":[
        "Gdova"
    ],
    "name:lit_x_preferred":[
        "Gdovas"
    ],
    "name:mhr_x_preferred":[
        "\u0413\u0434\u043e\u0432"
    ],
    "name:nld_x_preferred":[
        "Gdov"
    ],
    "name:nno_x_preferred":[
        "Gdov"
    ],
    "name:nob_x_preferred":[
        "Gdov"
    ],
    "name:nor_x_preferred":[
        "Gdov"
    ],
    "name:pol_x_preferred":[
        "Gdow"
    ],
    "name:por_x_preferred":[
        "Gdov"
    ],
    "name:rus_x_preferred":[
        "\u0413\u0434\u043e\u0432"
    ],
    "name:spa_x_preferred":[
        "Gdov"
    ],
    "name:srp_x_preferred":[
        "\u0413\u0434\u043e\u0432"
    ],
    "name:swe_x_preferred":[
        "Gdov"
    ],
    "name:tat_x_preferred":[
        "\u0413\u0434\u043e\u0432"
    ],
    "name:tgk_x_preferred":[
        "\u0413\u0434\u043e\u0432"
    ],
    "name:tgl_x_preferred":[
        "Gdov"
    ],
    "name:tur_x_preferred":[
        "Gdov"
    ],
    "name:ukr_x_preferred":[
        "\u0413\u0434\u043e\u0432"
    ],
    "name:unk_x_variant":[
        "Gdow"
    ],
    "name:vep_x_preferred":[
        "Gdov"
    ],
    "name:war_x_preferred":[
        "Gdov"
    ],
    "name:wol_x_preferred":[
        "Gdov"
    ],
    "name:zho_x_preferred":[
        "\u683c\u591a\u592b"
    ],
    "qs:name":"Gdov",
    "qs:name_adm0":"Russia",
    "qs:name_adm1":"Pskov Oblast",
    "qs:photos_9k":1,
    "qs:photos_9r":2,
    "qs:photos_all":37,
    "qs:photos_sr":0,
    "qs:placetype":"Town",
    "qs:pop_sr":"5",
    "wd:wordcount":1636,
    "wof:name":"Gdov",
    "wof:placetype":"locality",
    "wof:population":5521
},
  "geometry": {"coordinates":[27.81977,58.74424],"type":"Point"}
}