{
  "type": "Feature",
  "properties": {
    "gn:admin1_code":"85.0",
    "gn:asciiname":"Cherneyevo",
    "gn:country_code":"RU",
    "gn:dem":192,
    "gn:feature_class":"P",
    "gn:feature_code":"PPL",
    "gn:name":"Cherneyevo",
    "gn:population":0,
    "gn:timezone":"Europe/Moscow",
    "iso:country":"RU",
    "name:eng_x_preferred":[
        "Cherneyevo"
    ],
    "name:nor_x_preferred":[
        "Tsjernejevo"
    ],
    "name:rus_x_preferred":[
        "\u0427\u0435\u0440\u043d\u0435\u0435\u0432\u043e"
    ],
    "name:und_x_variant":[
        "\u0427\u0435\u0440\u043d\u0435\u0435\u0432\u043e",
        "Cherneyevo"
    ],
    "wof:name":"Cherneyevo",
    "wof:placetype":"locality"
},
  "geometry": {"coordinates":[38.92656,59.13271],"type":"Point"}
}