{
  "type": "Feature",
  "properties": {
    "gn:admin1_code":"45.0",
    "gn:asciiname":"Yerofeykovo",
    "gn:country_code":"RU",
    "gn:dem":144,
    "gn:feature_class":"P",
    "gn:feature_code":"PPL",
    "gn:name":"Yerofeykovo",
    "gn:population":0,
    "gn:timezone":"Europe/Moscow",
    "iso:country":"RU",
    "name:rus_x_preferred":[
        "\u0415\u0440\u043e\u0444\u0435\u0439\u043a\u043e\u0432\u043e"
    ],
    "wof:name":"Yerofeykovo",
    "wof:placetype":"locality"
},
  "geometry": {"coordinates":[48.76722,57.08278000000001],"type":"Point"}
}