{
  "type": "Feature",
  "properties": {
    "gn:admin1_code":"38",
    "gn:asciiname":"Vol'nyy Trud",
    "gn:country_code":"RU",
    "gn:dem":384,
    "gn:feature_class":"P",
    "gn:feature_code":"PPL",
    "gn:name":"Vol\u2019nyy Trud",
    "gn:population":0,
    "gn:timezone":"Europe/Moscow",
    "iso:country":"RU",
    "name:rus_x_preferred":[
        "\u0412\u043e\u043b\u044c\u043d\u044b\u0439 \u0422\u0440\u0443\u0434"
    ],
    "name:und_x_variant":[
        "Vol\u2019nyy Trud"
    ],
    "wof:name":"Vol'nyy Trud",
    "wof:placetype":"locality"
},
  "geometry": {"coordinates":[41.3469,44.5962],"type":"Point"}
}