{
  "type": "Feature",
  "properties": {
    "gn:admin1_code":"20",
    "gn:asciiname":"Kharety",
    "gn:country_code":"RU",
    "gn:dem":419,
    "gn:feature_class":"P",
    "gn:feature_code":"PPL",
    "gn:name":"Khar\u00ebty",
    "gn:population":0,
    "gn:timezone":"Asia/Irkutsk",
    "iso:country":"RU",
    "name:rus_x_preferred":[
        "\u0425\u0430\u0440\u0451\u0442\u044b"
    ],
    "name:und_x_variant":[
        "Volginskiy",
        "Khar\u00ebty"
    ],
    "wof:name":"Kharety",
    "wof:placetype":"locality"
},
  "geometry": {"coordinates":[102.73099999999999,53.8222],"type":"Point"}
}