{
  "type": "Feature",
  "properties": {
    "gn:admin1_code":"85",
    "gn:asciiname":"Nazarovo",
    "gn:country_code":"RU",
    "gn:dem":152,
    "gn:feature_class":"P",
    "gn:feature_code":"PPL",
    "gn:name":"Nazarovo",
    "gn:population":0,
    "gn:timezone":"Europe/Moscow",
    "iso:country":"RU",
    "name:rus_x_preferred":[
        "\u041d\u0430\u0437\u0430\u0440\u043e\u0432\u043e"
    ],
    "name:swe_x_preferred":[
        "Nazarovo"
    ],
    "name:tgl_x_preferred":[
        "Nazarovo"
    ],
    "name:und_x_variant":[
        "\u041d\u0430\u0437\u0430\u0440\u043e\u0432\u043e"
    ],
    "wof:name":"Nazarovo",
    "wof:placetype":"locality"
},
  "geometry": {"coordinates":[38.73761,59.12728000000001],"type":"Point"}
}