{
  "type": "Feature",
  "properties": {
    "gn:admin1_code":"40",
    "gn:asciiname":"Demino",
    "gn:cc2":"RU",
    "gn:country_code":"RU",
    "gn:dem":90,
    "gn:feature_class":"P",
    "gn:feature_code":"PPL",
    "gn:name":"D\u00ebmino",
    "gn:population":0,
    "gn:timezone":"Asia/Yekaterinburg",
    "iso:country":"RU",
    "name:eng_x_preferred":[
        "D\u00ebmino"
    ],
    "name:nor_x_preferred":[
        "Demina"
    ],
    "name:rus_x_preferred":[
        "\u0414\u0435\u043c\u0438\u043d\u0430"
    ],
    "name:rus_x_variant":[
        "\u0414\u0451\u043c\u0438\u043d\u043e"
    ],
    "name:und_x_variant":[
        "Deminskoye",
        "D\u00ebmina",
        "D\u00ebmino",
        "\u0414\u0451\u043c\u0438\u043d\u043e"
    ],
    "wof:name":"Demino",
    "wof:placetype":"locality"
},
  "geometry": {"coordinates":[63.56583000000001,55.97417],"type":"Point"}
}