{
  "type": "Feature",
  "properties": {
    "gn:admin1_code":"54",
    "gn:asciiname":"Georgiyevka",
    "gn:country_code":"RU",
    "gn:dem":114,
    "gn:feature_class":"P",
    "gn:feature_code":"PPL",
    "gn:name":"Georgiyevka",
    "gn:population":0,
    "gn:timezone":"Asia/Omsk",
    "iso:country":"RU",
    "name:eng_x_preferred":[
        "Georgiyevka"
    ],
    "name:nor_x_preferred":[
        "Georgijevka"
    ],
    "name:rus_x_preferred":[
        "\u0413\u0435\u043e\u0440\u0433\u0438\u0435\u0432\u043a\u0430"
    ],
    "wof:name":"Georgiyevka",
    "wof:placetype":"locality"
},
  "geometry": {"coordinates":[72.52025999999999,55.96361],"type":"Point"}
}