{
  "type": "Feature",
  "properties": {
    "gn:admin1_code":"8",
    "gn:asciiname":"Lavochnoye",
    "gn:country_code":"RU",
    "gn:dem":87,
    "gn:feature_class":"P",
    "gn:feature_code":"PPL",
    "gn:name":"Lavochnoye",
    "gn:population":0,
    "gn:timezone":"Asia/Yekaterinburg",
    "iso:country":"RU",
    "name:rus_x_preferred":[
        "\u041b\u0430\u0432\u043e\u0447\u043d\u043e\u0435"
    ],
    "name:und_x_variant":[
        "\u041b\u0430\u0432\u043e\u0447\u043d\u043e\u0435"
    ],
    "wof:name":"Lavochnoye",
    "wof:placetype":"locality"
},
  "geometry": {"coordinates":[56.00671,54.88119],"type":"Point"}
}