{
  "type": "Feature",
  "properties": {
    "gn:admin1_code":"62",
    "gn:asciiname":"Taptykovo",
    "gn:country_code":"RU",
    "gn:dem":143,
    "gn:feature_class":"P",
    "gn:feature_code":"PPL",
    "gn:name":"Taptykovo",
    "gn:population":0,
    "gn:timezone":"Europe/Moscow",
    "iso:country":"RU",
    "name:eng_x_preferred":[
        "Taptykovo"
    ],
    "name:nor_x_preferred":[
        "Taptykovo"
    ],
    "name:rus_x_preferred":[
        "\u0422\u0430\u043f\u0442\u044b\u043a\u043e\u0432\u043e"
    ],
    "name:und_x_variant":[
        "Toptykovo",
        "Topchikovo",
        "Taptykovo"
    ],
    "wof:name":"Taptykovo",
    "wof:placetype":"locality"
},
  "geometry": {"coordinates":[41.26499,53.74551],"type":"Point"}
}