{
  "type": "Feature",
  "properties": {
    "gn:admin1_code":"77",
    "gn:asciiname":"Koshelevka",
    "gn:country_code":"RU",
    "gn:dem":221,
    "gn:feature_class":"P",
    "gn:feature_code":"PPL",
    "gn:name":"Koshelevka",
    "gn:population":0,
    "gn:timezone":"Europe/Moscow",
    "iso:country":"RU",
    "name:che_x_preferred":[
        "\u041a\u043e\u0448\u0435\u043b\u0435\u0432\u043a\u0430"
    ],
    "name:rus_x_preferred":[
        "\u041a\u043e\u0448\u0435\u043b\u0435\u0432\u043a\u0430"
    ],
    "name:tgk_x_preferred":[
        "\u041a\u043e\u0448\u0435\u043b\u0435\u0432\u043a\u0430"
    ],
    "wof:name":"Koshelevka",
    "wof:placetype":"locality"
},
  "geometry": {"coordinates":[32.24139,56.59],"type":"Point"}
}