{
  "type": "Feature",
  "properties": {
    "gn:admin1_code":"86",
    "gn:asciiname":"Voloshino",
    "gn:country_code":"RU",
    "gn:dem":109,
    "gn:feature_class":"P",
    "gn:feature_code":"PPL",
    "gn:name":"Voloshino",
    "gn:population":0,
    "gn:timezone":"Europe/Moscow",
    "iso:country":"RU",
    "name:rus_x_preferred":[
        "\u0412\u043e\u043b\u043e\u0448\u0438\u043d\u043e"
    ],
    "name:und_x_variant":[
        "Boloshnik",
        "Voloshino"
    ],
    "wof:name":"Voloshino",
    "wof:placetype":"locality"
},
  "geometry": {"coordinates":[38.9396,50.8729],"type":"Point"}
}