{
  "type": "Feature",
  "properties": {
    "gn:admin1_code":"33.0",
    "gn:asciiname":"Nizhniye Zhuravli",
    "gn:country_code":"RU",
    "gn:dem":120,
    "gn:feature_class":"P",
    "gn:feature_code":"PPL",
    "gn:name":"Nizhniye Zhuravli",
    "gn:population":0,
    "gn:timezone":"Europe/Kirov",
    "iso:country":"RU",
    "name:rus_x_preferred":[
        "\u041d\u0438\u0436\u043d\u0438\u0435 \u0416\u0443\u0440\u0430\u0432\u043b\u0438"
    ],
    "name:und_x_variant":[
        "\u041d\u0438\u0436\u043d\u0438\u0435 \u0416\u0443\u0440\u0430\u0432\u043b\u0438"
    ],
    "wof:name":"Nizhniye Zhuravli",
    "wof:placetype":"locality"
},
  "geometry": {"coordinates":[48.93809,58.67196],"type":"Point"}
}