{
  "type": "Feature",
  "properties": {
    "gn:admin1_code":"13",
    "gn:asciiname":"Zauralovo",
    "gn:country_code":"RU",
    "gn:dem":323,
    "gn:feature_class":"P",
    "gn:feature_code":"PPL",
    "gn:name":"Zauralovo",
    "gn:population":0,
    "gn:timezone":"Asia/Yekaterinburg",
    "iso:country":"RU",
    "name:eng_x_preferred":[
        "Zauralovo"
    ],
    "name:nor_x_preferred":[
        "Zauralovo"
    ],
    "name:rus_x_preferred":[
        "\u0417\u0430\u0443\u0440\u0430\u043b\u043e\u0432\u043e"
    ],
    "name:und_x_variant":[
        "Mel\u2019nikovo-Zauralova",
        "Mel\u2019nikovo",
        "Mel\u2019nikovo-Zauralovo",
        "Zauralovo"
    ],
    "wof:name":"Zauralovo",
    "wof:placetype":"locality"
},
  "geometry": {"coordinates":[60.2043,54.6566],"type":"Point"}
}