{
  "type": "Feature",
  "properties": {
    "gn:admin1_code":"46",
    "gn:asciiname":"Novoye Bayevo",
    "gn:country_code":"RU",
    "gn:dem":150,
    "gn:feature_class":"P",
    "gn:feature_code":"PPL",
    "gn:name":"Novoye Bayevo",
    "gn:population":0,
    "gn:timezone":"Europe/Moscow",
    "iso:country":"RU",
    "name:eng_x_preferred":[
        "Novoye Bayevo"
    ],
    "name:nor_x_preferred":[
        "Nov.Bajevo"
    ],
    "name:rus_x_preferred":[
        "\u041d\u043e\u0432.\u0411\u0430\u0435\u0432\u043e"
    ],
    "name:rus_x_variant":[
        "\u041d\u043e\u0432\u043e\u0435 \u0411\u0430\u0435\u0432\u043e"
    ],
    "name:und_x_variant":[
        "Novobayevo"
    ],
    "wof:name":"Novoye Bayevo",
    "wof:placetype":"locality"
},
  "geometry": {"coordinates":[45.7311,54.89279000000001],"type":"Point"}
}