{
  "type": "Feature",
  "properties": {
    "gn:admin1_code":"47",
    "gn:asciiname":"Senino",
    "gn:country_code":"RU",
    "gn:dem":176,
    "gn:feature_class":"P",
    "gn:feature_code":"PPL",
    "gn:name":"Senino",
    "gn:population":0,
    "gn:timezone":"Europe/Moscow",
    "iso:country":"RU",
    "name:rus_x_preferred":[
        "\u0421\u0435\u043d\u0438\u043d\u043e"
    ],
    "name:und_x_variant":[
        "\u0421\u0435\u043d\u0438\u043d\u043e"
    ],
    "wof:name":"Senino",
    "wof:placetype":"locality"
},
  "geometry": {"coordinates":[37.39346,55.08751],"type":"Point"}
}