{
  "type": "Feature",
  "properties": {
    "gn:admin1_code":"77",
    "gn:asciiname":"Poplyakhny",
    "gn:country_code":"RU",
    "gn:dem":95,
    "gn:feature_class":"P",
    "gn:feature_code":"PPL",
    "gn:name":"Poplyakhny",
    "gn:population":0,
    "gn:timezone":"Europe/Moscow",
    "iso:country":"RU",
    "name:rus_x_preferred":[
        "\u041f\u043e\u043f\u043b\u044f\u0445\u043d\u044b"
    ],
    "wof:name":"Poplyakhny",
    "wof:placetype":"locality"
},
  "geometry": {"coordinates":[30.8901,56.8121],"type":"Point"}
}