{
  "type": "Feature",
  "properties": {
    "gn:admin1_code":"52.0",
    "gn:asciiname":"Fryunino",
    "gn:country_code":"RU",
    "gn:dem":98,
    "gn:feature_class":"P",
    "gn:feature_code":"PPL",
    "gn:name":"Fryunino",
    "gn:population":0,
    "gn:timezone":"Europe/Moscow",
    "iso:country":"RU",
    "name:rus_x_preferred":[
        "\u0424\u0440\u044e\u043d\u0438\u043d\u043e"
    ],
    "name:und_x_variant":[
        "Fryuni",
        "Fryunina",
        "Fryunino",
        "\u0424\u0440\u044e\u043d\u0438\u043d\u043e"
    ],
    "wof:name":"Fryunino",
    "wof:placetype":"locality"
},
  "geometry": {"coordinates":[30.75407,57.07853000000001],"type":"Point"}
}