{
  "type": "Feature",
  "properties": {
    "gn:admin1_code":"46",
    "gn:asciiname":"Pichineyka",
    "gn:country_code":"RU",
    "gn:dem":117,
    "gn:feature_class":"P",
    "gn:feature_code":"PPL",
    "gn:name":"Pichineyka",
    "gn:population":0,
    "gn:timezone":"Europe/Moscow",
    "iso:country":"RU",
    "name:rus_x_preferred":[
        "\u041f\u0438\u0447\u0438\u043d\u0435\u0439\u043a\u0430"
    ],
    "name:und_x_variant":[
        "\u041f\u0438\u0447\u0438\u043d\u0435\u0439\u043a\u0430"
    ],
    "wof:name":"Pichineyka",
    "wof:placetype":"locality"
},
  "geometry": {"coordinates":[45.8826,54.6192],"type":"Point"}
}