{
  "type": "Feature",
  "properties": {
    "gn:country":"RU",
    "gn:fcode":"PPL",
    "gn:pop":0,
    "iso:country":"RU",
    "name:rus_x_preferred":[
        "\u041b\u0435\u0441\u043d\u043e\u0435"
    ],
    "name:unk_x_variant":[
        "Pudovka"
    ],
    "qs:name":"Lesnoye",
    "qs:name_adm0":"Russia",
    "qs:name_adm1":"Moscow Oblast",
    "qs:photos_9r":0,
    "qs:photos_sr":0,
    "qs:placetype":"Town",
    "qs:pop_sr":"0",
    "wd:wordcount":99,
    "wof:name":"Lesnoye",
    "wof:placetype":"locality",
    "wof:population":0
},
  "geometry": {"coordinates":[39.46338,55.07579],"type":"Point"}
}