{
  "type": "Feature",
  "properties": {
    "gn:admin1_code":"77",
    "gn:asciiname":"Yurenevo",
    "gn:country_code":"RU",
    "gn:dem":128,
    "gn:feature_class":"P",
    "gn:feature_code":"PPL",
    "gn:name":"Yurenevo",
    "gn:population":0,
    "gn:timezone":"Europe/Moscow",
    "iso:country":"RU",
    "name:rus_x_preferred":[
        "\u042e\u0440\u0435\u043d\u0435\u0432\u043e"
    ],
    "wof:name":"Yurenevo",
    "wof:placetype":"locality"
},
  "geometry": {"coordinates":[36.9316,56.6852],"type":"Point"}
}