{
  "type": "Feature",
  "properties": {
    "gn:admin1_code":"47",
    "gn:asciiname":"Sokhino",
    "gn:country_code":"RU",
    "gn:dem":141,
    "gn:feature_class":"P",
    "gn:feature_code":"PPL",
    "gn:name":"Sokhino",
    "gn:population":0,
    "gn:timezone":"Europe/Moscow",
    "iso:country":"RU",
    "name:rus_x_preferred":[
        "\u0421\u043e\u0445\u0438\u043d\u043e"
    ],
    "name:und_x_variant":[
        "\u0421\u043e\u0445\u0438\u043d\u043e"
    ],
    "wof:name":"Sokhino",
    "wof:placetype":"locality"
},
  "geometry": {"coordinates":[39.1938,54.6543],"type":"Point"}
}