{
  "type": "Feature",
  "properties": {
    "gn:admin1_code":"77",
    "gn:asciiname":"Starovo",
    "gn:country_code":"RU",
    "gn:dem":169,
    "gn:feature_class":"P",
    "gn:feature_code":"PPL",
    "gn:name":"Starovo",
    "gn:population":0,
    "gn:timezone":"Europe/Moscow",
    "iso:country":"RU",
    "name:bul_x_preferred":[
        "\u0421\u0442\u0430\u0440\u043e\u0432\u043e"
    ],
    "name:ceb_x_preferred":[
        "Starovo"
    ],
    "name:fas_x_preferred":[
        "\u0627\u0633\u062a\u0627\u0631\u0648\u0641\u0648"
    ],
    "name:kaz_x_preferred":[
        "\u0421\u0442\u0430\u0440\u043e\u0432\u043e"
    ],
    "name:ron_x_preferred":[
        "Starovo"
    ],
    "name:rus_x_preferred":[
        "\u0421\u0442\u0430\u0440\u043e\u0432\u043e"
    ],
    "name:swe_x_preferred":[
        "Starovo"
    ],
    "name:ukr_x_preferred":[
        "\u0421\u0442\u0430\u0440\u043e\u0432\u043e"
    ],
    "wof:name":"Starovo",
    "wof:placetype":"locality"
},
  "geometry": {"coordinates":[36.3754,57.3784],"type":"Point"}
}