{
  "type": "Feature",
  "properties": {
    "gn:admin1_code":"32",
    "gn:asciiname":"Verkhniye Rezany",
    "gn:cc2":"RU",
    "gn:country_code":"RU",
    "gn:dem":3,
    "gn:feature_class":"P",
    "gn:feature_code":"PPL",
    "gn:name":"Verkhniye Rezany",
    "gn:population":0,
    "gn:timezone":"Asia/Yekaterinburg",
    "iso:country":"RU",
    "name:und_x_variant":[
        "Rezanskiye",
        "Ryazanskiye",
        "Verkhniye Rezany"
    ],
    "wof:name":"Verkhniye Rezany",
    "wof:placetype":"locality"
},
  "geometry": {"coordinates":[65.75,63.66667],"type":"Point"}
}