{
  "type": "Feature",
  "properties": {
    "gn:admin1_code":"28.0",
    "gn:asciiname":"Emelinvara",
    "gn:cc2":"RU",
    "gn:country_code":"RU",
    "gn:dem":195,
    "gn:feature_class":"P",
    "gn:feature_code":"PPL",
    "gn:name":"Emelinvara",
    "gn:population":0,
    "gn:timezone":"Europe/Moscow",
    "iso:country":"RU",
    "name:fin_x_preferred":[
        "Emelinvaara"
    ],
    "name:rus_x_preferred":[
        "\u042d\u043c\u0435\u043b\u0438\u043d\u0432\u0430\u0440\u0430"
    ],
    "name:und_x_variant":[
        "Yemelinavara",
        "Emilinvara",
        "Emelinvara",
        "\u042d\u043c\u0435\u043b\u0438\u043d\u0432\u0430\u0440\u0430"
    ],
    "wof:name":"Emelinvara",
    "wof:placetype":"locality"
},
  "geometry": {"coordinates":[31.71066,62.64213],"type":"Point"}
}