{
  "type": "Feature",
  "properties": {
    "gn:admin1_code":"52",
    "gn:asciiname":"Sakovo",
    "gn:country_code":"RU",
    "gn:dem":122,
    "gn:feature_class":"P",
    "gn:feature_code":"PPL",
    "gn:name":"Sakovo",
    "gn:population":0,
    "gn:timezone":"Europe/Moscow",
    "iso:country":"RU",
    "name:und_x_variant":[
        "Sokovo",
        "Sakovo"
    ],
    "wof:name":"Sakovo",
    "wof:placetype":"locality"
},
  "geometry": {"coordinates":[33.77389,58.54917],"type":"Point"}
}