{
  "type": "Feature",
  "properties": {
    "gn:admin1_code":"17",
    "gn:asciiname":"Nikabarkmakhi",
    "gn:country_code":"RU",
    "gn:dem":1963,
    "gn:feature_class":"P",
    "gn:feature_code":"PPL",
    "gn:name":"Nikabarkmakhi",
    "gn:population":0,
    "gn:timezone":"Europe/Moscow",
    "iso:country":"RU",
    "name:rus_x_preferred":[
        "\u041d\u0438\u043a\u0430\u0431\u0430\u0440\u043a\u043c\u0430\u0445\u0438"
    ],
    "wof:name":"Nikabarkmakhi",
    "wof:placetype":"locality"
},
  "geometry": {"coordinates":[47.44097,42.01293],"type":"Point"}
}