{
  "type": "Feature",
  "properties": {
    "gn:admin1_code":"83",
    "gn:asciiname":"Khotenskoye",
    "gn:country_code":"RU",
    "gn:dem":149,
    "gn:feature_class":"P",
    "gn:feature_code":"PPL",
    "gn:name":"Khotenskoye",
    "gn:population":0,
    "gn:timezone":"Europe/Moscow",
    "iso:country":"RU",
    "name:rus_x_preferred":[
        "\u0425\u043e\u0442\u0435\u043d\u0441\u043a\u043e\u0435"
    ],
    "wof:name":"Khotenskoye",
    "wof:placetype":"locality"
},
  "geometry": {"coordinates":[40.31076,56.22984],"type":"Point"}
}