{
  "type": "Feature",
  "properties": {
    "gn:admin1_code":"52",
    "gn:asciiname":"Tabol'",
    "gn:country_code":"RU",
    "gn:dem":22,
    "gn:feature_class":"P",
    "gn:feature_code":"PPL",
    "gn:name":"Tabol\u2019",
    "gn:population":0,
    "gn:timezone":"Europe/Moscow",
    "iso:country":"RU",
    "name:und_x_variant":[
        "Novoye Khramzino",
        "Tabol\u2019"
    ],
    "wof:name":"Tabol'",
    "wof:placetype":"locality"
},
  "geometry": {"coordinates":[31.12095,58.40917],"type":"Point"}
}