{
  "type": "Feature",
  "properties": {
    "gn:admin1_code":"41.0",
    "gn:asciiname":"Grafirovka",
    "gn:country_code":"RU",
    "gn:dem":205,
    "gn:feature_class":"P",
    "gn:feature_code":"PPL",
    "gn:name":"Grafirovka",
    "gn:population":0,
    "gn:timezone":"Europe/Moscow",
    "iso:country":"RU",
    "name:rus_x_preferred":[
        "\u0413\u043b\u0430\u0444\u0438\u0440\u043e\u0432\u043a\u0430"
    ],
    "name:und_x_variant":[
        "Glafirovka",
        "Grafirovka"
    ],
    "wof:name":"Grafirovka",
    "wof:placetype":"locality"
},
  "geometry": {"coordinates":[36.80991,51.17893],"type":"Point"}
}