{
  "type": "Feature",
  "properties": {
    "gn:admin1_code":"77",
    "gn:asciiname":"Ilovitsy",
    "gn:country_code":"RU",
    "gn:dem":274,
    "gn:feature_class":"P",
    "gn:feature_code":"PPL",
    "gn:name":"Ilovitsy",
    "gn:population":0,
    "gn:timezone":"Europe/Moscow",
    "iso:country":"RU",
    "name:eng_x_preferred":[
        "Ilovitsy"
    ],
    "name:nor_x_preferred":[
        "Ilovitsy"
    ],
    "name:rus_x_preferred":[
        "\u0418\u043b\u043e\u0432\u0438\u0446\u044b"
    ],
    "name:und_x_variant":[
        "Ilovetsy",
        "\u0418\u043b\u043e\u0432\u0438\u0446\u044b",
        "Ilovitsy"
    ],
    "wof:name":"Ilovitsy",
    "wof:placetype":"locality"
},
  "geometry": {"coordinates":[34.07545,57.18449],"type":"Point"}
}