{
  "type": "Feature",
  "properties": {
    "gn:admin1_code":"55",
    "gn:asciiname":"Ivanovka Vtoraya",
    "gn:country_code":"RU",
    "gn:dem":104,
    "gn:feature_class":"P",
    "gn:feature_code":"PPL",
    "gn:name":"Ivanovka Vtoraya",
    "gn:population":0,
    "gn:timezone":"Asia/Yekaterinburg",
    "iso:country":"RU",
    "name:eng_x_preferred":[
        "Ivanovka Vtoraya"
    ],
    "name:nor_x_preferred":[
        "Ivanovka Vtoraja"
    ],
    "name:rus_x_preferred":[
        "\u0418\u0432\u0430\u043d\u043e\u0432\u043a\u0430 \u0412\u0442\u043e\u0440\u0430\u044f"
    ],
    "wof:name":"Ivanovka Vtoraya",
    "wof:placetype":"locality"
},
  "geometry": {"coordinates":[53.3866,52.4597],"type":"Point"}
}