{
  "type": "Feature",
  "properties": {
    "gn:admin1_code":"29",
    "gn:asciiname":"Novovostochnyy",
    "gn:country_code":"RU",
    "gn:dem":202,
    "gn:feature_class":"P",
    "gn:feature_code":"PPL",
    "gn:name":"Novovostochnyy",
    "gn:population":0,
    "gn:timezone":"Asia/Novokuznetsk",
    "iso:country":"RU",
    "name:rus_x_preferred":[
        "\u041d\u043e\u0432\u043e\u0432\u043e\u0441\u0442\u043e\u0447\u043d\u044b\u0439"
    ],
    "name:und_x_variant":[
        "Vostochnyy"
    ],
    "wof:name":"Novovostochnyy",
    "wof:placetype":"locality"
},
  "geometry": {"coordinates":[88.54083,56.15726],"type":"Point"}
}