{
  "type": "Feature",
  "properties": {
    "gn:admin1_code":"67",
    "gn:asciiname":"Moskva",
    "gn:cc2":"RU",
    "gn:country_code":"RU",
    "gn:dem":55,
    "gn:feature_class":"P",
    "gn:feature_code":"PPL",
    "gn:name":"Moskva",
    "gn:population":0,
    "gn:timezone":"Europe/Saratov",
    "iso:country":"RU",
    "name:bak_x_preferred":[
        "\u041c\u04d9\u0441\u043a\u04d9\u04af"
    ],
    "name:bel_x_preferred":[
        "\u041c\u0430\u0441\u043a\u0432\u0430"
    ],
    "name:bos_x_preferred":[
        "Moskva"
    ],
    "name:bre_x_preferred":[
        "Moskva"
    ],
    "name:ceb_x_preferred":[
        "Moskva"
    ],
    "name:ces_x_preferred":[
        "Moskva"
    ],
    "name:deu_x_preferred":[
        "Moskva"
    ],
    "name:epo_x_preferred":[
        "Moskva"
    ],
    "name:fin_x_preferred":[
        "Moskva"
    ],
    "name:fra_x_preferred":[
        "Moskva"
    ],
    "name:hrv_x_preferred":[
        "Moskva"
    ],
    "name:hun_x_preferred":[
        "Moszkva"
    ],
    "name:hye_x_preferred":[
        "\u0544\u0578\u057d\u056f\u057e\u0561"
    ],
    "name:ita_x_preferred":[
        "Moskva"
    ],
    "name:jpn_x_preferred":[
        "\u30e2\u30b9\u30af\u30ef"
    ],
    "name:kor_x_preferred":[
        "\ubaa8\uc2a4\ud06c\ubc14"
    ],
    "name:krc_x_preferred":[
        "\u041c\u043e\u0441\u043a\u0432\u0430"
    ],
    "name:lit_x_preferred":[
        "Maskva"
    ],
    "name:mkd_x_preferred":[
        "\u041c\u043e\u0441\u043a\u0432\u0430"
    ],
    "name:nld_x_preferred":[
        "Moskva"
    ],
    "name:pol_x_preferred":[
        "Moskva"
    ],
    "name:rus_x_preferred":[
        "\u041c\u043e\u0441\u043a\u0432\u0430"
    ],
    "name:slk_x_preferred":[
        "Moskva"
    ],
    "name:swe_x_preferred":[
        "Moskva"
    ],
    "name:tur_x_preferred":[
        "Moskva"
    ],
    "name:ukr_x_preferred":[
        "\u041c\u043e\u0441\u043a\u0432\u0430"
    ],
    "name:und_x_variant":[
        "Novaya Moskva"
    ],
    "name:uzb_x_preferred":[
        "Moskva"
    ],
    "wof:name":"Moskva",
    "wof:placetype":"locality"
},
  "geometry": {"coordinates":[48.88333,52.18333],"type":"Point"}
}