{
  "type": "Feature",
  "properties": {
    "gn:admin1_code":"67",
    "gn:asciiname":"Moskva",
    "gn:cc2":"RU",
    "gn:country_code":"RU",
    "gn:dem":55,
    "gn:feature_class":"P",
    "gn:feature_code":"PPL",
    "gn:name":"Moskva",
    "gn:population":0,
    "gn:timezone":"Europe/Saratov",
    "iso:country":"RU",
    "name:rus_x_preferred":[
        "\u041c\u043e\u0441\u043a\u0432\u0430"
    ],
    "name:und_x_variant":[
        "Novaya Moskva",
        "Moskva",
        "\u041c\u043e\u0441\u043a\u0432\u0430"
    ],
    "wof:name":"Moskva",
    "wof:placetype":"locality"
},
  "geometry": {"coordinates":[48.88333,52.18333],"type":"Point"}
}