{
  "type": "Feature",
  "properties": {
    "gn:admin1_code":"45",
    "gn:asciiname":"Kushnur",
    "gn:country_code":"RU",
    "gn:dem":117,
    "gn:feature_class":"P",
    "gn:feature_code":"PPL",
    "gn:name":"Kushnur",
    "gn:population":0,
    "gn:timezone":"Europe/Moscow",
    "iso:country":"RU",
    "name:eng_x_preferred":[
        "Kushnur"
    ],
    "name:nor_x_preferred":[
        "Tasjnur"
    ],
    "name:rus_x_preferred":[
        "\u0422\u0430\u0448\u043d\u0443\u0440"
    ],
    "name:rus_x_variant":[
        "\u041a\u0443\u0448\u043d\u0443\u0440"
    ],
    "name:und_x_variant":[
        "Kishnur",
        "Kushnur",
        "\u041a\u0443\u0448\u043d\u0443\u0440"
    ],
    "wof:name":"Kushnur",
    "wof:placetype":"locality"
},
  "geometry": {"coordinates":[48.28972,56.18389000000001],"type":"Point"}
}