{
  "type": "Feature",
  "properties": {
    "gn:admin1_code":"52.0",
    "gn:asciiname":"Babichi",
    "gn:country_code":"RU",
    "gn:dem":208,
    "gn:feature_class":"P",
    "gn:feature_code":"PPL",
    "gn:name":"Babichi",
    "gn:population":0,
    "gn:timezone":"Europe/Moscow",
    "iso:country":"RU",
    "name:nor_x_preferred":[
        "Babitsji"
    ],
    "name:rus_x_preferred":[
        "\u0411\u0430\u0431\u0438\u0447\u0438"
    ],
    "wof:name":"Babichi",
    "wof:placetype":"locality"
},
  "geometry": {"coordinates":[33.98333,59.16667],"type":"Point"}
}