{
  "type": "Feature",
  "properties": {
    "gn:admin1_code":"10",
    "gn:asciiname":"Zaytsevskiy",
    "gn:country_code":"RU",
    "gn:dem":198,
    "gn:feature_class":"P",
    "gn:feature_code":"PPL",
    "gn:name":"Zaytsevskiy",
    "gn:population":0,
    "gn:timezone":"Europe/Moscow",
    "iso:country":"RU",
    "name:rus_x_preferred":[
        "\u0417\u0430\u0439\u0446\u0435\u0432\u0441\u043a\u0438\u0439"
    ],
    "name:und_x_variant":[
        "Zaytsevskiy Pervyy",
        "Zaytsevskiy Vtoroy"
    ],
    "wof:name":"Zaytsevskiy",
    "wof:placetype":"locality"
},
  "geometry": {"coordinates":[34.683,52.07114],"type":"Point"}
}