{
  "type": "Feature",
  "properties": {
    "gn:admin1_code":"84",
    "gn:asciiname":"Verkhniy Yeruslan",
    "gn:country_code":"RU",
    "gn:dem":22,
    "gn:feature_class":"P",
    "gn:feature_code":"PPL",
    "gn:name":"Verkhniy Yeruslan",
    "gn:population":0,
    "gn:timezone":"Europe/Volgograd",
    "iso:country":"RU",
    "name:und_x_variant":[
        "Gnadentau",
        "Verkhniy Yeruslan"
    ],
    "wof:name":"Verkhniy Yeruslan",
    "wof:placetype":"locality"
},
  "geometry": {"coordinates":[46.51922,50.50621],"type":"Point"}
}