{
  "type": "Feature",
  "properties": {
    "gn:admin1_code":"69",
    "gn:asciiname":"Simonovka",
    "gn:country_code":"RU",
    "gn:dem":199,
    "gn:feature_class":"P",
    "gn:feature_code":"PPL",
    "gn:name":"Simonovka",
    "gn:population":0,
    "gn:timezone":"Europe/Moscow",
    "iso:country":"RU",
    "name:rus_x_preferred":[
        "\u0421\u0438\u043c\u043e\u043d\u043e\u0432\u043a\u0430"
    ],
    "name:und_x_variant":[
        "\u0421\u0438\u043c\u043e\u043d\u043e\u0432\u043a\u0430"
    ],
    "wof:name":"Simonovka",
    "wof:placetype":"locality"
},
  "geometry": {"coordinates":[31.89815,55.11158],"type":"Point"}
}