{
  "type": "Feature",
  "properties": {
    "gn:admin1_code":"41",
    "gn:asciiname":"Panskoye",
    "gn:country_code":"RU",
    "gn:dem":198,
    "gn:feature_class":"P",
    "gn:feature_code":"PPL",
    "gn:name":"Panskoye",
    "gn:population":0,
    "gn:timezone":"Europe/Moscow",
    "iso:country":"RU",
    "name:rus_x_preferred":[
        "\u041f\u0430\u043d\u0441\u043a\u043e\u0435"
    ],
    "wof:name":"Panskoye",
    "wof:placetype":"locality"
},
  "geometry": {"coordinates":[37.358,51.7526],"type":"Point"}
}