{
  "type": "Feature",
  "properties": {
    "gn:admin1_code":"28",
    "gn:asciiname":"Okhta",
    "gn:cc2":"RU",
    "gn:country_code":"RU",
    "gn:dem":175,
    "gn:feature_class":"P",
    "gn:feature_code":"PPL",
    "gn:name":"Okhta",
    "gn:population":0,
    "gn:timezone":"Europe/Moscow",
    "iso:country":"RU",
    "name:ceb_x_preferred":[
        "\u041e\u0445\u0442\u0430"
    ],
    "name:ces_x_preferred":[
        "Ochta"
    ],
    "name:fin_x_preferred":[
        "Ohta"
    ],
    "name:rus_x_preferred":[
        "\u041e\u0445\u0442\u0430"
    ],
    "wof:name":"Okhta",
    "wof:placetype":"locality"
},
  "geometry": {"coordinates":[30.84824,65.51382],"type":"Point"}
}