{
  "type": "Feature",
  "properties": {
    "gn:admin1_code":"90",
    "gn:asciiname":"Isakova",
    "gn:country_code":"RU",
    "gn:dem":152,
    "gn:feature_class":"P",
    "gn:feature_code":"PPL",
    "gn:name":"Isakova",
    "gn:population":0,
    "gn:timezone":"Asia/Yekaterinburg",
    "iso:country":"RU",
    "name:rus_x_preferred":[
        "\u0418\u0441\u0430\u043a\u043e\u0432\u0430"
    ],
    "name:und_x_variant":[
        "\u0418\u0441\u0430\u043a\u043e\u0432\u0430"
    ],
    "wof:name":"Isakova",
    "wof:placetype":"locality"
},
  "geometry": {"coordinates":[54.413,59.1375],"type":"Point"}
}