{
  "type": "Feature",
  "properties": {
    "gn:admin1_code":"77",
    "gn:asciiname":"Chekmarevo",
    "gn:country_code":"RU",
    "gn:dem":135,
    "gn:feature_class":"P",
    "gn:feature_code":"PPL",
    "gn:name":"Chekmar\u00ebvo",
    "gn:population":0,
    "gn:timezone":"Europe/Moscow",
    "iso:country":"RU",
    "name:rus_x_preferred":[
        "\u0427\u0435\u043a\u043c\u0430\u0440\u0451\u0432\u043e"
    ],
    "name:und_x_variant":[
        "Chekmar\u00ebvo"
    ],
    "wof:name":"Chekmarevo",
    "wof:placetype":"locality"
},
  "geometry": {"coordinates":[37.6162,57.3921],"type":"Point"}
}