{
  "type": "Feature",
  "properties": {
    "gn:admin1_code":"90",
    "gn:asciiname":"Yermashi",
    "gn:country_code":"RU",
    "gn:dem":127,
    "gn:feature_class":"P",
    "gn:feature_code":"PPL",
    "gn:name":"Yermashi",
    "gn:population":0,
    "gn:timezone":"Asia/Yekaterinburg",
    "iso:country":"RU",
    "name:rus_x_preferred":[
        "\u0415\u0440\u043c\u0430\u0448\u0438"
    ],
    "wof:name":"Yermashi",
    "wof:placetype":"locality"
},
  "geometry": {"coordinates":[56.1266,57.8891],"type":"Point"}
}