{
  "type": "Feature",
  "properties": {
    "gn:admin1_code":"1.0",
    "gn:asciiname":"Chekhrak",
    "gn:cc2":"RU",
    "gn:country_code":"RU",
    "gn:dem":127,
    "gn:feature_class":"P",
    "gn:feature_code":"PPL",
    "gn:name":"Chekhrak",
    "gn:population":0,
    "gn:timezone":"Europe/Moscow",
    "iso:country":"RU",
    "name:rus_x_preferred":[
        "\u0427\u0435\u0445\u0440\u0430\u043a"
    ],
    "name:und_x_variant":[
        "Chokhrak",
        "Chekhrak"
    ],
    "wof:name":"Chekhrak",
    "wof:placetype":"locality"
},
  "geometry": {"coordinates":[40.37778,44.93389000000001],"type":"Point"}
}