{
  "type": "Feature",
  "properties": {
    "gn:admin1_code":"86.0",
    "gn:asciiname":"Pereryvnyy",
    "gn:country_code":"RU",
    "gn:dem":198,
    "gn:feature_class":"P",
    "gn:feature_code":"PPL",
    "gn:name":"Pereryvnyy",
    "gn:population":0,
    "gn:timezone":"Europe/Moscow",
    "iso:country":"RU",
    "name:rus_x_preferred":[
        "\u041f\u0435\u0440\u0435\u0440\u044b\u0432\u043d\u044b\u0439"
    ],
    "name:und_x_variant":[
        "Perevynyy",
        "Pereryvnyy"
    ],
    "wof:name":"Pereryvnyy",
    "wof:placetype":"locality"
},
  "geometry": {"coordinates":[38.8583,51.3908],"type":"Point"}
}