{
  "type": "Feature",
  "properties": {
    "gn:admin1_code":"33.0",
    "gn:asciiname":"Abyzovtsy",
    "gn:country_code":"RU",
    "gn:dem":192,
    "gn:feature_class":"P",
    "gn:feature_code":"PPL",
    "gn:name":"Abyzovtsy",
    "gn:population":0,
    "gn:timezone":"Europe/Kirov",
    "iso:country":"RU",
    "name:rus_x_preferred":[
        "\u0410\u0431\u044b\u0437\u043e\u0432\u0446\u044b"
    ],
    "wof:name":"Abyzovtsy",
    "wof:placetype":"locality"
},
  "geometry": {"coordinates":[51.5335,57.9185],"type":"Point"}
}