{
  "type": "Feature",
  "properties": {
    "gn:admin1_code":"62",
    "gn:asciiname":"Samyshka",
    "gn:country_code":"RU",
    "gn:dem":105,
    "gn:feature_class":"P",
    "gn:feature_code":"PPL",
    "gn:name":"Samyshka",
    "gn:population":0,
    "gn:timezone":"Europe/Moscow",
    "iso:country":"RU",
    "name:rus_x_preferred":[
        "\u0421\u0430\u043c\u044b\u0448\u043a\u0430"
    ],
    "name:und_x_variant":[
        "Samyshki",
        "Samyshka"
    ],
    "wof:name":"Samyshka",
    "wof:placetype":"locality"
},
  "geometry": {"coordinates":[41.69024,54.93833000000001],"type":"Point"}
}