{
  "type": "Feature",
  "properties": {
    "gn:admin1_code":"47",
    "gn:asciiname":"Kadnikovo",
    "gn:country_code":"RU",
    "gn:dem":221,
    "gn:feature_class":"P",
    "gn:feature_code":"PPL",
    "gn:name":"Kadnikovo",
    "gn:population":0,
    "gn:timezone":"Europe/Moscow",
    "iso:country":"RU",
    "name:rus_x_preferred":[
        "\u041a\u0430\u0434\u043d\u0438\u043a\u043e\u0432\u043e"
    ],
    "name:und_x_variant":[
        "\u041a\u0430\u0434\u043d\u0438\u043a\u043e\u0432\u043e"
    ],
    "wof:name":"Kadnikovo",
    "wof:placetype":"locality"
},
  "geometry": {"coordinates":[36.3842,56.1221],"type":"Point"}
}