{
  "type": "Feature",
  "properties": {
    "gn:admin1_code":"77",
    "gn:asciiname":"Kholm",
    "gn:country_code":"RU",
    "gn:dem":193,
    "gn:feature_class":"P",
    "gn:feature_code":"PPL",
    "gn:name":"Kholm",
    "gn:population":0,
    "gn:timezone":"Europe/Moscow",
    "iso:country":"RU",
    "name:ceb_x_preferred":[
        "Kholm"
    ],
    "name:deu_x_preferred":[
        "Kholm"
    ],
    "name:rus_x_preferred":[
        "\u0425\u043e\u043b\u043c"
    ],
    "name:swe_x_preferred":[
        "Kholm"
    ],
    "wof:name":"Kholm",
    "wof:placetype":"locality"
},
  "geometry": {"coordinates":[33.01699,56.03155],"type":"Point"}
}