{
  "type": "Feature",
  "properties": {
    "gn:admin1_code":"85",
    "gn:asciiname":"Konanikha",
    "gn:country_code":"RU",
    "gn:dem":133,
    "gn:feature_class":"P",
    "gn:feature_code":"PPL",
    "gn:name":"Konanikha",
    "gn:population":0,
    "gn:timezone":"Europe/Moscow",
    "iso:country":"RU",
    "name:rus_x_preferred":[
        "\u041a\u043e\u043d\u0430\u043d\u0438\u0445\u0430"
    ],
    "name:und_x_variant":[
        "\u041a\u043e\u043d\u0430\u043d\u0438\u0445\u0430"
    ],
    "wof:name":"Konanikha",
    "wof:placetype":"locality"
},
  "geometry": {"coordinates":[39.9765,59.692],"type":"Point"}
}