{
  "type": "Feature",
  "properties": {
    "gn:admin1_code":"93",
    "gn:asciiname":"Adom",
    "gn:country_code":"RU",
    "gn:dem":709,
    "gn:feature_class":"P",
    "gn:feature_code":"PPL",
    "gn:name":"Adom",
    "gn:population":0,
    "gn:timezone":"Asia/Chita",
    "iso:country":"RU",
    "name:eng_x_preferred":[
        "Adom"
    ],
    "name:nor_x_preferred":[
        "Adom"
    ],
    "name:rus_x_preferred":[
        "\u0410\u0434\u043e\u043c"
    ],
    "name:und_x_variant":[
        "Adomskiy"
    ],
    "wof:name":"Adom",
    "wof:placetype":"locality"
},
  "geometry": {"coordinates":[117.51305000000001,52.43976],"type":"Point"}
}