{
  "type": "Feature",
  "properties": {
    "gn:admin1_code":"20",
    "gn:asciiname":"Usyk",
    "gn:country_code":"RU",
    "gn:dem":503,
    "gn:feature_class":"P",
    "gn:feature_code":"PPL",
    "gn:name":"Usyk",
    "gn:population":0,
    "gn:timezone":"Asia/Irkutsk",
    "iso:country":"RU",
    "name:eng_x_preferred":[
        "Usyk"
    ],
    "name:nor_x_preferred":[
        "Usyk"
    ],
    "name:rus_x_preferred":[
        "\u0423\u0441\u044b\u043a"
    ],
    "name:und_x_variant":[
        "Khaga"
    ],
    "wof:name":"Usyk",
    "wof:placetype":"locality"
},
  "geometry": {"coordinates":[107.71672,53.34189],"type":"Point"}
}