{
  "type": "Feature",
  "properties": {
    "gn:admin1_code":"51",
    "gn:asciiname":"Maydan",
    "gn:cc2":"RU",
    "gn:country_code":"RU",
    "gn:dem":130,
    "gn:feature_class":"P",
    "gn:feature_code":"PPL",
    "gn:name":"Maydan",
    "gn:population":0,
    "gn:timezone":"Europe/Moscow",
    "iso:country":"RU",
    "name:rus_x_preferred":[
        "\u041c\u0430\u0439\u0434\u0430\u043d"
    ],
    "name:und_x_variant":[
        "Pogorelovskaya",
        "Maydan",
        "\u041c\u0430\u0439\u0434\u0430\u043d"
    ],
    "wof:name":"Maydan",
    "wof:placetype":"locality"
},
  "geometry": {"coordinates":[45.21667,55.58333],"type":"Point"}
}