{
  "type": "Feature",
  "properties": {
    "gn:admin1_code":"86.0",
    "gn:asciiname":"Slavgorod",
    "gn:country_code":"RU",
    "gn:dem":111,
    "gn:feature_class":"P",
    "gn:feature_code":"PPL",
    "gn:name":"Slavgorod",
    "gn:population":0,
    "gn:timezone":"Europe/Moscow",
    "iso:country":"RU",
    "name:ara_x_preferred":[
        "\u0633\u0644\u0627\u0641\u063a\u0648\u0631\u0648\u062f"
    ],
    "name:azb_x_preferred":[
        "\u0627\u0633\u0644\u0627\u0648\u0642\u0648\u0631\u0648\u062f"
    ],
    "name:bel_x_preferred":[
        "\u0421\u043b\u0430\u045e\u0433\u0430\u0440\u0430\u0434"
    ],
    "name:ben_x_preferred":[
        "\u09b8\u09cd\u09b2\u09be\u09ad\u0997\u09cb\u09b0\u09cb\u09a6"
    ],
    "name:bul_x_preferred":[
        "\u0421\u043b\u0430\u0432\u0433\u043e\u0440\u043e\u0434"
    ],
    "name:cat_x_preferred":[
        "Sl\u00e0vgorod"
    ],
    "name:ceb_x_preferred":[
        "Slavgorod"
    ],
    "name:ces_x_preferred":[
        "Slavgorod"
    ],
    "name:deu_x_preferred":[
        "Slawgorod"
    ],
    "name:ell_x_preferred":[
        "\u03a3\u03bb\u03ac\u03b2\u03b3\u03ba\u03bf\u03c1\u03bf\u03bd\u03c4"
    ],
    "name:epo_x_preferred":[
        "Slavgorod"
    ],
    "name:fas_x_preferred":[
        "\u0627\u0633\u0644\u0627\u0648\u06af\u0648\u0631\u0648\u062f"
    ],
    "name:fra_x_preferred":[
        "Slavgorod"
    ],
    "name:heb_x_preferred":[
        "\u05e1\u05dc\u05d1\u05d2\u05d5\u05e8\u05d5\u05d3"
    ],
    "name:hin_x_preferred":[
        "\u0938\u094d\u0932\u093e\u0935\u0917\u094b\u0930\u094b\u0921"
    ],
    "name:hsb_x_preferred":[
        "Slawgorod"
    ],
    "name:ind_x_preferred":[
        "Slavgorod"
    ],
    "name:ita_x_preferred":[
        "Slavgorod"
    ],
    "name:kor_x_preferred":[
        "\uc2ac\ub77c\ube0c\uace0\ub85c\ub4dc"
    ],
    "name:nld_x_preferred":[
        "Slavgorod"
    ],
    "name:nno_x_preferred":[
        "Slavgorod"
    ],
    "name:nor_x_preferred":[
        "Slavgorod"
    ],
    "name:pol_x_preferred":[
        "S\u0142awgorod"
    ],
    "name:rus_x_preferred":[
        "\u0421\u043b\u0430\u0432\u0433\u043e\u0440\u043e\u0434"
    ],
    "name:spa_x_preferred":[
        "Sl\u00e1vgorod"
    ],
    "name:srp_x_preferred":[
        "\u0421\u043b\u0430\u0432\u0433\u043e\u0440\u043e\u0434"
    ],
    "name:swe_x_preferred":[
        "Slavgorod"
    ],
    "name:tat_x_preferred":[
        "\u0421\u043b\u0430\u0432\u0433\u043e\u0440\u043e\u0434"
    ],
    "name:tgk_x_preferred":[
        "\u0421\u043b\u0430\u0432\u0433\u043e\u0440\u043e\u0434"
    ],
    "name:tgl_x_preferred":[
        "Slavgorod"
    ],
    "name:tur_x_preferred":[
        "Slavgorod"
    ],
    "name:ukr_x_preferred":[
        "\u0421\u043b\u0430\u0432\u0433\u043e\u0440\u043e\u0434"
    ],
    "name:urd_x_preferred":[
        "\u0633\u0644\u0627\u0648\u06af\u0648\u0631\u0648\u062f"
    ],
    "name:vep_x_preferred":[
        "Slavgorod"
    ],
    "name:war_x_preferred":[
        "Slavgorod"
    ],
    "name:zho_x_preferred":[
        "\u65af\u62c9\u592b\u6208\u7f85\u5fb7"
    ],
    "wof:name":"Slavgorod",
    "wof:placetype":"locality"
},
  "geometry": {"coordinates":[40.64444,51.11944],"type":"Point"}
}