{
  "type": "Feature",
  "properties": {
    "gn:admin1_code":"86.0",
    "gn:asciiname":"Slavgorod",
    "gn:country_code":"RU",
    "gn:dem":111,
    "gn:feature_class":"P",
    "gn:feature_code":"PPL",
    "gn:name":"Slavgorod",
    "gn:population":0,
    "gn:timezone":"Europe/Moscow",
    "iso:country":"RU",
    "wof:name":"Slavgorod",
    "wof:placetype":"locality"
},
  "geometry": {"coordinates":[40.64444,51.11944],"type":"Point"}
}