{
  "type": "Feature",
  "properties": {
    "gn:admin1_code":"37",
    "gn:asciiname":"Ushakovo",
    "gn:country_code":"RU",
    "gn:dem":161,
    "gn:feature_class":"P",
    "gn:feature_code":"PPL",
    "gn:name":"Ushakovo",
    "gn:population":0,
    "gn:timezone":"Europe/Moscow",
    "iso:country":"RU",
    "name:und_x_variant":[
        "Ushikovo",
        "Ushakovo"
    ],
    "wof:name":"Ushakovo",
    "wof:placetype":"locality"
},
  "geometry": {"coordinates":[41.90132,58.70914000000001],"type":"Point"}
}