{
  "type": "Feature",
  "properties": {
    "gn:admin1_code":"77",
    "gn:asciiname":"Tishnevo",
    "gn:country_code":"RU",
    "gn:dem":258,
    "gn:feature_class":"P",
    "gn:feature_code":"PPL",
    "gn:name":"Tishnevo",
    "gn:population":0,
    "gn:timezone":"Europe/Moscow",
    "iso:country":"RU",
    "wof:name":"Tishnevo",
    "wof:placetype":"locality"
},
  "geometry": {"coordinates":[33.37090999999999,56.42201],"type":"Point"}
}