{
  "type": "Feature",
  "properties": {
    "gn:admin1_code":"71",
    "gn:asciiname":"Chikman",
    "gn:country_code":"RU",
    "gn:dem":148,
    "gn:feature_class":"P",
    "gn:feature_code":"PPL",
    "gn:name":"Chikman",
    "gn:population":0,
    "gn:timezone":"Asia/Yekaterinburg",
    "iso:country":"RU",
    "name:che_x_preferred":[
        "\u0427\u0438\u043a\u043c\u0430\u043d"
    ],
    "name:rus_x_preferred":[
        "\u0427\u0438\u043a\u043c\u0430\u043d"
    ],
    "wof:name":"Chikman",
    "wof:placetype":"locality"
},
  "geometry": {"coordinates":[61.96666999999999,58.08333],"type":"Point"}
}