{
  "type": "Feature",
  "properties": {
    "gn:admin1_code":"76",
    "gn:asciiname":"Krugloye",
    "gn:country_code":"RU",
    "gn:dem":157,
    "gn:feature_class":"P",
    "gn:feature_code":"PPL",
    "gn:name":"Krugloye",
    "gn:population":0,
    "gn:timezone":"Europe/Moscow",
    "iso:country":"RU",
    "name:rus_x_preferred":[
        "\u041a\u0440\u0443\u0433\u043b\u043e\u0435"
    ],
    "name:und_x_variant":[
        "\u041a\u0440\u0443\u0433\u043b\u043e\u0435"
    ],
    "wof:name":"Krugloye",
    "wof:placetype":"locality"
},
  "geometry": {"coordinates":[37.9513,53.15367],"type":"Point"}
}