{
  "type": "Feature",
  "properties": {
    "gn:admin1_code":"86",
    "gn:asciiname":"Baranov",
    "gn:country_code":"RU",
    "gn:dem":214,
    "gn:feature_class":"P",
    "gn:feature_code":"PPL",
    "gn:name":"Baranov",
    "gn:population":0,
    "gn:timezone":"Europe/Moscow",
    "iso:country":"RU",
    "name:rus_x_preferred":[
        "\u0411\u0430\u0440\u0430\u043d\u043e\u0432"
    ],
    "wof:name":"Baranov",
    "wof:placetype":"locality"
},
  "geometry": {"coordinates":[38.5804,51.3783],"type":"Point"}
}