{
  "type": "Feature",
  "properties": {
    "gn:admin1_code":"91",
    "gn:asciiname":"Pustyn'",
    "gn:country_code":"RU",
    "gn:dem":510,
    "gn:feature_class":"P",
    "gn:feature_code":"PPL",
    "gn:name":"Pustyn\u2019",
    "gn:population":0,
    "gn:timezone":"Asia/Krasnoyarsk",
    "iso:country":"RU",
    "name:rus_x_preferred":[
        "\u041f\u0443\u0441\u0442\u044b\u043d\u044c"
    ],
    "name:und_x_variant":[
        "Nustyn\u2019",
        "Pustyn\u2019"
    ],
    "wof:name":"Pustyn'",
    "wof:placetype":"locality"
},
  "geometry": {"coordinates":[91.78333000000001,54.08333],"type":"Point"}
}