{
  "type": "Feature",
  "properties": {
    "gn:admin1_code":"40",
    "gn:asciiname":"Dolgiye",
    "gn:cc2":"RU",
    "gn:country_code":"RU",
    "gn:dem":130,
    "gn:feature_class":"P",
    "gn:feature_code":"PPL",
    "gn:name":"Dolgiye",
    "gn:population":0,
    "gn:timezone":"Asia/Yekaterinburg",
    "iso:country":"RU",
    "name:eng_x_preferred":[
        "Dolgiye"
    ],
    "name:nor_x_preferred":[
        "Dolgije"
    ],
    "name:rus_x_preferred":[
        "\u0414\u043e\u043b\u0433\u0438\u0435"
    ],
    "name:und_x_variant":[
        "Dolgovskoye",
        "\u0414\u043e\u043b\u0433\u0438\u0435",
        "Dolgiye"
    ],
    "wof:name":"Dolgiye",
    "wof:placetype":"locality"
},
  "geometry": {"coordinates":[67.735,55.44528],"type":"Point"}
}