{
  "type": "Feature",
  "properties": {
    "gn:admin1_code":"47.0",
    "gn:asciiname":"Brekhovo",
    "gn:country_code":"RU",
    "gn:dem":201,
    "gn:feature_class":"P",
    "gn:feature_code":"PPL",
    "gn:name":"Br\u00ebkhovo",
    "gn:population":887,
    "gn:timezone":"Europe/Moscow",
    "iso:country":"RU",
    "name:rus_x_preferred":[
        "\u0411\u0440\u0451\u0445\u043e\u0432\u043e"
    ],
    "name:und_x_variant":[
        "Br\u00ebkhovo",
        "\u0411\u0440\u0451\u0445\u043e\u0432\u043e"
    ],
    "wof:name":"Brekhovo",
    "wof:placetype":"locality",
    "wof:population":887
},
  "geometry": {"coordinates":[37.18917,55.93389000000001],"type":"Point"}
}