{
  "type": "Feature",
  "properties": {
    "gn:admin1_code":"54",
    "gn:asciiname":"Mezhdurech'ye",
    "gn:country_code":"RU",
    "gn:dem":67,
    "gn:feature_class":"P",
    "gn:feature_code":"PPL",
    "gn:name":"Mezhdurech\u2019ye",
    "gn:population":0,
    "gn:timezone":"Asia/Omsk",
    "iso:country":"RU",
    "name:rus_x_preferred":[
        "\u041c\u0435\u0436\u0434\u0443\u0440\u0435\u0447\u044c\u0435"
    ],
    "name:und_x_variant":[
        "Mezhdurech\u2019ye",
        "\u041c\u0435\u0436\u0434\u0443\u0440\u0435\u0447\u044c\u0435"
    ],
    "wof:name":"Mezhdurech'ye",
    "wof:placetype":"locality"
},
  "geometry": {"coordinates":[74.5947,56.8141],"type":"Point"}
}