{
  "type": "Feature",
  "properties": {
    "gn:admin1_code":"6",
    "gn:asciiname":"Ivashevskaya",
    "gn:country_code":"RU",
    "gn:dem":84,
    "gn:feature_class":"P",
    "gn:feature_code":"PPL",
    "gn:name":"Ivashevskaya",
    "gn:population":0,
    "gn:timezone":"Europe/Moscow",
    "iso:country":"RU",
    "name:eng_x_preferred":[
        "Ivashevskaya"
    ],
    "name:nor_x_preferred":[
        "Ivasjevskaja"
    ],
    "name:rus_x_preferred":[
        "\u0418\u0432\u0430\u0448\u0435\u0432\u0441\u043a\u0430\u044f"
    ],
    "name:und_x_variant":[
        "\u0418\u0432\u0430\u0448\u0435\u0432\u0441\u043a\u0430\u044f",
        "Ivashevskaya"
    ],
    "wof:name":"Ivashevskaya",
    "wof:placetype":"locality"
},
  "geometry": {"coordinates":[43.91389,61.6125],"type":"Point"}
}