{
  "type": "Feature",
  "properties": {
    "gn:admin1_code":"33",
    "gn:asciiname":"Moshkino",
    "gn:country_code":"RU",
    "gn:dem":138,
    "gn:feature_class":"P",
    "gn:feature_code":"PPL",
    "gn:name":"Moshkino",
    "gn:population":0,
    "gn:timezone":"Europe/Kirov",
    "iso:country":"RU",
    "name:rus_x_preferred":[
        "\u041c\u043e\u0448\u043a\u0438\u043d\u043e"
    ],
    "name:und_x_variant":[
        "\u041c\u043e\u0448\u043a\u0438\u043d\u043e"
    ],
    "wof:name":"Moshkino",
    "wof:placetype":"locality"
},
  "geometry": {"coordinates":[50.38172,58.42438000000001],"type":"Point"}
}