{
  "type": "Feature",
  "properties": {
    "gn:admin1_code":"47",
    "gn:asciiname":"Kurvino",
    "gn:country_code":"RU",
    "gn:dem":160,
    "gn:feature_class":"P",
    "gn:feature_code":"PPL",
    "gn:name":"Kurvino",
    "gn:population":0,
    "gn:timezone":"Europe/Moscow",
    "iso:country":"RU",
    "name:nor_x_preferred":[
        "Kurvino"
    ],
    "name:rus_x_preferred":[
        "\u041a\u0443\u0440\u0432\u0438\u043d\u043e"
    ],
    "wof:name":"Kurvino",
    "wof:placetype":"locality"
},
  "geometry": {"coordinates":[35.67532999999999,56.18682],"type":"Point"}
}