{
  "type": "Feature",
  "properties": {
    "gn:admin1_code":"56",
    "gn:asciiname":"Kopytets",
    "gn:country_code":"RU",
    "gn:dem":199,
    "gn:feature_class":"P",
    "gn:feature_code":"PPL",
    "gn:name":"Kopytets",
    "gn:population":0,
    "gn:timezone":"Europe/Moscow",
    "iso:country":"RU",
    "name:rus_x_preferred":[
        "\u041a\u043e\u043f\u044b\u0442\u0435\u0446"
    ],
    "name:und_x_variant":[
        "\u041a\u043e\u043f\u044b\u0442\u0435\u0446"
    ],
    "wof:name":"Kopytets",
    "wof:placetype":"locality"
},
  "geometry": {"coordinates":[35.36306,53.06306],"type":"Point"}
}