{
  "type": "Feature",
  "properties": {
    "gn:admin1_code":"8",
    "gn:asciiname":"Saratovskiy",
    "gn:country_code":"RU",
    "gn:dem":502,
    "gn:feature_class":"P",
    "gn:feature_code":"PPL",
    "gn:name":"Saratovskiy",
    "gn:population":0,
    "gn:timezone":"Asia/Yekaterinburg",
    "iso:country":"RU",
    "name:eng_x_preferred":[
        "Saratovskiy"
    ],
    "name:nor_x_preferred":[
        "Saratovskij"
    ],
    "name:rus_x_preferred":[
        "\u0421\u0430\u0440\u0430\u0442\u043e\u0432\u0441\u043a\u0438\u0439"
    ],
    "name:und_x_variant":[
        "\u0421\u0430\u0440\u0430\u0442\u043e\u0432\u0441\u043a\u0438\u0439",
        "Saratovskiy"
    ],
    "wof:name":"Saratovskiy",
    "wof:placetype":"locality"
},
  "geometry": {"coordinates":[57.2203,52.3869],"type":"Point"}
}