{
  "type": "Feature",
  "properties": {
    "gn:admin1_code":"38",
    "gn:asciiname":"Seyatel'",
    "gn:country_code":"RU",
    "gn:dem":145,
    "gn:feature_class":"P",
    "gn:feature_code":"PPL",
    "gn:name":"Seyatel\u2019",
    "gn:population":0,
    "gn:timezone":"Europe/Moscow",
    "iso:country":"RU",
    "name:rus_x_preferred":[
        "\u0421\u0435\u044f\u0442\u0435\u043b\u044c"
    ],
    "name:und_x_variant":[
        "Svyatel\u2019",
        "Seyatel\u2019",
        "\u0421\u0435\u044f\u0442\u0435\u043b\u044c"
    ],
    "wof:name":"Seyatel'",
    "wof:placetype":"locality"
},
  "geometry": {"coordinates":[40.545,44.95278],"type":"Point"}
}