{
  "type": "Feature",
  "properties": {
    "gn:admin1_code":"83",
    "gn:asciiname":"Kaznevo",
    "gn:country_code":"RU",
    "gn:dem":90,
    "gn:feature_class":"P",
    "gn:feature_code":"PPL",
    "gn:name":"Kazn\u00ebvo",
    "gn:population":0,
    "gn:timezone":"Europe/Moscow",
    "iso:country":"RU",
    "name:rus_x_preferred":[
        "\u041a\u0430\u0437\u043d\u0451\u0432\u043e"
    ],
    "name:und_x_variant":[
        "Kazneva",
        "Kazn\u00ebvo",
        "\u041a\u0430\u0437\u043d\u0451\u0432\u043e"
    ],
    "wof:name":"Kaznevo",
    "wof:placetype":"locality"
},
  "geometry": {"coordinates":[41.92714,55.29456],"type":"Point"}
}