{
  "type": "Feature",
  "properties": {
    "gn:admin1_code":"76",
    "gn:asciiname":"Sredniye Rostoki",
    "gn:country_code":"RU",
    "gn:dem":155,
    "gn:feature_class":"P",
    "gn:feature_code":"PPL",
    "gn:name":"Sredniye Rostoki",
    "gn:population":0,
    "gn:timezone":"Europe/Moscow",
    "iso:country":"RU",
    "wof:name":"Sredniye Rostoki",
    "wof:placetype":"locality"
},
  "geometry": {"coordinates":[36.3325,53.49806],"type":"Point"}
}