{
  "type": "Feature",
  "properties": {
    "gn:admin1_code":"76.0",
    "gn:asciiname":"Glebovo",
    "gn:country_code":"RU",
    "gn:dem":214,
    "gn:feature_class":"P",
    "gn:feature_code":"PPL",
    "gn:name":"Glebovo",
    "gn:population":0,
    "gn:timezone":"Europe/Moscow",
    "iso:country":"RU",
    "name:rus_x_preferred":[
        "\u0413\u043b\u0435\u0431\u043e\u0432\u043e"
    ],
    "name:und_x_variant":[
        "Glebovo-Durnovo",
        "Glebovo",
        "\u0413\u043b\u0435\u0431\u043e\u0432\u043e"
    ],
    "wof:name":"Glebovo",
    "wof:placetype":"locality"
},
  "geometry": {"coordinates":[37.41919,53.31139],"type":"Point"}
}