{
  "type": "Feature",
  "properties": {
    "gn:admin1_code":"20",
    "gn:asciiname":"Mankres",
    "gn:country_code":"RU",
    "gn:dem":1559,
    "gn:feature_class":"P",
    "gn:feature_code":"PPL",
    "gn:name":"Mankres",
    "gn:population":0,
    "gn:timezone":"Asia/Irkutsk",
    "iso:country":"RU",
    "name:rus_x_preferred":[
        "\u041c\u0430\u043d\u043a\u0440\u0435\u0441"
    ],
    "wof:name":"Mankres",
    "wof:placetype":"locality"
},
  "geometry": {"coordinates":[98.95,53.68333000000001],"type":"Point"}
}