{
  "type": "Feature",
  "properties": {
    "gn:admin1_code":"86.0",
    "gn:asciiname":"Semibratskiy",
    "gn:country_code":"RU",
    "gn:dem":201,
    "gn:feature_class":"P",
    "gn:feature_code":"PPL",
    "gn:name":"Semibratskiy",
    "gn:population":0,
    "gn:timezone":"Europe/Moscow",
    "iso:country":"RU",
    "name:rus_x_preferred":[
        "\u0421\u0435\u043c\u0438\u0431\u0440\u0430\u0442\u0441\u043a\u0438\u0439"
    ],
    "wof:name":"Semibratskiy",
    "wof:placetype":"locality"
},
  "geometry": {"coordinates":[41.0127,50.8075],"type":"Point"}
}