{
  "type": "Feature",
  "properties": {
    "gn:admin1_code":"33",
    "gn:asciiname":"Kozha",
    "gn:country_code":"RU",
    "gn:dem":142,
    "gn:feature_class":"P",
    "gn:feature_code":"PPL",
    "gn:name":"Kozha",
    "gn:population":0,
    "gn:timezone":"Europe/Kirov",
    "iso:country":"RU",
    "name:eng_x_preferred":[
        "Kozha"
    ],
    "name:nor_x_preferred":[
        "Kozja"
    ],
    "name:rus_x_preferred":[
        "\u041a\u043e\u0436\u0430"
    ],
    "name:und_x_variant":[
        "\u041a\u043e\u0436\u0430",
        "Kozha"
    ],
    "wof:name":"Kozha",
    "wof:placetype":"locality"
},
  "geometry": {"coordinates":[48.91518,57.79541],"type":"Point"}
}