{
  "type": "Feature",
  "properties": {
    "gn:admin1_code":"60",
    "gn:asciiname":"Myshkovo",
    "gn:country_code":"RU",
    "gn:dem":99,
    "gn:feature_class":"P",
    "gn:feature_code":"PPL",
    "gn:name":"Myshkovo",
    "gn:population":0,
    "gn:timezone":"Europe/Moscow",
    "iso:country":"RU",
    "name:rus_x_preferred":[
        "\u041c\u044b\u0448\u043a\u043e\u0432\u043e"
    ],
    "wof:name":"Myshkovo",
    "wof:placetype":"locality"
},
  "geometry": {"coordinates":[28.27612,56.75219],"type":"Point"}
}