{
  "type": "Feature",
  "properties": {
    "gn:admin1_code":"33",
    "gn:asciiname":"Natyunichi",
    "gn:country_code":"RU",
    "gn:dem":155,
    "gn:feature_class":"P",
    "gn:feature_code":"PPL",
    "gn:name":"Natyunichi",
    "gn:population":0,
    "gn:timezone":"Europe/Kirov",
    "iso:country":"RU",
    "name:rus_x_preferred":[
        "\u041d\u0430\u0442\u044e\u043d\u0438\u0447\u0438"
    ],
    "wof:name":"Natyunichi",
    "wof:placetype":"locality"
},
  "geometry": {"coordinates":[49.2195,59.0473],"type":"Point"}
}