{
  "type": "Feature",
  "properties": {
    "gn:admin1_code":"10",
    "gn:asciiname":"Karbovka",
    "gn:country_code":"RU",
    "gn:dem":161,
    "gn:feature_class":"P",
    "gn:feature_code":"PPL",
    "gn:name":"Karbovka",
    "gn:population":0,
    "gn:timezone":"Europe/Moscow",
    "iso:country":"RU",
    "name:rus_x_preferred":[
        "\u041a\u0430\u0440\u0431\u043e\u0432\u043a\u0430"
    ],
    "name:und_x_variant":[
        "Kambovka",
        "Karbovka"
    ],
    "wof:name":"Karbovka",
    "wof:placetype":"locality"
},
  "geometry": {"coordinates":[33.4475,52.64626],"type":"Point"}
}