{
  "type": "Feature",
  "properties": {
    "gn:admin1_code":"6",
    "gn:asciiname":"Nimen'gskiy",
    "gn:country_code":"RU",
    "gn:dem":174,
    "gn:feature_class":"P",
    "gn:feature_code":"PPL",
    "gn:name":"Nimen\u2019gskiy",
    "gn:population":0,
    "gn:timezone":"Europe/Moscow",
    "iso:country":"RU",
    "name:rus_x_preferred":[
        "\u041d\u0438\u043c\u0435\u043d\u044c\u0433\u0441\u043a\u0438\u0439"
    ],
    "name:und_x_variant":[
        "Nimen\u2019gskiy"
    ],
    "wof:name":"Nimen'gskiy",
    "wof:placetype":"locality"
},
  "geometry": {"coordinates":[39.65,61.15],"type":"Point"}
}