{
  "type": "Feature",
  "properties": {
    "gn:admin1_code":"71",
    "gn:asciiname":"Neustroyeva",
    "gn:country_code":"RU",
    "gn:dem":89,
    "gn:feature_class":"P",
    "gn:feature_code":"PPL",
    "gn:name":"Neustroyeva",
    "gn:population":0,
    "gn:timezone":"Asia/Yekaterinburg",
    "iso:country":"RU",
    "name:rus_x_preferred":[
        "\u041d\u0435\u0443\u0441\u0442\u0440\u043e\u0435\u0432\u0430"
    ],
    "name:und_x_variant":[
        "\u041d\u0435\u0443\u0441\u0442\u0440\u043e\u0435\u0432\u0430"
    ],
    "wof:name":"Neustroyeva",
    "wof:placetype":"locality"
},
  "geometry": {"coordinates":[62.44028,57.55817],"type":"Point"}
}