{
  "type": "Feature",
  "properties": {
    "gn:admin1_code":"73",
    "gn:asciiname":"Kugashevo",
    "gn:country_code":"RU",
    "gn:dem":114,
    "gn:feature_class":"P",
    "gn:feature_code":"PPL",
    "gn:name":"Kugashevo",
    "gn:population":0,
    "gn:timezone":"Europe/Moscow",
    "iso:country":"RU",
    "name:rus_x_preferred":[
        "\u041a\u0443\u0433\u0430\u0448\u0435\u0432\u043e"
    ],
    "wof:name":"Kugashevo",
    "wof:placetype":"locality"
},
  "geometry": {"coordinates":[52.6693,55.6155],"type":"Point"}
}