{
  "type": "Feature",
  "properties": {
    "gn:admin1_code":"20",
    "gn:asciiname":"Nizhnyaya Iret'",
    "gn:country_code":"RU",
    "gn:dem":463,
    "gn:feature_class":"P",
    "gn:feature_code":"PPL",
    "gn:name":"Nizhnyaya Iret\u2019",
    "gn:population":0,
    "gn:timezone":"Asia/Irkutsk",
    "iso:country":"RU",
    "name:rus_x_preferred":[
        "\u041d\u0438\u0436\u043d\u044f\u044f \u0418\u0440\u0435\u0442\u044c"
    ],
    "name:und_x_variant":[
        "Iret\u2019",
        "Nizhnyaya Iret\u2019",
        "\u041d\u0438\u0436\u043d\u044f\u044f \u0418\u0440\u0435\u0442\u044c"
    ],
    "wof:name":"Nizhnyaya Iret'",
    "wof:placetype":"locality"
},
  "geometry": {"coordinates":[102.49666999999999,52.98444],"type":"Point"}
}