{
  "type": "Feature",
  "properties": {
    "gn:admin1_code":"45.0",
    "gn:asciiname":"Malaya Kemsola",
    "gn:country_code":"RU",
    "gn:dem":164,
    "gn:feature_class":"P",
    "gn:feature_code":"PPL",
    "gn:name":"Malaya Kemsola",
    "gn:population":0,
    "gn:timezone":"Europe/Moscow",
    "iso:country":"RU",
    "name:rus_x_preferred":[
        "\u041c\u0430\u043b\u0430\u044f \u041a\u0435\u043c\u0441\u043e\u043b\u0430"
    ],
    "name:und_x_variant":[
        "\u041c\u0430\u043b\u0430\u044f \u041a\u0435\u043c\u0441\u043e\u043b\u0430"
    ],
    "wof:name":"Malaya Kemsola",
    "wof:placetype":"locality"
},
  "geometry": {"coordinates":[48.725,56.90667],"type":"Point"}
}