{
  "type": "Feature",
  "properties": {
    "gn:admin1_code":"60",
    "gn:asciiname":"Gorbuny",
    "gn:country_code":"RU",
    "gn:dem":80,
    "gn:feature_class":"P",
    "gn:feature_code":"PPL",
    "gn:name":"Gorbuny",
    "gn:population":0,
    "gn:timezone":"Europe/Moscow",
    "iso:country":"RU",
    "name:rus_x_preferred":[
        "\u0413\u043e\u0440\u0431\u0443\u043d\u044b"
    ],
    "wof:name":"Gorbuny",
    "wof:placetype":"locality"
},
  "geometry": {"coordinates":[28.52409,57.08774],"type":"Point"}
}