{
  "type": "Feature",
  "properties": {
    "gn:admin1_code":"86.0",
    "gn:asciiname":"Biryuch",
    "gn:country_code":"RU",
    "gn:dem":150,
    "gn:feature_class":"P",
    "gn:feature_code":"PPL",
    "gn:name":"Biryuch",
    "gn:population":0,
    "gn:timezone":"Europe/Moscow",
    "iso:country":"RU",
    "name:rus_x_preferred":[
        "\u0411\u0438\u0440\u044e\u0447"
    ],
    "name:und_x_variant":[
        "\u0411\u0438\u0440\u044e\u0447"
    ],
    "wof:name":"Biryuch",
    "wof:placetype":"locality"
},
  "geometry": {"coordinates":[40.28944,51.04194],"type":"Point"}
}