{
  "type": "Feature",
  "properties": {
    "gn:admin1_code":"69.0",
    "gn:asciiname":"Boldino",
    "gn:country_code":"RU",
    "gn:dem":192,
    "gn:feature_class":"P",
    "gn:feature_code":"PPL",
    "gn:name":"Boldino",
    "gn:population":0,
    "gn:timezone":"Europe/Moscow",
    "iso:country":"RU",
    "name:eng_x_preferred":[
        "Boldino"
    ],
    "name:nor_x_preferred":[
        "Boldino"
    ],
    "name:rus_x_preferred":[
        "\u0411\u043e\u043b\u0434\u0438\u043d\u043e"
    ],
    "name:und_x_variant":[
        "\u0411\u043e\u043b\u0434\u0438\u043d\u043e",
        "Boldino"
    ],
    "wof:name":"Boldino",
    "wof:placetype":"locality"
},
  "geometry": {"coordinates":[33.51725,54.92213],"type":"Point"}
}