{
  "type": "Feature",
  "properties": {
    "gn:admin1_code":"28",
    "gn:asciiname":"Seletskoye",
    "gn:country_code":"RU",
    "gn:dem":63,
    "gn:feature_class":"P",
    "gn:feature_code":"PPL",
    "gn:name":"Seletskoye",
    "gn:population":0,
    "gn:timezone":"Europe/Moscow",
    "iso:country":"RU",
    "name:fin_x_preferred":[
        "Seletska"
    ],
    "name:rus_x_preferred":[
        "\u0421\u0435\u043b\u0435\u0442\u0441\u043a\u043e\u0435"
    ],
    "wof:name":"Seletskoye",
    "wof:placetype":"locality"
},
  "geometry": {"coordinates":[34.91303,62.36284000000001],"type":"Point"}
}