{
  "type": "Feature",
  "properties": {
    "gn:admin1_code":"63",
    "gn:asciiname":"Krestyakh",
    "gn:country_code":"RU",
    "gn:dem":264,
    "gn:feature_class":"P",
    "gn:feature_code":"PPL",
    "gn:name":"Krestyakh",
    "gn:population":0,
    "gn:timezone":"Asia/Yakutsk",
    "iso:country":"RU",
    "name:che_x_preferred":[
        "\u041a\u0440\u0435\u0441\u0442\u044f\u0445"
    ],
    "name:eng_x_preferred":[
        "Krestyakh"
    ],
    "name:hye_x_preferred":[
        "\u053f\u0580\u0565\u057d\u057f\u0575\u0561\u056d"
    ],
    "name:nor_x_preferred":[
        "Krestjakh"
    ],
    "name:rus_x_preferred":[
        "\u041a\u0440\u0435\u0441\u0442\u044f\u0445"
    ],
    "name:sah_x_preferred":[
        "\u041a\u0438\u0440\u0438\u044d\u0441\u0442\u044d\u044d\u0445"
    ],
    "name:und_x_variant":[
        "\u041a\u0440\u0435\u0441\u0442\u044f\u0445",
        "Krestyakh"
    ],
    "wof:name":"Krestyakh",
    "wof:placetype":"locality"
},
  "geometry": {"coordinates":[131.65000000000001,61.06667],"type":"Point"}
}