{
  "type": "Feature",
  "properties": {
    "gn:admin1_code":"4",
    "gn:asciiname":"Tsibermanovo",
    "gn:country_code":"RU",
    "gn:dem":151,
    "gn:feature_class":"P",
    "gn:feature_code":"PPL",
    "gn:name":"Tsibermanovo",
    "gn:population":0,
    "gn:timezone":"Asia/Barnaul",
    "iso:country":"RU",
    "name:rus_x_preferred":[
        "\u0426\u0438\u0431\u0435\u0440\u043c\u0430\u043d\u043e\u0432\u043e"
    ],
    "name:und_x_variant":[
        "Novaya Tsibermanovka",
        "Tsibermanovo",
        "\u0426\u0438\u0431\u0435\u0440\u043c\u0430\u043d\u043e\u0432\u043e",
        "Novotsibermanovka"
    ],
    "wof:name":"Tsibermanovo",
    "wof:placetype":"locality"
},
  "geometry": {"coordinates":[79.8135,53.3042],"type":"Point"}
}