{
  "type": "Feature",
  "properties": {
    "gn:admin1_code":"90",
    "gn:asciiname":"Matveyevo",
    "gn:country_code":"RU",
    "gn:dem":181,
    "gn:feature_class":"P",
    "gn:feature_code":"PPL",
    "gn:name":"Matveyevo",
    "gn:population":0,
    "gn:timezone":"Asia/Yekaterinburg",
    "iso:country":"RU",
    "name:eng_x_preferred":[
        "Matveyevo"
    ],
    "name:nor_x_preferred":[
        "Matvejevo"
    ],
    "name:rus_x_preferred":[
        "\u041c\u0430\u0442\u0432\u0435\u0435\u0432\u043e"
    ],
    "name:und_x_variant":[
        "Matveyeva",
        "Matveyevo",
        "\u041c\u0430\u0442\u0432\u0435\u0435\u0432\u043e"
    ],
    "wof:name":"Matveyevo",
    "wof:placetype":"locality"
},
  "geometry": {"coordinates":[57.8426,57.7783],"type":"Point"}
}