{
  "type": "Feature",
  "properties": {
    "gn:admin1_code":"40.0",
    "gn:asciiname":"Dernova",
    "gn:country_code":"RU",
    "gn:dem":109,
    "gn:feature_class":"P",
    "gn:feature_code":"PPL",
    "gn:name":"Dernova",
    "gn:population":0,
    "gn:timezone":"Asia/Yekaterinburg",
    "iso:country":"RU",
    "name:rus_x_preferred":[
        "\u0414\u0435\u0440\u043d\u043e\u0432\u0430"
    ],
    "wof:name":"Dernova",
    "wof:placetype":"locality"
},
  "geometry": {"coordinates":[64.49460000000001,56.3522],"type":"Point"}
}