{
  "type": "Feature",
  "properties": {
    "gn:admin1_code":"80",
    "gn:asciiname":"Kozino",
    "gn:country_code":"RU",
    "gn:dem":144,
    "gn:feature_class":"P",
    "gn:feature_code":"PPL",
    "gn:name":"Kozino",
    "gn:population":0,
    "gn:timezone":"Europe/Samara",
    "iso:country":"RU",
    "name:rus_x_preferred":[
        "\u041a\u043e\u0437\u0438\u043d\u043e"
    ],
    "wof:name":"Kozino",
    "wof:placetype":"locality"
},
  "geometry": {"coordinates":[54.03055,57.30933],"type":"Point"}
}