{
  "type": "Feature",
  "properties": {
    "gn:admin1_code":"41",
    "gn:asciiname":"Krasnaya Strelitsa",
    "gn:country_code":"RU",
    "gn:dem":214,
    "gn:feature_class":"P",
    "gn:feature_code":"PPL",
    "gn:name":"Krasnaya Strelitsa",
    "gn:population":0,
    "gn:timezone":"Europe/Moscow",
    "iso:country":"RU",
    "name:rus_x_preferred":[
        "\u041a\u0440\u0430\u0441\u043d\u0430\u044f \u0421\u0442\u0440\u0435\u043b\u0438\u0446\u0430"
    ],
    "wof:name":"Krasnaya Strelitsa",
    "wof:placetype":"locality"
},
  "geometry": {"coordinates":[34.4877,51.8585],"type":"Point"}
}