{
  "type": "Feature",
  "properties": {
    "gn:admin1_code":"85",
    "gn:asciiname":"Velikiy Dvor",
    "gn:country_code":"RU",
    "gn:dem":143,
    "gn:feature_class":"P",
    "gn:feature_code":"PPL",
    "gn:name":"Velikiy Dvor",
    "gn:population":0,
    "gn:timezone":"Europe/Moscow",
    "iso:country":"RU",
    "name:rus_x_preferred":[
        "\u0412\u0435\u043b\u0438\u043a\u0438\u0439 \u0414\u0432\u043e\u0440"
    ],
    "name:und_x_variant":[
        "\u0412\u0435\u043b\u0438\u043a\u0438\u0439 \u0414\u0432\u043e\u0440"
    ],
    "wof:name":"Velikiy Dvor",
    "wof:placetype":"locality"
},
  "geometry": {"coordinates":[38.3339,59.9395],"type":"Point"}
}