{
  "type": "Feature",
  "properties": {
    "gn:admin1_code":"63",
    "gn:asciiname":"Cherendey",
    "gn:country_code":"RU",
    "gn:dem":376,
    "gn:feature_class":"P",
    "gn:feature_code":"PPL",
    "gn:name":"Cherendey",
    "gn:population":0,
    "gn:timezone":"Asia/Yakutsk",
    "iso:country":"RU",
    "name:eng_x_preferred":[
        "Cherendey"
    ],
    "name:nor_x_preferred":[
        "Tsjerendej"
    ],
    "name:rus_x_preferred":[
        "\u0427\u0435\u0440\u0435\u043d\u0434\u0435\u0439"
    ],
    "name:und_x_variant":[
        "\u0427\u0435\u0440\u0435\u043d\u0434\u0435\u0439",
        "Cherendey"
    ],
    "wof:name":"Cherendey",
    "wof:placetype":"locality"
},
  "geometry": {"coordinates":[119.35167,60.22528000000001],"type":"Point"}
}