{
  "type": "Feature",
  "properties": {
    "gn:admin1_code":"86",
    "gn:asciiname":"Samara",
    "gn:country_code":"RU",
    "gn:dem":201,
    "gn:feature_class":"P",
    "gn:feature_code":"PPL",
    "gn:name":"Samara",
    "gn:population":0,
    "gn:timezone":"Europe/Moscow",
    "iso:country":"RU",
    "name:rus_x_preferred":[
        "\u0421\u0430\u043c\u0430\u0440\u0430"
    ],
    "name:und_x_variant":[
        "\u0421\u0430\u043c\u0430\u0440\u0430"
    ],
    "wof:name":"Samara",
    "wof:placetype":"locality"
},
  "geometry": {"coordinates":[38.56667,51.88333],"type":"Point"}
}