{
  "type": "Feature",
  "properties": {
    "gn:admin1_code":"47",
    "gn:asciiname":"Shikhovo",
    "gn:country_code":"RU",
    "gn:dem":226,
    "gn:feature_class":"P",
    "gn:feature_code":"PPL",
    "gn:name":"Shikhovo",
    "gn:population":0,
    "gn:timezone":"Europe/Moscow",
    "iso:country":"RU",
    "name:rus_x_preferred":[
        "\u0428\u0438\u0445\u043e\u0432\u043e"
    ],
    "name:ukr_x_preferred":[
        "\u0428\u0438\u0445\u043e\u0432\u043e"
    ],
    "name:und_x_variant":[
        "\u0428\u0438\u0445\u043e\u0432\u043e"
    ],
    "wof:name":"Shikhovo",
    "wof:placetype":"locality"
},
  "geometry": {"coordinates":[37.28333,56.18333000000001],"type":"Point"}
}