{
  "type": "Feature",
  "properties": {
    "gn:admin1_code":"33.0",
    "gn:asciiname":"Smolikha",
    "gn:country_code":"RU",
    "gn:dem":117,
    "gn:feature_class":"P",
    "gn:feature_code":"PPL",
    "gn:name":"Smolikha",
    "gn:population":0,
    "gn:timezone":"Europe/Kirov",
    "iso:country":"RU",
    "name:rus_x_preferred":[
        "\u0421\u043c\u043e\u043b\u0438\u0445\u0430"
    ],
    "name:und_x_variant":[
        "\u0421\u043c\u043e\u043b\u0438\u0445\u0430"
    ],
    "wof:name":"Smolikha",
    "wof:placetype":"locality"
},
  "geometry": {"coordinates":[48.88952000000001,58.36288],"type":"Point"}
}