{
  "type": "Feature",
  "properties": {
    "gn:admin1_code":"90.0",
    "gn:asciiname":"Markovina",
    "gn:country_code":"RU",
    "gn:dem":160,
    "gn:feature_class":"P",
    "gn:feature_code":"PPL",
    "gn:name":"Markovina",
    "gn:population":0,
    "gn:timezone":"Asia/Yekaterinburg",
    "iso:country":"RU",
    "name:rus_x_preferred":[
        "\u041c\u0430\u0440\u043a\u043e\u0432\u0438\u043d\u0430"
    ],
    "wof:name":"Markovina",
    "wof:placetype":"locality"
},
  "geometry": {"coordinates":[55.0218,58.33],"type":"Point"}
}