{
  "type": "Feature",
  "properties": {
    "gn:admin1_code":"81",
    "gn:asciiname":"Prolomikha",
    "gn:country_code":"RU",
    "gn:dem":185,
    "gn:feature_class":"P",
    "gn:feature_code":"PPL",
    "gn:name":"Prolomikha",
    "gn:population":0,
    "gn:timezone":"Europe/Ulyanovsk",
    "iso:country":"RU",
    "name:eng_x_preferred":[
        "Prolomikha"
    ],
    "name:nor_x_preferred":[
        "Prolomikha"
    ],
    "name:rus_x_preferred":[
        "\u041f\u0440\u043e\u043b\u043e\u043c\u0438\u0445\u0430"
    ],
    "name:und_x_variant":[
        "\u041f\u0440\u043e\u043b\u043e\u043c\u0438\u0445\u0430",
        "Prolomikha"
    ],
    "wof:name":"Prolomikha",
    "wof:placetype":"locality"
},
  "geometry": {"coordinates":[46.42654,54.09753000000001],"type":"Point"}
}