{
  "type": "Feature",
  "properties": {
    "gn:admin1_code":"13",
    "gn:asciiname":"Klyuchi",
    "gn:country_code":"RU",
    "gn:dem":271,
    "gn:feature_class":"P",
    "gn:feature_code":"PPL",
    "gn:name":"Klyuchi",
    "gn:population":0,
    "gn:timezone":"Asia/Yekaterinburg",
    "iso:country":"RU",
    "name:ara_x_preferred":[
        "\u0643\u0644\u064a\u0648\u062a\u0634\u064a"
    ],
    "name:bel_x_preferred":[
        "\u041a\u043b\u044e\u0447\u044b"
    ],
    "name:ben_x_preferred":[
        "\u0995\u09cd\u09b2\u0987\u0989\u099a\u09bf"
    ],
    "name:ceb_x_preferred":[
        "\u041a\u043b\u044e\u0447\u0438"
    ],
    "name:ces_x_preferred":[
        "Klju\u010di"
    ],
    "name:deu_x_preferred":[
        "Kljutschi"
    ],
    "name:fas_x_preferred":[
        "\u06a9\u0644\u06cc\u0648\u0686\u06cc"
    ],
    "name:heb_x_preferred":[
        "\u05e7\u05dc\u05d9\u05d5\u05e6'\u05d9"
    ],
    "name:hin_x_preferred":[
        "\u0915\u094d\u0932\u094d\u092f\u0942\u091a\u0940"
    ],
    "name:hun_x_preferred":[
        "Klyuchi"
    ],
    "name:ind_x_preferred":[
        "Klyuchi"
    ],
    "name:kor_x_preferred":[
        "\ud074\ub958\uce58"
    ],
    "name:por_x_preferred":[
        "Klyuchi"
    ],
    "name:rus_x_preferred":[
        "\u041a\u043b\u044e\u0447\u0438"
    ],
    "name:swe_x_preferred":[
        "Klyutji"
    ],
    "name:tat_x_preferred":[
        "\u041a\u043b\u044e\u0447\u0438"
    ],
    "name:tur_x_preferred":[
        "Klyuchi"
    ],
    "name:ukr_x_preferred":[
        "\u041a\u043b\u044e\u0447\u0456"
    ],
    "name:und_x_variant":[
        "Klyuchevskoy",
        "Klyuchi"
    ],
    "name:urd_x_preferred":[
        "\u06a9\u0644\u06cc\u0648\u0686\u06cc"
    ],
    "name:vie_x_preferred":[
        "Klyuchi"
    ],
    "name:zho_cn_x_preferred":[
        "\u514b\u67f3\u5947"
    ],
    "name:zho_tw_x_preferred":[
        "\u514b\u67f3\u5947"
    ],
    "wof:name":"Klyuchi",
    "wof:placetype":"locality"
},
  "geometry": {"coordinates":[60.7675,55.0143],"type":"Point"}
}