{
  "type": "Feature",
  "properties": {
    "gn:admin1_code":"41",
    "gn:asciiname":"Krestishche",
    "gn:country_code":"RU",
    "gn:dem":190,
    "gn:feature_class":"P",
    "gn:feature_code":"PPL",
    "gn:name":"Krestishche",
    "gn:population":0,
    "gn:timezone":"Europe/Moscow",
    "iso:country":"RU",
    "name:eng_x_preferred":[
        "Nizhneye Krestishche"
    ],
    "name:nor_x_preferred":[
        "Krestisjtsje"
    ],
    "name:rus_x_preferred":[
        "\u041a\u0440\u0435\u0441\u0442\u0438\u0449\u0435"
    ],
    "wof:name":"Krestishche",
    "wof:placetype":"locality"
},
  "geometry": {"coordinates":[37.5685,51.7623],"type":"Point"}
}