{
  "type": "Feature",
  "properties": {
    "gn:admin1_code":"41",
    "gn:asciiname":"Rzhavchik",
    "gn:country_code":"RU",
    "gn:dem":211,
    "gn:feature_class":"P",
    "gn:feature_code":"PPL",
    "gn:name":"Rzhavchik",
    "gn:population":0,
    "gn:timezone":"Europe/Moscow",
    "iso:country":"RU",
    "name:rus_x_preferred":[
        "\u0420\u0436\u0430\u0432\u0447\u0438\u043a"
    ],
    "wof:name":"Rzhavchik",
    "wof:placetype":"locality"
},
  "geometry": {"coordinates":[36.63936,51.24396],"type":"Point"}
}