{
  "type": "Feature",
  "properties": {
    "gn:admin1_code":"16",
    "gn:asciiname":"Sormovo",
    "gn:country_code":"RU",
    "gn:dem":82,
    "gn:feature_class":"P",
    "gn:feature_code":"PPL",
    "gn:name":"Sormovo",
    "gn:population":0,
    "gn:timezone":"Europe/Moscow",
    "iso:country":"RU",
    "name:rus_x_preferred":[
        "\u0421\u043e\u0440\u043c\u043e\u0432\u043e"
    ],
    "wof:name":"Sormovo",
    "wof:placetype":"locality"
},
  "geometry": {"coordinates":[46.1939,55.6239],"type":"Point"}
}