{
  "type": "Feature",
  "properties": {
    "gn:admin1_code":"92",
    "gn:asciiname":"Karaga",
    "gn:country_code":"RU",
    "gn:dem":4,
    "gn:feature_class":"P",
    "gn:feature_code":"PPL",
    "gn:name":"Karaga",
    "gn:population":0,
    "gn:timezone":"Asia/Kamchatka",
    "iso:country":"RU",
    "name:ceb_x_preferred":[
        "Karaga"
    ],
    "name:eng_x_preferred":[
        "Karaga"
    ],
    "name:fra_x_preferred":[
        "Karaga"
    ],
    "name:nor_x_preferred":[
        "Karaga"
    ],
    "name:rus_x_preferred":[
        "\u041a\u0430\u0440\u0430\u0433\u0430"
    ],
    "name:swe_x_preferred":[
        "Karaga"
    ],
    "name:und_x_variant":[
        "Karaginsk"
    ],
    "wof:name":"Karaga",
    "wof:placetype":"locality"
},
  "geometry": {"coordinates":[163.12065000000001,59.10963],"type":"Point"}
}