{
  "type": "Feature",
  "properties": {
    "gn:admin1_code":"91.0",
    "gn:asciiname":"Radiostantsiya",
    "gn:country_code":"RU",
    "gn:dem":338,
    "gn:feature_class":"P",
    "gn:feature_code":"PPL",
    "gn:name":"Radiostantsiya",
    "gn:population":0,
    "gn:timezone":"Asia/Krasnoyarsk",
    "iso:country":"RU",
    "name:rus_x_preferred":[
        "\u0420\u0430\u0434\u0438\u043e\u0441\u0442\u0430\u043d\u0446\u0438\u044f"
    ],
    "wof:name":"Radiostantsiya",
    "wof:placetype":"locality"
},
  "geometry": {"coordinates":[92.5278,56.0654],"type":"Point"}
}