{
  "type": "Feature",
  "properties": {
    "gn:admin1_code":"54",
    "gn:asciiname":"Rassokhino",
    "gn:country_code":"RU",
    "gn:dem":86,
    "gn:feature_class":"P",
    "gn:feature_code":"PPL",
    "gn:name":"Rassokhino",
    "gn:population":0,
    "gn:timezone":"Asia/Omsk",
    "iso:country":"RU",
    "name:rus_x_preferred":[
        "\u0420\u0430\u0441\u0441\u043e\u0445\u0438\u043d\u043e"
    ],
    "wof:name":"Rassokhino",
    "wof:placetype":"locality"
},
  "geometry": {"coordinates":[74.62009999999999,54.2403],"type":"Point"}
}