{
  "type": "Feature",
  "properties": {
    "gn:admin1_code":"55",
    "gn:asciiname":"Nizhniy Bul'yar",
    "gn:country_code":"RU",
    "gn:dem":373,
    "gn:feature_class":"P",
    "gn:feature_code":"PPL",
    "gn:name":"Nizhniy Bul\u2019yar",
    "gn:population":0,
    "gn:timezone":"Asia/Yekaterinburg",
    "iso:country":"RU",
    "name:rus_x_preferred":[
        "\u041d\u0438\u0436\u043d\u0438\u0439 \u0411\u0443\u043b\u044c\u044f\u0440"
    ],
    "name:und_x_variant":[
        "Karaly-Nazargulovo",
        "Nizhniy Bul\u2019yar",
        "\u041d\u0438\u0436\u043d\u0438\u0439 \u0411\u0443\u043b\u044c\u044f\u0440"
    ],
    "wof:name":"Nizhniy Bul'yar",
    "wof:placetype":"locality"
},
  "geometry": {"coordinates":[57.61666999999999,51.73333],"type":"Point"}
}