{
  "type": "Feature",
  "properties": {
    "gn:admin1_code":"90.0",
    "gn:asciiname":"Antropova",
    "gn:country_code":"RU",
    "gn:dem":136,
    "gn:feature_class":"P",
    "gn:feature_code":"PPL",
    "gn:name":"Antropova",
    "gn:population":0,
    "gn:timezone":"Asia/Yekaterinburg",
    "iso:country":"RU",
    "name:rus_x_preferred":[
        "\u0410\u043d\u0442\u0440\u043e\u043f\u043e\u0432\u0430"
    ],
    "wof:name":"Antropova",
    "wof:placetype":"locality"
},
  "geometry": {"coordinates":[54.7203,59.1428],"type":"Point"}
}