{
  "type": "Feature",
  "properties": {
    "gn:admin1_code":"90.0",
    "gn:asciiname":"Russkiy Lem",
    "gn:country_code":"RU",
    "gn:dem":187,
    "gn:feature_class":"P",
    "gn:feature_code":"PPL",
    "gn:name":"Russkiy Lem",
    "gn:population":0,
    "gn:timezone":"Europe/Samara",
    "iso:country":"RU",
    "name:rus_x_preferred":[
        "\u0420\u0443\u0441\u0441\u043a\u0438\u0439 \u041b\u0435\u043c"
    ],
    "wof:name":"Russkiy Lem",
    "wof:placetype":"locality"
},
  "geometry": {"coordinates":[54.06994,57.65434000000001],"type":"Point"}
}