{
  "type": "Feature",
  "properties": {
    "gn:admin1_code":"72",
    "gn:asciiname":"Konoplyanskiy",
    "gn:country_code":"RU",
    "gn:dem":165,
    "gn:feature_class":"P",
    "gn:feature_code":"PPL",
    "gn:name":"Konoplyanskiy",
    "gn:population":0,
    "gn:timezone":"Europe/Moscow",
    "iso:country":"RU",
    "name:rus_x_preferred":[
        "\u041a\u043e\u043d\u043e\u043f\u043b\u044f\u043d\u0441\u043a\u0438\u0439"
    ],
    "name:und_x_variant":[
        "\u041a\u043e\u043d\u043e\u043f\u043b\u044f\u043d\u0441\u043a\u0438\u0439"
    ],
    "wof:name":"Konoplyanskiy",
    "wof:placetype":"locality"
},
  "geometry": {"coordinates":[42.7925,52.315],"type":"Point"}
}