{
  "type": "Feature",
  "properties": {
    "gn:admin1_code":"37",
    "gn:asciiname":"Vtoroy Starikovskiy",
    "gn:country_code":"RU",
    "gn:dem":186,
    "gn:feature_class":"P",
    "gn:feature_code":"PPL",
    "gn:name":"Vtoroy Starikovskiy",
    "gn:population":0,
    "gn:timezone":"Europe/Moscow",
    "iso:country":"RU",
    "name:rus_x_preferred":[
        "\u0412\u0442\u043e\u0440\u043e\u0439 \u0421\u0442\u0430\u0440\u0438\u043a\u043e\u0432\u0441\u043a\u0438\u0439"
    ],
    "name:und_x_variant":[
        "\u0412\u0442\u043e\u0440\u043e\u0439 \u0421\u0442\u0430\u0440\u0438\u043a\u043e\u0432\u0441\u043a\u0438\u0439"
    ],
    "wof:name":"Vtoroy Starikovskiy",
    "wof:placetype":"locality"
},
  "geometry": {"coordinates":[46.2326,59.0009],"type":"Point"}
}