{
  "type": "Feature",
  "properties": {
    "gn:admin1_code":"22",
    "gn:asciiname":"Opytnoye",
    "gn:country_code":"RU",
    "gn:dem":211,
    "gn:feature_class":"P",
    "gn:feature_code":"PPL",
    "gn:name":"Opytnoye",
    "gn:population":0,
    "gn:timezone":"Europe/Moscow",
    "iso:country":"RU",
    "name:rus_x_preferred":[
        "\u041e\u043f\u044b\u0442\u043d\u043e\u0435"
    ],
    "wof:name":"Opytnoye",
    "wof:placetype":"locality"
},
  "geometry": {"coordinates":[44.13664,43.62979],"type":"Point"}
}