{
  "type": "Feature",
  "properties": {
    "gn:admin1_code":"56",
    "gn:asciiname":"Borodinki",
    "gn:country_code":"RU",
    "gn:dem":224,
    "gn:feature_class":"P",
    "gn:feature_code":"PPL",
    "gn:name":"Borodinki",
    "gn:population":0,
    "gn:timezone":"Europe/Moscow",
    "iso:country":"RU",
    "name:rus_x_preferred":[
        "\u0411\u043e\u0440\u043e\u0434\u0438\u043d\u043a\u0438"
    ],
    "name:und_x_variant":[
        "\u0411\u043e\u0440\u043e\u0434\u0438\u043d\u043a\u0438"
    ],
    "wof:name":"Borodinki",
    "wof:placetype":"locality"
},
  "geometry": {"coordinates":[35.3412,52.6344],"type":"Point"}
}