{
  "type": "Feature",
  "properties": {
    "gn:admin1_code":"9",
    "gn:asciiname":"Nemtsevo",
    "gn:country_code":"RU",
    "gn:dem":213,
    "gn:feature_class":"P",
    "gn:feature_code":"PPL",
    "gn:name":"Nemtsevo",
    "gn:population":0,
    "gn:timezone":"Europe/Moscow",
    "iso:country":"RU",
    "name:eng_x_preferred":[
        "Nemtsev"
    ],
    "name:nor_x_preferred":[
        "Nemtsev"
    ],
    "name:rus_x_preferred":[
        "\u041d\u0435\u043c\u0446\u0435\u0432\u043e"
    ],
    "name:und_x_variant":[
        "Nemtsev",
        "Nemtsevo"
    ],
    "wof:name":"Nemtsevo",
    "wof:placetype":"locality"
},
  "geometry": {"coordinates":[37.68558,50.59903],"type":"Point"}
}