{
  "type": "Feature",
  "properties": {
    "gn:admin1_code":"85",
    "gn:asciiname":"Zhukovo",
    "gn:country_code":"RU",
    "gn:dem":122,
    "gn:feature_class":"P",
    "gn:feature_code":"PPL",
    "gn:name":"Zhukovo",
    "gn:population":0,
    "gn:timezone":"Europe/Moscow",
    "iso:country":"RU",
    "name:eng_x_preferred":[
        "Zhukovo"
    ],
    "name:nor_x_preferred":[
        "Zjukovo"
    ],
    "name:rus_x_preferred":[
        "\u0416\u0443\u043a\u043e\u0432\u043e"
    ],
    "wof:name":"Zhukovo",
    "wof:placetype":"locality"
},
  "geometry": {"coordinates":[36.7267,58.7762],"type":"Point"}
}