{
  "type": "Feature",
  "properties": {
    "gn:admin1_code":"10",
    "gn:asciiname":"Gostilovka",
    "gn:country_code":"RU",
    "gn:dem":158,
    "gn:feature_class":"P",
    "gn:feature_code":"PPL",
    "gn:name":"Gostilovka",
    "gn:population":0,
    "gn:timezone":"Europe/Moscow",
    "iso:country":"RU",
    "name:rus_x_preferred":[
        "\u0413\u043e\u0441\u0442\u0438\u043b\u043e\u0432\u043a\u0430"
    ],
    "wof:name":"Gostilovka",
    "wof:placetype":"locality"
},
  "geometry": {"coordinates":[33.69035,53.48421],"type":"Point"}
}