{
  "type": "Feature",
  "properties": {
    "gn:admin1_code":"33.0",
    "gn:asciiname":"Spirintsy",
    "gn:country_code":"RU",
    "gn:dem":257,
    "gn:feature_class":"P",
    "gn:feature_code":"PPL",
    "gn:name":"Spirintsy",
    "gn:population":0,
    "gn:timezone":"Europe/Kirov",
    "iso:country":"RU",
    "name:rus_x_preferred":[
        "\u0421\u043f\u0438\u0440\u0438\u043d\u0446\u044b"
    ],
    "wof:name":"Spirintsy",
    "wof:placetype":"locality"
},
  "geometry": {"coordinates":[52.5836,58.5405],"type":"Point"}
}