{
  "type": "Feature",
  "properties": {
    "gn:admin1_code":"73",
    "gn:asciiname":"Naratly",
    "gn:country_code":"RU",
    "gn:dem":221,
    "gn:feature_class":"P",
    "gn:feature_code":"PPL",
    "gn:name":"Naratly",
    "gn:population":0,
    "gn:timezone":"Europe/Moscow",
    "iso:country":"RU",
    "name:rus_x_preferred":[
        "\u041d\u0430\u0440\u0430\u0442\u043b\u044b"
    ],
    "wof:name":"Naratly",
    "wof:placetype":"locality"
},
  "geometry": {"coordinates":[52.5113,55.0439],"type":"Point"}
}