{
  "type": "Feature",
  "properties": {
    "gn:admin1_code":"8",
    "gn:asciiname":"Taetuba",
    "gn:country_code":"RU",
    "gn:dem":163,
    "gn:feature_class":"P",
    "gn:feature_code":"PPL",
    "gn:name":"Taetuba",
    "gn:population":0,
    "gn:timezone":"Asia/Yekaterinburg",
    "iso:country":"RU",
    "name:rus_x_preferred":[
        "\u0422\u0430\u044d\u0442\u0443\u0431\u0430"
    ],
    "name:und_x_variant":[
        "Taz-Guba"
    ],
    "wof:name":"Taetuba",
    "wof:placetype":"locality"
},
  "geometry": {"coordinates":[55.6328,56.0232],"type":"Point"}
}