{
  "type": "Feature",
  "properties": {
    "gn:admin1_code":"77",
    "gn:asciiname":"Korenevka",
    "gn:country_code":"RU",
    "gn:dem":176,
    "gn:feature_class":"P",
    "gn:feature_code":"PPL",
    "gn:name":"Korenevka",
    "gn:population":0,
    "gn:timezone":"Europe/Moscow",
    "iso:country":"RU",
    "name:rus_x_preferred":[
        "\u041a\u043e\u0440\u0435\u043d\u0435\u0432\u043a\u0430"
    ],
    "name:und_x_variant":[
        "\u041a\u043e\u0440\u0435\u043d\u0435\u0432\u043a\u0430"
    ],
    "wof:name":"Korenevka",
    "wof:placetype":"locality"
},
  "geometry": {"coordinates":[32.82472,56.05167],"type":"Point"}
}