{
  "type": "Feature",
  "properties": {
    "gn:admin1_code":"81",
    "gn:asciiname":"Ust'-Kulatka",
    "gn:country_code":"RU",
    "gn:dem":74,
    "gn:feature_class":"P",
    "gn:feature_code":"PPL",
    "gn:name":"Ust\u2019-Kulatka",
    "gn:population":0,
    "gn:timezone":"Europe/Ulyanovsk",
    "iso:country":"RU",
    "wof:name":"Ust'-Kulatka",
    "wof:placetype":"locality"
},
  "geometry": {"coordinates":[47.75494000000001,52.61346999999999],"type":"Point"}
}