{
  "type": "Feature",
  "properties": {
    "gn:admin1_code":"88",
    "gn:asciiname":"Chaylovo",
    "gn:country_code":"RU",
    "gn:dem":124,
    "gn:feature_class":"P",
    "gn:feature_code":"PPL",
    "gn:name":"Chaylovo",
    "gn:population":0,
    "gn:timezone":"Europe/Moscow",
    "iso:country":"RU",
    "name:rus_x_preferred":[
        "\u0427\u0430\u0439\u043b\u043e\u0432\u043e"
    ],
    "wof:name":"Chaylovo",
    "wof:placetype":"locality"
},
  "geometry": {"coordinates":[38.6145,57.8859],"type":"Point"}
}