{
  "type": "Feature",
  "properties": {
    "gn:admin1_code":"60",
    "gn:asciiname":"Lebedevo",
    "gn:country_code":"RU",
    "gn:dem":206,
    "gn:feature_class":"P",
    "gn:feature_code":"PPL",
    "gn:name":"Lebedevo",
    "gn:population":0,
    "gn:timezone":"Europe/Moscow",
    "iso:country":"RU",
    "name:rus_x_preferred":[
        "\u041b\u0435\u0431\u0435\u0434\u0435\u0432\u043e"
    ],
    "name:und_x_variant":[
        "\u041b\u0435\u0431\u0435\u0434\u0435\u0432\u043e"
    ],
    "wof:name":"Lebedevo",
    "wof:placetype":"locality"
},
  "geometry": {"coordinates":[29.9206,56.5858],"type":"Point"}
}