{
  "type": "Feature",
  "properties": {
    "gn:admin1_code":"76",
    "gn:asciiname":"Poloshkova",
    "gn:country_code":"RU",
    "gn:dem":206,
    "gn:feature_class":"P",
    "gn:feature_code":"PPL",
    "gn:name":"Poloshkova",
    "gn:population":0,
    "gn:timezone":"Europe/Moscow",
    "iso:country":"RU",
    "name:rus_x_preferred":[
        "\u041f\u043e\u043b\u043e\u0448\u043a\u043e\u0432\u0430"
    ],
    "name:und_x_variant":[
        "Poloshkovo"
    ],
    "wof:name":"Poloshkova",
    "wof:placetype":"locality"
},
  "geometry": {"coordinates":[38.18711,54.55015],"type":"Point"}
}