{
  "type": "Feature",
  "properties": {
    "gn:admin1_code":"88",
    "gn:asciiname":"Khlestovo",
    "gn:country_code":"RU",
    "gn:dem":103,
    "gn:feature_class":"P",
    "gn:feature_code":"PPL",
    "gn:name":"Khl\u00ebstovo",
    "gn:population":0,
    "gn:timezone":"Europe/Moscow",
    "iso:country":"RU",
    "name:rus_x_preferred":[
        "\u0425\u043b\u0451\u0441\u0442\u043e\u0432\u043e"
    ],
    "name:und_x_variant":[
        "Khl\u00ebstovo",
        "\u0425\u043b\u0451\u0441\u0442\u043e\u0432\u043e"
    ],
    "wof:name":"Khlestovo",
    "wof:placetype":"locality"
},
  "geometry": {"coordinates":[40.7036,58.07903],"type":"Point"}
}