{
  "type": "Feature",
  "properties": {
    "gn:admin1_code":"55",
    "gn:asciiname":"Tanalyk",
    "gn:country_code":"RU",
    "gn:dem":263,
    "gn:feature_class":"P",
    "gn:feature_code":"PPL",
    "gn:name":"Tanalyk",
    "gn:population":0,
    "gn:timezone":"Asia/Yekaterinburg",
    "iso:country":"RU",
    "name:eng_x_preferred":[
        "Tanalyk"
    ],
    "name:nor_x_preferred":[
        "Tanalyk"
    ],
    "name:rus_x_preferred":[
        "\u0422\u0430\u043d\u0430\u043b\u044b\u043a"
    ],
    "name:und_x_variant":[
        "Tanalykskiy"
    ],
    "wof:name":"Tanalyk",
    "wof:placetype":"locality"
},
  "geometry": {"coordinates":[58.9425,52.03417],"type":"Point"}
}