{
  "type": "Feature",
  "properties": {
    "gn:admin1_code":"51",
    "gn:asciiname":"Maresevo",
    "gn:country_code":"RU",
    "gn:dem":137,
    "gn:feature_class":"P",
    "gn:feature_code":"PPL",
    "gn:name":"Maresevo",
    "gn:population":0,
    "gn:timezone":"Europe/Moscow",
    "iso:country":"RU",
    "name:rus_x_preferred":[
        "\u041c\u0430\u0440\u0435\u0441\u0435\u0432\u043e"
    ],
    "wof:name":"Maresevo",
    "wof:placetype":"locality"
},
  "geometry": {"coordinates":[45.59083,55.25181],"type":"Point"}
}