{
  "type": "Feature",
  "properties": {
    "gn:admin1_code":"28",
    "gn:asciiname":"Liyete",
    "gn:cc2":"RU",
    "gn:country_code":"RU",
    "gn:dem":151,
    "gn:feature_class":"P",
    "gn:feature_code":"PPL",
    "gn:name":"Liyete",
    "gn:population":0,
    "gn:timezone":"Europe/Moscow",
    "iso:country":"RU",
    "name:fin_x_preferred":[
        "Lietteinkyl\u00e4"
    ],
    "name:rus_x_preferred":[
        "\u041b\u0438\u0435\u0442\u0435"
    ],
    "name:und_x_variant":[
        "Liyetteinkyulya",
        "Liete",
        "Liyete",
        "\u041b\u0438\u0435\u0442\u0435"
    ],
    "wof:name":"Liyete",
    "wof:placetype":"locality"
},
  "geometry": {"coordinates":[32.32418,62.10613000000001],"type":"Point"}
}