{
  "type": "Feature",
  "properties": {
    "gn:admin1_code":"45",
    "gn:asciiname":"Shekmino Pervoye",
    "gn:country_code":"RU",
    "gn:dem":139,
    "gn:feature_class":"P",
    "gn:feature_code":"PPL",
    "gn:name":"Shekmino Pervoye",
    "gn:population":0,
    "gn:timezone":"Europe/Moscow",
    "iso:country":"RU",
    "name:rus_x_preferred":[
        "\u0428\u0435\u043a\u043c\u0438\u043d\u043e \u041f\u0435\u0440\u0432\u043e\u0435"
    ],
    "name:und_x_variant":[
        "\u0428\u0435\u043a\u043c\u0438\u043d\u043e \u041f\u0435\u0440\u0432\u043e\u0435"
    ],
    "wof:name":"Shekmino Pervoye",
    "wof:placetype":"locality"
},
  "geometry": {"coordinates":[46.2428,56.1885],"type":"Point"}
}