{
  "type": "Feature",
  "properties": {
    "gn:admin1_code":"91",
    "gn:asciiname":"Novokargino",
    "gn:country_code":"RU",
    "gn:dem":78,
    "gn:feature_class":"P",
    "gn:feature_code":"PPL",
    "gn:name":"Novokargino",
    "gn:population":0,
    "gn:timezone":"Asia/Krasnoyarsk",
    "iso:country":"RU",
    "name:rus_x_preferred":[
        "\u041d\u043e\u0432\u043e\u043a\u0430\u0440\u0433\u0438\u043d\u043e"
    ],
    "wof:name":"Novokargino",
    "wof:placetype":"locality"
},
  "geometry": {"coordinates":[92.15000000000001,58.45],"type":"Point"}
}