{
  "type": "Feature",
  "properties": {
    "gn:admin1_code":"8.0",
    "gn:asciiname":"Amirovo",
    "gn:country_code":"RU",
    "gn:dem":153,
    "gn:feature_class":"P",
    "gn:feature_code":"PPL",
    "gn:name":"Amirovo",
    "gn:population":0,
    "gn:timezone":"Asia/Yekaterinburg",
    "iso:country":"RU",
    "name:aze_x_preferred":[
        "\u018fmir"
    ],
    "name:bak_x_preferred":[
        "\u04d8\u043c\u0438\u0440"
    ],
    "name:che_x_preferred":[
        "\u0410\u043c\u0438\u0440\u043e\u0432\u043e"
    ],
    "name:eng_x_preferred":[
        "Amirovo"
    ],
    "name:hye_x_preferred":[
        "\u0531\u0574\u056b\u0580\u0578\u057e\u0578"
    ],
    "name:kat_x_preferred":[
        "\u10d0\u10db\u10d8\u10e0\u10dd\u10d5\u10dd"
    ],
    "name:kaz_x_preferred":[
        "\u0410\u043c\u0438\u0440"
    ],
    "name:kir_x_preferred":[
        "\u0410\u043c\u0438\u0440"
    ],
    "name:nor_x_preferred":[
        "Amirovo"
    ],
    "name:rus_x_preferred":[
        "\u0410\u043c\u0438\u0440\u043e\u0432\u043e"
    ],
    "name:tat_x_preferred":[
        "\u04d8\u043c\u0438\u0440"
    ],
    "name:und_x_variant":[
        "Novoamirovo"
    ],
    "wof:name":"Amirovo",
    "wof:placetype":"locality"
},
  "geometry": {"coordinates":[54.55,54.68333000000001],"type":"Point"}
}