{
  "type": "Feature",
  "properties": {
    "gn:admin1_code":"8.0",
    "gn:asciiname":"Amirovo",
    "gn:country_code":"RU",
    "gn:dem":153,
    "gn:feature_class":"P",
    "gn:feature_code":"PPL",
    "gn:name":"Amirovo",
    "gn:population":0,
    "gn:timezone":"Asia/Yekaterinburg",
    "iso:country":"RU",
    "name:eng_x_preferred":[
        "Amirovo"
    ],
    "name:nor_x_preferred":[
        "Amirovo"
    ],
    "name:rus_x_preferred":[
        "\u0410\u043c\u0438\u0440\u043e\u0432\u043e"
    ],
    "name:und_x_variant":[
        "\u0410\u043c\u0438\u0440\u043e\u0432\u043e",
        "Amirovo",
        "Novoamirovo"
    ],
    "wof:name":"Amirovo",
    "wof:placetype":"locality"
},
  "geometry": {"coordinates":[54.55,54.68333000000001],"type":"Point"}
}