{
  "type": "Feature",
  "properties": {
    "gn:admin1_code":"17.0",
    "gn:admin2_code":"Charodinskiy Rayon",
    "gn:asciiname":"Gochob",
    "gn:country_code":"RU",
    "gn:dem":2020,
    "gn:feature_class":"P",
    "gn:feature_code":"PPL",
    "gn:name":"Gochob",
    "gn:population":0,
    "gn:timezone":"Europe/Moscow",
    "iso:country":"RU",
    "name:eng_x_preferred":[
        "Gochob"
    ],
    "name:nor_x_preferred":[
        "Gotsjob"
    ],
    "name:rus_x_preferred":[
        "\u0413\u043e\u0447\u043e\u0431"
    ],
    "name:und_x_variant":[
        "Gochoo"
    ],
    "wof:name":"Gochob",
    "wof:placetype":"locality"
},
  "geometry": {"coordinates":[46.6643,42.2379],"type":"Point"}
}