{
  "type": "Feature",
  "properties": {
    "gn:admin1_code":"28",
    "gn:asciiname":"Semchozero",
    "gn:country_code":"RU",
    "gn:dem":168,
    "gn:feature_class":"P",
    "gn:feature_code":"PPL",
    "gn:name":"Semchozero",
    "gn:population":0,
    "gn:timezone":"Europe/Moscow",
    "iso:country":"RU",
    "name:eng_x_preferred":[
        "Semchozero"
    ],
    "name:fin_x_preferred":[
        "Semsj\u00e4rvi"
    ],
    "name:nor_x_preferred":[
        "Semtsjeozero"
    ],
    "name:rus_x_preferred":[
        "\u0421\u0435\u043c\u0447\u0435\u043e\u0437\u0435\u0440\u043e"
    ],
    "name:rus_x_variant":[
        "\u0421\u0435\u043c\u0447\u043e\u0437\u0435\u0440\u043e"
    ],
    "name:und_x_variant":[
        "Pobeda",
        "Semchezero"
    ],
    "wof:name":"Semchozero",
    "wof:placetype":"locality"
},
  "geometry": {"coordinates":[33.62941,62.93574],"type":"Point"}
}