{
  "type": "Feature",
  "properties": {
    "gn:admin1_code":"55",
    "gn:asciiname":"Yekaterinovka",
    "gn:country_code":"RU",
    "gn:dem":136,
    "gn:feature_class":"P",
    "gn:feature_code":"PPL",
    "gn:name":"Yekaterinovka",
    "gn:population":0,
    "gn:timezone":"Asia/Yekaterinburg",
    "iso:country":"RU",
    "name:eng_x_preferred":[
        "Yekaterinovka"
    ],
    "name:nor_x_preferred":[
        "Jekaterinovka"
    ],
    "name:rus_x_preferred":[
        "\u0415\u043a\u0430\u0442\u0435\u0440\u0438\u043d\u043e\u0432\u043a\u0430"
    ],
    "wof:name":"Yekaterinovka",
    "wof:placetype":"locality"
},
  "geometry": {"coordinates":[52.2304,53.2693],"type":"Point"}
}