{
  "type": "Feature",
  "properties": {
    "gn:admin1_code":"8",
    "gn:asciiname":"Kashkarovo",
    "gn:country_code":"RU",
    "gn:dem":457,
    "gn:feature_class":"P",
    "gn:feature_code":"PPL",
    "gn:name":"Kashkarovo",
    "gn:population":0,
    "gn:timezone":"Asia/Yekaterinburg",
    "iso:country":"RU",
    "name:bak_x_preferred":[
        "\u04a0\u0430\u0448\u04a1\u0430\u0440"
    ],
    "name:che_x_preferred":[
        "\u041a\u0430\u0448\u043a\u0430\u0440\u043e\u0432\u043e"
    ],
    "name:eng_x_preferred":[
        "Kashkarovo"
    ],
    "name:hye_x_preferred":[
        "\u053f\u0561\u0577\u056f\u0561\u0580\u0578\u057e\u0578"
    ],
    "name:kat_x_preferred":[
        "\u10d9\u10d0\u10e8\u10d9\u10d0\u10e0\u10dd\u10d5\u10dd"
    ],
    "name:kaz_x_preferred":[
        "\u041a\u0430\u0448\u043a\u0430\u0440"
    ],
    "name:kir_x_preferred":[
        "\u041a\u0430\u0448\u043a\u0430\u0440"
    ],
    "name:nor_x_preferred":[
        "Kasjkarovo"
    ],
    "name:rus_x_preferred":[
        "\u041a\u0430\u0448\u043a\u0430\u0440\u043e\u0432\u043e"
    ],
    "name:tat_x_preferred":[
        "\u041a\u0430\u0448\u043a\u0430\u0440"
    ],
    "name:ukr_x_preferred":[
        "\u041a\u0430\u0448\u043a\u0430\u0440\u043e\u0432\u043e"
    ],
    "name:und_x_variant":[
        "\u041a\u0430\u0448\u043a\u0430\u0440\u043e\u0432\u043e",
        "Kashkarovo"
    ],
    "wof:name":"Kashkarovo",
    "wof:placetype":"locality"
},
  "geometry": {"coordinates":[57.765,52.3404],"type":"Point"}
}