{
  "type": "Feature",
  "properties": {
    "gn:admin1_code":"85",
    "gn:asciiname":"Serkovo",
    "gn:country_code":"RU",
    "gn:dem":163,
    "gn:feature_class":"P",
    "gn:feature_code":"PPL",
    "gn:name":"Serkovo",
    "gn:population":0,
    "gn:timezone":"Europe/Moscow",
    "iso:country":"RU",
    "name:rus_x_preferred":[
        "\u0421\u0435\u0440\u043a\u043e\u0432\u043e"
    ],
    "wof:name":"Serkovo",
    "wof:placetype":"locality"
},
  "geometry": {"coordinates":[35.9867,59.6026],"type":"Point"}
}