{
  "type": "Feature",
  "properties": {
    "gn:admin1_code":"33",
    "gn:asciiname":"Yul'yal",
    "gn:country_code":"RU",
    "gn:dem":116,
    "gn:feature_class":"P",
    "gn:feature_code":"PPL",
    "gn:name":"Yul\u2019yal",
    "gn:population":0,
    "gn:timezone":"Europe/Kirov",
    "iso:country":"RU",
    "name:rus_x_preferred":[
        "\u042e\u043b\u044c\u044f\u043b"
    ],
    "name:und_x_variant":[
        "Yul\u2019yal"
    ],
    "wof:name":"Yul'yal",
    "wof:placetype":"locality"
},
  "geometry": {"coordinates":[47.8769,57.1609],"type":"Point"}
}