{
  "type": "Feature",
  "properties": {
    "gn:admin1_code":"20",
    "gn:asciiname":"Polinchet",
    "gn:country_code":"RU",
    "gn:dem":169,
    "gn:feature_class":"P",
    "gn:feature_code":"PPL",
    "gn:name":"Polinchet",
    "gn:population":0,
    "gn:timezone":"Asia/Irkutsk",
    "iso:country":"RU",
    "name:eng_x_preferred":[
        "Polinchet"
    ],
    "name:nor_x_preferred":[
        "Polintsjet"
    ],
    "name:rus_x_preferred":[
        "\u041f\u043e\u043b\u0438\u043d\u0447\u0435\u0442"
    ],
    "wof:name":"Polinchet",
    "wof:placetype":"locality"
},
  "geometry": {"coordinates":[98.1112,57.3469],"type":"Point"}
}