{
  "type": "Feature",
  "properties": {
    "gn:admin1_code":"25.0",
    "gn:asciiname":"Poselok Voymirovskogo Shchebenochnogo Zavoda",
    "gn:country_code":"RU",
    "gn:dem":222,
    "gn:feature_class":"P",
    "gn:feature_code":"PPL",
    "gn:name":"Pos\u00eblok Voymirovskogo Shchebenochnogo Zavoda",
    "gn:population":0,
    "gn:timezone":"Europe/Moscow",
    "iso:country":"RU",
    "name:rus_x_preferred":[
        "\u041f\u043e\u0441\u0451\u043b\u043e\u043a \u0412\u043e\u0439\u043c\u0438\u0440\u043e\u0432\u0441\u043a\u043e\u0433\u043e \u0429\u0435\u0431\u0435\u043d\u043e\u0447\u043d\u043e\u0433\u043e \u0417\u0430\u0432\u043e\u0434\u0430"
    ],
    "name:und_x_variant":[
        "Pos\u00eblok Voymirovskogo Shchebenochnogo Zavoda"
    ],
    "wof:name":"Poselok Voymirovskogo Shchebenochnogo Zavoda",
    "wof:placetype":"locality"
},
  "geometry": {"coordinates":[34.96243,54.0382],"type":"Point"}
}