{
  "type": "Feature",
  "properties": {
    "gn:admin1_code":"42",
    "gn:asciiname":"Perebor",
    "gn:country_code":"RU",
    "gn:dem":61,
    "gn:feature_class":"P",
    "gn:feature_code":"PPL",
    "gn:name":"Perebor",
    "gn:population":0,
    "gn:timezone":"Europe/Moscow",
    "iso:country":"RU",
    "name:rus_x_preferred":[
        "\u041f\u0435\u0440\u0435\u0431\u043e\u0440"
    ],
    "name:und_x_variant":[
        "\u041f\u0435\u0440\u0435\u0431\u043e\u0440"
    ],
    "wof:name":"Perebor",
    "wof:placetype":"locality"
},
  "geometry": {"coordinates":[28.20366,59.05486],"type":"Point"}
}