{
  "type": "Feature",
  "properties": {
    "gn:admin1_code":"54",
    "gn:asciiname":"Kaychubay",
    "gn:country_code":"RU",
    "gn:dem":110,
    "gn:feature_class":"P",
    "gn:feature_code":"PPL",
    "gn:name":"Kaychubay",
    "gn:population":0,
    "gn:timezone":"Asia/Omsk",
    "iso:country":"RU",
    "name:eng_x_preferred":[
        "Kayshubay"
    ],
    "name:nor_x_preferred":[
        "Kajtsjubaj"
    ],
    "name:rus_x_preferred":[
        "\u041a\u0430\u0439\u0447\u0443\u0431\u0430\u0439"
    ],
    "wof:name":"Kaychubay",
    "wof:placetype":"locality"
},
  "geometry": {"coordinates":[72.71643,54.7215],"type":"Point"}
}