{
  "type": "Feature",
  "properties": {
    "gn:admin1_code":"60",
    "gn:asciiname":"Kurtashi",
    "gn:country_code":"RU",
    "gn:dem":64,
    "gn:feature_class":"P",
    "gn:feature_code":"PPL",
    "gn:name":"Kurtashi",
    "gn:population":0,
    "gn:timezone":"Europe/Moscow",
    "iso:country":"RU",
    "name:rus_x_preferred":[
        "\u041a\u0443\u0440\u0442\u0430\u0448\u0438"
    ],
    "name:und_x_variant":[
        "Kurtoshi",
        "Kurtashi"
    ],
    "wof:name":"Kurtashi",
    "wof:placetype":"locality"
},
  "geometry": {"coordinates":[28.18451,57.16225],"type":"Point"}
}