{
  "type": "Feature",
  "properties": {
    "gn:country":"RU",
    "gn:fcode":"PPL",
    "gn:pop":9976,
    "iso:country":"RU",
    "name:bel_x_preferred":[
        "\u041a\u0430\u043b\u044c\u0446\u043e\u0432\u0430"
    ],
    "name:ceb_x_preferred":[
        "Kol'tsovo"
    ],
    "name:che_x_preferred":[
        "\u041a\u043e\u043b\u044c\u0446\u043e\u0432\u043e"
    ],
    "name:deu_x_preferred":[
        "Kolzowo"
    ],
    "name:eng_x_preferred":[
        "Kol'tsovo"
    ],
    "name:eng_x_variant":[
        "Koltsovo"
    ],
    "name:fra_x_preferred":[
        "Koltsovo"
    ],
    "name:hsb_x_preferred":[
        "Kolcowo"
    ],
    "name:ita_x_preferred":[
        "Kol'covo"
    ],
    "name:nld_x_preferred":[
        "Koltsovo"
    ],
    "name:nor_x_preferred":[
        "Koltsovo"
    ],
    "name:pol_x_preferred":[
        "Kolcowo"
    ],
    "name:ron_x_preferred":[
        "Kol\u021bovo"
    ],
    "name:rus_x_preferred":[
        "\u041a\u043e\u043b\u044c\u0446\u043e\u0432\u043e"
    ],
    "name:ukr_x_preferred":[
        "\u041a\u043e\u043b\u044c\u0446\u043e\u0432\u043e"
    ],
    "name:unk_x_variant":[
        "\u041a\u043e\u043b\u044c\u0446\u043e\u0432\u043e"
    ],
    "name:zho_x_preferred":[
        "\u65b0\u897f\u4f2f\u5229\u4e9e\u5dde\u79d1\u5229\u4f50\u6c83"
    ],
    "qs:name":"Kol\u2019tsovo",
    "qs:photos_9r":0,
    "qs:photos_sr":0,
    "qs:pop_sr":"5",
    "wd:wordcount":42,
    "wof:name":"Kol\u2019tsovo",
    "wof:placetype":"locality",
    "wof:population":9976
},
  "geometry": {"coordinates":[83.1825,54.9376],"type":"Point"}
}