{
  "type": "Feature",
  "properties": {
    "gn:admin1_code":"54",
    "gn:asciiname":"Krasnyy Shar",
    "gn:country_code":"RU",
    "gn:dem":115,
    "gn:feature_class":"P",
    "gn:feature_code":"PPL",
    "gn:name":"Krasnyy Shar",
    "gn:population":0,
    "gn:timezone":"Asia/Omsk",
    "iso:country":"RU",
    "name:rus_x_preferred":[
        "\u041a\u0440\u0430\u0441\u043d\u044b\u0439 \u0428\u0430\u0440"
    ],
    "name:und_x_variant":[
        "\u041a\u0440\u0430\u0441\u043d\u044b\u0439 \u0428\u0430\u0440"
    ],
    "wof:name":"Krasnyy Shar",
    "wof:placetype":"locality"
},
  "geometry": {"coordinates":[72.3222,55.8571],"type":"Point"}
}