{
  "type": "Feature",
  "properties": {
    "gn:admin1_code":"42",
    "gn:asciiname":"Korpovo",
    "gn:country_code":"RU",
    "gn:dem":82,
    "gn:feature_class":"P",
    "gn:feature_code":"PPL",
    "gn:name":"Korpovo",
    "gn:population":0,
    "gn:timezone":"Europe/Moscow",
    "iso:country":"RU",
    "name:rus_x_preferred":[
        "\u041a\u043e\u0440\u043f\u043e\u0432\u043e"
    ],
    "wof:name":"Korpovo",
    "wof:placetype":"locality"
},
  "geometry": {"coordinates":[29.68194,58.70194],"type":"Point"}
}