{
  "type": "Feature",
  "properties": {
    "gn:admin1_code":"51.0",
    "gn:asciiname":"Melenki",
    "gn:country_code":"RU",
    "gn:dem":115,
    "gn:feature_class":"P",
    "gn:feature_code":"PPL",
    "gn:name":"Melenki",
    "gn:population":0,
    "gn:timezone":"Europe/Moscow",
    "iso:country":"RU",
    "name:ara_x_preferred":[
        "\u0645\u0644\u064a\u0646\u0643\u064a"
    ],
    "name:lav_x_preferred":[
        "Me\u013cenki"
    ],
    "name:nor_x_preferred":[
        "Melenki"
    ],
    "name:rus_x_preferred":[
        "\u041c\u0435\u043b\u0435\u043d\u043a\u0438"
    ],
    "name:tgl_x_preferred":[
        "Melenki"
    ],
    "wof:name":"Melenki",
    "wof:placetype":"locality"
},
  "geometry": {"coordinates":[43.527,56.96328000000001],"type":"Point"}
}