{
  "type": "Feature",
  "properties": {
    "gn:admin1_code":"40.0",
    "gn:asciiname":"Udarnik",
    "gn:country_code":"RU",
    "gn:dem":83,
    "gn:feature_class":"P",
    "gn:feature_code":"PPL",
    "gn:name":"Udarnik",
    "gn:population":0,
    "gn:timezone":"Asia/Yekaterinburg",
    "iso:country":"RU",
    "name:ces_x_preferred":[
        "\u00dadern\u00edk"
    ],
    "name:fin_x_preferred":[
        "Iskuruus"
    ],
    "name:hye_x_preferred":[
        "\u0540\u0561\u0580\u057e\u0561\u056e\u0561\u0575\u0576\u0578\u0582\u0569\u0575\u0578\u0582\u0576"
    ],
    "name:ita_x_preferred":[
        "Udarnik"
    ],
    "name:pol_x_preferred":[
        "Przodownik pracy"
    ],
    "name:rus_x_preferred":[
        "\u0423\u0434\u0430\u0440\u043d\u0438\u043a"
    ],
    "name:srp_x_preferred":[
        "\u0423\u0434\u0430\u0440\u043d\u0438\u043a"
    ],
    "wof:name":"Udarnik",
    "wof:placetype":"locality"
},
  "geometry": {"coordinates":[64.5219,56.2088],"type":"Point"}
}