{
  "type": "Feature",
  "properties": {
    "gn:admin1_code":"25",
    "gn:asciiname":"Medniki",
    "gn:country_code":"RU",
    "gn:dem":246,
    "gn:feature_class":"P",
    "gn:feature_code":"PPL",
    "gn:name":"Medniki",
    "gn:population":0,
    "gn:timezone":"Europe/Moscow",
    "iso:country":"RU",
    "wof:name":"Medniki",
    "wof:placetype":"locality"
},
  "geometry": {"coordinates":[35.66056,55.27083],"type":"Point"}
}