{
  "type": "Feature",
  "properties": {
    "gn:admin1_code":"47.0",
    "gn:asciiname":"Andreyevka",
    "gn:country_code":"RU",
    "gn:dem":130,
    "gn:feature_class":"P",
    "gn:feature_code":"PPL",
    "gn:name":"Andreyevka",
    "gn:population":0,
    "gn:timezone":"Europe/Moscow",
    "iso:country":"RU",
    "name:nor_x_preferred":[
        "Andrejevka"
    ],
    "name:rus_x_preferred":[
        "\u0410\u043d\u0434\u0440\u0435\u0435\u0432\u043a\u0430"
    ],
    "name:und_x_variant":[
        "Andreyevskoye",
        "Andreyevka"
    ],
    "wof:name":"Andreyevka",
    "wof:placetype":"locality"
},
  "geometry": {"coordinates":[38.56384,55.22543],"type":"Point"}
}