{
  "type": "Feature",
  "properties": {
    "gn:admin1_code":"20",
    "gn:asciiname":"Stroitel'",
    "gn:country_code":"RU",
    "gn:dem":444,
    "gn:feature_class":"P",
    "gn:feature_code":"PPL",
    "gn:name":"Stroitel\u2019",
    "gn:population":0,
    "gn:timezone":"Asia/Irkutsk",
    "iso:country":"RU",
    "name:rus_x_preferred":[
        "\u0421\u0442\u0440\u043e\u0438\u0442\u0435\u043b\u044c"
    ],
    "name:und_x_variant":[
        "Stroitel\u2019"
    ],
    "wof:name":"Stroitel'",
    "wof:placetype":"locality"
},
  "geometry": {"coordinates":[101.58636,56.1281],"type":"Point"}
}