{
  "type": "Feature",
  "properties": {
    "gn:admin1_code":"33.0",
    "gn:asciiname":"Chesnoki",
    "gn:country_code":"RU",
    "gn:dem":135,
    "gn:feature_class":"P",
    "gn:feature_code":"PPL",
    "gn:name":"Chesnoki",
    "gn:population":0,
    "gn:timezone":"Europe/Kirov",
    "iso:country":"RU",
    "name:rus_x_preferred":[
        "\u0427\u0435\u0441\u043d\u043e\u043a\u0438"
    ],
    "wof:name":"Chesnoki",
    "wof:placetype":"locality"
},
  "geometry": {"coordinates":[48.518,57.2017],"type":"Point"}
}