{
  "type": "Feature",
  "properties": {
    "gn:admin1_code":"13",
    "gn:asciiname":"Novoyershovskiy",
    "gn:country_code":"RU",
    "gn:dem":318,
    "gn:feature_class":"P",
    "gn:feature_code":"PPL",
    "gn:name":"Novoyershovskiy",
    "gn:population":0,
    "gn:timezone":"Asia/Yekaterinburg",
    "iso:country":"RU",
    "name:rus_x_preferred":[
        "\u041d\u043e\u0432\u043e\u0435\u0440\u0448\u043e\u0432\u0441\u043a\u0438\u0439"
    ],
    "wof:name":"Novoyershovskiy",
    "wof:placetype":"locality"
},
  "geometry": {"coordinates":[59.1225,52.4498],"type":"Point"}
}