{
  "type": "Feature",
  "properties": {
    "gn:admin1_code":"60",
    "gn:asciiname":"Zui",
    "gn:country_code":"RU",
    "gn:dem":143,
    "gn:feature_class":"P",
    "gn:feature_code":"PPL",
    "gn:name":"Zui",
    "gn:population":0,
    "gn:timezone":"Europe/Moscow",
    "iso:country":"RU",
    "name:rus_x_preferred":[
        "\u0417\u0443\u0438"
    ],
    "name:und_x_variant":[
        "\u0417\u0443\u0438"
    ],
    "wof:name":"Zui",
    "wof:placetype":"locality"
},
  "geometry": {"coordinates":[30.3974,56.0241],"type":"Point"}
}