{
  "type": "Feature",
  "properties": {
    "gn:admin1_code":"33",
    "gn:asciiname":"Seryaki",
    "gn:country_code":"RU",
    "gn:dem":144,
    "gn:feature_class":"P",
    "gn:feature_code":"PPL",
    "gn:name":"Seryaki",
    "gn:population":0,
    "gn:timezone":"Europe/Kirov",
    "iso:country":"RU",
    "name:rus_x_preferred":[
        "\u0421\u0435\u0440\u044f\u043a\u0438"
    ],
    "wof:name":"Seryaki",
    "wof:placetype":"locality"
},
  "geometry": {"coordinates":[48.21613,58.18985],"type":"Point"}
}