{
  "type": "Feature",
  "properties": {
    "gn:admin1_code":"56",
    "gn:asciiname":"Zhelyabugskiye Vyselki",
    "gn:country_code":"RU",
    "gn:dem":242,
    "gn:feature_class":"P",
    "gn:feature_code":"PPL",
    "gn:name":"Zhelyabugskiye Vyselki",
    "gn:population":0,
    "gn:timezone":"Europe/Moscow",
    "iso:country":"RU",
    "name:rus_x_preferred":[
        "\u0416\u0435\u043b\u044f\u0431\u0443\u0433\u0441\u043a\u0438\u0435 \u0412\u044b\u0441\u0435\u043b\u043a\u0438"
    ],
    "name:und_x_variant":[
        "Vysokiye",
        "Zhelyabugskiye Vyselki"
    ],
    "wof:name":"Zhelyabugskiye Vyselki",
    "wof:placetype":"locality"
},
  "geometry": {"coordinates":[36.65035,52.9513],"type":"Point"}
}