{
  "type": "Feature",
  "properties": {
    "gn:admin1_code":"68",
    "gn:asciiname":"Moska",
    "gn:country_code":"RU",
    "gn:dem":1581,
    "gn:feature_class":"P",
    "gn:feature_code":"PPL",
    "gn:name":"Moska",
    "gn:population":0,
    "gn:timezone":"Europe/Moscow",
    "iso:country":"RU",
    "name:rus_x_preferred":[
        "\u041c\u043e\u0441\u043a\u0430"
    ],
    "wof:name":"Moska",
    "wof:placetype":"locality"
},
  "geometry": {"coordinates":[43.68167,42.91563],"type":"Point"}
}