{
  "type": "Feature",
  "properties": {
    "gn:admin1_code":"55",
    "gn:asciiname":"Novosaranskiy",
    "gn:country_code":"RU",
    "gn:dem":452,
    "gn:feature_class":"P",
    "gn:feature_code":"PPL",
    "gn:name":"Novosaranskiy",
    "gn:population":0,
    "gn:timezone":"Asia/Yekaterinburg",
    "iso:country":"RU",
    "name:rus_x_preferred":[
        "\u041d\u043e\u0432\u043e\u0441\u0430\u0440\u0430\u043d\u0441\u043a\u0438\u0439"
    ],
    "name:und_x_variant":[
        "Novosarinskiy",
        "Novosaranskiy"
    ],
    "wof:name":"Novosaranskiy",
    "wof:placetype":"locality"
},
  "geometry": {"coordinates":[57.901,51.4818],"type":"Point"}
}