{
  "type": "Feature",
  "properties": {
    "gn:admin1_code":"90",
    "gn:asciiname":"Ust'-Mash",
    "gn:country_code":"RU",
    "gn:dem":273,
    "gn:feature_class":"P",
    "gn:feature_code":"PPL",
    "gn:name":"Ust\u2019-Mash",
    "gn:population":0,
    "gn:timezone":"Asia/Yekaterinburg",
    "iso:country":"RU",
    "wof:name":"Ust'-Mash",
    "wof:placetype":"locality"
},
  "geometry": {"coordinates":[57.01667,56.58333],"type":"Point"}
}