{
  "type": "Feature",
  "properties": {
    "gn:admin1_code":"72.0",
    "gn:asciiname":"Chernitovo",
    "gn:country_code":"RU",
    "gn:dem":95,
    "gn:feature_class":"P",
    "gn:feature_code":"PPL",
    "gn:name":"Chernitovo",
    "gn:population":0,
    "gn:timezone":"Europe/Moscow",
    "iso:country":"RU",
    "name:rus_x_preferred":[
        "\u0427\u0435\u0440\u043d\u0438\u0442\u043e\u0432\u043e"
    ],
    "wof:name":"Chernitovo",
    "wof:placetype":"locality"
},
  "geometry": {"coordinates":[41.78902,53.7271],"type":"Point"}
}