{
  "type": "Feature",
  "properties": {
    "gn:admin1_code":"17",
    "gn:asciiname":"Yukhari-Arkhit",
    "gn:country_code":"RU",
    "gn:dem":885,
    "gn:feature_class":"P",
    "gn:feature_code":"PPL",
    "gn:name":"Yukhari-Arkhit",
    "gn:population":0,
    "gn:timezone":"Europe/Moscow",
    "iso:country":"RU",
    "name:rus_x_preferred":[
        "\u042e\u0445\u0430\u0440\u0438-\u0410\u0440\u0445\u0438\u0442"
    ],
    "wof:name":"Yukhari-Arkhit",
    "wof:placetype":"locality"
},
  "geometry": {"coordinates":[47.95878,41.7405],"type":"Point"}
}