{
  "type": "Feature",
  "properties": {
    "gn:admin1_code":"42",
    "gn:asciiname":"Turyshkino",
    "gn:cc2":"RU",
    "gn:country_code":"RU",
    "gn:dem":49,
    "gn:feature_class":"P",
    "gn:feature_code":"PPL",
    "gn:name":"Turyshkino",
    "gn:population":0,
    "gn:timezone":"Europe/Moscow",
    "iso:country":"RU",
    "name:fin_x_preferred":[
        "Turuskina"
    ],
    "name:und_x_variant":[
        "Turyshkina",
        "Turyshkino"
    ],
    "wof:name":"Turyshkino",
    "wof:placetype":"locality"
},
  "geometry": {"coordinates":[31.23333,59.68333000000001],"type":"Point"}
}