{
  "type": "Feature",
  "properties": {
    "gn:admin1_code":"60",
    "gn:asciiname":"Krasnaya Repka",
    "gn:country_code":"RU",
    "gn:dem":55,
    "gn:feature_class":"P",
    "gn:feature_code":"PPL",
    "gn:name":"Krasnaya Repka",
    "gn:population":0,
    "gn:timezone":"Europe/Moscow",
    "iso:country":"RU",
    "name:rus_x_preferred":[
        "\u041a\u0440\u0430\u0441\u043d\u0430\u044f \u0420\u0435\u043f\u043a\u0430"
    ],
    "wof:name":"Krasnaya Repka",
    "wof:placetype":"locality"
},
  "geometry": {"coordinates":[28.0624,57.7579],"type":"Point"}
}