{
  "type": "Feature",
  "properties": {
    "gn:admin1_code":"43",
    "gn:asciiname":"Rusanovka",
    "gn:country_code":"RU",
    "gn:dem":213,
    "gn:feature_class":"P",
    "gn:feature_code":"PPL",
    "gn:name":"Rusanovka",
    "gn:population":0,
    "gn:timezone":"Europe/Moscow",
    "iso:country":"RU",
    "name:rus_x_preferred":[
        "\u0420\u0443\u0441\u0430\u043d\u043e\u0432\u043a\u0430"
    ],
    "wof:name":"Rusanovka",
    "wof:placetype":"locality"
},
  "geometry": {"coordinates":[38.43333,52.21667],"type":"Point"}
}