{
  "type": "Feature",
  "properties": {
    "gn:country":"RU",
    "gn:fcode":"PPL",
    "gn:pop":0,
    "iso:country":"RU",
    "name:rus_x_preferred":[
        "\u0414\u0430\u0448\u043a\u043e\u0432\u043a\u0430"
    ],
    "name:unk_x_variant":[
        "Doshkovka"
    ],
    "qs:name":"Dashkovka",
    "qs:name_adm0":"Russia",
    "qs:name_adm1":"Moscow Oblast",
    "qs:photos":91,
    "qs:photos_1k":18,
    "qs:photos_9k":1,
    "qs:photos_9r":3,
    "qs:photos_all":91,
    "qs:photos_sr":3,
    "qs:placetype":"Town",
    "qs:pop_sr":"0",
    "wof:name":"Dashkovka",
    "wof:placetype":"locality",
    "wof:population":0
},
  "geometry": {"coordinates":[37.33953,54.90011],"type":"Point"}
}