{
  "type": "Feature",
  "properties": {
    "gn:admin1_code":"67",
    "gn:asciiname":"Kolki",
    "gn:country_code":"RU",
    "gn:dem":243,
    "gn:feature_class":"P",
    "gn:feature_code":"PPL",
    "gn:name":"Kolki",
    "gn:population":0,
    "gn:timezone":"Europe/Saratov",
    "iso:country":"RU",
    "name:ceb_x_preferred":[
        "Kolki"
    ],
    "name:eng_x_preferred":[
        "Kolki"
    ],
    "name:fra_x_preferred":[
        "Kolki"
    ],
    "name:mai_x_preferred":[
        "\u0915\u094b\u0932\u094d\u0915\u0940"
    ],
    "name:msa_x_preferred":[
        "Kolki"
    ],
    "name:nep_x_preferred":[
        "\u0915\u094b\u0932\u094d\u0915\u0940"
    ],
    "name:new_x_preferred":[
        "\u0915\u094b\u0932\u094d\u0915\u0940"
    ],
    "name:nor_x_preferred":[
        "Kolki"
    ],
    "name:pol_x_preferred":[
        "Kolki"
    ],
    "name:rus_x_preferred":[
        "\u041a\u043e\u043b\u043a\u0438"
    ],
    "name:und_x_variant":[
        "\u041a\u043e\u043b\u043a\u0438",
        "Kolki"
    ],
    "wof:name":"Kolki",
    "wof:placetype":"locality"
},
  "geometry": {"coordinates":[45.50775,52.14822],"type":"Point"}
}