{
  "type": "Feature",
  "properties": {
    "gn:admin1_code":"16",
    "gn:asciiname":"Oykasy",
    "gn:country_code":"RU",
    "gn:dem":138,
    "gn:feature_class":"P",
    "gn:feature_code":"PPL",
    "gn:name":"Oykasy",
    "gn:population":0,
    "gn:timezone":"Europe/Moscow",
    "iso:country":"RU",
    "name:rus_x_preferred":[
        "\u041e\u0439\u043a\u0430\u0441\u044b"
    ],
    "wof:name":"Oykasy",
    "wof:placetype":"locality"
},
  "geometry": {"coordinates":[47.77309,55.75585],"type":"Point"}
}