{
  "type": "Feature",
  "properties": {
    "gn:admin1_code":"93",
    "gn:asciiname":"Chichatka",
    "gn:country_code":"RU",
    "gn:dem":559,
    "gn:feature_class":"P",
    "gn:feature_code":"PPL",
    "gn:name":"Chichatka",
    "gn:population":0,
    "gn:timezone":"Asia/Chita",
    "iso:country":"RU",
    "name:eng_x_preferred":[
        "Chichatka"
    ],
    "name:nor_x_preferred":[
        "Tsjitsjatka"
    ],
    "name:rus_x_preferred":[
        "\u0427\u0438\u0447\u0430\u0442\u043a\u0430"
    ],
    "wof:name":"Chichatka",
    "wof:placetype":"locality"
},
  "geometry": {"coordinates":[121.29986,54.04094],"type":"Point"}
}