{
  "type": "Feature",
  "properties": {
    "gn:admin1_code":"9",
    "gn:asciiname":"Setishche",
    "gn:country_code":"RU",
    "gn:dem":218,
    "gn:feature_class":"P",
    "gn:feature_code":"PPL",
    "gn:name":"Setishche",
    "gn:population":0,
    "gn:timezone":"Europe/Moscow",
    "iso:country":"RU",
    "name:eng_x_preferred":[
        "Setishche"
    ],
    "name:nor_x_preferred":[
        "Setisjtsje"
    ],
    "name:rus_x_preferred":[
        "\u0421\u0435\u0442\u0438\u0449\u0435"
    ],
    "name:und_x_variant":[
        "\u0421\u0435\u0442\u0438\u0449\u0435",
        "Setishche"
    ],
    "wof:name":"Setishche",
    "wof:placetype":"locality"
},
  "geometry": {"coordinates":[38.6411,50.9436],"type":"Point"}
}