{
  "type": "Feature",
  "properties": {
    "gn:admin1_code":"6.0",
    "gn:asciiname":"Kvakhtyuga",
    "gn:country_code":"RU",
    "gn:dem":34,
    "gn:feature_class":"P",
    "gn:feature_code":"PPL",
    "gn:name":"Kvakhtyuga",
    "gn:population":0,
    "gn:timezone":"Europe/Moscow",
    "iso:country":"RU",
    "name:rus_x_preferred":[
        "\u041a\u0432\u0430\u0445\u0442\u044e\u0433\u0430"
    ],
    "wof:name":"Kvakhtyuga",
    "wof:placetype":"locality"
},
  "geometry": {"coordinates":[43.1201,62.9117],"type":"Point"}
}