{
  "type": "Feature",
  "properties": {
    "gn:admin1_code":"60",
    "gn:asciiname":"Koshelevo",
    "gn:country_code":"RU",
    "gn:dem":178,
    "gn:feature_class":"P",
    "gn:feature_code":"PPL",
    "gn:name":"Koshel\u00ebvo",
    "gn:population":0,
    "gn:timezone":"Europe/Moscow",
    "iso:country":"RU",
    "name:rus_x_preferred":[
        "\u041a\u043e\u0448\u0435\u043b\u0451\u0432\u043e"
    ],
    "name:und_x_variant":[
        "Koshel\u00ebvo"
    ],
    "wof:name":"Koshelevo",
    "wof:placetype":"locality"
},
  "geometry": {"coordinates":[30.23687,55.93912],"type":"Point"}
}