{
  "type": "Feature",
  "properties": {
    "gn:admin1_code":"25",
    "gn:asciiname":"Tolmachevo",
    "gn:country_code":"RU",
    "gn:dem":200,
    "gn:feature_class":"P",
    "gn:feature_code":"PPL",
    "gn:name":"Tolmach\u00ebvo",
    "gn:population":0,
    "gn:timezone":"Europe/Moscow",
    "iso:country":"RU",
    "name:und_x_variant":[
        "Tolmacheva",
        "Tolmach\u00ebvo"
    ],
    "wof:name":"Tolmachevo",
    "wof:placetype":"locality"
},
  "geometry": {"coordinates":[36.94484,54.70636],"type":"Point"}
}