{
  "type": "Feature",
  "properties": {
    "gn:admin1_code":"8",
    "gn:asciiname":"Starosaitovo",
    "gn:country_code":"RU",
    "gn:dem":371,
    "gn:feature_class":"P",
    "gn:feature_code":"PPL",
    "gn:name":"Starosaitovo",
    "gn:population":0,
    "gn:timezone":"Asia/Yekaterinburg",
    "iso:country":"RU",
    "name:eng_x_preferred":[
        "Starosaitovo"
    ],
    "name:nor_x_preferred":[
        "Starosaitovo"
    ],
    "name:rus_x_preferred":[
        "\u0421\u0442\u0430\u0440\u043e\u0441\u0430\u0438\u0442\u043e\u0432\u043e"
    ],
    "name:und_x_variant":[
        "Saitova"
    ],
    "wof:name":"Starosaitovo",
    "wof:placetype":"locality"
},
  "geometry": {"coordinates":[56.97715,53.67688],"type":"Point"}
}