{
  "type": "Feature",
  "properties": {
    "gn:admin1_code":"33",
    "gn:asciiname":"Nizhnyaya Toyma",
    "gn:country_code":"RU",
    "gn:dem":71,
    "gn:feature_class":"P",
    "gn:feature_code":"PPL",
    "gn:name":"Nizhnyaya Toyma",
    "gn:population":0,
    "gn:timezone":"Europe/Kirov",
    "iso:country":"RU",
    "name:rus_x_preferred":[
        "\u041d\u0438\u0436\u043d\u044f\u044f \u0422\u043e\u0439\u043c\u0430"
    ],
    "name:und_x_variant":[
        "\u041d\u0438\u0436\u043d\u044f\u044f \u0422\u043e\u0439\u043c\u0430"
    ],
    "wof:name":"Nizhnyaya Toyma",
    "wof:placetype":"locality"
},
  "geometry": {"coordinates":[51.03922,56.23514],"type":"Point"}
}