{
  "type": "Feature",
  "properties": {
    "gn:admin1_code":"46.0",
    "gn:asciiname":"Al'za",
    "gn:country_code":"RU",
    "gn:dem":185,
    "gn:feature_class":"P",
    "gn:feature_code":"PPL",
    "gn:name":"Al\u2019za",
    "gn:population":0,
    "gn:timezone":"Europe/Moscow",
    "iso:country":"RU",
    "name:nor_x_preferred":[
        "Alza"
    ],
    "name:rus_x_preferred":[
        "\u0410\u043b\u044c\u0437\u0430"
    ],
    "name:und_x_variant":[
        "Al\u2019za"
    ],
    "wof:name":"Al'za",
    "wof:placetype":"locality"
},
  "geometry": {"coordinates":[45.7197,54.4223],"type":"Point"}
}