{
  "type": "Feature",
  "properties": {
    "gn:admin1_code":"25",
    "gn:asciiname":"Kryshilovo",
    "gn:country_code":"RU",
    "gn:dem":183,
    "gn:feature_class":"P",
    "gn:feature_code":"PPL",
    "gn:name":"Kryshilovo",
    "gn:population":0,
    "gn:timezone":"Europe/Moscow",
    "iso:country":"RU",
    "name:rus_x_preferred":[
        "\u041a\u0440\u044b\u0448\u0438\u043b\u043e\u0432\u043e"
    ],
    "wof:name":"Kryshilovo",
    "wof:placetype":"locality"
},
  "geometry": {"coordinates":[35.19306,54.4425],"type":"Point"}
}