{
  "type": "Feature",
  "properties": {
    "gn:admin1_code":"56",
    "gn:asciiname":"Malinovo",
    "gn:country_code":"RU",
    "gn:dem":252,
    "gn:feature_class":"P",
    "gn:feature_code":"PPL",
    "gn:name":"Malinovo",
    "gn:population":0,
    "gn:timezone":"Europe/Moscow",
    "iso:country":"RU",
    "name:eng_x_preferred":[
        "Malinovo"
    ],
    "name:nor_x_preferred":[
        "Malinovo"
    ],
    "name:rus_x_preferred":[
        "\u041c\u0430\u043b\u0438\u043d\u043e\u0432\u043e"
    ],
    "name:und_x_variant":[
        "Malinova",
        "\u041c\u0430\u043b\u0438\u043d\u043e\u0432\u043e",
        "Malinovo"
    ],
    "wof:name":"Malinovo",
    "wof:placetype":"locality"
},
  "geometry": {"coordinates":[37.85698,52.76723000000001],"type":"Point"}
}