{
  "type": "Feature",
  "properties": {
    "gn:admin1_code":"60",
    "gn:asciiname":"Nestroyevo",
    "gn:country_code":"RU",
    "gn:dem":153,
    "gn:feature_class":"P",
    "gn:feature_code":"PPL",
    "gn:name":"Nestroyevo",
    "gn:population":0,
    "gn:timezone":"Europe/Moscow",
    "iso:country":"RU",
    "name:rus_x_preferred":[
        "\u041d\u0435\u0441\u0442\u0440\u043e\u0435\u0432\u043e"
    ],
    "name:und_x_variant":[
        "Nestroyeva",
        "Nestroyevo",
        "\u041d\u0435\u0441\u0442\u0440\u043e\u0435\u0432\u043e"
    ],
    "wof:name":"Nestroyevo",
    "wof:placetype":"locality"
},
  "geometry": {"coordinates":[30.69716,56.06795],"type":"Point"}
}