{
  "type": "Feature",
  "properties": {
    "gn:admin1_code":"11",
    "gn:asciiname":"Khuzhir",
    "gn:country_code":"RU",
    "gn:dem":1049,
    "gn:feature_class":"P",
    "gn:feature_code":"PPL",
    "gn:name":"Khuzhir",
    "gn:population":0,
    "gn:timezone":"Asia/Irkutsk",
    "iso:country":"RU",
    "name:eng_x_preferred":[
        "Khuzhir"
    ],
    "name:nor_x_preferred":[
        "Khuzjir"
    ],
    "name:rus_x_preferred":[
        "\u0425\u0443\u0436\u0438\u0440"
    ],
    "name:und_x_variant":[
        "Dobunay-Adag",
        "Khuzhar",
        "Dodunay-Adag"
    ],
    "wof:name":"Khuzhir",
    "wof:placetype":"locality"
},
  "geometry": {"coordinates":[103.26730000000001,50.4221],"type":"Point"}
}