{
  "type": "Feature",
  "properties": {
    "gn:admin1_code":"64",
    "gn:asciiname":"Kharitonovka",
    "gn:cc2":"RU",
    "gn:country_code":"RU",
    "gn:dem":1,
    "gn:feature_class":"P",
    "gn:feature_code":"PPL",
    "gn:name":"Kharitonovka",
    "gn:population":0,
    "gn:timezone":"Asia/Magadan",
    "iso:country":"RU",
    "name:und_x_variant":[
        "Raishi",
        "Raisha",
        "Raisya"
    ],
    "wof:name":"Kharitonovka",
    "wof:placetype":"locality"
},
  "geometry": {"coordinates":[155.39444,50.02222],"type":"Point"}
}