{
  "type": "Feature",
  "properties": {
    "gn:country":"RU",
    "gn:fcode":"PPLX",
    "gn:population":0,
    "iso:country":"RU",
    "name:rus_x_preferred":[
        "\u0428\u0430\u0439\u0434\u043e\u0440\u043e\u0432\u043e"
    ],
    "name:und_x_variant":[
        "Shadrova"
    ],
    "qs:name":"Shaydorovo",
    "qs:name_adm0":"Russia",
    "qs:name_adm1":"Moscow Federal City",
    "qs:photos":1,
    "qs:photos_1k":1,
    "qs:photos_9k":1,
    "qs:photos_9r":1,
    "qs:photos_all":1,
    "qs:photos_sr":1,
    "qs:placetype":"Suburb",
    "qs:pop_sr":"0",
    "wof:name":"Shaydorovo",
    "wof:placetype":"neighbourhood",
    "wof:population":0
},
  "geometry": {"coordinates":[37.68333,55.63333],"type":"Point"}
}