{
  "type": "Feature",
  "properties": {
    "gn:admin1_code":"71",
    "gn:asciiname":"Nizhniy Ariy",
    "gn:country_code":"RU",
    "gn:dem":242,
    "gn:feature_class":"P",
    "gn:feature_code":"PPL",
    "gn:name":"Nizhniy Ariy",
    "gn:population":0,
    "gn:timezone":"Asia/Yekaterinburg",
    "iso:country":"RU",
    "name:rus_x_preferred":[
        "\u041d\u0438\u0436\u043d\u0438\u0439 \u0410\u0440\u0438\u0439"
    ],
    "name:und_x_variant":[
        "\u041d\u0438\u0436\u043d\u0438\u0439 \u0410\u0440\u0438\u0439"
    ],
    "wof:name":"Nizhniy Ariy",
    "wof:placetype":"locality"
},
  "geometry": {"coordinates":[58.20399999999999,56.7179],"type":"Point"}
}