{
  "type": "Feature",
  "properties": {
    "gn:admin1_code":"10.0",
    "gn:asciiname":"Bashevo",
    "gn:country_code":"RU",
    "gn:dem":212,
    "gn:feature_class":"P",
    "gn:feature_code":"PPL",
    "gn:name":"Bashevo",
    "gn:population":0,
    "gn:timezone":"Europe/Moscow",
    "iso:country":"RU",
    "name:nor_x_preferred":[
        "Basjevo"
    ],
    "name:rus_x_preferred":[
        "\u0411\u0430\u0448\u0435\u0432\u043e"
    ],
    "wof:name":"Bashevo",
    "wof:placetype":"locality"
},
  "geometry": {"coordinates":[33.39944000000001,53.84917],"type":"Point"}
}