{
  "type": "Feature",
  "properties": {
    "gn:admin1_code":"55",
    "gn:asciiname":"Kunduzlutomak",
    "gn:country_code":"RU",
    "gn:dem":103,
    "gn:feature_class":"P",
    "gn:feature_code":"PPL",
    "gn:name":"Kunduzlutomak",
    "gn:population":0,
    "gn:timezone":"Asia/Yekaterinburg",
    "iso:country":"RU",
    "name:rus_x_preferred":[
        "\u041a\u0443\u043d\u0434\u0443\u0437\u043b\u0443\u0442\u043e\u043c\u0430\u043a"
    ],
    "name:und_x_variant":[
        "Kunduzlutamak",
        "Kunduzlutomak",
        "\u041a\u0443\u043d\u0434\u0443\u0437\u043b\u0443\u0442\u043e\u043c\u0430\u043a"
    ],
    "wof:name":"Kunduzlutomak",
    "wof:placetype":"locality"
},
  "geometry": {"coordinates":[52.2571,52.1759],"type":"Point"}
}