{
  "type": "Feature",
  "properties": {
    "iso:country":"RU",
    "name:rus_x_preferred":[
        "\u0421\u0442\u0430\u0440\u043e-\u041f\u0430\u043d\u043e\u0432\u043e"
    ],
    "wof:name":"Staro-Panovo",
    "wof:placetype":"neighbourhood"
},
  "geometry": {"coordinates":[30.17375156090419,59.81553276286809],"type":"Point"}
}