{
  "type": "Feature",
  "properties": {
    "gn:admin1_code":"59",
    "gn:asciiname":"Sobolevka",
    "gn:country_code":"RU",
    "gn:dem":79,
    "gn:feature_class":"P",
    "gn:feature_code":"PPL",
    "gn:name":"Sobolevka",
    "gn:population":0,
    "gn:timezone":"Asia/Vladivostok",
    "iso:country":"RU",
    "name:rus_x_preferred":[
        "\u0421\u043e\u0431\u043e\u043b\u0435\u0432\u043a\u0430"
    ],
    "name:und_x_variant":[
        "\u0421\u043e\u0431\u043e\u043b\u0435\u0432\u043a\u0430"
    ],
    "wof:name":"Sobolevka",
    "wof:placetype":"locality"
},
  "geometry": {"coordinates":[137.94999999999999,46.23333],"type":"Point"}
}