{
  "type": "Feature",
  "properties": {
    "gn:admin1_code":"47",
    "gn:asciiname":"Timkovo",
    "gn:country_code":"RU",
    "gn:dem":137,
    "gn:feature_class":"P",
    "gn:feature_code":"PPL",
    "gn:name":"Timkovo",
    "gn:population":0,
    "gn:timezone":"Europe/Moscow",
    "iso:country":"RU",
    "name:eng_x_preferred":[
        "Timkovo"
    ],
    "name:nor_x_preferred":[
        "Timkovo"
    ],
    "name:rus_x_preferred":[
        "\u0422\u0438\u043c\u043a\u043e\u0432\u043e"
    ],
    "name:und_x_variant":[
        "Timkova",
        "Timkovo"
    ],
    "wof:name":"Timkovo",
    "wof:placetype":"locality"
},
  "geometry": {"coordinates":[38.6223,55.93181],"type":"Point"}
}