{
  "type": "Feature",
  "properties": {
    "gn:admin1_code":"69.0",
    "gn:asciiname":"Berezkino",
    "gn:country_code":"RU",
    "gn:dem":207,
    "gn:feature_class":"P",
    "gn:feature_code":"PPL",
    "gn:name":"Ber\u00ebzkino",
    "gn:population":0,
    "gn:timezone":"Europe/Moscow",
    "iso:country":"RU",
    "name:nor_x_preferred":[
        "Berjozkino"
    ],
    "name:rus_x_preferred":[
        "\u0411\u0435\u0440\u0451\u0437\u043a\u0438\u043d\u043e"
    ],
    "name:und_x_variant":[
        "Ber\u00ebzkino"
    ],
    "wof:name":"Berezkino",
    "wof:placetype":"locality"
},
  "geometry": {"coordinates":[32.49687,54.90181],"type":"Point"}
}