{
  "type": "Feature",
  "properties": {
    "gn:admin1_code":"8",
    "gn:asciiname":"Yardam",
    "gn:country_code":"RU",
    "gn:dem":252,
    "gn:feature_class":"P",
    "gn:feature_code":"PPL",
    "gn:name":"Yardam",
    "gn:population":0,
    "gn:timezone":"Asia/Yekaterinburg",
    "iso:country":"RU",
    "name:bak_x_preferred":[
        "\u042f\u0440\u0499\u0430\u043c"
    ],
    "name:che_x_preferred":[
        "\u042f\u0440\u0434\u0430\u043c"
    ],
    "name:hye_x_preferred":[
        "\u0545\u0561\u0580\u0564\u0561\u0574"
    ],
    "name:kaz_x_preferred":[
        "\u042f\u0440\u0434\u0430\u043c"
    ],
    "name:kir_x_preferred":[
        "\u042f\u0440\u0434\u0430\u043c"
    ],
    "name:rus_x_preferred":[
        "\u042f\u0440\u0434\u0430\u043c"
    ],
    "name:tat_x_preferred":[
        "\u042f\u0440\u0434\u04d9\u043c"
    ],
    "name:und_x_variant":[
        "\u042f\u0440\u0434\u0430\u043c"
    ],
    "wof:name":"Yardam",
    "wof:placetype":"locality"
},
  "geometry": {"coordinates":[54.6492,54.9197],"type":"Point"}
}