{
  "type": "Feature",
  "properties": {
    "gn:admin1_code":"59",
    "gn:asciiname":"Zhitkovo",
    "gn:country_code":"RU",
    "gn:dem":9,
    "gn:feature_class":"P",
    "gn:feature_code":"PPL",
    "gn:name":"Zhitkovo",
    "gn:population":0,
    "gn:timezone":"Asia/Vladivostok",
    "iso:country":"RU",
    "name:che_x_preferred":[
        "\u0416\u0438\u0442\u043a\u043e\u0432\u043e"
    ],
    "name:fin_x_preferred":[
        "Ristsepp\u00e4l\u00e4"
    ],
    "name:hye_x_preferred":[
        "\u053a\u056b\u057f\u056f\u0578\u057e\u0578"
    ],
    "name:rus_x_preferred":[
        "\u0416\u0438\u0442\u043a\u043e\u0432\u043e"
    ],
    "wof:name":"Zhitkovo",
    "wof:placetype":"locality"
},
  "geometry": {"coordinates":[131.92934,43.02318],"type":"Point"}
}