{
  "type": "Feature",
  "properties": {
    "gn:admin1_code":"60",
    "gn:asciiname":"Zhbany",
    "gn:country_code":"RU",
    "gn:dem":169,
    "gn:feature_class":"P",
    "gn:feature_code":"PPL",
    "gn:name":"Zhbany",
    "gn:population":0,
    "gn:timezone":"Europe/Moscow",
    "iso:country":"RU",
    "name:rus_x_preferred":[
        "\u0416\u0431\u0430\u043d\u044b"
    ],
    "wof:name":"Zhbany",
    "wof:placetype":"locality"
},
  "geometry": {"coordinates":[28.94047,56.06164],"type":"Point"}
}