{
  "type": "Feature",
  "properties": {
    "gn:admin1_code":"4",
    "gn:asciiname":"Vstavay Bednyak",
    "gn:country_code":"RU",
    "gn:dem":210,
    "gn:feature_class":"P",
    "gn:feature_code":"PPL",
    "gn:name":"Vstavay Bednyak",
    "gn:population":0,
    "gn:timezone":"Asia/Barnaul",
    "iso:country":"RU",
    "wof:name":"Vstavay Bednyak",
    "wof:placetype":"locality"
},
  "geometry": {"coordinates":[81.13333,53.73333],"type":"Point"}
}