{
  "type": "Feature",
  "properties": {
    "gn:admin1_code":"73",
    "gn:asciiname":"Yasak",
    "gn:country_code":"RU",
    "gn:dem":125,
    "gn:feature_class":"P",
    "gn:feature_code":"PPL",
    "gn:name":"Yasak",
    "gn:population":0,
    "gn:timezone":"Europe/Moscow",
    "iso:country":"RU",
    "name:bak_x_preferred":[
        "\u042f\u04bb\u0430\u04a1"
    ],
    "name:bel_x_preferred":[
        "\u042f\u0441\u0430\u043a"
    ],
    "name:ces_x_preferred":[
        "Jasak"
    ],
    "name:deu_x_preferred":[
        "Kronenzobel"
    ],
    "name:est_x_preferred":[
        "Jassakk"
    ],
    "name:fin_x_preferred":[
        "Jasakki"
    ],
    "name:fra_x_preferred":[
        "Iassak"
    ],
    "name:ita_x_preferred":[
        "Yasaq"
    ],
    "name:kaz_x_preferred":[
        "\u042f\u0441\u0430\u049b"
    ],
    "name:nld_x_preferred":[
        "Jasak"
    ],
    "name:pol_x_preferred":[
        "Jasak"
    ],
    "name:rus_x_preferred":[
        "\u042f\u0441\u0430\u043a"
    ],
    "name:sah_x_preferred":[
        "\u0414\u044c\u0430\u04bb\u0430\u0430\u0445"
    ],
    "name:spa_x_preferred":[
        "Yasak"
    ],
    "name:tat_x_preferred":[
        "Yasaq"
    ],
    "name:ukr_x_preferred":[
        "\u042f\u0441\u0430\u043a"
    ],
    "name:und_x_variant":[
        "\u042f\u0441\u0430\u043a"
    ],
    "name:zho_x_preferred":[
        "\u7259\u85a9\u514b"
    ],
    "wof:name":"Yasak",
    "wof:placetype":"locality"
},
  "geometry": {"coordinates":[51.2966,54.7371],"type":"Point"}
}