{
  "type": "Feature",
  "properties": {
    "gn:admin1_code":"86.0",
    "gn:asciiname":"Vasil'yevka",
    "gn:country_code":"RU",
    "gn:dem":163,
    "gn:feature_class":"P",
    "gn:feature_code":"PPL",
    "gn:name":"Vasil\u2019yevka",
    "gn:population":0,
    "gn:timezone":"Europe/Moscow",
    "iso:country":"RU",
    "wof:name":"Vasil'yevka",
    "wof:placetype":"locality"
},
  "geometry": {"coordinates":[40.09944,51.86],"type":"Point"}
}