{
  "type": "Feature",
  "properties": {
    "gn:admin1_code":"63",
    "gn:asciiname":"Ugol'naya Zyryanka",
    "gn:country_code":"RU",
    "gn:dem":118,
    "gn:feature_class":"P",
    "gn:feature_code":"PPL",
    "gn:name":"Ugol\u2019naya Zyryanka",
    "gn:population":0,
    "gn:timezone":"Asia/Magadan",
    "iso:country":"RU",
    "name:che_x_preferred":[
        "\u0423\u0433\u043e\u043b\u044c\u043d\u0438"
    ],
    "name:eng_x_preferred":[
        "Ugol'naya Zyryanka"
    ],
    "name:nor_x_preferred":[
        "Ugolnoje"
    ],
    "name:rus_x_preferred":[
        "\u0423\u0433\u043e\u043b\u044c\u043d\u043e\u0435"
    ],
    "name:ukr_x_preferred":[
        "\u0423\u0433\u043e\u043b\u044c\u043d\u0435"
    ],
    "name:und_x_variant":[
        "Ugol\u2019naya",
        "Ugol\u2019naya Zyryanka"
    ],
    "wof:name":"Ugol'naya Zyryanka",
    "wof:placetype":"locality"
},
  "geometry": {"coordinates":[149.74653000000001,65.74995],"type":"Point"}
}