{
  "type": "Feature",
  "properties": {
    "gn:admin1_code":"53",
    "gn:asciiname":"Kudryavtsevskiy",
    "gn:country_code":"RU",
    "gn:dem":173,
    "gn:feature_class":"P",
    "gn:feature_code":"PPL",
    "gn:name":"Kudryavtsevskiy",
    "gn:population":0,
    "gn:timezone":"Asia/Novosibirsk",
    "iso:country":"RU",
    "name:rus_x_preferred":[
        "\u041a\u0443\u0434\u0440\u044f\u0432\u0446\u0435\u0432\u0441\u043a\u0438\u0439"
    ],
    "wof:name":"Kudryavtsevskiy",
    "wof:placetype":"locality"
},
  "geometry": {"coordinates":[84.28333000000001,55.05],"type":"Point"}
}