{
  "type": "Feature",
  "properties": {
    "gn:admin1_code":"17",
    "gn:admin2_code":"549104",
    "gn:asciiname":"Mochokh",
    "gn:country_code":"RU",
    "gn:dem":1641,
    "gn:feature_class":"P",
    "gn:feature_code":"PPL",
    "gn:name":"Mochokh",
    "gn:population":0,
    "gn:timezone":"Europe/Moscow",
    "iso:country":"RU",
    "name:rus_x_preferred":[
        "\u041c\u043e\u0447\u043e\u0445"
    ],
    "name:und_x_variant":[
        "Mochok",
        "Mochokh"
    ],
    "wof:name":"Mochokh",
    "wof:placetype":"locality"
},
  "geometry": {"coordinates":[46.61242,42.63159],"type":"Point"}
}