{
  "type": "Feature",
  "properties": {
    "gn:admin1_code":"25.0",
    "gn:asciiname":"Yeleshnya Vtoraya",
    "gn:country_code":"RU",
    "gn:dem":206,
    "gn:feature_class":"P",
    "gn:feature_code":"PPL",
    "gn:name":"Yeleshnya Vtoraya",
    "gn:population":0,
    "gn:timezone":"Europe/Moscow",
    "iso:country":"RU",
    "wof:name":"Yeleshnya Vtoraya",
    "wof:placetype":"locality"
},
  "geometry": {"coordinates":[35.77867,54.97618000000001],"type":"Point"}
}