{
  "type": "Feature",
  "properties": {
    "gn:admin1_code":"60",
    "gn:asciiname":"Prosni",
    "gn:country_code":"RU",
    "gn:dem":140,
    "gn:feature_class":"P",
    "gn:feature_code":"PPL",
    "gn:name":"Prosni",
    "gn:population":0,
    "gn:timezone":"Europe/Moscow",
    "iso:country":"RU",
    "name:rus_x_preferred":[
        "\u041f\u0440\u043e\u0441\u043d\u0438"
    ],
    "wof:name":"Prosni",
    "wof:placetype":"locality"
},
  "geometry": {"coordinates":[28.67028,56.36911],"type":"Point"}
}