{
  "type": "Feature",
  "properties": {
    "gn:admin1_code":"60",
    "gn:asciiname":"Fedortsevo",
    "gn:country_code":"RU",
    "gn:dem":122,
    "gn:feature_class":"P",
    "gn:feature_code":"PPL",
    "gn:name":"F\u00ebdortsevo",
    "gn:population":0,
    "gn:timezone":"Europe/Moscow",
    "iso:country":"RU",
    "name:rus_x_preferred":[
        "\u0424\u0451\u0434\u043e\u0440\u0446\u0435\u0432\u043e"
    ],
    "name:und_x_variant":[
        "F\u00ebdortsevo"
    ],
    "wof:name":"Fedortsevo",
    "wof:placetype":"locality"
},
  "geometry": {"coordinates":[30.9105,56.3621],"type":"Point"}
}