{
  "type": "Feature",
  "properties": {
    "gn:admin1_code":"28",
    "gn:asciiname":"Talo",
    "gn:country_code":"RU",
    "gn:dem":55,
    "gn:feature_class":"P",
    "gn:feature_code":"PPL",
    "gn:name":"Talo",
    "gn:population":0,
    "gn:timezone":"Europe/Moscow",
    "iso:country":"RU",
    "name:ara_x_preferred":[
        "\u062a\u0627\u0644\u0648"
    ],
    "name:ben_x_preferred":[
        "\u09a4\u09be\u09b2\u09cb"
    ],
    "name:cat_x_preferred":[
        "Talo"
    ],
    "name:ceb_x_preferred":[
        "Talo"
    ],
    "name:deu_x_preferred":[
        "Talo"
    ],
    "name:ell_x_preferred":[
        "\u03a4\u03ac\u03bb\u03c9"
    ],
    "name:eng_x_preferred":[
        "Talo"
    ],
    "name:epo_x_preferred":[
        "Talo"
    ],
    "name:fas_x_preferred":[
        "\u062a\u0627\u0644\u0648"
    ],
    "name:fin_x_preferred":[
        "Viiso"
    ],
    "name:fin_x_variant":[
        "Talo"
    ],
    "name:fra_x_preferred":[
        "Talo"
    ],
    "name:glg_x_preferred":[
        "Talo"
    ],
    "name:heb_x_preferred":[
        "\u05d8\u05d0\u05dc\u05d5"
    ],
    "name:hin_x_preferred":[
        "\u0924\u093e\u0932\u094b"
    ],
    "name:hun_x_preferred":[
        "Talo"
    ],
    "name:ind_x_preferred":[
        "Talo"
    ],
    "name:ita_x_preferred":[
        "Talo"
    ],
    "name:jpn_x_preferred":[
        "\u30bf\u30ed\u5c71"
    ],
    "name:kor_x_preferred":[
        "\ud0c8\ub85c"
    ],
    "name:nld_x_preferred":[
        "Talo"
    ],
    "name:pol_x_preferred":[
        "Talo"
    ],
    "name:por_x_preferred":[
        "Talo"
    ],
    "name:rus_x_preferred":[
        "\u0433\u043e\u0440\u0430 \u0422\u0430\u043b\u043e"
    ],
    "name:spa_x_preferred":[
        "Talo"
    ],
    "name:swe_x_preferred":[
        "Talo"
    ],
    "name:tur_x_preferred":[
        "Talo"
    ],
    "name:ukr_x_preferred":[
        "\u0422\u0430\u043b\u043e"
    ],
    "name:urd_x_preferred":[
        "\u062a\u0627\u0644\u0648"
    ],
    "name:vie_x_preferred":[
        "N\u00fai Talo"
    ],
    "name:zho_cn_x_preferred":[
        "\u5854\u6d1b\u5c71"
    ],
    "name:zho_tw_x_preferred":[
        "\u5854\u6d1b\u5c71"
    ],
    "wof:name":"Talo",
    "wof:placetype":"locality"
},
  "geometry": {"coordinates":[30.86667,61.81667],"type":"Point"}
}