{
  "type": "Feature",
  "properties": {
    "gn:admin1_code":"28",
    "gn:asciiname":"Talo",
    "gn:country_code":"RU",
    "gn:dem":55,
    "gn:feature_class":"P",
    "gn:feature_code":"PPL",
    "gn:name":"Talo",
    "gn:population":0,
    "gn:timezone":"Europe/Moscow",
    "iso:country":"RU",
    "name:fin_x_preferred":[
        "Viiso"
    ],
    "wof:name":"Talo",
    "wof:placetype":"locality"
},
  "geometry": {"coordinates":[30.86667000000001,61.81667],"type":"Point"}
}