{
  "type": "Feature",
  "properties": {
    "gn:admin1_code":"33",
    "gn:asciiname":"Shishkino",
    "gn:country_code":"RU",
    "gn:dem":183,
    "gn:feature_class":"P",
    "gn:feature_code":"PPL",
    "gn:name":"Shishkino",
    "gn:population":0,
    "gn:timezone":"Europe/Kirov",
    "iso:country":"RU",
    "name:rus_x_preferred":[
        "\u0428\u0438\u0448\u043a\u0438\u043d\u043e"
    ],
    "name:und_x_variant":[
        "\u0428\u0438\u0448\u043a\u0438\u043d\u043e"
    ],
    "wof:name":"Shishkino",
    "wof:placetype":"locality"
},
  "geometry": {"coordinates":[50.05,57.78333000000001],"type":"Point"}
}