{
  "type": "Feature",
  "properties": {
    "gn:admin1_code":"51.0",
    "gn:asciiname":"Sherstino",
    "gn:country_code":"RU",
    "gn:dem":123,
    "gn:feature_class":"P",
    "gn:feature_code":"PPL",
    "gn:name":"Sherstino",
    "gn:population":0,
    "gn:timezone":"Europe/Moscow",
    "iso:country":"RU",
    "name:rus_x_preferred":[
        "\u0428\u0435\u0440\u0441\u0442\u0438\u043d\u043e"
    ],
    "wof:name":"Sherstino",
    "wof:placetype":"locality"
},
  "geometry": {"coordinates":[43.86144,55.32561],"type":"Point"}
}