{
  "type": "Feature",
  "properties": {
    "gn:admin1_code":"38",
    "gn:asciiname":"Prokhladnyy",
    "gn:country_code":"RU",
    "gn:dem":237,
    "gn:feature_class":"P",
    "gn:feature_code":"PPL",
    "gn:name":"Prokhladnyy",
    "gn:population":0,
    "gn:timezone":"Europe/Moscow",
    "iso:country":"RU",
    "name:rus_x_preferred":[
        "\u041f\u0440\u043e\u0445\u043b\u0430\u0434\u043d\u044b\u0439"
    ],
    "wof:name":"Prokhladnyy",
    "wof:placetype":"locality"
},
  "geometry": {"coordinates":[40.70056,44.71278],"type":"Point"}
}