{
  "type": "Feature",
  "properties": {
    "gn:admin1_code":"33.0",
    "gn:asciiname":"Sidorkino",
    "gn:country_code":"RU",
    "gn:dem":128,
    "gn:feature_class":"P",
    "gn:feature_code":"PPL",
    "gn:name":"Sidorkino",
    "gn:population":0,
    "gn:timezone":"Europe/Kirov",
    "iso:country":"RU",
    "name:rus_x_preferred":[
        "\u0421\u0438\u0434\u043e\u0440\u043a\u0438\u043d\u043e"
    ],
    "wof:name":"Sidorkino",
    "wof:placetype":"locality"
},
  "geometry": {"coordinates":[48.37197000000001,57.34015],"type":"Point"}
}