{
  "type": "Feature",
  "properties": {
    "gn:admin1_code":"60.0",
    "gn:asciiname":"Rat'kovo",
    "gn:country_code":"RU",
    "gn:dem":158,
    "gn:feature_class":"P",
    "gn:feature_code":"PPL",
    "gn:name":"Rat\u2019kovo",
    "gn:population":0,
    "gn:timezone":"Europe/Moscow",
    "iso:country":"RU",
    "name:rus_x_preferred":[
        "\u0420\u0430\u0442\u044c\u043a\u043e\u0432\u043e"
    ],
    "name:und_x_variant":[
        "Rat\u2019kovo"
    ],
    "wof:name":"Rat'kovo",
    "wof:placetype":"locality"
},
  "geometry": {"coordinates":[29.59702,55.95067],"type":"Point"}
}