{
  "type": "Feature",
  "properties": {
    "gn:admin1_code":"56",
    "gn:asciiname":"Goncharovy Dvory",
    "gn:country_code":"RU",
    "gn:dem":244,
    "gn:feature_class":"P",
    "gn:feature_code":"PPL",
    "gn:name":"Goncharovy Dvory",
    "gn:population":0,
    "gn:timezone":"Europe/Moscow",
    "iso:country":"RU",
    "name:rus_x_preferred":[
        "\u0413\u043e\u043d\u0447\u0430\u0440\u043e\u0432\u044b \u0414\u0432\u043e\u0440\u044b"
    ],
    "wof:name":"Goncharovy Dvory",
    "wof:placetype":"locality"
},
  "geometry": {"coordinates":[36.91667,52.71666999999999],"type":"Point"}
}