{
  "type": "Feature",
  "properties": {
    "gn:admin1_code":"10",
    "gn:asciiname":"Barsuki",
    "gn:country_code":"RU",
    "gn:dem":196,
    "gn:feature_class":"P",
    "gn:feature_code":"PPL",
    "gn:name":"Barsuki",
    "gn:population":0,
    "gn:timezone":"Europe/Moscow",
    "iso:country":"RU",
    "name:nor_x_preferred":[
        "Barsuki"
    ],
    "name:rus_x_preferred":[
        "\u0411\u0430\u0440\u0441\u0443\u043a\u0438"
    ],
    "wof:name":"Barsuki",
    "wof:placetype":"locality"
},
  "geometry": {"coordinates":[33.95194,53.31972],"type":"Point"}
}