{
  "type": "Feature",
  "properties": {
    "gn:admin1_code":"38.0",
    "gn:asciiname":"Bocharov",
    "gn:country_code":"RU",
    "gn:dem":309,
    "gn:feature_class":"P",
    "gn:feature_code":"PPL",
    "gn:name":"Bocharov",
    "gn:population":0,
    "gn:timezone":"Europe/Moscow",
    "iso:country":"RU",
    "name:rus_x_preferred":[
        "\u0411\u043e\u0447\u0430\u0440\u043e\u0432"
    ],
    "name:und_x_variant":[
        "Bocharoz",
        "Bocharov",
        "\u0411\u043e\u0447\u0430\u0440\u043e\u0432"
    ],
    "wof:name":"Bocharov",
    "wof:placetype":"locality"
},
  "geometry": {"coordinates":[41.0604,44.6758],"type":"Point"}
}