{
  "type": "Feature",
  "properties": {
    "gn:admin1_code":"51",
    "gn:asciiname":"Kochevatovo",
    "gn:country_code":"RU",
    "gn:dem":89,
    "gn:feature_class":"P",
    "gn:feature_code":"PPL",
    "gn:name":"Kochevatovo",
    "gn:population":0,
    "gn:timezone":"Europe/Moscow",
    "iso:country":"RU",
    "name:rus_x_preferred":[
        "\u041a\u043e\u0447\u0435\u0432\u0430\u0442\u043e\u0432\u043e"
    ],
    "wof:name":"Kochevatovo",
    "wof:placetype":"locality"
},
  "geometry": {"coordinates":[45.3561,57.0811],"type":"Point"}
}