{
  "type": "Feature",
  "properties": {
    "gn:admin1_code":"60",
    "gn:asciiname":"Vashkovka",
    "gn:country_code":"RU",
    "gn:dem":88,
    "gn:feature_class":"P",
    "gn:feature_code":"PPL",
    "gn:name":"Vashkovka",
    "gn:population":0,
    "gn:timezone":"Europe/Moscow",
    "iso:country":"RU",
    "name:rus_x_preferred":[
        "\u0412\u0430\u0448\u043a\u043e\u0432\u043a\u0430"
    ],
    "wof:name":"Vashkovka",
    "wof:placetype":"locality"
},
  "geometry": {"coordinates":[28.44752,56.96709],"type":"Point"}
}