{
  "type": "Feature",
  "properties": {
    "gn:admin1_code":"52",
    "gn:asciiname":"Latyshskoye Ogorovo",
    "gn:country_code":"RU",
    "gn:dem":45,
    "gn:feature_class":"P",
    "gn:feature_code":"PPL",
    "gn:name":"Latyshskoye Ogorovo",
    "gn:population":0,
    "gn:timezone":"Europe/Moscow",
    "iso:country":"RU",
    "name:rus_x_preferred":[
        "\u041b\u0430\u0442\u044b\u0448\u0441\u043a\u043e\u0435 \u041e\u0433\u043e\u0440\u043e\u0432\u043e"
    ],
    "wof:name":"Latyshskoye Ogorovo",
    "wof:placetype":"locality"
},
  "geometry": {"coordinates":[32.15,59.23333],"type":"Point"}
}