{
  "type": "Feature",
  "properties": {
    "gn:admin1_code":"61.0",
    "gn:asciiname":"Kulugury",
    "gn:country_code":"RU",
    "gn:dem":76,
    "gn:feature_class":"P",
    "gn:feature_code":"PPL",
    "gn:name":"Kulugury",
    "gn:population":0,
    "gn:timezone":"Europe/Moscow",
    "iso:country":"RU",
    "name:rus_x_preferred":[
        "\u041a\u0443\u043b\u0443\u0433\u0443\u0440\u044b"
    ],
    "wof:name":"Kulugury",
    "wof:placetype":"locality"
},
  "geometry": {"coordinates":[40.98569000000001,49.0259],"type":"Point"}
}