{
  "type": "Feature",
  "properties": {
    "gn:admin1_code":"33",
    "gn:asciiname":"Savvichi",
    "gn:country_code":"RU",
    "gn:dem":144,
    "gn:feature_class":"P",
    "gn:feature_code":"PPL",
    "gn:name":"Savvichi",
    "gn:population":0,
    "gn:timezone":"Europe/Kirov",
    "iso:country":"RU",
    "name:rus_x_preferred":[
        "\u0421\u0430\u0432\u0432\u0438\u0447\u0438"
    ],
    "name:und_x_variant":[
        "\u0421\u0430\u0432\u0432\u0438\u0447\u0438"
    ],
    "wof:name":"Savvichi",
    "wof:placetype":"locality"
},
  "geometry": {"coordinates":[48.86436,58.28826],"type":"Point"}
}