{
  "type": "Feature",
  "properties": {
    "gn:admin1_code":"60",
    "gn:asciiname":"Oreshkovo",
    "gn:country_code":"RU",
    "gn:dem":99,
    "gn:feature_class":"P",
    "gn:feature_code":"PPL",
    "gn:name":"Oreshkovo",
    "gn:population":0,
    "gn:timezone":"Europe/Moscow",
    "iso:country":"RU",
    "name:rus_x_preferred":[
        "\u041e\u0440\u0435\u0448\u043a\u043e\u0432\u043e"
    ],
    "name:und_x_variant":[
        "\u041e\u0440\u0435\u0448\u043a\u043e\u0432\u043e"
    ],
    "wof:name":"Oreshkovo",
    "wof:placetype":"locality"
},
  "geometry": {"coordinates":[30.18174,56.86836],"type":"Point"}
}