{
  "type": "Feature",
  "properties": {
    "gn:admin1_code":"83",
    "gn:asciiname":"Yelkhovka",
    "gn:country_code":"RU",
    "gn:dem":141,
    "gn:feature_class":"P",
    "gn:feature_code":"PPL",
    "gn:name":"Yelkhovka",
    "gn:population":0,
    "gn:timezone":"Europe/Moscow",
    "iso:country":"RU",
    "name:rus_x_preferred":[
        "\u0415\u043b\u0445\u043e\u0432\u043a\u0430"
    ],
    "wof:name":"Yelkhovka",
    "wof:placetype":"locality"
},
  "geometry": {"coordinates":[39.9374,56.20563000000001],"type":"Point"}
}