{
  "type": "Feature",
  "properties": {
    "gn:admin1_code":"45.0",
    "gn:asciiname":"Mari-Orsha",
    "gn:country_code":"RU",
    "gn:dem":173,
    "gn:feature_class":"P",
    "gn:feature_code":"PPL",
    "gn:name":"Mari-Orsha",
    "gn:population":0,
    "gn:timezone":"Europe/Moscow",
    "iso:country":"RU",
    "name:rus_x_preferred":[
        "\u041c\u0430\u0440\u0438-\u041e\u0440\u0448\u0430"
    ],
    "wof:name":"Mari-Orsha",
    "wof:placetype":"locality"
},
  "geometry": {"coordinates":[48.49778,56.8975],"type":"Point"}
}