{
  "type": "Feature",
  "properties": {
    "gn:country":"RU",
    "gn:fcode":"PPL",
    "gn:pop":914,
    "iso:country":"RU",
    "name:rus_x_preferred":[
        "\u041a\u0438\u043f\u0430\u0440\u0438\u0441\u043e\u0432\u043e-\u041f\u0435\u0440\u0432\u043e\u0435"
    ],
    "name:unk_x_variant":[
        "Kiparisovo Odin"
    ],
    "qs:name":"Kiparisovo",
    "qs:photos_9r":0,
    "qs:photos_sr":0,
    "qs:pop_sr":"2",
    "wd:wordcount":1060,
    "wof:name":"Kiparisovo",
    "wof:placetype":"locality",
    "wof:population":914
},
  "geometry": {"coordinates":[131.92250000000001,43.4782],"type":"Point"}
}