{
  "type": "Feature",
  "properties": {
    "gn:country":"RU",
    "gn:fcode":"PPL",
    "gn:population":914,
    "iso:country":"RU",
    "name:che_x_preferred":[
        "\u041d\u0430\u0434\u0435\u0436\u0434\u0438\u043d\u0441\u043a\u0430\u043d \u043a\u04c0\u043e\u0448\u0442"
    ],
    "name:deu_x_preferred":[
        "Nadeschdinski rajon"
    ],
    "name:eng_x_preferred":[
        "Nadezhdinsky District"
    ],
    "name:est_x_preferred":[
        "Nade\u017edinski rajoon"
    ],
    "name:fra_x_preferred":[
        "Nadezhdinsky"
    ],
    "name:hun_x_preferred":[
        "Nagyezsgyinszkojei j\u00e1r\u00e1s"
    ],
    "name:hye_x_preferred":[
        "\u0546\u0561\u0564\u0565\u056a\u0564\u056b\u0576\u057d\u056f\u056b \u0577\u0580\u057b\u0561\u0576"
    ],
    "name:ita_x_preferred":[
        "Nade\u017edinskij rajon"
    ],
    "name:jpn_x_preferred":[
        "\u30ca\u30b8\u30a7\u30b8\u30b8\u30f3\u30b9\u30b3\u30a8\u5730\u533a"
    ],
    "name:kor_x_preferred":[
        "\ub098\ub370\uc988\ub518\uc2a4\ud0a4 \uad70"
    ],
    "name:nld_x_preferred":[
        "Nadezjdinskiy rayon"
    ],
    "name:rus_x_preferred":[
        "\u041a\u0438\u043f\u0430\u0440\u0438\u0441\u043e\u0432\u043e-\u041f\u0435\u0440\u0432\u043e\u0435"
    ],
    "name:rus_x_variant":[
        "\u041d\u0430\u0434\u0435\u0436\u0434\u0438\u043d\u0441\u043a\u0438\u0439 \u0440\u0430\u0439\u043e\u043d"
    ],
    "name:sco_x_preferred":[
        "Nadezhdinsky Destrict"
    ],
    "name:tat_x_preferred":[
        "\u041d\u0430\u0434\u0435\u0436\u0434\u0438\u043d\u0441\u043a\u0438 \u0440\u0430\u0439\u043e\u043d\u044b"
    ],
    "name:ukr_x_preferred":[
        "\u041d\u0430\u0434\u0435\u0436\u0434\u0438\u043d\u0441\u044c\u043a\u0438\u0439 \u0440\u0430\u0439\u043e\u043d"
    ],
    "name:und_x_variant":[
        "Kiparisovo Odin"
    ],
    "name:vie_x_preferred":[
        "Nadezhdinsky"
    ],
    "name:zho_x_preferred":[
        "\u7d0d\u5091\u65e5\u91d1\u65af\u57fa\u5340"
    ],
    "qs:name":"Kiparisovo",
    "qs:photos_9r":0,
    "qs:photos_sr":0,
    "qs:pop_sr":"2",
    "wd:wordcount":1060,
    "wof:name":"Kiparisovo",
    "wof:placetype":"locality",
    "wof:population":914
},
  "geometry": {"coordinates":[131.92250000000001,43.4782],"type":"Point"}
}