{
  "type": "Feature",
  "properties": {
    "gn:admin1_code":"67.0",
    "gn:asciiname":"Chernobulak",
    "gn:country_code":"RU",
    "gn:dem":264,
    "gn:feature_class":"P",
    "gn:feature_code":"PPL",
    "gn:name":"Chernobulak",
    "gn:population":0,
    "gn:timezone":"Europe/Saratov",
    "iso:country":"RU",
    "name:rus_x_preferred":[
        "\u0427\u0435\u0440\u043d\u043e\u0431\u0443\u043b\u0430\u043a"
    ],
    "wof:name":"Chernobulak",
    "wof:placetype":"locality"
},
  "geometry": {"coordinates":[46.50918,52.65431],"type":"Point"}
}