{
  "type": "Feature",
  "properties": {
    "gn:admin1_code":"29",
    "gn:asciiname":"Novyy Vostok",
    "gn:country_code":"RU",
    "gn:dem":112,
    "gn:feature_class":"P",
    "gn:feature_code":"PPL",
    "gn:name":"Novyy Vostok",
    "gn:population":0,
    "gn:timezone":"Asia/Novokuznetsk",
    "iso:country":"RU",
    "name:rus_x_preferred":[
        "\u041d\u043e\u0432\u044b\u0439 \u0412\u043e\u0441\u0442\u043e\u043a"
    ],
    "name:und_x_variant":[
        "\u041d\u043e\u0432\u044b\u0439 \u0412\u043e\u0441\u0442\u043e\u043a"
    ],
    "wof:name":"Novyy Vostok",
    "wof:placetype":"locality"
},
  "geometry": {"coordinates":[84.96666999999999,55.88333000000001],"type":"Point"}
}