{
  "type": "Feature",
  "properties": {
    "gn:admin1_code":"88",
    "gn:asciiname":"Koskino",
    "gn:country_code":"RU",
    "gn:dem":186,
    "gn:feature_class":"P",
    "gn:feature_code":"PPL",
    "gn:name":"Koskino",
    "gn:population":0,
    "gn:timezone":"Europe/Moscow",
    "iso:country":"RU",
    "name:rus_x_preferred":[
        "\u041a\u043e\u0441\u043a\u0438\u043d\u043e"
    ],
    "wof:name":"Koskino",
    "wof:placetype":"locality"
},
  "geometry": {"coordinates":[39.15255,57.17902],"type":"Point"}
}