{
  "type": "Feature",
  "properties": {
    "gn:admin1_code":"61",
    "gn:asciiname":"Khudyakov",
    "gn:cc2":"RU",
    "gn:country_code":"RU",
    "gn:dem":70,
    "gn:feature_class":"P",
    "gn:feature_code":"PPL",
    "gn:name":"Khudyakov",
    "gn:population":0,
    "gn:timezone":"Europe/Moscow",
    "iso:country":"RU",
    "name:eng_x_preferred":[
        "Khudyakov"
    ],
    "name:nor_x_preferred":[
        "Khudjakov"
    ],
    "name:rus_x_preferred":[
        "\u0425\u0443\u0434\u044f\u043a\u043e\u0432"
    ],
    "name:und_x_variant":[
        "Khudyakovskiy",
        "\u0425\u0443\u0434\u044f\u043a\u043e\u0432",
        "Khudyakov"
    ],
    "wof:name":"Khudyakov",
    "wof:placetype":"locality"
},
  "geometry": {"coordinates":[41.08222,48.13194],"type":"Point"}
}