{
  "type": "Feature",
  "properties": {
    "gn:admin1_code":"45",
    "gn:asciiname":"Kuplonga",
    "gn:country_code":"RU",
    "gn:dem":97,
    "gn:feature_class":"P",
    "gn:feature_code":"PPL",
    "gn:name":"Kuplonga",
    "gn:population":0,
    "gn:timezone":"Europe/Moscow",
    "iso:country":"RU",
    "name:eng_x_preferred":[
        "Kuplonga"
    ],
    "name:nor_x_preferred":[
        "Kuplonga"
    ],
    "name:rus_x_preferred":[
        "\u041a\u0443\u043f\u043b\u043e\u043d\u0433\u0430"
    ],
    "name:und_x_variant":[
        "Bol\u2019shaya Kuplonga"
    ],
    "wof:name":"Kuplonga",
    "wof:placetype":"locality"
},
  "geometry": {"coordinates":[47.07785,56.40302],"type":"Point"}
}