{
  "type": "Feature",
  "properties": {
    "gn:admin1_code":"43",
    "gn:asciiname":"Arsenovka",
    "gn:country_code":"RU",
    "gn:dem":213,
    "gn:feature_class":"P",
    "gn:feature_code":"PPL",
    "gn:name":"Arsenovka",
    "gn:population":0,
    "gn:timezone":"Europe/Moscow",
    "iso:country":"RU",
    "name:rus_x_preferred":[
        "\u0410\u0440\u0441\u0435\u043d\u043e\u0432\u043a\u0430"
    ],
    "name:und_x_variant":[
        "\u0410\u0440\u0441\u0435\u043d\u043e\u0432\u043a\u0430"
    ],
    "wof:name":"Arsenovka",
    "wof:placetype":"locality"
},
  "geometry": {"coordinates":[39.2923,53.3554],"type":"Point"}
}