{
  "type": "Feature",
  "properties": {
    "gn:admin1_code":"21",
    "gn:asciiname":"Popkovo",
    "gn:country_code":"RU",
    "gn:dem":153,
    "gn:feature_class":"P",
    "gn:feature_code":"PPL",
    "gn:name":"Popkovo",
    "gn:population":0,
    "gn:timezone":"Europe/Moscow",
    "iso:country":"RU",
    "name:rus_x_preferred":[
        "\u041f\u043e\u043f\u043a\u043e\u0432\u043e"
    ],
    "name:und_x_variant":[
        "Popkova",
        "Popkovo"
    ],
    "wof:name":"Popkovo",
    "wof:placetype":"locality"
},
  "geometry": {"coordinates":[41.45493,57.43178],"type":"Point"}
}