{
  "type": "Feature",
  "properties": {
    "gn:admin1_code":"33",
    "gn:asciiname":"Kruglyye Polyanki",
    "gn:country_code":"RU",
    "gn:dem":106,
    "gn:feature_class":"P",
    "gn:feature_code":"PPL",
    "gn:name":"Kruglyye Polyanki",
    "gn:population":0,
    "gn:timezone":"Europe/Kirov",
    "iso:country":"RU",
    "name:rus_x_preferred":[
        "\u041a\u0440\u0443\u0433\u043b\u044b\u0435 \u041f\u043e\u043b\u044f\u043d\u043a\u0438"
    ],
    "name:und_x_variant":[
        "Kruglyye Polyany",
        "Kruglyye Polyanki"
    ],
    "wof:name":"Kruglyye Polyanki",
    "wof:placetype":"locality"
},
  "geometry": {"coordinates":[49.97357,57.346],"type":"Point"}
}