{
  "type": "Feature",
  "properties": {
    "gn:admin1_code":"37",
    "gn:asciiname":"Yelizarovo",
    "gn:country_code":"RU",
    "gn:dem":157,
    "gn:feature_class":"P",
    "gn:feature_code":"PPL",
    "gn:name":"Yelizarovo",
    "gn:population":0,
    "gn:timezone":"Europe/Moscow",
    "iso:country":"RU",
    "name:eng_x_preferred":[
        "Yelizarovo"
    ],
    "name:nor_x_preferred":[
        "Jelizarovo"
    ],
    "name:rus_x_preferred":[
        "\u0415\u043b\u0438\u0437\u0430\u0440\u043e\u0432\u043e"
    ],
    "wof:name":"Yelizarovo",
    "wof:placetype":"locality"
},
  "geometry": {"coordinates":[44.81619,58.53856999999999],"type":"Point"}
}