{
  "type": "Feature",
  "properties": {
    "gn:admin1_code":"75",
    "gn:asciiname":"Vakhtovyy Poselok Pervomayskiy",
    "gn:country_code":"RU",
    "gn:dem":94,
    "gn:feature_class":"P",
    "gn:feature_code":"PPL",
    "gn:name":"Vakhtovyy Pos\u00eblok Pervomayskiy",
    "gn:population":0,
    "gn:timezone":"Asia/Tomsk",
    "iso:country":"RU",
    "name:rus_x_preferred":[
        "\u0412\u0430\u0445\u0442\u043e\u0432\u044b\u0439 \u041f\u043e\u0441\u0451\u043b\u043e\u043a \u041f\u0435\u0440\u0432\u043e\u043c\u0430\u0439\u0441\u043a\u0438\u0439"
    ],
    "name:und_x_variant":[
        "Vakhtovyy Pos\u00eblok Pervomayskiy",
        "\u0412\u0430\u0445\u0442\u043e\u0432\u044b\u0439 \u041f\u043e\u0441\u0451\u043b\u043e\u043a \u041f\u0435\u0440\u0432\u043e\u043c\u0430\u0439\u0441\u043a\u0438\u0439"
    ],
    "wof:name":"Vakhtovyy Poselok Pervomayskiy",
    "wof:placetype":"locality"
},
  "geometry": {"coordinates":[75.81489999999999,59.1927],"type":"Point"}
}