{
  "type": "Feature",
  "properties": {
    "gn:admin1_code":"47",
    "gn:asciiname":"Luker'ino",
    "gn:country_code":"RU",
    "gn:dem":120,
    "gn:feature_class":"P",
    "gn:feature_code":"PPL",
    "gn:name":"Luker\u2019ino",
    "gn:population":0,
    "gn:timezone":"Europe/Moscow",
    "iso:country":"RU",
    "name:rus_x_preferred":[
        "\u041b\u0443\u043a\u0435\u0440\u044c\u0438\u043d\u043e"
    ],
    "name:und_x_variant":[
        "Luker\u2019ino"
    ],
    "wof:name":"Luker'ino",
    "wof:placetype":"locality"
},
  "geometry": {"coordinates":[38.64758,55.10169000000001],"type":"Point"}
}