{
  "type": "Feature",
  "properties": {
    "gn:admin1_code":"29",
    "gn:asciiname":"Kistal",
    "gn:country_code":"RU",
    "gn:dem":595,
    "gn:feature_class":"P",
    "gn:feature_code":"PPL",
    "gn:name":"Kistal",
    "gn:population":0,
    "gn:timezone":"Asia/Novokuznetsk",
    "iso:country":"RU",
    "name:eng_x_preferred":[
        "Kistal"
    ],
    "name:nor_x_preferred":[
        "Kistal"
    ],
    "name:rus_x_preferred":[
        "\u041a\u0438\u0441\u0442\u0430\u043b"
    ],
    "name:und_x_variant":[
        "\u041a\u0438\u0441\u0442\u0430\u043b",
        "Kistal"
    ],
    "wof:name":"Kistal",
    "wof:placetype":"locality"
},
  "geometry": {"coordinates":[87.48333000000002,52.75],"type":"Point"}
}