{
  "type": "Feature",
  "properties": {
    "gn:admin1_code":"84.0",
    "gn:asciiname":"Irnyy",
    "gn:country_code":"RU",
    "gn:dem":160,
    "gn:feature_class":"P",
    "gn:feature_code":"PPL",
    "gn:name":"Irnyy",
    "gn:population":0,
    "gn:timezone":"Europe/Volgograd",
    "iso:country":"RU",
    "name:eng_x_preferred":[
        "Irnyy"
    ],
    "name:nor_x_preferred":[
        "Mirnyj"
    ],
    "name:rus_x_preferred":[
        "\u041c\u0438\u0440\u043d\u044b\u0439"
    ],
    "name:und_x_variant":[
        "\u0418\u0440\u043d\u044b\u0439"
    ],
    "wof:name":"Irnyy",
    "wof:placetype":"locality"
},
  "geometry": {"coordinates":[42.82222,51.185],"type":"Point"}
}