{
  "type": "Feature",
  "properties": {
    "gn:admin1_code":"60",
    "gn:asciiname":"Usadishche",
    "gn:country_code":"RU",
    "gn:dem":68,
    "gn:feature_class":"P",
    "gn:feature_code":"PPL",
    "gn:name":"Usadishche",
    "gn:population":0,
    "gn:timezone":"Europe/Moscow",
    "iso:country":"RU",
    "name:rus_x_preferred":[
        "\u0423\u0441\u0430\u0434\u0438\u0449\u0435"
    ],
    "wof:name":"Usadishche",
    "wof:placetype":"locality"
},
  "geometry": {"coordinates":[28.53537,57.3508],"type":"Point"}
}