{
  "type": "Feature",
  "properties": {
    "gn:admin1_code":"71",
    "gn:asciiname":"Shumikha",
    "gn:country_code":"RU",
    "gn:dem":348,
    "gn:feature_class":"P",
    "gn:feature_code":"PPL",
    "gn:name":"Shumikha",
    "gn:population":0,
    "gn:timezone":"Asia/Yekaterinburg",
    "iso:country":"RU",
    "name:rus_x_preferred":[
        "\u0428\u0443\u043c\u0438\u0445\u0430"
    ],
    "name:und_x_variant":[
        "\u0428\u0443\u043c\u0438\u0445\u0430"
    ],
    "wof:name":"Shumikha",
    "wof:placetype":"locality"
},
  "geometry": {"coordinates":[59.68333000000001,58.08333],"type":"Point"}
}