{
  "type": "Feature",
  "properties": {
    "gn:admin1_code":"69",
    "gn:asciiname":"Kotiki",
    "gn:country_code":"RU",
    "gn:dem":211,
    "gn:feature_class":"P",
    "gn:feature_code":"PPL",
    "gn:name":"Kotiki",
    "gn:population":0,
    "gn:timezone":"Europe/Moscow",
    "iso:country":"RU",
    "name:rus_x_preferred":[
        "\u041a\u043e\u0442\u0438\u043a\u0438"
    ],
    "wof:name":"Kotiki",
    "wof:placetype":"locality"
},
  "geometry": {"coordinates":[32.79639,55.60694],"type":"Point"}
}