{
  "type": "Feature",
  "properties": {
    "gn:admin1_code":"55",
    "gn:asciiname":"Solov'yev",
    "gn:country_code":"RU",
    "gn:dem":96,
    "gn:feature_class":"P",
    "gn:feature_code":"PPL",
    "gn:name":"Solov\u2019y\u00ebv",
    "gn:population":0,
    "gn:timezone":"Asia/Yekaterinburg",
    "iso:country":"RU",
    "name:rus_x_preferred":[
        "\u0421\u043e\u043b\u043e\u0432\u044c\u0451\u0432"
    ],
    "name:und_x_variant":[
        "Solov\u2019y\u00ebvskiy",
        "Solov\u2019y\u00ebv",
        "\u0421\u043e\u043b\u043e\u0432\u044c\u0451\u0432"
    ],
    "wof:name":"Solov'yev",
    "wof:placetype":"locality"
},
  "geometry": {"coordinates":[53.56028000000001,51.79389000000001],"type":"Point"}
}