{
  "type": "Feature",
  "properties": {
    "gn:admin1_code":"47",
    "gn:asciiname":"Kobyakovo",
    "gn:country_code":"RU",
    "gn:dem":187,
    "gn:feature_class":"P",
    "gn:feature_code":"PPL",
    "gn:name":"Kobyakovo",
    "gn:population":0,
    "gn:timezone":"Europe/Moscow",
    "iso:country":"RU",
    "name:rus_x_preferred":[
        "\u041a\u043e\u0431\u044f\u043a\u043e\u0432\u043e"
    ],
    "name:und_x_variant":[
        "\u041a\u043e\u0431\u044f\u043a\u043e\u0432\u043e"
    ],
    "wof:name":"Kobyakovo",
    "wof:placetype":"locality"
},
  "geometry": {"coordinates":[37.00418,55.59408000000001],"type":"Point"}
}