{
  "type": "Feature",
  "properties": {
    "gn:admin1_code":"6",
    "gn:asciiname":"Zadnyaya",
    "gn:country_code":"RU",
    "gn:dem":16,
    "gn:feature_class":"P",
    "gn:feature_code":"PPL",
    "gn:name":"Zadnyaya",
    "gn:population":0,
    "gn:timezone":"Europe/Moscow",
    "iso:country":"RU",
    "name:rus_x_preferred":[
        "\u0417\u0430\u0434\u043d\u044f\u044f"
    ],
    "wof:name":"Zadnyaya",
    "wof:placetype":"locality"
},
  "geometry": {"coordinates":[41.9681,63.5434],"type":"Point"}
}