{
  "type": "Feature",
  "properties": {
    "gn:admin1_code":"20.0",
    "gn:asciiname":"Malomoleva",
    "gn:country_code":"RU",
    "gn:dem":556,
    "gn:feature_class":"P",
    "gn:feature_code":"PPL",
    "gn:name":"Malomol\u00ebva",
    "gn:population":0,
    "gn:timezone":"Asia/Irkutsk",
    "iso:country":"RU",
    "name:rus_x_preferred":[
        "\u041c\u0430\u043b\u043e\u043c\u043e\u043b\u0451\u0432\u0430"
    ],
    "name:und_x_variant":[
        "Malomol\u00ebva"
    ],
    "wof:name":"Malomoleva",
    "wof:placetype":"locality"
},
  "geometry": {"coordinates":[102.8323,53.4017],"type":"Point"}
}