{
  "type": "Feature",
  "properties": {
    "gn:admin1_code":"64",
    "gn:asciiname":"Kryuchevoye",
    "gn:cc2":"RU",
    "gn:country_code":"RU",
    "gn:dem":7,
    "gn:feature_class":"P",
    "gn:feature_code":"PPL",
    "gn:name":"Kryuchevoye",
    "gn:population":0,
    "gn:timezone":"Asia/Sakhalin",
    "iso:country":"RU",
    "name:rus_x_preferred":[
        "\u041a\u0440\u044e\u0447\u0435\u0432\u043e\u0435"
    ],
    "name:und_x_variant":[
        "T\u014dhoku",
        "Kryuchevoye"
    ],
    "wof:name":"Kryuchevoye",
    "wof:placetype":"locality"
},
  "geometry": {"coordinates":[141.88333,46.43333],"type":"Point"}
}