{
  "type": "Feature",
  "properties": {
    "gn:admin1_code":"83",
    "gn:asciiname":"Novovladimirovka",
    "gn:country_code":"RU",
    "gn:dem":140,
    "gn:feature_class":"P",
    "gn:feature_code":"PPL",
    "gn:name":"Novovladimirovka",
    "gn:population":0,
    "gn:timezone":"Europe/Moscow",
    "iso:country":"RU",
    "name:nor_x_preferred":[
        "Novovladimirovka"
    ],
    "name:rus_x_preferred":[
        "\u041d\u043e\u0432\u043e\u0432\u043b\u0430\u0434\u0438\u043c\u0438\u0440\u043e\u0432\u043a\u0430"
    ],
    "name:und_x_variant":[
        "Novaya Vladimirka",
        "Vladimirovka",
        "Novaya Vladimirovka"
    ],
    "wof:name":"Novovladimirovka",
    "wof:placetype":"locality"
},
  "geometry": {"coordinates":[42.60716,56.14579000000001],"type":"Point"}
}