{
  "type": "Feature",
  "properties": {
    "gn:admin1_code":"38",
    "gn:asciiname":"Kubanskaya Step'",
    "gn:country_code":"RU",
    "gn:dem":33,
    "gn:feature_class":"P",
    "gn:feature_code":"PPL",
    "gn:name":"Kubanskaya Step\u2019",
    "gn:population":0,
    "gn:timezone":"Europe/Moscow",
    "iso:country":"RU",
    "name:eng_x_preferred":[
        "Kubanskaya Step'"
    ],
    "name:nor_x_preferred":[
        "Kubanskaja-Step"
    ],
    "name:rus_x_preferred":[
        "\u041a\u0443\u0431\u0430\u043d\u0441\u043a\u0430\u044f-\u0421\u0442\u0435\u043f\u044c"
    ],
    "name:rus_x_variant":[
        "\u041a\u0443\u0431\u0430\u043d\u0441\u043a\u0430\u044f \u0421\u0442\u0435\u043f\u044c"
    ],
    "name:und_x_variant":[
        "Kubanskaya Step\u2019"
    ],
    "wof:name":"Kubanskaya Step'",
    "wof:placetype":"locality"
},
  "geometry": {"coordinates":[39.22904000000001,45.96611],"type":"Point"}
}