{
  "type": "Feature",
  "properties": {
    "gn:admin1_code":"21.0",
    "gn:asciiname":"Parshino",
    "gn:country_code":"RU",
    "gn:dem":115,
    "gn:feature_class":"P",
    "gn:feature_code":"PPL",
    "gn:name":"Parshino",
    "gn:population":0,
    "gn:timezone":"Europe/Moscow",
    "iso:country":"RU",
    "name:nor_x_preferred":[
        "Parsjino"
    ],
    "name:rus_x_preferred":[
        "\u041f\u0430\u0440\u0448\u0438\u043d\u043e"
    ],
    "wof:name":"Parshino",
    "wof:placetype":"locality"
},
  "geometry": {"coordinates":[42.65375,56.73289000000001],"type":"Point"}
}