{
  "type": "Feature",
  "properties": {
    "gn:admin1_code":"77",
    "gn:asciiname":"Rayevskoye",
    "gn:country_code":"RU",
    "gn:dem":154,
    "gn:feature_class":"P",
    "gn:feature_code":"PPL",
    "gn:name":"Rayevskoye",
    "gn:population":0,
    "gn:timezone":"Europe/Moscow",
    "iso:country":"RU",
    "name:eng_x_preferred":[
        "Rayevskoye"
    ],
    "name:nor_x_preferred":[
        "Rajevskoje"
    ],
    "name:rus_x_preferred":[
        "\u0420\u0430\u0435\u0432\u0441\u043a\u043e\u0435"
    ],
    "wof:name":"Rayevskoye",
    "wof:placetype":"locality"
},
  "geometry": {"coordinates":[35.58083,57.87806],"type":"Point"}
}