{
  "type": "Feature",
  "properties": {
    "gn:admin1_code":"10",
    "gn:asciiname":"Fanzonovshchina",
    "gn:country_code":"RU",
    "gn:dem":141,
    "gn:feature_class":"P",
    "gn:feature_code":"PPL",
    "gn:name":"Fanzonovshchina",
    "gn:population":0,
    "gn:timezone":"Europe/Moscow",
    "iso:country":"RU",
    "name:rus_x_preferred":[
        "\u0424\u0430\u043d\u0437\u043e\u043d\u043e\u0432\u0449\u0438\u043d\u0430"
    ],
    "wof:name":"Fanzonovshchina",
    "wof:placetype":"locality"
},
  "geometry": {"coordinates":[31.9508,52.7877],"type":"Point"}
}