{
  "type": "Feature",
  "properties": {
    "gn:admin1_code":"53",
    "gn:asciiname":"Mirnyy",
    "gn:country_code":"RU",
    "gn:dem":201,
    "gn:feature_class":"P",
    "gn:feature_code":"PPL",
    "gn:name":"Mirnyy",
    "gn:population":0,
    "gn:timezone":"Asia/Novosibirsk",
    "iso:country":"RU",
    "name:rus_x_preferred":[
        "\u041c\u0438\u0440\u043d\u044b\u0439"
    ],
    "name:und_x_variant":[
        "\u041c\u0438\u0440\u043d\u044b\u0439"
    ],
    "wof:name":"Mirnyy",
    "wof:placetype":"locality"
},
  "geometry": {"coordinates":[83.65000000000001,55.01667],"type":"Point"}
}