{
  "type": "Feature",
  "properties": {
    "gn:admin1_code":"47",
    "gn:asciiname":"Gol'nyy Bugor",
    "gn:country_code":"RU",
    "gn:dem":102,
    "gn:feature_class":"P",
    "gn:feature_code":"PPL",
    "gn:name":"Gol\u2019nyy Bugor",
    "gn:population":0,
    "gn:timezone":"Europe/Moscow",
    "iso:country":"RU",
    "name:rus_x_preferred":[
        "\u0413\u043e\u043b\u044c\u043d\u044b\u0439 \u0411\u0443\u0433\u043e\u0440"
    ],
    "name:und_x_variant":[
        "Nagol\u2019nyy Bugor",
        "Sovkhoz Nagol\u2019nyy Bugor",
        "Gol\u2019nyy Bugor",
        "\u0413\u043e\u043b\u044c\u043d\u044b\u0439 \u0411\u0443\u0433\u043e\u0440"
    ],
    "wof:name":"Gol'nyy Bugor",
    "wof:placetype":"locality"
},
  "geometry": {"coordinates":[39.28778,55.03333000000001],"type":"Point"}
}