{
  "type": "Feature",
  "properties": {
    "gn:admin1_code":"42",
    "gn:asciiname":"Sarkyula",
    "gn:country_code":"RU",
    "gn:dem":6,
    "gn:feature_class":"P",
    "gn:feature_code":"PPL",
    "gn:name":"Sarkyula",
    "gn:population":0,
    "gn:timezone":"Europe/Moscow",
    "iso:country":"RU",
    "name:fin_x_preferred":[
        "Saarkyl\u00e4"
    ],
    "name:rus_x_preferred":[
        "\u0421\u0430\u0440\u043a\u0443\u043b\u044c"
    ],
    "name:rus_x_variant":[
        "\u0421\u0430\u0440\u043a\u044e\u043b\u044f"
    ],
    "name:und_x_variant":[
        "Saarek\u00fcla",
        "Sarkyule",
        "Saark\u00fcla",
        "Sarkyula",
        "Sarkul\u2019",
        "\u0421\u0430\u0440\u043a\u0443\u043b\u044c"
    ],
    "wof:name":"Sarkyula",
    "wof:placetype":"locality"
},
  "geometry": {"coordinates":[28.07,59.48082],"type":"Point"}
}