{
  "type": "Feature",
  "properties": {
    "gn:admin1_code":"60",
    "gn:asciiname":"Zhegi",
    "gn:country_code":"RU",
    "gn:dem":118,
    "gn:feature_class":"P",
    "gn:feature_code":"PPL",
    "gn:name":"Zhegi",
    "gn:population":0,
    "gn:timezone":"Europe/Moscow",
    "iso:country":"RU",
    "name:rus_x_preferred":[
        "\u0416e\u0433\u0438"
    ],
    "wof:name":"Zhegi",
    "wof:placetype":"locality"
},
  "geometry": {"coordinates":[28.73724,56.48628000000001],"type":"Point"}
}