{
  "type": "Feature",
  "properties": {
    "gn:admin1_code":"8.0",
    "gn:asciiname":"Alibayevo",
    "gn:country_code":"RU",
    "gn:dem":286,
    "gn:feature_class":"P",
    "gn:feature_code":"PPL",
    "gn:name":"Alibayevo",
    "gn:population":0,
    "gn:timezone":"Asia/Yekaterinburg",
    "iso:country":"RU",
    "name:bak_x_preferred":[
        "\u04d8\u043b\u0435\u0431\u0430\u0439"
    ],
    "name:che_x_preferred":[
        "\u0410\u043b\u0438\u0431\u0430\u0435\u0432\u043e"
    ],
    "name:eng_x_preferred":[
        "Alibayevo"
    ],
    "name:hye_x_preferred":[
        "\u0531\u056c\u056b\u0562\u0561\u0587\u0578"
    ],
    "name:kaz_x_preferred":[
        "\u0410\u043b\u0438\u0431\u0430"
    ],
    "name:kir_x_preferred":[
        "\u0410\u043b\u0438\u0431\u0430"
    ],
    "name:nor_x_preferred":[
        "Alibajevo"
    ],
    "name:rus_x_preferred":[
        "\u0410\u043b\u0438\u0431\u0430\u0435\u0432\u043e"
    ],
    "name:tat_x_preferred":[
        "\u04d8\u043b\u0435\u0431\u0430\u0439"
    ],
    "name:ukr_x_preferred":[
        "\u0410\u043b\u0456\u0431\u0430\u0454\u0432\u043e"
    ],
    "name:und_x_variant":[
        "Alibayeva"
    ],
    "wof:name":"Alibayevo",
    "wof:placetype":"locality"
},
  "geometry": {"coordinates":[56.93104,51.94026],"type":"Point"}
}