{
  "type": "Feature",
  "properties": {
    "gn:admin1_code":"8.0",
    "gn:asciiname":"Alibayevo",
    "gn:country_code":"RU",
    "gn:dem":286,
    "gn:feature_class":"P",
    "gn:feature_code":"PPL",
    "gn:name":"Alibayevo",
    "gn:population":0,
    "gn:timezone":"Asia/Yekaterinburg",
    "iso:country":"RU",
    "name:eng_x_preferred":[
        "Alibayevo"
    ],
    "name:nor_x_preferred":[
        "Alibajevo"
    ],
    "name:rus_x_preferred":[
        "\u0410\u043b\u0438\u0431\u0430\u0435\u0432\u043e"
    ],
    "name:und_x_variant":[
        "Alibayeva",
        "\u0410\u043b\u0438\u0431\u0430\u0435\u0432\u043e",
        "Alibayevo"
    ],
    "wof:name":"Alibayevo",
    "wof:placetype":"locality"
},
  "geometry": {"coordinates":[56.93104,51.94026],"type":"Point"}
}