{
  "type": "Feature",
  "properties": {
    "gn:country":"RU",
    "gn:fcode":"PPL",
    "gn:pop":1323,
    "iso:country":"RU",
    "name:eng_x_preferred":[
        "Mordino"
    ],
    "name:nor_x_preferred":[
        "Mordino"
    ],
    "name:rus_x_preferred":[
        "\u041c\u043e\u0440\u0434\u0438\u043d\u043e"
    ],
    "name:unk_x_variant":[
        "\u041c\u043e\u0440\u0434\u0438\u043d\u043e"
    ],
    "qs:name":"Mordino",
    "qs:photos_9r":0,
    "qs:photos_sr":0,
    "qs:pop_sr":"3",
    "wof:name":"Mordino",
    "wof:placetype":"locality",
    "wof:population":1323
},
  "geometry": {"coordinates":[51.89574,61.35327],"type":"Point"}
}