{
  "type": "Feature",
  "properties": {
    "gn:admin1_code":"43",
    "gn:asciiname":"Lebyazhka",
    "gn:country_code":"RU",
    "gn:dem":183,
    "gn:feature_class":"P",
    "gn:feature_code":"PPL",
    "gn:name":"Lebyazhka",
    "gn:population":0,
    "gn:timezone":"Europe/Moscow",
    "iso:country":"RU",
    "name:rus_x_preferred":[
        "\u041b\u0435\u0431\u044f\u0436\u043a\u0430"
    ],
    "name:und_x_variant":[
        "Lebyazh\u2019ye",
        "Lebyazhka"
    ],
    "wof:name":"Lebyazhka",
    "wof:placetype":"locality"
},
  "geometry": {"coordinates":[37.9812,52.87905],"type":"Point"}
}