{
  "type": "Feature",
  "properties": {
    "gn:admin1_code":"69",
    "gn:asciiname":"Zarubinki",
    "gn:country_code":"RU",
    "gn:dem":196,
    "gn:feature_class":"P",
    "gn:feature_code":"PPL",
    "gn:name":"Zarubinki",
    "gn:population":0,
    "gn:timezone":"Europe/Moscow",
    "iso:country":"RU",
    "name:eng_x_preferred":[
        "Zarubinki"
    ],
    "name:nor_x_preferred":[
        "Zarubenki"
    ],
    "name:rus_x_preferred":[
        "\u0417\u0430\u0440\u0443\u0431\u0435\u043d\u043a\u0438"
    ],
    "name:und_x_variant":[
        "Bol\u2019shiye Zarubenki",
        "Zarubinki"
    ],
    "wof:name":"Zarubinki",
    "wof:placetype":"locality"
},
  "geometry": {"coordinates":[31.46955,54.92426],"type":"Point"}
}