{
  "type": "Feature",
  "properties": {
    "gn:admin1_code":"47",
    "gn:asciiname":"Dubrovino",
    "gn:country_code":"RU",
    "gn:dem":233,
    "gn:feature_class":"P",
    "gn:feature_code":"PPL",
    "gn:name":"Dubrovino",
    "gn:population":0,
    "gn:timezone":"Europe/Moscow",
    "iso:country":"RU",
    "name:rus_x_preferred":[
        "\u0414\u0443\u0431\u0440\u043e\u0432\u0438\u043d\u043e"
    ],
    "wof:name":"Dubrovino",
    "wof:placetype":"locality"
},
  "geometry": {"coordinates":[35.54176,55.9555],"type":"Point"}
}