{
  "type": "Feature",
  "properties": {
    "gn:admin1_code":"77",
    "gn:asciiname":"Guzino",
    "gn:country_code":"RU",
    "gn:dem":206,
    "gn:feature_class":"P",
    "gn:feature_code":"PPL",
    "gn:name":"Guzino",
    "gn:population":0,
    "gn:timezone":"Europe/Moscow",
    "iso:country":"RU",
    "name:rus_x_preferred":[
        "\u0413\u0443\u0437\u0438\u043d\u043e"
    ],
    "name:und_x_variant":[
        "\u0413\u0443\u0437\u0438\u043d\u043e"
    ],
    "wof:name":"Guzino",
    "wof:placetype":"locality"
},
  "geometry": {"coordinates":[33.86788,56.27484000000001],"type":"Point"}
}