{
  "type": "Feature",
  "properties": {
    "gn:admin1_code":"25",
    "gn:asciiname":"Stefanovo",
    "gn:country_code":"RU",
    "gn:dem":163,
    "gn:feature_class":"P",
    "gn:feature_code":"PPL",
    "gn:name":"Stefanovo",
    "gn:population":0,
    "gn:timezone":"Europe/Moscow",
    "iso:country":"RU",
    "name:bul_x_preferred":[
        "\u0421\u0442\u0435\u0444\u0430\u043d\u043e\u0432\u043e"
    ],
    "name:ceb_x_preferred":[
        "Stefanovo"
    ],
    "name:fra_x_preferred":[
        "Stefanovo"
    ],
    "name:pol_x_preferred":[
        "Stefanowo"
    ],
    "name:ron_x_preferred":[
        "Stefanovo"
    ],
    "name:rus_x_preferred":[
        "\u0421\u0442\u0435\u0444\u0430\u043d\u043e\u0432\u043e"
    ],
    "name:swe_x_preferred":[
        "Stefanovo"
    ],
    "name:ukr_x_preferred":[
        "\u0421\u0442\u0435\u0444\u0430\u043d\u043e\u0432\u043e"
    ],
    "name:und_x_variant":[
        "Tolkach\u00ebvo",
        "Stefanovo",
        "\u0421\u0442\u0435\u0444\u0430\u043d\u043e\u0432\u043e"
    ],
    "wof:name":"Stefanovo",
    "wof:placetype":"locality"
},
  "geometry": {"coordinates":[35.96097,54.78412],"type":"Point"}
}