{
  "type": "Feature",
  "properties": {
    "gn:admin1_code":"73",
    "gn:asciiname":"Novyy Cherkas",
    "gn:country_code":"RU",
    "gn:dem":79,
    "gn:feature_class":"P",
    "gn:feature_code":"PPL",
    "gn:name":"Novyy Cherkas",
    "gn:population":0,
    "gn:timezone":"Europe/Moscow",
    "iso:country":"RU",
    "name:rus_x_preferred":[
        "\u041d\u043e\u0432\u044b\u0439 \u0427\u0435\u0440\u043a\u0430\u0441"
    ],
    "wof:name":"Novyy Cherkas",
    "wof:placetype":"locality"
},
  "geometry": {"coordinates":[51.4581,55.9061],"type":"Point"}
}