{
  "type": "Feature",
  "properties": {
    "gn:admin1_code":"33.0",
    "gn:asciiname":"Nizhniye Moroki",
    "gn:country_code":"RU",
    "gn:dem":142,
    "gn:feature_class":"P",
    "gn:feature_code":"PPL",
    "gn:name":"Nizhniye Moroki",
    "gn:population":0,
    "gn:timezone":"Europe/Kirov",
    "iso:country":"RU",
    "name:rus_x_preferred":[
        "\u041d\u0438\u0436\u043d\u0438\u0435 \u041c\u043e\u0440\u043e\u043a\u0438"
    ],
    "name:und_x_variant":[
        "\u041d\u0438\u0436\u043d\u0438\u0435 \u041c\u043e\u0440\u043e\u043a\u0438"
    ],
    "wof:name":"Nizhniye Moroki",
    "wof:placetype":"locality"
},
  "geometry": {"coordinates":[49.0459,59.0071],"type":"Point"}
}