{
  "type": "Feature",
  "properties": {
    "gn:admin1_code":"46",
    "gn:asciiname":"Matveyevo",
    "gn:country_code":"RU",
    "gn:dem":159,
    "gn:feature_class":"P",
    "gn:feature_code":"PPL",
    "gn:name":"Matveyevo",
    "gn:population":0,
    "gn:timezone":"Europe/Moscow",
    "iso:country":"RU",
    "name:rus_x_preferred":[
        "\u041c\u0430\u0442\u0432\u0435\u0435\u0432\u043e"
    ],
    "name:und_x_variant":[
        "Matveyevka",
        "Matveyevo"
    ],
    "wof:name":"Matveyevo",
    "wof:placetype":"locality"
},
  "geometry": {"coordinates":[43.48877,54.55712],"type":"Point"}
}