{
  "type": "Feature",
  "properties": {
    "gn:admin1_code":"67",
    "gn:asciiname":"Ustinovka",
    "gn:country_code":"RU",
    "gn:dem":151,
    "gn:feature_class":"P",
    "gn:feature_code":"PPL",
    "gn:name":"Ustinovka",
    "gn:population":0,
    "gn:timezone":"Europe/Saratov",
    "iso:country":"RU",
    "name:eng_x_preferred":[
        "Ustinovka"
    ],
    "name:nor_x_preferred":[
        "Ustinovka"
    ],
    "name:rus_x_preferred":[
        "\u0423\u0441\u0442\u0438\u043d\u043e\u0432\u043a\u0430"
    ],
    "name:und_x_variant":[
        "Ustinovka Lager"
    ],
    "wof:name":"Ustinovka",
    "wof:placetype":"locality"
},
  "geometry": {"coordinates":[43.37486,51.45509000000001],"type":"Point"}
}