{
  "type": "Feature",
  "properties": {
    "gn:admin1_code":"69",
    "gn:asciiname":"Pervoye Buykovo",
    "gn:country_code":"RU",
    "gn:dem":193,
    "gn:feature_class":"P",
    "gn:feature_code":"PPL",
    "gn:name":"Pervoye Buykovo",
    "gn:population":0,
    "gn:timezone":"Europe/Moscow",
    "iso:country":"RU",
    "name:rus_x_preferred":[
        "\u041f\u0435\u0440\u0432\u043e\u0435 \u0411\u0443\u0439\u043a\u043e\u0432\u043e"
    ],
    "name:und_x_variant":[
        "Khlystovka",
        "Pervoye Buykovo"
    ],
    "wof:name":"Pervoye Buykovo",
    "wof:placetype":"locality"
},
  "geometry": {"coordinates":[33.50069000000001,54.10437],"type":"Point"}
}