{
  "type": "Feature",
  "properties": {
    "gn:admin1_code":"41",
    "gn:asciiname":"Kotovets",
    "gn:country_code":"RU",
    "gn:dem":192,
    "gn:feature_class":"P",
    "gn:feature_code":"PPL",
    "gn:name":"Kotovets",
    "gn:population":0,
    "gn:timezone":"Europe/Moscow",
    "iso:country":"RU",
    "name:rus_x_preferred":[
        "\u041a\u043e\u0442\u043e\u0432\u0435\u0446"
    ],
    "name:und_x_variant":[
        "Krasninovo",
        "Krasnikovo",
        "Kotovets",
        "\u041a\u043e\u0442\u043e\u0432\u0435\u0446"
    ],
    "wof:name":"Kotovets",
    "wof:placetype":"locality"
},
  "geometry": {"coordinates":[36.46076,51.72975],"type":"Point"}
}