{
  "type": "Feature",
  "properties": {
    "gn:admin1_code":"20",
    "gn:asciiname":"Shaloty",
    "gn:country_code":"RU",
    "gn:dem":476,
    "gn:feature_class":"P",
    "gn:feature_code":"PPL",
    "gn:name":"Shaloty",
    "gn:population":0,
    "gn:timezone":"Asia/Irkutsk",
    "iso:country":"RU",
    "name:eng_x_preferred":[
        "Shaloty"
    ],
    "name:nor_x_preferred":[
        "Sjaloty"
    ],
    "name:rus_x_preferred":[
        "\u0428\u0430\u043b\u043e\u0442\u044b"
    ],
    "name:und_x_variant":[
        "Shalot\u2019",
        "Shaloty",
        "\u0428\u0430\u043b\u043e\u0442\u044b"
    ],
    "wof:name":"Shaloty",
    "wof:placetype":"locality"
},
  "geometry": {"coordinates":[102.33278,53.16917],"type":"Point"}
}