{
  "type": "Feature",
  "properties": {
    "gn:admin1_code":"20",
    "gn:asciiname":"Antoshka",
    "gn:country_code":"RU",
    "gn:dem":668,
    "gn:feature_class":"P",
    "gn:feature_code":"PPL",
    "gn:name":"Antoshka",
    "gn:population":0,
    "gn:timezone":"Asia/Irkutsk",
    "iso:country":"RU",
    "name:nor_x_preferred":[
        "Antosjka"
    ],
    "name:rus_x_preferred":[
        "\u0410\u043d\u0442\u043e\u0448\u043a\u0430"
    ],
    "wof:name":"Antoshka",
    "wof:placetype":"locality"
},
  "geometry": {"coordinates":[107.71666999999999,55.53333000000001],"type":"Point"}
}