{
  "type": "Feature",
  "properties": {
    "gn:admin1_code":"8",
    "gn:asciiname":"Shingak-Kul'",
    "gn:country_code":"RU",
    "gn:dem":115,
    "gn:feature_class":"P",
    "gn:feature_code":"PPL",
    "gn:name":"Shingak-Kul\u2019",
    "gn:population":0,
    "gn:timezone":"Asia/Yekaterinburg",
    "iso:country":"RU",
    "name:eng_x_preferred":[
        "Shingakkul'"
    ],
    "name:nor_x_preferred":[
        "Sjingak-Kul"
    ],
    "name:rus_x_preferred":[
        "\u0428\u0438\u043d\u0433\u0430\u043a-\u041a\u0443\u043b\u044c"
    ],
    "name:und_x_variant":[
        "Shingak-Kul\u2019",
        "\u0428\u0438\u043d\u0433\u0430\u043a-\u041a\u0443\u043b\u044c"
    ],
    "wof:name":"Shingak-Kul'",
    "wof:placetype":"locality"
},
  "geometry": {"coordinates":[55.2089,54.38755],"type":"Point"}
}