{
  "type": "Feature",
  "properties": {
    "gn:admin1_code":"91",
    "gn:asciiname":"Malaya Ket'",
    "gn:country_code":"RU",
    "gn:dem":222,
    "gn:feature_class":"P",
    "gn:feature_code":"PPL",
    "gn:name":"Malaya Ket\u2019",
    "gn:population":0,
    "gn:timezone":"Asia/Krasnoyarsk",
    "iso:country":"RU",
    "name:rus_x_preferred":[
        "\u041c\u0430\u043b\u0430\u044f \u041a\u0435\u0442\u044c"
    ],
    "name:und_x_variant":[
        "Malaya Ket\u2019"
    ],
    "wof:name":"Malaya Ket'",
    "wof:placetype":"locality"
},
  "geometry": {"coordinates":[91.628,57.3444],"type":"Point"}
}