{
  "type": "Feature",
  "properties": {
    "gn:admin1_code":"91",
    "gn:asciiname":"Verkhnyaya Berezovka",
    "gn:country_code":"RU",
    "gn:dem":317,
    "gn:feature_class":"P",
    "gn:feature_code":"PPL",
    "gn:name":"Verkhnyaya Ber\u00ebzovka",
    "gn:population":0,
    "gn:timezone":"Asia/Krasnoyarsk",
    "iso:country":"RU",
    "name:eng_x_preferred":[
        "Verkhnyaya Berezovka"
    ],
    "name:nor_x_preferred":[
        "Verkhnjaja Berezovka"
    ],
    "name:rus_x_preferred":[
        "\u0412\u0435\u0440\u0445\u043d\u044f\u044f \u0411\u0435\u0440\u0435\u0437\u043e\u0432\u043a\u0430"
    ],
    "name:und_x_variant":[
        "Verkhnyaya Ber\u00ebzovka"
    ],
    "wof:name":"Verkhnyaya Berezovka",
    "wof:placetype":"locality"
},
  "geometry": {"coordinates":[90.28612,55.68691999999999],"type":"Point"}
}