{
  "type": "Feature",
  "properties": {
    "gn:admin1_code":"93",
    "gn:asciiname":"Nizhniy Shergol'dzhin",
    "gn:country_code":"RU",
    "gn:dem":861,
    "gn:feature_class":"P",
    "gn:feature_code":"PPL",
    "gn:name":"Nizhniy Shergol\u2019dzhin",
    "gn:population":0,
    "gn:timezone":"Asia/Chita",
    "iso:country":"RU",
    "name:rus_x_preferred":[
        "\u041d\u0438\u0436\u043d\u0438\u0439 \u0428\u0435\u0440\u0433\u043e\u043b\u044c\u0434\u0436\u0438\u043d"
    ],
    "name:und_x_variant":[
        "Nizhniy Shergol\u2019dzhin"
    ],
    "wof:name":"Nizhniy Shergol'dzhin",
    "wof:placetype":"locality"
},
  "geometry": {"coordinates":[108.23333,50.15],"type":"Point"}
}