{
  "type": "Feature",
  "properties": {
    "gn:admin1_code":"33",
    "gn:asciiname":"Tabekovo",
    "gn:country_code":"RU",
    "gn:dem":161,
    "gn:feature_class":"P",
    "gn:feature_code":"PPL",
    "gn:name":"Tabekovo",
    "gn:population":0,
    "gn:timezone":"Europe/Kirov",
    "iso:country":"RU",
    "name:eng_x_preferred":[
        "Tabekovo"
    ],
    "name:nor_x_preferred":[
        "Tabekovo"
    ],
    "name:rus_x_preferred":[
        "\u0422\u0430\u0431\u0435\u043a\u043e\u0432\u043e"
    ],
    "wof:name":"Tabekovo",
    "wof:placetype":"locality"
},
  "geometry": {"coordinates":[50.00787,57.23768000000001],"type":"Point"}
}