{
  "type": "Feature",
  "properties": {
    "gn:admin1_code":"8",
    "gn:asciiname":"Urmanayevo",
    "gn:country_code":"RU",
    "gn:dem":152,
    "gn:feature_class":"P",
    "gn:feature_code":"PPL",
    "gn:name":"Urmanayevo",
    "gn:population":0,
    "gn:timezone":"Asia/Yekaterinburg",
    "iso:country":"RU",
    "name:eng_x_preferred":[
        "Urmanayevo"
    ],
    "name:nor_x_preferred":[
        "Urmanajevo"
    ],
    "name:rus_x_preferred":[
        "\u0423\u0440\u043c\u0430\u043d\u0430\u0435\u0432\u043e"
    ],
    "wof:name":"Urmanayevo",
    "wof:placetype":"locality"
},
  "geometry": {"coordinates":[53.53333000000001,54.93333000000001],"type":"Point"}
}