{
  "type": "Feature",
  "properties": {
    "gn:admin1_code":"85",
    "gn:asciiname":"Mitenskoye",
    "gn:country_code":"RU",
    "gn:dem":144,
    "gn:feature_class":"P",
    "gn:feature_code":"PPL",
    "gn:name":"Mitenskoye",
    "gn:population":0,
    "gn:timezone":"Europe/Moscow",
    "iso:country":"RU",
    "name:rus_x_preferred":[
        "\u041c\u0438\u0442\u0435\u043d\u0441\u043a\u043e\u0435"
    ],
    "name:und_x_variant":[
        "\u041c\u0438\u0442\u0435\u043d\u0441\u043a\u043e\u0435"
    ],
    "wof:name":"Mitenskoye",
    "wof:placetype":"locality"
},
  "geometry": {"coordinates":[39.6404,59.29600000000001],"type":"Point"}
}