{
  "type": "Feature",
  "properties": {
    "gn:admin1_code":"76",
    "gn:asciiname":"Kol'na",
    "gn:country_code":"RU",
    "gn:dem":155,
    "gn:feature_class":"P",
    "gn:feature_code":"PPL",
    "gn:name":"Kol\u2019na",
    "gn:population":0,
    "gn:timezone":"Europe/Moscow",
    "iso:country":"RU",
    "name:eng_x_preferred":[
        "Kol'na"
    ],
    "name:nor_x_preferred":[
        "Kalna"
    ],
    "name:rus_x_preferred":[
        "\u041a\u0430\u043b\u044c\u043d\u0430"
    ],
    "name:rus_x_variant":[
        "\u041a\u043e\u043b\u044c\u043d\u0430"
    ],
    "name:und_x_variant":[
        "Kal\u2019na",
        "Kol\u2019na",
        "\u041a\u043e\u043b\u044c\u043d\u0430"
    ],
    "wof:name":"Kol'na",
    "wof:placetype":"locality"
},
  "geometry": {"coordinates":[36.59989,53.42746],"type":"Point"}
}