{
  "type": "Feature",
  "properties": {
    "gn:admin1_code":"78",
    "gn:asciiname":"Verkhnepinigino",
    "gn:country_code":"RU",
    "gn:dem":110,
    "gn:feature_class":"P",
    "gn:feature_code":"PPL",
    "gn:name":"Verkhnepinigino",
    "gn:population":0,
    "gn:timezone":"Asia/Yekaterinburg",
    "iso:country":"RU",
    "name:rus_x_preferred":[
        "\u0412\u0435\u0440\u0445\u043d\u0435\u043f\u0438\u043d\u0438\u0433\u0438\u043d\u043e"
    ],
    "name:und_x_variant":[
        "\u0412\u0435\u0440\u0445\u043d\u0435\u043f\u0438\u043d\u0438\u0433\u0438\u043d\u043e"
    ],
    "wof:name":"Verkhnepinigino",
    "wof:placetype":"locality"
},
  "geometry": {"coordinates":[70.0003,56.5244],"type":"Point"}
}