{
  "type": "Feature",
  "properties": {
    "gn:admin1_code":"57",
    "gn:asciiname":"Shkudim",
    "gn:country_code":"RU",
    "gn:dem":225,
    "gn:feature_class":"P",
    "gn:feature_code":"PPL",
    "gn:name":"Shkudim",
    "gn:population":0,
    "gn:timezone":"Europe/Moscow",
    "iso:country":"RU",
    "name:eng_x_preferred":[
        "Shkudim"
    ],
    "name:nor_x_preferred":[
        "Sjkudim"
    ],
    "name:rus_x_preferred":[
        "\u0428\u043a\u0443\u0434\u0438\u043c"
    ],
    "wof:name":"Shkudim",
    "wof:placetype":"locality"
},
  "geometry": {"coordinates":[46.44668,53.37948000000001],"type":"Point"}
}