{
  "type": "Feature",
  "properties": {
    "gn:admin1_code":"77",
    "gn:asciiname":"Mamatovo",
    "gn:country_code":"RU",
    "gn:dem":136,
    "gn:feature_class":"P",
    "gn:feature_code":"PPL",
    "gn:name":"Mamatovo",
    "gn:population":0,
    "gn:timezone":"Europe/Moscow",
    "iso:country":"RU",
    "name:rus_x_preferred":[
        "\u041c\u0430\u043c\u0430\u0442\u043e\u0432\u043e"
    ],
    "wof:name":"Mamatovo",
    "wof:placetype":"locality"
},
  "geometry": {"coordinates":[37.2225,57.3088],"type":"Point"}
}