{
  "type": "Feature",
  "properties": {
    "gn:admin1_code":"37",
    "gn:asciiname":"Sokol'nitsa",
    "gn:country_code":"RU",
    "gn:dem":173,
    "gn:feature_class":"P",
    "gn:feature_code":"PPL",
    "gn:name":"Sokol\u2019nitsa",
    "gn:population":0,
    "gn:timezone":"Europe/Moscow",
    "iso:country":"RU",
    "name:und_x_variant":[
        "Skolnitsa",
        "Sokol\u2019nitsa"
    ],
    "wof:name":"Sokol'nitsa",
    "wof:placetype":"locality"
},
  "geometry": {"coordinates":[41.37994000000001,58.04438],"type":"Point"}
}