{
  "type": "Feature",
  "properties": {
    "gn:admin1_code":"85",
    "gn:asciiname":"Mys",
    "gn:country_code":"RU",
    "gn:dem":116,
    "gn:feature_class":"P",
    "gn:feature_code":"PPL",
    "gn:name":"Mys",
    "gn:population":0,
    "gn:timezone":"Europe/Moscow",
    "iso:country":"RU",
    "name:eng_x_preferred":[
        "Mys"
    ],
    "name:nor_x_preferred":[
        "Mys"
    ],
    "name:rus_x_preferred":[
        "\u041c\u044b\u0441"
    ],
    "wof:name":"Mys",
    "wof:placetype":"locality"
},
  "geometry": {"coordinates":[39.31958,59.76999],"type":"Point"}
}