{
  "type": "Feature",
  "properties": {
    "gn:admin1_code":"33",
    "gn:asciiname":"Khozyaystvo",
    "gn:country_code":"RU",
    "gn:dem":139,
    "gn:feature_class":"P",
    "gn:feature_code":"PPL",
    "gn:name":"Khozyaystvo",
    "gn:population":0,
    "gn:timezone":"Europe/Kirov",
    "iso:country":"RU",
    "name:rus_x_preferred":[
        "\u0425\u043e\u0437\u044f\u0439\u0441\u0442\u0432\u043e"
    ],
    "wof:name":"Khozyaystvo",
    "wof:placetype":"locality"
},
  "geometry": {"coordinates":[49.6348,58.5621],"type":"Point"}
}