{
  "type": "Feature",
  "properties": {
    "gn:admin1_code":"33",
    "gn:asciiname":"Galkino",
    "gn:country_code":"RU",
    "gn:dem":100,
    "gn:feature_class":"P",
    "gn:feature_code":"PPL",
    "gn:name":"Galkino",
    "gn:population":0,
    "gn:timezone":"Europe/Kirov",
    "iso:country":"RU",
    "name:rus_x_preferred":[
        "\u0413\u0430\u043b\u043a\u0438\u043d\u043e"
    ],
    "name:und_x_variant":[
        "\u0413\u0430\u043b\u043a\u0438\u043d\u043e"
    ],
    "wof:name":"Galkino",
    "wof:placetype":"locality"
},
  "geometry": {"coordinates":[46.8411,56.9406],"type":"Point"}
}