{
  "type": "Feature",
  "properties": {
    "gn:admin1_code":"86.0",
    "gn:asciiname":"Syn Revolyutsii",
    "gn:country_code":"RU",
    "gn:dem":85,
    "gn:feature_class":"P",
    "gn:feature_code":"PPL",
    "gn:name":"Syn Revolyutsii",
    "gn:population":0,
    "gn:timezone":"Europe/Moscow",
    "iso:country":"RU",
    "name:rus_x_preferred":[
        "\u0421\u044b\u043d \u0420\u0435\u0432\u043e\u043b\u044e\u0446\u0438\u0438"
    ],
    "wof:name":"Syn Revolyutsii",
    "wof:placetype":"locality"
},
  "geometry": {"coordinates":[40.2819,50.569],"type":"Point"}
}