{
  "type": "Feature",
  "properties": {
    "gn:admin1_code":"91.0",
    "gn:asciiname":"Svetlaya",
    "gn:country_code":"RU",
    "gn:dem":445,
    "gn:feature_class":"P",
    "gn:feature_code":"PPL",
    "gn:name":"Svetlaya",
    "gn:population":0,
    "gn:timezone":"Asia/Krasnoyarsk",
    "iso:country":"RU",
    "wof:name":"Svetlaya",
    "wof:placetype":"locality"
},
  "geometry": {"coordinates":[89.95305,55.2441],"type":"Point"}
}