{
  "type": "Feature",
  "properties": {
    "gn:admin1_code":"47.0",
    "gn:asciiname":"Poselok Sanatoriya Mtsyri",
    "gn:country_code":"RU",
    "gn:dem":189,
    "gn:feature_class":"P",
    "gn:feature_code":"PPL",
    "gn:name":"Poselok Sanatoriya Mtsyri",
    "gn:population":329,
    "gn:timezone":"Europe/Moscow",
    "iso:country":"RU",
    "name:eng_x_preferred":[
        "Poselok Sanatoriya \"Mtsyri\""
    ],
    "name:rus_x_preferred":[
        "\u041f\u043e\u0441\u0451\u043b\u043e\u043a \u0421\u0430\u043d\u0430\u0442\u043e\u0440\u0438\u044f \"\u041c\u0446\u044b\u0440\u0438\""
    ],
    "name:und_x_variant":[
        "Sanatoriya Mtsyri",
        "\u0421\u0430\u043d\u0430\u0442\u043e\u0440\u0438\u044f \u041c\u0446\u044b\u0440\u0438",
        "\u041f\u043e\u0441\u0451\u043b\u043e\u043a \u0421\u0430\u043d\u0430\u0442\u043e\u0440\u0438\u044f \u041c\u0446\u044b\u0440\u0438",
        "Poselok Sanatoriya Mtsyri"
    ],
    "wof:name":"Poselok Sanatoriya Mtsyri",
    "wof:placetype":"locality",
    "wof:population":329
},
  "geometry": {"coordinates":[37.24112,55.92757],"type":"Point"}
}