{
  "type": "Feature",
  "properties": {
    "gn:admin1_code":"27",
    "gn:asciiname":"Verkhnyaya Teberda",
    "gn:country_code":"RU",
    "gn:dem":1230,
    "gn:feature_class":"P",
    "gn:feature_code":"PPL",
    "gn:name":"Verkhnyaya Teberda",
    "gn:population":0,
    "gn:timezone":"Europe/Moscow",
    "iso:country":"RU",
    "name:eng_x_preferred":[
        "Verkhnyaya Teberda"
    ],
    "name:rus_x_preferred":[
        "\u0412\u0435\u0440\u0445\u043d\u044f\u044f \u0422\u0435\u0431\u0435\u0440\u0434\u0430"
    ],
    "name:rus_x_variant":[
        "\u0422\u0435\u0431\u0435\u0440\u0434\u0430"
    ],
    "name:und_x_variant":[
        "Teberda",
        "Berzhni Teberdinskiy",
        "Verkhne-Teberdinskiy"
    ],
    "wof:name":"Verkhnyaya Teberda",
    "wof:placetype":"locality"
},
  "geometry": {"coordinates":[41.78237,43.54054],"type":"Point"}
}