{
  "type": "Feature",
  "properties": {
    "gn:admin1_code":"59",
    "gn:asciiname":"Lugokhutor",
    "gn:country_code":"RU",
    "gn:dem":140,
    "gn:feature_class":"P",
    "gn:feature_code":"PPL",
    "gn:name":"Lugokhutor",
    "gn:population":0,
    "gn:timezone":"Asia/Vladivostok",
    "iso:country":"RU",
    "name:rus_x_preferred":[
        "\u041b\u0443\u0433\u043e\u0445\u0443\u0442\u043e\u0440"
    ],
    "wof:name":"Lugokhutor",
    "wof:placetype":"locality"
},
  "geometry": {"coordinates":[133.21958999999998,44.20815],"type":"Point"}
}