{
  "type": "Feature",
  "properties": {
    "gn:admin1_code":"38",
    "gn:asciiname":"Rokkel'",
    "gn:country_code":"RU",
    "gn:dem":28,
    "gn:feature_class":"P",
    "gn:feature_code":"PPL",
    "gn:name":"Rokkel\u2019",
    "gn:population":0,
    "gn:timezone":"Europe/Moscow",
    "iso:country":"RU",
    "name:rus_x_preferred":[
        "\u0420\u043e\u043a\u043ae\u043b\u044c"
    ],
    "name:und_x_variant":[
        "Rokkel\u2019",
        "Rokul\u2019"
    ],
    "wof:name":"Rokkel'",
    "wof:placetype":"locality"
},
  "geometry": {"coordinates":[40.05487,46.53624],"type":"Point"}
}