{
  "type": "Feature",
  "properties": {
    "gn:admin1_code":"85",
    "gn:asciiname":"Ostakhovo",
    "gn:country_code":"RU",
    "gn:dem":176,
    "gn:feature_class":"P",
    "gn:feature_code":"PPL",
    "gn:name":"Ostakhovo",
    "gn:population":0,
    "gn:timezone":"Europe/Moscow",
    "iso:country":"RU",
    "name:rus_x_preferred":[
        "\u041e\u0441\u0442\u0430\u0445\u043e\u0432\u043e"
    ],
    "name:und_x_variant":[
        "\u041e\u0441\u0442\u0430\u0445\u043e\u0432\u043e"
    ],
    "wof:name":"Ostakhovo",
    "wof:placetype":"locality"
},
  "geometry": {"coordinates":[39.50745,59.37878000000001],"type":"Point"}
}