{
  "type": "Feature",
  "properties": {
    "gn:admin1_code":"20",
    "gn:asciiname":"Isakovka",
    "gn:country_code":"RU",
    "gn:dem":528,
    "gn:feature_class":"P",
    "gn:feature_code":"PPL",
    "gn:name":"Isakovka",
    "gn:population":0,
    "gn:timezone":"Asia/Irkutsk",
    "iso:country":"RU",
    "name:eng_x_preferred":[
        "Isakovka"
    ],
    "name:nor_x_preferred":[
        "Isakovka"
    ],
    "name:rus_x_preferred":[
        "\u0418\u0441\u0430\u043a\u043e\u0432\u043a\u0430"
    ],
    "wof:name":"Isakovka",
    "wof:placetype":"locality"
},
  "geometry": {"coordinates":[101.87972000000001,53.30194],"type":"Point"}
}