{
  "type": "Feature",
  "properties": {
    "gn:admin1_code":"90",
    "gn:asciiname":"Sredniye Kochergi",
    "gn:country_code":"RU",
    "gn:dem":127,
    "gn:feature_class":"P",
    "gn:feature_code":"PPL",
    "gn:name":"Sredniye Kochergi",
    "gn:population":0,
    "gn:timezone":"Asia/Yekaterinburg",
    "iso:country":"RU",
    "name:rus_x_preferred":[
        "\u0421\u0440\u0435\u0434\u043d\u0438\u0435 \u041a\u043e\u0447\u0435\u0440\u0433\u0438"
    ],
    "wof:name":"Sredniye Kochergi",
    "wof:placetype":"locality"
},
  "geometry": {"coordinates":[56.62691,57.27994],"type":"Point"}
}