{
  "type": "Feature",
  "properties": {
    "gn:admin1_code":"42",
    "gn:asciiname":"Virolaynen",
    "gn:cc2":"RU",
    "gn:country_code":"RU",
    "gn:dem":14,
    "gn:feature_class":"P",
    "gn:feature_code":"PPL",
    "gn:name":"Virolaynen",
    "gn:population":0,
    "gn:timezone":"Europe/Moscow",
    "iso:country":"RU",
    "name:fin_x_preferred":[
        "Haminanlahti"
    ],
    "name:und_x_variant":[
        "Virolainen",
        "Virolaynen"
    ],
    "wof:name":"Virolaynen",
    "wof:placetype":"locality"
},
  "geometry": {"coordinates":[30.53333,60.75],"type":"Point"}
}