{
  "type": "Feature",
  "properties": {
    "gn:country":"RU",
    "gn:fcode":"PPL",
    "gn:pop":0,
    "iso:country":"RU",
    "name:eng_x_preferred":[
        "Babichevo"
    ],
    "name:nor_x_preferred":[
        "Babitsjevo"
    ],
    "name:rus_x_preferred":[
        "\u0411\u0430\u0431\u0438\u0447\u0435\u0432\u043e"
    ],
    "name:unk_x_variant":[
        "\u0411\u0430\u0431\u0438\u0447\u0435\u0432\u043e"
    ],
    "qs:name":"Babichevo",
    "qs:name_adm0":"Russia",
    "qs:name_adm1":"Kaluga Oblast",
    "qs:photos_9r":0,
    "qs:photos_sr":0,
    "qs:placetype":"Town",
    "qs:pop_sr":"0",
    "wof:name":"Babichevo",
    "wof:placetype":"locality",
    "wof:population":0
},
  "geometry": {"coordinates":[36.29366,54.89772],"type":"Point"}
}