{
  "type": "Feature",
  "properties": {
    "gn:admin1_code":"80.0",
    "gn:asciiname":"Belyanovo",
    "gn:country_code":"RU",
    "gn:dem":196,
    "gn:feature_class":"P",
    "gn:feature_code":"PPL",
    "gn:name":"Belyanovo",
    "gn:population":0,
    "gn:timezone":"Europe/Samara",
    "iso:country":"RU",
    "name:nor_x_preferred":[
        "Beljanovo"
    ],
    "name:rus_x_preferred":[
        "\u0411\u0435\u043b\u044f\u043d\u043e\u0432\u043e"
    ],
    "wof:name":"Belyanovo",
    "wof:placetype":"locality"
},
  "geometry": {"coordinates":[52.0997,57.9799],"type":"Point"}
}