{
  "type": "Feature",
  "properties": {
    "gn:admin1_code":"5",
    "gn:asciiname":"Svetilovka",
    "gn:country_code":"RU",
    "gn:dem":147,
    "gn:feature_class":"P",
    "gn:feature_code":"PPL",
    "gn:name":"Svetilovka",
    "gn:population":0,
    "gn:timezone":"Asia/Yakutsk",
    "iso:country":"RU",
    "name:che_x_preferred":[
        "\u0421\u0432\u0435\u0442\u0438\u043b\u043e\u0432\u043a\u0430"
    ],
    "name:eng_x_preferred":[
        "Svetilovka"
    ],
    "name:nor_x_preferred":[
        "Svetilovka"
    ],
    "name:rus_x_preferred":[
        "\u0421\u0432\u0435\u0442\u0438\u043b\u043e\u0432\u043a\u0430"
    ],
    "name:tgk_x_preferred":[
        "\u0421\u0432\u0435\u0442\u0438\u043b\u043e\u0432\u043a\u0430"
    ],
    "name:und_x_variant":[
        "Svyatilovka",
        "Sbyatilovka",
        "Svetilovka"
    ],
    "wof:name":"Svetilovka",
    "wof:placetype":"locality"
},
  "geometry": {"coordinates":[127.96523999999999,50.98327000000001],"type":"Point"}
}