{
  "type": "Feature",
  "properties": {
    "gn:admin1_code":"59",
    "gn:asciiname":"Kabarga",
    "gn:country_code":"RU",
    "gn:dem":78,
    "gn:feature_class":"P",
    "gn:feature_code":"PPL",
    "gn:name":"Kabarga",
    "gn:population":0,
    "gn:timezone":"Asia/Vladivostok",
    "iso:country":"RU",
    "name:rus_x_preferred":[
        "\u041a\u0430\u0431\u0430\u0440\u0433\u0430"
    ],
    "name:und_x_variant":[
        "Kaul\u2019",
        "Kabarga",
        "\u041a\u0430\u0431\u0430\u0440\u0433\u0430"
    ],
    "wof:name":"Kabarga",
    "wof:placetype":"locality"
},
  "geometry": {"coordinates":[133.36541,45.31443],"type":"Point"}
}