{
  "type": "Feature",
  "properties": {
    "gn:admin1_code":"38",
    "gn:asciiname":"Maksima Gor'kogo",
    "gn:country_code":"RU",
    "gn:dem":7,
    "gn:feature_class":"P",
    "gn:feature_code":"PPL",
    "gn:name":"Maksima Gor\u2019kogo",
    "gn:population":0,
    "gn:timezone":"Europe/Moscow",
    "iso:country":"RU",
    "name:rus_x_preferred":[
        "\u041c\u0430\u043a\u0441\u0438\u043c\u0430 \u0413\u043e\u0440\u044c\u043a\u043e\u0433\u043e"
    ],
    "name:und_x_variant":[
        "Maksima Gor\u2019kogo"
    ],
    "wof:name":"Maksima Gor'kogo",
    "wof:placetype":"locality"
},
  "geometry": {"coordinates":[38.56114,45.78301],"type":"Point"}
}