{
  "type": "Feature",
  "properties": {
    "gn:admin1_code":"93",
    "gn:asciiname":"Arakhley",
    "gn:country_code":"RU",
    "gn:dem":970,
    "gn:feature_class":"P",
    "gn:feature_code":"PPL",
    "gn:name":"Arakhley",
    "gn:population":0,
    "gn:timezone":"Asia/Chita",
    "iso:country":"RU",
    "name:eng_x_preferred":[
        "Arakhley"
    ],
    "name:nor_x_preferred":[
        "Arakhlej"
    ],
    "name:rus_x_preferred":[
        "\u0410\u0440\u0430\u0445\u043b\u0435\u0439"
    ],
    "name:und_x_variant":[
        "\u0410\u0440\u0430\u0445\u043b\u0435\u0439",
        "Arakhley"
    ],
    "wof:name":"Arakhley",
    "wof:placetype":"locality"
},
  "geometry": {"coordinates":[112.83532,52.16266],"type":"Point"}
}