{
  "type": "Feature",
  "properties": {
    "gn:admin1_code":"32",
    "gn:asciiname":"Altay",
    "gn:country_code":"RU",
    "gn:dem":38,
    "gn:feature_class":"P",
    "gn:feature_code":"PPL",
    "gn:name":"Altay",
    "gn:population":0,
    "gn:timezone":"Asia/Yekaterinburg",
    "iso:country":"RU",
    "name:eng_x_preferred":[
        "Altay"
    ],
    "name:nor_x_preferred":[
        "Altaj"
    ],
    "name:rus_x_preferred":[
        "\u0410\u043b\u0442\u0430\u0439"
    ],
    "name:und_x_variant":[
        "\u0410\u043b\u0442\u0430\u0439",
        "Altay"
    ],
    "wof:name":"Altay",
    "wof:placetype":"locality"
},
  "geometry": {"coordinates":[68.96666999999999,60.33333],"type":"Point"}
}