{
  "type": "Feature",
  "properties": {
    "gn:admin1_code":"20",
    "gn:asciiname":"Fedorovka",
    "gn:cc2":"RU",
    "gn:country_code":"RU",
    "gn:dem":398,
    "gn:feature_class":"P",
    "gn:feature_code":"PPL",
    "gn:name":"F\u00ebdorovka",
    "gn:population":0,
    "gn:timezone":"Asia/Irkutsk",
    "iso:country":"RU",
    "name:rus_x_preferred":[
        "\u0424\u0451\u0434\u043e\u0440\u043e\u0432\u043a\u0430"
    ],
    "name:und_x_variant":[
        "Fedorova",
        "Fedorovskaya",
        "F\u00ebdorovka",
        "\u0424\u0451\u0434\u043e\u0440\u043e\u0432\u043a\u0430"
    ],
    "wof:name":"Fedorovka",
    "wof:placetype":"locality"
},
  "geometry": {"coordinates":[103.16667,54.71666999999999],"type":"Point"}
}