{
  "type": "Feature",
  "properties": {
    "gn:admin1_code":"9.0",
    "gn:asciiname":"Grachev",
    "gn:country_code":"RU",
    "gn:dem":151,
    "gn:feature_class":"P",
    "gn:feature_code":"PPL",
    "gn:name":"Grach\u00ebv",
    "gn:population":0,
    "gn:timezone":"Europe/Moscow",
    "iso:country":"RU",
    "name:rus_x_preferred":[
        "\u0413\u0440\u0430\u0447\u00eb\u0432"
    ],
    "name:und_x_variant":[
        "Grach\u00ebv"
    ],
    "wof:name":"Grachev",
    "wof:placetype":"locality"
},
  "geometry": {"coordinates":[38.5539,50.1927],"type":"Point"}
}