{
  "type": "Feature",
  "properties": {
    "gn:admin1_code":"76",
    "gn:asciiname":"Leski",
    "gn:country_code":"RU",
    "gn:dem":207,
    "gn:feature_class":"P",
    "gn:feature_code":"PPL",
    "gn:name":"Leski",
    "gn:population":0,
    "gn:timezone":"Europe/Moscow",
    "iso:country":"RU",
    "name:eng_x_preferred":[
        "Leski"
    ],
    "name:nor_x_preferred":[
        "Krasnogorje"
    ],
    "name:rus_x_preferred":[
        "\u041a\u0440\u0430\u0441\u043d\u043e\u0433\u043e\u0440\u044c\u0435"
    ],
    "name:rus_x_variant":[
        "\u041b\u0435\u0441\u043a\u0438"
    ],
    "name:und_x_variant":[
        "Krasnogor\u2019ye",
        "Leski",
        "\u041b\u0435\u0441\u043a\u0438"
    ],
    "wof:name":"Leski",
    "wof:placetype":"locality"
},
  "geometry": {"coordinates":[37.07238,53.7375],"type":"Point"}
}