{
  "type": "Feature",
  "properties": {
    "gn:admin1_code":"76.0",
    "gn:asciiname":"Shegostovo",
    "gn:country_code":"RU",
    "gn:dem":232,
    "gn:feature_class":"P",
    "gn:feature_code":"PPL",
    "gn:name":"Shegostovo",
    "gn:population":0,
    "gn:timezone":"Europe/Moscow",
    "iso:country":"RU",
    "name:und_x_variant":[
        "Shigostovo",
        "Shegostovo"
    ],
    "wof:name":"Shegostovo",
    "wof:placetype":"locality"
},
  "geometry": {"coordinates":[37.5681,54.62938000000001],"type":"Point"}
}