{
  "type": "Feature",
  "properties": {
    "gn:admin1_code":"30",
    "gn:asciiname":"Dzhonka",
    "gn:country_code":"RU",
    "gn:dem":48,
    "gn:feature_class":"P",
    "gn:feature_code":"PPL",
    "gn:name":"Dzhonka",
    "gn:population":0,
    "gn:timezone":"Asia/Vladivostok",
    "iso:country":"RU",
    "name:eng_x_preferred":[
        "Dzhonka"
    ],
    "name:nor_x_preferred":[
        "Dzjonki"
    ],
    "name:rus_x_preferred":[
        "\u0414\u0436\u043e\u043d\u043a\u0438"
    ],
    "name:rus_x_variant":[
        "\u0414\u0436\u043e\u043d\u043a\u0430"
    ],
    "name:und_x_variant":[
        "Dzhonki",
        "Dzhonka"
    ],
    "wof:name":"Dzhonka",
    "wof:placetype":"locality"
},
  "geometry": {"coordinates":[136.94433999999998,49.67222],"type":"Point"}
}