{
  "type": "Feature",
  "properties": {
    "gn:admin1_code":"10",
    "gn:asciiname":"Ryabkino",
    "gn:country_code":"RU",
    "gn:dem":150,
    "gn:feature_class":"P",
    "gn:feature_code":"PPL",
    "gn:name":"Ryabkino",
    "gn:population":0,
    "gn:timezone":"Europe/Moscow",
    "iso:country":"RU",
    "name:rus_x_preferred":[
        "\u0420\u044f\u0431\u043a\u0438\u043d\u043e"
    ],
    "name:und_x_variant":[
        "\u0420\u044f\u0431\u043a\u0438\u043d\u043e"
    ],
    "wof:name":"Ryabkino",
    "wof:placetype":"locality"
},
  "geometry": {"coordinates":[32.81667,53.25],"type":"Point"}
}