{
  "type": "Feature",
  "properties": {
    "gn:admin1_code":"91.0",
    "gn:asciiname":"Iginka",
    "gn:country_code":"RU",
    "gn:dem":209,
    "gn:feature_class":"P",
    "gn:feature_code":"PPL",
    "gn:name":"Iginka",
    "gn:population":0,
    "gn:timezone":"Asia/Krasnoyarsk",
    "iso:country":"RU",
    "name:rus_x_preferred":[
        "\u0418\u0433\u0438\u043d\u043a\u0430"
    ],
    "wof:name":"Iginka",
    "wof:placetype":"locality"
},
  "geometry": {"coordinates":[90.489,56.3473],"type":"Point"}
}