{
  "type": "Feature",
  "properties": {
    "gn:admin1_code":"33.0",
    "gn:asciiname":"Vetoshi",
    "gn:country_code":"RU",
    "gn:dem":179,
    "gn:feature_class":"P",
    "gn:feature_code":"PPL",
    "gn:name":"Vetoshi",
    "gn:population":0,
    "gn:timezone":"Europe/Kirov",
    "iso:country":"RU",
    "name:rus_x_preferred":[
        "\u0412\u0435\u0442\u043e\u0448\u0438"
    ],
    "wof:name":"Vetoshi",
    "wof:placetype":"locality"
},
  "geometry": {"coordinates":[50.66981,58.32231],"type":"Point"}
}