{
  "type": "Feature",
  "properties": {
    "gn:admin1_code":"76",
    "gn:asciiname":"Bol'shiye Teterki",
    "gn:country_code":"RU",
    "gn:dem":207,
    "gn:feature_class":"P",
    "gn:feature_code":"PPL",
    "gn:name":"Bol\u2019shiye Tet\u00ebrki",
    "gn:population":0,
    "gn:timezone":"Europe/Moscow",
    "iso:country":"RU",
    "name:rus_x_preferred":[
        "\u0411\u043e\u043b\u044c\u0448\u0438\u0435 \u0422\u0435\u0442\u0451\u0440\u043a\u0438"
    ],
    "name:und_x_variant":[
        "Bol\u2019shiye Tet\u00ebrki"
    ],
    "wof:name":"Bol'shiye Teterki",
    "wof:placetype":"locality"
},
  "geometry": {"coordinates":[38.2827,54.1534],"type":"Point"}
}