{
  "type": "Feature",
  "properties": {
    "gn:country":"RU",
    "gn:fcode":"PPL",
    "gn:pop":5278,
    "iso:country":"RU",
    "name:eng_x_preferred":[
        "Sambek"
    ],
    "name:nor_x_preferred":[
        "Sambek"
    ],
    "name:rus_x_preferred":[
        "\u0421\u0430\u043c\u0431\u0435\u043a"
    ],
    "name:unk_x_variant":[
        "\u0421\u0430\u043c\u0431\u0435\u043a"
    ],
    "qs:name":"Sambek",
    "qs:photos_9r":0,
    "qs:photos_sr":0,
    "qs:pop_sr":"5",
    "wof:name":"Sambek",
    "wof:placetype":"locality",
    "wof:population":5278
},
  "geometry": {"coordinates":[39.83083,47.74306],"type":"Point"}
}