{
  "type": "Feature",
  "properties": {
    "gn:admin1_code":"85",
    "gn:asciiname":"Vlas'yevo",
    "gn:country_code":"RU",
    "gn:dem":114,
    "gn:feature_class":"P",
    "gn:feature_code":"PPL",
    "gn:name":"Vlas\u2019yevo",
    "gn:population":0,
    "gn:timezone":"Europe/Moscow",
    "iso:country":"RU",
    "name:rus_x_preferred":[
        "\u0412\u043b\u0430\u0441\u044c\u0435\u0432\u043e"
    ],
    "name:und_x_variant":[
        "Vlas\u2019yevo"
    ],
    "wof:name":"Vlas'yevo",
    "wof:placetype":"locality"
},
  "geometry": {"coordinates":[39.8732,59.52],"type":"Point"}
}