{
  "type": "Feature",
  "properties": {
    "gn:admin1_code":"77",
    "gn:asciiname":"Khlomy",
    "gn:country_code":"RU",
    "gn:dem":196,
    "gn:feature_class":"P",
    "gn:feature_code":"PPL",
    "gn:name":"Khlomy",
    "gn:population":0,
    "gn:timezone":"Europe/Moscow",
    "iso:country":"RU",
    "name:rus_x_preferred":[
        "\u0425\u043b\u043e\u043c\u044b"
    ],
    "name:und_x_variant":[
        "\u0425\u043b\u043e\u043c\u044b"
    ],
    "wof:name":"Khlomy",
    "wof:placetype":"locality"
},
  "geometry": {"coordinates":[32.13417,55.80611],"type":"Point"}
}