{
  "type": "Feature",
  "properties": {
    "gn:admin1_code":"37",
    "gn:asciiname":"Dovodovo",
    "gn:country_code":"RU",
    "gn:dem":141,
    "gn:feature_class":"P",
    "gn:feature_code":"PPL",
    "gn:name":"Dovodovo",
    "gn:population":0,
    "gn:timezone":"Europe/Moscow",
    "iso:country":"RU",
    "name:rus_x_preferred":[
        "\u0414\u043e\u0432\u043e\u0434\u043e\u0432\u043e"
    ],
    "wof:name":"Dovodovo",
    "wof:placetype":"locality"
},
  "geometry": {"coordinates":[42.1795,58.5643],"type":"Point"}
}