{
  "type": "Feature",
  "properties": {
    "gn:admin1_code":"63",
    "gn:asciiname":"Bustor",
    "gn:cc2":"RU",
    "gn:country_code":"RU",
    "gn:dem":180,
    "gn:feature_class":"P",
    "gn:feature_code":"PPL",
    "gn:name":"Bustor",
    "gn:population":0,
    "gn:timezone":"Asia/Yakutsk",
    "iso:country":"RU",
    "name:rus_x_preferred":[
        "\u0411\u0443\u0441\u0442\u043e\u0440"
    ],
    "name:und_x_variant":[
        "Buotar",
        "Bustor"
    ],
    "wof:name":"Bustor",
    "wof:placetype":"locality"
},
  "geometry": {"coordinates":[127.18333,71.08333],"type":"Point"}
}