{
  "type": "Feature",
  "properties": {
    "gn:admin1_code":"33",
    "gn:asciiname":"Sarafannikovo",
    "gn:country_code":"RU",
    "gn:dem":135,
    "gn:feature_class":"P",
    "gn:feature_code":"PPL",
    "gn:name":"Sarafannikovo",
    "gn:population":0,
    "gn:timezone":"Europe/Kirov",
    "iso:country":"RU",
    "name:rus_x_preferred":[
        "\u0421\u0430\u0440\u0430\u0444\u0430\u043d\u043d\u0438\u043a\u043e\u0432\u043e"
    ],
    "wof:name":"Sarafannikovo",
    "wof:placetype":"locality"
},
  "geometry": {"coordinates":[47.9391,57.0978],"type":"Point"}
}