{
  "type": "Feature",
  "properties": {
    "gn:admin1_code":"81",
    "gn:asciiname":"Vyrypayevka",
    "gn:country_code":"RU",
    "gn:dem":142,
    "gn:feature_class":"P",
    "gn:feature_code":"PPL",
    "gn:name":"Vyrypayevka",
    "gn:population":0,
    "gn:timezone":"Europe/Ulyanovsk",
    "iso:country":"RU",
    "name:rus_x_preferred":[
        "\u0412\u044b\u0440\u044b\u043f\u0430\u0435\u0432\u043a\u0430"
    ],
    "wof:name":"Vyrypayevka",
    "wof:placetype":"locality"
},
  "geometry": {"coordinates":[47.0337,54.1062],"type":"Point"}
}