{
  "type": "Feature",
  "properties": {
    "gn:admin1_code":"34",
    "gn:asciiname":"Lemtybozh",
    "gn:country_code":"RU",
    "gn:dem":113,
    "gn:feature_class":"P",
    "gn:feature_code":"PPL",
    "gn:name":"Lemtybozh",
    "gn:population":0,
    "gn:timezone":"Europe/Moscow",
    "iso:country":"RU",
    "name:eng_x_preferred":[
        "Lemtybozh"
    ],
    "name:nor_x_preferred":[
        "Lemtybozj"
    ],
    "name:rus_x_preferred":[
        "\u041b\u0435\u043c\u0442\u044b\u0431\u043e\u0436"
    ],
    "name:und_x_variant":[
        "Lem-Di-Bozh",
        "Lemtibat",
        "\u041b\u0435\u043c\u0442\u044b\u0431\u043e\u0436",
        "Lemtybozh"
    ],
    "wof:name":"Lemtybozh",
    "wof:placetype":"locality"
},
  "geometry": {"coordinates":[56.94203,63.85556],"type":"Point"}
}