{
  "type": "Feature",
  "properties": {
    "gn:admin1_code":"8.0",
    "gn:asciiname":"Buzykayeva",
    "gn:country_code":"RU",
    "gn:dem":576,
    "gn:feature_class":"P",
    "gn:feature_code":"PPL",
    "gn:name":"Buzykayeva",
    "gn:population":0,
    "gn:timezone":"Asia/Yekaterinburg",
    "iso:country":"RU",
    "name:rus_x_preferred":[
        "\u0411\u0443\u0437\u044b\u043a\u0430\u0435\u0432\u0430"
    ],
    "name:und_x_variant":[
        "\u0411\u0443\u0437\u044b\u043a\u0430\u0435\u0432\u0430"
    ],
    "wof:name":"Buzykayeva",
    "wof:placetype":"locality"
},
  "geometry": {"coordinates":[58.33333,53.25],"type":"Point"}
}