{
  "type": "Feature",
  "properties": {
    "gn:admin1_code":"16",
    "gn:asciiname":"Mikshi-Enzey",
    "gn:country_code":"RU",
    "gn:dem":197,
    "gn:feature_class":"P",
    "gn:feature_code":"PPL",
    "gn:name":"Mikshi-Enzey",
    "gn:population":0,
    "gn:timezone":"Europe/Moscow",
    "iso:country":"RU",
    "name:rus_x_preferred":[
        "\u041c\u0438\u043a\u0448\u0438-\u042d\u043d\u0437\u0435\u0439"
    ],
    "name:und_x_variant":[
        "Mikish-Enzey"
    ],
    "wof:name":"Mikshi-Enzey",
    "wof:placetype":"locality"
},
  "geometry": {"coordinates":[47.04415,56.09838000000001],"type":"Point"}
}