{
  "type": "Feature",
  "properties": {
    "gn:admin1_code":"85",
    "gn:asciiname":"Zolotukha",
    "gn:country_code":"RU",
    "gn:dem":119,
    "gn:feature_class":"P",
    "gn:feature_code":"PPL",
    "gn:name":"Zolotukha",
    "gn:population":0,
    "gn:timezone":"Europe/Moscow",
    "iso:country":"RU",
    "name:che_x_preferred":[
        "\u0417\u043e\u043b\u043e\u0442\u0443\u0445\u0430"
    ],
    "name:hye_x_preferred":[
        "\u0536\u0578\u056c\u0578\u057f\u0578\u0582\u056d\u0561"
    ],
    "name:rus_x_preferred":[
        "\u0417\u043e\u043b\u043e\u0442\u0443\u0445\u0430"
    ],
    "name:tgk_x_preferred":[
        "\u0417\u043e\u043b\u043e\u0442\u0443\u0445\u0430"
    ],
    "wof:name":"Zolotukha",
    "wof:placetype":"locality"
},
  "geometry": {"coordinates":[38.516,59.5042],"type":"Point"}
}