{
  "type": "Feature",
  "properties": {
    "gn:admin1_code":"59",
    "gn:asciiname":"Romny",
    "gn:country_code":"RU",
    "gn:dem":116,
    "gn:feature_class":"P",
    "gn:feature_code":"PPL",
    "gn:name":"Romny",
    "gn:population":0,
    "gn:timezone":"Asia/Vladivostok",
    "iso:country":"RU",
    "name:ara_x_preferred":[
        "\u0631\u0648\u0645\u0646\u064a"
    ],
    "name:azb_x_preferred":[
        "\u0631\u0648\u0645\u0646\u06cc"
    ],
    "name:bel_x_preferred":[
        "\u0420\u0430\u043c\u043d\u044b"
    ],
    "name:bul_x_preferred":[
        "\u0420\u043e\u043c\u043d\u0438"
    ],
    "name:ceb_x_preferred":[
        "Romny"
    ],
    "name:ces_x_preferred":[
        "Romny"
    ],
    "name:crh_x_preferred":[
        "Romn\u0131"
    ],
    "name:deu_x_preferred":[
        "Romny"
    ],
    "name:eng_x_preferred":[
        "Romny"
    ],
    "name:est_x_preferred":[
        "Romn\u00f5"
    ],
    "name:fas_x_preferred":[
        "\u0631\u0648\u0645\u0646\u06cc"
    ],
    "name:fin_x_preferred":[
        "Romny"
    ],
    "name:fra_x_preferred":[
        "Romny"
    ],
    "name:heb_x_preferred":[
        "\u05e8\u05d5\u05de\u05e0\u05d9"
    ],
    "name:hsb_x_preferred":[
        "Romny"
    ],
    "name:hye_x_preferred":[
        "\u054c\u0578\u0574\u0576\u056b"
    ],
    "name:ita_x_preferred":[
        "Romny"
    ],
    "name:jpn_x_preferred":[
        "\u30ed\u30e0\u30cc\u30a3"
    ],
    "name:kat_x_preferred":[
        "\u10e0\u10dd\u10db\u10dc\u10d8"
    ],
    "name:kaz_x_preferred":[
        "\u0420\u043e\u043c\u043d\u044b"
    ],
    "name:kor_x_preferred":[
        "\ub86c\ub2c8"
    ],
    "name:lav_x_preferred":[
        "Romni"
    ],
    "name:lit_x_preferred":[
        "Romnai"
    ],
    "name:nno_x_preferred":[
        "Romny"
    ],
    "name:nor_x_preferred":[
        "Romny"
    ],
    "name:pol_x_preferred":[
        "Romny"
    ],
    "name:ron_x_preferred":[
        "Romn\u00ee"
    ],
    "name:rus_x_preferred":[
        "\u0420\u043e\u043c\u043d\u044b"
    ],
    "name:sah_x_preferred":[
        "\u0420\u043e\u043c\u043d\u044b"
    ],
    "name:spa_x_preferred":[
        "Romny"
    ],
    "name:srp_x_preferred":[
        "\u0420\u043e\u043c\u043d\u0438"
    ],
    "name:tat_x_preferred":[
        "\u0420\u043e\u043c\u043d\u044b"
    ],
    "name:ukr_x_preferred":[
        "\u0420\u043e\u043c\u043d\u0438"
    ],
    "name:und_x_variant":[
        "Zhuravlevka",
        "\u0420\u043e\u043c\u043d\u044b",
        "Romny"
    ],
    "name:vie_x_preferred":[
        "Romny"
    ],
    "name:zho_x_preferred":[
        "\u7f85\u59c6\u5167"
    ],
    "wof:name":"Romny",
    "wof:placetype":"locality"
},
  "geometry": {"coordinates":[134.47909999999999,45.73974000000001],"type":"Point"}
}