{
  "type": "Feature",
  "properties": {
    "gn:admin1_code":"59",
    "gn:asciiname":"Romny",
    "gn:country_code":"RU",
    "gn:dem":116,
    "gn:feature_class":"P",
    "gn:feature_code":"PPL",
    "gn:name":"Romny",
    "gn:population":0,
    "gn:timezone":"Asia/Vladivostok",
    "iso:country":"RU",
    "name:eng_x_preferred":[
        "Romny"
    ],
    "name:nor_x_preferred":[
        "Romny"
    ],
    "name:rus_x_preferred":[
        "\u0420\u043e\u043c\u043d\u044b"
    ],
    "name:und_x_variant":[
        "Zhuravlevka",
        "\u0420\u043e\u043c\u043d\u044b",
        "Romny"
    ],
    "wof:name":"Romny",
    "wof:placetype":"locality"
},
  "geometry": {"coordinates":[134.47909999999999,45.73974000000001],"type":"Point"}
}