{
  "type": "Feature",
  "properties": {
    "gn:admin1_code":"47",
    "gn:asciiname":"Imeni Pervogo Maya",
    "gn:country_code":"RU",
    "gn:dem":119,
    "gn:feature_class":"P",
    "gn:feature_code":"PPL",
    "gn:name":"Imeni Pervogo Maya",
    "gn:population":0,
    "gn:timezone":"Europe/Moscow",
    "iso:country":"RU",
    "name:rus_x_preferred":[
        "\u0418\u043c\u0435\u043d\u0438 \u041f\u0435\u0440\u0432\u043e\u0433\u043e \u041c\u0430\u044f"
    ],
    "name:und_x_variant":[
        "\u0418\u043c\u0435\u043d\u0438 \u041f\u0435\u0440\u0432\u043e\u0433\u043e \u041c\u0430\u044f"
    ],
    "wof:name":"Imeni Pervogo Maya",
    "wof:placetype":"locality"
},
  "geometry": {"coordinates":[39.20547,55.7592],"type":"Point"}
}