{
  "type": "Feature",
  "properties": {
    "gn:admin1_code":"51",
    "gn:asciiname":"Peskusha",
    "gn:country_code":"RU",
    "gn:dem":127,
    "gn:feature_class":"P",
    "gn:feature_code":"PPL",
    "gn:name":"Peskusha",
    "gn:population":0,
    "gn:timezone":"Europe/Moscow",
    "iso:country":"RU",
    "name:rus_x_preferred":[
        "\u041f\u0435\u0441\u043a\u0443\u0448\u0430"
    ],
    "wof:name":"Peskusha",
    "wof:placetype":"locality"
},
  "geometry": {"coordinates":[45.265,57.9128],"type":"Point"}
}