{
  "type": "Feature",
  "properties": {
    "gn:admin1_code":"8",
    "gn:asciiname":"Staroturumbetovo",
    "gn:country_code":"RU",
    "gn:dem":133,
    "gn:feature_class":"P",
    "gn:feature_code":"PPL",
    "gn:name":"Staroturumbetovo",
    "gn:population":0,
    "gn:timezone":"Asia/Yekaterinburg",
    "iso:country":"RU",
    "name:rus_x_preferred":[
        "\u0421\u0442\u0430\u0440\u043e\u0442\u0443\u0440\u0443\u043c\u0431\u0435\u0442\u043e\u0432\u043e"
    ],
    "name:und_x_variant":[
        "\u0421\u0442\u0430\u0440\u043e\u0442\u0443\u0440\u0443\u043c\u0431\u0435\u0442\u043e\u0432\u043e"
    ],
    "wof:name":"Staroturumbetovo",
    "wof:placetype":"locality"
},
  "geometry": {"coordinates":[55.7989,54.1016],"type":"Point"}
}