{
  "type": "Feature",
  "properties": {
    "gn:admin1_code":"16",
    "gn:asciiname":"Yelashi",
    "gn:country_code":"RU",
    "gn:dem":150,
    "gn:feature_class":"P",
    "gn:feature_code":"PPL",
    "gn:name":"Yelashi",
    "gn:population":0,
    "gn:timezone":"Europe/Moscow",
    "iso:country":"RU",
    "name:eng_x_preferred":[
        "Yelashi"
    ],
    "name:nor_x_preferred":[
        "Jelasji"
    ],
    "name:rus_x_preferred":[
        "\u0415\u043b\u0430\u0448\u0438"
    ],
    "wof:name":"Yelashi",
    "wof:placetype":"locality"
},
  "geometry": {"coordinates":[47.2446,55.927],"type":"Point"}
}