{
  "type": "Feature",
  "properties": {
    "gn:admin1_code":"85",
    "gn:asciiname":"Burkovshchina",
    "gn:country_code":"RU",
    "gn:dem":108,
    "gn:feature_class":"P",
    "gn:feature_code":"PPL",
    "gn:name":"Burkovshchina",
    "gn:population":0,
    "gn:timezone":"Europe/Moscow",
    "iso:country":"RU",
    "name:rus_x_preferred":[
        "\u0411\u0443\u0440\u043a\u043e\u0432\u0449\u0438\u043d\u0430"
    ],
    "name:und_x_variant":[
        "\u0411\u0443\u0440\u043a\u043e\u0432\u0449\u0438\u043d\u0430"
    ],
    "wof:name":"Burkovshchina",
    "wof:placetype":"locality"
},
  "geometry": {"coordinates":[46.2757,60.1022],"type":"Point"}
}