{
  "type": "Feature",
  "properties": {
    "gn:admin1_code":"65",
    "gn:asciiname":"Ryabinovka",
    "gn:country_code":"RU",
    "gn:dem":119,
    "gn:feature_class":"P",
    "gn:feature_code":"PPL",
    "gn:name":"Ryabinovka",
    "gn:population":0,
    "gn:timezone":"Europe/Samara",
    "iso:country":"RU",
    "name:rus_x_preferred":[
        "\u0420\u044f\u0431\u0438\u043d\u043e\u0432\u043a\u0430"
    ],
    "name:und_x_variant":[
        "\u0420\u044f\u0431\u0438\u043d\u043e\u0432\u043a\u0430"
    ],
    "wof:name":"Ryabinovka",
    "wof:placetype":"locality"
},
  "geometry": {"coordinates":[51.23333,53.76667],"type":"Point"}
}