{
  "type": "Feature",
  "properties": {
    "gn:admin1_code":"42.0",
    "gn:asciiname":"Dretno",
    "gn:country_code":"RU",
    "gn:dem":64,
    "gn:feature_class":"P",
    "gn:feature_code":"PPL",
    "gn:name":"Dretno",
    "gn:population":0,
    "gn:timezone":"Europe/Moscow",
    "iso:country":"RU",
    "name:rus_x_preferred":[
        "\u0414\u0440\u0435\u0442\u043d\u043e"
    ],
    "wof:name":"Dretno",
    "wof:placetype":"locality"
},
  "geometry": {"coordinates":[28.8684,58.99865],"type":"Point"}
}