{
  "type": "Feature",
  "properties": {
    "gn:admin1_code":"10",
    "gn:asciiname":"Sokoliy Bor",
    "gn:country_code":"RU",
    "gn:dem":175,
    "gn:feature_class":"P",
    "gn:feature_code":"PPL",
    "gn:name":"Sokoliy Bor",
    "gn:population":0,
    "gn:timezone":"Europe/Moscow",
    "iso:country":"RU",
    "name:rus_x_preferred":[
        "\u0421\u043e\u043a\u043e\u043b\u0438\u0439 \u0411\u043e\u0440"
    ],
    "name:und_x_variant":[
        "Sokolin Bor",
        "Sokoliy Bor"
    ],
    "wof:name":"Sokoliy Bor",
    "wof:placetype":"locality"
},
  "geometry": {"coordinates":[33.68945,53.91387],"type":"Point"}
}