{
  "type": "Feature",
  "properties": {
    "gn:admin1_code":"47",
    "gn:asciiname":"Shmanayevo",
    "gn:country_code":"RU",
    "gn:dem":149,
    "gn:feature_class":"P",
    "gn:feature_code":"PPL",
    "gn:name":"Shmanayevo",
    "gn:population":0,
    "gn:timezone":"Europe/Moscow",
    "iso:country":"RU",
    "name:rus_x_preferred":[
        "\u0428\u043c\u0430\u043d\u0430\u0435\u0432\u043e"
    ],
    "wof:name":"Shmanayevo",
    "wof:placetype":"locality"
},
  "geometry": {"coordinates":[38.41691,55.14777],"type":"Point"}
}