{
  "type": "Feature",
  "properties": {
    "gn:admin1_code":"21",
    "gn:asciiname":"Kukarino",
    "gn:country_code":"RU",
    "gn:dem":142,
    "gn:feature_class":"P",
    "gn:feature_code":"PPL",
    "gn:name":"Kukarino",
    "gn:population":0,
    "gn:timezone":"Europe/Moscow",
    "iso:country":"RU",
    "name:rus_x_preferred":[
        "\u041a\u0443\u043a\u0430\u0440\u0438\u043d\u043e"
    ],
    "wof:name":"Kukarino",
    "wof:placetype":"locality"
},
  "geometry": {"coordinates":[40.92505,56.84751],"type":"Point"}
}