{
  "type": "Feature",
  "properties": {
    "gn:admin1_code":"47",
    "gn:asciiname":"Laryushino",
    "gn:country_code":"RU",
    "gn:dem":173,
    "gn:feature_class":"P",
    "gn:feature_code":"PPL",
    "gn:name":"Laryushino",
    "gn:population":0,
    "gn:timezone":"Europe/Moscow",
    "iso:country":"RU",
    "name:rus_x_preferred":[
        "\u041b\u0430\u0440\u044e\u0448\u0438\u043d\u043e"
    ],
    "wof:name":"Laryushino",
    "wof:placetype":"locality"
},
  "geometry": {"coordinates":[36.98709,55.77034],"type":"Point"}
}