{
  "type": "Feature",
  "properties": {
    "gn:admin1_code":"72",
    "gn:asciiname":"Gorlovka",
    "gn:country_code":"RU",
    "gn:dem":152,
    "gn:feature_class":"P",
    "gn:feature_code":"PPL",
    "gn:name":"Gorlovka",
    "gn:population":0,
    "gn:timezone":"Europe/Moscow",
    "iso:country":"RU",
    "name:rus_x_preferred":[
        "\u0413\u043e\u0440\u043b\u043e\u0432\u043a\u0430"
    ],
    "wof:name":"Gorlovka",
    "wof:placetype":"locality"
},
  "geometry": {"coordinates":[40.28333,52.75],"type":"Point"}
}