{
  "type": "Feature",
  "properties": {
    "gn:admin1_code":"45",
    "gn:asciiname":"Lukovo",
    "gn:country_code":"RU",
    "gn:dem":169,
    "gn:feature_class":"P",
    "gn:feature_code":"PPL",
    "gn:name":"Lukovo",
    "gn:population":0,
    "gn:timezone":"Europe/Moscow",
    "iso:country":"RU",
    "name:rus_x_preferred":[
        "\u041b\u0443\u043a\u043e\u0432\u043e"
    ],
    "name:und_x_variant":[
        "\u041b\u0443\u043a\u043e\u0432\u043e"
    ],
    "wof:name":"Lukovo",
    "wof:placetype":"locality"
},
  "geometry": {"coordinates":[46.3512,56.2151],"type":"Point"}
}