{
  "type": "Feature",
  "properties": {
    "gn:admin1_code":"90",
    "gn:asciiname":"Kushmangort",
    "gn:country_code":"RU",
    "gn:dem":208,
    "gn:feature_class":"P",
    "gn:feature_code":"PPL",
    "gn:name":"Kushmangort",
    "gn:population":0,
    "gn:timezone":"Asia/Yekaterinburg",
    "iso:country":"RU",
    "name:che_x_preferred":[
        "\u041a\u0443\u0448\u043c\u0430\u043d\u0433\u043e\u0440\u0442"
    ],
    "name:hye_x_preferred":[
        "\u053f\u0578\u0582\u0577\u0574\u0561\u0576\u0563\u0578\u0580\u057f"
    ],
    "name:rus_x_preferred":[
        "\u041a\u0443\u0448\u043c\u0430\u043d\u0433\u043e\u0440\u0442"
    ],
    "wof:name":"Kushmangort",
    "wof:placetype":"locality"
},
  "geometry": {"coordinates":[56.2421,60.45587],"type":"Point"}
}