{
  "type": "Feature",
  "properties": {
    "gn:admin1_code":"85",
    "gn:asciiname":"Yevkovo",
    "gn:country_code":"RU",
    "gn:dem":135,
    "gn:feature_class":"P",
    "gn:feature_code":"PPL",
    "gn:name":"Yevkovo",
    "gn:population":0,
    "gn:timezone":"Europe/Moscow",
    "iso:country":"RU",
    "name:rus_x_preferred":[
        "\u0415\u0432\u043a\u043e\u0432\u043e"
    ],
    "wof:name":"Yevkovo",
    "wof:placetype":"locality"
},
  "geometry": {"coordinates":[39.9117,59.1844],"type":"Point"}
}