{
  "type": "Feature",
  "properties": {
    "gn:admin1_code":"85",
    "gn:asciiname":"Khrenovo",
    "gn:country_code":"RU",
    "gn:dem":145,
    "gn:feature_class":"P",
    "gn:feature_code":"PPL",
    "gn:name":"Khrenovo",
    "gn:population":0,
    "gn:timezone":"Europe/Moscow",
    "iso:country":"RU",
    "name:rus_x_preferred":[
        "\u0425\u0440\u0435\u043d\u043e\u0432\u043e"
    ],
    "name:und_x_variant":[
        "\u0425\u0440\u0435\u043d\u043e\u0432\u043e"
    ],
    "wof:name":"Khrenovo",
    "wof:placetype":"locality"
},
  "geometry": {"coordinates":[39.72256,59.26426],"type":"Point"}
}