{
  "type": "Feature",
  "properties": {
    "gn:admin1_code":"21.0",
    "gn:asciiname":"Fateyevo",
    "gn:country_code":"RU",
    "gn:dem":114,
    "gn:feature_class":"P",
    "gn:feature_code":"PPL",
    "gn:name":"Fateyevo",
    "gn:population":0,
    "gn:timezone":"Europe/Moscow",
    "iso:country":"RU",
    "name:rus_x_preferred":[
        "\u0424\u0430\u0442\u0435\u0435\u0432\u043e"
    ],
    "wof:name":"Fateyevo",
    "wof:placetype":"locality"
},
  "geometry": {"coordinates":[41.45347,56.67834000000001],"type":"Point"}
}