{
  "type": "Feature",
  "properties": {
    "gn:admin1_code":"34",
    "gn:asciiname":"Namsk",
    "gn:country_code":"RU",
    "gn:dem":125,
    "gn:feature_class":"P",
    "gn:feature_code":"PPL",
    "gn:name":"Namsk",
    "gn:population":0,
    "gn:timezone":"Europe/Moscow",
    "iso:country":"RU",
    "name:rus_x_preferred":[
        "\u041d\u0430\u043c\u0441\u043a"
    ],
    "wof:name":"Namsk",
    "wof:placetype":"locality"
},
  "geometry": {"coordinates":[52.09984,61.18233000000001],"type":"Point"}
}