{
  "type": "Feature",
  "properties": {
    "gn:admin1_code":"43",
    "gn:asciiname":"Limovaya",
    "gn:country_code":"RU",
    "gn:dem":215,
    "gn:feature_class":"P",
    "gn:feature_code":"PPL",
    "gn:name":"Limovaya",
    "gn:population":0,
    "gn:timezone":"Europe/Moscow",
    "iso:country":"RU",
    "name:rus_x_preferred":[
        "\u041b\u0438\u043c\u043e\u0432\u0430\u044f"
    ],
    "name:und_x_variant":[
        "\u041b\u0438\u043c\u043e\u0432\u0430\u044f",
        "Limovoye"
    ],
    "wof:name":"Limovaya",
    "wof:placetype":"locality"
},
  "geometry": {"coordinates":[38.6672,52.8932],"type":"Point"}
}