{
  "type": "Feature",
  "properties": {
    "gn:admin1_code":"63",
    "gn:asciiname":"Khatylyma",
    "gn:country_code":"RU",
    "gn:dem":153,
    "gn:feature_class":"P",
    "gn:feature_code":"PPL",
    "gn:name":"Khatylyma",
    "gn:population":0,
    "gn:timezone":"Asia/Yakutsk",
    "iso:country":"RU",
    "name:rus_x_preferred":[
        "\u0425\u0430\u0442\u044b\u043b\u044b\u043c\u0430"
    ],
    "name:und_x_variant":[
        "\u0425\u0430\u0442\u044b\u043b\u044b\u043c\u0430"
    ],
    "wof:name":"Khatylyma",
    "wof:placetype":"locality"
},
  "geometry": {"coordinates":[130.19999999999999,61.53333000000001],"type":"Point"}
}