{
  "type": "Feature",
  "properties": {
    "gn:admin1_code":"43",
    "gn:asciiname":"Verkhnyaya Mosolovka",
    "gn:country_code":"RU",
    "gn:dem":154,
    "gn:feature_class":"P",
    "gn:feature_code":"PPL",
    "gn:name":"Verkhnyaya Mosolovka",
    "gn:population":0,
    "gn:timezone":"Europe/Moscow",
    "iso:country":"RU",
    "name:rus_x_preferred":[
        "\u0412\u0435\u0440\u0445\u043d\u044f\u044f \u041c\u043e\u0441\u043e\u043b\u043e\u0432\u043a\u0430"
    ],
    "name:und_x_variant":[
        "Verkhnyaya Masolovka",
        "Verkhnyaya Mosolovka",
        "Verkhnyaya Masalovka"
    ],
    "wof:name":"Verkhnyaya Mosolovka",
    "wof:placetype":"locality"
},
  "geometry": {"coordinates":[40.0754,52.0549],"type":"Point"}
}