{
  "type": "Feature",
  "properties": {
    "gn:admin1_code":"24",
    "gn:asciiname":"Obil'noye",
    "gn:country_code":"RU",
    "gn:dem":56,
    "gn:feature_class":"P",
    "gn:feature_code":"PPL",
    "gn:name":"Obil\u2019noye",
    "gn:population":0,
    "gn:timezone":"Europe/Moscow",
    "iso:country":"RU",
    "name:eng_x_preferred":[
        "Obil'noye"
    ],
    "name:nor_x_preferred":[
        "Obilnoje"
    ],
    "name:rus_x_preferred":[
        "Obil\u2019noye"
    ],
    "name:rus_x_variant":[
        "\u041e\u0431\u0438\u043b\u044c\u043d\u043e\u0435"
    ],
    "name:und_x_variant":[
        "Unkryuk"
    ],
    "wof:name":"Obil'noye",
    "wof:placetype":"locality"
},
  "geometry": {"coordinates":[44.41778,47.5125],"type":"Point"}
}