{
  "type": "Feature",
  "properties": {
    "gn:admin1_code":"16",
    "gn:asciiname":"Kochino",
    "gn:country_code":"RU",
    "gn:dem":144,
    "gn:feature_class":"P",
    "gn:feature_code":"PPL",
    "gn:name":"Kochino",
    "gn:population":0,
    "gn:timezone":"Europe/Moscow",
    "iso:country":"RU",
    "name:rus_x_preferred":[
        "\u041a\u043e\u0447\u0438\u043d\u043e"
    ],
    "name:und_x_variant":[
        "\u041a\u043e\u0447\u0438\u043d\u043e"
    ],
    "wof:name":"Kochino",
    "wof:placetype":"locality"
},
  "geometry": {"coordinates":[47.61427,56.03318],"type":"Point"}
}