{
  "type": "Feature",
  "properties": {
    "gn:admin1_code":"10",
    "gn:asciiname":"Razrytoye",
    "gn:country_code":"RU",
    "gn:dem":193,
    "gn:feature_class":"P",
    "gn:feature_code":"PPL",
    "gn:name":"Razrytoye",
    "gn:population":0,
    "gn:timezone":"Europe/Moscow",
    "iso:country":"RU",
    "name:rus_x_preferred":[
        "\u0420\u0430\u0437\u0440\u044b\u0442\u043e\u0435"
    ],
    "wof:name":"Razrytoye",
    "wof:placetype":"locality"
},
  "geometry": {"coordinates":[32.96117,52.92624],"type":"Point"}
}