{
  "type": "Feature",
  "properties": {
    "gn:admin1_code":"59",
    "gn:asciiname":"Chistovodnoye",
    "gn:country_code":"RU",
    "gn:dem":232,
    "gn:feature_class":"P",
    "gn:feature_code":"PPL",
    "gn:name":"Chistovodnoye",
    "gn:population":0,
    "gn:timezone":"Asia/Vladivostok",
    "iso:country":"RU",
    "name:eng_x_preferred":[
        "Chistovodnoye"
    ],
    "name:nor_x_preferred":[
        "Tsjistovodnoje"
    ],
    "name:rus_x_preferred":[
        "\u0427\u0438\u0441\u0442\u043e\u0432\u043e\u0434\u043d\u043e\u0435"
    ],
    "name:und_x_variant":[
        "Vangou",
        "\u0427\u0438\u0441\u0442\u043e\u0432\u043e\u0434\u043d\u043e\u0435",
        "Chistovodnoye"
    ],
    "wof:name":"Chistovodnoye",
    "wof:placetype":"locality"
},
  "geometry": {"coordinates":[133.55275,43.05632],"type":"Point"}
}