{
  "type": "Feature",
  "properties": {
    "gn:admin1_code":"77",
    "gn:asciiname":"Eskino",
    "gn:country_code":"RU",
    "gn:dem":130,
    "gn:feature_class":"P",
    "gn:feature_code":"PPL",
    "gn:name":"Eskino",
    "gn:population":0,
    "gn:timezone":"Europe/Moscow",
    "iso:country":"RU",
    "name:rus_x_preferred":[
        "\u042d\u0441\u043a\u0438\u043d\u043e"
    ],
    "wof:name":"Eskino",
    "wof:placetype":"locality"
},
  "geometry": {"coordinates":[37.6096,57.3363],"type":"Point"}
}