{
  "type": "Feature",
  "properties": {
    "gn:admin1_code":"72",
    "gn:asciiname":"Vorontsovskiye Otruba",
    "gn:country_code":"RU",
    "gn:dem":166,
    "gn:feature_class":"P",
    "gn:feature_code":"PPL",
    "gn:name":"Vorontsovskiye Otruba",
    "gn:population":0,
    "gn:timezone":"Europe/Moscow",
    "iso:country":"RU",
    "name:und_x_variant":[
        "Voronovskiye Otruba",
        "Vorontsovskiye Otruba"
    ],
    "wof:name":"Vorontsovskiye Otruba",
    "wof:placetype":"locality"
},
  "geometry": {"coordinates":[41.13467,52.0847],"type":"Point"}
}