{
  "type": "Feature",
  "properties": {
    "gn:admin1_code":"33.0",
    "gn:asciiname":"Naberezhnyy",
    "gn:country_code":"RU",
    "gn:dem":89,
    "gn:feature_class":"P",
    "gn:feature_code":"PPL",
    "gn:name":"Naberezhnyy",
    "gn:population":0,
    "gn:timezone":"Europe/Kirov",
    "iso:country":"RU",
    "name:rus_x_preferred":[
        "\u041d\u0430\u0431\u0435\u0440\u0435\u0436\u043d\u044b\u0439"
    ],
    "name:und_x_variant":[
        "Arbazhskiy L\u2019nozavod",
        "Naberezhnyy",
        "\u041d\u0430\u0431\u0435\u0440\u0435\u0436\u043d\u044b\u0439"
    ],
    "wof:name":"Naberezhnyy",
    "wof:placetype":"locality"
},
  "geometry": {"coordinates":[48.20125,57.63956],"type":"Point"}
}