{
  "type": "Feature",
  "properties": {
    "gn:admin1_code":"56.0",
    "gn:asciiname":"Bol'shegor'ye",
    "gn:country_code":"RU",
    "gn:dem":213,
    "gn:feature_class":"P",
    "gn:feature_code":"PPL",
    "gn:name":"Bol\u2019shegor\u2019ye",
    "gn:population":0,
    "gn:timezone":"Europe/Moscow",
    "iso:country":"RU",
    "name:rus_x_preferred":[
        "\u0411\u043e\u043b\u044c\u0448\u0435\u0433\u043e\u0440\u044c\u0435"
    ],
    "name:und_x_variant":[
        "Durovka",
        "Bol\u2019shegor\u2019ye",
        "\u0411\u043e\u043b\u044c\u0448\u0435\u0433\u043e\u0440\u044c\u0435"
    ],
    "wof:name":"Bol'shegor'ye",
    "wof:placetype":"locality"
},
  "geometry": {"coordinates":[36.77013,52.73949],"type":"Point"}
}