{
  "type": "Feature",
  "properties": {
    "gn:admin1_code":"33",
    "gn:asciiname":"Goryui",
    "gn:country_code":"RU",
    "gn:dem":170,
    "gn:feature_class":"P",
    "gn:feature_code":"PPL",
    "gn:name":"Goryui",
    "gn:population":0,
    "gn:timezone":"Europe/Kirov",
    "iso:country":"RU",
    "name:rus_x_preferred":[
        "\u0413\u043e\u0440\u044e\u0438"
    ],
    "wof:name":"Goryui",
    "wof:placetype":"locality"
},
  "geometry": {"coordinates":[50.23333,57.96666999999999],"type":"Point"}
}