{
  "type": "Feature",
  "properties": {
    "gn:admin1_code":"42",
    "gn:asciiname":"Kukkuzi",
    "gn:country_code":"RU",
    "gn:dem":30,
    "gn:feature_class":"P",
    "gn:feature_code":"PPL",
    "gn:name":"Kukkuzi",
    "gn:population":0,
    "gn:timezone":"Europe/Moscow",
    "iso:country":"RU",
    "name:fin_x_preferred":[
        "Kukkosi"
    ],
    "name:nor_x_preferred":[
        "Kukkuzi"
    ],
    "name:rus_x_preferred":[
        "\u041a\u0443\u043a\u043a\u0443\u0437\u0438"
    ],
    "wof:name":"Kukkuzi",
    "wof:placetype":"locality"
},
  "geometry": {"coordinates":[29.63178,59.92588000000001],"type":"Point"}
}