{
  "type": "Feature",
  "properties": {
    "gn:admin1_code":"60",
    "gn:asciiname":"Yesenniki",
    "gn:country_code":"RU",
    "gn:dem":111,
    "gn:feature_class":"P",
    "gn:feature_code":"PPL",
    "gn:name":"Yesenniki",
    "gn:population":0,
    "gn:timezone":"Europe/Moscow",
    "iso:country":"RU",
    "name:eng_x_preferred":[
        "Yesenniki"
    ],
    "name:nor_x_preferred":[
        "Jesenniki"
    ],
    "name:rus_x_preferred":[
        "\u0415\u0441\u0435\u043d\u043d\u0438\u043a\u0438"
    ],
    "name:rus_x_variant":[
        "\u0415\u0441\u0441\u0435\u043d\u043d\u0438\u043a\u0438"
    ],
    "name:und_x_variant":[
        "Yesseniki",
        "Yessenniki"
    ],
    "wof:name":"Yesenniki",
    "wof:placetype":"locality"
},
  "geometry": {"coordinates":[28.80334,56.5164],"type":"Point"}
}