{
  "type": "Feature",
  "properties": {
    "gn:country":"RU",
    "gn:fcode":"PPL",
    "gn:population":6711,
    "iso:country":"RU",
    "name:nor_x_preferred":[
        "Nizjnjaja Tavda"
    ],
    "name:rus_x_preferred":[
        "\u041d\u0438\u0436\u043d\u044f\u044f \u0422\u0430\u0432\u0434\u0430"
    ],
    "name:und_x_variant":[
        "Tavdinskoe"
    ],
    "qs_pg:aaroncc":"RU",
    "qs_pg:gn_country":"RU",
    "qs_pg:gn_fcode":"PPL",
    "qs_pg:gn_pop":6711,
    "qs_pg:name":"Nizhnyaya Tavda",
    "qs_pg:name_adm0":"Russia",
    "qs_pg:name_adm1":"Tyumen Oblast",
    "qs_pg:photos_9r":0,
    "qs_pg:photos_sr":0,
    "qs_pg:pop_sr":5,
    "qs_pg:qs_pg_placetype":"locality",
    "qs_pg:qs_pg_placetype_gp":"Town",
    "qs_pg:woe_adm0":23424936,
    "woe:adm0_id":23424936,
    "woe:name_adm0":"Russia",
    "woe:name_adm1":"Tyumen Oblast",
    "woe:placetype":"Town",
    "wof:name":"Nizhnyaya Tavda",
    "wof:placetype":"locality",
    "wof:population":6711
},
  "geometry": {"coordinates":[66.1725,57.67306],"type":"Point"}
}