{
  "type": "Feature",
  "properties": {
    "gn:admin1_code":"10",
    "gn:asciiname":"Polonnoye",
    "gn:country_code":"RU",
    "gn:dem":217,
    "gn:feature_class":"P",
    "gn:feature_code":"PPL",
    "gn:name":"Polonnoye",
    "gn:population":0,
    "gn:timezone":"Europe/Moscow",
    "iso:country":"RU",
    "name:rus_x_preferred":[
        "\u041f\u043e\u043b\u043e\u043d\u043d\u043e\u0435"
    ],
    "wof:name":"Polonnoye",
    "wof:placetype":"locality"
},
  "geometry": {"coordinates":[34.98333,52.98333],"type":"Point"}
}