{
  "type": "Feature",
  "properties": {
    "gn:admin1_code":"53",
    "gn:asciiname":"Novokonovalovskiy",
    "gn:country_code":"RU",
    "gn:dem":149,
    "gn:feature_class":"P",
    "gn:feature_code":"PPL",
    "gn:name":"Novokonovalovskiy",
    "gn:population":0,
    "gn:timezone":"Asia/Novosibirsk",
    "iso:country":"RU",
    "name:rus_x_preferred":[
        "\u041d\u043e\u0432\u043e\u043a\u043e\u043d\u043e\u0432\u0430\u043b\u043e\u0432\u0441\u043a\u0438\u0439"
    ],
    "name:und_x_variant":[
        "Novokonovalovka",
        "Novokonovalovskiy"
    ],
    "wof:name":"Novokonovalovskiy",
    "wof:placetype":"locality"
},
  "geometry": {"coordinates":[82.1974,55.6942],"type":"Point"}
}