{
  "type": "Feature",
  "properties": {
    "gn:admin1_code":"59",
    "gn:asciiname":"Khasemi",
    "gn:country_code":"RU",
    "gn:dem":2,
    "gn:feature_class":"P",
    "gn:feature_code":"PPL",
    "gn:name":"Khasemi",
    "gn:population":0,
    "gn:timezone":"Asia/Vladivostok",
    "iso:country":"RU",
    "name:rus_x_preferred":[
        "\u0425\u0430\u0441\u0435\u043c\u0438"
    ],
    "wof:name":"Khasemi",
    "wof:placetype":"locality"
},
  "geometry": {"coordinates":[130.76471999999998,42.50944000000001],"type":"Point"}
}