{
  "type": "Feature",
  "properties": {
    "gn:admin1_code":"40",
    "gn:asciiname":"Zubarevka",
    "gn:country_code":"RU",
    "gn:dem":166,
    "gn:feature_class":"P",
    "gn:feature_code":"PPL",
    "gn:name":"Zubar\u00ebvka",
    "gn:population":0,
    "gn:timezone":"Asia/Yekaterinburg",
    "iso:country":"RU",
    "name:eng_x_preferred":[
        "Zubar\u00ebvka"
    ],
    "name:nor_x_preferred":[
        "Zubarevka"
    ],
    "name:rus_x_preferred":[
        "\u0417\u0443\u0431\u0430\u0440\u0435\u0432\u043a\u0430"
    ],
    "wof:name":"Zubarevka",
    "wof:placetype":"locality"
},
  "geometry": {"coordinates":[65.18682,54.3564],"type":"Point"}
}