{
  "type": "Feature",
  "properties": {
    "gn:admin1_code":"90",
    "gn:asciiname":"Pazderino",
    "gn:country_code":"RU",
    "gn:dem":127,
    "gn:feature_class":"P",
    "gn:feature_code":"PPL",
    "gn:name":"Pazderino",
    "gn:population":0,
    "gn:timezone":"Asia/Yekaterinburg",
    "iso:country":"RU",
    "name:rus_x_preferred":[
        "\u041f\u0430\u0437\u0434\u0435\u0440\u0438\u043d\u043e"
    ],
    "name:und_x_variant":[
        "\u041f\u0430\u0437\u0434\u0435\u0440\u0438\u043d\u043e"
    ],
    "wof:name":"Pazderino",
    "wof:placetype":"locality"
},
  "geometry": {"coordinates":[56.3263,57.9352],"type":"Point"}
}