{
  "type": "Feature",
  "properties": {
    "gn:admin1_code":"63",
    "gn:asciiname":"Agayakan",
    "gn:country_code":"RU",
    "gn:dem":777,
    "gn:feature_class":"P",
    "gn:feature_code":"PPL",
    "gn:name":"Agayakan",
    "gn:population":0,
    "gn:timezone":"Asia/Magadan",
    "iso:country":"RU",
    "name:nor_x_preferred":[
        "Agajakan"
    ],
    "name:rus_x_preferred":[
        "\u0410\u0433\u0430\u044f\u043a\u0430\u043d"
    ],
    "wof:name":"Agayakan",
    "wof:placetype":"locality"
},
  "geometry": {"coordinates":[141.73479,63.33804],"type":"Point"}
}