{
  "type": "Feature",
  "properties": {
    "gn:admin1_code":"38",
    "gn:asciiname":"Sokolikhin",
    "gn:country_code":"RU",
    "gn:dem":305,
    "gn:feature_class":"P",
    "gn:feature_code":"PPL",
    "gn:name":"Sokolikhin",
    "gn:population":0,
    "gn:timezone":"Europe/Moscow",
    "iso:country":"RU",
    "name:rus_x_preferred":[
        "\u0421\u043e\u043a\u043e\u043b\u0438\u0445\u0438\u043d"
    ],
    "wof:name":"Sokolikhin",
    "wof:placetype":"locality"
},
  "geometry": {"coordinates":[40.90417,44.67444],"type":"Point"}
}