{
  "type": "Feature",
  "properties": {
    "gn:admin1_code":"67",
    "gn:asciiname":"Peschanka",
    "gn:country_code":"RU",
    "gn:dem":26,
    "gn:feature_class":"P",
    "gn:feature_code":"PPL",
    "gn:name":"Peschanka",
    "gn:population":0,
    "gn:timezone":"Europe/Saratov",
    "iso:country":"RU",
    "name:rus_x_preferred":[
        "\u041f\u0435\u0441\u0447\u0430\u043d\u043a\u0430"
    ],
    "name:und_x_variant":[
        "Parsh\u00ebvka",
        "Parshovka",
        "Peschanka",
        "\u041f\u0435\u0441\u0447\u0430\u043d\u043a\u0430"
    ],
    "wof:name":"Peschanka",
    "wof:placetype":"locality"
},
  "geometry": {"coordinates":[46.79957,52.06675],"type":"Point"}
}