{
  "type": "Feature",
  "properties": {
    "gn:admin1_code":"77",
    "gn:asciiname":"Benek",
    "gn:country_code":"RU",
    "gn:dem":249,
    "gn:feature_class":"P",
    "gn:feature_code":"PPL",
    "gn:name":"Benek",
    "gn:population":0,
    "gn:timezone":"Europe/Moscow",
    "iso:country":"RU",
    "name:rus_x_preferred":[
        "\u0411\u0435\u043d\u0435\u043a"
    ],
    "wof:name":"Benek",
    "wof:placetype":"locality"
},
  "geometry": {"coordinates":[31.94515,56.86003],"type":"Point"}
}