{
  "type": "Feature",
  "properties": {
    "gn:admin1_code":"72",
    "gn:asciiname":"Velichkino",
    "gn:country_code":"RU",
    "gn:dem":156,
    "gn:feature_class":"P",
    "gn:feature_code":"PPL",
    "gn:name":"Velichkino",
    "gn:population":0,
    "gn:timezone":"Europe/Moscow",
    "iso:country":"RU",
    "name:und_x_variant":[
        "Vilichkino",
        "Velichkino"
    ],
    "wof:name":"Velichkino",
    "wof:placetype":"locality"
},
  "geometry": {"coordinates":[41.2409,52.14658],"type":"Point"}
}