{
  "type": "Feature",
  "properties": {
    "gn:admin1_code":"91",
    "gn:asciiname":"Shushkovo",
    "gn:country_code":"RU",
    "gn:dem":339,
    "gn:feature_class":"P",
    "gn:feature_code":"PPL",
    "gn:name":"Shushkovo",
    "gn:population":0,
    "gn:timezone":"Asia/Krasnoyarsk",
    "iso:country":"RU",
    "name:eng_x_preferred":[
        "Shushkovo"
    ],
    "name:nor_x_preferred":[
        "Sjusjkovo"
    ],
    "name:rus_x_preferred":[
        "\u0428\u0443\u0448\u043a\u043e\u0432\u043e"
    ],
    "wof:name":"Shushkovo",
    "wof:placetype":"locality"
},
  "geometry": {"coordinates":[91.25095,56.20042],"type":"Point"}
}