{
  "type": "Feature",
  "properties": {
    "gn:admin1_code":"75",
    "gn:asciiname":"Novopokrovka",
    "gn:country_code":"RU",
    "gn:dem":114,
    "gn:feature_class":"P",
    "gn:feature_code":"PPL",
    "gn:name":"Novopokrovka",
    "gn:population":0,
    "gn:timezone":"Asia/Tomsk",
    "iso:country":"RU",
    "name:eng_x_preferred":[
        "Novopokrovka"
    ],
    "name:nor_x_preferred":[
        "Novopokrovka"
    ],
    "name:rus_x_preferred":[
        "\u041d\u043e\u0432\u043e\u043f\u043e\u043a\u0440\u043e\u0432\u043a\u0430"
    ],
    "wof:name":"Novopokrovka",
    "wof:placetype":"locality"
},
  "geometry": {"coordinates":[83.86499999999999,56.31721999999999],"type":"Point"}
}