{
  "type": "Feature",
  "properties": {
    "gn:admin1_code":"13",
    "gn:asciiname":"Yagodnyy",
    "gn:country_code":"RU",
    "gn:dem":240,
    "gn:feature_class":"P",
    "gn:feature_code":"PPL",
    "gn:name":"Yagodnyy",
    "gn:population":0,
    "gn:timezone":"Asia/Yekaterinburg",
    "iso:country":"RU",
    "wof:name":"Yagodnyy",
    "wof:placetype":"locality"
},
  "geometry": {"coordinates":[61.24001,53.94648000000001],"type":"Point"}
}