{
  "type": "Feature",
  "properties": {
    "gn:admin1_code":"47",
    "gn:asciiname":"Sviridonovo",
    "gn:country_code":"RU",
    "gn:dem":164,
    "gn:feature_class":"P",
    "gn:feature_code":"PPL",
    "gn:name":"Sviridonovo",
    "gn:population":0,
    "gn:timezone":"Europe/Moscow",
    "iso:country":"RU",
    "name:und_x_variant":[
        "Suiridonovo",
        "Sviridonovo"
    ],
    "wof:name":"Sviridonovo",
    "wof:placetype":"locality"
},
  "geometry": {"coordinates":[38.62131,54.83586],"type":"Point"}
}