{
  "type": "Feature",
  "properties": {
    "gn:admin1_code":"33.0",
    "gn:asciiname":"Golyshi",
    "gn:country_code":"RU",
    "gn:dem":124,
    "gn:feature_class":"P",
    "gn:feature_code":"PPL",
    "gn:name":"Golyshi",
    "gn:population":0,
    "gn:timezone":"Europe/Kirov",
    "iso:country":"RU",
    "name:rus_x_preferred":[
        "\u0413\u043e\u043b\u044b\u0448\u0438"
    ],
    "name:und_x_variant":[
        "\u0413\u043e\u043b\u044b\u0448\u0438"
    ],
    "wof:name":"Golyshi",
    "wof:placetype":"locality"
},
  "geometry": {"coordinates":[49.11621,58.67474],"type":"Point"}
}