{
  "type": "Feature",
  "properties": {
    "gn:admin1_code":"47",
    "gn:asciiname":"Shikolovo",
    "gn:country_code":"RU",
    "gn:dem":191,
    "gn:feature_class":"P",
    "gn:feature_code":"PPL",
    "gn:name":"Shikolovo",
    "gn:population":0,
    "gn:timezone":"Europe/Moscow",
    "iso:country":"RU",
    "name:rus_x_preferred":[
        "\u0428\u0438\u043a\u043e\u043b\u043e\u0432\u043e"
    ],
    "name:und_x_variant":[
        "\u0428\u0438\u043a\u043e\u043b\u043e\u0432\u043e"
    ],
    "wof:name":"Shikolovo",
    "wof:placetype":"locality"
},
  "geometry": {"coordinates":[36.12833,55.50444],"type":"Point"}
}