{
  "type": "Feature",
  "properties": {
    "gn:admin1_code":"90.0",
    "gn:asciiname":"Dvadtsatka",
    "gn:country_code":"RU",
    "gn:dem":223,
    "gn:feature_class":"P",
    "gn:feature_code":"PPL",
    "gn:name":"Dvadtsatka",
    "gn:population":0,
    "gn:timezone":"Asia/Yekaterinburg",
    "iso:country":"RU",
    "name:eng_x_preferred":[
        "Dvadtsatka"
    ],
    "name:nor_x_preferred":[
        "Dvadtsatka"
    ],
    "name:rus_x_preferred":[
        "\u0414\u0432\u0430\u0434\u0446\u0430\u0442\u043a\u0430"
    ],
    "name:und_x_variant":[
        "\u0414\u0432\u0430\u0434\u0446\u0430\u0442\u043a\u0430"
    ],
    "wof:name":"Dvadtsatka",
    "wof:placetype":"locality"
},
  "geometry": {"coordinates":[58.65807,60.45281],"type":"Point"}
}