{
  "type": "Feature",
  "properties": {
    "gn:admin1_code":"51",
    "gn:asciiname":"Petryaksy",
    "gn:country_code":"RU",
    "gn:dem":104,
    "gn:feature_class":"P",
    "gn:feature_code":"PPL",
    "gn:name":"Petryaksy",
    "gn:population":0,
    "gn:timezone":"Europe/Moscow",
    "iso:country":"RU",
    "name:eng_x_preferred":[
        "Petryaksy"
    ],
    "name:nor_x_preferred":[
        "Petrjaksy"
    ],
    "name:rus_x_preferred":[
        "\u041f\u0435\u0442\u0440\u044f\u043a\u0441\u044b"
    ],
    "name:und_x_variant":[
        "Petraksa",
        "Petryaksa"
    ],
    "wof:name":"Petryaksy",
    "wof:placetype":"locality"
},
  "geometry": {"coordinates":[46.03296,55.41338],"type":"Point"}
}