{
  "type": "Feature",
  "properties": {
    "gn:admin1_code":"77.0",
    "gn:asciiname":"Chudinkovo",
    "gn:country_code":"RU",
    "gn:dem":148,
    "gn:feature_class":"P",
    "gn:feature_code":"PPL",
    "gn:name":"Chudinkovo",
    "gn:population":0,
    "gn:timezone":"Europe/Moscow",
    "iso:country":"RU",
    "name:rus_x_preferred":[
        "\u0427\u0443\u0434\u0438\u043d\u043a\u043e\u0432\u043e"
    ],
    "name:und_x_variant":[
        "\u0427\u0443\u0434\u0438\u043d\u043a\u043e\u0432\u043e"
    ],
    "wof:name":"Chudinkovo",
    "wof:placetype":"locality"
},
  "geometry": {"coordinates":[35.45,56.66667],"type":"Point"}
}