{
  "type": "Feature",
  "properties": {
    "gn:admin1_code":"53",
    "gn:asciiname":"Verkh-Achino",
    "gn:country_code":"RU",
    "gn:dem":233,
    "gn:feature_class":"P",
    "gn:feature_code":"PPL",
    "gn:name":"Verkh-Achino",
    "gn:population":0,
    "gn:timezone":"Asia/Novosibirsk",
    "iso:country":"RU",
    "name:rus_x_preferred":[
        "\u0412\u0435\u0440\u0445-\u0410\u0447\u0438\u043d\u043e"
    ],
    "name:und_x_variant":[
        "Verkhniy Achinskiy",
        "Verkhneye Achino",
        "Verkh-Achino"
    ],
    "wof:name":"Verkh-Achino",
    "wof:placetype":"locality"
},
  "geometry": {"coordinates":[84.625,55.44361],"type":"Point"}
}