{
  "type": "Feature",
  "properties": {
    "gn:admin1_code":"84",
    "gn:asciiname":"Osemenitel'naya Stantsiya",
    "gn:country_code":"RU",
    "gn:dem":101,
    "gn:feature_class":"P",
    "gn:feature_code":"PPL",
    "gn:name":"Osemenitel\u2019naya Stantsiya",
    "gn:population":0,
    "gn:timezone":"Europe/Volgograd",
    "iso:country":"RU",
    "name:rus_x_preferred":[
        "\u041e\u0441\u0435\u043c\u0435\u043d\u0438\u0442\u0435\u043b\u044c\u043d\u0430\u044f \u0421\u0442\u0430\u043d\u0446\u0438\u044f"
    ],
    "name:und_x_variant":[
        "Osemenitel\u2019naya Stantsiya"
    ],
    "wof:name":"Osemenitel'naya Stantsiya",
    "wof:placetype":"locality"
},
  "geometry": {"coordinates":[44.39259000000001,48.73078],"type":"Point"}
}