{
  "type": "Feature",
  "properties": {
    "gn:admin1_code":"43",
    "gn:asciiname":"Ognevka",
    "gn:country_code":"RU",
    "gn:dem":234,
    "gn:feature_class":"P",
    "gn:feature_code":"PPL",
    "gn:name":"Ogn\u00ebvka",
    "gn:population":0,
    "gn:timezone":"Europe/Moscow",
    "iso:country":"RU",
    "name:rus_x_preferred":[
        "\u041e\u0433\u043d\u0451\u0432\u043a\u0430"
    ],
    "name:und_x_variant":[
        "Ogn\u00ebvka"
    ],
    "wof:name":"Ognevka",
    "wof:placetype":"locality"
},
  "geometry": {"coordinates":[38.29498,52.90266999999999],"type":"Point"}
}