{
  "type": "Feature",
  "properties": {
    "gn:admin1_code":"53",
    "gn:asciiname":"Kazanka",
    "gn:country_code":"RU",
    "gn:dem":106,
    "gn:feature_class":"P",
    "gn:feature_code":"PPL",
    "gn:name":"Kazanka",
    "gn:population":0,
    "gn:timezone":"Asia/Novosibirsk",
    "iso:country":"RU",
    "name:bul_x_preferred":[
        "\u041a\u0430\u0437\u0430\u043d\u043a\u0430"
    ],
    "name:ceb_x_preferred":[
        "Kazanka"
    ],
    "name:ces_x_preferred":[
        "Kazanka"
    ],
    "name:deu_x_preferred":[
        "Kasanka"
    ],
    "name:eng_x_preferred":[
        "Kazanka"
    ],
    "name:fra_x_preferred":[
        "Kazanka"
    ],
    "name:hun_x_preferred":[
        "Kazanka"
    ],
    "name:pol_x_preferred":[
        "Kazanka"
    ],
    "name:rus_x_preferred":[
        "\u0410\u043b\u0435\u043a\u0441\u0430\u043d\u0434\u0440\u043e-\u041d\u0435\u0432\u0441\u043a\u0438\u0439"
    ],
    "name:rus_x_variant":[
        "\u041a\u0430\u0437\u0430\u043d\u043a\u0430"
    ],
    "name:swe_x_preferred":[
        "Kasanka"
    ],
    "name:ukr_x_preferred":[
        "\u041a\u0430\u0437\u0430\u043d\u043a\u0430"
    ],
    "name:und_x_variant":[
        "Aleksandro-Nevskiy",
        "Kazanskiy",
        "\u041a\u0430\u0437\u0430\u043d\u043a\u0430",
        "Kazanka"
    ],
    "wof:name":"Kazanka",
    "wof:placetype":"locality"
},
  "geometry": {"coordinates":[77.43182,53.98244],"type":"Point"}
}