{
  "type": "Feature",
  "properties": {
    "gn:admin1_code":"22",
    "gn:asciiname":"Blagoveshchenka",
    "gn:country_code":"RU",
    "gn:dem":306,
    "gn:feature_class":"P",
    "gn:feature_code":"PPL",
    "gn:name":"Blagoveshchenka",
    "gn:population":0,
    "gn:timezone":"Europe/Moscow",
    "iso:country":"RU",
    "name:rus_x_preferred":[
        "\u0411\u043b\u0430\u0433\u043e\u0432\u0435\u0449\u0435\u043d\u043a\u0430"
    ],
    "name:und_x_variant":[
        "Otradnyy",
        "Blagoveshchenka"
    ],
    "wof:name":"Blagoveshchenka",
    "wof:placetype":"locality"
},
  "geometry": {"coordinates":[43.72,43.69278],"type":"Point"}
}