{
  "type": "Feature",
  "properties": {
    "gn:admin1_code":"55",
    "gn:asciiname":"Ziyanchurino",
    "gn:country_code":"RU",
    "gn:dem":181,
    "gn:feature_class":"P",
    "gn:feature_code":"PPL",
    "gn:name":"Ziyanchurino",
    "gn:population":0,
    "gn:timezone":"Asia/Yekaterinburg",
    "iso:country":"RU",
    "name:eng_x_preferred":[
        "Ziyanchurino"
    ],
    "name:nor_x_preferred":[
        "Zijantsjurino"
    ],
    "name:rus_x_preferred":[
        "\u0417\u0438\u044f\u043d\u0447\u0443\u0440\u0438\u043d\u043e"
    ],
    "name:und_x_variant":[
        "Siyanchurino",
        "Zianchurino"
    ],
    "wof:name":"Ziyanchurino",
    "wof:placetype":"locality"
},
  "geometry": {"coordinates":[56.91667,51.56284],"type":"Point"}
}