{
  "type": "Feature",
  "properties": {
    "gn:admin1_code":"93",
    "gn:asciiname":"Zhipkovshino",
    "gn:country_code":"RU",
    "gn:dem":708,
    "gn:feature_class":"P",
    "gn:feature_code":"PPL",
    "gn:name":"Zhipkovshino",
    "gn:population":0,
    "gn:timezone":"Asia/Chita",
    "iso:country":"RU",
    "name:eng_x_preferred":[
        "Zhipkovshino"
    ],
    "name:nor_x_preferred":[
        "Zjipkovsjtsjina"
    ],
    "name:rus_x_preferred":[
        "\u0416\u0438\u043f\u043a\u043e\u0432\u0449\u0438\u043d\u0430"
    ],
    "name:und_x_variant":[
        "Zhipkoshino",
        "Zhipkovshchino",
        "Zhipkoshinskoye",
        "Zhipkovshchina",
        "Zhipkoshinsk",
        "Zhipkovshino"
    ],
    "wof:name":"Zhipkovshino",
    "wof:placetype":"locality"
},
  "geometry": {"coordinates":[113.01134999999999,51.80302],"type":"Point"}
}