{
  "type": "Feature",
  "properties": {
    "gn:country":"RU",
    "gn:fcode":"PPL",
    "gn:pop":1805,
    "iso:country":"RU",
    "name:eng_x_preferred":[
        "Atagay"
    ],
    "name:rus_x_preferred":[
        "\u0410\u0442\u0430\u0433\u0430\u0439"
    ],
    "qs:name":"Atagay",
    "qs:name_adm0":"Russia",
    "qs:name_adm1":"Irkutsk Oblast",
    "qs:photos_9r":0,
    "qs:photos_sr":0,
    "qs:placetype":"Town",
    "qs:pop_sr":"3",
    "wof:name":"Atagay",
    "wof:placetype":"locality",
    "wof:population":1805
},
  "geometry": {"coordinates":[99.3875,55.1033],"type":"Point"}
}