{
  "type": "Feature",
  "properties": {
    "gn:admin1_code":"70",
    "gn:asciiname":"Poperechnyy",
    "gn:country_code":"RU",
    "gn:dem":131,
    "gn:feature_class":"P",
    "gn:feature_code":"PPL",
    "gn:name":"Poperechnyy",
    "gn:population":0,
    "gn:timezone":"Europe/Moscow",
    "iso:country":"RU",
    "name:rus_x_preferred":[
        "\u041f\u043e\u043f\u0435\u0440\u0435\u0447\u043d\u044b\u0439"
    ],
    "name:und_x_variant":[
        "\u041f\u043e\u043f\u0435\u0440\u0435\u0447\u043d\u044b\u0439"
    ],
    "wof:name":"Poperechnyy",
    "wof:placetype":"locality"
},
  "geometry": {"coordinates":[43.2575,45.42167],"type":"Point"}
}