{
  "type": "Feature",
  "properties": {
    "gn:admin1_code":"33",
    "gn:asciiname":"Onuchino",
    "gn:country_code":"RU",
    "gn:dem":183,
    "gn:feature_class":"P",
    "gn:feature_code":"PPL",
    "gn:name":"Onuchino",
    "gn:population":0,
    "gn:timezone":"Europe/Kirov",
    "iso:country":"RU",
    "name:rus_x_preferred":[
        "\u041e\u043d\u0443\u0447\u0438\u043d\u043e"
    ],
    "name:und_x_variant":[
        "\u041e\u043d\u0443\u0447\u0438\u043d\u043e"
    ],
    "wof:name":"Onuchino",
    "wof:placetype":"locality"
},
  "geometry": {"coordinates":[48.83333,57.28333000000001],"type":"Point"}
}