{
  "type": "Feature",
  "properties": {
    "gn:admin1_code":"69",
    "gn:asciiname":"Demidovka",
    "gn:country_code":"RU",
    "gn:dem":193,
    "gn:feature_class":"P",
    "gn:feature_code":"PPL",
    "gn:name":"Demidovka",
    "gn:population":0,
    "gn:timezone":"Europe/Moscow",
    "iso:country":"RU",
    "name:rus_x_preferred":[
        "\u0414\u0435\u043c\u0438\u0434\u043e\u0432\u043a\u0430"
    ],
    "name:und_x_variant":[
        "\u0414\u0435\u043c\u0438\u0434\u043e\u0432\u043a\u0430"
    ],
    "wof:name":"Demidovka",
    "wof:placetype":"locality"
},
  "geometry": {"coordinates":[31.85343,54.75449],"type":"Point"}
}