{
  "type": "Feature",
  "properties": {
    "gn:admin1_code":"42.0",
    "gn:asciiname":"Bol'shiye Kolpany",
    "gn:country_code":"RU",
    "gn:dem":101,
    "gn:feature_class":"P",
    "gn:feature_code":"PPL",
    "gn:name":"Bol\u2019shiye Kolpany",
    "gn:population":0,
    "gn:timezone":"Europe/Moscow",
    "iso:country":"RU",
    "name:fin_x_preferred":[
        "Suuri-Kolppana"
    ],
    "name:rus_x_preferred":[
        "\u0411\u043e\u043b\u044c\u0448\u0438\u0435 \u041a\u043e\u043b\u043f\u0430\u043d\u044b"
    ],
    "name:und_x_variant":[
        "Bol\u2019shoye Kolpano",
        "Bol\u2019shiye Kolpany"
    ],
    "wof:name":"Bol'shiye Kolpany",
    "wof:placetype":"locality"
},
  "geometry": {"coordinates":[30.06944,59.52333],"type":"Point"}
}