{
  "type": "Feature",
  "properties": {
    "gn:admin1_code":"40",
    "gn:asciiname":"Shabarchina",
    "gn:country_code":"RU",
    "gn:dem":76,
    "gn:feature_class":"P",
    "gn:feature_code":"PPL",
    "gn:name":"Shabarchina",
    "gn:population":0,
    "gn:timezone":"Asia/Yekaterinburg",
    "iso:country":"RU",
    "name:rus_x_preferred":[
        "\u0428\u0430\u0431\u0430\u0440\u0447\u0438\u043d\u0430"
    ],
    "name:und_x_variant":[
        "\u0428\u0430\u0431\u0430\u0440\u0447\u0438\u043d\u0430"
    ],
    "wof:name":"Shabarchina",
    "wof:placetype":"locality"
},
  "geometry": {"coordinates":[64.46250000000001,55.97167],"type":"Point"}
}