{
  "type": "Feature",
  "properties": {
    "gn:admin1_code":"10",
    "gn:asciiname":"Kositsy",
    "gn:country_code":"RU",
    "gn:dem":170,
    "gn:feature_class":"P",
    "gn:feature_code":"PPL",
    "gn:name":"Kositsy",
    "gn:population":0,
    "gn:timezone":"Europe/Moscow",
    "iso:country":"RU",
    "name:rus_x_preferred":[
        "\u041a\u043e\u0441\u0438\u0446\u044b"
    ],
    "wof:name":"Kositsy",
    "wof:placetype":"locality"
},
  "geometry": {"coordinates":[34.4764,52.0619],"type":"Point"}
}