{
  "type": "Feature",
  "properties": {
    "gn:admin1_code":"05",
    "gn:asciiname":"Shcheglovka",
    "gn:cc2":"RU",
    "gn:country_code":"RU",
    "gn:dem":259,
    "gn:feature_class":"P",
    "gn:feature_code":"PPL",
    "gn:name":"Shcheglovka",
    "gn:population":0,
    "gn:timezone":"Asia/Yakutsk",
    "iso:country":"RU",
    "name:rus_x_preferred":[
        "\u0429\u0435\u0433\u043b\u043e\u0432\u043a\u0430"
    ],
    "name:und_x_variant":[
        "Shchegolevskiy",
        "Shchegalevskiy",
        "Shcheglovka",
        "\u0429\u0435\u0433\u043b\u043e\u0432\u043a\u0430"
    ],
    "wof:name":"Shcheglovka",
    "wof:placetype":"locality"
},
  "geometry": {"coordinates":[127.03333000000001,51.93333],"type":"Point"}
}