{
  "type": "Feature",
  "properties": {
    "gn:admin1_code":"21.0",
    "gn:asciiname":"Boris Gleb",
    "gn:country_code":"RU",
    "gn:dem":136,
    "gn:feature_class":"P",
    "gn:feature_code":"PPL",
    "gn:name":"Boris Gleb",
    "gn:population":0,
    "gn:timezone":"Europe/Moscow",
    "iso:country":"RU",
    "name:rus_x_preferred":[
        "\u0411\u043e\u0440\u0438\u0441 \u0413\u043b\u0435\u0431"
    ],
    "name:und_x_variant":[
        "\u0411\u043e\u0440\u0438\u0441 \u0413\u043b\u0435\u0431"
    ],
    "wof:name":"Boris Gleb",
    "wof:placetype":"locality"
},
  "geometry": {"coordinates":[41.67198,57.10496],"type":"Point"}
}