{
  "type": "Feature",
  "properties": {
    "gn:admin1_code":"61.0",
    "gn:asciiname":"Novospasovka",
    "gn:country_code":"RU",
    "gn:dem":169,
    "gn:feature_class":"P",
    "gn:feature_code":"PPL",
    "gn:name":"Novospasovka",
    "gn:population":0,
    "gn:timezone":"Europe/Moscow",
    "iso:country":"RU",
    "name:eng_x_preferred":[
        "Novo-Spasovka"
    ],
    "name:nor_x_preferred":[
        "Novospasovka"
    ],
    "name:rus_x_preferred":[
        "\u041d\u043e\u0432\u043e\u0441\u043f\u0430\u0441\u043e\u0432\u043a\u0430"
    ],
    "wof:name":"Novospasovka",
    "wof:placetype":"locality"
},
  "geometry": {"coordinates":[40.45572,48.9112],"type":"Point"}
}