{
  "type": "Feature",
  "properties": {
    "gn:admin1_code":"20",
    "gn:asciiname":"Krasnoozerskiy",
    "gn:country_code":"RU",
    "gn:dem":476,
    "gn:feature_class":"P",
    "gn:feature_code":"PPL",
    "gn:name":"Krasnooz\u00ebrskiy",
    "gn:population":0,
    "gn:timezone":"Asia/Irkutsk",
    "iso:country":"RU",
    "name:rus_x_preferred":[
        "\u041a\u0440\u0430\u0441\u043d\u043e\u043e\u0437\u0451\u0440\u0441\u043a\u0438\u0439"
    ],
    "name:und_x_variant":[
        "Krasnooz\u00ebrskiy"
    ],
    "wof:name":"Krasnoozerskiy",
    "wof:placetype":"locality"
},
  "geometry": {"coordinates":[100.6836,54.2433],"type":"Point"}
}