{
  "type": "Feature",
  "properties": {
    "gn:admin1_code":"60",
    "gn:asciiname":"Slepni",
    "gn:country_code":"RU",
    "gn:dem":76,
    "gn:feature_class":"P",
    "gn:feature_code":"PPL",
    "gn:name":"Slepni",
    "gn:population":0,
    "gn:timezone":"Europe/Moscow",
    "iso:country":"RU",
    "name:rus_x_preferred":[
        "\u0421\u043b\u0435\u043f\u043d\u0438"
    ],
    "name:und_x_variant":[
        "Seredkino-Slepni",
        "Slepni"
    ],
    "wof:name":"Slepni",
    "wof:placetype":"locality"
},
  "geometry": {"coordinates":[28.79252,57.10837],"type":"Point"}
}