{
  "type": "Feature",
  "properties": {
    "gn:admin1_code":"57.0",
    "gn:asciiname":"Pervoye Maya",
    "gn:country_code":"RU",
    "gn:dem":263,
    "gn:feature_class":"P",
    "gn:feature_code":"PPL",
    "gn:name":"Pervoye Maya",
    "gn:population":0,
    "gn:timezone":"Europe/Moscow",
    "iso:country":"RU",
    "name:rus_x_preferred":[
        "\u041f\u0435\u0440\u0432\u043e\u0435 \u041c\u0430\u044f"
    ],
    "wof:name":"Pervoye Maya",
    "wof:placetype":"locality"
},
  "geometry": {"coordinates":[45.91951,53.39574],"type":"Point"}
}