{
  "type": "Feature",
  "properties": {
    "gn:admin1_code":"47",
    "gn:asciiname":"Lapkovo",
    "gn:country_code":"RU",
    "gn:dem":232,
    "gn:feature_class":"P",
    "gn:feature_code":"PPL",
    "gn:name":"Lapkovo",
    "gn:population":0,
    "gn:timezone":"Europe/Moscow",
    "iso:country":"RU",
    "name:rus_x_preferred":[
        "\u041b\u0430\u043f\u043a\u043e\u0432\u043e"
    ],
    "name:und_x_variant":[
        "\u041b\u0430\u043f\u043a\u043e\u0432\u043e"
    ],
    "wof:name":"Lapkovo",
    "wof:placetype":"locality"
},
  "geometry": {"coordinates":[35.39694,55.245],"type":"Point"}
}