{
  "type": "Feature",
  "properties": {
    "gn:admin1_code":"28",
    "gn:asciiname":"Sorronniyemi",
    "gn:country_code":"RU",
    "gn:dem":115,
    "gn:feature_class":"P",
    "gn:feature_code":"PPL",
    "gn:name":"Sorronniyemi",
    "gn:population":0,
    "gn:timezone":"Europe/Moscow",
    "iso:country":"RU",
    "name:fin_x_preferred":[
        "Tsorinniemi"
    ],
    "name:rus_x_preferred":[
        "\u0421\u043e\u0440\u0440\u043e\u043d\u043d\u0438\u0435\u043c\u0438"
    ],
    "name:und_x_variant":[
        "\u0421\u043e\u0440\u0440\u043e\u043d\u043d\u0438\u0435\u043c\u0438",
        "Tsoroinniemi",
        "Sorronniemi"
    ],
    "wof:name":"Sorronniyemi",
    "wof:placetype":"locality"
},
  "geometry": {"coordinates":[32.59661,61.83821],"type":"Point"}
}