{
  "type": "Feature",
  "properties": {
    "gn:admin1_code":"47.0",
    "gn:asciiname":"Akhmatovo",
    "gn:country_code":"RU",
    "gn:dem":194,
    "gn:feature_class":"P",
    "gn:feature_code":"PPL",
    "gn:name":"Akhmatovo",
    "gn:population":0,
    "gn:timezone":"Europe/Moscow",
    "iso:country":"RU",
    "name:nor_x_preferred":[
        "Akhmatovo"
    ],
    "name:rus_x_preferred":[
        "\u0410\u0445\u043c\u0430\u0442\u043e\u0432\u043e"
    ],
    "wof:name":"Akhmatovo",
    "wof:placetype":"locality"
},
  "geometry": {"coordinates":[36.26583,55.23278000000001],"type":"Point"}
}