{
  "type": "Feature",
  "properties": {
    "gn:admin1_code":"10",
    "gn:asciiname":"Novoye",
    "gn:country_code":"RU",
    "gn:dem":190,
    "gn:feature_class":"P",
    "gn:feature_code":"PPL",
    "gn:name":"Novoye",
    "gn:population":0,
    "gn:timezone":"Europe/Moscow",
    "iso:country":"RU",
    "name:rus_x_preferred":[
        "\u041d\u043e\u0432\u043e\u0435"
    ],
    "name:und_x_variant":[
        "Nizhniye Avchukhi",
        "Avchukhi",
        "Novoye Nizhniye Avchukhi",
        "Novoye"
    ],
    "wof:name":"Novoye",
    "wof:placetype":"locality"
},
  "geometry": {"coordinates":[34.85,52.5912],"type":"Point"}
}