{
  "type": "Feature",
  "properties": {
    "gn:admin1_code":"47.0",
    "gn:asciiname":"Baskachi",
    "gn:country_code":"RU",
    "gn:dem":172,
    "gn:feature_class":"P",
    "gn:feature_code":"PPL",
    "gn:name":"Baskachi",
    "gn:population":0,
    "gn:timezone":"Europe/Moscow",
    "iso:country":"RU",
    "name:nor_x_preferred":[
        "Baskatsji"
    ],
    "name:rus_x_preferred":[
        "\u0411\u0430\u0441\u043a\u0430\u0447\u0438"
    ],
    "wof:name":"Baskachi",
    "wof:placetype":"locality"
},
  "geometry": {"coordinates":[38.31667,54.85],"type":"Point"}
}