{
  "type": "Feature",
  "properties": {
    "gn:admin1_code":"60",
    "gn:asciiname":"Kryzhovo",
    "gn:country_code":"RU",
    "gn:dem":154,
    "gn:feature_class":"P",
    "gn:feature_code":"PPL",
    "gn:name":"Kryzhovo",
    "gn:population":0,
    "gn:timezone":"Europe/Moscow",
    "iso:country":"RU",
    "name:rus_x_preferred":[
        "\u041a\u0440\u044b\u0436\u043e\u0432\u043e"
    ],
    "name:und_x_variant":[
        "\u041a\u0440\u044b\u0436\u043e\u0432\u043e"
    ],
    "wof:name":"Kryzhovo",
    "wof:placetype":"locality"
},
  "geometry": {"coordinates":[29.7049,56.9357],"type":"Point"}
}