{
  "type": "Feature",
  "properties": {
    "gn:admin1_code":"61",
    "gn:asciiname":"Zvonkiy",
    "gn:country_code":"RU",
    "gn:dem":84,
    "gn:feature_class":"P",
    "gn:feature_code":"PPL",
    "gn:name":"Zvonkiy",
    "gn:population":0,
    "gn:timezone":"Europe/Moscow",
    "iso:country":"RU",
    "wof:name":"Zvonkiy",
    "wof:placetype":"locality"
},
  "geometry": {"coordinates":[40.12583,47.04417],"type":"Point"}
}