{
  "type": "Feature",
  "properties": {
    "gn:admin1_code":"85.0",
    "gn:asciiname":"Glazovata",
    "gn:cc2":"RU",
    "gn:country_code":"RU",
    "gn:dem":142,
    "gn:feature_class":"P",
    "gn:feature_code":"PPL",
    "gn:name":"Glazovata",
    "gn:population":0,
    "gn:timezone":"Europe/Moscow",
    "iso:country":"RU",
    "name:rus_x_preferred":[
        "\u0413\u043b\u0430\u0437\u043e\u0432\u0430\u0442\u0430"
    ],
    "name:und_x_variant":[
        "Glazatovo",
        "Glazovata",
        "\u0413\u043b\u0430\u0437\u043e\u0432\u0430\u0442\u0430"
    ],
    "wof:name":"Glazovata",
    "wof:placetype":"locality"
},
  "geometry": {"coordinates":[45.98333,60.65],"type":"Point"}
}