{
  "type": "Feature",
  "properties": {
    "gn:admin1_code":"37",
    "gn:asciiname":"Smorodinka",
    "gn:cc2":"RU",
    "gn:country_code":"RU",
    "gn:dem":160,
    "gn:feature_class":"P",
    "gn:feature_code":"PPL",
    "gn:name":"Smorodinka",
    "gn:population":0,
    "gn:timezone":"Europe/Moscow",
    "iso:country":"RU",
    "name:rus_x_preferred":[
        "\u0421\u043c\u043e\u0440\u043e\u0434\u0438\u043d\u043a\u0430"
    ],
    "name:und_x_variant":[
        "Golodayka",
        "Smorodinka"
    ],
    "wof:name":"Smorodinka",
    "wof:placetype":"locality"
},
  "geometry": {"coordinates":[41.58333,58.15],"type":"Point"}
}