{
  "type": "Feature",
  "properties": {
    "gn:admin1_code":"17",
    "gn:asciiname":"Pilyaki",
    "gn:country_code":"RU",
    "gn:dem":1057,
    "gn:feature_class":"P",
    "gn:feature_code":"PPL",
    "gn:name":"Pilyaki",
    "gn:population":0,
    "gn:timezone":"Europe/Moscow",
    "iso:country":"RU",
    "name:rus_x_preferred":[
        "\u041f\u0438\u043b\u044f\u043a\u0438"
    ],
    "name:und_x_variant":[
        "Pilyagat",
        "Pilaki",
        "Pilagat",
        "Pilyaki",
        "\u041f\u0438\u043b\u044f\u043a\u0438"
    ],
    "wof:name":"Pilyaki",
    "wof:placetype":"locality"
},
  "geometry": {"coordinates":[47.85667,42.00537],"type":"Point"}
}