{
  "type": "Feature",
  "properties": {
    "gn:admin1_code":"44",
    "gn:asciiname":"Mayakan",
    "gn:cc2":"RU",
    "gn:country_code":"RU",
    "gn:dem":314,
    "gn:feature_class":"P",
    "gn:feature_code":"PPL",
    "gn:name":"Mayakan",
    "gn:population":0,
    "gn:timezone":"Asia/Magadan",
    "iso:country":"RU",
    "name:rus_x_preferred":[
        "\u041c\u0430\u044f\u043a\u0430\u043d"
    ],
    "name:und_x_variant":[
        "Mayakon",
        "Mayakan"
    ],
    "wof:name":"Mayakan",
    "wof:placetype":"locality"
},
  "geometry": {"coordinates":[151.75,60.06667],"type":"Point"}
}