{
  "type": "Feature",
  "properties": {
    "gn:admin1_code":"78",
    "gn:asciiname":"Shantemir",
    "gn:country_code":"RU",
    "gn:dem":137,
    "gn:feature_class":"P",
    "gn:feature_code":"PPL",
    "gn:name":"Shantemir",
    "gn:population":0,
    "gn:timezone":"Asia/Yekaterinburg",
    "iso:country":"RU",
    "name:rus_x_preferred":[
        "\u0428\u0430\u043d\u0442\u0435\u043c\u0438\u0440"
    ],
    "wof:name":"Shantemir",
    "wof:placetype":"locality"
},
  "geometry": {"coordinates":[69.63561999999999,55.88741],"type":"Point"}
}