{
  "type": "Feature",
  "properties": {
    "gn:admin1_code":"52",
    "gn:asciiname":"Lichino",
    "gn:country_code":"RU",
    "gn:dem":84,
    "gn:feature_class":"P",
    "gn:feature_code":"PPL",
    "gn:name":"Lichino",
    "gn:population":0,
    "gn:timezone":"Europe/Moscow",
    "iso:country":"RU",
    "name:rus_x_preferred":[
        "\u041b\u0438\u0447\u0438\u043d\u043e"
    ],
    "wof:name":"Lichino",
    "wof:placetype":"locality"
},
  "geometry": {"coordinates":[30.86037,57.87243],"type":"Point"}
}