{
  "type": "Feature",
  "properties": {
    "gn:admin1_code":"52",
    "gn:asciiname":"Knyazhevo",
    "gn:country_code":"RU",
    "gn:dem":140,
    "gn:feature_class":"P",
    "gn:feature_code":"PPL",
    "gn:name":"Knyazh\u00ebvo",
    "gn:population":0,
    "gn:timezone":"Europe/Moscow",
    "iso:country":"RU",
    "name:bul_x_preferred":[
        "\u041a\u043d\u044f\u0436\u0435\u0432\u043e"
    ],
    "name:deu_x_preferred":[
        "Knjaschewo"
    ],
    "name:fas_x_preferred":[
        "\u06a9\u0646\u06cc\u0627\u0698\u0648\u0648"
    ],
    "name:kaz_x_preferred":[
        "\u041a\u043d\u044f\u0436\u0435\u0432\u043e"
    ],
    "name:pol_x_preferred":[
        "Knja\u017cewo"
    ],
    "name:ron_x_preferred":[
        "Kneajevo"
    ],
    "name:rus_x_preferred":[
        "\u041a\u043d\u044f\u0436\u0451\u0432\u043e"
    ],
    "name:rus_x_variant":[
        "\u041a\u043d\u044f\u0436\u0435\u0432\u043e"
    ],
    "name:ukr_x_preferred":[
        "\u041a\u043d\u044f\u0436\u0435\u0432\u043e"
    ],
    "name:und_x_variant":[
        "Knyazh\u00ebvo",
        "\u041a\u043d\u044f\u0436\u0451\u0432\u043e"
    ],
    "wof:name":"Knyazhevo",
    "wof:placetype":"locality"
},
  "geometry": {"coordinates":[32.97790999999999,58.01125],"type":"Point"}
}