{
  "type": "Feature",
  "properties": {
    "gn:admin1_code":"38",
    "gn:asciiname":"Nezamayevskiy",
    "gn:country_code":"RU",
    "gn:dem":72,
    "gn:feature_class":"P",
    "gn:feature_code":"PPL",
    "gn:name":"Nezamayevskiy",
    "gn:population":0,
    "gn:timezone":"Europe/Moscow",
    "iso:country":"RU",
    "name:eng_x_preferred":[
        "Nezamayevskiy"
    ],
    "name:nor_x_preferred":[
        "Nezamajevskij"
    ],
    "name:rus_x_preferred":[
        "\u041d\u0435\u0437\u0430\u043c\u0430\u0435\u0432\u0441\u043a\u0438\u0439"
    ],
    "name:und_x_variant":[
        "Nezamovskiy",
        "\u041d\u0435\u0437\u0430\u043c\u0430\u0435\u0432\u0441\u043a\u0438\u0439",
        "Nezamayevskiy"
    ],
    "wof:name":"Nezamayevskiy",
    "wof:placetype":"locality"
},
  "geometry": {"coordinates":[40.3808,46.11892],"type":"Point"}
}