{
  "type": "Feature",
  "properties": {
    "gn:admin1_code":"90",
    "gn:asciiname":"Pakli",
    "gn:country_code":"RU",
    "gn:dem":110,
    "gn:feature_class":"P",
    "gn:feature_code":"PPL",
    "gn:name":"Pakli",
    "gn:population":0,
    "gn:timezone":"Asia/Yekaterinburg",
    "iso:country":"RU",
    "name:eng_x_preferred":[
        "Pakli"
    ],
    "name:nor_x_preferred":[
        "Pakli"
    ],
    "name:rus_x_preferred":[
        "\u041f\u0430\u043a\u043b\u0438"
    ],
    "name:und_x_variant":[
        "\u041f\u0430\u043a\u043b\u0438"
    ],
    "wof:name":"Pakli",
    "wof:placetype":"locality"
},
  "geometry": {"coordinates":[55.2681,57.2695],"type":"Point"}
}