{
  "type": "Feature",
  "properties": {
    "gn:admin1_code":"30",
    "gn:asciiname":"Konskaya Yarmarka",
    "gn:cc2":"RU",
    "gn:country_code":"RU",
    "gn:dem":28,
    "gn:feature_class":"P",
    "gn:feature_code":"PPL",
    "gn:name":"Konskaya Yarmarka",
    "gn:population":0,
    "gn:timezone":"Asia/Vladivostok",
    "iso:country":"RU",
    "name:rus_x_preferred":[
        "\u041a\u043e\u043d\u0441\u043a\u0430\u044f \u042f\u0440\u043c\u0430\u0440\u043a\u0430"
    ],
    "name:und_x_variant":[
        "Konskaya Yarmorka",
        "Konskaya Yarmarka"
    ],
    "wof:name":"Konskaya Yarmarka",
    "wof:placetype":"locality"
},
  "geometry": {"coordinates":[142.93333000000001,59.45],"type":"Point"}
}