{
  "type": "Feature",
  "properties": {
    "gn:admin1_code":"76",
    "gn:asciiname":"Chervonyy Yar",
    "gn:country_code":"RU",
    "gn:dem":256,
    "gn:feature_class":"P",
    "gn:feature_code":"PPL",
    "gn:name":"Chervonyy Yar",
    "gn:population":0,
    "gn:timezone":"Europe/Moscow",
    "iso:country":"RU",
    "name:rus_x_preferred":[
        "\u0427\u0435\u0440\u0432\u043e\u043d\u044b\u0439 \u042f\u0440"
    ],
    "name:und_x_variant":[
        "\u0427\u0435\u0440\u0432\u043e\u043d\u044b\u0439 \u042f\u0440"
    ],
    "wof:name":"Chervonyy Yar",
    "wof:placetype":"locality"
},
  "geometry": {"coordinates":[37.645,53.44],"type":"Point"}
}