{
  "type": "Feature",
  "properties": {
    "gn:admin1_code":"84.0",
    "gn:asciiname":"Frolov",
    "gn:country_code":"RU",
    "gn:dem":79,
    "gn:feature_class":"P",
    "gn:feature_code":"PPL",
    "gn:name":"Frolov",
    "gn:population":0,
    "gn:timezone":"Europe/Volgograd",
    "iso:country":"RU",
    "name:eng_x_preferred":[
        "Frolov"
    ],
    "name:nor_x_preferred":[
        "Frolov"
    ],
    "name:rus_x_preferred":[
        "\u0424\u0440\u043e\u043b\u043e\u0432"
    ],
    "name:und_x_variant":[
        "Frolovskiy",
        "\u0424\u0440\u043e\u043b\u043e\u0432",
        "Frolov"
    ],
    "wof:name":"Frolov",
    "wof:placetype":"locality"
},
  "geometry": {"coordinates":[42.6766,50.1223],"type":"Point"}
}