{
  "type": "Feature",
  "properties": {
    "gn:admin1_code":"84.0",
    "gn:asciiname":"Frolov",
    "gn:country_code":"RU",
    "gn:dem":79,
    "gn:feature_class":"P",
    "gn:feature_code":"PPL",
    "gn:name":"Frolov",
    "gn:population":0,
    "gn:timezone":"Europe/Volgograd",
    "iso:country":"RU",
    "name:bel_x_preferred":[
        "\u0424\u0440\u0430\u043b\u043e\u045e"
    ],
    "name:deu_x_preferred":[
        "Frolow"
    ],
    "name:eng_x_preferred":[
        "Frolov"
    ],
    "name:fra_x_preferred":[
        "Frolov"
    ],
    "name:hye_x_preferred":[
        "\u0556\u0580\u0578\u056c\u0578\u057e"
    ],
    "name:ita_x_preferred":[
        "Frolov"
    ],
    "name:jpn_x_preferred":[
        "\u30d5\u30ed\u30ed\u30d5"
    ],
    "name:lav_x_preferred":[
        "Frolovs"
    ],
    "name:nor_x_preferred":[
        "Frolov"
    ],
    "name:rus_x_preferred":[
        "\u0424\u0440\u043e\u043b\u043e\u0432"
    ],
    "name:slv_x_preferred":[
        "Frolov"
    ],
    "name:ukr_x_preferred":[
        "\u0424\u0440\u043e\u043b\u043e\u0432"
    ],
    "name:und_x_variant":[
        "Frolovskiy"
    ],
    "wof:name":"Frolov",
    "wof:placetype":"locality"
},
  "geometry": {"coordinates":[42.6766,50.1223],"type":"Point"}
}