{
  "type": "Feature",
  "properties": {
    "gn:admin1_code":"62",
    "gn:asciiname":"Yelizavetinka",
    "gn:country_code":"RU",
    "gn:dem":105,
    "gn:feature_class":"P",
    "gn:feature_code":"PPL",
    "gn:name":"Yelizavetinka",
    "gn:population":0,
    "gn:timezone":"Europe/Moscow",
    "iso:country":"RU",
    "wof:name":"Yelizavetinka",
    "wof:placetype":"locality"
},
  "geometry": {"coordinates":[39.56272,54.75261999999999],"type":"Point"}
}