{
  "type": "Feature",
  "properties": {
    "gn:admin1_code":"90.0",
    "gn:asciiname":"Orly",
    "gn:country_code":"RU",
    "gn:dem":232,
    "gn:feature_class":"P",
    "gn:feature_code":"PPL",
    "gn:name":"Orly",
    "gn:population":0,
    "gn:timezone":"Asia/Yekaterinburg",
    "iso:country":"RU",
    "name:azb_x_preferred":[
        "\u0627\u0648\u0631\u0644\u06cc"
    ],
    "name:cat_x_preferred":[
        "Orly"
    ],
    "name:ceb_x_preferred":[
        "Orly"
    ],
    "name:ces_x_preferred":[
        "Orly"
    ],
    "name:deu_x_preferred":[
        "Orly"
    ],
    "name:epo_x_preferred":[
        "Orly"
    ],
    "name:eus_x_preferred":[
        "Orly"
    ],
    "name:fas_x_preferred":[
        "\u0627\u0648\u0631\u0644\u06cc"
    ],
    "name:fra_x_preferred":[
        "Orly"
    ],
    "name:glg_x_preferred":[
        "Orly"
    ],
    "name:heb_x_preferred":[
        "\u05d0\u05d5\u05e8\u05dc\u05d9"
    ],
    "name:hun_x_preferred":[
        "Orly"
    ],
    "name:ita_x_preferred":[
        "Orly"
    ],
    "name:jpn_x_preferred":[
        "\u30aa\u30eb\u30ea\u30fc"
    ],
    "name:kaz_x_preferred":[
        "\u041e\u0440\u043b\u0438"
    ],
    "name:kor_x_preferred":[
        "\uc624\ub97c\ub9ac"
    ],
    "name:msa_x_preferred":[
        "Orly"
    ],
    "name:mzn_x_preferred":[
        "\u0627\u0648\u0631\u0644\u06cc"
    ],
    "name:nld_x_preferred":[
        "Orly"
    ],
    "name:nor_x_preferred":[
        "Orly"
    ],
    "name:oci_x_preferred":[
        "Orly"
    ],
    "name:pms_x_preferred":[
        "Orly"
    ],
    "name:pol_x_preferred":[
        "Orly"
    ],
    "name:por_x_preferred":[
        "Orly"
    ],
    "name:ron_x_preferred":[
        "Orly"
    ],
    "name:rus_x_preferred":[
        "\u041e\u0440\u043b\u044b"
    ],
    "name:rus_x_variant":[
        "\u041e\u0440\u043b\u0438"
    ],
    "name:sco_x_preferred":[
        "Orly"
    ],
    "name:slk_x_preferred":[
        "Orly"
    ],
    "name:slv_x_preferred":[
        "Orly"
    ],
    "name:spa_x_preferred":[
        "Orly"
    ],
    "name:srp_x_preferred":[
        "\u041e\u0440\u043b\u0438"
    ],
    "name:swa_x_preferred":[
        "Orly"
    ],
    "name:swe_x_preferred":[
        "Orly"
    ],
    "name:ukr_x_preferred":[
        "\u041e\u0440\u043b\u0456"
    ],
    "name:vec_x_preferred":[
        "Orly"
    ],
    "name:vie_x_preferred":[
        "Orly"
    ],
    "name:vol_x_preferred":[
        "Orly"
    ],
    "name:war_x_preferred":[
        "Orly"
    ],
    "name:zho_x_preferred":[
        "\u5965\u5229"
    ],
    "wof:name":"Orly",
    "wof:placetype":"locality"
},
  "geometry": {"coordinates":[55.9581,58.455],"type":"Point"}
}