{
  "type": "Feature",
  "properties": {
    "gn:admin1_code":"23",
    "gn:asciiname":"Krytoy Yar",
    "gn:country_code":"RU",
    "gn:dem":42,
    "gn:feature_class":"P",
    "gn:feature_code":"PPL",
    "gn:name":"Krytoy Yar",
    "gn:population":0,
    "gn:timezone":"Europe/Kaliningrad",
    "iso:country":"RU",
    "name:rus_x_preferred":[
        "\u041a\u0440\u044b\u0442\u043e\u0439 \u042f\u0440"
    ],
    "wof:name":"Krytoy Yar",
    "wof:placetype":"locality"
},
  "geometry": {"coordinates":[21.01,54.40694000000001],"type":"Point"}
}