{
  "type": "Feature",
  "properties": {
    "gn:admin1_code":"88",
    "gn:asciiname":"Partusovo",
    "gn:country_code":"RU",
    "gn:dem":135,
    "gn:feature_class":"P",
    "gn:feature_code":"PPL",
    "gn:name":"Partusovo",
    "gn:population":0,
    "gn:timezone":"Europe/Moscow",
    "iso:country":"RU",
    "name:rus_x_preferred":[
        "\u041f\u0430\u0440\u0442\u0443\u0441\u043e\u0432\u043e"
    ],
    "wof:name":"Partusovo",
    "wof:placetype":"locality"
},
  "geometry": {"coordinates":[38.4787,57.4443],"type":"Point"}
}