{
  "type": "Feature",
  "properties": {
    "gn:admin1_code":"69",
    "gn:asciiname":"Shily",
    "gn:country_code":"RU",
    "gn:dem":184,
    "gn:feature_class":"P",
    "gn:feature_code":"PPL",
    "gn:name":"Shily",
    "gn:population":0,
    "gn:timezone":"Europe/Moscow",
    "iso:country":"RU",
    "name:rus_x_preferred":[
        "\u0428\u0438\u043b\u044b"
    ],
    "wof:name":"Shily",
    "wof:placetype":"locality"
},
  "geometry": {"coordinates":[32.93556,53.94167],"type":"Point"}
}