{
  "type": "Feature",
  "properties": {
    "gn:admin1_code":"6",
    "gn:asciiname":"Kevrola",
    "gn:country_code":"RU",
    "gn:dem":40,
    "gn:feature_class":"P",
    "gn:feature_code":"PPL",
    "gn:name":"Kevrola",
    "gn:population":0,
    "gn:timezone":"Europe/Moscow",
    "iso:country":"RU",
    "name:che_x_preferred":[
        "\u041a\u0435\u0432\u0440\u043e\u043b\u0430"
    ],
    "name:eng_x_preferred":[
        "Kevrola"
    ],
    "name:hye_x_preferred":[
        "\u053f\u0587\u0580\u0578\u056c\u0561"
    ],
    "name:nor_x_preferred":[
        "Kevrola"
    ],
    "name:rus_x_preferred":[
        "\u041a\u0435\u0432\u0440\u043e\u043b\u0430"
    ],
    "name:und_x_variant":[
        "Kovrola"
    ],
    "wof:name":"Kevrola",
    "wof:placetype":"locality"
},
  "geometry": {"coordinates":[44.5093,63.9529],"type":"Point"}
}