{
  "type": "Feature",
  "properties": {
    "gn:country":"RU",
    "gn:fcode":"PPL",
    "gn:population":1592,
    "iso:country":"RU",
    "name:eng_x_preferred":[
        "Girvas"
    ],
    "name:fin_x_preferred":[
        "Hirvas"
    ],
    "name:nor_x_preferred":[
        "Girvas"
    ],
    "name:olo_x_preferred":[
        "Hirvas"
    ],
    "name:rus_x_preferred":[
        "\u0413\u0438\u0440\u0432\u0430\u0441"
    ],
    "qs:name":"Girvas",
    "qs:name_adm0":"Russia",
    "qs:name_adm1":"Karelia Republic",
    "qs:photos_9k":1,
    "qs:photos_9r":1,
    "qs:photos_all":1,
    "qs:photos_sr":0,
    "qs:placetype":"Town",
    "qs:pop_sr":"4",
    "wof:name":"Girvas",
    "wof:placetype":"locality",
    "wof:population":1592
},
  "geometry": {"coordinates":[33.68482,62.47962],"type":"Point"}
}