{
  "type": "Feature",
  "properties": {
    "gn:admin1_code":"55",
    "gn:asciiname":"Psyanchino",
    "gn:country_code":"RU",
    "gn:dem":254,
    "gn:feature_class":"P",
    "gn:feature_code":"PPL",
    "gn:name":"Psyanchino",
    "gn:population":0,
    "gn:timezone":"Asia/Yekaterinburg",
    "iso:country":"RU",
    "name:rus_x_preferred":[
        "\u041f\u0441\u044f\u043d\u0447\u0438\u043d\u043e"
    ],
    "wof:name":"Psyanchino",
    "wof:placetype":"locality"
},
  "geometry": {"coordinates":[57.51667,51.45],"type":"Point"}
}