{
  "type": "Feature",
  "properties": {
    "gn:admin1_code":"34",
    "gn:asciiname":"Lemty",
    "gn:country_code":"RU",
    "gn:dem":74,
    "gn:feature_class":"P",
    "gn:feature_code":"PPL",
    "gn:name":"Lemty",
    "gn:population":0,
    "gn:timezone":"Europe/Moscow",
    "iso:country":"RU",
    "name:eng_x_preferred":[
        "Lemty"
    ],
    "name:nor_x_preferred":[
        "Lemty"
    ],
    "name:rus_x_preferred":[
        "\u041b\u0435\u043c\u0442\u044b"
    ],
    "name:und_x_variant":[
        "\u041b\u0435\u043c\u0442\u044b",
        "Lemty"
    ],
    "wof:name":"Lemty",
    "wof:placetype":"locality"
},
  "geometry": {"coordinates":[56.83575,63.86603],"type":"Point"}
}