{
  "type": "Feature",
  "properties": {
    "gn:admin1_code":"17",
    "gn:admin2_code":"Tlyaratinskiy Rayon",
    "gn:asciiname":"Kversatl'",
    "gn:country_code":"RU",
    "gn:dem":1856,
    "gn:feature_class":"P",
    "gn:feature_code":"PPL",
    "gn:name":"Kversatl\u2019",
    "gn:population":0,
    "gn:timezone":"Europe/Moscow",
    "iso:country":"RU",
    "name:rus_x_preferred":[
        "\u041a\u0432\u0435\u0440\u0441\u0430\u0442\u043b\u044c"
    ],
    "name:und_x_variant":[
        "Kversatl\u2019",
        "\u041a\u0432\u0435\u0440\u0441\u0430\u0442\u043b\u044c"
    ],
    "wof:name":"Kversatl'",
    "wof:placetype":"locality"
},
  "geometry": {"coordinates":[46.39268,42.30206],"type":"Point"}
}