{
  "type": "Feature",
  "properties": {
    "gn:admin1_code":"68",
    "gn:asciiname":"Novogeorgiyevskoye",
    "gn:country_code":"RU",
    "gn:dem":125,
    "gn:feature_class":"P",
    "gn:feature_code":"PPL",
    "gn:name":"Novogeorgiyevskoye",
    "gn:population":0,
    "gn:timezone":"Europe/Moscow",
    "iso:country":"RU",
    "name:rus_x_preferred":[
        "\u041d\u043e\u0432\u043e\u0433\u0435\u043e\u0440\u0433\u0438\u0435\u0432\u0441\u043a\u043e\u0435"
    ],
    "name:und_x_variant":[
        "Novo-Georgiyevskiy",
        "Novo-Georgevskiy",
        "Novogeorgiyevskoye"
    ],
    "wof:name":"Novogeorgiyevskoye",
    "wof:placetype":"locality"
},
  "geometry": {"coordinates":[44.70607,43.75755],"type":"Point"}
}