{
  "type": "Feature",
  "properties": {
    "gn:admin1_code":"54",
    "gn:asciiname":"Nizhniye Tunguzy",
    "gn:country_code":"RU",
    "gn:dem":115,
    "gn:feature_class":"P",
    "gn:feature_code":"PPL",
    "gn:name":"Nizhniye Tunguzy",
    "gn:population":0,
    "gn:timezone":"Asia/Omsk",
    "iso:country":"RU",
    "name:rus_x_preferred":[
        "\u041d\u0438\u0436\u043d\u0438\u0435 \u0422\u0443\u043d\u0433\u0443\u0437\u044b"
    ],
    "name:und_x_variant":[
        "Nizhniye Tunzy",
        "Nizhniye Tunguzy",
        "\u041d\u0438\u0436\u043d\u0438\u0435 \u0422\u0443\u043d\u0433\u0443\u0437\u044b"
    ],
    "wof:name":"Nizhniye Tunguzy",
    "wof:placetype":"locality"
},
  "geometry": {"coordinates":[76.07413000000003,56.97663000000001],"type":"Point"}
}