{
  "type": "Feature",
  "properties": {
    "gn:admin1_code":"69",
    "gn:asciiname":"Zhakovino",
    "gn:country_code":"RU",
    "gn:dem":215,
    "gn:feature_class":"P",
    "gn:feature_code":"PPL",
    "gn:name":"Zhakovino",
    "gn:population":0,
    "gn:timezone":"Europe/Moscow",
    "iso:country":"RU",
    "name:rus_x_preferred":[
        "\u0416\u0430\u043a\u043e\u0432\u0438\u043d\u043e"
    ],
    "wof:name":"Zhakovino",
    "wof:placetype":"locality"
},
  "geometry": {"coordinates":[32.2961,55.51432],"type":"Point"}
}