{
  "type": "Feature",
  "properties": {
    "gn:admin1_code":"65",
    "gn:asciiname":"Karpovka",
    "gn:country_code":"RU",
    "gn:dem":84,
    "gn:feature_class":"P",
    "gn:feature_code":"PPL",
    "gn:name":"Karpovka",
    "gn:population":0,
    "gn:timezone":"Europe/Samara",
    "iso:country":"RU",
    "name:rus_x_preferred":[
        "\u041a\u0430\u0440\u043f\u043e\u0432\u043a\u0430"
    ],
    "name:und_x_variant":[
        "\u041a\u0430\u0440\u043f\u043e\u0432\u043a\u0430"
    ],
    "wof:name":"Karpovka",
    "wof:placetype":"locality"
},
  "geometry": {"coordinates":[51.1015,53.1242],"type":"Point"}
}