{
  "type": "Feature",
  "properties": {
    "gn:country":"RU",
    "gn:fcode":"PPL",
    "gn:population":0,
    "iso:country":"RU",
    "name:eng_x_preferred":[
        "Plekhany"
    ],
    "name:nor_x_preferred":[
        "Plekhany"
    ],
    "name:rus_x_preferred":[
        "\u041f\u043b\u0435\u0445\u0430\u043d\u044b"
    ],
    "name:und_x_variant":[
        "Plekhani"
    ],
    "qs:name":"Plekhanj",
    "qs:name_adm0":"Russia",
    "qs:name_adm1":"Saratov Oblast",
    "qs:photos_9r":0,
    "qs:photos_sr":0,
    "qs:placetype":"Town",
    "qs:pop_sr":"0",
    "wof:name":"Plekhanj",
    "wof:placetype":"locality",
    "wof:population":0
},
  "geometry": {"coordinates":[47.36624,51.9706],"type":"Point"}
}