{
  "type": "Feature",
  "properties": {
    "gn:admin1_code":"8.0",
    "gn:asciiname":"Buady-Bash",
    "gn:country_code":"RU",
    "gn:dem":175,
    "gn:feature_class":"P",
    "gn:feature_code":"PPL",
    "gn:name":"Buady-Bash",
    "gn:population":0,
    "gn:timezone":"Asia/Yekaterinburg",
    "iso:country":"RU",
    "name:rus_x_preferred":[
        "\u0411\u0443\u0430\u0434\u044b-\u0411\u0430\u0448"
    ],
    "name:und_x_variant":[
        "\u0411\u0443\u0430\u0434\u044b-\u0411\u0430\u0448"
    ],
    "wof:name":"Buady-Bash",
    "wof:placetype":"locality"
},
  "geometry": {"coordinates":[55.61666999999999,56.23333],"type":"Point"}
}