{
  "type": "Feature",
  "properties": {
    "gn:admin1_code":"37",
    "gn:asciiname":"Semeshevo",
    "gn:country_code":"RU",
    "gn:dem":160,
    "gn:feature_class":"P",
    "gn:feature_code":"PPL",
    "gn:name":"Semeshevo",
    "gn:population":0,
    "gn:timezone":"Europe/Moscow",
    "iso:country":"RU",
    "name:rus_x_preferred":[
        "\u0421\u0435\u043c\u0435\u0448\u0435\u0432\u043e"
    ],
    "name:und_x_variant":[
        "\u0421\u0435\u043c\u0435\u0448\u0435\u0432\u043e"
    ],
    "wof:name":"Semeshevo",
    "wof:placetype":"locality"
},
  "geometry": {"coordinates":[42.6361,58.0874],"type":"Point"}
}