{
  "type": "Feature",
  "properties": {
    "gn:admin1_code":"13",
    "gn:asciiname":"Afonas'yevskiy",
    "gn:country_code":"RU",
    "gn:dem":215,
    "gn:feature_class":"P",
    "gn:feature_code":"PPL",
    "gn:name":"Afonas\u2019yevskiy",
    "gn:population":0,
    "gn:timezone":"Asia/Yekaterinburg",
    "iso:country":"RU",
    "name:nor_x_preferred":[
        "Afonasievskij"
    ],
    "name:rus_x_preferred":[
        "\u0410\u0444\u043e\u043d\u0430\u0441\u044c\u0435\u0432\u0441\u043a\u0438\u0439"
    ],
    "name:und_x_variant":[
        "Afanas\u2019yevskiy",
        "Afonas\u2019yevskiy"
    ],
    "wof:name":"Afonas'yevskiy",
    "wof:placetype":"locality"
},
  "geometry": {"coordinates":[61.25,54.21666999999999],"type":"Point"}
}