{
  "type": "Feature",
  "properties": {
    "gn:admin1_code":"45.0",
    "gn:asciiname":"Abdayevo",
    "gn:country_code":"RU",
    "gn:dem":176,
    "gn:feature_class":"P",
    "gn:feature_code":"PPL",
    "gn:name":"Abdayevo",
    "gn:population":0,
    "gn:timezone":"Europe/Moscow",
    "iso:country":"RU",
    "name:nor_x_preferred":[
        "Abdajevo"
    ],
    "name:rus_x_preferred":[
        "\u0410\u0431\u0434\u0430\u0435\u0432\u043e"
    ],
    "wof:name":"Abdayevo",
    "wof:placetype":"locality"
},
  "geometry": {"coordinates":[48.77861,56.38889],"type":"Point"}
}