{
  "type": "Feature",
  "properties": {
    "gn:admin1_code":"42.0",
    "gn:asciiname":"Agasheva",
    "gn:country_code":"RU",
    "gn:dem":77,
    "gn:feature_class":"P",
    "gn:feature_code":"PPL",
    "gn:name":"Agasheva",
    "gn:population":0,
    "gn:timezone":"Europe/Moscow",
    "iso:country":"RU",
    "name:nor_x_preferred":[
        "Agasjeva"
    ],
    "name:rus_x_preferred":[
        "\u0410\u0433\u0430\u0448\u0435\u0432\u0430"
    ],
    "wof:name":"Agasheva",
    "wof:placetype":"locality"
},
  "geometry": {"coordinates":[34.04602,60.56321],"type":"Point"}
}