{
  "type": "Feature",
  "properties": {
    "gn:admin1_code":"75",
    "gn:asciiname":"Novouralka",
    "gn:country_code":"RU",
    "gn:dem":62,
    "gn:feature_class":"P",
    "gn:feature_code":"PPL",
    "gn:name":"Novouralka",
    "gn:population":0,
    "gn:timezone":"Asia/Tomsk",
    "iso:country":"RU",
    "name:rus_x_preferred":[
        "\u041d\u043e\u0432\u043e\u0443\u0440\u0430\u043b\u043a\u0430"
    ],
    "name:und_x_variant":[
        "\u041d\u043e\u0432\u043e\u0443\u0440\u0430\u043b\u043a\u0430"
    ],
    "wof:name":"Novouralka",
    "wof:placetype":"locality"
},
  "geometry": {"coordinates":[79.21666999999999,59.08333],"type":"Point"}
}