{
  "type": "Feature",
  "properties": {
    "gn:admin1_code":"51.0",
    "gn:asciiname":"Ostashino",
    "gn:country_code":"RU",
    "gn:dem":125,
    "gn:feature_class":"P",
    "gn:feature_code":"PPL",
    "gn:name":"Ostashino",
    "gn:population":0,
    "gn:timezone":"Europe/Moscow",
    "iso:country":"RU",
    "name:nor_x_preferred":[
        "Ostasjino"
    ],
    "name:rus_x_preferred":[
        "\u041e\u0441\u0442\u0430\u0448\u0438\u043d\u043e"
    ],
    "wof:name":"Ostashino",
    "wof:placetype":"locality"
},
  "geometry": {"coordinates":[42.96591,56.61384],"type":"Point"}
}