{
  "type": "Feature",
  "properties": {
    "gn:admin1_code":"6.0",
    "gn:asciiname":"Durnitsyno",
    "gn:country_code":"RU",
    "gn:dem":66,
    "gn:feature_class":"P",
    "gn:feature_code":"PPL",
    "gn:name":"Durnitsyno",
    "gn:population":0,
    "gn:timezone":"Europe/Moscow",
    "iso:country":"RU",
    "name:rus_x_preferred":[
        "\u0414\u0443\u0440\u043d\u0438\u0446\u044b\u043d\u043e"
    ],
    "wof:name":"Durnitsyno",
    "wof:placetype":"locality"
},
  "geometry": {"coordinates":[47.00649,61.30299],"type":"Point"}
}