{
  "type": "Feature",
  "properties": {
    "gn:admin1_code":"43",
    "gn:asciiname":"Bryanskiy",
    "gn:country_code":"RU",
    "gn:dem":152,
    "gn:feature_class":"P",
    "gn:feature_code":"PPL",
    "gn:name":"Bryanskiy",
    "gn:population":0,
    "gn:timezone":"Europe/Moscow",
    "iso:country":"RU",
    "name:rus_x_preferred":[
        "\u0411\u0440\u044f\u043d\u0441\u043a\u0438\u0439"
    ],
    "wof:name":"Bryanskiy",
    "wof:placetype":"locality"
},
  "geometry": {"coordinates":[40.5381,52.1576],"type":"Point"}
}