{
  "type": "Feature",
  "properties": {
    "gn:admin1_code":"41.0",
    "gn:asciiname":"Gniloye",
    "gn:country_code":"RU",
    "gn:dem":215,
    "gn:feature_class":"P",
    "gn:feature_code":"PPL",
    "gn:name":"Gniloye",
    "gn:population":0,
    "gn:timezone":"Europe/Moscow",
    "iso:country":"RU",
    "name:rus_x_preferred":[
        "\u0413\u043d\u0438\u043b\u043e\u0435"
    ],
    "name:und_x_variant":[
        "Gnilaya",
        "Gniloye"
    ],
    "wof:name":"Gniloye",
    "wof:placetype":"locality"
},
  "geometry": {"coordinates":[36.2313,52.15402],"type":"Point"}
}