{
  "type": "Feature",
  "properties": {
    "gn:admin1_code":"34",
    "gn:asciiname":"Kobra",
    "gn:country_code":"RU",
    "gn:dem":198,
    "gn:feature_class":"P",
    "gn:feature_code":"PPL",
    "gn:name":"Kobra",
    "gn:population":0,
    "gn:timezone":"Europe/Moscow",
    "iso:country":"RU",
    "name:ceb_x_preferred":[
        "Kobra"
    ],
    "name:ces_x_preferred":[
        "Kobra"
    ],
    "name:deu_x_preferred":[
        "Kobra"
    ],
    "name:eng_x_preferred":[
        "Kobra"
    ],
    "name:fin_x_preferred":[
        "Kobra"
    ],
    "name:hun_x_preferred":[
        "Kobra"
    ],
    "name:ita_x_preferred":[
        "Kobra"
    ],
    "name:lav_x_preferred":[
        "Kobra"
    ],
    "name:lit_x_preferred":[
        "Kobra"
    ],
    "name:nor_x_preferred":[
        "Kobra"
    ],
    "name:pol_x_preferred":[
        "Kobra"
    ],
    "name:por_x_preferred":[
        "Kobra"
    ],
    "name:rus_x_preferred":[
        "\u041a\u043e\u0431\u0440\u0430"
    ],
    "name:slk_x_preferred":[
        "Kobra"
    ],
    "name:srp_x_preferred":[
        "\u041a\u043e\u0431\u0440\u0430"
    ],
    "name:swe_x_preferred":[
        "Kobra"
    ],
    "name:tur_x_preferred":[
        "Kobra"
    ],
    "name:und_x_variant":[
        "\u041a\u043e\u0431\u0440\u0430",
        "Kobra"
    ],
    "wof:name":"Kobra",
    "wof:placetype":"locality"
},
  "geometry": {"coordinates":[50.78719,60.04691999999999],"type":"Point"}
}