{
  "type": "Feature",
  "properties": {
    "gn:admin1_code":"54",
    "gn:asciiname":"Zenkul'",
    "gn:country_code":"RU",
    "gn:dem":109,
    "gn:feature_class":"P",
    "gn:feature_code":"PPL",
    "gn:name":"Zenkul\u2019",
    "gn:population":0,
    "gn:timezone":"Asia/Omsk",
    "iso:country":"RU",
    "name:rus_x_preferred":[
        "\u0417\u0435\u043d\u043a\u0443\u043b\u044c"
    ],
    "name:und_x_variant":[
        "Zenkul\u2019",
        "\u0417\u0435\u043d\u043a\u0443\u043b\u044c"
    ],
    "wof:name":"Zenkul'",
    "wof:placetype":"locality"
},
  "geometry": {"coordinates":[74.75294,55.49129],"type":"Point"}
}