{
  "type": "Feature",
  "properties": {
    "gn:admin1_code":"83",
    "gn:asciiname":"Molodino",
    "gn:country_code":"RU",
    "gn:dem":124,
    "gn:feature_class":"P",
    "gn:feature_code":"PPL",
    "gn:name":"Molodino",
    "gn:population":0,
    "gn:timezone":"Europe/Moscow",
    "iso:country":"RU",
    "name:rus_x_preferred":[
        "\u041c\u043e\u043b\u043e\u0434\u0438\u043d\u043e"
    ],
    "name:und_x_variant":[
        "\u041c\u043e\u043b\u043e\u0434\u0438\u043d\u043e"
    ],
    "wof:name":"Molodino",
    "wof:placetype":"locality"
},
  "geometry": {"coordinates":[39.10278,55.88081],"type":"Point"}
}