{
  "type": "Feature",
  "properties": {
    "gn:admin1_code":"45.0",
    "gn:asciiname":"Tanerkovo",
    "gn:country_code":"RU",
    "gn:dem":163,
    "gn:feature_class":"P",
    "gn:feature_code":"PPL",
    "gn:name":"Tanerkovo",
    "gn:population":0,
    "gn:timezone":"Europe/Moscow",
    "iso:country":"RU",
    "name:rus_x_preferred":[
        "\u0422\u0430\u043d\u0435\u0440\u043a\u043e\u0432\u043e"
    ],
    "wof:name":"Tanerkovo",
    "wof:placetype":"locality"
},
  "geometry": {"coordinates":[48.40917,57.01167],"type":"Point"}
}