{
  "type": "Feature",
  "properties": {
    "gn:admin1_code":"43",
    "gn:asciiname":"Kuzminka",
    "gn:country_code":"RU",
    "gn:dem":169,
    "gn:feature_class":"P",
    "gn:feature_code":"PPL",
    "gn:name":"Kuzminka",
    "gn:population":0,
    "gn:timezone":"Europe/Moscow",
    "iso:country":"RU",
    "name:che_x_preferred":[
        "\u041a\u0443\u0437\u044c\u043c\u0438\u043d\u043a\u0430"
    ],
    "name:rus_x_preferred":[
        "\u041a\u0443\u0437\u043c\u0438\u043d\u043a\u0430"
    ],
    "name:rus_x_variant":[
        "\u041a\u0443\u0437\u044c\u043c\u0438\u043d\u043a\u0430"
    ],
    "name:und_x_variant":[
        "\u041a\u0443\u0437\u043c\u0438\u043d\u043a\u0430"
    ],
    "wof:name":"Kuzminka",
    "wof:placetype":"locality"
},
  "geometry": {"coordinates":[38.82528,53.29971999999999],"type":"Point"}
}