{
  "type": "Feature",
  "properties": {
    "gn:admin1_code":"73",
    "gn:asciiname":"Verkhniye Verezi",
    "gn:country_code":"RU",
    "gn:dem":117,
    "gn:feature_class":"P",
    "gn:feature_code":"PPL",
    "gn:name":"Verkhniye Verezi",
    "gn:population":0,
    "gn:timezone":"Europe/Moscow",
    "iso:country":"RU",
    "name:rus_x_preferred":[
        "\u0412\u0435\u0440\u0445\u043d\u0438\u0435 \u0412\u0435\u0440\u0435\u0437\u0438"
    ],
    "wof:name":"Verkhniye Verezi",
    "wof:placetype":"locality"
},
  "geometry": {"coordinates":[49.80627,56.15871],"type":"Point"}
}