{
  "type": "Feature",
  "properties": {
    "gn:admin1_code":"21.0",
    "gn:asciiname":"Bol'shiye Kameshki",
    "gn:country_code":"RU",
    "gn:dem":120,
    "gn:feature_class":"P",
    "gn:feature_code":"PPL",
    "gn:name":"Bol\u2019shiye Kameshki",
    "gn:population":0,
    "gn:timezone":"Europe/Moscow",
    "iso:country":"RU",
    "name:und_x_variant":[
        "Kameshki Bol\u2019shiye",
        "Bol\u2019shiye Kameshki"
    ],
    "wof:name":"Bol'shiye Kameshki",
    "wof:placetype":"locality"
},
  "geometry": {"coordinates":[42.78496,57.09619],"type":"Point"}
}