{
  "type": "Feature",
  "properties": {
    "gn:admin1_code":"47",
    "gn:asciiname":"Troitskoye-Kaynardzhi",
    "gn:country_code":"RU",
    "gn:dem":151,
    "gn:feature_class":"P",
    "gn:feature_code":"PPL",
    "gn:name":"Troitskoye-Kaynardzhi",
    "gn:population":0,
    "gn:timezone":"Europe/Moscow",
    "iso:country":"RU",
    "wof:name":"Troitskoye-Kaynardzhi",
    "wof:placetype":"locality"
},
  "geometry": {"coordinates":[37.96667,55.73333],"type":"Point"}
}