{
  "type": "Feature",
  "properties": {
    "gn:admin1_code":"42",
    "gn:asciiname":"Kras'kovo",
    "gn:country_code":"RU",
    "gn:dem":1,
    "gn:feature_class":"P",
    "gn:feature_code":"PPL",
    "gn:name":"Kras\u2019kovo",
    "gn:population":0,
    "gn:timezone":"Europe/Moscow",
    "iso:country":"RU",
    "name:eng_x_preferred":[
        "Kras'kovo"
    ],
    "name:fin_x_preferred":[
        "Kraskovo"
    ],
    "name:nor_x_preferred":[
        "Kraskovo"
    ],
    "name:rus_x_preferred":[
        "\u041a\u0440\u0430\u0441\u044c\u043a\u043e\u0432\u043e"
    ],
    "name:und_x_variant":[
        "Kras\u2019kovo"
    ],
    "wof:name":"Kras'kovo",
    "wof:placetype":"locality"
},
  "geometry": {"coordinates":[30.8966,60.31303000000001],"type":"Point"}
}