{
  "type": "Feature",
  "properties": {
    "gn:admin1_code":"10",
    "gn:asciiname":"Dashino",
    "gn:country_code":"RU",
    "gn:dem":143,
    "gn:feature_class":"P",
    "gn:feature_code":"PPL",
    "gn:name":"Dashino",
    "gn:population":0,
    "gn:timezone":"Europe/Moscow",
    "iso:country":"RU",
    "name:rus_x_preferred":[
        "\u0414\u0430\u0448\u0438\u043d\u043e"
    ],
    "name:und_x_variant":[
        "\u0414\u0430\u0448\u0438\u043d\u043e"
    ],
    "wof:name":"Dashino",
    "wof:placetype":"locality"
},
  "geometry": {"coordinates":[33.58969,52.52158000000001],"type":"Point"}
}