{
  "type": "Feature",
  "properties": {
    "gn:admin1_code":"90.0",
    "gn:asciiname":"Klimyata",
    "gn:country_code":"RU",
    "gn:dem":165,
    "gn:elevation":"165.0",
    "gn:feature_class":"P",
    "gn:feature_code":"PPL",
    "gn:name":"Klimyata",
    "gn:population":1,
    "gn:timezone":"Asia/Yekaterinburg",
    "iso:country":"RU",
    "name:rus_x_preferred":[
        "\u041a\u043b\u0438\u043c\u044f\u0442\u0430"
    ],
    "wof:name":"Klimyata",
    "wof:placetype":"locality",
    "wof:population":1
},
  "geometry": {"coordinates":[56.78607,57.63599],"type":"Point"}
}