{
  "type": "Feature",
  "properties": {
    "gn:admin1_code":"71",
    "gn:asciiname":"Kraychikova",
    "gn:country_code":"RU",
    "gn:dem":113,
    "gn:feature_class":"P",
    "gn:feature_code":"PPL",
    "gn:name":"Kraychikova",
    "gn:population":0,
    "gn:timezone":"Asia/Yekaterinburg",
    "iso:country":"RU",
    "name:rus_x_preferred":[
        "\u041a\u0440\u0430\u0439\u0447\u0438\u043a\u043e\u0432\u0430"
    ],
    "name:und_x_variant":[
        "\u041a\u0440\u0430\u0439\u0447\u0438\u043a\u043e\u0432\u0430"
    ],
    "wof:name":"Kraychikova",
    "wof:placetype":"locality"
},
  "geometry": {"coordinates":[62.0435,56.2195],"type":"Point"}
}