{
  "type": "Feature",
  "properties": {
    "gn:admin1_code":"90",
    "gn:asciiname":"Syzganka",
    "gn:country_code":"RU",
    "gn:dem":193,
    "gn:feature_class":"P",
    "gn:feature_code":"PPL",
    "gn:name":"Syzganka",
    "gn:population":0,
    "gn:timezone":"Asia/Yekaterinburg",
    "iso:country":"RU",
    "name:eng_x_preferred":[
        "Syzganka"
    ],
    "name:nor_x_preferred":[
        "Syzganka"
    ],
    "name:rus_x_preferred":[
        "\u0421\u044b\u0437\u0433\u0430\u043d\u043a\u0430"
    ],
    "wof:name":"Syzganka",
    "wof:placetype":"locality"
},
  "geometry": {"coordinates":[57.7823,57.1032],"type":"Point"}
}