{
  "type": "Feature",
  "properties": {
    "gn:admin1_code":"20",
    "gn:asciiname":"Nepa",
    "gn:country_code":"RU",
    "gn:dem":305,
    "gn:feature_class":"P",
    "gn:feature_code":"PPL",
    "gn:name":"Nepa",
    "gn:population":0,
    "gn:timezone":"Asia/Irkutsk",
    "iso:country":"RU",
    "name:eng_x_preferred":[
        "Nepa"
    ],
    "name:nor_x_preferred":[
        "Nepa"
    ],
    "name:rus_x_preferred":[
        "\u041d\u0435\u043f\u0430"
    ],
    "name:und_x_variant":[
        "\u041d\u0435\u043f\u0430",
        "Nepa"
    ],
    "wof:name":"Nepa",
    "wof:placetype":"locality"
},
  "geometry": {"coordinates":[108.22861,59.2525],"type":"Point"}
}