{
  "type": "Feature",
  "properties": {
    "gn:admin1_code":"79",
    "gn:asciiname":"Chinge-Dergun",
    "gn:country_code":"RU",
    "gn:dem":1399,
    "gn:feature_class":"P",
    "gn:feature_code":"PPL",
    "gn:name":"Chinge-D\u00ebrgun",
    "gn:population":0,
    "gn:timezone":"Asia/Krasnoyarsk",
    "iso:country":"RU",
    "name:rus_x_preferred":[
        "\u0427\u0438\u043d\u0433\u0435-\u0414\u0451\u0440\u0433\u0443\u043d"
    ],
    "name:und_x_variant":[
        "Chinge-D\u00ebrgun"
    ],
    "wof:name":"Chinge-Dergun",
    "wof:placetype":"locality"
},
  "geometry": {"coordinates":[92.90000000000001,50.83333],"type":"Point"}
}