{
  "type": "Feature",
  "properties": {
    "gn:admin1_code":"91",
    "gn:asciiname":"Tiberkul'",
    "gn:country_code":"RU",
    "gn:dem":455,
    "gn:feature_class":"P",
    "gn:feature_code":"PPL",
    "gn:name":"Tiberkul\u2019",
    "gn:population":0,
    "gn:timezone":"Asia/Krasnoyarsk",
    "iso:country":"RU",
    "name:rus_x_preferred":[
        "\u0422\u0438\u0431\u0435\u0440\u043a\u0443\u043b\u044c"
    ],
    "name:und_x_variant":[
        "Tiberkul\u2019",
        "Bol\u2019she-Tiberkul\u2019skaya"
    ],
    "wof:name":"Tiberkul'",
    "wof:placetype":"locality"
},
  "geometry": {"coordinates":[94.03189999999999,53.9074],"type":"Point"}
}