{
  "type": "Feature",
  "properties": {
    "gn:admin1_code":"83.0",
    "gn:asciiname":"Bulatnikovo",
    "gn:country_code":"RU",
    "gn:dem":122,
    "gn:feature_class":"P",
    "gn:feature_code":"PPL",
    "gn:name":"Bulatnikovo",
    "gn:population":0,
    "gn:timezone":"Europe/Moscow",
    "iso:country":"RU",
    "name:eng_x_preferred":[
        "Bulatnikovo"
    ],
    "name:nor_x_preferred":[
        "Bulatnikovo"
    ],
    "name:rus_x_preferred":[
        "\u0411\u0443\u043b\u0430\u0442\u043d\u0438\u043a\u043e\u0432\u043e"
    ],
    "name:und_x_variant":[
        "\u0411\u0443\u043b\u0430\u0442\u043d\u0438\u043a\u043e\u0432\u043e",
        "Bulatnikovo"
    ],
    "wof:name":"Bulatnikovo",
    "wof:placetype":"locality"
},
  "geometry": {"coordinates":[41.7623,55.6889],"type":"Point"}
}