{
  "type": "Feature",
  "properties": {
    "gn:admin1_code":"45",
    "gn:asciiname":"Pal'tikino",
    "gn:country_code":"RU",
    "gn:dem":108,
    "gn:feature_class":"P",
    "gn:feature_code":"PPL",
    "gn:name":"Pal\u2019tikino",
    "gn:population":0,
    "gn:timezone":"Europe/Moscow",
    "iso:country":"RU",
    "name:rus_x_preferred":[
        "\u041f\u0430\u043b\u044c\u0442\u0438\u043a\u0438\u043d\u043e"
    ],
    "name:und_x_variant":[
        "Pal\u2019tikino"
    ],
    "wof:name":"Pal'tikino",
    "wof:placetype":"locality"
},
  "geometry": {"coordinates":[46.4284,56.2133],"type":"Point"}
}