{
  "type": "Feature",
  "properties": {
    "gn:admin1_code":"73.0",
    "gn:asciiname":"Bol'shiye Berezi",
    "gn:country_code":"RU",
    "gn:dem":112,
    "gn:feature_class":"P",
    "gn:feature_code":"PPL",
    "gn:name":"Bol\u2019shiye Ber\u00ebzi",
    "gn:population":0,
    "gn:timezone":"Europe/Moscow",
    "iso:country":"RU",
    "name:rus_x_preferred":[
        "\u0411\u043e\u043b\u044c\u0448\u0438\u0435 \u0411\u0435\u0440\u0451\u0437\u0438"
    ],
    "name:und_x_variant":[
        "Bol\u2019shaya Bereske",
        "Bol\u2019shiye Ber\u00ebzki",
        "Bol\u2019shaya Bereza",
        "Bol\u2019shiye Verezki",
        "Bol\u2019shiye Verezi",
        "Bol\u2019shiye Ber\u00ebzi"
    ],
    "wof:name":"Bol'shiye Berezi",
    "wof:placetype":"locality"
},
  "geometry": {"coordinates":[49.26972,56.21917],"type":"Point"}
}