{
  "type": "Feature",
  "properties": {
    "gn:admin1_code":"60",
    "gn:asciiname":"Gornyye Bobyli",
    "gn:country_code":"RU",
    "gn:dem":51,
    "gn:feature_class":"P",
    "gn:feature_code":"PPL",
    "gn:name":"Gornyye Bobyli",
    "gn:population":0,
    "gn:timezone":"Europe/Moscow",
    "iso:country":"RU",
    "name:rus_x_preferred":[
        "\u0413\u043e\u0440\u043d\u044b\u0435 \u0411\u043e\u0431\u044b\u043b\u0438"
    ],
    "name:und_x_variant":[
        "Gora Bobyli",
        "Gor-Bobyli",
        "Gornyye Bobyli"
    ],
    "wof:name":"Gornyye Bobyli",
    "wof:placetype":"locality"
},
  "geometry": {"coordinates":[28.9045,57.7062],"type":"Point"}
}