{
  "type": "Feature",
  "properties": {
    "gn:admin1_code":"77",
    "gn:asciiname":"Pochep",
    "gn:country_code":"RU",
    "gn:dem":137,
    "gn:feature_class":"P",
    "gn:feature_code":"PPL",
    "gn:name":"Poch\u00ebp",
    "gn:population":0,
    "gn:timezone":"Europe/Moscow",
    "iso:country":"RU",
    "name:rus_x_preferred":[
        "\u041f\u043e\u0447\u0451\u043f"
    ],
    "name:rus_x_variant":[
        "\u041f\u043e\u0447\u0435\u043f"
    ],
    "name:ukr_x_preferred":[
        "\u041f\u043e\u0447\u0435\u043f"
    ],
    "name:und_x_variant":[
        "Poch\u00ebp",
        "\u041f\u043e\u0447\u0451\u043f"
    ],
    "wof:name":"Pochep",
    "wof:placetype":"locality"
},
  "geometry": {"coordinates":[37.5122,57.7127],"type":"Point"}
}