{
  "type": "Feature",
  "properties": {
    "gn:admin1_code":"10",
    "gn:asciiname":"Uzha",
    "gn:country_code":"RU",
    "gn:dem":195,
    "gn:feature_class":"P",
    "gn:feature_code":"PPL",
    "gn:name":"Uzha",
    "gn:population":0,
    "gn:timezone":"Europe/Moscow",
    "iso:country":"RU",
    "name:eng_x_preferred":[
        "Uzha"
    ],
    "name:nor_x_preferred":[
        "Uzja"
    ],
    "name:rus_x_preferred":[
        "\u0423\u0436\u0430"
    ],
    "name:und_x_variant":[
        "\u0423\u0436\u0430",
        "Uzha"
    ],
    "wof:name":"Uzha",
    "wof:placetype":"locality"
},
  "geometry": {"coordinates":[33.56035,52.60791999999999],"type":"Point"}
}