{
  "type": "Feature",
  "properties": {
    "gn:admin1_code":"83",
    "gn:asciiname":"Simonovo",
    "gn:country_code":"RU",
    "gn:dem":110,
    "gn:feature_class":"P",
    "gn:feature_code":"PPL",
    "gn:name":"Simonovo",
    "gn:population":0,
    "gn:timezone":"Europe/Moscow",
    "iso:country":"RU",
    "name:rus_x_preferred":[
        "\u0421\u0438\u043c\u043e\u043d\u043e\u0432o"
    ],
    "name:und_x_variant":[
        "Simonova",
        "Simonovo"
    ],
    "wof:name":"Simonovo",
    "wof:placetype":"locality"
},
  "geometry": {"coordinates":[40.94313,56.22346],"type":"Point"}
}