{
  "type": "Feature",
  "properties": {
    "gn:admin1_code":"69",
    "gn:asciiname":"Klestovo",
    "gn:country_code":"RU",
    "gn:dem":251,
    "gn:feature_class":"P",
    "gn:feature_code":"PPL",
    "gn:name":"Klestovo",
    "gn:population":0,
    "gn:timezone":"Europe/Moscow",
    "iso:country":"RU",
    "name:che_x_preferred":[
        "\u041a\u043b\u0435\u0441\u0442\u043e\u0432\u043e"
    ],
    "name:rus_x_preferred":[
        "\u041a\u043b\u0435\u0441\u0442\u043e\u0432\u043e"
    ],
    "wof:name":"Klestovo",
    "wof:placetype":"locality"
},
  "geometry": {"coordinates":[32.3253,55.4732],"type":"Point"}
}