{
  "type": "Feature",
  "properties": {
    "gn:admin1_code":"38",
    "gn:asciiname":"Krasnopartizanskoye",
    "gn:country_code":"RU",
    "gn:dem":29,
    "gn:feature_class":"P",
    "gn:feature_code":"PPL",
    "gn:name":"Krasnopartizanskoye",
    "gn:population":0,
    "gn:timezone":"Europe/Moscow",
    "iso:country":"RU",
    "name:rus_x_preferred":[
        "\u041a\u0440\u0430\u0441\u043do\u043f\u0430\u0440\u0442\u0438\u0437\u0430\u043dc\u043aoe"
    ],
    "name:und_x_variant":[
        "Krasny Paritizan",
        "Krasnopartizanskoye",
        "\u041a\u0440\u0430\u0441\u043do\u043f\u0430\u0440\u0442\u0438\u0437\u0430\u043dc\u043aoe",
        "Krasnyy Partizan"
    ],
    "wof:name":"Krasnopartizanskoye",
    "wof:placetype":"locality"
},
  "geometry": {"coordinates":[39.77115,46.07502],"type":"Point"}
}