{
  "type": "Feature",
  "properties": {
    "gn:admin1_code":"4",
    "gn:asciiname":"Krutikha",
    "gn:country_code":"RU",
    "gn:dem":203,
    "gn:feature_class":"P",
    "gn:feature_code":"PPL",
    "gn:name":"Krutikha",
    "gn:population":0,
    "gn:timezone":"Asia/Barnaul",
    "iso:country":"RU",
    "name:rus_x_preferred":[
        "\u041a\u0440\u0443\u0442\u0438\u0445\u0430"
    ],
    "wof:name":"Krutikha",
    "wof:placetype":"locality"
},
  "geometry": {"coordinates":[82.9658,52.7114],"type":"Point"}
}