{
  "type": "Feature",
  "properties": {
    "gn:admin1_code":"51",
    "gn:asciiname":"Alekhanovtsy",
    "gn:country_code":"RU",
    "gn:dem":143,
    "gn:feature_class":"P",
    "gn:feature_code":"PPL",
    "gn:name":"Alekhanovtsy",
    "gn:population":0,
    "gn:timezone":"Europe/Moscow",
    "iso:country":"RU",
    "name:rus_x_preferred":[
        "\u0410\u043b\u0435\u0445\u0430\u043d\u043e\u0432\u0446\u044b"
    ],
    "name:und_x_variant":[
        "\u0410\u043b\u0435\u0445\u0430\u043d\u043e\u0432\u0446\u044b"
    ],
    "wof:name":"Alekhanovtsy",
    "wof:placetype":"locality"
},
  "geometry": {"coordinates":[46.6177,57.6917],"type":"Point"}
}