{
  "type": "Feature",
  "properties": {
    "gn:admin1_code":"25",
    "gn:asciiname":"Golovnino",
    "gn:country_code":"RU",
    "gn:dem":156,
    "gn:feature_class":"P",
    "gn:feature_code":"PPL",
    "gn:name":"Golovnino",
    "gn:population":0,
    "gn:timezone":"Europe/Moscow",
    "iso:country":"RU",
    "name:eng_x_preferred":[
        "Golovnino"
    ],
    "name:rus_x_preferred":[
        "\u0413\u043e\u043b\u043e\u0432\u0438\u043d\u043e"
    ],
    "name:rus_x_variant":[
        "\u0413\u043e\u043b\u043e\u0432\u043d\u0438\u043d\u043e"
    ],
    "name:und_x_variant":[
        "Golovino"
    ],
    "wof:name":"Golovnino",
    "wof:placetype":"locality"
},
  "geometry": {"coordinates":[36.15587,54.39144],"type":"Point"}
}