{
  "type": "Feature",
  "properties": {
    "gn:admin1_code":"77",
    "gn:asciiname":"Leshchiny",
    "gn:country_code":"RU",
    "gn:dem":229,
    "gn:feature_class":"P",
    "gn:feature_code":"PPL",
    "gn:name":"Leshchiny",
    "gn:population":0,
    "gn:timezone":"Europe/Moscow",
    "iso:country":"RU",
    "name:rus_x_preferred":[
        "\u041b\u0435\u0449\u0438\u043d\u044b"
    ],
    "wof:name":"Leshchiny",
    "wof:placetype":"locality"
},
  "geometry": {"coordinates":[33.21807,57.2011],"type":"Point"}
}