{
  "type": "Feature",
  "properties": {
    "gn:admin1_code":"10",
    "gn:asciiname":"Pogreby",
    "gn:country_code":"RU",
    "gn:dem":194,
    "gn:feature_class":"P",
    "gn:feature_code":"PPL",
    "gn:name":"Pogreby",
    "gn:population":0,
    "gn:timezone":"Europe/Moscow",
    "iso:country":"RU",
    "name:eng_x_preferred":[
        "Pogreby"
    ],
    "name:lit_x_preferred":[
        "Pogrebai"
    ],
    "name:nor_x_preferred":[
        "Pogreby"
    ],
    "name:pol_x_preferred":[
        "Pogreby"
    ],
    "name:rus_x_preferred":[
        "\u041f\u043e\u0433\u0440\u0435\u0431\u044b"
    ],
    "name:ukr_x_preferred":[
        "\u041f\u043e\u0491\u0440\u0435\u0431\u0438"
    ],
    "wof:name":"Pogreby",
    "wof:placetype":"locality"
},
  "geometry": {"coordinates":[34.55,52.6558],"type":"Point"}
}