{
  "type": "Feature",
  "properties": {
    "gn:admin1_code":"85",
    "gn:asciiname":"Ul'yankino",
    "gn:country_code":"RU",
    "gn:dem":142,
    "gn:feature_class":"P",
    "gn:feature_code":"PPL",
    "gn:name":"Ul\u2019yankino",
    "gn:population":0,
    "gn:timezone":"Europe/Moscow",
    "iso:country":"RU",
    "name:eng_x_preferred":[
        "Ul'yankino"
    ],
    "name:nor_x_preferred":[
        "Uljankino"
    ],
    "name:rus_x_preferred":[
        "\u0423\u043b\u044c\u044f\u043d\u043a\u0438\u043d\u043e"
    ],
    "name:und_x_variant":[
        "Ul\u2019yankino"
    ],
    "wof:name":"Ul'yankino",
    "wof:placetype":"locality"
},
  "geometry": {"coordinates":[37.36563,59.98985],"type":"Point"}
}