{
  "type": "Feature",
  "properties": {
    "gn:admin1_code":"34",
    "gn:asciiname":"Lekhta",
    "gn:country_code":"RU",
    "gn:dem":134,
    "gn:feature_class":"P",
    "gn:feature_code":"PPL",
    "gn:name":"L\u00ebkhta",
    "gn:population":0,
    "gn:timezone":"Europe/Moscow",
    "iso:country":"RU",
    "name:eng_x_preferred":[
        "L\u00ebkhta"
    ],
    "name:nor_x_preferred":[
        "Lekhta"
    ],
    "name:rus_x_preferred":[
        "\u041b\u0435\u0445\u0442\u0430"
    ],
    "name:rus_x_variant":[
        "\u041b\u0451\u0445\u0442\u0430"
    ],
    "name:und_x_variant":[
        "L\u00ebkhta"
    ],
    "wof:name":"Lekhta",
    "wof:placetype":"locality"
},
  "geometry": {"coordinates":[48.73405,60.6421],"type":"Point"}
}