{
  "type": "Feature",
  "properties": {
    "gn:admin1_code":"83",
    "gn:asciiname":"Staryy Dvor",
    "gn:country_code":"RU",
    "gn:dem":154,
    "gn:feature_class":"P",
    "gn:feature_code":"PPL",
    "gn:name":"Staryy Dvor",
    "gn:population":0,
    "gn:timezone":"Europe/Moscow",
    "iso:country":"RU",
    "name:eng_x_preferred":[
        "Staryy Dvor"
    ],
    "name:nor_x_preferred":[
        "Star.Dvor"
    ],
    "name:rus_x_preferred":[
        "\u0421\u0442\u0430\u0440.\u0414\u0432\u043e\u0440"
    ],
    "name:rus_x_variant":[
        "\u0421\u0442\u0430\u0440\u044b\u0439 \u0414\u0432\u043e\u0440"
    ],
    "name:und_x_variant":[
        "Stary Dvor",
        "Staryy Dvor"
    ],
    "wof:name":"Staryy Dvor",
    "wof:placetype":"locality"
},
  "geometry": {"coordinates":[40.18315,56.28563000000001],"type":"Point"}
}