{
  "type": "Feature",
  "properties": {
    "gn:admin1_code":"43",
    "gn:asciiname":"Novikova",
    "gn:country_code":"RU",
    "gn:dem":224,
    "gn:feature_class":"P",
    "gn:feature_code":"PPL",
    "gn:name":"Novikova",
    "gn:population":0,
    "gn:timezone":"Europe/Moscow",
    "iso:country":"RU",
    "name:rus_x_preferred":[
        "\u041d\u043e\u0432\u0438\u043a\u043e\u0432\u0430"
    ],
    "name:und_x_variant":[
        "Shakhovskiye Vyselki",
        "Novikova",
        "Novikovo"
    ],
    "wof:name":"Novikova",
    "wof:placetype":"locality"
},
  "geometry": {"coordinates":[38.22465,52.92211999999999],"type":"Point"}
}