{
  "type": "Feature",
  "properties": {
    "gn:admin1_code":"33",
    "gn:asciiname":"Sushi",
    "gn:country_code":"RU",
    "gn:dem":80,
    "gn:feature_class":"P",
    "gn:feature_code":"PPL",
    "gn:name":"Sushi",
    "gn:population":0,
    "gn:timezone":"Europe/Kirov",
    "iso:country":"RU",
    "name:eng_x_preferred":[
        "Sushi"
    ],
    "name:nor_x_preferred":[
        "Susji"
    ],
    "name:rus_x_preferred":[
        "\u0421\u0443\u0448\u0438"
    ],
    "wof:name":"Sushi",
    "wof:placetype":"locality"
},
  "geometry": {"coordinates":[51.09862,56.32461],"type":"Point"}
}