{
  "type": "Feature",
  "properties": {
    "gn:admin1_code":"63",
    "gn:asciiname":"Talakhtakh",
    "gn:country_code":"RU",
    "gn:dem":33,
    "gn:feature_class":"P",
    "gn:feature_code":"PPL",
    "gn:name":"Talakhtakh",
    "gn:population":0,
    "gn:timezone":"Asia/Magadan",
    "iso:country":"RU",
    "wof:name":"Talakhtakh",
    "wof:placetype":"locality"
},
  "geometry": {"coordinates":[152.13333,67.08333],"type":"Point"}
}