{
  "type": "Feature",
  "properties": {
    "gn:admin1_code":"32",
    "gn:asciiname":"Kanterova",
    "gn:cc2":"RU",
    "gn:country_code":"RU",
    "gn:dem":57,
    "gn:feature_class":"P",
    "gn:feature_code":"PPL",
    "gn:name":"Kanterova",
    "gn:population":0,
    "gn:timezone":"Asia/Yekaterinburg",
    "iso:country":"RU",
    "name:rus_x_preferred":[
        "\u041a\u0430\u043d\u0442\u0435\u0440\u043e\u0432\u0430"
    ],
    "name:und_x_variant":[
        "Yurty Kanterova",
        "Kanterovy",
        "Kanterova G.",
        "Kanterova",
        "\u041a\u0430\u043d\u0442\u0435\u0440\u043e\u0432\u0430"
    ],
    "wof:name":"Kanterova",
    "wof:placetype":"locality"
},
  "geometry": {"coordinates":[72.18333,61.75],"type":"Point"}
}