{
  "type": "Feature",
  "properties": {
    "gn:admin1_code":"8",
    "gn:asciiname":"Natsmen",
    "gn:country_code":"RU",
    "gn:dem":194,
    "gn:feature_class":"P",
    "gn:feature_code":"PPL",
    "gn:name":"Natsmen",
    "gn:population":0,
    "gn:timezone":"Asia/Yekaterinburg",
    "iso:country":"RU",
    "name:rus_x_preferred":[
        "\u041d\u0430\u0446\u043c\u0435\u043d"
    ],
    "wof:name":"Natsmen",
    "wof:placetype":"locality"
},
  "geometry": {"coordinates":[56.61666999999999,54.75],"type":"Point"}
}