{
  "type": "Feature",
  "properties": {
    "gn:admin1_code":"90",
    "gn:asciiname":"Vekoshinka",
    "gn:country_code":"RU",
    "gn:dem":101,
    "gn:feature_class":"P",
    "gn:feature_code":"PPL",
    "gn:name":"Vekoshinka",
    "gn:population":0,
    "gn:timezone":"Asia/Yekaterinburg",
    "iso:country":"RU",
    "name:eng_x_preferred":[
        "Vekoshinka"
    ],
    "name:nor_x_preferred":[
        "Vekosjinka"
    ],
    "name:rus_x_preferred":[
        "\u0412\u0435\u043a\u043e\u0448\u0438\u043d\u043a\u0430"
    ],
    "wof:name":"Vekoshinka",
    "wof:placetype":"locality"
},
  "geometry": {"coordinates":[54.30886,56.94276],"type":"Point"}
}