{
  "type": "Feature",
  "properties": {
    "gn:admin1_code":"77",
    "gn:asciiname":"Zvanka",
    "gn:cc2":"RU",
    "gn:country_code":"RU",
    "gn:dem":178,
    "gn:feature_class":"P",
    "gn:feature_code":"PPL",
    "gn:name":"Zvanka",
    "gn:population":0,
    "gn:timezone":"Europe/Moscow",
    "iso:country":"RU",
    "name:und_x_variant":[
        "Ivankovo",
        "Zvanka"
    ],
    "wof:name":"Zvanka",
    "wof:placetype":"locality"
},
  "geometry": {"coordinates":[33.66667,58.13333000000001],"type":"Point"}
}