{
  "type": "Feature",
  "properties": {
    "gn:admin1_code":"72",
    "gn:asciiname":"Lizunovka",
    "gn:country_code":"RU",
    "gn:dem":169,
    "gn:feature_class":"P",
    "gn:feature_code":"PPL",
    "gn:name":"Lizunovka",
    "gn:population":0,
    "gn:timezone":"Europe/Moscow",
    "iso:country":"RU",
    "name:rus_x_preferred":[
        "\u041b\u0438\u0437\u0443\u043d\u043e\u0432\u043a\u0430"
    ],
    "name:und_x_variant":[
        "Lizgunovka",
        "Lizunovka",
        "\u041b\u0438\u0437\u0443\u043d\u043e\u0432\u043a\u0430"
    ],
    "wof:name":"Lizunovka",
    "wof:placetype":"locality"
},
  "geometry": {"coordinates":[40.9524,53.3306],"type":"Point"}
}