{
  "type": "Feature",
  "properties": {
    "gn:admin1_code":"81",
    "gn:asciiname":"Pilyugino",
    "gn:country_code":"RU",
    "gn:dem":166,
    "gn:feature_class":"P",
    "gn:feature_code":"PPL",
    "gn:name":"Pilyugino",
    "gn:population":0,
    "gn:timezone":"Europe/Ulyanovsk",
    "iso:country":"RU",
    "name:rus_x_preferred":[
        "\u041f\u0438\u043b\u044e\u0433\u0438\u043d\u043e"
    ],
    "wof:name":"Pilyugino",
    "wof:placetype":"locality"
},
  "geometry": {"coordinates":[47.9001,54.44],"type":"Point"}
}