{
  "type": "Feature",
  "properties": {
    "gn:admin1_code":"71",
    "gn:asciiname":"Sorok Chetvertyy Kvartal",
    "gn:country_code":"RU",
    "gn:dem":234,
    "gn:feature_class":"P",
    "gn:feature_code":"PPL",
    "gn:name":"Sorok Chetv\u00ebrtyy Kvartal",
    "gn:population":0,
    "gn:timezone":"Asia/Yekaterinburg",
    "iso:country":"RU",
    "name:rus_x_preferred":[
        "\u0421\u043e\u0440\u043e\u043a \u0427\u0435\u0442\u0432\u0451\u0440\u0442\u044b\u0439 \u041a\u0432\u0430\u0440\u0442\u0430\u043b"
    ],
    "name:rus_x_variant":[
        "Sorok Chetv\u00ebrtyy Kvartal"
    ],
    "name:und_x_variant":[
        "Sorok Chetv\u00ebrtyy Kvartal"
    ],
    "wof:name":"Sorok Chetvertyy Kvartal",
    "wof:placetype":"locality"
},
  "geometry": {"coordinates":[60.7965,56.9517],"type":"Point"}
}