{
  "type": "Feature",
  "properties": {
    "gn:admin1_code":"81.0",
    "gn:asciiname":"Arapovka",
    "gn:country_code":"RU",
    "gn:dem":176,
    "gn:feature_class":"P",
    "gn:feature_code":"PPL",
    "gn:name":"Arapovka",
    "gn:population":0,
    "gn:timezone":"Europe/Ulyanovsk",
    "iso:country":"RU",
    "name:nor_x_preferred":[
        "Arapovka"
    ],
    "name:rus_x_preferred":[
        "\u0410\u0440\u0430\u043f\u043e\u0432\u043a\u0430"
    ],
    "wof:name":"Arapovka",
    "wof:placetype":"locality"
},
  "geometry": {"coordinates":[47.40804,53.92426999999999],"type":"Point"}
}