{
  "type": "Feature",
  "properties": {
    "gn:admin1_code":"28",
    "gn:asciiname":"Karmala",
    "gn:country_code":"RU",
    "gn:dem":15,
    "gn:feature_class":"P",
    "gn:feature_code":"PPL",
    "gn:name":"Karmala",
    "gn:population":0,
    "gn:timezone":"Europe/Moscow",
    "iso:country":"RU",
    "name:ben_x_preferred":[
        "\u0995\u09be\u09b0\u09ae\u09be\u09b2\u09be"
    ],
    "name:bpy_x_preferred":[
        "\u0995\u09be\u09b0\u09ae\u09be\u09b2\u09be"
    ],
    "name:ceb_x_preferred":[
        "Karm\u0101la"
    ],
    "name:fin_x_preferred":[
        "Karmala"
    ],
    "name:ita_x_preferred":[
        "Karmala"
    ],
    "name:mar_x_preferred":[
        "\u0915\u0930\u092e\u093e\u0933\u093e"
    ],
    "name:msa_x_preferred":[
        "Karmala"
    ],
    "name:new_x_preferred":[
        "\u0915\u0930\u094d\u092e\u0932\u093e"
    ],
    "name:nld_x_preferred":[
        "Karmala"
    ],
    "name:por_x_preferred":[
        "Karmala"
    ],
    "name:rus_x_preferred":[
        "\u041a\u0430\u0440\u043c\u0430\u043b\u0430"
    ],
    "name:swe_x_preferred":[
        "Karm\u0101la"
    ],
    "name:und_x_variant":[
        "\u041a\u0430\u0440\u043c\u0430\u043b\u0430"
    ],
    "name:urd_x_preferred":[
        "\u06a9\u0631\u0645\u0644\u0627"
    ],
    "name:vie_x_preferred":[
        "Karmala"
    ],
    "name:zho_x_preferred":[
        "\u5361\u5c14\u9a6c\u62c9"
    ],
    "wof:name":"Karmala",
    "wof:placetype":"locality"
},
  "geometry": {"coordinates":[30.61134,61.70989],"type":"Point"}
}