{
  "type": "Feature",
  "properties": {
    "gn:admin1_code":"33",
    "gn:asciiname":"Kazan'-Omga",
    "gn:country_code":"RU",
    "gn:dem":114,
    "gn:feature_class":"P",
    "gn:feature_code":"PPL",
    "gn:name":"Kazan\u2019-Omga",
    "gn:population":0,
    "gn:timezone":"Europe/Kirov",
    "iso:country":"RU",
    "name:rus_x_preferred":[
        "\u041a\u0430\u0437\u0430\u043d\u044c-\u041e\u043c\u0433\u0430"
    ],
    "name:und_x_variant":[
        "Kazan\u2019-Omga",
        "\u041a\u0430\u0437\u0430\u043d\u044c-\u041e\u043c\u0433\u0430"
    ],
    "wof:name":"Kazan'-Omga",
    "wof:placetype":"locality"
},
  "geometry": {"coordinates":[51.19569,56.38159],"type":"Point"}
}