{
  "type": "Feature",
  "properties": {
    "gn:admin1_code":"90",
    "gn:asciiname":"Poludennaya",
    "gn:cc2":"RU",
    "gn:country_code":"RU",
    "gn:dem":138,
    "gn:feature_class":"P",
    "gn:feature_code":"PPL",
    "gn:name":"Poludennaya",
    "gn:population":0,
    "gn:timezone":"Asia/Yekaterinburg",
    "iso:country":"RU",
    "name:rus_x_preferred":[
        "\u041f\u043e\u043b\u0443\u0434\u0435\u043d\u043d\u0430\u044f"
    ],
    "name:und_x_variant":[
        "Poludenkaya",
        "Poludennaya",
        "\u041f\u043e\u043b\u0443\u0434\u0435\u043d\u043d\u0430\u044f"
    ],
    "wof:name":"Poludennaya",
    "wof:placetype":"locality"
},
  "geometry": {"coordinates":[53.91667,60.33333],"type":"Point"}
}