{
  "type": "Feature",
  "properties": {
    "gn:admin1_code":"91",
    "gn:asciiname":"Taymyr",
    "gn:country_code":"RU",
    "gn:dem":51,
    "gn:feature_class":"P",
    "gn:feature_code":"PPL",
    "gn:name":"Taymyr",
    "gn:population":0,
    "gn:timezone":"Asia/Krasnoyarsk",
    "iso:country":"RU",
    "name:bel_x_preferred":[
        "\u0422\u0430\u0439\u043c\u044b\u0440"
    ],
    "name:bul_x_preferred":[
        "\u0422\u0430\u0439\u043c\u0438\u0440"
    ],
    "name:ceb_x_preferred":[
        "Taimyr"
    ],
    "name:ces_x_preferred":[
        "Tajmyr"
    ],
    "name:deu_x_preferred":[
        "Taimyr"
    ],
    "name:est_x_preferred":[
        "Taim\u00f5r"
    ],
    "name:eus_x_preferred":[
        "Taimyr"
    ],
    "name:fra_x_preferred":[
        "Ta\u00efmyr"
    ],
    "name:heb_x_preferred":[
        "\u05d8\u05d9\u05d9\u05de\u05d9\u05e8"
    ],
    "name:hun_x_preferred":[
        "Tajmir"
    ],
    "name:ita_x_preferred":[
        "Tajmyr"
    ],
    "name:lav_x_preferred":[
        "Taimira"
    ],
    "name:lit_x_preferred":[
        "Taimyras"
    ],
    "name:nld_x_preferred":[
        "Tajmyr"
    ],
    "name:pol_x_preferred":[
        "Tajmyr"
    ],
    "name:rus_x_preferred":[
        "\u0422\u0430\u0439\u043c\u044b\u0440"
    ],
    "name:sah_x_preferred":[
        "\u0422\u0430\u0439\u043c\u044b\u044b\u0440"
    ],
    "name:slk_x_preferred":[
        "Tajmyr"
    ],
    "name:swe_x_preferred":[
        "Tajmyr"
    ],
    "wof:name":"Taymyr",
    "wof:placetype":"locality"
},
  "geometry": {"coordinates":[89.98719,68.21944999999999],"type":"Point"}
}