{
  "type": "Feature",
  "properties": {
    "gn:admin1_code":"15",
    "gn:asciiname":"Chuvanskoye",
    "gn:cc2":"RU",
    "gn:country_code":"RU",
    "gn:dem":40,
    "gn:feature_class":"P",
    "gn:feature_code":"PPL",
    "gn:name":"Chuvanskoye",
    "gn:population":0,
    "gn:timezone":"Asia/Anadyr",
    "iso:country":"RU",
    "name:nld_x_preferred":[
        "Tsjoevanskoje"
    ],
    "name:rus_x_preferred":[
        "\u0427\u0443\u0432\u0430\u043d\u0441\u043a\u043e\u0435"
    ],
    "name:und_x_variant":[
        "Chuvanskaya",
        "Chuvanskoye",
        "\u0427\u0443\u0432\u0430\u043d\u0441\u043a\u043e\u0435"
    ],
    "wof:name":"Chuvanskoye",
    "wof:placetype":"locality"
},
  "geometry": {"coordinates":[173.31666999999999,65.88333],"type":"Point"}
}