{
  "type": "Feature",
  "properties": {
    "gn:admin1_code":"83",
    "gn:asciiname":"Sheldyakovo",
    "gn:country_code":"RU",
    "gn:dem":121,
    "gn:feature_class":"P",
    "gn:feature_code":"PPL",
    "gn:name":"Sheldyakovo",
    "gn:population":0,
    "gn:timezone":"Europe/Moscow",
    "iso:country":"RU",
    "name:rus_x_preferred":[
        "\u0428\u0435\u043b\u0434\u044f\u043a\u043e\u0432\u043e"
    ],
    "name:und_x_variant":[
        "Sheludyakova",
        "Sheldyakovo"
    ],
    "wof:name":"Sheldyakovo",
    "wof:placetype":"locality"
},
  "geometry": {"coordinates":[39.9884,56.15386],"type":"Point"}
}