{
  "type": "Feature",
  "properties": {
    "gn:admin1_code":"21.0",
    "gn:asciiname":"Dunilovo",
    "gn:country_code":"RU",
    "gn:dem":99,
    "gn:feature_class":"P",
    "gn:feature_code":"PPL",
    "gn:name":"Dunilovo",
    "gn:population":0,
    "gn:timezone":"Europe/Moscow",
    "iso:country":"RU",
    "name:eng_x_preferred":[
        "Dunilovo"
    ],
    "name:nor_x_preferred":[
        "Dunilovo"
    ],
    "name:rus_x_preferred":[
        "\u0414\u0443\u043d\u0438\u043b\u043e\u0432\u043e"
    ],
    "name:und_x_variant":[
        "Donilovo",
        "\u0414\u0443\u043d\u0438\u043b\u043e\u0432\u043e",
        "Dunilovo"
    ],
    "wof:name":"Dunilovo",
    "wof:placetype":"locality"
},
  "geometry": {"coordinates":[41.41148,56.99779],"type":"Point"}
}