{
  "type": "Feature",
  "properties": {
    "gn:admin1_code":"77",
    "gn:asciiname":"Zelenikha",
    "gn:country_code":"RU",
    "gn:dem":168,
    "gn:feature_class":"P",
    "gn:feature_code":"PPL",
    "gn:name":"Zelenikha",
    "gn:population":0,
    "gn:timezone":"Europe/Moscow",
    "iso:country":"RU",
    "name:rus_x_preferred":[
        "\u0417\u0435\u043b\u0435\u043d\u0438\u0445\u0430"
    ],
    "name:und_x_variant":[
        "\u0417\u0435\u043b\u0435\u043d\u0438\u0445\u0430"
    ],
    "wof:name":"Zelenikha",
    "wof:placetype":"locality"
},
  "geometry": {"coordinates":[35.56912,58.4472],"type":"Point"}
}