{
  "type": "Feature",
  "properties": {
    "gn:admin1_code":"81.0",
    "gn:asciiname":"Bakhmet'yevka",
    "gn:country_code":"RU",
    "gn:dem":116,
    "gn:feature_class":"P",
    "gn:feature_code":"PPL",
    "gn:name":"Bakhmet\u2019yevka",
    "gn:population":0,
    "gn:timezone":"Europe/Ulyanovsk",
    "iso:country":"RU",
    "name:nor_x_preferred":[
        "Bakhmetjevka"
    ],
    "name:rus_x_preferred":[
        "\u0411\u0430\u0445\u043c\u0435\u0442\u044c\u0435\u0432\u043a\u0430"
    ],
    "name:und_x_variant":[
        "Bakhmet\u2019yevka"
    ],
    "wof:name":"Bakhmet'yevka",
    "wof:placetype":"locality"
},
  "geometry": {"coordinates":[46.45746,54.24159],"type":"Point"}
}