{
  "type": "Feature",
  "properties": {
    "gn:admin1_code":"67.0",
    "gn:asciiname":"Bauderovskiy",
    "gn:country_code":"RU",
    "gn:dem":46,
    "gn:feature_class":"P",
    "gn:feature_code":"PPL",
    "gn:name":"Bauderovskiy",
    "gn:population":0,
    "gn:timezone":"Europe/Saratov",
    "iso:country":"RU",
    "name:nor_x_preferred":[
        "Bauderovskij"
    ],
    "name:rus_x_preferred":[
        "\u0411\u0430\u0443\u0434\u0435\u0440\u043e\u0432\u0441\u043a\u0438\u0439"
    ],
    "wof:name":"Bauderovskiy",
    "wof:placetype":"locality"
},
  "geometry": {"coordinates":[48.68333,52.16667],"type":"Point"}
}