{
  "type": "Feature",
  "properties": {
    "gn:admin1_code":"60",
    "gn:asciiname":"Kopylok",
    "gn:country_code":"RU",
    "gn:dem":179,
    "gn:feature_class":"P",
    "gn:feature_code":"PPL",
    "gn:name":"Kopylok",
    "gn:population":0,
    "gn:timezone":"Europe/Moscow",
    "iso:country":"RU",
    "name:eng_x_preferred":[
        "Kopylok"
    ],
    "name:nor_x_preferred":[
        "Kopylok"
    ],
    "name:rus_x_preferred":[
        "\u041a\u043e\u043f\u044b\u043b\u043e\u043a"
    ],
    "wof:name":"Kopylok",
    "wof:placetype":"locality"
},
  "geometry": {"coordinates":[29.47514,56.39876999999999],"type":"Point"}
}