{
  "type": "Feature",
  "properties": {
    "gn:admin1_code":"62",
    "gn:asciiname":"Kipchakovo",
    "gn:country_code":"RU",
    "gn:dem":103,
    "gn:feature_class":"P",
    "gn:feature_code":"PPL",
    "gn:name":"Kipchakovo",
    "gn:population":0,
    "gn:timezone":"Europe/Moscow",
    "iso:country":"RU",
    "name:rus_x_preferred":[
        "\u041a\u0438\u043f\u0447\u0430\u043a\u043e\u0432\u043e"
    ],
    "wof:name":"Kipchakovo",
    "wof:placetype":"locality"
},
  "geometry": {"coordinates":[40.1476,53.87600000000001],"type":"Point"}
}