{
  "type": "Feature",
  "properties": {
    "gn:admin1_code":"60",
    "gn:asciiname":"Berdushki",
    "gn:country_code":"RU",
    "gn:dem":181,
    "gn:feature_class":"P",
    "gn:feature_code":"PPL",
    "gn:name":"Berdushki",
    "gn:population":0,
    "gn:timezone":"Europe/Moscow",
    "iso:country":"RU",
    "name:rus_x_preferred":[
        "\u0411\u0435\u0440\u0434\u0443\u0448\u043a\u0438"
    ],
    "wof:name":"Berdushki",
    "wof:placetype":"locality"
},
  "geometry": {"coordinates":[28.98719,56.58127],"type":"Point"}
}