{
  "type": "Feature",
  "properties": {
    "gn:admin1_code":"88",
    "gn:asciiname":"Podlipnaya",
    "gn:country_code":"RU",
    "gn:dem":144,
    "gn:feature_class":"P",
    "gn:feature_code":"PPL",
    "gn:name":"Podlipnaya",
    "gn:population":0,
    "gn:timezone":"Europe/Moscow",
    "iso:country":"RU",
    "name:rus_x_preferred":[
        "\u041f\u043e\u0434\u043b\u0438\u043f\u043d\u0430\u044f"
    ],
    "wof:name":"Podlipnaya",
    "wof:placetype":"locality"
},
  "geometry": {"coordinates":[37.6242,57.9642],"type":"Point"}
}