{
  "type": "Feature",
  "properties": {
    "gn:admin1_code":"41",
    "gn:asciiname":"Paninskaya Vys'",
    "gn:country_code":"RU",
    "gn:dem":187,
    "gn:feature_class":"P",
    "gn:feature_code":"PPL",
    "gn:name":"Paninskaya Vys\u2019",
    "gn:population":0,
    "gn:timezone":"Europe/Moscow",
    "iso:country":"RU",
    "name:rus_x_preferred":[
        "\u041f\u0430\u043d\u0438\u043d\u0441\u043a\u0430\u044f \u0412\u044b\u0441\u044c"
    ],
    "name:und_x_variant":[
        "Paninskaya Vys\u2019"
    ],
    "wof:name":"Paninskaya Vys'",
    "wof:placetype":"locality"
},
  "geometry": {"coordinates":[36.1966,51.55009],"type":"Point"}
}