{
  "type": "Feature",
  "properties": {
    "gn:admin1_code":"3",
    "gn:asciiname":"Balashtu",
    "gn:country_code":"RU",
    "gn:dem":1257,
    "gn:feature_class":"P",
    "gn:feature_code":"PPL",
    "gn:name":"Balashtu",
    "gn:population":0,
    "gn:timezone":"Asia/Omsk",
    "iso:country":"RU",
    "name:nor_x_preferred":[
        "Balasjtu"
    ],
    "name:rus_x_preferred":[
        "\u0411\u0430\u043b\u0430\u0448\u0442\u0443"
    ],
    "wof:name":"Balashtu",
    "wof:placetype":"locality"
},
  "geometry": {"coordinates":[84.36667,50.56667],"type":"Point"}
}