{
  "type": "Feature",
  "properties": {
    "gn:admin1_code":"90",
    "gn:asciiname":"Rogovo",
    "gn:country_code":"RU",
    "gn:dem":147,
    "gn:feature_class":"P",
    "gn:feature_code":"PPL",
    "gn:name":"Rogovo",
    "gn:population":0,
    "gn:timezone":"Asia/Yekaterinburg",
    "iso:country":"RU",
    "name:rus_x_preferred":[
        "\u0420\u043e\u0433\u043e\u0432\u043e"
    ],
    "wof:name":"Rogovo",
    "wof:placetype":"locality"
},
  "geometry": {"coordinates":[54.53333000000001,57.16667],"type":"Point"}
}