{
  "type": "Feature",
  "properties": {
    "gn:admin1_code":"40",
    "gn:asciiname":"Fatezhskaya",
    "gn:country_code":"RU",
    "gn:dem":98,
    "gn:feature_class":"P",
    "gn:feature_code":"PPL",
    "gn:name":"Fatezhskaya",
    "gn:population":0,
    "gn:timezone":"Asia/Yekaterinburg",
    "iso:country":"RU",
    "name:rus_x_preferred":[
        "\u0424\u0430\u0442\u0435\u0436\u0441\u043a\u0430\u044f"
    ],
    "wof:name":"Fatezhskaya",
    "wof:placetype":"locality"
},
  "geometry": {"coordinates":[66.62416999999999,55.99528000000001],"type":"Point"}
}