{
  "type": "Feature",
  "properties": {
    "gn:admin1_code":"55.0",
    "gn:asciiname":"Barskiy",
    "gn:country_code":"RU",
    "gn:dem":204,
    "gn:feature_class":"P",
    "gn:feature_code":"PPL",
    "gn:name":"Barskiy",
    "gn:population":0,
    "gn:timezone":"Asia/Yekaterinburg",
    "iso:country":"RU",
    "name:nor_x_preferred":[
        "Barskij"
    ],
    "name:rus_x_preferred":[
        "\u0411\u0430\u0440\u0441\u043a\u0438\u0439"
    ],
    "wof:name":"Barskiy",
    "wof:placetype":"locality"
},
  "geometry": {"coordinates":[51.96667,52.06667],"type":"Point"}
}