{
  "type": "Feature",
  "properties": {
    "gn:admin1_code":"65",
    "gn:asciiname":"Shilovka",
    "gn:country_code":"RU",
    "gn:dem":175,
    "gn:feature_class":"P",
    "gn:feature_code":"PPL",
    "gn:name":"Shilovka",
    "gn:population":0,
    "gn:timezone":"Europe/Samara",
    "iso:country":"RU",
    "name:rus_x_preferred":[
        "\u0428\u0438\u043b\u043e\u0432\u043a\u0430"
    ],
    "name:und_x_variant":[
        "\u0428\u0438\u043b\u043e\u0432\u043a\u0430"
    ],
    "wof:name":"Shilovka",
    "wof:placetype":"locality"
},
  "geometry": {"coordinates":[51.06667,54.18333000000001],"type":"Point"}
}