{
  "type": "Feature",
  "properties": {
    "gn:admin1_code":"05",
    "gn:asciiname":"Razdol'noye",
    "gn:country_code":"RU",
    "gn:dem":306,
    "gn:feature_class":"P",
    "gn:feature_code":"PPL",
    "gn:name":"Razdol\u2019noye",
    "gn:population":0,
    "gn:timezone":"Asia/Yakutsk",
    "iso:country":"RU",
    "name:eng_x_preferred":[
        "Razdol'noye"
    ],
    "name:nor_x_preferred":[
        "Razdolnoje"
    ],
    "name:rus_x_preferred":[
        "\u0420\u0430\u0437\u0434\u043e\u043b\u044c\u043d\u043e\u0435"
    ],
    "name:und_x_variant":[
        "\u0420\u0430\u0437\u0434\u043e\u043b\u044c\u043d\u043e\u0435",
        "Razdol\u2019noye"
    ],
    "wof:name":"Razdol'noye",
    "wof:placetype":"locality"
},
  "geometry": {"coordinates":[127.77419,52.09828],"type":"Point"}
}