{
  "type": "Feature",
  "properties": {
    "gn:admin1_code":"53",
    "gn:asciiname":"Dal'nyaya Orlovka",
    "gn:country_code":"RU",
    "gn:dem":135,
    "gn:feature_class":"P",
    "gn:feature_code":"PPL",
    "gn:name":"Dal\u2019nyaya Orlovka",
    "gn:population":0,
    "gn:timezone":"Asia/Novosibirsk",
    "iso:country":"RU",
    "name:eng_x_preferred":[
        "Dal'nyaya Orlovka"
    ],
    "name:nor_x_preferred":[
        "Orlovskoje"
    ],
    "name:rus_x_preferred":[
        "\u041e\u0440\u043b\u043e\u0432\u0441\u043a\u043e\u0435"
    ],
    "name:rus_x_variant":[
        "\u0414\u0430\u043b\u044c\u043d\u044f\u044f \u041e\u0440\u043b\u043e\u0432\u043a\u0430"
    ],
    "name:und_x_variant":[
        "Orlovskiy",
        "Orlovskoye",
        "Dal\u2019nyaya Orlovka",
        "\u0414\u0430\u043b\u044c\u043d\u044f\u044f \u041e\u0440\u043b\u043e\u0432\u043a\u0430"
    ],
    "wof:name":"Dal'nyaya Orlovka",
    "wof:placetype":"locality"
},
  "geometry": {"coordinates":[79.72824,55.51031],"type":"Point"}
}