{
  "type": "Feature",
  "properties": {
    "gn:admin1_code":"60",
    "gn:asciiname":"Vetchi",
    "gn:country_code":"RU",
    "gn:dem":77,
    "gn:feature_class":"P",
    "gn:feature_code":"PPL",
    "gn:name":"Vetchi",
    "gn:population":0,
    "gn:timezone":"Europe/Moscow",
    "iso:country":"RU",
    "name:rus_x_preferred":[
        "\u0412\u0435\u0442\u0447\u0438"
    ],
    "name:und_x_variant":[
        "\u0412\u0435\u0442\u0447\u0438"
    ],
    "wof:name":"Vetchi",
    "wof:placetype":"locality"
},
  "geometry": {"coordinates":[30.0365,57.6147],"type":"Point"}
}