{
  "type": "Feature",
  "properties": {
    "gn:admin1_code":"47",
    "gn:asciiname":"Likino",
    "gn:country_code":"RU",
    "gn:dem":134,
    "gn:feature_class":"P",
    "gn:feature_code":"PPL",
    "gn:name":"Likino",
    "gn:population":0,
    "gn:timezone":"Europe/Moscow",
    "iso:country":"RU",
    "name:rus_x_preferred":[
        "\u041b\u0438\u043a\u0438\u043d\u043e"
    ],
    "name:und_x_variant":[
        "\u041b\u0438\u043a\u0438\u043d\u043e"
    ],
    "wof:name":"Likino",
    "wof:placetype":"locality"
},
  "geometry": {"coordinates":[38.95,55.73333],"type":"Point"}
}