{
  "type": "Feature",
  "properties": {
    "gn:admin1_code":"33.0",
    "gn:asciiname":"Bulychi",
    "gn:country_code":"RU",
    "gn:dem":126,
    "gn:feature_class":"P",
    "gn:feature_code":"PPL",
    "gn:name":"Bulychi",
    "gn:population":0,
    "gn:timezone":"Europe/Kirov",
    "iso:country":"RU",
    "name:rus_x_preferred":[
        "\u0411\u0443\u043b\u044b\u0447\u0438"
    ],
    "wof:name":"Bulychi",
    "wof:placetype":"locality"
},
  "geometry": {"coordinates":[49.03813,58.82377],"type":"Point"}
}