{
  "type": "Feature",
  "properties": {
    "gn:admin1_code":"40",
    "gn:asciiname":"Vilkino",
    "gn:country_code":"RU",
    "gn:dem":98,
    "gn:feature_class":"P",
    "gn:feature_code":"PPL",
    "gn:name":"Vilkino",
    "gn:population":0,
    "gn:timezone":"Asia/Yekaterinburg",
    "iso:country":"RU",
    "name:eng_x_preferred":[
        "Vilkino"
    ],
    "name:nor_x_preferred":[
        "Vilkino"
    ],
    "name:rus_x_preferred":[
        "\u0412\u0438\u043b\u043a\u0438\u043d\u043e"
    ],
    "wof:name":"Vilkino",
    "wof:placetype":"locality"
},
  "geometry": {"coordinates":[64.12751999999999,55.54503],"type":"Point"}
}