{
  "type": "Feature",
  "properties": {
    "gn:admin1_code":"53",
    "gn:asciiname":"Sibiryak",
    "gn:country_code":"RU",
    "gn:dem":107,
    "gn:feature_class":"P",
    "gn:feature_code":"PPL",
    "gn:name":"Sibiryak",
    "gn:population":0,
    "gn:timezone":"Asia/Novosibirsk",
    "iso:country":"RU",
    "name:eng_x_preferred":[
        "Sibiryak"
    ],
    "name:nor_x_preferred":[
        "Sibirjak"
    ],
    "name:rus_x_preferred":[
        "\u0421\u0438\u0431\u0438\u0440\u044f\u043a"
    ],
    "wof:name":"Sibiryak",
    "wof:placetype":"locality"
},
  "geometry": {"coordinates":[76.82109,54.69768000000001],"type":"Point"}
}