{
  "type": "Feature",
  "properties": {
    "gn:country":"RU",
    "gn:fcode":"PPL",
    "gn:pop":3598,
    "iso:country":"RU",
    "name:aze_x_preferred":[
        "Sabnova"
    ],
    "name:ceb_x_preferred":[
        "Sabnova"
    ],
    "name:eng_x_preferred":[
        "Sabnova"
    ],
    "name:lez_x_preferred":[
        "\u0421\u0430\u0431\u043d\u043e\u0432\u0430"
    ],
    "name:nor_x_preferred":[
        "Sabnova"
    ],
    "name:rus_x_preferred":[
        "\u0421\u0430\u0431\u043d\u043e\u0432\u0430"
    ],
    "name:unk_x_variant":[
        "\u0421\u0430\u0431\u043d\u043e\u0432\u0430"
    ],
    "qs:name":"Sabnova",
    "qs:photos_9r":0,
    "qs:photos_sr":0,
    "qs:pop_sr":"4",
    "wof:name":"Sabnova",
    "wof:placetype":"locality",
    "wof:population":3598
},
  "geometry": {"coordinates":[48.24796,42.07617],"type":"Point"}
}