{
  "type": "Feature",
  "properties": {
    "gn:admin1_code":"88.0",
    "gn:asciiname":"Dorskoye",
    "gn:country_code":"RU",
    "gn:dem":142,
    "gn:feature_class":"P",
    "gn:feature_code":"PPL",
    "gn:name":"Dorskoye",
    "gn:population":0,
    "gn:timezone":"Europe/Moscow",
    "iso:country":"RU",
    "name:rus_x_preferred":[
        "\u0414\u043e\u0440\u0441\u043a\u043e\u0435"
    ],
    "name:und_x_variant":[
        "\u0414\u043e\u0440\u0441\u043a\u043e\u0435"
    ],
    "wof:name":"Dorskoye",
    "wof:placetype":"locality"
},
  "geometry": {"coordinates":[40.44257,58.45417],"type":"Point"}
}