{
  "type": "Feature",
  "properties": {
    "gn:admin1_code":"70",
    "gn:asciiname":"Russkoye",
    "gn:country_code":"RU",
    "gn:dem":144,
    "gn:feature_class":"P",
    "gn:feature_code":"PPL",
    "gn:name":"Russkoye",
    "gn:population":0,
    "gn:timezone":"Europe/Moscow",
    "iso:country":"RU",
    "name:rus_x_preferred":[
        "\u0420\u0443\u0441\u0441\u043a\u043e\u0435"
    ],
    "name:und_x_variant":[
        "\u0420\u0443\u0441\u0441\u043a\u043e\u0435"
    ],
    "wof:name":"Russkoye",
    "wof:placetype":"locality"
},
  "geometry": {"coordinates":[44.615,43.83972],"type":"Point"}
}