{
  "type": "Feature",
  "properties": {
    "gn:admin1_code":"77",
    "gn:asciiname":"Zhabero",
    "gn:country_code":"RU",
    "gn:dem":223,
    "gn:feature_class":"P",
    "gn:feature_code":"PPL",
    "gn:name":"Zhabero",
    "gn:population":0,
    "gn:timezone":"Europe/Moscow",
    "iso:country":"RU",
    "name:rus_x_preferred":[
        "\u0416\u0430\u0431\u0435\u0440\u043e"
    ],
    "wof:name":"Zhabero",
    "wof:placetype":"locality"
},
  "geometry": {"coordinates":[32.26792,56.72576],"type":"Point"}
}