{
  "type": "Feature",
  "properties": {
    "gn:admin1_code":"8",
    "gn:asciiname":"Voroshilovskoye",
    "gn:country_code":"RU",
    "gn:dem":147,
    "gn:feature_class":"P",
    "gn:feature_code":"PPL",
    "gn:name":"Voroshilovskoye",
    "gn:population":0,
    "gn:timezone":"Asia/Yekaterinburg",
    "iso:country":"RU",
    "name:rus_x_preferred":[
        "\u0412\u043e\u0440\u043e\u0448\u0438\u043b\u043e\u0432\u0441\u043a\u043e\u0435"
    ],
    "wof:name":"Voroshilovskoye",
    "wof:placetype":"locality"
},
  "geometry": {"coordinates":[56.6164,54.6927],"type":"Point"}
}