{
  "type": "Feature",
  "properties": {
    "gn:admin1_code":"77",
    "gn:asciiname":"Dymtsevo",
    "gn:country_code":"RU",
    "gn:dem":151,
    "gn:feature_class":"P",
    "gn:feature_code":"PPL",
    "gn:name":"Dymtsevo",
    "gn:population":0,
    "gn:timezone":"Europe/Moscow",
    "iso:country":"RU",
    "name:rus_x_preferred":[
        "\u0414\u044b\u043c\u0446\u0435\u0432\u043e"
    ],
    "name:und_x_variant":[
        "\u0414\u044b\u043c\u0446\u0435\u0432\u043e"
    ],
    "wof:name":"Dymtsevo",
    "wof:placetype":"locality"
},
  "geometry": {"coordinates":[37.106,58.0139],"type":"Point"}
}