{
  "type": "Feature",
  "properties": {
    "gn:admin1_code":"24.0",
    "gn:asciiname":"Bondarenko",
    "gn:country_code":"RU",
    "gn:dem":74,
    "gn:feature_class":"P",
    "gn:feature_code":"PPL",
    "gn:name":"Bondarenko",
    "gn:population":0,
    "gn:timezone":"Europe/Moscow",
    "iso:country":"RU",
    "name:rus_x_preferred":[
        "\u0411\u043e\u043d\u0434\u0430\u0440\u0435\u043d\u043a\u043e"
    ],
    "name:und_x_variant":[
        "\u0411\u043e\u043d\u0434\u0430\u0440\u0435\u043d\u043a\u043e"
    ],
    "wof:name":"Bondarenko",
    "wof:placetype":"locality"
},
  "geometry": {"coordinates":[41.91667,46.13333],"type":"Point"}
}