{
  "type": "Feature",
  "properties": {
    "gn:admin1_code":"77",
    "gn:asciiname":"Bol'shoye Barankovo",
    "gn:country_code":"RU",
    "gn:dem":145,
    "gn:feature_class":"P",
    "gn:feature_code":"PPL",
    "gn:name":"Bol\u2019shoye Barankovo",
    "gn:population":0,
    "gn:timezone":"Europe/Moscow",
    "iso:country":"RU",
    "name:rus_x_preferred":[
        "\u0411\u043e\u043b\u044c\u0448\u043e\u0435 \u0411\u0430\u0440\u0430\u043d\u043a\u043e\u0432\u043e"
    ],
    "name:und_x_variant":[
        "Bol\u2019shoye Barankovo",
        "\u0411\u043e\u043b\u044c\u0448\u043e\u0435 \u0411\u0430\u0440\u0430\u043d\u043a\u043e\u0432\u043e"
    ],
    "wof:name":"Bol'shoye Barankovo",
    "wof:placetype":"locality"
},
  "geometry": {"coordinates":[36.7461,57.7322],"type":"Point"}
}