{
  "type": "Feature",
  "properties": {
    "gn:admin1_code":"85",
    "gn:asciiname":"Nechayevo",
    "gn:country_code":"RU",
    "gn:dem":151,
    "gn:feature_class":"P",
    "gn:feature_code":"PPL",
    "gn:name":"Nechayevo",
    "gn:population":0,
    "gn:timezone":"Europe/Moscow",
    "iso:country":"RU",
    "name:rus_x_preferred":[
        "\u041d\u0435\u0447\u0430\u0435\u0432\u043e"
    ],
    "name:und_x_variant":[
        "\u041d\u0435\u0447\u0430\u0435\u0432\u043e"
    ],
    "wof:name":"Nechayevo",
    "wof:placetype":"locality"
},
  "geometry": {"coordinates":[38.09014000000001,59.73078],"type":"Point"}
}