{
  "type": "Feature",
  "properties": {
    "gn:admin1_code":"72",
    "gn:asciiname":"Khobotets",
    "gn:country_code":"RU",
    "gn:dem":160,
    "gn:feature_class":"P",
    "gn:feature_code":"PPL",
    "gn:name":"Khobotets",
    "gn:population":0,
    "gn:timezone":"Europe/Moscow",
    "iso:country":"RU",
    "name:rus_x_preferred":[
        "\u0425\u043e\u0431\u043e\u0442\u0435\u0446"
    ],
    "wof:name":"Khobotets",
    "wof:placetype":"locality"
},
  "geometry": {"coordinates":[40.85,53.18333000000001],"type":"Point"}
}