{
  "type": "Feature",
  "properties": {
    "gn:admin1_code":"37",
    "gn:asciiname":"Mikhlino",
    "gn:country_code":"RU",
    "gn:dem":198,
    "gn:feature_class":"P",
    "gn:feature_code":"PPL",
    "gn:name":"Mikhlino",
    "gn:population":0,
    "gn:timezone":"Europe/Moscow",
    "iso:country":"RU",
    "name:rus_x_preferred":[
        "\u041c\u0438\u0445\u043b\u0438\u043d\u043e"
    ],
    "name:und_x_variant":[
        "\u041c\u0438\u0445\u043b\u0438\u043d\u043e"
    ],
    "wof:name":"Mikhlino",
    "wof:placetype":"locality"
},
  "geometry": {"coordinates":[42.36252,58.14884],"type":"Point"}
}