{
  "type": "Feature",
  "properties": {
    "gn:gn_country":"RU",
    "gn:gn_fcode":"PPL",
    "gn:gn_pop":8588,
    "gn:population":8588,
    "iso:country":"RU",
    "name:eng_x_preferred":[
        "Temirgoyevskaya"
    ],
    "name:nor_x_preferred":[
        "Temirgojevskaja"
    ],
    "name:rus_x_preferred":[
        "\u0422\u0435\u043c\u0438\u0440\u0433\u043e\u0435\u0432\u0441\u043a\u0430\u044f"
    ],
    "name:unk_x_variant":[
        "Temirgofewskaja"
    ],
    "qs_pg:aaroncc":"RU",
    "qs_pg:gn_country":"RU",
    "qs_pg:gn_fcode":"PPL",
    "qs_pg:gn_pop":8588,
    "qs_pg:name":"Temirgoyevskaya",
    "qs_pg:photos_9r":0,
    "qs_pg:photos_sr":0,
    "qs_pg:pop_sr":5,
    "qs_pg:qs_pg_placetype":"locality",
    "wof:name":"Temirgoyevskaya",
    "wof:placetype":"locality",
    "wof:population":8588
},
  "geometry": {"coordinates":[40.28027,45.11414],"type":"Point"}
}