{
  "type": "Feature",
  "properties": {
    "gn:admin1_code":"88",
    "gn:asciiname":"Oleshkovo",
    "gn:country_code":"RU",
    "gn:dem":143,
    "gn:feature_class":"P",
    "gn:feature_code":"PPL",
    "gn:name":"Ol\u00ebshkovo",
    "gn:population":0,
    "gn:timezone":"Europe/Moscow",
    "iso:country":"RU",
    "name:rus_x_preferred":[
        "\u041e\u043b\u0451\u0448\u043a\u043e\u0432\u043e"
    ],
    "name:und_x_variant":[
        "Al\u00ebshkovo",
        "Ol\u00ebshkovo"
    ],
    "wof:name":"Oleshkovo",
    "wof:placetype":"locality"
},
  "geometry": {"coordinates":[39.44114,57.80103],"type":"Point"}
}