{
  "type": "Feature",
  "properties": {
    "gn:admin1_code":"33.0",
    "gn:asciiname":"Shulaki",
    "gn:country_code":"RU",
    "gn:dem":141,
    "gn:feature_class":"P",
    "gn:feature_code":"PPL",
    "gn:name":"Shulaki",
    "gn:population":0,
    "gn:timezone":"Europe/Kirov",
    "iso:country":"RU",
    "name:rus_x_preferred":[
        "\u0428\u0443\u043b\u0430\u043a\u0438"
    ],
    "wof:name":"Shulaki",
    "wof:placetype":"locality"
},
  "geometry": {"coordinates":[50.74139,59.26389],"type":"Point"}
}