{
  "type": "Feature",
  "properties": {
    "gn:admin1_code":"87",
    "gn:asciiname":"Taz",
    "gn:country_code":"RU",
    "gn:dem":33,
    "gn:feature_class":"P",
    "gn:feature_code":"PPL",
    "gn:name":"Taz",
    "gn:population":0,
    "gn:timezone":"Asia/Yekaterinburg",
    "iso:country":"RU",
    "name:bak_x_preferred":[
        "\u0422\u0430\u0499\u043b\u0430\u0440"
    ],
    "name:ceb_x_preferred":[
        "Taz"
    ],
    "name:ces_x_preferred":[
        "Taz"
    ],
    "name:dan_x_preferred":[
        "Taz"
    ],
    "name:deu_x_preferred":[
        "Taz"
    ],
    "name:fra_x_preferred":[
        "Taz"
    ],
    "name:nld_x_preferred":[
        "Taz"
    ],
    "name:pol_x_preferred":[
        "Taz"
    ],
    "name:por_x_preferred":[
        "Taz"
    ],
    "name:rus_x_preferred":[
        "\u0422\u0430\u0437"
    ],
    "name:slk_x_preferred":[
        "Panvov\u00e1 kos\u0165"
    ],
    "name:spa_x_preferred":[
        "Taz"
    ],
    "name:swe_x_preferred":[
        "Taz"
    ],
    "name:ukr_x_preferred":[
        "\u0422\u0430\u0437"
    ],
    "wof:name":"Taz",
    "wof:placetype":"locality"
},
  "geometry": {"coordinates":[82.18066,66.00726999999999],"type":"Point"}
}