{
  "type": "Feature",
  "properties": {
    "gn:admin1_code":"87",
    "gn:asciiname":"Taz",
    "gn:country_code":"RU",
    "gn:dem":33,
    "gn:feature_class":"P",
    "gn:feature_code":"PPL",
    "gn:name":"Taz",
    "gn:population":0,
    "gn:timezone":"Asia/Yekaterinburg",
    "iso:country":"RU",
    "name:ara_x_preferred":[
        "\u062a\u0627\u0632"
    ],
    "name:bak_x_preferred":[
        "\u0422\u0430\u0499\u043b\u0430\u0440"
    ],
    "name:ben_x_preferred":[
        "\u09a4\u09be\u099c"
    ],
    "name:ceb_x_preferred":[
        "Taz"
    ],
    "name:ces_x_preferred":[
        "Taz"
    ],
    "name:dan_x_preferred":[
        "Taz"
    ],
    "name:deu_x_preferred":[
        "Taz"
    ],
    "name:ell_x_preferred":[
        "\u03a4\u03b1\u03b6"
    ],
    "name:fas_x_preferred":[
        "\u062a\u0627\u0632"
    ],
    "name:fra_x_preferred":[
        "Taz"
    ],
    "name:heb_x_preferred":[
        "\u05d8\u05d0\u05d6"
    ],
    "name:hin_x_preferred":[
        "\u0924\u093e\u091c\u093c\u0940"
    ],
    "name:ind_x_preferred":[
        "Taz"
    ],
    "name:nld_x_preferred":[
        "Taz"
    ],
    "name:pol_x_preferred":[
        "Taz"
    ],
    "name:por_x_preferred":[
        "Taz"
    ],
    "name:rus_x_preferred":[
        "\u0422\u0430\u0437"
    ],
    "name:slk_x_preferred":[
        "Panvov\u00e1 kos\u0165"
    ],
    "name:spa_x_preferred":[
        "Taz"
    ],
    "name:swe_x_preferred":[
        "Taz"
    ],
    "name:ukr_x_preferred":[
        "\u0422\u0430\u0437"
    ],
    "name:urd_x_preferred":[
        "\u062a\u0627\u0632"
    ],
    "name:vie_x_preferred":[
        "S\u00f4ng Taz"
    ],
    "wof:name":"Taz",
    "wof:placetype":"locality"
},
  "geometry": {"coordinates":[82.18066,66.00727000000001],"type":"Point"}
}