{
  "type": "Feature",
  "properties": {
    "gn:admin1_code":"42",
    "gn:asciiname":"Prokshino",
    "gn:country_code":"RU",
    "gn:dem":11,
    "gn:feature_class":"P",
    "gn:feature_code":"PPL",
    "gn:name":"Prokshino",
    "gn:population":0,
    "gn:timezone":"Europe/Moscow",
    "iso:country":"RU",
    "name:rus_x_preferred":[
        "\u041f\u0440\u043e\u043a\u0448\u0438\u043d\u043e"
    ],
    "name:und_x_variant":[
        "Prok\u0161ino",
        "Prokshino"
    ],
    "wof:name":"Prokshino",
    "wof:placetype":"locality"
},
  "geometry": {"coordinates":[32.99126,60.32601],"type":"Point"}
}