{
  "type": "Feature",
  "properties": {
    "gn:admin1_code":"80.0",
    "gn:asciiname":"Nizhniy Kolevay",
    "gn:country_code":"RU",
    "gn:dem":197,
    "gn:feature_class":"P",
    "gn:feature_code":"PPL",
    "gn:name":"Nizhniy Kolevay",
    "gn:population":0,
    "gn:timezone":"Europe/Samara",
    "iso:country":"RU",
    "name:rus_x_preferred":[
        "\u041d\u0438\u0436\u043d\u0438\u0439 \u041a\u043e\u043b\u0435\u0432\u0430\u0439"
    ],
    "wof:name":"Nizhniy Kolevay",
    "wof:placetype":"locality"
},
  "geometry": {"coordinates":[52.4228,58.304],"type":"Point"}
}