{
  "type": "Feature",
  "properties": {
    "gn:admin1_code":"10",
    "gn:asciiname":"Solovskoy",
    "gn:country_code":"RU",
    "gn:dem":151,
    "gn:feature_class":"P",
    "gn:feature_code":"PPL",
    "gn:name":"Solovskoy",
    "gn:population":0,
    "gn:timezone":"Europe/Moscow",
    "iso:country":"RU",
    "name:rus_x_preferred":[
        "\u0421\u043e\u043b\u043e\u0432\u0441\u043a\u043e\u0439"
    ],
    "name:und_x_variant":[
        "\u0421\u043e\u043b\u043e\u0432\u0441\u043a\u043e\u0439"
    ],
    "wof:name":"Solovskoy",
    "wof:placetype":"locality"
},
  "geometry": {"coordinates":[32.54615,52.3807],"type":"Point"}
}