{
  "type": "Feature",
  "properties": {
    "gn:admin1_code":"84",
    "gn:asciiname":"Novogeorgiyevka",
    "gn:country_code":"RU",
    "gn:dem":107,
    "gn:feature_class":"P",
    "gn:feature_code":"PPL",
    "gn:name":"Novogeorgiyevka",
    "gn:population":0,
    "gn:timezone":"Europe/Volgograd",
    "iso:country":"RU",
    "name:eng_x_preferred":[
        "Novogeorgiyevka"
    ],
    "name:nor_x_preferred":[
        "Novogeorgijevka"
    ],
    "name:rus_x_preferred":[
        "\u041d\u043e\u0432\u043e\u0433\u0435\u043e\u0440\u0433\u0438\u0435\u0432\u043a\u0430"
    ],
    "name:und_x_variant":[
        "Novaya Georgiyevka",
        "Novogeorgiyevskoye",
        "Novogeorgiyevka"
    ],
    "wof:name":"Novogeorgiyevka",
    "wof:placetype":"locality"
},
  "geometry": {"coordinates":[44.83773,49.86227],"type":"Point"}
}