{
  "type": "Feature",
  "properties": {
    "gn:admin1_code":"91",
    "gn:asciiname":"Lazarevo",
    "gn:country_code":"RU",
    "gn:dem":266,
    "gn:feature_class":"P",
    "gn:feature_code":"PPL",
    "gn:name":"Lazarevo",
    "gn:population":0,
    "gn:timezone":"Asia/Krasnoyarsk",
    "iso:country":"RU",
    "name:eng_x_preferred":[
        "Lazarevo"
    ],
    "name:nor_x_preferred":[
        "Lazarevo"
    ],
    "name:rus_x_preferred":[
        "\u041b\u0430\u0437\u0430\u0440\u0435\u0432\u043e"
    ],
    "name:und_x_variant":[
        "Lazareva",
        "Lazarevo"
    ],
    "wof:name":"Lazarevo",
    "wof:placetype":"locality"
},
  "geometry": {"coordinates":[96.7992,56.82478],"type":"Point"}
}