{
  "type": "Feature",
  "properties": {
    "gn:admin1_code":"91",
    "gn:asciiname":"Lazarevo",
    "gn:country_code":"RU",
    "gn:dem":266,
    "gn:feature_class":"P",
    "gn:feature_code":"PPL",
    "gn:name":"Lazarevo",
    "gn:population":0,
    "gn:timezone":"Asia/Krasnoyarsk",
    "iso:country":"RU",
    "name:ceb_x_preferred":[
        "Lazarevo"
    ],
    "name:dan_x_preferred":[
        "Lazarevo"
    ],
    "name:deu_x_preferred":[
        "Lazarevo"
    ],
    "name:eng_x_preferred":[
        "Lazarevo"
    ],
    "name:epo_x_preferred":[
        "Lazarevo"
    ],
    "name:fas_x_preferred":[
        "\u0644\u0627\u0632\u0627\u0631\u0648\u0648"
    ],
    "name:fra_x_preferred":[
        "Lazarevo"
    ],
    "name:hrv_x_preferred":[
        "Lazarevo"
    ],
    "name:hun_x_preferred":[
        "L\u00e1z\u00e1rf\u00f6ld"
    ],
    "name:msa_x_preferred":[
        "Lazarevo"
    ],
    "name:nld_x_preferred":[
        "Lazarevo"
    ],
    "name:nor_x_preferred":[
        "Lazarevo"
    ],
    "name:ron_x_preferred":[
        "Lazarevo"
    ],
    "name:rus_x_preferred":[
        "\u041b\u0430\u0437\u0430\u0440\u0435\u0432\u043e"
    ],
    "name:sco_x_preferred":[
        "Lazarevo"
    ],
    "name:slv_x_preferred":[
        "Lazarevo"
    ],
    "name:srp_x_preferred":[
        "\u041b\u0430\u0437\u0430\u0440\u0435\u0432\u043e"
    ],
    "name:swe_x_preferred":[
        "Lazarevo"
    ],
    "name:und_x_variant":[
        "Lazareva",
        "Lazarevo"
    ],
    "wof:name":"Lazarevo",
    "wof:placetype":"locality"
},
  "geometry": {"coordinates":[96.7992,56.82478],"type":"Point"}
}