{
  "type": "Feature",
  "properties": {
    "gn:admin1_code":"63",
    "gn:asciiname":"Nimnyrskiy",
    "gn:country_code":"RU",
    "gn:dem":1158,
    "gn:feature_class":"P",
    "gn:feature_code":"PPL",
    "gn:name":"Nimnyrskiy",
    "gn:population":0,
    "gn:timezone":"Asia/Yakutsk",
    "iso:country":"RU",
    "name:rus_x_preferred":[
        "\u041d\u0438\u043c\u043d\u044b\u0440\u0441\u043a\u0438\u0439"
    ],
    "name:und_x_variant":[
        "\u041d\u0438\u043c\u043d\u044b\u0440\u0441\u043a\u0438\u0439"
    ],
    "wof:name":"Nimnyrskiy",
    "wof:placetype":"locality"
},
  "geometry": {"coordinates":[125.3777,57.82828000000001],"type":"Point"}
}