{
  "type": "Feature",
  "properties": {
    "gn:admin1_code":"85",
    "gn:asciiname":"Urzhumovo",
    "gn:country_code":"RU",
    "gn:dem":94,
    "gn:feature_class":"P",
    "gn:feature_code":"PPL",
    "gn:name":"Urzhumovo",
    "gn:population":0,
    "gn:timezone":"Europe/Moscow",
    "iso:country":"RU",
    "name:rus_x_preferred":[
        "\u0423\u0440\u0436\u0443\u043c\u043e\u0432\u043e"
    ],
    "wof:name":"Urzhumovo",
    "wof:placetype":"locality"
},
  "geometry": {"coordinates":[46.3881,60.8382],"type":"Point"}
}