{
  "type": "Feature",
  "properties": {
    "gn:admin1_code":"43",
    "gn:asciiname":"Selishche",
    "gn:country_code":"RU",
    "gn:dem":129,
    "gn:feature_class":"P",
    "gn:feature_code":"PPL",
    "gn:name":"Selishche",
    "gn:population":0,
    "gn:timezone":"Europe/Moscow",
    "iso:country":"RU",
    "name:rus_x_preferred":[
        "\u0421\u0435\u043b\u0438\u0449\u0435"
    ],
    "wof:name":"Selishche",
    "wof:placetype":"locality"
},
  "geometry": {"coordinates":[39.156,53.1296],"type":"Point"}
}