{
  "type": "Feature",
  "properties": {
    "gn:admin1_code":"51",
    "gn:asciiname":"Yegorovo",
    "gn:country_code":"RU",
    "gn:dem":92,
    "gn:feature_class":"P",
    "gn:feature_code":"PPL",
    "gn:name":"Yegorovo",
    "gn:population":0,
    "gn:timezone":"Europe/Moscow",
    "iso:country":"RU",
    "name:eng_x_preferred":[
        "Yegorovo"
    ],
    "name:nor_x_preferred":[
        "Jegorovo"
    ],
    "name:rus_x_preferred":[
        "\u0415\u0433\u043e\u0440\u043e\u0432\u043e"
    ],
    "wof:name":"Yegorovo",
    "wof:placetype":"locality"
},
  "geometry": {"coordinates":[45.62131,56.5903],"type":"Point"}
}