{
  "type": "Feature",
  "properties": {
    "gn:admin1_code":"55",
    "gn:asciiname":"Ugol'noye",
    "gn:country_code":"RU",
    "gn:dem":122,
    "gn:feature_class":"P",
    "gn:feature_code":"PPL",
    "gn:name":"Ugol\u2019noye",
    "gn:population":0,
    "gn:timezone":"Asia/Yekaterinburg",
    "iso:country":"RU",
    "name:eng_x_preferred":[
        "Ugol'noye"
    ],
    "name:nor_x_preferred":[
        "Ugolnoje"
    ],
    "name:rus_x_preferred":[
        "\u0423\u0433\u043e\u043b\u044c\u043d\u043e\u0435"
    ],
    "name:und_x_variant":[
        "Ugol\u2019nyy",
        "Ugol\u2019noye"
    ],
    "wof:name":"Ugol'noye",
    "wof:placetype":"locality"
},
  "geometry": {"coordinates":[55.17971,51.1104],"type":"Point"}
}