{
  "type": "Feature",
  "properties": {
    "gn:admin1_code":"12.0",
    "gn:asciiname":"Bosoy",
    "gn:country_code":"RU",
    "gn:dem":1562,
    "gn:feature_class":"P",
    "gn:feature_code":"PPL",
    "gn:name":"Bosoy",
    "gn:population":0,
    "gn:timezone":"Europe/Moscow",
    "iso:country":"RU",
    "name:rus_x_preferred":[
        "\u0411\u043e\u0441\u043e\u0439"
    ],
    "wof:name":"Bosoy",
    "wof:placetype":"locality"
},
  "geometry": {"coordinates":[45.89889,42.77972000000001],"type":"Point"}
}