{
  "type": "Feature",
  "properties": {
    "gn:admin1_code":"51",
    "gn:asciiname":"Filippovo",
    "gn:country_code":"RU",
    "gn:dem":119,
    "gn:feature_class":"P",
    "gn:feature_code":"PPL",
    "gn:name":"Filippovo",
    "gn:population":0,
    "gn:timezone":"Europe/Moscow",
    "iso:country":"RU",
    "name:rus_x_preferred":[
        "\u0424\u0438\u043b\u0438\u043f\u043f\u043e\u0432\u043e"
    ],
    "name:und_x_variant":[
        "\u0424\u0438\u043b\u0438\u043f\u043f\u043e\u0432\u043e"
    ],
    "wof:name":"Filippovo",
    "wof:placetype":"locality"
},
  "geometry": {"coordinates":[44.48332,56.69763],"type":"Point"}
}