{
  "type": "Feature",
  "properties": {
    "gn:admin1_code":"42.0",
    "gn:asciiname":"Kirkonkylae",
    "gn:country_code":"RU",
    "gn:dem":54,
    "gn:feature_class":"P",
    "gn:feature_code":"PPLL",
    "gn:name":"Kirkonkyl\u00e4",
    "gn:population":0,
    "gn:timezone":"Europe/Moscow",
    "iso:country":"RU",
    "wof:name":"Kirkonkylae",
    "wof:placetype":"locality"
},
  "geometry": {"coordinates":[30.54341,60.16806999999999],"type":"Point"}
}