{
  "type": "Feature",
  "properties": {
    "gn:admin1_code":"21.0",
    "gn:asciiname":"Nefed'yevo",
    "gn:country_code":"RU",
    "gn:dem":97,
    "gn:feature_class":"P",
    "gn:feature_code":"PPL",
    "gn:name":"Nefed\u2019yevo",
    "gn:population":0,
    "gn:timezone":"Europe/Moscow",
    "iso:country":"RU",
    "name:rus_x_preferred":[
        "\u041d\u0435\u0444\u0435\u0434\u044c\u0435\u0432\u043e"
    ],
    "name:und_x_variant":[
        "Nefed\u2019yevo",
        "\u041d\u0435\u0444\u0435\u0434\u044c\u0435\u0432\u043e"
    ],
    "wof:name":"Nefed'yevo",
    "wof:placetype":"locality"
},
  "geometry": {"coordinates":[41.32449,56.99646],"type":"Point"}
}