{
  "type": "Feature",
  "properties": {
    "gn:admin1_code":"33",
    "gn:asciiname":"Sergeyevskaya Vereteya",
    "gn:country_code":"RU",
    "gn:dem":176,
    "gn:feature_class":"P",
    "gn:feature_code":"PPL",
    "gn:name":"Sergeyevskaya Vereteya",
    "gn:population":0,
    "gn:timezone":"Europe/Kirov",
    "iso:country":"RU",
    "name:rus_x_preferred":[
        "\u0421\u0435\u0440\u0433\u0435\u0435\u0432\u0441\u043a\u0430\u044f \u0412\u0435\u0440\u0435\u0442\u0435\u044f"
    ],
    "name:und_x_variant":[
        "Sergeyevskaya",
        "Sergeyevskaya Vereteya"
    ],
    "wof:name":"Sergeyevskaya Vereteya",
    "wof:placetype":"locality"
},
  "geometry": {"coordinates":[48.33998,59.64747],"type":"Point"}
}