{
  "type": "Feature",
  "properties": {
    "gn:admin1_code":"51.0",
    "gn:asciiname":"Nagavitsyno",
    "gn:country_code":"RU",
    "gn:dem":100,
    "gn:feature_class":"P",
    "gn:feature_code":"PPL",
    "gn:name":"Nagavitsyno",
    "gn:population":0,
    "gn:timezone":"Europe/Moscow",
    "iso:country":"RU",
    "name:nor_x_preferred":[
        "Nagavitsyno"
    ],
    "name:rus_x_preferred":[
        "\u041d\u0430\u0433\u0430\u0432\u0438\u0446\u044b\u043d\u043e"
    ],
    "wof:name":"Nagavitsyno",
    "wof:placetype":"locality"
},
  "geometry": {"coordinates":[43.38364,56.70493],"type":"Point"}
}