{
  "type": "Feature",
  "properties": {
    "gn:country":"RU",
    "gn:fcode":"PPL",
    "gn:pop":300,
    "iso:country":"RU",
    "name:ceb_x_preferred":[
        "Ust'-Koysug"
    ],
    "name:che_x_preferred":[
        "\u0423\u0441\u0442\u044c-\u041a\u043e\u0439\u0441\u0443\u0433"
    ],
    "name:eng_x_preferred":[
        "Ust'-Koysug"
    ],
    "name:hye_x_preferred":[
        "\u0548\u0582\u057d\u057f-\u053f\u0578\u056b\u057d\u0578\u0582\u0563"
    ],
    "name:rus_x_preferred":[
        "\u0423\u0441\u0442\u044c-\u041a\u043e\u0439\u0441\u0443\u0433"
    ],
    "qs:name":"Ust'-Koysug",
    "qs:photos_9r":0,
    "qs:photos_sr":0,
    "qs:pop_sr":"2",
    "wof:name":"Ust'-Koysug",
    "wof:placetype":"locality",
    "wof:population":300
},
  "geometry": {"coordinates":[39.56786,47.14005],"type":"Point"}
}