{
  "type": "Feature",
  "properties": {
    "gn:admin1_code":"42",
    "gn:asciiname":"Sigalovo",
    "gn:country_code":"RU",
    "gn:dem":84,
    "gn:feature_class":"P",
    "gn:feature_code":"PPL",
    "gn:name":"Sigalovo",
    "gn:population":0,
    "gn:timezone":"Europe/Moscow",
    "iso:country":"RU",
    "name:fin_x_preferred":[
        "Siikala"
    ],
    "name:rus_x_preferred":[
        "\u0421\u0438\u0433\u0430\u043b\u043e\u0432\u043e"
    ],
    "wof:name":"Sigalovo",
    "wof:placetype":"locality"
},
  "geometry": {"coordinates":[31.19087,59.62246],"type":"Point"}
}