{
  "type": "Feature",
  "properties": {
    "gn:admin1_code":"37",
    "gn:asciiname":"Kozionikha",
    "gn:country_code":"RU",
    "gn:dem":129,
    "gn:feature_class":"P",
    "gn:feature_code":"PPL",
    "gn:name":"Kozionikha",
    "gn:population":0,
    "gn:timezone":"Europe/Moscow",
    "iso:country":"RU",
    "name:rus_x_preferred":[
        "\u041a\u043e\u0437\u0438\u043e\u043d\u0438\u0445\u0430"
    ],
    "name:und_x_variant":[
        "\u041a\u043e\u0437\u0438\u043e\u043d\u0438\u0445\u0430"
    ],
    "wof:name":"Kozionikha",
    "wof:placetype":"locality"
},
  "geometry": {"coordinates":[45.5951,58.157],"type":"Point"}
}