{
  "type": "Feature",
  "properties": {
    "gn:admin1_code":"71.0",
    "gn:asciiname":"Zelenyy",
    "gn:country_code":"RU",
    "gn:dem":73,
    "gn:feature_class":"P",
    "gn:feature_code":"PPL",
    "gn:name":"Zel\u00ebnyy",
    "gn:population":0,
    "gn:timezone":"Asia/Yekaterinburg",
    "iso:country":"RU",
    "name:rus_x_preferred":[
        "\u0417\u0435\u043b\u0451\u043d\u044b\u0439"
    ],
    "name:und_x_variant":[
        "Zel\u00ebnyy"
    ],
    "wof:name":"Zelenyy",
    "wof:placetype":"locality"
},
  "geometry": {"coordinates":[61.80219,59.10049],"type":"Point"}
}