{
  "type": "Feature",
  "properties": {
    "gn:admin1_code":"47",
    "gn:asciiname":"Ravenskaya",
    "gn:country_code":"RU",
    "gn:dem":140,
    "gn:feature_class":"P",
    "gn:feature_code":"PPL",
    "gn:name":"Ravenskaya",
    "gn:population":0,
    "gn:timezone":"Europe/Moscow",
    "iso:country":"RU",
    "name:rus_x_preferred":[
        "\u0420\u0430\u0432\u0435\u043d\u0441\u043a\u0430\u044f"
    ],
    "name:und_x_variant":[
        "\u0420\u0430\u0432\u0435\u043d\u0441\u043a\u0430\u044f"
    ],
    "wof:name":"Ravenskaya",
    "wof:placetype":"locality"
},
  "geometry": {"coordinates":[39.14893,55.49321],"type":"Point"}
}