{
  "type": "Feature",
  "properties": {
    "gn:admin1_code":"37",
    "gn:asciiname":"Khaldino",
    "gn:country_code":"RU",
    "gn:dem":170,
    "gn:feature_class":"P",
    "gn:feature_code":"PPL",
    "gn:name":"Khaldino",
    "gn:population":0,
    "gn:timezone":"Europe/Moscow",
    "iso:country":"RU",
    "name:rus_x_preferred":[
        "\u0425\u0430\u043b\u0434\u0438\u043d\u043e"
    ],
    "wof:name":"Khaldino",
    "wof:placetype":"locality"
},
  "geometry": {"coordinates":[42.3822,58.5056],"type":"Point"}
}