{
  "type": "Feature",
  "properties": {
    "gn:admin1_code":"52",
    "gn:asciiname":"Ploskovo",
    "gn:country_code":"RU",
    "gn:dem":42,
    "gn:feature_class":"P",
    "gn:feature_code":"PPL",
    "gn:name":"Ploskovo",
    "gn:population":0,
    "gn:timezone":"Europe/Moscow",
    "iso:country":"RU",
    "name:rus_x_preferred":[
        "\u041f\u043b\u043e\u0441\u043a\u043e\u0432\u043e"
    ],
    "wof:name":"Ploskovo",
    "wof:placetype":"locality"
},
  "geometry": {"coordinates":[30.27125,58.29794],"type":"Point"}
}