{
  "type": "Feature",
  "properties": {
    "gn:admin1_code":"90",
    "gn:asciiname":"Pikhtovka",
    "gn:country_code":"RU",
    "gn:dem":179,
    "gn:feature_class":"P",
    "gn:feature_code":"PPL",
    "gn:name":"Pikhtovka",
    "gn:population":0,
    "gn:timezone":"Asia/Yekaterinburg",
    "iso:country":"RU",
    "name:che_x_preferred":[
        "\u041f\u0438\u0445\u0442\u043e\u0432\u043a\u0430"
    ],
    "name:eng_x_preferred":[
        "Pikhtovka"
    ],
    "name:koi_x_preferred":[
        "\u041f\u0438\u043a\u0442\u043e\u0432\u043a\u0430"
    ],
    "name:nor_x_preferred":[
        "Pikhtovka"
    ],
    "name:rus_x_preferred":[
        "\u041f\u0438\u0445\u0442\u043e\u0432\u043a\u0430"
    ],
    "wof:name":"Pikhtovka",
    "wof:placetype":"locality"
},
  "geometry": {"coordinates":[54.93107,57.54987],"type":"Point"}
}