{
  "type": "Feature",
  "properties": {
    "gn:admin1_code":"72",
    "gn:asciiname":"Nizhnyaya Mazovka",
    "gn:country_code":"RU",
    "gn:dem":110,
    "gn:feature_class":"P",
    "gn:feature_code":"PPL",
    "gn:name":"Nizhnyaya Mazovka",
    "gn:population":0,
    "gn:timezone":"Europe/Moscow",
    "iso:country":"RU",
    "name:rus_x_preferred":[
        "\u041d\u0438\u0436\u043d\u044f\u044f \u041c\u0430\u0437\u043e\u0432\u043a\u0430"
    ],
    "wof:name":"Nizhnyaya Mazovka",
    "wof:placetype":"locality"
},
  "geometry": {"coordinates":[41.4866,53.00057],"type":"Point"}
}