{
  "type": "Feature",
  "properties": {
    "gn:admin1_code":"10",
    "gn:asciiname":"Rubezh",
    "gn:country_code":"RU",
    "gn:dem":141,
    "gn:feature_class":"P",
    "gn:feature_code":"PPL",
    "gn:name":"Rubezh",
    "gn:population":0,
    "gn:timezone":"Europe/Moscow",
    "iso:country":"RU",
    "name:rus_x_preferred":[
        "\u0420\u0443\u0431\u0435\u0436"
    ],
    "name:und_x_variant":[
        "\u0420\u0443\u0431\u0435\u0436"
    ],
    "wof:name":"Rubezh",
    "wof:placetype":"locality"
},
  "geometry": {"coordinates":[32.37971,52.24622],"type":"Point"}
}