{
  "type": "Feature",
  "properties": {
    "gn:admin1_code":"41",
    "gn:asciiname":"Druzhnaya",
    "gn:country_code":"RU",
    "gn:dem":167,
    "gn:feature_class":"P",
    "gn:feature_code":"PPL",
    "gn:name":"Druzhnaya",
    "gn:population":0,
    "gn:timezone":"Europe/Moscow",
    "iso:country":"RU",
    "name:che_x_preferred":[
        "\u0414\u0440\u0443\u0436\u043d\u0438"
    ],
    "name:eng_x_preferred":[
        "Druzhnaya"
    ],
    "name:rus_x_preferred":[
        "\u0414\u0440\u0443\u0436\u043d\u0430\u044f"
    ],
    "wof:name":"Druzhnaya",
    "wof:placetype":"locality"
},
  "geometry": {"coordinates":[35.57699,51.61763],"type":"Point"}
}