{
  "type": "Feature",
  "properties": {
    "gn:admin1_code":"73",
    "gn:asciiname":"Novoye Iglaykino",
    "gn:country_code":"RU",
    "gn:dem":81,
    "gn:feature_class":"P",
    "gn:feature_code":"PPL",
    "gn:name":"Novoye Iglaykino",
    "gn:population":0,
    "gn:timezone":"Europe/Moscow",
    "iso:country":"RU",
    "name:rus_x_preferred":[
        "\u041d\u043e\u0432\u043e\u0435 \u0418\u0433\u043b\u0430\u0439\u043a\u0438\u043d\u043e"
    ],
    "wof:name":"Novoye Iglaykino",
    "wof:placetype":"locality"
},
  "geometry": {"coordinates":[50.9075,54.40914],"type":"Point"}
}