{
  "type": "Feature",
  "properties": {
    "gn:admin1_code":"7",
    "gn:asciiname":"Tal'nikovyy",
    "gn:country_code":"RU",
    "gn:dem":-24,
    "gn:feature_class":"P",
    "gn:feature_code":"PPL",
    "gn:name":"Tal\u2019nikovyy",
    "gn:population":0,
    "gn:timezone":"Europe/Astrakhan",
    "iso:country":"RU",
    "name:rus_x_preferred":[
        "\u0422\u0430\u043b\u044c\u043d\u0438\u043a\u043e\u0432\u044b\u0439"
    ],
    "name:und_x_variant":[
        "Tal\u2019nikovyy"
    ],
    "wof:name":"Tal'nikovyy",
    "wof:placetype":"locality"
},
  "geometry": {"coordinates":[48.05201,46.63951],"type":"Point"}
}