{
  "type": "Feature",
  "properties": {
    "gn:admin1_code":"88",
    "gn:asciiname":"Velichkovo",
    "gn:country_code":"RU",
    "gn:dem":166,
    "gn:feature_class":"P",
    "gn:feature_code":"PPL",
    "gn:name":"Velichkovo",
    "gn:population":0,
    "gn:timezone":"Europe/Moscow",
    "iso:country":"RU",
    "name:rus_x_preferred":[
        "\u0412\u0435\u043b\u0438\u0447\u043a\u043e\u0432\u043e"
    ],
    "wof:name":"Velichkovo",
    "wof:placetype":"locality"
},
  "geometry": {"coordinates":[39.58725,57.41593],"type":"Point"}
}