{
  "type": "Feature",
  "properties": {
    "gn:admin1_code":"29.0",
    "gn:asciiname":"Tyrgan",
    "gn:country_code":"RU",
    "gn:dem":383,
    "gn:feature_class":"P",
    "gn:feature_code":"PPL",
    "gn:name":"Tyrgan",
    "gn:population":0,
    "gn:timezone":"Asia/Novokuznetsk",
    "iso:country":"RU",
    "name:rus_x_preferred":[
        "\u0422\u044b\u0440\u0433\u0430\u043d"
    ],
    "wof:name":"Tyrgan",
    "wof:placetype":"locality"
},
  "geometry": {"coordinates":[86.6426,53.9049],"type":"Point"}
}