{
  "type": "Feature",
  "properties": {
    "gn:admin1_code":"91.0",
    "gn:asciiname":"Zelenaya Gorka",
    "gn:country_code":"RU",
    "gn:dem":337,
    "gn:feature_class":"P",
    "gn:feature_code":"PPL",
    "gn:name":"Zel\u00ebnaya Gorka",
    "gn:population":0,
    "gn:timezone":"Asia/Krasnoyarsk",
    "iso:country":"RU",
    "wof:name":"Zelenaya Gorka",
    "wof:placetype":"locality"
},
  "geometry": {"coordinates":[89.9469,55.89418000000001],"type":"Point"}
}