{
  "type": "Feature",
  "properties": {
    "gn:admin1_code":"53",
    "gn:asciiname":"Novoshukhovo",
    "gn:country_code":"RU",
    "gn:dem":118,
    "gn:feature_class":"P",
    "gn:feature_code":"PPL",
    "gn:name":"Novoshukhovo",
    "gn:population":0,
    "gn:timezone":"Asia/Novosibirsk",
    "iso:country":"RU",
    "name:rus_x_preferred":[
        "\u041d\u043e\u0432\u043e\u0448\u0443\u0445\u043e\u0432\u043e"
    ],
    "name:und_x_variant":[
        "Novoye Shukhovo",
        "Novoshukhovo"
    ],
    "wof:name":"Novoshukhovo",
    "wof:placetype":"locality"
},
  "geometry": {"coordinates":[76.41667,56.36666999999999],"type":"Point"}
}