{
  "type": "Feature",
  "properties": {
    "gn:admin1_code":"6",
    "gn:asciiname":"Ploshchad'",
    "gn:country_code":"RU",
    "gn:dem":187,
    "gn:feature_class":"P",
    "gn:feature_code":"PPL",
    "gn:name":"Ploshchad\u2019",
    "gn:population":0,
    "gn:timezone":"Europe/Moscow",
    "iso:country":"RU",
    "name:eng_x_preferred":[
        "Ploshchad'"
    ],
    "name:nor_x_preferred":[
        "Plosjtsjad"
    ],
    "name:rus_x_preferred":[
        "\u041f\u043b\u043e\u0449\u0430\u0434\u044c"
    ],
    "name:und_x_variant":[
        "Vol\u2019skaya",
        "Kl\u00ebnovo-Ploshchad\u2019",
        "Klenovo-Vol\u2019skaya",
        "Ploshchad\u2019"
    ],
    "wof:name":"Ploshchad'",
    "wof:placetype":"locality"
},
  "geometry": {"coordinates":[39.37011,61.0189],"type":"Point"}
}