{
  "type": "Feature",
  "properties": {
    "gn:admin1_code":"90",
    "gn:asciiname":"Olekovo",
    "gn:country_code":"RU",
    "gn:dem":115,
    "gn:feature_class":"P",
    "gn:feature_code":"PPL",
    "gn:name":"Ol\u00ebkovo",
    "gn:population":0,
    "gn:timezone":"Asia/Yekaterinburg",
    "iso:country":"RU",
    "name:eng_x_preferred":[
        "Ol\u00ebkovo"
    ],
    "name:nor_x_preferred":[
        "Olekovo"
    ],
    "name:rus_x_preferred":[
        "\u041e\u043b\u0435\u043a\u043e\u0432\u043e"
    ],
    "name:rus_x_variant":[
        "\u041e\u043b\u0451\u043a\u043e\u0432\u043e"
    ],
    "name:und_x_variant":[
        "Olekova"
    ],
    "wof:name":"Olekovo",
    "wof:placetype":"locality"
},
  "geometry": {"coordinates":[55.8562,58.7897],"type":"Point"}
}