{
  "type": "Feature",
  "properties": {
    "gn:admin1_code":"29",
    "gn:asciiname":"Benzherep Vtoroy",
    "gn:country_code":"RU",
    "gn:dem":243,
    "gn:feature_class":"P",
    "gn:feature_code":"PPL",
    "gn:name":"Benzherep Vtoroy",
    "gn:population":0,
    "gn:timezone":"Asia/Novokuznetsk",
    "iso:country":"RU",
    "name:nor_x_preferred":[
        "Benzjerep Vtoroj"
    ],
    "name:rus_x_preferred":[
        "\u0411\u0435\u043d\u0436\u0435\u0440\u0435\u043f \u0412\u0442\u043e\u0440\u043e\u0439"
    ],
    "wof:name":"Benzherep Vtoroy",
    "wof:placetype":"locality"
},
  "geometry": {"coordinates":[86.79559999999999,53.2629],"type":"Point"}
}