{
  "type": "Feature",
  "properties": {
    "gn:admin1_code":"85",
    "gn:asciiname":"Zhokhovo",
    "gn:country_code":"RU",
    "gn:dem":138,
    "gn:feature_class":"P",
    "gn:feature_code":"PPL",
    "gn:name":"Zhokhovo",
    "gn:population":0,
    "gn:timezone":"Europe/Moscow",
    "iso:country":"RU",
    "name:rus_x_preferred":[
        "\u0416\u043e\u0445\u043e\u0432\u043e"
    ],
    "name:und_x_variant":[
        "\u0416\u043e\u0445\u043e\u0432\u043e"
    ],
    "wof:name":"Zhokhovo",
    "wof:placetype":"locality"
},
  "geometry": {"coordinates":[38.31209000000001,59.94505],"type":"Point"}
}