{
  "type": "Feature",
  "properties": {
    "gn:admin1_code":"56",
    "gn:asciiname":"Kalinina",
    "gn:country_code":"RU",
    "gn:dem":231,
    "gn:feature_class":"P",
    "gn:feature_code":"PPL",
    "gn:name":"Kalinina",
    "gn:population":0,
    "gn:timezone":"Europe/Moscow",
    "iso:country":"RU",
    "name:rus_x_preferred":[
        "\u041a\u0430\u043b\u0438\u043d\u0438\u043d\u0430"
    ],
    "name:und_x_variant":[
        "\u041a\u0430\u043b\u0438\u043d\u0438\u043d\u0430"
    ],
    "wof:name":"Kalinina",
    "wof:placetype":"locality"
},
  "geometry": {"coordinates":[36.0253,53.51841],"type":"Point"}
}