{
  "type": "Feature",
  "properties": {
    "gn:admin1_code":"51",
    "gn:asciiname":"Pershino",
    "gn:country_code":"RU",
    "gn:dem":84,
    "gn:feature_class":"P",
    "gn:feature_code":"PPL",
    "gn:name":"Pershino",
    "gn:population":0,
    "gn:timezone":"Europe/Moscow",
    "iso:country":"RU",
    "name:nor_x_preferred":[
        "Persjino"
    ],
    "name:rus_x_preferred":[
        "\u041f\u0435\u0440\u0448\u0438\u043d\u043e"
    ],
    "wof:name":"Pershino",
    "wof:placetype":"locality"
},
  "geometry": {"coordinates":[43.97961,56.50852],"type":"Point"}
}