{
  "type": "Feature",
  "properties": {
    "gn:admin1_code":"52",
    "gn:asciiname":"Teremovo",
    "gn:country_code":"RU",
    "gn:dem":58,
    "gn:feature_class":"P",
    "gn:feature_code":"PPL",
    "gn:name":"Teremovo",
    "gn:population":0,
    "gn:timezone":"Europe/Moscow",
    "iso:country":"RU",
    "name:rus_x_preferred":[
        "\u0422\u0435\u0440\u0435\u043c\u043e\u0432\u043e"
    ],
    "name:und_x_variant":[
        "\u0422\u0435\u0440\u0435\u043c\u043e\u0432\u043e"
    ],
    "wof:name":"Teremovo",
    "wof:placetype":"locality"
},
  "geometry": {"coordinates":[31.29865,57.74068000000001],"type":"Point"}
}