{
  "type": "Feature",
  "properties": {
    "gn:admin1_code":"79",
    "gn:asciiname":"Khut",
    "gn:country_code":"RU",
    "gn:dem":985,
    "gn:feature_class":"P",
    "gn:feature_code":"PPL",
    "gn:name":"Khut",
    "gn:population":0,
    "gn:timezone":"Asia/Krasnoyarsk",
    "iso:country":"RU",
    "name:eng_x_preferred":[
        "Khut"
    ],
    "name:nor_x_preferred":[
        "Khut"
    ],
    "name:rus_x_preferred":[
        "\u0425\u0443\u0442"
    ],
    "wof:name":"Khut",
    "wof:placetype":"locality"
},
  "geometry": {"coordinates":[94.55333,52.61833000000001],"type":"Point"}
}