{
  "type": "Feature",
  "properties": {
    "gn:admin1_code":"40",
    "gn:asciiname":"Sukhanova",
    "gn:country_code":"RU",
    "gn:dem":135,
    "gn:feature_class":"P",
    "gn:feature_code":"PPL",
    "gn:name":"Sukhanova",
    "gn:population":0,
    "gn:timezone":"Asia/Yekaterinburg",
    "iso:country":"RU",
    "name:rus_x_preferred":[
        "\u0421\u0443\u0445\u0430\u043d\u043e\u0432\u0430"
    ],
    "name:und_x_variant":[
        "\u0421\u0443\u0445\u0430\u043d\u043e\u0432\u0430"
    ],
    "wof:name":"Sukhanova",
    "wof:placetype":"locality"
},
  "geometry": {"coordinates":[64.11444,55.32083000000001],"type":"Point"}
}