{
  "type": "Feature",
  "properties": {
    "gn:admin1_code":"88",
    "gn:asciiname":"Konditovo",
    "gn:country_code":"RU",
    "gn:dem":124,
    "gn:feature_class":"P",
    "gn:feature_code":"PPL",
    "gn:name":"Konditovo",
    "gn:population":0,
    "gn:timezone":"Europe/Moscow",
    "iso:country":"RU",
    "name:rus_x_preferred":[
        "\u041a\u043e\u043d\u0434\u0438\u0442\u043e\u0432\u043e"
    ],
    "wof:name":"Konditovo",
    "wof:placetype":"locality"
},
  "geometry": {"coordinates":[39.61702,57.32234],"type":"Point"}
}