{
  "type": "Feature",
  "properties": {
    "gn:admin1_code":"60",
    "gn:asciiname":"Makarova",
    "gn:cc2":"RU",
    "gn:country_code":"RU",
    "gn:dem":83,
    "gn:feature_class":"P",
    "gn:feature_code":"PPL",
    "gn:name":"Makarova",
    "gn:population":0,
    "gn:timezone":"Europe/Moscow",
    "iso:country":"RU",
    "name:rus_x_preferred":[
        "\u041c\u0430\u043a\u0430\u0440\u043e\u0432\u0430"
    ],
    "name:und_x_variant":[
        "M\u00e4\u00eb M\u00e4karova",
        "Makarova",
        "\u041c\u0430\u043a\u0430\u0440\u043e\u0432\u0430"
    ],
    "wof:name":"Makarova",
    "wof:placetype":"locality"
},
  "geometry": {"coordinates":[27.81667,57.78333000000001],"type":"Point"}
}