{
  "type": "Feature",
  "properties": {
    "gn:admin1_code":"65",
    "gn:asciiname":"Il'ichevskiy",
    "gn:country_code":"RU",
    "gn:dem":182,
    "gn:feature_class":"P",
    "gn:feature_code":"PPL",
    "gn:name":"Il\u2019ich\u00ebvskiy",
    "gn:population":0,
    "gn:timezone":"Europe/Samara",
    "iso:country":"RU",
    "name:rus_x_preferred":[
        "\u0418\u043b\u044c\u0438\u0447\u0451\u0432\u0441\u043a\u0438\u0439"
    ],
    "name:und_x_variant":[
        "Il\u2019ich\u00ebvskiy"
    ],
    "wof:name":"Il'ichevskiy",
    "wof:placetype":"locality"
},
  "geometry": {"coordinates":[51.181,52.50100000000001],"type":"Point"}
}