{
  "type": "Feature",
  "properties": {
    "gn:admin1_code":"21.0",
    "gn:asciiname":"Rostonovo",
    "gn:country_code":"RU",
    "gn:dem":101,
    "gn:feature_class":"P",
    "gn:feature_code":"PPL",
    "gn:name":"Rostonovo",
    "gn:population":0,
    "gn:timezone":"Europe/Moscow",
    "iso:country":"RU",
    "name:rus_x_preferred":[
        "\u0420\u043e\u0441\u0442\u043e\u043d\u043e\u0432\u043e"
    ],
    "name:und_x_variant":[
        "\u0420\u043e\u0441\u0442\u043e\u043d\u043e\u0432\u043e"
    ],
    "wof:name":"Rostonovo",
    "wof:placetype":"locality"
},
  "geometry": {"coordinates":[42.80147,57.32523000000001],"type":"Point"}
}