{
  "type": "Feature",
  "properties": {
    "gn:admin1_code":"6",
    "gn:asciiname":"Yemen'gskiy",
    "gn:country_code":"RU",
    "gn:dem":163,
    "gn:feature_class":"P",
    "gn:feature_code":"PPL",
    "gn:name":"Yemen\u2019gskiy",
    "gn:population":0,
    "gn:timezone":"Europe/Moscow",
    "iso:country":"RU",
    "wof:name":"Yemen'gskiy",
    "wof:placetype":"locality"
},
  "geometry": {"coordinates":[40.93333,61.45],"type":"Point"}
}