{
  "type": "Feature",
  "properties": {
    "gn:admin1_code":"57",
    "gn:asciiname":"Karmanovka",
    "gn:country_code":"RU",
    "gn:dem":292,
    "gn:feature_class":"P",
    "gn:feature_code":"PPL",
    "gn:name":"Karmanovka",
    "gn:population":0,
    "gn:timezone":"Europe/Moscow",
    "iso:country":"RU",
    "name:rus_x_preferred":[
        "\u041a\u0430\u0440\u043c\u0430\u043d\u043e\u0432\u043a\u0430"
    ],
    "name:und_x_variant":[
        "\u041a\u0430\u0440\u043c\u0430\u043d\u043e\u0432\u043a\u0430"
    ],
    "wof:name":"Karmanovka",
    "wof:placetype":"locality"
},
  "geometry": {"coordinates":[46.75,53.06667],"type":"Point"}
}