{
  "type": "Feature",
  "properties": {
    "gn:admin1_code":"64",
    "gn:asciiname":"Parusnoye",
    "gn:country_code":"RU",
    "gn:dem":19,
    "gn:feature_class":"P",
    "gn:feature_code":"PPL",
    "gn:name":"Parusnoye",
    "gn:population":0,
    "gn:timezone":"Asia/Tokyo",
    "iso:country":"RU",
    "name:rus_x_preferred":[
        "\u041f\u0430\u0440\u0443\u0441\u043d\u043e\u0435"
    ],
    "name:und_x_variant":[
        "Porosu",
        "Horosu",
        "Parusnoye"
    ],
    "wof:name":"Parusnoye",
    "wof:placetype":"locality"
},
  "geometry": {"coordinates":[148.34474,45.29251],"type":"Point"}
}