{
  "type": "Feature",
  "properties": {
    "gn:admin1_code":"33",
    "gn:asciiname":"Gremyachevo",
    "gn:country_code":"RU",
    "gn:dem":115,
    "gn:feature_class":"P",
    "gn:feature_code":"PPL",
    "gn:name":"Gremyachevo",
    "gn:population":0,
    "gn:timezone":"Europe/Kirov",
    "iso:country":"RU",
    "name:ara_x_preferred":[
        "\u063a\u0631\u064a\u0645\u064a\u0634\u0648\u0641\u0648"
    ],
    "name:che_x_preferred":[
        "\u0413\u0440\u0435\u043c\u044f\u0447\u0435\u0432\u043e"
    ],
    "name:rus_x_preferred":[
        "\u0413\u0440\u0435\u043c\u044f\u0447\u0435\u0432\u043e"
    ],
    "wof:name":"Gremyachevo",
    "wof:placetype":"locality"
},
  "geometry": {"coordinates":[48.4105,58.4857],"type":"Point"}
}