{
  "type": "Feature",
  "properties": {
    "gn:admin1_code":"8",
    "gn:asciiname":"Novokaragishevo",
    "gn:country_code":"RU",
    "gn:dem":156,
    "gn:feature_class":"P",
    "gn:feature_code":"PPL",
    "gn:name":"Novokaragishevo",
    "gn:population":0,
    "gn:timezone":"Asia/Yekaterinburg",
    "iso:country":"RU",
    "name:rus_x_preferred":[
        "\u041d\u043e\u0432\u043e\u043a\u0430\u0440\u0430\u0433\u0438\u0448\u0435\u0432\u043e"
    ],
    "name:und_x_variant":[
        "\u041d\u043e\u0432\u043e\u043a\u0430\u0440\u0430\u0433\u0438\u0448\u0435\u0432\u043e"
    ],
    "wof:name":"Novokaragishevo",
    "wof:placetype":"locality"
},
  "geometry": {"coordinates":[55.7179,55.727],"type":"Point"}
}