{
  "type": "Feature",
  "properties": {
    "gn:admin1_code":"90",
    "gn:asciiname":"Os'kino",
    "gn:country_code":"RU",
    "gn:dem":188,
    "gn:feature_class":"P",
    "gn:feature_code":"PPL",
    "gn:name":"Os\u2019kino",
    "gn:population":0,
    "gn:timezone":"Asia/Yekaterinburg",
    "iso:country":"RU",
    "name:rus_x_preferred":[
        "\u041e\u0441\u044c\u043a\u0438\u043d\u043e"
    ],
    "name:und_x_variant":[
        "Os\u2019kina",
        "Os\u2019kino",
        "\u041e\u0441\u044c\u043a\u0438\u043d\u043e"
    ],
    "wof:name":"Os'kino",
    "wof:placetype":"locality"
},
  "geometry": {"coordinates":[55.0024,58.1514],"type":"Point"}
}