{
  "type": "Feature",
  "properties": {
    "gn:admin1_code":"41",
    "gn:asciiname":"Vyshniy Terebuzh",
    "gn:country_code":"RU",
    "gn:dem":227,
    "gn:feature_class":"P",
    "gn:feature_code":"PPL",
    "gn:name":"Vyshniy Terebuzh",
    "gn:population":0,
    "gn:timezone":"Europe/Moscow",
    "iso:country":"RU",
    "name:rus_x_preferred":[
        "\u0412\u044b\u0448\u043d\u0438\u0439 \u0422\u0435\u0440\u0435\u0431\u0443\u0436"
    ],
    "wof:name":"Vyshniy Terebuzh",
    "wof:placetype":"locality"
},
  "geometry": {"coordinates":[36.7006,52.0762],"type":"Point"}
}