{
  "type": "Feature",
  "properties": {
    "gn:admin1_code":"91",
    "gn:asciiname":"Tyulyapsy",
    "gn:country_code":"RU",
    "gn:dem":151,
    "gn:feature_class":"P",
    "gn:feature_code":"PPL",
    "gn:name":"Tyulyapsy",
    "gn:population":0,
    "gn:timezone":"Asia/Krasnoyarsk",
    "iso:country":"RU",
    "name:eng_x_preferred":[
        "Tyulyapsy"
    ],
    "name:nor_x_preferred":[
        "Tjuljapsy"
    ],
    "name:rus_x_preferred":[
        "\u0422\u044e\u043b\u044f\u043f\u0441\u044b"
    ],
    "name:und_x_variant":[
        "Tyulyapsinskiy",
        "Tyulyapsy"
    ],
    "wof:name":"Tyulyapsy",
    "wof:placetype":"locality"
},
  "geometry": {"coordinates":[89.64234,57.46504],"type":"Point"}
}