{
  "type": "Feature",
  "properties": {
    "gn:admin1_code":"72.0",
    "gn:asciiname":"Bol'shoye Nikol'skoye",
    "gn:country_code":"RU",
    "gn:dem":147,
    "gn:feature_class":"P",
    "gn:feature_code":"PPL",
    "gn:name":"Bol\u2019shoye Nikol\u2019skoye",
    "gn:population":0,
    "gn:timezone":"Europe/Moscow",
    "iso:country":"RU",
    "name:rus_x_preferred":[
        "\u0411\u043e\u043b\u044c\u0448\u043e\u0435 \u041d\u0438\u043a\u043e\u043b\u044c\u0441\u043a\u043e\u0435"
    ],
    "name:und_x_variant":[
        "Bol\u2019shoye Nikol\u2019skoye"
    ],
    "wof:name":"Bol'shoye Nikol'skoye",
    "wof:placetype":"locality"
},
  "geometry": {"coordinates":[41.91626,53.06193],"type":"Point"}
}