{
  "type": "Feature",
  "properties": {
    "gn:admin1_code":"10",
    "gn:asciiname":"Krasnyye Gorki",
    "gn:country_code":"RU",
    "gn:dem":176,
    "gn:feature_class":"P",
    "gn:feature_code":"PPL",
    "gn:name":"Krasnyye Gorki",
    "gn:population":0,
    "gn:timezone":"Europe/Moscow",
    "iso:country":"RU",
    "name:rus_x_preferred":[
        "\u041a\u0440\u0430\u0441\u043d\u044b\u0435 \u0413\u043e\u0440\u043a\u0438"
    ],
    "name:und_x_variant":[
        "\u041a\u0440\u0430\u0441\u043d\u044b\u0435 \u0413\u043e\u0440\u043a\u0438"
    ],
    "wof:name":"Krasnyye Gorki",
    "wof:placetype":"locality"
},
  "geometry": {"coordinates":[33.3531,52.9719],"type":"Point"}
}