{
  "type": "Feature",
  "properties": {
    "gn:admin1_code":"11",
    "gn:asciiname":"Kharagun",
    "gn:country_code":"RU",
    "gn:dem":746,
    "gn:feature_class":"P",
    "gn:feature_code":"PPL",
    "gn:name":"Kharagun",
    "gn:population":0,
    "gn:timezone":"Asia/Irkutsk",
    "iso:country":"RU",
    "name:rus_x_preferred":[
        "\u0425\u0430\u0440\u0430\u0433\u0443\u043d"
    ],
    "wof:name":"Kharagun",
    "wof:placetype":"locality"
},
  "geometry": {"coordinates":[102.2157,51.673],"type":"Point"}
}