{
  "type": "Feature",
  "properties": {
    "gn:admin1_code":"28",
    "gn:asciiname":"Nil'ma Guba",
    "gn:country_code":"RU",
    "gn:dem":184,
    "gn:feature_class":"P",
    "gn:feature_code":"PPL",
    "gn:name":"Nil\u2019ma Guba",
    "gn:population":0,
    "gn:timezone":"Europe/Moscow",
    "iso:country":"RU",
    "name:fin_x_preferred":[
        "Nilmalahti"
    ],
    "name:rus_x_preferred":[
        "\u041d\u0438\u043b\u044c\u043c\u0430 \u0413\u0443\u0431\u0430"
    ],
    "name:und_x_variant":[
        "Nil\u2019ma Guba"
    ],
    "wof:name":"Nil'ma Guba",
    "wof:placetype":"locality"
},
  "geometry": {"coordinates":[30.26015,64.48959000000001],"type":"Point"}
}