{
  "type": "Feature",
  "properties": {
    "gn:admin1_code":"52",
    "gn:asciiname":"Shchelino",
    "gn:country_code":"RU",
    "gn:dem":47,
    "gn:feature_class":"P",
    "gn:feature_code":"PPL",
    "gn:name":"Shchelino",
    "gn:population":0,
    "gn:timezone":"Europe/Moscow",
    "iso:country":"RU",
    "name:rus_x_preferred":[
        "\u0429\u0435\u043b\u0438\u043d\u043e"
    ],
    "wof:name":"Shchelino",
    "wof:placetype":"locality"
},
  "geometry": {"coordinates":[30.48346,58.31766999999999],"type":"Point"}
}