{
  "type": "Feature",
  "properties": {
    "gn:admin1_code":"60",
    "gn:asciiname":"Khvatynya",
    "gn:country_code":"RU",
    "gn:dem":168,
    "gn:feature_class":"P",
    "gn:feature_code":"PPL",
    "gn:name":"Khvatynya",
    "gn:population":0,
    "gn:timezone":"Europe/Moscow",
    "iso:country":"RU",
    "name:rus_x_preferred":[
        "\u0425\u0432\u0430\u0442\u044b\u043d\u044f"
    ],
    "name:und_x_variant":[
        "\u0425\u0432\u0430\u0442\u044b\u043d\u044f"
    ],
    "wof:name":"Khvatynya",
    "wof:placetype":"locality"
},
  "geometry": {"coordinates":[29.68333,55.81667],"type":"Point"}
}