{
  "type": "Feature",
  "properties": {
    "gn:admin1_code":"47",
    "gn:asciiname":"Strekovo",
    "gn:country_code":"RU",
    "gn:dem":200,
    "gn:feature_class":"P",
    "gn:feature_code":"PPL",
    "gn:name":"Strekovo",
    "gn:population":0,
    "gn:timezone":"Europe/Moscow",
    "iso:country":"RU",
    "name:rus_x_preferred":[
        "\u0421\u0442\u0440\u0435\u043a\u043e\u0432\u043e"
    ],
    "name:und_x_variant":[
        "\u0421\u0442\u0440\u0435\u043a\u043e\u0432\u043e"
    ],
    "wof:name":"Strekovo",
    "wof:placetype":"locality"
},
  "geometry": {"coordinates":[37.45,56.25],"type":"Point"}
}