{
  "type": "Feature",
  "properties": {
    "gn:admin1_code":"1.0",
    "gn:asciiname":"Mikhel'sonovskiy",
    "gn:country_code":"RU",
    "gn:dem":183,
    "gn:feature_class":"P",
    "gn:feature_code":"PPL",
    "gn:name":"Mikhel\u2019sonovskiy",
    "gn:population":0,
    "gn:timezone":"Europe/Moscow",
    "iso:country":"RU",
    "name:rus_x_preferred":[
        "\u041c\u0438\u0445\u0435\u043b\u044c\u0441\u043e\u043d\u043e\u0432\u0441\u043a\u0438\u0439"
    ],
    "name:und_x_variant":[
        "Mikhel\u2019sonovskiy",
        "\u041c\u0438\u0445\u0435\u043b\u044c\u0441\u043e\u043d\u043e\u0432\u0441\u043a\u0438\u0439"
    ],
    "wof:name":"Mikhel'sonovskiy",
    "wof:placetype":"locality"
},
  "geometry": {"coordinates":[40.31028,44.765],"type":"Point"}
}