{
  "type": "Feature",
  "properties": {
    "gn:admin1_code":"75",
    "gn:asciiname":"Korotkino",
    "gn:cc2":"RU",
    "gn:country_code":"RU",
    "gn:dem":63,
    "gn:feature_class":"P",
    "gn:feature_code":"PPL",
    "gn:name":"Korotkino",
    "gn:population":0,
    "gn:timezone":"Asia/Tomsk",
    "iso:country":"RU",
    "name:eng_x_preferred":[
        "Korotkino"
    ],
    "name:nor_x_preferred":[
        "Novokorotkino"
    ],
    "name:rus_x_preferred":[
        "\u041d\u043e\u0432\u043e\u043a\u043e\u0440\u043e\u0442\u043a\u0438\u043d\u043e"
    ],
    "name:rus_x_variant":[
        "\u041a\u043e\u0440\u043e\u0442\u043a\u0438\u043d\u043e"
    ],
    "name:und_x_variant":[
        "Korotkina"
    ],
    "wof:name":"Korotkino",
    "wof:placetype":"locality"
},
  "geometry": {"coordinates":[82.96666999999999,58.01667],"type":"Point"}
}