{
  "type": "Feature",
  "properties": {
    "gn:admin1_code":"32",
    "gn:asciiname":"Nazarovo",
    "gn:country_code":"RU",
    "gn:dem":38,
    "gn:feature_class":"P",
    "gn:feature_code":"PPL",
    "gn:name":"Nazarovo",
    "gn:population":0,
    "gn:timezone":"Asia/Yekaterinburg",
    "iso:country":"RU",
    "name:eng_x_preferred":[
        "Nazarovo"
    ],
    "name:nor_x_preferred":[
        "Nazarovo"
    ],
    "name:rus_x_preferred":[
        "\u041d\u0430\u0437\u0430\u0440\u043e\u0432\u043e"
    ],
    "name:swe_x_preferred":[
        "Nazarovo"
    ],
    "name:tgl_x_preferred":[
        "Nazarovo"
    ],
    "wof:name":"Nazarovo",
    "wof:placetype":"locality"
},
  "geometry": {"coordinates":[64.33333,60.28333000000001],"type":"Point"}
}