{
  "type": "Feature",
  "properties": {
    "gn:admin1_code":"81",
    "gn:asciiname":"Krasnaya Estoniya",
    "gn:country_code":"RU",
    "gn:dem":153,
    "gn:feature_class":"P",
    "gn:feature_code":"PPL",
    "gn:name":"Krasnaya Estoniya",
    "gn:population":0,
    "gn:timezone":"Europe/Ulyanovsk",
    "iso:country":"RU",
    "name:rus_x_preferred":[
        "\u041a\u0440\u0430\u0441\u043d\u0430\u044f \u042d\u0441\u0442\u043e\u043d\u0438\u044f"
    ],
    "name:und_x_variant":[
        "\u041a\u0440\u0430\u0441\u043d\u0430\u044f \u042d\u0441\u0442\u043e\u043d\u0438\u044f"
    ],
    "wof:name":"Krasnaya Estoniya",
    "wof:placetype":"locality"
},
  "geometry": {"coordinates":[47.3879,53.9773],"type":"Point"}
}