{
  "type": "Feature",
  "properties": {
    "gn:admin1_code":"40",
    "gn:asciiname":"Baskovskoye",
    "gn:country_code":"RU",
    "gn:dem":131,
    "gn:feature_class":"P",
    "gn:feature_code":"PPL",
    "gn:name":"Baskovskoye",
    "gn:population":0,
    "gn:timezone":"Asia/Yekaterinburg",
    "iso:country":"RU",
    "name:eng_x_preferred":[
        "Baskovskoye"
    ],
    "name:nor_x_preferred":[
        "Baskovskoje"
    ],
    "name:rus_x_preferred":[
        "\u0411\u0430\u0441\u043a\u043e\u0432\u0441\u043a\u043e\u0435"
    ],
    "name:und_x_variant":[
        "Baskoye",
        "Baskovskiy"
    ],
    "wof:name":"Baskovskoye",
    "wof:placetype":"locality"
},
  "geometry": {"coordinates":[67.49056,55.03083],"type":"Point"}
}