{
  "type": "Feature",
  "properties": {
    "gn:admin1_code":"33",
    "gn:asciiname":"Krutovrazh'ye",
    "gn:country_code":"RU",
    "gn:dem":131,
    "gn:feature_class":"P",
    "gn:feature_code":"PPL",
    "gn:name":"Krutovrazh\u2019ye",
    "gn:population":0,
    "gn:timezone":"Europe/Kirov",
    "iso:country":"RU",
    "name:rus_x_preferred":[
        "\u041a\u0440\u0443\u0442\u043e\u0432\u0440\u0430\u0436\u044c\u0435"
    ],
    "name:und_x_variant":[
        "Krutovrazh\u2019ye"
    ],
    "wof:name":"Krutovrazh'ye",
    "wof:placetype":"locality"
},
  "geometry": {"coordinates":[47.36600000000001,57.24],"type":"Point"}
}