{
  "type": "Feature",
  "properties": {
    "gn:admin1_code":"90.0",
    "gn:asciiname":"Maloye Zapol'ye",
    "gn:country_code":"RU",
    "gn:dem":153,
    "gn:feature_class":"P",
    "gn:feature_code":"PPL",
    "gn:name":"Maloye Zapol\u2019ye",
    "gn:population":0,
    "gn:timezone":"Asia/Yekaterinburg",
    "iso:country":"RU",
    "name:und_x_variant":[
        "Maloye Zapol\u2019ye",
        "\u041c\u0430\u043b\u043e\u0435 \u0417\u0430\u043f\u043e\u043b\u044c\u0435"
    ],
    "wof:name":"Maloye Zapol'ye",
    "wof:placetype":"locality"
},
  "geometry": {"coordinates":[56.2666,58.549],"type":"Point"}
}