{
  "type": "Feature",
  "properties": {
    "gn:admin1_code":"76.0",
    "gn:asciiname":"Zelenyye Luzhki",
    "gn:country_code":"RU",
    "gn:dem":231,
    "gn:feature_class":"P",
    "gn:feature_code":"PPL",
    "gn:name":"Zel\u00ebnyye Luzhki",
    "gn:population":0,
    "gn:timezone":"Europe/Moscow",
    "iso:country":"RU",
    "name:und_x_variant":[
        "Zel\u00ebnyy Luzhok",
        "Zel\u00ebnyye Luzhki"
    ],
    "wof:name":"Zelenyye Luzhki",
    "wof:placetype":"locality"
},
  "geometry": {"coordinates":[36.14068,54.11661],"type":"Point"}
}