{
  "type": "Feature",
  "properties": {
    "gn:admin1_code":"63",
    "gn:asciiname":"Bereg",
    "gn:country_code":"RU",
    "gn:dem":100,
    "gn:feature_class":"P",
    "gn:feature_code":"PPL",
    "gn:name":"Bereg",
    "gn:population":0,
    "gn:timezone":"Asia/Yakutsk",
    "iso:country":"RU",
    "name:deu_x_preferred":[
        "Bereg"
    ],
    "name:fra_x_preferred":[
        "Bereg"
    ],
    "name:hrv_x_preferred":[
        "Bereg"
    ],
    "name:nld_x_preferred":[
        "Bereg"
    ],
    "name:nor_x_preferred":[
        "Bereg"
    ],
    "name:rus_x_preferred":[
        "\u0411\u0435\u0440\u0435\u0433"
    ],
    "wof:name":"Bereg",
    "wof:placetype":"locality"
},
  "geometry": {"coordinates":[133.13333,63.33333],"type":"Point"}
}