{
  "type": "Feature",
  "properties": {
    "gn:admin1_code":"77",
    "gn:asciiname":"Chernorytyye",
    "gn:country_code":"RU",
    "gn:dem":242,
    "gn:feature_class":"P",
    "gn:feature_code":"PPL",
    "gn:name":"Chernorytyye",
    "gn:population":0,
    "gn:timezone":"Europe/Moscow",
    "iso:country":"RU",
    "name:rus_x_preferred":[
        "\u0427\u0435\u0440\u043d\u043e\u0440\u044b\u0442\u044b\u0435"
    ],
    "wof:name":"Chernorytyye",
    "wof:placetype":"locality"
},
  "geometry": {"coordinates":[33.71556,56.92333000000001],"type":"Point"}
}