{
  "type": "Feature",
  "properties": {
    "gn:admin1_code":"42",
    "gn:asciiname":"Nevazhi",
    "gn:cc2":"RU",
    "gn:country_code":"RU",
    "gn:dem":31,
    "gn:feature_class":"P",
    "gn:feature_code":"PPL",
    "gn:name":"Nevazhi",
    "gn:population":0,
    "gn:timezone":"Europe/Moscow",
    "iso:country":"RU",
    "name:rus_x_preferred":[
        "\u041d\u0435\u0432\u0430\u0436\u0438"
    ],
    "name:und_x_variant":[
        "Nevazha",
        "Nevazhi",
        "\u041d\u0435\u0432\u0430\u0436\u0438"
    ],
    "wof:name":"Nevazhi",
    "wof:placetype":"locality"
},
  "geometry": {"coordinates":[32.25,59.98333],"type":"Point"}
}