{
  "type": "Feature",
  "properties": {
    "gn:admin1_code":"56",
    "gn:asciiname":"Pyatinskaya",
    "gn:country_code":"RU",
    "gn:dem":226,
    "gn:feature_class":"P",
    "gn:feature_code":"PPL",
    "gn:name":"Pyatinskaya",
    "gn:population":0,
    "gn:timezone":"Europe/Moscow",
    "iso:country":"RU",
    "name:rus_x_preferred":[
        "\u041f\u044f\u0442\u0438\u043d\u0441\u043a\u0430\u044f"
    ],
    "wof:name":"Pyatinskaya",
    "wof:placetype":"locality"
},
  "geometry": {"coordinates":[36.8071,52.4718],"type":"Point"}
}