{
  "type": "Feature",
  "properties": {
    "gn:admin1_code":"67",
    "gn:asciiname":"Ol'gino",
    "gn:country_code":"RU",
    "gn:dem":135,
    "gn:feature_class":"P",
    "gn:feature_code":"PPL",
    "gn:name":"Ol\u2019gino",
    "gn:population":0,
    "gn:timezone":"Europe/Saratov",
    "iso:country":"RU",
    "name:rus_x_preferred":[
        "\u041e\u043b\u044c\u0433\u0438\u043d\u043e"
    ],
    "name:und_x_variant":[
        "Ol\u2019gino",
        "\u041e\u043b\u044c\u0433\u0438\u043d\u043e"
    ],
    "wof:name":"Ol'gino",
    "wof:placetype":"locality"
},
  "geometry": {"coordinates":[43.68945,51.87319],"type":"Point"}
}