{
  "type": "Feature",
  "properties": {
    "gn:admin1_code":"42",
    "gn:asciiname":"Nizhnecherkasovo",
    "gn:cc2":"RU",
    "gn:country_code":"RU",
    "gn:dem":8,
    "gn:feature_class":"P",
    "gn:feature_code":"PPL",
    "gn:name":"Nizhnecherkasovo",
    "gn:population":0,
    "gn:timezone":"Europe/Moscow",
    "iso:country":"RU",
    "name:fin_x_preferred":[
        "Alas\u00e4ini\u00f6"
    ],
    "name:rus_x_preferred":[
        "\u041d\u0438\u0436\u043d\u0435\u0447\u0435\u0440\u043a\u0430\u0441\u043e\u0432\u043e"
    ],
    "name:und_x_variant":[
        "Ala-Syaynio",
        "Ala Syayniye",
        "Nizhnecherkasovo"
    ],
    "wof:name":"Nizhnecherkasovo",
    "wof:placetype":"locality"
},
  "geometry": {"coordinates":[28.83333,60.66667],"type":"Point"}
}