{
  "type": "Feature",
  "properties": {
    "gn:admin1_code":"86",
    "gn:asciiname":"Kopanaya Pervaya",
    "gn:country_code":"RU",
    "gn:dem":122,
    "gn:feature_class":"P",
    "gn:feature_code":"PPL",
    "gn:name":"Kopanaya Pervaya",
    "gn:population":0,
    "gn:timezone":"Europe/Moscow",
    "iso:country":"RU",
    "name:rus_x_preferred":[
        "\u041a\u043e\u043f\u0430\u043d\u0430\u044f \u041f\u0435\u0440\u0432\u0430\u044f"
    ],
    "name:und_x_variant":[
        "Kopanki",
        "Kopannoye",
        "Kopanaya",
        "Kopanaya Pervaya",
        "\u041a\u043e\u043f\u0430\u043d\u0430\u044f \u041f\u0435\u0440\u0432\u0430\u044f"
    ],
    "wof:name":"Kopanaya Pervaya",
    "wof:placetype":"locality"
},
  "geometry": {"coordinates":[39.09312,50.44441],"type":"Point"}
}