{
  "type": "Feature",
  "properties": {
    "gn:admin1_code":"25",
    "gn:asciiname":"Kuz'menki",
    "gn:country_code":"RU",
    "gn:dem":195,
    "gn:feature_class":"P",
    "gn:feature_code":"PPL",
    "gn:name":"\u041a\u0443\u0437\u044c\u043c\u0435\u043d\u043a\u0438",
    "gn:population":0,
    "gn:timezone":"Europe/Moscow",
    "iso:country":"RU",
    "name:rus_x_preferred":[
        "\u041a\u0443\u0437\u044c\u043c\u0435\u043d\u043a\u0438"
    ],
    "name:und_x_variant":[
        "\u041a\u0443\u0437\u044c\u043c\u0435\u043d\u043a\u0438",
        "Kuz\u2019menki"
    ],
    "wof:name":"Kuz'menki",
    "wof:placetype":"locality"
},
  "geometry": {"coordinates":[35.76468,54.19995],"type":"Point"}
}