{
  "type": "Feature",
  "properties": {
    "gn:admin1_code":"33.0",
    "gn:asciiname":"Tomilovy",
    "gn:country_code":"RU",
    "gn:dem":136,
    "gn:feature_class":"P",
    "gn:feature_code":"PPL",
    "gn:name":"Tomilovy",
    "gn:population":0,
    "gn:timezone":"Europe/Kirov",
    "iso:country":"RU",
    "name:rus_x_preferred":[
        "\u0422\u043e\u043c\u0438\u043b\u043e\u0432\u044b"
    ],
    "wof:name":"Tomilovy",
    "wof:placetype":"locality"
},
  "geometry": {"coordinates":[49.47006,58.56113000000001],"type":"Point"}
}