{
  "type": "Feature",
  "properties": {
    "gn:admin1_code":"60",
    "gn:asciiname":"Malakhi",
    "gn:country_code":"RU",
    "gn:dem":164,
    "gn:feature_class":"P",
    "gn:feature_code":"PPL",
    "gn:name":"Malakhi",
    "gn:population":0,
    "gn:timezone":"Europe/Moscow",
    "iso:country":"RU",
    "name:rus_x_preferred":[
        "\u041c\u0430\u043b\u0430\u0445\u0438"
    ],
    "name:und_x_variant":[
        "\u041c\u0430\u043b\u0430\u0445\u0438"
    ],
    "wof:name":"Malakhi",
    "wof:placetype":"locality"
},
  "geometry": {"coordinates":[29.21145,56.14623],"type":"Point"}
}