{
  "type": "Feature",
  "properties": {
    "gn:admin1_code":"91.0",
    "gn:asciiname":"Khaybalyk",
    "gn:country_code":"RU",
    "gn:dem":326,
    "gn:feature_class":"P",
    "gn:feature_code":"PPL",
    "gn:name":"Khaybalyk",
    "gn:population":0,
    "gn:timezone":"Asia/Krasnoyarsk",
    "iso:country":"RU",
    "name:rus_x_preferred":[
        "\u0425\u0430\u0439\u0431\u0430\u043b\u044b\u043a"
    ],
    "wof:name":"Khaybalyk",
    "wof:placetype":"locality"
},
  "geometry": {"coordinates":[93.03830000000001,53.7612],"type":"Point"}
}