{
  "type": "Feature",
  "properties": {
    "gn:admin1_code":"38",
    "gn:asciiname":"Sementsovka",
    "gn:country_code":"RU",
    "gn:dem":126,
    "gn:feature_class":"P",
    "gn:feature_code":"PPL",
    "gn:name":"Sementsovka",
    "gn:population":0,
    "gn:timezone":"Europe/Moscow",
    "iso:country":"RU",
    "name:rus_x_preferred":[
        "\u0421\u0435\u043c\u0435\u043d\u0446\u043e\u0432\u043a\u0430"
    ],
    "name:und_x_variant":[
        "Sementsovskiy",
        "Sementsovka",
        "\u0421\u0435\u043c\u0435\u043d\u0446\u043e\u0432\u043a\u0430"
    ],
    "wof:name":"Sementsovka",
    "wof:placetype":"locality"
},
  "geometry": {"coordinates":[38.00587,44.83919],"type":"Point"}
}