{
  "type": "Feature",
  "properties": {
    "gn:admin1_code":"45.0",
    "gn:asciiname":"Bakhtiarovo",
    "gn:country_code":"RU",
    "gn:dem":142,
    "gn:feature_class":"P",
    "gn:feature_code":"PPL",
    "gn:name":"Bakhtiarovo",
    "gn:population":0,
    "gn:timezone":"Europe/Moscow",
    "iso:country":"RU",
    "name:nor_x_preferred":[
        "Bakhtiarovo"
    ],
    "name:rus_x_preferred":[
        "\u0411\u0430\u0445\u0442\u0438\u0430\u0440\u043e\u0432\u043e"
    ],
    "name:und_x_variant":[
        "Bakhtiarova",
        "Bakhtiarovo"
    ],
    "wof:name":"Bakhtiarovo",
    "wof:placetype":"locality"
},
  "geometry": {"coordinates":[48.26167,56.70056],"type":"Point"}
}