{
  "type": "Feature",
  "properties": {
    "gn:admin1_code":"52",
    "gn:asciiname":"Svetlaya",
    "gn:country_code":"RU",
    "gn:dem":70,
    "gn:feature_class":"P",
    "gn:feature_code":"PPL",
    "gn:name":"Svetlaya",
    "gn:population":0,
    "gn:timezone":"Europe/Moscow",
    "iso:country":"RU",
    "name:und_x_variant":[
        "Svinorezha",
        "Svinorezhi",
        "Svetlaya"
    ],
    "wof:name":"Svetlaya",
    "wof:placetype":"locality"
},
  "geometry": {"coordinates":[30.06552000000001,58.4224],"type":"Point"}
}