{
  "type": "Feature",
  "properties": {
    "gn:admin1_code":"21",
    "gn:asciiname":"Krutitsy",
    "gn:country_code":"RU",
    "gn:dem":109,
    "gn:feature_class":"P",
    "gn:feature_code":"PPL",
    "gn:name":"Krutitsy",
    "gn:population":0,
    "gn:timezone":"Europe/Moscow",
    "iso:country":"RU",
    "name:deu_x_preferred":[
        "Krutizy"
    ],
    "name:fra_x_preferred":[
        "Kroutitski"
    ],
    "name:rus_x_preferred":[
        "\u041a\u0440\u0443\u0442\u0438\u0446\u044b"
    ],
    "name:rus_x_variant":[
        "\u041a\u0440\u0443\u0442\u0438\u0446\u043a\u043e\u0435 \u043f\u043e\u0434\u0432\u043e\u0440\u044c\u0435"
    ],
    "wof:name":"Krutitsy",
    "wof:placetype":"locality"
},
  "geometry": {"coordinates":[40.36147,56.59716],"type":"Point"}
}