{
  "type": "Feature",
  "properties": {
    "gn:admin1_code":"21.0",
    "gn:asciiname":"Skorodumka",
    "gn:country_code":"RU",
    "gn:dem":143,
    "gn:feature_class":"P",
    "gn:feature_code":"PPL",
    "gn:name":"Skorodumka",
    "gn:population":0,
    "gn:timezone":"Europe/Moscow",
    "iso:country":"RU",
    "name:rus_x_preferred":[
        "\u0421\u043a\u043e\u0440\u043e\u0434\u0443\u043c\u043a\u0430"
    ],
    "name:und_x_variant":[
        "\u0421\u043a\u043e\u0440\u043e\u0434\u0443\u043c\u043a\u0430"
    ],
    "wof:name":"Skorodumka",
    "wof:placetype":"locality"
},
  "geometry": {"coordinates":[41.54231,57.44942],"type":"Point"}
}