{
  "type": "Feature",
  "properties": {
    "gn:admin1_code":"54",
    "gn:asciiname":"Kirpichnoye",
    "gn:country_code":"RU",
    "gn:dem":118,
    "gn:feature_class":"P",
    "gn:feature_code":"PPL",
    "gn:name":"Kirpichnoye",
    "gn:population":0,
    "gn:timezone":"Asia/Omsk",
    "iso:country":"RU",
    "name:eng_x_preferred":[
        "Kirpichnaya"
    ],
    "name:nor_x_preferred":[
        "Kirpitsjnoje"
    ],
    "name:rus_x_preferred":[
        "\u041a\u0438\u0440\u043f\u0438\u0447\u043d\u043e\u0435"
    ],
    "name:und_x_variant":[
        "Kirpichny",
        "Kirpichnyy",
        "Kirpichnoye"
    ],
    "wof:name":"Kirpichnoye",
    "wof:placetype":"locality"
},
  "geometry": {"coordinates":[75.88705,56.87149],"type":"Point"}
}