{
  "type": "Feature",
  "properties": {
    "gn:admin1_code":"80",
    "gn:asciiname":"Tatarskiy Toymobash",
    "gn:country_code":"RU",
    "gn:dem":115,
    "gn:feature_class":"P",
    "gn:feature_code":"PPL",
    "gn:name":"Tatarskiy Toymobash",
    "gn:population":0,
    "gn:timezone":"Europe/Samara",
    "iso:country":"RU",
    "name:und_x_variant":[
        "Toymobash Tatarskiy",
        "Tatarskiy Taymobash",
        "Tatarskiy Toymobash"
    ],
    "wof:name":"Tatarskiy Toymobash",
    "wof:placetype":"locality"
},
  "geometry": {"coordinates":[52.48209,56.21621],"type":"Point"}
}