{
  "type": "Feature",
  "properties": {
    "gn:admin1_code":"1",
    "gn:admin2_code":"11205695",
    "gn:asciiname":"Psekups",
    "gn:country_code":"RU",
    "gn:dem":37,
    "gn:feature_class":"P",
    "gn:feature_code":"PPL",
    "gn:name":"Psekups",
    "gn:population":0,
    "gn:timezone":"Europe/Moscow",
    "iso:country":"RU",
    "name:rus_x_preferred":[
        "\u041f\u0441\u0435\u043a\u0443\u043f\u0441"
    ],
    "name:und_x_variant":[
        "Volkorezov",
        "Pritsepilovka",
        "Psekups"
    ],
    "wof:name":"Psekups",
    "wof:placetype":"locality"
},
  "geometry": {"coordinates":[39.21432,44.83077],"type":"Point"}
}