{
  "type": "Feature",
  "properties": {
    "gn:admin1_code":"88.0",
    "gn:asciiname":"Kobylyayevo",
    "gn:country_code":"RU",
    "gn:dem":99,
    "gn:feature_class":"P",
    "gn:feature_code":"PPL",
    "gn:name":"Kobylyayevo",
    "gn:population":0,
    "gn:timezone":"Europe/Moscow",
    "iso:country":"RU",
    "name:und_x_variant":[
        "Kobylyaikha",
        "Kobylyayevo"
    ],
    "wof:name":"Kobylyayevo",
    "wof:placetype":"locality"
},
  "geometry": {"coordinates":[40.04307,57.64923],"type":"Point"}
}