{
  "type": "Feature",
  "properties": {
    "gn:admin1_code":"33",
    "gn:asciiname":"Parfenovshchina",
    "gn:country_code":"RU",
    "gn:dem":175,
    "gn:feature_class":"P",
    "gn:feature_code":"PPL",
    "gn:name":"Parfenovshchina",
    "gn:population":0,
    "gn:timezone":"Europe/Kirov",
    "iso:country":"RU",
    "name:rus_x_preferred":[
        "\u041f\u0430\u0440\u0444\u0435\u043d\u043e\u0432\u0449\u0438\u043d\u0430"
    ],
    "name:und_x_variant":[
        "\u041f\u0430\u0440\u0444\u0435\u043d\u043e\u0432\u0449\u0438\u043d\u0430"
    ],
    "wof:name":"Parfenovshchina",
    "wof:placetype":"locality"
},
  "geometry": {"coordinates":[49.97218,58.13446],"type":"Point"}
}