{
  "type": "Feature",
  "properties": {
    "gn:admin1_code":"75",
    "gn:asciiname":"Nizhne-Mokhovaya",
    "gn:country_code":"RU",
    "gn:dem":95,
    "gn:feature_class":"P",
    "gn:feature_code":"PPL",
    "gn:name":"Nizhne-Mokhovaya",
    "gn:population":0,
    "gn:timezone":"Asia/Tomsk",
    "iso:country":"RU",
    "name:rus_x_preferred":[
        "\u041d\u0438\u0436\u043d\u0435-\u041c\u043e\u0445\u043e\u0432\u0430\u044f"
    ],
    "wof:name":"Nizhne-Mokhovaya",
    "wof:placetype":"locality"
},
  "geometry": {"coordinates":[81.43333,57.31667],"type":"Point"}
}