{
  "type": "Feature",
  "properties": {
    "gn:admin1_code":"84",
    "gn:asciiname":"Novodubovskiy",
    "gn:country_code":"RU",
    "gn:dem":167,
    "gn:feature_class":"P",
    "gn:feature_code":"PPL",
    "gn:name":"Novodubovskiy",
    "gn:population":0,
    "gn:timezone":"Europe/Volgograd",
    "iso:country":"RU",
    "name:rus_x_preferred":[
        "\u041d\u043e\u0432\u043e\u0434\u0443\u0431\u043e\u0432\u0441\u043a\u0438\u0439"
    ],
    "name:und_x_variant":[
        "\u041d\u043e\u0432\u043e\u0434\u0443\u0431\u043e\u0432\u0441\u043a\u0438\u0439"
    ],
    "wof:name":"Novodubovskiy",
    "wof:placetype":"locality"
},
  "geometry": {"coordinates":[43.46456,50.95466],"type":"Point"}
}