{
  "type": "Feature",
  "properties": {
    "gn:admin1_code":"33",
    "gn:asciiname":"Morozovka",
    "gn:country_code":"RU",
    "gn:dem":148,
    "gn:feature_class":"P",
    "gn:feature_code":"PPL",
    "gn:name":"Morozovka",
    "gn:population":0,
    "gn:timezone":"Europe/Kirov",
    "iso:country":"RU",
    "name:che_x_preferred":[
        "\u041c\u043e\u0440\u043e\u0437\u043e\u0432\u043a\u0430"
    ],
    "name:rus_x_preferred":[
        "\u041c\u043e\u0440\u043e\u0437\u043e\u0432\u043a\u0430"
    ],
    "name:und_x_variant":[
        "Soplyaki",
        "Morozovka"
    ],
    "wof:name":"Morozovka",
    "wof:placetype":"locality"
},
  "geometry": {"coordinates":[48.9333,58.2239],"type":"Point"}
}