{
  "type": "Feature",
  "properties": {
    "gn:admin1_code":"77",
    "gn:asciiname":"Moshki",
    "gn:country_code":"RU",
    "gn:dem":153,
    "gn:feature_class":"P",
    "gn:feature_code":"PPL",
    "gn:name":"Moshki",
    "gn:population":0,
    "gn:timezone":"Europe/Moscow",
    "iso:country":"RU",
    "name:eng_x_preferred":[
        "Moshki"
    ],
    "name:nor_x_preferred":[
        "Mosjki"
    ],
    "name:rus_x_preferred":[
        "\u041c\u043e\u0448\u043a\u0438"
    ],
    "name:und_x_variant":[
        "\u041c\u043e\u0448\u043a\u0438",
        "Moshki"
    ],
    "wof:name":"Moshki",
    "wof:placetype":"locality"
},
  "geometry": {"coordinates":[35.04476,56.83071],"type":"Point"}
}