{
  "type": "Feature",
  "properties": {
    "gn:country":"RU",
    "gn:fcode":"PPL",
    "gn:pop":3376,
    "iso:country":"RU",
    "name:che_x_preferred":[
        "\u042f\u043a\u0441\u0430\u0442\u043e\u0432\u043e"
    ],
    "name:eng_x_preferred":[
        "Yaksatovo"
    ],
    "name:nld_x_preferred":[
        "Yaksatovo"
    ],
    "name:nor_x_preferred":[
        "Jaksatovo"
    ],
    "name:rus_x_preferred":[
        "\u042f\u043a\u0441\u0430\u0442\u043e\u0432\u043e"
    ],
    "name:tat_x_preferred":[
        "\u041c\u0430\u0439\u043b\u044b\u0433\u04af\u043b"
    ],
    "name:tgk_x_preferred":[
        "\u042f\u043a\u0441\u0430\u0442\u043e\u0432\u043e"
    ],
    "name:unk_x_variant":[
        "\u042f\u043a\u0441\u0430\u0442\u043e\u0432\u043e"
    ],
    "qs:name":"Yaksatovo",
    "qs:name_adm0":"Russia",
    "qs:name_adm1":"Astrakhan Oblast",
    "qs:photos_9r":0,
    "qs:photos_sr":0,
    "qs:placetype":"Town",
    "qs:pop_sr":"4",
    "wof:name":"Yaksatovo",
    "wof:placetype":"locality",
    "wof:population":3376
},
  "geometry": {"coordinates":[48.01514,46.24342],"type":"Point"}
}