{
  "type": "Feature",
  "properties": {
    "gn:country":"RU",
    "gn:fcode":"PPL",
    "gn:population":3376,
    "iso:country":"RU",
    "name:arz_x_preferred":[
        "\u064a\u0627\u0643\u0633\u0627\u062a\u0648\u06a4\u0648"
    ],
    "name:azb_x_preferred":[
        "\u06cc\u0627\u06a9\u0633\u0627\u062a\u0648\u0648\u0648"
    ],
    "name:ceb_x_preferred":[
        "Yaksatovo"
    ],
    "name:che_x_preferred":[
        "\u042f\u043a\u0441\u0430\u0442\u043e\u0432\u043e"
    ],
    "name:crh_x_preferred":[
        "Yaksatovo"
    ],
    "name:eng_x_preferred":[
        "Yaksatovo"
    ],
    "name:fas_x_preferred":[
        "\u06cc\u0627\u06a9\u0633\u0627\u062a\u0648\u0648"
    ],
    "name:nan_x_preferred":[
        "Yaksatovo"
    ],
    "name:nld_x_preferred":[
        "Yaksatovo"
    ],
    "name:nno_x_preferred":[
        "Jaksatovo"
    ],
    "name:nob_x_preferred":[
        "Jaksatovo"
    ],
    "name:nor_x_preferred":[
        "Jaksatovo"
    ],
    "name:rus_x_preferred":[
        "\u042f\u043a\u0441\u0430\u0442\u043e\u0432\u043e"
    ],
    "name:sqi_x_preferred":[
        "Jaksatovo"
    ],
    "name:tat_x_preferred":[
        "\u041c\u0430\u0439\u043b\u044b\u0433\u04af\u043b"
    ],
    "name:tgk_x_preferred":[
        "\u042f\u043a\u0441\u0430\u0442\u043e\u0432\u043e"
    ],
    "name:ukr_x_preferred":[
        "\u042f\u043a\u0441\u0430\u0442\u043e\u0432\u043e"
    ],
    "qs:name":"Yaksatovo",
    "qs:name_adm0":"Russia",
    "qs:name_adm1":"Astrakhan Oblast",
    "qs:photos_9r":0,
    "qs:photos_sr":0,
    "qs:placetype":"Town",
    "qs:pop_sr":"4",
    "wof:name":"Yaksatovo",
    "wof:placetype":"locality",
    "wof:population":3376
},
  "geometry": {"coordinates":[48.01514,46.24342],"type":"Point"}
}