{
  "type": "Feature",
  "properties": {
    "gn:admin1_code":"85.0",
    "gn:asciiname":"Rameshki",
    "gn:country_code":"RU",
    "gn:dem":181,
    "gn:feature_class":"P",
    "gn:feature_code":"PPL",
    "gn:name":"Rameshki",
    "gn:population":0,
    "gn:timezone":"Europe/Moscow",
    "iso:country":"RU",
    "name:rus_x_preferred":[
        "\u0420\u0430\u043c\u0435\u0448\u043a\u0438"
    ],
    "name:und_x_variant":[
        "\u0420\u0430\u043c\u0435\u0448\u043a\u0438"
    ],
    "wof:name":"Rameshki",
    "wof:placetype":"locality"
},
  "geometry": {"coordinates":[40.51066,58.84783],"type":"Point"}
}