{
  "type": "Feature",
  "properties": {
    "gn:admin1_code":"51",
    "gn:asciiname":"Urubkovo",
    "gn:country_code":"RU",
    "gn:dem":104,
    "gn:feature_class":"P",
    "gn:feature_code":"PPL",
    "gn:name":"Urubkovo",
    "gn:population":0,
    "gn:timezone":"Europe/Moscow",
    "iso:country":"RU",
    "name:eng_x_preferred":[
        "Urubkovo"
    ],
    "name:nor_x_preferred":[
        "Urubkovo"
    ],
    "name:rus_x_preferred":[
        "\u0423\u0440\u0443\u0431\u043a\u043e\u0432\u043e"
    ],
    "wof:name":"Urubkovo",
    "wof:placetype":"locality"
},
  "geometry": {"coordinates":[45.45364,56.7421],"type":"Point"}
}