{
  "type": "Feature",
  "properties": {
    "gn:country":"RU",
    "gn:fcode":"PPL",
    "gn:population":0,
    "iso:country":"RU",
    "name:nor_x_preferred":[
        "Grigorovka"
    ],
    "name:rus_x_preferred":[
        "\u0413\u0440\u0438\u0433\u043e\u0440\u043e\u0432\u043a\u0430"
    ],
    "qs:name":"Grigorovka",
    "qs:name_adm0":"Russia",
    "qs:name_adm1":"Kaluga Oblast",
    "qs:photos_9r":0,
    "qs:photos_sr":0,
    "qs:placetype":"Town",
    "qs:pop_sr":"0",
    "wof:name":"Grigorovka",
    "wof:placetype":"locality",
    "wof:population":0
},
  "geometry": {"coordinates":[36.33733,54.63306],"type":"Point"}
}