{
  "type": "Feature",
  "properties": {
    "gn:admin1_code":"80",
    "gn:asciiname":"Oktyabr'skaya",
    "gn:country_code":"RU",
    "gn:dem":104,
    "gn:feature_class":"P",
    "gn:feature_code":"PPL",
    "gn:name":"Oktyabr\u2019skaya",
    "gn:population":0,
    "gn:timezone":"Europe/Samara",
    "iso:country":"RU",
    "name:rus_x_preferred":[
        "\u041e\u043a\u0442\u044f\u0431\u0440\u044c\u0441\u043a\u0430\u044f"
    ],
    "name:und_x_variant":[
        "Oktyabr\u2019skaya",
        "\u041e\u043a\u0442\u044f\u0431\u0440\u044c\u0441\u043a\u0430\u044f"
    ],
    "wof:name":"Oktyabr'skaya",
    "wof:placetype":"locality"
},
  "geometry": {"coordinates":[54.2618,56.3926],"type":"Point"}
}