{
  "type": "Feature",
  "properties": {
    "gn:admin1_code":"90",
    "gn:asciiname":"Ramen'ye",
    "gn:country_code":"RU",
    "gn:dem":249,
    "gn:feature_class":"P",
    "gn:feature_code":"PPL",
    "gn:name":"Ramen\u2019ye",
    "gn:population":0,
    "gn:timezone":"Asia/Yekaterinburg",
    "iso:country":"RU",
    "name:rus_x_preferred":[
        "\u0420\u0430\u043c\u0435\u043d\u044c\u0435"
    ],
    "name:und_x_variant":[
        "Ramen\u2019ye",
        "\u0420\u0430\u043c\u0435\u043d\u044c\u0435"
    ],
    "wof:name":"Ramen'ye",
    "wof:placetype":"locality"
},
  "geometry": {"coordinates":[53.91223000000001,59.05785],"type":"Point"}
}