{
  "type": "Feature",
  "properties": {
    "gn:admin1_code":"72",
    "gn:asciiname":"Svishchevka",
    "gn:country_code":"RU",
    "gn:dem":160,
    "gn:feature_class":"P",
    "gn:feature_code":"PPL",
    "gn:name":"Svishch\u00ebvka",
    "gn:population":0,
    "gn:timezone":"Europe/Moscow",
    "iso:country":"RU",
    "name:und_x_variant":[
        "Svishevka",
        "Svishch\u00ebvka"
    ],
    "wof:name":"Svishchevka",
    "wof:placetype":"locality"
},
  "geometry": {"coordinates":[42.45912,52.59001],"type":"Point"}
}