{
  "type": "Feature",
  "properties": {
    "gn:admin1_code":"80.0",
    "gn:asciiname":"Mukaban",
    "gn:country_code":"RU",
    "gn:dem":215,
    "gn:feature_class":"P",
    "gn:feature_code":"PPL",
    "gn:name":"Mukaban",
    "gn:population":0,
    "gn:timezone":"Europe/Samara",
    "iso:country":"RU",
    "name:rus_x_preferred":[
        "\u041c\u0443\u043a\u0430\u0431\u0430\u043d"
    ],
    "wof:name":"Mukaban",
    "wof:placetype":"locality"
},
  "geometry": {"coordinates":[54.08302,57.39149000000001],"type":"Point"}
}