{
  "type": "Feature",
  "properties": {
    "gn:admin1_code":"51.0",
    "gn:asciiname":"Lyapunikha",
    "gn:country_code":"RU",
    "gn:dem":74,
    "gn:feature_class":"P",
    "gn:feature_code":"PPL",
    "gn:name":"Lyapunikha",
    "gn:population":0,
    "gn:timezone":"Europe/Moscow",
    "iso:country":"RU",
    "name:nor_x_preferred":[
        "Ljapunikha"
    ],
    "name:rus_x_preferred":[
        "\u041b\u044f\u043f\u0443\u043d\u0438\u0445\u0430"
    ],
    "wof:name":"Lyapunikha",
    "wof:placetype":"locality"
},
  "geometry": {"coordinates":[43.45948,56.58894],"type":"Point"}
}