{
  "type": "Feature",
  "properties": {
    "gn:admin1_code":"10.0",
    "gn:asciiname":"Aksamentovo",
    "gn:country_code":"RU",
    "gn:dem":151,
    "gn:feature_class":"P",
    "gn:feature_code":"PPL",
    "gn:name":"Aksamentovo",
    "gn:population":0,
    "gn:timezone":"Europe/Moscow",
    "iso:country":"RU",
    "name:nor_x_preferred":[
        "Aksamitovo"
    ],
    "name:rus_x_preferred":[
        "\u0410\u043a\u0441\u0430\u043c\u0435\u043d\u0442\u043e\u0432\u043e"
    ],
    "name:und_x_variant":[
        "\u0410\u043a\u0441\u0430\u043c\u0435\u043d\u0442\u043e\u0432\u043e",
        "Aksamitovo"
    ],
    "wof:name":"Aksamentovo",
    "wof:placetype":"locality"
},
  "geometry": {"coordinates":[33.29061,52.87011999999999],"type":"Point"}
}