{
  "type": "Feature",
  "properties": {
    "gn:admin1_code":"46",
    "gn:asciiname":"Prisurskiy",
    "gn:country_code":"RU",
    "gn:dem":105,
    "gn:feature_class":"P",
    "gn:feature_code":"PPL",
    "gn:name":"Prisurskiy",
    "gn:population":0,
    "gn:timezone":"Europe/Moscow",
    "iso:country":"RU",
    "name:rus_x_preferred":[
        "\u041f\u0440\u0438\u0441\u0443\u0440\u0441\u043a\u0438\u0439"
    ],
    "name:und_x_variant":[
        "\u041f\u0440\u0438\u0441\u0443\u0440\u0441\u043a\u0438\u0439"
    ],
    "wof:name":"Prisurskiy",
    "wof:placetype":"locality"
},
  "geometry": {"coordinates":[45.9522,54.1493],"type":"Point"}
}