{
  "type": "Feature",
  "properties": {
    "gn:admin1_code":"47",
    "gn:asciiname":"Kolshino",
    "gn:country_code":"RU",
    "gn:dem":242,
    "gn:feature_class":"P",
    "gn:feature_code":"PPL",
    "gn:name":"Kolshino",
    "gn:population":0,
    "gn:timezone":"Europe/Moscow",
    "iso:country":"RU",
    "name:rus_x_preferred":[
        "\u041a\u043e\u043b\u0448\u0438\u043d\u043e"
    ],
    "name:und_x_variant":[
        "\u041a\u043e\u043b\u0448\u0438\u043d\u043e"
    ],
    "wof:name":"Kolshino",
    "wof:placetype":"locality"
},
  "geometry": {"coordinates":[36.32611,55.96581],"type":"Point"}
}