{
  "type": "Feature",
  "properties": {
    "gn:admin1_code":"83.0",
    "gn:asciiname":"Barkino",
    "gn:country_code":"RU",
    "gn:dem":145,
    "gn:feature_class":"P",
    "gn:feature_code":"PPL",
    "gn:name":"Barkino",
    "gn:population":0,
    "gn:timezone":"Europe/Moscow",
    "iso:country":"RU",
    "name:nor_x_preferred":[
        "Barkino"
    ],
    "name:rus_x_preferred":[
        "\u0411\u0430\u0440\u043a\u0438\u043d\u043e"
    ],
    "wof:name":"Barkino",
    "wof:placetype":"locality"
},
  "geometry": {"coordinates":[41.2617,55.8653],"type":"Point"}
}