{
  "type": "Feature",
  "properties": {
    "gn:admin1_code":"28",
    "gn:asciiname":"Nizhniye Zady",
    "gn:country_code":"RU",
    "gn:dem":109,
    "gn:feature_class":"P",
    "gn:feature_code":"PPL",
    "gn:name":"Nizhniye Zady",
    "gn:population":0,
    "gn:timezone":"Europe/Moscow",
    "iso:country":"RU",
    "name:rus_x_preferred":[
        "\u041d\u0438\u0436\u043d\u0438\u0435 \u0417\u0430\u0434\u044b"
    ],
    "name:und_x_variant":[
        "\u041d\u0438\u0436\u043d\u0438\u0435 \u0417\u0430\u0434\u044b"
    ],
    "wof:name":"Nizhniye Zady",
    "wof:placetype":"locality"
},
  "geometry": {"coordinates":[34.36667,62.16667],"type":"Point"}
}