{
  "type": "Feature",
  "properties": {
    "gn:admin1_code":"71",
    "gn:asciiname":"Georgiyevskoye",
    "gn:country_code":"RU",
    "gn:dem":78,
    "gn:feature_class":"P",
    "gn:feature_code":"PPL",
    "gn:name":"Georgiyevskoye",
    "gn:population":0,
    "gn:timezone":"Asia/Yekaterinburg",
    "iso:country":"RU",
    "name:rus_x_preferred":[
        "\u0413\u0435\u043e\u0440\u0433\u0438\u0435\u0432\u0441\u043a\u043e\u0435"
    ],
    "name:und_x_variant":[
        "Karckoye",
        "Georgiyevskiy",
        "Georgiyevskoye"
    ],
    "wof:name":"Georgiyevskoye",
    "wof:placetype":"locality"
},
  "geometry": {"coordinates":[62.57186,59.52392],"type":"Point"}
}