{
  "type": "Feature",
  "properties": {
    "gn:admin1_code":"47",
    "gn:asciiname":"Solnyshkovo",
    "gn:country_code":"RU",
    "gn:dem":153,
    "gn:feature_class":"P",
    "gn:feature_code":"PPL",
    "gn:name":"Solnyshkovo",
    "gn:population":0,
    "gn:timezone":"Europe/Moscow",
    "iso:country":"RU",
    "name:rus_x_preferred":[
        "\u0421\u043e\u043b\u043d\u044b\u0448\u043a\u043e\u0432\u043e"
    ],
    "name:und_x_variant":[
        "\u0421\u043e\u043b\u043d\u044b\u0448\u043a\u043e\u0432\u043e"
    ],
    "wof:name":"Solnyshkovo",
    "wof:placetype":"locality"
},
  "geometry": {"coordinates":[37.48562,55.11925],"type":"Point"}
}