{
  "type": "Feature",
  "properties": {
    "gn:admin1_code":"15",
    "gn:asciiname":"Vilka",
    "gn:cc2":"RU",
    "gn:country_code":"RU",
    "gn:dem":1,
    "gn:feature_class":"P",
    "gn:feature_code":"PPL",
    "gn:name":"Vilka",
    "gn:population":0,
    "gn:timezone":"Asia/Anadyr",
    "iso:country":"RU",
    "name:und_x_variant":[
        "Vllka",
        "Vilka"
    ],
    "wof:name":"Vilka",
    "wof:placetype":"locality"
},
  "geometry": {"coordinates":[173.73333,65.28333000000001],"type":"Point"}
}