{
  "type": "Feature",
  "properties": {
    "gn:admin1_code":"56",
    "gn:asciiname":"Novosergeyevka",
    "gn:country_code":"RU",
    "gn:dem":206,
    "gn:feature_class":"P",
    "gn:feature_code":"PPL",
    "gn:name":"Novosergeyevka",
    "gn:population":0,
    "gn:timezone":"Europe/Moscow",
    "iso:country":"RU",
    "name:rus_x_preferred":[
        "\u041d\u043e\u0432\u043e\u0441\u0435\u0440\u0433\u0435\u0435\u0432\u043a\u0430"
    ],
    "wof:name":"Novosergeyevka",
    "wof:placetype":"locality"
},
  "geometry": {"coordinates":[37.51823,52.1138],"type":"Point"}
}