{
  "type": "Feature",
  "properties": {
    "gn:admin1_code":"69",
    "gn:asciiname":"Bol'shoye Chermesnoye",
    "gn:country_code":"RU",
    "gn:dem":198,
    "gn:feature_class":"P",
    "gn:feature_code":"PPL",
    "gn:name":"Bol\u2019shoye Chermesnoye",
    "gn:population":0,
    "gn:timezone":"Europe/Moscow",
    "iso:country":"RU",
    "name:rus_x_preferred":[
        "\u0411\u043e\u043b\u044c\u0448\u043e\u0435 \u0427\u0435\u0440\u043c\u0435\u0441\u043d\u043e\u0435"
    ],
    "name:und_x_variant":[
        "Bol\u2019shoye Chermesnoye",
        "Bol\u2019shoye Nermesnoye"
    ],
    "wof:name":"Bol'shoye Chermesnoye",
    "wof:placetype":"locality"
},
  "geometry": {"coordinates":[34.91285999999999,55.07957],"type":"Point"}
}