{
  "type": "Feature",
  "properties": {
    "gn:admin1_code":"30",
    "gn:asciiname":"Dyappe",
    "gn:cc2":"RU",
    "gn:country_code":"RU",
    "gn:dem":118,
    "gn:feature_class":"P",
    "gn:feature_code":"PPL",
    "gn:name":"Dyappe",
    "gn:population":0,
    "gn:timezone":"Asia/Vladivostok",
    "iso:country":"RU",
    "name:rus_x_preferred":[
        "\u0414\u044f\u043f\u043f\u0435"
    ],
    "name:und_x_variant":[
        "Dyappi",
        "Dyappe"
    ],
    "wof:name":"Dyappe",
    "wof:placetype":"locality"
},
  "geometry": {"coordinates":[139.25,51.75],"type":"Point"}
}