{
  "type": "Feature",
  "properties": {
    "gn:admin1_code":"83",
    "gn:asciiname":"Peski",
    "gn:country_code":"RU",
    "gn:dem":123,
    "gn:feature_class":"P",
    "gn:feature_code":"PPL",
    "gn:name":"Peski",
    "gn:population":0,
    "gn:timezone":"Europe/Moscow",
    "iso:country":"RU",
    "name:nor_x_preferred":[
        "Peski"
    ],
    "name:rus_x_preferred":[
        "\u041f\u0435\u0441\u043a\u0438"
    ],
    "wof:name":"Peski",
    "wof:placetype":"locality"
},
  "geometry": {"coordinates":[42.25321,56.1926],"type":"Point"}
}