{
  "type": "Feature",
  "properties": {
    "gn:admin1_code":"33.0",
    "gn:asciiname":"Pankraty",
    "gn:country_code":"RU",
    "gn:dem":131,
    "gn:feature_class":"P",
    "gn:feature_code":"PPL",
    "gn:name":"Pankraty",
    "gn:population":0,
    "gn:timezone":"Europe/Kirov",
    "iso:country":"RU",
    "name:rus_x_preferred":[
        "\u041f\u0430\u043d\u043a\u0440\u0430\u0442\u044b"
    ],
    "wof:name":"Pankraty",
    "wof:placetype":"locality"
},
  "geometry": {"coordinates":[48.50951,57.73072],"type":"Point"}
}