{
  "type": "Feature",
  "properties": {
    "gn:admin1_code":"90",
    "gn:asciiname":"Polovinka",
    "gn:country_code":"RU",
    "gn:dem":168,
    "gn:feature_class":"P",
    "gn:feature_code":"PPL",
    "gn:name":"Polovinka",
    "gn:population":0,
    "gn:timezone":"Asia/Yekaterinburg",
    "iso:country":"RU",
    "name:rus_x_preferred":[
        "\u041f\u043e\u043b\u043e\u0432\u0438\u043d\u043a\u0430"
    ],
    "name:und_x_variant":[
        "Polovinnaya",
        "Polovinka"
    ],
    "wof:name":"Polovinka",
    "wof:placetype":"locality"
},
  "geometry": {"coordinates":[55.272,57.8952],"type":"Point"}
}