{
  "type": "Feature",
  "properties": {
    "gn:admin1_code":"71",
    "gn:asciiname":"Shabalino",
    "gn:country_code":"RU",
    "gn:dem":97,
    "gn:feature_class":"P",
    "gn:feature_code":"PPL",
    "gn:name":"Shabalino",
    "gn:population":0,
    "gn:timezone":"Asia/Yekaterinburg",
    "iso:country":"RU",
    "name:rus_x_preferred":[
        "\u0428\u0430\u0431\u0430\u043b\u0438\u043d\u043e"
    ],
    "wof:name":"Shabalino",
    "wof:placetype":"locality"
},
  "geometry": {"coordinates":[65.5282,57.78644],"type":"Point"}
}