{
  "type": "Feature",
  "properties": {
    "gn:admin1_code":"13",
    "gn:asciiname":"Filimonova",
    "gn:cc2":"RU",
    "gn:country_code":"RU",
    "gn:dem":214,
    "gn:feature_class":"P",
    "gn:feature_code":"PPL",
    "gn:name":"Filimonova",
    "gn:population":0,
    "gn:timezone":"Asia/Yekaterinburg",
    "iso:country":"RU",
    "name:rus_x_preferred":[
        "\u0424\u0438\u043b\u0438\u043c\u043e\u043d\u043e\u0432\u0430"
    ],
    "name:und_x_variant":[
        "Filimonovka",
        "Filimonova"
    ],
    "wof:name":"Filimonova",
    "wof:placetype":"locality"
},
  "geometry": {"coordinates":[61.78333000000001,54.28333000000001],"type":"Point"}
}