{
  "type": "Feature",
  "properties": {
    "gn:admin1_code":"72",
    "gn:asciiname":"Tafino",
    "gn:country_code":"RU",
    "gn:dem":122,
    "gn:feature_class":"P",
    "gn:feature_code":"PPL",
    "gn:name":"Tafino",
    "gn:population":0,
    "gn:timezone":"Europe/Moscow",
    "iso:country":"RU",
    "name:rus_x_preferred":[
        "\u0422\u0430\u0444\u0438\u043d\u043e"
    ],
    "wof:name":"Tafino",
    "wof:placetype":"locality"
},
  "geometry": {"coordinates":[40.3559,52.5356],"type":"Point"}
}