{
  "type": "Feature",
  "properties": {
    "gn:admin1_code":"10",
    "gn:asciiname":"Klinskoye",
    "gn:country_code":"RU",
    "gn:dem":188,
    "gn:feature_class":"P",
    "gn:feature_code":"PPL",
    "gn:name":"Klinskoye",
    "gn:population":0,
    "gn:timezone":"Europe/Moscow",
    "iso:country":"RU",
    "name:rus_x_preferred":[
        "\u041a\u043b\u0438\u043d\u0441\u043a\u043e\u0435"
    ],
    "wof:name":"Klinskoye",
    "wof:placetype":"locality"
},
  "geometry": {"coordinates":[34.62298,52.70338],"type":"Point"}
}