{
  "type": "Feature",
  "properties": {
    "gn:admin1_code":"6.0",
    "gn:asciiname":"Poperechka",
    "gn:country_code":"RU",
    "gn:dem":73,
    "gn:feature_class":"P",
    "gn:feature_code":"PPL",
    "gn:name":"Poperechka",
    "gn:population":0,
    "gn:timezone":"Europe/Moscow",
    "iso:country":"RU",
    "name:rus_x_preferred":[
        "\u041f\u043e\u043f\u0435\u0440\u0435\u0447\u043a\u0430"
    ],
    "wof:name":"Poperechka",
    "wof:placetype":"locality"
},
  "geometry": {"coordinates":[44.6136,62.0206],"type":"Point"}
}