{
  "type": "Feature",
  "properties": {
    "gn:admin1_code":"6",
    "gn:asciiname":"Semushinskaya",
    "gn:country_code":"RU",
    "gn:dem":142,
    "gn:feature_class":"P",
    "gn:feature_code":"PPL",
    "gn:name":"Semushinskaya",
    "gn:population":0,
    "gn:timezone":"Europe/Moscow",
    "iso:country":"RU",
    "name:rus_x_preferred":[
        "\u0421\u0435\u043c\u0443\u0448\u0438\u043d\u0441\u043a\u0430\u044f"
    ],
    "name:und_x_variant":[
        "\u0421\u0435\u043c\u0443\u0448\u0438\u043d\u0441\u043a\u0430\u044f"
    ],
    "wof:name":"Semushinskaya",
    "wof:placetype":"locality"
},
  "geometry": {"coordinates":[43.25646,60.91078],"type":"Point"}
}