{
  "type": "Feature",
  "properties": {
    "gn:admin1_code":"63",
    "gn:asciiname":"Bagadya",
    "gn:country_code":"RU",
    "gn:dem":215,
    "gn:feature_class":"P",
    "gn:feature_code":"PPL",
    "gn:name":"Bagadya",
    "gn:population":0,
    "gn:timezone":"Asia/Yakutsk",
    "iso:country":"RU",
    "name:eng_x_preferred":[
        "Bagadya"
    ],
    "name:nor_x_preferred":[
        "Bagadja"
    ],
    "name:rus_x_preferred":[
        "\u0411\u0430\u0433\u0430\u0434\u044f"
    ],
    "name:und_x_variant":[
        "Surpuluk",
        "Bagadzha",
        "Bagad\u2019a",
        "\u0411\u0430\u0433\u0430\u0434\u044f",
        "Bagadya"
    ],
    "wof:name":"Bagadya",
    "wof:placetype":"locality"
},
  "geometry": {"coordinates":[119.71028,64.3325],"type":"Point"}
}