{
  "type": "Feature",
  "properties": {
    "gn:admin1_code":"33.0",
    "gn:asciiname":"Nizhniye Pololyata",
    "gn:country_code":"RU",
    "gn:dem":130,
    "gn:feature_class":"P",
    "gn:feature_code":"PPL",
    "gn:name":"Nizhniye Pololyata",
    "gn:population":0,
    "gn:timezone":"Europe/Kirov",
    "iso:country":"RU",
    "name:rus_x_preferred":[
        "\u041d\u0438\u0436\u043d\u0438\u0435 \u041f\u043e\u043b\u043e\u043b\u044f\u0442\u0430"
    ],
    "name:und_x_variant":[
        "\u041d\u0438\u0436\u043d\u0438\u0435 \u041f\u043e\u043b\u043e\u043b\u044f\u0442\u0430"
    ],
    "wof:name":"Nizhniye Pololyata",
    "wof:placetype":"locality"
},
  "geometry": {"coordinates":[48.04278,58.45972],"type":"Point"}
}