{
  "type": "Feature",
  "properties": {
    "gn:admin1_code":"45.0",
    "gn:asciiname":"Russkiy Yoshkarener",
    "gn:country_code":"RU",
    "gn:dem":191,
    "gn:feature_class":"P",
    "gn:feature_code":"PPL",
    "gn:name":"Russkiy Yoshkarener",
    "gn:population":0,
    "gn:timezone":"Europe/Moscow",
    "iso:country":"RU",
    "name:rus_x_preferred":[
        "\u0420\u0443\u0441\u0441\u043a\u0438\u0439 \u0419\u043e\u0448\u043a\u0430\u0440\u0435\u043d\u0435\u0440"
    ],
    "wof:name":"Russkiy Yoshkarener",
    "wof:placetype":"locality"
},
  "geometry": {"coordinates":[48.85722,56.75944000000001],"type":"Point"}
}