{
  "type": "Feature",
  "properties": {
    "gn:admin1_code":"80.0",
    "gn:asciiname":"Garevskaya",
    "gn:country_code":"RU",
    "gn:dem":256,
    "gn:feature_class":"P",
    "gn:feature_code":"PPL",
    "gn:name":"Garevskaya",
    "gn:population":0,
    "gn:timezone":"Europe/Samara",
    "iso:country":"RU",
    "name:rus_x_preferred":[
        "\u0413\u0430\u0440\u0435\u0432\u0441\u043a\u0430\u044f"
    ],
    "wof:name":"Garevskaya",
    "wof:placetype":"locality"
},
  "geometry": {"coordinates":[53.5199,58.4168],"type":"Point"}
}