{
  "type": "Feature",
  "properties": {
    "gn:admin1_code":"70",
    "gn:asciiname":"Vysokopol'ye",
    "gn:country_code":"RU",
    "gn:dem":457,
    "gn:feature_class":"P",
    "gn:feature_code":"PPL",
    "gn:name":"Vysokopol'ye",
    "gn:population":0,
    "gn:timezone":"Europe/Moscow",
    "iso:country":"RU",
    "wof:name":"Vysokopol'ye",
    "wof:placetype":"locality"
},
  "geometry": {"coordinates":[41.74306,44.52889],"type":"Point"}
}