{
  "type": "Feature",
  "properties": {
    "gn:admin1_code":"67.0",
    "gn:asciiname":"Malaya Lapukhovka",
    "gn:country_code":"RU",
    "gn:dem":81,
    "gn:feature_class":"P",
    "gn:feature_code":"PPL",
    "gn:name":"Malaya Lapukhovka",
    "gn:population":0,
    "gn:timezone":"Europe/Saratov",
    "iso:country":"RU",
    "name:rus_x_preferred":[
        "\u041c\u0430\u043b\u0430\u044f \u041b\u0430\u043f\u0443\u0445\u043e\u0432\u043a\u0430"
    ],
    "name:und_x_variant":[
        "\u041c\u0430\u043b\u0430\u044f \u041b\u0430\u043f\u0443\u0445\u043e\u0432\u043a\u0430"
    ],
    "wof:name":"Malaya Lapukhovka",
    "wof:placetype":"locality"
},
  "geometry": {"coordinates":[46.96187000000001,52.4062],"type":"Point"}
}