{
  "type": "Feature",
  "properties": {
    "gn:admin1_code":"83",
    "gn:asciiname":"Snegirevo",
    "gn:country_code":"RU",
    "gn:dem":160,
    "gn:feature_class":"P",
    "gn:feature_code":"PPL",
    "gn:name":"Snegir\u00ebvo",
    "gn:population":0,
    "gn:timezone":"Europe/Moscow",
    "iso:country":"RU",
    "name:rus_x_preferred":[
        "\u0421\u043d\u0435\u0433\u0438\u0440\u0451\u0432\u043e"
    ],
    "name:und_x_variant":[
        "Snegir\u00ebvo"
    ],
    "wof:name":"Snegirevo",
    "wof:placetype":"locality"
},
  "geometry": {"coordinates":[39.7165,56.24256],"type":"Point"}
}