{
  "type": "Feature",
  "properties": {
    "gn:admin1_code":"60",
    "gn:asciiname":"Lobok",
    "gn:country_code":"RU",
    "gn:dem":169,
    "gn:feature_class":"P",
    "gn:feature_code":"PPL",
    "gn:name":"Lobok",
    "gn:population":0,
    "gn:timezone":"Europe/Moscow",
    "iso:country":"RU",
    "name:rus_x_preferred":[
        "\u041b\u043e\u0431\u043e\u043a"
    ],
    "name:und_x_variant":[
        "\u041b\u043e\u0431\u043e\u043a"
    ],
    "wof:name":"Lobok",
    "wof:placetype":"locality"
},
  "geometry": {"coordinates":[29.96667,55.86666999999999],"type":"Point"}
}