{
  "type": "Feature",
  "properties": {
    "gn:admin1_code":"77",
    "gn:asciiname":"Golenkovo",
    "gn:country_code":"RU",
    "gn:dem":209,
    "gn:feature_class":"P",
    "gn:feature_code":"PPL",
    "gn:name":"Golenkovo",
    "gn:population":0,
    "gn:timezone":"Europe/Moscow",
    "iso:country":"RU",
    "name:rus_x_preferred":[
        "\u0413\u043e\u043b\u0435\u043d\u043a\u043e\u0432\u043e"
    ],
    "wof:name":"Golenkovo",
    "wof:placetype":"locality"
},
  "geometry": {"coordinates":[33.49056,56.96694],"type":"Point"}
}