{
  "type": "Feature",
  "properties": {
    "gn:admin1_code":"16",
    "gn:asciiname":"Marks",
    "gn:country_code":"RU",
    "gn:dem":221,
    "gn:feature_class":"P",
    "gn:feature_code":"PPL",
    "gn:name":"Marks",
    "gn:population":0,
    "gn:timezone":"Europe/Moscow",
    "iso:country":"RU",
    "name:aze_x_preferred":[
        "Marks"
    ],
    "name:ceb_x_preferred":[
        "Marks"
    ],
    "name:ces_x_preferred":[
        "Marks"
    ],
    "name:deu_x_preferred":[
        "Marks"
    ],
    "name:fra_x_preferred":[
        "Marks"
    ],
    "name:jpn_x_preferred":[
        "\u30de\u30fc\u30af\u30b9"
    ],
    "name:kor_x_preferred":[
        "\ub9c8\ud06c\uc2a4"
    ],
    "name:nld_x_preferred":[
        "Marks"
    ],
    "name:pol_x_preferred":[
        "Marks"
    ],
    "name:por_x_preferred":[
        "Marks"
    ],
    "name:rus_x_preferred":[
        "\u041c\u0430\u0440\u043a\u0441"
    ],
    "name:swe_x_preferred":[
        "Marks"
    ],
    "name:und_x_variant":[
        "\u041c\u0430\u0440\u043a\u0441"
    ],
    "wof:name":"Marks",
    "wof:placetype":"locality"
},
  "geometry": {"coordinates":[46.98333,55.26667],"type":"Point"}
}