{
  "type": "Feature",
  "properties": {
    "gn:admin1_code":"16",
    "gn:asciiname":"Marks",
    "gn:country_code":"RU",
    "gn:dem":221,
    "gn:feature_class":"P",
    "gn:feature_code":"PPL",
    "gn:name":"Marks",
    "gn:population":0,
    "gn:timezone":"Europe/Moscow",
    "iso:country":"RU",
    "name:rus_x_preferred":[
        "\u041c\u0430\u0440\u043a\u0441"
    ],
    "name:und_x_variant":[
        "\u041c\u0430\u0440\u043a\u0441"
    ],
    "wof:name":"Marks",
    "wof:placetype":"locality"
},
  "geometry": {"coordinates":[46.98333,55.26667],"type":"Point"}
}