{
  "type": "Feature",
  "properties": {
    "gn:admin1_code":"11",
    "gn:asciiname":"Verkhniy Zhirim",
    "gn:country_code":"RU",
    "gn:dem":704,
    "gn:feature_class":"P",
    "gn:feature_code":"PPL",
    "gn:name":"Verkhniy Zhirim",
    "gn:population":0,
    "gn:timezone":"Asia/Irkutsk",
    "iso:country":"RU",
    "name:eng_x_preferred":[
        "Verkhniy Zhirim"
    ],
    "name:nor_x_preferred":[
        "Verkh.Zjirim"
    ],
    "name:rus_x_preferred":[
        "\u0412\u0435\u0440\u0445.\u0416\u0438\u0440\u0438\u043c"
    ],
    "name:und_x_variant":[
        "Sharikha",
        "Bol\u2019shaya Sharika"
    ],
    "wof:name":"Verkhniy Zhirim",
    "wof:placetype":"locality"
},
  "geometry": {"coordinates":[107.22055,51.32639],"type":"Point"}
}