{
  "type": "Feature",
  "properties": {
    "gn:admin1_code":"85",
    "gn:asciiname":"Obrochnaya",
    "gn:country_code":"RU",
    "gn:dem":119,
    "gn:feature_class":"P",
    "gn:feature_code":"PPL",
    "gn:name":"Obrochnaya",
    "gn:population":0,
    "gn:timezone":"Europe/Moscow",
    "iso:country":"RU",
    "name:rus_x_preferred":[
        "\u041e\u0431\u0440\u043e\u0447\u043d\u0430\u044f"
    ],
    "name:und_x_variant":[
        "\u041e\u0431\u0440\u043e\u0447\u043d\u0430\u044f"
    ],
    "wof:name":"Obrochnaya",
    "wof:placetype":"locality"
},
  "geometry": {"coordinates":[46.2753,60.5095],"type":"Point"}
}