{
  "type": "Feature",
  "properties": {
    "gn:admin1_code":"13",
    "gn:asciiname":"Sanatornyy",
    "gn:country_code":"RU",
    "gn:dem":220,
    "gn:feature_class":"P",
    "gn:feature_code":"PPL",
    "gn:name":"Sanatornyy",
    "gn:population":0,
    "gn:timezone":"Asia/Yekaterinburg",
    "iso:country":"RU",
    "name:rus_x_preferred":[
        "\u0421\u0430\u043d\u0430\u0442\u043e\u0440\u043d\u044b\u0439"
    ],
    "wof:name":"Sanatornyy",
    "wof:placetype":"locality"
},
  "geometry": {"coordinates":[61.6143,54.8238],"type":"Point"}
}