{
  "type": "Feature",
  "properties": {
    "gn:admin1_code":"8",
    "gn:asciiname":"Narystau",
    "gn:country_code":"RU",
    "gn:dem":124,
    "gn:feature_class":"P",
    "gn:feature_code":"PPL",
    "gn:name":"Narystau",
    "gn:population":0,
    "gn:timezone":"Asia/Yekaterinburg",
    "iso:country":"RU",
    "name:rus_x_preferred":[
        "\u041d\u0430\u0440\u044b\u0441\u0442\u0430\u0443"
    ],
    "name:und_x_variant":[
        "Narastau",
        "Narystau"
    ],
    "wof:name":"Narystau",
    "wof:placetype":"locality"
},
  "geometry": {"coordinates":[55.03881,53.84864],"type":"Point"}
}