{
  "type": "Feature",
  "properties": {
    "gn:admin1_code":"25",
    "gn:asciiname":"Ramenskiy",
    "gn:country_code":"RU",
    "gn:dem":212,
    "gn:feature_class":"P",
    "gn:feature_code":"PPL",
    "gn:name":"Ramenskiy",
    "gn:population":0,
    "gn:timezone":"Europe/Moscow",
    "iso:country":"RU",
    "name:rus_x_preferred":[
        "\u0420\u0430\u043c\u0435\u043d\u0441\u043a\u0438\u0439"
    ],
    "name:und_x_variant":[
        "Sovkhoz Ramenskiy",
        "Ramenskiy"
    ],
    "wof:name":"Ramenskiy",
    "wof:placetype":"locality"
},
  "geometry": {"coordinates":[34.89417,54.58971999999999],"type":"Point"}
}