{
  "type": "Feature",
  "properties": {
    "gn:admin1_code":"10",
    "gn:asciiname":"Novoluboshevo",
    "gn:country_code":"RU",
    "gn:dem":184,
    "gn:feature_class":"P",
    "gn:feature_code":"PPL",
    "gn:name":"Novoluboshevo",
    "gn:population":0,
    "gn:timezone":"Europe/Moscow",
    "iso:country":"RU",
    "name:rus_x_preferred":[
        "\u041d\u043e\u0432\u043e\u043b\u0443\u0431\u043e\u0448\u0435\u0432\u043e"
    ],
    "wof:name":"Novoluboshevo",
    "wof:placetype":"locality"
},
  "geometry": {"coordinates":[34.6003,52.4664],"type":"Point"}
}