{
  "type": "Feature",
  "properties": {
    "gn:admin1_code":"86.0",
    "gn:asciiname":"Novouspenka",
    "gn:country_code":"RU",
    "gn:dem":168,
    "gn:feature_class":"P",
    "gn:feature_code":"PPL",
    "gn:name":"Novouspenka",
    "gn:population":0,
    "gn:timezone":"Europe/Moscow",
    "iso:country":"RU",
    "name:rus_x_preferred":[
        "\u041d\u043e\u0432\u043e\u0443\u0441\u043f\u0435\u043d\u043a\u0430"
    ],
    "name:und_x_variant":[
        "Dovgal\u00ebvka",
        "Novoye Uspenskoye",
        "Novouspenka"
    ],
    "wof:name":"Novouspenka",
    "wof:placetype":"locality"
},
  "geometry": {"coordinates":[39.08837,51.17206],"type":"Point"}
}