{
  "type": "Feature",
  "properties": {
    "gn:admin1_code":"77",
    "gn:asciiname":"Rashkovo",
    "gn:country_code":"RU",
    "gn:dem":184,
    "gn:feature_class":"P",
    "gn:feature_code":"PPL",
    "gn:name":"Rashkovo",
    "gn:population":0,
    "gn:timezone":"Europe/Moscow",
    "iso:country":"RU",
    "name:rus_x_preferred":[
        "\u0420\u0430\u0448\u043a\u043e\u0432\u043e"
    ],
    "name:und_x_variant":[
        "\u0420\u0430\u0448\u043a\u043e\u0432\u043e"
    ],
    "wof:name":"Rashkovo",
    "wof:placetype":"locality"
},
  "geometry": {"coordinates":[36.6475,58.3126],"type":"Point"}
}