{
  "type": "Feature",
  "properties": {
    "gn:admin1_code":"62",
    "gn:asciiname":"Studenets",
    "gn:country_code":"RU",
    "gn:dem":171,
    "gn:feature_class":"P",
    "gn:feature_code":"PPL",
    "gn:name":"Studenets",
    "gn:population":0,
    "gn:timezone":"Europe/Moscow",
    "iso:country":"RU",
    "name:ceb_x_preferred":[
        "Studenets"
    ],
    "name:swe_x_preferred":[
        "Studenets"
    ],
    "wof:name":"Studenets",
    "wof:placetype":"locality"
},
  "geometry": {"coordinates":[39.52583,54.30917],"type":"Point"}
}