{
  "type": "Feature",
  "properties": {
    "gn:admin1_code":"8",
    "gn:asciiname":"Kandakovka",
    "gn:country_code":"RU",
    "gn:dem":226,
    "gn:feature_class":"P",
    "gn:feature_code":"PPL",
    "gn:name":"Kandakovka",
    "gn:population":0,
    "gn:timezone":"Asia/Yekaterinburg",
    "iso:country":"RU",
    "name:eng_x_preferred":[
        "Kandakovka"
    ],
    "name:nor_x_preferred":[
        "Kandakovka"
    ],
    "name:rus_x_preferred":[
        "\u041a\u0430\u043d\u0434\u0430\u043a\u043e\u0432\u043a\u0430"
    ],
    "name:und_x_variant":[
        "Kondakovka",
        "\u041a\u0430\u043d\u0434\u0430\u043a\u043e\u0432\u043a\u0430",
        "Kandakovka"
    ],
    "wof:name":"Kandakovka",
    "wof:placetype":"locality"
},
  "geometry": {"coordinates":[58.4782,55.6001],"type":"Point"}
}