{
  "type": "Feature",
  "properties": {
    "gn:admin1_code":"8",
    "gn:asciiname":"Kandakovka",
    "gn:country_code":"RU",
    "gn:dem":226,
    "gn:feature_class":"P",
    "gn:feature_code":"PPL",
    "gn:name":"Kandakovka",
    "gn:population":0,
    "gn:timezone":"Asia/Yekaterinburg",
    "iso:country":"RU",
    "name:bak_x_preferred":[
        "\u041a\u0430\u043d\u0434\u0430\u043a\u043e\u0432\u043a\u0430"
    ],
    "name:che_x_preferred":[
        "\u041a\u0430\u043d\u0434\u0430\u043a\u043e\u0432\u043a\u0430"
    ],
    "name:eng_x_preferred":[
        "Kandakovka"
    ],
    "name:hye_x_preferred":[
        "\u053f\u0561\u0576\u0564\u0561\u056f\u0578\u057e\u056f\u0561"
    ],
    "name:kaz_x_preferred":[
        "\u041a\u0430\u043d\u0434\u0430\u043a\u043e\u0432\u043a\u0430"
    ],
    "name:kir_x_preferred":[
        "\u041a\u0430\u043d\u0434\u0430\u043a\u043e\u0432\u043a\u0430"
    ],
    "name:nor_x_preferred":[
        "Kandakovka"
    ],
    "name:rus_x_preferred":[
        "\u041a\u0430\u043d\u0434\u0430\u043a\u043e\u0432\u043a\u0430"
    ],
    "name:tat_x_preferred":[
        "\u041a\u0430\u043d\u0434\u0430\u043a\u043e\u0432\u043a\u0430"
    ],
    "name:und_x_variant":[
        "Kondakovka"
    ],
    "wof:name":"Kandakovka",
    "wof:placetype":"locality"
},
  "geometry": {"coordinates":[58.4782,55.6001],"type":"Point"}
}