{
  "type": "Feature",
  "properties": {
    "gn:admin1_code":"43",
    "gn:asciiname":"Krasnaya Pervaya",
    "gn:country_code":"RU",
    "gn:dem":213,
    "gn:feature_class":"P",
    "gn:feature_code":"PPL",
    "gn:name":"Krasnaya Pervaya",
    "gn:population":0,
    "gn:timezone":"Europe/Moscow",
    "iso:country":"RU",
    "name:rus_x_preferred":[
        "\u041a\u0440\u0430\u0441\u043d\u0430\u044f \u041f\u0435\u0440\u0432\u0430\u044f"
    ],
    "name:und_x_variant":[
        "Pervoye Krasnoye",
        "Krasnaya Pervaya"
    ],
    "wof:name":"Krasnaya Pervaya",
    "wof:placetype":"locality"
},
  "geometry": {"coordinates":[38.68915,53.07307],"type":"Point"}
}