{
  "type": "Feature",
  "properties": {
    "gn:admin1_code":"6.0",
    "gn:asciiname":"Chernyatinskaya",
    "gn:cc2":"RU",
    "gn:country_code":"RU",
    "gn:dem":32,
    "gn:feature_class":"P",
    "gn:feature_code":"PPL",
    "gn:name":"Chernyatinskaya",
    "gn:population":0,
    "gn:timezone":"Europe/Moscow",
    "iso:country":"RU",
    "name:rus_x_preferred":[
        "\u0427\u0435\u0440\u043d\u044f\u0442\u0438\u043d\u0441\u043a\u0430\u044f"
    ],
    "name:und_x_variant":[
        "Chemyatinskaya",
        "Chernyatinskaya",
        "\u0427\u0435\u0440\u043d\u044f\u0442\u0438\u043d\u0441\u043a\u0430\u044f"
    ],
    "wof:name":"Chernyatinskaya",
    "wof:placetype":"locality"
},
  "geometry": {"coordinates":[42.03333,63.08333],"type":"Point"}
}