{
  "type": "Feature",
  "properties": {
    "gn:admin1_code":"25.0",
    "gn:asciiname":"Poselok Babyninskoye Otdeleniye",
    "gn:country_code":"RU",
    "gn:dem":232,
    "gn:feature_class":"P",
    "gn:feature_code":"PPL",
    "gn:name":"Pos\u00eblok Babyninskoye Otdeleniye",
    "gn:population":0,
    "gn:timezone":"Europe/Moscow",
    "iso:country":"RU",
    "name:rus_x_preferred":[
        "\u041f\u043e\u0441\u0451\u043b\u043e\u043a \u0411\u0430\u0431\u044b\u043d\u0438\u043d\u0441\u043a\u043e\u0435 \u041e\u0442\u0434\u0435\u043b\u0435\u043d\u0438\u0435"
    ],
    "name:und_x_variant":[
        "Sovkhoz Babynino",
        "Pos\u00eblok Babyninskoye Otdeleniye"
    ],
    "wof:name":"Poselok Babyninskoye Otdeleniye",
    "wof:placetype":"locality"
},
  "geometry": {"coordinates":[35.71673,54.40429],"type":"Point"}
}