{
  "type": "Feature",
  "properties": {
    "gn:admin1_code":"72.0",
    "gn:asciiname":"Bezdushnyy Kust",
    "gn:country_code":"RU",
    "gn:dem":197,
    "gn:feature_class":"P",
    "gn:feature_code":"PPL",
    "gn:name":"Bezdushnyy Kust",
    "gn:population":0,
    "gn:timezone":"Europe/Moscow",
    "iso:country":"RU",
    "wof:name":"Bezdushnyy Kust",
    "wof:placetype":"locality"
},
  "geometry": {"coordinates":[41.96209,52.63217],"type":"Point"}
}