{
  "type": "Feature",
  "properties": {
    "gn:admin1_code":"45",
    "gn:asciiname":"Ishtyra",
    "gn:country_code":"RU",
    "gn:dem":148,
    "gn:feature_class":"P",
    "gn:feature_code":"PPL",
    "gn:name":"Ishtyra",
    "gn:population":0,
    "gn:timezone":"Europe/Moscow",
    "iso:country":"RU",
    "name:eng_x_preferred":[
        "Ishtyra"
    ],
    "name:nor_x_preferred":[
        "Isjtyra"
    ],
    "name:rus_x_preferred":[
        "\u0418\u0448\u0442\u044b\u0440\u0430"
    ],
    "name:und_x_variant":[
        "Ishtra",
        "\u0418\u0448\u0442\u044b\u0440\u0430",
        "Ishtyra"
    ],
    "wof:name":"Ishtyra",
    "wof:placetype":"locality"
},
  "geometry": {"coordinates":[49.4825,56.89556],"type":"Point"}
}