{
  "type": "Feature",
  "properties": {
    "gn:admin1_code":"37",
    "gn:asciiname":"Selezenevo",
    "gn:country_code":"RU",
    "gn:dem":151,
    "gn:feature_class":"P",
    "gn:feature_code":"PPL",
    "gn:name":"Selezenevo",
    "gn:population":0,
    "gn:timezone":"Europe/Moscow",
    "iso:country":"RU",
    "name:eng_x_preferred":[
        "Selezenevo"
    ],
    "name:nor_x_preferred":[
        "Seleznevo"
    ],
    "name:rus_x_preferred":[
        "\u0421\u0435\u043b\u0435\u0437\u043d\u0435\u0432\u043e"
    ],
    "name:rus_x_variant":[
        "\u0421\u0435\u043b\u0435\u0437\u0435\u043d\u0435\u0432\u043e"
    ],
    "name:und_x_variant":[
        "Selezn\u00ebvo"
    ],
    "wof:name":"Selezenevo",
    "wof:placetype":"locality"
},
  "geometry": {"coordinates":[42.2883,59.17849],"type":"Point"}
}