{
  "type": "Feature",
  "properties": {
    "gn:admin1_code":"88",
    "gn:asciiname":"Nily",
    "gn:country_code":"RU",
    "gn:dem":169,
    "gn:feature_class":"P",
    "gn:feature_code":"PPL",
    "gn:name":"Nily",
    "gn:population":0,
    "gn:timezone":"Europe/Moscow",
    "iso:country":"RU",
    "name:rus_x_preferred":[
        "\u041d\u0438\u043b\u044b"
    ],
    "name:und_x_variant":[
        "\u041d\u0438\u043b\u044b"
    ],
    "wof:name":"Nily",
    "wof:placetype":"locality"
},
  "geometry": {"coordinates":[38.96854,56.77933],"type":"Point"}
}