{
  "type": "Feature",
  "properties": {
    "gn:admin1_code":"33.0",
    "gn:asciiname":"Merinovo",
    "gn:country_code":"RU",
    "gn:dem":147,
    "gn:feature_class":"P",
    "gn:feature_code":"PPL",
    "gn:name":"Merinovo",
    "gn:population":0,
    "gn:timezone":"Europe/Kirov",
    "iso:country":"RU",
    "name:rus_x_preferred":[
        "\u041c\u0435\u0440\u0438\u043d\u043e\u0432\u043e"
    ],
    "wof:name":"Merinovo",
    "wof:placetype":"locality"
},
  "geometry": {"coordinates":[48.8599,57.3087],"type":"Point"}
}