{
  "type": "Feature",
  "properties": {
    "gn:admin1_code":"37",
    "gn:asciiname":"Mikheyevo",
    "gn:country_code":"RU",
    "gn:dem":94,
    "gn:feature_class":"P",
    "gn:feature_code":"PPL",
    "gn:name":"Mikheyevo",
    "gn:population":0,
    "gn:timezone":"Europe/Moscow",
    "iso:country":"RU",
    "name:eng_x_preferred":[
        "Mikheyevo"
    ],
    "name:nor_x_preferred":[
        "Mikhejevo"
    ],
    "name:rus_x_preferred":[
        "\u041c\u0438\u0445\u0435\u0435\u0432\u043e"
    ],
    "wof:name":"Mikheyevo",
    "wof:placetype":"locality"
},
  "geometry": {"coordinates":[43.27144000000001,57.8379],"type":"Point"}
}