{
  "type": "Feature",
  "properties": {
    "gn:admin1_code":"24.0",
    "gn:asciiname":"Kotya",
    "gn:country_code":"RU",
    "gn:dem":-1,
    "gn:feature_class":"P",
    "gn:feature_code":"PPL",
    "gn:name":"Kotya",
    "gn:population":0,
    "gn:timezone":"Europe/Moscow",
    "iso:country":"RU",
    "name:rus_x_preferred":[
        "\u041a\u043e\u0442\u044f"
    ],
    "name:und_x_variant":[
        "\u041a\u043e\u0442\u044f"
    ],
    "wof:name":"Kotya",
    "wof:placetype":"locality"
},
  "geometry": {"coordinates":[45.25583,47.22139],"type":"Point"}
}