{
  "type": "Feature",
  "properties": {
    "gn:admin1_code":"67.0",
    "gn:asciiname":"Gnoyevskiy",
    "gn:country_code":"RU",
    "gn:dem":50,
    "gn:feature_class":"P",
    "gn:feature_code":"PPL",
    "gn:name":"Gnoyevskiy",
    "gn:population":0,
    "gn:timezone":"Europe/Saratov",
    "iso:country":"RU",
    "name:rus_x_preferred":[
        "\u0413\u043d\u043e\u0435\u0432\u0441\u043a\u0438\u0439"
    ],
    "name:und_x_variant":[
        "\u0413\u043d\u043e\u0435\u0432\u0441\u043a\u0438\u0439"
    ],
    "wof:name":"Gnoyevskiy",
    "wof:placetype":"locality"
},
  "geometry": {"coordinates":[46.93333,50.55],"type":"Point"}
}