{
  "type": "Feature",
  "properties": {
    "gn:admin1_code":"77",
    "gn:asciiname":"Sapkovo",
    "gn:country_code":"RU",
    "gn:dem":133,
    "gn:feature_class":"P",
    "gn:feature_code":"PPL",
    "gn:name":"Sapkovo",
    "gn:population":0,
    "gn:timezone":"Europe/Moscow",
    "iso:country":"RU",
    "name:rus_x_preferred":[
        "\u0421\u0430\u043f\u043a\u043e\u0432\u043e"
    ],
    "wof:name":"Sapkovo",
    "wof:placetype":"locality"
},
  "geometry": {"coordinates":[36.0709,56.887],"type":"Point"}
}