{
  "type": "Feature",
  "properties": {
    "gn:admin1_code":"10",
    "gn:asciiname":"Selets",
    "gn:country_code":"RU",
    "gn:dem":150,
    "gn:feature_class":"P",
    "gn:feature_code":"PPL",
    "gn:name":"Selets",
    "gn:population":0,
    "gn:timezone":"Europe/Moscow",
    "iso:country":"RU",
    "name:eng_x_preferred":[
        "Selets"
    ],
    "name:nor_x_preferred":[
        "Selets"
    ],
    "name:rus_x_preferred":[
        "\u0421\u0435\u043b\u0435\u0446"
    ],
    "name:und_x_variant":[
        "\u0421\u0435\u043b\u0435\u0446",
        "Selets"
    ],
    "wof:name":"Selets",
    "wof:placetype":"locality"
},
  "geometry": {"coordinates":[31.6884,52.9542],"type":"Point"}
}