{
  "type": "Feature",
  "properties": {
    "gn:admin1_code":"53",
    "gn:asciiname":"Nikitinka",
    "gn:cc2":"RU",
    "gn:country_code":"RU",
    "gn:dem":107,
    "gn:feature_class":"P",
    "gn:feature_code":"PPL",
    "gn:name":"Nikitinka",
    "gn:population":0,
    "gn:timezone":"Asia/Novosibirsk",
    "iso:country":"RU",
    "name:bak_x_preferred":[
        "\u041d\u0438\u043a\u0438\u0442\u0438\u043d\u043a\u0430"
    ],
    "name:che_x_preferred":[
        "\u041d\u0438\u043a\u0438\u0442\u0438\u043d\u043a\u0430"
    ],
    "name:chv_x_preferred":[
        "\u041d\u0438\u043a\u0438\u0442\u0438\u043d\u043a\u0430"
    ],
    "name:hye_x_preferred":[
        "\u0546\u056b\u056f\u056b\u057f\u056b\u0576\u056f\u0561"
    ],
    "name:kaz_x_preferred":[
        "\u041d\u0438\u043a\u0438\u0442\u0438\u043d\u043a\u0430"
    ],
    "name:kir_x_preferred":[
        "\u041d\u0438\u043a\u0438\u0442\u0438\u043d\u043a\u0430"
    ],
    "name:rus_x_preferred":[
        "\u041d\u0438\u043a\u0438\u0442\u0438\u043d\u043a\u0430"
    ],
    "name:tat_x_preferred":[
        "\u041d\u0438\u043a\u0438\u0442\u0438\u043d\u043a\u0430"
    ],
    "name:ukr_x_preferred":[
        "\u041d\u0456\u043a\u0456\u0442\u0456\u043d\u043a\u0430"
    ],
    "name:und_x_variant":[
        "Nikitinskiy",
        "Nikitinka"
    ],
    "wof:name":"Nikitinka",
    "wof:placetype":"locality"
},
  "geometry": {"coordinates":[75.48333000000002,55.85],"type":"Point"}
}