{
  "type": "Feature",
  "properties": {
    "gn:admin1_code":"53",
    "gn:asciiname":"Nikitinka",
    "gn:cc2":"RU",
    "gn:country_code":"RU",
    "gn:dem":107,
    "gn:feature_class":"P",
    "gn:feature_code":"PPL",
    "gn:name":"Nikitinka",
    "gn:population":0,
    "gn:timezone":"Asia/Novosibirsk",
    "iso:country":"RU",
    "name:rus_x_preferred":[
        "\u041d\u0438\u043a\u0438\u0442\u0438\u043d\u043a\u0430"
    ],
    "name:und_x_variant":[
        "Nikitinskiy",
        "Nikitinka",
        "\u041d\u0438\u043a\u0438\u0442\u0438\u043d\u043a\u0430"
    ],
    "wof:name":"Nikitinka",
    "wof:placetype":"locality"
},
  "geometry": {"coordinates":[75.48333000000002,55.85],"type":"Point"}
}