{
  "type": "Feature",
  "properties": {
    "gn:admin1_code":"91",
    "gn:asciiname":"Kresty",
    "gn:cc2":"RU",
    "gn:country_code":"RU",
    "gn:dem":32,
    "gn:feature_class":"P",
    "gn:feature_code":"PPL",
    "gn:name":"Kresty",
    "gn:population":0,
    "gn:timezone":"Asia/Krasnoyarsk",
    "iso:country":"RU",
    "name:eng_x_preferred":[
        "Kresty"
    ],
    "name:nor_x_preferred":[
        "Kresty"
    ],
    "name:rus_x_preferred":[
        "\u041a\u0440\u0435\u0441\u0442\u044b"
    ],
    "name:und_x_variant":[
        "Faktoriya Kresty",
        "Stanok Kresty",
        "Kresty"
    ],
    "wof:name":"Kresty",
    "wof:placetype":"locality"
},
  "geometry": {"coordinates":[89.90318000000001,70.86089],"type":"Point"}
}