{
  "type": "Feature",
  "properties": {
    "gn:admin1_code":"64",
    "gn:asciiname":"Podgornoye",
    "gn:country_code":"RU",
    "gn:dem":42,
    "gn:feature_class":"P",
    "gn:feature_code":"PPL",
    "gn:name":"Podgornoye",
    "gn:population":0,
    "gn:timezone":"Asia/Sakhalin",
    "iso:country":"RU",
    "name:nor_x_preferred":[
        "Podgornoje"
    ],
    "name:rus_x_preferred":[
        "\u041f\u043e\u0434\u0433\u043e\u0440\u043d\u043e\u0435"
    ],
    "name:und_x_variant":[
        "Kita-obara",
        "Kami-obara",
        "Podgornaya",
        "Podgornoye"
    ],
    "wof:name":"Podgornoye",
    "wof:placetype":"locality"
},
  "geometry": {"coordinates":[142.42764,46.76916],"type":"Point"}
}