{
  "type": "Feature",
  "properties": {
    "gn:admin1_code":"38.0",
    "gn:asciiname":"Amosov",
    "gn:country_code":"RU",
    "gn:dem":63,
    "gn:feature_class":"P",
    "gn:feature_code":"PPL",
    "gn:name":"Amosov",
    "gn:population":0,
    "gn:timezone":"Europe/Moscow",
    "iso:country":"RU",
    "name:nor_x_preferred":[
        "Amosov"
    ],
    "name:rus_x_preferred":[
        "\u0410\u043c\u043e\u0441\u043e\u0432"
    ],
    "name:ukr_x_preferred":[
        "\u0410\u043c\u043e\u0441\u043e\u0432"
    ],
    "wof:name":"Amosov",
    "wof:placetype":"locality"
},
  "geometry": {"coordinates":[39.87279,45.00192],"type":"Point"}
}