{
  "type": "Feature",
  "properties": {
    "gn:admin1_code":"25.0",
    "gn:asciiname":"Poselok Imeni Karla Marksa",
    "gn:country_code":"RU",
    "gn:dem":189,
    "gn:feature_class":"P",
    "gn:feature_code":"PPL",
    "gn:name":"Pos\u00eblok Imeni Karla Marksa",
    "gn:population":0,
    "gn:timezone":"Europe/Moscow",
    "iso:country":"RU",
    "name:rus_x_preferred":[
        "\u041f\u043e\u0441\u0451\u043b\u043e\u043a \u0418\u043c\u0435\u043d\u0438 \u041a\u0430\u0440\u043b\u0430 \u041c\u0430\u0440\u043a\u0441\u0430"
    ],
    "name:und_x_variant":[
        "Pos\u00eblok Imeni Karla Marksa",
        "\u041f\u043e\u0441\u0451\u043b\u043e\u043a \u0418\u043c\u0435\u043d\u0438 \u041a\u0430\u0440\u043b\u0430 \u041c\u0430\u0440\u043a\u0441\u0430"
    ],
    "wof:name":"Poselok Imeni Karla Marksa",
    "wof:placetype":"locality"
},
  "geometry": {"coordinates":[35.47327999999999,54.90878000000001],"type":"Point"}
}