{
  "type": "Feature",
  "properties": {
    "gn:admin1_code":"77",
    "gn:asciiname":"Mal'yakina",
    "gn:country_code":"RU",
    "gn:dem":201,
    "gn:feature_class":"P",
    "gn:feature_code":"PPL",
    "gn:name":"Mal\u2019yakina",
    "gn:population":0,
    "gn:timezone":"Europe/Moscow",
    "iso:country":"RU",
    "name:rus_x_preferred":[
        "\u041c\u0430\u043b\u044c\u044f\u043a\u0438\u043d\u0430"
    ],
    "name:und_x_variant":[
        "Mal\u2019yaki",
        "Mal\u2019yakina"
    ],
    "wof:name":"Mal'yakina",
    "wof:placetype":"locality"
},
  "geometry": {"coordinates":[34.91667,56.25],"type":"Point"}
}