{
  "type": "Feature",
  "properties": {
    "gn:admin1_code":"40",
    "gn:asciiname":"Antoshkino",
    "gn:country_code":"RU",
    "gn:dem":142,
    "gn:feature_class":"P",
    "gn:feature_code":"PPL",
    "gn:name":"Antoshkino",
    "gn:population":0,
    "gn:timezone":"Asia/Yekaterinburg",
    "iso:country":"RU",
    "name:nor_x_preferred":[
        "Antosjkino"
    ],
    "name:rus_x_preferred":[
        "\u0410\u043d\u0442\u043e\u0448\u043a\u0438\u043d\u043e"
    ],
    "wof:name":"Antoshkino",
    "wof:placetype":"locality"
},
  "geometry": {"coordinates":[63.13861,55.62778],"type":"Point"}
}