{
  "type": "Feature",
  "properties": {
    "gn:admin1_code":"64",
    "gn:asciiname":"Podorozhnaya",
    "gn:cc2":"RU",
    "gn:country_code":"RU",
    "gn:dem":83,
    "gn:feature_class":"P",
    "gn:feature_code":"PPL",
    "gn:name":"Podorozhnaya",
    "gn:population":0,
    "gn:timezone":"Asia/Sakhalin",
    "iso:country":"RU",
    "name:rus_x_preferred":[
        "\u041f\u043e\u0434\u043e\u0440\u043e\u0436\u043d\u0430\u044f"
    ],
    "name:und_x_variant":[
        "Minagishi",
        "Podporozhnaya",
        "Griboroshchnoy",
        "Podoroshnaya",
        "Minakishi",
        "Podorozhnaya"
    ],
    "wof:name":"Podorozhnaya",
    "wof:placetype":"locality"
},
  "geometry": {"coordinates":[142.96666999999999,46.83333],"type":"Point"}
}