{
  "type": "Feature",
  "properties": {
    "gn:admin1_code":"56",
    "gn:asciiname":"Suslovo",
    "gn:country_code":"RU",
    "gn:dem":141,
    "gn:feature_class":"P",
    "gn:feature_code":"PPL",
    "gn:name":"Suslovo",
    "gn:population":0,
    "gn:timezone":"Europe/Moscow",
    "iso:country":"RU",
    "name:bak_x_preferred":[
        "\u0421\u0443\u0441\u043b\u043e\u0432"
    ],
    "name:che_x_preferred":[
        "\u0421\u0443\u0441\u043b\u043e\u0432\u043e"
    ],
    "name:hye_x_preferred":[
        "\u054d\u0578\u0582\u057d\u056c\u0578\u057e\u0578"
    ],
    "name:kaz_x_preferred":[
        "\u0421\u0443\u0441\u043b"
    ],
    "name:kir_x_preferred":[
        "\u0421\u0443\u0441\u043b"
    ],
    "name:rus_x_preferred":[
        "\u0421\u0443\u0441\u043b\u043e\u0432\u043e"
    ],
    "name:tat_x_preferred":[
        "\u0421\u0443\u0441\u043b\u043e\u0432\u043e"
    ],
    "wof:name":"Suslovo",
    "wof:placetype":"locality"
},
  "geometry": {"coordinates":[37.73565,52.36618],"type":"Point"}
}