{
  "type": "Feature",
  "properties": {
    "gn:admin1_code":"46",
    "gn:asciiname":"Selishchi",
    "gn:country_code":"RU",
    "gn:dem":100,
    "gn:feature_class":"P",
    "gn:feature_code":"PPL",
    "gn:name":"Selishchi",
    "gn:population":0,
    "gn:timezone":"Europe/Moscow",
    "iso:country":"RU",
    "name:eng_x_preferred":[
        "Selishche"
    ],
    "name:nor_x_preferred":[
        "Selisjtsji"
    ],
    "name:rus_x_preferred":[
        "\u0421\u0435\u043b\u0438\u0449\u0438"
    ],
    "name:und_x_variant":[
        "Selishche",
        "Selishchi",
        "\u0421\u0435\u043b\u0438\u0449\u0438"
    ],
    "wof:name":"Selishchi",
    "wof:placetype":"locality"
},
  "geometry": {"coordinates":[45.63824,54.73833000000001],"type":"Point"}
}