{
  "type": "Feature",
  "properties": {
    "gn:admin1_code":"16",
    "gn:asciiname":"Kudemery",
    "gn:country_code":"RU",
    "gn:dem":108,
    "gn:feature_class":"P",
    "gn:feature_code":"PPL",
    "gn:name":"Kudemery",
    "gn:population":0,
    "gn:timezone":"Europe/Moscow",
    "iso:country":"RU",
    "name:rus_x_preferred":[
        "\u041a\u0443\u0434\u0435\u043c\u0435\u0440\u044b"
    ],
    "wof:name":"Kudemery",
    "wof:placetype":"locality"
},
  "geometry": {"coordinates":[47.82343,55.83745],"type":"Point"}
}