{
  "type": "Feature",
  "properties": {
    "gn:admin1_code":"63",
    "gn:asciiname":"Dabygy",
    "gn:country_code":"RU",
    "gn:dem":219,
    "gn:feature_class":"P",
    "gn:feature_code":"PPL",
    "gn:name":"Dabygy",
    "gn:population":0,
    "gn:timezone":"Asia/Yakutsk",
    "iso:country":"RU",
    "name:rus_x_preferred":[
        "\u0414\u0430\u0431\u044b\u0433\u044b"
    ],
    "wof:name":"Dabygy",
    "wof:placetype":"locality"
},
  "geometry": {"coordinates":[126.68333,62.11666999999999],"type":"Point"}
}