{
  "type": "Feature",
  "properties": {
    "gn:admin1_code":"9.0",
    "gn:asciiname":"Sitnoye",
    "gn:country_code":"RU",
    "gn:dem":198,
    "gn:feature_class":"P",
    "gn:feature_code":"PPL",
    "gn:name":"Sitnoye",
    "gn:population":0,
    "gn:timezone":"Europe/Moscow",
    "iso:country":"RU",
    "name:rus_x_preferred":[
        "\u0421\u0438\u0442\u043d\u043e\u0435"
    ],
    "wof:name":"Sitnoye",
    "wof:placetype":"locality"
},
  "geometry": {"coordinates":[35.955,50.7334],"type":"Point"}
}