{
  "type": "Feature",
  "properties": {
    "gn:admin1_code":"20.0",
    "gn:asciiname":"Kirzavod",
    "gn:country_code":"RU",
    "gn:dem":545,
    "gn:feature_class":"P",
    "gn:feature_code":"PPL",
    "gn:name":"Kirzavod",
    "gn:population":0,
    "gn:timezone":"Asia/Irkutsk",
    "iso:country":"RU",
    "name:rus_x_preferred":[
        "\u041a\u0438\u0440\u0437\u0430\u0432\u043e\u0434"
    ],
    "wof:name":"Kirzavod",
    "wof:placetype":"locality"
},
  "geometry": {"coordinates":[102.9316,53.2246],"type":"Point"}
}