{
  "type": "Feature",
  "properties": {
    "gn:admin1_code":"9.0",
    "gn:asciiname":"Gnilitsa",
    "gn:country_code":"RU",
    "gn:dem":208,
    "gn:feature_class":"P",
    "gn:feature_code":"PPL",
    "gn:name":"Gnilitsa",
    "gn:population":0,
    "gn:timezone":"Europe/Moscow",
    "iso:country":"RU",
    "name:rus_x_preferred":[
        "\u0413\u043d\u0438\u043b\u0438\u0446\u0430"
    ],
    "wof:name":"Gnilitsa",
    "wof:placetype":"locality"
},
  "geometry": {"coordinates":[37.4926,50.6571],"type":"Point"}
}