{
  "type": "Feature",
  "properties": {
    "gn:admin1_code":"73",
    "gn:asciiname":"Fionovka",
    "gn:country_code":"RU",
    "gn:dem":94,
    "gn:feature_class":"P",
    "gn:feature_code":"PPL",
    "gn:name":"Fionovka",
    "gn:population":0,
    "gn:timezone":"Europe/Moscow",
    "iso:country":"RU",
    "name:rus_x_preferred":[
        "\u0424\u0438\u043e\u043d\u043e\u0432\u043a\u0430"
    ],
    "wof:name":"Fionovka",
    "wof:placetype":"locality"
},
  "geometry": {"coordinates":[52.9182,55.6969],"type":"Point"}
}