{
  "type": "Feature",
  "properties": {
    "gn:admin1_code":"60",
    "gn:asciiname":"Volokovo",
    "gn:country_code":"RU",
    "gn:dem":190,
    "gn:feature_class":"P",
    "gn:feature_code":"PPL",
    "gn:name":"Volokovo",
    "gn:population":0,
    "gn:timezone":"Europe/Moscow",
    "iso:country":"RU",
    "name:rus_x_preferred":[
        "\u0412\u043e\u043b\u043e\u043a\u043e\u0432\u043e"
    ],
    "name:und_x_variant":[
        "\u0412\u043e\u043b\u043e\u043a\u043e\u0432\u043e"
    ],
    "wof:name":"Volokovo",
    "wof:placetype":"locality"
},
  "geometry": {"coordinates":[29.3844,56.6906],"type":"Point"}
}