{
  "type": "Feature",
  "properties": {
    "gn:admin1_code":"69",
    "gn:asciiname":"Skvortsy",
    "gn:country_code":"RU",
    "gn:dem":173,
    "gn:feature_class":"P",
    "gn:feature_code":"PPL",
    "gn:name":"Skvortsy",
    "gn:population":0,
    "gn:timezone":"Europe/Moscow",
    "iso:country":"RU",
    "name:rus_x_preferred":[
        "\u0421\u043a\u0432\u043e\u0440\u0446\u044b"
    ],
    "wof:name":"Skvortsy",
    "wof:placetype":"locality"
},
  "geometry": {"coordinates":[31.0607,54.73104],"type":"Point"}
}