{
  "type": "Feature",
  "properties": {
    "gn:admin1_code":"56",
    "gn:asciiname":"Lazavka",
    "gn:country_code":"RU",
    "gn:dem":232,
    "gn:feature_class":"P",
    "gn:feature_code":"PPL",
    "gn:name":"Lazavka",
    "gn:population":0,
    "gn:timezone":"Europe/Moscow",
    "iso:country":"RU",
    "name:rus_x_preferred":[
        "\u041b\u0430\u0437\u0430\u0432\u043a\u0430"
    ],
    "name:und_x_variant":[
        "Lozovka",
        "Lazavka",
        "\u041b\u0430\u0437\u0430\u0432\u043a\u0430"
    ],
    "wof:name":"Lazavka",
    "wof:placetype":"locality"
},
  "geometry": {"coordinates":[37.6802,52.89097],"type":"Point"}
}