{
  "type": "Feature",
  "properties": {
    "gn:admin1_code":"81",
    "gn:asciiname":"Zagarino",
    "gn:country_code":"RU",
    "gn:dem":147,
    "gn:feature_class":"P",
    "gn:feature_code":"PPL",
    "gn:name":"Zagarino",
    "gn:population":0,
    "gn:timezone":"Europe/Ulyanovsk",
    "iso:country":"RU",
    "name:che_x_preferred":[
        "\u0417\u0430\u0433\u0430\u0440\u0438\u043d\u043e"
    ],
    "name:eng_x_preferred":[
        "Zagarino"
    ],
    "name:nor_x_preferred":[
        "Zagarino"
    ],
    "name:rus_x_preferred":[
        "\u0417\u0430\u0433\u0430\u0440\u0438\u043d\u043e"
    ],
    "wof:name":"Zagarino",
    "wof:placetype":"locality"
},
  "geometry": {"coordinates":[47.24508,53.42292],"type":"Point"}
}