{
  "type": "Feature",
  "properties": {
    "gn:admin1_code":"62.0",
    "gn:asciiname":"Chuliksa",
    "gn:country_code":"RU",
    "gn:dem":125,
    "gn:feature_class":"P",
    "gn:feature_code":"PPL",
    "gn:name":"Chuliksa",
    "gn:population":0,
    "gn:timezone":"Europe/Moscow",
    "iso:country":"RU",
    "name:rus_x_preferred":[
        "\u0427\u0443\u043b\u0438\u043a\u0441\u0430"
    ],
    "name:und_x_variant":[
        "Uvarova",
        "Chuliksy",
        "Chuliksa"
    ],
    "wof:name":"Chuliksa",
    "wof:placetype":"locality"
},
  "geometry": {"coordinates":[41.27663,55.12921],"type":"Point"}
}