{
  "type": "Feature",
  "properties": {
    "gn:admin1_code":"77",
    "gn:asciiname":"Krasnyy Stan",
    "gn:country_code":"RU",
    "gn:dem":214,
    "gn:feature_class":"P",
    "gn:feature_code":"PPL",
    "gn:name":"Krasnyy Stan",
    "gn:population":0,
    "gn:timezone":"Europe/Moscow",
    "iso:country":"RU",
    "name:rus_x_preferred":[
        "\u041a\u0440\u0430\u0441\u043d\u044b\u0439 \u0421\u0442\u0430\u043d"
    ],
    "wof:name":"Krasnyy Stan",
    "wof:placetype":"locality"
},
  "geometry": {"coordinates":[32.885,55.98056],"type":"Point"}
}