{
  "type": "Feature",
  "properties": {
    "gn:admin1_code":"73",
    "gn:asciiname":"Bol'shoye Kadryakovo",
    "gn:country_code":"RU",
    "gn:dem":103,
    "gn:feature_class":"P",
    "gn:feature_code":"PPL",
    "gn:name":"Bol\u2019shoye Kadryakovo",
    "gn:population":0,
    "gn:timezone":"Europe/Moscow",
    "iso:country":"RU",
    "name:rus_x_preferred":[
        "\u0411\u043e\u043b\u044c\u0448\u043e\u0435 \u041a\u0430\u0434\u0440\u044f\u043a\u043e\u0432\u043e"
    ],
    "name:und_x_variant":[
        "Bol\u2019shoye Kadryakovo"
    ],
    "wof:name":"Bol'shoye Kadryakovo",
    "wof:placetype":"locality"
},
  "geometry": {"coordinates":[50.58095,55.63738000000001],"type":"Point"}
}