{
  "type": "Feature",
  "properties": {
    "gn:admin1_code":"11",
    "gn:asciiname":"Tsaram",
    "gn:country_code":"RU",
    "gn:dem":668,
    "gn:feature_class":"P",
    "gn:feature_code":"PPL",
    "gn:name":"Tsaram",
    "gn:population":0,
    "gn:timezone":"Asia/Irkutsk",
    "iso:country":"RU",
    "wof:name":"Tsaram",
    "wof:placetype":"locality"
},
  "geometry": {"coordinates":[106.87782,50.82496],"type":"Point"}
}