{
  "type": "Feature",
  "properties": {
    "gn:admin1_code":"12.0",
    "gn:asciiname":"Chaimyakhki",
    "gn:country_code":"RU",
    "gn:dem":1072,
    "gn:feature_class":"P",
    "gn:feature_code":"PPL",
    "gn:name":"Chaimyakhki",
    "gn:population":0,
    "gn:timezone":"Europe/Moscow",
    "iso:country":"RU",
    "name:rus_x_preferred":[
        "\u0427\u0430\u0438\u043c\u044f\u0445\u043a\u0438"
    ],
    "wof:name":"Chaimyakhki",
    "wof:placetype":"locality"
},
  "geometry": {"coordinates":[45.67972,42.81167],"type":"Point"}
}