{
  "type": "Feature",
  "properties": {
    "gn:admin1_code":"33",
    "gn:asciiname":"Zhivotovo",
    "gn:country_code":"RU",
    "gn:dem":131,
    "gn:feature_class":"P",
    "gn:feature_code":"PPL",
    "gn:name":"Zhivotovo",
    "gn:population":0,
    "gn:timezone":"Europe/Kirov",
    "iso:country":"RU",
    "name:eng_x_preferred":[
        "Zhivotovo"
    ],
    "name:nor_x_preferred":[
        "Zjivotovo"
    ],
    "name:rus_x_preferred":[
        "\u0416\u0438\u0432\u043e\u0442\u043e\u0432\u043e"
    ],
    "wof:name":"Zhivotovo",
    "wof:placetype":"locality"
},
  "geometry": {"coordinates":[47.6828,60.8419],"type":"Point"}
}