{
  "type": "Feature",
  "properties": {
    "gn:admin1_code":"29",
    "gn:asciiname":"Babinskaya",
    "gn:country_code":"RU",
    "gn:dem":338,
    "gn:feature_class":"P",
    "gn:feature_code":"PPL",
    "gn:name":"Babinskaya",
    "gn:population":0,
    "gn:timezone":"Asia/Omsk",
    "iso:country":"RU",
    "name:nor_x_preferred":[
        "Babinskaja"
    ],
    "name:rus_x_preferred":[
        "\u0411\u0430\u0431\u0438\u043d\u0441\u043a\u0430\u044f"
    ],
    "wof:name":"Babinskaya",
    "wof:placetype":"locality"
},
  "geometry": {"coordinates":[85.21666999999999,54.23333],"type":"Point"}
}