{
  "type": "Feature",
  "properties": {
    "gn:admin1_code":"10",
    "gn:asciiname":"Ryukhov",
    "gn:country_code":"RU",
    "gn:dem":197,
    "gn:feature_class":"P",
    "gn:feature_code":"PPL",
    "gn:name":"Ryukhov",
    "gn:population":0,
    "gn:timezone":"Europe/Moscow",
    "iso:country":"RU",
    "name:eng_x_preferred":[
        "Ryukhovo"
    ],
    "name:nor_x_preferred":[
        "Rjukhovo"
    ],
    "name:rus_x_preferred":[
        "\u0420\u044e\u0445\u043e\u0432\u043e"
    ],
    "name:rus_x_variant":[
        "\u0420\u044e\u0445\u043e\u0432"
    ],
    "wof:name":"Ryukhov",
    "wof:placetype":"locality"
},
  "geometry": {"coordinates":[32.77603,52.77345],"type":"Point"}
}