{
  "type": "Feature",
  "properties": {
    "gn:admin1_code":"60",
    "gn:asciiname":"Tovarets",
    "gn:country_code":"RU",
    "gn:dem":46,
    "gn:feature_class":"P",
    "gn:feature_code":"PPL",
    "gn:name":"Tovarets",
    "gn:population":0,
    "gn:timezone":"Europe/Moscow",
    "iso:country":"RU",
    "name:rus_x_preferred":[
        "\u0422\u043e\u0432\u0430\u0440\u0435\u0446"
    ],
    "wof:name":"Tovarets",
    "wof:placetype":"locality"
},
  "geometry": {"coordinates":[28.7734,57.7209],"type":"Point"}
}