{
  "type": "Feature",
  "properties": {
    "gn:admin1_code":"33",
    "gn:asciiname":"Bol'shaya Polomka",
    "gn:country_code":"RU",
    "gn:dem":107,
    "gn:feature_class":"P",
    "gn:feature_code":"PPL",
    "gn:name":"Bol\u2019shaya Polomka",
    "gn:population":0,
    "gn:timezone":"Europe/Kirov",
    "iso:country":"RU",
    "name:rus_x_preferred":[
        "\u0411\u043e\u043b\u044c\u0448\u0430\u044f \u041f\u043e\u043b\u043e\u043c\u043a\u0430"
    ],
    "name:und_x_variant":[
        "Bol\u2019shaya Polomka"
    ],
    "wof:name":"Bol'shaya Polomka",
    "wof:placetype":"locality"
},
  "geometry": {"coordinates":[46.9394,57.0541],"type":"Point"}
}