{
  "type": "Feature",
  "properties": {
    "gn:admin1_code":"21.0",
    "gn:asciiname":"Agrofenino",
    "gn:country_code":"RU",
    "gn:dem":106,
    "gn:feature_class":"P",
    "gn:feature_code":"PPL",
    "gn:name":"Agrofenino",
    "gn:population":0,
    "gn:timezone":"Europe/Moscow",
    "iso:country":"RU",
    "name:und_x_variant":[
        "Agrafenino",
        "Agrofenino"
    ],
    "wof:name":"Agrofenino",
    "wof:placetype":"locality"
},
  "geometry": {"coordinates":[41.00622,56.5788],"type":"Point"}
}