{
  "type": "Feature",
  "properties": {
    "gn:admin1_code":"53",
    "gn:asciiname":"Tarasovskiy",
    "gn:country_code":"RU",
    "gn:dem":293,
    "gn:feature_class":"P",
    "gn:feature_code":"PPL",
    "gn:name":"Tarasovskiy",
    "gn:population":0,
    "gn:timezone":"Asia/Novosibirsk",
    "iso:country":"RU",
    "wof:name":"Tarasovskiy",
    "wof:placetype":"locality"
},
  "geometry": {"coordinates":[84.15000000000001,54.23333],"type":"Point"}
}