{
  "type": "Feature",
  "properties": {
    "gn:admin1_code":"40",
    "gn:asciiname":"Karas'ye",
    "gn:country_code":"RU",
    "gn:dem":130,
    "gn:feature_class":"P",
    "gn:feature_code":"PPL",
    "gn:name":"Karas\u2019ye",
    "gn:population":0,
    "gn:timezone":"Asia/Yekaterinburg",
    "iso:country":"RU",
    "name:eng_x_preferred":[
        "Karas'ye"
    ],
    "name:nor_x_preferred":[
        "Karasie"
    ],
    "name:rus_x_preferred":[
        "\u041a\u0430\u0440\u0430\u0441\u044c\u0435"
    ],
    "name:und_x_variant":[
        "\u041a\u0430\u0440\u0430\u0441\u044c\u0435",
        "Karas\u2019ye"
    ],
    "wof:name":"Karas'ye",
    "wof:placetype":"locality"
},
  "geometry": {"coordinates":[68.32056,55.4175],"type":"Point"}
}