{
  "type": "Feature",
  "properties": {
    "gn:admin1_code":"60",
    "gn:asciiname":"Alferovo",
    "gn:country_code":"RU",
    "gn:dem":138,
    "gn:feature_class":"P",
    "gn:feature_code":"PPL",
    "gn:name":"Alferovo",
    "gn:population":0,
    "gn:timezone":"Europe/Moscow",
    "iso:country":"RU",
    "name:nor_x_preferred":[
        "Alferovo"
    ],
    "name:rus_x_preferred":[
        "\u0410\u043b\u0444\u0435\u0440\u043e\u0432\u043e"
    ],
    "wof:name":"Alferovo",
    "wof:placetype":"locality"
},
  "geometry": {"coordinates":[30.94694,56.40167],"type":"Point"}
}