{
  "type": "Feature",
  "properties": {
    "gn:admin1_code":"85",
    "gn:asciiname":"Bessolovo",
    "gn:country_code":"RU",
    "gn:dem":119,
    "gn:feature_class":"P",
    "gn:feature_code":"PPL",
    "gn:name":"Bessolovo",
    "gn:population":0,
    "gn:timezone":"Europe/Moscow",
    "iso:country":"RU",
    "name:rus_x_preferred":[
        "\u0411\u0435\u0441\u0441\u043e\u043b\u043e\u0432\u043e"
    ],
    "wof:name":"Bessolovo",
    "wof:placetype":"locality"
},
  "geometry": {"coordinates":[38.5222,59.3068],"type":"Point"}
}