{
  "type": "Feature",
  "properties": {
    "gn:admin1_code":"73",
    "gn:asciiname":"Novoye Akkuzino",
    "gn:country_code":"RU",
    "gn:dem":104,
    "gn:feature_class":"P",
    "gn:feature_code":"PPL",
    "gn:name":"Novoye Akkuzino",
    "gn:population":0,
    "gn:timezone":"Europe/Moscow",
    "iso:country":"RU",
    "name:rus_x_preferred":[
        "\u041d\u043e\u0432\u043e\u0435 \u0410\u043a\u043a\u0443\u0437\u0438\u043d\u043e"
    ],
    "name:und_x_variant":[
        "\u041d\u043e\u0432\u043e\u0435 \u0410\u043a\u043a\u0443\u0437\u0438\u043d\u043e"
    ],
    "wof:name":"Novoye Akkuzino",
    "wof:placetype":"locality"
},
  "geometry": {"coordinates":[52.73968000000001,56.26806],"type":"Point"}
}