{
  "type": "Feature",
  "properties": {
    "gn:admin1_code":"76",
    "gn:asciiname":"Vyazovo",
    "gn:country_code":"RU",
    "gn:dem":191,
    "gn:feature_class":"P",
    "gn:feature_code":"PPL",
    "gn:name":"Vyazovo",
    "gn:population":0,
    "gn:timezone":"Europe/Moscow",
    "iso:country":"RU",
    "name:rus_x_preferred":[
        "\u0412\u044f\u0437\u043e\u0432\u043e"
    ],
    "name:und_x_variant":[
        "\u0412\u044f\u0437\u043e\u0432\u043e"
    ],
    "wof:name":"Vyazovo",
    "wof:placetype":"locality"
},
  "geometry": {"coordinates":[38.43402,53.20171],"type":"Point"}
}