{
  "type": "Feature",
  "properties": {
    "gn:admin1_code":"63",
    "gn:asciiname":"Sogobut",
    "gn:country_code":"RU",
    "gn:dem":184,
    "gn:feature_class":"P",
    "gn:feature_code":"PPL",
    "gn:name":"Sogobut",
    "gn:population":0,
    "gn:timezone":"Asia/Yakutsk",
    "iso:country":"RU",
    "name:rus_x_preferred":[
        "\u0421\u043e\u0433\u043e\u0431\u0443\u0442"
    ],
    "wof:name":"Sogobut",
    "wof:placetype":"locality"
},
  "geometry": {"coordinates":[122.23333,64.55],"type":"Point"}
}