{
  "type": "Feature",
  "properties": {
    "gn:admin1_code":"40",
    "gn:asciiname":"Linevo",
    "gn:country_code":"RU",
    "gn:dem":144,
    "gn:feature_class":"P",
    "gn:feature_code":"PPL",
    "gn:name":"Lin\u00ebvo",
    "gn:population":0,
    "gn:timezone":"Asia/Yekaterinburg",
    "iso:country":"RU",
    "name:eng_x_preferred":[
        "Lin\u00ebvo"
    ],
    "name:nor_x_preferred":[
        "Lenevo"
    ],
    "name:rus_x_preferred":[
        "\u041b\u0435\u043d\u0435\u0432\u043e"
    ],
    "name:rus_x_variant":[
        "\u041b\u0438\u043d\u0451\u0432\u043e"
    ],
    "wof:name":"Linevo",
    "wof:placetype":"locality"
},
  "geometry": {"coordinates":[63.34694,55.6525],"type":"Point"}
}