{
  "type": "Feature",
  "properties": {
    "gn:admin1_code":"63",
    "gn:asciiname":"Mys Krest",
    "gn:country_code":"RU",
    "gn:dem":111,
    "gn:feature_class":"P",
    "gn:feature_code":"PPL",
    "gn:name":"Mys Krest",
    "gn:population":0,
    "gn:timezone":"Asia/Vladivostok",
    "iso:country":"RU",
    "name:rus_x_preferred":[
        "\u041c\u044b\u0441 \u041a\u0440\u0435\u0441\u0442"
    ],
    "name:und_x_variant":[
        "\u041c\u044b\u0441 \u041a\u0440\u0435\u0441\u0442"
    ],
    "wof:name":"Mys Krest",
    "wof:placetype":"locality"
},
  "geometry": {"coordinates":[135.58333000000002,62.58333],"type":"Point"}
}