{
  "type": "Feature",
  "properties": {
    "gn:admin1_code":"47",
    "gn:asciiname":"Orlovka",
    "gn:country_code":"RU",
    "gn:dem":143,
    "gn:feature_class":"P",
    "gn:feature_code":"PPL",
    "gn:name":"Orlovka",
    "gn:population":0,
    "gn:timezone":"Europe/Moscow",
    "iso:country":"RU",
    "name:rus_x_preferred":[
        "\u041e\u0440\u043b\u043e\u0432\u043a\u0430"
    ],
    "wof:name":"Orlovka",
    "wof:placetype":"locality"
},
  "geometry": {"coordinates":[38.15226,55.87191],"type":"Point"}
}