{
  "type": "Feature",
  "properties": {
    "gn:admin1_code":"91",
    "gn:asciiname":"Shumikha",
    "gn:country_code":"RU",
    "gn:dem":351,
    "gn:feature_class":"P",
    "gn:feature_code":"PPL",
    "gn:name":"Shumikha",
    "gn:population":0,
    "gn:timezone":"Asia/Krasnoyarsk",
    "iso:country":"RU",
    "name:eng_x_preferred":[
        "Shumikha"
    ],
    "name:nor_x_preferred":[
        "Sjumikha"
    ],
    "name:rus_x_preferred":[
        "\u0428\u0443\u043c\u0438\u0445\u0430"
    ],
    "wof:name":"Shumikha",
    "wof:placetype":"locality"
},
  "geometry": {"coordinates":[93.64833,56.32611],"type":"Point"}
}