{
  "type": "Feature",
  "properties": {
    "gn:admin1_code":"33",
    "gn:asciiname":"Knyazevo",
    "gn:country_code":"RU",
    "gn:dem":144,
    "gn:feature_class":"P",
    "gn:feature_code":"PPL",
    "gn:name":"Knyazevo",
    "gn:population":0,
    "gn:timezone":"Europe/Kirov",
    "iso:country":"RU",
    "name:aze_x_preferred":[
        "Knyazev"
    ],
    "name:bak_x_preferred":[
        "\u041a\u043d\u044f\u0437\u0435\u0432"
    ],
    "name:che_x_preferred":[
        "\u041a\u043d\u044f\u0437\u0435\u0432\u043e"
    ],
    "name:hye_x_preferred":[
        "\u053f\u0576\u0575\u0561\u0566\u0587\u0578"
    ],
    "name:kat_x_preferred":[
        "\u10d9\u10dc\u10d8\u10d0\u10d6\u10d4\u10d5\u10dd"
    ],
    "name:kaz_x_preferred":[
        "\u041a\u043d\u044f\u0437"
    ],
    "name:kir_x_preferred":[
        "\u041a\u043d\u044f\u0437"
    ],
    "name:rus_x_preferred":[
        "\u041a\u043d\u044f\u0437\u0435\u0432\u043e"
    ],
    "name:tat_x_preferred":[
        "\u041a\u043d\u044f\u0437\u0435\u0432"
    ],
    "name:ukr_x_preferred":[
        "\u041a\u043d\u044f\u0437\u0435\u0432\u043e"
    ],
    "name:und_x_variant":[
        "\u041a\u043d\u044f\u0437\u0435\u0432\u043e"
    ],
    "wof:name":"Knyazevo",
    "wof:placetype":"locality"
},
  "geometry": {"coordinates":[51.2545,57.6111],"type":"Point"}
}