{
  "type": "Feature",
  "properties": {
    "gn:admin1_code":"71",
    "gn:asciiname":"Yeremina",
    "gn:country_code":"RU",
    "gn:dem":72,
    "gn:feature_class":"P",
    "gn:feature_code":"PPL",
    "gn:name":"Yer\u00ebmina",
    "gn:population":0,
    "gn:timezone":"Asia/Yekaterinburg",
    "iso:country":"RU",
    "name:eng_x_preferred":[
        "Yer\u00ebmina"
    ],
    "name:nor_x_preferred":[
        "Jeremina"
    ],
    "name:rus_x_preferred":[
        "\u0415\u0440\u0435\u043c\u0438\u043d\u0430"
    ],
    "name:rus_x_variant":[
        "\u0415\u0440\u0451\u043c\u0438\u043d\u0430"
    ],
    "name:und_x_variant":[
        "Yer\u00ebmina",
        "\u0415\u0440\u0451\u043c\u0438\u043d\u0430"
    ],
    "wof:name":"Yeremina",
    "wof:placetype":"locality"
},
  "geometry": {"coordinates":[62.80794,57.87392],"type":"Point"}
}