{
  "type": "Feature",
  "properties": {
    "gn:admin1_code":"88",
    "gn:asciiname":"Murakino",
    "gn:country_code":"RU",
    "gn:dem":109,
    "gn:feature_class":"P",
    "gn:feature_code":"PPL",
    "gn:name":"Murakino",
    "gn:population":0,
    "gn:timezone":"Europe/Moscow",
    "iso:country":"RU",
    "name:rus_x_preferred":[
        "\u041c\u0443\u0440\u0430\u043a\u0438\u043d\u043e"
    ],
    "wof:name":"Murakino",
    "wof:placetype":"locality"
},
  "geometry": {"coordinates":[38.4751,57.8563],"type":"Point"}
}