{
  "type": "Feature",
  "properties": {
    "gn:admin1_code":"37",
    "gn:asciiname":"Anfimovo",
    "gn:country_code":"RU",
    "gn:dem":164,
    "gn:feature_class":"P",
    "gn:feature_code":"PPL",
    "gn:name":"Anfimovo",
    "gn:population":0,
    "gn:timezone":"Europe/Moscow",
    "iso:country":"RU",
    "name:rus_x_preferred":[
        "\u0410\u043d\u0444\u0438\u043c\u043e\u0432\u043e"
    ],
    "wof:name":"Anfimovo",
    "wof:placetype":"locality"
},
  "geometry": {"coordinates":[43.2658,58.5068],"type":"Point"}
}