{
  "type": "Feature",
  "properties": {
    "gn:admin1_code":"69",
    "gn:asciiname":"Perevoloch'ye",
    "gn:country_code":"RU",
    "gn:dem":192,
    "gn:feature_class":"P",
    "gn:feature_code":"PPL",
    "gn:name":"Perevoloch\u2019ye",
    "gn:population":0,
    "gn:timezone":"Europe/Moscow",
    "iso:country":"RU",
    "name:eng_x_preferred":[
        "Perevoloch'ye"
    ],
    "name:nor_x_preferred":[
        "Perevolotsje"
    ],
    "name:rus_x_preferred":[
        "\u041f\u0435\u0440\u0435\u0432\u043e\u043b\u043e\u0447\u044c\u0435"
    ],
    "name:und_x_variant":[
        "Perevoloch\u2019ye"
    ],
    "wof:name":"Perevoloch'ye",
    "wof:placetype":"locality"
},
  "geometry": {"coordinates":[31.11911,55.00349],"type":"Point"}
}