{
  "type": "Feature",
  "properties": {
    "gn:admin1_code":"52.0",
    "gn:asciiname":"Cherenchitsy",
    "gn:country_code":"RU",
    "gn:dem":31,
    "gn:feature_class":"P",
    "gn:feature_code":"PPL",
    "gn:name":"Cherenchitsy",
    "gn:population":0,
    "gn:timezone":"Europe/Moscow",
    "iso:country":"RU",
    "name:eng_x_preferred":[
        "Cherenchitsy"
    ],
    "name:nor_x_preferred":[
        "Tsjerentsjitsy"
    ],
    "name:rus_x_preferred":[
        "\u0427\u0435\u0440\u0435\u043d\u0447\u0438\u0446\u044b"
    ],
    "name:und_x_variant":[
        "\u0427\u0435\u0440\u0435\u043d\u0447\u0438\u0446\u044b",
        "Cherenchitsy"
    ],
    "wof:name":"Cherenchitsy",
    "wof:placetype":"locality"
},
  "geometry": {"coordinates":[31.63,57.75389000000001],"type":"Point"}
}