{
  "type": "Feature",
  "properties": {
    "gn:admin1_code":"91",
    "gn:asciiname":"Sharyp",
    "gn:country_code":"RU",
    "gn:dem":362,
    "gn:feature_class":"P",
    "gn:feature_code":"PPL",
    "gn:name":"Sharyp",
    "gn:population":0,
    "gn:timezone":"Asia/Krasnoyarsk",
    "iso:country":"RU",
    "name:rus_x_preferred":[
        "\u0428\u0430\u0440\u044b\u043f"
    ],
    "wof:name":"Sharyp",
    "wof:placetype":"locality"
},
  "geometry": {"coordinates":[91.62528,53.10194],"type":"Point"}
}