{
  "type": "Feature",
  "properties": {
    "gn:admin1_code":"25",
    "gn:asciiname":"Govardova",
    "gn:country_code":"RU",
    "gn:dem":134,
    "gn:feature_class":"P",
    "gn:feature_code":"PPL",
    "gn:name":"Govardova",
    "gn:population":0,
    "gn:timezone":"Europe/Moscow",
    "iso:country":"RU",
    "name:rus_x_preferred":[
        "\u0413\u043e\u0432\u0430\u0440\u0434\u043e\u0432\u0430"
    ],
    "name:und_x_variant":[
        "\u0413\u043e\u0432\u0430\u0440\u0434\u043e\u0432\u0430"
    ],
    "wof:name":"Govardova",
    "wof:placetype":"locality"
},
  "geometry": {"coordinates":[35.94167,54.75666999999999],"type":"Point"}
}