{
  "type": "Feature",
  "properties": {
    "gn:admin1_code":"54",
    "gn:asciiname":"Kazatovo",
    "gn:country_code":"RU",
    "gn:dem":82,
    "gn:feature_class":"P",
    "gn:feature_code":"PPL",
    "gn:name":"Kazatovo",
    "gn:population":0,
    "gn:timezone":"Asia/Omsk",
    "iso:country":"RU",
    "name:eng_x_preferred":[
        "Kazatova"
    ],
    "name:nor_x_preferred":[
        "Kazatovo"
    ],
    "name:rus_x_preferred":[
        "\u041a\u0430\u0437\u0430\u0442\u043e\u0432\u043e"
    ],
    "name:und_x_variant":[
        "Kazatovy"
    ],
    "wof:name":"Kazatovo",
    "wof:placetype":"locality"
},
  "geometry": {"coordinates":[74.26692,56.54816],"type":"Point"}
}