{
  "type": "Feature",
  "properties": {
    "gn:admin1_code":"16",
    "gn:asciiname":"Igorvary",
    "gn:country_code":"RU",
    "gn:dem":156,
    "gn:feature_class":"P",
    "gn:feature_code":"PPL",
    "gn:name":"Igorvary",
    "gn:population":0,
    "gn:timezone":"Europe/Moscow",
    "iso:country":"RU",
    "name:rus_x_preferred":[
        "\u0418\u0433\u043e\u0440\u0432\u0430\u0440\u044b"
    ],
    "name:und_x_variant":[
        "\u0418\u0433\u043e\u0440\u0432\u0430\u0440\u044b"
    ],
    "wof:name":"Igorvary",
    "wof:placetype":"locality"
},
  "geometry": {"coordinates":[47.66362,55.77793000000001],"type":"Point"}
}