{
  "type": "Feature",
  "properties": {
    "gn:admin1_code":"53",
    "gn:asciiname":"Legostayevo",
    "gn:country_code":"RU",
    "gn:dem":141,
    "gn:feature_class":"P",
    "gn:feature_code":"PPL",
    "gn:name":"Legostayevo",
    "gn:population":0,
    "gn:timezone":"Asia/Novosibirsk",
    "iso:country":"RU",
    "name:eng_x_preferred":[
        "Legostayevo"
    ],
    "name:nor_x_preferred":[
        "Legostajevo"
    ],
    "name:rus_x_preferred":[
        "\u041b\u0435\u0433\u043e\u0441\u0442\u0430\u0435\u0432\u043e"
    ],
    "name:und_x_variant":[
        "\u041b\u0435\u0433\u043e\u0441\u0442\u0430\u0435\u0432\u043e",
        "Legostayevo"
    ],
    "wof:name":"Legostayevo",
    "wof:placetype":"locality"
},
  "geometry": {"coordinates":[83.8237,54.6386],"type":"Point"}
}