{
  "type": "Feature",
  "properties": {
    "gn:admin1_code":"91",
    "gn:asciiname":"Kangotovo",
    "gn:cc2":"RU",
    "gn:country_code":"RU",
    "gn:dem":47,
    "gn:feature_class":"P",
    "gn:feature_code":"PPL",
    "gn:name":"Kangotovo",
    "gn:population":0,
    "gn:timezone":"Asia/Krasnoyarsk",
    "iso:country":"RU",
    "name:eng_x_preferred":[
        "Kangotovo"
    ],
    "name:nor_x_preferred":[
        "Kangotovo"
    ],
    "name:rus_x_preferred":[
        "\u041a\u0430\u043d\u0433\u043e\u0442\u043e\u0432\u043e"
    ],
    "name:und_x_variant":[
        "Kangatovo"
    ],
    "wof:name":"Kangotovo",
    "wof:placetype":"locality"
},
  "geometry": {"coordinates":[87.30528000000002,63.445],"type":"Point"}
}