{
  "type": "Feature",
  "properties": {
    "gn:admin1_code":"77.0",
    "gn:asciiname":"Bol'shoye Boryatino",
    "gn:country_code":"RU",
    "gn:dem":256,
    "gn:feature_class":"P",
    "gn:feature_code":"PPL",
    "gn:name":"Bol\u2019shoye Boryatino",
    "gn:population":0,
    "gn:timezone":"Europe/Moscow",
    "iso:country":"RU",
    "name:rus_x_preferred":[
        "\u0411\u043e\u043b\u044c\u0448\u043e\u0435 \u0411\u043e\u0440\u044f\u0442\u0438\u043d\u043e"
    ],
    "name:und_x_variant":[
        "Bol\u2019shoye Boyartino",
        "Bol\u2019shoye Boryatino",
        "\u0411\u043e\u043b\u044c\u0448\u043e\u0435 \u0411\u043e\u0440\u044f\u0442\u0438\u043d\u043e"
    ],
    "wof:name":"Bol'shoye Boryatino",
    "wof:placetype":"locality"
},
  "geometry": {"coordinates":[33.30139,56.03111],"type":"Point"}
}