{
  "type": "Feature",
  "properties": {
    "gn:admin1_code":"90",
    "gn:asciiname":"Lomovka",
    "gn:country_code":"RU",
    "gn:dem":339,
    "gn:feature_class":"P",
    "gn:feature_code":"PPL",
    "gn:name":"Lomovka",
    "gn:population":0,
    "gn:timezone":"Asia/Yekaterinburg",
    "iso:country":"RU",
    "name:rus_x_preferred":[
        "\u041b\u043e\u043c\u043e\u0432\u043a\u0430"
    ],
    "name:und_x_variant":[
        "\u041b\u043e\u043c\u043e\u0432\u043a\u0430"
    ],
    "wof:name":"Lomovka",
    "wof:placetype":"locality"
},
  "geometry": {"coordinates":[58.59328000000001,57.68012],"type":"Point"}
}