{
  "type": "Feature",
  "properties": {
    "gn:admin1_code":"90.0",
    "gn:asciiname":"Ust'-Teles",
    "gn:country_code":"RU",
    "gn:dem":160,
    "gn:feature_class":"P",
    "gn:feature_code":"PPL",
    "gn:name":"Ust\u2019-Tel\u00ebs",
    "gn:population":0,
    "gn:timezone":"Asia/Yekaterinburg",
    "iso:country":"RU",
    "name:rus_x_preferred":[
        "\u0423\u0441\u0442\u044c-\u0422\u0435\u043b\u0451\u0441"
    ],
    "name:und_x_variant":[
        "Ust\u2019-Tel\u00ebs"
    ],
    "wof:name":"Ust'-Teles",
    "wof:placetype":"locality"
},
  "geometry": {"coordinates":[56.76274,56.86122],"type":"Point"}
}