{
  "type": "Feature",
  "properties": {
    "gn:admin1_code":"76",
    "gn:asciiname":"Sudakovo",
    "gn:country_code":"RU",
    "gn:dem":196,
    "gn:feature_class":"P",
    "gn:feature_code":"PPL",
    "gn:name":"Sudakovo",
    "gn:population":0,
    "gn:timezone":"Europe/Moscow",
    "iso:country":"RU",
    "name:rus_x_preferred":[
        "\u0421\u0443\u0434\u0430\u043a\u043e\u0432\u043e"
    ],
    "wof:name":"Sudakovo",
    "wof:placetype":"locality"
},
  "geometry": {"coordinates":[38.75344000000001,53.70638],"type":"Point"}
}