{
  "type": "Feature",
  "properties": {
    "gn:admin1_code":"63",
    "gn:asciiname":"Buor-Khaya",
    "gn:country_code":"RU",
    "gn:dem":14,
    "gn:feature_class":"P",
    "gn:feature_code":"PPL",
    "gn:name":"Buor-Khaya",
    "gn:population":0,
    "gn:timezone":"Asia/Yakutsk",
    "iso:country":"RU",
    "name:eng_x_historical":[
        "Borkhia"
    ],
    "name:eng_x_preferred":[
        "Borkhia"
    ],
    "name:rus_x_preferred":[
        "\u0411\u0443\u043e\u0440-\u0425\u0430\u044f"
    ],
    "wof:name":"Buor-Khaya",
    "wof:placetype":"locality"
},
  "geometry": {"coordinates":[127.80258000000001,72.28655999999999],"type":"Point"}
}