{
  "type": "Feature",
  "properties": {
    "gn:admin1_code":"77",
    "gn:asciiname":"Nipity",
    "gn:country_code":"RU",
    "gn:dem":160,
    "gn:feature_class":"P",
    "gn:feature_code":"PPL",
    "gn:name":"Nipity",
    "gn:population":0,
    "gn:timezone":"Europe/Moscow",
    "iso:country":"RU",
    "name:rus_x_preferred":[
        "\u041d\u0438\u043f\u0438\u0442\u044b"
    ],
    "name:und_x_variant":[
        "Napity",
        "Nipity",
        "\u041d\u0438\u043f\u0438\u0442\u044b"
    ],
    "wof:name":"Nipity",
    "wof:placetype":"locality"
},
  "geometry": {"coordinates":[36.6455,58.26108000000001],"type":"Point"}
}