{
  "type": "Feature",
  "properties": {
    "gn:admin1_code":"85",
    "gn:asciiname":"Podval'ye",
    "gn:country_code":"RU",
    "gn:dem":127,
    "gn:feature_class":"P",
    "gn:feature_code":"PPL",
    "gn:name":"Podval\u2019ye",
    "gn:population":0,
    "gn:timezone":"Europe/Moscow",
    "iso:country":"RU",
    "name:rus_x_preferred":[
        "\u041f\u043e\u0434\u0432\u0430\u043b\u044c\u0435"
    ],
    "name:und_x_variant":[
        "Podval\u2019ye"
    ],
    "wof:name":"Podval'ye",
    "wof:placetype":"locality"
},
  "geometry": {"coordinates":[46.3514,60.3862],"type":"Point"}
}