{
  "type": "Feature",
  "properties": {
    "gn:admin1_code":"53",
    "gn:asciiname":"Novyy Baganenok",
    "gn:country_code":"RU",
    "gn:dem":121,
    "gn:feature_class":"P",
    "gn:feature_code":"PPL",
    "gn:name":"Novyy Bagan\u00ebnok",
    "gn:population":0,
    "gn:timezone":"Asia/Novosibirsk",
    "iso:country":"RU",
    "name:eng_x_preferred":[
        "Novobagan\u00ebnok"
    ],
    "name:nor_x_preferred":[
        "Nov.Baganenok"
    ],
    "name:rus_x_preferred":[
        "\u041d\u043e\u0432.\u0411\u0430\u0433\u0430\u043d\u0435\u043d\u043e\u043a"
    ],
    "name:rus_x_variant":[
        "\u041d\u043e\u0432\u044b\u0439 \u0411\u0430\u0433\u0430\u043d\u0451\u043d\u043e\u043a",
        "\u041d\u043e\u0432\u044b\u0439 \u0411\u0430\u0433\u0430\u043d\u0435\u043d\u043e\u043a"
    ],
    "name:und_x_variant":[
        "Novo-Boganskoye",
        "Novyy Bagan\u00ebnok"
    ],
    "wof:name":"Novyy Baganenok",
    "wof:placetype":"locality"
},
  "geometry": {"coordinates":[78.72686,53.86974],"type":"Point"}
}