{
  "type": "Feature",
  "properties": {
    "gn:admin1_code":"33",
    "gn:asciiname":"Peregoryashchevo",
    "gn:country_code":"RU",
    "gn:dem":141,
    "gn:feature_class":"P",
    "gn:feature_code":"PPL",
    "gn:name":"Peregoryashchevo",
    "gn:population":0,
    "gn:timezone":"Europe/Kirov",
    "iso:country":"RU",
    "name:eng_x_preferred":[
        "Peregoryashchevo"
    ],
    "name:nor_x_preferred":[
        "Peregorjasjtsjevo"
    ],
    "name:rus_x_preferred":[
        "\u041f\u0435\u0440\u0435\u0433\u043e\u0440\u044f\u0449\u0435\u0432\u043e"
    ],
    "name:und_x_variant":[
        "\u041f\u0435\u0440\u0435\u0433\u043e\u0440\u044f\u0449\u0435\u0432\u043e",
        "Peregoryashchevo"
    ],
    "wof:name":"Peregoryashchevo",
    "wof:placetype":"locality"
},
  "geometry": {"coordinates":[46.44821,58.15371999999999],"type":"Point"}
}