{
  "type": "Feature",
  "properties": {
    "gn:admin1_code":"31",
    "gn:asciiname":"Raykov",
    "gn:country_code":"RU",
    "gn:dem":272,
    "gn:feature_class":"P",
    "gn:feature_code":"PPL",
    "gn:name":"Raykov",
    "gn:population":0,
    "gn:timezone":"Asia/Krasnoyarsk",
    "iso:country":"RU",
    "name:eng_x_preferred":[
        "Raykov"
    ],
    "name:nor_x_preferred":[
        "Rajkov"
    ],
    "name:rus_x_preferred":[
        "\u0420\u0430\u0439\u043a\u043e\u0432"
    ],
    "wof:name":"Raykov",
    "wof:placetype":"locality"
},
  "geometry": {"coordinates":[91.17194000000001,53.52166999999999],"type":"Point"}
}