{
  "type": "Feature",
  "properties": {
    "gn:admin1_code":"91",
    "gn:asciiname":"Murty",
    "gn:country_code":"RU",
    "gn:dem":475,
    "gn:feature_class":"P",
    "gn:feature_code":"PPL",
    "gn:name":"Murty",
    "gn:population":0,
    "gn:timezone":"Asia/Krasnoyarsk",
    "iso:country":"RU",
    "name:deu_x_preferred":[
        "Murty"
    ],
    "name:rus_x_preferred":[
        "\u041c\u0443\u0440\u0442\u044b"
    ],
    "wof:name":"Murty",
    "wof:placetype":"locality"
},
  "geometry": {"coordinates":[91.98333,53.78333000000001],"type":"Point"}
}