{
  "type": "Feature",
  "properties": {
    "gn:admin1_code":"8",
    "gn:asciiname":"Sanninskoye",
    "gn:country_code":"RU",
    "gn:dem":206,
    "gn:feature_class":"P",
    "gn:feature_code":"PPL",
    "gn:name":"Sanninskoye",
    "gn:population":0,
    "gn:timezone":"Asia/Yekaterinburg",
    "iso:country":"RU",
    "name:eng_x_preferred":[
        "Sanninskoye"
    ],
    "name:nor_x_preferred":[
        "Sanninskoje"
    ],
    "name:rus_x_preferred":[
        "\u0421\u0430\u043d\u043d\u0438\u043d\u0441\u043a\u043e\u0435"
    ],
    "name:und_x_variant":[
        "Saninskoye",
        "\u0421\u0430\u043d\u043d\u0438\u043d\u0441\u043a\u043e\u0435",
        "Sanninskoye"
    ],
    "wof:name":"Sanninskoye",
    "wof:placetype":"locality"
},
  "geometry": {"coordinates":[56.14193,55.28374],"type":"Point"}
}