{
  "type": "Feature",
  "properties": {
    "gn:admin1_code":"62",
    "gn:asciiname":"Pal'nyye",
    "gn:country_code":"RU",
    "gn:dem":116,
    "gn:feature_class":"P",
    "gn:feature_code":"PPL",
    "gn:name":"Pal\u2019nyye",
    "gn:population":0,
    "gn:timezone":"Europe/Moscow",
    "iso:country":"RU",
    "name:eng_x_preferred":[
        "Pal'nyye"
    ],
    "name:nor_x_preferred":[
        "Palnye"
    ],
    "name:rus_x_preferred":[
        "\u041f\u0430\u043b\u044c\u043d\u044b\u0435"
    ],
    "name:und_x_variant":[
        "Pal\u2019noye",
        "Pal\u2019nyye"
    ],
    "wof:name":"Pal'nyye",
    "wof:placetype":"locality"
},
  "geometry": {"coordinates":[39.2812,54.6126],"type":"Point"}
}