{
  "type": "Feature",
  "properties": {
    "gn:admin1_code":"8",
    "gn:asciiname":"Kyzylga",
    "gn:country_code":"RU",
    "gn:dem":212,
    "gn:feature_class":"P",
    "gn:feature_code":"PPL",
    "gn:name":"Kyzylga",
    "gn:population":0,
    "gn:timezone":"Asia/Yekaterinburg",
    "iso:country":"RU",
    "name:rus_x_preferred":[
        "\u041a\u044b\u0437\u044b\u043b\u0433\u0430"
    ],
    "wof:name":"Kyzylga",
    "wof:placetype":"locality"
},
  "geometry": {"coordinates":[55.4445,54.4114],"type":"Point"}
}