{
  "type": "Feature",
  "properties": {
    "gn:admin1_code":"41.0",
    "gn:asciiname":"Banino",
    "gn:country_code":"RU",
    "gn:dem":204,
    "gn:feature_class":"P",
    "gn:feature_code":"PPL",
    "gn:name":"Banino",
    "gn:population":0,
    "gn:timezone":"Europe/Moscow",
    "iso:country":"RU",
    "name:ceb_x_preferred":[
        "Banino"
    ],
    "name:csb_x_preferred":[
        "Banino"
    ],
    "name:ita_x_preferred":[
        "Banino"
    ],
    "name:nld_x_preferred":[
        "Banino"
    ],
    "name:nor_x_preferred":[
        "Banino"
    ],
    "name:pol_x_preferred":[
        "Banino"
    ],
    "name:rus_x_preferred":[
        "\u0411\u0430\u043d\u0438\u043d\u043e"
    ],
    "name:szl_x_preferred":[
        "Ba\u0144ino"
    ],
    "name:ukr_x_preferred":[
        "\u0411\u0430\u043d\u0456\u043d\u043e"
    ],
    "wof:name":"Banino",
    "wof:placetype":"locality"
},
  "geometry": {"coordinates":[35.93861,52.13889],"type":"Point"}
}