{
  "type": "Feature",
  "properties": {
    "gn:admin1_code":"54",
    "gn:asciiname":"Shefer",
    "gn:country_code":"RU",
    "gn:dem":113,
    "gn:feature_class":"P",
    "gn:feature_code":"PPL",
    "gn:name":"Shefer",
    "gn:population":0,
    "gn:timezone":"Asia/Omsk",
    "iso:country":"RU",
    "name:ces_x_preferred":[
        "\u0160efer"
    ],
    "name:heb_x_preferred":[
        "\u05e9\u05e4\u05e8"
    ],
    "name:nno_x_preferred":[
        "Shefer"
    ],
    "name:pol_x_preferred":[
        "Szefer"
    ],
    "name:rus_x_preferred":[
        "\u0428\u0435\u0444\u0435\u0440"
    ],
    "name:und_x_variant":[
        "Shafer",
        "\u0428\u0430\u0444\u0435\u0440",
        "Shefer",
        "\u0428\u0435\u0444\u0435\u0440"
    ],
    "name:urd_x_preferred":[
        "\u0634\u06cc\u0641\u0631"
    ],
    "wof:name":"Shefer",
    "wof:placetype":"locality"
},
  "geometry": {"coordinates":[72.02015,55.00671],"type":"Point"}
}