{
  "type": "Feature",
  "properties": {
    "gn:admin1_code":"77",
    "gn:asciiname":"Rantsevo",
    "gn:country_code":"RU",
    "gn:dem":257,
    "gn:feature_class":"P",
    "gn:feature_code":"PPL",
    "gn:name":"Rantsevo",
    "gn:population":0,
    "gn:timezone":"Europe/Moscow",
    "iso:country":"RU",
    "name:eng_x_preferred":[
        "Rantsevo"
    ],
    "name:nor_x_preferred":[
        "Rantsevo"
    ],
    "name:rus_x_preferred":[
        "\u0420\u0430\u043d\u0446\u0435\u0432\u043e"
    ],
    "name:und_x_variant":[
        "\u0420\u0430\u043d\u0446\u0435\u0432\u043e",
        "Rantsevo"
    ],
    "wof:name":"Rantsevo",
    "wof:placetype":"locality"
},
  "geometry": {"coordinates":[34.04583,56.94300000000001],"type":"Point"}
}