{
  "type": "Feature",
  "properties": {
    "gn:admin1_code":"76",
    "gn:asciiname":"Sizenevo",
    "gn:country_code":"RU",
    "gn:dem":230,
    "gn:feature_class":"P",
    "gn:feature_code":"PPL",
    "gn:name":"Sizenevo",
    "gn:population":0,
    "gn:timezone":"Europe/Moscow",
    "iso:country":"RU",
    "name:nor_x_preferred":[
        "Sizenevo"
    ],
    "name:rus_x_preferred":[
        "\u0421\u0438\u0437\u0435\u043d\u0435\u0432\u043e"
    ],
    "wof:name":"Sizenevo",
    "wof:placetype":"locality"
},
  "geometry": {"coordinates":[36.85995,54.081],"type":"Point"}
}