{
  "type": "Feature",
  "properties": {
    "gn:admin1_code":"71",
    "gn:asciiname":"Krivoye Ozero",
    "gn:country_code":"RU",
    "gn:dem":95,
    "gn:feature_class":"P",
    "gn:feature_code":"PPL",
    "gn:name":"Krivoye Ozero",
    "gn:population":0,
    "gn:timezone":"Asia/Yekaterinburg",
    "iso:country":"RU",
    "name:rus_x_preferred":[
        "\u041a\u0440\u0438\u0432\u043e\u0435 \u041e\u0437\u0435\u0440\u043e"
    ],
    "wof:name":"Krivoye Ozero",
    "wof:placetype":"locality"
},
  "geometry": {"coordinates":[60.96645,58.83435],"type":"Point"}
}