{
  "type": "Feature",
  "properties": {
    "gn:admin1_code":"51",
    "gn:asciiname":"Kosolapovo",
    "gn:country_code":"RU",
    "gn:dem":128,
    "gn:feature_class":"P",
    "gn:feature_code":"PPL",
    "gn:name":"Kosolapovo",
    "gn:population":0,
    "gn:timezone":"Europe/Moscow",
    "iso:country":"RU",
    "name:rus_x_preferred":[
        "\u041a\u043e\u0441\u043e\u043b\u0430\u043f\u043e\u0432\u043e"
    ],
    "wof:name":"Kosolapovo",
    "wof:placetype":"locality"
},
  "geometry": {"coordinates":[45.79,57.5991],"type":"Point"}
}