{
  "type": "Feature",
  "properties": {
    "gn:admin1_code":"30",
    "gn:asciiname":"Molodezhnyy",
    "gn:country_code":"RU",
    "gn:dem":23,
    "gn:feature_class":"P",
    "gn:feature_code":"PPL",
    "gn:name":"Molod\u00ebzhnyy",
    "gn:population":0,
    "gn:timezone":"Asia/Vladivostok",
    "iso:country":"RU",
    "name:eng_x_preferred":[
        "Molodezhnyy"
    ],
    "name:nor_x_preferred":[
        "Molodezjnyj"
    ],
    "name:rus_x_preferred":[
        "\u041c\u043e\u043b\u043e\u0434\u0435\u0436\u043d\u044b\u0439"
    ],
    "name:und_x_variant":[
        "Molod\u00ebzhnyy"
    ],
    "wof:name":"Molodezhnyy",
    "wof:placetype":"locality"
},
  "geometry": {"coordinates":[136.94936000000001,50.3773],"type":"Point"}
}