{
  "type": "Feature",
  "properties": {
    "gn:admin1_code":"69.0",
    "gn:asciiname":"Fadeyeva Buda",
    "gn:country_code":"RU",
    "gn:dem":216,
    "gn:feature_class":"P",
    "gn:feature_code":"PPL",
    "gn:name":"Fadeyeva Buda",
    "gn:population":0,
    "gn:timezone":"Europe/Moscow",
    "iso:country":"RU",
    "name:rus_x_preferred":[
        "\u0424\u0430\u0434\u0435\u0435\u0432\u0430 \u0411\u0443\u0434\u0430"
    ],
    "wof:name":"Fadeyeva Buda",
    "wof:placetype":"locality"
},
  "geometry": {"coordinates":[32.86667,54.25],"type":"Point"}
}