{
  "type": "Feature",
  "properties": {
    "gn:admin1_code":"62",
    "gn:asciiname":"Lubonos",
    "gn:country_code":"RU",
    "gn:dem":121,
    "gn:feature_class":"P",
    "gn:feature_code":"PPL",
    "gn:name":"Lubonos",
    "gn:population":0,
    "gn:timezone":"Europe/Moscow",
    "iso:country":"RU",
    "name:eng_x_preferred":[
        "Lubonos"
    ],
    "name:nor_x_preferred":[
        "Lubonos"
    ],
    "name:rus_x_preferred":[
        "\u041b\u0443\u0431\u043e\u043d\u043e\u0441"
    ],
    "name:und_x_variant":[
        "Lubono",
        "Lubanos",
        "\u041b\u0443\u0431\u043e\u043d\u043e\u0441",
        "Lubonos"
    ],
    "wof:name":"Lubonos",
    "wof:placetype":"locality"
},
  "geometry": {"coordinates":[41.37561,54.55431],"type":"Point"}
}