{
  "type": "Feature",
  "properties": {
    "gn:admin1_code":"52",
    "gn:asciiname":"Parykhalovo",
    "gn:country_code":"RU",
    "gn:dem":157,
    "gn:feature_class":"P",
    "gn:feature_code":"PPL",
    "gn:name":"Parykhalovo",
    "gn:population":0,
    "gn:timezone":"Europe/Moscow",
    "iso:country":"RU",
    "name:rus_x_preferred":[
        "\u041f\u0430\u0440\u044b\u0445\u0430\u043b\u043e\u0432\u043e"
    ],
    "name:und_x_variant":[
        "\u041f\u0430\u0440\u044b\u0445\u0430\u043b\u043e\u0432\u043e"
    ],
    "wof:name":"Parykhalovo",
    "wof:placetype":"locality"
},
  "geometry": {"coordinates":[32.82202,58.67693000000001],"type":"Point"}
}