{
  "type": "Feature",
  "properties": {
    "gn:admin1_code":"24.0",
    "gn:asciiname":"Blagodatnaya",
    "gn:country_code":"RU",
    "gn:dem":-23,
    "gn:feature_class":"P",
    "gn:feature_code":"PPL",
    "gn:name":"Blagodatnaya",
    "gn:population":0,
    "gn:timezone":"Europe/Moscow",
    "iso:country":"RU",
    "name:rus_x_preferred":[
        "\u0411\u043b\u0430\u0433\u043e\u0434\u0430\u0442\u043d\u0430\u044f"
    ],
    "name:und_x_variant":[
        "\u0411\u043b\u0430\u0433\u043e\u0434\u0430\u0442\u043d\u0430\u044f"
    ],
    "wof:name":"Blagodatnaya",
    "wof:placetype":"locality"
},
  "geometry": {"coordinates":[46.98333,45.45],"type":"Point"}
}