{
  "type": "Feature",
  "properties": {
    "gn:admin1_code":"85.0",
    "gn:asciiname":"Bol'shoye Yurkino",
    "gn:country_code":"RU",
    "gn:dem":177,
    "gn:feature_class":"P",
    "gn:feature_code":"PPL",
    "gn:name":"Bol\u2019shoye Yurkino",
    "gn:population":0,
    "gn:timezone":"Europe/Moscow",
    "iso:country":"RU",
    "name:rus_x_preferred":[
        "\u0411\u043e\u043b\u044c\u0448\u043e\u0435 \u042e\u0440\u043a\u0438\u043d\u043e"
    ],
    "name:und_x_variant":[
        "Bol\u2019shoye Yurkino"
    ],
    "wof:name":"Bol'shoye Yurkino",
    "wof:placetype":"locality"
},
  "geometry": {"coordinates":[41.8491,60.4284],"type":"Point"}
}