{
  "type": "Feature",
  "properties": {
    "gn:admin1_code":"10",
    "gn:asciiname":"Pikurinskiy",
    "gn:country_code":"RU",
    "gn:dem":178,
    "gn:feature_class":"P",
    "gn:feature_code":"PPL",
    "gn:name":"Pikurinskiy",
    "gn:population":0,
    "gn:timezone":"Europe/Moscow",
    "iso:country":"RU",
    "name:rus_x_preferred":[
        "\u041f\u0438\u043a\u0443\u0440\u0438\u043d\u0441\u043a\u0438\u0439"
    ],
    "wof:name":"Pikurinskiy",
    "wof:placetype":"locality"
},
  "geometry": {"coordinates":[33.5562,52.68],"type":"Point"}
}