{
  "type": "Feature",
  "properties": {
    "gn:admin1_code":"47.0",
    "gn:admin2_code":"465636",
    "gn:asciiname":"Alfer'yevo",
    "gn:country_code":"RU",
    "gn:dem":183,
    "gn:feature_class":"P",
    "gn:feature_code":"PPL",
    "gn:name":"Alfer\u2019yevo",
    "gn:population":0,
    "gn:timezone":"Europe/Moscow",
    "iso:country":"RU",
    "name:nor_x_preferred":[
        "Alferjevo"
    ],
    "name:rus_x_preferred":[
        "\u0410\u043b\u0444\u0435\u0440\u044c\u0435\u0432\u043e"
    ],
    "name:und_x_variant":[
        "Alfer\u2019yevo"
    ],
    "wof:name":"Alfer'yevo",
    "wof:placetype":"locality"
},
  "geometry": {"coordinates":[37.93333,56.38333000000001],"type":"Point"}
}