{
  "type": "Feature",
  "properties": {
    "gn:admin1_code":"8.0",
    "gn:asciiname":"Bargata",
    "gn:country_code":"RU",
    "gn:dem":89,
    "gn:feature_class":"P",
    "gn:feature_code":"PPL",
    "gn:name":"Bargata",
    "gn:population":0,
    "gn:timezone":"Asia/Yekaterinburg",
    "iso:country":"RU",
    "name:bak_x_preferred":[
        "\u0411\u0430\u0440\u0493\u0430\u0442\u044b"
    ],
    "name:che_x_preferred":[
        "\u0411\u0430\u0440\u0433\u0430\u0442\u0430"
    ],
    "name:hye_x_preferred":[
        "\u0532\u0561\u0580\u0563\u0561\u057f\u0561"
    ],
    "name:kaz_x_preferred":[
        "\u0411\u0430\u0440\u0433\u0430\u0442\u0430"
    ],
    "name:kir_x_preferred":[
        "\u0411\u0430\u0440\u0433\u0430\u0442\u0430"
    ],
    "name:nor_x_preferred":[
        "Bargata"
    ],
    "name:rus_x_preferred":[
        "\u0411\u0430\u0440\u0433\u0430\u0442\u0430"
    ],
    "name:tat_x_preferred":[
        "\u0411\u043e\u0440\u0433\u0430\u0442\u0430"
    ],
    "wof:name":"Bargata",
    "wof:placetype":"locality"
},
  "geometry": {"coordinates":[55.12468000000001,55.58089],"type":"Point"}
}