{
  "type": "Feature",
  "properties": {
    "gn:admin1_code":"60",
    "gn:asciiname":"Lyadinki",
    "gn:country_code":"RU",
    "gn:dem":99,
    "gn:feature_class":"P",
    "gn:feature_code":"PPL",
    "gn:name":"Lyadinki",
    "gn:population":0,
    "gn:timezone":"Europe/Moscow",
    "iso:country":"RU",
    "name:rus_x_preferred":[
        "\u041b\u044f\u0434\u0438\u043d\u043a\u0438"
    ],
    "name:und_x_variant":[
        "Ledinki",
        "Ladinki",
        "Lyadinki",
        "\u041b\u044f\u0434\u0438\u043d\u043a\u0438"
    ],
    "wof:name":"Lyadinki",
    "wof:placetype":"locality"
},
  "geometry": {"coordinates":[27.8581,56.89855],"type":"Point"}
}