{
  "type": "Feature",
  "properties": {
    "gn:admin1_code":"84",
    "gn:asciiname":"Kuybyshev",
    "gn:country_code":"RU",
    "gn:dem":-6,
    "gn:feature_class":"P",
    "gn:feature_code":"PPL",
    "gn:name":"Kuybyshev",
    "gn:population":0,
    "gn:timezone":"Europe/Volgograd",
    "iso:country":"RU",
    "name:bel_x_preferred":[
        "\u041a\u0443\u0439\u0431\u044b\u0448\u0430\u045e"
    ],
    "name:bul_x_preferred":[
        "\u041a\u0443\u0439\u0431\u0438\u0448\u0435\u0432"
    ],
    "name:cat_x_preferred":[
        "K\u00faibixev"
    ],
    "name:ceb_x_preferred":[
        "Kuybyshev"
    ],
    "name:ces_x_preferred":[
        "Kujby\u0161ev"
    ],
    "name:deu_x_preferred":[
        "Kuibyschew"
    ],
    "name:fin_x_preferred":[
        "Kuiby\u0161ev"
    ],
    "name:fra_x_preferred":[
        "Kou\u00efbychev"
    ],
    "name:heb_x_preferred":[
        "\u05e7\u05d5\u05d9\u05d1\u05d9\u05e9\u05d1"
    ],
    "name:hun_x_preferred":[
        "Kujbisev"
    ],
    "name:ita_x_preferred":[
        "Kujby\u0161ev"
    ],
    "name:jpn_x_preferred":[
        "\u30af\u30a4\u30d3\u30b7\u30a7\u30d5"
    ],
    "name:kat_x_preferred":[
        "\u10d9\u10e3\u10d8\u10d1\u10d8\u10e8\u10d4\u10d5\u10d8"
    ],
    "name:kor_x_preferred":[
        "\ucfe0\uc774\ube44\uc170\ud504"
    ],
    "name:lit_x_preferred":[
        "Kuiby\u0161evas"
    ],
    "name:nld_x_preferred":[
        "Koejbysjev"
    ],
    "name:pol_x_preferred":[
        "Kujbyszew"
    ],
    "name:rus_x_preferred":[
        "\u041a\u0443\u0439\u0431\u044b\u0448\u0435\u0432"
    ],
    "name:slk_x_preferred":[
        "Kujby\u0161ev"
    ],
    "name:slv_x_preferred":[
        "Kujbi\u0161ev"
    ],
    "name:spa_x_preferred":[
        "K\u00faibyshev"
    ],
    "name:swe_x_preferred":[
        "Kuybyshev"
    ],
    "name:ukr_x_preferred":[
        "\u041a\u0443\u0439\u0431\u0438\u0448\u0435\u0432"
    ],
    "name:und_x_variant":[
        "Kuybyshevo",
        "Imeni Kuybysheva"
    ],
    "name:zho_x_preferred":[
        "\u53e4\u6bd4\u96ea\u592b"
    ],
    "wof:name":"Kuybyshev",
    "wof:placetype":"locality"
},
  "geometry": {"coordinates":[44.85315,48.67882],"type":"Point"}
}