{
  "type": "Feature",
  "properties": {
    "gn:admin1_code":"84",
    "gn:asciiname":"Kuybyshev",
    "gn:country_code":"RU",
    "gn:dem":-6,
    "gn:feature_class":"P",
    "gn:feature_code":"PPL",
    "gn:name":"Kuybyshev",
    "gn:population":0,
    "gn:timezone":"Europe/Volgograd",
    "iso:country":"RU",
    "name:rus_x_preferred":[
        "\u041a\u0443\u0439\u0431\u044b\u0448\u0435\u0432"
    ],
    "name:und_x_variant":[
        "Kuybyshevo",
        "Imeni Kuybysheva",
        "Kuybyshev"
    ],
    "wof:name":"Kuybyshev",
    "wof:placetype":"locality"
},
  "geometry": {"coordinates":[44.85315,48.67882],"type":"Point"}
}