{
  "type": "Feature",
  "properties": {
    "gn:admin1_code":"8.0",
    "gn:asciiname":"Bulyak",
    "gn:country_code":"RU",
    "gn:dem":135,
    "gn:feature_class":"P",
    "gn:feature_code":"PPL",
    "gn:name":"Bulyak",
    "gn:population":0,
    "gn:timezone":"Asia/Yekaterinburg",
    "iso:country":"RU",
    "name:rus_x_preferred":[
        "\u0411\u0443\u043b\u044f\u043a"
    ],
    "name:und_x_variant":[
        "\u0411\u0443\u043b\u044f\u043a"
    ],
    "wof:name":"Bulyak",
    "wof:placetype":"locality"
},
  "geometry": {"coordinates":[54.36666999999999,55.11666999999999],"type":"Point"}
}