{
  "type": "Feature",
  "properties": {
    "gn:admin1_code":"60",
    "gn:asciiname":"Derbinka",
    "gn:country_code":"RU",
    "gn:dem":51,
    "gn:feature_class":"P",
    "gn:feature_code":"PPL",
    "gn:name":"Derbinka",
    "gn:population":0,
    "gn:timezone":"Europe/Moscow",
    "iso:country":"RU",
    "name:rus_x_preferred":[
        "\u0414\u0435\u0440\u0431\u0438\u043d\u043a\u0430"
    ],
    "wof:name":"Derbinka",
    "wof:placetype":"locality"
},
  "geometry": {"coordinates":[28.46642,57.55629],"type":"Point"}
}