{
  "type": "Feature",
  "properties": {
    "gn:admin1_code":"9.0",
    "gn:asciiname":"Babichev",
    "gn:country_code":"RU",
    "gn:dem":206,
    "gn:feature_class":"P",
    "gn:feature_code":"PPL",
    "gn:name":"Babichev",
    "gn:population":0,
    "gn:timezone":"Europe/Moscow",
    "iso:country":"RU",
    "name:nor_x_preferred":[
        "Babitsjev"
    ],
    "name:rus_x_preferred":[
        "\u0411\u0430\u0431\u0438\u0447\u0435\u0432"
    ],
    "wof:name":"Babichev",
    "wof:placetype":"locality"
},
  "geometry": {"coordinates":[38.967,50.4624],"type":"Point"}
}