{
  "type": "Feature",
  "properties": {
    "gn:admin1_code":"91",
    "gn:asciiname":"Verkhnyaya Tugusha",
    "gn:country_code":"RU",
    "gn:dem":371,
    "gn:feature_class":"P",
    "gn:feature_code":"PPL",
    "gn:name":"Verkhnyaya Tugusha",
    "gn:population":0,
    "gn:timezone":"Asia/Krasnoyarsk",
    "iso:country":"RU",
    "name:rus_x_preferred":[
        "\u0412\u0435\u0440\u0445\u043d\u044f\u044f \u0422\u0443\u0433\u0443\u0448\u0430"
    ],
    "wof:name":"Verkhnyaya Tugusha",
    "wof:placetype":"locality"
},
  "geometry": {"coordinates":[96.5934,55.8819],"type":"Point"}
}