{
  "type": "Feature",
  "properties": {
    "gn:admin1_code":"60",
    "gn:asciiname":"Groznovo",
    "gn:country_code":"RU",
    "gn:dem":112,
    "gn:feature_class":"P",
    "gn:feature_code":"PPL",
    "gn:name":"Groznovo",
    "gn:population":0,
    "gn:timezone":"Europe/Moscow",
    "iso:country":"RU",
    "name:rus_x_preferred":[
        "\u0413\u0440\u043e\u0437\u043d\u043e\u0432\u043e"
    ],
    "wof:name":"Groznovo",
    "wof:placetype":"locality"
},
  "geometry": {"coordinates":[28.44132,56.86789],"type":"Point"}
}