{
  "type": "Feature",
  "properties": {
    "gn:admin1_code":"6.0",
    "gn:asciiname":"Felovo",
    "gn:country_code":"RU",
    "gn:dem":9,
    "gn:feature_class":"P",
    "gn:feature_code":"PPL",
    "gn:name":"F\u00eblovo",
    "gn:population":0,
    "gn:timezone":"Europe/Moscow",
    "iso:country":"RU",
    "name:rus_x_preferred":[
        "\u0424\u0451\u043b\u043e\u0432\u043e"
    ],
    "name:und_x_variant":[
        "F\u00eblovo",
        "F\u00eblova"
    ],
    "wof:name":"Felovo",
    "wof:placetype":"locality"
},
  "geometry": {"coordinates":[41.9007,63.4984],"type":"Point"}
}