{
  "type": "Feature",
  "properties": {
    "gn:admin1_code":"1",
    "gn:asciiname":"Sovetskiy",
    "gn:country_code":"RU",
    "gn:dem":59,
    "gn:feature_class":"P",
    "gn:feature_code":"PPL",
    "gn:name":"Sovetskiy",
    "gn:population":0,
    "gn:timezone":"Europe/Moscow",
    "iso:country":"RU",
    "wof:name":"Sovetskiy",
    "wof:placetype":"locality"
},
  "geometry": {"coordinates":[39.75,45.03306],"type":"Point"}
}