{
  "type": "Feature",
  "properties": {
    "gn:admin1_code":"69",
    "gn:asciiname":"Parshuki",
    "gn:country_code":"RU",
    "gn:dem":249,
    "gn:feature_class":"P",
    "gn:feature_code":"PPL",
    "gn:name":"Parshuki",
    "gn:population":0,
    "gn:timezone":"Europe/Moscow",
    "iso:country":"RU",
    "name:rus_x_preferred":[
        "\u041f\u0430\u0440\u0448\u0443\u043a\u0438"
    ],
    "wof:name":"Parshuki",
    "wof:placetype":"locality"
},
  "geometry": {"coordinates":[34.09881,55.28738000000001],"type":"Point"}
}