{
  "type": "Feature",
  "properties": {
    "gn:admin1_code":"77",
    "gn:asciiname":"Glinki",
    "gn:country_code":"RU",
    "gn:dem":246,
    "gn:feature_class":"P",
    "gn:feature_code":"PPL",
    "gn:name":"Glinki",
    "gn:population":0,
    "gn:timezone":"Europe/Moscow",
    "iso:country":"RU",
    "name:deu_x_preferred":[
        "Glinki"
    ],
    "name:fra_x_preferred":[
        "Glinki"
    ],
    "name:lit_x_preferred":[
        "Glinkai"
    ],
    "name:pol_x_preferred":[
        "Glinki"
    ],
    "name:rus_x_preferred":[
        "\u0413\u043b\u0438\u043d\u043a\u0438"
    ],
    "name:ukr_x_preferred":[
        "\u0490\u043b\u0456\u043d\u043a\u0456"
    ],
    "name:und_x_variant":[
        "\u0413\u043b\u0438\u043d\u043a\u0438"
    ],
    "wof:name":"Glinki",
    "wof:placetype":"locality"
},
  "geometry": {"coordinates":[33.46111,55.91917],"type":"Point"}
}