{
  "type": "Feature",
  "properties": {
    "gn:admin1_code":"68",
    "gn:asciiname":"Kamunta",
    "gn:country_code":"RU",
    "gn:dem":1836,
    "gn:feature_class":"P",
    "gn:feature_code":"PPL",
    "gn:name":"Kamunta",
    "gn:population":0,
    "gn:timezone":"Europe/Moscow",
    "iso:country":"RU",
    "name:eng_x_preferred":[
        "Kamunta"
    ],
    "name:nor_x_preferred":[
        "Dunta"
    ],
    "name:rus_x_preferred":[
        "\u0414\u0443\u043d\u0442\u0430"
    ],
    "name:rus_x_variant":[
        "\u041a\u0430\u043c\u0443\u043d\u0442\u0430"
    ],
    "name:und_x_variant":[
        "Komunta",
        "Kamenta"
    ],
    "wof:name":"Kamunta",
    "wof:placetype":"locality"
},
  "geometry": {"coordinates":[43.85445,42.90928],"type":"Point"}
}