{
  "type": "Feature",
  "properties": {
    "gn:admin1_code":"52",
    "gn:asciiname":"Podterem'ye",
    "gn:country_code":"RU",
    "gn:dem":41,
    "gn:feature_class":"P",
    "gn:feature_code":"PPL",
    "gn:name":"Podterem\u2019ye",
    "gn:population":0,
    "gn:timezone":"Europe/Moscow",
    "iso:country":"RU",
    "name:rus_x_preferred":[
        "\u041f\u043e\u0434\u0442\u0435\u0440\u0435\u043c\u044c\u0435"
    ],
    "name:und_x_variant":[
        "Podterem\u2019ye",
        "\u041f\u043e\u0434\u0442\u0435\u0440\u0435\u043c\u044c\u0435"
    ],
    "wof:name":"Podterem'ye",
    "wof:placetype":"locality"
},
  "geometry": {"coordinates":[31.03912,58.08034],"type":"Point"}
}