{
  "type": "Feature",
  "properties": {
    "gn:admin1_code":"25",
    "gn:asciiname":"Shchiglevo",
    "gn:country_code":"RU",
    "gn:dem":130,
    "gn:feature_class":"P",
    "gn:feature_code":"PPL",
    "gn:name":"Shchiglevo",
    "gn:population":0,
    "gn:timezone":"Europe/Moscow",
    "iso:country":"RU",
    "name:nor_x_preferred":[
        "Sjtsjiglevo"
    ],
    "name:rus_x_preferred":[
        "\u0429\u0438\u0433\u043b\u0435\u0432\u043e"
    ],
    "name:und_x_variant":[
        "Arsen\u2019yevka",
        "Shchiglevo"
    ],
    "wof:name":"Shchiglevo",
    "wof:placetype":"locality"
},
  "geometry": {"coordinates":[36.87194,54.93743000000001],"type":"Point"}
}