{
  "type": "Feature",
  "properties": {
    "gn:admin1_code":"73",
    "gn:asciiname":"Tavlarovo",
    "gn:country_code":"RU",
    "gn:dem":114,
    "gn:feature_class":"P",
    "gn:feature_code":"PPL",
    "gn:name":"Tavlarovo",
    "gn:population":0,
    "gn:timezone":"Europe/Moscow",
    "iso:country":"RU",
    "name:rus_x_preferred":[
        "\u0422\u0430\u0432\u043b\u0430\u0440\u043e\u0432\u043e"
    ],
    "wof:name":"Tavlarovo",
    "wof:placetype":"locality"
},
  "geometry": {"coordinates":[50.5897,55.6944],"type":"Point"}
}