{
  "type": "Feature",
  "properties": {
    "gn:admin1_code":"55",
    "gn:asciiname":"Podgornyy",
    "gn:country_code":"RU",
    "gn:dem":99,
    "gn:feature_class":"P",
    "gn:feature_code":"PPL",
    "gn:name":"Podgornyy",
    "gn:population":0,
    "gn:timezone":"Asia/Yekaterinburg",
    "iso:country":"RU",
    "name:rus_x_preferred":[
        "\u041f\u043e\u0434\u0433\u043e\u0440\u043d\u044b\u0439"
    ],
    "name:und_x_variant":[
        "\u041f\u043e\u0434\u0433\u043e\u0440\u043d\u044b\u0439"
    ],
    "wof:name":"Podgornyy",
    "wof:placetype":"locality"
},
  "geometry": {"coordinates":[52.508,53.11600000000001],"type":"Point"}
}