{
  "type": "Feature",
  "properties": {
    "gn:admin1_code":"42",
    "gn:asciiname":"Khudanki",
    "gn:country_code":"RU",
    "gn:dem":143,
    "gn:feature_class":"P",
    "gn:feature_code":"PPL",
    "gn:name":"Khudanki",
    "gn:population":0,
    "gn:timezone":"Europe/Moscow",
    "iso:country":"RU",
    "name:nor_x_preferred":[
        "Khudanki"
    ],
    "name:rus_x_preferred":[
        "\u0425\u0443\u0434\u0430\u043d\u043a\u0438"
    ],
    "wof:name":"Khudanki",
    "wof:placetype":"locality"
},
  "geometry": {"coordinates":[29.32513,59.48823],"type":"Point"}
}