{
  "type": "Feature",
  "properties": {
    "gn:admin1_code":"47",
    "gn:asciiname":"Gryaz'",
    "gn:country_code":"RU",
    "gn:dem":144,
    "gn:feature_class":"P",
    "gn:feature_code":"PPL",
    "gn:name":"Gryaz\u2019",
    "gn:population":0,
    "gn:timezone":"Europe/Moscow",
    "iso:country":"RU",
    "name:rus_x_preferred":[
        "\u0413\u0440\u044f\u0437\u044c"
    ],
    "name:und_x_variant":[
        "Gryaz\u2019",
        "\u0413\u0440\u044f\u0437\u044c"
    ],
    "wof:name":"Gryaz'",
    "wof:placetype":"locality"
},
  "geometry": {"coordinates":[36.94134,55.74498000000001],"type":"Point"}
}