{
  "type": "Feature",
  "properties": {
    "gn:admin1_code":"8",
    "gn:asciiname":"Miyakinskaya RTS",
    "gn:country_code":"RU",
    "gn:dem":284,
    "gn:feature_class":"P",
    "gn:feature_code":"PPL",
    "gn:name":"Miyakinskaya RTS",
    "gn:population":0,
    "gn:timezone":"Asia/Yekaterinburg",
    "iso:country":"RU",
    "name:rus_x_preferred":[
        "\u041c\u0438\u044f\u043a\u0438\u043d\u0441\u043a\u0430\u044f \u0420\u0422\u0421"
    ],
    "wof:name":"Miyakinskaya RTS",
    "wof:placetype":"locality"
},
  "geometry": {"coordinates":[54.8129,53.5973],"type":"Point"}
}