{
  "type": "Feature",
  "properties": {
    "gn:gn_country":"RU",
    "gn:gn_fcode":"PPL",
    "gn:gn_pop":0,
    "iso:country":"RU",
    "name:eng_x_preferred":[
        "Moldovka"
    ],
    "name:nor_x_preferred":[
        "Moldovka"
    ],
    "name:rus_x_preferred":[
        "\u041c\u043e\u043b\u0434\u043e\u0432\u043a\u0430"
    ],
    "name:unk_x_variant":[
        "Moldavka"
    ],
    "qs_pg:aaroncc":"RU",
    "qs_pg:gn_country":"RU",
    "qs_pg:gn_fcode":"PPL",
    "qs_pg:gn_pop":0,
    "qs_pg:name":"Moldovka",
    "qs_pg:name_adm0":"Russia",
    "qs_pg:name_adm1":"Krasnodar Krai",
    "qs_pg:photos":63,
    "qs_pg:photos_1k":13,
    "qs_pg:photos_9k":1,
    "qs_pg:photos_9r":2,
    "qs_pg:photos_all":63,
    "qs_pg:photos_sr":2,
    "qs_pg:pop_sr":0,
    "qs_pg:qs_pg_placetype":"locality",
    "qs_pg:qs_pg_placetype_gp":"Town",
    "qs_pg:woe_adm0":23424936,
    "woe:adm0_id":23424936,
    "woe:name_adm0":"Russia",
    "woe:name_adm1":"Krasnodar Krai",
    "woe:placetype":"Town",
    "wof:name":"Moldovka",
    "wof:placetype":"locality"
},
  "geometry": {"coordinates":[39.94167,43.44889],"type":"Point"}
}