{
  "type": "Feature",
  "properties": {
    "gn:admin1_code":"38.0",
    "gn:asciiname":"Dolmeny",
    "gn:country_code":"RU",
    "gn:dem":305,
    "gn:feature_class":"P",
    "gn:feature_code":"PPL",
    "gn:name":"Dolmeny",
    "gn:population":0,
    "gn:timezone":"Europe/Moscow",
    "iso:country":"RU",
    "name:rus_x_preferred":[
        "\u0414\u043e\u043b\u043c\u0435\u043d\u044b"
    ],
    "name:und_x_variant":[
        "\u0414\u043e\u043b\u043c\u0435\u043d\u044b"
    ],
    "wof:name":"Dolmeny",
    "wof:placetype":"locality"
},
  "geometry": {"coordinates":[38.37917,44.7375],"type":"Point"}
}