{
  "type": "Feature",
  "properties": {
    "gn:admin1_code":"85",
    "gn:asciiname":"Podlip'ye",
    "gn:country_code":"RU",
    "gn:dem":155,
    "gn:feature_class":"P",
    "gn:feature_code":"PPL",
    "gn:name":"Podlip\u2019ye",
    "gn:population":0,
    "gn:timezone":"Europe/Moscow",
    "iso:country":"RU",
    "name:rus_x_preferred":[
        "\u041f\u043e\u0434\u043b\u0438\u043f\u044c\u0435"
    ],
    "name:und_x_variant":[
        "Podlip\u2019ye"
    ],
    "wof:name":"Podlip'ye",
    "wof:placetype":"locality"
},
  "geometry": {"coordinates":[35.23146,58.82141],"type":"Point"}
}