{
  "type": "Feature",
  "properties": {
    "gn:admin1_code":"71",
    "gn:asciiname":"Nizhniy Katarach",
    "gn:country_code":"RU",
    "gn:dem":117,
    "gn:feature_class":"P",
    "gn:feature_code":"PPL",
    "gn:name":"Nizhniy Katarach",
    "gn:population":0,
    "gn:timezone":"Asia/Yekaterinburg",
    "iso:country":"RU",
    "name:eng_x_preferred":[
        "Nizhniy Katarach"
    ],
    "name:nor_x_preferred":[
        "Nizj.Kataratsj"
    ],
    "name:rus_x_preferred":[
        "\u041d\u0438\u0436.\u041a\u0430\u0442\u0430\u0440\u0430\u0447"
    ],
    "name:rus_x_variant":[
        "\u041d\u0438\u0436\u043d\u0438\u0439 \u041a\u0430\u0442\u0430\u0440\u0430\u0447"
    ],
    "name:und_x_variant":[
        "\u041d\u0438\u0436\u043d\u0438\u0439 \u041a\u0430\u0442\u0430\u0440\u0430\u0447"
    ],
    "wof:name":"Nizhniy Katarach",
    "wof:placetype":"locality"
},
  "geometry": {"coordinates":[64.10129999999999,56.6455],"type":"Point"}
}