{
  "type": "Feature",
  "properties": {
    "gn:admin1_code":"21",
    "gn:asciiname":"Tol'kovo",
    "gn:country_code":"RU",
    "gn:dem":120,
    "gn:feature_class":"P",
    "gn:feature_code":"PPL",
    "gn:name":"Tol\u2019kovo",
    "gn:population":0,
    "gn:timezone":"Europe/Moscow",
    "iso:country":"RU",
    "name:und_x_variant":[
        "Tol\u2019kova",
        "Tol\u2019nova",
        "Tol\u2019kovo"
    ],
    "wof:name":"Tol'kovo",
    "wof:placetype":"locality"
},
  "geometry": {"coordinates":[41.96276,57.24076],"type":"Point"}
}