{
  "type": "Feature",
  "properties": {
    "gn:admin1_code":"91",
    "gn:asciiname":"Nalobino",
    "gn:country_code":"RU",
    "gn:dem":218,
    "gn:feature_class":"P",
    "gn:feature_code":"PPL",
    "gn:name":"Nalobino",
    "gn:population":0,
    "gn:timezone":"Asia/Krasnoyarsk",
    "iso:country":"RU",
    "name:rus_x_preferred":[
        "\u041d\u0430\u043b\u043e\u0431\u0438\u043d\u043e"
    ],
    "name:und_x_variant":[
        "Nalobina",
        "Nalobino"
    ],
    "wof:name":"Nalobino",
    "wof:placetype":"locality"
},
  "geometry": {"coordinates":[94.6901,55.907],"type":"Point"}
}