{
  "type": "Feature",
  "properties": {
    "gn:admin1_code":"85",
    "gn:asciiname":"Uspen'ye",
    "gn:country_code":"RU",
    "gn:dem":139,
    "gn:feature_class":"P",
    "gn:feature_code":"PPL",
    "gn:name":"Uspen\u2019ye",
    "gn:population":0,
    "gn:timezone":"Europe/Moscow",
    "iso:country":"RU",
    "name:eng_x_preferred":[
        "Uspen'ye"
    ],
    "name:nor_x_preferred":[
        "Uspenje"
    ],
    "name:rus_x_preferred":[
        "\u0423\u0441\u043f\u0435\u043d\u044c\u0435"
    ],
    "name:und_x_variant":[
        "Tol\u2019shemskiy-Uspenskiy",
        "Uspen\u2019ye"
    ],
    "wof:name":"Uspen'ye",
    "wof:placetype":"locality"
},
  "geometry": {"coordinates":[42.78247,59.40314],"type":"Point"}
}