{
  "type": "Feature",
  "properties": {
    "gn:admin1_code":"29",
    "gn:asciiname":"Malyye Uzuntsy",
    "gn:country_code":"RU",
    "gn:dem":338,
    "gn:feature_class":"P",
    "gn:feature_code":"PPL",
    "gn:name":"Malyye Uzuntsy",
    "gn:population":0,
    "gn:timezone":"Asia/Novokuznetsk",
    "iso:country":"RU",
    "name:rus_x_preferred":[
        "\u041c\u0430\u043b\u044b\u0435 \u0423\u0437\u0443\u043d\u0446\u044b"
    ],
    "wof:name":"Malyye Uzuntsy",
    "wof:placetype":"locality"
},
  "geometry": {"coordinates":[87.6768,53.9496],"type":"Point"}
}