{
  "type": "Feature",
  "properties": {
    "gn:admin1_code":"69.0",
    "gn:asciiname":"Bortenevo",
    "gn:cc2":"RU",
    "gn:country_code":"RU",
    "gn:dem":218,
    "gn:feature_class":"P",
    "gn:feature_code":"PPL",
    "gn:name":"Bortenevo",
    "gn:population":0,
    "gn:timezone":"Europe/Moscow",
    "iso:country":"RU",
    "name:rus_x_preferred":[
        "\u0411\u043e\u0440\u0442\u0435\u043d\u0435\u0432\u043e"
    ],
    "name:und_x_variant":[
        "Borten\u2019yevo",
        "Bortenevo",
        "\u0411\u043e\u0440\u0442\u0435\u043d\u0435\u0432\u043e"
    ],
    "wof:name":"Bortenevo",
    "wof:placetype":"locality"
},
  "geometry": {"coordinates":[33.35,55.23333],"type":"Point"}
}