{
  "type": "Feature",
  "properties": {
    "gn:admin1_code":"40",
    "gn:asciiname":"Bukharinka",
    "gn:country_code":"RU",
    "gn:dem":123,
    "gn:feature_class":"P",
    "gn:feature_code":"PPL",
    "gn:name":"Bukharinka",
    "gn:population":0,
    "gn:timezone":"Asia/Yekaterinburg",
    "iso:country":"RU",
    "name:rus_x_preferred":[
        "\u0411\u0443\u0445\u0430\u0440\u0438\u043d\u043a\u0430"
    ],
    "wof:name":"Bukharinka",
    "wof:placetype":"locality"
},
  "geometry": {"coordinates":[63.78333000000001,54.48889000000001],"type":"Point"}
}