{
  "type": "Feature",
  "properties": {
    "gn:admin1_code":"56.0",
    "gn:asciiname":"Darishchi",
    "gn:country_code":"RU",
    "gn:dem":268,
    "gn:feature_class":"P",
    "gn:feature_code":"PPL",
    "gn:name":"Darishchi",
    "gn:population":0,
    "gn:timezone":"Europe/Moscow",
    "iso:country":"RU",
    "name:rus_x_preferred":[
        "\u0414\u0430\u0440\u0438\u0449\u0438"
    ],
    "name:und_x_variant":[
        "\u0414\u0430\u0440\u0438\u0449\u0438"
    ],
    "wof:name":"Darishchi",
    "wof:placetype":"locality"
},
  "geometry": {"coordinates":[37.7157,52.97501],"type":"Point"}
}