{
  "type": "Feature",
  "properties": {
    "gn:admin1_code":"47",
    "gn:asciiname":"Serednikovo",
    "gn:country_code":"RU",
    "gn:dem":192,
    "gn:feature_class":"P",
    "gn:feature_code":"PPL",
    "gn:name":"Serednikovo",
    "gn:population":103,
    "gn:timezone":"Europe/Moscow",
    "iso:country":"RU",
    "name:rus_x_preferred":[
        "\u0421\u0435\u0440\u0435\u0434\u043d\u0438\u043a\u043e\u0432\u043e"
    ],
    "name:und_x_variant":[
        "Srednikovo"
    ],
    "wof:name":"Serednikovo",
    "wof:placetype":"locality",
    "wof:population":103
},
  "geometry": {"coordinates":[37.22451,55.93307],"type":"Point"}
}