{
  "type": "Feature",
  "properties": {
    "gn:admin1_code":"25.0",
    "gn:asciiname":"Bogdanino",
    "gn:country_code":"RU",
    "gn:dem":202,
    "gn:feature_class":"P",
    "gn:feature_code":"PPL",
    "gn:name":"Bogdanino",
    "gn:population":0,
    "gn:timezone":"Europe/Moscow",
    "iso:country":"RU",
    "name:nor_x_preferred":[
        "Bogdanino"
    ],
    "name:rus_x_preferred":[
        "\u0411\u043e\u0433\u0434\u0430\u043d\u0438\u043d\u043e"
    ],
    "wof:name":"Bogdanino",
    "wof:placetype":"locality"
},
  "geometry": {"coordinates":[36.85555,54.40276],"type":"Point"}
}