{
  "type": "Feature",
  "properties": {
    "gn:admin1_code":"23",
    "gn:asciiname":"Vzmor'ye",
    "gn:country_code":"RU",
    "gn:dem":2,
    "gn:feature_class":"P",
    "gn:feature_code":"PPL",
    "gn:name":"Vzmor\u2019ye",
    "gn:population":0,
    "gn:timezone":"Europe/Kaliningrad",
    "iso:country":"RU",
    "name:eng_x_preferred":[
        "Vzmor'ye"
    ],
    "name:nor_x_preferred":[
        "Vzmorje"
    ],
    "name:rus_x_preferred":[
        "\u0412\u0437\u043c\u043e\u0440\u044c\u0435"
    ],
    "name:und_x_variant":[
        "Grossheidekrug",
        "Gross-Heydekrug",
        "Grobheiderkrug",
        "Gross Khaydekrug",
        "Gros-Kheydekrug",
        "Vzmor\u2019ye"
    ],
    "wof:name":"Vzmor'ye",
    "wof:placetype":"locality"
},
  "geometry": {"coordinates":[20.24758,54.69807],"type":"Point"}
}