{
  "type": "Feature",
  "properties": {
    "gn:admin1_code":"76",
    "gn:asciiname":"Alekhino",
    "gn:country_code":"RU",
    "gn:dem":236,
    "gn:feature_class":"P",
    "gn:feature_code":"PPL",
    "gn:name":"Alekhino",
    "gn:population":0,
    "gn:timezone":"Europe/Moscow",
    "iso:country":"RU",
    "name:nor_x_preferred":[
        "Alekhino"
    ],
    "name:rus_x_preferred":[
        "\u0410\u043b\u0435\u0445\u0438\u043d\u043e"
    ],
    "wof:name":"Alekhino",
    "wof:placetype":"locality"
},
  "geometry": {"coordinates":[36.75376,53.82994],"type":"Point"}
}