{
  "type": "Feature",
  "properties": {
    "gn:admin1_code":"29",
    "gn:asciiname":"Sarsaz",
    "gn:country_code":"RU",
    "gn:dem":171,
    "gn:feature_class":"P",
    "gn:feature_code":"PPL",
    "gn:name":"Sarsaz",
    "gn:population":0,
    "gn:timezone":"Asia/Novokuznetsk",
    "iso:country":"RU",
    "name:bak_x_preferred":[
        "\u04ba\u0430\u0440\u044b\u04bb\u0430\u0499"
    ],
    "name:che_x_preferred":[
        "\u0421\u0430\u0440\u0441\u0430\u0437"
    ],
    "name:eng_x_preferred":[
        "Sarsaz"
    ],
    "name:hye_x_preferred":[
        "\u054d\u0561\u0580\u057d\u0561\u0566"
    ],
    "name:kaz_x_preferred":[
        "\u0421\u0430\u0440\u0441\u0430\u0437"
    ],
    "name:kir_x_preferred":[
        "\u0421\u0430\u0440\u0441\u0430\u0437"
    ],
    "name:nor_x_preferred":[
        "Sarsaz"
    ],
    "name:rus_x_preferred":[
        "\u0421\u0430\u0440\u0441\u0430\u0437"
    ],
    "name:tat_x_preferred":[
        "\u0421\u0430\u0440\u0441\u0430\u0437"
    ],
    "wof:name":"Sarsaz",
    "wof:placetype":"locality"
},
  "geometry": {"coordinates":[84.82971999999999,55.68972],"type":"Point"}
}