{
  "type": "Feature",
  "properties": {
    "gn:admin1_code":"6.0",
    "gn:asciiname":"Isakogorka",
    "gn:country_code":"RU",
    "gn:dem":15,
    "gn:feature_class":"P",
    "gn:feature_code":"PPL",
    "gn:name":"Isakogorka",
    "gn:population":28571,
    "gn:timezone":"Europe/Moscow",
    "iso:country":"RU",
    "name:rus_x_preferred":[
        "\u0418\u0441\u0430\u043a\u043e\u0433\u043e\u0440\u043a\u0430"
    ],
    "wof:name":"Isakogorka",
    "wof:placetype":"locality",
    "wof:population":28571
},
  "geometry": {"coordinates":[40.6531,64.446],"type":"Point"}
}