{
  "type": "Feature",
  "properties": {
    "gn:admin1_code":"77",
    "gn:asciiname":"Bochkovo",
    "gn:country_code":"RU",
    "gn:dem":234,
    "gn:feature_class":"P",
    "gn:feature_code":"PPL",
    "gn:name":"Bochkovo",
    "gn:population":0,
    "gn:timezone":"Europe/Moscow",
    "iso:country":"RU",
    "name:rus_x_preferred":[
        "\u0411\u043e\u0447\u043a\u043e\u0432\u043e"
    ],
    "name:und_x_variant":[
        "\u0411\u043e\u0447\u043a\u043e\u0432\u043e"
    ],
    "wof:name":"Bochkovo",
    "wof:placetype":"locality"
},
  "geometry": {"coordinates":[33.61162,56.40561],"type":"Point"}
}