{
  "type": "Feature",
  "properties": {
    "gn:admin1_code":"05",
    "gn:asciiname":"Bomnak",
    "gn:country_code":"RU",
    "gn:dem":331,
    "gn:feature_class":"P",
    "gn:feature_code":"PPL",
    "gn:name":"Bomnak",
    "gn:population":0,
    "gn:timezone":"Asia/Yakutsk",
    "iso:country":"RU",
    "name:eng_x_preferred":[
        "Bomnak"
    ],
    "name:nor_x_preferred":[
        "Bomnak"
    ],
    "name:rus_x_preferred":[
        "\u0411\u043e\u043c\u043d\u0430\u043a"
    ],
    "name:und_x_variant":[
        "Bamnak",
        "Bomnakskiy",
        "Buomnaakh",
        "Buomnakh",
        "\u0411\u043e\u043c\u043d\u0430\u043a",
        "Bomnak"
    ],
    "wof:name":"Bomnak",
    "wof:placetype":"locality"
},
  "geometry": {"coordinates":[128.84773999999999,54.70923000000001],"type":"Point"}
}