{
  "type": "Feature",
  "properties": {
    "gn:admin1_code":"6",
    "gn:asciiname":"Orekhovshchina",
    "gn:country_code":"RU",
    "gn:dem":46,
    "gn:feature_class":"P",
    "gn:feature_code":"PPL",
    "gn:name":"Orekhovshchina",
    "gn:population":0,
    "gn:timezone":"Europe/Moscow",
    "iso:country":"RU",
    "name:rus_x_preferred":[
        "\u041e\u0440\u0435\u0445\u043e\u0432\u0449\u0438\u043d\u0430"
    ],
    "wof:name":"Orekhovshchina",
    "wof:placetype":"locality"
},
  "geometry": {"coordinates":[43.51667,64.96666999999999],"type":"Point"}
}