{
  "type": "Feature",
  "properties": {
    "gn:admin1_code":"15",
    "gn:asciiname":"Zapadnyy",
    "gn:country_code":"RU",
    "gn:dem":-9999,
    "gn:feature_class":"P",
    "gn:feature_code":"PPL",
    "gn:name":"Zapadnyy",
    "gn:population":0,
    "gn:timezone":"Asia/Anadyr",
    "iso:country":"RU",
    "name:eng_x_preferred":[
        "Zapadnyy"
    ],
    "name:nor_x_preferred":[
        "Zapadnyj"
    ],
    "name:rus_x_preferred":[
        "\u0417\u0430\u043f\u0430\u0434\u043d\u044b\u0439"
    ],
    "name:und_x_variant":[
        "Pervyy",
        "Zapadnyy"
    ],
    "wof:name":"Zapadnyy",
    "wof:placetype":"locality"
},
  "geometry": {"coordinates":[170.59710000000001,69.58946],"type":"Point"}
}