{
  "type": "Feature",
  "properties": {
    "gn:admin1_code":"77",
    "gn:asciiname":"Kuchino",
    "gn:country_code":"RU",
    "gn:dem":240,
    "gn:feature_class":"P",
    "gn:feature_code":"PPL",
    "gn:name":"Kuchino",
    "gn:population":0,
    "gn:timezone":"Europe/Moscow",
    "iso:country":"RU",
    "name:eng_x_preferred":[
        "Kuchino"
    ],
    "name:nor_x_preferred":[
        "Kutsjino"
    ],
    "name:rus_x_preferred":[
        "\u041a\u0443\u0447\u0438\u043d\u043e"
    ],
    "name:und_x_variant":[
        "Kuchina",
        "\u041a\u0443\u0447\u0438\u043d\u043e",
        "Kuchino"
    ],
    "wof:name":"Kuchino",
    "wof:placetype":"locality"
},
  "geometry": {"coordinates":[35.15455,55.98986],"type":"Point"}
}