{
  "type": "Feature",
  "properties": {
    "gn:admin1_code":"70",
    "gn:asciiname":"Trudovoye",
    "gn:cc2":"RU",
    "gn:country_code":"RU",
    "gn:dem":190,
    "gn:feature_class":"P",
    "gn:feature_code":"PPL",
    "gn:name":"Trudovoye",
    "gn:population":0,
    "gn:timezone":"Europe/Moscow",
    "iso:country":"RU",
    "name:und_x_variant":[
        "Veytsenfel\u2019d",
        "Trudovoye"
    ],
    "wof:name":"Trudovoye",
    "wof:placetype":"locality"
},
  "geometry": {"coordinates":[44.33167,44.06944],"type":"Point"}
}