{
  "type": "Feature",
  "properties": {
    "gn:admin1_code":"72",
    "gn:asciiname":"Novoye Yumatovo",
    "gn:country_code":"RU",
    "gn:dem":167,
    "gn:feature_class":"P",
    "gn:feature_code":"PPL",
    "gn:name":"Novoye Yumatovo",
    "gn:population":0,
    "gn:timezone":"Europe/Moscow",
    "iso:country":"RU",
    "name:rus_x_preferred":[
        "\u041d\u043e\u0432\u043e\u0435 \u042e\u043c\u0430\u0442\u043e\u0432\u043e"
    ],
    "wof:name":"Novoye Yumatovo",
    "wof:placetype":"locality"
},
  "geometry": {"coordinates":[41.23511,52.59562],"type":"Point"}
}