{
  "type": "Feature",
  "properties": {
    "gn:admin1_code":"38",
    "gn:asciiname":"Smelyy",
    "gn:country_code":"RU",
    "gn:dem":25,
    "gn:feature_class":"P",
    "gn:feature_code":"PPL",
    "gn:name":"Smelyy",
    "gn:population":0,
    "gn:timezone":"Europe/Moscow",
    "iso:country":"RU",
    "name:rus_x_preferred":[
        "\u0421\u043c\u0435\u043b\u044b\u0439"
    ],
    "name:und_x_variant":[
        "Smely",
        "Smelyy"
    ],
    "wof:name":"Smelyy",
    "wof:placetype":"locality"
},
  "geometry": {"coordinates":[39.55057,46.24268],"type":"Point"}
}