{
  "type": "Feature",
  "properties": {
    "gn:admin1_code":"65",
    "gn:asciiname":"Oktyabr'sk",
    "gn:country_code":"RU",
    "gn:dem":48,
    "gn:feature_class":"P",
    "gn:feature_code":"PPL",
    "gn:name":"Oktyabr\u2019sk",
    "gn:population":0,
    "gn:timezone":"Europe/Samara",
    "iso:country":"RU",
    "name:rus_x_preferred":[
        "Oktyabr\u2019sk"
    ],
    "name:rus_x_variant":[
        "\u041e\u043a\u0442\u044f\u0431\u0440\u044c\u0441\u043a",
        "Krasnyy Oktyabr\u2019"
    ],
    "name:und_x_variant":[
        "Krasny Oktyabr\u2019",
        "Krasnyy Oktyabr\u2019"
    ],
    "wof:name":"Oktyabr'sk",
    "wof:placetype":"locality"
},
  "geometry": {"coordinates":[48.8791,53.1998],"type":"Point"}
}