{
  "type": "Feature",
  "properties": {
    "gn:admin1_code":"77",
    "gn:asciiname":"Razmorskoye",
    "gn:country_code":"RU",
    "gn:dem":158,
    "gn:feature_class":"P",
    "gn:feature_code":"PPL",
    "gn:name":"Razmorskoye",
    "gn:population":0,
    "gn:timezone":"Europe/Moscow",
    "iso:country":"RU",
    "name:rus_x_preferred":[
        "\u0420\u0430\u0437\u043c\u043e\u0440\u0441\u043a\u043e\u0435"
    ],
    "name:und_x_variant":[
        "\u0420\u0430\u0437\u043c\u043e\u0440\u0441\u043a\u043e\u0435"
    ],
    "wof:name":"Razmorskoye",
    "wof:placetype":"locality"
},
  "geometry": {"coordinates":[36.4775,57.5758],"type":"Point"}
}