{
  "type": "Feature",
  "properties": {
    "gn:admin1_code":"52",
    "gn:asciiname":"Yershino",
    "gn:country_code":"RU",
    "gn:dem":33,
    "gn:feature_class":"P",
    "gn:feature_code":"PPL",
    "gn:name":"Yershino",
    "gn:population":0,
    "gn:timezone":"Europe/Moscow",
    "iso:country":"RU",
    "name:rus_x_preferred":[
        "\u0415\u0440\u0448\u0438\u043d\u043e"
    ],
    "name:und_x_variant":[
        "\u0415\u0440\u0448\u0438\u043d\u043e"
    ],
    "wof:name":"Yershino",
    "wof:placetype":"locality"
},
  "geometry": {"coordinates":[31.6449,57.87761],"type":"Point"}
}