{
  "type": "Feature",
  "properties": {
    "gn:admin1_code":"41.0",
    "gn:asciiname":"Koptevo",
    "gn:country_code":"RU",
    "gn:dem":162,
    "gn:feature_class":"P",
    "gn:feature_code":"PPL",
    "gn:name":"Koptevo",
    "gn:population":0,
    "gn:timezone":"Europe/Moscow",
    "iso:country":"RU",
    "name:rus_x_preferred":[
        "\u041a\u043e\u043f\u0442\u0435\u0432\u043e"
    ],
    "wof:name":"Koptevo",
    "wof:placetype":"locality"
},
  "geometry": {"coordinates":[36.03291,51.17658],"type":"Point"}
}