{
  "type": "Feature",
  "properties": {
    "gn:admin1_code":"30",
    "gn:asciiname":"Samurskiy",
    "gn:country_code":"RU",
    "gn:dem":118,
    "gn:feature_class":"P",
    "gn:feature_code":"PPL",
    "gn:name":"Samurskiy",
    "gn:population":0,
    "gn:timezone":"Asia/Vladivostok",
    "iso:country":"RU",
    "name:rus_x_preferred":[
        "\u0421\u0430\u043c\u0443\u0440\u0441\u043a\u0438\u0439"
    ],
    "wof:name":"Samurskiy",
    "wof:placetype":"locality"
},
  "geometry": {"coordinates":[134.11667,46.73333],"type":"Point"}
}