{
  "type": "Feature",
  "properties": {
    "gn:admin1_code":"45",
    "gn:asciiname":"Oshlamuchash",
    "gn:country_code":"RU",
    "gn:dem":123,
    "gn:feature_class":"P",
    "gn:feature_code":"PPL",
    "gn:name":"Oshlamuchash",
    "gn:population":0,
    "gn:timezone":"Europe/Moscow",
    "iso:country":"RU",
    "name:rus_x_preferred":[
        "\u041e\u0448\u043b\u0430\u043c\u0443\u0447\u0430\u0448"
    ],
    "wof:name":"Oshlamuchash",
    "wof:placetype":"locality"
},
  "geometry": {"coordinates":[47.77268,56.8133],"type":"Point"}
}