{
  "type": "Feature",
  "properties": {
    "gn:admin1_code":"37",
    "gn:asciiname":"Durtsovo",
    "gn:country_code":"RU",
    "gn:dem":153,
    "gn:feature_class":"P",
    "gn:feature_code":"PPL",
    "gn:name":"Durtsovo",
    "gn:population":0,
    "gn:timezone":"Europe/Moscow",
    "iso:country":"RU",
    "name:rus_x_preferred":[
        "\u0414\u0443\u0440\u0446\u043e\u0432\u043e"
    ],
    "name:und_x_variant":[
        "\u0414\u0443\u0440\u0446\u043e\u0432\u043e"
    ],
    "wof:name":"Durtsovo",
    "wof:placetype":"locality"
},
  "geometry": {"coordinates":[42.0625,58.1998],"type":"Point"}
}