{
  "type": "Feature",
  "properties": {
    "gn:admin1_code":"65",
    "gn:asciiname":"Novozaborovskiy",
    "gn:country_code":"RU",
    "gn:dem":123,
    "gn:feature_class":"P",
    "gn:feature_code":"PPL",
    "gn:name":"Novozaborovskiy",
    "gn:population":0,
    "gn:timezone":"Europe/Samara",
    "iso:country":"RU",
    "name:rus_x_preferred":[
        "\u041d\u043e\u0432\u043e\u0437\u0430\u0431\u043e\u0440\u043e\u0432\u0441\u043a\u0438\u0439"
    ],
    "wof:name":"Novozaborovskiy",
    "wof:placetype":"locality"
},
  "geometry": {"coordinates":[48.3484,53.1839],"type":"Point"}
}