{
  "type": "Feature",
  "properties": {
    "gn:admin1_code":"10",
    "gn:asciiname":"Sytaya Buda",
    "gn:country_code":"RU",
    "gn:dem":174,
    "gn:feature_class":"P",
    "gn:feature_code":"PPL",
    "gn:name":"Sytaya Buda",
    "gn:population":0,
    "gn:timezone":"Europe/Moscow",
    "iso:country":"RU",
    "name:rus_x_preferred":[
        "\u0421\u044b\u0442\u0430\u044f \u0411\u0443\u0434\u0430"
    ],
    "wof:name":"Sytaya Buda",
    "wof:placetype":"locality"
},
  "geometry": {"coordinates":[32.25158,52.48313],"type":"Point"}
}