{
  "type": "Feature",
  "properties": {
    "gn:admin1_code":"75",
    "gn:asciiname":"Chiginy",
    "gn:country_code":"RU",
    "gn:dem":80,
    "gn:feature_class":"P",
    "gn:feature_code":"PPL",
    "gn:name":"Chiginy",
    "gn:population":0,
    "gn:timezone":"Asia/Tomsk",
    "iso:country":"RU",
    "name:rus_x_preferred":[
        "\u0427\u0438\u0433\u0438\u043d\u044b"
    ],
    "name:und_x_variant":[
        "Yurty Chiginy",
        "Chishny",
        "Chiginy",
        "\u0427\u0438\u0433\u0438\u043d\u044b"
    ],
    "wof:name":"Chiginy",
    "wof:placetype":"locality"
},
  "geometry": {"coordinates":[81.23333000000002,59.71666999999999],"type":"Point"}
}