{
  "type": "Feature",
  "properties": {
    "gn:admin1_code":"52",
    "gn:asciiname":"Porog",
    "gn:country_code":"RU",
    "gn:dem":79,
    "gn:feature_class":"P",
    "gn:feature_code":"PPL",
    "gn:name":"Porog",
    "gn:population":0,
    "gn:timezone":"Europe/Moscow",
    "iso:country":"RU",
    "name:eng_x_preferred":[
        "Porog"
    ],
    "name:nor_x_preferred":[
        "Porog"
    ],
    "name:rus_x_preferred":[
        "\u041f\u043e\u0440\u043e\u0433"
    ],
    "wof:name":"Porog",
    "wof:placetype":"locality"
},
  "geometry": {"coordinates":[33.40685999999999,59.26592],"type":"Point"}
}