{
  "type": "Feature",
  "properties": {
    "gn:admin1_code":"23",
    "gn:asciiname":"Losevo",
    "gn:country_code":"RU",
    "gn:dem":41,
    "gn:feature_class":"P",
    "gn:feature_code":"PPL",
    "gn:name":"Losevo",
    "gn:population":0,
    "gn:timezone":"Europe/Kaliningrad",
    "iso:country":"RU",
    "name:deu_x_preferred":[
        "Lossewo"
    ],
    "name:rus_x_preferred":[
        "\u041b\u043e\u0441\u0435\u0432\u043e"
    ],
    "name:spa_x_preferred":[
        "L\u00f3sevo"
    ],
    "wof:name":"Losevo",
    "wof:placetype":"locality"
},
  "geometry": {"coordinates":[22.63444,54.88694],"type":"Point"}
}