{
  "type": "Feature",
  "properties": {
    "gn:admin1_code":"46",
    "gn:asciiname":"Luch",
    "gn:country_code":"RU",
    "gn:dem":156,
    "gn:feature_class":"P",
    "gn:feature_code":"PPL",
    "gn:name":"Luch",
    "gn:population":0,
    "gn:timezone":"Europe/Moscow",
    "iso:country":"RU",
    "name:ceb_x_preferred":[
        "Luch"
    ],
    "name:deu_x_preferred":[
        "Luch"
    ],
    "name:fra_x_preferred":[
        "Luch"
    ],
    "name:rus_x_preferred":[
        "\u041b\u0443\u0447"
    ],
    "wof:name":"Luch",
    "wof:placetype":"locality"
},
  "geometry": {"coordinates":[45.7803,54.1866],"type":"Point"}
}