{
  "type": "Feature",
  "properties": {
    "gn:admin1_code":"63",
    "gn:asciiname":"Uritskoye",
    "gn:country_code":"RU",
    "gn:dem":161,
    "gn:feature_class":"P",
    "gn:feature_code":"PPL",
    "gn:name":"Uritskoye",
    "gn:population":0,
    "gn:timezone":"Asia/Yakutsk",
    "iso:country":"RU",
    "name:eng_x_preferred":[
        "Uritskoye"
    ],
    "name:nor_x_preferred":[
        "Uritskoje"
    ],
    "name:rus_x_preferred":[
        "\u0423\u0440\u0438\u0446\u043a\u043e\u0435"
    ],
    "wof:name":"Uritskoye",
    "wof:placetype":"locality"
},
  "geometry": {"coordinates":[122.39366,60.55846999999999],"type":"Point"}
}