{
  "type": "Feature",
  "properties": {
    "gn:admin1_code":"77",
    "gn:asciiname":"Rzhavtsy",
    "gn:country_code":"RU",
    "gn:dem":216,
    "gn:feature_class":"P",
    "gn:feature_code":"PPL",
    "gn:name":"Rzhavtsy",
    "gn:population":0,
    "gn:timezone":"Europe/Moscow",
    "iso:country":"RU",
    "name:rus_x_preferred":[
        "\u0420\u0436\u0430\u0432\u0446\u044b"
    ],
    "wof:name":"Rzhavtsy",
    "wof:placetype":"locality"
},
  "geometry": {"coordinates":[33.38361,56.75255],"type":"Point"}
}