{
  "type": "Feature",
  "properties": {
    "gn:admin1_code":"20",
    "gn:asciiname":"Buluk",
    "gn:country_code":"RU",
    "gn:dem":457,
    "gn:feature_class":"P",
    "gn:feature_code":"PPL",
    "gn:name":"Buluk",
    "gn:population":0,
    "gn:timezone":"Asia/Irkutsk",
    "iso:country":"RU",
    "name:eng_x_preferred":[
        "Staryy Buluk"
    ],
    "name:nor_x_preferred":[
        "Buluk"
    ],
    "name:rus_x_preferred":[
        "\u0411\u0443\u043b\u0443\u043a"
    ],
    "name:rus_x_variant":[
        "\u0421\u0442\u0430\u0440\u044b\u0439 \u0411\u0443\u043b\u0443\u043a"
    ],
    "name:und_x_variant":[
        "Staryy Buluk",
        "\u0421\u0442\u0430\u0440\u044b\u0439 \u0411\u0443\u043b\u0443\u043a",
        "Bulak"
    ],
    "wof:name":"Buluk",
    "wof:placetype":"locality"
},
  "geometry": {"coordinates":[100.88571,55.10332],"type":"Point"}
}