{
  "type": "Feature",
  "properties": {
    "gn:admin1_code":"69",
    "gn:asciiname":"Tabory",
    "gn:country_code":"RU",
    "gn:dem":195,
    "gn:feature_class":"P",
    "gn:feature_code":"PPL",
    "gn:name":"Tabory",
    "gn:population":0,
    "gn:timezone":"Europe/Moscow",
    "iso:country":"RU",
    "name:ceb_x_preferred":[
        "Tabory"
    ],
    "name:deu_x_preferred":[
        "Tabory"
    ],
    "name:rus_x_preferred":[
        "\u0422\u0430\u0431\u043e\u0440\u044b"
    ],
    "wof:name":"Tabory",
    "wof:placetype":"locality"
},
  "geometry": {"coordinates":[33.64232,54.94602],"type":"Point"}
}