{
  "type": "Feature",
  "properties": {
    "gn:admin1_code":"88.0",
    "gn:asciiname":"Perepechino",
    "gn:country_code":"RU",
    "gn:dem":98,
    "gn:feature_class":"P",
    "gn:feature_code":"PPL",
    "gn:name":"Perepechino",
    "gn:population":0,
    "gn:timezone":"Europe/Moscow",
    "iso:country":"RU",
    "name:rus_x_preferred":[
        "\u041f\u0435\u0440\u0435\u043f\u0435\u0447\u0438\u043d\u043e"
    ],
    "name:und_x_variant":[
        "\u041f\u0435\u0440\u0435\u043f\u0435\u0447\u0438\u043d\u043e"
    ],
    "wof:name":"Perepechino",
    "wof:placetype":"locality"
},
  "geometry": {"coordinates":[40.57409000000001,58.05079],"type":"Point"}
}