{
  "type": "Feature",
  "properties": {
    "gn:admin1_code":"69",
    "gn:asciiname":"Logovitsy",
    "gn:country_code":"RU",
    "gn:dem":175,
    "gn:feature_class":"P",
    "gn:feature_code":"PPL",
    "gn:name":"Logovitsy",
    "gn:population":0,
    "gn:timezone":"Europe/Moscow",
    "iso:country":"RU",
    "name:rus_x_preferred":[
        "\u041b\u043e\u0433\u043e\u0432\u0438\u0446\u044b"
    ],
    "wof:name":"Logovitsy",
    "wof:placetype":"locality"
},
  "geometry": {"coordinates":[31.41865,55.32254],"type":"Point"}
}