{
  "type": "Feature",
  "properties": {
    "gn:admin1_code":"52",
    "gn:asciiname":"Yevdoksino",
    "gn:country_code":"RU",
    "gn:dem":31,
    "gn:feature_class":"P",
    "gn:feature_code":"PPL",
    "gn:name":"Yevdoksino",
    "gn:population":0,
    "gn:timezone":"Europe/Moscow",
    "iso:country":"RU",
    "name:rus_x_preferred":[
        "\u0415\u0432\u0434\u043e\u043a\u0441\u0438\u043d\u043e"
    ],
    "wof:name":"Yevdoksino",
    "wof:placetype":"locality"
},
  "geometry": {"coordinates":[31.265,57.8899],"type":"Point"}
}