{
  "type": "Feature",
  "properties": {
    "gn:admin1_code":"69",
    "gn:asciiname":"Makarovka",
    "gn:country_code":"RU",
    "gn:dem":176,
    "gn:feature_class":"P",
    "gn:feature_code":"PPL",
    "gn:name":"Makarovka",
    "gn:population":0,
    "gn:timezone":"Europe/Moscow",
    "iso:country":"RU",
    "name:rus_x_preferred":[
        "\u041c\u0430\u043a\u0430\u0440\u043e\u0432\u043a\u0430"
    ],
    "name:und_x_variant":[
        "\u041c\u0430\u043a\u0430\u0440\u043e\u0432\u043a\u0430"
    ],
    "wof:name":"Makarovka",
    "wof:placetype":"locality"
},
  "geometry": {"coordinates":[31.00838,54.76155],"type":"Point"}
}