{
  "type": "Feature",
  "properties": {
    "gn:admin1_code":"37.0",
    "gn:asciiname":"Dereven'ka",
    "gn:country_code":"RU",
    "gn:dem":125,
    "gn:feature_class":"P",
    "gn:feature_code":"PPL",
    "gn:name":"Dereven\u2019ka",
    "gn:population":0,
    "gn:timezone":"Europe/Moscow",
    "iso:country":"RU",
    "name:rus_x_preferred":[
        "\u0414\u0435\u0440\u0435\u0432\u0435\u043d\u044c\u043a\u0430"
    ],
    "name:und_x_variant":[
        "Dereven\u2019ka",
        "\u0414\u0435\u0440\u0435\u0432\u0435\u043d\u044c\u043a\u0430"
    ],
    "wof:name":"Dereven'ka",
    "wof:placetype":"locality"
},
  "geometry": {"coordinates":[41.3663,57.45296999999999],"type":"Point"}
}