{
  "type": "Feature",
  "properties": {
    "gn:admin1_code":"91",
    "gn:asciiname":"Andreyev Klyuch",
    "gn:country_code":"RU",
    "gn:dem":348,
    "gn:feature_class":"P",
    "gn:feature_code":"PPL",
    "gn:name":"Andreyev Klyuch",
    "gn:population":0,
    "gn:timezone":"Asia/Krasnoyarsk",
    "iso:country":"RU",
    "name:nor_x_preferred":[
        "Andrejev Kljutsj"
    ],
    "name:rus_x_preferred":[
        "\u0410\u043d\u0434\u0440\u0435\u0435\u0432 \u041a\u043b\u044e\u0447"
    ],
    "wof:name":"Andreyev Klyuch",
    "wof:placetype":"locality"
},
  "geometry": {"coordinates":[93.1525,54.06333000000001],"type":"Point"}
}