{
  "type": "Feature",
  "properties": {
    "gn:admin1_code":"33",
    "gn:asciiname":"Guliny",
    "gn:country_code":"RU",
    "gn:dem":138,
    "gn:feature_class":"P",
    "gn:feature_code":"PPL",
    "gn:name":"Guliny",
    "gn:population":0,
    "gn:timezone":"Europe/Kirov",
    "iso:country":"RU",
    "name:eng_x_preferred":[
        "Guliny"
    ],
    "name:nor_x_preferred":[
        "Guliny"
    ],
    "name:rus_x_preferred":[
        "\u0413\u0443\u043b\u0438\u043d\u044b"
    ],
    "wof:name":"Guliny",
    "wof:placetype":"locality"
},
  "geometry": {"coordinates":[48.39764,57.7452],"type":"Point"}
}