{
  "type": "Feature",
  "properties": {
    "gn:admin1_code":"43.0",
    "gn:asciiname":"Chernava",
    "gn:country_code":"RU",
    "gn:dem":132,
    "gn:feature_class":"P",
    "gn:feature_code":"PPL",
    "gn:name":"Chernava",
    "gn:population":0,
    "gn:timezone":"Europe/Moscow",
    "iso:country":"RU",
    "name:rus_x_preferred":[
        "\u0427\u0435\u0440\u043d\u0430\u0432\u0430"
    ],
    "name:und_x_variant":[
        "Nikitskoye",
        "Chernova-Nikitskoye",
        "Chernava-Nikitskoye",
        "Chernava",
        "\u0427\u0435\u0440\u043d\u0430\u0432\u0430",
        "Chernova"
    ],
    "wof:name":"Chernava",
    "wof:placetype":"locality"
},
  "geometry": {"coordinates":[38.06132,52.49565],"type":"Point"}
}