{
  "type": "Feature",
  "properties": {
    "gn:admin1_code":"77",
    "gn:asciiname":"Kopylovo",
    "gn:country_code":"RU",
    "gn:dem":204,
    "gn:feature_class":"P",
    "gn:feature_code":"PPL",
    "gn:name":"Kopylovo",
    "gn:population":0,
    "gn:timezone":"Europe/Moscow",
    "iso:country":"RU",
    "name:rus_x_preferred":[
        "\u041a\u043e\u043f\u044b\u043b\u043e\u0432\u043e"
    ],
    "name:und_x_variant":[
        "Kopylova",
        "Kopylovo"
    ],
    "wof:name":"Kopylovo",
    "wof:placetype":"locality"
},
  "geometry": {"coordinates":[34.91426,56.12909000000001],"type":"Point"}
}