{
  "type": "Feature",
  "properties": {
    "gn:admin1_code":"73",
    "gn:asciiname":"Yantsobino",
    "gn:country_code":"RU",
    "gn:dem":152,
    "gn:feature_class":"P",
    "gn:feature_code":"PPL",
    "gn:name":"Yantsobino",
    "gn:population":0,
    "gn:timezone":"Europe/Moscow",
    "iso:country":"RU",
    "name:rus_x_preferred":[
        "\u042f\u043d\u0446\u043e\u0431\u0438\u043d\u043e"
    ],
    "name:und_x_variant":[
        "Yansobino",
        "Yantsobino"
    ],
    "wof:name":"Yantsobino",
    "wof:placetype":"locality"
},
  "geometry": {"coordinates":[50.7949,56.2267],"type":"Point"}
}