{
  "type": "Feature",
  "properties": {
    "gn:admin1_code":"37",
    "gn:asciiname":"Kosyapino",
    "gn:country_code":"RU",
    "gn:dem":195,
    "gn:feature_class":"P",
    "gn:feature_code":"PPL",
    "gn:name":"Kosyapino",
    "gn:population":0,
    "gn:timezone":"Europe/Moscow",
    "iso:country":"RU",
    "name:rus_x_preferred":[
        "\u041a\u043e\u0441\u044f\u043f\u0438\u043d\u043e"
    ],
    "wof:name":"Kosyapino",
    "wof:placetype":"locality"
},
  "geometry": {"coordinates":[42.6429,58.5615],"type":"Point"}
}