{
  "type": "Feature",
  "properties": {
    "gn:admin1_code":"59",
    "gn:asciiname":"Stark",
    "gn:country_code":"RU",
    "gn:dem":5,
    "gn:feature_class":"P",
    "gn:feature_code":"PPL",
    "gn:name":"Stark",
    "gn:population":0,
    "gn:timezone":"Asia/Vladivostok",
    "iso:country":"RU",
    "name:bel_x_preferred":[
        "\u0421\u0442\u0430\u0440\u043a"
    ],
    "name:bul_x_preferred":[
        "\u0421\u0442\u0430\u0440\u043a"
    ],
    "name:cat_x_preferred":[
        "Stark"
    ],
    "name:ceb_x_preferred":[
        "Stark"
    ],
    "name:ces_x_preferred":[
        "Stark"
    ],
    "name:deu_x_preferred":[
        "Stark"
    ],
    "name:fin_x_preferred":[
        "Stark"
    ],
    "name:fra_x_preferred":[
        "Stark"
    ],
    "name:heb_x_preferred":[
        "\u05e1\u05d8\u05d0\u05e8\u05e7"
    ],
    "name:ita_x_preferred":[
        "Stark"
    ],
    "name:nld_x_preferred":[
        "Stark"
    ],
    "name:pol_x_preferred":[
        "Stark"
    ],
    "name:por_x_preferred":[
        "Stark"
    ],
    "name:ron_x_preferred":[
        "Stark"
    ],
    "name:rus_x_preferred":[
        "\u0421\u0442\u0430\u0440\u043a"
    ],
    "name:spa_x_preferred":[
        "Stark"
    ],
    "name:srp_x_preferred":[
        "\u0421\u0442\u0430\u0440\u043a"
    ],
    "name:swe_x_preferred":[
        "Stark"
    ],
    "name:ukr_x_preferred":[
        "\u0421\u0442\u0430\u0440\u043a"
    ],
    "name:vol_x_preferred":[
        "Stark"
    ],
    "wof:name":"Stark",
    "wof:placetype":"locality"
},
  "geometry": {"coordinates":[131.74451000000002,42.96905],"type":"Point"}
}