{
  "type": "Feature",
  "properties": {
    "gn:admin1_code":"59",
    "gn:asciiname":"Stark",
    "gn:country_code":"RU",
    "gn:dem":5,
    "gn:feature_class":"P",
    "gn:feature_code":"PPL",
    "gn:name":"Stark",
    "gn:population":0,
    "gn:timezone":"Asia/Vladivostok",
    "iso:country":"RU",
    "name:rus_x_preferred":[
        "\u0421\u0442\u0430\u0440\u043a"
    ],
    "name:und_x_variant":[
        "\u0421\u0442\u0430\u0440\u043a"
    ],
    "wof:name":"Stark",
    "wof:placetype":"locality"
},
  "geometry": {"coordinates":[131.74451000000002,42.96905],"type":"Point"}
}