{
  "type": "Feature",
  "properties": {
    "gn:admin1_code":"47",
    "gn:admin2_code":"472430",
    "gn:asciiname":"Golubtsovo",
    "gn:country_code":"RU",
    "gn:dem":266,
    "gn:feature_class":"P",
    "gn:feature_code":"PPL",
    "gn:name":"Golubtsovo",
    "gn:population":0,
    "gn:timezone":"Europe/Moscow",
    "iso:country":"RU",
    "name:rus_x_preferred":[
        "\u0413\u043e\u043b\u0443\u0431\u0446\u043e\u0432\u043e"
    ],
    "wof:name":"Golubtsovo",
    "wof:placetype":"locality"
},
  "geometry": {"coordinates":[36.055,56.0681],"type":"Point"}
}