{
  "type": "Feature",
  "properties": {
    "gn:admin1_code":"69",
    "gn:asciiname":"Novaya Prismara",
    "gn:country_code":"RU",
    "gn:dem":199,
    "gn:feature_class":"P",
    "gn:feature_code":"PPL",
    "gn:name":"Novaya Prismara",
    "gn:population":0,
    "gn:timezone":"Europe/Moscow",
    "iso:country":"RU",
    "name:rus_x_preferred":[
        "\u041d\u043e\u0432\u0430\u044f \u041f\u0440\u0438\u0441\u043c\u0430\u0440\u0430"
    ],
    "wof:name":"Novaya Prismara",
    "wof:placetype":"locality"
},
  "geometry": {"coordinates":[33.37441,54.1803],"type":"Point"}
}