{
  "type": "Feature",
  "properties": {
    "gn:admin1_code":"51",
    "gn:asciiname":"Ul'yanovo",
    "gn:country_code":"RU",
    "gn:dem":157,
    "gn:feature_class":"P",
    "gn:feature_code":"PPL",
    "gn:name":"Ul\u2019yanovo",
    "gn:population":0,
    "gn:timezone":"Europe/Moscow",
    "iso:country":"RU",
    "name:eng_x_preferred":[
        "Ul'yanovo"
    ],
    "name:nor_x_preferred":[
        "Uljanovo"
    ],
    "name:rus_x_preferred":[
        "\u0423\u043b\u044c\u044f\u043d\u043e\u0432\u043e"
    ],
    "name:und_x_variant":[
        "Ul\u2019yanovo"
    ],
    "wof:name":"Ul'yanovo",
    "wof:placetype":"locality"
},
  "geometry": {"coordinates":[44.39986,55.04799000000001],"type":"Point"}
}