{
  "type": "Feature",
  "properties": {
    "gn:admin1_code":"47.0",
    "gn:asciiname":"Usovo-Tupik",
    "gn:country_code":"RU",
    "gn:dem":161,
    "gn:feature_class":"P",
    "gn:feature_code":"PPL",
    "gn:name":"Usovo-Tupik",
    "gn:population":0,
    "gn:timezone":"Europe/Moscow",
    "iso:country":"RU",
    "wof:name":"Usovo-Tupik",
    "wof:placetype":"locality"
},
  "geometry": {"coordinates":[37.22014,55.72968],"type":"Point"}
}