{
  "type": "Feature",
  "properties": {
    "gn:admin1_code":"33.0",
    "gn:asciiname":"Usenki",
    "gn:country_code":"RU",
    "gn:dem":110,
    "gn:feature_class":"P",
    "gn:feature_code":"PPL",
    "gn:name":"Usenki",
    "gn:population":0,
    "gn:timezone":"Europe/Kirov",
    "iso:country":"RU",
    "name:rus_x_preferred":[
        "\u0423\u0441\u0435\u043d\u043a\u0438"
    ],
    "wof:name":"Usenki",
    "wof:placetype":"locality"
},
  "geometry": {"coordinates":[48.47607,58.59898000000001],"type":"Point"}
}