{
  "type": "Feature",
  "properties": {
    "gn:admin1_code":"61",
    "gn:asciiname":"Savchenko",
    "gn:cc2":"RU",
    "gn:country_code":"RU",
    "gn:dem":48,
    "gn:feature_class":"P",
    "gn:feature_code":"PPL",
    "gn:name":"Savchenko",
    "gn:population":0,
    "gn:timezone":"Europe/Moscow",
    "iso:country":"RU",
    "name:rus_x_preferred":[
        "\u0421\u0430\u0432\u0447\u0435\u043d\u043a\u043e"
    ],
    "name:slv_x_preferred":[
        "Sav\u010denko"
    ],
    "name:und_x_variant":[
        "Savchenkov",
        "Savchenko"
    ],
    "wof:name":"Savchenko",
    "wof:placetype":"locality"
},
  "geometry": {"coordinates":[39.46417,47.48833],"type":"Point"}
}