{
  "type": "Feature",
  "properties": {
    "gn:admin1_code":"67.0",
    "gn:asciiname":"Bogatovka",
    "gn:country_code":"RU",
    "gn:dem":182,
    "gn:feature_class":"P",
    "gn:feature_code":"PPL",
    "gn:name":"Bogatovka",
    "gn:population":0,
    "gn:timezone":"Europe/Saratov",
    "iso:country":"RU",
    "name:rus_x_preferred":[
        "\u0411\u043e\u0433\u0430\u0442\u043e\u0432\u043a\u0430"
    ],
    "name:und_x_variant":[
        "\u0411\u043e\u0433\u0430\u0442\u043e\u0432\u043a\u0430"
    ],
    "wof:name":"Bogatovka",
    "wof:placetype":"locality"
},
  "geometry": {"coordinates":[44.27155,51.74127],"type":"Point"}
}