{
  "type": "Feature",
  "properties": {
    "gn:admin1_code":"13",
    "gn:asciiname":"Druzhnyy",
    "gn:country_code":"RU",
    "gn:dem":231,
    "gn:feature_class":"P",
    "gn:feature_code":"PPL",
    "gn:name":"Druzhnyy",
    "gn:population":0,
    "gn:timezone":"Asia/Yekaterinburg",
    "iso:country":"RU",
    "name:rus_x_preferred":[
        "\u0414\u0440\u0443\u0436\u043d\u044b\u0439"
    ],
    "wof:name":"Druzhnyy",
    "wof:placetype":"locality"
},
  "geometry": {"coordinates":[61.3256,54.2986],"type":"Point"}
}