{
  "type": "Feature",
  "properties": {
    "gn:admin1_code":"86",
    "gn:asciiname":"Khutor Mokhnatyy",
    "gn:cc2":"RU",
    "gn:country_code":"RU",
    "gn:dem":148,
    "gn:feature_class":"P",
    "gn:feature_code":"PPL",
    "gn:name":"Khutor Mokhnatyy",
    "gn:population":0,
    "gn:timezone":"Europe/Moscow",
    "iso:country":"RU",
    "name:rus_x_preferred":[
        "\u0425\u0443\u0442\u043e\u0440 \u041c\u043e\u0445\u043d\u0430\u0442\u044b\u0439"
    ],
    "name:und_x_variant":[
        "Mokhnaty",
        "Mokhnatnny",
        "Khutor Mokhnatyy",
        "\u0425\u0443\u0442\u043e\u0440 \u041c\u043e\u0445\u043d\u0430\u0442\u044b\u0439"
    ],
    "wof:name":"Khutor Mokhnatyy",
    "wof:placetype":"locality"
},
  "geometry": {"coordinates":[39.91167,51.06278],"type":"Point"}
}