{
  "type": "Feature",
  "properties": {
    "gn:admin1_code":"30",
    "gn:asciiname":"Dauki",
    "gn:country_code":"RU",
    "gn:dem":15,
    "gn:feature_class":"P",
    "gn:feature_code":"PPL",
    "gn:name":"Dauki",
    "gn:population":0,
    "gn:timezone":"Asia/Vladivostok",
    "iso:country":"RU",
    "name:rus_x_preferred":[
        "\u0414\u0430\u0443\u043a\u0438"
    ],
    "wof:name":"Dauki",
    "wof:placetype":"locality"
},
  "geometry": {"coordinates":[136.78333000000001,49.76667],"type":"Point"}
}