{
  "type": "Feature",
  "properties": {
    "gn:admin1_code":"52.0",
    "gn:asciiname":"Denesino",
    "gn:country_code":"RU",
    "gn:dem":176,
    "gn:feature_class":"P",
    "gn:feature_code":"PPL",
    "gn:name":"Denesino",
    "gn:population":0,
    "gn:timezone":"Europe/Moscow",
    "iso:country":"RU",
    "name:nor_x_preferred":[
        "Denesino"
    ],
    "name:rus_x_preferred":[
        "\u0414\u0435\u043d\u0435\u0441\u0438\u043d\u043e"
    ],
    "wof:name":"Denesino",
    "wof:placetype":"locality"
},
  "geometry": {"coordinates":[33.5938,58.29501],"type":"Point"}
}