{
  "type": "Feature",
  "properties": {
    "gn:admin1_code":"57",
    "gn:asciiname":"Novaya Kashtanovka",
    "gn:country_code":"RU",
    "gn:dem":150,
    "gn:feature_class":"P",
    "gn:feature_code":"PPL",
    "gn:name":"Novaya Kashtanovka",
    "gn:population":0,
    "gn:timezone":"Europe/Moscow",
    "iso:country":"RU",
    "name:eng_x_preferred":[
        "Novaya Kashtanovka"
    ],
    "name:nor_x_preferred":[
        "Nov.Kasjtanovka"
    ],
    "name:rus_x_preferred":[
        "\u041d\u043e\u0432.\u041a\u0430\u0448\u0442\u0430\u043d\u043e\u0432\u043a\u0430"
    ],
    "name:rus_x_variant":[
        "\u041d\u043e\u0432\u0430\u044f \u041a\u0430\u0448\u0442\u0430\u043d\u043e\u0432\u043a\u0430"
    ],
    "wof:name":"Novaya Kashtanovka",
    "wof:placetype":"locality"
},
  "geometry": {"coordinates":[43.24937,53.02848],"type":"Point"}
}