{
  "type": "Feature",
  "properties": {
    "gn:admin1_code":"73",
    "gn:asciiname":"Khozesanovo",
    "gn:country_code":"RU",
    "gn:dem":109,
    "gn:feature_class":"P",
    "gn:feature_code":"PPL",
    "gn:name":"Khozesanovo",
    "gn:population":0,
    "gn:timezone":"Europe/Moscow",
    "iso:country":"RU",
    "name:rus_x_preferred":[
        "\u0425\u043e\u0437\u0435\u0441\u0430\u043d\u043e\u0432\u043e"
    ],
    "name:und_x_variant":[
        "Khazesanovo",
        "Khozyasanovo",
        "Khazezanovo",
        "Khozesanovo"
    ],
    "wof:name":"Khozesanovo",
    "wof:placetype":"locality"
},
  "geometry": {"coordinates":[47.8367,55.36744],"type":"Point"}
}