{
  "type": "Feature",
  "properties": {
    "gn:admin1_code":"56",
    "gn:asciiname":"Kazinka",
    "gn:country_code":"RU",
    "gn:dem":235,
    "gn:feature_class":"P",
    "gn:feature_code":"PPL",
    "gn:name":"Kazinka",
    "gn:population":0,
    "gn:timezone":"Europe/Moscow",
    "iso:country":"RU",
    "name:rus_x_preferred":[
        "\u041a\u0430\u0437\u0438\u043d\u043a\u0430"
    ],
    "name:und_x_variant":[
        "Kozinka"
    ],
    "wof:name":"Kazinka",
    "wof:placetype":"locality"
},
  "geometry": {"coordinates":[36.51749,52.98244],"type":"Point"}
}