{
  "type": "Feature",
  "properties": {
    "gn:admin1_code":"77",
    "gn:asciiname":"Bonyak",
    "gn:country_code":"RU",
    "gn:dem":150,
    "gn:feature_class":"P",
    "gn:feature_code":"PPL",
    "gn:name":"Bonyak",
    "gn:population":0,
    "gn:timezone":"Europe/Moscow",
    "iso:country":"RU",
    "name:rus_x_preferred":[
        "\u0411\u043e\u043d\u044f\u043a"
    ],
    "name:und_x_variant":[
        "\u0411\u043e\u043d\u044f\u043a"
    ],
    "wof:name":"Bonyak",
    "wof:placetype":"locality"
},
  "geometry": {"coordinates":[36.5482,58.2082],"type":"Point"}
}