{
  "type": "Feature",
  "properties": {
    "gn:admin1_code":"51",
    "gn:asciiname":"Klin",
    "gn:country_code":"RU",
    "gn:dem":146,
    "gn:feature_class":"P",
    "gn:feature_code":"PPL",
    "gn:name":"Klin",
    "gn:population":0,
    "gn:timezone":"Europe/Moscow",
    "iso:country":"RU",
    "name:ben_x_preferred":[
        "\u0995\u09cd\u09b2\u09bf\u09a8"
    ],
    "name:bul_x_preferred":[
        "\u041a\u043b\u0438\u043d"
    ],
    "name:ceb_x_preferred":[
        "Klin"
    ],
    "name:ces_x_preferred":[
        "Kl\u00edn"
    ],
    "name:deu_x_preferred":[
        "Klin"
    ],
    "name:epo_x_preferred":[
        "Klin"
    ],
    "name:fra_x_preferred":[
        "Klin"
    ],
    "name:hin_x_preferred":[
        "\u0915\u094d\u0932\u093f\u0928"
    ],
    "name:hun_x_preferred":[
        "Klin"
    ],
    "name:ind_x_preferred":[
        "Klin"
    ],
    "name:ita_x_preferred":[
        "Klin"
    ],
    "name:nld_x_preferred":[
        "Klin"
    ],
    "name:pol_x_preferred":[
        "Klin"
    ],
    "name:rus_x_preferred":[
        "\u041a\u043b\u0438\u043d"
    ],
    "name:slk_x_preferred":[
        "Klin"
    ],
    "name:srp_x_preferred":[
        "\u041a\u043b\u0438\u043d"
    ],
    "name:swe_x_preferred":[
        "Klin"
    ],
    "name:ukr_x_preferred":[
        "\u041a\u043b\u0438\u043d"
    ],
    "name:urd_x_preferred":[
        "\u06a9\u0644\u0646"
    ],
    "wof:name":"Klin",
    "wof:placetype":"locality"
},
  "geometry": {"coordinates":[46.4513,57.6211],"type":"Point"}
}