{
  "type": "Feature",
  "properties": {
    "gn:admin1_code":"51",
    "gn:asciiname":"Klin",
    "gn:country_code":"RU",
    "gn:dem":146,
    "gn:feature_class":"P",
    "gn:feature_code":"PPL",
    "gn:name":"Klin",
    "gn:population":0,
    "gn:timezone":"Europe/Moscow",
    "iso:country":"RU",
    "name:rus_x_preferred":[
        "\u041a\u043b\u0438\u043d"
    ],
    "name:und_x_variant":[
        "\u041a\u043b\u0438\u043d"
    ],
    "wof:name":"Klin",
    "wof:placetype":"locality"
},
  "geometry": {"coordinates":[46.4513,57.6211],"type":"Point"}
}