{
  "type": "Feature",
  "properties": {
    "gn:admin1_code":"63",
    "gn:asciiname":"Nokhtuysk",
    "gn:cc2":"RU",
    "gn:country_code":"RU",
    "gn:dem":230,
    "gn:feature_class":"P",
    "gn:feature_code":"PPL",
    "gn:name":"Nokhtuysk",
    "gn:population":0,
    "gn:timezone":"Asia/Yakutsk",
    "iso:country":"RU",
    "name:eng_x_preferred":[
        "Nokhtuysk"
    ],
    "name:nor_x_preferred":[
        "Nokhtujsk"
    ],
    "name:rus_x_preferred":[
        "\u041d\u043e\u0445\u0442\u0443\u0439\u0441\u043a"
    ],
    "name:und_x_variant":[
        "Nokhtuyskaya",
        "Nokhtuyskoye",
        "Noktuyskoye"
    ],
    "wof:name":"Nokhtuysk",
    "wof:placetype":"locality"
},
  "geometry": {"coordinates":[117.60361,59.93194],"type":"Point"}
}