{
  "type": "Feature",
  "properties": {
    "gn:admin1_code":"10",
    "gn:asciiname":"Golakhovo",
    "gn:country_code":"RU",
    "gn:dem":210,
    "gn:feature_class":"P",
    "gn:feature_code":"PPL",
    "gn:name":"Golakhovo",
    "gn:population":0,
    "gn:timezone":"Europe/Moscow",
    "iso:country":"RU",
    "name:rus_x_preferred":[
        "\u0413\u043e\u043b\u0430\u0445\u043e\u0432\u043e"
    ],
    "name:und_x_variant":[
        "\u0413\u043e\u043b\u0430\u0445\u043e\u0432\u043e"
    ],
    "wof:name":"Golakhovo",
    "wof:placetype":"locality"
},
  "geometry": {"coordinates":[33.86417,53.5575],"type":"Point"}
}