{
  "type": "Feature",
  "properties": {
    "gn:admin1_code":"20",
    "gn:asciiname":"Malaya Bugul'deyka",
    "gn:country_code":"RU",
    "gn:dem":472,
    "gn:feature_class":"P",
    "gn:feature_code":"PPL",
    "gn:name":"Malaya Bugul\u2019deyka",
    "gn:population":0,
    "gn:timezone":"Asia/Irkutsk",
    "iso:country":"RU",
    "name:rus_x_preferred":[
        "\u041c\u0430\u043b\u0430\u044f \u0411\u0443\u0433\u0443\u043b\u044c\u0434\u0435\u0439\u043a\u0430"
    ],
    "name:und_x_variant":[
        "Malaya Bugul\u2019deyka"
    ],
    "wof:name":"Malaya Bugul'deyka",
    "wof:placetype":"locality"
},
  "geometry": {"coordinates":[106.13333,52.56667],"type":"Point"}
}