{
  "type": "Feature",
  "properties": {
    "gn:admin1_code":"90.0",
    "gn:asciiname":"Yefimkovo",
    "gn:country_code":"RU",
    "gn:dem":216,
    "gn:feature_class":"P",
    "gn:feature_code":"PPL",
    "gn:name":"Yefimkovo",
    "gn:population":0,
    "gn:timezone":"Asia/Yekaterinburg",
    "iso:country":"RU",
    "name:rus_x_preferred":[
        "\u0415\u0444\u0438\u043c\u043a\u043e\u0432\u043e"
    ],
    "wof:name":"Yefimkovo",
    "wof:placetype":"locality"
},
  "geometry": {"coordinates":[53.9485,58.2409],"type":"Point"}
}