{
  "type": "Feature",
  "properties": {
    "gn:admin1_code":"33.0",
    "gn:asciiname":"Barichi",
    "gn:country_code":"RU",
    "gn:dem":159,
    "gn:feature_class":"P",
    "gn:feature_code":"PPL",
    "gn:name":"Barichi",
    "gn:population":0,
    "gn:timezone":"Europe/Kirov",
    "iso:country":"RU",
    "name:eng_x_preferred":[
        "Barichi"
    ],
    "name:nor_x_preferred":[
        "Baritsji"
    ],
    "name:rus_x_preferred":[
        "\u0411\u0430\u0440\u0438\u0447\u0438"
    ],
    "wof:name":"Barichi",
    "wof:placetype":"locality"
},
  "geometry": {"coordinates":[49.76976,58.2777],"type":"Point"}
}