{
  "type": "Feature",
  "properties": {
    "gn:admin1_code":"73",
    "gn:asciiname":"Kazkeyevo",
    "gn:country_code":"RU",
    "gn:dem":76,
    "gn:feature_class":"P",
    "gn:feature_code":"PPL",
    "gn:name":"Kazkeyevo",
    "gn:population":0,
    "gn:timezone":"Europe/Moscow",
    "iso:country":"RU",
    "name:rus_x_preferred":[
        "\u041a\u0430\u0437\u043a\u0435\u0435\u0432\u043e"
    ],
    "name:und_x_variant":[
        "\u041a\u0430\u0437\u043a\u0435\u0435\u0432\u043e"
    ],
    "wof:name":"Kazkeyevo",
    "wof:placetype":"locality"
},
  "geometry": {"coordinates":[54.19114,55.66117],"type":"Point"}
}