{
  "type": "Feature",
  "properties": {
    "gn:admin1_code":"86",
    "gn:asciiname":"Novogremyachenskoye",
    "gn:country_code":"RU",
    "gn:dem":97,
    "gn:feature_class":"P",
    "gn:feature_code":"PPL",
    "gn:name":"Novogremyachenskoye",
    "gn:population":0,
    "gn:timezone":"Europe/Moscow",
    "iso:country":"RU",
    "name:rus_x_preferred":[
        "\u041d\u043e\u0432\u043e\u0433\u0440\u0435\u043c\u044f\u0447\u0435\u043d\u0441\u043a\u043e\u0435"
    ],
    "name:und_x_variant":[
        "Sovkhoz Gremyachenskiy",
        "Novogremyachenskoye"
    ],
    "wof:name":"Novogremyachenskoye",
    "wof:placetype":"locality"
},
  "geometry": {"coordinates":[39.04861,51.53099],"type":"Point"}
}