{
  "type": "Feature",
  "properties": {
    "gn:admin1_code":"81",
    "gn:asciiname":"Agronom",
    "gn:country_code":"RU",
    "gn:dem":121,
    "gn:feature_class":"P",
    "gn:feature_code":"PPL",
    "gn:name":"Agronom",
    "gn:population":0,
    "gn:timezone":"Europe/Ulyanovsk",
    "iso:country":"RU",
    "name:rus_x_preferred":[
        "\u0410\u0433\u0440\u043e\u043d\u043e\u043c"
    ],
    "name:und_x_variant":[
        "\u0410\u0433\u0440\u043e\u043d\u043e\u043c"
    ],
    "wof:name":"Agronom",
    "wof:placetype":"locality"
},
  "geometry": {"coordinates":[47.9767,53.89100000000001],"type":"Point"}
}