{
  "type": "Feature",
  "properties": {
    "gn:admin1_code":"60",
    "gn:asciiname":"Pankratovo",
    "gn:country_code":"RU",
    "gn:dem":73,
    "gn:feature_class":"P",
    "gn:feature_code":"PPL",
    "gn:name":"Pankratovo",
    "gn:population":0,
    "gn:timezone":"Europe/Moscow",
    "iso:country":"RU",
    "name:rus_x_preferred":[
        "\u041f\u0430\u043d\u043a\u0440\u0430\u0442\u043e\u0432\u043e"
    ],
    "name:und_x_variant":[
        "Novo-Pankratovo",
        "Novoye Pankratovo",
        "Pankratovo"
    ],
    "wof:name":"Pankratovo",
    "wof:placetype":"locality"
},
  "geometry": {"coordinates":[30.23547,57.8204],"type":"Point"}
}