{
  "type": "Feature",
  "properties": {
    "gn:admin1_code":"42",
    "gn:asciiname":"Likovskoye",
    "gn:country_code":"RU",
    "gn:dem":78,
    "gn:feature_class":"P",
    "gn:feature_code":"PPL",
    "gn:name":"Likovskoye",
    "gn:population":0,
    "gn:timezone":"Europe/Moscow",
    "iso:country":"RU",
    "name:eng_x_preferred":[
        "Likovskoye"
    ],
    "name:nor_x_preferred":[
        "Likovskoje"
    ],
    "name:rus_x_preferred":[
        "\u041b\u0438\u043a\u043e\u0432\u0441\u043a\u043e\u0435"
    ],
    "wof:name":"Likovskoye",
    "wof:placetype":"locality"
},
  "geometry": {"coordinates":[28.76371,59.11158],"type":"Point"}
}