{
  "type": "Feature",
  "properties": {
    "gn:gn_country":"RU",
    "gn:gn_fcode":"PPL",
    "gn:gn_pop":0,
    "iso:country":"RU",
    "name:rus_x_preferred":[
        "\u041d\u0430\u0443\u0433\u043e\u043b\u044c\u043d\u043e\u0435"
    ],
    "name:unk_x_variant":[
        "Naugolino"
    ],
    "qs_pg:aaroncc":"RU",
    "qs_pg:gn_country":"RU",
    "qs_pg:gn_fcode":"PPL",
    "qs_pg:gn_pop":0,
    "qs_pg:name":"Naugol'noe",
    "qs_pg:name_adm0":"Russia",
    "qs_pg:name_adm1":"Moscow Oblast",
    "qs_pg:photos_9k":1,
    "qs_pg:photos_9r":1,
    "qs_pg:photos_all":14,
    "qs_pg:photos_sr":0,
    "qs_pg:pop_sr":0,
    "qs_pg:qs_pg_placetype":"locality",
    "qs_pg:qs_pg_placetype_gp":"Town",
    "qs_pg:woe_adm0":23424936,
    "woe:adm0_id":23424936,
    "woe:name_adm0":"Russia",
    "woe:name_adm1":"Moscow Oblast",
    "woe:placetype":"Town",
    "wof:name":"Naugol'noe",
    "wof:placetype":"locality"
},
  "geometry": {"coordinates":[38.18333,56.36667],"type":"Point"}
}