{
  "type": "Feature",
  "properties": {
    "gn:admin1_code":"20",
    "gn:asciiname":"Abalakovo",
    "gn:country_code":"RU",
    "gn:dem":482,
    "gn:feature_class":"P",
    "gn:feature_code":"PPL",
    "gn:name":"Abalakovo",
    "gn:population":0,
    "gn:timezone":"Asia/Irkutsk",
    "iso:country":"RU",
    "name:eng_x_preferred":[
        "Abalakova"
    ],
    "name:rus_x_preferred":[
        "\u0410\u0431\u0430\u043b\u0430\u043a\u043e\u0432\u043e"
    ],
    "name:ukr_x_preferred":[
        "\u0410\u0431\u0430\u043b\u0430\u043a\u043e\u0432\u043e"
    ],
    "name:und_x_variant":[
        "Abalakovo"
    ],
    "wof:name":"Abalakovo",
    "wof:placetype":"locality"
},
  "geometry": {"coordinates":[99.11360000000001,54.7433],"type":"Point"}
}