{
  "type": "Feature",
  "properties": {
    "gn:country":"RU",
    "gn:fcode":"PPL",
    "gn:population":0,
    "iso:country":"RU",
    "name:ast_x_preferred":[
        "Parikkala"
    ],
    "name:cat_x_preferred":[
        "Parikkala"
    ],
    "name:ceb_x_preferred":[
        "Parikkala"
    ],
    "name:dan_x_preferred":[
        "Parikkala"
    ],
    "name:deu_x_preferred":[
        "Parikkala"
    ],
    "name:eng_x_preferred":[
        "Parikkala"
    ],
    "name:epo_x_preferred":[
        "Parikkala"
    ],
    "name:est_x_preferred":[
        "Parikkala vald"
    ],
    "name:fas_x_preferred":[
        "\u067e\u0627\u0631\u06cc\u06a9\u06a9\u0627\u0644\u0627"
    ],
    "name:fin_x_preferred":[
        "Parikka"
    ],
    "name:fin_x_variant":[
        "Parikkala"
    ],
    "name:fra_x_preferred":[
        "Parikkala"
    ],
    "name:gle_x_preferred":[
        "Parikkala"
    ],
    "name:glg_x_preferred":[
        "Parikkala"
    ],
    "name:heb_x_preferred":[
        "\u05e4\u05e8\u05d9\u05e7\u05e7\u05dc\u05d4"
    ],
    "name:ita_x_preferred":[
        "Parikkala"
    ],
    "name:jpn_x_preferred":[
        "\u30d1\u30ea\u30c3\u30ab\u30e9"
    ],
    "name:nld_x_preferred":[
        "Parikkala"
    ],
    "name:nno_x_preferred":[
        "Parikkala"
    ],
    "name:nob_x_preferred":[
        "Parikkala"
    ],
    "name:pol_x_preferred":[
        "Parikkala"
    ],
    "name:por_x_preferred":[
        "Parikkala"
    ],
    "name:ron_x_preferred":[
        "Parikkala"
    ],
    "name:rus_x_preferred":[
        "\u041f\u0430\u0440\u0438\u043a\u043a\u0430"
    ],
    "name:rus_x_variant":[
        "\u041f\u0430\u0440\u0438\u043a\u043a\u0430\u043b\u0430"
    ],
    "name:sme_x_preferred":[
        "Parikkala"
    ],
    "name:smn_x_preferred":[
        "Parikkala"
    ],
    "name:sms_x_preferred":[
        "Parikkala"
    ],
    "name:spa_x_preferred":[
        "Parikkala"
    ],
    "name:sqi_x_preferred":[
        "Parikkala"
    ],
    "name:swe_x_preferred":[
        "Parikkala"
    ],
    "name:tur_x_preferred":[
        "Parikkala"
    ],
    "name:urd_x_preferred":[
        "\u067e\u0627\u0631\u06cc\u06a9\u0627\u0644\u0627"
    ],
    "name:zho_x_preferred":[
        "\u5e15\u91cc\u5361\u62c9"
    ],
    "qs:name":"Parikkala",
    "qs:name_adm0":"Suomi",
    "qs:name_adm1":"Etel\u00e4-Karjalan maakunta",
    "qs:photos":158,
    "qs:photos_1k":32,
    "qs:photos_9k":1,
    "qs:photos_9r":4,
    "qs:photos_all":158,
    "qs:photos_sr":4,
    "qs:placetype":"Town",
    "qs:pop_sr":"0",
    "wd:wordcount":516,
    "wof:name":"Parikkala",
    "wof:placetype":"locality",
    "wof:population":0
},
  "geometry": {"coordinates":[29.95,61.63333],"type":"Point"}
}