{
  "type": "Feature",
  "properties": {
    "gn:country":"RU",
    "gn:fcode":"PPL",
    "gn:pop":0,
    "iso:country":"RU",
    "name:fin_x_preferred":[
        "Parikka"
    ],
    "name:rus_x_preferred":[
        "\u041f\u0430\u0440\u0438\u043a\u043a\u0430"
    ],
    "name:unk_x_variant":[
        "\u041f\u0430\u0440\u0438\u043a\u043a\u0430"
    ],
    "qs:name":"Parikkala",
    "qs:name_adm0":"Suomi",
    "qs:name_adm1":"Etel\u00e4-Karjalan maakunta",
    "qs:photos":158,
    "qs:photos_1k":32,
    "qs:photos_9k":1,
    "qs:photos_9r":4,
    "qs:photos_all":158,
    "qs:photos_sr":4,
    "qs:placetype":"Town",
    "qs:pop_sr":"0",
    "wd:wordcount":516,
    "wof:name":"Parikkala",
    "wof:placetype":"locality",
    "wof:population":0
},
  "geometry": {"coordinates":[29.95,61.63333],"type":"Point"}
}