{
  "type": "Feature",
  "properties": {
    "gn:admin1_code":"42",
    "gn:asciiname":"Terebochevo",
    "gn:country_code":"RU",
    "gn:dem":38,
    "gn:feature_class":"P",
    "gn:feature_code":"PPL",
    "gn:name":"Terebochevo",
    "gn:population":0,
    "gn:timezone":"Europe/Moscow",
    "iso:country":"RU",
    "name:eng_x_preferred":[
        "Terebochevo"
    ],
    "name:nor_x_preferred":[
        "Terebatsjevo"
    ],
    "name:rus_x_preferred":[
        "\u0422\u0435\u0440\u0435\u0431\u0430\u0447\u0435\u0432\u043e"
    ],
    "wof:name":"Terebochevo",
    "wof:placetype":"locality"
},
  "geometry": {"coordinates":[32.21894,59.74381999999999],"type":"Point"}
}