{
  "type": "Feature",
  "properties": {
    "gn:admin1_code":"9.0",
    "gn:asciiname":"Afanasovo",
    "gn:country_code":"RU",
    "gn:dem":128,
    "gn:feature_class":"P",
    "gn:feature_code":"PPL",
    "gn:name":"Afanasovo",
    "gn:population":0,
    "gn:timezone":"Europe/Moscow",
    "iso:country":"RU",
    "name:nor_x_preferred":[
        "Afanasovo"
    ],
    "name:rus_x_preferred":[
        "\u0410\u0444\u0430\u043d\u0430\u0441\u043e\u0432\u043e"
    ],
    "name:und_x_variant":[
        "Atanasovo"
    ],
    "wof:name":"Afanasovo",
    "wof:placetype":"locality"
},
  "geometry": {"coordinates":[37.15344,50.73217],"type":"Point"}
}