{
  "type": "Feature",
  "properties": {
    "gn:admin1_code":"25.0",
    "gn:asciiname":"Glotovo",
    "gn:country_code":"RU",
    "gn:dem":224,
    "gn:feature_class":"P",
    "gn:feature_code":"PPL",
    "gn:name":"Glotovo",
    "gn:population":0,
    "gn:timezone":"Europe/Moscow",
    "iso:country":"RU",
    "name:che_x_preferred":[
        "\u0413\u043b\u043e\u0442\u043e\u0432\u043e"
    ],
    "name:kom_x_preferred":[
        "\u0421\u043b\u04e7\u0431\u04e7\u0434\u0430"
    ],
    "name:rus_x_preferred":[
        "\u0413\u043b\u043e\u0442\u043e\u0432\u043e"
    ],
    "name:tat_x_preferred":[
        "\u0413\u043b\u043e\u0442\u043e\u0432\u043e"
    ],
    "name:und_x_variant":[
        "\u0413\u043b\u043e\u0442\u043e\u0432\u043e"
    ],
    "wof:name":"Glotovo",
    "wof:placetype":"locality"
},
  "geometry": {"coordinates":[35.38333,53.33333],"type":"Point"}
}