{
  "type": "Feature",
  "properties": {
    "gn:admin1_code":"23",
    "gn:asciiname":"Shishkovo",
    "gn:country_code":"RU",
    "gn:dem":63,
    "gn:feature_class":"P",
    "gn:feature_code":"PPL",
    "gn:name":"Shishkovo",
    "gn:population":0,
    "gn:timezone":"Europe/Kaliningrad",
    "iso:country":"RU",
    "name:rus_x_preferred":[
        "\u0428\u0438\u0448\u043a\u043e\u0432\u043e"
    ],
    "wof:name":"Shishkovo",
    "wof:placetype":"locality"
},
  "geometry": {"coordinates":[21.85756,54.49864],"type":"Point"}
}