{
  "type": "Feature",
  "properties": {
    "gn:admin1_code":"60",
    "gn:asciiname":"Tolkovo",
    "gn:country_code":"RU",
    "gn:dem":59,
    "gn:feature_class":"P",
    "gn:feature_code":"PPL",
    "gn:name":"Tolkovo",
    "gn:population":0,
    "gn:timezone":"Europe/Moscow",
    "iso:country":"RU",
    "name:rus_x_preferred":[
        "\u0422\u043e\u043b\u043a\u043e\u0432\u043e"
    ],
    "wof:name":"Tolkovo",
    "wof:placetype":"locality"
},
  "geometry": {"coordinates":[28.07918,57.27542],"type":"Point"}
}