{
  "type": "Feature",
  "properties": {
    "gn:admin1_code":"16",
    "gn:asciiname":"Maloye Kamayevo",
    "gn:country_code":"RU",
    "gn:dem":142,
    "gn:feature_class":"P",
    "gn:feature_code":"PPL",
    "gn:name":"Maloye Kamayevo",
    "gn:population":0,
    "gn:timezone":"Europe/Moscow",
    "iso:country":"RU",
    "name:rus_x_preferred":[
        "\u041c\u0430\u043b\u043e\u0435 \u041a\u0430\u043c\u0430\u0435\u0432\u043e"
    ],
    "name:und_x_variant":[
        "\u041c\u0430\u043b\u043e\u0435 \u041a\u0430\u043c\u0430\u0435\u0432\u043e"
    ],
    "wof:name":"Maloye Kamayevo",
    "wof:placetype":"locality"
},
  "geometry": {"coordinates":[47.62949,56.00628],"type":"Point"}
}