{
  "type": "Feature",
  "properties": {
    "gn:admin1_code":"50",
    "gn:asciiname":"Vonda",
    "gn:country_code":"RU",
    "gn:dem":50,
    "gn:feature_class":"P",
    "gn:feature_code":"PPL",
    "gn:name":"Vonda",
    "gn:population":0,
    "gn:timezone":"Europe/Moscow",
    "iso:country":"RU",
    "name:fra_x_preferred":[
        "Vonda"
    ],
    "wof:name":"Vonda",
    "wof:placetype":"locality"
},
  "geometry": {"coordinates":[53.86666999999999,67.08333],"type":"Point"}
}