{
  "type": "Feature",
  "properties": {
    "gn:admin1_code":"91",
    "gn:asciiname":"Zachulymka",
    "gn:country_code":"RU",
    "gn:dem":199,
    "gn:feature_class":"P",
    "gn:feature_code":"PPL",
    "gn:name":"Zachulymka",
    "gn:population":0,
    "gn:timezone":"Asia/Krasnoyarsk",
    "iso:country":"RU",
    "name:eng_x_preferred":[
        "Zachulymka"
    ],
    "name:nor_x_preferred":[
        "Zatsjulymka"
    ],
    "name:rus_x_preferred":[
        "\u0417\u0430\u0447\u0443\u043b\u044b\u043c\u043a\u0430"
    ],
    "name:und_x_variant":[
        "Zachulymskoye",
        "Zachulymka"
    ],
    "wof:name":"Zachulymka",
    "wof:placetype":"locality"
},
  "geometry": {"coordinates":[90.45650000000001,56.8891],"type":"Point"}
}