{
  "type": "Feature",
  "properties": {
    "gn:admin1_code":"6.0",
    "gn:asciiname":"Bor",
    "gn:country_code":"RU",
    "gn:dem":34,
    "gn:feature_class":"P",
    "gn:feature_code":"PPL",
    "gn:name":"Bor",
    "gn:population":0,
    "gn:timezone":"Europe/Moscow",
    "iso:country":"RU",
    "name:rus_x_preferred":[
        "\u0411\u043e\u0440"
    ],
    "name:und_x_variant":[
        "Borovskoye",
        "Bor",
        "Borovskaya"
    ],
    "wof:name":"Bor",
    "wof:placetype":"locality"
},
  "geometry": {"coordinates":[44.3865,65.7067],"type":"Point"}
}