{
  "type": "Feature",
  "properties": {
    "gn:admin1_code":"85",
    "gn:asciiname":"Biryuchevo",
    "gn:country_code":"RU",
    "gn:dem":140,
    "gn:feature_class":"P",
    "gn:feature_code":"PPL",
    "gn:name":"Biryuchevo",
    "gn:population":0,
    "gn:timezone":"Europe/Moscow",
    "iso:country":"RU",
    "name:rus_x_preferred":[
        "\u0411\u0438\u0440\u044e\u0447\u0435\u0432\u043e"
    ],
    "wof:name":"Biryuchevo",
    "wof:placetype":"locality"
},
  "geometry": {"coordinates":[39.6919,59.4136],"type":"Point"}
}