{
  "type": "Feature",
  "properties": {
    "gn:admin1_code":"60",
    "gn:asciiname":"Rogali",
    "gn:country_code":"RU",
    "gn:dem":92,
    "gn:feature_class":"P",
    "gn:feature_code":"PPL",
    "gn:name":"Rogali",
    "gn:population":0,
    "gn:timezone":"Europe/Moscow",
    "iso:country":"RU",
    "name:rus_x_preferred":[
        "\u0420\u043e\u0433\u0430\u043b\u0438"
    ],
    "wof:name":"Rogali",
    "wof:placetype":"locality"
},
  "geometry": {"coordinates":[28.47419,56.85153],"type":"Point"}
}