{
  "type": "Feature",
  "properties": {
    "gn:admin1_code":"17",
    "gn:asciiname":"Laklakyurt",
    "gn:country_code":"RU",
    "gn:dem":15,
    "gn:feature_class":"P",
    "gn:feature_code":"PPL",
    "gn:name":"Laklakyurt",
    "gn:population":0,
    "gn:timezone":"Europe/Moscow",
    "iso:country":"RU",
    "name:rus_x_preferred":[
        "\u041b\u0430\u043a\u043b\u0430\u043a\u044e\u0440\u0442"
    ],
    "wof:name":"Laklakyurt",
    "wof:placetype":"locality"
},
  "geometry": {"coordinates":[46.80168,43.30534],"type":"Point"}
}