{
  "type": "Feature",
  "properties": {
    "gn:admin1_code":"8",
    "gn:asciiname":"Iskino",
    "gn:country_code":"RU",
    "gn:dem":93,
    "gn:feature_class":"P",
    "gn:feature_code":"PPL",
    "gn:name":"Iskino",
    "gn:population":567,
    "gn:timezone":"Asia/Yekaterinburg",
    "iso:country":"RU",
    "name:rus_x_preferred":[
        "\u0418\u0441\u043a\u0438\u043d\u043e"
    ],
    "wof:name":"Iskino",
    "wof:placetype":"locality",
    "wof:population":567
},
  "geometry": {"coordinates":[55.911,54.5191],"type":"Point"}
}