{
  "type": "Feature",
  "properties": {
    "gn:admin1_code":"5",
    "gn:asciiname":"Zolotogorka",
    "gn:cc2":"RU",
    "gn:country_code":"RU",
    "gn:dem":206,
    "gn:feature_class":"P",
    "gn:feature_code":"PPL",
    "gn:name":"Zolotogorka",
    "gn:population":0,
    "gn:timezone":"Asia/Yakutsk",
    "iso:country":"RU",
    "name:und_x_variant":[
        "Zlatogorskoye",
        "Zolotogorka"
    ],
    "wof:name":"Zolotogorka",
    "wof:placetype":"locality"
},
  "geometry": {"coordinates":[129.83333000000002,52.35],"type":"Point"}
}