{
  "type": "Feature",
  "properties": {
    "gn:admin1_code":"80.0",
    "gn:asciiname":"Biligurt",
    "gn:country_code":"RU",
    "gn:dem":169,
    "gn:feature_class":"P",
    "gn:feature_code":"PPL",
    "gn:name":"Biligurt",
    "gn:population":0,
    "gn:timezone":"Europe/Samara",
    "iso:country":"RU",
    "name:rus_x_preferred":[
        "\u0411\u0438\u043b\u0438\u0433\u0443\u0440\u0442"
    ],
    "name:und_x_variant":[
        "\u0411\u0438\u043b\u0438\u0433\u0443\u0440\u0442"
    ],
    "wof:name":"Biligurt",
    "wof:placetype":"locality"
},
  "geometry": {"coordinates":[52.51883,57.30674000000001],"type":"Point"}
}