{
  "type": "Feature",
  "properties": {
    "gn:admin1_code":"60",
    "gn:asciiname":"Staryye Karavai",
    "gn:country_code":"RU",
    "gn:dem":155,
    "gn:feature_class":"P",
    "gn:feature_code":"PPL",
    "gn:name":"Staryye Karavai",
    "gn:population":0,
    "gn:timezone":"Europe/Moscow",
    "iso:country":"RU",
    "name:rus_x_preferred":[
        "\u0421\u0442\u0430\u0440\u044b\u0435 \u041a\u0430\u0440\u0430\u0432\u0430\u0438"
    ],
    "wof:name":"Staryye Karavai",
    "wof:placetype":"locality"
},
  "geometry": {"coordinates":[30.0026,56.0144],"type":"Point"}
}