{
  "type": "Feature",
  "properties": {
    "gn:admin1_code":"6",
    "gn:asciiname":"Sintsovskaya",
    "gn:cc2":"RU",
    "gn:country_code":"RU",
    "gn:dem":41,
    "gn:feature_class":"P",
    "gn:feature_code":"PPL",
    "gn:name":"Sintsovskaya",
    "gn:population":0,
    "gn:timezone":"Europe/Moscow",
    "iso:country":"RU",
    "name:rus_x_preferred":[
        "\u0421\u0438\u043d\u0446\u043e\u0432\u0441\u043a\u0430\u044f"
    ],
    "name:und_x_variant":[
        "Sinitsino",
        "Sintsovskaya",
        "\u0421\u0438\u043d\u0446\u043e\u0432\u0441\u043a\u0430\u044f"
    ],
    "wof:name":"Sintsovskaya",
    "wof:placetype":"locality"
},
  "geometry": {"coordinates":[42.435,61.67],"type":"Point"}
}