{
  "type": "Feature",
  "properties": {
    "gn:admin1_code":"78",
    "gn:asciiname":"Supra",
    "gn:country_code":"RU",
    "gn:dem":48,
    "gn:feature_class":"P",
    "gn:feature_code":"PPL",
    "gn:name":"Supra",
    "gn:population":0,
    "gn:timezone":"Asia/Yekaterinburg",
    "iso:country":"RU",
    "name:deu_x_preferred":[
        "Supra"
    ],
    "name:eng_x_preferred":[
        "Supra"
    ],
    "name:fra_x_preferred":[
        "Supra"
    ],
    "name:ind_x_preferred":[
        "Supra"
    ],
    "name:ita_x_preferred":[
        "Supra"
    ],
    "name:nor_x_preferred":[
        "Supra"
    ],
    "name:rus_x_preferred":[
        "\u0421\u0443\u043f\u0440\u0430"
    ],
    "name:vep_x_preferred":[
        "Supra"
    ],
    "wof:name":"Supra",
    "wof:placetype":"locality"
},
  "geometry": {"coordinates":[69.56111,57.99611],"type":"Point"}
}