{
  "type": "Feature",
  "properties": {
    "gn:admin1_code":"77",
    "gn:asciiname":"Karzovo",
    "gn:country_code":"RU",
    "gn:dem":170,
    "gn:feature_class":"P",
    "gn:feature_code":"PPL",
    "gn:name":"Karzovo",
    "gn:population":0,
    "gn:timezone":"Europe/Moscow",
    "iso:country":"RU",
    "name:rus_x_preferred":[
        "\u041a\u0430\u0440\u0437\u043e\u0432\u043e"
    ],
    "name:und_x_variant":[
        "\u041a\u0430\u0440\u0437\u043e\u0432\u043e"
    ],
    "wof:name":"Karzovo",
    "wof:placetype":"locality"
},
  "geometry": {"coordinates":[35.12278,57.71389],"type":"Point"}
}