{
  "type": "Feature",
  "properties": {
    "gn:admin1_code":"77",
    "gn:asciiname":"Pochinok",
    "gn:country_code":"RU",
    "gn:dem":167,
    "gn:feature_class":"P",
    "gn:feature_code":"PPL",
    "gn:name":"Pochinok",
    "gn:population":0,
    "gn:timezone":"Europe/Moscow",
    "iso:country":"RU",
    "name:rus_x_preferred":[
        "\u041f\u043e\u0447\u0438\u043d\u043e\u043a"
    ],
    "name:und_x_variant":[
        "\u041f\u043e\u0447\u0438\u043d\u043e\u043a"
    ],
    "wof:name":"Pochinok",
    "wof:placetype":"locality"
},
  "geometry": {"coordinates":[36.5504,57.4721],"type":"Point"}
}