{
  "type": "Feature",
  "properties": {
    "gn:admin1_code":"53",
    "gn:asciiname":"Sarayevka",
    "gn:country_code":"RU",
    "gn:dem":111,
    "gn:feature_class":"P",
    "gn:feature_code":"PPL",
    "gn:name":"Sarayevka",
    "gn:population":0,
    "gn:timezone":"Asia/Novosibirsk",
    "iso:country":"RU",
    "name:rus_x_preferred":[
        "\u0421\u0430\u0440\u0430\u0435\u0432\u043a\u0430"
    ],
    "name:und_x_variant":[
        "Sarayevskiy",
        "Sarayevka"
    ],
    "wof:name":"Sarayevka",
    "wof:placetype":"locality"
},
  "geometry": {"coordinates":[77.80901999999998,54.202],"type":"Point"}
}