{
  "type": "Feature",
  "properties": {
    "gn:admin1_code":"60",
    "gn:asciiname":"Mostki",
    "gn:country_code":"RU",
    "gn:dem":75,
    "gn:feature_class":"P",
    "gn:feature_code":"PPL",
    "gn:name":"Mostki",
    "gn:population":0,
    "gn:timezone":"Europe/Moscow",
    "iso:country":"RU",
    "name:bel_x_preferred":[
        "\u041c\u0430\u0441\u0442\u043a\u0456"
    ],
    "name:ceb_x_preferred":[
        "Mostki"
    ],
    "name:deu_x_preferred":[
        "Mostki"
    ],
    "name:fra_x_preferred":[
        "Mostki"
    ],
    "name:pol_x_preferred":[
        "Mostki"
    ],
    "name:rus_x_preferred":[
        "\u041c\u043e\u0441\u0442\u043a\u0438"
    ],
    "name:szl_x_preferred":[
        "Mostki"
    ],
    "name:ukr_x_preferred":[
        "\u041c\u043e\u0441\u0442\u043a\u0456"
    ],
    "name:und_x_variant":[
        "\u041c\u043e\u0441\u0442\u043a\u0438"
    ],
    "wof:name":"Mostki",
    "wof:placetype":"locality"
},
  "geometry": {"coordinates":[30.0497,57.5325],"type":"Point"}
}