{
  "type": "Feature",
  "properties": {
    "gn:admin1_code":"51",
    "gn:asciiname":"Bol'shaya Pogorelka",
    "gn:country_code":"RU",
    "gn:dem":115,
    "gn:feature_class":"P",
    "gn:feature_code":"PPL",
    "gn:name":"Bol\u2019shaya Pogorelka",
    "gn:population":0,
    "gn:timezone":"Europe/Moscow",
    "iso:country":"RU",
    "name:rus_x_preferred":[
        "\u0411\u043e\u043b\u044c\u0448\u0430\u044f \u041f\u043e\u0433\u043e\u0440\u0435\u043b\u043a\u0430"
    ],
    "name:und_x_variant":[
        "Bol\u2019shaya Pogorelka"
    ],
    "wof:name":"Bol'shaya Pogorelka",
    "wof:placetype":"locality"
},
  "geometry": {"coordinates":[44.5435,57.2852],"type":"Point"}
}