{
  "type": "Feature",
  "properties": {
    "gn:admin1_code":"90.0",
    "gn:asciiname":"Bol'shaya Mar'ina",
    "gn:country_code":"RU",
    "gn:dem":187,
    "gn:feature_class":"P",
    "gn:feature_code":"PPL",
    "gn:name":"Bol\u2019shaya Mar\u2019ina",
    "gn:population":0,
    "gn:timezone":"Asia/Yekaterinburg",
    "iso:country":"RU",
    "name:rus_x_preferred":[
        "\u0411\u043e\u043b\u044c\u0448\u0430\u044f \u041c\u0430\u0440\u044c\u0438\u043d\u0430"
    ],
    "name:und_x_variant":[
        "Bol\u2019shaya Mar\u2019ina"
    ],
    "wof:name":"Bol'shaya Mar'ina",
    "wof:placetype":"locality"
},
  "geometry": {"coordinates":[57.08333,59.73333],"type":"Point"}
}