{
  "type": "Feature",
  "properties": {
    "gn:country":"RU",
    "gn:fcode":"PPL",
    "gn:pop":0,
    "iso:country":"RU",
    "name:rus_x_preferred":[
        "\u041a\u0430\u0447\u0430\u043b\u0438\u043d\u043e"
    ],
    "name:unk_x_variant":[
        "Kachalino"
    ],
    "qs:name":"Kachalin",
    "qs:name_adm0":"Russia",
    "qs:name_adm1":"Volgograd Oblast",
    "qs:photos_9r":0,
    "qs:photos_sr":0,
    "qs:placetype":"Town",
    "qs:pop_sr":"0",
    "wof:name":"Kachalin",
    "wof:placetype":"locality",
    "wof:population":0
},
  "geometry": {"coordinates":[44.05804,49.12148],"type":"Point"}
}