{
  "type": "Feature",
  "properties": {
    "gn:admin1_code":"11",
    "gn:asciiname":"Dede-Tala",
    "gn:country_code":"RU",
    "gn:dem":690,
    "gn:feature_class":"P",
    "gn:feature_code":"PPL",
    "gn:name":"Dede-Tala",
    "gn:population":0,
    "gn:timezone":"Asia/Irkutsk",
    "iso:country":"RU",
    "name:rus_x_preferred":[
        "\u0414\u044d\u0434\u044d-\u0422\u0430\u043b\u0430"
    ],
    "wof:name":"Dede-Tala",
    "wof:placetype":"locality"
},
  "geometry": {"coordinates":[108.79456999999999,51.58617],"type":"Point"}
}