{
  "type": "Feature",
  "properties": {
    "gn:admin1_code":"83",
    "gn:asciiname":"Mikhaylovskaya",
    "gn:country_code":"RU",
    "gn:dem":97,
    "gn:feature_class":"P",
    "gn:feature_code":"PPL",
    "gn:name":"Mikhaylovskaya",
    "gn:population":0,
    "gn:timezone":"Europe/Moscow",
    "iso:country":"RU",
    "name:eng_x_preferred":[
        "Mikhaylovskoye"
    ],
    "name:nor_x_preferred":[
        "Mikhajlovskaja"
    ],
    "name:rus_x_preferred":[
        "\u041c\u0438\u0445\u0430\u0439\u043b\u043e\u0432\u0441\u043a\u0430\u044f"
    ],
    "name:und_x_variant":[
        "Mikhaylovskaya"
    ],
    "wof:name":"Mikhaylovskaya",
    "wof:placetype":"locality"
},
  "geometry": {"coordinates":[42.37338,56.05127],"type":"Point"}
}