{
  "type": "Feature",
  "properties": {
    "gn:admin1_code":"85",
    "gn:asciiname":"Lipovitsa",
    "gn:country_code":"RU",
    "gn:dem":139,
    "gn:feature_class":"P",
    "gn:feature_code":"PPL",
    "gn:name":"Lipovitsa",
    "gn:population":0,
    "gn:timezone":"Europe/Moscow",
    "iso:country":"RU",
    "name:rus_x_preferred":[
        "\u041b\u0438\u043f\u043e\u0432\u0438\u0446\u0430"
    ],
    "name:und_x_variant":[
        "\u041b\u0438\u043f\u043e\u0432\u0438\u0446\u0430"
    ],
    "wof:name":"Lipovitsa",
    "wof:placetype":"locality"
},
  "geometry": {"coordinates":[41.29136,59.56491],"type":"Point"}
}