{
  "type": "Feature",
  "properties": {
    "gn:admin1_code":"54",
    "gn:asciiname":"Bogolyubovka",
    "gn:country_code":"RU",
    "gn:dem":113,
    "gn:feature_class":"P",
    "gn:feature_code":"PPL",
    "gn:name":"Bogolyubovka",
    "gn:population":0,
    "gn:timezone":"Asia/Omsk",
    "iso:country":"RU",
    "name:eng_x_preferred":[
        "Bogolyubovka"
    ],
    "name:nor_x_preferred":[
        "Bogoljubovka"
    ],
    "name:rus_x_preferred":[
        "\u0411\u043e\u0433\u043e\u043b\u044e\u0431\u043e\u0432\u043a\u0430"
    ],
    "name:und_x_variant":[
        "Bogolyubovo",
        "\u0411\u043e\u0433\u043e\u043b\u044e\u0431\u043e\u0432\u043a\u0430",
        "Bogolyubovka"
    ],
    "wof:name":"Bogolyubovka",
    "wof:placetype":"locality"
},
  "geometry": {"coordinates":[72.66070999999999,55.30609000000001],"type":"Point"}
}