{
  "type": "Feature",
  "properties": {
    "gn:admin1_code":"65",
    "gn:asciiname":"Sof'ino",
    "gn:country_code":"RU",
    "gn:dem":106,
    "gn:feature_class":"P",
    "gn:feature_code":"PPL",
    "gn:name":"Sof\u2019ino",
    "gn:population":0,
    "gn:timezone":"Europe/Samara",
    "iso:country":"RU",
    "name:rus_x_preferred":[
        "\u0421\u043e\u0444\u044c\u0438\u043d\u043e"
    ],
    "name:und_x_variant":[
        "Sofokno",
        "Sof\u2019ino",
        "\u0421\u043e\u0444\u044c\u0438\u043d\u043e"
    ],
    "wof:name":"Sof'ino",
    "wof:placetype":"locality"
},
  "geometry": {"coordinates":[52.06414,54.10516],"type":"Point"}
}