{
  "type": "Feature",
  "properties": {
    "gn:admin1_code":"60",
    "gn:asciiname":"Maloye Krupovo",
    "gn:country_code":"RU",
    "gn:dem":139,
    "gn:feature_class":"P",
    "gn:feature_code":"PPL",
    "gn:name":"Maloye Krupovo",
    "gn:population":0,
    "gn:timezone":"Europe/Moscow",
    "iso:country":"RU",
    "name:rus_x_preferred":[
        "\u041c\u0430\u043b\u043e\u0435 \u041a\u0440\u0443\u043f\u043e\u0432\u043e"
    ],
    "wof:name":"Maloye Krupovo",
    "wof:placetype":"locality"
},
  "geometry": {"coordinates":[28.2885,56.1259],"type":"Point"}
}