{
  "type": "Feature",
  "properties": {
    "gn:admin1_code":"69",
    "gn:asciiname":"Mysh'yaki",
    "gn:country_code":"RU",
    "gn:dem":239,
    "gn:feature_class":"P",
    "gn:feature_code":"PPL",
    "gn:name":"Mysh\u2019yaki",
    "gn:population":0,
    "gn:timezone":"Europe/Moscow",
    "iso:country":"RU",
    "wof:name":"Mysh'yaki",
    "wof:placetype":"locality"
},
  "geometry": {"coordinates":[35.27,55.60639000000001],"type":"Point"}
}