{
  "type": "Feature",
  "properties": {
    "gn:admin1_code":"9",
    "gn:asciiname":"Shaporevo",
    "gn:country_code":"RU",
    "gn:dem":124,
    "gn:feature_class":"P",
    "gn:feature_code":"PPL",
    "gn:name":"Shapor\u00ebvo",
    "gn:population":0,
    "gn:timezone":"Europe/Moscow",
    "iso:country":"RU",
    "name:rus_x_preferred":[
        "\u0428\u0430\u043f\u043e\u0440\u0451\u0432\u043e"
    ],
    "name:und_x_variant":[
        "Nikolayevka",
        "Shapor\u00ebva",
        "Shapor\u00ebvo",
        "Shopor\u00ebvo"
    ],
    "wof:name":"Shaporevo",
    "wof:placetype":"locality"
},
  "geometry": {"coordinates":[38.9851,50.4035],"type":"Point"}
}