{
  "type": "Feature",
  "properties": {
    "gn:country":"RU",
    "gn:fcode":"PPL",
    "gn:population":2110,
    "iso:country":"RU",
    "name:eng_x_preferred":[
        "Imeni Vorovskogo"
    ],
    "name:nor_x_preferred":[
        "Im.Vorovskogo"
    ],
    "name:rus_x_preferred":[
        "\u0418\u043c.\u0412\u043e\u0440\u043e\u0432\u0441\u043a\u043e\u0433\u043e"
    ],
    "name:rus_x_variant":[
        "\u0438\u043c\u0435\u043d\u0438 \u0412\u043e\u0440\u043e\u0432\u0441\u043a\u043e\u0433\u043e",
        "\u0418\u043c\u0435\u043d\u0438 \u0412\u043e\u0440\u043e\u0432\u0441\u043a\u043e\u0433\u043e"
    ],
    "name:und_x_variant":[
        "Pos\u00eblok Imeni Vorovskogo"
    ],
    "qs:name":"Imeni Vorovskogo",
    "qs:photos_9r":0,
    "qs:photos_sr":0,
    "qs:pop_sr":"4",
    "wd:wordcount":22,
    "wof:name":"Imeni Vorovskogo",
    "wof:placetype":"locality",
    "wof:population":2110
},
  "geometry": {"coordinates":[41.119,55.7237],"type":"Point"}
}