{
  "type": "Feature",
  "properties": {
    "gn:admin1_code":"60",
    "gn:asciiname":"Zerkali",
    "gn:country_code":"RU",
    "gn:dem":72,
    "gn:feature_class":"P",
    "gn:feature_code":"PPL",
    "gn:name":"Zerkali",
    "gn:population":0,
    "gn:timezone":"Europe/Moscow",
    "iso:country":"RU",
    "name:rus_x_preferred":[
        "\u0417\u0435\u0440\u043a\u0430\u043b\u0438"
    ],
    "wof:name":"Zerkali",
    "wof:placetype":"locality"
},
  "geometry": {"coordinates":[28.0892,57.12728000000001],"type":"Point"}
}