{
  "type": "Feature",
  "properties": {
    "gn:admin1_code":"6",
    "gn:asciiname":"Okruga",
    "gn:country_code":"RU",
    "gn:dem":114,
    "gn:feature_class":"P",
    "gn:feature_code":"PPL",
    "gn:name":"Okruga",
    "gn:population":0,
    "gn:timezone":"Europe/Moscow",
    "iso:country":"RU",
    "name:rus_x_preferred":[
        "\u041e\u043a\u0440\u0443\u0433\u0430"
    ],
    "wof:name":"Okruga",
    "wof:placetype":"locality"
},
  "geometry": {"coordinates":[38.95,62.11666999999999],"type":"Point"}
}