{
  "type": "Feature",
  "properties": {
    "gn:admin1_code":"85",
    "gn:asciiname":"Verkhovino",
    "gn:country_code":"RU",
    "gn:dem":220,
    "gn:feature_class":"P",
    "gn:feature_code":"PPL",
    "gn:name":"Verkhovino",
    "gn:population":0,
    "gn:timezone":"Europe/Moscow",
    "iso:country":"RU",
    "name:eng_x_preferred":[
        "Verkhovino"
    ],
    "name:nor_x_preferred":[
        "Verkhovino"
    ],
    "name:rus_x_preferred":[
        "\u0412\u0435\u0440\u0445\u043e\u0432\u0438\u043d\u043e"
    ],
    "name:und_x_variant":[
        "Verkhovina"
    ],
    "wof:name":"Verkhovino",
    "wof:placetype":"locality"
},
  "geometry": {"coordinates":[44.70766,59.55186],"type":"Point"}
}