{
  "type": "Feature",
  "properties": {
    "gn:admin1_code":"5",
    "gn:asciiname":"Zhuravlevka",
    "gn:country_code":"RU",
    "gn:dem":95,
    "gn:feature_class":"P",
    "gn:feature_code":"PPL",
    "gn:name":"Zhuravl\u00ebvka",
    "gn:population":0,
    "gn:timezone":"Asia/Yakutsk",
    "iso:country":"RU",
    "name:eng_x_preferred":[
        "Zhuravl\u00ebvka"
    ],
    "name:nor_x_preferred":[
        "Zjuravlevka"
    ],
    "name:rus_x_preferred":[
        "\u0416\u0443\u0440\u0430\u0432\u043b\u0435\u0432\u043a\u0430"
    ],
    "name:rus_x_variant":[
        "\u0416\u0443\u0440\u0430\u0432\u043b\u0451\u0432\u043a\u0430"
    ],
    "name:und_x_variant":[
        "Zhuravlevo",
        "Zhuravl\u00ebvka"
    ],
    "wof:name":"Zhuravlevka",
    "wof:placetype":"locality"
},
  "geometry": {"coordinates":[129.99741,49.0812],"type":"Point"}
}