{
  "type": "Feature",
  "properties": {
    "gn:admin1_code":"56",
    "gn:asciiname":"Pyryatinka",
    "gn:country_code":"RU",
    "gn:dem":200,
    "gn:feature_class":"P",
    "gn:feature_code":"PPL",
    "gn:name":"Pyryatinka",
    "gn:population":0,
    "gn:timezone":"Europe/Moscow",
    "iso:country":"RU",
    "name:rus_x_preferred":[
        "\u041f\u044b\u0440\u044f\u0442\u0438\u043d\u043a\u0430"
    ],
    "name:und_x_variant":[
        "Pyryatino",
        "Pyryatinka",
        "\u041f\u044b\u0440\u044f\u0442\u0438\u043d\u043a\u0430"
    ],
    "wof:name":"Pyryatinka",
    "wof:placetype":"locality"
},
  "geometry": {"coordinates":[35.16414,53.24603000000001],"type":"Point"}
}