{
  "type": "Feature",
  "properties": {
    "gn:admin1_code":"85",
    "gn:asciiname":"Sotnikovo",
    "gn:country_code":"RU",
    "gn:dem":77,
    "gn:feature_class":"P",
    "gn:feature_code":"PPL",
    "gn:name":"Sotnikovo",
    "gn:population":0,
    "gn:timezone":"Europe/Moscow",
    "iso:country":"RU",
    "name:rus_x_preferred":[
        "\u0421\u043e\u0442\u043d\u0438\u043a\u043e\u0432\u043e"
    ],
    "wof:name":"Sotnikovo",
    "wof:placetype":"locality"
},
  "geometry": {"coordinates":[46.3336,60.807],"type":"Point"}
}