{
  "type": "Feature",
  "properties": {
    "gn:admin1_code":"32",
    "gn:asciiname":"Voytekhovskiye",
    "gn:cc2":"RU",
    "gn:country_code":"RU",
    "gn:dem":5,
    "gn:feature_class":"P",
    "gn:feature_code":"PPL",
    "gn:name":"Voytekhovskiye",
    "gn:population":0,
    "gn:timezone":"Asia/Yekaterinburg",
    "iso:country":"RU",
    "name:eng_x_preferred":[
        "Voytekhovskiye"
    ],
    "name:nor_x_preferred":[
        "Vojtekhovskije"
    ],
    "name:rus_x_preferred":[
        "\u0412\u043e\u0439\u0442\u0435\u0445\u043e\u0432\u0441\u043a\u0438\u0435"
    ],
    "name:und_x_variant":[
        "Voytekhovskoye",
        "Voytekhovskiye"
    ],
    "wof:name":"Voytekhovskiye",
    "wof:placetype":"locality"
},
  "geometry": {"coordinates":[65.59999999999999,63.96666999999999],"type":"Point"}
}