{
  "type": "Feature",
  "properties": {
    "gn:admin1_code":"57.0",
    "gn:asciiname":"Intenkhoz",
    "gn:country_code":"RU",
    "gn:dem":161,
    "gn:feature_class":"P",
    "gn:feature_code":"PPL",
    "gn:name":"Intenkhoz",
    "gn:population":0,
    "gn:timezone":"Europe/Moscow",
    "iso:country":"RU",
    "name:rus_x_preferred":[
        "\u0418\u043d\u0442\u0435\u043d\u0445\u043e\u0437"
    ],
    "wof:name":"Intenkhoz",
    "wof:placetype":"locality"
},
  "geometry": {"coordinates":[44.3691,52.7112],"type":"Point"}
}