{
  "type": "Feature",
  "properties": {
    "gn:admin1_code":"91",
    "gn:asciiname":"Urman",
    "gn:country_code":"RU",
    "gn:dem":276,
    "gn:feature_class":"P",
    "gn:feature_code":"PPL",
    "gn:name":"Urman",
    "gn:population":0,
    "gn:timezone":"Asia/Krasnoyarsk",
    "iso:country":"RU",
    "name:eng_x_preferred":[
        "Urman"
    ],
    "name:nor_x_preferred":[
        "Urman"
    ],
    "name:rus_x_preferred":[
        "\u0423\u0440\u043c\u0430\u043d"
    ],
    "wof:name":"Urman",
    "wof:placetype":"locality"
},
  "geometry": {"coordinates":[92.9806,55.5553],"type":"Point"}
}