{
  "type": "Feature",
  "properties": {
    "gn:admin1_code":"69",
    "gn:asciiname":"Rebrovo",
    "gn:cc2":"RU",
    "gn:country_code":"RU",
    "gn:dem":223,
    "gn:feature_class":"P",
    "gn:feature_code":"PPL",
    "gn:name":"Rebrovo",
    "gn:population":0,
    "gn:timezone":"Europe/Moscow",
    "iso:country":"RU",
    "name:bul_x_preferred":[
        "\u0420\u0435\u0431\u0440\u043e\u0432\u043e"
    ],
    "name:ceb_x_preferred":[
        "Rebrovo"
    ],
    "name:fas_x_preferred":[
        "\u0631\u0628\u0631\u0648\u0641\u0648"
    ],
    "name:kaz_x_preferred":[
        "\u0420\u0435\u0431\u0440\u043e\u0432\u043e"
    ],
    "name:ron_x_preferred":[
        "Rebrovo"
    ],
    "name:rus_x_preferred":[
        "\u0420\u0435\u0431\u0440\u043e\u0432\u043e"
    ],
    "name:swe_x_preferred":[
        "Rebrovo"
    ],
    "name:ukr_x_preferred":[
        "\u0420\u0435\u0431\u0440\u043e\u0432\u043e"
    ],
    "name:und_x_variant":[
        "Rebrova"
    ],
    "wof:name":"Rebrovo",
    "wof:placetype":"locality"
},
  "geometry": {"coordinates":[33.88944,55.14944000000001],"type":"Point"}
}