{
  "type": "Feature",
  "properties": {
    "gn:admin1_code":"70",
    "gn:asciiname":"Manychstroy",
    "gn:country_code":"RU",
    "gn:dem":23,
    "gn:feature_class":"P",
    "gn:feature_code":"PPL",
    "gn:name":"Manychstroy",
    "gn:population":0,
    "gn:timezone":"Europe/Moscow",
    "iso:country":"RU",
    "name:rus_x_preferred":[
        "\u041c\u0430\u043d\u044b\u0447\u0441\u0442\u0440\u043e\u0439"
    ],
    "wof:name":"Manychstroy",
    "wof:placetype":"locality"
},
  "geometry": {"coordinates":[45.23556,44.96556],"type":"Point"}
}