{
  "type": "Feature",
  "properties": {
    "gn:admin1_code":"61.0",
    "gn:asciiname":"Rynok-Romanovskiy",
    "gn:country_code":"RU",
    "gn:dem":19,
    "gn:feature_class":"P",
    "gn:feature_code":"PPL",
    "gn:name":"Rynok-Romanovskiy",
    "gn:population":0,
    "gn:timezone":"Europe/Moscow",
    "iso:country":"RU",
    "name:rus_x_preferred":[
        "\u0420\u044b\u043d\u043e\u043a-\u0420\u043e\u043c\u0430\u043d\u043e\u0432\u0441\u043a\u0438\u0439"
    ],
    "wof:name":"Rynok-Romanovskiy",
    "wof:placetype":"locality"
},
  "geometry": {"coordinates":[42.017,47.6263],"type":"Point"}
}