{
  "type": "Feature",
  "properties": {
    "gn:admin1_code":"62",
    "gn:asciiname":"Sidanovo",
    "gn:country_code":"RU",
    "gn:dem":137,
    "gn:feature_class":"P",
    "gn:feature_code":"PPL",
    "gn:name":"Sidanovo",
    "gn:population":0,
    "gn:timezone":"Europe/Moscow",
    "iso:country":"RU",
    "name:rus_x_preferred":[
        "\u0421\u0438\u0434\u0430\u043d\u043e\u0432\u043e"
    ],
    "wof:name":"Sidanovo",
    "wof:placetype":"locality"
},
  "geometry": {"coordinates":[41.5974,54.9672],"type":"Point"}
}