{
  "type": "Feature",
  "properties": {
    "gn:admin1_code":"17",
    "gn:asciiname":"Shiguri",
    "gn:country_code":"RU",
    "gn:dem":-15,
    "gn:feature_class":"P",
    "gn:feature_code":"PPL",
    "gn:name":"Shiguri",
    "gn:population":0,
    "gn:timezone":"Europe/Moscow",
    "iso:country":"RU",
    "name:rus_x_preferred":[
        "\u0428\u0438\u0433\u0443\u0440\u0438"
    ],
    "name:und_x_variant":[
        "\u0428\u0438\u0433\u0443\u0440\u0438"
    ],
    "wof:name":"Shiguri",
    "wof:placetype":"locality"
},
  "geometry": {"coordinates":[47.05802,43.67828],"type":"Point"}
}