{
  "type": "Feature",
  "properties": {
    "gn:admin1_code":"08",
    "gn:asciiname":"Shaydala",
    "gn:country_code":"RU",
    "gn:dem":341,
    "gn:feature_class":"P",
    "gn:feature_code":"PPL",
    "gn:name":"Shaydala",
    "gn:population":0,
    "gn:timezone":"Asia/Yekaterinburg",
    "iso:country":"RU",
    "name:eng_x_preferred":[
        "Shaydala"
    ],
    "name:nor_x_preferred":[
        "Sjajdala"
    ],
    "name:rus_x_preferred":[
        "\u0428\u0430\u0439\u0434\u0430\u043b\u0430"
    ],
    "name:und_x_variant":[
        "\u0428\u0430\u0439\u0434\u0430\u043b\u0430",
        "Shaydala"
    ],
    "wof:name":"Shaydala",
    "wof:placetype":"locality"
},
  "geometry": {"coordinates":[59.20611,56.12278000000001],"type":"Point"}
}