{
  "type": "Feature",
  "properties": {
    "gn:admin1_code":"69",
    "gn:asciiname":"Laptevo",
    "gn:country_code":"RU",
    "gn:dem":224,
    "gn:feature_class":"P",
    "gn:feature_code":"PPL",
    "gn:name":"Lapt\u00ebvo",
    "gn:population":0,
    "gn:timezone":"Europe/Moscow",
    "iso:country":"RU",
    "name:rus_x_preferred":[
        "\u041b\u0430\u043f\u0442\u0451\u0432\u043e"
    ],
    "name:und_x_variant":[
        "Lapt\u00ebvo"
    ],
    "wof:name":"Laptevo",
    "wof:placetype":"locality"
},
  "geometry": {"coordinates":[33.83361,55.02111],"type":"Point"}
}