{
  "type": "Feature",
  "properties": {
    "gn:admin1_code":"43",
    "gn:asciiname":"Klicheno",
    "gn:country_code":"RU",
    "gn:dem":195,
    "gn:feature_class":"P",
    "gn:feature_code":"PPL",
    "gn:name":"Klicheno",
    "gn:population":0,
    "gn:timezone":"Europe/Moscow",
    "iso:country":"RU",
    "name:rus_x_preferred":[
        "\u041a\u043b\u0438\u0447\u0435\u043d\u043e"
    ],
    "name:und_x_variant":[
        "Klichino",
        "Klicheno"
    ],
    "wof:name":"Klicheno",
    "wof:placetype":"locality"
},
  "geometry": {"coordinates":[38.01534,52.95513],"type":"Point"}
}