{
  "type": "Feature",
  "properties": {
    "gn:admin1_code":"84",
    "gn:asciiname":"Plesovskiy",
    "gn:country_code":"RU",
    "gn:dem":96,
    "gn:feature_class":"P",
    "gn:feature_code":"PPL",
    "gn:name":"Plesovskiy",
    "gn:population":0,
    "gn:timezone":"Europe/Volgograd",
    "iso:country":"RU",
    "name:rus_x_preferred":[
        "\u041f\u043b\u0435\u0441\u043e\u0432\u0441\u043a\u0438\u0439"
    ],
    "name:und_x_variant":[
        "\u041f\u043b\u0435\u0441\u043e\u0432\u0441\u043a\u0438\u0439"
    ],
    "wof:name":"Plesovskiy",
    "wof:placetype":"locality"
},
  "geometry": {"coordinates":[43.06667,48.28333],"type":"Point"}
}