{
  "type": "Feature",
  "properties": {
    "gn:admin1_code":"57.0",
    "gn:asciiname":"Gay",
    "gn:country_code":"RU",
    "gn:dem":193,
    "gn:feature_class":"P",
    "gn:feature_code":"PPL",
    "gn:name":"Gay",
    "gn:population":0,
    "gn:timezone":"Europe/Moscow",
    "iso:country":"RU",
    "name:rus_x_preferred":[
        "\u0413\u0430\u0439"
    ],
    "name:und_x_variant":[
        "\u0413\u0430\u0439"
    ],
    "wof:name":"Gay",
    "wof:placetype":"locality"
},
  "geometry": {"coordinates":[43.94517000000001,52.9639],"type":"Point"}
}