{
  "type": "Feature",
  "properties": {
    "gn:admin1_code":"70",
    "gn:asciiname":"Starotarskiy",
    "gn:cc2":"RU",
    "gn:country_code":"RU",
    "gn:dem":468,
    "gn:feature_class":"P",
    "gn:feature_code":"PPL",
    "gn:name":"Starotarskiy",
    "gn:population":0,
    "gn:timezone":"Europe/Moscow",
    "iso:country":"RU",
    "name:rus_x_preferred":[
        "\u0421\u0442\u0430\u0440\u043e\u0442\u0430\u0440\u0441\u043a\u0438\u0439"
    ],
    "name:und_x_variant":[
        "Starotarskaya",
        "Starotarskiy",
        "\u0421\u0442\u0430\u0440\u043e\u0442\u0430\u0440\u0441\u043a\u0438\u0439"
    ],
    "wof:name":"Starotarskiy",
    "wof:placetype":"locality"
},
  "geometry": {"coordinates":[43.07361,44.39194000000001],"type":"Point"}
}