{
  "type": "Feature",
  "properties": {
    "gn:admin1_code":"55",
    "gn:asciiname":"Sredneaskarovo",
    "gn:country_code":"RU",
    "gn:dem":160,
    "gn:feature_class":"P",
    "gn:feature_code":"PPL",
    "gn:name":"Sredneaskarovo",
    "gn:population":0,
    "gn:timezone":"Asia/Yekaterinburg",
    "iso:country":"RU",
    "name:rus_x_preferred":[
        "\u0421\u0440\u0435\u0434\u043d\u0435\u0430\u0441\u043a\u0430\u0440\u043e\u0432\u043e"
    ],
    "name:und_x_variant":[
        "Sredneye Askarovo",
        "Sredneaskarovo"
    ],
    "wof:name":"Sredneaskarovo",
    "wof:placetype":"locality"
},
  "geometry": {"coordinates":[56.59087,52.05485],"type":"Point"}
}