{
  "type": "Feature",
  "properties": {
    "gn:admin1_code":"33",
    "gn:asciiname":"Lukoyanka",
    "gn:country_code":"RU",
    "gn:dem":108,
    "gn:feature_class":"P",
    "gn:feature_code":"PPL",
    "gn:name":"Lukoyanka",
    "gn:population":0,
    "gn:timezone":"Europe/Kirov",
    "iso:country":"RU",
    "name:rus_x_preferred":[
        "\u041b\u0443\u043a\u043e\u044f\u043d\u043a\u0430"
    ],
    "wof:name":"Lukoyanka",
    "wof:placetype":"locality"
},
  "geometry": {"coordinates":[47.87300000000001,57.6757],"type":"Point"}
}