{
  "type": "Feature",
  "properties": {
    "gn:admin1_code":"62",
    "gn:asciiname":"Plishkino",
    "gn:country_code":"RU",
    "gn:dem":130,
    "gn:feature_class":"P",
    "gn:feature_code":"PPL",
    "gn:name":"Plishkino",
    "gn:population":0,
    "gn:timezone":"Europe/Moscow",
    "iso:country":"RU",
    "name:che_x_preferred":[
        "\u041f\u043b\u0438\u0448\u043a\u0438\u043d\u043e"
    ],
    "name:eng_x_preferred":[
        "Plishkino"
    ],
    "name:nor_x_preferred":[
        "Plisjkino"
    ],
    "name:rus_x_preferred":[
        "\u041f\u043b\u0438\u0448\u043a\u0438\u043d\u043e"
    ],
    "name:und_x_variant":[
        "\u041f\u043b\u0438\u0448\u043a\u0438\u043d\u043e",
        "Plishkino"
    ],
    "wof:name":"Plishkino",
    "wof:placetype":"locality"
},
  "geometry": {"coordinates":[40.46702,55.21937],"type":"Point"}
}