{
  "type": "Feature",
  "properties": {
    "gn:admin1_code":"13",
    "gn:asciiname":"Cheremushki",
    "gn:country_code":"RU",
    "gn:dem":204,
    "gn:feature_class":"P",
    "gn:feature_code":"PPL",
    "gn:name":"Cher\u00ebmushki",
    "gn:population":0,
    "gn:timezone":"Asia/Yekaterinburg",
    "iso:country":"RU",
    "name:rus_x_preferred":[
        "\u0427\u0435\u0440\u0451\u043c\u0443\u0448\u043a\u0438"
    ],
    "name:und_x_variant":[
        "Cher\u00ebmushki",
        "\u0427\u0435\u0440\u0451\u043c\u0443\u0448\u043a\u0438"
    ],
    "wof:name":"Cheremushki",
    "wof:placetype":"locality"
},
  "geometry": {"coordinates":[61.7145,55.3455],"type":"Point"}
}