{
  "type": "Feature",
  "properties": {
    "gn:admin1_code":"92",
    "gn:asciiname":"Yuzhnyye Koryaki",
    "gn:country_code":"RU",
    "gn:dem":97,
    "gn:feature_class":"P",
    "gn:feature_code":"PPL",
    "gn:name":"Yuzhnyye Koryaki",
    "gn:population":0,
    "gn:timezone":"Asia/Kamchatka",
    "iso:country":"RU",
    "name:rus_x_preferred":[
        "\u042e\u0436\u043d\u044b\u0435 \u041a\u043e\u0440\u044f\u043a\u0438"
    ],
    "wof:name":"Yuzhnyye Koryaki",
    "wof:placetype":"locality"
},
  "geometry": {"coordinates":[158.12908000000004,53.26441],"type":"Point"}
}