{
  "type": "Feature",
  "properties": {
    "gn:admin1_code":"60",
    "gn:asciiname":"Plaksino",
    "gn:country_code":"RU",
    "gn:dem":146,
    "gn:feature_class":"P",
    "gn:feature_code":"PPL",
    "gn:name":"Plaksino",
    "gn:population":0,
    "gn:timezone":"Europe/Moscow",
    "iso:country":"RU",
    "name:eng_x_preferred":[
        "Plaksino"
    ],
    "name:nor_x_preferred":[
        "Plaksino"
    ],
    "name:rus_x_preferred":[
        "\u041f\u043b\u0430\u043a\u0441\u0438\u043d\u043e"
    ],
    "name:und_x_variant":[
        "Plaksina"
    ],
    "wof:name":"Plaksino",
    "wof:placetype":"locality"
},
  "geometry": {"coordinates":[30.69072,56.18139],"type":"Point"}
}