{
  "type": "Feature",
  "properties": {
    "gn:admin1_code":"43",
    "gn:asciiname":"Batsevka",
    "gn:country_code":"RU",
    "gn:dem":159,
    "gn:feature_class":"P",
    "gn:feature_code":"PPL",
    "gn:name":"Batsevka",
    "gn:population":0,
    "gn:timezone":"Europe/Moscow",
    "iso:country":"RU",
    "name:rus_x_preferred":[
        "\u0411\u0430\u0446\u0435\u0432\u043a\u0430"
    ],
    "wof:name":"Batsevka",
    "wof:placetype":"locality"
},
  "geometry": {"coordinates":[38.1018,51.9559],"type":"Point"}
}