{
  "type": "Feature",
  "properties": {
    "gn:admin1_code":"87",
    "gn:asciiname":"Yuribey",
    "gn:country_code":"RU",
    "gn:dem":12,
    "gn:feature_class":"P",
    "gn:feature_code":"PPL",
    "gn:name":"Yuribey",
    "gn:population":0,
    "gn:timezone":"Asia/Yekaterinburg",
    "iso:country":"RU",
    "name:eng_x_preferred":[
        "Yuribey"
    ],
    "name:nor_x_preferred":[
        "Juribej"
    ],
    "name:rus_x_preferred":[
        "\u042e\u0440\u0438\u0431\u0435\u0439"
    ],
    "name:und_x_variant":[
        "Factoriya Yurebey",
        "Yuribey"
    ],
    "wof:name":"Yuribey",
    "wof:placetype":"locality"
},
  "geometry": {"coordinates":[76.95765,71.03536],"type":"Point"}
}