{
  "type": "Feature",
  "properties": {
    "gn:admin1_code":"46.0",
    "gn:asciiname":"Boldasevo",
    "gn:country_code":"RU",
    "gn:dem":129,
    "gn:feature_class":"P",
    "gn:feature_code":"PPL",
    "gn:name":"Boldasevo",
    "gn:population":0,
    "gn:timezone":"Europe/Moscow",
    "iso:country":"RU",
    "name:eng_x_preferred":[
        "Boldasevo"
    ],
    "name:nor_x_preferred":[
        "Boldasevo"
    ],
    "name:rus_x_preferred":[
        "\u0411\u043e\u043b\u0434\u0430\u0441\u0435\u0432\u043e"
    ],
    "name:und_x_variant":[
        "Baldasevo"
    ],
    "wof:name":"Boldasevo",
    "wof:placetype":"locality"
},
  "geometry": {"coordinates":[45.55109,54.70923000000001],"type":"Point"}
}