{
  "type": "Feature",
  "properties": {
    "gn:admin1_code":"85",
    "gn:asciiname":"Ploskoye",
    "gn:country_code":"RU",
    "gn:dem":178,
    "gn:feature_class":"P",
    "gn:feature_code":"PPL",
    "gn:name":"Ploskoye",
    "gn:population":0,
    "gn:timezone":"Europe/Moscow",
    "iso:country":"RU",
    "name:eng_x_preferred":[
        "Ploskoye"
    ],
    "name:nor_x_preferred":[
        "Ploskoje"
    ],
    "name:rus_x_preferred":[
        "\u041f\u043b\u043e\u0441\u043a\u043e\u0435"
    ],
    "name:und_x_variant":[
        "Chilkova"
    ],
    "wof:name":"Ploskoye",
    "wof:placetype":"locality"
},
  "geometry": {"coordinates":[35.6957,59.7364],"type":"Point"}
}