{
  "type": "Feature",
  "properties": {
    "gn:admin1_code":"69.0",
    "gn:asciiname":"Blagodatnoye",
    "gn:country_code":"RU",
    "gn:dem":188,
    "gn:feature_class":"P",
    "gn:feature_code":"PPL",
    "gn:name":"Blagodatnoye",
    "gn:population":0,
    "gn:timezone":"Europe/Moscow",
    "iso:country":"RU",
    "name:rus_x_preferred":[
        "\u0411\u043b\u0430\u0433\u043e\u0434\u0430\u0442\u043d\u043e\u0435"
    ],
    "name:und_x_variant":[
        "Kobel\u00ebvo",
        "Blagodatnoye",
        "Blagodatnaya"
    ],
    "wof:name":"Blagodatnoye",
    "wof:placetype":"locality"
},
  "geometry": {"coordinates":[34.82312,55.77059000000001],"type":"Point"}
}