{
  "type": "Feature",
  "properties": {
    "gn:admin1_code":"33",
    "gn:asciiname":"Shchuchkino",
    "gn:country_code":"RU",
    "gn:dem":198,
    "gn:feature_class":"P",
    "gn:feature_code":"PPL",
    "gn:name":"Shchuchkino",
    "gn:population":0,
    "gn:timezone":"Europe/Kirov",
    "iso:country":"RU",
    "name:eng_x_preferred":[
        "Shchuchkino"
    ],
    "name:nor_x_preferred":[
        "Sjtsjutsjkino"
    ],
    "name:rus_x_preferred":[
        "\u0429\u0443\u0447\u043a\u0438\u043d\u043e"
    ],
    "name:und_x_variant":[
        "Shchuchkiny",
        "\u0429\u0443\u0447\u043a\u0438\u043d\u043e",
        "Shchuchkino"
    ],
    "wof:name":"Shchuchkino",
    "wof:placetype":"locality"
},
  "geometry": {"coordinates":[50.88417000000001,59.78807],"type":"Point"}
}