{
  "type": "Feature",
  "properties": {
    "gn:admin1_code":"17",
    "gn:asciiname":"Gunnamakhi",
    "gn:country_code":"RU",
    "gn:dem":1706,
    "gn:feature_class":"P",
    "gn:feature_code":"PPL",
    "gn:name":"Gunnamakhi",
    "gn:population":0,
    "gn:timezone":"Europe/Moscow",
    "iso:country":"RU",
    "name:rus_x_preferred":[
        "\u0413\u0443\u043d\u043d\u0430\u043c\u0430\u0445\u0438"
    ],
    "wof:name":"Gunnamakhi",
    "wof:placetype":"locality"
},
  "geometry": {"coordinates":[47.37328,42.04729],"type":"Point"}
}