{
  "type": "Feature",
  "properties": {
    "gn:admin1_code":"73",
    "gn:asciiname":"Churayevo",
    "gn:country_code":"RU",
    "gn:dem":131,
    "gn:feature_class":"P",
    "gn:feature_code":"PPL",
    "gn:name":"Churayevo",
    "gn:population":0,
    "gn:timezone":"Europe/Moscow",
    "iso:country":"RU",
    "name:rus_x_preferred":[
        "\u0427\u0443\u0440\u0430\u0435\u0432\u043e"
    ],
    "name:und_x_variant":[
        "\u0427\u0443\u0440\u0430\u0435\u0432\u043e"
    ],
    "wof:name":"Churayevo",
    "wof:placetype":"locality"
},
  "geometry": {"coordinates":[53.6585,55.6383],"type":"Point"}
}