{
  "type": "Feature",
  "properties": {
    "gn:admin1_code":"73",
    "gn:asciiname":"Churayevo",
    "gn:country_code":"RU",
    "gn:dem":131,
    "gn:feature_class":"P",
    "gn:feature_code":"PPL",
    "gn:name":"Churayevo",
    "gn:population":0,
    "gn:timezone":"Europe/Moscow",
    "iso:country":"RU",
    "name:bak_x_preferred":[
        "\u0421\u0443\u0440\u0430\u0439"
    ],
    "name:che_x_preferred":[
        "\u0427\u0443\u0440\u0430\u0435\u0432\u043e"
    ],
    "name:hye_x_preferred":[
        "\u0549\u0578\u0582\u0580\u0561\u0587\u0578"
    ],
    "name:kat_x_preferred":[
        "\u10e9\u10e3\u10e0\u10d0\u10d4\u10d5\u10dd"
    ],
    "name:kaz_x_preferred":[
        "\u0427\u0443\u0440\u0430"
    ],
    "name:rus_x_preferred":[
        "\u0427\u0443\u0440\u0430\u0435\u0432\u043e"
    ],
    "name:tat_x_preferred":[
        "\u0427\u0443\u0440\u0430\u0439"
    ],
    "name:ukr_x_preferred":[
        "\u0427\u0443\u0440\u0430\u0454\u0432\u043e"
    ],
    "name:und_x_variant":[
        "\u0427\u0443\u0440\u0430\u0435\u0432\u043e"
    ],
    "wof:name":"Churayevo",
    "wof:placetype":"locality"
},
  "geometry": {"coordinates":[53.6585,55.6383],"type":"Point"}
}