{
  "type": "Feature",
  "properties": {
    "gn:admin1_code":"77",
    "gn:asciiname":"Borzikovo",
    "gn:country_code":"RU",
    "gn:dem":133,
    "gn:feature_class":"P",
    "gn:feature_code":"PPL",
    "gn:name":"Borzikovo",
    "gn:population":0,
    "gn:timezone":"Europe/Moscow",
    "iso:country":"RU",
    "name:rus_x_preferred":[
        "\u0411\u043e\u0440\u0437\u0438\u043a\u043e\u0432\u043e"
    ],
    "wof:name":"Borzikovo",
    "wof:placetype":"locality"
},
  "geometry": {"coordinates":[36.9754,56.9365],"type":"Point"}
}