{
  "type": "Feature",
  "properties": {
    "gn:admin1_code":"85",
    "gn:asciiname":"Shnyakino",
    "gn:country_code":"RU",
    "gn:dem":144,
    "gn:feature_class":"P",
    "gn:feature_code":"PPL",
    "gn:name":"Shnyakino",
    "gn:population":0,
    "gn:timezone":"Europe/Moscow",
    "iso:country":"RU",
    "name:rus_x_preferred":[
        "\u0428\u043d\u044f\u043a\u0438\u043d\u043e"
    ],
    "name:und_x_variant":[
        "\u0428\u043d\u044f\u043a\u0438\u043d\u043e"
    ],
    "wof:name":"Shnyakino",
    "wof:placetype":"locality"
},
  "geometry": {"coordinates":[39.97063,58.99513],"type":"Point"}
}