{
  "type": "Feature",
  "properties": {
    "gn:admin1_code":"60",
    "gn:asciiname":"Starokozlovo",
    "gn:country_code":"RU",
    "gn:dem":126,
    "gn:feature_class":"P",
    "gn:feature_code":"PPL",
    "gn:name":"Starokozlovo",
    "gn:population":0,
    "gn:timezone":"Europe/Moscow",
    "iso:country":"RU",
    "name:rus_x_preferred":[
        "\u0421\u0442\u0430\u0440\u043e\u043a\u043e\u0437\u043b\u043e\u0432\u043e"
    ],
    "wof:name":"Starokozlovo",
    "wof:placetype":"locality"
},
  "geometry": {"coordinates":[28.8738,56.3225],"type":"Point"}
}