{
  "type": "Feature",
  "properties": {
    "gn:admin1_code":"56",
    "gn:asciiname":"Sakovninki",
    "gn:country_code":"RU",
    "gn:dem":220,
    "gn:feature_class":"P",
    "gn:feature_code":"PPL",
    "gn:name":"Sakovninki",
    "gn:population":0,
    "gn:timezone":"Europe/Moscow",
    "iso:country":"RU",
    "name:rus_x_preferred":[
        "\u0421\u0430\u043a\u043e\u0432\u043d\u0438\u043d\u043a\u0438"
    ],
    "name:und_x_variant":[
        "Sakovinka",
        "Sakovninki"
    ],
    "wof:name":"Sakovninki",
    "wof:placetype":"locality"
},
  "geometry": {"coordinates":[35.844,52.4313],"type":"Point"}
}