{
  "type": "Feature",
  "properties": {
    "gn:admin1_code":"38.0",
    "gn:asciiname":"Bugas",
    "gn:country_code":"RU",
    "gn:dem":16,
    "gn:feature_class":"P",
    "gn:feature_code":"PPL",
    "gn:name":"Bugas",
    "gn:population":0,
    "gn:timezone":"Europe/Moscow",
    "iso:country":"RU",
    "name:rus_x_preferred":[
        "\u0411\u0443\u0433\u0430\u0441"
    ],
    "name:und_x_variant":[
        "\u0411\u0443\u0433\u0430\u0441"
    ],
    "wof:name":"Bugas",
    "wof:placetype":"locality"
},
  "geometry": {"coordinates":[36.88417000000001,45.14667],"type":"Point"}
}