{
  "type": "Feature",
  "properties": {
    "gn:admin1_code":"47",
    "gn:asciiname":"Markovo",
    "gn:country_code":"RU",
    "gn:dem":170,
    "gn:feature_class":"P",
    "gn:feature_code":"PPL",
    "gn:name":"Markovo",
    "gn:population":0,
    "gn:timezone":"Europe/Moscow",
    "iso:country":"RU",
    "name:nor_x_preferred":[
        "Markovo"
    ],
    "name:rus_x_preferred":[
        "\u041c\u0430\u0440\u043a\u043e\u0432\u043e"
    ],
    "wof:name":"Markovo",
    "wof:placetype":"locality"
},
  "geometry": {"coordinates":[35.44483,56.22147],"type":"Point"}
}