{
  "type": "Feature",
  "properties": {
    "gn:admin1_code":"90",
    "gn:asciiname":"Gorshki",
    "gn:country_code":"RU",
    "gn:dem":118,
    "gn:feature_class":"P",
    "gn:feature_code":"PPL",
    "gn:name":"Gorshki",
    "gn:population":0,
    "gn:timezone":"Asia/Yekaterinburg",
    "iso:country":"RU",
    "name:eng_x_preferred":[
        "Gorshki"
    ],
    "name:nor_x_preferred":[
        "Gorsjki"
    ],
    "name:rus_x_preferred":[
        "\u0413\u043e\u0440\u0448\u043a\u0438"
    ],
    "name:und_x_variant":[
        "\u0413\u043e\u0440\u0448\u043a\u0438"
    ],
    "wof:name":"Gorshki",
    "wof:placetype":"locality"
},
  "geometry": {"coordinates":[55.7425,57.9382],"type":"Point"}
}