{
  "type": "Feature",
  "properties": {
    "gn:admin1_code":"76",
    "gn:asciiname":"Kramskoye",
    "gn:country_code":"RU",
    "gn:dem":180,
    "gn:feature_class":"P",
    "gn:feature_code":"PPL",
    "gn:name":"Kramskoye",
    "gn:population":0,
    "gn:timezone":"Europe/Moscow",
    "iso:country":"RU",
    "name:rus_x_preferred":[
        "\u041a\u0440\u0430\u043c\u0441\u043a\u043e\u0435"
    ],
    "wof:name":"Kramskoye",
    "wof:placetype":"locality"
},
  "geometry": {"coordinates":[38.4847,53.5731],"type":"Point"}
}