{
  "type": "Feature",
  "properties": {
    "gn:gn_country":"RU",
    "gn:gn_fcode":"PPL",
    "gn:gn_pop":5383,
    "gn:population":5383,
    "iso:country":"RU",
    "name:eng_x_preferred":[
        "Bureya"
    ],
    "name:nld_x_preferred":[
        "Boereja"
    ],
    "name:nor_x_preferred":[
        "Bureja"
    ],
    "name:rus_x_preferred":[
        "\u0411\u0443\u0440\u0435\u044f"
    ],
    "name:unk_x_variant":[
        "Bureia"
    ],
    "qs_pg:aaroncc":"RU",
    "qs_pg:gn_country":"RU",
    "qs_pg:gn_fcode":"PPL",
    "qs_pg:gn_pop":5383,
    "qs_pg:name":"Bureya",
    "qs_pg:photos_9r":0,
    "qs_pg:photos_sr":0,
    "qs_pg:pop_sr":5,
    "qs_pg:qs_pg_placetype":"locality",
    "wof:name":"Bureya",
    "wof:placetype":"locality",
    "wof:population":5383
},
  "geometry": {"coordinates":[129.81278,49.81212],"type":"Point"}
}