{
  "type": "Feature",
  "properties": {
    "gn:admin1_code":"70",
    "gn:asciiname":"Karmalinovskaya",
    "gn:country_code":"RU",
    "gn:dem":140,
    "gn:feature_class":"P",
    "gn:feature_code":"PPL",
    "gn:name":"Karmalinovskaya",
    "gn:population":0,
    "gn:timezone":"Europe/Moscow",
    "iso:country":"RU",
    "name:eng_x_preferred":[
        "Karmalinovskaya"
    ],
    "name:nor_x_preferred":[
        "Karmalinovskaja"
    ],
    "name:rus_x_preferred":[
        "\u041a\u0430\u0440\u043c\u0430\u043b\u0438\u043d\u043e\u0432\u0441\u043a\u0430\u044f"
    ],
    "name:und_x_variant":[
        "Karmalinovskoye"
    ],
    "wof:name":"Karmalinovskaya",
    "wof:placetype":"locality"
},
  "geometry": {"coordinates":[41.3596,45.41454],"type":"Point"}
}