{
  "type": "Feature",
  "properties": {
    "gn:admin1_code":"53",
    "gn:asciiname":"Ust'-Tandovka",
    "gn:country_code":"RU",
    "gn:dem":112,
    "gn:feature_class":"P",
    "gn:feature_code":"PPL",
    "gn:name":"Ust\u2019-Tandovka",
    "gn:population":0,
    "gn:timezone":"Asia/Novosibirsk",
    "iso:country":"RU",
    "name:eng_x_preferred":[
        "Ust'-Tandovka"
    ],
    "name:nor_x_preferred":[
        "Ust-Tandovka"
    ],
    "name:rus_x_preferred":[
        "\u0423\u0441\u0442\u044c-\u0422\u0430\u043d\u0434\u043e\u0432\u043a\u0430"
    ],
    "name:und_x_variant":[
        "Ust\u2019-Tandovskaya",
        "Ust\u2019-Tandovka"
    ],
    "wof:name":"Ust'-Tandovka",
    "wof:placetype":"locality"
},
  "geometry": {"coordinates":[78.08240000000001,55.00795],"type":"Point"}
}