{
  "type": "Feature",
  "properties": {
    "gn:admin1_code":"42",
    "gn:asciiname":"Mukhovitsy",
    "gn:country_code":"RU",
    "gn:dem":146,
    "gn:feature_class":"P",
    "gn:feature_code":"PPL",
    "gn:name":"Mukhovitsy",
    "gn:population":0,
    "gn:timezone":"Europe/Moscow",
    "iso:country":"RU",
    "name:eng_x_preferred":[
        "Mukhovitsy"
    ],
    "name:nor_x_preferred":[
        "Mukhovitsy"
    ],
    "name:rus_x_preferred":[
        "\u041c\u0443\u0445\u043e\u0432\u0438\u0446\u044b"
    ],
    "wof:name":"Mukhovitsy",
    "wof:placetype":"locality"
},
  "geometry": {"coordinates":[29.48576,59.69994000000001],"type":"Point"}
}