{
  "type": "Feature",
  "properties": {
    "gn:admin1_code":"77",
    "gn:asciiname":"Zabor'ye",
    "gn:country_code":"RU",
    "gn:dem":216,
    "gn:feature_class":"P",
    "gn:feature_code":"PPL",
    "gn:name":"Zabor\u2019ye",
    "gn:population":0,
    "gn:timezone":"Europe/Moscow",
    "iso:country":"RU",
    "name:eng_x_preferred":[
        "Zabor'ye"
    ],
    "name:nor_x_preferred":[
        "Zaborje"
    ],
    "name:rus_x_preferred":[
        "\u0417\u0430\u0431\u043e\u0440\u044c\u0435"
    ],
    "name:und_x_variant":[
        "Saborja",
        "Zabar\u2019ya",
        "Zabor\u2019ye"
    ],
    "wof:name":"Zabor'ye",
    "wof:placetype":"locality"
},
  "geometry": {"coordinates":[32.9503,57.1911],"type":"Point"}
}