{
  "type": "Feature",
  "properties": {
    "gn:admin1_code":"71",
    "gn:asciiname":"Koksharovo",
    "gn:country_code":"RU",
    "gn:dem":168,
    "gn:feature_class":"P",
    "gn:feature_code":"PPL",
    "gn:name":"Koksharovo",
    "gn:population":0,
    "gn:timezone":"Asia/Yekaterinburg",
    "iso:country":"RU",
    "name:eng_x_preferred":[
        "Koksharovo"
    ],
    "name:nor_x_preferred":[
        "Koksjarovo"
    ],
    "name:rus_x_preferred":[
        "\u041a\u043e\u043a\u0448\u0430\u0440\u043e\u0432\u043e"
    ],
    "name:und_x_variant":[
        "Koksharova"
    ],
    "wof:name":"Koksharovo",
    "wof:placetype":"locality"
},
  "geometry": {"coordinates":[60.90316,58.30719000000001],"type":"Point"}
}