{
  "type": "Feature",
  "properties": {
    "gn:admin1_code":"47",
    "gn:asciiname":"Korpusa",
    "gn:country_code":"RU",
    "gn:dem":135,
    "gn:feature_class":"P",
    "gn:feature_code":"PPL",
    "gn:name":"Korpusa",
    "gn:population":0,
    "gn:timezone":"Europe/Moscow",
    "iso:country":"RU",
    "name:rus_x_preferred":[
        "\u041a\u043e\u0440\u043f\u0443\u0441\u0430"
    ],
    "name:und_x_variant":[
        "Korpusy",
        "Korpusa"
    ],
    "wof:name":"Korpusa",
    "wof:placetype":"locality"
},
  "geometry": {"coordinates":[38.22634,55.8737],"type":"Point"}
}