{
  "type": "Feature",
  "properties": {
    "gn:admin1_code":"45.0",
    "gn:asciiname":"Akhmatener",
    "gn:country_code":"RU",
    "gn:dem":153,
    "gn:feature_class":"P",
    "gn:feature_code":"PPL",
    "gn:name":"Akhmatener",
    "gn:population":0,
    "gn:timezone":"Europe/Moscow",
    "iso:country":"RU",
    "name:nor_x_preferred":[
        "Akhmatener"
    ],
    "name:rus_x_preferred":[
        "\u0410\u0445\u043c\u0430\u0442\u0435\u043d\u0435\u0440"
    ],
    "wof:name":"Akhmatener",
    "wof:placetype":"locality"
},
  "geometry": {"coordinates":[49.3353,56.957],"type":"Point"}
}