{
  "type": "Feature",
  "properties": {
    "gn:admin1_code":"73",
    "gn:asciiname":"Kushtovo",
    "gn:country_code":"RU",
    "gn:dem":69,
    "gn:feature_class":"P",
    "gn:feature_code":"PPL",
    "gn:name":"Kushtovo",
    "gn:population":0,
    "gn:timezone":"Europe/Moscow",
    "iso:country":"RU",
    "name:rus_x_preferred":[
        "\u041a\u0443\u0448\u0442\u043e\u0432\u043e"
    ],
    "wof:name":"Kushtovo",
    "wof:placetype":"locality"
},
  "geometry": {"coordinates":[48.28686,55.14716],"type":"Point"}
}