{
  "type": "Feature",
  "properties": {
    "gn:admin1_code":"90.0",
    "gn:asciiname":"Bol'shaya Biz'",
    "gn:country_code":"RU",
    "gn:dem":294,
    "gn:feature_class":"P",
    "gn:feature_code":"PPL",
    "gn:name":"Bol\u2019shaya Biz\u2019",
    "gn:population":0,
    "gn:timezone":"Asia/Yekaterinburg",
    "iso:country":"RU",
    "name:rus_x_preferred":[
        "\u0411\u043e\u043b\u044c\u0448\u0430\u044f \u0411\u0438\u0437\u044c"
    ],
    "name:und_x_variant":[
        "Bol\u2019shaya Biz\u2019",
        "\u0411\u043e\u043b\u044c\u0448\u0430\u044f \u0411\u0438\u0437\u044c"
    ],
    "wof:name":"Bol'shaya Biz'",
    "wof:placetype":"locality"
},
  "geometry": {"coordinates":[58.48893,57.60241],"type":"Point"}
}