{
  "type": "Feature",
  "properties": {
    "gn:admin1_code":"83.0",
    "gn:asciiname":"Alferovo",
    "gn:country_code":"RU",
    "gn:dem":106,
    "gn:feature_class":"P",
    "gn:feature_code":"PPL",
    "gn:name":"Alferovo",
    "gn:population":0,
    "gn:timezone":"Europe/Moscow",
    "iso:country":"RU",
    "name:rus_x_preferred":[
        "\u0410\u043b\u0444\u0435\u0440\u043e\u0432\u043e"
    ],
    "wof:name":"Alferovo",
    "wof:placetype":"locality"
},
  "geometry": {"coordinates":[40.2286,56.0149],"type":"Point"}
}