{
  "type": "Feature",
  "properties": {
    "gn:admin1_code":"24",
    "gn:asciiname":"Smushkovoye",
    "gn:cc2":"RU",
    "gn:country_code":"RU",
    "gn:dem":0,
    "gn:feature_class":"P",
    "gn:feature_code":"PPL",
    "gn:name":"Smushkovoye",
    "gn:population":0,
    "gn:timezone":"Europe/Moscow",
    "iso:country":"RU",
    "name:rus_x_preferred":[
        "\u0421\u043c\u0443\u0448\u043a\u043e\u0432\u043e\u0435"
    ],
    "name:und_x_variant":[
        "Burata",
        "Khot-Burata",
        "Smushkovoye",
        "\u0421\u043c\u0443\u0448\u043a\u043e\u0432\u043e\u0435"
    ],
    "wof:name":"Smushkovoye",
    "wof:placetype":"locality"
},
  "geometry": {"coordinates":[45.95,47.33333],"type":"Point"}
}