{
  "type": "Feature",
  "properties": {
    "gn:admin1_code":"52",
    "gn:asciiname":"Karoksa",
    "gn:country_code":"RU",
    "gn:dem":62,
    "gn:feature_class":"P",
    "gn:feature_code":"PPL",
    "gn:name":"Karoksa",
    "gn:population":0,
    "gn:timezone":"Europe/Moscow",
    "iso:country":"RU",
    "name:rus_x_preferred":[
        "\u041a\u0430\u0440\u043e\u043a\u0441\u0430"
    ],
    "wof:name":"Karoksa",
    "wof:placetype":"locality"
},
  "geometry": {"coordinates":[30.22393,58.43975],"type":"Point"}
}