{
  "type": "Feature",
  "properties": {
    "gn:admin1_code":"69",
    "gn:asciiname":"Kozhina",
    "gn:country_code":"RU",
    "gn:dem":219,
    "gn:feature_class":"P",
    "gn:feature_code":"PPL",
    "gn:name":"Kozhina",
    "gn:population":0,
    "gn:timezone":"Europe/Moscow",
    "iso:country":"RU",
    "name:rus_x_preferred":[
        "\u041a\u043e\u0436\u0438\u043d\u0430"
    ],
    "name:und_x_variant":[
        "\u041a\u043e\u0436\u0438\u043d\u0430"
    ],
    "wof:name":"Kozhina",
    "wof:placetype":"locality"
},
  "geometry": {"coordinates":[32.07417,54.99833],"type":"Point"}
}