{
  "type": "Feature",
  "properties": {
    "gn:admin1_code":"65",
    "gn:asciiname":"Krasnaya Dubrava",
    "gn:country_code":"RU",
    "gn:dem":183,
    "gn:feature_class":"P",
    "gn:feature_code":"PPL",
    "gn:name":"Krasnaya Dubrava",
    "gn:population":0,
    "gn:timezone":"Europe/Samara",
    "iso:country":"RU",
    "name:rus_x_preferred":[
        "\u041a\u0440\u0430\u0441\u043d\u0430\u044f \u0414\u0443\u0431\u0440\u0430\u0432\u0430"
    ],
    "name:und_x_variant":[
        "Krasnaya Dubrovka",
        "Krasnaya Dubrava"
    ],
    "wof:name":"Krasnaya Dubrava",
    "wof:placetype":"locality"
},
  "geometry": {"coordinates":[49.8786,53.7115],"type":"Point"}
}