{
  "type": "Feature",
  "properties": {
    "gn:admin1_code":"16",
    "gn:asciiname":"Verkhneye Anchikovo",
    "gn:country_code":"RU",
    "gn:dem":140,
    "gn:feature_class":"P",
    "gn:feature_code":"PPL",
    "gn:name":"Verkhneye Anchikovo",
    "gn:population":0,
    "gn:timezone":"Europe/Moscow",
    "iso:country":"RU",
    "name:rus_x_preferred":[
        "\u0412\u0435\u0440\u0445\u043d\u0435\u0435 \u0410\u043d\u0447\u0438\u043a\u043e\u0432\u043e"
    ],
    "name:und_x_variant":[
        "Verkhnoye",
        "Verkhneye Anchikovo"
    ],
    "wof:name":"Verkhneye Anchikovo",
    "wof:placetype":"locality"
},
  "geometry": {"coordinates":[48.14393,55.8086],"type":"Point"}
}