{
  "type": "Feature",
  "properties": {
    "gn:admin1_code":"8.0",
    "gn:asciiname":"Blagoveshchenka",
    "gn:country_code":"RU",
    "gn:dem":131,
    "gn:feature_class":"P",
    "gn:feature_code":"PPL",
    "gn:name":"Blagoveshchenka",
    "gn:population":0,
    "gn:timezone":"Asia/Yekaterinburg",
    "iso:country":"RU",
    "name:eng_x_preferred":[
        "Blagoveshchenka"
    ],
    "name:nor_x_preferred":[
        "Blagovesjtsjenka"
    ],
    "name:rus_x_preferred":[
        "\u0411\u043b\u0430\u0433\u043e\u0432\u0435\u0449\u0435\u043d\u043a\u0430"
    ],
    "name:und_x_variant":[
        "\u0411\u043b\u0430\u0433\u043e\u0432\u0435\u0449\u0435\u043d\u043a\u0430",
        "Blagoveshchenka"
    ],
    "wof:name":"Blagoveshchenka",
    "wof:placetype":"locality"
},
  "geometry": {"coordinates":[56.65069,54.50694],"type":"Point"}
}