{
  "type": "Feature",
  "properties": {
    "gn:admin1_code":"37",
    "gn:asciiname":"Klyzhikha",
    "gn:country_code":"RU",
    "gn:dem":130,
    "gn:feature_class":"P",
    "gn:feature_code":"PPL",
    "gn:name":"Klyzhikha",
    "gn:population":0,
    "gn:timezone":"Europe/Moscow",
    "iso:country":"RU",
    "name:rus_x_preferred":[
        "\u041a\u043b\u044b\u0436\u0438\u0445\u0430"
    ],
    "wof:name":"Klyzhikha",
    "wof:placetype":"locality"
},
  "geometry": {"coordinates":[45.8178,58.195],"type":"Point"}
}