{
  "type": "Feature",
  "properties": {
    "gn:admin1_code":"8",
    "gn:asciiname":"Tynbayevo",
    "gn:country_code":"RU",
    "gn:dem":126,
    "gn:feature_class":"P",
    "gn:feature_code":"PPL",
    "gn:name":"Tynbayevo",
    "gn:population":0,
    "gn:timezone":"Asia/Yekaterinburg",
    "iso:country":"RU",
    "name:eng_x_preferred":[
        "Tynbayevo"
    ],
    "name:nor_x_preferred":[
        "Tynbajevo"
    ],
    "name:rus_x_preferred":[
        "\u0422\u044b\u043d\u0431\u0430\u0435\u0432\u043e"
    ],
    "wof:name":"Tynbayevo",
    "wof:placetype":"locality"
},
  "geometry": {"coordinates":[55.45962,55.60012],"type":"Point"}
}