{
  "type": "Feature",
  "properties": {
    "gn:admin1_code":"80",
    "gn:asciiname":"Katekshur",
    "gn:country_code":"RU",
    "gn:dem":170,
    "gn:feature_class":"P",
    "gn:feature_code":"PPL",
    "gn:name":"Katekshur",
    "gn:population":0,
    "gn:timezone":"Europe/Samara",
    "iso:country":"RU",
    "name:rus_x_preferred":[
        "\u041a\u0430\u0442\u0435\u043a\u0448\u0443\u0440"
    ],
    "name:und_x_variant":[
        "\u041a\u0430\u0442\u0435\u043a\u0448\u0443\u0440"
    ],
    "wof:name":"Katekshur",
    "wof:placetype":"locality"
},
  "geometry": {"coordinates":[52.13333,56.33333],"type":"Point"}
}