{
  "type": "Feature",
  "properties": {
    "gn:admin1_code":"62.0",
    "gn:asciiname":"Gavrilovka",
    "gn:country_code":"RU",
    "gn:dem":161,
    "gn:feature_class":"P",
    "gn:feature_code":"PPL",
    "gn:name":"Gavrilovka",
    "gn:population":0,
    "gn:timezone":"Europe/Moscow",
    "iso:country":"RU",
    "name:rus_x_preferred":[
        "\u0413\u0430\u0432\u0440\u0438\u043b\u043e\u0432\u043a\u0430"
    ],
    "name:und_x_variant":[
        "\u0413\u0430\u0432\u0440\u0438\u043b\u043e\u0432\u043a\u0430"
    ],
    "wof:name":"Gavrilovka",
    "wof:placetype":"locality"
},
  "geometry": {"coordinates":[41.46262,54.17303],"type":"Point"}
}