{
  "type": "Feature",
  "properties": {
    "gn:admin1_code":"73",
    "gn:asciiname":"Ryazanovo",
    "gn:country_code":"RU",
    "gn:dem":58,
    "gn:feature_class":"P",
    "gn:feature_code":"PPL",
    "gn:name":"Ryazanovo",
    "gn:population":0,
    "gn:timezone":"Europe/Moscow",
    "iso:country":"RU",
    "name:rus_x_preferred":[
        "\u0420\u044f\u0437\u0430\u043d\u043e\u0432\u043e"
    ],
    "wof:name":"Ryazanovo",
    "wof:placetype":"locality"
},
  "geometry": {"coordinates":[48.3382,55.6499],"type":"Point"}
}