{
  "type": "Feature",
  "properties": {
    "gn:admin1_code":"52.0",
    "gn:asciiname":"Yablonovo",
    "gn:country_code":"RU",
    "gn:dem":82,
    "gn:feature_class":"P",
    "gn:feature_code":"PPL",
    "gn:name":"Yablonovo",
    "gn:population":0,
    "gn:timezone":"Europe/Moscow",
    "iso:country":"RU",
    "name:rus_x_preferred":[
        "\u042f\u0431\u043b\u043e\u043d\u043e\u0432\u043e"
    ],
    "name:und_x_variant":[
        "Bol\u2019shaya Yablonova",
        "Yablonovo",
        "\u042f\u0431\u043b\u043e\u043d\u043e\u0432\u043e"
    ],
    "wof:name":"Yablonovo",
    "wof:placetype":"locality"
},
  "geometry": {"coordinates":[31.04858,57.39449000000001],"type":"Point"}
}