{
  "type": "Feature",
  "properties": {
    "gn:admin1_code":"60",
    "gn:asciiname":"Golubovo",
    "gn:country_code":"RU",
    "gn:dem":88,
    "gn:feature_class":"P",
    "gn:feature_code":"PPL",
    "gn:name":"Golubovo",
    "gn:population":0,
    "gn:timezone":"Europe/Moscow",
    "iso:country":"RU",
    "name:rus_x_preferred":[
        "\u0413\u043e\u043b\u0443\u0431\u043e\u0432\u043e"
    ],
    "name:und_x_variant":[
        "\u0413\u043e\u043b\u0443\u0431\u043e\u0432\u043e"
    ],
    "wof:name":"Golubovo",
    "wof:placetype":"locality"
},
  "geometry": {"coordinates":[30.6592,56.7524],"type":"Point"}
}