{
  "type": "Feature",
  "properties": {
    "gn:admin1_code":"73",
    "gn:asciiname":"Shadrino",
    "gn:country_code":"RU",
    "gn:dem":60,
    "gn:feature_class":"P",
    "gn:feature_code":"PPL",
    "gn:name":"Shadrino",
    "gn:population":0,
    "gn:timezone":"Europe/Moscow",
    "iso:country":"RU",
    "name:rus_x_preferred":[
        "\u0428\u0430\u0434\u0440\u0438\u043d\u043e"
    ],
    "name:und_x_variant":[
        "\u0428\u0430\u0434\u0440\u0438\u043d\u043e"
    ],
    "wof:name":"Shadrino",
    "wof:placetype":"locality"
},
  "geometry": {"coordinates":[53.31667,55.81667],"type":"Point"}
}