{
  "type": "Feature",
  "properties": {
    "gn:admin1_code":"77",
    "gn:asciiname":"Slavnoye",
    "gn:country_code":"RU",
    "gn:dem":139,
    "gn:feature_class":"P",
    "gn:feature_code":"PPL",
    "gn:name":"Slavnoye",
    "gn:population":0,
    "gn:timezone":"Europe/Moscow",
    "iso:country":"RU",
    "name:eng_x_preferred":[
        "Slavnoye"
    ],
    "name:nor_x_preferred":[
        "Slavnoje"
    ],
    "name:rus_x_preferred":[
        "\u0421\u043b\u0430\u0432\u043d\u043e\u0435"
    ],
    "wof:name":"Slavnoye",
    "wof:placetype":"locality"
},
  "geometry": {"coordinates":[36.05622,56.99639000000001],"type":"Point"}
}