{
  "type": "Feature",
  "properties": {
    "gn:admin1_code":"10",
    "gn:asciiname":"Sokolovka",
    "gn:country_code":"RU",
    "gn:dem":183,
    "gn:feature_class":"P",
    "gn:feature_code":"PPL",
    "gn:name":"Sokolovka",
    "gn:population":0,
    "gn:timezone":"Europe/Moscow",
    "iso:country":"RU",
    "name:rus_x_preferred":[
        "\u0421\u043e\u043a\u043e\u043b\u043e\u0432\u043a\u0430"
    ],
    "name:und_x_variant":[
        "Sokholovka",
        "Sokolovka",
        "\u0421\u043e\u043a\u043e\u043b\u043e\u0432\u043a\u0430"
    ],
    "wof:name":"Sokolovka",
    "wof:placetype":"locality"
},
  "geometry": {"coordinates":[32.74047,52.49889],"type":"Point"}
}