{
  "type": "Feature",
  "properties": {
    "gn:admin1_code":"7.0",
    "gn:asciiname":"Kononenko",
    "gn:country_code":"RU",
    "gn:dem":-18,
    "gn:feature_class":"P",
    "gn:feature_code":"PPL",
    "gn:name":"Kononenko",
    "gn:population":0,
    "gn:timezone":"Europe/Astrakhan",
    "iso:country":"RU",
    "name:rus_x_preferred":[
        "\u041a\u043e\u043d\u043e\u043d\u0435\u043d\u043a\u043e"
    ],
    "name:slv_x_preferred":[
        "Kononenko"
    ],
    "name:und_x_variant":[
        "Kananenko"
    ],
    "wof:name":"Kononenko",
    "wof:placetype":"locality"
},
  "geometry": {"coordinates":[46.22207,48.15246],"type":"Point"}
}