{
  "type": "Feature",
  "properties": {
    "gn:admin1_code":"83",
    "gn:asciiname":"Klyuchiki",
    "gn:country_code":"RU",
    "gn:dem":108,
    "gn:feature_class":"P",
    "gn:feature_code":"PPL",
    "gn:name":"Klyuchiki",
    "gn:population":0,
    "gn:timezone":"Europe/Moscow",
    "iso:country":"RU",
    "name:rus_x_preferred":[
        "\u041a\u043b\u044e\u0447\u0438\u043a\u0438"
    ],
    "wof:name":"Klyuchiki",
    "wof:placetype":"locality"
},
  "geometry": {"coordinates":[41.68333,56.03333000000001],"type":"Point"}
}