{
  "type": "Feature",
  "properties": {
    "gn:country":"RU",
    "gn:fcode":"PPL",
    "gn:pop":0,
    "iso:country":"RU",
    "name:aze_x_preferred":[
        "Qorki"
    ],
    "name:bel_x_preferred":[
        "\u0413\u043e\u0440\u043a\u0456"
    ],
    "name:bul_x_preferred":[
        "\u0413\u043e\u0440\u043a\u0438"
    ],
    "name:cat_x_preferred":[
        "Gorki"
    ],
    "name:ceb_x_preferred":[
        "Gorki"
    ],
    "name:ces_x_preferred":[
        "Gorki"
    ],
    "name:dan_x_preferred":[
        "Gorki"
    ],
    "name:deu_x_preferred":[
        "Gorki"
    ],
    "name:epo_x_preferred":[
        "Gorki"
    ],
    "name:est_x_preferred":[
        "Gorki"
    ],
    "name:fin_x_preferred":[
        "Gorki"
    ],
    "name:fra_x_preferred":[
        "Gorki"
    ],
    "name:heb_x_preferred":[
        "\u05d2\u05d5\u05e8\u05e7\u05d9"
    ],
    "name:hun_x_preferred":[
        "Gorki"
    ],
    "name:hye_x_preferred":[
        "\u0533\u0578\u0580\u056f\u056b"
    ],
    "name:ita_x_preferred":[
        "Gorki"
    ],
    "name:lav_x_preferred":[
        "Gorki"
    ],
    "name:mon_x_preferred":[
        "\u0413\u043e\u0440\u044c\u043a\u0438\u0439"
    ],
    "name:nld_x_preferred":[
        "Gorki"
    ],
    "name:pol_x_preferred":[
        "Gorki"
    ],
    "name:rus_x_preferred":[
        "\u0413\u043e\u0440\u043a\u0438"
    ],
    "name:spa_x_preferred":[
        "Gorki"
    ],
    "name:srp_x_preferred":[
        "\u0413\u043e\u0440\u043a\u0438"
    ],
    "name:swe_x_preferred":[
        "Gorki"
    ],
    "name:ukr_x_preferred":[
        "\u0413\u043e\u0440\u043a\u0438"
    ],
    "name:unk_x_variant":[
        "\u0413\u043e\u0440\u043a\u0438"
    ],
    "qs:name":"Gorki",
    "qs:name_adm0":"Russia",
    "qs:name_adm1":"Moscow Oblast",
    "qs:photos_9r":0,
    "qs:photos_sr":0,
    "qs:placetype":"Town",
    "qs:pop_sr":"0",
    "wd:wordcount":54,
    "wof:name":"Gorki",
    "wof:placetype":"locality",
    "wof:population":0
},
  "geometry": {"coordinates":[37.35,56.18333],"type":"Point"}
}