{
  "type": "Feature",
  "properties": {
    "gn:country":"RU",
    "gn:fcode":"PPL",
    "gn:pop":0,
    "iso:country":"RU",
    "name:rus_x_preferred":[
        "\u0413\u043e\u0440\u043a\u0438"
    ],
    "name:unk_x_variant":[
        "\u0413\u043e\u0440\u043a\u0438"
    ],
    "qs:name":"Gorki",
    "qs:name_adm0":"Russia",
    "qs:name_adm1":"Moscow Oblast",
    "qs:photos_9r":0,
    "qs:photos_sr":0,
    "qs:placetype":"Town",
    "qs:pop_sr":"0",
    "wd:wordcount":54,
    "wof:name":"Gorki",
    "wof:placetype":"locality",
    "wof:population":0
},
  "geometry": {"coordinates":[37.35,56.18333],"type":"Point"}
}