{
  "type": "Feature",
  "properties": {
    "gn:admin1_code":"25",
    "gn:asciiname":"Stepanovka",
    "gn:country_code":"RU",
    "gn:dem":183,
    "gn:feature_class":"P",
    "gn:feature_code":"PPL",
    "gn:name":"Stepanovka",
    "gn:population":0,
    "gn:timezone":"Europe/Moscow",
    "iso:country":"RU",
    "name:rus_x_preferred":[
        "\u0421\u0442\u0435\u043f\u0430\u043d\u043e\u0432\u0441\u043a\u043e\u0435"
    ],
    "name:rus_x_variant":[
        "\u0421\u0442\u0435\u043f\u0430\u043d\u043e\u0432ka"
    ],
    "name:und_x_variant":[
        "Stepanovskoye",
        "Stepanovka"
    ],
    "wof:name":"Stepanovka",
    "wof:placetype":"locality"
},
  "geometry": {"coordinates":[36.58308,54.70736],"type":"Point"}
}