{
  "type": "Feature",
  "properties": {
    "gn:admin1_code":"56",
    "gn:asciiname":"Bol'shak",
    "gn:country_code":"RU",
    "gn:dem":241,
    "gn:feature_class":"P",
    "gn:feature_code":"PPL",
    "gn:name":"Bol\u2019shak",
    "gn:population":0,
    "gn:timezone":"Europe/Moscow",
    "iso:country":"RU",
    "name:rus_x_preferred":[
        "\u0411\u043e\u043b\u044c\u0448\u0430\u043a"
    ],
    "name:und_x_variant":[
        "Bol\u2019shak",
        "\u0411\u043e\u043b\u044c\u0448\u0430\u043a"
    ],
    "wof:name":"Bol'shak",
    "wof:placetype":"locality"
},
  "geometry": {"coordinates":[37.37417,53.00389000000001],"type":"Point"}
}