{
  "type": "Feature",
  "properties": {
    "gn:admin1_code":"84",
    "gn:asciiname":"Ternovoy",
    "gn:country_code":"RU",
    "gn:dem":130,
    "gn:feature_class":"P",
    "gn:feature_code":"PPL",
    "gn:name":"Ternovoy",
    "gn:population":0,
    "gn:timezone":"Europe/Volgograd",
    "iso:country":"RU",
    "name:eng_x_preferred":[
        "Ternovoy"
    ],
    "name:nor_x_preferred":[
        "Ternovoj"
    ],
    "name:rus_x_preferred":[
        "\u0422\u0435\u0440\u043d\u043e\u0432\u043e\u0439"
    ],
    "name:und_x_variant":[
        "Ternovyy"
    ],
    "wof:name":"Ternovoy",
    "wof:placetype":"locality"
},
  "geometry": {"coordinates":[43.6568,47.84874],"type":"Point"}
}