{
  "type": "Feature",
  "properties": {
    "gn:admin1_code":"6",
    "gn:asciiname":"Pantysh",
    "gn:country_code":"RU",
    "gn:dem":78,
    "gn:feature_class":"P",
    "gn:feature_code":"PPL",
    "gn:name":"Pantysh",
    "gn:population":0,
    "gn:timezone":"Europe/Moscow",
    "iso:country":"RU",
    "name:eng_x_preferred":[
        "Pantysh"
    ],
    "name:nor_x_preferred":[
        "Lantysj"
    ],
    "name:rus_x_preferred":[
        "\u041b\u0430\u043d\u0442\u044b\u0448"
    ],
    "name:rus_x_variant":[
        "\u041f\u0430\u043d\u0442\u044b\u0448"
    ],
    "name:und_x_variant":[
        "\u041f\u0430\u043d\u0442\u044b\u0448"
    ],
    "wof:name":"Pantysh",
    "wof:placetype":"locality"
},
  "geometry": {"coordinates":[49.14625,62.13924],"type":"Point"}
}