{
  "type": "Feature",
  "properties": {
    "gn:admin1_code":"37",
    "gn:asciiname":"Spornovo",
    "gn:country_code":"RU",
    "gn:dem":204,
    "gn:feature_class":"P",
    "gn:feature_code":"PPL",
    "gn:name":"Spornovo",
    "gn:population":0,
    "gn:timezone":"Europe/Moscow",
    "iso:country":"RU",
    "name:rus_x_preferred":[
        "\u0421\u043f\u043e\u0440\u043d\u043e\u0432\u043e"
    ],
    "wof:name":"Spornovo",
    "wof:placetype":"locality"
},
  "geometry": {"coordinates":[43.3334,58.555],"type":"Point"}
}