{
  "type": "Feature",
  "properties": {
    "gn:admin1_code":"25",
    "gn:asciiname":"Doktorovo",
    "gn:country_code":"RU",
    "gn:dem":208,
    "gn:feature_class":"P",
    "gn:feature_code":"PPL",
    "gn:name":"Doktorovo",
    "gn:population":0,
    "gn:timezone":"Europe/Moscow",
    "iso:country":"RU",
    "name:rus_x_preferred":[
        "\u0414\u043e\u043a\u0442\u043e\u0440\u043e\u0432\u043e"
    ],
    "wof:name":"Doktorovo",
    "wof:placetype":"locality"
},
  "geometry": {"coordinates":[35.23084,53.3122],"type":"Point"}
}