{
  "type": "Feature",
  "properties": {
    "gn:admin1_code":"47",
    "gn:asciiname":"Noskovo",
    "gn:country_code":"RU",
    "gn:dem":195,
    "gn:feature_class":"P",
    "gn:feature_code":"PPL",
    "gn:name":"Noskovo",
    "gn:population":51,
    "gn:timezone":"Europe/Moscow",
    "iso:country":"RU",
    "name:eng_x_preferred":[
        "Noskovo"
    ],
    "name:nor_x_preferred":[
        "Noskovo"
    ],
    "name:rus_x_preferred":[
        "\u041d\u043e\u0441\u043a\u043e\u0432\u043e"
    ],
    "wof:name":"Noskovo",
    "wof:placetype":"locality",
    "wof:population":51
},
  "geometry": {"coordinates":[37.68989000000001,56.45633],"type":"Point"}
}