{
  "type": "Feature",
  "properties": {
    "gn:admin1_code":"44",
    "gn:asciiname":"Buryuk",
    "gn:country_code":"RU",
    "gn:dem":70,
    "gn:feature_class":"P",
    "gn:feature_code":"PPL",
    "gn:name":"Buryuk",
    "gn:population":0,
    "gn:timezone":"Asia/Magadan",
    "iso:country":"RU",
    "name:rus_x_preferred":[
        "\u0411\u0443\u0440\u044e\u043a"
    ],
    "name:und_x_variant":[
        "\u0411\u0443\u0440\u044e\u043a"
    ],
    "wof:name":"Buryuk",
    "wof:placetype":"locality"
},
  "geometry": {"coordinates":[151.55000000000001,65.21666999999999],"type":"Point"}
}