{
  "type": "Feature",
  "properties": {
    "gn:admin1_code":"6",
    "gn:asciiname":"Krasnaya Lyaga",
    "gn:country_code":"RU",
    "gn:dem":155,
    "gn:feature_class":"P",
    "gn:feature_code":"PPL",
    "gn:name":"Krasnaya Lyaga",
    "gn:population":1,
    "gn:timezone":"Europe/Moscow",
    "iso:country":"RU",
    "name:rus_x_preferred":[
        "\u041a\u0440\u0430\u0441\u043d\u0430\u044f \u041b\u044f\u0433\u0430"
    ],
    "wof:name":"Krasnaya Lyaga",
    "wof:placetype":"locality",
    "wof:population":1
},
  "geometry": {"coordinates":[38.65538,61.60057],"type":"Point"}
}