{
  "type": "Feature",
  "properties": {
    "gn:admin1_code":"33",
    "gn:asciiname":"Verkhniye Ryabi",
    "gn:country_code":"RU",
    "gn:dem":167,
    "gn:feature_class":"P",
    "gn:feature_code":"PPL",
    "gn:name":"Verkhniye Ryabi",
    "gn:population":0,
    "gn:timezone":"Europe/Kirov",
    "iso:country":"RU",
    "name:rus_x_preferred":[
        "\u0412\u0435\u0440\u0445\u043d\u0438\u0435 \u0420\u044f\u0431\u0438"
    ],
    "wof:name":"Verkhniye Ryabi",
    "wof:placetype":"locality"
},
  "geometry": {"coordinates":[50.1428,57.7698],"type":"Point"}
}