{
  "type": "Feature",
  "properties": {
    "gn:admin1_code":"93",
    "gn:asciiname":"Maloarkhangel'sk",
    "gn:country_code":"RU",
    "gn:dem":772,
    "gn:feature_class":"P",
    "gn:feature_code":"PPL",
    "gn:name":"Maloarkhangel\u2019sk",
    "gn:population":0,
    "gn:timezone":"Asia/Chita",
    "iso:country":"RU",
    "name:eng_x_preferred":[
        "Maloarkhangel'skoye"
    ],
    "name:nor_x_preferred":[
        "Maloarkhangelsk"
    ],
    "name:rus_x_preferred":[
        "\u041c\u0430\u043b\u043e\u0430\u0440\u0445\u0430\u043d\u0433\u0435\u043b\u044c\u0441\u043a"
    ],
    "name:und_x_variant":[
        "Maloarkhangel\u2019sk",
        "Malo-Arkhangel\u2019skoye"
    ],
    "wof:name":"Maloarkhangel'sk",
    "wof:placetype":"locality"
},
  "geometry": {"coordinates":[108.83709,50.39669],"type":"Point"}
}