{
  "type": "Feature",
  "properties": {
    "gn:admin1_code":"42",
    "gn:asciiname":"Savol'shchina",
    "gn:country_code":"RU",
    "gn:dem":131,
    "gn:feature_class":"P",
    "gn:feature_code":"PPL",
    "gn:name":"Savol\u2019shchina",
    "gn:population":0,
    "gn:timezone":"Europe/Moscow",
    "iso:country":"RU",
    "name:nor_x_preferred":[
        "Savolsjtsjina"
    ],
    "name:rus_x_preferred":[
        "\u0421\u0430\u0432\u043e\u043b\u044c\u0449\u0438\u043d\u0430"
    ],
    "name:und_x_variant":[
        "Savol\u2019shchina"
    ],
    "wof:name":"Savol'shchina",
    "wof:placetype":"locality"
},
  "geometry": {"coordinates":[29.31963,59.68926],"type":"Point"}
}