{
  "type": "Feature",
  "properties": {
    "gn:admin1_code":"6",
    "gn:asciiname":"Kelareva Gorka",
    "gn:country_code":"RU",
    "gn:dem":159,
    "gn:feature_class":"P",
    "gn:feature_code":"PPL",
    "gn:name":"Kelar\u00ebva Gorka",
    "gn:population":0,
    "gn:timezone":"Europe/Moscow",
    "iso:country":"RU",
    "name:eng_x_preferred":[
        "Kelar\u00ebva Gorka"
    ],
    "name:nor_x_preferred":[
        "Kelareva Gorka"
    ],
    "name:rus_x_preferred":[
        "\u041a\u0435\u043b\u0430\u0440\u0435\u0432\u0430 \u0413\u043e\u0440\u043a\u0430"
    ],
    "name:rus_x_variant":[
        "\u041a\u0435\u043b\u0430\u0440\u0451\u0432\u0430 \u0413\u043e\u0440\u043a\u0430",
        "Kelar\u00ebva Gorka"
    ],
    "name:und_x_variant":[
        "Kelar\u00ebva"
    ],
    "wof:name":"Kelareva Gorka",
    "wof:placetype":"locality"
},
  "geometry": {"coordinates":[41.399,61.067],"type":"Point"}
}