{
  "type": "Feature",
  "properties": {
    "gn:admin1_code":"28",
    "gn:asciiname":"Tyur'ya",
    "gn:country_code":"RU",
    "gn:dem":69,
    "gn:feature_class":"P",
    "gn:feature_code":"PPL",
    "gn:name":"Tyur\u2019ya",
    "gn:population":0,
    "gn:timezone":"Europe/Moscow",
    "iso:country":"RU",
    "name:fin_x_preferred":[
        "Tyrj\u00e4"
    ],
    "wof:name":"Tyur'ya",
    "wof:placetype":"locality"
},
  "geometry": {"coordinates":[29.78428,61.55239],"type":"Point"}
}