{
  "type": "Feature",
  "properties": {
    "gn:country":"RU",
    "gn:fcode":"PPL",
    "gn:population":0,
    "iso:country":"RU",
    "name:aze_x_preferred":[
        "Kamenka"
    ],
    "name:bel_x_preferred":[
        "\u041a\u0430\u043c\u0435\u043d\u043a\u0430"
    ],
    "name:ceb_x_preferred":[
        "Kamenka"
    ],
    "name:ces_x_preferred":[
        "Kamenka"
    ],
    "name:deu_x_preferred":[
        "Kamenka"
    ],
    "name:epo_x_preferred":[
        "Kamenka"
    ],
    "name:est_x_preferred":[
        "Kamenka"
    ],
    "name:fin_x_preferred":[
        "Kamenka"
    ],
    "name:fra_x_preferred":[
        "Kamenka"
    ],
    "name:hye_x_preferred":[
        "\u053f\u0561\u0574\u0565\u0576\u056f\u0561"
    ],
    "name:ita_x_preferred":[
        "Kamenka"
    ],
    "name:kat_x_preferred":[
        "\u10d9\u10d0\u10db\u10d4\u10dc\u10d9\u10d0"
    ],
    "name:kaz_x_preferred":[
        "\u041a\u0430\u043c\u0435\u043d\u043a\u0430"
    ],
    "name:lav_x_preferred":[
        "Kamenka"
    ],
    "name:lit_x_preferred":[
        "Kamenka"
    ],
    "name:myv_x_preferred":[
        "\u041a\u0430\u043c\u0435\u043d\u043a\u0430"
    ],
    "name:rus_x_preferred":[
        "\u041a\u0430\u043c\u0435\u043d\u043a\u0430"
    ],
    "name:srp_x_preferred":[
        "\u041a\u0430\u043c\u0435\u043d\u043a\u0430"
    ],
    "name:swe_x_preferred":[
        "Kamenka"
    ],
    "name:ukr_x_preferred":[
        "\u041a\u0430\u043c\u0435\u043d\u043a\u0430"
    ],
    "qs:name":"Kamenka",
    "qs:name_adm0":"Russia",
    "qs:name_adm1":"Moscow Oblast",
    "qs:photos_9k":1,
    "qs:photos_9r":1,
    "qs:photos_all":4,
    "qs:photos_sr":0,
    "qs:placetype":"Town",
    "qs:pop_sr":"0",
    "wd:wordcount":157,
    "wof:name":"Kamenka",
    "wof:placetype":"locality",
    "wof:population":0
},
  "geometry": {"coordinates":[36.99473,55.22077],"type":"Point"}
}