{
  "type": "Feature",
  "properties": {
    "gn:admin1_code":"63",
    "gn:asciiname":"Kharyya",
    "gn:country_code":"RU",
    "gn:dem":87,
    "gn:feature_class":"P",
    "gn:feature_code":"PPL",
    "gn:name":"Kharyya",
    "gn:population":0,
    "gn:timezone":"Asia/Yakutsk",
    "iso:country":"RU",
    "name:che_x_preferred":[
        "\u042b\u043c\u044b\u044f\u0445\u0442\u0430\u0445"
    ],
    "name:rus_x_preferred":[
        "\u0425\u0430\u0440\u044b\u044f"
    ],
    "name:rus_x_variant":[
        "\u042b\u043c\u044b\u044f\u0445\u0442\u0430\u0445"
    ],
    "name:sah_x_preferred":[
        "\u042b\u043c\u044b\u0439\u0430\u0445\u0442\u0430\u0430\u0445"
    ],
    "name:und_x_variant":[
        "Ymyyakhtakh",
        "Kharyya",
        "\u0425\u0430\u0440\u044b\u044f"
    ],
    "wof:name":"Kharyya",
    "wof:placetype":"locality"
},
  "geometry": {"coordinates":[129.88463999999999,62.45843000000001],"type":"Point"}
}