{
  "type": "Feature",
  "properties": {
    "gn:admin1_code":"29",
    "gn:asciiname":"Ustyuzhanino",
    "gn:country_code":"RU",
    "gn:dem":185,
    "gn:feature_class":"P",
    "gn:feature_code":"PPL",
    "gn:name":"Ustyuzhanino",
    "gn:population":0,
    "gn:timezone":"Asia/Novokuznetsk",
    "iso:country":"RU",
    "name:eng_x_preferred":[
        "Ustyuzhanino"
    ],
    "name:nor_x_preferred":[
        "Ustjuzjanino"
    ],
    "name:rus_x_preferred":[
        "\u0423\u0441\u0442\u044e\u0436\u0430\u043d\u0438\u043d\u043e"
    ],
    "name:und_x_variant":[
        "Ustyuzhanina"
    ],
    "wof:name":"Ustyuzhanino",
    "wof:placetype":"locality"
},
  "geometry": {"coordinates":[86.0102,54.5059],"type":"Point"}
}