{
  "type": "Feature",
  "properties": {
    "gn:admin1_code":"11",
    "gn:asciiname":"Angoya",
    "gn:country_code":"RU",
    "gn:dem":492,
    "gn:feature_class":"P",
    "gn:feature_code":"PPL",
    "gn:name":"Angoya",
    "gn:population":0,
    "gn:timezone":"Asia/Irkutsk",
    "iso:country":"RU",
    "name:nor_x_preferred":[
        "Angoja"
    ],
    "name:rus_x_preferred":[
        "\u0410\u043d\u0433\u043e\u044f"
    ],
    "wof:name":"Angoya",
    "wof:placetype":"locality"
},
  "geometry": {"coordinates":[110.95,56.01667],"type":"Point"}
}