{
  "type": "Feature",
  "properties": {
    "gn:admin1_code":"23",
    "gn:asciiname":"Krasnodonskoye",
    "gn:country_code":"RU",
    "gn:dem":10,
    "gn:feature_class":"P",
    "gn:feature_code":"PPL",
    "gn:name":"Krasnodonskoye",
    "gn:population":0,
    "gn:timezone":"Europe/Kaliningrad",
    "iso:country":"RU",
    "name:rus_x_preferred":[
        "\u041a\u0440\u0430\u0441\u043d\u043e\u0434\u043e\u043d\u0441\u043a\u043e\u0435"
    ],
    "wof:name":"Krasnodonskoye",
    "wof:placetype":"locality"
},
  "geometry": {"coordinates":[19.99361,54.50139],"type":"Point"}
}