{
  "type": "Feature",
  "properties": {
    "gn:admin1_code":"47.0",
    "gn:asciiname":"Argunovo",
    "gn:country_code":"RU",
    "gn:dem":148,
    "gn:feature_class":"P",
    "gn:feature_code":"PPL",
    "gn:name":"Argunovo",
    "gn:population":0,
    "gn:timezone":"Europe/Moscow",
    "iso:country":"RU",
    "name:nor_x_preferred":[
        "Argunovo"
    ],
    "name:rus_x_preferred":[
        "\u0410\u0440\u0433\u0443\u043d\u043e\u0432\u043e"
    ],
    "wof:name":"Argunovo",
    "wof:placetype":"locality"
},
  "geometry": {"coordinates":[38.39335,55.28394],"type":"Point"}
}