{
  "type": "Feature",
  "properties": {
    "gn:admin1_code":"88",
    "gn:asciiname":"Lysovskaya",
    "gn:country_code":"RU",
    "gn:dem":110,
    "gn:feature_class":"P",
    "gn:feature_code":"PPL",
    "gn:name":"Lysovskaya",
    "gn:population":0,
    "gn:timezone":"Europe/Moscow",
    "iso:country":"RU",
    "name:rus_x_preferred":[
        "\u041b\u044b\u0441\u043e\u0432\u0441\u043a\u0430\u044f"
    ],
    "wof:name":"Lysovskaya",
    "wof:placetype":"locality"
},
  "geometry": {"coordinates":[38.2506,57.8542],"type":"Point"}
}