{
  "type": "Feature",
  "properties": {
    "gn:admin1_code":"21.0",
    "gn:asciiname":"Rezhevo",
    "gn:country_code":"RU",
    "gn:dem":141,
    "gn:feature_class":"P",
    "gn:feature_code":"PPL",
    "gn:name":"Rezhevo",
    "gn:population":0,
    "gn:timezone":"Europe/Moscow",
    "iso:country":"RU",
    "name:rus_x_preferred":[
        "\u0420\u0435\u0436\u0435\u0432\u043e"
    ],
    "name:und_x_variant":[
        "\u0420\u0435\u0436\u0435\u0432\u043e"
    ],
    "wof:name":"Rezhevo",
    "wof:placetype":"locality"
},
  "geometry": {"coordinates":[41.4367,57.36539000000001],"type":"Point"}
}