{
  "type": "Feature",
  "properties": {
    "gn:admin1_code":"62",
    "gn:asciiname":"Pustyn'",
    "gn:country_code":"RU",
    "gn:dem":79,
    "gn:feature_class":"P",
    "gn:feature_code":"PPL",
    "gn:name":"Pustyn\u2019",
    "gn:population":0,
    "gn:timezone":"Europe/Moscow",
    "iso:country":"RU",
    "name:rus_x_preferred":[
        "\u041f\u0443\u0441\u0442\u044b\u043d\u044c"
    ],
    "name:und_x_variant":[
        "Pustyn\u2019",
        "\u041f\u0443\u0441\u0442\u044b\u043d\u044c"
    ],
    "wof:name":"Pustyn'",
    "wof:placetype":"locality"
},
  "geometry": {"coordinates":[41.76667,54.93333000000001],"type":"Point"}
}