{
  "type": "Feature",
  "properties": {
    "gn:admin1_code":"88",
    "gn:asciiname":"Birichevo",
    "gn:country_code":"RU",
    "gn:dem":150,
    "gn:feature_class":"P",
    "gn:feature_code":"PPL",
    "gn:name":"Birichevo",
    "gn:population":0,
    "gn:timezone":"Europe/Moscow",
    "iso:country":"RU",
    "name:rus_x_preferred":[
        "\u0411\u0438\u0440\u0438\u0447\u0435\u0432\u043e"
    ],
    "wof:name":"Birichevo",
    "wof:placetype":"locality"
},
  "geometry": {"coordinates":[39.75656,57.11774000000001],"type":"Point"}
}