{
  "type": "Feature",
  "properties": {
    "gn:admin1_code":"56",
    "gn:asciiname":"Kuban'",
    "gn:country_code":"RU",
    "gn:dem":217,
    "gn:feature_class":"P",
    "gn:feature_code":"PPL",
    "gn:name":"Kuban\u2019",
    "gn:population":0,
    "gn:timezone":"Europe/Moscow",
    "iso:country":"RU",
    "name:rus_x_preferred":[
        "\u041a\u0443\u0431\u0430\u043d\u044c"
    ],
    "name:und_x_variant":[
        "Kuban\u2019"
    ],
    "wof:name":"Kuban'",
    "wof:placetype":"locality"
},
  "geometry": {"coordinates":[35.43278,53.18028],"type":"Point"}
}