{
  "type": "Feature",
  "properties": {
    "gn:admin1_code":"91",
    "gn:asciiname":"Ust'-Tulat",
    "gn:country_code":"RU",
    "gn:dem":217,
    "gn:feature_class":"P",
    "gn:feature_code":"PPL",
    "gn:name":"Ust\u2019-Tulat",
    "gn:population":0,
    "gn:timezone":"Asia/Krasnoyarsk",
    "iso:country":"RU",
    "name:eng_x_preferred":[
        "Ust'-Tulat"
    ],
    "name:nor_x_preferred":[
        "Ust-Tulat"
    ],
    "name:rus_x_preferred":[
        "\u0423\u0441\u0442\u044c-\u0422\u0443\u043b\u0430\u0442"
    ],
    "name:und_x_variant":[
        "Ust\u2019-Tulat"
    ],
    "wof:name":"Ust'-Tulat",
    "wof:placetype":"locality"
},
  "geometry": {"coordinates":[90.9752,56.4988],"type":"Point"}
}