{
  "type": "Feature",
  "properties": {
    "gn:admin1_code":"8",
    "gn:asciiname":"Bayrash",
    "gn:country_code":"RU",
    "gn:dem":158,
    "gn:feature_class":"P",
    "gn:feature_code":"PPL",
    "gn:name":"Bayrash",
    "gn:population":0,
    "gn:timezone":"Asia/Yekaterinburg",
    "iso:country":"RU",
    "name:rus_x_preferred":[
        "\u0411\u0430\u0439\u0440\u0430\u0448"
    ],
    "name:und_x_variant":[
        "\u0411\u0430\u0439\u0440\u0430\u0448"
    ],
    "wof:name":"Bayrash",
    "wof:placetype":"locality"
},
  "geometry": {"coordinates":[54.5132,54.6967],"type":"Point"}
}