{
  "type": "Feature",
  "properties": {
    "gn:admin1_code":"93",
    "gn:asciiname":"Dogoy",
    "gn:country_code":"RU",
    "gn:dem":675,
    "gn:feature_class":"P",
    "gn:feature_code":"PPL",
    "gn:name":"Dogoy",
    "gn:population":0,
    "gn:timezone":"Asia/Chita",
    "iso:country":"RU",
    "name:eng_x_preferred":[
        "Dogoy"
    ],
    "name:nor_x_preferred":[
        "Dogoj"
    ],
    "name:rus_x_preferred":[
        "\u0414\u043e\u0433\u043e\u0439"
    ],
    "wof:name":"Dogoy",
    "wof:placetype":"locality"
},
  "geometry": {"coordinates":[114.83333,51.28333],"type":"Point"}
}