{
  "type": "Feature",
  "properties": {
    "iso:country":"RU",
    "name:rus_x_preferred":[
        "\u041d\u043e\u0432\u043e-\u041f\u0435\u0440\u0435\u0434\u0435\u043b\u043a\u0438\u043d\u043e"
    ],
    "wof:name":"Novo-Peredelkino",
    "wof:placetype":"neighbourhood"
},
  "geometry": {"coordinates":[37.35526740008223,55.64839779423678],"type":"Point"}
}