{
  "type": "Feature",
  "properties": {
    "gn:admin1_code":"10",
    "gn:asciiname":"Oskolkovo",
    "gn:country_code":"RU",
    "gn:dem":171,
    "gn:feature_class":"P",
    "gn:feature_code":"PPL",
    "gn:name":"Oskolkovo",
    "gn:population":0,
    "gn:timezone":"Europe/Moscow",
    "iso:country":"RU",
    "name:rus_x_preferred":[
        "\u041e\u0441\u043a\u043e\u043b\u043a\u043e\u0432\u043e"
    ],
    "name:und_x_variant":[
        "\u041e\u0441\u043a\u043e\u043b\u043a\u043e\u0432\u043e"
    ],
    "wof:name":"Oskolkovo",
    "wof:placetype":"locality"
},
  "geometry": {"coordinates":[32.75961,52.66265],"type":"Point"}
}