{
  "type": "Feature",
  "properties": {
    "gn:admin1_code":"34",
    "gn:asciiname":"Priural'skiy",
    "gn:country_code":"RU",
    "gn:dem":130,
    "gn:feature_class":"P",
    "gn:feature_code":"PPL",
    "gn:name":"Priural\u2019skiy",
    "gn:population":0,
    "gn:timezone":"Europe/Moscow",
    "iso:country":"RU",
    "name:eng_x_preferred":[
        "Priural'skiy"
    ],
    "name:nor_x_preferred":[
        "Priuralskij"
    ],
    "name:rus_x_preferred":[
        "\u041f\u0440\u0438\u0443\u0440\u0430\u043b\u044c\u0441\u043a\u0438\u0439"
    ],
    "name:und_x_variant":[
        "Gabe",
        "Martiyudin",
        "\u041f\u0440\u0438\u0443\u0440\u0430\u043b\u044c\u0441\u043a\u0438\u0439",
        "Priural\u2019skiy"
    ],
    "wof:name":"Priural'skiy",
    "wof:placetype":"locality"
},
  "geometry": {"coordinates":[57.45855,62.62616],"type":"Point"}
}