{
  "type": "Feature",
  "properties": {
    "gn:admin1_code":"05",
    "gn:asciiname":"Bardagon",
    "gn:country_code":"RU",
    "gn:dem":148,
    "gn:feature_class":"P",
    "gn:feature_code":"PPL",
    "gn:name":"Bardagon",
    "gn:population":0,
    "gn:timezone":"Asia/Yakutsk",
    "iso:country":"RU",
    "name:nor_x_preferred":[
        "Bardagon"
    ],
    "name:rus_x_preferred":[
        "\u0411\u0430\u0440\u0434\u0430\u0433\u043e\u043d"
    ],
    "name:und_x_variant":[
        "Bordagon",
        "Bardan\u2019",
        "Bardagon"
    ],
    "wof:name":"Bardagon",
    "wof:placetype":"locality"
},
  "geometry": {"coordinates":[128.13613000000001,51.28398],"type":"Point"}
}