{
  "type": "Feature",
  "properties": {
    "gn:admin1_code":"83",
    "gn:asciiname":"Yevdokimtsevo",
    "gn:country_code":"RU",
    "gn:dem":140,
    "gn:feature_class":"P",
    "gn:feature_code":"PPL",
    "gn:name":"Yevdokimtsevo",
    "gn:population":0,
    "gn:timezone":"Europe/Moscow",
    "iso:country":"RU",
    "name:rus_x_preferred":[
        "\u0415\u0432\u0434\u043e\u043a\u0438\u043c\u0446\u0435\u0432\u043e"
    ],
    "wof:name":"Yevdokimtsevo",
    "wof:placetype":"locality"
},
  "geometry": {"coordinates":[39.51257,56.01024],"type":"Point"}
}