{
  "type": "Feature",
  "properties": {
    "gn:admin1_code":"71",
    "gn:asciiname":"Zakharova",
    "gn:country_code":"RU",
    "gn:dem":95,
    "gn:feature_class":"P",
    "gn:feature_code":"PPL",
    "gn:name":"Zakharova",
    "gn:population":0,
    "gn:timezone":"Asia/Yekaterinburg",
    "iso:country":"RU",
    "name:eng_x_preferred":[
        "Zakharova"
    ],
    "name:nor_x_preferred":[
        "Zakharova"
    ],
    "name:rus_x_preferred":[
        "\u0417\u0430\u0445\u0430\u0440\u043e\u0432\u0430"
    ],
    "wof:name":"Zakharova",
    "wof:placetype":"locality"
},
  "geometry": {"coordinates":[63.98982,57.40957],"type":"Point"}
}