{
  "type": "Feature",
  "properties": {
    "gn:admin1_code":"11",
    "gn:asciiname":"Ulus Khatyurta",
    "gn:cc2":"RU",
    "gn:country_code":"RU",
    "gn:dem":907,
    "gn:feature_class":"P",
    "gn:feature_code":"PPL",
    "gn:name":"Ulus Khatyurta",
    "gn:population":0,
    "gn:timezone":"Asia/Irkutsk",
    "iso:country":"RU",
    "name:und_x_variant":[
        "Khatyurta",
        "Khartyurta Settlement",
        "Ulus Khatyurta"
    ],
    "wof:name":"Ulus Khatyurta",
    "wof:placetype":"locality"
},
  "geometry": {"coordinates":[107.96666999999999,50.83333],"type":"Point"}
}