{
  "type": "Feature",
  "properties": {
    "gn:admin1_code":"28",
    "gn:asciiname":"Kavgozero",
    "gn:country_code":"RU",
    "gn:dem":54,
    "gn:feature_class":"P",
    "gn:feature_code":"PPL",
    "gn:name":"Kavgozero",
    "gn:population":0,
    "gn:timezone":"Europe/Moscow",
    "iso:country":"RU",
    "name:fin_x_preferred":[
        "Kaukaj\u00e4rvi"
    ],
    "name:rus_x_preferred":[
        "\u041a\u0430\u0432\u0433\u043e\u0437\u0435\u0440\u043e"
    ],
    "name:und_x_variant":[
        "\u041a\u0430\u0432\u0433\u043e\u0437\u0435\u0440\u043e"
    ],
    "wof:name":"Kavgozero",
    "wof:placetype":"locality"
},
  "geometry": {"coordinates":[32.27670999999999,61.27876],"type":"Point"}
}