{
  "type": "Feature",
  "properties": {
    "gn:admin1_code":"25",
    "gn:asciiname":"Shlippovo",
    "gn:country_code":"RU",
    "gn:dem":232,
    "gn:feature_class":"P",
    "gn:feature_code":"PPL",
    "gn:name":"Shlippovo",
    "gn:population":0,
    "gn:timezone":"Europe/Moscow",
    "iso:country":"RU",
    "name:rus_x_preferred":[
        "\u0428\u043b\u0438\u043f\u043f\u043e\u0432\u043e"
    ],
    "name:und_x_variant":[
        "Shlipovo",
        "Shlippovo",
        "\u0428\u043b\u0438\u043f\u043f\u043e\u0432\u043e"
    ],
    "wof:name":"Shlippovo",
    "wof:placetype":"locality"
},
  "geometry": {"coordinates":[35.1181,54.17081999999999],"type":"Point"}
}