{
  "type": "Feature",
  "properties": {
    "gn:admin1_code":"76",
    "gn:asciiname":"Lyubichki",
    "gn:country_code":"RU",
    "gn:dem":215,
    "gn:feature_class":"P",
    "gn:feature_code":"PPL",
    "gn:name":"Lyubichki",
    "gn:population":0,
    "gn:timezone":"Europe/Moscow",
    "iso:country":"RU",
    "name:rus_x_preferred":[
        "\u041b\u044e\u0431\u0438\u0447\u043a\u0438"
    ],
    "wof:name":"Lyubichki",
    "wof:placetype":"locality"
},
  "geometry": {"coordinates":[37.42927,54.51695],"type":"Point"}
}