{
  "type": "Feature",
  "properties": {
    "gn:admin1_code":"21.0",
    "gn:asciiname":"Kanino",
    "gn:country_code":"RU",
    "gn:dem":115,
    "gn:feature_class":"P",
    "gn:feature_code":"PPL",
    "gn:name":"Kanino",
    "gn:population":0,
    "gn:timezone":"Europe/Moscow",
    "iso:country":"RU",
    "name:bul_x_preferred":[
        "\u041a\u0430\u043d\u0438\u043d\u043e"
    ],
    "name:ell_x_preferred":[
        "\u039a\u03ac\u03bd\u03b9\u03bd\u03bf"
    ],
    "name:epo_x_preferred":[
        "Kanino"
    ],
    "name:fra_x_preferred":[
        "Kanino"
    ],
    "name:hun_x_preferred":[
        "Kanino"
    ],
    "name:mkd_x_preferred":[
        "\u041a\u0430\u043d\u0438\u043d\u043e"
    ],
    "name:pol_x_preferred":[
        "Kanino"
    ],
    "name:rus_x_preferred":[
        "\u041a\u0430\u043d\u0438\u043d\u043e"
    ],
    "name:sqi_x_preferred":[
        "Kanina"
    ],
    "name:srp_x_preferred":[
        "\u041a\u0430\u043d\u0438\u043d\u043e"
    ],
    "wof:name":"Kanino",
    "wof:placetype":"locality"
},
  "geometry": {"coordinates":[41.95195,57.33388000000001],"type":"Point"}
}