{
  "type": "Feature",
  "properties": {
    "gn:admin1_code":"11",
    "gn:asciiname":"Bulak",
    "gn:country_code":"RU",
    "gn:dem":743,
    "gn:feature_class":"P",
    "gn:feature_code":"PPL",
    "gn:name":"Bulak",
    "gn:population":0,
    "gn:timezone":"Asia/Irkutsk",
    "iso:country":"RU",
    "name:eng_x_preferred":[
        "Bulag"
    ],
    "name:nor_x_preferred":[
        "Bulak"
    ],
    "name:rus_x_preferred":[
        "\u0411\u0443\u043b\u0430\u043a"
    ],
    "name:und_x_variant":[
        "Bulag",
        "Bulak"
    ],
    "wof:name":"Bulak",
    "wof:placetype":"locality"
},
  "geometry": {"coordinates":[110.56074,51.96836],"type":"Point"}
}