{
  "type": "Feature",
  "properties": {
    "gn:admin1_code":"77",
    "gn:asciiname":"Kolobovo",
    "gn:country_code":"RU",
    "gn:dem":214,
    "gn:feature_class":"P",
    "gn:feature_code":"PPL",
    "gn:name":"Kolobovo",
    "gn:population":0,
    "gn:timezone":"Europe/Moscow",
    "iso:country":"RU",
    "name:rus_x_preferred":[
        "\u041a\u043e\u043b\u043e\u0431\u043e\u0432\u043e"
    ],
    "wof:name":"Kolobovo",
    "wof:placetype":"locality"
},
  "geometry": {"coordinates":[32.7898,56.7073],"type":"Point"}
}