{
  "type": "Feature",
  "properties": {
    "gn:admin1_code":"77",
    "gn:asciiname":"Goryutino",
    "gn:country_code":"RU",
    "gn:dem":135,
    "gn:feature_class":"P",
    "gn:feature_code":"PPL",
    "gn:name":"Goryutino",
    "gn:population":0,
    "gn:timezone":"Europe/Moscow",
    "iso:country":"RU",
    "name:rus_x_preferred":[
        "\u0413\u043e\u0440\u044e\u0442\u0438\u043d\u043e"
    ],
    "wof:name":"Goryutino",
    "wof:placetype":"locality"
},
  "geometry": {"coordinates":[36.06197,56.89224],"type":"Point"}
}