{
  "type": "Feature",
  "properties": {
    "gn:admin1_code":"8",
    "gn:asciiname":"Milisonovka",
    "gn:country_code":"RU",
    "gn:dem":219,
    "gn:feature_class":"P",
    "gn:feature_code":"PPL",
    "gn:name":"Milisonovka",
    "gn:population":0,
    "gn:timezone":"Asia/Yekaterinburg",
    "iso:country":"RU",
    "name:rus_x_preferred":[
        "\u041c\u0438\u043b\u0438\u0441\u043e\u043d\u043e\u0432\u043a\u0430"
    ],
    "wof:name":"Milisonovka",
    "wof:placetype":"locality"
},
  "geometry": {"coordinates":[54.0221,53.7817],"type":"Point"}
}