{
  "type": "Feature",
  "properties": {
    "gn:admin1_code":"53",
    "gn:asciiname":"Pautovo",
    "gn:country_code":"RU",
    "gn:dem":137,
    "gn:feature_class":"P",
    "gn:feature_code":"PPL",
    "gn:name":"Pautovo",
    "gn:population":0,
    "gn:timezone":"Asia/Novosibirsk",
    "iso:country":"RU",
    "name:rus_x_preferred":[
        "\u041f\u0430\u0443\u0442\u043e\u0432\u043e"
    ],
    "name:und_x_variant":[
        "Pautova",
        "Pautovo"
    ],
    "wof:name":"Pautovo",
    "wof:placetype":"locality"
},
  "geometry": {"coordinates":[82.7597,55.5443],"type":"Point"}
}