{
  "type": "Feature",
  "properties": {
    "gn:admin1_code":"37",
    "gn:asciiname":"Ploskovo",
    "gn:cc2":"RU",
    "gn:country_code":"RU",
    "gn:dem":168,
    "gn:feature_class":"P",
    "gn:feature_code":"PPL",
    "gn:name":"Ploskovo",
    "gn:population":0,
    "gn:timezone":"Europe/Moscow",
    "iso:country":"RU",
    "name:rus_x_preferred":[
        "\u041f\u043b\u043e\u0441\u043a\u043e\u0432\u043e"
    ],
    "name:und_x_variant":[
        "Ploskaya",
        "Ploskova",
        "Ploskovo"
    ],
    "wof:name":"Ploskovo",
    "wof:placetype":"locality"
},
  "geometry": {"coordinates":[41.63333,57.78333000000001],"type":"Point"}
}