{
  "type": "Feature",
  "properties": {
    "gn:admin1_code":"61",
    "gn:asciiname":"Grekovo-Stepanovka",
    "gn:country_code":"RU",
    "gn:dem":100,
    "gn:feature_class":"P",
    "gn:feature_code":"PPL",
    "gn:name":"Grekovo-Stepanovka",
    "gn:population":0,
    "gn:timezone":"Europe/Moscow",
    "iso:country":"RU",
    "name:eng_x_preferred":[
        "Grekovo-Stepanovka"
    ],
    "name:nor_x_preferred":[
        "Grekovo-Stepanovka"
    ],
    "name:rus_x_preferred":[
        "\u0413\u0440\u0435\u043a\u043e\u0432\u043e-\u0421\u0442\u0435\u043f\u0430\u043d\u043e\u0432\u043a\u0430"
    ],
    "name:und_x_variant":[
        "Girekovo-Stepanovka",
        "Grekovo-stepanovskaya"
    ],
    "wof:name":"Grekovo-Stepanovka",
    "wof:placetype":"locality"
},
  "geometry": {"coordinates":[40.66226,49.34462],"type":"Point"}
}