{
  "type": "Feature",
  "properties": {
    "gn:admin1_code":"61",
    "gn:asciiname":"Paliy",
    "gn:country_code":"RU",
    "gn:dem":108,
    "gn:feature_class":"P",
    "gn:feature_code":"PPL",
    "gn:name":"Paliy",
    "gn:population":0,
    "gn:timezone":"Europe/Moscow",
    "iso:country":"RU",
    "name:rus_x_preferred":[
        "\u041f\u0430\u043b\u0438\u0439"
    ],
    "name:und_x_variant":[
        "Poliyev",
        "Paliy"
    ],
    "wof:name":"Paliy",
    "wof:placetype":"locality"
},
  "geometry": {"coordinates":[38.71176,47.5073],"type":"Point"}
}