{
  "type": "Feature",
  "properties": {
    "gn:admin1_code":"77",
    "gn:asciiname":"Vetoshki",
    "gn:country_code":"RU",
    "gn:dem":243,
    "gn:feature_class":"P",
    "gn:feature_code":"PPL",
    "gn:name":"Vetoshki",
    "gn:population":0,
    "gn:timezone":"Europe/Moscow",
    "iso:country":"RU",
    "name:eng_x_preferred":[
        "Vetoshki"
    ],
    "name:nor_x_preferred":[
        "Vetosjki"
    ],
    "name:rus_x_preferred":[
        "\u0412\u0435\u0442\u043e\u0448\u043a\u0438"
    ],
    "name:und_x_variant":[
        "\u0412\u0435\u0442\u043e\u0448\u043a\u0438",
        "Vetoshki"
    ],
    "wof:name":"Vetoshki",
    "wof:placetype":"locality"
},
  "geometry": {"coordinates":[31.49223,56.90868],"type":"Point"}
}