{
  "type": "Feature",
  "properties": {
    "gn:admin1_code":"61",
    "gn:asciiname":"Khirnyy",
    "gn:country_code":"RU",
    "gn:dem":11,
    "gn:feature_class":"P",
    "gn:feature_code":"PPL",
    "gn:name":"Khirnyy",
    "gn:population":0,
    "gn:timezone":"Europe/Moscow",
    "iso:country":"RU",
    "name:rus_x_preferred":[
        "\u0425\u0438\u0440\u043d\u044b\u0439"
    ],
    "name:und_x_variant":[
        "Khirny",
        "Khirnyy",
        "\u0425\u0438\u0440\u043d\u044b\u0439"
    ],
    "wof:name":"Khirnyy",
    "wof:placetype":"locality"
},
  "geometry": {"coordinates":[41.12173,47.06462],"type":"Point"}
}