{
  "type": "Feature",
  "properties": {
    "gn:admin1_code":"54",
    "gn:asciiname":"Berkin",
    "gn:country_code":"RU",
    "gn:dem":109,
    "gn:feature_class":"P",
    "gn:feature_code":"PPL",
    "gn:name":"Berkin",
    "gn:population":0,
    "gn:timezone":"Asia/Omsk",
    "iso:country":"RU",
    "name:deu_x_preferred":[
        "Berkin"
    ],
    "name:nor_x_preferred":[
        "Berkin"
    ],
    "name:rus_x_preferred":[
        "\u0411\u0435\u0440\u043a\u0438\u043d"
    ],
    "name:tur_x_preferred":[
        "Berkin"
    ],
    "wof:name":"Berkin",
    "wof:placetype":"locality"
},
  "geometry": {"coordinates":[72.76666999999998,54.76667],"type":"Point"}
}