{
  "type": "Feature",
  "properties": {
    "gn:admin1_code":"34.0",
    "gn:asciiname":"Belyayevskaya",
    "gn:country_code":"RU",
    "gn:dem":149,
    "gn:feature_class":"P",
    "gn:feature_code":"PPL",
    "gn:name":"Belyayevskaya",
    "gn:population":0,
    "gn:timezone":"Europe/Moscow",
    "iso:country":"RU",
    "name:nor_x_preferred":[
        "Beljaevskaja"
    ],
    "name:rus_x_preferred":[
        "\u0411\u0435\u043b\u044f\u0435\u0432\u0441\u043a\u0430\u044f"
    ],
    "name:und_x_variant":[
        "Belyayevtsy",
        "Belyayevskaya"
    ],
    "wof:name":"Belyayevskaya",
    "wof:placetype":"locality"
},
  "geometry": {"coordinates":[49.63887,60.31148],"type":"Point"}
}