{
  "type": "Feature",
  "properties": {
    "gn:admin1_code":"71",
    "gn:asciiname":"Lipovskiy",
    "gn:country_code":"RU",
    "gn:dem":269,
    "gn:feature_class":"P",
    "gn:feature_code":"PPL",
    "gn:name":"Lipovskiy",
    "gn:population":0,
    "gn:timezone":"Asia/Yekaterinburg",
    "iso:country":"RU",
    "name:eng_x_preferred":[
        "Lipovskiy"
    ],
    "name:nor_x_preferred":[
        "Lipovskij"
    ],
    "name:rus_x_preferred":[
        "\u041b\u0438\u043f\u043e\u0432\u0441\u043a\u0438\u0439"
    ],
    "name:und_x_variant":[
        "Lipovskoye"
    ],
    "wof:name":"Lipovskiy",
    "wof:placetype":"locality"
},
  "geometry": {"coordinates":[61.11896,57.01825],"type":"Point"}
}