{
  "type": "Feature",
  "properties": {
    "gn:admin1_code":"21",
    "gn:asciiname":"Rylkovo",
    "gn:country_code":"RU",
    "gn:dem":93,
    "gn:feature_class":"P",
    "gn:feature_code":"PPL",
    "gn:name":"Rylkovo",
    "gn:population":0,
    "gn:timezone":"Europe/Moscow",
    "iso:country":"RU",
    "name:rus_x_preferred":[
        "\u0420\u044b\u043b\u043a\u043e\u0432\u043e"
    ],
    "name:und_x_variant":[
        "Rylkova",
        "Rylkovo",
        "\u0420\u044b\u043b\u043a\u043e\u0432\u043e"
    ],
    "wof:name":"Rylkovo",
    "wof:placetype":"locality"
},
  "geometry": {"coordinates":[41.22006,57.39832],"type":"Point"}
}