{
  "type": "Feature",
  "properties": {
    "gn:admin1_code":"54",
    "gn:asciiname":"Nikolenko",
    "gn:country_code":"RU",
    "gn:dem":117,
    "gn:feature_class":"P",
    "gn:feature_code":"PPL",
    "gn:name":"Nikolenko",
    "gn:population":0,
    "gn:timezone":"Asia/Omsk",
    "iso:country":"RU",
    "name:rus_x_preferred":[
        "\u041d\u0438\u043a\u043e\u043b\u0435\u043d\u043a\u043e"
    ],
    "wof:name":"Nikolenko",
    "wof:placetype":"locality"
},
  "geometry": {"coordinates":[73.87317,54.79188000000001],"type":"Point"}
}