{
  "type": "Feature",
  "properties": {
    "gn:admin1_code":"76",
    "gn:asciiname":"Savinki",
    "gn:cc2":"RU",
    "gn:country_code":"RU",
    "gn:dem":200,
    "gn:feature_class":"P",
    "gn:feature_code":"PPL",
    "gn:name":"Savinki",
    "gn:population":0,
    "gn:timezone":"Europe/Moscow",
    "iso:country":"RU",
    "name:rus_x_preferred":[
        "\u0421\u0430\u0432\u0438\u043d\u043a\u0438"
    ],
    "name:und_x_variant":[
        "Savinskiy",
        "Savinki"
    ],
    "wof:name":"Savinki",
    "wof:placetype":"locality"
},
  "geometry": {"coordinates":[36.55,53.56667],"type":"Point"}
}