{
  "type": "Feature",
  "properties": {
    "gn:admin1_code":"85",
    "gn:asciiname":"Vorob'yevo",
    "gn:country_code":"RU",
    "gn:dem":134,
    "gn:feature_class":"P",
    "gn:feature_code":"PPL",
    "gn:name":"Vorob\u2019y\u00ebvo",
    "gn:population":0,
    "gn:timezone":"Europe/Moscow",
    "iso:country":"RU",
    "name:rus_x_preferred":[
        "\u0412\u043e\u0440\u043e\u0431\u044c\u0451\u0432\u043e"
    ],
    "name:und_x_variant":[
        "Vorob\u2019y\u00ebvo",
        "\u0412\u043e\u0440\u043e\u0431\u044c\u0451\u0432\u043e"
    ],
    "wof:name":"Vorob'yevo",
    "wof:placetype":"locality"
},
  "geometry": {"coordinates":[38.20768,59.85684000000001],"type":"Point"}
}