{
  "type": "Feature",
  "properties": {
    "gn:admin1_code":"85.0",
    "gn:asciiname":"Rudino",
    "gn:country_code":"RU",
    "gn:dem":160,
    "gn:feature_class":"P",
    "gn:feature_code":"PPL",
    "gn:name":"Rudino",
    "gn:population":0,
    "gn:timezone":"Europe/Moscow",
    "iso:country":"RU",
    "name:rus_x_preferred":[
        "\u0420\u0443\u0434\u0438\u043d\u043e"
    ],
    "wof:name":"Rudino",
    "wof:placetype":"locality"
},
  "geometry": {"coordinates":[40.36177,58.9188],"type":"Point"}
}