{
  "type": "Feature",
  "properties": {
    "gn:admin1_code":"91.0",
    "gn:asciiname":"Pinchino",
    "gn:country_code":"RU",
    "gn:dem":337,
    "gn:feature_class":"P",
    "gn:feature_code":"PPL",
    "gn:name":"Pinchino",
    "gn:population":0,
    "gn:timezone":"Asia/Krasnoyarsk",
    "iso:country":"RU",
    "name:rus_x_preferred":[
        "\u041f\u0438\u043d\u0447\u0438\u043d\u043e"
    ],
    "wof:name":"Pinchino",
    "wof:placetype":"locality"
},
  "geometry": {"coordinates":[93.82250000000001,55.8498],"type":"Point"}
}