{
  "type": "Feature",
  "properties": {
    "gn:admin1_code":"1",
    "gn:asciiname":"Novoprokhladnoye",
    "gn:country_code":"RU",
    "gn:dem":653,
    "gn:feature_class":"P",
    "gn:feature_code":"PPL",
    "gn:name":"Novoprokhladnoye",
    "gn:population":0,
    "gn:timezone":"Europe/Moscow",
    "iso:country":"RU",
    "name:eng_x_preferred":[
        "Novoprokhladnoye"
    ],
    "name:nor_x_preferred":[
        "Novoprokhladnoje"
    ],
    "name:rus_x_preferred":[
        "\u041d\u043e\u0432\u043e\u043f\u0440\u043e\u0445\u043b\u0430\u0434\u043d\u043e\u0435"
    ],
    "name:und_x_variant":[
        "\u041d\u043e\u0432\u043e\u043f\u0440\u043e\u0445\u043b\u0430\u0434\u043d\u043e\u0435",
        "Novoprokhladnoye"
    ],
    "wof:name":"Novoprokhladnoye",
    "wof:placetype":"locality"
},
  "geometry": {"coordinates":[40.2875,44.13861],"type":"Point"}
}