{
  "type": "Feature",
  "properties": {
    "gn:admin1_code":"44",
    "gn:asciiname":"Mal'dyak",
    "gn:country_code":"RU",
    "gn:dem":787,
    "gn:feature_class":"P",
    "gn:feature_code":"PPL",
    "gn:name":"Mal\u2019dyak",
    "gn:population":0,
    "gn:timezone":"Asia/Magadan",
    "iso:country":"RU",
    "name:eng_x_preferred":[
        "Mal'dyak"
    ],
    "name:nor_x_preferred":[
        "Maldjak"
    ],
    "name:rus_x_preferred":[
        "\u041c\u0430\u043b\u044c\u0434\u044f\u043a"
    ],
    "name:und_x_variant":[
        "Mal\u2019dyakh",
        "Mal\u2019dyak"
    ],
    "wof:name":"Mal'dyak",
    "wof:placetype":"locality"
},
  "geometry": {"coordinates":[148.23688000000001,62.99871],"type":"Point"}
}