{
  "type": "Feature",
  "properties": {
    "gn:admin1_code":"28",
    "gn:asciiname":"Pazhilo",
    "gn:country_code":"RU",
    "gn:dem":80,
    "gn:feature_class":"P",
    "gn:feature_code":"PPL",
    "gn:name":"Pazhilo",
    "gn:population":0,
    "gn:timezone":"Europe/Moscow",
    "iso:country":"RU",
    "name:fin_x_preferred":[
        "Pasala"
    ],
    "name:rus_x_preferred":[
        "\u041f\u0430\u0436\u0438\u043b\u043e"
    ],
    "name:und_x_variant":[
        "\u041f\u0430\u0436\u0438\u043b\u043e"
    ],
    "wof:name":"Pazhilo",
    "wof:placetype":"locality"
},
  "geometry": {"coordinates":[32.26667,61.68333000000001],"type":"Point"}
}