{
  "type": "Feature",
  "properties": {
    "gn:admin1_code":"85",
    "gn:asciiname":"Studenets",
    "gn:country_code":"RU",
    "gn:dem":190,
    "gn:feature_class":"P",
    "gn:feature_code":"PPL",
    "gn:name":"Studenets",
    "gn:population":0,
    "gn:timezone":"Europe/Moscow",
    "iso:country":"RU",
    "name:ceb_x_preferred":[
        "Studenets"
    ],
    "name:rus_x_preferred":[
        "\u0421\u0442\u0443\u0434\u0435\u043d\u0435\u0446"
    ],
    "name:swe_x_preferred":[
        "Studenets"
    ],
    "wof:name":"Studenets",
    "wof:placetype":"locality"
},
  "geometry": {"coordinates":[40.25778,58.77583000000001],"type":"Point"}
}