{
  "type": "Feature",
  "properties": {
    "gn:admin1_code":"71",
    "gn:asciiname":"Mezhevka",
    "gn:country_code":"RU",
    "gn:dem":260,
    "gn:feature_class":"P",
    "gn:feature_code":"PPL",
    "gn:name":"Mezh\u00ebvka",
    "gn:population":0,
    "gn:timezone":"Asia/Yekaterinburg",
    "iso:country":"RU",
    "name:rus_x_preferred":[
        "\u041c\u0435\u0436\u0451\u0432\u043a\u0430"
    ],
    "name:und_x_variant":[
        "Mezh\u00ebvka",
        "\u041c\u0435\u0436\u0451\u0432\u043a\u0430"
    ],
    "wof:name":"Mezhevka",
    "wof:placetype":"locality"
},
  "geometry": {"coordinates":[58.4843,56.55087],"type":"Point"}
}