{
  "type": "Feature",
  "properties": {
    "gn:admin1_code":"20",
    "gn:asciiname":"Ust'ye Ilima",
    "gn:country_code":"RU",
    "gn:dem":291,
    "gn:feature_class":"P",
    "gn:feature_code":"PPL",
    "gn:name":"Ust\u2019ye Ilima",
    "gn:population":0,
    "gn:timezone":"Asia/Irkutsk",
    "iso:country":"RU",
    "wof:name":"Ust'ye Ilima",
    "wof:placetype":"locality"
},
  "geometry": {"coordinates":[102.58333,57.66667],"type":"Point"}
}