{
  "type": "Feature",
  "properties": {
    "gn:admin1_code":"15",
    "gn:asciiname":"Pogyndeno",
    "gn:cc2":"RU",
    "gn:country_code":"RU",
    "gn:dem":77,
    "gn:feature_class":"P",
    "gn:feature_code":"PPL",
    "gn:name":"Pogyndeno",
    "gn:population":0,
    "gn:timezone":"Asia/Anadyr",
    "iso:country":"RU",
    "name:rus_x_preferred":[
        "\u041f\u043e\u0433\u044b\u043d\u0434\u0435\u043d\u043e"
    ],
    "name:und_x_variant":[
        "Togondino",
        "Pogynden",
        "Pogyndino",
        "Pogyndeno"
    ],
    "wof:name":"Pogyndeno",
    "wof:placetype":"locality"
},
  "geometry": {"coordinates":[163.94999999999999,68.18333],"type":"Point"}
}