{
  "type": "Feature",
  "properties": {
    "gn:admin1_code":"84",
    "gn:asciiname":"Gryanchenko",
    "gn:country_code":"RU",
    "gn:dem":30,
    "gn:feature_class":"P",
    "gn:feature_code":"PPL",
    "gn:name":"Gryanchenko",
    "gn:population":0,
    "gn:timezone":"Europe/Volgograd",
    "iso:country":"RU",
    "name:rus_x_preferred":[
        "\u0413\u0440\u044f\u043d\u0447\u0435\u043d\u043a\u043e"
    ],
    "name:und_x_variant":[
        "\u0413\u0440\u044f\u043d\u0447\u0435\u043d\u043a\u043e"
    ],
    "wof:name":"Gryanchenko",
    "wof:placetype":"locality"
},
  "geometry": {"coordinates":[45.55,49.73333],"type":"Point"}
}