{
  "type": "Feature",
  "properties": {
    "gn:admin1_code":"55.0",
    "gn:asciiname":"Aptulla",
    "gn:country_code":"RU",
    "gn:dem":404,
    "gn:feature_class":"P",
    "gn:feature_code":"PPL",
    "gn:name":"Aptulla",
    "gn:population":0,
    "gn:timezone":"Asia/Yekaterinburg",
    "iso:country":"RU",
    "name:nor_x_preferred":[
        "Aptulla"
    ],
    "name:rus_x_preferred":[
        "\u0410\u043f\u0442\u0443\u043b\u043b\u0430"
    ],
    "wof:name":"Aptulla",
    "wof:placetype":"locality"
},
  "geometry": {"coordinates":[57.91667,51.56667],"type":"Point"}
}