{
  "type": "Feature",
  "properties": {
    "gn:admin1_code":"86",
    "gn:asciiname":"Petrovskoye",
    "gn:cc2":"RU",
    "gn:country_code":"RU",
    "gn:dem":160,
    "gn:feature_class":"P",
    "gn:feature_code":"PPL",
    "gn:name":"Petrovskoye",
    "gn:population":0,
    "gn:timezone":"Europe/Moscow",
    "iso:country":"RU",
    "name:rus_x_preferred":[
        "\u041f\u0435\u0442\u0440\u043e\u0432\u0441\u043a\u043e\u0435"
    ],
    "name:und_x_variant":[
        "Krivtsovka",
        "Petrovskoye"
    ],
    "wof:name":"Petrovskoye",
    "wof:placetype":"locality"
},
  "geometry": {"coordinates":[40.09444000000001,51.93667],"type":"Point"}
}