{
  "type": "Feature",
  "properties": {
    "gn:admin1_code":"71",
    "gn:asciiname":"Listvyannoye",
    "gn:country_code":"RU",
    "gn:dem":245,
    "gn:feature_class":"P",
    "gn:feature_code":"PPL",
    "gn:name":"Listvyannoye",
    "gn:population":0,
    "gn:timezone":"Asia/Yekaterinburg",
    "iso:country":"RU",
    "name:rus_x_preferred":[
        "\u041b\u0438\u0441\u0442\u0432\u044f\u043d\u043d\u043e\u0435"
    ],
    "name:und_x_variant":[
        "Listvennaya"
    ],
    "wof:name":"Listvyannoye",
    "wof:placetype":"locality"
},
  "geometry": {"coordinates":[60.18111,57.35861],"type":"Point"}
}