{
  "type": "Feature",
  "properties": {
    "gn:admin1_code":"25.0",
    "gn:asciiname":"Chubarovo",
    "gn:country_code":"RU",
    "gn:dem":171,
    "gn:feature_class":"P",
    "gn:feature_code":"PPL",
    "gn:name":"Chubarovo",
    "gn:population":130,
    "gn:timezone":"Europe/Moscow",
    "iso:country":"RU",
    "name:eng_x_preferred":[
        "Chubarovo"
    ],
    "name:nor_x_preferred":[
        "Tsjubarovo"
    ],
    "name:rus_x_preferred":[
        "\u0427\u0443\u0431\u0430\u0440\u043e\u0432\u043e"
    ],
    "wof:name":"Chubarovo",
    "wof:placetype":"locality",
    "wof:population":130
},
  "geometry": {"coordinates":[36.9223,55.1993],"type":"Point"}
}