{
  "type": "Feature",
  "properties": {
    "gn:admin1_code":"77",
    "gn:asciiname":"Igut'yevo",
    "gn:country_code":"RU",
    "gn:dem":151,
    "gn:feature_class":"P",
    "gn:feature_code":"PPL",
    "gn:name":"Igut\u2019yevo",
    "gn:population":0,
    "gn:timezone":"Europe/Moscow",
    "iso:country":"RU",
    "name:nor_x_preferred":[
        "Igutjevo"
    ],
    "name:rus_x_preferred":[
        "\u0418\u0433\u0443\u0442\u044c\u0435\u0432\u043e"
    ],
    "name:und_x_variant":[
        "Igut\u2019yevo"
    ],
    "wof:name":"Igut'yevo",
    "wof:placetype":"locality"
},
  "geometry": {"coordinates":[35.23699000000001,56.65888],"type":"Point"}
}