{
  "type": "Feature",
  "properties": {
    "gn:admin1_code":"85.0",
    "gn:asciiname":"Batranskiy",
    "gn:country_code":"RU",
    "gn:dem":130,
    "gn:feature_class":"P",
    "gn:feature_code":"PPL",
    "gn:name":"Batranskiy",
    "gn:population":0,
    "gn:timezone":"Europe/Moscow",
    "iso:country":"RU",
    "name:nor_x_preferred":[
        "Batranskij"
    ],
    "name:rus_x_preferred":[
        "\u0411\u0430\u0442\u0440\u0430\u043d\u0441\u043a\u0438\u0439"
    ],
    "wof:name":"Batranskiy",
    "wof:placetype":"locality"
},
  "geometry": {"coordinates":[37.91667,59.13333000000001],"type":"Point"}
}