{
  "type": "Feature",
  "properties": {
    "gn:admin1_code":"41",
    "gn:asciiname":"Andrianovka",
    "gn:country_code":"RU",
    "gn:dem":193,
    "gn:feature_class":"P",
    "gn:feature_code":"PPL",
    "gn:name":"Andrianovka",
    "gn:population":0,
    "gn:timezone":"Europe/Moscow",
    "iso:country":"RU",
    "name:rus_x_preferred":[
        "\u0410\u043d\u0434\u0440\u0438\u0430\u043d\u043e\u0432\u043a\u0430"
    ],
    "wof:name":"Andrianovka",
    "wof:placetype":"locality"
},
  "geometry": {"coordinates":[35.9285,51.5233],"type":"Point"}
}