{
  "type": "Feature",
  "properties": {
    "gn:admin1_code":"25",
    "gn:asciiname":"Krasnyy Lipnik",
    "gn:country_code":"RU",
    "gn:dem":212,
    "gn:feature_class":"P",
    "gn:feature_code":"PPL",
    "gn:name":"Krasnyy Lipnik",
    "gn:population":0,
    "gn:timezone":"Europe/Moscow",
    "iso:country":"RU",
    "name:rus_x_preferred":[
        "\u041a\u0440\u0430\u0441\u043d\u044b\u0439 \u041b\u0438\u043f\u043d\u0438\u043a"
    ],
    "name:und_x_variant":[
        "\u041a\u0440\u0430\u0441\u043d\u044b\u0439 \u041b\u0438\u043f\u043d\u0438\u043a"
    ],
    "wof:name":"Krasnyy Lipnik",
    "wof:placetype":"locality"
},
  "geometry": {"coordinates":[35.54806,53.97917],"type":"Point"}
}