{
  "type": "Feature",
  "properties": {
    "gn:admin1_code":"12.0",
    "gn:asciiname":"Ami",
    "gn:country_code":"RU",
    "gn:dem":2020,
    "gn:feature_class":"P",
    "gn:feature_code":"PPL",
    "gn:name":"Ami",
    "gn:population":0,
    "gn:timezone":"Europe/Moscow",
    "iso:country":"RU",
    "name:nor_x_preferred":[
        "Ami"
    ],
    "name:rus_x_preferred":[
        "\u0410\u043c\u0438"
    ],
    "wof:name":"Ami",
    "wof:placetype":"locality"
},
  "geometry": {"coordinates":[45.25556,42.75361],"type":"Point"}
}