{
  "type": "Feature",
  "properties": {
    "gn:admin1_code":"85",
    "gn:asciiname":"Nizhneye Pankratovo",
    "gn:country_code":"RU",
    "gn:dem":65,
    "gn:feature_class":"P",
    "gn:feature_code":"PPL",
    "gn:name":"Nizhneye Pankratovo",
    "gn:population":0,
    "gn:timezone":"Europe/Moscow",
    "iso:country":"RU",
    "name:rus_x_preferred":[
        "\u041d\u0438\u0436\u043d\u0435\u0435 \u041f\u0430\u043d\u043a\u0440\u0430\u0442\u043e\u0432\u043e"
    ],
    "wof:name":"Nizhneye Pankratovo",
    "wof:placetype":"locality"
},
  "geometry": {"coordinates":[46.4182,60.7744],"type":"Point"}
}