{
  "type": "Feature",
  "properties": {
    "gn:admin1_code":"20",
    "gn:asciiname":"Baganta",
    "gn:country_code":"RU",
    "gn:dem":680,
    "gn:feature_class":"P",
    "gn:feature_code":"PPL",
    "gn:name":"Baganta",
    "gn:population":0,
    "gn:timezone":"Asia/Irkutsk",
    "iso:country":"RU",
    "name:eng_x_preferred":[
        "Baganta"
    ],
    "name:nor_x_preferred":[
        "Baganta"
    ],
    "name:rus_x_preferred":[
        "\u0411\u0430\u0433\u0430\u043d\u0442\u0430"
    ],
    "name:und_x_variant":[
        "Ada",
        "Boganta",
        "\u0411\u0430\u0433\u0430\u043d\u0442\u0430",
        "Baganta"
    ],
    "wof:name":"Baganta",
    "wof:placetype":"locality"
},
  "geometry": {"coordinates":[106.09083,53.10056],"type":"Point"}
}