{
  "type": "Feature",
  "properties": {
    "gn:admin1_code":"52",
    "gn:asciiname":"Volot",
    "gn:country_code":"RU",
    "gn:dem":78,
    "gn:feature_class":"P",
    "gn:feature_code":"PPL",
    "gn:name":"Volot",
    "gn:population":0,
    "gn:timezone":"Europe/Moscow",
    "iso:country":"RU",
    "name:ceb_x_preferred":[
        "Volot"
    ],
    "name:rus_x_preferred":[
        "\u0412\u043e\u043b\u043e\u0442"
    ],
    "name:und_x_variant":[
        "Pos\u00eblok Volot",
        "\u041f\u043e\u0441\u0451\u043b\u043e\u043a \u0412\u043e\u043b\u043e\u0442",
        "Volot",
        "\u0412\u043e\u043b\u043e\u0442"
    ],
    "wof:name":"Volot",
    "wof:placetype":"locality"
},
  "geometry": {"coordinates":[30.6858,57.93816],"type":"Point"}
}