{
  "type": "Feature",
  "properties": {
    "gn:admin1_code":"83.0",
    "gn:asciiname":"Ababurovo",
    "gn:country_code":"RU",
    "gn:dem":190,
    "gn:feature_class":"P",
    "gn:feature_code":"PPL",
    "gn:name":"Ababurovo",
    "gn:population":0,
    "gn:timezone":"Europe/Moscow",
    "iso:country":"RU",
    "name:nor_x_preferred":[
        "Ababurovo"
    ],
    "name:rus_x_preferred":[
        "\u0410\u0431\u0430\u0431\u0443\u0440\u043e\u0432\u043e"
    ],
    "name:und_x_variant":[
        "Oboburovo",
        "Ababurovo"
    ],
    "wof:name":"Ababurovo",
    "wof:placetype":"locality"
},
  "geometry": {"coordinates":[40.04832,56.32077],"type":"Point"}
}