{
  "type": "Feature",
  "properties": {
    "gn:admin1_code":"8",
    "gn:asciiname":"Tokberdino",
    "gn:country_code":"RU",
    "gn:dem":156,
    "gn:feature_class":"P",
    "gn:feature_code":"PPL",
    "gn:name":"Tokberdino",
    "gn:population":0,
    "gn:timezone":"Asia/Yekaterinburg",
    "iso:country":"RU",
    "name:eng_x_preferred":[
        "Tokberdino"
    ],
    "name:nor_x_preferred":[
        "Tokberdino"
    ],
    "name:rus_x_preferred":[
        "\u0422\u043e\u043a\u0431\u0435\u0440\u0434\u0438\u043d\u043e"
    ],
    "name:und_x_variant":[
        "Takberdino",
        "Tokberdina"
    ],
    "wof:name":"Tokberdino",
    "wof:placetype":"locality"
},
  "geometry": {"coordinates":[53.89278,55.13833],"type":"Point"}
}