{
  "type": "Feature",
  "properties": {
    "gn:admin1_code":"54",
    "gn:asciiname":"Pochekuyevo",
    "gn:country_code":"RU",
    "gn:dem":76,
    "gn:feature_class":"P",
    "gn:feature_code":"PPL",
    "gn:name":"Pochekuyevo",
    "gn:population":0,
    "gn:timezone":"Asia/Omsk",
    "iso:country":"RU",
    "name:eng_x_preferred":[
        "Pochekuyevo"
    ],
    "name:nor_x_preferred":[
        "Potsjekujevo"
    ],
    "name:rus_x_preferred":[
        "\u041f\u043e\u0447\u0435\u043a\u0443\u0435\u0432\u043e"
    ],
    "wof:name":"Pochekuyevo",
    "wof:placetype":"locality"
},
  "geometry": {"coordinates":[74.45938000000002,56.51516],"type":"Point"}
}