{
  "type": "Feature",
  "properties": {
    "gn:admin1_code":"73",
    "gn:asciiname":"Berezovka",
    "gn:country_code":"RU",
    "gn:dem":100,
    "gn:feature_class":"P",
    "gn:feature_code":"PPL",
    "gn:name":"Berezovka",
    "gn:population":0,
    "gn:timezone":"Europe/Moscow",
    "iso:country":"RU",
    "name:ceb_x_preferred":[
        "Berezovka"
    ],
    "name:lav_x_preferred":[
        "Berezovka"
    ],
    "name:lit_x_preferred":[
        "Berezovka"
    ],
    "name:nor_x_preferred":[
        "Berezovka"
    ],
    "name:rus_x_preferred":[
        "\u0411\u0435\u0440\u0451\u0437\u043e\u0432\u043a\u0430"
    ],
    "name:swe_x_preferred":[
        "Berezovka"
    ],
    "name:und_x_variant":[
        "\u0411\u0435\u0440\u0451\u0437\u043e\u0432\u043a\u0430",
        "Berezovka"
    ],
    "wof:name":"Berezovka",
    "wof:placetype":"locality"
},
  "geometry": {"coordinates":[50.29254,55.13419],"type":"Point"}
}