{
  "type": "Feature",
  "properties": {
    "gn:admin1_code":"59",
    "gn:asciiname":"Novovarvarovka",
    "gn:country_code":"RU",
    "gn:dem":221,
    "gn:feature_class":"P",
    "gn:feature_code":"PPL",
    "gn:name":"Novovarvarovka",
    "gn:population":0,
    "gn:timezone":"Asia/Vladivostok",
    "iso:country":"RU",
    "name:eng_x_preferred":[
        "Novovarvarovka"
    ],
    "name:nor_x_preferred":[
        "Novovarvarovka"
    ],
    "name:rus_x_preferred":[
        "\u041d\u043e\u0432\u043e\u0432\u0430\u0440\u0432\u0430\u0440\u043e\u0432\u043a\u0430"
    ],
    "name:und_x_variant":[
        "Novaya Varvarovka"
    ],
    "wof:name":"Novovarvarovka",
    "wof:placetype":"locality"
},
  "geometry": {"coordinates":[132.98466000000002,43.97336],"type":"Point"}
}