{
  "type": "Feature",
  "properties": {
    "gn:admin1_code":"59",
    "gn:asciiname":"Terekhovka",
    "gn:country_code":"RU",
    "gn:dem":26,
    "gn:feature_class":"P",
    "gn:feature_code":"PPL",
    "gn:name":"Terekhovka",
    "gn:population":0,
    "gn:timezone":"Asia/Vladivostok",
    "iso:country":"RU",
    "name:eng_x_preferred":[
        "Terekhovka"
    ],
    "name:nor_x_preferred":[
        "Terekhovka"
    ],
    "name:rus_x_preferred":[
        "\u0422\u0435\u0440\u0435\u0445\u043e\u0432\u043a\u0430"
    ],
    "wof:name":"Terekhovka",
    "wof:placetype":"locality"
},
  "geometry": {"coordinates":[131.91796000000002,43.64042],"type":"Point"}
}