{
  "type": "Feature",
  "properties": {
    "gn:admin1_code":"16.0",
    "gn:asciiname":"Aslyyaly",
    "gn:country_code":"RU",
    "gn:dem":150,
    "gn:feature_class":"P",
    "gn:feature_code":"PPL",
    "gn:name":"Aslyyaly",
    "gn:population":0,
    "gn:timezone":"Europe/Moscow",
    "iso:country":"RU",
    "name:nor_x_preferred":[
        "Aslyjaly"
    ],
    "name:rus_x_preferred":[
        "\u0410\u0441\u043b\u044b\u044f\u043b\u044b"
    ],
    "wof:name":"Aslyyaly",
    "wof:placetype":"locality"
},
  "geometry": {"coordinates":[47.3577,55.68213000000001],"type":"Point"}
}