{
  "type": "Feature",
  "properties": {
    "gn:admin1_code":"11",
    "gn:asciiname":"Ranzhurovo",
    "gn:country_code":"RU",
    "gn:dem":464,
    "gn:feature_class":"P",
    "gn:feature_code":"PPL",
    "gn:name":"Ranzhurovo",
    "gn:population":0,
    "gn:timezone":"Asia/Irkutsk",
    "iso:country":"RU",
    "name:eng_x_preferred":[
        "Ranzhurovo"
    ],
    "name:nor_x_preferred":[
        "Ranzjurovo"
    ],
    "name:rus_x_preferred":[
        "\u0420\u0430\u043d\u0436\u0443\u0440\u043e\u0432\u043e"
    ],
    "name:und_x_variant":[
        "\u0420\u0430\u043d\u0436\u0443\u0440\u043e\u0432\u043e",
        "Ranzhurovo"
    ],
    "wof:name":"Ranzhurovo",
    "wof:placetype":"locality"
},
  "geometry": {"coordinates":[106.41861000000002,52.17417],"type":"Point"}
}