{
  "type": "Feature",
  "properties": {
    "gn:admin1_code":"56",
    "gn:asciiname":"Natal'ino",
    "gn:country_code":"RU",
    "gn:dem":204,
    "gn:feature_class":"P",
    "gn:feature_code":"PPL",
    "gn:name":"Natal\u2019ino",
    "gn:population":0,
    "gn:timezone":"Europe/Moscow",
    "iso:country":"RU",
    "wof:name":"Natal'ino",
    "wof:placetype":"locality"
},
  "geometry": {"coordinates":[35.08267,52.94337],"type":"Point"}
}