{
  "type": "Feature",
  "properties": {
    "gn:admin1_code":"55",
    "gn:asciiname":"Kutuyevo",
    "gn:country_code":"RU",
    "gn:dem":317,
    "gn:feature_class":"P",
    "gn:feature_code":"PPL",
    "gn:name":"Kutuyevo",
    "gn:population":0,
    "gn:timezone":"Asia/Yekaterinburg",
    "iso:country":"RU",
    "name:rus_x_preferred":[
        "\u041a\u0443\u0442\u0443\u0435\u0432\u043e"
    ],
    "wof:name":"Kutuyevo",
    "wof:placetype":"locality"
},
  "geometry": {"coordinates":[54.85,53.08333],"type":"Point"}
}