{
  "type": "Feature",
  "properties": {
    "gn:admin1_code":"43",
    "gn:asciiname":"Slepukha",
    "gn:country_code":"RU",
    "gn:dem":191,
    "gn:feature_class":"P",
    "gn:feature_code":"PPL",
    "gn:name":"Slepukha",
    "gn:population":0,
    "gn:timezone":"Europe/Moscow",
    "iso:country":"RU",
    "name:eng_x_preferred":[
        "Slepukha"
    ],
    "name:nor_x_preferred":[
        "Slepukha"
    ],
    "name:rus_x_preferred":[
        "\u0421\u043b\u0435\u043f\u0443\u0445\u0430"
    ],
    "name:und_x_variant":[
        "Bol\u2019shaya Slepukha",
        "\u0421\u043b\u0435\u043f\u0443\u0445\u0430",
        "Slepukha"
    ],
    "wof:name":"Slepukha",
    "wof:placetype":"locality"
},
  "geometry": {"coordinates":[38.63578,52.33568],"type":"Point"}
}