{
  "type": "Feature",
  "properties": {
    "gn:admin1_code":"11.0",
    "gn:asciiname":"Kotokel'",
    "gn:country_code":"RU",
    "gn:dem":463,
    "gn:feature_class":"P",
    "gn:feature_code":"PPL",
    "gn:name":"Kotokel\u2019",
    "gn:population":0,
    "gn:timezone":"Asia/Irkutsk",
    "iso:country":"RU",
    "name:rus_x_preferred":[
        "\u041a\u043e\u0442\u043e\u043a\u0435\u043b\u044c"
    ],
    "name:und_x_variant":[
        "Kotokel\u2019"
    ],
    "wof:name":"Kotokel'",
    "wof:placetype":"locality"
},
  "geometry": {"coordinates":[108.0778,52.7617],"type":"Point"}
}