{
  "type": "Feature",
  "properties": {
    "gn:admin1_code":"34",
    "gn:asciiname":"Okunev Nos",
    "gn:country_code":"RU",
    "gn:dem":31,
    "gn:feature_class":"P",
    "gn:feature_code":"PPL",
    "gn:name":"Okunev Nos",
    "gn:population":0,
    "gn:timezone":"Europe/Moscow",
    "iso:country":"RU",
    "name:eng_x_preferred":[
        "Okunev Nos"
    ],
    "name:nor_x_preferred":[
        "Okunev Nos"
    ],
    "name:rus_x_preferred":[
        "\u041e\u043a\u0443\u043d\u0435\u0432 \u041d\u043e\u0441"
    ],
    "wof:name":"Okunev Nos",
    "wof:placetype":"locality"
},
  "geometry": {"coordinates":[52.56255,66.25761],"type":"Point"}
}