{
  "type": "Feature",
  "properties": {
    "gn:admin1_code":"30",
    "gn:asciiname":"Yudoma-Krestovskaya",
    "gn:country_code":"RU",
    "gn:dem":534,
    "gn:feature_class":"P",
    "gn:feature_code":"PPL",
    "gn:name":"Yudoma-Krestovskaya",
    "gn:population":0,
    "gn:timezone":"Asia/Vladivostok",
    "iso:country":"RU",
    "wof:name":"Yudoma-Krestovskaya",
    "wof:placetype":"locality"
},
  "geometry": {"coordinates":[139.80651,60.08535],"type":"Point"}
}