{
  "type": "Feature",
  "properties": {
    "gn:admin1_code":"38",
    "gn:asciiname":"Udobno-Grushka",
    "gn:country_code":"RU",
    "gn:dem":677,
    "gn:feature_class":"P",
    "gn:feature_code":"PPL",
    "gn:name":"Udobno-Grushka",
    "gn:population":0,
    "gn:timezone":"Europe/Moscow",
    "iso:country":"RU",
    "name:rus_x_preferred":[
        "\u0423\u0434\u043e\u0431\u043d\u043e-\u0413\u0440\u0443\u0448\u043a\u0430"
    ],
    "wof:name":"Udobno-Grushka",
    "wof:placetype":"locality"
},
  "geometry": {"coordinates":[41.6577,44.3371],"type":"Point"}
}