{
  "type": "Feature",
  "properties": {
    "gn:admin1_code":"29",
    "gn:asciiname":"Anan'ina",
    "gn:country_code":"RU",
    "gn:dem":269,
    "gn:feature_class":"P",
    "gn:feature_code":"PPL",
    "gn:name":"Anan\u2019ina",
    "gn:population":0,
    "gn:timezone":"Asia/Novokuznetsk",
    "iso:country":"RU",
    "name:eng_x_preferred":[
        "Anan'ina"
    ],
    "name:nor_x_preferred":[
        "Ananina"
    ],
    "name:rus_x_preferred":[
        "\u0410\u043d\u0430\u043d\u044c\u0438\u043d\u0430"
    ],
    "name:und_x_variant":[
        "\u0410\u043d\u0430\u043d\u044c\u0438\u043d\u0430",
        "Anan\u2019ina",
        "Anan\u2019ino"
    ],
    "wof:name":"Anan'ina",
    "wof:placetype":"locality"
},
  "geometry": {"coordinates":[86.86060000000001,53.5772],"type":"Point"}
}