{
  "type": "Feature",
  "properties": {
    "gn:admin1_code":"90",
    "gn:asciiname":"Rybinka",
    "gn:country_code":"RU",
    "gn:dem":239,
    "gn:feature_class":"P",
    "gn:feature_code":"PPL",
    "gn:name":"Rybinka",
    "gn:population":0,
    "gn:timezone":"Asia/Yekaterinburg",
    "iso:country":"RU",
    "name:rus_x_preferred":[
        "\u0420\u044b\u0431\u0438\u043d\u043a\u0430"
    ],
    "name:und_x_variant":[
        "\u0420\u044b\u0431\u0438\u043d\u043a\u0430"
    ],
    "wof:name":"Rybinka",
    "wof:placetype":"locality"
},
  "geometry": {"coordinates":[56.3181,57.4445],"type":"Point"}
}