{
  "type": "Feature",
  "properties": {
    "gn:admin1_code":"77",
    "gn:asciiname":"Shchemelinino",
    "gn:country_code":"RU",
    "gn:dem":166,
    "gn:feature_class":"P",
    "gn:feature_code":"PPL",
    "gn:name":"Shchemelinino",
    "gn:population":0,
    "gn:timezone":"Europe/Moscow",
    "iso:country":"RU",
    "name:rus_x_preferred":[
        "\u0429\u0435\u043c\u0435\u043b\u0438\u043d\u0438\u043d\u043e"
    ],
    "name:und_x_variant":[
        "\u0429\u0435\u043c\u0435\u043b\u0438\u043d\u0438\u043d\u043e"
    ],
    "wof:name":"Shchemelinino",
    "wof:placetype":"locality"
},
  "geometry": {"coordinates":[34.84024,56.82786],"type":"Point"}
}