{
  "type": "Feature",
  "properties": {
    "gn:country":"RU",
    "gn:fcode":"PPL",
    "gn:pop":0,
    "iso:country":"RU",
    "name:rus_x_preferred":[
        "\u041f\u0440\u0438\u043e\u0437\u0435\u0440\u044c\u0435"
    ],
    "name:unk_x_variant":[
        "Ostolopovo"
    ],
    "qs:name":"Priozer'ye",
    "qs:name_adm0":"Russia",
    "qs:name_adm1":"Vologda Oblast",
    "qs:photos_9r":0,
    "qs:photos_sr":0,
    "qs:placetype":"Town",
    "qs:pop_sr":"0",
    "wof:name":"Priozer'ye",
    "wof:placetype":"locality",
    "wof:population":0
},
  "geometry": {"coordinates":[38.30711,59.91148],"type":"Point"}
}