{
  "type": "Feature",
  "properties": {
    "gn:admin1_code":"13.0",
    "gn:asciiname":"Azyam",
    "gn:country_code":"RU",
    "gn:dem":445,
    "gn:feature_class":"P",
    "gn:feature_code":"PPL",
    "gn:name":"Azyam",
    "gn:population":0,
    "gn:timezone":"Asia/Yekaterinburg",
    "iso:country":"RU",
    "name:rus_x_preferred":[
        "\u0410\u0437\u044f\u043c"
    ],
    "wof:name":"Azyam",
    "wof:placetype":"locality"
},
  "geometry": {"coordinates":[59.4745,55.6934],"type":"Point"}
}