{
  "type": "Feature",
  "properties": {
    "gn:admin1_code":"60.0",
    "gn:asciiname":"Balakhi",
    "gn:country_code":"RU",
    "gn:dem":136,
    "gn:feature_class":"P",
    "gn:feature_code":"PPL",
    "gn:name":"Balakhi",
    "gn:population":0,
    "gn:timezone":"Europe/Moscow",
    "iso:country":"RU",
    "name:nor_x_preferred":[
        "Belokhi"
    ],
    "name:rus_x_preferred":[
        "\u0411a\u043ba\u0445\u0438"
    ],
    "name:und_x_variant":[
        "Balakhi"
    ],
    "wof:name":"Balakhi",
    "wof:placetype":"locality"
},
  "geometry": {"coordinates":[28.7035,56.5737],"type":"Point"}
}