{
  "type": "Feature",
  "properties": {
    "gn:admin1_code":"85",
    "gn:asciiname":"Tel'tevo",
    "gn:country_code":"RU",
    "gn:dem":129,
    "gn:feature_class":"P",
    "gn:feature_code":"PPL",
    "gn:name":"Tel\u2019tevo",
    "gn:population":0,
    "gn:timezone":"Europe/Moscow",
    "iso:country":"RU",
    "name:rus_x_preferred":[
        "\u0422\u0435\u043b\u044c\u0442\u0435\u0432\u043e"
    ],
    "name:und_x_variant":[
        "Tel\u2019tevo",
        "\u0422\u0435\u043b\u044c\u0442\u0435\u0432\u043e"
    ],
    "wof:name":"Tel'tevo",
    "wof:placetype":"locality"
},
  "geometry": {"coordinates":[46.0966,60.7343],"type":"Point"}
}