{
  "type": "Feature",
  "properties": {
    "gn:admin1_code":"4",
    "gn:asciiname":"Trusovo",
    "gn:country_code":"RU",
    "gn:dem":217,
    "gn:feature_class":"P",
    "gn:feature_code":"PPL",
    "gn:name":"Trusovo",
    "gn:population":0,
    "gn:timezone":"Asia/Barnaul",
    "iso:country":"RU",
    "name:che_x_preferred":[
        "\u0422\u0440\u0443\u0441\u043e\u0432\u043e"
    ],
    "name:eng_x_preferred":[
        "Trusovo"
    ],
    "name:nor_x_preferred":[
        "Trusovo"
    ],
    "name:rus_x_preferred":[
        "\u0422\u0440\u0443\u0441\u043e\u0432\u043e"
    ],
    "name:tgk_x_preferred":[
        "\u0422\u0440\u0443\u0441\u043e\u0432\u043e"
    ],
    "name:und_x_variant":[
        "Trusovskoye",
        "Trusova"
    ],
    "wof:name":"Trusovo",
    "wof:placetype":"locality"
},
  "geometry": {"coordinates":[82.48617,51.70969],"type":"Point"}
}