{
  "type": "Feature",
  "properties": {
    "gn:admin1_code":"33",
    "gn:asciiname":"Tolkuyevskaya",
    "gn:country_code":"RU",
    "gn:dem":152,
    "gn:feature_class":"P",
    "gn:feature_code":"PPL",
    "gn:name":"Tolkuyevskaya",
    "gn:population":0,
    "gn:timezone":"Europe/Kirov",
    "iso:country":"RU",
    "wof:name":"Tolkuyevskaya",
    "wof:placetype":"locality"
},
  "geometry": {"coordinates":[51.05,57.71666999999999],"type":"Point"}
}