{
  "type": "Feature",
  "properties": {
    "gn:admin1_code":"4",
    "gn:asciiname":"Ovtsevod",
    "gn:country_code":"RU",
    "gn:dem":157,
    "gn:feature_class":"P",
    "gn:feature_code":"PPL",
    "gn:name":"Ovtsevod",
    "gn:population":0,
    "gn:timezone":"Asia/Barnaul",
    "iso:country":"RU",
    "name:rus_x_preferred":[
        "\u041e\u0432\u0446\u0435\u0432\u043e\u0434"
    ],
    "wof:name":"Ovtsevod",
    "wof:placetype":"locality"
},
  "geometry": {"coordinates":[80.16667,52.56667],"type":"Point"}
}