{
  "type": "Feature",
  "properties": {
    "gn:admin1_code":"88",
    "gn:asciiname":"Yefimovo",
    "gn:country_code":"RU",
    "gn:dem":125,
    "gn:feature_class":"P",
    "gn:feature_code":"PPL",
    "gn:name":"Yefimovo",
    "gn:population":0,
    "gn:timezone":"Europe/Moscow",
    "iso:country":"RU",
    "name:rus_x_preferred":[
        "\u0415\u0444\u0438\u043c\u043e\u0432\u043e"
    ],
    "wof:name":"Yefimovo",
    "wof:placetype":"locality"
},
  "geometry": {"coordinates":[39.32611,57.86419],"type":"Point"}
}