{
  "type": "Feature",
  "properties": {
    "gn:admin1_code":"5.0",
    "gn:asciiname":"Polevoye",
    "gn:country_code":"RU",
    "gn:dem":153,
    "gn:feature_class":"P",
    "gn:feature_code":"PPL",
    "gn:name":"Polevoye",
    "gn:population":0,
    "gn:timezone":"Asia/Yakutsk",
    "iso:country":"RU",
    "wof:name":"Polevoye",
    "wof:placetype":"locality"
},
  "geometry": {"coordinates":[128.02829,50.66595],"type":"Point"}
}