{
  "type": "Feature",
  "properties": {
    "gn:admin1_code":"8",
    "gn:asciiname":"Isyanovo",
    "gn:country_code":"RU",
    "gn:dem":552,
    "gn:feature_class":"P",
    "gn:feature_code":"PPL",
    "gn:name":"Isyanovo",
    "gn:population":0,
    "gn:timezone":"Asia/Yekaterinburg",
    "iso:country":"RU",
    "name:eng_x_preferred":[
        "Isyanovo"
    ],
    "name:nor_x_preferred":[
        "Isianovo"
    ],
    "name:rus_x_preferred":[
        "\u0418\u0441\u044f\u043d\u043e\u0432\u043e"
    ],
    "name:und_x_variant":[
        "Isyanova",
        "\u0418\u0441\u044f\u043d\u043e\u0432\u043e",
        "Isyanovo"
    ],
    "wof:name":"Isyanovo",
    "wof:placetype":"locality"
},
  "geometry": {"coordinates":[58.24611,52.81916999999999],"type":"Point"}
}