{
  "type": "Feature",
  "properties": {
    "gn:admin1_code":"83.0",
    "gn:asciiname":"Borshchevnya",
    "gn:country_code":"RU",
    "gn:dem":125,
    "gn:feature_class":"P",
    "gn:feature_code":"PPL",
    "gn:name":"Borshchevnya",
    "gn:population":0,
    "gn:timezone":"Europe/Moscow",
    "iso:country":"RU",
    "name:rus_x_preferred":[
        "\u0411\u043e\u0440\u0449\u0435\u0432\u043d\u044f"
    ],
    "name:und_x_variant":[
        "\u0411\u043e\u0440\u0449\u0435\u0432\u043d\u044f"
    ],
    "wof:name":"Borshchevnya",
    "wof:placetype":"locality"
},
  "geometry": {"coordinates":[39.45,55.91667],"type":"Point"}
}