{
  "type": "Feature",
  "properties": {
    "gn:admin1_code":"47",
    "gn:asciiname":"Novyye Rameshki",
    "gn:country_code":"RU",
    "gn:dem":230,
    "gn:feature_class":"P",
    "gn:feature_code":"PPL",
    "gn:name":"Novyye Rameshki",
    "gn:population":0,
    "gn:timezone":"Europe/Moscow",
    "iso:country":"RU",
    "name:rus_x_preferred":[
        "\u041d\u043e\u0432\u044b\u0435 \u0420\u0430\u043c\u0435\u0448\u043a\u0438"
    ],
    "name:und_x_variant":[
        "\u041d\u043e\u0432\u044b\u0435 \u0420\u0430\u043c\u0435\u0448\u043a\u0438"
    ],
    "wof:name":"Novyye Rameshki",
    "wof:placetype":"locality"
},
  "geometry": {"coordinates":[35.27667,55.92417],"type":"Point"}
}