{
  "type": "Feature",
  "properties": {
    "gn:admin1_code":"42",
    "gn:asciiname":"Zales'ye",
    "gn:country_code":"RU",
    "gn:dem":56,
    "gn:feature_class":"P",
    "gn:feature_code":"PPL",
    "gn:name":"Zales\u2019ye",
    "gn:population":0,
    "gn:timezone":"Europe/Moscow",
    "iso:country":"RU",
    "wof:name":"Zales'ye",
    "wof:placetype":"locality"
},
  "geometry": {"coordinates":[32.05869000000001,59.82109000000001],"type":"Point"}
}