{
  "type": "Feature",
  "properties": {
    "gn:admin1_code":"91",
    "gn:asciiname":"Stepanovka",
    "gn:country_code":"RU",
    "gn:dem":233,
    "gn:feature_class":"P",
    "gn:feature_code":"PPL",
    "gn:name":"Stepanovka",
    "gn:population":0,
    "gn:timezone":"Asia/Krasnoyarsk",
    "iso:country":"RU",
    "name:rus_x_preferred":[
        "\u0421\u0442\u0435\u043f\u0430\u043d\u043e\u0432\u043a\u0430"
    ],
    "wof:name":"Stepanovka",
    "wof:placetype":"locality"
},
  "geometry": {"coordinates":[90.1245,56.2831],"type":"Point"}
}