{
  "type": "Feature",
  "properties": {
    "gn:admin1_code":"28.0",
    "gn:asciiname":"Chelmozero",
    "gn:country_code":"RU",
    "gn:dem":172,
    "gn:feature_class":"P",
    "gn:feature_code":"PPL",
    "gn:name":"Chelmozero",
    "gn:population":0,
    "gn:timezone":"Europe/Moscow",
    "iso:country":"RU",
    "name:fin_x_preferred":[
        "Tsolma"
    ],
    "name:rus_x_preferred":[
        "\u0427\u0435\u043b\u043c\u043e\u0437\u0435\u0440\u043e"
    ],
    "name:und_x_variant":[
        "\u0427\u0435\u043b\u043c\u043e\u0437\u0435\u0440\u043e"
    ],
    "wof:name":"Chelmozero",
    "wof:placetype":"locality"
},
  "geometry": {"coordinates":[31.81606,64.26591999999999],"type":"Point"}
}