{
  "type": "Feature",
  "properties": {
    "gn:admin1_code":"93",
    "gn:asciiname":"Chuprovo",
    "gn:country_code":"RU",
    "gn:dem":652,
    "gn:feature_class":"P",
    "gn:feature_code":"PPL",
    "gn:name":"Chuprovo",
    "gn:population":0,
    "gn:timezone":"Asia/Chita",
    "iso:country":"RU",
    "name:eng_x_preferred":[
        "Chuprovo"
    ],
    "name:nor_x_preferred":[
        "Tsjuprovo"
    ],
    "name:rus_x_preferred":[
        "\u0427\u0443\u043f\u0440\u043e\u0432\u043e"
    ],
    "wof:name":"Chuprovo",
    "wof:placetype":"locality"
},
  "geometry": {"coordinates":[118.99724999999999,50.98557],"type":"Point"}
}