{
  "type": "Feature",
  "properties": {
    "gn:admin1_code":"52",
    "gn:asciiname":"Karnaukhovo",
    "gn:country_code":"RU",
    "gn:dem":61,
    "gn:feature_class":"P",
    "gn:feature_code":"PPL",
    "gn:name":"Karnaukhovo",
    "gn:population":0,
    "gn:timezone":"Europe/Moscow",
    "iso:country":"RU",
    "name:rus_x_preferred":[
        "\u041a\u0430\u0440\u043d\u0430\u0443\u0445\u043e\u0432\u043e"
    ],
    "wof:name":"Karnaukhovo",
    "wof:placetype":"locality"
},
  "geometry": {"coordinates":[32.69467,58.02763],"type":"Point"}
}