{
  "type": "Feature",
  "properties": {
    "gn:admin1_code":"25.0",
    "gn:asciiname":"Durakovo",
    "gn:country_code":"RU",
    "gn:dem":185,
    "gn:feature_class":"P",
    "gn:feature_code":"PPL",
    "gn:name":"Durakovo",
    "gn:population":0,
    "gn:timezone":"Europe/Moscow",
    "iso:country":"RU",
    "name:che_x_preferred":[
        "\u0414\u0443\u0440\u0430\u043a\u043e\u0432\u043e"
    ],
    "wof:name":"Durakovo",
    "wof:placetype":"locality"
},
  "geometry": {"coordinates":[36.68692,54.96309],"type":"Point"}
}