{
  "type": "Feature",
  "properties": {
    "gn:admin1_code":"33",
    "gn:asciiname":"Zauzly",
    "gn:country_code":"RU",
    "gn:dem":106,
    "gn:feature_class":"P",
    "gn:feature_code":"PPL",
    "gn:name":"Zauzly",
    "gn:population":0,
    "gn:timezone":"Europe/Kirov",
    "iso:country":"RU",
    "name:rus_x_preferred":[
        "\u0417\u0430\u0443\u0437\u043b\u044b"
    ],
    "wof:name":"Zauzly",
    "wof:placetype":"locality"
},
  "geometry": {"coordinates":[48.54168,57.55205],"type":"Point"}
}