{
  "type": "Feature",
  "properties": {
    "gn:admin1_code":"40",
    "gn:asciiname":"Yershovka",
    "gn:country_code":"RU",
    "gn:dem":153,
    "gn:feature_class":"P",
    "gn:feature_code":"PPL",
    "gn:name":"Yershovka",
    "gn:population":0,
    "gn:timezone":"Asia/Yekaterinburg",
    "iso:country":"RU",
    "name:che_x_preferred":[
        "\u0415\u0440\u0448\u043e\u0432\u043a\u0430"
    ],
    "name:rus_x_preferred":[
        "\u0415\u0440\u0448\u043e\u0432\u043a\u0430"
    ],
    "wof:name":"Yershovka",
    "wof:placetype":"locality"
},
  "geometry": {"coordinates":[65.48779,54.7206],"type":"Point"}
}