{
  "type": "Feature",
  "properties": {
    "gn:admin1_code":"73",
    "gn:asciiname":"Timerkul'",
    "gn:country_code":"RU",
    "gn:dem":142,
    "gn:feature_class":"P",
    "gn:feature_code":"PPL",
    "gn:name":"Timerkul\u2019",
    "gn:population":0,
    "gn:timezone":"Europe/Moscow",
    "iso:country":"RU",
    "name:rus_x_preferred":[
        "\u0422\u0438\u043c\u0435\u0440\u043a\u0443\u043b\u044c"
    ],
    "name:und_x_variant":[
        "Timerkul\u2019",
        "\u0422\u0438\u043c\u0435\u0440\u043a\u0443\u043b\u044c"
    ],
    "wof:name":"Timerkul'",
    "wof:placetype":"locality"
},
  "geometry": {"coordinates":[53.9335,55.6648],"type":"Point"}
}