{
  "type": "Feature",
  "properties": {
    "gn:admin1_code":"41.0",
    "gn:asciiname":"Demino",
    "gn:country_code":"RU",
    "gn:dem":160,
    "gn:feature_class":"P",
    "gn:feature_code":"PPL",
    "gn:name":"Demino",
    "gn:population":0,
    "gn:timezone":"Europe/Moscow",
    "iso:country":"RU",
    "name:che_x_preferred":[
        "\u0414\u0435\u043c\u0438\u043d\u043e"
    ],
    "name:koi_x_preferred":[
        "\u0414\u0451\u043c\u0430"
    ],
    "name:rus_x_preferred":[
        "\u0414\u0435\u043c\u0438\u043d\u043e"
    ],
    "wof:name":"Demino",
    "wof:placetype":"locality"
},
  "geometry": {"coordinates":[36.60556,51.58528],"type":"Point"}
}