{
  "type": "Feature",
  "properties": {
    "gn:admin1_code":"20",
    "gn:asciiname":"Bol'shoy Karluk",
    "gn:country_code":"RU",
    "gn:dem":469,
    "gn:feature_class":"P",
    "gn:feature_code":"PPL",
    "gn:name":"Bol\u2019shoy Karluk",
    "gn:population":0,
    "gn:timezone":"Asia/Irkutsk",
    "iso:country":"RU",
    "name:rus_x_preferred":[
        "\u0411\u043e\u043b\u044c\u0448\u043e\u0439 \u041a\u0430\u0440\u043b\u0443\u043a"
    ],
    "name:und_x_variant":[
        "Bol\u2019shoy Karluk"
    ],
    "wof:name":"Bol'shoy Karluk",
    "wof:placetype":"locality"
},
  "geometry": {"coordinates":[102.4134,53.4856],"type":"Point"}
}