{
  "type": "Feature",
  "properties": {
    "gn:admin1_code":"90",
    "gn:asciiname":"Shuvalova",
    "gn:country_code":"RU",
    "gn:dem":156,
    "gn:feature_class":"P",
    "gn:feature_code":"PPL",
    "gn:name":"Shuvalova",
    "gn:population":0,
    "gn:timezone":"Asia/Yekaterinburg",
    "iso:country":"RU",
    "name:rus_x_preferred":[
        "\u0428\u0443\u0432\u0430\u043b\u043e\u0432\u0430"
    ],
    "name:und_x_variant":[
        "\u0428\u0443\u0432\u0430\u043b\u043e\u0432\u0430"
    ],
    "wof:name":"Shuvalova",
    "wof:placetype":"locality"
},
  "geometry": {"coordinates":[55.231,58.1258],"type":"Point"}
}