{
  "type": "Feature",
  "properties": {
    "gn:admin1_code":"88",
    "gn:asciiname":"Spirdovo",
    "gn:country_code":"RU",
    "gn:dem":131,
    "gn:feature_class":"P",
    "gn:feature_code":"PPL",
    "gn:name":"Spirdovo",
    "gn:population":0,
    "gn:timezone":"Europe/Moscow",
    "iso:country":"RU",
    "name:rus_x_preferred":[
        "\u0421\u043f\u0438\u0440\u0434\u043e\u0432\u043e"
    ],
    "name:und_x_variant":[
        "\u0421\u043f\u0438\u0440\u0434\u043e\u0432\u043e"
    ],
    "wof:name":"Spirdovo",
    "wof:placetype":"locality"
},
  "geometry": {"coordinates":[38.1423,57.8435],"type":"Point"}
}