{
  "type": "Feature",
  "properties": {
    "gn:admin1_code":"55.0",
    "gn:asciiname":"Bashirovo",
    "gn:country_code":"RU",
    "gn:dem":145,
    "gn:feature_class":"P",
    "gn:feature_code":"PPL",
    "gn:name":"Bashirovo",
    "gn:population":0,
    "gn:timezone":"Asia/Yekaterinburg",
    "iso:country":"RU",
    "name:eng_x_preferred":[
        "Bashirovo"
    ],
    "name:nor_x_preferred":[
        "Basjirovo"
    ],
    "name:rus_x_preferred":[
        "\u0411\u0430\u0448\u0438\u0440\u043e\u0432\u043e"
    ],
    "name:und_x_variant":[
        "\u0411\u0430\u0448\u0438\u0440\u043e\u0432\u043e",
        "Bashirovo"
    ],
    "wof:name":"Bashirovo",
    "wof:placetype":"locality"
},
  "geometry": {"coordinates":[52.828,52.0806],"type":"Point"}
}