{
  "type": "Feature",
  "properties": {
    "gn:admin1_code":"34",
    "gn:asciiname":"Kanin",
    "gn:cc2":"RU",
    "gn:country_code":"RU",
    "gn:dem":43,
    "gn:feature_class":"P",
    "gn:feature_code":"PPL",
    "gn:name":"Kanin",
    "gn:population":0,
    "gn:timezone":"Europe/Moscow",
    "iso:country":"RU",
    "name:ces_x_preferred":[
        "Kanin"
    ],
    "name:deu_x_preferred":[
        "Kanin"
    ],
    "name:eus_x_preferred":[
        "Kanin"
    ],
    "name:fra_x_preferred":[
        "Kanin"
    ],
    "name:msa_x_preferred":[
        "Kanin"
    ],
    "name:nld_x_preferred":[
        "Kanin"
    ],
    "name:pol_x_preferred":[
        "Kanin"
    ],
    "name:rus_x_preferred":[
        "\u041a\u0430\u043d\u0438\u043d"
    ],
    "name:swe_x_preferred":[
        "Kanin"
    ],
    "name:tgl_x_preferred":[
        "Kanin"
    ],
    "name:und_x_variant":[
        "Kanin Nos",
        "Kanin",
        "\u041a\u0430\u043d\u0438\u043d"
    ],
    "wof:name":"Kanin",
    "wof:placetype":"locality"
},
  "geometry": {"coordinates":[57.16667,65.45],"type":"Point"}
}