{
  "type": "Feature",
  "properties": {
    "gn:admin1_code":"69",
    "gn:asciiname":"Nakhimovskoye",
    "gn:cc2":"RU",
    "gn:country_code":"RU",
    "gn:dem":203,
    "gn:feature_class":"P",
    "gn:feature_code":"PPL",
    "gn:name":"Nakhimovskoye",
    "gn:population":0,
    "gn:timezone":"Europe/Moscow",
    "iso:country":"RU",
    "name:eng_x_preferred":[
        "Nakhimovskoye"
    ],
    "name:nor_x_preferred":[
        "Nakhimovskoje"
    ],
    "name:rus_x_preferred":[
        "\u041d\u0430\u0445\u0438\u043c\u043e\u0432\u0441\u043a\u043e\u0435"
    ],
    "name:und_x_variant":[
        "Voloch\u00ebk",
        "Nakhimovo",
        "\u041d\u0430\u0445\u0438\u043c\u043e\u0432\u0441\u043a\u043e\u0435",
        "Nakhimovskoye"
    ],
    "wof:name":"Nakhimovskoye",
    "wof:placetype":"locality"
},
  "geometry": {"coordinates":[33.7475,55.52139],"type":"Point"}
}