{
  "type": "Feature",
  "properties": {
    "gn:admin1_code":"38.0",
    "gn:asciiname":"Bulgakov",
    "gn:country_code":"RU",
    "gn:dem":115,
    "gn:feature_class":"P",
    "gn:feature_code":"PPL",
    "gn:name":"Bulgakov",
    "gn:population":0,
    "gn:timezone":"Europe/Moscow",
    "iso:country":"RU",
    "name:rus_x_preferred":[
        "\u0411\u0443\u043b\u0433\u0430\u043a\u043e\u0432"
    ],
    "wof:name":"Bulgakov",
    "wof:placetype":"locality"
},
  "geometry": {"coordinates":[40.50694,45.18444],"type":"Point"}
}