{
  "type": "Feature",
  "properties": {
    "gn:admin1_code":"8",
    "gn:asciiname":"Tallykul'",
    "gn:country_code":"RU",
    "gn:dem":122,
    "gn:feature_class":"P",
    "gn:feature_code":"PPL",
    "gn:name":"Tallykul\u2019",
    "gn:population":0,
    "gn:timezone":"Asia/Yekaterinburg",
    "iso:country":"RU",
    "name:rus_x_preferred":[
        "\u0422\u0430\u043b\u043b\u044b\u043a\u0443\u043b\u044c"
    ],
    "name:und_x_variant":[
        "Tallykul\u2019"
    ],
    "wof:name":"Tallykul'",
    "wof:placetype":"locality"
},
  "geometry": {"coordinates":[53.8034,54.8812],"type":"Point"}
}