{
  "type": "Feature",
  "properties": {
    "gn:admin1_code":"54",
    "gn:asciiname":"Ostanovochnyy Punkt Dve Tysyachi Pyat'sot Davdtsat' Devyatyy Kilometr",
    "gn:country_code":"RU",
    "gn:dem":127,
    "gn:feature_class":"P",
    "gn:feature_code":"PPL",
    "gn:name":"Ostanovochnyy Punkt Dve Tysyachi Pyat\u2019sot Davdtsat\u2019 Devyatyy Kilometr",
    "gn:population":0,
    "gn:timezone":"Asia/Omsk",
    "iso:country":"RU",
    "name:rus_x_preferred":[
        "\u041e\u0441\u0442\u0430\u043d\u043e\u0432\u043e\u0447\u043d\u044b\u0439 \u041f\u0443\u043d\u043a\u0442 \u0414\u0432\u0435 \u0422\u044b\u0441\u044f\u0447\u0438 \u041f\u044f\u0442\u044c\u0441\u043e\u0442 \u0414\u0432\u0430\u0434\u0446\u0430\u0442\u044c \u0414\u0435\u0432\u044f\u0442\u044b\u0439 \u041a\u0438\u043b\u043e\u043c\u0435\u0442\u0440"
    ],
    "name:und_x_variant":[
        "Ostanovochnyy Punkt Dve Tysyachi Pyat\u2019sot Davdtsat\u2019 Devyatyy Kilometr"
    ],
    "wof:name":"Ostanovochnyy Punkt Dve Tysyachi Pyat'sot Davdtsat' Devyatyy Kilometr",
    "wof:placetype":"locality"
},
  "geometry": {"coordinates":[70.90560000000001,55.7225],"type":"Point"}
}