{
  "type": "Feature",
  "properties": {
    "gn:admin1_code":"85",
    "gn:asciiname":"Yermolovo",
    "gn:country_code":"RU",
    "gn:dem":127,
    "gn:feature_class":"P",
    "gn:feature_code":"PPL",
    "gn:name":"Yermolovo",
    "gn:population":0,
    "gn:timezone":"Europe/Moscow",
    "iso:country":"RU",
    "name:rus_x_preferred":[
        "\u0415\u0440\u043c\u043e\u043b\u043e\u0432\u043e"
    ],
    "wof:name":"Yermolovo",
    "wof:placetype":"locality"
},
  "geometry": {"coordinates":[39.77078,59.27777],"type":"Point"}
}