{
  "type": "Feature",
  "properties": {
    "gn:admin1_code":"16",
    "gn:asciiname":"Pinery",
    "gn:country_code":"RU",
    "gn:dem":173,
    "gn:feature_class":"P",
    "gn:feature_code":"PPL",
    "gn:name":"Pinery",
    "gn:population":0,
    "gn:timezone":"Europe/Moscow",
    "iso:country":"RU",
    "name:rus_x_preferred":[
        "\u041f\u0438\u043d\u0435\u0440\u044b"
    ],
    "name:und_x_variant":[
        "Piner",
        "Pinery"
    ],
    "wof:name":"Pinery",
    "wof:placetype":"locality"
},
  "geometry": {"coordinates":[46.66996,55.49997],"type":"Point"}
}