{
  "type": "Feature",
  "properties": {
    "gn:admin1_code":"80",
    "gn:asciiname":"Stepanenki",
    "gn:country_code":"RU",
    "gn:dem":252,
    "gn:feature_class":"P",
    "gn:feature_code":"PPL",
    "gn:name":"Stepanenki",
    "gn:population":0,
    "gn:timezone":"Europe/Samara",
    "iso:country":"RU",
    "name:eng_x_preferred":[
        "Stepanenki"
    ],
    "name:nor_x_preferred":[
        "Stepanenki"
    ],
    "name:rus_x_preferred":[
        "\u0421\u0442\u0435\u043f\u0430\u043d\u0435\u043d\u043a\u0438"
    ],
    "wof:name":"Stepanenki",
    "wof:placetype":"locality"
},
  "geometry": {"coordinates":[53.5604,58.2308],"type":"Point"}
}