{
  "type": "Feature",
  "properties": {
    "gn:admin1_code":"77",
    "gn:asciiname":"Prosveshcheniye",
    "gn:country_code":"RU",
    "gn:dem":186,
    "gn:feature_class":"P",
    "gn:feature_code":"PPL",
    "gn:name":"Prosveshcheniye",
    "gn:population":0,
    "gn:timezone":"Europe/Moscow",
    "iso:country":"RU",
    "name:rus_x_preferred":[
        "\u041f\u0440\u043e\u0441\u0432\u0435\u0449\u0435\u043d\u0438\u0435"
    ],
    "name:tur_x_preferred":[
        "Prosve\u015f\u00e7eniye"
    ],
    "name:und_x_variant":[
        "\u041f\u0440\u043e\u0441\u0432\u0435\u0449\u0435\u043d\u0438\u0435"
    ],
    "wof:name":"Prosveshcheniye",
    "wof:placetype":"locality"
},
  "geometry": {"coordinates":[36.3977,57.4906],"type":"Point"}
}