{
  "type": "Feature",
  "properties": {
    "gn:admin1_code":"91",
    "gn:asciiname":"Solomatova",
    "gn:country_code":"RU",
    "gn:dem":327,
    "gn:feature_class":"P",
    "gn:feature_code":"PPL",
    "gn:name":"Solomatova",
    "gn:population":0,
    "gn:timezone":"Asia/Krasnoyarsk",
    "iso:country":"RU",
    "name:rus_x_preferred":[
        "\u0421\u043e\u043b\u043e\u043c\u0430\u0442\u043e\u0432\u0430"
    ],
    "wof:name":"Solomatova",
    "wof:placetype":"locality"
},
  "geometry": {"coordinates":[94.88833,55.63],"type":"Point"}
}