{
  "type": "Feature",
  "properties": {
    "gn:admin1_code":"61.0",
    "gn:asciiname":"Opytnyy",
    "gn:country_code":"RU",
    "gn:dem":106,
    "gn:feature_class":"P",
    "gn:feature_code":"PPL",
    "gn:name":"Opytnyy",
    "gn:population":0,
    "gn:timezone":"Europe/Moscow",
    "iso:country":"RU",
    "name:rus_x_preferred":[
        "Opytn\u2019"
    ],
    "name:rus_x_variant":[
        "\u041e\u043f\u044b\u0442\u043d\u044c",
        "\u041e\u043f\u044b\u0442\u043d\u044b\u0439"
    ],
    "wof:name":"Opytnyy",
    "wof:placetype":"locality"
},
  "geometry": {"coordinates":[39.99243,47.33621],"type":"Point"}
}