{
  "type": "Feature",
  "properties": {
    "gn:admin1_code":"77",
    "gn:asciiname":"Kon'kovo",
    "gn:country_code":"RU",
    "gn:dem":218,
    "gn:feature_class":"P",
    "gn:feature_code":"PPL",
    "gn:name":"Kon\u2019kovo",
    "gn:population":0,
    "gn:timezone":"Europe/Moscow",
    "iso:country":"RU",
    "name:nor_x_preferred":[
        "Konkovo"
    ],
    "name:rus_x_preferred":[
        "\u041a\u043e\u043d\u044c\u043a\u043e\u0432\u043e"
    ],
    "name:und_x_variant":[
        "Kon\u2019kovo"
    ],
    "wof:name":"Kon'kovo",
    "wof:placetype":"locality"
},
  "geometry": {"coordinates":[35.07866,56.17495],"type":"Point"}
}