{
  "type": "Feature",
  "properties": {
    "gn:admin1_code":"32",
    "gn:asciiname":"Kamennyy Mys",
    "gn:country_code":"RU",
    "gn:dem":72,
    "gn:feature_class":"P",
    "gn:feature_code":"PPL",
    "gn:name":"Kamennyy Mys",
    "gn:population":0,
    "gn:timezone":"Asia/Yekaterinburg",
    "iso:country":"RU",
    "name:eng_x_preferred":[
        "Kamennyy Mys"
    ],
    "name:nor_x_preferred":[
        "Kamennyj Mys"
    ],
    "name:rus_x_preferred":[
        "\u041a\u0430\u043c\u0435\u043d\u043d\u044b\u0439 \u041c\u044b\u0441"
    ],
    "wof:name":"Kamennyy Mys",
    "wof:placetype":"locality"
},
  "geometry": {"coordinates":[73.41667,61.16667],"type":"Point"}
}