{
  "type": "Feature",
  "properties": {
    "gn:admin1_code":"88",
    "gn:asciiname":"Varvarinskaya",
    "gn:country_code":"RU",
    "gn:dem":122,
    "gn:feature_class":"P",
    "gn:feature_code":"PPL",
    "gn:name":"Varvarinskaya",
    "gn:population":0,
    "gn:timezone":"Europe/Moscow",
    "iso:country":"RU",
    "name:rus_x_preferred":[
        "\u0412\u0430\u0440\u0432\u0430\u0440\u0438\u043d\u0441\u043a\u0430\u044f"
    ],
    "wof:name":"Varvarinskaya",
    "wof:placetype":"locality"
},
  "geometry": {"coordinates":[38.3545,57.7035],"type":"Point"}
}