{
  "type": "Feature",
  "properties": {
    "gn:admin1_code":"69",
    "gn:asciiname":"Shushkovshchina",
    "gn:country_code":"RU",
    "gn:dem":215,
    "gn:feature_class":"P",
    "gn:feature_code":"PPL",
    "gn:name":"Shushkovshchina",
    "gn:population":0,
    "gn:timezone":"Europe/Moscow",
    "iso:country":"RU",
    "name:rus_x_preferred":[
        "\u0428\u0443\u0448\u043a\u043e\u0432\u0449\u0438\u043d\u0430"
    ],
    "name:und_x_variant":[
        "\u0428\u0443\u0448\u043a\u043e\u0432\u0449\u0438\u043d\u0430"
    ],
    "wof:name":"Shushkovshchina",
    "wof:placetype":"locality"
},
  "geometry": {"coordinates":[31.94881,54.64766],"type":"Point"}
}