{
  "type": "Feature",
  "properties": {
    "gn:admin1_code":"41",
    "gn:asciiname":"Step'",
    "gn:country_code":"RU",
    "gn:dem":187,
    "gn:feature_class":"P",
    "gn:feature_code":"PPL",
    "gn:name":"Step\u2019",
    "gn:population":0,
    "gn:timezone":"Europe/Moscow",
    "iso:country":"RU",
    "name:rus_x_preferred":[
        "\u0421\u0442\u0435\u043f\u044c"
    ],
    "name:und_x_variant":[
        "Step\u2019",
        "\u0421\u0442\u0435\u043f\u044c"
    ],
    "wof:name":"Step'",
    "wof:placetype":"locality"
},
  "geometry": {"coordinates":[36.4331,52.0483],"type":"Point"}
}