{
  "type": "Feature",
  "properties": {
    "gn:admin1_code":"61",
    "gn:asciiname":"Krasnyy Yar",
    "gn:cc2":"RU",
    "gn:country_code":"RU",
    "gn:dem":29,
    "gn:feature_class":"P",
    "gn:feature_code":"PPL",
    "gn:name":"Krasnyy Yar",
    "gn:population":0,
    "gn:timezone":"Europe/Moscow",
    "iso:country":"RU",
    "name:rus_x_preferred":[
        "\u041a\u0440\u0430\u0441\u043d\u044b\u0439 \u042f\u0440"
    ],
    "name:und_x_variant":[
        "Krasny Yar",
        "Krasnyy Yar"
    ],
    "wof:name":"Krasnyy Yar",
    "wof:placetype":"locality"
},
  "geometry": {"coordinates":[41.78028,46.51444],"type":"Point"}
}