{
  "type": "Feature",
  "properties": {
    "gn:admin1_code":"62",
    "gn:asciiname":"Krasnoye",
    "gn:country_code":"RU",
    "gn:dem":105,
    "gn:feature_class":"P",
    "gn:feature_code":"PPL",
    "gn:name":"Krasnoye",
    "gn:population":256,
    "gn:timezone":"Europe/Moscow",
    "iso:country":"RU",
    "name:eng_x_preferred":[
        "Krasnoye"
    ],
    "name:nor_x_preferred":[
        "Krasnoje"
    ],
    "name:rus_x_preferred":[
        "\u041a\u0440\u0430\u0441\u043d\u043e\u0435"
    ],
    "wof:name":"Krasnoye",
    "wof:placetype":"locality",
    "wof:population":256
},
  "geometry": {"coordinates":[40.87722,53.98556],"type":"Point"}
}