{
  "type": "Feature",
  "properties": {
    "gn:admin1_code":"41",
    "gn:asciiname":"Kunach",
    "gn:country_code":"RU",
    "gn:dem":193,
    "gn:feature_class":"P",
    "gn:feature_code":"PPL",
    "gn:name":"Kunach",
    "gn:population":0,
    "gn:timezone":"Europe/Moscow",
    "iso:country":"RU",
    "name:rus_x_preferred":[
        "\u041a\u0443\u043d\u0430\u0447"
    ],
    "name:und_x_variant":[
        "Kulach",
        "Kunach"
    ],
    "wof:name":"Kunach",
    "wof:placetype":"locality"
},
  "geometry": {"coordinates":[36.77901,51.8309],"type":"Point"}
}