{
  "type": "Feature",
  "properties": {
    "gn:admin1_code":"13",
    "gn:asciiname":"Kisegach",
    "gn:country_code":"RU",
    "gn:dem":331,
    "gn:feature_class":"P",
    "gn:feature_code":"PPL",
    "gn:name":"Kisegach",
    "gn:population":0,
    "gn:timezone":"Asia/Yekaterinburg",
    "iso:country":"RU",
    "name:eng_x_preferred":[
        "Kisegach"
    ],
    "name:nor_x_preferred":[
        "Kisegatsj"
    ],
    "name:rus_x_preferred":[
        "\u041a\u0438\u0441\u0435\u0433\u0430\u0447"
    ],
    "wof:name":"Kisegach",
    "wof:placetype":"locality"
},
  "geometry": {"coordinates":[60.2978,54.9826],"type":"Point"}
}