{
  "type": "Feature",
  "properties": {
    "gn:admin1_code":"8",
    "gn:asciiname":"Verkhneivanayevo",
    "gn:country_code":"RU",
    "gn:dem":113,
    "gn:feature_class":"P",
    "gn:feature_code":"PPL",
    "gn:name":"Verkhneivanayevo",
    "gn:population":0,
    "gn:timezone":"Asia/Yekaterinburg",
    "iso:country":"RU",
    "name:aze_x_preferred":[
        "A\u015fa\u011f\u0131 \u0130vanay"
    ],
    "name:bak_x_preferred":[
        "\u04ae\u0440\u0433\u0435 \u0418\u0432\u0430\u043d\u0430\u0439"
    ],
    "name:che_x_preferred":[
        "\u0412\u0435\u0440\u0445\u043d\u0435\u0438\u0432\u0430\u043d\u0430\u0435\u0432\u043e"
    ],
    "name:eng_x_preferred":[
        "Verkhneivanayevo"
    ],
    "name:hun_x_preferred":[
        "Verhnyeivanajevo"
    ],
    "name:hye_x_preferred":[
        "\u054e\u0565\u0580\u056d\u0576\u0565\u056b\u057e\u0561\u0576\u0561\u0587\u0578"
    ],
    "name:kaz_x_preferred":[
        "\u0416\u043e\u0493\u0430\u0440\u0493\u044b \u0438\u0432\u0430\u043d\u0430"
    ],
    "name:kir_x_preferred":[
        "\u0416\u043e\u0433\u043e\u0440\u043a\u0443 \u0438\u0432\u0430\u043d\u0430"
    ],
    "name:nor_x_preferred":[
        "Verkhneivanajevo"
    ],
    "name:rus_x_preferred":[
        "\u0412\u0435\u0440\u0445\u043d\u0435\u0438\u0432\u0430\u043d\u0430\u0435\u0432\u043e"
    ],
    "name:tat_x_preferred":[
        "\u042e\u0433\u0430\u0440\u044b \u0418\u0432\u0430\u043d\u0430\u0439"
    ],
    "wof:name":"Verkhneivanayevo",
    "wof:placetype":"locality"
},
  "geometry": {"coordinates":[56.01074000000001,55.94381],"type":"Point"}
}