{
  "type": "Feature",
  "properties": {
    "gn:admin1_code":"8",
    "gn:asciiname":"Verkhneivanayevo",
    "gn:country_code":"RU",
    "gn:dem":113,
    "gn:feature_class":"P",
    "gn:feature_code":"PPL",
    "gn:name":"Verkhneivanayevo",
    "gn:population":0,
    "gn:timezone":"Asia/Yekaterinburg",
    "iso:country":"RU",
    "name:eng_x_preferred":[
        "Verkhneivanayevo"
    ],
    "name:nor_x_preferred":[
        "Verkhneivanajevo"
    ],
    "name:rus_x_preferred":[
        "\u0412\u0435\u0440\u0445\u043d\u0435\u0438\u0432\u0430\u043d\u0430\u0435\u0432\u043e"
    ],
    "wof:name":"Verkhneivanayevo",
    "wof:placetype":"locality"
},
  "geometry": {"coordinates":[56.01074000000001,55.94381],"type":"Point"}
}