{
  "type": "Feature",
  "properties": {
    "gn:admin1_code":"86",
    "gn:asciiname":"Makogonovo",
    "gn:country_code":"RU",
    "gn:dem":204,
    "gn:feature_class":"P",
    "gn:feature_code":"PPL",
    "gn:name":"Makogonovo",
    "gn:population":0,
    "gn:timezone":"Europe/Moscow",
    "iso:country":"RU",
    "name:rus_x_preferred":[
        "\u041c\u0430\u043a\u043e\u0433\u043e\u043d\u043e\u0432\u043e"
    ],
    "wof:name":"Makogonovo",
    "wof:placetype":"locality"
},
  "geometry": {"coordinates":[40.82139,50.92889],"type":"Point"}
}