{
  "type": "Feature",
  "properties": {
    "gn:admin1_code":"73",
    "gn:asciiname":"Kakre-Yelga",
    "gn:country_code":"RU",
    "gn:dem":168,
    "gn:feature_class":"P",
    "gn:feature_code":"PPL",
    "gn:name":"Kakre-Yelga",
    "gn:population":0,
    "gn:timezone":"Europe/Moscow",
    "iso:country":"RU",
    "name:eng_x_preferred":[
        "Kakre Yelga"
    ],
    "name:nor_x_preferred":[
        "Kakre-Jelga"
    ],
    "name:rus_x_preferred":[
        "\u041a\u0430\u043a\u0440\u0435-\u0415\u043b\u0433\u0430"
    ],
    "name:und_x_variant":[
        "Kakry-Yelga",
        "Kakre-Yelga",
        "\u041a\u0430\u043a\u0440\u0435-\u0415\u043b\u0433\u0430"
    ],
    "wof:name":"Kakre-Yelga",
    "wof:placetype":"locality"
},
  "geometry": {"coordinates":[52.9237,54.9454],"type":"Point"}
}