{
  "type": "Feature",
  "properties": {
    "gn:admin1_code":"71",
    "gn:asciiname":"Klimicheva",
    "gn:country_code":"RU",
    "gn:dem":75,
    "gn:feature_class":"P",
    "gn:feature_code":"PPL",
    "gn:name":"Klimich\u00ebva",
    "gn:population":0,
    "gn:timezone":"Asia/Yekaterinburg",
    "iso:country":"RU",
    "name:rus_x_preferred":[
        "\u041a\u043b\u0438\u043c\u0438\u0447\u0451\u0432\u0430"
    ],
    "name:und_x_variant":[
        "Klimich\u00ebva",
        "\u041a\u043b\u0438\u043c\u0438\u0447\u0451\u0432\u0430"
    ],
    "wof:name":"Klimicheva",
    "wof:placetype":"locality"
},
  "geometry": {"coordinates":[61.93333000000001,59.76667],"type":"Point"}
}