{
  "type": "Feature",
  "properties": {
    "gn:admin1_code":"12.0",
    "gn:admin2_code":"Itum-Kalinskiy Rayon",
    "gn:asciiname":"Butti",
    "gn:country_code":"RU",
    "gn:dem":1810,
    "gn:feature_class":"P",
    "gn:feature_code":"PPL",
    "gn:name":"Butti",
    "gn:population":0,
    "gn:timezone":"Europe/Moscow",
    "iso:country":"RU",
    "name:che_x_preferred":[
        "Buti"
    ],
    "name:che_x_variant":[
        "\u0411\u0443\u0442\u0438"
    ],
    "name:rus_x_preferred":[
        "\u0411\u0443\u0442\u0442\u0438"
    ],
    "wof:name":"Butti",
    "wof:placetype":"locality"
},
  "geometry": {"coordinates":[45.97871,42.6603],"type":"Point"}
}