{
  "type": "Feature",
  "properties": {
    "gn:admin1_code":"69",
    "gn:asciiname":"Pokhodino",
    "gn:country_code":"RU",
    "gn:dem":198,
    "gn:feature_class":"P",
    "gn:feature_code":"PPL",
    "gn:name":"Pokhodino",
    "gn:population":0,
    "gn:timezone":"Europe/Moscow",
    "iso:country":"RU",
    "name:rus_x_preferred":[
        "\u041f\u043e\u0445\u043e\u0434\u0438\u043d\u043e"
    ],
    "name:und_x_variant":[
        "\u041f\u043e\u0445\u043e\u0434\u0438\u043d\u043e"
    ],
    "wof:name":"Pokhodino",
    "wof:placetype":"locality"
},
  "geometry": {"coordinates":[33.62235,55.01984],"type":"Point"}
}