{
  "type": "Feature",
  "properties": {
    "gn:admin1_code":"85.0",
    "gn:asciiname":"Churnevo",
    "gn:cc2":"RU",
    "gn:country_code":"RU",
    "gn:dem":64,
    "gn:feature_class":"P",
    "gn:feature_code":"PPL",
    "gn:name":"Churnevo",
    "gn:population":0,
    "gn:timezone":"Europe/Moscow",
    "iso:country":"RU",
    "name:rus_x_preferred":[
        "\u0427\u0443\u0440\u043d\u0435\u0432\u043e"
    ],
    "name:und_x_variant":[
        "T\u0161urnevo",
        "Churnevo",
        "\u0427\u0443\u0440\u043d\u0435\u0432\u043e"
    ],
    "wof:name":"Churnevo",
    "wof:placetype":"locality"
},
  "geometry": {"coordinates":[36.08333,60.98333],"type":"Point"}
}