{
  "type": "Feature",
  "properties": {
    "gn:admin1_code":"62.0",
    "gn:asciiname":"Adelino",
    "gn:country_code":"RU",
    "gn:dem":132,
    "gn:feature_class":"P",
    "gn:feature_code":"PPL",
    "gn:name":"Adelino",
    "gn:population":0,
    "gn:timezone":"Europe/Moscow",
    "iso:country":"RU",
    "name:nor_x_preferred":[
        "Adelino"
    ],
    "name:rus_x_preferred":[
        "\u0410\u0434\u0435\u043b\u0438\u043d\u043e"
    ],
    "wof:name":"Adelino",
    "wof:placetype":"locality"
},
  "geometry": {"coordinates":[41.28209,54.46985],"type":"Point"}
}