{
  "type": "Feature",
  "properties": {
    "gn:admin1_code":"52.0",
    "gn:asciiname":"Cheremenets",
    "gn:country_code":"RU",
    "gn:dem":56,
    "gn:feature_class":"P",
    "gn:feature_code":"PPL",
    "gn:name":"Cheremenets",
    "gn:population":0,
    "gn:timezone":"Europe/Moscow",
    "iso:country":"RU",
    "name:rus_x_preferred":[
        "\u0427\u0435\u0440\u0435\u043c\u0435\u043d\u0435\u0446"
    ],
    "name:und_x_variant":[
        "Cheremets",
        "Cheremenets",
        "\u0427\u0435\u0440\u0435\u043c\u0435\u043d\u0435\u0446"
    ],
    "wof:name":"Cheremenets",
    "wof:placetype":"locality"
},
  "geometry": {"coordinates":[30.07194,58.20573],"type":"Point"}
}