{
  "type": "Feature",
  "properties": {
    "gn:admin1_code":"56",
    "gn:asciiname":"Selemenevo",
    "gn:country_code":"RU",
    "gn:dem":200,
    "gn:feature_class":"P",
    "gn:feature_code":"PPL",
    "gn:name":"Selemenevo",
    "gn:population":0,
    "gn:timezone":"Europe/Moscow",
    "iso:country":"RU",
    "name:rus_x_preferred":[
        "\u0421\u0435\u043b\u0435\u043c\u0435\u043d\u0435\u0432\u043e"
    ],
    "wof:name":"Selemenevo",
    "wof:placetype":"locality"
},
  "geometry": {"coordinates":[35.87102,53.38886],"type":"Point"}
}