{
  "type": "Feature",
  "properties": {
    "gn:admin1_code":"21",
    "gn:asciiname":"Frol'tsevo",
    "gn:country_code":"RU",
    "gn:dem":128,
    "gn:feature_class":"P",
    "gn:feature_code":"PPL",
    "gn:name":"Frol\u2019tsevo",
    "gn:population":0,
    "gn:timezone":"Europe/Moscow",
    "iso:country":"RU",
    "name:rus_x_preferred":[
        "\u0424\u0440\u043e\u043b\u044c\u0446\u0435\u0432\u043e"
    ],
    "name:und_x_variant":[
        "Frol\u2019tsevo"
    ],
    "wof:name":"Frol'tsevo",
    "wof:placetype":"locality"
},
  "geometry": {"coordinates":[39.77208,56.88445],"type":"Point"}
}