{
  "type": "Feature",
  "properties": {
    "gn:admin1_code":"40",
    "gn:asciiname":"Staryy Prosvet",
    "gn:cc2":"RU",
    "gn:country_code":"RU",
    "gn:dem":98,
    "gn:feature_class":"P",
    "gn:feature_code":"PPL",
    "gn:name":"Staryy Prosvet",
    "gn:population":0,
    "gn:timezone":"Asia/Yekaterinburg",
    "iso:country":"RU",
    "name:eng_x_preferred":[
        "Staryy Prosvet"
    ],
    "name:nor_x_preferred":[
        "Nov.Prosvet"
    ],
    "name:rus_x_preferred":[
        "\u041d\u043e\u0432.\u041f\u0440\u043e\u0441\u0432\u0435\u0442"
    ],
    "name:rus_x_variant":[
        "\u0421\u0442\u0430\u0440\u044b\u0439 \u041f\u0440\u043e\u0441\u0432\u0435\u0442"
    ],
    "name:und_x_variant":[
        "Prosvet",
        "Staryy Prosvet",
        "\u0421\u0442\u0430\u0440\u044b\u0439 \u041f\u0440\u043e\u0441\u0432\u0435\u0442"
    ],
    "wof:name":"Staryy Prosvet",
    "wof:placetype":"locality"
},
  "geometry": {"coordinates":[65.05916999999999,55.59833],"type":"Point"}
}