{
  "type": "Feature",
  "properties": {
    "gn:admin1_code":"77",
    "gn:asciiname":"Zanepryad'",
    "gn:country_code":"RU",
    "gn:dem":165,
    "gn:feature_class":"P",
    "gn:feature_code":"PPL",
    "gn:name":"Zanepryad\u2019",
    "gn:population":0,
    "gn:timezone":"Europe/Moscow",
    "iso:country":"RU",
    "name:rus_x_preferred":[
        "\u0417\u0430\u043d\u0435\u043f\u0440\u044f\u0434\u044c"
    ],
    "name:und_x_variant":[
        "Zanepryad\u2019"
    ],
    "wof:name":"Zanepryad'",
    "wof:placetype":"locality"
},
  "geometry": {"coordinates":[36.3918,58.2247],"type":"Point"}
}