{
  "type": "Feature",
  "properties": {
    "gn:admin1_code":"90.0",
    "gn:asciiname":"Novoselovskiy Lesouchastok",
    "gn:country_code":"RU",
    "gn:dem":189,
    "gn:feature_class":"P",
    "gn:feature_code":"PPL",
    "gn:name":"Novos\u00eblovskiy Lesouchastok",
    "gn:population":0,
    "gn:timezone":"Asia/Yekaterinburg",
    "iso:country":"RU",
    "name:rus_x_preferred":[
        "\u041d\u043e\u0432\u043e\u0441\u0451\u043b\u043e\u0432\u0441\u043a\u0438\u0439 \u041b\u0435\u0441\u043e\u0443\u0447\u0430\u0441\u0442\u043e\u043a"
    ],
    "name:und_x_variant":[
        "Novos\u00eblovskiy Lesouchastok"
    ],
    "wof:name":"Novoselovskiy Lesouchastok",
    "wof:placetype":"locality"
},
  "geometry": {"coordinates":[54.6893,58.9081],"type":"Point"}
}