{
  "type": "Feature",
  "properties": {
    "gn:admin1_code":"76",
    "gn:asciiname":"Spasskoye-Krivtsovo",
    "gn:country_code":"RU",
    "gn:dem":217,
    "gn:feature_class":"P",
    "gn:feature_code":"PPL",
    "gn:name":"Spasskoye-Krivtsovo",
    "gn:population":0,
    "gn:timezone":"Europe/Moscow",
    "iso:country":"RU",
    "name:rus_x_preferred":[
        "\u0421\u043f\u0430\u0441\u0441\u043a\u043e\u0435-\u041a\u0440\u0438\u0432\u0446\u043e\u0432\u043e"
    ],
    "name:und_x_variant":[
        "Spasskoye Krivtsevo",
        "Spasskoye-Krivtsovo",
        "\u0421\u043f\u0430\u0441\u0441\u043a\u043e\u0435-\u041a\u0440\u0438\u0432\u0446\u043e\u0432\u043e"
    ],
    "wof:name":"Spasskoye-Krivtsovo",
    "wof:placetype":"locality"
},
  "geometry": {"coordinates":[37.41738,53.3414],"type":"Point"}
}