{
  "type": "Feature",
  "properties": {
    "gn:admin1_code":"45",
    "gn:asciiname":"Parazhbelyak",
    "gn:country_code":"RU",
    "gn:dem":170,
    "gn:feature_class":"P",
    "gn:feature_code":"PPL",
    "gn:name":"Parazhbelyak",
    "gn:population":0,
    "gn:timezone":"Europe/Moscow",
    "iso:country":"RU",
    "name:rus_x_preferred":[
        "\u041f\u0430\u0440\u0430\u0436\u0431\u0435\u043b\u044f\u043a"
    ],
    "name:und_x_variant":[
        "Parash-Belyak",
        "Parazhbelyak",
        "\u041f\u0430\u0440\u0430\u0436\u0431\u0435\u043b\u044f\u043a"
    ],
    "wof:name":"Parazhbelyak",
    "wof:placetype":"locality"
},
  "geometry": {"coordinates":[48.775,56.11417],"type":"Point"}
}