{
  "type": "Feature",
  "properties": {
    "gn:admin1_code":"4",
    "gn:asciiname":"Bol'sheromanovka",
    "gn:country_code":"RU",
    "gn:dem":115,
    "gn:feature_class":"P",
    "gn:feature_code":"PPL",
    "gn:name":"Bol\u2019sheromanovka",
    "gn:population":0,
    "gn:timezone":"Asia/Barnaul",
    "iso:country":"RU",
    "name:eng_x_preferred":[
        "Bol'shaya Romanovka"
    ],
    "name:nor_x_preferred":[
        "Bolsjeromanovka"
    ],
    "name:rus_x_preferred":[
        "\u0411\u043e\u043b\u044c\u0448\u0435\u0440\u043e\u043c\u0430\u043d\u043e\u0432\u043a\u0430"
    ],
    "name:und_x_variant":[
        "\u0411\u043e\u043b\u044c\u0448\u0435\u0440\u043e\u043c\u0430\u043d\u043e\u0432\u043a\u0430",
        "Bol\u2019sheromanovka",
        "Bol\u2019shaya Romanovka"
    ],
    "wof:name":"Bol'sheromanovka",
    "wof:placetype":"locality"
},
  "geometry": {"coordinates":[78.85899999999999,52.9953],"type":"Point"}
}