{
  "type": "Feature",
  "properties": {
    "gn:admin1_code":"84",
    "gn:asciiname":"Kurnayevka",
    "gn:country_code":"RU",
    "gn:dem":18,
    "gn:feature_class":"P",
    "gn:feature_code":"PPL",
    "gn:name":"Kurnayevka",
    "gn:population":0,
    "gn:timezone":"Europe/Volgograd",
    "iso:country":"RU",
    "name:eng_x_preferred":[
        "Kurnayevka"
    ],
    "name:nor_x_preferred":[
        "Kurnajevka"
    ],
    "name:rus_x_preferred":[
        "\u041a\u0443\u0440\u043d\u0430\u0435\u0432\u043a\u0430"
    ],
    "wof:name":"Kurnayevka",
    "wof:placetype":"locality"
},
  "geometry": {"coordinates":[45.93443,50.38854],"type":"Point"}
}