{
  "type": "Feature",
  "properties": {
    "gn:country":"RU",
    "gn:fcode":"PPL",
    "gn:pop":20463,
    "iso:country":"RU",
    "name:ara_x_preferred":[
        "\u063a\u0648\u0628\u0643\u064a\u0646\u0633\u0643\u064a"
    ],
    "name:azb_x_preferred":[
        "\u0642\u0648\u0628\u06a9\u06cc\u0646\u0633\u06a9\u06cc"
    ],
    "name:bel_x_preferred":[
        "\u0413\u0443\u0431\u043a\u0456\u043d\u0441\u043a\u0456"
    ],
    "name:bul_x_preferred":[
        "\u0413\u0443\u0431\u043a\u0438\u043d\u0441\u043a\u0438"
    ],
    "name:ceb_x_preferred":[
        "Gubkinskiy"
    ],
    "name:deu_x_preferred":[
        "Gubkinski"
    ],
    "name:ell_x_preferred":[
        "\u0393\u03ba\u03bf\u03c5\u03bc\u03c0\u03ba\u03af\u03bd\u03c3\u03ba\u03b9"
    ],
    "name:eng_x_preferred":[
        "Gubkinsky"
    ],
    "name:epo_x_preferred":[
        "Gubkinskij"
    ],
    "name:fas_x_preferred":[
        "\u06af\u0648\u0628\u06a9\u06cc\u0646\u0633\u06a9\u06cc\u06cc"
    ],
    "name:fin_x_preferred":[
        "Gubkinski"
    ],
    "name:fra_x_preferred":[
        "Goubkinski"
    ],
    "name:hsb_x_preferred":[
        "Gubkinskij"
    ],
    "name:ita_x_preferred":[
        "Gubkinskij"
    ],
    "name:lit_x_preferred":[
        "Gubkinskis"
    ],
    "name:nld_x_preferred":[
        "Goebkinski"
    ],
    "name:nno_x_preferred":[
        "Gubkinskij"
    ],
    "name:nob_x_preferred":[
        "Gubkinskij"
    ],
    "name:nor_x_preferred":[
        "Gubkinskij"
    ],
    "name:pol_x_preferred":[
        "Gubkinskij"
    ],
    "name:rus_x_preferred":[
        "\u0413\u0443\u0431\u043a\u0438\u043d\u0441\u043a\u0438\u0439"
    ],
    "name:srp_x_preferred":[
        "\u0413\u0443\u043f\u043a\u0438\u043d\u0441\u043a\u0438"
    ],
    "name:tat_x_preferred":[
        "\u0413\u0443\u0431\u043a\u0438\u043d\u0441\u043a\u0438"
    ],
    "name:tgk_x_preferred":[
        "\u0413\u0443\u0431\u043a\u0438\u043d\u0441\u043a\u0438\u0439"
    ],
    "name:tgl_x_preferred":[
        "Gubkinsky"
    ],
    "name:tur_x_preferred":[
        "Gubkinski"
    ],
    "name:ukr_x_preferred":[
        "\u0413\u0443\u0431\u043a\u0456\u043d\u0441\u044c\u043a\u0438\u0439"
    ],
    "name:vep_x_preferred":[
        "Gubkinskii"
    ],
    "name:war_x_preferred":[
        "Gubkinsky"
    ],
    "name:zho_x_preferred":[
        "\u53e4\u5e03\u91d1\u65af\u57fa"
    ],
    "qs:name":"Gubkinskiy",
    "qs:photos_9r":0,
    "qs:photos_sr":0,
    "qs:pop_sr":"7",
    "wd:wordcount":41,
    "wof:name":"Gubkinskiy",
    "wof:placetype":"locality",
    "wof:population":20463
},
  "geometry": {"coordinates":[76.50261,64.434],"type":"Point"}
}