{
  "type": "Feature",
  "properties": {
    "gn:admin1_code":"65",
    "gn:asciiname":"Taganche-Martynovskiy",
    "gn:country_code":"RU",
    "gn:dem":128,
    "gn:feature_class":"P",
    "gn:feature_code":"PPL",
    "gn:name":"Taganche-Martynovskiy",
    "gn:population":0,
    "gn:timezone":"Europe/Samara",
    "iso:country":"RU",
    "name:rus_x_preferred":[
        "\u0422\u0430\u0433\u0430\u043d\u0447\u0435-\u041c\u0430\u0440\u0442\u044b\u043d\u043e\u0432\u0441\u043a\u0438\u0439"
    ],
    "name:und_x_variant":[
        "Martynovskiy",
        "Taganche-Martynovskiy"
    ],
    "wof:name":"Taganche-Martynovskiy",
    "wof:placetype":"locality"
},
  "geometry": {"coordinates":[49.6573,52.7678],"type":"Point"}
}