{
  "type": "Feature",
  "properties": {
    "gn:admin1_code":"34",
    "gn:asciiname":"Krasnyy Yag",
    "gn:country_code":"RU",
    "gn:dem":41,
    "gn:feature_class":"P",
    "gn:feature_code":"PPL",
    "gn:name":"Krasnyy Yag",
    "gn:population":0,
    "gn:timezone":"Europe/Moscow",
    "iso:country":"RU",
    "name:eng_x_preferred":[
        "Krasnyy Yag"
    ],
    "name:nor_x_preferred":[
        "Krasnyj Jag"
    ],
    "name:rus_x_preferred":[
        "\u041a\u0440\u0430\u0441\u043d\u044b\u0439 \u042f\u0433"
    ],
    "name:und_x_variant":[
        "Krasnoborskaya",
        "\u041a\u0440\u0430\u0441\u043d\u044b\u0439 \u042f\u0433",
        "Krasnyy Yag"
    ],
    "wof:name":"Krasnyy Yag",
    "wof:placetype":"locality"
},
  "geometry": {"coordinates":[57.29264000000001,65.08610999999999],"type":"Point"}
}