{
  "type": "Feature",
  "properties": {
    "gn:admin1_code":"46",
    "gn:asciiname":"Malyye Manadyshi",
    "gn:country_code":"RU",
    "gn:dem":200,
    "gn:feature_class":"P",
    "gn:feature_code":"PPL",
    "gn:name":"Malyye Manadyshi",
    "gn:population":0,
    "gn:timezone":"Europe/Moscow",
    "iso:country":"RU",
    "name:rus_x_preferred":[
        "\u041c\u0430\u043b\u044b\u0435 \u041c\u0430\u043d\u0430\u0434\u044b\u0448\u0438"
    ],
    "name:und_x_variant":[
        "\u041c\u0430\u043b\u044b\u0435 \u041c\u0430\u043d\u0430\u0434\u044b\u0448\u0438"
    ],
    "wof:name":"Malyye Manadyshi",
    "wof:placetype":"locality"
},
  "geometry": {"coordinates":[46.01442,54.50557],"type":"Point"}
}