{
  "type": "Feature",
  "properties": {
    "gn:admin1_code":"16",
    "gn:asciiname":"Lyubimovka",
    "gn:country_code":"RU",
    "gn:dem":109,
    "gn:feature_class":"P",
    "gn:feature_code":"PPL",
    "gn:name":"Lyubimovka",
    "gn:population":0,
    "gn:timezone":"Europe/Moscow",
    "iso:country":"RU",
    "name:aze_x_preferred":[
        "Lyubimovka"
    ],
    "name:bak_x_preferred":[
        "\u041b\u044e\u0431\u0438\u043c\u043e\u0432\u043a\u0430"
    ],
    "name:che_x_preferred":[
        "\u041b\u044e\u0431\u0438\u043c\u043e\u0432\u043a\u0430"
    ],
    "name:hye_x_preferred":[
        "\u053c\u0575\u0578\u0582\u0562\u056b\u0574\u0578\u057e\u056f\u0561"
    ],
    "name:kat_x_preferred":[
        "\u10da\u10d8\u10e3\u10d1\u10d8\u10db\u10dd\u10d5\u10d9\u10d0"
    ],
    "name:kaz_x_preferred":[
        "\u041b\u044e\u0431\u0438\u043c\u043e\u0432\u043a\u0430"
    ],
    "name:kir_x_preferred":[
        "\u041b\u044e\u0431\u0438\u043c\u043e\u0432\u043a\u0430"
    ],
    "name:rus_x_preferred":[
        "\u041b\u044e\u0431\u0438\u043c\u043e\u0432\u043a\u0430"
    ],
    "name:tat_x_preferred":[
        "\u041b\u044e\u0431\u0438\u043c\u043e\u0432\u043a\u0430"
    ],
    "name:und_x_variant":[
        "\u041b\u044e\u0431\u0438\u043c\u043e\u0432\u043a\u0430"
    ],
    "wof:name":"Lyubimovka",
    "wof:placetype":"locality"
},
  "geometry": {"coordinates":[46.41793,55.0508],"type":"Point"}
}