{
  "type": "Feature",
  "properties": {
    "gn:admin1_code":"16",
    "gn:asciiname":"Lyubimovka",
    "gn:country_code":"RU",
    "gn:dem":109,
    "gn:feature_class":"P",
    "gn:feature_code":"PPL",
    "gn:name":"Lyubimovka",
    "gn:population":0,
    "gn:timezone":"Europe/Moscow",
    "iso:country":"RU",
    "name:rus_x_preferred":[
        "\u041b\u044e\u0431\u0438\u043c\u043e\u0432\u043a\u0430"
    ],
    "name:und_x_variant":[
        "\u041b\u044e\u0431\u0438\u043c\u043e\u0432\u043a\u0430"
    ],
    "wof:name":"Lyubimovka",
    "wof:placetype":"locality"
},
  "geometry": {"coordinates":[46.41793,55.0508],"type":"Point"}
}