{
  "type": "Feature",
  "properties": {
    "gn:admin1_code":"29",
    "gn:asciiname":"Kar'yernyy",
    "gn:country_code":"RU",
    "gn:dem":124,
    "gn:feature_class":"P",
    "gn:feature_code":"PPL",
    "gn:name":"Kar\u2019yernyy",
    "gn:population":0,
    "gn:timezone":"Asia/Novokuznetsk",
    "iso:country":"RU",
    "name:rus_x_preferred":[
        "\u041a\u0430\u0440\u044c\u0435\u0440\u043d\u044b\u0439"
    ],
    "name:und_x_variant":[
        "Kar\u2019yernyy"
    ],
    "wof:name":"Kar'yernyy",
    "wof:placetype":"locality"
},
  "geometry": {"coordinates":[85.93170000000001,55.3841],"type":"Point"}
}