{
  "type": "Feature",
  "properties": {
    "gn:admin1_code":"54",
    "gn:asciiname":"Neverovka",
    "gn:country_code":"RU",
    "gn:dem":107,
    "gn:feature_class":"P",
    "gn:feature_code":"PPL",
    "gn:name":"Neverovka",
    "gn:population":0,
    "gn:timezone":"Asia/Omsk",
    "iso:country":"RU",
    "name:eng_x_preferred":[
        "Neverovka"
    ],
    "name:nor_x_preferred":[
        "Neverovka"
    ],
    "name:rus_x_preferred":[
        "\u041d\u0435\u0432\u0435\u0440\u043e\u0432\u043a\u0430"
    ],
    "name:und_x_variant":[
        "Neverovo"
    ],
    "wof:name":"Neverovka",
    "wof:placetype":"locality"
},
  "geometry": {"coordinates":[73.29649999999999,54.45791],"type":"Point"}
}