{
  "type": "Feature",
  "properties": {
    "gn:admin1_code":"73",
    "gn:asciiname":"Blagodarovka",
    "gn:country_code":"RU",
    "gn:dem":135,
    "gn:feature_class":"P",
    "gn:feature_code":"PPL",
    "gn:name":"Blagodarovka",
    "gn:population":0,
    "gn:timezone":"Europe/Moscow",
    "iso:country":"RU",
    "name:rus_x_preferred":[
        "\u0411\u043b\u0430\u0433\u043e\u0434\u0430\u0440\u043e\u0432\u043a\u0430"
    ],
    "name:und_x_variant":[
        "\u0411\u043b\u0430\u0433\u043e\u0434\u0430\u0440\u043e\u0432\u043a\u0430"
    ],
    "wof:name":"Blagodarovka",
    "wof:placetype":"locality"
},
  "geometry": {"coordinates":[50.9016,55.0801],"type":"Point"}
}