{
  "type": "Feature",
  "properties": {
    "gn:admin1_code":"20",
    "gn:asciiname":"Tukolon'",
    "gn:country_code":"RU",
    "gn:dem":457,
    "gn:feature_class":"P",
    "gn:feature_code":"PPL",
    "gn:name":"Tukolon\u2019",
    "gn:population":0,
    "gn:timezone":"Asia/Irkutsk",
    "iso:country":"RU",
    "name:und_x_variant":[
        "Tyukolon",
        "Tukolon\u2019"
    ],
    "wof:name":"Tukolon'",
    "wof:placetype":"locality"
},
  "geometry": {"coordinates":[107.71904000000001,55.40717],"type":"Point"}
}