{
  "type": "Feature",
  "properties": {
    "gn:admin1_code":"67",
    "gn:asciiname":"Pogranichnyy",
    "gn:cc2":"RU",
    "gn:country_code":"RU",
    "gn:dem":231,
    "gn:feature_class":"P",
    "gn:feature_code":"PPL",
    "gn:name":"Pogranichnyy",
    "gn:population":0,
    "gn:timezone":"Europe/Saratov",
    "iso:country":"RU",
    "name:rus_x_preferred":[
        "\u041f\u043e\u0433\u0440\u0430\u043d\u0438\u0447\u043d\u044b\u0439"
    ],
    "name:und_x_variant":[
        "Ney Moor",
        "Pogranichnyy",
        "\u041f\u043e\u0433\u0440\u0430\u043d\u0438\u0447\u043d\u044b\u0439"
    ],
    "wof:name":"Pogranichnyy",
    "wof:placetype":"locality"
},
  "geometry": {"coordinates":[45.26667,50.91667],"type":"Point"}
}