{
  "type": "Feature",
  "properties": {
    "gn:admin1_code":"45.0",
    "gn:asciiname":"Kirpichnyy",
    "gn:country_code":"RU",
    "gn:dem":67,
    "gn:feature_class":"P",
    "gn:feature_code":"PPL",
    "gn:name":"Kirpichnyy",
    "gn:population":0,
    "gn:timezone":"Europe/Moscow",
    "iso:country":"RU",
    "name:rus_x_preferred":[
        "\u041a\u0438\u0440\u043f\u0438\u0447\u043d\u044b\u0439"
    ],
    "wof:name":"Kirpichnyy",
    "wof:placetype":"locality"
},
  "geometry": {"coordinates":[48.35278,56.12444],"type":"Point"}
}