{
  "type": "Feature",
  "properties": {
    "gn:admin1_code":"60",
    "gn:asciiname":"Osipki",
    "gn:country_code":"RU",
    "gn:dem":74,
    "gn:feature_class":"P",
    "gn:feature_code":"PPL",
    "gn:name":"Osipki",
    "gn:population":0,
    "gn:timezone":"Europe/Moscow",
    "iso:country":"RU",
    "name:rus_x_preferred":[
        "\u041e\u0441\u0438\u043f\u043a\u0438"
    ],
    "wof:name":"Osipki",
    "wof:placetype":"locality"
},
  "geometry": {"coordinates":[28.17226,57.05376999999999],"type":"Point"}
}