{
  "type": "Feature",
  "properties": {
    "gn:admin1_code":"63",
    "gn:asciiname":"Alysardakh",
    "gn:country_code":"RU",
    "gn:dem":595,
    "gn:feature_class":"P",
    "gn:feature_code":"PPL",
    "gn:name":"Alysardakh",
    "gn:population":0,
    "gn:timezone":"Asia/Vladivostok",
    "iso:country":"RU",
    "name:nor_x_preferred":[
        "Alysardakh"
    ],
    "name:rus_x_preferred":[
        "\u0410\u043b\u044b\u0441\u0430\u0440\u0434\u0430\u0445"
    ],
    "name:und_x_variant":[
        "Alysardaakh",
        "Alysardakh"
    ],
    "wof:name":"Alysardakh",
    "wof:placetype":"locality"
},
  "geometry": {"coordinates":[138.05654999999999,61.23896],"type":"Point"}
}