{
  "type": "Feature",
  "properties": {
    "gn:admin1_code":"16",
    "gn:asciiname":"Sredniye Tatmyshi",
    "gn:country_code":"RU",
    "gn:dem":140,
    "gn:feature_class":"P",
    "gn:feature_code":"PPL",
    "gn:name":"Sredniye Tatmyshi",
    "gn:population":0,
    "gn:timezone":"Europe/Moscow",
    "iso:country":"RU",
    "name:rus_x_preferred":[
        "\u0421\u0440\u0435\u0434\u043d\u0438\u0435 \u0422\u0430\u0442\u043c\u044b\u0448\u0438"
    ],
    "name:und_x_variant":[
        "Sredniye Tatmishi",
        "Sredniye Tatmyshi",
        "\u0421\u0440\u0435\u0434\u043d\u0438\u0435 \u0422\u0430\u0442\u043c\u044b\u0448\u0438"
    ],
    "wof:name":"Sredniye Tatmyshi",
    "wof:placetype":"locality"
},
  "geometry": {"coordinates":[47.22536,55.45011],"type":"Point"}
}