{
  "type": "Feature",
  "properties": {
    "gn:admin1_code":"85",
    "gn:asciiname":"Mitropol'ye",
    "gn:country_code":"RU",
    "gn:dem":181,
    "gn:feature_class":"P",
    "gn:feature_code":"PPL",
    "gn:name":"Mitropol\u2019ye",
    "gn:population":0,
    "gn:timezone":"Europe/Moscow",
    "iso:country":"RU",
    "name:rus_x_preferred":[
        "\u041c\u0438\u0442\u0440\u043f\u043e\u043b\u044c\u0435"
    ],
    "name:und_x_variant":[
        "Mitropol\u2019ye",
        "\u041c\u0438\u0442\u0440\u043f\u043e\u043b\u044c\u0435"
    ],
    "wof:name":"Mitropol'ye",
    "wof:placetype":"locality"
},
  "geometry": {"coordinates":[39.1463,59.5438],"type":"Point"}
}