{
  "type": "Feature",
  "properties": {
    "gn:admin1_code":"71",
    "gn:asciiname":"Shaytanskiy",
    "gn:country_code":"RU",
    "gn:dem":153,
    "gn:feature_class":"P",
    "gn:feature_code":"PPL",
    "gn:name":"Shaytanskiy",
    "gn:population":0,
    "gn:timezone":"Asia/Yekaterinburg",
    "iso:country":"RU",
    "name:rus_x_preferred":[
        "\u0428\u0430\u0439\u0442\u0430\u043d\u0441\u043a\u0438\u0439"
    ],
    "name:und_x_variant":[
        "\u0428\u0430\u0439\u0442\u0430\u043d\u0441\u043a\u0438\u0439"
    ],
    "wof:name":"Shaytanskiy",
    "wof:placetype":"locality"
},
  "geometry": {"coordinates":[60.38333000000001,58.65],"type":"Point"}
}