{
  "type": "Feature",
  "properties": {
    "gn:admin1_code":"6",
    "gn:asciiname":"Semzha",
    "gn:country_code":"RU",
    "gn:dem":36,
    "gn:feature_class":"P",
    "gn:feature_code":"PPL",
    "gn:name":"S\u00ebmzha",
    "gn:population":0,
    "gn:timezone":"Europe/Moscow",
    "iso:country":"RU",
    "name:eng_x_preferred":[
        "S\u00ebmzha"
    ],
    "name:nor_x_preferred":[
        "Semzja"
    ],
    "name:rus_x_preferred":[
        "\u0421\u0435\u043c\u0436\u0430"
    ],
    "name:rus_x_variant":[
        "\u0421\u0451\u043c\u0436\u0430"
    ],
    "name:und_x_variant":[
        "Derevnya Semzha",
        "S\u00ebmzha",
        "\u0421\u0451\u043c\u0436\u0430"
    ],
    "wof:name":"Semzha",
    "wof:placetype":"locality"
},
  "geometry": {"coordinates":[44.11662000000001,66.14885],"type":"Point"}
}