{
  "type": "Feature",
  "properties": {
    "gn:admin1_code":"47.0",
    "gn:asciiname":"Dergayevo",
    "gn:country_code":"RU",
    "gn:dem":149,
    "gn:feature_class":"P",
    "gn:feature_code":"PPL",
    "gn:name":"Dergayevo",
    "gn:population":0,
    "gn:timezone":"Europe/Moscow",
    "iso:country":"RU",
    "name:rus_x_preferred":[
        "\u0414\u0435\u0440\u0433\u0430\u0435\u0432\u043e"
    ],
    "name:und_x_variant":[
        "\u0414\u0435\u0440\u0433\u0430\u0435\u0432\u043e"
    ],
    "wof:name":"Dergayevo",
    "wof:placetype":"locality"
},
  "geometry": {"coordinates":[38.67398,55.65166],"type":"Point"}
}