{
  "type": "Feature",
  "properties": {
    "gn:admin1_code":"4.0",
    "gn:asciiname":"Podstepnovskiy",
    "gn:country_code":"RU",
    "gn:dem":263,
    "gn:feature_class":"P",
    "gn:feature_code":"PPL",
    "gn:name":"Podstepnovskiy",
    "gn:population":0,
    "gn:timezone":"Asia/Barnaul",
    "iso:country":"RU",
    "name:rus_x_preferred":[
        "\u041f\u043e\u0434\u0441\u0442\u0435\u043f\u043d\u043e\u0432\u0441\u043a\u0438\u0439"
    ],
    "wof:name":"Podstepnovskiy",
    "wof:placetype":"locality"
},
  "geometry": {"coordinates":[81.9019,52.9888],"type":"Point"}
}