{
  "type": "Feature",
  "properties": {
    "gn:admin1_code":"8.0",
    "gn:asciiname":"Alaguzovo",
    "gn:country_code":"RU",
    "gn:dem":291,
    "gn:feature_class":"P",
    "gn:feature_code":"PPL",
    "gn:name":"Alaguzovo",
    "gn:population":0,
    "gn:timezone":"Asia/Yekaterinburg",
    "iso:country":"RU",
    "name:eng_x_preferred":[
        "Alaguzovo"
    ],
    "name:nor_x_preferred":[
        "Alaguzovo"
    ],
    "name:rus_x_preferred":[
        "\u0410\u043b\u0430\u0433\u0443\u0437\u043e\u0432\u043e"
    ],
    "name:und_x_variant":[
        "Allaguzovo",
        "Allegazovo"
    ],
    "wof:name":"Alaguzovo",
    "wof:placetype":"locality"
},
  "geometry": {"coordinates":[58.7763,55.5911],"type":"Point"}
}