{
  "type": "Feature",
  "properties": {
    "gn:admin1_code":"17",
    "gn:admin2_code":"549104",
    "gn:asciiname":"Ebuta",
    "gn:country_code":"RU",
    "gn:dem":1942,
    "gn:feature_class":"P",
    "gn:feature_code":"PPL",
    "gn:name":"Ebuta",
    "gn:population":0,
    "gn:timezone":"Europe/Moscow",
    "iso:country":"RU",
    "name:rus_x_preferred":[
        "\u042d\u0431\u0443\u0442\u0430"
    ],
    "wof:name":"Ebuta",
    "wof:placetype":"locality"
},
  "geometry": {"coordinates":[46.66626,42.59275],"type":"Point"}
}