{
  "type": "Feature",
  "properties": {
    "gn:admin1_code":"12.0",
    "gn:asciiname":"Dzhubik-Aul",
    "gn:country_code":"RU",
    "gn:dem":1599,
    "gn:feature_class":"P",
    "gn:feature_code":"PPL",
    "gn:name":"Dzhubik-Aul",
    "gn:population":0,
    "gn:timezone":"Europe/Moscow",
    "iso:country":"RU",
    "name:rus_x_preferred":[
        "\u0414\u0436\u0443\u0431\u0438\u043a-\u0410\u0443\u043b"
    ],
    "wof:name":"Dzhubik-Aul",
    "wof:placetype":"locality"
},
  "geometry": {"coordinates":[45.93083,42.8325],"type":"Point"}
}