{
  "type": "Feature",
  "properties": {
    "gn:admin1_code":"33.0",
    "gn:asciiname":"Repnyye",
    "gn:country_code":"RU",
    "gn:dem":127,
    "gn:feature_class":"P",
    "gn:feature_code":"PPL",
    "gn:name":"Repnyye",
    "gn:population":0,
    "gn:timezone":"Europe/Kirov",
    "iso:country":"RU",
    "name:rus_x_preferred":[
        "\u0420\u0435\u043f\u043d\u044b\u0435"
    ],
    "wof:name":"Repnyye",
    "wof:placetype":"locality"
},
  "geometry": {"coordinates":[49.18677,58.43636],"type":"Point"}
}