{
  "type": "Feature",
  "properties": {
    "gn:admin1_code":"54",
    "gn:asciiname":"Lozhnikovo",
    "gn:country_code":"RU",
    "gn:dem":67,
    "gn:feature_class":"P",
    "gn:feature_code":"PPL",
    "gn:name":"Lozhnikovo",
    "gn:population":0,
    "gn:timezone":"Asia/Omsk",
    "iso:country":"RU",
    "name:eng_x_preferred":[
        "Lozhnikovo"
    ],
    "name:nor_x_preferred":[
        "Lozjnikovo"
    ],
    "name:rus_x_preferred":[
        "\u041b\u043e\u0436\u043d\u0438\u043a\u043e\u0432\u043e"
    ],
    "name:und_x_variant":[
        "Lozhnikova",
        "\u041b\u043e\u0436\u043d\u0438\u043a\u043e\u0432\u043e",
        "Lozhnikovo"
    ],
    "wof:name":"Lozhnikovo",
    "wof:placetype":"locality"
},
  "geometry": {"coordinates":[73.87855,56.89211],"type":"Point"}
}