{
  "type": "Feature",
  "properties": {
    "gn:admin1_code":"25.0",
    "gn:asciiname":"Alekseyevskoye",
    "gn:country_code":"RU",
    "gn:dem":185,
    "gn:feature_class":"P",
    "gn:feature_code":"PPL",
    "gn:name":"Alekseyevskoye",
    "gn:population":0,
    "gn:timezone":"Europe/Moscow",
    "iso:country":"RU",
    "name:und_x_variant":[
        "Alekseyevka",
        "Alekseyevskoye"
    ],
    "wof:name":"Alekseyevskoye",
    "wof:placetype":"locality"
},
  "geometry": {"coordinates":[35.27833,54.64361],"type":"Point"}
}