{
  "type": "Feature",
  "properties": {
    "gn:admin1_code":"71",
    "gn:asciiname":"Fominskoye",
    "gn:country_code":"RU",
    "gn:dem":90,
    "gn:feature_class":"P",
    "gn:feature_code":"PPL",
    "gn:name":"Fominskoye",
    "gn:population":0,
    "gn:timezone":"Asia/Yekaterinburg",
    "iso:country":"RU",
    "name:eng_x_preferred":[
        "Fominskoye"
    ],
    "name:nor_x_preferred":[
        "Fominskoje"
    ],
    "name:rus_x_preferred":[
        "\u0424\u043e\u043c\u0438\u043d\u0441\u043a\u043e\u0435"
    ],
    "wof:name":"Fominskoye",
    "wof:placetype":"locality"
},
  "geometry": {"coordinates":[62.19376,58.49954],"type":"Point"}
}