{
  "type": "Feature",
  "properties": {
    "gn:admin1_code":"69",
    "gn:asciiname":"Krasnozabor'ye",
    "gn:country_code":"RU",
    "gn:dem":175,
    "gn:feature_class":"P",
    "gn:feature_code":"PPL",
    "gn:name":"Krasnozabor\u2019ye",
    "gn:population":0,
    "gn:timezone":"Europe/Moscow",
    "iso:country":"RU",
    "name:rus_x_preferred":[
        "\u041a\u0440\u0430\u0441\u043d\u043e\u0437\u0430\u0431\u043e\u0440\u044c\u0435"
    ],
    "name:und_x_variant":[
        "Krasnozabor\u2019ye"
    ],
    "wof:name":"Krasnozabor'ye",
    "wof:placetype":"locality"
},
  "geometry": {"coordinates":[32.53389,53.74194],"type":"Point"}
}