{
  "type": "Feature",
  "properties": {
    "gn:admin1_code":"23",
    "gn:asciiname":"Eichen",
    "gn:country_code":"RU",
    "gn:dem":7,
    "gn:feature_class":"P",
    "gn:feature_code":"PPL",
    "gn:name":"Eichen",
    "gn:population":0,
    "gn:timezone":"Europe/Kaliningrad",
    "iso:country":"RU",
    "name:ceb_x_preferred":[
        "Eichen"
    ],
    "name:deu_x_preferred":[
        "Eichen"
    ],
    "name:epo_x_preferred":[
        "Eichen"
    ],
    "name:eus_x_preferred":[
        "Eichen"
    ],
    "name:fas_x_preferred":[
        "\u0622\u06cc\u062e\u0646"
    ],
    "name:fra_x_preferred":[
        "Eichen"
    ],
    "name:hun_x_preferred":[
        "Eichen"
    ],
    "name:ita_x_preferred":[
        "Eichen"
    ],
    "name:kaz_x_preferred":[
        "\u0410\u0439\u0445\u0435\u043d"
    ],
    "name:kir_x_preferred":[
        "\u0410\u0439\u0445\u0435\u043d"
    ],
    "name:msa_x_preferred":[
        "Eichen"
    ],
    "name:nld_x_preferred":[
        "Eichen"
    ],
    "name:pol_x_preferred":[
        "Eichen"
    ],
    "name:por_x_preferred":[
        "Eichen"
    ],
    "name:ron_x_preferred":[
        "Eichen"
    ],
    "name:rus_x_preferred":[
        "\u042d\u0438\u0447\u0435\u043d"
    ],
    "name:rus_x_variant":[
        "\u0410\u0439\u0445\u0435\u043d"
    ],
    "name:spa_x_preferred":[
        "Eichen"
    ],
    "name:srp_x_preferred":[
        "\u0410\u0458\u0445\u0435\u043d"
    ],
    "name:ukr_x_preferred":[
        "\u0410\u0439\u0445\u0435\u043d"
    ],
    "name:und_x_variant":[
        "\u042d\u0438\u0447\u0435\u043d"
    ],
    "name:uzb_x_preferred":[
        "Eichen"
    ],
    "name:vie_x_preferred":[
        "Eichen"
    ],
    "name:vol_x_preferred":[
        "Eichen"
    ],
    "name:war_x_preferred":[
        "Eichen"
    ],
    "wof:name":"Eichen",
    "wof:placetype":"locality"
},
  "geometry": {"coordinates":[20.94028,54.68778],"type":"Point"}
}