{
  "type": "Feature",
  "properties": {
    "gn:admin1_code":"23",
    "gn:asciiname":"Eichen",
    "gn:country_code":"RU",
    "gn:dem":7,
    "gn:feature_class":"P",
    "gn:feature_code":"PPL",
    "gn:name":"Eichen",
    "gn:population":0,
    "gn:timezone":"Europe/Kaliningrad",
    "iso:country":"RU",
    "name:rus_x_preferred":[
        "\u042d\u0438\u0447\u0435\u043d"
    ],
    "name:und_x_variant":[
        "\u042d\u0438\u0447\u0435\u043d"
    ],
    "wof:name":"Eichen",
    "wof:placetype":"locality"
},
  "geometry": {"coordinates":[20.94028,54.68778],"type":"Point"}
}