{
  "type": "Feature",
  "properties": {
    "gn:admin1_code":"37",
    "gn:asciiname":"Yur'yevo",
    "gn:country_code":"RU",
    "gn:dem":170,
    "gn:feature_class":"P",
    "gn:feature_code":"PPL",
    "gn:name":"Yur\u2019yevo",
    "gn:population":0,
    "gn:timezone":"Europe/Moscow",
    "iso:country":"RU",
    "name:rus_x_preferred":[
        "\u042e\u0440\u044c\u0435\u0432\u043e"
    ],
    "name:und_x_variant":[
        "Yur\u2019yevo"
    ],
    "wof:name":"Yur'yevo",
    "wof:placetype":"locality"
},
  "geometry": {"coordinates":[42.8323,58.1641],"type":"Point"}
}