{
  "type": "Feature",
  "properties": {
    "gn:admin1_code":"8",
    "gn:asciiname":"Ishkil'dina",
    "gn:country_code":"RU",
    "gn:dem":422,
    "gn:feature_class":"P",
    "gn:feature_code":"PPL",
    "gn:name":"Ishkil\u2019dina",
    "gn:population":0,
    "gn:timezone":"Asia/Yekaterinburg",
    "iso:country":"RU",
    "name:rus_x_preferred":[
        "\u0418\u0448\u043a\u0438\u043b\u044c\u0434\u0438\u043d\u0430"
    ],
    "name:und_x_variant":[
        "Ishkimdina",
        "Ishkil\u2019dino",
        "Ishkil\u2019dina",
        "\u0418\u0448\u043a\u0438\u043b\u044c\u0434\u0438\u043d\u0430"
    ],
    "wof:name":"Ishkil'dina",
    "wof:placetype":"locality"
},
  "geometry": {"coordinates":[57.58333,51.88333],"type":"Point"}
}