{
  "type": "Feature",
  "properties": {
    "gn:admin1_code":"28",
    "gn:asciiname":"Kappa",
    "gn:country_code":"RU",
    "gn:dem":34,
    "gn:feature_class":"P",
    "gn:feature_code":"PPL",
    "gn:name":"Kappa",
    "gn:population":0,
    "gn:timezone":"Europe/Moscow",
    "iso:country":"RU",
    "name:fin_x_preferred":[
        "Kaapanhieru"
    ],
    "name:rus_x_preferred":[
        "\u041a\u0430\u043f\u043f\u0430"
    ],
    "name:und_x_variant":[
        "\u041a\u0430\u043f\u043f\u0430"
    ],
    "wof:name":"Kappa",
    "wof:placetype":"locality"
},
  "geometry": {"coordinates":[32.33333,61.25],"type":"Point"}
}