{
  "type": "Feature",
  "properties": {
    "gn:admin1_code":"56",
    "gn:asciiname":"Chertovoye",
    "gn:country_code":"RU",
    "gn:dem":215,
    "gn:feature_class":"P",
    "gn:feature_code":"PPL",
    "gn:name":"Chertovoye",
    "gn:population":0,
    "gn:timezone":"Europe/Moscow",
    "iso:country":"RU",
    "name:rus_x_preferred":[
        "\u0427\u0435\u0440\u0442\u043e\u0432\u043e\u0435"
    ],
    "name:und_x_variant":[
        "Chertovaya",
        "Chertovoye"
    ],
    "wof:name":"Chertovoye",
    "wof:placetype":"locality"
},
  "geometry": {"coordinates":[35.33868,53.10741],"type":"Point"}
}