{
  "type": "Feature",
  "properties": {
    "gn:admin1_code":"33",
    "gn:asciiname":"Kobeli",
    "gn:country_code":"RU",
    "gn:dem":141,
    "gn:feature_class":"P",
    "gn:feature_code":"PPL",
    "gn:name":"Kobeli",
    "gn:population":0,
    "gn:timezone":"Europe/Kirov",
    "iso:country":"RU",
    "name:rus_x_preferred":[
        "\u041a\u043e\u0431\u0435\u043b\u0438"
    ],
    "name:und_x_variant":[
        "Kobelikha",
        "Kobeli",
        "\u041a\u043e\u0431\u0435\u043b\u0438"
    ],
    "wof:name":"Kobeli",
    "wof:placetype":"locality"
},
  "geometry": {"coordinates":[49.6025,58.50389000000001],"type":"Point"}
}