{
  "type": "Feature",
  "properties": {
    "gn:admin1_code":"60",
    "gn:asciiname":"Peski",
    "gn:country_code":"RU",
    "gn:dem":147,
    "gn:feature_class":"P",
    "gn:feature_code":"PPL",
    "gn:name":"Peski",
    "gn:population":0,
    "gn:timezone":"Europe/Moscow",
    "iso:country":"RU",
    "name:rus_x_preferred":[
        "\u041f\u0435\u0441\u043a\u0438"
    ],
    "name:und_x_variant":[
        "\u041f\u0435\u0441\u043a\u0438"
    ],
    "wof:name":"Peski",
    "wof:placetype":"locality"
},
  "geometry": {"coordinates":[30.4655,56.1897],"type":"Point"}
}