{
  "type": "Feature",
  "properties": {
    "gn:admin1_code":"38",
    "gn:asciiname":"Plastunka",
    "gn:country_code":"RU",
    "gn:dem":400,
    "gn:feature_class":"P",
    "gn:feature_code":"PPL",
    "gn:name":"Plastunka",
    "gn:population":0,
    "gn:timezone":"Europe/Moscow",
    "iso:country":"RU",
    "name:rus_x_preferred":[
        "\u041f\u043b\u0430\u0441\u0442\u0443\u043d\u043a\u0430"
    ],
    "name:und_x_variant":[
        "\u041f\u043b\u0430\u0441\u0442\u0443\u043d\u043a\u0430"
    ],
    "wof:name":"Plastunka",
    "wof:placetype":"locality"
},
  "geometry": {"coordinates":[39.79141,43.65845],"type":"Point"}
}