{
  "type": "Feature",
  "properties": {
    "gn:country":"RU",
    "gn:fcode":"PPL",
    "gn:population":0,
    "iso:country":"RU",
    "name:azb_x_preferred":[
        "\u0627\u0648\u062a\u0631\u0627\u062f\u0646\u0648\u06cc "
    ],
    "name:bul_x_preferred":[
        "\u041e\u0442\u0440\u0430\u0434\u043d\u043e"
    ],
    "name:ceb_x_preferred":[
        "Otradnoye District"
    ],
    "name:eng_x_preferred":[
        "Otradnoye District"
    ],
    "name:fra_x_preferred":[
        "Otradno\u00efe"
    ],
    "name:heb_x_preferred":[
        "\u05d0\u05d5\u05d8\u05e8\u05d0\u05d3\u05e0\u05d5\u05d9\u05d4"
    ],
    "name:ita_x_preferred":[
        "Otradnoe"
    ],
    "name:nan_x_preferred":[
        "Otradnoye Ko\u0101n"
    ],
    "name:nld_x_preferred":[
        "Otradnoe"
    ],
    "name:por_x_preferred":[
        "Otradnoye"
    ],
    "name:rus_x_preferred":[
        "\u041e\u0442\u0440\u0430\u0434\u043d\u043e\u0435"
    ],
    "name:sco_x_preferred":[
        "Otradnoye Destrict"
    ],
    "name:tgk_x_preferred":[
        "\u041d\u043e\u04b3\u0438\u044f\u0438 \u041e\u0442\u0440\u0430\u0434\u043d\u043e\u0435"
    ],
    "name:ukr_x_preferred":[
        "\u041e\u0442\u0440\u0430\u0434\u043d\u0435"
    ],
    "name:und_x_variant":[
        "Sovkhoz Otradnoye"
    ],
    "name:zho_x_preferred":[
        "\u6109\u6085\u5340"
    ],
    "qs:name":"Otradnoe",
    "qs:name_adm0":"Russia",
    "qs:name_adm1":"Moscow Oblast",
    "qs:photos_9k":1,
    "qs:photos_9r":1,
    "qs:photos_all":11,
    "qs:photos_sr":0,
    "qs:placetype":"Town",
    "qs:pop_sr":"0",
    "wd:wordcount":62,
    "wof:name":"Otradnoe",
    "wof:placetype":"locality",
    "wof:population":0
},
  "geometry": {"coordinates":[37.31023,55.87526],"type":"Point"}
}