{
  "type": "Feature",
  "properties": {
    "gn:admin1_code":"20.0",
    "gn:asciiname":"Veselyy Bor",
    "gn:country_code":"RU",
    "gn:dem":526,
    "gn:feature_class":"P",
    "gn:feature_code":"PPL",
    "gn:name":"Ves\u00eblyy Bor",
    "gn:population":0,
    "gn:timezone":"Asia/Irkutsk",
    "iso:country":"RU",
    "name:rus_x_preferred":[
        "\u0412\u0435\u0441\u0451\u043b\u044b\u0439 \u0411\u043e\u0440"
    ],
    "name:und_x_variant":[
        "Ves\u00eblyy Bor"
    ],
    "wof:name":"Veselyy Bor",
    "wof:placetype":"locality"
},
  "geometry": {"coordinates":[102.3683,56.5267],"type":"Point"}
}