{
  "type": "Feature",
  "properties": {
    "gn:admin1_code":"81",
    "gn:asciiname":"Mordovo",
    "gn:country_code":"RU",
    "gn:dem":66,
    "gn:feature_class":"P",
    "gn:feature_code":"PPL",
    "gn:name":"Mordovo",
    "gn:population":0,
    "gn:timezone":"Europe/Ulyanovsk",
    "iso:country":"RU",
    "name:rus_x_preferred":[
        "\u041c\u043e\u0440\u0434\u043e\u0432\u043e"
    ],
    "wof:name":"Mordovo",
    "wof:placetype":"locality"
},
  "geometry": {"coordinates":[48.8865,53.8045],"type":"Point"}
}