{
  "type": "Feature",
  "properties": {
    "gn:admin1_code":"4",
    "gn:asciiname":"Borovlyanka",
    "gn:country_code":"RU",
    "gn:dem":508,
    "gn:feature_class":"P",
    "gn:feature_code":"PPL",
    "gn:name":"Borovlyanka",
    "gn:population":0,
    "gn:timezone":"Asia/Barnaul",
    "iso:country":"RU",
    "name:eng_x_preferred":[
        "Borovlyanka"
    ],
    "name:nor_x_preferred":[
        "Borovljanka"
    ],
    "name:rus_x_preferred":[
        "\u0411\u043e\u0440\u043e\u0432\u043b\u044f\u043d\u043a\u0430"
    ],
    "wof:name":"Borovlyanka",
    "wof:placetype":"locality"
},
  "geometry": {"coordinates":[83.75449999999999,51.4066],"type":"Point"}
}