{
  "type": "Feature",
  "properties": {
    "gn:admin1_code":"38.0",
    "gn:asciiname":"Verkhneadagum",
    "gn:country_code":"RU",
    "gn:dem":52,
    "gn:feature_class":"P",
    "gn:feature_code":"PPL",
    "gn:name":"Verkhneadagum",
    "gn:population":0,
    "gn:timezone":"Europe/Moscow",
    "iso:country":"RU",
    "name:rus_x_preferred":[
        "\u0412\u0435\u0440\u0445\u043d\u0435\u0430\u0434\u0430\u0433\u0443\u043c"
    ],
    "name:und_x_variant":[
        "Verkhniy Adagum",
        "Verkhneadagum"
    ],
    "wof:name":"Verkhneadagum",
    "wof:placetype":"locality"
},
  "geometry": {"coordinates":[37.92647,44.88208],"type":"Point"}
}