{
  "type": "Feature",
  "properties": {
    "gn:admin1_code":"77",
    "gn:asciiname":"Maloye Ploskoye",
    "gn:country_code":"RU",
    "gn:dem":189,
    "gn:feature_class":"P",
    "gn:feature_code":"PPL",
    "gn:name":"Maloye Ploskoye",
    "gn:population":0,
    "gn:timezone":"Europe/Moscow",
    "iso:country":"RU",
    "name:rus_x_preferred":[
        "\u041c\u0430\u043b\u043e\u0435 \u041f\u043b\u043e\u0441\u043a\u043e\u0435"
    ],
    "name:und_x_variant":[
        "Ploskaya",
        "Maloye Ploskoye",
        "\u041c\u0430\u043b\u043e\u0435 \u041f\u043b\u043e\u0441\u043a\u043e\u0435"
    ],
    "wof:name":"Maloye Ploskoye",
    "wof:placetype":"locality"
},
  "geometry": {"coordinates":[35.54998,57.28627],"type":"Point"}
}