{
  "type": "Feature",
  "properties": {
    "gn:admin1_code":"30",
    "gn:asciiname":"Dippy",
    "gn:country_code":"RU",
    "gn:dem":27,
    "gn:feature_class":"P",
    "gn:feature_code":"PPL",
    "gn:name":"Dippy",
    "gn:population":0,
    "gn:timezone":"Asia/Vladivostok",
    "iso:country":"RU",
    "name:eng_x_preferred":[
        "Dippy"
    ],
    "name:nor_x_preferred":[
        "Dippy"
    ],
    "name:rus_x_preferred":[
        "\u0414\u0438\u043f\u043f\u044b"
    ],
    "name:und_x_variant":[
        "Angasal\u2019",
        "Dipky",
        "\u0414\u0438\u043f\u043f\u044b",
        "Dippy"
    ],
    "wof:name":"Dippy",
    "wof:placetype":"locality"
},
  "geometry": {"coordinates":[136.98106000000001,50.1499],"type":"Point"}
}