{
  "type": "Feature",
  "properties": {
    "gn:admin1_code":"21.0",
    "gn:asciiname":"Sokernovo",
    "gn:country_code":"RU",
    "gn:dem":117,
    "gn:feature_class":"P",
    "gn:feature_code":"PPL",
    "gn:name":"Sokernovo",
    "gn:population":0,
    "gn:timezone":"Europe/Moscow",
    "iso:country":"RU",
    "name:rus_x_preferred":[
        "\u0421\u043e\u043a\u0435\u0440\u043d\u043e\u0432\u043e"
    ],
    "wof:name":"Sokernovo",
    "wof:placetype":"locality"
},
  "geometry": {"coordinates":[42.62073,57.39125],"type":"Point"}
}