{
  "type": "Feature",
  "properties": {
    "gn:admin1_code":"60",
    "gn:asciiname":"Moshnino",
    "gn:country_code":"RU",
    "gn:dem":131,
    "gn:feature_class":"P",
    "gn:feature_code":"PPL",
    "gn:name":"Moshnino",
    "gn:population":0,
    "gn:timezone":"Europe/Moscow",
    "iso:country":"RU",
    "name:eng_x_preferred":[
        "Moshnino"
    ],
    "name:nor_x_preferred":[
        "Mosjnino"
    ],
    "name:rus_x_preferred":[
        "\u041c\u043e\u0448\u043d\u0438\u043d\u043e"
    ],
    "wof:name":"Moshnino",
    "wof:placetype":"locality"
},
  "geometry": {"coordinates":[28.73816,58.27681],"type":"Point"}
}