{
  "type": "Feature",
  "properties": {
    "gn:admin1_code":"33",
    "gn:asciiname":"Molevskiy",
    "gn:country_code":"RU",
    "gn:dem":160,
    "gn:feature_class":"P",
    "gn:feature_code":"PPL",
    "gn:name":"Molevskiy",
    "gn:population":0,
    "gn:timezone":"Europe/Kirov",
    "iso:country":"RU",
    "name:rus_x_preferred":[
        "\u041c\u043e\u043b\u0435\u0432\u0441\u043a\u0438\u0439"
    ],
    "wof:name":"Molevskiy",
    "wof:placetype":"locality"
},
  "geometry": {"coordinates":[47.61667,60.55],"type":"Point"}
}