{
  "type": "Feature",
  "properties": {
    "gn:admin1_code":"47.0",
    "gn:asciiname":"Bolotnya",
    "gn:country_code":"RU",
    "gn:dem":186,
    "gn:feature_class":"P",
    "gn:feature_code":"PPL",
    "gn:name":"Bolotnya",
    "gn:population":0,
    "gn:timezone":"Europe/Moscow",
    "iso:country":"RU",
    "name:rus_x_preferred":[
        "\u0411\u043e\u043b\u043e\u0442\u043d\u044f"
    ],
    "name:und_x_variant":[
        "Bolotni",
        "Bolotnya",
        "\u0411\u043e\u043b\u043e\u0442\u043d\u044f"
    ],
    "wof:name":"Bolotnya",
    "wof:placetype":"locality"
},
  "geometry": {"coordinates":[38.64529,54.71397],"type":"Point"}
}