{
  "type": "Feature",
  "properties": {
    "gn:admin1_code":"69",
    "gn:asciiname":"Pustoy-Vtornik",
    "gn:country_code":"RU",
    "gn:dem":231,
    "gn:feature_class":"P",
    "gn:feature_code":"PPL",
    "gn:name":"Pustoy-Vtornik",
    "gn:population":0,
    "gn:timezone":"Europe/Moscow",
    "iso:country":"RU",
    "name:rus_x_preferred":[
        "\u041f\u0443\u0441\u0442\u043e\u0439-\u0412\u0442\u043e\u0440\u043d\u0438\u043a"
    ],
    "wof:name":"Pustoy-Vtornik",
    "wof:placetype":"locality"
},
  "geometry": {"coordinates":[35.09056,55.9525],"type":"Point"}
}