{
  "type": "Feature",
  "properties": {
    "gn:admin1_code":"10",
    "gn:asciiname":"Sushany",
    "gn:country_code":"RU",
    "gn:dem":145,
    "gn:feature_class":"P",
    "gn:feature_code":"PPL",
    "gn:name":"Sushany",
    "gn:population":200,
    "gn:timezone":"Europe/Moscow",
    "iso:country":"RU",
    "name:rus_x_preferred":[
        "\u0421\u0443\u0448\u0430\u043d\u044b"
    ],
    "name:und_x_variant":[
        "\u0421\u0443\u0448\u0430\u043d\u044b"
    ],
    "wof:name":"Sushany",
    "wof:placetype":"locality",
    "wof:population":200
},
  "geometry": {"coordinates":[32.30635,52.1957],"type":"Point"}
}