{
  "type": "Feature",
  "properties": {
    "gn:admin1_code":"77",
    "gn:asciiname":"Kozlovka",
    "gn:country_code":"RU",
    "gn:dem":217,
    "gn:feature_class":"P",
    "gn:feature_code":"PPL",
    "gn:name":"Kozlovka",
    "gn:population":0,
    "gn:timezone":"Europe/Moscow",
    "iso:country":"RU",
    "name:rus_x_preferred":[
        "\u041a\u043e\u0437\u043b\u043e\u0432\u043a\u0430"
    ],
    "name:und_x_variant":[
        "\u041a\u043e\u0437\u043b\u043e\u0432\u043a\u0430"
    ],
    "wof:name":"Kozlovka",
    "wof:placetype":"locality"
},
  "geometry": {"coordinates":[31.36667000000001,56.51667],"type":"Point"}
}