{
  "type": "Feature",
  "properties": {
    "gn:admin1_code":"56",
    "gn:asciiname":"Kochevaya",
    "gn:country_code":"RU",
    "gn:dem":206,
    "gn:feature_class":"P",
    "gn:feature_code":"PPL",
    "gn:name":"Kochevaya",
    "gn:population":0,
    "gn:timezone":"Europe/Moscow",
    "iso:country":"RU",
    "name:che_x_preferred":[
        "\u041a\u043e\u0447\u0435\u0432\u0438"
    ],
    "name:rus_x_preferred":[
        "\u041a\u043e\u0447\u0435\u0432\u0430\u044f"
    ],
    "name:und_x_variant":[
        "\u041a\u043e\u0447\u0435\u0432\u0430\u044f"
    ],
    "wof:name":"Kochevaya",
    "wof:placetype":"locality"
},
  "geometry": {"coordinates":[35.60778,52.8025],"type":"Point"}
}