{
  "type": "Feature",
  "properties": {
    "gn:admin1_code":"88",
    "gn:asciiname":"Degtyaritsy",
    "gn:country_code":"RU",
    "gn:dem":118,
    "gn:feature_class":"P",
    "gn:feature_code":"PPL",
    "gn:name":"Degtyaritsy",
    "gn:population":0,
    "gn:timezone":"Europe/Moscow",
    "iso:country":"RU",
    "name:rus_x_preferred":[
        "\u0414\u0435\u0433\u0442\u044f\u0440\u0438\u0446\u044b"
    ],
    "wof:name":"Degtyaritsy",
    "wof:placetype":"locality"
},
  "geometry": {"coordinates":[38.518,57.9089],"type":"Point"}
}