{
  "type": "Feature",
  "properties": {
    "gn:admin1_code":"7",
    "gn:asciiname":"Bakharevskiy",
    "gn:country_code":"RU",
    "gn:dem":-30,
    "gn:feature_class":"P",
    "gn:feature_code":"PPL",
    "gn:name":"Bakhar\u00ebvskiy",
    "gn:population":0,
    "gn:timezone":"Europe/Astrakhan",
    "iso:country":"RU",
    "name:rus_x_preferred":[
        "\u0411\u0430\u0445\u0430\u0440\u0451\u0432\u0441\u043a\u0438\u0439"
    ],
    "name:und_x_variant":[
        "Bakhar\u00ebvskiy"
    ],
    "wof:name":"Bakharevskiy",
    "wof:placetype":"locality"
},
  "geometry": {"coordinates":[47.94300000000001,46.8114],"type":"Point"}
}