{
  "type": "Feature",
  "properties": {
    "gn:admin1_code":"53",
    "gn:asciiname":"Kozino",
    "gn:country_code":"RU",
    "gn:dem":96,
    "gn:feature_class":"P",
    "gn:feature_code":"PPL",
    "gn:name":"Kozino",
    "gn:population":0,
    "gn:timezone":"Asia/Novosibirsk",
    "iso:country":"RU",
    "name:eng_x_preferred":[
        "Kozinka"
    ],
    "name:nor_x_preferred":[
        "Kozino"
    ],
    "name:rus_x_preferred":[
        "\u041a\u043e\u0437\u0438\u043d\u043e"
    ],
    "name:und_x_variant":[
        "Kozinskiy",
        "Kozina"
    ],
    "wof:name":"Kozino",
    "wof:placetype":"locality"
},
  "geometry": {"coordinates":[75.49212,55.51559],"type":"Point"}
}