{
  "type": "Feature",
  "properties": {
    "gn:admin1_code":"73",
    "gn:asciiname":"Tatarskiye-Naratly",
    "gn:country_code":"RU",
    "gn:dem":56,
    "gn:feature_class":"P",
    "gn:feature_code":"PPL",
    "gn:name":"Tatarskiye-Naratly",
    "gn:population":0,
    "gn:timezone":"Europe/Moscow",
    "iso:country":"RU",
    "name:rus_x_preferred":[
        "\u0422\u0430\u0442\u0430\u0440\u0441\u043a\u0438\u0435 \u041d\u0430\u0440\u0430\u0442\u043b\u044b"
    ],
    "name:und_x_variant":[
        "Naratley",
        "Tatarskiy Naratley",
        "Agisheva",
        "Tatarskiye-Naratly"
    ],
    "wof:name":"Tatarskiye-Naratly",
    "wof:placetype":"locality"
},
  "geometry": {"coordinates":[48.34312,55.5135],"type":"Point"}
}