{
  "type": "Feature",
  "properties": {
    "gn:admin1_code":"05",
    "gn:asciiname":"Gulik",
    "gn:country_code":"RU",
    "gn:dem":249,
    "gn:feature_class":"P",
    "gn:feature_code":"PPL",
    "gn:name":"Gulik",
    "gn:population":0,
    "gn:timezone":"Asia/Yakutsk",
    "iso:country":"RU",
    "name:eng_x_preferred":[
        "Gulik"
    ],
    "name:nor_x_preferred":[
        "Gulik"
    ],
    "name:rus_x_preferred":[
        "\u0413\u0443\u043b\u0438\u043a"
    ],
    "name:und_x_variant":[
        "\u0413\u0443\u043b\u0438\u043a",
        "Gulik"
    ],
    "wof:name":"Gulik",
    "wof:placetype":"locality"
},
  "geometry": {"coordinates":[127.09873,53.7469],"type":"Point"}
}