{
  "type": "Feature",
  "properties": {
    "gn:admin1_code":"25",
    "gn:asciiname":"Salovo",
    "gn:country_code":"RU",
    "gn:dem":207,
    "gn:feature_class":"P",
    "gn:feature_code":"PPL",
    "gn:name":"Salovo",
    "gn:population":0,
    "gn:timezone":"Europe/Moscow",
    "iso:country":"RU",
    "name:rus_x_preferred":[
        "\u0421\u0430\u043b\u043e\u0432\u043e"
    ],
    "name:und_x_variant":[
        "\u0421\u0430\u043b\u043e\u0432\u043e"
    ],
    "wof:name":"Salovo",
    "wof:placetype":"locality"
},
  "geometry": {"coordinates":[34.38257,54.26364],"type":"Point"}
}