{
  "type": "Feature",
  "properties": {
    "gn:admin1_code":"20",
    "gn:asciiname":"Uk-Badaranovka",
    "gn:country_code":"RU",
    "gn:dem":365,
    "gn:feature_class":"P",
    "gn:feature_code":"PPL",
    "gn:name":"Uk-Badaranovka",
    "gn:population":0,
    "gn:timezone":"Asia/Irkutsk",
    "iso:country":"RU",
    "name:eng_x_preferred":[
        "Ukovskaya Badaranovka"
    ],
    "name:nor_x_preferred":[
        "Ukovskaja-Badaranovka"
    ],
    "name:rus_x_preferred":[
        "\u0423\u043a\u043e\u0432\u0441\u043a\u0430\u044f-\u0411\u0430\u0434\u0430\u0440\u0430\u043d\u043e\u0432\u043a\u0430"
    ],
    "name:rus_x_variant":[
        "\u0423\u043a-\u0411\u0430\u0434\u0430\u0440\u0430\u043d\u043e\u0432\u043a\u0430"
    ],
    "name:und_x_variant":[
        "Uk-Badaranovka"
    ],
    "wof:name":"Uk-Badaranovka",
    "wof:placetype":"locality"
},
  "geometry": {"coordinates":[99.24379999999999,55.0875],"type":"Point"}
}