{
  "type": "Feature",
  "properties": {
    "gn:admin1_code":"83",
    "gn:asciiname":"Vakhromeyevo",
    "gn:country_code":"RU",
    "gn:dem":101,
    "gn:feature_class":"P",
    "gn:feature_code":"PPL",
    "gn:name":"Vakhromeyevo",
    "gn:population":0,
    "gn:timezone":"Europe/Moscow",
    "iso:country":"RU",
    "name:rus_x_preferred":[
        "\u0412\u0430\u0445\u0440\u043e\u043c\u0435\u0435\u0432\u043e"
    ],
    "wof:name":"Vakhromeyevo",
    "wof:placetype":"locality"
},
  "geometry": {"coordinates":[40.94837,56.47404],"type":"Point"}
}