{
  "type": "Feature",
  "properties": {
    "gn:admin1_code":"42",
    "gn:asciiname":"Smolenets",
    "gn:country_code":"RU",
    "gn:dem":73,
    "gn:feature_class":"P",
    "gn:feature_code":"PPL",
    "gn:name":"Smolenets",
    "gn:population":0,
    "gn:timezone":"Europe/Moscow",
    "iso:country":"RU",
    "name:eng_x_preferred":[
        "Smolenets"
    ],
    "name:nor_x_preferred":[
        "Smolenets"
    ],
    "name:rus_x_preferred":[
        "\u0421\u043c\u043e\u043b\u0435\u043d\u0435\u0446"
    ],
    "wof:name":"Smolenets",
    "wof:placetype":"locality"
},
  "geometry": {"coordinates":[33.74232,59.77666],"type":"Point"}
}