{
  "type": "Feature",
  "properties": {
    "gn:admin1_code":"77",
    "gn:asciiname":"Mezha",
    "gn:country_code":"RU",
    "gn:dem":173,
    "gn:feature_class":"P",
    "gn:feature_code":"PPL",
    "gn:name":"Mezha",
    "gn:population":0,
    "gn:timezone":"Europe/Moscow",
    "iso:country":"RU",
    "name:rus_x_preferred":[
        "\u041c\u0435\u0436\u0430"
    ],
    "name:und_x_variant":[
        "\u041c\u0435\u0436\u0430"
    ],
    "wof:name":"Mezha",
    "wof:placetype":"locality"
},
  "geometry": {"coordinates":[32.55806,55.96417],"type":"Point"}
}