{
  "type": "Feature",
  "properties": {
    "gn:admin1_code":"91",
    "gn:asciiname":"Prospikhino",
    "gn:cc2":"RU",
    "gn:country_code":"RU",
    "gn:dem":164,
    "gn:feature_class":"P",
    "gn:feature_code":"PPL",
    "gn:name":"Prospikhino",
    "gn:population":0,
    "gn:timezone":"Asia/Krasnoyarsk",
    "iso:country":"RU",
    "name:eng_x_preferred":[
        "Prospikhino"
    ],
    "name:nor_x_preferred":[
        "Prospikhino"
    ],
    "name:rus_x_preferred":[
        "\u041f\u0440\u043e\u0441\u043f\u0438\u0445\u0438\u043d\u043e"
    ],
    "name:und_x_variant":[
        "Prospikhina",
        "Prospikhino"
    ],
    "wof:name":"Prospikhino",
    "wof:placetype":"locality"
},
  "geometry": {"coordinates":[99.38028,58.595],"type":"Point"}
}