{
  "type": "Feature",
  "properties": {
    "gn:admin1_code":"73",
    "gn:asciiname":"Malyy Buseryak",
    "gn:country_code":"RU",
    "gn:dem":112,
    "gn:feature_class":"P",
    "gn:feature_code":"PPL",
    "gn:name":"Malyy Buseryak",
    "gn:population":0,
    "gn:timezone":"Europe/Moscow",
    "iso:country":"RU",
    "name:rus_x_preferred":[
        "\u041c\u0430\u043b\u044b\u0439 \u0411\u0443\u0441\u0435\u0440\u044f\u043a"
    ],
    "wof:name":"Malyy Buseryak",
    "wof:placetype":"locality"
},
  "geometry": {"coordinates":[52.1899,55.1635],"type":"Point"}
}