{
  "type": "Feature",
  "properties": {
    "gn:admin1_code":"85",
    "gn:asciiname":"Morozovitsa",
    "gn:country_code":"RU",
    "gn:dem":74,
    "gn:feature_class":"P",
    "gn:feature_code":"PPL",
    "gn:name":"Morozovitsa",
    "gn:population":0,
    "gn:timezone":"Europe/Moscow",
    "iso:country":"RU",
    "name:eng_x_preferred":[
        "Morozovitsa"
    ],
    "name:nor_x_preferred":[
        "Morozovitsa"
    ],
    "name:rus_x_preferred":[
        "\u041c\u043e\u0440\u043e\u0437\u043e\u0432\u0438\u0446\u0430"
    ],
    "wof:name":"Morozovitsa",
    "wof:placetype":"locality"
},
  "geometry": {"coordinates":[46.30244,60.71043],"type":"Point"}
}