{
  "type": "Feature",
  "properties": {
    "gn:admin1_code":"60",
    "gn:asciiname":"Mikhaylov Pogost",
    "gn:country_code":"RU",
    "gn:dem":77,
    "gn:feature_class":"P",
    "gn:feature_code":"PPL",
    "gn:name":"Mikhaylov Pogost",
    "gn:population":0,
    "gn:timezone":"Europe/Moscow",
    "iso:country":"RU",
    "name:rus_x_preferred":[
        "\u041c\u0438\u0445\u0430\u0439\u043b\u043e\u0432 \u041f\u043e\u0433\u043e\u0441\u0442"
    ],
    "name:und_x_variant":[
        "Pogost Mikhaylovskiy",
        "Mikhaylovskiy",
        "Mikhaylov Pogost"
    ],
    "wof:name":"Mikhaylov Pogost",
    "wof:placetype":"locality"
},
  "geometry": {"coordinates":[30.25206,57.82941999999999],"type":"Point"}
}