{
  "type": "Feature",
  "properties": {
    "gn:admin1_code":"20",
    "gn:asciiname":"Khokhonok",
    "gn:country_code":"RU",
    "gn:dem":598,
    "gn:feature_class":"P",
    "gn:feature_code":"PPL",
    "gn:name":"Khokhonok",
    "gn:population":0,
    "gn:timezone":"Asia/Irkutsk",
    "iso:country":"RU",
    "name:rus_x_preferred":[
        "\u0425\u043e\u0445\u043e\u043d\u043e\u043a"
    ],
    "name:und_x_variant":[
        "\u0425\u043e\u0445\u043e\u043d\u043e\u043a"
    ],
    "wof:name":"Khokhonok",
    "wof:placetype":"locality"
},
  "geometry": {"coordinates":[105.93333,53.73333],"type":"Point"}
}