{
  "type": "Feature",
  "properties": {
    "gn:admin1_code":"52",
    "gn:asciiname":"Manuilovo",
    "gn:country_code":"RU",
    "gn:dem":171,
    "gn:feature_class":"P",
    "gn:feature_code":"PPL",
    "gn:name":"Manuilovo",
    "gn:population":0,
    "gn:timezone":"Europe/Moscow",
    "iso:country":"RU",
    "name:und_x_variant":[
        "Manuylovo",
        "Manuilovo"
    ],
    "wof:name":"Manuilovo",
    "wof:placetype":"locality"
},
  "geometry": {"coordinates":[33.19306,58.3475],"type":"Point"}
}