{
  "type": "Feature",
  "properties": {
    "gn:admin1_code":"47",
    "gn:asciiname":"Komlevo",
    "gn:country_code":"RU",
    "gn:dem":119,
    "gn:feature_class":"P",
    "gn:feature_code":"PPL",
    "gn:name":"Komlevo",
    "gn:population":0,
    "gn:timezone":"Europe/Moscow",
    "iso:country":"RU",
    "name:rus_x_preferred":[
        "\u041a\u043e\u043c\u043b\u0435\u0432\u043e"
    ],
    "wof:name":"Komlevo",
    "wof:placetype":"locality"
},
  "geometry": {"coordinates":[39.06112,55.16144],"type":"Point"}
}