{
  "type": "Feature",
  "properties": {
    "gn:admin1_code":"66",
    "gn:asciiname":"Mozhayskiy",
    "gn:country_code":"RU",
    "gn:dem":98,
    "gn:feature_class":"P",
    "gn:feature_code":"PPL",
    "gn:name":"Mozhayskiy",
    "gn:population":0,
    "gn:timezone":"Europe/Moscow",
    "iso:country":"RU",
    "name:fin_x_preferred":[
        "Tuutari"
    ],
    "name:rus_x_preferred":[
        "\u041c\u043e\u0436\u0430\u0439\u0441\u043a\u0438\u0439"
    ],
    "name:und_x_variant":[
        "Dudergof",
        "Nagornoye",
        "Mozhayskiy",
        "\u041c\u043e\u0436\u0430\u0439\u0441\u043a\u0438\u0439"
    ],
    "wof:name":"Mozhayskiy",
    "wof:placetype":"locality"
},
  "geometry": {"coordinates":[30.12151,59.69919],"type":"Point"}
}