{
  "type": "Feature",
  "properties": {
    "gn:admin1_code":"68.0",
    "gn:asciiname":"Lamardon",
    "gn:country_code":"RU",
    "gn:dem":1559,
    "gn:feature_class":"P",
    "gn:feature_code":"PPL",
    "gn:name":"Lamardon",
    "gn:population":0,
    "gn:timezone":"Europe/Moscow",
    "iso:country":"RU",
    "name:rus_x_preferred":[
        "\u041b\u0430\u043c\u0430\u0440\u0434\u043e\u043d"
    ],
    "name:und_x_variant":[
        "Lamardon-Tsagat",
        "Lamardon"
    ],
    "wof:name":"Lamardon",
    "wof:placetype":"locality"
},
  "geometry": {"coordinates":[44.41142,42.83779000000001],"type":"Point"}
}