{
  "type": "Feature",
  "properties": {
    "gn:admin1_code":"77",
    "gn:asciiname":"Vanya",
    "gn:cc2":"RU",
    "gn:country_code":"RU",
    "gn:dem":183,
    "gn:feature_class":"P",
    "gn:feature_code":"PPL",
    "gn:name":"Vanya",
    "gn:population":0,
    "gn:timezone":"Europe/Moscow",
    "iso:country":"RU",
    "name:ceb_x_preferred":[
        "Vanya"
    ],
    "name:deu_x_preferred":[
        "Wanja"
    ],
    "name:fra_x_preferred":[
        "Vania"
    ],
    "name:hye_x_preferred":[
        "\u054e\u0561\u0576\u0575\u0561"
    ],
    "name:rus_x_preferred":[
        "\u0412\u0430\u043d\u044f"
    ],
    "name:und_x_variant":[
        "Vakya"
    ],
    "wof:name":"Vanya",
    "wof:placetype":"locality"
},
  "geometry": {"coordinates":[32.0725,55.86833000000001],"type":"Point"}
}