{
  "type": "Feature",
  "properties": {
    "gn:admin1_code":"77",
    "gn:asciiname":"Vanya",
    "gn:cc2":"RU",
    "gn:country_code":"RU",
    "gn:dem":183,
    "gn:feature_class":"P",
    "gn:feature_code":"PPL",
    "gn:name":"Vanya",
    "gn:population":0,
    "gn:timezone":"Europe/Moscow",
    "iso:country":"RU",
    "name:und_x_variant":[
        "Vakya",
        "Vanya"
    ],
    "wof:name":"Vanya",
    "wof:placetype":"locality"
},
  "geometry": {"coordinates":[32.0725,55.86833000000001],"type":"Point"}
}