{
  "type": "Feature",
  "properties": {
    "gn:admin1_code":"81.0",
    "gn:asciiname":"Bryandino",
    "gn:country_code":"RU",
    "gn:dem":137,
    "gn:feature_class":"P",
    "gn:feature_code":"PPL",
    "gn:name":"Bryandino",
    "gn:population":0,
    "gn:timezone":"Europe/Ulyanovsk",
    "iso:country":"RU",
    "name:eng_x_preferred":[
        "Bryandino"
    ],
    "name:nor_x_preferred":[
        "Brjandino"
    ],
    "name:rus_x_preferred":[
        "\u0411\u0440\u044f\u043d\u0434\u0438\u043d\u043e"
    ],
    "wof:name":"Bryandino",
    "wof:placetype":"locality"
},
  "geometry": {"coordinates":[49.38333,54.38333000000001],"type":"Point"}
}