{
  "type": "Feature",
  "properties": {
    "gn:admin1_code":"77",
    "gn:asciiname":"Makarovo",
    "gn:country_code":"RU",
    "gn:dem":248,
    "gn:feature_class":"P",
    "gn:feature_code":"PPL",
    "gn:name":"Makarovo",
    "gn:population":0,
    "gn:timezone":"Europe/Moscow",
    "iso:country":"RU",
    "name:rus_x_preferred":[
        "\u041c\u0430\u043a\u0430\u0440\u043e\u0432\u043e"
    ],
    "name:und_x_variant":[
        "\u041c\u0430\u043a\u0430\u0440\u043e\u0432\u043e"
    ],
    "wof:name":"Makarovo",
    "wof:placetype":"locality"
},
  "geometry": {"coordinates":[33.32294,56.35418000000001],"type":"Point"}
}