{
  "type": "Feature",
  "properties": {
    "gn:admin1_code":"8",
    "gn:asciiname":"Yashasen",
    "gn:country_code":"RU",
    "gn:dem":145,
    "gn:feature_class":"P",
    "gn:feature_code":"PPL",
    "gn:name":"Yashasen",
    "gn:population":0,
    "gn:timezone":"Asia/Yekaterinburg",
    "iso:country":"RU",
    "name:rus_x_preferred":[
        "\u042f\u0448\u0430\u0441\u0435\u043d"
    ],
    "wof:name":"Yashasen",
    "wof:placetype":"locality"
},
  "geometry": {"coordinates":[54.6728,53.7964],"type":"Point"}
}