{
  "type": "Feature",
  "properties": {
    "gn:admin1_code":"8.0",
    "gn:asciiname":"Alatana",
    "gn:country_code":"RU",
    "gn:dem":153,
    "gn:feature_class":"P",
    "gn:feature_code":"PPL",
    "gn:name":"Alatana",
    "gn:population":0,
    "gn:timezone":"Asia/Yekaterinburg",
    "iso:country":"RU",
    "name:eng_x_preferred":[
        "Alatana"
    ],
    "name:nor_x_preferred":[
        "Alatana"
    ],
    "name:rus_x_preferred":[
        "\u0410\u043b\u0430\u0442\u0430\u043d\u0430"
    ],
    "wof:name":"Alatana",
    "wof:placetype":"locality"
},
  "geometry": {"coordinates":[56.15064,53.71519],"type":"Point"}
}