{
  "type": "Feature",
  "properties": {
    "gn:admin1_code":"77",
    "gn:asciiname":"Chizhi",
    "gn:country_code":"RU",
    "gn:dem":222,
    "gn:feature_class":"P",
    "gn:feature_code":"PPL",
    "gn:name":"Chizhi",
    "gn:population":0,
    "gn:timezone":"Europe/Moscow",
    "iso:country":"RU",
    "name:rus_x_preferred":[
        "\u0427\u0438\u0436\u0438"
    ],
    "wof:name":"Chizhi",
    "wof:placetype":"locality"
},
  "geometry": {"coordinates":[33.46302,56.76381],"type":"Point"}
}