{
  "type": "Feature",
  "properties": {
    "gn:admin1_code":"10",
    "gn:asciiname":"Sokol'ya Sloboda",
    "gn:country_code":"RU",
    "gn:dem":187,
    "gn:feature_class":"P",
    "gn:feature_code":"PPL",
    "gn:name":"Sokol\u2019ya Sloboda",
    "gn:population":0,
    "gn:timezone":"Europe/Moscow",
    "iso:country":"RU",
    "name:rus_x_preferred":[
        "\u0421\u043e\u043a\u043e\u043b\u044c\u044f \u0421\u043b\u043e\u0431\u043e\u0434\u0430"
    ],
    "name:und_x_variant":[
        "Sokol\u2019ya",
        "Sokol\u2019ya Sloboda"
    ],
    "wof:name":"Sokol'ya Sloboda",
    "wof:placetype":"locality"
},
  "geometry": {"coordinates":[33.43405,53.25321],"type":"Point"}
}