{
  "type": "Feature",
  "properties": {
    "gn:admin1_code":"29",
    "gn:asciiname":"Tomskoye",
    "gn:country_code":"RU",
    "gn:dem":360,
    "gn:feature_class":"P",
    "gn:feature_code":"PPL",
    "gn:name":"Tomskoye",
    "gn:population":0,
    "gn:timezone":"Asia/Novokuznetsk",
    "iso:country":"RU",
    "name:eng_x_preferred":[
        "Tomskoye"
    ],
    "name:nor_x_preferred":[
        "Tomskoje"
    ],
    "name:rus_x_preferred":[
        "\u0422\u043e\u043c\u0441\u043a\u043e\u0435"
    ],
    "name:und_x_variant":[
        "Tomskiy Zavod",
        "Tomskoye"
    ],
    "wof:name":"Tomskoye",
    "wof:placetype":"locality"
},
  "geometry": {"coordinates":[86.48309999999999,53.6063],"type":"Point"}
}