{
  "type": "Feature",
  "properties": {
    "gn:admin1_code":"17",
    "gn:asciiname":"Umarotar",
    "gn:country_code":"RU",
    "gn:dem":10,
    "gn:feature_class":"P",
    "gn:feature_code":"PPL",
    "gn:name":"Umarotar",
    "gn:population":0,
    "gn:timezone":"Europe/Moscow",
    "iso:country":"RU",
    "name:rus_x_preferred":[
        "\u0423\u043c\u0430\u0440\u043e\u0442\u0430\u0440"
    ],
    "name:und_x_variant":[
        "Omar-Otar",
        "Umarotar"
    ],
    "wof:name":"Umarotar",
    "wof:placetype":"locality"
},
  "geometry": {"coordinates":[46.69025,43.42388],"type":"Point"}
}