{
  "type": "Feature",
  "properties": {
    "gn:admin1_code":"60",
    "gn:asciiname":"Poshetni",
    "gn:country_code":"RU",
    "gn:dem":80,
    "gn:feature_class":"P",
    "gn:feature_code":"PPL",
    "gn:name":"Poshetni",
    "gn:population":0,
    "gn:timezone":"Europe/Moscow",
    "iso:country":"RU",
    "name:rus_x_preferred":[
        "\u041f\u043e\u0448\u0435\u0442\u043d\u0438"
    ],
    "wof:name":"Poshetni",
    "wof:placetype":"locality"
},
  "geometry": {"coordinates":[28.78267,56.98455],"type":"Point"}
}