{
  "type": "Feature",
  "properties": {
    "gn:admin1_code":"72",
    "gn:asciiname":"Pyatnitskiy",
    "gn:country_code":"RU",
    "gn:dem":186,
    "gn:feature_class":"P",
    "gn:feature_code":"PPL",
    "gn:name":"Pyatnitskiy",
    "gn:population":0,
    "gn:timezone":"Europe/Moscow",
    "iso:country":"RU",
    "name:rus_x_preferred":[
        "\u041f\u044f\u0442\u043d\u0438\u0442\u0441\u043a\u0438\u0439"
    ],
    "wof:name":"Pyatnitskiy",
    "wof:placetype":"locality"
},
  "geometry": {"coordinates":[41.83333,52.18333],"type":"Point"}
}