{
  "type": "Feature",
  "properties": {
    "gn:admin1_code":"90",
    "gn:asciiname":"Tyushevskoye",
    "gn:cc2":"RU",
    "gn:country_code":"RU",
    "gn:dem":402,
    "gn:feature_class":"P",
    "gn:feature_code":"PPL",
    "gn:name":"Tyushevskoye",
    "gn:population":0,
    "gn:timezone":"Asia/Yekaterinburg",
    "iso:country":"RU",
    "name:und_x_variant":[
        "Tyushevskiy",
        "Tyushchevskoye"
    ],
    "wof:name":"Tyushevskoye",
    "wof:placetype":"locality"
},
  "geometry": {"coordinates":[59.06194,58.78583],"type":"Point"}
}