{
  "type": "Feature",
  "properties": {
    "gn:admin1_code":"6.0",
    "gn:asciiname":"Aksenovo",
    "gn:country_code":"RU",
    "gn:dem":193,
    "gn:feature_class":"P",
    "gn:feature_code":"PPL",
    "gn:name":"Aks\u00ebnovo",
    "gn:population":0,
    "gn:timezone":"Europe/Moscow",
    "iso:country":"RU",
    "name:rus_x_preferred":[
        "Aks\u00ebnovo"
    ],
    "name:rus_x_variant":[
        "\u0410\u043a\u0441\u0451\u043d\u043e\u0432\u043e"
    ],
    "wof:name":"Aksenovo",
    "wof:placetype":"locality"
},
  "geometry": {"coordinates":[40.0365,60.7731],"type":"Point"}
}