{
  "type": "Feature",
  "properties": {
    "gn:admin1_code":"25",
    "gn:asciiname":"Kurchino",
    "gn:country_code":"RU",
    "gn:dem":163,
    "gn:feature_class":"P",
    "gn:feature_code":"PPL",
    "gn:name":"Kurchino",
    "gn:population":0,
    "gn:timezone":"Europe/Moscow",
    "iso:country":"RU",
    "name:rus_x_preferred":[
        "\u041a\u0443\u0440\u0447\u0438\u043d\u043e"
    ],
    "wof:name":"Kurchino",
    "wof:placetype":"locality"
},
  "geometry": {"coordinates":[36.30444,55.15694000000001],"type":"Point"}
}