{
  "type": "Feature",
  "properties": {
    "gn:admin1_code":"33.0",
    "gn:asciiname":"Akhmanovo",
    "gn:country_code":"RU",
    "gn:dem":119,
    "gn:feature_class":"P",
    "gn:feature_code":"PPL",
    "gn:name":"Akhmanovo",
    "gn:population":0,
    "gn:timezone":"Europe/Kirov",
    "iso:country":"RU",
    "name:aze_x_preferred":[
        "Akman"
    ],
    "name:bak_x_preferred":[
        "\u0410\u0445\u043c\u0430\u043d"
    ],
    "name:che_x_preferred":[
        "\u0410\u0445\u043c\u0430\u043d\u043e\u0432\u043e"
    ],
    "name:chv_x_preferred":[
        "\u0410\u0445\u043c\u0430\u043d"
    ],
    "name:eng_x_preferred":[
        "Akhmanovo"
    ],
    "name:hye_x_preferred":[
        "\u0531\u056d\u0574\u0561\u0576\u0578\u057e\u0578"
    ],
    "name:kaz_x_preferred":[
        "\u0410\u0445\u043c\u0430\u043d"
    ],
    "name:kir_x_preferred":[
        "\u0410\u0445\u043c\u0430\u043d"
    ],
    "name:nor_x_preferred":[
        "Akhmanovo"
    ],
    "name:rus_x_preferred":[
        "\u0410\u0445\u043c\u0430\u043d\u043e\u0432\u043e"
    ],
    "name:tat_x_preferred":[
        "\u0410\u043a\u043c\u0430\u043d"
    ],
    "name:und_x_variant":[
        "\u0410\u0445\u043c\u0430\u043d\u043e\u0432\u043e",
        "Akhmanovo"
    ],
    "wof:name":"Akhmanovo",
    "wof:placetype":"locality"
},
  "geometry": {"coordinates":[48.50288,57.36467],"type":"Point"}
}