{
  "type": "Feature",
  "properties": {
    "gn:admin1_code":"9.0",
    "gn:asciiname":"Novikovo",
    "gn:country_code":"RU",
    "gn:dem":124,
    "gn:feature_class":"P",
    "gn:feature_code":"PPL",
    "gn:name":"Novikovo",
    "gn:population":0,
    "gn:timezone":"Europe/Moscow",
    "iso:country":"RU",
    "name:rus_x_preferred":[
        "\u041d\u043e\u0432\u0438\u043a\u043e\u0432\u043e"
    ],
    "name:und_x_variant":[
        "Novikovo Pervoye",
        "Novikovo Vtoroye"
    ],
    "wof:name":"Novikovo",
    "wof:placetype":"locality"
},
  "geometry": {"coordinates":[37.8915,51.1502],"type":"Point"}
}