{
  "type": "Feature",
  "properties": {
    "gn:admin1_code":"46",
    "gn:asciiname":"Yelkhi",
    "gn:country_code":"RU",
    "gn:dem":190,
    "gn:feature_class":"P",
    "gn:feature_code":"PPL",
    "gn:name":"Yelkhi",
    "gn:population":0,
    "gn:timezone":"Europe/Moscow",
    "iso:country":"RU",
    "name:rus_x_preferred":[
        "\u0415\u043b\u0445\u0438"
    ],
    "name:und_x_variant":[
        "\u0415\u043b\u0445\u0438"
    ],
    "wof:name":"Yelkhi",
    "wof:placetype":"locality"
},
  "geometry": {"coordinates":[45.9881,54.6974],"type":"Point"}
}