{
  "type": "Feature",
  "properties": {
    "gn:admin1_code":"52",
    "gn:asciiname":"Veryassko",
    "gn:country_code":"RU",
    "gn:dem":30,
    "gn:feature_class":"P",
    "gn:feature_code":"PPL",
    "gn:name":"Veryassko",
    "gn:population":0,
    "gn:timezone":"Europe/Moscow",
    "iso:country":"RU",
    "name:rus_x_preferred":[
        "\u0412\u0435\u0440\u044f\u0441\u0441\u043a\u043e"
    ],
    "wof:name":"Veryassko",
    "wof:placetype":"locality"
},
  "geometry": {"coordinates":[31.58028,57.71949],"type":"Point"}
}