{
  "type": "Feature",
  "properties": {
    "gn:admin1_code":"10",
    "gn:asciiname":"Shirkovka",
    "gn:country_code":"RU",
    "gn:dem":165,
    "gn:feature_class":"P",
    "gn:feature_code":"PPL",
    "gn:name":"Shirkovka",
    "gn:population":0,
    "gn:timezone":"Europe/Moscow",
    "iso:country":"RU",
    "name:eng_x_preferred":[
        "Shirkovka"
    ],
    "name:nor_x_preferred":[
        "Sjirkovka"
    ],
    "name:rus_x_preferred":[
        "\u0428\u0438\u0440\u043a\u043e\u0432\u043a\u0430"
    ],
    "name:und_x_variant":[
        "Bol\u2019shaya Shirkovka"
    ],
    "wof:name":"Shirkovka",
    "wof:placetype":"locality"
},
  "geometry": {"coordinates":[32.83939,53.32274],"type":"Point"}
}