{
  "type": "Feature",
  "properties": {
    "gn:admin1_code":"33",
    "gn:asciiname":"Kapustina",
    "gn:cc2":"RU",
    "gn:country_code":"RU",
    "gn:dem":158,
    "gn:feature_class":"P",
    "gn:feature_code":"PPL",
    "gn:name":"Kapustina",
    "gn:population":0,
    "gn:timezone":"Europe/Kirov",
    "iso:country":"RU",
    "name:rus_x_preferred":[
        "\u041a\u0430\u043f\u0443\u0441\u0442\u0438\u043d\u0430"
    ],
    "name:und_x_variant":[
        "Kapuyetina",
        "Kapustina",
        "\u041a\u0430\u043f\u0443\u0441\u0442\u0438\u043d\u0430"
    ],
    "wof:name":"Kapustina",
    "wof:placetype":"locality"
},
  "geometry": {"coordinates":[48.28333,60.06667],"type":"Point"}
}