{
  "type": "Feature",
  "properties": {
    "gn:admin1_code":"16.0",
    "gn:asciiname":"Bagishi",
    "gn:country_code":"RU",
    "gn:dem":127,
    "gn:feature_class":"P",
    "gn:feature_code":"PPL",
    "gn:name":"Bagishi",
    "gn:population":0,
    "gn:timezone":"Europe/Moscow",
    "iso:country":"RU",
    "name:rus_x_preferred":[
        "\u0411\u0430\u0433\u0438\u0448\u0438"
    ],
    "wof:name":"Bagishi",
    "wof:placetype":"locality"
},
  "geometry": {"coordinates":[46.5138,55.8086],"type":"Point"}
}