{
  "type": "Feature",
  "properties": {
    "gn:admin1_code":"21",
    "gn:asciiname":"Yelkhovo",
    "gn:country_code":"RU",
    "gn:dem":105,
    "gn:feature_class":"P",
    "gn:feature_code":"PPL",
    "gn:name":"Yelkhovo",
    "gn:population":0,
    "gn:timezone":"Europe/Moscow",
    "iso:country":"RU",
    "name:und_x_variant":[
        "Yelokhova",
        "Yelkhovo"
    ],
    "wof:name":"Yelkhovo",
    "wof:placetype":"locality"
},
  "geometry": {"coordinates":[40.99849,56.66085],"type":"Point"}
}