{
  "type": "Feature",
  "properties": {
    "gn:admin1_code":"33",
    "gn:asciiname":"Novinskaya Zapolitsa",
    "gn:country_code":"RU",
    "gn:dem":126,
    "gn:feature_class":"P",
    "gn:feature_code":"PPL",
    "gn:name":"Novinskaya Zapolitsa",
    "gn:population":0,
    "gn:timezone":"Europe/Kirov",
    "iso:country":"RU",
    "name:rus_x_preferred":[
        "\u041d\u043e\u0432\u0438\u043d\u0441\u043a\u0430\u044f \u0417\u0430\u043f\u043e\u043b\u0438\u0446\u0430"
    ],
    "wof:name":"Novinskaya Zapolitsa",
    "wof:placetype":"locality"
},
  "geometry": {"coordinates":[50.1595,57.7036],"type":"Point"}
}