{
  "type": "Feature",
  "properties": {
    "gn:admin1_code":"53",
    "gn:asciiname":"Seredino",
    "gn:country_code":"RU",
    "gn:dem":129,
    "gn:feature_class":"P",
    "gn:feature_code":"PPL",
    "gn:name":"Seredino",
    "gn:population":0,
    "gn:timezone":"Asia/Novosibirsk",
    "iso:country":"RU",
    "name:eng_x_preferred":[
        "Seredino"
    ],
    "name:nor_x_preferred":[
        "Seredino"
    ],
    "name:rus_x_preferred":[
        "\u0421\u0435\u0440\u0435\u0434\u0438\u043d\u043e"
    ],
    "name:und_x_variant":[
        "Seredina"
    ],
    "wof:name":"Seredino",
    "wof:placetype":"locality"
},
  "geometry": {"coordinates":[83.0795,55.7978],"type":"Point"}
}