{
  "type": "Feature",
  "properties": {
    "gn:admin1_code":"10",
    "gn:asciiname":"Rudnya",
    "gn:country_code":"RU",
    "gn:dem":205,
    "gn:feature_class":"P",
    "gn:feature_code":"PPL",
    "gn:name":"Rudnya",
    "gn:population":0,
    "gn:timezone":"Europe/Moscow",
    "iso:country":"RU",
    "name:rus_x_preferred":[
        "\u0420\u0443\u0434\u043d\u044f"
    ],
    "name:und_x_variant":[
        "\u0420\u0443\u0434\u043d\u044f"
    ],
    "wof:name":"Rudnya",
    "wof:placetype":"locality"
},
  "geometry": {"coordinates":[33.17569,52.80509],"type":"Point"}
}