{
  "type": "Feature",
  "properties": {
    "gn:admin1_code":"81",
    "gn:asciiname":"Salmanovka",
    "gn:country_code":"RU",
    "gn:dem":90,
    "gn:feature_class":"P",
    "gn:feature_code":"PPL",
    "gn:name":"Salmanovka",
    "gn:population":0,
    "gn:timezone":"Europe/Ulyanovsk",
    "iso:country":"RU",
    "name:eng_x_preferred":[
        "Salmanovka"
    ],
    "name:nor_x_preferred":[
        "Salmanovka"
    ],
    "name:rus_x_preferred":[
        "\u0421\u0430\u043b\u043c\u0430\u043d\u043e\u0432\u043a\u0430"
    ],
    "wof:name":"Salmanovka",
    "wof:placetype":"locality"
},
  "geometry": {"coordinates":[48.26681,54.47102],"type":"Point"}
}