{
  "type": "Feature",
  "properties": {
    "gn:admin1_code":"71",
    "gn:asciiname":"Verkhnyaya Plekhanova",
    "gn:country_code":"RU",
    "gn:dem":95,
    "gn:feature_class":"P",
    "gn:feature_code":"PPL",
    "gn:name":"Verkhnyaya Plekhanova",
    "gn:population":0,
    "gn:timezone":"Asia/Yekaterinburg",
    "iso:country":"RU",
    "name:rus_x_preferred":[
        "\u0412\u0435\u0440\u0445\u043d\u044f\u044f \u041f\u043b\u0435\u0445\u0430\u043d\u043e\u0432\u0430"
    ],
    "name:und_x_variant":[
        "\u0412\u0435\u0440\u0445\u043d\u044f\u044f \u041f\u043b\u0435\u0445\u0430\u043d\u043e\u0432\u0430"
    ],
    "wof:name":"Verkhnyaya Plekhanova",
    "wof:placetype":"locality"
},
  "geometry": {"coordinates":[64.05179,57.15163],"type":"Point"}
}