{
  "type": "Feature",
  "properties": {
    "gn:admin1_code":"8",
    "gn:asciiname":"Yermolkino",
    "gn:country_code":"RU",
    "gn:dem":255,
    "gn:feature_class":"P",
    "gn:feature_code":"PPL",
    "gn:name":"Yermolkino",
    "gn:population":0,
    "gn:timezone":"Asia/Yekaterinburg",
    "iso:country":"RU",
    "name:eng_x_preferred":[
        "Yermolkino"
    ],
    "name:nor_x_preferred":[
        "Jermolkino"
    ],
    "name:rus_x_preferred":[
        "\u0415\u0440\u043c\u043e\u043b\u043a\u0438\u043d\u043e"
    ],
    "name:und_x_variant":[
        "Yermolkina Adil\u2019kina",
        "Yermolkino",
        "\u0415\u0440\u043c\u043e\u043b\u043a\u0438\u043d\u043e"
    ],
    "wof:name":"Yermolkino",
    "wof:placetype":"locality"
},
  "geometry": {"coordinates":[53.912,54.18986999999999],"type":"Point"}
}