{
  "type": "Feature",
  "properties": {
    "gn:admin1_code":"8",
    "gn:asciiname":"Yermolkino",
    "gn:country_code":"RU",
    "gn:dem":255,
    "gn:feature_class":"P",
    "gn:feature_code":"PPL",
    "gn:name":"Yermolkino",
    "gn:population":0,
    "gn:timezone":"Asia/Yekaterinburg",
    "iso:country":"RU",
    "name:bak_x_preferred":[
        "\u0415\u0440\u043c\u043e\u043b\u043a\u0438\u043d"
    ],
    "name:che_x_preferred":[
        "\u0415\u0440\u043c\u043e\u043b\u043a\u0438\u043d\u043e"
    ],
    "name:chv_x_preferred":[
        "\u042f\u0440\u043c\u0443\u043b\u0430\u0439"
    ],
    "name:eng_x_preferred":[
        "Yermolkino"
    ],
    "name:hye_x_preferred":[
        "\u0535\u0580\u0574\u0578\u056c\u056f\u056b\u0576\u0578"
    ],
    "name:kaz_x_preferred":[
        "\u0415\u0440\u043c\u043e\u043b\u043a\u0438\u043d\u043e"
    ],
    "name:kir_x_preferred":[
        "\u0415\u0440\u043c\u043e\u043b\u043a\u0438\u043d\u043e"
    ],
    "name:nor_x_preferred":[
        "Jermolkino"
    ],
    "name:rus_x_preferred":[
        "\u0415\u0440\u043c\u043e\u043b\u043a\u0438\u043d\u043e"
    ],
    "name:tat_x_preferred":[
        "\u042f\u0440\u043c\u0443\u043b\u0430\u0439"
    ],
    "name:ukr_x_preferred":[
        "\u0404\u0440\u043c\u043e\u043b\u043a\u0456\u043d\u043e"
    ],
    "name:und_x_variant":[
        "Yermolkina Adil\u2019kina",
        "Yermolkino",
        "\u0415\u0440\u043c\u043e\u043b\u043a\u0438\u043d\u043e"
    ],
    "wof:name":"Yermolkino",
    "wof:placetype":"locality"
},
  "geometry": {"coordinates":[53.912,54.18986999999999],"type":"Point"}
}