{
  "type": "Feature",
  "properties": {
    "gn:country":"RU",
    "gn:fcode":"PPL",
    "gn:population":0,
    "iso:country":"RU",
    "name:eng_x_preferred":[
        "Atyur'yevo"
    ],
    "name:nor_x_preferred":[
        "Atjurjevo"
    ],
    "name:rus_x_preferred":[
        "\u0410\u0442\u044e\u0440\u044c\u0435\u0432\u043e"
    ],
    "qs:name":"Atyur'yevo",
    "qs:name_adm0":"Russia",
    "qs:name_adm1":"Mordovia Republic",
    "qs:photos_9r":0,
    "qs:photos_sr":0,
    "qs:placetype":"Town",
    "qs:pop_sr":"4",
    "wof:name":"Atyur'yevo",
    "wof:placetype":"locality",
    "wof:population":0
},
  "geometry": {"coordinates":[43.33957,54.3229],"type":"Point"}
}