{
  "type": "Feature",
  "properties": {
    "gn:admin1_code":"65",
    "gn:asciiname":"Klinovskiy",
    "gn:country_code":"RU",
    "gn:dem":118,
    "gn:feature_class":"P",
    "gn:feature_code":"PPL",
    "gn:name":"Klinovskiy",
    "gn:population":0,
    "gn:timezone":"Europe/Samara",
    "iso:country":"RU",
    "name:rus_x_preferred":[
        "\u041a\u043b\u0438\u043d\u043e\u0432\u0441\u043a\u0438\u0439"
    ],
    "wof:name":"Klinovskiy",
    "wof:placetype":"locality"
},
  "geometry": {"coordinates":[51.0331,54.4584],"type":"Point"}
}