{
  "type": "Feature",
  "properties": {
    "gn:country":"RU",
    "gn:fcode":"PPL",
    "gn:population":0,
    "iso:country":"RU",
    "name:eng_x_preferred":[
        "Spas-Zaulok"
    ],
    "name:nor_x_preferred":[
        "Spas-Zaulok"
    ],
    "name:rus_x_preferred":[
        "\u0421\u043f\u0430\u0441-\u0417\u0430\u0443\u043b\u043e\u043a"
    ],
    "name:und_x_variant":[
        "Spas-Zavlok"
    ],
    "qs:name":"Spas-Zaulok",
    "qs:name_adm0":"Russia",
    "qs:name_adm1":"Moscow Oblast",
    "qs:photos_9k":1,
    "qs:photos_9r":1,
    "qs:photos_all":2,
    "qs:photos_sr":0,
    "qs:placetype":"Town",
    "qs:pop_sr":"0",
    "wof:name":"Spas-Zaulok",
    "wof:placetype":"locality",
    "wof:population":0
},
  "geometry": {"coordinates":[36.56667,56.48333],"type":"Point"}
}