{
  "type": "Feature",
  "properties": {
    "gn:admin1_code":"77.0",
    "gn:asciiname":"Dulovo",
    "gn:country_code":"RU",
    "gn:dem":78,
    "gn:feature_class":"P",
    "gn:feature_code":"PPL",
    "gn:name":"Dulovo",
    "gn:population":0,
    "gn:timezone":"Europe/Moscow",
    "iso:country":"RU",
    "name:ceb_x_preferred":[
        "Dulovo"
    ],
    "name:epo_x_preferred":[
        "Dulovo"
    ],
    "name:fra_x_preferred":[
        "Dulovo"
    ],
    "name:ita_x_preferred":[
        "Dulovo"
    ],
    "name:jpn_x_preferred":[
        "\u30c9\u30a5\u30ed\u30f4\u30a9"
    ],
    "name:por_x_preferred":[
        "Dulovo"
    ],
    "name:rus_x_preferred":[
        "\u0414\u0443\u043b\u043e\u0432\u043e"
    ],
    "name:slk_x_preferred":[
        "Dulovo"
    ],
    "name:srp_x_preferred":[
        "\u0414\u0443\u043b\u043e\u0432\u043e"
    ],
    "name:swe_x_preferred":[
        "Dulovo"
    ],
    "name:und_x_variant":[
        "\u0414\u0443\u043b\u043e\u0432\u043e"
    ],
    "wof:name":"Dulovo",
    "wof:placetype":"locality"
},
  "geometry": {"coordinates":[30.88333,56.88333000000001],"type":"Point"}
}