{
  "type": "Feature",
  "properties": {
    "gn:admin1_code":"54",
    "gn:asciiname":"Tumba",
    "gn:country_code":"RU",
    "gn:dem":96,
    "gn:feature_class":"P",
    "gn:feature_code":"PPL",
    "gn:name":"Tumba",
    "gn:population":0,
    "gn:timezone":"Asia/Omsk",
    "iso:country":"RU",
    "name:ceb_x_preferred":[
        "Tumba"
    ],
    "name:ces_x_preferred":[
        "Tumba"
    ],
    "name:deu_x_preferred":[
        "Tumba"
    ],
    "name:eng_x_preferred":[
        "Tumba"
    ],
    "name:fin_x_preferred":[
        "Tumba"
    ],
    "name:fra_x_preferred":[
        "Tumba"
    ],
    "name:hrv_x_preferred":[
        "Tumba"
    ],
    "name:ita_x_preferred":[
        "Tumba"
    ],
    "name:lat_x_preferred":[
        "Tumba"
    ],
    "name:lav_x_preferred":[
        "Tumba"
    ],
    "name:nld_x_preferred":[
        "Tumba"
    ],
    "name:nor_x_preferred":[
        "Tumba"
    ],
    "name:pol_x_preferred":[
        "Tumba"
    ],
    "name:rus_x_preferred":[
        "\u0422\u0443\u043c\u0431\u0430"
    ],
    "name:slk_x_preferred":[
        "Tumba"
    ],
    "name:swe_x_preferred":[
        "Tumba"
    ],
    "wof:name":"Tumba",
    "wof:placetype":"locality"
},
  "geometry": {"coordinates":[71.73538000000001,54.73268],"type":"Point"}
}