{
  "type": "Feature",
  "properties": {
    "gn:admin1_code":"34.0",
    "gn:asciiname":"Churkin-Yag",
    "gn:country_code":"RU",
    "gn:dem":55,
    "gn:feature_class":"P",
    "gn:feature_code":"PPL",
    "gn:name":"Churkin-Yag",
    "gn:population":0,
    "gn:timezone":"Europe/Moscow",
    "iso:country":"RU",
    "name:rus_x_preferred":[
        "\u0427\u0443\u0440\u043a\u0438\u043d-\u042f\u0433"
    ],
    "wof:name":"Churkin-Yag",
    "wof:placetype":"locality"
},
  "geometry": {"coordinates":[57.63333000000001,64.93333],"type":"Point"}
}