{
  "type": "Feature",
  "properties": {
    "gn:admin1_code":"62",
    "gn:asciiname":"Malyy Prolom",
    "gn:country_code":"RU",
    "gn:dem":149,
    "gn:feature_class":"P",
    "gn:feature_code":"PPL",
    "gn:name":"Malyy Prolom",
    "gn:population":0,
    "gn:timezone":"Europe/Moscow",
    "iso:country":"RU",
    "name:rus_x_preferred":[
        "\u041c\u0430\u043b\u044b\u0439 \u041f\u0440\u043e\u043b\u043e\u043c"
    ],
    "name:und_x_variant":[
        "Maly Prolom",
        "Malyy Prolom"
    ],
    "wof:name":"Malyy Prolom",
    "wof:placetype":"locality"
},
  "geometry": {"coordinates":[41.70096,54.07421],"type":"Point"}
}