{
  "type": "Feature",
  "properties": {
    "gn:admin1_code":"77",
    "gn:asciiname":"Novomikhnevo",
    "gn:country_code":"RU",
    "gn:dem":144,
    "gn:feature_class":"P",
    "gn:feature_code":"PPL",
    "gn:name":"Novomikhn\u00ebvo",
    "gn:population":0,
    "gn:timezone":"Europe/Moscow",
    "iso:country":"RU",
    "name:rus_x_preferred":[
        "\u041d\u043e\u0432\u043e\u043c\u0438\u0445\u043d\u0451\u0432\u043e"
    ],
    "name:und_x_variant":[
        "Novomikhn\u00ebvo",
        "\u041d\u043e\u0432\u043e\u043c\u0438\u0445\u043d\u0451\u0432\u043e"
    ],
    "wof:name":"Novomikhnevo",
    "wof:placetype":"locality"
},
  "geometry": {"coordinates":[36.17048,57.18878],"type":"Point"}
}