{
  "type": "Feature",
  "properties": {
    "gn:admin1_code":"75",
    "gn:asciiname":"Sto Sem'desyat Chetvertyy Kilometr",
    "gn:country_code":"RU",
    "gn:dem":138,
    "gn:feature_class":"P",
    "gn:feature_code":"PPL",
    "gn:name":"Sto Sem\u2019desyat Chetv\u00ebrtyy Kilometr",
    "gn:population":0,
    "gn:timezone":"Asia/Tomsk",
    "iso:country":"RU",
    "name:rus_x_preferred":[
        "\u0421\u0442\u043e \u0421\u0435\u043c\u044c\u0434\u0435\u0441\u044f\u0442 \u0427\u0435\u0442\u0432\u0451\u0440\u0442\u044b\u0439 \u041a\u0438\u043b\u043e\u043c\u0435\u0442\u0440"
    ],
    "name:und_x_variant":[
        "Sto Sem\u2019desyat Chetv\u00ebrtyy Kilometr"
    ],
    "wof:name":"Sto Sem'desyat Chetvertyy Kilometr",
    "wof:placetype":"locality"
},
  "geometry": {"coordinates":[86.0856,56.9549],"type":"Point"}
}