{
  "type": "Feature",
  "properties": {
    "gn:admin1_code":"55",
    "gn:asciiname":"Turgay",
    "gn:country_code":"RU",
    "gn:dem":144,
    "gn:feature_class":"P",
    "gn:feature_code":"PPL",
    "gn:name":"Turgay",
    "gn:population":0,
    "gn:timezone":"Europe/Samara",
    "iso:country":"RU",
    "name:ara_x_preferred":[
        "\u062a\u0648\u0631\u063a\u0627\u064a"
    ],
    "name:ben_x_preferred":[
        "\u09a4\u09c1\u09b0\u09cd\u0997\u09c7"
    ],
    "name:ceb_x_preferred":[
        "Turgay"
    ],
    "name:deu_x_preferred":[
        "Turgai"
    ],
    "name:deu_x_variant":[
        "Turgay"
    ],
    "name:ell_x_preferred":[
        "\u03a4\u03bf\u03c5\u03c1\u03b3\u03ba\u03ac\u03b9"
    ],
    "name:fas_x_preferred":[
        "\u062a\u0648\u0631\u06af\u0627\u06cc"
    ],
    "name:fra_x_preferred":[
        "Turgay"
    ],
    "name:heb_x_preferred":[
        "\u05d8\u05d5\u05e8\u05d2\u05d9\u05d9"
    ],
    "name:hin_x_preferred":[
        "\u091f\u0941\u0930\u094d\u0917\u0947"
    ],
    "name:hun_x_preferred":[
        "Turgay"
    ],
    "name:ind_x_preferred":[
        "Turgay"
    ],
    "name:ita_x_preferred":[
        "Turgay"
    ],
    "name:jpn_x_preferred":[
        "\u30bf\u30fc\u30b2\u30a4"
    ],
    "name:kor_x_preferred":[
        "\ud22c\ub974\uac00\uc774"
    ],
    "name:por_x_preferred":[
        "Turgay"
    ],
    "name:rus_x_preferred":[
        "\u0422\u0443\u0440\u0433\u0430\u0439"
    ],
    "name:spa_x_preferred":[
        "Turgai"
    ],
    "name:swe_x_preferred":[
        "Turgay"
    ],
    "name:tur_x_preferred":[
        "Turgay"
    ],
    "name:urd_x_preferred":[
        "\u0679\u0631\u06af\u06d2"
    ],
    "name:vie_x_preferred":[
        "Turgay"
    ],
    "name:zho_cn_x_preferred":[
        "\u56fe\u5c14\u76d6"
    ],
    "name:zho_tw_x_preferred":[
        "\u5716\u723e\u84cb"
    ],
    "wof:name":"Turgay",
    "wof:placetype":"locality"
},
  "geometry": {"coordinates":[52.44637,54.09976],"type":"Point"}
}