{
  "type": "Feature",
  "properties": {
    "gn:admin1_code":"55",
    "gn:asciiname":"Turgay",
    "gn:country_code":"RU",
    "gn:dem":144,
    "gn:feature_class":"P",
    "gn:feature_code":"PPL",
    "gn:name":"Turgay",
    "gn:population":0,
    "gn:timezone":"Europe/Samara",
    "iso:country":"RU",
    "name:rus_x_preferred":[
        "\u0422\u0443\u0440\u0433\u0430\u0439"
    ],
    "name:und_x_variant":[
        "\u0422\u0443\u0440\u0433\u0430\u0439"
    ],
    "wof:name":"Turgay",
    "wof:placetype":"locality"
},
  "geometry": {"coordinates":[52.44637,54.09976],"type":"Point"}
}