{
  "type": "Feature",
  "properties": {
    "gn:admin1_code":"70.0",
    "gn:asciiname":"Dovlatkin",
    "gn:country_code":"RU",
    "gn:dem":127,
    "gn:feature_class":"P",
    "gn:feature_code":"PPL",
    "gn:name":"Dovlatkin",
    "gn:population":0,
    "gn:timezone":"Europe/Moscow",
    "iso:country":"RU",
    "name:rus_x_preferred":[
        "\u0414\u043e\u0432\u043b\u0430\u0442\u043a\u0438\u043d"
    ],
    "wof:name":"Dovlatkin",
    "wof:placetype":"locality"
},
  "geometry": {"coordinates":[44.84056,43.89083],"type":"Point"}
}