{
  "type": "Feature",
  "properties": {
    "gn:admin1_code":"80.0",
    "gn:asciiname":"Doma 5 km",
    "gn:country_code":"RU",
    "gn:dem":165,
    "gn:feature_class":"P",
    "gn:feature_code":"PPL",
    "gn:name":"Doma 5 km",
    "gn:population":0,
    "gn:timezone":"Europe/Samara",
    "iso:country":"RU",
    "name:rus_x_preferred":[
        "\u0414\u043e\u043c\u0430 5 \u043a\u043c"
    ],
    "wof:name":"Doma 5 km",
    "wof:placetype":"locality"
},
  "geometry": {"coordinates":[53.2835,57.8295],"type":"Point"}
}