{
  "type": "Feature",
  "properties": {
    "gn:admin1_code":"21.0",
    "gn:asciiname":"Avdot'ino",
    "gn:country_code":"RU",
    "gn:dem":130,
    "gn:feature_class":"P",
    "gn:feature_code":"PPL",
    "gn:name":"Avdot\u2019ino",
    "gn:population":0,
    "gn:timezone":"Europe/Moscow",
    "iso:country":"RU",
    "name:nor_x_preferred":[
        "Avdotino"
    ],
    "name:rus_x_preferred":[
        "\u0410\u0432\u0434\u043e\u0442\u044c\u0438\u043d\u043e"
    ],
    "name:und_x_variant":[
        "Avdot\u2019ino"
    ],
    "wof:name":"Avdot'ino",
    "wof:placetype":"locality"
},
  "geometry": {"coordinates":[40.92139,57.0375],"type":"Point"}
}