{
  "type": "Feature",
  "properties": {
    "gn:admin1_code":"45",
    "gn:asciiname":"Malyy Sermananger",
    "gn:country_code":"RU",
    "gn:dem":145,
    "gn:feature_class":"P",
    "gn:feature_code":"PPL",
    "gn:name":"Malyy Sermananger",
    "gn:population":0,
    "gn:timezone":"Europe/Moscow",
    "iso:country":"RU",
    "name:rus_x_preferred":[
        "\u041c\u0430\u043b\u044b\u0439 \u0421\u0435\u0440\u043c\u0430\u043d\u0430\u043d\u0433\u0435\u0440"
    ],
    "name:und_x_variant":[
        "Malyy Sermanger"
    ],
    "wof:name":"Malyy Sermananger",
    "wof:placetype":"locality"
},
  "geometry": {"coordinates":[46.66,56.1821],"type":"Point"}
}