{
  "type": "Feature",
  "properties": {
    "gn:admin1_code":"69",
    "gn:asciiname":"Mileyevo",
    "gn:country_code":"RU",
    "gn:dem":221,
    "gn:feature_class":"P",
    "gn:feature_code":"PPL",
    "gn:name":"Mileyevo",
    "gn:population":0,
    "gn:timezone":"Europe/Moscow",
    "iso:country":"RU",
    "name:rus_x_preferred":[
        "\u041c\u0438\u043b\u0435\u0435\u0432\u043e"
    ],
    "wof:name":"Mileyevo",
    "wof:placetype":"locality"
},
  "geometry": {"coordinates":[33.06944,54.5256],"type":"Point"}
}