{
  "type": "Feature",
  "properties": {
    "gn:admin1_code":"20.0",
    "gn:asciiname":"Neftebaza",
    "gn:country_code":"RU",
    "gn:dem":391,
    "gn:feature_class":"P",
    "gn:feature_code":"PPL",
    "gn:name":"Neftebaza",
    "gn:population":0,
    "gn:timezone":"Asia/Irkutsk",
    "iso:country":"RU",
    "name:rus_x_preferred":[
        "\u041d\u0435\u0444\u0442\u0435\u0431\u0430\u0437\u0430"
    ],
    "wof:name":"Neftebaza",
    "wof:placetype":"locality"
},
  "geometry": {"coordinates":[103.22199999999999,53.8809],"type":"Point"}
}