{
  "type": "Feature",
  "properties": {
    "gn:admin1_code":"37",
    "gn:asciiname":"Zhemchugovo",
    "gn:country_code":"RU",
    "gn:dem":137,
    "gn:feature_class":"P",
    "gn:feature_code":"PPL",
    "gn:name":"Zhemchugovo",
    "gn:population":0,
    "gn:timezone":"Europe/Moscow",
    "iso:country":"RU",
    "name:rus_x_preferred":[
        "\u0416\u0435\u043c\u0447\u0443\u0433\u043e\u0432\u043e"
    ],
    "name:und_x_variant":[
        "\u0416\u0435\u043c\u0447\u0443\u0433\u043e\u0432\u043e",
        "Zhemchugova"
    ],
    "wof:name":"Zhemchugovo",
    "wof:placetype":"locality"
},
  "geometry": {"coordinates":[43.6913,58.05433000000001],"type":"Point"}
}