{
  "type": "Feature",
  "properties": {
    "iso:country":"RU",
    "name:ces_x_preferred":[
        "Moskovskaja"
    ],
    "name:deu_x_preferred":[
        "Moskowskaja"
    ],
    "name:epo_x_preferred":[
        "Moskovskaja"
    ],
    "name:ita_x_preferred":[
        "Moskovskaja"
    ],
    "name:nld_x_preferred":[
        "Moskovskaja"
    ],
    "name:rus_x_preferred":[
        "\u041c\u043e\u0441\u043a\u043e\u0432\u0441\u043a\u0438\u0439"
    ],
    "name:rus_x_variant":[
        "\u041c\u043e\u0441\u043a\u043e\u0432\u0441\u043a\u0430\u044f"
    ],
    "name:vie_x_preferred":[
        "Moskovsky"
    ],
    "wof:name":"Moskovsky",
    "wof:placetype":"neighbourhood"
},
  "geometry": {"coordinates":[37.35094725325517,55.60227171383454],"type":"Point"}
}