{
  "type": "Feature",
  "properties": {
    "gn:admin1_code":"73.0",
    "gn:asciiname":"Bol'shiye Achasyry",
    "gn:country_code":"RU",
    "gn:dem":139,
    "gn:feature_class":"P",
    "gn:feature_code":"PPL",
    "gn:name":"Bol\u2019shiye Achasyry",
    "gn:population":0,
    "gn:timezone":"Europe/Moscow",
    "iso:country":"RU",
    "name:rus_x_preferred":[
        "Bol\u2019shiye Achasyry"
    ],
    "name:rus_x_variant":[
        "\u0411\u043e\u043b\u044c\u0448\u0438\u0435 \u0410\u0447\u0430\u0441\u044b\u0440\u044b",
        "Bol\u2019shiye Achasyr"
    ],
    "wof:name":"Bol'shiye Achasyry",
    "wof:placetype":"locality"
},
  "geometry": {"coordinates":[48.34379000000001,55.70936999999999],"type":"Point"}
}