{
  "type": "Feature",
  "properties": {
    "gn:admin1_code":"77.0",
    "gn:asciiname":"Bukholovo",
    "gn:country_code":"RU",
    "gn:dem":235,
    "gn:feature_class":"P",
    "gn:feature_code":"PPL",
    "gn:name":"Bukholovo",
    "gn:population":0,
    "gn:timezone":"Europe/Moscow",
    "iso:country":"RU",
    "name:rus_x_preferred":[
        "\u0411\u0443\u0445\u043e\u043b\u043e\u0432\u043e"
    ],
    "wof:name":"Bukholovo",
    "wof:placetype":"locality"
},
  "geometry": {"coordinates":[33.53333,57.56667],"type":"Point"}
}