{
  "type": "Feature",
  "properties": {
    "gn:admin1_code":"10",
    "gn:asciiname":"Chekhov",
    "gn:country_code":"RU",
    "gn:dem":137,
    "gn:feature_class":"P",
    "gn:feature_code":"PPL",
    "gn:name":"Chekhov",
    "gn:population":0,
    "gn:timezone":"Europe/Moscow",
    "iso:country":"RU",
    "name:rus_x_preferred":[
        "\u0427\u0435\u0445\u043e\u0432"
    ],
    "wof:name":"Chekhov",
    "wof:placetype":"locality"
},
  "geometry": {"coordinates":[31.6061,52.4328],"type":"Point"}
}