{
  "type": "Feature",
  "properties": {
    "gn:admin1_code":"70",
    "gn:asciiname":"Maki",
    "gn:country_code":"RU",
    "gn:dem":57,
    "gn:feature_class":"P",
    "gn:feature_code":"PPL",
    "gn:name":"Maki",
    "gn:population":0,
    "gn:timezone":"Europe/Moscow",
    "iso:country":"RU",
    "name:rus_x_preferred":[
        "\u041c\u0430\u043a\u0438"
    ],
    "name:und_x_variant":[
        "\u041c\u0430\u043a\u0438"
    ],
    "wof:name":"Maki",
    "wof:placetype":"locality"
},
  "geometry": {"coordinates":[43.20722,46.00556],"type":"Point"}
}