{
  "type": "Feature",
  "properties": {
    "gn:admin1_code":"70",
    "gn:asciiname":"Maki",
    "gn:country_code":"RU",
    "gn:dem":57,
    "gn:feature_class":"P",
    "gn:feature_code":"PPL",
    "gn:name":"Maki",
    "gn:population":0,
    "gn:timezone":"Europe/Moscow",
    "iso:country":"RU",
    "name:ara_x_preferred":[
        "\u0645\u0627\u0643\u064a"
    ],
    "name:cat_x_preferred":[
        "Maki"
    ],
    "name:ceb_x_preferred":[
        "Maki"
    ],
    "name:ces_x_preferred":[
        "Maki"
    ],
    "name:dan_x_preferred":[
        "Maki"
    ],
    "name:deu_x_preferred":[
        "Maki"
    ],
    "name:eus_x_preferred":[
        "Maki"
    ],
    "name:fas_x_preferred":[
        "\u0645\u06a9\u06cc"
    ],
    "name:fin_x_preferred":[
        "Maki"
    ],
    "name:fra_x_preferred":[
        "Maki"
    ],
    "name:ind_x_preferred":[
        "Maki"
    ],
    "name:ita_x_preferred":[
        "Maki"
    ],
    "name:pol_x_preferred":[
        "Maki"
    ],
    "name:por_x_preferred":[
        "Maki"
    ],
    "name:rus_x_preferred":[
        "\u041c\u0430\u043a\u0438"
    ],
    "name:spa_x_preferred":[
        "Maki"
    ],
    "name:swe_x_preferred":[
        "Maki"
    ],
    "wof:name":"Maki",
    "wof:placetype":"locality"
},
  "geometry": {"coordinates":[43.20722,46.00556],"type":"Point"}
}