{
  "type": "Feature",
  "properties": {
    "gn:admin1_code":"8",
    "gn:asciiname":"Balyklybashevo",
    "gn:country_code":"RU",
    "gn:dem":312,
    "gn:feature_class":"P",
    "gn:feature_code":"PPL",
    "gn:name":"Balyklybashevo",
    "gn:population":0,
    "gn:timezone":"Asia/Yekaterinburg",
    "iso:country":"RU",
    "name:rus_x_preferred":[
        "\u0411\u0430\u043b\u044b\u043a\u043b\u044b\u0431\u0430\u0448\u0435\u0432\u043e"
    ],
    "wof:name":"Balyklybashevo",
    "wof:placetype":"locality"
},
  "geometry": {"coordinates":[55.1852,53.1211],"type":"Point"}
}