{
  "type": "Feature",
  "properties": {
    "gn:admin1_code":"37",
    "gn:asciiname":"Yur'yevka",
    "gn:country_code":"RU",
    "gn:dem":118,
    "gn:feature_class":"P",
    "gn:feature_code":"PPL",
    "gn:name":"Yur\u2019yevka",
    "gn:population":0,
    "gn:timezone":"Europe/Moscow",
    "iso:country":"RU",
    "name:und_x_variant":[
        "Yuryavets",
        "Yur\u2019yevets",
        "Yur\u2019yevo",
        "Yur\u2019yevka"
    ],
    "wof:name":"Yur'yevka",
    "wof:placetype":"locality"
},
  "geometry": {"coordinates":[41.03161,57.66514],"type":"Point"}
}