{
  "type": "Feature",
  "properties": {
    "gn:admin1_code":"61",
    "gn:asciiname":"Gok",
    "gn:country_code":"RU",
    "gn:dem":59,
    "gn:feature_class":"P",
    "gn:feature_code":"PPL",
    "gn:name":"Gok",
    "gn:population":0,
    "gn:timezone":"Europe/Moscow",
    "iso:country":"RU",
    "name:rus_x_preferred":[
        "\u0413\u043e\u043a"
    ],
    "wof:name":"Gok",
    "wof:placetype":"locality"
},
  "geometry": {"coordinates":[41.5577,45.9879],"type":"Point"}
}