{
  "type": "Feature",
  "properties": {
    "gn:admin1_code":"77",
    "gn:asciiname":"Lazutino",
    "gn:country_code":"RU",
    "gn:dem":206,
    "gn:feature_class":"P",
    "gn:feature_code":"PPL",
    "gn:name":"Lazutino",
    "gn:population":0,
    "gn:timezone":"Europe/Moscow",
    "iso:country":"RU",
    "name:rus_x_preferred":[
        "\u041b\u0430\u0437\u0443\u0442\u0438\u043d\u043e"
    ],
    "name:und_x_variant":[
        "\u041b\u0430\u0437\u0443\u0442\u0438\u043d\u043e"
    ],
    "wof:name":"Lazutino",
    "wof:placetype":"locality"
},
  "geometry": {"coordinates":[34.91667,57.06667],"type":"Point"}
}