{
  "type": "Feature",
  "properties": {
    "gn:admin1_code":"51",
    "gn:asciiname":"Lisenki",
    "gn:country_code":"RU",
    "gn:dem":78,
    "gn:feature_class":"P",
    "gn:feature_code":"PPL",
    "gn:name":"Lisenki",
    "gn:population":0,
    "gn:timezone":"Europe/Moscow",
    "iso:country":"RU",
    "name:nor_x_preferred":[
        "Lisenki"
    ],
    "name:rus_x_preferred":[
        "\u041b\u0438\u0441\u0435\u043d\u043a\u0438"
    ],
    "name:und_x_variant":[
        "Lysenki"
    ],
    "wof:name":"Lisenki",
    "wof:placetype":"locality"
},
  "geometry": {"coordinates":[42.95348,56.13742],"type":"Point"}
}