{
  "type": "Feature",
  "properties": {
    "gn:admin1_code":"88",
    "gn:asciiname":"Proshevo",
    "gn:country_code":"RU",
    "gn:dem":101,
    "gn:feature_class":"P",
    "gn:feature_code":"PPL",
    "gn:name":"Proshevo",
    "gn:population":0,
    "gn:timezone":"Europe/Moscow",
    "iso:country":"RU",
    "name:rus_x_preferred":[
        "\u041f\u0440\u043e\u0448\u0435\u0432\u043e"
    ],
    "wof:name":"Proshevo",
    "wof:placetype":"locality"
},
  "geometry": {"coordinates":[39.7262,57.81],"type":"Point"}
}