{
  "type": "Feature",
  "properties": {
    "gn:admin1_code":"69",
    "gn:asciiname":"Ardenevo",
    "gn:country_code":"RU",
    "gn:dem":208,
    "gn:feature_class":"P",
    "gn:feature_code":"PPL",
    "gn:name":"Ardenevo",
    "gn:population":0,
    "gn:timezone":"Europe/Moscow",
    "iso:country":"RU",
    "name:nor_x_preferred":[
        "Ardenevo"
    ],
    "name:rus_x_preferred":[
        "\u0410\u0440\u0434\u0435\u043d\u0435\u0432\u043e"
    ],
    "wof:name":"Ardenevo",
    "wof:placetype":"locality"
},
  "geometry": {"coordinates":[34.94546,55.4242],"type":"Point"}
}