{
  "type": "Feature",
  "properties": {
    "gn:admin1_code":"60",
    "gn:asciiname":"Zapryagayevo",
    "gn:country_code":"RU",
    "gn:dem":80,
    "gn:feature_class":"P",
    "gn:feature_code":"PPL",
    "gn:name":"Zapryagayevo",
    "gn:population":0,
    "gn:timezone":"Europe/Moscow",
    "iso:country":"RU",
    "name:rus_x_preferred":[
        "\u0417\u0430\u043f\u0440\u044f\u0433\u0430\u0435\u0432\u043e"
    ],
    "wof:name":"Zapryagayevo",
    "wof:placetype":"locality"
},
  "geometry": {"coordinates":[28.57022000000001,56.99753000000001],"type":"Point"}
}