{
  "type": "Feature",
  "properties": {
    "gn:admin1_code":"87",
    "gn:asciiname":"Azyal-Gort",
    "gn:country_code":"RU",
    "gn:dem":28,
    "gn:feature_class":"P",
    "gn:feature_code":"PPL",
    "gn:name":"Azyal-Gort",
    "gn:population":0,
    "gn:timezone":"Asia/Yekaterinburg",
    "iso:country":"RU",
    "name:nor_x_preferred":[
        "Azial-Gort"
    ],
    "name:rus_x_preferred":[
        "\u0410\u0437\u044f\u043b-\u0413\u043e\u0440\u0442"
    ],
    "name:und_x_variant":[
        "Azyap-Gort",
        "Azyal-Gort"
    ],
    "wof:name":"Azyal-Gort",
    "wof:placetype":"locality"
},
  "geometry": {"coordinates":[67.08333,64.81667],"type":"Point"}
}