{
  "type": "Feature",
  "properties": {
    "gn:admin1_code":"76",
    "gn:asciiname":"Bakhtino-Fomino",
    "gn:country_code":"RU",
    "gn:dem":160,
    "gn:feature_class":"P",
    "gn:feature_code":"PPL",
    "gn:name":"Bakhtino-Fomino",
    "gn:population":0,
    "gn:timezone":"Europe/Moscow",
    "iso:country":"RU",
    "name:nor_x_preferred":[
        "Bakhtino-Fomino"
    ],
    "name:rus_x_preferred":[
        "\u0411\u0430\u0445\u0442\u0438\u043d\u043e-\u0424\u043e\u043c\u0438\u043d\u043e"
    ],
    "name:und_x_variant":[
        "Fominovka"
    ],
    "wof:name":"Bakhtino-Fomino",
    "wof:placetype":"locality"
},
  "geometry": {"coordinates":[38.53911,53.80093000000001],"type":"Point"}
}