{
  "type": "Feature",
  "properties": {
    "gn:admin1_code":"28",
    "gn:asciiname":"Pertozero",
    "gn:country_code":"RU",
    "gn:dem":30,
    "gn:feature_class":"P",
    "gn:feature_code":"PPL",
    "gn:name":"Pertozero",
    "gn:population":0,
    "gn:timezone":"Europe/Moscow",
    "iso:country":"RU",
    "name:rus_x_preferred":[
        "\u041f\u0435\u0440\u0442\u043e\u0437\u0435\u0440\u043e"
    ],
    "name:und_x_variant":[
        "\u041f\u0435\u0440\u0442\u043e\u0437\u0435\u0440\u043e"
    ],
    "wof:name":"Pertozero",
    "wof:placetype":"locality"
},
  "geometry": {"coordinates":[35.61667,64.18333],"type":"Point"}
}