{
  "type": "Feature",
  "properties": {
    "gn:admin1_code":"85",
    "gn:asciiname":"Yurmanga",
    "gn:country_code":"RU",
    "gn:dem":137,
    "gn:feature_class":"P",
    "gn:feature_code":"PPL",
    "gn:name":"Yurmanga",
    "gn:population":0,
    "gn:timezone":"Europe/Moscow",
    "iso:country":"RU",
    "name:eng_x_preferred":[
        "Yurmanga"
    ],
    "name:nor_x_preferred":[
        "Jurmanga"
    ],
    "name:rus_x_preferred":[
        "\u042e\u0440\u043c\u0430\u043d\u0433\u0430"
    ],
    "wof:name":"Yurmanga",
    "wof:placetype":"locality"
},
  "geometry": {"coordinates":[43.11813,59.78464],"type":"Point"}
}