{
  "type": "Feature",
  "properties": {
    "gn:admin1_code":"21.0",
    "gn:asciiname":"Fefelovka",
    "gn:country_code":"RU",
    "gn:dem":128,
    "gn:feature_class":"P",
    "gn:feature_code":"PPL",
    "gn:name":"Fefelovka",
    "gn:population":0,
    "gn:timezone":"Europe/Moscow",
    "iso:country":"RU",
    "name:rus_x_preferred":[
        "\u0424\u0435\u0444\u0435\u043b\u043e\u0432\u043a\u0430"
    ],
    "name:und_x_variant":[
        "Feofilovka",
        "Fefelovka",
        "\u0424\u0435\u0444\u0435\u043b\u043e\u0432\u043a\u0430"
    ],
    "wof:name":"Fefelovka",
    "wof:placetype":"locality"
},
  "geometry": {"coordinates":[41.88288,57.52244],"type":"Point"}
}