{
  "type": "Feature",
  "properties": {
    "gn:admin1_code":"55.0",
    "gn:asciiname":"Akchura",
    "gn:country_code":"RU",
    "gn:dem":249,
    "gn:feature_class":"P",
    "gn:feature_code":"PPL",
    "gn:name":"Akchura",
    "gn:population":0,
    "gn:timezone":"Asia/Yekaterinburg",
    "iso:country":"RU",
    "name:eng_x_preferred":[
        "Akchura"
    ],
    "name:nor_x_preferred":[
        "Aktsjura"
    ],
    "name:rus_x_preferred":[
        "\u0410\u043a\u0447\u0443\u0440\u0430"
    ],
    "name:und_x_variant":[
        "Bol\u2019shoye Akchurino",
        "Akchurina"
    ],
    "wof:name":"Akchura",
    "wof:placetype":"locality"
},
  "geometry": {"coordinates":[57.5124,51.6972],"type":"Point"}
}