{
  "type": "Feature",
  "properties": {
    "gn:admin1_code":"88",
    "gn:asciiname":"Kotovo",
    "gn:country_code":"RU",
    "gn:dem":128,
    "gn:feature_class":"P",
    "gn:feature_code":"PPL",
    "gn:name":"Kotovo",
    "gn:population":0,
    "gn:timezone":"Europe/Moscow",
    "iso:country":"RU",
    "name:hye_x_preferred":[
        "\u053f\u0578\u057f\u0578\u057e\u0578"
    ],
    "name:rus_x_preferred":[
        "\u041a\u043e\u0442\u043e\u0432\u043e"
    ],
    "name:und_x_variant":[
        "\u041a\u043e\u0442\u043e\u0432\u043e",
        "Ketovo"
    ],
    "wof:name":"Kotovo",
    "wof:placetype":"locality"
},
  "geometry": {"coordinates":[37.988,58.2067],"type":"Point"}
}