{
  "type": "Feature",
  "properties": {
    "gn:admin1_code":"77",
    "gn:asciiname":"Rogatkino",
    "gn:country_code":"RU",
    "gn:dem":144,
    "gn:feature_class":"P",
    "gn:feature_code":"PPL",
    "gn:name":"Rogatkino",
    "gn:population":0,
    "gn:timezone":"Europe/Moscow",
    "iso:country":"RU",
    "name:rus_x_preferred":[
        "\u0420\u043e\u0433\u0430\u0442\u043a\u0438\u043d\u043e"
    ],
    "name:und_x_variant":[
        "\u0420\u043e\u0433\u0430\u0442\u043a\u0438\u043d\u043e"
    ],
    "wof:name":"Rogatkino",
    "wof:placetype":"locality"
},
  "geometry": {"coordinates":[31.27759,56.72571],"type":"Point"}
}