{
  "type": "Feature",
  "properties": {
    "gn:admin1_code":"8.0",
    "gn:asciiname":"Dyurtyuli",
    "gn:country_code":"RU",
    "gn:dem":119,
    "gn:feature_class":"P",
    "gn:feature_code":"PPL",
    "gn:name":"Dyurtyuli",
    "gn:population":0,
    "gn:timezone":"Asia/Yekaterinburg",
    "iso:country":"RU",
    "name:eng_x_preferred":[
        "Dyurtyuli"
    ],
    "name:nor_x_preferred":[
        "Djurtjuli"
    ],
    "name:rus_x_preferred":[
        "\u0414\u044e\u0440\u0442\u044e\u043b\u0438"
    ],
    "name:und_x_variant":[
        "Dyurtyulli",
        "\u0414\u044e\u0440\u0442\u044e\u043b\u0438",
        "Dyurtyuli"
    ],
    "wof:name":"Dyurtyuli",
    "wof:placetype":"locality"
},
  "geometry": {"coordinates":[55.06706,54.14416],"type":"Point"}
}