{
  "type": "Feature",
  "properties": {
    "gn:admin1_code":"8.0",
    "gn:asciiname":"Dyurtyuli",
    "gn:country_code":"RU",
    "gn:dem":119,
    "gn:feature_class":"P",
    "gn:feature_code":"PPL",
    "gn:name":"Dyurtyuli",
    "gn:population":0,
    "gn:timezone":"Asia/Yekaterinburg",
    "iso:country":"RU",
    "name:ara_x_preferred":[
        "\u062f\u064a\u0648\u0631\u062a\u064a\u0648\u0644\u064a"
    ],
    "name:azb_x_preferred":[
        "\u062f\u06cc\u0648\u0631\u062a\u06cc\u0648\u0644\u06cc"
    ],
    "name:aze_x_preferred":[
        "D\u00fcrt\u00fcli"
    ],
    "name:bak_x_preferred":[
        "\u0414\u04af\u0440\u0442\u04e9\u0439\u043b\u04e9"
    ],
    "name:bel_x_preferred":[
        "\u0414\u0437\u044e\u0440\u0446\u044e\u043b\u0456"
    ],
    "name:bul_x_preferred":[
        "\u0414\u044e\u0440\u0442\u044e\u043b\u0438"
    ],
    "name:ceb_x_preferred":[
        "Dyurtyuli"
    ],
    "name:ces_x_preferred":[
        "\u010eur\u0165uli"
    ],
    "name:deu_x_preferred":[
        "Djurtjuli"
    ],
    "name:ell_x_preferred":[
        "\u039d\u03c4\u03b9\u03bf\u03c5\u03c1\u03c4\u03b3\u03b9\u03bf\u03cd\u03bb\u03b9"
    ],
    "name:eng_x_preferred":[
        "Dyurtyuli"
    ],
    "name:epo_x_preferred":[
        "Djurtjuli"
    ],
    "name:fas_x_preferred":[
        "\u062f\u06cc\u0648\u0631\u062a\u06cc\u0648\u0644\u06cc"
    ],
    "name:fin_x_preferred":[
        "Djurtjuli"
    ],
    "name:fra_x_preferred":[
        "Diourtiouli"
    ],
    "name:hsb_x_preferred":[
        "Djurtjuli"
    ],
    "name:hun_x_preferred":[
        "Gyurtyuli"
    ],
    "name:ita_x_preferred":[
        "Djurtjuli"
    ],
    "name:kat_x_preferred":[
        "\u10d3\u10d8\u10e3\u10e0\u10e2\u10d8\u10e3\u10da\u10d8"
    ],
    "name:lit_x_preferred":[
        "Diurtiuli"
    ],
    "name:mhr_x_preferred":[
        "\u0414\u04f1\u0440\u0442\u04f1\u043b\u04e7"
    ],
    "name:nno_x_preferred":[
        "Djurtjuli"
    ],
    "name:nor_x_preferred":[
        "Djurtjuli"
    ],
    "name:pol_x_preferred":[
        "Diurtiuli"
    ],
    "name:por_x_preferred":[
        "Dyurtyuli"
    ],
    "name:rus_x_preferred":[
        "\u0414\u044e\u0440\u0442\u044e\u043b\u0438"
    ],
    "name:spa_x_preferred":[
        "Diurtiul\u00ed"
    ],
    "name:srp_x_preferred":[
        "\u0414\u0458\u0443\u0440\u0442\u0458\u0443\u043b\u0438"
    ],
    "name:tat_x_preferred":[
        "\u0414\u04af\u0440\u0442\u04e9\u0439\u043b\u0435"
    ],
    "name:tgk_x_preferred":[
        "\u0414\u044e\u0440\u0442\u044e\u043b\u0438"
    ],
    "name:tgl_x_preferred":[
        "Dyurtyuli"
    ],
    "name:tur_x_preferred":[
        "D\u00fcrt\u00fcli"
    ],
    "name:ukr_x_preferred":[
        "\u0414\u044e\u0440\u0442\u044e\u043b\u0456"
    ],
    "name:und_x_variant":[
        "Dyurtyulli"
    ],
    "name:vep_x_preferred":[
        "D\u00fcrt\u00fcli"
    ],
    "name:vie_x_preferred":[
        "Dyurtyuli"
    ],
    "name:war_x_preferred":[
        "Dyurtyuli"
    ],
    "name:xal_x_preferred":[
        "\u0414\u044e\u0440\u0442\u044e\u043b\u0438 \u0431\u0430\u043b\u04bb\u0441\u043d"
    ],
    "name:zho_x_preferred":[
        "\u4e45\u723e\u79cb\u5229"
    ],
    "wof:name":"Dyurtyuli",
    "wof:placetype":"locality"
},
  "geometry": {"coordinates":[55.06706,54.14416],"type":"Point"}
}