{
  "type": "Feature",
  "properties": {
    "gn:admin1_code":"33",
    "gn:asciiname":"Stepintsy",
    "gn:country_code":"RU",
    "gn:dem":192,
    "gn:feature_class":"P",
    "gn:feature_code":"PPL",
    "gn:name":"St\u00ebpintsy",
    "gn:population":0,
    "gn:timezone":"Europe/Kirov",
    "iso:country":"RU",
    "name:rus_x_preferred":[
        "\u0421\u0442\u0451\u043f\u0438\u043d\u0446\u044b"
    ],
    "name:und_x_variant":[
        "St\u00ebpintsy"
    ],
    "wof:name":"Stepintsy",
    "wof:placetype":"locality"
},
  "geometry": {"coordinates":[50.6513,59.2011],"type":"Point"}
}