{
  "type": "Feature",
  "properties": {
    "gn:admin1_code":"61",
    "gn:asciiname":"Grafskaya",
    "gn:country_code":"RU",
    "gn:dem":82,
    "gn:feature_class":"P",
    "gn:feature_code":"PPL",
    "gn:name":"Grafskaya",
    "gn:population":0,
    "gn:timezone":"Europe/Moscow",
    "iso:country":"RU",
    "name:rus_x_preferred":[
        "\u0413\u0440\u0430\u0444\u0441\u043a\u0430\u044f"
    ],
    "wof:name":"Grafskaya",
    "wof:placetype":"locality"
},
  "geometry": {"coordinates":[38.58333,47.35],"type":"Point"}
}