{
  "type": "Feature",
  "properties": {
    "gn:admin1_code":"77",
    "gn:asciiname":"Yakimkovo",
    "gn:country_code":"RU",
    "gn:dem":140,
    "gn:feature_class":"P",
    "gn:feature_code":"PPL",
    "gn:name":"Yakimkovo",
    "gn:population":0,
    "gn:timezone":"Europe/Moscow",
    "iso:country":"RU",
    "name:rus_x_preferred":[
        "\u042f\u043a\u0438\u043c\u043a\u043e\u0432\u043e"
    ],
    "name:und_x_variant":[
        "\u042f\u043a\u0438\u043c\u043a\u043e\u0432\u043e"
    ],
    "wof:name":"Yakimkovo",
    "wof:placetype":"locality"
},
  "geometry": {"coordinates":[36.0773,57.2754],"type":"Point"}
}