{
  "type": "Feature",
  "properties": {
    "gn:admin1_code":"62",
    "gn:asciiname":"Nizhniy Yakimets",
    "gn:country_code":"RU",
    "gn:dem":142,
    "gn:feature_class":"P",
    "gn:feature_code":"PPL",
    "gn:name":"Nizhniy Yakimets",
    "gn:population":0,
    "gn:timezone":"Europe/Moscow",
    "iso:country":"RU",
    "name:rus_x_preferred":[
        "\u041d\u0438\u0436\u043d\u0438\u0439 \u042f\u043a\u0438\u043c\u0435\u0446"
    ],
    "name:und_x_variant":[
        "Nizhniy Yekimets"
    ],
    "wof:name":"Nizhniy Yakimets",
    "wof:placetype":"locality"
},
  "geometry": {"coordinates":[40.1808,53.4683],"type":"Point"}
}