{
  "type": "Feature",
  "properties": {
    "gn:admin1_code":"89",
    "gn:asciiname":"Bol'shoy Kitay",
    "gn:country_code":"RU",
    "gn:dem":144,
    "gn:feature_class":"P",
    "gn:feature_code":"PPL",
    "gn:name":"Bol\u2019shoy Kitay",
    "gn:population":0,
    "gn:timezone":"Asia/Vladivostok",
    "iso:country":"RU",
    "name:rus_x_preferred":[
        "\u0411\u043e\u043b\u044c\u0448\u043e\u0439 \u041a\u0438\u0442\u0430\u0439"
    ],
    "name:und_x_variant":[
        "Bol\u2019shoy Kitay",
        "\u0411\u043e\u043b\u044c\u0448\u043e\u0439 \u041a\u0438\u0442\u0430\u0439"
    ],
    "wof:name":"Bol'shoy Kitay",
    "wof:placetype":"locality"
},
  "geometry": {"coordinates":[132.31666999999999,49.01667],"type":"Point"}
}