{
  "type": "Feature",
  "properties": {
    "gn:admin1_code":"16",
    "gn:asciiname":"Sesmery",
    "gn:country_code":"RU",
    "gn:dem":165,
    "gn:feature_class":"P",
    "gn:feature_code":"PPL",
    "gn:name":"Sesmery",
    "gn:population":0,
    "gn:timezone":"Europe/Moscow",
    "iso:country":"RU",
    "name:rus_x_preferred":[
        "\u0421\u0435\u0441\u043c\u0435\u0440\u044b"
    ],
    "wof:name":"Sesmery",
    "wof:placetype":"locality"
},
  "geometry": {"coordinates":[46.9878,55.8737],"type":"Point"}
}