{
  "type": "Feature",
  "properties": {
    "gn:admin1_code":"13",
    "gn:asciiname":"Svetlyye Ozera",
    "gn:country_code":"RU",
    "gn:dem":340,
    "gn:feature_class":"P",
    "gn:feature_code":"PPL",
    "gn:name":"Svetlyye Oz\u00ebra",
    "gn:population":0,
    "gn:timezone":"Asia/Yekaterinburg",
    "iso:country":"RU",
    "name:und_x_variant":[
        "Oz\u00ebra",
        "Svetlyye Oz\u00ebra"
    ],
    "wof:name":"Svetlyye Ozera",
    "wof:placetype":"locality"
},
  "geometry": {"coordinates":[60.33466,52.60876],"type":"Point"}
}