{
  "type": "Feature",
  "properties": {
    "gn:admin1_code":"88",
    "gn:asciiname":"Sablukovo",
    "gn:country_code":"RU",
    "gn:dem":132,
    "gn:feature_class":"P",
    "gn:feature_code":"PPL",
    "gn:name":"Sablukovo",
    "gn:population":0,
    "gn:timezone":"Europe/Moscow",
    "iso:country":"RU",
    "name:rus_x_preferred":[
        "\u0421\u0430\u0431\u043b\u0443\u043a\u043e\u0432\u043e"
    ],
    "name:und_x_variant":[
        "Soblukovo",
        "Sablukovo"
    ],
    "wof:name":"Sablukovo",
    "wof:placetype":"locality"
},
  "geometry": {"coordinates":[39.43247,57.8297],"type":"Point"}
}