{
  "type": "Feature",
  "properties": {
    "gn:admin1_code":"56",
    "gn:asciiname":"Kleymenovo",
    "gn:country_code":"RU",
    "gn:dem":229,
    "gn:feature_class":"P",
    "gn:feature_code":"PPL",
    "gn:name":"Kleym\u00ebnovo",
    "gn:population":0,
    "gn:timezone":"Europe/Moscow",
    "iso:country":"RU",
    "name:rus_x_preferred":[
        "\u041a\u043b\u0435\u0439\u043c\u0451\u043d\u043e\u0432\u043e"
    ],
    "name:und_x_variant":[
        "Klem\u00ebnovo",
        "Kleym\u00ebnovo",
        "\u041a\u043b\u0435\u0439\u043c\u0451\u043d\u043e\u0432\u043e"
    ],
    "wof:name":"Kleymenovo",
    "wof:placetype":"locality"
},
  "geometry": {"coordinates":[36.19582,53.15459],"type":"Point"}
}