{
  "type": "Feature",
  "properties": {
    "gn:admin1_code":"63",
    "gn:asciiname":"Bol'shoy Duray",
    "gn:country_code":"RU",
    "gn:dem":748,
    "gn:feature_class":"P",
    "gn:feature_code":"PPL",
    "gn:name":"Bol\u2019shoy Duray",
    "gn:population":0,
    "gn:timezone":"Asia/Yakutsk",
    "iso:country":"RU",
    "name:rus_x_preferred":[
        "\u0411\u043e\u043b\u044c\u0448\u043e\u0439 \u0414\u0443\u0440\u0430\u0439"
    ],
    "name:und_x_variant":[
        "Bol\u2019shoy Duray",
        "\u0411\u043e\u043b\u044c\u0448\u043e\u0439 \u0414\u0443\u0440\u0430\u0439"
    ],
    "wof:name":"Bol'shoy Duray",
    "wof:placetype":"locality"
},
  "geometry": {"coordinates":[124.81106,57.20641],"type":"Point"}
}