{
  "type": "Feature",
  "properties": {
    "gn:admin1_code":"88.0",
    "gn:asciiname":"Kaishevo",
    "gn:country_code":"RU",
    "gn:dem":162,
    "gn:feature_class":"P",
    "gn:feature_code":"PPL",
    "gn:name":"Kaishevo",
    "gn:population":0,
    "gn:timezone":"Europe/Moscow",
    "iso:country":"RU",
    "name:rus_x_preferred":[
        "\u041a\u0430\u0438\u0448\u0435\u0432\u043e"
    ],
    "name:und_x_variant":[
        "\u041a\u0430\u0438\u0448\u0435\u0432\u043e"
    ],
    "wof:name":"Kaishevo",
    "wof:placetype":"locality"
},
  "geometry": {"coordinates":[40.00511,58.24952],"type":"Point"}
}