{
  "type": "Feature",
  "properties": {
    "gn:admin1_code":"8",
    "gn:asciiname":"Novoaktashevo",
    "gn:country_code":"RU",
    "gn:dem":118,
    "gn:feature_class":"P",
    "gn:feature_code":"PPL",
    "gn:name":"Novoaktashevo",
    "gn:population":0,
    "gn:timezone":"Asia/Yekaterinburg",
    "iso:country":"RU",
    "name:rus_x_preferred":[
        "\u041d\u043e\u0432\u043e\u0430\u043a\u0442\u0430\u0448\u0435\u0432\u043e"
    ],
    "name:und_x_variant":[
        "\u041d\u043e\u0432\u043e\u0430\u043a\u0442\u0430\u0448\u0435\u0432\u043e"
    ],
    "wof:name":"Novoaktashevo",
    "wof:placetype":"locality"
},
  "geometry": {"coordinates":[56.2367,54.4038],"type":"Point"}
}