{
  "type": "Feature",
  "properties": {
    "gn:admin1_code":"84",
    "gn:asciiname":"Koka",
    "gn:country_code":"RU",
    "gn:dem":26,
    "gn:feature_class":"P",
    "gn:feature_code":"PPL",
    "gn:name":"Koka",
    "gn:population":0,
    "gn:timezone":"Europe/Volgograd",
    "iso:country":"RU",
    "name:rus_x_preferred":[
        "\u041a\u043e\u043a\u0430"
    ],
    "name:und_x_variant":[
        "\u041a\u043e\u043a\u0430"
    ],
    "wof:name":"Koka",
    "wof:placetype":"locality"
},
  "geometry": {"coordinates":[45.86667,49.71667],"type":"Point"}
}