{
  "type": "Feature",
  "properties": {
    "gn:country":"RU",
    "gn:fcode":"PPL",
    "gn:population":337,
    "iso:country":"RU",
    "name:ceb_x_preferred":[
        "Torzhokskiy Rayon"
    ],
    "name:che_x_preferred":[
        "\u0422\u043e\u0440\u0436\u043e\u043a\u0430\u043d \u043a\u04c0\u043e\u0448\u0442"
    ],
    "name:chv_x_preferred":[
        "\u0422\u043e\u0440\u0436\u043e\u043a \u0440\u0430\u0439\u043e\u043d\u0115"
    ],
    "name:est_x_preferred":[
        "Tor\u017eoki rajoon"
    ],
    "name:fin_x_preferred":[
        "Tor\u017eokin piiri"
    ],
    "name:hun_x_preferred":[
        "Torzsoki j\u00e1r\u00e1s"
    ],
    "name:hye_x_preferred":[
        "\u054f\u0578\u0580\u056a\u0578\u056f\u057d\u056f\u056b \u0577\u0580\u057b\u0561\u0576"
    ],
    "name:ita_x_preferred":[
        "Tor\u017eokskij rajon"
    ],
    "name:rus_x_preferred":[
        "\u0411\u0443\u043b\u0430\u0442\u043d\u0438\u043a\u043e\u0432\u043e"
    ],
    "name:rus_x_variant":[
        "\u0422\u043e\u0440\u0436\u043e\u043a\u0441\u043a\u0438\u0439 \u0440\u0430\u0439\u043e\u043d"
    ],
    "name:srp_x_preferred":[
        "\u0422\u043e\u0440\u0436\u043e\u0447\u043a\u0438 \u0440\u0435\u0458\u043e\u043d"
    ],
    "name:vie_x_preferred":[
        "Torzhoksky"
    ],
    "qs:name":"Bulatnikovo",
    "qs:name_adm0":"Russia",
    "qs:name_adm1":"Moscow Oblast",
    "qs:photos_9k":1,
    "qs:photos_9r":1,
    "qs:photos_all":24,
    "qs:photos_sr":0,
    "qs:placetype":"Town",
    "qs:pop_sr":"2",
    "wd:wordcount":1912,
    "wof:name":"Bulatnikovo",
    "wof:placetype":"locality",
    "wof:population":337
},
  "geometry": {"coordinates":[37.6675,55.56222],"type":"Point"}
}