{
  "type": "Feature",
  "properties": {
    "gn:admin1_code":"33",
    "gn:asciiname":"Pan'shonki",
    "gn:country_code":"RU",
    "gn:dem":172,
    "gn:feature_class":"P",
    "gn:feature_code":"PPL",
    "gn:name":"Pan\u2019shonki",
    "gn:population":0,
    "gn:timezone":"Europe/Kirov",
    "iso:country":"RU",
    "name:eng_x_preferred":[
        "Pan'shonki"
    ],
    "name:nor_x_preferred":[
        "Pansjonki"
    ],
    "name:rus_x_preferred":[
        "\u041f\u0430\u043d\u044c\u0448\u043e\u043d\u043a\u0438"
    ],
    "name:und_x_variant":[
        "Pan\u2019shonki"
    ],
    "wof:name":"Pan'shonki",
    "wof:placetype":"locality"
},
  "geometry": {"coordinates":[51.5292,57.9222],"type":"Point"}
}