{
  "type": "Feature",
  "properties": {
    "gn:admin1_code":"62",
    "gn:asciiname":"Isayevka",
    "gn:country_code":"RU",
    "gn:dem":124,
    "gn:feature_class":"P",
    "gn:feature_code":"PPL",
    "gn:name":"Isayevka",
    "gn:population":0,
    "gn:timezone":"Europe/Moscow",
    "iso:country":"RU",
    "name:rus_x_preferred":[
        "\u0418\u0441\u0430\u0435\u0432\u043a\u0430"
    ],
    "wof:name":"Isayevka",
    "wof:placetype":"locality"
},
  "geometry": {"coordinates":[40.0399,53.9524],"type":"Point"}
}