{
  "type": "Feature",
  "properties": {
    "gn:admin1_code":"91",
    "gn:asciiname":"Donnikova",
    "gn:country_code":"RU",
    "gn:dem":223,
    "gn:feature_class":"P",
    "gn:feature_code":"PPL",
    "gn:name":"Donnikova",
    "gn:population":0,
    "gn:timezone":"Asia/Krasnoyarsk",
    "iso:country":"RU",
    "name:rus_x_preferred":[
        "\u0414\u043e\u043d\u043d\u0438\u043a\u043e\u0432\u0430"
    ],
    "wof:name":"Donnikova",
    "wof:placetype":"locality"
},
  "geometry": {"coordinates":[92.46666999999999,55.58333],"type":"Point"}
}