{
  "type": "Feature",
  "properties": {
    "iso:country":"RU",
    "name:rus_x_preferred":[
        "\u0414\u0435\u0441\u0451\u043d\u043e\u0432\u0441\u043a\u043e\u0435"
    ],
    "wof:name":"Desyonovskoye",
    "wof:placetype":"neighbourhood"
},
  "geometry": {"coordinates":[37.36937225031871,55.49551627801817],"type":"Point"}
}