{
  "type": "Feature",
  "properties": {
    "gn:admin1_code":"6.0",
    "gn:asciiname":"Yangory",
    "gn:country_code":"RU",
    "gn:dem":169,
    "gn:feature_class":"P",
    "gn:feature_code":"PPL",
    "gn:name":"Yangory",
    "gn:population":0,
    "gn:timezone":"Europe/Moscow",
    "iso:country":"RU",
    "name:rus_x_preferred":[
        "\u042f\u043d\u0433\u043e\u0440\u044b"
    ],
    "wof:name":"Yangory",
    "wof:placetype":"locality"
},
  "geometry": {"coordinates":[37.9979,62.7398],"type":"Point"}
}