{
  "type": "Feature",
  "properties": {
    "gn:country":"RU",
    "gn:fcode":"PPL",
    "gn:pop":0,
    "iso:country":"RU",
    "name:eng_x_preferred":[
        "Vyshka"
    ],
    "name:nor_x_preferred":[
        "Vysjka"
    ],
    "name:rus_x_preferred":[
        "\u0412\u044b\u0448\u043a\u0430"
    ],
    "qs:name":"Vyshka",
    "qs:name_adm0":"Russia",
    "qs:name_adm1":"Astrakhan Oblast",
    "qs:photos_9r":0,
    "qs:photos_sr":0,
    "qs:placetype":"Town",
    "qs:pop_sr":"0",
    "wof:name":"Vyshka",
    "wof:placetype":"locality",
    "wof:population":0
},
  "geometry": {"coordinates":[47.64225,45.60894],"type":"Point"}
}