{
  "type": "Feature",
  "properties": {
    "gn:admin1_code":"77",
    "gn:asciiname":"Luzhnikovo",
    "gn:country_code":"RU",
    "gn:dem":212,
    "gn:feature_class":"P",
    "gn:feature_code":"PPL",
    "gn:name":"Luzhnikovo",
    "gn:population":0,
    "gn:timezone":"Europe/Moscow",
    "iso:country":"RU",
    "name:eng_x_preferred":[
        "Luzhnikovo"
    ],
    "name:nor_x_preferred":[
        "Luzjnikovo"
    ],
    "name:rus_x_preferred":[
        "\u041b\u0443\u0436\u043d\u0438\u043a\u043e\u0432\u043e"
    ],
    "name:und_x_variant":[
        "Luzhnikova"
    ],
    "wof:name":"Luzhnikovo",
    "wof:placetype":"locality"
},
  "geometry": {"coordinates":[34.14462,57.40351999999999],"type":"Point"}
}