{
  "type": "Feature",
  "properties": {
    "gn:admin1_code":"81",
    "gn:asciiname":"Tsypovka",
    "gn:country_code":"RU",
    "gn:dem":99,
    "gn:feature_class":"P",
    "gn:feature_code":"PPL",
    "gn:name":"Tsypovka",
    "gn:population":0,
    "gn:timezone":"Europe/Ulyanovsk",
    "iso:country":"RU",
    "name:rus_x_preferred":[
        "\u0426\u044b\u043f\u043e\u0432\u043a\u0430"
    ],
    "name:und_x_variant":[
        "\u0426\u044b\u043f\u043e\u0432\u043a\u0430"
    ],
    "wof:name":"Tsypovka",
    "wof:placetype":"locality"
},
  "geometry": {"coordinates":[46.65367,54.59388000000001],"type":"Point"}
}