{
  "type": "Feature",
  "properties": {
    "gn:admin1_code":"77",
    "gn:asciiname":"Fedyushina",
    "gn:country_code":"RU",
    "gn:dem":226,
    "gn:feature_class":"P",
    "gn:feature_code":"PPL",
    "gn:name":"Fedyushina",
    "gn:population":0,
    "gn:timezone":"Europe/Moscow",
    "iso:country":"RU",
    "name:rus_x_preferred":[
        "\u0424\u0435\u0434\u044e\u0448\u0438\u043d\u0430"
    ],
    "wof:name":"Fedyushina",
    "wof:placetype":"locality"
},
  "geometry": {"coordinates":[33.13333,55.89139],"type":"Point"}
}