{
  "type": "Feature",
  "properties": {
    "gn:admin1_code":"53",
    "gn:asciiname":"Zolotaya Polyana",
    "gn:country_code":"RU",
    "gn:dem":242,
    "gn:feature_class":"P",
    "gn:feature_code":"PPL",
    "gn:name":"Zolotaya Polyana",
    "gn:population":0,
    "gn:timezone":"Asia/Novosibirsk",
    "iso:country":"RU",
    "wof:name":"Zolotaya Polyana",
    "wof:placetype":"locality"
},
  "geometry": {"coordinates":[83.45,54.78333000000001],"type":"Point"}
}