{
  "type": "Feature",
  "properties": {
    "gn:admin1_code":"5",
    "gn:asciiname":"Verkhnezeysk",
    "gn:country_code":"RU",
    "gn:dem":335,
    "gn:feature_class":"P",
    "gn:feature_code":"PPL",
    "gn:name":"Verkhnezeysk",
    "gn:population":0,
    "gn:timezone":"Asia/Yakutsk",
    "iso:country":"RU",
    "name:che_x_preferred":[
        "\u0412\u0435\u0440\u0445\u043d\u0435\u0437\u0435\u0439\u0441\u043a"
    ],
    "name:rus_x_preferred":[
        "\u0412\u0435\u0440\u0445\u043d\u0435\u0437\u0435\u0439\u0441\u043a"
    ],
    "name:tgk_x_preferred":[
        "\u0412\u0435\u0440\u0445\u043d\u0435\u0437\u0435\u0439\u0441\u043a"
    ],
    "wof:name":"Verkhnezeysk",
    "wof:placetype":"locality"
},
  "geometry": {"coordinates":[128.51837,54.62891],"type":"Point"}
}