{
  "type": "Feature",
  "properties": {
    "gn:admin1_code":"61.0",
    "gn:asciiname":"Demishev",
    "gn:country_code":"RU",
    "gn:dem":72,
    "gn:feature_class":"P",
    "gn:feature_code":"PPL",
    "gn:name":"Demishev",
    "gn:population":0,
    "gn:timezone":"Europe/Moscow",
    "iso:country":"RU",
    "name:rus_x_preferred":[
        "\u0414\u0435\u043c\u0438\u0448\u0435\u0432"
    ],
    "name:und_x_variant":[
        "Demishov",
        "Demishev",
        "\u0414\u0435\u043c\u0438\u0448\u0435\u0432"
    ],
    "wof:name":"Demishev",
    "wof:placetype":"locality"
},
  "geometry": {"coordinates":[40.95145,48.4635],"type":"Point"}
}