{
  "type": "Feature",
  "properties": {
    "gn:admin1_code":"61",
    "gn:asciiname":"Soldatovskiy",
    "gn:country_code":"RU",
    "gn:dem":100,
    "gn:feature_class":"P",
    "gn:feature_code":"PPL",
    "gn:name":"Soldatovskiy",
    "gn:population":0,
    "gn:timezone":"Europe/Moscow",
    "iso:country":"RU",
    "name:rus_x_preferred":[
        "\u0421\u043e\u043b\u0434\u0430\u0442\u043e\u0432\u0441\u043a\u0438\u0439"
    ],
    "name:und_x_variant":[
        "\u0421\u043e\u043b\u0434\u0430\u0442\u043e\u0432\u0441\u043a\u0438\u0439"
    ],
    "wof:name":"Soldatovskiy",
    "wof:placetype":"locality"
},
  "geometry": {"coordinates":[41.87261,49.72957],"type":"Point"}
}