{
  "type": "Feature",
  "properties": {
    "gn:admin1_code":"90",
    "gn:asciiname":"Pervunyata",
    "gn:country_code":"RU",
    "gn:dem":159,
    "gn:feature_class":"P",
    "gn:feature_code":"PPL",
    "gn:name":"Pervunyata",
    "gn:population":0,
    "gn:timezone":"Asia/Yekaterinburg",
    "iso:country":"RU",
    "name:rus_x_preferred":[
        "\u041f\u0435\u0440\u0432\u0443\u043d\u044f\u0442\u0430"
    ],
    "name:und_x_variant":[
        "Pervinyata",
        "Pervunyata",
        "\u041f\u0435\u0440\u0432\u0443\u043d\u044f\u0442\u0430"
    ],
    "wof:name":"Pervunyata",
    "wof:placetype":"locality"
},
  "geometry": {"coordinates":[55.3097,58.1938],"type":"Point"}
}