{
  "type": "Feature",
  "properties": {
    "gn:admin1_code":"53",
    "gn:asciiname":"Chingisy",
    "gn:country_code":"RU",
    "gn:dem":117,
    "gn:feature_class":"P",
    "gn:feature_code":"PPL",
    "gn:name":"Chingisy",
    "gn:population":0,
    "gn:timezone":"Asia/Novosibirsk",
    "iso:country":"RU",
    "name:eng_x_preferred":[
        "Chingisy"
    ],
    "name:nor_x_preferred":[
        "Tsjingis"
    ],
    "name:rus_x_preferred":[
        "\u0427\u0438\u043d\u0433\u0438\u0441"
    ],
    "name:rus_x_variant":[
        "\u0427\u0438\u043d\u0433\u0438\u0441\u044b"
    ],
    "name:und_x_variant":[
        "Chingis",
        "Chingisskoye",
        "Chingisy"
    ],
    "wof:name":"Chingisy",
    "wof:placetype":"locality"
},
  "geometry": {"coordinates":[81.62,54.1254],"type":"Point"}
}