{
  "type": "Feature",
  "properties": {
    "gn:admin1_code":"37.0",
    "gn:asciiname":"Bol'shoy Zaingir'",
    "gn:country_code":"RU",
    "gn:dem":126,
    "gn:feature_class":"P",
    "gn:feature_code":"PPL",
    "gn:name":"Bol\u2019shoy Zaingir\u2019",
    "gn:population":0,
    "gn:timezone":"Europe/Moscow",
    "iso:country":"RU",
    "name:rus_x_preferred":[
        "\u0411\u043e\u043b\u044c\u0448\u043e\u0439 \u0417\u0430\u0438\u043d\u0433\u0438\u0440\u044c"
    ],
    "name:und_x_variant":[
        "Bol\u2019shoy Zaingir\u2019"
    ],
    "wof:name":"Bol'shoy Zaingir'",
    "wof:placetype":"locality"
},
  "geometry": {"coordinates":[43.97018,58.45677],"type":"Point"}
}