{
  "type": "Feature",
  "properties": {
    "gn:admin1_code":"43",
    "gn:asciiname":"Rep'yevka",
    "gn:country_code":"RU",
    "gn:dem":218,
    "gn:feature_class":"P",
    "gn:feature_code":"PPL",
    "gn:name":"Rep\u2019y\u00ebvka",
    "gn:population":0,
    "gn:timezone":"Europe/Moscow",
    "iso:country":"RU",
    "name:rus_x_preferred":[
        "\u0420\u0435\u043f\u044c\u0451\u0432\u043a\u0430"
    ],
    "name:und_x_variant":[
        "Rep\u2019y\u00ebvka"
    ],
    "wof:name":"Rep'yevka",
    "wof:placetype":"locality"
},
  "geometry": {"coordinates":[38.61667,52.86666999999999],"type":"Point"}
}