{
  "type": "Feature",
  "properties": {
    "gn:admin1_code":"84.0",
    "gn:asciiname":"Altynnikov",
    "gn:country_code":"RU",
    "gn:dem":96,
    "gn:feature_class":"P",
    "gn:feature_code":"PPL",
    "gn:name":"Altynnikov",
    "gn:population":0,
    "gn:timezone":"Europe/Volgograd",
    "iso:country":"RU",
    "name:nor_x_preferred":[
        "Altynnikov"
    ],
    "name:rus_x_preferred":[
        "\u0410\u043b\u0442\u044b\u043d\u043d\u0438\u043a\u043e\u0432"
    ],
    "wof:name":"Altynnikov",
    "wof:placetype":"locality"
},
  "geometry": {"coordinates":[41.85833,50.22944],"type":"Point"}
}