{
  "type": "Feature",
  "properties": {
    "gn:admin1_code":"83",
    "gn:asciiname":"Shablykino",
    "gn:country_code":"RU",
    "gn:dem":184,
    "gn:feature_class":"P",
    "gn:feature_code":"PPL",
    "gn:name":"Shablykino",
    "gn:population":340,
    "gn:timezone":"Europe/Moscow",
    "iso:country":"RU",
    "name:rus_x_preferred":[
        "\u0428\u0430\u0431\u043b\u044b\u043a\u0438\u043d\u043e"
    ],
    "wof:name":"Shablykino",
    "wof:placetype":"locality",
    "wof:population":340
},
  "geometry": {"coordinates":[38.54382,56.35579],"type":"Point"}
}