{
  "type": "Feature",
  "properties": {
    "gn:admin1_code":"16",
    "gn:asciiname":"Tolbaykasy",
    "gn:country_code":"RU",
    "gn:dem":140,
    "gn:feature_class":"P",
    "gn:feature_code":"PPL",
    "gn:name":"Tolbaykasy",
    "gn:population":0,
    "gn:timezone":"Europe/Moscow",
    "iso:country":"RU",
    "name:rus_x_preferred":[
        "\u0422\u043e\u043b\u0431\u0430\u0439\u043a\u0430\u0441\u044b"
    ],
    "wof:name":"Tolbaykasy",
    "wof:placetype":"locality"
},
  "geometry": {"coordinates":[47.2565,55.9178],"type":"Point"}
}