{
  "type": "Feature",
  "properties": {
    "gn:admin1_code":"77",
    "gn:asciiname":"Volkovskaya",
    "gn:country_code":"RU",
    "gn:dem":86,
    "gn:feature_class":"P",
    "gn:feature_code":"PPL",
    "gn:name":"Volkovskaya",
    "gn:population":0,
    "gn:timezone":"Europe/Moscow",
    "iso:country":"RU",
    "name:rus_x_preferred":[
        "\u0412\u043e\u043b\u043a\u043e\u0432\u0441\u043a\u0430\u044f"
    ],
    "name:und_x_variant":[
        "\u0412\u043e\u043b\u043a\u043e\u0432\u0441\u043a\u0430\u044f"
    ],
    "wof:name":"Volkovskaya",
    "wof:placetype":"locality"
},
  "geometry": {"coordinates":[31.09141,56.87408000000001],"type":"Point"}
}