{
  "type": "Feature",
  "properties": {
    "gn:admin1_code":"80",
    "gn:asciiname":"Mokretsy",
    "gn:cc2":"RU",
    "gn:country_code":"RU",
    "gn:dem":236,
    "gn:feature_class":"P",
    "gn:feature_code":"PPL",
    "gn:name":"Mokretsy",
    "gn:population":0,
    "gn:timezone":"Europe/Samara",
    "iso:country":"RU",
    "name:rus_x_preferred":[
        "\u041c\u043e\u043a\u0440\u0435\u0446\u044b"
    ],
    "name:und_x_variant":[
        "Makretsy",
        "Mokretsy",
        "\u041c\u043e\u043a\u0440\u0435\u0446\u044b"
    ],
    "wof:name":"Mokretsy",
    "wof:placetype":"locality"
},
  "geometry": {"coordinates":[53.11666999999999,58.31667],"type":"Point"}
}