{
  "type": "Feature",
  "properties": {
    "gn:admin1_code":"65.0",
    "gn:asciiname":"Almazovka",
    "gn:country_code":"RU",
    "gn:dem":53,
    "gn:feature_class":"P",
    "gn:feature_code":"PPL",
    "gn:name":"Almazovka",
    "gn:population":0,
    "gn:timezone":"Europe/Samara",
    "iso:country":"RU",
    "name:nor_x_preferred":[
        "Almazovka"
    ],
    "name:rus_x_preferred":[
        "\u0410\u043b\u043c\u0430\u0437\u043e\u0432\u043a\u0430"
    ],
    "wof:name":"Almazovka",
    "wof:placetype":"locality"
},
  "geometry": {"coordinates":[50.34176,53.78947],"type":"Point"}
}