{
  "type": "Feature",
  "properties": {
    "gn:admin1_code":"47",
    "gn:asciiname":"Sazheni",
    "gn:country_code":"RU",
    "gn:dem":117,
    "gn:feature_class":"P",
    "gn:feature_code":"PPL",
    "gn:name":"Sazheni",
    "gn:population":0,
    "gn:timezone":"Europe/Moscow",
    "iso:country":"RU",
    "name:rus_x_preferred":[
        "\u0421\u0430\u0436\u0435\u043d\u0438"
    ],
    "name:und_x_variant":[
        "Pos\u00eblok Sazheni",
        "Sazheni",
        "\u0421\u0430\u0436\u0435\u043d\u0438"
    ],
    "wof:name":"Sazheni",
    "wof:placetype":"locality"
},
  "geometry": {"coordinates":[39.0377,55.76498],"type":"Point"}
}