{
  "type": "Feature",
  "properties": {
    "gn:admin1_code":"29",
    "gn:asciiname":"Krylovo",
    "gn:country_code":"RU",
    "gn:dem":110,
    "gn:feature_class":"P",
    "gn:feature_code":"PPL",
    "gn:name":"Krylovo",
    "gn:population":0,
    "gn:timezone":"Asia/Novokuznetsk",
    "iso:country":"RU",
    "name:rus_x_preferred":[
        "\u041a\u0440\u044b\u043b\u043e\u0432\u043e"
    ],
    "name:und_x_variant":[
        "Krylova",
        "Krylovo"
    ],
    "wof:name":"Krylovo",
    "wof:placetype":"locality"
},
  "geometry": {"coordinates":[85.2683,55.6587],"type":"Point"}
}