{
  "type": "Feature",
  "properties": {
    "gn:admin1_code":"77",
    "gn:asciiname":"Pyatnitsa-Plot",
    "gn:country_code":"RU",
    "gn:dem":163,
    "gn:feature_class":"P",
    "gn:feature_code":"PPL",
    "gn:name":"Pyatnitsa-Plot",
    "gn:population":0,
    "gn:timezone":"Europe/Moscow",
    "iso:country":"RU",
    "name:rus_x_preferred":[
        "\u041f\u044f\u0442\u043d\u0438\u0446\u0430-\u041f\u043b\u043e\u0442"
    ],
    "wof:name":"Pyatnitsa-Plot",
    "wof:placetype":"locality"
},
  "geometry": {"coordinates":[34.7622,57.08265],"type":"Point"}
}