{
  "type": "Feature",
  "properties": {
    "gn:admin1_code":"54",
    "gn:asciiname":"Kochkovatskiy",
    "gn:country_code":"RU",
    "gn:dem":123,
    "gn:feature_class":"P",
    "gn:feature_code":"PPL",
    "gn:name":"Kochkovatskiy",
    "gn:population":0,
    "gn:timezone":"Asia/Omsk",
    "iso:country":"RU",
    "name:rus_x_preferred":[
        "\u041a\u043e\u0447\u043a\u043e\u0432\u0430\u0442\u0441\u043a\u0438\u0439"
    ],
    "name:und_x_variant":[
        "\u041a\u043e\u0447\u043a\u043e\u0432\u0430\u0442\u0441\u043a\u0438\u0439"
    ],
    "wof:name":"Kochkovatskiy",
    "wof:placetype":"locality"
},
  "geometry": {"coordinates":[71.69962,55.45144000000001],"type":"Point"}
}