{
  "type": "Feature",
  "properties": {
    "gn:admin1_code":"91",
    "gn:asciiname":"Sliznevo",
    "gn:country_code":"RU",
    "gn:dem":191,
    "gn:feature_class":"P",
    "gn:feature_code":"PPL",
    "gn:name":"Slizn\u00ebvo",
    "gn:population":0,
    "gn:timezone":"Asia/Krasnoyarsk",
    "iso:country":"RU",
    "name:eng_x_preferred":[
        "Slizn\u00ebvo"
    ],
    "name:nor_x_preferred":[
        "Sliznevo"
    ],
    "name:rus_x_preferred":[
        "\u0421\u043b\u0438\u0437\u043d\u0435\u0432\u043e"
    ],
    "name:rus_x_variant":[
        "\u0421\u043b\u0438\u0437\u043d\u0451\u0432\u043e"
    ],
    "name:und_x_variant":[
        "Slizn\u00ebvo"
    ],
    "wof:name":"Sliznevo",
    "wof:placetype":"locality"
},
  "geometry": {"coordinates":[92.6133,55.9555],"type":"Point"}
}