{
  "type": "Feature",
  "properties": {
    "gn:admin1_code":"8.0",
    "gn:asciiname":"Baykal",
    "gn:country_code":"RU",
    "gn:dem":225,
    "gn:feature_class":"P",
    "gn:feature_code":"PPL",
    "gn:name":"Baykal",
    "gn:population":0,
    "gn:timezone":"Asia/Yekaterinburg",
    "iso:country":"RU",
    "name:nor_x_preferred":[
        "Bajkal"
    ],
    "name:rus_x_preferred":[
        "\u0411\u0430\u0439\u043a\u0430\u043b"
    ],
    "wof:name":"Baykal",
    "wof:placetype":"locality"
},
  "geometry": {"coordinates":[55.88482,53.92654],"type":"Point"}
}