{
  "type": "Feature",
  "properties": {
    "gn:admin1_code":"60",
    "gn:asciiname":"Kadolovo",
    "gn:country_code":"RU",
    "gn:dem":150,
    "gn:feature_class":"P",
    "gn:feature_code":"PPL",
    "gn:name":"Kadolovo",
    "gn:population":0,
    "gn:timezone":"Europe/Moscow",
    "iso:country":"RU",
    "name:rus_x_preferred":[
        "\u041a\u0430\u0434\u043e\u043b\u043e\u0432\u043e"
    ],
    "name:und_x_variant":[
        "\u041a\u0430\u0434\u043e\u043b\u043e\u0432\u043e"
    ],
    "wof:name":"Kadolovo",
    "wof:placetype":"locality"
},
  "geometry": {"coordinates":[30.5735,56.0482],"type":"Point"}
}