{
  "type": "Feature",
  "properties": {
    "gn:admin1_code":"20",
    "gn:asciiname":"Sukhoy Ruchey",
    "gn:country_code":"RU",
    "gn:dem":503,
    "gn:feature_class":"P",
    "gn:feature_code":"PPL",
    "gn:name":"Sukhoy Ruchey",
    "gn:population":0,
    "gn:timezone":"Asia/Irkutsk",
    "iso:country":"RU",
    "name:eng_x_preferred":[
        "Sukhoy Ruchey"
    ],
    "name:nor_x_preferred":[
        "Sukhoj-Rutsjej"
    ],
    "name:rus_x_preferred":[
        "\u0421\u0443\u0445\u043e\u0439-\u0420\u0443\u0447\u0435\u0439"
    ],
    "name:rus_x_variant":[
        "\u0421\u0443\u0445\u043e\u0439 \u0420\u0443\u0447\u0435\u0439"
    ],
    "wof:name":"Sukhoy Ruchey",
    "wof:placetype":"locality"
},
  "geometry": {"coordinates":[103.81028000000001,51.61917],"type":"Point"}
}