{
  "type": "Feature",
  "properties": {
    "gn:admin1_code":"77",
    "gn:asciiname":"Kes'ma",
    "gn:country_code":"RU",
    "gn:dem":192,
    "gn:feature_class":"P",
    "gn:feature_code":"PPL",
    "gn:name":"Kes\u2019ma",
    "gn:population":0,
    "gn:timezone":"Europe/Moscow",
    "iso:country":"RU",
    "name:eng_x_preferred":[
        "Kes'ma"
    ],
    "name:nor_x_preferred":[
        "Kesma"
    ],
    "name:rus_x_preferred":[
        "\u041a\u0435\u0441\u044c\u043c\u0430"
    ],
    "name:und_x_variant":[
        "\u041a\u0435\u0441\u044c\u043c\u0430",
        "Kes\u2019ma"
    ],
    "wof:name":"Kes'ma",
    "wof:placetype":"locality"
},
  "geometry": {"coordinates":[37.06422,58.39961],"type":"Point"}
}