{
  "type": "Feature",
  "properties": {
    "gn:admin1_code":"13",
    "gn:asciiname":"Soboleva",
    "gn:country_code":"RU",
    "gn:dem":170,
    "gn:feature_class":"P",
    "gn:feature_code":"PPL",
    "gn:name":"Soboleva",
    "gn:population":0,
    "gn:timezone":"Asia/Yekaterinburg",
    "iso:country":"RU",
    "name:rus_x_preferred":[
        "\u0421\u043e\u0431\u043e\u043b\u0435\u0432\u0430"
    ],
    "name:und_x_variant":[
        "\u0421\u043e\u0431\u043e\u043b\u0435\u0432\u0430"
    ],
    "wof:name":"Soboleva",
    "wof:placetype":"locality"
},
  "geometry": {"coordinates":[61.61666999999999,55.78333000000001],"type":"Point"}
}