{
  "type": "Feature",
  "properties": {
    "gn:admin1_code":"85",
    "gn:asciiname":"Guznovo",
    "gn:country_code":"RU",
    "gn:dem":152,
    "gn:feature_class":"P",
    "gn:feature_code":"PPL",
    "gn:name":"Guznovo",
    "gn:population":0,
    "gn:timezone":"Europe/Moscow",
    "iso:country":"RU",
    "name:rus_x_preferred":[
        "\u0413\u0443\u0437\u043d\u043e\u0432\u043e"
    ],
    "name:und_x_variant":[
        "\u0413\u0443\u0437\u043d\u043e\u0432\u043e"
    ],
    "wof:name":"Guznovo",
    "wof:placetype":"locality"
},
  "geometry": {"coordinates":[38.80043,59.0801],"type":"Point"}
}