{
  "type": "Feature",
  "properties": {
    "gn:admin1_code":"90",
    "gn:asciiname":"Sokol",
    "gn:country_code":"RU",
    "gn:dem":118,
    "gn:feature_class":"P",
    "gn:feature_code":"PPL",
    "gn:name":"Sokol",
    "gn:population":1505,
    "gn:timezone":"Asia/Yekaterinburg",
    "iso:country":"RU",
    "name:rus_x_preferred":[
        "\u0421\u043e\u043a\u043e\u043b"
    ],
    "name:und_x_variant":[
        "\u0421\u043e\u043a\u043e\u043b"
    ],
    "wof:name":"Sokol",
    "wof:placetype":"locality",
    "wof:population":1505
},
  "geometry": {"coordinates":[56.0456,57.9146],"type":"Point"}
}