{
  "type": "Feature",
  "properties": {
    "gn:admin1_code":"90",
    "gn:asciiname":"Sokol",
    "gn:country_code":"RU",
    "gn:dem":118,
    "gn:feature_class":"P",
    "gn:feature_code":"PPL",
    "gn:name":"Sokol",
    "gn:population":1505,
    "gn:timezone":"Asia/Yekaterinburg",
    "iso:country":"RU",
    "name:cat_x_preferred":[
        "Sokol"
    ],
    "name:ces_x_preferred":[
        "Sokol"
    ],
    "name:deu_x_preferred":[
        "Sokol"
    ],
    "name:epo_x_preferred":[
        "Sokol-movado"
    ],
    "name:fra_x_preferred":[
        "Sokol"
    ],
    "name:hrv_x_preferred":[
        "Sokol"
    ],
    "name:ita_x_preferred":[
        "Sokol"
    ],
    "name:jpn_x_preferred":[
        "\u30bd\u30b3\u30eb"
    ],
    "name:nld_x_preferred":[
        "Sokol"
    ],
    "name:pol_x_preferred":[
        "Sok\u00f3\u0142"
    ],
    "name:ron_x_preferred":[
        "Sokol"
    ],
    "name:rus_x_preferred":[
        "\u0421\u043e\u043a\u043e\u043b"
    ],
    "name:rus_x_variant":[
        "\u0421\u043e\u043a\u043e\u043b\u044c\u0441\u043a\u043e\u0435 \u0434\u0432\u0438\u0436\u0435\u043d\u0438\u0435"
    ],
    "name:slv_x_preferred":[
        "Sokol"
    ],
    "name:spa_x_preferred":[
        "Sokol"
    ],
    "name:swe_x_preferred":[
        "Sokol"
    ],
    "name:ukr_x_preferred":[
        "\u0421\u043e\u043a\u0456\u043b"
    ],
    "wof:name":"Sokol",
    "wof:placetype":"locality",
    "wof:population":1505
},
  "geometry": {"coordinates":[56.0456,57.9146],"type":"Point"}
}