{
  "type": "Feature",
  "properties": {
    "gn:admin1_code":"37",
    "gn:asciiname":"Mokrusha",
    "gn:country_code":"RU",
    "gn:dem":162,
    "gn:feature_class":"P",
    "gn:feature_code":"PPL",
    "gn:name":"Mokrusha",
    "gn:population":0,
    "gn:timezone":"Europe/Moscow",
    "iso:country":"RU",
    "name:rus_x_preferred":[
        "\u041c\u043e\u043a\u0440\u0443\u0448\u0430"
    ],
    "name:und_x_variant":[
        "\u041c\u043e\u043a\u0440\u0443\u0448\u0430"
    ],
    "wof:name":"Mokrusha",
    "wof:placetype":"locality"
},
  "geometry": {"coordinates":[46.9769,58.8875],"type":"Point"}
}