{
  "type": "Feature",
  "properties": {
    "gn:admin1_code":"54",
    "gn:asciiname":"Shipitsyno",
    "gn:country_code":"RU",
    "gn:dem":82,
    "gn:feature_class":"P",
    "gn:feature_code":"PPL",
    "gn:name":"Shipitsyno",
    "gn:population":0,
    "gn:timezone":"Asia/Omsk",
    "iso:country":"RU",
    "name:bel_x_preferred":[
        "\u0428\u044b\u043f\u0456\u0446\u044b\u043d\u0430"
    ],
    "name:ceb_x_preferred":[
        "Shipitsyno"
    ],
    "name:che_x_preferred":[
        "\u0428\u0438\u043f\u0438\u0446\u044b\u043d\u043e"
    ],
    "name:deu_x_preferred":[
        "Schipizyno"
    ],
    "name:eng_x_preferred":[
        "Shipitsyno"
    ],
    "name:hun_x_preferred":[
        "Spicino"
    ],
    "name:hye_x_preferred":[
        "\u0547\u056b\u057a\u056b\u0581\u056b\u0576\u0578"
    ],
    "name:ita_x_preferred":[
        "\u0160ipicyno"
    ],
    "name:nor_x_preferred":[
        "Sjipitsyno"
    ],
    "name:pol_x_preferred":[
        "Szypicyno"
    ],
    "name:rus_x_preferred":[
        "\u0428\u0438\u043f\u0438\u0446\u044b\u043d\u043e"
    ],
    "name:und_x_variant":[
        "Shipitsino",
        "Shipitsyna",
        "\u0428\u0438\u043f\u0438\u0446\u044b\u043d\u043e",
        "Shipitsyno"
    ],
    "name:urd_x_preferred":[
        "\u0634\u06cc\u067e\u062a\u0633\u0646\u0648"
    ],
    "wof:name":"Shipitsyno",
    "wof:placetype":"locality"
},
  "geometry": {"coordinates":[74.57165000000001,56.0161],"type":"Point"}
}