{
  "type": "Feature",
  "properties": {
    "gn:admin1_code":"88",
    "gn:asciiname":"Staroselovo",
    "gn:country_code":"RU",
    "gn:dem":178,
    "gn:feature_class":"P",
    "gn:feature_code":"PPL",
    "gn:name":"Staroselovo",
    "gn:population":0,
    "gn:timezone":"Europe/Moscow",
    "iso:country":"RU",
    "name:rus_x_preferred":[
        "\u0421\u0442\u0430\u0440\u043e\u0441\u0435\u043b\u043e\u0432\u043e"
    ],
    "wof:name":"Staroselovo",
    "wof:placetype":"locality"
},
  "geometry": {"coordinates":[39.51587,57.41016],"type":"Point"}
}