{
  "type": "Feature",
  "properties": {
    "gn:admin1_code":"52",
    "gn:asciiname":"Shchetinovo",
    "gn:country_code":"RU",
    "gn:dem":146,
    "gn:feature_class":"P",
    "gn:feature_code":"PPL",
    "gn:name":"Shchetinovo",
    "gn:population":0,
    "gn:timezone":"Europe/Moscow",
    "iso:country":"RU",
    "name:rus_x_preferred":[
        "\u0429\u0435\u0442\u0438\u043d\u043e\u0432\u043e"
    ],
    "name:und_x_variant":[
        "Shetinovo",
        "Shchetinovo",
        "\u0429\u0435\u0442\u0438\u043d\u043e\u0432\u043e"
    ],
    "wof:name":"Shchetinovo",
    "wof:placetype":"locality"
},
  "geometry": {"coordinates":[34.18814,58.301],"type":"Point"}
}