{
  "type": "Feature",
  "properties": {
    "gn:admin1_code":"10",
    "gn:asciiname":"Snytkino",
    "gn:country_code":"RU",
    "gn:dem":179,
    "gn:feature_class":"P",
    "gn:feature_code":"PPL",
    "gn:name":"Snytkino",
    "gn:population":0,
    "gn:timezone":"Europe/Moscow",
    "iso:country":"RU",
    "name:eng_x_preferred":[
        "Snytkino"
    ],
    "name:nor_x_preferred":[
        "Snytkino"
    ],
    "name:rus_x_preferred":[
        "\u0421\u043d\u044b\u0442\u043a\u0438\u043d\u043e"
    ],
    "wof:name":"Snytkino",
    "wof:placetype":"locality"
},
  "geometry": {"coordinates":[34.6672,52.6016],"type":"Point"}
}