{
  "type": "Feature",
  "properties": {
    "gn:admin1_code":"8",
    "gn:asciiname":"Novotroitskoye",
    "gn:country_code":"RU",
    "gn:dem":186,
    "gn:feature_class":"P",
    "gn:feature_code":"PPL",
    "gn:name":"Novotroitskoye",
    "gn:population":0,
    "gn:timezone":"Asia/Yekaterinburg",
    "iso:country":"RU",
    "name:eng_x_preferred":[
        "Novotroitskoye"
    ],
    "name:nor_x_preferred":[
        "Novotroitskoje"
    ],
    "name:rus_x_preferred":[
        "\u041d\u043e\u0432\u043e\u0442\u0440\u043e\u0438\u0446\u043a\u043e\u0435"
    ],
    "name:rus_x_variant":[
        "\u041d\u043e\u0432\u043e\u0442\u0440\u043e\u0438\u0442\u0441\u043a\u043e\u0435"
    ],
    "wof:name":"Novotroitskoye",
    "wof:placetype":"locality"
},
  "geometry": {"coordinates":[56.21486,55.74676],"type":"Point"}
}