{
  "type": "Feature",
  "properties": {
    "gn:admin1_code":"43",
    "gn:asciiname":"Knyazhaya Baygora",
    "gn:country_code":"RU",
    "gn:dem":113,
    "gn:feature_class":"P",
    "gn:feature_code":"PPL",
    "gn:name":"Knyazhaya Baygora",
    "gn:population":0,
    "gn:timezone":"Europe/Moscow",
    "iso:country":"RU",
    "name:eng_x_preferred":[
        "Knyazhaya Baygora"
    ],
    "name:nor_x_preferred":[
        "Knjazjaja Bajgora"
    ],
    "name:rus_x_preferred":[
        "\u041a\u043d\u044f\u0436\u0430\u044f \u0411\u0430\u0439\u0433\u043e\u0440\u0430"
    ],
    "name:rus_x_variant":[
        "Knyazh\u2019ye Baygora"
    ],
    "name:und_x_variant":[
        "Knyazh\u2019ye Baygora",
        "\u041a\u043d\u044f\u0436\u0430\u044f \u0411\u0430\u0439\u0433\u043e\u0440\u0430",
        "Knyazhaya Baygora"
    ],
    "wof:name":"Knyazhaya Baygora",
    "wof:placetype":"locality"
},
  "geometry": {"coordinates":[40.0216,52.3826],"type":"Point"}
}