{
  "type": "Feature",
  "properties": {
    "gn:admin1_code":"13",
    "gn:asciiname":"Novaya Pokrovka",
    "gn:country_code":"RU",
    "gn:dem":202,
    "gn:feature_class":"P",
    "gn:feature_code":"PPL",
    "gn:name":"Novaya Pokrovka",
    "gn:population":0,
    "gn:timezone":"Asia/Yekaterinburg",
    "iso:country":"RU",
    "name:rus_x_preferred":[
        "\u041d\u043e\u0432\u0430\u044f \u041f\u043e\u043a\u0440\u043e\u0432\u043a\u0430"
    ],
    "wof:name":"Novaya Pokrovka",
    "wof:placetype":"locality"
},
  "geometry": {"coordinates":[61.83333,54.51667],"type":"Point"}
}