{
  "type": "Feature",
  "properties": {
    "gn:admin1_code":"20",
    "gn:asciiname":"Ivanov Mys",
    "gn:country_code":"RU",
    "gn:dem":226,
    "gn:feature_class":"P",
    "gn:feature_code":"PPL",
    "gn:name":"Ivanov Mys",
    "gn:population":0,
    "gn:timezone":"Asia/Irkutsk",
    "iso:country":"RU",
    "name:eng_x_preferred":[
        "Ivanov Mys"
    ],
    "name:rus_x_preferred":[
        "\u0418\u0432\u0430\u043d\u043e\u0432 \u041c\u044b\u0441"
    ],
    "name:rus_x_variant":[
        "\u0418\u0432\u0430\u043d\u043e\u0432-\u041c\u044b\u0441"
    ],
    "wof:name":"Ivanov Mys",
    "wof:placetype":"locality"
},
  "geometry": {"coordinates":[98.4085,56.512],"type":"Point"}
}