{
  "type": "Feature",
  "properties": {
    "gn:admin1_code":"17",
    "gn:admin2_code":"Shamil'skiy Rayon",
    "gn:asciiname":"Teletl'",
    "gn:country_code":"RU",
    "gn:dem":1430,
    "gn:feature_class":"P",
    "gn:feature_code":"PPL",
    "gn:name":"Teletl\u2019",
    "gn:population":0,
    "gn:timezone":"Europe/Moscow",
    "iso:country":"RU",
    "name:eng_x_preferred":[
        "Teletl'"
    ],
    "name:nor_x_preferred":[
        "Teletl"
    ],
    "name:rus_x_preferred":[
        "\u0422\u0435\u043b\u0435\u0442\u043b\u044c"
    ],
    "name:und_x_variant":[
        "Teletl\u2019"
    ],
    "wof:name":"Teletl'",
    "wof:placetype":"locality"
},
  "geometry": {"coordinates":[46.73202,42.42902],"type":"Point"}
}