{
  "type": "Feature",
  "properties": {
    "gn:admin1_code":"20",
    "gn:asciiname":"Zarechnaya",
    "gn:country_code":"RU",
    "gn:dem":802,
    "gn:feature_class":"P",
    "gn:feature_code":"PPL",
    "gn:name":"Zarechnaya",
    "gn:population":0,
    "gn:timezone":"Asia/Irkutsk",
    "iso:country":"RU",
    "wof:name":"Zarechnaya",
    "wof:placetype":"locality"
},
  "geometry": {"coordinates":[107.28333000000001,54.98333],"type":"Point"}
}