{
  "type": "Feature",
  "properties": {
    "gn:admin1_code":"65",
    "gn:asciiname":"Kommunar",
    "gn:country_code":"RU",
    "gn:dem":118,
    "gn:feature_class":"P",
    "gn:feature_code":"PPL",
    "gn:name":"Kommunar",
    "gn:population":0,
    "gn:timezone":"Europe/Samara",
    "iso:country":"RU",
    "name:aze_x_preferred":[
        "Kommunar adas\u0131"
    ],
    "name:bel_x_preferred":[
        "\u041a\u0430\u043c\u0443\u043d\u0430\u0440"
    ],
    "name:ceb_x_preferred":[
        "Kommunar"
    ],
    "name:deu_x_preferred":[
        "Kommunar"
    ],
    "name:hye_x_preferred":[
        "\u053f\u0578\u0574\u0574\u0578\u0582\u0576\u0561\u0580"
    ],
    "name:ita_x_preferred":[
        "Kommunar"
    ],
    "name:lit_x_preferred":[
        "Komunaras"
    ],
    "name:rus_x_preferred":[
        "\u041a\u043e\u043c\u043c\u0443\u043d\u0430\u0440"
    ],
    "name:sco_x_preferred":[
        "Kommunar"
    ],
    "name:spa_x_preferred":[
        "Komunar"
    ],
    "name:ukr_x_preferred":[
        "\u041a\u043e\u043c\u0443\u043d\u0430\u0440"
    ],
    "wof:name":"Kommunar",
    "wof:placetype":"locality"
},
  "geometry": {"coordinates":[50.28614,52.65289],"type":"Point"}
}