{
  "type": "Feature",
  "properties": {
    "gn:admin1_code":"42",
    "gn:asciiname":"Simagino",
    "gn:cc2":"RU",
    "gn:country_code":"RU",
    "gn:dem":89,
    "gn:feature_class":"P",
    "gn:feature_code":"PPL",
    "gn:name":"Simagino",
    "gn:population":0,
    "gn:timezone":"Europe/Moscow",
    "iso:country":"RU",
    "name:eng_x_preferred":[
        "Simagino"
    ],
    "name:fin_x_preferred":[
        "Joutselk\u00e4"
    ],
    "name:rus_x_preferred":[
        "\u0421\u0438\u043c\u0430\u0433\u0438\u043d\u043e"
    ],
    "name:und_x_variant":[
        "Ioutsel'kya",
        "Ioutsel'khya"
    ],
    "wof:name":"Simagino",
    "wof:placetype":"locality"
},
  "geometry": {"coordinates":[29.82265,60.27549000000001],"type":"Point"}
}