{
  "type": "Feature",
  "properties": {
    "gn:admin1_code":"60",
    "gn:asciiname":"Orel",
    "gn:country_code":"RU",
    "gn:dem":45,
    "gn:feature_class":"P",
    "gn:feature_code":"PPL",
    "gn:name":"Or\u00ebl",
    "gn:population":0,
    "gn:timezone":"Europe/Moscow",
    "iso:country":"RU",
    "name:bel_x_preferred":[
        "\u0410\u0440\u043e\u043b"
    ],
    "name:bre_x_preferred":[
        "Oryol"
    ],
    "name:ceb_x_preferred":[
        "Orel"
    ],
    "name:ces_x_preferred":[
        "Orel"
    ],
    "name:deu_x_preferred":[
        "Orel"
    ],
    "name:fra_x_preferred":[
        "Orel"
    ],
    "name:ita_x_preferred":[
        "Orel"
    ],
    "name:jpn_x_preferred":[
        "\u30aa\u30ea\u30e7\u30fc\u30eb"
    ],
    "name:nld_x_preferred":[
        "Orel"
    ],
    "name:rus_x_preferred":[
        "\u041e\u0440\u0451\u043b"
    ],
    "name:slk_x_preferred":[
        "Orel"
    ],
    "name:slv_x_preferred":[
        "Orel"
    ],
    "name:swe_x_preferred":[
        "Orel"
    ],
    "name:und_x_variant":[
        "Or\u00ebl",
        "\u041e\u0440\u0451\u043b"
    ],
    "wof:name":"Orel",
    "wof:placetype":"locality"
},
  "geometry": {"coordinates":[27.77917,58.94349],"type":"Point"}
}