{
  "type": "Feature",
  "properties": {
    "gn:admin1_code":"17.0",
    "gn:asciiname":"Bil'bil'-Kazmalyar",
    "gn:country_code":"RU",
    "gn:dem":25,
    "gn:feature_class":"P",
    "gn:feature_code":"PPL",
    "gn:name":"Bil\u2019bil\u2019-Kazmalyar",
    "gn:population":0,
    "gn:timezone":"Europe/Moscow",
    "iso:country":"RU",
    "name:aze_x_preferred":[
        "Bilbil"
    ],
    "name:aze_x_variant":[
        "Bilbil Qazmalar"
    ],
    "name:rus_x_preferred":[
        "\u0411\u0438\u043b\u044c\u0431\u0438\u043b\u044c-\u041a\u0430\u0437\u043c\u0430\u043b\u044f\u0440"
    ],
    "name:und_x_variant":[
        "Bil\u2019bilkent",
        "Bil\u2019bil\u2019-Kazmalyar"
    ],
    "wof:name":"Bil'bil'-Kazmalyar",
    "wof:placetype":"locality"
},
  "geometry": {"coordinates":[48.5448,41.82188],"type":"Point"}
}