{
  "type": "Feature",
  "properties": {
    "gn:admin1_code":"23",
    "gn:asciiname":"Ganino",
    "gn:country_code":"RU",
    "gn:dem":13,
    "gn:feature_class":"P",
    "gn:feature_code":"PPL",
    "gn:name":"Ganino",
    "gn:population":0,
    "gn:timezone":"Europe/Kaliningrad",
    "iso:country":"RU",
    "name:rus_x_preferred":[
        "\u0413\u0430\u043d\u0438\u043d\u043e"
    ],
    "wof:name":"Ganino",
    "wof:placetype":"locality"
},
  "geometry": {"coordinates":[21.50887,54.6579],"type":"Point"}
}