{
  "type": "Feature",
  "properties": {
    "gn:admin1_code":"20",
    "gn:asciiname":"Kamenka",
    "gn:country_code":"RU",
    "gn:dem":413,
    "gn:feature_class":"P",
    "gn:feature_code":"PPL",
    "gn:name":"Kamenka",
    "gn:population":0,
    "gn:timezone":"Asia/Irkutsk",
    "iso:country":"RU",
    "name:eng_x_preferred":[
        "Kamenka"
    ],
    "name:nor_x_preferred":[
        "Kamenka"
    ],
    "name:rus_x_preferred":[
        "\u041a\u0430\u043c\u0435\u043d\u043a\u0430"
    ],
    "name:und_x_variant":[
        "Verkhneye Ostrozhnoye",
        "Kamenskoye",
        "Kamenka",
        "\u041a\u0430\u043c\u0435\u043d\u043a\u0430"
    ],
    "wof:name":"Kamenka",
    "wof:placetype":"locality"
},
  "geometry": {"coordinates":[103.37111,53.16694],"type":"Point"}
}