{
  "type": "Feature",
  "properties": {
    "gn:admin1_code":"84",
    "gn:asciiname":"Novoaleksandrovskiy",
    "gn:country_code":"RU",
    "gn:dem":59,
    "gn:feature_class":"P",
    "gn:feature_code":"PPL",
    "gn:name":"Novoaleksandrovskiy",
    "gn:population":0,
    "gn:timezone":"Europe/Volgograd",
    "iso:country":"RU",
    "name:eng_x_preferred":[
        "Novoaleksandrovskiy"
    ],
    "name:nor_x_preferred":[
        "Novoaleksandrovskij"
    ],
    "name:rus_x_preferred":[
        "\u041d\u043e\u0432\u043e\u0430\u043b\u0435\u043a\u0441\u0430\u043d\u0434\u0440\u043e\u0432\u0441\u043a\u0438\u0439"
    ],
    "name:und_x_variant":[
        "\u041d\u043e\u0432\u043e\u0430\u043b\u0435\u043a\u0441\u0430\u043d\u0434\u0440\u043e\u0432\u0441\u043a\u0438\u0439",
        "Novoaleksandrovskiy"
    ],
    "wof:name":"Novoaleksandrovskiy",
    "wof:placetype":"locality"
},
  "geometry": {"coordinates":[42.7054,49.632],"type":"Point"}
}