{
  "type": "Feature",
  "properties": {
    "gn:admin1_code":"52.0",
    "gn:asciiname":"Berezhok",
    "gn:country_code":"RU",
    "gn:dem":65,
    "gn:feature_class":"P",
    "gn:feature_code":"PPL",
    "gn:name":"Berezhok",
    "gn:population":0,
    "gn:timezone":"Europe/Moscow",
    "iso:country":"RU",
    "name:hye_x_preferred":[
        "\u0532\u0565\u0580\u0565\u056a\u0578\u056f"
    ],
    "name:nor_x_preferred":[
        "Berezjok"
    ],
    "name:pol_x_preferred":[
        "Bere\u017cek"
    ],
    "name:ron_x_preferred":[
        "Berejok"
    ],
    "name:rus_x_preferred":[
        "\u0411\u0435\u0440\u0435\u0436\u043e\u043a"
    ],
    "name:ukr_x_preferred":[
        "\u0411\u0435\u0440\u0435\u0436\u043e\u043a"
    ],
    "name:zho_x_preferred":[
        "\u5225\u5217\u82e5\u514b"
    ],
    "wof:name":"Berezhok",
    "wof:placetype":"locality"
},
  "geometry": {"coordinates":[30.46793,58.04368],"type":"Point"}
}