{
  "type": "Feature",
  "properties": {
    "gn:admin1_code":"16",
    "gn:asciiname":"Ismendery",
    "gn:country_code":"RU",
    "gn:dem":169,
    "gn:feature_class":"P",
    "gn:feature_code":"PPL",
    "gn:name":"Ismendery",
    "gn:population":0,
    "gn:timezone":"Europe/Moscow",
    "iso:country":"RU",
    "name:rus_x_preferred":[
        "\u0418\u0441\u043c\u0435\u043d\u0434\u0435\u0440\u044b"
    ],
    "name:und_x_variant":[
        "\u0418\u0441\u043c\u0435\u043d\u0434\u0435\u0440\u044b"
    ],
    "wof:name":"Ismendery",
    "wof:placetype":"locality"
},
  "geometry": {"coordinates":[46.5448,55.81671],"type":"Point"}
}