{
  "type": "Feature",
  "properties": {
    "gn:admin1_code":"60",
    "gn:asciiname":"Gverezdka",
    "gn:country_code":"RU",
    "gn:dem":58,
    "gn:feature_class":"P",
    "gn:feature_code":"PPL",
    "gn:name":"Gver\u00ebzdka",
    "gn:population":0,
    "gn:timezone":"Europe/Moscow",
    "iso:country":"RU",
    "name:rus_x_preferred":[
        "Gver\u00ebzdka"
    ],
    "name:rus_x_variant":[
        "\u0413\u0432\u0435\u0440\u0451\u0437\u0434\u043a\u0430"
    ],
    "name:und_x_variant":[
        "Gverestka"
    ],
    "wof:name":"Gverezdka",
    "wof:placetype":"locality"
},
  "geometry": {"coordinates":[28.28997,58.67656],"type":"Point"}
}