{
  "type": "Feature",
  "properties": {
    "gn:admin1_code":"17.0",
    "gn:asciiname":"Dzhul'dzhinif",
    "gn:country_code":"RU",
    "gn:dem":912,
    "gn:feature_class":"P",
    "gn:feature_code":"PPL",
    "gn:name":"Dzhul\u2019dzhinif",
    "gn:population":0,
    "gn:timezone":"Europe/Moscow",
    "iso:country":"RU",
    "name:rus_x_preferred":[
        "\u0414\u0436\u0443\u043b\u044c\u0434\u0436\u0438\u043d\u0438\u0444"
    ],
    "name:und_x_variant":[
        "Dzhulzhinif",
        "Dzhul\u2019dzhinif"
    ],
    "wof:name":"Dzhul'dzhinif",
    "wof:placetype":"locality"
},
  "geometry": {"coordinates":[47.89794000000001,41.95472],"type":"Point"}
}