{
  "type": "Feature",
  "properties": {
    "gn:admin1_code":"63",
    "gn:asciiname":"Tinyay",
    "gn:country_code":"RU",
    "gn:dem":361,
    "gn:feature_class":"P",
    "gn:feature_code":"PPL",
    "gn:name":"Tinyay",
    "gn:population":0,
    "gn:timezone":"Asia/Yakutsk",
    "iso:country":"RU",
    "wof:name":"Tinyay",
    "wof:placetype":"locality"
},
  "geometry": {"coordinates":[131.59999999999999,67.95],"type":"Point"}
}