{
  "type": "Feature",
  "properties": {
    "gn:admin1_code":"62",
    "gn:asciiname":"Knyazhoye",
    "gn:country_code":"RU",
    "gn:dem":122,
    "gn:feature_class":"P",
    "gn:feature_code":"PPL",
    "gn:name":"Knyazhoye",
    "gn:population":0,
    "gn:timezone":"Europe/Moscow",
    "iso:country":"RU",
    "name:eng_x_preferred":[
        "Knyazhoye"
    ],
    "name:nor_x_preferred":[
        "Knjazjoje"
    ],
    "name:rus_x_preferred":[
        "\u041a\u043d\u044f\u0436\u043e\u0435"
    ],
    "name:und_x_variant":[
        "Knyazhevo",
        "\u041a\u043d\u044f\u0436\u043e\u0435",
        "Knyazhoye"
    ],
    "wof:name":"Knyazhoye",
    "wof:placetype":"locality"
},
  "geometry": {"coordinates":[40.1758,53.8923],"type":"Point"}
}