{
  "type": "Feature",
  "properties": {
    "gn:admin1_code":"88",
    "gn:asciiname":"Shakhovka",
    "gn:country_code":"RU",
    "gn:dem":120,
    "gn:feature_class":"P",
    "gn:feature_code":"PPL",
    "gn:name":"Shakhovka",
    "gn:population":0,
    "gn:timezone":"Europe/Moscow",
    "iso:country":"RU",
    "name:rus_x_preferred":[
        "\u0428\u0430\u0445\u043e\u0432\u043a\u0430"
    ],
    "name:und_x_variant":[
        "\u0428\u0430\u0445\u043e\u0432\u043a\u0430"
    ],
    "wof:name":"Shakhovka",
    "wof:placetype":"locality"
},
  "geometry": {"coordinates":[38.98071,58.51846],"type":"Point"}
}