{
  "type": "Feature",
  "properties": {
    "gn:admin1_code":"41",
    "gn:asciiname":"Liman",
    "gn:country_code":"RU",
    "gn:dem":179,
    "gn:feature_class":"P",
    "gn:feature_code":"PPL",
    "gn:name":"Liman",
    "gn:population":0,
    "gn:timezone":"Europe/Moscow",
    "iso:country":"RU",
    "name:aze_x_preferred":[
        "Liman"
    ],
    "name:bel_x_preferred":[
        "\u041b\u0456\u043c\u0430\u043d"
    ],
    "name:bul_x_preferred":[
        "\u041b\u0438\u043c\u0430\u043d"
    ],
    "name:ceb_x_preferred":[
        "Liman"
    ],
    "name:deu_x_preferred":[
        "Liman"
    ],
    "name:heb_x_preferred":[
        "\u05dc\u05d9\u05de\u05df"
    ],
    "name:hrv_x_preferred":[
        "Liman"
    ],
    "name:hye_x_preferred":[
        "\u053c\u056b\u0574\u0561\u0576"
    ],
    "name:ita_x_preferred":[
        "Liman"
    ],
    "name:pol_x_preferred":[
        "Liman"
    ],
    "name:rus_x_preferred":[
        "\u041b\u0438\u043c\u0430\u043d"
    ],
    "name:slk_x_preferred":[
        "Liman"
    ],
    "name:srp_x_preferred":[
        "\u041b\u0438\u043c\u0430\u043d"
    ],
    "name:swe_x_preferred":[
        "Liman"
    ],
    "name:ukr_x_preferred":[
        "\u041b\u0438\u043c\u0430\u043d"
    ],
    "wof:name":"Liman",
    "wof:placetype":"locality"
},
  "geometry": {"coordinates":[36.3526,52.0948],"type":"Point"}
}