{
  "type": "Feature",
  "properties": {
    "gn:admin1_code":"54",
    "gn:asciiname":"Pogranichno-Grigor'yevka",
    "gn:country_code":"RU",
    "gn:dem":106,
    "gn:feature_class":"P",
    "gn:feature_code":"PPL",
    "gn:name":"Pogranichno-Grigor\u2019yevka",
    "gn:population":0,
    "gn:timezone":"Asia/Omsk",
    "iso:country":"RU",
    "name:rus_x_preferred":[
        "\u041f\u043e\u0433\u0440\u0430\u043d\u0438\u0447\u043d\u043e-\u0413\u0440\u0438\u0433\u043e\u0440\u044c\u0435\u0432\u043a\u0430"
    ],
    "name:und_x_variant":[
        "Pofranichno-Grigor\u2019yevskoye",
        "Pogranichno-Grugor\u2019yevskiy",
        "Pogranichno-Grigor\u2019yevka"
    ],
    "wof:name":"Pogranichno-Grigor'yevka",
    "wof:placetype":"locality"
},
  "geometry": {"coordinates":[75.2898,54.1033],"type":"Point"}
}