{
  "type": "Feature",
  "properties": {
    "gn:admin1_code":"47",
    "gn:asciiname":"Voropayevka",
    "gn:country_code":"RU",
    "gn:dem":136,
    "gn:feature_class":"P",
    "gn:feature_code":"PPL",
    "gn:name":"Voropayevka",
    "gn:population":0,
    "gn:timezone":"Europe/Moscow",
    "iso:country":"RU",
    "name:rus_x_preferred":[
        "\u0412\u043e\u0440\u044b\u043f\u0430\u0435\u0432\u043a\u0430"
    ],
    "name:und_x_variant":[
        "Vyropayevka",
        "Vyroparevka",
        "Voropayevka"
    ],
    "wof:name":"Voropayevka",
    "wof:placetype":"locality"
},
  "geometry": {"coordinates":[38.64708,55.13786],"type":"Point"}
}