{
  "type": "Feature",
  "properties": {
    "gn:admin1_code":"10",
    "gn:asciiname":"Zaus'ye",
    "gn:country_code":"RU",
    "gn:dem":181,
    "gn:feature_class":"P",
    "gn:feature_code":"PPL",
    "gn:name":"Zaus\u2019ye",
    "gn:population":0,
    "gn:timezone":"Europe/Moscow",
    "iso:country":"RU",
    "name:rus_x_preferred":[
        "\u0417\u0430\u0443\u0441\u044c\u0435"
    ],
    "name:und_x_variant":[
        "Zaus\u2019ye"
    ],
    "wof:name":"Zaus'ye",
    "wof:placetype":"locality"
},
  "geometry": {"coordinates":[33.3386,53.1491],"type":"Point"}
}