{
  "type": "Feature",
  "properties": {
    "gn:admin1_code":"33",
    "gn:asciiname":"Malyy Satnur",
    "gn:country_code":"RU",
    "gn:dem":107,
    "gn:feature_class":"P",
    "gn:feature_code":"PPL",
    "gn:name":"Malyy Satnur",
    "gn:population":0,
    "gn:timezone":"Europe/Kirov",
    "iso:country":"RU",
    "name:rus_x_preferred":[
        "\u041c\u0430\u043b\u044b\u0439 \u0421\u0430\u0442\u043d\u0443\u0440"
    ],
    "wof:name":"Malyy Satnur",
    "wof:placetype":"locality"
},
  "geometry": {"coordinates":[50.9564,56.5639],"type":"Point"}
}