{
  "type": "Feature",
  "properties": {
    "gn:admin1_code":"47",
    "gn:asciiname":"Smenki",
    "gn:country_code":"RU",
    "gn:dem":113,
    "gn:feature_class":"P",
    "gn:feature_code":"PPL",
    "gn:name":"Smenki",
    "gn:population":0,
    "gn:timezone":"Europe/Moscow",
    "iso:country":"RU",
    "name:rus_x_preferred":[
        "\u0421\u043c\u0435\u043d\u043a\u0438"
    ],
    "wof:name":"Smenki",
    "wof:placetype":"locality"
},
  "geometry": {"coordinates":[37.55,56.81667],"type":"Point"}
}