{
  "type": "Feature",
  "properties": {
    "gn:admin1_code":"52",
    "gn:asciiname":"Zaborov'ye",
    "gn:country_code":"RU",
    "gn:dem":106,
    "gn:feature_class":"P",
    "gn:feature_code":"PPL",
    "gn:name":"Zaborov\u2019ye",
    "gn:population":0,
    "gn:timezone":"Europe/Moscow",
    "iso:country":"RU",
    "name:rus_x_preferred":[
        "\u0417\u0430\u0431\u043e\u0440\u043e\u0432\u044c\u0435"
    ],
    "name:und_x_variant":[
        "Zaborov\u2019ye"
    ],
    "wof:name":"Zaborov'ye",
    "wof:placetype":"locality"
},
  "geometry": {"coordinates":[32.0705,57.3185],"type":"Point"}
}