{
  "type": "Feature",
  "properties": {
    "gn:admin1_code":"33",
    "gn:asciiname":"Semintsy",
    "gn:country_code":"RU",
    "gn:dem":194,
    "gn:feature_class":"P",
    "gn:feature_code":"PPL",
    "gn:name":"Semintsy",
    "gn:population":0,
    "gn:timezone":"Europe/Kirov",
    "iso:country":"RU",
    "name:rus_x_preferred":[
        "\u0421\u0435\u043c\u0438\u043d\u0446\u044b"
    ],
    "name:und_x_variant":[
        "\u0421\u0435\u043c\u0438\u043d\u0446\u044b"
    ],
    "wof:name":"Semintsy",
    "wof:placetype":"locality"
},
  "geometry": {"coordinates":[49.73333,58.93333000000001],"type":"Point"}
}