{
  "type": "Feature",
  "properties": {
    "gn:country":"RU",
    "gn:fcode":"PPL",
    "gn:pop":2232,
    "iso:country":"RU",
    "name:che_x_preferred":[
        "\u0421\u0442\u0430\u0440\u0430\u044f \u0422\u043e\u0440\u043e\u043f\u0430"
    ],
    "name:eng_x_preferred":[
        "Staraya Toropa"
    ],
    "name:nor_x_preferred":[
        "Staraja Toropa"
    ],
    "name:rus_x_preferred":[
        "\u0421\u0442\u0430\u0440\u0430\u044f \u0422\u043e\u0440\u043e\u043f\u0430"
    ],
    "name:srp_x_preferred":[
        "\u0421\u0442\u0430\u0440\u0430\u0458\u0430 \u0422\u043e\u0440\u043e\u043f\u0430"
    ],
    "name:unk_x_variant":[
        "Toropa"
    ],
    "qs:name":"Staraya Toropa",
    "qs:photos_9r":0,
    "qs:photos_sr":0,
    "qs:pop_sr":"4",
    "wd:wordcount":1177,
    "wof:name":"Staraya Toropa",
    "wof:placetype":"locality",
    "wof:population":2232
},
  "geometry": {"coordinates":[31.67018,56.28012],"type":"Point"}
}