{
  "type": "Feature",
  "properties": {
    "gn:admin1_code":"84.0",
    "gn:asciiname":"Desyat' Let Oktyabrya",
    "gn:country_code":"RU",
    "gn:dem":126,
    "gn:feature_class":"P",
    "gn:feature_code":"PPL",
    "gn:name":"Desyat\u2019 Let Oktyabrya",
    "gn:population":0,
    "gn:timezone":"Europe/Volgograd",
    "iso:country":"RU",
    "name:rus_x_preferred":[
        "\u0414\u0435\u0441\u044f\u0442\u044c \u041b\u0435\u0442 \u041e\u043a\u0442\u044f\u0431\u0440\u044f"
    ],
    "name:und_x_variant":[
        "Desyat\u2019 Let Oktyabrya"
    ],
    "wof:name":"Desyat' Let Oktyabrya",
    "wof:placetype":"locality"
},
  "geometry": {"coordinates":[43.38333,48.75],"type":"Point"}
}