{
  "type": "Feature",
  "properties": {
    "gn:admin1_code":"77",
    "gn:asciiname":"Cherkunovo",
    "gn:country_code":"RU",
    "gn:dem":203,
    "gn:feature_class":"P",
    "gn:feature_code":"PPL",
    "gn:name":"Cherkunovo",
    "gn:population":0,
    "gn:timezone":"Europe/Moscow",
    "iso:country":"RU",
    "name:nor_x_preferred":[
        "Tsjerkunovo"
    ],
    "name:rus_x_preferred":[
        "\u0427\u0435\u0440\u043a\u0443\u043d\u043e\u0432\u043e"
    ],
    "wof:name":"Cherkunovo",
    "wof:placetype":"locality"
},
  "geometry": {"coordinates":[35.07749,56.24531],"type":"Point"}
}