{
  "type": "Feature",
  "properties": {
    "gn:country":"RU",
    "gn:fcode":"PPLX",
    "gn:population":27000,
    "iso:country":"RU",
    "name:ara_x_preferred":[
        "\u0632\u0627\u0631\u064a\u0627"
    ],
    "name:bul_x_preferred":[
        "\u0417\u0430\u0440\u044f"
    ],
    "name:cat_x_preferred":[
        "Zaria"
    ],
    "name:ces_x_preferred":[
        "Zarja"
    ],
    "name:dan_x_preferred":[
        "Zarja"
    ],
    "name:deu_x_preferred":[
        "Sarja"
    ],
    "name:eng_x_preferred":[
        "Zarya"
    ],
    "name:est_x_preferred":[
        "Zarja"
    ],
    "name:fin_x_preferred":[
        "Zarya"
    ],
    "name:fra_x_preferred":[
        "Zarya"
    ],
    "name:hun_x_preferred":[
        "Zarja"
    ],
    "name:ind_x_preferred":[
        "Zarya"
    ],
    "name:ita_x_preferred":[
        "Zarja"
    ],
    "name:jpn_x_preferred":[
        "\u30b6\u30fc\u30ea\u30e3"
    ],
    "name:kor_x_preferred":[
        "\uc790\ub7b4 \ubaa8\ub4c8"
    ],
    "name:lat_x_preferred":[
        "Zaria"
    ],
    "name:lav_x_preferred":[
        "Zarja"
    ],
    "name:lit_x_preferred":[
        "Zaria"
    ],
    "name:ltz_x_preferred":[
        "Sarja"
    ],
    "name:msa_x_preferred":[
        "Zarya"
    ],
    "name:nld_x_preferred":[
        "Zarya"
    ],
    "name:nob_x_preferred":[
        "Zarja"
    ],
    "name:pol_x_preferred":[
        "Zarja"
    ],
    "name:por_x_preferred":[
        "Zarya"
    ],
    "name:rus_x_preferred":[
        "\u0417\u0430\u0440\u044f"
    ],
    "name:slk_x_preferred":[
        "Zaria"
    ],
    "name:spa_x_preferred":[
        "Zary\u00e1"
    ],
    "name:srp_x_preferred":[
        "\u0417\u043e\u0440\u0430"
    ],
    "name:swe_x_preferred":[
        "Zarja"
    ],
    "name:tam_x_preferred":[
        "\u0b9a\u0bb0\u0bcd\u0baf\u0bbe"
    ],
    "name:tha_x_preferred":[
        "\u0e0b\u0e32\u0e23\u0e4c\u0e22\u0e32"
    ],
    "name:ukr_x_preferred":[
        "\u0417\u0430\u0440\u044f"
    ],
    "name:vie_x_preferred":[
        "Zarya"
    ],
    "name:zho_x_preferred":[
        "\u66d9\u5149\u865f\u529f\u80fd\u8ca8\u8259"
    ],
    "qs:name":"Zarya",
    "qs:photos_9r":0,
    "qs:photos_sr":0,
    "qs:pop_sr":"7",
    "wd:wordcount":887,
    "wof:name":"Zarya",
    "wof:placetype":"neighbourhood",
    "wof:population":27000
},
  "geometry": {"coordinates":[38.09578,55.75533],"type":"Point"}
}