{
  "type": "Feature",
  "properties": {
    "gn:country":"RU",
    "gn:fcode":"PPLX",
    "gn:pop":27000,
    "iso:country":"RU",
    "name:rus_x_preferred":[
        "\u0417\u0430\u0440\u044f"
    ],
    "qs:name":"Zarya",
    "qs:photos_9r":0,
    "qs:photos_sr":0,
    "qs:pop_sr":"7",
    "wd:wordcount":887,
    "wof:name":"Zarya",
    "wof:placetype":"neighbourhood",
    "wof:population":27000
},
  "geometry": {"coordinates":[38.09578,55.75533],"type":"Point"}
}