{
  "type": "Feature",
  "properties": {
    "gn:admin1_code":"71",
    "gn:asciiname":"Veterok",
    "gn:country_code":"RU",
    "gn:dem":77,
    "gn:feature_class":"P",
    "gn:feature_code":"PPL",
    "gn:name":"Veterok",
    "gn:population":0,
    "gn:timezone":"Asia/Yekaterinburg",
    "iso:country":"RU",
    "name:rus_x_preferred":[
        "\u0412\u0435\u0442\u0435\u0440\u043e\u043a"
    ],
    "wof:name":"Veterok",
    "wof:placetype":"locality"
},
  "geometry": {"coordinates":[63.07625,57.81047],"type":"Point"}
}