{
  "type": "Feature",
  "properties": {
    "gn:admin1_code":"91",
    "gn:asciiname":"Kozhevnikova",
    "gn:country_code":"RU",
    "gn:dem":110,
    "gn:feature_class":"P",
    "gn:feature_code":"PPL",
    "gn:name":"Kozhevnikova",
    "gn:population":0,
    "gn:timezone":"Asia/Krasnoyarsk",
    "iso:country":"RU",
    "name:rus_x_preferred":[
        "\u041a\u043e\u0436\u0435\u0432\u043d\u0438\u043a\u043e\u0432\u0430"
    ],
    "wof:name":"Kozhevnikova",
    "wof:placetype":"locality"
},
  "geometry": {"coordinates":[88.84999999999999,59.76667],"type":"Point"}
}