{
  "type": "Feature",
  "properties": {
    "gn:admin1_code":"70",
    "gn:asciiname":"Tokmachan",
    "gn:cc2":"RU",
    "gn:country_code":"RU",
    "gn:dem":66,
    "gn:feature_class":"P",
    "gn:feature_code":"PPL",
    "gn:name":"Tokmachan",
    "gn:population":0,
    "gn:timezone":"Europe/Moscow",
    "iso:country":"RU",
    "name:und_x_variant":[
        "Takmacha",
        "Tokmacha",
        "Tokmachan"
    ],
    "wof:name":"Tokmachan",
    "wof:placetype":"locality"
},
  "geometry": {"coordinates":[43.36583,45.80667],"type":"Point"}
}