{
  "type": "Feature",
  "properties": {
    "gn:admin1_code":"38.0",
    "gn:asciiname":"Kapustin",
    "gn:country_code":"RU",
    "gn:dem":100,
    "gn:feature_class":"P",
    "gn:feature_code":"PPL",
    "gn:name":"Kapustin",
    "gn:population":0,
    "gn:timezone":"Europe/Moscow",
    "iso:country":"RU",
    "name:rus_x_preferred":[
        "\u041a\u0430\u043f\u0443\u0441\u0442\u0438\u043d"
    ],
    "wof:name":"Kapustin",
    "wof:placetype":"locality"
},
  "geometry": {"coordinates":[39.92396,44.89822],"type":"Point"}
}