{
  "type": "Feature",
  "properties": {
    "gn:admin1_code":"53",
    "gn:asciiname":"Batrak",
    "gn:country_code":"RU",
    "gn:dem":109,
    "gn:feature_class":"P",
    "gn:feature_code":"PPL",
    "gn:name":"Batrak",
    "gn:population":0,
    "gn:timezone":"Asia/Novosibirsk",
    "iso:country":"RU",
    "name:aze_x_preferred":[
        "Batrak"
    ],
    "name:bak_x_preferred":[
        "\u0411\u0430\u0442\u0440\u0430\u043a"
    ],
    "name:che_x_preferred":[
        "\u0411\u0430\u0442\u0440\u0430\u043a"
    ],
    "name:hye_x_preferred":[
        "\u0532\u0561\u057f\u0580\u0561\u056f"
    ],
    "name:kaz_x_preferred":[
        "\u0411\u0430\u0442\u0440\u0430\u043a"
    ],
    "name:kir_x_preferred":[
        "\u0411\u0430\u0442\u0440\u0430\u043a"
    ],
    "name:nor_x_preferred":[
        "Batrak"
    ],
    "name:rus_x_preferred":[
        "\u0411\u0430\u0442\u0440\u0430\u043a"
    ],
    "name:tat_x_preferred":[
        "\u0411\u0430\u0442\u0440\u0430\u043a"
    ],
    "wof:name":"Batrak",
    "wof:placetype":"locality"
},
  "geometry": {"coordinates":[75.71666999999999,55.75],"type":"Point"}
}