{
  "type": "Feature",
  "properties": {
    "gn:admin1_code":"24.0",
    "gn:asciiname":"Shuran Khuduk",
    "gn:country_code":"RU",
    "gn:dem":4,
    "gn:feature_class":"P",
    "gn:feature_code":"PPL",
    "gn:name":"Shuran Khuduk",
    "gn:population":0,
    "gn:timezone":"Europe/Moscow",
    "iso:country":"RU",
    "wof:name":"Shuran Khuduk",
    "wof:placetype":"locality"
},
  "geometry": {"coordinates":[45.11234,47.74456],"type":"Point"}
}