{
  "type": "Feature",
  "properties": {
    "gn:admin1_code":"61",
    "gn:asciiname":"Malo-Khlopovskiy",
    "gn:cc2":"RU",
    "gn:country_code":"RU",
    "gn:dem":130,
    "gn:feature_class":"P",
    "gn:feature_code":"PPL",
    "gn:name":"Malo-Khlopovskiy",
    "gn:population":0,
    "gn:timezone":"Europe/Moscow",
    "iso:country":"RU",
    "name:rus_x_preferred":[
        "\u041c\u0430\u043b\u043e-\u0425\u043b\u043e\u043f\u043e\u0432\u0441\u043a\u0438\u0439"
    ],
    "name:und_x_variant":[
        "Yermakov",
        "Malo-Khlopovskiy",
        "\u041c\u0430\u043b\u043e-\u0425\u043b\u043e\u043f\u043e\u0432\u0441\u043a\u0438\u0439"
    ],
    "wof:name":"Malo-Khlopovskiy",
    "wof:placetype":"locality"
},
  "geometry": {"coordinates":[41.8325,48.20528],"type":"Point"}
}