{
  "type": "Feature",
  "properties": {
    "gn:admin1_code":"88.0",
    "gn:asciiname":"Bryakovo",
    "gn:country_code":"RU",
    "gn:dem":139,
    "gn:feature_class":"P",
    "gn:feature_code":"PPL",
    "gn:name":"Bryakovo",
    "gn:population":0,
    "gn:timezone":"Europe/Moscow",
    "iso:country":"RU",
    "name:rus_x_preferred":[
        "\u0411\u0440\u044f\u043a\u043e\u0432\u043e"
    ],
    "wof:name":"Bryakovo",
    "wof:placetype":"locality"
},
  "geometry": {"coordinates":[40.82549,58.45615],"type":"Point"}
}