{
  "type": "Feature",
  "properties": {
    "gn:admin1_code":"84",
    "gn:asciiname":"Glinkovskiy",
    "gn:country_code":"RU",
    "gn:dem":91,
    "gn:feature_class":"P",
    "gn:feature_code":"PPL",
    "gn:name":"Glinkovskiy",
    "gn:population":0,
    "gn:timezone":"Europe/Volgograd",
    "iso:country":"RU",
    "name:rus_x_preferred":[
        "\u0413\u043b\u0438\u043d\u043a\u043e\u0432\u0441\u043a\u0438\u0439"
    ],
    "wof:name":"Glinkovskiy",
    "wof:placetype":"locality"
},
  "geometry": {"coordinates":[41.8283,51.1132],"type":"Point"}
}