{
  "type": "Feature",
  "properties": {
    "gn:admin1_code":"47",
    "gn:asciiname":"Nizhneye Myachkovo",
    "gn:country_code":"RU",
    "gn:dem":117,
    "gn:feature_class":"P",
    "gn:feature_code":"PPL",
    "gn:name":"Nizhneye Myachkovo",
    "gn:population":0,
    "gn:timezone":"Europe/Moscow",
    "iso:country":"RU",
    "name:rus_x_preferred":[
        "\u041d\u0438\u0436\u043d\u0435\u0435 \u041c\u044f\u0447\u043a\u043e\u0432\u043e"
    ],
    "wof:name":"Nizhneye Myachkovo",
    "wof:placetype":"locality"
},
  "geometry": {"coordinates":[37.97327,55.54239000000001],"type":"Point"}
}