{
  "type": "Feature",
  "properties": {
    "gn:admin1_code":"21.0",
    "gn:asciiname":"Sokerikha",
    "gn:country_code":"RU",
    "gn:dem":127,
    "gn:feature_class":"P",
    "gn:feature_code":"PPL",
    "gn:name":"Sokerikha",
    "gn:population":0,
    "gn:timezone":"Europe/Moscow",
    "iso:country":"RU",
    "name:rus_x_preferred":[
        "\u0421\u043e\u043a\u0435\u0440\u0438\u0445\u0430"
    ],
    "wof:name":"Sokerikha",
    "wof:placetype":"locality"
},
  "geometry": {"coordinates":[41.82347,57.26533000000001],"type":"Point"}
}