{
  "type": "Feature",
  "properties": {
    "gn:admin1_code":"77",
    "gn:asciiname":"Vichikha",
    "gn:country_code":"RU",
    "gn:dem":203,
    "gn:feature_class":"P",
    "gn:feature_code":"PPL",
    "gn:name":"Vichikha",
    "gn:population":0,
    "gn:timezone":"Europe/Moscow",
    "iso:country":"RU",
    "name:rus_x_preferred":[
        "\u0412\u0438\u0447\u0438\u0445\u0430"
    ],
    "name:und_x_variant":[
        "\u0412\u0438\u0447\u0438\u0445\u0430"
    ],
    "wof:name":"Vichikha",
    "wof:placetype":"locality"
},
  "geometry": {"coordinates":[36.7211,58.3866],"type":"Point"}
}