{
  "type": "Feature",
  "properties": {
    "gn:admin1_code":"72",
    "gn:asciiname":"Zelenoye",
    "gn:country_code":"RU",
    "gn:dem":160,
    "gn:feature_class":"P",
    "gn:feature_code":"PPL",
    "gn:name":"Zel\u00ebnoye",
    "gn:population":0,
    "gn:timezone":"Europe/Moscow",
    "iso:country":"RU",
    "name:eng_x_preferred":[
        "Zel\u00ebnoye"
    ],
    "name:nor_x_preferred":[
        "Zelenoje"
    ],
    "name:rus_x_preferred":[
        "\u0417\u0435\u043b\u0435\u043d\u043e\u0435"
    ],
    "name:rus_x_variant":[
        "\u0417\u0435\u043b\u0451\u043d\u043e\u0435"
    ],
    "name:und_x_variant":[
        "Zelenaya",
        "Zel\u00ebnoye"
    ],
    "wof:name":"Zelenoye",
    "wof:placetype":"locality"
},
  "geometry": {"coordinates":[40.9353,53.2064],"type":"Point"}
}