{
  "type": "Feature",
  "properties": {
    "gn:admin1_code":"65",
    "gn:asciiname":"Yermolovka",
    "gn:country_code":"RU",
    "gn:dem":161,
    "gn:feature_class":"P",
    "gn:feature_code":"PPL",
    "gn:name":"Yermolovka",
    "gn:population":0,
    "gn:timezone":"Europe/Samara",
    "iso:country":"RU",
    "name:rus_x_preferred":[
        "\u0415\u0440\u043c\u043e\u043b\u043e\u0432\u043a\u0430"
    ],
    "wof:name":"Yermolovka",
    "wof:placetype":"locality"
},
  "geometry": {"coordinates":[50.91498,54.19743],"type":"Point"}
}