{
  "type": "Feature",
  "properties": {
    "gn:admin1_code":"33",
    "gn:asciiname":"Krutenskiy",
    "gn:country_code":"RU",
    "gn:dem":150,
    "gn:feature_class":"P",
    "gn:feature_code":"PPL",
    "gn:name":"Krutenskiy",
    "gn:population":0,
    "gn:timezone":"Europe/Kirov",
    "iso:country":"RU",
    "name:eng_x_preferred":[
        "Krutenskiy"
    ],
    "name:nor_x_preferred":[
        "Krutenskij"
    ],
    "name:rus_x_preferred":[
        "\u041a\u0440\u0443\u0442\u0435\u043d\u0441\u043a\u0438\u0439"
    ],
    "name:und_x_variant":[
        "\u041a\u0440\u0443\u0442\u0435\u043d\u0441\u043a\u0438\u0439",
        "Krutenskiy"
    ],
    "wof:name":"Krutenskiy",
    "wof:placetype":"locality"
},
  "geometry": {"coordinates":[46.87914,58.32333000000001],"type":"Point"}
}