{
  "type": "Feature",
  "properties": {
    "gn:admin1_code":"77",
    "gn:asciiname":"Bol'shoye Volkovo",
    "gn:country_code":"RU",
    "gn:dem":152,
    "gn:feature_class":"P",
    "gn:feature_code":"PPL",
    "gn:name":"Bol\u2019shoye Volkovo",
    "gn:population":0,
    "gn:timezone":"Europe/Moscow",
    "iso:country":"RU",
    "name:nor_x_preferred":[
        "Bolsjoje Volkovo"
    ],
    "name:rus_x_preferred":[
        "\u0411\u043e\u043b\u044c\u0448\u043e\u0435 \u0412\u043e\u043b\u043a\u043e\u0432\u043e"
    ],
    "name:und_x_variant":[
        "Volkovo",
        "Bol\u2019shoye Volkovo"
    ],
    "wof:name":"Bol'shoye Volkovo",
    "wof:placetype":"locality"
},
  "geometry": {"coordinates":[35.35846,56.3891],"type":"Point"}
}