{
  "type": "Feature",
  "properties": {
    "gn:admin1_code":"80.0",
    "gn:asciiname":"Lynvay",
    "gn:country_code":"RU",
    "gn:dem":257,
    "gn:feature_class":"P",
    "gn:feature_code":"PPL",
    "gn:name":"Lynvay",
    "gn:population":0,
    "gn:timezone":"Europe/Samara",
    "iso:country":"RU",
    "name:rus_x_preferred":[
        "\u041b\u044b\u043d\u0432\u0430\u0439"
    ],
    "wof:name":"Lynvay",
    "wof:placetype":"locality"
},
  "geometry": {"coordinates":[52.7089,57.3347],"type":"Point"}
}