{
  "type": "Feature",
  "properties": {
    "gn:admin1_code":"41",
    "gn:asciiname":"Dontsy",
    "gn:country_code":"RU",
    "gn:dem":191,
    "gn:feature_class":"P",
    "gn:feature_code":"PPL",
    "gn:name":"Dontsy",
    "gn:population":0,
    "gn:timezone":"Europe/Moscow",
    "iso:country":"RU",
    "name:rus_x_preferred":[
        "\u0414\u043e\u043d\u0446\u044b"
    ],
    "wof:name":"Dontsy",
    "wof:placetype":"locality"
},
  "geometry": {"coordinates":[35.7724,51.5603],"type":"Point"}
}