{
  "type": "Feature",
  "properties": {
    "gn:admin1_code":"33.0",
    "gn:asciiname":"Korsakovy",
    "gn:country_code":"RU",
    "gn:dem":115,
    "gn:feature_class":"P",
    "gn:feature_code":"PPL",
    "gn:name":"Korsakovy",
    "gn:population":0,
    "gn:timezone":"Europe/Kirov",
    "iso:country":"RU",
    "name:rus_x_preferred":[
        "\u041a\u043e\u0440\u0441\u0430\u043a\u043e\u0432\u044b"
    ],
    "name:und_x_variant":[
        "\u041a\u043e\u0440\u0441\u0430\u043a\u043e\u0432\u044b"
    ],
    "wof:name":"Korsakovy",
    "wof:placetype":"locality"
},
  "geometry": {"coordinates":[48.89906,58.39816999999999],"type":"Point"}
}