{
  "type": "Feature",
  "properties": {
    "gn:admin1_code":"77",
    "gn:asciiname":"Griblyanka",
    "gn:country_code":"RU",
    "gn:dem":166,
    "gn:feature_class":"P",
    "gn:feature_code":"PPL",
    "gn:name":"Griblyanka",
    "gn:population":0,
    "gn:timezone":"Europe/Moscow",
    "iso:country":"RU",
    "name:eng_x_preferred":[
        "Griblyanka"
    ],
    "name:nor_x_preferred":[
        "Gribljanka"
    ],
    "name:rus_x_preferred":[
        "\u0413\u0440\u0438\u0431\u043b\u044f\u043d\u043a\u0430"
    ],
    "name:und_x_variant":[
        "Pos\u00eblok Griblyanka"
    ],
    "wof:name":"Griblyanka",
    "wof:placetype":"locality"
},
  "geometry": {"coordinates":[34.76576,57.90867],"type":"Point"}
}