{
  "type": "Feature",
  "properties": {
    "gn:admin1_code":"56",
    "gn:asciiname":"Sharikhina",
    "gn:country_code":"RU",
    "gn:dem":209,
    "gn:feature_class":"P",
    "gn:feature_code":"PPL",
    "gn:name":"Sharikhina",
    "gn:population":0,
    "gn:timezone":"Europe/Moscow",
    "iso:country":"RU",
    "name:rus_x_preferred":[
        "\u0428\u0430\u0440\u0438\u0445\u0438\u043d\u0430"
    ],
    "name:und_x_variant":[
        "Sharikhino",
        "Sharikhina",
        "\u0428\u0430\u0440\u0438\u0445\u0438\u043d\u0430"
    ],
    "wof:name":"Sharikhina",
    "wof:placetype":"locality"
},
  "geometry": {"coordinates":[35.88258,53.45918],"type":"Point"}
}