{
  "type": "Feature",
  "properties": {
    "gn:admin1_code":"32",
    "gn:asciiname":"Satarino",
    "gn:country_code":"RU",
    "gn:dem":48,
    "gn:feature_class":"P",
    "gn:feature_code":"PPL",
    "gn:name":"Satarino",
    "gn:population":0,
    "gn:timezone":"Asia/Yekaterinburg",
    "iso:country":"RU",
    "name:eng_x_preferred":[
        "Satarino"
    ],
    "name:nor_x_preferred":[
        "Satarino"
    ],
    "name:rus_x_preferred":[
        "\u0421\u0430\u0442\u0430\u0440\u0438\u043d\u043e"
    ],
    "wof:name":"Satarino",
    "wof:placetype":"locality"
},
  "geometry": {"coordinates":[71.73333000000002,60.96666999999999],"type":"Point"}
}