{
  "type": "Feature",
  "properties": {
    "gn:admin1_code":"29",
    "gn:asciiname":"Mal'tsevo",
    "gn:country_code":"RU",
    "gn:dem":162,
    "gn:feature_class":"P",
    "gn:feature_code":"PPL",
    "gn:name":"Mal\u2019tsevo",
    "gn:population":0,
    "gn:timezone":"Asia/Novokuznetsk",
    "iso:country":"RU",
    "name:rus_x_preferred":[
        "\u041c\u0430\u043b\u044c\u0446\u0435\u0432\u043e"
    ],
    "name:und_x_variant":[
        "Mal\u2019tseva",
        "Mal\u2019tsevka",
        "Mal\u2019tsevo",
        "\u041c\u0430\u043b\u044c\u0446\u0435\u0432\u043e"
    ],
    "wof:name":"Mal'tsevo",
    "wof:placetype":"locality"
},
  "geometry": {"coordinates":[86.45123000000002,56.12024],"type":"Point"}
}