{
  "type": "Feature",
  "properties": {
    "gn:country":"RU",
    "gn:fcode":"PPL",
    "gn:pop":0,
    "iso:country":"RU",
    "name:fin_x_historical":[
        "Kuuj\u00e4rvi"
    ],
    "name:fin_x_preferred":[
        "Makula"
    ],
    "name:fin_x_variant":[
        "Kuuj\u00e4rvi"
    ],
    "name:rus_x_historical":[
        "\u041a\u0443\u0443\u044f\u0440\u0432\u0438"
    ],
    "name:rus_x_preferred":[
        "\u041a\u0440\u0430\u0441\u043d\u043e\u0444\u043b\u043e\u0442\u0441\u043a\u043e\u0435"
    ],
    "name:rus_x_variant":[
        "\u041a\u0443\u0443\u044f\u0440\u0432\u0438"
    ],
    "qs:name":"Krasnoflotskoye",
    "qs:name_adm0":"Russia",
    "qs:name_adm1":"Leningrad Oblast",
    "qs:photos_9r":0,
    "qs:photos_sr":0,
    "qs:placetype":"Town",
    "qs:pop_sr":"0",
    "wd:wordcount":1584,
    "wof:name":"Krasnoflotskoye",
    "wof:placetype":"locality",
    "wof:population":0
},
  "geometry": {"coordinates":[29.10401,60.34134],"type":"Point"}
}