{
  "type": "Feature",
  "properties": {
    "gn:country":"RU",
    "gn:fcode":"PPL",
    "gn:population":0,
    "iso:country":"RU",
    "name:azb_x_preferred":[
        "\u0644\u0628\u06cc\u0627\u0698\u06cc"
    ],
    "name:bel_x_preferred":[
        "\u041b\u044f\u0431\u044f\u0436\u0436\u0430"
    ],
    "name:bul_x_preferred":[
        "\u041b\u0435\u0431\u044f\u0436\u0435"
    ],
    "name:cat_x_preferred":[
        "Lebyazhye"
    ],
    "name:ceb_x_preferred":[
        "Lebyazh'ye"
    ],
    "name:che_x_preferred":[
        "\u041b\u0435\u0431\u044f\u0436\u044c\u0435"
    ],
    "name:deu_x_preferred":[
        "Lebja\u017ee"
    ],
    "name:deu_x_variant":[
        "Lebjaschje"
    ],
    "name:eng_x_preferred":[
        "Lebyazhye"
    ],
    "name:est_x_preferred":[
        "Lebja\u017eje"
    ],
    "name:fin_x_historical":[
        "Kuuj\u00e4rvi"
    ],
    "name:fin_x_preferred":[
        "Makula"
    ],
    "name:fin_x_variant":[
        "Kuuj\u00e4rvi",
        "Lep\u00e4si"
    ],
    "name:fra_x_preferred":[
        "Lebyazhye"
    ],
    "name:hye_x_preferred":[
        "\u053c\u0565\u0562\u0575\u0561\u056a\u0565"
    ],
    "name:ita_x_preferred":[
        "Lebja\u017e'e"
    ],
    "name:jpn_x_preferred":[
        "\u30ec\u30d3\u30e3\u30b8\u30a8"
    ],
    "name:nld_x_preferred":[
        "Lebyazhye"
    ],
    "name:nno_x_preferred":[
        "Lebjazje"
    ],
    "name:nob_x_preferred":[
        "Lebjazje"
    ],
    "name:oci_x_preferred":[
        "Lebyazhye"
    ],
    "name:pol_x_preferred":[
        "Lebia\u017cje"
    ],
    "name:rus_x_historical":[
        "\u041a\u0443\u0443\u044f\u0440\u0432\u0438"
    ],
    "name:rus_x_preferred":[
        "\u041a\u0440\u0430\u0441\u043d\u043e\u0444\u043b\u043e\u0442\u0441\u043a\u043e\u0435"
    ],
    "name:rus_x_variant":[
        "\u041a\u0443\u0443\u044f\u0440\u0432\u0438",
        "\u041b\u0435\u0431\u044f\u0436\u044c\u0435"
    ],
    "name:spa_x_preferred":[
        "Lebyazhye"
    ],
    "name:srp_x_preferred":[
        "\u041b\u0435\u0431\u0458\u0430\u0436\u0458\u0435"
    ],
    "name:ukr_x_preferred":[
        "\u041b\u0435\u0431'\u044f\u0436\u0435"
    ],
    "qs:name":"Krasnoflotskoye",
    "qs:name_adm0":"Russia",
    "qs:name_adm1":"Leningrad Oblast",
    "qs:photos_9r":0,
    "qs:photos_sr":0,
    "qs:placetype":"Town",
    "qs:pop_sr":"0",
    "wd:wordcount":1584,
    "wof:name":"Krasnoflotskoye",
    "wof:placetype":"locality",
    "wof:population":0
},
  "geometry": {"coordinates":[29.10401,60.34134],"type":"Point"}
}