{
  "type": "Feature",
  "properties": {
    "gn:admin1_code":"52",
    "gn:asciiname":"Dobrosli",
    "gn:country_code":"RU",
    "gn:dem":48,
    "gn:feature_class":"P",
    "gn:feature_code":"PPL",
    "gn:name":"Dobrosli",
    "gn:population":0,
    "gn:timezone":"Europe/Moscow",
    "iso:country":"RU",
    "name:rus_x_preferred":[
        "\u0414\u043e\u0431\u0440\u043e\u0441\u043b\u0438"
    ],
    "wof:name":"Dobrosli",
    "wof:placetype":"locality"
},
  "geometry": {"coordinates":[32.4219,57.65519000000001],"type":"Point"}
}