{
  "type": "Feature",
  "properties": {
    "gn:admin1_code":"80.0",
    "gn:asciiname":"Staraya Bisarka",
    "gn:country_code":"RU",
    "gn:dem":111,
    "gn:feature_class":"P",
    "gn:feature_code":"PPL",
    "gn:name":"Staraya Bisarka",
    "gn:population":0,
    "gn:timezone":"Europe/Samara",
    "iso:country":"RU",
    "name:eng_x_preferred":[
        "Staraya Bisarka"
    ],
    "name:rus_x_preferred":[
        "\u0421\u0442\u0430\u0440.\u0411\u0438\u0441\u0430\u0440\u043a\u0430"
    ],
    "name:rus_x_variant":[
        "\u0421\u0442\u0430\u0440\u0430\u044f \u0411\u0438\u0441\u0430\u0440\u043a\u0430"
    ],
    "name:und_x_variant":[
        "Bisarka"
    ],
    "wof:name":"Staraya Bisarka",
    "wof:placetype":"locality"
},
  "geometry": {"coordinates":[53.79987,56.22674],"type":"Point"}
}