{
  "type": "Feature",
  "properties": {
    "gn:admin1_code":"38",
    "gn:asciiname":"Krasnogvardeyets",
    "gn:country_code":"RU",
    "gn:dem":22,
    "gn:feature_class":"P",
    "gn:feature_code":"PPL",
    "gn:name":"Krasnogvardeyets",
    "gn:population":0,
    "gn:timezone":"Europe/Moscow",
    "iso:country":"RU",
    "name:eng_x_preferred":[
        "Krasnogvardeyets"
    ],
    "name:nor_x_preferred":[
        "Krasnogvardejets"
    ],
    "name:rus_x_preferred":[
        "\u041a\u0440\u0430\u0441\u043d\u043e\u0433\u0432\u0430\u0440\u0434\u0435\u0435\u0446"
    ],
    "wof:name":"Krasnogvardeyets",
    "wof:placetype":"locality"
},
  "geometry": {"coordinates":[39.17071,46.1617],"type":"Point"}
}