{
  "type": "Feature",
  "properties": {
    "gn:admin1_code":"46",
    "gn:asciiname":"Levzha",
    "gn:country_code":"RU",
    "gn:dem":172,
    "gn:feature_class":"P",
    "gn:feature_code":"PPL",
    "gn:name":"Levzha",
    "gn:population":0,
    "gn:timezone":"Europe/Moscow",
    "iso:country":"RU",
    "name:eng_x_preferred":[
        "Levzha"
    ],
    "name:nor_x_preferred":[
        "Levzja"
    ],
    "name:rus_x_preferred":[
        "\u041b\u0435\u0432\u0436\u0430"
    ],
    "wof:name":"Levzha",
    "wof:placetype":"locality"
},
  "geometry": {"coordinates":[45.00641,54.08421],"type":"Point"}
}