{
  "type": "Feature",
  "properties": {
    "gn:admin1_code":"52",
    "gn:asciiname":"Posad",
    "gn:country_code":"RU",
    "gn:dem":98,
    "gn:feature_class":"P",
    "gn:feature_code":"PPL",
    "gn:name":"Posad",
    "gn:population":0,
    "gn:timezone":"Europe/Moscow",
    "iso:country":"RU",
    "name:rus_x_preferred":[
        "\u041f\u043e\u0441\u0430\u0434"
    ],
    "name:und_x_variant":[
        "\u041f\u043e\u0441\u0430\u0434"
    ],
    "wof:name":"Posad",
    "wof:placetype":"locality"
},
  "geometry": {"coordinates":[32.91667,58.78333000000001],"type":"Point"}
}