{
  "type": "Feature",
  "properties": {
    "gn:admin1_code":"52",
    "gn:asciiname":"Khlebnevo",
    "gn:country_code":"RU",
    "gn:dem":149,
    "gn:feature_class":"P",
    "gn:feature_code":"PPL",
    "gn:name":"Khlebnevo",
    "gn:population":0,
    "gn:timezone":"Europe/Moscow",
    "iso:country":"RU",
    "name:rus_x_preferred":[
        "\u0425\u043b\u0435\u0431\u043d\u0435\u0432\u043e"
    ],
    "name:und_x_variant":[
        "\u0425\u043b\u0435\u0431\u043d\u0435\u0432\u043e"
    ],
    "wof:name":"Khlebnevo",
    "wof:placetype":"locality"
},
  "geometry": {"coordinates":[34.46119,58.38246],"type":"Point"}
}