{
  "type": "Feature",
  "properties": {
    "gn:admin1_code":"9.0",
    "gn:asciiname":"Batlukov",
    "gn:country_code":"RU",
    "gn:dem":110,
    "gn:feature_class":"P",
    "gn:feature_code":"PPL",
    "gn:name":"Batlukov",
    "gn:population":0,
    "gn:timezone":"Europe/Moscow",
    "iso:country":"RU",
    "name:nor_x_preferred":[
        "Batlukov"
    ],
    "name:rus_x_preferred":[
        "\u0411\u0430\u0442\u043b\u0443\u043a\u043e\u0432"
    ],
    "wof:name":"Batlukov",
    "wof:placetype":"locality"
},
  "geometry": {"coordinates":[38.8359,50.58],"type":"Point"}
}