{
  "type": "Feature",
  "properties": {
    "gn:admin1_code":"05",
    "gn:asciiname":"Taburachka",
    "gn:cc2":"RU",
    "gn:country_code":"RU",
    "gn:dem":188,
    "gn:feature_class":"P",
    "gn:feature_code":"PPL",
    "gn:name":"Taburachka",
    "gn:population":0,
    "gn:timezone":"Asia/Yakutsk",
    "iso:country":"RU",
    "name:eng_x_preferred":[
        "Taburachka"
    ],
    "name:nor_x_preferred":[
        "Taburatsjka"
    ],
    "name:rus_x_preferred":[
        "\u0422\u0430\u0431\u0443\u0440\u0430\u0447\u043a\u0430"
    ],
    "name:und_x_variant":[
        "Zimovka Kazennoye",
        "Taburochka",
        "Taburachka"
    ],
    "wof:name":"Taburachka",
    "wof:placetype":"locality"
},
  "geometry": {"coordinates":[129.58333000000002,51.95],"type":"Point"}
}