{
  "type": "Feature",
  "properties": {
    "gn:admin1_code":"67.0",
    "gn:asciiname":"Kurdyum",
    "gn:country_code":"RU",
    "gn:dem":96,
    "gn:feature_class":"P",
    "gn:feature_code":"PPL",
    "gn:name":"Kurdyum",
    "gn:population":0,
    "gn:timezone":"Europe/Saratov",
    "iso:country":"RU",
    "name:rus_x_preferred":[
        "\u041a\u0443\u0440\u0434\u044e\u043c"
    ],
    "name:und_x_variant":[
        "\u041a\u0443\u0440\u0434\u044e\u043c"
    ],
    "wof:name":"Kurdyum",
    "wof:placetype":"locality"
},
  "geometry": {"coordinates":[45.76181,51.64864],"type":"Point"}
}