{
  "type": "Feature",
  "properties": {
    "gn:admin1_code":"60",
    "gn:asciiname":"Seredkinskiy",
    "gn:country_code":"RU",
    "gn:dem":79,
    "gn:feature_class":"P",
    "gn:feature_code":"PPL",
    "gn:name":"Seredkinskiy",
    "gn:population":0,
    "gn:timezone":"Europe/Moscow",
    "iso:country":"RU",
    "name:rus_x_preferred":[
        "\u0421\u0435\u0440\u0435\u0434\u043a\u0438\u043d\u0441\u043a\u0438\u0439"
    ],
    "name:und_x_variant":[
        "\u0421\u0435\u0440\u0435\u0434\u043a\u0438\u043d\u0441\u043a\u0438\u0439"
    ],
    "wof:name":"Seredkinskiy",
    "wof:placetype":"locality"
},
  "geometry": {"coordinates":[28.68333,57.16667],"type":"Point"}
}