{
  "type": "Feature",
  "properties": {
    "gn:admin1_code":"20",
    "gn:asciiname":"Goryashina",
    "gn:country_code":"RU",
    "gn:dem":498,
    "gn:feature_class":"P",
    "gn:feature_code":"PPL",
    "gn:name":"Goryashina",
    "gn:population":0,
    "gn:timezone":"Asia/Irkutsk",
    "iso:country":"RU",
    "name:rus_x_preferred":[
        "\u0413\u043e\u0440\u044f\u0448\u0438\u043d\u043e"
    ],
    "name:und_x_variant":[
        "Goryashino",
        "Goryashina"
    ],
    "wof:name":"Goryashina",
    "wof:placetype":"locality"
},
  "geometry": {"coordinates":[104.25,52.58333],"type":"Point"}
}