{
  "type": "Feature",
  "properties": {
    "gn:admin1_code":"47",
    "gn:asciiname":"Mishchukovo",
    "gn:country_code":"RU",
    "gn:dem":143,
    "gn:feature_class":"P",
    "gn:feature_code":"PPL",
    "gn:name":"Mishchukovo",
    "gn:population":0,
    "gn:timezone":"Europe/Moscow",
    "iso:country":"RU",
    "name:rus_x_preferred":[
        "\u041c\u0438\u0449\u0443\u043a\u043e\u0432\u043e"
    ],
    "name:und_x_variant":[
        "Mishukovo",
        "Mishchukovo"
    ],
    "wof:name":"Mishchukovo",
    "wof:placetype":"locality"
},
  "geometry": {"coordinates":[38.26902000000001,55.90824],"type":"Point"}
}