{
  "type": "Feature",
  "properties": {
    "gn:admin1_code":"06",
    "gn:asciiname":"Bereznik",
    "gn:country_code":"RU",
    "gn:dem":29,
    "gn:feature_class":"P",
    "gn:feature_code":"PPL",
    "gn:name":"Bereznik",
    "gn:population":0,
    "gn:timezone":"Europe/Moscow",
    "iso:country":"RU",
    "name:und_x_variant":[
        "Malobereznitskoye",
        "Nizhniy Bereznik",
        "Bereznik"
    ],
    "wof:name":"Bereznik",
    "wof:placetype":"locality"
},
  "geometry": {"coordinates":[44.9982,65.47629999999999],"type":"Point"}
}