{
  "type": "Feature",
  "properties": {
    "gn:admin1_code":"6",
    "gn:asciiname":"Zaruchen'ye",
    "gn:country_code":"RU",
    "gn:dem":231,
    "gn:feature_class":"P",
    "gn:feature_code":"PPL",
    "gn:name":"Zaruchen\u2019ye",
    "gn:population":0,
    "gn:timezone":"Europe/Moscow",
    "iso:country":"RU",
    "name:rus_x_preferred":[
        "\u0417\u0430\u0440\u0443\u0447\u0435\u043d\u044c\u0435"
    ],
    "name:und_x_variant":[
        "Zaruchen\u2019ye"
    ],
    "wof:name":"Zaruchen'ye",
    "wof:placetype":"locality"
},
  "geometry": {"coordinates":[40.2031,61.7204],"type":"Point"}
}