{
  "type": "Feature",
  "properties": {
    "gn:admin1_code":"85",
    "gn:asciiname":"Prilukovo",
    "gn:country_code":"RU",
    "gn:dem":97,
    "gn:feature_class":"P",
    "gn:feature_code":"PPL",
    "gn:name":"Prilukovo",
    "gn:population":0,
    "gn:timezone":"Europe/Moscow",
    "iso:country":"RU",
    "name:rus_x_preferred":[
        "\u041f\u0440\u0438\u043b\u0443\u043a\u043e\u0432\u043e"
    ],
    "wof:name":"Prilukovo",
    "wof:placetype":"locality"
},
  "geometry": {"coordinates":[46.5516,60.0366],"type":"Point"}
}