{
  "type": "Feature",
  "properties": {
    "gn:admin1_code":"12",
    "gn:asciiname":"Neftyanoy",
    "gn:cc2":"RU",
    "gn:country_code":"RU",
    "gn:dem":473,
    "gn:feature_class":"P",
    "gn:feature_code":"PPL",
    "gn:name":"Neftyanoy",
    "gn:population":0,
    "gn:timezone":"Europe/Moscow",
    "iso:country":"RU",
    "name:rus_x_preferred":[
        "\u041d\u0435\u0444\u0442\u044f\u043d\u043e\u0439"
    ],
    "name:und_x_variant":[
        "Alkhazova",
        "Neftyanoy"
    ],
    "wof:name":"Neftyanoy",
    "wof:placetype":"locality"
},
  "geometry": {"coordinates":[44.90444,43.54917],"type":"Point"}
}