{
  "type": "Feature",
  "properties": {
    "gn:admin1_code":"10",
    "gn:asciiname":"Krasnyy Zavod",
    "gn:country_code":"RU",
    "gn:dem":145,
    "gn:feature_class":"P",
    "gn:feature_code":"PPL",
    "gn:name":"Krasnyy Zavod",
    "gn:population":0,
    "gn:timezone":"Europe/Moscow",
    "iso:country":"RU",
    "name:rus_x_preferred":[
        "\u041a\u0440\u0430\u0441\u043d\u044b\u0439 \u0417\u0430\u0432\u043e\u0434"
    ],
    "name:und_x_variant":[
        "Zavod",
        "Krasnyy Zavod",
        "\u041a\u0440\u0430\u0441\u043d\u044b\u0439 \u0417\u0430\u0432\u043e\u0434"
    ],
    "wof:name":"Krasnyy Zavod",
    "wof:placetype":"locality"
},
  "geometry": {"coordinates":[32.43523,53.00221],"type":"Point"}
}