{
  "type": "Feature",
  "properties": {
    "gn:admin1_code":"85",
    "gn:asciiname":"Korchagino",
    "gn:country_code":"RU",
    "gn:dem":96,
    "gn:feature_class":"P",
    "gn:feature_code":"PPL",
    "gn:name":"Korchagino",
    "gn:population":0,
    "gn:timezone":"Europe/Moscow",
    "iso:country":"RU",
    "name:rus_x_preferred":[
        "\u041a\u043e\u0440\u0447\u0430\u0433\u0438\u043d\u043e"
    ],
    "name:und_x_variant":[
        "\u041a\u043e\u0440\u0447\u0430\u0433\u0438\u043d\u043e"
    ],
    "wof:name":"Korchagino",
    "wof:placetype":"locality"
},
  "geometry": {"coordinates":[46.1043,60.6758],"type":"Point"}
}