{
  "type": "Feature",
  "properties": {
    "gn:admin1_code":"61",
    "gn:asciiname":"L'vov",
    "gn:country_code":"RU",
    "gn:dem":87,
    "gn:feature_class":"P",
    "gn:feature_code":"PPL",
    "gn:name":"L\u2019vov",
    "gn:population":0,
    "gn:timezone":"Europe/Moscow",
    "iso:country":"RU",
    "name:rus_x_preferred":[
        "\u041b\u044c\u0432\u043e\u0432"
    ],
    "name:und_x_variant":[
        "L\u2019voy",
        "L\u2019vovskiy",
        "L\u2019vov",
        "\u041b\u044c\u0432\u043e\u0432"
    ],
    "wof:name":"L'vov",
    "wof:placetype":"locality"
},
  "geometry": {"coordinates":[42.33861,46.68667],"type":"Point"}
}