{
  "type": "Feature",
  "properties": {
    "gn:admin1_code":"45",
    "gn:asciiname":"Urzhumskoye Lesnichestvo",
    "gn:country_code":"RU",
    "gn:dem":73,
    "gn:feature_class":"P",
    "gn:feature_code":"PPL",
    "gn:name":"Urzhumskoye Lesnichestvo",
    "gn:population":0,
    "gn:timezone":"Europe/Moscow",
    "iso:country":"RU",
    "wof:name":"Urzhumskoye Lesnichestvo",
    "wof:placetype":"locality"
},
  "geometry": {"coordinates":[47.50727,56.16382],"type":"Point"}
}