{
  "type": "Feature",
  "properties": {
    "gn:admin1_code":"72",
    "gn:asciiname":"Malyy Lomovis",
    "gn:country_code":"RU",
    "gn:dem":121,
    "gn:feature_class":"P",
    "gn:feature_code":"PPL",
    "gn:name":"Malyy Lomovis",
    "gn:population":0,
    "gn:timezone":"Europe/Moscow",
    "iso:country":"RU",
    "name:eng_x_preferred":[
        "Malyy Lomovis"
    ],
    "name:nor_x_preferred":[
        "Bol.Lomovis"
    ],
    "name:rus_x_preferred":[
        "\u0411\u043e\u043b.\u041b\u043e\u043c\u043e\u0432\u0438\u0441"
    ],
    "name:rus_x_variant":[
        "\u041c\u0430\u043b\u044b\u0439 \u041b\u043e\u043c\u043e\u0432\u0438\u0441"
    ],
    "name:und_x_variant":[
        "Maly Lomovis",
        "Malyy Lomovis",
        "\u041c\u0430\u043b\u044b\u0439 \u041b\u043e\u043c\u043e\u0432\u0438\u0441"
    ],
    "wof:name":"Malyy Lomovis",
    "wof:placetype":"locality"
},
  "geometry": {"coordinates":[42.04587,53.19198000000001],"type":"Point"}
}