{
  "type": "Feature",
  "properties": {
    "gn:admin1_code":"15",
    "gn:asciiname":"Penkigney",
    "gn:cc2":"RU",
    "gn:country_code":"RU",
    "gn:dem":43,
    "gn:feature_class":"P",
    "gn:feature_code":"PPL",
    "gn:name":"Penkigney",
    "gn:population":0,
    "gn:timezone":"Asia/Anadyr",
    "iso:country":"RU",
    "name:rus_x_preferred":[
        "\u041f\u0435\u043d\u043a\u0438\u0433\u043d\u0435\u0439"
    ],
    "name:und_x_variant":[
        "Penkegney",
        "Penkignei",
        "Penkigney"
    ],
    "wof:name":"Penkigney",
    "wof:placetype":"locality"
},
  "geometry": {"coordinates":[-172.93333000000001,64.86667],"type":"Point"}
}