{
  "type": "Feature",
  "properties": {
    "gn:admin1_code":"13",
    "gn:asciiname":"Novotroitskiy",
    "gn:country_code":"RU",
    "gn:dem":248,
    "gn:feature_class":"P",
    "gn:feature_code":"PPL",
    "gn:name":"Novotroitskiy",
    "gn:population":0,
    "gn:timezone":"Asia/Yekaterinburg",
    "iso:country":"RU",
    "name:rus_x_preferred":[
        "\u041d\u043e\u0432\u043e\u0442\u0440\u043e\u0438\u0442\u0441\u043a\u0438\u0439"
    ],
    "wof:name":"Novotroitskiy",
    "wof:placetype":"locality"
},
  "geometry": {"coordinates":[61.0777,54.9694],"type":"Point"}
}