{
  "type": "Feature",
  "properties": {
    "gn:admin1_code":"93",
    "gn:asciiname":"Turga",
    "gn:country_code":"RU",
    "gn:dem":801,
    "gn:feature_class":"P",
    "gn:feature_code":"PPL",
    "gn:name":"Turga",
    "gn:population":0,
    "gn:timezone":"Asia/Chita",
    "iso:country":"RU",
    "name:eng_x_preferred":[
        "Turga"
    ],
    "name:nor_x_preferred":[
        "Targa"
    ],
    "name:rus_x_preferred":[
        "\u0422\u0430\u0440\u0433\u0430"
    ],
    "wof:name":"Turga",
    "wof:placetype":"locality"
},
  "geometry": {"coordinates":[116.62958999999999,51.05306],"type":"Point"}
}