{
  "type": "Feature",
  "properties": {
    "gn:admin1_code":"88",
    "gn:asciiname":"Shirokanovo",
    "gn:country_code":"RU",
    "gn:dem":149,
    "gn:feature_class":"P",
    "gn:feature_code":"PPL",
    "gn:name":"Shirokanovo",
    "gn:population":0,
    "gn:timezone":"Europe/Moscow",
    "iso:country":"RU",
    "name:rus_x_preferred":[
        "\u0428\u0438\u0440\u043e\u043a\u0430\u043d\u043e\u0432\u043e"
    ],
    "wof:name":"Shirokanovo",
    "wof:placetype":"locality"
},
  "geometry": {"coordinates":[38.8583,57.5585],"type":"Point"}
}