{
  "type": "Feature",
  "properties": {
    "gn:admin1_code":"16",
    "gn:asciiname":"Voskhod",
    "gn:country_code":"RU",
    "gn:dem":108,
    "gn:feature_class":"P",
    "gn:feature_code":"PPL",
    "gn:name":"Voskhod",
    "gn:population":0,
    "gn:timezone":"Europe/Moscow",
    "iso:country":"RU",
    "name:bel_x_preferred":[
        "\u0423\u0441\u0445\u043e\u0434"
    ],
    "name:bul_x_preferred":[
        "\u0412\u043e\u0441\u0445\u043e\u0434"
    ],
    "name:cat_x_preferred":[
        "Voskhod"
    ],
    "name:ceb_x_preferred":[
        "Voskhod"
    ],
    "name:ces_x_preferred":[
        "Voschod"
    ],
    "name:deu_x_preferred":[
        "Woschod"
    ],
    "name:heb_x_preferred":[
        "\u05d5\u05d5\u05e1\u05d7\u05d5\u05d3"
    ],
    "name:hun_x_preferred":[
        "Voszhod"
    ],
    "name:ita_x_preferred":[
        "Voschod"
    ],
    "name:kaz_x_preferred":[
        "\u0412\u043e\u0441\u0445\u043e\u0434"
    ],
    "name:nld_x_preferred":[
        "Voschod"
    ],
    "name:por_x_preferred":[
        "Voskhod"
    ],
    "name:rus_x_preferred":[
        "\u0412\u043e\u0441\u0445\u043e\u0434"
    ],
    "name:spa_x_preferred":[
        "Vosjod"
    ],
    "name:ukr_x_preferred":[
        "\u0412\u043e\u0441\u0445\u043e\u0434"
    ],
    "name:und_x_variant":[
        "\u0412\u043e\u0441\u0445\u043e\u0434"
    ],
    "wof:name":"Voskhod",
    "wof:placetype":"locality"
},
  "geometry": {"coordinates":[46.5812,54.8045],"type":"Point"}
}