{
  "type": "Feature",
  "properties": {
    "gn:admin1_code":"41",
    "gn:asciiname":"Glebovo",
    "gn:country_code":"RU",
    "gn:dem":203,
    "gn:feature_class":"P",
    "gn:feature_code":"PPL",
    "gn:name":"Glebovo",
    "gn:population":0,
    "gn:timezone":"Europe/Moscow",
    "iso:country":"RU",
    "name:rus_x_preferred":[
        "\u0413\u043b\u0435\u0431\u043e\u0432\u043e"
    ],
    "wof:name":"Glebovo",
    "wof:placetype":"locality"
},
  "geometry": {"coordinates":[35.7757,51.4643],"type":"Point"}
}