{
  "type": "Feature",
  "properties": {
    "gn:admin1_code":"38",
    "gn:asciiname":"Krasnaya Slobodka",
    "gn:country_code":"RU",
    "gn:dem":28,
    "gn:feature_class":"P",
    "gn:feature_code":"PPL",
    "gn:name":"Krasnaya Slobodka",
    "gn:population":0,
    "gn:timezone":"Europe/Moscow",
    "iso:country":"RU",
    "name:rus_x_preferred":[
        "\u041a\u0440\u0430\u0441\u043d\u0430\u044f \u0421\u043b\u043e\u0431\u043e\u0434\u043a\u0430"
    ],
    "name:und_x_variant":[
        "\u041a\u0440\u0430\u0441\u043d\u0430\u044f \u0421\u043b\u043e\u0431\u043e\u0434\u043a\u0430",
        "Krasnaya Sloboda"
    ],
    "wof:name":"Krasnaya Slobodka",
    "wof:placetype":"locality"
},
  "geometry": {"coordinates":[39.9249,46.74217],"type":"Point"}
}