{
  "type": "Feature",
  "properties": {
    "gn:admin1_code":"91",
    "gn:asciiname":"Pshenichnyy Ruchey",
    "gn:country_code":"RU",
    "gn:dem":67,
    "gn:feature_class":"P",
    "gn:feature_code":"PPL",
    "gn:name":"Pshenichnyy Ruchey",
    "gn:population":0,
    "gn:timezone":"Asia/Krasnoyarsk",
    "iso:country":"RU",
    "name:eng_x_preferred":[
        "Pshenichnyy Ruchey"
    ],
    "name:nor_x_preferred":[
        "Psjenitsjnyj-Rutsjej"
    ],
    "name:rus_x_preferred":[
        "\u041f\u0448\u0435\u043d\u0438\u0447\u043d\u044b\u0439-\u0420\u0443\u0447\u0435\u0439"
    ],
    "name:rus_x_variant":[
        "\u041f\u0448\u0435\u043d\u0438\u0447\u043d\u044b\u0439 \u0420\u0443\u0447\u0435\u0439"
    ],
    "wof:name":"Pshenichnyy Ruchey",
    "wof:placetype":"locality"
},
  "geometry": {"coordinates":[86.12444000000001,69.45444000000001],"type":"Point"}
}