{
  "type": "Feature",
  "properties": {
    "gn:admin1_code":"90.0",
    "gn:asciiname":"Pachi",
    "gn:country_code":"RU",
    "gn:dem":155,
    "gn:feature_class":"P",
    "gn:feature_code":"PPL",
    "gn:name":"Pachi",
    "gn:population":0,
    "gn:timezone":"Asia/Yekaterinburg",
    "iso:country":"RU",
    "name:ceb_x_preferred":[
        "Pachi"
    ],
    "name:rus_x_preferred":[
        "\u041f\u0430\u0447\u0438"
    ],
    "name:swe_x_preferred":[
        "Pachi"
    ],
    "wof:name":"Pachi",
    "wof:placetype":"locality"
},
  "geometry": {"coordinates":[55.3627,58.7938],"type":"Point"}
}