{
  "type": "Feature",
  "properties": {
    "gn:admin1_code":"63",
    "gn:asciiname":"Tas-Kumsa",
    "gn:cc2":"RU",
    "gn:country_code":"RU",
    "gn:dem":130,
    "gn:feature_class":"P",
    "gn:feature_code":"PPL",
    "gn:name":"Tas-Kumsa",
    "gn:population":0,
    "gn:timezone":"Asia/Yakutsk",
    "iso:country":"RU",
    "name:und_x_variant":[
        "Tas-Tumsa",
        "Tas-Kumsa"
    ],
    "wof:name":"Tas-Kumsa",
    "wof:placetype":"locality"
},
  "geometry": {"coordinates":[133.05000000000001,68.63333],"type":"Point"}
}