{
  "type": "Feature",
  "properties": {
    "gn:admin1_code":"69",
    "gn:asciiname":"Golovkova",
    "gn:country_code":"RU",
    "gn:dem":222,
    "gn:feature_class":"P",
    "gn:feature_code":"PPL",
    "gn:name":"Golovkova",
    "gn:population":0,
    "gn:timezone":"Europe/Moscow",
    "iso:country":"RU",
    "name:rus_x_preferred":[
        "\u0413\u043e\u043b\u043e\u0432\u043a\u043e\u0432\u0430"
    ],
    "name:und_x_variant":[
        "\u0413\u043e\u043b\u043e\u0432\u043a\u043e\u0432\u0430"
    ],
    "wof:name":"Golovkova",
    "wof:placetype":"locality"
},
  "geometry": {"coordinates":[33.05,55.56667],"type":"Point"}
}