{
  "type": "Feature",
  "properties": {
    "gn:admin1_code":"77",
    "gn:asciiname":"Zaykovo",
    "gn:country_code":"RU",
    "gn:dem":112,
    "gn:feature_class":"P",
    "gn:feature_code":"PPL",
    "gn:name":"Zaykovo",
    "gn:population":0,
    "gn:timezone":"Europe/Moscow",
    "iso:country":"RU",
    "name:eng_x_preferred":[
        "Zaykova"
    ],
    "name:nor_x_preferred":[
        "Zajkovo"
    ],
    "name:rus_x_preferred":[
        "\u0417\u0430\u0439\u043a\u043e\u0432\u043e"
    ],
    "name:und_x_variant":[
        "\u0417\u0430\u0439\u043a\u043e\u0432\u043e",
        "Zaykova"
    ],
    "wof:name":"Zaykovo",
    "wof:placetype":"locality"
},
  "geometry": {"coordinates":[31.19056,56.71336],"type":"Point"}
}