{
  "type": "Feature",
  "properties": {
    "gn:admin1_code":"9",
    "gn:asciiname":"Pogorelyy",
    "gn:country_code":"RU",
    "gn:dem":198,
    "gn:feature_class":"P",
    "gn:feature_code":"PPL",
    "gn:name":"Pogorelyy",
    "gn:population":0,
    "gn:timezone":"Europe/Moscow",
    "iso:country":"RU",
    "name:rus_x_preferred":[
        "\u041f\u043e\u0433\u043e\u0440\u0435\u043b\u044b\u0439"
    ],
    "wof:name":"Pogorelyy",
    "wof:placetype":"locality"
},
  "geometry": {"coordinates":[37.13448,50.80741],"type":"Point"}
}