{
  "type": "Feature",
  "properties": {
    "gn:admin1_code":"42",
    "gn:asciiname":"Kamenka",
    "gn:country_code":"RU",
    "gn:dem":49,
    "gn:feature_class":"P",
    "gn:feature_code":"PPL",
    "gn:name":"Kamenka",
    "gn:population":8212,
    "gn:timezone":"Europe/Moscow",
    "iso:country":"RU",
    "name:ben_x_preferred":[
        "\u0995\u09be\u09ae\u09c7\u0999\u09cd\u0995\u09be"
    ],
    "name:che_x_preferred":[
        "\u041a\u0430\u043c\u0435\u043d\u043a\u0430"
    ],
    "name:ell_x_preferred":[
        "\u039a\u03b1\u03bc\u03ad\u03bd\u03ba\u03b1"
    ],
    "name:eng_x_preferred":[
        "Kamenka"
    ],
    "name:fin_x_preferred":[
        "Kaukj\u00e4rvi"
    ],
    "name:heb_x_preferred":[
        "\u05e7\u05de\u05e0\u05e7\u05d4"
    ],
    "name:hin_x_preferred":[
        "\u0915\u093e\u092e\u0947\u0902\u0915\u093e"
    ],
    "name:hye_x_preferred":[
        "\u053f\u0561\u0574\u0565\u0576\u056f\u0561"
    ],
    "name:ind_x_preferred":[
        "Kamenka"
    ],
    "name:jpn_x_preferred":[
        "\u30ab\u30e1\u30f3\u30ab"
    ],
    "name:kor_x_preferred":[
        "\uce74\uba58\uce74"
    ],
    "name:nno_x_preferred":[
        "Kamenka"
    ],
    "name:nor_x_preferred":[
        "Kamenka"
    ],
    "name:rus_x_preferred":[
        "\u041a\u0430\u043c\u0435\u043d\u043a\u0430"
    ],
    "name:spa_x_preferred":[
        "Kamenka"
    ],
    "name:swe_x_preferred":[
        "Kamenka"
    ],
    "name:und_x_variant":[
        "Kelola"
    ],
    "name:urd_x_preferred":[
        "\u06a9\u0627\u0645\u06cc\u0646\u06a9\u0627"
    ],
    "name:vie_x_preferred":[
        "Kamenka"
    ],
    "wof:name":"Kamenka",
    "wof:placetype":"locality",
    "wof:population":8212
},
  "geometry": {"coordinates":[29.0829,60.44639],"type":"Point"}
}