{
  "type": "Feature",
  "properties": {
    "gn:admin1_code":"42",
    "gn:asciiname":"Kamenka",
    "gn:country_code":"RU",
    "gn:dem":49,
    "gn:feature_class":"P",
    "gn:feature_code":"PPL",
    "gn:name":"Kamenka",
    "gn:population":8212,
    "gn:timezone":"Europe/Moscow",
    "iso:country":"RU",
    "name:eng_x_preferred":[
        "Kamenka"
    ],
    "name:fin_x_preferred":[
        "Kaukj\u00e4rvi"
    ],
    "name:nor_x_preferred":[
        "Kamenka"
    ],
    "name:rus_x_preferred":[
        "\u041a\u0430\u043c\u0435\u043d\u043a\u0430"
    ],
    "name:und_x_variant":[
        "Kelola",
        "\u041a\u0430\u043c\u0435\u043d\u043a\u0430",
        "Kamenka",
        "Kaukj\u00e4rvi"
    ],
    "wof:name":"Kamenka",
    "wof:placetype":"locality",
    "wof:population":8212
},
  "geometry": {"coordinates":[29.0829,60.44639],"type":"Point"}
}