{
  "type": "Feature",
  "properties": {
    "gn:admin1_code":"90",
    "gn:asciiname":"Durakovo",
    "gn:country_code":"RU",
    "gn:dem":187,
    "gn:feature_class":"P",
    "gn:feature_code":"PPL",
    "gn:name":"Durakovo",
    "gn:population":0,
    "gn:timezone":"Asia/Yekaterinburg",
    "iso:country":"RU",
    "name:che_x_preferred":[
        "\u0414\u0443\u0440\u0430\u043a\u043e\u0432\u043e"
    ],
    "name:rus_x_preferred":[
        "\u0414\u0443\u0440\u0430\u043a\u043e\u0432\u043e"
    ],
    "wof:name":"Durakovo",
    "wof:placetype":"locality"
},
  "geometry": {"coordinates":[56.8812,57.7585],"type":"Point"}
}