{
  "type": "Feature",
  "properties": {
    "gn:admin1_code":"47.0",
    "gn:asciiname":"Arbuzovo",
    "gn:country_code":"RU",
    "gn:dem":199,
    "gn:feature_class":"P",
    "gn:feature_code":"PPL",
    "gn:name":"Arbuzovo",
    "gn:population":0,
    "gn:timezone":"Europe/Moscow",
    "iso:country":"RU",
    "name:nor_x_preferred":[
        "Arbuzovo"
    ],
    "name:rus_x_preferred":[
        "\u0410\u0440\u0431\u0443\u0437\u043e\u0432\u043e"
    ],
    "wof:name":"Arbuzovo",
    "wof:placetype":"locality"
},
  "geometry": {"coordinates":[37.21667,56.26667],"type":"Point"}
}