{
  "type": "Feature",
  "properties": {
    "gn:admin1_code":"37.0",
    "gn:asciiname":"Bezneg",
    "gn:country_code":"RU",
    "gn:dem":111,
    "gn:feature_class":"P",
    "gn:feature_code":"PPL",
    "gn:name":"Bezneg",
    "gn:population":0,
    "gn:timezone":"Europe/Moscow",
    "iso:country":"RU",
    "name:nor_x_preferred":[
        "Bezneg"
    ],
    "name:rus_x_preferred":[
        "\u0411\u0435\u0437\u043d\u0435\u0433"
    ],
    "wof:name":"Bezneg",
    "wof:placetype":"locality"
},
  "geometry": {"coordinates":[45.38255,58.38556],"type":"Point"}
}