{
  "type": "Feature",
  "properties": {
    "gn:admin1_code":"90",
    "gn:asciiname":"Monastyr'",
    "gn:country_code":"RU",
    "gn:dem":134,
    "gn:feature_class":"P",
    "gn:feature_code":"PPL",
    "gn:name":"Monastyr\u2019",
    "gn:population":0,
    "gn:timezone":"Asia/Yekaterinburg",
    "iso:country":"RU",
    "name:rus_x_preferred":[
        "\u041c\u043e\u043d\u0430\u0441\u0442\u044b\u0440\u044c"
    ],
    "name:und_x_variant":[
        "Monastyr\u2019",
        "\u041c\u043e\u043d\u0430\u0441\u0442\u044b\u0440\u044c"
    ],
    "wof:name":"Monastyr'",
    "wof:placetype":"locality"
},
  "geometry": {"coordinates":[53.95,60.25],"type":"Point"}
}