{
  "type": "Feature",
  "properties": {
    "gn:admin1_code":"77",
    "gn:asciiname":"Nazimovo",
    "gn:country_code":"RU",
    "gn:dem":152,
    "gn:feature_class":"P",
    "gn:feature_code":"PPL",
    "gn:name":"Nazimovo",
    "gn:population":0,
    "gn:timezone":"Europe/Moscow",
    "iso:country":"RU",
    "name:rus_x_preferred":[
        "\u041d\u0430\u0437\u0438\u043c\u043e\u0432\u043e"
    ],
    "wof:name":"Nazimovo",
    "wof:placetype":"locality"
},
  "geometry": {"coordinates":[37.41132,57.99144],"type":"Point"}
}