{
  "type": "Feature",
  "properties": {
    "gn:admin1_code":"33.0",
    "gn:asciiname":"Volkovshchina",
    "gn:country_code":"RU",
    "gn:dem":116,
    "gn:feature_class":"P",
    "gn:feature_code":"PPL",
    "gn:name":"Volkovshchina",
    "gn:population":0,
    "gn:timezone":"Europe/Kirov",
    "iso:country":"RU",
    "name:rus_x_preferred":[
        "\u0412\u043e\u043b\u043a\u043e\u0432\u0449\u0438\u043d\u0430"
    ],
    "wof:name":"Volkovshchina",
    "wof:placetype":"locality"
},
  "geometry": {"coordinates":[48.4653,58.5332],"type":"Point"}
}