{
  "type": "Feature",
  "properties": {
    "gn:admin1_code":"51",
    "gn:asciiname":"Tyuriki",
    "gn:country_code":"RU",
    "gn:dem":129,
    "gn:feature_class":"P",
    "gn:feature_code":"PPL",
    "gn:name":"Tyuriki",
    "gn:population":0,
    "gn:timezone":"Europe/Moscow",
    "iso:country":"RU",
    "name:rus_x_preferred":[
        "\u0422\u044e\u0440\u0438\u043a\u0438"
    ],
    "name:und_x_variant":[
        "\u0422\u044e\u0440\u0438\u043a\u0438"
    ],
    "wof:name":"Tyuriki",
    "wof:placetype":"locality"
},
  "geometry": {"coordinates":[46.5192,57.6626],"type":"Point"}
}