{
  "type": "Feature",
  "properties": {
    "gn:admin1_code":"60",
    "gn:asciiname":"Chernoruch'ye",
    "gn:country_code":"RU",
    "gn:dem":45,
    "gn:feature_class":"P",
    "gn:feature_code":"PPL",
    "gn:name":"Chernoruch\u2019ye",
    "gn:population":0,
    "gn:timezone":"Europe/Moscow",
    "iso:country":"RU",
    "name:rus_x_preferred":[
        "\u0427\u0435\u0440\u043d\u043e\u0440\u0443\u0447\u044c\u0435"
    ],
    "name:und_x_variant":[
        "Chernoruch\u2019ye"
    ],
    "wof:name":"Chernoruch'ye",
    "wof:placetype":"locality"
},
  "geometry": {"coordinates":[28.4827,57.6991],"type":"Point"}
}