{
  "type": "Feature",
  "properties": {
    "gn:admin1_code":"56.0",
    "gn:asciiname":"Bogoroditskoye",
    "gn:country_code":"RU",
    "gn:dem":192,
    "gn:feature_class":"P",
    "gn:feature_code":"PPL",
    "gn:name":"Bogoroditskoye",
    "gn:population":0,
    "gn:timezone":"Europe/Moscow",
    "iso:country":"RU",
    "name:eng_x_preferred":[
        "Bogoroditskoye"
    ],
    "name:nor_x_preferred":[
        "Bogoroditskoje"
    ],
    "name:rus_x_preferred":[
        "\u0411\u043e\u0433\u043e\u0440\u043e\u0434\u0438\u0446\u043a\u043e\u0435"
    ],
    "wof:name":"Bogoroditskoye",
    "wof:placetype":"locality"
},
  "geometry": {"coordinates":[36.38716,52.82015],"type":"Point"}
}