{
  "type": "Feature",
  "properties": {
    "gn:admin1_code":"71.0",
    "gn:asciiname":"Bol'shiye Urmy",
    "gn:country_code":"RU",
    "gn:dem":276,
    "gn:feature_class":"P",
    "gn:feature_code":"PPL",
    "gn:name":"Bol\u2019shiye Urmy",
    "gn:population":0,
    "gn:timezone":"Asia/Yekaterinburg",
    "iso:country":"RU",
    "name:rus_x_preferred":[
        "\u0411\u043e\u043b\u044c\u0448\u0438\u0435 \u0423\u0440\u043c\u044b"
    ],
    "name:und_x_variant":[
        "Urmy",
        "Bol\u2019shiye Urmy"
    ],
    "wof:name":"Bol'shiye Urmy",
    "wof:placetype":"locality"
},
  "geometry": {"coordinates":[58.23333,57.58333],"type":"Point"}
}