{
  "type": "Feature",
  "properties": {
    "gn:admin1_code":"30",
    "gn:asciiname":"Dayerga",
    "gn:country_code":"RU",
    "gn:dem":29,
    "gn:feature_class":"P",
    "gn:feature_code":"PPL",
    "gn:name":"Dayerga",
    "gn:population":0,
    "gn:timezone":"Asia/Vladivostok",
    "iso:country":"RU",
    "name:eng_x_preferred":[
        "Dayerga"
    ],
    "name:nor_x_preferred":[
        "Dajerga"
    ],
    "name:rus_x_preferred":[
        "\u0414\u0430\u0435\u0440\u0433\u0430"
    ],
    "name:und_x_variant":[
        "Dierga",
        "Dayerginsk",
        "Dayerga"
    ],
    "wof:name":"Dayerga",
    "wof:placetype":"locality"
},
  "geometry": {"coordinates":[136.47429,49.26587],"type":"Point"}
}