{
  "type": "Feature",
  "properties": {
    "gn:admin1_code":"77",
    "gn:asciiname":"Olokhovo",
    "gn:country_code":"RU",
    "gn:dem":164,
    "gn:feature_class":"P",
    "gn:feature_code":"PPL",
    "gn:name":"Olokhovo",
    "gn:population":0,
    "gn:timezone":"Europe/Moscow",
    "iso:country":"RU",
    "name:rus_x_preferred":[
        "\u041e\u043b\u043e\u0445\u043e\u0432\u043e"
    ],
    "name:und_x_variant":[
        "\u041e\u043b\u043e\u0445\u043e\u0432\u043e"
    ],
    "wof:name":"Olokhovo",
    "wof:placetype":"locality"
},
  "geometry": {"coordinates":[36.767,58.0026],"type":"Point"}
}