{
  "type": "Feature",
  "properties": {
    "gn:admin1_code":"85",
    "gn:asciiname":"Lukanikha",
    "gn:country_code":"RU",
    "gn:dem":163,
    "gn:feature_class":"P",
    "gn:feature_code":"PPL",
    "gn:name":"Lukanikha",
    "gn:population":0,
    "gn:timezone":"Europe/Moscow",
    "iso:country":"RU",
    "name:rus_x_preferred":[
        "\u041b\u0443\u043a\u0430\u043d\u0438\u0445\u0430"
    ],
    "wof:name":"Lukanikha",
    "wof:placetype":"locality"
},
  "geometry": {"coordinates":[38.636,60.4289],"type":"Point"}
}