{
  "type": "Feature",
  "properties": {
    "gn:admin1_code":"10",
    "gn:asciiname":"Gromyshi",
    "gn:country_code":"RU",
    "gn:dem":203,
    "gn:feature_class":"P",
    "gn:feature_code":"PPL",
    "gn:name":"Gromyshi",
    "gn:population":0,
    "gn:timezone":"Europe/Moscow",
    "iso:country":"RU",
    "name:rus_x_preferred":[
        "\u0413\u0440\u043e\u043c\u044b\u0448\u0438"
    ],
    "name:und_x_variant":[
        "Gramyshi",
        "Gromyshi"
    ],
    "wof:name":"Gromyshi",
    "wof:placetype":"locality"
},
  "geometry": {"coordinates":[34.8039,52.236],"type":"Point"}
}