{
  "type": "Feature",
  "properties": {
    "gn:admin1_code":"45",
    "gn:asciiname":"Danilkino",
    "gn:country_code":"RU",
    "gn:dem":125,
    "gn:feature_class":"P",
    "gn:feature_code":"PPL",
    "gn:name":"Danilkino",
    "gn:population":0,
    "gn:timezone":"Europe/Moscow",
    "iso:country":"RU",
    "name:rus_x_preferred":[
        "\u0414\u0430\u043d\u0438\u043b\u043a\u0438\u043d\u043e"
    ],
    "wof:name":"Danilkino",
    "wof:placetype":"locality"
},
  "geometry": {"coordinates":[47.71219,56.69236],"type":"Point"}
}