{
  "type": "Feature",
  "properties": {
    "gn:admin1_code":"4",
    "gn:asciiname":"Mel'nikovo",
    "gn:country_code":"RU",
    "gn:dem":274,
    "gn:feature_class":"P",
    "gn:feature_code":"PPL",
    "gn:name":"Mel\u2019nikovo",
    "gn:population":0,
    "gn:timezone":"Asia/Barnaul",
    "iso:country":"RU",
    "name:rus_x_preferred":[
        "\u041c\u0435\u043b\u044c\u043d\u0438\u043a\u043e\u0432\u043e"
    ],
    "name:und_x_variant":[
        "Mel\u2019nikovo"
    ],
    "wof:name":"Mel'nikovo",
    "wof:placetype":"locality"
},
  "geometry": {"coordinates":[86.28579999999999,53.4694],"type":"Point"}
}