{
  "type": "Feature",
  "properties": {
    "gn:admin1_code":"11",
    "gn:asciiname":"Klyuchi",
    "gn:country_code":"RU",
    "gn:dem":651,
    "gn:feature_class":"P",
    "gn:feature_code":"PPL",
    "gn:name":"Klyuchi",
    "gn:population":0,
    "gn:timezone":"Asia/Irkutsk",
    "iso:country":"RU",
    "name:bel_x_preferred":[
        "\u041a\u043b\u044e\u0447\u044b"
    ],
    "name:ceb_x_preferred":[
        "\u041a\u043b\u044e\u0447\u0438"
    ],
    "name:ces_x_preferred":[
        "Klju\u010di"
    ],
    "name:deu_x_preferred":[
        "Kljutschi"
    ],
    "name:eng_x_preferred":[
        "Klyuchi"
    ],
    "name:kor_x_preferred":[
        "\ud074\ub958\uce58"
    ],
    "name:nor_x_preferred":[
        "Kljutsji"
    ],
    "name:rus_x_preferred":[
        "\u041a\u043b\u044e\u0447\u0438"
    ],
    "name:tat_x_preferred":[
        "\u041a\u043b\u044e\u0447\u0438"
    ],
    "name:ukr_x_preferred":[
        "\u041a\u043b\u044e\u0447\u0456"
    ],
    "name:und_x_variant":[
        "\u041a\u043b\u044e\u0447\u0438",
        "Klyuchi"
    ],
    "wof:name":"Klyuchi",
    "wof:placetype":"locality"
},
  "geometry": {"coordinates":[107.17865999999999,51.6876],"type":"Point"}
}