{
  "type": "Feature",
  "properties": {
    "gn:admin1_code":"84",
    "gn:asciiname":"Popov",
    "gn:country_code":"RU",
    "gn:dem":158,
    "gn:feature_class":"P",
    "gn:feature_code":"PPL",
    "gn:name":"Popov",
    "gn:population":0,
    "gn:timezone":"Europe/Volgograd",
    "iso:country":"RU",
    "name:eng_x_preferred":[
        "Popov"
    ],
    "name:est_x_preferred":[
        "Popov"
    ],
    "name:lav_x_preferred":[
        "Popovs"
    ],
    "name:nor_x_preferred":[
        "Popov"
    ],
    "name:rus_x_preferred":[
        "\u041f\u043e\u043f\u043e\u0432"
    ],
    "name:slv_x_preferred":[
        "Popov"
    ],
    "wof:name":"Popov",
    "wof:placetype":"locality"
},
  "geometry": {"coordinates":[43.2788,50.3909],"type":"Point"}
}