{
  "type": "Feature",
  "properties": {
    "gn:admin1_code":"51.0",
    "gn:asciiname":"Lazarevo",
    "gn:country_code":"RU",
    "gn:dem":135,
    "gn:feature_class":"P",
    "gn:feature_code":"PPL",
    "gn:name":"Lazarevo",
    "gn:population":0,
    "gn:timezone":"Europe/Moscow",
    "iso:country":"RU",
    "name:nor_x_preferred":[
        "Lazarevo"
    ],
    "name:rus_x_preferred":[
        "\u041b\u0430\u0437\u0430\u0440\u0435\u0432\u043e"
    ],
    "wof:name":"Lazarevo",
    "wof:placetype":"locality"
},
  "geometry": {"coordinates":[43.5778,56.06233],"type":"Point"}
}