{
  "type": "Feature",
  "properties": {
    "gn:admin1_code":"20",
    "gn:asciiname":"Shitkhulun",
    "gn:country_code":"RU",
    "gn:dem":597,
    "gn:feature_class":"P",
    "gn:feature_code":"PPL",
    "gn:name":"Shitkhulun",
    "gn:population":0,
    "gn:timezone":"Asia/Irkutsk",
    "iso:country":"RU",
    "name:rus_x_preferred":[
        "\u0428\u0438\u0442\u0445\u0443\u043b\u0443\u043d"
    ],
    "name:und_x_variant":[
        "Shetkholun",
        "Shetkhulun",
        "Shitkhulun"
    ],
    "wof:name":"Shitkhulun",
    "wof:placetype":"locality"
},
  "geometry": {"coordinates":[105.94583,53.32806],"type":"Point"}
}