{
  "type": "Feature",
  "properties": {
    "gn:admin1_code":"41",
    "gn:asciiname":"Kapystichi",
    "gn:country_code":"RU",
    "gn:dem":145,
    "gn:feature_class":"P",
    "gn:feature_code":"PPL",
    "gn:name":"Kapystichi",
    "gn:population":0,
    "gn:timezone":"Europe/Moscow",
    "iso:country":"RU",
    "name:eng_x_preferred":[
        "Kapystichi"
    ],
    "name:nor_x_preferred":[
        "Kapystitsji"
    ],
    "name:rus_x_preferred":[
        "\u041a\u0430\u043f\u044b\u0441\u0442\u0438\u0447\u0438"
    ],
    "name:und_x_variant":[
        "Kopystychi",
        "Kapustichi",
        "\u041a\u0430\u043f\u044b\u0441\u0442\u0438\u0447\u0438",
        "Kapystichi"
    ],
    "wof:name":"Kapystichi",
    "wof:placetype":"locality"
},
  "geometry": {"coordinates":[34.8471,51.6975],"type":"Point"}
}