{
  "type": "Feature",
  "properties": {
    "gn:admin1_code":"8",
    "gn:asciiname":"Remashta",
    "gn:country_code":"RU",
    "gn:dem":329,
    "gn:feature_class":"P",
    "gn:feature_code":"PPL",
    "gn:name":"Remashta",
    "gn:population":0,
    "gn:timezone":"Asia/Yekaterinburg",
    "iso:country":"RU",
    "name:rus_x_preferred":[
        "\u0420\u0435\u043c\u0430\u0448\u0442\u0430"
    ],
    "name:und_x_variant":[
        "Remashty",
        "Rimashty",
        "Remashta"
    ],
    "wof:name":"Remashta",
    "wof:placetype":"locality"
},
  "geometry": {"coordinates":[57.4991,54.1049],"type":"Point"}
}