{
  "type": "Feature",
  "properties": {
    "gn:admin1_code":"80",
    "gn:asciiname":"Yelovo",
    "gn:country_code":"RU",
    "gn:dem":230,
    "gn:feature_class":"P",
    "gn:feature_code":"PPL",
    "gn:name":"Yelovo",
    "gn:population":0,
    "gn:timezone":"Europe/Samara",
    "iso:country":"RU",
    "name:rus_x_preferred":[
        "\u0415\u043b\u043e\u0432\u043e"
    ],
    "wof:name":"Yelovo",
    "wof:placetype":"locality"
},
  "geometry": {"coordinates":[52.399,57.7706],"type":"Point"}
}