{
  "type": "Feature",
  "properties": {
    "gn:admin1_code":"42",
    "gn:asciiname":"Shelogino",
    "gn:country_code":"RU",
    "gn:dem":31,
    "gn:feature_class":"P",
    "gn:feature_code":"PPL",
    "gn:name":"Shelogino",
    "gn:population":0,
    "gn:timezone":"Europe/Moscow",
    "iso:country":"RU",
    "name:rus_x_preferred":[
        "\u0428\u0435\u043b\u043e\u0433\u0438\u043d\u043e"
    ],
    "wof:name":"Shelogino",
    "wof:placetype":"locality"
},
  "geometry": {"coordinates":[32.05914,59.58565],"type":"Point"}
}