{
  "type": "Feature",
  "properties": {
    "gn:admin1_code":"60",
    "gn:asciiname":"Beshkovo",
    "gn:country_code":"RU",
    "gn:dem":110,
    "gn:feature_class":"P",
    "gn:feature_code":"PPL",
    "gn:name":"Beshkovo",
    "gn:population":0,
    "gn:timezone":"Europe/Moscow",
    "iso:country":"RU",
    "name:rus_x_preferred":[
        "\u0411\u0435\u0448\u043a\u043e\u0432\u043e"
    ],
    "name:und_x_variant":[
        "\u0411\u0435\u0448\u043a\u043e\u0432\u043e"
    ],
    "wof:name":"Beshkovo",
    "wof:placetype":"locality"
},
  "geometry": {"coordinates":[28.844,58.5508],"type":"Point"}
}