{
  "type": "Feature",
  "properties": {
    "gn:admin1_code":"55",
    "gn:asciiname":"Kristalka",
    "gn:country_code":"RU",
    "gn:dem":133,
    "gn:feature_class":"P",
    "gn:feature_code":"PPL",
    "gn:name":"Kristalka",
    "gn:population":0,
    "gn:timezone":"Asia/Yekaterinburg",
    "iso:country":"RU",
    "name:eng_x_preferred":[
        "Kristalka"
    ],
    "name:nor_x_preferred":[
        "Kristalka"
    ],
    "name:rus_x_preferred":[
        "\u041a\u0440\u0438\u0441\u0442\u0430\u043b\u043a\u0430"
    ],
    "name:und_x_variant":[
        "\u041a\u0440\u0438\u0441\u0442\u0430\u043b\u043a\u0430",
        "Kristalka"
    ],
    "wof:name":"Kristalka",
    "wof:placetype":"locality"
},
  "geometry": {"coordinates":[53.48333,53.03333000000001],"type":"Point"}
}