{
  "type": "Feature",
  "properties": {
    "gn:admin1_code":"70",
    "gn:asciiname":"Verkhnebalkovskiy",
    "gn:country_code":"RU",
    "gn:dem":395,
    "gn:feature_class":"P",
    "gn:feature_code":"PPL",
    "gn:name":"Verkhnebalkovskiy",
    "gn:population":0,
    "gn:timezone":"Europe/Moscow",
    "iso:country":"RU",
    "name:rus_x_preferred":[
        "\u0412\u0435\u0440\u0445\u043d\u0435\u0431\u0430\u043b\u043a\u043e\u0432\u0441\u043a\u0438\u0439"
    ],
    "wof:name":"Verkhnebalkovskiy",
    "wof:placetype":"locality"
},
  "geometry": {"coordinates":[42.7207,44.297],"type":"Point"}
}