{
  "type": "Feature",
  "properties": {
    "gn:country":"RU",
    "gn:fcode":"PPL",
    "gn:population":3143,
    "iso:country":"RU",
    "name:ara_x_preferred":[
        "\u0643\u0648\u0645\u0633\u0648\u0645\u0648\u0644\u064a\u062a\u0633"
    ],
    "name:ben_x_preferred":[
        "\u0995\u09cb\u09ae\u09b8\u09cb\u09ae\u09cb\u09b2\u09c7\u09a4\u09b8"
    ],
    "name:ceb_x_preferred":[
        "Komsomolets"
    ],
    "name:deu_x_preferred":[
        "Komsomolets"
    ],
    "name:ell_x_preferred":[
        "\u039a\u03bf\u03bc\u03c3\u03bf\u03bc\u03cc\u03bb\u03b5\u03c4\u03c2"
    ],
    "name:eng_x_preferred":[
        "Komsomolets"
    ],
    "name:est_x_preferred":[
        "Komsomolets"
    ],
    "name:fas_x_preferred":[
        "\u06a9\u0627\u0645\u0633\u0648\u0645\u0648\u0644\u062a\u0633"
    ],
    "name:fin_x_preferred":[
        "Komsomolets"
    ],
    "name:fra_x_preferred":[
        "Karabalyk"
    ],
    "name:fra_x_variant":[
        "Komsomolets"
    ],
    "name:heb_x_preferred":[
        "\u05e7\u05d5\u05de\u05e1\u05d5\u05de\u05d5\u05dc\u05e5"
    ],
    "name:hin_x_preferred":[
        "\u0915\u094b\u092e\u0938\u094b\u092e\u094b\u0932\u0947\u091f\u094d\u0938"
    ],
    "name:hun_x_preferred":[
        "Komsomolets"
    ],
    "name:ind_x_preferred":[
        "Komsomolets"
    ],
    "name:jpn_x_preferred":[
        "\u30b3\u30e0\u30bd\u30e2\u30ec\u30c4"
    ],
    "name:kor_x_preferred":[
        "\ucf64\uc18c\ubaa8\ub81b"
    ],
    "name:nor_x_preferred":[
        "Komsomolets"
    ],
    "name:por_x_preferred":[
        "Komsomolets"
    ],
    "name:rus_x_preferred":[
        "\u041a\u043e\u043c\u0441\u043e\u043c\u043e\u043b\u0435\u0446"
    ],
    "name:spa_x_preferred":[
        "Komsomolets"
    ],
    "name:swe_x_preferred":[
        "Komsomolets"
    ],
    "name:tur_x_preferred":[
        "Komsomolets"
    ],
    "name:urd_x_preferred":[
        "\u06a9\u0648\u0645\u0633\u0648\u0645\u0648\u0644\u06cc\u0679\u0633"
    ],
    "name:vie_x_preferred":[
        "Komsomolets"
    ],
    "qs:name":"Komsomolets",
    "qs:photos_9r":0,
    "qs:photos_sr":0,
    "qs:pop_sr":"4",
    "wd:wordcount":84,
    "wof:name":"Komsomolets",
    "wof:placetype":"locality",
    "wof:population":3143
},
  "geometry": {"coordinates":[43.56972,44.01972],"type":"Point"}
}