{
  "type": "Feature",
  "properties": {
    "gn:country":"RU",
    "gn:fcode":"PPL",
    "gn:pop":3143,
    "iso:country":"RU",
    "name:eng_x_preferred":[
        "Komsomolets"
    ],
    "name:nor_x_preferred":[
        "Komsomolets"
    ],
    "name:rus_x_preferred":[
        "\u041a\u043e\u043c\u0441\u043e\u043c\u043e\u043b\u0435\u0446"
    ],
    "name:unk_x_variant":[
        "\u041a\u043e\u043c\u0441\u043e\u043c\u043e\u043b\u0435\u0446"
    ],
    "qs:name":"Komsomolets",
    "qs:photos_9r":0,
    "qs:photos_sr":0,
    "qs:pop_sr":"4",
    "wd:wordcount":84,
    "wof:name":"Komsomolets",
    "wof:placetype":"locality",
    "wof:population":3143
},
  "geometry": {"coordinates":[43.56972,44.01972],"type":"Point"}
}