{
  "type": "Feature",
  "properties": {
    "gn:admin1_code":"83.0",
    "gn:asciiname":"Fedotovo",
    "gn:country_code":"RU",
    "gn:dem":134,
    "gn:feature_class":"P",
    "gn:feature_code":"PPL",
    "gn:name":"Fedotovo",
    "gn:population":0,
    "gn:timezone":"Europe/Moscow",
    "iso:country":"RU",
    "name:eng_x_preferred":[
        "Fedotovo"
    ],
    "name:nor_x_preferred":[
        "Fedotovo"
    ],
    "name:rus_x_preferred":[
        "\u0424\u0435\u0434\u043e\u0442\u043e\u0432\u043e"
    ],
    "name:und_x_variant":[
        "\u0424\u0435\u0434\u043e\u0442\u043e\u0432\u043e",
        "Fedotovo"
    ],
    "wof:name":"Fedotovo",
    "wof:placetype":"locality"
},
  "geometry": {"coordinates":[40.91958,55.67666],"type":"Point"}
}