{
  "type": "Feature",
  "properties": {
    "gn:country":"RU",
    "gn:fcode":"PPL",
    "gn:pop":2697,
    "iso:country":"RU",
    "name:ceb_x_preferred":[
        "Moshenskoye"
    ],
    "name:che_x_preferred":[
        "\u041c\u043e\u0448\u0435\u043d\u0441\u043a\u043e\u0435"
    ],
    "name:deu_x_preferred":[
        "Moschenskoje"
    ],
    "name:eng_x_preferred":[
        "Moshenskoye"
    ],
    "name:fin_x_preferred":[
        "Mo\u0161enskoje"
    ],
    "name:nld_x_preferred":[
        "Moshenskoye"
    ],
    "name:nor_x_preferred":[
        "Mosjenskoje"
    ],
    "name:rus_x_preferred":[
        "\u041c\u043e\u0448\u0435\u043d\u0441\u043a\u043e\u0435"
    ],
    "name:srp_x_preferred":[
        "\u041c\u043e\u0448\u0435\u043d\u0441\u043a\u043e\u0458\u0435"
    ],
    "name:unk_x_variant":[
        "Nikolo-Moshenskoye"
    ],
    "qs:name":"Moshenskoye",
    "qs:photos_9r":0,
    "qs:photos_sr":0,
    "qs:pop_sr":"4",
    "wd:wordcount":30,
    "wof:name":"Moshenskoye",
    "wof:placetype":"locality",
    "wof:population":2697
},
  "geometry": {"coordinates":[34.59108,58.51016],"type":"Point"}
}