{
  "type": "Feature",
  "properties": {
    "gn:country":"RU",
    "gn:fcode":"PPL",
    "gn:population":2697,
    "iso:country":"RU",
    "name:arz_x_preferred":[
        "\u0645\u0648\u0634\u064a\u0646\u0633\u0643\u0648\u0649"
    ],
    "name:azb_x_preferred":[
        "\u0645\u0648\u0634\u0646\u0632\u06a9\u0648\u06cc"
    ],
    "name:bel_x_preferred":[
        "\u041c\u0430\u0448\u0430\u043d\u0441\u043a\u043e\u0435"
    ],
    "name:ceb_x_preferred":[
        "Moshenskoye"
    ],
    "name:che_x_preferred":[
        "\u041c\u043e\u0448\u0435\u043d\u0441\u043a\u043e\u0435"
    ],
    "name:deu_x_preferred":[
        "Moschenskoje"
    ],
    "name:eng_x_preferred":[
        "Moshenskoye"
    ],
    "name:epo_x_preferred":[
        "Mo\u015denskoje"
    ],
    "name:fin_x_preferred":[
        "Mo\u0161enskoje"
    ],
    "name:nld_x_preferred":[
        "Moshenskoye"
    ],
    "name:nno_x_preferred":[
        "Mosjenskoje"
    ],
    "name:nob_x_preferred":[
        "Mosjenskoje"
    ],
    "name:nor_x_preferred":[
        "Mosjenskoje"
    ],
    "name:rus_x_preferred":[
        "\u041c\u043e\u0448\u0435\u043d\u0441\u043a\u043e\u0435"
    ],
    "name:sqi_x_preferred":[
        "Mosenskoe"
    ],
    "name:srp_x_preferred":[
        "\u041c\u043e\u0448\u0435\u043d\u0441\u043a\u043e\u0458\u0435"
    ],
    "name:ukr_x_preferred":[
        "\u041c\u043e\u0448\u0435\u043d\u0441\u044c\u043a\u0435"
    ],
    "name:und_x_variant":[
        "Nikolo-Moshenskoye"
    ],
    "qs:name":"Moshenskoye",
    "qs:photos_9r":0,
    "qs:photos_sr":0,
    "qs:pop_sr":"4",
    "wd:wordcount":30,
    "wof:name":"Moshenskoye",
    "wof:placetype":"locality",
    "wof:population":2697
},
  "geometry": {"coordinates":[34.59108,58.51016],"type":"Point"}
}