{
  "type": "Feature",
  "properties": {
    "gn:country":"RU",
    "gn:fcode":"PPL",
    "gn:pop":600,
    "iso:country":"RU",
    "name:rus_x_preferred":[
        "\u041c\u043e\u0445\u043d\u0430\u0442\u0443\u0448\u043a\u0430"
    ],
    "name:rus_x_variant":[
        "\u0426\u0435\u043d\u0442\u0440\u0430\u043b\u044c\u043d\u044b\u0439 \u0440\u0430\u0439\u043e\u043d"
    ],
    "name:ukr_x_preferred":[
        "\u0426\u0435\u043d\u0442\u0440\u0430\u043b\u044c\u043d\u0438\u0439 \u0440\u0430\u0439\u043e\u043d"
    ],
    "name:unk_x_variant":[
        "\u041c\u043e\u0445\u043d\u0430\u0442\u0443\u0448\u043a\u0430"
    ],
    "qs:name":"Mokhnatushka",
    "qs:photos_9r":0,
    "qs:photos_sr":0,
    "qs:pop_sr":"2",
    "wd:wordcount":490,
    "wof:name":"Mokhnatushka",
    "wof:placetype":"locality",
    "wof:population":600
},
  "geometry": {"coordinates":[83.57944000000001,53.22944],"type":"Point"}
}