{
  "type": "Feature",
  "properties": {
    "gn:admin1_code":"61",
    "gn:asciiname":"Svobodnoye",
    "gn:country_code":"RU",
    "gn:dem":139,
    "gn:feature_class":"P",
    "gn:feature_code":"PPL",
    "gn:name":"Svobodnoye",
    "gn:population":0,
    "gn:timezone":"Europe/Moscow",
    "iso:country":"RU",
    "name:eng_x_preferred":[
        "Svobodnoye"
    ],
    "name:nor_x_preferred":[
        "Svobodnoje"
    ],
    "name:rus_x_preferred":[
        "\u0421\u0432\u043e\u0431\u043e\u0434\u043d\u043e\u0435"
    ],
    "name:und_x_variant":[
        "Sukta",
        "Ves\u00ebloye",
        "Svobodnoye"
    ],
    "wof:name":"Svobodnoye",
    "wof:placetype":"locality"
},
  "geometry": {"coordinates":[44.1596,46.92696],"type":"Point"}
}