{
  "type": "Feature",
  "properties": {
    "gn:admin1_code":"69",
    "gn:asciiname":"Sharipino",
    "gn:country_code":"RU",
    "gn:dem":236,
    "gn:feature_class":"P",
    "gn:feature_code":"PPL",
    "gn:name":"Sharipino",
    "gn:population":0,
    "gn:timezone":"Europe/Moscow",
    "iso:country":"RU",
    "name:rus_x_preferred":[
        "\u0428\u0430\u0440\u0438\u043f\u0438\u043d\u043e"
    ],
    "wof:name":"Sharipino",
    "wof:placetype":"locality"
},
  "geometry": {"coordinates":[33.36556,54.75833000000001],"type":"Point"}
}