{
  "type": "Feature",
  "properties": {
    "gn:admin1_code":"16",
    "gn:asciiname":"Vanyushkasy",
    "gn:country_code":"RU",
    "gn:dem":141,
    "gn:feature_class":"P",
    "gn:feature_code":"PPL",
    "gn:name":"Vanyushkasy",
    "gn:population":0,
    "gn:timezone":"Europe/Moscow",
    "iso:country":"RU",
    "name:rus_x_preferred":[
        "\u0412\u0430\u043d\u044e\u0448\u043a\u0430\u0441\u044b"
    ],
    "name:und_x_variant":[
        "Yanyush-Kasy",
        "Vanyushkasy"
    ],
    "wof:name":"Vanyushkasy",
    "wof:placetype":"locality"
},
  "geometry": {"coordinates":[47.25073,55.81694],"type":"Point"}
}