{
  "type": "Feature",
  "properties": {
    "gn:admin1_code":"20",
    "gn:asciiname":"Kharbatovo",
    "gn:country_code":"RU",
    "gn:dem":544,
    "gn:feature_class":"P",
    "gn:feature_code":"PPL",
    "gn:name":"Kharbatovo",
    "gn:population":460,
    "gn:timezone":"Asia/Irkutsk",
    "iso:country":"RU",
    "name:eng_x_preferred":[
        "Kharbatovo"
    ],
    "name:nor_x_preferred":[
        "Kharbatovo"
    ],
    "name:rus_x_preferred":[
        "\u0425\u0430\u0440\u0431\u0430\u0442\u043e\u0432\u043e"
    ],
    "name:und_x_variant":[
        "Kharbatovol"
    ],
    "wof:name":"Kharbatovo",
    "wof:placetype":"locality",
    "wof:population":460
},
  "geometry": {"coordinates":[106.00472000000001,53.74944],"type":"Point"}
}