{
  "type": "Feature",
  "properties": {
    "gn:admin1_code":"54",
    "gn:asciiname":"Strel'nikovo",
    "gn:country_code":"RU",
    "gn:dem":110,
    "gn:feature_class":"P",
    "gn:feature_code":"PPL",
    "gn:name":"Strel\u2019nikovo",
    "gn:population":0,
    "gn:timezone":"Asia/Omsk",
    "iso:country":"RU",
    "name:eng_x_preferred":[
        "Strel'nikovo"
    ],
    "name:nor_x_preferred":[
        "Strelnikovo"
    ],
    "name:rus_x_preferred":[
        "\u0421\u0442\u0440\u0435\u043b\u044c\u043d\u0438\u043a\u043e\u0432\u043e"
    ],
    "name:und_x_variant":[
        "Lyubchino",
        "Strel\u2019nikovo"
    ],
    "wof:name":"Strel'nikovo",
    "wof:placetype":"locality"
},
  "geometry": {"coordinates":[74.98966999999998,54.74939000000001],"type":"Point"}
}