{
  "type": "Feature",
  "properties": {
    "gn:admin1_code":"28",
    "gn:asciiname":"Sieminki",
    "gn:cc2":"RU",
    "gn:country_code":"RU",
    "gn:dem":282,
    "gn:feature_class":"P",
    "gn:feature_code":"PPL",
    "gn:name":"Sieminki",
    "gn:population":0,
    "gn:timezone":"Europe/Moscow",
    "iso:country":"RU",
    "name:rus_x_preferred":[
        "\u0421\u0438\u0435\u043c\u0438\u043d\u043a\u0438"
    ],
    "name:und_x_variant":[
        "Siyeminki",
        "\u0421\u0438\u0435\u043c\u0438\u043d\u043a\u0438"
    ],
    "wof:name":"Sieminki",
    "wof:placetype":"locality"
},
  "geometry": {"coordinates":[30.08333,66.63333],"type":"Point"}
}