{
  "type": "Feature",
  "properties": {
    "gn:admin1_code":"24.0",
    "gn:asciiname":"Ustin-Boro",
    "gn:country_code":"RU",
    "gn:dem":-15,
    "gn:feature_class":"P",
    "gn:feature_code":"PPL",
    "gn:name":"Ustin-Boro",
    "gn:population":0,
    "gn:timezone":"Europe/Moscow",
    "iso:country":"RU",
    "wof:name":"Ustin-Boro",
    "wof:placetype":"locality"
},
  "geometry": {"coordinates":[45.90278,45.68833],"type":"Point"}
}