{
  "type": "Feature",
  "properties": {
    "gn:admin1_code":"69",
    "gn:asciiname":"Budovets",
    "gn:country_code":"RU",
    "gn:dem":195,
    "gn:feature_class":"P",
    "gn:feature_code":"PPL",
    "gn:name":"Budovets",
    "gn:population":0,
    "gn:timezone":"Europe/Moscow",
    "iso:country":"RU",
    "name:rus_x_preferred":[
        "\u0411\u0443\u0434\u043e\u0432\u0435\u0446"
    ],
    "wof:name":"Budovets",
    "wof:placetype":"locality"
},
  "geometry": {"coordinates":[32.11889,55.55833000000001],"type":"Point"}
}