{
  "type": "Feature",
  "properties": {
    "gn:admin1_code":"52",
    "gn:asciiname":"Gorki Lesovyye",
    "gn:cc2":"RU",
    "gn:country_code":"RU",
    "gn:dem":98,
    "gn:feature_class":"P",
    "gn:feature_code":"PPL",
    "gn:name":"Gorki Lesovyye",
    "gn:population":0,
    "gn:timezone":"Europe/Moscow",
    "iso:country":"RU",
    "name:rus_x_preferred":[
        "\u0413\u043e\u0440\u043a\u0438 \u041b\u0435\u0441\u043e\u0432\u044b\u0435"
    ],
    "name:und_x_variant":[
        "Gorki",
        "Gorki Lesovyye"
    ],
    "wof:name":"Gorki Lesovyye",
    "wof:placetype":"locality"
},
  "geometry": {"coordinates":[30.75,57.15],"type":"Point"}
}