{
  "type": "Feature",
  "properties": {
    "gn:admin1_code":"90",
    "gn:asciiname":"Kolpashniki",
    "gn:country_code":"RU",
    "gn:dem":124,
    "gn:feature_class":"P",
    "gn:feature_code":"PPL",
    "gn:name":"Kolpashniki",
    "gn:population":0,
    "gn:timezone":"Asia/Yekaterinburg",
    "iso:country":"RU",
    "name:rus_x_preferred":[
        "\u041a\u043e\u043b\u043f\u0430\u0448\u043d\u0438\u043a\u0438"
    ],
    "wof:name":"Kolpashniki",
    "wof:placetype":"locality"
},
  "geometry": {"coordinates":[56.7351,57.32261999999999],"type":"Point"}
}