{
  "type": "Feature",
  "properties": {
    "gn:admin1_code":"33.0",
    "gn:asciiname":"Kokushka",
    "gn:country_code":"RU",
    "gn:dem":131,
    "gn:feature_class":"P",
    "gn:feature_code":"PPL",
    "gn:name":"Kokushka",
    "gn:population":0,
    "gn:timezone":"Europe/Kirov",
    "iso:country":"RU",
    "name:rus_x_preferred":[
        "\u041a\u043e\u043a\u0443\u0448\u043a\u0430"
    ],
    "wof:name":"Kokushka",
    "wof:placetype":"locality"
},
  "geometry": {"coordinates":[48.16803,58.36553000000001],"type":"Point"}
}