{
  "type": "Feature",
  "properties": {
    "gn:admin1_code":"63",
    "gn:asciiname":"Balagachchy",
    "gn:country_code":"RU",
    "gn:dem":151,
    "gn:feature_class":"P",
    "gn:feature_code":"PPL",
    "gn:name":"Balagachchy",
    "gn:population":0,
    "gn:timezone":"Asia/Yakutsk",
    "iso:country":"RU",
    "name:che_x_preferred":[
        "\u0411\u0430\u043b\u0430\u0433\u0430\u0447\u0447\u044b"
    ],
    "name:eng_x_preferred":[
        "Balagachchy"
    ],
    "name:nor_x_preferred":[
        "Balagatsjtsjy"
    ],
    "name:rus_x_preferred":[
        "\u0411\u0430\u043b\u0430\u0433\u0430\u0447\u0447\u044b"
    ],
    "name:sah_x_preferred":[
        "\u0411\u0430\u043b\u0430\u0495\u0430\u0447\u0447\u044b"
    ],
    "wof:name":"Balagachchy",
    "wof:placetype":"locality"
},
  "geometry": {"coordinates":[125.50530000000001,63.44532],"type":"Point"}
}