{
  "type": "Feature",
  "properties": {
    "gn:admin1_code":"67.0",
    "gn:asciiname":"Fermy",
    "gn:country_code":"RU",
    "gn:dem":192,
    "gn:feature_class":"P",
    "gn:feature_code":"PPL",
    "gn:name":"Fermy",
    "gn:population":0,
    "gn:timezone":"Europe/Saratov",
    "iso:country":"RU",
    "name:rus_x_preferred":[
        "\u0424\u0435\u0440\u043c\u044b"
    ],
    "wof:name":"Fermy",
    "wof:placetype":"locality"
},
  "geometry": {"coordinates":[45.6462,51.91654000000001],"type":"Point"}
}