{
  "type": "Feature",
  "properties": {
    "gn:admin1_code":"8",
    "gn:asciiname":"Urgala",
    "gn:country_code":"RU",
    "gn:dem":350,
    "gn:feature_class":"P",
    "gn:feature_code":"PPL",
    "gn:name":"Urgala",
    "gn:population":0,
    "gn:timezone":"Asia/Yekaterinburg",
    "iso:country":"RU",
    "name:eng_x_preferred":[
        "Urgala"
    ],
    "name:nor_x_preferred":[
        "Urgala"
    ],
    "name:rus_x_preferred":[
        "\u0423\u0440\u0433\u0430\u043b\u0430"
    ],
    "wof:name":"Urgala",
    "wof:placetype":"locality"
},
  "geometry": {"coordinates":[59.50417,55.54667],"type":"Point"}
}