{
  "type": "Feature",
  "properties": {
    "gn:admin1_code":"54",
    "gn:asciiname":"Skobelevka",
    "gn:country_code":"RU",
    "gn:dem":115,
    "gn:feature_class":"P",
    "gn:feature_code":"PPL",
    "gn:name":"Skobelevka",
    "gn:population":0,
    "gn:timezone":"Asia/Omsk",
    "iso:country":"RU",
    "name:aze_x_preferred":[
        "Skobelyovka"
    ],
    "name:msa_x_preferred":[
        "Skobelevka"
    ],
    "name:rus_x_preferred":[
        "\u0421\u043a\u043e\u0431\u0435\u043b\u0435\u0432\u043a\u0430"
    ],
    "wof:name":"Skobelevka",
    "wof:placetype":"locality"
},
  "geometry": {"coordinates":[72.01666999999998,55.28333000000001],"type":"Point"}
}