{
  "type": "Feature",
  "properties": {
    "gn:admin1_code":"33.0",
    "gn:asciiname":"Bol'shoy Kulyanur",
    "gn:country_code":"RU",
    "gn:dem":135,
    "gn:feature_class":"P",
    "gn:feature_code":"PPL",
    "gn:name":"Bol\u2019shoy Kulyanur",
    "gn:population":0,
    "gn:timezone":"Europe/Kirov",
    "iso:country":"RU",
    "name:rus_x_preferred":[
        "\u0411\u043e\u043b\u044c\u0448\u043e\u0439 \u041a\u0443\u043b\u044f\u043d\u0443\u0440"
    ],
    "name:und_x_variant":[
        "Bol\u2019shoy Kolyanur",
        "Bol\u2019shoy Kulyanur"
    ],
    "wof:name":"Bol'shoy Kulyanur",
    "wof:placetype":"locality"
},
  "geometry": {"coordinates":[48.43006,57.39405],"type":"Point"}
}