{
  "type": "Feature",
  "properties": {
    "gn:admin1_code":"6.0",
    "gn:asciiname":"Proshinskaya",
    "gn:country_code":"RU",
    "gn:dem":55,
    "gn:feature_class":"P",
    "gn:feature_code":"PPL",
    "gn:name":"Proshinskaya",
    "gn:population":0,
    "gn:timezone":"Europe/Moscow",
    "iso:country":"RU",
    "name:rus_x_preferred":[
        "\u041f\u0440\u043e\u0448\u0438\u043d\u0441\u043a\u0430\u044f"
    ],
    "wof:name":"Proshinskaya",
    "wof:placetype":"locality"
},
  "geometry": {"coordinates":[45.2169,62.1172],"type":"Point"}
}