{
  "type": "Feature",
  "properties": {
    "gn:admin1_code":"69",
    "gn:asciiname":"Trosno-Isayevo",
    "gn:cc2":"RU",
    "gn:country_code":"RU",
    "gn:dem":187,
    "gn:feature_class":"P",
    "gn:feature_code":"PPL",
    "gn:name":"Trosno-Isayevo",
    "gn:population":0,
    "gn:timezone":"Europe/Moscow",
    "iso:country":"RU",
    "name:und_x_variant":[
        "Trosno",
        "Trosno-Isayevo"
    ],
    "wof:name":"Trosno-Isayevo",
    "wof:placetype":"locality"
},
  "geometry": {"coordinates":[32.96083,53.67028000000001],"type":"Point"}
}