{
  "type": "Feature",
  "properties": {
    "gn:admin1_code":"33.0",
    "gn:asciiname":"Malkovy",
    "gn:country_code":"RU",
    "gn:dem":114,
    "gn:feature_class":"P",
    "gn:feature_code":"PPL",
    "gn:name":"Malkovy",
    "gn:population":0,
    "gn:timezone":"Europe/Kirov",
    "iso:country":"RU",
    "name:rus_x_preferred":[
        "\u041c\u0430\u043b\u043a\u043e\u0432\u044b"
    ],
    "wof:name":"Malkovy",
    "wof:placetype":"locality"
},
  "geometry": {"coordinates":[48.42099,58.5658],"type":"Point"}
}