{
  "type": "Feature",
  "properties": {
    "gn:admin1_code":"88",
    "gn:asciiname":"Korchmino",
    "gn:country_code":"RU",
    "gn:dem":123,
    "gn:feature_class":"P",
    "gn:feature_code":"PPL",
    "gn:name":"Korchmino",
    "gn:population":0,
    "gn:timezone":"Europe/Moscow",
    "iso:country":"RU",
    "name:rus_x_preferred":[
        "\u041a\u043e\u0440\u0447\u043c\u0438\u043d\u043e"
    ],
    "name:und_x_variant":[
        "\u041a\u043e\u0440\u0447\u043c\u0438\u043d\u043e"
    ],
    "wof:name":"Korchmino",
    "wof:placetype":"locality"
},
  "geometry": {"coordinates":[38.2584,57.7365],"type":"Point"}
}