{
  "type": "Feature",
  "properties": {
    "gn:admin1_code":"85.0",
    "gn:asciiname":"Kachalovo",
    "gn:country_code":"RU",
    "gn:dem":187,
    "gn:feature_class":"P",
    "gn:feature_code":"PPL",
    "gn:name":"Kachalovo",
    "gn:population":0,
    "gn:timezone":"Europe/Moscow",
    "iso:country":"RU",
    "name:rus_x_preferred":[
        "\u041a\u0430\u0447\u0430\u043b\u043e\u0432\u043e"
    ],
    "wof:name":"Kachalovo",
    "wof:placetype":"locality"
},
  "geometry": {"coordinates":[40.11719,58.90299],"type":"Point"}
}