{
  "type": "Feature",
  "properties": {
    "gn:admin1_code":"91",
    "gn:asciiname":"Ust'-Parnaya",
    "gn:country_code":"RU",
    "gn:dem":350,
    "gn:feature_class":"P",
    "gn:feature_code":"PPL",
    "gn:name":"Ust\u2019-Parnaya",
    "gn:population":0,
    "gn:timezone":"Asia/Krasnoyarsk",
    "iso:country":"RU",
    "name:eng_x_preferred":[
        "Ust'-Parnaya"
    ],
    "name:nor_x_preferred":[
        "Ust-Parnaja"
    ],
    "name:rus_x_preferred":[
        "\u0423\u0441\u0442\u044c-\u041f\u0430\u0440\u043d\u0430\u044f"
    ],
    "name:und_x_variant":[
        "Ust\u2019-Parnaya"
    ],
    "wof:name":"Ust'-Parnaya",
    "wof:placetype":"locality"
},
  "geometry": {"coordinates":[89.13018000000002,55.41],"type":"Point"}
}