{
  "type": "Feature",
  "properties": {
    "gn:admin1_code":"86",
    "gn:asciiname":"Agarkov",
    "gn:country_code":"RU",
    "gn:dem":155,
    "gn:feature_class":"P",
    "gn:feature_code":"PPL",
    "gn:name":"Agarkov",
    "gn:population":0,
    "gn:timezone":"Europe/Moscow",
    "iso:country":"RU",
    "name:rus_x_preferred":[
        "\u0410\u0433\u0430\u0440\u043a\u043e\u0432"
    ],
    "name:und_x_variant":[
        "Ogarkov",
        "Agarkov"
    ],
    "wof:name":"Agarkov",
    "wof:placetype":"locality"
},
  "geometry": {"coordinates":[40.02639,51.44361],"type":"Point"}
}