{
  "type": "Feature",
  "properties": {
    "gn:admin1_code":"90.0",
    "gn:asciiname":"Verkhnemostovaya",
    "gn:country_code":"RU",
    "gn:dem":163,
    "gn:feature_class":"P",
    "gn:feature_code":"PPL",
    "gn:name":"Verkhnemostovaya",
    "gn:population":0,
    "gn:timezone":"Asia/Yekaterinburg",
    "iso:country":"RU",
    "name:rus_x_preferred":[
        "\u0412\u0435\u0440\u0445\u043d\u0435\u043c\u043e\u0441\u0442\u043e\u0432\u0430\u044f"
    ],
    "name:und_x_variant":[
        "Verkhnyaya Mostovaya",
        "Verkhnemostovaya"
    ],
    "wof:name":"Verkhnemostovaya",
    "wof:placetype":"locality"
},
  "geometry": {"coordinates":[56.23735,58.14527],"type":"Point"}
}