{
  "type": "Feature",
  "properties": {
    "gn:admin1_code":"77",
    "gn:asciiname":"Vorob'ikha",
    "gn:country_code":"RU",
    "gn:dem":154,
    "gn:feature_class":"P",
    "gn:feature_code":"PPL",
    "gn:name":"Vorob\u2019ikha",
    "gn:population":0,
    "gn:timezone":"Europe/Moscow",
    "iso:country":"RU",
    "name:rus_x_preferred":[
        "\u0412\u043e\u0440\u043e\u0431\u044c\u0438\u0445\u0430"
    ],
    "name:und_x_variant":[
        "Vorob\u2019ikha",
        "\u0412\u043e\u0440\u043e\u0431\u044c\u0438\u0445\u0430"
    ],
    "wof:name":"Vorob'ikha",
    "wof:placetype":"locality"
},
  "geometry": {"coordinates":[37.49534,58.05049],"type":"Point"}
}