{
  "type": "Feature",
  "properties": {
    "gn:country":"RU",
    "gn:fcode":"PPL",
    "gn:pop":0,
    "iso:country":"RU",
    "name:eng_x_preferred":[
        "Merkul'yevo"
    ],
    "name:nor_x_preferred":[
        "Merkuljevo"
    ],
    "name:rus_x_preferred":[
        "\u041c\u0435\u0440\u043a\u0443\u043b\u044c\u0435\u0432\u043e"
    ],
    "name:unk_x_variant":[
        "\u041c\u0435\u0440\u043a\u0443\u043b\u044c\u0435\u0432\u043e"
    ],
    "qs:name":"Merkul'yevo",
    "qs:name_adm0":"Russia",
    "qs:name_adm1":"Bryansk Oblast",
    "qs:photos_9r":0,
    "qs:photos_sr":0,
    "qs:placetype":"Town",
    "qs:pop_sr":"0",
    "wof:name":"Merkul'yevo",
    "wof:placetype":"locality",
    "wof:population":0
},
  "geometry": {"coordinates":[34.15616,53.27451],"type":"Point"}
}