{
  "type": "Feature",
  "properties": {
    "gn:admin1_code":"37",
    "gn:asciiname":"Zhikhorevo",
    "gn:country_code":"RU",
    "gn:dem":165,
    "gn:feature_class":"P",
    "gn:feature_code":"PPL",
    "gn:name":"Zhikhor\u00ebvo",
    "gn:population":0,
    "gn:timezone":"Europe/Moscow",
    "iso:country":"RU",
    "name:rus_x_preferred":[
        "\u0416\u0438\u0445\u043e\u0440\u00eb\u0432\u043e"
    ],
    "name:und_x_variant":[
        "Zhikhor\u00ebvo",
        "Zhikhar\u00ebvo"
    ],
    "wof:name":"Zhikhorevo",
    "wof:placetype":"locality"
},
  "geometry": {"coordinates":[43.00784,58.37422],"type":"Point"}
}