{
  "type": "Feature",
  "properties": {
    "gn:admin1_code":"71",
    "gn:asciiname":"Gorbunovskoye",
    "gn:country_code":"RU",
    "gn:dem":79,
    "gn:feature_class":"P",
    "gn:feature_code":"PPL",
    "gn:name":"Gorbunovskoye",
    "gn:population":0,
    "gn:timezone":"Asia/Yekaterinburg",
    "iso:country":"RU",
    "name:eng_x_preferred":[
        "Gorbunovskoye"
    ],
    "name:nor_x_preferred":[
        "Gorbunovskoje"
    ],
    "name:rus_x_preferred":[
        "\u0413\u043e\u0440\u0431\u0443\u043d\u043e\u0432\u0441\u043a\u043e\u0435"
    ],
    "name:und_x_variant":[
        "Gorbunovo"
    ],
    "wof:name":"Gorbunovskoye",
    "wof:placetype":"locality"
},
  "geometry": {"coordinates":[63.62548,57.08638000000001],"type":"Point"}
}