{
  "type": "Feature",
  "properties": {
    "gn:admin1_code":"6.0",
    "gn:asciiname":"Staroaksenovskaya",
    "gn:country_code":"RU",
    "gn:dem":62,
    "gn:feature_class":"P",
    "gn:feature_code":"PPL",
    "gn:name":"Staroaks\u00ebnovskaya",
    "gn:population":0,
    "gn:timezone":"Europe/Moscow",
    "iso:country":"RU",
    "name:rus_x_preferred":[
        "\u0421\u0442\u0430\u0440\u043e\u0430\u043a\u0441\u00eb\u043d\u043e\u0432\u0441\u043a\u0430\u044f"
    ],
    "name:und_x_variant":[
        "Staroaks\u00ebnovskaya"
    ],
    "wof:name":"Staroaksenovskaya",
    "wof:placetype":"locality"
},
  "geometry": {"coordinates":[45.0415,62.2296],"type":"Point"}
}