{
  "type": "Feature",
  "properties": {
    "gn:admin1_code":"17",
    "gn:admin2_code":"Tsuntinskiy Rayon",
    "gn:asciiname":"Tsibari",
    "gn:country_code":"RU",
    "gn:dem":1735,
    "gn:feature_class":"P",
    "gn:feature_code":"PPL",
    "gn:name":"Tsibari",
    "gn:population":0,
    "gn:timezone":"Europe/Moscow",
    "iso:country":"RU",
    "name:rus_x_preferred":[
        "\u0426\u0438\u0431\u0430\u0440\u0438"
    ],
    "name:und_x_variant":[
        "Tsebari",
        "Tsiburi",
        "Tsibari"
    ],
    "wof:name":"Tsibari",
    "wof:placetype":"locality"
},
  "geometry": {"coordinates":[45.87861,42.25213],"type":"Point"}
}