{
  "type": "Feature",
  "properties": {
    "gn:admin1_code":"75",
    "gn:asciiname":"Yurty",
    "gn:country_code":"RU",
    "gn:dem":55,
    "gn:feature_class":"P",
    "gn:feature_code":"PPL",
    "gn:name":"Yurty",
    "gn:population":0,
    "gn:timezone":"Asia/Tomsk",
    "iso:country":"RU",
    "name:rus_x_preferred":[
        "\u042e\u0440\u0442\u044b"
    ],
    "name:und_x_variant":[
        "Yurty-Inkiny",
        "Yurty"
    ],
    "wof:name":"Yurty",
    "wof:placetype":"locality"
},
  "geometry": {"coordinates":[82.1652,58.4924],"type":"Point"}
}