{
  "type": "Feature",
  "properties": {
    "gn:admin1_code":"68",
    "gn:asciiname":"Potiyev",
    "gn:cc2":"RU",
    "gn:country_code":"RU",
    "gn:dem":448,
    "gn:feature_class":"P",
    "gn:feature_code":"PPL",
    "gn:name":"Potiyev",
    "gn:population":0,
    "gn:timezone":"Europe/Moscow",
    "iso:country":"RU",
    "name:rus_x_preferred":[
        "\u041f\u043e\u0442\u0438\u0435\u0432"
    ],
    "name:und_x_variant":[
        "Potnev",
        "Potiyev",
        "\u041f\u043e\u0442\u0438\u0435\u0432"
    ],
    "wof:name":"Potiyev",
    "wof:placetype":"locality"
},
  "geometry": {"coordinates":[44.46667,43.45],"type":"Point"}
}