{
  "type": "Feature",
  "properties": {
    "gn:admin1_code":"73",
    "gn:asciiname":"Novoye Sumarokovo",
    "gn:country_code":"RU",
    "gn:dem":229,
    "gn:feature_class":"P",
    "gn:feature_code":"PPL",
    "gn:name":"Novoye Sumarokovo",
    "gn:population":0,
    "gn:timezone":"Europe/Moscow",
    "iso:country":"RU",
    "name:eng_x_preferred":[
        "Novosumarokovo"
    ],
    "name:nor_x_preferred":[
        "Novoje Sumarokovo"
    ],
    "name:rus_x_preferred":[
        "\u041d\u043e\u0432\u043e\u0435 \u0421\u0443\u043c\u0430\u0440\u043e\u043a\u043e\u0432\u043e"
    ],
    "wof:name":"Novoye Sumarokovo",
    "wof:placetype":"locality"
},
  "geometry": {"coordinates":[53.0298,54.65042],"type":"Point"}
}