{
  "type": "Feature",
  "properties": {
    "gn:admin1_code":"65",
    "gn:asciiname":"Kamennyy Ovrag",
    "gn:country_code":"RU",
    "gn:dem":79,
    "gn:feature_class":"P",
    "gn:feature_code":"PPL",
    "gn:name":"Kamennyy Ovrag",
    "gn:population":0,
    "gn:timezone":"Europe/Samara",
    "iso:country":"RU",
    "name:rus_x_preferred":[
        "\u041a\u0430\u043c\u0435\u043d\u043d\u044b\u0439 \u041e\u0432\u0440\u0430\u0433"
    ],
    "name:und_x_variant":[
        "\u041a\u0430\u043c\u0435\u043d\u043d\u044b\u0439 \u041e\u0432\u0440\u0430\u0433"
    ],
    "wof:name":"Kamennyy Ovrag",
    "wof:placetype":"locality"
},
  "geometry": {"coordinates":[50.5708,54.2806],"type":"Point"}
}