{
  "type": "Feature",
  "properties": {
    "gn:admin1_code":"51.0",
    "gn:asciiname":"Prokurino",
    "gn:country_code":"RU",
    "gn:dem":114,
    "gn:feature_class":"P",
    "gn:feature_code":"PPL",
    "gn:name":"Prokurino",
    "gn:population":0,
    "gn:timezone":"Europe/Moscow",
    "iso:country":"RU",
    "name:nor_x_preferred":[
        "Prokurino"
    ],
    "name:rus_x_preferred":[
        "\u041f\u0440\u043e\u043a\u0443\u0440\u0438\u043d\u043e"
    ],
    "wof:name":"Prokurino",
    "wof:placetype":"locality"
},
  "geometry": {"coordinates":[43.75699,56.9205],"type":"Point"}
}