{
  "type": "Feature",
  "properties": {
    "gn:admin1_code":"43",
    "gn:asciiname":"Osinovo",
    "gn:country_code":"RU",
    "gn:dem":209,
    "gn:feature_class":"P",
    "gn:feature_code":"PPL",
    "gn:name":"Osinovo",
    "gn:population":0,
    "gn:timezone":"Europe/Moscow",
    "iso:country":"RU",
    "name:rus_x_preferred":[
        "\u041e\u0441\u0438\u043d\u043e\u0432\u043e"
    ],
    "name:und_x_variant":[
        "Osinovoye",
        "Osinovo"
    ],
    "wof:name":"Osinovo",
    "wof:placetype":"locality"
},
  "geometry": {"coordinates":[38.68825,53.09538000000001],"type":"Point"}
}