{
  "type": "Feature",
  "properties": {
    "gn:admin1_code":"3",
    "gn:asciiname":"Ozero-Kureyevo",
    "gn:country_code":"RU",
    "gn:dem":262,
    "gn:feature_class":"P",
    "gn:feature_code":"PPL",
    "gn:name":"Ozero-Kureyevo",
    "gn:population":388,
    "gn:timezone":"Asia/Omsk",
    "iso:country":"RU",
    "name:ceb_x_preferred":[
        "Ozero-Kureyevo"
    ],
    "name:che_x_preferred":[
        "\u041e\u0437\u0435\u0440\u043e-\u041a\u0443\u0440\u0435\u0435\u0432\u043e"
    ],
    "name:eng_x_preferred":[
        "Ozero-Kureyevo"
    ],
    "name:nor_x_preferred":[
        "Ozero Kurejevo"
    ],
    "name:rus_x_preferred":[
        "\u041e\u0437\u0435\u0440\u043e \u041a\u0443\u0440\u0435\u0435\u0432\u043e"
    ],
    "name:rus_x_variant":[
        "\u041e\u0437\u0435\u0440\u043e-\u041a\u0443\u0440\u0435\u0435\u0432\u043e"
    ],
    "name:tat_x_preferred":[
        "\u041e\u0437\u0435\u0440\u043e-\u041a\u0443\u0440\u0435\u0435\u0432\u043e"
    ],
    "name:ukr_x_preferred":[
        "\u041e\u0437\u0435\u0440\u043e-\u041a\u0443\u0440\u0435\u0454\u0432\u043e"
    ],
    "wof:name":"Ozero-Kureyevo",
    "wof:placetype":"locality",
    "wof:population":388
},
  "geometry": {"coordinates":[86.75020000000001,52.4661],"type":"Point"}
}