{
  "type": "Feature",
  "properties": {
    "gn:admin1_code":"16",
    "gn:asciiname":"Nizhneye Timercheyevo",
    "gn:country_code":"RU",
    "gn:dem":132,
    "gn:feature_class":"P",
    "gn:feature_code":"PPL",
    "gn:name":"Nizhneye Timercheyevo",
    "gn:population":0,
    "gn:timezone":"Europe/Moscow",
    "iso:country":"RU",
    "name:rus_x_preferred":[
        "\u041d\u0438\u0436\u043d\u0435\u0435 \u0422\u0438\u043c\u0435\u0440\u0447\u0435\u0435\u0432\u043e"
    ],
    "name:und_x_variant":[
        "Nizhneye Timrecheyevo",
        "Nishneye Timercheyevo",
        "Nizhneye Timercheyevo",
        "\u041d\u0438\u0436\u043d\u0435\u0435 \u0422\u0438\u043c\u0435\u0440\u0447\u0435\u0435\u0432\u043e"
    ],
    "wof:name":"Nizhneye Timercheyevo",
    "wof:placetype":"locality"
},
  "geometry": {"coordinates":[47.39235,55.18559000000001],"type":"Point"}
}