{
  "type": "Feature",
  "properties": {
    "gn:admin1_code":"84",
    "gn:asciiname":"Kolobrodov",
    "gn:country_code":"RU",
    "gn:dem":98,
    "gn:feature_class":"P",
    "gn:feature_code":"PPL",
    "gn:name":"Kolobrodov",
    "gn:population":0,
    "gn:timezone":"Europe/Volgograd",
    "iso:country":"RU",
    "name:rus_x_preferred":[
        "\u041a\u043e\u043b\u043e\u0431\u0440\u043e\u0434\u043e\u0432"
    ],
    "name:und_x_variant":[
        "Khutor Kolobrodov",
        "Kolobrodov",
        "\u041a\u043e\u043b\u043e\u0431\u0440\u043e\u0434\u043e\u0432"
    ],
    "wof:name":"Kolobrodov",
    "wof:placetype":"locality"
},
  "geometry": {"coordinates":[43.46341,49.79422],"type":"Point"}
}