{
  "type": "Feature",
  "properties": {
    "gn:admin1_code":"45.0",
    "gn:asciiname":"Vonzhedur",
    "gn:country_code":"RU",
    "gn:dem":136,
    "gn:feature_class":"P",
    "gn:feature_code":"PPL",
    "gn:name":"Vonzhedur",
    "gn:population":0,
    "gn:timezone":"Europe/Moscow",
    "iso:country":"RU",
    "name:rus_x_preferred":[
        "\u0412\u043e\u043d\u0436\u0435\u0434\u0443\u0440"
    ],
    "wof:name":"Vonzhedur",
    "wof:placetype":"locality"
},
  "geometry": {"coordinates":[48.75694,56.42528000000001],"type":"Point"}
}