{
  "type": "Feature",
  "properties": {
    "gn:admin1_code":"6",
    "gn:asciiname":"Sobolevo",
    "gn:country_code":"RU",
    "gn:dem":146,
    "gn:feature_class":"P",
    "gn:feature_code":"PPL",
    "gn:name":"Sobolevo",
    "gn:population":0,
    "gn:timezone":"Europe/Moscow",
    "iso:country":"RU",
    "wof:name":"Sobolevo",
    "wof:placetype":"locality"
},
  "geometry": {"coordinates":[44.46667,61.21666999999999],"type":"Point"}
}