{
  "type": "Feature",
  "properties": {
    "gn:admin1_code":"23",
    "gn:asciiname":"Kuybyshevskoye",
    "gn:country_code":"RU",
    "gn:dem":13,
    "gn:feature_class":"P",
    "gn:feature_code":"PPL",
    "gn:name":"Kuybyshevskoye",
    "gn:population":0,
    "gn:timezone":"Europe/Kaliningrad",
    "iso:country":"RU",
    "name:rus_x_preferred":[
        "\u041a\u0443\u0439\u0431\u044b\u0448\u0435\u0432\u0441\u043a\u043e\u0435"
    ],
    "name:und_x_variant":[
        "Petersdorf",
        "Kuybyshevskoye",
        "\u041a\u0443\u0439\u0431\u044b\u0448\u0435\u0432\u0441\u043a\u043e\u0435"
    ],
    "wof:name":"Kuybyshevskoye",
    "wof:placetype":"locality"
},
  "geometry": {"coordinates":[21.28035,54.6435],"type":"Point"}
}