{
  "type": "Feature",
  "properties": {
    "gn:admin1_code":"85",
    "gn:asciiname":"Sergozero",
    "gn:country_code":"RU",
    "gn:dem":156,
    "gn:feature_class":"P",
    "gn:feature_code":"PPL",
    "gn:name":"Sergozero",
    "gn:population":0,
    "gn:timezone":"Europe/Moscow",
    "iso:country":"RU",
    "name:rus_x_preferred":[
        "\u0421\u0435\u0440\u0433\u043e\u0437\u0435\u0440\u043e"
    ],
    "name:und_x_variant":[
        "\u0421\u0435\u0440\u0433\u043e\u0437\u0435\u0440\u043e"
    ],
    "wof:name":"Sergozero",
    "wof:placetype":"locality"
},
  "geometry": {"coordinates":[39.7612,60.2624],"type":"Point"}
}