{
  "type": "Feature",
  "properties": {
    "gn:admin1_code":"60",
    "gn:asciiname":"Surni",
    "gn:country_code":"RU",
    "gn:dem":125,
    "gn:feature_class":"P",
    "gn:feature_code":"PPL",
    "gn:name":"Surni",
    "gn:population":0,
    "gn:timezone":"Europe/Moscow",
    "iso:country":"RU",
    "name:rus_x_preferred":[
        "\u0421\u0443\u0440\u044c\u043d\u0438"
    ],
    "name:rus_x_variant":[
        "\u0421\u0443\u0440\u043d\u0438"
    ],
    "name:und_x_variant":[
        "Sur\u2019ni",
        "Surni"
    ],
    "wof:name":"Surni",
    "wof:placetype":"locality"
},
  "geometry": {"coordinates":[28.68718,56.65443000000001],"type":"Point"}
}