{
  "type": "Feature",
  "properties": {
    "gn:admin1_code":"78",
    "gn:asciiname":"Ashlyk",
    "gn:country_code":"RU",
    "gn:dem":55,
    "gn:feature_class":"P",
    "gn:feature_code":"PPL",
    "gn:name":"Ashlyk",
    "gn:population":0,
    "gn:timezone":"Asia/Yekaterinburg",
    "iso:country":"RU",
    "name:eng_x_preferred":[
        "Ashlyk"
    ],
    "name:nor_x_preferred":[
        "Asjlyk"
    ],
    "name:rus_x_preferred":[
        "\u0410\u0448\u043b\u044b\u043a"
    ],
    "wof:name":"Ashlyk",
    "wof:placetype":"locality"
},
  "geometry": {"coordinates":[68.66667,57.55],"type":"Point"}
}