{
  "type": "Feature",
  "properties": {
    "gn:admin1_code":"42",
    "gn:asciiname":"Samola",
    "gn:country_code":"RU",
    "gn:dem":9,
    "gn:feature_class":"P",
    "gn:feature_code":"PPL",
    "gn:name":"Samola",
    "gn:population":0,
    "gn:timezone":"Europe/Moscow",
    "iso:country":"RU",
    "name:rus_x_preferred":[
        "\u0421\u0430\u043c\u043e\u043b\u0430"
    ],
    "name:und_x_variant":[
        "\u0421\u0430\u043c\u043e\u043b\u0430"
    ],
    "wof:name":"Samola",
    "wof:placetype":"locality"
},
  "geometry": {"coordinates":[28.68333,60.63333000000001],"type":"Point"}
}