{
  "type": "Feature",
  "properties": {
    "gn:admin1_code":"28.0",
    "gn:asciiname":"Shalgovaara",
    "gn:country_code":"RU",
    "gn:dem":113,
    "gn:feature_class":"P",
    "gn:feature_code":"PPL",
    "gn:name":"Shalgovaara",
    "gn:population":100,
    "gn:timezone":"Europe/Moscow",
    "iso:country":"RU",
    "name:fin_x_preferred":[
        "Salkovaara"
    ],
    "name:rus_x_preferred":[
        "\u0428\u0430\u043b\u0433\u043e\u0432\u0430\u0430\u0440\u0430"
    ],
    "wof:name":"Shalgovaara",
    "wof:placetype":"locality",
    "wof:population":100
},
  "geometry": {"coordinates":[33.24772,63.51106],"type":"Point"}
}