{
  "type": "Feature",
  "properties": {
    "gn:admin1_code":"20",
    "gn:asciiname":"Polovina",
    "gn:country_code":"RU",
    "gn:dem":516,
    "gn:feature_class":"P",
    "gn:feature_code":"PPL",
    "gn:name":"Polovina",
    "gn:population":0,
    "gn:timezone":"Asia/Irkutsk",
    "iso:country":"RU",
    "name:pol_x_preferred":[
        "Polovina"
    ],
    "wof:name":"Polovina",
    "wof:placetype":"locality"
},
  "geometry": {"coordinates":[103.23305999999999,53.01667],"type":"Point"}
}