{
  "type": "Feature",
  "properties": {
    "gn:admin1_code":"6",
    "gn:asciiname":"Pozdyayevskaya",
    "gn:country_code":"RU",
    "gn:dem":147,
    "gn:feature_class":"P",
    "gn:feature_code":"PPL",
    "gn:name":"Pozdyayevskaya",
    "gn:population":0,
    "gn:timezone":"Europe/Moscow",
    "iso:country":"RU",
    "name:rus_x_preferred":[
        "\u041f\u043e\u0437\u0434\u044f\u0435\u0432\u0441\u043a\u0430\u044f"
    ],
    "name:und_x_variant":[
        "Pozdeyevskaya",
        "Pozdyayevskaya"
    ],
    "wof:name":"Pozdyayevskaya",
    "wof:placetype":"locality"
},
  "geometry": {"coordinates":[48.38308,60.99129],"type":"Point"}
}