{
  "type": "Feature",
  "properties": {
    "gn:admin1_code":"9",
    "gn:asciiname":"Podseredneye",
    "gn:country_code":"RU",
    "gn:dem":167,
    "gn:feature_class":"P",
    "gn:feature_code":"PPL",
    "gn:name":"Podseredneye",
    "gn:population":0,
    "gn:timezone":"Europe/Moscow",
    "iso:country":"RU",
    "name:eng_x_preferred":[
        "Podserednoye"
    ],
    "name:nor_x_preferred":[
        "Podseredneje"
    ],
    "name:rus_x_preferred":[
        "\u041f\u043e\u0434\u0441\u0435\u0440\u0435\u0434\u043d\u0435\u0435"
    ],
    "name:und_x_variant":[
        "Poserednoye",
        "Podserednoye",
        "Podseredneye"
    ],
    "wof:name":"Podseredneye",
    "wof:placetype":"locality"
},
  "geometry": {"coordinates":[38.5626,50.7087],"type":"Point"}
}