{
  "type": "Feature",
  "properties": {
    "gn:country":"RU",
    "gn:fcode":"PPL",
    "gn:population":0,
    "iso:country":"RU",
    "name:jpn_x_preferred":[
        "\u897f\u90e8\u8ecd\u7ba1\u533a"
    ],
    "name:kor_x_preferred":[
        "\uc11c\ubd80 \uad70\uad00\uad6c"
    ],
    "name:nno_x_preferred":[
        "Vestre milit\u00e6rdistrikt"
    ],
    "name:nob_x_preferred":[
        "Vestre milit\u00e6rdistrikt"
    ],
    "name:rus_x_preferred":[
        "\u041c\u0435\u0447\u043d\u0438\u043a\u043e\u0432\u043e"
    ],
    "name:und_x_variant":[
        "Pos\u00eblok Mechnikova"
    ],
    "name:zho_x_preferred":[
        "Blagoveshchensky"
    ],
    "name:zho_x_variant":[
        "\u897f\u90e8\u8ecd\u5340"
    ],
    "qs:name":"Mechnikovo",
    "qs:name_adm0":"Russia",
    "qs:name_adm1":"Moscow Oblast",
    "qs:photos_9r":0,
    "qs:photos_sr":0,
    "qs:placetype":"Town",
    "qs:pop_sr":"0",
    "wd:wordcount":643,
    "wof:name":"Mechnikovo",
    "wof:placetype":"locality",
    "wof:population":0
},
  "geometry": {"coordinates":[37.16427,55.75472],"type":"Point"}
}