{
  "type": "Feature",
  "properties": {
    "gn:country":"RU",
    "gn:fcode":"PPL",
    "gn:pop":0,
    "iso:country":"RU",
    "name:rus_x_preferred":[
        "\u041c\u0435\u0447\u043d\u0438\u043a\u043e\u0432\u043e"
    ],
    "name:unk_x_variant":[
        "Pos\u00eblok Mechnikova"
    ],
    "qs:name":"Mechnikovo",
    "qs:name_adm0":"Russia",
    "qs:name_adm1":"Moscow Oblast",
    "qs:photos_9r":0,
    "qs:photos_sr":0,
    "qs:placetype":"Town",
    "qs:pop_sr":"0",
    "wd:wordcount":643,
    "wof:name":"Mechnikovo",
    "wof:placetype":"locality",
    "wof:population":0
},
  "geometry": {"coordinates":[37.16427,55.75472],"type":"Point"}
}