{
  "type": "Feature",
  "properties": {
    "gn:admin1_code":"20.0",
    "gn:asciiname":"Tinskaya Dacha",
    "gn:country_code":"RU",
    "gn:dem":333,
    "gn:feature_class":"P",
    "gn:feature_code":"PPL",
    "gn:name":"Tinskaya Dacha",
    "gn:population":0,
    "gn:timezone":"Asia/Irkutsk",
    "iso:country":"RU",
    "name:rus_x_preferred":[
        "\u0422\u0438\u043d\u0441\u043a\u0430\u044f \u0414\u0430\u0447\u0430"
    ],
    "wof:name":"Tinskaya Dacha",
    "wof:placetype":"locality"
},
  "geometry": {"coordinates":[97.29519999999999,56.0034],"type":"Point"}
}