{
  "type": "Feature",
  "properties": {
    "gn:admin1_code":"53",
    "gn:asciiname":"Lukovskiy",
    "gn:country_code":"RU",
    "gn:dem":108,
    "gn:feature_class":"P",
    "gn:feature_code":"PPL",
    "gn:name":"Lukovskiy",
    "gn:population":0,
    "gn:timezone":"Asia/Novosibirsk",
    "iso:country":"RU",
    "name:eng_x_preferred":[
        "Lukovskiy"
    ],
    "name:nor_x_preferred":[
        "Lukovskij"
    ],
    "name:rus_x_preferred":[
        "\u041b\u0443\u043a\u043e\u0432\u0441\u043a\u0438\u0439"
    ],
    "name:und_x_variant":[
        "Lukovka"
    ],
    "wof:name":"Lukovskiy",
    "wof:placetype":"locality"
},
  "geometry": {"coordinates":[77.46987,55.72503],"type":"Point"}
}