{
  "type": "Feature",
  "properties": {
    "gn:country":"RU",
    "gn:fcode":"PPL",
    "gn:pop":3865,
    "iso:country":"RU",
    "name:arm_x_preferred":[
        "\u0532\u0578\u0582\u0564\u0578\u0563\u0578\u0577\u0579"
    ],
    "name:bul_x_preferred":[
        "\u0411\u0443\u0434\u043e\u0433\u043e\u0448\u0447"
    ],
    "name:che_x_preferred":[
        "\u0411\u0443\u0434\u043e\u0433\u043e\u0449\u044c"
    ],
    "name:dut_x_preferred":[
        "Boedogosjtsj"
    ],
    "name:eng_x_preferred":[
        "Budogoshch'"
    ],
    "name:est_x_preferred":[
        "Budogo\u0161t\u0161"
    ],
    "name:fin_x_preferred":[
        "Budogo\u0161t\u0161"
    ],
    "name:fre_x_preferred":[
        "Budogochtch"
    ],
    "name:ita_x_preferred":[
        "Budogo\u0161\u010d'"
    ],
    "name:nor_x_preferred":[
        "Budogosjtsj"
    ],
    "name:rus_x_preferred":[
        "\u0411\u0443\u0434\u043e\u0433\u043e\u0449\u044c"
    ],
    "name:srp_x_preferred":[
        "\u0411\u0443\u0434\u043e\u0433\u043e\u0448\u0447"
    ],
    "name:unk_x_variant":[
        "Budogoschtsch"
    ],
    "qs:name":"Budogoshch'",
    "qs:name_adm0":"Russia",
    "qs:name_adm1":"Leningrad Oblast",
    "qs:photos_9r":0,
    "qs:photos_sr":0,
    "qs:placetype":"Town",
    "qs:pop_sr":"4",
    "wd:wordcount":1389,
    "wof:name":"Budogoshch'",
    "wof:placetype":"locality",
    "wof:population":3865
},
  "geometry": {"coordinates":[32.47074,59.28158],"type":"Point"}
}