{
  "type": "Feature",
  "properties": {
    "gn:admin1_code":"53",
    "gn:asciiname":"Kourak",
    "gn:country_code":"RU",
    "gn:dem":209,
    "gn:feature_class":"P",
    "gn:feature_code":"PPL",
    "gn:name":"Kourak",
    "gn:population":0,
    "gn:timezone":"Asia/Novosibirsk",
    "iso:country":"RU",
    "name:eng_x_preferred":[
        "Kourak"
    ],
    "name:nor_x_preferred":[
        "Kourak"
    ],
    "name:rus_x_preferred":[
        "\u041a\u043e\u0443\u0440\u0430\u043a"
    ],
    "wof:name":"Kourak",
    "wof:placetype":"locality"
},
  "geometry": {"coordinates":[84.67694,54.82917],"type":"Point"}
}