{
  "type": "Feature",
  "properties": {
    "gn:admin1_code":"4",
    "gn:asciiname":"Zelenaya Roshcha",
    "gn:country_code":"RU",
    "gn:dem":226,
    "gn:feature_class":"P",
    "gn:feature_code":"PPL",
    "gn:name":"Zel\u00ebnaya Roshcha",
    "gn:population":0,
    "gn:timezone":"Asia/Barnaul",
    "iso:country":"RU",
    "name:eng_x_preferred":[
        "Zel\u00ebnaya Roshcha"
    ],
    "name:nor_x_preferred":[
        "Zelenaja Rosjtsja"
    ],
    "name:rus_x_preferred":[
        "\u0417\u0435\u043b\u0435\u043d\u0430\u044f \u0420\u043e\u0449\u0430"
    ],
    "name:rus_x_variant":[
        "\u0417\u0435\u043b\u0451\u043d\u0430\u044f \u0420\u043e\u0449\u0430"
    ],
    "wof:name":"Zelenaya Roshcha",
    "wof:placetype":"locality"
},
  "geometry": {"coordinates":[82.5025,53.06222],"type":"Point"}
}