{
  "type": "Feature",
  "properties": {
    "gn:admin1_code":"10.0",
    "gn:asciiname":"Chernechek",
    "gn:country_code":"RU",
    "gn:dem":229,
    "gn:feature_class":"P",
    "gn:feature_code":"PPL",
    "gn:name":"Chernechek",
    "gn:population":0,
    "gn:timezone":"Europe/Moscow",
    "iso:country":"RU",
    "name:rus_x_preferred":[
        "\u0427\u0435\u0440\u043d\u0435\u0447\u0435\u043a"
    ],
    "name:und_x_variant":[
        "Chernechik",
        "Chernechek"
    ],
    "wof:name":"Chernechek",
    "wof:placetype":"locality"
},
  "geometry": {"coordinates":[35.0116,52.6079],"type":"Point"}
}