{
  "type": "Feature",
  "properties": {
    "gn:admin1_code":"28",
    "gn:asciiname":"Ivanovskaya",
    "gn:country_code":"RU",
    "gn:dem":29,
    "gn:feature_class":"P",
    "gn:feature_code":"PPL",
    "gn:name":"Ivanovskaya",
    "gn:population":0,
    "gn:timezone":"Europe/Moscow",
    "iso:country":"RU",
    "name:fin_x_preferred":[
        "Iivanisto"
    ],
    "name:und_x_variant":[
        "\u0418\u0432\u0430\u043d\u043e\u0432\u0441\u043a\u0430\u044f"
    ],
    "wof:name":"Ivanovskaya",
    "wof:placetype":"locality"
},
  "geometry": {"coordinates":[34.23923,61.9072],"type":"Point"}
}