{
  "type": "Feature",
  "properties": {
    "gn:admin1_code":"88",
    "gn:asciiname":"Karpovskoye",
    "gn:country_code":"RU",
    "gn:dem":141,
    "gn:feature_class":"P",
    "gn:feature_code":"PPL",
    "gn:name":"Karpovskoye",
    "gn:population":0,
    "gn:timezone":"Europe/Moscow",
    "iso:country":"RU",
    "name:rus_x_preferred":[
        "\u041a\u0430\u0440\u043f\u043e\u0432\u0441\u043a\u043e\u0435"
    ],
    "wof:name":"Karpovskoye",
    "wof:placetype":"locality"
},
  "geometry": {"coordinates":[39.14152,57.85373000000001],"type":"Point"}
}