{
  "type": "Feature",
  "properties": {
    "gn:admin1_code":"63",
    "gn:asciiname":"Oros'-Ottokh",
    "gn:country_code":"RU",
    "gn:dem":191,
    "gn:feature_class":"P",
    "gn:feature_code":"PPL",
    "gn:name":"Oros\u2019-Ottokh",
    "gn:population":0,
    "gn:timezone":"Asia/Vladivostok",
    "iso:country":"RU",
    "name:rus_x_preferred":[
        "\u041e\u0440\u043e\u0441\u044c-\u041e\u0442\u0442\u043e\u0445"
    ],
    "name:und_x_variant":[
        "Oros\u2019-Ottakh",
        "Oros\u2019-Ottokh"
    ],
    "wof:name":"Oros'-Ottokh",
    "wof:placetype":"locality"
},
  "geometry": {"coordinates":[132.83611000000002,66.65083],"type":"Point"}
}