{
  "type": "Feature",
  "properties": {
    "gn:admin1_code":"54",
    "gn:asciiname":"Luk'yanovka",
    "gn:country_code":"RU",
    "gn:dem":115,
    "gn:feature_class":"P",
    "gn:feature_code":"PPL",
    "gn:name":"Luk\u2019yanovka",
    "gn:population":0,
    "gn:timezone":"Asia/Omsk",
    "iso:country":"RU",
    "name:eng_x_preferred":[
        "Luk'yanovka"
    ],
    "name:nor_x_preferred":[
        "Lukjanovka"
    ],
    "name:rus_x_preferred":[
        "\u041b\u0443\u043a\u044c\u044f\u043d\u043e\u0432\u043a\u0430"
    ],
    "name:und_x_variant":[
        "Luk\u2019yanovskoye",
        "Luk\u2019yanovka"
    ],
    "wof:name":"Luk'yanovka",
    "wof:placetype":"locality"
},
  "geometry": {"coordinates":[73.0591,54.3143],"type":"Point"}
}