{
  "type": "Feature",
  "properties": {
    "gn:admin1_code":"69",
    "gn:asciiname":"Koparikha",
    "gn:country_code":"RU",
    "gn:dem":232,
    "gn:feature_class":"P",
    "gn:feature_code":"PPL",
    "gn:name":"Koparikha",
    "gn:population":0,
    "gn:timezone":"Europe/Moscow",
    "iso:country":"RU",
    "name:rus_x_preferred":[
        "\u041a\u043e\u043f\u0430\u0440\u0438\u0445\u0430"
    ],
    "name:und_x_variant":[
        "\u041a\u043e\u043f\u0430\u0440\u0438\u0445\u0430",
        "Koporikha"
    ],
    "wof:name":"Koparikha",
    "wof:placetype":"locality"
},
  "geometry": {"coordinates":[34.22717,55.63335],"type":"Point"}
}