{
  "type": "Feature",
  "properties": {
    "gn:admin1_code":"51",
    "gn:asciiname":"Tol'skiy Maydan",
    "gn:country_code":"RU",
    "gn:dem":207,
    "gn:feature_class":"P",
    "gn:feature_code":"PPL",
    "gn:name":"Tol\u2019skiy Maydan",
    "gn:population":0,
    "gn:timezone":"Europe/Moscow",
    "iso:country":"RU",
    "name:eng_x_preferred":[
        "Tol'skiy Maydan"
    ],
    "name:nor_x_preferred":[
        "Tolskij Majdan"
    ],
    "name:rus_x_preferred":[
        "\u0422\u043e\u043b\u044c\u0441\u043a\u0438\u0439 \u041c\u0430\u0439\u0434\u0430\u043d"
    ],
    "name:und_x_variant":[
        "Tal\u2019skiy Maydan",
        "Tol\u2019skiy Maydan"
    ],
    "wof:name":"Tol'skiy Maydan",
    "wof:placetype":"locality"
},
  "geometry": {"coordinates":[44.65256,54.94896],"type":"Point"}
}