{
  "type": "Feature",
  "properties": {
    "gn:admin1_code":"33",
    "gn:asciiname":"Trifonyata",
    "gn:country_code":"RU",
    "gn:dem":158,
    "gn:feature_class":"P",
    "gn:feature_code":"PPL",
    "gn:name":"Trifonyata",
    "gn:population":0,
    "gn:timezone":"Europe/Kirov",
    "iso:country":"RU",
    "name:rus_x_preferred":[
        "\u0422\u0440\u0438\u0444\u043e\u043d\u044f\u0442\u0430"
    ],
    "wof:name":"Trifonyata",
    "wof:placetype":"locality"
},
  "geometry": {"coordinates":[49.3335,57.4047],"type":"Point"}
}