{
  "type": "Feature",
  "properties": {
    "gn:admin1_code":"8",
    "gn:asciiname":"Nizhniye Lemezy",
    "gn:country_code":"RU",
    "gn:dem":110,
    "gn:feature_class":"P",
    "gn:feature_code":"PPL",
    "gn:name":"Nizhniye Lemezy",
    "gn:population":0,
    "gn:timezone":"Asia/Yekaterinburg",
    "iso:country":"RU",
    "name:eng_x_preferred":[
        "Nizhnelemezy"
    ],
    "name:nor_x_preferred":[
        "Nizj.Lemezy"
    ],
    "name:rus_x_preferred":[
        "\u041d\u0438\u0436.\u041b\u0435\u043c\u0435\u0437\u044b"
    ],
    "name:rus_x_variant":[
        "\u041d\u0438\u0436\u043d\u0438\u0435 \u041b\u0435\u043c\u0435\u0437\u044b"
    ],
    "name:und_x_variant":[
        "Nizhnyaya Lemeza",
        "Nizhne-Lemeza",
        "Nizhniye Lemezy",
        "Nizhnelemezy",
        "\u041d\u0438\u0436\u043d\u0438\u0435 \u041b\u0435\u043c\u0435\u0437\u044b"
    ],
    "wof:name":"Nizhniye Lemezy",
    "wof:placetype":"locality"
},
  "geometry": {"coordinates":[56.99046,54.75406],"type":"Point"}
}