{
  "type": "Feature",
  "properties": {
    "gn:admin1_code":"8",
    "gn:asciiname":"Nizhniye Lemezy",
    "gn:country_code":"RU",
    "gn:dem":110,
    "gn:feature_class":"P",
    "gn:feature_code":"PPL",
    "gn:name":"Nizhniye Lemezy",
    "gn:population":0,
    "gn:timezone":"Asia/Yekaterinburg",
    "iso:country":"RU",
    "name:bak_x_preferred":[
        "\u0422\u04af\u0431\u04d9\u043d\u0433\u0435 \u041b\u04d9\u043c\u04d9\u0499"
    ],
    "name:che_x_preferred":[
        "\u041d\u0438\u0436\u043d\u0438 \u041b\u0435\u043c\u0435\u0437\u044b"
    ],
    "name:eng_x_preferred":[
        "Nizhnelemezy"
    ],
    "name:hye_x_preferred":[
        "\u0546\u056b\u056a\u0576\u056b\u0565 \u053c\u0565\u0574\u0565\u0566\u056b"
    ],
    "name:kaz_x_preferred":[
        "\u041d\u0438\u0436\u043d\u0438\u0435 \u041b\u0435\u043c\u0435\u0437\u044b"
    ],
    "name:kir_x_preferred":[
        "\u041d\u0438\u0436\u043d\u0438\u0435 \u041b\u0435\u043c\u0435\u0437\u044b"
    ],
    "name:nor_x_preferred":[
        "Nizj.Lemezy"
    ],
    "name:rus_x_preferred":[
        "\u041d\u0438\u0436.\u041b\u0435\u043c\u0435\u0437\u044b"
    ],
    "name:rus_x_variant":[
        "\u041d\u0438\u0436\u043d\u0438\u0435 \u041b\u0435\u043c\u0435\u0437\u044b"
    ],
    "name:tat_x_preferred":[
        "\u0422\u04af\u0431\u04d9\u043d\u0433\u0435 \u041b\u04d9\u043c\u04d9\u0437"
    ],
    "name:ukr_x_preferred":[
        "\u041d\u0438\u0436\u043d\u0456 \u041b\u0435\u043c\u0435\u0437\u0438"
    ],
    "name:und_x_variant":[
        "Nizhnyaya Lemeza",
        "Nizhne-Lemeza",
        "Nizhniye Lemezy",
        "Nizhnelemezy",
        "\u041d\u0438\u0436\u043d\u0438\u0435 \u041b\u0435\u043c\u0435\u0437\u044b"
    ],
    "wof:name":"Nizhniye Lemezy",
    "wof:placetype":"locality"
},
  "geometry": {"coordinates":[56.99046,54.75406],"type":"Point"}
}