{
  "type": "Feature",
  "properties": {
    "gn:admin1_code":"78",
    "gn:asciiname":"Kushluk",
    "gn:country_code":"RU",
    "gn:dem":132,
    "gn:feature_class":"P",
    "gn:feature_code":"PPL",
    "gn:name":"Kushluk",
    "gn:population":0,
    "gn:timezone":"Asia/Yekaterinburg",
    "iso:country":"RU",
    "name:eng_x_preferred":[
        "Kushluk"
    ],
    "name:nor_x_preferred":[
        "Kusjluk"
    ],
    "name:rus_x_preferred":[
        "\u041a\u0443\u0448\u043b\u0443\u043a"
    ],
    "wof:name":"Kushluk",
    "wof:placetype":"locality"
},
  "geometry": {"coordinates":[68.53361,55.54278000000001],"type":"Point"}
}