{
  "type": "Feature",
  "properties": {
    "gn:admin1_code":"77",
    "gn:asciiname":"Gushchino",
    "gn:country_code":"RU",
    "gn:dem":210,
    "gn:feature_class":"P",
    "gn:feature_code":"PPL",
    "gn:name":"Gushchino",
    "gn:population":0,
    "gn:timezone":"Europe/Moscow",
    "iso:country":"RU",
    "wof:name":"Gushchino",
    "wof:placetype":"locality"
},
  "geometry": {"coordinates":[34.68333,56.36666999999999],"type":"Point"}
}