{
  "type": "Feature",
  "properties": {
    "gn:admin1_code":"69",
    "gn:asciiname":"Ilovets",
    "gn:country_code":"RU",
    "gn:dem":205,
    "gn:feature_class":"P",
    "gn:feature_code":"PPL",
    "gn:name":"Ilovets",
    "gn:population":0,
    "gn:timezone":"Europe/Moscow",
    "iso:country":"RU",
    "name:rus_x_preferred":[
        "\u0418\u043b\u043e\u0432\u0435\u0446"
    ],
    "name:und_x_variant":[
        "\u0418\u043b\u043e\u0432\u0435\u0446"
    ],
    "wof:name":"Ilovets",
    "wof:placetype":"locality"
},
  "geometry": {"coordinates":[33.71005,54.3343],"type":"Point"}
}