{
  "type": "Feature",
  "properties": {
    "gn:admin1_code":"85",
    "gn:asciiname":"Starodvorskaya",
    "gn:country_code":"RU",
    "gn:dem":123,
    "gn:feature_class":"P",
    "gn:feature_code":"PPL",
    "gn:name":"Starodvorskaya",
    "gn:population":0,
    "gn:timezone":"Europe/Moscow",
    "iso:country":"RU",
    "name:rus_x_preferred":[
        "\u0421\u0442\u0430\u0440\u043e\u0434\u0432\u043e\u0440\u0441\u043a\u0430\u044f"
    ],
    "wof:name":"Starodvorskaya",
    "wof:placetype":"locality"
},
  "geometry": {"coordinates":[43.5149,60.417],"type":"Point"}
}