{
  "type": "Feature",
  "properties": {
    "gn:admin1_code":"67",
    "gn:asciiname":"Marinovka",
    "gn:country_code":"RU",
    "gn:dem":80,
    "gn:feature_class":"P",
    "gn:feature_code":"PPL",
    "gn:name":"Marinovka",
    "gn:population":0,
    "gn:timezone":"Europe/Saratov",
    "iso:country":"RU",
    "name:eng_x_preferred":[
        "Marinovka"
    ],
    "name:nor_x_preferred":[
        "Marinovka"
    ],
    "name:rus_x_preferred":[
        "\u041c\u0430\u0440\u0438\u043d\u043e\u0432\u043a\u0430"
    ],
    "name:und_x_variant":[
        "Mangeym",
        "Marinovka"
    ],
    "wof:name":"Marinovka",
    "wof:placetype":"locality"
},
  "geometry": {"coordinates":[47.56005,51.43931],"type":"Point"}
}