{
  "type": "Feature",
  "properties": {
    "gn:admin1_code":"60",
    "gn:asciiname":"Polonoye",
    "gn:country_code":"RU",
    "gn:dem":52,
    "gn:feature_class":"P",
    "gn:feature_code":"PPL",
    "gn:name":"Polonoye",
    "gn:population":0,
    "gn:timezone":"Europe/Moscow",
    "iso:country":"RU",
    "name:eng_x_preferred":[
        "Polonoye"
    ],
    "name:nor_x_preferred":[
        "Polonoje"
    ],
    "name:rus_x_preferred":[
        "\u041f\u043e\u043b\u043e\u043d\u043e\u0435"
    ],
    "wof:name":"Polonoye",
    "wof:placetype":"locality"
},
  "geometry": {"coordinates":[29.63199,57.78019000000001],"type":"Point"}
}