{
  "type": "Feature",
  "properties": {
    "gn:admin1_code":"8.0",
    "gn:asciiname":"Burgadzhino",
    "gn:country_code":"RU",
    "gn:dem":201,
    "gn:feature_class":"P",
    "gn:feature_code":"PPL",
    "gn:name":"Burgadzhino",
    "gn:population":0,
    "gn:timezone":"Asia/Yekaterinburg",
    "iso:country":"RU",
    "name:eng_x_preferred":[
        "Burgadzhino"
    ],
    "name:nor_x_preferred":[
        "Burgadzjino"
    ],
    "name:rus_x_preferred":[
        "\u0411\u0443\u0440\u0433\u0430\u0434\u0436\u0438\u043d\u043e"
    ],
    "name:und_x_variant":[
        "Bargadzhina",
        "Bargadzhino"
    ],
    "wof:name":"Burgadzhino",
    "wof:placetype":"locality"
},
  "geometry": {"coordinates":[57.91112,55.95611],"type":"Point"}
}