{
  "type": "Feature",
  "properties": {
    "gn:admin1_code":"93",
    "gn:asciiname":"Topolevka",
    "gn:country_code":"RU",
    "gn:dem":581,
    "gn:feature_class":"P",
    "gn:feature_code":"PPL",
    "gn:name":"Topol\u00ebvka",
    "gn:population":0,
    "gn:timezone":"Asia/Chita",
    "iso:country":"RU",
    "wof:name":"Topolevka",
    "wof:placetype":"locality"
},
  "geometry": {"coordinates":[115.6063,50.90405],"type":"Point"}
}