{
  "type": "Feature",
  "properties": {
    "gn:admin1_code":"77",
    "gn:asciiname":"Kulatino",
    "gn:country_code":"RU",
    "gn:dem":157,
    "gn:feature_class":"P",
    "gn:feature_code":"PPL",
    "gn:name":"Kulatino",
    "gn:population":0,
    "gn:timezone":"Europe/Moscow",
    "iso:country":"RU",
    "name:rus_x_preferred":[
        "\u041a\u0443\u043b\u0430\u0442\u0438\u043d\u043e"
    ],
    "name:und_x_variant":[
        "\u041a\u0443\u043b\u0430\u0442\u0438\u043d\u043e"
    ],
    "wof:name":"Kulatino",
    "wof:placetype":"locality"
},
  "geometry": {"coordinates":[37.3992,57.7116],"type":"Point"}
}