{
  "type": "Feature",
  "properties": {
    "gn:admin1_code":"41",
    "gn:asciiname":"Yakimov",
    "gn:country_code":"RU",
    "gn:dem":172,
    "gn:feature_class":"P",
    "gn:feature_code":"PPL",
    "gn:name":"Yakimov",
    "gn:population":0,
    "gn:timezone":"Europe/Moscow",
    "iso:country":"RU",
    "name:rus_x_preferred":[
        "\u042f\u043a\u0438\u043c\u043e\u0432"
    ],
    "wof:name":"Yakimov",
    "wof:placetype":"locality"
},
  "geometry": {"coordinates":[35.3373,51.83600000000001],"type":"Point"}
}