{
  "type": "Feature",
  "properties": {
    "gn:admin1_code":"47.0",
    "gn:asciiname":"Blaznovo",
    "gn:country_code":"RU",
    "gn:dem":190,
    "gn:feature_class":"P",
    "gn:feature_code":"PPL",
    "gn:name":"Blaznovo",
    "gn:population":0,
    "gn:timezone":"Europe/Moscow",
    "iso:country":"RU",
    "name:rus_x_preferred":[
        "\u0411\u043b\u0430\u0437\u043d\u043e\u0432\u043e"
    ],
    "wof:name":"Blaznovo",
    "wof:placetype":"locality"
},
  "geometry": {"coordinates":[35.93333,55.55],"type":"Point"}
}