{
  "type": "Feature",
  "properties": {
    "gn:admin1_code":"91.0",
    "gn:asciiname":"Ur'kinskiy",
    "gn:country_code":"RU",
    "gn:dem":236,
    "gn:feature_class":"P",
    "gn:feature_code":"PPL",
    "gn:name":"Ur\u2019kinskiy",
    "gn:population":0,
    "gn:timezone":"Asia/Krasnoyarsk",
    "iso:country":"RU",
    "name:rus_x_preferred":[
        "\u0423\u0440\u044c\u043a\u0438\u043d\u0441\u043a\u0438\u0439"
    ],
    "name:und_x_variant":[
        "Ur\u2019kinskiy"
    ],
    "wof:name":"Ur'kinskiy",
    "wof:placetype":"locality"
},
  "geometry": {"coordinates":[95.48269999999999,56.0589],"type":"Point"}
}