{
  "type": "Feature",
  "properties": {
    "gn:admin1_code":"73.0",
    "gn:asciiname":"Chemertsy",
    "gn:country_code":"RU",
    "gn:dem":92,
    "gn:feature_class":"P",
    "gn:feature_code":"PPL",
    "gn:name":"Chemertsy",
    "gn:population":0,
    "gn:timezone":"Europe/Moscow",
    "iso:country":"RU",
    "name:rus_x_preferred":[
        "\u0427\u0435\u043c\u0435\u0440\u0446\u044b"
    ],
    "name:und_x_variant":[
        "\u0427\u0435\u043c\u0435\u0440\u0446\u044b"
    ],
    "wof:name":"Chemertsy",
    "wof:placetype":"locality"
},
  "geometry": {"coordinates":[49.7063,56.05606],"type":"Point"}
}