{
  "type": "Feature",
  "properties": {
    "gn:admin1_code":"20",
    "gn:asciiname":"Utalay",
    "gn:country_code":"RU",
    "gn:dem":497,
    "gn:feature_class":"P",
    "gn:feature_code":"PPL",
    "gn:name":"Utalay",
    "gn:population":0,
    "gn:timezone":"Asia/Irkutsk",
    "iso:country":"RU",
    "name:eng_x_preferred":[
        "Utalay"
    ],
    "name:nor_x_preferred":[
        "Utalaj"
    ],
    "name:rus_x_preferred":[
        "\u0423\u0442\u0430\u043b\u0430\u0439"
    ],
    "wof:name":"Utalay",
    "wof:placetype":"locality"
},
  "geometry": {"coordinates":[100.90983,54.3385],"type":"Point"}
}