{
  "type": "Feature",
  "properties": {
    "gn:admin1_code":"43",
    "gn:asciiname":"Gudalovka",
    "gn:country_code":"RU",
    "gn:dem":196,
    "gn:feature_class":"P",
    "gn:feature_code":"PPL",
    "gn:name":"Gudalovka",
    "gn:population":0,
    "gn:timezone":"Europe/Moscow",
    "iso:country":"RU",
    "name:rus_x_preferred":[
        "\u0413\u0443\u0434\u0430\u043b\u043e\u0432\u043a\u0430"
    ],
    "wof:name":"Gudalovka",
    "wof:placetype":"locality"
},
  "geometry": {"coordinates":[38.58482,52.48846],"type":"Point"}
}