{
  "type": "Feature",
  "properties": {
    "gn:admin1_code":"69",
    "gn:asciiname":"Vertekhovo",
    "gn:country_code":"RU",
    "gn:dem":200,
    "gn:feature_class":"P",
    "gn:feature_code":"PPL",
    "gn:name":"Vertekhovo",
    "gn:population":0,
    "gn:timezone":"Europe/Moscow",
    "iso:country":"RU",
    "name:und_x_variant":[
        "Verterkhovo",
        "Vertekhovo"
    ],
    "wof:name":"Vertekhovo",
    "wof:placetype":"locality"
},
  "geometry": {"coordinates":[34.34139,54.68361],"type":"Point"}
}