{
  "type": "Feature",
  "properties": {
    "gn:admin1_code":"85.0",
    "gn:asciiname":"Bonchakovo",
    "gn:country_code":"RU",
    "gn:dem":168,
    "gn:feature_class":"P",
    "gn:feature_code":"PPL",
    "gn:name":"Bonchakovo",
    "gn:population":0,
    "gn:timezone":"Europe/Moscow",
    "iso:country":"RU",
    "name:rus_x_preferred":[
        "\u0411\u043e\u043d\u0447\u0430\u043a\u043e\u0432\u043e"
    ],
    "wof:name":"Bonchakovo",
    "wof:placetype":"locality"
},
  "geometry": {"coordinates":[40.50606,58.6065],"type":"Point"}
}