{
  "type": "Feature",
  "properties": {
    "gn:admin1_code":"51",
    "gn:asciiname":"Kostylikha",
    "gn:country_code":"RU",
    "gn:dem":172,
    "gn:feature_class":"P",
    "gn:feature_code":"PPL",
    "gn:name":"Kostylikha",
    "gn:population":0,
    "gn:timezone":"Europe/Moscow",
    "iso:country":"RU",
    "name:rus_x_preferred":[
        "\u041a\u043e\u0441\u0442\u044b\u043b\u0438\u0445\u0430"
    ],
    "name:und_x_variant":[
        "\u041a\u043e\u0441\u0442\u044b\u043b\u0438\u0445\u0430"
    ],
    "wof:name":"Kostylikha",
    "wof:placetype":"locality"
},
  "geometry": {"coordinates":[43.59418,55.49087],"type":"Point"}
}