{
  "type": "Feature",
  "properties": {
    "gn:admin1_code":"83",
    "gn:asciiname":"Noven'kaya",
    "gn:country_code":"RU",
    "gn:dem":118,
    "gn:feature_class":"P",
    "gn:feature_code":"PPL",
    "gn:name":"Noven\u2019kaya",
    "gn:population":0,
    "gn:timezone":"Europe/Moscow",
    "iso:country":"RU",
    "name:rus_x_preferred":[
        "\u041d\u043e\u0432\u0435\u043d\u044c\u043a\u0430\u044f"
    ],
    "name:und_x_variant":[
        "Novin\u2019koye",
        "Noven\u2019kaya",
        "\u041d\u043e\u0432\u0435\u043d\u044c\u043a\u0430\u044f"
    ],
    "wof:name":"Noven'kaya",
    "wof:placetype":"locality"
},
  "geometry": {"coordinates":[41.8916,55.409],"type":"Point"}
}