{
  "type": "Feature",
  "properties": {
    "gn:admin1_code":"78",
    "gn:asciiname":"Ikovskoye",
    "gn:country_code":"RU",
    "gn:dem":69,
    "gn:feature_class":"P",
    "gn:feature_code":"PPL",
    "gn:name":"Ikovskoye",
    "gn:population":0,
    "gn:timezone":"Asia/Yekaterinburg",
    "iso:country":"RU",
    "name:rus_x_preferred":[
        "\u0418\u043a\u043e\u0432\u0441\u043a\u043e\u0435"
    ],
    "name:und_x_variant":[
        "\u0418\u043a\u043e\u0432\u0441\u043a\u043e\u0435"
    ],
    "wof:name":"Ikovskoye",
    "wof:placetype":"locality"
},
  "geometry": {"coordinates":[70.3754,56.8134],"type":"Point"}
}