{
  "type": "Feature",
  "properties": {
    "gn:admin1_code":"62",
    "gn:asciiname":"Zheleznitsy",
    "gn:country_code":"RU",
    "gn:dem":176,
    "gn:feature_class":"P",
    "gn:feature_code":"PPL",
    "gn:name":"Zheleznitsy",
    "gn:population":0,
    "gn:timezone":"Europe/Moscow",
    "iso:country":"RU",
    "name:rus_x_preferred":[
        "\u0416\u0435\u043b\u0435\u0437\u043d\u0438\u0446\u044b"
    ],
    "wof:name":"Zheleznitsy",
    "wof:placetype":"locality"
},
  "geometry": {"coordinates":[38.85009,54.58633],"type":"Point"}
}