{
  "type": "Feature",
  "properties": {
    "gn:admin1_code":"31",
    "gn:asciiname":"Synnik",
    "gn:country_code":"RU",
    "gn:dem":642,
    "gn:feature_class":"P",
    "gn:feature_code":"PPL",
    "gn:name":"Synnik",
    "gn:population":0,
    "gn:timezone":"Asia/Krasnoyarsk",
    "iso:country":"RU",
    "name:eng_x_preferred":[
        "Synnik"
    ],
    "name:nor_x_preferred":[
        "Synnyg"
    ],
    "name:rus_x_preferred":[
        "\u0421\u044b\u043d\u043d\u044b\u0433"
    ],
    "wof:name":"Synnik",
    "wof:placetype":"locality"
},
  "geometry": {"coordinates":[89.53333000000001,54.16667],"type":"Point"}
}