{
  "type": "Feature",
  "properties": {
    "gn:admin1_code":"20",
    "gn:asciiname":"Tyumentsevo",
    "gn:country_code":"RU",
    "gn:dem":323,
    "gn:feature_class":"P",
    "gn:feature_code":"PPL",
    "gn:name":"Tyumentsevo",
    "gn:population":0,
    "gn:timezone":"Asia/Irkutsk",
    "iso:country":"RU",
    "name:ceb_x_preferred":[
        "Tyumentsevo"
    ],
    "name:che_x_preferred":[
        "\u0422\u044e\u043c\u0435\u043d\u0446\u0435\u0432\u043e"
    ],
    "name:deu_x_preferred":[
        "Tjumenzewo"
    ],
    "name:hye_x_preferred":[
        "\u054f\u0575\u0578\u0582\u0574\u0565\u0576\u0581\u0587\u0578"
    ],
    "name:ita_x_preferred":[
        "Tjumencevo"
    ],
    "name:rus_x_preferred":[
        "\u0422\u044e\u043c\u0435\u043d\u0446\u0435\u0432\u043e"
    ],
    "name:und_x_variant":[
        "Tyumentseva"
    ],
    "wof:name":"Tyumentsevo",
    "wof:placetype":"locality"
},
  "geometry": {"coordinates":[106.16667,56.36666999999999],"type":"Point"}
}