{
  "type": "Feature",
  "properties": {
    "gn:admin1_code":"51",
    "gn:asciiname":"Vorozhtsovo",
    "gn:country_code":"RU",
    "gn:dem":120,
    "gn:feature_class":"P",
    "gn:feature_code":"PPL",
    "gn:name":"Vorozhtsovo",
    "gn:population":0,
    "gn:timezone":"Europe/Moscow",
    "iso:country":"RU",
    "name:rus_x_preferred":[
        "\u0412\u043e\u0440\u043e\u0436\u0446\u043e\u0432\u043e"
    ],
    "wof:name":"Vorozhtsovo",
    "wof:placetype":"locality"
},
  "geometry": {"coordinates":[47.3907,57.7065],"type":"Point"}
}