{
  "type": "Feature",
  "properties": {
    "gn:admin1_code":"51",
    "gn:asciiname":"Igumnovo",
    "gn:country_code":"RU",
    "gn:dem":134,
    "gn:feature_class":"P",
    "gn:feature_code":"PPL",
    "gn:name":"Igumnovo",
    "gn:population":0,
    "gn:timezone":"Europe/Moscow",
    "iso:country":"RU",
    "name:rus_x_preferred":[
        "\u0418\u0433\u0443\u043c\u043d\u043e\u0432\u043e"
    ],
    "name:und_x_variant":[
        "Slobodka",
        "Igumnovo"
    ],
    "wof:name":"Igumnovo",
    "wof:placetype":"locality"
},
  "geometry": {"coordinates":[44.72886,55.94564],"type":"Point"}
}