{
  "type": "Feature",
  "properties": {
    "gn:admin1_code":"61",
    "gn:asciiname":"Novyy Mir",
    "gn:country_code":"RU",
    "gn:dem":112,
    "gn:feature_class":"P",
    "gn:feature_code":"PPL",
    "gn:name":"Novyy Mir",
    "gn:population":0,
    "gn:timezone":"Europe/Moscow",
    "iso:country":"RU",
    "name:rus_x_preferred":[
        "\u041d\u043e\u0432\u044b\u0439 \u041c\u0438\u0440"
    ],
    "wof:name":"Novyy Mir",
    "wof:placetype":"locality"
},
  "geometry": {"coordinates":[41.52083,48.3025],"type":"Point"}
}