{
  "type": "Feature",
  "properties": {
    "gn:admin1_code":"80",
    "gn:asciiname":"Kychen",
    "gn:country_code":"RU",
    "gn:dem":162,
    "gn:feature_class":"P",
    "gn:feature_code":"PPL",
    "gn:name":"Kychen",
    "gn:population":0,
    "gn:timezone":"Europe/Samara",
    "iso:country":"RU",
    "name:rus_x_preferred":[
        "\u041a\u044b\u0447\u0435\u043d"
    ],
    "name:und_x_variant":[
        "Kuchanovskaya",
        "Kychinovskaya",
        "Kychen"
    ],
    "wof:name":"Kychen",
    "wof:placetype":"locality"
},
  "geometry": {"coordinates":[52.1793,58.0585],"type":"Point"}
}