{
  "type": "Feature",
  "properties": {
    "gn:admin1_code":"42",
    "gn:asciiname":"Telzhevo",
    "gn:country_code":"RU",
    "gn:dem":17,
    "gn:feature_class":"P",
    "gn:feature_code":"PPL",
    "gn:name":"Telzhevo",
    "gn:population":0,
    "gn:timezone":"Europe/Moscow",
    "iso:country":"RU",
    "name:eng_x_preferred":[
        "Telzhevo"
    ],
    "name:nor_x_preferred":[
        "Telzjevo"
    ],
    "name:rus_x_preferred":[
        "\u0422\u0435\u043b\u0436\u0435\u0432\u043e"
    ],
    "wof:name":"Telzhevo",
    "wof:placetype":"locality"
},
  "geometry": {"coordinates":[32.76028,60.19511],"type":"Point"}
}