{
  "type": "Feature",
  "properties": {
    "gn:admin1_code":"8",
    "gn:asciiname":"Novosemenkino",
    "gn:country_code":"RU",
    "gn:dem":230,
    "gn:feature_class":"P",
    "gn:feature_code":"PPL",
    "gn:name":"Novosem\u00ebnkino",
    "gn:population":0,
    "gn:timezone":"Asia/Yekaterinburg",
    "iso:country":"RU",
    "name:bak_x_preferred":[
        "\u042f\u04a3\u044b \u0421\u0435\u043c\u0435\u043d\u043a\u0438\u043d"
    ],
    "name:che_x_preferred":[
        "\u041d\u043e\u0432\u043e\u0441\u0435\u043c\u0435\u043d\u043a\u0438\u043d\u043e"
    ],
    "name:chv_x_preferred":[
        "\u00c7\u0115\u043d\u0115 \u0421\u0438\u043c\u0435\u043d\u043a\u043a\u0435"
    ],
    "name:eng_x_preferred":[
        "Novosem\u00ebnkino"
    ],
    "name:hye_x_preferred":[
        "\u0546\u0578\u057e\u0578\u057d\u0565\u0574\u0565\u0576\u056f\u056b\u0576\u0578"
    ],
    "name:kaz_x_preferred":[
        "\u0416\u0430\u04a3\u0430 \u0441\u0435\u043c\u0435\u043d\u043a\u0438\u043d\u043e"
    ],
    "name:kir_x_preferred":[
        "\u0416\u0430\u04a3\u044b \u0441\u0435\u043c\u0435\u043d\u043a\u0438\u043d\u043e"
    ],
    "name:nor_x_preferred":[
        "Novosemenkino"
    ],
    "name:rus_x_preferred":[
        "\u041d\u043e\u0432\u043e\u0441\u0435\u043c\u0435\u043d\u043a\u0438\u043d\u043e"
    ],
    "name:rus_x_variant":[
        "\u041d\u043e\u0432\u043e\u0441\u0435\u043c\u0451\u043d\u043a\u0438\u043d\u043e"
    ],
    "name:tat_x_preferred":[
        "\u042f\u04a3\u0430 \u0421\u0438\u043c\u0435\u043d\u043a\u0435"
    ],
    "name:ukr_x_preferred":[
        "\u041d\u043e\u0432\u043e\u0441\u0435\u043c\u0435\u043d\u043a\u0456\u043d\u043e"
    ],
    "wof:name":"Novosemenkino",
    "wof:placetype":"locality"
},
  "geometry": {"coordinates":[54.31667,54.38333000000001],"type":"Point"}
}