{
  "type": "Feature",
  "properties": {
    "gn:admin1_code":"78",
    "gn:asciiname":"Polovinnoye",
    "gn:cc2":"RU",
    "gn:country_code":"RU",
    "gn:dem":135,
    "gn:feature_class":"P",
    "gn:feature_code":"PPL",
    "gn:name":"Polovinnoye",
    "gn:population":0,
    "gn:timezone":"Asia/Yekaterinburg",
    "iso:country":"RU",
    "name:rus_x_preferred":[
        "\u041f\u043e\u043b\u043e\u0432\u0438\u043d\u043d\u043e\u0435"
    ],
    "name:und_x_variant":[
        "Polovinnaya",
        "Polovinnoye"
    ],
    "wof:name":"Polovinnoye",
    "wof:placetype":"locality"
},
  "geometry": {"coordinates":[68.65694000000001,55.42806],"type":"Point"}
}