{
  "type": "Feature",
  "properties": {
    "gn:admin1_code":"42.0",
    "gn:asciiname":"Bol'shiye Polya",
    "gn:country_code":"RU",
    "gn:dem":35,
    "gn:feature_class":"P",
    "gn:feature_code":"PPL",
    "gn:name":"Bol\u2019shiye Polya",
    "gn:population":0,
    "gn:timezone":"Europe/Moscow",
    "iso:country":"RU",
    "name:rus_x_preferred":[
        "\u0411\u043e\u043b\u044c\u0448\u0438\u0435 \u041f\u043e\u043b\u044f"
    ],
    "name:und_x_variant":[
        "Bol\u2019shiye Polya"
    ],
    "wof:name":"Bol'shiye Polya",
    "wof:placetype":"locality"
},
  "geometry": {"coordinates":[28.0659,59.13333000000001],"type":"Point"}
}