{
  "type": "Feature",
  "properties": {
    "gn:admin1_code":"9.0",
    "gn:asciiname":"Degtyarnoye",
    "gn:country_code":"RU",
    "gn:dem":184,
    "gn:feature_class":"P",
    "gn:feature_code":"PPL",
    "gn:name":"Degtyarnoye",
    "gn:population":0,
    "gn:timezone":"Europe/Moscow",
    "iso:country":"RU",
    "name:eng_x_preferred":[
        "Degtyarnoye"
    ],
    "name:nor_x_preferred":[
        "Degtjarnoje"
    ],
    "name:rus_x_preferred":[
        "\u0414\u0435\u0433\u0442\u044f\u0440\u043d\u043e\u0435"
    ],
    "name:und_x_variant":[
        "Dekhtyarnoye",
        "Degtyarnaya"
    ],
    "wof:name":"Degtyarnoye",
    "wof:placetype":"locality"
},
  "geometry": {"coordinates":[38.6727,50.2742],"type":"Point"}
}