{
  "type": "Feature",
  "properties": {
    "gn:country":"RU",
    "gn:fcode":"PPL",
    "gn:population":0,
    "iso:country":"RU",
    "name:ceb_x_preferred":[
        "\u0160etka"
    ],
    "name:fra_x_preferred":[
        "\u0160etka"
    ],
    "name:msa_x_preferred":[
        "\u0160etka"
    ],
    "name:por_x_preferred":[
        "\u0160etka"
    ],
    "name:rus_x_preferred":[
        "\u0421\u0435\u0442\u043a\u0430"
    ],
    "name:slv_x_preferred":[
        "\u0160etka"
    ],
    "name:srp_x_preferred":[
        "\u0428\u0435\u0442\u043a\u0430"
    ],
    "qs:name":"Setka",
    "qs:name_adm0":"Russia",
    "qs:name_adm1":"Tula Oblast",
    "qs:photos_9r":0,
    "qs:photos_sr":0,
    "qs:placetype":"Town",
    "qs:pop_sr":"0",
    "wd:wordcount":69,
    "wof:name":"Setka",
    "wof:placetype":"locality",
    "wof:population":0
},
  "geometry": {"coordinates":[38.17556,54.66861],"type":"Point"}
}