{
  "type": "Feature",
  "properties": {
    "gn:country":"RU",
    "gn:fcode":"PPL",
    "gn:pop":0,
    "iso:country":"RU",
    "name:rus_x_preferred":[
        "\u041a\u0440\u0443\u0442\u043e\u0439 \u0412\u0435\u0440\u0445"
    ],
    "name:unk_x_variant":[
        "Krutaya"
    ],
    "qs:name":"Krutoy Verkh",
    "qs:name_adm0":"Russia",
    "qs:name_adm1":"Tula Oblast",
    "qs:photos_9r":0,
    "qs:photos_sr":0,
    "qs:placetype":"Town",
    "qs:pop_sr":"0",
    "wof:name":"Krutoy Verkh",
    "wof:placetype":"locality",
    "wof:population":0
},
  "geometry": {"coordinates":[38.0686,53.86528],"type":"Point"}
}