{
  "type": "Feature",
  "properties": {
    "gn:admin1_code":"16",
    "gn:asciiname":"Khozakasy",
    "gn:country_code":"RU",
    "gn:dem":83,
    "gn:feature_class":"P",
    "gn:feature_code":"PPL",
    "gn:name":"Khozakasy",
    "gn:population":0,
    "gn:timezone":"Europe/Moscow",
    "iso:country":"RU",
    "name:rus_x_preferred":[
        "\u0425\u043e\u0437\u0430\u043a\u0430\u0441\u044b"
    ],
    "name:und_x_variant":[
        "Khozy-Kasy",
        "Khozakasy",
        "\u0425\u043e\u0437\u0430\u043a\u0430\u0441\u044b"
    ],
    "wof:name":"Khozakasy",
    "wof:placetype":"locality"
},
  "geometry": {"coordinates":[47.23497,55.77206999999999],"type":"Point"}
}