{
  "type": "Feature",
  "properties": {
    "gn:admin1_code":"60",
    "gn:asciiname":"Il'mova Gora",
    "gn:country_code":"RU",
    "gn:dem":73,
    "gn:feature_class":"P",
    "gn:feature_code":"PPL",
    "gn:name":"Il\u2019mova Gora",
    "gn:population":0,
    "gn:timezone":"Europe/Moscow",
    "iso:country":"RU",
    "name:eng_x_preferred":[
        "Il'mova Gora"
    ],
    "name:nor_x_preferred":[
        "Ilmova Gora"
    ],
    "name:rus_x_preferred":[
        "\u0418\u043b\u044c\u043c\u043e\u0432\u0430 \u0413\u043e\u0440\u0430"
    ],
    "name:und_x_variant":[
        "Il\u2019mova Gora"
    ],
    "wof:name":"Il'mova Gora",
    "wof:placetype":"locality"
},
  "geometry": {"coordinates":[28.74663,56.85594],"type":"Point"}
}