{
  "type": "Feature",
  "properties": {
    "gn:admin1_code":"55",
    "gn:asciiname":"Kolpakskoye",
    "gn:country_code":"RU",
    "gn:dem":220,
    "gn:feature_class":"P",
    "gn:feature_code":"PPL",
    "gn:name":"Kolpakskoye",
    "gn:population":0,
    "gn:timezone":"Asia/Yekaterinburg",
    "iso:country":"RU",
    "name:eng_x_preferred":[
        "Kolpakskoye"
    ],
    "name:nor_x_preferred":[
        "Kolpakskoje"
    ],
    "name:rus_x_preferred":[
        "\u041a\u043e\u043b\u043f\u0430\u043a\u0441\u043a\u043e\u0435"
    ],
    "name:und_x_variant":[
        "Kalpak",
        "Kolpakski",
        "Kolpakskiy",
        "\u041a\u043e\u043b\u043f\u0430\u043a\u0441\u043a\u043e\u0435",
        "Kolpakskoye"
    ],
    "wof:name":"Kolpakskoye",
    "wof:placetype":"locality"
},
  "geometry": {"coordinates":[58.7273,51.4792],"type":"Point"}
}