{
  "type": "Feature",
  "properties": {
    "gn:admin1_code":"46.0",
    "gn:asciiname":"Tatarskoye Tenishevo",
    "gn:country_code":"RU",
    "gn:dem":162,
    "gn:feature_class":"P",
    "gn:feature_code":"PPL",
    "gn:name":"Tatarskoye Tenishevo",
    "gn:population":0,
    "gn:timezone":"Europe/Moscow",
    "iso:country":"RU",
    "wof:name":"Tatarskoye Tenishevo",
    "wof:placetype":"locality"
},
  "geometry": {"coordinates":[43.43897,54.23539],"type":"Point"}
}