{
  "type": "Feature",
  "properties": {
    "gn:admin1_code":"71",
    "gn:asciiname":"Mokhireva",
    "gn:country_code":"RU",
    "gn:dem":80,
    "gn:feature_class":"P",
    "gn:feature_code":"PPL",
    "gn:name":"Mokhireva",
    "gn:population":0,
    "gn:timezone":"Asia/Yekaterinburg",
    "iso:country":"RU",
    "name:eng_x_preferred":[
        "Mokhireva"
    ],
    "name:nor_x_preferred":[
        "Mokhireva"
    ],
    "name:rus_x_preferred":[
        "\u041c\u043e\u0445\u0438\u0440\u0435\u0432\u0430"
    ],
    "name:und_x_variant":[
        "\u041c\u043e\u0445\u0438\u0440\u0435\u0432\u0430",
        "Mokhireva"
    ],
    "wof:name":"Mokhireva",
    "wof:placetype":"locality"
},
  "geometry": {"coordinates":[64.02726,57.01339],"type":"Point"}
}