{
  "type": "Feature",
  "properties": {
    "gn:admin1_code":"9.0",
    "gn:asciiname":"Bol'shaya Gostenka",
    "gn:country_code":"RU",
    "gn:dem":156,
    "gn:feature_class":"P",
    "gn:feature_code":"PPL",
    "gn:name":"Bol\u2019shaya Gostenka",
    "gn:population":0,
    "gn:timezone":"Europe/Moscow",
    "iso:country":"RU",
    "name:rus_x_preferred":[
        "\u0411\u043e\u043b\u044c\u0448\u0430\u044f \u0413\u043e\u0441\u0442\u0435\u043d\u043a\u0430"
    ],
    "name:und_x_variant":[
        "Gostyanka",
        "Bol\u2019shaya Gostenka"
    ],
    "wof:name":"Bol'shaya Gostenka",
    "wof:placetype":"locality"
},
  "geometry": {"coordinates":[36.07919,50.53639],"type":"Point"}
}