{
  "type": "Feature",
  "properties": {
    "gn:admin1_code":"85",
    "gn:asciiname":"Lunevo",
    "gn:country_code":"RU",
    "gn:dem":146,
    "gn:feature_class":"P",
    "gn:feature_code":"PPL",
    "gn:name":"Lun\u00ebvo",
    "gn:population":0,
    "gn:timezone":"Europe/Moscow",
    "iso:country":"RU",
    "name:rus_x_preferred":[
        "\u041b\u0443\u043d\u0451\u0432\u043e"
    ],
    "name:und_x_variant":[
        "Lun\u00ebvo",
        "\u041b\u0443\u043d\u0451\u0432\u043e"
    ],
    "wof:name":"Lunevo",
    "wof:placetype":"locality"
},
  "geometry": {"coordinates":[36.2494,59.5659],"type":"Point"}
}