{
  "type": "Feature",
  "properties": {
    "gn:admin1_code":"38.0",
    "gn:asciiname":"Svoboda",
    "gn:country_code":"RU",
    "gn:dem":60,
    "gn:feature_class":"P",
    "gn:feature_code":"PPL",
    "gn:name":"Svoboda",
    "gn:population":0,
    "gn:timezone":"Europe/Moscow",
    "iso:country":"RU",
    "name:bel_x_preferred":[
        "\u0421\u0432\u0430\u0431\u043e\u0434\u0430"
    ],
    "name:bul_x_preferred":[
        "\u0421\u0432\u043e\u0431\u043e\u0434\u0430"
    ],
    "name:ceb_x_preferred":[
        "Svoboda"
    ],
    "name:ces_x_preferred":[
        "Svoboda"
    ],
    "name:deu_x_preferred":[
        "Svoboda"
    ],
    "name:epo_x_preferred":[
        "Svoboda"
    ],
    "name:fin_x_preferred":[
        "Svoboda"
    ],
    "name:fra_x_preferred":[
        "Svoboda"
    ],
    "name:hye_x_preferred":[
        "\u054d\u057e\u0578\u0562\u0578\u0564\u0561"
    ],
    "name:ita_x_preferred":[
        "Svoboda"
    ],
    "name:jpn_x_preferred":[
        "\u30b9\u30f4\u30a9\u30dc\u30c0"
    ],
    "name:kor_x_preferred":[
        "\uc2a4\ubcf4\ubcf4\ub2e4"
    ],
    "name:lit_x_preferred":[
        "Svoboda"
    ],
    "name:nld_x_preferred":[
        "Svoboda"
    ],
    "name:ron_x_preferred":[
        "Svoboda"
    ],
    "name:rus_x_preferred":[
        "\u0421\u0432\u043e\u0431\u043e\u0434\u0430"
    ],
    "name:slk_x_preferred":[
        "Svoboda"
    ],
    "name:slv_x_preferred":[
        "Svoboda"
    ],
    "name:spa_x_preferred":[
        "Svoboda"
    ],
    "name:swe_x_preferred":[
        "Svoboda"
    ],
    "name:tur_x_preferred":[
        "Svoboda"
    ],
    "name:ukr_x_preferred":[
        "\u0421\u0432\u043e\u0431\u043e\u0434\u0430"
    ],
    "wof:name":"Svoboda",
    "wof:placetype":"locality"
},
  "geometry": {"coordinates":[37.8996,44.95447],"type":"Point"}
}