{
  "type": "Feature",
  "properties": {
    "gn:country":"RU",
    "gn:fcode":"PPLX",
    "gn:pop":1500,
    "iso:country":"RU",
    "name:eng_x_preferred":[
        "Otradnoye"
    ],
    "name:rus_x_preferred":[
        "\u041e\u0442\u0440\u0430\u0434\u043d\u043e\u0435"
    ],
    "name:unk_x_variant":[
        "\u041e\u0442\u0440\u0430\u0434\u043d\u043e\u0435"
    ],
    "qs:name":"Otradnoye",
    "qs:photos_9r":0,
    "qs:photos_sr":0,
    "qs:pop_sr":"3",
    "wd:wordcount":62,
    "wof:name":"Otradnoye",
    "wof:placetype":"neighbourhood",
    "wof:population":1500
},
  "geometry": {"coordinates":[20.11396,54.94114],"type":"Point"}
}