{
  "type": "Feature",
  "properties": {
    "gn:admin1_code":"10",
    "gn:asciiname":"Khmelevka",
    "gn:country_code":"RU",
    "gn:dem":150,
    "gn:feature_class":"P",
    "gn:feature_code":"PPL",
    "gn:name":"Khmel\u00ebvka",
    "gn:population":0,
    "gn:timezone":"Europe/Moscow",
    "iso:country":"RU",
    "name:rus_x_preferred":[
        "\u0425\u043c\u0435\u043b\u0451\u0432\u043a\u0430"
    ],
    "name:rus_x_variant":[
        "Khmel\u00ebvka"
    ],
    "name:und_x_variant":[
        "Khmel\u00ebvka",
        "\u0425\u043c\u0435\u043b\u0451\u0432\u043a\u0430"
    ],
    "wof:name":"Khmelevka",
    "wof:placetype":"locality"
},
  "geometry": {"coordinates":[32.93257,52.52916],"type":"Point"}
}