{
  "type": "Feature",
  "properties": {
    "gn:admin1_code":"73",
    "gn:asciiname":"Berdibyakovo",
    "gn:country_code":"RU",
    "gn:dem":91,
    "gn:feature_class":"P",
    "gn:feature_code":"PPL",
    "gn:name":"Berdibyakovo",
    "gn:population":0,
    "gn:timezone":"Europe/Moscow",
    "iso:country":"RU",
    "name:nor_x_preferred":[
        "Berdibjakovo"
    ],
    "name:rus_x_preferred":[
        "\u0411\u0435\u0440\u0434\u0438\u0431\u044f\u043a\u043e\u0432\u043e"
    ],
    "name:und_x_variant":[
        "Berdebyakovo",
        "Berdibyakovo"
    ],
    "wof:name":"Berdibyakovo",
    "wof:placetype":"locality"
},
  "geometry": {"coordinates":[50.59167,55.65545],"type":"Point"}
}