{
  "type": "Feature",
  "properties": {
    "gn:admin1_code":"51",
    "gn:asciiname":"Kolosikha",
    "gn:country_code":"RU",
    "gn:dem":161,
    "gn:feature_class":"P",
    "gn:feature_code":"PPL",
    "gn:name":"Kolosikha",
    "gn:population":0,
    "gn:timezone":"Europe/Moscow",
    "iso:country":"RU",
    "name:rus_x_preferred":[
        "\u041a\u043e\u043b\u043e\u0441\u0438\u0445\u0430"
    ],
    "wof:name":"Kolosikha",
    "wof:placetype":"locality"
},
  "geometry": {"coordinates":[45.8528,57.9606],"type":"Point"}
}