{
  "type": "Feature",
  "properties": {
    "gn:admin1_code":"28",
    "gn:asciiname":"Lakhdenkyulya",
    "gn:country_code":"RU",
    "gn:dem":27,
    "gn:feature_class":"P",
    "gn:feature_code":"PPL",
    "gn:name":"Lakhdenkyulya",
    "gn:population":0,
    "gn:timezone":"Europe/Moscow",
    "iso:country":"RU",
    "name:fin_x_preferred":[
        "Lahdenkyl\u00e4"
    ],
    "name:rus_x_preferred":[
        "\u041b\u0430\u0445\u0434\u0435\u043d\u043a\u044e\u043b\u044f"
    ],
    "name:und_x_variant":[
        "\u041b\u0430\u0445\u0434\u0435\u043d\u043a\u044e\u043b\u044f"
    ],
    "wof:name":"Lakhdenkyulya",
    "wof:placetype":"locality"
},
  "geometry": {"coordinates":[30.7382,61.74193],"type":"Point"}
}