{
  "type": "Feature",
  "properties": {
    "gn:country":"RU",
    "gn:fcode":"PPL",
    "gn:pop":6799,
    "iso:country":"RU",
    "name:che_x_preferred":[
        "\u041a\u0440\u0430\u0442\u043e\u0432\u043e"
    ],
    "name:eng_x_preferred":[
        "Kratovo"
    ],
    "name:heb_x_preferred":[
        "\u05e7\u05e8\u05d0\u05d8\u05d5\u05d1\u05d5"
    ],
    "name:hye_x_preferred":[
        "\u053f\u0580\u0561\u057f\u0578\u057e\u0578"
    ],
    "name:ita_x_preferred":[
        "Kratovo"
    ],
    "name:lit_x_preferred":[
        "Kratovas"
    ],
    "name:nld_x_preferred":[
        "Kratovo"
    ],
    "name:nno_x_preferred":[
        "Kratovo"
    ],
    "name:nob_x_preferred":[
        "Kratovo"
    ],
    "name:nor_x_preferred":[
        "Kratovo"
    ],
    "name:rus_x_preferred":[
        "\u041a\u0440\u0430\u0442\u043e\u0432\u043e"
    ],
    "name:unk_x_variant":[
        "\u041a\u0440\u0430\u0442\u043e\u0432\u043e"
    ],
    "name:zho_x_preferred":[
        "\u514b\u62c9\u6258\u6c83"
    ],
    "qs:name":"Kratovo",
    "qs:name_adm0":"Russia",
    "qs:name_adm1":"Moscow Oblast",
    "qs:photos":669,
    "qs:photos_1k":136,
    "qs:photos_9k":3,
    "qs:photos_9r":5,
    "qs:photos_all":669,
    "qs:photos_sr":8,
    "qs:placetype":"Town",
    "qs:pop_sr":"5",
    "wd:wordcount":42,
    "wof:name":"Kratovo",
    "wof:placetype":"locality",
    "wof:population":6799
},
  "geometry": {"coordinates":[38.17743,55.59728],"type":"Point"}
}