{
  "type": "Feature",
  "properties": {
    "gn:admin1_code":"92",
    "gn:asciiname":"Kombinat Imeni Mikoyana Nomer Pervyy",
    "gn:cc2":"RU",
    "gn:country_code":"RU",
    "gn:dem":-9999,
    "gn:feature_class":"P",
    "gn:feature_code":"PPL",
    "gn:name":"Kombinat Imeni Mikoyana Nomer Pervyy",
    "gn:population":0,
    "gn:timezone":"Asia/Kamchatka",
    "iso:country":"RU",
    "name:rus_x_preferred":[
        "\u041a\u043e\u043c\u0431\u0438\u043d\u0430\u0442 \u0418\u043c\u0435\u043d\u0438 \u041c\u0438\u043a\u043e\u044f\u043d\u0430 \u041d\u043e\u043c\u0435\u0440 \u041f\u0435\u0440\u0432\u044b\u0439"
    ],
    "name:und_x_variant":[
        "Mikoyana",
        "Kombinat Imeni Mikoyana Nomer Pervyy"
    ],
    "wof:name":"Kombinat Imeni Mikoyana Nomer Pervyy",
    "wof:placetype":"locality"
},
  "geometry": {"coordinates":[156.13333,52.88333000000001],"type":"Point"}
}