{
  "type": "Feature",
  "properties": {
    "gn:admin1_code":"10",
    "gn:asciiname":"Lubnysh",
    "gn:country_code":"RU",
    "gn:dem":190,
    "gn:feature_class":"P",
    "gn:feature_code":"PPL",
    "gn:name":"Lubnysh",
    "gn:population":0,
    "gn:timezone":"Europe/Moscow",
    "iso:country":"RU",
    "name:rus_x_preferred":[
        "\u041b\u0443\u0431\u043d\u044b\u0448"
    ],
    "wof:name":"Lubnysh",
    "wof:placetype":"locality"
},
  "geometry": {"coordinates":[34.3567,52.3433],"type":"Point"}
}