{
  "type": "Feature",
  "properties": {
    "gn:admin1_code":"33",
    "gn:asciiname":"Kotel'noye",
    "gn:country_code":"RU",
    "gn:dem":191,
    "gn:feature_class":"P",
    "gn:feature_code":"PPL",
    "gn:name":"Kotel\u2019noye",
    "gn:population":0,
    "gn:timezone":"Europe/Kirov",
    "iso:country":"RU",
    "name:rus_x_preferred":[
        "\u041a\u043e\u0442\u0435\u043b\u044c\u043d\u043e\u0435"
    ],
    "name:und_x_variant":[
        "Kotel\u2019noye",
        "\u041a\u043e\u0442\u0435\u043b\u044c\u043d\u043e\u0435"
    ],
    "wof:name":"Kotel'noye",
    "wof:placetype":"locality"
},
  "geometry": {"coordinates":[49.2023,58.14824],"type":"Point"}
}