{
  "type": "Feature",
  "properties": {
    "gn:admin1_code":"4",
    "gn:asciiname":"Nizhnyaya Suyetka",
    "gn:country_code":"RU",
    "gn:dem":111,
    "gn:feature_class":"P",
    "gn:feature_code":"PPL",
    "gn:name":"Nizhnyaya Suyetka",
    "gn:population":0,
    "gn:timezone":"Asia/Barnaul",
    "iso:country":"RU",
    "name:eng_x_preferred":[
        "Nizhnyaya Suyetka"
    ],
    "name:nor_x_preferred":[
        "Nizj.Sujetka"
    ],
    "name:rus_x_preferred":[
        "\u041d\u0438\u0436.\u0421\u0443\u0435\u0442\u043a\u0430"
    ],
    "name:rus_x_variant":[
        "\u041d\u0438\u0436\u043d\u044f\u044f \u0421\u0443\u0435\u0442\u043a\u0430"
    ],
    "name:und_x_variant":[
        "Nizhne-Suyetka"
    ],
    "wof:name":"Nizhnyaya Suyetka",
    "wof:placetype":"locality"
},
  "geometry": {"coordinates":[79.89660000000001,53.2216],"type":"Point"}
}