{
  "type": "Feature",
  "properties": {
    "gn:admin1_code":"69",
    "gn:asciiname":"Khoronevo",
    "gn:country_code":"RU",
    "gn:dem":186,
    "gn:feature_class":"P",
    "gn:feature_code":"PPL",
    "gn:name":"Khoronevo",
    "gn:population":0,
    "gn:timezone":"Europe/Moscow",
    "iso:country":"RU",
    "name:rus_x_preferred":[
        "\u0425\u043e\u0440\u043e\u043d\u0435\u0432\u043e"
    ],
    "wof:name":"Khoronevo",
    "wof:placetype":"locality"
},
  "geometry": {"coordinates":[32.2384,53.89467],"type":"Point"}
}