{
  "type": "Feature",
  "properties": {
    "gn:admin1_code":"77",
    "gn:asciiname":"Savinskoye",
    "gn:country_code":"RU",
    "gn:dem":157,
    "gn:feature_class":"P",
    "gn:feature_code":"PPL",
    "gn:name":"Savinskoye",
    "gn:population":0,
    "gn:timezone":"Europe/Moscow",
    "iso:country":"RU",
    "name:nor_x_preferred":[
        "Savinskoje"
    ],
    "name:rus_x_preferred":[
        "\u0421\u0430\u0432\u0438\u043d\u0441\u043a\u043e\u0435"
    ],
    "wof:name":"Savinskoye",
    "wof:placetype":"locality"
},
  "geometry": {"coordinates":[35.16158,56.96623],"type":"Point"}
}