{
  "type": "Feature",
  "properties": {
    "gn:admin1_code":"84",
    "gn:asciiname":"Korolev",
    "gn:country_code":"RU",
    "gn:dem":92,
    "gn:feature_class":"P",
    "gn:feature_code":"PPL",
    "gn:name":"Korol\u00ebv",
    "gn:population":0,
    "gn:timezone":"Europe/Volgograd",
    "iso:country":"RU",
    "name:rus_x_preferred":[
        "\u041a\u043e\u0440\u043e\u043b\u0451\u0432"
    ],
    "name:und_x_variant":[
        "Korol\u00ebv"
    ],
    "wof:name":"Korolev",
    "wof:placetype":"locality"
},
  "geometry": {"coordinates":[42.58333,50.41667],"type":"Point"}
}