{
  "type": "Feature",
  "properties": {
    "gn:admin1_code":"33.0",
    "gn:asciiname":"Sandalovy",
    "gn:country_code":"RU",
    "gn:dem":162,
    "gn:feature_class":"P",
    "gn:feature_code":"PPL",
    "gn:name":"Sandalovy",
    "gn:population":0,
    "gn:timezone":"Europe/Kirov",
    "iso:country":"RU",
    "name:rus_x_preferred":[
        "\u0421\u0430\u043d\u0434\u0430\u043b\u043e\u0432\u044b"
    ],
    "name:und_x_variant":[
        "\u0421\u0430\u043d\u0434\u0430\u043b\u043e\u0432\u044b"
    ],
    "wof:name":"Sandalovy",
    "wof:placetype":"locality"
},
  "geometry": {"coordinates":[49.68749,58.41951],"type":"Point"}
}