{
  "type": "Feature",
  "properties": {
    "gn:admin1_code":"70",
    "gn:asciiname":"Vinogradnoye",
    "gn:cc2":"RU",
    "gn:country_code":"RU",
    "gn:dem":145,
    "gn:feature_class":"P",
    "gn:feature_code":"PPL",
    "gn:name":"Vinogradnoye",
    "gn:population":0,
    "gn:timezone":"Europe/Moscow",
    "iso:country":"RU",
    "name:eng_x_preferred":[
        "Vinogradnoye"
    ],
    "name:nor_x_preferred":[
        "Bogdanovka"
    ],
    "name:rus_x_preferred":[
        "\u0411\u043e\u0433\u0434\u0430\u043d\u043e\u0432\u043a\u0430"
    ],
    "name:und_x_variant":[
        "Engel\u2019s"
    ],
    "wof:name":"Vinogradnoye",
    "wof:placetype":"locality"
},
  "geometry": {"coordinates":[44.66778,44.13306],"type":"Point"}
}