{
  "type": "Feature",
  "properties": {
    "gn:admin1_code":"85",
    "gn:asciiname":"Oreshnik",
    "gn:country_code":"RU",
    "gn:dem":152,
    "gn:feature_class":"P",
    "gn:feature_code":"PPL",
    "gn:name":"Oreshnik",
    "gn:population":0,
    "gn:timezone":"Europe/Moscow",
    "iso:country":"RU",
    "name:bul_x_preferred":[
        "\u041e\u0440\u0435\u0448\u043d\u0438\u043a"
    ],
    "name:ceb_x_preferred":[
        "Oreshnik"
    ],
    "name:fas_x_preferred":[
        "\u0627\u0648\u0631\u0634\u0646\u06cc\u06a9"
    ],
    "name:pol_x_preferred":[
        "Oresznik"
    ],
    "name:ron_x_preferred":[
        "Ore\u0219nik"
    ],
    "name:rus_x_preferred":[
        "\u041e\u0440\u0435\u0448\u043d\u0438\u043a"
    ],
    "name:swe_x_preferred":[
        "Oresjnik"
    ],
    "name:ukr_x_preferred":[
        "\u041e\u0440\u0435\u0448\u043d\u0438\u043a"
    ],
    "wof:name":"Oreshnik",
    "wof:placetype":"locality"
},
  "geometry": {"coordinates":[38.9931,59.42100000000001],"type":"Point"}
}