{
  "type": "Feature",
  "properties": {
    "gn:admin1_code":"40",
    "gn:asciiname":"Zaural'ye",
    "gn:country_code":"RU",
    "gn:dem":137,
    "gn:feature_class":"P",
    "gn:feature_code":"PPL",
    "gn:name":"Zaural\u2019ye",
    "gn:population":0,
    "gn:timezone":"Asia/Yekaterinburg",
    "iso:country":"RU",
    "wof:name":"Zaural'ye",
    "wof:placetype":"locality"
},
  "geometry": {"coordinates":[66.06681,55.79297],"type":"Point"}
}