{
  "type": "Feature",
  "properties": {
    "gn:admin1_code":"4",
    "gn:asciiname":"Ozerki",
    "gn:country_code":"RU",
    "gn:dem":173,
    "gn:feature_class":"P",
    "gn:feature_code":"PPL",
    "gn:name":"Ozerki",
    "gn:population":0,
    "gn:timezone":"Asia/Barnaul",
    "iso:country":"RU",
    "name:eng_x_preferred":[
        "Ozerki"
    ],
    "name:nor_x_preferred":[
        "Ozerki"
    ],
    "name:rus_x_preferred":[
        "\u041e\u0437\u0435\u0440\u043a\u0438"
    ],
    "name:und_x_variant":[
        "\u041e\u0437\u0435\u0440\u043a\u0438",
        "Ozerki",
        "Stantsiya Ozerki"
    ],
    "wof:name":"Ozerki",
    "wof:placetype":"locality"
},
  "geometry": {"coordinates":[83.6927,53.6658],"type":"Point"}
}