{
  "type": "Feature",
  "properties": {
    "gn:admin1_code":"33.0",
    "gn:asciiname":"Otyatskoye",
    "gn:country_code":"RU",
    "gn:dem":189,
    "gn:feature_class":"P",
    "gn:feature_code":"PPL",
    "gn:name":"Otyatskoye",
    "gn:population":0,
    "gn:timezone":"Europe/Kirov",
    "iso:country":"RU",
    "name:rus_x_preferred":[
        "\u041e\u0442\u044f\u0446\u043a\u043e\u0435"
    ],
    "wof:name":"Otyatskoye",
    "wof:placetype":"locality"
},
  "geometry": {"coordinates":[50.09868,58.49726],"type":"Point"}
}