{
  "type": "Feature",
  "properties": {
    "gn:admin1_code":"43",
    "gn:asciiname":"Pestovka",
    "gn:country_code":"RU",
    "gn:dem":157,
    "gn:feature_class":"P",
    "gn:feature_code":"PPL",
    "gn:name":"Pestovka",
    "gn:population":0,
    "gn:timezone":"Europe/Moscow",
    "iso:country":"RU",
    "name:rus_x_preferred":[
        "\u041f\u0435\u0441\u0442\u043e\u0432\u043a\u0430"
    ],
    "wof:name":"Pestovka",
    "wof:placetype":"locality"
},
  "geometry": {"coordinates":[38.71667,52.38333],"type":"Point"}
}