{
  "type": "Feature",
  "properties": {
    "gn:admin1_code":"34",
    "gn:asciiname":"Nivshera",
    "gn:country_code":"RU",
    "gn:dem":105,
    "gn:feature_class":"P",
    "gn:feature_code":"PPL",
    "gn:name":"Nivshera",
    "gn:population":0,
    "gn:timezone":"Europe/Moscow",
    "iso:country":"RU",
    "name:eng_x_preferred":[
        "Nivshera"
    ],
    "name:nor_x_preferred":[
        "Nivsjera"
    ],
    "name:rus_x_preferred":[
        "\u041d\u0438\u0432\u0448\u0435\u0440\u0430"
    ],
    "name:und_x_variant":[
        "\u041d\u0438\u0432\u0448\u0435\u0440\u0430",
        "Nivshera"
    ],
    "wof:name":"Nivshera",
    "wof:placetype":"locality"
},
  "geometry": {"coordinates":[52.91745,62.3571],"type":"Point"}
}