{
  "type": "Feature",
  "properties": {
    "gn:admin1_code":"63",
    "gn:asciiname":"Arylakh",
    "gn:country_code":"RU",
    "gn:dem":214,
    "gn:feature_class":"P",
    "gn:feature_code":"PPL",
    "gn:name":"Arylakh",
    "gn:population":0,
    "gn:timezone":"Asia/Vladivostok",
    "iso:country":"RU",
    "name:eng_x_preferred":[
        "Arylakh"
    ],
    "name:nor_x_preferred":[
        "Arylakh"
    ],
    "name:rus_x_preferred":[
        "\u0410\u0440\u044b\u043b\u0430\u0445"
    ],
    "name:und_x_variant":[
        "Dryllakh"
    ],
    "wof:name":"Arylakh",
    "wof:placetype":"locality"
},
  "geometry": {"coordinates":[133.74182999999999,60.15221999999999],"type":"Point"}
}