{
  "type": "Feature",
  "properties": {
    "gn:admin1_code":"37",
    "gn:asciiname":"Irdom",
    "gn:country_code":"RU",
    "gn:dem":138,
    "gn:feature_class":"P",
    "gn:feature_code":"PPL",
    "gn:name":"Irdom",
    "gn:population":0,
    "gn:timezone":"Europe/Moscow",
    "iso:country":"RU",
    "name:rus_x_preferred":[
        "\u0418\u0440\u0434\u043e\u043c"
    ],
    "name:und_x_variant":[
        "Grobovka",
        "Irdom"
    ],
    "wof:name":"Irdom",
    "wof:placetype":"locality"
},
  "geometry": {"coordinates":[46.96115,58.96018],"type":"Point"}
}