{
  "type": "Feature",
  "properties": {
    "gn:admin1_code":"25",
    "gn:asciiname":"Starki",
    "gn:country_code":"RU",
    "gn:dem":143,
    "gn:feature_class":"P",
    "gn:feature_code":"PPL",
    "gn:name":"Starki",
    "gn:population":0,
    "gn:timezone":"Europe/Moscow",
    "iso:country":"RU",
    "name:nor_x_preferred":[
        "Starki"
    ],
    "name:pol_x_preferred":[
        "Starki"
    ],
    "name:rus_x_preferred":[
        "\u0421\u0442\u0430\u0440\u043a\u0438"
    ],
    "name:vie_x_preferred":[
        "Starki"
    ],
    "wof:name":"Starki",
    "wof:placetype":"locality"
},
  "geometry": {"coordinates":[35.99934000000001,54.74491999999999],"type":"Point"}
}