{
  "type": "Feature",
  "properties": {
    "gn:admin1_code":"61",
    "gn:asciiname":"Sovetskiy Dar",
    "gn:cc2":"RU",
    "gn:country_code":"RU",
    "gn:dem":16,
    "gn:feature_class":"P",
    "gn:feature_code":"PPL",
    "gn:name":"Sovetskiy Dar",
    "gn:population":0,
    "gn:timezone":"Europe/Moscow",
    "iso:country":"RU",
    "name:rus_x_preferred":[
        "\u0421\u043e\u0432\u0435\u0442\u0441\u043a\u0438\u0439 \u0414\u0430\u0440"
    ],
    "name:und_x_variant":[
        "Sovdar",
        "Sovetskiy Dar"
    ],
    "wof:name":"Sovetskiy Dar",
    "wof:placetype":"locality"
},
  "geometry": {"coordinates":[39.15667,46.62278],"type":"Point"}
}