{
  "type": "Feature",
  "properties": {
    "gn:admin1_code":"53",
    "gn:asciiname":"Blagodatnoye",
    "gn:country_code":"RU",
    "gn:dem":113,
    "gn:feature_class":"P",
    "gn:feature_code":"PPL",
    "gn:name":"Blagodatnoye",
    "gn:population":0,
    "gn:timezone":"Asia/Novosibirsk",
    "iso:country":"RU",
    "name:eng_x_preferred":[
        "Blagodatnoye"
    ],
    "name:nor_x_preferred":[
        "Blagodatnoje"
    ],
    "name:rus_x_preferred":[
        "\u0411\u043b\u0430\u0433\u043e\u0434\u0430\u0442\u043d\u043e\u0435"
    ],
    "name:und_x_variant":[
        "Blagodatoya"
    ],
    "wof:name":"Blagodatnoye",
    "wof:placetype":"locality"
},
  "geometry": {"coordinates":[78.05417,53.84512],"type":"Point"}
}