{
  "type": "Feature",
  "properties": {
    "gn:admin1_code":"33",
    "gn:asciiname":"Kuzhenerka",
    "gn:country_code":"RU",
    "gn:dem":119,
    "gn:feature_class":"P",
    "gn:feature_code":"PPL",
    "gn:name":"Kuzhenerka",
    "gn:population":0,
    "gn:timezone":"Europe/Kirov",
    "iso:country":"RU",
    "name:rus_x_preferred":[
        "\u041a\u0443\u0436\u0435\u043d\u0435\u0440\u043a\u0430"
    ],
    "name:und_x_variant":[
        "Kuzhinerka",
        "Kuzhenerka"
    ],
    "wof:name":"Kuzhenerka",
    "wof:placetype":"locality"
},
  "geometry": {"coordinates":[50.49219,56.7152],"type":"Point"}
}