{
  "type": "Feature",
  "properties": {
    "gn:admin1_code":"91",
    "gn:asciiname":"Kirbey",
    "gn:cc2":"RU",
    "gn:country_code":"RU",
    "gn:dem":263,
    "gn:feature_class":"P",
    "gn:feature_code":"PPL",
    "gn:name":"Kirbey",
    "gn:population":0,
    "gn:timezone":"Asia/Krasnoyarsk",
    "iso:country":"RU",
    "name:rus_x_preferred":[
        "\u041a\u0438\u0440\u0431\u0435\u0439"
    ],
    "name:und_x_variant":[
        "Faktoriya Kirbey",
        "Kirbey"
    ],
    "wof:name":"Kirbey",
    "wof:placetype":"locality"
},
  "geometry": {"coordinates":[104.46666999999999,69.09999999999999],"type":"Point"}
}