{
  "type": "Feature",
  "properties": {
    "gn:admin1_code":"20.0",
    "gn:asciiname":"Nevel'skaya",
    "gn:country_code":"RU",
    "gn:dem":259,
    "gn:feature_class":"P",
    "gn:feature_code":"PPL",
    "gn:name":"Nevel\u2019skaya",
    "gn:population":0,
    "gn:timezone":"Asia/Irkutsk",
    "iso:country":"RU",
    "name:rus_x_preferred":[
        "\u041d\u0435\u0432\u0435\u043b\u044c\u0441\u043a\u0430\u044f"
    ],
    "name:und_x_variant":[
        "Nevel\u2019skaya"
    ],
    "wof:name":"Nevel'skaya",
    "wof:placetype":"locality"
},
  "geometry": {"coordinates":[98.5381,56.1201],"type":"Point"}
}