{
  "type": "Feature",
  "properties": {
    "gn:admin1_code":"90",
    "gn:asciiname":"Nizhnyaya Yershovka",
    "gn:country_code":"RU",
    "gn:dem":121,
    "gn:feature_class":"P",
    "gn:feature_code":"PPL",
    "gn:name":"Nizhnyaya Yershovka",
    "gn:population":0,
    "gn:timezone":"Asia/Yekaterinburg",
    "iso:country":"RU",
    "name:nor_x_preferred":[
        "Nizjnjaja Jersjovka"
    ],
    "name:rus_x_preferred":[
        "\u041d\u0438\u0436\u043d\u044f\u044f \u0415\u0440\u0448\u043e\u0432\u043a\u0430"
    ],
    "wof:name":"Nizhnyaya Yershovka",
    "wof:placetype":"locality"
},
  "geometry": {"coordinates":[56.16667,58.53333000000001],"type":"Point"}
}