{
  "type": "Feature",
  "properties": {
    "gn:admin1_code":"59.0",
    "gn:asciiname":"Yasnoye",
    "gn:country_code":"RU",
    "gn:dem":21,
    "gn:feature_class":"P",
    "gn:feature_code":"PPL",
    "gn:name":"Yasnoye",
    "gn:population":0,
    "gn:timezone":"Asia/Vladivostok",
    "iso:country":"RU",
    "name:rus_x_preferred":[
        "\u042f\u0441\u043d\u043e\u0435"
    ],
    "wof:name":"Yasnoye",
    "wof:placetype":"locality"
},
  "geometry": {"coordinates":[132.15875,43.45395],"type":"Point"}
}