{
  "type": "Feature",
  "properties": {
    "gn:admin1_code":"77",
    "gn:asciiname":"Pal'tsevo",
    "gn:country_code":"RU",
    "gn:dem":206,
    "gn:feature_class":"P",
    "gn:feature_code":"PPL",
    "gn:name":"Pal\u2019tsevo",
    "gn:population":0,
    "gn:timezone":"Europe/Moscow",
    "iso:country":"RU",
    "name:rus_x_preferred":[
        "\u041f\u0430\u043b\u044c\u0446\u0435\u0432\u043e"
    ],
    "name:und_x_variant":[
        "Pal\u2019tsevo",
        "\u041f\u0430\u043b\u044c\u0446\u0435\u0432\u043e"
    ],
    "wof:name":"Pal'tsevo",
    "wof:placetype":"locality"
},
  "geometry": {"coordinates":[36.8236,58.3713],"type":"Point"}
}