{
  "type": "Feature",
  "properties": {
    "gn:admin1_code":"78",
    "gn:asciiname":"Yershovo",
    "gn:country_code":"RU",
    "gn:dem":88,
    "gn:feature_class":"P",
    "gn:feature_code":"PPL",
    "gn:name":"Yershovo",
    "gn:population":0,
    "gn:timezone":"Asia/Yekaterinburg",
    "iso:country":"RU",
    "name:eng_x_preferred":[
        "Yershovo"
    ],
    "name:nor_x_preferred":[
        "Jersjovo"
    ],
    "name:rus_x_preferred":[
        "\u0415\u0440\u0448\u043e\u0432\u043e"
    ],
    "name:und_x_variant":[
        "Bezrukovo",
        "Yershovo"
    ],
    "wof:name":"Yershovo",
    "wof:placetype":"locality"
},
  "geometry": {"coordinates":[69.30370000000001,56.17846],"type":"Point"}
}