{
  "type": "Feature",
  "properties": {
    "gn:admin1_code":"60",
    "gn:asciiname":"Kurochkino",
    "gn:country_code":"RU",
    "gn:dem":207,
    "gn:feature_class":"P",
    "gn:feature_code":"PPL",
    "gn:name":"Kurochkino",
    "gn:population":0,
    "gn:timezone":"Europe/Moscow",
    "iso:country":"RU",
    "name:rus_x_preferred":[
        "\u041a\u0443\u0440\u043e\u0447\u043a\u0438\u043d\u043e"
    ],
    "wof:name":"Kurochkino",
    "wof:placetype":"locality"
},
  "geometry": {"coordinates":[29.2468,56.7724],"type":"Point"}
}