{
  "type": "Feature",
  "properties": {
    "gn:admin1_code":"91",
    "gn:asciiname":"Kargino",
    "gn:country_code":"RU",
    "gn:dem":90,
    "gn:feature_class":"P",
    "gn:feature_code":"PPL",
    "gn:name":"Kargino",
    "gn:population":0,
    "gn:timezone":"Asia/Krasnoyarsk",
    "iso:country":"RU",
    "name:eng_x_preferred":[
        "Kargino"
    ],
    "name:nor_x_preferred":[
        "Novokargino"
    ],
    "name:rus_x_preferred":[
        "\u041d\u043e\u0432\u043e\u043a\u0430\u0440\u0433\u0438\u043d\u043e"
    ],
    "name:rus_x_variant":[
        "\u041a\u0430\u0440\u0433\u0438\u043d\u043e"
    ],
    "name:und_x_variant":[
        "Novokargino",
        "Kargino"
    ],
    "wof:name":"Kargino",
    "wof:placetype":"locality"
},
  "geometry": {"coordinates":[92.9743,58.0067],"type":"Point"}
}