{
  "type": "Feature",
  "properties": {
    "gn:admin1_code":"88.0",
    "gn:asciiname":"Parkhachevo",
    "gn:country_code":"RU",
    "gn:dem":128,
    "gn:feature_class":"P",
    "gn:feature_code":"PPL",
    "gn:name":"Parkhach\u00ebvo",
    "gn:population":0,
    "gn:timezone":"Europe/Moscow",
    "iso:country":"RU",
    "name:rus_x_preferred":[
        "\u041f\u0430\u0440\u0445\u0430\u0447\u0451\u0432\u043e"
    ],
    "name:und_x_variant":[
        "Parkhach\u00ebvo",
        "\u041f\u0430\u0440\u0445\u0430\u0447\u0451\u0432\u043e"
    ],
    "wof:name":"Parkhachevo",
    "wof:placetype":"locality"
},
  "geometry": {"coordinates":[40.49943,58.31614],"type":"Point"}
}