{
  "type": "Feature",
  "properties": {
    "gn:country":"RU",
    "gn:fcode":"PPL",
    "gn:population":405,
    "iso:country":"RU",
    "name:bul_x_preferred":[
        "\u0414\u043e\u043c\u0431\u0430\u0439"
    ],
    "name:ceb_x_preferred":[
        "Dombay"
    ],
    "name:che_x_preferred":[
        "\u0414\u043e\u043c\u0431\u0430\u0439"
    ],
    "name:deu_x_preferred":[
        "Dombai"
    ],
    "name:eng_x_preferred":[
        "Dombay"
    ],
    "name:fra_x_preferred":[
        "Domba\u00ef"
    ],
    "name:hye_x_preferred":[
        "\u0534\u0578\u0574\u0562\u0561\u0575"
    ],
    "name:ita_x_preferred":[
        "Dombaj"
    ],
    "name:jpn_x_preferred":[
        "\u30c9\u30f3\u30d9\u30a4"
    ],
    "name:nld_x_preferred":[
        "Dombay"
    ],
    "name:nor_x_preferred":[
        "Dombaj"
    ],
    "name:pol_x_preferred":[
        "Dombaj"
    ],
    "name:rus_x_preferred":[
        "\u0414\u043e\u043c\u0431\u0430\u0439"
    ],
    "name:und_x_variant":[
        "Al\u2019plager\u2019 Dombay"
    ],
    "name:vie_x_preferred":[
        "Dombai"
    ],
    "name:zho_x_preferred":[
        "\u68df\u5df4\u4f0a"
    ],
    "qs:name":"Dombay",
    "qs:photos_9r":0,
    "qs:photos_sr":0,
    "qs:pop_sr":"2",
    "wd:wordcount":53,
    "wof:name":"Dombay",
    "wof:placetype":"locality",
    "wof:population":405
},
  "geometry": {"coordinates":[41.62167,43.29167],"type":"Point"}
}