{
  "type": "Feature",
  "properties": {
    "gn:admin1_code":"8",
    "gn:asciiname":"Karaidel'skiy",
    "gn:country_code":"RU",
    "gn:dem":192,
    "gn:feature_class":"P",
    "gn:feature_code":"PPL",
    "gn:name":"Karaidel\u2019skiy",
    "gn:population":0,
    "gn:timezone":"Asia/Yekaterinburg",
    "iso:country":"RU",
    "name:eng_x_preferred":[
        "Karaidel'skiy"
    ],
    "name:nor_x_preferred":[
        "Karaidelskij"
    ],
    "name:rus_x_preferred":[
        "\u041a\u0430\u0440\u0430\u0438\u0434\u0435\u043b\u044c\u0441\u043a\u0438\u0439"
    ],
    "name:und_x_variant":[
        "Karaidel\u2019skiy",
        "\u041a\u0430\u0440\u0430\u0438\u0434\u0435\u043b\u044c\u0441\u043a\u0438\u0439"
    ],
    "wof:name":"Karaidel'skiy",
    "wof:placetype":"locality"
},
  "geometry": {"coordinates":[57.10616,55.82183000000001],"type":"Point"}
}