{
  "type": "Feature",
  "properties": {
    "gn:admin1_code":"81",
    "gn:asciiname":"Syuksyum",
    "gn:country_code":"RU",
    "gn:dem":181,
    "gn:feature_class":"P",
    "gn:feature_code":"PPL",
    "gn:name":"Syuksyum",
    "gn:population":0,
    "gn:timezone":"Europe/Ulyanovsk",
    "iso:country":"RU",
    "name:eng_x_preferred":[
        "Syuksyum"
    ],
    "name:nor_x_preferred":[
        "Siuksium"
    ],
    "name:rus_x_preferred":[
        "\u0421\u044e\u043a\u0441\u044e\u043c"
    ],
    "name:und_x_variant":[
        "Syunsyum",
        "\u0421\u044e\u043a\u0441\u044e\u043c",
        "Syuksyum"
    ],
    "wof:name":"Syuksyum",
    "wof:placetype":"locality"
},
  "geometry": {"coordinates":[46.4607,53.81452],"type":"Point"}
}