{
  "type": "Feature",
  "properties": {
    "gn:country":"RU",
    "gn:fcode":"PPL",
    "gn:population":2959,
    "iso:country":"RU",
    "name:nor_x_preferred":[
        "Tsjernitsyno"
    ],
    "name:rus_x_preferred":[
        "\u0427\u0435\u0440\u043d\u0438\u0446\u044b\u043d\u043e"
    ],
    "qs:name":"Chernitsyno",
    "qs:photos_9r":0,
    "qs:photos_sr":0,
    "qs:pop_sr":"4",
    "wof:name":"Chernitsyno",
    "wof:placetype":"locality",
    "wof:population":2959
},
  "geometry": {"coordinates":[36.05101,51.50739],"type":"Point"}
}