{
  "type": "Feature",
  "properties": {
    "gn:admin1_code":"51.0",
    "gn:asciiname":"Sboikha",
    "gn:country_code":"RU",
    "gn:dem":97,
    "gn:feature_class":"P",
    "gn:feature_code":"PPL",
    "gn:name":"Sboikha",
    "gn:population":0,
    "gn:timezone":"Europe/Moscow",
    "iso:country":"RU",
    "name:nor_x_preferred":[
        "Sboikha"
    ],
    "name:rus_x_preferred":[
        "\u0421\u0431\u043e\u0438\u0445\u0430"
    ],
    "wof:name":"Sboikha",
    "wof:placetype":"locality"
},
  "geometry": {"coordinates":[43.62971,56.70092],"type":"Point"}
}