{
  "type": "Feature",
  "properties": {
    "gn:admin1_code":"56.0",
    "gn:asciiname":"Dobrovody",
    "gn:country_code":"RU",
    "gn:dem":237,
    "gn:feature_class":"P",
    "gn:feature_code":"PPL",
    "gn:name":"Dobrovody",
    "gn:population":0,
    "gn:timezone":"Europe/Moscow",
    "iso:country":"RU",
    "name:fra_x_preferred":[
        "Dobrovody"
    ],
    "name:rus_x_preferred":[
        "\u0414\u043e\u0431\u0440\u043e\u0432\u043e\u0434\u044b"
    ],
    "name:ukr_x_preferred":[
        "\u0414\u043e\u0431\u0440\u043e\u0432\u043e\u0434\u0438"
    ],
    "name:und_x_variant":[
        "\u0414\u043e\u0431\u0440\u043e\u0432\u043e\u0434\u044b"
    ],
    "wof:name":"Dobrovody",
    "wof:placetype":"locality"
},
  "geometry": {"coordinates":[36.51528,53.11583],"type":"Point"}
}