{
  "type": "Feature",
  "properties": {
    "gn:admin1_code":"69.0",
    "gn:asciiname":"Chernenovo",
    "gn:cc2":"RU",
    "gn:country_code":"RU",
    "gn:dem":220,
    "gn:feature_class":"P",
    "gn:feature_code":"PPL",
    "gn:name":"Chern\u00ebnovo",
    "gn:population":0,
    "gn:timezone":"Europe/Moscow",
    "iso:country":"RU",
    "name:rus_x_preferred":[
        "\u0427\u0435\u0440\u043d\u0451\u043d\u043e\u0432\u043e"
    ],
    "name:und_x_variant":[
        "Chernenova",
        "Chern\u00ebnovo"
    ],
    "wof:name":"Chernenovo",
    "wof:placetype":"locality"
},
  "geometry": {"coordinates":[33.53556,55.46361],"type":"Point"}
}