{
  "type": "Feature",
  "properties": {
    "gn:admin1_code":"77",
    "gn:asciiname":"Bol'shiye Ushany",
    "gn:country_code":"RU",
    "gn:dem":201,
    "gn:feature_class":"P",
    "gn:feature_code":"PPL",
    "gn:name":"Bol\u2019shiye Ushany",
    "gn:population":0,
    "gn:timezone":"Europe/Moscow",
    "iso:country":"RU",
    "name:rus_x_preferred":[
        "\u0411\u043e\u043b\u044c\u0448\u0438\u0435 \u0423\u0448\u0430\u043d\u044b"
    ],
    "name:und_x_variant":[
        "Bol\u2019shiye Ushchani",
        "Bol\u2019shiye Ushany"
    ],
    "wof:name":"Bol'shiye Ushany",
    "wof:placetype":"locality"
},
  "geometry": {"coordinates":[32.32057,56.24012],"type":"Point"}
}