{
  "type": "Feature",
  "properties": {
    "gn:admin1_code":"90",
    "gn:asciiname":"Verkhnyaya Chermoda",
    "gn:country_code":"RU",
    "gn:dem":143,
    "gn:feature_class":"P",
    "gn:feature_code":"PPL",
    "gn:name":"Verkhnyaya Chermoda",
    "gn:population":0,
    "gn:timezone":"Asia/Yekaterinburg",
    "iso:country":"RU",
    "name:rus_x_preferred":[
        "\u0412\u0435\u0440\u0445\u043d\u044f\u044f \u0427\u0435\u0440\u043c\u043e\u0434\u0430"
    ],
    "wof:name":"Verkhnyaya Chermoda",
    "wof:placetype":"locality"
},
  "geometry": {"coordinates":[55.6616,57.1138],"type":"Point"}
}