{
  "type": "Feature",
  "properties": {
    "gn:admin1_code":"77.0",
    "gn:asciiname":"Ozeryanki",
    "gn:country_code":"RU",
    "gn:dem":206,
    "gn:feature_class":"P",
    "gn:feature_code":"PPL",
    "gn:name":"Ozeryanki",
    "gn:population":0,
    "gn:timezone":"Europe/Moscow",
    "iso:country":"RU",
    "name:nor_x_preferred":[
        "Ozerjanki"
    ],
    "name:rus_x_preferred":[
        "\u041e\u0437\u0435\u0440\u044f\u043d\u043a\u0438"
    ],
    "name:und_x_variant":[
        "Burkhino",
        "Ozeryanki"
    ],
    "wof:name":"Ozeryanki",
    "wof:placetype":"locality"
},
  "geometry": {"coordinates":[35.07027,56.19262],"type":"Point"}
}