{
  "type": "Feature",
  "properties": {
    "gn:admin1_code":"10",
    "gn:asciiname":"Novoveseloye",
    "gn:country_code":"RU",
    "gn:dem":198,
    "gn:feature_class":"P",
    "gn:feature_code":"PPL",
    "gn:name":"Novoves\u00ebloye",
    "gn:population":0,
    "gn:timezone":"Europe/Moscow",
    "iso:country":"RU",
    "name:rus_x_preferred":[
        "\u041d\u043e\u0432\u043e\u0432\u0435\u0441\u0451\u043b\u043e\u0435"
    ],
    "name:und_x_variant":[
        "Novoves\u00ebloye"
    ],
    "wof:name":"Novoveseloye",
    "wof:placetype":"locality"
},
  "geometry": {"coordinates":[34.3991,52.1372],"type":"Point"}
}