{
  "type": "Feature",
  "properties": {
    "gn:country":"RU",
    "gn:fcode":"PPL",
    "gn:population":11765,
    "iso:country":"RU",
    "name:eng_x_preferred":[
        "Nizhneye Kazanishche"
    ],
    "name:nor_x_preferred":[
        "Nizjneje-Kazanisjtsje"
    ],
    "name:rus_x_preferred":[
        "\u041d\u0438\u0436\u043d\u0435\u0435 \u041a\u0430\u0437\u0430\u043d\u0438\u0449\u0435"
    ],
    "name:und_x_variant":[
        "Nizhniye Kazanishche"
    ],
    "qs:name":"Nizhneye Kazanishche",
    "qs:name_adm0":"Russia",
    "qs:name_adm1":"Dagestan Republic",
    "qs:photos_9r":0,
    "qs:photos_sr":0,
    "qs:placetype":"Town",
    "qs:pop_sr":"6",
    "wof:name":"Nizhneye Kazanishche",
    "wof:placetype":"locality",
    "wof:population":11765
},
  "geometry": {"coordinates":[47.16027,42.76369],"type":"Point"}
}