{
  "type": "Feature",
  "properties": {
    "gn:admin1_code":"61",
    "gn:asciiname":"Ul'yanovskiy",
    "gn:country_code":"RU",
    "gn:dem":80,
    "gn:feature_class":"P",
    "gn:feature_code":"PPL",
    "gn:name":"Ul\u2019yanovskiy",
    "gn:population":0,
    "gn:timezone":"Europe/Moscow",
    "iso:country":"RU",
    "name:rus_x_preferred":[
        "Ul\u2019yanovskiy"
    ],
    "name:ukr_x_preferred":[
        "Ul\u2019yanovs\u2019kyy"
    ],
    "wof:name":"Ul'yanovskiy",
    "wof:placetype":"locality"
},
  "geometry": {"coordinates":[38.35386,47.38408],"type":"Point"}
}