{
  "type": "Feature",
  "properties": {
    "gn:admin1_code":"83",
    "gn:asciiname":"Turtino",
    "gn:country_code":"RU",
    "gn:dem":135,
    "gn:feature_class":"P",
    "gn:feature_code":"PPL",
    "gn:name":"Turtino",
    "gn:population":0,
    "gn:timezone":"Europe/Moscow",
    "iso:country":"RU",
    "name:eng_x_preferred":[
        "Turtino"
    ],
    "name:nor_x_preferred":[
        "Turtino"
    ],
    "name:rus_x_preferred":[
        "\u0422\u0443\u0440\u0442\u0438\u043d\u043e"
    ],
    "wof:name":"Turtino",
    "wof:placetype":"locality"
},
  "geometry": {"coordinates":[40.32819,56.34335],"type":"Point"}
}