{
  "type": "Feature",
  "properties": {
    "gn:admin1_code":"78",
    "gn:asciiname":"Okunevo",
    "gn:country_code":"RU",
    "gn:dem":140,
    "gn:feature_class":"P",
    "gn:feature_code":"PPL",
    "gn:name":"Okun\u00ebvo",
    "gn:population":0,
    "gn:timezone":"Asia/Yekaterinburg",
    "iso:country":"RU",
    "name:eng_x_preferred":[
        "Okun\u00ebvo"
    ],
    "name:nor_x_preferred":[
        "Okunevo"
    ],
    "name:rus_x_preferred":[
        "\u041e\u043a\u0443\u043d\u0435\u0432\u043e"
    ],
    "name:rus_x_variant":[
        "\u041e\u043a\u0443\u043d\u0451\u0432\u043e"
    ],
    "name:und_x_variant":[
        "Okun\u00ebvo",
        "\u041e\u043a\u0443\u043d\u0451\u0432\u043e"
    ],
    "wof:name":"Okunevo",
    "wof:placetype":"locality"
},
  "geometry": {"coordinates":[68.69333,55.71806],"type":"Point"}
}