{
  "type": "Feature",
  "properties": {
    "gn:admin1_code":"41",
    "gn:asciiname":"Malyye Ugony",
    "gn:country_code":"RU",
    "gn:dem":146,
    "gn:feature_class":"P",
    "gn:feature_code":"PPL",
    "gn:name":"Malyye Ugony",
    "gn:population":0,
    "gn:timezone":"Europe/Moscow",
    "iso:country":"RU",
    "name:rus_x_preferred":[
        "\u041c\u0430\u043b\u044b\u0435 \u0423\u0433\u043e\u043d\u044b"
    ],
    "name:und_x_variant":[
        "\u041c\u0430\u043b\u044b\u0435 \u0423\u0433\u043e\u043d\u044b"
    ],
    "wof:name":"Malyye Ugony",
    "wof:placetype":"locality"
},
  "geometry": {"coordinates":[35.40417,51.61861],"type":"Point"}
}