{
  "type": "Feature",
  "properties": {
    "gn:admin1_code":"77",
    "gn:asciiname":"Gornestrugov",
    "gn:country_code":"RU",
    "gn:dem":219,
    "gn:feature_class":"P",
    "gn:feature_code":"PPL",
    "gn:name":"Gornestrugov",
    "gn:population":0,
    "gn:timezone":"Europe/Moscow",
    "iso:country":"RU",
    "name:rus_x_preferred":[
        "\u0413\u043e\u0440\u043d\u0435\u0441\u0442\u0440\u0443\u0433\u043e\u0432"
    ],
    "wof:name":"Gornestrugov",
    "wof:placetype":"locality"
},
  "geometry": {"coordinates":[31.76667,56.66667],"type":"Point"}
}