{
  "type": "Feature",
  "properties": {
    "gn:admin1_code":"53",
    "gn:asciiname":"Levyy Kurundus",
    "gn:cc2":"RU",
    "gn:country_code":"RU",
    "gn:dem":179,
    "gn:feature_class":"P",
    "gn:feature_code":"PPL",
    "gn:name":"Levyy Kurundus",
    "gn:population":0,
    "gn:timezone":"Asia/Novosibirsk",
    "iso:country":"RU",
    "name:rus_x_preferred":[
        "\u041b\u0435\u0432\u044b\u0439 \u041a\u0443\u0440\u0443\u043d\u0434\u0443\u0441"
    ],
    "name:und_x_variant":[
        "Kurundus Levyy",
        "Levyy Kurundus",
        "\u041b\u0435\u0432\u044b\u0439 \u041a\u0443\u0440\u0443\u043d\u0434\u0443\u0441"
    ],
    "wof:name":"Levyy Kurundus",
    "wof:placetype":"locality"
},
  "geometry": {"coordinates":[84.31667,55.01667],"type":"Point"}
}