{
  "type": "Feature",
  "properties": {
    "gn:admin1_code":"69",
    "gn:asciiname":"Ragozino",
    "gn:cc2":"RU",
    "gn:country_code":"RU",
    "gn:dem":183,
    "gn:feature_class":"P",
    "gn:feature_code":"PPL",
    "gn:name":"Ragozino",
    "gn:population":0,
    "gn:timezone":"Europe/Moscow",
    "iso:country":"RU",
    "name:rus_x_preferred":[
        "\u0420\u0430\u0433\u043e\u0437\u0438\u043d\u043e"
    ],
    "name:und_x_variant":[
        "Ragozina",
        "Ragozino"
    ],
    "wof:name":"Ragozino",
    "wof:placetype":"locality"
},
  "geometry": {"coordinates":[34.76417,55.70056],"type":"Point"}
}