{
  "type": "Feature",
  "properties": {
    "gn:admin1_code":"88",
    "gn:asciiname":"Vnukovo",
    "gn:country_code":"RU",
    "gn:dem":143,
    "gn:feature_class":"P",
    "gn:feature_code":"PPL",
    "gn:name":"Vnukovo",
    "gn:population":0,
    "gn:timezone":"Europe/Moscow",
    "iso:country":"RU",
    "name:rus_x_preferred":[
        "\u0412\u043d\u0443\u043a\u043e\u0432\u043e"
    ],
    "wof:name":"Vnukovo",
    "wof:placetype":"locality"
},
  "geometry": {"coordinates":[39.84896,57.52895],"type":"Point"}
}