{
  "type": "Feature",
  "properties": {
    "gn:admin1_code":"83",
    "gn:asciiname":"Zobishchi",
    "gn:country_code":"RU",
    "gn:dem":125,
    "gn:feature_class":"P",
    "gn:feature_code":"PPL",
    "gn:name":"Zobishchi",
    "gn:population":32,
    "gn:timezone":"Europe/Moscow",
    "iso:country":"RU",
    "wof:name":"Zobishchi",
    "wof:placetype":"locality",
    "wof:population":32
},
  "geometry": {"coordinates":[42.02004,56.188],"type":"Point"}
}