{
  "type": "Feature",
  "properties": {
    "gn:admin1_code":"56",
    "gn:asciiname":"Parnaya",
    "gn:country_code":"RU",
    "gn:dem":202,
    "gn:feature_class":"P",
    "gn:feature_code":"PPL",
    "gn:name":"Parnaya",
    "gn:population":0,
    "gn:timezone":"Europe/Moscow",
    "iso:country":"RU",
    "name:rus_x_preferred":[
        "\u041f\u0430\u0440\u043d\u0430\u044f"
    ],
    "name:und_x_variant":[
        "\u041f\u0430\u0440\u043d\u0430\u044f"
    ],
    "wof:name":"Parnaya",
    "wof:placetype":"locality"
},
  "geometry": {"coordinates":[37.91667,52.33333],"type":"Point"}
}