{
  "type": "Feature",
  "properties": {
    "gn:admin1_code":"69",
    "gn:asciiname":"Karna",
    "gn:country_code":"RU",
    "gn:dem":207,
    "gn:feature_class":"P",
    "gn:feature_code":"PPL",
    "gn:name":"Karna",
    "gn:population":0,
    "gn:timezone":"Europe/Moscow",
    "iso:country":"RU",
    "name:asm_x_preferred":[
        "\u0995\u09f0\u09cd\u09a3"
    ],
    "name:ben_x_preferred":[
        "\u0995\u09b0\u09cd\u09a3"
    ],
    "name:deu_x_preferred":[
        "Karna"
    ],
    "name:fas_x_preferred":[
        "\u0644\u0646\u062f\u0647\u0648\u0631"
    ],
    "name:fra_x_preferred":[
        "Karna"
    ],
    "name:guj_x_preferred":[
        "\u0a95\u0ab0\u0acd\u0aa3"
    ],
    "name:hin_x_preferred":[
        "\u0915\u0930\u094d\u0923"
    ],
    "name:ind_x_preferred":[
        "Karna"
    ],
    "name:ita_x_preferred":[
        "Karna"
    ],
    "name:jav_x_preferred":[
        "Karna"
    ],
    "name:jpn_x_preferred":[
        "\u30ab\u30eb\u30ca"
    ],
    "name:kan_x_preferred":[
        "\u0c95\u0cb0\u0ccd\u0ca3"
    ],
    "name:lit_x_preferred":[
        "Karna"
    ],
    "name:mai_x_preferred":[
        "\u0915\u0930\u094d\u0923"
    ],
    "name:mal_x_preferred":[
        "\u0d15\u0d7c\u0d23\u0d4d\u0d23\u0d7b"
    ],
    "name:mar_x_preferred":[
        "\u0915\u0930\u094d\u0923"
    ],
    "name:nep_x_preferred":[
        "\u0915\u0930\u094d\u0923"
    ],
    "name:new_x_preferred":[
        "\u0915\u0930\u094d\u0923"
    ],
    "name:ori_x_preferred":[
        "\u0b15\u0b30\u0b4d\u0b23\u0b4d\u0b23"
    ],
    "name:pan_x_preferred":[
        "\u0a15\u0a30\u0a23"
    ],
    "name:rus_x_preferred":[
        "\u041a\u0430\u0440\u043d\u0430"
    ],
    "name:slk_x_preferred":[
        "Karna"
    ],
    "name:spa_x_preferred":[
        "Karna"
    ],
    "name:sun_x_preferred":[
        "Karna"
    ],
    "name:tam_x_preferred":[
        "\u0b95\u0bb0\u0bcd\u0ba3\u0ba9\u0bcd"
    ],
    "name:tel_x_preferred":[
        "\u0c15\u0c30\u0c4d\u0c23\u0c41\u0c21\u0c41"
    ],
    "name:tha_x_preferred":[
        "\u0e01\u0e23\u0e23\u0e13\u0e30"
    ],
    "name:ukr_x_preferred":[
        "\u041a\u0430\u0440\u043d\u0430"
    ],
    "name:urd_x_preferred":[
        "\u06a9\u0631\u0646"
    ],
    "name:zho_x_preferred":[
        "\u8fe6\u723e\u7d0d"
    ],
    "wof:name":"Karna",
    "wof:placetype":"locality"
},
  "geometry": {"coordinates":[32.42194,54.31361],"type":"Point"}
}