{
  "type": "Feature",
  "properties": {
    "gn:admin1_code":"59",
    "gn:asciiname":"Krasnoyarovka",
    "gn:country_code":"RU",
    "gn:dem":134,
    "gn:feature_class":"P",
    "gn:feature_code":"PPL",
    "gn:name":"Krasnoyarovka",
    "gn:population":0,
    "gn:timezone":"Asia/Vladivostok",
    "iso:country":"RU",
    "name:eng_x_preferred":[
        "Krasnoyarovka"
    ],
    "name:nor_x_preferred":[
        "Krasnojarovka"
    ],
    "name:rus_x_preferred":[
        "\u041a\u0440\u0430\u0441\u043d\u043e\u044f\u0440\u043e\u0432\u043a\u0430"
    ],
    "name:und_x_variant":[
        "Novo-Krasnoyarovo",
        "Novo-Krasnoyarovka",
        "Novo-Krasnovarskova",
        "\u041a\u0440\u0430\u0441\u043d\u043e\u044f\u0440\u043e\u0432\u043a\u0430",
        "Krasnoyarovka"
    ],
    "wof:name":"Krasnoyarovka",
    "wof:placetype":"locality"
},
  "geometry": {"coordinates":[133.81474,44.64532],"type":"Point"}
}