{
  "type": "Feature",
  "properties": {
    "gn:admin1_code":"53",
    "gn:asciiname":"Peschanoye Ozero",
    "gn:country_code":"RU",
    "gn:dem":109,
    "gn:feature_class":"P",
    "gn:feature_code":"PPL",
    "gn:name":"Peschanoye Ozero",
    "gn:population":0,
    "gn:timezone":"Asia/Novosibirsk",
    "iso:country":"RU",
    "name:eng_x_preferred":[
        "Peschanoye Ozero"
    ],
    "name:nor_x_preferred":[
        "Pestsjanoje-Ozero"
    ],
    "name:rus_x_preferred":[
        "\u041f\u0435\u0441\u0447\u0430\u043d\u043e\u0435-\u041e\u0437\u0435\u0440\u043e"
    ],
    "name:rus_x_variant":[
        "\u041f\u0435\u0441\u0447\u0430\u043d\u043e\u0435 \u041e\u0437\u0435\u0440\u043e"
    ],
    "name:und_x_variant":[
        "Chanovskiy"
    ],
    "wof:name":"Peschanoye Ozero",
    "wof:placetype":"locality"
},
  "geometry": {"coordinates":[76.64678000000001,55.02836],"type":"Point"}
}