{
  "type": "Feature",
  "properties": {
    "gn:admin1_code":"65",
    "gn:asciiname":"Chekalinka",
    "gn:country_code":"RU",
    "gn:dem":132,
    "gn:feature_class":"P",
    "gn:feature_code":"PPL",
    "gn:name":"Chekalinka",
    "gn:population":0,
    "gn:timezone":"Europe/Samara",
    "iso:country":"RU",
    "name:rus_x_preferred":[
        "\u0427\u0435\u043a\u0430\u043b\u0438\u043d\u043a\u0430"
    ],
    "wof:name":"Chekalinka",
    "wof:placetype":"locality"
},
  "geometry": {"coordinates":[52.0392,53.5705],"type":"Point"}
}