{
  "type": "Feature",
  "properties": {
    "gn:admin1_code":"4",
    "gn:asciiname":"Pryanishnikovo",
    "gn:cc2":"RU",
    "gn:country_code":"RU",
    "gn:dem":345,
    "gn:feature_class":"P",
    "gn:feature_code":"PPL",
    "gn:name":"Pryanishnikovo",
    "gn:population":0,
    "gn:timezone":"Asia/Barnaul",
    "iso:country":"RU",
    "name:rus_x_preferred":[
        "\u041f\u0440\u044f\u043d\u0438\u0448\u043d\u0438\u043a\u043e\u0432\u043e"
    ],
    "name:und_x_variant":[
        "Pryanishnikov",
        "Pryanishnikovo",
        "\u041f\u0440\u044f\u043d\u0438\u0448\u043d\u0438\u043a\u043e\u0432\u043e"
    ],
    "wof:name":"Pryanishnikovo",
    "wof:placetype":"locality"
},
  "geometry": {"coordinates":[86.65000000000001,52.31667],"type":"Point"}
}