{
  "type": "Feature",
  "properties": {
    "gn:admin1_code":"88",
    "gn:asciiname":"Isady",
    "gn:country_code":"RU",
    "gn:dem":87,
    "gn:feature_class":"P",
    "gn:feature_code":"PPL",
    "gn:name":"Isady",
    "gn:population":0,
    "gn:timezone":"Europe/Moscow",
    "iso:country":"RU",
    "name:nor_x_preferred":[
        "Isady"
    ],
    "name:rus_x_preferred":[
        "\u0418\u0441\u0430\u0434\u044b"
    ],
    "wof:name":"Isady",
    "wof:placetype":"locality"
},
  "geometry": {"coordinates":[40.30391,57.76876],"type":"Point"}
}