{
  "type": "Feature",
  "properties": {
    "gn:admin1_code":"55",
    "gn:asciiname":"Eksperimental'nyy",
    "gn:country_code":"RU",
    "gn:dem":122,
    "gn:feature_class":"P",
    "gn:feature_code":"PPL",
    "gn:name":"Eksperimental\u2019nyy",
    "gn:population":0,
    "gn:timezone":"Asia/Yekaterinburg",
    "iso:country":"RU",
    "name:rus_x_preferred":[
        "\u042d\u043a\u0441\u043f\u0435\u0440\u0438\u043c\u0435\u043d\u0442\u043b\u044c\u043d\u044b\u0439"
    ],
    "name:und_x_variant":[
        "Eksperimental\u2019nyy"
    ],
    "wof:name":"Eksperimental'nyy",
    "wof:placetype":"locality"
},
  "geometry": {"coordinates":[55.03222,51.53506],"type":"Point"}
}