{
  "type": "Feature",
  "properties": {
    "gn:admin1_code":"53",
    "gn:asciiname":"Aksenovo",
    "gn:country_code":"RU",
    "gn:dem":99,
    "gn:feature_class":"P",
    "gn:feature_code":"PPL",
    "gn:name":"Aks\u00ebnovo",
    "gn:population":0,
    "gn:timezone":"Asia/Novosibirsk",
    "iso:country":"RU",
    "name:nor_x_preferred":[
        "Aksionovo"
    ],
    "name:rus_x_preferred":[
        "\u0410\u043a\u0441\u0451\u043d\u043e\u0432\u043e"
    ],
    "name:und_x_variant":[
        "Aks\u00ebnovo"
    ],
    "wof:name":"Aksenovo",
    "wof:placetype":"locality"
},
  "geometry": {"coordinates":[75.83333,54.78333000000001],"type":"Point"}
}