{
  "type": "Feature",
  "properties": {
    "gn:admin1_code":"10",
    "gn:asciiname":"Vorob'yevskiye",
    "gn:country_code":"RU",
    "gn:dem":174,
    "gn:feature_class":"P",
    "gn:feature_code":"PPL",
    "gn:name":"Vorob\u2019yevskiye",
    "gn:population":0,
    "gn:timezone":"Europe/Moscow",
    "iso:country":"RU",
    "name:rus_x_preferred":[
        "Vorob\u2019yevskiye"
    ],
    "wof:name":"Vorob'yevskiye",
    "wof:placetype":"locality"
},
  "geometry": {"coordinates":[32.15889,52.47361],"type":"Point"}
}