{
  "type": "Feature",
  "properties": {
    "gn:admin1_code":"23",
    "gn:asciiname":"Kurskoye",
    "gn:country_code":"RU",
    "gn:dem":52,
    "gn:feature_class":"P",
    "gn:feature_code":"PPL",
    "gn:name":"Kurskoye",
    "gn:population":0,
    "gn:timezone":"Europe/Kaliningrad",
    "iso:country":"RU",
    "name:rus_x_preferred":[
        "\u041a\u0443\u0440\u0441\u043a\u043e\u0435"
    ],
    "name:und_x_variant":[
        "\u041a\u0443\u0440\u0441\u043a\u043e\u0435"
    ],
    "wof:name":"Kurskoye",
    "wof:placetype":"locality"
},
  "geometry": {"coordinates":[20.63521,54.4365],"type":"Point"}
}