{
  "type": "Feature",
  "properties": {
    "gn:admin1_code":"21",
    "gn:asciiname":"Lezhakhovo",
    "gn:country_code":"RU",
    "gn:dem":111,
    "gn:feature_class":"P",
    "gn:feature_code":"PPL",
    "gn:name":"Lezhakhovo",
    "gn:population":0,
    "gn:timezone":"Europe/Moscow",
    "iso:country":"RU",
    "name:rus_x_preferred":[
        "\u041b\u0435\u0436\u0430\u0445\u043e\u0432\u043e"
    ],
    "wof:name":"Lezhakhovo",
    "wof:placetype":"locality"
},
  "geometry": {"coordinates":[41.90777,56.98578000000001],"type":"Point"}
}