{
  "type": "Feature",
  "properties": {
    "gn:admin1_code":"86.0",
    "gn:asciiname":"Kusakinskiy",
    "gn:country_code":"RU",
    "gn:dem":205,
    "gn:feature_class":"P",
    "gn:feature_code":"PPL",
    "gn:name":"Kusakinskiy",
    "gn:population":0,
    "gn:timezone":"Europe/Moscow",
    "iso:country":"RU",
    "name:rus_x_preferred":[
        "\u041a\u0443\u0441\u0430\u043a\u0438\u043d\u0441\u043a\u0438\u0439"
    ],
    "wof:name":"Kusakinskiy",
    "wof:placetype":"locality"
},
  "geometry": {"coordinates":[40.87472,51.06611],"type":"Point"}
}