{
  "type": "Feature",
  "properties": {
    "gn:admin1_code":"77",
    "gn:asciiname":"Kraskovo",
    "gn:country_code":"RU",
    "gn:dem":137,
    "gn:feature_class":"P",
    "gn:feature_code":"PPL",
    "gn:name":"Kraskovo",
    "gn:population":0,
    "gn:timezone":"Europe/Moscow",
    "iso:country":"RU",
    "name:rus_x_preferred":[
        "\u041a\u0440\u0430\u0441\u043a\u043e\u0432\u043e"
    ],
    "name:und_x_variant":[
        "\u041a\u0440\u0430\u0441\u043a\u043e\u0432\u043e"
    ],
    "wof:name":"Kraskovo",
    "wof:placetype":"locality"
},
  "geometry": {"coordinates":[36.5797,57.666],"type":"Point"}
}