{
  "type": "Feature",
  "properties": {
    "gn:admin1_code":"51.0",
    "gn:asciiname":"Ideal",
    "gn:country_code":"RU",
    "gn:dem":165,
    "gn:feature_class":"P",
    "gn:feature_code":"PPL",
    "gn:name":"Ideal",
    "gn:population":0,
    "gn:timezone":"Europe/Moscow",
    "iso:country":"RU",
    "name:cat_x_preferred":[
        "Ideal"
    ],
    "name:ces_x_preferred":[
        "Ide\u00e1l"
    ],
    "name:dan_x_preferred":[
        "Ideel"
    ],
    "name:deu_x_preferred":[
        "Ideal"
    ],
    "name:ell_x_preferred":[
        "\u0399\u03b4\u03b5\u03ce\u03b4\u03b5\u03c2"
    ],
    "name:eus_x_preferred":[
        "Ideal"
    ],
    "name:fas_x_preferred":[
        "\u0627\u06cc\u062f\u0626\u0627\u0644"
    ],
    "name:fin_x_preferred":[
        "Ideaali"
    ],
    "name:fra_x_preferred":[
        "Id\u00e9al"
    ],
    "name:heb_x_preferred":[
        "\u05d0\u05d9\u05d3\u05d9\u05d0\u05dc"
    ],
    "name:hun_x_preferred":[
        "Ide\u00e1l"
    ],
    "name:ita_x_preferred":[
        "Ideal"
    ],
    "name:jpn_x_preferred":[
        "\u30a2\u30a4\u30c7\u30a2\u30eb"
    ],
    "name:kat_x_preferred":[
        "\u10d8\u10d3\u10d4\u10d0\u10da\u10d8"
    ],
    "name:kor_x_preferred":[
        "\uc544\uc774\ub514\uc5bc"
    ],
    "name:nld_x_preferred":[
        "Ideal"
    ],
    "name:nor_x_preferred":[
        "Ideal"
    ],
    "name:pol_x_preferred":[
        "Ideal"
    ],
    "name:por_x_preferred":[
        "Ideal"
    ],
    "name:ron_x_preferred":[
        "Ideal"
    ],
    "name:rus_x_preferred":[
        "\u0418\u0434\u0435\u0430\u043b"
    ],
    "name:slk_x_preferred":[
        "Ide\u00e1l"
    ],
    "name:spa_x_preferred":[
        "Ideal"
    ],
    "name:srp_x_preferred":[
        "\u0418\u0434\u0435\u0430\u043b"
    ],
    "name:swe_x_preferred":[
        "Ideal"
    ],
    "name:ukr_x_preferred":[
        "\u0406\u0434\u0435\u0430\u043b"
    ],
    "name:uzb_x_preferred":[
        "Ideal"
    ],
    "wof:name":"Ideal",
    "wof:placetype":"locality"
},
  "geometry": {"coordinates":[43.49103,55.24086],"type":"Point"}
}