{
  "type": "Feature",
  "properties": {
    "gn:admin1_code":"20.0",
    "gn:asciiname":"Burinskaya Dacha",
    "gn:country_code":"RU",
    "gn:dem":463,
    "gn:feature_class":"P",
    "gn:feature_code":"PPL",
    "gn:name":"Burinskaya Dacha",
    "gn:population":0,
    "gn:timezone":"Asia/Irkutsk",
    "iso:country":"RU",
    "name:rus_x_preferred":[
        "\u0411\u0443\u0440\u0438\u043d\u0441\u043a\u0430\u044f \u0414\u0430\u0447\u0430"
    ],
    "wof:name":"Burinskaya Dacha",
    "wof:placetype":"locality"
},
  "geometry": {"coordinates":[102.1345,54.0728],"type":"Point"}
}