{
  "type": "Feature",
  "properties": {
    "gn:country":"RU",
    "gn:fcode":"PPL",
    "gn:pop":0,
    "iso:country":"RU",
    "name:rus_x_preferred":[
        "\u041d\u0438\u043a\u043e\u043b\u044c\u0441\u043a\u043e\u0435"
    ],
    "name:unk_x_variant":[
        "Nikol\u2019skoye"
    ],
    "qs:name":"Nikol'skoye",
    "qs:name_adm0":"Russia",
    "qs:name_adm1":"Belgorod Oblast",
    "qs:photos_9r":0,
    "qs:photos_sr":0,
    "qs:placetype":"Town",
    "qs:pop_sr":"0",
    "wd:wordcount":259,
    "wof:name":"Nikol'skoye",
    "wof:placetype":"locality",
    "wof:population":0
},
  "geometry": {"coordinates":[36.58114,50.44331],"type":"Point"}
}