{
  "type": "Feature",
  "properties": {
    "gn:admin1_code":"60",
    "gn:asciiname":"Shumikhi",
    "gn:country_code":"RU",
    "gn:dem":155,
    "gn:feature_class":"P",
    "gn:feature_code":"PPL",
    "gn:name":"Shumikhi",
    "gn:population":0,
    "gn:timezone":"Europe/Moscow",
    "iso:country":"RU",
    "name:rus_x_preferred":[
        "\u0428\u0443\u043c\u0438\u0445\u0438"
    ],
    "wof:name":"Shumikhi",
    "wof:placetype":"locality"
},
  "geometry": {"coordinates":[29.0875,56.5181],"type":"Point"}
}