{
  "type": "Feature",
  "properties": {
    "gn:admin1_code":"54",
    "gn:asciiname":"Yevlant'yevka",
    "gn:country_code":"RU",
    "gn:dem":95,
    "gn:feature_class":"P",
    "gn:feature_code":"PPL",
    "gn:name":"Yevlant\u2019yevka",
    "gn:population":0,
    "gn:timezone":"Asia/Omsk",
    "iso:country":"RU",
    "name:eng_x_preferred":[
        "Yevlant'yevka"
    ],
    "name:nor_x_preferred":[
        "Jevlantjevka"
    ],
    "name:rus_x_preferred":[
        "\u0415\u0432\u043b\u0430\u043d\u0442\u044c\u0435\u0432\u043a\u0430"
    ],
    "name:und_x_variant":[
        "Yevlant\u2019yevka",
        "\u0415\u0432\u043b\u0430\u043d\u0442\u044c\u0435\u0432\u043a\u0430"
    ],
    "wof:name":"Yevlant'yevka",
    "wof:placetype":"locality"
},
  "geometry": {"coordinates":[75.46163,56.92714],"type":"Point"}
}