{
  "type": "Feature",
  "properties": {
    "gn:admin1_code":"4",
    "gn:asciiname":"Samarskiy",
    "gn:country_code":"RU",
    "gn:dem":218,
    "gn:feature_class":"P",
    "gn:feature_code":"PPL",
    "gn:name":"Samarskiy",
    "gn:population":0,
    "gn:timezone":"Asia/Barnaul",
    "iso:country":"RU",
    "name:eng_x_preferred":[
        "Samarskiy"
    ],
    "name:nor_x_preferred":[
        "Samarka"
    ],
    "name:rus_x_preferred":[
        "\u0421\u0430\u043c\u0430\u0440\u043a\u0430"
    ],
    "name:rus_x_variant":[
        "\u0421\u0430\u043c\u0430\u0440\u0441\u043a\u0438\u0439"
    ],
    "name:und_x_variant":[
        "\u0421\u0430\u043c\u0430\u0440\u0441\u043a\u0438\u0439"
    ],
    "wof:name":"Samarskiy",
    "wof:placetype":"locality"
},
  "geometry": {"coordinates":[81.26666999999998,51.38333],"type":"Point"}
}