{
  "type": "Feature",
  "properties": {
    "gn:admin1_code":"77",
    "gn:asciiname":"Pavlikha",
    "gn:country_code":"RU",
    "gn:dem":220,
    "gn:feature_class":"P",
    "gn:feature_code":"PPL",
    "gn:name":"Pavlikha",
    "gn:population":0,
    "gn:timezone":"Europe/Moscow",
    "iso:country":"RU",
    "name:eng_x_preferred":[
        "Pavlikha"
    ],
    "name:nor_x_preferred":[
        "Pavlikha"
    ],
    "name:rus_x_preferred":[
        "\u041f\u0430\u0432\u043b\u0438\u0445\u0430"
    ],
    "wof:name":"Pavlikha",
    "wof:placetype":"locality"
},
  "geometry": {"coordinates":[32.92851,57.31501],"type":"Point"}
}