{
  "type": "Feature",
  "properties": {
    "gn:admin1_code":"85",
    "gn:asciiname":"Matveyeva Gora",
    "gn:country_code":"RU",
    "gn:dem":148,
    "gn:feature_class":"P",
    "gn:feature_code":"PPL",
    "gn:name":"Matveyeva Gora",
    "gn:population":0,
    "gn:timezone":"Europe/Moscow",
    "iso:country":"RU",
    "name:rus_x_preferred":[
        "\u041c\u0430\u0442\u0432\u0435\u0435\u0432\u0430 \u0413\u043e\u0440\u0430"
    ],
    "name:und_x_variant":[
        "Indoman-Matveyeva Gora"
    ],
    "wof:name":"Matveyeva Gora",
    "wof:placetype":"locality"
},
  "geometry": {"coordinates":[37.7804,60.5343],"type":"Point"}
}