{
  "type": "Feature",
  "properties": {
    "iso:country":"RU",
    "name:rus_x_preferred":[
        "\u041a\u043e\u043c\u0430\u0440\u043e\u0432\u043e"
    ],
    "wof:name":"Komarovo",
    "wof:placetype":"neighbourhood"
},
  "geometry": {"coordinates":[29.80750384085567,60.1894779332532],"type":"Point"}
}