{
  "type": "Feature",
  "properties": {
    "gn:admin1_code":"75",
    "gn:asciiname":"Lukashkin Yar",
    "gn:country_code":"RU",
    "gn:dem":35,
    "gn:feature_class":"P",
    "gn:feature_code":"PPL",
    "gn:name":"Lukashkin Yar",
    "gn:population":0,
    "gn:timezone":"Asia/Tomsk",
    "iso:country":"RU",
    "name:eng_x_preferred":[
        "Lukashkin Yar"
    ],
    "name:nor_x_preferred":[
        "Lukasjkin Jar"
    ],
    "name:rus_x_preferred":[
        "\u041b\u0443\u043a\u0430\u0448\u043a\u0438\u043d \u042f\u0440"
    ],
    "wof:name":"Lukashkin Yar",
    "wof:placetype":"locality"
},
  "geometry": {"coordinates":[78.39416999999997,60.33],"type":"Point"}
}