{
  "type": "Feature",
  "properties": {
    "gn:admin1_code":"57.0",
    "gn:asciiname":"Belyy Klyuch",
    "gn:country_code":"RU",
    "gn:dem":200,
    "gn:feature_class":"P",
    "gn:feature_code":"PPL",
    "gn:name":"Belyy Klyuch",
    "gn:population":0,
    "gn:timezone":"Europe/Moscow",
    "iso:country":"RU",
    "name:nor_x_preferred":[
        "Belyj Kljutsj"
    ],
    "name:rus_x_preferred":[
        "\u0411\u0435\u043b\u044b\u0439 \u041a\u043b\u044e\u0447"
    ],
    "name:und_x_variant":[
        "Bely Klyuch",
        "Belyy Klyuch"
    ],
    "wof:name":"Belyy Klyuch",
    "wof:placetype":"locality"
},
  "geometry": {"coordinates":[45.47266,53.87785],"type":"Point"}
}