{
  "type": "Feature",
  "properties": {
    "gn:admin1_code":"33.0",
    "gn:asciiname":"Chuchalovy",
    "gn:country_code":"RU",
    "gn:dem":205,
    "gn:feature_class":"P",
    "gn:feature_code":"PPL",
    "gn:name":"Chuchalovy",
    "gn:population":0,
    "gn:timezone":"Europe/Kirov",
    "iso:country":"RU",
    "name:rus_x_preferred":[
        "\u0427\u0443\u0447\u0430\u043b\u043e\u0432\u044b"
    ],
    "name:und_x_variant":[
        "\u0427\u0443\u0447\u0430\u043b\u043e\u0432\u044b"
    ],
    "wof:name":"Chuchalovy",
    "wof:placetype":"locality"
},
  "geometry": {"coordinates":[49.38308,57.98759],"type":"Point"}
}