{
  "type": "Feature",
  "properties": {
    "gn:admin1_code":"30",
    "gn:asciiname":"Verkhnyaya Pakhta",
    "gn:country_code":"RU",
    "gn:dem":6,
    "gn:feature_class":"P",
    "gn:feature_code":"PPL",
    "gn:name":"Verkhnyaya Pakhta",
    "gn:population":0,
    "gn:timezone":"Asia/Vladivostok",
    "iso:country":"RU",
    "wof:name":"Verkhnyaya Pakhta",
    "wof:placetype":"locality"
},
  "geometry": {"coordinates":[139.73333,51.68333],"type":"Point"}
}