{
  "type": "Feature",
  "properties": {
    "gn:admin1_code":"17",
    "gn:admin2_code":"Gergebil'skiy Rayon",
    "gn:asciiname":"Maali",
    "gn:country_code":"RU",
    "gn:dem":993,
    "gn:feature_class":"P",
    "gn:feature_code":"PPL",
    "gn:name":"Maali",
    "gn:population":0,
    "gn:timezone":"Europe/Moscow",
    "iso:country":"RU",
    "name:eng_x_preferred":[
        "Maali"
    ],
    "name:nor_x_preferred":[
        "Maali"
    ],
    "name:rus_x_preferred":[
        "\u041c\u0430\u0430\u043b\u0438"
    ],
    "name:und_x_variant":[
        "\u041c\u0430\u0430\u043b\u0438",
        "Maali"
    ],
    "wof:name":"Maali",
    "wof:placetype":"locality"
},
  "geometry": {"coordinates":[46.92003,42.48688],"type":"Point"}
}