{
  "type": "Feature",
  "properties": {
    "gn:admin1_code":"60",
    "gn:asciiname":"Obryadikha",
    "gn:country_code":"RU",
    "gn:dem":109,
    "gn:feature_class":"P",
    "gn:feature_code":"PPL",
    "gn:name":"Obryadikha",
    "gn:population":0,
    "gn:timezone":"Europe/Moscow",
    "iso:country":"RU",
    "name:rus_x_preferred":[
        "\u041e\u0431\u0440\u044f\u0434\u0438\u0445\u0430"
    ],
    "wof:name":"Obryadikha",
    "wof:placetype":"locality"
},
  "geometry": {"coordinates":[29.07974,58.47264000000001],"type":"Point"}
}