{
  "type": "Feature",
  "properties": {
    "gn:admin1_code":"76",
    "gn:asciiname":"Lomintsevo",
    "gn:country_code":"RU",
    "gn:dem":199,
    "gn:feature_class":"P",
    "gn:feature_code":"PPL",
    "gn:name":"Lomintsevo",
    "gn:population":0,
    "gn:timezone":"Europe/Moscow",
    "iso:country":"RU",
    "name:rus_x_preferred":[
        "\u041b\u043e\u043c\u0438\u043d\u0446\u0435\u0432\u043e"
    ],
    "name:und_x_variant":[
        "Lomintsevskiy",
        "Lomintsevo"
    ],
    "wof:name":"Lomintsevo",
    "wof:placetype":"locality"
},
  "geometry": {"coordinates":[37.67208,54.01328],"type":"Point"}
}