{
  "type": "Feature",
  "properties": {
    "gn:admin1_code":"41",
    "gn:asciiname":"Puchkov",
    "gn:country_code":"RU",
    "gn:dem":173,
    "gn:feature_class":"P",
    "gn:feature_code":"PPL",
    "gn:name":"Puchkov",
    "gn:population":0,
    "gn:timezone":"Europe/Moscow",
    "iso:country":"RU",
    "name:rus_x_preferred":[
        "\u041f\u0443\u0447\u043a\u043e\u0432"
    ],
    "wof:name":"Puchkov",
    "wof:placetype":"locality"
},
  "geometry": {"coordinates":[35.5256,51.8762],"type":"Point"}
}