{
  "type": "Feature",
  "properties": {
    "gn:admin1_code":"25.0",
    "gn:asciiname":"Durnevo",
    "gn:country_code":"RU",
    "gn:dem":151,
    "gn:feature_class":"P",
    "gn:feature_code":"PPL",
    "gn:name":"Durn\u00ebvo",
    "gn:population":0,
    "gn:timezone":"Europe/Moscow",
    "iso:country":"RU",
    "name:rus_x_preferred":[
        "\u0414\u0443\u0440\u043d\u0451\u0432\u043e"
    ],
    "name:und_x_variant":[
        "Durn\u00ebvo"
    ],
    "wof:name":"Durnevo",
    "wof:placetype":"locality"
},
  "geometry": {"coordinates":[35.61816,53.73114],"type":"Point"}
}