{
  "type": "Feature",
  "properties": {
    "gn:admin1_code":"20",
    "gn:asciiname":"Novoilimsk",
    "gn:country_code":"RU",
    "gn:dem":392,
    "gn:feature_class":"P",
    "gn:feature_code":"PPL",
    "gn:name":"Novoilimsk",
    "gn:population":0,
    "gn:timezone":"Asia/Irkutsk",
    "iso:country":"RU",
    "name:rus_x_preferred":[
        "\u041d\u043e\u0432\u043e\u0438\u043b\u0438\u043c\u0441\u043a"
    ],
    "wof:name":"Novoilimsk",
    "wof:placetype":"locality"
},
  "geometry": {"coordinates":[103.6799,57.2914],"type":"Point"}
}