{
  "type": "Feature",
  "properties": {
    "gn:admin1_code":"61",
    "gn:asciiname":"Valuyevo",
    "gn:cc2":"RU",
    "gn:country_code":"RU",
    "gn:dem":51,
    "gn:feature_class":"P",
    "gn:feature_code":"PPL",
    "gn:name":"Valuyevo",
    "gn:population":0,
    "gn:timezone":"Europe/Moscow",
    "iso:country":"RU",
    "name:che_x_preferred":[
        "\u0412\u0430\u043b\u0443\u0435\u0432\u043e"
    ],
    "name:rus_x_preferred":[
        "\u0412\u0430\u043b\u0443\u0435\u0432\u043e"
    ],
    "name:tgk_x_preferred":[
        "\u0412\u0430\u043b\u0443\u0435\u0432\u043e"
    ],
    "name:und_x_variant":[
        "Valuyevskiy",
        "Valuyevo"
    ],
    "wof:name":"Valuyevo",
    "wof:placetype":"locality"
},
  "geometry": {"coordinates":[39.31944,47.45083],"type":"Point"}
}