{
  "type": "Feature",
  "properties": {
    "gn:admin1_code":"42",
    "gn:asciiname":"Putkelovo",
    "gn:country_code":"RU",
    "gn:dem":66,
    "gn:feature_class":"P",
    "gn:feature_code":"PPL",
    "gn:name":"Putkelovo",
    "gn:population":0,
    "gn:timezone":"Europe/Moscow",
    "iso:country":"RU",
    "name:fin_x_preferred":[
        "Putkela"
    ],
    "name:rus_x_preferred":[
        "\u041f\u0443\u0442\u043a\u0435\u043b\u043e\u0432\u043e"
    ],
    "wof:name":"Putkelovo",
    "wof:placetype":"locality"
},
  "geometry": {"coordinates":[30.51667,60.38333000000001],"type":"Point"}
}