{
  "type": "Feature",
  "properties": {
    "gn:admin1_code":"38",
    "gn:asciiname":"Sinegorsk",
    "gn:country_code":"RU",
    "gn:dem":83,
    "gn:feature_class":"P",
    "gn:feature_code":"PPL",
    "gn:name":"Sinegorsk",
    "gn:population":0,
    "gn:timezone":"Europe/Moscow",
    "iso:country":"RU",
    "name:eng_x_preferred":[
        "Sinegorsk"
    ],
    "name:nor_x_preferred":[
        "Sinegorsk"
    ],
    "name:rus_x_preferred":[
        "\u0421\u0438\u043d\u0435\u0433\u043e\u0440\u0441\u043a"
    ],
    "wof:name":"Sinegorsk",
    "wof:placetype":"locality"
},
  "geometry": {"coordinates":[38.34295,44.77111],"type":"Point"}
}