{
  "type": "Feature",
  "properties": {
    "gn:admin1_code":"55",
    "gn:asciiname":"Meshcheryakovka",
    "gn:country_code":"RU",
    "gn:dem":166,
    "gn:feature_class":"P",
    "gn:feature_code":"PPL",
    "gn:name":"Meshcheryakovka",
    "gn:population":0,
    "gn:timezone":"Asia/Yekaterinburg",
    "iso:country":"RU",
    "name:eng_x_preferred":[
        "Meshcheryakovka"
    ],
    "name:nor_x_preferred":[
        "Mesjtsjerjakovka"
    ],
    "name:rus_x_preferred":[
        "\u041c\u0435\u0449\u0435\u0440\u044f\u043a\u043e\u0432\u043a\u0430"
    ],
    "wof:name":"Meshcheryakovka",
    "wof:placetype":"locality"
},
  "geometry": {"coordinates":[55.27461,51.38816],"type":"Point"}
}