{
  "type": "Feature",
  "properties": {
    "gn:admin1_code":"62",
    "gn:asciiname":"Storozhevka",
    "gn:country_code":"RU",
    "gn:dem":92,
    "gn:feature_class":"P",
    "gn:feature_code":"PPL",
    "gn:name":"Storozhevka",
    "gn:population":0,
    "gn:timezone":"Europe/Moscow",
    "iso:country":"RU",
    "name:rus_x_preferred":[
        "\u0421\u0442\u043e\u0440\u043e\u0436\u0435\u0432\u043a\u0430"
    ],
    "wof:name":"Storozhevka",
    "wof:placetype":"locality"
},
  "geometry": {"coordinates":[42.0001,54.7714],"type":"Point"}
}