{
  "type": "Feature",
  "properties": {
    "gn:admin1_code":"80.0",
    "gn:asciiname":"Martelenki",
    "gn:country_code":"RU",
    "gn:dem":252,
    "gn:feature_class":"P",
    "gn:feature_code":"PPL",
    "gn:name":"Martelenki",
    "gn:population":0,
    "gn:timezone":"Europe/Samara",
    "iso:country":"RU",
    "name:rus_x_preferred":[
        "\u041c\u0430\u0440\u0442\u0435\u043b\u0435\u043d\u043a\u0438"
    ],
    "wof:name":"Martelenki",
    "wof:placetype":"locality"
},
  "geometry": {"coordinates":[53.363,58.2096],"type":"Point"}
}