{
  "type": "Feature",
  "properties": {
    "gn:admin1_code":"37",
    "gn:asciiname":"Mundor",
    "gn:country_code":"RU",
    "gn:dem":133,
    "gn:feature_class":"P",
    "gn:feature_code":"PPL",
    "gn:name":"Mundor",
    "gn:population":0,
    "gn:timezone":"Europe/Moscow",
    "iso:country":"RU",
    "name:rus_x_preferred":[
        "\u041c\u0443\u043d\u0434\u043e\u0440"
    ],
    "name:und_x_variant":[
        "\u041c\u0443\u043d\u0434\u043e\u0440"
    ],
    "wof:name":"Mundor",
    "wof:placetype":"locality"
},
  "geometry": {"coordinates":[46.0084,58.9282],"type":"Point"}
}