{
  "type": "Feature",
  "properties": {
    "gn:admin1_code":"56",
    "gn:asciiname":"Ognichnoye",
    "gn:country_code":"RU",
    "gn:dem":233,
    "gn:feature_class":"P",
    "gn:feature_code":"PPL",
    "gn:name":"Ognichnoye",
    "gn:population":0,
    "gn:timezone":"Europe/Moscow",
    "iso:country":"RU",
    "name:rus_x_preferred":[
        "\u041e\u0433\u043d\u0438\u0447\u043d\u043e\u0435"
    ],
    "wof:name":"Ognichnoye",
    "wof:placetype":"locality"
},
  "geometry": {"coordinates":[35.2427,52.5011],"type":"Point"}
}