{
  "type": "Feature",
  "properties": {
    "gn:admin1_code":"43",
    "gn:asciiname":"Orlovskiy",
    "gn:country_code":"RU",
    "gn:dem":156,
    "gn:feature_class":"P",
    "gn:feature_code":"PPL",
    "gn:name":"Orlovskiy",
    "gn:population":0,
    "gn:timezone":"Europe/Moscow",
    "iso:country":"RU",
    "name:rus_x_preferred":[
        "\u041e\u0440\u043b\u043e\u0432\u0441\u043a\u0438\u0439"
    ],
    "wof:name":"Orlovskiy",
    "wof:placetype":"locality"
},
  "geometry": {"coordinates":[40.53333,52.13333],"type":"Point"}
}