{
  "type": "Feature",
  "properties": {
    "gn:admin1_code":"93",
    "gn:asciiname":"Alentuy",
    "gn:country_code":"RU",
    "gn:dem":846,
    "gn:feature_class":"P",
    "gn:feature_code":"PPL",
    "gn:name":"Alentuy",
    "gn:population":0,
    "gn:timezone":"Asia/Chita",
    "iso:country":"RU",
    "name:nor_x_preferred":[
        "Alentuj"
    ],
    "name:rus_x_preferred":[
        "\u0410\u043b\u0435\u043d\u0442\u0443\u0439"
    ],
    "wof:name":"Alentuy",
    "wof:placetype":"locality"
},
  "geometry": {"coordinates":[110.78333000000001,51.41667],"type":"Point"}
}