{
  "type": "Feature",
  "properties": {
    "gn:admin1_code":"7.0",
    "gn:asciiname":"Malyy Baklaniy",
    "gn:cc2":"RU",
    "gn:country_code":"RU",
    "gn:dem":-27,
    "gn:feature_class":"P",
    "gn:feature_code":"PPL",
    "gn:name":"Malyy Baklaniy",
    "gn:population":0,
    "gn:timezone":"Europe/Astrakhan",
    "iso:country":"RU",
    "name:rus_x_preferred":[
        "\u041c\u0430\u043b\u044b\u0439 \u0411\u0430\u043a\u043b\u0430\u043d\u0438\u0439"
    ],
    "name:und_x_variant":[
        "Kononenko",
        "Malyy Baklaniy",
        "\u041c\u0430\u043b\u044b\u0439 \u0411\u0430\u043a\u043b\u0430\u043d\u0438\u0439"
    ],
    "wof:name":"Malyy Baklaniy",
    "wof:placetype":"locality"
},
  "geometry": {"coordinates":[48.21472,45.91028],"type":"Point"}
}