{
  "type": "Feature",
  "properties": {
    "gn:admin1_code":"73",
    "gn:asciiname":"Urguda",
    "gn:country_code":"RU",
    "gn:dem":104,
    "gn:feature_class":"P",
    "gn:feature_code":"PPL",
    "gn:name":"Urguda",
    "gn:population":0,
    "gn:timezone":"Europe/Moscow",
    "iso:country":"RU",
    "name:rus_x_preferred":[
        "\u0423\u0440\u0433\u0443\u0434\u0430"
    ],
    "name:und_x_variant":[
        "\u0423\u0440\u0433\u0443\u0434\u0430"
    ],
    "wof:name":"Urguda",
    "wof:placetype":"locality"
},
  "geometry": {"coordinates":[52.674,55.5739],"type":"Point"}
}