{
  "type": "Feature",
  "properties": {
    "gn:gn_country":"RU",
    "gn:gn_fcode":"PPL",
    "gn:gn_pop":2472,
    "gn:population":2472,
    "iso:country":"RU",
    "name:ara_x_preferred":[
        "\u0641\u064a\u0644\u064a\u0643\u0648\u0648\u0643\u062a\u064a\u0627\u0628\u0631\u0633\u0643\u064a\u064a"
    ],
    "name:ceb_x_preferred":[
        "Velikooktyabr'skiy"
    ],
    "name:che_x_preferred":[
        "\u0412\u0435\u043b\u0438\u043a\u043e\u043e\u043a\u0442\u044f\u0431\u0440\u044c\u0441\u043a\u0438\u0439"
    ],
    "name:eng_x_preferred":[
        "Velikooktyabr'skiy"
    ],
    "name:eng_x_variant":[
        "Velikooktyabrsky"
    ],
    "name:nor_x_preferred":[
        "Velikooktjabrskij"
    ],
    "name:pol_x_preferred":[
        "Wielikooktiabr\u00b4skij"
    ],
    "name:rus_x_preferred":[
        "\u0412\u0435\u043b\u0438\u043a\u043e\u043e\u043a\u0442\u044f\u0431\u0440\u044c\u0441\u043a\u0438\u0439"
    ],
    "name:srp_x_preferred":[
        "\u0412\u0435\u043b\u0438\u043a\u043e\u043e\u043a\u0442\u0458\u0430\u0431\u0440\u0441\u043a\u0438"
    ],
    "name:unk_x_variant":[
        "Velikiy Oktyabr\u2019"
    ],
    "qs_pg:aaroncc":"RU",
    "qs_pg:gn_country":"RU",
    "qs_pg:gn_fcode":"PPL",
    "qs_pg:gn_pop":2472,
    "qs_pg:name":"Velikooktyabr\u2019skiy",
    "qs_pg:photos_9r":0,
    "qs_pg:photos_sr":0,
    "qs_pg:pop_sr":4,
    "qs_pg:qs_pg_placetype":"locality",
    "wof:name":"Velikooktyabr\u2019skiy",
    "wof:placetype":"locality",
    "wof:population":2472
},
  "geometry": {"coordinates":[33.81595,57.43334],"type":"Point"}
}