{
  "type": "Feature",
  "properties": {
    "gn:admin1_code":"6",
    "gn:asciiname":"Khmelevskaya",
    "gn:country_code":"RU",
    "gn:dem":113,
    "gn:feature_class":"P",
    "gn:feature_code":"PPL",
    "gn:name":"Khmelevskaya",
    "gn:population":0,
    "gn:timezone":"Europe/Moscow",
    "iso:country":"RU",
    "name:rus_x_preferred":[
        "\u0425\u043c\u0435\u043b\u0435\u0432\u0441\u043a\u0430\u044f"
    ],
    "wof:name":"Khmelevskaya",
    "wof:placetype":"locality"
},
  "geometry": {"coordinates":[45.91088,61.46057],"type":"Point"}
}