{
  "type": "Feature",
  "properties": {
    "gn:admin1_code":"30",
    "gn:asciiname":"Aleksandro-Mikhaylovskoye",
    "gn:cc2":"RU",
    "gn:country_code":"RU",
    "gn:dem":92,
    "gn:feature_class":"P",
    "gn:feature_code":"PPL",
    "gn:name":"Aleksandro-Mikhaylovskoye",
    "gn:population":0,
    "gn:timezone":"Asia/Vladivostok",
    "iso:country":"RU",
    "name:und_x_variant":[
        "Alexandro-Mikhailovskoye",
        "Aleksandro-Mikhaylovskoye"
    ],
    "wof:name":"Aleksandro-Mikhaylovskoye",
    "wof:placetype":"locality"
},
  "geometry": {"coordinates":[135.58333000000002,47.85],"type":"Point"}
}