{
  "type": "Feature",
  "properties": {
    "gn:admin1_code":"61.0",
    "gn:asciiname":"Zernovoy",
    "gn:country_code":"RU",
    "gn:dem":70,
    "gn:feature_class":"P",
    "gn:feature_code":"PPL",
    "gn:name":"Zernovoy",
    "gn:population":0,
    "gn:timezone":"Europe/Moscow",
    "iso:country":"RU",
    "name:rus_x_preferred":[
        "\u0417\u0435\u0440\u043d\u043e\u0432\u043e\u0439"
    ],
    "wof:name":"Zernovoy",
    "wof:placetype":"locality"
},
  "geometry": {"coordinates":[40.2412,46.8358],"type":"Point"}
}