{
  "type": "Feature",
  "properties": {
    "gn:admin1_code":"51.0",
    "gn:asciiname":"Prudy",
    "gn:country_code":"RU",
    "gn:dem":98,
    "gn:feature_class":"P",
    "gn:feature_code":"PPL",
    "gn:name":"Prudy",
    "gn:population":0,
    "gn:timezone":"Europe/Moscow",
    "iso:country":"RU",
    "name:nor_x_preferred":[
        "Prudy"
    ],
    "name:rus_x_preferred":[
        "\u041f\u0440\u0443\u0434\u044b"
    ],
    "wof:name":"Prudy",
    "wof:placetype":"locality"
},
  "geometry": {"coordinates":[43.84927,56.09972],"type":"Point"}
}