{
  "type": "Feature",
  "properties": {
    "gn:admin1_code":"93",
    "gn:asciiname":"Matakan",
    "gn:country_code":"RU",
    "gn:dem":460,
    "gn:feature_class":"P",
    "gn:feature_code":"PPL",
    "gn:name":"Matakan",
    "gn:population":0,
    "gn:timezone":"Asia/Chita",
    "iso:country":"RU",
    "name:rus_x_preferred":[
        "\u041c\u0430\u0442\u0430\u043a\u0430\u043d"
    ],
    "name:und_x_variant":[
        "\u041c\u0430\u0442\u0430\u043a\u0430\u043d"
    ],
    "wof:name":"Matakan",
    "wof:placetype":"locality"
},
  "geometry": {"coordinates":[117.66076,52.22014],"type":"Point"}
}