{
  "type": "Feature",
  "properties": {
    "gn:country":"RU",
    "gn:fcode":"PPL",
    "gn:population":0,
    "iso:country":"RU",
    "name:eng_x_preferred":[
        "Ratovo"
    ],
    "name:nor_x_preferred":[
        "Ratovo"
    ],
    "name:rus_x_preferred":[
        "\u0420\u0430\u0442\u043e\u0432\u043e"
    ],
    "qs:name":"Ratovo",
    "qs:name_adm0":"Russia",
    "qs:name_adm1":"Nizhny Novgorod Oblast",
    "qs:photos":8,
    "qs:photos_1k":2,
    "qs:photos_9k":1,
    "qs:photos_9r":1,
    "qs:photos_all":8,
    "qs:photos_sr":1,
    "qs:placetype":"Town",
    "qs:pop_sr":"0",
    "wof:name":"Ratovo",
    "wof:placetype":"locality",
    "wof:population":0
},
  "geometry": {"coordinates":[46.16436,55.33293],"type":"Point"}
}