{
  "type": "Feature",
  "properties": {
    "gn:admin1_code":"46",
    "gn:asciiname":"Peregon",
    "gn:country_code":"RU",
    "gn:dem":183,
    "gn:feature_class":"P",
    "gn:feature_code":"PPL",
    "gn:name":"Peregon",
    "gn:population":0,
    "gn:timezone":"Europe/Moscow",
    "iso:country":"RU",
    "name:rus_x_preferred":[
        "\u041f\u0435\u0440\u0435\u0433\u043e\u043d"
    ],
    "wof:name":"Peregon",
    "wof:placetype":"locality"
},
  "geometry": {"coordinates":[42.4201,54.0703],"type":"Point"}
}