{
  "type": "Feature",
  "properties": {
    "gn:admin1_code":"61",
    "gn:asciiname":"Novorubashkin",
    "gn:country_code":"RU",
    "gn:dem":39,
    "gn:feature_class":"P",
    "gn:feature_code":"PPL",
    "gn:name":"Novorubashkin",
    "gn:population":0,
    "gn:timezone":"Europe/Moscow",
    "iso:country":"RU",
    "name:eng_x_preferred":[
        "Novorubashkin"
    ],
    "name:nor_x_preferred":[
        "Novorubasjkin"
    ],
    "name:rus_x_preferred":[
        "\u041d\u043e\u0432\u043e\u0440\u0443\u0431\u0430\u0448\u043a\u0438\u043d"
    ],
    "wof:name":"Novorubashkin",
    "wof:placetype":"locality"
},
  "geometry": {"coordinates":[42.55083,47.34639],"type":"Point"}
}