{
  "type": "Feature",
  "properties": {
    "gn:admin1_code":"88.0",
    "gn:asciiname":"Neznayka",
    "gn:country_code":"RU",
    "gn:dem":159,
    "gn:feature_class":"P",
    "gn:feature_code":"PPL",
    "gn:name":"Neznayka",
    "gn:population":0,
    "gn:timezone":"Europe/Moscow",
    "iso:country":"RU",
    "name:rus_x_preferred":[
        "\u041d\u0435\u0437\u043d\u0430\u0439\u043a\u0430"
    ],
    "name:und_x_variant":[
        "\u041d\u0435\u0437\u043d\u0430\u0439\u043a\u0430"
    ],
    "wof:name":"Neznayka",
    "wof:placetype":"locality"
},
  "geometry": {"coordinates":[40.21583,58.44315],"type":"Point"}
}