{
  "type": "Feature",
  "properties": {
    "gn:admin1_code":"37.0",
    "gn:asciiname":"Betelevo",
    "gn:country_code":"RU",
    "gn:dem":165,
    "gn:feature_class":"P",
    "gn:feature_code":"PPL",
    "gn:name":"Betel\u00ebvo",
    "gn:population":0,
    "gn:timezone":"Europe/Moscow",
    "iso:country":"RU",
    "name:nor_x_preferred":[
        "Beteljovo"
    ],
    "name:rus_x_preferred":[
        "\u0411\u0435\u0442\u0435\u043b\u0451\u0432\u043e"
    ],
    "name:und_x_variant":[
        "Bertelevo",
        "Betel\u00ebvo"
    ],
    "wof:name":"Betelevo",
    "wof:placetype":"locality"
},
  "geometry": {"coordinates":[42.89575,58.17726],"type":"Point"}
}