{
  "type": "Feature",
  "properties": {
    "gn:admin1_code":"61",
    "gn:asciiname":"Novostroyka",
    "gn:country_code":"RU",
    "gn:dem":97,
    "gn:feature_class":"P",
    "gn:feature_code":"PPL",
    "gn:name":"Novostroyka",
    "gn:population":0,
    "gn:timezone":"Europe/Moscow",
    "iso:country":"RU",
    "name:rus_x_preferred":[
        "\u041d\u043e\u0432\u043e\u0441\u0442\u0440\u043e\u0439\u043a\u0430"
    ],
    "wof:name":"Novostroyka",
    "wof:placetype":"locality"
},
  "geometry": {"coordinates":[40.75755,46.87274],"type":"Point"}
}