{
  "type": "Feature",
  "properties": {
    "gn:admin1_code":"76",
    "gn:asciiname":"Malyy Kon'",
    "gn:country_code":"RU",
    "gn:dem":199,
    "gn:feature_class":"P",
    "gn:feature_code":"PPL",
    "gn:name":"Malyy Kon\u2019",
    "gn:population":0,
    "gn:timezone":"Europe/Moscow",
    "iso:country":"RU",
    "name:rus_x_preferred":[
        "\u041c\u0430\u043b\u044b\u0439 \u041a\u043e\u043d\u044c"
    ],
    "name:und_x_variant":[
        "Malyy Kon\u2019"
    ],
    "wof:name":"Malyy Kon'",
    "wof:placetype":"locality"
},
  "geometry": {"coordinates":[37.01667,53.43333000000001],"type":"Point"}
}