{
  "type": "Feature",
  "properties": {
    "gn:admin1_code":"33",
    "gn:asciiname":"Nizhnyaya Sibir'",
    "gn:country_code":"RU",
    "gn:dem":200,
    "gn:feature_class":"P",
    "gn:feature_code":"PPL",
    "gn:name":"Nizhnyaya Sibir\u2019",
    "gn:population":0,
    "gn:timezone":"Europe/Kirov",
    "iso:country":"RU",
    "name:rus_x_preferred":[
        "\u041d\u0438\u0436\u043d\u044f\u044f \u0421\u0438\u0431\u0438\u0440\u044c"
    ],
    "name:und_x_variant":[
        "Nizhnyaya Sibir\u2019"
    ],
    "wof:name":"Nizhnyaya Sibir'",
    "wof:placetype":"locality"
},
  "geometry": {"coordinates":[51.35,57.81667],"type":"Point"}
}