{
  "type": "Feature",
  "properties": {
    "gn:admin1_code":"92",
    "gn:asciiname":"Saichik",
    "gn:cc2":"RU",
    "gn:country_code":"RU",
    "gn:dem":2,
    "gn:feature_class":"P",
    "gn:feature_code":"PPL",
    "gn:name":"Saichik",
    "gn:population":0,
    "gn:timezone":"Asia/Kamchatka",
    "iso:country":"RU",
    "name:rus_x_preferred":[
        "\u0421\u0430\u0438\u0447\u0438\u043a"
    ],
    "name:und_x_variant":[
        "Saychek",
        "Saichik"
    ],
    "wof:name":"Saichik",
    "wof:placetype":"locality"
},
  "geometry": {"coordinates":[155.71666999999999,55.81667],"type":"Point"}
}