{
  "type": "Feature",
  "properties": {
    "gn:admin1_code":"21.0",
    "gn:asciiname":"Maklakovo",
    "gn:country_code":"RU",
    "gn:dem":94,
    "gn:feature_class":"P",
    "gn:feature_code":"PPL",
    "gn:name":"Maklakovo",
    "gn:population":0,
    "gn:timezone":"Europe/Moscow",
    "iso:country":"RU",
    "name:rus_x_preferred":[
        "\u041c\u0430\u043a\u043b\u0430\u043a\u043e\u0432\u043e"
    ],
    "wof:name":"Maklakovo",
    "wof:placetype":"locality"
},
  "geometry": {"coordinates":[41.48699000000001,56.703],"type":"Point"}
}