{
  "type": "Feature",
  "properties": {
    "gn:admin1_code":"23",
    "gn:asciiname":"Svoboda",
    "gn:country_code":"RU",
    "gn:dem":38,
    "gn:feature_class":"P",
    "gn:feature_code":"PPL",
    "gn:name":"Svoboda",
    "gn:population":0,
    "gn:timezone":"Europe/Kaliningrad",
    "iso:country":"RU",
    "name:eng_x_preferred":[
        "Svoboda"
    ],
    "name:nor_x_preferred":[
        "Svoboda"
    ],
    "name:rus_x_preferred":[
        "\u0421\u0432\u043e\u0431\u043e\u0434\u0430"
    ],
    "name:und_x_variant":[
        "Yenishken",
        "Iyenishken",
        "J\u00e4nichen",
        "J\u00e4nischken",
        "Jaenischken",
        "Svoboda"
    ],
    "wof:name":"Svoboda",
    "wof:placetype":"locality"
},
  "geometry": {"coordinates":[21.73054,54.54469],"type":"Point"}
}