{
  "type": "Feature",
  "properties": {
    "gn:admin1_code":"52",
    "gn:asciiname":"Shershnevo",
    "gn:country_code":"RU",
    "gn:dem":70,
    "gn:feature_class":"P",
    "gn:feature_code":"PPL",
    "gn:name":"Shershn\u00ebvo",
    "gn:population":0,
    "gn:timezone":"Europe/Moscow",
    "iso:country":"RU",
    "name:rus_x_preferred":[
        "\u0428\u0435\u0440\u0448\u043d\u0451\u0432\u043e"
    ],
    "name:und_x_variant":[
        "Shershn\u00ebvo",
        "\u0428\u0435\u0440\u0448\u043d\u0451\u0432\u043e"
    ],
    "wof:name":"Shershnevo",
    "wof:placetype":"locality"
},
  "geometry": {"coordinates":[31.09213,57.04766],"type":"Point"}
}