{
  "type": "Feature",
  "properties": {
    "gn:admin1_code":"13",
    "gn:asciiname":"Pyl'noye",
    "gn:country_code":"RU",
    "gn:dem":403,
    "gn:feature_class":"P",
    "gn:feature_code":"PPL",
    "gn:name":"Pyl\u2019noye",
    "gn:population":0,
    "gn:timezone":"Asia/Yekaterinburg",
    "iso:country":"RU",
    "name:rus_x_preferred":[
        "\u041f\u044b\u043b\u044c\u043d\u043e\u0435"
    ],
    "name:und_x_variant":[
        "Pyl\u2019noye",
        "\u041f\u044b\u043b\u044c\u043d\u043e\u0435"
    ],
    "wof:name":"Pyl'noye",
    "wof:placetype":"locality"
},
  "geometry": {"coordinates":[59.387,53.3754],"type":"Point"}
}