{
  "type": "Feature",
  "properties": {
    "gn:admin1_code":"77",
    "gn:asciiname":"Grechnevo",
    "gn:country_code":"RU",
    "gn:dem":145,
    "gn:feature_class":"P",
    "gn:feature_code":"PPL",
    "gn:name":"Grechnevo",
    "gn:population":0,
    "gn:timezone":"Europe/Moscow",
    "iso:country":"RU",
    "name:rus_x_preferred":[
        "\u0413\u0440\u0435\u0447\u043d\u0435\u0432\u043e"
    ],
    "wof:name":"Grechnevo",
    "wof:placetype":"locality"
},
  "geometry": {"coordinates":[34.74714,58.21341],"type":"Point"}
}