{
  "type": "Feature",
  "properties": {
    "gn:admin1_code":"69",
    "gn:asciiname":"Red'ki",
    "gn:country_code":"RU",
    "gn:dem":214,
    "gn:feature_class":"P",
    "gn:feature_code":"PPL",
    "gn:name":"Red\u2019ki",
    "gn:population":0,
    "gn:timezone":"Europe/Moscow",
    "iso:country":"RU",
    "name:rus_x_preferred":[
        "\u0420\u0435\u0434\u044c\u043a\u0438"
    ],
    "name:und_x_variant":[
        "Red\u2019ki",
        "\u0420\u0435\u0434\u044c\u043a\u0438"
    ],
    "wof:name":"Red'ki",
    "wof:placetype":"locality"
},
  "geometry": {"coordinates":[31.05,54.96666999999999],"type":"Point"}
}