{
  "type": "Feature",
  "properties": {
    "gn:admin1_code":"67",
    "gn:asciiname":"Lyagoshi",
    "gn:country_code":"RU",
    "gn:dem":76,
    "gn:feature_class":"P",
    "gn:feature_code":"PPL",
    "gn:name":"Lyagoshi",
    "gn:population":0,
    "gn:timezone":"Europe/Saratov",
    "iso:country":"RU",
    "name:rus_x_preferred":[
        "\u041b\u044f\u0433\u043e\u0448\u0438"
    ],
    "wof:name":"Lyagoshi",
    "wof:placetype":"locality"
},
  "geometry": {"coordinates":[47.32273,52.3006],"type":"Point"}
}