{
  "type": "Feature",
  "properties": {
    "gn:admin1_code":"77",
    "gn:asciiname":"Bernikovo",
    "gn:country_code":"RU",
    "gn:dem":114,
    "gn:feature_class":"P",
    "gn:feature_code":"PPL",
    "gn:name":"Bernikovo",
    "gn:population":0,
    "gn:timezone":"Europe/Moscow",
    "iso:country":"RU",
    "name:rus_x_preferred":[
        "\u0411\u0435\u0440\u043d\u0438\u043a\u043e\u0432\u043e"
    ],
    "wof:name":"Bernikovo",
    "wof:placetype":"locality"
},
  "geometry": {"coordinates":[37.766,57.1053],"type":"Point"}
}