{
  "type": "Feature",
  "properties": {
    "gn:admin1_code":"56",
    "gn:asciiname":"Makarovskiy",
    "gn:country_code":"RU",
    "gn:dem":224,
    "gn:feature_class":"P",
    "gn:feature_code":"PPL",
    "gn:name":"Makarovskiy",
    "gn:population":0,
    "gn:timezone":"Europe/Moscow",
    "iso:country":"RU",
    "name:rus_x_preferred":[
        "\u041c\u0430\u043a\u0430\u0440\u043e\u0432\u0441\u043a\u0438\u0439"
    ],
    "name:und_x_variant":[
        "Markovskiy",
        "Makarovskiy",
        "\u041c\u0430\u043a\u0430\u0440\u043e\u0432\u0441\u043a\u0438\u0439"
    ],
    "wof:name":"Makarovskiy",
    "wof:placetype":"locality"
},
  "geometry": {"coordinates":[35.47117,53.14694],"type":"Point"}
}