{
  "type": "Feature",
  "properties": {
    "gn:admin1_code":"73",
    "gn:asciiname":"Novaya Salaus'",
    "gn:country_code":"RU",
    "gn:dem":86,
    "gn:feature_class":"P",
    "gn:feature_code":"PPL",
    "gn:name":"Novaya Salaus\u2019",
    "gn:population":0,
    "gn:timezone":"Europe/Moscow",
    "iso:country":"RU",
    "name:rus_x_preferred":[
        "\u041d\u043e\u0432\u0430\u044f \u0421\u0430\u043b\u0430\u0443\u0441\u044c"
    ],
    "name:und_x_variant":[
        "Novaya Salaus\u2019"
    ],
    "wof:name":"Novaya Salaus'",
    "wof:placetype":"locality"
},
  "geometry": {"coordinates":[50.3086,56.3736],"type":"Point"}
}