{
  "type": "Feature",
  "properties": {
    "gn:admin1_code":"63",
    "gn:asciiname":"Us-Kyuyele",
    "gn:cc2":"RU",
    "gn:country_code":"RU",
    "gn:dem":167,
    "gn:feature_class":"P",
    "gn:feature_code":"PPL",
    "gn:name":"Us-Kyuyele",
    "gn:population":0,
    "gn:timezone":"Asia/Yakutsk",
    "iso:country":"RU",
    "name:und_x_variant":[
        "Us-Kyuyelya",
        "Us-Kyuyele"
    ],
    "wof:name":"Us-Kyuyele",
    "wof:placetype":"locality"
},
  "geometry": {"coordinates":[131.15000000000001,62.35],"type":"Point"}
}