{
  "type": "Feature",
  "properties": {
    "gn:admin1_code":"33.0",
    "gn:asciiname":"Novyy",
    "gn:country_code":"RU",
    "gn:dem":128,
    "gn:feature_class":"P",
    "gn:feature_code":"PPL",
    "gn:name":"Novyy",
    "gn:population":0,
    "gn:timezone":"Europe/Kirov",
    "iso:country":"RU",
    "name:rus_x_preferred":[
        "\u041d\u043e\u0432\u044b\u0439"
    ],
    "name:und_x_variant":[
        "\u041d\u043e\u0432\u044b\u0439"
    ],
    "wof:name":"Novyy",
    "wof:placetype":"locality"
},
  "geometry": {"coordinates":[48.95065,57.54467],"type":"Point"}
}