{
  "type": "Feature",
  "properties": {
    "gn:admin1_code":"45.0",
    "gn:asciiname":"Orshanka",
    "gn:country_code":"RU",
    "gn:dem":151,
    "gn:feature_class":"P",
    "gn:feature_code":"PPL",
    "gn:name":"Orshanka",
    "gn:population":0,
    "gn:timezone":"Europe/Moscow",
    "iso:country":"RU",
    "name:rus_x_preferred":[
        "\u041e\u0440\u0448\u0430\u043d\u043a\u0430"
    ],
    "name:und_x_variant":[
        "\u041e\u0440\u0448\u0430\u043d\u043a\u0430"
    ],
    "wof:name":"Orshanka",
    "wof:placetype":"locality"
},
  "geometry": {"coordinates":[48.30333,56.69333],"type":"Point"}
}