{
  "type": "Feature",
  "properties": {
    "gn:admin1_code":"56",
    "gn:asciiname":"Panki",
    "gn:country_code":"RU",
    "gn:dem":262,
    "gn:feature_class":"P",
    "gn:feature_code":"PPL",
    "gn:name":"Panki",
    "gn:population":0,
    "gn:timezone":"Europe/Moscow",
    "iso:country":"RU",
    "name:bel_x_preferred":[
        "\u041f\u0430\u043d\u043a\u0456"
    ],
    "name:ceb_x_preferred":[
        "Panki"
    ],
    "name:rus_x_preferred":[
        "\u041f\u0430\u043d\u043a\u0438"
    ],
    "name:swe_x_preferred":[
        "Panki"
    ],
    "wof:name":"Panki",
    "wof:placetype":"locality"
},
  "geometry": {"coordinates":[37.42694,53.12944],"type":"Point"}
}