{
  "type": "Feature",
  "properties": {
    "gn:admin1_code":"28",
    "gn:asciiname":"Nigostrov",
    "gn:country_code":"RU",
    "gn:dem":54,
    "gn:feature_class":"P",
    "gn:feature_code":"PPL",
    "gn:name":"Nigostrov",
    "gn:population":0,
    "gn:timezone":"Europe/Moscow",
    "iso:country":"RU",
    "name:fin_x_preferred":[
        "Nikasaari"
    ],
    "wof:name":"Nigostrov",
    "wof:placetype":"locality"
},
  "geometry": {"coordinates":[34.29691,62.26951999999999],"type":"Point"}
}