{
  "type": "Feature",
  "properties": {
    "gn:admin1_code":"52",
    "gn:asciiname":"Mamayevshchina",
    "gn:country_code":"RU",
    "gn:dem":181,
    "gn:feature_class":"P",
    "gn:feature_code":"PPL",
    "gn:name":"Mamayevshchina",
    "gn:population":0,
    "gn:timezone":"Europe/Moscow",
    "iso:country":"RU",
    "name:rus_x_preferred":[
        "\u041c\u0430\u043c\u0430\u0435\u0432\u0449\u0438\u043d\u0430"
    ],
    "wof:name":"Mamayevshchina",
    "wof:placetype":"locality"
},
  "geometry": {"coordinates":[32.7113,57.6941],"type":"Point"}
}