{
  "type": "Feature",
  "properties": {
    "gn:admin1_code":"21",
    "gn:asciiname":"Golyakovo",
    "gn:country_code":"RU",
    "gn:dem":117,
    "gn:feature_class":"P",
    "gn:feature_code":"PPL",
    "gn:name":"Golyakovo",
    "gn:population":0,
    "gn:timezone":"Europe/Moscow",
    "iso:country":"RU",
    "name:rus_x_preferred":[
        "\u0413\u043e\u043b\u044f\u043a\u043e\u0432\u043e"
    ],
    "wof:name":"Golyakovo",
    "wof:placetype":"locality"
},
  "geometry": {"coordinates":[40.98325,56.86351],"type":"Point"}
}