{
  "type": "Feature",
  "properties": {
    "gn:admin1_code":"90.0",
    "gn:asciiname":"Durnyata",
    "gn:country_code":"RU",
    "gn:dem":156,
    "gn:feature_class":"P",
    "gn:feature_code":"PPL",
    "gn:name":"Durnyata",
    "gn:population":0,
    "gn:timezone":"Asia/Yekaterinburg",
    "iso:country":"RU",
    "name:nor_x_preferred":[
        "Durnjata"
    ],
    "name:rus_x_preferred":[
        "\u0414\u0443\u0440\u043d\u044f\u0442\u0430"
    ],
    "wof:name":"Durnyata",
    "wof:placetype":"locality"
},
  "geometry": {"coordinates":[56.9503,58.7714],"type":"Point"}
}