{
  "type": "Feature",
  "properties": {
    "gn:admin1_code":"91.0",
    "gn:asciiname":"Bogdanovka",
    "gn:country_code":"RU",
    "gn:dem":322,
    "gn:feature_class":"P",
    "gn:feature_code":"PPL",
    "gn:name":"Bogdanovka",
    "gn:population":0,
    "gn:timezone":"Asia/Krasnoyarsk",
    "iso:country":"RU",
    "name:rus_x_preferred":[
        "\u0411\u043e\u0433\u0434\u0430\u043d\u043e\u0432\u043a\u0430"
    ],
    "wof:name":"Bogdanovka",
    "wof:placetype":"locality"
},
  "geometry": {"coordinates":[95.89306000000001,56.46056],"type":"Point"}
}