{
  "type": "Feature",
  "properties": {
    "gn:admin1_code":"38",
    "gn:asciiname":"Tserkovnyy",
    "gn:cc2":"RU",
    "gn:country_code":"RU",
    "gn:dem":126,
    "gn:feature_class":"P",
    "gn:feature_code":"PPL",
    "gn:name":"Tserkovnyy",
    "gn:population":0,
    "gn:timezone":"Europe/Moscow",
    "iso:country":"RU",
    "name:und_x_variant":[
        "Tserkovny",
        "Tserkovnyy"
    ],
    "wof:name":"Tserkovnyy",
    "wof:placetype":"locality"
},
  "geometry": {"coordinates":[38.28889,44.41472],"type":"Point"}
}