{
  "type": "Feature",
  "properties": {
    "gn:admin1_code":"90.0",
    "gn:asciiname":"Vil'-Zhukova",
    "gn:country_code":"RU",
    "gn:dem":174,
    "gn:feature_class":"P",
    "gn:feature_code":"PPL",
    "gn:name":"Vil\u2019-Zhukova",
    "gn:population":0,
    "gn:timezone":"Asia/Yekaterinburg",
    "iso:country":"RU",
    "name:rus_x_preferred":[
        "\u0412\u0438\u043b\u044c-\u0416\u0443\u043a\u043e\u0432\u0430"
    ],
    "name:und_x_variant":[
        "Vil\u2019-Zhukova"
    ],
    "wof:name":"Vil'-Zhukova",
    "wof:placetype":"locality"
},
  "geometry": {"coordinates":[54.2382,58.9767],"type":"Point"}
}