{
  "type": "Feature",
  "properties": {
    "gn:admin1_code":"76",
    "gn:asciiname":"Zakhar'inskiye Vyselki",
    "gn:country_code":"RU",
    "gn:dem":176,
    "gn:feature_class":"P",
    "gn:feature_code":"PPL",
    "gn:name":"Zakhar\u2019inskiye Vyselki",
    "gn:population":0,
    "gn:timezone":"Europe/Moscow",
    "iso:country":"RU",
    "wof:name":"Zakhar'inskiye Vyselki",
    "wof:placetype":"locality"
},
  "geometry": {"coordinates":[37.91667,54.63333000000001],"type":"Point"}
}