{
  "type": "Feature",
  "properties": {
    "gn:admin1_code":"9.0",
    "gn:asciiname":"Cheremoshnoye",
    "gn:country_code":"RU",
    "gn:dem":156,
    "gn:feature_class":"P",
    "gn:feature_code":"PPL",
    "gn:name":"Cheremoshnoye",
    "gn:population":0,
    "gn:timezone":"Europe/Moscow",
    "iso:country":"RU",
    "name:rus_x_preferred":[
        "\u0427\u0435\u0440\u0451\u043c\u043e\u0448\u043d\u043e\u0435"
    ],
    "name:und_x_variant":[
        "Cher\u00ebmoshnoye",
        "\u0427\u0435\u0440\u0451\u043c\u043e\u0448\u043d\u043e\u0435",
        "Cheremoshnoye",
        "\u0427\u0435\u0440\u0435\u043c\u043e\u0448\u043d\u043e\u0435"
    ],
    "wof:name":"Cheremoshnoye",
    "wof:placetype":"locality"
},
  "geometry": {"coordinates":[36.49808,50.38852],"type":"Point"}
}