{
  "type": "Feature",
  "properties": {
    "gn:admin1_code":"51",
    "gn:asciiname":"Rylovo",
    "gn:country_code":"RU",
    "gn:dem":203,
    "gn:feature_class":"P",
    "gn:feature_code":"PPL",
    "gn:name":"Rylovo",
    "gn:population":0,
    "gn:timezone":"Europe/Moscow",
    "iso:country":"RU",
    "name:rus_x_preferred":[
        "\u0420\u044b\u043b\u043e\u0432\u043e"
    ],
    "wof:name":"Rylovo",
    "wof:placetype":"locality"
},
  "geometry": {"coordinates":[42.8125,55.7663],"type":"Point"}
}