{
  "type": "Feature",
  "properties": {
    "gn:admin1_code":"42",
    "gn:asciiname":"Zapovednoye",
    "gn:cc2":"RU",
    "gn:country_code":"RU",
    "gn:dem":16,
    "gn:feature_class":"P",
    "gn:feature_code":"PPL",
    "gn:name":"Zapovednoye",
    "gn:population":0,
    "gn:timezone":"Europe/Moscow",
    "iso:country":"RU",
    "name:fin_x_preferred":[
        "Vaskela"
    ],
    "wof:name":"Zapovednoye",
    "wof:placetype":"locality"
},
  "geometry": {"coordinates":[30.45994,60.55998],"type":"Point"}
}