{
  "type": "Feature",
  "properties": {
    "gn:admin1_code":"56",
    "gn:asciiname":"Prostor",
    "gn:country_code":"RU",
    "gn:dem":254,
    "gn:feature_class":"P",
    "gn:feature_code":"PPL",
    "gn:name":"Prostor",
    "gn:population":0,
    "gn:timezone":"Europe/Moscow",
    "iso:country":"RU",
    "name:rus_x_preferred":[
        "\u041f\u0440\u043e\u0441\u0442\u043e\u0440"
    ],
    "name:und_x_variant":[
        "\u041f\u0440\u043e\u0441\u0442\u043e\u0440"
    ],
    "wof:name":"Prostor",
    "wof:placetype":"locality"
},
  "geometry": {"coordinates":[37.78733,52.82999],"type":"Point"}
}