{
  "type": "Feature",
  "properties": {
    "gn:admin1_code":"65",
    "gn:asciiname":"Proskurnya",
    "gn:country_code":"RU",
    "gn:dem":99,
    "gn:feature_class":"P",
    "gn:feature_code":"PPL",
    "gn:name":"Proskurnya",
    "gn:population":0,
    "gn:timezone":"Europe/Samara",
    "iso:country":"RU",
    "name:rus_x_preferred":[
        "\u041f\u0440\u043e\u0441\u043a\u0443\u0440\u043d\u044f"
    ],
    "name:und_x_variant":[
        "\u041f\u0440\u043e\u0441\u043a\u0443\u0440\u043d\u044f"
    ],
    "wof:name":"Proskurnya",
    "wof:placetype":"locality"
},
  "geometry": {"coordinates":[50.43333,52.13333],"type":"Point"}
}