{
  "type": "Feature",
  "properties": {
    "gn:admin1_code":"31",
    "gn:asciiname":"Tisin",
    "gn:country_code":"RU",
    "gn:dem":673,
    "gn:feature_class":"P",
    "gn:feature_code":"PPL",
    "gn:name":"Tisin",
    "gn:population":0,
    "gn:timezone":"Asia/Krasnoyarsk",
    "iso:country":"RU",
    "wof:name":"Tisin",
    "wof:placetype":"locality"
},
  "geometry": {"coordinates":[90.03348000000003,54.28061999999999],"type":"Point"}
}