{
  "type": "Feature",
  "properties": {
    "gn:admin1_code":"25.0",
    "gn:asciiname":"Glushonki",
    "gn:country_code":"RU",
    "gn:dem":208,
    "gn:feature_class":"P",
    "gn:feature_code":"PPL",
    "gn:name":"Glushonki",
    "gn:population":0,
    "gn:timezone":"Europe/Moscow",
    "iso:country":"RU",
    "wof:name":"Glushonki",
    "wof:placetype":"locality"
},
  "geometry": {"coordinates":[36.82023,54.37779000000001],"type":"Point"}
}