{
  "type": "Feature",
  "properties": {
    "gn:admin1_code":"45",
    "gn:asciiname":"Sosnovo",
    "gn:country_code":"RU",
    "gn:dem":95,
    "gn:feature_class":"P",
    "gn:feature_code":"PPL",
    "gn:name":"Sosnovo",
    "gn:population":0,
    "gn:timezone":"Europe/Moscow",
    "iso:country":"RU",
    "name:rus_x_preferred":[
        "\u0421\u043e\u0441\u043d\u043e\u0432\u043e"
    ],
    "name:und_x_variant":[
        "\u0421\u043e\u0441\u043d\u043e\u0432\u043e"
    ],
    "wof:name":"Sosnovo",
    "wof:placetype":"locality"
},
  "geometry": {"coordinates":[47.8813,56.69116999999999],"type":"Point"}
}