{
  "type": "Feature",
  "properties": {
    "gn:admin1_code":"88",
    "gn:asciiname":"Kozarka",
    "gn:country_code":"RU",
    "gn:dem":115,
    "gn:feature_class":"P",
    "gn:feature_code":"PPL",
    "gn:name":"Kozarka",
    "gn:population":0,
    "gn:timezone":"Europe/Moscow",
    "iso:country":"RU",
    "name:rus_x_preferred":[
        "\u041a\u043e\u0437\u0430\u0440\u043a\u0430"
    ],
    "wof:name":"Kozarka",
    "wof:placetype":"locality"
},
  "geometry": {"coordinates":[39.26302,57.11721],"type":"Point"}
}