{
  "type": "Feature",
  "properties": {
    "gn:admin1_code":"52",
    "gn:asciiname":"Lesnaya",
    "gn:country_code":"RU",
    "gn:dem":29,
    "gn:feature_class":"P",
    "gn:feature_code":"PPL",
    "gn:name":"Lesnaya",
    "gn:population":0,
    "gn:timezone":"Europe/Moscow",
    "iso:country":"RU",
    "name:eng_x_preferred":[
        "Lesnaya"
    ],
    "name:nor_x_preferred":[
        "Lesnaja"
    ],
    "name:rus_x_preferred":[
        "\u041b\u0435\u0441\u043d\u0430\u044f"
    ],
    "name:und_x_variant":[
        "Torfopodstilochnaya",
        "Gryaznyye Kharchevni",
        "\u041b\u0435\u0441\u043d\u0430\u044f",
        "Lesnaya"
    ],
    "wof:name":"Lesnaya",
    "wof:placetype":"locality"
},
  "geometry": {"coordinates":[30.88733,58.30143],"type":"Point"}
}