{
  "type": "Feature",
  "properties": {
    "gn:admin1_code":"61",
    "gn:asciiname":"Verkhne-Kol'tsov",
    "gn:country_code":"RU",
    "gn:dem":83,
    "gn:feature_class":"P",
    "gn:feature_code":"PPL",
    "gn:name":"Verkhne-Kol\u2019tsov",
    "gn:population":0,
    "gn:timezone":"Europe/Moscow",
    "iso:country":"RU",
    "name:und_x_variant":[
        "Verkhniy Kol\u2019tsov",
        "Verkhne-Kol\u2019tsov"
    ],
    "wof:name":"Verkhne-Kol'tsov",
    "wof:placetype":"locality"
},
  "geometry": {"coordinates":[41.33434000000001,48.03879000000001],"type":"Point"}
}