{
  "type": "Feature",
  "properties": {
    "gn:admin1_code":"38",
    "gn:asciiname":"Trudovaya Armeniya",
    "gn:country_code":"RU",
    "gn:dem":4,
    "gn:feature_class":"P",
    "gn:feature_code":"PPL",
    "gn:name":"Trudovaya Armeniya",
    "gn:population":0,
    "gn:timezone":"Europe/Moscow",
    "iso:country":"RU",
    "name:rus_x_preferred":[
        "\u0422\u0440\u0443\u0434\u043e\u0432\u0430\u044f \u0410\u0440\u043c\u0435\u043d\u0438\u044f"
    ],
    "wof:name":"Trudovaya Armeniya",
    "wof:placetype":"locality"
},
  "geometry": {"coordinates":[38.84421,46.17819],"type":"Point"}
}