{
  "type": "Feature",
  "properties": {
    "gn:admin1_code":"8.0",
    "gn:asciiname":"Bayguzino",
    "gn:country_code":"RU",
    "gn:dem":180,
    "gn:feature_class":"P",
    "gn:feature_code":"PPL",
    "gn:name":"Bayguzino",
    "gn:population":0,
    "gn:timezone":"Asia/Yekaterinburg",
    "iso:country":"RU",
    "name:eng_x_preferred":[
        "Bayguzino"
    ],
    "name:nor_x_preferred":[
        "Bajguzino"
    ],
    "name:rus_x_preferred":[
        "\u0411\u0430\u0439\u0433\u0443\u0437\u0438\u043d\u043e"
    ],
    "name:und_x_variant":[
        "\u0411\u0430\u0439\u0433\u0443\u0437\u0438\u043d\u043e",
        "Bayguzino"
    ],
    "wof:name":"Bayguzino",
    "wof:placetype":"locality"
},
  "geometry": {"coordinates":[56.1549,53.4284],"type":"Point"}
}