{
  "type": "Feature",
  "properties": {
    "gn:admin1_code":"9",
    "gn:asciiname":"Gryaznoye",
    "gn:country_code":"RU",
    "gn:dem":196,
    "gn:feature_class":"P",
    "gn:feature_code":"PPL",
    "gn:name":"Gryaznoye",
    "gn:population":0,
    "gn:timezone":"Europe/Moscow",
    "iso:country":"RU",
    "name:eng_x_preferred":[
        "Gryaznoye"
    ],
    "name:nor_x_preferred":[
        "Grjaznoje"
    ],
    "name:rus_x_preferred":[
        "\u0413\u0440\u044f\u0437\u043d\u043e\u0435"
    ],
    "name:und_x_variant":[
        "Greznoye"
    ],
    "wof:name":"Gryaznoye",
    "wof:placetype":"locality"
},
  "geometry": {"coordinates":[36.52065,50.9942],"type":"Point"}
}