{
  "type": "Feature",
  "properties": {
    "gn:admin1_code":"42",
    "gn:asciiname":"Khlupino",
    "gn:country_code":"RU",
    "gn:dem":72,
    "gn:feature_class":"P",
    "gn:feature_code":"PPL",
    "gn:name":"Khlupino",
    "gn:population":0,
    "gn:timezone":"Europe/Moscow",
    "iso:country":"RU",
    "name:rus_x_preferred":[
        "\u0425\u043b\u0443\u043f\u0438\u043d\u043e"
    ],
    "name:und_x_variant":[
        "\u0425\u043b\u0443\u043f\u0438\u043d\u043e"
    ],
    "wof:name":"Khlupino",
    "wof:placetype":"locality"
},
  "geometry": {"coordinates":[30.37453,58.7811],"type":"Point"}
}