{
  "type": "Feature",
  "properties": {
    "gn:admin1_code":"77",
    "gn:asciiname":"Vasil'ki",
    "gn:country_code":"RU",
    "gn:dem":159,
    "gn:feature_class":"P",
    "gn:feature_code":"PPL",
    "gn:name":"Vasil\u2019ki",
    "gn:population":0,
    "gn:timezone":"Europe/Moscow",
    "iso:country":"RU",
    "name:rus_x_preferred":[
        "\u0412\u0430\u0441\u0438\u043b\u044c\u043a\u0438"
    ],
    "name:und_x_variant":[
        "Vasil\u2019ki",
        "\u0412\u0430\u0441\u0438\u043b\u044c\u043a\u0438"
    ],
    "wof:name":"Vasil'ki",
    "wof:placetype":"locality"
},
  "geometry": {"coordinates":[36.291,57.3201],"type":"Point"}
}