{
  "type": "Feature",
  "properties": {
    "gn:admin1_code":"84",
    "gn:asciiname":"Gusevka",
    "gn:country_code":"RU",
    "gn:dem":78,
    "gn:feature_class":"P",
    "gn:feature_code":"PPL",
    "gn:name":"Gusevka",
    "gn:population":0,
    "gn:timezone":"Europe/Volgograd",
    "iso:country":"RU",
    "name:eng_x_preferred":[
        "Gusevka"
    ],
    "name:nor_x_preferred":[
        "Gusevka"
    ],
    "name:rus_x_preferred":[
        "\u0413\u0443\u0441\u0435\u0432\u043a\u0430"
    ],
    "name:und_x_variant":[
        "Gusevko"
    ],
    "wof:name":"Gusevka",
    "wof:placetype":"locality"
},
  "geometry": {"coordinates":[44.68832,49.90906],"type":"Point"}
}