{
  "type": "Feature",
  "properties": {
    "gn:admin1_code":"4",
    "gn:asciiname":"Druzhba",
    "gn:country_code":"RU",
    "gn:dem":208,
    "gn:feature_class":"P",
    "gn:feature_code":"PPL",
    "gn:name":"Druzhba",
    "gn:population":0,
    "gn:timezone":"Asia/Barnaul",
    "iso:country":"RU",
    "name:rus_x_preferred":[
        "\u0414\u0440\u0443\u0436\u0431\u0430"
    ],
    "wof:name":"Druzhba",
    "wof:placetype":"locality"
},
  "geometry": {"coordinates":[83.05710000000001,52.6915],"type":"Point"}
}