{
  "type": "Feature",
  "properties": {
    "gn:admin1_code":"1.0",
    "gn:asciiname":"Rud",
    "gn:country_code":"RU",
    "gn:dem":328,
    "gn:feature_class":"P",
    "gn:feature_code":"PPL",
    "gn:name":"Rud",
    "gn:population":0,
    "gn:timezone":"Europe/Moscow",
    "iso:country":"RU",
    "name:aze_x_preferred":[
        "Rud"
    ],
    "name:rus_x_preferred":[
        "\u0420\u0443\u0434"
    ],
    "wof:name":"Rud",
    "wof:placetype":"locality"
},
  "geometry": {"coordinates":[39.97667,44.35639000000001],"type":"Point"}
}