{
  "type": "Feature",
  "properties": {
    "gn:admin1_code":"85",
    "gn:asciiname":"Zimnitsa",
    "gn:country_code":"RU",
    "gn:dem":169,
    "gn:feature_class":"P",
    "gn:feature_code":"PPL",
    "gn:name":"Zimnitsa",
    "gn:population":0,
    "gn:timezone":"Europe/Moscow",
    "iso:country":"RU",
    "name:rus_x_preferred":[
        "\u0417\u0438\u043c\u043d\u0438\u0446\u0430"
    ],
    "wof:name":"Zimnitsa",
    "wof:placetype":"locality"
},
  "geometry": {"coordinates":[39.8803,59.9424],"type":"Point"}
}