{
  "type": "Feature",
  "properties": {
    "gn:admin1_code":"61",
    "gn:asciiname":"Zagor'ye",
    "gn:country_code":"RU",
    "gn:dem":64,
    "gn:feature_class":"P",
    "gn:feature_code":"PPL",
    "gn:name":"Zagor\u2019ye",
    "gn:population":0,
    "gn:timezone":"Europe/Moscow",
    "iso:country":"RU",
    "name:rus_x_preferred":[
        "\u0417\u0430\u0433\u043e\u0440\u044c\u0435"
    ],
    "name:und_x_variant":[
        "Zagor\u2019ye",
        "\u0417\u0430\u0433\u043e\u0440\u044c\u0435"
    ],
    "wof:name":"Zagor'ye",
    "wof:placetype":"locality"
},
  "geometry": {"coordinates":[41.2571,46.5719],"type":"Point"}
}