{
  "type": "Feature",
  "properties": {
    "gn:admin1_code":"72",
    "gn:asciiname":"Otkhozheye",
    "gn:country_code":"RU",
    "gn:dem":177,
    "gn:feature_class":"P",
    "gn:feature_code":"PPL",
    "gn:name":"Otkhozheye",
    "gn:population":0,
    "gn:timezone":"Europe/Moscow",
    "iso:country":"RU",
    "name:eng_x_preferred":[
        "Otkhozheye"
    ],
    "name:nor_x_preferred":[
        "Otkhozjeje"
    ],
    "name:rus_x_preferred":[
        "\u041e\u0442\u0445\u043e\u0436\u0435\u0435"
    ],
    "wof:name":"Otkhozheye",
    "wof:placetype":"locality"
},
  "geometry": {"coordinates":[42.08139,52.06711],"type":"Point"}
}