{
  "type": "Feature",
  "properties": {
    "gn:admin1_code":"38.0",
    "gn:asciiname":"Nepil'",
    "gn:country_code":"RU",
    "gn:dem":35,
    "gn:feature_class":"P",
    "gn:feature_code":"PPL",
    "gn:name":"Nepil\u2019",
    "gn:population":0,
    "gn:timezone":"Europe/Moscow",
    "iso:country":"RU",
    "name:rus_x_preferred":[
        "\u041d\u0435\u043f\u0438\u043b\u044c"
    ],
    "name:und_x_variant":[
        "Nepil\u2019",
        "\u041d\u0435\u043f\u0438\u043b\u044c"
    ],
    "wof:name":"Nepil'",
    "wof:placetype":"locality"
},
  "geometry": {"coordinates":[37.74179,45.05346],"type":"Point"}
}