{
  "type": "Feature",
  "properties": {
    "gn:admin1_code":"85",
    "gn:asciiname":"Pakhtusovo",
    "gn:country_code":"RU",
    "gn:dem":179,
    "gn:feature_class":"P",
    "gn:feature_code":"PPL",
    "gn:name":"Pakhtusovo",
    "gn:population":0,
    "gn:timezone":"Europe/Moscow",
    "iso:country":"RU",
    "name:eng_x_preferred":[
        "Pakhtusovo"
    ],
    "name:nor_x_preferred":[
        "Pakhtusovo"
    ],
    "name:rus_x_preferred":[
        "\u041f\u0430\u0445\u0442\u0443\u0441\u043e\u0432\u043e"
    ],
    "name:und_x_variant":[
        "Pakhtusova"
    ],
    "wof:name":"Pakhtusovo",
    "wof:placetype":"locality"
},
  "geometry": {"coordinates":[42.27369,59.96491],"type":"Point"}
}