{
  "type": "Feature",
  "properties": {
    "gn:admin1_code":"71",
    "gn:asciiname":"Sergulovka",
    "gn:country_code":"RU",
    "gn:dem":139,
    "gn:feature_class":"P",
    "gn:feature_code":"PPL",
    "gn:name":"Sergulovka",
    "gn:population":0,
    "gn:timezone":"Asia/Yekaterinburg",
    "iso:country":"RU",
    "name:eng_x_preferred":[
        "Sergulovka"
    ],
    "name:nor_x_preferred":[
        "Sergulovka"
    ],
    "name:rus_x_preferred":[
        "\u0421\u0435\u0440\u0433\u0443\u043b\u043e\u0432\u043a\u0430"
    ],
    "name:und_x_variant":[
        "Sergunovka",
        "\u0421\u0435\u0440\u0433\u0443\u043b\u043e\u0432\u043a\u0430",
        "Sergulovka"
    ],
    "wof:name":"Sergulovka",
    "wof:placetype":"locality"
},
  "geometry": {"coordinates":[62.2752,56.9165],"type":"Point"}
}