{
  "type": "Feature",
  "properties": {
    "gn:admin1_code":"84",
    "gn:asciiname":"Zhukovskiy",
    "gn:country_code":"RU",
    "gn:dem":112,
    "gn:feature_class":"P",
    "gn:feature_code":"PPL",
    "gn:name":"Zhukovskiy",
    "gn:population":0,
    "gn:timezone":"Europe/Volgograd",
    "iso:country":"RU",
    "name:rus_x_preferred":[
        "\u0416\u0443\u043a\u043e\u0432\u0441\u043a\u0438\u0439"
    ],
    "wof:name":"Zhukovskiy",
    "wof:placetype":"locality"
},
  "geometry": {"coordinates":[42.7845,50.0041],"type":"Point"}
}