{
  "type": "Feature",
  "properties": {
    "gn:admin1_code":"41",
    "gn:asciiname":"Otruba",
    "gn:country_code":"RU",
    "gn:dem":142,
    "gn:feature_class":"P",
    "gn:feature_code":"PPL",
    "gn:name":"Otruba",
    "gn:population":0,
    "gn:timezone":"Europe/Moscow",
    "iso:country":"RU",
    "name:rus_x_preferred":[
        "\u041e\u0442\u0440\u0443\u0431\u0430"
    ],
    "wof:name":"Otruba",
    "wof:placetype":"locality"
},
  "geometry": {"coordinates":[34.4819,51.3564],"type":"Point"}
}