{
  "type": "Feature",
  "properties": {
    "gn:admin1_code":"13",
    "gn:asciiname":"Argazi",
    "gn:country_code":"RU",
    "gn:dem":301,
    "gn:feature_class":"P",
    "gn:feature_code":"PPL",
    "gn:name":"Argazi",
    "gn:population":0,
    "gn:timezone":"Asia/Yekaterinburg",
    "iso:country":"RU",
    "name:nor_x_preferred":[
        "Argazi"
    ],
    "name:rus_x_preferred":[
        "\u0410\u0440\u0433\u0430\u0437\u0438"
    ],
    "wof:name":"Argazi",
    "wof:placetype":"locality"
},
  "geometry": {"coordinates":[60.4324,55.3577],"type":"Point"}
}