{
  "type": "Feature",
  "properties": {
    "gn:admin1_code":"77",
    "gn:asciiname":"Bobyl'shchina",
    "gn:country_code":"RU",
    "gn:dem":190,
    "gn:feature_class":"P",
    "gn:feature_code":"PPL",
    "gn:name":"Bobyl\u2019shchina",
    "gn:population":0,
    "gn:timezone":"Europe/Moscow",
    "iso:country":"RU",
    "name:nor_x_preferred":[
        "Babylysjtsjina"
    ],
    "name:rus_x_preferred":[
        "\u0411o\u0431\u044b\u043b\u044c\u0449\u0438\u043d\u0430"
    ],
    "name:und_x_variant":[
        "Babylyshchina",
        "Bobyl\u2019shchina"
    ],
    "wof:name":"Bobyl'shchina",
    "wof:placetype":"locality"
},
  "geometry": {"coordinates":[32.21223,56.04161],"type":"Point"}
}