{
  "type": "Feature",
  "properties": {
    "gn:admin1_code":"77",
    "gn:asciiname":"Protiv'ye",
    "gn:country_code":"RU",
    "gn:dem":106,
    "gn:feature_class":"P",
    "gn:feature_code":"PPL",
    "gn:name":"Protiv\u2019ye",
    "gn:population":0,
    "gn:timezone":"Europe/Moscow",
    "iso:country":"RU",
    "name:eng_x_preferred":[
        "Protiv'ye"
    ],
    "name:nor_x_preferred":[
        "Protivje"
    ],
    "name:rus_x_preferred":[
        "\u041f\u0440\u043e\u0442\u0438\u0432\u044c\u0435"
    ],
    "name:und_x_variant":[
        "Protiv\u2019ye"
    ],
    "wof:name":"Protiv'ye",
    "wof:placetype":"locality"
},
  "geometry": {"coordinates":[37.53308,58.50994],"type":"Point"}
}