{
  "type": "Feature",
  "properties": {
    "gn:admin1_code":"67.0",
    "gn:asciiname":"Raskovo",
    "gn:country_code":"RU",
    "gn:dem":81,
    "gn:feature_class":"P",
    "gn:feature_code":"PPL",
    "gn:name":"Raskovo",
    "gn:population":0,
    "gn:timezone":"Europe/Saratov",
    "iso:country":"RU",
    "name:und_x_variant":[
        "Sovkhoz Leninskiy Put\u2019",
        "Raskovo"
    ],
    "wof:name":"Raskovo",
    "wof:placetype":"locality"
},
  "geometry": {"coordinates":[46.03306,51.62306],"type":"Point"}
}