{
  "type": "Feature",
  "properties": {
    "gn:admin1_code":"10",
    "gn:asciiname":"Borshnya",
    "gn:country_code":"RU",
    "gn:dem":161,
    "gn:feature_class":"P",
    "gn:feature_code":"PPL",
    "gn:name":"Borshnya",
    "gn:population":0,
    "gn:timezone":"Europe/Moscow",
    "iso:country":"RU",
    "name:rus_x_preferred":[
        "\u0411\u043e\u0440\u0448\u043d\u044f"
    ],
    "wof:name":"Borshnya",
    "wof:placetype":"locality"
},
  "geometry": {"coordinates":[33.52847,52.58767],"type":"Point"}
}