{
  "type": "Feature",
  "properties": {
    "gn:admin1_code":"37",
    "gn:asciiname":"Zhuravli",
    "gn:country_code":"RU",
    "gn:dem":174,
    "gn:feature_class":"P",
    "gn:feature_code":"PPL",
    "gn:name":"Zhuravli",
    "gn:population":0,
    "gn:timezone":"Europe/Moscow",
    "iso:country":"RU",
    "name:rus_x_preferred":[
        "\u0416\u0443\u0440\u0430\u0432\u043b\u0438"
    ],
    "name:und_x_variant":[
        "\u0416\u0443\u0440\u0430\u0432\u043b\u0438"
    ],
    "wof:name":"Zhuravli",
    "wof:placetype":"locality"
},
  "geometry": {"coordinates":[46.4219,59.2306],"type":"Point"}
}