{
  "type": "Feature",
  "properties": {
    "gn:admin1_code":"85",
    "gn:asciiname":"Lyubotovo",
    "gn:country_code":"RU",
    "gn:dem":127,
    "gn:feature_class":"P",
    "gn:feature_code":"PPL",
    "gn:name":"Lyubotovo",
    "gn:population":0,
    "gn:timezone":"Europe/Moscow",
    "iso:country":"RU",
    "name:eng_x_preferred":[
        "Lyubotovo"
    ],
    "name:nor_x_preferred":[
        "Ljubotovo"
    ],
    "name:rus_x_preferred":[
        "\u041b\u044e\u0431\u043e\u0442\u043e\u0432\u043e"
    ],
    "name:und_x_variant":[
        "Lyubotova"
    ],
    "wof:name":"Lyubotovo",
    "wof:placetype":"locality"
},
  "geometry": {"coordinates":[36.2633,58.8287],"type":"Point"}
}