{
  "type": "Feature",
  "properties": {
    "gn:admin1_code":"69",
    "gn:asciiname":"Kurtsovo",
    "gn:country_code":"RU",
    "gn:dem":193,
    "gn:feature_class":"P",
    "gn:feature_code":"PPL",
    "gn:name":"Kurtsovo",
    "gn:population":0,
    "gn:timezone":"Europe/Moscow",
    "iso:country":"RU",
    "name:rus_x_preferred":[
        "\u041a\u0443\u0440\u0446\u043e\u0432\u043e"
    ],
    "wof:name":"Kurtsovo",
    "wof:placetype":"locality"
},
  "geometry": {"coordinates":[32.5742,55.0508],"type":"Point"}
}