{
  "type": "Feature",
  "properties": {
    "gn:admin1_code":"42",
    "gn:admin2_code":"6695196",
    "gn:asciiname":"Solnechnoye",
    "gn:country_code":"RU",
    "gn:dem":17,
    "gn:feature_class":"P",
    "gn:feature_code":"PPL",
    "gn:name":"Solnechnoye",
    "gn:population":0,
    "gn:timezone":"Europe/Moscow",
    "iso:country":"RU",
    "name:fin_x_preferred":[
        "Rotjanlahti"
    ],
    "name:rus_x_preferred":[
        "\u0421\u043e\u043b\u043d\u0435\u0447\u043d\u043e\u0435"
    ],
    "name:und_x_variant":[
        "Rot\u2019yaklakhti",
        "Rot\u2019yanlakhti",
        "Solnechnoye"
    ],
    "wof:name":"Solnechnoye",
    "wof:placetype":"locality"
},
  "geometry": {"coordinates":[30.26978,60.85489000000001],"type":"Point"}
}