{
  "type": "Feature",
  "properties": {
    "gn:admin1_code":"29",
    "gn:asciiname":"Kazas",
    "gn:country_code":"RU",
    "gn:dem":233,
    "gn:feature_class":"P",
    "gn:feature_code":"PPL",
    "gn:name":"Kazas",
    "gn:population":0,
    "gn:timezone":"Asia/Novokuznetsk",
    "iso:country":"RU",
    "name:eng_x_preferred":[
        "Kazas"
    ],
    "name:nor_x_preferred":[
        "Kazas"
    ],
    "name:rus_x_preferred":[
        "\u041a\u0430\u0437\u0430\u0441"
    ],
    "name:und_x_variant":[
        "\u041a\u0430\u0437\u0430\u0441",
        "Kazas"
    ],
    "wof:name":"Kazas",
    "wof:placetype":"locality"
},
  "geometry": {"coordinates":[87.84269999999999,53.6067],"type":"Point"}
}