{
  "type": "Feature",
  "properties": {
    "gn:admin1_code":"61.0",
    "gn:asciiname":"Shramko",
    "gn:country_code":"RU",
    "gn:dem":70,
    "gn:feature_class":"P",
    "gn:feature_code":"PPL",
    "gn:name":"Shramko",
    "gn:population":0,
    "gn:timezone":"Europe/Moscow",
    "iso:country":"RU",
    "name:rus_x_preferred":[
        "\u0428\u0440\u0430\u043c\u043a\u043e"
    ],
    "wof:name":"Shramko",
    "wof:placetype":"locality"
},
  "geometry": {"coordinates":[38.40266,47.61413],"type":"Point"}
}