{
  "type": "Feature",
  "properties": {
    "gn:admin1_code":"62",
    "gn:asciiname":"Zerkaly",
    "gn:country_code":"RU",
    "gn:dem":133,
    "gn:feature_class":"P",
    "gn:feature_code":"PPL",
    "gn:name":"Zerkaly",
    "gn:population":0,
    "gn:timezone":"Europe/Moscow",
    "iso:country":"RU",
    "name:rus_x_preferred":[
        "\u0417\u0435\u0440\u043a\u0430\u043b\u0443"
    ],
    "name:und_x_variant":[
        "Karavayevo",
        "Zerkaly"
    ],
    "wof:name":"Zerkaly",
    "wof:placetype":"locality"
},
  "geometry": {"coordinates":[39.55814,53.49800000000001],"type":"Point"}
}