{
  "type": "Feature",
  "properties": {
    "gn:admin1_code":"45",
    "gn:asciiname":"Gavrenikha",
    "gn:country_code":"RU",
    "gn:dem":133,
    "gn:feature_class":"P",
    "gn:feature_code":"PPL",
    "gn:name":"Gavrenikha",
    "gn:population":0,
    "gn:timezone":"Europe/Moscow",
    "iso:country":"RU",
    "name:rus_x_preferred":[
        "\u0413\u0430\u0432\u0440\u0435\u043d\u0438\u0445\u0430"
    ],
    "name:und_x_variant":[
        "\u0413\u0430\u0432\u0440\u0435\u043d\u0438\u0445\u0430"
    ],
    "wof:name":"Gavrenikha",
    "wof:placetype":"locality"
},
  "geometry": {"coordinates":[46.5121,56.2891],"type":"Point"}
}