{
  "type": "Feature",
  "properties": {
    "gn:admin1_code":"24",
    "gn:asciiname":"Yuzhnyy",
    "gn:country_code":"RU",
    "gn:dem":81,
    "gn:feature_class":"P",
    "gn:feature_code":"PPL",
    "gn:name":"Yuzhnyy",
    "gn:population":0,
    "gn:timezone":"Europe/Moscow",
    "iso:country":"RU",
    "name:rus_x_preferred":[
        "\u042e\u0436\u043d\u044b\u0439"
    ],
    "wof:name":"Yuzhnyy",
    "wof:placetype":"locality"
},
  "geometry": {"coordinates":[42.0193,46.1057],"type":"Point"}
}