{
  "type": "Feature",
  "properties": {
    "gn:admin1_code":"80.0",
    "gn:asciiname":"Novyy Kenovay",
    "gn:country_code":"RU",
    "gn:dem":212,
    "gn:feature_class":"P",
    "gn:feature_code":"PPL",
    "gn:name":"Novyy Kenovay",
    "gn:population":0,
    "gn:timezone":"Europe/Samara",
    "iso:country":"RU",
    "name:rus_x_preferred":[
        "\u041d\u043e\u0432\u044b\u0439 \u041a\u0435\u043d\u043e\u0432\u0430\u0439"
    ],
    "wof:name":"Novyy Kenovay",
    "wof:placetype":"locality"
},
  "geometry": {"coordinates":[52.4752,57.6803],"type":"Point"}
}