{
  "type": "Feature",
  "properties": {
    "gn:admin1_code":"67",
    "gn:asciiname":"Vasil'yevka Vtoraya",
    "gn:country_code":"RU",
    "gn:dem":67,
    "gn:feature_class":"P",
    "gn:feature_code":"PPL",
    "gn:name":"Vasil\u2019yevka Vtoraya",
    "gn:population":0,
    "gn:timezone":"Europe/Saratov",
    "iso:country":"RU",
    "name:rus_x_preferred":[
        "Vasil\u2019yevka Vtoraya"
    ],
    "name:rus_x_variant":[
        "\u0412\u0430\u0441\u0438\u043b\u044c\u0435\u0432\u043a\u0430 \u0412\u0442\u043e\u0440\u0430\u044f"
    ],
    "wof:name":"Vasil'yevka Vtoraya",
    "wof:placetype":"locality"
},
  "geometry": {"coordinates":[48.6323,51.2726],"type":"Point"}
}