{
  "type": "Feature",
  "properties": {
    "gn:admin1_code":"30",
    "gn:asciiname":"Grossevichi",
    "gn:country_code":"RU",
    "gn:dem":10,
    "gn:feature_class":"P",
    "gn:feature_code":"PPL",
    "gn:name":"Grossevichi",
    "gn:population":0,
    "gn:timezone":"Asia/Vladivostok",
    "iso:country":"RU",
    "name:eng_x_preferred":[
        "Grossevichi"
    ],
    "name:nor_x_preferred":[
        "Grossevitsji"
    ],
    "name:rus_x_preferred":[
        "\u0413\u0440\u043e\u0441\u0441\u0435\u0432\u0438\u0447\u0438"
    ],
    "name:und_x_variant":[
        "Grosservicha",
        "Grossevicha"
    ],
    "wof:name":"Grossevichi",
    "wof:placetype":"locality"
},
  "geometry": {"coordinates":[139.53093000000001,47.98582],"type":"Point"}
}