{
  "type": "Feature",
  "properties": {
    "gn:admin1_code":"72",
    "gn:asciiname":"Sbornaya",
    "gn:country_code":"RU",
    "gn:dem":158,
    "gn:feature_class":"P",
    "gn:feature_code":"PPL",
    "gn:name":"Sbornaya",
    "gn:population":0,
    "gn:timezone":"Europe/Moscow",
    "iso:country":"RU",
    "name:rus_x_preferred":[
        "\u0421\u0431\u043e\u0440\u043d\u0430\u044f"
    ],
    "name:und_x_variant":[
        "\u0421\u0431\u043e\u0440\u043d\u0430\u044f"
    ],
    "wof:name":"Sbornaya",
    "wof:placetype":"locality"
},
  "geometry": {"coordinates":[41.78333,52.36667],"type":"Point"}
}