{
  "type": "Feature",
  "properties": {
    "gn:admin1_code":"69",
    "gn:asciiname":"Uda",
    "gn:country_code":"RU",
    "gn:dem":199,
    "gn:feature_class":"P",
    "gn:feature_code":"PPL",
    "gn:name":"Uda",
    "gn:population":0,
    "gn:timezone":"Europe/Moscow",
    "iso:country":"RU",
    "name:ara_x_preferred":[
        "\u0639\u0648\u062f\u0627"
    ],
    "name:bel_x_preferred":[
        "\u0423\u0434\u0430"
    ],
    "name:ben_x_preferred":[
        "\u0989\u09a6\u09be"
    ],
    "name:ceb_x_preferred":[
        "Uda"
    ],
    "name:ces_x_preferred":[
        "Uda"
    ],
    "name:dan_x_preferred":[
        "Uda"
    ],
    "name:deu_x_preferred":[
        "Uda"
    ],
    "name:ell_x_preferred":[
        "\u039f\u03cd\u03bd\u03c4\u03b1"
    ],
    "name:fas_x_preferred":[
        "\u0627\u0648\u062f\u0627"
    ],
    "name:fin_x_preferred":[
        "Uda"
    ],
    "name:fra_x_preferred":[
        "Uda"
    ],
    "name:heb_x_preferred":[
        "\u05d0\u05d5\u05d3\u05d4"
    ],
    "name:hin_x_preferred":[
        "\u0909\u0921\u093e"
    ],
    "name:hrv_x_preferred":[
        "Uda"
    ],
    "name:ind_x_preferred":[
        "Uda"
    ],
    "name:kor_x_preferred":[
        "\uc6b0\ub2e4"
    ],
    "name:lat_x_preferred":[
        "Uda"
    ],
    "name:lit_x_preferred":[
        "Uda"
    ],
    "name:nld_x_preferred":[
        "Uda"
    ],
    "name:nor_x_preferred":[
        "Uda"
    ],
    "name:pol_x_preferred":[
        "Uda"
    ],
    "name:por_x_preferred":[
        "Uda"
    ],
    "name:ron_x_preferred":[
        "Uda"
    ],
    "name:rus_x_preferred":[
        "\u0423\u0434\u0430"
    ],
    "name:srp_x_preferred":[
        "\u0423\u0434\u0430"
    ],
    "name:swe_x_preferred":[
        "Uda"
    ],
    "name:tur_x_preferred":[
        "Uda"
    ],
    "name:ukr_x_preferred":[
        "\u0423\u0434\u0430"
    ],
    "name:urd_x_preferred":[
        "\u0627\u0648\u062f\u0627"
    ],
    "name:vie_x_preferred":[
        "Uda"
    ],
    "wof:name":"Uda",
    "wof:placetype":"locality"
},
  "geometry": {"coordinates":[34.53393,55.13446],"type":"Point"}
}