{
  "type": "Feature",
  "properties": {
    "gn:admin1_code":"69",
    "gn:asciiname":"Uda",
    "gn:country_code":"RU",
    "gn:dem":199,
    "gn:feature_class":"P",
    "gn:feature_code":"PPL",
    "gn:name":"Uda",
    "gn:population":0,
    "gn:timezone":"Europe/Moscow",
    "iso:country":"RU",
    "name:bel_x_preferred":[
        "\u0423\u0434\u0430"
    ],
    "name:ceb_x_preferred":[
        "Uda"
    ],
    "name:ces_x_preferred":[
        "Uda"
    ],
    "name:dan_x_preferred":[
        "Uda"
    ],
    "name:deu_x_preferred":[
        "Uda"
    ],
    "name:fin_x_preferred":[
        "Uda"
    ],
    "name:fra_x_preferred":[
        "Uda"
    ],
    "name:hrv_x_preferred":[
        "Uda"
    ],
    "name:lat_x_preferred":[
        "Uda"
    ],
    "name:lit_x_preferred":[
        "Uda"
    ],
    "name:nld_x_preferred":[
        "Uda"
    ],
    "name:nor_x_preferred":[
        "Uda"
    ],
    "name:pol_x_preferred":[
        "Uda"
    ],
    "name:ron_x_preferred":[
        "Uda"
    ],
    "name:rus_x_preferred":[
        "\u0423\u0434\u0430"
    ],
    "name:srp_x_preferred":[
        "\u0423\u0434\u0430"
    ],
    "name:swe_x_preferred":[
        "Uda"
    ],
    "name:ukr_x_preferred":[
        "\u0423\u0434\u0430"
    ],
    "name:vie_x_preferred":[
        "Uda"
    ],
    "wof:name":"Uda",
    "wof:placetype":"locality"
},
  "geometry": {"coordinates":[34.53393,55.13446],"type":"Point"}
}