{
  "type": "Feature",
  "properties": {
    "gn:admin1_code":"56",
    "gn:asciiname":"Lyubovsha",
    "gn:country_code":"RU",
    "gn:dem":261,
    "gn:feature_class":"P",
    "gn:feature_code":"PPL",
    "gn:name":"Lyubovsha",
    "gn:population":0,
    "gn:timezone":"Europe/Moscow",
    "iso:country":"RU",
    "name:rus_x_preferred":[
        "\u041b\u044e\u0431\u043e\u0432\u0448\u0430"
    ],
    "name:und_x_variant":[
        "Lyubovka",
        "Lyubovsha",
        "\u041b\u044e\u0431\u043e\u0432\u0448\u0430"
    ],
    "wof:name":"Lyubovsha",
    "wof:placetype":"locality"
},
  "geometry": {"coordinates":[37.66094,52.99558],"type":"Point"}
}