{
  "type": "Feature",
  "properties": {
    "gn:admin1_code":"67",
    "gn:asciiname":"Vorotayevka",
    "gn:country_code":"RU",
    "gn:dem":25,
    "gn:feature_class":"P",
    "gn:feature_code":"PPL",
    "gn:name":"Vorotayevka",
    "gn:population":0,
    "gn:timezone":"Europe/Saratov",
    "iso:country":"RU",
    "name:eng_x_preferred":[
        "Vorotayevka"
    ],
    "name:nor_x_preferred":[
        "Vorotajevka"
    ],
    "name:rus_x_preferred":[
        "\u0412\u043e\u0440\u043e\u0442\u0430\u0435\u0432\u043a\u0430"
    ],
    "name:und_x_variant":[
        "Bettinger"
    ],
    "wof:name":"Vorotayevka",
    "wof:placetype":"locality"
},
  "geometry": {"coordinates":[47.26215,51.9204],"type":"Point"}
}