{
  "type": "Feature",
  "properties": {
    "iso:country":"RU",
    "name:rus_x_preferred":[
        "\u041a\u0443\u043f\u0447\u0438\u043d\u043e"
    ],
    "wof:name":"Kupchino",
    "wof:placetype":"neighbourhood"
},
  "geometry": {"coordinates":[30.37353689397049,59.86286831868287],"type":"Point"}
}