{
  "type": "Feature",
  "properties": {
    "gn:admin1_code":"33",
    "gn:asciiname":"Novokryukovo",
    "gn:country_code":"RU",
    "gn:dem":141,
    "gn:feature_class":"P",
    "gn:feature_code":"PPL",
    "gn:name":"Novokryukovo",
    "gn:population":0,
    "gn:timezone":"Europe/Kirov",
    "iso:country":"RU",
    "name:rus_x_preferred":[
        "\u041d\u043e\u0432\u043e\u043a\u0440\u044e\u043a\u043e\u0432\u043e"
    ],
    "wof:name":"Novokryukovo",
    "wof:placetype":"locality"
},
  "geometry": {"coordinates":[49.7387,57.24],"type":"Point"}
}