{
  "type": "Feature",
  "properties": {
    "gn:admin1_code":"87",
    "gn:asciiname":"Saleta",
    "gn:cc2":"RU",
    "gn:country_code":"RU",
    "gn:dem":13,
    "gn:feature_class":"P",
    "gn:feature_code":"PPL",
    "gn:name":"Saleta",
    "gn:population":0,
    "gn:timezone":"Asia/Yekaterinburg",
    "iso:country":"RU",
    "name:rus_x_preferred":[
        "\u0421\u0430\u043b\u0435\u0442\u0430"
    ],
    "name:und_x_variant":[
        "Faktoriya Saletta",
        "Saletta",
        "Saleta"
    ],
    "wof:name":"Saleta",
    "wof:placetype":"locality"
},
  "geometry": {"coordinates":[72.43333,67.40000000000001],"type":"Point"}
}