{
  "type": "Feature",
  "properties": {
    "gn:admin1_code":"61",
    "gn:asciiname":"Nizhnenagol'naya",
    "gn:country_code":"RU",
    "gn:dem":61,
    "gn:feature_class":"P",
    "gn:feature_code":"PPL",
    "gn:name":"Nizhnenagol\u2019naya",
    "gn:population":0,
    "gn:timezone":"Europe/Moscow",
    "iso:country":"RU",
    "name:eng_x_preferred":[
        "Nizhnenagol'naya"
    ],
    "name:nor_x_preferred":[
        "Nizjnenagolnaja"
    ],
    "name:rus_x_preferred":[
        "\u041d\u0438\u0436\u043d\u0435\u043d\u0430\u0433\u043e\u043b\u044c\u043d\u0430\u044f"
    ],
    "name:und_x_variant":[
        "Nizhnenagol\u2019naya"
    ],
    "wof:name":"Nizhnenagol'naya",
    "wof:placetype":"locality"
},
  "geometry": {"coordinates":[39.95144000000001,49.00292],"type":"Point"}
}