{
  "type": "Feature",
  "properties": {
    "gn:admin1_code":"88.0",
    "gn:asciiname":"Dubovik",
    "gn:country_code":"RU",
    "gn:dem":160,
    "gn:feature_class":"P",
    "gn:feature_code":"PPL",
    "gn:name":"Dubovik",
    "gn:population":0,
    "gn:timezone":"Europe/Moscow",
    "iso:country":"RU",
    "name:rus_x_preferred":[
        "\u0414\u0443\u0431\u043e\u0432\u0438\u043a"
    ],
    "name:und_x_variant":[
        "\u0414\u0443\u0431\u043e\u0432\u0438\u043a"
    ],
    "wof:name":"Dubovik",
    "wof:placetype":"locality"
},
  "geometry": {"coordinates":[39.70652000000001,58.43307],"type":"Point"}
}