{
  "type": "Feature",
  "properties": {
    "gn:admin1_code":"8",
    "gn:asciiname":"Kashalya",
    "gn:country_code":"RU",
    "gn:dem":294,
    "gn:feature_class":"P",
    "gn:feature_code":"PPL",
    "gn:name":"Kashalya",
    "gn:population":0,
    "gn:timezone":"Asia/Yekaterinburg",
    "iso:country":"RU",
    "name:eng_x_preferred":[
        "Kashelya"
    ],
    "name:nor_x_preferred":[
        "Kasjalja"
    ],
    "name:rus_x_preferred":[
        "\u041a\u0430\u0448\u0430\u043b\u044f"
    ],
    "name:und_x_variant":[
        "Kashalya"
    ],
    "wof:name":"Kashalya",
    "wof:placetype":"locality"
},
  "geometry": {"coordinates":[56.83025,53.16135],"type":"Point"}
}