{
  "type": "Feature",
  "properties": {
    "gn:admin1_code":"76",
    "gn:asciiname":"Kryuchek",
    "gn:country_code":"RU",
    "gn:dem":168,
    "gn:feature_class":"P",
    "gn:feature_code":"PPL",
    "gn:name":"Kryuchek",
    "gn:population":0,
    "gn:timezone":"Europe/Moscow",
    "iso:country":"RU",
    "name:rus_x_preferred":[
        "\u041a\u0440\u044e\u0447\u0435\u043a"
    ],
    "name:und_x_variant":[
        "Kryuchok"
    ],
    "wof:name":"Kryuchek",
    "wof:placetype":"locality"
},
  "geometry": {"coordinates":[38.4964,53.5742],"type":"Point"}
}