{
  "type": "Feature",
  "properties": {
    "gn:admin1_code":"71.0",
    "gn:asciiname":"Glubokaya",
    "gn:country_code":"RU",
    "gn:dem":165,
    "gn:feature_class":"P",
    "gn:feature_code":"PPL",
    "gn:name":"Glubokaya",
    "gn:population":0,
    "gn:timezone":"Asia/Yekaterinburg",
    "iso:country":"RU",
    "name:rus_x_preferred":[
        "\u0413\u043b\u0443\u0431\u043e\u043a\u0430\u044f"
    ],
    "wof:name":"Glubokaya",
    "wof:placetype":"locality"
},
  "geometry": {"coordinates":[59.8171,58.7662],"type":"Point"}
}