{
  "type": "Feature",
  "properties": {
    "gn:admin1_code":"25",
    "gn:asciiname":"Ivashevo",
    "gn:cc2":"RU",
    "gn:country_code":"RU",
    "gn:dem":202,
    "gn:feature_class":"P",
    "gn:feature_code":"PPL",
    "gn:name":"Ivash\u00ebvo",
    "gn:population":0,
    "gn:timezone":"Europe/Moscow",
    "iso:country":"RU",
    "name:rus_x_preferred":[
        "\u0418\u0432\u0430\u0448\u0451\u0432\u043e"
    ],
    "name:und_x_variant":[
        "Ivashova",
        "Ivash\u00ebvo"
    ],
    "wof:name":"Ivashevo",
    "wof:placetype":"locality"
},
  "geometry": {"coordinates":[35.55,54.93333000000001],"type":"Point"}
}