{
  "type": "Feature",
  "properties": {
    "gn:admin1_code":"21",
    "gn:asciiname":"Simakovo",
    "gn:country_code":"RU",
    "gn:dem":125,
    "gn:feature_class":"P",
    "gn:feature_code":"PPL",
    "gn:name":"Simakovo",
    "gn:population":0,
    "gn:timezone":"Europe/Moscow",
    "iso:country":"RU",
    "name:eng_x_preferred":[
        "Simakovo"
    ],
    "name:nor_x_preferred":[
        "Simakovo"
    ],
    "name:rus_x_preferred":[
        "\u0421\u0438\u043c\u0430\u043a\u043e\u0432\u043e"
    ],
    "name:und_x_variant":[
        "\u0421\u0438\u043c\u0430\u043a\u043e\u0432\u043e",
        "Simakovo"
    ],
    "wof:name":"Simakovo",
    "wof:placetype":"locality"
},
  "geometry": {"coordinates":[42.76754,56.87321],"type":"Point"}
}