{
  "type": "Feature",
  "properties": {
    "gn:admin1_code":"90",
    "gn:asciiname":"Kiryakovka",
    "gn:country_code":"RU",
    "gn:dem":171,
    "gn:feature_class":"P",
    "gn:feature_code":"PPL",
    "gn:name":"Kiryakovka",
    "gn:population":0,
    "gn:timezone":"Asia/Yekaterinburg",
    "iso:country":"RU",
    "name:rus_x_preferred":[
        "\u041a\u0438\u0440\u044f\u043a\u043e\u0432\u043a\u0430"
    ],
    "wof:name":"Kiryakovka",
    "wof:placetype":"locality"
},
  "geometry": {"coordinates":[57.0536,57.4202],"type":"Point"}
}