{
  "type": "Feature",
  "properties": {
    "gn:admin1_code":"8.0",
    "gn:asciiname":"Bikzyan",
    "gn:country_code":"RU",
    "gn:dem":94,
    "gn:feature_class":"P",
    "gn:feature_code":"PPL",
    "gn:name":"Bikzyan",
    "gn:population":0,
    "gn:timezone":"Asia/Yekaterinburg",
    "iso:country":"RU",
    "name:bak_x_preferred":[
        "\u0411\u0438\u043a\u0439\u04d9\u043d"
    ],
    "name:che_x_preferred":[
        "\u0411\u0438\u043a\u0437\u044f\u043d"
    ],
    "name:hye_x_preferred":[
        "\u0532\u056b\u056f\u0566\u0575\u0561\u0576"
    ],
    "name:kaz_x_preferred":[
        "\u0411\u0438\u043a\u0437\u044f\u043d"
    ],
    "name:rus_x_preferred":[
        "\u0411\u0438\u043a\u0437\u044f\u043d"
    ],
    "name:tat_x_preferred":[
        "\u0411\u0438\u043a\u0497\u04d9\u043d"
    ],
    "wof:name":"Bikzyan",
    "wof:placetype":"locality"
},
  "geometry": {"coordinates":[55.39437,55.86529],"type":"Point"}
}