{
  "type": "Feature",
  "properties": {
    "gn:admin1_code":"8.0",
    "gn:asciiname":"Bikzyan",
    "gn:country_code":"RU",
    "gn:dem":94,
    "gn:feature_class":"P",
    "gn:feature_code":"PPL",
    "gn:name":"Bikzyan",
    "gn:population":0,
    "gn:timezone":"Asia/Yekaterinburg",
    "iso:country":"RU",
    "name:rus_x_preferred":[
        "\u0411\u0438\u043a\u0437\u044f\u043d"
    ],
    "name:und_x_variant":[
        "\u0411\u0438\u043a\u0437\u044f\u043d"
    ],
    "wof:name":"Bikzyan",
    "wof:placetype":"locality"
},
  "geometry": {"coordinates":[55.39437,55.86529],"type":"Point"}
}