{
  "type": "Feature",
  "properties": {
    "gn:admin1_code":"76",
    "gn:asciiname":"Butinovo",
    "gn:country_code":"RU",
    "gn:dem":235,
    "gn:feature_class":"P",
    "gn:feature_code":"PPL",
    "gn:name":"Butinovo",
    "gn:population":0,
    "gn:timezone":"Europe/Moscow",
    "iso:country":"RU",
    "name:rus_x_preferred":[
        "\u0411\u0443\u0442\u0438\u043d\u043e\u0432\u043e"
    ],
    "wof:name":"Butinovo",
    "wof:placetype":"locality"
},
  "geometry": {"coordinates":[37.31194,54.64444],"type":"Point"}
}