{
  "type": "Feature",
  "properties": {
    "gn:admin1_code":"60",
    "gn:asciiname":"Pokormovo",
    "gn:country_code":"RU",
    "gn:dem":76,
    "gn:feature_class":"P",
    "gn:feature_code":"PPL",
    "gn:name":"Pokormovo",
    "gn:population":0,
    "gn:timezone":"Europe/Moscow",
    "iso:country":"RU",
    "name:rus_x_preferred":[
        "\u041f\u043e\u043a\u043e\u0440\u043c\u043e\u0432\u043e"
    ],
    "wof:name":"Pokormovo",
    "wof:placetype":"locality"
},
  "geometry": {"coordinates":[28.76097,57.02754],"type":"Point"}
}