{
  "type": "Feature",
  "properties": {
    "gn:admin1_code":"47",
    "gn:asciiname":"Peshki",
    "gn:country_code":"RU",
    "gn:dem":158,
    "gn:feature_class":"P",
    "gn:feature_code":"PPL",
    "gn:name":"Peshki",
    "gn:population":0,
    "gn:timezone":"Europe/Moscow",
    "iso:country":"RU",
    "name:nor_x_preferred":[
        "Pesjki"
    ],
    "name:rus_x_preferred":[
        "\u041f\u0435\u0448\u043a\u0438"
    ],
    "wof:name":"Peshki",
    "wof:placetype":"locality"
},
  "geometry": {"coordinates":[35.57464,56.30844],"type":"Point"}
}