{
  "type": "Feature",
  "properties": {
    "gn:admin1_code":"85",
    "gn:asciiname":"Pogost Sidoro-Slobodskiy",
    "gn:country_code":"RU",
    "gn:dem":182,
    "gn:feature_class":"P",
    "gn:feature_code":"PPL",
    "gn:name":"Pogost Sidoro-Slobodskiy",
    "gn:population":0,
    "gn:timezone":"Europe/Moscow",
    "iso:country":"RU",
    "name:rus_x_preferred":[
        "\u041f\u043e\u0433\u043e\u0441\u0442 \u0421\u0438\u0434\u043e\u0440\u043e-\u0421\u043b\u043e\u0431\u043e\u0434\u0441\u043a\u0438\u0439"
    ],
    "name:und_x_variant":[
        "Sidoro-Slobodskiy",
        "Pogost Sidoro-Slobodskiy",
        "\u041f\u043e\u0433\u043e\u0441\u0442 \u0421\u0438\u0434\u043e\u0440\u043e-\u0421\u043b\u043e\u0431\u043e\u0434\u0441\u043a\u0438\u0439"
    ],
    "wof:name":"Pogost Sidoro-Slobodskiy",
    "wof:placetype":"locality"
},
  "geometry": {"coordinates":[42.30499,60.7141],"type":"Point"}
}