{
  "type": "Feature",
  "properties": {
    "gn:admin1_code":"75.0",
    "gn:asciiname":"Bykovo",
    "gn:country_code":"RU",
    "gn:dem":75,
    "gn:feature_class":"P",
    "gn:feature_code":"PPL",
    "gn:name":"Bykovo",
    "gn:population":0,
    "gn:timezone":"Asia/Tomsk",
    "iso:country":"RU",
    "name:rus_x_preferred":[
        "\u0411\u044b\u043a\u043e\u0432\u043e"
    ],
    "wof:name":"Bykovo",
    "wof:placetype":"locality"
},
  "geometry": {"coordinates":[84.75731999999998,56.56431],"type":"Point"}
}