{
  "type": "Feature",
  "properties": {
    "gn:admin1_code":"81.0",
    "gn:asciiname":"Akulovka",
    "gn:country_code":"RU",
    "gn:dem":150,
    "gn:feature_class":"P",
    "gn:feature_code":"PPL",
    "gn:name":"Akulovka",
    "gn:population":0,
    "gn:timezone":"Europe/Ulyanovsk",
    "iso:country":"RU",
    "name:nor_x_preferred":[
        "Akulovka"
    ],
    "name:rus_x_preferred":[
        "\u0410\u043a\u0443\u043b\u043e\u0432\u043a\u0430"
    ],
    "wof:name":"Akulovka",
    "wof:placetype":"locality"
},
  "geometry": {"coordinates":[47.36667,53.05],"type":"Point"}
}