{
  "type": "Feature",
  "properties": {
    "gn:admin1_code":"40",
    "gn:asciiname":"Yelizavetinka",
    "gn:country_code":"RU",
    "gn:dem":110,
    "gn:feature_class":"P",
    "gn:feature_code":"PPL",
    "gn:name":"Yelizavetinka",
    "gn:population":0,
    "gn:timezone":"Asia/Yekaterinburg",
    "iso:country":"RU",
    "wof:name":"Yelizavetinka",
    "wof:placetype":"locality"
},
  "geometry": {"coordinates":[64.47093000000001,55.29486],"type":"Point"}
}