{
  "type": "Feature",
  "properties": {
    "gn:admin1_code":"4",
    "gn:asciiname":"Pospelikhinskiy",
    "gn:country_code":"RU",
    "gn:dem":223,
    "gn:feature_class":"P",
    "gn:feature_code":"PPL",
    "gn:name":"Pospelikhinskiy",
    "gn:population":0,
    "gn:timezone":"Asia/Barnaul",
    "iso:country":"RU",
    "name:eng_x_preferred":[
        "Pospelikhinskiy"
    ],
    "name:nor_x_preferred":[
        "Pospelikhinskij"
    ],
    "name:rus_x_preferred":[
        "\u041f\u043e\u0441\u043f\u0435\u043b\u0438\u0445\u0438\u043d\u0441\u043a\u0438\u0439"
    ],
    "wof:name":"Pospelikhinskiy",
    "wof:placetype":"locality"
},
  "geometry": {"coordinates":[81.83333,51.85],"type":"Point"}
}