{
  "type": "Feature",
  "properties": {
    "gn:admin1_code":"53",
    "gn:asciiname":"Kavkuy",
    "gn:country_code":"RU",
    "gn:dem":112,
    "gn:feature_class":"P",
    "gn:feature_code":"PPL",
    "gn:name":"Kavkuy",
    "gn:population":0,
    "gn:timezone":"Asia/Novosibirsk",
    "iso:country":"RU",
    "name:eng_x_preferred":[
        "Kavkuy"
    ],
    "name:nor_x_preferred":[
        "Kavkuj"
    ],
    "name:rus_x_preferred":[
        "\u041a\u0430\u0432\u043a\u0443\u0439"
    ],
    "name:und_x_variant":[
        "\u041a\u0430\u0432\u043a\u0443\u0439",
        "Kavkuy"
    ],
    "wof:name":"Kavkuy",
    "wof:placetype":"locality"
},
  "geometry": {"coordinates":[78.15841999999998,53.64841],"type":"Point"}
}