{
  "type": "Feature",
  "properties": {
    "gn:admin1_code":"60",
    "gn:asciiname":"Kinikovo",
    "gn:country_code":"RU",
    "gn:dem":212,
    "gn:feature_class":"P",
    "gn:feature_code":"PPL",
    "gn:name":"Kinikovo",
    "gn:population":0,
    "gn:timezone":"Europe/Moscow",
    "iso:country":"RU",
    "name:rus_x_preferred":[
        "\u041a\u0438\u043d\u0438\u043a\u043e\u0432\u043e"
    ],
    "name:und_x_variant":[
        "\u041a\u0438\u043d\u0438\u043a\u043e\u0432\u043e"
    ],
    "wof:name":"Kinikovo",
    "wof:placetype":"locality"
},
  "geometry": {"coordinates":[29.7965,56.7416],"type":"Point"}
}