{
  "type": "Feature",
  "properties": {
    "gn:admin1_code":"52.0",
    "gn:asciiname":"Bronnitsa",
    "gn:country_code":"RU",
    "gn:dem":30,
    "gn:feature_class":"P",
    "gn:feature_code":"PPL",
    "gn:name":"Bronnitsa",
    "gn:population":0,
    "gn:timezone":"Europe/Moscow",
    "iso:country":"RU",
    "name:eng_x_preferred":[
        "Bronnitsa"
    ],
    "name:nor_x_preferred":[
        "Bronnitsa"
    ],
    "name:rus_x_preferred":[
        "\u0411\u0440\u043e\u043d\u043d\u0438\u0446\u0430"
    ],
    "name:und_x_variant":[
        "Msta",
        "Bronnitsy"
    ],
    "wof:name":"Bronnitsa",
    "wof:placetype":"locality"
},
  "geometry": {"coordinates":[31.67341,58.44804],"type":"Point"}
}