{
  "type": "Feature",
  "properties": {
    "gn:admin1_code":"57",
    "gn:asciiname":"Korsayevka",
    "gn:country_code":"RU",
    "gn:dem":162,
    "gn:feature_class":"P",
    "gn:feature_code":"PPL",
    "gn:name":"Korsayevka",
    "gn:population":0,
    "gn:timezone":"Europe/Moscow",
    "iso:country":"RU",
    "name:eng_x_preferred":[
        "Korsayevka"
    ],
    "name:nor_x_preferred":[
        "Korsajevka"
    ],
    "name:rus_x_preferred":[
        "\u041a\u043e\u0440\u0441\u0430\u0435\u0432\u043a\u0430"
    ],
    "name:und_x_variant":[
        "Karsayevka",
        "\u041a\u043e\u0440\u0441\u0430\u0435\u0432\u043a\u0430",
        "Korsayevka"
    ],
    "wof:name":"Korsayevka",
    "wof:placetype":"locality"
},
  "geometry": {"coordinates":[43.22133,52.98846999999999],"type":"Point"}
}