{
  "type": "Feature",
  "properties": {
    "gn:admin1_code":"71",
    "gn:asciiname":"Iskra",
    "gn:country_code":"RU",
    "gn:dem":230,
    "gn:feature_class":"P",
    "gn:feature_code":"PPL",
    "gn:name":"Iskra",
    "gn:population":0,
    "gn:timezone":"Asia/Yekaterinburg",
    "iso:country":"RU",
    "name:rus_x_preferred":[
        "\u0418\u0441\u043a\u0440\u0430"
    ],
    "name:und_x_variant":[
        "\u0418\u0441\u043a\u0440\u0430"
    ],
    "wof:name":"Iskra",
    "wof:placetype":"locality"
},
  "geometry": {"coordinates":[61.0076,57.547],"type":"Point"}
}