{
  "type": "Feature",
  "properties": {
    "gn:admin1_code":"29",
    "gn:asciiname":"Krasnoselka",
    "gn:country_code":"RU",
    "gn:dem":164,
    "gn:feature_class":"P",
    "gn:feature_code":"PPL",
    "gn:name":"Krasnoselka",
    "gn:population":0,
    "gn:timezone":"Asia/Novokuznetsk",
    "iso:country":"RU",
    "name:eng_x_preferred":[
        "Krasnoselka"
    ],
    "name:nor_x_preferred":[
        "Krasnoselka"
    ],
    "name:rus_x_preferred":[
        "\u041a\u0440\u0430\u0441\u043d\u043e\u0441\u0435\u043b\u043a\u0430"
    ],
    "name:und_x_variant":[
        "Krasnaya",
        "Krasnoye",
        "\u041a\u0440\u0430\u0441\u043d\u043e\u0441\u0435\u043b\u043a\u0430",
        "Krasnoselka"
    ],
    "wof:name":"Krasnoselka",
    "wof:placetype":"locality"
},
  "geometry": {"coordinates":[85.2043,55.8702],"type":"Point"}
}