{
  "type": "Feature",
  "properties": {
    "gn:admin1_code":"88",
    "gn:asciiname":"Tashlyki",
    "gn:country_code":"RU",
    "gn:dem":124,
    "gn:feature_class":"P",
    "gn:feature_code":"PPL",
    "gn:name":"Tashlyki",
    "gn:population":0,
    "gn:timezone":"Europe/Moscow",
    "iso:country":"RU",
    "name:rus_x_preferred":[
        "\u0422\u0430\u0448\u043b\u044b\u043a\u0438"
    ],
    "name:und_x_variant":[
        "\u0422\u0430\u0448\u043b\u044b\u043a\u0438"
    ],
    "wof:name":"Tashlyki",
    "wof:placetype":"locality"
},
  "geometry": {"coordinates":[38.3111,57.8913],"type":"Point"}
}