{
  "type": "Feature",
  "properties": {
    "gn:admin1_code":"13",
    "gn:asciiname":"Verkhneustselemovo",
    "gn:country_code":"RU",
    "gn:dem":353,
    "gn:feature_class":"P",
    "gn:feature_code":"PPL",
    "gn:name":"Verkhneustselemovo",
    "gn:population":0,
    "gn:timezone":"Asia/Yekaterinburg",
    "iso:country":"RU",
    "name:rus_x_preferred":[
        "\u0412\u0435\u0440\u0445\u043d\u0435\u0443\u0441\u0446\u0435\u043b\u0435\u043c\u043e\u0432\u043e"
    ],
    "name:und_x_variant":[
        "Verkhne-Ustselemovskiy",
        "Verkhniy Ustelemovskiy",
        "Verkhneustselemovo"
    ],
    "wof:name":"Verkhneustselemovo",
    "wof:placetype":"locality"
},
  "geometry": {"coordinates":[60.0743,54.4605],"type":"Point"}
}