{
  "type": "Feature",
  "properties": {
    "gn:admin1_code":"86",
    "gn:asciiname":"Kriushanskiye Vyselki Pervyye",
    "gn:country_code":"RU",
    "gn:dem":152,
    "gn:feature_class":"P",
    "gn:feature_code":"PPL",
    "gn:name":"Kriushanskiye Vyselki Pervyye",
    "gn:population":0,
    "gn:timezone":"Europe/Moscow",
    "iso:country":"RU",
    "name:rus_x_preferred":[
        "\u041a\u0440\u0438\u0443\u0448\u0430\u043d\u0441\u043a\u0438\u0435 \u0412\u044b\u0441\u0435\u043b\u043a\u0438 \u041f\u0435\u0440\u0432\u044b\u0435"
    ],
    "name:und_x_variant":[
        "Pervyye Kriushanskiye Vyselki",
        "Kriushinskiye Vyselki",
        "Kriushanskiye Vyselki Pervyye"
    ],
    "wof:name":"Kriushanskiye Vyselki Pervyye",
    "wof:placetype":"locality"
},
  "geometry": {"coordinates":[39.95385,51.44581],"type":"Point"}
}