{
  "type": "Feature",
  "properties": {
    "gn:admin1_code":"43",
    "gn:asciiname":"Kolodezskaya",
    "gn:country_code":"RU",
    "gn:dem":210,
    "gn:feature_class":"P",
    "gn:feature_code":"PPL",
    "gn:name":"Kolodezskaya",
    "gn:population":0,
    "gn:timezone":"Europe/Moscow",
    "iso:country":"RU",
    "name:rus_x_preferred":[
        "\u041a\u043e\u043b\u043e\u0434\u0435\u0437\u0441\u043a\u0430\u044f"
    ],
    "name:und_x_variant":[
        "Kolodez\u2019ki",
        "Kolodezskaya",
        "Kolodezskiye"
    ],
    "wof:name":"Kolodezskaya",
    "wof:placetype":"locality"
},
  "geometry": {"coordinates":[38.64268,52.78338000000001],"type":"Point"}
}