{
  "type": "Feature",
  "properties": {
    "gn:admin1_code":"62",
    "gn:asciiname":"Poselok Otdeleniya Imeni Kalinina Sel'skokhozyaystvennogo Predpriyatiya Vozrozhdeniye",
    "gn:country_code":"RU",
    "gn:dem":194,
    "gn:feature_class":"P",
    "gn:feature_code":"PPL",
    "gn:name":"Pos\u00eblok Otdeleniya Imeni Kalinina Sel\u2019skokhozyaystvennogo Predpriyatiya Vozrozhdeniye",
    "gn:population":0,
    "gn:timezone":"Europe/Moscow",
    "iso:country":"RU",
    "name:rus_x_preferred":[
        "\u041f\u043e\u0441\u00eb\u043b\u043e\u043a \u041e\u0442\u0434\u0435\u043b\u0435\u043d\u0438\u044f \u0418\u043c\u0435\u043d\u0438 \u041a\u0430\u043b\u0438\u043d\u0438\u043d\u0430 \u0421\u0435\u043b\u044c\u0441\u043a\u043e\u0445\u043e\u0437\u044f\u0439\u0441\u0442\u0432\u0435\u043d\u043d\u043e\u0433\u043e \u041f\u0440\u0435\u0434\u043f\u0440\u0438\u044f\u0442\u0438\u044f \u0412\u043e\u0437\u0440\u043e\u0436\u0434\u0435\u043d\u0438\u0435"
    ],
    "name:und_x_variant":[
        "Pos\u00eblok Otdeleniya Imeni Kalinina Sel\u2019skokhozyaystvennogo Predpriyatiya Vozrozhdeniye",
        "Pos\u00eblok Otdeleniya Imeni Kalinina Sovkhoza Vozrozhdeniye"
    ],
    "wof:name":"Poselok Otdeleniya Imeni Kalinina Sel'skokhozyaystvennogo Predpriyatiya Vozrozhdeniye",
    "wof:placetype":"locality"
},
  "geometry": {"coordinates":[39.0962,53.9699],"type":"Point"}
}