{
  "type": "Feature",
  "properties": {
    "gn:admin1_code":"6",
    "gn:asciiname":"Tugolukovskiy",
    "gn:cc2":"RU",
    "gn:country_code":"RU",
    "gn:dem":93,
    "gn:feature_class":"P",
    "gn:feature_code":"PPL",
    "gn:name":"Tugolukovskiy",
    "gn:population":0,
    "gn:timezone":"Europe/Moscow",
    "iso:country":"RU",
    "name:und_x_variant":[
        "Tul\u2019gol\u2019skiy Pogost",
        "Tugol\u2019skiy",
        "Tugolukovskiy"
    ],
    "wof:name":"Tugolukovskiy",
    "wof:placetype":"locality"
},
  "geometry": {"coordinates":[43.53333,63.58333],"type":"Point"}
}