{
  "type": "Feature",
  "properties": {
    "gn:admin1_code":"16",
    "gn:asciiname":"Kadysh",
    "gn:country_code":"RU",
    "gn:dem":160,
    "gn:feature_class":"P",
    "gn:feature_code":"PPL",
    "gn:name":"Kadysh",
    "gn:population":0,
    "gn:timezone":"Europe/Moscow",
    "iso:country":"RU",
    "name:bak_x_preferred":[
        "\u04a0\u0430\u0499\u044b\u0448"
    ],
    "name:hye_x_preferred":[
        "\u053f\u0561\u0564\u056b\u0577"
    ],
    "name:kat_x_preferred":[
        "\u10d9\u10d0\u10d3\u10d8\u10e8\u10d8"
    ],
    "name:kaz_x_preferred":[
        "\u041a\u0430\u0434\u044b\u0448"
    ],
    "name:rus_x_preferred":[
        "\u041a\u0430\u0434\u044b\u0448"
    ],
    "name:tat_x_preferred":[
        "\u041a\u0430\u0434\u044b\u0448"
    ],
    "name:ukr_x_preferred":[
        "\u041a\u0430\u0434\u0438\u0448"
    ],
    "wof:name":"Kadysh",
    "wof:placetype":"locality"
},
  "geometry": {"coordinates":[47.57139,55.86167],"type":"Point"}
}