{
  "type": "Feature",
  "properties": {
    "gn:admin1_code":"60",
    "gn:asciiname":"Mozuli",
    "gn:country_code":"RU",
    "gn:dem":105,
    "gn:feature_class":"P",
    "gn:feature_code":"PPL",
    "gn:name":"Mozuli",
    "gn:population":0,
    "gn:timezone":"Europe/Moscow",
    "iso:country":"RU",
    "name:eng_x_preferred":[
        "Mozuli"
    ],
    "name:nor_x_preferred":[
        "Mozuli"
    ],
    "name:rus_x_preferred":[
        "\u041c\u043e\u0437\u0443\u043b\u0438"
    ],
    "wof:name":"Mozuli",
    "wof:placetype":"locality"
},
  "geometry": {"coordinates":[28.18441,56.60365],"type":"Point"}
}