{
  "type": "Feature",
  "properties": {
    "gn:admin1_code":"4.0",
    "gn:asciiname":"Sadovyy",
    "gn:country_code":"RU",
    "gn:dem":326,
    "gn:feature_class":"P",
    "gn:feature_code":"PPL",
    "gn:name":"Sadovyy",
    "gn:population":0,
    "gn:timezone":"Asia/Barnaul",
    "iso:country":"RU",
    "name:rus_x_preferred":[
        "\u0421\u0430\u0434\u043e\u0432\u044b\u0439"
    ],
    "wof:name":"Sadovyy",
    "wof:placetype":"locality"
},
  "geometry": {"coordinates":[84.12909999999999,51.7451],"type":"Point"}
}