{
  "type": "Feature",
  "properties": {
    "gn:admin1_code":"63",
    "gn:admin2_code":"Nyurbinsky District (undefined)",
    "gn:asciiname":"Khar-Dzhiye",
    "gn:country_code":"RU",
    "gn:dem":132,
    "gn:feature_class":"P",
    "gn:feature_code":"PPL",
    "gn:name":"Khar-Dzhiye",
    "gn:population":0,
    "gn:timezone":"Asia/Yakutsk",
    "iso:country":"RU",
    "name:rus_x_preferred":[
        "\u0425\u0430\u0440-\u0414\u0436\u0438\u0435"
    ],
    "name:und_x_variant":[
        "\u0425\u0430\u0440-\u0414\u0436\u0438\u0435"
    ],
    "wof:name":"Khar-Dzhiye",
    "wof:placetype":"locality"
},
  "geometry": {"coordinates":[118.13333,63.16667],"type":"Point"}
}