{
  "type": "Feature",
  "properties": {
    "gn:admin1_code":"8",
    "gn:asciiname":"Kachevan",
    "gn:country_code":"RU",
    "gn:dem":206,
    "gn:feature_class":"P",
    "gn:feature_code":"PPL",
    "gn:name":"Kachevan",
    "gn:population":0,
    "gn:timezone":"Asia/Yekaterinburg",
    "iso:country":"RU",
    "name:rus_x_preferred":[
        "\u041a\u0430\u0447\u0435\u0432\u0430\u043d"
    ],
    "wof:name":"Kachevan",
    "wof:placetype":"locality"
},
  "geometry": {"coordinates":[56.0577,54.3069],"type":"Point"}
}