{
  "type": "Feature",
  "properties": {
    "gn:admin1_code":"93",
    "gn:asciiname":"Aliya",
    "gn:country_code":"RU",
    "gn:dem":650,
    "gn:feature_class":"P",
    "gn:feature_code":"PPL",
    "gn:name":"Aliya",
    "gn:population":0,
    "gn:timezone":"Asia/Chita",
    "iso:country":"RU",
    "name:eng_x_preferred":[
        "Aliya"
    ],
    "name:nor_x_preferred":[
        "Alia"
    ],
    "name:rus_x_preferred":[
        "\u0410\u043b\u0438\u044f"
    ],
    "wof:name":"Aliya",
    "wof:placetype":"locality"
},
  "geometry": {"coordinates":[117.10312999999999,51.63848],"type":"Point"}
}