{
  "type": "Feature",
  "properties": {
    "gn:admin1_code":"9.0",
    "gn:asciiname":"Dmitriyevka",
    "gn:country_code":"RU",
    "gn:dem":217,
    "gn:feature_class":"P",
    "gn:feature_code":"PPL",
    "gn:name":"Dmitriyevka",
    "gn:population":0,
    "gn:timezone":"Europe/Moscow",
    "iso:country":"RU",
    "name:rus_x_preferred":[
        "\u0414\u043c\u0438\u0442\u0440\u0438\u0435\u0432\u043a\u0430"
    ],
    "name:und_x_variant":[
        "Yumatovka",
        "Dmitriyevka",
        "\u0414\u043c\u0438\u0442\u0440\u0438\u0435\u0432\u043a\u0430"
    ],
    "wof:name":"Dmitriyevka",
    "wof:placetype":"locality"
},
  "geometry": {"coordinates":[36.33956,50.82799],"type":"Point"}
}