{
  "type": "Feature",
  "properties": {
    "gn:admin1_code":"33",
    "gn:asciiname":"Krasnogor'ye",
    "gn:country_code":"RU",
    "gn:dem":140,
    "gn:feature_class":"P",
    "gn:feature_code":"PPL",
    "gn:name":"Krasnogor\u2019ye",
    "gn:population":0,
    "gn:timezone":"Europe/Kirov",
    "iso:country":"RU",
    "name:eng_x_preferred":[
        "Krasnogor'ye"
    ],
    "name:nor_x_preferred":[
        "Lopatovsjtsjina"
    ],
    "name:rus_x_preferred":[
        "\u041b\u043e\u043f\u0430\u0442\u043e\u0432\u0449\u0438\u043d\u0430"
    ],
    "name:rus_x_variant":[
        "\u041a\u0440\u0430\u0441\u043d\u043e\u0433\u043e\u0440\u044c\u0435"
    ],
    "name:und_x_variant":[
        "Lopatovshchina",
        "Lapatovshchina",
        "Krasnogor\u2019ye",
        "\u041a\u0440\u0430\u0441\u043d\u043e\u0433\u043e\u0440\u044c\u0435"
    ],
    "wof:name":"Krasnogor'ye",
    "wof:placetype":"locality"
},
  "geometry": {"coordinates":[48.38718,58.47326],"type":"Point"}
}