{
  "type": "Feature",
  "properties": {
    "gn:admin1_code":"41",
    "gn:asciiname":"Karmanovo",
    "gn:country_code":"RU",
    "gn:dem":177,
    "gn:feature_class":"P",
    "gn:feature_code":"PPL",
    "gn:name":"Karmanovo",
    "gn:population":0,
    "gn:timezone":"Europe/Moscow",
    "iso:country":"RU",
    "name:eng_x_preferred":[
        "Karmanovo"
    ],
    "name:nor_x_preferred":[
        "Karmanovo"
    ],
    "name:rus_x_preferred":[
        "\u041a\u0430\u0440\u043c\u0430\u043d\u043e\u0432\u043e"
    ],
    "name:und_x_variant":[
        "\u041a\u0430\u0440\u043c\u0430\u043d\u043e\u0432\u043e",
        "Karmanovo",
        "Zharmanovo"
    ],
    "wof:name":"Karmanovo",
    "wof:placetype":"locality"
},
  "geometry": {"coordinates":[35.356,52.1534],"type":"Point"}
}