{
  "type": "Feature",
  "properties": {
    "gn:admin1_code":"42.0",
    "gn:asciiname":"Dorozhnyy Post",
    "gn:country_code":"RU",
    "gn:dem":72,
    "gn:feature_class":"P",
    "gn:feature_code":"PPL",
    "gn:name":"Dorozhnyy Post",
    "gn:population":0,
    "gn:timezone":"Europe/Moscow",
    "iso:country":"RU",
    "name:rus_x_preferred":[
        "\u0414\u043e\u0440\u043e\u0436\u043d\u044b\u0439 \u041f\u043e\u0441\u0442"
    ],
    "wof:name":"Dorozhnyy Post",
    "wof:placetype":"locality"
},
  "geometry": {"coordinates":[30.36278,59.50889],"type":"Point"}
}