{
  "type": "Feature",
  "properties": {
    "gn:admin1_code":"4",
    "gn:asciiname":"Verkh-Bekhtemir",
    "gn:country_code":"RU",
    "gn:dem":235,
    "gn:feature_class":"P",
    "gn:feature_code":"PPL",
    "gn:name":"Verkh-Bekhtemir",
    "gn:population":1200,
    "gn:timezone":"Asia/Barnaul",
    "iso:country":"RU",
    "name:ceb_x_preferred":[
        "Verkh-Bekhtemir"
    ],
    "name:che_x_preferred":[
        "\u0412\u0435\u0440\u0445-\u0411\u0435\u0445\u0442\u0435\u043c\u0438\u0440"
    ],
    "name:eng_x_preferred":[
        "Verkhniy Bekhtemir"
    ],
    "name:nor_x_preferred":[
        "Verkh-Bekhtemir"
    ],
    "name:rus_x_preferred":[
        "\u0412\u0435\u0440\u0445-\u0411\u0435\u0445\u0442\u0435\u043c\u0438\u0440"
    ],
    "name:und_x_variant":[
        "Verkhniy Bekhzhemor",
        "Verkhniy Bakhtemir",
        "Verkhne-Bekhtemirskoye"
    ],
    "wof:name":"Verkh-Bekhtemir",
    "wof:placetype":"locality",
    "wof:population":1200
},
  "geometry": {"coordinates":[85.90508,52.76596],"type":"Point"}
}