{
  "type": "Feature",
  "properties": {
    "gn:admin1_code":"17",
    "gn:asciiname":"Gel'bakh",
    "gn:country_code":"RU",
    "gn:dem":106,
    "gn:feature_class":"P",
    "gn:feature_code":"PPL",
    "gn:name":"Gel\u2019bakh",
    "gn:population":0,
    "gn:timezone":"Europe/Moscow",
    "iso:country":"RU",
    "name:rus_x_preferred":[
        "\u0413\u0435\u043b\u044c\u0431\u0430\u0445"
    ],
    "name:und_x_variant":[
        "Verkhniy Chiryurt",
        "Gel\u2019bakh"
    ],
    "wof:name":"Gel'bakh",
    "wof:placetype":"locality"
},
  "geometry": {"coordinates":[46.85751,43.15101],"type":"Point"}
}