{
  "type": "Feature",
  "properties": {
    "gn:admin1_code":"42",
    "gn:admin2_code":"470541",
    "gn:asciiname":"Podborov'ye",
    "gn:country_code":"RU",
    "gn:dem":-9999,
    "gn:feature_class":"P",
    "gn:feature_code":"PPL",
    "gn:name":"Podborov\u2019ye",
    "gn:population":0,
    "gn:timezone":"Europe/Moscow",
    "iso:country":"RU",
    "name:fin_x_preferred":[
        "Karppila"
    ],
    "name:rus_x_historical":[
        "\u041a\u0430\u0440\u043f\u043f\u0438\u043b\u0430"
    ],
    "name:rus_x_preferred":[
        "\u041f\u043e\u0434\u0431\u043e\u0440\u043e\u0432\u044c\u0435"
    ],
    "name:rus_x_variant":[
        "\u041a\u0430\u0440\u043f\u043f\u0438\u043b\u0430"
    ],
    "name:und_x_variant":[
        "Podborov\u2019ye"
    ],
    "wof:name":"Podborov'ye",
    "wof:placetype":"locality"
},
  "geometry": {"coordinates":[28.5278,60.67461],"type":"Point"}
}