{
  "type": "Feature",
  "properties": {
    "gn:admin1_code":"70",
    "gn:asciiname":"Rodnikovskiy",
    "gn:country_code":"RU",
    "gn:dem":385,
    "gn:feature_class":"P",
    "gn:feature_code":"PPL",
    "gn:name":"Rodnikovskiy",
    "gn:population":0,
    "gn:timezone":"Europe/Moscow",
    "iso:country":"RU",
    "name:eng_x_preferred":[
        "Rodnikovskiy"
    ],
    "name:nor_x_preferred":[
        "Rodnikovskij"
    ],
    "name:rus_x_preferred":[
        "\u0420\u043e\u0434\u043d\u0438\u043a\u043e\u0432\u0441\u043a\u0438\u0439"
    ],
    "wof:name":"Rodnikovskiy",
    "wof:placetype":"locality"
},
  "geometry": {"coordinates":[42.01694000000001,44.51944],"type":"Point"}
}