{
  "type": "Feature",
  "properties": {
    "gn:admin1_code":"33.0",
    "gn:asciiname":"Klyukino",
    "gn:country_code":"RU",
    "gn:dem":177,
    "gn:feature_class":"P",
    "gn:feature_code":"PPL",
    "gn:name":"Klyukino",
    "gn:population":0,
    "gn:timezone":"Europe/Kirov",
    "iso:country":"RU",
    "name:rus_x_preferred":[
        "\u041a\u043b\u044e\u043a\u0438\u043d\u043e"
    ],
    "name:und_x_variant":[
        "Bol\u2019shoye Klyukino",
        "Klyukino",
        "\u041a\u043b\u044e\u043a\u0438\u043d\u043e"
    ],
    "wof:name":"Klyukino",
    "wof:placetype":"locality"
},
  "geometry": {"coordinates":[50.02361,59.00361],"type":"Point"}
}