{
  "type": "Feature",
  "properties": {
    "gn:admin1_code":"65",
    "gn:asciiname":"Novogeran'kino",
    "gn:country_code":"RU",
    "gn:dem":107,
    "gn:feature_class":"P",
    "gn:feature_code":"PPL",
    "gn:name":"Novogeran\u2019kino",
    "gn:population":0,
    "gn:timezone":"Europe/Samara",
    "iso:country":"RU",
    "name:eng_x_preferred":[
        "Novogeran'kino"
    ],
    "name:nor_x_preferred":[
        "Novogerankino"
    ],
    "name:rus_x_preferred":[
        "\u041d\u043e\u0432\u043e-\u0413\u0435\u0440\u0430\u043d\u044c\u043a\u0438\u043d\u043e"
    ],
    "name:und_x_variant":[
        "Novoye Geran\u2019kino",
        "\u041d\u043e\u0432\u043e-\u0413\u0435\u0440\u0430\u043d\u044c\u043a\u0438\u043d\u043e",
        "Novogeran\u2019kino"
    ],
    "wof:name":"Novogeran'kino",
    "wof:placetype":"locality"
},
  "geometry": {"coordinates":[51.84592,53.1814],"type":"Point"}
}