{
  "type": "Feature",
  "properties": {
    "gn:admin1_code":"84",
    "gn:asciiname":"Sedov",
    "gn:country_code":"RU",
    "gn:dem":79,
    "gn:feature_class":"P",
    "gn:feature_code":"PPL",
    "gn:name":"Sedov",
    "gn:population":0,
    "gn:timezone":"Europe/Volgograd",
    "iso:country":"RU",
    "name:bel_x_preferred":[
        "\u0421\u044f\u0434\u043e\u045e"
    ],
    "name:fra_x_preferred":[
        "Sedov"
    ],
    "name:ita_x_preferred":[
        "Sedov"
    ],
    "name:jpn_x_preferred":[
        "\u30bb\u30c9\u30d5"
    ],
    "name:nld_x_preferred":[
        "Sedov"
    ],
    "name:pol_x_preferred":[
        "Siedow"
    ],
    "name:rus_x_preferred":[
        "\u0421\u0435\u0434\u043e\u0432"
    ],
    "name:ukr_x_preferred":[
        "\u0421\u0454\u0434\u043e\u0432"
    ],
    "wof:name":"Sedov",
    "wof:placetype":"locality"
},
  "geometry": {"coordinates":[42.6234,49.6868],"type":"Point"}
}