{
  "type": "Feature",
  "properties": {
    "gn:admin1_code":"53",
    "gn:asciiname":"Uryupino",
    "gn:country_code":"RU",
    "gn:dem":118,
    "gn:feature_class":"P",
    "gn:feature_code":"PPL",
    "gn:name":"Uryupino",
    "gn:population":0,
    "gn:timezone":"Asia/Novosibirsk",
    "iso:country":"RU",
    "name:eng_x_preferred":[
        "Uryupino"
    ],
    "name:nor_x_preferred":[
        "Urjupino"
    ],
    "name:rus_x_preferred":[
        "\u0423\u0440\u044e\u043f\u0438\u043d\u043e"
    ],
    "wof:name":"Uryupino",
    "wof:placetype":"locality"
},
  "geometry": {"coordinates":[78.99615,54.13315],"type":"Point"}
}