{
  "type": "Feature",
  "properties": {
    "gn:admin1_code":"55",
    "gn:asciiname":"Linevka",
    "gn:country_code":"RU",
    "gn:dem":79,
    "gn:feature_class":"P",
    "gn:feature_code":"PPL",
    "gn:name":"Linevka",
    "gn:population":0,
    "gn:timezone":"Asia/Yekaterinburg",
    "iso:country":"RU",
    "name:eng_x_preferred":[
        "Linevka"
    ],
    "name:nor_x_preferred":[
        "Linevka"
    ],
    "name:rus_x_preferred":[
        "\u041b\u0438\u043d\u0435\u0432\u043a\u0430"
    ],
    "name:und_x_variant":[
        "Lineyeskaya",
        "Linewka",
        "Linevskaya",
        "\u041b\u0438\u043d\u0435\u0432\u043a\u0430",
        "Linevka"
    ],
    "wof:name":"Linevka",
    "wof:placetype":"locality"
},
  "geometry": {"coordinates":[54.11804,51.14062],"type":"Point"}
}