{
  "type": "Feature",
  "properties": {
    "gn:admin1_code":"76",
    "gn:asciiname":"Katalovka",
    "gn:country_code":"RU",
    "gn:dem":198,
    "gn:feature_class":"P",
    "gn:feature_code":"PPL",
    "gn:name":"Katalovka",
    "gn:population":0,
    "gn:timezone":"Europe/Moscow",
    "iso:country":"RU",
    "name:rus_x_preferred":[
        "\u041a\u0430\u0442\u0430\u043b\u043e\u0432\u043a\u0430"
    ],
    "wof:name":"Katalovka",
    "wof:placetype":"locality"
},
  "geometry": {"coordinates":[38.0975,53.17111],"type":"Point"}
}