{
  "type": "Feature",
  "properties": {
    "gn:admin1_code":"33",
    "gn:asciiname":"Martynovy",
    "gn:country_code":"RU",
    "gn:dem":149,
    "gn:feature_class":"P",
    "gn:feature_code":"PPL",
    "gn:name":"Martynovy",
    "gn:population":0,
    "gn:timezone":"Europe/Kirov",
    "iso:country":"RU",
    "name:rus_x_preferred":[
        "\u041c\u0430\u0440\u0442\u044b\u043d\u043e\u0432\u044b"
    ],
    "wof:name":"Martynovy",
    "wof:placetype":"locality"
},
  "geometry": {"coordinates":[49.16732,58.36447],"type":"Point"}
}