{
  "type": "Feature",
  "properties": {
    "gn:admin1_code":"77.0",
    "gn:asciiname":"Bakhmara",
    "gn:country_code":"RU",
    "gn:dem":168,
    "gn:feature_class":"P",
    "gn:feature_code":"PPL",
    "gn:name":"Bakhmara",
    "gn:population":0,
    "gn:timezone":"Europe/Moscow",
    "iso:country":"RU",
    "name:eng_x_preferred":[
        "Bakhmara"
    ],
    "name:nor_x_preferred":[
        "Bakhmara"
    ],
    "name:rus_x_preferred":[
        "\u0411\u0430\u0445\u043c\u0430\u0440\u0430"
    ],
    "name:und_x_variant":[
        "Bakhmary",
        "Bakhmyry",
        "\u0411\u0430\u0445\u043c\u0430\u0440\u0430",
        "Bakhmara"
    ],
    "wof:name":"Bakhmara",
    "wof:placetype":"locality"
},
  "geometry": {"coordinates":[34.33947,57.66983000000001],"type":"Point"}
}