{
  "type": "Feature",
  "properties": {
    "gn:admin1_code":"71",
    "gn:asciiname":"Ovinnyy",
    "gn:country_code":"RU",
    "gn:dem":190,
    "gn:feature_class":"P",
    "gn:feature_code":"PPL",
    "gn:name":"Ovinnyy",
    "gn:population":0,
    "gn:timezone":"Asia/Yekaterinburg",
    "iso:country":"RU",
    "name:rus_x_preferred":[
        "\u041e\u0432\u0438\u043d\u043d\u044b\u0439"
    ],
    "wof:name":"Ovinnyy",
    "wof:placetype":"locality"
},
  "geometry": {"coordinates":[61.65,57.65],"type":"Point"}
}