{
  "type": "Feature",
  "properties": {
    "gn:admin1_code":"33",
    "gn:asciiname":"Goryunok",
    "gn:country_code":"RU",
    "gn:dem":200,
    "gn:feature_class":"P",
    "gn:feature_code":"PPL",
    "gn:name":"Goryunok",
    "gn:population":0,
    "gn:timezone":"Europe/Kirov",
    "iso:country":"RU",
    "name:rus_x_preferred":[
        "\u0413\u043e\u0440\u044e\u043d\u043e\u043a"
    ],
    "name:und_x_variant":[
        "\u0413\u043e\u0440\u044e\u043d\u043e\u043a"
    ],
    "wof:name":"Goryunok",
    "wof:placetype":"locality"
},
  "geometry": {"coordinates":[49.67479,57.92749],"type":"Point"}
}