{
  "type": "Feature",
  "properties": {
    "gn:admin1_code":"67",
    "gn:asciiname":"Lopatino",
    "gn:country_code":"RU",
    "gn:dem":148,
    "gn:feature_class":"P",
    "gn:feature_code":"PPL",
    "gn:name":"Lopatino",
    "gn:population":0,
    "gn:timezone":"Europe/Saratov",
    "iso:country":"RU",
    "name:eng_x_preferred":[
        "Lopatino"
    ],
    "name:nor_x_preferred":[
        "Lopatino"
    ],
    "name:rus_x_preferred":[
        "\u041b\u043e\u043f\u0430\u0442\u0438\u043d\u043e"
    ],
    "wof:name":"Lopatino",
    "wof:placetype":"locality"
},
  "geometry": {"coordinates":[43.50267,52.14417],"type":"Point"}
}