{
  "type": "Feature",
  "properties": {
    "gn:admin1_code":"42.0",
    "gn:asciiname":"Akkolovo",
    "gn:country_code":"RU",
    "gn:dem":119,
    "gn:feature_class":"P",
    "gn:feature_code":"PPL",
    "gn:name":"Akkolovo",
    "gn:population":0,
    "gn:timezone":"Europe/Moscow",
    "iso:country":"RU",
    "name:fin_x_preferred":[
        "Akkala"
    ],
    "name:nor_x_preferred":[
        "Akkolovo"
    ],
    "name:rus_x_preferred":[
        "\u0410\u043a\u043a\u043e\u043b\u043e\u0432\u043e"
    ],
    "wof:name":"Akkolovo",
    "wof:placetype":"locality"
},
  "geometry": {"coordinates":[29.866,59.57566],"type":"Point"}
}