{
  "type": "Feature",
  "properties": {
    "gn:admin1_code":"84",
    "gn:asciiname":"Glukhoy",
    "gn:country_code":"RU",
    "gn:dem":-6,
    "gn:feature_class":"P",
    "gn:feature_code":"PPL",
    "gn:name":"Glukhoy",
    "gn:population":0,
    "gn:timezone":"Europe/Volgograd",
    "iso:country":"RU",
    "name:rus_x_preferred":[
        "\u0413\u043b\u0443\u0445\u043e\u0439"
    ],
    "name:und_x_variant":[
        "Khutor Glukhoy",
        "Glukhoy"
    ],
    "wof:name":"Glukhoy",
    "wof:placetype":"locality"
},
  "geometry": {"coordinates":[45.37703,48.47607],"type":"Point"}
}