{
  "type": "Feature",
  "properties": {
    "gn:admin1_code":"77.0",
    "gn:asciiname":"Bol'shoye Vyzhlyatnikovo",
    "gn:country_code":"RU",
    "gn:dem":265,
    "gn:feature_class":"P",
    "gn:feature_code":"PPL",
    "gn:name":"Bol\u2019shoye Vyzhlyatnikovo",
    "gn:population":0,
    "gn:timezone":"Europe/Moscow",
    "iso:country":"RU",
    "name:rus_x_preferred":[
        "\u0411\u043e\u043b\u044c\u0448\u043e\u0435 \u0412\u044b\u0436\u043b\u044f\u0442\u043d\u0438\u043a\u043e\u0432\u043e"
    ],
    "name:und_x_variant":[
        "Vyzhlyatnikovo",
        "Bol\u2019shoye Vyzhlyatnikovo"
    ],
    "wof:name":"Bol'shoye Vyzhlyatnikovo",
    "wof:placetype":"locality"
},
  "geometry": {"coordinates":[33.227,56.72252],"type":"Point"}
}