{
  "type": "Feature",
  "properties": {
    "gn:admin1_code":"77",
    "gn:asciiname":"Voyevodkino",
    "gn:country_code":"RU",
    "gn:dem":193,
    "gn:feature_class":"P",
    "gn:feature_code":"PPL",
    "gn:name":"Voyevodkino",
    "gn:population":0,
    "gn:timezone":"Europe/Moscow",
    "iso:country":"RU",
    "name:rus_x_preferred":[
        "\u0412\u043e\u0435\u0432\u043e\u0434\u043a\u0438\u043d\u043e"
    ],
    "wof:name":"Voyevodkino",
    "wof:placetype":"locality"
},
  "geometry": {"coordinates":[32.91461,56.12279],"type":"Point"}
}