{
  "type": "Feature",
  "properties": {
    "gn:admin1_code":"25",
    "gn:asciiname":"Kolodezi",
    "gn:country_code":"RU",
    "gn:dem":194,
    "gn:feature_class":"P",
    "gn:feature_code":"PPL",
    "gn:name":"Kolodezi",
    "gn:population":0,
    "gn:timezone":"Europe/Moscow",
    "iso:country":"RU",
    "name:rus_x_preferred":[
        "\u041a\u043e\u043b\u043e\u0434\u0435\u0437\u0438"
    ],
    "name:und_x_variant":[
        "Kolodez\u2019",
        "Kolodezi",
        "\u041a\u043e\u043b\u043e\u0434\u0435\u0437\u0438"
    ],
    "wof:name":"Kolodezi",
    "wof:placetype":"locality"
},
  "geometry": {"coordinates":[35.9176,55.03089],"type":"Point"}
}