{
  "type": "Feature",
  "properties": {
    "gn:admin1_code":"61",
    "gn:asciiname":"Nikolayev",
    "gn:country_code":"RU",
    "gn:dem":120,
    "gn:feature_class":"P",
    "gn:feature_code":"PPL",
    "gn:name":"Nikolayev",
    "gn:population":0,
    "gn:timezone":"Europe/Moscow",
    "iso:country":"RU",
    "name:eng_x_preferred":[
        "Nikolayev"
    ],
    "name:nor_x_preferred":[
        "Nikolajev"
    ],
    "name:rus_x_preferred":[
        "\u041d\u0438\u043a\u043e\u043b\u0430\u0435\u0432"
    ],
    "name:und_x_variant":[
        "\u041d\u0438\u043a\u043e\u043b\u0430\u0435\u0432",
        "Nikolayev"
    ],
    "wof:name":"Nikolayev",
    "wof:placetype":"locality"
},
  "geometry": {"coordinates":[41.73632,48.01839],"type":"Point"}
}