{
  "type": "Feature",
  "properties": {
    "gn:admin1_code":"61",
    "gn:asciiname":"Nikolayev",
    "gn:country_code":"RU",
    "gn:dem":120,
    "gn:feature_class":"P",
    "gn:feature_code":"PPL",
    "gn:name":"Nikolayev",
    "gn:population":0,
    "gn:timezone":"Europe/Moscow",
    "iso:country":"RU",
    "name:bel_x_preferred":[
        "\u041d\u0456\u043a\u0430\u043b\u0430\u0435\u045e"
    ],
    "name:bul_x_preferred":[
        "\u041d\u0438\u043a\u043e\u043b\u0430\u0435\u0432"
    ],
    "name:ceb_x_preferred":[
        "Nikolayev"
    ],
    "name:ces_x_preferred":[
        "Nikolajev"
    ],
    "name:chv_x_preferred":[
        "\u041d\u0438\u043a\u043e\u043b\u0430\u0435\u0432"
    ],
    "name:deu_x_preferred":[
        "Nikolajew"
    ],
    "name:eng_x_preferred":[
        "Nikolayev"
    ],
    "name:fin_x_preferred":[
        "Nikolajev"
    ],
    "name:fra_x_preferred":[
        "Nikola\u00efev"
    ],
    "name:hun_x_preferred":[
        "Nyikolajev"
    ],
    "name:ita_x_preferred":[
        "Nikolaev"
    ],
    "name:jpn_x_preferred":[
        "\u30cb\u30b3\u30e9\u30fc\u30a8\u30d5"
    ],
    "name:kor_x_preferred":[
        "\ub2c8\ucf5c\ub77c\uc608\ud504"
    ],
    "name:nor_x_preferred":[
        "Nikolajev"
    ],
    "name:pol_x_preferred":[
        "Niko\u0142ajew"
    ],
    "name:rus_x_preferred":[
        "\u041d\u0438\u043a\u043e\u043b\u0430\u0435\u0432"
    ],
    "name:sah_x_preferred":[
        "\u041d\u0438\u043a\u043e\u043b\u0430\u0435\u0432"
    ],
    "name:slv_x_preferred":[
        "Nikolajev"
    ],
    "name:spa_x_preferred":[
        "Nikol\u00e1yev"
    ],
    "name:swe_x_preferred":[
        "Nikolajev"
    ],
    "name:ukr_x_preferred":[
        "\u041d\u0456\u043a\u043e\u043b\u0430\u0454\u0432"
    ],
    "name:und_x_variant":[
        "\u041d\u0438\u043a\u043e\u043b\u0430\u0435\u0432",
        "Nikolayev"
    ],
    "name:vep_x_preferred":[
        "Nikolajev"
    ],
    "name:zho_x_preferred":[
        "\u5c3c\u53e4\u62c9\u8036\u592b"
    ],
    "wof:name":"Nikolayev",
    "wof:placetype":"locality"
},
  "geometry": {"coordinates":[41.73632,48.01839],"type":"Point"}
}