{
  "type": "Feature",
  "properties": {
    "gn:admin1_code":"90",
    "gn:asciiname":"Veslyanka",
    "gn:country_code":"RU",
    "gn:dem":128,
    "gn:feature_class":"P",
    "gn:feature_code":"PPL",
    "gn:name":"Veslyanka",
    "gn:population":0,
    "gn:timezone":"Asia/Yekaterinburg",
    "iso:country":"RU",
    "name:eng_x_preferred":[
        "Veslyanka"
    ],
    "name:nor_x_preferred":[
        "Vesljanka"
    ],
    "name:rus_x_preferred":[
        "\u0412\u0435\u0441\u043b\u044f\u043d\u043a\u0430"
    ],
    "wof:name":"Veslyanka",
    "wof:placetype":"locality"
},
  "geometry": {"coordinates":[56.68875,57.29342],"type":"Point"}
}