{
  "type": "Feature",
  "properties": {
    "gn:admin1_code":"73",
    "gn:asciiname":"Nekrasovka",
    "gn:country_code":"RU",
    "gn:dem":80,
    "gn:feature_class":"P",
    "gn:feature_code":"PPL",
    "gn:name":"Nekrasovka",
    "gn:population":0,
    "gn:timezone":"Europe/Moscow",
    "iso:country":"RU",
    "name:ceb_x_preferred":[
        "Nekrasovka"
    ],
    "name:nld_x_preferred":[
        "Nekrasovka"
    ],
    "name:rus_x_preferred":[
        "\u041d\u0435\u043a\u0440\u0430\u0441\u043e\u0432\u043a\u0430"
    ],
    "name:und_x_variant":[
        "\u041d\u0435\u043a\u0440\u0430\u0441\u043e\u0432\u043a\u0430"
    ],
    "wof:name":"Nekrasovka",
    "wof:placetype":"locality"
},
  "geometry": {"coordinates":[50.9035,54.4021],"type":"Point"}
}