{
  "type": "Feature",
  "properties": {
    "gn:admin1_code":"47.0",
    "gn:asciiname":"Davydkovo",
    "gn:country_code":"RU",
    "gn:dem":186,
    "gn:feature_class":"P",
    "gn:feature_code":"PPL",
    "gn:name":"Davydkovo",
    "gn:population":156,
    "gn:timezone":"Europe/Moscow",
    "iso:country":"RU",
    "name:rus_x_preferred":[
        "\u0414\u0430\u0432\u044b\u0434\u043a\u043e\u0432\u043e"
    ],
    "wof:name":"Davydkovo",
    "wof:placetype":"locality",
    "wof:population":156
},
  "geometry": {"coordinates":[36.81667,56.28333000000001],"type":"Point"}
}