{
  "type": "Feature",
  "properties": {
    "gn:admin1_code":"15",
    "gn:asciiname":"Vyyekvyn",
    "gn:country_code":"RU",
    "gn:dem":220,
    "gn:feature_class":"P",
    "gn:feature_code":"PPL",
    "gn:name":"Vyyekvyn",
    "gn:population":0,
    "gn:timezone":"Asia/Anadyr",
    "iso:country":"RU",
    "wof:name":"Vyyekvyn",
    "wof:placetype":"locality"
},
  "geometry": {"coordinates":[-172.46666999999999,64.96666999999999],"type":"Point"}
}