{
  "type": "Feature",
  "properties": {
    "gn:admin1_code":"85",
    "gn:asciiname":"Legalovo",
    "gn:country_code":"RU",
    "gn:dem":132,
    "gn:feature_class":"P",
    "gn:feature_code":"PPL",
    "gn:name":"Legalovo",
    "gn:population":0,
    "gn:timezone":"Europe/Moscow",
    "iso:country":"RU",
    "name:rus_x_preferred":[
        "\u041b\u0435\u0433\u0430\u043b\u043e\u0432\u043e"
    ],
    "name:und_x_variant":[
        "\u041b\u0435\u0433\u0430\u043b\u043e\u0432\u043e"
    ],
    "wof:name":"Legalovo",
    "wof:placetype":"locality"
},
  "geometry": {"coordinates":[36.3568,58.8076],"type":"Point"}
}