{
  "type": "Feature",
  "properties": {
    "gn:admin1_code":"80",
    "gn:asciiname":"Russkiy Pychas",
    "gn:country_code":"RU",
    "gn:dem":170,
    "gn:feature_class":"P",
    "gn:feature_code":"PPL",
    "gn:name":"Russkiy Pychas",
    "gn:population":0,
    "gn:timezone":"Europe/Samara",
    "iso:country":"RU",
    "name:eng_x_preferred":[
        "Russkiy Pychas"
    ],
    "name:nor_x_preferred":[
        "Russkij Pytsjas"
    ],
    "name:rus_x_preferred":[
        "\u0420\u0443\u0441\u0441\u043a\u0438\u0439 \u041f\u044b\u0447\u0430\u0441"
    ],
    "name:und_x_variant":[
        "Pychassy",
        "Pychas-Russkiy",
        "\u0420\u0443\u0441\u0441\u043a\u0438\u0439 \u041f\u044b\u0447\u0430\u0441",
        "Russkiy Pychas"
    ],
    "wof:name":"Russkiy Pychas",
    "wof:placetype":"locality"
},
  "geometry": {"coordinates":[52.51727,56.65541999999999],"type":"Point"}
}