{
  "type": "Feature",
  "properties": {
    "gn:admin1_code":"41.0",
    "gn:asciiname":"Dronovka",
    "gn:country_code":"RU",
    "gn:dem":154,
    "gn:feature_class":"P",
    "gn:feature_code":"PPL",
    "gn:name":"Dronovka",
    "gn:population":0,
    "gn:timezone":"Europe/Moscow",
    "iso:country":"RU",
    "name:rus_x_preferred":[
        "\u0414\u0440\u043e\u043d\u043e\u0432\u043a\u0430"
    ],
    "name:und_x_variant":[
        "\u0414\u0440\u043e\u043d\u043e\u0432\u043a\u0430"
    ],
    "wof:name":"Dronovka",
    "wof:placetype":"locality"
},
  "geometry": {"coordinates":[34.29,51.4291],"type":"Point"}
}