{
  "type": "Feature",
  "properties": {
    "gn:admin1_code":"47",
    "gn:asciiname":"Ugornaya Sloboda",
    "gn:country_code":"RU",
    "gn:dem":123,
    "gn:feature_class":"P",
    "gn:feature_code":"PPL",
    "gn:name":"Ugornaya Sloboda",
    "gn:population":0,
    "gn:timezone":"Europe/Moscow",
    "iso:country":"RU",
    "wof:name":"Ugornaya Sloboda",
    "wof:placetype":"locality"
},
  "geometry": {"coordinates":[39.06793,55.16614000000001],"type":"Point"}
}