{
  "type": "Feature",
  "properties": {
    "gn:admin1_code":"90.0",
    "gn:asciiname":"Tarasy",
    "gn:country_code":"RU",
    "gn:dem":185,
    "gn:feature_class":"P",
    "gn:feature_code":"PPL",
    "gn:name":"Tarasy",
    "gn:population":0,
    "gn:timezone":"Asia/Yekaterinburg",
    "iso:country":"RU",
    "name:bel_x_preferred":[
        "\u0422\u0430\u0440\u0430\u0441\u044b"
    ],
    "name:rus_x_preferred":[
        "\u0422\u0430\u0440\u0430\u0441\u044b"
    ],
    "name:spa_x_preferred":[
        "Tarasy"
    ],
    "name:ukr_x_preferred":[
        "\u0422\u0430\u0440\u0430\u0441\u0438"
    ],
    "wof:name":"Tarasy",
    "wof:placetype":"locality"
},
  "geometry": {"coordinates":[55.5367,58.4995],"type":"Point"}
}