{
  "type": "Feature",
  "properties": {
    "gn:admin1_code":"85.0",
    "gn:asciiname":"Churilovo",
    "gn:country_code":"RU",
    "gn:dem":161,
    "gn:feature_class":"P",
    "gn:feature_code":"PPL",
    "gn:name":"Churilovo",
    "gn:population":0,
    "gn:timezone":"Europe/Moscow",
    "iso:country":"RU",
    "name:bul_x_preferred":[
        "\u0427\u0443\u0440\u0438\u043b\u043e\u0432\u043e"
    ],
    "name:fas_x_preferred":[
        "\u0686\u0648\u0631\u06cc\u0644\u0648\u0641\u0648"
    ],
    "name:kaz_x_preferred":[
        "\u0427\u0443\u0440\u0438\u043b\u043e\u0432\u043e"
    ],
    "name:mkd_x_preferred":[
        "\u0427\u0443\u0440\u0438\u043b\u043e\u0432\u043e"
    ],
    "name:ron_x_preferred":[
        "Ciurilovo"
    ],
    "name:rus_x_preferred":[
        "\u0427\u0443\u0440\u0438\u043b\u043e\u0432\u043e"
    ],
    "name:ukr_x_preferred":[
        "\u0427\u0443\u0440\u0438\u043b\u043e\u0432\u043e"
    ],
    "wof:name":"Churilovo",
    "wof:placetype":"locality"
},
  "geometry": {"coordinates":[38.71101,59.20494],"type":"Point"}
}