{
  "type": "Feature",
  "properties": {
    "gn:admin1_code":"51",
    "gn:asciiname":"Snoved'",
    "gn:country_code":"RU",
    "gn:dem":104,
    "gn:feature_class":"P",
    "gn:feature_code":"PPL",
    "gn:name":"Snoved\u2019",
    "gn:population":0,
    "gn:timezone":"Europe/Moscow",
    "iso:country":"RU",
    "name:eng_x_preferred":[
        "Snoved'"
    ],
    "name:nor_x_preferred":[
        "Snoved"
    ],
    "name:rus_x_preferred":[
        "\u0421\u043d\u043e\u0432\u0435\u0434\u044c"
    ],
    "name:und_x_variant":[
        "Snovad\u2019",
        "\u0421\u043d\u043e\u0432\u0435\u0434\u044c",
        "Snoved\u2019"
    ],
    "wof:name":"Snoved'",
    "wof:placetype":"locality"
},
  "geometry": {"coordinates":[42.0482,55.1167],"type":"Point"}
}