{
  "type": "Feature",
  "properties": {
    "gn:admin1_code":"13",
    "gn:asciiname":"Bersenevka",
    "gn:country_code":"RU",
    "gn:dem":175,
    "gn:feature_class":"P",
    "gn:feature_code":"PPL",
    "gn:name":"Bersenevka",
    "gn:population":0,
    "gn:timezone":"Asia/Yekaterinburg",
    "iso:country":"RU",
    "name:nor_x_preferred":[
        "Bersenevka"
    ],
    "name:rus_x_preferred":[
        "\u0411\u0435\u0440\u0441\u0435\u043d\u0435\u0432\u043a\u0430"
    ],
    "wof:name":"Bersenevka",
    "wof:placetype":"locality"
},
  "geometry": {"coordinates":[62.1613,55.09],"type":"Point"}
}