{
  "type": "Feature",
  "properties": {
    "gn:admin1_code":"21.0",
    "gn:asciiname":"Smagino",
    "gn:country_code":"RU",
    "gn:dem":116,
    "gn:feature_class":"P",
    "gn:feature_code":"PPL",
    "gn:name":"Smagino",
    "gn:population":0,
    "gn:timezone":"Europe/Moscow",
    "iso:country":"RU",
    "name:nor_x_preferred":[
        "Smagino"
    ],
    "name:rus_x_preferred":[
        "\u0421\u043c\u0430\u0433\u0438\u043d\u043e"
    ],
    "wof:name":"Smagino",
    "wof:placetype":"locality"
},
  "geometry": {"coordinates":[43.11001,56.99961],"type":"Point"}
}