{
  "type": "Feature",
  "properties": {
    "gn:admin1_code":"63",
    "gn:asciiname":"Bulun",
    "gn:country_code":"RU",
    "gn:dem":99,
    "gn:feature_class":"P",
    "gn:feature_code":"PPL",
    "gn:name":"Bulun",
    "gn:population":0,
    "gn:timezone":"Asia/Yakutsk",
    "iso:country":"RU",
    "name:rus_x_preferred":[
        "\u0411\u0443\u043b\u0443\u043d"
    ],
    "name:und_x_variant":[
        "\u0411\u0443\u043b\u0443\u043d"
    ],
    "wof:name":"Bulun",
    "wof:placetype":"locality"
},
  "geometry": {"coordinates":[133.28111000000001,63.02444000000001],"type":"Point"}
}