{
  "type": "Feature",
  "properties": {
    "gn:admin1_code":"86.0",
    "gn:asciiname":"Druzhelyubiye",
    "gn:country_code":"RU",
    "gn:dem":110,
    "gn:feature_class":"P",
    "gn:feature_code":"PPL",
    "gn:name":"Druzhelyubiye",
    "gn:population":0,
    "gn:timezone":"Europe/Moscow",
    "iso:country":"RU",
    "name:rus_x_preferred":[
        "\u0414\u0440\u0443\u0436\u0435\u043b\u044e\u0431\u0438\u0435"
    ],
    "name:und_x_variant":[
        "Druzhelyubnoye",
        "Druzhelyubiye"
    ],
    "wof:name":"Druzhelyubiye",
    "wof:placetype":"locality"
},
  "geometry": {"coordinates":[39.52548,51.54395],"type":"Point"}
}