{
  "type": "Feature",
  "properties": {
    "gn:admin1_code":"38",
    "gn:asciiname":"Goytkh",
    "gn:country_code":"RU",
    "gn:dem":294,
    "gn:feature_class":"P",
    "gn:feature_code":"PPL",
    "gn:name":"Goytkh",
    "gn:population":0,
    "gn:timezone":"Europe/Moscow",
    "iso:country":"RU",
    "name:eng_x_preferred":[
        "Goytkh"
    ],
    "name:nor_x_preferred":[
        "Gojtkh"
    ],
    "name:rus_x_preferred":[
        "\u0413\u043e\u0439\u0442\u0445"
    ],
    "name:und_x_variant":[
        "Goitkh",
        "\u0413\u043e\u0439\u0442\u0445",
        "Goytkh"
    ],
    "wof:name":"Goytkh",
    "wof:placetype":"locality"
},
  "geometry": {"coordinates":[39.3772,44.2459],"type":"Point"}
}