{
  "type": "Feature",
  "properties": {
    "gn:admin1_code":"10",
    "gn:asciiname":"Vpered",
    "gn:country_code":"RU",
    "gn:dem":212,
    "gn:feature_class":"P",
    "gn:feature_code":"PPL",
    "gn:name":"Vper\u00ebd",
    "gn:population":0,
    "gn:timezone":"Europe/Moscow",
    "iso:country":"RU",
    "name:hye_x_preferred":[
        "\u054e\u057a\u0565\u0580\u0575\u0578\u0564 \u056d\u0578\u0582\u0574\u0562"
    ],
    "name:rus_x_preferred":[
        "\u0413\u0440\u0443\u043f\u043f\u0430 \u00ab\u0412\u043f\u0435\u0440\u0451\u0434\u00bb"
    ],
    "wof:name":"Vpered",
    "wof:placetype":"locality"
},
  "geometry": {"coordinates":[33.28333,53.58333],"type":"Point"}
}