{
  "type": "Feature",
  "properties": {
    "gn:admin1_code":"85",
    "gn:asciiname":"Lymzino",
    "gn:country_code":"RU",
    "gn:dem":167,
    "gn:feature_class":"P",
    "gn:feature_code":"PPL",
    "gn:name":"Lymzino",
    "gn:population":0,
    "gn:timezone":"Europe/Moscow",
    "iso:country":"RU",
    "name:rus_x_preferred":[
        "\u041b\u044b\u043c\u0437\u0438\u043d\u043e"
    ],
    "wof:name":"Lymzino",
    "wof:placetype":"locality"
},
  "geometry": {"coordinates":[42.12448,60.64341999999999],"type":"Point"}
}