{
  "type": "Feature",
  "properties": {
    "gn:admin1_code":"33",
    "gn:asciiname":"Shchegly",
    "gn:country_code":"RU",
    "gn:dem":131,
    "gn:feature_class":"P",
    "gn:feature_code":"PPL",
    "gn:name":"Shchegly",
    "gn:population":0,
    "gn:timezone":"Europe/Kirov",
    "iso:country":"RU",
    "name:rus_x_preferred":[
        "\u0429\u0435\u0433\u043b\u044b"
    ],
    "name:und_x_variant":[
        "Malyye Shchegly"
    ],
    "wof:name":"Shchegly",
    "wof:placetype":"locality"
},
  "geometry": {"coordinates":[47.9674,57.091],"type":"Point"}
}