{
  "type": "Feature",
  "properties": {
    "gn:admin1_code":"60",
    "gn:asciiname":"Bol'shaya Kretivlya",
    "gn:country_code":"RU",
    "gn:dem":170,
    "gn:feature_class":"P",
    "gn:feature_code":"PPL",
    "gn:name":"Bol\u2019shaya Kretivlya",
    "gn:population":0,
    "gn:timezone":"Europe/Moscow",
    "iso:country":"RU",
    "name:eng_x_preferred":[
        "Kretivlya"
    ],
    "name:nor_x_preferred":[
        "Kretivlja"
    ],
    "name:rus_x_preferred":[
        "\u0411\u043e\u043b\u044c\u0448\u0430\u044f \u041a\u0440\u0435\u0442\u0438\u0432\u043b\u044f"
    ],
    "name:und_x_variant":[
        "Bol\u2019shaya Kretivlya"
    ],
    "wof:name":"Bol'shaya Kretivlya",
    "wof:placetype":"locality"
},
  "geometry": {"coordinates":[31.18057,56.09387],"type":"Point"}
}