{
  "type": "Feature",
  "properties": {
    "gn:admin1_code":"29",
    "gn:asciiname":"Pravdinka",
    "gn:country_code":"RU",
    "gn:dem":152,
    "gn:feature_class":"P",
    "gn:feature_code":"PPL",
    "gn:name":"Pravdinka",
    "gn:population":0,
    "gn:timezone":"Asia/Novokuznetsk",
    "iso:country":"RU",
    "name:eng_x_preferred":[
        "Pravdinka"
    ],
    "name:nor_x_preferred":[
        "Pravdinka"
    ],
    "name:rus_x_preferred":[
        "\u041f\u0440\u0430\u0432\u0434\u0438\u043d\u043a\u0430"
    ],
    "name:und_x_variant":[
        "Pravdinskaya",
        "\u041f\u0440\u0430\u0432\u0434\u0438\u043d\u043a\u0430",
        "Pravdinka"
    ],
    "wof:name":"Pravdinka",
    "wof:placetype":"locality"
},
  "geometry": {"coordinates":[87.17571,56.33031],"type":"Point"}
}