{
  "type": "Feature",
  "properties": {
    "gn:admin1_code":"28.0",
    "gn:asciiname":"Gerova Storona",
    "gn:country_code":"RU",
    "gn:dem":141,
    "gn:feature_class":"P",
    "gn:feature_code":"PPL",
    "gn:name":"Gerova Storona",
    "gn:population":0,
    "gn:timezone":"Europe/Moscow",
    "iso:country":"RU",
    "name:rus_x_preferred":[
        "\u0413\u0435\u0440\u043e\u0432\u0430 \u0421\u0442\u043e\u0440\u043e\u043d\u0430"
    ],
    "name:und_x_variant":[
        "\u0413\u0435\u0440\u043e\u0432\u0430 \u0421\u0442\u043e\u0440\u043e\u043d\u0430"
    ],
    "wof:name":"Gerova Storona",
    "wof:placetype":"locality"
},
  "geometry": {"coordinates":[31.18658,64.38596],"type":"Point"}
}