{
  "type": "Feature",
  "properties": {
    "gn:admin1_code":"42",
    "gn:admin2_code":"472711",
    "gn:asciiname":"Vymovo",
    "gn:country_code":"RU",
    "gn:dem":40,
    "gn:feature_class":"P",
    "gn:feature_code":"PPL",
    "gn:name":"Vymovo",
    "gn:population":0,
    "gn:timezone":"Europe/Moscow",
    "iso:country":"RU",
    "name:rus_x_preferred":[
        "\u0412\u044b\u043c\u043e\u0432\u043e"
    ],
    "wof:name":"Vymovo",
    "wof:placetype":"locality"
},
  "geometry": {"coordinates":[32.81836,60.04141],"type":"Point"}
}