{
  "type": "Feature",
  "properties": {
    "gn:admin1_code":"46",
    "gn:asciiname":"Mokshaley",
    "gn:country_code":"RU",
    "gn:dem":238,
    "gn:feature_class":"P",
    "gn:feature_code":"PPL",
    "gn:name":"Mokshaley",
    "gn:population":0,
    "gn:timezone":"Europe/Moscow",
    "iso:country":"RU",
    "name:eng_x_preferred":[
        "Mokshaley"
    ],
    "name:nor_x_preferred":[
        "Moksjalej"
    ],
    "name:rus_x_preferred":[
        "\u041c\u043e\u043a\u0448\u0430\u043b\u0435\u0439"
    ],
    "wof:name":"Mokshaley",
    "wof:placetype":"locality"
},
  "geometry": {"coordinates":[45.63422,54.25547],"type":"Point"}
}