{
  "type": "Feature",
  "properties": {
    "gn:admin1_code":"33",
    "gn:asciiname":"Butyrki",
    "gn:country_code":"RU",
    "gn:dem":169,
    "gn:feature_class":"P",
    "gn:feature_code":"PPL",
    "gn:name":"Butyrki",
    "gn:population":0,
    "gn:timezone":"Europe/Kirov",
    "iso:country":"RU",
    "name:rus_x_preferred":[
        "\u0411\u0443\u0442\u044b\u0440\u043a\u0438"
    ],
    "wof:name":"Butyrki",
    "wof:placetype":"locality"
},
  "geometry": {"coordinates":[49.48524000000001,58.19575],"type":"Point"}
}