{
  "type": "Feature",
  "properties": {
    "gn:admin1_code":"83",
    "gn:asciiname":"Sukmanikha",
    "gn:country_code":"RU",
    "gn:dem":175,
    "gn:feature_class":"P",
    "gn:feature_code":"PPL",
    "gn:name":"Sukmanikha",
    "gn:population":0,
    "gn:timezone":"Europe/Moscow",
    "iso:country":"RU",
    "name:rus_x_preferred":[
        "\u0421\u0443\u043a\u043c\u0430\u043d\u0438\u0445\u0430"
    ],
    "wof:name":"Sukmanikha",
    "wof:placetype":"locality"
},
  "geometry": {"coordinates":[39.48,56.2502],"type":"Point"}
}