{
  "type": "Feature",
  "properties": {
    "gn:admin1_code":"46",
    "gn:asciiname":"Lesnoye Ardashevo",
    "gn:country_code":"RU",
    "gn:dem":141,
    "gn:feature_class":"P",
    "gn:feature_code":"PPL",
    "gn:name":"Lesnoye Ardashevo",
    "gn:population":0,
    "gn:timezone":"Europe/Moscow",
    "iso:country":"RU",
    "name:eng_x_preferred":[
        "Lesnoye Ardashevo"
    ],
    "name:nor_x_preferred":[
        "Lesnoje Ardasjevo"
    ],
    "name:rus_x_preferred":[
        "\u041b\u0435\u0441\u043d\u043e\u0435 \u0410\u0440\u0434\u0430\u0448\u0435\u0432\u043e"
    ],
    "wof:name":"Lesnoye Ardashevo",
    "wof:placetype":"locality"
},
  "geometry": {"coordinates":[43.13419,54.58356],"type":"Point"}
}