{
  "type": "Feature",
  "properties": {
    "gn:admin1_code":"51.0",
    "gn:asciiname":"Bol'shoye Tarasovo",
    "gn:country_code":"RU",
    "gn:dem":134,
    "gn:feature_class":"P",
    "gn:feature_code":"PPL",
    "gn:name":"Bol\u2019shoye Tarasovo",
    "gn:population":0,
    "gn:timezone":"Europe/Moscow",
    "iso:country":"RU",
    "name:rus_x_preferred":[
        "\u0411\u043e\u043b\u044c\u0448\u043e\u0435 \u0422\u0430\u0440\u0430\u0441\u043e\u0432\u043e"
    ],
    "name:und_x_variant":[
        "Bol\u2019shoye Tarasovo"
    ],
    "wof:name":"Bol'shoye Tarasovo",
    "wof:placetype":"locality"
},
  "geometry": {"coordinates":[45.98848,57.29738],"type":"Point"}
}