{
  "type": "Feature",
  "properties": {
    "gn:admin1_code":"86",
    "gn:asciiname":"Novopokrovka",
    "gn:country_code":"RU",
    "gn:dem":157,
    "gn:feature_class":"P",
    "gn:feature_code":"PPL",
    "gn:name":"Novopokrovka",
    "gn:population":0,
    "gn:timezone":"Europe/Moscow",
    "iso:country":"RU",
    "name:rus_x_preferred":[
        "\u041d\u043e\u0432\u043e\u043f\u043e\u043a\u0440\u043e\u0432\u043a\u0430"
    ],
    "wof:name":"Novopokrovka",
    "wof:placetype":"locality"
},
  "geometry": {"coordinates":[40.317,51.7422],"type":"Point"}
}