{
  "type": "Feature",
  "properties": {
    "gn:admin1_code":"28",
    "gn:asciiname":"Mal'yanen",
    "gn:country_code":"RU",
    "gn:dem":37,
    "gn:feature_class":"P",
    "gn:feature_code":"PPL",
    "gn:name":"Mal\u2019yanen",
    "gn:population":0,
    "gn:timezone":"Europe/Moscow",
    "iso:country":"RU",
    "name:fin_x_preferred":[
        "Maljanen"
    ],
    "name:rus_x_preferred":[
        "\u041c\u0430\u043b\u044c\u044f\u043d\u0435\u043d"
    ],
    "name:und_x_variant":[
        "Mal\u2019yanen",
        "\u041c\u0430\u043b\u044c\u044f\u043d\u0435\u043d"
    ],
    "wof:name":"Mal'yanen",
    "wof:placetype":"locality"
},
  "geometry": {"coordinates":[31.62998,61.5114],"type":"Point"}
}