{
  "type": "Feature",
  "properties": {
    "gn:admin1_code":"4",
    "gn:asciiname":"Tokarevo",
    "gn:country_code":"RU",
    "gn:dem":137,
    "gn:feature_class":"P",
    "gn:feature_code":"PPL",
    "gn:name":"Tokar\u00ebvo",
    "gn:population":0,
    "gn:timezone":"Asia/Barnaul",
    "iso:country":"RU",
    "name:rus_x_preferred":[
        "\u0422\u043e\u043a\u0430\u0440\u00eb\u0432\u043e"
    ],
    "name:und_x_variant":[
        "Tokar\u00ebvo"
    ],
    "wof:name":"Tokarevo",
    "wof:placetype":"locality"
},
  "geometry": {"coordinates":[83.947,53.45],"type":"Point"}
}