{
  "type": "Feature",
  "properties": {
    "gn:admin1_code":"91",
    "gn:asciiname":"Novotroitsk",
    "gn:country_code":"RU",
    "gn:dem":186,
    "gn:feature_class":"P",
    "gn:feature_code":"PPL",
    "gn:name":"Novotroitsk",
    "gn:population":0,
    "gn:timezone":"Asia/Krasnoyarsk",
    "iso:country":"RU",
    "name:eng_x_preferred":[
        "Novotroitsk"
    ],
    "name:nor_x_preferred":[
        "Novotroitsk"
    ],
    "name:rus_x_preferred":[
        "\u041d\u043e\u0432\u043e\u0442\u0440\u043e\u0438\u0446\u043a"
    ],
    "wof:name":"Novotroitsk",
    "wof:placetype":"locality"
},
  "geometry": {"coordinates":[93.5735,57.6009],"type":"Point"}
}