{
  "type": "Feature",
  "properties": {
    "gn:admin1_code":"61.0",
    "gn:asciiname":"Kalabukhov",
    "gn:country_code":"RU",
    "gn:dem":67,
    "gn:feature_class":"P",
    "gn:feature_code":"PPL",
    "gn:name":"Kalabukhov",
    "gn:population":0,
    "gn:timezone":"Europe/Moscow",
    "iso:country":"RU",
    "name:rus_x_preferred":[
        "\u041a\u0430\u043b\u0430\u0431\u0443\u0445\u043e\u0432"
    ],
    "wof:name":"Kalabukhov",
    "wof:placetype":"locality"
},
  "geometry": {"coordinates":[40.91778,48.37],"type":"Point"}
}