{
  "type": "Feature",
  "properties": {
    "gn:admin1_code":"85",
    "gn:asciiname":"Ust'ye Arbezh",
    "gn:country_code":"RU",
    "gn:dem":135,
    "gn:feature_class":"P",
    "gn:feature_code":"PPL",
    "gn:name":"Ust\u2019ye Arbezh",
    "gn:population":0,
    "gn:timezone":"Europe/Moscow",
    "iso:country":"RU",
    "name:und_x_variant":[
        "Ust\u2019ye Arbekh",
        "Ust\u2019ye Arbezh"
    ],
    "wof:name":"Ust'ye Arbezh",
    "wof:placetype":"locality"
},
  "geometry": {"coordinates":[45.48333,60.86666999999999],"type":"Point"}
}