{
  "type": "Feature",
  "properties": {
    "gn:admin1_code":"6",
    "gn:asciiname":"Palkinskaya",
    "gn:country_code":"RU",
    "gn:dem":96,
    "gn:feature_class":"P",
    "gn:feature_code":"PPL",
    "gn:name":"Palkinskaya",
    "gn:population":0,
    "gn:timezone":"Europe/Moscow",
    "iso:country":"RU",
    "name:eng_x_preferred":[
        "Palkinskaya"
    ],
    "name:nor_x_preferred":[
        "Palkinskaja"
    ],
    "name:rus_x_preferred":[
        "\u041f\u0430\u043b\u043a\u0438\u043d\u0441\u043a\u0430\u044f"
    ],
    "name:und_x_variant":[
        "Romanikha"
    ],
    "wof:name":"Palkinskaya",
    "wof:placetype":"locality"
},
  "geometry": {"coordinates":[42.18039,61.10331],"type":"Point"}
}