{
  "type": "Feature",
  "properties": {
    "gn:admin1_code":"88",
    "gn:asciiname":"Pasynkovo",
    "gn:country_code":"RU",
    "gn:dem":128,
    "gn:feature_class":"P",
    "gn:feature_code":"PPL",
    "gn:name":"Pasynkovo",
    "gn:population":0,
    "gn:timezone":"Europe/Moscow",
    "iso:country":"RU",
    "name:rus_x_preferred":[
        "\u041f\u0430\u0441\u044b\u043d\u043a\u043e\u0432\u043e"
    ],
    "wof:name":"Pasynkovo",
    "wof:placetype":"locality"
},
  "geometry": {"coordinates":[39.31789000000001,57.88568000000001],"type":"Point"}
}