{
  "type": "Feature",
  "properties": {
    "gn:admin1_code":"10",
    "gn:asciiname":"Nechui",
    "gn:country_code":"RU",
    "gn:dem":135,
    "gn:feature_class":"P",
    "gn:feature_code":"PPL",
    "gn:name":"Nechui",
    "gn:population":0,
    "gn:timezone":"Europe/Moscow",
    "iso:country":"RU",
    "name:rus_x_preferred":[
        "\u041d\u0435\u0447\u0443\u0438"
    ],
    "name:und_x_variant":[
        "\u041d\u0435\u0447\u0443\u0438"
    ],
    "wof:name":"Nechui",
    "wof:placetype":"locality"
},
  "geometry": {"coordinates":[33.3188,52.48646],"type":"Point"}
}