{
  "type": "Feature",
  "properties": {
    "gn:admin1_code":"80",
    "gn:asciiname":"Malaya Cheptsa",
    "gn:country_code":"RU",
    "gn:dem":170,
    "gn:feature_class":"P",
    "gn:feature_code":"PPL",
    "gn:name":"Malaya Cheptsa",
    "gn:population":0,
    "gn:timezone":"Europe/Samara",
    "iso:country":"RU",
    "name:rus_x_preferred":[
        "\u041c\u0430\u043b\u0430\u044f \u0427\u0435\u043f\u0446\u0430"
    ],
    "name:und_x_variant":[
        "\u041c\u0430\u043b\u0430\u044f \u0427\u0435\u043f\u0446\u0430"
    ],
    "wof:name":"Malaya Cheptsa",
    "wof:placetype":"locality"
},
  "geometry": {"coordinates":[53.7646,57.6338],"type":"Point"}
}