{
  "type": "Feature",
  "properties": {
    "gn:admin1_code":"62",
    "gn:asciiname":"Smirnovka",
    "gn:country_code":"RU",
    "gn:dem":120,
    "gn:feature_class":"P",
    "gn:feature_code":"PPL",
    "gn:name":"Smirnovka",
    "gn:population":0,
    "gn:timezone":"Europe/Moscow",
    "iso:country":"RU",
    "name:che_x_preferred":[
        "\u0421\u043c\u0438\u0440\u043d\u043e\u0432\u043a\u0430"
    ],
    "name:rus_x_preferred":[
        "\u0421\u043c\u0438\u0440\u043d\u043e\u0432\u043a\u0430"
    ],
    "name:tgk_x_preferred":[
        "\u0421\u043c\u0438\u0440\u043d\u043e\u0432\u043a\u0430"
    ],
    "name:und_x_variant":[
        "\u0421\u043c\u0438\u0440\u043d\u043e\u0432\u043a\u0430"
    ],
    "wof:name":"Smirnovka",
    "wof:placetype":"locality"
},
  "geometry": {"coordinates":[41.27722,54.39861],"type":"Point"}
}