{
  "type": "Feature",
  "properties": {
    "gn:country":"RU",
    "gn:fcode":"PPL",
    "gn:population":4374,
    "iso:country":"RU",
    "name:bel_x_preferred":[
        "\u0421\u043e\u043a\u0430\u043b"
    ],
    "name:ben_x_preferred":[
        "\u09b8\u09cb\u0995\u09cb\u09b2"
    ],
    "name:bul_x_preferred":[
        "\u0421\u043e\u043a\u043e\u043b"
    ],
    "name:ceb_x_preferred":[
        "Sokol"
    ],
    "name:che_x_preferred":[
        "\u0421\u043e\u043a\u043e\u043b"
    ],
    "name:deu_x_preferred":[
        "Sokol"
    ],
    "name:ell_x_preferred":[
        "\u03a3\u03bf\u03ba\u03cc\u03bb"
    ],
    "name:eng_x_preferred":[
        "Sokol"
    ],
    "name:heb_x_preferred":[
        "\u05e1\u05d5\u05e7\u05d5\u05dc"
    ],
    "name:hin_x_preferred":[
        "\u0938\u094b\u0915\u094b\u0932"
    ],
    "name:ind_x_preferred":[
        "Sokol"
    ],
    "name:ita_x_preferred":[
        "Sokol"
    ],
    "name:jpn_x_preferred":[
        "\u30bd\u30b3\u30eb"
    ],
    "name:nld_x_preferred":[
        "Sokol"
    ],
    "name:nor_x_preferred":[
        "Sokol"
    ],
    "name:pol_x_preferred":[
        "Soko\u0142"
    ],
    "name:rus_x_preferred":[
        "\u0421\u043e\u043a\u043e\u043b"
    ],
    "name:slk_x_preferred":[
        "Sokol"
    ],
    "name:spa_x_preferred":[
        "Sokol"
    ],
    "name:swe_x_preferred":[
        "Sokol"
    ],
    "name:tgl_x_preferred":[
        "Sokol"
    ],
    "name:urd_x_preferred":[
        "\u0633\u0648\u06a9\u0648\u0644"
    ],
    "name:vie_x_preferred":[
        "Sokol"
    ],
    "name:zho_x_preferred":[
        "\u7d22\u79d1\u723e"
    ],
    "qs:name":"Sokol",
    "qs:name_adm0":"Russia",
    "qs:name_adm1":"Magadan Oblast",
    "qs:photos_9k":1,
    "qs:photos_9r":2,
    "qs:photos_all":41,
    "qs:photos_sr":0,
    "qs:placetype":"Town",
    "qs:pop_sr":"4",
    "wd:wordcount":2486,
    "wof:name":"Sokol",
    "wof:placetype":"locality",
    "wof:population":4374
},
  "geometry": {"coordinates":[150.74956,59.91834],"type":"Point"}
}