{
  "type": "Feature",
  "properties": {
    "gn:admin1_code":"90",
    "gn:asciiname":"Zemplyagash",
    "gn:country_code":"RU",
    "gn:dem":163,
    "gn:feature_class":"P",
    "gn:feature_code":"PPL",
    "gn:name":"Zemplyagash",
    "gn:population":0,
    "gn:timezone":"Asia/Yekaterinburg",
    "iso:country":"RU",
    "name:eng_x_preferred":[
        "Zemplyagash"
    ],
    "name:nor_x_preferred":[
        "Zempljagasj"
    ],
    "name:rus_x_preferred":[
        "\u0417\u0435\u043c\u043f\u043b\u044f\u0433\u0430\u0448"
    ],
    "wof:name":"Zemplyagash",
    "wof:placetype":"locality"
},
  "geometry": {"coordinates":[55.3549,56.6688],"type":"Point"}
}