{
  "type": "Feature",
  "properties": {
    "gn:admin1_code":"8",
    "gn:asciiname":"Kyryn-Yurt",
    "gn:country_code":"RU",
    "gn:dem":519,
    "gn:feature_class":"P",
    "gn:feature_code":"PPL",
    "gn:name":"Kyryn-Yurt",
    "gn:population":0,
    "gn:timezone":"Asia/Yekaterinburg",
    "iso:country":"RU",
    "wof:name":"Kyryn-Yurt",
    "wof:placetype":"locality"
},
  "geometry": {"coordinates":[56.88333000000001,53.73333],"type":"Point"}
}