{
  "type": "Feature",
  "properties": {
    "gn:admin1_code":"62",
    "gn:asciiname":"Svishchevo",
    "gn:country_code":"RU",
    "gn:dem":118,
    "gn:feature_class":"P",
    "gn:feature_code":"PPL",
    "gn:name":"Svishch\u00ebvo",
    "gn:population":0,
    "gn:timezone":"Europe/Moscow",
    "iso:country":"RU",
    "wof:name":"Svishchevo",
    "wof:placetype":"locality"
},
  "geometry": {"coordinates":[41.79856,54.48813000000001],"type":"Point"}
}