{
  "type": "Feature",
  "properties": {
    "gn:admin1_code":"83",
    "gn:asciiname":"Pribrezhnaya",
    "gn:country_code":"RU",
    "gn:dem":105,
    "gn:feature_class":"P",
    "gn:feature_code":"PPL",
    "gn:name":"Pribrezhnaya",
    "gn:population":0,
    "gn:timezone":"Europe/Moscow",
    "iso:country":"RU",
    "name:rus_x_preferred":[
        "\u041f\u0440\u0438\u0431\u0440\u0435\u0436\u043d\u0430\u044f"
    ],
    "name:und_x_variant":[
        "Mar\u2019in-Oselok",
        "Pribrezhnaya"
    ],
    "wof:name":"Pribrezhnaya",
    "wof:placetype":"locality"
},
  "geometry": {"coordinates":[41.742,55.9668],"type":"Point"}
}