{
  "type": "Feature",
  "properties": {
    "gn:admin1_code":"17",
    "gn:asciiname":"Shizhivut",
    "gn:country_code":"RU",
    "gn:dem":-17,
    "gn:feature_class":"P",
    "gn:feature_code":"PPL",
    "gn:name":"Shizhivut",
    "gn:population":0,
    "gn:timezone":"Europe/Moscow",
    "iso:country":"RU",
    "name:rus_x_preferred":[
        "\u0428\u0438\u0436\u0438\u0432\u0443\u0442"
    ],
    "name:und_x_variant":[
        "\u0428\u0438\u0436\u0438\u0432\u0443\u0442"
    ],
    "wof:name":"Shizhivut",
    "wof:placetype":"locality"
},
  "geometry": {"coordinates":[47.21667,43.78333],"type":"Point"}
}