{
  "type": "Feature",
  "properties": {
    "gn:admin1_code":"84",
    "gn:asciiname":"Morozovo",
    "gn:country_code":"RU",
    "gn:dem":130,
    "gn:feature_class":"P",
    "gn:feature_code":"PPL",
    "gn:name":"Morozovo",
    "gn:population":0,
    "gn:timezone":"Europe/Volgograd",
    "iso:country":"RU",
    "name:eng_x_preferred":[
        "Morozovo"
    ],
    "name:nor_x_preferred":[
        "Morozovo"
    ],
    "name:rus_x_preferred":[
        "\u041c\u043e\u0440\u043e\u0437\u043e\u0432\u043e"
    ],
    "wof:name":"Morozovo",
    "wof:placetype":"locality"
},
  "geometry": {"coordinates":[44.88976,50.75871],"type":"Point"}
}