{
  "type": "Feature",
  "properties": {
    "gn:admin1_code":"28",
    "gn:asciiname":"Kutunen",
    "gn:cc2":"RU",
    "gn:country_code":"RU",
    "gn:dem":189,
    "gn:feature_class":"P",
    "gn:feature_code":"PPL",
    "gn:name":"Kutunen",
    "gn:population":0,
    "gn:timezone":"Europe/Moscow",
    "iso:country":"RU",
    "name:fin_x_preferred":[
        "Kutunen"
    ],
    "name:rus_x_preferred":[
        "\u041a\u0443\u0442\u0443\u043d\u0435\u043d"
    ],
    "name:und_x_variant":[
        "Kutun\u2019"
    ],
    "wof:name":"Kutunen",
    "wof:placetype":"locality"
},
  "geometry": {"coordinates":[30.74661,65.68316999999999],"type":"Point"}
}