{
  "type": "Feature",
  "properties": {
    "gn:admin1_code":"69",
    "gn:asciiname":"Zakharovo",
    "gn:country_code":"RU",
    "gn:dem":240,
    "gn:feature_class":"P",
    "gn:feature_code":"PPL",
    "gn:name":"Zakharovo",
    "gn:population":0,
    "gn:timezone":"Europe/Moscow",
    "iso:country":"RU",
    "wof:name":"Zakharovo",
    "wof:placetype":"locality"
},
  "geometry": {"coordinates":[33.55975,55.74556],"type":"Point"}
}