{
  "type": "Feature",
  "properties": {
    "gn:admin1_code":"10",
    "gn:asciiname":"Polyakovka",
    "gn:country_code":"RU",
    "gn:dem":217,
    "gn:feature_class":"P",
    "gn:feature_code":"PPL",
    "gn:name":"Polyakovka",
    "gn:population":0,
    "gn:timezone":"Europe/Moscow",
    "iso:country":"RU",
    "name:rus_x_preferred":[
        "\u041f\u043e\u043b\u044f\u043a\u043e\u0432\u043a\u0430"
    ],
    "wof:name":"Polyakovka",
    "wof:placetype":"locality"
},
  "geometry": {"coordinates":[33.2454,53.6173],"type":"Point"}
}