{
  "type": "Feature",
  "properties": {
    "gn:country":"RU",
    "gn:fcode":"PPL",
    "gn:population":2824,
    "iso:country":"RU",
    "name:nor_x_preferred":[
        "Firsanovka"
    ],
    "name:rus_x_preferred":[
        "\u0424\u0438\u0440\u0441\u0430\u043d\u043e\u0432\u043a\u0430"
    ],
    "name:und_x_variant":[
        "Firsanovskiy"
    ],
    "qs:name":"Firsanovka",
    "qs:name_adm0":"Russia",
    "qs:name_adm1":"Moscow Oblast",
    "qs:photos_9k":1,
    "qs:photos_9r":4,
    "qs:photos_all":184,
    "qs:photos_sr":0,
    "qs:placetype":"Town",
    "qs:pop_sr":"4",
    "wof:name":"Firsanovka",
    "wof:placetype":"locality",
    "wof:population":2824
},
  "geometry": {"coordinates":[37.24083,55.95361],"type":"Point"}
}