{
  "type": "Feature",
  "properties": {
    "gn:admin1_code":"40",
    "gn:asciiname":"Nikitino",
    "gn:country_code":"RU",
    "gn:dem":170,
    "gn:feature_class":"P",
    "gn:feature_code":"PPL",
    "gn:name":"Nikitino",
    "gn:population":0,
    "gn:timezone":"Asia/Yekaterinburg",
    "iso:country":"RU",
    "name:eng_x_preferred":[
        "Nikitino"
    ],
    "name:nor_x_preferred":[
        "Nikitino"
    ],
    "name:rus_x_preferred":[
        "\u041d\u0438\u043a\u0438\u0442\u0438\u043d\u043e"
    ],
    "name:und_x_variant":[
        "\u041d\u0438\u043a\u0438\u0442\u0438\u043d\u043e",
        "Nikitino"
    ],
    "wof:name":"Nikitino",
    "wof:placetype":"locality"
},
  "geometry": {"coordinates":[62.62556,55.46306],"type":"Point"}
}