{
  "type": "Feature",
  "properties": {
    "gn:admin1_code":"61",
    "gn:asciiname":"Grinev",
    "gn:country_code":"RU",
    "gn:dem":54,
    "gn:feature_class":"P",
    "gn:feature_code":"PPL",
    "gn:name":"Grin\u00ebv",
    "gn:population":0,
    "gn:timezone":"Europe/Moscow",
    "iso:country":"RU",
    "name:rus_x_preferred":[
        "\u0413\u0440\u0438\u043d\u0451\u0432"
    ],
    "name:und_x_variant":[
        "Grin\u00ebv"
    ],
    "wof:name":"Grinev",
    "wof:placetype":"locality"
},
  "geometry": {"coordinates":[41.37371,48.43175],"type":"Point"}
}