{
  "type": "Feature",
  "properties": {
    "gn:admin1_code":"46",
    "gn:asciiname":"Rybnyy",
    "gn:country_code":"RU",
    "gn:dem":163,
    "gn:feature_class":"P",
    "gn:feature_code":"PPL",
    "gn:name":"Rybnyy",
    "gn:population":0,
    "gn:timezone":"Europe/Moscow",
    "iso:country":"RU",
    "name:rus_x_preferred":[
        "\u0420\u044b\u0431\u043d\u044b\u0439"
    ],
    "name:und_x_variant":[
        "\u0420\u044b\u0431\u043d\u044b\u0439"
    ],
    "wof:name":"Rybnyy",
    "wof:placetype":"locality"
},
  "geometry": {"coordinates":[45.0199,54.1253],"type":"Point"}
}