{
  "type": "Feature",
  "properties": {
    "gn:admin1_code":"76",
    "gn:asciiname":"Gvardeyskiy",
    "gn:country_code":"RU",
    "gn:dem":233,
    "gn:feature_class":"P",
    "gn:feature_code":"PPL",
    "gn:name":"Gvardeyskiy",
    "gn:population":0,
    "gn:timezone":"Europe/Moscow",
    "iso:country":"RU",
    "name:nor_x_preferred":[
        "Gvardejskij"
    ],
    "name:rus_x_preferred":[
        "\u0413\u0432\u0430\u0440\u0434\u0435\u0439\u0441\u043a\u0438\u0439"
    ],
    "wof:name":"Gvardeyskiy",
    "wof:placetype":"locality"
},
  "geometry": {"coordinates":[36.9375,54.11878000000001],"type":"Point"}
}