{
  "type": "Feature",
  "properties": {
    "gn:admin1_code":"57",
    "gn:asciiname":"Volkhon-Umet",
    "gn:country_code":"RU",
    "gn:dem":231,
    "gn:feature_class":"P",
    "gn:feature_code":"PPL",
    "gn:name":"Volkhon-Um\u00ebt",
    "gn:population":0,
    "gn:timezone":"Europe/Moscow",
    "iso:country":"RU",
    "name:und_x_variant":[
        "Volkh-Umet",
        "Vol\u2019ny Umet",
        "Volkhono-Umet",
        "Volkhon-Um\u00ebt"
    ],
    "wof:name":"Volkhon-Umet",
    "wof:placetype":"locality"
},
  "geometry": {"coordinates":[45.1248,52.70905],"type":"Point"}
}