{
  "type": "Feature",
  "properties": {
    "gn:admin1_code":"23",
    "gn:asciiname":"Pyatidorozhnoye",
    "gn:country_code":"RU",
    "gn:dem":74,
    "gn:feature_class":"P",
    "gn:feature_code":"PPL",
    "gn:name":"Pyatidorozhnoye",
    "gn:population":0,
    "gn:timezone":"Europe/Kaliningrad",
    "iso:country":"RU",
    "name:eng_x_preferred":[
        "Pyatidorozhnoye"
    ],
    "name:nor_x_preferred":[
        "Pjatidorozjnoje"
    ],
    "name:rus_x_preferred":[
        "\u041f\u044f\u0442\u0438\u0434\u043e\u0440\u043e\u0436\u043d\u043e\u0435"
    ],
    "name:und_x_variant":[
        "Bladiau",
        "Pjatidoro\u017enoe",
        "Bladyau",
        "\u041f\u044f\u0442\u0438\u0434\u043e\u0440\u043e\u0436\u043d\u043e\u0435",
        "Pyatidorozhnoye"
    ],
    "wof:name":"Pyatidorozhnoye",
    "wof:placetype":"locality"
},
  "geometry": {"coordinates":[20.09893,54.50202],"type":"Point"}
}