{
  "type": "Feature",
  "properties": {
    "gn:admin1_code":"9.0",
    "gn:asciiname":"Nadezhda",
    "gn:country_code":"RU",
    "gn:dem":104,
    "gn:feature_class":"P",
    "gn:feature_code":"PPL",
    "gn:name":"Nadezhda",
    "gn:population":0,
    "gn:timezone":"Europe/Moscow",
    "iso:country":"RU",
    "name:bul_x_preferred":[
        "\u041d\u0430\u0434\u0435\u0436\u0434\u0430"
    ],
    "name:ceb_x_preferred":[
        "Nadezhda"
    ],
    "name:deu_x_preferred":[
        "Nadezhda"
    ],
    "name:fra_x_preferred":[
        "Nad\u00e8ge"
    ],
    "name:hye_x_preferred":[
        "\u0546\u0561\u0564\u0565\u056a\u0564\u0561"
    ],
    "name:nld_x_preferred":[
        "Nadezjda"
    ],
    "name:rus_x_preferred":[
        "\u041d\u0430\u0434\u0435\u0436\u0434\u0430"
    ],
    "name:slk_x_preferred":[
        "N\u00e1dej"
    ],
    "name:spa_x_preferred":[
        "Nadezhda"
    ],
    "name:swe_x_preferred":[
        "Nadezhda"
    ],
    "name:ukr_x_preferred":[
        "\u041d\u0430\u0434\u0435\u0436\u0434\u0430"
    ],
    "wof:name":"Nadezhda",
    "wof:placetype":"locality"
},
  "geometry": {"coordinates":[38.38583,50.13111],"type":"Point"}
}