{
  "type": "Feature",
  "properties": {
    "gn:admin1_code":"90",
    "gn:asciiname":"Ust'-Syny",
    "gn:country_code":"RU",
    "gn:dem":102,
    "gn:feature_class":"P",
    "gn:feature_code":"PPL",
    "gn:name":"Ust\u2019-Syny",
    "gn:population":0,
    "gn:timezone":"Asia/Yekaterinburg",
    "iso:country":"RU",
    "name:eng_x_preferred":[
        "Ust'-Syny"
    ],
    "name:nor_x_preferred":[
        "Ust-Syny"
    ],
    "name:rus_x_preferred":[
        "\u0423\u0441\u0442\u044c-\u0421\u044b\u043d\u044b"
    ],
    "name:und_x_variant":[
        "Ust\u2019-Syny"
    ],
    "wof:name":"Ust'-Syny",
    "wof:placetype":"locality"
},
  "geometry": {"coordinates":[55.5755,58.0449],"type":"Point"}
}