{
  "type": "Feature",
  "properties": {
    "gn:admin1_code":"28",
    "gn:asciiname":"Rantue",
    "gn:country_code":"RU",
    "gn:dem":11,
    "gn:feature_class":"P",
    "gn:feature_code":"PPL",
    "gn:name":"Rantue",
    "gn:population":0,
    "gn:timezone":"Europe/Moscow",
    "iso:country":"RU",
    "name:fin_x_preferred":[
        "Rantue"
    ],
    "name:rus_x_preferred":[
        "\u0420\u0430\u043d\u0442\u0443\u044d"
    ],
    "wof:name":"Rantue",
    "wof:placetype":"locality"
},
  "geometry": {"coordinates":[30.71667,61.66667],"type":"Point"}
}