{
  "type": "Feature",
  "properties": {
    "gn:admin1_code":"33.0",
    "gn:asciiname":"Molchanovshchina",
    "gn:country_code":"RU",
    "gn:dem":129,
    "gn:feature_class":"P",
    "gn:feature_code":"PPL",
    "gn:name":"Molchanovshchina",
    "gn:population":0,
    "gn:timezone":"Europe/Kirov",
    "iso:country":"RU",
    "name:rus_x_preferred":[
        "\u041c\u043e\u043b\u0447\u0430\u043d\u043e\u0432\u0449\u0438\u043d\u0430"
    ],
    "wof:name":"Molchanovshchina",
    "wof:placetype":"locality"
},
  "geometry": {"coordinates":[48.29091,58.6894],"type":"Point"}
}