{
  "type": "Feature",
  "properties": {
    "gn:admin1_code":"42",
    "gn:asciiname":"Moiseyevo",
    "gn:country_code":"RU",
    "gn:dem":42,
    "gn:feature_class":"P",
    "gn:feature_code":"PPL",
    "gn:name":"Moiseyevo",
    "gn:population":0,
    "gn:timezone":"Europe/Moscow",
    "iso:country":"RU",
    "name:rus_x_preferred":[
        "\u041c\u043e\u0438\u0441\u0435\u0435\u0432\u043e"
    ],
    "name:und_x_variant":[
        "Moseyevo",
        "Moiseyevo",
        "\u041c\u043e\u0438\u0441\u0435\u0435\u0432\u043e"
    ],
    "wof:name":"Moiseyevo",
    "wof:placetype":"locality"
},
  "geometry": {"coordinates":[32.40295,59.68834],"type":"Point"}
}