{
  "type": "Feature",
  "properties": {
    "gn:asciiname":"Privol'ye",
    "gn:country_code":"RU",
    "gn:dem":123,
    "gn:feature_class":"P",
    "gn:feature_code":"PPL",
    "gn:name":"Privol'ye",
    "gn:population":0,
    "gn:timezone":"Europe/Moscow",
    "iso:country":"RU",
    "wof:name":"Privol'ye",
    "wof:placetype":"locality"
},
  "geometry": {"coordinates":[44.06668,54.41294],"type":"Point"}
}