{
  "type": "Feature",
  "properties": {
    "gn:admin1_code":"88",
    "gn:asciiname":"Shishelovo",
    "gn:country_code":"RU",
    "gn:dem":122,
    "gn:feature_class":"P",
    "gn:feature_code":"PPL",
    "gn:name":"Shishelovo",
    "gn:population":0,
    "gn:timezone":"Europe/Moscow",
    "iso:country":"RU",
    "name:rus_x_preferred":[
        "\u0428\u0438\u0448\u0435\u043b\u043e\u0432\u043e"
    ],
    "name:und_x_variant":[
        "\u0428\u0438\u0448\u0435\u043b\u043e\u0432\u043e",
        "Shishelevo"
    ],
    "wof:name":"Shishelovo",
    "wof:placetype":"locality"
},
  "geometry": {"coordinates":[38.8658,57.8561],"type":"Point"}
}