{
  "type": "Feature",
  "properties": {
    "gn:admin1_code":"61.0",
    "gn:asciiname":"Blagodarnyy",
    "gn:country_code":"RU",
    "gn:dem":64,
    "gn:feature_class":"P",
    "gn:feature_code":"PPL",
    "gn:name":"Blagodarnyy",
    "gn:population":0,
    "gn:timezone":"Europe/Moscow",
    "iso:country":"RU",
    "name:rus_x_preferred":[
        "\u0411\u043b\u0430\u0433\u043e\u0434\u0430\u0440\u043d\u044b\u0439"
    ],
    "name:und_x_variant":[
        "Blagodarnaya"
    ],
    "wof:name":"Blagodarnyy",
    "wof:placetype":"locality"
},
  "geometry": {"coordinates":[41.16864,46.76552],"type":"Point"}
}