{
  "type": "Feature",
  "properties": {
    "gn:admin1_code":"10",
    "gn:asciiname":"Verkhniy Sushets",
    "gn:country_code":"RU",
    "gn:dem":151,
    "gn:feature_class":"P",
    "gn:feature_code":"PPL",
    "gn:name":"Verkhniy Sushets",
    "gn:population":0,
    "gn:timezone":"Europe/Moscow",
    "iso:country":"RU",
    "wof:name":"Verkhniy Sushets",
    "wof:placetype":"locality"
},
  "geometry": {"coordinates":[31.64139,53.03639],"type":"Point"}
}