{
  "type": "Feature",
  "properties": {
    "gn:admin1_code":"20",
    "gn:asciiname":"Biryusa",
    "gn:country_code":"RU",
    "gn:dem":244,
    "gn:feature_class":"P",
    "gn:feature_code":"PPL",
    "gn:name":"Biryusa",
    "gn:population":0,
    "gn:timezone":"Asia/Irkutsk",
    "iso:country":"RU",
    "name:eng_x_preferred":[
        "Biryusa"
    ],
    "name:nor_x_preferred":[
        "Birjusa"
    ],
    "name:rus_x_preferred":[
        "\u0411\u0438\u0440\u044e\u0441\u0430"
    ],
    "name:und_x_variant":[
        "\u0411\u0438\u0440\u044e\u0441\u0430",
        "Biryusa"
    ],
    "wof:name":"Biryusa",
    "wof:placetype":"locality"
},
  "geometry": {"coordinates":[97.8942,55.994],"type":"Point"}
}