{
  "type": "Feature",
  "properties": {
    "gn:admin1_code":"47",
    "gn:asciiname":"Merenishchevo",
    "gn:cc2":"RU",
    "gn:country_code":"RU",
    "gn:dem":236,
    "gn:feature_class":"P",
    "gn:feature_code":"PPL",
    "gn:name":"Merenishchevo",
    "gn:population":0,
    "gn:timezone":"Europe/Moscow",
    "iso:country":"RU",
    "name:rus_x_preferred":[
        "\u041c\u0435\u0440\u0435\u043d\u0438\u0449\u0435\u0432\u043e"
    ],
    "name:und_x_variant":[
        "Butyrki",
        "Merenishchevo"
    ],
    "wof:name":"Merenishchevo",
    "wof:placetype":"locality"
},
  "geometry": {"coordinates":[35.33667,55.56194],"type":"Point"}
}