{
  "type": "Feature",
  "properties": {
    "gn:admin1_code":"38.0",
    "gn:asciiname":"Gladkovskie",
    "gn:country_code":"RU",
    "gn:dem":18,
    "gn:feature_class":"P",
    "gn:feature_code":"PPL",
    "gn:name":"Gladkovskie",
    "gn:population":0,
    "gn:timezone":"Europe/Moscow",
    "iso:country":"RU",
    "name:rus_x_preferred":[
        "\u0413\u043b\u0430\u0434\u043a\u043e\u0432\u0441\u043a\u0438\u044d"
    ],
    "wof:name":"Gladkovskie",
    "wof:placetype":"locality"
},
  "geometry": {"coordinates":[38.07667,44.90861],"type":"Point"}
}