{
  "type": "Feature",
  "properties": {
    "gn:admin1_code":"90",
    "gn:asciiname":"Ozhga",
    "gn:country_code":"RU",
    "gn:dem":168,
    "gn:feature_class":"P",
    "gn:feature_code":"PPL",
    "gn:name":"Ozhga",
    "gn:population":0,
    "gn:timezone":"Asia/Yekaterinburg",
    "iso:country":"RU",
    "name:rus_x_preferred":[
        "\u041e\u0436\u0433\u0430"
    ],
    "wof:name":"Ozhga",
    "wof:placetype":"locality"
},
  "geometry": {"coordinates":[56.75642,57.62767],"type":"Point"}
}