{
  "type": "Feature",
  "properties": {
    "gn:admin1_code":"11",
    "gn:asciiname":"Apkharok",
    "gn:country_code":"RU",
    "gn:dem":914,
    "gn:feature_class":"P",
    "gn:feature_code":"PPL",
    "gn:name":"Apkharok",
    "gn:population":0,
    "gn:timezone":"Asia/Irkutsk",
    "iso:country":"RU",
    "name:nor_x_preferred":[
        "Apkharok"
    ],
    "name:rus_x_preferred":[
        "\u0410\u043f\u0445\u0430\u0440\u043e\u043a"
    ],
    "wof:name":"Apkharok",
    "wof:placetype":"locality"
},
  "geometry": {"coordinates":[112.90000000000001,53.36666999999999],"type":"Point"}
}