{
  "type": "Feature",
  "properties": {
    "gn:admin1_code":"5.0",
    "gn:asciiname":"Grigor'yevka",
    "gn:country_code":"RU",
    "gn:dem":216,
    "gn:feature_class":"P",
    "gn:feature_code":"PPL",
    "gn:name":"Grigor\u2019yevka",
    "gn:population":0,
    "gn:timezone":"Asia/Yakutsk",
    "iso:country":"RU",
    "name:kir_x_preferred":[
        "\u0413\u0440\u0438\u0433\u043e\u0440\u044c\u0435\u0432\u043a\u0430"
    ],
    "name:rus_x_preferred":[
        "\u0413\u0440\u0438\u0433\u043e\u0440\u044c\u0435\u0432\u043a\u0430"
    ],
    "wof:name":"Grigor'yevka",
    "wof:placetype":"locality"
},
  "geometry": {"coordinates":[128.78666000000001,50.5178],"type":"Point"}
}