{
  "type": "Feature",
  "properties": {
    "gn:admin1_code":"73",
    "gn:asciiname":"Bol'shaya Mesha",
    "gn:country_code":"RU",
    "gn:dem":109,
    "gn:feature_class":"P",
    "gn:feature_code":"PPL",
    "gn:name":"Bol\u2019shaya M\u00ebsha",
    "gn:population":0,
    "gn:timezone":"Europe/Moscow",
    "iso:country":"RU",
    "name:rus_x_preferred":[
        "\u0411\u043e\u043b\u044c\u0448\u0430\u044f \u041c\u00eb\u0448\u0430"
    ],
    "name:und_x_variant":[
        "Bol\u2019shaya M\u00ebsha"
    ],
    "wof:name":"Bol'shaya Mesha",
    "wof:placetype":"locality"
},
  "geometry": {"coordinates":[50.5238,55.8189],"type":"Point"}
}