{
  "type": "Feature",
  "properties": {
    "gn:admin1_code":"70",
    "gn:asciiname":"Tuguluk",
    "gn:country_code":"RU",
    "gn:dem":278,
    "gn:feature_class":"P",
    "gn:feature_code":"PPL",
    "gn:name":"Tuguluk",
    "gn:population":0,
    "gn:timezone":"Europe/Moscow",
    "iso:country":"RU",
    "name:eng_x_preferred":[
        "Tuguluk"
    ],
    "name:nor_x_preferred":[
        "Tuguluk"
    ],
    "name:rus_x_preferred":[
        "\u0422\u0443\u0433\u0443\u043b\u0443\u043a"
    ],
    "wof:name":"Tuguluk",
    "wof:placetype":"locality"
},
  "geometry": {"coordinates":[42.24778,45.33778],"type":"Point"}
}