{
  "type": "Feature",
  "properties": {
    "gn:admin1_code":"53",
    "gn:asciiname":"Ovchinnikovo",
    "gn:cc2":"RU",
    "gn:country_code":"RU",
    "gn:dem":163,
    "gn:feature_class":"P",
    "gn:feature_code":"PPL",
    "gn:name":"Ovchinnikovo",
    "gn:population":0,
    "gn:timezone":"Asia/Novosibirsk",
    "iso:country":"RU",
    "name:eng_x_preferred":[
        "Ovchinnikovo"
    ],
    "name:nor_x_preferred":[
        "Ovtsjinnikovo"
    ],
    "name:rus_x_preferred":[
        "\u041e\u0432\u0447\u0438\u043d\u043d\u0438\u043a\u043e\u0432\u043e"
    ],
    "name:und_x_variant":[
        "Ovchimikova",
        "\u041e\u0432\u0447\u0438\u043d\u043d\u0438\u043a\u043e\u0432\u043e",
        "Ovchinnikovo"
    ],
    "wof:name":"Ovchinnikovo",
    "wof:placetype":"locality"
},
  "geometry": {"coordinates":[81.68833000000002,55.19861],"type":"Point"}
}