{
  "type": "Feature",
  "properties": {
    "gn:admin1_code":"52.0",
    "gn:asciiname":"Dorokhovo",
    "gn:country_code":"RU",
    "gn:dem":175,
    "gn:feature_class":"P",
    "gn:feature_code":"PPL",
    "gn:name":"Dorokhovo",
    "gn:population":0,
    "gn:timezone":"Europe/Moscow",
    "iso:country":"RU",
    "name:rus_x_preferred":[
        "\u0414\u043e\u0440\u043e\u0445\u043e\u0432\u043e"
    ],
    "wof:name":"Dorokhovo",
    "wof:placetype":"locality"
},
  "geometry": {"coordinates":[35.41667,58.48333],"type":"Point"}
}