{
  "type": "Feature",
  "properties": {
    "gn:admin1_code":"33.0",
    "gn:asciiname":"Chuchi",
    "gn:country_code":"RU",
    "gn:dem":129,
    "gn:feature_class":"P",
    "gn:feature_code":"PPL",
    "gn:name":"Chuchi",
    "gn:population":0,
    "gn:timezone":"Europe/Kirov",
    "iso:country":"RU",
    "name:rus_x_preferred":[
        "\u0427\u0443\u0447\u0438"
    ],
    "wof:name":"Chuchi",
    "wof:placetype":"locality"
},
  "geometry": {"coordinates":[49.42683,58.54519000000001],"type":"Point"}
}