{
  "type": "Feature",
  "properties": {
    "gn:admin1_code":"52",
    "gn:asciiname":"Shushelovo",
    "gn:country_code":"RU",
    "gn:dem":85,
    "gn:feature_class":"P",
    "gn:feature_code":"PPL",
    "gn:name":"Shushelovo",
    "gn:population":0,
    "gn:timezone":"Europe/Moscow",
    "iso:country":"RU",
    "name:rus_x_preferred":[
        "\u0428\u0443\u0448\u0435\u043b\u043e\u0432\u043e"
    ],
    "name:und_x_variant":[
        "Vet\u2019ye",
        "Shushelovo",
        "\u0428\u0443\u0448\u0435\u043b\u043e\u0432\u043e"
    ],
    "wof:name":"Shushelovo",
    "wof:placetype":"locality"
},
  "geometry": {"coordinates":[30.54504,57.48941],"type":"Point"}
}