{
  "type": "Feature",
  "properties": {
    "gn:admin1_code":"90",
    "gn:asciiname":"Isakovo",
    "gn:country_code":"RU",
    "gn:dem":166,
    "gn:feature_class":"P",
    "gn:feature_code":"PPL",
    "gn:name":"Isakovo",
    "gn:population":0,
    "gn:timezone":"Asia/Yekaterinburg",
    "iso:country":"RU",
    "name:rus_x_preferred":[
        "\u0418\u0441\u0430\u043a\u043e\u0432\u043e"
    ],
    "name:und_x_variant":[
        "\u0418\u0441\u0430\u043a\u043e\u0432\u043e"
    ],
    "wof:name":"Isakovo",
    "wof:placetype":"locality"
},
  "geometry": {"coordinates":[56.25899999999999,59.9422],"type":"Point"}
}