{
  "type": "Feature",
  "properties": {
    "gn:admin1_code":"73",
    "gn:asciiname":"Kichkeyevo",
    "gn:country_code":"RU",
    "gn:dem":75,
    "gn:feature_class":"P",
    "gn:feature_code":"PPL",
    "gn:name":"Kichkeyevo",
    "gn:population":0,
    "gn:timezone":"Europe/Moscow",
    "iso:country":"RU",
    "name:rus_x_preferred":[
        "\u041a\u0438\u0447\u043a\u0435\u0435\u0432\u043e"
    ],
    "wof:name":"Kichkeyevo",
    "wof:placetype":"locality"
},
  "geometry": {"coordinates":[47.99406,55.48475],"type":"Point"}
}