{
  "type": "Feature",
  "properties": {
    "gn:admin1_code":"59",
    "gn:asciiname":"Pospelovo",
    "gn:country_code":"RU",
    "gn:dem":13,
    "gn:feature_class":"P",
    "gn:feature_code":"PPL",
    "gn:name":"Pospelovo",
    "gn:population":0,
    "gn:timezone":"Asia/Vladivostok",
    "iso:country":"RU",
    "name:rus_x_preferred":[
        "\u041f\u043e\u0441\u043f\u0435\u043b\u043e\u0432\u043e"
    ],
    "wof:name":"Pospelovo",
    "wof:placetype":"locality"
},
  "geometry": {"coordinates":[131.88756999999998,43.05846],"type":"Point"}
}