{
  "type": "Feature",
  "properties": {
    "gn:admin1_code":"16",
    "gn:asciiname":"Khozankino",
    "gn:country_code":"RU",
    "gn:dem":164,
    "gn:feature_class":"P",
    "gn:feature_code":"PPL",
    "gn:name":"Khozankino",
    "gn:population":0,
    "gn:timezone":"Europe/Moscow",
    "iso:country":"RU",
    "name:rus_x_preferred":[
        "\u0425\u043e\u0437\u0430\u043d\u043a\u0438\u043d\u043e"
    ],
    "name:und_x_variant":[
        "\u0425\u043e\u0437\u0430\u043d\u043a\u0438\u043d\u043e"
    ],
    "wof:name":"Khozankino",
    "wof:placetype":"locality"
},
  "geometry": {"coordinates":[46.32468,55.72042],"type":"Point"}
}