{
  "type": "Feature",
  "properties": {
    "gn:admin1_code":"83",
    "gn:asciiname":"Levenda",
    "gn:country_code":"RU",
    "gn:dem":121,
    "gn:feature_class":"P",
    "gn:feature_code":"PPL",
    "gn:name":"Levenda",
    "gn:population":0,
    "gn:timezone":"Europe/Moscow",
    "iso:country":"RU",
    "name:rus_x_preferred":[
        "\u041b\u0435\u0432\u0435\u043d\u0434\u0430"
    ],
    "name:und_x_variant":[
        "\u041b\u0435\u0432\u0435\u043d\u0434\u0430"
    ],
    "wof:name":"Levenda",
    "wof:placetype":"locality"
},
  "geometry": {"coordinates":[41.79766,55.31744000000001],"type":"Point"}
}