{
  "type": "Feature",
  "properties": {
    "gn:admin1_code":"6",
    "gn:asciiname":"Ust'ye",
    "gn:country_code":"RU",
    "gn:dem":115,
    "gn:feature_class":"P",
    "gn:feature_code":"PPL",
    "gn:name":"Ust\u2019ye",
    "gn:population":0,
    "gn:timezone":"Europe/Moscow",
    "iso:country":"RU",
    "name:eng_x_preferred":[
        "Ust'ye"
    ],
    "name:nor_x_preferred":[
        "Ustje"
    ],
    "name:rus_x_preferred":[
        "\u0423\u0441\u0442\u044c\u0435"
    ],
    "name:und_x_variant":[
        "Ust\u2019ye"
    ],
    "wof:name":"Ust'ye",
    "wof:placetype":"locality"
},
  "geometry": {"coordinates":[47.79525,61.51126],"type":"Point"}
}