{
  "type": "Feature",
  "properties": {
    "gn:admin1_code":"88",
    "gn:asciiname":"Troitsa",
    "gn:country_code":"RU",
    "gn:dem":150,
    "gn:feature_class":"P",
    "gn:feature_code":"PPL",
    "gn:name":"Troitsa",
    "gn:population":0,
    "gn:timezone":"Europe/Moscow",
    "iso:country":"RU",
    "name:eng_x_preferred":[
        "Troitsa"
    ],
    "name:nor_x_preferred":[
        "Troitsa"
    ],
    "name:rus_x_preferred":[
        "\u0422\u0440\u043e\u0438\u0446\u0430"
    ],
    "wof:name":"Troitsa",
    "wof:placetype":"locality"
},
  "geometry": {"coordinates":[40.70506,58.4977],"type":"Point"}
}