{
  "type": "Feature",
  "properties": {
    "gn:admin1_code":"28",
    "gn:asciiname":"Yurkovo",
    "gn:country_code":"RU",
    "gn:dem":37,
    "gn:feature_class":"P",
    "gn:feature_code":"PPL",
    "gn:name":"Yurkovo",
    "gn:population":0,
    "gn:timezone":"Europe/Moscow",
    "iso:country":"RU",
    "name:che_x_preferred":[
        "\u042e\u0440\u043a\u043e\u0432\u043e"
    ],
    "name:rus_x_preferred":[
        "\u042e\u0440\u043a\u043e\u0432\u043e"
    ],
    "wof:name":"Yurkovo",
    "wof:placetype":"locality"
},
  "geometry": {"coordinates":[34.75,62.61666999999999],"type":"Point"}
}