{
  "type": "Feature",
  "properties": {
    "gn:admin1_code":"56",
    "gn:asciiname":"Muratovo",
    "gn:country_code":"RU",
    "gn:dem":185,
    "gn:feature_class":"P",
    "gn:feature_code":"PPL",
    "gn:name":"Muratovo",
    "gn:population":0,
    "gn:timezone":"Europe/Moscow",
    "iso:country":"RU",
    "name:rus_x_preferred":[
        "\u041c\u0443\u0440\u0430\u0442\u043e\u0432\u043e"
    ],
    "name:und_x_variant":[
        "Muratovo Vtoroye",
        "Muratovo Pervoye",
        "Muratovo"
    ],
    "wof:name":"Muratovo",
    "wof:placetype":"locality"
},
  "geometry": {"coordinates":[35.64789000000001,53.06763],"type":"Point"}
}