{
  "type": "Feature",
  "properties": {
    "gn:admin1_code":"10",
    "gn:asciiname":"Krasnaya Zvezda",
    "gn:country_code":"RU",
    "gn:dem":172,
    "gn:feature_class":"P",
    "gn:feature_code":"PPL",
    "gn:name":"Krasnaya Zvezda",
    "gn:population":0,
    "gn:timezone":"Europe/Moscow",
    "iso:country":"RU",
    "name:ara_x_preferred":[
        "\u0627\u0644\u0646\u062c\u0645 \u0627\u0644\u0623\u062d\u0645\u0631"
    ],
    "name:ces_x_preferred":[
        "Krasnaja zvezda"
    ],
    "name:dan_x_preferred":[
        "Krasnaja Svesda"
    ],
    "name:deu_x_preferred":[
        "Krasnaja Swesda"
    ],
    "name:fin_x_preferred":[
        "Krasnaja zvezda"
    ],
    "name:fra_x_preferred":[
        "Krasna\u00efa Zvezda"
    ],
    "name:heb_x_preferred":[
        "\u05d4\u05db\u05d5\u05db\u05d1 \u05d4\u05d0\u05d3\u05d5\u05dd"
    ],
    "name:hye_x_preferred":[
        "\u053f\u0580\u0561\u057d\u0576\u0561\u0575\u0561 \u0566\u057e\u0565\u0566\u0564\u0561"
    ],
    "name:ita_x_preferred":[
        "Stella Rossa"
    ],
    "name:jpn_x_preferred":[
        "\u30af\u30e9\u30b9\u30ca\u30e4\u30fb\u30ba\u30f4\u30a7\u30ba\u30c0"
    ],
    "name:nor_x_preferred":[
        "Krasnaja Zvezda"
    ],
    "name:pol_x_preferred":[
        "Krasnaja Zwiezda"
    ],
    "name:rus_x_preferred":[
        "\u041a\u0440\u0430\u0441\u043d\u0430\u044f \u0417\u0432\u0435\u0437\u0434\u0430"
    ],
    "name:rus_x_variant":[
        "\u041a\u0440\u0430\u0441\u043d\u0430\u044f \u0437\u0432\u0435\u0437\u0434\u0430"
    ],
    "name:spa_x_preferred":[
        "Kr\u00e1snaya zvezd\u00e1"
    ],
    "name:swe_x_preferred":[
        "Krasnaja Zvezda"
    ],
    "name:tha_x_preferred":[
        "\u0e04\u0e23\u0e31\u0e2a\u0e19\u0e32\u0e22\u0e32\u0e0b\u0e40\u0e27\u0e0b\u0e14\u0e32"
    ],
    "name:tur_x_preferred":[
        "Krasnaya zvezda"
    ],
    "name:ukr_x_preferred":[
        "\u041a\u0440\u0430\u0441\u043d\u0430\u044f \u0417\u0432\u0435\u0437\u0434\u0430"
    ],
    "name:zho_x_preferred":[
        "\u7ea2\u661f\u62a5"
    ],
    "wof:name":"Krasnaya Zvezda",
    "wof:placetype":"locality"
},
  "geometry": {"coordinates":[32.76981,52.52835],"type":"Point"}
}