{
  "type": "Feature",
  "properties": {
    "gn:admin1_code":"53",
    "gn:asciiname":"Golubinskiy",
    "gn:country_code":"RU",
    "gn:dem":189,
    "gn:feature_class":"P",
    "gn:feature_code":"PPL",
    "gn:name":"Golubinskiy",
    "gn:population":0,
    "gn:timezone":"Asia/Omsk",
    "iso:country":"RU",
    "name:eng_x_preferred":[
        "Golubinskiy"
    ],
    "name:nor_x_preferred":[
        "Golubinskij"
    ],
    "name:rus_x_preferred":[
        "\u0413\u043e\u043b\u0443\u0431\u0438\u043d\u0441\u043a\u0438\u0439"
    ],
    "wof:name":"Golubinskiy",
    "wof:placetype":"locality"
},
  "geometry": {"coordinates":[79.2693,53.70259],"type":"Point"}
}