{
  "type": "Feature",
  "properties": {
    "gn:admin1_code":"90",
    "gn:asciiname":"Zagibovka",
    "gn:country_code":"RU",
    "gn:dem":164,
    "gn:feature_class":"P",
    "gn:feature_code":"PPL",
    "gn:name":"Zagibovka",
    "gn:population":0,
    "gn:timezone":"Asia/Yekaterinburg",
    "iso:country":"RU",
    "name:che_x_preferred":[
        "\u0417\u0430\u0433\u0438\u0431\u043e\u0432\u043a\u0430"
    ],
    "name:rus_x_preferred":[
        "\u0417\u0430\u0433\u0438\u0431\u043e\u0432\u043a\u0430"
    ],
    "wof:name":"Zagibovka",
    "wof:placetype":"locality"
},
  "geometry": {"coordinates":[54.1862,57.3807],"type":"Point"}
}