{
  "type": "Feature",
  "properties": {
    "gn:admin1_code":"53",
    "gn:asciiname":"Novomotkovo",
    "gn:country_code":"RU",
    "gn:dem":133,
    "gn:feature_class":"P",
    "gn:feature_code":"PPL",
    "gn:name":"Novomotkovo",
    "gn:population":0,
    "gn:timezone":"Asia/Novosibirsk",
    "iso:country":"RU",
    "name:eng_x_preferred":[
        "Novomotkovo"
    ],
    "name:nor_x_preferred":[
        "Motkovo"
    ],
    "name:rus_x_preferred":[
        "\u041c\u043e\u0442\u043a\u043e\u0432\u043e"
    ],
    "name:rus_x_variant":[
        "\u041d\u043e\u0432\u043e\u043c\u043e\u0442\u043a\u043e\u0432\u043e"
    ],
    "wof:name":"Novomotkovo",
    "wof:placetype":"locality"
},
  "geometry": {"coordinates":[83.5596,55.1149],"type":"Point"}
}