{
  "type": "Feature",
  "properties": {
    "gn:admin1_code":"17",
    "gn:asciiname":"Mukhakh",
    "gn:country_code":"RU",
    "gn:dem":2258,
    "gn:feature_class":"P",
    "gn:feature_code":"PPL",
    "gn:name":"Mukhakh",
    "gn:population":0,
    "gn:timezone":"Europe/Moscow",
    "iso:country":"RU",
    "name:rus_x_preferred":[
        "\u041c\u0443\u0445\u0430\u0445"
    ],
    "name:und_x_variant":[
        "Mukhukh"
    ],
    "wof:name":"Mukhakh",
    "wof:placetype":"locality"
},
  "geometry": {"coordinates":[46.99153,41.70079000000001],"type":"Point"}
}