{
  "type": "Feature",
  "properties": {
    "gn:admin1_code":"72.0",
    "gn:asciiname":"Belevitino",
    "gn:country_code":"RU",
    "gn:dem":153,
    "gn:feature_class":"P",
    "gn:feature_code":"PPL",
    "gn:name":"Belevitino",
    "gn:population":0,
    "gn:timezone":"Europe/Moscow",
    "iso:country":"RU",
    "name:nor_x_preferred":[
        "Belevitino"
    ],
    "name:rus_x_preferred":[
        "\u0411\u0435\u043b\u0435\u0432\u0438\u0442\u0438\u043d\u043e"
    ],
    "wof:name":"Belevitino",
    "wof:placetype":"locality"
},
  "geometry": {"coordinates":[41.13463,52.58247],"type":"Point"}
}