{
  "type": "Feature",
  "properties": {
    "gn:country":"RU",
    "gn:fcode":"PPL",
    "gn:population":300,
    "iso:country":"RU",
    "name:ceb_x_preferred":[
        "Pervomayka"
    ],
    "name:rus_x_preferred":[
        "\u041f\u0435\u0440\u0432\u043e\u043c\u0430\u0439\u043a\u0430"
    ],
    "name:swe_x_preferred":[
        "Pervomayka"
    ],
    "name:und_x_variant":[
        "Pervomayskiy"
    ],
    "qs:name":"Pervomayka",
    "qs:photos_9r":0,
    "qs:photos_sr":0,
    "qs:pop_sr":"2",
    "wof:name":"Pervomayka",
    "wof:placetype":"locality",
    "wof:population":300
},
  "geometry": {"coordinates":[38.18036,55.5518],"type":"Point"}
}