{
  "type": "Feature",
  "properties": {
    "gn:admin1_code":"69",
    "gn:asciiname":"Plotki",
    "gn:country_code":"RU",
    "gn:dem":231,
    "gn:feature_class":"P",
    "gn:feature_code":"PPL",
    "gn:name":"Plotki",
    "gn:population":0,
    "gn:timezone":"Europe/Moscow",
    "iso:country":"RU",
    "name:rus_x_preferred":[
        "\u041f\u043b\u043e\u0442\u043a\u0438"
    ],
    "name:und_x_variant":[
        "\u041f\u043b\u043e\u0442\u043a\u0438"
    ],
    "wof:name":"Plotki",
    "wof:placetype":"locality"
},
  "geometry": {"coordinates":[32.91694,54.60194],"type":"Point"}
}