{
  "type": "Feature",
  "properties": {
    "gn:admin1_code":"16",
    "gn:asciiname":"Novoye Baygulovo",
    "gn:country_code":"RU",
    "gn:dem":119,
    "gn:feature_class":"P",
    "gn:feature_code":"PPL",
    "gn:name":"Novoye Baygulovo",
    "gn:population":0,
    "gn:timezone":"Europe/Moscow",
    "iso:country":"RU",
    "name:rus_x_preferred":[
        "\u041d\u043e\u0432\u043e\u0435 \u0411\u0430\u0439\u0433\u0443\u043b\u043e\u0432\u043e"
    ],
    "wof:name":"Novoye Baygulovo",
    "wof:placetype":"locality"
},
  "geometry": {"coordinates":[47.97724,55.87837],"type":"Point"}
}