{
  "type": "Feature",
  "properties": {
    "gn:admin1_code":"63",
    "gn:asciiname":"Mysovaya",
    "gn:cc2":"RU",
    "gn:country_code":"RU",
    "gn:dem":15,
    "gn:feature_class":"P",
    "gn:feature_code":"PPL",
    "gn:name":"Mysovaya",
    "gn:population":0,
    "gn:timezone":"Asia/Magadan",
    "iso:country":"RU",
    "name:rus_x_preferred":[
        "\u041c\u044b\u0441\u043e\u0432\u0430\u044f"
    ],
    "name:und_x_variant":[
        "Zimov\u2019ye Mysovaya",
        "Mysovaya",
        "\u041c\u044b\u0441\u043e\u0432\u0430\u044f"
    ],
    "wof:name":"Mysovaya",
    "wof:placetype":"locality"
},
  "geometry": {"coordinates":[156.26667,67.63333],"type":"Point"}
}