{
  "type": "Feature",
  "properties": {
    "gn:admin1_code":"77",
    "gn:asciiname":"Mindyukino",
    "gn:country_code":"RU",
    "gn:dem":186,
    "gn:feature_class":"P",
    "gn:feature_code":"PPL",
    "gn:name":"Mindyukino",
    "gn:population":0,
    "gn:timezone":"Europe/Moscow",
    "iso:country":"RU",
    "name:rus_x_preferred":[
        "\u041c\u0438\u043d\u0434\u044e\u043a\u0438\u043d\u043e"
    ],
    "name:und_x_variant":[
        "\u041c\u0438\u043d\u0434\u044e\u043a\u0438\u043d\u043e"
    ],
    "wof:name":"Mindyukino",
    "wof:placetype":"locality"
},
  "geometry": {"coordinates":[36.7691,58.6544],"type":"Point"}
}