{
  "type": "Feature",
  "properties": {
    "gn:admin1_code":"8",
    "gn:asciiname":"Manyshta",
    "gn:country_code":"RU",
    "gn:dem":254,
    "gn:feature_class":"P",
    "gn:feature_code":"PPL",
    "gn:name":"Manyshta",
    "gn:population":0,
    "gn:timezone":"Asia/Yekaterinburg",
    "iso:country":"RU",
    "name:bak_x_preferred":[
        "\u041c\u0430\u043d\u044b\u0448\u0442\u044b"
    ],
    "name:che_x_preferred":[
        "\u041c\u0430\u043d\u044b\u0448\u0442\u0430"
    ],
    "name:eng_x_preferred":[
        "Manyshta"
    ],
    "name:hye_x_preferred":[
        "\u0544\u0561\u0576\u056b\u0577\u057f\u0561"
    ],
    "name:kat_x_preferred":[
        "\u10db\u10d0\u10dc\u10d8\u10e8\u10e2\u10d0"
    ],
    "name:kaz_x_preferred":[
        "\u041c\u0430\u043d\u044b\u0448\u0442\u0430"
    ],
    "name:kir_x_preferred":[
        "\u041c\u0430\u043d\u044b\u0448\u0442\u0430"
    ],
    "name:nor_x_preferred":[
        "Manysjta"
    ],
    "name:rus_x_preferred":[
        "\u041c\u0430\u043d\u044b\u0448\u0442\u0430"
    ],
    "name:tat_x_preferred":[
        "\u041c\u0430\u043d\u044b\u0448\u0442\u044b"
    ],
    "name:ukr_x_preferred":[
        "\u041c\u0430\u043d\u0438\u0448\u0442\u0430"
    ],
    "name:und_x_variant":[
        "Manyshty",
        "\u041c\u0430\u043d\u044b\u0448\u0442\u0430",
        "Manyshta"
    ],
    "wof:name":"Manyshta",
    "wof:placetype":"locality"
},
  "geometry": {"coordinates":[57.6036,54.2676],"type":"Point"}
}