{
  "type": "Feature",
  "properties": {
    "gn:admin1_code":"75",
    "gn:asciiname":"Ilovka",
    "gn:country_code":"RU",
    "gn:dem":110,
    "gn:feature_class":"P",
    "gn:feature_code":"PPL",
    "gn:name":"Ilovka",
    "gn:population":0,
    "gn:timezone":"Asia/Tomsk",
    "iso:country":"RU",
    "name:eng_x_preferred":[
        "Ilovka"
    ],
    "name:nor_x_preferred":[
        "Ilovka"
    ],
    "name:rus_x_preferred":[
        "\u0418\u043b\u043e\u0432\u043a\u0430"
    ],
    "name:und_x_variant":[
        "\u0418\u043b\u043e\u0432\u043a\u0430",
        "Ilovka"
    ],
    "wof:name":"Ilovka",
    "wof:placetype":"locality"
},
  "geometry": {"coordinates":[86.82465000000001,56.88938],"type":"Point"}
}