{
  "type": "Feature",
  "properties": {
    "gn:admin1_code":"45",
    "gn:asciiname":"Kul'bash",
    "gn:country_code":"RU",
    "gn:dem":177,
    "gn:feature_class":"P",
    "gn:feature_code":"PPL",
    "gn:name":"Kul\u2019bash",
    "gn:population":0,
    "gn:timezone":"Europe/Moscow",
    "iso:country":"RU",
    "name:eng_x_preferred":[
        "Kul'bash"
    ],
    "name:nor_x_preferred":[
        "Kulbasj"
    ],
    "name:rus_x_preferred":[
        "\u041a\u0443\u043b\u044c\u0431\u0430\u0448"
    ],
    "name:und_x_variant":[
        "\u041a\u0443\u043b\u044c\u0431\u0430\u0448",
        "Kul\u2019bash"
    ],
    "wof:name":"Kul'bash",
    "wof:placetype":"locality"
},
  "geometry": {"coordinates":[48.79722,56.28861],"type":"Point"}
}