{
  "type": "Feature",
  "properties": {
    "gn:admin1_code":"41",
    "gn:asciiname":"Platonovskiy",
    "gn:country_code":"RU",
    "gn:dem":209,
    "gn:feature_class":"P",
    "gn:feature_code":"PPL",
    "gn:name":"Platonovskiy",
    "gn:population":0,
    "gn:timezone":"Europe/Moscow",
    "iso:country":"RU",
    "name:rus_x_preferred":[
        "\u041f\u043b\u0430\u0442\u043e\u043d\u043e\u0432\u0441\u043a\u0438\u0439"
    ],
    "wof:name":"Platonovskiy",
    "wof:placetype":"locality"
},
  "geometry": {"coordinates":[35.331,52.3476],"type":"Point"}
}