{
  "type": "Feature",
  "properties": {
    "gn:admin1_code":"31",
    "gn:asciiname":"Mayskiy",
    "gn:country_code":"RU",
    "gn:dem":677,
    "gn:feature_class":"P",
    "gn:feature_code":"PPL",
    "gn:name":"Mayskiy",
    "gn:population":0,
    "gn:timezone":"Asia/Krasnoyarsk",
    "iso:country":"RU",
    "name:eng_x_preferred":[
        "Mayskiy"
    ],
    "name:nor_x_preferred":[
        "Majskij"
    ],
    "name:rus_x_preferred":[
        "\u041c\u0430\u0439\u0441\u043a\u0438\u0439"
    ],
    "wof:name":"Mayskiy",
    "wof:placetype":"locality"
},
  "geometry": {"coordinates":[90.05417,53.58111],"type":"Point"}
}