{
  "type": "Feature",
  "properties": {
    "gn:admin1_code":"91",
    "gn:asciiname":"Staraya Kuzurba",
    "gn:country_code":"RU",
    "gn:dem":382,
    "gn:feature_class":"P",
    "gn:feature_code":"PPL",
    "gn:name":"Staraya Kuzurba",
    "gn:population":0,
    "gn:timezone":"Asia/Krasnoyarsk",
    "iso:country":"RU",
    "name:eng_x_preferred":[
        "Staraya Kuzurba"
    ],
    "name:nor_x_preferred":[
        "Staraja Kuzurba"
    ],
    "name:rus_x_preferred":[
        "\u0421\u0442\u0430\u0440\u0430\u044f \u041a\u0443\u0437\u0443\u0440\u0431\u0430"
    ],
    "name:und_x_variant":[
        "Kuzurba",
        "Staraya Kuzurba"
    ],
    "wof:name":"Staraya Kuzurba",
    "wof:placetype":"locality"
},
  "geometry": {"coordinates":[90.35611,55.21861],"type":"Point"}
}