{
  "type": "Feature",
  "properties": {
    "gn:admin1_code":"21.0",
    "gn:asciiname":"Lamna",
    "gn:country_code":"RU",
    "gn:dem":104,
    "gn:feature_class":"P",
    "gn:feature_code":"PPL",
    "gn:name":"Lamna",
    "gn:population":0,
    "gn:timezone":"Europe/Moscow",
    "iso:country":"RU",
    "name:ara_x_preferred":[
        "\u0644\u064a\u0627\u0621"
    ],
    "name:azb_x_preferred":[
        "\u0644\u0627\u0645\u0646\u0627"
    ],
    "name:ceb_x_preferred":[
        "Lamna"
    ],
    "name:deu_x_preferred":[
        "Heringshaie"
    ],
    "name:fas_x_preferred":[
        "\u0644\u0627\u0645\u0646\u0627"
    ],
    "name:fra_x_preferred":[
        "Lamna"
    ],
    "name:glg_x_preferred":[
        "Lamna"
    ],
    "name:heb_x_preferred":[
        "\u05dc\u05de\u05e0\u05d4"
    ],
    "name:hun_x_preferred":[
        "Lamna"
    ],
    "name:ita_x_preferred":[
        "Lamna"
    ],
    "name:kaz_x_preferred":[
        "\u0421\u043a\u0443\u043c\u0431\u0440\u0438\u044f \u0430\u043a\u0443\u043b\u0430\u0441\u044b"
    ],
    "name:kor_x_preferred":[
        "\uc545\uc0c1\uc5b4\uc18d"
    ],
    "name:lav_x_preferred":[
        "Si\u013c\u0137u haizivis"
    ],
    "name:nld_x_preferred":[
        "Lamna"
    ],
    "name:nor_x_preferred":[
        "Lamna"
    ],
    "name:pol_x_preferred":[
        "Lamna"
    ],
    "name:rus_x_preferred":[
        "\u041b\u0430\u043c\u043d\u0430"
    ],
    "name:rus_x_variant":[
        "\u0421\u0435\u043b\u044c\u0434\u0435\u0432\u044b\u0435 \u0430\u043a\u0443\u043b\u044b"
    ],
    "name:spa_x_preferred":[
        "Lamna"
    ],
    "name:swe_x_preferred":[
        "Lamna"
    ],
    "name:ukr_x_preferred":[
        "\u041e\u0441\u0435\u043b\u0435\u0434\u0446\u0435\u0432\u0430 \u0430\u043a\u0443\u043b\u0430"
    ],
    "name:war_x_preferred":[
        "Lamna"
    ],
    "name:zho_x_preferred":[
        "\u9f20\u9ca8\u5c5e"
    ],
    "wof:name":"Lamna",
    "wof:placetype":"locality"
},
  "geometry": {"coordinates":[42.00971,56.64717],"type":"Point"}
}