{
  "type": "Feature",
  "properties": {
    "gn:admin1_code":"21.0",
    "gn:asciiname":"Lamna",
    "gn:country_code":"RU",
    "gn:dem":104,
    "gn:feature_class":"P",
    "gn:feature_code":"PPL",
    "gn:name":"Lamna",
    "gn:population":0,
    "gn:timezone":"Europe/Moscow",
    "iso:country":"RU",
    "name:nor_x_preferred":[
        "Lamna"
    ],
    "name:rus_x_preferred":[
        "\u041b\u0430\u043c\u043d\u0430"
    ],
    "wof:name":"Lamna",
    "wof:placetype":"locality"
},
  "geometry": {"coordinates":[42.00971,56.64717],"type":"Point"}
}