{
  "type": "Feature",
  "properties": {
    "gn:admin1_code":"69",
    "gn:asciiname":"Proverzhenka",
    "gn:country_code":"RU",
    "gn:dem":188,
    "gn:feature_class":"P",
    "gn:feature_code":"PPL",
    "gn:name":"Proverzhenka",
    "gn:population":0,
    "gn:timezone":"Europe/Moscow",
    "iso:country":"RU",
    "name:rus_x_preferred":[
        "\u041f\u0440\u043e\u0432\u0435\u0440\u0436\u0435\u043d\u043a\u0430"
    ],
    "wof:name":"Proverzhenka",
    "wof:placetype":"locality"
},
  "geometry": {"coordinates":[32.42208,54.39501],"type":"Point"}
}