{
  "type": "Feature",
  "properties": {
    "gn:admin1_code":"85",
    "gn:asciiname":"Komonevskiy Pogost",
    "gn:cc2":"RU",
    "gn:country_code":"RU",
    "gn:dem":158,
    "gn:feature_class":"P",
    "gn:feature_code":"PPL",
    "gn:name":"Komonevskiy Pogost",
    "gn:population":0,
    "gn:timezone":"Europe/Moscow",
    "iso:country":"RU",
    "name:rus_x_preferred":[
        "\u041a\u043e\u043c\u043e\u043d\u0435\u0432\u0441\u043a\u0438\u0439 \u041f\u043e\u0433\u043e\u0441\u0442"
    ],
    "name:und_x_variant":[
        "Komonevskiy",
        "Komonevskoye",
        "Komonevskiy Pogost"
    ],
    "wof:name":"Komonevskiy Pogost",
    "wof:placetype":"locality"
},
  "geometry": {"coordinates":[36.36667,60.08333],"type":"Point"}
}