{
  "type": "Feature",
  "properties": {
    "gn:admin1_code":"23",
    "gn:asciiname":"Partizanskoye",
    "gn:country_code":"RU",
    "gn:dem":23,
    "gn:feature_class":"P",
    "gn:feature_code":"PPL",
    "gn:name":"Partizanskoye",
    "gn:population":0,
    "gn:timezone":"Europe/Kaliningrad",
    "iso:country":"RU",
    "name:rus_x_preferred":[
        "\u041f\u0430\u0440\u0442\u0438\u0437\u0430\u043d\u0441\u043a\u043e\u0435"
    ],
    "name:und_x_variant":[
        "\u041f\u0430\u0440\u0442\u0438\u0437\u0430\u043d\u0441\u043a\u043e\u0435"
    ],
    "wof:name":"Partizanskoye",
    "wof:placetype":"locality"
},
  "geometry": {"coordinates":[21.5226,54.71016],"type":"Point"}
}