{
  "type": "Feature",
  "properties": {
    "gn:admin1_code":"60",
    "gn:asciiname":"Shcherbovo",
    "gn:country_code":"RU",
    "gn:dem":121,
    "gn:feature_class":"P",
    "gn:feature_code":"PPL",
    "gn:name":"Shcherbovo",
    "gn:population":0,
    "gn:timezone":"Europe/Moscow",
    "iso:country":"RU",
    "name:rus_x_preferred":[
        "\u0429\u0435\u0440\u0431\u043e\u0432\u043e"
    ],
    "name:und_x_variant":[
        "\u0429\u0435\u0440\u0431\u043e\u0432\u043e"
    ],
    "wof:name":"Shcherbovo",
    "wof:placetype":"locality"
},
  "geometry": {"coordinates":[29.1849,56.9534],"type":"Point"}
}