{
  "type": "Feature",
  "properties": {
    "gn:admin1_code":"4.0",
    "gn:asciiname":"Kasmalinka",
    "gn:country_code":"RU",
    "gn:dem":203,
    "gn:feature_class":"P",
    "gn:feature_code":"PPL",
    "gn:name":"Kasmalinka",
    "gn:population":0,
    "gn:timezone":"Asia/Barnaul",
    "iso:country":"RU",
    "name:eng_x_preferred":[
        "Kasmalinka"
    ],
    "name:nor_x_preferred":[
        "Kasmalinka"
    ],
    "name:rus_x_preferred":[
        "\u041a\u0430\u0441\u043c\u0430\u043b\u0438\u043d\u043a\u0430"
    ],
    "name:und_x_variant":[
        "\u041a\u0430\u0441\u043c\u0430\u043b\u0438\u043d\u043a\u0430",
        "Kasmalinka"
    ],
    "wof:name":"Kasmalinka",
    "wof:placetype":"locality"
},
  "geometry": {"coordinates":[82.47,53.12167],"type":"Point"}
}