{
  "type": "Feature",
  "properties": {
    "gn:admin1_code":"75",
    "gn:asciiname":"Zhurilovskiy",
    "gn:cc2":"RU",
    "gn:country_code":"RU",
    "gn:dem":104,
    "gn:feature_class":"P",
    "gn:feature_code":"PPL",
    "gn:name":"Zhurilovskiy",
    "gn:population":0,
    "gn:timezone":"Asia/Tomsk",
    "iso:country":"RU",
    "name:und_x_variant":[
        "Zhurilevskiy",
        "Zhurilovskiy"
    ],
    "wof:name":"Zhurilovskiy",
    "wof:placetype":"locality"
},
  "geometry": {"coordinates":[83.80167,56.09806],"type":"Point"}
}