{
  "type": "Feature",
  "properties": {
    "gn:admin1_code":"42",
    "gn:admin2_code":"575409",
    "gn:asciiname":"Prokushevo",
    "gn:country_code":"RU",
    "gn:dem":218,
    "gn:feature_class":"P",
    "gn:feature_code":"PPL",
    "gn:name":"Prokushevo",
    "gn:population":0,
    "gn:timezone":"Europe/Moscow",
    "iso:country":"RU",
    "name:eng_x_preferred":[
        "Prokushevo"
    ],
    "name:fin_x_preferred":[
        "\u0160idj\u00e4rvi"
    ],
    "name:nor_x_preferred":[
        "Prokusjevo"
    ],
    "name:rus_x_preferred":[
        "\u041f\u0440\u043e\u043a\u0443\u0448\u0435\u0432\u043e"
    ],
    "name:und_x_variant":[
        "\u041f\u0440\u043e\u043a\u0443\u0448\u0435\u0432\u043e",
        "Prokushevo"
    ],
    "name:vep_x_preferred":[
        "\u0160id\u00e4rv"
    ],
    "wof:name":"Prokushevo",
    "wof:placetype":"locality"
},
  "geometry": {"coordinates":[34.92583,59.91556],"type":"Point"}
}