{
  "type": "Feature",
  "properties": {
    "gn:admin1_code":"91",
    "gn:asciiname":"Miroslavka",
    "gn:country_code":"RU",
    "gn:dem":211,
    "gn:feature_class":"P",
    "gn:feature_code":"PPL",
    "gn:name":"Miroslavka",
    "gn:population":0,
    "gn:timezone":"Asia/Krasnoyarsk",
    "iso:country":"RU",
    "name:rus_x_preferred":[
        "\u041c\u0438\u0440\u043e\u0441\u043b\u0430\u0432\u043a\u0430"
    ],
    "wof:name":"Miroslavka",
    "wof:placetype":"locality"
},
  "geometry": {"coordinates":[89.51833000000001,56.58167],"type":"Point"}
}