{
  "type": "Feature",
  "properties": {
    "gn:admin1_code":"42",
    "gn:asciiname":"Traktornoye",
    "gn:country_code":"RU",
    "gn:dem":22,
    "gn:feature_class":"P",
    "gn:feature_code":"PPL",
    "gn:name":"Traktornoye",
    "gn:population":0,
    "gn:timezone":"Europe/Moscow",
    "iso:country":"RU",
    "name:fin_x_preferred":[
        "Valkeam\u00e4ki"
    ],
    "wof:name":"Traktornoye",
    "wof:placetype":"locality"
},
  "geometry": {"coordinates":[30.13691,60.85586],"type":"Point"}
}