{
  "type": "Feature",
  "properties": {
    "gn:admin1_code":"47",
    "gn:asciiname":"Shelogurovo",
    "gn:country_code":"RU",
    "gn:dem":128,
    "gn:feature_class":"P",
    "gn:feature_code":"PPL",
    "gn:name":"Shelogurovo",
    "gn:population":0,
    "gn:timezone":"Europe/Moscow",
    "iso:country":"RU",
    "name:rus_x_preferred":[
        "\u0428\u0435\u043b\u043e\u0433\u0443\u0440\u043e\u0432\u043e"
    ],
    "name:und_x_variant":[
        "\u0428\u0435\u043b\u043e\u0433\u0443\u0440\u043e\u0432\u043e"
    ],
    "wof:name":"Shelogurovo",
    "wof:placetype":"locality"
},
  "geometry": {"coordinates":[39.81176,55.22051],"type":"Point"}
}