{
  "type": "Feature",
  "properties": {
    "gn:admin1_code":"41",
    "gn:asciiname":"Tolstyy Lug",
    "gn:country_code":"RU",
    "gn:dem":148,
    "gn:feature_class":"P",
    "gn:feature_code":"PPL",
    "gn:name":"Tolstyy Lug",
    "gn:population":0,
    "gn:timezone":"Europe/Moscow",
    "iso:country":"RU",
    "name:rus_x_preferred":[
        "\u0422\u043e\u043b\u0441\u0442\u044b\u0439 \u041b\u0443\u0433"
    ],
    "name:und_x_variant":[
        "Tolsty Lug",
        "Toletyylug",
        "Tolstyy Lug"
    ],
    "wof:name":"Tolstyy Lug",
    "wof:placetype":"locality"
},
  "geometry": {"coordinates":[35.0773,51.2974],"type":"Point"}
}