{
  "type": "Feature",
  "properties": {
    "gn:admin1_code":"21.0",
    "gn:asciiname":"Falyushino",
    "gn:country_code":"RU",
    "gn:dem":86,
    "gn:feature_class":"P",
    "gn:feature_code":"PPL",
    "gn:name":"Falyushino",
    "gn:population":0,
    "gn:timezone":"Europe/Moscow",
    "iso:country":"RU",
    "name:rus_x_preferred":[
        "\u0424\u0430\u043b\u044e\u0448\u0438\u043d\u043e"
    ],
    "wof:name":"Falyushino",
    "wof:placetype":"locality"
},
  "geometry": {"coordinates":[41.5915,56.64883],"type":"Point"}
}