{
  "type": "Feature",
  "properties": {
    "gn:admin1_code":"60",
    "gn:asciiname":"Tupy",
    "gn:country_code":"RU",
    "gn:dem":52,
    "gn:feature_class":"P",
    "gn:feature_code":"PPL",
    "gn:name":"Tupy",
    "gn:population":0,
    "gn:timezone":"Europe/Moscow",
    "iso:country":"RU",
    "name:deu_x_preferred":[
        "Tupy"
    ],
    "name:rus_x_preferred":[
        "\u0422\u0443\u043f\u044b"
    ],
    "name:slk_x_preferred":[
        "Tupy"
    ],
    "wof:name":"Tupy",
    "wof:placetype":"locality"
},
  "geometry": {"coordinates":[28.0824,57.8142],"type":"Point"}
}