{
  "type": "Feature",
  "properties": {
    "gn:country":"RU",
    "gn:fcode":"PPL",
    "gn:pop":7845,
    "iso:country":"RU",
    "name:eng_x_preferred":[
        "Suponevo"
    ],
    "name:nor_x_preferred":[
        "Suponevo"
    ],
    "name:rus_x_preferred":[
        "\u0421\u0443\u043f\u043e\u043d\u0435\u0432\u043e"
    ],
    "name:unk_x_variant":[
        "\u0421\u0443\u043f\u043e\u043d\u0435\u0432\u043e"
    ],
    "qs:name":"Suponevo",
    "qs:name_adm0":"Russia",
    "qs:name_adm1":"Bryansk Oblast",
    "qs:photos_9r":0,
    "qs:photos_sr":0,
    "qs:placetype":"Town",
    "qs:pop_sr":"5",
    "wof:name":"Suponevo",
    "wof:placetype":"locality",
    "wof:population":7845
},
  "geometry": {"coordinates":[34.29597,53.20492],"type":"Point"}
}