{
  "type": "Feature",
  "properties": {
    "gn:admin1_code":"90",
    "gn:asciiname":"Krivtsy",
    "gn:country_code":"RU",
    "gn:dem":146,
    "gn:feature_class":"P",
    "gn:feature_code":"PPL",
    "gn:name":"Krivtsy",
    "gn:population":0,
    "gn:timezone":"Asia/Yekaterinburg",
    "iso:country":"RU",
    "name:che_x_preferred":[
        "\u041a\u0440\u0438\u0432\u0446\u044b"
    ],
    "name:eng_x_preferred":[
        "Krivtsy"
    ],
    "name:nor_x_preferred":[
        "Krivtsy"
    ],
    "name:rus_x_preferred":[
        "\u041a\u0440\u0438\u0432\u0446\u044b"
    ],
    "wof:name":"Krivtsy",
    "wof:placetype":"locality"
},
  "geometry": {"coordinates":[55.0375,60.21261],"type":"Point"}
}