{
  "type": "Feature",
  "properties": {
    "gn:admin1_code":"90",
    "gn:asciiname":"Ust'-Nytva",
    "gn:country_code":"RU",
    "gn:dem":91,
    "gn:feature_class":"P",
    "gn:feature_code":"PPL",
    "gn:name":"Ust\u2019-Nytva",
    "gn:population":0,
    "gn:timezone":"Asia/Yekaterinburg",
    "iso:country":"RU",
    "name:rus_x_preferred":[
        "\u0423\u0441\u0442\u044c-\u041d\u044b\u0442\u0432\u0430"
    ],
    "name:und_x_variant":[
        "Ust\u2019-Nytva"
    ],
    "wof:name":"Ust'-Nytva",
    "wof:placetype":"locality"
},
  "geometry": {"coordinates":[55.3551,57.8762],"type":"Point"}
}