{
  "type": "Feature",
  "properties": {
    "gn:admin1_code":"90",
    "gn:asciiname":"Poroshevo",
    "gn:country_code":"RU",
    "gn:dem":175,
    "gn:feature_class":"P",
    "gn:feature_code":"PPL",
    "gn:name":"Poroshevo",
    "gn:population":0,
    "gn:timezone":"Asia/Yekaterinburg",
    "iso:country":"RU",
    "name:che_x_preferred":[
        "\u041f\u043e\u0440\u043e\u0448\u0435\u0432\u043e"
    ],
    "name:eng_x_preferred":[
        "Poroshevo"
    ],
    "name:koi_x_preferred":[
        "\u041f\u043e\u0440\u043e\u0448\u0432\u043e\u043b\u044c"
    ],
    "name:nor_x_preferred":[
        "Porosjevo"
    ],
    "name:rus_x_preferred":[
        "\u041f\u043e\u0440\u043e\u0448\u0435\u0432\u043e"
    ],
    "name:und_x_variant":[
        "Porshevo",
        "Poroshevo",
        "\u041f\u043e\u0440\u043e\u0448\u0435\u0432\u043e"
    ],
    "wof:name":"Poroshevo",
    "wof:placetype":"locality"
},
  "geometry": {"coordinates":[54.88649,60.11971],"type":"Point"}
}