{
  "type": "Feature",
  "properties": {
    "gn:admin1_code":"24",
    "gn:asciiname":"Shin Mer",
    "gn:country_code":"RU",
    "gn:dem":50,
    "gn:feature_class":"P",
    "gn:feature_code":"PPL",
    "gn:name":"Shin Mer",
    "gn:population":0,
    "gn:timezone":"Europe/Moscow",
    "iso:country":"RU",
    "name:rus_x_preferred":[
        "\u0428\u0438\u043d \u041c\u0435\u0440"
    ],
    "wof:name":"Shin Mer",
    "wof:placetype":"locality"
},
  "geometry": {"coordinates":[44.5183,47.3962],"type":"Point"}
}