{
  "type": "Feature",
  "properties": {
    "gn:admin1_code":"69.0",
    "gn:asciiname":"Besedka",
    "gn:country_code":"RU",
    "gn:dem":180,
    "gn:feature_class":"P",
    "gn:feature_code":"PPL",
    "gn:name":"Besedka",
    "gn:population":0,
    "gn:timezone":"Europe/Moscow",
    "iso:country":"RU",
    "name:nor_x_preferred":[
        "Besedka"
    ],
    "name:rus_x_preferred":[
        "\u0411\u0435\u0441\u0435\u0434\u043a\u0430"
    ],
    "wof:name":"Besedka",
    "wof:placetype":"locality"
},
  "geometry": {"coordinates":[32.62556,53.64389],"type":"Point"}
}