{
  "type": "Feature",
  "properties": {
    "gn:admin1_code":"69.0",
    "gn:asciiname":"Buravlevo",
    "gn:country_code":"RU",
    "gn:dem":193,
    "gn:feature_class":"P",
    "gn:feature_code":"PPL",
    "gn:name":"Buravlevo",
    "gn:population":0,
    "gn:timezone":"Europe/Moscow",
    "iso:country":"RU",
    "name:rus_x_preferred":[
        "\u0411y\u0440a\u0432\u043b\u0435\u0432\u043e"
    ],
    "name:und_x_variant":[
        "Borovlevo",
        "Buravlevo"
    ],
    "wof:name":"Buravlevo",
    "wof:placetype":"locality"
},
  "geometry": {"coordinates":[32.85609,55.04644],"type":"Point"}
}