{
  "type": "Feature",
  "properties": {
    "gn:country":"RU",
    "gn:fcode":"PPL",
    "gn:pop":1971,
    "iso:country":"RU",
    "name:nor_x_preferred":[
        "Volotsjajevka-Vtoraja"
    ],
    "name:rus_x_preferred":[
        "\u0412\u043e\u043b\u043e\u0447\u0430\u0435\u0432\u043a\u0430-\u0412\u0442\u043e\u0440\u0430\u044f"
    ],
    "name:rus_x_variant":[
        "\u0412\u043e\u043b\u043e\u0447\u0430\u0435\u0432\u043a\u0430 \u0412\u0442\u043e\u0440\u0430\u044f"
    ],
    "name:unk_x_variant":[
        "Vtoraya Volochayevka"
    ],
    "qs:name":"Volochayevka Vtoraya",
    "qs:name_adm0":"Russia",
    "qs:name_adm1":"Jewish Autonomous Oblast",
    "qs:photos_9k":1,
    "qs:photos_9r":1,
    "qs:photos_all":5,
    "qs:photos_sr":0,
    "qs:placetype":"Town",
    "qs:pop_sr":"3",
    "wof:name":"Volochayevka Vtoraya",
    "wof:placetype":"locality",
    "wof:population":1971
},
  "geometry": {"coordinates":[134.58232000000001,48.56695],"type":"Point"}
}