{
  "type": "Feature",
  "properties": {
    "gn:admin1_code":"21",
    "gn:asciiname":"Shushkovo",
    "gn:country_code":"RU",
    "gn:dem":145,
    "gn:feature_class":"P",
    "gn:feature_code":"PPL",
    "gn:name":"Shushkovo",
    "gn:population":0,
    "gn:timezone":"Europe/Moscow",
    "iso:country":"RU",
    "name:rus_x_preferred":[
        "\u0428\u0443\u0448\u043a\u043e\u0432\u043e"
    ],
    "wof:name":"Shushkovo",
    "wof:placetype":"locality"
},
  "geometry": {"coordinates":[41.72951,57.54715],"type":"Point"}
}