{
  "type": "Feature",
  "properties": {
    "gn:admin1_code":"56",
    "gn:asciiname":"Retyazhi",
    "gn:country_code":"RU",
    "gn:dem":170,
    "gn:feature_class":"P",
    "gn:feature_code":"PPL",
    "gn:name":"Retyazhi",
    "gn:population":0,
    "gn:timezone":"Europe/Moscow",
    "iso:country":"RU",
    "name:eng_x_preferred":[
        "Retyazhi"
    ],
    "name:nor_x_preferred":[
        "Retjazji"
    ],
    "name:rus_x_preferred":[
        "\u0420\u0435\u0442\u044f\u0436\u0438"
    ],
    "wof:name":"Retyazhi",
    "wof:placetype":"locality"
},
  "geometry": {"coordinates":[35.93417,52.59861],"type":"Point"}
}