{
  "type": "Feature",
  "properties": {
    "gn:admin1_code":"46",
    "gn:asciiname":"At'minskiy",
    "gn:country_code":"RU",
    "gn:dem":106,
    "gn:feature_class":"P",
    "gn:feature_code":"PPL",
    "gn:name":"At\u2019minskiy",
    "gn:population":0,
    "gn:timezone":"Europe/Moscow",
    "iso:country":"RU",
    "name:rus_x_preferred":[
        "\u0410\u0442\u044c\u043c\u0438\u043d\u0441\u043a\u0438\u0439"
    ],
    "name:und_x_variant":[
        "At\u2019minskiy"
    ],
    "wof:name":"At'minskiy",
    "wof:placetype":"locality"
},
  "geometry": {"coordinates":[45.3799,54.5507],"type":"Point"}
}