{
  "type": "Feature",
  "properties": {
    "gn:admin1_code":"77",
    "gn:asciiname":"Zelenaya",
    "gn:country_code":"RU",
    "gn:dem":245,
    "gn:feature_class":"P",
    "gn:feature_code":"PPL",
    "gn:name":"Zel\u00ebnaya",
    "gn:population":0,
    "gn:timezone":"Europe/Moscow",
    "iso:country":"RU",
    "wof:name":"Zelenaya",
    "wof:placetype":"locality"
},
  "geometry": {"coordinates":[33.48387,56.5028],"type":"Point"}
}