{
  "type": "Feature",
  "properties": {
    "gn:admin1_code":"83",
    "gn:asciiname":"Grigorevo",
    "gn:country_code":"RU",
    "gn:dem":133,
    "gn:feature_class":"P",
    "gn:feature_code":"PPL",
    "gn:name":"Grigorevo",
    "gn:population":0,
    "gn:timezone":"Europe/Moscow",
    "iso:country":"RU",
    "name:rus_x_preferred":[
        "\u0413\u0440\u0438\u0433\u043e\u0440\u0435\u0432\u043e"
    ],
    "name:und_x_variant":[
        "Grigorovo",
        "Grigorevo"
    ],
    "wof:name":"Grigorevo",
    "wof:placetype":"locality"
},
  "geometry": {"coordinates":[40.25545,56.42919000000001],"type":"Point"}
}