{
  "type": "Feature",
  "properties": {
    "gn:admin1_code":"57",
    "gn:asciiname":"Koldais",
    "gn:country_code":"RU",
    "gn:dem":163,
    "gn:feature_class":"P",
    "gn:feature_code":"PPL",
    "gn:name":"Koldais",
    "gn:population":0,
    "gn:timezone":"Europe/Moscow",
    "iso:country":"RU",
    "name:eng_x_preferred":[
        "Koldais"
    ],
    "name:nor_x_preferred":[
        "Koldais"
    ],
    "name:rus_x_preferred":[
        "\u041a\u043e\u043b\u0434\u0430\u0438\u0441"
    ],
    "name:und_x_variant":[
        "Suchkino"
    ],
    "wof:name":"Koldais",
    "wof:placetype":"locality"
},
  "geometry": {"coordinates":[45.5429,53.0791],"type":"Point"}
}