{
  "type": "Feature",
  "properties": {
    "gn:admin1_code":"51.0",
    "gn:asciiname":"Lytkino",
    "gn:country_code":"RU",
    "gn:dem":110,
    "gn:feature_class":"P",
    "gn:feature_code":"PPL",
    "gn:name":"Lytkino",
    "gn:population":0,
    "gn:timezone":"Europe/Moscow",
    "iso:country":"RU",
    "name:rus_x_preferred":[
        "\u041b\u044b\u0442\u043a\u0438\u043d\u043e"
    ],
    "name:und_x_variant":[
        "\u041b\u044b\u0442\u043a\u0438\u043d\u043e"
    ],
    "wof:name":"Lytkino",
    "wof:placetype":"locality"
},
  "geometry": {"coordinates":[44.76253,56.00792],"type":"Point"}
}