{
  "type": "Feature",
  "properties": {
    "gn:admin1_code":"83.0",
    "gn:asciiname":"Nevezhino",
    "gn:country_code":"RU",
    "gn:dem":117,
    "gn:feature_class":"P",
    "gn:feature_code":"PPL",
    "gn:name":"Nevezhino",
    "gn:population":0,
    "gn:timezone":"Europe/Moscow",
    "iso:country":"RU",
    "name:rus_x_preferred":[
        "\u041d\u0435\u0432\u0435\u0436\u0438\u043d\u043e"
    ],
    "wof:name":"Nevezhino",
    "wof:placetype":"locality"
},
  "geometry": {"coordinates":[41.71676,56.10903],"type":"Point"}
}