{
  "type": "Feature",
  "properties": {
    "gn:admin1_code":"69",
    "gn:asciiname":"Khomino",
    "gn:country_code":"RU",
    "gn:dem":194,
    "gn:feature_class":"P",
    "gn:feature_code":"PPL",
    "gn:name":"Khomino",
    "gn:population":0,
    "gn:timezone":"Europe/Moscow",
    "iso:country":"RU",
    "name:rus_x_preferred":[
        "\u0425\u043e\u043c\u0438\u043d\u043e"
    ],
    "name:und_x_variant":[
        "\u0425\u043e\u043c\u0438\u043d\u043e"
    ],
    "wof:name":"Khomino",
    "wof:placetype":"locality"
},
  "geometry": {"coordinates":[31.01486,54.84458000000001],"type":"Point"}
}