{
  "type": "Feature",
  "properties": {
    "gn:admin1_code":"75",
    "gn:asciiname":"Starokuskovo",
    "gn:country_code":"RU",
    "gn:dem":101,
    "gn:feature_class":"P",
    "gn:feature_code":"PPL",
    "gn:name":"Starokuskovo",
    "gn:population":0,
    "gn:timezone":"Asia/Tomsk",
    "iso:country":"RU",
    "name:eng_x_preferred":[
        "Starokuskovo"
    ],
    "name:nor_x_preferred":[
        "Novokuskovo"
    ],
    "name:rus_x_preferred":[
        "\u041d\u043e\u0432\u043e\u043a\u0443\u0441\u043a\u043e\u0432\u043e"
    ],
    "name:rus_x_variant":[
        "\u0421\u0442\u0430\u0440\u043e\u043a\u0443\u0441\u043a\u043e\u0432\u043e"
    ],
    "name:und_x_variant":[
        "\u0421\u0442\u0430\u0440\u043e\u043a\u0443\u0441\u043a\u043e\u0432\u043e"
    ],
    "wof:name":"Starokuskovo",
    "wof:placetype":"locality"
},
  "geometry": {"coordinates":[86.0386,57.0684],"type":"Point"}
}