{
  "type": "Feature",
  "properties": {
    "gn:admin1_code":"60",
    "gn:asciiname":"Zhdani",
    "gn:country_code":"RU",
    "gn:dem":119,
    "gn:feature_class":"P",
    "gn:feature_code":"PPL",
    "gn:name":"Zhdani",
    "gn:population":0,
    "gn:timezone":"Europe/Moscow",
    "iso:country":"RU",
    "name:rus_x_preferred":[
        "\u0416\u0434\u0430\u043d\u0438"
    ],
    "name:und_x_variant":[
        "\u0416\u0434\u0430\u043d\u0438"
    ],
    "wof:name":"Zhdani",
    "wof:placetype":"locality"
},
  "geometry": {"coordinates":[28.9546,58.4013],"type":"Point"}
}