{
  "type": "Feature",
  "properties": {
    "gn:admin1_code":"77",
    "gn:asciiname":"Rakovo",
    "gn:country_code":"RU",
    "gn:dem":212,
    "gn:feature_class":"P",
    "gn:feature_code":"PPL",
    "gn:name":"Rakovo",
    "gn:population":0,
    "gn:timezone":"Europe/Moscow",
    "iso:country":"RU",
    "name:bul_x_preferred":[
        "\u0420\u0430\u043a\u043e\u0432\u043e"
    ],
    "name:ceb_x_preferred":[
        "Rakovo"
    ],
    "name:deu_x_preferred":[
        "Rakowe"
    ],
    "name:eng_x_preferred":[
        "Rakovo"
    ],
    "name:epo_x_preferred":[
        "Rakovo"
    ],
    "name:fra_x_preferred":[
        "Rakovo"
    ],
    "name:nor_x_preferred":[
        "Praslovo"
    ],
    "name:ron_x_preferred":[
        "Rakovo"
    ],
    "name:rus_x_preferred":[
        "\u041f\u0440\u0430\u0441\u043b\u043e\u0432\u043e"
    ],
    "name:rus_x_variant":[
        "\u0420\u0430\u043a\u043e\u0432\u043e"
    ],
    "name:srp_x_preferred":[
        "\u0420\u0430\u043a\u043e\u0432\u043e"
    ],
    "name:swe_x_preferred":[
        "Rakovo"
    ],
    "name:ukr_x_preferred":[
        "\u0420\u0430\u043a\u043e\u0432\u0435"
    ],
    "wof:name":"Rakovo",
    "wof:placetype":"locality"
},
  "geometry": {"coordinates":[34.8646,56.07731999999999],"type":"Point"}
}