{
  "type": "Feature",
  "properties": {
    "gn:admin1_code":"33",
    "gn:asciiname":"Prokop'ye",
    "gn:country_code":"RU",
    "gn:dem":178,
    "gn:feature_class":"P",
    "gn:feature_code":"PPL",
    "gn:name":"Prokop\u2019ye",
    "gn:population":0,
    "gn:timezone":"Europe/Kirov",
    "iso:country":"RU",
    "name:eng_x_preferred":[
        "Prokop'ye"
    ],
    "name:nor_x_preferred":[
        "Prokopje"
    ],
    "name:rus_x_preferred":[
        "\u041f\u0440\u043e\u043a\u043e\u043f\u044c\u0435"
    ],
    "name:und_x_variant":[
        "Prokop\u2019ye"
    ],
    "wof:name":"Prokop'ye",
    "wof:placetype":"locality"
},
  "geometry": {"coordinates":[50.59722,58.90944],"type":"Point"}
}