{
  "type": "Feature",
  "properties": {
    "gn:admin1_code":"9",
    "gn:asciiname":"Arinkin",
    "gn:country_code":"RU",
    "gn:dem":208,
    "gn:feature_class":"P",
    "gn:feature_code":"PPL",
    "gn:name":"Arinkin",
    "gn:population":0,
    "gn:timezone":"Europe/Moscow",
    "iso:country":"RU",
    "name:rus_x_preferred":[
        "\u0410\u0440\u0438\u043d\u043a\u0438\u043d"
    ],
    "wof:name":"Arinkin",
    "wof:placetype":"locality"
},
  "geometry": {"coordinates":[37.94266,50.84813],"type":"Point"}
}