{
  "type": "Feature",
  "properties": {
    "gn:admin1_code":"7",
    "gn:asciiname":"Zaykovka",
    "gn:country_code":"RU",
    "gn:dem":-23,
    "gn:feature_class":"P",
    "gn:feature_code":"PPL",
    "gn:name":"Zaykovka",
    "gn:population":0,
    "gn:timezone":"Europe/Astrakhan",
    "iso:country":"RU",
    "name:che_x_preferred":[
        "\u0417\u0430\u0439\u043a\u043e\u0432\u043a\u0430"
    ],
    "name:eng_x_preferred":[
        "Zaykovka"
    ],
    "name:nor_x_preferred":[
        "Zajkovka"
    ],
    "name:rus_x_preferred":[
        "\u0417\u0430\u0439\u043a\u043e\u0432\u043a\u0430"
    ],
    "name:tgk_x_preferred":[
        "\u0417\u0430\u0439\u043a\u043e\u0432\u043a\u0430"
    ],
    "name:und_x_variant":[
        "Zaykovskiy"
    ],
    "wof:name":"Zaykovka",
    "wof:placetype":"locality"
},
  "geometry": {"coordinates":[48.29654,46.58983],"type":"Point"}
}