{
  "type": "Feature",
  "properties": {
    "gn:admin1_code":"56",
    "gn:asciiname":"Krutaya Gora",
    "gn:country_code":"RU",
    "gn:dem":226,
    "gn:feature_class":"P",
    "gn:feature_code":"PPL",
    "gn:name":"Krutaya Gora",
    "gn:population":0,
    "gn:timezone":"Europe/Moscow",
    "iso:country":"RU",
    "name:rus_x_preferred":[
        "\u041a\u0440\u0443\u0442\u0430\u044f \u0413\u043e\u0440\u0430"
    ],
    "wof:name":"Krutaya Gora",
    "wof:placetype":"locality"
},
  "geometry": {"coordinates":[36.22892,52.94976],"type":"Point"}
}