{
  "type": "Feature",
  "properties": {
    "gn:country":"RU",
    "gn:fcode":"PPL",
    "gn:pop":0,
    "iso:country":"RU",
    "name:arm_x_preferred":[
        "\u0556\u0565\u0564\u0575\u0561\u056f\u0578\u057e\u0578"
    ],
    "name:che_x_preferred":[
        "\u0424\u0435\u0434\u044f\u043a\u043e\u0432\u043e"
    ],
    "name:dut_x_preferred":[
        "Fedyakovo"
    ],
    "name:eng_x_preferred":[
        "Fedyakovo"
    ],
    "name:rus_x_preferred":[
        "\u0424\u0435\u0434\u044f\u043a\u043e\u0432\u043e"
    ],
    "name:unk_x_variant":[
        "\u0424\u0435\u0434\u044f\u043a\u043e\u0432\u043e"
    ],
    "qs:name":"Fedyakovo",
    "qs:name_adm0":"Russia",
    "qs:name_adm1":"Nizhny Novgorod Oblast",
    "qs:photos_9r":0,
    "qs:photos_sr":0,
    "qs:placetype":"Town",
    "qs:pop_sr":"0",
    "wd:wordcount":37,
    "wof:name":"Fedyakovo",
    "wof:placetype":"locality",
    "wof:population":0
},
  "geometry": {"coordinates":[44.05516,56.22806],"type":"Point"}
}