{
  "type": "Feature",
  "properties": {
    "gn:admin1_code":"60",
    "gn:asciiname":"Stan'kovo",
    "gn:country_code":"RU",
    "gn:dem":189,
    "gn:feature_class":"P",
    "gn:feature_code":"PPL",
    "gn:name":"Stan\u2019kovo",
    "gn:population":0,
    "gn:timezone":"Europe/Moscow",
    "iso:country":"RU",
    "name:rus_x_preferred":[
        "\u0421\u0442\u0430\u043d\u044c\u043a\u043e\u0432\u043e"
    ],
    "name:und_x_variant":[
        "Stan\u2019kovo"
    ],
    "wof:name":"Stan'kovo",
    "wof:placetype":"locality"
},
  "geometry": {"coordinates":[29.9485,56.3091],"type":"Point"}
}