{
  "type": "Feature",
  "properties": {
    "gn:country":"RU",
    "gn:fcode":"PPL",
    "gn:pop":8702,
    "iso:country":"RU",
    "name:che_x_preferred":[
        "\u042e\u0446\u0430"
    ],
    "name:dut_x_preferred":[
        "Yutsa"
    ],
    "name:eng_x_preferred":[
        "Yutsa"
    ],
    "name:nor_x_preferred":[
        "Jutsa"
    ],
    "name:rus_x_preferred":[
        "\u042e\u0446\u0430"
    ],
    "name:ukr_x_preferred":[
        "\u042e\u0446\u0430"
    ],
    "name:unk_x_variant":[
        "Dzhutskiy"
    ],
    "qs:name":"Yutsa",
    "qs:photos_9r":0,
    "qs:photos_sr":0,
    "qs:pop_sr":"5",
    "wd:wordcount":170,
    "wof:name":"Yutsa",
    "wof:placetype":"locality",
    "wof:population":8702
},
  "geometry": {"coordinates":[43.01278,43.95639],"type":"Point"}
}