{
  "type": "Feature",
  "properties": {
    "gn:admin1_code":"45",
    "gn:asciiname":"Pizhma",
    "gn:country_code":"RU",
    "gn:dem":96,
    "gn:feature_class":"P",
    "gn:feature_code":"PPL",
    "gn:name":"Pizhma",
    "gn:population":0,
    "gn:timezone":"Europe/Moscow",
    "iso:country":"RU",
    "name:eng_x_preferred":[
        "Pizhma"
    ],
    "name:nor_x_preferred":[
        "Pizjma"
    ],
    "name:rus_x_preferred":[
        "\u041f\u0438\u0436\u043c\u0430"
    ],
    "wof:name":"Pizhma",
    "wof:placetype":"locality"
},
  "geometry": {"coordinates":[47.38647,56.82487],"type":"Point"}
}