{
  "type": "Feature",
  "properties": {
    "gn:admin1_code":"52",
    "gn:asciiname":"Khriptsy",
    "gn:country_code":"RU",
    "gn:dem":59,
    "gn:feature_class":"P",
    "gn:feature_code":"PPL",
    "gn:name":"Khriptsy",
    "gn:population":0,
    "gn:timezone":"Europe/Moscow",
    "iso:country":"RU",
    "name:rus_x_preferred":[
        "\u0425\u0440\u0438\u043f\u0446\u044b"
    ],
    "wof:name":"Khriptsy",
    "wof:placetype":"locality"
},
  "geometry": {"coordinates":[30.64436,58.64261],"type":"Point"}
}