{
  "type": "Feature",
  "properties": {
    "gn:admin1_code":"90.0",
    "gn:asciiname":"Buldyri",
    "gn:country_code":"RU",
    "gn:dem":159,
    "gn:feature_class":"P",
    "gn:feature_code":"PPL",
    "gn:name":"Buldyri",
    "gn:population":0,
    "gn:timezone":"Asia/Yekaterinburg",
    "iso:country":"RU",
    "name:eng_x_preferred":[
        "Buldyri"
    ],
    "name:nor_x_preferred":[
        "Buldyri"
    ],
    "name:rus_x_preferred":[
        "\u0411\u0443\u043b\u0434\u044b\u0440\u0438"
    ],
    "name:und_x_variant":[
        "Buldyreva",
        "Buldyri",
        "\u0411\u0443\u043b\u0434\u044b\u0440\u0438"
    ],
    "wof:name":"Buldyri",
    "wof:placetype":"locality"
},
  "geometry": {"coordinates":[54.6427,59.4814],"type":"Point"}
}