{
  "type": "Feature",
  "properties": {
    "gn:admin1_code":"42",
    "gn:asciiname":"Shevtsovo",
    "gn:country_code":"RU",
    "gn:dem":66,
    "gn:feature_class":"P",
    "gn:feature_code":"PPL",
    "gn:name":"Shevtsovo",
    "gn:population":0,
    "gn:timezone":"Europe/Moscow",
    "iso:country":"RU",
    "name:rus_x_preferred":[
        "\u0428\u0435\u0432\u0446\u043e\u0432\u043e"
    ],
    "wof:name":"Shevtsovo",
    "wof:placetype":"locality"
},
  "geometry": {"coordinates":[28.33333,59.05],"type":"Point"}
}