{
  "type": "Feature",
  "properties": {
    "gn:admin1_code":"4",
    "gn:asciiname":"Novosmolenka",
    "gn:country_code":"RU",
    "gn:dem":173,
    "gn:feature_class":"P",
    "gn:feature_code":"PPL",
    "gn:name":"Novosmolenka",
    "gn:population":0,
    "gn:timezone":"Asia/Barnaul",
    "iso:country":"RU",
    "name:eng_x_preferred":[
        "Novosmolenskoye"
    ],
    "name:nor_x_preferred":[
        "Novosmolenka"
    ],
    "name:rus_x_preferred":[
        "\u041d\u043e\u0432\u043e\u0441\u043c\u043e\u043b\u0435\u043d\u043a\u0430"
    ],
    "name:und_x_variant":[
        "Novosmolenskoye",
        "Novosmolenka"
    ],
    "wof:name":"Novosmolenka",
    "wof:placetype":"locality"
},
  "geometry": {"coordinates":[84.7291,52.2335],"type":"Point"}
}