{
  "type": "Feature",
  "properties": {
    "gn:admin1_code":"60",
    "gn:asciiname":"Glukhovo",
    "gn:country_code":"RU",
    "gn:dem":76,
    "gn:feature_class":"P",
    "gn:feature_code":"PPL",
    "gn:name":"Glukhovo",
    "gn:population":0,
    "gn:timezone":"Europe/Moscow",
    "iso:country":"RU",
    "name:rus_x_preferred":[
        "\u0413\u043b\u0443\u0445\u043e\u0432\u043e"
    ],
    "wof:name":"Glukhovo",
    "wof:placetype":"locality"
},
  "geometry": {"coordinates":[28.37954,57.02886],"type":"Point"}
}