{
  "type": "Feature",
  "properties": {
    "gn:admin1_code":"52.0",
    "gn:asciiname":"Bol'shiye Nivki",
    "gn:country_code":"RU",
    "gn:dem":88,
    "gn:feature_class":"P",
    "gn:feature_code":"PPL",
    "gn:name":"Bol\u2019shiye Nivki",
    "gn:population":0,
    "gn:timezone":"Europe/Moscow",
    "iso:country":"RU",
    "name:rus_x_preferred":[
        "\u0411\u043e\u043b\u044c\u0448\u0438\u0435 \u041d\u0438\u0432\u043a\u0438"
    ],
    "name:und_x_variant":[
        "Bol\u2019shiye Nivki",
        "\u0411\u043e\u043b\u044c\u0448\u0438\u0435 \u041d\u0438\u0432\u043a\u0438"
    ],
    "wof:name":"Bol'shiye Nivki",
    "wof:placetype":"locality"
},
  "geometry": {"coordinates":[30.76667,57.75],"type":"Point"}
}