{
  "type": "Feature",
  "properties": {
    "gn:admin1_code":"44",
    "gn:asciiname":"Torfyanaya",
    "gn:country_code":"RU",
    "gn:dem":586,
    "gn:feature_class":"P",
    "gn:feature_code":"PPL",
    "gn:name":"Torfyanaya",
    "gn:population":0,
    "gn:timezone":"Asia/Magadan",
    "iso:country":"RU",
    "wof:name":"Torfyanaya",
    "wof:placetype":"locality"
},
  "geometry": {"coordinates":[149.26667,62.65],"type":"Point"}
}