{
  "type": "Feature",
  "properties": {
    "gn:admin1_code":"33",
    "gn:asciiname":"Khrobysty",
    "gn:country_code":"RU",
    "gn:dem":261,
    "gn:feature_class":"P",
    "gn:feature_code":"PPL",
    "gn:name":"Khrobysty",
    "gn:population":0,
    "gn:timezone":"Europe/Kirov",
    "iso:country":"RU",
    "name:eng_x_preferred":[
        "Khrobysty"
    ],
    "name:nor_x_preferred":[
        "Khrobysty"
    ],
    "name:rus_x_preferred":[
        "\u0425\u0440\u043e\u0431\u044b\u0441\u0442\u044b"
    ],
    "name:und_x_variant":[
        "Khrobystovskaya"
    ],
    "wof:name":"Khrobysty",
    "wof:placetype":"locality"
},
  "geometry": {"coordinates":[52.6401,58.4323],"type":"Point"}
}