{
  "type": "Feature",
  "properties": {
    "gn:admin1_code":"73.0",
    "gn:asciiname":"Appakovo",
    "gn:country_code":"RU",
    "gn:dem":108,
    "gn:feature_class":"P",
    "gn:feature_code":"PPL",
    "gn:name":"Appakovo",
    "gn:population":0,
    "gn:timezone":"Europe/Moscow",
    "iso:country":"RU",
    "name:eng_x_preferred":[
        "Appakovo"
    ],
    "name:nor_x_preferred":[
        "Appakovo"
    ],
    "name:rus_x_preferred":[
        "\u0410\u043f\u043f\u0430\u043a\u043e\u0432\u043e"
    ],
    "name:und_x_variant":[
        "Apakovo"
    ],
    "wof:name":"Appakovo",
    "wof:placetype":"locality"
},
  "geometry": {"coordinates":[51.90698,54.93334],"type":"Point"}
}