{
  "type": "Feature",
  "properties": {
    "gn:admin1_code":"12",
    "gn:admin2_code":"Itum-Kalinskiy Rayon",
    "gn:asciiname":"Anchilatli",
    "gn:country_code":"RU",
    "gn:dem":1701,
    "gn:feature_class":"P",
    "gn:feature_code":"PPL",
    "gn:name":"Anchilatli",
    "gn:population":0,
    "gn:timezone":"Europe/Moscow",
    "iso:country":"RU",
    "name:nor_x_preferred":[
        "Antsjilatli"
    ],
    "name:rus_x_preferred":[
        "\u0410\u043d\u0447\u0438\u043b\u0430\u0442\u043b\u0438"
    ],
    "wof:name":"Anchilatli",
    "wof:placetype":"locality"
},
  "geometry": {"coordinates":[45.97611,42.63167],"type":"Point"}
}