{
  "type": "Feature",
  "properties": {
    "gn:admin1_code":"16",
    "gn:asciiname":"Yangasy",
    "gn:country_code":"RU",
    "gn:dem":122,
    "gn:feature_class":"P",
    "gn:feature_code":"PPL",
    "gn:name":"Yangasy",
    "gn:population":0,
    "gn:timezone":"Europe/Moscow",
    "iso:country":"RU",
    "name:rus_x_preferred":[
        "\u042f\u043d\u0433\u0430\u0441\u044b"
    ],
    "wof:name":"Yangasy",
    "wof:placetype":"locality"
},
  "geometry": {"coordinates":[47.17524,55.74068000000001],"type":"Point"}
}