{
  "type": "Feature",
  "properties": {
    "gn:admin1_code":"37",
    "gn:asciiname":"Zaymishche",
    "gn:country_code":"RU",
    "gn:dem":158,
    "gn:feature_class":"P",
    "gn:feature_code":"PPL",
    "gn:name":"Zaymishche",
    "gn:population":0,
    "gn:timezone":"Europe/Moscow",
    "iso:country":"RU",
    "name:rus_x_preferred":[
        "\u0417\u0430\u0439\u043c\u0438\u0449\u0435"
    ],
    "name:und_x_variant":[
        "\u0417\u0430\u0439\u043c\u0438\u0449\u0435"
    ],
    "wof:name":"Zaymishche",
    "wof:placetype":"locality"
},
  "geometry": {"coordinates":[42.50769,58.00873000000001],"type":"Point"}
}