{
  "type": "Feature",
  "properties": {
    "gn:country":"RU",
    "gn:fcode":"PPL",
    "gn:population":3614,
    "iso:country":"RU",
    "name:bul_x_preferred":[
        "\u0421\u0438\u043b\u0438\u043a\u0430\u0442\u043d\u0438"
    ],
    "name:ceb_x_preferred":[
        "Silikatnyy"
    ],
    "name:che_x_preferred":[
        "\u0421\u0438\u043b\u0438\u043a\u0430\u0442\u043d\u044b\u0439"
    ],
    "name:eng_x_preferred":[
        "Silikatnyy"
    ],
    "name:hye_x_preferred":[
        "\u054d\u056b\u056c\u056b\u056f\u0561\u057f\u0576\u056b\u0575"
    ],
    "name:nor_x_preferred":[
        "Silikatnyj"
    ],
    "name:rus_x_preferred":[
        "\u0421\u0438\u043b\u0438\u043a\u0430\u0442\u043d\u044b\u0439"
    ],
    "qs:name":"Silikatnyy",
    "qs:name_adm0":"Russia",
    "qs:name_adm1":"Ulyanovsk Oblast",
    "qs:photos_9r":0,
    "qs:photos_sr":0,
    "qs:placetype":"Town",
    "qs:pop_sr":"4",
    "wof:name":"Silikatnyy",
    "wof:placetype":"locality",
    "wof:population":3614
},
  "geometry": {"coordinates":[48.3275,53.98957],"type":"Point"}
}