{
  "type": "Feature",
  "properties": {
    "gn:admin1_code":"73",
    "gn:asciiname":"Kobyakovo",
    "gn:country_code":"RU",
    "gn:dem":111,
    "gn:feature_class":"P",
    "gn:feature_code":"PPL",
    "gn:name":"Kobyakovo",
    "gn:population":0,
    "gn:timezone":"Europe/Moscow",
    "iso:country":"RU",
    "name:eng_x_preferred":[
        "Kobyakovo"
    ],
    "name:nor_x_preferred":[
        "Kobjakovo"
    ],
    "name:rus_x_preferred":[
        "\u041a\u043e\u0431\u044f\u043a\u043e\u0432\u043e"
    ],
    "name:und_x_variant":[
        "Kodyakovo",
        "Kobyakovo"
    ],
    "wof:name":"Kobyakovo",
    "wof:placetype":"locality"
},
  "geometry": {"coordinates":[49.82611,55.91464000000001],"type":"Point"}
}