{
  "type": "Feature",
  "properties": {
    "gn:admin1_code":"8",
    "gn:asciiname":"Kuyubarovo",
    "gn:country_code":"RU",
    "gn:dem":285,
    "gn:feature_class":"P",
    "gn:feature_code":"PPL",
    "gn:name":"Kuyubarovo",
    "gn:population":0,
    "gn:timezone":"Asia/Yekaterinburg",
    "iso:country":"RU",
    "name:rus_x_preferred":[
        "\u041a\u0443\u044e\u0431\u0430\u0440\u043e\u0432\u043e"
    ],
    "name:und_x_variant":[
        "Kuyu-Bar",
        "Kuyubarovo"
    ],
    "wof:name":"Kuyubarovo",
    "wof:placetype":"locality"
},
  "geometry": {"coordinates":[56.91324,52.02004],"type":"Point"}
}