{
  "type": "Feature",
  "properties": {
    "gn:admin1_code":"25.0",
    "gn:asciiname":"Malyshevo",
    "gn:country_code":"RU",
    "gn:dem":173,
    "gn:feature_class":"P",
    "gn:feature_code":"PPL",
    "gn:name":"Malyshevo",
    "gn:population":0,
    "gn:timezone":"Europe/Moscow",
    "iso:country":"RU",
    "name:rus_x_preferred":[
        "\u041c\u0430\u043b\u044b\u0448\u0435\u0432\u043e"
    ],
    "wof:name":"Malyshevo",
    "wof:placetype":"locality"
},
  "geometry": {"coordinates":[35.06,54.61],"type":"Point"}
}