{
  "type": "Feature",
  "properties": {
    "gn:admin1_code":"60",
    "gn:asciiname":"Morzhino",
    "gn:country_code":"RU",
    "gn:dem":179,
    "gn:feature_class":"P",
    "gn:feature_code":"PPL",
    "gn:name":"Morzhino",
    "gn:population":0,
    "gn:timezone":"Europe/Moscow",
    "iso:country":"RU",
    "name:rus_x_preferred":[
        "\u041c\u043e\u0440\u0436\u0438\u043d\u043e"
    ],
    "name:und_x_variant":[
        "\u041c\u043e\u0440\u0436\u0438\u043d\u043e"
    ],
    "wof:name":"Morzhino",
    "wof:placetype":"locality"
},
  "geometry": {"coordinates":[30.13306,55.86065],"type":"Point"}
}