{
  "type": "Feature",
  "properties": {
    "gn:admin1_code":"47.0",
    "gn:admin2_code":"472430",
    "gn:asciiname":"Khvorostinino",
    "gn:country_code":"RU",
    "gn:dem":185,
    "gn:feature_class":"P",
    "gn:feature_code":"PPL",
    "gn:name":"Khvorostinino",
    "gn:population":0,
    "gn:timezone":"Europe/Moscow",
    "iso:country":"RU",
    "name:rus_x_preferred":[
        "\u0425\u0432\u043e\u0440\u043e\u0441\u0442\u0438\u043d\u0438\u043d\u043e"
    ],
    "wof:name":"Khvorostinino",
    "wof:placetype":"locality"
},
  "geometry": {"coordinates":[35.91611,56.0321],"type":"Point"}
}