{
  "type": "Feature",
  "properties": {
    "gn:admin1_code":"76",
    "gn:asciiname":"Sotino",
    "gn:country_code":"RU",
    "gn:dem":162,
    "gn:feature_class":"P",
    "gn:feature_code":"PPL",
    "gn:name":"Sotino",
    "gn:population":0,
    "gn:timezone":"Europe/Moscow",
    "iso:country":"RU",
    "name:rus_x_preferred":[
        "\u0421\u043e\u0442\u0438\u043d\u043e"
    ],
    "wof:name":"Sotino",
    "wof:placetype":"locality"
},
  "geometry": {"coordinates":[37.21972,54.58456],"type":"Point"}
}