{
  "type": "Feature",
  "properties": {
    "gn:admin1_code":"28",
    "gn:asciiname":"Tsyakinsel'kya",
    "gn:country_code":"RU",
    "gn:dem":182,
    "gn:feature_class":"P",
    "gn:feature_code":"PPL",
    "gn:name":"Tsyakinsel\u2019kya",
    "gn:population":0,
    "gn:timezone":"Europe/Moscow",
    "iso:country":"RU",
    "name:fin_x_preferred":[
        "Ts\u00e4kinselk\u00e4"
    ],
    "name:und_x_variant":[
        "Pyakinsel\u2019kya",
        "Tsyakinsel\u2019kya"
    ],
    "wof:name":"Tsyakinsel'kya",
    "wof:placetype":"locality"
},
  "geometry": {"coordinates":[31.29353,62.1193],"type":"Point"}
}