{
  "type": "Feature",
  "properties": {
    "gn:admin1_code":"05",
    "gn:asciiname":"Kamyshenka",
    "gn:country_code":"RU",
    "gn:dem":224,
    "gn:feature_class":"P",
    "gn:feature_code":"PPL",
    "gn:name":"Kamyshenka",
    "gn:population":0,
    "gn:timezone":"Asia/Yakutsk",
    "iso:country":"RU",
    "name:eng_x_preferred":[
        "Kamyshenka"
    ],
    "name:nor_x_preferred":[
        "Kamysjinka"
    ],
    "name:rus_x_preferred":[
        "\u041a\u0430\u043c\u044b\u0448\u0438\u043d\u043a\u0430"
    ],
    "name:rus_x_variant":[
        "\u041a\u0430\u043c\u044b\u0448\u0435\u043d\u043a\u0430"
    ],
    "name:und_x_variant":[
        "Kamyshevka"
    ],
    "wof:name":"Kamyshenka",
    "wof:placetype":"locality"
},
  "geometry": {"coordinates":[129.33269999999999,50.0935],"type":"Point"}
}