{
  "type": "Feature",
  "properties": {
    "gn:admin1_code":"43",
    "gn:asciiname":"Yaman'",
    "gn:country_code":"RU",
    "gn:dem":119,
    "gn:feature_class":"P",
    "gn:feature_code":"PPL",
    "gn:name":"Yaman\u2019",
    "gn:population":0,
    "gn:timezone":"Europe/Moscow",
    "iso:country":"RU",
    "name:rus_x_preferred":[
        "\u042f\u043c\u0430\u043d\u044c"
    ],
    "name:und_x_variant":[
        "Yaman\u2019",
        "\u042f\u043c\u0430\u043d\u044c"
    ],
    "wof:name":"Yaman'",
    "wof:placetype":"locality"
},
  "geometry": {"coordinates":[39.58681,52.38975],"type":"Point"}
}