{
  "type": "Feature",
  "properties": {
    "gn:admin1_code":"37",
    "gn:asciiname":"Voroshilovo",
    "gn:country_code":"RU",
    "gn:dem":173,
    "gn:feature_class":"P",
    "gn:feature_code":"PPL",
    "gn:name":"Voroshilovo",
    "gn:population":0,
    "gn:timezone":"Europe/Moscow",
    "iso:country":"RU",
    "name:bak_x_preferred":[
        "\u0412\u043e\u0440\u043e\u0448\u0438\u043b\u043e\u0432"
    ],
    "name:che_x_preferred":[
        "\u0412\u043e\u0440\u043e\u0448\u0438\u043b\u043e\u0432\u043e"
    ],
    "name:hye_x_preferred":[
        "\u054e\u0578\u0580\u0578\u0577\u056b\u056c\u0578\u057e\u0578"
    ],
    "name:kaz_x_preferred":[
        "\u0412\u043e\u0440\u043e\u0448\u0438\u043b"
    ],
    "name:kir_x_preferred":[
        "\u0412\u043e\u0440\u043e\u0448\u0438\u043b"
    ],
    "name:rus_x_preferred":[
        "\u0412\u043e\u0440\u043e\u0448\u0438\u043b\u043e\u0432\u043e"
    ],
    "name:tat_x_preferred":[
        "\u0412\u043e\u0440\u043e\u0448\u0438\u043b\u043e\u0432\u043e"
    ],
    "name:ukr_x_preferred":[
        "\u0412\u043e\u0440\u043e\u0448\u0438\u043b\u043e\u0432\u043e"
    ],
    "wof:name":"Voroshilovo",
    "wof:placetype":"locality"
},
  "geometry": {"coordinates":[43.44726,58.57229],"type":"Point"}
}