{
  "type": "Feature",
  "properties": {
    "gn:admin1_code":"37",
    "gn:asciiname":"Voroshilovo",
    "gn:country_code":"RU",
    "gn:dem":173,
    "gn:feature_class":"P",
    "gn:feature_code":"PPL",
    "gn:name":"Voroshilovo",
    "gn:population":0,
    "gn:timezone":"Europe/Moscow",
    "iso:country":"RU",
    "name:rus_x_preferred":[
        "\u0412\u043e\u0440\u043e\u0448\u0438\u043b\u043e\u0432\u043e"
    ],
    "name:und_x_variant":[
        "\u0412\u043e\u0440\u043e\u0448\u0438\u043b\u043e\u0432\u043e"
    ],
    "wof:name":"Voroshilovo",
    "wof:placetype":"locality"
},
  "geometry": {"coordinates":[43.44726,58.57229],"type":"Point"}
}