{
  "type": "Feature",
  "properties": {
    "gn:admin1_code":"67",
    "gn:asciiname":"Makar'yevo",
    "gn:country_code":"RU",
    "gn:dem":27,
    "gn:feature_class":"P",
    "gn:feature_code":"PPL",
    "gn:name":"Makar\u2019yevo",
    "gn:population":0,
    "gn:timezone":"Europe/Saratov",
    "iso:country":"RU",
    "name:rus_x_preferred":[
        "\u041c\u0430\u043a\u0430\u0440\u044c\u0435\u0432\u043e"
    ],
    "name:und_x_variant":[
        "Makar\u2019yevo",
        "\u041c\u0430\u043a\u0430\u0440\u044c\u0435\u0432\u043e"
    ],
    "wof:name":"Makar'yevo",
    "wof:placetype":"locality"
},
  "geometry": {"coordinates":[48.28333,52.21667],"type":"Point"}
}