{
  "type": "Feature",
  "properties": {
    "gn:admin1_code":"13",
    "gn:asciiname":"Atamanovskiy",
    "gn:country_code":"RU",
    "gn:dem":277,
    "gn:feature_class":"P",
    "gn:feature_code":"PPL",
    "gn:name":"Atamanovskiy",
    "gn:population":0,
    "gn:timezone":"Asia/Yekaterinburg",
    "iso:country":"RU",
    "name:eng_x_preferred":[
        "Atamanovskiy"
    ],
    "name:nor_x_preferred":[
        "Atamanovskij"
    ],
    "name:rus_x_preferred":[
        "\u0410\u0442\u0430\u043c\u0430\u043d\u043e\u0432\u0441\u043a\u0438\u0439"
    ],
    "name:und_x_variant":[
        "Atamanskiy",
        "\u0410\u0442\u0430\u043c\u0430\u043d\u043e\u0432\u0441\u043a\u0438\u0439",
        "Atamanovskiy"
    ],
    "wof:name":"Atamanovskiy",
    "wof:placetype":"locality"
},
  "geometry": {"coordinates":[60.70389,52.22722],"type":"Point"}
}