{
  "type": "Feature",
  "properties": {
    "gn:admin1_code":"69",
    "gn:asciiname":"Krestovaya",
    "gn:country_code":"RU",
    "gn:dem":166,
    "gn:feature_class":"P",
    "gn:feature_code":"PPL",
    "gn:name":"Krestovaya",
    "gn:population":0,
    "gn:timezone":"Europe/Moscow",
    "iso:country":"RU",
    "name:rus_x_preferred":[
        "\u041a\u0440\u0435\u0441\u0442\u043e\u0432\u0430\u044f"
    ],
    "wof:name":"Krestovaya",
    "wof:placetype":"locality"
},
  "geometry": {"coordinates":[32.88694,53.5475],"type":"Point"}
}