{
  "type": "Feature",
  "properties": {
    "gn:admin1_code":"33.0",
    "gn:asciiname":"Patrushi",
    "gn:country_code":"RU",
    "gn:dem":89,
    "gn:feature_class":"P",
    "gn:feature_code":"PPL",
    "gn:name":"Patrushi",
    "gn:population":0,
    "gn:timezone":"Europe/Kirov",
    "iso:country":"RU",
    "name:rus_x_preferred":[
        "\u041f\u0430\u0442\u0440\u0443\u0448\u0438"
    ],
    "wof:name":"Patrushi",
    "wof:placetype":"locality"
},
  "geometry": {"coordinates":[48.93735,57.53136],"type":"Point"}
}