{
  "type": "Feature",
  "properties": {
    "gn:admin1_code":"71",
    "gn:asciiname":"Loginovo",
    "gn:country_code":"RU",
    "gn:dem":236,
    "gn:feature_class":"P",
    "gn:feature_code":"PPL",
    "gn:name":"Loginovo",
    "gn:population":0,
    "gn:timezone":"Asia/Yekaterinburg",
    "iso:country":"RU",
    "name:eng_x_preferred":[
        "Loginovo"
    ],
    "name:nor_x_preferred":[
        "Loginovo"
    ],
    "name:rus_x_preferred":[
        "\u041b\u043e\u0433\u0438\u043d\u043e\u0432\u043e"
    ],
    "name:und_x_variant":[
        "Loginovskiy",
        "\u041b\u043e\u0433\u0438\u043d\u043e\u0432\u043e",
        "Loginovo"
    ],
    "wof:name":"Loginovo",
    "wof:placetype":"locality"
},
  "geometry": {"coordinates":[61.29861,56.62444],"type":"Point"}
}