{
  "type": "Feature",
  "properties": {
    "gn:admin1_code":"64",
    "gn:asciiname":"Belkino",
    "gn:country_code":"RU",
    "gn:dem":7,
    "gn:feature_class":"P",
    "gn:feature_code":"PPL",
    "gn:name":"Belkino",
    "gn:population":0,
    "gn:timezone":"Asia/Sakhalin",
    "iso:country":"RU",
    "name:nor_x_preferred":[
        "Belkino"
    ],
    "name:rus_x_preferred":[
        "\u0411\u0435\u043b\u043a\u0438\u043d\u043e"
    ],
    "name:und_x_variant":[
        "Yorukunai",
        "Atsunai",
        "Yarukunai",
        "Erukunay",
        "Yokunai",
        "Berkino",
        "Belkino"
    ],
    "wof:name":"Belkino",
    "wof:placetype":"locality"
},
  "geometry": {"coordinates":[142.16333999999995,49.82369],"type":"Point"}
}