{
  "type": "Feature",
  "properties": {
    "gn:admin1_code":"85",
    "gn:asciiname":"Malyy Dor",
    "gn:country_code":"RU",
    "gn:dem":151,
    "gn:feature_class":"P",
    "gn:feature_code":"PPL",
    "gn:name":"Malyy Dor",
    "gn:population":0,
    "gn:timezone":"Europe/Moscow",
    "iso:country":"RU",
    "name:rus_x_preferred":[
        "\u041c\u0430\u043b\u044b\u0439 \u0414\u043e\u0440"
    ],
    "name:und_x_variant":[
        "\u041c\u0430\u043b\u044b\u0439 \u0414\u043e\u0440"
    ],
    "wof:name":"Malyy Dor",
    "wof:placetype":"locality"
},
  "geometry": {"coordinates":[46.2523,60.1096],"type":"Point"}
}