{
  "type": "Feature",
  "properties": {
    "gn:admin1_code":"69",
    "gn:asciiname":"Ostolopovo",
    "gn:country_code":"RU",
    "gn:dem":183,
    "gn:feature_class":"P",
    "gn:feature_code":"PPL",
    "gn:name":"Ostolopovo",
    "gn:population":0,
    "gn:timezone":"Europe/Moscow",
    "iso:country":"RU",
    "name:rus_x_preferred":[
        "\u041e\u0441\u0442\u043e\u043b\u043e\u043f\u043e\u0432\u043e"
    ],
    "name:und_x_variant":[
        "\u041e\u0441\u0442\u043e\u043b\u043e\u043f\u043e\u0432\u043e"
    ],
    "wof:name":"Ostolopovo",
    "wof:placetype":"locality"
},
  "geometry": {"coordinates":[34.47069,55.75131999999999],"type":"Point"}
}