{
  "type": "Feature",
  "properties": {
    "gn:admin1_code":"52",
    "gn:asciiname":"Novoye Murav'yevo",
    "gn:country_code":"RU",
    "gn:dem":183,
    "gn:feature_class":"P",
    "gn:feature_code":"PPL",
    "gn:name":"Novoye Murav\u2019yevo",
    "gn:population":0,
    "gn:timezone":"Europe/Moscow",
    "iso:country":"RU",
    "name:rus_x_preferred":[
        "\u041d\u043e\u0432\u043e\u0435 \u041c\u0443\u0440\u0430\u0432\u044c\u0435\u0432\u043e"
    ],
    "name:und_x_variant":[
        "Novoye Murav\u2019yevo",
        "\u041d\u043e\u0432\u043e\u0435 \u041c\u0443\u0440\u0430\u0432\u044c\u0435\u0432\u043e"
    ],
    "wof:name":"Novoye Murav'yevo",
    "wof:placetype":"locality"
},
  "geometry": {"coordinates":[35.48678,58.44256],"type":"Point"}
}