{
  "type": "Feature",
  "properties": {
    "gn:admin1_code":"23",
    "gn:asciiname":"Vyshkino Pervoye",
    "gn:country_code":"RU",
    "gn:dem":33,
    "gn:feature_class":"P",
    "gn:feature_code":"PPL",
    "gn:name":"Vyshkino Pervoye",
    "gn:population":0,
    "gn:timezone":"Europe/Kaliningrad",
    "iso:country":"RU",
    "wof:name":"Vyshkino Pervoye",
    "wof:placetype":"locality"
},
  "geometry": {"coordinates":[22.35944,54.91389],"type":"Point"}
}