{
  "type": "Feature",
  "properties": {
    "gn:admin1_code":"33",
    "gn:asciiname":"Malyshikha",
    "gn:country_code":"RU",
    "gn:dem":144,
    "gn:feature_class":"P",
    "gn:feature_code":"PPL",
    "gn:name":"Malyshikha",
    "gn:population":0,
    "gn:timezone":"Europe/Kirov",
    "iso:country":"RU",
    "name:rus_x_preferred":[
        "\u041c\u0430\u043b\u044b\u0448\u0438\u0445\u0430"
    ],
    "wof:name":"Malyshikha",
    "wof:placetype":"locality"
},
  "geometry": {"coordinates":[49.1319,58.4062],"type":"Point"}
}