{
  "type": "Feature",
  "properties": {
    "gn:admin1_code":"65",
    "gn:asciiname":"Moksha",
    "gn:country_code":"RU",
    "gn:dem":88,
    "gn:feature_class":"P",
    "gn:feature_code":"PPL",
    "gn:name":"Moksha",
    "gn:population":0,
    "gn:timezone":"Europe/Samara",
    "iso:country":"RU",
    "name:eng_x_preferred":[
        "Moksha"
    ],
    "name:nor_x_preferred":[
        "Moksja"
    ],
    "name:rus_x_preferred":[
        "\u041c\u043e\u043a\u0448\u0430"
    ],
    "wof:name":"Moksha",
    "wof:placetype":"locality"
},
  "geometry": {"coordinates":[50.40443,52.67213],"type":"Point"}
}