{
  "type": "Feature",
  "properties": {
    "gn:admin1_code":"63",
    "gn:asciiname":"Pionerka",
    "gn:country_code":"RU",
    "gn:dem":785,
    "gn:feature_class":"P",
    "gn:feature_code":"PPL",
    "gn:name":"Pionerka",
    "gn:population":0,
    "gn:timezone":"Asia/Yakutsk",
    "iso:country":"RU",
    "name:rus_x_preferred":[
        "\u041f\u0438\u043e\u043d\u0435\u0440\u043a\u0430"
    ],
    "wof:name":"Pionerka",
    "wof:placetype":"locality"
},
  "geometry": {"coordinates":[124.84999999999999,56.98333],"type":"Point"}
}