{
  "type": "Feature",
  "properties": {
    "gn:admin1_code":"77",
    "gn:asciiname":"Titovskoye",
    "gn:country_code":"RU",
    "gn:dem":132,
    "gn:feature_class":"P",
    "gn:feature_code":"PPL",
    "gn:name":"Titovskoye",
    "gn:population":0,
    "gn:timezone":"Europe/Moscow",
    "iso:country":"RU",
    "name:rus_x_preferred":[
        "\u0422\u0438\u0442\u043e\u0432\u0441\u043a\u043e\u0435"
    ],
    "name:und_x_variant":[
        "\u0422\u0438\u0442\u043e\u0432\u0441\u043a\u043e\u0435"
    ],
    "wof:name":"Titovskoye",
    "wof:placetype":"locality"
},
  "geometry": {"coordinates":[37.1432,58.5474],"type":"Point"}
}