{
  "type": "Feature",
  "properties": {
    "gn:admin1_code":"61",
    "gn:asciiname":"Novoselovka",
    "gn:country_code":"RU",
    "gn:dem":85,
    "gn:feature_class":"P",
    "gn:feature_code":"PPL",
    "gn:name":"Novos\u00eblovka",
    "gn:population":0,
    "gn:timezone":"Europe/Moscow",
    "iso:country":"RU",
    "name:eng_x_preferred":[
        "Novos\u00eblovka"
    ],
    "name:nor_x_preferred":[
        "Novoselovka"
    ],
    "name:rus_x_preferred":[
        "\u041d\u043e\u0432\u043e\u0441\u0435\u043b\u043e\u0432\u043a\u0430"
    ],
    "name:rus_x_variant":[
        "\u041d\u043e\u0432\u043e\u0441\u0451\u043b\u043e\u0432\u043a\u0430"
    ],
    "name:und_x_variant":[
        "Novos\u00eblovka",
        "\u041d\u043e\u0432\u043e\u0441\u0451\u043b\u043e\u0432\u043a\u0430"
    ],
    "wof:name":"Novoselovka",
    "wof:placetype":"locality"
},
  "geometry": {"coordinates":[40.3598,49.26023],"type":"Point"}
}