{
  "type": "Feature",
  "properties": {
    "gn:admin1_code":"88",
    "gn:asciiname":"Neverovo",
    "gn:country_code":"RU",
    "gn:dem":114,
    "gn:feature_class":"P",
    "gn:feature_code":"PPL",
    "gn:name":"Neverovo",
    "gn:population":0,
    "gn:timezone":"Europe/Moscow",
    "iso:country":"RU",
    "name:rus_x_preferred":[
        "\u041d\u0435\u0432\u0435\u0440\u043e\u0432\u043e"
    ],
    "name:und_x_variant":[
        "\u041d\u0435\u0432\u0435\u0440\u043e\u0432\u043e"
    ],
    "wof:name":"Neverovo",
    "wof:placetype":"locality"
},
  "geometry": {"coordinates":[38.4799,57.7642],"type":"Point"}
}