{
  "type": "Feature",
  "properties": {
    "gn:admin1_code":"33",
    "gn:asciiname":"Starkovskaya",
    "gn:country_code":"RU",
    "gn:dem":182,
    "gn:feature_class":"P",
    "gn:feature_code":"PPL",
    "gn:name":"Starkovskaya",
    "gn:population":0,
    "gn:timezone":"Europe/Kirov",
    "iso:country":"RU",
    "name:rus_x_preferred":[
        "\u0421\u0442\u0430\u0440\u043a\u043e\u0432\u0441\u043a\u0430\u044f"
    ],
    "wof:name":"Starkovskaya",
    "wof:placetype":"locality"
},
  "geometry": {"coordinates":[52.53106,59.62441999999999],"type":"Point"}
}