{
  "type": "Feature",
  "properties": {
    "gn:admin1_code":"73",
    "gn:asciiname":"Zabornaya Polyana",
    "gn:country_code":"RU",
    "gn:dem":66,
    "gn:feature_class":"P",
    "gn:feature_code":"PPL",
    "gn:name":"Zabornaya Polyana",
    "gn:population":0,
    "gn:timezone":"Europe/Moscow",
    "iso:country":"RU",
    "name:rus_x_preferred":[
        "\u0417\u0430\u0431\u043e\u0440\u043d\u0430\u044f \u041f\u043e\u043b\u044f\u043d\u0430"
    ],
    "wof:name":"Zabornaya Polyana",
    "wof:placetype":"locality"
},
  "geometry": {"coordinates":[48.6196,55.3819],"type":"Point"}
}