{
  "type": "Feature",
  "properties": {
    "gn:admin1_code":"83",
    "gn:asciiname":"Zheldybino",
    "gn:country_code":"RU",
    "gn:dem":203,
    "gn:feature_class":"P",
    "gn:feature_code":"PPL",
    "gn:name":"Zheldybino",
    "gn:population":0,
    "gn:timezone":"Europe/Moscow",
    "iso:country":"RU",
    "name:rus_x_preferred":[
        "\u0416\u0435\u043b\u0434\u044b\u0431\u0438\u043d\u043e"
    ],
    "wof:name":"Zheldybino",
    "wof:placetype":"locality"
},
  "geometry": {"coordinates":[39.09649,56.25364],"type":"Point"}
}