{
  "type": "Feature",
  "properties": {
    "gn:admin1_code":"52.0",
    "gn:asciiname":"Chizhovo",
    "gn:country_code":"RU",
    "gn:dem":226,
    "gn:feature_class":"P",
    "gn:feature_code":"PPL",
    "gn:name":"Chizhovo",
    "gn:population":0,
    "gn:timezone":"Europe/Moscow",
    "iso:country":"RU",
    "name:rus_x_preferred":[
        "\u0427\u0438\u0436\u043e\u0432\u043e"
    ],
    "wof:name":"Chizhovo",
    "wof:placetype":"locality"
},
  "geometry": {"coordinates":[32.77655,57.53314],"type":"Point"}
}