{
  "type": "Feature",
  "properties": {
    "gn:admin1_code":"63",
    "gn:asciiname":"Olom",
    "gn:country_code":"RU",
    "gn:dem":204,
    "gn:feature_class":"P",
    "gn:feature_code":"PPL",
    "gn:name":"Olom",
    "gn:population":0,
    "gn:timezone":"Asia/Yakutsk",
    "iso:country":"RU",
    "name:eng_x_preferred":[
        "Olom"
    ],
    "name:nor_x_preferred":[
        "Olom-Kjuel"
    ],
    "name:rus_x_preferred":[
        "\u041e\u043b\u043e\u043c-\u041a\u044e\u0435\u043b\u044c"
    ],
    "name:rus_x_variant":[
        "\u041e\u043b\u043e\u043c"
    ],
    "name:und_x_variant":[
        "Olom-Kyuyel\u2019"
    ],
    "wof:name":"Olom",
    "wof:placetype":"locality"
},
  "geometry": {"coordinates":[130.87932000000001,61.2787],"type":"Point"}
}