{
  "type": "Feature",
  "properties": {
    "gn:admin1_code":"13",
    "gn:asciiname":"Kubagusheva",
    "gn:country_code":"RU",
    "gn:dem":166,
    "gn:feature_class":"P",
    "gn:feature_code":"PPL",
    "gn:name":"Kubagusheva",
    "gn:population":0,
    "gn:timezone":"Asia/Yekaterinburg",
    "iso:country":"RU",
    "name:eng_x_preferred":[
        "Kubagusheva"
    ],
    "name:nor_x_preferred":[
        "Kubagusjeva"
    ],
    "name:rus_x_preferred":[
        "\u041a\u0443\u0431\u0430\u0433\u0443\u0448\u0435\u0432\u0430"
    ],
    "wof:name":"Kubagusheva",
    "wof:placetype":"locality"
},
  "geometry": {"coordinates":[61.8797,55.8329],"type":"Point"}
}