{
  "type": "Feature",
  "properties": {
    "gn:admin1_code":"52",
    "gn:asciiname":"Varygino",
    "gn:country_code":"RU",
    "gn:dem":177,
    "gn:feature_class":"P",
    "gn:feature_code":"PPL",
    "gn:name":"Varygino",
    "gn:population":0,
    "gn:timezone":"Europe/Moscow",
    "iso:country":"RU",
    "name:rus_x_preferred":[
        "\u0412\u0430\u0440\u044b\u0433\u0438\u043d\u043e"
    ],
    "name:und_x_variant":[
        "\u0412\u0430\u0440\u044b\u0433\u0438\u043d\u043e",
        "Vorygino"
    ],
    "wof:name":"Varygino",
    "wof:placetype":"locality"
},
  "geometry": {"coordinates":[35.11537,58.33702],"type":"Point"}
}