{
  "type": "Feature",
  "properties": {
    "gn:admin1_code":"62",
    "gn:asciiname":"Munyakovo",
    "gn:country_code":"RU",
    "gn:dem":97,
    "gn:feature_class":"P",
    "gn:feature_code":"PPL",
    "gn:name":"Munyakovo",
    "gn:population":0,
    "gn:timezone":"Europe/Moscow",
    "iso:country":"RU",
    "name:eng_x_preferred":[
        "Munyakovo"
    ],
    "name:nor_x_preferred":[
        "Munjakovo"
    ],
    "name:rus_x_preferred":[
        "\u041c\u0443\u043d\u044f\u043a\u043e\u0432\u043e"
    ],
    "wof:name":"Munyakovo",
    "wof:placetype":"locality"
},
  "geometry": {"coordinates":[40.2056,54.201],"type":"Point"}
}