{
  "type": "Feature",
  "properties": {
    "gn:country":"RU",
    "gn:fcode":"PPL",
    "gn:population":0,
    "iso:country":"RU",
    "name:eng_x_preferred":[
        "Novoye Rakhino"
    ],
    "name:nor_x_preferred":[
        "Nov.Rakhino"
    ],
    "name:rus_x_preferred":[
        "\u041d\u043e\u0432.\u0420\u0430\u0445\u0438\u043d\u043e"
    ],
    "name:rus_x_variant":[
        "\u041d\u043e\u0432\u043e\u0435 \u0420\u0430\u0445\u0438\u043d\u043e"
    ],
    "qs:name":"Novoye Rakhino",
    "qs:name_adm0":"Russia",
    "qs:name_adm1":"Novgorod Oblast",
    "qs:photos_9k":1,
    "qs:photos_9r":1,
    "qs:photos_all":1,
    "qs:photos_sr":0,
    "qs:placetype":"Town",
    "qs:pop_sr":"0",
    "wof:name":"Novoye Rakhino",
    "wof:placetype":"locality",
    "wof:population":0
},
  "geometry": {"coordinates":[32.76067,58.145],"type":"Point"}
}