{
  "type": "Feature",
  "properties": {
    "gn:admin1_code":"41",
    "gn:asciiname":"Vorobzha",
    "gn:country_code":"RU",
    "gn:dem":171,
    "gn:feature_class":"P",
    "gn:feature_code":"PPL",
    "gn:name":"Vorobzha",
    "gn:population":0,
    "gn:timezone":"Europe/Moscow",
    "iso:country":"RU",
    "name:rus_x_preferred":[
        "\u0412\u043e\u0440\u043e\u0431\u0436\u0430"
    ],
    "name:und_x_variant":[
        "Vorozhba",
        "Vorobzha"
    ],
    "wof:name":"Vorobzha",
    "wof:placetype":"locality"
},
  "geometry": {"coordinates":[35.48556,51.16139],"type":"Point"}
}