{
  "type": "Feature",
  "properties": {
    "gn:admin1_code":"67",
    "gn:asciiname":"Khlebnovka",
    "gn:country_code":"RU",
    "gn:dem":32,
    "gn:feature_class":"P",
    "gn:feature_code":"PPL",
    "gn:name":"Khlebnovka",
    "gn:population":0,
    "gn:timezone":"Europe/Saratov",
    "iso:country":"RU",
    "name:eng_x_preferred":[
        "Khlebnovka"
    ],
    "name:nor_x_preferred":[
        "Khlebnovka"
    ],
    "name:rus_x_preferred":[
        "\u0425\u043b\u0435\u0431\u043d\u043e\u0432\u043a\u0430"
    ],
    "name:und_x_variant":[
        "Khlevnovka",
        "\u0425\u043b\u0435\u0431\u043d\u043e\u0432\u043a\u0430",
        "Khlebnovka"
    ],
    "wof:name":"Khlebnovka",
    "wof:placetype":"locality"
},
  "geometry": {"coordinates":[48.3614,52.1379],"type":"Point"}
}