{
  "type": "Feature",
  "properties": {
    "gn:admin1_code":"46",
    "gn:asciiname":"Kochunovo",
    "gn:country_code":"RU",
    "gn:dem":116,
    "gn:feature_class":"P",
    "gn:feature_code":"PPL",
    "gn:name":"Kochunovo",
    "gn:population":0,
    "gn:timezone":"Europe/Moscow",
    "iso:country":"RU",
    "name:rus_x_preferred":[
        "\u041a\u043e\u0447\u0443\u043d\u043e\u0432\u043e"
    ],
    "wof:name":"Kochunovo",
    "wof:placetype":"locality"
},
  "geometry": {"coordinates":[45.4594,54.4226],"type":"Point"}
}