{
  "type": "Feature",
  "properties": {
    "gn:admin1_code":"60",
    "gn:asciiname":"Kholmatka",
    "gn:country_code":"RU",
    "gn:dem":76,
    "gn:feature_class":"P",
    "gn:feature_code":"PPL",
    "gn:name":"Kholmatka",
    "gn:population":0,
    "gn:timezone":"Europe/Moscow",
    "iso:country":"RU",
    "name:rus_x_preferred":[
        "\u0425\u043e\u043b\u043c\u0430\u0442\u043a\u0430"
    ],
    "wof:name":"Kholmatka",
    "wof:placetype":"locality"
},
  "geometry": {"coordinates":[28.13877,57.10206],"type":"Point"}
}