{
  "type": "Feature",
  "properties": {
    "gn:admin1_code":"16.0",
    "gn:asciiname":"Bol'shiye Kryshki",
    "gn:country_code":"RU",
    "gn:dem":130,
    "gn:feature_class":"P",
    "gn:feature_code":"PPL",
    "gn:name":"Bol\u2019shiye Kryshki",
    "gn:population":0,
    "gn:timezone":"Europe/Moscow",
    "iso:country":"RU",
    "name:rus_x_preferred":[
        "\u0411\u043e\u043b\u044c\u0448\u0438\u0435 \u041a\u0440\u044b\u0448\u043a\u0438"
    ],
    "name:und_x_variant":[
        "Bol\u2019shiye Kryshki"
    ],
    "wof:name":"Bol'shiye Kryshki",
    "wof:placetype":"locality"
},
  "geometry": {"coordinates":[47.78894,55.8434],"type":"Point"}
}