{
  "type": "Feature",
  "properties": {
    "gn:admin1_code":"34.0",
    "gn:asciiname":"Chikshino",
    "gn:country_code":"RU",
    "gn:dem":81,
    "gn:feature_class":"P",
    "gn:feature_code":"PPL",
    "gn:name":"Chikshino",
    "gn:population":0,
    "gn:timezone":"Europe/Moscow",
    "iso:country":"RU",
    "name:eng_x_preferred":[
        "Chikshino"
    ],
    "name:nor_x_preferred":[
        "Tsjiksjino"
    ],
    "name:rus_x_preferred":[
        "\u0427\u0438\u043a\u0448\u0438\u043d\u043e"
    ],
    "name:und_x_variant":[
        "\u0427\u0438\u043a\u0448\u0438\u043d\u043e",
        "Chikshino"
    ],
    "wof:name":"Chikshino",
    "wof:placetype":"locality"
},
  "geometry": {"coordinates":[56.4186,64.89941],"type":"Point"}
}