{
  "type": "Feature",
  "properties": {
    "gn:admin1_code":"77",
    "gn:asciiname":"Krutyak",
    "gn:country_code":"RU",
    "gn:dem":256,
    "gn:feature_class":"P",
    "gn:feature_code":"PPL",
    "gn:name":"Krutyak",
    "gn:population":0,
    "gn:timezone":"Europe/Moscow",
    "iso:country":"RU",
    "name:rus_x_preferred":[
        "\u041a\u0440\u0443\u0442\u044f\u043a"
    ],
    "wof:name":"Krutyak",
    "wof:placetype":"locality"
},
  "geometry": {"coordinates":[33.85556,56.88639000000001],"type":"Point"}
}