{
  "type": "Feature",
  "properties": {
    "gn:admin1_code":"56",
    "gn:asciiname":"Sosenskiy",
    "gn:country_code":"RU",
    "gn:dem":169,
    "gn:feature_class":"P",
    "gn:feature_code":"PPL",
    "gn:name":"Sosenskiy",
    "gn:population":0,
    "gn:timezone":"Europe/Moscow",
    "iso:country":"RU",
    "name:rus_x_preferred":[
        "\u0421\u043e\u0441\u0435\u043d\u0441\u043a\u0438\u0439"
    ],
    "name:und_x_variant":[
        "Podkobak",
        "Podkabak",
        "Sosenskiy"
    ],
    "wof:name":"Sosenskiy",
    "wof:placetype":"locality"
},
  "geometry": {"coordinates":[36.74424000000001,52.27024],"type":"Point"}
}