{
  "type": "Feature",
  "properties": {
    "gn:admin1_code":"5",
    "gn:asciiname":"Urkima",
    "gn:country_code":"RU",
    "gn:dem":620,
    "gn:feature_class":"P",
    "gn:feature_code":"PPL",
    "gn:name":"Urkima",
    "gn:population":0,
    "gn:timezone":"Asia/Yakutsk",
    "iso:country":"RU",
    "wof:name":"Urkima",
    "wof:placetype":"locality"
},
  "geometry": {"coordinates":[123.38333,55.18333000000001],"type":"Point"}
}