{
  "type": "Feature",
  "properties": {
    "gn:admin1_code":"41",
    "gn:asciiname":"Uyedinennoye",
    "gn:country_code":"RU",
    "gn:dem":163,
    "gn:feature_class":"P",
    "gn:feature_code":"PPL",
    "gn:name":"Uyedinennoye",
    "gn:population":0,
    "gn:timezone":"Europe/Moscow",
    "iso:country":"RU",
    "name:rus_x_preferred":[
        "\u0423\u0435\u0434\u0438\u043d\u0435\u043d\u043d\u043e\u0435"
    ],
    "wof:name":"Uyedinennoye",
    "wof:placetype":"locality"
},
  "geometry": {"coordinates":[37.1544,51.9614],"type":"Point"}
}