{
  "type": "Feature",
  "properties": {
    "gn:admin1_code":"65",
    "gn:asciiname":"Ozerki",
    "gn:country_code":"RU",
    "gn:dem":72,
    "gn:feature_class":"P",
    "gn:feature_code":"PPL",
    "gn:name":"Ozerki",
    "gn:population":0,
    "gn:timezone":"Europe/Samara",
    "iso:country":"RU",
    "name:rus_x_preferred":[
        "\u041e\u0437\u0435\u0440\u043a\u0438"
    ],
    "wof:name":"Ozerki",
    "wof:placetype":"locality"
},
  "geometry": {"coordinates":[50.53381,52.74322],"type":"Point"}
}