{
  "type": "Feature",
  "properties": {
    "gn:admin1_code":"46",
    "gn:asciiname":"Kulikovo",
    "gn:country_code":"RU",
    "gn:dem":187,
    "gn:feature_class":"P",
    "gn:feature_code":"PPL",
    "gn:name":"Kulikovo",
    "gn:population":0,
    "gn:timezone":"Europe/Moscow",
    "iso:country":"RU",
    "name:nor_x_preferred":[
        "Kulikovo"
    ],
    "name:rus_x_preferred":[
        "\u041a\u0443\u043b\u0438\u043a\u043e\u0432\u043e"
    ],
    "wof:name":"Kulikovo",
    "wof:placetype":"locality"
},
  "geometry": {"coordinates":[43.65057,54.41212],"type":"Point"}
}