{
  "type": "Feature",
  "properties": {
    "gn:admin1_code":"72",
    "gn:asciiname":"Peschanoye",
    "gn:country_code":"RU",
    "gn:dem":149,
    "gn:feature_class":"P",
    "gn:feature_code":"PPL",
    "gn:name":"Peschanoye",
    "gn:population":0,
    "gn:timezone":"Europe/Moscow",
    "iso:country":"RU",
    "name:eng_x_preferred":[
        "Peschanoye"
    ],
    "name:nor_x_preferred":[
        "Pestsjanoje"
    ],
    "name:rus_x_preferred":[
        "\u041f\u0435\u0441\u0447\u0430\u043d\u043e\u0435"
    ],
    "wof:name":"Peschanoye",
    "wof:placetype":"locality"
},
  "geometry": {"coordinates":[40.5739,52.6386],"type":"Point"}
}