{
  "type": "Feature",
  "properties": {
    "gn:admin1_code":"6",
    "gn:asciiname":"Yamnaya",
    "gn:country_code":"RU",
    "gn:dem":122,
    "gn:feature_class":"P",
    "gn:feature_code":"PPL",
    "gn:name":"Yamnaya",
    "gn:population":0,
    "gn:timezone":"Europe/Moscow",
    "iso:country":"RU",
    "name:eng_x_preferred":[
        "Yamnaya"
    ],
    "name:nor_x_preferred":[
        "Jamnaja"
    ],
    "name:rus_x_preferred":[
        "\u042f\u043c\u043d\u0430\u044f"
    ],
    "wof:name":"Yamnaya",
    "wof:placetype":"locality"
},
  "geometry": {"coordinates":[43.89389,61.36889],"type":"Point"}
}