{
  "type": "Feature",
  "properties": {
    "gn:admin1_code":"77",
    "gn:asciiname":"Kiryakovo",
    "gn:country_code":"RU",
    "gn:dem":130,
    "gn:feature_class":"P",
    "gn:feature_code":"PPL",
    "gn:name":"Kiryakovo",
    "gn:population":0,
    "gn:timezone":"Europe/Moscow",
    "iso:country":"RU",
    "name:rus_x_preferred":[
        "\u041a\u0438\u0440\u044f\u043a\u043e\u0432\u043e"
    ],
    "wof:name":"Kiryakovo",
    "wof:placetype":"locality"
},
  "geometry": {"coordinates":[37.8338,57.3506],"type":"Point"}
}