{
  "type": "Feature",
  "properties": {
    "gn:admin1_code":"21",
    "gn:asciiname":"Snetinovo",
    "gn:country_code":"RU",
    "gn:dem":113,
    "gn:feature_class":"P",
    "gn:feature_code":"PPL",
    "gn:name":"Snetinovo",
    "gn:population":0,
    "gn:timezone":"Europe/Moscow",
    "iso:country":"RU",
    "name:eng_x_preferred":[
        "Snetinovo"
    ],
    "name:nor_x_preferred":[
        "Snetinovo"
    ],
    "name:rus_x_preferred":[
        "\u0421\u043d\u0435\u0442\u0438\u043d\u043e\u0432\u043e"
    ],
    "wof:name":"Snetinovo",
    "wof:placetype":"locality"
},
  "geometry": {"coordinates":[41.30825,57.16178000000001],"type":"Point"}
}