{
  "type": "Feature",
  "properties": {
    "gn:admin1_code":"52",
    "gn:asciiname":"Savkino",
    "gn:country_code":"RU",
    "gn:dem":209,
    "gn:feature_class":"P",
    "gn:feature_code":"PPL",
    "gn:name":"Savkino",
    "gn:population":0,
    "gn:timezone":"Europe/Moscow",
    "iso:country":"RU",
    "name:bak_x_preferred":[
        "\u0421\u0430\u0432\u043a\u0438\u043d"
    ],
    "name:che_x_preferred":[
        "\u0421\u0430\u0432\u043a\u0438\u043d\u043e"
    ],
    "name:chv_x_preferred":[
        "\u00c7\u0438\u0440\u0115\u043a\u043b\u0115"
    ],
    "name:hye_x_preferred":[
        "\u054d\u0561\u057e\u056f\u056b\u0576\u0578"
    ],
    "name:kaz_x_preferred":[
        "\u0421\u0430\u0432\u043a\u0438\u043d\u043e"
    ],
    "name:kir_x_preferred":[
        "\u0421\u0430\u0432\u043a\u0438\u043d\u043e"
    ],
    "name:rus_x_preferred":[
        "\u0421\u0430\u0432\u043a\u0438\u043d\u043e"
    ],
    "name:tat_x_preferred":[
        "\u0421\u0430\u0432\u043a\u0438\u043d\u043e"
    ],
    "name:ukr_x_preferred":[
        "\u0421\u0430\u0432\u043a\u0456\u043d\u043e"
    ],
    "name:und_x_variant":[
        "\u0421\u0430\u0432\u043a\u0438\u043d\u043e"
    ],
    "wof:name":"Savkino",
    "wof:placetype":"locality"
},
  "geometry": {"coordinates":[33.25611,57.81916999999999],"type":"Point"}
}