{
  "type": "Feature",
  "properties": {
    "gn:admin1_code":"42",
    "gn:asciiname":"Svatkovo",
    "gn:country_code":"RU",
    "gn:dem":56,
    "gn:feature_class":"P",
    "gn:feature_code":"PPL",
    "gn:name":"Svatkovo",
    "gn:population":0,
    "gn:timezone":"Europe/Moscow",
    "iso:country":"RU",
    "wof:name":"Svatkovo",
    "wof:placetype":"locality"
},
  "geometry": {"coordinates":[29.05187,59.05931999999999],"type":"Point"}
}