{
  "type": "Feature",
  "properties": {
    "gn:admin1_code":"10",
    "gn:asciiname":"Kunichev",
    "gn:country_code":"RU",
    "gn:dem":144,
    "gn:feature_class":"P",
    "gn:feature_code":"PPL",
    "gn:name":"Kunichev",
    "gn:population":0,
    "gn:timezone":"Europe/Moscow",
    "iso:country":"RU",
    "name:rus_x_preferred":[
        "\u041a\u0443\u043d\u0438\u0447\u0435\u0432"
    ],
    "name:und_x_variant":[
        "\u041a\u0443\u043d\u0438\u0447\u0435\u0432",
        "Kunicha"
    ],
    "wof:name":"Kunichev",
    "wof:placetype":"locality"
},
  "geometry": {"coordinates":[32.50765,52.34999000000001],"type":"Point"}
}