{
  "type": "Feature",
  "properties": {
    "gn:admin1_code":"75",
    "gn:asciiname":"Smolokurovka",
    "gn:country_code":"RU",
    "gn:dem":85,
    "gn:feature_class":"P",
    "gn:feature_code":"PPL",
    "gn:name":"Smolokurovka",
    "gn:population":0,
    "gn:timezone":"Asia/Tomsk",
    "iso:country":"RU",
    "name:eng_x_preferred":[
        "Smolokurovka"
    ],
    "name:nor_x_preferred":[
        "Smolokurovka"
    ],
    "name:rus_x_preferred":[
        "\u0421\u043c\u043e\u043b\u043e\u043a\u0443\u0440\u043e\u0432\u043a\u0430"
    ],
    "name:und_x_variant":[
        "\u0421\u043c\u043e\u043b\u043e\u043a\u0443\u0440\u043e\u0432\u043a\u0430",
        "Smolokurovka"
    ],
    "wof:name":"Smolokurovka",
    "wof:placetype":"locality"
},
  "geometry": {"coordinates":[84.50917,57.84806],"type":"Point"}
}