{
  "type": "Feature",
  "properties": {
    "gn:admin1_code":"85",
    "gn:asciiname":"Ogudalovo",
    "gn:country_code":"RU",
    "gn:dem":145,
    "gn:feature_class":"P",
    "gn:feature_code":"PPL",
    "gn:name":"Ogudalovo",
    "gn:population":0,
    "gn:timezone":"Europe/Moscow",
    "iso:country":"RU",
    "name:rus_x_preferred":[
        "\u041e\u0433\u0443\u0434\u0430\u043b\u043e\u0432\u043e"
    ],
    "name:und_x_variant":[
        "\u041e\u0433\u0443\u0434\u0430\u043b\u043e\u0432\u043e"
    ],
    "wof:name":"Ogudalovo",
    "wof:placetype":"locality"
},
  "geometry": {"coordinates":[44.245,60.85778000000001],"type":"Point"}
}