{
  "type": "Feature",
  "properties": {
    "gn:admin1_code":"33",
    "gn:asciiname":"Zaimka",
    "gn:country_code":"RU",
    "gn:dem":193,
    "gn:feature_class":"P",
    "gn:feature_code":"PPL",
    "gn:name":"Zaimka",
    "gn:population":0,
    "gn:timezone":"Europe/Kirov",
    "iso:country":"RU",
    "name:bak_x_preferred":[
        "\u0417\u0430\u0438\u043c\u043a\u0430"
    ],
    "name:che_x_preferred":[
        "\u0417\u0430\u0438\u043c\u043a\u0430"
    ],
    "name:hye_x_preferred":[
        "\u0536\u0561\u056b\u0574\u056f\u0561"
    ],
    "name:rus_x_preferred":[
        "\u0417\u0430\u0438\u043c\u043a\u0430"
    ],
    "wof:name":"Zaimka",
    "wof:placetype":"locality"
},
  "geometry": {"coordinates":[49.12985,59.21585],"type":"Point"}
}