{
  "type": "Feature",
  "properties": {
    "gn:admin1_code":"67",
    "gn:asciiname":"Tsementnyy",
    "gn:country_code":"RU",
    "gn:dem":110,
    "gn:feature_class":"P",
    "gn:feature_code":"PPL",
    "gn:name":"Tsementnyy",
    "gn:population":0,
    "gn:timezone":"Europe/Saratov",
    "iso:country":"RU",
    "name:eng_x_preferred":[
        "Tsementnyy"
    ],
    "name:rus_x_preferred":[
        "\u0412\u043e\u0441\u0442\u043e\u0447\u043d\u044b\u0439"
    ],
    "name:rus_x_variant":[
        "\u0426\u0435\u043c\u0435\u043d\u0442\u043d\u044b\u0439"
    ],
    "name:und_x_variant":[
        "Vostochnyy",
        "Trikhachev"
    ],
    "wof:name":"Tsementnyy",
    "wof:placetype":"locality"
},
  "geometry": {"coordinates":[49.2685,50.9407],"type":"Point"}
}