{
  "type": "Feature",
  "properties": {
    "gn:admin1_code":"17",
    "gn:admin2_code":"Charodinskiy Rayon",
    "gn:asciiname":"Moksob",
    "gn:country_code":"RU",
    "gn:dem":1870,
    "gn:feature_class":"P",
    "gn:feature_code":"PPL",
    "gn:name":"Moksob",
    "gn:population":0,
    "gn:timezone":"Europe/Moscow",
    "iso:country":"RU",
    "name:rus_x_preferred":[
        "\u041c\u043e\u043a\u0441\u043e\u0431"
    ],
    "wof:name":"Moksob",
    "wof:placetype":"locality"
},
  "geometry": {"coordinates":[46.6942,42.26859],"type":"Point"}
}