{
  "type": "Feature",
  "properties": {
    "gn:admin1_code":"28",
    "gn:asciiname":"Sambatuksa",
    "gn:country_code":"RU",
    "gn:dem":55,
    "gn:feature_class":"P",
    "gn:feature_code":"PPL",
    "gn:name":"Sambatuksa",
    "gn:population":0,
    "gn:timezone":"Europe/Moscow",
    "iso:country":"RU",
    "name:fin_x_preferred":[
        "Sammatus"
    ],
    "name:rus_x_preferred":[
        "\u0421\u0430\u043c\u0431\u0430\u0442\u0443\u043a\u0441\u0430"
    ],
    "wof:name":"Sambatuksa",
    "wof:placetype":"locality"
},
  "geometry": {"coordinates":[33.25375,60.93111999999999],"type":"Point"}
}