{
  "type": "Feature",
  "properties": {
    "gn:admin1_code":"33.0",
    "gn:asciiname":"Shuglyanur",
    "gn:country_code":"RU",
    "gn:dem":155,
    "gn:feature_class":"P",
    "gn:feature_code":"PPL",
    "gn:name":"Shuglyanur",
    "gn:population":0,
    "gn:timezone":"Europe/Kirov",
    "iso:country":"RU",
    "name:rus_x_preferred":[
        "\u0428\u0443\u0433\u043b\u044f\u043d\u0443\u0440"
    ],
    "name:und_x_variant":[
        "Kosaryata",
        "Shuglyanur",
        "\u0428\u0443\u0433\u043b\u044f\u043d\u0443\u0440"
    ],
    "wof:name":"Shuglyanur",
    "wof:placetype":"locality"
},
  "geometry": {"coordinates":[48.4849,57.1684],"type":"Point"}
}