{
  "type": "Feature",
  "properties": {
    "gn:admin1_code":"10",
    "gn:asciiname":"Varvarka",
    "gn:country_code":"RU",
    "gn:dem":199,
    "gn:feature_class":"P",
    "gn:feature_code":"PPL",
    "gn:name":"Varvarka",
    "gn:population":0,
    "gn:timezone":"Europe/Moscow",
    "iso:country":"RU",
    "name:rus_x_preferred":[
        "\u0412\u0430\u0432\u0430\u0440\u043a\u0430"
    ],
    "wof:name":"Varvarka",
    "wof:placetype":"locality"
},
  "geometry": {"coordinates":[34.7063,52.6066],"type":"Point"}
}