{
  "type": "Feature",
  "properties": {
    "gn:admin1_code":"7",
    "gn:asciiname":"Baranovka",
    "gn:country_code":"RU",
    "gn:dem":-23,
    "gn:feature_class":"P",
    "gn:feature_code":"PPL",
    "gn:name":"Baranovka",
    "gn:population":0,
    "gn:timezone":"Europe/Astrakhan",
    "iso:country":"RU",
    "name:ceb_x_preferred":[
        "Baranovka"
    ],
    "name:rus_x_preferred":[
        "\u0411\u0430\u0440\u0430\u043d\u043e\u0432\u043a\u0430"
    ],
    "name:swe_x_preferred":[
        "Baranovka"
    ],
    "wof:name":"Baranovka",
    "wof:placetype":"locality"
},
  "geometry": {"coordinates":[48.73058,46.37488],"type":"Point"}
}