{
  "type": "Feature",
  "properties": {
    "gn:admin1_code":"47",
    "gn:asciiname":"Manushkino",
    "gn:country_code":"RU",
    "gn:dem":166,
    "gn:feature_class":"P",
    "gn:feature_code":"PPL",
    "gn:name":"Manushkino",
    "gn:population":0,
    "gn:timezone":"Europe/Moscow",
    "iso:country":"RU",
    "name:rus_x_preferred":[
        "\u041c\u0430\u043d\u0443\u0448\u043a\u0438\u043d\u043e"
    ],
    "name:und_x_variant":[
        "Manushenki",
        "Manushkino",
        "\u041c\u0430\u043d\u0443\u0448\u043a\u0438\u043d\u043e"
    ],
    "wof:name":"Manushkino",
    "wof:placetype":"locality"
},
  "geometry": {"coordinates":[37.46121,55.11755],"type":"Point"}
}