{
  "type": "Feature",
  "properties": {
    "gn:admin1_code":"79",
    "gn:asciiname":"Shuy",
    "gn:country_code":"RU",
    "gn:dem":1197,
    "gn:feature_class":"P",
    "gn:feature_code":"PPL",
    "gn:name":"Shuy",
    "gn:population":0,
    "gn:timezone":"Asia/Krasnoyarsk",
    "iso:country":"RU",
    "name:eng_x_preferred":[
        "Shuy"
    ],
    "name:nor_x_preferred":[
        "Sjuj"
    ],
    "name:rus_x_preferred":[
        "\u0428\u0443\u0439"
    ],
    "name:und_x_variant":[
        "\u0428\u0443\u0439",
        "Shuy"
    ],
    "wof:name":"Shuy",
    "wof:placetype":"locality"
},
  "geometry": {"coordinates":[90.40000000000001,50.85],"type":"Point"}
}