{
  "type": "Feature",
  "properties": {
    "gn:admin1_code":"28",
    "gn:asciiname":"Pakhomova-Vara",
    "gn:cc2":"RU",
    "gn:country_code":"RU",
    "gn:dem":265,
    "gn:feature_class":"P",
    "gn:feature_code":"PPL",
    "gn:name":"Pakhomova-Vara",
    "gn:population":0,
    "gn:timezone":"Europe/Moscow",
    "iso:country":"RU",
    "name:fin_x_preferred":[
        "Paahkomienvaara"
    ],
    "name:rus_x_preferred":[
        "\u041f\u0430\u0445\u043e\u043c\u043e\u0432\u0430-\u0412\u0430\u0440\u0430"
    ],
    "name:und_x_variant":[
        "Pakhomovavaara",
        "Pakhomova-Vara"
    ],
    "wof:name":"Pakhomova-Vara",
    "wof:placetype":"locality"
},
  "geometry": {"coordinates":[30.15,64.83333],"type":"Point"}
}