{
  "type": "Feature",
  "properties": {
    "gn:admin1_code":"4",
    "gn:asciiname":"Dmitriyevskiy",
    "gn:country_code":"RU",
    "gn:dem":662,
    "gn:feature_class":"P",
    "gn:feature_code":"PPL",
    "gn:name":"Dmitriyevskiy",
    "gn:population":0,
    "gn:timezone":"Asia/Barnaul",
    "iso:country":"RU",
    "name:rus_x_preferred":[
        "\u0414\u043c\u0438\u0442\u0440\u0438\u0435\u0432\u0441\u043a\u0438\u0439"
    ],
    "name:und_x_variant":[
        "\u0414\u043c\u0438\u0442\u0440\u0438\u0435\u0432\u0441\u043a\u0438\u0439"
    ],
    "wof:name":"Dmitriyevskiy",
    "wof:placetype":"locality"
},
  "geometry": {"coordinates":[84.40000000000001,51.73333],"type":"Point"}
}