{
  "type": "Feature",
  "properties": {
    "gn:admin1_code":"88",
    "gn:asciiname":"Novo",
    "gn:country_code":"RU",
    "gn:dem":99,
    "gn:feature_class":"P",
    "gn:feature_code":"PPL",
    "gn:name":"Novo",
    "gn:population":0,
    "gn:timezone":"Europe/Moscow",
    "iso:country":"RU",
    "name:fra_x_preferred":[
        "Novo"
    ],
    "name:rus_x_preferred":[
        "\u041d\u043e\u0432\u043e"
    ],
    "name:und_x_variant":[
        "Novaya"
    ],
    "wof:name":"Novo",
    "wof:placetype":"locality"
},
  "geometry": {"coordinates":[39.36192,57.09653],"type":"Point"}
}