{
  "type": "Feature",
  "properties": {
    "gn:admin1_code":"69",
    "gn:asciiname":"Shchelkino",
    "gn:country_code":"RU",
    "gn:dem":205,
    "gn:feature_class":"P",
    "gn:feature_code":"PPL",
    "gn:name":"Shch\u00eblkino",
    "gn:population":0,
    "gn:timezone":"Europe/Moscow",
    "iso:country":"RU",
    "name:rus_x_preferred":[
        "\u0429\u0451\u043b\u043a\u0438\u043d\u043e"
    ],
    "name:und_x_variant":[
        "Shelkina",
        "Shch\u00eblkino",
        "\u0429\u0451\u043b\u043a\u0438\u043d\u043e"
    ],
    "wof:name":"Shchelkino",
    "wof:placetype":"locality"
},
  "geometry": {"coordinates":[33.41556,54.60018],"type":"Point"}
}