{
  "type": "Feature",
  "properties": {
    "gn:admin1_code":"41",
    "gn:asciiname":"Strokino",
    "gn:country_code":"RU",
    "gn:dem":211,
    "gn:feature_class":"P",
    "gn:feature_code":"PPL",
    "gn:name":"Strokino",
    "gn:population":0,
    "gn:timezone":"Europe/Moscow",
    "iso:country":"RU",
    "name:rus_x_preferred":[
        "\u0421\u0442\u0440\u043e\u043a\u0438\u043d\u043e"
    ],
    "name:und_x_variant":[
        "\u0421\u0442\u0440\u043e\u043a\u0438\u043d\u043e"
    ],
    "wof:name":"Strokino",
    "wof:placetype":"locality"
},
  "geometry": {"coordinates":[37.2645,51.3186],"type":"Point"}
}