{
  "type": "Feature",
  "properties": {
    "gn:admin1_code":"62",
    "gn:asciiname":"Yegorovka",
    "gn:country_code":"RU",
    "gn:dem":145,
    "gn:feature_class":"P",
    "gn:feature_code":"PPL",
    "gn:name":"Yegorovka",
    "gn:population":0,
    "gn:timezone":"Europe/Moscow",
    "iso:country":"RU",
    "name:rus_x_preferred":[
        "\u0415\u0433\u043e\u0440\u043e\u0432\u043a\u0430"
    ],
    "wof:name":"Yegorovka",
    "wof:placetype":"locality"
},
  "geometry": {"coordinates":[39.9337,54.12],"type":"Point"}
}