{
  "type": "Feature",
  "properties": {
    "gn:admin1_code":"45",
    "gn:asciiname":"Malaya Orsha",
    "gn:country_code":"RU",
    "gn:dem":116,
    "gn:feature_class":"P",
    "gn:feature_code":"PPL",
    "gn:name":"Malaya Orsha",
    "gn:population":0,
    "gn:timezone":"Europe/Moscow",
    "iso:country":"RU",
    "name:rus_x_preferred":[
        "\u041c\u0430\u043b\u0430\u044f \u041e\u0440\u0448\u0430"
    ],
    "name:und_x_variant":[
        "Maloye Ovechkino",
        "Malaya Orsha"
    ],
    "wof:name":"Malaya Orsha",
    "wof:placetype":"locality"
},
  "geometry": {"coordinates":[47.84042,56.90868],"type":"Point"}
}