{
  "type": "Feature",
  "properties": {
    "gn:admin1_code":"90",
    "gn:asciiname":"Krasnyy Lug",
    "gn:country_code":"RU",
    "gn:dem":177,
    "gn:feature_class":"P",
    "gn:feature_code":"PPL",
    "gn:name":"Krasnyy Lug",
    "gn:population":0,
    "gn:timezone":"Asia/Yekaterinburg",
    "iso:country":"RU",
    "name:eng_x_preferred":[
        "Krasnyy Lug"
    ],
    "name:nor_x_preferred":[
        "Krasnyj Lug"
    ],
    "name:rus_x_preferred":[
        "\u041a\u0440\u0430\u0441\u043d\u044b\u0439 \u041b\u0443\u0433"
    ],
    "name:und_x_variant":[
        "\u041a\u0440\u0430\u0441\u043d\u044b\u0439 \u041b\u0443\u0433"
    ],
    "wof:name":"Krasnyy Lug",
    "wof:placetype":"locality"
},
  "geometry": {"coordinates":[57.8405,57.1371],"type":"Point"}
}