{
  "type": "Feature",
  "properties": {
    "gn:admin1_code":"86",
    "gn:asciiname":"Volokonovka",
    "gn:country_code":"RU",
    "gn:dem":92,
    "gn:feature_class":"P",
    "gn:feature_code":"PPL",
    "gn:name":"Volokonovka",
    "gn:population":0,
    "gn:timezone":"Europe/Moscow",
    "iso:country":"RU",
    "name:eng_x_preferred":[
        "Volokonovka"
    ],
    "name:nor_x_preferred":[
        "Volokonovka"
    ],
    "name:rus_x_preferred":[
        "\u0412\u043e\u043b\u043e\u043a\u043e\u043d\u043e\u0432\u043a\u0430"
    ],
    "name:und_x_variant":[
        "Khutor Volokonsk",
        "Volokonsk"
    ],
    "wof:name":"Volokonovka",
    "wof:placetype":"locality"
},
  "geometry": {"coordinates":[39.38702,49.84329],"type":"Point"}
}