{
  "type": "Feature",
  "properties": {
    "gn:admin1_code":"88",
    "gn:asciiname":"Pletenevo",
    "gn:country_code":"RU",
    "gn:dem":159,
    "gn:feature_class":"P",
    "gn:feature_code":"PPL",
    "gn:name":"Pleten\u00ebvo",
    "gn:population":0,
    "gn:timezone":"Europe/Moscow",
    "iso:country":"RU",
    "name:rus_x_preferred":[
        "\u041f\u043b\u0435\u0442\u0435\u043d\u0451\u0432\u043e"
    ],
    "name:und_x_variant":[
        "Pletn\u00ebvo",
        "Pleten\u00ebvo",
        "\u041f\u043b\u0435\u0442\u0435\u043d\u0451\u0432\u043e"
    ],
    "wof:name":"Pletenevo",
    "wof:placetype":"locality"
},
  "geometry": {"coordinates":[40.72575,58.49039000000001],"type":"Point"}
}