{
  "type": "Feature",
  "properties": {
    "gn:admin1_code":"47",
    "gn:asciiname":"Pereshchapovo",
    "gn:country_code":"RU",
    "gn:dem":190,
    "gn:feature_class":"P",
    "gn:feature_code":"PPL",
    "gn:name":"Pereshchapovo",
    "gn:population":0,
    "gn:timezone":"Europe/Moscow",
    "iso:country":"RU",
    "name:rus_x_preferred":[
        "\u041f\u0435\u0440\u0435\u0449\u0430\u043f\u043e\u0432\u043e"
    ],
    "name:und_x_variant":[
        "\u041f\u0435\u0440\u0435\u0449\u0430\u043f\u043e\u0432\u043e"
    ],
    "wof:name":"Pereshchapovo",
    "wof:placetype":"locality"
},
  "geometry": {"coordinates":[35.88180999999999,55.63083],"type":"Point"}
}