{
  "type": "Feature",
  "properties": {
    "gn:admin1_code":"88",
    "gn:asciiname":"Azarkino",
    "gn:country_code":"RU",
    "gn:dem":114,
    "gn:feature_class":"P",
    "gn:feature_code":"PPL",
    "gn:name":"Azarkino",
    "gn:population":0,
    "gn:timezone":"Europe/Moscow",
    "iso:country":"RU",
    "name:rus_x_preferred":[
        "\u0410\u0437\u0430\u0440\u043a\u0438\u043d\u043e"
    ],
    "wof:name":"Azarkino",
    "wof:placetype":"locality"
},
  "geometry": {"coordinates":[38.4061,57.9875],"type":"Point"}
}