{
  "type": "Feature",
  "properties": {
    "gn:admin1_code":"22.0",
    "gn:asciiname":"Dogaut",
    "gn:cc2":"RU",
    "gn:country_code":"RU",
    "gn:dem":1107,
    "gn:feature_class":"P",
    "gn:feature_code":"PPL",
    "gn:name":"Dogaut",
    "gn:population":0,
    "gn:timezone":"Europe/Moscow",
    "iso:country":"RU",
    "name:rus_x_preferred":[
        "\u0414\u043e\u0433\u0430\u0443\u0442"
    ],
    "name:und_x_variant":[
        "Dagaut",
        "Dogaut"
    ],
    "wof:name":"Dogaut",
    "wof:placetype":"locality"
},
  "geometry": {"coordinates":[43.59972,43.19944],"type":"Point"}
}