{
  "type": "Feature",
  "properties": {
    "gn:admin1_code":"62",
    "gn:asciiname":"Novopol'ye",
    "gn:country_code":"RU",
    "gn:dem":129,
    "gn:feature_class":"P",
    "gn:feature_code":"PPL",
    "gn:name":"Novopol\u2019ye",
    "gn:population":0,
    "gn:timezone":"Europe/Moscow",
    "iso:country":"RU",
    "name:rus_x_preferred":[
        "\u041d\u043e\u0432\u043e\u043f\u043e\u043b\u044c\u0435"
    ],
    "name:und_x_variant":[
        "Novopol\u2019ye",
        "\u041d\u043e\u0432\u043e\u043f\u043e\u043b\u044c\u0435"
    ],
    "wof:name":"Novopol'ye",
    "wof:placetype":"locality"
},
  "geometry": {"coordinates":[41.25788,53.68012],"type":"Point"}
}