{
  "type": "Feature",
  "properties": {
    "gn:admin1_code":"51",
    "gn:asciiname":"Levashovo",
    "gn:country_code":"RU",
    "gn:dem":127,
    "gn:feature_class":"P",
    "gn:feature_code":"PPL",
    "gn:name":"Levashovo",
    "gn:population":0,
    "gn:timezone":"Europe/Moscow",
    "iso:country":"RU",
    "name:rus_x_preferred":[
        "\u041b\u0435\u0432\u0430\u0448\u043e\u0432\u043e"
    ],
    "name:und_x_variant":[
        "\u041b\u0435\u0432\u0430\u0448\u043e\u0432\u043e"
    ],
    "wof:name":"Levashovo",
    "wof:placetype":"locality"
},
  "geometry": {"coordinates":[46.3529,57.8998],"type":"Point"}
}