{
  "type": "Feature",
  "properties": {
    "gn:admin1_code":"52",
    "gn:asciiname":"Vel'ye Stany",
    "gn:country_code":"RU",
    "gn:dem":215,
    "gn:feature_class":"P",
    "gn:feature_code":"PPL",
    "gn:name":"Vel\u2019ye Stany",
    "gn:population":0,
    "gn:timezone":"Europe/Moscow",
    "iso:country":"RU",
    "name:eng_x_preferred":[
        "Vel'ye Stany"
    ],
    "name:nor_x_preferred":[
        "Velje-Stany"
    ],
    "name:rus_x_preferred":[
        "\u0412\u0435\u043b\u044c\u0435-\u0421\u0442\u0430\u043d\u044b"
    ],
    "name:rus_x_variant":[
        "\u0412\u0435\u043b\u044c\u0435 \u0421\u0442\u0430\u043d\u044b"
    ],
    "name:und_x_variant":[
        "Vel\u2019ye",
        "Vel\u2019ye Stany"
    ],
    "wof:name":"Vel'ye Stany",
    "wof:placetype":"locality"
},
  "geometry": {"coordinates":[32.9959,57.7017],"type":"Point"}
}