{
  "type": "Feature",
  "properties": {
    "gn:admin1_code":"45.0",
    "gn:asciiname":"Shorsola",
    "gn:country_code":"RU",
    "gn:dem":246,
    "gn:feature_class":"P",
    "gn:feature_code":"PPL",
    "gn:name":"Shorsola",
    "gn:population":0,
    "gn:timezone":"Europe/Moscow",
    "iso:country":"RU",
    "name:rus_x_preferred":[
        "\u0428\u043e\u0440\u0441\u043e\u043b\u0430"
    ],
    "wof:name":"Shorsola",
    "wof:placetype":"locality"
},
  "geometry": {"coordinates":[49.07389000000001,56.82333000000001],"type":"Point"}
}