{
  "type": "Feature",
  "properties": {
    "gn:admin1_code":"85.0",
    "gn:asciiname":"Dubnishnoye",
    "gn:country_code":"RU",
    "gn:dem":202,
    "gn:feature_class":"P",
    "gn:feature_code":"PPL",
    "gn:name":"Dubnishnoye",
    "gn:population":0,
    "gn:timezone":"Europe/Moscow",
    "iso:country":"RU",
    "name:rus_x_preferred":[
        "\u0414\u0443\u0431\u043d\u0438\u0448\u043d\u043e\u0435"
    ],
    "name:und_x_variant":[
        "Dubishnoye",
        "Dubnishnoye",
        "\u0414\u0443\u0431\u043d\u0438\u0448\u043d\u043e\u0435"
    ],
    "wof:name":"Dubnishnoye",
    "wof:placetype":"locality"
},
  "geometry": {"coordinates":[38.67955,58.8768],"type":"Point"}
}