{
  "type": "Feature",
  "properties": {
    "gn:admin1_code":"25",
    "gn:asciiname":"Yastrebovka",
    "gn:country_code":"RU",
    "gn:dem":214,
    "gn:feature_class":"P",
    "gn:feature_code":"PPL",
    "gn:name":"Yastrebovka",
    "gn:population":0,
    "gn:timezone":"Europe/Moscow",
    "iso:country":"RU",
    "name:eng_x_preferred":[
        "Yastrebovka"
    ],
    "name:nor_x_preferred":[
        "Jastrebovka"
    ],
    "name:rus_x_preferred":[
        "\u042f\u0441\u0442\u0440\u0435\u0431\u043e\u0432\u043a\u0430"
    ],
    "wof:name":"Yastrebovka",
    "wof:placetype":"locality"
},
  "geometry": {"coordinates":[36.40003,54.60603],"type":"Point"}
}