{
  "type": "Feature",
  "properties": {
    "gn:admin1_code":"8",
    "gn:asciiname":"Bulyakovo",
    "gn:country_code":"RU",
    "gn:dem":162,
    "gn:feature_class":"P",
    "gn:feature_code":"PPL",
    "gn:name":"Bulyakovo",
    "gn:population":0,
    "gn:timezone":"Asia/Yekaterinburg",
    "iso:country":"RU",
    "name:rus_x_preferred":[
        "\u0411\u0443\u043b\u044f\u043a\u043e\u0432\u043e"
    ],
    "wof:name":"Bulyakovo",
    "wof:placetype":"locality"
},
  "geometry": {"coordinates":[53.8774,54.8309],"type":"Point"}
}