{
  "type": "Feature",
  "properties": {
    "gn:admin1_code":"8",
    "gn:asciiname":"Avangard",
    "gn:country_code":"RU",
    "gn:dem":168,
    "gn:feature_class":"P",
    "gn:feature_code":"PPL",
    "gn:name":"Avangard",
    "gn:population":0,
    "gn:timezone":"Asia/Yekaterinburg",
    "iso:country":"RU",
    "name:deu_x_preferred":[
        "Avangard"
    ],
    "name:rus_x_preferred":[
        "\u0410\u0432\u0430\u043d\u0433\u0430\u0440\u0434"
    ],
    "name:tat_x_preferred":[
        "Avangard"
    ],
    "wof:name":"Avangard",
    "wof:placetype":"locality"
},
  "geometry": {"coordinates":[56.722,54.9083],"type":"Point"}
}