{
  "type": "Feature",
  "properties": {
    "gn:admin1_code":"4",
    "gn:asciiname":"Buranovo",
    "gn:country_code":"RU",
    "gn:dem":165,
    "gn:feature_class":"P",
    "gn:feature_code":"PPL",
    "gn:name":"Buranovo",
    "gn:population":0,
    "gn:timezone":"Asia/Barnaul",
    "iso:country":"RU",
    "name:bul_x_preferred":[
        "\u0411\u0443\u0440\u0430\u043d\u043e\u0432\u043e"
    ],
    "name:eng_x_preferred":[
        "Buranovo"
    ],
    "name:epo_x_preferred":[
        "Buranovo"
    ],
    "name:hye_x_preferred":[
        "\u0532\u0578\u0582\u0580\u0561\u0576\u0578\u057e\u0578"
    ],
    "name:nor_x_preferred":[
        "Buranovo"
    ],
    "name:rus_x_preferred":[
        "\u0411\u0443\u0440\u0430\u043d\u043e\u0432\u043e"
    ],
    "name:ukr_x_preferred":[
        "\u0411\u0443\u0440\u0430\u043d\u043e\u0432\u043e"
    ],
    "name:und_x_variant":[
        "Burakovskoye",
        "Burakova",
        "Buranovskoye",
        "\u0411\u0443\u0440\u0430\u043d\u043e\u0432\u043e",
        "Buranovo"
    ],
    "wof:name":"Buranovo",
    "wof:placetype":"locality"
},
  "geometry": {"coordinates":[82.93389999999999,52.0208],"type":"Point"}
}