{
  "type": "Feature",
  "properties": {
    "gn:admin1_code":"33",
    "gn:asciiname":"Zyablovo",
    "gn:country_code":"RU",
    "gn:dem":165,
    "gn:feature_class":"P",
    "gn:feature_code":"PPL",
    "gn:name":"Zyablovo",
    "gn:population":0,
    "gn:timezone":"Europe/Kirov",
    "iso:country":"RU",
    "name:eng_x_preferred":[
        "Zyablovo"
    ],
    "name:nor_x_preferred":[
        "Ziablovo"
    ],
    "name:rus_x_preferred":[
        "\u0417\u044f\u0431\u043b\u043e\u0432\u043e"
    ],
    "name:und_x_variant":[
        "Zyablovskiy",
        "Zyablovskaya"
    ],
    "wof:name":"Zyablovo",
    "wof:placetype":"locality"
},
  "geometry": {"coordinates":[52.91078,59.37838000000001],"type":"Point"}
}