{
  "type": "Feature",
  "properties": {
    "gn:admin1_code":"16",
    "gn:asciiname":"Turi-Vyla",
    "gn:country_code":"RU",
    "gn:dem":165,
    "gn:feature_class":"P",
    "gn:feature_code":"PPL",
    "gn:name":"Turi-Vyla",
    "gn:population":0,
    "gn:timezone":"Europe/Moscow",
    "iso:country":"RU",
    "name:rus_x_preferred":[
        "\u0422\u0443\u0440\u0438-\u0412\u044b\u043b\u0430"
    ],
    "wof:name":"Turi-Vyla",
    "wof:placetype":"locality"
},
  "geometry": {"coordinates":[46.5227,55.67341],"type":"Point"}
}