{
  "type": "Feature",
  "properties": {
    "gn:admin1_code":"60",
    "gn:asciiname":"Kriviny",
    "gn:country_code":"RU",
    "gn:dem":99,
    "gn:feature_class":"P",
    "gn:feature_code":"PPL",
    "gn:name":"Kriviny",
    "gn:population":0,
    "gn:timezone":"Europe/Moscow",
    "iso:country":"RU",
    "name:rus_x_preferred":[
        "\u041a\u0440\u0438\u0432\u0438\u043d\u044b"
    ],
    "name:und_x_variant":[
        "Krivino",
        "Kriviny"
    ],
    "wof:name":"Kriviny",
    "wof:placetype":"locality"
},
  "geometry": {"coordinates":[28.28717,56.70498000000001],"type":"Point"}
}