{
  "type": "Feature",
  "properties": {
    "gn:admin1_code":"63",
    "gn:asciiname":"Ebe-Basa",
    "gn:country_code":"RU",
    "gn:dem":95,
    "gn:feature_class":"P",
    "gn:feature_code":"PPL",
    "gn:name":"Ebe-Basa",
    "gn:population":0,
    "gn:timezone":"Asia/Yakutsk",
    "iso:country":"RU",
    "name:eng_x_preferred":[
        "Ebe-Basa"
    ],
    "name:nor_x_preferred":[
        "Ebe-Basa"
    ],
    "name:rus_x_preferred":[
        "\u042d\u0431\u0435-\u0411\u0430\u0441\u0430"
    ],
    "name:und_x_variant":[
        "\u042d\u0431\u0435-\u0411\u0430\u0441\u0430",
        "Ebe-Basa"
    ],
    "wof:name":"Ebe-Basa",
    "wof:placetype":"locality"
},
  "geometry": {"coordinates":[129.78437,62.96657],"type":"Point"}
}