{
  "type": "Feature",
  "properties": {
    "gn:admin1_code":"90",
    "gn:asciiname":"Khukhryata",
    "gn:country_code":"RU",
    "gn:dem":145,
    "gn:feature_class":"P",
    "gn:feature_code":"PPL",
    "gn:name":"Khukhryata",
    "gn:population":0,
    "gn:timezone":"Asia/Yekaterinburg",
    "iso:country":"RU",
    "name:rus_x_preferred":[
        "\u0425\u0443\u0445\u0440\u044f\u0442\u0430"
    ],
    "name:und_x_variant":[
        "\u0425\u0443\u0445\u0440\u044f\u0442\u0430"
    ],
    "wof:name":"Khukhryata",
    "wof:placetype":"locality"
},
  "geometry": {"coordinates":[55.8953,58.0745],"type":"Point"}
}