{
  "type": "Feature",
  "properties": {
    "gn:admin1_code":"6",
    "gn:asciiname":"Tundra",
    "gn:country_code":"RU",
    "gn:dem":90,
    "gn:feature_class":"P",
    "gn:feature_code":"PPL",
    "gn:name":"Tundra",
    "gn:population":0,
    "gn:timezone":"Europe/Moscow",
    "iso:country":"RU",
    "name:eng_x_preferred":[
        "Tundra"
    ],
    "name:nor_x_preferred":[
        "Tundra"
    ],
    "name:rus_x_preferred":[
        "\u0422\u0443\u043d\u0434\u0440\u0430"
    ],
    "wof:name":"Tundra",
    "wof:placetype":"locality"
},
  "geometry": {"coordinates":[40.5886,64.1541],"type":"Point"}
}