{
  "type": "Feature",
  "properties": {
    "gn:admin1_code":"34",
    "gn:asciiname":"Kanach",
    "gn:country_code":"RU",
    "gn:dem":98,
    "gn:feature_class":"P",
    "gn:feature_code":"PPL",
    "gn:name":"Kanach",
    "gn:population":0,
    "gn:timezone":"Europe/Moscow",
    "iso:country":"RU",
    "name:rus_x_preferred":[
        "\u041a\u0430\u043d\u0430\u0447"
    ],
    "name:und_x_variant":[
        "\u041a\u0430\u043d\u0430\u0447"
    ],
    "wof:name":"Kanach",
    "wof:placetype":"locality"
},
  "geometry": {"coordinates":[46.95,64.08333],"type":"Point"}
}