{
  "type": "Feature",
  "properties": {
    "gn:admin1_code":"33",
    "gn:asciiname":"Olenevo",
    "gn:country_code":"RU",
    "gn:dem":111,
    "gn:feature_class":"P",
    "gn:feature_code":"PPL",
    "gn:name":"Olenevo",
    "gn:population":0,
    "gn:timezone":"Europe/Kirov",
    "iso:country":"RU",
    "name:eng_x_preferred":[
        "Olenevo"
    ],
    "name:nor_x_preferred":[
        "Olenevo"
    ],
    "name:rus_x_preferred":[
        "\u041e\u043b\u0435\u043d\u0435\u0432\u043e"
    ],
    "name:und_x_variant":[
        "\u041e\u043b\u0435\u043d\u0435\u0432\u043e",
        "Olenevo"
    ],
    "wof:name":"Olenevo",
    "wof:placetype":"locality"
},
  "geometry": {"coordinates":[47.23214,57.15622],"type":"Point"}
}