{
  "type": "Feature",
  "properties": {
    "gn:admin1_code":"8",
    "gn:asciiname":"Novoshakhovo",
    "gn:country_code":"RU",
    "gn:dem":218,
    "gn:feature_class":"P",
    "gn:feature_code":"PPL",
    "gn:name":"Novoshakhovo",
    "gn:population":0,
    "gn:timezone":"Asia/Yekaterinburg",
    "iso:country":"RU",
    "name:bak_x_preferred":[
        "\u042f\u04a3\u044b \u0428\u0430\u0445"
    ],
    "name:che_x_preferred":[
        "\u041d\u043e\u0432\u043e\u0448\u0430\u0445\u043e\u0432\u043e"
    ],
    "name:eng_x_preferred":[
        "Novoshakhovo"
    ],
    "name:hye_x_preferred":[
        "\u0546\u0578\u057e\u0578\u0577\u0561\u056d\u0578\u057e\u0578"
    ],
    "name:kaz_x_preferred":[
        "\u0416\u0430\u04a3\u0430 \u0448\u0430\u0445"
    ],
    "name:kir_x_preferred":[
        "\u0416\u0430\u04a3\u044b \u0448\u0430\u0445"
    ],
    "name:nor_x_preferred":[
        "Novosjakhovo"
    ],
    "name:rus_x_preferred":[
        "\u041d\u043e\u0432\u043e\u0448\u0430\u0445\u043e\u0432\u043e"
    ],
    "name:tat_x_preferred":[
        "\u042f\u04a3\u0430 \u0428\u0430\u0445"
    ],
    "name:ukr_x_preferred":[
        "\u041d\u043e\u0432\u043e\u0448\u0430\u0445\u043e\u0432\u043e"
    ],
    "name:und_x_variant":[
        "Novoye Shakhovo"
    ],
    "wof:name":"Novoshakhovo",
    "wof:placetype":"locality"
},
  "geometry": {"coordinates":[53.83333,53.81667],"type":"Point"}
}