{
  "type": "Feature",
  "properties": {
    "gn:admin1_code":"8",
    "gn:asciiname":"Novoshakhovo",
    "gn:country_code":"RU",
    "gn:dem":218,
    "gn:feature_class":"P",
    "gn:feature_code":"PPL",
    "gn:name":"Novoshakhovo",
    "gn:population":0,
    "gn:timezone":"Asia/Yekaterinburg",
    "iso:country":"RU",
    "name:eng_x_preferred":[
        "Novoshakhovo"
    ],
    "name:nor_x_preferred":[
        "Novosjakhovo"
    ],
    "name:rus_x_preferred":[
        "\u041d\u043e\u0432\u043e\u0448\u0430\u0445\u043e\u0432\u043e"
    ],
    "name:und_x_variant":[
        "Novoye Shakhovo",
        "\u041d\u043e\u0432\u043e\u0448\u0430\u0445\u043e\u0432\u043e",
        "Novoshakhovo"
    ],
    "wof:name":"Novoshakhovo",
    "wof:placetype":"locality"
},
  "geometry": {"coordinates":[53.83333,53.81667],"type":"Point"}
}