{
  "type": "Feature",
  "properties": {
    "gn:admin1_code":"77",
    "gn:asciiname":"Kletino",
    "gn:country_code":"RU",
    "gn:dem":230,
    "gn:feature_class":"P",
    "gn:feature_code":"PPL",
    "gn:name":"Kletino",
    "gn:population":150,
    "gn:timezone":"Europe/Moscow",
    "iso:country":"RU",
    "name:rus_x_preferred":[
        "\u041a\u043b\u0435\u0442\u0438\u043d\u043e"
    ],
    "wof:name":"Kletino",
    "wof:placetype":"locality",
    "wof:population":150
},
  "geometry": {"coordinates":[33.44257,57.10337],"type":"Point"}
}