{
  "type": "Feature",
  "properties": {
    "gn:admin1_code":"80.0",
    "gn:asciiname":"Gumenki",
    "gn:country_code":"RU",
    "gn:dem":259,
    "gn:feature_class":"P",
    "gn:feature_code":"PPL",
    "gn:name":"Gumenki",
    "gn:population":0,
    "gn:timezone":"Europe/Samara",
    "iso:country":"RU",
    "name:rus_x_preferred":[
        "\u0413\u0443\u043c\u0435\u043d\u043a\u0438"
    ],
    "wof:name":"Gumenki",
    "wof:placetype":"locality"
},
  "geometry": {"coordinates":[53.2997,58.195],"type":"Point"}
}