{
  "type": "Feature",
  "properties": {
    "gn:admin1_code":"83",
    "gn:asciiname":"Chetvert'",
    "gn:country_code":"RU",
    "gn:dem":200,
    "gn:feature_class":"P",
    "gn:feature_code":"PPL",
    "gn:name":"Chetv\u00ebrt\u2019",
    "gn:population":0,
    "gn:timezone":"Europe/Moscow",
    "iso:country":"RU",
    "name:rus_x_preferred":[
        "\u0427\u0435\u0442\u0432\u0451\u0440\u0442\u044c"
    ],
    "name:und_x_variant":[
        "Chetv\u00ebrt\u2019"
    ],
    "wof:name":"Chetvert'",
    "wof:placetype":"locality"
},
  "geometry": {"coordinates":[39.17077000000001,56.47745],"type":"Point"}
}