{
  "type": "Feature",
  "properties": {
    "gn:admin1_code":"69",
    "gn:asciiname":"Sleptsovo",
    "gn:country_code":"RU",
    "gn:dem":219,
    "gn:feature_class":"P",
    "gn:feature_code":"PPL",
    "gn:name":"Sleptsovo",
    "gn:population":0,
    "gn:timezone":"Europe/Moscow",
    "iso:country":"RU",
    "name:rus_x_preferred":[
        "\u0421\u043b\u0435\u043f\u0446\u043e\u0432\u043e"
    ],
    "name:und_x_variant":[
        "\u0421\u043b\u0435\u043f\u0446\u043e\u0432\u043e"
    ],
    "wof:name":"Sleptsovo",
    "wof:placetype":"locality"
},
  "geometry": {"coordinates":[33.84896,55.6691],"type":"Point"}
}