{
  "type": "Feature",
  "properties": {
    "gn:admin1_code":"45",
    "gn:asciiname":"Salmandayevo",
    "gn:country_code":"RU",
    "gn:dem":111,
    "gn:feature_class":"P",
    "gn:feature_code":"PPL",
    "gn:name":"Salmandayevo",
    "gn:population":0,
    "gn:timezone":"Europe/Moscow",
    "iso:country":"RU",
    "name:rus_x_preferred":[
        "\u0421\u0430\u043b\u043c\u0430\u043d\u0434\u0430\u0435\u0432\u043e"
    ],
    "name:und_x_variant":[
        "Salamandayevo",
        "Salmandayevo",
        "\u0421\u0430\u043b\u043c\u0430\u043d\u0434\u0430\u0435\u0432\u043e"
    ],
    "wof:name":"Salmandayevo",
    "wof:placetype":"locality"
},
  "geometry": {"coordinates":[46.28464,56.19701],"type":"Point"}
}