{
  "type": "Feature",
  "properties": {
    "gn:admin1_code":"51.0",
    "gn:asciiname":"Imeni M. I. Kalinina",
    "gn:country_code":"RU",
    "gn:dem":69,
    "gn:feature_class":"P",
    "gn:feature_code":"PPL",
    "gn:name":"Imeni M. I. Kalinina",
    "gn:population":0,
    "gn:timezone":"Europe/Moscow",
    "iso:country":"RU",
    "name:bel_x_preferred":[
        "\u0406\u043c\u044f \u041c. \u0406. \u041a\u0430\u043b\u0456\u043d\u0456\u043d\u0430"
    ],
    "name:est_x_preferred":[
        "Imeni M. I. Kalinina"
    ],
    "name:rus_x_preferred":[
        "\u0420\u0430\u0431\u043e\u0447\u0438\u0439 \u043f\u043e\u0441\u0451\u043b\u043e\u043a \u0438\u043c\u0435\u043d\u0438 \u041c. \u0418. \u041a\u0430\u043b\u0438\u043d\u0438\u043d\u0430"
    ],
    "name:und_x_variant":[
        "Pos\u00eblok Imeni Kalinina",
        "Imeni Kalinina"
    ],
    "wof:name":"Imeni M. I. Kalinina",
    "wof:placetype":"locality"
},
  "geometry": {"coordinates":[44.33098,56.17926],"type":"Point"}
}