{
  "type": "Feature",
  "properties": {
    "gn:admin1_code":"45.0",
    "gn:asciiname":"Aryp-Murza",
    "gn:country_code":"RU",
    "gn:dem":135,
    "gn:feature_class":"P",
    "gn:feature_code":"PPL",
    "gn:name":"Aryp-Murza",
    "gn:population":0,
    "gn:timezone":"Europe/Moscow",
    "iso:country":"RU",
    "name:nor_x_preferred":[
        "Aryn"
    ],
    "name:rus_x_preferred":[
        "\u0410\u0440\u044b\u043f-\u041c\u0443\u0440\u0437\u0430"
    ],
    "name:und_x_variant":[
        "Aryn",
        "Aryp-Murza"
    ],
    "wof:name":"Aryp-Murza",
    "wof:placetype":"locality"
},
  "geometry": {"coordinates":[49.61028,56.945],"type":"Point"}
}