{
  "type": "Feature",
  "properties": {
    "gn:admin1_code":"69",
    "gn:asciiname":"Gridneva",
    "gn:country_code":"RU",
    "gn:dem":205,
    "gn:feature_class":"P",
    "gn:feature_code":"PPL",
    "gn:name":"Gridneva",
    "gn:population":0,
    "gn:timezone":"Europe/Moscow",
    "iso:country":"RU",
    "name:rus_x_preferred":[
        "\u0413\u0440\u0438\u0434\u043d\u0435\u0432\u0430"
    ],
    "name:und_x_variant":[
        "\u0413\u0440\u0438\u0434\u043d\u0435\u0432\u0430"
    ],
    "wof:name":"Gridneva",
    "wof:placetype":"locality"
},
  "geometry": {"coordinates":[33.46777,54.7523],"type":"Point"}
}