{
  "type": "Feature",
  "properties": {
    "gn:admin1_code":"6",
    "gn:asciiname":"Kuchema",
    "gn:country_code":"RU",
    "gn:dem":67,
    "gn:feature_class":"P",
    "gn:feature_code":"PPL",
    "gn:name":"Kuchema",
    "gn:population":0,
    "gn:timezone":"Europe/Moscow",
    "iso:country":"RU",
    "name:eng_x_preferred":[
        "Kuchema"
    ],
    "name:nor_x_preferred":[
        "Kutsjema"
    ],
    "name:rus_x_preferred":[
        "\u041a\u0443\u0447\u0435\u043c\u0430"
    ],
    "name:und_x_variant":[
        "Stanovishche Sundukovo",
        "Staroye Sundukovo",
        "Stanovishche Kuchema"
    ],
    "wof:name":"Kuchema",
    "wof:placetype":"locality"
},
  "geometry": {"coordinates":[42.5414,65.6069],"type":"Point"}
}