{
  "type": "Feature",
  "properties": {
    "gn:admin1_code":"17",
    "gn:asciiname":"Kug",
    "gn:country_code":"RU",
    "gn:dem":1195,
    "gn:feature_class":"P",
    "gn:feature_code":"PPL",
    "gn:name":"Kug",
    "gn:population":0,
    "gn:timezone":"Europe/Moscow",
    "iso:country":"RU",
    "name:fas_x_preferred":[
        "\u06a9\u0648\u06af"
    ],
    "name:rus_x_preferred":[
        "\u041a\u0443\u0433"
    ],
    "wof:name":"Kug",
    "wof:placetype":"locality"
},
  "geometry": {"coordinates":[47.96451,41.7711],"type":"Point"}
}