{
  "type": "Feature",
  "properties": {
    "gn:admin1_code":"85",
    "gn:asciiname":"Kichigino",
    "gn:country_code":"RU",
    "gn:dem":174,
    "gn:feature_class":"P",
    "gn:feature_code":"PPL",
    "gn:name":"Kichigino",
    "gn:population":0,
    "gn:timezone":"Europe/Moscow",
    "iso:country":"RU",
    "name:rus_x_preferred":[
        "\u041a\u0438\u0447\u0438\u0433\u0438\u043d\u043e"
    ],
    "wof:name":"Kichigino",
    "wof:placetype":"locality"
},
  "geometry": {"coordinates":[40.1115,59.07698000000001],"type":"Point"}
}