{
  "type": "Feature",
  "properties": {
    "gn:admin1_code":"47",
    "gn:asciiname":"Bol'shoye Orekhovo",
    "gn:country_code":"RU",
    "gn:dem":165,
    "gn:feature_class":"P",
    "gn:feature_code":"PPL",
    "gn:name":"Bol\u2019shoye Orekhovo",
    "gn:population":0,
    "gn:timezone":"Europe/Moscow",
    "iso:country":"RU",
    "name:rus_x_preferred":[
        "\u0411\u043e\u043b\u0448\u043e\u0435 \u041e\u0440\u0435\u0445\u043e\u0432\u043e"
    ],
    "name:und_x_variant":[
        "Bol\u2019shoye Orekhovo"
    ],
    "wof:name":"Bol'shoye Orekhovo",
    "wof:placetype":"locality"
},
  "geometry": {"coordinates":[38.4393,54.528],"type":"Point"}
}