{
  "type": "Feature",
  "properties": {
    "gn:admin1_code":"23",
    "gn:asciiname":"Zelenoles'ye",
    "gn:country_code":"RU",
    "gn:dem":23,
    "gn:feature_class":"P",
    "gn:feature_code":"PPL",
    "gn:name":"Zelenoles\u2019ye",
    "gn:population":0,
    "gn:timezone":"Europe/Kaliningrad",
    "iso:country":"RU",
    "name:und_x_variant":[
        "Griklyaugken",
        "Zelenoles\u2019ye"
    ],
    "wof:name":"Zelenoles'ye",
    "wof:placetype":"locality"
},
  "geometry": {"coordinates":[22.44111,54.99306],"type":"Point"}
}