{
  "type": "Feature",
  "properties": {
    "gn:admin1_code":"20",
    "gn:asciiname":"Angara",
    "gn:country_code":"RU",
    "gn:dem":432,
    "gn:feature_class":"P",
    "gn:feature_code":"PPL",
    "gn:name":"Angara",
    "gn:population":0,
    "gn:timezone":"Asia/Irkutsk",
    "iso:country":"RU",
    "name:ara_x_preferred":[
        "\u0646\u0647\u0631 \u0623\u0646\u063a\u0627\u0631\u0627"
    ],
    "name:aze_x_preferred":[
        "Anqara"
    ],
    "name:bel_x_preferred":[
        "\u0420\u0430\u043a\u0430 \u0410\u043d\u0433\u0430\u0440\u0430"
    ],
    "name:ben_x_preferred":[
        "\u0986\u0999\u09cd\u0997\u09be\u09b0\u09be \u09a8\u09a6\u09c0"
    ],
    "name:bul_x_preferred":[
        "\u0410\u043d\u0433\u0430\u0440\u0430"
    ],
    "name:cat_x_preferred":[
        "Angar\u00e0"
    ],
    "name:chv_x_preferred":[
        "\u0410\u043d\u0433\u0430\u0440\u0430"
    ],
    "name:cym_x_preferred":[
        "Afon Angara"
    ],
    "name:eng_x_preferred":[
        "Angara River"
    ],
    "name:fas_x_preferred":[
        "\u0631\u0648\u062f \u0622\u0646\u06af\u0627\u0631\u0627"
    ],
    "name:glg_x_preferred":[
        "R\u00edo Angara"
    ],
    "name:heb_x_preferred":[
        "\u05d0\u05e0\u05d2\u05e8\u05d4"
    ],
    "name:hin_x_preferred":[
        "\u0905\u0902\u0917\u093e\u0930\u093e \u0928\u0926\u0940"
    ],
    "name:hye_x_preferred":[
        "\u0531\u0576\u0563\u0561\u0580\u0561"
    ],
    "name:jav_x_preferred":[
        "Kali Angara"
    ],
    "name:jpn_x_preferred":[
        "\u30a2\u30f3\u30ac\u30e9\u5ddd"
    ],
    "name:kat_x_preferred":[
        "\u10d0\u10dc\u10d2\u10d0\u10e0\u10d0"
    ],
    "name:kor_x_preferred":[
        "\uc548\uac00\ub77c \uac15"
    ],
    "name:mkd_x_preferred":[
        "\u0410\u043d\u0433\u0430\u0440\u0430"
    ],
    "name:nor_x_preferred":[
        "Angara"
    ],
    "name:pnb_x_preferred":[
        "\u062f\u0631\u06cc\u0627\u06d3 \u0627\u0646\u06af\u0627\u0631\u0627"
    ],
    "name:por_x_preferred":[
        "Rio Angara"
    ],
    "name:rus_x_preferred":[
        "\u0410\u043d\u0433\u0430\u0440\u0430"
    ],
    "name:spa_x_preferred":[
        "R\u00edo Angar\u00e1"
    ],
    "name:srp_x_preferred":[
        "\u0410\u043d\u0433\u0430\u0440\u0430"
    ],
    "name:tur_x_preferred":[
        "Angara Nehri"
    ],
    "name:ukr_x_preferred":[
        "\u0410\u043d\u0433\u0430\u0440\u0430"
    ],
    "name:vie_x_preferred":[
        "S\u00f4ng Angara"
    ],
    "name:zho_x_preferred":[
        "\u5b89\u52a0\u62c9\u6cb3"
    ],
    "wof:name":"Angara",
    "wof:placetype":"locality"
},
  "geometry": {"coordinates":[104.22917,52.38722],"type":"Point"}
}