{
  "type": "Feature",
  "properties": {
    "gn:admin1_code":"60",
    "gn:asciiname":"Andrekhovshchina",
    "gn:country_code":"RU",
    "gn:dem":62,
    "gn:feature_class":"P",
    "gn:feature_code":"PPL",
    "gn:name":"Andrekhovshchina",
    "gn:population":0,
    "gn:timezone":"Europe/Moscow",
    "iso:country":"RU",
    "name:rus_x_preferred":[
        "\u0410\u043d\u0434\u0440\u0435\u0445\u043e\u0432\u0449\u0438\u043d\u0430"
    ],
    "name:und_x_variant":[
        "\u0410\u043d\u0434\u0440\u0435\u0445\u043e\u0432\u0449\u0438\u043d\u0430"
    ],
    "wof:name":"Andrekhovshchina",
    "wof:placetype":"locality"
},
  "geometry": {"coordinates":[28.2857,58.0449],"type":"Point"}
}