{
  "type": "Feature",
  "properties": {
    "gn:admin1_code":"52",
    "gn:asciiname":"Shedomitsy",
    "gn:country_code":"RU",
    "gn:dem":174,
    "gn:feature_class":"P",
    "gn:feature_code":"PPL",
    "gn:name":"Shedomitsy",
    "gn:population":0,
    "gn:timezone":"Europe/Moscow",
    "iso:country":"RU",
    "name:eng_x_preferred":[
        "Shedomitsy"
    ],
    "name:nor_x_preferred":[
        "Sjedomitsy"
    ],
    "name:rus_x_preferred":[
        "\u0428\u0435\u0434\u043e\u043c\u0438\u0446\u044b"
    ],
    "name:und_x_variant":[
        "Shedomitsa",
        "Shedomits",
        "Shadomichi"
    ],
    "wof:name":"Shedomitsy",
    "wof:placetype":"locality"
},
  "geometry": {"coordinates":[34.31462,58.51027],"type":"Point"}
}