{
  "type": "Feature",
  "properties": {
    "gn:admin1_code":"37",
    "gn:asciiname":"Verkhneye Lyadovo",
    "gn:country_code":"RU",
    "gn:dem":164,
    "gn:feature_class":"P",
    "gn:feature_code":"PPL",
    "gn:name":"Verkhneye Lyadovo",
    "gn:population":0,
    "gn:timezone":"Europe/Moscow",
    "iso:country":"RU",
    "name:rus_x_preferred":[
        "\u0412\u0435\u0440\u0445\u043d\u0435\u0435 \u041b\u044f\u0434\u043e\u0432\u043e"
    ],
    "wof:name":"Verkhneye Lyadovo",
    "wof:placetype":"locality"
},
  "geometry": {"coordinates":[46.71957,59.32719],"type":"Point"}
}