{
  "type": "Feature",
  "properties": {
    "gn:admin1_code":"57.0",
    "gn:asciiname":"Akmatovka",
    "gn:country_code":"RU",
    "gn:dem":204,
    "gn:feature_class":"P",
    "gn:feature_code":"PPL",
    "gn:name":"Akmatovka",
    "gn:population":0,
    "gn:timezone":"Europe/Moscow",
    "iso:country":"RU",
    "name:nor_x_preferred":[
        "Akmatovka"
    ],
    "name:rus_x_preferred":[
        "\u0410\u043a\u043c\u0430\u0442\u043e\u0432\u043a\u0430"
    ],
    "wof:name":"Akmatovka",
    "wof:placetype":"locality"
},
  "geometry": {"coordinates":[46.53333,52.85],"type":"Point"}
}