{
  "type": "Feature",
  "properties": {
    "gn:admin1_code":"13.0",
    "gn:asciiname":"Neplyuyevskiy",
    "gn:country_code":"RU",
    "gn:dem":310,
    "gn:feature_class":"P",
    "gn:feature_code":"PPL",
    "gn:name":"Neplyuyevskiy",
    "gn:population":0,
    "gn:timezone":"Asia/Yekaterinburg",
    "iso:country":"RU",
    "name:rus_x_preferred":[
        "\u041d\u0435\u043f\u043b\u044e\u0435\u0432\u0441\u043a\u0438\u0439"
    ],
    "wof:name":"Neplyuyevskiy",
    "wof:placetype":"locality"
},
  "geometry": {"coordinates":[60.60100000000001,52.872],"type":"Point"}
}