{
  "type": "Feature",
  "properties": {
    "gn:admin1_code":"52",
    "gn:asciiname":"Myshlyach'ye",
    "gn:country_code":"RU",
    "gn:dem":182,
    "gn:feature_class":"P",
    "gn:feature_code":"PPL",
    "gn:name":"Myshlyach\u2019ye",
    "gn:population":0,
    "gn:timezone":"Europe/Moscow",
    "iso:country":"RU",
    "name:rus_x_preferred":[
        "\u041c\u044b\u0448\u043b\u044f\u0447\u044c\u0435"
    ],
    "name:und_x_variant":[
        "Myshlyach\u2019ye"
    ],
    "wof:name":"Myshlyach'ye",
    "wof:placetype":"locality"
},
  "geometry": {"coordinates":[34.45075,58.4424],"type":"Point"}
}