{
  "type": "Feature",
  "properties": {
    "gn:admin1_code":"28",
    "gn:asciiname":"Vozritsy",
    "gn:country_code":"RU",
    "gn:dem":29,
    "gn:feature_class":"P",
    "gn:feature_code":"PPL",
    "gn:name":"Vozritsy",
    "gn:population":0,
    "gn:timezone":"Europe/Moscow",
    "iso:country":"RU",
    "name:eng_x_preferred":[
        "Vozritsy"
    ],
    "name:nor_x_preferred":[
        "Vozritsy"
    ],
    "name:rus_x_preferred":[
        "\u0412\u043e\u0437\u0440\u0438\u0446\u044b"
    ],
    "wof:name":"Vozritsy",
    "wof:placetype":"locality"
},
  "geometry": {"coordinates":[35.38889,62.67534000000001],"type":"Point"}
}