{
  "type": "Feature",
  "properties": {
    "gn:admin1_code":"71",
    "gn:asciiname":"Yemel'yashevka",
    "gn:country_code":"RU",
    "gn:dem":78,
    "gn:feature_class":"P",
    "gn:feature_code":"PPL",
    "gn:name":"Yemel\u2019yashevka",
    "gn:population":0,
    "gn:timezone":"Asia/Yekaterinburg",
    "iso:country":"RU",
    "name:eng_x_preferred":[
        "Yemel'yashevka"
    ],
    "name:nor_x_preferred":[
        "Jemeljasjevka"
    ],
    "name:rus_x_preferred":[
        "\u0415\u043c\u0435\u043b\u044c\u044f\u0448\u0435\u0432\u043a\u0430"
    ],
    "name:und_x_variant":[
        "Yemel\u2019yashevskiy",
        "\u0415\u043c\u0435\u043b\u044c\u044f\u0448\u0435\u0432\u043a\u0430",
        "Yemel\u2019yashevka"
    ],
    "wof:name":"Yemel'yashevka",
    "wof:placetype":"locality"
},
  "geometry": {"coordinates":[64.27648000000001,58.35919000000001],"type":"Point"}
}