{
  "type": "Feature",
  "properties": {
    "gn:admin1_code":"25",
    "gn:asciiname":"Likhovatka",
    "gn:country_code":"RU",
    "gn:dem":199,
    "gn:feature_class":"P",
    "gn:feature_code":"PPL",
    "gn:name":"Likhovatka",
    "gn:population":0,
    "gn:timezone":"Europe/Moscow",
    "iso:country":"RU",
    "name:rus_x_preferred":[
        "\u041b\u0438\u0445\u043e\u0432\u0430\u0442\u043a\u0430"
    ],
    "wof:name":"Likhovatka",
    "wof:placetype":"locality"
},
  "geometry": {"coordinates":[34.72458,53.51056],"type":"Point"}
}