{
  "type": "Feature",
  "properties": {
    "gn:admin1_code":"23",
    "gn:asciiname":"Denisovo",
    "gn:country_code":"RU",
    "gn:dem":14,
    "gn:feature_class":"P",
    "gn:feature_code":"PPL",
    "gn:name":"Denisovo",
    "gn:population":0,
    "gn:timezone":"Europe/Kaliningrad",
    "iso:country":"RU",
    "name:rus_x_preferred":[
        "\u0414\u0435\u043d\u0438\u0441\u043e\u0432\u043e"
    ],
    "name:und_x_variant":[
        "\u0414\u0435\u043d\u0438\u0441\u043e\u0432\u043e"
    ],
    "wof:name":"Denisovo",
    "wof:placetype":"locality"
},
  "geometry": {"coordinates":[21.19583,54.6075],"type":"Point"}
}