{
  "type": "Feature",
  "properties": {
    "gn:admin1_code":"59",
    "gn:asciiname":"Uritskoye",
    "gn:cc2":"RU",
    "gn:country_code":"RU",
    "gn:dem":102,
    "gn:feature_class":"P",
    "gn:feature_code":"PPL",
    "gn:name":"Uritskoye",
    "gn:population":0,
    "gn:timezone":"Asia/Vladivostok",
    "iso:country":"RU",
    "name:und_x_variant":[
        "Uritskiy",
        "Uritskoye"
    ],
    "wof:name":"Uritskoye",
    "wof:placetype":"locality"
},
  "geometry": {"coordinates":[133.76667,45.51667],"type":"Point"}
}