{
  "type": "Feature",
  "properties": {
    "gn:admin1_code":"69.0",
    "gn:asciiname":"Byvalki",
    "gn:country_code":"RU",
    "gn:dem":218,
    "gn:feature_class":"P",
    "gn:feature_code":"PPL",
    "gn:name":"Byvalki",
    "gn:population":0,
    "gn:timezone":"Europe/Moscow",
    "iso:country":"RU",
    "name:eng_x_preferred":[
        "Byvalki"
    ],
    "name:nor_x_preferred":[
        "Byvalki"
    ],
    "name:rus_x_preferred":[
        "\u0411\u044b\u0432\u0430\u043b\u043a\u0438"
    ],
    "name:und_x_variant":[
        "Buvalki",
        "Byralki",
        "\u0411\u044b\u0432\u0430\u043b\u043a\u0438",
        "Byvalki"
    ],
    "wof:name":"Byvalki",
    "wof:placetype":"locality"
},
  "geometry": {"coordinates":[33.60129000000001,54.42325],"type":"Point"}
}