{
  "type": "Feature",
  "properties": {
    "gn:admin1_code":"43",
    "gn:asciiname":"Zhiloye",
    "gn:country_code":"RU",
    "gn:dem":239,
    "gn:feature_class":"P",
    "gn:feature_code":"PPL",
    "gn:name":"Zhiloye",
    "gn:population":0,
    "gn:timezone":"Europe/Moscow",
    "iso:country":"RU",
    "name:rus_x_preferred":[
        "\u0416\u0438\u043b\u043e\u0435"
    ],
    "name:und_x_variant":[
        "Zhilaya",
        "Zhiloye",
        "\u0416\u0438\u043b\u043e\u0435"
    ],
    "wof:name":"Zhiloye",
    "wof:placetype":"locality"
},
  "geometry": {"coordinates":[38.10944,52.7936],"type":"Point"}
}