{
  "type": "Feature",
  "properties": {
    "gn:admin1_code":"21.0",
    "gn:asciiname":"Molokovka",
    "gn:country_code":"RU",
    "gn:dem":122,
    "gn:feature_class":"P",
    "gn:feature_code":"PPL",
    "gn:name":"Molokovka",
    "gn:population":0,
    "gn:timezone":"Europe/Moscow",
    "iso:country":"RU",
    "name:rus_x_preferred":[
        "\u041c\u043e\u043b\u043e\u043a\u043e\u0432\u043a\u0430"
    ],
    "name:und_x_variant":[
        "\u041c\u043e\u043b\u043e\u043a\u043e\u0432\u043a\u0430"
    ],
    "wof:name":"Molokovka",
    "wof:placetype":"locality"
},
  "geometry": {"coordinates":[42.53002,57.38458000000001],"type":"Point"}
}