{
  "type": "Feature",
  "properties": {
    "gn:admin1_code":"85",
    "gn:asciiname":"Terino",
    "gn:country_code":"RU",
    "gn:dem":174,
    "gn:feature_class":"P",
    "gn:feature_code":"PPL",
    "gn:name":"Terino",
    "gn:population":0,
    "gn:timezone":"Europe/Moscow",
    "iso:country":"RU",
    "name:rus_x_preferred":[
        "\u0422\u0435\u0440\u0438\u043d\u043e"
    ],
    "name:und_x_variant":[
        "\u0422\u0435\u0440\u0438\u043d\u043e"
    ],
    "wof:name":"Terino",
    "wof:placetype":"locality"
},
  "geometry": {"coordinates":[38.01178,59.45978],"type":"Point"}
}