{
  "type": "Feature",
  "properties": {
    "gn:admin1_code":"42",
    "gn:asciiname":"Bol'shaya Yashchera",
    "gn:country_code":"RU",
    "gn:dem":95,
    "gn:feature_class":"P",
    "gn:feature_code":"PPL",
    "gn:name":"Bol\u2019shaya Yashchera",
    "gn:population":0,
    "gn:timezone":"Europe/Moscow",
    "iso:country":"RU",
    "name:eng_x_preferred":[
        "Yashchera"
    ],
    "name:nor_x_preferred":[
        "Jasjtsjera"
    ],
    "name:rus_x_preferred":[
        "\u042f\u0449\u0435\u0440\u0430"
    ],
    "name:und_x_variant":[
        "Bol\u2019shaya Yashchera"
    ],
    "wof:name":"Bol'shaya Yashchera",
    "wof:placetype":"locality"
},
  "geometry": {"coordinates":[29.9143,59.1553],"type":"Point"}
}