{
  "type": "Feature",
  "properties": {
    "gn:admin1_code":"62",
    "gn:asciiname":"Shabayevo",
    "gn:country_code":"RU",
    "gn:dem":114,
    "gn:feature_class":"P",
    "gn:feature_code":"PPL",
    "gn:name":"Shabayevo",
    "gn:population":0,
    "gn:timezone":"Europe/Moscow",
    "iso:country":"RU",
    "name:rus_x_preferred":[
        "\u0428\u0430\u0431\u0430\u0435\u0432\u043e"
    ],
    "name:und_x_variant":[
        "\u0428\u0430\u0431\u0430\u0435\u0432\u043e"
    ],
    "wof:name":"Shabayevo",
    "wof:placetype":"locality"
},
  "geometry": {"coordinates":[40.20105,55.14138000000001],"type":"Point"}
}