{
  "type": "Feature",
  "properties": {
    "gn:admin1_code":"90",
    "gn:asciiname":"Zolotyata",
    "gn:country_code":"RU",
    "gn:dem":123,
    "gn:feature_class":"P",
    "gn:feature_code":"PPL",
    "gn:name":"Zolotyata",
    "gn:population":0,
    "gn:timezone":"Asia/Yekaterinburg",
    "iso:country":"RU",
    "name:rus_x_preferred":[
        "\u0417\u043e\u043b\u043e\u0442\u044f\u0442\u0430"
    ],
    "wof:name":"Zolotyata",
    "wof:placetype":"locality"
},
  "geometry": {"coordinates":[56.9096,58.7192],"type":"Point"}
}