{
  "type": "Feature",
  "properties": {
    "gn:admin1_code":"21.0",
    "gn:asciiname":"Perepechino Bol'shoye",
    "gn:country_code":"RU",
    "gn:dem":111,
    "gn:feature_class":"P",
    "gn:feature_code":"PPL",
    "gn:name":"Perepechino Bol\u2019shoye",
    "gn:population":0,
    "gn:timezone":"Europe/Moscow",
    "iso:country":"RU",
    "name:rus_x_preferred":[
        "\u041f\u0435\u0440\u0435\u043f\u0435\u0447\u0438\u043d\u043e \u0411\u043e\u043b\u044c\u0448\u043e\u0435"
    ],
    "name:und_x_variant":[
        "Perepechino",
        "Bol\u2019shoye Perepechino",
        "Perepechino Bol\u2019shoye"
    ],
    "wof:name":"Perepechino Bol'shoye",
    "wof:placetype":"locality"
},
  "geometry": {"coordinates":[40.94857,56.75769],"type":"Point"}
}