{
  "type": "Feature",
  "properties": {
    "gn:admin1_code":"77.0",
    "gn:asciiname":"Kulitskaya",
    "gn:country_code":"RU",
    "gn:dem":147,
    "gn:feature_class":"P",
    "gn:feature_code":"PPL",
    "gn:name":"Kulitskaya",
    "gn:population":0,
    "gn:timezone":"Europe/Moscow",
    "iso:country":"RU",
    "name:nor_x_preferred":[
        "Kulitskaja"
    ],
    "name:rus_x_preferred":[
        "\u041a\u0443\u043b\u0438\u0446\u043a\u0430\u044f"
    ],
    "wof:name":"Kulitskaya",
    "wof:placetype":"locality"
},
  "geometry": {"coordinates":[35.68377,56.97701],"type":"Point"}
}