{
  "type": "Feature",
  "properties": {
    "gn:admin1_code":"33",
    "gn:asciiname":"Zagrebiny",
    "gn:country_code":"RU",
    "gn:dem":127,
    "gn:feature_class":"P",
    "gn:feature_code":"PPL",
    "gn:name":"Zagrebiny",
    "gn:population":0,
    "gn:timezone":"Europe/Kirov",
    "iso:country":"RU",
    "name:rus_x_preferred":[
        "\u0417\u0430\u0433\u0440\u0435\u0431\u0438\u043d\u044b"
    ],
    "wof:name":"Zagrebiny",
    "wof:placetype":"locality"
},
  "geometry": {"coordinates":[47.58328,58.20733000000001],"type":"Point"}
}