{
  "type": "Feature",
  "properties": {
    "gn:admin1_code":"77",
    "gn:asciiname":"Strekachevo",
    "gn:country_code":"RU",
    "gn:dem":192,
    "gn:feature_class":"P",
    "gn:feature_code":"PPL",
    "gn:name":"Strekachevo",
    "gn:population":0,
    "gn:timezone":"Europe/Moscow",
    "iso:country":"RU",
    "name:rus_x_preferred":[
        "\u0421\u0442\u0440\u0435\u043a\u0430\u0447\u0435\u0432\u043e"
    ],
    "name:und_x_variant":[
        "\u0421\u0442\u0440\u0435\u043a\u0430\u0447\u0435\u0432\u043e"
    ],
    "wof:name":"Strekachevo",
    "wof:placetype":"locality"
},
  "geometry": {"coordinates":[36.7689,58.6048],"type":"Point"}
}