{
  "type": "Feature",
  "properties": {
    "gn:admin1_code":"56.0",
    "gn:asciiname":"Alad'yevo",
    "gn:country_code":"RU",
    "gn:dem":213,
    "gn:feature_class":"P",
    "gn:feature_code":"PPL",
    "gn:name":"Alad\u2019yevo",
    "gn:population":0,
    "gn:timezone":"Europe/Moscow",
    "iso:country":"RU",
    "name:nor_x_preferred":[
        "Aladjevo"
    ],
    "name:rus_x_preferred":[
        "\u0410\u043b\u0430\u0434\u044c\u0435\u0432\u043e"
    ],
    "name:und_x_variant":[
        "Alad\u2019yevo"
    ],
    "wof:name":"Alad'yevo",
    "wof:placetype":"locality"
},
  "geometry": {"coordinates":[36.58655,52.268],"type":"Point"}
}