{
  "type": "Feature",
  "properties": {
    "gn:admin1_code":"72.0",
    "gn:asciiname":"Burovshchino",
    "gn:country_code":"RU",
    "gn:dem":123,
    "gn:feature_class":"P",
    "gn:feature_code":"PPL",
    "gn:name":"Burovshchino",
    "gn:population":0,
    "gn:timezone":"Europe/Moscow",
    "iso:country":"RU",
    "name:rus_x_preferred":[
        "\u0411\u0443\u0440\u043e\u0432\u0449\u0438\u043d\u043e"
    ],
    "wof:name":"Burovshchino",
    "wof:placetype":"locality"
},
  "geometry": {"coordinates":[42.65923,52.45456],"type":"Point"}
}