{
  "type": "Feature",
  "properties": {
    "gn:admin1_code":"86",
    "gn:asciiname":"Vol'nyy",
    "gn:country_code":"RU",
    "gn:dem":142,
    "gn:feature_class":"P",
    "gn:feature_code":"PPL",
    "gn:name":"Vol\u2019nyy",
    "gn:population":0,
    "gn:timezone":"Europe/Moscow",
    "iso:country":"RU",
    "name:und_x_variant":[
        "Vol\u2019ny",
        "Vol\u2019nyy"
    ],
    "wof:name":"Vol'nyy",
    "wof:placetype":"locality"
},
  "geometry": {"coordinates":[39.65778,51.24639000000001],"type":"Point"}
}