{
  "type": "Feature",
  "properties": {
    "gn:admin1_code":"6.0",
    "gn:asciiname":"Kulemikha",
    "gn:country_code":"RU",
    "gn:dem":84,
    "gn:feature_class":"P",
    "gn:feature_code":"PPL",
    "gn:name":"Kulemikha",
    "gn:population":0,
    "gn:timezone":"Europe/Moscow",
    "iso:country":"RU",
    "name:rus_x_preferred":[
        "\u041a\u0443\u043b\u0435\u043c\u0438\u0445\u0430"
    ],
    "wof:name":"Kulemikha",
    "wof:placetype":"locality"
},
  "geometry": {"coordinates":[40.9187,61.7748],"type":"Point"}
}