{
  "type": "Feature",
  "properties": {
    "gn:admin1_code":"37",
    "gn:asciiname":"Nagatino",
    "gn:country_code":"RU",
    "gn:dem":162,
    "gn:feature_class":"P",
    "gn:feature_code":"PPL",
    "gn:name":"Nagatino",
    "gn:population":0,
    "gn:timezone":"Europe/Moscow",
    "iso:country":"RU",
    "name:rus_x_preferred":[
        "\u041d\u0430\u0433\u0430\u0442\u0438\u043d\u043e"
    ],
    "wof:name":"Nagatino",
    "wof:placetype":"locality"
},
  "geometry": {"coordinates":[42.1013,58.3927],"type":"Point"}
}