{
  "type": "Feature",
  "properties": {
    "gn:admin1_code":"62",
    "gn:asciiname":"Trud",
    "gn:country_code":"RU",
    "gn:dem":151,
    "gn:feature_class":"P",
    "gn:feature_code":"PPL",
    "gn:name":"Trud",
    "gn:population":0,
    "gn:timezone":"Europe/Moscow",
    "iso:country":"RU",
    "name:bel_x_preferred":[
        "\u0422\u0440\u0443\u0434"
    ],
    "name:bul_x_preferred":[
        "\u0422\u0440\u0443\u0434"
    ],
    "name:ceb_x_preferred":[
        "Trud"
    ],
    "name:deu_x_preferred":[
        "Trude"
    ],
    "name:est_x_preferred":[
        "Trud"
    ],
    "name:hye_x_preferred":[
        "\u054f\u0580\u0578\u0582\u0564"
    ],
    "name:pol_x_preferred":[
        "Trud"
    ],
    "name:rus_x_preferred":[
        "\u0422\u0440\u0443\u0434"
    ],
    "name:spa_x_preferred":[
        "Trud"
    ],
    "name:swe_x_preferred":[
        "Trud"
    ],
    "name:ukr_x_preferred":[
        "\u0422\u0440\u0443\u0434"
    ],
    "wof:name":"Trud",
    "wof:placetype":"locality"
},
  "geometry": {"coordinates":[41.58301,54.33871],"type":"Point"}
}