{
  "type": "Feature",
  "properties": {
    "gn:admin1_code":"40",
    "gn:asciiname":"Bol'shoye Bannikovo",
    "gn:country_code":"RU",
    "gn:dem":121,
    "gn:feature_class":"P",
    "gn:feature_code":"PPL",
    "gn:name":"Bol\u2019shoye Bannikovo",
    "gn:population":0,
    "gn:timezone":"Asia/Yekaterinburg",
    "iso:country":"RU",
    "name:rus_x_preferred":[
        "\u0411\u043e\u043b\u044c\u0448\u043e\u0435 \u0411\u0430\u043d\u043d\u0438\u043a\u043e\u0432\u043e"
    ],
    "name:und_x_variant":[
        "Bol\u2019shaya Bannikova",
        "Bol\u2019shoye Bannikovo"
    ],
    "wof:name":"Bol'shoye Bannikovo",
    "wof:placetype":"locality"
},
  "geometry": {"coordinates":[64.86,55.73944],"type":"Point"}
}