{
  "type": "Feature",
  "properties": {
    "gn:admin1_code":"49",
    "gn:asciiname":"Loparskaya",
    "gn:country_code":"RU",
    "gn:dem":44,
    "gn:feature_class":"P",
    "gn:feature_code":"PPL",
    "gn:name":"Loparskaya",
    "gn:population":0,
    "gn:timezone":"Europe/Moscow",
    "iso:country":"RU",
    "name:che_x_preferred":[
        "\u041b\u043e\u043f\u0430\u0440\u0441\u043a\u0438"
    ],
    "name:eng_x_preferred":[
        "Loparskaya"
    ],
    "name:nor_x_preferred":[
        "Loparskaja"
    ],
    "name:rus_x_preferred":[
        "\u041b\u043e\u043f\u0430\u0440\u0441\u043a\u0430\u044f"
    ],
    "name:und_x_variant":[
        "\u041b\u043e\u043f\u0430\u0440\u0441\u043a\u0430\u044f",
        "Loparskaya"
    ],
    "wof:name":"Loparskaya",
    "wof:placetype":"locality"
},
  "geometry": {"coordinates":[33.21968,68.63744],"type":"Point"}
}