{
  "type": "Feature",
  "properties": {
    "gn:admin1_code":"76.0",
    "gn:asciiname":"Chernogryazka",
    "gn:country_code":"RU",
    "gn:dem":149,
    "gn:feature_class":"P",
    "gn:feature_code":"PPL",
    "gn:name":"Chernogryazka",
    "gn:population":0,
    "gn:timezone":"Europe/Moscow",
    "iso:country":"RU",
    "name:rus_x_preferred":[
        "\u0427\u0435\u0440\u043d\u043e\u0433\u0440\u044f\u0437\u043a\u0430"
    ],
    "wof:name":"Chernogryazka",
    "wof:placetype":"locality"
},
  "geometry": {"coordinates":[36.25275,53.66245],"type":"Point"}
}