{
  "type": "Feature",
  "properties": {
    "gn:admin1_code":"53",
    "gn:asciiname":"Manuylovo",
    "gn:country_code":"RU",
    "gn:dem":160,
    "gn:feature_class":"P",
    "gn:feature_code":"PPL",
    "gn:name":"Manuylovo",
    "gn:population":0,
    "gn:timezone":"Asia/Novosibirsk",
    "iso:country":"RU",
    "name:eng_x_preferred":[
        "Manuylovo"
    ],
    "name:nor_x_preferred":[
        "Manujlovo"
    ],
    "name:rus_x_preferred":[
        "\u041c\u0430\u043d\u0443\u0439\u043b\u043e\u0432\u043e"
    ],
    "name:und_x_variant":[
        "Manoylova"
    ],
    "wof:name":"Manuylovo",
    "wof:placetype":"locality"
},
  "geometry": {"coordinates":[84.402,55.5883],"type":"Point"}
}