{
  "type": "Feature",
  "properties": {
    "gn:admin1_code":"61",
    "gn:asciiname":"Verkhnetalovka",
    "gn:country_code":"RU",
    "gn:dem":93,
    "gn:feature_class":"P",
    "gn:feature_code":"PPL",
    "gn:name":"Verkhnetalovka",
    "gn:population":0,
    "gn:timezone":"Europe/Moscow",
    "iso:country":"RU",
    "name:rus_x_preferred":[
        "\u0412\u0435\u0440\u0445\u043d\u0435\u0442\u0430\u043b\u043e\u0432\u043a\u0430"
    ],
    "name:und_x_variant":[
        "\u0412\u0435\u0440\u0445\u043d\u0435\u0442\u0430\u043b\u043e\u0432\u043a\u0430"
    ],
    "wof:name":"Verkhnetalovka",
    "wof:placetype":"locality"
},
  "geometry": {"coordinates":[40.36334,48.82061],"type":"Point"}
}