{
  "type": "Feature",
  "properties": {
    "gn:country":"RU",
    "gn:fcode":"PPL",
    "gn:pop":0,
    "iso:country":"RU",
    "name:bos_x_preferred":[
        "Petrovo"
    ],
    "name:bul_x_preferred":[
        "\u041f\u0435\u0442\u0440\u043e\u0432\u043e"
    ],
    "name:ceb_x_preferred":[
        "Petrovo"
    ],
    "name:deu_x_preferred":[
        "Petrowo"
    ],
    "name:eng_x_preferred":[
        "Petrovo"
    ],
    "name:eus_x_preferred":[
        "Petrovo"
    ],
    "name:fra_x_preferred":[
        "Petrovo"
    ],
    "name:ita_x_preferred":[
        "Petrovo"
    ],
    "name:nld_x_preferred":[
        "Petrovo"
    ],
    "name:nor_x_preferred":[
        "Petrovo"
    ],
    "name:pol_x_preferred":[
        "Petrowo"
    ],
    "name:ron_x_preferred":[
        "Petrovo"
    ],
    "name:rus_x_preferred":[
        "\u041f\u0435\u0442\u0440\u043e\u0432\u043e"
    ],
    "name:srp_x_preferred":[
        "\u041f\u0435\u0442\u0440\u043e\u0432\u043e"
    ],
    "name:swe_x_preferred":[
        "Petrovo"
    ],
    "name:ukr_x_preferred":[
        "\u041f\u0435\u0442\u0440\u043e\u0432\u043e"
    ],
    "name:unk_x_variant":[
        "Mineyevok"
    ],
    "qs:name":"Petrovo",
    "qs:name_adm0":"Russia",
    "qs:name_adm1":"Moscow Oblast",
    "qs:photos_9k":1,
    "qs:photos_9r":1,
    "qs:photos_all":1,
    "qs:photos_sr":0,
    "qs:placetype":"Town",
    "qs:pop_sr":"0",
    "wd:wordcount":218,
    "wof:name":"Petrovo",
    "wof:placetype":"locality",
    "wof:population":0
},
  "geometry": {"coordinates":[38.13594,54.9955],"type":"Point"}
}