{
  "type": "Feature",
  "properties": {
    "gn:admin1_code":"91",
    "gn:asciiname":"Opol'chum",
    "gn:country_code":"RU",
    "gn:dem":163,
    "gn:feature_class":"P",
    "gn:feature_code":"PPL",
    "gn:name":"Opol\u2019chum",
    "gn:population":0,
    "gn:timezone":"Asia/Krasnoyarsk",
    "iso:country":"RU",
    "name:rus_x_preferred":[
        "\u041e\u043f\u043e\u043b\u044c\u0447\u0443\u043c"
    ],
    "name:und_x_variant":[
        "Opol\u2019chum"
    ],
    "wof:name":"Opol'chum",
    "wof:placetype":"locality"
},
  "geometry": {"coordinates":[88.05,59.95],"type":"Point"}
}