{
  "type": "Feature",
  "properties": {
    "gn:admin1_code":"85",
    "gn:asciiname":"Vasil'yevskaya",
    "gn:country_code":"RU",
    "gn:dem":159,
    "gn:feature_class":"P",
    "gn:feature_code":"PPL",
    "gn:name":"Vasil\u2019yevskaya",
    "gn:population":0,
    "gn:timezone":"Europe/Moscow",
    "iso:country":"RU",
    "name:und_x_variant":[
        "Porozi",
        "Vasil\u2019yevskaya"
    ],
    "wof:name":"Vasil'yevskaya",
    "wof:placetype":"locality"
},
  "geometry": {"coordinates":[40.55752,60.52117],"type":"Point"}
}