{
  "type": "Feature",
  "properties": {
    "gn:admin1_code":"8",
    "gn:asciiname":"Mukhamed'yanovo",
    "gn:country_code":"RU",
    "gn:dem":325,
    "gn:feature_class":"P",
    "gn:feature_code":"PPL",
    "gn:name":"Mukhamed\u2019yanovo",
    "gn:population":0,
    "gn:timezone":"Asia/Yekaterinburg",
    "iso:country":"RU",
    "name:eng_x_preferred":[
        "Mukhamed'yanovo"
    ],
    "name:nor_x_preferred":[
        "Mukhamedjanovo"
    ],
    "name:rus_x_preferred":[
        "\u041c\u0443\u0445\u0430\u043c\u0435\u0434\u044c\u044f\u043d\u043e\u0432\u043e"
    ],
    "name:und_x_variant":[
        "Mukhametzyanovo",
        "Mukhamedzyanovo",
        "\u041c\u0443\u0445\u0430\u043c\u0435\u0434\u044c\u044f\u043d\u043e\u0432\u043e",
        "Mukhamed\u2019yanovo"
    ],
    "wof:name":"Mukhamed'yanovo",
    "wof:placetype":"locality"
},
  "geometry": {"coordinates":[56.94661,51.97365],"type":"Point"}
}