{
  "type": "Feature",
  "properties": {
    "gn:admin1_code":"81.0",
    "gn:asciiname":"Tashla",
    "gn:country_code":"RU",
    "gn:dem":298,
    "gn:feature_class":"P",
    "gn:feature_code":"PPL",
    "gn:name":"Tashla",
    "gn:population":0,
    "gn:timezone":"Europe/Ulyanovsk",
    "iso:country":"RU",
    "name:rus_x_preferred":[
        "\u0422\u0430\u0448\u043b\u0430"
    ],
    "wof:name":"Tashla",
    "wof:placetype":"locality"
},
  "geometry": {"coordinates":[48.3943,53.8975],"type":"Point"}
}