{
  "type": "Feature",
  "properties": {
    "gn:admin1_code":"69",
    "gn:asciiname":"Ust'ye",
    "gn:country_code":"RU",
    "gn:dem":179,
    "gn:feature_class":"P",
    "gn:feature_code":"PPL",
    "gn:name":"Ust\u2019ye",
    "gn:population":0,
    "gn:timezone":"Europe/Moscow",
    "iso:country":"RU",
    "name:rus_x_preferred":[
        "\u0423\u0441\u0442\u044c\u0435"
    ],
    "name:und_x_variant":[
        "Ust\u2019ye"
    ],
    "wof:name":"Ust'ye",
    "wof:placetype":"locality"
},
  "geometry": {"coordinates":[32.2655,54.3208],"type":"Point"}
}