{
  "type": "Feature",
  "properties": {
    "gn:admin1_code":"12",
    "gn:admin2_code":"Vedenskiy Rayon",
    "gn:asciiname":"Mesedoy",
    "gn:country_code":"RU",
    "gn:dem":713,
    "gn:feature_class":"P",
    "gn:feature_code":"PPL",
    "gn:name":"Mesedoy",
    "gn:population":0,
    "gn:timezone":"Europe/Moscow",
    "iso:country":"RU",
    "name:che_x_preferred":[
        "Mesadayn-Khotar"
    ],
    "name:che_x_variant":[
        "Mesadoyn-Khotar",
        "\u041c\u0435\u0441\u0430\u0434\u0430\u0439\u043d-\u041a\u0406\u043e\u0442\u0430\u0440",
        "\u041c\u0435\u0441\u0430\u0434\u043e\u0439\u043d-\u041a\u0406\u043e\u0442\u0430\u0440"
    ],
    "name:rus_x_preferred":[
        "\u041c\u0435\u0441\u0435\u0434\u043e\u0439"
    ],
    "name:und_x_variant":[
        "Mesedoj"
    ],
    "wof:name":"Mesedoy",
    "wof:placetype":"locality"
},
  "geometry": {"coordinates":[46.12139000000001,43.02056],"type":"Point"}
}