{
  "type": "Feature",
  "properties": {
    "gn:country":"RU",
    "gn:fcode":"PPL",
    "gn:population":3060,
    "iso:country":"RU",
    "name:eng_x_preferred":[
        "Bessonovka"
    ],
    "name:nor_x_preferred":[
        "Bessonovka"
    ],
    "name:rus_x_preferred":[
        "\u0411\u0435\u0441\u0441\u043e\u043d\u043e\u0432\u043a\u0430"
    ],
    "name:und_x_variant":[
        "Bessonowka"
    ],
    "qs:name":"Bessonovka",
    "qs:name_adm0":"Russia",
    "qs:name_adm1":"Belgorod Oblast",
    "qs:photos_9r":0,
    "qs:photos_sr":0,
    "qs:placetype":"Town",
    "qs:pop_sr":"4",
    "wd:wordcount":110,
    "wof:name":"Bessonovka",
    "wof:placetype":"locality",
    "wof:population":3060
},
  "geometry": {"coordinates":[36.30107,50.52644],"type":"Point"}
}