{
  "type": "Feature",
  "properties": {
    "gn:admin1_code":"67",
    "gn:asciiname":"Kondrashovka",
    "gn:country_code":"RU",
    "gn:dem":183,
    "gn:feature_class":"P",
    "gn:feature_code":"PPL",
    "gn:name":"Kondrashovka",
    "gn:population":0,
    "gn:timezone":"Europe/Saratov",
    "iso:country":"RU",
    "name:rus_x_preferred":[
        "\u041a\u043e\u043d\u0434\u0440\u0430\u0448\u043e\u0432\u043a\u0430"
    ],
    "name:und_x_variant":[
        "Kondrashevka",
        "Kondrashovka",
        "\u041a\u043e\u043d\u0434\u0440\u0430\u0448\u043e\u0432\u043a\u0430"
    ],
    "wof:name":"Kondrashovka",
    "wof:placetype":"locality"
},
  "geometry": {"coordinates":[44.15495,51.89822],"type":"Point"}
}