{
  "type": "Feature",
  "properties": {
    "gn:admin1_code":"77.0",
    "gn:asciiname":"Bol'shiye Malosheviny",
    "gn:country_code":"RU",
    "gn:dem":157,
    "gn:feature_class":"P",
    "gn:feature_code":"PPL",
    "gn:name":"Bol\u2019shiye Malosheviny",
    "gn:population":0,
    "gn:timezone":"Europe/Moscow",
    "iso:country":"RU",
    "name:rus_x_preferred":[
        "\u0411\u043e\u043b\u044c\u0448\u0438\u0435 \u041c\u0430\u043b\u043e\u0448\u0435\u0432\u0438\u043d\u044b"
    ],
    "name:und_x_variant":[
        "Malosheviny",
        "Maloshevina",
        "Bol\u2019shiye Malosheviny",
        "\u0411\u043e\u043b\u044c\u0448\u0438\u0435 \u041c\u0430\u043b\u043e\u0448\u0435\u0432\u0438\u043d\u044b"
    ],
    "wof:name":"Bol'shiye Malosheviny",
    "wof:placetype":"locality"
},
  "geometry": {"coordinates":[34.65953,57.79467],"type":"Point"}
}