{
  "type": "Feature",
  "properties": {
    "gn:admin1_code":"4",
    "gn:asciiname":"Kordon Krasnosel'skiy",
    "gn:country_code":"RU",
    "gn:dem":302,
    "gn:feature_class":"P",
    "gn:feature_code":"PPL",
    "gn:name":"Kordon Krasnosel\u2019skiy",
    "gn:population":0,
    "gn:timezone":"Asia/Barnaul",
    "iso:country":"RU",
    "name:rus_x_preferred":[
        "\u041a\u043e\u0440\u0434\u043e\u043d \u041a\u0440\u0430\u0441\u043d\u043e\u0441\u0435\u043b\u044c\u0441\u043a\u0438\u0439"
    ],
    "name:und_x_variant":[
        "Kordon Krasnosel\u2019skiy"
    ],
    "wof:name":"Kordon Krasnosel'skiy",
    "wof:placetype":"locality"
},
  "geometry": {"coordinates":[85.31100000000001,54.0959],"type":"Point"}
}