{
  "type": "Feature",
  "properties": {
    "gn:admin1_code":"7",
    "gn:asciiname":"Tselukha",
    "gn:country_code":"RU",
    "gn:dem":-22,
    "gn:feature_class":"P",
    "gn:feature_code":"PPL",
    "gn:name":"Tselukha",
    "gn:population":0,
    "gn:timezone":"Europe/Astrakhan",
    "iso:country":"RU",
    "name:rus_x_preferred":[
        "\u0426\u0435\u043b\u0443\u0445\u0430"
    ],
    "name:und_x_variant":[
        "\u0426\u0435\u043b\u0443\u0445\u0430"
    ],
    "wof:name":"Tselukha",
    "wof:placetype":"locality"
},
  "geometry": {"coordinates":[47.5181,47.1225],"type":"Point"}
}