{
  "type": "Feature",
  "properties": {
    "gn:admin1_code":"37.0",
    "gn:asciiname":"Belaya Reka",
    "gn:country_code":"RU",
    "gn:dem":151,
    "gn:feature_class":"P",
    "gn:feature_code":"PPL",
    "gn:name":"Belaya Reka",
    "gn:population":0,
    "gn:timezone":"Europe/Moscow",
    "iso:country":"RU",
    "name:nor_x_preferred":[
        "Belaja Reka"
    ],
    "name:rus_x_preferred":[
        "\u0411\u0435\u043b\u0430\u044f \u0420\u0435\u043a\u0430"
    ],
    "wof:name":"Belaya Reka",
    "wof:placetype":"locality"
},
  "geometry": {"coordinates":[41.46536,57.90619],"type":"Point"}
}