{
  "type": "Feature",
  "properties": {
    "gn:admin1_code":"43",
    "gn:asciiname":"Spasskaya",
    "gn:country_code":"RU",
    "gn:dem":193,
    "gn:feature_class":"P",
    "gn:feature_code":"PPL",
    "gn:name":"Spasskaya",
    "gn:population":0,
    "gn:timezone":"Europe/Moscow",
    "iso:country":"RU",
    "name:rus_x_preferred":[
        "\u0421\u043f\u0430\u0441\u0441\u043a\u0430\u044f"
    ],
    "name:und_x_variant":[
        "\u0421\u043f\u0430\u0441\u0441\u043a\u0430\u044f"
    ],
    "wof:name":"Spasskaya",
    "wof:placetype":"locality"
},
  "geometry": {"coordinates":[38.3444,52.2228],"type":"Point"}
}