{
  "type": "Feature",
  "properties": {
    "gn:admin1_code":"72",
    "gn:asciiname":"Khomutets",
    "gn:country_code":"RU",
    "gn:dem":147,
    "gn:feature_class":"P",
    "gn:feature_code":"PPL",
    "gn:name":"Khomutets",
    "gn:population":0,
    "gn:timezone":"Europe/Moscow",
    "iso:country":"RU",
    "name:rus_x_preferred":[
        "\u0425\u043e\u043c\u0443\u0442\u0435\u0446"
    ],
    "wof:name":"Khomutets",
    "wof:placetype":"locality"
},
  "geometry": {"coordinates":[40.7697,52.0321],"type":"Point"}
}