{
  "type": "Feature",
  "properties": {
    "gn:admin1_code":"88.0",
    "gn:asciiname":"Bochkino",
    "gn:country_code":"RU",
    "gn:dem":151,
    "gn:feature_class":"P",
    "gn:feature_code":"PPL",
    "gn:name":"Bochkino",
    "gn:population":0,
    "gn:timezone":"Europe/Moscow",
    "iso:country":"RU",
    "name:rus_x_preferred":[
        "\u0411\u043e\u0447\u043a\u0438\u043d\u043e"
    ],
    "name:und_x_variant":[
        "\u0411\u043e\u0447\u043a\u0438\u043d\u043e"
    ],
    "wof:name":"Bochkino",
    "wof:placetype":"locality"
},
  "geometry": {"coordinates":[40.21271,58.32855],"type":"Point"}
}