{
  "type": "Feature",
  "properties": {
    "gn:admin1_code":"88",
    "gn:asciiname":"Yemishevo",
    "gn:country_code":"RU",
    "gn:dem":125,
    "gn:feature_class":"P",
    "gn:feature_code":"PPL",
    "gn:name":"Yemishevo",
    "gn:population":0,
    "gn:timezone":"Europe/Moscow",
    "iso:country":"RU",
    "name:rus_x_preferred":[
        "\u0415\u043c\u0438\u0448\u0435\u0432\u043e"
    ],
    "wof:name":"Yemishevo",
    "wof:placetype":"locality"
},
  "geometry": {"coordinates":[39.40501,57.9041],"type":"Point"}
}