{
  "type": "Feature",
  "properties": {
    "gn:admin1_code":"28",
    "gn:asciiname":"Peninga",
    "gn:country_code":"RU",
    "gn:dem":214,
    "gn:feature_class":"P",
    "gn:feature_code":"PPL",
    "gn:name":"Peninga",
    "gn:population":0,
    "gn:timezone":"Europe/Moscow",
    "iso:country":"RU",
    "name:eng_x_preferred":[
        "Peninga"
    ],
    "name:nor_x_preferred":[
        "Peninga"
    ],
    "name:olo_x_preferred":[
        "Pienink\u00e4"
    ],
    "name:rus_x_preferred":[
        "\u041f\u0435\u043d\u0438\u043d\u0433\u0430"
    ],
    "name:und_x_variant":[
        "\u041f\u0435\u043d\u0438\u043d\u0433\u0430",
        "Peninga"
    ],
    "wof:name":"Peninga",
    "wof:placetype":"locality"
},
  "geometry": {"coordinates":[32.04229,63.5552],"type":"Point"}
}