{
  "type": "Feature",
  "properties": {
    "gn:admin1_code":"60",
    "gn:asciiname":"Vashi",
    "gn:country_code":"RU",
    "gn:dem":103,
    "gn:feature_class":"P",
    "gn:feature_code":"PPL",
    "gn:name":"Vashi",
    "gn:population":0,
    "gn:timezone":"Europe/Moscow",
    "iso:country":"RU",
    "name:und_x_variant":[
        "Voshi",
        "Vashi"
    ],
    "wof:name":"Vashi",
    "wof:placetype":"locality"
},
  "geometry": {"coordinates":[31.00714,56.53386999999999],"type":"Point"}
}