{
  "type": "Feature",
  "properties": {
    "gn:admin1_code":"60",
    "gn:asciiname":"Vashi",
    "gn:country_code":"RU",
    "gn:dem":103,
    "gn:feature_class":"P",
    "gn:feature_code":"PPL",
    "gn:name":"Vashi",
    "gn:population":0,
    "gn:timezone":"Europe/Moscow",
    "iso:country":"RU",
    "name:fas_x_preferred":[
        "\u0648\u0634\u06cc"
    ],
    "name:fra_x_preferred":[
        "Vashi"
    ],
    "name:hin_x_preferred":[
        "\u0935\u093e\u0936\u0940"
    ],
    "name:mal_x_preferred":[
        "\u0d35\u0d3e\u0d36\u0d3f"
    ],
    "name:mar_x_preferred":[
        "\u0935\u093e\u0936\u0940"
    ],
    "name:nor_x_preferred":[
        "Vashi"
    ],
    "name:und_x_variant":[
        "Voshi"
    ],
    "wof:name":"Vashi",
    "wof:placetype":"locality"
},
  "geometry": {"coordinates":[31.00714,56.53386999999999],"type":"Point"}
}