{
  "type": "Feature",
  "properties": {
    "gn:admin1_code":"88",
    "gn:asciiname":"Shakhovaya",
    "gn:country_code":"RU",
    "gn:dem":126,
    "gn:feature_class":"P",
    "gn:feature_code":"PPL",
    "gn:name":"Shakhovaya",
    "gn:population":0,
    "gn:timezone":"Europe/Moscow",
    "iso:country":"RU",
    "name:rus_x_preferred":[
        "\u0428\u0430\u0445\u043e\u0432\u0430\u044f"
    ],
    "wof:name":"Shakhovaya",
    "wof:placetype":"locality"
},
  "geometry": {"coordinates":[38.03261,58.1707],"type":"Point"}
}