{
  "type": "Feature",
  "properties": {
    "gn:admin1_code":"27.0",
    "gn:asciiname":"Baralki",
    "gn:country_code":"RU",
    "gn:dem":487,
    "gn:feature_class":"P",
    "gn:feature_code":"PPL",
    "gn:name":"Baralki",
    "gn:population":0,
    "gn:timezone":"Europe/Moscow",
    "iso:country":"RU",
    "name:nor_x_preferred":[
        "Baralki"
    ],
    "name:rus_x_preferred":[
        "\u0411\u0430\u0440\u0430\u043b\u043a\u0438"
    ],
    "wof:name":"Baralki",
    "wof:placetype":"locality"
},
  "geometry": {"coordinates":[41.8016,44.34935],"type":"Point"}
}