{
  "type": "Feature",
  "properties": {
    "gn:admin1_code":"10.0",
    "gn:asciiname":"Bliznitsy",
    "gn:country_code":"RU",
    "gn:dem":180,
    "gn:feature_class":"P",
    "gn:feature_code":"PPL",
    "gn:name":"Bliznitsy",
    "gn:population":0,
    "gn:timezone":"Europe/Moscow",
    "iso:country":"RU",
    "name:rus_x_preferred":[
        "\u0411\u043b\u0438\u0437\u043d\u0438\u0446\u044b"
    ],
    "name:und_x_variant":[
        "Bliznetsy",
        "Bliznitsy"
    ],
    "wof:name":"Bliznitsy",
    "wof:placetype":"locality"
},
  "geometry": {"coordinates":[33.2342,53.0674],"type":"Point"}
}