{
  "type": "Feature",
  "properties": {
    "gn:admin1_code":"71",
    "gn:asciiname":"Yeremeyevka",
    "gn:country_code":"RU",
    "gn:dem":223,
    "gn:feature_class":"P",
    "gn:feature_code":"PPL",
    "gn:name":"Yeremeyevka",
    "gn:population":0,
    "gn:timezone":"Asia/Yekaterinburg",
    "iso:country":"RU",
    "name:rus_x_preferred":[
        "\u0415\u0440\u0435\u043c\u0435\u0435\u0432\u043a\u0430"
    ],
    "wof:name":"Yeremeyevka",
    "wof:placetype":"locality"
},
  "geometry": {"coordinates":[58.0295,57.0137],"type":"Point"}
}