{
  "type": "Feature",
  "properties": {
    "gn:admin1_code":"77",
    "gn:asciiname":"Luchka",
    "gn:country_code":"RU",
    "gn:dem":88,
    "gn:feature_class":"P",
    "gn:feature_code":"PPL",
    "gn:name":"Luchka",
    "gn:population":0,
    "gn:timezone":"Europe/Moscow",
    "iso:country":"RU",
    "name:rus_x_preferred":[
        "\u041b\u0443\u0447\u043a\u0430"
    ],
    "wof:name":"Luchka",
    "wof:placetype":"locality"
},
  "geometry": {"coordinates":[30.9624,56.8642],"type":"Point"}
}