{
  "type": "Feature",
  "properties": {
    "gn:admin1_code":"34",
    "gn:asciiname":"Ul'yashevo",
    "gn:country_code":"RU",
    "gn:dem":50,
    "gn:feature_class":"P",
    "gn:feature_code":"PPL",
    "gn:name":"Ul\u2019yash\u00ebvo",
    "gn:population":0,
    "gn:timezone":"Europe/Moscow",
    "iso:country":"RU",
    "name:eng_x_preferred":[
        "Ul'yash\u00ebvo"
    ],
    "name:nor_x_preferred":[
        "Uljasjevo"
    ],
    "name:rus_x_preferred":[
        "\u0423\u043b\u044f\u0448\u0435\u0432\u043e"
    ],
    "name:und_x_variant":[
        "Ul\u2019yash\u00ebvo"
    ],
    "wof:name":"Ul'yashevo",
    "wof:placetype":"locality"
},
  "geometry": {"coordinates":[57.03146,65.43401],"type":"Point"}
}