{
  "type": "Feature",
  "properties": {
    "gn:admin1_code":"61.0",
    "gn:asciiname":"Korotkov",
    "gn:country_code":"RU",
    "gn:dem":49,
    "gn:feature_class":"P",
    "gn:feature_code":"PPL",
    "gn:name":"Korotkov",
    "gn:population":0,
    "gn:timezone":"Europe/Moscow",
    "iso:country":"RU",
    "name:rus_x_preferred":[
        "\u041a\u043e\u0440\u043e\u0442\u043a\u043e\u0432"
    ],
    "name:und_x_variant":[
        "\u041a\u043e\u0440\u043e\u0442\u043a\u043e\u0432"
    ],
    "wof:name":"Korotkov",
    "wof:placetype":"locality"
},
  "geometry": {"coordinates":[41.12472,48.70833],"type":"Point"}
}