{
  "type": "Feature",
  "properties": {
    "gn:admin1_code":"80",
    "gn:asciiname":"Kel'dyki",
    "gn:country_code":"RU",
    "gn:dem":161,
    "gn:feature_class":"P",
    "gn:feature_code":"PPL",
    "gn:name":"Kel\u2019dyki",
    "gn:population":0,
    "gn:timezone":"Europe/Samara",
    "iso:country":"RU",
    "name:rus_x_preferred":[
        "\u041a\u0435\u043b\u044c\u0434\u044b\u043a\u0438"
    ],
    "name:und_x_variant":[
        "Kel\u2019dyki",
        "\u041a\u0435\u043b\u044c\u0434\u044b\u043a\u0438"
    ],
    "wof:name":"Kel'dyki",
    "wof:placetype":"locality"
},
  "geometry": {"coordinates":[52.0109,57.9649],"type":"Point"}
}