{
  "type": "Feature",
  "properties": {
    "gn:admin1_code":"91",
    "gn:asciiname":"Novoivanovka",
    "gn:cc2":"RU",
    "gn:country_code":"RU",
    "gn:dem":242,
    "gn:feature_class":"P",
    "gn:feature_code":"PPL",
    "gn:name":"Novoivanovka",
    "gn:population":0,
    "gn:timezone":"Asia/Krasnoyarsk",
    "iso:country":"RU",
    "name:rus_x_preferred":[
        "\u041d\u043e\u0432\u043e\u0438\u0432\u0430\u043d\u043e\u0432\u043a\u0430"
    ],
    "name:und_x_variant":[
        "Novo-Ivanovskaya",
        "Novoivanovka"
    ],
    "wof:name":"Novoivanovka",
    "wof:placetype":"locality"
},
  "geometry": {"coordinates":[95.45,57.05],"type":"Point"}
}