{
  "type": "Feature",
  "properties": {
    "gn:admin1_code":"84",
    "gn:asciiname":"Zakhoperskiy",
    "gn:country_code":"RU",
    "gn:dem":80,
    "gn:feature_class":"P",
    "gn:feature_code":"PPL",
    "gn:name":"Zakhoperskiy",
    "gn:population":0,
    "gn:timezone":"Europe/Volgograd",
    "iso:country":"RU",
    "name:rus_x_preferred":[
        "\u0417\u0430\u0445\u043e\u043f\u0435\u0440\u0441\u043a\u0438\u0439"
    ],
    "wof:name":"Zakhoperskiy",
    "wof:placetype":"locality"
},
  "geometry": {"coordinates":[41.9047,50.771],"type":"Point"}
}