{
  "type": "Feature",
  "properties": {
    "gn:admin1_code":"33",
    "gn:asciiname":"Yershovka",
    "gn:country_code":"RU",
    "gn:dem":129,
    "gn:feature_class":"P",
    "gn:feature_code":"PPL",
    "gn:name":"Yershovka",
    "gn:population":0,
    "gn:timezone":"Europe/Kirov",
    "iso:country":"RU",
    "name:che_x_preferred":[
        "\u0415\u0440\u0448\u043e\u0432\u043a\u0430"
    ],
    "name:eng_x_preferred":[
        "Yershovka"
    ],
    "name:nor_x_preferred":[
        "Jersjovka"
    ],
    "name:rus_x_preferred":[
        "\u0415\u0440\u0448\u043e\u0432\u043a\u0430"
    ],
    "wof:name":"Yershovka",
    "wof:placetype":"locality"
},
  "geometry": {"coordinates":[51.0245,56.16684],"type":"Point"}
}