{
  "type": "Feature",
  "properties": {
    "gn:admin1_code":"11",
    "gn:asciiname":"Bulum",
    "gn:country_code":"RU",
    "gn:dem":710,
    "gn:feature_class":"P",
    "gn:feature_code":"PPL",
    "gn:name":"Bulum",
    "gn:population":0,
    "gn:timezone":"Asia/Irkutsk",
    "iso:country":"RU",
    "name:eng_x_preferred":[
        "Bulam"
    ],
    "name:nor_x_preferred":[
        "Bulum"
    ],
    "name:rus_x_preferred":[
        "\u0411\u0443\u043b\u0443\u043c"
    ],
    "wof:name":"Bulum",
    "wof:placetype":"locality"
},
  "geometry": {"coordinates":[110.11181999999999,52.28417],"type":"Point"}
}