{
  "type": "Feature",
  "properties": {
    "gn:admin1_code":"54",
    "gn:asciiname":"Beketovka",
    "gn:country_code":"RU",
    "gn:dem":121,
    "gn:feature_class":"P",
    "gn:feature_code":"PPL",
    "gn:name":"Beketovka",
    "gn:population":0,
    "gn:timezone":"Asia/Omsk",
    "iso:country":"RU",
    "name:che_x_preferred":[
        "\u0411\u0435\u043a\u0435\u0442\u043e\u0432\u043a\u0430"
    ],
    "name:nor_x_preferred":[
        "Beketovka"
    ],
    "name:rus_x_preferred":[
        "\u0411\u0435\u043a\u0435\u0442\u043e\u0432\u043a\u0430"
    ],
    "name:tgk_x_preferred":[
        "\u0411\u0435\u043a\u0435\u0442\u043e\u0432\u043a\u0430"
    ],
    "wof:name":"Beketovka",
    "wof:placetype":"locality"
},
  "geometry": {"coordinates":[73.53333000000001,55.13333000000001],"type":"Point"}
}