{
  "type": "Feature",
  "properties": {
    "gn:admin1_code":"38.0",
    "gn:asciiname":"Den' Urozhaya",
    "gn:country_code":"RU",
    "gn:dem":3,
    "gn:feature_class":"P",
    "gn:feature_code":"PPL",
    "gn:name":"Den\u2019 Urozhaya",
    "gn:population":0,
    "gn:timezone":"Europe/Moscow",
    "iso:country":"RU",
    "name:rus_x_preferred":[
        "\u0414\u0435\u043d\u044c \u0423\u0440\u043e\u0436\u0430\u044f"
    ],
    "name:und_x_variant":[
        "Den\u2019 Urazhaya",
        "Den\u2019 Urozhaya"
    ],
    "wof:name":"Den' Urozhaya",
    "wof:placetype":"locality"
},
  "geometry": {"coordinates":[38.45205,45.86338],"type":"Point"}
}