{
  "type": "Feature",
  "properties": {
    "gn:admin1_code":"37.0",
    "gn:asciiname":"Antipino",
    "gn:country_code":"RU",
    "gn:dem":132,
    "gn:feature_class":"P",
    "gn:feature_code":"PPL",
    "gn:name":"Antipino",
    "gn:population":0,
    "gn:timezone":"Europe/Moscow",
    "iso:country":"RU",
    "name:nor_x_preferred":[
        "Antipino"
    ],
    "name:rus_x_preferred":[
        "\u0410\u043d\u0442\u0438\u043f\u0438\u043d\u043e"
    ],
    "wof:name":"Antipino",
    "wof:placetype":"locality"
},
  "geometry": {"coordinates":[41.44667000000001,57.82518],"type":"Point"}
}