{
  "type": "Feature",
  "properties": {
    "gn:admin1_code":"63",
    "gn:asciiname":"Kubergene",
    "gn:country_code":"RU",
    "gn:dem":43,
    "gn:feature_class":"P",
    "gn:feature_code":"PPL",
    "gn:name":"Kubergene",
    "gn:population":0,
    "gn:timezone":"Asia/Magadan",
    "iso:country":"RU",
    "name:eng_x_preferred":[
        "Kubergene"
    ],
    "name:nor_x_preferred":[
        "Kuberganja"
    ],
    "name:rus_x_preferred":[
        "\u041a\u0443\u0431\u0435\u0440\u0433\u0430\u043d\u044f"
    ],
    "name:rus_x_variant":[
        "\u041a\u0443\u0431\u0435\u0440\u0433\u0435\u043d\u0435"
    ],
    "name:und_x_variant":[
        "Kebergene",
        "Kubergene",
        "\u041a\u0443\u0431\u0435\u0440\u0433\u0435\u043d\u0435"
    ],
    "wof:name":"Kubergene",
    "wof:placetype":"locality"
},
  "geometry": {"coordinates":[144.49090000000001,67.76968000000001],"type":"Point"}
}