{
  "type": "Feature",
  "properties": {
    "gn:admin1_code":"60",
    "gn:asciiname":"Zanyusskoye",
    "gn:country_code":"RU",
    "gn:dem":150,
    "gn:feature_class":"P",
    "gn:feature_code":"PPL",
    "gn:name":"Zanyusskoye",
    "gn:population":0,
    "gn:timezone":"Europe/Moscow",
    "iso:country":"RU",
    "name:rus_x_preferred":[
        "\u0417\u0430\u043d\u044e\u0441\u0441\u043a\u043e\u0435"
    ],
    "wof:name":"Zanyusskoye",
    "wof:placetype":"locality"
},
  "geometry": {"coordinates":[30.5214,56.0363],"type":"Point"}
}