{
  "type": "Feature",
  "properties": {
    "gn:admin1_code":"85",
    "gn:asciiname":"Malaya Novinka",
    "gn:country_code":"RU",
    "gn:dem":182,
    "gn:feature_class":"P",
    "gn:feature_code":"PPL",
    "gn:name":"Malaya Novinka",
    "gn:population":0,
    "gn:timezone":"Europe/Moscow",
    "iso:country":"RU",
    "name:rus_x_preferred":[
        "\u041c\u0430\u043b\u0430\u044f \u041d\u043e\u0432\u0438\u043d\u043a\u0430"
    ],
    "name:und_x_variant":[
        "\u041c\u0430\u043b\u0430\u044f \u041d\u043e\u0432\u0438\u043d\u043a\u0430"
    ],
    "wof:name":"Malaya Novinka",
    "wof:placetype":"locality"
},
  "geometry": {"coordinates":[38.2591,58.942],"type":"Point"}
}