{
  "type": "Feature",
  "properties": {
    "gn:admin1_code":"20.0",
    "gn:asciiname":"Seredkina",
    "gn:country_code":"RU",
    "gn:dem":409,
    "gn:feature_class":"P",
    "gn:feature_code":"PPL",
    "gn:name":"Ser\u00ebdkina",
    "gn:population":0,
    "gn:timezone":"Asia/Irkutsk",
    "iso:country":"RU",
    "name:rus_x_preferred":[
        "\u0421\u0435\u0440\u0451\u0434\u043a\u0438\u043d\u0430"
    ],
    "name:und_x_variant":[
        "Ser\u00ebdkina"
    ],
    "wof:name":"Seredkina",
    "wof:placetype":"locality"
},
  "geometry": {"coordinates":[103.4014,53.4397],"type":"Point"}
}