{
  "type": "Feature",
  "properties": {
    "gn:admin1_code":"90",
    "gn:asciiname":"Kunitsyna",
    "gn:country_code":"RU",
    "gn:dem":164,
    "gn:feature_class":"P",
    "gn:feature_code":"PPL",
    "gn:name":"Kunitsyna",
    "gn:population":0,
    "gn:timezone":"Asia/Yekaterinburg",
    "iso:country":"RU",
    "name:rus_x_preferred":[
        "\u041a\u0443\u043d\u0438\u0446\u044b\u043d\u0430"
    ],
    "name:und_x_variant":[
        "\u041a\u0443\u043d\u0438\u0446\u044b\u043d\u0430"
    ],
    "wof:name":"Kunitsyna",
    "wof:placetype":"locality"
},
  "geometry": {"coordinates":[57.08333,59.75],"type":"Point"}
}