{
  "type": "Feature",
  "properties": {
    "gn:admin1_code":"8",
    "gn:asciiname":"Nizhneye Babalarovo",
    "gn:country_code":"RU",
    "gn:dem":129,
    "gn:feature_class":"P",
    "gn:feature_code":"PPL",
    "gn:name":"Nizhneye Babalarovo",
    "gn:population":0,
    "gn:timezone":"Asia/Yekaterinburg",
    "iso:country":"RU",
    "name:rus_x_preferred":[
        "\u041d\u0438\u0436\u043d\u0435\u0435 \u0411\u0430\u0431\u0430\u043b\u0430\u0440\u043e\u0432\u043e"
    ],
    "wof:name":"Nizhneye Babalarovo",
    "wof:placetype":"locality"
},
  "geometry": {"coordinates":[55.5311,52.4013],"type":"Point"}
}