{
  "type": "Feature",
  "properties": {
    "gn:admin1_code":"23",
    "gn:asciiname":"Burgino",
    "gn:country_code":"RU",
    "gn:dem":24,
    "gn:feature_class":"P",
    "gn:feature_code":"PPL",
    "gn:name":"Burgino",
    "gn:population":0,
    "gn:timezone":"Europe/Kaliningrad",
    "iso:country":"RU",
    "name:rus_x_preferred":[
        "\u0411\u0443\u0440\u0433\u0438\u043d\u043e"
    ],
    "name:und_x_variant":[
        "Charlottenhof",
        "Burgino"
    ],
    "wof:name":"Burgino",
    "wof:placetype":"locality"
},
  "geometry": {"coordinates":[20.53443,54.59133000000001],"type":"Point"}
}