{
  "type": "Feature",
  "properties": {
    "gn:admin1_code":"16",
    "gn:asciiname":"Polevyye Yaushi",
    "gn:country_code":"RU",
    "gn:dem":150,
    "gn:feature_class":"P",
    "gn:feature_code":"PPL",
    "gn:name":"Polevyye Yaushi",
    "gn:population":0,
    "gn:timezone":"Europe/Moscow",
    "iso:country":"RU",
    "name:rus_x_preferred":[
        "\u041f\u043e\u043b\u0435\u0432\u044b\u0435 \u042f\u0443\u0448\u0438"
    ],
    "name:und_x_variant":[
        "Polevo-Yaushi",
        "Polevyye Yaushi"
    ],
    "wof:name":"Polevyye Yaushi",
    "wof:placetype":"locality"
},
  "geometry": {"coordinates":[47.48896,55.18012],"type":"Point"}
}