{
  "type": "Feature",
  "properties": {
    "gn:admin1_code":"86",
    "gn:asciiname":"Sklyayevo Vtoroye",
    "gn:country_code":"RU",
    "gn:dem":125,
    "gn:feature_class":"P",
    "gn:feature_code":"PPL",
    "gn:name":"Sklyayevo Vtoroye",
    "gn:population":0,
    "gn:timezone":"Europe/Moscow",
    "iso:country":"RU",
    "name:rus_x_preferred":[
        "\u0421\u043a\u043b\u044f\u0435\u0432\u043e \u0412\u0442\u043e\u0440\u043e\u0435"
    ],
    "name:und_x_variant":[
        "Timoshino",
        "Sklyayevo Vtoroye"
    ],
    "wof:name":"Sklyayevo Vtoroye",
    "wof:placetype":"locality"
},
  "geometry": {"coordinates":[39.03226,51.9546],"type":"Point"}
}