{
  "type": "Feature",
  "properties": {
    "gn:admin1_code":"17",
    "gn:admin2_code":"571887",
    "gn:asciiname":"Ashino",
    "gn:country_code":"RU",
    "gn:dem":986,
    "gn:feature_class":"P",
    "gn:feature_code":"PPL",
    "gn:name":"Ashino",
    "gn:population":0,
    "gn:timezone":"Europe/Moscow",
    "iso:country":"RU",
    "name:nor_x_preferred":[
        "Asjino"
    ],
    "name:rus_x_preferred":[
        "\u0410\u0448\u0438\u043d\u043e"
    ],
    "wof:name":"Ashino",
    "wof:placetype":"locality"
},
  "geometry": {"coordinates":[46.1631,42.68199],"type":"Point"}
}