{
  "type": "Feature",
  "properties": {
    "gn:admin1_code":"91",
    "gn:asciiname":"Tembenchi",
    "gn:cc2":"RU",
    "gn:country_code":"RU",
    "gn:dem":185,
    "gn:feature_class":"P",
    "gn:feature_code":"PPL",
    "gn:name":"Tembenchi",
    "gn:population":0,
    "gn:timezone":"Asia/Krasnoyarsk",
    "iso:country":"RU",
    "name:und_x_variant":[
        "Tembenchi-Burungda",
        "Tembenchi"
    ],
    "wof:name":"Tembenchi",
    "wof:placetype":"locality"
},
  "geometry": {"coordinates":[98.84999999999999,64.95],"type":"Point"}
}