{
  "type": "Feature",
  "properties": {
    "gn:admin1_code":"70.0",
    "gn:asciiname":"Uspenovka",
    "gn:country_code":"RU",
    "gn:dem":381,
    "gn:feature_class":"P",
    "gn:feature_code":"PPL",
    "gn:name":"Uspenovka",
    "gn:population":0,
    "gn:timezone":"Europe/Moscow",
    "iso:country":"RU",
    "name:rus_x_preferred":[
        "\u0423\u0441\u043f\u0435\u043d\u043e\u0432\u043a\u0430"
    ],
    "name:und_x_variant":[
        "\u0423\u0441\u043f\u0435\u043d\u043e\u0432\u043a\u0430"
    ],
    "wof:name":"Uspenovka",
    "wof:placetype":"locality"
},
  "geometry": {"coordinates":[42.8504,44.2312],"type":"Point"}
}