{
  "type": "Feature",
  "properties": {
    "gn:admin1_code":"33",
    "gn:asciiname":"Machikhino",
    "gn:country_code":"RU",
    "gn:dem":168,
    "gn:feature_class":"P",
    "gn:feature_code":"PPL",
    "gn:name":"Machikhino",
    "gn:population":0,
    "gn:timezone":"Europe/Kirov",
    "iso:country":"RU",
    "name:rus_x_preferred":[
        "\u041c\u0430\u0447\u0438\u0445\u0438\u043d\u043e"
    ],
    "name:und_x_variant":[
        "\u041c\u0430\u0447\u0438\u0445\u0438\u043d\u043e"
    ],
    "wof:name":"Machikhino",
    "wof:placetype":"locality"
},
  "geometry": {"coordinates":[49.96667,57.15],"type":"Point"}
}