{
  "type": "Feature",
  "properties": {
    "gn:admin1_code":"28",
    "gn:asciiname":"Kalattoma",
    "gn:country_code":"RU",
    "gn:dem":97,
    "gn:feature_class":"P",
    "gn:feature_code":"PPL",
    "gn:name":"Kalattoma",
    "gn:population":0,
    "gn:timezone":"Europe/Moscow",
    "iso:country":"RU",
    "name:fin_x_preferred":[
        "Kalattoma"
    ],
    "name:rus_x_preferred":[
        "\u041a\u0430\u043b\u0430\u0442\u0442\u043e\u043c\u0430"
    ],
    "wof:name":"Kalattoma",
    "wof:placetype":"locality"
},
  "geometry": {"coordinates":[30.18734000000001,61.8278],"type":"Point"}
}