{
  "type": "Feature",
  "properties": {
    "gn:admin1_code":"33",
    "gn:asciiname":"Severnyye Polyanki",
    "gn:country_code":"RU",
    "gn:dem":102,
    "gn:feature_class":"P",
    "gn:feature_code":"PPL",
    "gn:name":"Severnyye Polyanki",
    "gn:population":0,
    "gn:timezone":"Europe/Kirov",
    "iso:country":"RU",
    "name:rus_x_preferred":[
        "\u0421\u0435\u0432\u0435\u0440\u043d\u044b\u0435 \u041f\u043e\u043b\u044f\u043d\u043a\u0438"
    ],
    "name:und_x_variant":[
        "\u0421\u0435\u0432\u0435\u0440\u043d\u044b\u0435 \u041f\u043e\u043b\u044f\u043d\u043a\u0438"
    ],
    "wof:name":"Severnyye Polyanki",
    "wof:placetype":"locality"
},
  "geometry": {"coordinates":[47.5511,60.7496],"type":"Point"}
}