{
  "type": "Feature",
  "properties": {
    "gn:admin1_code":"16",
    "gn:asciiname":"Staroye Akhperdino",
    "gn:country_code":"RU",
    "gn:dem":127,
    "gn:feature_class":"P",
    "gn:feature_code":"PPL",
    "gn:name":"Staroye Akhperdino",
    "gn:population":0,
    "gn:timezone":"Europe/Moscow",
    "iso:country":"RU",
    "name:rus_x_preferred":[
        "\u0421\u0442\u0430\u0440\u043e\u0435 \u0410\u0445\u043f\u0435\u0440\u0434\u0438\u043d\u043e"
    ],
    "name:und_x_variant":[
        "Staryye Akhperdino",
        "Staroye Akhperdino"
    ],
    "wof:name":"Staroye Akhperdino",
    "wof:placetype":"locality"
},
  "geometry": {"coordinates":[47.61965,55.47322],"type":"Point"}
}