{
  "type": "Feature",
  "properties": {
    "gn:admin1_code":"41",
    "gn:asciiname":"Imeni Chapayeva",
    "gn:country_code":"RU",
    "gn:dem":164,
    "gn:feature_class":"P",
    "gn:feature_code":"PPL",
    "gn:name":"Imeni Chapayeva",
    "gn:population":0,
    "gn:timezone":"Europe/Moscow",
    "iso:country":"RU",
    "name:rus_x_preferred":[
        "\u0418\u043c\u0435\u043d\u0438 \u0427\u0430\u043f\u0430\u0435\u0432\u0430"
    ],
    "wof:name":"Imeni Chapayeva",
    "wof:placetype":"locality"
},
  "geometry": {"coordinates":[34.9654,51.9509],"type":"Point"}
}