{
  "type": "Feature",
  "properties": {
    "gn:admin1_code":"33",
    "gn:asciiname":"Kashkalovo",
    "gn:country_code":"RU",
    "gn:dem":199,
    "gn:feature_class":"P",
    "gn:feature_code":"PPL",
    "gn:name":"Kashkalovo",
    "gn:population":0,
    "gn:timezone":"Europe/Kirov",
    "iso:country":"RU",
    "name:rus_x_preferred":[
        "\u041a\u0430\u0448\u043a\u0430\u043b\u043e\u0432\u043e"
    ],
    "wof:name":"Kashkalovo",
    "wof:placetype":"locality"
},
  "geometry": {"coordinates":[49.0743,58.0857],"type":"Point"}
}