{
  "type": "Feature",
  "properties": {
    "gn:admin1_code":"12.0",
    "gn:asciiname":"Chaynari",
    "gn:country_code":"RU",
    "gn:dem":1830,
    "gn:feature_class":"P",
    "gn:feature_code":"PPL",
    "gn:name":"Chaynari",
    "gn:population":0,
    "gn:timezone":"Europe/Moscow",
    "iso:country":"RU",
    "name:rus_x_preferred":[
        "\u0427\u0430\u0439\u043d\u0430\u0440\u0438"
    ],
    "wof:name":"Chaynari",
    "wof:placetype":"locality"
},
  "geometry": {"coordinates":[45.69028,42.7125],"type":"Point"}
}