{
  "type": "Feature",
  "properties": {
    "gn:admin1_code":"31",
    "gn:asciiname":"Imeni Il'icha",
    "gn:country_code":"RU",
    "gn:dem":313,
    "gn:feature_class":"P",
    "gn:feature_code":"PPL",
    "gn:name":"Imeni Il\u2019icha",
    "gn:population":0,
    "gn:timezone":"Asia/Krasnoyarsk",
    "iso:country":"RU",
    "name:eng_x_preferred":[
        "Imeni Il'icha"
    ],
    "name:nor_x_preferred":[
        "im.Ilitsja"
    ],
    "name:rus_x_preferred":[
        "\u0438\u043c.\u0418\u043b\u044c\u0438\u0447\u0430"
    ],
    "name:rus_x_variant":[
        "\u0418\u043c\u0435\u043d\u0438 \u0418\u043b\u044c\u0438\u0447\u0430"
    ],
    "name:und_x_variant":[
        "Poselok Imeni Il\u2019icha",
        "Kar\u2019yer",
        "Imeni Il\u2019icha"
    ],
    "wof:name":"Imeni Il'icha",
    "wof:placetype":"locality"
},
  "geometry": {"coordinates":[90.92944,53.51556],"type":"Point"}
}