{
  "type": "Feature",
  "properties": {
    "gn:admin1_code":"21.0",
    "gn:asciiname":"Leonidovo",
    "gn:country_code":"RU",
    "gn:dem":115,
    "gn:feature_class":"P",
    "gn:feature_code":"PPL",
    "gn:name":"Leonidovo",
    "gn:population":0,
    "gn:timezone":"Europe/Moscow",
    "iso:country":"RU",
    "name:rus_x_preferred":[
        "\u041b\u0435\u043e\u043d\u0438\u0434\u043e\u0432\u043e"
    ],
    "name:und_x_variant":[
        "\u041b\u0435\u043e\u043d\u0438\u0434\u043e\u0432\u043e"
    ],
    "wof:name":"Leonidovo",
    "wof:placetype":"locality"
},
  "geometry": {"coordinates":[42.90919,57.05362],"type":"Point"}
}