{
  "type": "Feature",
  "properties": {
    "gn:admin1_code":"17.0",
    "gn:asciiname":"Darada",
    "gn:country_code":"RU",
    "gn:dem":1532,
    "gn:feature_class":"P",
    "gn:feature_code":"PPL",
    "gn:name":"Darada",
    "gn:population":0,
    "gn:timezone":"Europe/Moscow",
    "iso:country":"RU",
    "name:rus_x_preferred":[
        "\u0414\u0430\u0440\u0430\u0434\u0430"
    ],
    "wof:name":"Darada",
    "wof:placetype":"locality"
},
  "geometry": {"coordinates":[46.93874,42.46443],"type":"Point"}
}