{
  "type": "Feature",
  "properties": {
    "gn:admin1_code":"40",
    "gn:asciiname":"Berdyuzhka",
    "gn:country_code":"RU",
    "gn:dem":131,
    "gn:feature_class":"P",
    "gn:feature_code":"PPL",
    "gn:name":"Berdyuzhka",
    "gn:population":0,
    "gn:timezone":"Asia/Yekaterinburg",
    "iso:country":"RU",
    "name:nor_x_preferred":[
        "Berdjuzjka"
    ],
    "name:rus_x_preferred":[
        "\u0411\u0435\u0440\u0434\u044e\u0436\u043a\u0430"
    ],
    "wof:name":"Berdyuzhka",
    "wof:placetype":"locality"
},
  "geometry": {"coordinates":[68.12416999999999,55.31944],"type":"Point"}
}