{
  "type": "Feature",
  "properties": {
    "gn:admin1_code":"80.0",
    "gn:asciiname":"Kirenki",
    "gn:country_code":"RU",
    "gn:dem":248,
    "gn:feature_class":"P",
    "gn:feature_code":"PPL",
    "gn:name":"Kirenki",
    "gn:population":0,
    "gn:timezone":"Europe/Samara",
    "iso:country":"RU",
    "name:rus_x_preferred":[
        "\u041a\u0438\u0440\u0435\u043d\u043a\u0438"
    ],
    "wof:name":"Kirenki",
    "wof:placetype":"locality"
},
  "geometry": {"coordinates":[53.2895,58.2668],"type":"Point"}
}