{
  "type": "Feature",
  "properties": {
    "gn:admin1_code":"51",
    "gn:asciiname":"Zubilikha",
    "gn:country_code":"RU",
    "gn:dem":125,
    "gn:feature_class":"P",
    "gn:feature_code":"PPL",
    "gn:name":"Zubilikha",
    "gn:population":0,
    "gn:timezone":"Europe/Moscow",
    "iso:country":"RU",
    "name:rus_x_preferred":[
        "\u0417\u0443\u0431\u0438\u043b\u0438\u0445\u0430"
    ],
    "name:und_x_variant":[
        "\u0417\u0443\u0431\u0438\u043b\u0438\u0445\u0430"
    ],
    "wof:name":"Zubilikha",
    "wof:placetype":"locality"
},
  "geometry": {"coordinates":[45.14409000000001,57.06504],"type":"Point"}
}