{
  "type": "Feature",
  "properties": {
    "gn:admin1_code":"17",
    "gn:asciiname":"Tselyagyun",
    "gn:country_code":"RU",
    "gn:dem":412,
    "gn:feature_class":"P",
    "gn:feature_code":"PPL",
    "gn:name":"Tselyagyun",
    "gn:population":0,
    "gn:timezone":"Europe/Moscow",
    "iso:country":"RU",
    "name:rus_x_preferred":[
        "\u0426\u0435\u043b\u044f\u0433\u044e\u043d"
    ],
    "name:und_x_variant":[
        "Tselegyun",
        "Tselyagyun"
    ],
    "wof:name":"Tselyagyun",
    "wof:placetype":"locality"
},
  "geometry": {"coordinates":[48.29539000000001,41.66065],"type":"Point"}
}