{
  "type": "Feature",
  "properties": {
    "gn:admin1_code":"21.0",
    "gn:asciiname":"Chertoviki",
    "gn:country_code":"RU",
    "gn:dem":115,
    "gn:feature_class":"P",
    "gn:feature_code":"PPL",
    "gn:name":"Chertoviki",
    "gn:population":0,
    "gn:timezone":"Europe/Moscow",
    "iso:country":"RU",
    "name:eng_x_preferred":[
        "Chertoviki"
    ],
    "name:nor_x_preferred":[
        "Tsjertoviki"
    ],
    "name:rus_x_preferred":[
        "\u0427\u0435\u0440\u0442\u043e\u0432\u0438\u043a\u0438"
    ],
    "wof:name":"Chertoviki",
    "wof:placetype":"locality"
},
  "geometry": {"coordinates":[40.95614000000001,56.55124],"type":"Point"}
}