{
  "type": "Feature",
  "properties": {
    "gn:admin1_code":"9.0",
    "gn:asciiname":"Shirokiy Gul",
    "gn:country_code":"RU",
    "gn:dem":213,
    "gn:feature_class":"P",
    "gn:feature_code":"PPL",
    "gn:name":"Shirokiy Gul",
    "gn:population":0,
    "gn:timezone":"Europe/Moscow",
    "iso:country":"RU",
    "wof:name":"Shirokiy Gul",
    "wof:placetype":"locality"
},
  "geometry": {"coordinates":[37.36972,50.7975],"type":"Point"}
}