{
  "type": "Feature",
  "properties": {
    "gn:country":"RU",
    "gn:fcode":"PPL",
    "gn:population":2614,
    "iso:country":"RU",
    "name:eng_x_preferred":[
        "Luknovo"
    ],
    "name:nor_x_preferred":[
        "Luknovo"
    ],
    "name:rus_x_preferred":[
        "\u041b\u0443\u043a\u043d\u043e\u0432\u043e"
    ],
    "qs:name":"Luknovo",
    "qs:name_adm0":"Russia",
    "qs:name_adm1":"Vladimir Oblast",
    "qs:photos_9r":0,
    "qs:photos_sr":0,
    "qs:placetype":"Town",
    "qs:pop_sr":"4",
    "wof:name":"Luknovo",
    "wof:placetype":"locality",
    "wof:population":2614
},
  "geometry": {"coordinates":[42.03987,56.18045],"type":"Point"}
}