{
  "type": "Feature",
  "properties": {
    "gn:admin1_code":"69",
    "gn:asciiname":"Yegorovka",
    "gn:country_code":"RU",
    "gn:dem":186,
    "gn:feature_class":"P",
    "gn:feature_code":"PPL",
    "gn:name":"Yegorovka",
    "gn:population":0,
    "gn:timezone":"Europe/Moscow",
    "iso:country":"RU",
    "name:bak_x_preferred":[
        "\u0415\u0433\u043e\u0440\u043e\u0432\u043a\u0430"
    ],
    "name:che_x_preferred":[
        "\u0415\u0433\u043e\u0440\u043e\u0432\u043a\u0430"
    ],
    "name:hye_x_preferred":[
        "\u0535\u0563\u0578\u0580\u0578\u057e\u056f\u0561"
    ],
    "name:kaz_x_preferred":[
        "\u0415\u0433\u043e\u0440\u043e\u0432\u043a\u0430"
    ],
    "name:kir_x_preferred":[
        "\u0415\u0433\u043e\u0440\u043e\u0432\u043a\u0430"
    ],
    "name:rus_x_preferred":[
        "\u0415\u0433\u043e\u0440\u043e\u0432\u043a\u0430"
    ],
    "name:tat_x_preferred":[
        "\u0415\u0433\u043e\u0440\u043e\u0432\u043a\u0430"
    ],
    "name:ukr_x_preferred":[
        "\u0404\u0433\u043e\u0440\u043e\u0432\u043a\u0430"
    ],
    "wof:name":"Yegorovka",
    "wof:placetype":"locality"
},
  "geometry": {"coordinates":[32.81667,53.65],"type":"Point"}
}