{
  "type": "Feature",
  "properties": {
    "gn:admin1_code":"60",
    "gn:asciiname":"Sherstinovo",
    "gn:country_code":"RU",
    "gn:dem":200,
    "gn:feature_class":"P",
    "gn:feature_code":"PPL",
    "gn:name":"Sherstinovo",
    "gn:population":0,
    "gn:timezone":"Europe/Moscow",
    "iso:country":"RU",
    "name:rus_x_preferred":[
        "\u0428\u0435\u0440\u0441\u0442\u0438\u043d\u043e\u0432\u043e"
    ],
    "wof:name":"Sherstinovo",
    "wof:placetype":"locality"
},
  "geometry": {"coordinates":[29.8162,56.6129],"type":"Point"}
}