{
  "type": "Feature",
  "properties": {
    "gn:admin1_code":"51",
    "gn:asciiname":"Lazazey",
    "gn:country_code":"RU",
    "gn:dem":125,
    "gn:feature_class":"P",
    "gn:feature_code":"PPL",
    "gn:name":"Lazazey",
    "gn:population":0,
    "gn:timezone":"Europe/Moscow",
    "iso:country":"RU",
    "name:rus_x_preferred":[
        "\u041b\u0430\u0437\u0430\u0437\u0435\u0439"
    ],
    "name:und_x_variant":[
        "\u041b\u0430\u0437\u0430\u0437\u0435\u0439"
    ],
    "wof:name":"Lazazey",
    "wof:placetype":"locality"
},
  "geometry": {"coordinates":[44.18131,55.842],"type":"Point"}
}