{
  "type": "Feature",
  "properties": {
    "gn:admin1_code":"88",
    "gn:asciiname":"Uslavtsevo",
    "gn:country_code":"RU",
    "gn:dem":118,
    "gn:feature_class":"P",
    "gn:feature_code":"PPL",
    "gn:name":"Uslavtsevo",
    "gn:population":0,
    "gn:timezone":"Europe/Moscow",
    "iso:country":"RU",
    "name:rus_x_preferred":[
        "\u0423\u0441\u043b\u0430\u0432\u0446\u0435\u0432\u043e"
    ],
    "wof:name":"Uslavtsevo",
    "wof:placetype":"locality"
},
  "geometry": {"coordinates":[39.13867,57.38423],"type":"Point"}
}