{
  "type": "Feature",
  "properties": {
    "gn:admin1_code":"61",
    "gn:asciiname":"Ostradnaya",
    "gn:country_code":"RU",
    "gn:dem":116,
    "gn:feature_class":"P",
    "gn:feature_code":"PPL",
    "gn:name":"Ostradnaya",
    "gn:population":0,
    "gn:timezone":"Europe/Moscow",
    "iso:country":"RU",
    "name:rus_x_preferred":[
        "\u041e\u0441\u0442\u0440\u0430\u0434\u043d\u0430\u044f"
    ],
    "wof:name":"Ostradnaya",
    "wof:placetype":"locality"
},
  "geometry": {"coordinates":[43.1716,47.40032],"type":"Point"}
}