{
  "type": "Feature",
  "properties": {
    "gn:admin1_code":"86",
    "gn:asciiname":"Tulubovskaya",
    "gn:country_code":"RU",
    "gn:dem":129,
    "gn:feature_class":"P",
    "gn:feature_code":"PPL",
    "gn:name":"Tulubovskaya",
    "gn:population":0,
    "gn:timezone":"Europe/Moscow",
    "iso:country":"RU",
    "name:rus_x_preferred":[
        "\u0422\u0443\u043b\u0443\u0431\u043e\u0432\u0441\u043a\u0430\u044f"
    ],
    "wof:name":"Tulubovskaya",
    "wof:placetype":"locality"
},
  "geometry": {"coordinates":[38.7341,51.6212],"type":"Point"}
}