{
  "type": "Feature",
  "properties": {
    "gn:country":"RU",
    "gn:fcode":"PPLX",
    "gn:pop":10641,
    "iso:country":"RU",
    "name:bel_x_preferred":[
        "\u0421\u043e\u043d\u0435\u0447\u043d\u044b"
    ],
    "name:ceb_x_preferred":[
        "\u0421\u043e\u043b\u043d\u0435\u0447\u043d\u044b\u0439"
    ],
    "name:deu_x_preferred":[
        "Solnetschny"
    ],
    "name:hun_x_preferred":[
        "Szolnyecsnij"
    ],
    "name:hye_x_preferred":[
        "\u054d\u0578\u056c\u0576\u0565\u0579\u0576\u056b"
    ],
    "name:rus_x_preferred":[
        "\u0421\u043e\u043b\u043d\u0435\u0447\u043d\u044b\u0439"
    ],
    "name:ukr_x_preferred":[
        "\u0421\u043e\u043b\u043d\u0435\u0447\u043d\u0438\u0439"
    ],
    "name:unk_x_variant":[
        "Uzhur-4"
    ],
    "qs:name":"Solnechnyy",
    "qs:photos_9r":0,
    "qs:photos_sr":0,
    "qs:pop_sr":"6",
    "wd:wordcount":55,
    "wof:name":"Solnechnyy",
    "wof:placetype":"neighbourhood",
    "wof:population":10641
},
  "geometry": {"coordinates":[92.92528,56.11583],"type":"Point"}
}