{
  "type": "Feature",
  "properties": {
    "gn:admin1_code":"8",
    "gn:asciiname":"Solenyy",
    "gn:country_code":"RU",
    "gn:dem":187,
    "gn:feature_class":"P",
    "gn:feature_code":"PPL",
    "gn:name":"Sol\u00ebnyy",
    "gn:population":0,
    "gn:timezone":"Asia/Yekaterinburg",
    "iso:country":"RU",
    "name:rus_x_preferred":[
        "\u0421\u043e\u043b\u0451\u043d\u044b\u0439"
    ],
    "name:und_x_variant":[
        "Sol\u00ebnyy",
        "\u0421\u043e\u043b\u0451\u043d\u044b\u0439"
    ],
    "wof:name":"Solenyy",
    "wof:placetype":"locality"
},
  "geometry": {"coordinates":[56.26667,53.55],"type":"Point"}
}