{
  "type": "Feature",
  "properties": {
    "gn:admin1_code":"61",
    "gn:asciiname":"Pushkin",
    "gn:country_code":"RU",
    "gn:dem":154,
    "gn:feature_class":"P",
    "gn:feature_code":"PPL",
    "gn:name":"Pushkin",
    "gn:population":0,
    "gn:timezone":"Europe/Moscow",
    "iso:country":"RU",
    "name:rus_x_preferred":[
        "\u041f\u0443\u0448\u043a\u0438\u043d"
    ],
    "name:und_x_variant":[
        "\u041f\u0443\u0448\u043a\u0438\u043d"
    ],
    "wof:name":"Pushkin",
    "wof:placetype":"locality"
},
  "geometry": {"coordinates":[40.15336,47.82339],"type":"Point"}
}