{
  "type": "Feature",
  "properties": {
    "gn:admin1_code":"34",
    "gn:asciiname":"Yerozdino",
    "gn:country_code":"RU",
    "gn:dem":81,
    "gn:feature_class":"P",
    "gn:feature_code":"PPL",
    "gn:name":"Yerozdino",
    "gn:population":0,
    "gn:timezone":"Europe/Moscow",
    "iso:country":"RU",
    "name:eng_x_preferred":[
        "Yerozdino"
    ],
    "name:nor_x_preferred":[
        "Jerozdino"
    ],
    "name:rus_x_preferred":[
        "\u0415\u0440\u043e\u0437\u0434\u0438\u043d\u043e"
    ],
    "wof:name":"Yerozdino",
    "wof:placetype":"locality"
},
  "geometry": {"coordinates":[50.56667,62.26667],"type":"Point"}
}