{
  "type": "Feature",
  "properties": {
    "gn:admin1_code":"59.0",
    "gn:asciiname":"Lozovyy",
    "gn:country_code":"RU",
    "gn:dem":78,
    "gn:feature_class":"P",
    "gn:feature_code":"PPL",
    "gn:name":"Lozovyy",
    "gn:population":0,
    "gn:timezone":"Asia/Vladivostok",
    "iso:country":"RU",
    "name:rus_x_preferred":[
        "\u041b\u043e\u0437\u043e\u0432\u044b\u0439"
    ],
    "wof:name":"Lozovyy",
    "wof:placetype":"locality"
},
  "geometry": {"coordinates":[133.11893999999998,43.06388],"type":"Point"}
}