{
  "type": "Feature",
  "properties": {
    "gn:admin1_code":"77.0",
    "gn:asciiname":"Bol'shiye Ledinki",
    "gn:country_code":"RU",
    "gn:dem":203,
    "gn:feature_class":"P",
    "gn:feature_code":"PPL",
    "gn:name":"Bol\u2019shiye Ledinki",
    "gn:population":0,
    "gn:timezone":"Europe/Moscow",
    "iso:country":"RU",
    "name:eng_x_preferred":[
        "Bol'shiye Ledinki"
    ],
    "name:nor_x_preferred":[
        "Ledinki"
    ],
    "name:rus_x_preferred":[
        "\u041b\u0435\u0434\u0438\u043d\u043a\u0438"
    ],
    "name:rus_x_variant":[
        "\u0411\u043e\u043b\u044c\u0448\u0438\u0435 \u041b\u0435\u0434\u0438\u043d\u043a\u0438"
    ],
    "name:und_x_variant":[
        "Bol\u2019shiye Ledinki"
    ],
    "wof:name":"Bol'shiye Ledinki",
    "wof:placetype":"locality"
},
  "geometry": {"coordinates":[34.97446,56.45755],"type":"Point"}
}