{
  "type": "Feature",
  "properties": {
    "gn:admin1_code":"53",
    "gn:asciiname":"Stepnoy",
    "gn:country_code":"RU",
    "gn:dem":182,
    "gn:feature_class":"P",
    "gn:feature_code":"PPL",
    "gn:name":"Stepnoy",
    "gn:population":0,
    "gn:timezone":"Asia/Novosibirsk",
    "iso:country":"RU",
    "name:eng_x_preferred":[
        "Stepnoy"
    ],
    "name:nor_x_preferred":[
        "Stepnoj"
    ],
    "name:rus_x_preferred":[
        "\u0421\u0442\u0435\u043f\u043d\u043e\u0439"
    ],
    "name:und_x_variant":[
        "Vtoroy Kochen\u00ebvskiy",
        "\u0421\u0442\u0435\u043f\u043d\u043e\u0439",
        "Stepnoy"
    ],
    "wof:name":"Stepnoy",
    "wof:placetype":"locality"
},
  "geometry": {"coordinates":[82.1108,54.6892],"type":"Point"}
}