{
  "type": "Feature",
  "properties": {
    "gn:admin1_code":"85",
    "gn:asciiname":"Pavshozero",
    "gn:cc2":"RU",
    "gn:country_code":"RU",
    "gn:dem":212,
    "gn:feature_class":"P",
    "gn:feature_code":"PPL",
    "gn:name":"Pavshozero",
    "gn:population":0,
    "gn:timezone":"Europe/Moscow",
    "iso:country":"RU",
    "name:rus_x_preferred":[
        "\u041f\u0430\u0432\u0448\u043e\u0437\u0435\u0440\u043e"
    ],
    "name:und_x_variant":[
        "Pau\u0161j\u00e4rvi",
        "Pavshozero"
    ],
    "wof:name":"Pavshozero",
    "wof:placetype":"locality"
},
  "geometry": {"coordinates":[35.56667,60.63333000000001],"type":"Point"}
}