{
  "type": "Feature",
  "properties": {
    "gn:admin1_code":"51.0",
    "gn:asciiname":"Meshkovo",
    "gn:country_code":"RU",
    "gn:dem":114,
    "gn:feature_class":"P",
    "gn:feature_code":"PPL",
    "gn:name":"Meshkovo",
    "gn:population":0,
    "gn:timezone":"Europe/Moscow",
    "iso:country":"RU",
    "name:che_x_preferred":[
        "\u041c\u0435\u0448\u043a\u043e\u0432\u043e"
    ],
    "name:nor_x_preferred":[
        "Mesjkovo"
    ],
    "name:rus_x_preferred":[
        "\u041c\u0435\u0448\u043a\u043e\u0432\u043e"
    ],
    "name:tgk_x_preferred":[
        "\u041c\u0435\u0448\u043a\u043e\u0432\u043e"
    ],
    "wof:name":"Meshkovo",
    "wof:placetype":"locality"
},
  "geometry": {"coordinates":[43.96864,57.01703000000001],"type":"Point"}
}