{
  "type": "Feature",
  "properties": {
    "gn:admin1_code":"72",
    "gn:asciiname":"Kochetovka",
    "gn:country_code":"RU",
    "gn:dem":139,
    "gn:feature_class":"P",
    "gn:feature_code":"PPL",
    "gn:name":"Kochetovka",
    "gn:population":0,
    "gn:timezone":"Europe/Moscow",
    "iso:country":"RU",
    "name:rus_x_preferred":[
        "\u041a\u043e\u0447\u0435\u0442\u043e\u0432\u043a\u0430"
    ],
    "wof:name":"Kochetovka",
    "wof:placetype":"locality"
},
  "geometry": {"coordinates":[40.09167,52.57083000000001],"type":"Point"}
}