{
  "type": "Feature",
  "properties": {
    "gn:admin1_code":"52",
    "gn:asciiname":"Sokol'ye",
    "gn:country_code":"RU",
    "gn:dem":77,
    "gn:feature_class":"P",
    "gn:feature_code":"PPL",
    "gn:name":"Sokol\u2019ye",
    "gn:population":0,
    "gn:timezone":"Europe/Moscow",
    "iso:country":"RU",
    "name:eng_x_preferred":[
        "Sokol'ye"
    ],
    "name:nor_x_preferred":[
        "Sokolje"
    ],
    "name:rus_x_preferred":[
        "\u0421\u043e\u043a\u043e\u043b\u044c\u0435"
    ],
    "name:und_x_variant":[
        "Szokolja",
        "Sokolje",
        "\u0421\u043e\u043a\u043e\u043b\u044c\u0435",
        "Sokol\u2019ye"
    ],
    "wof:name":"Sokol'ye",
    "wof:placetype":"locality"
},
  "geometry": {"coordinates":[31.08292,57.44974000000001],"type":"Point"}
}