{
  "type": "Feature",
  "properties": {
    "gn:admin1_code":"84",
    "gn:asciiname":"Teterevyatka",
    "gn:country_code":"RU",
    "gn:dem":236,
    "gn:feature_class":"P",
    "gn:feature_code":"PPL",
    "gn:name":"Teterevyatka",
    "gn:population":0,
    "gn:timezone":"Europe/Volgograd",
    "iso:country":"RU",
    "name:eng_x_preferred":[
        "Teterevyatka"
    ],
    "name:nor_x_preferred":[
        "Teterevjatka"
    ],
    "name:rus_x_preferred":[
        "\u0422\u0435\u0442\u0435\u0440\u0435\u0432\u044f\u0442\u043a\u0430"
    ],
    "wof:name":"Teterevyatka",
    "wof:placetype":"locality"
},
  "geometry": {"coordinates":[45.13505,50.66367],"type":"Point"}
}