{
  "type": "Feature",
  "properties": {
    "gn:admin1_code":"73",
    "gn:asciiname":"Yanga-Ural",
    "gn:country_code":"RU",
    "gn:dem":140,
    "gn:feature_class":"P",
    "gn:feature_code":"PPL",
    "gn:name":"Yanga-Ural",
    "gn:population":0,
    "gn:timezone":"Europe/Moscow",
    "iso:country":"RU",
    "name:rus_x_preferred":[
        "\u042f\u043d\u0433\u0430-\u0423\u0440\u0430\u043b"
    ],
    "name:und_x_variant":[
        "Yanga",
        "Yanga-Ural"
    ],
    "wof:name":"Yanga-Ural",
    "wof:placetype":"locality"
},
  "geometry": {"coordinates":[50.64847,55.18936],"type":"Point"}
}