{
  "type": "Feature",
  "properties": {
    "gn:admin1_code":"90",
    "gn:asciiname":"Mokhovoye",
    "gn:country_code":"RU",
    "gn:dem":153,
    "gn:feature_class":"P",
    "gn:feature_code":"PPL",
    "gn:name":"Mokhovoye",
    "gn:population":0,
    "gn:timezone":"Asia/Yekaterinburg",
    "iso:country":"RU",
    "name:rus_x_preferred":[
        "\u041c\u043e\u0445\u043e\u0432\u043e\u0435"
    ],
    "name:und_x_variant":[
        "\u041c\u043e\u0445\u043e\u0432\u043e\u0435"
    ],
    "wof:name":"Mokhovoye",
    "wof:placetype":"locality"
},
  "geometry": {"coordinates":[56.8528,57.6148],"type":"Point"}
}