{
  "type": "Feature",
  "properties": {
    "gn:admin1_code":"88",
    "gn:asciiname":"Arkharovo",
    "gn:country_code":"RU",
    "gn:dem":115,
    "gn:feature_class":"P",
    "gn:feature_code":"PPL",
    "gn:name":"Arkharovo",
    "gn:population":0,
    "gn:timezone":"Europe/Moscow",
    "iso:country":"RU",
    "name:rus_x_preferred":[
        "\u0410\u0440\u0445\u0430\u0440\u043e\u0432\u043e"
    ],
    "wof:name":"Arkharovo",
    "wof:placetype":"locality"
},
  "geometry": {"coordinates":[38.68693,58.01412],"type":"Point"}
}