{
  "type": "Feature",
  "properties": {
    "gn:admin1_code":"88",
    "gn:asciiname":"Lopyrevo",
    "gn:country_code":"RU",
    "gn:dem":118,
    "gn:feature_class":"P",
    "gn:feature_code":"PPL",
    "gn:name":"Lopyr\u00ebvo",
    "gn:population":0,
    "gn:timezone":"Europe/Moscow",
    "iso:country":"RU",
    "name:rus_x_preferred":[
        "\u041b\u043e\u043f\u044b\u0440\u0451\u0432\u043e"
    ],
    "name:und_x_variant":[
        "Lopyr\u00ebvo"
    ],
    "wof:name":"Lopyrevo",
    "wof:placetype":"locality"
},
  "geometry": {"coordinates":[39.3902,57.60761],"type":"Point"}
}