{
  "type": "Feature",
  "properties": {
    "gn:admin1_code":"78",
    "gn:asciiname":"Cherpiya",
    "gn:country_code":"RU",
    "gn:dem":48,
    "gn:feature_class":"P",
    "gn:feature_code":"PPL",
    "gn:name":"Cherpiya",
    "gn:population":0,
    "gn:timezone":"Asia/Yekaterinburg",
    "iso:country":"RU",
    "name:rus_x_preferred":[
        "\u0427\u0435\u0440\u043f\u0438\u044f"
    ],
    "wof:name":"Cherpiya",
    "wof:placetype":"locality"
},
  "geometry": {"coordinates":[68.63333,58.95],"type":"Point"}
}