{
  "type": "Feature",
  "properties": {
    "gn:admin1_code":"42",
    "gn:asciiname":"Samushkino",
    "gn:country_code":"RU",
    "gn:dem":18,
    "gn:feature_class":"P",
    "gn:feature_code":"PPL",
    "gn:name":"Samushkino",
    "gn:population":0,
    "gn:timezone":"Europe/Moscow",
    "iso:country":"RU",
    "name:rus_x_preferred":[
        "\u0421\u0430\u043c\u0443\u0448\u043a\u0438\u043d\u043e"
    ],
    "wof:name":"Samushkino",
    "wof:placetype":"locality"
},
  "geometry": {"coordinates":[32.77403,60.27051],"type":"Point"}
}