{
  "type": "Feature",
  "properties": {
    "gn:admin1_code":"69",
    "gn:asciiname":"Krasitsy",
    "gn:country_code":"RU",
    "gn:dem":201,
    "gn:feature_class":"P",
    "gn:feature_code":"PPL",
    "gn:name":"Krasitsy",
    "gn:population":0,
    "gn:timezone":"Europe/Moscow",
    "iso:country":"RU",
    "name:rus_x_preferred":[
        "\u041a\u0440\u0430\u0441\u0438\u0446\u044b"
    ],
    "name:und_x_variant":[
        "\u041a\u0440\u0430\u0441\u0438\u0446\u044b"
    ],
    "wof:name":"Krasitsy",
    "wof:placetype":"locality"
},
  "geometry": {"coordinates":[34.81317,55.52711],"type":"Point"}
}