{
  "type": "Feature",
  "properties": {
    "gn:admin1_code":"33",
    "gn:asciiname":"Chirukhovskaya",
    "gn:country_code":"RU",
    "gn:dem":143,
    "gn:feature_class":"P",
    "gn:feature_code":"PPL",
    "gn:name":"Chirukhovskaya",
    "gn:population":0,
    "gn:timezone":"Europe/Kirov",
    "iso:country":"RU",
    "name:rus_x_preferred":[
        "\u0427\u0438\u0440\u0443\u0445\u043e\u0432\u0441\u043a\u0430\u044f"
    ],
    "wof:name":"Chirukhovskaya",
    "wof:placetype":"locality"
},
  "geometry": {"coordinates":[47.3465,60.5876],"type":"Point"}
}