{
  "type": "Feature",
  "properties": {
    "gn:admin1_code":"10",
    "gn:asciiname":"Lukavitsa",
    "gn:country_code":"RU",
    "gn:dem":165,
    "gn:feature_class":"P",
    "gn:feature_code":"PPL",
    "gn:name":"Lukavitsa",
    "gn:population":0,
    "gn:timezone":"Europe/Moscow",
    "iso:country":"RU",
    "name:rus_x_preferred":[
        "\u041b\u0443\u043a\u0430\u0432\u0438\u0446\u0430"
    ],
    "wof:name":"Lukavitsa",
    "wof:placetype":"locality"
},
  "geometry": {"coordinates":[32.83909,53.23713000000001],"type":"Point"}
}