{
  "type": "Feature",
  "properties": {
    "gn:admin1_code":"51",
    "gn:asciiname":"Mart'yanovo",
    "gn:country_code":"RU",
    "gn:dem":112,
    "gn:feature_class":"P",
    "gn:feature_code":"PPL",
    "gn:name":"Mart\u2019yanovo",
    "gn:population":0,
    "gn:timezone":"Europe/Moscow",
    "iso:country":"RU",
    "name:rus_x_preferred":[
        "\u041c\u0430\u0440\u0442\u044c\u044f\u043d\u043e\u0432\u043e"
    ],
    "name:und_x_variant":[
        "Mart\u2019yanovo",
        "\u041c\u0430\u0440\u0442\u044c\u044f\u043d\u043e\u0432\u043e"
    ],
    "wof:name":"Mart'yanovo",
    "wof:placetype":"locality"
},
  "geometry": {"coordinates":[45.15565,56.79973],"type":"Point"}
}