{
  "type": "Feature",
  "properties": {
    "gn:admin1_code":"80",
    "gn:asciiname":"Kabanovo",
    "gn:country_code":"RU",
    "gn:dem":212,
    "gn:feature_class":"P",
    "gn:feature_code":"PPL",
    "gn:name":"Kabanovo",
    "gn:population":0,
    "gn:timezone":"Europe/Samara",
    "iso:country":"RU",
    "name:rus_x_preferred":[
        "\u041a\u0430\u0431\u0430\u043d\u043e\u0432\u043e"
    ],
    "wof:name":"Kabanovo",
    "wof:placetype":"locality"
},
  "geometry": {"coordinates":[53.4906,57.4295],"type":"Point"}
}