{
  "type": "Feature",
  "properties": {
    "gn:admin1_code":"4.0",
    "gn:asciiname":"Zagotskot",
    "gn:country_code":"RU",
    "gn:dem":217,
    "gn:feature_class":"P",
    "gn:feature_code":"PPL",
    "gn:name":"Zagotskot",
    "gn:population":0,
    "gn:timezone":"Asia/Barnaul",
    "iso:country":"RU",
    "name:rus_x_preferred":[
        "\u0417\u0430\u0433\u043e\u0442\u0441\u043a\u043e\u0442"
    ],
    "wof:name":"Zagotskot",
    "wof:placetype":"locality"
},
  "geometry": {"coordinates":[84.5157,52.059],"type":"Point"}
}