{
  "type": "Feature",
  "properties": {
    "gn:admin1_code":"12",
    "gn:admin2_code":"Itum-Kalinskiy Rayon",
    "gn:asciiname":"Intsubatu",
    "gn:country_code":"RU",
    "gn:dem":1530,
    "gn:feature_class":"P",
    "gn:feature_code":"PPL",
    "gn:name":"Intsubatu",
    "gn:population":0,
    "gn:timezone":"Europe/Moscow",
    "iso:country":"RU",
    "name:rus_x_preferred":[
        "\u0418\u043d\u0446\u0443\u0431\u0430\u0442\u0443"
    ],
    "wof:name":"Intsubatu",
    "wof:placetype":"locality"
},
  "geometry": {"coordinates":[45.93556,42.645],"type":"Point"}
}