{
  "type": "Feature",
  "properties": {
    "gn:admin1_code":"17",
    "gn:asciiname":"Kulushats",
    "gn:country_code":"RU",
    "gn:dem":1895,
    "gn:feature_class":"P",
    "gn:feature_code":"PPL",
    "gn:name":"Kulushats",
    "gn:population":0,
    "gn:timezone":"Europe/Moscow",
    "iso:country":"RU",
    "name:eng_x_preferred":[
        "Kulushats"
    ],
    "name:nor_x_preferred":[
        "Kulusjats"
    ],
    "name:rus_x_preferred":[
        "\u041a\u0443\u043b\u0443\u0448\u0430\u0446"
    ],
    "name:und_x_variant":[
        "Kulushchats",
        "\u041a\u0443\u043b\u0443\u0448\u0430\u0446",
        "Kulushats"
    ],
    "wof:name":"Kulushats",
    "wof:placetype":"locality"
},
  "geometry": {"coordinates":[47.09752,42.12877],"type":"Point"}
}