{
  "type": "Feature",
  "properties": {
    "gn:admin1_code":"70",
    "gn:asciiname":"Komintern",
    "gn:country_code":"RU",
    "gn:dem":224,
    "gn:feature_class":"P",
    "gn:feature_code":"PPL",
    "gn:name":"Komintern",
    "gn:population":0,
    "gn:timezone":"Europe/Moscow",
    "iso:country":"RU",
    "name:bel_x_preferred":[
        "\u041a\u0430\u043c\u0456\u043d\u0442\u044d\u0440\u043d"
    ],
    "name:ceb_x_preferred":[
        "Komintern"
    ],
    "name:deu_x_preferred":[
        "Komintern"
    ],
    "name:hye_x_preferred":[
        "\u053f\u0578\u0574\u056b\u0576\u057f\u0565\u0580\u0576"
    ],
    "name:kaz_x_preferred":[
        "\u041a\u043e\u043c\u0438\u043d\u0442\u0435\u0440\u043d"
    ],
    "name:pol_x_preferred":[
        "Komintern"
    ],
    "name:rus_x_preferred":[
        "\u041a\u043e\u043c\u0438\u043d\u0442\u0435\u0440\u043d"
    ],
    "name:spa_x_preferred":[
        "Komintern"
    ],
    "name:ukr_x_preferred":[
        "\u041a\u043e\u043c\u0456\u043d\u0442\u0435\u0440\u043d"
    ],
    "wof:name":"Komintern",
    "wof:placetype":"locality"
},
  "geometry": {"coordinates":[42.45,45.16667],"type":"Point"}
}