{
  "type": "Feature",
  "properties": {
    "gn:admin1_code":"41.0",
    "gn:asciiname":"Dar'ino",
    "gn:country_code":"RU",
    "gn:dem":167,
    "gn:feature_class":"P",
    "gn:feature_code":"PPL",
    "gn:name":"Dar\u2019ino",
    "gn:population":0,
    "gn:timezone":"Europe/Moscow",
    "iso:country":"RU",
    "name:rus_x_preferred":[
        "\u0414\u0430\u0440\u044c\u0438\u043d\u043e"
    ],
    "name:und_x_variant":[
        "Dar\u2019ino",
        "\u0414\u0430\u0440\u044c\u0438\u043d\u043e"
    ],
    "wof:name":"Dar'ino",
    "wof:placetype":"locality"
},
  "geometry": {"coordinates":[35.0304,51.2599],"type":"Point"}
}