{
  "type": "Feature",
  "properties": {
    "gn:admin1_code":"16",
    "gn:asciiname":"Oykas-Aslamasy",
    "gn:country_code":"RU",
    "gn:dem":157,
    "gn:feature_class":"P",
    "gn:feature_code":"PPL",
    "gn:name":"Oykas-Aslamasy",
    "gn:population":0,
    "gn:timezone":"Europe/Moscow",
    "iso:country":"RU",
    "name:und_x_variant":[
        "\u041e\u0439\u043a\u0430\u0441-\u0410\u0441\u043b\u0430\u043c\u0430\u0441\u044b"
    ],
    "wof:name":"Oykas-Aslamasy",
    "wof:placetype":"locality"
},
  "geometry": {"coordinates":[46.50028,55.95139],"type":"Point"}
}