{
  "type": "Feature",
  "properties": {
    "gn:admin1_code":"77",
    "gn:asciiname":"Ivankovo",
    "gn:country_code":"RU",
    "gn:dem":194,
    "gn:feature_class":"P",
    "gn:feature_code":"PPL",
    "gn:name":"Ivankovo",
    "gn:population":0,
    "gn:timezone":"Europe/Moscow",
    "iso:country":"RU",
    "name:rus_x_preferred":[
        "\u0418\u0432\u0430\u043d\u043a\u043e\u0432\u043e"
    ],
    "wof:name":"Ivankovo",
    "wof:placetype":"locality"
},
  "geometry": {"coordinates":[34.88333,56.46666999999999],"type":"Point"}
}