{
  "type": "Feature",
  "properties": {
    "gn:admin1_code":"8",
    "gn:asciiname":"Karaberda",
    "gn:country_code":"RU",
    "gn:dem":231,
    "gn:feature_class":"P",
    "gn:feature_code":"PPL",
    "gn:name":"Karaberda",
    "gn:population":0,
    "gn:timezone":"Asia/Yekaterinburg",
    "iso:country":"RU",
    "name:rus_x_preferred":[
        "\u041a\u0430\u0440\u0430\u0431\u0435\u0440\u0434\u0430"
    ],
    "wof:name":"Karaberda",
    "wof:placetype":"locality"
},
  "geometry": {"coordinates":[56.38347,52.27706],"type":"Point"}
}