{
  "type": "Feature",
  "properties": {
    "gn:admin1_code":"21",
    "gn:asciiname":"Pochinki",
    "gn:country_code":"RU",
    "gn:dem":127,
    "gn:feature_class":"P",
    "gn:feature_code":"PPL",
    "gn:name":"Pochinki",
    "gn:population":0,
    "gn:timezone":"Europe/Moscow",
    "iso:country":"RU",
    "name:rus_x_preferred":[
        "\u041f\u043e\u0447\u0438\u043d\u043a\u0438"
    ],
    "name:und_x_variant":[
        "\u041f\u043e\u0447\u0438\u043d\u043a\u0438"
    ],
    "wof:name":"Pochinki",
    "wof:placetype":"locality"
},
  "geometry": {"coordinates":[41.15563,57.02211],"type":"Point"}
}