{
  "type": "Feature",
  "properties": {
    "gn:admin1_code":"67",
    "gn:asciiname":"Nikandrovka",
    "gn:country_code":"RU",
    "gn:dem":170,
    "gn:feature_class":"P",
    "gn:feature_code":"PPL",
    "gn:name":"Nikandrovka",
    "gn:population":0,
    "gn:timezone":"Europe/Saratov",
    "iso:country":"RU",
    "name:rus_x_preferred":[
        "\u041d\u0438\u043a\u0430\u043d\u0434\u0440\u043e\u0432\u043a\u0430"
    ],
    "name:und_x_variant":[
        "\u041d\u0438\u043a\u0430\u043d\u0434\u0440\u043e\u0432\u043a\u0430"
    ],
    "wof:name":"Nikandrovka",
    "wof:placetype":"locality"
},
  "geometry": {"coordinates":[44.55,52.25],"type":"Point"}
}