{
  "type": "Feature",
  "properties": {
    "gn:admin1_code":"51.0",
    "gn:asciiname":"Sadki",
    "gn:country_code":"RU",
    "gn:dem":128,
    "gn:feature_class":"P",
    "gn:feature_code":"PPL",
    "gn:name":"Sadki",
    "gn:population":0,
    "gn:timezone":"Europe/Moscow",
    "iso:country":"RU",
    "name:ceb_x_preferred":[
        "Sadki"
    ],
    "name:nld_x_preferred":[
        "Sadki"
    ],
    "name:nor_x_preferred":[
        "Sadki"
    ],
    "name:pol_x_preferred":[
        "Sadki"
    ],
    "name:rus_x_preferred":[
        "\u0421\u0430\u0434\u043a\u0438"
    ],
    "name:ukr_x_preferred":[
        "\u0421\u0430\u0434\u043a\u0456"
    ],
    "wof:name":"Sadki",
    "wof:placetype":"locality"
},
  "geometry": {"coordinates":[43.55993,56.05972],"type":"Point"}
}