{
  "type": "Feature",
  "properties": {
    "gn:admin1_code":"47",
    "gn:asciiname":"Sukhonovo",
    "gn:country_code":"RU",
    "gn:dem":163,
    "gn:feature_class":"P",
    "gn:feature_code":"PPL",
    "gn:name":"Sukhonovo",
    "gn:population":0,
    "gn:timezone":"Europe/Moscow",
    "iso:country":"RU",
    "name:rus_x_preferred":[
        "\u0421\u0443\u0445\u043e\u043d\u043e\u0432\u043e"
    ],
    "wof:name":"Sukhonovo",
    "wof:placetype":"locality"
},
  "geometry": {"coordinates":[38.65,55.25],"type":"Point"}
}