{
  "type": "Feature",
  "properties": {
    "gn:admin1_code":"37",
    "gn:asciiname":"Nefedovka",
    "gn:country_code":"RU",
    "gn:dem":189,
    "gn:feature_class":"P",
    "gn:feature_code":"PPL",
    "gn:name":"Nefedovka",
    "gn:population":0,
    "gn:timezone":"Europe/Moscow",
    "iso:country":"RU",
    "name:rus_x_preferred":[
        "\u041d\u0435\u0444\u0435\u0434\u043e\u0432\u043a\u0430"
    ],
    "name:und_x_variant":[
        "\u041d\u0435\u0444\u0435\u0434\u043e\u0432\u043a\u0430"
    ],
    "wof:name":"Nefedovka",
    "wof:placetype":"locality"
},
  "geometry": {"coordinates":[46.992,59.0155],"type":"Point"}
}