{
  "type": "Feature",
  "properties": {
    "gn:admin1_code":"83",
    "gn:asciiname":"Kineshemskiy Pogost",
    "gn:country_code":"RU",
    "gn:dem":74,
    "gn:feature_class":"P",
    "gn:feature_code":"PPL",
    "gn:name":"Kineshemskiy Pogost",
    "gn:population":0,
    "gn:timezone":"Europe/Moscow",
    "iso:country":"RU",
    "wof:name":"Kineshemskiy Pogost",
    "wof:placetype":"locality"
},
  "geometry": {"coordinates":[42.08022,56.29734000000001],"type":"Point"}
}