{
  "type": "Feature",
  "properties": {
    "gn:admin1_code":"8",
    "gn:asciiname":"Novoye Dumeyevo",
    "gn:country_code":"RU",
    "gn:dem":132,
    "gn:feature_class":"P",
    "gn:feature_code":"PPL",
    "gn:name":"Novoye Dumeyevo",
    "gn:population":0,
    "gn:timezone":"Asia/Yekaterinburg",
    "iso:country":"RU",
    "name:rus_x_preferred":[
        "\u041d\u043e\u0432\u043e\u0435 \u0414\u0443\u043c\u0435\u0435\u0432\u043e"
    ],
    "name:und_x_variant":[
        "\u041d\u043e\u0432\u043e\u0435 \u0414\u0443\u043c\u0435\u0435\u0432\u043e"
    ],
    "wof:name":"Novoye Dumeyevo",
    "wof:placetype":"locality"
},
  "geometry": {"coordinates":[54.36666999999999,55.18333000000001],"type":"Point"}
}