{
  "type": "Feature",
  "properties": {
    "gn:admin1_code":"38",
    "gn:asciiname":"Sazhevyy Zavod",
    "gn:country_code":"RU",
    "gn:dem":194,
    "gn:feature_class":"P",
    "gn:feature_code":"PPL",
    "gn:name":"Sazhevyy Zavod",
    "gn:population":0,
    "gn:timezone":"Europe/Moscow",
    "iso:country":"RU",
    "name:rus_x_preferred":[
        "\u0421\u0430\u0436\u0435\u0432\u044b\u0439 \u0417\u0430\u0432\u043e\u0434"
    ],
    "name:und_x_variant":[
        "\u0421\u0430\u0436\u0435\u0432\u044b\u0439 \u0417\u0430\u0432\u043e\u0434"
    ],
    "wof:name":"Sazhevyy Zavod",
    "wof:placetype":"locality"
},
  "geometry": {"coordinates":[41.0775,45.0159],"type":"Point"}
}