{
  "type": "Feature",
  "properties": {
    "gn:admin1_code":"59",
    "gn:asciiname":"Starovarvarovka",
    "gn:country_code":"RU",
    "gn:dem":233,
    "gn:feature_class":"P",
    "gn:feature_code":"PPL",
    "gn:name":"Starovarvarovka",
    "gn:population":0,
    "gn:timezone":"Asia/Vladivostok",
    "iso:country":"RU",
    "name:eng_x_preferred":[
        "Starovarvarovka"
    ],
    "name:nor_x_preferred":[
        "Starovarvarovka"
    ],
    "name:rus_x_preferred":[
        "\u0421\u0442\u0430\u0440\u043e\u0432\u0430\u0440\u0432\u0430\u0440\u043e\u0432\u043a\u0430"
    ],
    "name:und_x_variant":[
        "Varvarovka",
        "Staraya Varvarovka",
        "Yarvarovka",
        "Staraya Yarvarovka",
        "\u0421\u0442\u0430\u0440\u043e\u0432\u0430\u0440\u0432\u0430\u0440\u043e\u0432\u043a\u0430",
        "Starovarvarovka"
    ],
    "wof:name":"Starovarvarovka",
    "wof:placetype":"locality"
},
  "geometry": {"coordinates":[132.92983000000001,43.88607],"type":"Point"}
}