{
  "type": "Feature",
  "properties": {
    "gn:admin1_code":"85",
    "gn:asciiname":"Pesok",
    "gn:country_code":"RU",
    "gn:dem":153,
    "gn:feature_class":"P",
    "gn:feature_code":"PPL",
    "gn:name":"Pesok",
    "gn:population":0,
    "gn:timezone":"Europe/Moscow",
    "iso:country":"RU",
    "name:che_x_preferred":[
        "\u041f\u0435\u0441\u043e\u043a"
    ],
    "name:eng_x_preferred":[
        "Pesok"
    ],
    "name:ita_x_preferred":[
        "Pesok"
    ],
    "name:nor_x_preferred":[
        "Pesok"
    ],
    "name:rus_x_preferred":[
        "\u041f\u0435\u0441\u043e\u043a"
    ],
    "name:und_x_variant":[
        "\u041f\u0435\u0441\u043e\u043a",
        "Pesok"
    ],
    "wof:name":"Pesok",
    "wof:placetype":"locality"
},
  "geometry": {"coordinates":[39.8825,60.4537],"type":"Point"}
}