{
  "type": "Feature",
  "properties": {
    "gn:admin1_code":"13",
    "gn:asciiname":"Chernovskoye",
    "gn:country_code":"RU",
    "gn:dem":367,
    "gn:feature_class":"P",
    "gn:feature_code":"PPL",
    "gn:name":"Chernovskoye",
    "gn:population":0,
    "gn:timezone":"Asia/Yekaterinburg",
    "iso:country":"RU",
    "name:eng_x_preferred":[
        "Chernovskoye"
    ],
    "name:nor_x_preferred":[
        "Tsjernaja Retsjka"
    ],
    "name:rus_x_preferred":[
        "\u0427\u0435\u0440\u043d\u0430\u044f \u0420\u0435\u0447\u043a\u0430"
    ],
    "name:rus_x_variant":[
        "\u0427\u0435\u0440\u043d\u043e\u0432\u0441\u043a\u043e\u0435"
    ],
    "name:und_x_variant":[
        "Chernaya Rechka",
        "Chernovskoye",
        "\u0427\u0435\u0440\u043d\u043e\u0432\u0441\u043a\u043e\u0435"
    ],
    "wof:name":"Chernovskoye",
    "wof:placetype":"locality"
},
  "geometry": {"coordinates":[60.0621,54.9224],"type":"Point"}
}