{
  "type": "Feature",
  "properties": {
    "gn:admin1_code":"83",
    "gn:asciiname":"Teterino",
    "gn:country_code":"RU",
    "gn:dem":123,
    "gn:feature_class":"P",
    "gn:feature_code":"PPL",
    "gn:name":"Tet\u00ebrino",
    "gn:population":0,
    "gn:timezone":"Europe/Moscow",
    "iso:country":"RU",
    "name:rus_x_preferred":[
        "\u0422\u0435\u0442\u0451\u0440\u0438\u043d\u043e"
    ],
    "name:und_x_variant":[
        "Tet\u00ebrino"
    ],
    "wof:name":"Teterino",
    "wof:placetype":"locality"
},
  "geometry": {"coordinates":[40.51738,56.57329],"type":"Point"}
}