{
  "type": "Feature",
  "properties": {
    "gn:admin1_code":"72",
    "gn:asciiname":"Mosolovka",
    "gn:country_code":"RU",
    "gn:dem":163,
    "gn:feature_class":"P",
    "gn:feature_code":"PPL",
    "gn:name":"Mosolovka",
    "gn:population":0,
    "gn:timezone":"Europe/Moscow",
    "iso:country":"RU",
    "name:rus_x_preferred":[
        "\u041c\u043e\u0441\u043e\u043b\u043e\u0432\u043a\u0430"
    ],
    "wof:name":"Mosolovka",
    "wof:placetype":"locality"
},
  "geometry": {"coordinates":[40.544,53.1362],"type":"Point"}
}