{
  "type": "Feature",
  "properties": {
    "gn:admin1_code":"42",
    "gn:asciiname":"Pirgora",
    "gn:country_code":"RU",
    "gn:dem":28,
    "gn:feature_class":"P",
    "gn:feature_code":"PPL",
    "gn:name":"Pirgora",
    "gn:population":0,
    "gn:timezone":"Europe/Moscow",
    "iso:country":"RU",
    "name:rus_x_preferred":[
        "\u041f\u0438\u0440\u0433\u043e\u0440\u0430"
    ],
    "name:und_x_variant":[
        "Pirgola",
        "Pirgora",
        "\u041f\u0438\u0440\u0433\u043e\u0440\u0430"
    ],
    "wof:name":"Pirgora",
    "wof:placetype":"locality"
},
  "geometry": {"coordinates":[31.75236,59.91578000000001],"type":"Point"}
}