{
  "type": "Feature",
  "properties": {
    "gn:admin1_code":"43",
    "gn:asciiname":"Oktyabr'skoye",
    "gn:country_code":"RU",
    "gn:dem":156,
    "gn:feature_class":"P",
    "gn:feature_code":"PPL",
    "gn:name":"Oktyabr\u2019skoye",
    "gn:population":0,
    "gn:timezone":"Europe/Moscow",
    "iso:country":"RU",
    "name:eng_x_preferred":[
        "Oktyabr'skoye"
    ],
    "name:rus_x_preferred":[
        "\u0414\u0440\u044f\u0437\u0433\u0438"
    ],
    "name:rus_x_variant":[
        "\u041e\u043a\u0442\u044f\u0431\u0440\u044c\u0441\u043a\u043e\u0435"
    ],
    "name:und_x_variant":[
        "Molotovo",
        "Dryazgi",
        "Oktyabr\u2019skoye"
    ],
    "wof:name":"Oktyabr'skoye",
    "wof:placetype":"locality"
},
  "geometry": {"coordinates":[39.72778,52.30554],"type":"Point"}
}