{
  "type": "Feature",
  "properties": {
    "gn:admin1_code":"17.0",
    "gn:asciiname":"Mashtak- Kuyu",
    "gn:country_code":"RU",
    "gn:dem":10,
    "gn:feature_class":"P",
    "gn:feature_code":"PPL",
    "gn:name":"Mashtak- Kuyu",
    "gn:population":0,
    "gn:timezone":"Europe/Moscow",
    "iso:country":"RU",
    "wof:name":"Mashtak- Kuyu",
    "wof:placetype":"locality"
},
  "geometry": {"coordinates":[45.96419,44.14397],"type":"Point"}
}