{
  "type": "Feature",
  "properties": {
    "gn:admin1_code":"76",
    "gn:asciiname":"Dachnyy",
    "gn:country_code":"RU",
    "gn:dem":233,
    "gn:feature_class":"P",
    "gn:feature_code":"PPL",
    "gn:name":"Dachnyy",
    "gn:population":0,
    "gn:timezone":"Europe/Moscow",
    "iso:country":"RU",
    "name:rus_x_preferred":[
        "\u0414\u0430\u0447\u043d\u044b\u0439"
    ],
    "wof:name":"Dachnyy",
    "wof:placetype":"locality"
},
  "geometry": {"coordinates":[38.1499,53.7854],"type":"Point"}
}