{
  "type": "Feature",
  "properties": {
    "gn:admin1_code":"10",
    "gn:asciiname":"Kropotovo",
    "gn:country_code":"RU",
    "gn:dem":192,
    "gn:feature_class":"P",
    "gn:feature_code":"PPL",
    "gn:name":"Kropotovo",
    "gn:population":0,
    "gn:timezone":"Europe/Moscow",
    "iso:country":"RU",
    "name:rus_x_preferred":[
        "\u041a\u0440\u043e\u043f\u043e\u0442\u043e\u0432\u043e"
    ],
    "name:und_x_variant":[
        "Koropotovo",
        "Kropotovo",
        "\u041a\u0440\u043e\u043f\u043e\u0442\u043e\u0432\u043e"
    ],
    "wof:name":"Kropotovo",
    "wof:placetype":"locality"
},
  "geometry": {"coordinates":[34.6919,52.6271],"type":"Point"}
}