{
  "type": "Feature",
  "properties": {
    "gn:admin1_code":"88",
    "gn:asciiname":"Borisovo",
    "gn:country_code":"RU",
    "gn:dem":119,
    "gn:feature_class":"P",
    "gn:feature_code":"PPL",
    "gn:name":"Borisovo",
    "gn:population":0,
    "gn:timezone":"Europe/Moscow",
    "iso:country":"RU",
    "name:rus_x_preferred":[
        "\u0411\u043e\u0440\u0438\u0441\u043e\u0432\u043e"
    ],
    "wof:name":"Borisovo",
    "wof:placetype":"locality"
},
  "geometry": {"coordinates":[39.98671,57.48733000000001],"type":"Point"}
}