{
  "type": "Feature",
  "properties": {
    "gn:admin1_code":"88",
    "gn:asciiname":"Borisovo",
    "gn:country_code":"RU",
    "gn:dem":119,
    "gn:feature_class":"P",
    "gn:feature_code":"PPL",
    "gn:name":"Borisovo",
    "gn:population":0,
    "gn:timezone":"Europe/Moscow",
    "iso:country":"RU",
    "name:bel_x_preferred":[
        "\u0411\u0430\u0440\u044b\u0441\u0430\u0432\u0430"
    ],
    "name:bul_x_preferred":[
        "\u0411\u043e\u0440\u0438\u0441\u043e\u0432\u043e"
    ],
    "name:ceb_x_preferred":[
        "Borisovo"
    ],
    "name:deu_x_preferred":[
        "Borissowo"
    ],
    "name:fra_x_preferred":[
        "Borisovo"
    ],
    "name:hye_x_preferred":[
        "\u0532\u0578\u0580\u056b\u057d\u0578\u057e\u0578"
    ],
    "name:ron_x_preferred":[
        "Borisovo"
    ],
    "name:rus_x_preferred":[
        "\u0411\u043e\u0440\u0438\u0441\u043e\u0432\u043e"
    ],
    "name:srp_x_preferred":[
        "\u0411\u043e\u0440\u0438\u0441\u043e\u0432\u043e"
    ],
    "name:swe_x_preferred":[
        "Borisovo"
    ],
    "name:ukr_x_preferred":[
        "\u0411\u043e\u0440\u0438\u0441\u043e\u0432\u043e"
    ],
    "wof:name":"Borisovo",
    "wof:placetype":"locality"
},
  "geometry": {"coordinates":[39.98671,57.48733000000001],"type":"Point"}
}