{
  "type": "Feature",
  "properties": {
    "gn:admin1_code":"71",
    "gn:asciiname":"Lipovka",
    "gn:country_code":"RU",
    "gn:dem":123,
    "gn:feature_class":"P",
    "gn:feature_code":"PPL",
    "gn:name":"Lipovka",
    "gn:population":0,
    "gn:timezone":"Asia/Yekaterinburg",
    "iso:country":"RU",
    "name:rus_x_preferred":[
        "\u041b\u0438\u043f\u043e\u0432\u043a\u0430"
    ],
    "name:und_x_variant":[
        "Pipovka",
        "Lipovka"
    ],
    "wof:name":"Lipovka",
    "wof:placetype":"locality"
},
  "geometry": {"coordinates":[61.81788,58.81441],"type":"Point"}
}