{
  "type": "Feature",
  "properties": {
    "gn:admin1_code":"49",
    "gn:asciiname":"Krugloye",
    "gn:cc2":"RU",
    "gn:country_code":"RU",
    "gn:dem":93,
    "gn:feature_class":"P",
    "gn:feature_code":"PPL",
    "gn:name":"Krugloye",
    "gn:population":0,
    "gn:timezone":"Europe/Moscow",
    "iso:country":"RU",
    "name:che_x_preferred":[
        "\u041a\u0440\u0443\u0433\u043b\u0438"
    ],
    "name:rus_x_preferred":[
        "\u041a\u0440\u0443\u0433\u043b\u043e\u0435"
    ],
    "name:tgk_x_preferred":[
        "\u041a\u0440\u0443\u0433\u043b\u043e\u0435"
    ],
    "name:und_x_variant":[
        "Krogloye",
        "Krugloye",
        "\u041a\u0440\u0443\u0433\u043b\u043e\u0435"
    ],
    "wof:name":"Krugloye",
    "wof:placetype":"locality"
},
  "geometry": {"coordinates":[38.25,68.43333],"type":"Point"}
}