{
  "type": "Feature",
  "properties": {
    "gn:admin1_code":"62.0",
    "gn:asciiname":"Dem'yanovo",
    "gn:country_code":"RU",
    "gn:dem":106,
    "gn:feature_class":"P",
    "gn:feature_code":"PPL",
    "gn:name":"Dem\u2019yanovo",
    "gn:population":0,
    "gn:timezone":"Europe/Moscow",
    "iso:country":"RU",
    "name:rus_x_preferred":[
        "\u0414\u0435\u043c\u044c\u044f\u043d\u043e\u0432\u043e"
    ],
    "name:und_x_variant":[
        "Dem\u2019yanovo",
        "\u0414\u0435\u043c\u044c\u044f\u043d\u043e\u0432\u043e"
    ],
    "wof:name":"Dem'yanovo",
    "wof:placetype":"locality"
},
  "geometry": {"coordinates":[40.1819,53.9695],"type":"Point"}
}