{
  "type": "Feature",
  "properties": {
    "gn:admin1_code":"76",
    "gn:asciiname":"Kharino",
    "gn:country_code":"RU",
    "gn:dem":221,
    "gn:feature_class":"P",
    "gn:feature_code":"PPL",
    "gn:name":"Kharino",
    "gn:population":0,
    "gn:timezone":"Europe/Moscow",
    "iso:country":"RU",
    "name:rus_x_preferred":[
        "\u0425\u0430\u0440\u0438\u043d\u043e"
    ],
    "wof:name":"Kharino",
    "wof:placetype":"locality"
},
  "geometry": {"coordinates":[37.47739,54.15517],"type":"Point"}
}