{
  "type": "Feature",
  "properties": {
    "gn:country":"RU",
    "gn:fcode":"PPL",
    "gn:pop":7337,
    "iso:country":"RU",
    "name:rus_x_preferred":[
        "\u0416\u0435\u043b\u0435\u0437\u043d\u043e\u0434\u043e\u0440\u043e\u0436\u043d\u044b\u0439"
    ],
    "qs:name":"Zheleznodorozhnyy",
    "qs:photos_9r":0,
    "qs:photos_sr":0,
    "qs:pop_sr":"5",
    "wd:wordcount":57,
    "wof:name":"Zheleznodorozhnyy",
    "wof:placetype":"locality",
    "wof:population":7337
},
  "geometry": {"coordinates":[61.54926,55.10183],"type":"Point"}
}