{
  "type": "Feature",
  "properties": {
    "gn:admin1_code":"77",
    "gn:asciiname":"Rozhino",
    "gn:country_code":"RU",
    "gn:dem":176,
    "gn:feature_class":"P",
    "gn:feature_code":"PPL",
    "gn:name":"Rozhino",
    "gn:population":0,
    "gn:timezone":"Europe/Moscow",
    "iso:country":"RU",
    "name:rus_x_preferred":[
        "\u0420\u043e\u0436\u0438\u043d\u043e"
    ],
    "wof:name":"Rozhino",
    "wof:placetype":"locality"
},
  "geometry": {"coordinates":[32.45755,55.74663],"type":"Point"}
}