{
  "type": "Feature",
  "properties": {
    "gn:admin1_code":"42.0",
    "gn:asciiname":"Russkoye Bryzgovo",
    "gn:country_code":"RU",
    "gn:dem":151,
    "gn:feature_class":"P",
    "gn:feature_code":"PPL",
    "gn:name":"Russkoye Bryzgovo",
    "gn:population":0,
    "gn:timezone":"Europe/Moscow",
    "iso:country":"RU",
    "wof:name":"Russkoye Bryzgovo",
    "wof:placetype":"locality"
},
  "geometry": {"coordinates":[29.32258,59.5604],"type":"Point"}
}