{
  "type": "Feature",
  "properties": {
    "gn:admin1_code":"25",
    "gn:asciiname":"Kornoye",
    "gn:country_code":"RU",
    "gn:dem":205,
    "gn:feature_class":"P",
    "gn:feature_code":"PPL",
    "gn:name":"Kornoye",
    "gn:population":0,
    "gn:timezone":"Europe/Moscow",
    "iso:country":"RU",
    "name:rus_x_preferred":[
        "\u041a\u043e\u0440\u043d\u0430"
    ],
    "name:und_x_variant":[
        "Korna",
        "Kornoye"
    ],
    "wof:name":"Kornoye",
    "wof:placetype":"locality"
},
  "geometry": {"coordinates":[35.01972,54.41694],"type":"Point"}
}