{
  "type": "Feature",
  "properties": {
    "gn:admin1_code":"42",
    "gn:asciiname":"Pogost Rebovskiy",
    "gn:cc2":"RU",
    "gn:country_code":"RU",
    "gn:dem":99,
    "gn:feature_class":"P",
    "gn:feature_code":"PPL",
    "gn:name":"Pogost Rebovskiy",
    "gn:population":0,
    "gn:timezone":"Europe/Moscow",
    "iso:country":"RU",
    "name:rus_x_preferred":[
        "\u041f\u043e\u0433\u043e\u0441\u0442 \u0420\u0435\u0431\u043e\u0432\u0441\u043a\u0438\u0439"
    ],
    "name:und_x_variant":[
        "Rebovinkirkonkyl\u00e4",
        "Pogost Rebovskiy"
    ],
    "wof:name":"Pogost Rebovskiy",
    "wof:placetype":"locality"
},
  "geometry": {"coordinates":[34.28333,60.23333],"type":"Point"}
}