{
  "type": "Feature",
  "properties": {
    "gn:admin1_code":"52",
    "gn:asciiname":"Meglino",
    "gn:country_code":"RU",
    "gn:dem":94,
    "gn:feature_class":"P",
    "gn:feature_code":"PPL",
    "gn:name":"Meglino",
    "gn:population":0,
    "gn:timezone":"Europe/Moscow",
    "iso:country":"RU",
    "name:rus_x_preferred":[
        "\u041c\u0435\u0433\u043b\u0438\u043do"
    ],
    "wof:name":"Meglino",
    "wof:placetype":"locality"
},
  "geometry": {"coordinates":[32.44808,57.55458],"type":"Point"}
}