{
  "type": "Feature",
  "properties": {
    "gn:admin1_code":"1",
    "gn:asciiname":"Kruglyy",
    "gn:country_code":"RU",
    "gn:dem":203,
    "gn:feature_class":"P",
    "gn:feature_code":"PPL",
    "gn:name":"Kruglyy",
    "gn:population":0,
    "gn:timezone":"Europe/Moscow",
    "iso:country":"RU",
    "name:rus_x_preferred":[
        "\u041a\u0440\u0443\u0433\u043b\u044b\u0439"
    ],
    "wof:name":"Kruglyy",
    "wof:placetype":"locality"
},
  "geometry": {"coordinates":[40.16861,44.71167],"type":"Point"}
}