{
  "type": "Feature",
  "properties": {
    "gn:admin1_code":"63",
    "gn:asciiname":"Yansatay",
    "gn:cc2":"RU",
    "gn:country_code":"RU",
    "gn:dem":88,
    "gn:feature_class":"P",
    "gn:feature_code":"PPL",
    "gn:name":"Yansatay",
    "gn:population":0,
    "gn:timezone":"Asia/Yakutsk",
    "iso:country":"RU",
    "name:und_x_variant":[
        "Doma",
        "Dolya",
        "Dora",
        "Yansatay"
    ],
    "wof:name":"Yansatay",
    "wof:placetype":"locality"
},
  "geometry": {"coordinates":[132.28333000000001,69.90000000000001],"type":"Point"}
}