{
  "type": "Feature",
  "properties": {
    "gn:admin1_code":"77",
    "gn:asciiname":"Novyy Dvor",
    "gn:country_code":"RU",
    "gn:dem":179,
    "gn:feature_class":"P",
    "gn:feature_code":"PPL",
    "gn:name":"Novyy Dvor",
    "gn:population":0,
    "gn:timezone":"Europe/Moscow",
    "iso:country":"RU",
    "name:rus_x_preferred":[
        "\u041d\u043e\u0432\u044b\u0439 \u0414\u0432\u043e\u0440"
    ],
    "name:und_x_variant":[
        "Novy Dvor",
        "Novyy Dvor"
    ],
    "wof:name":"Novyy Dvor",
    "wof:placetype":"locality"
},
  "geometry": {"coordinates":[32.16857,56.04279],"type":"Point"}
}