{
  "type": "Feature",
  "properties": {
    "gn:admin1_code":"38",
    "gn:asciiname":"Zhuravskaya",
    "gn:country_code":"RU",
    "gn:dem":41,
    "gn:feature_class":"P",
    "gn:feature_code":"PPL",
    "gn:name":"Zhuravskaya",
    "gn:population":0,
    "gn:timezone":"Europe/Moscow",
    "iso:country":"RU",
    "name:rus_x_preferred":[
        "\u0416\u0443\u0440\u0430\u0432\u0441\u043a\u0430\u044f"
    ],
    "wof:name":"Zhuravskaya",
    "wof:placetype":"locality"
},
  "geometry": {"coordinates":[39.6179,45.57968],"type":"Point"}
}