{
  "type": "Feature",
  "properties": {
    "gn:admin1_code":"11",
    "gn:asciiname":"Agafonovo",
    "gn:country_code":"RU",
    "gn:dem":478,
    "gn:feature_class":"P",
    "gn:feature_code":"PPL",
    "gn:name":"Agafonovo",
    "gn:population":0,
    "gn:timezone":"Asia/Irkutsk",
    "iso:country":"RU",
    "name:nor_x_preferred":[
        "Agafonovo"
    ],
    "name:rus_x_preferred":[
        "\u0410\u0433\u0430\u0444\u043e\u043d\u043e\u0432\u043e"
    ],
    "name:und_x_variant":[
        "Agafonova",
        "Agafonovo"
    ],
    "wof:name":"Agafonovo",
    "wof:placetype":"locality"
},
  "geometry": {"coordinates":[109.68333,53.55],"type":"Point"}
}