{
  "type": "Feature",
  "properties": {
    "gn:admin1_code":"55",
    "gn:asciiname":"Staritskoye",
    "gn:country_code":"RU",
    "gn:dem":181,
    "gn:feature_class":"P",
    "gn:feature_code":"PPL",
    "gn:name":"Staritskoye",
    "gn:population":0,
    "gn:timezone":"Asia/Yekaterinburg",
    "iso:country":"RU",
    "name:eng_x_preferred":[
        "Staritskoye"
    ],
    "name:nor_x_preferred":[
        "Staritskoje"
    ],
    "name:rus_x_preferred":[
        "\u0421\u0442\u0430\u0440\u0438\u0446\u043a\u043e\u0435"
    ],
    "name:rus_x_variant":[
        "\u0421\u0442\u0430\u0440\u0438\u0442\u0441\u043a\u043e\u0435"
    ],
    "name:und_x_variant":[
        "Staritskiy",
        "Staritskoye"
    ],
    "wof:name":"Staritskoye",
    "wof:placetype":"locality"
},
  "geometry": {"coordinates":[55.69919,51.44769],"type":"Point"}
}