{
  "type": "Feature",
  "properties": {
    "gn:admin1_code":"77.0",
    "gn:asciiname":"Bervenets",
    "gn:country_code":"RU",
    "gn:dem":231,
    "gn:feature_class":"P",
    "gn:feature_code":"PPL",
    "gn:name":"Bervenets",
    "gn:population":0,
    "gn:timezone":"Europe/Moscow",
    "iso:country":"RU",
    "name:eng_x_preferred":[
        "Bervenets"
    ],
    "name:nor_x_preferred":[
        "Bervenets"
    ],
    "name:rus_x_preferred":[
        "\u0411\u0435\u0440\u0432\u0435\u043d\u0435\u0446"
    ],
    "name:und_x_variant":[
        "Brevenets",
        "Bervenets"
    ],
    "wof:name":"Bervenets",
    "wof:placetype":"locality"
},
  "geometry": {"coordinates":[32.50230999999999,56.98446],"type":"Point"}
}