{
  "type": "Feature",
  "properties": {
    "gn:admin1_code":"77",
    "gn:asciiname":"Zanogi",
    "gn:country_code":"RU",
    "gn:dem":238,
    "gn:feature_class":"P",
    "gn:feature_code":"PPL",
    "gn:name":"Zanogi",
    "gn:population":0,
    "gn:timezone":"Europe/Moscow",
    "iso:country":"RU",
    "name:rus_x_preferred":[
        "\u0417\u0430\u043d\u043e\u0433\u0438"
    ],
    "wof:name":"Zanogi",
    "wof:placetype":"locality"
},
  "geometry": {"coordinates":[32.07597,56.82681],"type":"Point"}
}