{
  "type": "Feature",
  "properties": {
    "gn:admin1_code":"76.0",
    "gn:asciiname":"Belopol'ye",
    "gn:country_code":"RU",
    "gn:dem":235,
    "gn:feature_class":"P",
    "gn:feature_code":"PPL",
    "gn:name":"Belopol\u2019ye",
    "gn:population":0,
    "gn:timezone":"Europe/Moscow",
    "iso:country":"RU",
    "name:nor_x_preferred":[
        "Belopolje"
    ],
    "name:rus_x_preferred":[
        "\u0411\u0435\u043b\u043e\u043f\u043e\u043b\u044c\u0435"
    ],
    "name:und_x_variant":[
        "Razdory",
        "Belopol\u2019ye"
    ],
    "wof:name":"Belopol'ye",
    "wof:placetype":"locality"
},
  "geometry": {"coordinates":[37.57614,54.35223000000001],"type":"Point"}
}