{
  "type": "Feature",
  "properties": {
    "gn:admin1_code":"05",
    "gn:asciiname":"Dzheskogon",
    "gn:country_code":"RU",
    "gn:dem":573,
    "gn:feature_class":"P",
    "gn:feature_code":"PPL",
    "gn:name":"Dzheskogon",
    "gn:population":0,
    "gn:timezone":"Asia/Yakutsk",
    "iso:country":"RU",
    "name:eng_x_preferred":[
        "Dzheskogon"
    ],
    "name:nor_x_preferred":[
        "Dzjeskogan"
    ],
    "name:rus_x_preferred":[
        "\u0414\u0436\u0435\u0441\u043a\u043e\u0433\u0430\u043d"
    ],
    "name:rus_x_variant":[
        "\u0414\u0436\u0435\u0441\u043a\u043e\u0433\u043e\u043d"
    ],
    "wof:name":"Dzheskogon",
    "wof:placetype":"locality"
},
  "geometry": {"coordinates":[129.78288999999998,53.92574000000001],"type":"Point"}
}