{
  "type": "Feature",
  "properties": {
    "gn:admin1_code":"88",
    "gn:asciiname":"Yurkino",
    "gn:country_code":"RU",
    "gn:dem":129,
    "gn:feature_class":"P",
    "gn:feature_code":"PPL",
    "gn:name":"Yurkino",
    "gn:population":0,
    "gn:timezone":"Europe/Moscow",
    "iso:country":"RU",
    "name:eng_x_preferred":[
        "Yurkino"
    ],
    "name:nor_x_preferred":[
        "Jurkino"
    ],
    "name:rus_x_preferred":[
        "\u042e\u0440\u043a\u0438\u043d\u043e"
    ],
    "wof:name":"Yurkino",
    "wof:placetype":"locality"
},
  "geometry": {"coordinates":[39.07857,57.41676999999999],"type":"Point"}
}