{
  "type": "Feature",
  "properties": {
    "gn:admin1_code":"52",
    "gn:asciiname":"Mavrino",
    "gn:country_code":"RU",
    "gn:dem":34,
    "gn:feature_class":"P",
    "gn:feature_code":"PPL",
    "gn:name":"Mavrino",
    "gn:population":0,
    "gn:timezone":"Europe/Moscow",
    "iso:country":"RU",
    "name:rus_x_preferred":[
        "\u041c\u0430\u0432\u0440\u0438\u043d\u043e"
    ],
    "wof:name":"Mavrino",
    "wof:placetype":"locality"
},
  "geometry": {"coordinates":[31.3649,57.8447],"type":"Point"}
}