{
  "type": "Feature",
  "properties": {
    "gn:admin1_code":"42",
    "gn:asciiname":"Zelenets",
    "gn:country_code":"RU",
    "gn:dem":52,
    "gn:feature_class":"P",
    "gn:feature_code":"PPL",
    "gn:name":"Zelenets",
    "gn:population":44,
    "gn:timezone":"Europe/Moscow",
    "iso:country":"RU",
    "name:rus_x_preferred":[
        "\u0417\u0435\u043b\u0435\u043d\u0435\u0446"
    ],
    "name:und_x_variant":[
        "Setenets",
        "Troitsko-Zelentskiy",
        "Zelenets"
    ],
    "wof:name":"Zelenets",
    "wof:placetype":"locality",
    "wof:population":44
},
  "geometry": {"coordinates":[32.77793,59.79174],"type":"Point"}
}