{
  "type": "Feature",
  "properties": {
    "gn:admin1_code":"85.0",
    "gn:asciiname":"Zykovo",
    "gn:country_code":"RU",
    "gn:dem":131,
    "gn:feature_class":"P",
    "gn:feature_code":"PPL",
    "gn:name":"Zykovo",
    "gn:population":0,
    "gn:timezone":"Europe/Moscow",
    "iso:country":"RU",
    "name:rus_x_preferred":[
        "\u0417\u044b\u043a\u043e\u0432\u043e"
    ],
    "wof:name":"Zykovo",
    "wof:placetype":"locality"
},
  "geometry": {"coordinates":[38.6963,60.3143],"type":"Point"}
}