{
  "type": "Feature",
  "properties": {
    "gn:admin1_code":"91",
    "gn:asciiname":"Chingasan",
    "gn:cc2":"RU",
    "gn:country_code":"RU",
    "gn:dem":204,
    "gn:feature_class":"P",
    "gn:feature_code":"PPL",
    "gn:name":"Chingasan",
    "gn:population":0,
    "gn:timezone":"Asia/Krasnoyarsk",
    "iso:country":"RU",
    "name:rus_x_preferred":[
        "\u0427\u0438\u043d\u0433\u0430\u0441\u0430\u043d"
    ],
    "name:und_x_variant":[
        "Chingasak",
        "Chingosak",
        "Chingasan"
    ],
    "wof:name":"Chingasan",
    "wof:placetype":"locality"
},
  "geometry": {"coordinates":[91.90000000000001,60.71666999999999],"type":"Point"}
}