{
  "type": "Feature",
  "properties": {
    "gn:admin1_code":"76",
    "gn:asciiname":"Zarechenskiy",
    "gn:country_code":"RU",
    "gn:dem":181,
    "gn:feature_class":"P",
    "gn:feature_code":"PPL",
    "gn:name":"Zarechenskiy",
    "gn:population":0,
    "gn:timezone":"Europe/Moscow",
    "iso:country":"RU",
    "name:rus_x_preferred":[
        "\u0417\u0430\u0440\u0435\u0447\u0435\u043d\u0441\u043a\u0438\u0439"
    ],
    "name:und_x_variant":[
        "Zarech\u2019ye",
        "Zarechenskiy"
    ],
    "wof:name":"Zarechenskiy",
    "wof:placetype":"locality"
},
  "geometry": {"coordinates":[38.0045,53.9721],"type":"Point"}
}