{
  "type": "Feature",
  "properties": {
    "gn:admin1_code":"33",
    "gn:asciiname":"Shuymar-Verkhovskaya",
    "gn:country_code":"RU",
    "gn:dem":144,
    "gn:feature_class":"P",
    "gn:feature_code":"PPL",
    "gn:name":"Shuymar-Verkhovskaya",
    "gn:population":0,
    "gn:timezone":"Europe/Kirov",
    "iso:country":"RU",
    "name:rus_x_preferred":[
        "\u0428\u0443\u0439\u043c\u0430\u0440-\u0412\u0435\u0440\u0445\u043e\u0432\u0441\u043a\u0430\u044f"
    ],
    "wof:name":"Shuymar-Verkhovskaya",
    "wof:placetype":"locality"
},
  "geometry": {"coordinates":[47.918,57.0953],"type":"Point"}
}