{
  "type": "Feature",
  "properties": {
    "gn:admin1_code":"37.0",
    "gn:asciiname":"Burdovo",
    "gn:country_code":"RU",
    "gn:dem":129,
    "gn:feature_class":"P",
    "gn:feature_code":"PPL",
    "gn:name":"Burdovo",
    "gn:population":0,
    "gn:timezone":"Europe/Moscow",
    "iso:country":"RU",
    "name:eng_x_preferred":[
        "Burdovo"
    ],
    "name:nor_x_preferred":[
        "Burdovo"
    ],
    "name:rus_x_preferred":[
        "\u0411\u0443\u0440\u0434\u043e\u0432\u043e"
    ],
    "wof:name":"Burdovo",
    "wof:placetype":"locality"
},
  "geometry": {"coordinates":[44.14889,58.9008],"type":"Point"}
}