{
  "type": "Feature",
  "properties": {
    "gn:admin1_code":"86.0",
    "gn:asciiname":"Bratolyubov",
    "gn:country_code":"RU",
    "gn:dem":166,
    "gn:feature_class":"P",
    "gn:feature_code":"PPL",
    "gn:name":"Bratolyubov",
    "gn:population":0,
    "gn:timezone":"Europe/Moscow",
    "iso:country":"RU",
    "name:rus_x_preferred":[
        "\u0411\u0440\u0430\u0442\u043e\u043b\u044e\u0431\u043e\u0432"
    ],
    "wof:name":"Bratolyubov",
    "wof:placetype":"locality"
},
  "geometry": {"coordinates":[40.14139,49.95],"type":"Point"}
}