{
  "type": "Feature",
  "properties": {
    "gn:admin1_code":"68",
    "gn:asciiname":"Veselovskoye",
    "gn:country_code":"RU",
    "gn:dem":137,
    "gn:feature_class":"P",
    "gn:feature_code":"PPL",
    "gn:name":"Veselovskoye",
    "gn:population":0,
    "gn:timezone":"Europe/Moscow",
    "iso:country":"RU",
    "name:rus_x_preferred":[
        "\u0412\u0435\u0441\u0435\u043b\u043e\u0432\u0441\u043a\u043e\u0435"
    ],
    "name:und_x_variant":[
        "Beselovskoye",
        "Veselyy",
        "Veselovskoye"
    ],
    "wof:name":"Veselovskoye",
    "wof:placetype":"locality"
},
  "geometry": {"coordinates":[44.72759,43.7684],"type":"Point"}
}