{
  "type": "Feature",
  "properties": {
    "gn:admin1_code":"8",
    "gn:asciiname":"Yuldashevo",
    "gn:country_code":"RU",
    "gn:dem":318,
    "gn:feature_class":"P",
    "gn:feature_code":"PPL",
    "gn:name":"Yuldashevo",
    "gn:population":0,
    "gn:timezone":"Asia/Yekaterinburg",
    "iso:country":"RU",
    "name:eng_x_preferred":[
        "Yuldashevo"
    ],
    "name:nor_x_preferred":[
        "Juldasjevo"
    ],
    "name:rus_x_preferred":[
        "\u042e\u043b\u0434\u0430\u0448\u0435\u0432\u043e"
    ],
    "wof:name":"Yuldashevo",
    "wof:placetype":"locality"
},
  "geometry": {"coordinates":[59.26806,55.65639],"type":"Point"}
}