{
  "type": "Feature",
  "properties": {
    "gn:admin1_code":"8",
    "gn:asciiname":"Yuldashevo",
    "gn:country_code":"RU",
    "gn:dem":318,
    "gn:feature_class":"P",
    "gn:feature_code":"PPL",
    "gn:name":"Yuldashevo",
    "gn:population":0,
    "gn:timezone":"Asia/Yekaterinburg",
    "iso:country":"RU",
    "name:aze_x_preferred":[
        "Yulda\u015f"
    ],
    "name:bak_x_preferred":[
        "\u042e\u043b\u0434\u0430\u0448"
    ],
    "name:che_x_preferred":[
        "\u042e\u043b\u0434\u0430\u0448\u0435\u0432\u043e"
    ],
    "name:eng_x_preferred":[
        "Yuldashevo"
    ],
    "name:hye_x_preferred":[
        "\u0545\u0578\u0582\u056c\u0564\u0561\u0577\u0587\u0578"
    ],
    "name:kat_x_preferred":[
        "\u10d8\u10e3\u10da\u10d3\u10d0\u10e8\u10d4\u10d5\u10dd"
    ],
    "name:kaz_x_preferred":[
        "\u042e\u043b\u0434\u0430\u0448"
    ],
    "name:kir_x_preferred":[
        "\u042e\u043b\u0434\u0430\u0448"
    ],
    "name:nor_x_preferred":[
        "Juldasjevo"
    ],
    "name:rus_x_preferred":[
        "\u042e\u043b\u0434\u0430\u0448\u0435\u0432\u043e"
    ],
    "name:tat_x_preferred":[
        "\u042e\u043b\u0434\u0430\u0448"
    ],
    "name:ukr_x_preferred":[
        "\u042e\u043b\u0434\u0430\u0448\u0435\u0432\u043e"
    ],
    "wof:name":"Yuldashevo",
    "wof:placetype":"locality"
},
  "geometry": {"coordinates":[59.26806,55.65639],"type":"Point"}
}