{
  "type": "Feature",
  "properties": {
    "gn:country":"RU",
    "gn:fcode":"PPL",
    "gn:population":12626,
    "iso:country":"RU",
    "name:eng_x_preferred":[
        "Lyangasovo"
    ],
    "name:nor_x_preferred":[
        "Ljangasovo"
    ],
    "name:rus_x_preferred":[
        "\u041b\u044f\u043d\u0433\u0430\u0441\u043e\u0432\u043e"
    ],
    "qs:name":"Lyangasovo",
    "qs:name_adm0":"Russia",
    "qs:name_adm1":"Kirov Oblast",
    "qs:photos_9r":0,
    "qs:photos_sr":0,
    "qs:placetype":"Town",
    "qs:pop_sr":"6",
    "wof:name":"Lyangasovo",
    "wof:placetype":"locality",
    "wof:population":12626
},
  "geometry": {"coordinates":[49.44718,58.51759],"type":"Point"}
}