{
  "type": "Feature",
  "properties": {
    "gn:admin1_code":"47",
    "gn:asciiname":"Novo-Aleksandrovka",
    "gn:country_code":"RU",
    "gn:dem":200,
    "gn:feature_class":"P",
    "gn:feature_code":"PPL",
    "gn:name":"Novo-Aleksandrovka",
    "gn:population":0,
    "gn:timezone":"Europe/Moscow",
    "iso:country":"RU",
    "wof:name":"Novo-Aleksandrovka",
    "wof:placetype":"locality"
},
  "geometry": {"coordinates":[36.00472,55.255],"type":"Point"}
}