{
  "type": "Feature",
  "properties": {
    "gn:admin1_code":"60",
    "gn:asciiname":"Prokhnovo",
    "gn:country_code":"RU",
    "gn:dem":101,
    "gn:feature_class":"P",
    "gn:feature_code":"PPL",
    "gn:name":"Prokhnovo",
    "gn:population":0,
    "gn:timezone":"Europe/Moscow",
    "iso:country":"RU",
    "name:rus_x_preferred":[
        "\u041f\u0440\u043e\u0445\u043d\u043e\u0432\u043e"
    ],
    "wof:name":"Prokhnovo",
    "wof:placetype":"locality"
},
  "geometry": {"coordinates":[30.83069,56.4735],"type":"Point"}
}