{
  "type": "Feature",
  "properties": {
    "gn:admin1_code":"45.0",
    "gn:asciiname":"Verkhnyaya Krasnaya Gorka",
    "gn:country_code":"RU",
    "gn:dem":87,
    "gn:feature_class":"P",
    "gn:feature_code":"PPL",
    "gn:name":"Verkhnyaya Krasnaya Gorka",
    "gn:population":0,
    "gn:timezone":"Europe/Moscow",
    "iso:country":"RU",
    "name:rus_x_preferred":[
        "\u0412\u0435\u0440\u0445\u043d\u044f\u044f \u041a\u0440\u0430\u0441\u043d\u0430\u044f \u0413\u043e\u0440\u043a\u0430"
    ],
    "wof:name":"Verkhnyaya Krasnaya Gorka",
    "wof:placetype":"locality"
},
  "geometry": {"coordinates":[48.77667,56.205],"type":"Point"}
}