{
  "type": "Feature",
  "properties": {
    "gn:admin1_code":"21",
    "gn:asciiname":"Tormosovo",
    "gn:country_code":"RU",
    "gn:dem":146,
    "gn:feature_class":"P",
    "gn:feature_code":"PPL",
    "gn:name":"Tormosovo",
    "gn:population":0,
    "gn:timezone":"Europe/Moscow",
    "iso:country":"RU",
    "name:rus_x_preferred":[
        "\u0422\u043e\u0440\u043c\u043e\u0441\u043e\u0432\u043e"
    ],
    "wof:name":"Tormosovo",
    "wof:placetype":"locality"
},
  "geometry": {"coordinates":[39.74131,57.05403],"type":"Point"}
}