{
  "type": "Feature",
  "properties": {
    "gn:admin1_code":"78",
    "gn:asciiname":"Lipinka",
    "gn:country_code":"RU",
    "gn:dem":128,
    "gn:feature_class":"P",
    "gn:feature_code":"PPL",
    "gn:name":"Lipinka",
    "gn:population":0,
    "gn:timezone":"Asia/Yekaterinburg",
    "iso:country":"RU",
    "name:rus_x_preferred":[
        "\u041b\u0438\u043f\u0438\u043d\u043a\u0430"
    ],
    "name:und_x_variant":[
        "\u041b\u0438\u043f\u0438\u043d\u043a\u0430"
    ],
    "wof:name":"Lipinka",
    "wof:placetype":"locality"
},
  "geometry": {"coordinates":[70.65000000000001,55.98333],"type":"Point"}
}