{
  "type": "Feature",
  "properties": {
    "gn:admin1_code":"60",
    "gn:asciiname":"Stvol'no",
    "gn:country_code":"RU",
    "gn:dem":95,
    "gn:feature_class":"P",
    "gn:feature_code":"PPL",
    "gn:name":"Stvol\u2019no",
    "gn:population":0,
    "gn:timezone":"Europe/Moscow",
    "iso:country":"RU",
    "name:rus_x_preferred":[
        "\u0421\u0442\u0432\u043e\u043b\u044c\u043d\u043e"
    ],
    "name:und_x_variant":[
        "Stvol\u2019no",
        "\u0421\u0442\u0432\u043e\u043b\u044c\u043d\u043e"
    ],
    "wof:name":"Stvol'no",
    "wof:placetype":"locality"
},
  "geometry": {"coordinates":[30.35,57.08333],"type":"Point"}
}