{
  "type": "Feature",
  "properties": {
    "gn:admin1_code":"93",
    "gn:asciiname":"Khilogoson",
    "gn:country_code":"RU",
    "gn:dem":853,
    "gn:feature_class":"P",
    "gn:feature_code":"PPL",
    "gn:name":"Khilogoson",
    "gn:population":0,
    "gn:timezone":"Asia/Chita",
    "iso:country":"RU",
    "name:eng_x_preferred":[
        "Khilogoson"
    ],
    "name:nor_x_preferred":[
        "Khilogoson"
    ],
    "name:rus_x_preferred":[
        "\u0425\u0438\u043b\u043e\u0433\u043e\u0441\u043e\u043d"
    ],
    "name:und_x_variant":[
        "Khilkoson",
        "\u0425\u0438\u043b\u043e\u0433\u043e\u0441\u043e\u043d",
        "Khilogoson"
    ],
    "wof:name":"Khilogoson",
    "wof:placetype":"locality"
},
  "geometry": {"coordinates":[110.63885999999999,51.15343],"type":"Point"}
}