{
  "type": "Feature",
  "properties": {
    "gn:admin1_code":"62",
    "gn:asciiname":"Veret'ye",
    "gn:country_code":"RU",
    "gn:dem":108,
    "gn:feature_class":"P",
    "gn:feature_code":"PPL",
    "gn:name":"Veret\u2019ye",
    "gn:population":0,
    "gn:timezone":"Europe/Moscow",
    "iso:country":"RU",
    "name:eng_x_preferred":[
        "Veret'ye"
    ],
    "name:nor_x_preferred":[
        "Veretje"
    ],
    "name:rus_x_preferred":[
        "\u0412\u0435\u0440\u0435\u0442\u044c\u0435"
    ],
    "name:und_x_variant":[
        "Veret\u2019ye"
    ],
    "wof:name":"Veret'ye",
    "wof:placetype":"locality"
},
  "geometry": {"coordinates":[40.4849,54.6597],"type":"Point"}
}