{
  "type": "Feature",
  "properties": {
    "gn:admin1_code":"77.0",
    "gn:asciiname":"Semekhino",
    "gn:country_code":"RU",
    "gn:dem":240,
    "gn:feature_class":"P",
    "gn:feature_code":"PPL",
    "gn:name":"Semekhino",
    "gn:population":0,
    "gn:timezone":"Europe/Moscow",
    "iso:country":"RU",
    "name:rus_x_preferred":[
        "\u0421\u0435\u043c\u0435\u0445\u0438\u043d\u043e"
    ],
    "name:und_x_variant":[
        "Semekhina",
        "Semekhino",
        "Bol\u2019shoye Semikhino"
    ],
    "wof:name":"Semekhino",
    "wof:placetype":"locality"
},
  "geometry": {"coordinates":[31.64465,56.9757],"type":"Point"}
}