{
  "type": "Feature",
  "properties": {
    "gn:admin1_code":"81",
    "gn:asciiname":"Yelkhovka",
    "gn:country_code":"RU",
    "gn:dem":172,
    "gn:feature_class":"P",
    "gn:feature_code":"PPL",
    "gn:name":"Yelkhovka",
    "gn:population":0,
    "gn:timezone":"Europe/Ulyanovsk",
    "iso:country":"RU",
    "name:rus_x_preferred":[
        "\u0415\u043b\u0445\u043e\u0432\u043a\u0430"
    ],
    "name:und_x_variant":[
        "\u0415\u043b\u0445\u043e\u0432\u043a\u0430"
    ],
    "wof:name":"Yelkhovka",
    "wof:placetype":"locality"
},
  "geometry": {"coordinates":[47.07100000000001,53.6708],"type":"Point"}
}