{
  "type": "Feature",
  "properties": {
    "gn:admin1_code":"72",
    "gn:asciiname":"Timofeyevka",
    "gn:country_code":"RU",
    "gn:dem":161,
    "gn:feature_class":"P",
    "gn:feature_code":"PPL",
    "gn:name":"Timofeyevka",
    "gn:population":0,
    "gn:timezone":"Europe/Moscow",
    "iso:country":"RU",
    "name:eng_x_preferred":[
        "Timofeyevka"
    ],
    "name:nor_x_preferred":[
        "Timofejevka"
    ],
    "name:rus_x_preferred":[
        "\u0422\u0438\u043c\u043e\u0444\u0435\u0435\u0432\u043a\u0430"
    ],
    "wof:name":"Timofeyevka",
    "wof:placetype":"locality"
},
  "geometry": {"coordinates":[41.96054,52.18996],"type":"Point"}
}