{
  "type": "Feature",
  "properties": {
    "gn:admin1_code":"16",
    "gn:asciiname":"Yanmurzino",
    "gn:country_code":"RU",
    "gn:dem":99,
    "gn:feature_class":"P",
    "gn:feature_code":"PPL",
    "gn:name":"Yanmurzino",
    "gn:population":0,
    "gn:timezone":"Europe/Moscow",
    "iso:country":"RU",
    "name:rus_x_preferred":[
        "\u042f\u043d\u043c\u0443\u0440\u0437\u0438\u043d\u043e"
    ],
    "wof:name":"Yanmurzino",
    "wof:placetype":"locality"
},
  "geometry": {"coordinates":[47.12574,55.70877],"type":"Point"}
}