{
  "type": "Feature",
  "properties": {
    "gn:admin1_code":"77",
    "gn:asciiname":"L'ba",
    "gn:country_code":"RU",
    "gn:dem":200,
    "gn:feature_class":"P",
    "gn:feature_code":"PPL",
    "gn:name":"L\u2019ba",
    "gn:population":0,
    "gn:timezone":"Europe/Moscow",
    "iso:country":"RU",
    "name:rus_x_preferred":[
        "\u041b\u044c\u0431\u0430"
    ],
    "name:und_x_variant":[
        "L\u2019ba",
        "\u041b\u044c\u0431\u0430"
    ],
    "wof:name":"L'ba",
    "wof:placetype":"locality"
},
  "geometry": {"coordinates":[32.88889,55.93944000000001],"type":"Point"}
}