{
  "type": "Feature",
  "properties": {
    "gn:admin1_code":"4",
    "gn:asciiname":"Chumanka",
    "gn:cc2":"RU",
    "gn:country_code":"RU",
    "gn:dem":224,
    "gn:feature_class":"P",
    "gn:feature_code":"PPL",
    "gn:name":"Chumanka",
    "gn:population":0,
    "gn:timezone":"Asia/Barnaul",
    "iso:country":"RU",
    "name:eng_x_preferred":[
        "Chumanka"
    ],
    "name:nor_x_preferred":[
        "Tsjumanka"
    ],
    "name:rus_x_preferred":[
        "\u0427\u0443\u043c\u0430\u043d\u043a\u0430"
    ],
    "name:und_x_variant":[
        "Chumanskoye"
    ],
    "wof:name":"Chumanka",
    "wof:placetype":"locality"
},
  "geometry": {"coordinates":[80.43333,53.51667],"type":"Point"}
}