{
  "type": "Feature",
  "properties": {
    "gn:country":"RU",
    "gn:fcode":"PPL",
    "gn:population":1450,
    "iso:country":"RU",
    "name:azb_x_preferred":[
        "\u0644\u0648\u0631\u06cc\u0646\u0648"
    ],
    "name:bul_x_preferred":[
        "\u041b\u043e\u0440\u0438\u043d\u043e"
    ],
    "name:cat_x_preferred":[
        "Lorino"
    ],
    "name:ceb_x_preferred":[
        "Lorino"
    ],
    "name:che_x_preferred":[
        "\u041b\u043e\u0440\u0438\u043d\u043e"
    ],
    "name:deu_x_preferred":[
        "Lorino"
    ],
    "name:eng_x_preferred":[
        "Lorino"
    ],
    "name:fra_x_preferred":[
        "Lorino"
    ],
    "name:heb_x_preferred":[
        "\u05dc\u05d5\u05e8\u05d9\u05e0\u05d5"
    ],
    "name:ita_x_preferred":[
        "Lorino"
    ],
    "name:jpn_x_preferred":[
        "\u30ed\u30ea\u30ce"
    ],
    "name:lav_x_preferred":[
        "Lorina"
    ],
    "name:lit_x_preferred":[
        "Lorinas"
    ],
    "name:nld_x_preferred":[
        "Lorino"
    ],
    "name:nno_x_preferred":[
        "Lorino"
    ],
    "name:nob_x_preferred":[
        "Lorino"
    ],
    "name:rus_x_preferred":[
        "\u041b\u043e\u0440\u0438\u043d\u043e"
    ],
    "name:sqi_x_preferred":[
        "Lorino"
    ],
    "name:swe_x_preferred":[
        "Lorino"
    ],
    "name:ukr_x_preferred":[
        "\u041b\u043e\u0440\u0456\u043d\u043e"
    ],
    "name:und_x_variant":[
        "Loren"
    ],
    "qs:name":"Lorino",
    "qs:photos_9r":0,
    "qs:photos_sr":0,
    "qs:pop_sr":"3",
    "wd:wordcount":26,
    "wof:name":"Lorino",
    "wof:placetype":"locality",
    "wof:population":1450
},
  "geometry": {"coordinates":[-171.70396,65.50331],"type":"Point"}
}