{
  "type": "Feature",
  "properties": {
    "gn:country":"RU",
    "gn:fcode":"PPL",
    "gn:pop":1450,
    "iso:country":"RU",
    "name:bul_x_preferred":[
        "\u041b\u043e\u0440\u0438\u043d\u043e"
    ],
    "name:cat_x_preferred":[
        "Lorino"
    ],
    "name:ceb_x_preferred":[
        "Lorino"
    ],
    "name:che_x_preferred":[
        "\u041b\u043e\u0440\u0438\u043d\u043e"
    ],
    "name:deu_x_preferred":[
        "Lorino"
    ],
    "name:eng_x_preferred":[
        "Lorino"
    ],
    "name:fra_x_preferred":[
        "Lorino"
    ],
    "name:ita_x_preferred":[
        "Lorino"
    ],
    "name:lit_x_preferred":[
        "Lorinas"
    ],
    "name:nld_x_preferred":[
        "Lorino"
    ],
    "name:rus_x_preferred":[
        "\u041b\u043e\u0440\u0438\u043d\u043e"
    ],
    "name:swe_x_preferred":[
        "Lorino"
    ],
    "name:unk_x_variant":[
        "Loren"
    ],
    "qs:name":"Lorino",
    "qs:photos_9r":0,
    "qs:photos_sr":0,
    "qs:pop_sr":"3",
    "wd:wordcount":26,
    "wof:name":"Lorino",
    "wof:placetype":"locality",
    "wof:population":1450
},
  "geometry": {"coordinates":[-171.70396,65.50331],"type":"Point"}
}