{
  "type": "Feature",
  "properties": {
    "gn:admin1_code":"16",
    "gn:asciiname":"Yalushevo",
    "gn:country_code":"RU",
    "gn:dem":93,
    "gn:feature_class":"P",
    "gn:feature_code":"PPL",
    "gn:name":"Yalushevo",
    "gn:population":0,
    "gn:timezone":"Europe/Moscow",
    "iso:country":"RU",
    "name:rus_x_preferred":[
        "\u042f\u043b\u0443\u0448\u0435\u0432\u043e"
    ],
    "name:und_x_variant":[
        "\u042f\u043b\u0443\u0448\u0435\u0432\u043e"
    ],
    "wof:name":"Yalushevo",
    "wof:placetype":"locality"
},
  "geometry": {"coordinates":[46.5394,54.8666],"type":"Point"}
}