{
  "type": "Feature",
  "properties": {
    "gn:admin1_code":"42",
    "gn:asciiname":"Khevron'ino",
    "gn:country_code":"RU",
    "gn:dem":76,
    "gn:feature_class":"P",
    "gn:feature_code":"PPL",
    "gn:name":"Khevron\u2019ino",
    "gn:population":0,
    "gn:timezone":"Europe/Moscow",
    "iso:country":"RU",
    "name:eng_x_preferred":[
        "Khevron'ino"
    ],
    "name:nor_x_preferred":[
        "Khevronino"
    ],
    "name:rus_x_preferred":[
        "\u0425\u0435\u0432\u0440\u043e\u043d\u044c\u0438\u043d\u043e"
    ],
    "name:und_x_variant":[
        "Khevron\u2019ino"
    ],
    "wof:name":"Khevron'ino",
    "wof:placetype":"locality"
},
  "geometry": {"coordinates":[34.35,60.95],"type":"Point"}
}