{
  "type": "Feature",
  "properties": {
    "gn:admin1_code":"13",
    "gn:asciiname":"Voskresenskoye",
    "gn:country_code":"RU",
    "gn:dem":247,
    "gn:feature_class":"P",
    "gn:feature_code":"PPL",
    "gn:name":"Voskresenskoye",
    "gn:population":0,
    "gn:timezone":"Asia/Yekaterinburg",
    "iso:country":"RU",
    "name:eng_x_preferred":[
        "Voskresenskoye"
    ],
    "name:nor_x_preferred":[
        "Voskresenskoje"
    ],
    "name:rus_x_preferred":[
        "\u0412\u043e\u0441\u043a\u0440\u0435\u0441\u0435\u043d\u0441\u043a\u043e\u0435"
    ],
    "wof:name":"Voskresenskoye",
    "wof:placetype":"locality"
},
  "geometry": {"coordinates":[60.8328,56.0664],"type":"Point"}
}