{
  "type": "Feature",
  "properties": {
    "gn:admin1_code":"69",
    "gn:asciiname":"Semukhina",
    "gn:country_code":"RU",
    "gn:dem":216,
    "gn:feature_class":"P",
    "gn:feature_code":"PPL",
    "gn:name":"Semukhina",
    "gn:population":0,
    "gn:timezone":"Europe/Moscow",
    "iso:country":"RU",
    "name:rus_x_preferred":[
        "\u0421\u0435\u043c\u0443\u0445\u0438\u043d\u0430"
    ],
    "name:und_x_variant":[
        "\u0421\u0435\u043c\u0443\u0445\u0438\u043d\u0430"
    ],
    "wof:name":"Semukhina",
    "wof:placetype":"locality"
},
  "geometry": {"coordinates":[32.62222,55.09972],"type":"Point"}
}