{
  "type": "Feature",
  "properties": {
    "gn:admin1_code":"31",
    "gn:asciiname":"Bol'shoy Anzas",
    "gn:country_code":"RU",
    "gn:dem":1138,
    "gn:feature_class":"P",
    "gn:feature_code":"PPL",
    "gn:name":"Bol\u2019shoy Anzas",
    "gn:population":0,
    "gn:timezone":"Asia/Krasnoyarsk",
    "iso:country":"RU",
    "name:rus_x_preferred":[
        "\u0411\u043e\u043b\u044c\u0448\u043e\u0439 \u0410\u043d\u0437\u0430\u0441"
    ],
    "name:und_x_variant":[
        "Bol\u2019shoy Anzas"
    ],
    "wof:name":"Bol'shoy Anzas",
    "wof:placetype":"locality"
},
  "geometry": {"coordinates":[89.56667,52.21667],"type":"Point"}
}