{
  "type": "Feature",
  "properties": {
    "gn:admin1_code":"67.0",
    "gn:asciiname":"Baltiyka",
    "gn:country_code":"RU",
    "gn:dem":74,
    "gn:feature_class":"P",
    "gn:feature_code":"PPL",
    "gn:name":"Baltiyka",
    "gn:population":0,
    "gn:timezone":"Europe/Saratov",
    "iso:country":"RU",
    "name:eng_x_preferred":[
        "Baltiyka"
    ],
    "name:nor_x_preferred":[
        "Baltijka"
    ],
    "name:rus_x_preferred":[
        "\u0411\u0430\u043b\u0442\u0438\u0439\u043a\u0430"
    ],
    "wof:name":"Baltiyka",
    "wof:placetype":"locality"
},
  "geometry": {"coordinates":[47.30487,50.94618],"type":"Point"}
}