{
  "type": "Feature",
  "properties": {
    "gn:admin1_code":"77.0",
    "gn:asciiname":"Borisovka",
    "gn:country_code":"RU",
    "gn:dem":228,
    "gn:feature_class":"P",
    "gn:feature_code":"PPL",
    "gn:name":"Borisovka",
    "gn:population":0,
    "gn:timezone":"Europe/Moscow",
    "iso:country":"RU",
    "name:rus_x_preferred":[
        "\u0411\u043e\u0440\u0438\u0441\u043e\u0432\u043a\u0430"
    ],
    "name:und_x_variant":[
        "\u0411\u043e\u0440\u0438\u0441\u043e\u0432\u043a\u0430"
    ],
    "wof:name":"Borisovka",
    "wof:placetype":"locality"
},
  "geometry": {"coordinates":[33.57611,56.47444],"type":"Point"}
}