{
  "type": "Feature",
  "properties": {
    "gn:admin1_code":"73",
    "gn:asciiname":"Ural",
    "gn:country_code":"RU",
    "gn:dem":177,
    "gn:feature_class":"P",
    "gn:feature_code":"PPL",
    "gn:name":"Ural",
    "gn:population":0,
    "gn:timezone":"Europe/Moscow",
    "iso:country":"RU",
    "name:ara_x_preferred":[
        "\u0623\u0648\u0631\u0627\u0644"
    ],
    "name:aze_x_preferred":[
        "Ural"
    ],
    "name:bak_x_preferred":[
        "\u0423\u0440\u0430\u043b"
    ],
    "name:bar_x_preferred":[
        "Ural"
    ],
    "name:ben_x_preferred":[
        "\u0987\u0989\u09b0\u09be\u09b2"
    ],
    "name:bos_x_preferred":[
        "Ural"
    ],
    "name:bul_x_preferred":[
        "\u0423\u0440\u0430\u043b"
    ],
    "name:ceb_x_preferred":[
        "Ural"
    ],
    "name:ces_x_preferred":[
        "Ural"
    ],
    "name:cym_x_preferred":[
        "Wral"
    ],
    "name:deu_x_preferred":[
        "Ural"
    ],
    "name:epo_x_preferred":[
        "Uralo"
    ],
    "name:est_x_preferred":[
        "Ural"
    ],
    "name:fas_x_preferred":[
        "\u0627\u0648\u0631\u0627\u0644"
    ],
    "name:fin_x_preferred":[
        "Ural"
    ],
    "name:frr_x_preferred":[
        "Uraal"
    ],
    "name:fry_x_preferred":[
        "Oeral"
    ],
    "name:heb_x_preferred":[
        "\u05d0\u05d5\u05e8\u05dc"
    ],
    "name:hrv_x_preferred":[
        "Ural"
    ],
    "name:hsb_x_preferred":[
        "Ural"
    ],
    "name:hun_x_preferred":[
        "Ur\u00e1l"
    ],
    "name:hye_x_preferred":[
        "\u0548\u0582\u0580\u0561\u056c"
    ],
    "name:ita_x_preferred":[
        "Ural"
    ],
    "name:jpn_x_preferred":[
        "\u30a6\u30e9\u30eb"
    ],
    "name:kat_x_preferred":[
        "\u10e3\u10e0\u10d0\u10da\u10d8"
    ],
    "name:lav_x_preferred":[
        "Ural"
    ],
    "name:lit_x_preferred":[
        "Uralas"
    ],
    "name:mkd_x_preferred":[
        "\u0423\u0440\u0430\u043b"
    ],
    "name:nld_x_preferred":[
        "Oeral"
    ],
    "name:nno_x_preferred":[
        "Ural"
    ],
    "name:nor_x_preferred":[
        "Ural"
    ],
    "name:pol_x_preferred":[
        "Ural"
    ],
    "name:ron_x_preferred":[
        "Ural"
    ],
    "name:rus_x_preferred":[
        "\u0423\u0440\u0430\u043b"
    ],
    "name:sin_x_preferred":[
        "\u0dba\u0dd6\u0dbb\u0dbd\u0dca"
    ],
    "name:slk_x_preferred":[
        "Ural"
    ],
    "name:slv_x_preferred":[
        "Ural"
    ],
    "name:spa_x_preferred":[
        "Ural"
    ],
    "name:srp_x_preferred":[
        "\u0423\u0440\u0430\u043b"
    ],
    "name:swa_x_preferred":[
        "Ural"
    ],
    "name:swe_x_preferred":[
        "Ural"
    ],
    "name:tat_x_preferred":[
        "\u0496\u0430\u0435\u043a"
    ],
    "name:tgl_x_preferred":[
        "Ural"
    ],
    "name:tur_x_preferred":[
        "Ural"
    ],
    "name:ukr_x_preferred":[
        "\u0423\u0440\u0430\u043b"
    ],
    "name:urd_x_preferred":[
        "\u0627\u0648\u0631\u0627\u0644"
    ],
    "name:uzb_x_preferred":[
        "Ural"
    ],
    "name:zho_x_preferred":[
        "\u70cf\u62c9\u723e"
    ],
    "wof:name":"Ural",
    "wof:placetype":"locality"
},
  "geometry": {"coordinates":[53.13333000000001,54.68333000000001],"type":"Point"}
}