{
  "type": "Feature",
  "properties": {
    "gn:admin1_code":"73",
    "gn:asciiname":"Ural",
    "gn:country_code":"RU",
    "gn:dem":177,
    "gn:feature_class":"P",
    "gn:feature_code":"PPL",
    "gn:name":"Ural",
    "gn:population":0,
    "gn:timezone":"Europe/Moscow",
    "iso:country":"RU",
    "name:rus_x_preferred":[
        "\u0423\u0440\u0430\u043b"
    ],
    "name:und_x_variant":[
        "\u0423\u0440\u0430\u043b"
    ],
    "wof:name":"Ural",
    "wof:placetype":"locality"
},
  "geometry": {"coordinates":[53.13333000000001,54.68333000000001],"type":"Point"}
}