{
  "type": "Feature",
  "properties": {
    "gn:admin1_code":"54",
    "gn:asciiname":"Glukhovka",
    "gn:country_code":"RU",
    "gn:dem":94,
    "gn:feature_class":"P",
    "gn:feature_code":"PPL",
    "gn:name":"Glukhovka",
    "gn:population":0,
    "gn:timezone":"Asia/Omsk",
    "iso:country":"RU",
    "name:rus_x_preferred":[
        "\u0413\u043b\u0443\u0445\u043e\u0432\u043a\u0430"
    ],
    "wof:name":"Glukhovka",
    "wof:placetype":"locality"
},
  "geometry": {"coordinates":[74.71207,55.08665],"type":"Point"}
}