{
  "type": "Feature",
  "properties": {
    "gn:admin1_code":"67.0",
    "gn:asciiname":"Aleksandrovsk",
    "gn:country_code":"RU",
    "gn:dem":88,
    "gn:feature_class":"P",
    "gn:feature_code":"PPL",
    "gn:name":"Aleksandrovsk",
    "gn:population":0,
    "gn:timezone":"Europe/Saratov",
    "iso:country":"RU",
    "name:nor_x_preferred":[
        "Aleksandrovsk"
    ],
    "name:rus_x_preferred":[
        "\u0410\u043b\u0435\u043a\u0441\u0430\u043d\u0434\u0440\u043e\u0432\u0441\u043a"
    ],
    "name:und_x_variant":[
        "Aleksandrovskiy"
    ],
    "wof:name":"Aleksandrovsk",
    "wof:placetype":"locality"
},
  "geometry": {"coordinates":[48.91667,51.46667],"type":"Point"}
}