{
  "type": "Feature",
  "properties": {
    "gn:admin1_code":"86.0",
    "gn:asciiname":"Abrosimovo",
    "gn:country_code":"RU",
    "gn:dem":127,
    "gn:feature_class":"P",
    "gn:feature_code":"PPL",
    "gn:name":"Abrosimovo",
    "gn:population":0,
    "gn:timezone":"Europe/Moscow",
    "iso:country":"RU",
    "name:nor_x_preferred":[
        "Abrosimovo"
    ],
    "name:rus_x_preferred":[
        "\u0410\u0431\u0440\u043e\u0441\u0438\u043c\u043e\u0432\u043e"
    ],
    "name:und_x_variant":[
        "Abrasimovo"
    ],
    "wof:name":"Abrosimovo",
    "wof:placetype":"locality"
},
  "geometry": {"coordinates":[40.89532,49.89106],"type":"Point"}
}