{
  "type": "Feature",
  "properties": {
    "gn:admin1_code":"77.0",
    "gn:asciiname":"Bosharovo",
    "gn:country_code":"RU",
    "gn:dem":261,
    "gn:feature_class":"P",
    "gn:feature_code":"PPL",
    "gn:name":"Bosharovo",
    "gn:population":0,
    "gn:timezone":"Europe/Moscow",
    "iso:country":"RU",
    "name:rus_x_preferred":[
        "\u0411\u043e\u0448\u0430\u0440\u043e\u0432\u043e"
    ],
    "wof:name":"Bosharovo",
    "wof:placetype":"locality"
},
  "geometry": {"coordinates":[34.35902,56.74369],"type":"Point"}
}