{
  "type": "Feature",
  "properties": {
    "gn:admin1_code":"45",
    "gn:asciiname":"Pertyukovo",
    "gn:country_code":"RU",
    "gn:dem":172,
    "gn:feature_class":"P",
    "gn:feature_code":"PPL",
    "gn:name":"Pertyukovo",
    "gn:population":0,
    "gn:timezone":"Europe/Moscow",
    "iso:country":"RU",
    "name:rus_x_preferred":[
        "\u041f\u0435\u0440\u0442\u044e\u043a\u043e\u0432\u043e"
    ],
    "name:und_x_variant":[
        "Petryukovo",
        "Pertyukovo",
        "\u041f\u0435\u0440\u0442\u044e\u043a\u043e\u0432\u043e"
    ],
    "wof:name":"Pertyukovo",
    "wof:placetype":"locality"
},
  "geometry": {"coordinates":[46.36735,56.15626],"type":"Point"}
}