{
  "type": "Feature",
  "properties": {
    "gn:admin1_code":"25",
    "gn:asciiname":"Yeropkino",
    "gn:country_code":"RU",
    "gn:dem":187,
    "gn:feature_class":"P",
    "gn:feature_code":"PPL",
    "gn:name":"Yeropkino",
    "gn:population":0,
    "gn:timezone":"Europe/Moscow",
    "iso:country":"RU",
    "name:und_x_variant":[
        "Yerobkino",
        "Yeropkino"
    ],
    "wof:name":"Yeropkino",
    "wof:placetype":"locality"
},
  "geometry": {"coordinates":[35.30837000000001,54.25556],"type":"Point"}
}