{
  "type": "Feature",
  "properties": {
    "gn:country":"RU",
    "gn:fcode":"PPL",
    "gn:population":0,
    "iso:country":"RU",
    "name:eng_x_preferred":[
        "Naumovka"
    ],
    "name:nor_x_preferred":[
        "Naumovka"
    ],
    "name:rus_x_preferred":[
        "\u041d\u0430\u0443\u043c\u043e\u0432\u043a\u0430"
    ],
    "qs:name":"Naumovka",
    "qs:name_adm0":"Russia",
    "qs:name_adm1":"Bashkortostan Republic",
    "qs:photos_9r":0,
    "qs:photos_sr":0,
    "qs:placetype":"Town",
    "qs:pop_sr":"0",
    "wof:name":"Naumovka",
    "wof:placetype":"locality",
    "wof:population":0
},
  "geometry": {"coordinates":[55.91763,53.52229],"type":"Point"}
}