{
  "type": "Feature",
  "properties": {
    "gn:admin1_code":"85",
    "gn:asciiname":"Safonikha",
    "gn:country_code":"RU",
    "gn:dem":160,
    "gn:feature_class":"P",
    "gn:feature_code":"PPL",
    "gn:name":"Safonikha",
    "gn:population":0,
    "gn:timezone":"Europe/Moscow",
    "iso:country":"RU",
    "name:eng_x_preferred":[
        "Safonikha"
    ],
    "name:nor_x_preferred":[
        "Safonikha"
    ],
    "name:rus_x_preferred":[
        "\u0421\u0430\u0444\u043e\u043d\u0438\u0445\u0430"
    ],
    "wof:name":"Safonikha",
    "wof:placetype":"locality"
},
  "geometry": {"coordinates":[40.68046,59.98522],"type":"Point"}
}