{
  "type": "Feature",
  "properties": {
    "gn:admin1_code":"11",
    "gn:asciiname":"Todogto",
    "gn:country_code":"RU",
    "gn:dem":595,
    "gn:feature_class":"P",
    "gn:feature_code":"PPL",
    "gn:name":"Todogto",
    "gn:population":0,
    "gn:timezone":"Asia/Irkutsk",
    "iso:country":"RU",
    "name:rus_x_preferred":[
        "\u0422\u043e\u0434\u043e\u0433\u0442\u043e"
    ],
    "name:und_x_variant":[
        "Opytnoye Pole",
        "Todogto"
    ],
    "wof:name":"Todogto",
    "wof:placetype":"locality"
},
  "geometry": {"coordinates":[108.05098999999998,51.84769],"type":"Point"}
}