{
  "type": "Feature",
  "properties": {
    "gn:country":"RU",
    "gn:fcode":"PPL",
    "gn:population":0,
    "iso:country":"RU",
    "name:eng_x_preferred":[
        "Moskva"
    ],
    "name:nor_x_preferred":[
        "Moskva"
    ],
    "name:ukr_x_preferred":[
        "\u041c\u043e\u0441\u043a\u0432\u0430"
    ],
    "qs:name":"Moskvyata",
    "qs:name_adm0":"Russia",
    "qs:name_adm1":"Kirov Oblast",
    "qs:photos_9r":0,
    "qs:photos_sr":0,
    "qs:placetype":"Town",
    "qs:pop_sr":"0",
    "wof:name":"Moskvyata",
    "wof:placetype":"locality",
    "wof:population":0
},
  "geometry": {"coordinates":[49.10618,57.96818],"type":"Point"}
}