{
  "type": "Feature",
  "properties": {
    "gn:admin1_code":"33",
    "gn:asciiname":"Malyye Bulatovtsy",
    "gn:country_code":"RU",
    "gn:dem":153,
    "gn:feature_class":"P",
    "gn:feature_code":"PPL",
    "gn:name":"Malyye Bulatovtsy",
    "gn:population":0,
    "gn:timezone":"Europe/Kirov",
    "iso:country":"RU",
    "name:rus_x_preferred":[
        "\u041c\u0430\u043b\u044b\u0435 \u0411\u0443\u043b\u0430\u0442\u043e\u0432\u0446\u044b"
    ],
    "name:und_x_variant":[
        "\u041c\u0430\u043b\u044b\u0435 \u0411\u0443\u043b\u0430\u0442\u043e\u0432\u0446\u044b"
    ],
    "wof:name":"Malyye Bulatovtsy",
    "wof:placetype":"locality"
},
  "geometry": {"coordinates":[51.61667,57.56667],"type":"Point"}
}