{
  "type": "Feature",
  "properties": {
    "gn:admin1_code":"33",
    "gn:asciiname":"Shchetkino",
    "gn:country_code":"RU",
    "gn:dem":109,
    "gn:feature_class":"P",
    "gn:feature_code":"PPL",
    "gn:name":"Shch\u00ebtkino",
    "gn:population":0,
    "gn:timezone":"Europe/Kirov",
    "iso:country":"RU",
    "name:eng_x_preferred":[
        "Shch\u00ebtkino"
    ],
    "name:nor_x_preferred":[
        "Sjtsjetkino"
    ],
    "name:rus_x_preferred":[
        "\u0429\u0435\u0442\u043a\u0438\u043d\u043e"
    ],
    "name:rus_x_variant":[
        "\u0429\u0451\u0442\u043a\u0438\u043d\u043e"
    ],
    "name:und_x_variant":[
        "Selo-Shch\u00ebtkino",
        "Shetkino",
        "Shch\u00ebtkino",
        "\u0429\u0451\u0442\u043a\u0438\u043d\u043e"
    ],
    "wof:name":"Shchetkino",
    "wof:placetype":"locality"
},
  "geometry": {"coordinates":[47.43098,60.21725],"type":"Point"}
}