{
  "type": "Feature",
  "properties": {
    "gn:admin1_code":"13",
    "gn:asciiname":"Chuykova",
    "gn:country_code":"RU",
    "gn:dem":210,
    "gn:feature_class":"P",
    "gn:feature_code":"PPL",
    "gn:name":"Chuykova",
    "gn:population":0,
    "gn:timezone":"Asia/Yekaterinburg",
    "iso:country":"RU",
    "name:rus_x_preferred":[
        "\u0427\u0443\u0439\u043a\u043e\u0432\u0430"
    ],
    "wof:name":"Chuykova",
    "wof:placetype":"locality"
},
  "geometry": {"coordinates":[61.95,54.55],"type":"Point"}
}