{
  "type": "Feature",
  "properties": {
    "gn:admin1_code":"42",
    "gn:asciiname":"Zales'ye",
    "gn:country_code":"RU",
    "gn:dem":76,
    "gn:feature_class":"P",
    "gn:feature_code":"PPL",
    "gn:name":"Zales\u2019ye",
    "gn:population":0,
    "gn:timezone":"Europe/Moscow",
    "iso:country":"RU",
    "name:fin_x_preferred":[
        "Mets\u00e4kyl\u00e4"
    ],
    "name:rus_x_preferred":[
        "\u0417\u0430\u043f\u043e\u043b\u044c\u0435"
    ],
    "name:und_x_variant":[
        "Zales\u2019ye"
    ],
    "wof:name":"Zales'ye",
    "wof:placetype":"locality"
},
  "geometry": {"coordinates":[28.47728,59.79635],"type":"Point"}
}