{
  "type": "Feature",
  "properties": {
    "gn:admin1_code":"47.0",
    "gn:asciiname":"Bol'shoye Karasevo",
    "gn:country_code":"RU",
    "gn:dem":154,
    "gn:feature_class":"P",
    "gn:feature_code":"PPL",
    "gn:name":"Bol\u2019shoye Karas\u00ebvo",
    "gn:population":0,
    "gn:timezone":"Europe/Moscow",
    "iso:country":"RU",
    "name:rus_x_preferred":[
        "\u0411\u043e\u043b\u044c\u0448\u043e\u0435 \u041a\u0430\u0440\u0430\u0441\u0451\u0432\u043e"
    ],
    "name:und_x_variant":[
        "Karas\u00ebvo",
        "Bol\u2019shoye Karas\u00ebvo"
    ],
    "wof:name":"Bol'shoye Karasevo",
    "wof:placetype":"locality"
},
  "geometry": {"coordinates":[38.63475,55.00088],"type":"Point"}
}