{
  "type": "Feature",
  "properties": {
    "gn:admin1_code":"75",
    "gn:asciiname":"Vakhtovyy Poselok Oleniy",
    "gn:country_code":"RU",
    "gn:dem":91,
    "gn:feature_class":"P",
    "gn:feature_code":"PPL",
    "gn:name":"Vakhtovyy Pos\u00eblok Oleniy",
    "gn:population":0,
    "gn:timezone":"Asia/Tomsk",
    "iso:country":"RU",
    "name:rus_x_preferred":[
        "\u0412\u0430\u0445\u0442\u043e\u0432\u044b\u0439 \u041f\u043e\u0441\u0451\u043b\u043e\u043a \u041e\u043b\u0435\u043d\u0438\u0439"
    ],
    "name:und_x_variant":[
        "Vakhtovyy Pos\u00eblok Oleniy",
        "\u0412\u0430\u0445\u0442\u043e\u0432\u044b\u0439 \u041f\u043e\u0441\u0451\u043b\u043e\u043a \u041e\u043b\u0435\u043d\u0438\u0439"
    ],
    "wof:name":"Vakhtovyy Poselok Oleniy",
    "wof:placetype":"locality"
},
  "geometry": {"coordinates":[76.32470000000001,59.3519],"type":"Point"}
}