{
  "type": "Feature",
  "properties": {
    "gn:admin1_code":"55",
    "gn:asciiname":"Nikol'sk",
    "gn:country_code":"RU",
    "gn:dem":156,
    "gn:feature_class":"P",
    "gn:feature_code":"PPL",
    "gn:name":"Nikol\u2019sk",
    "gn:population":0,
    "gn:timezone":"Asia/Yekaterinburg",
    "iso:country":"RU",
    "name:eng_x_preferred":[
        "Nikol'sk"
    ],
    "name:rus_x_preferred":[
        "\u041d\u0438\u043a\u043e\u043b\u044c\u0441\u043a\u043e\u0435"
    ],
    "name:rus_x_variant":[
        "\u041d\u0438\u043a\u043e\u043b\u044c\u0441\u043a"
    ],
    "name:und_x_variant":[
        "Nikolski",
        "Nikol\u2019skiy",
        "Nikol\u2019skoye",
        "Nikol\u2019sk"
    ],
    "wof:name":"Nikol'sk",
    "wof:placetype":"locality"
},
  "geometry": {"coordinates":[57.1077,51.3522],"type":"Point"}
}