{
  "type": "Feature",
  "properties": {
    "gn:admin1_code":"33",
    "gn:asciiname":"Meletskiye Gorki",
    "gn:country_code":"RU",
    "gn:dem":85,
    "gn:feature_class":"P",
    "gn:feature_code":"PPL",
    "gn:name":"Meletskiye Gorki",
    "gn:population":0,
    "gn:timezone":"Europe/Kirov",
    "iso:country":"RU",
    "name:rus_x_preferred":[
        "\u041c\u0435\u043b\u0435\u0442\u0441\u043a\u0438\u0435 \u0413\u043e\u0440\u043a\u0438"
    ],
    "name:und_x_variant":[
        "Gorki",
        "Meletskiye Gorki",
        "\u041c\u0435\u043b\u0435\u0442\u0441\u043a\u0438\u0435 \u0413\u043e\u0440\u043a\u0438"
    ],
    "wof:name":"Meletskiye Gorki",
    "wof:placetype":"locality"
},
  "geometry": {"coordinates":[50.78100000000001,56.6091],"type":"Point"}
}