{
  "type": "Feature",
  "properties": {
    "gn:admin1_code":"73",
    "gn:asciiname":"Staroye Akhmetovo",
    "gn:country_code":"RU",
    "gn:dem":109,
    "gn:feature_class":"P",
    "gn:feature_code":"PPL",
    "gn:name":"Staroye Akhmetovo",
    "gn:population":0,
    "gn:timezone":"Europe/Moscow",
    "iso:country":"RU",
    "name:rus_x_preferred":[
        "\u0421\u0442\u0430\u0440\u043e\u0435 \u0410\u0445\u043c\u0435\u0442\u043e\u0432\u043e"
    ],
    "wof:name":"Staroye Akhmetovo",
    "wof:placetype":"locality"
},
  "geometry": {"coordinates":[52.6029,55.2931],"type":"Point"}
}