{
  "type": "Feature",
  "properties": {
    "gn:admin1_code":"42.0",
    "gn:asciiname":"Azmozero",
    "gn:country_code":"RU",
    "gn:dem":159,
    "gn:feature_class":"P",
    "gn:feature_code":"PPL",
    "gn:name":"Azmozero",
    "gn:population":0,
    "gn:timezone":"Europe/Moscow",
    "iso:country":"RU",
    "name:nor_x_preferred":[
        "Azmozero"
    ],
    "name:rus_x_preferred":[
        "\u0410\u0437\u043c\u043e\u0437\u0435\u0440\u043e"
    ],
    "wof:name":"Azmozero",
    "wof:placetype":"locality"
},
  "geometry": {"coordinates":[34.95873,60.45634],"type":"Point"}
}