{
  "type": "Feature",
  "properties": {
    "gn:admin1_code":"23",
    "gn:asciiname":"Zalivino",
    "gn:country_code":"RU",
    "gn:dem":1,
    "gn:feature_class":"P",
    "gn:feature_code":"PPL",
    "gn:name":"Zalivino",
    "gn:population":0,
    "gn:timezone":"Europe/Kaliningrad",
    "iso:country":"RU",
    "name:und_x_variant":[
        "Haffwinkel",
        "Labaginen",
        "Zalivino"
    ],
    "wof:name":"Zalivino",
    "wof:placetype":"locality"
},
  "geometry": {"coordinates":[21.05798,54.89829],"type":"Point"}
}