{
  "type": "Feature",
  "properties": {
    "gn:admin1_code":"8",
    "gn:asciiname":"Kara-Mala",
    "gn:country_code":"RU",
    "gn:dem":397,
    "gn:feature_class":"P",
    "gn:feature_code":"PPL",
    "gn:name":"Kara-Mala",
    "gn:population":0,
    "gn:timezone":"Asia/Yekaterinburg",
    "iso:country":"RU",
    "name:rus_x_preferred":[
        "\u041a\u0430\u0440\u0430-\u041c\u0430\u043b\u0430"
    ],
    "name:und_x_variant":[
        "\u041a\u0430\u0440\u0430-\u041c\u0430\u043b\u0430"
    ],
    "wof:name":"Kara-Mala",
    "wof:placetype":"locality"
},
  "geometry": {"coordinates":[57.05,53.38333000000001],"type":"Point"}
}