{
  "type": "Feature",
  "properties": {
    "gn:admin1_code":"49.0",
    "gn:asciiname":"Belokamenka",
    "gn:country_code":"RU",
    "gn:dem":1,
    "gn:feature_class":"P",
    "gn:feature_code":"PPL",
    "gn:name":"Belokamenka",
    "gn:population":0,
    "gn:timezone":"Europe/Moscow",
    "iso:country":"RU",
    "name:eng_x_preferred":[
        "Belokamenka"
    ],
    "name:nor_x_preferred":[
        "Belokamenka"
    ],
    "name:rus_x_preferred":[
        "\u0411\u0435\u043b\u043e\u043a\u0430\u043c\u0435\u043d\u043a\u0430"
    ],
    "name:und_x_variant":[
        "Belokamennaya",
        "Belokomenka",
        "Bjelokamennaja",
        "\u0411\u0435\u043b\u043e\u043a\u0430\u043c\u0435\u043d\u043a\u0430",
        "Belokamenka"
    ],
    "wof:name":"Belokamenka",
    "wof:placetype":"locality"
},
  "geometry": {"coordinates":[33.17760999999999,69.08117],"type":"Point"}
}