{
  "type": "Feature",
  "properties": {
    "gn:admin1_code":"78",
    "gn:asciiname":"Zubareva",
    "gn:country_code":"RU",
    "gn:dem":95,
    "gn:feature_class":"P",
    "gn:feature_code":"PPL",
    "gn:name":"Zubareva",
    "gn:population":0,
    "gn:timezone":"Asia/Yekaterinburg",
    "iso:country":"RU",
    "name:rus_x_preferred":[
        "\u0417\u0443\u0431\u0430\u0440\u0435\u0432\u0430"
    ],
    "wof:name":"Zubareva",
    "wof:placetype":"locality"
},
  "geometry": {"coordinates":[65.268,57.0847],"type":"Point"}
}