{
  "type": "Feature",
  "properties": {
    "gn:admin1_code":"38",
    "gn:asciiname":"Khutor Tarana",
    "gn:cc2":"RU",
    "gn:country_code":"RU",
    "gn:dem":3,
    "gn:feature_class":"P",
    "gn:feature_code":"PPL",
    "gn:name":"Khutor Tarana",
    "gn:population":0,
    "gn:timezone":"Europe/Moscow",
    "iso:country":"RU",
    "name:rus_x_preferred":[
        "\u0425\u0443\u0442\u043e\u0440 \u0422\u0430\u0440\u0430\u043d\u0430"
    ],
    "name:und_x_variant":[
        "Tarana",
        "Khutor Tarana"
    ],
    "wof:name":"Khutor Tarana",
    "wof:placetype":"locality"
},
  "geometry": {"coordinates":[38.51667,45.83333],"type":"Point"}
}