{
  "type": "Feature",
  "properties": {
    "gn:admin1_code":"38",
    "gn:asciiname":"Terskiy",
    "gn:country_code":"RU",
    "gn:dem":380,
    "gn:feature_class":"P",
    "gn:feature_code":"PPL",
    "gn:name":"Terskiy",
    "gn:population":0,
    "gn:timezone":"Europe/Moscow",
    "iso:country":"RU",
    "wof:name":"Terskiy",
    "wof:placetype":"locality"
},
  "geometry": {"coordinates":[41.16417,44.60778],"type":"Point"}
}