{
  "type": "Feature",
  "properties": {
    "gn:admin1_code":"49",
    "gn:asciiname":"Kiurilo",
    "gn:country_code":"RU",
    "gn:dem":179,
    "gn:feature_class":"P",
    "gn:feature_code":"PPL",
    "gn:name":"Kiurilo",
    "gn:population":0,
    "gn:timezone":"Europe/Moscow",
    "iso:country":"RU",
    "name:rus_x_preferred":[
        "\u041a\u0438\u0443\u0440\u0438\u043b\u043e"
    ],
    "name:und_x_variant":[
        "\u041a\u0438\u0443\u0440\u0438\u043b\u043e"
    ],
    "wof:name":"Kiurilo",
    "wof:placetype":"locality"
},
  "geometry": {"coordinates":[28.89103,68.75078000000001],"type":"Point"}
}