{
  "type": "Feature",
  "properties": {
    "gn:admin1_code":"51",
    "gn:asciiname":"Krasnyy Oselok",
    "gn:country_code":"RU",
    "gn:dem":164,
    "gn:feature_class":"P",
    "gn:feature_code":"PPL",
    "gn:name":"Krasnyy Oselok",
    "gn:population":0,
    "gn:timezone":"Europe/Moscow",
    "iso:country":"RU",
    "name:rus_x_preferred":[
        "\u041a\u0440\u0430\u0441\u043d\u044b\u0439 \u041e\u0441\u0435\u043b\u043e\u043a"
    ],
    "name:und_x_variant":[
        "\u041a\u0440\u0430\u0441\u043d\u044b\u0439 \u041e\u0441\u0435\u043b\u043e\u043a"
    ],
    "wof:name":"Krasnyy Oselok",
    "wof:placetype":"locality"
},
  "geometry": {"coordinates":[45.27306,56.08416999999999],"type":"Point"}
}