{
  "type": "Feature",
  "properties": {
    "gn:admin1_code":"8.0",
    "gn:asciiname":"Battalovo",
    "gn:country_code":"RU",
    "gn:dem":503,
    "gn:feature_class":"P",
    "gn:feature_code":"PPL",
    "gn:name":"Battalovo",
    "gn:population":0,
    "gn:timezone":"Asia/Yekaterinburg",
    "iso:country":"RU",
    "name:nor_x_preferred":[
        "Battalovo"
    ],
    "name:rus_x_preferred":[
        "\u0411\u0430\u0442\u0442\u0430\u043b\u043e\u0432\u043e"
    ],
    "name:und_x_variant":[
        "Batalova",
        "Batalovo"
    ],
    "wof:name":"Battalovo",
    "wof:placetype":"locality"
},
  "geometry": {"coordinates":[58.8734,53.8835],"type":"Point"}
}