{
  "type": "Feature",
  "properties": {
    "gn:admin1_code":"10",
    "gn:asciiname":"Verkhneye Bunevo",
    "gn:country_code":"RU",
    "gn:dem":183,
    "gn:feature_class":"P",
    "gn:feature_code":"PPL",
    "gn:name":"Verkhneye Bun\u00ebvo",
    "gn:population":0,
    "gn:timezone":"Europe/Moscow",
    "iso:country":"RU",
    "name:rus_x_preferred":[
        "\u0412\u0435\u0440\u0445\u043d\u0435\u0435 \u0411\u0443\u043d\u0451\u0432\u043e"
    ],
    "name:und_x_variant":[
        "Verkhneye Bun\u00ebvo"
    ],
    "wof:name":"Verkhneye Bunevo",
    "wof:placetype":"locality"
},
  "geometry": {"coordinates":[33.77188,53.93013000000001],"type":"Point"}
}