{
  "type": "Feature",
  "properties": {
    "gn:admin1_code":"76",
    "gn:asciiname":"Kholtobino",
    "gn:country_code":"RU",
    "gn:dem":210,
    "gn:feature_class":"P",
    "gn:feature_code":"PPL",
    "gn:name":"Kholtobino",
    "gn:population":0,
    "gn:timezone":"Europe/Moscow",
    "iso:country":"RU",
    "name:eng_x_preferred":[
        "Kholtobino"
    ],
    "name:nor_x_preferred":[
        "Kholtobino"
    ],
    "name:rus_x_preferred":[
        "\u0425\u043e\u043b\u0442\u043e\u0431\u0438\u043d\u043e"
    ],
    "wof:name":"Kholtobino",
    "wof:placetype":"locality"
},
  "geometry": {"coordinates":[38.47988,54.18281],"type":"Point"}
}