{
  "type": "Feature",
  "properties": {
    "gn:admin1_code":"62",
    "gn:asciiname":"Manturovo",
    "gn:country_code":"RU",
    "gn:dem":118,
    "gn:feature_class":"P",
    "gn:feature_code":"PPL",
    "gn:name":"Manturovo",
    "gn:population":0,
    "gn:timezone":"Europe/Moscow",
    "iso:country":"RU",
    "name:rus_x_preferred":[
        "\u041c\u0430\u043d\u0442\u0443\u0440\u043e\u0432\u043e"
    ],
    "name:und_x_variant":[
        "\u041c\u0430\u043d\u0442\u0443\u0440\u043e\u0432\u043e"
    ],
    "name:vie_x_preferred":[
        "Manturovo"
    ],
    "wof:name":"Manturovo",
    "wof:placetype":"locality"
},
  "geometry": {"coordinates":[39.44293,54.68292],"type":"Point"}
}