{
  "type": "Feature",
  "properties": {
    "gn:admin1_code":"91",
    "gn:asciiname":"Kosyye Lozhki",
    "gn:country_code":"RU",
    "gn:dem":372,
    "gn:feature_class":"P",
    "gn:feature_code":"PPL",
    "gn:name":"Kosyye Lozhki",
    "gn:population":0,
    "gn:timezone":"Asia/Krasnoyarsk",
    "iso:country":"RU",
    "name:eng_x_preferred":[
        "Kosyye Lozhki"
    ],
    "name:nor_x_preferred":[
        "Kosye-Lozjki"
    ],
    "name:rus_x_preferred":[
        "\u041a\u043e\u0441\u044b\u0435-\u041b\u043e\u0436\u043a\u0438"
    ],
    "name:rus_x_variant":[
        "\u041a\u043e\u0441\u044b\u0435 \u041b\u043e\u0436\u043a\u0438"
    ],
    "name:und_x_variant":[
        "Kosoy Lozhon",
        "Kosoy Lozhok",
        "Kosay Lozhok",
        "Kosyye Lozhki"
    ],
    "wof:name":"Kosyye Lozhki",
    "wof:placetype":"locality"
},
  "geometry": {"coordinates":[89.21722,55.37889000000001],"type":"Point"}
}