{
  "type": "Feature",
  "properties": {
    "gn:admin1_code":"70.0",
    "gn:asciiname":"Borodynovka",
    "gn:cc2":"RU",
    "gn:country_code":"RU",
    "gn:dem":323,
    "gn:feature_class":"P",
    "gn:feature_code":"PPL",
    "gn:name":"Borodynovka",
    "gn:population":0,
    "gn:timezone":"Europe/Moscow",
    "iso:country":"RU",
    "name:rus_x_preferred":[
        "\u0411\u043e\u0440\u043e\u0434\u044b\u043d\u043e\u0432\u043a\u0430"
    ],
    "name:und_x_variant":[
        "Borodynka",
        "Borodynovka",
        "\u0411\u043e\u0440\u043e\u0434\u044b\u043d\u043e\u0432\u043a\u0430"
    ],
    "wof:name":"Borodynovka",
    "wof:placetype":"locality"
},
  "geometry": {"coordinates":[43.13556,44.14861],"type":"Point"}
}