{
  "type": "Feature",
  "properties": {
    "gn:admin1_code":"84",
    "gn:asciiname":"Zimovskaya Panika",
    "gn:country_code":"RU",
    "gn:dem":91,
    "gn:feature_class":"P",
    "gn:feature_code":"PPL",
    "gn:name":"Zimovskaya Panika",
    "gn:population":0,
    "gn:timezone":"Europe/Volgograd",
    "iso:country":"RU",
    "name:rus_x_preferred":[
        "\u0417\u0438\u043c\u043e\u0432\u0441\u043a\u0430\u044f \u041f\u0430\u043d\u0438\u043a\u0430"
    ],
    "wof:name":"Zimovskaya Panika",
    "wof:placetype":"locality"
},
  "geometry": {"coordinates":[43.6836,49.6193],"type":"Point"}
}