{
  "type": "Feature",
  "properties": {
    "gn:admin1_code":"56",
    "gn:asciiname":"Gorbatovka",
    "gn:country_code":"RU",
    "gn:dem":226,
    "gn:feature_class":"P",
    "gn:feature_code":"PPL",
    "gn:name":"Gorbatovka",
    "gn:population":0,
    "gn:timezone":"Europe/Moscow",
    "iso:country":"RU",
    "name:rus_x_preferred":[
        "\u0413\u043e\u0440\u0431\u0430\u0442\u043e\u0432\u043a\u0430"
    ],
    "name:und_x_variant":[
        "\u0413\u043e\u0440\u0431\u0430\u0442\u043e\u0432\u043a\u0430"
    ],
    "wof:name":"Gorbatovka",
    "wof:placetype":"locality"
},
  "geometry": {"coordinates":[36.68333,53.18333000000001],"type":"Point"}
}