{
  "type": "Feature",
  "properties": {
    "gn:admin1_code":"56",
    "gn:asciiname":"Gorbatovka",
    "gn:country_code":"RU",
    "gn:dem":226,
    "gn:feature_class":"P",
    "gn:feature_code":"PPL",
    "gn:name":"Gorbatovka",
    "gn:population":0,
    "gn:timezone":"Europe/Moscow",
    "iso:country":"RU",
    "name:ara_x_preferred":[
        "\u063a\u0648\u0631\u0628\u0627\u062a\u0648\u0641\u0643\u0627"
    ],
    "name:ceb_x_preferred":[
        "Gorbatovka"
    ],
    "name:che_x_preferred":[
        "\u0413\u043e\u0440\u0431\u0430\u0442\u043e\u0432\u043a\u0430"
    ],
    "name:pol_x_preferred":[
        "Gorbatowka"
    ],
    "name:rus_x_preferred":[
        "\u0413\u043e\u0440\u0431\u0430\u0442\u043e\u0432\u043a\u0430"
    ],
    "name:ukr_x_preferred":[
        "\u0413\u043e\u0440\u0431\u0430\u0442\u043e\u0432\u043a\u0430"
    ],
    "wof:name":"Gorbatovka",
    "wof:placetype":"locality"
},
  "geometry": {"coordinates":[36.68333,53.18333000000001],"type":"Point"}
}