{
  "type": "Feature",
  "properties": {
    "gn:admin1_code":"90",
    "gn:asciiname":"Mys",
    "gn:country_code":"RU",
    "gn:dem":157,
    "gn:feature_class":"P",
    "gn:feature_code":"PPL",
    "gn:name":"Mys",
    "gn:population":0,
    "gn:timezone":"Asia/Yekaterinburg",
    "iso:country":"RU",
    "name:eng_x_preferred":[
        "Mys"
    ],
    "name:nor_x_preferred":[
        "Mys"
    ],
    "name:rus_x_preferred":[
        "\u041c\u044b\u0441"
    ],
    "name:und_x_variant":[
        "\u041c\u044b\u0441"
    ],
    "wof:name":"Mys",
    "wof:placetype":"locality"
},
  "geometry": {"coordinates":[57.4661,58.5519],"type":"Point"}
}