{
  "type": "Feature",
  "properties": {
    "gn:admin1_code":"81.0",
    "gn:asciiname":"Stantsiya Yakushka",
    "gn:country_code":"RU",
    "gn:dem":100,
    "gn:feature_class":"P",
    "gn:feature_code":"PPL",
    "gn:name":"Stantsiya Yakushka",
    "gn:population":0,
    "gn:timezone":"Europe/Ulyanovsk",
    "iso:country":"RU",
    "name:rus_x_preferred":[
        "\u0421\u0442\u0430\u043d\u0446\u0438\u044f \u042f\u043a\u0443\u0448\u043a\u0430"
    ],
    "wof:name":"Stantsiya Yakushka",
    "wof:placetype":"locality"
},
  "geometry": {"coordinates":[50.074,54.1971],"type":"Point"}
}