{
  "type": "Feature",
  "properties": {
    "gn:admin1_code":"83",
    "gn:asciiname":"Parkovyy",
    "gn:country_code":"RU",
    "gn:dem":146,
    "gn:feature_class":"P",
    "gn:feature_code":"PPL",
    "gn:name":"Parkovyy",
    "gn:population":0,
    "gn:timezone":"Europe/Moscow",
    "iso:country":"RU",
    "name:rus_x_preferred":[
        "\u041f\u0430\u0440\u043a\u043e\u0432\u044b\u0439"
    ],
    "wof:name":"Parkovyy",
    "wof:placetype":"locality"
},
  "geometry": {"coordinates":[39.58328,56.64074],"type":"Point"}
}