{
  "type": "Feature",
  "properties": {
    "gn:admin1_code":"29.0",
    "gn:asciiname":"Kooperativny",
    "gn:country_code":"RU",
    "gn:dem":177,
    "gn:feature_class":"P",
    "gn:feature_code":"PPL",
    "gn:name":"Kooperativny",
    "gn:population":0,
    "gn:timezone":"Asia/Novokuznetsk",
    "iso:country":"RU",
    "name:rus_x_preferred":[
        "\u041a\u043e\u043e\u043f\u0435\u0440\u0430\u0442\u0438\u0432\u043d\u044b"
    ],
    "wof:name":"Kooperativny",
    "wof:placetype":"locality"
},
  "geometry": {"coordinates":[86.2282,54.5571],"type":"Point"}
}