{
  "type": "Feature",
  "properties": {
    "gn:admin1_code":"33.0",
    "gn:asciiname":"Zasora",
    "gn:country_code":"RU",
    "gn:dem":150,
    "gn:feature_class":"P",
    "gn:feature_code":"PPL",
    "gn:name":"Zasora",
    "gn:population":0,
    "gn:timezone":"Europe/Kirov",
    "iso:country":"RU",
    "name:rus_x_preferred":[
        "\u0417\u0430\u0441\u043e\u0440\u0430"
    ],
    "wof:name":"Zasora",
    "wof:placetype":"locality"
},
  "geometry": {"coordinates":[48.59778,58.68778],"type":"Point"}
}