{
  "type": "Feature",
  "properties": {
    "gn:admin1_code":"54",
    "gn:asciiname":"Vedernikovo",
    "gn:cc2":"RU",
    "gn:country_code":"RU",
    "gn:dem":98,
    "gn:feature_class":"P",
    "gn:feature_code":"PPL",
    "gn:name":"Vedernikovo",
    "gn:population":0,
    "gn:timezone":"Asia/Omsk",
    "iso:country":"RU",
    "name:und_x_variant":[
        "Vedernikovskiy",
        "Vedernikovo"
    ],
    "wof:name":"Vedernikovo",
    "wof:placetype":"locality"
},
  "geometry": {"coordinates":[75.61667,56.96666999999999],"type":"Point"}
}