{
  "type": "Feature",
  "properties": {
    "gn:admin1_code":"8.0",
    "gn:asciiname":"Belorus-Aleksandrovka",
    "gn:country_code":"RU",
    "gn:dem":115,
    "gn:feature_class":"P",
    "gn:feature_code":"PPL",
    "gn:name":"Belorus-Aleksandrovka",
    "gn:population":0,
    "gn:timezone":"Asia/Yekaterinburg",
    "iso:country":"RU",
    "name:nor_x_preferred":[
        "Belorus-Aleksandrovskoje"
    ],
    "name:rus_x_preferred":[
        "\u0411\u0435\u043b\u043e\u0440\u0443\u0441-\u0410\u043b\u0435\u043a\u0441\u0430\u043d\u0434\u0440\u043e\u0432\u043a\u0430"
    ],
    "name:und_x_variant":[
        "Belorus-Aleksandrovskoye",
        "Belorus-Aleksandrovka"
    ],
    "wof:name":"Belorus-Aleksandrovka",
    "wof:placetype":"locality"
},
  "geometry": {"coordinates":[56.6645,54.5514],"type":"Point"}
}