{
  "type": "Feature",
  "properties": {
    "gn:admin1_code":"6",
    "gn:asciiname":"Navalok",
    "gn:country_code":"RU",
    "gn:dem":82,
    "gn:feature_class":"P",
    "gn:feature_code":"PPL",
    "gn:name":"Navalok",
    "gn:population":0,
    "gn:timezone":"Europe/Moscow",
    "iso:country":"RU",
    "name:eng_x_preferred":[
        "Navalok"
    ],
    "name:nor_x_preferred":[
        "Navolok"
    ],
    "name:rus_x_preferred":[
        "\u041d\u0430\u0432\u043e\u043b\u043e\u043a"
    ],
    "name:rus_x_variant":[
        "\u041d\u0430\u0432\u0430\u043b\u043e\u043a"
    ],
    "name:und_x_variant":[
        "\u041d\u0430\u0432\u0430\u043b\u043e\u043a"
    ],
    "wof:name":"Navalok",
    "wof:placetype":"locality"
},
  "geometry": {"coordinates":[40.8914,61.8756],"type":"Point"}
}