{
  "type": "Feature",
  "properties": {
    "gn:country":"RU",
    "gn:fcode":"PPL",
    "gn:population":0,
    "iso:country":"RU",
    "name:rus_x_preferred":[
        "\u0420\u044f\u0431\u0438\u043d\u043e\u0432\u043a\u0430"
    ],
    "name:und_x_variant":[
        "Ryabinovka"
    ],
    "qs:name":"Yablonovka",
    "qs:name_adm0":"Russia",
    "qs:name_adm1":"Ulyanovsk Oblast",
    "qs:photos_9r":0,
    "qs:photos_sr":0,
    "qs:placetype":"Town",
    "qs:pop_sr":"0",
    "wd:wordcount":152,
    "wof:name":"Yablonovka",
    "wof:placetype":"locality",
    "wof:population":0
},
  "geometry": {"coordinates":[48.6667,53.6388],"type":"Point"}
}