{
  "type": "Feature",
  "properties": {
    "gn:admin1_code":"76",
    "gn:asciiname":"Streshnevo",
    "gn:country_code":"RU",
    "gn:dem":200,
    "gn:feature_class":"P",
    "gn:feature_code":"PPL",
    "gn:name":"Streshn\u00ebvo",
    "gn:population":0,
    "gn:timezone":"Europe/Moscow",
    "iso:country":"RU",
    "name:rus_x_preferred":[
        "\u0421\u0442\u0440\u0435\u0448\u043d\u0451\u0432\u043e"
    ],
    "name:und_x_variant":[
        "Ostreshnevo",
        "Otreshnevo",
        "Streshn\u00ebvo",
        "\u0421\u0442\u0440\u0435\u0448\u043d\u0451\u0432\u043e"
    ],
    "wof:name":"Streshnevo",
    "wof:placetype":"locality"
},
  "geometry": {"coordinates":[37.51746,53.50023],"type":"Point"}
}