{
  "type": "Feature",
  "properties": {
    "gn:admin1_code":"52",
    "gn:asciiname":"Il'ichino",
    "gn:country_code":"RU",
    "gn:dem":234,
    "gn:feature_class":"P",
    "gn:feature_code":"PPL",
    "gn:name":"Il\u2019ichino",
    "gn:population":0,
    "gn:timezone":"Europe/Moscow",
    "iso:country":"RU",
    "name:nor_x_preferred":[
        "Ilitsjino"
    ],
    "name:rus_x_preferred":[
        "\u0418\u043b\u044c\u0438\u0447\u0438\u043d\u043e"
    ],
    "name:und_x_variant":[
        "Il\u2019igino",
        "Il\u2019ichino"
    ],
    "wof:name":"Il'ichino",
    "wof:placetype":"locality"
},
  "geometry": {"coordinates":[33.9325,58.89014],"type":"Point"}
}