{
  "type": "Feature",
  "properties": {
    "gn:admin1_code":"52",
    "gn:asciiname":"Kozynevo",
    "gn:country_code":"RU",
    "gn:dem":26,
    "gn:feature_class":"P",
    "gn:feature_code":"PPL",
    "gn:name":"Kozyn\u00ebvo",
    "gn:population":0,
    "gn:timezone":"Europe/Moscow",
    "iso:country":"RU",
    "name:rus_x_preferred":[
        "\u041a\u043e\u0437\u044b\u043d\u0451\u0432\u043e"
    ],
    "name:und_x_variant":[
        "Kozyn\u00ebvo"
    ],
    "wof:name":"Kozynevo",
    "wof:placetype":"locality"
},
  "geometry": {"coordinates":[31.21618,58.397],"type":"Point"}
}