{
  "type": "Feature",
  "properties": {
    "gn:admin1_code":"60",
    "gn:asciiname":"Goroncharovo",
    "gn:cc2":"RU",
    "gn:country_code":"RU",
    "gn:dem":172,
    "gn:feature_class":"P",
    "gn:feature_code":"PPL",
    "gn:name":"Goroncharovo",
    "gn:population":0,
    "gn:timezone":"Europe/Moscow",
    "iso:country":"RU",
    "name:rus_x_preferred":[
        "\u0413\u043e\u0440\u043e\u043d\u0447\u0430\u0440\u043e\u0432\u043e"
    ],
    "name:und_x_variant":[
        "Goront\u0161arova",
        "Goroncharovo"
    ],
    "wof:name":"Goroncharovo",
    "wof:placetype":"locality"
},
  "geometry": {"coordinates":[27.48333,57.65],"type":"Point"}
}