{
  "type": "Feature",
  "properties": {
    "iso:country":"RU",
    "name:ceb_x_preferred":[
        "Ust-Maya Airport"
    ],
    "name:eng_x_preferred":[
        "Ust-Maya Airport"
    ],
    "name:fra_x_preferred":[
        "\u0423\u0441\u0442\u044c-\u041c\u0430\u044f"
    ],
    "name:ron_x_preferred":[
        "Aeroportul Ust-Maya"
    ],
    "name:rus_x_preferred":[
        "\u0423\u0441\u0442\u044c-\u041c\u0430\u044f"
    ],
    "oa:elevation_ft":"561",
    "oa:type":"small_airport",
    "wd:wordcount":49,
    "woe:hierarchy":{
        "country_id":23424936,
        "county_id":12597649,
        "planet_id":1,
        "state_id":2346881
    },
    "wof:name":"Ust Maya Airport",
    "wof:placetype":"campus"
},
  "geometry": {"coordinates":[134.44900000000001,60.3639],"type":"Point"}
}