{
  "type": "Feature",
  "properties": {
    "gn:admin1_code":"93",
    "gn:asciiname":"Chengul'",
    "gn:country_code":"RU",
    "gn:dem":616,
    "gn:feature_class":"P",
    "gn:feature_code":"PPL",
    "gn:name":"Chengul\u2019",
    "gn:population":0,
    "gn:timezone":"Asia/Chita",
    "iso:country":"RU",
    "name:eng_x_preferred":[
        "Chongul'"
    ],
    "name:nor_x_preferred":[
        "Tsjongul"
    ],
    "name:rus_x_preferred":[
        "\u0427\u0435\u043d\u0433\u0443\u043b\u044c"
    ],
    "name:und_x_variant":[
        "Chengul",
        "Changul\u2019skiy",
        "Chongul\u2019skiy",
        "Chongul\u2019skoye",
        "Chengul\u2019skiy",
        "Chongul\u2019",
        "Chengul\u2019"
    ],
    "wof:name":"Chengul'",
    "wof:placetype":"locality"
},
  "geometry": {"coordinates":[117.72953,51.9539],"type":"Point"}
}