{
  "type": "Feature",
  "properties": {
    "gn:admin1_code":"46",
    "gn:asciiname":"Zarya",
    "gn:country_code":"RU",
    "gn:dem":117,
    "gn:feature_class":"P",
    "gn:feature_code":"PPL",
    "gn:name":"Zarya",
    "gn:population":0,
    "gn:timezone":"Europe/Moscow",
    "iso:country":"RU",
    "name:rus_x_preferred":[
        "\u0417\u0430\u0440\u044f"
    ],
    "name:und_x_variant":[
        "\u0417\u0430\u0440\u044f"
    ],
    "wof:name":"Zarya",
    "wof:placetype":"locality"
},
  "geometry": {"coordinates":[45.8585,54.6113],"type":"Point"}
}