{
  "type": "Feature",
  "properties": {
    "gn:admin1_code":"88",
    "gn:asciiname":"Pakhonino",
    "gn:country_code":"RU",
    "gn:dem":113,
    "gn:feature_class":"P",
    "gn:feature_code":"PPL",
    "gn:name":"Pakhonino",
    "gn:population":0,
    "gn:timezone":"Europe/Moscow",
    "iso:country":"RU",
    "name:rus_x_preferred":[
        "\u041f\u0430\u0445\u043e\u043d\u0438\u043d\u043e"
    ],
    "name:und_x_variant":[
        "\u041f\u0430\u0445\u043e\u043d\u0438\u043d\u043e"
    ],
    "wof:name":"Pakhonino",
    "wof:placetype":"locality"
},
  "geometry": {"coordinates":[38.87056,58.3156],"type":"Point"}
}