{
  "type": "Feature",
  "properties": {
    "gn:admin1_code":"88",
    "gn:asciiname":"Ramenka",
    "gn:country_code":"RU",
    "gn:dem":138,
    "gn:feature_class":"P",
    "gn:feature_code":"PPL",
    "gn:name":"Ramenka",
    "gn:population":0,
    "gn:timezone":"Europe/Moscow",
    "iso:country":"RU",
    "name:rus_x_preferred":[
        "\u0420\u0430\u043c\u0435\u043d\u043a\u0430"
    ],
    "name:und_x_variant":[
        "\u0420\u0430\u043c\u0435\u043d\u043a\u0430"
    ],
    "wof:name":"Ramenka",
    "wof:placetype":"locality"
},
  "geometry": {"coordinates":[38.96353,57.48961],"type":"Point"}
}