{
  "type": "Feature",
  "properties": {
    "gn:admin1_code":"69",
    "gn:asciiname":"Korotnevo",
    "gn:country_code":"RU",
    "gn:dem":249,
    "gn:feature_class":"P",
    "gn:feature_code":"PPL",
    "gn:name":"Korotn\u00ebvo",
    "gn:population":0,
    "gn:timezone":"Europe/Moscow",
    "iso:country":"RU",
    "name:rus_x_preferred":[
        "\u041a\u043e\u0440\u043e\u0442\u043d\u0451\u0432\u043e"
    ],
    "name:und_x_variant":[
        "Korotneva",
        "Korotn\u00ebvo"
    ],
    "wof:name":"Korotnevo",
    "wof:placetype":"locality"
},
  "geometry": {"coordinates":[34.14667,55.4714],"type":"Point"}
}