{
  "type": "Feature",
  "properties": {
    "gn:admin1_code":"91",
    "gn:asciiname":"Zyryanovo",
    "gn:country_code":"RU",
    "gn:dem":26,
    "gn:feature_class":"P",
    "gn:feature_code":"PPL",
    "gn:name":"Zyryanovo",
    "gn:population":0,
    "gn:timezone":"Asia/Krasnoyarsk",
    "iso:country":"RU",
    "name:eng_x_preferred":[
        "Zyryanovo"
    ],
    "name:nor_x_preferred":[
        "Zyrjanovo"
    ],
    "name:rus_x_preferred":[
        "\u0417\u044b\u0440\u044f\u043d\u043e\u0432\u043e"
    ],
    "name:und_x_variant":[
        "Peskovskaya",
        "Zyryanovo"
    ],
    "wof:name":"Zyryanovo",
    "wof:placetype":"locality"
},
  "geometry": {"coordinates":[87.32625999999998,63.70029],"type":"Point"}
}