{
  "type": "Feature",
  "properties": {
    "gn:admin1_code":"91.0",
    "gn:asciiname":"Uskovskoye",
    "gn:country_code":"RU",
    "gn:dem":194,
    "gn:feature_class":"P",
    "gn:feature_code":"PPL",
    "gn:name":"Uskovskoye",
    "gn:population":0,
    "gn:timezone":"Asia/Krasnoyarsk",
    "iso:country":"RU",
    "name:rus_x_preferred":[
        "\u0423\u0441\u043a\u043e\u0432\u0441\u043a\u043e\u0435"
    ],
    "wof:name":"Uskovskoye",
    "wof:placetype":"locality"
},
  "geometry": {"coordinates":[92.4765,57.56548000000001],"type":"Point"}
}