{
  "type": "Feature",
  "properties": {
    "gn:admin1_code":"10",
    "gn:asciiname":"Roshcha",
    "gn:country_code":"RU",
    "gn:dem":185,
    "gn:feature_class":"P",
    "gn:feature_code":"PPL",
    "gn:name":"Roshcha",
    "gn:population":0,
    "gn:timezone":"Europe/Moscow",
    "iso:country":"RU",
    "name:bak_x_preferred":[
        "\u0420\u043e\u0449\u0430"
    ],
    "name:che_x_preferred":[
        "\u0420\u043e\u0449\u0430"
    ],
    "name:hye_x_preferred":[
        "\u054c\u0578\u0577\u0579\u0561"
    ],
    "name:kat_x_preferred":[
        "\u10e0\u10dd\u10e8\u10e9\u10d0"
    ],
    "name:kaz_x_preferred":[
        "\u0420\u043e\u0449\u0430"
    ],
    "name:kir_x_preferred":[
        "\u0420\u043e\u0449\u0430"
    ],
    "name:rus_x_preferred":[
        "\u0420\u043e\u0449\u0430"
    ],
    "name:tat_x_preferred":[
        "\u0420\u043e\u0449\u0430"
    ],
    "name:ukr_x_preferred":[
        "\u0420\u043e\u0449\u0430"
    ],
    "name:und_x_variant":[
        "\u0420\u043e\u0449\u0430"
    ],
    "wof:name":"Roshcha",
    "wof:placetype":"locality"
},
  "geometry": {"coordinates":[33.1608,52.89125],"type":"Point"}
}