{
  "type": "Feature",
  "properties": {
    "gn:admin1_code":"33.0",
    "gn:asciiname":"Bobyli",
    "gn:country_code":"RU",
    "gn:dem":133,
    "gn:feature_class":"P",
    "gn:feature_code":"PPL",
    "gn:name":"Bobyli",
    "gn:population":0,
    "gn:timezone":"Europe/Kirov",
    "iso:country":"RU",
    "name:rus_x_preferred":[
        "\u0411\u043e\u0431\u044b\u043b\u0438"
    ],
    "name:und_x_variant":[
        "\u0411\u043e\u0431\u044b\u043b\u0438"
    ],
    "wof:name":"Bobyli",
    "wof:placetype":"locality"
},
  "geometry": {"coordinates":[48.92734,58.37649],"type":"Point"}
}