{
  "type": "Feature",
  "properties": {
    "gn:admin1_code":"86.0",
    "gn:asciiname":"Bereznyagi",
    "gn:country_code":"RU",
    "gn:dem":160,
    "gn:feature_class":"P",
    "gn:feature_code":"PPL",
    "gn:name":"Bereznyagi",
    "gn:population":0,
    "gn:timezone":"Europe/Moscow",
    "iso:country":"RU",
    "name:nor_x_preferred":[
        "Bereznjagi"
    ],
    "name:rus_x_preferred":[
        "\u0411\u0435\u0440\u0435\u0437\u043d\u044f\u0433\u0438"
    ],
    "name:und_x_variant":[
        "Bereznyaki",
        "Bereznyagi"
    ],
    "wof:name":"Bereznyagi",
    "wof:placetype":"locality"
},
  "geometry": {"coordinates":[40.0566,51.6556],"type":"Point"}
}