{
  "type": "Feature",
  "properties": {
    "gn:admin1_code":"62",
    "gn:asciiname":"Novoye Poshatovo",
    "gn:country_code":"RU",
    "gn:dem":104,
    "gn:feature_class":"P",
    "gn:feature_code":"PPL",
    "gn:name":"Novoye Poshatovo",
    "gn:population":0,
    "gn:timezone":"Europe/Moscow",
    "iso:country":"RU",
    "name:rus_x_preferred":[
        "\u041d\u043e\u0432\u043e\u0435 \u041f\u043e\u0448\u0430\u0442\u043e\u0432\u043e"
    ],
    "wof:name":"Novoye Poshatovo",
    "wof:placetype":"locality"
},
  "geometry": {"coordinates":[42.4036,54.6329],"type":"Point"}
}