{
  "type": "Feature",
  "properties": {
    "gn:admin1_code":"80.0",
    "gn:asciiname":"Anyushino",
    "gn:country_code":"RU",
    "gn:dem":286,
    "gn:feature_class":"P",
    "gn:feature_code":"PPL",
    "gn:name":"Anyushino",
    "gn:population":0,
    "gn:timezone":"Europe/Samara",
    "iso:country":"RU",
    "name:rus_x_preferred":[
        "\u0410\u043d\u044e\u0448\u0438\u043d\u043e"
    ],
    "wof:name":"Anyushino",
    "wof:placetype":"locality"
},
  "geometry": {"coordinates":[53.5911,58.2526],"type":"Point"}
}