{
  "type": "Feature",
  "properties": {
    "gn:admin1_code":"53",
    "gn:asciiname":"Lokti",
    "gn:country_code":"RU",
    "gn:dem":157,
    "gn:feature_class":"P",
    "gn:feature_code":"PPL",
    "gn:name":"Lokti",
    "gn:population":0,
    "gn:timezone":"Asia/Novosibirsk",
    "iso:country":"RU",
    "name:eng_x_preferred":[
        "Lokti"
    ],
    "name:nor_x_preferred":[
        "Lokti"
    ],
    "name:rus_x_preferred":[
        "\u041b\u043e\u043a\u0442\u0438"
    ],
    "name:und_x_variant":[
        "Loktinskaya"
    ],
    "wof:name":"Lokti",
    "wof:placetype":"locality"
},
  "geometry": {"coordinates":[83.1876,55.268],"type":"Point"}
}