{
  "type": "Feature",
  "properties": {
    "gn:admin1_code":"88",
    "gn:asciiname":"Moseytsevo",
    "gn:country_code":"RU",
    "gn:dem":152,
    "gn:feature_class":"P",
    "gn:feature_code":"PPL",
    "gn:name":"Moseytsevo",
    "gn:population":0,
    "gn:timezone":"Europe/Moscow",
    "iso:country":"RU",
    "name:eng_x_preferred":[
        "Moseytsevo"
    ],
    "name:nor_x_preferred":[
        "Mosejtsevo"
    ],
    "name:rus_x_preferred":[
        "\u041c\u043e\u0441\u0435\u0439\u0446\u0435\u0432\u043e"
    ],
    "name:und_x_variant":[
        "Moseytsovo"
    ],
    "wof:name":"Moseytsevo",
    "wof:placetype":"locality"
},
  "geometry": {"coordinates":[39.73915,57.11044],"type":"Point"}
}