{
  "type": "Feature",
  "properties": {
    "gn:admin1_code":"77",
    "gn:asciiname":"Terpnikovo",
    "gn:country_code":"RU",
    "gn:dem":173,
    "gn:feature_class":"P",
    "gn:feature_code":"PPL",
    "gn:name":"Terpnikovo",
    "gn:population":0,
    "gn:timezone":"Europe/Moscow",
    "iso:country":"RU",
    "wof:name":"Terpnikovo",
    "wof:placetype":"locality"
},
  "geometry": {"coordinates":[35.40198,56.32351],"type":"Point"}
}