{
  "type": "Feature",
  "properties": {
    "gn:admin1_code":"23",
    "gn:asciiname":"Maloye Putyatino",
    "gn:country_code":"RU",
    "gn:dem":107,
    "gn:feature_class":"P",
    "gn:feature_code":"PPL",
    "gn:name":"Maloye Putyatino",
    "gn:population":0,
    "gn:timezone":"Europe/Kaliningrad",
    "iso:country":"RU",
    "name:rus_x_preferred":[
        "\u041c\u0430\u043b\u043e\u0435 \u041f\u0443\u0442\u044f\u0442\u0438\u043d\u043e"
    ],
    "wof:name":"Maloye Putyatino",
    "wof:placetype":"locality"
},
  "geometry": {"coordinates":[21.98003,54.48145],"type":"Point"}
}