{
  "type": "Feature",
  "properties": {
    "gn:admin1_code":"85",
    "gn:asciiname":"Meleshovo",
    "gn:country_code":"RU",
    "gn:dem":177,
    "gn:feature_class":"P",
    "gn:feature_code":"PPL",
    "gn:name":"Meleshovo",
    "gn:population":0,
    "gn:timezone":"Europe/Moscow",
    "iso:country":"RU",
    "name:eng_x_preferred":[
        "Meleshovo"
    ],
    "name:nor_x_preferred":[
        "Melesjovo"
    ],
    "name:rus_x_preferred":[
        "\u041c\u0435\u043b\u0435\u0448\u043e\u0432\u043e"
    ],
    "name:und_x_variant":[
        "Zaoz\u00ebr\u2019ye-Meleshovo",
        "\u041c\u0435\u043b\u0435\u0448\u043e\u0432\u043e",
        "Meleshovo"
    ],
    "wof:name":"Meleshovo",
    "wof:placetype":"locality"
},
  "geometry": {"coordinates":[42.26768,60.25144],"type":"Point"}
}