{
  "type": "Feature",
  "properties": {
    "gn:admin1_code":"83",
    "gn:asciiname":"Maryukhino",
    "gn:country_code":"RU",
    "gn:dem":143,
    "gn:feature_class":"P",
    "gn:feature_code":"PPL",
    "gn:name":"Maryukhino",
    "gn:population":0,
    "gn:timezone":"Europe/Moscow",
    "iso:country":"RU",
    "name:rus_x_preferred":[
        "\u041c\u0430\u0440\u044e\u0445\u0438\u043d\u043e"
    ],
    "name:und_x_variant":[
        "Maryukhina",
        "Maryukhino",
        "\u041c\u0430\u0440\u044e\u0445\u0438\u043d\u043e"
    ],
    "wof:name":"Maryukhino",
    "wof:placetype":"locality"
},
  "geometry": {"coordinates":[40.40275,55.95498000000001],"type":"Point"}
}