{
  "type": "Feature",
  "properties": {
    "gn:admin1_code":"56",
    "gn:asciiname":"Shubino",
    "gn:country_code":"RU",
    "gn:dem":203,
    "gn:feature_class":"P",
    "gn:feature_code":"PPL",
    "gn:name":"Shubino",
    "gn:population":0,
    "gn:timezone":"Europe/Moscow",
    "iso:country":"RU",
    "name:rus_x_preferred":[
        "\u0428\u0443\u0431\u0438\u043d\u043e"
    ],
    "wof:name":"Shubino",
    "wof:placetype":"locality"
},
  "geometry": {"coordinates":[35.62676,53.12026],"type":"Point"}
}