{
  "type": "Feature",
  "properties": {
    "gn:admin1_code":"5",
    "gn:asciiname":"Uyutnyy",
    "gn:country_code":"RU",
    "gn:dem":293,
    "gn:feature_class":"P",
    "gn:feature_code":"PPL",
    "gn:name":"Uyutnyy",
    "gn:population":0,
    "gn:timezone":"Asia/Yakutsk",
    "iso:country":"RU",
    "wof:name":"Uyutnyy",
    "wof:placetype":"locality"
},
  "geometry": {"coordinates":[126.84999999999999,53.43333000000001],"type":"Point"}
}