{
  "type": "Feature",
  "properties": {
    "gn:admin1_code":"81",
    "gn:asciiname":"Zabaluyka",
    "gn:country_code":"RU",
    "gn:dem":137,
    "gn:feature_class":"P",
    "gn:feature_code":"PPL",
    "gn:name":"Zabaluyka",
    "gn:population":0,
    "gn:timezone":"Europe/Ulyanovsk",
    "iso:country":"RU",
    "name:eng_x_preferred":[
        "Zabaluyka"
    ],
    "name:nor_x_preferred":[
        "Zabalujka"
    ],
    "name:rus_x_preferred":[
        "\u0417\u0430\u0431\u0430\u043b\u0443\u0439\u043a\u0430"
    ],
    "wof:name":"Zabaluyka",
    "wof:placetype":"locality"
},
  "geometry": {"coordinates":[46.24596,53.87716],"type":"Point"}
}