{
  "type": "Feature",
  "properties": {
    "gn:admin1_code":"53",
    "gn:asciiname":"Anikinskiy",
    "gn:country_code":"RU",
    "gn:dem":137,
    "gn:feature_class":"P",
    "gn:feature_code":"PPL",
    "gn:name":"Anikinskiy",
    "gn:population":0,
    "gn:timezone":"Asia/Novosibirsk",
    "iso:country":"RU",
    "name:nor_x_preferred":[
        "Anikinskij"
    ],
    "name:rus_x_preferred":[
        "\u0410\u043d\u0438\u043a\u0438\u043d\u0441\u043a\u0438\u0439"
    ],
    "wof:name":"Anikinskiy",
    "wof:placetype":"locality"
},
  "geometry": {"coordinates":[80.41667,56.03333000000001],"type":"Point"}
}