{
  "type": "Feature",
  "properties": {
    "gn:admin1_code":"77.0",
    "gn:asciiname":"An'kovo",
    "gn:country_code":"RU",
    "gn:dem":154,
    "gn:feature_class":"P",
    "gn:feature_code":"PPL",
    "gn:name":"An\u2019kovo",
    "gn:population":0,
    "gn:timezone":"Europe/Moscow",
    "iso:country":"RU",
    "name:nor_x_preferred":[
        "Ankovo"
    ],
    "name:rus_x_preferred":[
        "\u0410\u043d\u044c\u043a\u043e\u0432\u043e"
    ],
    "name:und_x_variant":[
        "An\u2019kovo"
    ],
    "wof:name":"An'kovo",
    "wof:placetype":"locality"
},
  "geometry": {"coordinates":[35.57035,58.36154000000001],"type":"Point"}
}