{
  "type": "Feature",
  "properties": {
    "gn:admin1_code":"90",
    "gn:asciiname":"Nadyashcher",
    "gn:country_code":"RU",
    "gn:dem":260,
    "gn:feature_class":"P",
    "gn:feature_code":"PPL",
    "gn:name":"Nadyashcher",
    "gn:population":0,
    "gn:timezone":"Asia/Yekaterinburg",
    "iso:country":"RU",
    "name:rus_x_preferred":[
        "\u041d\u0430\u0434\u044f\u0449\u0435\u0440"
    ],
    "name:und_x_variant":[
        "\u041d\u0430\u0434\u044f\u0449\u0435\u0440"
    ],
    "wof:name":"Nadyashcher",
    "wof:placetype":"locality"
},
  "geometry": {"coordinates":[58.03388,60.62845],"type":"Point"}
}