{
  "type": "Feature",
  "properties": {
    "gn:admin1_code":"28",
    "gn:asciiname":"Sheppovaraka",
    "gn:country_code":"RU",
    "gn:dem":134,
    "gn:feature_class":"P",
    "gn:feature_code":"PPL",
    "gn:name":"Sheppovaraka",
    "gn:population":0,
    "gn:timezone":"Europe/Moscow",
    "iso:country":"RU",
    "name:rus_x_preferred":[
        "\u0428\u0435\u043f\u043f\u043e\u0432\u0430\u0440\u0430\u043a\u0430"
    ],
    "wof:name":"Sheppovaraka",
    "wof:placetype":"locality"
},
  "geometry": {"coordinates":[34.15,64.45],"type":"Point"}
}