{
  "type": "Feature",
  "properties": {
    "gn:admin1_code":"5.0",
    "gn:asciiname":"Lenino",
    "gn:country_code":"RU",
    "gn:dem":182,
    "gn:feature_class":"P",
    "gn:feature_code":"PPL",
    "gn:name":"Lenino",
    "gn:population":0,
    "gn:timezone":"Asia/Yakutsk",
    "iso:country":"RU",
    "name:bel_x_preferred":[
        "\u041b\u0435\u043d\u0456\u043d\u0430"
    ],
    "name:kaz_x_preferred":[
        "\u041b\u0435\u043d\u0438\u043d\u043e"
    ],
    "name:pol_x_preferred":[
        "Lenino"
    ],
    "name:rus_x_preferred":[
        "\u041b\u0435\u043d\u0438\u043d\u043e"
    ],
    "name:srp_x_preferred":[
        "\u041b\u0435\u045a\u0438\u043d\u043e"
    ],
    "name:ukr_x_preferred":[
        "\u041b\u0435\u043d\u0456\u043d\u043e"
    ],
    "wof:name":"Lenino",
    "wof:placetype":"locality"
},
  "geometry": {"coordinates":[129.31555,49.81332],"type":"Point"}
}