{
  "type": "Feature",
  "properties": {
    "gn:admin1_code":"8",
    "gn:asciiname":"Kebyachevo",
    "gn:country_code":"RU",
    "gn:dem":209,
    "gn:feature_class":"P",
    "gn:feature_code":"PPL",
    "gn:name":"Kebyachevo",
    "gn:population":0,
    "gn:timezone":"Asia/Yekaterinburg",
    "iso:country":"RU",
    "name:aze_x_preferred":[
        "K\u0259b\u0259\u00e7"
    ],
    "name:bak_x_preferred":[
        "\u041a\u04d9\u0431\u04d9\u0441"
    ],
    "name:che_x_preferred":[
        "\u041a\u0435\u0431\u044f\u0447\u0435\u0432\u043e"
    ],
    "name:chv_x_preferred":[
        "\u041a\u0435\u043f\u0435\u00e7"
    ],
    "name:eng_x_preferred":[
        "Kebyachevo"
    ],
    "name:hye_x_preferred":[
        "\u053f\u0565\u0562\u0575\u0561\u0579\u0587\u0578"
    ],
    "name:kaz_x_preferred":[
        "\u041a\u0435\u0431\u044f\u0447"
    ],
    "name:kir_x_preferred":[
        "\u041a\u0435\u0431\u044f\u0447"
    ],
    "name:nor_x_preferred":[
        "Kebjatsjevo"
    ],
    "name:rus_x_preferred":[
        "\u041a\u0435\u0431\u044f\u0447\u0435\u0432\u043e"
    ],
    "name:tat_x_preferred":[
        "\u041a\u04d9\u0431\u04d9\u0447"
    ],
    "name:ukr_x_preferred":[
        "\u041a\u0435\u0431\u044f\u0447\u0435\u0432\u043e"
    ],
    "wof:name":"Kebyachevo",
    "wof:placetype":"locality"
},
  "geometry": {"coordinates":[55.93981,53.93838],"type":"Point"}
}