{
  "type": "Feature",
  "properties": {
    "gn:admin1_code":"23",
    "gn:asciiname":"Grushevka",
    "gn:country_code":"RU",
    "gn:dem":34,
    "gn:feature_class":"P",
    "gn:feature_code":"PPL",
    "gn:name":"Grushevka",
    "gn:population":0,
    "gn:timezone":"Europe/Kaliningrad",
    "iso:country":"RU",
    "name:rus_x_preferred":[
        "\u0413\u0440\u0443\u0448\u0435\u0432\u043a\u0430"
    ],
    "name:und_x_variant":[
        "Sommerfeld",
        "Grushevka"
    ],
    "wof:name":"Grushevka",
    "wof:placetype":"locality"
},
  "geometry": {"coordinates":[20.89403,54.49572],"type":"Point"}
}