{
  "type": "Feature",
  "properties": {
    "gn:admin1_code":"33.0",
    "gn:asciiname":"Volodiny",
    "gn:country_code":"RU",
    "gn:dem":120,
    "gn:feature_class":"P",
    "gn:feature_code":"PPL",
    "gn:name":"Volodiny",
    "gn:population":0,
    "gn:timezone":"Europe/Kirov",
    "iso:country":"RU",
    "name:rus_x_preferred":[
        "\u0412\u043e\u043b\u043e\u0434\u0438\u043d\u044b"
    ],
    "name:und_x_variant":[
        "D\u00ebmshchiny",
        "Volodiny"
    ],
    "wof:name":"Volodiny",
    "wof:placetype":"locality"
},
  "geometry": {"coordinates":[48.82807,58.52513],"type":"Point"}
}