{
  "type": "Feature",
  "properties": {
    "gn:admin1_code":"61",
    "gn:asciiname":"Novotroitskiy",
    "gn:country_code":"RU",
    "gn:dem":45,
    "gn:feature_class":"P",
    "gn:feature_code":"PPL",
    "gn:name":"Novotroitskiy",
    "gn:population":0,
    "gn:timezone":"Europe/Moscow",
    "iso:country":"RU",
    "name:rus_x_preferred":[
        "\u041d\u043e\u0432\u043e\u0442\u0440\u043e\u0438\u0442\u0441\u043a\u0438\u0439"
    ],
    "name:rus_x_variant":[
        "\u041d\u043e\u0432\u043e\u0442\u0440\u043e\u0438\u0446\u043a\u0438\u0439"
    ],
    "wof:name":"Novotroitskiy",
    "wof:placetype":"locality"
},
  "geometry": {"coordinates":[39.69139000000001,47.67333],"type":"Point"}
}