{
  "type": "Feature",
  "properties": {
    "gn:admin1_code":"73",
    "gn:asciiname":"Sharlama",
    "gn:country_code":"RU",
    "gn:dem":152,
    "gn:feature_class":"P",
    "gn:feature_code":"PPL",
    "gn:name":"Sharlama",
    "gn:population":0,
    "gn:timezone":"Europe/Moscow",
    "iso:country":"RU",
    "name:rus_x_preferred":[
        "\u0428\u0430\u0440\u043b\u0430\u043c\u0430"
    ],
    "wof:name":"Sharlama",
    "wof:placetype":"locality"
},
  "geometry": {"coordinates":[52.5951,54.9878],"type":"Point"}
}