{
  "type": "Feature",
  "properties": {
    "gn:admin1_code":"69.0",
    "gn:asciiname":"Baskakovka",
    "gn:country_code":"RU",
    "gn:dem":223,
    "gn:feature_class":"P",
    "gn:feature_code":"PPL",
    "gn:name":"Baskakovka",
    "gn:population":0,
    "gn:timezone":"Europe/Moscow",
    "iso:country":"RU",
    "name:nor_x_preferred":[
        "Baskakovka"
    ],
    "name:rus_x_preferred":[
        "\u0411\u0430\u0441\u043a\u0430\u043a\u043e\u0432\u043a\u0430"
    ],
    "wof:name":"Baskakovka",
    "wof:placetype":"locality"
},
  "geometry": {"coordinates":[34.34472,54.61221],"type":"Point"}
}