{
  "type": "Feature",
  "properties": {
    "gn:admin1_code":"69",
    "gn:asciiname":"Azarova Pervaya",
    "gn:country_code":"RU",
    "gn:dem":193,
    "gn:feature_class":"P",
    "gn:feature_code":"PPL",
    "gn:name":"Azarova Pervaya",
    "gn:population":0,
    "gn:timezone":"Europe/Moscow",
    "iso:country":"RU",
    "name:nor_x_preferred":[
        "Azarova Pervaja"
    ],
    "name:rus_x_preferred":[
        "\u0410\u0437\u0430\u0440\u043e\u0432\u0430 \u041f\u0435\u0440\u0432\u0430\u044f"
    ],
    "wof:name":"Azarova Pervaya",
    "wof:placetype":"locality"
},
  "geometry": {"coordinates":[33.38972,54.2025],"type":"Point"}
}