{
  "type": "Feature",
  "properties": {
    "gn:admin1_code":"28",
    "gn:asciiname":"Kindasovo",
    "gn:country_code":"RU",
    "gn:dem":72,
    "gn:feature_class":"P",
    "gn:feature_code":"PPL",
    "gn:name":"Kindasovo",
    "gn:population":6,
    "gn:timezone":"Europe/Moscow",
    "iso:country":"RU",
    "name:eng_x_preferred":[
        "Kindasovo"
    ],
    "name:fin_x_preferred":[
        "Kintas"
    ],
    "name:nor_x_preferred":[
        "Kindasovo"
    ],
    "name:rus_x_preferred":[
        "\u041a\u0438\u043d\u0434\u0430\u0441\u043e\u0432\u043e"
    ],
    "name:und_x_variant":[
        "\u041a\u0438\u043d\u0434\u0430\u0441\u043e\u0432\u043e",
        "Kindasovo"
    ],
    "wof:name":"Kindasovo",
    "wof:placetype":"locality",
    "wof:population":6
},
  "geometry": {"coordinates":[33.45675,61.72424],"type":"Point"}
}