{
  "type": "Feature",
  "properties": {
    "gn:admin1_code":"47",
    "gn:asciiname":"Khilovo",
    "gn:country_code":"RU",
    "gn:dem":159,
    "gn:feature_class":"P",
    "gn:feature_code":"PPL",
    "gn:name":"Khilovo",
    "gn:population":0,
    "gn:timezone":"Europe/Moscow",
    "iso:country":"RU",
    "name:eng_x_preferred":[
        "Khilovo"
    ],
    "name:nor_x_preferred":[
        "Khilovo"
    ],
    "name:rus_x_preferred":[
        "\u0425\u0438\u043b\u043e\u0432\u043e"
    ],
    "name:und_x_variant":[
        "\u0425\u0438\u043b\u043e\u0432\u043e",
        "Khilovo"
    ],
    "wof:name":"Khilovo",
    "wof:placetype":"locality"
},
  "geometry": {"coordinates":[35.64165,56.31656],"type":"Point"}
}