{
  "type": "Feature",
  "properties": {
    "gn:admin1_code":"88",
    "gn:asciiname":"Opukhovo",
    "gn:country_code":"RU",
    "gn:dem":168,
    "gn:feature_class":"P",
    "gn:feature_code":"PPL",
    "gn:name":"Opukhovo",
    "gn:population":0,
    "gn:timezone":"Europe/Moscow",
    "iso:country":"RU",
    "name:rus_x_preferred":[
        "\u041e\u043f\u0443\u0445\u043e\u0432\u043e"
    ],
    "wof:name":"Opukhovo",
    "wof:placetype":"locality"
},
  "geometry": {"coordinates":[38.6337,57.2949],"type":"Point"}
}