{
  "type": "Feature",
  "properties": {
    "gn:admin1_code":"6",
    "gn:asciiname":"Vlas'yevskaya",
    "gn:country_code":"RU",
    "gn:dem":47,
    "gn:feature_class":"P",
    "gn:feature_code":"PPL",
    "gn:name":"Vlas\u2019yevskaya",
    "gn:population":0,
    "gn:timezone":"Europe/Moscow",
    "iso:country":"RU",
    "name:eng_x_preferred":[
        "Vlas'yevskaya"
    ],
    "name:nor_x_preferred":[
        "Vlasievskaja"
    ],
    "name:rus_x_preferred":[
        "\u0412\u043b\u0430\u0441\u044c\u0435\u0432\u0441\u043a\u0430\u044f"
    ],
    "name:und_x_variant":[
        "Vlas\u2019yevskaya"
    ],
    "wof:name":"Vlas'yevskaya",
    "wof:placetype":"locality"
},
  "geometry": {"coordinates":[44.3383,62.3093],"type":"Point"}
}