{
  "type": "Feature",
  "properties": {
    "gn:admin1_code":"10",
    "gn:asciiname":"Lavenka",
    "gn:country_code":"RU",
    "gn:dem":154,
    "gn:feature_class":"P",
    "gn:feature_code":"PPL",
    "gn:name":"Lavenka",
    "gn:population":0,
    "gn:timezone":"Europe/Moscow",
    "iso:country":"RU",
    "name:eng_x_preferred":[
        "Lavenka"
    ],
    "name:nor_x_preferred":[
        "Levenki"
    ],
    "name:rus_x_preferred":[
        "\u041b\u0435\u0432\u0435\u043d\u043a\u0438"
    ],
    "wof:name":"Lavenka",
    "wof:placetype":"locality"
},
  "geometry": {"coordinates":[32.88611,52.58361],"type":"Point"}
}