{
  "type": "Feature",
  "properties": {
    "gn:admin1_code":"40",
    "gn:asciiname":"Zimina",
    "gn:country_code":"RU",
    "gn:dem":135,
    "gn:feature_class":"P",
    "gn:feature_code":"PPL",
    "gn:name":"Zimina",
    "gn:population":0,
    "gn:timezone":"Asia/Yekaterinburg",
    "iso:country":"RU",
    "name:eng_x_preferred":[
        "Zimina"
    ],
    "name:nor_x_preferred":[
        "Zimina"
    ],
    "name:rus_x_preferred":[
        "\u0417\u0438\u043c\u0438\u043d\u0430"
    ],
    "name:und_x_variant":[
        "\u0417\u0438\u043c\u0438\u043d\u0430"
    ],
    "wof:name":"Zimina",
    "wof:placetype":"locality"
},
  "geometry": {"coordinates":[65.1267,56.0103],"type":"Point"}
}