{
  "type": "Feature",
  "properties": {
    "gn:admin1_code":"9.0",
    "gn:asciiname":"Astakhov",
    "gn:country_code":"RU",
    "gn:dem":204,
    "gn:feature_class":"P",
    "gn:feature_code":"PPL",
    "gn:name":"Astakhov",
    "gn:population":0,
    "gn:timezone":"Europe/Moscow",
    "iso:country":"RU",
    "name:nor_x_preferred":[
        "Astakhov"
    ],
    "name:rus_x_preferred":[
        "\u0410\u0441\u0442\u0430\u0445\u043e\u0432"
    ],
    "wof:name":"Astakhov",
    "wof:placetype":"locality"
},
  "geometry": {"coordinates":[37.70806,50.27972000000001],"type":"Point"}
}