{
  "type": "Feature",
  "properties": {
    "gn:admin1_code":"71",
    "gn:asciiname":"Gagarskaya",
    "gn:country_code":"RU",
    "gn:dem":77,
    "gn:feature_class":"P",
    "gn:feature_code":"PPL",
    "gn:name":"Gagarskaya",
    "gn:population":0,
    "gn:timezone":"Asia/Yekaterinburg",
    "iso:country":"RU",
    "name:rus_x_preferred":[
        "\u0413\u0430\u0433\u0430\u0440\u0441\u043a\u0430\u044f"
    ],
    "name:und_x_variant":[
        "\u0413\u0430\u0433\u0430\u0440\u0441\u043a\u0430\u044f"
    ],
    "wof:name":"Gagarskaya",
    "wof:placetype":"locality"
},
  "geometry": {"coordinates":[62.63333000000001,59.81667],"type":"Point"}
}