{
  "type": "Feature",
  "properties": {
    "gn:admin1_code":"17.0",
    "gn:asciiname":"Dzhanga",
    "gn:country_code":"RU",
    "gn:dem":219,
    "gn:feature_class":"P",
    "gn:feature_code":"PPL",
    "gn:name":"Dzhanga",
    "gn:population":0,
    "gn:timezone":"Europe/Moscow",
    "iso:country":"RU",
    "name:rus_x_preferred":[
        "\u0414\u0436\u0430\u043d\u0433\u0430"
    ],
    "wof:name":"Dzhanga",
    "wof:placetype":"locality"
},
  "geometry": {"coordinates":[47.76518,42.51617],"type":"Point"}
}