{
  "type": "Feature",
  "properties": {
    "gn:admin1_code":"33.0",
    "gn:asciiname":"Durkino",
    "gn:country_code":"RU",
    "gn:dem":148,
    "gn:feature_class":"P",
    "gn:feature_code":"PPL",
    "gn:name":"Durkino",
    "gn:population":0,
    "gn:timezone":"Europe/Kirov",
    "iso:country":"RU",
    "name:rus_x_preferred":[
        "\u0414\u0443\u0440\u043a\u0438\u043d\u043e"
    ],
    "name:und_x_variant":[
        "\u0414\u0443\u0440\u043a\u0438\u043d\u043e"
    ],
    "wof:name":"Durkino",
    "wof:placetype":"locality"
},
  "geometry": {"coordinates":[49.58072,58.53295],"type":"Point"}
}