{
  "type": "Feature",
  "properties": {
    "gn:admin1_code":"69",
    "gn:asciiname":"Kiselevo",
    "gn:country_code":"RU",
    "gn:dem":242,
    "gn:feature_class":"P",
    "gn:feature_code":"PPL",
    "gn:name":"Kiselevo",
    "gn:population":0,
    "gn:timezone":"Europe/Moscow",
    "iso:country":"RU",
    "name:bul_x_preferred":[
        "\u041a\u0438\u0441\u0435\u043b\u0435\u0432\u043e"
    ],
    "name:ceb_x_preferred":[
        "Kiselevo"
    ],
    "name:fas_x_preferred":[
        "\u06a9\u06cc\u0633\u0644\u0648\u0648"
    ],
    "name:kaz_x_preferred":[
        "\u041a\u0438\u0441\u0435\u043b\u0435\u0432\u043e"
    ],
    "name:msa_x_preferred":[
        "Kiselevo"
    ],
    "name:ron_x_preferred":[
        "Kiselevo"
    ],
    "name:rus_x_preferred":[
        "\u041a\u0438\u0441\u0435\u043b\u0435\u0432\u043e"
    ],
    "name:swe_x_preferred":[
        "Kiselevo"
    ],
    "name:ukr_x_preferred":[
        "\u041a\u0438\u0441\u0435\u043b\u0435\u0432\u043e"
    ],
    "wof:name":"Kiselevo",
    "wof:placetype":"locality"
},
  "geometry": {"coordinates":[34.86360999999999,55.32941999999999],"type":"Point"}
}