{
  "type": "Feature",
  "properties": {
    "gn:admin1_code":"77",
    "gn:asciiname":"Novoborovaya",
    "gn:country_code":"RU",
    "gn:dem":165,
    "gn:feature_class":"P",
    "gn:feature_code":"PPL",
    "gn:name":"Novoborovaya",
    "gn:population":0,
    "gn:timezone":"Europe/Moscow",
    "iso:country":"RU",
    "name:rus_x_preferred":[
        "\u041d\u043e\u0432\u043e\u0431\u043e\u0440\u043e\u0432\u0430\u044f"
    ],
    "name:und_x_variant":[
        "Novyye Borovyye",
        "\u041d\u043e\u0432\u043e\u0431\u043e\u0440\u043e\u0432\u0430\u044f",
        "Novoborovaya"
    ],
    "wof:name":"Novoborovaya",
    "wof:placetype":"locality"
},
  "geometry": {"coordinates":[31.89095,56.04498],"type":"Point"}
}