{
  "type": "Feature",
  "properties": {
    "gn:admin1_code":"33",
    "gn:asciiname":"Klenovaya",
    "gn:country_code":"RU",
    "gn:dem":166,
    "gn:feature_class":"P",
    "gn:feature_code":"PPL",
    "gn:name":"Klenovaya",
    "gn:population":0,
    "gn:timezone":"Europe/Kirov",
    "iso:country":"RU",
    "name:rus_x_preferred":[
        "\u041a\u043b\u0435\u043d\u043e\u0432\u0430\u044f"
    ],
    "wof:name":"Klenovaya",
    "wof:placetype":"locality"
},
  "geometry": {"coordinates":[49.477,58.31084],"type":"Point"}
}