{
  "type": "Feature",
  "properties": {
    "gn:admin1_code":"77",
    "gn:asciiname":"Novoryazanchikha",
    "gn:country_code":"RU",
    "gn:dem":140,
    "gn:feature_class":"P",
    "gn:feature_code":"PPL",
    "gn:name":"Novoryazanchikha",
    "gn:population":0,
    "gn:timezone":"Europe/Moscow",
    "iso:country":"RU",
    "name:rus_x_preferred":[
        "\u041d\u043e\u0432\u043e\u0440\u044f\u0437\u0430\u043d\u0447\u0438\u0445\u0430"
    ],
    "wof:name":"Novoryazanchikha",
    "wof:placetype":"locality"
},
  "geometry": {"coordinates":[36.4269,57.1581],"type":"Point"}
}