{
  "type": "Feature",
  "properties": {
    "gn:admin1_code":"8",
    "gn:asciiname":"Utarkul'",
    "gn:country_code":"RU",
    "gn:dem":252,
    "gn:feature_class":"P",
    "gn:feature_code":"PPL",
    "gn:name":"Utarkul\u2019",
    "gn:population":0,
    "gn:timezone":"Asia/Yekaterinburg",
    "iso:country":"RU",
    "name:rus_x_preferred":[
        "\u0423\u0442\u0430\u0440\u043a\u0443\u043b\u044c"
    ],
    "name:und_x_variant":[
        "Utarkul\u2019"
    ],
    "wof:name":"Utarkul'",
    "wof:placetype":"locality"
},
  "geometry": {"coordinates":[55.96165,53.94696999999999],"type":"Point"}
}