{
  "type": "Feature",
  "properties": {
    "gn:admin1_code":"25",
    "gn:asciiname":"Nizhnyaya Pesochnya",
    "gn:country_code":"RU",
    "gn:dem":189,
    "gn:feature_class":"P",
    "gn:feature_code":"PPL",
    "gn:name":"Nizhnyaya Pesochnya",
    "gn:population":0,
    "gn:timezone":"Europe/Moscow",
    "iso:country":"RU",
    "name:rus_x_preferred":[
        "\u041d\u0438\u0436\u043d\u044f\u044f \u041f\u0435\u0441\u043e\u0447\u043d\u044f"
    ],
    "name:und_x_variant":[
        "Vysel\u2019tsy",
        "Nizhnyaya Pesochnya"
    ],
    "wof:name":"Nizhnyaya Pesochnya",
    "wof:placetype":"locality"
},
  "geometry": {"coordinates":[34.21926,54.13159],"type":"Point"}
}