{
  "type": "Feature",
  "properties": {
    "gn:admin1_code":"7",
    "gn:asciiname":"Shagala",
    "gn:country_code":"RU",
    "gn:dem":-26,
    "gn:feature_class":"P",
    "gn:feature_code":"PPL",
    "gn:name":"Shagala",
    "gn:population":0,
    "gn:timezone":"Europe/Astrakhan",
    "iso:country":"RU",
    "name:rus_x_preferred":[
        "\u0428\u0430\u0433\u0430\u043b\u0430"
    ],
    "wof:name":"Shagala",
    "wof:placetype":"locality"
},
  "geometry": {"coordinates":[48.40284000000001,46.64798],"type":"Point"}
}