{
  "type": "Feature",
  "properties": {
    "gn:admin1_code":"77",
    "gn:asciiname":"Kosonogovo",
    "gn:country_code":"RU",
    "gn:dem":221,
    "gn:feature_class":"P",
    "gn:feature_code":"PPL",
    "gn:name":"Kosonogovo",
    "gn:population":0,
    "gn:timezone":"Europe/Moscow",
    "iso:country":"RU",
    "name:rus_x_preferred":[
        "\u041a\u043e\u0441\u043e\u043d\u043e\u0433\u043e\u0432\u043e"
    ],
    "name:und_x_variant":[
        "\u041a\u043e\u0441\u043e\u043d\u043e\u0433\u043e\u0432\u043e"
    ],
    "wof:name":"Kosonogovo",
    "wof:placetype":"locality"
},
  "geometry": {"coordinates":[36.4493,57.5303],"type":"Point"}
}