{
  "type": "Feature",
  "properties": {
    "gn:country":"RU",
    "gn:fcode":"PPL",
    "gn:pop":0,
    "iso:country":"RU",
    "name:eng_x_preferred":[
        "Perevalovo"
    ],
    "name:nor_x_preferred":[
        "Perevalovo"
    ],
    "name:rus_x_preferred":[
        "\u041f\u0435\u0440\u0435\u0432\u0430\u043b\u043e\u0432\u043e"
    ],
    "name:unk_x_variant":[
        "\u041f\u0435\u0440\u0435\u0432\u0430\u043b\u043e\u0432\u043e"
    ],
    "qs:name":"Perevalovo",
    "qs:name_adm0":"Russia",
    "qs:name_adm1":"Tyumen Oblast",
    "qs:photos_9k":1,
    "qs:photos_9r":1,
    "qs:photos_all":1,
    "qs:photos_sr":0,
    "qs:placetype":"Town",
    "qs:pop_sr":"0",
    "wof:name":"Perevalovo",
    "wof:placetype":"locality",
    "wof:population":0
},
  "geometry": {"coordinates":[65.23132,57.08242],"type":"Point"}
}