{
  "type": "Feature",
  "properties": {
    "gn:admin1_code":"73",
    "gn:asciiname":"Nizhnyaya Chegodayka",
    "gn:country_code":"RU",
    "gn:dem":152,
    "gn:feature_class":"P",
    "gn:feature_code":"PPL",
    "gn:name":"Nizhnyaya Chegodayka",
    "gn:population":0,
    "gn:timezone":"Europe/Moscow",
    "iso:country":"RU",
    "name:rus_x_preferred":[
        "\u041d\u0438\u0436\u043d\u044f\u044f \u0427\u0435\u0433\u043e\u0434\u0430\u0439\u043a\u0430"
    ],
    "name:und_x_variant":[
        "Nizhniy Chegoday",
        "\u041d\u0438\u0436\u043d\u044f\u044f \u0427\u0435\u0433\u043e\u0434\u0430\u0439\u043a\u0430"
    ],
    "wof:name":"Nizhnyaya Chegodayka",
    "wof:placetype":"locality"
},
  "geometry": {"coordinates":[51.56667,54.65],"type":"Point"}
}