{
  "type": "Feature",
  "properties": {
    "gn:admin1_code":"88",
    "gn:asciiname":"Karachikha",
    "gn:country_code":"RU",
    "gn:dem":97,
    "gn:feature_class":"P",
    "gn:feature_code":"PPL",
    "gn:name":"Karachikha",
    "gn:population":0,
    "gn:timezone":"Europe/Moscow",
    "iso:country":"RU",
    "name:rus_x_preferred":[
        "\u041a\u0430\u0440\u0430\u0447\u0438\u0445\u0430"
    ],
    "wof:name":"Karachikha",
    "wof:placetype":"locality"
},
  "geometry": {"coordinates":[39.77979000000001,57.64343],"type":"Point"}
}