{
  "type": "Feature",
  "properties": {
    "gn:admin1_code":"69",
    "gn:asciiname":"Cherepovishche",
    "gn:country_code":"RU",
    "gn:dem":168,
    "gn:feature_class":"P",
    "gn:feature_code":"PPL",
    "gn:name":"Cherepovishche",
    "gn:population":0,
    "gn:timezone":"Europe/Moscow",
    "iso:country":"RU",
    "name:rus_x_preferred":[
        "\u0427\u0435\u0440\u0435\u043f\u043e\u0432\u0438\u0449\u0435"
    ],
    "wof:name":"Cherepovishche",
    "wof:placetype":"locality"
},
  "geometry": {"coordinates":[32.2116,54.2072],"type":"Point"}
}