{
  "type": "Feature",
  "properties": {
    "gn:admin1_code":"51",
    "gn:asciiname":"Karachary",
    "gn:country_code":"RU",
    "gn:dem":135,
    "gn:feature_class":"P",
    "gn:feature_code":"PPL",
    "gn:name":"Karachary",
    "gn:population":0,
    "gn:timezone":"Europe/Moscow",
    "iso:country":"RU",
    "name:rus_x_preferred":[
        "\u041a\u0430\u0440\u0430\u0447\u0430\u0440\u044b"
    ],
    "name:und_x_variant":[
        "Karatayevka",
        "Karachary",
        "\u041a\u0430\u0440\u0430\u0447\u0430\u0440\u044b"
    ],
    "wof:name":"Karachary",
    "wof:placetype":"locality"
},
  "geometry": {"coordinates":[46.2374,55.39872],"type":"Point"}
}