{
  "type": "Feature",
  "properties": {
    "gn:admin1_code":"15",
    "gn:asciiname":"Rykaramkyn",
    "gn:country_code":"RU",
    "gn:dem":114,
    "gn:feature_class":"P",
    "gn:feature_code":"PPL",
    "gn:name":"Rykaramkyn",
    "gn:population":0,
    "gn:timezone":"Asia/Anadyr",
    "iso:country":"RU",
    "name:rus_x_preferred":[
        "\u0420\u044b\u043a\u0430\u0440\u0430\u043c\u043a\u044b\u043d"
    ],
    "wof:name":"Rykaramkyn",
    "wof:placetype":"locality"
},
  "geometry": {"coordinates":[172.84999999999999,64.84999999999999],"type":"Point"}
}