{
  "type": "Feature",
  "properties": {
    "gn:admin1_code":"61",
    "gn:asciiname":"Krasnaya Koloniya",
    "gn:country_code":"RU",
    "gn:dem":106,
    "gn:feature_class":"P",
    "gn:feature_code":"PPL",
    "gn:name":"Krasnaya Koloniya",
    "gn:population":0,
    "gn:timezone":"Europe/Moscow",
    "iso:country":"RU",
    "name:rus_x_preferred":[
        "\u041a\u0440\u0430\u0441\u043d\u0430\u044f \u041a\u043e\u043b\u043e\u043d\u0438\u044f"
    ],
    "name:und_x_variant":[
        "\u041a\u0440\u0430\u0441\u043d\u0430\u044f \u041a\u043e\u043b\u043e\u043d\u0438\u044f"
    ],
    "wof:name":"Krasnaya Koloniya",
    "wof:placetype":"locality"
},
  "geometry": {"coordinates":[38.63333,47.41667],"type":"Point"}
}