{
  "type": "Feature",
  "properties": {
    "gn:admin1_code":"11",
    "gn:asciiname":"Darkhetu",
    "gn:cc2":"RU",
    "gn:country_code":"RU",
    "gn:dem":962,
    "gn:feature_class":"P",
    "gn:feature_code":"PPL",
    "gn:name":"Darkhetu",
    "gn:population":0,
    "gn:timezone":"Asia/Irkutsk",
    "iso:country":"RU",
    "name:rus_x_preferred":[
        "\u0414\u0430\u0440\u0445\u0435\u0442\u0443"
    ],
    "name:und_x_variant":[
        "Ulus Darkhetu",
        "Darkhetu"
    ],
    "wof:name":"Darkhetu",
    "wof:placetype":"locality"
},
  "geometry": {"coordinates":[112.63333,52.53333000000001],"type":"Point"}
}