{
  "type": "Feature",
  "properties": {
    "gn:admin1_code":"55",
    "gn:asciiname":"Kozlovka",
    "gn:country_code":"RU",
    "gn:dem":276,
    "gn:feature_class":"P",
    "gn:feature_code":"PPL",
    "gn:name":"Kozlovka",
    "gn:population":0,
    "gn:timezone":"Asia/Yekaterinburg",
    "iso:country":"RU",
    "name:ara_x_preferred":[
        "\u0643\u0648\u0632\u0644\u0648\u0641\u0643\u0627"
    ],
    "name:rus_x_preferred":[
        "\u041a\u043e\u0437\u043b\u043e\u0432\u043a\u0430"
    ],
    "wof:name":"Kozlovka",
    "wof:placetype":"locality"
},
  "geometry": {"coordinates":[56.19611,52.28972],"type":"Point"}
}