{
  "type": "Feature",
  "properties": {
    "gn:admin1_code":"45.0",
    "gn:asciiname":"Malaya Sosnovka",
    "gn:country_code":"RU",
    "gn:dem":93,
    "gn:feature_class":"P",
    "gn:feature_code":"PPL",
    "gn:name":"Malaya Sosnovka",
    "gn:population":0,
    "gn:timezone":"Europe/Moscow",
    "iso:country":"RU",
    "name:rus_x_preferred":[
        "\u041c\u0430\u043b\u0430\u044f \u0421\u043e\u0441\u043d\u043e\u0432\u043a\u0430"
    ],
    "name:und_x_variant":[
        "\u041c\u0430\u043b\u0430\u044f \u0421\u043e\u0441\u043d\u043e\u0432\u043a\u0430"
    ],
    "wof:name":"Malaya Sosnovka",
    "wof:placetype":"locality"
},
  "geometry": {"coordinates":[48.68139,56.07167],"type":"Point"}
}