{
  "type": "Feature",
  "properties": {
    "gn:admin1_code":"90.0",
    "gn:asciiname":"Burtsevo",
    "gn:country_code":"RU",
    "gn:dem":318,
    "gn:feature_class":"P",
    "gn:feature_code":"PPL",
    "gn:name":"Burtsevo",
    "gn:population":0,
    "gn:timezone":"Asia/Yekaterinburg",
    "iso:country":"RU",
    "name:rus_x_preferred":[
        "\u0411\u0443\u0440\u0446\u0435\u0432\u043e"
    ],
    "name:und_x_variant":[
        "Burtseva",
        "Burtsevo"
    ],
    "wof:name":"Burtsevo",
    "wof:placetype":"locality"
},
  "geometry": {"coordinates":[57.13036,56.27838000000001],"type":"Point"}
}