{
  "type": "Feature",
  "properties": {
    "gn:admin1_code":"43",
    "gn:asciiname":"Natal'ino",
    "gn:country_code":"RU",
    "gn:dem":177,
    "gn:feature_class":"P",
    "gn:feature_code":"PPL",
    "gn:name":"Natal\u2019ino",
    "gn:population":0,
    "gn:timezone":"Europe/Moscow",
    "iso:country":"RU",
    "name:rus_x_preferred":[
        "\u041d\u0430\u0442\u0430\u043b\u044c\u0438\u043d\u043e"
    ],
    "name:und_x_variant":[
        "Natal\u2019ino",
        "\u041d\u0430\u0442\u0430\u043b\u044c\u0438\u043d\u043e"
    ],
    "wof:name":"Natal'ino",
    "wof:placetype":"locality"
},
  "geometry": {"coordinates":[38.90384,53.27221],"type":"Point"}
}