{
  "type": "Feature",
  "properties": {
    "gn:admin1_code":"6.0",
    "gn:asciiname":"Zelenyy Lug",
    "gn:country_code":"RU",
    "gn:dem":3,
    "gn:feature_class":"P",
    "gn:feature_code":"PPL",
    "gn:name":"Zel\u00ebnyy Lug",
    "gn:population":0,
    "gn:timezone":"Europe/Moscow",
    "iso:country":"RU",
    "name:rus_x_preferred":[
        "\u0417\u0435\u043b\u0451\u043d\u044b\u0439 \u041b\u0443\u0433"
    ],
    "name:und_x_variant":[
        "Zel\u00ebnyy Lug"
    ],
    "wof:name":"Zelenyy Lug",
    "wof:placetype":"locality"
},
  "geometry": {"coordinates":[40.4474,64.5334],"type":"Point"}
}