{
  "type": "Feature",
  "properties": {
    "gn:admin1_code":"24.0",
    "gn:asciiname":"Ar-Keryul'chi",
    "gn:country_code":"RU",
    "gn:dem":-1,
    "gn:feature_class":"P",
    "gn:feature_code":"PPL",
    "gn:name":"Ar-Keryul\u2019chi",
    "gn:population":0,
    "gn:timezone":"Europe/Moscow",
    "iso:country":"RU",
    "name:nor_x_preferred":[
        "Ar-Kerjultsji"
    ],
    "name:rus_x_preferred":[
        "\u0410\u0440-\u041a\u0435\u0440\u044e\u043b\u044c\u0447\u0438"
    ],
    "name:und_x_variant":[
        "Ar-Keryul\u2019chi"
    ],
    "wof:name":"Ar-Keryul'chi",
    "wof:placetype":"locality"
},
  "geometry": {"coordinates":[45.09306,46.95139],"type":"Point"}
}