{
  "type": "Feature",
  "properties": {
    "gn:admin1_code":"41",
    "gn:asciiname":"Kurchaninovka",
    "gn:country_code":"RU",
    "gn:dem":192,
    "gn:feature_class":"P",
    "gn:feature_code":"PPL",
    "gn:name":"Kurchaninovka",
    "gn:population":0,
    "gn:timezone":"Europe/Moscow",
    "iso:country":"RU",
    "name:rus_x_preferred":[
        "\u041a\u0443\u0440\u0447\u0430\u043d\u0438\u043d\u043e\u0432\u043a\u0430"
    ],
    "name:und_x_variant":[
        "\u041a\u0443\u0440\u0447\u0430\u043d\u0438\u043d\u043e\u0432\u043a\u0430"
    ],
    "wof:name":"Kurchaninovka",
    "wof:placetype":"locality"
},
  "geometry": {"coordinates":[35.41667,51.21667],"type":"Point"}
}