{
  "type": "Feature",
  "properties": {
    "gn:admin1_code":"86",
    "gn:asciiname":"Kopanishche",
    "gn:country_code":"RU",
    "gn:dem":92,
    "gn:feature_class":"P",
    "gn:feature_code":"PPL",
    "gn:name":"Kopanishche",
    "gn:population":0,
    "gn:timezone":"Europe/Moscow",
    "iso:country":"RU",
    "name:eng_x_preferred":[
        "Kopanishche"
    ],
    "name:nor_x_preferred":[
        "Kopanisjtsje"
    ],
    "name:rus_x_preferred":[
        "\u041a\u043e\u043f\u0430\u043d\u0438\u0449\u0435"
    ],
    "wof:name":"Kopanishche",
    "wof:placetype":"locality"
},
  "geometry": {"coordinates":[39.33343,51.00386],"type":"Point"}
}