{
  "type": "Feature",
  "properties": {
    "gn:admin1_code":"85.0",
    "gn:asciiname":"Ankundinovskaya",
    "gn:cc2":"RU",
    "gn:country_code":"RU",
    "gn:dem":205,
    "gn:feature_class":"P",
    "gn:feature_code":"PPL",
    "gn:name":"Ankundinovskaya",
    "gn:population":0,
    "gn:timezone":"Europe/Moscow",
    "iso:country":"RU",
    "name:nor_x_preferred":[
        "Ankundinovskaja"
    ],
    "name:rus_x_preferred":[
        "\u0410\u043d\u043a\u0443\u043d\u0434\u0438\u043d\u043e\u0432\u0441\u043a\u0430\u044f"
    ],
    "name:und_x_variant":[
        "Ankudinovo",
        "Ankundinovskaya"
    ],
    "wof:name":"Ankundinovskaya",
    "wof:placetype":"locality"
},
  "geometry": {"coordinates":[42.45,60.15],"type":"Point"}
}