{
  "type": "Feature",
  "properties": {
    "gn:admin1_code":"13",
    "gn:asciiname":"Vasilovka",
    "gn:country_code":"RU",
    "gn:dem":362,
    "gn:feature_class":"P",
    "gn:feature_code":"PPL",
    "gn:name":"Vasilovka",
    "gn:population":0,
    "gn:timezone":"Asia/Yekaterinburg",
    "iso:country":"RU",
    "name:rus_x_preferred":[
        "\u0412\u0430\u0441\u0438\u043b\u043e\u0432\u043a\u0430"
    ],
    "wof:name":"Vasilovka",
    "wof:placetype":"locality"
},
  "geometry": {"coordinates":[58.4471,54.8438],"type":"Point"}
}