{
  "type": "Feature",
  "properties": {
    "gn:admin1_code":"25",
    "gn:asciiname":"Kudinovskoye",
    "gn:country_code":"RU",
    "gn:dem":177,
    "gn:feature_class":"P",
    "gn:feature_code":"PPL",
    "gn:name":"Kudinovskoye",
    "gn:population":0,
    "gn:timezone":"Europe/Moscow",
    "iso:country":"RU",
    "name:rus_x_preferred":[
        "\u041a\u0443\u0434\u0438\u043d\u043e\u0432\u0441\u043a\u043e\u0435"
    ],
    "name:und_x_variant":[
        "\u041a\u0443\u0434\u0438\u043d\u043e\u0432\u0441\u043a\u043e\u0435"
    ],
    "wof:name":"Kudinovskoye",
    "wof:placetype":"locality"
},
  "geometry": {"coordinates":[36.07722,54.92833],"type":"Point"}
}