{
  "type": "Feature",
  "properties": {
    "gn:admin1_code":"45",
    "gn:asciiname":"Malyy Karlygan",
    "gn:country_code":"RU",
    "gn:dem":159,
    "gn:feature_class":"P",
    "gn:feature_code":"PPL",
    "gn:name":"Malyy Karlygan",
    "gn:population":0,
    "gn:timezone":"Europe/Moscow",
    "iso:country":"RU",
    "name:rus_x_preferred":[
        "\u041c\u0430\u043b\u044b\u0439 \u041a\u0430\u0440\u043b\u044b\u0433\u0430\u043d"
    ],
    "wof:name":"Malyy Karlygan",
    "wof:placetype":"locality"
},
  "geometry": {"coordinates":[50.0879,56.5746],"type":"Point"}
}