{
  "type": "Feature",
  "properties": {
    "gn:admin1_code":"52",
    "gn:asciiname":"Malyye Lovositsy",
    "gn:country_code":"RU",
    "gn:dem":28,
    "gn:feature_class":"P",
    "gn:feature_code":"PPL",
    "gn:name":"Malyye Lovositsy",
    "gn:population":0,
    "gn:timezone":"Europe/Moscow",
    "iso:country":"RU",
    "name:rus_x_preferred":[
        "\u041c\u0430\u043b\u044b\u0435 \u041b\u043e\u0432\u043e\u0441\u0438\u0446\u044b"
    ],
    "name:und_x_variant":[
        "Malyye Lovasitsy",
        "Malyye Lovositsy"
    ],
    "wof:name":"Malyye Lovositsy",
    "wof:placetype":"locality"
},
  "geometry": {"coordinates":[31.80161,57.96228000000001],"type":"Point"}
}