{
  "type": "Feature",
  "properties": {
    "gn:admin1_code":"42",
    "gn:asciiname":"Lug",
    "gn:country_code":"RU",
    "gn:dem":49,
    "gn:feature_class":"P",
    "gn:feature_code":"PPL",
    "gn:name":"Lug",
    "gn:population":0,
    "gn:timezone":"Europe/Moscow",
    "iso:country":"RU",
    "name:bel_x_preferred":[
        "\u041b\u0443\u0433"
    ],
    "name:bos_x_preferred":[
        "Lug"
    ],
    "name:ceb_x_preferred":[
        "Lug"
    ],
    "name:deu_x_preferred":[
        "Lug"
    ],
    "name:eng_x_preferred":[
        "Lug"
    ],
    "name:est_x_preferred":[
        "Lug"
    ],
    "name:fra_x_preferred":[
        "Lug"
    ],
    "name:hrv_x_preferred":[
        "Lug"
    ],
    "name:hun_x_preferred":[
        "Lug"
    ],
    "name:hye_x_preferred":[
        "\u053c\u0578\u0582\u0563"
    ],
    "name:nld_x_preferred":[
        "Lug"
    ],
    "name:nor_x_preferred":[
        "Lug"
    ],
    "name:pol_x_preferred":[
        "Lug"
    ],
    "name:por_x_preferred":[
        "Lug"
    ],
    "name:ron_x_preferred":[
        "Lug"
    ],
    "name:rus_x_preferred":[
        "\u041b\u0443\u0433"
    ],
    "name:slv_x_preferred":[
        "Lug"
    ],
    "name:spa_x_preferred":[
        "Lug"
    ],
    "name:srp_x_preferred":[
        "\u041b\u0443\u0433"
    ],
    "name:swe_x_preferred":[
        "Lug"
    ],
    "name:ukr_x_preferred":[
        "\u041b\u0443\u0433"
    ],
    "name:und_x_variant":[
        "\u041b\u0443\u0433",
        "Lug"
    ],
    "wof:name":"Lug",
    "wof:placetype":"locality"
},
  "geometry": {"coordinates":[32.64719,59.35356],"type":"Point"}
}