{
  "type": "Feature",
  "properties": {
    "gn:admin1_code":"65",
    "gn:asciiname":"Zelenyy Klyuch",
    "gn:country_code":"RU",
    "gn:dem":180,
    "gn:feature_class":"P",
    "gn:feature_code":"PPL",
    "gn:name":"Zel\u00ebnyy Klyuch",
    "gn:population":0,
    "gn:timezone":"Europe/Samara",
    "iso:country":"RU",
    "name:rus_x_preferred":[
        "\u0417\u0435\u043b\u0451\u043d\u044b\u0439 \u041a\u043b\u044e\u0447"
    ],
    "name:und_x_variant":[
        "Sefeny Klyuch",
        "Zel\u00ebnyy Klyuch"
    ],
    "wof:name":"Zelenyy Klyuch",
    "wof:placetype":"locality"
},
  "geometry": {"coordinates":[51.88333,54.31667],"type":"Point"}
}