{
  "type": "Feature",
  "properties": {
    "gn:admin1_code":"29",
    "gn:asciiname":"Karakan",
    "gn:country_code":"RU",
    "gn:dem":202,
    "gn:feature_class":"P",
    "gn:feature_code":"PPL",
    "gn:name":"Karakan",
    "gn:population":0,
    "gn:timezone":"Asia/Novokuznetsk",
    "iso:country":"RU",
    "name:eng_x_preferred":[
        "Karakan"
    ],
    "name:nor_x_preferred":[
        "Karakan"
    ],
    "name:rus_x_preferred":[
        "\u041a\u0430\u0440\u0430\u043a\u0430\u043d"
    ],
    "name:und_x_variant":[
        "Karakanskoye"
    ],
    "wof:name":"Karakan",
    "wof:placetype":"locality"
},
  "geometry": {"coordinates":[86.7773,54.3944],"type":"Point"}
}