{
  "type": "Feature",
  "properties": {
    "gn:admin1_code":"76",
    "gn:asciiname":"Turgenevskiy",
    "gn:country_code":"RU",
    "gn:dem":187,
    "gn:feature_class":"P",
    "gn:feature_code":"PPL",
    "gn:name":"Turgenevskiy",
    "gn:population":0,
    "gn:timezone":"Europe/Moscow",
    "iso:country":"RU",
    "name:rus_x_preferred":[
        "\u0422\u0443\u0440\u0433\u0435\u043d\u0435\u0432\u0441\u043a\u0438\u0439"
    ],
    "wof:name":"Turgenevskiy",
    "wof:placetype":"locality"
},
  "geometry": {"coordinates":[38.2572,53.8808],"type":"Point"}
}