{
  "type": "Feature",
  "properties": {
    "gn:admin1_code":"88.0",
    "gn:asciiname":"Ivanikovo",
    "gn:country_code":"RU",
    "gn:dem":93,
    "gn:feature_class":"P",
    "gn:feature_code":"PPL",
    "gn:name":"Ivanikovo",
    "gn:population":0,
    "gn:timezone":"Europe/Moscow",
    "iso:country":"RU",
    "name:rus_x_preferred":[
        "\u0418\u0432\u0430\u043d\u0438\u043a\u043e\u0432\u043e"
    ],
    "name:und_x_variant":[
        "\u0418\u0432\u0430\u043d\u0438\u043a\u043e\u0432\u043e"
    ],
    "wof:name":"Ivanikovo",
    "wof:placetype":"locality"
},
  "geometry": {"coordinates":[40.65829,58.02759],"type":"Point"}
}