{
  "type": "Feature",
  "properties": {
    "gn:admin1_code":"42",
    "gn:asciiname":"Louzna",
    "gn:country_code":"RU",
    "gn:dem":125,
    "gn:feature_class":"P",
    "gn:feature_code":"PPL",
    "gn:name":"Louzna",
    "gn:population":0,
    "gn:timezone":"Europe/Moscow",
    "iso:country":"RU",
    "name:fin_x_preferred":[
        "Lousnankyl\u00e4"
    ],
    "name:rus_x_preferred":[
        "\u041b\u043e\u0443\u0437\u043d\u0430"
    ],
    "wof:name":"Louzna",
    "wof:placetype":"locality"
},
  "geometry": {"coordinates":[28.96122,59.58769],"type":"Point"}
}