{
  "type": "Feature",
  "properties": {
    "gn:admin1_code":"51.0",
    "gn:asciiname":"V'yushkino",
    "gn:country_code":"RU",
    "gn:dem":179,
    "gn:feature_class":"P",
    "gn:feature_code":"PPL",
    "gn:name":"V\u2019yushkino",
    "gn:population":0,
    "gn:timezone":"Europe/Moscow",
    "iso:country":"RU",
    "name:rus_x_preferred":[
        "\u0412\u044c\u044e\u0448\u043a\u0438\u043d\u043e"
    ],
    "name:und_x_variant":[
        "V\u2019yushkino"
    ],
    "wof:name":"V'yushkino",
    "wof:placetype":"locality"
},
  "geometry": {"coordinates":[44.98166,54.57286],"type":"Point"}
}