{
  "type": "Feature",
  "properties": {
    "gn:admin1_code":"10",
    "gn:asciiname":"Novyye Ivaytenki",
    "gn:country_code":"RU",
    "gn:dem":191,
    "gn:feature_class":"P",
    "gn:feature_code":"PPL",
    "gn:name":"Novyye Ivaytenki",
    "gn:population":0,
    "gn:timezone":"Europe/Moscow",
    "iso:country":"RU",
    "name:eng_x_preferred":[
        "Ivaytenki"
    ],
    "name:nor_x_preferred":[
        "Novye Ivajteny"
    ],
    "name:rus_x_preferred":[
        "\u041d\u043e\u0432\u044b\u0435 \u0418\u0432\u0430\u0439\u0442\u0435\u043d\u044b"
    ],
    "name:rus_x_variant":[
        "\u041d\u043e\u0432\u044b\u0435 \u0418\u0432\u0430\u0439\u0442\u0435\u043d\u043a\u0438"
    ],
    "name:und_x_variant":[
        "\u041d\u043e\u0432\u044b\u0435 \u0418\u0432\u0430\u0439\u0442\u0435\u043d\u043a\u0438",
        "Ivaytenki"
    ],
    "wof:name":"Novyye Ivaytenki",
    "wof:placetype":"locality"
},
  "geometry": {"coordinates":[33.06629,52.78369],"type":"Point"}
}