{
  "type": "Feature",
  "properties": {
    "gn:admin1_code":"25",
    "gn:asciiname":"Okhotnoye",
    "gn:country_code":"RU",
    "gn:dem":180,
    "gn:feature_class":"P",
    "gn:feature_code":"PPL",
    "gn:name":"Okhotnoye",
    "gn:population":0,
    "gn:timezone":"Europe/Moscow",
    "iso:country":"RU",
    "name:eng_x_preferred":[
        "Okhotnoye"
    ],
    "name:nor_x_preferred":[
        "Okhotnoje"
    ],
    "name:rus_x_preferred":[
        "\u041e\u0445\u043e\u0442\u043d\u043e\u0435"
    ],
    "wof:name":"Okhotnoye",
    "wof:placetype":"locality"
},
  "geometry": {"coordinates":[35.15156,54.09526],"type":"Point"}
}