{
  "type": "Feature",
  "properties": {
    "gn:admin1_code":"61",
    "gn:asciiname":"Dal'neye Pole",
    "gn:country_code":"RU",
    "gn:dem":52,
    "gn:feature_class":"P",
    "gn:feature_code":"PPL",
    "gn:name":"Dal\u2019neye Pole",
    "gn:population":0,
    "gn:timezone":"Europe/Moscow",
    "iso:country":"RU",
    "name:rus_x_preferred":[
        "\u0414\u0430\u043b\u044c\u043d\u0435\u0435 \u041f\u043e\u043b\u0435"
    ],
    "name:und_x_variant":[
        "Dal\u2019neye Pole"
    ],
    "wof:name":"Dal'neye Pole",
    "wof:placetype":"locality"
},
  "geometry": {"coordinates":[41.6501,46.0981],"type":"Point"}
}