{
  "type": "Feature",
  "properties": {
    "gn:admin1_code":"6",
    "gn:asciiname":"Kuz'mino",
    "gn:country_code":"RU",
    "gn:dem":7,
    "gn:feature_class":"P",
    "gn:feature_code":"PPL",
    "gn:name":"Kuz\u2019mino",
    "gn:population":0,
    "gn:timezone":"Europe/Moscow",
    "iso:country":"RU",
    "name:eng_x_preferred":[
        "Kuz'mino"
    ],
    "name:nor_x_preferred":[
        "Kuzmino"
    ],
    "name:rus_x_preferred":[
        "\u041a\u0443\u0437\u044c\u043c\u0438\u043d\u043e"
    ],
    "name:und_x_variant":[
        "Kuz\u2019mino"
    ],
    "wof:name":"Kuz'mino",
    "wof:placetype":"locality"
},
  "geometry": {"coordinates":[40.9564,64.3796],"type":"Point"}
}