{
  "type": "Feature",
  "properties": {
    "gn:admin1_code":"56",
    "gn:asciiname":"Khutor",
    "gn:country_code":"RU",
    "gn:dem":245,
    "gn:feature_class":"P",
    "gn:feature_code":"PPL",
    "gn:name":"Khutor",
    "gn:population":0,
    "gn:timezone":"Europe/Moscow",
    "iso:country":"RU",
    "name:bel_x_preferred":[
        "\u0425\u0443\u0442\u0430\u0440"
    ],
    "name:bul_x_preferred":[
        "\u0425\u0443\u0442\u043e\u0440"
    ],
    "name:cat_x_preferred":[
        "Kh\u00fator"
    ],
    "name:che_x_preferred":[
        "\u041aI\u043e\u0442\u0430\u0440"
    ],
    "name:chv_x_preferred":[
        "\u0425\u0443\u0442\u043e\u0440"
    ],
    "name:est_x_preferred":[
        "Huutor"
    ],
    "name:fin_x_preferred":[
        "Huuttori"
    ],
    "name:fra_x_preferred":[
        "Khoutor"
    ],
    "name:hye_x_preferred":[
        "\u053d\u0578\u0582\u057f\u0578\u0580"
    ],
    "name:ita_x_preferred":[
        "Chutor"
    ],
    "name:kaz_x_preferred":[
        "\u049a\u044b\u0441\u0442\u0430\u049b"
    ],
    "name:lav_x_preferred":[
        "Viens\u0113ta"
    ],
    "name:lit_x_preferred":[
        "Viens\u0117dis"
    ],
    "name:mhr_x_preferred":[
        "\u0425\u0443\u0442\u043e\u0440"
    ],
    "name:msa_x_preferred":[
        "Kebun kecil"
    ],
    "name:nld_x_preferred":[
        "Choetor"
    ],
    "name:pol_x_preferred":[
        "Chutor"
    ],
    "name:ron_x_preferred":[
        "Hutor"
    ],
    "name:rus_x_preferred":[
        "\u0425\u0443\u0442\u043e\u0440"
    ],
    "name:spa_x_preferred":[
        "J\u00fator"
    ],
    "name:srp_x_preferred":[
        "\u0425\u0443\u0442\u043e\u0440"
    ],
    "name:tat_x_preferred":[
        "\u0425\u0443\u0442\u043e\u0440"
    ],
    "name:ukr_x_preferred":[
        "\u0425\u0443\u0442\u0456\u0440"
    ],
    "name:und_x_variant":[
        "\u0425\u0443\u0442\u043e\u0440"
    ],
    "wof:name":"Khutor",
    "wof:placetype":"locality"
},
  "geometry": {"coordinates":[37.65032,53.07905],"type":"Point"}
}