{
  "type": "Feature",
  "properties": {
    "gn:admin1_code":"56",
    "gn:asciiname":"Khutor",
    "gn:country_code":"RU",
    "gn:dem":245,
    "gn:feature_class":"P",
    "gn:feature_code":"PPL",
    "gn:name":"Khutor",
    "gn:population":0,
    "gn:timezone":"Europe/Moscow",
    "iso:country":"RU",
    "name:rus_x_preferred":[
        "\u0425\u0443\u0442\u043e\u0440"
    ],
    "name:und_x_variant":[
        "\u0425\u0443\u0442\u043e\u0440"
    ],
    "wof:name":"Khutor",
    "wof:placetype":"locality"
},
  "geometry": {"coordinates":[37.65032,53.07905],"type":"Point"}
}