{
  "type": "Feature",
  "properties": {
    "gn:admin1_code":"34",
    "gn:asciiname":"Ust'-Vacherga",
    "gn:country_code":"RU",
    "gn:dem":98,
    "gn:feature_class":"P",
    "gn:feature_code":"PPL",
    "gn:name":"Ust\u2019-Vacherga",
    "gn:population":0,
    "gn:timezone":"Europe/Moscow",
    "iso:country":"RU",
    "name:eng_x_preferred":[
        "Ust'-Vacherga"
    ],
    "name:nor_x_preferred":[
        "Ust-Vatsjerga"
    ],
    "name:rus_x_preferred":[
        "\u0423\u0441\u0442\u044c-\u0412\u0430\u0447\u0435\u0440\u0433\u0430"
    ],
    "name:und_x_variant":[
        "Ust\u2019-Vacherskaya",
        "Ust\u2019-Vacherga"
    ],
    "wof:name":"Ust'-Vacherga",
    "wof:placetype":"locality"
},
  "geometry": {"coordinates":[47.9112,63.3696],"type":"Point"}
}