{
  "type": "Feature",
  "properties": {
    "gn:admin1_code":"73",
    "gn:asciiname":"Russkiy Pakshin",
    "gn:country_code":"RU",
    "gn:dem":94,
    "gn:feature_class":"P",
    "gn:feature_code":"PPL",
    "gn:name":"Russkiy Pakshin",
    "gn:population":0,
    "gn:timezone":"Europe/Moscow",
    "iso:country":"RU",
    "name:rus_x_preferred":[
        "\u0420\u0443\u0441\u0441\u043a\u0438\u0439 \u041f\u0430\u043a\u0448\u0438\u043d"
    ],
    "name:und_x_variant":[
        "\u0420\u0443\u0441\u0441\u043a\u0438\u0439 \u041f\u0430\u043a\u0448\u0438\u043d"
    ],
    "wof:name":"Russkiy Pakshin",
    "wof:placetype":"locality"
},
  "geometry": {"coordinates":[51.3254,55.6138],"type":"Point"}
}