{
  "type": "Feature",
  "properties": {
    "gn:admin1_code":"69.0",
    "gn:asciiname":"Derebuzh Pervyy",
    "gn:country_code":"RU",
    "gn:dem":175,
    "gn:feature_class":"P",
    "gn:feature_code":"PPL",
    "gn:name":"Derebuzh Pervyy",
    "gn:population":0,
    "gn:timezone":"Europe/Moscow",
    "iso:country":"RU",
    "name:rus_x_preferred":[
        "\u0414\u0435\u0440\u0435\u0431\u0443\u0436 \u041f\u0435\u0440\u0432\u044b\u0439"
    ],
    "name:und_x_variant":[
        "Derebuzh",
        "Derebuzh Pervyy"
    ],
    "wof:name":"Derebuzh Pervyy",
    "wof:placetype":"locality"
},
  "geometry": {"coordinates":[32.59191,54.07631],"type":"Point"}
}