{
  "type": "Feature",
  "properties": {
    "gn:admin1_code":"90.0",
    "gn:asciiname":"Yesaul",
    "gn:country_code":"RU",
    "gn:dem":168,
    "gn:feature_class":"P",
    "gn:feature_code":"PPL",
    "gn:name":"Yesaul",
    "gn:population":0,
    "gn:timezone":"Asia/Yekaterinburg",
    "iso:country":"RU",
    "name:aze_x_preferred":[
        "Yasavul"
    ],
    "name:bel_x_preferred":[
        "\u0415\u0441\u0430\u0443\u043b"
    ],
    "name:ces_x_preferred":[
        "Esaul"
    ],
    "name:deu_x_preferred":[
        "Jessaul"
    ],
    "name:ell_x_preferred":[
        "\u0393\u03b9\u03b5\u03c3\u03b1\u03bf\u03cd\u03bb"
    ],
    "name:fra_x_preferred":[
        "Iessaoul"
    ],
    "name:ita_x_preferred":[
        "Yesaul"
    ],
    "name:kat_x_preferred":[
        "\u10d8\u10d0\u10e1\u10d0\u10e3\u10da\u10d8"
    ],
    "name:lit_x_preferred":[
        "Esaulas"
    ],
    "name:nor_x_preferred":[
        "Jesaul"
    ],
    "name:pol_x_preferred":[
        "Esau\u0142"
    ],
    "name:rus_x_preferred":[
        "\u0415\u0441\u0430\u0443\u043b"
    ],
    "name:spa_x_preferred":[
        "Yesa\u00fal"
    ],
    "name:swe_x_preferred":[
        "Jesaul"
    ],
    "name:ukr_x_preferred":[
        "\u041e\u0441\u0430\u0432\u0443\u043b"
    ],
    "name:und_x_variant":[
        "Bol\u2019shoy Yesaul",
        "\u0411\u043e\u043b\u044c\u0448\u043e\u0439 \u0415\u0441\u0430\u0443\u043b",
        "Yesaul"
    ],
    "name:uzb_x_preferred":[
        "Yasovul"
    ],
    "wof:name":"Yesaul",
    "wof:placetype":"locality"
},
  "geometry": {"coordinates":[56.28975,56.35715],"type":"Point"}
}