{
  "type": "Feature",
  "properties": {
    "gn:admin1_code":"90.0",
    "gn:asciiname":"Yesaul",
    "gn:country_code":"RU",
    "gn:dem":168,
    "gn:feature_class":"P",
    "gn:feature_code":"PPL",
    "gn:name":"Yesaul",
    "gn:population":0,
    "gn:timezone":"Asia/Yekaterinburg",
    "iso:country":"RU",
    "name:rus_x_preferred":[
        "\u0415\u0441\u0430\u0443\u043b"
    ],
    "name:und_x_variant":[
        "Bol\u2019shoy Yesaul",
        "\u0411\u043e\u043b\u044c\u0448\u043e\u0439 \u0415\u0441\u0430\u0443\u043b",
        "Yesaul"
    ],
    "wof:name":"Yesaul",
    "wof:placetype":"locality"
},
  "geometry": {"coordinates":[56.28975,56.35715],"type":"Point"}
}