{
  "type": "Feature",
  "properties": {
    "gn:admin1_code":"8",
    "gn:asciiname":"Neforoshchanka",
    "gn:country_code":"RU",
    "gn:dem":145,
    "gn:feature_class":"P",
    "gn:feature_code":"PPL",
    "gn:name":"Neforoshchanka",
    "gn:population":0,
    "gn:timezone":"Asia/Yekaterinburg",
    "iso:country":"RU",
    "name:eng_x_preferred":[
        "Neforoshcha"
    ],
    "name:nor_x_preferred":[
        "Neforosjtsjanka"
    ],
    "name:rus_x_preferred":[
        "\u041d\u0435\u0444\u043e\u0440\u043e\u0449\u0430\u043d\u043a\u0430"
    ],
    "name:und_x_variant":[
        "Neforoshcha",
        "Neforoshchanka"
    ],
    "wof:name":"Neforoshchanka",
    "wof:placetype":"locality"
},
  "geometry": {"coordinates":[55.44814,53.96953000000001],"type":"Point"}
}