{
  "type": "Feature",
  "properties": {
    "gn:admin1_code":"38",
    "gn:asciiname":"Lenina",
    "gn:country_code":"RU",
    "gn:dem":33,
    "gn:feature_class":"P",
    "gn:feature_code":"PPL",
    "gn:name":"Lenina",
    "gn:population":0,
    "gn:timezone":"Europe/Moscow",
    "iso:country":"RU",
    "name:rus_x_preferred":[
        "\u041b\u0435\u043d\u0438\u043d\u0430"
    ],
    "name:und_x_variant":[
        "Khutor Imeni Lenina",
        "Lenina",
        "\u041b\u0435\u043d\u0438\u043d\u0430"
    ],
    "wof:name":"Lenina",
    "wof:placetype":"locality"
},
  "geometry": {"coordinates":[39.22099,45.0214],"type":"Point"}
}