{
  "type": "Feature",
  "properties": {
    "gn:admin1_code":"60",
    "gn:asciiname":"Perkhovo",
    "gn:country_code":"RU",
    "gn:dem":267,
    "gn:feature_class":"P",
    "gn:feature_code":"PPL",
    "gn:name":"Perkhovo",
    "gn:population":0,
    "gn:timezone":"Europe/Moscow",
    "iso:country":"RU",
    "name:rus_x_preferred":[
        "\u041f\u0435\u0440\u0445\u043e\u0432\u043e"
    ],
    "name:und_x_variant":[
        "\u041f\u0435\u0440\u0445\u043e\u0432\u043e"
    ],
    "wof:name":"Perkhovo",
    "wof:placetype":"locality"
},
  "geometry": {"coordinates":[29.3539,56.8567],"type":"Point"}
}