{
  "type": "Feature",
  "properties": {
    "gn:admin1_code":"61",
    "gn:asciiname":"Kon'kov",
    "gn:country_code":"RU",
    "gn:dem":82,
    "gn:feature_class":"P",
    "gn:feature_code":"PPL",
    "gn:name":"Kon\u2019kov",
    "gn:population":0,
    "gn:timezone":"Europe/Moscow",
    "iso:country":"RU",
    "name:rus_x_preferred":[
        "\u041a\u043e\u043d\u044c\u043a\u043e\u0432"
    ],
    "name:und_x_variant":[
        "Kon\u2019kov",
        "\u041a\u043e\u043d\u044c\u043a\u043e\u0432"
    ],
    "wof:name":"Kon'kov",
    "wof:placetype":"locality"
},
  "geometry": {"coordinates":[41.69935,48.82714],"type":"Point"}
}