{
  "type": "Feature",
  "properties": {
    "gn:admin1_code":"3",
    "gn:asciiname":"Ten'ga",
    "gn:country_code":"RU",
    "gn:dem":1000,
    "gn:feature_class":"P",
    "gn:feature_code":"PPL",
    "gn:name":"Ten\u2019ga",
    "gn:population":0,
    "gn:timezone":"Asia/Omsk",
    "iso:country":"RU",
    "name:eng_x_preferred":[
        "Ten'ga"
    ],
    "name:nor_x_preferred":[
        "Tenga"
    ],
    "name:rus_x_preferred":[
        "\u0422\u0435\u043d\u044c\u0433\u0430"
    ],
    "name:und_x_variant":[
        "Ten\u2019ga"
    ],
    "wof:name":"Ten'ga",
    "wof:placetype":"locality"
},
  "geometry": {"coordinates":[85.6575,50.8389],"type":"Point"}
}