{
  "type": "Feature",
  "properties": {
    "gn:admin1_code":"77.0",
    "gn:asciiname":"Filippkovo",
    "gn:country_code":"RU",
    "gn:dem":132,
    "gn:feature_class":"P",
    "gn:feature_code":"PPL",
    "gn:name":"Filippkovo",
    "gn:population":0,
    "gn:timezone":"Europe/Moscow",
    "iso:country":"RU",
    "name:rus_x_preferred":[
        "\u0424\u0438\u043b\u0438\u043f\u043f\u043a\u043e\u0432\u043e"
    ],
    "name:und_x_variant":[
        "\u0424\u0438\u043b\u0438\u043f\u043f\u043a\u043e\u0432\u043e"
    ],
    "wof:name":"Filippkovo",
    "wof:placetype":"locality"
},
  "geometry": {"coordinates":[36.64556,57.21083],"type":"Point"}
}