{
  "type": "Feature",
  "properties": {
    "gn:admin1_code":"85",
    "gn:asciiname":"Maletino",
    "gn:country_code":"RU",
    "gn:dem":61,
    "gn:feature_class":"P",
    "gn:feature_code":"PPL",
    "gn:name":"Mal\u00ebtino",
    "gn:population":0,
    "gn:timezone":"Europe/Moscow",
    "iso:country":"RU",
    "name:rus_x_preferred":[
        "\u041c\u0430\u043b\u0451\u0442\u0438\u043d\u043e"
    ],
    "name:und_x_variant":[
        "Mal\u00ebtino"
    ],
    "wof:name":"Maletino",
    "wof:placetype":"locality"
},
  "geometry": {"coordinates":[46.46667,60.91667],"type":"Point"}
}