{
  "type": "Feature",
  "properties": {
    "gn:admin1_code":"78",
    "gn:asciiname":"Zarosloye",
    "gn:country_code":"RU",
    "gn:dem":136,
    "gn:feature_class":"P",
    "gn:feature_code":"PPL",
    "gn:name":"Zarosloye",
    "gn:population":0,
    "gn:timezone":"Asia/Yekaterinburg",
    "iso:country":"RU",
    "name:eng_x_preferred":[
        "Zarosloye"
    ],
    "name:nor_x_preferred":[
        "Zarosloje"
    ],
    "name:rus_x_preferred":[
        "\u0417\u0430\u0440\u043e\u0441\u043b\u043e\u0435"
    ],
    "wof:name":"Zarosloye",
    "wof:placetype":"locality"
},
  "geometry": {"coordinates":[68.61156,55.4782],"type":"Point"}
}