{
  "type": "Feature",
  "properties": {
    "gn:admin1_code":"31",
    "gn:asciiname":"Tupik",
    "gn:country_code":"RU",
    "gn:dem":533,
    "gn:feature_class":"P",
    "gn:feature_code":"PPL",
    "gn:name":"Tupik",
    "gn:population":0,
    "gn:timezone":"Asia/Krasnoyarsk",
    "iso:country":"RU",
    "name:eng_x_preferred":[
        "Tupik"
    ],
    "name:nor_x_preferred":[
        "Tupik"
    ],
    "name:rus_x_preferred":[
        "\u0422\u0443\u043f\u0438\u043a"
    ],
    "wof:name":"Tupik",
    "wof:placetype":"locality"
},
  "geometry": {"coordinates":[89.93521,54.38688000000001],"type":"Point"}
}