{
  "type": "Feature",
  "properties": {
    "gn:admin1_code":"10",
    "gn:asciiname":"Babka",
    "gn:country_code":"RU",
    "gn:dem":185,
    "gn:feature_class":"P",
    "gn:feature_code":"PPL",
    "gn:name":"Babka",
    "gn:population":0,
    "gn:timezone":"Europe/Moscow",
    "iso:country":"RU",
    "name:bel_x_preferred":[
        "\u0411\u0430\u0431\u043a\u0430"
    ],
    "name:ceb_x_preferred":[
        "Babka"
    ],
    "name:ces_x_preferred":[
        "Babka"
    ],
    "name:deu_x_preferred":[
        "Babka"
    ],
    "name:hye_x_preferred":[
        "\u0532\u0561\u0562\u056f\u0561"
    ],
    "name:kaz_x_preferred":[
        "\u0411\u0430\u0441\u0448\u0430"
    ],
    "name:nno_x_preferred":[
        "Babka"
    ],
    "name:nor_x_preferred":[
        "Babka"
    ],
    "name:pol_x_preferred":[
        "Babka"
    ],
    "name:rus_x_preferred":[
        "\u0411\u0430\u0431\u043a\u0430"
    ],
    "name:slk_x_preferred":[
        "Babka"
    ],
    "name:swe_x_preferred":[
        "Babka"
    ],
    "name:ukr_x_preferred":[
        "\u0411\u0430\u0431\u043a\u0430"
    ],
    "name:zho_x_preferred":[
        "\u5df4\u5e03\u5361"
    ],
    "wof:name":"Babka",
    "wof:placetype":"locality"
},
  "geometry": {"coordinates":[33.244,53.4291],"type":"Point"}
}