{
  "type": "Feature",
  "properties": {
    "gn:admin1_code":"10",
    "gn:asciiname":"Babka",
    "gn:country_code":"RU",
    "gn:dem":185,
    "gn:feature_class":"P",
    "gn:feature_code":"PPL",
    "gn:name":"Babka",
    "gn:population":0,
    "gn:timezone":"Europe/Moscow",
    "iso:country":"RU",
    "name:nor_x_preferred":[
        "Babka"
    ],
    "name:rus_x_preferred":[
        "\u0411\u0430\u0431\u043a\u0430"
    ],
    "wof:name":"Babka",
    "wof:placetype":"locality"
},
  "geometry": {"coordinates":[33.244,53.4291],"type":"Point"}
}