{
  "type": "Feature",
  "properties": {
    "gn:admin1_code":"77",
    "gn:asciiname":"Vseluki",
    "gn:country_code":"RU",
    "gn:dem":207,
    "gn:feature_class":"P",
    "gn:feature_code":"PPL",
    "gn:name":"Vseluki",
    "gn:population":0,
    "gn:timezone":"Europe/Moscow",
    "iso:country":"RU",
    "name:rus_x_preferred":[
        "\u0412\u0441\u0435\u043b\u0443\u043a\u0438"
    ],
    "name:und_x_variant":[
        "Vseluk",
        "Vseluki"
    ],
    "wof:name":"Vseluki",
    "wof:placetype":"locality"
},
  "geometry": {"coordinates":[32.65714000000001,56.98056999999999],"type":"Point"}
}