{
  "type": "Feature",
  "properties": {
    "gn:admin1_code":"37",
    "gn:asciiname":"Chirkovo",
    "gn:country_code":"RU",
    "gn:dem":210,
    "gn:feature_class":"P",
    "gn:feature_code":"PPL",
    "gn:name":"Chirkovo",
    "gn:population":0,
    "gn:timezone":"Europe/Moscow",
    "iso:country":"RU",
    "name:che_x_preferred":[
        "\u0427\u0438\u0440\u043a\u043e\u0432\u043e"
    ],
    "name:rus_x_preferred":[
        "\u0427\u0438\u0440\u043a\u043e\u0432\u043e"
    ],
    "wof:name":"Chirkovo",
    "wof:placetype":"locality"
},
  "geometry": {"coordinates":[42.6037,58.4364],"type":"Point"}
}