{
  "type": "Feature",
  "properties": {
    "gn:admin1_code":"90",
    "gn:asciiname":"Pleshki",
    "gn:country_code":"RU",
    "gn:dem":192,
    "gn:feature_class":"P",
    "gn:feature_code":"PPL",
    "gn:name":"Pleshki",
    "gn:population":0,
    "gn:timezone":"Asia/Yekaterinburg",
    "iso:country":"RU",
    "name:rus_x_preferred":[
        "\u041f\u043b\u0435\u0448\u043a\u0438"
    ],
    "wof:name":"Pleshki",
    "wof:placetype":"locality"
},
  "geometry": {"coordinates":[55.53333000000001,58.71666999999999],"type":"Point"}
}