{
  "type": "Feature",
  "properties": {
    "gn:admin1_code":"8",
    "gn:asciiname":"Usmanovo",
    "gn:country_code":"RU",
    "gn:dem":171,
    "gn:feature_class":"P",
    "gn:feature_code":"PPL",
    "gn:name":"Usmanovo",
    "gn:population":0,
    "gn:timezone":"Asia/Yekaterinburg",
    "iso:country":"RU",
    "name:rus_x_preferred":[
        "\u0423\u0441\u043c\u0430\u043d\u043e\u0432\u043e"
    ],
    "name:und_x_variant":[
        "Usmankino",
        "Usmanovo"
    ],
    "wof:name":"Usmanovo",
    "wof:placetype":"locality"
},
  "geometry": {"coordinates":[55.74385,53.92939000000001],"type":"Point"}
}