{
  "type": "Feature",
  "properties": {
    "gn:admin1_code":"8",
    "gn:asciiname":"Urtakul'skoye",
    "gn:country_code":"RU",
    "gn:dem":217,
    "gn:feature_class":"P",
    "gn:feature_code":"PPL",
    "gn:name":"Urtakul\u2019skoye",
    "gn:population":0,
    "gn:timezone":"Asia/Yekaterinburg",
    "iso:country":"RU",
    "name:rus_x_preferred":[
        "\u0423\u0440\u0442\u0430\u043a\u0443\u043b\u044c\u0441\u043a\u043e\u0435"
    ],
    "name:und_x_variant":[
        "Urtakul\u2019skoye"
    ],
    "wof:name":"Urtakul'skoye",
    "wof:placetype":"locality"
},
  "geometry": {"coordinates":[54.467,54.5112],"type":"Point"}
}