{
  "type": "Feature",
  "properties": {
    "gn:admin1_code":"70.0",
    "gn:asciiname":"Bezivanovka",
    "gn:country_code":"RU",
    "gn:dem":389,
    "gn:feature_class":"P",
    "gn:feature_code":"PPL",
    "gn:name":"Bezivanovka",
    "gn:population":0,
    "gn:timezone":"Europe/Moscow",
    "iso:country":"RU",
    "name:nor_x_preferred":[
        "Bezivanovka"
    ],
    "name:rus_x_preferred":[
        "\u0411\u0435\u0437\u0438\u0432\u0430\u043d\u043e\u0432\u043a\u0430"
    ],
    "name:und_x_variant":[
        "Bezyvanovka"
    ],
    "wof:name":"Bezivanovka",
    "wof:placetype":"locality"
},
  "geometry": {"coordinates":[43.08417,44.41],"type":"Point"}
}