{
  "type": "Feature",
  "properties": {
    "gn:country":"RU",
    "gn:fcode":"PPL",
    "gn:population":3966,
    "iso:country":"RU",
    "name:eng_x_preferred":[
        "Krasnovka"
    ],
    "name:nor_x_preferred":[
        "Krasnovka"
    ],
    "name:rus_x_preferred":[
        "\u041a\u0440\u0430\u0441\u043d\u043e\u0432\u043a\u0430"
    ],
    "qs:name":"Krasnovka",
    "qs:name_adm0":"Russia",
    "qs:name_adm1":"Rostov Oblast",
    "qs:photos_9r":0,
    "qs:photos_sr":0,
    "qs:placetype":"Town",
    "qs:pop_sr":"4",
    "wof:name":"Krasnovka",
    "wof:placetype":"locality",
    "wof:population":3966
},
  "geometry": {"coordinates":[40.09226,48.81769],"type":"Point"}
}