{
  "type": "Feature",
  "properties": {
    "gn:admin1_code":"37",
    "gn:asciiname":"Dudinskaya Vtoraya",
    "gn:country_code":"RU",
    "gn:dem":173,
    "gn:feature_class":"P",
    "gn:feature_code":"PPL",
    "gn:name":"Dudinskaya Vtoraya",
    "gn:population":0,
    "gn:timezone":"Europe/Moscow",
    "iso:country":"RU",
    "name:rus_x_preferred":[
        "\u0414\u0443\u0434\u0438\u043d\u0441\u043a\u0430\u044f \u0412\u0442\u043e\u0440\u0430\u044f"
    ],
    "wof:name":"Dudinskaya Vtoraya",
    "wof:placetype":"locality"
},
  "geometry": {"coordinates":[47.278,59.0474],"type":"Point"}
}