{
  "type": "Feature",
  "properties": {
    "gn:admin1_code":"13",
    "gn:asciiname":"Kashigina",
    "gn:country_code":"RU",
    "gn:dem":326,
    "gn:feature_class":"P",
    "gn:feature_code":"PPL",
    "gn:name":"Kashigina",
    "gn:population":0,
    "gn:timezone":"Asia/Yekaterinburg",
    "iso:country":"RU",
    "name:rus_x_preferred":[
        "\u041a\u0430\u0448\u0438\u0433\u0438\u043d\u0430"
    ],
    "wof:name":"Kashigina",
    "wof:placetype":"locality"
},
  "geometry": {"coordinates":[60.66667,55.03333000000001],"type":"Point"}
}