{
  "type": "Feature",
  "properties": {
    "gn:admin1_code":"90",
    "gn:asciiname":"Katyshi",
    "gn:country_code":"RU",
    "gn:dem":129,
    "gn:feature_class":"P",
    "gn:feature_code":"PPL",
    "gn:name":"Katyshi",
    "gn:population":0,
    "gn:timezone":"Asia/Yekaterinburg",
    "iso:country":"RU",
    "name:rus_x_preferred":[
        "\u041a\u0430\u0442\u044b\u0448\u0438"
    ],
    "wof:name":"Katyshi",
    "wof:placetype":"locality"
},
  "geometry": {"coordinates":[55.9243,58.2232],"type":"Point"}
}