{
  "type": "Feature",
  "properties": {
    "gn:admin1_code":"38.0",
    "gn:asciiname":"Nizhneye Orekhovo",
    "gn:country_code":"RU",
    "gn:dem":147,
    "gn:feature_class":"P",
    "gn:feature_code":"PPL",
    "gn:name":"Nizhneye Orekhovo",
    "gn:population":0,
    "gn:timezone":"Europe/Moscow",
    "iso:country":"RU",
    "name:rus_x_preferred":[
        "\u041d\u0438\u0436\u043d\u0435\u0435 \u041e\u0440\u0435\u0445\u043e\u0432\u043e"
    ],
    "wof:name":"Nizhneye Orekhovo",
    "wof:placetype":"locality"
},
  "geometry": {"coordinates":[39.77738,43.70696],"type":"Point"}
}