{
  "type": "Feature",
  "properties": {
    "gn:admin1_code":"52",
    "gn:asciiname":"Staroye Yablonovo",
    "gn:country_code":"RU",
    "gn:dem":92,
    "gn:feature_class":"P",
    "gn:feature_code":"PPL",
    "gn:name":"Staroye Yablonovo",
    "gn:population":0,
    "gn:timezone":"Europe/Moscow",
    "iso:country":"RU",
    "name:rus_x_preferred":[
        "\u0421\u0442\u0430\u0440\u043e\u0435 \u042f\u0431\u043b\u043e\u043d\u043e\u0432\u043e"
    ],
    "name:und_x_variant":[
        "\u0421\u0442\u0430\u0440\u043e\u0435 \u042f\u0431\u043b\u043e\u043d\u043e\u0432\u043e"
    ],
    "wof:name":"Staroye Yablonovo",
    "wof:placetype":"locality"
},
  "geometry": {"coordinates":[30.63333,57.48333],"type":"Point"}
}