{
  "type": "Feature",
  "properties": {
    "gn:admin1_code":"37",
    "gn:asciiname":"Nikola",
    "gn:country_code":"RU",
    "gn:dem":168,
    "gn:feature_class":"P",
    "gn:feature_code":"PPL",
    "gn:name":"Nikola",
    "gn:population":0,
    "gn:timezone":"Europe/Moscow",
    "iso:country":"RU",
    "name:bul_x_preferred":[
        "\u041d\u0438\u043a\u043e\u043b\u0430"
    ],
    "name:ces_x_preferred":[
        "Nikola"
    ],
    "name:deu_x_preferred":[
        "Nikola"
    ],
    "name:eng_x_preferred":[
        "Nikola"
    ],
    "name:hrv_x_preferred":[
        "Nikola"
    ],
    "name:lav_x_preferred":[
        "Nikola"
    ],
    "name:nor_x_preferred":[
        "Nikola"
    ],
    "name:pol_x_preferred":[
        "Nikola"
    ],
    "name:rus_x_preferred":[
        "\u041d\u0438\u043a\u043e\u043b\u0430"
    ],
    "name:slk_x_preferred":[
        "Nikola"
    ],
    "name:slv_x_preferred":[
        "Nikola"
    ],
    "name:srp_x_preferred":[
        "\u041d\u0438\u043a\u043e\u043b\u0430"
    ],
    "name:swe_x_preferred":[
        "Nikola"
    ],
    "name:und_x_variant":[
        "Nikol\u2019skoye",
        "\u041d\u0438\u043a\u043e\u043b\u0430",
        "Nikola"
    ],
    "wof:name":"Nikola",
    "wof:placetype":"locality"
},
  "geometry": {"coordinates":[44.91985,58.86245],"type":"Point"}
}