{
  "type": "Feature",
  "properties": {
    "gn:admin1_code":"25",
    "gn:asciiname":"Yamshino",
    "gn:country_code":"RU",
    "gn:dem":233,
    "gn:feature_class":"P",
    "gn:feature_code":"PPL",
    "gn:name":"Yamshino",
    "gn:population":0,
    "gn:timezone":"Europe/Moscow",
    "iso:country":"RU",
    "wof:name":"Yamshino",
    "wof:placetype":"locality"
},
  "geometry": {"coordinates":[35.57889,54.08389],"type":"Point"}
}