{
  "type": "Feature",
  "properties": {
    "gn:admin1_code":"28",
    "gn:asciiname":"Kimovaara",
    "gn:country_code":"RU",
    "gn:dem":165,
    "gn:feature_class":"P",
    "gn:feature_code":"PPL",
    "gn:name":"Kimovaara",
    "gn:population":0,
    "gn:timezone":"Europe/Moscow",
    "iso:country":"RU",
    "name:eng_x_preferred":[
        "Kimovaara"
    ],
    "name:nor_x_preferred":[
        "Kimovaara"
    ],
    "name:rus_x_preferred":[
        "\u041a\u0438\u043c\u043e\u0432\u0430\u0430\u0440\u0430"
    ],
    "name:und_x_variant":[
        "Kimovary",
        "Kiimaanvaara",
        "\u041a\u0438\u043c\u043e\u0432\u0430\u0430\u0440\u0430",
        "Kimovaara"
    ],
    "wof:name":"Kimovaara",
    "wof:placetype":"locality"
},
  "geometry": {"coordinates":[31.04246,63.64281],"type":"Point"}
}