{
  "type": "Feature",
  "properties": {
    "gn:admin1_code":"80",
    "gn:asciiname":"Udmurt-Syugail",
    "gn:country_code":"RU",
    "gn:dem":182,
    "gn:feature_class":"P",
    "gn:feature_code":"PPL",
    "gn:name":"Udmurt-Syugail",
    "gn:population":0,
    "gn:timezone":"Europe/Samara",
    "iso:country":"RU",
    "name:und_x_variant":[
        "Syugail Udmurtskiy",
        "Udmurtskiy Syugail",
        "Udmurt-Syugail"
    ],
    "wof:name":"Udmurt-Syugail",
    "wof:placetype":"locality"
},
  "geometry": {"coordinates":[52.17192,56.41353],"type":"Point"}
}