{
  "type": "Feature",
  "properties": {
    "gn:admin1_code":"17.0",
    "gn:asciiname":"Gubechaul",
    "gn:country_code":"RU",
    "gn:dem":-22,
    "gn:feature_class":"P",
    "gn:feature_code":"PPL",
    "gn:name":"Gubechaul",
    "gn:population":0,
    "gn:timezone":"Europe/Moscow",
    "iso:country":"RU",
    "name:rus_x_preferred":[
        "\u0413\u0443\u0431\u0435\u0447\u0430\u0443\u043b"
    ],
    "wof:name":"Gubechaul",
    "wof:placetype":"locality"
},
  "geometry": {"coordinates":[47.36183,43.41424],"type":"Point"}
}