{
  "type": "Feature",
  "properties": {
    "gn:admin1_code":"69",
    "gn:asciiname":"Staroye Syrokoren'ye",
    "gn:country_code":"RU",
    "gn:dem":187,
    "gn:feature_class":"P",
    "gn:feature_code":"PPL",
    "gn:name":"Staroye Syrokoren\u2019ye",
    "gn:population":0,
    "gn:timezone":"Europe/Moscow",
    "iso:country":"RU",
    "name:rus_x_preferred":[
        "\u0421\u0442\u0430\u0440\u043e\u0435 \u0421\u044b\u0440\u043e\u043a\u043e\u0440\u0435\u043d\u044c\u0435"
    ],
    "name:und_x_variant":[
        "Syrokoren\u2019ye",
        "Sorokoren\u2019ye",
        "Staroye Syrokoren\u2019ye"
    ],
    "wof:name":"Staroye Syrokoren'ye",
    "wof:placetype":"locality"
},
  "geometry": {"coordinates":[33.36755,54.16206],"type":"Point"}
}