{
  "type": "Feature",
  "properties": {
    "gn:admin1_code":"33.0",
    "gn:asciiname":"Bachikha",
    "gn:country_code":"RU",
    "gn:dem":138,
    "gn:feature_class":"P",
    "gn:feature_code":"PPL",
    "gn:name":"Bachikha",
    "gn:population":0,
    "gn:timezone":"Europe/Kirov",
    "iso:country":"RU",
    "name:nor_x_preferred":[
        "Batsjikha"
    ],
    "name:rus_x_preferred":[
        "\u0411\u0430\u0447\u0438\u0445\u0430"
    ],
    "name:und_x_variant":[
        "Bochikhi",
        "Bochiki",
        "Bachikha"
    ],
    "wof:name":"Bachikha",
    "wof:placetype":"locality"
},
  "geometry": {"coordinates":[49.54865,58.85441],"type":"Point"}
}