{
  "type": "Feature",
  "properties": {
    "gn:admin1_code":"20",
    "gn:asciiname":"Kukuy",
    "gn:cc2":"RU",
    "gn:country_code":"RU",
    "gn:dem":544,
    "gn:feature_class":"P",
    "gn:feature_code":"PPL",
    "gn:name":"Kukuy",
    "gn:population":0,
    "gn:timezone":"Asia/Irkutsk",
    "iso:country":"RU",
    "name:rus_x_preferred":[
        "\u041a\u0443\u043a\u0443\u0439"
    ],
    "name:und_x_variant":[
        "Rukuy",
        "Nukuy",
        "Kukuy",
        "\u041a\u0443\u043a\u0443\u0439"
    ],
    "wof:name":"Kukuy",
    "wof:placetype":"locality"
},
  "geometry": {"coordinates":[106.31139,53.87361],"type":"Point"}
}