{
  "type": "Feature",
  "properties": {
    "gn:admin1_code":"24",
    "gn:asciiname":"Vinogradnoye",
    "gn:country_code":"RU",
    "gn:dem":81,
    "gn:feature_class":"P",
    "gn:feature_code":"PPL",
    "gn:name":"Vinogradnoye",
    "gn:population":0,
    "gn:timezone":"Europe/Moscow",
    "iso:country":"RU",
    "name:eng_x_preferred":[
        "Vinogradnoye"
    ],
    "name:nor_x_preferred":[
        "Vinogradnoje"
    ],
    "name:rus_x_preferred":[
        "\u0412\u0438\u043d\u043e\u0433\u0440\u0430\u0434\u043d\u043e\u0435"
    ],
    "name:und_x_variant":[
        "Shenterlo",
        "Vinogradnyy",
        "Shin-Terl",
        "\u0412\u0438\u043d\u043e\u0433\u0440\u0430\u0434\u043d\u043e\u0435",
        "Vinogradnoye"
    ],
    "wof:name":"Vinogradnoye",
    "wof:placetype":"locality"
},
  "geometry": {"coordinates":[41.96896,46.22009],"type":"Point"}
}