{
  "type": "Feature",
  "properties": {
    "gn:admin1_code":"90",
    "gn:asciiname":"Yelevo",
    "gn:country_code":"RU",
    "gn:dem":182,
    "gn:feature_class":"P",
    "gn:feature_code":"PPL",
    "gn:name":"Yelevo",
    "gn:population":0,
    "gn:timezone":"Asia/Yekaterinburg",
    "iso:country":"RU",
    "name:che_x_preferred":[
        "\u0415\u043b\u0435\u0432\u043e"
    ],
    "name:eng_x_preferred":[
        "Yelevo"
    ],
    "name:nor_x_preferred":[
        "Jelevo"
    ],
    "name:rus_x_preferred":[
        "\u0415\u043b\u0435\u0432\u043e"
    ],
    "name:und_x_variant":[
        "Yeleva",
        "Yelevo"
    ],
    "wof:name":"Yelevo",
    "wof:placetype":"locality"
},
  "geometry": {"coordinates":[54.37422,60.21864],"type":"Point"}
}