{
  "type": "Feature",
  "properties": {
    "gn:admin1_code":"45",
    "gn:asciiname":"Verkhniy Kugener",
    "gn:country_code":"RU",
    "gn:dem":164,
    "gn:feature_class":"P",
    "gn:feature_code":"PPL",
    "gn:name":"Verkhniy Kugener",
    "gn:population":0,
    "gn:timezone":"Europe/Moscow",
    "iso:country":"RU",
    "name:rus_x_preferred":[
        "\u0412\u0435\u0440\u0445\u043d\u0438\u0439 \u041a\u0443\u0433\u0435\u043d\u0435\u0440"
    ],
    "wof:name":"Verkhniy Kugener",
    "wof:placetype":"locality"
},
  "geometry": {"coordinates":[49.19639,56.89],"type":"Point"}
}