{
  "type": "Feature",
  "properties": {
    "gn:admin1_code":"88",
    "gn:asciiname":"Reutovo",
    "gn:country_code":"RU",
    "gn:dem":140,
    "gn:feature_class":"P",
    "gn:feature_code":"PPL",
    "gn:name":"Reutovo",
    "gn:population":0,
    "gn:timezone":"Europe/Moscow",
    "iso:country":"RU",
    "name:rus_x_preferred":[
        "\u0420\u0435\u0443\u0442\u043e\u0432\u043e"
    ],
    "name:und_x_variant":[
        "\u0420\u0435\u0443\u0442\u043e\u0432\u043e"
    ],
    "wof:name":"Reutovo",
    "wof:placetype":"locality"
},
  "geometry": {"coordinates":[37.7763,57.8671],"type":"Point"}
}