{
  "type": "Feature",
  "properties": {
    "gn:admin1_code":"71",
    "gn:asciiname":"Ayatskoye",
    "gn:country_code":"RU",
    "gn:dem":214,
    "gn:feature_class":"P",
    "gn:feature_code":"PPL",
    "gn:name":"Ayatskoye",
    "gn:population":0,
    "gn:timezone":"Asia/Yekaterinburg",
    "iso:country":"RU",
    "name:eng_x_preferred":[
        "Ayatskoye"
    ],
    "name:nor_x_preferred":[
        "Ajatskoje"
    ],
    "name:rus_x_preferred":[
        "\u0410\u044f\u0442\u0441\u043a\u043e\u0435"
    ],
    "name:und_x_variant":[
        "\u0410\u044f\u0442\u0441\u043a\u043e\u0435",
        "Ayatskoye"
    ],
    "wof:name":"Ayatskoye",
    "wof:placetype":"locality"
},
  "geometry": {"coordinates":[60.69448000000001,57.41278000000001],"type":"Point"}
}