{
  "type": "Feature",
  "properties": {
    "gn:admin1_code":"54",
    "gn:asciiname":"Fadino",
    "gn:country_code":"RU",
    "gn:dem":88,
    "gn:feature_class":"P",
    "gn:feature_code":"PPL",
    "gn:name":"Fadino",
    "gn:population":0,
    "gn:timezone":"Asia/Omsk",
    "iso:country":"RU",
    "name:rus_x_preferred":[
        "\u0424\u0430\u0434\u0438\u043d\u043e"
    ],
    "wof:name":"Fadino",
    "wof:placetype":"locality"
},
  "geometry": {"coordinates":[73.34096,54.7851],"type":"Point"}
}