{
  "type": "Feature",
  "properties": {
    "gn:admin1_code":"40",
    "gn:asciiname":"Korchazhka",
    "gn:country_code":"RU",
    "gn:dem":99,
    "gn:feature_class":"P",
    "gn:feature_code":"PPL",
    "gn:name":"Korchazhka",
    "gn:population":0,
    "gn:timezone":"Asia/Yekaterinburg",
    "iso:country":"RU",
    "name:eng_x_preferred":[
        "Korchazhka"
    ],
    "name:nor_x_preferred":[
        "Kortsjazjka"
    ],
    "name:rus_x_preferred":[
        "\u041a\u043e\u0440\u0447\u0430\u0436\u043a\u0430"
    ],
    "name:und_x_variant":[
        "\u041a\u043e\u0440\u0447\u0430\u0436\u043a\u0430",
        "Korchazhka"
    ],
    "wof:name":"Korchazhka",
    "wof:placetype":"locality"
},
  "geometry": {"coordinates":[63.72667,55.50972],"type":"Point"}
}