{
  "type": "Feature",
  "properties": {
    "gn:admin1_code":"8",
    "gn:asciiname":"Stolyarovka",
    "gn:country_code":"RU",
    "gn:dem":179,
    "gn:feature_class":"P",
    "gn:feature_code":"PPL",
    "gn:name":"Stolyarovka",
    "gn:population":0,
    "gn:timezone":"Asia/Yekaterinburg",
    "iso:country":"RU",
    "name:rus_x_preferred":[
        "\u0421\u0442\u043e\u043b\u044f\u0440\u043e\u0432\u043a\u0430"
    ],
    "wof:name":"Stolyarovka",
    "wof:placetype":"locality"
},
  "geometry": {"coordinates":[55.8913,53.2961],"type":"Point"}
}