{
  "type": "Feature",
  "properties": {
    "gn:admin1_code":"8",
    "gn:asciiname":"Tatyr-Uzyak",
    "gn:country_code":"RU",
    "gn:dem":307,
    "gn:feature_class":"P",
    "gn:feature_code":"PPL",
    "gn:name":"Tatyr-Uzyak",
    "gn:population":0,
    "gn:timezone":"Asia/Yekaterinburg",
    "iso:country":"RU",
    "wof:name":"Tatyr-Uzyak",
    "wof:placetype":"locality"
},
  "geometry": {"coordinates":[58.20667,51.86917],"type":"Point"}
}