{
  "type": "Feature",
  "properties": {
    "gn:admin1_code":"57",
    "gn:asciiname":"Tatarsko-Nikol'skoye",
    "gn:country_code":"RU",
    "gn:dem":164,
    "gn:feature_class":"P",
    "gn:feature_code":"PPL",
    "gn:name":"Tatarsko-Nikol\u2019skoye",
    "gn:population":0,
    "gn:timezone":"Europe/Moscow",
    "iso:country":"RU",
    "name:und_x_variant":[
        "Nikol\u2019skoye",
        "Tataro-Nikol\u2019skoye",
        "Nikol\u2019skoye Tatarskoye",
        "Tatarsko-Nikol\u2019skoye"
    ],
    "wof:name":"Tatarsko-Nikol'skoye",
    "wof:placetype":"locality"
},
  "geometry": {"coordinates":[43.02561,53.44663000000001],"type":"Point"}
}