{
  "type": "Feature",
  "properties": {
    "gn:admin1_code":"88",
    "gn:asciiname":"Maleyevo",
    "gn:country_code":"RU",
    "gn:dem":138,
    "gn:feature_class":"P",
    "gn:feature_code":"PPL",
    "gn:name":"Maleyevo",
    "gn:population":0,
    "gn:timezone":"Europe/Moscow",
    "iso:country":"RU",
    "name:rus_x_preferred":[
        "\u041c\u0430\u043b\u0435\u0435\u0432\u043e"
    ],
    "name:und_x_variant":[
        "\u041c\u0430\u043b\u0435\u0435\u0432\u043e",
        "Moleyevo"
    ],
    "wof:name":"Maleyevo",
    "wof:placetype":"locality"
},
  "geometry": {"coordinates":[37.9731,58.0046],"type":"Point"}
}