{
  "type": "Feature",
  "properties": {
    "gn:admin1_code":"65.0",
    "gn:asciiname":"Studenyy",
    "gn:country_code":"RU",
    "gn:dem":38,
    "gn:feature_class":"P",
    "gn:feature_code":"PPL",
    "gn:name":"Stud\u00ebnyy",
    "gn:population":0,
    "gn:timezone":"Europe/Samara",
    "iso:country":"RU",
    "name:rus_x_preferred":[
        "\u0421\u0442\u0443\u0434\u0451\u043d\u044b\u0439"
    ],
    "name:und_x_variant":[
        "Stud\u00ebnyy"
    ],
    "wof:name":"Studenyy",
    "wof:placetype":"locality"
},
  "geometry": {"coordinates":[50.6057,53.64504],"type":"Point"}
}