{
  "type": "Feature",
  "properties": {
    "gn:admin1_code":"17",
    "gn:admin2_code":"Shamil'skiy Rayon",
    "gn:asciiname":"Urib",
    "gn:country_code":"RU",
    "gn:dem":1581,
    "gn:feature_class":"P",
    "gn:feature_code":"PPL",
    "gn:name":"Urib",
    "gn:population":0,
    "gn:timezone":"Europe/Moscow",
    "iso:country":"RU",
    "name:ara_x_preferred":[
        "\u0639\u0631\u064a\u0628"
    ],
    "name:ava_x_preferred":[
        "\u0413I\u0443\u0440\u0438\u0431"
    ],
    "name:rus_x_preferred":[
        "\u0423\u0440\u0438\u0431"
    ],
    "wof:name":"Urib",
    "wof:placetype":"locality"
},
  "geometry": {"coordinates":[46.67371,42.45713],"type":"Point"}
}