{
  "type": "Feature",
  "properties": {
    "gn:admin1_code":"57",
    "gn:asciiname":"Zalesnyy",
    "gn:cc2":"RU",
    "gn:country_code":"RU",
    "gn:dem":209,
    "gn:feature_class":"P",
    "gn:feature_code":"PPL",
    "gn:name":"Zalesnyy",
    "gn:population":0,
    "gn:timezone":"Europe/Moscow",
    "iso:country":"RU",
    "name:und_x_variant":[
        "Zalesny",
        "Zalesnyy"
    ],
    "wof:name":"Zalesnyy",
    "wof:placetype":"locality"
},
  "geometry": {"coordinates":[43.26861,53.46833],"type":"Point"}
}