{
  "type": "Feature",
  "properties": {
    "gn:admin1_code":"31",
    "gn:asciiname":"Neozhidannyy",
    "gn:country_code":"RU",
    "gn:dem":512,
    "gn:feature_class":"P",
    "gn:feature_code":"PPL",
    "gn:name":"Neozhidannyy",
    "gn:population":0,
    "gn:timezone":"Asia/Krasnoyarsk",
    "iso:country":"RU",
    "name:rus_x_preferred":[
        "\u041d\u0435\u043e\u0436\u0438\u0434\u0430\u043d\u043d\u044b\u0439"
    ],
    "name:und_x_variant":[
        "\u041d\u0435\u043e\u0436\u0438\u0434\u0430\u043d\u043d\u044b\u0439"
    ],
    "wof:name":"Neozhidannyy",
    "wof:placetype":"locality"
},
  "geometry": {"coordinates":[89.07603,53.34735],"type":"Point"}
}