{
  "type": "Feature",
  "properties": {
    "gn:admin1_code":"53",
    "gn:asciiname":"Mokhovka",
    "gn:country_code":"RU",
    "gn:dem":310,
    "gn:feature_class":"P",
    "gn:feature_code":"PPL",
    "gn:name":"Mokhovka",
    "gn:population":0,
    "gn:timezone":"Asia/Novosibirsk",
    "iso:country":"RU",
    "name:rus_x_preferred":[
        "\u041c\u043e\u0445\u043e\u0432\u043a\u0430"
    ],
    "name:und_x_variant":[
        "\u041c\u043e\u0445\u043e\u0432\u043a\u0430"
    ],
    "wof:name":"Mokhovka",
    "wof:placetype":"locality"
},
  "geometry": {"coordinates":[84.59999999999999,54.26667],"type":"Point"}
}