{
  "type": "Feature",
  "properties": {
    "gn:admin1_code":"71",
    "gn:asciiname":"Makhnevo",
    "gn:country_code":"RU",
    "gn:dem":83,
    "gn:feature_class":"P",
    "gn:feature_code":"PPL",
    "gn:name":"Makhn\u00ebvo",
    "gn:population":0,
    "gn:timezone":"Asia/Yekaterinburg",
    "iso:country":"RU",
    "name:che_x_preferred":[
        "\u041c\u0430\u0445\u043d\u0451\u0432\u043e"
    ],
    "name:deu_x_preferred":[
        "Machnjowo"
    ],
    "name:eng_x_preferred":[
        "Makhnyovo"
    ],
    "name:nor_x_preferred":[
        "Makhnevo"
    ],
    "name:pol_x_preferred":[
        "Machniowo"
    ],
    "name:rus_x_preferred":[
        "\u041c\u0430\u0445\u043d\u0435\u0432\u043e"
    ],
    "name:rus_x_variant":[
        "\u041c\u0430\u0445\u043d\u0451\u0432\u043e"
    ],
    "name:swe_x_preferred":[
        "Machnjovo"
    ],
    "name:tat_x_preferred":[
        "\u041c\u0430\u0445\u043d\u0451\u0432\u043e"
    ],
    "name:tgk_x_preferred":[
        "\u041c\u0430\u0445\u043d\u0435\u0432\u043e"
    ],
    "name:und_x_variant":[
        "Makhneva",
        "Makhn\u00ebvo",
        "\u041c\u0430\u0445\u043d\u0451\u0432\u043e"
    ],
    "wof:name":"Makhnevo",
    "wof:placetype":"locality"
},
  "geometry": {"coordinates":[61.70463,58.45081999999999],"type":"Point"}
}