{
  "type": "Feature",
  "properties": {
    "gn:admin1_code":"10",
    "gn:asciiname":"Tureyevka",
    "gn:country_code":"RU",
    "gn:dem":194,
    "gn:feature_class":"P",
    "gn:feature_code":"PPL",
    "gn:name":"Tureyevka",
    "gn:population":0,
    "gn:timezone":"Europe/Moscow",
    "iso:country":"RU",
    "name:rus_x_preferred":[
        "\u0422\u0443\u0440\u0435\u0435\u0432\u043a\u0430"
    ],
    "name:und_x_variant":[
        "Tureyskiye",
        "Tureyevka"
    ],
    "wof:name":"Tureyevka",
    "wof:placetype":"locality"
},
  "geometry": {"coordinates":[33.52494,53.49729],"type":"Point"}
}