{
  "type": "Feature",
  "properties": {
    "gn:admin1_code":"75",
    "gn:asciiname":"Nelyubino",
    "gn:country_code":"RU",
    "gn:dem":124,
    "gn:feature_class":"P",
    "gn:feature_code":"PPL",
    "gn:name":"Nelyubino",
    "gn:population":0,
    "gn:timezone":"Asia/Tomsk",
    "iso:country":"RU",
    "name:eng_x_preferred":[
        "Nelyubino"
    ],
    "name:nor_x_preferred":[
        "Neljubino"
    ],
    "name:rus_x_preferred":[
        "\u041d\u0435\u043b\u044e\u0431\u0438\u043d\u043e"
    ],
    "name:und_x_variant":[
        "Nelyubiko",
        "Nelyubino"
    ],
    "wof:name":"Nelyubino",
    "wof:placetype":"locality"
},
  "geometry": {"coordinates":[84.5468,56.56383],"type":"Point"}
}