{
  "type": "Feature",
  "properties": {
    "gn:admin1_code":"8",
    "gn:asciiname":"Chernolesovskiy",
    "gn:country_code":"RU",
    "gn:dem":127,
    "gn:feature_class":"P",
    "gn:feature_code":"PPL",
    "gn:name":"Chernolesovskiy",
    "gn:population":0,
    "gn:timezone":"Asia/Yekaterinburg",
    "iso:country":"RU",
    "name:rus_x_preferred":[
        "\u0427\u0435\u0440\u043d\u043e\u043b\u0435\u0441\u043e\u0432\u0441\u043a\u0438\u0439"
    ],
    "name:und_x_variant":[
        "\u0427\u0435\u0440\u043d\u043e\u043b\u0435\u0441\u043e\u0432\u0441\u043a\u0438\u0439"
    ],
    "wof:name":"Chernolesovskiy",
    "wof:placetype":"locality"
},
  "geometry": {"coordinates":[55.81444000000001,54.86388],"type":"Point"}
}