{
  "type": "Feature",
  "properties": {
    "gn:admin1_code":"33",
    "gn:asciiname":"Kokorikha",
    "gn:country_code":"RU",
    "gn:dem":185,
    "gn:feature_class":"P",
    "gn:feature_code":"PPL",
    "gn:name":"Kokorikha",
    "gn:population":0,
    "gn:timezone":"Europe/Kirov",
    "iso:country":"RU",
    "name:eng_x_preferred":[
        "Kokorikha"
    ],
    "name:nor_x_preferred":[
        "Kokorikha"
    ],
    "name:rus_x_preferred":[
        "\u041a\u043e\u043a\u043e\u0440\u0438\u0445\u0430"
    ],
    "name:und_x_variant":[
        "\u041a\u043e\u043a\u043e\u0440\u0438\u0445\u0430",
        "Kokorikha"
    ],
    "wof:name":"Kokorikha",
    "wof:placetype":"locality"
},
  "geometry": {"coordinates":[49.95435,58.14092],"type":"Point"}
}