{
  "type": "Feature",
  "properties": {
    "gn:admin1_code":"40",
    "gn:asciiname":"Ryasovo",
    "gn:country_code":"RU",
    "gn:dem":91,
    "gn:feature_class":"P",
    "gn:feature_code":"PPL",
    "gn:name":"Ryasovo",
    "gn:population":0,
    "gn:timezone":"Asia/Yekaterinburg",
    "iso:country":"RU",
    "name:rus_x_preferred":[
        "\u0420\u044f\u0441\u043e\u0432\u043e"
    ],
    "wof:name":"Ryasovo",
    "wof:placetype":"locality"
},
  "geometry": {"coordinates":[64.74110999999999,54.67389],"type":"Point"}
}