{
  "type": "Feature",
  "properties": {
    "gn:admin1_code":"61",
    "gn:asciiname":"Kuryachiy",
    "gn:country_code":"RU",
    "gn:dem":118,
    "gn:feature_class":"P",
    "gn:feature_code":"PPL",
    "gn:name":"Kuryachiy",
    "gn:population":0,
    "gn:timezone":"Europe/Moscow",
    "iso:country":"RU",
    "name:eng_x_preferred":[
        "Kuryachiy"
    ],
    "name:nor_x_preferred":[
        "Kurjatsjij"
    ],
    "name:rus_x_preferred":[
        "\u041a\u0443\u0440\u044f\u0447\u0438\u0439"
    ],
    "name:und_x_variant":[
        "\u041a\u0443\u0440\u044f\u0447\u0438\u0439",
        "Kuryachiy"
    ],
    "wof:name":"Kuryachiy",
    "wof:placetype":"locality"
},
  "geometry": {"coordinates":[42.8155,46.8014],"type":"Point"}
}