{
  "type": "Feature",
  "properties": {
    "gn:admin1_code":"10.0",
    "gn:asciiname":"Sovkhoz",
    "gn:country_code":"RU",
    "gn:dem":173,
    "gn:feature_class":"P",
    "gn:feature_code":"PPL",
    "gn:name":"Sovkhoz",
    "gn:population":0,
    "gn:timezone":"Europe/Moscow",
    "iso:country":"RU",
    "name:bak_x_preferred":[
        "\u0421\u043e\u0432\u0445\u043e\u0437"
    ],
    "name:bel_x_preferred":[
        "\u0421\u0430\u045e\u0433\u0430\u0441"
    ],
    "name:bos_x_preferred":[
        "Sovhoz"
    ],
    "name:bul_x_preferred":[
        "\u0421\u043e\u0432\u0445\u043e\u0437"
    ],
    "name:cat_x_preferred":[
        "Sovkhoz"
    ],
    "name:ces_x_preferred":[
        "Sovchoz"
    ],
    "name:deu_x_preferred":[
        "Sowchos"
    ],
    "name:epo_x_preferred":[
        "Sov\u0125ozo"
    ],
    "name:est_x_preferred":[
        "Sovhoos"
    ],
    "name:eus_x_preferred":[
        "Sovkhoz"
    ],
    "name:fas_x_preferred":[
        "\u0633\u0648\u062e\u0648\u0632"
    ],
    "name:fin_x_preferred":[
        "Sovhoosi"
    ],
    "name:fra_x_preferred":[
        "Sovkhoze"
    ],
    "name:heb_x_preferred":[
        "\u05e1\u05d5\u05d1\u05d7\u05d5\u05d6"
    ],
    "name:hye_x_preferred":[
        "\u054d\u0578\u057e\u056d\u0578\u0566"
    ],
    "name:ind_x_preferred":[
        "Sovkhoz"
    ],
    "name:ita_x_preferred":[
        "Sovchoz"
    ],
    "name:jpn_x_preferred":[
        "\u30bd\u30d5\u30db\u30fc\u30ba"
    ],
    "name:kaz_x_preferred":[
        "\u0421\u043e\u0432\u0445\u043e\u0437"
    ],
    "name:kor_x_preferred":[
        "\uc19d\ud638\uc2a4"
    ],
    "name:lav_x_preferred":[
        "Padomju saimniec\u012bba"
    ],
    "name:lit_x_preferred":[
        "Tarybinis \u016bkis"
    ],
    "name:nld_x_preferred":[
        "Sovchoz"
    ],
    "name:oci_x_preferred":[
        "Sovkhoz"
    ],
    "name:pol_x_preferred":[
        "Sowchoz"
    ],
    "name:por_x_preferred":[
        "Sovkhoz"
    ],
    "name:ron_x_preferred":[
        "Sovhoz"
    ],
    "name:rus_x_preferred":[
        "\u0421\u043e\u0432\u0445\u043e\u0437"
    ],
    "name:spa_x_preferred":[
        "Sovj\u00f3s"
    ],
    "name:srp_x_preferred":[
        "\u0421\u043e\u0432\u0445\u043e\u0437"
    ],
    "name:swe_x_preferred":[
        "Sovchos"
    ],
    "name:tat_x_preferred":[
        "\u0421\u043e\u0432\u0445\u043e\u0437"
    ],
    "name:tgk_x_preferred":[
        "\u0421\u043e\u0432\u0445\u043e\u0437"
    ],
    "name:tur_x_preferred":[
        "Sovhoz"
    ],
    "name:ukr_x_preferred":[
        "\u0420\u0430\u0434\u0433\u043e\u0441\u043f"
    ],
    "name:uzb_x_preferred":[
        "Sovxoz"
    ],
    "name:wln_x_preferred":[
        "Sovxh\u00f4ze"
    ],
    "name:zho_x_preferred":[
        "\u570b\u71df\u8fb2\u5834"
    ],
    "wof:name":"Sovkhoz",
    "wof:placetype":"locality"
},
  "geometry": {"coordinates":[33.8367,53.7782],"type":"Point"}
}