{
  "type": "Feature",
  "properties": {
    "gn:admin1_code":"10.0",
    "gn:asciiname":"Sovkhoz",
    "gn:country_code":"RU",
    "gn:dem":173,
    "gn:feature_class":"P",
    "gn:feature_code":"PPL",
    "gn:name":"Sovkhoz",
    "gn:population":0,
    "gn:timezone":"Europe/Moscow",
    "iso:country":"RU",
    "name:rus_x_preferred":[
        "\u0421\u043e\u0432\u0445\u043e\u0437"
    ],
    "wof:name":"Sovkhoz",
    "wof:placetype":"locality"
},
  "geometry": {"coordinates":[33.8367,53.7782],"type":"Point"}
}