{
  "type": "Feature",
  "properties": {
    "gn:admin1_code":"47",
    "gn:asciiname":"Zadniy Dvor",
    "gn:country_code":"RU",
    "gn:dem":140,
    "gn:feature_class":"P",
    "gn:feature_code":"PPL",
    "gn:name":"Zadniy Dvor",
    "gn:population":0,
    "gn:timezone":"Europe/Moscow",
    "iso:country":"RU",
    "name:rus_x_preferred":[
        "\u0417\u0430\u0434\u043d\u0438\u0439 \u0414\u0432\u043e\u0440"
    ],
    "wof:name":"Zadniy Dvor",
    "wof:placetype":"locality"
},
  "geometry": {"coordinates":[36.8917,56.5505],"type":"Point"}
}