{
  "type": "Feature",
  "properties": {
    "gn:admin1_code":"41.0",
    "gn:asciiname":"Ovechiy Verkh",
    "gn:country_code":"RU",
    "gn:dem":182,
    "gn:feature_class":"P",
    "gn:feature_code":"PPL",
    "gn:name":"Ovechiy Verkh",
    "gn:population":0,
    "gn:timezone":"Europe/Moscow",
    "iso:country":"RU",
    "wof:name":"Ovechiy Verkh",
    "wof:placetype":"locality"
},
  "geometry": {"coordinates":[36.70917,51.61917],"type":"Point"}
}