{
  "type": "Feature",
  "properties": {
    "gn:admin1_code":"60",
    "gn:asciiname":"Lopukhi",
    "gn:country_code":"RU",
    "gn:dem":147,
    "gn:feature_class":"P",
    "gn:feature_code":"PPL",
    "gn:name":"Lopukhi",
    "gn:population":0,
    "gn:timezone":"Europe/Moscow",
    "iso:country":"RU",
    "name:rus_x_preferred":[
        "\u041b\u043e\u043fy\u0445\u0438"
    ],
    "wof:name":"Lopukhi",
    "wof:placetype":"locality"
},
  "geometry": {"coordinates":[28.741,56.2919],"type":"Point"}
}