{
  "type": "Feature",
  "properties": {
    "gn:admin1_code":"73",
    "gn:asciiname":"Maltabarovo",
    "gn:country_code":"RU",
    "gn:dem":112,
    "gn:feature_class":"P",
    "gn:feature_code":"PPL",
    "gn:name":"Maltabarovo",
    "gn:population":0,
    "gn:timezone":"Europe/Moscow",
    "iso:country":"RU",
    "name:rus_x_preferred":[
        "\u041c\u0430\u043b\u0442\u0430\u0431\u0430\u0440\u043e\u0432\u043e"
    ],
    "name:und_x_variant":[
        "\u041c\u0430\u043b\u0442\u0430\u0431\u0430\u0440\u043e\u0432\u043e"
    ],
    "wof:name":"Maltabarovo",
    "wof:placetype":"locality"
},
  "geometry": {"coordinates":[52.79176,55.79803],"type":"Point"}
}