{
  "type": "Feature",
  "properties": {
    "gn:admin1_code":"33",
    "gn:asciiname":"Timofeyevskaya",
    "gn:country_code":"RU",
    "gn:dem":223,
    "gn:feature_class":"P",
    "gn:feature_code":"PPL",
    "gn:name":"Timofeyevskaya",
    "gn:population":0,
    "gn:timezone":"Europe/Kirov",
    "iso:country":"RU",
    "wof:name":"Timofeyevskaya",
    "wof:placetype":"locality"
},
  "geometry": {"coordinates":[53.11666999999999,58.96666999999999],"type":"Point"}
}