{
  "type": "Feature",
  "properties": {
    "gn:admin1_code":"62",
    "gn:asciiname":"Mileyka",
    "gn:country_code":"RU",
    "gn:dem":134,
    "gn:feature_class":"P",
    "gn:feature_code":"PPL",
    "gn:name":"Mileyka",
    "gn:population":0,
    "gn:timezone":"Europe/Moscow",
    "iso:country":"RU",
    "name:rus_x_preferred":[
        "\u041c\u0438\u043b\u0435\u0439\u043a\u0430"
    ],
    "wof:name":"Mileyka",
    "wof:placetype":"locality"
},
  "geometry": {"coordinates":[42.3771,54.9119],"type":"Point"}
}