{
  "type": "Feature",
  "properties": {
    "gn:admin1_code":"73",
    "gn:asciiname":"Maksimov Pochinok",
    "gn:country_code":"RU",
    "gn:dem":94,
    "gn:feature_class":"P",
    "gn:feature_code":"PPL",
    "gn:name":"Maksimov Pochinok",
    "gn:population":0,
    "gn:timezone":"Europe/Moscow",
    "iso:country":"RU",
    "name:rus_x_preferred":[
        "\u041c\u0430\u043a\u0441\u0438\u043c\u043e\u0432 \u041f\u043e\u0447\u0438\u043d\u043e\u043a"
    ],
    "wof:name":"Maksimov Pochinok",
    "wof:placetype":"locality"
},
  "geometry": {"coordinates":[51.28898,55.68827],"type":"Point"}
}