{
  "type": "Feature",
  "properties": {
    "gn:admin1_code":"88",
    "gn:asciiname":"Yeremino",
    "gn:country_code":"RU",
    "gn:dem":117,
    "gn:feature_class":"P",
    "gn:feature_code":"PPL",
    "gn:name":"Yer\u00ebmino",
    "gn:population":0,
    "gn:timezone":"Europe/Moscow",
    "iso:country":"RU",
    "name:rus_x_preferred":[
        "\u0415\u0440\u0451\u043c\u0438\u043d\u043e"
    ],
    "name:und_x_variant":[
        "Yer\u00ebmino"
    ],
    "wof:name":"Yeremino",
    "wof:placetype":"locality"
},
  "geometry": {"coordinates":[39.91621,57.87008],"type":"Point"}
}