{
  "type": "Feature",
  "properties": {
    "gn:admin1_code":"60",
    "gn:asciiname":"Platony",
    "gn:country_code":"RU",
    "gn:dem":103,
    "gn:feature_class":"P",
    "gn:feature_code":"PPL",
    "gn:name":"Platony",
    "gn:population":0,
    "gn:timezone":"Europe/Moscow",
    "iso:country":"RU",
    "name:rus_x_preferred":[
        "\u041f\u043b\u0435\u0442\u0435\u043d\u044b"
    ],
    "name:rus_x_variant":[
        "\u041f\u043b\u0430\u0442\u043e\u043d\u044b"
    ],
    "name:und_x_variant":[
        "Plugany",
        "Pleteny",
        "Platony"
    ],
    "wof:name":"Platony",
    "wof:placetype":"locality"
},
  "geometry": {"coordinates":[28.86381,56.67692],"type":"Point"}
}