{
  "type": "Feature",
  "properties": {
    "gn:admin1_code":"85",
    "gn:asciiname":"Kapelino",
    "gn:country_code":"RU",
    "gn:dem":136,
    "gn:feature_class":"P",
    "gn:feature_code":"PPL",
    "gn:name":"Kapelino",
    "gn:population":0,
    "gn:timezone":"Europe/Moscow",
    "iso:country":"RU",
    "name:rus_x_preferred":[
        "\u041a\u0430\u043f\u0435\u043b\u0438\u043d\u043e"
    ],
    "wof:name":"Kapelino",
    "wof:placetype":"locality"
},
  "geometry": {"coordinates":[39.1463,59.9887],"type":"Point"}
}