{
  "type": "Feature",
  "properties": {
    "gn:admin1_code":"85",
    "gn:asciiname":"Lobanovo",
    "gn:country_code":"RU",
    "gn:dem":140,
    "gn:feature_class":"P",
    "gn:feature_code":"PPL",
    "gn:name":"Lobanovo",
    "gn:population":0,
    "gn:timezone":"Europe/Moscow",
    "iso:country":"RU",
    "name:ceb_x_preferred":[
        "Lobanovo"
    ],
    "name:che_x_preferred":[
        "\u041b\u043e\u0431\u0430\u043d\u043e\u0432\u043e"
    ],
    "name:hye_x_preferred":[
        "\u053c\u0578\u0562\u0561\u0576\u0578\u057e\u0578"
    ],
    "name:rus_x_preferred":[
        "\u041b\u043e\u0431\u0430\u043d\u043e\u0432\u043e"
    ],
    "wof:name":"Lobanovo",
    "wof:placetype":"locality"
},
  "geometry": {"coordinates":[39.6338,59.8565],"type":"Point"}
}