{
  "type": "Feature",
  "properties": {
    "gn:admin1_code":"9.0",
    "gn:asciiname":"Yamskaya",
    "gn:country_code":"RU",
    "gn:dem":128,
    "gn:feature_class":"P",
    "gn:feature_code":"PPL",
    "gn:name":"Yamskaya",
    "gn:population":0,
    "gn:timezone":"Europe/Moscow",
    "iso:country":"RU",
    "name:eng_x_preferred":[
        "Yamskaya"
    ],
    "name:nor_x_preferred":[
        "Jamskaja"
    ],
    "name:rus_x_preferred":[
        "\u042f\u043c\u0441\u043a\u0430\u044f"
    ],
    "wof:name":"Yamskaya",
    "wof:placetype":"locality"
},
  "geometry": {"coordinates":[37.88028,51.28194000000001],"type":"Point"}
}