{
  "type": "Feature",
  "properties": {
    "gn:admin1_code":"42.0",
    "gn:admin2_code":"534332",
    "gn:asciiname":"Lomakha",
    "gn:country_code":"RU",
    "gn:dem":116,
    "gn:feature_class":"P",
    "gn:feature_code":"PPL",
    "gn:name":"Lomakha",
    "gn:population":0,
    "gn:timezone":"Europe/Moscow",
    "iso:country":"RU",
    "name:fin_x_preferred":[
        "Lommaha"
    ],
    "name:rus_x_preferred":[
        "\u041b\u043e\u043c\u0430\u0445\u0430"
    ],
    "wof:name":"Lomakha",
    "wof:placetype":"locality"
},
  "geometry": {"coordinates":[29.02834,59.66947],"type":"Point"}
}