{
  "type": "Feature",
  "properties": {
    "gn:admin1_code":"61",
    "gn:asciiname":"Khmyzov",
    "gn:country_code":"RU",
    "gn:dem":93,
    "gn:feature_class":"P",
    "gn:feature_code":"PPL",
    "gn:name":"Khmyzov",
    "gn:population":0,
    "gn:timezone":"Europe/Moscow",
    "iso:country":"RU",
    "name:eng_x_preferred":[
        "Khmyzov"
    ],
    "name:nor_x_preferred":[
        "Khmyzov"
    ],
    "name:rus_x_preferred":[
        "\u0425\u043c\u044b\u0437\u043e\u0432"
    ],
    "name:und_x_variant":[
        "\u0425\u043c\u044b\u0437\u043e\u0432",
        "Khmyzov"
    ],
    "wof:name":"Khmyzov",
    "wof:placetype":"locality"
},
  "geometry": {"coordinates":[40.80089,49.12234],"type":"Point"}
}