{
  "type": "Feature",
  "properties": {
    "gn:admin1_code":"83",
    "gn:asciiname":"Usol'ye",
    "gn:country_code":"RU",
    "gn:dem":94,
    "gn:feature_class":"P",
    "gn:feature_code":"PPL",
    "gn:name":"Usol\u2019ye",
    "gn:population":0,
    "gn:timezone":"Europe/Moscow",
    "iso:country":"RU",
    "name:eng_x_preferred":[
        "Usol'ye"
    ],
    "name:nor_x_preferred":[
        "Usolje"
    ],
    "name:rus_x_preferred":[
        "\u0423\u0441\u043e\u043b\u044c\u0435"
    ],
    "name:und_x_variant":[
        "Usol\u2019ye"
    ],
    "wof:name":"Usol'ye",
    "wof:placetype":"locality"
},
  "geometry": {"coordinates":[41.10394,56.46291],"type":"Point"}
}