{
  "type": "Feature",
  "properties": {
    "gn:admin1_code":"60",
    "gn:asciiname":"Mukharevo",
    "gn:country_code":"RU",
    "gn:dem":94,
    "gn:feature_class":"P",
    "gn:feature_code":"PPL",
    "gn:name":"Mukhar\u00ebvo",
    "gn:population":0,
    "gn:timezone":"Europe/Moscow",
    "iso:country":"RU",
    "name:eng_x_preferred":[
        "Mukhar\u00ebvo"
    ],
    "name:nor_x_preferred":[
        "Mukharevo"
    ],
    "name:rus_x_preferred":[
        "\u041c\u0443\u0445\u0430\u0440\u0435\u0432\u043e"
    ],
    "name:rus_x_variant":[
        "\u041c\u0443\u0445\u0430\u0440\u0451\u0432\u043e"
    ],
    "name:und_x_variant":[
        "Makharevo",
        "Mokharevo"
    ],
    "wof:name":"Mukharevo",
    "wof:placetype":"locality"
},
  "geometry": {"coordinates":[30.40786,57.41255],"type":"Point"}
}