{
  "type": "Feature",
  "properties": {
    "gn:admin1_code":"41.0",
    "gn:asciiname":"Trufanovka",
    "gn:country_code":"RU",
    "gn:dem":163,
    "gn:feature_class":"P",
    "gn:feature_code":"PPL",
    "gn:name":"Trufanovka",
    "gn:population":0,
    "gn:timezone":"Europe/Moscow",
    "iso:country":"RU",
    "name:rus_x_preferred":[
        "\u0422\u0440\u0443\u0444\u0430\u043d\u043e\u0432\u043a\u0430"
    ],
    "wof:name":"Trufanovka",
    "wof:placetype":"locality"
},
  "geometry": {"coordinates":[34.3306,51.6089],"type":"Point"}
}