{
  "type": "Feature",
  "properties": {
    "gn:admin1_code":"65",
    "gn:asciiname":"Pravaya Yelshanka",
    "gn:country_code":"RU",
    "gn:dem":121,
    "gn:feature_class":"P",
    "gn:feature_code":"PPL",
    "gn:name":"Pravaya Yelshanka",
    "gn:population":0,
    "gn:timezone":"Europe/Samara",
    "iso:country":"RU",
    "name:rus_x_preferred":[
        "\u041f\u0440\u0430\u0432\u0430\u044f \u0415\u043b\u0448\u0430\u043d\u043a\u0430"
    ],
    "wof:name":"Pravaya Yelshanka",
    "wof:placetype":"locality"
},
  "geometry": {"coordinates":[50.32872,54.20922],"type":"Point"}
}