{
  "type": "Feature",
  "properties": {
    "gn:admin1_code":"71",
    "gn:asciiname":"Kurort-Samotsvet",
    "gn:country_code":"RU",
    "gn:dem":199,
    "gn:feature_class":"P",
    "gn:feature_code":"PPL",
    "gn:name":"Kurort-Samotsvet",
    "gn:population":0,
    "gn:timezone":"Asia/Yekaterinburg",
    "iso:country":"RU",
    "name:rus_x_preferred":[
        "\u041a\u0443\u0440\u043e\u0440\u0442 \u0421\u0430\u043c\u043e\u0446\u0432\u0435\u0442"
    ],
    "name:und_x_variant":[
        "Samotsvet",
        "Kurort-Samotsvet",
        "\u041a\u0443\u0440\u043e\u0440\u0442 \u0421\u0430\u043c\u043e\u0446\u0432\u0435\u0442"
    ],
    "wof:name":"Kurort-Samotsvet",
    "wof:placetype":"locality"
},
  "geometry": {"coordinates":[61.75883,57.58449],"type":"Point"}
}