{
  "type": "Feature",
  "properties": {
    "gn:admin1_code":"62",
    "gn:asciiname":"Gremyachiy Klyuch",
    "gn:country_code":"RU",
    "gn:dem":135,
    "gn:feature_class":"P",
    "gn:feature_code":"PPL",
    "gn:name":"Gremyachiy Klyuch",
    "gn:population":0,
    "gn:timezone":"Europe/Moscow",
    "iso:country":"RU",
    "name:rus_x_preferred":[
        "\u0413\u0440\u0435\u043c\u044f\u0447\u0438\u0439 \u041a\u043b\u044e\u0447"
    ],
    "wof:name":"Gremyachiy Klyuch",
    "wof:placetype":"locality"
},
  "geometry": {"coordinates":[42.042,54.7202],"type":"Point"}
}