{
  "type": "Feature",
  "properties": {
    "gn:admin1_code":"47",
    "gn:asciiname":"Simakovo",
    "gn:country_code":"RU",
    "gn:dem":244,
    "gn:feature_class":"P",
    "gn:feature_code":"PPL",
    "gn:name":"Simakovo",
    "gn:population":0,
    "gn:timezone":"Europe/Moscow",
    "iso:country":"RU",
    "wof:name":"Simakovo",
    "wof:placetype":"locality"
},
  "geometry": {"coordinates":[35.47027999999999,55.59194],"type":"Point"}
}