{
  "type": "Feature",
  "properties": {
    "gn:admin1_code":"51.0",
    "gn:asciiname":"Berdniki",
    "gn:country_code":"RU",
    "gn:dem":130,
    "gn:feature_class":"P",
    "gn:feature_code":"PPL",
    "gn:name":"Berdniki",
    "gn:population":0,
    "gn:timezone":"Europe/Moscow",
    "iso:country":"RU",
    "name:eng_x_preferred":[
        "Berdniki"
    ],
    "name:nor_x_preferred":[
        "Berdniki"
    ],
    "name:rus_x_preferred":[
        "\u0411\u0435\u0440\u0434\u043d\u0438\u043a\u0438"
    ],
    "name:und_x_variant":[
        "Bol\u2019shiye Berdniki"
    ],
    "wof:name":"Berdniki",
    "wof:placetype":"locality"
},
  "geometry": {"coordinates":[46.52325,57.42162],"type":"Point"}
}