{
  "type": "Feature",
  "properties": {
    "gn:admin1_code":"17",
    "gn:admin2_code":"Tlyaratinskiy Rayon",
    "gn:asciiname":"Shidib",
    "gn:country_code":"RU",
    "gn:dem":1770,
    "gn:feature_class":"P",
    "gn:feature_code":"PPL",
    "gn:name":"Shidib",
    "gn:population":0,
    "gn:timezone":"Europe/Moscow",
    "iso:country":"RU",
    "name:rus_x_preferred":[
        "\u0428\u0438\u0434\u0438\u0431"
    ],
    "wof:name":"Shidib",
    "wof:placetype":"locality"
},
  "geometry": {"coordinates":[46.30157,42.21357],"type":"Point"}
}