{
  "type": "Feature",
  "properties": {
    "gn:admin1_code":"52",
    "gn:asciiname":"Ostsy",
    "gn:country_code":"RU",
    "gn:dem":94,
    "gn:feature_class":"P",
    "gn:feature_code":"PPL",
    "gn:name":"Ostsy",
    "gn:population":0,
    "gn:timezone":"Europe/Moscow",
    "iso:country":"RU",
    "name:rus_x_preferred":[
        "\u041e\u0441\u0446\u044b"
    ],
    "name:und_x_variant":[
        "\u041e\u0441\u0446\u044b"
    ],
    "wof:name":"Ostsy",
    "wof:placetype":"locality"
},
  "geometry": {"coordinates":[31.32194,57.04331],"type":"Point"}
}