{
  "type": "Feature",
  "properties": {
    "gn:admin1_code":"17.0",
    "gn:asciiname":"Gaziya",
    "gn:country_code":"RU",
    "gn:dem":547,
    "gn:feature_class":"P",
    "gn:feature_code":"PPL",
    "gn:name":"Gaziya",
    "gn:population":0,
    "gn:timezone":"Europe/Moscow",
    "iso:country":"RU",
    "name:rus_x_preferred":[
        "\u0413\u0430\u0437\u0438\u044f"
    ],
    "name:und_x_variant":[
        "Gaz\u2019ye",
        "Gaziya",
        "\u0413\u0430\u0437\u0438\u044f"
    ],
    "wof:name":"Gaziya",
    "wof:placetype":"locality"
},
  "geometry": {"coordinates":[47.81744000000001,42.09105],"type":"Point"}
}