{
  "type": "Feature",
  "properties": {
    "gn:admin1_code":"78",
    "gn:asciiname":"Berdyuzh'ye",
    "gn:country_code":"RU",
    "gn:dem":130,
    "gn:feature_class":"P",
    "gn:feature_code":"PPL",
    "gn:name":"Berdyuzh\u2019ye",
    "gn:population":0,
    "gn:timezone":"Asia/Yekaterinburg",
    "iso:country":"RU",
    "name:eng_x_preferred":[
        "Berdyuzh'ye"
    ],
    "name:nor_x_preferred":[
        "Berdjuzje"
    ],
    "name:rus_x_preferred":[
        "\u0411\u0435\u0440\u0434\u044e\u0436\u044c\u0435"
    ],
    "name:und_x_variant":[
        "Berdyuzh\u2019ye"
    ],
    "wof:name":"Berdyuzh'ye",
    "wof:placetype":"locality"
},
  "geometry": {"coordinates":[68.32056,55.80444],"type":"Point"}
}