{
  "type": "Feature",
  "properties": {
    "gn:admin1_code":"59.0",
    "gn:asciiname":"Zarechnoye",
    "gn:country_code":"RU",
    "gn:dem":54,
    "gn:feature_class":"P",
    "gn:feature_code":"PPL",
    "gn:name":"Zarechnoye",
    "gn:population":0,
    "gn:timezone":"Asia/Vladivostok",
    "iso:country":"RU",
    "name:rus_x_preferred":[
        "\u0417\u0430\u0440\u0435\u0447\u043d\u043e\u0435"
    ],
    "wof:name":"Zarechnoye",
    "wof:placetype":"locality"
},
  "geometry": {"coordinates":[132.10586000000001,43.69892],"type":"Point"}
}