{
  "type": "Feature",
  "properties": {
    "iso:country":"RU",
    "name:rus_x_preferred":[
        "\u0412\u043e\u043b\u043a\u043e\u0432\u0441\u043a\u043e\u0435"
    ],
    "wof:name":"Volkovskoye",
    "wof:placetype":"neighbourhood"
},
  "geometry": {"coordinates":[30.36232167836659,59.89330687291198],"type":"Point"}
}