{
  "type": "Feature",
  "properties": {
    "gn:admin1_code":"56",
    "gn:asciiname":"Lesnaya Kashcheyva",
    "gn:country_code":"RU",
    "gn:dem":216,
    "gn:feature_class":"P",
    "gn:feature_code":"PPL",
    "gn:name":"Lesnaya Kashcheyva",
    "gn:population":0,
    "gn:timezone":"Europe/Moscow",
    "iso:country":"RU",
    "name:rus_x_preferred":[
        "\u041b\u0435\u0441\u043d\u0430\u044f \u041a\u0430\u0449\u0435\u0439\u0432\u0430"
    ],
    "name:und_x_variant":[
        "Kashcheyva",
        "Lesnaya Kashcheyva"
    ],
    "wof:name":"Lesnaya Kashcheyva",
    "wof:placetype":"locality"
},
  "geometry": {"coordinates":[35.51505,53.34846],"type":"Point"}
}