{
  "type": "Feature",
  "properties": {
    "gn:admin1_code":"45",
    "gn:asciiname":"Udel'naya",
    "gn:country_code":"RU",
    "gn:dem":62,
    "gn:feature_class":"P",
    "gn:feature_code":"PPL",
    "gn:name":"Udel\u2019naya",
    "gn:population":0,
    "gn:timezone":"Europe/Moscow",
    "iso:country":"RU",
    "name:rus_x_preferred":[
        "\u0423\u0434\u0435\u043b\u044c\u043d\u0430\u044f"
    ],
    "name:und_x_variant":[
        "Udel\u2019naya"
    ],
    "wof:name":"Udel'naya",
    "wof:placetype":"locality"
},
  "geometry": {"coordinates":[46.1771,56.2684],"type":"Point"}
}