{
  "type": "Feature",
  "properties": {
    "gn:admin1_code":"54",
    "gn:asciiname":"Bocherinskiy",
    "gn:country_code":"RU",
    "gn:dem":131,
    "gn:feature_class":"P",
    "gn:feature_code":"PPL",
    "gn:name":"Bocherinskiy",
    "gn:population":0,
    "gn:timezone":"Asia/Omsk",
    "iso:country":"RU",
    "name:rus_x_preferred":[
        "\u0411\u043e\u0447\u0435\u0440\u0438\u043d\u0441\u043a\u0438\u0439"
    ],
    "name:und_x_variant":[
        "\u0411\u043e\u0447\u0435\u0440\u0438\u043d\u0441\u043a\u0438\u0439"
    ],
    "wof:name":"Bocherinskiy",
    "wof:placetype":"locality"
},
  "geometry": {"coordinates":[75.28333000000001,56.53333000000001],"type":"Point"}
}