{
  "type": "Feature",
  "properties": {
    "gn:admin1_code":"60",
    "gn:asciiname":"Streletskoye",
    "gn:country_code":"RU",
    "gn:dem":63,
    "gn:feature_class":"P",
    "gn:feature_code":"PPL",
    "gn:name":"Streletskoye",
    "gn:population":0,
    "gn:timezone":"Europe/Moscow",
    "iso:country":"RU",
    "name:rus_x_preferred":[
        "\u0421\u0442\u0440\u0435\u043b\u0435\u0446\u043a\u043e\u0435"
    ],
    "wof:name":"Streletskoye",
    "wof:placetype":"locality"
},
  "geometry": {"coordinates":[28.31654,57.45585],"type":"Point"}
}