{
  "type": "Feature",
  "properties": {
    "gn:admin1_code":"33.0",
    "gn:asciiname":"Gurenki",
    "gn:country_code":"RU",
    "gn:dem":108,
    "gn:feature_class":"P",
    "gn:feature_code":"PPL",
    "gn:name":"Gurenki",
    "gn:population":0,
    "gn:timezone":"Europe/Kirov",
    "iso:country":"RU",
    "name:rus_x_preferred":[
        "\u0413\u0443\u0440\u0435\u043d\u043a\u0438"
    ],
    "name:und_x_variant":[
        "\u0413\u0443\u0440\u0435\u043d\u043a\u0438"
    ],
    "wof:name":"Gurenki",
    "wof:placetype":"locality"
},
  "geometry": {"coordinates":[48.26413,58.05919],"type":"Point"}
}