{
  "type": "Feature",
  "properties": {
    "gn:admin1_code":"25",
    "gn:asciiname":"Kireyevo",
    "gn:country_code":"RU",
    "gn:dem":146,
    "gn:feature_class":"P",
    "gn:feature_code":"PPL",
    "gn:name":"Kireyevo",
    "gn:population":0,
    "gn:timezone":"Europe/Moscow",
    "iso:country":"RU",
    "name:nor_x_preferred":[
        "Kirejevo"
    ],
    "name:rus_x_preferred":[
        "\u041a\u0438\u0440\u0435\u0435\u0432\u043e"
    ],
    "wof:name":"Kireyevo",
    "wof:placetype":"locality"
},
  "geometry": {"coordinates":[36.22009,54.3239],"type":"Point"}
}