{
  "type": "Feature",
  "properties": {
    "gn:admin1_code":"78",
    "gn:asciiname":"Chapayevo",
    "gn:country_code":"RU",
    "gn:dem":129,
    "gn:feature_class":"P",
    "gn:feature_code":"PPL",
    "gn:name":"Chapayevo",
    "gn:population":0,
    "gn:timezone":"Asia/Yekaterinburg",
    "iso:country":"RU",
    "name:ceb_x_preferred":[
        "Chapayevo"
    ],
    "name:rus_x_preferred":[
        "\u0427\u0430\u043f\u0430\u0435\u0432\u043e"
    ],
    "name:swe_x_preferred":[
        "Chapayevo"
    ],
    "name:und_x_variant":[
        "Imeni Chapayeva",
        "Chapayevo",
        "\u0427\u0430\u043f\u0430\u0435\u0432\u043e"
    ],
    "wof:name":"Chapayevo",
    "wof:placetype":"locality"
},
  "geometry": {"coordinates":[70.38283,55.96697],"type":"Point"}
}