{
  "type": "Feature",
  "properties": {
    "gn:admin1_code":"72.0",
    "gn:asciiname":"Bogoroditskoye",
    "gn:country_code":"RU",
    "gn:dem":154,
    "gn:feature_class":"P",
    "gn:feature_code":"PPL",
    "gn:name":"Bogoroditskoye",
    "gn:population":0,
    "gn:timezone":"Europe/Moscow",
    "iso:country":"RU",
    "name:rus_x_preferred":[
        "\u0411\u043e\u0433\u043e\u0440\u043e\u0434\u0438\u0442\u0441\u043a\u043e\u0435"
    ],
    "wof:name":"Bogoroditskoye",
    "wof:placetype":"locality"
},
  "geometry": {"coordinates":[41.63333,52.51667],"type":"Point"}
}