{
  "type": "Feature",
  "properties": {
    "gn:admin1_code":"69",
    "gn:asciiname":"Agarshevo",
    "gn:country_code":"RU",
    "gn:dem":195,
    "gn:feature_class":"P",
    "gn:feature_code":"PPL",
    "gn:name":"Agarshevo",
    "gn:population":0,
    "gn:timezone":"Europe/Moscow",
    "iso:country":"RU",
    "name:nor_x_preferred":[
        "Agarsjevo"
    ],
    "name:rus_x_preferred":[
        "\u0410\u0433\u0430\u0440\u0448\u0435\u0432\u043e"
    ],
    "wof:name":"Agarshevo",
    "wof:placetype":"locality"
},
  "geometry": {"coordinates":[34.34385,55.83501],"type":"Point"}
}