{
  "type": "Feature",
  "properties": {
    "gn:admin1_code":"77",
    "gn:asciiname":"Strekunovo",
    "gn:country_code":"RU",
    "gn:dem":143,
    "gn:feature_class":"P",
    "gn:feature_code":"PPL",
    "gn:name":"Strekunovo",
    "gn:population":0,
    "gn:timezone":"Europe/Moscow",
    "iso:country":"RU",
    "name:rus_x_preferred":[
        "\u0421\u0442\u0440\u0435\u043a\u0443\u043d\u043e\u0432\u043e"
    ],
    "wof:name":"Strekunovo",
    "wof:placetype":"locality"
},
  "geometry": {"coordinates":[36.8857,58.6632],"type":"Point"}
}