{
  "type": "Feature",
  "properties": {
    "gn:admin1_code":"20",
    "gn:asciiname":"Troitsk",
    "gn:cc2":"RU",
    "gn:country_code":"RU",
    "gn:dem":496,
    "gn:feature_class":"P",
    "gn:feature_code":"PPL",
    "gn:name":"Troitsk",
    "gn:population":0,
    "gn:timezone":"Asia/Irkutsk",
    "iso:country":"RU",
    "name:eng_x_preferred":[
        "Troitsk"
    ],
    "name:nor_x_preferred":[
        "Troitsk"
    ],
    "name:rus_x_preferred":[
        "\u0422\u0440\u043e\u0438\u0446\u043a"
    ],
    "name:und_x_variant":[
        "Troitskiy",
        "Troitski Zavod",
        "Troitskiy Zavod",
        "Troitskoye",
        "\u0422\u0440\u043e\u0438\u0446\u043a",
        "Troitsk"
    ],
    "wof:name":"Troitsk",
    "wof:placetype":"locality"
},
  "geometry": {"coordinates":[102.1575,53.46361],"type":"Point"}
}