{
  "type": "Feature",
  "properties": {
    "gn:admin1_code":"44",
    "gn:asciiname":"Vetka",
    "gn:country_code":"RU",
    "gn:dem":592,
    "gn:feature_class":"P",
    "gn:feature_code":"PPL",
    "gn:name":"Vetka",
    "gn:population":0,
    "gn:timezone":"Asia/Magadan",
    "iso:country":"RU",
    "wof:name":"Vetka",
    "wof:placetype":"locality"
},
  "geometry": {"coordinates":[156.61667,63.75],"type":"Point"}
}