{
  "type": "Feature",
  "properties": {
    "gn:admin1_code":"8",
    "gn:asciiname":"Kuznetsovskiy",
    "gn:country_code":"RU",
    "gn:dem":205,
    "gn:feature_class":"P",
    "gn:feature_code":"PPL",
    "gn:name":"Kuznetsovskiy",
    "gn:population":0,
    "gn:timezone":"Asia/Yekaterinburg",
    "iso:country":"RU",
    "name:rus_x_preferred":[
        "\u041a\u0443\u0437\u043d\u0435\u0446\u043e\u0432\u0441\u043a\u0438\u0439"
    ],
    "wof:name":"Kuznetsovskiy",
    "wof:placetype":"locality"
},
  "geometry": {"coordinates":[56.3687,54.608],"type":"Point"}
}