{
  "type": "Feature",
  "properties": {
    "gn:admin1_code":"46",
    "gn:asciiname":"Shadrino",
    "gn:country_code":"RU",
    "gn:dem":197,
    "gn:feature_class":"P",
    "gn:feature_code":"PPL",
    "gn:name":"Shadrino",
    "gn:population":0,
    "gn:timezone":"Europe/Moscow",
    "iso:country":"RU",
    "name:rus_x_preferred":[
        "\u0428\u0430\u0434\u0440\u0438\u043d\u043e"
    ],
    "wof:name":"Shadrino",
    "wof:placetype":"locality"
},
  "geometry": {"coordinates":[43.84361,53.86194],"type":"Point"}
}