{
  "type": "Feature",
  "properties": {
    "gn:admin1_code":"47",
    "gn:asciiname":"Redrikovy Gory",
    "gn:country_code":"RU",
    "gn:dem":203,
    "gn:feature_class":"P",
    "gn:feature_code":"PPL",
    "gn:name":"Redrikovy Gory",
    "gn:population":0,
    "gn:timezone":"Europe/Moscow",
    "iso:country":"RU",
    "wof:name":"Redrikovy Gory",
    "wof:placetype":"locality"
},
  "geometry": {"coordinates":[38.38333,56.45],"type":"Point"}
}