{
  "type": "Feature",
  "properties": {
    "gn:admin1_code":"53",
    "gn:asciiname":"Kolotovo",
    "gn:cc2":"RU",
    "gn:country_code":"RU",
    "gn:dem":101,
    "gn:feature_class":"P",
    "gn:feature_code":"PPL",
    "gn:name":"Kolotovo",
    "gn:population":0,
    "gn:timezone":"Asia/Novosibirsk",
    "iso:country":"RU",
    "name:rus_x_preferred":[
        "\u041a\u043e\u043b\u043e\u0442\u043e\u0432\u043e"
    ],
    "name:und_x_variant":[
        "Cheremukhova",
        "Kolotovo",
        "\u041a\u043e\u043b\u043e\u0442\u043e\u0432\u043e"
    ],
    "wof:name":"Kolotovo",
    "wof:placetype":"locality"
},
  "geometry": {"coordinates":[77.36667,54.71666999999999],"type":"Point"}
}