{
  "type": "Feature",
  "properties": {
    "gn:admin1_code":"85",
    "gn:asciiname":"Malaya Kislikha",
    "gn:country_code":"RU",
    "gn:dem":185,
    "gn:feature_class":"P",
    "gn:feature_code":"PPL",
    "gn:name":"Malaya Kislikha",
    "gn:population":0,
    "gn:timezone":"Europe/Moscow",
    "iso:country":"RU",
    "name:rus_x_preferred":[
        "\u041c\u0430\u043b\u0430\u044f \u041a\u0438\u0441\u043b\u0438\u0445\u0430"
    ],
    "wof:name":"Malaya Kislikha",
    "wof:placetype":"locality"
},
  "geometry": {"coordinates":[38.6832,59.2953],"type":"Point"}
}