{
  "type": "Feature",
  "properties": {
    "gn:admin1_code":"93",
    "gn:asciiname":"Zubkovshchina",
    "gn:country_code":"RU",
    "gn:dem":695,
    "gn:feature_class":"P",
    "gn:feature_code":"PPL",
    "gn:name":"Zubkovshchina",
    "gn:population":0,
    "gn:timezone":"Asia/Chita",
    "iso:country":"RU",
    "name:eng_x_preferred":[
        "Zubkovshchina"
    ],
    "name:nor_x_preferred":[
        "Zubkovsjtsjina"
    ],
    "name:rus_x_preferred":[
        "\u0417\u0443\u0431\u043a\u043e\u0432\u0449\u0438\u043d\u0430"
    ],
    "wof:name":"Zubkovshchina",
    "wof:placetype":"locality"
},
  "geometry": {"coordinates":[114.39830000000001,51.49851],"type":"Point"}
}