{
  "type": "Feature",
  "properties": {
    "gn:admin1_code":"13",
    "gn:asciiname":"Shuvalovskiy",
    "gn:country_code":"RU",
    "gn:dem":311,
    "gn:feature_class":"P",
    "gn:feature_code":"PPL",
    "gn:name":"Shuvalovskiy",
    "gn:population":0,
    "gn:timezone":"Asia/Yekaterinburg",
    "iso:country":"RU",
    "name:rus_x_preferred":[
        "\u0428\u0443\u0432\u0430\u043b\u043e\u0432\u0441\u043a\u0438\u0439"
    ],
    "wof:name":"Shuvalovskiy",
    "wof:placetype":"locality"
},
  "geometry": {"coordinates":[60.66667,55.25],"type":"Point"}
}