{
  "type": "Feature",
  "properties": {
    "gn:admin1_code":"41",
    "gn:asciiname":"Verkhniye Khalchi",
    "gn:country_code":"RU",
    "gn:dem":211,
    "gn:feature_class":"P",
    "gn:feature_code":"PPL",
    "gn:name":"Verkhniye Khalchi",
    "gn:population":0,
    "gn:timezone":"Europe/Moscow",
    "iso:country":"RU",
    "name:eng_x_preferred":[
        "Verkhniye Khalchi"
    ],
    "name:nor_x_preferred":[
        "Verkhnije Kaltsji"
    ],
    "name:rus_x_preferred":[
        "\u0412\u0435\u0440\u0445\u043d\u0438\u0435 \u041a\u0430\u043b\u0447\u0438"
    ],
    "name:rus_x_variant":[
        "\u0412\u0435\u0440\u0445\u043d\u0438\u0435 \u0425\u0430\u043b\u0447\u0438"
    ],
    "name:und_x_variant":[
        "Verkhniye Kholchi",
        "Verkhniye Kolchi",
        "Verkhniye Khalchi"
    ],
    "wof:name":"Verkhniye Khalchi",
    "wof:placetype":"locality"
},
  "geometry": {"coordinates":[35.629,51.9965],"type":"Point"}
}