{
  "type": "Feature",
  "properties": {
    "gn:admin1_code":"85",
    "gn:asciiname":"Yangolokhta",
    "gn:country_code":"RU",
    "gn:dem":170,
    "gn:feature_class":"P",
    "gn:feature_code":"PPL",
    "gn:name":"Yangolokhta",
    "gn:population":0,
    "gn:timezone":"Europe/Moscow",
    "iso:country":"RU",
    "name:eng_x_preferred":[
        "Yangolokhta"
    ],
    "name:nor_x_preferred":[
        "Jangolokhta"
    ],
    "name:rus_x_preferred":[
        "\u042f\u043d\u0433\u043e\u043b\u043e\u0445\u0442\u0430"
    ],
    "name:und_x_variant":[
        "Yangolakhta"
    ],
    "wof:name":"Yangolokhta",
    "wof:placetype":"locality"
},
  "geometry": {"coordinates":[36.1576,60.1858],"type":"Point"}
}