{
  "type": "Feature",
  "properties": {
    "gn:admin1_code":"52",
    "gn:asciiname":"Lyublino",
    "gn:country_code":"RU",
    "gn:dem":70,
    "gn:feature_class":"P",
    "gn:feature_code":"PPL",
    "gn:name":"Lyublino",
    "gn:population":0,
    "gn:timezone":"Europe/Moscow",
    "iso:country":"RU",
    "name:eng_x_preferred":[
        "Lyublino"
    ],
    "name:nor_x_preferred":[
        "Gubino"
    ],
    "name:rus_x_preferred":[
        "\u0413\u0443\u0431\u0438\u043d\u043e"
    ],
    "name:rus_x_variant":[
        "\u041b\u044e\u0431\u043b\u0438\u043d\u043e"
    ],
    "name:und_x_variant":[
        "\u041b\u044e\u0431\u043b\u0438\u043d\u043e"
    ],
    "wof:name":"Lyublino",
    "wof:placetype":"locality"
},
  "geometry": {"coordinates":[31.3729,57.3715],"type":"Point"}
}