{
  "type": "Feature",
  "properties": {
    "gn:admin1_code":"60",
    "gn:asciiname":"Beloye",
    "gn:country_code":"RU",
    "gn:dem":207,
    "gn:feature_class":"P",
    "gn:feature_code":"PPL",
    "gn:name":"Beloye",
    "gn:population":0,
    "gn:timezone":"Europe/Moscow",
    "iso:country":"RU",
    "name:rus_x_preferred":[
        "\u0411\u0435\u043b\u043e\u0435"
    ],
    "name:und_x_variant":[
        "\u0411\u0435\u043b\u043e\u0435"
    ],
    "wof:name":"Beloye",
    "wof:placetype":"locality"
},
  "geometry": {"coordinates":[29.8225,56.2235],"type":"Point"}
}