{
  "type": "Feature",
  "properties": {
    "gn:admin1_code":"77",
    "gn:asciiname":"Kablukovo",
    "gn:country_code":"RU",
    "gn:dem":144,
    "gn:feature_class":"P",
    "gn:feature_code":"PPL",
    "gn:name":"Kablukovo",
    "gn:population":0,
    "gn:timezone":"Europe/Moscow",
    "iso:country":"RU",
    "name:eng_x_preferred":[
        "Kablukovo"
    ],
    "name:nor_x_preferred":[
        "Kablukovo"
    ],
    "name:rus_x_preferred":[
        "\u041a\u0430\u0431\u043b\u0443\u043a\u043e\u0432\u043e"
    ],
    "wof:name":"Kablukovo",
    "wof:placetype":"locality"
},
  "geometry": {"coordinates":[36.21174,56.83461],"type":"Point"}
}