{
  "type": "Feature",
  "properties": {
    "gn:admin1_code":"13",
    "gn:asciiname":"Katenino",
    "gn:country_code":"RU",
    "gn:dem":258,
    "gn:feature_class":"P",
    "gn:feature_code":"PPL",
    "gn:name":"Katenino",
    "gn:population":0,
    "gn:timezone":"Asia/Yekaterinburg",
    "iso:country":"RU",
    "name:eng_x_preferred":[
        "Katenino"
    ],
    "name:nor_x_preferred":[
        "Katenino"
    ],
    "name:rus_x_preferred":[
        "\u041a\u0430\u0442\u0435\u043d\u0438\u043d\u043e"
    ],
    "name:und_x_variant":[
        "Kateninskiy"
    ],
    "wof:name":"Katenino",
    "wof:placetype":"locality"
},
  "geometry": {"coordinates":[61.05714,53.1789],"type":"Point"}
}