{
  "type": "Feature",
  "properties": {
    "gn:admin1_code":"70",
    "gn:asciiname":"Mamayka",
    "gn:country_code":"RU",
    "gn:dem":590,
    "gn:feature_class":"P",
    "gn:feature_code":"PPL",
    "gn:name":"Mamayka",
    "gn:population":0,
    "gn:timezone":"Europe/Moscow",
    "iso:country":"RU",
    "name:rus_x_preferred":[
        "\u041c\u0430\u043c\u0430\u0439\u043a\u0430"
    ],
    "wof:name":"Mamayka",
    "wof:placetype":"locality"
},
  "geometry": {"coordinates":[41.9462,45.0151],"type":"Point"}
}