{
  "type": "Feature",
  "properties": {
    "gn:admin1_code":"33.0",
    "gn:asciiname":"Makukha",
    "gn:country_code":"RU",
    "gn:dem":156,
    "gn:feature_class":"P",
    "gn:feature_code":"PPL",
    "gn:name":"Makukha",
    "gn:population":0,
    "gn:timezone":"Europe/Kirov",
    "iso:country":"RU",
    "name:rus_x_preferred":[
        "\u041c\u0430\u043a\u0443\u0445\u0430"
    ],
    "wof:name":"Makukha",
    "wof:placetype":"locality"
},
  "geometry": {"coordinates":[47.3319,60.5544],"type":"Point"}
}