{
  "type": "Feature",
  "properties": {
    "gn:admin1_code":"52",
    "gn:asciiname":"Radishchevo",
    "gn:cc2":"RU",
    "gn:country_code":"RU",
    "gn:dem":22,
    "gn:feature_class":"P",
    "gn:feature_code":"PPL",
    "gn:name":"Radishchevo",
    "gn:population":0,
    "gn:timezone":"Europe/Moscow",
    "iso:country":"RU",
    "name:rus_x_preferred":[
        "\u0420\u0430\u0434\u0438\u0449\u0435\u0432\u043e"
    ],
    "name:und_x_variant":[
        "Kholop\u2019ya Polist\u2019",
        "Radishchevo",
        "\u0420\u0430\u0434\u0438\u0449\u0435\u0432\u043e"
    ],
    "wof:name":"Radishchevo",
    "wof:placetype":"locality"
},
  "geometry": {"coordinates":[31.61667000000001,59.06667],"type":"Point"}
}