{
  "type": "Feature",
  "properties": {
    "gn:admin1_code":"33",
    "gn:asciiname":"Syrtsevy",
    "gn:country_code":"RU",
    "gn:dem":230,
    "gn:feature_class":"P",
    "gn:feature_code":"PPL",
    "gn:name":"Syrtsevy",
    "gn:population":0,
    "gn:timezone":"Europe/Kirov",
    "iso:country":"RU",
    "wof:name":"Syrtsevy",
    "wof:placetype":"locality"
},
  "geometry": {"coordinates":[50.11667,58.08333],"type":"Point"}
}