{
  "type": "Feature",
  "properties": {
    "gn:admin1_code":"8",
    "gn:asciiname":"Kob-Pokrovka",
    "gn:country_code":"RU",
    "gn:dem":140,
    "gn:feature_class":"P",
    "gn:feature_code":"PPL",
    "gn:name":"Kob-Pokrovka",
    "gn:population":0,
    "gn:timezone":"Asia/Yekaterinburg",
    "iso:country":"RU",
    "name:bak_x_preferred":[
        "\u041a\u043e\u0431-\u041f\u043e\u043a\u0440\u043e\u0432\u043a\u0430"
    ],
    "name:che_x_preferred":[
        "\u041a\u043e\u0431-\u041f\u043e\u043a\u0440\u043e\u0432\u043a\u0430"
    ],
    "name:hye_x_preferred":[
        "\u053f\u0578\u0562-\u054a\u0578\u056f\u0580\u0578\u057e\u056f\u0561"
    ],
    "name:kaz_x_preferred":[
        "\u041a\u043e\u0431-\u041f\u043e\u043a\u0440\u043e\u0432\u043a\u0430"
    ],
    "name:kir_x_preferred":[
        "\u041a\u043e\u0431-\u041f\u043e\u043a\u0440\u043e\u0432\u043a\u0430"
    ],
    "name:rus_x_preferred":[
        "\u041a\u043e\u0431-\u041f\u043e\u043a\u0440\u043e\u0432\u043a\u0430"
    ],
    "name:tat_x_preferred":[
        "\u041a\u043e\u0431-\u041f\u043e\u043a\u0440\u043e\u0432\u043a\u0430"
    ],
    "wof:name":"Kob-Pokrovka",
    "wof:placetype":"locality"
},
  "geometry": {"coordinates":[55.0001,54.7165],"type":"Point"}
}