{
  "type": "Feature",
  "properties": {
    "gn:admin1_code":"6",
    "gn:asciiname":"Kremlevo",
    "gn:country_code":"RU",
    "gn:dem":196,
    "gn:feature_class":"P",
    "gn:feature_code":"PPL",
    "gn:name":"Kreml\u00ebvo",
    "gn:population":0,
    "gn:timezone":"Europe/Moscow",
    "iso:country":"RU",
    "name:eng_x_preferred":[
        "Kreml\u00ebvo"
    ],
    "name:nor_x_preferred":[
        "Kremlevo"
    ],
    "name:rus_x_preferred":[
        "\u041a\u0440\u0435\u043c\u043b\u0435\u0432\u043e"
    ],
    "name:rus_x_variant":[
        "\u041a\u0440\u0435\u043c\u043b\u0451\u0432\u043e",
        "Kreml\u00ebvo"
    ],
    "name:und_x_variant":[
        "Kreml\u00ebvo",
        "\u041a\u0440\u0435\u043c\u043b\u0451\u0432\u043e"
    ],
    "wof:name":"Kremlevo",
    "wof:placetype":"locality"
},
  "geometry": {"coordinates":[40.3353,60.8797],"type":"Point"}
}