{
  "type": "Feature",
  "properties": {
    "gn:admin1_code":"49",
    "gn:asciiname":"Knyazhaya",
    "gn:country_code":"RU",
    "gn:dem":32,
    "gn:feature_class":"P",
    "gn:feature_code":"PPL",
    "gn:name":"Knyazhaya",
    "gn:population":0,
    "gn:timezone":"Europe/Moscow",
    "iso:country":"RU",
    "name:fin_x_preferred":[
        "Vanha Kn\u00e4s\u00f6i"
    ],
    "name:rus_x_preferred":[
        "\u041a\u043d\u044f\u0436\u0430\u044f"
    ],
    "wof:name":"Knyazhaya",
    "wof:placetype":"locality"
},
  "geometry": {"coordinates":[32.421,66.8716],"type":"Point"}
}