{
  "type": "Feature",
  "properties": {
    "gn:admin1_code":"20",
    "gn:asciiname":"Perevoz",
    "gn:country_code":"RU",
    "gn:dem":332,
    "gn:feature_class":"P",
    "gn:feature_code":"PPL",
    "gn:name":"Perevoz",
    "gn:population":0,
    "gn:timezone":"Asia/Irkutsk",
    "iso:country":"RU",
    "name:eng_x_preferred":[
        "Perevoz"
    ],
    "name:nor_x_preferred":[
        "Perevoz"
    ],
    "name:rus_x_preferred":[
        "\u041f\u0435\u0440\u0435\u0432\u043e\u0437"
    ],
    "name:und_x_variant":[
        "\u041f\u0435\u0440\u0435\u0432\u043e\u0437",
        "Perevoz"
    ],
    "wof:name":"Perevoz",
    "wof:placetype":"locality"
},
  "geometry": {"coordinates":[116.91528,58.99889],"type":"Point"}
}