{
  "type": "Feature",
  "properties": {
    "gn:admin1_code":"34",
    "gn:asciiname":"Verkhneveslyanskiy",
    "gn:country_code":"RU",
    "gn:dem":119,
    "gn:feature_class":"P",
    "gn:feature_code":"PPL",
    "gn:name":"Verkhneveslyanskiy",
    "gn:population":0,
    "gn:timezone":"Europe/Moscow",
    "iso:country":"RU",
    "name:eng_x_preferred":[
        "Verkhneveslyanskiy"
    ],
    "name:nor_x_preferred":[
        "Verkhnevesljanskij"
    ],
    "name:rus_x_preferred":[
        "\u0412\u0435\u0440\u0445\u043d\u0435\u0432\u0435\u0441\u043b\u044f\u043d\u0441\u043a\u0438\u0439"
    ],
    "name:und_x_variant":[
        "\u0412\u0435\u0440\u0445\u043d\u0435\u0432\u0435\u0441\u043b\u044f\u043d\u0441\u043a\u0438\u0439",
        "Verkhneveslyanskiy"
    ],
    "wof:name":"Verkhneveslyanskiy",
    "wof:placetype":"locality"
},
  "geometry": {"coordinates":[52.08548,63.06275],"type":"Point"}
}