{
  "type": "Feature",
  "properties": {
    "gn:admin1_code":"21.0",
    "gn:asciiname":"Bol'shoye Kostyayevo",
    "gn:country_code":"RU",
    "gn:dem":110,
    "gn:feature_class":"P",
    "gn:feature_code":"PPL",
    "gn:name":"Bol\u2019shoye Kostyayevo",
    "gn:population":0,
    "gn:timezone":"Europe/Moscow",
    "iso:country":"RU",
    "name:und_x_variant":[
        "Kostyayevo Bol\u2019shoye",
        "Bol\u2019shoye Kostyayevo"
    ],
    "wof:name":"Bol'shoye Kostyayevo",
    "wof:placetype":"locality"
},
  "geometry": {"coordinates":[42.7285,57.26178],"type":"Point"}
}