{
  "type": "Feature",
  "properties": {
    "gn:admin1_code":"52",
    "gn:asciiname":"Gusina Gorka",
    "gn:country_code":"RU",
    "gn:dem":64,
    "gn:feature_class":"P",
    "gn:feature_code":"PPL",
    "gn:name":"Gusina Gorka",
    "gn:population":0,
    "gn:timezone":"Europe/Moscow",
    "iso:country":"RU",
    "name:rus_x_preferred":[
        "\u0413\u0443\u0441\u0438\u043d\u0430 \u0413\u043e\u0440\u043a\u0430"
    ],
    "wof:name":"Gusina Gorka",
    "wof:placetype":"locality"
},
  "geometry": {"coordinates":[30.28402,58.60252],"type":"Point"}
}