{
  "type": "Feature",
  "properties": {
    "gn:admin1_code":"34",
    "gn:asciiname":"Timsher",
    "gn:country_code":"RU",
    "gn:dem":123,
    "gn:feature_class":"P",
    "gn:feature_code":"PPL",
    "gn:name":"Timsher",
    "gn:population":0,
    "gn:timezone":"Europe/Moscow",
    "iso:country":"RU",
    "name:eng_x_preferred":[
        "Timsher"
    ],
    "name:nor_x_preferred":[
        "Timsjer"
    ],
    "name:rus_x_preferred":[
        "\u0422\u0438\u043c\u0448\u0435\u0440"
    ],
    "name:und_x_variant":[
        "Lesnoy Uchastok Timshor",
        "Timshor"
    ],
    "wof:name":"Timsher",
    "wof:placetype":"locality"
},
  "geometry": {"coordinates":[55.11215,61.89875],"type":"Point"}
}