{
  "type": "Feature",
  "properties": {
    "gn:admin1_code":"42",
    "gn:asciiname":"Nizhneye Toyvino",
    "gn:country_code":"RU",
    "gn:dem":111,
    "gn:feature_class":"P",
    "gn:feature_code":"PPL",
    "gn:name":"Nizhneye Toyvino",
    "gn:population":0,
    "gn:timezone":"Europe/Moscow",
    "iso:country":"RU",
    "name:rus_x_preferred":[
        "\u041d\u0438\u0436\u043d\u0435\u0435 \u0422\u043e\u0439\u0432\u0438\u043d\u043e"
    ],
    "name:und_x_variant":[
        "\u041d\u0438\u0436\u043d\u0435\u0435 \u0422\u043e\u0439\u0432\u0438\u043d\u043e"
    ],
    "wof:name":"Nizhneye Toyvino",
    "wof:placetype":"locality"
},
  "geometry": {"coordinates":[34.25,60.45],"type":"Point"}
}