{
  "type": "Feature",
  "properties": {
    "gn:admin1_code":"33.0",
    "gn:asciiname":"Legkoye",
    "gn:country_code":"RU",
    "gn:dem":174,
    "gn:feature_class":"P",
    "gn:feature_code":"PPL",
    "gn:name":"L\u00ebgkoye",
    "gn:population":0,
    "gn:timezone":"Europe/Kirov",
    "iso:country":"RU",
    "name:rus_x_preferred":[
        "\u041b\u0451\u0433\u043a\u043e\u0435"
    ],
    "name:und_x_variant":[
        "L\u00ebgkoye",
        "\u041b\u0451\u0433\u043a\u043e\u0435"
    ],
    "wof:name":"Legkoye",
    "wof:placetype":"locality"
},
  "geometry": {"coordinates":[49.17896,59.17732],"type":"Point"}
}