{
  "type": "Feature",
  "properties": {
    "gn:admin1_code":"69",
    "gn:asciiname":"Shui",
    "gn:country_code":"RU",
    "gn:dem":196,
    "gn:feature_class":"P",
    "gn:feature_code":"PPL",
    "gn:name":"Shui",
    "gn:population":0,
    "gn:timezone":"Europe/Moscow",
    "iso:country":"RU",
    "name:ceb_x_preferred":[
        "Shui"
    ],
    "name:eng_x_preferred":[
        "Shui"
    ],
    "name:nor_x_preferred":[
        "Sjui"
    ],
    "name:rus_x_preferred":[
        "\u0428\u0443\u0438"
    ],
    "name:swe_x_preferred":[
        "Shui"
    ],
    "name:und_x_variant":[
        "Shuy"
    ],
    "wof:name":"Shui",
    "wof:placetype":"locality"
},
  "geometry": {"coordinates":[33.59702,54.22067],"type":"Point"}
}