{
  "type": "Feature",
  "properties": {
    "gn:admin1_code":"67",
    "gn:asciiname":"Russkaya Karaguzha",
    "gn:country_code":"RU",
    "gn:dem":107,
    "gn:feature_class":"P",
    "gn:feature_code":"PPL",
    "gn:name":"Russkaya Karaguzha",
    "gn:population":0,
    "gn:timezone":"Europe/Saratov",
    "iso:country":"RU",
    "name:rus_x_preferred":[
        "\u0420\u0443\u0441\u0441\u043a\u0430\u044f \u041a\u0430\u0440\u0430\u0433\u0443\u0436\u0430"
    ],
    "name:und_x_variant":[
        "\u0420\u0443\u0441\u0441\u043a\u0430\u044f \u041a\u0430\u0440\u0430\u0433\u0443\u0436\u0430"
    ],
    "wof:name":"Russkaya Karaguzha",
    "wof:placetype":"locality"
},
  "geometry": {"coordinates":[48.13333,52.76667],"type":"Point"}
}