{
  "type": "Feature",
  "properties": {
    "gn:admin1_code":"33.0",
    "gn:asciiname":"Brezga",
    "gn:country_code":"RU",
    "gn:dem":165,
    "gn:feature_class":"P",
    "gn:feature_code":"PPL",
    "gn:name":"Brezga",
    "gn:population":0,
    "gn:timezone":"Europe/Kirov",
    "iso:country":"RU",
    "name:rus_x_preferred":[
        "\u0411\u0440\u0435\u0437\u0433\u0430"
    ],
    "wof:name":"Brezga",
    "wof:placetype":"locality"
},
  "geometry": {"coordinates":[48.85,59.03333000000001],"type":"Point"}
}