{
  "type": "Feature",
  "properties": {
    "gn:admin1_code":"38",
    "gn:asciiname":"Teteryatnik",
    "gn:country_code":"RU",
    "gn:dem":3,
    "gn:feature_class":"P",
    "gn:feature_code":"PPL",
    "gn:name":"Teteryatnik",
    "gn:population":0,
    "gn:timezone":"Europe/Moscow",
    "iso:country":"RU",
    "name:rus_x_preferred":[
        "\u0422\u0435\u0442\u0435\u0440\u044f\u0442\u043d\u0438\u043a"
    ],
    "wof:name":"Teteryatnik",
    "wof:placetype":"locality"
},
  "geometry": {"coordinates":[37.84128,45.14145],"type":"Point"}
}