{
  "type": "Feature",
  "properties": {
    "gn:admin1_code":"13.0",
    "gn:asciiname":"Aylino",
    "gn:country_code":"RU",
    "gn:dem":343,
    "gn:feature_class":"P",
    "gn:feature_code":"PPL",
    "gn:name":"Aylino",
    "gn:population":0,
    "gn:timezone":"Asia/Yekaterinburg",
    "iso:country":"RU",
    "name:eng_x_preferred":[
        "Aylino"
    ],
    "name:nor_x_preferred":[
        "Ajlino"
    ],
    "name:rus_x_preferred":[
        "\u0410\u0439\u043b\u0438\u043d\u043e"
    ],
    "name:und_x_variant":[
        "\u0410\u0439\u043b\u0438\u043d\u043e",
        "Aylino"
    ],
    "wof:name":"Aylino",
    "wof:placetype":"locality"
},
  "geometry": {"coordinates":[58.8242,55.2261],"type":"Point"}
}