{
  "type": "Feature",
  "properties": {
    "gn:admin1_code":"90.0",
    "gn:asciiname":"Mostovaya",
    "gn:country_code":"RU",
    "gn:dem":128,
    "gn:feature_class":"P",
    "gn:feature_code":"PPL",
    "gn:name":"Mostovaya",
    "gn:population":0,
    "gn:timezone":"Asia/Yekaterinburg",
    "iso:country":"RU",
    "name:rus_x_preferred":[
        "\u041c\u043e\u0441\u0442\u043e\u0432\u0430\u044f"
    ],
    "wof:name":"Mostovaya",
    "wof:placetype":"locality"
},
  "geometry": {"coordinates":[55.5663,56.962],"type":"Point"}
}