{
  "type": "Feature",
  "properties": {
    "gn:admin1_code":"25",
    "gn:asciiname":"Prokhody",
    "gn:country_code":"RU",
    "gn:dem":209,
    "gn:feature_class":"P",
    "gn:feature_code":"PPL",
    "gn:name":"Prokhody",
    "gn:population":0,
    "gn:timezone":"Europe/Moscow",
    "iso:country":"RU",
    "name:rus_x_preferred":[
        "\u041f\u0440\u043e\u0445\u043e\u0434\u044b"
    ],
    "name:und_x_variant":[
        "\u041f\u0440\u043e\u0445\u043e\u0434\u044b"
    ],
    "wof:name":"Prokhody",
    "wof:placetype":"locality"
},
  "geometry": {"coordinates":[34.99444,54.42333000000001],"type":"Point"}
}