{
  "type": "Feature",
  "properties": {
    "gn:admin1_code":"90.0",
    "gn:asciiname":"Kormino",
    "gn:country_code":"RU",
    "gn:dem":155,
    "gn:feature_class":"P",
    "gn:feature_code":"PPL",
    "gn:name":"Kormino",
    "gn:population":0,
    "gn:timezone":"Asia/Yekaterinburg",
    "iso:country":"RU",
    "name:rus_x_preferred":[
        "\u041a\u043e\u0440\u043c\u0438\u043d\u043e"
    ],
    "wof:name":"Kormino",
    "wof:placetype":"locality"
},
  "geometry": {"coordinates":[55.2575,58.7055],"type":"Point"}
}