{
  "type": "Feature",
  "properties": {
    "gn:admin1_code":"60",
    "gn:asciiname":"Plavnitsa",
    "gn:country_code":"RU",
    "gn:dem":95,
    "gn:feature_class":"P",
    "gn:feature_code":"PPL",
    "gn:name":"Plavnitsa",
    "gn:population":0,
    "gn:timezone":"Europe/Moscow",
    "iso:country":"RU",
    "name:rus_x_preferred":[
        "\u041f\u043b\u0430\u0432\u043d\u0438\u0446\u0430"
    ],
    "wof:name":"Plavnitsa",
    "wof:placetype":"locality"
},
  "geometry": {"coordinates":[30.36667000000001,57.11666999999999],"type":"Point"}
}