{
  "type": "Feature",
  "properties": {
    "gn:admin1_code":"88",
    "gn:asciiname":"Ageyevo",
    "gn:country_code":"RU",
    "gn:dem":120,
    "gn:feature_class":"P",
    "gn:feature_code":"PPL",
    "gn:name":"Ageyevo",
    "gn:population":0,
    "gn:timezone":"Europe/Moscow",
    "iso:country":"RU",
    "name:rus_x_preferred":[
        "\u0410\u0433\u0435\u0435\u0432\u043e"
    ],
    "wof:name":"Ageyevo",
    "wof:placetype":"locality"
},
  "geometry": {"coordinates":[39.91978,57.98072],"type":"Point"}
}