{
  "type": "Feature",
  "properties": {
    "gn:admin1_code":"53",
    "gn:asciiname":"Staryy Koshkul'",
    "gn:country_code":"RU",
    "gn:dem":107,
    "gn:feature_class":"P",
    "gn:feature_code":"PPL",
    "gn:name":"Staryy Koshkul\u2019",
    "gn:population":0,
    "gn:timezone":"Asia/Novosibirsk",
    "iso:country":"RU",
    "name:eng_x_preferred":[
        "Staryy Koshkul'"
    ],
    "name:nor_x_preferred":[
        "Staryj Kosjkul"
    ],
    "name:rus_x_preferred":[
        "\u0421\u0442\u0430\u0440\u044b\u0439 \u041a\u043e\u0448\u043a\u0443\u043b\u044c"
    ],
    "name:und_x_variant":[
        "Staraya Koshkul\u2019",
        "Koshkul\u2019skiy",
        "Starokoshkul\u2019",
        "\u0421\u0442\u0430\u0440\u044b\u0439 \u041a\u043e\u0448\u043a\u0443\u043b\u044c",
        "Staryy Koshkul\u2019"
    ],
    "wof:name":"Staryy Koshkul'",
    "wof:placetype":"locality"
},
  "geometry": {"coordinates":[76.65727,54.9686],"type":"Point"}
}