{
  "type": "Feature",
  "properties": {
    "gn:admin1_code":"77",
    "gn:asciiname":"Teshilovo",
    "gn:country_code":"RU",
    "gn:dem":138,
    "gn:feature_class":"P",
    "gn:feature_code":"PPL",
    "gn:name":"Teshilovo",
    "gn:population":0,
    "gn:timezone":"Europe/Moscow",
    "iso:country":"RU",
    "name:rus_x_preferred":[
        "\u0422\u0435\u0448\u0438\u043b\u043e\u0432\u043e"
    ],
    "name:und_x_variant":[
        "Teshelovo"
    ],
    "wof:name":"Teshilovo",
    "wof:placetype":"locality"
},
  "geometry": {"coordinates":[36.45,56.56667],"type":"Point"}
}