{
  "type": "Feature",
  "properties": {
    "gn:admin1_code":"80.0",
    "gn:asciiname":"Makshur",
    "gn:country_code":"RU",
    "gn:dem":185,
    "gn:feature_class":"P",
    "gn:feature_code":"PPL",
    "gn:name":"Makshur",
    "gn:population":0,
    "gn:timezone":"Europe/Samara",
    "iso:country":"RU",
    "name:rus_x_preferred":[
        "\u041c\u0430\u043a\u0448\u0443\u0440"
    ],
    "wof:name":"Makshur",
    "wof:placetype":"locality"
},
  "geometry": {"coordinates":[52.4311,57.9555],"type":"Point"}
}