{
  "type": "Feature",
  "properties": {
    "gn:admin1_code":"52",
    "gn:asciiname":"Gornoye Veret'ye",
    "gn:country_code":"RU",
    "gn:dem":53,
    "gn:feature_class":"P",
    "gn:feature_code":"PPL",
    "gn:name":"Gornoye Veret\u2019y\u00eb",
    "gn:population":0,
    "gn:timezone":"Europe/Moscow",
    "iso:country":"RU",
    "name:rus_x_preferred":[
        "\u0413\u043e\u0440\u043d\u043e\u0435 \u0412\u0435\u0440\u0435\u0442\u044c\u0451"
    ],
    "name:und_x_variant":[
        "Gornoye Veret\u2019y\u00eb"
    ],
    "wof:name":"Gornoye Veret'ye",
    "wof:placetype":"locality"
},
  "geometry": {"coordinates":[30.64729,58.33917],"type":"Point"}
}