{
  "type": "Feature",
  "properties": {
    "gn:admin1_code":"25",
    "gn:asciiname":"Pustosh'",
    "gn:country_code":"RU",
    "gn:dem":207,
    "gn:feature_class":"P",
    "gn:feature_code":"PPL",
    "gn:name":"Pustosh\u2019",
    "gn:population":0,
    "gn:timezone":"Europe/Moscow",
    "iso:country":"RU",
    "name:rus_x_preferred":[
        "\u041f\u0443\u0441\u0442\u043e\u0448\u044c"
    ],
    "name:und_x_variant":[
        "Pustosh\u2019",
        "\u041f\u0443\u0441\u0442\u043e\u0448\u044c"
    ],
    "wof:name":"Pustosh'",
    "wof:placetype":"locality"
},
  "geometry": {"coordinates":[34.86694,53.66417],"type":"Point"}
}