{
  "type": "Feature",
  "properties": {
    "gn:admin1_code":"52",
    "gn:asciiname":"Lubno",
    "gn:country_code":"RU",
    "gn:dem":74,
    "gn:feature_class":"P",
    "gn:feature_code":"PPL",
    "gn:name":"Lubno",
    "gn:population":0,
    "gn:timezone":"Europe/Moscow",
    "iso:country":"RU",
    "name:ces_x_preferred":[
        "Lubno"
    ],
    "name:fra_x_preferred":[
        "Lubno"
    ],
    "name:pol_x_preferred":[
        "Lubno"
    ],
    "name:rus_x_preferred":[
        "\u041b\u0443\u0431\u043d\u043e"
    ],
    "name:ukr_x_preferred":[
        "\u041b\u044e\u0431\u043d\u043e"
    ],
    "name:und_x_variant":[
        "Pos\u00eblok Lyubno",
        "Lyubno",
        "Lubno"
    ],
    "wof:name":"Lubno",
    "wof:placetype":"locality"
},
  "geometry": {"coordinates":[32.28603,57.48727],"type":"Point"}
}