{
  "type": "Feature",
  "properties": {
    "gn:admin1_code":"45.0",
    "gn:asciiname":"Polanur",
    "gn:country_code":"RU",
    "gn:dem":160,
    "gn:feature_class":"P",
    "gn:feature_code":"PPL",
    "gn:name":"Polanur",
    "gn:population":0,
    "gn:timezone":"Europe/Moscow",
    "iso:country":"RU",
    "name:rus_x_preferred":[
        "\u041f\u043e\u043b\u0430\u043d\u0443\u0440"
    ],
    "name:und_x_variant":[
        "\u041f\u043e\u043b\u0430\u043d\u0443\u0440"
    ],
    "wof:name":"Polanur",
    "wof:placetype":"locality"
},
  "geometry": {"coordinates":[49.17639000000001,56.92194],"type":"Point"}
}