{
  "type": "Feature",
  "properties": {
    "gn:admin1_code":"85",
    "gn:asciiname":"Yesipovo",
    "gn:country_code":"RU",
    "gn:dem":135,
    "gn:feature_class":"P",
    "gn:feature_code":"PPL",
    "gn:name":"Yesipovo",
    "gn:population":0,
    "gn:timezone":"Europe/Moscow",
    "iso:country":"RU",
    "name:rus_x_preferred":[
        "\u0415\u0441\u0438\u043f\u043e\u0432\u043e"
    ],
    "wof:name":"Yesipovo",
    "wof:placetype":"locality"
},
  "geometry": {"coordinates":[38.016,60.0177],"type":"Point"}
}