{
  "type": "Feature",
  "properties": {
    "gn:admin1_code":"11",
    "gn:asciiname":"Ulus Khygynyg",
    "gn:cc2":"RU",
    "gn:country_code":"RU",
    "gn:dem":631,
    "gn:feature_class":"P",
    "gn:feature_code":"PPL",
    "gn:name":"Ulus Khygynyg",
    "gn:population":0,
    "gn:timezone":"Asia/Irkutsk",
    "iso:country":"RU",
    "name:und_x_variant":[
        "Khygynyg",
        "Ulus Khygynyg"
    ],
    "wof:name":"Ulus Khygynyg",
    "wof:placetype":"locality"
},
  "geometry": {"coordinates":[110.66667,54.18333000000001],"type":"Point"}
}