{
  "type": "Feature",
  "properties": {
    "gn:admin1_code":"33",
    "gn:asciiname":"Bliny",
    "gn:country_code":"RU",
    "gn:dem":172,
    "gn:feature_class":"P",
    "gn:feature_code":"PPL",
    "gn:name":"Bliny",
    "gn:population":0,
    "gn:timezone":"Europe/Kirov",
    "iso:country":"RU",
    "name:rus_x_preferred":[
        "\u0411\u043b\u0438\u043d\u044b"
    ],
    "wof:name":"Bliny",
    "wof:placetype":"locality"
},
  "geometry": {"coordinates":[46.97581,58.32241],"type":"Point"}
}