{
  "type": "Feature",
  "properties": {
    "gn:admin1_code":"83.0",
    "gn:asciiname":"Lukhovets",
    "gn:country_code":"RU",
    "gn:dem":154,
    "gn:feature_class":"P",
    "gn:feature_code":"PPL",
    "gn:name":"Lukhovets",
    "gn:population":0,
    "gn:timezone":"Europe/Moscow",
    "iso:country":"RU",
    "name:rus_x_preferred":[
        "\u041b\u0443\u0445\u043e\u0432\u0435\u0446"
    ],
    "wof:name":"Lukhovets",
    "wof:placetype":"locality"
},
  "geometry": {"coordinates":[40.10529,56.16515],"type":"Point"}
}