{
  "type": "Feature",
  "properties": {
    "gn:admin1_code":"23",
    "gn:asciiname":"Krylovka",
    "gn:country_code":"RU",
    "gn:dem":4,
    "gn:feature_class":"P",
    "gn:feature_code":"PPL",
    "gn:name":"Krylovka",
    "gn:population":0,
    "gn:timezone":"Europe/Kaliningrad",
    "iso:country":"RU",
    "name:rus_x_preferred":[
        "\u041a\u0440\u044b\u043b\u043e\u0432\u043a\u0430"
    ],
    "name:und_x_variant":[
        "\u041a\u0440\u044b\u043b\u043e\u0432\u043a\u0430"
    ],
    "wof:name":"Krylovka",
    "wof:placetype":"locality"
},
  "geometry": {"coordinates":[20.04697,54.73956999999999],"type":"Point"}
}