{
  "type": "Feature",
  "properties": {
    "gn:admin1_code":"60",
    "gn:asciiname":"Dedov Kamen'",
    "gn:country_code":"RU",
    "gn:dem":157,
    "gn:feature_class":"P",
    "gn:feature_code":"PPL",
    "gn:name":"Dedov Kamen\u2019",
    "gn:population":0,
    "gn:timezone":"Europe/Moscow",
    "iso:country":"RU",
    "name:rus_x_preferred":[
        "\u0414\u0435\u0434\u043e\u0432 \u041a\u0430\u043c\u0435\u043d\u044c"
    ],
    "name:und_x_variant":[
        "Dedov Kamen\u2019"
    ],
    "wof:name":"Dedov Kamen'",
    "wof:placetype":"locality"
},
  "geometry": {"coordinates":[29.5602,56.0568],"type":"Point"}
}