{
  "type": "Feature",
  "properties": {
    "gn:admin1_code":"5",
    "gn:asciiname":"Ulyagir",
    "gn:country_code":"RU",
    "gn:dem":410,
    "gn:feature_class":"P",
    "gn:feature_code":"PPL",
    "gn:name":"Ulyagir",
    "gn:population":0,
    "gn:timezone":"Asia/Yakutsk",
    "iso:country":"RU",
    "name:che_x_preferred":[
        "\u0423\u043b\u044f\u0433\u0438\u0440"
    ],
    "name:eng_x_preferred":[
        "Ulyagir"
    ],
    "name:nor_x_preferred":[
        "Uljagir"
    ],
    "name:rus_x_preferred":[
        "\u0423\u043b\u044f\u0433\u0438\u0440"
    ],
    "wof:name":"Ulyagir",
    "wof:placetype":"locality"
},
  "geometry": {"coordinates":[123.22807,54.02577],"type":"Point"}
}