{
  "type": "Feature",
  "properties": {
    "gn:admin1_code":"6",
    "gn:asciiname":"Terebino",
    "gn:country_code":"RU",
    "gn:dem":70,
    "gn:feature_class":"P",
    "gn:feature_code":"PPL",
    "gn:name":"Terebino",
    "gn:population":0,
    "gn:timezone":"Europe/Moscow",
    "iso:country":"RU",
    "name:che_x_preferred":[
        "\u0422\u0435\u0440\u0435\u0431\u0438\u043d\u043e"
    ],
    "name:eng_x_preferred":[
        "Terebino"
    ],
    "name:ita_x_preferred":[
        "Terebino"
    ],
    "name:nor_x_preferred":[
        "Terebino"
    ],
    "name:rus_x_preferred":[
        "\u0422\u0435\u0440\u0435\u0431\u0438\u043d\u043e"
    ],
    "name:tat_x_preferred":[
        "\u0422\u0435\u0440\u0435\u0431\u0438\u043d\u043e"
    ],
    "name:tgk_x_preferred":[
        "\u0422\u0435\u0440\u0435\u0431\u0438\u043d\u043e"
    ],
    "wof:name":"Terebino",
    "wof:placetype":"locality"
},
  "geometry": {"coordinates":[42.11013,60.86661],"type":"Point"}
}