{
  "type": "Feature",
  "properties": {
    "gn:admin1_code":"76",
    "gn:asciiname":"Poddolgoye",
    "gn:country_code":"RU",
    "gn:dem":184,
    "gn:feature_class":"P",
    "gn:feature_code":"PPL",
    "gn:name":"Poddolgoye",
    "gn:population":0,
    "gn:timezone":"Europe/Moscow",
    "iso:country":"RU",
    "name:eng_x_preferred":[
        "Poddolgoye"
    ],
    "name:nor_x_preferred":[
        "Poddolgoje"
    ],
    "name:rus_x_preferred":[
        "\u041f\u043e\u0434\u0434\u043e\u043b\u0433\u043e\u0435"
    ],
    "name:und_x_variant":[
        "Poddolgaya",
        "\u041f\u043e\u0434\u0434\u043e\u043b\u0433\u043e\u0435",
        "Poddolgoye"
    ],
    "wof:name":"Poddolgoye",
    "wof:placetype":"locality"
},
  "geometry": {"coordinates":[38.05949,53.20648000000001],"type":"Point"}
}