{
  "type": "Feature",
  "properties": {
    "gn:admin1_code":"42.0",
    "gn:asciiname":"Belozerki",
    "gn:country_code":"RU",
    "gn:dem":11,
    "gn:feature_class":"P",
    "gn:feature_code":"PPL",
    "gn:name":"Beloz\u00ebrki",
    "gn:population":0,
    "gn:timezone":"Europe/Moscow",
    "iso:country":"RU",
    "name:nor_x_preferred":[
        "Beloziorki"
    ],
    "name:rus_x_preferred":[
        "\u0411\u0435\u043b\u043e\u0437\u0451\u0440\u043a\u0438"
    ],
    "name:und_x_variant":[
        "Belozerka",
        "Beloz\u00ebrki"
    ],
    "wof:name":"Belozerki",
    "wof:placetype":"locality"
},
  "geometry": {"coordinates":[31.66667,60.16667],"type":"Point"}
}