{
  "type": "Feature",
  "properties": {
    "gn:admin1_code":"9",
    "gn:asciiname":"Starokhmelevoye",
    "gn:country_code":"RU",
    "gn:dem":146,
    "gn:feature_class":"P",
    "gn:feature_code":"PPL",
    "gn:name":"Starokhmelevoye",
    "gn:population":0,
    "gn:timezone":"Europe/Moscow",
    "iso:country":"RU",
    "name:rus_x_preferred":[
        "\u0421\u0442\u0430\u0440\u043e\u0445\u043c\u0435\u043b\u0435\u0432\u043e\u0435"
    ],
    "name:und_x_variant":[
        "Staro-Khmelevaya",
        "Starokhmelevoye"
    ],
    "wof:name":"Starokhmelevoye",
    "wof:placetype":"locality"
},
  "geometry": {"coordinates":[37.66334000000001,51.0697],"type":"Point"}
}