{
  "type": "Feature",
  "properties": {
    "gn:admin1_code":"85",
    "gn:asciiname":"Verkhnyaya Kolen'ga",
    "gn:country_code":"RU",
    "gn:dem":131,
    "gn:feature_class":"P",
    "gn:feature_code":"PPL",
    "gn:name":"Verkhnyaya Kolen\u2019ga",
    "gn:population":0,
    "gn:timezone":"Europe/Moscow",
    "iso:country":"RU",
    "wof:name":"Verkhnyaya Kolen'ga",
    "wof:placetype":"locality"
},
  "geometry": {"coordinates":[42.81667,60.73333],"type":"Point"}
}