{
  "type": "Feature",
  "properties": {
    "gn:admin1_code":"73",
    "gn:asciiname":"Staryy Kayensar",
    "gn:country_code":"RU",
    "gn:dem":156,
    "gn:feature_class":"P",
    "gn:feature_code":"PPL",
    "gn:name":"Staryy Kayensar",
    "gn:population":0,
    "gn:timezone":"Europe/Moscow",
    "iso:country":"RU",
    "name:rus_x_preferred":[
        "\u0421\u0442\u0430\u0440\u044b\u0439 \u041a\u0430\u0435\u043d\u0441\u0430\u0440"
    ],
    "wof:name":"Staryy Kayensar",
    "wof:placetype":"locality"
},
  "geometry": {"coordinates":[50.9919,56.0589],"type":"Point"}
}