{
  "type": "Feature",
  "properties": {
    "gn:admin1_code":"20",
    "gn:asciiname":"Vilensk",
    "gn:country_code":"RU",
    "gn:dem":576,
    "gn:feature_class":"P",
    "gn:feature_code":"PPL",
    "gn:name":"Vilensk",
    "gn:population":0,
    "gn:timezone":"Asia/Irkutsk",
    "iso:country":"RU",
    "name:rus_x_preferred":[
        "\u0412\u0438\u043b\u0435\u043d\u0441\u043a"
    ],
    "name:und_x_variant":[
        "Valinskiy"
    ],
    "wof:name":"Vilensk",
    "wof:placetype":"locality"
},
  "geometry": {"coordinates":[99.88872000000001,54.54861],"type":"Point"}
}