{
  "type": "Feature",
  "properties": {
    "gn:admin1_code":"53",
    "gn:asciiname":"Veselyy Bednyak",
    "gn:country_code":"RU",
    "gn:dem":199,
    "gn:feature_class":"P",
    "gn:feature_code":"PPL",
    "gn:name":"Ves\u00eblyy Bednyak",
    "gn:population":0,
    "gn:timezone":"Asia/Novosibirsk",
    "iso:country":"RU",
    "wof:name":"Veselyy Bednyak",
    "wof:placetype":"locality"
},
  "geometry": {"coordinates":[80.93333,54.53333000000001],"type":"Point"}
}