{
  "type": "Feature",
  "properties": {
    "gn:admin1_code":"56",
    "gn:asciiname":"Trosna",
    "gn:country_code":"RU",
    "gn:dem":245,
    "gn:feature_class":"P",
    "gn:feature_code":"PPL",
    "gn:name":"Trosna",
    "gn:population":0,
    "gn:timezone":"Europe/Moscow",
    "iso:country":"RU",
    "wof:name":"Trosna",
    "wof:placetype":"locality"
},
  "geometry": {"coordinates":[36.38333,52.41667],"type":"Point"}
}