{
  "type": "Feature",
  "properties": {
    "gn:admin1_code":"4",
    "gn:asciiname":"Polomoshnoye",
    "gn:country_code":"RU",
    "gn:dem":226,
    "gn:feature_class":"P",
    "gn:feature_code":"PPL",
    "gn:name":"Polomoshnoye",
    "gn:population":0,
    "gn:timezone":"Asia/Barnaul",
    "iso:country":"RU",
    "name:rus_x_preferred":[
        "\u041f\u043e\u043b\u043e\u043c\u043e\u0448\u043d\u043e\u0435"
    ],
    "name:und_x_variant":[
        "Polomyshnoye",
        "Polomoshnoye Vtoroye",
        "Polomoshnoye"
    ],
    "wof:name":"Polomoshnoye",
    "wof:placetype":"locality"
},
  "geometry": {"coordinates":[81.4872,52.2822],"type":"Point"}
}