{
  "type": "Feature",
  "properties": {
    "gn:admin1_code":"8",
    "gn:asciiname":"Leninsky",
    "gn:country_code":"RU",
    "gn:dem":444,
    "gn:feature_class":"P",
    "gn:feature_code":"PPL",
    "gn:name":"Leninsky",
    "gn:population":0,
    "gn:timezone":"Asia/Yekaterinburg",
    "iso:country":"RU",
    "name:bel_x_preferred":[
        "\u041b\u0435\u043d\u0456\u043d\u0441\u043a\u0456"
    ],
    "name:cat_x_preferred":[
        "L\u00e9ninski"
    ],
    "name:deu_x_preferred":[
        "Leninski"
    ],
    "name:ita_x_preferred":[
        "Leninskij"
    ],
    "name:rus_x_preferred":[
        "\u041b\u0435\u043d\u0438\u043d\u0441\u043a\u044b"
    ],
    "name:rus_x_variant":[
        "\u041b\u0435\u043d\u0438\u043d\u0441\u043a\u0438\u0439"
    ],
    "name:sco_x_preferred":[
        "Leninsky"
    ],
    "name:spa_x_preferred":[
        "L\u00e9ninski"
    ],
    "name:swe_x_preferred":[
        "Leninskij"
    ],
    "name:tat_x_preferred":[
        "\u041b\u0435\u043d\u0438\u043d\u0441\u043a\u0438\u0439"
    ],
    "name:ukr_x_preferred":[
        "\u041b\u0435\u043d\u0456\u043d\u0441\u044c\u043a\u0438\u0439"
    ],
    "name:und_x_variant":[
        "\u041b\u0435\u043d\u0438\u043d\u0441\u043a\u044b"
    ],
    "wof:name":"Leninsky",
    "wof:placetype":"locality"
},
  "geometry": {"coordinates":[59.48333,54.21666999999999],"type":"Point"}
}