{
  "type": "Feature",
  "properties": {
    "gn:admin1_code":"52",
    "gn:asciiname":"Novaya Krapivna",
    "gn:country_code":"RU",
    "gn:dem":115,
    "gn:feature_class":"P",
    "gn:feature_code":"PPL",
    "gn:name":"Novaya Krapivna",
    "gn:population":0,
    "gn:timezone":"Europe/Moscow",
    "iso:country":"RU",
    "name:eng_x_preferred":[
        "Novaya Krapivna"
    ],
    "name:nor_x_preferred":[
        "Nov.Krapivna"
    ],
    "name:rus_x_preferred":[
        "\u041d\u043e\u0432.\u041a\u0440\u0430\u043f\u0438\u0432\u043d\u0430"
    ],
    "name:rus_x_variant":[
        "\u041d\u043e\u0432\u0430\u044f \u041a\u0440\u0430\u043f\u0438\u0432\u043d\u0430"
    ],
    "name:und_x_variant":[
        "Krapivna"
    ],
    "wof:name":"Novaya Krapivna",
    "wof:placetype":"locality"
},
  "geometry": {"coordinates":[33.48175999999999,59.19055],"type":"Point"}
}