{
  "type": "Feature",
  "properties": {
    "gn:admin1_code":"59",
    "gn:asciiname":"Sukhaya Rechka",
    "gn:country_code":"RU",
    "gn:dem":52,
    "gn:feature_class":"P",
    "gn:feature_code":"PPL",
    "gn:name":"Sukhaya Rechka",
    "gn:population":0,
    "gn:timezone":"Asia/Vladivostok",
    "iso:country":"RU",
    "name:rus_x_preferred":[
        "\u0421\u0443\u0445\u0430\u044f \u0420\u0435\u0447\u043a\u0430"
    ],
    "wof:name":"Sukhaya Rechka",
    "wof:placetype":"locality"
},
  "geometry": {"coordinates":[131.53332,43.04926],"type":"Point"}
}