{
  "type": "Feature",
  "properties": {
    "gn:admin1_code":"6",
    "gn:asciiname":"Lyakhovskaya",
    "gn:country_code":"RU",
    "gn:dem":46,
    "gn:feature_class":"P",
    "gn:feature_code":"PPL",
    "gn:name":"Lyakhovskaya",
    "gn:population":0,
    "gn:timezone":"Europe/Moscow",
    "iso:country":"RU",
    "name:rus_x_preferred":[
        "\u041b\u044f\u0445\u043e\u0432\u0441\u043a\u0430\u044f"
    ],
    "name:und_x_variant":[
        "\u041b\u044f\u0445\u043e\u0432\u0441\u043a\u0430\u044f"
    ],
    "wof:name":"Lyakhovskaya",
    "wof:placetype":"locality"
},
  "geometry": {"coordinates":[45.16537,61.88621],"type":"Point"}
}