{
  "type": "Feature",
  "properties": {
    "gn:admin1_code":"62",
    "gn:asciiname":"Poselok Vtoroy Fermy",
    "gn:country_code":"RU",
    "gn:dem":170,
    "gn:feature_class":"P",
    "gn:feature_code":"PPL",
    "gn:name":"Pos\u00eblok Vtoroy Fermy",
    "gn:population":0,
    "gn:timezone":"Europe/Moscow",
    "iso:country":"RU",
    "name:rus_x_preferred":[
        "\u041f\u043e\u0441\u00eb\u043b\u043e\u043a \u0412\u0442\u043e\u0440\u043e\u0439 \u0424\u0435\u0440\u043c\u044b"
    ],
    "name:und_x_variant":[
        "Pos\u00eblok Vtoroy Fermy"
    ],
    "wof:name":"Poselok Vtoroy Fermy",
    "wof:placetype":"locality"
},
  "geometry": {"coordinates":[39.5954,53.655],"type":"Point"}
}