{
  "type": "Feature",
  "properties": {
    "gn:admin1_code":"10",
    "gn:asciiname":"Belyayeva",
    "gn:country_code":"RU",
    "gn:dem":221,
    "gn:feature_class":"P",
    "gn:feature_code":"PPL",
    "gn:name":"Belyayeva",
    "gn:population":0,
    "gn:timezone":"Europe/Moscow",
    "iso:country":"RU",
    "name:nor_x_preferred":[
        "Beljaeva"
    ],
    "name:rus_x_preferred":[
        "\u0411\u0435\u043b\u044f\u0435\u0432\u0430"
    ],
    "name:und_x_variant":[
        "Belyayevo",
        "Belyayeva"
    ],
    "wof:name":"Belyayeva",
    "wof:placetype":"locality"
},
  "geometry": {"coordinates":[34.92018,53.01797],"type":"Point"}
}