{
  "type": "Feature",
  "properties": {
    "gn:admin1_code":"77",
    "gn:asciiname":"Shizderovo",
    "gn:country_code":"RU",
    "gn:dem":213,
    "gn:feature_class":"P",
    "gn:feature_code":"PPL",
    "gn:name":"Shizderovo",
    "gn:population":0,
    "gn:timezone":"Europe/Moscow",
    "iso:country":"RU",
    "name:rus_x_preferred":[
        "\u0428\u0438\u0437\u0434\u0435\u0440\u043e\u0432\u043e"
    ],
    "name:und_x_variant":[
        "Shizoyerovo",
        "Shizderovo",
        "\u0428\u0438\u0437\u0434\u0435\u0440\u043e\u0432\u043e"
    ],
    "wof:name":"Shizderovo",
    "wof:placetype":"locality"
},
  "geometry": {"coordinates":[33.41094,55.94232],"type":"Point"}
}