{
  "type": "Feature",
  "properties": {
    "gn:admin1_code":"42",
    "gn:asciiname":"Nizhniye Mandrogi",
    "gn:country_code":"RU",
    "gn:dem":32,
    "gn:feature_class":"P",
    "gn:feature_code":"PPL",
    "gn:name":"Nizhniye Mandrogi",
    "gn:population":0,
    "gn:timezone":"Europe/Moscow",
    "iso:country":"RU",
    "name:rus_x_preferred":[
        "\u041d\u0438\u0436\u043d\u0438\u0435 \u041c\u0430\u043d\u0434\u0440\u043e\u0433\u0438"
    ],
    "name:und_x_variant":[
        "\u041d\u0438\u0436\u043d\u0438\u0435 \u041c\u0430\u043d\u0434\u0440\u043e\u0433\u0438"
    ],
    "wof:name":"Nizhniye Mandrogi",
    "wof:placetype":"locality"
},
  "geometry": {"coordinates":[33.76667,60.86666999999999],"type":"Point"}
}