{
  "type": "Feature",
  "properties": {
    "gn:admin1_code":"92",
    "gn:asciiname":"Perevesnaya",
    "gn:country_code":"RU",
    "gn:dem":126,
    "gn:feature_class":"P",
    "gn:feature_code":"PPL",
    "gn:name":"Perevesnaya",
    "gn:population":0,
    "gn:timezone":"Asia/Kamchatka",
    "iso:country":"RU",
    "name:rus_x_preferred":[
        "\u041f\u0435\u0440\u0435\u0432\u0435\u0441\u043d\u0430\u044f"
    ],
    "name:und_x_variant":[
        "\u041f\u0435\u0440\u0435\u0432\u0435\u0441\u043d\u0430\u044f"
    ],
    "wof:name":"Perevesnaya",
    "wof:placetype":"locality"
},
  "geometry": {"coordinates":[156.91666999999995,53.08333],"type":"Point"}
}