{
  "type": "Feature",
  "properties": {
    "gn:admin1_code":"33.0",
    "gn:asciiname":"Agalachenki",
    "gn:country_code":"RU",
    "gn:dem":155,
    "gn:feature_class":"P",
    "gn:feature_code":"PPL",
    "gn:name":"Agalachenki",
    "gn:population":0,
    "gn:timezone":"Europe/Kirov",
    "iso:country":"RU",
    "name:nor_x_preferred":[
        "Agalatsjenki"
    ],
    "name:rus_x_preferred":[
        "\u0410\u0433\u0430\u043b\u0430\u0447\u0435\u043d\u043a\u0438"
    ],
    "name:und_x_variant":[
        "Agolechenki",
        "Agalachenki"
    ],
    "wof:name":"Agalachenki",
    "wof:placetype":"locality"
},
  "geometry": {"coordinates":[49.10102,58.92251],"type":"Point"}
}