{
  "type": "Feature",
  "properties": {
    "gn:admin1_code":"23",
    "gn:asciiname":"Rechki",
    "gn:cc2":"RU",
    "gn:country_code":"RU",
    "gn:dem":4,
    "gn:feature_class":"P",
    "gn:feature_code":"PPL",
    "gn:name":"Rechki",
    "gn:population":0,
    "gn:timezone":"Europe/Kaliningrad",
    "iso:country":"RU",
    "name:rus_x_preferred":[
        "\u0420\u0435\u0447\u043a\u0438"
    ],
    "name:und_x_variant":[
        "Gro\u00df P\u00f6ppeln",
        "Rechki",
        "\u0420\u0435\u0447\u043a\u0438"
    ],
    "wof:name":"Rechki",
    "wof:placetype":"locality"
},
  "geometry": {"coordinates":[21.15778,54.80444],"type":"Point"}
}