{
  "type": "Feature",
  "properties": {
    "gn:admin1_code":"88",
    "gn:asciiname":"Bol'shoye Khvastovo",
    "gn:country_code":"RU",
    "gn:dem":145,
    "gn:feature_class":"P",
    "gn:feature_code":"PPL",
    "gn:name":"Bol\u2019shoye Khvastovo",
    "gn:population":0,
    "gn:timezone":"Europe/Moscow",
    "iso:country":"RU",
    "name:rus_x_preferred":[
        "\u0411\u043e\u043b\u044c\u0448\u043e\u0435 \u0425\u0432\u0430\u0441\u0442\u043e\u0432\u043e"
    ],
    "name:und_x_variant":[
        "Bol\u2019shoye Khvastovo"
    ],
    "wof:name":"Bol'shoye Khvastovo",
    "wof:placetype":"locality"
},
  "geometry": {"coordinates":[38.8149,57.2833],"type":"Point"}
}