{
  "type": "Feature",
  "properties": {
    "gn:admin1_code":"88.0",
    "gn:asciiname":"Chur'yakovo",
    "gn:country_code":"RU",
    "gn:dem":118,
    "gn:feature_class":"P",
    "gn:feature_code":"PPL",
    "gn:name":"Chur\u2019yakovo",
    "gn:population":0,
    "gn:timezone":"Europe/Moscow",
    "iso:country":"RU",
    "name:nor_x_preferred":[
        "Tsjurjakovo"
    ],
    "name:rus_x_preferred":[
        "\u0427\u0443\u0440\u044c\u044f\u043a\u043e\u0432\u043e"
    ],
    "name:und_x_variant":[
        "Chur\u2019yakovo"
    ],
    "wof:name":"Chur'yakovo",
    "wof:placetype":"locality"
},
  "geometry": {"coordinates":[40.4059,57.99171],"type":"Point"}
}