{
  "type": "Feature",
  "properties": {
    "gn:admin1_code":"8",
    "gn:asciiname":"Mukhamet-Rakhimova",
    "gn:country_code":"RU",
    "gn:dem":403,
    "gn:feature_class":"P",
    "gn:feature_code":"PPL",
    "gn:name":"Mukhamet-Rakhimova",
    "gn:population":0,
    "gn:timezone":"Asia/Yekaterinburg",
    "iso:country":"RU",
    "name:rus_x_preferred":[
        "\u041c\u0443\u0445\u0430\u043c\u0435\u0442-\u0420\u0430\u0445\u0438\u043c\u043e\u0432\u0430"
    ],
    "wof:name":"Mukhamet-Rakhimova",
    "wof:placetype":"locality"
},
  "geometry": {"coordinates":[58.01667,52.25],"type":"Point"}
}