{
  "type": "Feature",
  "properties": {
    "gn:admin1_code":"85",
    "gn:asciiname":"Roman'kovo",
    "gn:country_code":"RU",
    "gn:dem":129,
    "gn:feature_class":"P",
    "gn:feature_code":"PPL",
    "gn:name":"Roman\u2019kovo",
    "gn:population":0,
    "gn:timezone":"Europe/Moscow",
    "iso:country":"RU",
    "name:rus_x_preferred":[
        "\u0420\u043e\u043c\u0430\u043d\u044c\u043a\u043e\u0432\u043e"
    ],
    "name:und_x_variant":[
        "Roman\u2019kovo",
        "\u0420\u043e\u043c\u0430\u043d\u044c\u043a\u043e\u0432\u043e"
    ],
    "wof:name":"Roman'kovo",
    "wof:placetype":"locality"
},
  "geometry": {"coordinates":[36.4329,58.8152],"type":"Point"}
}