{
  "type": "Feature",
  "properties": {
    "gn:admin1_code":"33",
    "gn:asciiname":"Tokhtino",
    "gn:country_code":"RU",
    "gn:dem":117,
    "gn:feature_class":"P",
    "gn:feature_code":"PPL",
    "gn:name":"Tokhtino",
    "gn:population":0,
    "gn:timezone":"Europe/Kirov",
    "iso:country":"RU",
    "name:rus_x_preferred":[
        "\u0422\u043e\u0445\u0442\u0438\u043d\u043e"
    ],
    "wof:name":"Tokhtino",
    "wof:placetype":"locality"
},
  "geometry": {"coordinates":[48.52905,58.62919],"type":"Point"}
}