{
  "type": "Feature",
  "properties": {
    "gn:admin1_code":"33.0",
    "gn:asciiname":"Bushuyevy",
    "gn:country_code":"RU",
    "gn:dem":155,
    "gn:feature_class":"P",
    "gn:feature_code":"PPL",
    "gn:name":"Bushuyevy",
    "gn:population":0,
    "gn:timezone":"Europe/Kirov",
    "iso:country":"RU",
    "name:rus_x_preferred":[
        "\u0411\u0443\u0448\u0443\u0435\u0432\u044b"
    ],
    "name:und_x_variant":[
        "\u0411\u0443\u0448\u0443\u0435\u0432\u044b"
    ],
    "wof:name":"Bushuyevy",
    "wof:placetype":"locality"
},
  "geometry": {"coordinates":[49.82831,58.74796],"type":"Point"}
}