{
  "type": "Feature",
  "properties": {
    "gn:admin1_code":"55",
    "gn:asciiname":"Kuvak",
    "gn:country_code":"RU",
    "gn:dem":205,
    "gn:feature_class":"P",
    "gn:feature_code":"PPL",
    "gn:name":"Kuvak",
    "gn:population":0,
    "gn:timezone":"Asia/Yekaterinburg",
    "iso:country":"RU",
    "name:rus_x_preferred":[
        "\u041a\u0443\u0432\u0430\u043a"
    ],
    "name:und_x_variant":[
        "\u041a\u0443\u0432\u0430\u043a"
    ],
    "wof:name":"Kuvak",
    "wof:placetype":"locality"
},
  "geometry": {"coordinates":[52.6544,54.2572],"type":"Point"}
}