{
  "type": "Feature",
  "properties": {
    "gn:admin1_code":"51",
    "gn:asciiname":"Shchukino",
    "gn:country_code":"RU",
    "gn:dem":164,
    "gn:feature_class":"P",
    "gn:feature_code":"PPL",
    "gn:name":"Shchukino",
    "gn:population":0,
    "gn:timezone":"Europe/Moscow",
    "iso:country":"RU",
    "name:rus_x_preferred":[
        "\u0429\u0443\u043a\u0438\u043d\u043e"
    ],
    "wof:name":"Shchukino",
    "wof:placetype":"locality"
},
  "geometry": {"coordinates":[46.17334,55.35029],"type":"Point"}
}