{
  "type": "Feature",
  "properties": {
    "gn:admin1_code":"51",
    "gn:asciiname":"Nagornoye",
    "gn:cc2":"RU",
    "gn:country_code":"RU",
    "gn:dem":93,
    "gn:feature_class":"P",
    "gn:feature_code":"PPL",
    "gn:name":"Nagornoye",
    "gn:population":0,
    "gn:timezone":"Europe/Moscow",
    "iso:country":"RU",
    "name:rus_x_preferred":[
        "\u041d\u0430\u0433\u043e\u0440\u043d\u043e\u0435"
    ],
    "name:und_x_variant":[
        "Durashikha",
        "Nagornoye"
    ],
    "wof:name":"Nagornoye",
    "wof:placetype":"locality"
},
  "geometry": {"coordinates":[45.43333,56.83333],"type":"Point"}
}