{
  "type": "Feature",
  "properties": {
    "gn:admin1_code":"55",
    "gn:asciiname":"Novosomarskiy",
    "gn:country_code":"RU",
    "gn:dem":291,
    "gn:feature_class":"P",
    "gn:feature_code":"PPL",
    "gn:name":"Novosomarskiy",
    "gn:population":0,
    "gn:timezone":"Asia/Yekaterinburg",
    "iso:country":"RU",
    "name:rus_x_preferred":[
        "\u041d\u043e\u0432\u043e\u0441\u043e\u043c\u0430\u0440\u0441\u043a\u0438\u0439"
    ],
    "name:und_x_variant":[
        "\u041d\u043e\u0432\u043e\u0441\u043e\u043c\u0430\u0440\u0441\u043a\u0438\u0439"
    ],
    "wof:name":"Novosomarskiy",
    "wof:placetype":"locality"
},
  "geometry": {"coordinates":[56.75,51.58333],"type":"Point"}
}