{
  "type": "Feature",
  "properties": {
    "gn:admin1_code":"21.0",
    "gn:asciiname":"Krapivki",
    "gn:country_code":"RU",
    "gn:dem":144,
    "gn:feature_class":"P",
    "gn:feature_code":"PPL",
    "gn:name":"Krapivki",
    "gn:population":0,
    "gn:timezone":"Europe/Moscow",
    "iso:country":"RU",
    "name:rus_x_preferred":[
        "\u041a\u0440\u0430\u043f\u0438\u0432\u043a\u0438"
    ],
    "wof:name":"Krapivki",
    "wof:placetype":"locality"
},
  "geometry": {"coordinates":[41.7651,57.57924000000001],"type":"Point"}
}