{
  "type": "Feature",
  "properties": {
    "gn:admin1_code":"61.0",
    "gn:asciiname":"Lichnyy Trud",
    "gn:country_code":"RU",
    "gn:dem":150,
    "gn:feature_class":"P",
    "gn:feature_code":"PPL",
    "gn:name":"Lichnyy Trud",
    "gn:population":0,
    "gn:timezone":"Europe/Moscow",
    "iso:country":"RU",
    "name:rus_x_preferred":[
        "\u041b\u0438\u0447\u043d\u044b\u0439 \u0422\u0440\u0443\u0434"
    ],
    "wof:name":"Lichnyy Trud",
    "wof:placetype":"locality"
},
  "geometry": {"coordinates":[39.8301,47.80217],"type":"Point"}
}