{
  "type": "Feature",
  "properties": {
    "gn:admin1_code":"70",
    "gn:asciiname":"Novokanovo",
    "gn:country_code":"RU",
    "gn:dem":186,
    "gn:feature_class":"P",
    "gn:feature_code":"PPL",
    "gn:name":"Novokanovo",
    "gn:population":0,
    "gn:timezone":"Europe/Moscow",
    "iso:country":"RU",
    "name:rus_x_preferred":[
        "\u041d\u043e\u0432\u043e\u043a\u0430\u043d\u043e\u0432\u043e"
    ],
    "wof:name":"Novokanovo",
    "wof:placetype":"locality"
},
  "geometry": {"coordinates":[44.37667,44.12917],"type":"Point"}
}