{
  "type": "Feature",
  "properties": {
    "gn:admin1_code":"73",
    "gn:asciiname":"Novoye Min'kino",
    "gn:country_code":"RU",
    "gn:dem":59,
    "gn:feature_class":"P",
    "gn:feature_code":"PPL",
    "gn:name":"Novoye Min\u2019kino",
    "gn:population":0,
    "gn:timezone":"Europe/Moscow",
    "iso:country":"RU",
    "name:rus_x_preferred":[
        "\u041d\u043e\u0432\u043e\u0435 \u041c\u0438\u043d\u044c\u043a\u0438\u043d\u043e"
    ],
    "name:und_x_variant":[
        "Novoye Min\u2019kino",
        "\u041d\u043e\u0432\u043e\u0435 \u041c\u0438\u043d\u044c\u043a\u0438\u043d\u043e"
    ],
    "wof:name":"Novoye Min'kino",
    "wof:placetype":"locality"
},
  "geometry": {"coordinates":[51.6391,55.5457],"type":"Point"}
}