{
  "type": "Feature",
  "properties": {
    "gn:admin1_code":"45",
    "gn:asciiname":"Kuplonginskiy",
    "gn:country_code":"RU",
    "gn:dem":96,
    "gn:feature_class":"P",
    "gn:feature_code":"PPL",
    "gn:name":"Kuplonginskiy",
    "gn:population":0,
    "gn:timezone":"Europe/Moscow",
    "iso:country":"RU",
    "name:rus_x_preferred":[
        "\u041a\u0443\u043f\u043b\u043e\u043d\u0433\u0438\u043d\u0441\u043a\u0438\u0439"
    ],
    "name:und_x_variant":[
        "\u041a\u0443\u043f\u043b\u043e\u043d\u0433\u0438\u043d\u0441\u043a\u0438\u0439"
    ],
    "wof:name":"Kuplonginskiy",
    "wof:placetype":"locality"
},
  "geometry": {"coordinates":[47.06137,56.38602],"type":"Point"}
}