{
  "type": "Feature",
  "properties": {
    "gn:admin1_code":"29",
    "gn:asciiname":"Ust'-Yura",
    "gn:country_code":"RU",
    "gn:dem":174,
    "gn:feature_class":"P",
    "gn:feature_code":"PPL",
    "gn:name":"Ust'-Yura",
    "gn:population":0,
    "gn:timezone":"Asia/Novokuznetsk",
    "iso:country":"RU",
    "wof:name":"Ust'-Yura",
    "wof:placetype":"locality"
},
  "geometry": {"coordinates":[88.05,56.13333000000001],"type":"Point"}
}