{
  "type": "Feature",
  "properties": {
    "gn:admin1_code":"29",
    "gn:asciiname":"Chernyy Etap",
    "gn:cc2":"RU",
    "gn:country_code":"RU",
    "gn:dem":165,
    "gn:feature_class":"P",
    "gn:feature_code":"PPL",
    "gn:name":"Ch\u00ebrnyy Etap",
    "gn:population":0,
    "gn:timezone":"Asia/Novokuznetsk",
    "iso:country":"RU",
    "name:eng_x_preferred":[
        "Ch\u00ebrnyy Etap"
    ],
    "name:nor_x_preferred":[
        "Tsjernyj Etap"
    ],
    "name:rus_x_preferred":[
        "\u0427\u0435\u0440\u043d\u044b\u0439 \u042d\u0442\u0430\u043f"
    ],
    "name:rus_x_variant":[
        "\u0427\u0451\u0440\u043d\u044b\u0439 \u042d\u0442\u0430\u043f"
    ],
    "name:und_x_variant":[
        "Cherny Etap",
        "Ch\u00ebrnyy Etap",
        "\u0427\u0451\u0440\u043d\u044b\u0439 \u042d\u0442\u0430\u043f"
    ],
    "wof:name":"Chernyy Etap",
    "wof:placetype":"locality"
},
  "geometry": {"coordinates":[87.43333,54.53333000000001],"type":"Point"}
}