{
  "type": "Feature",
  "properties": {
    "gn:admin1_code":"52",
    "gn:asciiname":"Libunitsy",
    "gn:country_code":"RU",
    "gn:dem":63,
    "gn:feature_class":"P",
    "gn:feature_code":"PPL",
    "gn:name":"Libunitsy",
    "gn:population":0,
    "gn:timezone":"Europe/Moscow",
    "iso:country":"RU",
    "name:eng_x_preferred":[
        "Libunitsy"
    ],
    "name:nor_x_preferred":[
        "Ljubunitsy"
    ],
    "name:rus_x_preferred":[
        "\u041b\u044e\u0431\u0443\u043d\u0438\u0446\u044b"
    ],
    "name:rus_x_variant":[
        "\u041b\u0438\u0431\u0443\u043d\u0438\u0446\u044b"
    ],
    "name:und_x_variant":[
        "Lyubunitsy"
    ],
    "wof:name":"Libunitsy",
    "wof:placetype":"locality"
},
  "geometry": {"coordinates":[30.89708,58.7416],"type":"Point"}
}