{
  "type": "Feature",
  "properties": {
    "gn:admin1_code":"93",
    "gn:asciiname":"Novodoroninskoye",
    "gn:country_code":"RU",
    "gn:dem":796,
    "gn:feature_class":"P",
    "gn:feature_code":"PPL",
    "gn:name":"Novodoroninskoye",
    "gn:population":0,
    "gn:timezone":"Asia/Chita",
    "iso:country":"RU",
    "name:rus_x_preferred":[
        "\u041d\u043e\u0432\u043e\u0434\u043e\u0440\u043e\u043d\u0438\u043d\u0441\u043a\u043e\u0435"
    ],
    "name:und_x_variant":[
        "Novoye Doronino",
        "Novo-Doronino",
        "Novodoroninskoye"
    ],
    "wof:name":"Novodoroninskoye",
    "wof:placetype":"locality"
},
  "geometry": {"coordinates":[112.14019999999999,51.12723],"type":"Point"}
}