{
  "type": "Feature",
  "properties": {
    "gn:admin1_code":"8",
    "gn:asciiname":"Novobogazy",
    "gn:country_code":"RU",
    "gn:dem":214,
    "gn:feature_class":"P",
    "gn:feature_code":"PPL",
    "gn:name":"Novobogazy",
    "gn:population":0,
    "gn:timezone":"Asia/Yekaterinburg",
    "iso:country":"RU",
    "name:rus_x_preferred":[
        "\u041d\u043e\u0432\u043e\u0431\u043e\u0433\u0430\u0437\u044b"
    ],
    "name:und_x_variant":[
        "Novyye Bogazy",
        "Novobogazy"
    ],
    "wof:name":"Novobogazy",
    "wof:placetype":"locality"
},
  "geometry": {"coordinates":[56.70545,56.00311],"type":"Point"}
}