{
  "type": "Feature",
  "properties": {
    "gn:admin1_code":"90",
    "gn:asciiname":"Chan'sher",
    "gn:country_code":"RU",
    "gn:dem":162,
    "gn:feature_class":"P",
    "gn:feature_code":"PPL",
    "gn:name":"Chan\u2019sher",
    "gn:population":0,
    "gn:timezone":"Asia/Yekaterinburg",
    "iso:country":"RU",
    "name:rus_x_preferred":[
        "\u0427\u0430\u043d\u044c\u0448\u0435\u0440"
    ],
    "name:und_x_variant":[
        "Chen\u2019shor",
        "Chan\u2019sher",
        "\u0427\u0430\u043d\u044c\u0448\u0435\u0440"
    ],
    "wof:name":"Chan'sher",
    "wof:placetype":"locality"
},
  "geometry": {"coordinates":[54.91837,58.45685],"type":"Point"}
}