{
  "type": "Feature",
  "properties": {
    "gn:admin1_code":"86.0",
    "gn:asciiname":"Dubovyy",
    "gn:country_code":"RU",
    "gn:dem":145,
    "gn:feature_class":"P",
    "gn:feature_code":"PPL",
    "gn:name":"Dubovyy",
    "gn:population":0,
    "gn:timezone":"Europe/Moscow",
    "iso:country":"RU",
    "name:rus_x_preferred":[
        "\u0414\u0443\u0431\u043e\u0432\u044b\u0439"
    ],
    "name:und_x_variant":[
        "\u0414\u0443\u0431\u043e\u0432\u044b\u0439"
    ],
    "wof:name":"Dubovyy",
    "wof:placetype":"locality"
},
  "geometry": {"coordinates":[40.6183,51.1514],"type":"Point"}
}