{
  "type": "Feature",
  "properties": {
    "gn:admin1_code":"65",
    "gn:asciiname":"Sredneyagodnyy",
    "gn:country_code":"RU",
    "gn:dem":90,
    "gn:feature_class":"P",
    "gn:feature_code":"PPL",
    "gn:name":"Sredneyagodnyy",
    "gn:population":0,
    "gn:timezone":"Europe/Samara",
    "iso:country":"RU",
    "name:rus_x_preferred":[
        "\u0421\u0440\u0435\u0434\u043d\u0435\u044f\u0433\u043e\u0434\u043d\u044b\u0439"
    ],
    "name:und_x_variant":[
        "\u0421\u0440\u0435\u0434\u043d\u0435\u044f\u0433\u043e\u0434\u043d\u044b\u0439",
        "Sredneyagodnoye"
    ],
    "wof:name":"Sredneyagodnyy",
    "wof:placetype":"locality"
},
  "geometry": {"coordinates":[51.8286,53.5723],"type":"Point"}
}