{
  "type": "Feature",
  "properties": {
    "gn:admin1_code":"13",
    "gn:asciiname":"Bol'shakovo",
    "gn:country_code":"RU",
    "gn:dem":307,
    "gn:feature_class":"P",
    "gn:feature_code":"PPL",
    "gn:name":"Bol\u2019shakovo",
    "gn:population":0,
    "gn:timezone":"Asia/Yekaterinburg",
    "iso:country":"RU",
    "name:eng_x_preferred":[
        "Bol'shakovo"
    ],
    "name:nor_x_preferred":[
        "Bolsjakovo"
    ],
    "name:rus_x_preferred":[
        "\u0411\u043e\u043b\u044c\u0448\u0430\u043a\u043e\u0432\u043e"
    ],
    "name:und_x_variant":[
        "Bol\u2019shakovo"
    ],
    "wof:name":"Bol'shakovo",
    "wof:placetype":"locality"
},
  "geometry": {"coordinates":[60.4258,54.6475],"type":"Point"}
}