{
  "type": "Feature",
  "properties": {
    "gn:admin1_code":"63",
    "gn:asciiname":"Delyankirskiy",
    "gn:country_code":"RU",
    "gn:dem":835,
    "gn:feature_class":"P",
    "gn:feature_code":"PPL",
    "gn:name":"Delyankirskiy",
    "gn:population":0,
    "gn:timezone":"Asia/Magadan",
    "iso:country":"RU",
    "name:rus_x_preferred":[
        "\u0414\u0435\u043b\u044f\u043d\u043a\u0438\u0440\u0441\u043a\u0438\u0439"
    ],
    "name:und_x_variant":[
        "\u0414\u0435\u043b\u044f\u043d\u043a\u0438\u0440\u0441\u043a\u0438\u0439"
    ],
    "wof:name":"Delyankirskiy",
    "wof:placetype":"locality"
},
  "geometry": {"coordinates":[145.59999999999999,63.85],"type":"Point"}
}