{
  "type": "Feature",
  "properties": {
    "gn:admin1_code":"10",
    "gn:asciiname":"Kirpichnyy Zavod",
    "gn:country_code":"RU",
    "gn:dem":154,
    "gn:feature_class":"P",
    "gn:feature_code":"PPL",
    "gn:name":"Kirpichnyy Zavod",
    "gn:population":0,
    "gn:timezone":"Europe/Moscow",
    "iso:country":"RU",
    "name:rus_x_preferred":[
        "\u041a\u0438\u0440\u043f\u0438\u0447\u043d\u044b\u0439 \u0417\u0430\u0432\u043e\u0434"
    ],
    "name:und_x_variant":[
        "\u041a\u0438\u0440\u043f\u0438\u0447\u043d\u044b\u0439 \u0417\u0430\u0432\u043e\u0434"
    ],
    "wof:name":"Kirpichnyy Zavod",
    "wof:placetype":"locality"
},
  "geometry": {"coordinates":[33.5326,52.9042],"type":"Point"}
}