{
  "type": "Feature",
  "properties": {
    "gn:admin1_code":"93",
    "gn:asciiname":"Arenur",
    "gn:country_code":"RU",
    "gn:dem":897,
    "gn:feature_class":"P",
    "gn:feature_code":"PPL",
    "gn:name":"Arenur",
    "gn:population":0,
    "gn:timezone":"Asia/Chita",
    "iso:country":"RU",
    "name:eng_x_preferred":[
        "Arenur"
    ],
    "name:nor_x_preferred":[
        "Arenur"
    ],
    "name:rus_x_preferred":[
        "\u0410\u0440\u0435\u043d\u0443\u0440"
    ],
    "wof:name":"Arenur",
    "wof:placetype":"locality"
},
  "geometry": {"coordinates":[111.42115,51.37688],"type":"Point"}
}