{
  "type": "Feature",
  "properties": {
    "gn:admin1_code":"47",
    "gn:asciiname":"Ledovo",
    "gn:country_code":"RU",
    "gn:dem":151,
    "gn:feature_class":"P",
    "gn:feature_code":"PPL",
    "gn:name":"Ledovo",
    "gn:population":0,
    "gn:timezone":"Europe/Moscow",
    "iso:country":"RU",
    "name:rus_x_preferred":[
        "\u041b\u0435\u0434\u043e\u0432\u043e"
    ],
    "wof:name":"Ledovo",
    "wof:placetype":"locality"
},
  "geometry": {"coordinates":[38.4892,54.99346],"type":"Point"}
}