{
  "type": "Feature",
  "properties": {
    "gn:admin1_code":"41",
    "gn:asciiname":"Borenkov",
    "gn:country_code":"RU",
    "gn:dem":180,
    "gn:feature_class":"P",
    "gn:feature_code":"PPL",
    "gn:name":"Borenkov",
    "gn:population":0,
    "gn:timezone":"Europe/Moscow",
    "iso:country":"RU",
    "name:rus_x_preferred":[
        "\u0411\u043e\u0440\u0435\u043d\u043a\u043e\u0432"
    ],
    "wof:name":"Borenkov",
    "wof:placetype":"locality"
},
  "geometry": {"coordinates":[35.14667,52.24194],"type":"Point"}
}