{
  "type": "Feature",
  "properties": {
    "gn:admin1_code":"51.0",
    "gn:asciiname":"Krasnoye Pleso",
    "gn:country_code":"RU",
    "gn:dem":90,
    "gn:feature_class":"P",
    "gn:feature_code":"PPL",
    "gn:name":"Krasnoye Pleso",
    "gn:population":0,
    "gn:timezone":"Europe/Moscow",
    "iso:country":"RU",
    "wof:name":"Krasnoye Pleso",
    "wof:placetype":"locality"
},
  "geometry": {"coordinates":[44.65844,56.66675],"type":"Point"}
}