{
  "type": "Feature",
  "properties": {
    "gn:admin1_code":"25",
    "gn:asciiname":"Sezhikovo",
    "gn:country_code":"RU",
    "gn:dem":232,
    "gn:feature_class":"P",
    "gn:feature_code":"PPL",
    "gn:name":"Sezhikovo",
    "gn:population":0,
    "gn:timezone":"Europe/Moscow",
    "iso:country":"RU",
    "name:rus_x_preferred":[
        "\u0421\u0435\u0436\u0438\u043a\u043e\u0432\u043e"
    ],
    "wof:name":"Sezhikovo",
    "wof:placetype":"locality"
},
  "geometry": {"coordinates":[34.07508,54.4425],"type":"Point"}
}