{
  "type": "Feature",
  "properties": {
    "gn:admin1_code":"20",
    "gn:asciiname":"Kiyevskiy",
    "gn:country_code":"RU",
    "gn:dem":357,
    "gn:feature_class":"P",
    "gn:feature_code":"PPL",
    "gn:name":"Kiyevskiy",
    "gn:population":0,
    "gn:timezone":"Asia/Irkutsk",
    "iso:country":"RU",
    "name:rus_x_preferred":[
        "\u041a\u0438\u0435\u0432\u0441\u043a\u0438\u0439"
    ],
    "name:und_x_variant":[
        "\u041a\u0438\u0435\u0432\u0441\u043a\u0438\u0439"
    ],
    "wof:name":"Kiyevskiy",
    "wof:placetype":"locality"
},
  "geometry": {"coordinates":[99.01667,55.68333000000001],"type":"Point"}
}