{
  "type": "Feature",
  "properties": {
    "gn:admin1_code":"8",
    "gn:asciiname":"Baltino",
    "gn:country_code":"RU",
    "gn:dem":112,
    "gn:feature_class":"P",
    "gn:feature_code":"PPL",
    "gn:name":"Baltino",
    "gn:population":0,
    "gn:timezone":"Asia/Yekaterinburg",
    "iso:country":"RU",
    "name:rus_x_preferred":[
        "\u0411\u0430\u043b\u0442\u0438\u043d\u043e"
    ],
    "name:und_x_variant":[
        "\u0411\u0430\u043b\u0442\u0438\u043d\u043e"
    ],
    "wof:name":"Baltino",
    "wof:placetype":"locality"
},
  "geometry": {"coordinates":[56.0253,54.4758],"type":"Point"}
}