{
  "type": "Feature",
  "properties": {
    "gn:admin1_code":"4.0",
    "gn:asciiname":"Berezovka",
    "gn:country_code":"RU",
    "gn:dem":251,
    "gn:feature_class":"P",
    "gn:feature_code":"PPL",
    "gn:name":"Ber\u00ebzovka",
    "gn:population":0,
    "gn:timezone":"Asia/Barnaul",
    "iso:country":"RU",
    "name:rus_x_preferred":[
        "\u0411\u0435\u0440\u0451\u0437\u043e\u0432\u043a\u0430"
    ],
    "name:und_x_variant":[
        "Ber\u00ebzovka"
    ],
    "wof:name":"Berezovka",
    "wof:placetype":"locality"
},
  "geometry": {"coordinates":[81.7754,52.1992],"type":"Point"}
}