{
  "type": "Feature",
  "properties": {
    "iso:country":"RU",
    "qs:name":"Bol. Vyazemy",
    "qs:name_adm0":"Russia",
    "qs:name_adm1":"Moscow Oblast",
    "qs:photos":22,
    "qs:photos_1k":4,
    "qs:photos_9k":1,
    "qs:photos_9r":1,
    "qs:photos_all":22,
    "qs:photos_sr":1,
    "qs:placetype":"Town",
    "qs:pop_sr":"0",
    "wof:name":"Bol. Vyazemy",
    "wof:placetype":"locality"
},
  "geometry": {"coordinates":[36.9836705,55.629982],"type":"Point"}
}