{
  "type": "Feature",
  "properties": {
    "gn:admin1_code":"41.0",
    "gn:asciiname":"Melvedkov Kolodez",
    "gn:country_code":"RU",
    "gn:dem":191,
    "gn:feature_class":"P",
    "gn:feature_code":"PPL",
    "gn:name":"Melvedkov Kolodez",
    "gn:population":0,
    "gn:timezone":"Europe/Moscow",
    "iso:country":"RU",
    "wof:name":"Melvedkov Kolodez",
    "wof:placetype":"locality"
},
  "geometry": {"coordinates":[36.69983,51.80009],"type":"Point"}
}