{
  "type": "Feature",
  "properties": {
    "gn:admin1_code":"88",
    "gn:asciiname":"Beleshino",
    "gn:country_code":"RU",
    "gn:dem":147,
    "gn:feature_class":"P",
    "gn:feature_code":"PPL",
    "gn:name":"Beleshino",
    "gn:population":0,
    "gn:timezone":"Europe/Moscow",
    "iso:country":"RU",
    "name:rus_x_preferred":[
        "\u0411\u0435\u043b\u0435\u0448\u0438\u043d\u043e"
    ],
    "wof:name":"Beleshino",
    "wof:placetype":"locality"
},
  "geometry": {"coordinates":[39.52589,57.71869],"type":"Point"}
}