{
  "type": "Feature",
  "properties": {
    "gn:admin1_code":"33",
    "gn:asciiname":"Peschanka",
    "gn:country_code":"RU",
    "gn:dem":166,
    "gn:feature_class":"P",
    "gn:feature_code":"PPL",
    "gn:name":"Peschanka",
    "gn:population":0,
    "gn:timezone":"Europe/Kirov",
    "iso:country":"RU",
    "name:eng_x_preferred":[
        "Peschanka"
    ],
    "name:nor_x_preferred":[
        "Pestsjanka"
    ],
    "name:rus_x_preferred":[
        "\u041f\u0435\u0441\u0447\u0430\u043d\u043a\u0430"
    ],
    "wof:name":"Peschanka",
    "wof:placetype":"locality"
},
  "geometry": {"coordinates":[51.06407,58.93024000000001],"type":"Point"}
}