{
  "type": "Feature",
  "properties": {
    "gn:admin1_code":"90",
    "gn:asciiname":"Plishkari",
    "gn:country_code":"RU",
    "gn:dem":181,
    "gn:feature_class":"P",
    "gn:feature_code":"PPL",
    "gn:name":"Plishkari",
    "gn:population":0,
    "gn:timezone":"Asia/Yekaterinburg",
    "iso:country":"RU",
    "name:eng_x_preferred":[
        "Plishkari"
    ],
    "name:nor_x_preferred":[
        "Plisjkari"
    ],
    "name:rus_x_preferred":[
        "\u041f\u043b\u0438\u0448\u043a\u0430\u0440\u0438"
    ],
    "name:und_x_variant":[
        "\u041f\u043b\u0438\u0448\u043a\u0430\u0440\u0438"
    ],
    "wof:name":"Plishkari",
    "wof:placetype":"locality"
},
  "geometry": {"coordinates":[55.0738,56.9995],"type":"Point"}
}