{
  "type": "Feature",
  "properties": {
    "gn:admin1_code":"69",
    "gn:asciiname":"Yurechets",
    "gn:country_code":"RU",
    "gn:dem":206,
    "gn:feature_class":"P",
    "gn:feature_code":"PPL",
    "gn:name":"Yurechets",
    "gn:population":0,
    "gn:timezone":"Europe/Moscow",
    "iso:country":"RU",
    "name:rus_x_preferred":[
        "\u042e\u0440\u0435\u0447\u0435\u0446"
    ],
    "wof:name":"Yurechets",
    "wof:placetype":"locality"
},
  "geometry": {"coordinates":[32.664,55.4516],"type":"Point"}
}