{
  "type": "Feature",
  "properties": {
    "gn:admin1_code":"69.0",
    "gn:asciiname":"Dernovo",
    "gn:cc2":"RU",
    "gn:country_code":"RU",
    "gn:dem":266,
    "gn:feature_class":"P",
    "gn:feature_code":"PPL",
    "gn:name":"Dernovo",
    "gn:population":0,
    "gn:timezone":"Europe/Moscow",
    "iso:country":"RU",
    "name:rus_x_preferred":[
        "\u0414\u0435\u0440\u043d\u043e\u0432\u043e"
    ],
    "name:und_x_variant":[
        "Dernov",
        "Dernova",
        "Dernovo"
    ],
    "wof:name":"Dernovo",
    "wof:placetype":"locality"
},
  "geometry": {"coordinates":[33.96139,55.43972],"type":"Point"}
}