{
  "type": "Feature",
  "properties": {
    "gn:admin1_code":"10",
    "gn:asciiname":"Ozerishche",
    "gn:country_code":"RU",
    "gn:dem":156,
    "gn:feature_class":"P",
    "gn:feature_code":"PPL",
    "gn:name":"Oz\u00ebrishche",
    "gn:population":0,
    "gn:timezone":"Europe/Moscow",
    "iso:country":"RU",
    "name:rus_x_preferred":[
        "\u041e\u0437\u00eb\u0440\u0438\u0449\u0435"
    ],
    "name:und_x_variant":[
        "Oz\u00ebrishche"
    ],
    "wof:name":"Ozerishche",
    "wof:placetype":"locality"
},
  "geometry": {"coordinates":[31.7534,52.331],"type":"Point"}
}