{
  "type": "Feature",
  "properties": {
    "gn:admin1_code":"60",
    "gn:asciiname":"Mikushkino",
    "gn:country_code":"RU",
    "gn:dem":159,
    "gn:feature_class":"P",
    "gn:feature_code":"PPL",
    "gn:name":"Mikushkino",
    "gn:population":0,
    "gn:timezone":"Europe/Moscow",
    "iso:country":"RU",
    "name:rus_x_preferred":[
        "\u041c\u0438\u043a\u0443\u0448\u043a\u0438\u043d\u043e"
    ],
    "name:und_x_variant":[
        "\u041c\u0438\u043a\u0443\u0448\u043a\u0438\u043d\u043e"
    ],
    "wof:name":"Mikushkino",
    "wof:placetype":"locality"
},
  "geometry": {"coordinates":[30.9212,56.0318],"type":"Point"}
}