{
  "type": "Feature",
  "properties": {
    "gn:admin1_code":"43",
    "gn:asciiname":"Sezenovo Pervoye",
    "gn:country_code":"RU",
    "gn:dem":183,
    "gn:feature_class":"P",
    "gn:feature_code":"PPL",
    "gn:name":"Sezenovo Pervoye",
    "gn:population":0,
    "gn:timezone":"Europe/Moscow",
    "iso:country":"RU",
    "name:rus_x_preferred":[
        "\u0421\u0435\u0437\u0435\u043d\u043e\u0432\u043e \u041f\u0435\u0440\u0432\u043e\u0435"
    ],
    "name:und_x_variant":[
        "\u0421\u0435\u0437\u0435\u043d\u043e\u0432\u043e \u041f\u0435\u0440\u0432\u043e\u0435",
        "Sezenovo"
    ],
    "wof:name":"Sezenovo Pervoye",
    "wof:placetype":"locality"
},
  "geometry": {"coordinates":[39.34154,53.09314000000001],"type":"Point"}
}