{
  "type": "Feature",
  "properties": {
    "gn:admin1_code":"38",
    "gn:asciiname":"Zapadnyy",
    "gn:country_code":"RU",
    "gn:dem":7,
    "gn:feature_class":"P",
    "gn:feature_code":"PPL",
    "gn:name":"Zapadnyy",
    "gn:population":0,
    "gn:timezone":"Europe/Moscow",
    "iso:country":"RU",
    "wof:name":"Zapadnyy",
    "wof:placetype":"locality"
},
  "geometry": {"coordinates":[38.85,46.35],"type":"Point"}
}