{
  "type": "Feature",
  "properties": {
    "gn:admin1_code":"77",
    "gn:asciiname":"Nekrasovo",
    "gn:country_code":"RU",
    "gn:dem":145,
    "gn:feature_class":"P",
    "gn:feature_code":"PPL",
    "gn:name":"Nekrasovo",
    "gn:population":0,
    "gn:timezone":"Europe/Moscow",
    "iso:country":"RU",
    "name:eng_x_preferred":[
        "Nekrasovo"
    ],
    "name:nor_x_preferred":[
        "Nekrasovo"
    ],
    "name:rus_x_preferred":[
        "\u041d\u0435\u043a\u0440\u0430\u0441\u043e\u0432\u043e"
    ],
    "name:und_x_variant":[
        "Nosilovo",
        "\u041d\u0435\u043a\u0440\u0430\u0441\u043e\u0432\u043e",
        "Nekrasovo"
    ],
    "wof:name":"Nekrasovo",
    "wof:placetype":"locality"
},
  "geometry": {"coordinates":[36.69194,57.37639],"type":"Point"}
}