{
  "type": "Feature",
  "properties": {
    "gn:admin1_code":"69",
    "gn:asciiname":"Triputino",
    "gn:country_code":"RU",
    "gn:dem":171,
    "gn:feature_class":"P",
    "gn:feature_code":"PPL",
    "gn:name":"Triputino",
    "gn:population":0,
    "gn:timezone":"Europe/Moscow",
    "iso:country":"RU",
    "name:rus_x_preferred":[
        "\u0422\u0440\u0438\u043f\u0443\u0442\u0438\u043d\u043e"
    ],
    "wof:name":"Triputino",
    "wof:placetype":"locality"
},
  "geometry": {"coordinates":[32.1234,54.14011],"type":"Point"}
}