{
  "type": "Feature",
  "properties": {
    "gn:admin1_code":"43",
    "gn:asciiname":"Kolousovka",
    "gn:country_code":"RU",
    "gn:dem":121,
    "gn:feature_class":"P",
    "gn:feature_code":"PPL",
    "gn:name":"Kolousovka",
    "gn:population":0,
    "gn:timezone":"Europe/Moscow",
    "iso:country":"RU",
    "name:rus_x_preferred":[
        "\u041a\u043e\u043b\u043e\u0443\u0441\u043e\u0432\u043a\u0430"
    ],
    "wof:name":"Kolousovka",
    "wof:placetype":"locality"
},
  "geometry": {"coordinates":[40.1005,52.4663],"type":"Point"}
}