{
  "type": "Feature",
  "properties": {
    "gn:admin1_code":"54",
    "gn:asciiname":"Panovo",
    "gn:country_code":"RU",
    "gn:dem":84,
    "gn:feature_class":"P",
    "gn:feature_code":"PPL",
    "gn:name":"Panovo",
    "gn:population":0,
    "gn:timezone":"Asia/Omsk",
    "iso:country":"RU",
    "name:eng_x_preferred":[
        "Panovo"
    ],
    "name:nor_x_preferred":[
        "Panovo"
    ],
    "name:rus_x_preferred":[
        "\u041f\u0430\u043d\u043e\u0432\u043e"
    ],
    "name:und_x_variant":[
        "\u041f\u0430\u043d\u043e\u0432\u043e",
        "Panovo"
    ],
    "wof:name":"Panovo",
    "wof:placetype":"locality"
},
  "geometry": {"coordinates":[70.96899999999999,56.3525],"type":"Point"}
}