{
  "type": "Feature",
  "properties": {
    "gn:admin1_code":"52",
    "gn:asciiname":"Ottenskiy",
    "gn:country_code":"RU",
    "gn:dem":57,
    "gn:feature_class":"P",
    "gn:feature_code":"PPL",
    "gn:name":"Ottenskiy",
    "gn:population":0,
    "gn:timezone":"Europe/Moscow",
    "iso:country":"RU",
    "name:rus_x_preferred":[
        "\u041e\u0442\u0442\u0435\u043d\u0441\u043a\u0438\u0439"
    ],
    "name:und_x_variant":[
        "\u041e\u0442\u0442\u0435\u043d\u0441\u043a\u0438\u0439"
    ],
    "wof:name":"Ottenskiy",
    "wof:placetype":"locality"
},
  "geometry": {"coordinates":[31.71667,58.73333],"type":"Point"}
}