{
  "type": "Feature",
  "properties": {
    "gn:admin1_code":"52",
    "gn:asciiname":"Apanitsy",
    "gn:country_code":"RU",
    "gn:dem":187,
    "gn:feature_class":"P",
    "gn:feature_code":"PPL",
    "gn:name":"Apanitsy",
    "gn:population":0,
    "gn:timezone":"Europe/Moscow",
    "iso:country":"RU",
    "name:rus_x_preferred":[
        "\u0410\u043f\u0430\u043d\u0438\u0446\u044b"
    ],
    "wof:name":"Apanitsy",
    "wof:placetype":"locality"
},
  "geometry": {"coordinates":[32.9617,57.9066],"type":"Point"}
}