{
  "type": "Feature",
  "properties": {
    "gn:admin1_code":"20",
    "gn:asciiname":"Ishidey",
    "gn:country_code":"RU",
    "gn:dem":564,
    "gn:feature_class":"P",
    "gn:feature_code":"PPL",
    "gn:name":"Ishidey",
    "gn:population":350,
    "gn:timezone":"Asia/Irkutsk",
    "iso:country":"RU",
    "name:eng_x_preferred":[
        "Ishidey"
    ],
    "name:nor_x_preferred":[
        "Isjidej"
    ],
    "name:rus_x_preferred":[
        "\u0418\u0448\u0438\u0434\u0435\u0439"
    ],
    "name:und_x_variant":[
        "\u0418\u0448\u0438\u0434\u0435\u0439",
        "Ishidey"
    ],
    "wof:name":"Ishidey",
    "wof:placetype":"locality",
    "wof:population":350
},
  "geometry": {"coordinates":[99.7162,54.1202],"type":"Point"}
}