{
  "type": "Feature",
  "properties": {
    "gn:admin1_code":"73.0",
    "gn:asciiname":"Chutay",
    "gn:country_code":"RU",
    "gn:dem":71,
    "gn:feature_class":"P",
    "gn:feature_code":"PPL",
    "gn:name":"Chutay",
    "gn:population":0,
    "gn:timezone":"Europe/Volgograd",
    "iso:country":"RU",
    "name:rus_x_preferred":[
        "\u0427\u0443\u0442\u0430\u0439"
    ],
    "name:und_x_variant":[
        "Chetay",
        "Chutay",
        "\u0427\u0443\u0442\u0430\u0439"
    ],
    "wof:name":"Chutay",
    "wof:placetype":"locality"
},
  "geometry": {"coordinates":[50.5123,56.5112],"type":"Point"}
}