{
  "type": "Feature",
  "properties": {
    "gn:admin1_code":"80.0",
    "gn:asciiname":"Nefedovo",
    "gn:country_code":"RU",
    "gn:dem":181,
    "gn:feature_class":"P",
    "gn:feature_code":"PPL",
    "gn:name":"Nef\u00ebdovo",
    "gn:population":0,
    "gn:timezone":"Europe/Samara",
    "iso:country":"RU",
    "name:rus_x_preferred":[
        "\u041d\u0435\u0444\u0451\u0434\u043e\u0432\u043e"
    ],
    "name:und_x_variant":[
        "Nef\u00ebdovo"
    ],
    "wof:name":"Nefedovo",
    "wof:placetype":"locality"
},
  "geometry": {"coordinates":[52.8128,57.7387],"type":"Point"}
}