{
  "type": "Feature",
  "properties": {
    "gn:admin1_code":"88",
    "gn:asciiname":"Semenkovo",
    "gn:country_code":"RU",
    "gn:dem":114,
    "gn:feature_class":"P",
    "gn:feature_code":"PPL",
    "gn:name":"Sem\u00ebnkovo",
    "gn:population":0,
    "gn:timezone":"Europe/Moscow",
    "iso:country":"RU",
    "name:rus_x_preferred":[
        "\u0421\u0435\u043c\u0451\u043d\u043a\u043e\u0432\u043e"
    ],
    "name:und_x_variant":[
        "Sem\u00ebnkovo"
    ],
    "wof:name":"Semenkovo",
    "wof:placetype":"locality"
},
  "geometry": {"coordinates":[40.81231,58.43442],"type":"Point"}
}