{
  "type": "Feature",
  "properties": {
    "gn:admin1_code":"28",
    "gn:asciiname":"Kokkosalma",
    "gn:country_code":"RU",
    "gn:dem":11,
    "gn:feature_class":"P",
    "gn:feature_code":"PPL",
    "gn:name":"Kokkosalma",
    "gn:population":0,
    "gn:timezone":"Europe/Moscow",
    "iso:country":"RU",
    "name:eng_x_preferred":[
        "Kokkosalma"
    ],
    "name:fin_x_preferred":[
        "Kokkosalmi"
    ],
    "name:nor_x_preferred":[
        "Kokkosalma"
    ],
    "name:rus_x_preferred":[
        "\u041a\u043e\u043a\u043a\u043e\u0441\u0430\u043b\u043c\u0430"
    ],
    "wof:name":"Kokkosalma",
    "wof:placetype":"locality"
},
  "geometry": {"coordinates":[34.66624,65.75972],"type":"Point"}
}