{
  "type": "Feature",
  "properties": {
    "gn:admin1_code":"24",
    "gn:asciiname":"Tselinnyy",
    "gn:country_code":"RU",
    "gn:dem":55,
    "gn:feature_class":"P",
    "gn:feature_code":"PPL",
    "gn:name":"Tselinnyy",
    "gn:population":0,
    "gn:timezone":"Europe/Moscow",
    "iso:country":"RU",
    "name:eng_x_preferred":[
        "Tselinnyy"
    ],
    "name:nor_x_preferred":[
        "Tselinnyj"
    ],
    "name:rus_x_preferred":[
        "\u0426\u0435\u043b\u0438\u043d\u043d\u044b\u0439"
    ],
    "name:und_x_variant":[
        "Stepnoy",
        "Stepnovskiy",
        "Tselinnyy"
    ],
    "wof:name":"Tselinnyy",
    "wof:placetype":"locality"
},
  "geometry": {"coordinates":[44.5235,46.664],"type":"Point"}
}