{
  "type": "Feature",
  "properties": {
    "gn:admin1_code":"4",
    "gn:asciiname":"Dzhantay",
    "gn:country_code":"RU",
    "gn:dem":157,
    "gn:feature_class":"P",
    "gn:feature_code":"PPL",
    "gn:name":"Dzhantay",
    "gn:population":0,
    "gn:timezone":"Asia/Barnaul",
    "iso:country":"RU",
    "name:rus_x_preferred":[
        "\u0414\u0436\u0430\u043d\u0442\u0430\u0439"
    ],
    "name:und_x_variant":[
        "\u0414\u0436\u0430\u043d\u0442\u0430\u0439"
    ],
    "wof:name":"Dzhantay",
    "wof:placetype":"locality"
},
  "geometry": {"coordinates":[79.48528,51.63583],"type":"Point"}
}