{
  "type": "Feature",
  "properties": {
    "gn:admin1_code":"10.0",
    "gn:asciiname":"Bol'shoye Akulovo",
    "gn:country_code":"RU",
    "gn:dem":236,
    "gn:feature_class":"P",
    "gn:feature_code":"PPL",
    "gn:name":"Bol\u2019shoye Akulovo",
    "gn:population":0,
    "gn:timezone":"Europe/Moscow",
    "iso:country":"RU",
    "name:rus_x_preferred":[
        "\u0411\u043e\u043b\u044c\u0448\u043e\u0435 \u0410\u043a\u0443\u043b\u043e\u0432\u043e"
    ],
    "name:und_x_variant":[
        "Bol\u2019shoye Akulovo",
        "\u0411\u043e\u043b\u044c\u0448\u043e\u0435 \u0410\u043a\u0443\u043b\u043e\u0432\u043e"
    ],
    "wof:name":"Bol'shoye Akulovo",
    "wof:placetype":"locality"
},
  "geometry": {"coordinates":[34.87139000000001,53.02472],"type":"Point"}
}