{
  "type": "Feature",
  "properties": {
    "gn:admin1_code":"20.0",
    "gn:asciiname":"Zangut",
    "gn:country_code":"RU",
    "gn:dem":687,
    "gn:feature_class":"P",
    "gn:feature_code":"PPL",
    "gn:name":"Zangut",
    "gn:population":0,
    "gn:timezone":"Asia/Irkutsk",
    "iso:country":"RU",
    "name:rus_x_preferred":[
        "\u0417\u0430\u043d\u0433\u0443\u0442"
    ],
    "wof:name":"Zangut",
    "wof:placetype":"locality"
},
  "geometry": {"coordinates":[105.6711,53.1321],"type":"Point"}
}