{
  "type": "Feature",
  "properties": {
    "gn:admin1_code":"56",
    "gn:asciiname":"Melynki",
    "gn:country_code":"RU",
    "gn:dem":191,
    "gn:feature_class":"P",
    "gn:feature_code":"PPL",
    "gn:name":"Melynki",
    "gn:population":0,
    "gn:timezone":"Europe/Moscow",
    "iso:country":"RU",
    "name:rus_x_preferred":[
        "\u041c\u0435\u043b\u044b\u043d\u043a\u0438"
    ],
    "wof:name":"Melynki",
    "wof:placetype":"locality"
},
  "geometry": {"coordinates":[35.77669,53.0074],"type":"Point"}
}