{
  "type": "Feature",
  "properties": {
    "gn:admin1_code":"77",
    "gn:asciiname":"Vas'kovo",
    "gn:country_code":"RU",
    "gn:dem":182,
    "gn:feature_class":"P",
    "gn:feature_code":"PPL",
    "gn:name":"Vas\u2019kovo",
    "gn:population":0,
    "gn:timezone":"Europe/Moscow",
    "iso:country":"RU",
    "name:rus_x_preferred":[
        "\u0412\u0430\u0441\u044c\u043a\u043e\u0432\u043e"
    ],
    "name:und_x_variant":[
        "Vas\u2019kovo"
    ],
    "wof:name":"Vas'kovo",
    "wof:placetype":"locality"
},
  "geometry": {"coordinates":[35.41321,58.09689],"type":"Point"}
}