{
  "type": "Feature",
  "properties": {
    "gn:admin1_code":"25",
    "gn:asciiname":"Zhelov'",
    "gn:country_code":"RU",
    "gn:dem":175,
    "gn:feature_class":"P",
    "gn:feature_code":"PPL",
    "gn:name":"Zhelov\u2019",
    "gn:population":0,
    "gn:timezone":"Europe/Moscow",
    "iso:country":"RU",
    "name:und_x_variant":[
        "Zh\u00eblovo",
        "Zhelov\u2019"
    ],
    "wof:name":"Zhelov'",
    "wof:placetype":"locality"
},
  "geometry": {"coordinates":[36.36139,54.34416],"type":"Point"}
}