{
  "type": "Feature",
  "properties": {
    "gn:admin1_code":"61",
    "gn:asciiname":"Imeni Sakko",
    "gn:cc2":"RU",
    "gn:country_code":"RU",
    "gn:dem":15,
    "gn:feature_class":"P",
    "gn:feature_code":"PPL",
    "gn:name":"Imeni Sakko",
    "gn:population":0,
    "gn:timezone":"Europe/Moscow",
    "iso:country":"RU",
    "name:rus_x_preferred":[
        "\u0418\u043c\u0435\u043d\u0438 \u0421\u0430\u043a\u043a\u043e"
    ],
    "name:und_x_variant":[
        "Khutor Imeni Sakko",
        "Imeni Sakko",
        "\u0418\u043c\u0435\u043d\u0438 \u0421\u0430\u043a\u043a\u043e"
    ],
    "wof:name":"Imeni Sakko",
    "wof:placetype":"locality"
},
  "geometry": {"coordinates":[38.98333,46.88333],"type":"Point"}
}