{
  "type": "Feature",
  "properties": {
    "gn:admin1_code":"33",
    "gn:asciiname":"Sochnevo",
    "gn:country_code":"RU",
    "gn:dem":192,
    "gn:feature_class":"P",
    "gn:feature_code":"PPL",
    "gn:name":"Sochnevo",
    "gn:population":0,
    "gn:timezone":"Europe/Kirov",
    "iso:country":"RU",
    "name:rus_x_preferred":[
        "\u0421\u043e\u0447\u043d\u0435\u0432\u043e"
    ],
    "wof:name":"Sochnevo",
    "wof:placetype":"locality"
},
  "geometry": {"coordinates":[50.7377,59.2888],"type":"Point"}
}