{
  "type": "Feature",
  "properties": {
    "gn:admin1_code":"17.0",
    "gn:asciiname":"Abdurashid",
    "gn:country_code":"RU",
    "gn:dem":22,
    "gn:feature_class":"P",
    "gn:feature_code":"PPL",
    "gn:name":"Abdurashid",
    "gn:population":0,
    "gn:timezone":"Europe/Moscow",
    "iso:country":"RU",
    "name:nor_x_preferred":[
        "Abdurasjid"
    ],
    "name:rus_x_preferred":[
        "\u0410\u0431\u0434\u0443\u0440\u0430\u0448\u0438\u0434"
    ],
    "name:und_x_variant":[
        "Abdrashit-Otar",
        "Abdurashid-Otar",
        "Abdurashid"
    ],
    "wof:name":"Abdurashid",
    "wof:placetype":"locality"
},
  "geometry": {"coordinates":[46.67183,43.38644],"type":"Point"}
}