{
  "type": "Feature",
  "properties": {
    "gn:admin1_code":"73",
    "gn:asciiname":"Tatarskiy Studenets",
    "gn:country_code":"RU",
    "gn:dem":119,
    "gn:feature_class":"P",
    "gn:feature_code":"PPL",
    "gn:name":"Tatarskiy Studenets",
    "gn:population":0,
    "gn:timezone":"Europe/Moscow",
    "iso:country":"RU",
    "name:rus_x_preferred":[
        "\u0422\u0430\u0442\u0430\u0440\u0441\u043a\u0438\u0439 \u0421\u0442\u0443\u0434\u0435\u043d\u0435\u0446"
    ],
    "wof:name":"Tatarskiy Studenets",
    "wof:placetype":"locality"
},
  "geometry": {"coordinates":[50.0458,54.8312],"type":"Point"}
}