{
  "type": "Feature",
  "properties": {
    "gn:admin1_code":"43.0",
    "gn:asciiname":"Fedyanino",
    "gn:country_code":"RU",
    "gn:dem":207,
    "gn:feature_class":"P",
    "gn:feature_code":"PPL",
    "gn:name":"Fedyanino",
    "gn:population":0,
    "gn:timezone":"Europe/Moscow",
    "iso:country":"RU",
    "name:rus_x_preferred":[
        "\u0424\u0435\u0434\u044f\u043d\u0438\u043d\u043e"
    ],
    "wof:name":"Fedyanino",
    "wof:placetype":"locality"
},
  "geometry": {"coordinates":[38.65982,53.00419],"type":"Point"}
}