{
  "type": "Feature",
  "properties": {
    "gn:admin1_code":"44",
    "gn:asciiname":"Merenga",
    "gn:country_code":"RU",
    "gn:dem":233,
    "gn:feature_class":"P",
    "gn:feature_code":"PPL",
    "gn:name":"Merenga",
    "gn:population":0,
    "gn:timezone":"Asia/Magadan",
    "iso:country":"RU",
    "name:eng_x_preferred":[
        "Merenga"
    ],
    "name:nor_x_preferred":[
        "Merenga"
    ],
    "name:rus_x_preferred":[
        "\u041c\u0435\u0440\u0435\u043d\u0433\u0430"
    ],
    "name:und_x_variant":[
        "\u041c\u0435\u0440\u0435\u043d\u0433\u0430",
        "Merenga"
    ],
    "wof:name":"Merenga",
    "wof:placetype":"locality"
},
  "geometry": {"coordinates":[156.13613000000001,61.89055],"type":"Point"}
}