{
  "type": "Feature",
  "properties": {
    "gn:admin1_code":"71",
    "gn:asciiname":"Sukhoyash",
    "gn:country_code":"RU",
    "gn:dem":325,
    "gn:feature_class":"P",
    "gn:feature_code":"PPL",
    "gn:name":"Sukhoyash",
    "gn:population":0,
    "gn:timezone":"Asia/Yekaterinburg",
    "iso:country":"RU",
    "name:rus_x_preferred":[
        "\u0421\u0443\u0445\u043e\u044f\u0448"
    ],
    "wof:name":"Sukhoyash",
    "wof:placetype":"locality"
},
  "geometry": {"coordinates":[58.78333000000001,56.33333],"type":"Point"}
}