{
  "type": "Feature",
  "properties": {
    "gn:admin1_code":"56",
    "gn:asciiname":"Nakhlestovo",
    "gn:country_code":"RU",
    "gn:dem":212,
    "gn:feature_class":"P",
    "gn:feature_code":"PPL",
    "gn:name":"Nakhl\u00ebstovo",
    "gn:population":0,
    "gn:timezone":"Europe/Moscow",
    "iso:country":"RU",
    "name:rus_x_preferred":[
        "\u041d\u0430\u0445\u043b\u0451\u0441\u0442\u043e\u0432\u043e"
    ],
    "name:und_x_variant":[
        "Nakhl\u00ebstovo",
        "\u041d\u0430\u0445\u043b\u0451\u0441\u0442\u043e\u0432\u043e"
    ],
    "wof:name":"Nakhlestovo",
    "wof:placetype":"locality"
},
  "geometry": {"coordinates":[36.35597,52.65259],"type":"Point"}
}