{
  "type": "Feature",
  "properties": {
    "gn:country":"RU",
    "gn:fcode":"PPL",
    "gn:population":300,
    "iso:country":"RU",
    "name:rus_x_preferred":[
        "\u041d\u0430\u0433\u043e\u0440\u043d\u043e\u0435"
    ],
    "name:und_x_variant":[
        "Nagornoye"
    ],
    "qs:name":"Nagornoe",
    "qs:name_adm0":"Russia",
    "qs:name_adm1":"Moscow Oblast",
    "qs:photos":216,
    "qs:photos_1k":44,
    "qs:photos_9k":1,
    "qs:photos_9r":4,
    "qs:photos_all":216,
    "qs:photos_sr":4,
    "qs:placetype":"Town",
    "qs:pop_sr":"2",
    "wof:name":"Nagornoe",
    "wof:placetype":"locality",
    "wof:population":300
},
  "geometry": {"coordinates":[37.62716,55.90391],"type":"Point"}
}