{
  "type": "Feature",
  "properties": {
    "gn:admin1_code":"23",
    "gn:asciiname":"Kustovka",
    "gn:country_code":"RU",
    "gn:dem":7,
    "gn:feature_class":"P",
    "gn:feature_code":"PPL",
    "gn:name":"Kustovka",
    "gn:population":0,
    "gn:timezone":"Europe/Kaliningrad",
    "iso:country":"RU",
    "name:rus_x_preferred":[
        "\u041a\u0443\u0441\u0442\u043e\u0432\u043a\u0430"
    ],
    "wof:name":"Kustovka",
    "wof:placetype":"locality"
},
  "geometry": {"coordinates":[20.9809,54.79404],"type":"Point"}
}