{
  "type": "Feature",
  "properties": {
    "gn:admin1_code":"6",
    "gn:asciiname":"Maloye Krotovo",
    "gn:country_code":"RU",
    "gn:dem":47,
    "gn:feature_class":"P",
    "gn:feature_code":"PPL",
    "gn:name":"Maloye Krotovo",
    "gn:population":100,
    "gn:timezone":"Europe/Moscow",
    "iso:country":"RU",
    "name:eng_x_preferred":[
        "Maloye Krotovo"
    ],
    "name:nor_x_preferred":[
        "Mal.Krotovo"
    ],
    "name:rus_x_preferred":[
        "\u041c\u0430\u043b.\u041a\u0440\u043e\u0442\u043e\u0432\u043e"
    ],
    "name:rus_x_variant":[
        "\u041c\u0430\u043b\u043e\u0435 \u041a\u0440\u043e\u0442\u043e\u0432\u043e"
    ],
    "name:und_x_variant":[
        "Malove Krotovo"
    ],
    "wof:name":"Maloye Krotovo",
    "wof:placetype":"locality",
    "wof:population":100
},
  "geometry": {"coordinates":[44.1909,63.9315],"type":"Point"}
}