{
  "type": "Feature",
  "properties": {
    "gn:admin1_code":"37",
    "gn:asciiname":"Kostylevo",
    "gn:country_code":"RU",
    "gn:dem":154,
    "gn:feature_class":"P",
    "gn:feature_code":"PPL",
    "gn:name":"Kostyl\u00ebvo",
    "gn:population":0,
    "gn:timezone":"Europe/Moscow",
    "iso:country":"RU",
    "name:rus_x_preferred":[
        "\u041a\u043e\u0441\u0442\u044b\u043b\u0451\u0432\u043e"
    ],
    "name:und_x_variant":[
        "Kostyl\u00ebvo"
    ],
    "wof:name":"Kostylevo",
    "wof:placetype":"locality"
},
  "geometry": {"coordinates":[42.7539,58.8417],"type":"Point"}
}