{
  "type": "Feature",
  "properties": {
    "gn:admin1_code":"45.0",
    "gn:asciiname":"Verkhniy Malyy Sernur",
    "gn:country_code":"RU",
    "gn:dem":144,
    "gn:feature_class":"P",
    "gn:feature_code":"PPL",
    "gn:name":"Verkhniy Malyy Sernur",
    "gn:population":0,
    "gn:timezone":"Europe/Moscow",
    "iso:country":"RU",
    "name:rus_x_preferred":[
        "\u0412\u0435\u0440\u0445\u043d\u0438\u0439 \u041c\u0430\u043b\u044b\u0439 \u0421\u0435\u0440\u043d\u0443\u0440"
    ],
    "wof:name":"Verkhniy Malyy Sernur",
    "wof:placetype":"locality"
},
  "geometry": {"coordinates":[49.20056,56.9725],"type":"Point"}
}