{
  "type": "Feature",
  "properties": {
    "gn:admin1_code":"71",
    "gn:asciiname":"Ust'-Bugalysh",
    "gn:country_code":"RU",
    "gn:dem":189,
    "gn:feature_class":"P",
    "gn:feature_code":"PPL",
    "gn:name":"Ust\u2019-Bugalysh",
    "gn:population":0,
    "gn:timezone":"Asia/Yekaterinburg",
    "iso:country":"RU",
    "name:eng_x_preferred":[
        "Ust'-Bugalysh"
    ],
    "name:nor_x_preferred":[
        "Ust-Bugalysj"
    ],
    "name:rus_x_preferred":[
        "\u0423\u0441\u0442\u044c-\u0411\u0443\u0433\u0430\u043b\u044b\u0448"
    ],
    "name:und_x_variant":[
        "Ust\u2019-Bugalysh"
    ],
    "wof:name":"Ust'-Bugalysh",
    "wof:placetype":"locality"
},
  "geometry": {"coordinates":[57.86413,56.2933],"type":"Point"}
}