{
  "type": "Feature",
  "properties": {
    "gn:admin1_code":"16",
    "gn:asciiname":"Basurmany",
    "gn:country_code":"RU",
    "gn:dem":164,
    "gn:feature_class":"P",
    "gn:feature_code":"PPL",
    "gn:name":"Basurmany",
    "gn:population":0,
    "gn:timezone":"Europe/Moscow",
    "iso:country":"RU",
    "name:rus_x_preferred":[
        "\u0411\u0430\u0441\u0443\u0440\u043c\u0430\u043d\u044b"
    ],
    "name:und_x_variant":[
        "\u0411\u0430\u0441\u0443\u0440\u043c\u0430\u043d\u044b"
    ],
    "wof:name":"Basurmany",
    "wof:placetype":"locality"
},
  "geometry": {"coordinates":[46.7892,56.0036],"type":"Point"}
}