{
  "type": "Feature",
  "properties": {
    "gn:admin1_code":"76",
    "gn:asciiname":"Baydyachka",
    "gn:country_code":"RU",
    "gn:dem":190,
    "gn:feature_class":"P",
    "gn:feature_code":"PPL",
    "gn:name":"Baydyachka",
    "gn:population":0,
    "gn:timezone":"Europe/Moscow",
    "iso:country":"RU",
    "name:nor_x_preferred":[
        "Bajdjatsjka"
    ],
    "name:rus_x_preferred":[
        "\u0411\u0430\u0439\u0434\u044f\u0447\u043a\u0430"
    ],
    "wof:name":"Baydyachka",
    "wof:placetype":"locality"
},
  "geometry": {"coordinates":[36.91647,53.41026],"type":"Point"}
}