{
  "type": "Feature",
  "properties": {
    "gn:admin1_code":"60",
    "gn:asciiname":"Dereven'ki",
    "gn:country_code":"RU",
    "gn:dem":192,
    "gn:feature_class":"P",
    "gn:feature_code":"PPL",
    "gn:name":"Dereven\u2019ki",
    "gn:population":0,
    "gn:timezone":"Europe/Moscow",
    "iso:country":"RU",
    "name:rus_x_preferred":[
        "\u0414\u0435\u0440\u0435\u0432\u0435\u043d\u044c\u043a\u0438"
    ],
    "name:und_x_variant":[
        "Dereven\u2019ki"
    ],
    "wof:name":"Dereven'ki",
    "wof:placetype":"locality"
},
  "geometry": {"coordinates":[29.0109,56.6281],"type":"Point"}
}