{
  "type": "Feature",
  "properties": {
    "gn:admin1_code":"69",
    "gn:asciiname":"Gavryushino",
    "gn:country_code":"RU",
    "gn:dem":219,
    "gn:feature_class":"P",
    "gn:feature_code":"PPL",
    "gn:name":"Gavryushino",
    "gn:population":0,
    "gn:timezone":"Europe/Moscow",
    "iso:country":"RU",
    "name:rus_x_preferred":[
        "\u0413\u0430\u0432\u0440\u044e\u0448\u0438\u043d\u043e"
    ],
    "name:und_x_variant":[
        "\u0413\u0430\u0432\u0440\u044e\u0448\u0438\u043d\u043e"
    ],
    "wof:name":"Gavryushino",
    "wof:placetype":"locality"
},
  "geometry": {"coordinates":[33.04806,55.48222],"type":"Point"}
}