{
  "type": "Feature",
  "properties": {
    "gn:admin1_code":"56",
    "gn:asciiname":"Malyy Pakhomov",
    "gn:country_code":"RU",
    "gn:dem":190,
    "gn:feature_class":"P",
    "gn:feature_code":"PPL",
    "gn:name":"Malyy Pakhomov",
    "gn:population":0,
    "gn:timezone":"Europe/Moscow",
    "iso:country":"RU",
    "name:rus_x_preferred":[
        "\u041c\u0430\u043b\u044b\u0439 \u041f\u0430\u0445\u043e\u043c\u043e\u0432"
    ],
    "wof:name":"Malyy Pakhomov",
    "wof:placetype":"locality"
},
  "geometry": {"coordinates":[35.96667,53.06667],"type":"Point"}
}