{
  "type": "Feature",
  "properties": {
    "gn:admin1_code":"41",
    "gn:asciiname":"Mitrofanova",
    "gn:country_code":"RU",
    "gn:dem":158,
    "gn:feature_class":"P",
    "gn:feature_code":"PPL",
    "gn:name":"Mitrofanova",
    "gn:population":0,
    "gn:timezone":"Europe/Moscow",
    "iso:country":"RU",
    "name:rus_x_preferred":[
        "\u041c\u0438\u0442\u0440\u043e\u0444\u0430\u043d\u043e\u0432\u0430"
    ],
    "wof:name":"Mitrofanova",
    "wof:placetype":"locality"
},
  "geometry": {"coordinates":[35.8236,51.6439],"type":"Point"}
}