{
  "type": "Feature",
  "properties": {
    "gn:admin1_code":"47",
    "gn:asciiname":"Shemetovo",
    "gn:country_code":"RU",
    "gn:dem":152,
    "gn:feature_class":"P",
    "gn:feature_code":"PPL",
    "gn:name":"Shem\u00ebtovo",
    "gn:population":0,
    "gn:timezone":"Europe/Moscow",
    "iso:country":"RU",
    "name:rus_x_preferred":[
        "\u0428\u0435\u043c\u0451\u0442\u043e\u0432\u043e"
    ],
    "name:und_x_variant":[
        "Shem\u00ebtovo"
    ],
    "wof:name":"Shemetovo",
    "wof:placetype":"locality"
},
  "geometry": {"coordinates":[38.62375,55.15891],"type":"Point"}
}