{
  "type": "Feature",
  "properties": {
    "gn:admin1_code":"76.0",
    "gn:asciiname":"Aydarovo",
    "gn:country_code":"RU",
    "gn:dem":129,
    "gn:feature_class":"P",
    "gn:feature_code":"PPL",
    "gn:name":"Aydarovo",
    "gn:population":0,
    "gn:timezone":"Europe/Moscow",
    "iso:country":"RU",
    "name:nor_x_preferred":[
        "Ajdarovo"
    ],
    "name:rus_x_preferred":[
        "\u0410\u0439\u0434\u0430\u0440\u043e\u0432\u043e"
    ],
    "wof:name":"Aydarovo",
    "wof:placetype":"locality"
},
  "geometry": {"coordinates":[37.15532,54.59641],"type":"Point"}
}