{
  "type": "Feature",
  "properties": {
    "gn:admin1_code":"21.0",
    "gn:asciiname":"Orzhanniki",
    "gn:country_code":"RU",
    "gn:dem":132,
    "gn:feature_class":"P",
    "gn:feature_code":"PPL",
    "gn:name":"Orzhanniki",
    "gn:population":0,
    "gn:timezone":"Europe/Moscow",
    "iso:country":"RU",
    "name:nor_x_preferred":[
        "Orzjanniki"
    ],
    "name:rus_x_preferred":[
        "\u041e\u0440\u0436\u0430\u043d\u043d\u0438\u043a\u0438"
    ],
    "wof:name":"Orzhanniki",
    "wof:placetype":"locality"
},
  "geometry": {"coordinates":[43.09278,56.8331],"type":"Point"}
}