{
  "type": "Feature",
  "properties": {
    "gn:admin1_code":"33.0",
    "gn:asciiname":"Kassiny",
    "gn:country_code":"RU",
    "gn:dem":149,
    "gn:feature_class":"P",
    "gn:feature_code":"PPL",
    "gn:name":"Kassiny",
    "gn:population":0,
    "gn:timezone":"Europe/Kirov",
    "iso:country":"RU",
    "name:rus_x_preferred":[
        "\u041a\u0430\u0441\u0441\u0438\u043d\u044b"
    ],
    "name:und_x_variant":[
        "\u041a\u0430\u0441\u0441\u0438\u043d\u044b"
    ],
    "wof:name":"Kassiny",
    "wof:placetype":"locality"
},
  "geometry": {"coordinates":[49.76194,58.66948000000001],"type":"Point"}
}