{
  "type": "Feature",
  "properties": {
    "gn:admin1_code":"85",
    "gn:asciiname":"Pruzhinino",
    "gn:country_code":"RU",
    "gn:dem":123,
    "gn:feature_class":"P",
    "gn:feature_code":"PPL",
    "gn:name":"Pruzhinino",
    "gn:population":0,
    "gn:timezone":"Europe/Moscow",
    "iso:country":"RU",
    "name:rus_x_preferred":[
        "\u041f\u0440\u0443\u0436\u0438\u043d\u0438\u043d\u043e"
    ],
    "wof:name":"Pruzhinino",
    "wof:placetype":"locality"
},
  "geometry": {"coordinates":[38.1581,59.88800000000001],"type":"Point"}
}