{
  "type": "Feature",
  "properties": {
    "gn:admin1_code":"69",
    "gn:asciiname":"Nikolayevo",
    "gn:country_code":"RU",
    "gn:dem":204,
    "gn:feature_class":"P",
    "gn:feature_code":"PPL",
    "gn:name":"Nikolayevo",
    "gn:population":0,
    "gn:timezone":"Europe/Moscow",
    "iso:country":"RU",
    "name:rus_x_preferred":[
        "\u041d\u0438\u043a\u043e\u043b\u0430\u0435\u0432\u043e"
    ],
    "name:und_x_variant":[
        "Durman",
        "Nikolayevo"
    ],
    "wof:name":"Nikolayevo",
    "wof:placetype":"locality"
},
  "geometry": {"coordinates":[32.9266,55.5647],"type":"Point"}
}