{
  "type": "Feature",
  "properties": {
    "gn:admin1_code":"93",
    "gn:asciiname":"Ust'-Yasytay",
    "gn:country_code":"RU",
    "gn:dem":1066,
    "gn:feature_class":"P",
    "gn:feature_code":"PPL",
    "gn:name":"Ust\u2019-Yasytay",
    "gn:population":0,
    "gn:timezone":"Asia/Chita",
    "iso:country":"RU",
    "name:rus_x_preferred":[
        "\u0423\u0441\u0442\u044c-\u042f\u0441\u044b\u0442\u0430\u0439"
    ],
    "name:und_x_variant":[
        "Esutay",
        "Ust\u2019-Yasytay"
    ],
    "wof:name":"Ust'-Yasytay",
    "wof:placetype":"locality"
},
  "geometry": {"coordinates":[110.41822000000001,50.17146],"type":"Point"}
}