{
  "type": "Feature",
  "properties": {
    "gn:admin1_code":"77",
    "gn:asciiname":"Zhukopa",
    "gn:country_code":"RU",
    "gn:dem":209,
    "gn:feature_class":"P",
    "gn:feature_code":"PPL",
    "gn:name":"Zhukopa",
    "gn:population":0,
    "gn:timezone":"Europe/Moscow",
    "iso:country":"RU",
    "name:rus_x_preferred":[
        "\u0416\u0443\u043a\u043e\u043f\u0430"
    ],
    "wof:name":"Zhukopa",
    "wof:placetype":"locality"
},
  "geometry": {"coordinates":[32.78789,56.88654],"type":"Point"}
}