{
  "type": "Feature",
  "properties": {
    "gn:admin1_code":"55",
    "gn:asciiname":"Seredinovka",
    "gn:country_code":"RU",
    "gn:dem":222,
    "gn:feature_class":"P",
    "gn:feature_code":"PPL",
    "gn:name":"Seredinovka",
    "gn:population":0,
    "gn:timezone":"Asia/Yekaterinburg",
    "iso:country":"RU",
    "name:rus_x_preferred":[
        "\u0421\u0435\u0440\u0435\u0434\u0438\u043d\u043e\u0432\u043a\u0430"
    ],
    "wof:name":"Seredinovka",
    "wof:placetype":"locality"
},
  "geometry": {"coordinates":[54.73333,53.13333000000001],"type":"Point"}
}