{
  "type": "Feature",
  "properties": {
    "gn:admin1_code":"62.0",
    "gn:asciiname":"Voskresenye",
    "gn:country_code":"RU",
    "gn:dem":121,
    "gn:feature_class":"P",
    "gn:feature_code":"PPL",
    "gn:name":"Voskresenye",
    "gn:population":1,
    "gn:timezone":"Europe/Moscow",
    "iso:country":"RU",
    "name:rus_x_preferred":[
        "\u0412\u043e\u0441\u043a\u0440\u0435\u0441\u0435\u043d\u044c\u0435"
    ],
    "wof:name":"Voskresenye",
    "wof:placetype":"locality",
    "wof:population":1
},
  "geometry": {"coordinates":[40.77704,55.07011],"type":"Point"}
}