{
  "type": "Feature",
  "properties": {
    "gn:admin1_code":"67",
    "gn:asciiname":"Staraya Motovilovka",
    "gn:country_code":"RU",
    "gn:dem":183,
    "gn:feature_class":"P",
    "gn:feature_code":"PPL",
    "gn:name":"Staraya Motovilovka",
    "gn:population":0,
    "gn:timezone":"Europe/Saratov",
    "iso:country":"RU",
    "name:rus_x_preferred":[
        "\u0421\u0442\u0430\u0440\u0430\u044f \u041c\u043e\u0442\u043e\u0432\u0438\u043b\u043e\u0432\u043a\u0430"
    ],
    "wof:name":"Staraya Motovilovka",
    "wof:placetype":"locality"
},
  "geometry": {"coordinates":[45.2916,51.89861],"type":"Point"}
}