{
  "type": "Feature",
  "properties": {
    "gn:admin1_code":"77",
    "gn:asciiname":"Pryamik",
    "gn:country_code":"RU",
    "gn:dem":171,
    "gn:feature_class":"P",
    "gn:feature_code":"PPL",
    "gn:name":"Pryamik",
    "gn:population":0,
    "gn:timezone":"Europe/Moscow",
    "iso:country":"RU",
    "name:rus_x_preferred":[
        "\u041f\u0440\u044f\u043c\u0438\u043a"
    ],
    "name:und_x_variant":[
        "\u041f\u0440\u044f\u043c\u0438\u043a"
    ],
    "wof:name":"Pryamik",
    "wof:placetype":"locality"
},
  "geometry": {"coordinates":[34.57234,57.45728],"type":"Point"}
}