{
  "type": "Feature",
  "properties": {
    "gn:admin1_code":"90",
    "gn:asciiname":"Nizhniy Shavlyash",
    "gn:country_code":"RU",
    "gn:dem":156,
    "gn:feature_class":"P",
    "gn:feature_code":"PPL",
    "gn:name":"Nizhniy Shavlyash",
    "gn:population":0,
    "gn:timezone":"Asia/Yekaterinburg",
    "iso:country":"RU",
    "name:rus_x_preferred":[
        "\u041d\u0438\u0436\u043d\u0438\u0439 \u0428\u0430\u0432\u043b\u044f\u0448"
    ],
    "name:und_x_variant":[
        "\u041d\u0438\u0436\u043d\u0438\u0439 \u0428\u0430\u0432\u043b\u044f\u0448"
    ],
    "wof:name":"Nizhniy Shavlyash",
    "wof:placetype":"locality"
},
  "geometry": {"coordinates":[56.5761,57.4384],"type":"Point"}
}