{
  "type": "Feature",
  "properties": {
    "gn:admin1_code":"33.0",
    "gn:asciiname":"Kazarintsy",
    "gn:country_code":"RU",
    "gn:dem":166,
    "gn:feature_class":"P",
    "gn:feature_code":"PPL",
    "gn:name":"Kazarintsy",
    "gn:population":0,
    "gn:timezone":"Europe/Kirov",
    "iso:country":"RU",
    "name:rus_x_preferred":[
        "\u041a\u0430\u0437\u0430\u0440\u0438\u043d\u0446\u044b"
    ],
    "name:und_x_variant":[
        "Kozarino",
        "Kazarintsy"
    ],
    "wof:name":"Kazarintsy",
    "wof:placetype":"locality"
},
  "geometry": {"coordinates":[50.45013,58.2917],"type":"Point"}
}