{
  "type": "Feature",
  "properties": {
    "gn:admin1_code":"77",
    "gn:asciiname":"Krupshevo",
    "gn:country_code":"RU",
    "gn:dem":135,
    "gn:feature_class":"P",
    "gn:feature_code":"PPL",
    "gn:name":"Krupshevo",
    "gn:population":0,
    "gn:timezone":"Europe/Moscow",
    "iso:country":"RU",
    "name:rus_x_preferred":[
        "\u041a\u0440\u0443\u043f\u0448\u0435\u0432\u043e"
    ],
    "wof:name":"Krupshevo",
    "wof:placetype":"locality"
},
  "geometry": {"coordinates":[36.1694,56.816],"type":"Point"}
}