{
  "type": "Feature",
  "properties": {
    "gn:admin1_code":"71",
    "gn:asciiname":"Lyampa",
    "gn:country_code":"RU",
    "gn:dem":222,
    "gn:feature_class":"P",
    "gn:feature_code":"PPL",
    "gn:name":"Lyampa",
    "gn:population":0,
    "gn:timezone":"Asia/Yekaterinburg",
    "iso:country":"RU",
    "name:eng_x_preferred":[
        "Lyampa"
    ],
    "name:nor_x_preferred":[
        "Ljampa"
    ],
    "name:rus_x_preferred":[
        "\u041b\u044f\u043c\u043f\u0430"
    ],
    "wof:name":"Lyampa",
    "wof:placetype":"locality"
},
  "geometry": {"coordinates":[57.9526,56.9795],"type":"Point"}
}