{
  "type": "Feature",
  "properties": {
    "gn:admin1_code":"60",
    "gn:asciiname":"Arapy",
    "gn:country_code":"RU",
    "gn:dem":113,
    "gn:feature_class":"P",
    "gn:feature_code":"PPL",
    "gn:name":"Arapy",
    "gn:population":0,
    "gn:timezone":"Europe/Moscow",
    "iso:country":"RU",
    "name:rus_x_preferred":[
        "\u0410\u0440\u0430\u043f\u044b"
    ],
    "wof:name":"Arapy",
    "wof:placetype":"locality"
},
  "geometry": {"coordinates":[28.48201,56.65935],"type":"Point"}
}