{
  "type": "Feature",
  "properties": {
    "gn:admin1_code":"79",
    "gn:asciiname":"Kyzyl-Tayga",
    "gn:cc2":"RU",
    "gn:country_code":"RU",
    "gn:dem":1155,
    "gn:feature_class":"P",
    "gn:feature_code":"PPL",
    "gn:name":"Kyzyl-Tayga",
    "gn:population":0,
    "gn:timezone":"Asia/Krasnoyarsk",
    "iso:country":"RU",
    "name:eng_x_preferred":[
        "Kyzyl-Tayga"
    ],
    "name:nor_x_preferred":[
        "Kyzyl-Tajga"
    ],
    "name:rus_x_preferred":[
        "\u041a\u044b\u0437\u044b\u043b-\u0422\u0430\u0439\u0433\u0430"
    ],
    "name:und_x_variant":[
        "Ezim-Ada",
        "Kyzyl-Tayga"
    ],
    "wof:name":"Kyzyl-Tayga",
    "wof:placetype":"locality"
},
  "geometry": {"coordinates":[90.15000000000001,51.31667],"type":"Point"}
}