{
  "type": "Feature",
  "properties": {
    "gn:admin1_code":"16",
    "gn:asciiname":"Peredniye Bokashi",
    "gn:country_code":"RU",
    "gn:dem":138,
    "gn:feature_class":"P",
    "gn:feature_code":"PPL",
    "gn:name":"Peredniye Bokashi",
    "gn:population":0,
    "gn:timezone":"Europe/Moscow",
    "iso:country":"RU",
    "name:rus_x_preferred":[
        "\u041f\u0435\u0440\u0435\u0434\u043d\u0438\u0435 \u0411\u043e\u043a\u0430\u0448\u0438"
    ],
    "wof:name":"Peredniye Bokashi",
    "wof:placetype":"locality"
},
  "geometry": {"coordinates":[47.80043,55.93094],"type":"Point"}
}