{
  "type": "Feature",
  "properties": {
    "gn:admin1_code":"11",
    "gn:asciiname":"Staroye Nomokhonovo",
    "gn:cc2":"RU",
    "gn:country_code":"RU",
    "gn:dem":547,
    "gn:feature_class":"P",
    "gn:feature_code":"PPL",
    "gn:name":"Staroye Nomokhonovo",
    "gn:population":0,
    "gn:timezone":"Asia/Irkutsk",
    "iso:country":"RU",
    "name:rus_x_preferred":[
        "\u0421\u0442\u0430\u0440\u043e\u0435 \u041d\u043e\u043c\u043e\u0445\u043e\u043d\u043e\u0432\u043e"
    ],
    "name:und_x_variant":[
        "Nomokhonovo",
        "Staroye Nomokhonovo"
    ],
    "wof:name":"Staroye Nomokhonovo",
    "wof:placetype":"locality"
},
  "geometry": {"coordinates":[106.38333,50.98333],"type":"Point"}
}