{
  "type": "Feature",
  "properties": {
    "gn:admin1_code":"85.0",
    "gn:asciiname":"Plesnikha",
    "gn:country_code":"RU",
    "gn:dem":163,
    "gn:feature_class":"P",
    "gn:feature_code":"PPL",
    "gn:name":"Pl\u00ebsnikha",
    "gn:population":0,
    "gn:timezone":"Europe/Moscow",
    "iso:country":"RU",
    "name:rus_x_preferred":[
        "\u041f\u043b\u0451\u0441\u043d\u0438\u0445\u0430"
    ],
    "name:und_x_variant":[
        "Pl\u00ebsnikha"
    ],
    "wof:name":"Plesnikha",
    "wof:placetype":"locality"
},
  "geometry": {"coordinates":[39.6292,60.2523],"type":"Point"}
}