{
  "type": "Feature",
  "properties": {
    "gn:admin1_code":"55.0",
    "gn:asciiname":"Uran",
    "gn:country_code":"RU",
    "gn:dem":91,
    "gn:feature_class":"P",
    "gn:feature_code":"PPL",
    "gn:name":"Uran",
    "gn:population":0,
    "gn:timezone":"Asia/Yekaterinburg",
    "iso:country":"RU",
    "name:rus_x_preferred":[
        "\u0423\u0440\u0430\u043d"
    ],
    "wof:name":"Uran",
    "wof:placetype":"locality"
},
  "geometry": {"coordinates":[53.08600000000001,52.5275],"type":"Point"}
}