{
  "type": "Feature",
  "properties": {
    "gn:admin1_code":"69.0",
    "gn:asciiname":"Bushuki",
    "gn:country_code":"RU",
    "gn:dem":213,
    "gn:feature_class":"P",
    "gn:feature_code":"PPL",
    "gn:name":"Bushuki",
    "gn:population":0,
    "gn:timezone":"Europe/Moscow",
    "iso:country":"RU",
    "name:eng_x_preferred":[
        "Bushuki"
    ],
    "name:nor_x_preferred":[
        "Busjukovo"
    ],
    "name:rus_x_preferred":[
        "\u0411\u0443\u0448\u0443\u043a\u043e\u0432\u043e"
    ],
    "name:rus_x_variant":[
        "\u0411\u0443\u0448\u0443\u043a\u0438"
    ],
    "name:und_x_variant":[
        "Bashukovo",
        "Bushukovo"
    ],
    "wof:name":"Bushuki",
    "wof:placetype":"locality"
},
  "geometry": {"coordinates":[33.80725,55.03364000000001],"type":"Point"}
}