{
  "type": "Feature",
  "properties": {
    "gn:admin1_code":"51.0",
    "gn:asciiname":"Bukaley",
    "gn:country_code":"RU",
    "gn:dem":116,
    "gn:feature_class":"P",
    "gn:feature_code":"PPL",
    "gn:name":"Bukaley",
    "gn:population":0,
    "gn:timezone":"Europe/Moscow",
    "iso:country":"RU",
    "name:rus_x_preferred":[
        "\u0411\u0443\u043a\u0430\u043b\u0435\u0439"
    ],
    "wof:name":"Bukaley",
    "wof:placetype":"locality"
},
  "geometry": {"coordinates":[45.13177,55.50778],"type":"Point"}
}