{
  "type": "Feature",
  "properties": {
    "gn:admin1_code":"69",
    "gn:asciiname":"Panskoye Vtoroye",
    "gn:country_code":"RU",
    "gn:dem":211,
    "gn:feature_class":"P",
    "gn:feature_code":"PPL",
    "gn:name":"Panskoye Vtoroye",
    "gn:population":0,
    "gn:timezone":"Europe/Moscow",
    "iso:country":"RU",
    "name:rus_x_preferred":[
        "\u041f\u0430\u043d\u0441\u043a\u043e\u0435 \u0412\u0442\u043e\u0440\u043e\u0435"
    ],
    "wof:name":"Panskoye Vtoroye",
    "wof:placetype":"locality"
},
  "geometry": {"coordinates":[32.37691,54.57319],"type":"Point"}
}