{
  "type": "Feature",
  "properties": {
    "gn:admin1_code":"77",
    "gn:asciiname":"Kudinovo",
    "gn:country_code":"RU",
    "gn:dem":189,
    "gn:feature_class":"P",
    "gn:feature_code":"PPL",
    "gn:name":"Kudinovo",
    "gn:population":0,
    "gn:timezone":"Europe/Moscow",
    "iso:country":"RU",
    "name:rus_x_preferred":[
        "\u041a\u0443\u0434\u0438\u043d\u043e\u0432\u043e"
    ],
    "name:und_x_variant":[
        "\u041a\u0443\u0434\u0438\u043d\u043e\u0432\u043e"
    ],
    "wof:name":"Kudinovo",
    "wof:placetype":"locality"
},
  "geometry": {"coordinates":[32.05833,56.30333],"type":"Point"}
}