{
  "type": "Feature",
  "properties": {
    "gn:admin1_code":"93",
    "gn:asciiname":"Kopun'",
    "gn:country_code":"RU",
    "gn:dem":578,
    "gn:feature_class":"P",
    "gn:feature_code":"PPL",
    "gn:name":"Kopun\u2019",
    "gn:population":0,
    "gn:timezone":"Asia/Chita",
    "iso:country":"RU",
    "name:eng_x_preferred":[
        "Kopun'"
    ],
    "name:nor_x_preferred":[
        "Kopun"
    ],
    "name:rus_x_preferred":[
        "\u041a\u043e\u043f\u0443\u043d\u044c"
    ],
    "name:und_x_variant":[
        "\u041a\u043e\u043f\u0443\u043d\u044c",
        "Kopun\u2019"
    ],
    "wof:name":"Kopun'",
    "wof:placetype":"locality"
},
  "geometry": {"coordinates":[117.65025,51.87175],"type":"Point"}
}