{
  "type": "Feature",
  "properties": {
    "gn:admin1_code":"6",
    "gn:asciiname":"Pakhomovskaya",
    "gn:country_code":"RU",
    "gn:dem":40,
    "gn:feature_class":"P",
    "gn:feature_code":"PPL",
    "gn:name":"Pakhomovskaya",
    "gn:population":0,
    "gn:timezone":"Europe/Moscow",
    "iso:country":"RU",
    "name:rus_x_preferred":[
        "\u041f\u0430\u0445\u043e\u043c\u043e\u0432\u0441\u043a\u0430\u044f"
    ],
    "wof:name":"Pakhomovskaya",
    "wof:placetype":"locality"
},
  "geometry": {"coordinates":[42.37389,61.68944000000001],"type":"Point"}
}