{
  "type": "Feature",
  "properties": {
    "gn:admin1_code":"17",
    "gn:admin2_code":"549104",
    "gn:asciiname":"Ochlo",
    "gn:country_code":"RU",
    "gn:dem":1741,
    "gn:feature_class":"P",
    "gn:feature_code":"PPL",
    "gn:name":"Ochlo",
    "gn:population":0,
    "gn:timezone":"Europe/Moscow",
    "iso:country":"RU",
    "name:rus_x_preferred":[
        "\u041e\u0447\u043b\u043e"
    ],
    "name:und_x_variant":[
        "\u041e\u0447\u043b\u043e"
    ],
    "wof:name":"Ochlo",
    "wof:placetype":"locality"
},
  "geometry": {"coordinates":[46.64562,42.6403],"type":"Point"}
}