{
  "type": "Feature",
  "properties": {
    "gn:admin1_code":"28",
    "gn:asciiname":"Unusozero",
    "gn:country_code":"RU",
    "gn:dem":134,
    "gn:feature_class":"P",
    "gn:feature_code":"PPL",
    "gn:name":"Unusozero",
    "gn:population":0,
    "gn:timezone":"Europe/Moscow",
    "iso:country":"RU",
    "name:fin_x_preferred":[
        "Unusj\u00e4rvi"
    ],
    "wof:name":"Unusozero",
    "wof:placetype":"locality"
},
  "geometry": {"coordinates":[32.80037,62.33423000000001],"type":"Point"}
}