{
  "type": "Feature",
  "properties": {
    "gn:admin1_code":"46",
    "gn:asciiname":"Sabur-Machkasy",
    "gn:country_code":"RU",
    "gn:dem":184,
    "gn:feature_class":"P",
    "gn:feature_code":"PPL",
    "gn:name":"Sabur-Machkasy",
    "gn:population":0,
    "gn:timezone":"Europe/Moscow",
    "iso:country":"RU",
    "name:eng_x_preferred":[
        "Sabur-Machkasy"
    ],
    "name:nor_x_preferred":[
        "Sabur-Matsjkasy"
    ],
    "name:rus_x_preferred":[
        "\u0421\u0430\u0431\u0443\u0440-\u041c\u0430\u0447\u043a\u0430\u0441\u044b"
    ],
    "name:und_x_variant":[
        "Sabur-Machkassy"
    ],
    "wof:name":"Sabur-Machkasy",
    "wof:placetype":"locality"
},
  "geometry": {"coordinates":[45.86901,54.47981],"type":"Point"}
}