{
  "type": "Feature",
  "properties": {
    "gn:admin1_code":"53",
    "gn:asciiname":"Krasnogorka",
    "gn:cc2":"RU",
    "gn:country_code":"RU",
    "gn:dem":120,
    "gn:feature_class":"P",
    "gn:feature_code":"PPL",
    "gn:name":"Krasnogorka",
    "gn:population":0,
    "gn:timezone":"Asia/Novosibirsk",
    "iso:country":"RU",
    "name:rus_x_preferred":[
        "\u041a\u0440\u0430\u0441\u043d\u043e\u0433\u043e\u0440\u043a\u0430"
    ],
    "name:und_x_variant":[
        "Krasnogorskiy",
        "Krasnogorka",
        "\u041a\u0440\u0430\u0441\u043d\u043e\u0433\u043e\u0440\u043a\u0430"
    ],
    "wof:name":"Krasnogorka",
    "wof:placetype":"locality"
},
  "geometry": {"coordinates":[77.66667,55.96666999999999],"type":"Point"}
}