{
  "type": "Feature",
  "properties": {
    "gn:admin1_code":"86",
    "gn:asciiname":"Krasnyye Solontsy",
    "gn:country_code":"RU",
    "gn:dem":109,
    "gn:feature_class":"P",
    "gn:feature_code":"PPL",
    "gn:name":"Krasnyye Solontsy",
    "gn:population":0,
    "gn:timezone":"Europe/Moscow",
    "iso:country":"RU",
    "name:rus_x_preferred":[
        "\u041a\u0440\u0430\u0441\u043d\u044b\u0435 \u0421\u043e\u043b\u043e\u043d\u0446\u044b"
    ],
    "wof:name":"Krasnyye Solontsy",
    "wof:placetype":"locality"
},
  "geometry": {"coordinates":[38.8593,51.7153],"type":"Point"}
}