{
  "type": "Feature",
  "properties": {
    "gn:admin1_code":"21.0",
    "gn:asciiname":"Fedyayevo",
    "gn:country_code":"RU",
    "gn:dem":145,
    "gn:feature_class":"P",
    "gn:feature_code":"PPL",
    "gn:name":"Fedyayevo",
    "gn:population":0,
    "gn:timezone":"Europe/Moscow",
    "iso:country":"RU",
    "name:eng_x_preferred":[
        "Fedyayevo"
    ],
    "name:nor_x_preferred":[
        "Fedjaevo"
    ],
    "name:rus_x_preferred":[
        "\u0424\u0435\u0434\u044f\u0435\u0432\u043e"
    ],
    "wof:name":"Fedyayevo",
    "wof:placetype":"locality"
},
  "geometry": {"coordinates":[42.00063,57.20381999999999],"type":"Point"}
}