{
  "type": "Feature",
  "properties": {
    "gn:admin1_code":"21.0",
    "gn:asciiname":"Posokhovo",
    "gn:country_code":"RU",
    "gn:dem":99,
    "gn:feature_class":"P",
    "gn:feature_code":"PPL",
    "gn:name":"Posokhovo",
    "gn:population":0,
    "gn:timezone":"Europe/Moscow",
    "iso:country":"RU",
    "name:rus_x_preferred":[
        "\u041f\u043e\u0441\u043e\u0445\u043e\u0432\u043e"
    ],
    "name:und_x_variant":[
        "\u041f\u043e\u0441\u043e\u0445\u043e\u0432\u043e"
    ],
    "wof:name":"Posokhovo",
    "wof:placetype":"locality"
},
  "geometry": {"coordinates":[41.41921,56.89874],"type":"Point"}
}