{
  "type": "Feature",
  "properties": {
    "gn:admin1_code":"90.0",
    "gn:asciiname":"Pan'yashor",
    "gn:country_code":"RU",
    "gn:dem":225,
    "gn:feature_class":"P",
    "gn:feature_code":"PPL",
    "gn:name":"Pan\u2019yashor",
    "gn:population":0,
    "gn:timezone":"Asia/Yekaterinburg",
    "iso:country":"RU",
    "name:rus_x_preferred":[
        "\u041f\u0430\u043d\u044c\u044f\u0448\u043e\u0440"
    ],
    "name:und_x_variant":[
        "Pan\u2019yashor"
    ],
    "wof:name":"Pan'yashor",
    "wof:placetype":"locality"
},
  "geometry": {"coordinates":[54.3044,58.8422],"type":"Point"}
}