{
  "type": "Feature",
  "properties": {
    "gn:admin1_code":"9",
    "gn:asciiname":"Luganka",
    "gn:country_code":"RU",
    "gn:dem":135,
    "gn:feature_class":"P",
    "gn:feature_code":"PPL",
    "gn:name":"Luganka",
    "gn:population":0,
    "gn:timezone":"Europe/Moscow",
    "iso:country":"RU",
    "name:rus_x_preferred":[
        "\u041b\u0443\u0433\u0430\u043d\u043a\u0430"
    ],
    "wof:name":"Luganka",
    "wof:placetype":"locality"
},
  "geometry": {"coordinates":[38.3023,51.1324],"type":"Point"}
}