{
  "type": "Feature",
  "properties": {
    "gn:admin1_code":"77",
    "gn:asciiname":"Stan",
    "gn:country_code":"RU",
    "gn:dem":216,
    "gn:feature_class":"P",
    "gn:feature_code":"PPL",
    "gn:name":"Stan",
    "gn:population":0,
    "gn:timezone":"Europe/Moscow",
    "iso:country":"RU",
    "name:rus_x_preferred":[
        "\u0421\u0442\u0430\u043d"
    ],
    "name:und_x_variant":[
        "\u0421\u0442\u0430\u043d"
    ],
    "wof:name":"Stan",
    "wof:placetype":"locality"
},
  "geometry": {"coordinates":[33.65858,57.29098000000001],"type":"Point"}
}