{
  "type": "Feature",
  "properties": {
    "gn:admin1_code":"33",
    "gn:asciiname":"Kruteyka",
    "gn:country_code":"RU",
    "gn:dem":133,
    "gn:feature_class":"P",
    "gn:feature_code":"PPL",
    "gn:name":"Kruteyka",
    "gn:population":0,
    "gn:timezone":"Europe/Kirov",
    "iso:country":"RU",
    "name:rus_x_preferred":[
        "\u041a\u0440\u0443\u0442\u0435\u0439\u043a\u0430"
    ],
    "wof:name":"Kruteyka",
    "wof:placetype":"locality"
},
  "geometry": {"coordinates":[46.8427,57.414],"type":"Point"}
}