{
  "type": "Feature",
  "properties": {
    "gn:admin1_code":"85.0",
    "gn:asciiname":"Aksent'yevo",
    "gn:country_code":"RU",
    "gn:dem":130,
    "gn:feature_class":"P",
    "gn:feature_code":"PPL",
    "gn:name":"Aks\u00ebnt\u2019yevo",
    "gn:population":0,
    "gn:timezone":"Europe/Moscow",
    "iso:country":"RU",
    "name:rus_x_preferred":[
        "\u0410\u043a\u0441\u0451\u043d\u0442\u044c\u0435\u0432\u043e"
    ],
    "name:und_x_variant":[
        "Aks\u00ebnt\u2019yevo"
    ],
    "wof:name":"Aksent'yevo",
    "wof:placetype":"locality"
},
  "geometry": {"coordinates":[37.7043,60.3348],"type":"Point"}
}