{
  "type": "Feature",
  "properties": {
    "gn:admin1_code":"56",
    "gn:asciiname":"Strukovo",
    "gn:country_code":"RU",
    "gn:dem":168,
    "gn:feature_class":"P",
    "gn:feature_code":"PPL",
    "gn:name":"Strukovo",
    "gn:population":0,
    "gn:timezone":"Europe/Moscow",
    "iso:country":"RU",
    "name:rus_x_preferred":[
        "\u0421\u0442\u0440\u0443\u043a\u043e\u0432\u043e"
    ],
    "wof:name":"Strukovo",
    "wof:placetype":"locality"
},
  "geometry": {"coordinates":[35.91228,53.43279],"type":"Point"}
}