{
  "type": "Feature",
  "properties": {
    "gn:admin1_code":"83.0",
    "gn:asciiname":"Mordviny",
    "gn:country_code":"RU",
    "gn:dem":130,
    "gn:feature_class":"P",
    "gn:feature_code":"PPL",
    "gn:name":"Mordviny",
    "gn:population":0,
    "gn:timezone":"Europe/Moscow",
    "iso:country":"RU",
    "name:rus_x_preferred":[
        "\u041c\u043e\u0440\u0434\u0432\u0438\u043d\u044b"
    ],
    "name:und_x_variant":[
        "\u041c\u043e\u0440\u0434\u0432\u0438\u043d\u044b"
    ],
    "wof:name":"Mordviny",
    "wof:placetype":"locality"
},
  "geometry": {"coordinates":[41.41822,56.11632],"type":"Point"}
}