{
  "type": "Feature",
  "properties": {
    "gn:admin1_code":"85",
    "gn:asciiname":"Podol",
    "gn:country_code":"RU",
    "gn:dem":171,
    "gn:feature_class":"P",
    "gn:feature_code":"PPL",
    "gn:name":"Podol",
    "gn:population":0,
    "gn:timezone":"Europe/Moscow",
    "iso:country":"RU",
    "name:rus_x_preferred":[
        "\u041f\u043e\u0434\u043e\u043b"
    ],
    "name:und_x_variant":[
        "\u041f\u043e\u0434\u043e\u043b"
    ],
    "wof:name":"Podol",
    "wof:placetype":"locality"
},
  "geometry": {"coordinates":[42.83333,59.41667],"type":"Point"}
}