{
  "type": "Feature",
  "properties": {
    "gn:admin1_code":"71",
    "gn:asciiname":"Krasnoyarskoye",
    "gn:country_code":"RU",
    "gn:dem":79,
    "gn:feature_class":"P",
    "gn:feature_code":"PPL",
    "gn:name":"Krasnoyarskoye",
    "gn:population":0,
    "gn:timezone":"Asia/Yekaterinburg",
    "iso:country":"RU",
    "name:rus_x_preferred":[
        "\u041a\u0440\u0430\u0441\u043d\u043e\u044f\u0440\u0441\u043a\u043e\u0435"
    ],
    "wof:name":"Krasnoyarskoye",
    "wof:placetype":"locality"
},
  "geometry": {"coordinates":[63.06719,56.84524],"type":"Point"}
}