{
  "type": "Feature",
  "properties": {
    "gn:admin1_code":"9",
    "gn:asciiname":"Shenshinovka",
    "gn:country_code":"RU",
    "gn:dem":133,
    "gn:feature_class":"P",
    "gn:feature_code":"PPL",
    "gn:name":"Shenshinovka",
    "gn:population":0,
    "gn:timezone":"Europe/Moscow",
    "iso:country":"RU",
    "name:rus_x_preferred":[
        "\u0428\u0435\u043d\u0448\u0438\u043d\u043e\u0432\u043a\u0430"
    ],
    "name:und_x_variant":[
        "Ishninovka",
        "Shenshinovka",
        "\u0428\u0435\u043d\u0448\u0438\u043d\u043e\u0432\u043a\u0430",
        "Shenshinovka Vtoraya",
        "Shenshinovka Pervaya"
    ],
    "wof:name":"Shenshinovka",
    "wof:placetype":"locality"
},
  "geometry": {"coordinates":[38.0658,50.5723],"type":"Point"}
}