{
  "type": "Feature",
  "properties": {
    "gn:admin1_code":"77",
    "gn:asciiname":"Maloye Khoroshevo",
    "gn:country_code":"RU",
    "gn:dem":244,
    "gn:feature_class":"P",
    "gn:feature_code":"PPL",
    "gn:name":"Maloye Khoroshevo",
    "gn:population":0,
    "gn:timezone":"Europe/Moscow",
    "iso:country":"RU",
    "name:rus_x_preferred":[
        "\u041c\u0430\u043b\u043e\u0435 \u0425\u043e\u0440\u043e\u0448\u0435\u0432\u043e"
    ],
    "wof:name":"Maloye Khoroshevo",
    "wof:placetype":"locality"
},
  "geometry": {"coordinates":[34.23603,56.73316],"type":"Point"}
}