{
  "type": "Feature",
  "properties": {
    "gn:admin1_code":"10",
    "gn:asciiname":"Serpeyevka",
    "gn:country_code":"RU",
    "gn:dem":209,
    "gn:feature_class":"P",
    "gn:feature_code":"PPL",
    "gn:name":"Serpeyevka",
    "gn:population":0,
    "gn:timezone":"Europe/Moscow",
    "iso:country":"RU",
    "name:rus_x_preferred":[
        "\u0421\u0435\u0440\u043f\u0435\u0435\u0432\u043a\u0430"
    ],
    "wof:name":"Serpeyevka",
    "wof:placetype":"locality"
},
  "geometry": {"coordinates":[33.36951,53.60803000000001],"type":"Point"}
}