{
  "type": "Feature",
  "properties": {
    "gn:admin1_code":"60",
    "gn:asciiname":"Trubino",
    "gn:country_code":"RU",
    "gn:dem":119,
    "gn:feature_class":"P",
    "gn:feature_code":"PPL",
    "gn:name":"Trubino",
    "gn:population":0,
    "gn:timezone":"Europe/Moscow",
    "iso:country":"RU",
    "name:rus_x_preferred":[
        "\u0422\u0440\u0443\u0431\u0438\u043d\u043e"
    ],
    "wof:name":"Trubino",
    "wof:placetype":"locality"
},
  "geometry": {"coordinates":[28.8745,56.36799],"type":"Point"}
}