{
  "type": "Feature",
  "properties": {
    "gn:admin1_code":"61",
    "gn:asciiname":"Nizhne-Vodyanoy",
    "gn:country_code":"RU",
    "gn:dem":38,
    "gn:feature_class":"P",
    "gn:feature_code":"PPL",
    "gn:name":"Nizhne-Vodyanoy",
    "gn:population":0,
    "gn:timezone":"Europe/Moscow",
    "iso:country":"RU",
    "name:rus_x_preferred":[
        "\u041d\u0438\u0436\u043d\u0435-\u0412\u043e\u0434\u044f\u043d\u043e\u0439"
    ],
    "wof:name":"Nizhne-Vodyanoy",
    "wof:placetype":"locality"
},
  "geometry": {"coordinates":[42.725,46.56083],"type":"Point"}
}