{
  "type": "Feature",
  "properties": {
    "gn:admin1_code":"41",
    "gn:asciiname":"Tishina Loshchina",
    "gn:country_code":"RU",
    "gn:dem":229,
    "gn:feature_class":"P",
    "gn:feature_code":"PPL",
    "gn:name":"Tishina Loshchina",
    "gn:population":0,
    "gn:timezone":"Europe/Moscow",
    "iso:country":"RU",
    "name:rus_x_preferred":[
        "\u0422\u0438\u0448\u0438\u043d\u0430 \u041b\u043e\u0449\u0438\u043d\u0430"
    ],
    "wof:name":"Tishina Loshchina",
    "wof:placetype":"locality"
},
  "geometry": {"coordinates":[36.3016,52.3499],"type":"Point"}
}