{
  "type": "Feature",
  "properties": {
    "gn:admin1_code":"46.0",
    "gn:asciiname":"Krasnaya Rudnya",
    "gn:country_code":"RU",
    "gn:dem":147,
    "gn:feature_class":"P",
    "gn:feature_code":"PPL",
    "gn:name":"Krasnaya Rudnya",
    "gn:population":0,
    "gn:timezone":"Europe/Moscow",
    "iso:country":"RU",
    "name:rus_x_preferred":[
        "\u041a\u0440\u0430\u0441\u043d\u0430\u044f \u0420\u0443\u0434\u043d\u044f"
    ],
    "wof:name":"Krasnaya Rudnya",
    "wof:placetype":"locality"
},
  "geometry": {"coordinates":[44.84117,54.32616],"type":"Point"}
}