{
  "type": "Feature",
  "properties": {
    "gn:admin1_code":"88",
    "gn:asciiname":"Karabikha",
    "gn:country_code":"RU",
    "gn:dem":145,
    "gn:feature_class":"P",
    "gn:feature_code":"PPL",
    "gn:name":"Karabikha",
    "gn:population":0,
    "gn:timezone":"Europe/Moscow",
    "iso:country":"RU",
    "name:eng_x_preferred":[
        "Karabikha"
    ],
    "name:nor_x_preferred":[
        "Karabikha"
    ],
    "name:rus_x_preferred":[
        "\u041a\u0430\u0440\u0430\u0431\u0438\u0445\u0430"
    ],
    "name:und_x_variant":[
        "\u041a\u0430\u0440\u0430\u0431\u0438\u0445\u0430",
        "Karabikha"
    ],
    "wof:name":"Karabikha",
    "wof:placetype":"locality"
},
  "geometry": {"coordinates":[39.76987,57.51269],"type":"Point"}
}