{
  "type": "Feature",
  "properties": {
    "gn:admin1_code":"46",
    "gn:asciiname":"Mamolayevo",
    "gn:country_code":"RU",
    "gn:dem":140,
    "gn:feature_class":"P",
    "gn:feature_code":"PPL",
    "gn:name":"Mamolayevo",
    "gn:population":0,
    "gn:timezone":"Europe/Moscow",
    "iso:country":"RU",
    "name:eng_x_preferred":[
        "Mamolayevo"
    ],
    "name:nor_x_preferred":[
        "Mamolajevo"
    ],
    "name:rus_x_preferred":[
        "\u041c\u0430\u043c\u043e\u043b\u0430\u0435\u0432\u043e"
    ],
    "wof:name":"Mamolayevo",
    "wof:placetype":"locality"
},
  "geometry": {"coordinates":[43.96136,54.29874],"type":"Point"}
}