{
  "type": "Feature",
  "properties": {
    "gn:admin1_code":"63",
    "gn:asciiname":"Kustakh",
    "gn:country_code":"RU",
    "gn:dem":263,
    "gn:feature_class":"P",
    "gn:feature_code":"PPL",
    "gn:name":"Kustakh",
    "gn:population":0,
    "gn:timezone":"Asia/Vladivostok",
    "iso:country":"RU",
    "name:rus_x_preferred":[
        "\u041a\u0443\u0441\u0442\u0430\u0445"
    ],
    "wof:name":"Kustakh",
    "wof:placetype":"locality"
},
  "geometry": {"coordinates":[133.19999999999999,60.15],"type":"Point"}
}