{
  "type": "Feature",
  "properties": {
    "gn:admin1_code":"57",
    "gn:asciiname":"Kevda-Vershina",
    "gn:country_code":"RU",
    "gn:dem":230,
    "gn:feature_class":"P",
    "gn:feature_code":"PPL",
    "gn:name":"Kevda-Vershina",
    "gn:population":0,
    "gn:timezone":"Europe/Moscow",
    "iso:country":"RU",
    "name:eng_x_preferred":[
        "Kevda-Vershina"
    ],
    "name:nor_x_preferred":[
        "Kevdo-Versjina"
    ],
    "name:rus_x_preferred":[
        "\u041a\u0435\u0432\u0434\u043e-\u0412\u0435\u0440\u0448\u0438\u043d\u0430"
    ],
    "name:rus_x_variant":[
        "\u041a\u0435\u0432\u0434\u0430-\u0412\u0435\u0440\u0448\u0438\u043d\u0430"
    ],
    "name:und_x_variant":[
        "Kevdo-Vershina"
    ],
    "wof:name":"Kevda-Vershina",
    "wof:placetype":"locality"
},
  "geometry": {"coordinates":[43.47405,53.12536],"type":"Point"}
}