{
  "type": "Feature",
  "properties": {
    "gn:admin1_code":"78",
    "gn:asciiname":"Ust'-Lamenka",
    "gn:country_code":"RU",
    "gn:dem":90,
    "gn:feature_class":"P",
    "gn:feature_code":"PPL",
    "gn:name":"Ust\u2019-Lamenka",
    "gn:population":0,
    "gn:timezone":"Asia/Yekaterinburg",
    "iso:country":"RU",
    "name:eng_x_preferred":[
        "Ust'-Lamenka"
    ],
    "name:nor_x_preferred":[
        "Ust-Lamenka"
    ],
    "name:rus_x_preferred":[
        "\u0423\u0441\u0442\u044c-\u041b\u0430\u043c\u0435\u043d\u043a\u0430"
    ],
    "name:und_x_variant":[
        "Ust\u2019-Lemenka",
        "Ust\u2019-Lamenka"
    ],
    "wof:name":"Ust'-Lamenka",
    "wof:placetype":"locality"
},
  "geometry": {"coordinates":[68.07429999999999,56.49856],"type":"Point"}
}