{
  "type": "Feature",
  "properties": {
    "gn:admin1_code":"47",
    "gn:asciiname":"Yazevo",
    "gn:country_code":"RU",
    "gn:dem":192,
    "gn:feature_class":"P",
    "gn:feature_code":"PPL",
    "gn:name":"Yazevo",
    "gn:population":0,
    "gn:timezone":"Europe/Moscow",
    "iso:country":"RU",
    "wof:name":"Yazevo",
    "wof:placetype":"locality"
},
  "geometry": {"coordinates":[36.02722,55.45639],"type":"Point"}
}