{
  "type": "Feature",
  "properties": {
    "gn:admin1_code":"7.0",
    "gn:asciiname":"Futniki",
    "gn:country_code":"RU",
    "gn:dem":-25,
    "gn:feature_class":"P",
    "gn:feature_code":"PPL",
    "gn:name":"Futniki",
    "gn:population":0,
    "gn:timezone":"Europe/Astrakhan",
    "iso:country":"RU",
    "name:rus_x_preferred":[
        "\u0424\u0443\u0442\u043d\u0438\u043a\u0438"
    ],
    "name:und_x_variant":[
        "\u0424\u0443\u0442\u043d\u0438\u043a\u0438"
    ],
    "wof:name":"Futniki",
    "wof:placetype":"locality"
},
  "geometry": {"coordinates":[47.57278,45.82611],"type":"Point"}
}