{
  "type": "Feature",
  "properties": {
    "gn:admin1_code":"90.0",
    "gn:asciiname":"Polovinnaya",
    "gn:country_code":"RU",
    "gn:dem":130,
    "gn:feature_class":"P",
    "gn:feature_code":"PPL",
    "gn:name":"Polovinnaya",
    "gn:population":0,
    "gn:timezone":"Asia/Yekaterinburg",
    "iso:country":"RU",
    "name:rus_x_preferred":[
        "\u041f\u043e\u043b\u043e\u0432\u0438\u043d\u043d\u0430\u044f"
    ],
    "wof:name":"Polovinnaya",
    "wof:placetype":"locality"
},
  "geometry": {"coordinates":[55.1548,58.0697],"type":"Point"}
}