{
  "type": "Feature",
  "properties": {
    "gn:admin1_code":"57",
    "gn:asciiname":"Sabanovo",
    "gn:country_code":"RU",
    "gn:dem":224,
    "gn:feature_class":"P",
    "gn:feature_code":"PPL",
    "gn:name":"Sabanovo",
    "gn:population":0,
    "gn:timezone":"Europe/Moscow",
    "iso:country":"RU",
    "name:eng_x_preferred":[
        "Sabanovo"
    ],
    "name:nor_x_preferred":[
        "Sabanovo"
    ],
    "name:rus_x_preferred":[
        "\u0421\u0430\u0431\u0430\u043d\u043e\u0432\u043e"
    ],
    "name:und_x_variant":[
        "\u0421\u0430\u0431\u0430\u043d\u043e\u0432\u043e",
        "Sabanovo"
    ],
    "wof:name":"Sabanovo",
    "wof:placetype":"locality"
},
  "geometry": {"coordinates":[46.0921,53.56958],"type":"Point"}
}