{
  "type": "Feature",
  "properties": {
    "gn:admin1_code":"20",
    "gn:asciiname":"Nizhniy Nomagut",
    "gn:country_code":"RU",
    "gn:dem":391,
    "gn:feature_class":"P",
    "gn:feature_code":"PPL",
    "gn:name":"Nizhniy Nomagut",
    "gn:population":0,
    "gn:timezone":"Asia/Irkutsk",
    "iso:country":"RU",
    "name:rus_x_preferred":[
        "\u041d\u0438\u0436\u043d\u0438\u0439 \u041d\u043e\u043c\u0430\u0433\u0443\u0442"
    ],
    "name:und_x_variant":[
        "Nizhniy Naymogodskiy",
        "Nizhniy Naymagut",
        "Nizhniy Nomagut"
    ],
    "wof:name":"Nizhniy Nomagut",
    "wof:placetype":"locality"
},
  "geometry": {"coordinates":[103.7093,53.5775],"type":"Point"}
}