{
  "type": "Feature",
  "properties": {
    "gn:admin1_code":"8",
    "gn:asciiname":"Kinzebyzovo Pervoye",
    "gn:country_code":"RU",
    "gn:dem":170,
    "gn:feature_class":"P",
    "gn:feature_code":"PPL",
    "gn:name":"Kinzebyzovo Pervoye",
    "gn:population":0,
    "gn:timezone":"Asia/Yekaterinburg",
    "iso:country":"RU",
    "name:rus_x_preferred":[
        "\u041a\u0438\u043d\u0437\u0435\u0431\u044b\u0437\u043e\u0432\u043e \u041f\u0435\u0440\u0432\u043e\u0435"
    ],
    "name:und_x_variant":[
        "Kinzyabyzovo Pervoye",
        "Kinzebyzovo Pervoye"
    ],
    "wof:name":"Kinzebyzovo Pervoye",
    "wof:placetype":"locality"
},
  "geometry": {"coordinates":[55.48333,52.66667],"type":"Point"}
}