{
  "type": "Feature",
  "properties": {
    "gn:admin1_code":"80",
    "gn:asciiname":"Lystem",
    "gn:country_code":"RU",
    "gn:dem":102,
    "gn:feature_class":"P",
    "gn:feature_code":"PPL",
    "gn:name":"Lystem",
    "gn:population":0,
    "gn:timezone":"Europe/Samara",
    "iso:country":"RU",
    "name:rus_x_preferred":[
        "\u041b\u044b\u0441\u0442\u0435\u043c"
    ],
    "name:und_x_variant":[
        "Lystem-Mozhga",
        "Lystem",
        "\u041b\u044b\u0441\u0442\u0435\u043c"
    ],
    "wof:name":"Lystem",
    "wof:placetype":"locality"
},
  "geometry": {"coordinates":[51.80562000000001,56.83955],"type":"Point"}
}