{
  "type": "Feature",
  "properties": {
    "gn:admin1_code":"62",
    "gn:asciiname":"Tys'ya",
    "gn:country_code":"RU",
    "gn:dem":139,
    "gn:feature_class":"P",
    "gn:feature_code":"PPL",
    "gn:name":"Tys\u2019ya",
    "gn:population":0,
    "gn:timezone":"Europe/Moscow",
    "iso:country":"RU",
    "name:rus_x_preferred":[
        "\u0422\u044b\u0441\u044c\u044f"
    ],
    "name:und_x_variant":[
        "Tys\u2019ya"
    ],
    "wof:name":"Tys'ya",
    "wof:placetype":"locality"
},
  "geometry": {"coordinates":[40.0608,54.4195],"type":"Point"}
}