{
  "type": "Feature",
  "properties": {
    "gn:admin1_code":"31",
    "gn:asciiname":"Chistobay",
    "gn:country_code":"RU",
    "gn:dem":694,
    "gn:feature_class":"P",
    "gn:feature_code":"PPL",
    "gn:name":"Chistobay",
    "gn:population":0,
    "gn:timezone":"Asia/Krasnoyarsk",
    "iso:country":"RU",
    "name:eng_x_preferred":[
        "Chistobay"
    ],
    "name:nor_x_preferred":[
        "Tsjistobaj"
    ],
    "name:rus_x_preferred":[
        "\u0427\u0438\u0441\u0442\u043e\u0431\u0430\u0439"
    ],
    "name:und_x_variant":[
        "\u0427\u0438\u0441\u0442\u043e\u0431\u0430\u0439",
        "Chistobay"
    ],
    "wof:name":"Chistobay",
    "wof:placetype":"locality"
},
  "geometry": {"coordinates":[90.40000000000001,52.56667],"type":"Point"}
}