{
  "type": "Feature",
  "properties": {
    "gn:admin1_code":"33.0",
    "gn:asciiname":"Medveditsa",
    "gn:country_code":"RU",
    "gn:dem":105,
    "gn:feature_class":"P",
    "gn:feature_code":"PPL",
    "gn:name":"Medveditsa",
    "gn:population":0,
    "gn:timezone":"Europe/Kirov",
    "iso:country":"RU",
    "name:bel_x_preferred":[
        "\u041c\u044f\u0434\u0437\u0432\u0435\u0434\u0437\u0456\u0446\u0430"
    ],
    "name:ceb_x_preferred":[
        "Medveditsa"
    ],
    "name:ces_x_preferred":[
        "Medvedica"
    ],
    "name:deu_x_preferred":[
        "Medwediza"
    ],
    "name:fra_x_preferred":[
        "Medveditsa"
    ],
    "name:ita_x_preferred":[
        "Medvedica"
    ],
    "name:nor_x_preferred":[
        "Medveditsa"
    ],
    "name:rus_x_preferred":[
        "\u041c\u0435\u0434\u0432\u0435\u0434\u0438\u0446\u0430"
    ],
    "name:srp_x_preferred":[
        "\u041c\u0435\u0434\u0432\u0435\u0434\u0438\u0446\u0430"
    ],
    "name:ukr_x_preferred":[
        "\u041c\u0435\u0434\u0432\u0435\u0434\u0438\u0446\u044f"
    ],
    "name:und_x_variant":[
        "\u041c\u0435\u0434\u0432\u0435\u0434\u0438\u0446\u0430"
    ],
    "wof:name":"Medveditsa",
    "wof:placetype":"locality"
},
  "geometry": {"coordinates":[48.6387,57.5607],"type":"Point"}
}