{
  "type": "Feature",
  "properties": {
    "gn:admin1_code":"90",
    "gn:asciiname":"Pruddor",
    "gn:country_code":"RU",
    "gn:dem":148,
    "gn:feature_class":"P",
    "gn:feature_code":"PPL",
    "gn:name":"Pruddor",
    "gn:population":0,
    "gn:timezone":"Asia/Yekaterinburg",
    "iso:country":"RU",
    "name:che_x_preferred":[
        "\u041f\u0440\u0443\u0434\u0434\u043e\u0440"
    ],
    "name:koi_x_preferred":[
        "\u041f\u0440\u0443\u0434\u0434\u043e\u0440"
    ],
    "name:rus_x_preferred":[
        "\u041f\u0440\u0443\u0434\u0434\u043e\u0440"
    ],
    "wof:name":"Pruddor",
    "wof:placetype":"locality"
},
  "geometry": {"coordinates":[54.4931,59.1277],"type":"Point"}
}