{
  "type": "Feature",
  "properties": {
    "gn:admin1_code":"85",
    "gn:asciiname":"Nizhniy Kuloy",
    "gn:country_code":"RU",
    "gn:dem":107,
    "gn:feature_class":"P",
    "gn:feature_code":"PPL",
    "gn:name":"Nizhniy Kuloy",
    "gn:population":0,
    "gn:timezone":"Europe/Moscow",
    "iso:country":"RU",
    "name:eng_x_preferred":[
        "Nizhniy Kuloy"
    ],
    "name:nor_x_preferred":[
        "Urusovskaja"
    ],
    "name:rus_x_preferred":[
        "\u0423\u0440\u0443\u0441\u043e\u0432\u0441\u043a\u0430\u044f"
    ],
    "name:rus_x_variant":[
        "\u041d\u0438\u0436\u043d\u0438\u0439 \u041a\u0443\u043b\u043e\u0439"
    ],
    "name:und_x_variant":[
        "Kuloy-Pokrovskiy",
        "Urusovskaya",
        "Kuloysko-Pokrovskiy Pogost"
    ],
    "wof:name":"Nizhniy Kuloy",
    "wof:placetype":"locality"
},
  "geometry": {"coordinates":[42.59562,60.71086999999999],"type":"Point"}
}