{
  "type": "Feature",
  "properties": {
    "gn:admin1_code":"76",
    "gn:asciiname":"Gryzlovo",
    "gn:country_code":"RU",
    "gn:dem":179,
    "gn:feature_class":"P",
    "gn:feature_code":"PPL",
    "gn:name":"Gryzlovo",
    "gn:population":0,
    "gn:timezone":"Europe/Moscow",
    "iso:country":"RU",
    "name:rus_x_preferred":[
        "\u0413\u0440\u044b\u0437\u043b\u043e\u0432\u043e"
    ],
    "wof:name":"Gryzlovo",
    "wof:placetype":"locality"
},
  "geometry": {"coordinates":[38.17993,54.1313],"type":"Point"}
}