{
  "type": "Feature",
  "properties": {
    "gn:admin1_code":"72",
    "gn:asciiname":"Vasil'yevka",
    "gn:country_code":"RU",
    "gn:dem":166,
    "gn:feature_class":"P",
    "gn:feature_code":"PPL",
    "gn:name":"Vasil\u2019yevka",
    "gn:population":0,
    "gn:timezone":"Europe/Moscow",
    "iso:country":"RU",
    "name:und_x_variant":[
        "Vasil\u2019yerka",
        "Vasil\u2019yevka"
    ],
    "wof:name":"Vasil'yevka",
    "wof:placetype":"locality"
},
  "geometry": {"coordinates":[41.28088,51.97863],"type":"Point"}
}