{
  "type": "Feature",
  "properties": {
    "gn:admin1_code":"60.0",
    "gn:asciiname":"Khrameyevo",
    "gn:country_code":"RU",
    "gn:dem":117,
    "gn:feature_class":"P",
    "gn:feature_code":"PPL",
    "gn:name":"Khrameyevo",
    "gn:population":0,
    "gn:timezone":"Europe/Moscow",
    "iso:country":"RU",
    "name:rus_x_preferred":[
        "\u0425\u0440\u0430\u043c\u0435\u0435\u0432\u043e"
    ],
    "wof:name":"Khrameyevo",
    "wof:placetype":"locality"
},
  "geometry": {"coordinates":[28.35784,56.86493000000001],"type":"Point"}
}