{
  "type": "Feature",
  "properties": {
    "gn:admin1_code":"16",
    "gn:asciiname":"Novoillarionovo",
    "gn:country_code":"RU",
    "gn:dem":128,
    "gn:feature_class":"P",
    "gn:feature_code":"PPL",
    "gn:name":"Novoillarionovo",
    "gn:population":0,
    "gn:timezone":"Europe/Moscow",
    "iso:country":"RU",
    "name:rus_x_preferred":[
        "\u041d\u043e\u0432\u043e\u0438\u043b\u043b\u0430\u0440\u0438\u043e\u043d\u043e\u0432\u043e"
    ],
    "wof:name":"Novoillarionovo",
    "wof:placetype":"locality"
},
  "geometry": {"coordinates":[47.1814,56.15314],"type":"Point"}
}