{
  "type": "Feature",
  "properties": {
    "gn:admin1_code":"37",
    "gn:asciiname":"Sukhovskoye",
    "gn:country_code":"RU",
    "gn:dem":156,
    "gn:feature_class":"P",
    "gn:feature_code":"PPL",
    "gn:name":"Sukhovskoye",
    "gn:population":0,
    "gn:timezone":"Europe/Moscow",
    "iso:country":"RU",
    "name:rus_x_preferred":[
        "\u0421\u0443\u0445\u043e\u0432\u0441\u043a\u043e\u0435"
    ],
    "wof:name":"Sukhovskoye",
    "wof:placetype":"locality"
},
  "geometry": {"coordinates":[44.98308,58.70981999999999],"type":"Point"}
}