{
  "type": "Feature",
  "properties": {
    "gn:admin1_code":"60",
    "gn:asciiname":"Priskukha",
    "gn:country_code":"RU",
    "gn:dem":116,
    "gn:feature_class":"P",
    "gn:feature_code":"PPL",
    "gn:name":"Priskukha",
    "gn:population":0,
    "gn:timezone":"Europe/Moscow",
    "iso:country":"RU",
    "name:rus_x_preferred":[
        "\u041f\u0440\u0438\u0441\u043a\u0443\u0445\u0430"
    ],
    "name:und_x_variant":[
        "Pryskukha",
        "Priskukha"
    ],
    "wof:name":"Priskukha",
    "wof:placetype":"locality"
},
  "geometry": {"coordinates":[30.16036,56.6285],"type":"Point"}
}