{
  "type": "Feature",
  "properties": {
    "gn:admin1_code":"84",
    "gn:asciiname":"Yarskoy",
    "gn:country_code":"RU",
    "gn:dem":53,
    "gn:feature_class":"P",
    "gn:feature_code":"PPL",
    "gn:name":"Yarskoy",
    "gn:population":0,
    "gn:timezone":"Europe/Volgograd",
    "iso:country":"RU",
    "name:rus_x_preferred":[
        "\u042f\u0440\u0441\u043a\u043e\u0439"
    ],
    "name:und_x_variant":[
        "\u042f\u0440\u0441\u043a\u043e\u0439"
    ],
    "wof:name":"Yarskoy",
    "wof:placetype":"locality"
},
  "geometry": {"coordinates":[42.33214,48.49775],"type":"Point"}
}