{
  "type": "Feature",
  "properties": {
    "gn:admin1_code":"69.0",
    "gn:asciiname":"Chizhaki",
    "gn:country_code":"RU",
    "gn:dem":184,
    "gn:feature_class":"P",
    "gn:feature_code":"PPL",
    "gn:name":"Chizhaki",
    "gn:population":0,
    "gn:timezone":"Europe/Moscow",
    "iso:country":"RU",
    "name:rus_x_preferred":[
        "\u0427\u0438\u0436\u0430\u043a\u0438"
    ],
    "name:und_x_variant":[
        "\u0427\u0438\u0436\u0430\u043a\u0438"
    ],
    "wof:name":"Chizhaki",
    "wof:placetype":"locality"
},
  "geometry": {"coordinates":[31.86591,55.57775],"type":"Point"}
}