{
  "type": "Feature",
  "properties": {
    "gn:admin1_code":"8",
    "gn:asciiname":"Matveyevka",
    "gn:country_code":"RU",
    "gn:dem":372,
    "gn:feature_class":"P",
    "gn:feature_code":"PPL",
    "gn:name":"Matveyevka",
    "gn:population":0,
    "gn:timezone":"Asia/Yekaterinburg",
    "iso:country":"RU",
    "name:eng_x_preferred":[
        "Matveyevka"
    ],
    "name:nor_x_preferred":[
        "Matvejevka"
    ],
    "name:rus_x_preferred":[
        "\u041c\u0430\u0442\u0432\u0435\u0435\u0432\u043a\u0430"
    ],
    "name:und_x_variant":[
        "\u041c\u0430\u0442\u0432\u0435\u0435\u0432\u043a\u0430",
        "Matveyevka"
    ],
    "wof:name":"Matveyevka",
    "wof:placetype":"locality"
},
  "geometry": {"coordinates":[59.4158,55.5195],"type":"Point"}
}