{
  "type": "Feature",
  "properties": {
    "gn:admin1_code":"85",
    "gn:asciiname":"Skovyatino",
    "gn:country_code":"RU",
    "gn:dem":117,
    "gn:feature_class":"P",
    "gn:feature_code":"PPL",
    "gn:name":"Skovyatino",
    "gn:population":0,
    "gn:timezone":"Europe/Moscow",
    "iso:country":"RU",
    "name:rus_x_preferred":[
        "\u0421\u043a\u043e\u0432\u044f\u0442\u0438\u043d\u043e"
    ],
    "name:und_x_variant":[
        "\u0421\u043a\u043e\u0432\u044f\u0442\u0438\u043d\u043e"
    ],
    "wof:name":"Skovyatino",
    "wof:placetype":"locality"
},
  "geometry": {"coordinates":[37.39542,58.80198000000001],"type":"Point"}
}