{
  "type": "Feature",
  "properties": {
    "gn:admin1_code":"38.0",
    "gn:asciiname":"Bzhedukhov",
    "gn:country_code":"RU",
    "gn:dem":229,
    "gn:feature_class":"P",
    "gn:feature_code":"PPL",
    "gn:name":"Bzhedukhov",
    "gn:population":0,
    "gn:timezone":"Europe/Moscow",
    "iso:country":"RU",
    "wof:name":"Bzhedukhov",
    "wof:placetype":"locality"
},
  "geometry": {"coordinates":[39.82028,44.54139],"type":"Point"}
}