{
  "type": "Feature",
  "properties": {
    "gn:admin1_code":"56",
    "gn:asciiname":"Okunevy Gory",
    "gn:country_code":"RU",
    "gn:dem":143,
    "gn:feature_class":"P",
    "gn:feature_code":"PPL",
    "gn:name":"Okunevy Gory",
    "gn:population":0,
    "gn:timezone":"Europe/Moscow",
    "iso:country":"RU",
    "name:rus_x_preferred":[
        "\u041e\u043a\u0443\u043d\u0435\u0432\u044b \u0413\u043e\u0440\u044b"
    ],
    "name:und_x_variant":[
        "Kostromytino",
        "Okunevy Gory",
        "\u041e\u043a\u0443\u043d\u0435\u0432\u044b \u0413\u043e\u0440\u044b"
    ],
    "wof:name":"Okunevy Gory",
    "wof:placetype":"locality"
},
  "geometry": {"coordinates":[37.95459,52.3796],"type":"Point"}
}