{
  "type": "Feature",
  "properties": {
    "gn:admin1_code":"33",
    "gn:asciiname":"Silenki",
    "gn:country_code":"RU",
    "gn:dem":299,
    "gn:feature_class":"P",
    "gn:feature_code":"PPL",
    "gn:name":"Sil\u00ebnki",
    "gn:population":0,
    "gn:timezone":"Europe/Kirov",
    "iso:country":"RU",
    "name:rus_x_preferred":[
        "\u0421\u0438\u043b\u0451\u043d\u043a\u0438"
    ],
    "name:und_x_variant":[
        "Sil\u00ebnki"
    ],
    "wof:name":"Silenki",
    "wof:placetype":"locality"
},
  "geometry": {"coordinates":[53.2165,58.4868],"type":"Point"}
}