{
  "type": "Feature",
  "properties": {
    "gn:country":"RU",
    "gn:fcode":"PPL",
    "gn:population":0,
    "iso:country":"RU",
    "name:eng_x_preferred":[
        "Bobrovka"
    ],
    "name:nor_x_preferred":[
        "Bobrovka"
    ],
    "name:rus_x_preferred":[
        "\u0411\u043e\u0431\u0440\u043e\u0432\u043a\u0430"
    ],
    "qs:name":"Borovka",
    "qs:name_adm0":"Russia",
    "qs:name_adm1":"Samara Oblast",
    "qs:photos_9r":0,
    "qs:photos_sr":0,
    "qs:placetype":"Town",
    "qs:pop_sr":"0",
    "wof:name":"Borovka",
    "wof:placetype":"locality",
    "wof:population":0
},
  "geometry": {"coordinates":[50.64527,53.15299],"type":"Point"}
}