{
  "type": "Feature",
  "properties": {
    "gn:admin1_code":"59",
    "gn:asciiname":"Tayezhnyy",
    "gn:country_code":"RU",
    "gn:dem":21,
    "gn:feature_class":"P",
    "gn:feature_code":"PPL",
    "gn:name":"Tay\u00ebzhnyy",
    "gn:population":0,
    "gn:timezone":"Asia/Vladivostok",
    "iso:country":"RU",
    "name:rus_x_preferred":[
        "\u0422\u0430\u0451\u0436\u043d\u044b\u0439"
    ],
    "name:und_x_variant":[
        "Tay\u00ebzhnyy"
    ],
    "wof:name":"Tayezhnyy",
    "wof:placetype":"locality"
},
  "geometry": {"coordinates":[131.93563999999998,43.47193],"type":"Point"}
}