{
  "type": "Feature",
  "properties": {
    "gn:admin1_code":"91.0",
    "gn:asciiname":"Cheremushki",
    "gn:country_code":"RU",
    "gn:dem":172,
    "gn:feature_class":"P",
    "gn:feature_code":"PPL",
    "gn:name":"Cher\u00ebmushki",
    "gn:population":0,
    "gn:timezone":"Asia/Krasnoyarsk",
    "iso:country":"RU",
    "name:rus_x_preferred":[
        "\u0427\u0435\u0440\u00eb\u043c\u0443\u0448\u043a\u0438"
    ],
    "name:und_x_variant":[
        "Cher\u00ebmushki",
        "Cher\u00ebmushka"
    ],
    "wof:name":"Cheremushki",
    "wof:placetype":"locality"
},
  "geometry": {"coordinates":[93.02173999999999,55.98466],"type":"Point"}
}