{
  "type": "Feature",
  "properties": {
    "gn:admin1_code":"16",
    "gn:asciiname":"Shibegechi",
    "gn:country_code":"RU",
    "gn:dem":150,
    "gn:feature_class":"P",
    "gn:feature_code":"PPL",
    "gn:name":"Shibegechi",
    "gn:population":0,
    "gn:timezone":"Europe/Moscow",
    "iso:country":"RU",
    "name:rus_x_preferred":[
        "\u0428\u0438\u0431\u0435\u0433\u0435\u0447\u0438"
    ],
    "name:und_x_variant":[
        "Shibegech\u2019",
        "Shibegach\u2019",
        "Shibegechi",
        "\u0428\u0438\u0431\u0435\u0433\u0435\u0447\u0438"
    ],
    "wof:name":"Shibegechi",
    "wof:placetype":"locality"
},
  "geometry": {"coordinates":[47.03252,55.36861999999999],"type":"Point"}
}