{
  "type": "Feature",
  "properties": {
    "gn:admin1_code":"57.0",
    "gn:asciiname":"Chernozer'ye",
    "gn:country_code":"RU",
    "gn:dem":163,
    "gn:feature_class":"P",
    "gn:feature_code":"PPL",
    "gn:name":"Chernoz\u00ebr\u2019ye",
    "gn:population":0,
    "gn:timezone":"Europe/Moscow",
    "iso:country":"RU",
    "name:eng_x_preferred":[
        "Chernoz\u00ebr'ye"
    ],
    "name:nor_x_preferred":[
        "Tsjernozerje"
    ],
    "name:rus_x_preferred":[
        "\u0427\u0435\u0440\u043d\u043e\u0437\u0435\u0440\u044c\u0435"
    ],
    "name:rus_x_variant":[
        "\u0427\u0435\u0440\u043d\u043e\u0437\u0451\u0440\u044c\u0435"
    ],
    "name:und_x_variant":[
        "Chernoozer\u2019ye",
        "Chernoz\u00ebr\u2019ye",
        "\u0427\u0435\u0440\u043d\u043e\u0437\u0451\u0440\u044c\u0435"
    ],
    "wof:name":"Chernozer'ye",
    "wof:placetype":"locality"
},
  "geometry": {"coordinates":[44.33835,53.57979],"type":"Point"}
}