{
  "type": "Feature",
  "properties": {
    "gn:admin1_code":"69",
    "gn:asciiname":"Sukhodol",
    "gn:country_code":"RU",
    "gn:dem":209,
    "gn:feature_class":"P",
    "gn:feature_code":"PPL",
    "gn:name":"Sukhodol",
    "gn:population":0,
    "gn:timezone":"Europe/Moscow",
    "iso:country":"RU",
    "name:bul_x_preferred":[
        "\u0421\u0443\u0445\u043e\u0434\u043e\u043b"
    ],
    "name:che_x_preferred":[
        "\u0421\u0443\u0445\u043e\u0434\u043e\u043b"
    ],
    "name:deu_x_preferred":[
        "Suchodol"
    ],
    "name:hye_x_preferred":[
        "\u054d\u0578\u0582\u056d\u0578\u0564\u0578\u056c"
    ],
    "name:rus_x_preferred":[
        "\u0421\u0443\u0445\u043e\u0434\u043e\u043b"
    ],
    "wof:name":"Sukhodol",
    "wof:placetype":"locality"
},
  "geometry": {"coordinates":[32.18979,54.8524],"type":"Point"}
}