{
  "type": "Feature",
  "properties": {
    "gn:admin1_code":"83",
    "gn:asciiname":"Stanovtsevo",
    "gn:country_code":"RU",
    "gn:dem":148,
    "gn:feature_class":"P",
    "gn:feature_code":"PPL",
    "gn:name":"Stanovtsevo",
    "gn:population":0,
    "gn:timezone":"Europe/Moscow",
    "iso:country":"RU",
    "name:rus_x_preferred":[
        "\u0421\u0442\u0430\u043d\u043e\u0432\u0446\u0435\u0432\u043e"
    ],
    "wof:name":"Stanovtsevo",
    "wof:placetype":"locality"
},
  "geometry": {"coordinates":[39.45539,56.04806],"type":"Point"}
}