{
  "type": "Feature",
  "properties": {
    "gn:admin1_code":"62",
    "gn:asciiname":"Taninskaya",
    "gn:country_code":"RU",
    "gn:dem":168,
    "gn:feature_class":"P",
    "gn:feature_code":"PPL",
    "gn:name":"Taninskaya",
    "gn:population":0,
    "gn:timezone":"Europe/Moscow",
    "iso:country":"RU",
    "name:rus_x_preferred":[
        "\u0422\u0430\u043d\u0438\u043d\u0441\u043a\u0430\u044f"
    ],
    "wof:name":"Taninskaya",
    "wof:placetype":"locality"
},
  "geometry": {"coordinates":[39.539,54.4481],"type":"Point"}
}