{
  "type": "Feature",
  "properties": {
    "gn:admin1_code":"38",
    "gn:asciiname":"Uspenskiy",
    "gn:country_code":"RU",
    "gn:dem":356,
    "gn:feature_class":"P",
    "gn:feature_code":"PPL",
    "gn:name":"Uspenskiy",
    "gn:population":0,
    "gn:timezone":"Europe/Moscow",
    "iso:country":"RU",
    "name:rus_x_preferred":[
        "\u0423\u0441\u043f\u0435\u043d\u0441\u043a\u0438\u0439"
    ],
    "wof:name":"Uspenskiy",
    "wof:placetype":"locality"
},
  "geometry": {"coordinates":[41.46292,44.73622],"type":"Point"}
}