{
  "type": "Feature",
  "properties": {
    "gn:admin1_code":"90",
    "gn:asciiname":"Romanyata",
    "gn:country_code":"RU",
    "gn:dem":137,
    "gn:feature_class":"P",
    "gn:feature_code":"PPL",
    "gn:name":"Romanyata",
    "gn:population":0,
    "gn:timezone":"Asia/Yekaterinburg",
    "iso:country":"RU",
    "name:che_x_preferred":[
        "\u0420\u043e\u043c\u0430\u043d\u044f\u0442\u0430"
    ],
    "name:eng_x_preferred":[
        "Romanyata"
    ],
    "name:nor_x_preferred":[
        "Romanjata"
    ],
    "name:rus_x_preferred":[
        "\u0420\u043e\u043c\u0430\u043d\u044f\u0442\u0430"
    ],
    "wof:name":"Romanyata",
    "wof:placetype":"locality"
},
  "geometry": {"coordinates":[54.7687,56.78435],"type":"Point"}
}