{
  "type": "Feature",
  "properties": {
    "gn:admin1_code":"42",
    "gn:asciiname":"Saralog",
    "gn:country_code":"RU",
    "gn:dem":61,
    "gn:feature_class":"P",
    "gn:feature_code":"PPL",
    "gn:name":"Saralog",
    "gn:population":0,
    "gn:timezone":"Europe/Moscow",
    "iso:country":"RU",
    "name:rus_x_preferred":[
        "\u0421\u0430\u0440\u0430\u043b\u043e\u0433"
    ],
    "name:und_x_variant":[
        "\u0421\u0430\u0440\u0430\u043b\u043e\u0433"
    ],
    "wof:name":"Saralog",
    "wof:placetype":"locality"
},
  "geometry": {"coordinates":[29.16163,58.97445],"type":"Point"}
}