{
  "type": "Feature",
  "properties": {
    "gn:admin1_code":"85.0",
    "gn:asciiname":"Bel'",
    "gn:country_code":"RU",
    "gn:dem":125,
    "gn:feature_class":"P",
    "gn:feature_code":"PPL",
    "gn:name":"Bel\u2019",
    "gn:population":0,
    "gn:timezone":"Europe/Moscow",
    "iso:country":"RU",
    "name:rus_x_preferred":[
        "Bel\u2019"
    ],
    "name:rus_x_variant":[
        "\u0411\u0435\u043b\u044c"
    ],
    "wof:name":"Bel'",
    "wof:placetype":"locality"
},
  "geometry": {"coordinates":[40.44111,59.11722],"type":"Point"}
}