{
  "type": "Feature",
  "properties": {
    "gn:country":"RU",
    "gn:fcode":"PPL",
    "gn:pop":23,
    "iso:country":"RU",
    "name:eng_x_preferred":[
        "Karabula"
    ],
    "name:nor_x_preferred":[
        "Karabula"
    ],
    "name:rus_x_preferred":[
        "\u041a\u0430\u0440\u0430\u0431\u0443\u043b\u0430"
    ],
    "qs:name":"Karabula",
    "qs:photos_9r":0,
    "qs:photos_sr":0,
    "qs:pop_sr":"1",
    "wof:name":"Karabula",
    "wof:placetype":"locality",
    "wof:population":23
},
  "geometry": {"coordinates":[97.39444,58.03389],"type":"Point"}
}