{
  "type": "Feature",
  "properties": {
    "gn:admin1_code":"16",
    "gn:asciiname":"Sitcharaki",
    "gn:country_code":"RU",
    "gn:dem":145,
    "gn:feature_class":"P",
    "gn:feature_code":"PPL",
    "gn:name":"Sitcharaki",
    "gn:population":0,
    "gn:timezone":"Europe/Moscow",
    "iso:country":"RU",
    "name:rus_x_preferred":[
        "\u0421\u0438\u0442\u0447\u0430\u0440\u0430\u043a\u0438"
    ],
    "wof:name":"Sitcharaki",
    "wof:placetype":"locality"
},
  "geometry": {"coordinates":[47.38318,55.93006],"type":"Point"}
}