{
  "type": "Feature",
  "properties": {
    "gn:admin1_code":"52",
    "gn:asciiname":"Klevenets",
    "gn:country_code":"RU",
    "gn:dem":48,
    "gn:feature_class":"P",
    "gn:feature_code":"PPL",
    "gn:name":"Klevenets",
    "gn:population":0,
    "gn:timezone":"Europe/Moscow",
    "iso:country":"RU",
    "name:rus_x_preferred":[
        "\u041a\u043b\u0435\u0432\u0435\u043d\u0435\u0446"
    ],
    "name:und_x_variant":[
        "\u041a\u043b\u0435\u0432\u0435\u043d\u0435\u0446"
    ],
    "wof:name":"Klevenets",
    "wof:placetype":"locality"
},
  "geometry": {"coordinates":[30.34917,58.40623000000001],"type":"Point"}
}