{
  "type": "Feature",
  "properties": {
    "gn:admin1_code":"60",
    "gn:asciiname":"Mel'nitsa",
    "gn:country_code":"RU",
    "gn:dem":62,
    "gn:feature_class":"P",
    "gn:feature_code":"PPL",
    "gn:name":"Mel\u2019nitsa",
    "gn:population":0,
    "gn:timezone":"Europe/Moscow",
    "iso:country":"RU",
    "name:rus_x_preferred":[
        "\u041c\u0435\u043b\u044c\u043d\u0438\u0446\u0430"
    ],
    "name:und_x_variant":[
        "Mel\u2019nitsa"
    ],
    "wof:name":"Mel'nitsa",
    "wof:placetype":"locality"
},
  "geometry": {"coordinates":[28.22589,57.20069],"type":"Point"}
}