{
  "type": "Feature",
  "properties": {
    "gn:admin1_code":"71",
    "gn:asciiname":"Petrova",
    "gn:cc2":"RU",
    "gn:country_code":"RU",
    "gn:dem":90,
    "gn:feature_class":"P",
    "gn:feature_code":"PPL",
    "gn:name":"Petrova",
    "gn:population":0,
    "gn:timezone":"Asia/Yekaterinburg",
    "iso:country":"RU",
    "name:eng_x_preferred":[
        "Petrova"
    ],
    "name:nor_x_preferred":[
        "Petrova"
    ],
    "name:rus_x_preferred":[
        "\u041f\u0435\u0442\u0440\u043e\u0432\u0430"
    ],
    "name:und_x_variant":[
        "Petrovo"
    ],
    "wof:name":"Petrova",
    "wof:placetype":"locality"
},
  "geometry": {"coordinates":[60.5075,60.04472],"type":"Point"}
}