{
  "type": "Feature",
  "properties": {
    "gn:admin1_code":"42",
    "gn:asciiname":"Vasil'yevo",
    "gn:country_code":"RU",
    "gn:dem":18,
    "gn:feature_class":"P",
    "gn:feature_code":"PPL",
    "gn:name":"Vasil\u2019yevo",
    "gn:population":0,
    "gn:timezone":"Europe/Moscow",
    "iso:country":"RU",
    "name:eng_x_preferred":[
        "Vasil'yevo"
    ],
    "name:fin_x_preferred":[
        "Tiuri"
    ],
    "name:nor_x_preferred":[
        "Vasiljevo"
    ],
    "name:rus_x_preferred":[
        "\u0412\u0430\u0441\u0438\u043b\u044c\u0435\u0432\u043e"
    ],
    "name:und_x_variant":[
        "Vasil\u2019yevo"
    ],
    "wof:name":"Vasil'yevo",
    "wof:placetype":"locality"
},
  "geometry": {"coordinates":[29.82136,60.86113],"type":"Point"}
}