{
  "type": "Feature",
  "properties": {
    "iso:country":"RU",
    "qs:name":"Ramenskiy Rayon",
    "qs:name_adm0":"Russia",
    "qs:name_adm1":"Moscow Oblast",
    "qs:photos":110,
    "qs:photos_1k":22,
    "qs:photos_9k":1,
    "qs:photos_9r":3,
    "qs:photos_all":110,
    "qs:photos_sr":3,
    "qs:placetype":"Town",
    "qs:pop_sr":"0",
    "wof:name":"Ramenskiy Rayon",
    "wof:placetype":"locality"
},
  "geometry": {"coordinates":[38.145732,55.568736],"type":"Point"}
}