{
  "type": "Feature",
  "properties": {
    "gn:admin1_code":"88",
    "gn:asciiname":"Mikheyevo",
    "gn:country_code":"RU",
    "gn:dem":129,
    "gn:feature_class":"P",
    "gn:feature_code":"PPL",
    "gn:name":"Mikheyevo",
    "gn:population":0,
    "gn:timezone":"Europe/Moscow",
    "iso:country":"RU",
    "name:rus_x_preferred":[
        "\u041c\u0438\u0445\u0435\u0435\u0432\u043e"
    ],
    "name:und_x_variant":[
        "\u041c\u0438\u0445\u0435\u0435\u0432\u043e"
    ],
    "wof:name":"Mikheyevo",
    "wof:placetype":"locality"
},
  "geometry": {"coordinates":[38.9463,57.9401],"type":"Point"}
}