{
  "type": "Feature",
  "properties": {
    "gn:admin1_code":"51",
    "gn:asciiname":"Makhoni",
    "gn:country_code":"RU",
    "gn:dem":101,
    "gn:feature_class":"P",
    "gn:feature_code":"PPL",
    "gn:name":"Makhoni",
    "gn:population":0,
    "gn:timezone":"Europe/Moscow",
    "iso:country":"RU",
    "name:rus_x_preferred":[
        "\u041c\u0430\u0445\u043e\u043d\u0438"
    ],
    "name:und_x_variant":[
        "\u041c\u0430\u0445\u043e\u043d\u0438"
    ],
    "wof:name":"Makhoni",
    "wof:placetype":"locality"
},
  "geometry": {"coordinates":[45.4233,57.8353],"type":"Point"}
}