{
  "type": "Feature",
  "properties": {
    "gn:admin1_code":"67",
    "gn:asciiname":"Staraya Medynka",
    "gn:country_code":"RU",
    "gn:dem":27,
    "gn:feature_class":"P",
    "gn:feature_code":"PPL",
    "gn:name":"Staraya Medynka",
    "gn:population":0,
    "gn:timezone":"Europe/Saratov",
    "iso:country":"RU",
    "name:rus_x_preferred":[
        "\u0421\u0442\u0430\u0440\u0430\u044f \u041c\u0435\u0434\u044b\u043d\u043a\u0430"
    ],
    "name:und_x_variant":[
        "Medynka"
    ],
    "wof:name":"Staraya Medynka",
    "wof:placetype":"locality"
},
  "geometry": {"coordinates":[48.3158,52.1566],"type":"Point"}
}