{
  "type": "Feature",
  "properties": {
    "gn:admin1_code":"60",
    "gn:asciiname":"Il'ino",
    "gn:country_code":"RU",
    "gn:dem":186,
    "gn:feature_class":"P",
    "gn:feature_code":"PPL",
    "gn:name":"Il\u2019ino",
    "gn:population":0,
    "gn:timezone":"Europe/Moscow",
    "iso:country":"RU",
    "name:rus_x_preferred":[
        "\u0418\u043b\u044c\u0438\u043d\u043e"
    ],
    "name:und_x_variant":[
        "Il\u2019ino",
        "\u0418\u043b\u044c\u0438\u043d\u043e"
    ],
    "wof:name":"Il'ino",
    "wof:placetype":"locality"
},
  "geometry": {"coordinates":[29.8335,56.5644],"type":"Point"}
}