{
  "type": "Feature",
  "properties": {
    "gn:admin1_code":"21.0",
    "gn:asciiname":"Gol'tsovka",
    "gn:country_code":"RU",
    "gn:dem":118,
    "gn:feature_class":"P",
    "gn:feature_code":"PPL",
    "gn:name":"Gol\u2019tsovka",
    "gn:population":0,
    "gn:timezone":"Europe/Moscow",
    "iso:country":"RU",
    "name:rus_x_preferred":[
        "\u0413\u043e\u043b\u044c\u0446\u043e\u0432\u043a\u0430"
    ],
    "name:und_x_variant":[
        "Gol\u2019tsovka",
        "\u0413\u043e\u043b\u044c\u0446\u043e\u0432\u043a\u0430"
    ],
    "wof:name":"Gol'tsovka",
    "wof:placetype":"locality"
},
  "geometry": {"coordinates":[41.89543,57.47425],"type":"Point"}
}