{
  "type": "Feature",
  "properties": {
    "gn:admin1_code":"38.0",
    "gn:asciiname":"Novorozhdestvenskiy",
    "gn:country_code":"RU",
    "gn:dem":40,
    "gn:feature_class":"P",
    "gn:feature_code":"PPL",
    "gn:name":"Novorozhdestvenskiy",
    "gn:population":0,
    "gn:timezone":"Europe/Moscow",
    "iso:country":"RU",
    "wof:name":"Novorozhdestvenskiy",
    "wof:placetype":"locality"
},
  "geometry": {"coordinates":[38.6775,44.88167],"type":"Point"}
}