{
  "type": "Feature",
  "properties": {
    "gn:admin1_code":"10",
    "gn:asciiname":"Petrovaya",
    "gn:country_code":"RU",
    "gn:dem":176,
    "gn:feature_class":"P",
    "gn:feature_code":"PPL",
    "gn:name":"Petrovaya",
    "gn:population":0,
    "gn:timezone":"Europe/Moscow",
    "iso:country":"RU",
    "name:rus_x_preferred":[
        "\u041f\u0435\u0442\u0440\u043e\u0432\u0430\u044f"
    ],
    "name:und_x_variant":[
        "Malakhovka",
        "Petrovaya"
    ],
    "wof:name":"Petrovaya",
    "wof:placetype":"locality"
},
  "geometry": {"coordinates":[33.0089,53.5383],"type":"Point"}
}