{
  "type": "Feature",
  "properties": {
    "gn:admin1_code":"73",
    "gn:asciiname":"Staryy Ashit",
    "gn:country_code":"RU",
    "gn:dem":133,
    "gn:feature_class":"P",
    "gn:feature_code":"PPL",
    "gn:name":"Staryy Ashit",
    "gn:population":0,
    "gn:timezone":"Europe/Moscow",
    "iso:country":"RU",
    "name:eng_x_preferred":[
        "Staryy Ashit"
    ],
    "name:nor_x_preferred":[
        "Star.Asjit"
    ],
    "name:rus_x_preferred":[
        "\u0421\u0442\u0430\u0440.\u0410\u0448\u0438\u0442"
    ],
    "name:rus_x_variant":[
        "\u0421\u0442\u0430\u0440\u044b\u0439 \u0410\u0448\u0438\u0442"
    ],
    "wof:name":"Staryy Ashit",
    "wof:placetype":"locality"
},
  "geometry": {"coordinates":[49.66425,56.34685],"type":"Point"}
}