{
  "type": "Feature",
  "properties": {
    "gn:admin1_code":"90",
    "gn:asciiname":"Kuznetsy",
    "gn:country_code":"RU",
    "gn:dem":208,
    "gn:feature_class":"P",
    "gn:feature_code":"PPL",
    "gn:name":"Kuznetsy",
    "gn:population":0,
    "gn:timezone":"Asia/Yekaterinburg",
    "iso:country":"RU",
    "name:che_x_preferred":[
        "\u041a\u0443\u0437\u043d\u0435\u0446\u044b"
    ],
    "name:rus_x_preferred":[
        "\u041a\u0443\u0437\u043d\u0435\u0446\u044b"
    ],
    "wof:name":"Kuznetsy",
    "wof:placetype":"locality"
},
  "geometry": {"coordinates":[57.5831,57.6252],"type":"Point"}
}