{
  "type": "Feature",
  "properties": {
    "gn:admin1_code":"11",
    "gn:asciiname":"Tarbagatayskiy Stanok",
    "gn:country_code":"RU",
    "gn:dem":615,
    "gn:feature_class":"P",
    "gn:feature_code":"PPL",
    "gn:name":"Tarbagatayskiy Stanok",
    "gn:population":0,
    "gn:timezone":"Asia/Irkutsk",
    "iso:country":"RU",
    "name:und_x_variant":[
        "Tarbagatayskaya Pochtovaya Stantsiya",
        "Tarbagatayskiy Stanok"
    ],
    "wof:name":"Tarbagatayskiy Stanok",
    "wof:placetype":"locality"
},
  "geometry": {"coordinates":[109.23333,52.13333],"type":"Point"}
}