{
  "type": "Feature",
  "properties": {
    "gn:admin1_code":"88.0",
    "gn:asciiname":"Pochinok-Shumilov",
    "gn:country_code":"RU",
    "gn:dem":92,
    "gn:feature_class":"P",
    "gn:feature_code":"PPL",
    "gn:name":"Pochinok-Shumilov",
    "gn:population":0,
    "gn:timezone":"Europe/Moscow",
    "iso:country":"RU",
    "name:rus_x_preferred":[
        "\u041f\u043e\u0447\u0438\u043d\u043e\u043a-\u0428\u0443\u043c\u0438\u043b\u043e\u0432"
    ],
    "wof:name":"Pochinok-Shumilov",
    "wof:placetype":"locality"
},
  "geometry": {"coordinates":[40.9013,58.20236],"type":"Point"}
}