{
  "type": "Feature",
  "properties": {
    "gn:admin1_code":"77",
    "gn:asciiname":"Khoznitsy",
    "gn:country_code":"RU",
    "gn:dem":157,
    "gn:feature_class":"P",
    "gn:feature_code":"PPL",
    "gn:name":"Khoznitsy",
    "gn:population":0,
    "gn:timezone":"Europe/Moscow",
    "iso:country":"RU",
    "name:rus_x_preferred":[
        "\u0425\u043e\u0437\u043d\u0438\u0446\u044b"
    ],
    "name:und_x_variant":[
        "\u0425\u043e\u0437\u043d\u0438\u0446\u044b"
    ],
    "wof:name":"Khoznitsy",
    "wof:placetype":"locality"
},
  "geometry": {"coordinates":[36.871,57.5103],"type":"Point"}
}