{
  "type": "Feature",
  "properties": {
    "gn:admin1_code":"78",
    "gn:asciiname":"Odina",
    "gn:cc2":"RU",
    "gn:country_code":"RU",
    "gn:dem":82,
    "gn:feature_class":"P",
    "gn:feature_code":"PPL",
    "gn:name":"Odina",
    "gn:population":0,
    "gn:timezone":"Asia/Yekaterinburg",
    "iso:country":"RU",
    "name:ceb_x_preferred":[
        "Odina"
    ],
    "name:eng_x_preferred":[
        "Odina"
    ],
    "name:nld_x_preferred":[
        "Odina"
    ],
    "name:nor_x_preferred":[
        "Odino"
    ],
    "name:nor_x_variant":[
        "Odina"
    ],
    "name:rus_x_preferred":[
        "\u041e\u0434\u0438\u043d\u043e"
    ],
    "name:rus_x_variant":[
        "\u041e\u0434\u0438\u043d\u0430"
    ],
    "name:swe_x_preferred":[
        "Odina"
    ],
    "name:und_x_variant":[
        "Odino",
        "Odina",
        "\u041e\u0434\u0438\u043d\u0430"
    ],
    "name:vie_x_preferred":[
        "Odina"
    ],
    "name:war_x_preferred":[
        "Odina"
    ],
    "wof:name":"Odina",
    "wof:placetype":"locality"
},
  "geometry": {"coordinates":[66.03333000000001,56.13333000000001],"type":"Point"}
}