{
  "type": "Feature",
  "properties": {
    "gn:admin1_code":"47",
    "gn:asciiname":"Slepushkino",
    "gn:country_code":"RU",
    "gn:dem":195,
    "gn:feature_class":"P",
    "gn:feature_code":"PPL",
    "gn:name":"Slepushkino",
    "gn:population":0,
    "gn:timezone":"Europe/Moscow",
    "iso:country":"RU",
    "name:rus_x_preferred":[
        "\u0421\u043b\u0435\u043f\u0443\u0448\u043a\u0438\u043d\u043e"
    ],
    "name:und_x_variant":[
        "\u0421\u043b\u0435\u043f\u0443\u0448\u043a\u0438\u043d\u043e"
    ],
    "wof:name":"Slepushkino",
    "wof:placetype":"locality"
},
  "geometry": {"coordinates":[37.35541,55.22541],"type":"Point"}
}