{
  "type": "Feature",
  "properties": {
    "gn:admin1_code":"8",
    "gn:asciiname":"Yakovlevka",
    "gn:country_code":"RU",
    "gn:dem":469,
    "gn:feature_class":"P",
    "gn:feature_code":"PPL",
    "gn:name":"Yakovlevka",
    "gn:population":0,
    "gn:timezone":"Asia/Yekaterinburg",
    "iso:country":"RU",
    "name:rus_x_preferred":[
        "\u042f\u043a\u043e\u0432\u043b\u0435\u0432\u043a\u0430"
    ],
    "wof:name":"Yakovlevka",
    "wof:placetype":"locality"
},
  "geometry": {"coordinates":[57.9734,52.0018],"type":"Point"}
}