{
  "type": "Feature",
  "properties": {
    "gn:admin1_code":"42",
    "gn:asciiname":"Pogorelets",
    "gn:country_code":"RU",
    "gn:dem":63,
    "gn:feature_class":"P",
    "gn:feature_code":"PPL",
    "gn:name":"Pogorelets",
    "gn:population":0,
    "gn:timezone":"Europe/Moscow",
    "iso:country":"RU",
    "name:che_x_preferred":[
        "\u041f\u043e\u0433\u043e\u0440\u0435\u043b\u0435\u0446"
    ],
    "name:rus_x_preferred":[
        "\u041f\u043e\u0433\u043e\u0440\u0435\u043b\u0435\u0446"
    ],
    "name:und_x_variant":[
        "\u041f\u043e\u0433\u043e\u0440\u0435\u043b\u0435\u0446"
    ],
    "wof:name":"Pogorelets",
    "wof:placetype":"locality"
},
  "geometry": {"coordinates":[32.94887,59.90203],"type":"Point"}
}