{
  "type": "Feature",
  "properties": {
    "gn:admin1_code":"37.0",
    "gn:asciiname":"Sukhonogovo",
    "gn:country_code":"RU",
    "gn:dem":103,
    "gn:feature_class":"P",
    "gn:feature_code":"PPL",
    "gn:name":"Sukhonogovo",
    "gn:population":0,
    "gn:timezone":"Europe/Moscow",
    "iso:country":"RU",
    "name:rus_x_preferred":[
        "\u0421\u0443\u0445\u043e\u043d\u043e\u0433\u043e\u0432\u043e"
    ],
    "name:und_x_variant":[
        "Pos\u00eblok Sukhonogovo",
        "Sukhonogovo",
        "\u0421\u0443\u0445\u043e\u043d\u043e\u0433\u043e\u0432\u043e"
    ],
    "wof:name":"Sukhonogovo",
    "wof:placetype":"locality"
},
  "geometry": {"coordinates":[41.0505,57.58068000000001],"type":"Point"}
}