{
  "type": "Feature",
  "properties": {
    "gn:admin1_code":"9",
    "gn:asciiname":"Kiselevka",
    "gn:country_code":"RU",
    "gn:dem":207,
    "gn:feature_class":"P",
    "gn:feature_code":"PPL",
    "gn:name":"Kisel\u00ebvka",
    "gn:population":0,
    "gn:timezone":"Europe/Moscow",
    "iso:country":"RU",
    "name:rus_x_preferred":[
        "\u041a\u0438\u0441\u0435\u043b\u0451\u0432\u043a\u0430"
    ],
    "name:und_x_variant":[
        "Kisel\u00ebvka"
    ],
    "wof:name":"Kiselevka",
    "wof:placetype":"locality"
},
  "geometry": {"coordinates":[35.8166,50.8135],"type":"Point"}
}