{
  "type": "Feature",
  "properties": {
    "gn:admin1_code":"42",
    "gn:asciiname":"Nesterkovo",
    "gn:country_code":"RU",
    "gn:dem":56,
    "gn:feature_class":"P",
    "gn:feature_code":"PPL",
    "gn:name":"Nesterkovo",
    "gn:population":0,
    "gn:timezone":"Europe/Moscow",
    "iso:country":"RU",
    "name:eng_x_preferred":[
        "Nesterkovo"
    ],
    "name:nor_x_preferred":[
        "Nesterkovo"
    ],
    "name:rus_x_preferred":[
        "\u041d\u0435\u0441\u0442\u0435\u0440\u043a\u043e\u0432\u043e"
    ],
    "name:und_x_variant":[
        "Nesterkova",
        "\u041d\u0435\u0441\u0442\u0435\u0440\u043a\u043e\u0432\u043e",
        "Nesterkovo"
    ],
    "wof:name":"Nesterkovo",
    "wof:placetype":"locality"
},
  "geometry": {"coordinates":[30.55417000000001,59.16222],"type":"Point"}
}