{
  "type": "Feature",
  "properties": {
    "gn:admin1_code":"80.0",
    "gn:asciiname":"Garchentsy",
    "gn:country_code":"RU",
    "gn:dem":250,
    "gn:feature_class":"P",
    "gn:feature_code":"PPL",
    "gn:name":"Garchentsy",
    "gn:population":0,
    "gn:timezone":"Europe/Samara",
    "iso:country":"RU",
    "name:rus_x_preferred":[
        "\u0413\u0430\u0440\u0447\u0435\u043d\u0446\u044b"
    ],
    "name:und_x_variant":[
        "Garchen"
    ],
    "wof:name":"Garchentsy",
    "wof:placetype":"locality"
},
  "geometry": {"coordinates":[53.5025,58.4235],"type":"Point"}
}