{
  "type": "Feature",
  "properties": {
    "gn:country":"RU",
    "gn:fcode":"PPL",
    "gn:pop":0,
    "iso:country":"RU",
    "qs:name":"Naumikha",
    "qs:name_adm0":"Russia",
    "qs:name_adm1":"Yaroslavl Oblast",
    "qs:photos_9r":0,
    "qs:photos_sr":0,
    "qs:placetype":"Town",
    "qs:pop_sr":"0",
    "wof:name":"Naumikha",
    "wof:placetype":"locality",
    "wof:population":0
},
  "geometry": {"coordinates":[40.19306,57.75056],"type":"Point"}
}