{
  "type": "Feature",
  "properties": {
    "gn:admin1_code":"33.0",
    "gn:asciiname":"Yermaki",
    "gn:country_code":"RU",
    "gn:dem":174,
    "gn:feature_class":"P",
    "gn:feature_code":"PPL",
    "gn:name":"Yermaki",
    "gn:population":0,
    "gn:timezone":"Europe/Kirov",
    "iso:country":"RU",
    "name:rus_x_preferred":[
        "\u0415\u0440\u043c\u0430\u043a\u0438"
    ],
    "wof:name":"Yermaki",
    "wof:placetype":"locality"
},
  "geometry": {"coordinates":[51.581,57.6391],"type":"Point"}
}