{
  "type": "Feature",
  "properties": {
    "gn:admin1_code":"20",
    "gn:asciiname":"Tseloty",
    "gn:country_code":"RU",
    "gn:dem":454,
    "gn:feature_class":"P",
    "gn:feature_code":"PPL",
    "gn:name":"Tseloty",
    "gn:population":0,
    "gn:timezone":"Asia/Irkutsk",
    "iso:country":"RU",
    "name:eng_x_preferred":[
        "Tseloty"
    ],
    "name:nor_x_preferred":[
        "Tseloty"
    ],
    "name:rus_x_preferred":[
        "\u0426\u0435\u043b\u043e\u0442\u044b"
    ],
    "name:und_x_variant":[
        "Cheloty",
        "Tselota",
        "Cheloti"
    ],
    "wof:name":"Tseloty",
    "wof:placetype":"locality"
},
  "geometry": {"coordinates":[103.54324,52.47716],"type":"Point"}
}