{
  "type": "Feature",
  "properties": {
    "gn:admin1_code":"25",
    "gn:asciiname":"Zimnitskiye Khutora",
    "gn:country_code":"RU",
    "gn:dem":221,
    "gn:feature_class":"P",
    "gn:feature_code":"PPL",
    "gn:name":"Zimnitskiye Khutora",
    "gn:population":0,
    "gn:timezone":"Europe/Moscow",
    "iso:country":"RU",
    "wof:name":"Zimnitskiye Khutora",
    "wof:placetype":"locality"
},
  "geometry": {"coordinates":[34.11952,54.00699],"type":"Point"}
}