{
  "type": "Feature",
  "properties": {
    "gn:admin1_code":"57",
    "gn:asciiname":"Novyy Valovoy",
    "gn:country_code":"RU",
    "gn:dem":203,
    "gn:feature_class":"P",
    "gn:feature_code":"PPL",
    "gn:name":"Novyy Valovoy",
    "gn:population":0,
    "gn:timezone":"Europe/Moscow",
    "iso:country":"RU",
    "name:eng_x_preferred":[
        "Novyy Valovoy"
    ],
    "name:nor_x_preferred":[
        "Nov.Valovaj"
    ],
    "name:rus_x_preferred":[
        "\u041d\u043e\u0432.\u0412\u0430\u043b\u043e\u0432\u0430\u0439"
    ],
    "name:rus_x_variant":[
        "\u041d\u043e\u0432\u044b\u0439 \u0412\u0430\u043b\u043e\u0432\u043e\u0439"
    ],
    "name:und_x_variant":[
        "Novy Valovay",
        "Novyy Valovay"
    ],
    "wof:name":"Novyy Valovoy",
    "wof:placetype":"locality"
},
  "geometry": {"coordinates":[43.24372,53.20016],"type":"Point"}
}