{
  "type": "Feature",
  "properties": {
    "gn:admin1_code":"33",
    "gn:asciiname":"Maloye Panchino",
    "gn:country_code":"RU",
    "gn:dem":126,
    "gn:feature_class":"P",
    "gn:feature_code":"PPL",
    "gn:name":"Maloye Panchino",
    "gn:population":0,
    "gn:timezone":"Europe/Kirov",
    "iso:country":"RU",
    "name:rus_x_preferred":[
        "\u041c\u0430\u043b\u043e\u0435 \u041f\u0430\u043d\u0447\u0438\u043d\u043e"
    ],
    "wof:name":"Maloye Panchino",
    "wof:placetype":"locality"
},
  "geometry": {"coordinates":[47.8658,57.4066],"type":"Point"}
}