{
  "type": "Feature",
  "properties": {
    "gn:admin1_code":"73",
    "gn:asciiname":"Maskara",
    "gn:country_code":"RU",
    "gn:dem":77,
    "gn:feature_class":"P",
    "gn:feature_code":"PPL",
    "gn:name":"Maskara",
    "gn:population":0,
    "gn:timezone":"Europe/Moscow",
    "iso:country":"RU",
    "name:rus_x_preferred":[
        "\u041c\u0430\u0441\u043a\u0430\u0440\u0430"
    ],
    "wof:name":"Maskara",
    "wof:placetype":"locality"
},
  "geometry": {"coordinates":[50.8331,56.3398],"type":"Point"}
}