{
  "type": "Feature",
  "properties": {
    "gn:admin1_code":"77.0",
    "gn:asciiname":"Berezha",
    "gn:country_code":"RU",
    "gn:dem":140,
    "gn:feature_class":"P",
    "gn:feature_code":"PPL",
    "gn:name":"Berezha",
    "gn:population":0,
    "gn:timezone":"Europe/Moscow",
    "iso:country":"RU",
    "name:eng_x_preferred":[
        "Berezha"
    ],
    "name:rus_x_preferred":[
        "\u0411\u043e\u043b.\u0411\u0435\u0440\u0435\u0436\u0430"
    ],
    "name:rus_x_variant":[
        "\u0411\u0435\u0440\u0435\u0436\u0430"
    ],
    "name:und_x_variant":[
        "Beresha",
        "Bol\u2019shaya Berezha"
    ],
    "wof:name":"Berezha",
    "wof:placetype":"locality"
},
  "geometry": {"coordinates":[36.37311,57.6311],"type":"Point"}
}