{
  "type": "Feature",
  "properties": {
    "gn:country":"RU",
    "gn:fcode":"PPL",
    "gn:population":0,
    "iso:country":"RU",
    "name:fin_x_preferred":[
        "Paaritsa"
    ],
    "name:rus_x_preferred":[
        "\u041f\u0430\u0440\u0438\u0446\u044b"
    ],
    "name:und_x_variant":[
        "Paritsy"
    ],
    "qs:name":"Paritsj",
    "qs:name_adm0":"Russia",
    "qs:name_adm1":"Leningrad Oblast",
    "qs:photos_9r":0,
    "qs:photos_sr":0,
    "qs:placetype":"Town",
    "qs:pop_sr":"0",
    "wof:name":"Paritsj",
    "wof:placetype":"locality",
    "wof:population":0
},
  "geometry": {"coordinates":[30.03611,59.53556],"type":"Point"}
}