{
  "type": "Feature",
  "properties": {
    "gn:admin1_code":"61.0",
    "gn:asciiname":"Balabanovka",
    "gn:country_code":"RU",
    "gn:dem":78,
    "gn:feature_class":"P",
    "gn:feature_code":"PPL",
    "gn:name":"Balabanovka",
    "gn:population":0,
    "gn:timezone":"Europe/Moscow",
    "iso:country":"RU",
    "name:nor_x_preferred":[
        "Balabanovka"
    ],
    "name:rus_x_preferred":[
        "\u0411\u0430\u043b\u0430\u0431\u0430\u043d\u043e\u0432\u043a\u0430"
    ],
    "wof:name":"Balabanovka",
    "wof:placetype":"locality"
},
  "geometry": {"coordinates":[40.70976,49.04049000000001],"type":"Point"}
}