{
  "type": "Feature",
  "properties": {
    "gn:admin1_code":"88",
    "gn:asciiname":"Yepikharka",
    "gn:country_code":"RU",
    "gn:dem":188,
    "gn:feature_class":"P",
    "gn:feature_code":"PPL",
    "gn:name":"Yepikharka",
    "gn:population":0,
    "gn:timezone":"Europe/Moscow",
    "iso:country":"RU",
    "name:rus_x_preferred":[
        "\u0415\u043f\u0438\u0445\u0430\u0440\u043a\u0430"
    ],
    "wof:name":"Yepikharka",
    "wof:placetype":"locality"
},
  "geometry": {"coordinates":[38.6161,57.36600000000001],"type":"Point"}
}