{
  "type": "Feature",
  "properties": {
    "gn:admin1_code":"28",
    "gn:asciiname":"Lekhta",
    "gn:country_code":"RU",
    "gn:dem":102,
    "gn:feature_class":"P",
    "gn:feature_code":"PPL",
    "gn:name":"Lekhta",
    "gn:population":0,
    "gn:timezone":"Europe/Moscow",
    "iso:country":"RU",
    "name:eng_x_preferred":[
        "Lekhta"
    ],
    "name:fin_x_preferred":[
        "Lehto"
    ],
    "name:nor_x_preferred":[
        "Lekhta"
    ],
    "name:rus_x_preferred":[
        "\u041b\u0435\u0445\u0442\u0430"
    ],
    "wof:name":"Lekhta",
    "wof:placetype":"locality"
},
  "geometry": {"coordinates":[33.98034000000001,64.42201999999999],"type":"Point"}
}