{
  "type": "Feature",
  "properties": {
    "gn:admin1_code":"71",
    "gn:asciiname":"Yermakovo",
    "gn:country_code":"RU",
    "gn:dem":59,
    "gn:feature_class":"P",
    "gn:feature_code":"PPL",
    "gn:name":"Yermakovo",
    "gn:population":0,
    "gn:timezone":"Asia/Yekaterinburg",
    "iso:country":"RU",
    "name:rus_x_preferred":[
        "\u0415\u0440\u043c\u0430\u043a\u043e\u0432\u043e"
    ],
    "name:und_x_variant":[
        "Yermakova",
        "Yermakovo",
        "\u0415\u0440\u043c\u0430\u043a\u043e\u0432\u043e"
    ],
    "wof:name":"Yermakovo",
    "wof:placetype":"locality"
},
  "geometry": {"coordinates":[64.75168000000001,58.48425],"type":"Point"}
}