{
  "type": "Feature",
  "properties": {
    "gn:admin1_code":"77",
    "gn:asciiname":"Osinovik",
    "gn:country_code":"RU",
    "gn:dem":165,
    "gn:feature_class":"P",
    "gn:feature_code":"PPL",
    "gn:name":"Osinovik",
    "gn:population":0,
    "gn:timezone":"Europe/Moscow",
    "iso:country":"RU",
    "name:eng_x_preferred":[
        "Osinovik"
    ],
    "name:nor_x_preferred":[
        "Osinovik"
    ],
    "name:rus_x_preferred":[
        "\u041e\u0441\u0438\u043d\u043e\u0432\u0438\u043a"
    ],
    "name:und_x_variant":[
        "Osinovika",
        "\u041e\u0441\u0438\u043d\u043e\u0432\u0438\u043a",
        "Osinovik"
    ],
    "wof:name":"Osinovik",
    "wof:placetype":"locality"
},
  "geometry": {"coordinates":[34.8468,57.76994000000001],"type":"Point"}
}