{
  "type": "Feature",
  "properties": {
    "gn:admin1_code":"12.0",
    "gn:asciiname":"Tsinchemerker",
    "gn:country_code":"RU",
    "gn:dem":2037,
    "gn:feature_class":"P",
    "gn:feature_code":"PPL",
    "gn:name":"Tsinchemerker",
    "gn:population":0,
    "gn:timezone":"Europe/Moscow",
    "iso:country":"RU",
    "wof:name":"Tsinchemerker",
    "wof:placetype":"locality"
},
  "geometry": {"coordinates":[45.24361,42.73583],"type":"Point"}
}