{
  "type": "Feature",
  "properties": {
    "gn:admin1_code":"90",
    "gn:asciiname":"Barbautovo",
    "gn:country_code":"RU",
    "gn:dem":144,
    "gn:feature_class":"P",
    "gn:feature_code":"PPL",
    "gn:name":"Barbautovo",
    "gn:population":0,
    "gn:timezone":"Asia/Yekaterinburg",
    "iso:country":"RU",
    "name:nor_x_preferred":[
        "Barbautovo"
    ],
    "name:rus_x_preferred":[
        "\u0411\u0430\u0440\u0431\u0430\u0443\u0442\u043e\u0432\u043e"
    ],
    "wof:name":"Barbautovo",
    "wof:placetype":"locality"
},
  "geometry": {"coordinates":[56.5473,57.4989],"type":"Point"}
}