{
  "type": "Feature",
  "properties": {
    "gn:admin1_code":"33",
    "gn:asciiname":"Gorinovo",
    "gn:country_code":"RU",
    "gn:dem":130,
    "gn:feature_class":"P",
    "gn:feature_code":"PPL",
    "gn:name":"Gorinovo",
    "gn:population":0,
    "gn:timezone":"Europe/Kirov",
    "iso:country":"RU",
    "name:rus_x_preferred":[
        "\u0413\u043e\u0440\u0438\u043d\u043e\u0432\u043e"
    ],
    "wof:name":"Gorinovo",
    "wof:placetype":"locality"
},
  "geometry": {"coordinates":[49.0476,57.32899999999999],"type":"Point"}
}