{
  "type": "Feature",
  "properties": {
    "gn:admin1_code":"8.0",
    "gn:asciiname":"Badryash",
    "gn:country_code":"RU",
    "gn:dem":85,
    "gn:feature_class":"P",
    "gn:feature_code":"PPL",
    "gn:name":"Badryash",
    "gn:population":0,
    "gn:timezone":"Asia/Yekaterinburg",
    "iso:country":"RU",
    "name:nor_x_preferred":[
        "Badrjasj"
    ],
    "name:rus_x_preferred":[
        "\u0411\u0430\u0434\u0440\u044f\u0448"
    ],
    "wof:name":"Badryash",
    "wof:placetype":"locality"
},
  "geometry": {"coordinates":[54.73333,56.25],"type":"Point"}
}