{
  "type": "Feature",
  "properties": {
    "gn:admin1_code":"10.0",
    "gn:asciiname":"Bystraya",
    "gn:country_code":"RU",
    "gn:dem":175,
    "gn:feature_class":"P",
    "gn:feature_code":"PPL",
    "gn:name":"Bystraya",
    "gn:population":0,
    "gn:timezone":"Europe/Moscow",
    "iso:country":"RU",
    "name:rus_x_preferred":[
        "\u0411\u044b\u0441\u0442\u0440\u0430\u044f"
    ],
    "wof:name":"Bystraya",
    "wof:placetype":"locality"
},
  "geometry": {"coordinates":[33.19772,53.3119],"type":"Point"}
}