{
  "type": "Feature",
  "properties": {
    "gn:admin1_code":"7.0",
    "gn:asciiname":"Ozernoye",
    "gn:country_code":"RU",
    "gn:dem":-21,
    "gn:feature_class":"P",
    "gn:feature_code":"PPL",
    "gn:name":"Oz\u00ebrnoye",
    "gn:population":0,
    "gn:timezone":"Europe/Astrakhan",
    "iso:country":"RU",
    "name:eng_x_preferred":[
        "Ozernoye"
    ],
    "name:nor_x_preferred":[
        "Ozernoje"
    ],
    "name:rus_x_preferred":[
        "\u041e\u0437\u0435\u0440\u043d\u043e\u0435"
    ],
    "name:rus_x_variant":[
        "\u041e\u0437\u0451\u0440\u043d\u043e\u0435"
    ],
    "name:und_x_variant":[
        "Oz\u00ebrnoye"
    ],
    "wof:name":"Ozernoye",
    "wof:placetype":"locality"
},
  "geometry": {"coordinates":[47.47712,46.08022],"type":"Point"}
}