{
  "type": "Feature",
  "properties": {
    "gn:admin1_code":"71",
    "gn:asciiname":"Cheremkhovo",
    "gn:country_code":"RU",
    "gn:dem":166,
    "gn:feature_class":"P",
    "gn:feature_code":"PPL",
    "gn:name":"Cheremkhovo",
    "gn:population":0,
    "gn:timezone":"Asia/Yekaterinburg",
    "iso:country":"RU",
    "name:eng_x_preferred":[
        "Cheremkhovo"
    ],
    "name:nor_x_preferred":[
        "Tsjeremkhovo"
    ],
    "name:rus_x_preferred":[
        "\u0427\u0435\u0440\u0435\u043c\u0445\u043e\u0432\u043e"
    ],
    "name:und_x_variant":[
        "Cheremkhovskoye",
        "\u0427\u0435\u0440\u0435\u043c\u0445\u043e\u0432\u043e",
        "Cheremkhovo",
        "Bortnikovo"
    ],
    "wof:name":"Cheremkhovo",
    "wof:placetype":"locality"
},
  "geometry": {"coordinates":[61.78639,56.49472],"type":"Point"}
}