{
  "type": "Feature",
  "properties": {
    "gn:admin1_code":"6.0",
    "gn:asciiname":"Bol'shoye Samkovo",
    "gn:country_code":"RU",
    "gn:dem":99,
    "gn:feature_class":"P",
    "gn:feature_code":"PPL",
    "gn:name":"Bol\u2019shoye Samkovo",
    "gn:population":0,
    "gn:timezone":"Europe/Moscow",
    "iso:country":"RU",
    "name:eng_x_preferred":[
        "Bol'shoye Samkovo"
    ],
    "name:nor_x_preferred":[
        "Samkovo"
    ],
    "name:rus_x_preferred":[
        "\u0421\u0430\u043c\u043a\u043e\u0432\u043e"
    ],
    "name:rus_x_variant":[
        "\u0411\u043e\u043b\u044c\u0448\u043e\u0435 \u0421\u0430\u043c\u043a\u043e\u0432\u043e"
    ],
    "name:und_x_variant":[
        "Samkovo",
        "Bol\u2019shoye Samkovo",
        "\u0411\u043e\u043b\u044c\u0448\u043e\u0435 \u0421\u0430\u043c\u043a\u043e\u0432\u043e"
    ],
    "wof:name":"Bol'shoye Samkovo",
    "wof:placetype":"locality"
},
  "geometry": {"coordinates":[38.69368,62.1452],"type":"Point"}
}