{
  "type": "Feature",
  "properties": {
    "gn:admin1_code":"33",
    "gn:asciiname":"Kolpaki",
    "gn:country_code":"RU",
    "gn:dem":172,
    "gn:feature_class":"P",
    "gn:feature_code":"PPL",
    "gn:name":"Kolpaki",
    "gn:population":0,
    "gn:timezone":"Europe/Kirov",
    "iso:country":"RU",
    "name:rus_x_preferred":[
        "\u041a\u043e\u043b\u043f\u0430\u043a\u0438"
    ],
    "wof:name":"Kolpaki",
    "wof:placetype":"locality"
},
  "geometry": {"coordinates":[49.79142,58.37859],"type":"Point"}
}