{
  "type": "Feature",
  "properties": {
    "gn:admin1_code":"40",
    "gn:asciiname":"Nizhnetobol'noye",
    "gn:country_code":"RU",
    "gn:dem":65,
    "gn:feature_class":"P",
    "gn:feature_code":"PPL",
    "gn:name":"Nizhnetobol\u2019noye",
    "gn:population":0,
    "gn:timezone":"Asia/Yekaterinburg",
    "iso:country":"RU",
    "name:eng_x_preferred":[
        "Nizhnetobol'noye"
    ],
    "name:nor_x_preferred":[
        "Mensjtsjikovo"
    ],
    "name:rus_x_preferred":[
        "\u041c\u0435\u043d\u044c\u0449\u0438\u043a\u043e\u0432\u043e"
    ],
    "name:rus_x_variant":[
        "\u041d\u0438\u0436\u043d\u0435\u0442\u043e\u0431\u043e\u043b\u044c\u043d\u043e\u0435"
    ],
    "name:und_x_variant":[
        "Men\u2019shikova",
        "Men\u2019shchikovo",
        "Nizhnetobol\u2019noye"
    ],
    "wof:name":"Nizhnetobol'noye",
    "wof:placetype":"locality"
},
  "geometry": {"coordinates":[65.61139,55.77111],"type":"Point"}
}