{
  "type": "Feature",
  "properties": {
    "gn:admin1_code":"69",
    "gn:asciiname":"Pyatoye",
    "gn:country_code":"RU",
    "gn:dem":196,
    "gn:feature_class":"P",
    "gn:feature_code":"PPL",
    "gn:name":"Pyatoye",
    "gn:population":0,
    "gn:timezone":"Europe/Moscow",
    "iso:country":"RU",
    "name:rus_x_preferred":[
        "\u041f\u044f\u0442\u043e\u0435"
    ],
    "name:und_x_variant":[
        "Pyataya",
        "Pyatoye"
    ],
    "wof:name":"Pyatoye",
    "wof:placetype":"locality"
},
  "geometry": {"coordinates":[32.77014,54.20452],"type":"Point"}
}