{
  "type": "Feature",
  "properties": {
    "gn:admin1_code":"85",
    "gn:asciiname":"Yartsevo",
    "gn:country_code":"RU",
    "gn:dem":132,
    "gn:feature_class":"P",
    "gn:feature_code":"PPL",
    "gn:name":"Yartsevo",
    "gn:population":0,
    "gn:timezone":"Europe/Moscow",
    "iso:country":"RU",
    "name:rus_x_preferred":[
        "\u042f\u0440\u0446\u0435\u0432\u043e"
    ],
    "wof:name":"Yartsevo",
    "wof:placetype":"locality"
},
  "geometry": {"coordinates":[36.7518,58.7262],"type":"Point"}
}