{
  "type": "Feature",
  "properties": {
    "gn:admin1_code":"38",
    "gn:asciiname":"Protichka",
    "gn:country_code":"RU",
    "gn:dem":2,
    "gn:feature_class":"P",
    "gn:feature_code":"PPL",
    "gn:name":"Protichka",
    "gn:population":0,
    "gn:timezone":"Europe/Moscow",
    "iso:country":"RU",
    "name:eng_x_preferred":[
        "Protichka"
    ],
    "name:nor_x_preferred":[
        "Protitsjka"
    ],
    "name:rus_x_preferred":[
        "\u041f\u0440\u043e\u0442\u0438\u0447\u043a\u0430"
    ],
    "wof:name":"Protichka",
    "wof:placetype":"locality"
},
  "geometry": {"coordinates":[38.09844,45.41378],"type":"Point"}
}