{
  "type": "Feature",
  "properties": {
    "gn:admin1_code":"59",
    "gn:asciiname":"Zaysanovka",
    "gn:country_code":"RU",
    "gn:dem":44,
    "gn:feature_class":"P",
    "gn:feature_code":"PPL",
    "gn:name":"Zaysanovka",
    "gn:population":0,
    "gn:timezone":"Asia/Vladivostok",
    "iso:country":"RU",
    "name:rus_x_preferred":[
        "\u0417\u0430\u0439\u0441\u0430\u043d\u043e\u0432\u043a\u0430"
    ],
    "wof:name":"Zaysanovka",
    "wof:placetype":"locality"
},
  "geometry": {"coordinates":[130.83948000000001,42.71126],"type":"Point"}
}