{
  "type": "Feature",
  "properties": {
    "gn:admin1_code":"21.0",
    "gn:asciiname":"Meshino",
    "gn:country_code":"RU",
    "gn:dem":132,
    "gn:feature_class":"P",
    "gn:feature_code":"PPL",
    "gn:name":"Meshino",
    "gn:population":0,
    "gn:timezone":"Europe/Moscow",
    "iso:country":"RU",
    "name:rus_x_preferred":[
        "\u041c\u0435\u0448\u0438\u043d\u043e"
    ],
    "wof:name":"Meshino",
    "wof:placetype":"locality"
},
  "geometry": {"coordinates":[42.3522,57.42762],"type":"Point"}
}