{
  "type": "Feature",
  "properties": {
    "gn:admin1_code":"77",
    "gn:asciiname":"Lugi",
    "gn:country_code":"RU",
    "gn:dem":232,
    "gn:feature_class":"P",
    "gn:feature_code":"PPL",
    "gn:name":"Lugi",
    "gn:population":0,
    "gn:timezone":"Europe/Moscow",
    "iso:country":"RU",
    "name:bre_x_preferred":[
        "Lugi"
    ],
    "name:cat_x_preferred":[
        "Loges"
    ],
    "name:deu_x_preferred":[
        "Lugi"
    ],
    "name:rus_x_preferred":[
        "\u041b\u0443\u0433\u0438"
    ],
    "name:spa_x_preferred":[
        "Lugi"
    ],
    "wof:name":"Lugi",
    "wof:placetype":"locality"
},
  "geometry": {"coordinates":[32.46103,56.71527],"type":"Point"}
}