{
  "type": "Feature",
  "properties": {
    "gn:admin1_code":"69.0",
    "gn:asciiname":"Gavryukovo",
    "gn:cc2":"RU",
    "gn:country_code":"RU",
    "gn:dem":203,
    "gn:feature_class":"P",
    "gn:feature_code":"PPL",
    "gn:name":"Gavryukovo",
    "gn:population":0,
    "gn:timezone":"Europe/Moscow",
    "iso:country":"RU",
    "name:rus_x_preferred":[
        "\u0413\u0430\u0432\u0440\u044e\u043a\u043e\u0432\u043e"
    ],
    "name:und_x_variant":[
        "Pryukovo",
        "Gryukovo",
        "Gavryukovo"
    ],
    "wof:name":"Gavryukovo",
    "wof:placetype":"locality"
},
  "geometry": {"coordinates":[33.6825,54.86806],"type":"Point"}
}