{
  "type": "Feature",
  "properties": {
    "gn:admin1_code":"69",
    "gn:asciiname":"Ivashutino",
    "gn:country_code":"RU",
    "gn:dem":185,
    "gn:feature_class":"P",
    "gn:feature_code":"PPL",
    "gn:name":"Ivashutino",
    "gn:population":0,
    "gn:timezone":"Europe/Moscow",
    "iso:country":"RU",
    "name:rus_x_preferred":[
        "\u0418\u0432\u0430\u0448\u0443\u0442\u0438\u043d\u043e"
    ],
    "name:und_x_variant":[
        "Ivashutina",
        "Ivashutino",
        "\u0418\u0432\u0430\u0448\u0443\u0442\u0438\u043d\u043e"
    ],
    "wof:name":"Ivashutino",
    "wof:placetype":"locality"
},
  "geometry": {"coordinates":[34.86991,55.03315],"type":"Point"}
}