{
  "type": "Feature",
  "properties": {
    "gn:admin1_code":"56",
    "gn:asciiname":"Shakhovo",
    "gn:country_code":"RU",
    "gn:dem":161,
    "gn:feature_class":"P",
    "gn:feature_code":"PPL",
    "gn:name":"Shakhovo",
    "gn:population":0,
    "gn:timezone":"Europe/Moscow",
    "iso:country":"RU",
    "name:eng_x_preferred":[
        "Shakhovo"
    ],
    "name:nor_x_preferred":[
        "Sjakhovo"
    ],
    "name:rus_x_preferred":[
        "\u0428\u0430\u0445\u043e\u0432\u043e"
    ],
    "wof:name":"Shakhovo",
    "wof:placetype":"locality"
},
  "geometry": {"coordinates":[35.85843,52.75965],"type":"Point"}
}