{
  "type": "Feature",
  "properties": {
    "gn:admin1_code":"51.0",
    "gn:asciiname":"Slyshkovo",
    "gn:country_code":"RU",
    "gn:dem":106,
    "gn:feature_class":"P",
    "gn:feature_code":"PPL",
    "gn:name":"Slyshkovo",
    "gn:population":0,
    "gn:timezone":"Europe/Moscow",
    "iso:country":"RU",
    "name:nor_x_preferred":[
        "Slysjkovo"
    ],
    "name:rus_x_preferred":[
        "\u0421\u043b\u044b\u0448\u043a\u043e\u0432\u043e"
    ],
    "wof:name":"Slyshkovo",
    "wof:placetype":"locality"
},
  "geometry": {"coordinates":[43.73754,56.85014],"type":"Point"}
}