{
  "type": "Feature",
  "properties": {
    "gn:admin1_code":"62",
    "gn:asciiname":"Kamennyy Khutor Pervyy",
    "gn:country_code":"RU",
    "gn:dem":136,
    "gn:feature_class":"P",
    "gn:feature_code":"PPL",
    "gn:name":"Kamennyy Khutor Pervyy",
    "gn:population":0,
    "gn:timezone":"Europe/Moscow",
    "iso:country":"RU",
    "name:rus_x_preferred":[
        "\u041a\u0430\u043c\u0435\u043d\u043d\u044b\u0439 \u0425\u0443\u0442\u043e\u0440 \u041f\u0435\u0440\u0432\u044b\u0439"
    ],
    "name:und_x_variant":[
        "Kamennyye Vyselki Pervyye",
        "Kamennyy Khutor Pervyy",
        "\u041a\u0430\u043c\u0435\u043d\u043d\u044b\u0439 \u0425\u0443\u0442\u043e\u0440 \u041f\u0435\u0440\u0432\u044b\u0439"
    ],
    "wof:name":"Kamennyy Khutor Pervyy",
    "wof:placetype":"locality"
},
  "geometry": {"coordinates":[39.2786,54.0668],"type":"Point"}
}