{
  "type": "Feature",
  "properties": {
    "gn:admin1_code":"90.0",
    "gn:asciiname":"Bol'shoy Sars",
    "gn:country_code":"RU",
    "gn:dem":265,
    "gn:feature_class":"P",
    "gn:feature_code":"PPL",
    "gn:name":"Bol\u2019shoy Sars",
    "gn:population":0,
    "gn:timezone":"Asia/Yekaterinburg",
    "iso:country":"RU",
    "name:eng_x_preferred":[
        "Bol'shoy Sars"
    ],
    "name:rus_x_preferred":[
        "\u0411\u043e\u043b.\u0421\u0430\u0440\u0441"
    ],
    "name:rus_x_variant":[
        "\u0421\u0430\u0440\u0441",
        "\u0411\u043e\u043b\u044c\u0448\u043e\u0439 \u0421\u0430\u0440\u0441"
    ],
    "name:und_x_variant":[
        "Sars",
        "Bol\u2019shoy Sars",
        "\u0411\u043e\u043b\u044c\u0448\u043e\u0439 \u0421\u0430\u0440\u0441"
    ],
    "wof:name":"Bol'shoy Sars",
    "wof:placetype":"locality"
},
  "geometry": {"coordinates":[57.11733,56.47488000000001],"type":"Point"}
}