{
  "type": "Feature",
  "properties": {
    "gn:admin1_code":"13",
    "gn:asciiname":"Sotsgorod",
    "gn:country_code":"RU",
    "gn:dem":231,
    "gn:feature_class":"P",
    "gn:feature_code":"PPL",
    "gn:name":"Sotsgorod",
    "gn:population":0,
    "gn:timezone":"Asia/Yekaterinburg",
    "iso:country":"RU",
    "name:rus_x_preferred":[
        "\u0421\u043e\u0446\u0433\u043e\u0440\u043e\u0434"
    ],
    "name:und_x_variant":[
        "\u0421\u043e\u0446\u0433\u043e\u0440\u043e\u0434"
    ],
    "wof:name":"Sotsgorod",
    "wof:placetype":"locality"
},
  "geometry": {"coordinates":[61.3756,55.2561],"type":"Point"}
}