{
  "type": "Feature",
  "properties": {
    "gn:admin1_code":"54",
    "gn:asciiname":"Novopavlovka",
    "gn:country_code":"RU",
    "gn:dem":115,
    "gn:feature_class":"P",
    "gn:feature_code":"PPL",
    "gn:name":"Novopavlovka",
    "gn:population":0,
    "gn:timezone":"Asia/Omsk",
    "iso:country":"RU",
    "name:rus_x_preferred":[
        "\u041d\u043e\u0432\u043e\u043f\u0430\u0432\u043b\u043e\u0432\u043a\u0430"
    ],
    "wof:name":"Novopavlovka",
    "wof:placetype":"locality"
},
  "geometry": {"coordinates":[72.98860000000001,54.2859],"type":"Point"}
}