{
  "type": "Feature",
  "properties": {
    "gn:admin1_code":"86",
    "gn:asciiname":"Krivaya Bereza",
    "gn:country_code":"RU",
    "gn:dem":202,
    "gn:feature_class":"P",
    "gn:feature_code":"PPL",
    "gn:name":"Krivaya Ber\u00ebza",
    "gn:population":0,
    "gn:timezone":"Europe/Moscow",
    "iso:country":"RU",
    "name:rus_x_preferred":[
        "\u041a\u0440\u0438\u0432\u0430\u044f \u0411\u0435\u0440\u0451\u0437\u0430"
    ],
    "name:und_x_variant":[
        "Krivaya Ber\u00ebza",
        "\u041a\u0440\u0438\u0432\u0430\u044f \u0411\u0435\u0440\u0451\u0437\u0430"
    ],
    "wof:name":"Krivaya Bereza",
    "wof:placetype":"locality"
},
  "geometry": {"coordinates":[39.02284,50.43699],"type":"Point"}
}