{
  "type": "Feature",
  "properties": {
    "gn:admin1_code":"42",
    "gn:asciiname":"Korkholan-Yaama",
    "gn:country_code":"RU",
    "gn:dem":38,
    "gn:feature_class":"P",
    "gn:feature_code":"PPL",
    "gn:name":"Korkholan-Yaama",
    "gn:population":0,
    "gn:timezone":"Europe/Moscow",
    "iso:country":"RU",
    "name:fin_x_preferred":[
        "Korholanjaama"
    ],
    "name:rus_x_preferred":[
        "\u041a\u043e\u0440\u0445\u043e\u043b\u0430\u043d-\u042f\u0430\u043c\u0430"
    ],
    "name:und_x_variant":[
        "\u041a\u043e\u0440\u0445\u043e\u043b\u0430\u043d-\u042f\u0430\u043c\u0430"
    ],
    "wof:name":"Korkholan-Yaama",
    "wof:placetype":"locality"
},
  "geometry": {"coordinates":[30.56705,60.53398000000001],"type":"Point"}
}