{
  "type": "Feature",
  "properties": {
    "gn:admin1_code":"76",
    "gn:asciiname":"Petelino",
    "gn:country_code":"RU",
    "gn:dem":219,
    "gn:feature_class":"P",
    "gn:feature_code":"PPL",
    "gn:name":"Petelino",
    "gn:population":0,
    "gn:timezone":"Europe/Moscow",
    "iso:country":"RU",
    "name:rus_x_preferred":[
        "\u041f\u0435\u0442\u0435\u043b\u0438\u043d\u043e"
    ],
    "name:und_x_variant":[
        "Pitel\u2019nya",
        "Potelino",
        "Petelino"
    ],
    "wof:name":"Petelino",
    "wof:placetype":"locality"
},
  "geometry": {"coordinates":[37.70432,54.13141],"type":"Point"}
}