{
  "type": "Feature",
  "properties": {
    "gn:admin1_code":"78",
    "gn:asciiname":"Tyunevo",
    "gn:country_code":"RU",
    "gn:dem":69,
    "gn:feature_class":"P",
    "gn:feature_code":"PPL",
    "gn:name":"Tyun\u00ebvo",
    "gn:population":0,
    "gn:timezone":"Asia/Yekaterinburg",
    "iso:country":"RU",
    "name:eng_x_preferred":[
        "Tyun\u00ebvo"
    ],
    "name:nor_x_preferred":[
        "Tjunevo"
    ],
    "name:rus_x_preferred":[
        "\u0422\u044e\u043d\u0435\u0432\u043e"
    ],
    "name:rus_x_variant":[
        "\u0422\u044e\u043d\u0451\u0432\u043e"
    ],
    "wof:name":"Tyunevo",
    "wof:placetype":"locality"
},
  "geometry": {"coordinates":[65.69738000000001,57.39032],"type":"Point"}
}