{
  "type": "Feature",
  "properties": {
    "gn:admin1_code":"60",
    "gn:asciiname":"Grivino",
    "gn:country_code":"RU",
    "gn:dem":105,
    "gn:feature_class":"P",
    "gn:feature_code":"PPL",
    "gn:name":"Grivino",
    "gn:population":0,
    "gn:timezone":"Europe/Moscow",
    "iso:country":"RU",
    "name:rus_x_preferred":[
        "\u0413\u0440\u0438\u0432\u0438\u043d\u043e"
    ],
    "name:und_x_variant":[
        "\u0413\u0440\u0438\u0432\u0438\u043d\u043e"
    ],
    "wof:name":"Grivino",
    "wof:placetype":"locality"
},
  "geometry": {"coordinates":[29.54129,57.00723000000001],"type":"Point"}
}