{
  "type": "Feature",
  "properties": {
    "gn:admin1_code":"90.0",
    "gn:asciiname":"Novoil'inskiy",
    "gn:country_code":"RU",
    "gn:dem":98,
    "gn:feature_class":"P",
    "gn:feature_code":"PPL",
    "gn:name":"Novoil\u2019inskiy",
    "gn:population":0,
    "gn:timezone":"Asia/Yekaterinburg",
    "iso:country":"RU",
    "name:rus_x_preferred":[
        "\u041d\u043e\u0432\u043e\u0438\u043b\u044c\u0438\u043d\u0441\u043a\u0438\u0439"
    ],
    "name:und_x_variant":[
        "Novoil\u2019inskiy",
        "\u041d\u043e\u0432\u043e\u0438\u043b\u044c\u0438\u043d\u0441\u043a\u0438\u0439"
    ],
    "wof:name":"Novoil'inskiy",
    "wof:placetype":"locality"
},
  "geometry": {"coordinates":[55.4914,57.9211],"type":"Point"}
}