{
  "type": "Feature",
  "properties": {
    "gn:admin1_code":"53",
    "gn:asciiname":"Klyuchevskoy",
    "gn:cc2":"RU",
    "gn:country_code":"RU",
    "gn:dem":186,
    "gn:feature_class":"P",
    "gn:feature_code":"PPL",
    "gn:name":"Klyuchevskoy",
    "gn:population":0,
    "gn:timezone":"Asia/Novosibirsk",
    "iso:country":"RU",
    "name:rus_x_preferred":[
        "\u041a\u043b\u044e\u0447\u0435\u0432\u0441\u043a\u043e\u0439"
    ],
    "name:und_x_variant":[
        "Klyuchevskiy",
        "Klyuchevskoy"
    ],
    "wof:name":"Klyuchevskoy",
    "wof:placetype":"locality"
},
  "geometry": {"coordinates":[83.65000000000001,55.48333],"type":"Point"}
}