{
  "type": "Feature",
  "properties": {
    "gn:admin1_code":"21",
    "gn:asciiname":"Malyye Lomy",
    "gn:country_code":"RU",
    "gn:dem":140,
    "gn:feature_class":"P",
    "gn:feature_code":"PPL",
    "gn:name":"Malyye Lomy",
    "gn:population":0,
    "gn:timezone":"Europe/Moscow",
    "iso:country":"RU",
    "name:rus_x_preferred":[
        "\u041c\u0430\u043b\u044b\u0435 \u041b\u043e\u043c\u044b"
    ],
    "wof:name":"Malyye Lomy",
    "wof:placetype":"locality"
},
  "geometry": {"coordinates":[41.66667,57.28333000000001],"type":"Point"}
}