{
  "type": "Feature",
  "properties": {
    "gn:admin1_code":"63",
    "gn:asciiname":"Bere-Khaldzhayy",
    "gn:country_code":"RU",
    "gn:dem":202,
    "gn:feature_class":"P",
    "gn:feature_code":"PPL",
    "gn:name":"Bere-Khaldzhayy",
    "gn:population":0,
    "gn:timezone":"Asia/Yakutsk",
    "iso:country":"RU",
    "name:eng_x_preferred":[
        "Bere-Khaldzhayy"
    ],
    "name:rus_x_preferred":[
        "\u0411\u0435\u0440\u0435-\u0425\u043e\u043b\u0434\u0436\u0430\u0439\u044b"
    ],
    "name:rus_x_variant":[
        "\u0411\u0435\u0440\u0435-\u0425\u0430\u043b\u0434\u0436\u0430\u0439\u044b"
    ],
    "name:und_x_variant":[
        "Bere-Khal\u2019daayy",
        "Bere-Khaldzhayy"
    ],
    "wof:name":"Bere-Khaldzhayy",
    "wof:placetype":"locality"
},
  "geometry": {"coordinates":[130.77536000000001,61.54597],"type":"Point"}
}