{
  "type": "Feature",
  "properties": {
    "gn:admin1_code":"52",
    "gn:asciiname":"Khobol'",
    "gn:country_code":"RU",
    "gn:dem":73,
    "gn:feature_class":"P",
    "gn:feature_code":"PPL",
    "gn:name":"Khobol\u2019",
    "gn:population":0,
    "gn:timezone":"Europe/Moscow",
    "iso:country":"RU",
    "name:rus_x_preferred":[
        "\u0425\u043e\u0431\u043e\u043b\u044c"
    ],
    "name:und_x_variant":[
        "Khobol\u2019",
        "\u0425\u043e\u0431\u043e\u043b\u044c"
    ],
    "wof:name":"Khobol'",
    "wof:placetype":"locality"
},
  "geometry": {"coordinates":[31.32109,57.28656],"type":"Point"}
}