{
  "type": "Feature",
  "properties": {
    "gn:admin1_code":"90",
    "gn:asciiname":"Miteva",
    "gn:country_code":"RU",
    "gn:dem":154,
    "gn:feature_class":"P",
    "gn:feature_code":"PPL",
    "gn:name":"Miteva",
    "gn:population":0,
    "gn:timezone":"Asia/Yekaterinburg",
    "iso:country":"RU",
    "name:rus_x_preferred":[
        "\u041c\u0438\u0442\u0435\u0432\u0430"
    ],
    "wof:name":"Miteva",
    "wof:placetype":"locality"
},
  "geometry": {"coordinates":[54.3938,59.107],"type":"Point"}
}