{
  "type": "Feature",
  "properties": {
    "gn:admin1_code":"85",
    "gn:asciiname":"Volnino",
    "gn:country_code":"RU",
    "gn:dem":175,
    "gn:feature_class":"P",
    "gn:feature_code":"PPL",
    "gn:name":"Volnino",
    "gn:population":0,
    "gn:timezone":"Europe/Moscow",
    "iso:country":"RU",
    "name:rus_x_preferred":[
        "\u0412\u043e\u043b\u043d\u0438\u043d\u043e"
    ],
    "name:und_x_variant":[
        "\u0412\u043e\u043b\u043d\u0438\u043d\u043e"
    ],
    "wof:name":"Volnino",
    "wof:placetype":"locality"
},
  "geometry": {"coordinates":[39.6986,59.07459],"type":"Point"}
}