{
  "type": "Feature",
  "properties": {
    "gn:admin1_code":"47",
    "gn:asciiname":"Kharpay",
    "gn:country_code":"RU",
    "gn:dem":159,
    "gn:feature_class":"P",
    "gn:feature_code":"PPL",
    "gn:name":"Kharpay",
    "gn:population":0,
    "gn:timezone":"Europe/Moscow",
    "iso:country":"RU",
    "name:nor_x_preferred":[
        "Kharpaj"
    ],
    "name:rus_x_preferred":[
        "\u0425\u0430\u0440\u043f\u0430\u0439"
    ],
    "name:und_x_variant":[
        "Kharpai",
        "Kharpay"
    ],
    "wof:name":"Kharpay",
    "wof:placetype":"locality"
},
  "geometry": {"coordinates":[35.5173,56.26371999999999],"type":"Point"}
}