{
  "type": "Feature",
  "properties": {
    "gn:admin1_code":"21.0",
    "gn:asciiname":"Dvoryanskoye",
    "gn:country_code":"RU",
    "gn:dem":106,
    "gn:feature_class":"P",
    "gn:feature_code":"PPL",
    "gn:name":"Dvoryanskoye",
    "gn:population":0,
    "gn:timezone":"Europe/Moscow",
    "iso:country":"RU",
    "name:rus_x_preferred":[
        "\u0414\u0432\u043e\u0440\u044f\u043d\u0441\u043a\u043e\u0435"
    ],
    "name:und_x_variant":[
        "\u0414\u0432\u043e\u0440\u044f\u043d\u0441\u043a\u043e\u0435"
    ],
    "wof:name":"Dvoryanskoye",
    "wof:placetype":"locality"
},
  "geometry": {"coordinates":[41.79584000000001,56.99763000000001],"type":"Point"}
}