{
  "type": "Feature",
  "properties": {
    "gn:admin1_code":"29",
    "gn:asciiname":"Yurty Konstantinovy",
    "gn:country_code":"RU",
    "gn:dem":93,
    "gn:feature_class":"P",
    "gn:feature_code":"PPL",
    "gn:name":"Yurty Konstantinovy",
    "gn:population":0,
    "gn:timezone":"Asia/Novokuznetsk",
    "iso:country":"RU",
    "name:und_x_variant":[
        "Yurta Konstantinovka",
        "Yurty Konstantinovy"
    ],
    "wof:name":"Yurty Konstantinovy",
    "wof:placetype":"locality"
},
  "geometry": {"coordinates":[84.95553000000002,56.06638],"type":"Point"}
}