{
  "type": "Feature",
  "properties": {
    "gn:country":"RU",
    "gn:fcode":"PPL",
    "gn:pop":200,
    "iso:country":"RU",
    "name:eng_x_preferred":[
        "Medved'"
    ],
    "name:nor_x_preferred":[
        "Medved"
    ],
    "name:rus_x_preferred":[
        "\u041c\u0435\u0434\u0432\u0435\u0434\u044c"
    ],
    "name:unk_x_variant":[
        "\u041c\u0435\u0434\u0432\u0435\u0434\u044c"
    ],
    "qs:name":"Medved\u2019",
    "qs:photos_9r":0,
    "qs:photos_sr":0,
    "qs:pop_sr":"4",
    "wof:name":"Medved\u2019",
    "wof:placetype":"locality",
    "wof:population":200
},
  "geometry": {"coordinates":[30.51054,58.30088],"type":"Point"}
}