{
  "type": "Feature",
  "properties": {
    "gn:admin1_code":"76",
    "gn:asciiname":"Zhadomo-Yefremovo",
    "gn:cc2":"RU",
    "gn:country_code":"RU",
    "gn:dem":271,
    "gn:feature_class":"P",
    "gn:feature_code":"PPL",
    "gn:name":"Zhadomo-Yefremovo",
    "gn:population":0,
    "gn:timezone":"Europe/Moscow",
    "iso:country":"RU",
    "name:und_x_variant":[
        "Zhadoma-Yefremovo",
        "Zhadomo-Yefremovo"
    ],
    "wof:name":"Zhadomo-Yefremovo",
    "wof:placetype":"locality"
},
  "geometry": {"coordinates":[37.34639,53.49],"type":"Point"}
}