{
  "type": "Feature",
  "properties": {
    "gn:admin1_code":"27.0",
    "gn:asciiname":"Maloabazinka",
    "gn:country_code":"RU",
    "gn:dem":603,
    "gn:feature_class":"P",
    "gn:feature_code":"PPL",
    "gn:name":"Maloabazinka",
    "gn:population":0,
    "gn:timezone":"Europe/Moscow",
    "iso:country":"RU",
    "name:rus_x_preferred":[
        "\u041c\u0430\u043b\u043e\u0430\u0431\u0430\u0437\u0438\u043d\u043a\u0430"
    ],
    "name:und_x_variant":[
        "Malo-Abazinskiy",
        "Maloabazinka",
        "\u041c\u0430\u043b\u043e\u0430\u0431\u0430\u0437\u0438\u043d\u043a\u0430"
    ],
    "wof:name":"Maloabazinka",
    "wof:placetype":"locality"
},
  "geometry": {"coordinates":[41.6776,44.3822],"type":"Point"}
}