{
  "type": "Feature",
  "properties": {
    "gn:admin1_code":"37",
    "gn:asciiname":"Zadnevo",
    "gn:country_code":"RU",
    "gn:dem":131,
    "gn:feature_class":"P",
    "gn:feature_code":"PPL",
    "gn:name":"Zadnevo",
    "gn:population":0,
    "gn:timezone":"Europe/Moscow",
    "iso:country":"RU",
    "name:rus_x_preferred":[
        "\u0417\u0430\u0434\u043d\u0435\u0432\u043e"
    ],
    "wof:name":"Zadnevo",
    "wof:placetype":"locality"
},
  "geometry": {"coordinates":[42.2157,58.5772],"type":"Point"}
}