{
  "type": "Feature",
  "properties": {
    "gn:admin1_code":"88",
    "gn:asciiname":"Krasnyy Oktyabr'",
    "gn:country_code":"RU",
    "gn:dem":136,
    "gn:feature_class":"P",
    "gn:feature_code":"PPL",
    "gn:name":"Krasnyy Oktyabr\u2019",
    "gn:population":0,
    "gn:timezone":"Europe/Moscow",
    "iso:country":"RU",
    "name:eng_x_preferred":[
        "Krasnyy Oktyabr'"
    ],
    "name:nor_x_preferred":[
        "Krasnyj Oktjabr"
    ],
    "name:rus_x_preferred":[
        "\u041a\u0440\u0430\u0441\u043d\u044b\u0439 \u041e\u043a\u0442\u044f\u0431\u0440\u044c"
    ],
    "name:und_x_variant":[
        "Krasnyy Oktyabr\u2019"
    ],
    "wof:name":"Krasnyy Oktyabr'",
    "wof:placetype":"locality"
},
  "geometry": {"coordinates":[39.01278,57.32522],"type":"Point"}
}