{
  "type": "Feature",
  "properties": {
    "gn:admin1_code":"46",
    "gn:asciiname":"Guzyntsy",
    "gn:country_code":"RU",
    "gn:dem":163,
    "gn:feature_class":"P",
    "gn:feature_code":"PPL",
    "gn:name":"Guzyntsy",
    "gn:population":0,
    "gn:timezone":"Europe/Moscow",
    "iso:country":"RU",
    "name:rus_x_preferred":[
        "\u0413\u0443\u0437\u044b\u043d\u0446\u044b"
    ],
    "name:und_x_variant":[
        "Guryntsy",
        "Guzyntsy",
        "\u0413\u0443\u0437\u044b\u043d\u0446\u044b"
    ],
    "wof:name":"Guzyntsy",
    "wof:placetype":"locality"
},
  "geometry": {"coordinates":[45.70294000000001,54.18946999999999],"type":"Point"}
}