{
  "type": "Feature",
  "properties": {
    "gn:admin1_code":"62.0",
    "gn:asciiname":"Boriskovo",
    "gn:country_code":"RU",
    "gn:dem":106,
    "gn:feature_class":"P",
    "gn:feature_code":"PPL",
    "gn:name":"Boriskovo",
    "gn:population":0,
    "gn:timezone":"Europe/Moscow",
    "iso:country":"RU",
    "name:eng_x_preferred":[
        "Boriskovo"
    ],
    "name:nor_x_preferred":[
        "Boriskovo"
    ],
    "name:rus_x_preferred":[
        "\u0411\u043e\u0440\u0438\u0441\u043a\u043e\u0432\u043e"
    ],
    "name:und_x_variant":[
        "\u0411\u043e\u0440\u0438\u0441\u043a\u043e\u0432\u043e",
        "Boriskovo"
    ],
    "wof:name":"Boriskovo",
    "wof:placetype":"locality"
},
  "geometry": {"coordinates":[40.21098,54.77708000000001],"type":"Point"}
}