{
  "type": "Feature",
  "properties": {
    "gn:country":"RU",
    "gn:fcode":"PPL",
    "gn:population":10780,
    "iso:country":"RU",
    "name:azb_x_preferred":[
        "\u0646\u0627\u062f\u0648\u0648\u06cc\u062a\u0633\u06cc"
    ],
    "name:bel_x_preferred":[
        "\u041d\u0430\u0434\u0432\u043e\u0456\u0446\u044b"
    ],
    "name:ceb_x_preferred":[
        "Nadvoitsy"
    ],
    "name:che_x_preferred":[
        "\u041d\u0430\u0434\u0432\u043e\u0438\u0446\u044b"
    ],
    "name:crh_x_preferred":[
        "Nadvoits\u0131"
    ],
    "name:deu_x_preferred":[
        "Nadwoizy"
    ],
    "name:eng_x_preferred":[
        "Nadvoitsy"
    ],
    "name:fin_x_preferred":[
        "Vojatsu"
    ],
    "name:fin_x_variant":[
        "Vojat\u0161u"
    ],
    "name:fra_x_preferred":[
        "Vojat\u0161u"
    ],
    "name:hye_x_preferred":[
        "\u0546\u0561\u0564\u057e\u0578\u056b\u0581\u056b"
    ],
    "name:nld_x_preferred":[
        "Nadvoitsi"
    ],
    "name:nor_x_preferred":[
        "Nadvoitsy"
    ],
    "name:olo_x_preferred":[
        "Voja\u010d\u010du"
    ],
    "name:pol_x_preferred":[
        "Nadwojcy"
    ],
    "name:rus_x_preferred":[
        "\u041d\u0430\u0434\u0432\u043e\u0438\u0446\u044b"
    ],
    "name:spa_x_preferred":[
        "Nadvoitsy"
    ],
    "name:swe_x_preferred":[
        "Nadvoitsy"
    ],
    "name:und_x_variant":[
        "Otvet Kulaku"
    ],
    "name:war_x_preferred":[
        "Nadvoitsy"
    ],
    "name:zho_x_preferred":[
        "\u7eb3\u5fb7\u6c83\u4f0a\u9f50"
    ],
    "qs:name":"Nadvoitsy",
    "qs:photos_9r":0,
    "qs:photos_sr":0,
    "qs:pop_sr":"6",
    "wd:wordcount":899,
    "wof:name":"Nadvoitsy",
    "wof:placetype":"locality",
    "wof:population":10780
},
  "geometry": {"coordinates":[34.31667,63.86667],"type":"Point"}
}