{
  "type": "Feature",
  "properties": {
    "gn:country":"RU",
    "gn:fcode":"PPL",
    "gn:pop":10780,
    "iso:country":"RU",
    "name:eng_x_preferred":[
        "Nadvoitsy"
    ],
    "name:fin_x_preferred":[
        "Vojatsu"
    ],
    "name:nor_x_preferred":[
        "Nadvoitsy"
    ],
    "name:rus_x_preferred":[
        "\u041d\u0430\u0434\u0432\u043e\u0438\u0446\u044b"
    ],
    "name:unk_x_variant":[
        "Otvet Kulaku"
    ],
    "qs:name":"Nadvoitsy",
    "qs:photos_9r":0,
    "qs:photos_sr":0,
    "qs:pop_sr":"6",
    "wd:wordcount":899,
    "wof:name":"Nadvoitsy",
    "wof:placetype":"locality",
    "wof:population":10780
},
  "geometry": {"coordinates":[34.31667,63.86667],"type":"Point"}
}