{
  "type": "Feature",
  "properties": {
    "gn:admin1_code":"75",
    "gn:asciiname":"Beloyarovka",
    "gn:country_code":"RU",
    "gn:dem":72,
    "gn:feature_class":"P",
    "gn:feature_code":"PPL",
    "gn:name":"Beloyarovka",
    "gn:population":0,
    "gn:timezone":"Asia/Tomsk",
    "iso:country":"RU",
    "name:eng_x_preferred":[
        "Beloyarovka"
    ],
    "name:nor_x_preferred":[
        "Belojarovka"
    ],
    "name:rus_x_preferred":[
        "\u0411\u0435\u043b\u043e\u044f\u0440\u043e\u0432\u043a\u0430"
    ],
    "name:und_x_variant":[
        "Bely Yar",
        "Belyy Yar"
    ],
    "wof:name":"Beloyarovka",
    "wof:placetype":"locality"
},
  "geometry": {"coordinates":[83.34944,58.42083],"type":"Point"}
}