{
  "type": "Feature",
  "properties": {
    "gn:admin1_code":"85.0",
    "gn:asciiname":"Balakhtimerevo",
    "gn:country_code":"RU",
    "gn:dem":137,
    "gn:feature_class":"P",
    "gn:feature_code":"PPL",
    "gn:name":"Balakhtimerevo",
    "gn:population":0,
    "gn:timezone":"Europe/Moscow",
    "iso:country":"RU",
    "name:nor_x_preferred":[
        "Balakhtimerevo"
    ],
    "name:rus_x_preferred":[
        "\u0411\u0430\u043b\u0430\u0445\u0442\u0438\u043c\u0435\u0440\u0435\u0432\u043e"
    ],
    "wof:name":"Balakhtimerevo",
    "wof:placetype":"locality"
},
  "geometry": {"coordinates":[36.31,58.7453],"type":"Point"}
}