{
  "type": "Feature",
  "properties": {
    "gn:admin1_code":"63",
    "gn:asciiname":"Koylyukyu",
    "gn:cc2":"RU",
    "gn:country_code":"RU",
    "gn:dem":242,
    "gn:feature_class":"P",
    "gn:feature_code":"PPL",
    "gn:name":"Koylyukyu",
    "gn:population":0,
    "gn:timezone":"Asia/Vladivostok",
    "iso:country":"RU",
    "name:rus_x_preferred":[
        "\u041a\u043e\u0439\u043b\u044e\u043a\u044e"
    ],
    "name:und_x_variant":[
        "Keylyukyu",
        "Koylyukyo",
        "Koylyukyu"
    ],
    "wof:name":"Koylyukyu",
    "wof:placetype":"locality"
},
  "geometry": {"coordinates":[135.38040000000001,70.00099],"type":"Point"}
}