{
  "type": "Feature",
  "properties": {
    "gn:admin1_code":"56.0",
    "gn:asciiname":"Bukreyevka",
    "gn:country_code":"RU",
    "gn:dem":207,
    "gn:feature_class":"P",
    "gn:feature_code":"PPL",
    "gn:name":"Bukreyevka",
    "gn:population":0,
    "gn:timezone":"Europe/Moscow",
    "iso:country":"RU",
    "name:rus_x_preferred":[
        "\u0411\u0443\u043a\u0440\u0435\u0435\u0432\u043a\u0430"
    ],
    "name:und_x_variant":[
        "\u0411\u0443\u043a\u0440\u0435\u0435\u0432\u043a\u0430"
    ],
    "wof:name":"Bukreyevka",
    "wof:placetype":"locality"
},
  "geometry": {"coordinates":[37.0622,52.14125],"type":"Point"}
}