{
  "type": "Feature",
  "properties": {
    "gn:admin1_code":"78",
    "gn:asciiname":"Kuliki",
    "gn:country_code":"RU",
    "gn:dem":55,
    "gn:feature_class":"P",
    "gn:feature_code":"PPL",
    "gn:name":"Kuliki",
    "gn:population":0,
    "gn:timezone":"Asia/Yekaterinburg",
    "iso:country":"RU",
    "name:bel_x_preferred":[
        "\u041a\u0443\u043b\u0456\u043a\u0456"
    ],
    "name:hye_x_preferred":[
        "\u053f\u0578\u0582\u056c\u056b\u056f\u056b"
    ],
    "name:pol_x_preferred":[
        "Kuliki"
    ],
    "name:rus_x_preferred":[
        "\u041a\u0443\u043b\u0438\u043a\u0438"
    ],
    "name:ukr_x_preferred":[
        "\u041a\u0443\u043b\u0438\u043a\u0438"
    ],
    "name:und_x_variant":[
        "\u041a\u0443\u043b\u0438\u043a\u0438"
    ],
    "wof:name":"Kuliki",
    "wof:placetype":"locality"
},
  "geometry": {"coordinates":[66.81667,56.91667],"type":"Point"}
}