{
  "type": "Feature",
  "properties": {
    "gn:admin1_code":"54",
    "gn:asciiname":"Astyrovka",
    "gn:country_code":"RU",
    "gn:dem":107,
    "gn:feature_class":"P",
    "gn:feature_code":"PPL",
    "gn:name":"Astyrovka",
    "gn:population":0,
    "gn:timezone":"Asia/Omsk",
    "iso:country":"RU",
    "name:eng_x_preferred":[
        "Astyrovka"
    ],
    "name:nor_x_preferred":[
        "Astyrovka"
    ],
    "name:rus_x_preferred":[
        "\u0410\u0441\u0442\u044b\u0440\u043e\u0432\u043a\u0430"
    ],
    "name:und_x_variant":[
        "\u0410\u0441\u0442\u044b\u0440\u043e\u0432\u043a\u0430",
        "Astyrovka"
    ],
    "wof:name":"Astyrovka",
    "wof:placetype":"locality"
},
  "geometry": {"coordinates":[74.44048000000002,55.35976],"type":"Point"}
}