{
  "type": "Feature",
  "properties": {
    "gn:country":"RU",
    "gn:fcode":"PPL",
    "gn:pop":0,
    "iso:country":"RU",
    "name:eng_x_preferred":[
        "Myasnoy Bor"
    ],
    "name:nor_x_preferred":[
        "Mjasnoj Bor"
    ],
    "name:rus_x_preferred":[
        "\u041c\u044f\u0441\u043d\u043e\u0439 \u0411\u043e\u0440"
    ],
    "name:unk_x_variant":[
        "\u041c\u044f\u0441\u043d\u043e\u0439 \u0411\u043e\u0440"
    ],
    "qs:name":"Myasnoy Bor",
    "qs:name_adm0":"Russia",
    "qs:name_adm1":"Novgorod Oblast",
    "qs:photos_9k":1,
    "qs:photos_9r":1,
    "qs:photos_all":1,
    "qs:photos_sr":0,
    "qs:placetype":"Town",
    "qs:pop_sr":"0",
    "wof:name":"Myasnoy Bor",
    "wof:placetype":"locality",
    "wof:population":0
},
  "geometry": {"coordinates":[31.47615,58.82292],"type":"Point"}
}