{
  "type": "Feature",
  "properties": {
    "gn:admin1_code":"11",
    "gn:asciiname":"Bol'shoy Lug",
    "gn:country_code":"RU",
    "gn:dem":566,
    "gn:feature_class":"P",
    "gn:feature_code":"PPL",
    "gn:name":"Bol\u2019shoy Lug",
    "gn:population":0,
    "gn:timezone":"Asia/Irkutsk",
    "iso:country":"RU",
    "name:rus_x_preferred":[
        "\u0411\u043e\u043b\u044c\u0448\u043e\u0439 \u041b\u0443\u0433"
    ],
    "name:und_x_variant":[
        "Ulus Bol\u2019shoy Lug",
        "Ulusy Bolshoy Lug",
        "Bol\u2019shoy Lug"
    ],
    "wof:name":"Bol'shoy Lug",
    "wof:placetype":"locality"
},
  "geometry": {"coordinates":[106.77667,50.60806],"type":"Point"}
}