{
  "type": "Feature",
  "properties": {
    "gn:admin1_code":"63",
    "gn:asciiname":"Kharyyalakh",
    "gn:country_code":"RU",
    "gn:dem":123,
    "gn:feature_class":"P",
    "gn:feature_code":"PPL",
    "gn:name":"Kharyyalakh",
    "gn:population":0,
    "gn:timezone":"Asia/Yakutsk",
    "iso:country":"RU",
    "name:eng_x_preferred":[
        "Kharyyalakh"
    ],
    "name:nor_x_preferred":[
        "Kharyjalakh"
    ],
    "name:rus_x_preferred":[
        "\u0425\u0430\u0440\u044b\u044f\u043b\u0430\u0445"
    ],
    "name:und_x_variant":[
        "\u0425\u0430\u0440\u044b\u044f\u043b\u0430\u0445",
        "Kharyyalakh"
    ],
    "wof:name":"Kharyyalakh",
    "wof:placetype":"locality"
},
  "geometry": {"coordinates":[120.15191000000002,63.47306],"type":"Point"}
}