{
  "type": "Feature",
  "properties": {
    "gn:admin1_code":"54",
    "gn:asciiname":"Kazyrly",
    "gn:country_code":"RU",
    "gn:dem":96,
    "gn:feature_class":"P",
    "gn:feature_code":"PPL",
    "gn:name":"Kazyrly",
    "gn:population":0,
    "gn:timezone":"Asia/Omsk",
    "iso:country":"RU",
    "name:eng_x_preferred":[
        "Kazyrly"
    ],
    "name:nor_x_preferred":[
        "Kazyrly"
    ],
    "name:rus_x_preferred":[
        "\u041a\u0430\u0437\u044b\u0440\u043b\u044b"
    ],
    "name:und_x_variant":[
        "\u041a\u0430\u0437\u044b\u0440\u043b\u044b",
        "Kazyrly"
    ],
    "wof:name":"Kazyrly",
    "wof:placetype":"locality"
},
  "geometry": {"coordinates":[73.73339,55.83285],"type":"Point"}
}