{
  "type": "Feature",
  "properties": {
    "gn:admin1_code":"90",
    "gn:asciiname":"Kharichi",
    "gn:country_code":"RU",
    "gn:dem":183,
    "gn:feature_class":"P",
    "gn:feature_code":"PPL",
    "gn:name":"Kharichi",
    "gn:population":0,
    "gn:timezone":"Asia/Yekaterinburg",
    "iso:country":"RU",
    "name:eng_x_preferred":[
        "Kharichi"
    ],
    "name:nor_x_preferred":[
        "Kharitsji"
    ],
    "name:rus_x_preferred":[
        "\u0425\u0430\u0440\u0438\u0447\u0438"
    ],
    "name:und_x_variant":[
        "Karichi"
    ],
    "wof:name":"Kharichi",
    "wof:placetype":"locality"
},
  "geometry": {"coordinates":[55.0179,58.2392],"type":"Point"}
}