{
  "type": "Feature",
  "properties": {
    "gn:admin1_code":"88",
    "gn:asciiname":"Uvaikha",
    "gn:country_code":"RU",
    "gn:dem":99,
    "gn:feature_class":"P",
    "gn:feature_code":"PPL",
    "gn:name":"Uvaikha",
    "gn:population":0,
    "gn:timezone":"Europe/Moscow",
    "iso:country":"RU",
    "name:rus_x_preferred":[
        "\u0423\u0432\u0430\u0438\u0445\u0430"
    ],
    "wof:name":"Uvaikha",
    "wof:placetype":"locality"
},
  "geometry": {"coordinates":[39.38231,57.21853],"type":"Point"}
}