{
  "type": "Feature",
  "properties": {
    "gn:admin1_code":"70",
    "gn:asciiname":"Vodorazdel",
    "gn:country_code":"RU",
    "gn:dem":444,
    "gn:feature_class":"P",
    "gn:feature_code":"PPL",
    "gn:name":"Vodorazdel",
    "gn:population":0,
    "gn:timezone":"Europe/Moscow",
    "iso:country":"RU",
    "name:eng_x_preferred":[
        "Vodorazdel"
    ],
    "name:nor_x_preferred":[
        "Vodorazdel"
    ],
    "name:rus_x_preferred":[
        "\u0412\u043e\u0434\u043e\u0440\u0430\u0437\u0434\u0435\u043b"
    ],
    "wof:name":"Vodorazdel",
    "wof:placetype":"locality"
},
  "geometry": {"coordinates":[42.36111,44.51639],"type":"Point"}
}