{
  "type": "Feature",
  "properties": {
    "gn:admin1_code":"84",
    "gn:asciiname":"Shurupovskiy",
    "gn:country_code":"RU",
    "gn:dem":107,
    "gn:feature_class":"P",
    "gn:feature_code":"PPL",
    "gn:name":"Shurupovskiy",
    "gn:population":0,
    "gn:timezone":"Europe/Volgograd",
    "iso:country":"RU",
    "name:eng_x_preferred":[
        "Shurupovskiy"
    ],
    "name:nor_x_preferred":[
        "Sjurupovskij"
    ],
    "name:rus_x_preferred":[
        "\u0428\u0443\u0440\u0443\u043f\u043e\u0432\u0441\u043a\u0438\u0439"
    ],
    "name:und_x_variant":[
        "Shurupovka"
    ],
    "wof:name":"Shurupovskiy",
    "wof:placetype":"locality"
},
  "geometry": {"coordinates":[43.71453,49.73125],"type":"Point"}
}