{
  "type": "Feature",
  "properties": {
    "gn:admin1_code":"4",
    "gn:asciiname":"Levo-Berezhnyy Ozernyy",
    "gn:country_code":"RU",
    "gn:dem":127,
    "gn:feature_class":"P",
    "gn:feature_code":"PPL",
    "gn:name":"Levo-Berezhnyy Oz\u00ebrnyy",
    "gn:population":0,
    "gn:timezone":"Asia/Barnaul",
    "iso:country":"RU",
    "name:rus_x_preferred":[
        "\u041b\u0435\u0432\u043e-\u0411\u0435\u0440\u0435\u0436\u043d\u044b\u0439 \u041e\u0437\u0451\u0440\u043d\u044b\u0439"
    ],
    "name:und_x_variant":[
        "Levo-Berezhnyy Oz\u00ebrnyy"
    ],
    "wof:name":"Levo-Berezhnyy Ozernyy",
    "wof:placetype":"locality"
},
  "geometry": {"coordinates":[78.86667,52.48333],"type":"Point"}
}