{
  "type": "Feature",
  "properties": {
    "gn:admin1_code":"6",
    "gn:asciiname":"Gory",
    "gn:cc2":"RU",
    "gn:country_code":"RU",
    "gn:dem":53,
    "gn:feature_class":"P",
    "gn:feature_code":"PPL",
    "gn:name":"Gory",
    "gn:population":0,
    "gn:timezone":"Europe/Moscow",
    "iso:country":"RU",
    "name:ceb_x_preferred":[
        "Gory"
    ],
    "name:deu_x_preferred":[
        "G\u00f3ry"
    ],
    "name:eng_x_preferred":[
        "Gory"
    ],
    "name:fra_x_preferred":[
        "Gory"
    ],
    "name:ita_x_preferred":[
        "Gory"
    ],
    "name:lit_x_preferred":[
        "Gurai"
    ],
    "name:nor_x_preferred":[
        "Gory"
    ],
    "name:rus_x_preferred":[
        "\u0413\u043e\u0440\u044b"
    ],
    "name:swe_x_preferred":[
        "Gory"
    ],
    "name:und_x_variant":[
        "Gora"
    ],
    "wof:name":"Gory",
    "wof:placetype":"locality"
},
  "geometry": {"coordinates":[42.40611,61.33333],"type":"Point"}
}