{
  "type": "Feature",
  "properties": {
    "gn:admin1_code":"52.0",
    "gn:asciiname":"Baranikha",
    "gn:country_code":"RU",
    "gn:dem":35,
    "gn:feature_class":"P",
    "gn:feature_code":"PPL",
    "gn:name":"Baranikha",
    "gn:population":0,
    "gn:timezone":"Europe/Moscow",
    "iso:country":"RU",
    "name:nor_x_preferred":[
        "Baranikha"
    ],
    "name:rus_x_preferred":[
        "\u0411\u0430\u0440\u0430\u043d\u0438\u0445\u0430"
    ],
    "wof:name":"Baranikha",
    "wof:placetype":"locality"
},
  "geometry": {"coordinates":[31.83755,58.60226],"type":"Point"}
}