{
  "type": "Feature",
  "properties": {
    "gn:admin1_code":"73",
    "gn:asciiname":"Karek-Serma",
    "gn:country_code":"RU",
    "gn:dem":170,
    "gn:feature_class":"P",
    "gn:feature_code":"PPL",
    "gn:name":"Karek-Serma",
    "gn:population":0,
    "gn:timezone":"Europe/Moscow",
    "iso:country":"RU",
    "name:rus_x_preferred":[
        "\u041a\u0430\u0440\u0435\u043a-\u0421\u0435\u0440\u043c\u0430"
    ],
    "wof:name":"Karek-Serma",
    "wof:placetype":"locality"
},
  "geometry": {"coordinates":[50.312,56.4671],"type":"Point"}
}