{
  "type": "Feature",
  "properties": {
    "gn:admin1_code":"65",
    "gn:asciiname":"Lesnoy",
    "gn:country_code":"RU",
    "gn:dem":67,
    "gn:feature_class":"P",
    "gn:feature_code":"PPL",
    "gn:name":"Lesnoy",
    "gn:population":0,
    "gn:timezone":"Europe/Samara",
    "iso:country":"RU",
    "name:eng_x_preferred":[
        "Lesnoy"
    ],
    "name:nor_x_preferred":[
        "Lesnoj"
    ],
    "name:rus_x_preferred":[
        "\u041b\u0435\u0441\u043d\u043e\u0439"
    ],
    "name:und_x_variant":[
        "Rogozhinskiy",
        "\u041b\u0435\u0441\u043d\u043e\u0439",
        "Lesnoy"
    ],
    "wof:name":"Lesnoy",
    "wof:placetype":"locality"
},
  "geometry": {"coordinates":[51.86752,53.03043],"type":"Point"}
}