{
  "type": "Feature",
  "properties": {
    "gn:admin1_code":"42.0",
    "gn:asciiname":"Bugry",
    "gn:country_code":"RU",
    "gn:dem":93,
    "gn:feature_class":"P",
    "gn:feature_code":"PPL",
    "gn:name":"Bugry",
    "gn:population":0,
    "gn:timezone":"Europe/Moscow",
    "iso:country":"RU",
    "name:fin_x_preferred":[
        "Pukrankyl\u00e4"
    ],
    "name:rus_x_preferred":[
        "\u0411\u0443\u0433\u0440\u044b"
    ],
    "wof:name":"Bugry",
    "wof:placetype":"locality"
},
  "geometry": {"coordinates":[30.2425,59.63417],"type":"Point"}
}