{
  "type": "Feature",
  "properties": {
    "gn:admin1_code":"51",
    "gn:asciiname":"Novomikhaylovka",
    "gn:country_code":"RU",
    "gn:dem":132,
    "gn:feature_class":"P",
    "gn:feature_code":"PPL",
    "gn:name":"Novomikhaylovka",
    "gn:population":0,
    "gn:timezone":"Europe/Moscow",
    "iso:country":"RU",
    "name:eng_x_preferred":[
        "Novomikhaylovka"
    ],
    "name:nor_x_preferred":[
        "Novomikhajlovka"
    ],
    "name:rus_x_preferred":[
        "\u041d\u043e\u0432\u043e\u043c\u0438\u0445\u0430\u0439\u043b\u043e\u0432\u043a\u0430"
    ],
    "name:und_x_variant":[
        "Mikhaylovka",
        "Novomikhaylovka"
    ],
    "wof:name":"Novomikhaylovka",
    "wof:placetype":"locality"
},
  "geometry": {"coordinates":[44.40454,54.82179],"type":"Point"}
}