{
  "type": "Feature",
  "properties": {
    "gn:admin1_code":"85",
    "gn:asciiname":"Abakanovo",
    "gn:country_code":"RU",
    "gn:dem":176,
    "gn:feature_class":"P",
    "gn:feature_code":"PPL",
    "gn:name":"Abakanovo",
    "gn:population":0,
    "gn:timezone":"Europe/Moscow",
    "iso:country":"RU",
    "name:rus_x_preferred":[
        "\u0410\u0431\u0430\u043a\u0430\u043d\u043e\u0432\u043e"
    ],
    "wof:name":"Abakanovo",
    "wof:placetype":"locality"
},
  "geometry": {"coordinates":[39.6222,59.4125],"type":"Point"}
}