{
  "type": "Feature",
  "properties": {
    "gn:admin1_code":"77",
    "gn:asciiname":"Stepanovo",
    "gn:country_code":"RU",
    "gn:dem":229,
    "gn:feature_class":"P",
    "gn:feature_code":"PPL",
    "gn:name":"Stepanovo",
    "gn:population":0,
    "gn:timezone":"Europe/Moscow",
    "iso:country":"RU",
    "name:rus_x_preferred":[
        "\u0421\u0442\u0435\u043f\u0430\u043d\u043e\u0432\u043e"
    ],
    "name:und_x_variant":[
        "Stepan\u2019kova",
        "Stepanovo",
        "\u0421\u0442\u0435\u043f\u0430\u043d\u043e\u0432\u043e"
    ],
    "wof:name":"Stepanovo",
    "wof:placetype":"locality"
},
  "geometry": {"coordinates":[33.14850999999999,55.78556999999999],"type":"Point"}
}