{
  "type": "Feature",
  "properties": {
    "gn:admin1_code":"8",
    "gn:asciiname":"Shushnur",
    "gn:country_code":"RU",
    "gn:dem":97,
    "gn:feature_class":"P",
    "gn:feature_code":"PPL",
    "gn:name":"Shushnur",
    "gn:population":0,
    "gn:timezone":"Asia/Yekaterinburg",
    "iso:country":"RU",
    "name:eng_x_preferred":[
        "Shushnur"
    ],
    "name:nor_x_preferred":[
        "Sjusjnur"
    ],
    "name:rus_x_preferred":[
        "\u0428\u0443\u0448\u043d\u0443\u0440"
    ],
    "wof:name":"Shushnur",
    "wof:placetype":"locality"
},
  "geometry": {"coordinates":[54.36061,55.89579000000001],"type":"Point"}
}