{
  "type": "Feature",
  "properties": {
    "gn:admin1_code":"73.0",
    "gn:asciiname":"Mullanur Vakhitov",
    "gn:country_code":"RU",
    "gn:dem":85,
    "gn:feature_class":"P",
    "gn:feature_code":"PPL",
    "gn:name":"Mullanur Vakhitov",
    "gn:population":0,
    "gn:timezone":"Europe/Moscow",
    "iso:country":"RU",
    "wof:name":"Mullanur Vakhitov",
    "wof:placetype":"locality"
},
  "geometry": {"coordinates":[48.12659,54.93468000000001],"type":"Point"}
}