{
  "type": "Feature",
  "properties": {
    "gn:admin1_code":"88",
    "gn:asciiname":"Bol'shoye Skrylevo",
    "gn:country_code":"RU",
    "gn:dem":140,
    "gn:feature_class":"P",
    "gn:feature_code":"PPL",
    "gn:name":"Bol\u2019shoye Skryl\u00ebvo",
    "gn:population":0,
    "gn:timezone":"Europe/Moscow",
    "iso:country":"RU",
    "name:rus_x_preferred":[
        "\u0411\u043e\u043b\u044c\u0448\u043e\u0435 \u0421\u043a\u0440\u044b\u043b\u0451\u0432\u043e"
    ],
    "name:und_x_variant":[
        "Bol\u2019shoye Skryl\u00ebvo"
    ],
    "wof:name":"Bol'shoye Skrylevo",
    "wof:placetype":"locality"
},
  "geometry": {"coordinates":[39.02451,57.76925],"type":"Point"}
}