{
  "type": "Feature",
  "properties": {
    "gn:admin1_code":"85",
    "gn:asciiname":"Kondyrikha",
    "gn:country_code":"RU",
    "gn:dem":155,
    "gn:feature_class":"P",
    "gn:feature_code":"PPL",
    "gn:name":"Kondyrikha",
    "gn:population":0,
    "gn:timezone":"Europe/Moscow",
    "iso:country":"RU",
    "name:rus_x_preferred":[
        "\u041a\u043e\u043d\u0434\u044b\u0440\u0438\u0445\u0430"
    ],
    "wof:name":"Kondyrikha",
    "wof:placetype":"locality"
},
  "geometry": {"coordinates":[39.47097,59.14684000000001],"type":"Point"}
}