{
  "type": "Feature",
  "properties": {
    "gn:admin1_code":"76",
    "gn:asciiname":"Semenovskiy Khutor",
    "gn:country_code":"RU",
    "gn:dem":258,
    "gn:feature_class":"P",
    "gn:feature_code":"PPL",
    "gn:name":"Sem\u00ebnovskiy Khutor",
    "gn:population":0,
    "gn:timezone":"Europe/Moscow",
    "iso:country":"RU",
    "name:rus_x_preferred":[
        "\u0421\u0435\u043c\u0451\u043d\u043e\u0432\u0441\u043a\u0438\u0439 \u0425\u0443\u0442\u043e\u0440"
    ],
    "name:und_x_variant":[
        "Sem\u00ebnovskiy Khutor",
        "\u0421\u0435\u043c\u0451\u043d\u043e\u0432\u0441\u043a\u0438\u0439 \u0425\u0443\u0442\u043e\u0440"
    ],
    "wof:name":"Semenovskiy Khutor",
    "wof:placetype":"locality"
},
  "geometry": {"coordinates":[37.36056,53.80278000000001],"type":"Point"}
}