{
  "type": "Feature",
  "properties": {
    "gn:admin1_code":"77",
    "gn:asciiname":"Pozhar'ye",
    "gn:country_code":"RU",
    "gn:dem":141,
    "gn:feature_class":"P",
    "gn:feature_code":"PPL",
    "gn:name":"Pozhar\u2019ye",
    "gn:population":0,
    "gn:timezone":"Europe/Moscow",
    "iso:country":"RU",
    "name:eng_x_preferred":[
        "Pozhar'ye"
    ],
    "name:nor_x_preferred":[
        "Pozjarje"
    ],
    "name:rus_x_preferred":[
        "\u041f\u043e\u0436\u0430\u0440\u044c\u0435"
    ],
    "name:und_x_variant":[
        "\u041f\u043e\u0436\u0430\u0440\u044c\u0435",
        "Pozhar\u2019ye"
    ],
    "wof:name":"Pozhar'ye",
    "wof:placetype":"locality"
},
  "geometry": {"coordinates":[36.13504,58.24249],"type":"Point"}
}