{
  "type": "Feature",
  "properties": {
    "gn:admin1_code":"88",
    "gn:asciiname":"Savinskoye",
    "gn:country_code":"RU",
    "gn:dem":117,
    "gn:feature_class":"P",
    "gn:feature_code":"PPL",
    "gn:name":"Savinskoye",
    "gn:population":0,
    "gn:timezone":"Europe/Moscow",
    "iso:country":"RU",
    "name:eng_x_preferred":[
        "Savinskoye"
    ],
    "name:nor_x_preferred":[
        "Savinskoje"
    ],
    "name:rus_x_preferred":[
        "\u0421\u0430\u0432\u0438\u043d\u0441\u043a\u043e\u0435"
    ],
    "name:und_x_variant":[
        "Krasnyy Oktyabr\u2019",
        "Savinskoye"
    ],
    "wof:name":"Savinskoye",
    "wof:placetype":"locality"
},
  "geometry": {"coordinates":[39.36917,57.94046],"type":"Point"}
}