{
  "type": "Feature",
  "properties": {
    "gn:admin1_code":"56.0",
    "gn:asciiname":"Bol'shiye Ozerki",
    "gn:country_code":"RU",
    "gn:dem":247,
    "gn:feature_class":"P",
    "gn:feature_code":"PPL",
    "gn:name":"Bol\u2019shiye Ozerki",
    "gn:population":0,
    "gn:timezone":"Europe/Moscow",
    "iso:country":"RU",
    "name:rus_x_preferred":[
        "\u0411\u043e\u043b\u044c\u0448\u0438\u0435 \u041e\u0437\u0435\u0440\u043a\u0438"
    ],
    "name:und_x_variant":[
        "Bol\u2019shiye Ozerki",
        "\u0411\u043e\u043b\u044c\u0448\u0438\u0435 \u041e\u0437\u0435\u0440\u043a\u0438"
    ],
    "wof:name":"Bol'shiye Ozerki",
    "wof:placetype":"locality"
},
  "geometry": {"coordinates":[37.46627,53.21032],"type":"Point"}
}