{
  "type": "Feature",
  "properties": {
    "gn:admin1_code":"37",
    "gn:asciiname":"Yershovtsy",
    "gn:country_code":"RU",
    "gn:dem":130,
    "gn:feature_class":"P",
    "gn:feature_code":"PPL",
    "gn:name":"Yershovtsy",
    "gn:population":0,
    "gn:timezone":"Europe/Moscow",
    "iso:country":"RU",
    "name:rus_x_preferred":[
        "\u0415\u0440\u0448\u043e\u0432\u0446\u044b"
    ],
    "name:und_x_variant":[
        "\u0415\u0440\u0448\u043e\u0432\u0446\u044b"
    ],
    "wof:name":"Yershovtsy",
    "wof:placetype":"locality"
},
  "geometry": {"coordinates":[46.22600000000001,58.8203],"type":"Point"}
}