{
  "type": "Feature",
  "properties": {
    "gn:admin1_code":"60",
    "gn:asciiname":"Yaz'vo",
    "gn:country_code":"RU",
    "gn:dem":68,
    "gn:feature_class":"P",
    "gn:feature_code":"PPL",
    "gn:name":"Yaz\u2019vo",
    "gn:population":0,
    "gn:timezone":"Europe/Moscow",
    "iso:country":"RU",
    "name:rus_x_preferred":[
        "\u042f\u0437\u044c\u0432\u043e"
    ],
    "name:und_x_variant":[
        "Yaz\u2019vo",
        "Yazvi"
    ],
    "wof:name":"Yaz'vo",
    "wof:placetype":"locality"
},
  "geometry": {"coordinates":[28.39697,58.79991],"type":"Point"}
}