{
  "type": "Feature",
  "properties": {
    "gn:admin1_code":"91",
    "gn:asciiname":"Skripachi",
    "gn:country_code":"RU",
    "gn:dem":244,
    "gn:feature_class":"P",
    "gn:feature_code":"PPL",
    "gn:name":"Skripachi",
    "gn:population":0,
    "gn:timezone":"Asia/Novokuznetsk",
    "iso:country":"RU",
    "name:eng_x_preferred":[
        "Skripachi"
    ],
    "name:nor_x_preferred":[
        "Skripatsji"
    ],
    "name:rus_x_preferred":[
        "\u0421\u043a\u0440\u0438\u043f\u0430\u0447\u0438"
    ],
    "name:und_x_variant":[
        "Skripochnikova"
    ],
    "wof:name":"Skripachi",
    "wof:placetype":"locality"
},
  "geometry": {"coordinates":[89.38194,55.79083000000001],"type":"Point"}
}