{
  "type": "Feature",
  "properties": {
    "gn:admin1_code":"38",
    "gn:asciiname":"Mnogopol'nyy",
    "gn:country_code":"RU",
    "gn:dem":31,
    "gn:feature_class":"P",
    "gn:feature_code":"PPL",
    "gn:name":"Mnogopol\u2019nyy",
    "gn:population":0,
    "gn:timezone":"Europe/Moscow",
    "iso:country":"RU",
    "name:rus_x_preferred":[
        "\u041c\u043d\u043e\u0433\u043e\u043f\u043e\u043b\u044c\u043d\u044b\u0439"
    ],
    "name:und_x_variant":[
        "Mnogopol\u2019nyy",
        "\u041c\u043d\u043e\u0433\u043e\u043f\u043e\u043b\u044c\u043d\u044b\u0439"
    ],
    "wof:name":"Mnogopol'nyy",
    "wof:placetype":"locality"
},
  "geometry": {"coordinates":[39.13333,46.23333],"type":"Point"}
}