{
  "type": "Feature",
  "properties": {
    "gn:admin1_code":"34",
    "gn:asciiname":"Pup",
    "gn:country_code":"RU",
    "gn:dem":199,
    "gn:feature_class":"P",
    "gn:feature_code":"PPL",
    "gn:name":"Pup",
    "gn:population":0,
    "gn:timezone":"Europe/Moscow",
    "iso:country":"RU",
    "name:deu_x_preferred":[
        "Pup"
    ],
    "name:nld_x_preferred":[
        "Pup"
    ],
    "name:rus_x_preferred":[
        "\u041f\u0443\u043f"
    ],
    "name:tgl_x_preferred":[
        "Pup"
    ],
    "wof:name":"Pup",
    "wof:placetype":"locality"
},
  "geometry": {"coordinates":[49.35,59.51667],"type":"Point"}
}