{
  "type": "Feature",
  "properties": {
    "gn:admin1_code":"25",
    "gn:asciiname":"Nizhneye Alopovo",
    "gn:country_code":"RU",
    "gn:dem":178,
    "gn:feature_class":"P",
    "gn:feature_code":"PPL",
    "gn:name":"Nizhneye Alopovo",
    "gn:population":0,
    "gn:timezone":"Europe/Moscow",
    "iso:country":"RU",
    "name:rus_x_preferred":[
        "\u041d\u0438\u0436\u043d\u0435\u0435 \u0410\u043b\u043e\u043f\u043e\u0432\u043e"
    ],
    "name:und_x_variant":[
        "Nizhneye Lopovo",
        "Nizhneye Alopovo"
    ],
    "wof:name":"Nizhneye Alopovo",
    "wof:placetype":"locality"
},
  "geometry": {"coordinates":[35.98799,54.21203000000001],"type":"Point"}
}