{
  "type": "Feature",
  "properties": {
    "gn:admin1_code":"41.0",
    "gn:asciiname":"Nikolayevo",
    "gn:country_code":"RU",
    "gn:dem":174,
    "gn:feature_class":"P",
    "gn:feature_code":"PPL",
    "gn:name":"Nikolayevo",
    "gn:population":0,
    "gn:timezone":"Europe/Moscow",
    "iso:country":"RU",
    "name:rus_x_preferred":[
        "\u041d\u0438\u043a\u043e\u043b\u0430\u0435\u0432\u043e"
    ],
    "name:und_x_variant":[
        "Nikolayevka"
    ],
    "wof:name":"Nikolayevo",
    "wof:placetype":"locality"
},
  "geometry": {"coordinates":[37.4878,51.7824],"type":"Point"}
}