{
  "type": "Feature",
  "properties": {
    "gn:admin1_code":"61",
    "gn:asciiname":"Dikuny",
    "gn:country_code":"RU",
    "gn:dem":230,
    "gn:feature_class":"P",
    "gn:feature_code":"PPL",
    "gn:name":"Dikuny",
    "gn:population":0,
    "gn:timezone":"Europe/Moscow",
    "iso:country":"RU",
    "name:rus_x_preferred":[
        "\u0414\u0438\u043a\u0443\u043d\u044b"
    ],
    "name:und_x_variant":[
        "\u0414\u0438\u043a\u0443\u043d\u044b"
    ],
    "wof:name":"Dikuny",
    "wof:placetype":"locality"
},
  "geometry": {"coordinates":[40.17889,49.62472],"type":"Point"}
}