{
  "type": "Feature",
  "properties": {
    "gn:admin1_code":"77",
    "gn:asciiname":"Shchapitsy",
    "gn:country_code":"RU",
    "gn:dem":121,
    "gn:feature_class":"P",
    "gn:feature_code":"PPL",
    "gn:name":"Shchapitsy",
    "gn:population":0,
    "gn:timezone":"Europe/Moscow",
    "iso:country":"RU",
    "name:rus_x_preferred":[
        "\u0429\u0430\u043f\u0438\u0446\u044b"
    ],
    "name:und_x_variant":[
        "\u0429\u0430\u043f\u0438\u0446\u044b"
    ],
    "wof:name":"Shchapitsy",
    "wof:placetype":"locality"
},
  "geometry": {"coordinates":[37.9649,57.3151],"type":"Point"}
}