{
  "type": "Feature",
  "properties": {
    "gn:admin1_code":"55",
    "gn:asciiname":"Zemskov",
    "gn:country_code":"RU",
    "gn:dem":171,
    "gn:feature_class":"P",
    "gn:feature_code":"PPL",
    "gn:name":"Zemskov",
    "gn:population":0,
    "gn:timezone":"Asia/Yekaterinburg",
    "iso:country":"RU",
    "name:rus_x_preferred":[
        "\u0417\u0435\u043c\u0441\u043a\u043e\u0432"
    ],
    "name:und_x_variant":[
        "\u0417\u0435\u043c\u0441\u043a\u043e\u0432"
    ],
    "wof:name":"Zemskov",
    "wof:placetype":"locality"
},
  "geometry": {"coordinates":[52.8179,53.9927],"type":"Point"}
}