{
  "type": "Feature",
  "properties": {
    "gn:admin1_code":"55",
    "gn:asciiname":"Khasimov",
    "gn:country_code":"RU",
    "gn:dem":169,
    "gn:feature_class":"P",
    "gn:feature_code":"PPL",
    "gn:name":"Khasimov",
    "gn:population":0,
    "gn:timezone":"Asia/Yekaterinburg",
    "iso:country":"RU",
    "name:rus_x_preferred":[
        "\u0425\u0430\u0441\u0438\u043c\u043e\u0432"
    ],
    "name:und_x_variant":[
        "\u0425\u0430\u0441\u0438\u043c\u043e\u0432"
    ],
    "wof:name":"Khasimov",
    "wof:placetype":"locality"
},
  "geometry": {"coordinates":[56.55,51.06667],"type":"Point"}
}