{
  "type": "Feature",
  "properties": {
    "gn:admin1_code":"60",
    "gn:asciiname":"Vashkovo",
    "gn:country_code":"RU",
    "gn:dem":92,
    "gn:feature_class":"P",
    "gn:feature_code":"PPL",
    "gn:name":"Vashkovo",
    "gn:population":0,
    "gn:timezone":"Europe/Moscow",
    "iso:country":"RU",
    "name:rus_x_preferred":[
        "\u0412\u0430\u0448\u043a\u043e\u0432\u043e"
    ],
    "wof:name":"Vashkovo",
    "wof:placetype":"locality"
},
  "geometry": {"coordinates":[28.50424000000001,56.77396],"type":"Point"}
}