{
  "type": "Feature",
  "properties": {
    "gn:admin1_code":"91",
    "gn:asciiname":"Bol'shaya Avda",
    "gn:country_code":"RU",
    "gn:dem":326,
    "gn:feature_class":"P",
    "gn:feature_code":"PPL",
    "gn:name":"Bol\u2019shaya Avda",
    "gn:population":0,
    "gn:timezone":"Asia/Krasnoyarsk",
    "iso:country":"RU",
    "name:rus_x_preferred":[
        "\u0411\u043e\u043b\u044c\u0448\u0430\u044f \u0410\u0432\u0434\u0430"
    ],
    "name:und_x_variant":[
        "Bol\u2019shaya Avda"
    ],
    "wof:name":"Bol'shaya Avda",
    "wof:placetype":"locality"
},
  "geometry": {"coordinates":[94.61667,55.73333],"type":"Point"}
}