{
  "type": "Feature",
  "properties": {
    "gn:admin1_code":"34",
    "gn:asciiname":"Zakharvan'",
    "gn:country_code":"RU",
    "gn:dem":30,
    "gn:feature_class":"P",
    "gn:feature_code":"PPL",
    "gn:name":"Zakharvan\u2019",
    "gn:population":0,
    "gn:timezone":"Europe/Moscow",
    "iso:country":"RU",
    "name:eng_x_preferred":[
        "Zakharvan'"
    ],
    "name:nor_x_preferred":[
        "Zakharvan"
    ],
    "name:rus_x_preferred":[
        "\u0417\u0430\u0445\u0430\u0440\u0432\u0430\u043d\u044c"
    ],
    "name:und_x_variant":[
        "Zakharvan\u2019"
    ],
    "wof:name":"Zakharvan'",
    "wof:placetype":"locality"
},
  "geometry": {"coordinates":[55.86532,66.33205],"type":"Point"}
}