{
  "type": "Feature",
  "properties": {
    "gn:admin1_code":"47",
    "gn:asciiname":"Stremoukhovo",
    "gn:country_code":"RU",
    "gn:dem":236,
    "gn:feature_class":"P",
    "gn:feature_code":"PPL",
    "gn:name":"Stremoukhovo",
    "gn:population":0,
    "gn:timezone":"Europe/Moscow",
    "iso:country":"RU",
    "name:eng_x_preferred":[
        "Stremoukhovo"
    ],
    "name:rus_x_preferred":[
        "\u0421\u0442\u0440\u0435\u043c\u043e\u0443\u0445\u043e\u0432\u043e"
    ],
    "wof:name":"Stremoukhovo",
    "wof:placetype":"locality"
},
  "geometry": {"coordinates":[35.82912,55.9659],"type":"Point"}
}