{
  "type": "Feature",
  "properties": {
    "gn:admin1_code":"20",
    "gn:asciiname":"Nevanka",
    "gn:country_code":"RU",
    "gn:dem":224,
    "gn:feature_class":"P",
    "gn:feature_code":"PPL",
    "gn:name":"Nevanka",
    "gn:population":0,
    "gn:timezone":"Asia/Irkutsk",
    "iso:country":"RU",
    "name:eng_x_preferred":[
        "Nevanka"
    ],
    "name:nor_x_preferred":[
        "Nevanka"
    ],
    "name:rus_x_preferred":[
        "\u041d\u0435\u0432\u0430\u043d\u043a\u0430"
    ],
    "wof:name":"Nevanka",
    "wof:placetype":"locality"
},
  "geometry": {"coordinates":[98.9173,56.4916],"type":"Point"}
}