{
  "type": "Feature",
  "properties": {
    "gn:admin1_code":"33",
    "gn:asciiname":"Podvolochnaya",
    "gn:cc2":"RU",
    "gn:country_code":"RU",
    "gn:dem":120,
    "gn:feature_class":"P",
    "gn:feature_code":"PPL",
    "gn:name":"Podvolochnaya",
    "gn:population":0,
    "gn:timezone":"Europe/Kirov",
    "iso:country":"RU",
    "name:rus_x_preferred":[
        "\u041f\u043e\u0434\u0432\u043e\u043b\u043e\u0447\u043d\u0430\u044f"
    ],
    "name:und_x_variant":[
        "Bol\u2019she Podvolochnaya",
        "Podvolochnaya",
        "\u041f\u043e\u0434\u0432\u043e\u043b\u043e\u0447\u043d\u0430\u044f"
    ],
    "wof:name":"Podvolochnaya",
    "wof:placetype":"locality"
},
  "geometry": {"coordinates":[48.03333,57.93333000000001],"type":"Point"}
}