{
  "type": "Feature",
  "properties": {
    "gn:admin1_code":"76.0",
    "gn:asciiname":"Dobroye Semya",
    "gn:country_code":"RU",
    "gn:dem":161,
    "gn:feature_class":"P",
    "gn:feature_code":"PPL",
    "gn:name":"Dobroye Semya",
    "gn:population":0,
    "gn:timezone":"Europe/Moscow",
    "iso:country":"RU",
    "name:rus_x_preferred":[
        "\u0414\u043e\u0431\u0440\u043e\u0435 \u0421\u0435\u043c\u044f"
    ],
    "name:und_x_variant":[
        "\u0414\u043e\u0431\u0440\u043e\u0435 \u0421\u0435\u043c\u044f"
    ],
    "wof:name":"Dobroye Semya",
    "wof:placetype":"locality"
},
  "geometry": {"coordinates":[37.2156,54.11596],"type":"Point"}
}