{
  "type": "Feature",
  "properties": {
    "gn:admin1_code":"86",
    "gn:asciiname":"Ostrovki",
    "gn:country_code":"RU",
    "gn:dem":107,
    "gn:feature_class":"P",
    "gn:feature_code":"PPL",
    "gn:name":"Ostrovki",
    "gn:population":0,
    "gn:timezone":"Europe/Moscow",
    "iso:country":"RU",
    "name:eng_x_preferred":[
        "Ostrovki"
    ],
    "name:nor_x_preferred":[
        "Ostrovki"
    ],
    "name:rus_x_preferred":[
        "\u041e\u0441\u0442\u0440\u043e\u0432\u043a\u0438"
    ],
    "name:und_x_variant":[
        "\u041e\u0441\u0442\u0440\u043e\u0432\u043a\u0438",
        "Ostrovki"
    ],
    "wof:name":"Ostrovki",
    "wof:placetype":"locality"
},
  "geometry": {"coordinates":[40.925,51.4254],"type":"Point"}
}