{
  "type": "Feature",
  "properties": {
    "gn:admin1_code":"8",
    "gn:asciiname":"Nizhniye Bishindy",
    "gn:country_code":"RU",
    "gn:dem":140,
    "gn:feature_class":"P",
    "gn:feature_code":"PPL",
    "gn:name":"Nizhniye Bishindy",
    "gn:population":0,
    "gn:timezone":"Asia/Yekaterinburg",
    "iso:country":"RU",
    "name:rus_x_preferred":[
        "\u041d\u0438\u0436\u043d\u0438\u0435 \u0411\u0438\u0448\u0438\u043d\u0434\u044b"
    ],
    "name:und_x_variant":[
        "Nizhne-Bishindy",
        "Nizhniye Bishindy"
    ],
    "wof:name":"Nizhniye Bishindy",
    "wof:placetype":"locality"
},
  "geometry": {"coordinates":[53.74084000000001,54.48904],"type":"Point"}
}