{
  "type": "Feature",
  "properties": {
    "gn:admin1_code":"51",
    "gn:asciiname":"Lipovki",
    "gn:country_code":"RU",
    "gn:dem":75,
    "gn:feature_class":"P",
    "gn:feature_code":"PPL",
    "gn:name":"Lipovki",
    "gn:population":0,
    "gn:timezone":"Europe/Moscow",
    "iso:country":"RU",
    "name:nor_x_preferred":[
        "Lipovki"
    ],
    "name:rus_x_preferred":[
        "\u041b\u0438\u043f\u043e\u0432\u043a\u0438"
    ],
    "name:und_x_variant":[
        "Lipovka",
        "Lipovki"
    ],
    "wof:name":"Lipovki",
    "wof:placetype":"locality"
},
  "geometry": {"coordinates":[43.44845,56.57146],"type":"Point"}
}