{
  "type": "Feature",
  "properties": {
    "gn:admin1_code":"52",
    "gn:asciiname":"Mintsy",
    "gn:cc2":"RU",
    "gn:country_code":"RU",
    "gn:dem":155,
    "gn:feature_class":"P",
    "gn:feature_code":"PPL",
    "gn:name":"Mintsy",
    "gn:population":0,
    "gn:timezone":"Europe/Moscow",
    "iso:country":"RU",
    "name:eng_x_preferred":[
        "Mintsy"
    ],
    "name:nor_x_preferred":[
        "Mintsy"
    ],
    "name:rus_x_preferred":[
        "\u041c\u0438\u043d\u0446\u044b"
    ],
    "name:und_x_variant":[
        "Minzy",
        "\u041c\u0438\u043d\u0446\u044b",
        "Mintsy"
    ],
    "wof:name":"Mintsy",
    "wof:placetype":"locality"
},
  "geometry": {"coordinates":[34.75,58.95],"type":"Point"}
}