{
  "type": "Feature",
  "properties": {
    "gn:admin1_code":"13.0",
    "gn:asciiname":"Baydashka",
    "gn:country_code":"RU",
    "gn:dem":377,
    "gn:feature_class":"P",
    "gn:feature_code":"PPL",
    "gn:name":"Baydashka",
    "gn:population":0,
    "gn:timezone":"Asia/Yekaterinburg",
    "iso:country":"RU",
    "name:nor_x_preferred":[
        "Bajdasjka"
    ],
    "name:rus_x_preferred":[
        "\u0411\u0430\u0439\u0434\u0430\u0448\u043a\u0430"
    ],
    "wof:name":"Baydashka",
    "wof:placetype":"locality"
},
  "geometry": {"coordinates":[57.66667,55.26667],"type":"Point"}
}