{
  "type": "Feature",
  "properties": {
    "gn:admin1_code":"88",
    "gn:asciiname":"Sloboda",
    "gn:country_code":"RU",
    "gn:dem":172,
    "gn:feature_class":"P",
    "gn:feature_code":"PPL",
    "gn:name":"Sloboda",
    "gn:population":0,
    "gn:timezone":"Europe/Moscow",
    "iso:country":"RU",
    "name:rus_x_preferred":[
        "\u0421\u043b\u043e\u0431\u043e\u0434\u0430"
    ],
    "name:und_x_variant":[
        "Telyach\u2019ya Sloboda",
        "Sloboda",
        "\u0421\u043b\u043e\u0431\u043e\u0434\u0430"
    ],
    "wof:name":"Sloboda",
    "wof:placetype":"locality"
},
  "geometry": {"coordinates":[40.36096,58.51586999999999],"type":"Point"}
}