{
  "type": "Feature",
  "properties": {
    "gn:admin1_code":"80.0",
    "gn:asciiname":"Matys'lud",
    "gn:country_code":"RU",
    "gn:dem":241,
    "gn:feature_class":"P",
    "gn:feature_code":"PPL",
    "gn:name":"Matys\u2019lud",
    "gn:population":0,
    "gn:timezone":"Europe/Samara",
    "iso:country":"RU",
    "name:rus_x_preferred":[
        "\u041c\u0430\u0442\u044b\u0441\u044c\u043b\u0443\u0434"
    ],
    "name:und_x_variant":[
        "Matys\u2019lud"
    ],
    "wof:name":"Matys'lud",
    "wof:placetype":"locality"
},
  "geometry": {"coordinates":[53.6247,57.9703],"type":"Point"}
}