{
  "type": "Feature",
  "properties": {
    "gn:admin1_code":"47",
    "gn:asciiname":"Kryukovo",
    "gn:country_code":"RU",
    "gn:dem":140,
    "gn:feature_class":"P",
    "gn:feature_code":"PPL",
    "gn:name":"Kryukovo",
    "gn:population":0,
    "gn:timezone":"Europe/Moscow",
    "iso:country":"RU",
    "name:rus_x_preferred":[
        "\u041a\u0440\u044e\u043a\u043e\u0432\u043e"
    ],
    "name:sco_x_preferred":[
        "Kryukovo"
    ],
    "name:ukr_x_preferred":[
        "\u041a\u0440\u044e\u043a\u043e\u0432\u0435"
    ],
    "wof:name":"Kryukovo",
    "wof:placetype":"locality"
},
  "geometry": {"coordinates":[36.4118,56.4199],"type":"Point"}
}