{
  "type": "Feature",
  "properties": {
    "gn:admin1_code":"60",
    "gn:asciiname":"Lavry",
    "gn:country_code":"RU",
    "gn:dem":163,
    "gn:feature_class":"P",
    "gn:feature_code":"PPL",
    "gn:name":"Lavry",
    "gn:population":0,
    "gn:timezone":"Europe/Moscow",
    "iso:country":"RU",
    "name:che_x_preferred":[
        "\u041b\u0430\u0432\u0440\u044b"
    ],
    "name:eng_x_preferred":[
        "Lavry"
    ],
    "name:est_x_preferred":[
        "Laura"
    ],
    "name:fra_x_preferred":[
        "Lavry"
    ],
    "name:lav_x_preferred":[
        "Lavri"
    ],
    "name:nor_x_preferred":[
        "Lavry"
    ],
    "name:rus_x_preferred":[
        "\u041b\u0430\u0432\u0440\u044b"
    ],
    "wof:name":"Lavry",
    "wof:placetype":"locality"
},
  "geometry": {"coordinates":[27.48293,57.57515],"type":"Point"}
}