{
  "type": "Feature",
  "properties": {
    "gn:admin1_code":"83",
    "gn:asciiname":"Mityakovo",
    "gn:country_code":"RU",
    "gn:dem":109,
    "gn:feature_class":"P",
    "gn:feature_code":"PPL",
    "gn:name":"Mityakovo",
    "gn:population":0,
    "gn:timezone":"Europe/Moscow",
    "iso:country":"RU",
    "name:rus_x_preferred":[
        "\u041c\u0438\u0442\u044f\u043a\u043e\u0432\u043e"
    ],
    "name:und_x_variant":[
        "\u041c\u0438\u0442\u044f\u043a\u043e\u0432\u043e"
    ],
    "wof:name":"Mityakovo",
    "wof:placetype":"locality"
},
  "geometry": {"coordinates":[41.7749,55.9589],"type":"Point"}
}