{
  "type": "Feature",
  "properties": {
    "gn:admin1_code":"20",
    "gn:asciiname":"Verkhneye Markovo",
    "gn:cc2":"RU",
    "gn:country_code":"RU",
    "gn:dem":346,
    "gn:feature_class":"P",
    "gn:feature_code":"PPL",
    "gn:name":"Verkhneye Markovo",
    "gn:population":0,
    "gn:timezone":"Asia/Irkutsk",
    "iso:country":"RU",
    "name:eng_x_preferred":[
        "Verkhneye Markovo"
    ],
    "name:nor_x_preferred":[
        "Verkhnemarkovo"
    ],
    "name:rus_x_preferred":[
        "\u0412\u0435\u0440\u0445\u043d\u0435\u043c\u0430\u0440\u043a\u043e\u0432\u043e"
    ],
    "name:und_x_variant":[
        "Verkhneye Markovskoye"
    ],
    "wof:name":"Verkhneye Markovo",
    "wof:placetype":"locality"
},
  "geometry": {"coordinates":[107.09999999999999,57.33333],"type":"Point"}
}