{
  "type": "Feature",
  "properties": {
    "gn:admin1_code":"77.0",
    "gn:asciiname":"Glebtsevo",
    "gn:country_code":"RU",
    "gn:dem":174,
    "gn:feature_class":"P",
    "gn:feature_code":"PPL",
    "gn:name":"Glebtsevo",
    "gn:population":0,
    "gn:timezone":"Europe/Moscow",
    "iso:country":"RU",
    "name:rus_x_preferred":[
        "\u0413\u043b\u0435\u0431\u0446\u0435\u0432\u043e"
    ],
    "wof:name":"Glebtsevo",
    "wof:placetype":"locality"
},
  "geometry": {"coordinates":[34.96855,57.64957],"type":"Point"}
}