{
  "type": "Feature",
  "properties": {
    "gn:admin1_code":"51",
    "gn:asciiname":"Fominskiye",
    "gn:country_code":"RU",
    "gn:dem":121,
    "gn:feature_class":"P",
    "gn:feature_code":"PPL",
    "gn:name":"Fominskiye",
    "gn:population":0,
    "gn:timezone":"Europe/Moscow",
    "iso:country":"RU",
    "name:rus_x_preferred":[
        "\u0424\u043e\u043c\u0438\u043d\u0441\u043a\u0438\u0435"
    ],
    "name:und_x_variant":[
        "\u0424\u043e\u043c\u0438\u043d\u0441\u043a\u0438\u0435"
    ],
    "wof:name":"Fominskiye",
    "wof:placetype":"locality"
},
  "geometry": {"coordinates":[46.5337,57.0793],"type":"Point"}
}