{
  "type": "Feature",
  "properties": {
    "gn:admin1_code":"23",
    "gn:asciiname":"Ochakovo",
    "gn:country_code":"RU",
    "gn:dem":62,
    "gn:feature_class":"P",
    "gn:feature_code":"PPL",
    "gn:name":"Ochakovo",
    "gn:population":0,
    "gn:timezone":"Europe/Kaliningrad",
    "iso:country":"RU",
    "name:rus_x_preferred":[
        "\u041e\u0447\u0430\u043a\u043e\u0432\u043e"
    ],
    "wof:name":"Ochakovo",
    "wof:placetype":"locality"
},
  "geometry": {"coordinates":[22.21556,54.65556],"type":"Point"}
}