{
  "type": "Feature",
  "properties": {
    "gn:admin1_code":"62",
    "gn:asciiname":"Nekrasovka",
    "gn:country_code":"RU",
    "gn:dem":137,
    "gn:feature_class":"P",
    "gn:feature_code":"PPL",
    "gn:name":"Nekrasovka",
    "gn:population":0,
    "gn:timezone":"Europe/Moscow",
    "iso:country":"RU",
    "name:ceb_x_preferred":[
        "Nekrasovka"
    ],
    "name:eng_x_preferred":[
        "Nekrasovka"
    ],
    "name:nld_x_preferred":[
        "Nekrasovka"
    ],
    "name:nor_x_preferred":[
        "Nekrasovka"
    ],
    "name:rus_x_preferred":[
        "\u041d\u0435\u043a\u0440\u0430\u0441\u043e\u0432\u043a\u0430"
    ],
    "wof:name":"Nekrasovka",
    "wof:placetype":"locality"
},
  "geometry": {"coordinates":[42.1753,54.802],"type":"Point"}
}