{
  "type": "Feature",
  "properties": {
    "gn:admin1_code":"13",
    "gn:asciiname":"Krasnoyarskiy",
    "gn:country_code":"RU",
    "gn:dem":381,
    "gn:feature_class":"P",
    "gn:feature_code":"PPL",
    "gn:name":"Krasnoyarskiy",
    "gn:population":0,
    "gn:timezone":"Asia/Yekaterinburg",
    "iso:country":"RU",
    "name:rus_x_preferred":[
        "\u041a\u0440\u0430\u0441\u043d\u043e\u044f\u0440\u0441\u043a\u0438\u0439"
    ],
    "name:und_x_variant":[
        "\u041a\u0440\u0430\u0441\u043d\u043e\u044f\u0440\u0441\u043a\u0438\u0439"
    ],
    "wof:name":"Krasnoyarskiy",
    "wof:placetype":"locality"
},
  "geometry": {"coordinates":[59.41389,53.48167],"type":"Point"}
}