{
  "type": "Feature",
  "properties": {
    "gn:admin1_code":"6.0",
    "gn:asciiname":"Smutovo",
    "gn:country_code":"RU",
    "gn:dem":58,
    "gn:feature_class":"P",
    "gn:feature_code":"PPL",
    "gn:name":"Smutovo",
    "gn:population":0,
    "gn:timezone":"Europe/Moscow",
    "iso:country":"RU",
    "name:rus_x_preferred":[
        "\u0421\u043c\u0443\u0442\u043e\u0432\u043e"
    ],
    "wof:name":"Smutovo",
    "wof:placetype":"locality"
},
  "geometry": {"coordinates":[45.1863,63.8157],"type":"Point"}
}