{
  "type": "Feature",
  "properties": {
    "gn:admin1_code":"8",
    "gn:asciiname":"Ivshinskiy",
    "gn:country_code":"RU",
    "gn:dem":298,
    "gn:feature_class":"P",
    "gn:feature_code":"PPL",
    "gn:name":"Ivshinskiy",
    "gn:population":0,
    "gn:timezone":"Asia/Yekaterinburg",
    "iso:country":"RU",
    "name:rus_x_preferred":[
        "\u0418\u0432\u0448\u0438\u043d\u0441\u043a\u0438\u0439"
    ],
    "wof:name":"Ivshinskiy",
    "wof:placetype":"locality"
},
  "geometry": {"coordinates":[58.03333000000001,55.78333000000001],"type":"Point"}
}