{
  "type": "Feature",
  "properties": {
    "gn:admin1_code":"6",
    "gn:asciiname":"Titovskiy Pochinok",
    "gn:country_code":"RU",
    "gn:dem":61,
    "gn:feature_class":"P",
    "gn:feature_code":"PPL",
    "gn:name":"Titovskiy Pochinok",
    "gn:population":0,
    "gn:timezone":"Europe/Moscow",
    "iso:country":"RU",
    "wof:name":"Titovskiy Pochinok",
    "wof:placetype":"locality"
},
  "geometry": {"coordinates":[46.16291,61.48723],"type":"Point"}
}