{
  "type": "Feature",
  "properties": {
    "gn:admin1_code":"9.0",
    "gn:asciiname":"Krepatskiy",
    "gn:country_code":"RU",
    "gn:dem":146,
    "gn:feature_class":"P",
    "gn:feature_code":"PPL",
    "gn:name":"Krepatskiy",
    "gn:population":0,
    "gn:timezone":"Europe/Moscow",
    "iso:country":"RU",
    "name:rus_x_preferred":[
        "\u041a\u0440\u0435\u043f\u0430\u0446\u043a\u0438\u0439"
    ],
    "name:und_x_variant":[
        "Krepatskoye",
        "Krepatskiy"
    ],
    "wof:name":"Krepatskiy",
    "wof:placetype":"locality"
},
  "geometry": {"coordinates":[37.4242,50.5381],"type":"Point"}
}