{
  "type": "Feature",
  "properties": {
    "gn:admin1_code":"91",
    "gn:asciiname":"Kuz'movka",
    "gn:country_code":"RU",
    "gn:dem":73,
    "gn:feature_class":"P",
    "gn:feature_code":"PPL",
    "gn:name":"Kuz\u2019movka",
    "gn:population":0,
    "gn:timezone":"Asia/Krasnoyarsk",
    "iso:country":"RU",
    "name:eng_x_preferred":[
        "Kuz'movka"
    ],
    "name:nor_x_preferred":[
        "Kuzmovka"
    ],
    "name:rus_x_preferred":[
        "\u041a\u0443\u0437\u044c\u043c\u043e\u0432\u043a\u0430"
    ],
    "name:und_x_variant":[
        "Kuz\u2019movka"
    ],
    "wof:name":"Kuz'movka",
    "wof:placetype":"locality"
},
  "geometry": {"coordinates":[92.11778,62.31083],"type":"Point"}
}