{
  "type": "Feature",
  "properties": {
    "gn:admin1_code":"20",
    "gn:asciiname":"Sharabora",
    "gn:country_code":"RU",
    "gn:dem":310,
    "gn:feature_class":"P",
    "gn:feature_code":"PPL",
    "gn:name":"Sharabora",
    "gn:population":0,
    "gn:timezone":"Asia/Irkutsk",
    "iso:country":"RU",
    "name:rus_x_preferred":[
        "\u0428\u0430\u0440\u0430\u0431\u043e\u0440\u0430"
    ],
    "name:und_x_variant":[
        "\u0428\u0430\u0440\u0430\u0431\u043e\u0440\u0430"
    ],
    "wof:name":"Sharabora",
    "wof:placetype":"locality"
},
  "geometry": {"coordinates":[108.03784,56.79653],"type":"Point"}
}