{
  "type": "Feature",
  "properties": {
    "gn:admin1_code":"10",
    "gn:asciiname":"Lesnoye",
    "gn:country_code":"RU",
    "gn:dem":190,
    "gn:feature_class":"P",
    "gn:feature_code":"PPL",
    "gn:name":"Lesnoye",
    "gn:population":0,
    "gn:timezone":"Europe/Moscow",
    "iso:country":"RU",
    "name:eng_x_preferred":[
        "Lesnoye"
    ],
    "name:nor_x_preferred":[
        "Batagovo"
    ],
    "name:rus_x_preferred":[
        "\u0411\u0430\u0442\u0430\u0433\u043e\u0432\u043e"
    ],
    "name:rus_x_variant":[
        "\u041b\u0435\u0441\u043d\u043e\u0435"
    ],
    "name:und_x_variant":[
        "Batogovo"
    ],
    "wof:name":"Lesnoye",
    "wof:placetype":"locality"
},
  "geometry": {"coordinates":[34.59068,53.35915],"type":"Point"}
}