{
  "type": "Feature",
  "properties": {
    "gn:admin1_code":"42",
    "gn:asciiname":"Vladychkino",
    "gn:country_code":"RU",
    "gn:dem":78,
    "gn:feature_class":"P",
    "gn:feature_code":"PPL",
    "gn:name":"Vladychkino",
    "gn:population":0,
    "gn:timezone":"Europe/Moscow",
    "iso:country":"RU",
    "name:eng_x_preferred":[
        "Vladychkino"
    ],
    "name:nor_x_preferred":[
        "Vladytsjkino"
    ],
    "name:rus_x_preferred":[
        "\u0412\u043b\u0430\u0434\u044b\u0447\u043a\u0438\u043d\u043e"
    ],
    "wof:name":"Vladychkino",
    "wof:placetype":"locality"
},
  "geometry": {"coordinates":[30.06444,59.02333],"type":"Point"}
}