{
  "type": "Feature",
  "properties": {
    "gn:admin1_code":"45",
    "gn:asciiname":"Malyy Shuduguzh",
    "gn:country_code":"RU",
    "gn:dem":93,
    "gn:feature_class":"P",
    "gn:feature_code":"PPL",
    "gn:name":"Malyy Shuduguzh",
    "gn:population":0,
    "gn:timezone":"Europe/Moscow",
    "iso:country":"RU",
    "name:rus_x_preferred":[
        "\u041c\u0430\u043b\u044b\u0439 \u0428\u0443\u0434\u0443\u0433\u0443\u0436"
    ],
    "name:und_x_variant":[
        "Malyy Shudguzh",
        "Malyy Shudugush",
        "Malyy Shuduguzh"
    ],
    "wof:name":"Malyy Shuduguzh",
    "wof:placetype":"locality"
},
  "geometry": {"coordinates":[46.43874,56.87434],"type":"Point"}
}