{
  "type": "Feature",
  "properties": {
    "gn:admin1_code":"41",
    "gn:asciiname":"Lutovka",
    "gn:country_code":"RU",
    "gn:dem":216,
    "gn:feature_class":"P",
    "gn:feature_code":"PPL",
    "gn:name":"Lutovka",
    "gn:population":0,
    "gn:timezone":"Europe/Moscow",
    "iso:country":"RU",
    "name:rus_x_preferred":[
        "\u041b\u0443\u0442\u043e\u0432\u043a\u0430"
    ],
    "wof:name":"Lutovka",
    "wof:placetype":"locality"
},
  "geometry": {"coordinates":[36.48923,52.0725],"type":"Point"}
}