{
  "type": "Feature",
  "properties": {
    "gn:admin1_code":"37",
    "gn:asciiname":"Krasavitsa",
    "gn:country_code":"RU",
    "gn:dem":165,
    "gn:feature_class":"P",
    "gn:feature_code":"PPL",
    "gn:name":"Krasavitsa",
    "gn:population":0,
    "gn:timezone":"Europe/Moscow",
    "iso:country":"RU",
    "name:rus_x_preferred":[
        "\u041a\u0440\u0430\u0441\u0430\u0432\u0438\u0446\u0430"
    ],
    "wof:name":"Krasavitsa",
    "wof:placetype":"locality"
},
  "geometry": {"coordinates":[44.76667,58.63333000000001],"type":"Point"}
}