{
  "type": "Feature",
  "properties": {
    "gn:admin1_code":"90.0",
    "gn:asciiname":"Lyagushino",
    "gn:country_code":"RU",
    "gn:dem":106,
    "gn:feature_class":"P",
    "gn:feature_code":"PPL",
    "gn:name":"Lyagushino",
    "gn:population":0,
    "gn:timezone":"Asia/Yekaterinburg",
    "iso:country":"RU",
    "name:che_x_preferred":[
        "\u041b\u044f\u0433\u0443\u0448\u0438\u043d\u043e"
    ],
    "name:rus_x_preferred":[
        "\u041b\u044f\u0433\u0443\u0448\u0438\u043d\u043e"
    ],
    "wof:name":"Lyagushino",
    "wof:placetype":"locality"
},
  "geometry": {"coordinates":[55.3322,58.0854],"type":"Point"}
}