{
  "type": "Feature",
  "properties": {
    "gn:admin1_code":"47.0",
    "gn:asciiname":"Denis'yevo",
    "gn:country_code":"RU",
    "gn:dem":120,
    "gn:feature_class":"P",
    "gn:feature_code":"PPL",
    "gn:name":"Denis\u2019yevo",
    "gn:population":0,
    "gn:timezone":"Europe/Moscow",
    "iso:country":"RU",
    "name:rus_x_preferred":[
        "\u0414\u0435\u043d\u0438\u0441\u044c\u0435\u0432\u043e"
    ],
    "name:und_x_variant":[
        "Denis\u2019yevo",
        "\u0414\u0435\u043d\u0438\u0441\u044c\u0435\u0432\u043e"
    ],
    "wof:name":"Denis'yevo",
    "wof:placetype":"locality"
},
  "geometry": {"coordinates":[39.87062,55.28998000000001],"type":"Point"}
}