{
  "type": "Feature",
  "properties": {
    "gn:admin1_code":"9.0",
    "gn:asciiname":"Bankino",
    "gn:country_code":"RU",
    "gn:dem":190,
    "gn:feature_class":"P",
    "gn:feature_code":"PPL",
    "gn:name":"Bankino",
    "gn:population":0,
    "gn:timezone":"Europe/Moscow",
    "iso:country":"RU",
    "name:nor_x_preferred":[
        "Bankino"
    ],
    "name:rus_x_preferred":[
        "\u0411\u0430\u043d\u043a\u0438\u043d\u043e"
    ],
    "name:und_x_variant":[
        "Ban\u2019kin"
    ],
    "wof:name":"Bankino",
    "wof:placetype":"locality"
},
  "geometry": {"coordinates":[38.7453,50.1113],"type":"Point"}
}