{
  "type": "Feature",
  "properties": {
    "gn:admin1_code":"51",
    "gn:asciiname":"Kiseli",
    "gn:country_code":"RU",
    "gn:dem":120,
    "gn:feature_class":"P",
    "gn:feature_code":"PPL",
    "gn:name":"Kiseli",
    "gn:population":0,
    "gn:timezone":"Europe/Moscow",
    "iso:country":"RU",
    "name:rus_x_preferred":[
        "\u041a\u0438\u0441\u0435\u043b\u0438"
    ],
    "name:und_x_variant":[
        "\u041a\u0438\u0441\u0435\u043b\u0438"
    ],
    "wof:name":"Kiseli",
    "wof:placetype":"locality"
},
  "geometry": {"coordinates":[46.6557,56.9716],"type":"Point"}
}