{
  "type": "Feature",
  "properties": {
    "gn:admin1_code":"62",
    "gn:asciiname":"Vyalsy",
    "gn:country_code":"RU",
    "gn:dem":92,
    "gn:feature_class":"P",
    "gn:feature_code":"PPL",
    "gn:name":"Vyalsy",
    "gn:population":0,
    "gn:timezone":"Europe/Moscow",
    "iso:country":"RU",
    "name:eng_x_preferred":[
        "Vyalsy"
    ],
    "name:nor_x_preferred":[
        "Vjalsy"
    ],
    "name:rus_x_preferred":[
        "\u0412\u044f\u043b\u0441\u044b"
    ],
    "wof:name":"Vyalsy",
    "wof:placetype":"locality"
},
  "geometry": {"coordinates":[42.0009,54.2718],"type":"Point"}
}