{
  "type": "Feature",
  "properties": {
    "gn:admin1_code":"38",
    "gn:asciiname":"Shirokaya Pshadskaya Shchel'",
    "gn:country_code":"RU",
    "gn:dem":84,
    "gn:feature_class":"P",
    "gn:feature_code":"PPL",
    "gn:name":"Shirokaya Pshadskaya Shchel\u2019",
    "gn:population":0,
    "gn:timezone":"Europe/Moscow",
    "iso:country":"RU",
    "name:rus_x_preferred":[
        "\u0428\u0438\u0440\u043e\u043a\u0430\u044f \u041f\u0448\u0430\u0434\u0441\u043a\u0430\u044f \u0429\u0435\u043b\u044c"
    ],
    "name:und_x_variant":[
        "Shirokaya Pshadskaya Shchel\u2019"
    ],
    "wof:name":"Shirokaya Pshadskaya Shchel'",
    "wof:placetype":"locality"
},
  "geometry": {"coordinates":[38.3546,44.4918],"type":"Point"}
}