{
  "type": "Feature",
  "properties": {
    "gn:admin1_code":"80",
    "gn:asciiname":"Kizner",
    "gn:country_code":"RU",
    "gn:dem":93,
    "gn:feature_class":"P",
    "gn:feature_code":"PPL",
    "gn:name":"Kizner",
    "gn:population":0,
    "gn:timezone":"Europe/Samara",
    "iso:country":"RU",
    "name:eng_x_preferred":[
        "Kizner"
    ],
    "name:nor_x_preferred":[
        "Kizner"
    ],
    "name:rus_x_preferred":[
        "\u041a\u0438\u0437\u043d\u0435\u0440"
    ],
    "name:und_x_variant":[
        "\u041a\u0438\u0437\u043d\u0435\u0440"
    ],
    "wof:name":"Kizner",
    "wof:placetype":"locality"
},
  "geometry": {"coordinates":[51.51624,56.31161],"type":"Point"}
}