{
  "type": "Feature",
  "properties": {
    "gn:admin1_code":"51",
    "gn:asciiname":"Nershevo",
    "gn:country_code":"RU",
    "gn:dem":176,
    "gn:feature_class":"P",
    "gn:feature_code":"PPL",
    "gn:name":"Nershevo",
    "gn:population":0,
    "gn:timezone":"Europe/Moscow",
    "iso:country":"RU",
    "name:rus_x_preferred":[
        "\u041d\u0435\u0440\u0448\u0435\u0432\u043e"
    ],
    "wof:name":"Nershevo",
    "wof:placetype":"locality"
},
  "geometry": {"coordinates":[42.8726,55.7625],"type":"Point"}
}