{
  "type": "Feature",
  "properties": {
    "gn:admin1_code":"91",
    "gn:asciiname":"Idzha",
    "gn:cc2":"RU",
    "gn:country_code":"RU",
    "gn:dem":303,
    "gn:feature_class":"P",
    "gn:feature_code":"PPL",
    "gn:name":"Idzha",
    "gn:population":0,
    "gn:timezone":"Asia/Krasnoyarsk",
    "iso:country":"RU",
    "name:eng_x_preferred":[
        "Idzha"
    ],
    "name:nor_x_preferred":[
        "Idzja"
    ],
    "name:rus_x_preferred":[
        "\u0418\u0434\u0436\u0430"
    ],
    "name:und_x_variant":[
        "Ija",
        "Idzha"
    ],
    "wof:name":"Idzha",
    "wof:placetype":"locality"
},
  "geometry": {"coordinates":[91.97667,53.18806],"type":"Point"}
}