{
  "type": "Feature",
  "properties": {
    "gn:gn_country":"RU",
    "gn:gn_fcode":"PPL",
    "gn:gn_pop":7090,
    "gn:population":7090,
    "iso:country":"RU",
    "name:eng_x_preferred":[
        "Komarichi"
    ],
    "name:nor_x_preferred":[
        "Komaritsji"
    ],
    "name:rus_x_preferred":[
        "\u041a\u043e\u043c\u0430\u0440\u0438\u0447\u0438"
    ],
    "name:unk_x_variant":[
        "Komaritschi"
    ],
    "qs_pg:aaroncc":"RU",
    "qs_pg:gn_country":"RU",
    "qs_pg:gn_fcode":"PPL",
    "qs_pg:gn_pop":7090,
    "qs_pg:name":"Kozarichi",
    "qs_pg:name_adm0":"Russia",
    "qs_pg:name_adm1":"Bryansk Oblast",
    "qs_pg:photos_9r":0,
    "qs_pg:photos_sr":0,
    "qs_pg:pop_sr":5,
    "qs_pg:qs_pg_placetype":"locality",
    "qs_pg:qs_pg_placetype_gp":"Town",
    "qs_pg:woe_adm0":23424936,
    "woe:adm0_id":23424936,
    "woe:name_adm0":"Russia",
    "woe:name_adm1":"Bryansk Oblast",
    "woe:placetype":"Town",
    "wof:name":"Kozarichi",
    "wof:placetype":"locality",
    "wof:population":7090
},
  "geometry": {"coordinates":[34.7905,52.4151],"type":"Point"}
}