{
  "type": "Feature",
  "properties": {
    "gn:admin1_code":"54",
    "gn:asciiname":"Kubrino",
    "gn:country_code":"RU",
    "gn:dem":72,
    "gn:feature_class":"P",
    "gn:feature_code":"PPL",
    "gn:name":"Kubrino",
    "gn:population":0,
    "gn:timezone":"Asia/Omsk",
    "iso:country":"RU",
    "name:eng_x_preferred":[
        "Kubrino"
    ],
    "name:nor_x_preferred":[
        "Kubrino"
    ],
    "name:rus_x_preferred":[
        "\u041a\u0443\u0431\u0440\u0438\u043d\u043e"
    ],
    "wof:name":"Kubrino",
    "wof:placetype":"locality"
},
  "geometry": {"coordinates":[73.95159,56.86469],"type":"Point"}
}