{
  "type": "Feature",
  "properties": {
    "gn:admin1_code":"91",
    "gn:asciiname":"Bartanas",
    "gn:country_code":"RU",
    "gn:dem":157,
    "gn:feature_class":"P",
    "gn:feature_code":"PPL",
    "gn:name":"Bartanas",
    "gn:population":0,
    "gn:timezone":"Asia/Krasnoyarsk",
    "iso:country":"RU",
    "name:eng_x_preferred":[
        "Bartanas"
    ],
    "name:nor_x_preferred":[
        "Bartanas"
    ],
    "name:rus_x_preferred":[
        "\u0411\u0430\u0440\u0442\u0430\u043d\u0430\u0441"
    ],
    "wof:name":"Bartanas",
    "wof:placetype":"locality"
},
  "geometry": {"coordinates":[94.66189,57.25857],"type":"Point"}
}