{
  "type": "Feature",
  "properties": {
    "gn:admin1_code":"77",
    "gn:asciiname":"Vados",
    "gn:country_code":"RU",
    "gn:dem":75,
    "gn:feature_class":"P",
    "gn:feature_code":"PPL",
    "gn:name":"Vados",
    "gn:population":0,
    "gn:timezone":"Europe/Moscow",
    "iso:country":"RU",
    "name:rus_x_preferred":[
        "\u0412\u0430\u0434\u043e\u0441"
    ],
    "name:und_x_variant":[
        "\u0412\u0430\u0434\u043e\u0441"
    ],
    "wof:name":"Vados",
    "wof:placetype":"locality"
},
  "geometry": {"coordinates":[30.9539,56.8744],"type":"Point"}
}