{
  "type": "Feature",
  "properties": {
    "gn:admin1_code":"16.0",
    "gn:asciiname":"Demkino",
    "gn:country_code":"RU",
    "gn:dem":168,
    "gn:feature_class":"P",
    "gn:feature_code":"PPL",
    "gn:name":"D\u00ebmkino",
    "gn:population":0,
    "gn:timezone":"Europe/Moscow",
    "iso:country":"RU",
    "name:rus_x_preferred":[
        "\u0414\u0451\u043c\u043a\u0438\u043d\u043e"
    ],
    "name:und_x_variant":[
        "D\u00ebmkino"
    ],
    "wof:name":"Demkino",
    "wof:placetype":"locality"
},
  "geometry": {"coordinates":[46.53787,55.92706],"type":"Point"}
}