{
  "type": "Feature",
  "properties": {
    "gn:admin1_code":"23",
    "gn:asciiname":"Dyunnoye",
    "gn:country_code":"RU",
    "gn:dem":-2,
    "gn:feature_class":"P",
    "gn:feature_code":"PPL",
    "gn:name":"Dyunnoye",
    "gn:population":0,
    "gn:timezone":"Europe/Kaliningrad",
    "iso:country":"RU",
    "name:rus_x_preferred":[
        "\u0414\u044e\u043d\u043d\u043e\u0435"
    ],
    "name:und_x_variant":[
        "\u0414\u044e\u043d\u043d\u043e\u0435"
    ],
    "wof:name":"Dyunnoye",
    "wof:placetype":"locality"
},
  "geometry": {"coordinates":[21.39822,55.2133],"type":"Point"}
}