{
  "type": "Feature",
  "properties": {
    "gn:admin1_code":"8",
    "gn:asciiname":"Nikolayevka",
    "gn:country_code":"RU",
    "gn:dem":304,
    "gn:feature_class":"P",
    "gn:feature_code":"PPL",
    "gn:name":"Nikolayevka",
    "gn:population":0,
    "gn:timezone":"Asia/Yekaterinburg",
    "iso:country":"RU",
    "name:aze_x_preferred":[
        "Nikolayevka"
    ],
    "name:deu_x_preferred":[
        "Nikolajewka"
    ],
    "name:eng_x_preferred":[
        "Nikolayevka"
    ],
    "name:hye_x_preferred":[
        "\u0546\u056b\u056f\u0578\u056c\u0561\u0587\u056f\u0561"
    ],
    "name:ita_x_preferred":[
        "Nikolaevka"
    ],
    "name:lav_x_preferred":[
        "Nikolajevka"
    ],
    "name:nld_x_preferred":[
        "Nikolajevka"
    ],
    "name:nor_x_preferred":[
        "Nikolajevka"
    ],
    "name:ron_x_preferred":[
        "Nicolaevca"
    ],
    "name:rus_x_preferred":[
        "\u041d\u0438\u043a\u043e\u043b\u0430\u0435\u0432\u043a\u0430"
    ],
    "name:spa_x_preferred":[
        "Nikolaevka"
    ],
    "name:ukr_x_preferred":[
        "\u041d\u0456\u043a\u043e\u043b\u0430\u0454\u0432\u043a\u0430"
    ],
    "wof:name":"Nikolayevka",
    "wof:placetype":"locality"
},
  "geometry": {"coordinates":[55.08844000000001,53.69999],"type":"Point"}
}