{
  "type": "Feature",
  "properties": {
    "gn:admin1_code":"33",
    "gn:asciiname":"Klyapino",
    "gn:country_code":"RU",
    "gn:dem":110,
    "gn:feature_class":"P",
    "gn:feature_code":"PPL",
    "gn:name":"Klyapino",
    "gn:population":0,
    "gn:timezone":"Europe/Kirov",
    "iso:country":"RU",
    "name:rus_x_preferred":[
        "\u041a\u043b\u044f\u043f\u0438\u043d\u043e"
    ],
    "wof:name":"Klyapino",
    "wof:placetype":"locality"
},
  "geometry": {"coordinates":[47.8741,57.2616],"type":"Point"}
}