{
  "type": "Feature",
  "properties": {
    "gn:admin1_code":"9",
    "gn:asciiname":"Bondarev",
    "gn:country_code":"RU",
    "gn:dem":210,
    "gn:feature_class":"P",
    "gn:feature_code":"PPL",
    "gn:name":"Bondarev",
    "gn:population":0,
    "gn:timezone":"Europe/Moscow",
    "iso:country":"RU",
    "name:rus_x_preferred":[
        "\u0411\u043e\u043d\u0434\u0430\u0440\u0435\u0432"
    ],
    "wof:name":"Bondarev",
    "wof:placetype":"locality"
},
  "geometry": {"coordinates":[37.6345,50.6209],"type":"Point"}
}