{
  "type": "Feature",
  "properties": {
    "gn:admin1_code":"4",
    "gn:asciiname":"Bludovka",
    "gn:cc2":"RU",
    "gn:country_code":"RU",
    "gn:dem":121,
    "gn:feature_class":"P",
    "gn:feature_code":"PPL",
    "gn:name":"Bludovka",
    "gn:population":0,
    "gn:timezone":"Asia/Barnaul",
    "iso:country":"RU",
    "name:rus_x_preferred":[
        "\u0411\u043b\u0443\u0434\u043e\u0432\u043a\u0430"
    ],
    "name:und_x_variant":[
        "Bludovskiy",
        "Bludovka"
    ],
    "wof:name":"Bludovka",
    "wof:placetype":"locality"
},
  "geometry": {"coordinates":[78.59999999999999,53.21666999999999],"type":"Point"}
}