{
  "type": "Feature",
  "properties": {
    "gn:admin1_code":"85",
    "gn:asciiname":"Korolevo",
    "gn:country_code":"RU",
    "gn:dem":90,
    "gn:feature_class":"P",
    "gn:feature_code":"PPL",
    "gn:name":"Korol\u00ebvo",
    "gn:population":0,
    "gn:timezone":"Europe/Moscow",
    "iso:country":"RU",
    "name:bel_x_preferred":[
        "\u041a\u0430\u0440\u0430\u043b\u044d\u0432\u0430"
    ],
    "name:ceb_x_preferred":[
        "Korolevo"
    ],
    "name:ces_x_preferred":[
        "Korolevo"
    ],
    "name:crh_x_preferred":[
        "Korolevo"
    ],
    "name:deu_x_preferred":[
        "Korolewo"
    ],
    "name:epo_x_preferred":[
        "Korolevo"
    ],
    "name:hun_x_preferred":[
        "Kir\u00e1lyh\u00e1za"
    ],
    "name:hye_x_preferred":[
        "\u053f\u0578\u0580\u0578\u056c\u0575\u0578\u057e\u0578"
    ],
    "name:pol_x_preferred":[
        "Koro\u0142ewo"
    ],
    "name:ron_x_preferred":[
        "Korolevo"
    ],
    "name:rus_x_preferred":[
        "\u041a\u043e\u0440\u043e\u043b\u0451\u0432\u043e"
    ],
    "name:ukr_x_preferred":[
        "\u041a\u043e\u0440\u043e\u043b\u0435\u0432\u043e"
    ],
    "name:und_x_variant":[
        "Korol\u00ebvo"
    ],
    "name:zho_x_preferred":[
        "\u79d1\u7f85\u5217\u6c83"
    ],
    "wof:name":"Korolevo",
    "wof:placetype":"locality"
},
  "geometry": {"coordinates":[46.8499,60.6555],"type":"Point"}
}