{
  "type": "Feature",
  "properties": {
    "gn:admin1_code":"85",
    "gn:asciiname":"Korolevo",
    "gn:country_code":"RU",
    "gn:dem":90,
    "gn:feature_class":"P",
    "gn:feature_code":"PPL",
    "gn:name":"Korol\u00ebvo",
    "gn:population":0,
    "gn:timezone":"Europe/Moscow",
    "iso:country":"RU",
    "name:rus_x_preferred":[
        "\u041a\u043e\u0440\u043e\u043b\u0451\u0432\u043e"
    ],
    "name:und_x_variant":[
        "Korol\u00ebvo",
        "\u041a\u043e\u0440\u043e\u043b\u0451\u0432\u043e"
    ],
    "wof:name":"Korolevo",
    "wof:placetype":"locality"
},
  "geometry": {"coordinates":[46.8499,60.6555],"type":"Point"}
}