{
  "type": "Feature",
  "properties": {
    "gn:admin1_code":"3",
    "gn:asciiname":"Suranash",
    "gn:country_code":"RU",
    "gn:dem":374,
    "gn:feature_class":"P",
    "gn:feature_code":"PPL",
    "gn:name":"Suranash",
    "gn:population":0,
    "gn:timezone":"Asia/Omsk",
    "iso:country":"RU",
    "name:rus_x_preferred":[
        "\u0421\u0443\u0440\u0430\u043d\u0430\u0448"
    ],
    "name:und_x_variant":[
        "\u0421\u0443\u0440\u0430\u043d\u0430\u0448"
    ],
    "wof:name":"Suranash",
    "wof:placetype":"locality"
},
  "geometry": {"coordinates":[87.75749999999999,52.2954],"type":"Point"}
}