{
  "type": "Feature",
  "properties": {
    "gn:admin1_code":"25",
    "gn:asciiname":"Kas'kovo",
    "gn:country_code":"RU",
    "gn:dem":233,
    "gn:feature_class":"P",
    "gn:feature_code":"PPL",
    "gn:name":"Kas\u2019kovo",
    "gn:population":0,
    "gn:timezone":"Europe/Moscow",
    "iso:country":"RU",
    "name:rus_x_preferred":[
        "\u041a\u0430\u0441\u044c\u043a\u043e\u0432\u043e"
    ],
    "name:und_x_variant":[
        "Kas\u2019kovo",
        "\u041a\u0430\u0441\u044c\u043a\u043e\u0432\u043e"
    ],
    "wof:name":"Kas'kovo",
    "wof:placetype":"locality"
},
  "geometry": {"coordinates":[34.43887,54.38094],"type":"Point"}
}