{
  "type": "Feature",
  "properties": {
    "gn:admin1_code":"78",
    "gn:asciiname":"Meshalkina",
    "gn:country_code":"RU",
    "gn:dem":95,
    "gn:feature_class":"P",
    "gn:feature_code":"PPL",
    "gn:name":"Meshalkina",
    "gn:population":0,
    "gn:timezone":"Asia/Yekaterinburg",
    "iso:country":"RU",
    "name:rus_x_preferred":[
        "\u041c\u0435\u0448\u0430\u043b\u043a\u0438\u043d\u0430"
    ],
    "wof:name":"Meshalkina",
    "wof:placetype":"locality"
},
  "geometry": {"coordinates":[70.06699999999999,56.0839],"type":"Point"}
}