{
  "type": "Feature",
  "properties": {
    "gn:admin1_code":"70",
    "gn:asciiname":"Kalausskiy",
    "gn:country_code":"RU",
    "gn:dem":70,
    "gn:feature_class":"P",
    "gn:feature_code":"PPL",
    "gn:name":"Kalausskiy",
    "gn:population":0,
    "gn:timezone":"Europe/Moscow",
    "iso:country":"RU",
    "name:rus_x_preferred":[
        "\u041a\u0430\u043b\u0430\u0443\u0441\u0441\u043a\u0438\u0439"
    ],
    "wof:name":"Kalausskiy",
    "wof:placetype":"locality"
},
  "geometry": {"coordinates":[43.29778,45.80111],"type":"Point"}
}