{
  "type": "Feature",
  "properties": {
    "gn:admin1_code":"62",
    "gn:asciiname":"Proyavnyy",
    "gn:cc2":"RU",
    "gn:country_code":"RU",
    "gn:dem":139,
    "gn:feature_class":"P",
    "gn:feature_code":"PPL",
    "gn:name":"Proyavnyy",
    "gn:population":0,
    "gn:timezone":"Europe/Moscow",
    "iso:country":"RU",
    "name:rus_x_preferred":[
        "\u041f\u0440\u043e\u044f\u0432\u043d\u044b\u0439"
    ],
    "name:und_x_variant":[
        "Proyavny",
        "Proyavnyy"
    ],
    "wof:name":"Proyavnyy",
    "wof:placetype":"locality"
},
  "geometry": {"coordinates":[40.85,53.93333000000001],"type":"Point"}
}