{
  "type": "Feature",
  "properties": {
    "gn:admin1_code":"28",
    "gn:asciiname":"Sosnovyy",
    "gn:country_code":"RU",
    "gn:dem":124,
    "gn:feature_class":"P",
    "gn:feature_code":"PPL",
    "gn:name":"Sosnovyy",
    "gn:population":0,
    "gn:timezone":"Europe/Moscow",
    "iso:country":"RU",
    "name:eng_x_preferred":[
        "Sosnovyy"
    ],
    "name:fin_x_preferred":[
        "Sosnovyi"
    ],
    "name:nor_x_preferred":[
        "Sosnovyj"
    ],
    "name:rus_x_preferred":[
        "\u0421\u043e\u0441\u043d\u043e\u0432\u044b\u0439"
    ],
    "name:und_x_variant":[
        "\u0421\u043e\u0441\u043d\u043e\u0432\u044b\u0439",
        "Sosnovyy"
    ],
    "wof:name":"Sosnovyy",
    "wof:placetype":"locality"
},
  "geometry": {"coordinates":[32.31924,66.0016],"type":"Point"}
}