{
  "type": "Feature",
  "properties": {
    "gn:admin1_code":"63",
    "gn:asciiname":"Kyubyume",
    "gn:country_code":"RU",
    "gn:dem":1031,
    "gn:feature_class":"P",
    "gn:feature_code":"PPL",
    "gn:name":"Kyubyume",
    "gn:population":0,
    "gn:timezone":"Asia/Magadan",
    "iso:country":"RU",
    "name:eng_x_preferred":[
        "Kyubyume"
    ],
    "name:nor_x_preferred":[
        "Kjubjume"
    ],
    "name:rus_x_preferred":[
        "\u041a\u044e\u0431\u044e\u043c\u0435"
    ],
    "name:und_x_variant":[
        "K\u00ebbyume",
        "Kyubyume"
    ],
    "wof:name":"Kyubyume",
    "wof:placetype":"locality"
},
  "geometry": {"coordinates":[140.60246000000001,63.4278],"type":"Point"}
}