{
  "type": "Feature",
  "properties": {
    "gn:admin1_code":"52.0",
    "gn:asciiname":"Budki",
    "gn:country_code":"RU",
    "gn:dem":107,
    "gn:feature_class":"P",
    "gn:feature_code":"PPL",
    "gn:name":"Budki",
    "gn:population":0,
    "gn:timezone":"Europe/Moscow",
    "iso:country":"RU",
    "name:deu_x_preferred":[
        "Budki"
    ],
    "name:fra_x_preferred":[
        "Budki"
    ],
    "name:nld_x_preferred":[
        "Budki"
    ],
    "name:pol_x_preferred":[
        "Budki"
    ],
    "name:rus_x_preferred":[
        "\u0411\u0443\u0434\u043a\u0438"
    ],
    "name:ukr_x_preferred":[
        "\u0411\u0443\u0434\u043a\u0456"
    ],
    "name:und_x_variant":[
        "\u0411\u0443\u0434\u043a\u0438"
    ],
    "wof:name":"Budki",
    "wof:placetype":"locality"
},
  "geometry": {"coordinates":[32.61096,58.44164],"type":"Point"}
}