{
  "type": "Feature",
  "properties": {
    "gn:admin1_code":"25",
    "gn:asciiname":"Kirilovskoye",
    "gn:country_code":"RU",
    "gn:dem":193,
    "gn:feature_class":"P",
    "gn:feature_code":"PPL",
    "gn:name":"Kirilovskoye",
    "gn:population":0,
    "gn:timezone":"Europe/Moscow",
    "iso:country":"RU",
    "name:nor_x_preferred":[
        "Kirilovskoje"
    ],
    "name:rus_x_preferred":[
        "\u041a\u0438\u0440\u0438\u043b\u043e\u0432\u0441\u043a\u043e\u0435"
    ],
    "wof:name":"Kirilovskoye",
    "wof:placetype":"locality"
},
  "geometry": {"coordinates":[36.42988,54.28092],"type":"Point"}
}