{
  "type": "Feature",
  "properties": {
    "gn:admin1_code":"8",
    "gn:asciiname":"Uzytamak",
    "gn:country_code":"RU",
    "gn:dem":198,
    "gn:feature_class":"P",
    "gn:feature_code":"PPL",
    "gn:name":"Uzytamak",
    "gn:population":0,
    "gn:timezone":"Asia/Yekaterinburg",
    "iso:country":"RU",
    "name:eng_x_preferred":[
        "Uzytamak"
    ],
    "name:nor_x_preferred":[
        "Uzytamak"
    ],
    "name:rus_x_preferred":[
        "\u0423\u0437\u044b\u0442\u0430\u043c\u0430\u043a"
    ],
    "name:und_x_variant":[
        "Alkino",
        "Uzytamak",
        "\u0423\u0437\u044b\u0442\u0430\u043c\u0430\u043a"
    ],
    "wof:name":"Uzytamak",
    "wof:placetype":"locality"
},
  "geometry": {"coordinates":[55.59106,54.65363000000001],"type":"Point"}
}