{
  "type": "Feature",
  "properties": {
    "gn:admin1_code":"25",
    "gn:asciiname":"Murzino",
    "gn:country_code":"RU",
    "gn:dem":187,
    "gn:feature_class":"P",
    "gn:feature_code":"PPL",
    "gn:name":"Murzino",
    "gn:population":0,
    "gn:timezone":"Europe/Moscow",
    "iso:country":"RU",
    "name:nor_x_preferred":[
        "Murzino"
    ],
    "name:rus_x_preferred":[
        "\u041c\u0443\u0440\u0437\u0438\u043d\u043e"
    ],
    "name:und_x_variant":[
        "Murzinc"
    ],
    "wof:name":"Murzino",
    "wof:placetype":"locality"
},
  "geometry": {"coordinates":[36.35441,54.96021999999999],"type":"Point"}
}