{
  "type": "Feature",
  "properties": {
    "gn:admin1_code":"6",
    "gn:asciiname":"Milovskiye Novinki",
    "gn:country_code":"RU",
    "gn:dem":170,
    "gn:feature_class":"P",
    "gn:feature_code":"PPL",
    "gn:name":"Milovskiye Novinki",
    "gn:population":0,
    "gn:timezone":"Europe/Moscow",
    "iso:country":"RU",
    "name:rus_x_preferred":[
        "\u041c\u0438\u043b\u043e\u0432\u0441\u043a\u0438\u0435 \u041d\u043e\u0432\u0438\u043d\u043a\u0438"
    ],
    "wof:name":"Milovskiye Novinki",
    "wof:placetype":"locality"
},
  "geometry": {"coordinates":[45.35,62.45],"type":"Point"}
}