{
  "type": "Feature",
  "properties": {
    "gn:admin1_code":"8",
    "gn:asciiname":"Yagunovo",
    "gn:country_code":"RU",
    "gn:dem":240,
    "gn:feature_class":"P",
    "gn:feature_code":"PPL",
    "gn:name":"Yagunovo",
    "gn:population":0,
    "gn:timezone":"Asia/Yekaterinburg",
    "iso:country":"RU",
    "name:rus_x_preferred":[
        "\u042f\u0433\u0443\u043d\u043e\u0432\u043e"
    ],
    "name:und_x_variant":[
        "Yagunova",
        "Yagunovo"
    ],
    "wof:name":"Yagunovo",
    "wof:placetype":"locality"
},
  "geometry": {"coordinates":[58.528,55.2637],"type":"Point"}
}