{
  "type": "Feature",
  "properties": {
    "gn:admin1_code":"70.0",
    "gn:asciiname":"Staro-Mar'yerskoye",
    "gn:country_code":"RU",
    "gn:dem":189,
    "gn:feature_class":"P",
    "gn:feature_code":"PPL",
    "gn:name":"Staro-Mar'yerskoye",
    "gn:population":0,
    "gn:timezone":"Europe/Moscow",
    "iso:country":"RU",
    "wof:name":"Staro-Mar'yerskoye",
    "wof:placetype":"locality"
},
  "geometry": {"coordinates":[42.88556,45.30444],"type":"Point"}
}