{
  "type": "Feature",
  "properties": {
    "gn:admin1_code":"6.0",
    "gn:asciiname":"Perkhina",
    "gn:country_code":"RU",
    "gn:dem":65,
    "gn:feature_class":"P",
    "gn:feature_code":"PPL",
    "gn:name":"Perkhina",
    "gn:population":0,
    "gn:timezone":"Europe/Moscow",
    "iso:country":"RU",
    "name:rus_x_preferred":[
        "\u041f\u0435\u0440\u0445\u0438\u043d\u0430"
    ],
    "wof:name":"Perkhina",
    "wof:placetype":"locality"
},
  "geometry": {"coordinates":[41.32376,62.73553],"type":"Point"}
}