{
  "type": "Feature",
  "properties": {
    "gn:admin1_code":"90",
    "gn:asciiname":"Krasnogorka",
    "gn:country_code":"RU",
    "gn:dem":229,
    "gn:feature_class":"P",
    "gn:feature_code":"PPL",
    "gn:name":"Krasnogorka",
    "gn:population":0,
    "gn:timezone":"Asia/Yekaterinburg",
    "iso:country":"RU",
    "name:eng_x_preferred":[
        "Krasnogorka"
    ],
    "name:nor_x_preferred":[
        "Krasnogorka"
    ],
    "name:rus_x_preferred":[
        "\u041a\u0440\u0430\u0441\u043d\u043e\u0433\u043e\u0440\u043a\u0430"
    ],
    "wof:name":"Krasnogorka",
    "wof:placetype":"locality"
},
  "geometry": {"coordinates":[56.17764,56.81392],"type":"Point"}
}