{
  "type": "Feature",
  "properties": {
    "gn:admin1_code":"51",
    "gn:asciiname":"Malyy Lom",
    "gn:country_code":"RU",
    "gn:dem":140,
    "gn:feature_class":"P",
    "gn:feature_code":"PPL",
    "gn:name":"Malyy Lom",
    "gn:population":0,
    "gn:timezone":"Europe/Moscow",
    "iso:country":"RU",
    "name:rus_x_preferred":[
        "\u041c\u0430\u043b\u044b\u0439 \u041b\u043e\u043c"
    ],
    "name:und_x_variant":[
        "\u041c\u0430\u043b\u044b\u0439 \u041b\u043e\u043c",
        "Malyye Lomy"
    ],
    "wof:name":"Malyy Lom",
    "wof:placetype":"locality"
},
  "geometry": {"coordinates":[46.9476,57.6927],"type":"Point"}
}