{
  "type": "Feature",
  "properties": {
    "gn:admin1_code":"60",
    "gn:asciiname":"Antonenki",
    "gn:country_code":"RU",
    "gn:dem":97,
    "gn:feature_class":"P",
    "gn:feature_code":"PPL",
    "gn:name":"Antonenki",
    "gn:population":0,
    "gn:timezone":"Europe/Moscow",
    "iso:country":"RU",
    "name:rus_x_preferred":[
        "\u0410\u043d\u0442\u043e\u043d\u0435\u043d\u043a\u0438"
    ],
    "wof:name":"Antonenki",
    "wof:placetype":"locality"
},
  "geometry": {"coordinates":[28.16129,56.85122],"type":"Point"}
}