{
  "type": "Feature",
  "properties": {
    "gn:admin1_code":"51",
    "gn:asciiname":"Maslovskoye",
    "gn:country_code":"RU",
    "gn:dem":86,
    "gn:feature_class":"P",
    "gn:feature_code":"PPL",
    "gn:name":"Maslovskoye",
    "gn:population":0,
    "gn:timezone":"Europe/Moscow",
    "iso:country":"RU",
    "name:rus_x_preferred":[
        "\u041c\u0430\u0441\u043b\u043e\u0432\u0441\u043a\u043e\u0435"
    ],
    "wof:name":"Maslovskoye",
    "wof:placetype":"locality"
},
  "geometry": {"coordinates":[42.371,55.5371],"type":"Point"}
}