{
  "type": "Feature",
  "properties": {
    "gn:admin1_code":"63",
    "gn:asciiname":"Syaganakh",
    "gn:cc2":"RU",
    "gn:country_code":"RU",
    "gn:dem":93,
    "gn:feature_class":"P",
    "gn:feature_code":"PPL",
    "gn:name":"Syaganakh",
    "gn:population":0,
    "gn:timezone":"Asia/Magadan",
    "iso:country":"RU",
    "name:und_x_variant":[
        "Stantsiya Syaganakh",
        "Syaganakh"
    ],
    "wof:name":"Syaganakh",
    "wof:placetype":"locality"
},
  "geometry": {"coordinates":[148.86667,68.84999999999999],"type":"Point"}
}