{
  "type": "Feature",
  "properties": {
    "gn:admin1_code":"42",
    "gn:asciiname":"Zhavoronok",
    "gn:country_code":"RU",
    "gn:dem":75,
    "gn:feature_class":"P",
    "gn:feature_code":"PPL",
    "gn:name":"Zhavoronok",
    "gn:population":0,
    "gn:timezone":"Europe/Moscow",
    "iso:country":"RU",
    "name:rus_x_preferred":[
        "\u0416\u0430\u0432\u043e\u0440\u043e\u043d\u043e\u043a"
    ],
    "name:und_x_variant":[
        "\u0416\u0430\u0432\u043e\u0440\u043e\u043d\u043e\u043a"
    ],
    "wof:name":"Zhavoronok",
    "wof:placetype":"locality"
},
  "geometry": {"coordinates":[28.6617,58.8921],"type":"Point"}
}