{
  "type": "Feature",
  "properties": {
    "gn:admin1_code":"69",
    "gn:asciiname":"Mazenki",
    "gn:country_code":"RU",
    "gn:dem":211,
    "gn:feature_class":"P",
    "gn:feature_code":"PPL",
    "gn:name":"Mazenki",
    "gn:population":0,
    "gn:timezone":"Europe/Moscow",
    "iso:country":"RU",
    "wof:name":"Mazenki",
    "wof:placetype":"locality"
},
  "geometry": {"coordinates":[33.53639,54.75056],"type":"Point"}
}