{
  "type": "Feature",
  "properties": {
    "gn:admin1_code":"81",
    "gn:asciiname":"Staryy Mostyak",
    "gn:country_code":"RU",
    "gn:dem":116,
    "gn:feature_class":"P",
    "gn:feature_code":"PPL",
    "gn:name":"Staryy Mostyak",
    "gn:population":0,
    "gn:timezone":"Europe/Ulyanovsk",
    "iso:country":"RU",
    "name:eng_x_preferred":[
        "Staryy Mostyak"
    ],
    "name:nor_x_preferred":[
        "Star.Mostjak"
    ],
    "name:rus_x_preferred":[
        "\u0421\u0442\u0430\u0440.\u041c\u043e\u0441\u0442\u044f\u043a"
    ],
    "name:rus_x_variant":[
        "\u0421\u0442\u0430\u0440\u044b\u0439 \u041c\u043e\u0441\u0442\u044f\u043a"
    ],
    "name:und_x_variant":[
        "Stary Mostyak"
    ],
    "wof:name":"Staryy Mostyak",
    "wof:placetype":"locality"
},
  "geometry": {"coordinates":[47.41323,52.69856],"type":"Point"}
}