{
  "type": "Feature",
  "properties": {
    "gn:admin1_code":"61.0",
    "gn:asciiname":"Balabonov",
    "gn:country_code":"RU",
    "gn:dem":128,
    "gn:feature_class":"P",
    "gn:feature_code":"PPL",
    "gn:name":"Balabonov",
    "gn:population":0,
    "gn:timezone":"Europe/Moscow",
    "iso:country":"RU",
    "name:nor_x_preferred":[
        "Balabonov"
    ],
    "name:rus_x_preferred":[
        "\u0411\u0430\u043b\u0430\u0431\u043e\u043d\u043e\u0432"
    ],
    "name:und_x_variant":[
        "Balabanov",
        "Balabonov"
    ],
    "wof:name":"Balabonov",
    "wof:placetype":"locality"
},
  "geometry": {"coordinates":[39.35861,47.7475],"type":"Point"}
}