{
  "type": "Feature",
  "properties": {
    "gn:admin1_code":"63",
    "gn:asciiname":"Toiogos",
    "gn:country_code":"RU",
    "gn:dem":115,
    "gn:feature_class":"P",
    "gn:feature_code":"PPL",
    "gn:name":"Toiogos",
    "gn:population":0,
    "gn:timezone":"Asia/Yakutsk",
    "iso:country":"RU",
    "name:eng_x_preferred":[
        "Toiogos"
    ],
    "name:nor_x_preferred":[
        "Tonogos"
    ],
    "name:rus_x_preferred":[
        "\u0422\u043e\u043d\u043e\u0433\u043e\u0441"
    ],
    "wof:name":"Toiogos",
    "wof:placetype":"locality"
},
  "geometry": {"coordinates":[131.92938000000001,62.97564000000001],"type":"Point"}
}