{
  "type": "Feature",
  "properties": {
    "gn:admin1_code":"33.0",
    "gn:asciiname":"Ryakhi",
    "gn:country_code":"RU",
    "gn:dem":130,
    "gn:feature_class":"P",
    "gn:feature_code":"PPL",
    "gn:name":"Ryakhi",
    "gn:population":0,
    "gn:timezone":"Europe/Kirov",
    "iso:country":"RU",
    "name:rus_x_preferred":[
        "\u0420\u044f\u0445\u0438"
    ],
    "wof:name":"Ryakhi",
    "wof:placetype":"locality"
},
  "geometry": {"coordinates":[50.70808,58.47665],"type":"Point"}
}