{
  "type": "Feature",
  "properties": {
    "gn:admin1_code":"52",
    "gn:asciiname":"Krasnaya Visherka",
    "gn:country_code":"RU",
    "gn:dem":47,
    "gn:feature_class":"P",
    "gn:feature_code":"PPL",
    "gn:name":"Krasnaya Visherka",
    "gn:population":0,
    "gn:timezone":"Europe/Moscow",
    "iso:country":"RU",
    "name:rus_x_preferred":[
        "\u041a\u0440\u0430\u0441\u043d\u0430\u044f \u0412\u0438\u0448\u0435\u0440\u043a\u0430"
    ],
    "wof:name":"Krasnaya Visherka",
    "wof:placetype":"locality"
},
  "geometry": {"coordinates":[32.05,58.78333000000001],"type":"Point"}
}