{
  "type": "Feature",
  "properties": {
    "gn:admin1_code":"47",
    "gn:asciiname":"L'yalovo",
    "gn:country_code":"RU",
    "gn:dem":212,
    "gn:feature_class":"P",
    "gn:feature_code":"PPL",
    "gn:name":"L\u2019yalovo",
    "gn:population":0,
    "gn:timezone":"Europe/Moscow",
    "iso:country":"RU",
    "name:eng_x_preferred":[
        "L'yalovo"
    ],
    "name:nor_x_preferred":[
        "Ljalovo"
    ],
    "name:rus_x_preferred":[
        "\u041b\u044c\u044f\u043b\u043e\u0432\u043e"
    ],
    "name:und_x_variant":[
        "\u041b\u044c\u044f\u043b\u043e\u0432\u043e",
        "L\u2019yalovo"
    ],
    "wof:name":"L'yalovo",
    "wof:placetype":"locality"
},
  "geometry": {"coordinates":[37.23333,56.05],"type":"Point"}
}