{
  "type": "Feature",
  "properties": {
    "gn:admin1_code":"45",
    "gn:asciiname":"Srednyaya Tursha",
    "gn:country_code":"RU",
    "gn:dem":117,
    "gn:feature_class":"P",
    "gn:feature_code":"PPL",
    "gn:name":"Srednyaya Tursha",
    "gn:population":0,
    "gn:timezone":"Europe/Moscow",
    "iso:country":"RU",
    "name:rus_x_preferred":[
        "\u0421\u0440\u0435\u0434\u043d\u044f\u044f \u0422\u0443\u0440\u0448\u0430"
    ],
    "name:und_x_variant":[
        "\u0421\u0440\u0435\u0434\u043d\u044f\u044f \u0422\u0443\u0440\u0448\u0430"
    ],
    "wof:name":"Srednyaya Tursha",
    "wof:placetype":"locality"
},
  "geometry": {"coordinates":[47.5787,56.87882],"type":"Point"}
}