{
  "type": "Feature",
  "properties": {
    "gn:admin1_code":"8",
    "gn:asciiname":"Lesnichestvo Nagayevskoye",
    "gn:country_code":"RU",
    "gn:dem":103,
    "gn:feature_class":"P",
    "gn:feature_code":"PPL",
    "gn:name":"Lesnichestvo Nagayevskoye",
    "gn:population":0,
    "gn:timezone":"Asia/Yekaterinburg",
    "iso:country":"RU",
    "name:rus_x_preferred":[
        "\u041b\u0435\u0441\u043d\u0438\u0447\u0435\u0441\u0442\u0432\u043e \u041d\u0430\u0433\u0430\u0435\u0432\u0441\u043a\u043e\u0435"
    ],
    "name:und_x_variant":[
        "\u041b\u0435\u0441\u043d\u0438\u0447\u0435\u0441\u0442\u0432\u043e \u041d\u0430\u0433\u0430\u0435\u0432\u0441\u043a\u043e\u0435"
    ],
    "wof:name":"Lesnichestvo Nagayevskoye",
    "wof:placetype":"locality"
},
  "geometry": {"coordinates":[56.0466,54.6227],"type":"Point"}
}