{
  "type": "Feature",
  "properties": {
    "gn:admin1_code":"80.0",
    "gn:asciiname":"Nizhnyaya Bogatyrka",
    "gn:country_code":"RU",
    "gn:dem":177,
    "gn:feature_class":"P",
    "gn:feature_code":"PPL",
    "gn:name":"Nizhnyaya Bogatyrka",
    "gn:population":0,
    "gn:timezone":"Europe/Samara",
    "iso:country":"RU",
    "name:rus_x_preferred":[
        "\u041d\u0438\u0436\u043d\u044f\u044f \u0411\u043e\u0433\u0430\u0442\u044b\u0440\u043a\u0430"
    ],
    "wof:name":"Nizhnyaya Bogatyrka",
    "wof:placetype":"locality"
},
  "geometry": {"coordinates":[52.6176,58.199],"type":"Point"}
}