{
  "type": "Feature",
  "properties": {
    "gn:admin1_code":"16",
    "gn:asciiname":"Yanshikhovo-Chelly",
    "gn:country_code":"RU",
    "gn:dem":150,
    "gn:feature_class":"P",
    "gn:feature_code":"PPL",
    "gn:name":"Yanshikhovo-Chelly",
    "gn:population":0,
    "gn:timezone":"Europe/Moscow",
    "iso:country":"RU",
    "name:rus_x_preferred":[
        "\u042f\u043d\u0448\u0438\u0445\u043e\u0432\u043e-\u0427\u0435\u043b\u043b\u044b"
    ],
    "name:und_x_variant":[
        "Bol\u2019shiye Chely",
        "Yanshikhovo",
        "Bol\u2019shiye Chelly",
        "Yanshikhovo-Chelly"
    ],
    "wof:name":"Yanshikhovo-Chelly",
    "wof:placetype":"locality"
},
  "geometry": {"coordinates":[47.29335,55.74576],"type":"Point"}
}