{
  "type": "Feature",
  "properties": {
    "gn:admin1_code":"61.0",
    "gn:asciiname":"Novozaryanskiy",
    "gn:country_code":"RU",
    "gn:dem":109,
    "gn:feature_class":"P",
    "gn:feature_code":"PPL",
    "gn:name":"Novozaryanskiy",
    "gn:population":0,
    "gn:timezone":"Europe/Moscow",
    "iso:country":"RU",
    "name:rus_x_preferred":[
        "\u041d\u043e\u0432\u043e\u0437\u0430\u0440\u044f\u043d\u0441\u043a\u0438\u0439"
    ],
    "name:und_x_variant":[
        "Sovkhoz Komsomolets",
        "Komsomolets",
        "Novozaryanskiy"
    ],
    "wof:name":"Novozaryanskiy",
    "wof:placetype":"locality"
},
  "geometry": {"coordinates":[40.43026,47.66747],"type":"Point"}
}