{
  "type": "Feature",
  "properties": {
    "gn:admin1_code":"23",
    "gn:asciiname":"Prigorodnoye",
    "gn:country_code":"RU",
    "gn:dem":0,
    "gn:feature_class":"P",
    "gn:feature_code":"PPL",
    "gn:name":"Prigorodnoye",
    "gn:population":0,
    "gn:timezone":"Europe/Kaliningrad",
    "iso:country":"RU",
    "name:rus_x_preferred":[
        "\u041f\u0440\u0438\u0433\u043e\u0440\u043e\u0434\u043d\u043e\u0435"
    ],
    "wof:name":"Prigorodnoye",
    "wof:placetype":"locality"
},
  "geometry": {"coordinates":[21.71608,55.02523000000001],"type":"Point"}
}