{
  "type": "Feature",
  "properties": {
    "gn:admin1_code":"90.0",
    "gn:asciiname":"Kachka",
    "gn:country_code":"RU",
    "gn:dem":103,
    "gn:feature_class":"P",
    "gn:feature_code":"PPL",
    "gn:name":"Kachka",
    "gn:population":0,
    "gn:timezone":"Asia/Yekaterinburg",
    "iso:country":"RU",
    "name:rus_x_preferred":[
        "\u041a\u0430\u0447\u043a\u0430"
    ],
    "name:und_x_variant":[
        "\u041a\u0430\u0447\u043a\u0430"
    ],
    "wof:name":"Kachka",
    "wof:placetype":"locality"
},
  "geometry": {"coordinates":[55.7674,57.9805],"type":"Point"}
}