{
  "type": "Feature",
  "properties": {
    "gn:admin1_code":"57",
    "gn:asciiname":"Vyrypayevo",
    "gn:country_code":"RU",
    "gn:dem":185,
    "gn:feature_class":"P",
    "gn:feature_code":"PPL",
    "gn:name":"Vyrypayevo",
    "gn:population":0,
    "gn:timezone":"Europe/Moscow",
    "iso:country":"RU",
    "name:eng_x_preferred":[
        "Vyrypayevo"
    ],
    "name:nor_x_preferred":[
        "Varypajevo"
    ],
    "name:rus_x_preferred":[
        "\u0412\u0430\u0440\u044b\u043f\u0430\u0435\u0432\u043e"
    ],
    "name:und_x_variant":[
        "Varypayevo",
        "Vyrypayevo"
    ],
    "wof:name":"Vyrypayevo",
    "wof:placetype":"locality"
},
  "geometry": {"coordinates":[45.20931,52.68695],"type":"Point"}
}