{
  "type": "Feature",
  "properties": {
    "gn:admin1_code":"69",
    "gn:asciiname":"Goryupino",
    "gn:country_code":"RU",
    "gn:dem":178,
    "gn:feature_class":"P",
    "gn:feature_code":"PPL",
    "gn:name":"Goryupino",
    "gn:population":0,
    "gn:timezone":"Europe/Moscow",
    "iso:country":"RU",
    "name:rus_x_preferred":[
        "\u0413\u043e\u0440\u044e\u043f\u0438\u043d\u043e"
    ],
    "name:und_x_variant":[
        "Garyupina",
        "Goryupino"
    ],
    "wof:name":"Goryupino",
    "wof:placetype":"locality"
},
  "geometry": {"coordinates":[32.38525,54.76272],"type":"Point"}
}