{
  "type": "Feature",
  "properties": {
    "gn:country":"RU",
    "gn:fcode":"PPL",
    "gn:pop":3044,
    "iso:country":"RU",
    "name:eng_x_preferred":[
        "Putyatino"
    ],
    "name:rus_x_preferred":[
        "\u041f\u0443\u0442\u044f\u043d\u0438\u043d\u043e"
    ],
    "name:rus_x_variant":[
        "\u041f\u0443\u0442\u044f\u0442\u0438\u043d\u043e"
    ],
    "name:unk_x_variant":[
        "\u041f\u0443\u0442\u044f\u0442\u0438\u043d\u043e"
    ],
    "qs:name":"Putyatino",
    "qs:photos_9r":0,
    "qs:photos_sr":0,
    "qs:pop_sr":"4",
    "wd:wordcount":317,
    "wof:name":"Putyatino",
    "wof:placetype":"locality",
    "wof:population":3044
},
  "geometry": {"coordinates":[41.1169,54.15998],"type":"Point"}
}