{
  "type": "Feature",
  "properties": {
    "gn:admin1_code":"8",
    "gn:asciiname":"Kuchukovo",
    "gn:country_code":"RU",
    "gn:dem":375,
    "gn:feature_class":"P",
    "gn:feature_code":"PPL",
    "gn:name":"Kuchukovo",
    "gn:population":0,
    "gn:timezone":"Asia/Yekaterinburg",
    "iso:country":"RU",
    "name:rus_x_preferred":[
        "\u041a\u0443\u0447\u0443\u043a\u043e\u0432\u043e"
    ],
    "name:und_x_variant":[
        "Kuchukova",
        "Kuchukovo",
        "\u041a\u0443\u0447\u0443\u043a\u043e\u0432\u043e"
    ],
    "wof:name":"Kuchukovo",
    "wof:placetype":"locality"
},
  "geometry": {"coordinates":[59.9124,54.8371],"type":"Point"}
}