{
  "type": "Feature",
  "properties": {
    "gn:admin1_code":"4",
    "gn:asciiname":"Tushkanikha",
    "gn:country_code":"RU",
    "gn:dem":366,
    "gn:feature_class":"P",
    "gn:feature_code":"PPL",
    "gn:name":"Tushkanikha",
    "gn:population":0,
    "gn:timezone":"Asia/Barnaul",
    "iso:country":"RU",
    "name:eng_x_preferred":[
        "Tushkanikha"
    ],
    "name:nor_x_preferred":[
        "Tusjkanikha"
    ],
    "name:rus_x_preferred":[
        "\u0422\u0443\u0448\u043a\u0430\u043d\u0438\u0445\u0430"
    ],
    "wof:name":"Tushkanikha",
    "wof:placetype":"locality"
},
  "geometry": {"coordinates":[81.71259999999999,51.26032],"type":"Point"}
}