{
  "type": "Feature",
  "properties": {
    "gn:admin1_code":"70",
    "gn:asciiname":"Novyy Mayak",
    "gn:country_code":"RU",
    "gn:dem":232,
    "gn:feature_class":"P",
    "gn:feature_code":"PPL",
    "gn:name":"Novyy Mayak",
    "gn:population":0,
    "gn:timezone":"Europe/Moscow",
    "iso:country":"RU",
    "name:rus_x_preferred":[
        "\u041d\u043e\u0432\u044b\u0439 \u041c\u0430\u044f\u043a"
    ],
    "wof:name":"Novyy Mayak",
    "wof:placetype":"locality"
},
  "geometry": {"coordinates":[43.18917,44.81917],"type":"Point"}
}