{
  "type": "Feature",
  "properties": {
    "gn:admin1_code":"49",
    "gn:asciiname":"Konevo",
    "gn:country_code":"RU",
    "gn:dem":1,
    "gn:feature_class":"P",
    "gn:feature_code":"PPL",
    "gn:name":"Kon\u00ebvo",
    "gn:population":0,
    "gn:timezone":"Europe/Moscow",
    "iso:country":"RU",
    "name:rus_x_preferred":[
        "\u041a\u043e\u043d\u0451\u0432\u043e"
    ],
    "name:und_x_variant":[
        "Kon\u00ebvo",
        "\u041a\u043e\u043d\u0451\u0432\u043e"
    ],
    "wof:name":"Konevo",
    "wof:placetype":"locality"
},
  "geometry": {"coordinates":[33.03333,69.05],"type":"Point"}
}