{
  "type": "Feature",
  "properties": {
    "gn:admin1_code":"69",
    "gn:asciiname":"Steshino",
    "gn:cc2":"RU",
    "gn:country_code":"RU",
    "gn:dem":200,
    "gn:feature_class":"P",
    "gn:feature_code":"PPL",
    "gn:name":"St\u00ebshino",
    "gn:population":0,
    "gn:timezone":"Europe/Moscow",
    "iso:country":"RU",
    "name:eng_x_preferred":[
        "St\u00ebshino"
    ],
    "name:nor_x_preferred":[
        "Stesjino"
    ],
    "name:rus_x_preferred":[
        "\u0421\u0442\u0435\u0448\u0438\u043d\u043e"
    ],
    "name:rus_x_variant":[
        "\u0421\u0442\u0451\u0448\u0438\u043d\u043e"
    ],
    "name:und_x_variant":[
        "Rokhlino",
        "St\u00ebshino",
        "\u0421\u0442\u0451\u0448\u0438\u043d\u043e"
    ],
    "wof:name":"Steshino",
    "wof:placetype":"locality"
},
  "geometry": {"coordinates":[33.56556,55.44361],"type":"Point"}
}