{
  "type": "Feature",
  "properties": {
    "gn:admin1_code":"20",
    "gn:asciiname":"Nadezhnyy",
    "gn:country_code":"RU",
    "gn:dem":763,
    "gn:feature_class":"P",
    "gn:feature_code":"PPL",
    "gn:name":"Nad\u00ebzhnyy",
    "gn:population":0,
    "gn:timezone":"Asia/Irkutsk",
    "iso:country":"RU",
    "name:eng_x_preferred":[
        "Nad\u00ebzhnyy"
    ],
    "name:nor_x_preferred":[
        "Nadezjnyj"
    ],
    "name:rus_x_preferred":[
        "\u041d\u0430\u0434\u0435\u0436\u043d\u044b\u0439"
    ],
    "name:rus_x_variant":[
        "\u041d\u0430\u0434\u0451\u0436\u043d\u044b\u0439"
    ],
    "wof:name":"Nadezhnyy",
    "wof:placetype":"locality"
},
  "geometry": {"coordinates":[111.66722,57.48611],"type":"Point"}
}