{
  "type": "Feature",
  "properties": {
    "gn:admin1_code":"25.0",
    "gn:asciiname":"Derevyagino",
    "gn:country_code":"RU",
    "gn:dem":230,
    "gn:feature_class":"P",
    "gn:feature_code":"PPL",
    "gn:name":"Derevyagino",
    "gn:population":0,
    "gn:timezone":"Europe/Moscow",
    "iso:country":"RU",
    "name:rus_x_preferred":[
        "\u0414\u0435\u0440\u0435\u0432\u044f\u0433\u0438\u043d\u043e"
    ],
    "name:und_x_variant":[
        "\u0414\u0435\u0440\u0435\u0432\u044f\u0433\u0438\u043d\u043e"
    ],
    "wof:name":"Derevyagino",
    "wof:placetype":"locality"
},
  "geometry": {"coordinates":[35.13864,54.24663],"type":"Point"}
}