{
  "type": "Feature",
  "properties": {
    "gn:admin1_code":"60.0",
    "gn:asciiname":"Dubrovy",
    "gn:country_code":"RU",
    "gn:dem":105,
    "gn:feature_class":"P",
    "gn:feature_code":"PPL",
    "gn:name":"Dubrovy",
    "gn:population":0,
    "gn:timezone":"Europe/Moscow",
    "iso:country":"RU",
    "name:eng_x_preferred":[
        "Dubrovy"
    ],
    "name:nor_x_preferred":[
        "Dubrovy"
    ],
    "name:rus_x_preferred":[
        "\u0414\u0443\u0431\u0440\u043e\u0432\u044b"
    ],
    "wof:name":"Dubrovy",
    "wof:placetype":"locality"
},
  "geometry": {"coordinates":[29.20366,56.97877],"type":"Point"}
}