{
  "type": "Feature",
  "properties": {
    "gn:admin1_code":"86",
    "gn:asciiname":"Malaya Vereyka",
    "gn:country_code":"RU",
    "gn:dem":177,
    "gn:feature_class":"P",
    "gn:feature_code":"PPL",
    "gn:name":"Malaya Vereyka",
    "gn:population":0,
    "gn:timezone":"Europe/Moscow",
    "iso:country":"RU",
    "name:eng_x_preferred":[
        "Malaya Vereyka"
    ],
    "name:nor_x_preferred":[
        "Malaja Verejka"
    ],
    "name:rus_x_preferred":[
        "\u041c\u0430\u043b\u0430\u044f \u0412\u0435\u0440\u0435\u0439\u043a\u0430"
    ],
    "name:und_x_variant":[
        "Vereyka",
        "\u041c\u0430\u043b\u0430\u044f \u0412\u0435\u0440\u0435\u0439\u043a\u0430",
        "Malaya Vereyka"
    ],
    "wof:name":"Malaya Vereyka",
    "wof:placetype":"locality"
},
  "geometry": {"coordinates":[38.7128,51.9678],"type":"Point"}
}