{
  "type": "Feature",
  "properties": {
    "gn:admin1_code":"4",
    "gn:asciiname":"Troitsk",
    "gn:country_code":"RU",
    "gn:dem":359,
    "gn:feature_class":"P",
    "gn:feature_code":"PPL",
    "gn:name":"Troitsk",
    "gn:population":0,
    "gn:timezone":"Asia/Barnaul",
    "iso:country":"RU",
    "name:eng_x_preferred":[
        "Troitskiy"
    ],
    "name:nor_x_preferred":[
        "Troitskij"
    ],
    "name:rus_x_preferred":[
        "\u0422\u0440\u043e\u0438\u0446\u043a\u0438\u0439"
    ],
    "name:rus_x_variant":[
        "\u0422\u0440\u043e\u0438\u0446\u043a"
    ],
    "name:und_x_variant":[
        "Troitsk"
    ],
    "wof:name":"Troitsk",
    "wof:placetype":"locality"
},
  "geometry": {"coordinates":[86.505,53.153],"type":"Point"}
}