{
  "type": "Feature",
  "properties": {
    "gn:admin1_code":"90",
    "gn:asciiname":"Zmeyevka",
    "gn:country_code":"RU",
    "gn:dem":137,
    "gn:feature_class":"P",
    "gn:feature_code":"PPL",
    "gn:name":"Zmey\u00ebvka",
    "gn:population":0,
    "gn:timezone":"Asia/Yekaterinburg",
    "iso:country":"RU",
    "name:eng_x_preferred":[
        "Zmey\u00ebvka"
    ],
    "name:nor_x_preferred":[
        "Zmejevka"
    ],
    "name:rus_x_preferred":[
        "\u0417\u043c\u0435\u0435\u0432\u043a\u0430"
    ],
    "wof:name":"Zmeyevka",
    "wof:placetype":"locality"
},
  "geometry": {"coordinates":[56.60626,57.27029],"type":"Point"}
}