{
  "type": "Feature",
  "properties": {
    "gn:admin1_code":"16.0",
    "gn:asciiname":"Anastasovo Vtoroye",
    "gn:country_code":"RU",
    "gn:dem":91,
    "gn:feature_class":"P",
    "gn:feature_code":"PPL",
    "gn:name":"Anastasovo Vtoroye",
    "gn:population":0,
    "gn:timezone":"Europe/Moscow",
    "iso:country":"RU",
    "name:nor_x_preferred":[
        "Anastasovo Vtoroje"
    ],
    "name:rus_x_preferred":[
        "\u0410\u043d\u0430\u0441\u0442\u0430\u0441\u043e\u0432\u043e \u0412\u0442\u043e\u0440\u043e\u0435"
    ],
    "wof:name":"Anastasovo Vtoroye",
    "wof:placetype":"locality"
},
  "geometry": {"coordinates":[46.24444,55.18639],"type":"Point"}
}