{
  "type": "Feature",
  "properties": {
    "gn:admin1_code":"60.0",
    "gn:asciiname":"Belaya",
    "gn:country_code":"RU",
    "gn:dem":63,
    "gn:feature_class":"P",
    "gn:feature_code":"PPL",
    "gn:name":"Belaya",
    "gn:population":0,
    "gn:timezone":"Europe/Moscow",
    "iso:country":"RU",
    "name:nor_x_preferred":[
        "Belaja"
    ],
    "name:rus_x_preferred":[
        "\u0411\u0435\u043b\u0430\u044f"
    ],
    "name:und_x_variant":[
        "Bely",
        "Belyy",
        "Belaya"
    ],
    "wof:name":"Belaya",
    "wof:placetype":"locality"
},
  "geometry": {"coordinates":[30.0095,57.6685],"type":"Point"}
}