{
  "type": "Feature",
  "properties": {
    "gn:admin1_code":"37",
    "gn:asciiname":"Bekrenevo",
    "gn:country_code":"RU",
    "gn:dem":152,
    "gn:feature_class":"P",
    "gn:feature_code":"PPL",
    "gn:name":"Bekrenevo",
    "gn:population":0,
    "gn:timezone":"Europe/Moscow",
    "iso:country":"RU",
    "name:rus_x_preferred":[
        "\u0411\u0435\u043a\u0440\u0435\u043d\u0435\u0432\u043e"
    ],
    "name:und_x_variant":[
        "\u0411\u0435\u043a\u0440\u0435\u043d\u0435\u0432\u043e"
    ],
    "wof:name":"Bekrenevo",
    "wof:placetype":"locality"
},
  "geometry": {"coordinates":[43.078,58.4509],"type":"Point"}
}