{
  "type": "Feature",
  "properties": {
    "gn:admin1_code":"69",
    "gn:asciiname":"Pnevka",
    "gn:country_code":"RU",
    "gn:dem":199,
    "gn:feature_class":"P",
    "gn:feature_code":"PPL",
    "gn:name":"Pn\u00ebvka",
    "gn:population":0,
    "gn:timezone":"Europe/Moscow",
    "iso:country":"RU",
    "name:rus_x_preferred":[
        "\u041f\u043d\u0451\u0432\u043a\u0430"
    ],
    "name:und_x_variant":[
        "Pn\u00ebvka"
    ],
    "wof:name":"Pnevka",
    "wof:placetype":"locality"
},
  "geometry": {"coordinates":[31.67757000000001,54.33082],"type":"Point"}
}