{
  "type": "Feature",
  "properties": {
    "gn:country":"RU",
    "gn:fcode":"PPL",
    "gn:pop":0,
    "iso:country":"RU",
    "name:rus_x_preferred":[
        "\u041d\u043e\u0432\u043e\u0441\u0451\u043b\u043a\u0438"
    ],
    "name:unk_x_variant":[
        "Novos\u00eblki"
    ],
    "qs:name":"Novoselki",
    "qs:name_adm0":"Russia",
    "qs:name_adm1":"Moscow Oblast",
    "qs:photos_9r":0,
    "qs:photos_sr":0,
    "qs:placetype":"Town",
    "qs:pop_sr":"0",
    "wd:wordcount":2108,
    "wof:name":"Novoselki",
    "wof:placetype":"locality",
    "wof:population":0
},
  "geometry": {"coordinates":[37.60462,55.33843],"type":"Point"}
}