{
  "type": "Feature",
  "properties": {
    "gn:country":"RU",
    "gn:fcode":"PPL",
    "gn:population":5097,
    "iso:country":"RU",
    "name:eng_x_preferred":[
        "Novobataysk"
    ],
    "name:nor_x_preferred":[
        "Novobatajsk"
    ],
    "name:rus_x_preferred":[
        "\u041d\u043e\u0432\u043e\u0431\u0430\u0442\u0430\u0439\u0441\u043a"
    ],
    "qs:name":"Novobataysk",
    "qs:name_adm0":"Russia",
    "qs:name_adm1":"Rostov Oblast",
    "qs:photos_9r":0,
    "qs:photos_sr":0,
    "qs:placetype":"Town",
    "qs:pop_sr":"5",
    "wof:name":"Novobataysk",
    "wof:placetype":"locality",
    "wof:population":5097
},
  "geometry": {"coordinates":[39.78194,46.89806],"type":"Point"}
}