{
  "type": "Feature",
  "properties": {
    "gn:admin1_code":"9",
    "gn:asciiname":"Kalashnikov",
    "gn:cc2":"RU",
    "gn:country_code":"RU",
    "gn:dem":205,
    "gn:feature_class":"P",
    "gn:feature_code":"PPL",
    "gn:name":"Kalashnikov",
    "gn:population":0,
    "gn:timezone":"Europe/Moscow",
    "iso:country":"RU",
    "name:rus_x_preferred":[
        "\u041a\u0430\u043b\u0430\u0448\u043d\u0438\u043a\u043e\u0432"
    ],
    "name:und_x_variant":[
        "Kalinichenko",
        "Kalashnikov",
        "\u041a\u0430\u043b\u0430\u0448\u043d\u0438\u043a\u043e\u0432"
    ],
    "wof:name":"Kalashnikov",
    "wof:placetype":"locality"
},
  "geometry": {"coordinates":[38.98333,50.16667],"type":"Point"}
}