{
  "type": "Feature",
  "properties": {
    "gn:admin1_code":"9",
    "gn:asciiname":"Kalashnikov",
    "gn:cc2":"RU",
    "gn:country_code":"RU",
    "gn:dem":205,
    "gn:feature_class":"P",
    "gn:feature_code":"PPL",
    "gn:name":"Kalashnikov",
    "gn:population":0,
    "gn:timezone":"Europe/Moscow",
    "iso:country":"RU",
    "name:ara_x_preferred":[
        "\u0643\u0644\u0627\u0634\u0646\u0643\u0648\u0641"
    ],
    "name:deu_x_preferred":[
        "Kalaschnikow"
    ],
    "name:eus_x_preferred":[
        "Kalaxnikov"
    ],
    "name:fra_x_preferred":[
        "Kalachnikov"
    ],
    "name:heb_x_preferred":[
        "\u05e7\u05dc\u05e9\u05e0\u05d9\u05e7\u05d5\u05d1"
    ],
    "name:hun_x_preferred":[
        "Kalasnyikov"
    ],
    "name:ita_x_preferred":[
        "Kala\u0161nikov"
    ],
    "name:jpn_x_preferred":[
        "\u30ab\u30e9\u30b7\u30cb\u30b3\u30d5"
    ],
    "name:kor_x_preferred":[
        "\uce7c\ub77c\uc2dc\ub2c8\ucf54\ud504"
    ],
    "name:lav_x_preferred":[
        "Kala\u0161\u0146ikovs"
    ],
    "name:lit_x_preferred":[
        "Kala\u0161nikovas"
    ],
    "name:nld_x_preferred":[
        "Kalasjnikov"
    ],
    "name:por_x_preferred":[
        "Kalashnikov"
    ],
    "name:ron_x_preferred":[
        "Kala\u0219nikov"
    ],
    "name:rus_x_preferred":[
        "\u041a\u0430\u043b\u0430\u0448\u043d\u0438\u043a\u043e\u0432"
    ],
    "name:slk_x_preferred":[
        "Kala\u0161nikov"
    ],
    "name:slv_x_preferred":[
        "Kala\u0161nikov"
    ],
    "name:spa_x_preferred":[
        "Kalashnikov"
    ],
    "name:srp_x_preferred":[
        "\u041a\u0430\u043b\u0430\u0448\u045a\u0438\u043a\u043e\u0432"
    ],
    "name:swe_x_preferred":[
        "Kalasjnikov"
    ],
    "name:tat_x_preferred":[
        "\u041a\u0430\u043b\u0430\u0448\u043d\u0438\u043a\u043e\u0432"
    ],
    "name:tur_x_preferred":[
        "Kala\u015fnikov"
    ],
    "name:ukr_x_preferred":[
        "\u041a\u0430\u043b\u0430\u0448\u043d\u0438\u043a\u043e\u0432"
    ],
    "name:und_x_variant":[
        "Kalinichenko"
    ],
    "name:zho_x_preferred":[
        "\u5361\u62c9\u4ec0\u5c3c\u79d1\u592b"
    ],
    "wof:name":"Kalashnikov",
    "wof:placetype":"locality"
},
  "geometry": {"coordinates":[38.98333,50.16667],"type":"Point"}
}