{
  "type": "Feature",
  "properties": {
    "gn:admin1_code":"57",
    "gn:asciiname":"Staraya Selya",
    "gn:country_code":"RU",
    "gn:dem":236,
    "gn:feature_class":"P",
    "gn:feature_code":"PPL",
    "gn:name":"Staraya Selya",
    "gn:population":0,
    "gn:timezone":"Europe/Moscow",
    "iso:country":"RU",
    "name:rus_x_preferred":[
        "\u0421\u0442\u0430\u0440\u0430\u044f \u0421\u0435\u043b\u044f"
    ],
    "name:und_x_variant":[
        "Stataraya Selya",
        "Staraya Selya",
        "\u0421\u0442\u0430\u0440\u0430\u044f \u0421\u0435\u043b\u044f"
    ],
    "wof:name":"Staraya Selya",
    "wof:placetype":"locality"
},
  "geometry": {"coordinates":[46.28701,53.69086],"type":"Point"}
}