{
  "type": "Feature",
  "properties": {
    "gn:admin1_code":"17",
    "gn:asciiname":"Mekegi",
    "gn:country_code":"RU",
    "gn:dem":1347,
    "gn:feature_class":"P",
    "gn:feature_code":"PPL",
    "gn:name":"Mekegi",
    "gn:population":0,
    "gn:timezone":"Europe/Moscow",
    "iso:country":"RU",
    "name:eng_x_preferred":[
        "Mekegi"
    ],
    "name:nor_x_preferred":[
        "Mekegi"
    ],
    "name:rus_x_preferred":[
        "\u041c\u0435\u043a\u0435\u0433\u0438"
    ],
    "name:und_x_variant":[
        "Mekege",
        "\u041c\u0435\u043a\u0435\u0433\u0438",
        "Mekegi"
    ],
    "wof:name":"Mekegi",
    "wof:placetype":"locality"
},
  "geometry": {"coordinates":[47.46038,42.39738],"type":"Point"}
}