{
  "type": "Feature",
  "properties": {
    "gn:admin1_code":"12",
    "gn:asciiname":"Tsa-Vedeno",
    "gn:country_code":"RU",
    "gn:dem":597,
    "gn:feature_class":"P",
    "gn:feature_code":"PPL",
    "gn:name":"Tsa-Vedeno",
    "gn:population":0,
    "gn:timezone":"Europe/Moscow",
    "iso:country":"RU",
    "name:che_x_preferred":[
        "Maha\u00e7-Aul"
    ],
    "name:che_x_variant":[
        "Ca-Vedeno",
        "\u0426\u0406\u0435\u043d \u0412\u0435\u0434\u0430\u043d\u0430",
        "\u041c\u0430\u0445\u0430\u0447-\u0410\u0443\u043b"
    ],
    "name:eng_x_preferred":[
        "Tsa-Vedeno"
    ],
    "name:nor_x_preferred":[
        "Tsa-Vedeno"
    ],
    "name:rus_x_preferred":[
        "\u0426\u0430-\u0412\u0435\u0434\u0435\u043d\u043e"
    ],
    "name:und_x_variant":[
        "Cen Vedana",
        "Verkhneye Tsa-Vedeno",
        "Makhach-Aul",
        "Tsa-Vedeno"
    ],
    "wof:name":"Tsa-Vedeno",
    "wof:placetype":"locality"
},
  "geometry": {"coordinates":[46.05692,43.01877],"type":"Point"}
}