{
  "type": "Feature",
  "properties": {
    "gn:admin1_code":"77",
    "gn:asciiname":"Rachevo",
    "gn:country_code":"RU",
    "gn:dem":168,
    "gn:feature_class":"P",
    "gn:feature_code":"PPL",
    "gn:name":"Rachevo",
    "gn:population":0,
    "gn:timezone":"Europe/Moscow",
    "iso:country":"RU",
    "name:eng_x_preferred":[
        "Rachevo"
    ],
    "name:nor_x_preferred":[
        "Ratsjevo"
    ],
    "name:rus_x_preferred":[
        "\u0420\u0430\u0447\u0435\u0432\u043e"
    ],
    "name:und_x_variant":[
        "\u0420\u0430\u0447\u0435\u0432\u043e",
        "Rachevo"
    ],
    "wof:name":"Rachevo",
    "wof:placetype":"locality"
},
  "geometry": {"coordinates":[37.44838,58.10845],"type":"Point"}
}