{
  "type": "Feature",
  "properties": {
    "gn:admin1_code":"71",
    "gn:asciiname":"Vologina",
    "gn:country_code":"RU",
    "gn:dem":133,
    "gn:feature_class":"P",
    "gn:feature_code":"PPL",
    "gn:name":"Vologina",
    "gn:population":0,
    "gn:timezone":"Asia/Yekaterinburg",
    "iso:country":"RU",
    "name:eng_x_preferred":[
        "Vologina"
    ],
    "name:nor_x_preferred":[
        "Vologina"
    ],
    "name:rus_x_preferred":[
        "\u0412\u043e\u043b\u043e\u0433\u0438\u043d\u0430"
    ],
    "name:und_x_variant":[
        "Vologino",
        "Vologina"
    ],
    "wof:name":"Vologina",
    "wof:placetype":"locality"
},
  "geometry": {"coordinates":[60.30868,58.73931],"type":"Point"}
}