{
  "type": "Feature",
  "properties": {
    "gn:admin1_code":"90",
    "gn:asciiname":"Berdykayevo",
    "gn:country_code":"RU",
    "gn:dem":191,
    "gn:feature_class":"P",
    "gn:feature_code":"PPL",
    "gn:name":"Berdykayevo",
    "gn:population":0,
    "gn:timezone":"Asia/Yekaterinburg",
    "iso:country":"RU",
    "name:rus_x_preferred":[
        "\u0411\u0435\u0440\u0434\u044b\u043a\u0430\u0435\u0432\u043e"
    ],
    "wof:name":"Berdykayevo",
    "wof:placetype":"locality"
},
  "geometry": {"coordinates":[57.7814,57.0395],"type":"Point"}
}