{
  "type": "Feature",
  "properties": {
    "gn:admin1_code":"80.0",
    "gn:asciiname":"Berezovka",
    "gn:country_code":"RU",
    "gn:dem":216,
    "gn:feature_class":"P",
    "gn:feature_code":"PPL",
    "gn:name":"Ber\u00ebzovka",
    "gn:population":0,
    "gn:timezone":"Europe/Samara",
    "iso:country":"RU",
    "name:ceb_x_preferred":[
        "Berezovka"
    ],
    "name:lav_x_preferred":[
        "Berezovka"
    ],
    "name:lit_x_preferred":[
        "Berezovka"
    ],
    "name:nor_x_preferred":[
        "Berjozovka"
    ],
    "name:rus_x_preferred":[
        "\u0411\u0435\u0440\u0451\u0437\u043e\u0432\u043a\u0430"
    ],
    "name:swe_x_preferred":[
        "Berezovka"
    ],
    "name:und_x_variant":[
        "Numyrez\u2019",
        "Ber\u00ebzovka"
    ],
    "wof:name":"Berezovka",
    "wof:placetype":"locality"
},
  "geometry": {"coordinates":[53.7825,57.7164],"type":"Point"}
}