{
  "type": "Feature",
  "properties": {
    "gn:admin1_code":"80.0",
    "gn:asciiname":"Moseny",
    "gn:country_code":"RU",
    "gn:dem":246,
    "gn:feature_class":"P",
    "gn:feature_code":"PPL",
    "gn:name":"Moseny",
    "gn:population":0,
    "gn:timezone":"Europe/Samara",
    "iso:country":"RU",
    "name:rus_x_preferred":[
        "\u041c\u043e\u0441\u0435\u043d\u044b"
    ],
    "wof:name":"Moseny",
    "wof:placetype":"locality"
},
  "geometry": {"coordinates":[53.2108,58.2414],"type":"Point"}
}