{
  "type": "Feature",
  "properties": {
    "gn:admin1_code":"90",
    "gn:asciiname":"Klimikha",
    "gn:country_code":"RU",
    "gn:dem":189,
    "gn:feature_class":"P",
    "gn:feature_code":"PPL",
    "gn:name":"Klimikha",
    "gn:population":0,
    "gn:timezone":"Asia/Yekaterinburg",
    "iso:country":"RU",
    "name:rus_x_preferred":[
        "\u041a\u043b\u0438\u043c\u0438\u0445\u0430"
    ],
    "name:und_x_variant":[
        "\u041a\u043b\u0438\u043c\u0438\u0445\u0430"
    ],
    "wof:name":"Klimikha",
    "wof:placetype":"locality"
},
  "geometry": {"coordinates":[56.74864,57.16231],"type":"Point"}
}