{
  "type": "Feature",
  "properties": {
    "gn:admin1_code":"6",
    "gn:asciiname":"Rusoma",
    "gn:country_code":"RU",
    "gn:dem":37,
    "gn:feature_class":"P",
    "gn:feature_code":"PPL",
    "gn:name":"Rusoma",
    "gn:population":0,
    "gn:timezone":"Europe/Moscow",
    "iso:country":"RU",
    "name:eng_x_preferred":[
        "Rusoma"
    ],
    "name:nor_x_preferred":[
        "Rusoma"
    ],
    "name:rus_x_preferred":[
        "\u0420\u0443\u0441\u043e\u043c\u0430"
    ],
    "wof:name":"Rusoma",
    "wof:placetype":"locality"
},
  "geometry": {"coordinates":[45.8826,64.7313],"type":"Point"}
}