{
  "type": "Feature",
  "properties": {
    "gn:admin1_code":"8.0",
    "gn:asciiname":"Abulyaisovo",
    "gn:country_code":"RU",
    "gn:dem":223,
    "gn:feature_class":"P",
    "gn:feature_code":"PPL",
    "gn:name":"Abulyaisovo",
    "gn:population":0,
    "gn:timezone":"Asia/Yekaterinburg",
    "iso:country":"RU",
    "name:eng_x_preferred":[
        "Abulyaisovo"
    ],
    "name:nor_x_preferred":[
        "Abuljaisovo"
    ],
    "name:rus_x_preferred":[
        "\u0410\u0431\u0443\u043b\u044f\u0438\u0441\u043e\u0432\u043e"
    ],
    "name:und_x_variant":[
        "Bulyasovo",
        "Ablyaisovo",
        "\u0410\u0431\u0443\u043b\u044f\u0438\u0441\u043e\u0432\u043e",
        "Abulyaisovo"
    ],
    "wof:name":"Abulyaisovo",
    "wof:placetype":"locality"
},
  "geometry": {"coordinates":[56.89193,51.75100000000001],"type":"Point"}
}