{
  "type": "Feature",
  "properties": {
    "gn:admin1_code":"8.0",
    "gn:asciiname":"Abulyaisovo",
    "gn:country_code":"RU",
    "gn:dem":223,
    "gn:feature_class":"P",
    "gn:feature_code":"PPL",
    "gn:name":"Abulyaisovo",
    "gn:population":0,
    "gn:timezone":"Asia/Yekaterinburg",
    "iso:country":"RU",
    "name:bak_x_preferred":[
        "\u04d8\u0431\u04af\u043b\u04d9\u0439\u0435\u0441"
    ],
    "name:che_x_preferred":[
        "\u0410\u0431\u0443\u043b\u044f\u0438\u0441\u043e\u0432\u043e"
    ],
    "name:eng_x_preferred":[
        "Abulyaisovo"
    ],
    "name:hye_x_preferred":[
        "\u0531\u0562\u0578\u0582\u056c\u0575\u0561\u056b\u057d\u0578\u057e\u0578"
    ],
    "name:kaz_x_preferred":[
        "\u04d8\u0431\u0443\u043b\u044f\u0439\u044b\u0441"
    ],
    "name:kir_x_preferred":[
        "\u0410\u0431\u0443\u043b\u044f\u0439\u044b\u0441"
    ],
    "name:nor_x_preferred":[
        "Abuljaisovo"
    ],
    "name:rus_x_preferred":[
        "\u0410\u0431\u0443\u043b\u044f\u0438\u0441\u043e\u0432\u043e"
    ],
    "name:tat_x_preferred":[
        "\u04d8\u0431\u04af\u043b\u04d9\u0438\u0441"
    ],
    "name:ukr_x_preferred":[
        "\u0410\u0431\u0443\u043b\u044f\u0457\u0441\u043e\u0432\u043e"
    ],
    "name:und_x_variant":[
        "Bulyasovo",
        "Ablyaisovo"
    ],
    "wof:name":"Abulyaisovo",
    "wof:placetype":"locality"
},
  "geometry": {"coordinates":[56.89193,51.75100000000001],"type":"Point"}
}