{
  "type": "Feature",
  "properties": {
    "gn:admin1_code":"44",
    "gn:asciiname":"Temp",
    "gn:cc2":"RU",
    "gn:country_code":"RU",
    "gn:dem":7,
    "gn:feature_class":"P",
    "gn:feature_code":"PPL",
    "gn:name":"Temp",
    "gn:population":0,
    "gn:timezone":"Asia/Magadan",
    "iso:country":"RU",
    "name:dan_x_preferred":[
        "Temp"
    ],
    "name:fra_x_preferred":[
        "Temp"
    ],
    "name:kaz_x_preferred":[
        "\u0422\u0435\u043c\u043f"
    ],
    "name:rus_x_preferred":[
        "\u0422\u0435\u043c\u043f"
    ],
    "name:und_x_variant":[
        "Tem",
        "Temp"
    ],
    "wof:name":"Temp",
    "wof:placetype":"locality"
},
  "geometry": {"coordinates":[149.80000000000001,59.75],"type":"Point"}
}