{
  "type": "Feature",
  "properties": {
    "gn:admin1_code":"42",
    "gn:asciiname":"Lyashozero",
    "gn:country_code":"RU",
    "gn:dem":101,
    "gn:feature_class":"P",
    "gn:feature_code":"PPL",
    "gn:name":"Lyashozero",
    "gn:population":0,
    "gn:timezone":"Europe/Moscow",
    "iso:country":"RU",
    "name:rus_x_preferred":[
        "\u041b\u044f\u0448\u043e\u0437\u0435\u0440\u043e"
    ],
    "wof:name":"Lyashozero",
    "wof:placetype":"locality"
},
  "geometry": {"coordinates":[33.90357,60.44974000000001],"type":"Point"}
}