{
  "type": "Feature",
  "properties": {
    "gn:admin1_code":"6.0",
    "gn:asciiname":"Borisovskaya",
    "gn:country_code":"RU",
    "gn:dem":30,
    "gn:feature_class":"P",
    "gn:feature_code":"PPL",
    "gn:name":"Borisovskaya",
    "gn:population":0,
    "gn:timezone":"Europe/Moscow",
    "iso:country":"RU",
    "name:rus_x_preferred":[
        "\u0411\u043e\u0440\u0438\u0441\u043e\u0432\u0441\u043a\u0430\u044f"
    ],
    "wof:name":"Borisovskaya",
    "wof:placetype":"locality"
},
  "geometry": {"coordinates":[45.0947,62.0502],"type":"Point"}
}