{
  "type": "Feature",
  "properties": {
    "gn:admin1_code":"53",
    "gn:asciiname":"Karpysak",
    "gn:country_code":"RU",
    "gn:dem":177,
    "gn:feature_class":"P",
    "gn:feature_code":"PPL",
    "gn:name":"Karpysak",
    "gn:population":0,
    "gn:timezone":"Asia/Novosibirsk",
    "iso:country":"RU",
    "name:eng_x_preferred":[
        "Karpysak"
    ],
    "name:nor_x_preferred":[
        "Karnysak"
    ],
    "name:rus_x_preferred":[
        "\u041a\u0430\u0440\u043d\u044b\u0441\u0430\u043a"
    ],
    "name:rus_x_variant":[
        "\u041a\u0430\u0440\u043f\u044b\u0441\u0430\u043a"
    ],
    "name:und_x_variant":[
        "Korpysak",
        "Karpysak",
        "\u041a\u0430\u0440\u043f\u044b\u0441\u0430\u043a"
    ],
    "wof:name":"Karpysak",
    "wof:placetype":"locality"
},
  "geometry": {"coordinates":[83.7069,55.0378],"type":"Point"}
}