{
  "type": "Feature",
  "properties": {
    "gn:admin1_code":"77",
    "gn:asciiname":"Chetverty",
    "gn:country_code":"RU",
    "gn:dem":181,
    "gn:feature_class":"P",
    "gn:feature_code":"PPL",
    "gn:name":"Chetverty",
    "gn:population":0,
    "gn:timezone":"Europe/Moscow",
    "iso:country":"RU",
    "name:rus_x_preferred":[
        "\u0427\u0435\u0442\u0432\u0435\u0440\u0442\u044b"
    ],
    "name:und_x_variant":[
        "\u0427\u0435\u0442\u0432\u0435\u0440\u0442\u044b"
    ],
    "wof:name":"Chetverty",
    "wof:placetype":"locality"
},
  "geometry": {"coordinates":[32.71361,56.04861],"type":"Point"}
}