{
  "type": "Feature",
  "properties": {
    "gn:admin1_code":"63",
    "gn:asciiname":"Vershina Aldana",
    "gn:cc2":"RU",
    "gn:country_code":"RU",
    "gn:dem":1443,
    "gn:feature_class":"P",
    "gn:feature_code":"PPL",
    "gn:name":"Vershina Aldana",
    "gn:population":0,
    "gn:timezone":"Asia/Yakutsk",
    "iso:country":"RU",
    "name:und_x_variant":[
        "Zimov\u2019ye Vershina Alcana",
        "Vershina Aldana"
    ],
    "wof:name":"Vershina Aldana",
    "wof:placetype":"locality"
},
  "geometry": {"coordinates":[123.43333,56.58333],"type":"Point"}
}