{
  "type": "Feature",
  "properties": {
    "gn:admin1_code":"30",
    "gn:asciiname":"Lesopil'noye",
    "gn:country_code":"RU",
    "gn:dem":57,
    "gn:feature_class":"P",
    "gn:feature_code":"PPL",
    "gn:name":"Lesopil\u2019noye",
    "gn:population":0,
    "gn:timezone":"Asia/Vladivostok",
    "iso:country":"RU",
    "name:eng_x_preferred":[
        "Lesopil'noye"
    ],
    "name:rus_x_preferred":[
        "\u041b\u0435\u0441\u043e\u043f\u0438\u043b\u044c\u043d\u043e\u0435"
    ],
    "name:und_x_variant":[
        "Lesopyl\u2019nyy",
        "Lesopil\u2019nyy",
        "Lesopilny",
        "Lesopil\u2019noye"
    ],
    "wof:name":"Lesopil'noye",
    "wof:placetype":"locality"
},
  "geometry": {"coordinates":[134.34173000000001,46.7417],"type":"Point"}
}