{
  "type": "Feature",
  "properties": {
    "gn:admin1_code":"77",
    "gn:asciiname":"Volgoverkhov'ye",
    "gn:country_code":"RU",
    "gn:dem":231,
    "gn:elevation":"50.0",
    "gn:feature_class":"P",
    "gn:feature_code":"PPL",
    "gn:name":"Volgoverkhov\u2019ye",
    "gn:population":8,
    "gn:timezone":"Europe/Moscow",
    "iso:country":"RU",
    "name:eng_x_preferred":[
        "Volgoverkhov'ye"
    ],
    "name:nor_x_preferred":[
        "Volgoverkhovje"
    ],
    "name:rus_x_preferred":[
        "\u0412\u043e\u043b\u0433\u043e\u0432\u0435\u0440\u0445\u043e\u0432\u044c\u0435"
    ],
    "name:und_x_variant":[
        "Volgoverkhovo",
        "Volgino-Verkhov\u2019ye",
        "Volgoverkhov\u2019ye"
    ],
    "wof:name":"Volgoverkhov'ye",
    "wof:placetype":"locality",
    "wof:population":8
},
  "geometry": {"coordinates":[32.4718,57.25376],"type":"Point"}
}