{
  "type": "Feature",
  "properties": {
    "gn:admin1_code":"85",
    "gn:asciiname":"Tavlash",
    "gn:country_code":"RU",
    "gn:dem":114,
    "gn:feature_class":"P",
    "gn:feature_code":"PPL",
    "gn:name":"Tavlash",
    "gn:population":0,
    "gn:timezone":"Europe/Moscow",
    "iso:country":"RU",
    "name:rus_x_preferred":[
        "\u0422\u0430\u0432\u043b\u0430\u0448"
    ],
    "wof:name":"Tavlash",
    "wof:placetype":"locality"
},
  "geometry": {"coordinates":[39.30272,59.80216],"type":"Point"}
}