{
  "type": "Feature",
  "properties": {
    "gn:admin1_code":"65.0",
    "gn:asciiname":"Chekalino",
    "gn:cc2":"RU",
    "gn:country_code":"RU",
    "gn:dem":85,
    "gn:feature_class":"P",
    "gn:feature_code":"PPL",
    "gn:name":"Chekalino",
    "gn:population":0,
    "gn:timezone":"Europe/Samara",
    "iso:country":"RU",
    "name:eng_x_preferred":[
        "Chekalino"
    ],
    "name:nor_x_preferred":[
        "Tsjekalino"
    ],
    "name:rus_x_preferred":[
        "\u0427\u0435\u043a\u0430\u043b\u0438\u043d\u043e"
    ],
    "name:und_x_variant":[
        "Chekalano"
    ],
    "wof:name":"Chekalino",
    "wof:placetype":"locality"
},
  "geometry": {"coordinates":[48.44861,53.31833],"type":"Point"}
}