{
  "type": "Feature",
  "properties": {
    "gn:admin1_code":"29",
    "gn:asciiname":"Tenguly",
    "gn:country_code":"RU",
    "gn:dem":129,
    "gn:feature_class":"P",
    "gn:feature_code":"PPL",
    "gn:name":"Tenguly",
    "gn:population":0,
    "gn:timezone":"Asia/Novokuznetsk",
    "iso:country":"RU",
    "name:eng_x_preferred":[
        "Tenguly"
    ],
    "name:nor_x_preferred":[
        "Tenguly"
    ],
    "name:rus_x_preferred":[
        "\u0422\u0435\u043d\u0433\u0443\u043b\u044b"
    ],
    "name:und_x_variant":[
        "Tengul\u2019skoye"
    ],
    "wof:name":"Tenguly",
    "wof:placetype":"locality"
},
  "geometry": {"coordinates":[87.55503,56.38177],"type":"Point"}
}