{
  "type": "Feature",
  "properties": {
    "gn:admin1_code":"62",
    "gn:asciiname":"Tarkhan'",
    "gn:country_code":"RU",
    "gn:dem":100,
    "gn:feature_class":"P",
    "gn:feature_code":"PPL",
    "gn:name":"Tarkhan\u2019",
    "gn:population":0,
    "gn:timezone":"Europe/Moscow",
    "iso:country":"RU",
    "name:rus_x_preferred":[
        "\u0422\u0430\u0440\u0445\u0430\u043d\u044c"
    ],
    "name:und_x_variant":[
        "Tarkhan\u2019"
    ],
    "wof:name":"Tarkhan'",
    "wof:placetype":"locality"
},
  "geometry": {"coordinates":[42.0093,54.1798],"type":"Point"}
}