{
  "type": "Feature",
  "properties": {
    "gn:admin1_code":"17",
    "gn:asciiname":"Ikra",
    "gn:country_code":"RU",
    "gn:dem":981,
    "gn:feature_class":"P",
    "gn:feature_code":"PPL",
    "gn:name":"Ikra",
    "gn:population":0,
    "gn:timezone":"Europe/Moscow",
    "iso:country":"RU",
    "name:eng_x_preferred":[
        "Ikra"
    ],
    "name:nor_x_preferred":[
        "Ikra"
    ],
    "name:rus_x_preferred":[
        "\u0418\u043a\u0440\u0430"
    ],
    "wof:name":"Ikra",
    "wof:placetype":"locality"
},
  "geometry": {"coordinates":[48.01262,41.56194],"type":"Point"}
}