{
  "type": "Feature",
  "properties": {
    "gn:admin1_code":"76",
    "gn:asciiname":"Sloboda",
    "gn:country_code":"RU",
    "gn:dem":194,
    "gn:feature_class":"P",
    "gn:feature_code":"PPL",
    "gn:name":"Sloboda",
    "gn:population":0,
    "gn:timezone":"Europe/Moscow",
    "iso:country":"RU",
    "name:rus_x_preferred":[
        "\u0421\u043b\u043e\u0431\u043e\u0434\u0430"
    ],
    "name:und_x_variant":[
        "\u0421\u043b\u043e\u0431\u043e\u0434\u0430"
    ],
    "wof:name":"Sloboda",
    "wof:placetype":"locality"
},
  "geometry": {"coordinates":[36.09351,53.68569],"type":"Point"}
}