{
  "type": "Feature",
  "properties": {
    "gn:admin1_code":"90.0",
    "gn:asciiname":"Pomortsevo",
    "gn:country_code":"RU",
    "gn:dem":128,
    "gn:feature_class":"P",
    "gn:feature_code":"PPL",
    "gn:name":"Pomortsevo",
    "gn:population":0,
    "gn:timezone":"Asia/Yekaterinburg",
    "iso:country":"RU",
    "name:rus_x_preferred":[
        "\u041f\u043e\u043c\u043e\u0440\u0446\u0435\u0432\u043e"
    ],
    "wof:name":"Pomortsevo",
    "wof:placetype":"locality"
},
  "geometry": {"coordinates":[56.6379,58.8708],"type":"Point"}
}