{
  "type": "Feature",
  "properties": {
    "gn:admin1_code":"63",
    "gn:asciiname":"Bel'kachi",
    "gn:country_code":"RU",
    "gn:dem":182,
    "gn:feature_class":"P",
    "gn:feature_code":"PPL",
    "gn:name":"Bel\u2019kachi",
    "gn:population":0,
    "gn:timezone":"Asia/Yakutsk",
    "iso:country":"RU",
    "name:eng_x_preferred":[
        "Bel'kachi"
    ],
    "name:nor_x_preferred":[
        "Belkatsji"
    ],
    "name:rus_x_preferred":[
        "\u0411\u0435\u043b\u044c\u043a\u0430\u0447\u0438"
    ],
    "name:und_x_variant":[
        "Bel\u2019gechi",
        "Bielkechi",
        "Bel\u2019kachi"
    ],
    "wof:name":"Bel'kachi",
    "wof:placetype":"locality"
},
  "geometry": {"coordinates":[131.89227,59.18488000000001],"type":"Point"}
}