{
  "type": "Feature",
  "properties": {
    "gn:admin1_code":"42.0",
    "gn:asciiname":"Bol'shiye Tomiki",
    "gn:country_code":"RU",
    "gn:dem":44,
    "gn:feature_class":"P",
    "gn:feature_code":"PPL",
    "gn:name":"Bol\u2019shiye Tomiki",
    "gn:population":0,
    "gn:timezone":"Europe/Moscow",
    "iso:country":"RU",
    "name:fin_x_preferred":[
        "Tammikko"
    ],
    "name:rus_x_preferred":[
        "\u0411\u043e\u043b\u044c\u0448\u0438\u0435 \u0422\u043e\u043c\u0438\u043a\u0438"
    ],
    "name:und_x_variant":[
        "Bol\u2019shiye Tomiki",
        "\u0411\u043e\u043b\u044c\u0448\u0438\u0435 \u0422\u043e\u043c\u0438\u043a\u0438"
    ],
    "wof:name":"Bol'shiye Tomiki",
    "wof:placetype":"locality"
},
  "geometry": {"coordinates":[30.03426,59.77586],"type":"Point"}
}