{
  "type": "Feature",
  "properties": {
    "gn:admin1_code":"37",
    "gn:asciiname":"Demid'yevo",
    "gn:country_code":"RU",
    "gn:dem":132,
    "gn:feature_class":"P",
    "gn:feature_code":"PPL",
    "gn:name":"Demid\u2019yevo",
    "gn:population":0,
    "gn:timezone":"Europe/Moscow",
    "iso:country":"RU",
    "name:rus_x_preferred":[
        "\u0414\u0435\u043c\u0438\u0434\u044c\u0435\u0432\u043e"
    ],
    "name:und_x_variant":[
        "Demid\u2019yevo",
        "\u0414\u0435\u043c\u0438\u0434\u044c\u0435\u0432\u043e"
    ],
    "wof:name":"Demid'yevo",
    "wof:placetype":"locality"
},
  "geometry": {"coordinates":[43.5974,58.0042],"type":"Point"}
}