{
  "type": "Feature",
  "properties": {
    "gn:admin1_code":"69",
    "gn:asciiname":"Peschivo",
    "gn:country_code":"RU",
    "gn:dem":193,
    "gn:feature_class":"P",
    "gn:feature_code":"PPL",
    "gn:name":"Peschivo",
    "gn:population":0,
    "gn:timezone":"Europe/Moscow",
    "iso:country":"RU",
    "name:rus_x_preferred":[
        "\u041f\u0435\u0441\u0447\u0438\u0432o"
    ],
    "name:und_x_variant":[
        "Pesniva",
        "Peschiva",
        "Peschivo"
    ],
    "wof:name":"Peschivo",
    "wof:placetype":"locality"
},
  "geometry": {"coordinates":[32.4927,55.5905],"type":"Point"}
}