{
  "type": "Feature",
  "properties": {
    "gn:admin1_code":"05",
    "gn:asciiname":"Ostaf'yevo",
    "gn:country_code":"RU",
    "gn:dem":376,
    "gn:feature_class":"P",
    "gn:feature_code":"PPL",
    "gn:name":"Ostaf\u2019yevo",
    "gn:population":0,
    "gn:timezone":"Asia/Yakutsk",
    "iso:country":"RU",
    "name:rus_x_preferred":[
        "\u041e\u0441\u0442\u0430\u0444\u044c\u0435\u0432\u043e"
    ],
    "name:und_x_variant":[
        "Ostaphsvo",
        "Ostaf\u2019yevo"
    ],
    "wof:name":"Ostaf'yevo",
    "wof:placetype":"locality"
},
  "geometry": {"coordinates":[122.83333,53.66667],"type":"Point"}
}