{
  "type": "Feature",
  "properties": {
    "gn:admin1_code":"53",
    "gn:asciiname":"Bol'shaya Cheremshanka",
    "gn:country_code":"RU",
    "gn:dem":108,
    "gn:feature_class":"P",
    "gn:feature_code":"PPL",
    "gn:name":"Bol\u2019shaya Cheremshanka",
    "gn:population":0,
    "gn:timezone":"Asia/Novosibirsk",
    "iso:country":"RU",
    "name:rus_x_preferred":[
        "\u0411\u043e\u043b\u044c\u0448\u0430\u044f \u0427\u0435\u0440\u0435\u043c\u0448\u0430\u043d\u043a\u0430"
    ],
    "name:und_x_variant":[
        "Cheremshanskiy",
        "Bol\u2019shaya Cheremshanka",
        "\u0411\u043e\u043b\u044c\u0448\u0430\u044f \u0427\u0435\u0440\u0435\u043c\u0448\u0430\u043d\u043a\u0430"
    ],
    "wof:name":"Bol'shaya Cheremshanka",
    "wof:placetype":"locality"
},
  "geometry": {"coordinates":[76.32151999999998,56.98916],"type":"Point"}
}