{
  "type": "Feature",
  "properties": {
    "gn:admin1_code":"77",
    "gn:asciiname":"Strenevo",
    "gn:country_code":"RU",
    "gn:dem":262,
    "gn:feature_class":"P",
    "gn:feature_code":"PPL",
    "gn:name":"Strenevo",
    "gn:population":0,
    "gn:timezone":"Europe/Moscow",
    "iso:country":"RU",
    "name:rus_x_preferred":[
        "\u0421\u0442\u0440\u0435\u043d\u0435\u0432\u043e"
    ],
    "wof:name":"Strenevo",
    "wof:placetype":"locality"
},
  "geometry": {"coordinates":[34.42764,56.68604000000001],"type":"Point"}
}