{
  "type": "Feature",
  "properties": {
    "gn:admin1_code":"33",
    "gn:asciiname":"Kazanskiye",
    "gn:country_code":"RU",
    "gn:dem":105,
    "gn:feature_class":"P",
    "gn:feature_code":"PPL",
    "gn:name":"Kazanskiye",
    "gn:population":0,
    "gn:timezone":"Europe/Kirov",
    "iso:country":"RU",
    "name:rus_x_preferred":[
        "\u041a\u0430\u0437\u0430\u043d\u0441\u043a\u0438\u0435"
    ],
    "name:und_x_variant":[
        "Kazanskaya",
        "Kazanskiye"
    ],
    "wof:name":"Kazanskiye",
    "wof:placetype":"locality"
},
  "geometry": {"coordinates":[47.0846,57.00644000000001],"type":"Point"}
}