{
  "type": "Feature",
  "properties": {
    "gn:admin1_code":"41.0",
    "gn:asciiname":"Bobrava",
    "gn:country_code":"RU",
    "gn:dem":154,
    "gn:feature_class":"P",
    "gn:feature_code":"PPL",
    "gn:name":"Bobrava",
    "gn:population":0,
    "gn:timezone":"Europe/Moscow",
    "iso:country":"RU",
    "name:eng_x_preferred":[
        "Bobrava"
    ],
    "name:nor_x_preferred":[
        "Bobrava"
    ],
    "name:rus_x_preferred":[
        "\u0411\u043e\u0431\u0440\u0430\u0432\u0430"
    ],
    "name:und_x_variant":[
        "\u0411\u043e\u0431\u0440\u0430\u0432\u0430",
        "Bobrava"
    ],
    "wof:name":"Bobrava",
    "wof:placetype":"locality"
},
  "geometry": {"coordinates":[35.8156,51.0807],"type":"Point"}
}