{
  "type": "Feature",
  "properties": {
    "gn:admin1_code":"41",
    "gn:asciiname":"Trubatskoye",
    "gn:country_code":"RU",
    "gn:dem":186,
    "gn:feature_class":"P",
    "gn:feature_code":"PPL",
    "gn:name":"Trubatskoye",
    "gn:population":0,
    "gn:timezone":"Europe/Moscow",
    "iso:country":"RU",
    "name:rus_x_preferred":[
        "\u0422\u0440\u0443\u0431\u0430\u0446\u043a\u043e\u0435"
    ],
    "name:und_x_variant":[
        "Trubatskaya"
    ],
    "wof:name":"Trubatskoye",
    "wof:placetype":"locality"
},
  "geometry": {"coordinates":[37.1388,51.3812],"type":"Point"}
}