{
  "type": "Feature",
  "properties": {
    "gn:admin1_code":"76",
    "gn:asciiname":"Zherlovo-Lukino",
    "gn:country_code":"RU",
    "gn:dem":149,
    "gn:feature_class":"P",
    "gn:feature_code":"PPL",
    "gn:name":"Zherlovo-Lukino",
    "gn:population":0,
    "gn:timezone":"Europe/Moscow",
    "iso:country":"RU",
    "wof:name":"Zherlovo-Lukino",
    "wof:placetype":"locality"
},
  "geometry": {"coordinates":[36.57083,53.42639000000001],"type":"Point"}
}