{
  "type": "Feature",
  "properties": {
    "gn:admin1_code":"56",
    "gn:asciiname":"Khabarovka",
    "gn:country_code":"RU",
    "gn:dem":191,
    "gn:feature_class":"P",
    "gn:feature_code":"PPL",
    "gn:name":"Khabarovka",
    "gn:population":0,
    "gn:timezone":"Europe/Moscow",
    "iso:country":"RU",
    "name:rus_x_preferred":[
        "\u0425\u0430\u0431\u0430\u0440\u043e\u0432\u043a\u0430"
    ],
    "name:und_x_variant":[
        "\u0425\u0430\u0431\u0430\u0440\u043e\u0432\u043a\u0430"
    ],
    "wof:name":"Khabarovka",
    "wof:placetype":"locality"
},
  "geometry": {"coordinates":[36.80635,53.17738000000001],"type":"Point"}
}