{
  "type": "Feature",
  "properties": {
    "gn:admin1_code":"52",
    "gn:asciiname":"Gorodtsy",
    "gn:country_code":"RU",
    "gn:dem":69,
    "gn:feature_class":"P",
    "gn:feature_code":"PPL",
    "gn:name":"Gorodtsy",
    "gn:population":0,
    "gn:timezone":"Europe/Moscow",
    "iso:country":"RU",
    "name:eng_x_preferred":[
        "Gorodtsy"
    ],
    "name:nor_x_preferred":[
        "Gorodtsy"
    ],
    "name:rus_x_preferred":[
        "\u0413\u043e\u0440\u043e\u0434\u0446\u044b"
    ],
    "wof:name":"Gorodtsy",
    "wof:placetype":"locality"
},
  "geometry": {"coordinates":[30.76977,57.98965],"type":"Point"}
}