{
  "type": "Feature",
  "properties": {
    "gn:admin1_code":"54",
    "gn:asciiname":"Sitnikovo",
    "gn:country_code":"RU",
    "gn:dem":110,
    "gn:feature_class":"P",
    "gn:feature_code":"PPL",
    "gn:name":"Sitnikovo",
    "gn:population":0,
    "gn:timezone":"Asia/Omsk",
    "iso:country":"RU",
    "name:che_x_preferred":[
        "\u0421\u0438\u0442\u043d\u0438\u043a\u043e\u0432\u043e"
    ],
    "name:rus_x_preferred":[
        "\u0421\u0438\u0442\u043d\u0438\u043a\u043e\u0432\u043e"
    ],
    "name:und_x_variant":[
        "Sovkhoz Nekrasovskiy"
    ],
    "wof:name":"Sitnikovo",
    "wof:placetype":"locality"
},
  "geometry": {"coordinates":[74.79040999999999,55.66556],"type":"Point"}
}