{
  "type": "Feature",
  "properties": {
    "gn:admin1_code":"72",
    "gn:asciiname":"Grachevka",
    "gn:country_code":"RU",
    "gn:dem":119,
    "gn:feature_class":"P",
    "gn:feature_code":"PPL",
    "gn:name":"Grach\u00ebvka",
    "gn:population":0,
    "gn:timezone":"Europe/Moscow",
    "iso:country":"RU",
    "name:rus_x_preferred":[
        "\u0413\u0440\u0430\u0447\u0451\u0432\u043a\u0430"
    ],
    "name:und_x_variant":[
        "Grach\u00ebvka",
        "\u0413\u0440\u0430\u0447\u0451\u0432\u043a\u0430"
    ],
    "wof:name":"Grachevka",
    "wof:placetype":"locality"
},
  "geometry": {"coordinates":[40.38417000000001,52.38806],"type":"Point"}
}