{
  "type": "Feature",
  "properties": {
    "gn:country":"RU",
    "gn:fcode":"PPL",
    "gn:pop":236,
    "iso:country":"RU",
    "name:nor_x_preferred":[
        "Abramtsevo"
    ],
    "name:rus_x_preferred":[
        "\u0410\u0431\u0440\u0430\u043c\u0446\u0435\u0432\u043e"
    ],
    "qs:name":"Abramtsevo",
    "qs:name_adm0":"Russia",
    "qs:name_adm1":"Moscow Oblast",
    "qs:photos_9r":0,
    "qs:photos_sr":0,
    "qs:placetype":"Town",
    "qs:pop_sr":"2",
    "wd:wordcount":159,
    "wof:name":"Abramtsevo",
    "wof:placetype":"locality",
    "wof:population":236
},
  "geometry": {"coordinates":[37.83787,55.83216],"type":"Point"}
}