{
  "type": "Feature",
  "properties": {
    "gn:admin1_code":"62",
    "gn:asciiname":"Vol'naya Zhizn'",
    "gn:country_code":"RU",
    "gn:dem":119,
    "gn:feature_class":"P",
    "gn:feature_code":"PPL",
    "gn:name":"Vol\u2019naya Zhizn\u2019",
    "gn:population":0,
    "gn:timezone":"Europe/Moscow",
    "iso:country":"RU",
    "wof:name":"Vol'naya Zhizn'",
    "wof:placetype":"locality"
},
  "geometry": {"coordinates":[40.015,53.64417],"type":"Point"}
}