{
  "type": "Feature",
  "properties": {
    "gn:admin1_code":"69",
    "gn:asciiname":"Krasnoye",
    "gn:country_code":"RU",
    "gn:dem":238,
    "gn:feature_class":"P",
    "gn:feature_code":"PPL",
    "gn:name":"Krasnoye",
    "gn:population":0,
    "gn:timezone":"Europe/Moscow",
    "iso:country":"RU",
    "name:rus_x_preferred":[
        "\u041a\u0440\u0430\u0441\u043d\u043e\u0435"
    ],
    "wof:name":"Krasnoye",
    "wof:placetype":"locality"
},
  "geometry": {"coordinates":[33.91778,55.57417],"type":"Point"}
}