{
  "type": "Feature",
  "properties": {
    "gn:admin1_code":"91",
    "gn:asciiname":"Malaya Tes'",
    "gn:country_code":"RU",
    "gn:dem":275,
    "gn:feature_class":"P",
    "gn:feature_code":"PPL",
    "gn:name":"Malaya Tes\u2019",
    "gn:population":0,
    "gn:timezone":"Asia/Krasnoyarsk",
    "iso:country":"RU",
    "name:rus_x_preferred":[
        "\u041c\u0430\u043b\u0430\u044f \u0422\u0435\u0441\u044c"
    ],
    "name:und_x_variant":[
        "Malaya Tes\u2019"
    ],
    "wof:name":"Malaya Tes'",
    "wof:placetype":"locality"
},
  "geometry": {"coordinates":[91.05,54.78333000000001],"type":"Point"}
}