{
  "type": "Feature",
  "properties": {
    "gn:admin1_code":"16",
    "gn:asciiname":"Yermoshkino",
    "gn:country_code":"RU",
    "gn:dem":96,
    "gn:feature_class":"P",
    "gn:feature_code":"PPL",
    "gn:name":"Yermoshkino",
    "gn:population":0,
    "gn:timezone":"Europe/Moscow",
    "iso:country":"RU",
    "name:rus_x_preferred":[
        "\u0415\u0440\u043c\u043e\u0448\u043a\u0438\u043d\u043e"
    ],
    "wof:name":"Yermoshkino",
    "wof:placetype":"locality"
},
  "geometry": {"coordinates":[46.92283,55.66656],"type":"Point"}
}