{
  "type": "Feature",
  "properties": {
    "gn:admin1_code":"8",
    "gn:asciiname":"Nikol'sk",
    "gn:country_code":"RU",
    "gn:dem":201,
    "gn:feature_class":"P",
    "gn:feature_code":"PPL",
    "gn:name":"Nikol\u2019sk",
    "gn:population":0,
    "gn:timezone":"Asia/Yekaterinburg",
    "iso:country":"RU",
    "name:rus_x_preferred":[
        "\u041d\u0438\u043a\u043e\u043b\u044c\u0441\u043a"
    ],
    "name:und_x_variant":[
        "Nikol\u2019sk"
    ],
    "wof:name":"Nikol'sk",
    "wof:placetype":"locality"
},
  "geometry": {"coordinates":[55.8026,54.004],"type":"Point"}
}