{
  "type": "Feature",
  "properties": {
    "gn:admin1_code":"77",
    "gn:asciiname":"Poselok Narachino",
    "gn:country_code":"RU",
    "gn:dem":196,
    "gn:feature_class":"P",
    "gn:feature_code":"PPL",
    "gn:name":"Pos\u00eblok Narachino",
    "gn:population":0,
    "gn:timezone":"Europe/Moscow",
    "iso:country":"RU",
    "name:rus_x_preferred":[
        "\u041f\u043e\u0441\u0451\u043b\u043e\u043a \u041d\u0430\u0440\u0430\u0447\u0438\u043d\u043e"
    ],
    "name:und_x_variant":[
        "Narachino",
        "Pos\u00eblok Narachino",
        "\u041f\u043e\u0441\u0451\u043b\u043e\u043a \u041d\u0430\u0440\u0430\u0447\u0438\u043d\u043e"
    ],
    "wof:name":"Poselok Narachino",
    "wof:placetype":"locality"
},
  "geometry": {"coordinates":[33.74306,57.91056],"type":"Point"}
}