{
  "type": "Feature",
  "properties": {
    "gn:admin1_code":"56.0",
    "gn:asciiname":"Chibisovka",
    "gn:country_code":"RU",
    "gn:dem":221,
    "gn:feature_class":"P",
    "gn:feature_code":"PPL",
    "gn:name":"Chibisovka",
    "gn:population":0,
    "gn:timezone":"Europe/Moscow",
    "iso:country":"RU",
    "name:rus_x_preferred":[
        "\u0427\u0438\u0431\u0438\u0441\u043e\u0432\u043a\u0430"
    ],
    "wof:name":"Chibisovka",
    "wof:placetype":"locality"
},
  "geometry": {"coordinates":[36.81346,52.55903000000001],"type":"Point"}
}