{
  "type": "Feature",
  "properties": {
    "gn:admin1_code":"84",
    "gn:asciiname":"Obraztsy",
    "gn:country_code":"RU",
    "gn:dem":150,
    "gn:feature_class":"P",
    "gn:feature_code":"PPL",
    "gn:name":"Obraztsy",
    "gn:population":0,
    "gn:timezone":"Europe/Volgograd",
    "iso:country":"RU",
    "name:eng_x_preferred":[
        "Obraztsy"
    ],
    "name:nor_x_preferred":[
        "Obraztsy"
    ],
    "name:rus_x_preferred":[
        "\u041e\u0431\u0440\u0430\u0437\u0446\u044b"
    ],
    "name:und_x_variant":[
        "Obraztsovskaya",
        "Obraztsy"
    ],
    "wof:name":"Obraztsy",
    "wof:placetype":"locality"
},
  "geometry": {"coordinates":[44.00981,49.78313],"type":"Point"}
}