{
  "type": "Feature",
  "properties": {
    "gn:admin1_code":"8",
    "gn:asciiname":"Sosnovyy Bor",
    "gn:country_code":"RU",
    "gn:dem":345,
    "gn:feature_class":"P",
    "gn:feature_code":"PPL",
    "gn:name":"Sosnovyy Bor",
    "gn:population":0,
    "gn:timezone":"Asia/Yekaterinburg",
    "iso:country":"RU",
    "name:rus_x_preferred":[
        "\u0421\u043e\u0441\u043d\u043e\u0432\u044b\u0439 \u0411\u043e\u0440"
    ],
    "name:und_x_variant":[
        "\u0421\u043e\u0441\u043d\u043e\u0432\u044b\u0439 \u0411\u043e\u0440"
    ],
    "wof:name":"Sosnovyy Bor",
    "wof:placetype":"locality"
},
  "geometry": {"coordinates":[54.31667,54.23333],"type":"Point"}
}