{
  "type": "Feature",
  "properties": {
    "gn:admin1_code":"90",
    "gn:asciiname":"Kuzino",
    "gn:country_code":"RU",
    "gn:dem":130,
    "gn:feature_class":"P",
    "gn:feature_code":"PPL",
    "gn:name":"Kuzino",
    "gn:population":0,
    "gn:timezone":"Asia/Yekaterinburg",
    "iso:country":"RU",
    "name:eng_x_preferred":[
        "Kuzina"
    ],
    "name:hye_x_preferred":[
        "\u053f\u0578\u0582\u0566\u056b\u0576\u0578"
    ],
    "name:ita_x_preferred":[
        "Kuzino"
    ],
    "name:nor_x_preferred":[
        "Kuzino"
    ],
    "name:pol_x_preferred":[
        "Kuzino"
    ],
    "name:rus_x_preferred":[
        "\u041a\u0443\u0437\u0438\u043d\u043e"
    ],
    "name:und_x_variant":[
        "Kuzina",
        "Kuzino"
    ],
    "wof:name":"Kuzino",
    "wof:placetype":"locality"
},
  "geometry": {"coordinates":[54.47058000000001,57.59952],"type":"Point"}
}