{
  "type": "Feature",
  "properties": {
    "gn:admin1_code":"23",
    "gn:asciiname":"Ryadino",
    "gn:country_code":"RU",
    "gn:dem":23,
    "gn:feature_class":"P",
    "gn:feature_code":"PPL",
    "gn:name":"Ryadino",
    "gn:population":0,
    "gn:timezone":"Europe/Kaliningrad",
    "iso:country":"RU",
    "name:rus_x_preferred":[
        "\u0420\u044f\u0434\u0438\u043d\u043e"
    ],
    "wof:name":"Ryadino",
    "wof:placetype":"locality"
},
  "geometry": {"coordinates":[22.19556,55.02944],"type":"Point"}
}