{
  "type": "Feature",
  "properties": {
    "gn:admin1_code":"77",
    "gn:asciiname":"Ladozino",
    "gn:country_code":"RU",
    "gn:dem":162,
    "gn:feature_class":"P",
    "gn:feature_code":"PPL",
    "gn:name":"Ladozino",
    "gn:population":0,
    "gn:timezone":"Europe/Moscow",
    "iso:country":"RU",
    "name:nor_x_preferred":[
        "Ladozino"
    ],
    "name:rus_x_preferred":[
        "\u041b\u0430\u0434\u043e\u0437\u0438\u043d\u043e"
    ],
    "wof:name":"Ladozino",
    "wof:placetype":"locality"
},
  "geometry": {"coordinates":[35.0951,56.39185],"type":"Point"}
}