{
  "type": "Feature",
  "properties": {
    "gn:admin1_code":"5",
    "gn:asciiname":"Zagornaya Selit'ba",
    "gn:country_code":"RU",
    "gn:dem":240,
    "gn:feature_class":"P",
    "gn:feature_code":"PPL",
    "gn:name":"Zagornaya Selit\u2019ba",
    "gn:population":0,
    "gn:timezone":"Asia/Yakutsk",
    "iso:country":"RU",
    "name:eng_x_preferred":[
        "Zagornaya Selit'ba"
    ],
    "name:nor_x_preferred":[
        "Zagornaja-Selitba"
    ],
    "name:rus_x_preferred":[
        "\u0417\u0430\u0433\u043e\u0440\u043d\u0430\u044f-\u0421\u0435\u043b\u0438\u0442\u044c\u0431\u0430"
    ],
    "name:rus_x_variant":[
        "\u0417\u0430\u0433\u043e\u0440\u043d\u0430\u044f \u0421\u0435\u043b\u0438\u0442\u044c\u0431\u0430"
    ],
    "name:und_x_variant":[
        "Selit\u2019ba-Zagorodnaya",
        "Zagomaya Selit\u2019ba",
        "Kamenushka",
        "Zagornaya Selit\u2019ba"
    ],
    "wof:name":"Zagornaya Selit'ba",
    "wof:placetype":"locality"
},
  "geometry": {"coordinates":[127.24724000000001,51.14088],"type":"Point"}
}