{
  "type": "Feature",
  "properties": {
    "gn:admin1_code":"81",
    "gn:asciiname":"Gorodets",
    "gn:country_code":"RU",
    "gn:dem":168,
    "gn:feature_class":"P",
    "gn:feature_code":"PPL",
    "gn:name":"Gorodets",
    "gn:population":0,
    "gn:timezone":"Europe/Ulyanovsk",
    "iso:country":"RU",
    "name:rus_x_preferred":[
        "\u0413\u043e\u0440\u043e\u0434\u0435\u0446"
    ],
    "wof:name":"Gorodets",
    "wof:placetype":"locality"
},
  "geometry": {"coordinates":[47.2239,54.4327],"type":"Point"}
}