{
  "type": "Feature",
  "properties": {
    "gn:admin1_code":"33.0",
    "gn:asciiname":"Kardashi",
    "gn:country_code":"RU",
    "gn:dem":170,
    "gn:feature_class":"P",
    "gn:feature_code":"PPL",
    "gn:name":"Kardashi",
    "gn:population":0,
    "gn:timezone":"Europe/Kirov",
    "iso:country":"RU",
    "name:rus_x_preferred":[
        "\u041a\u0430\u0440\u0434\u0430\u0448\u0438"
    ],
    "name:und_x_variant":[
        "\u041a\u0430\u0440\u0434\u0430\u0448\u0438"
    ],
    "wof:name":"Kardashi",
    "wof:placetype":"locality"
},
  "geometry": {"coordinates":[50.73081,58.56428],"type":"Point"}
}