{
  "type": "Feature",
  "properties": {
    "gn:admin1_code":"21",
    "gn:asciiname":"Nazarkovo",
    "gn:country_code":"RU",
    "gn:dem":126,
    "gn:feature_class":"P",
    "gn:feature_code":"PPL",
    "gn:name":"Nazarkovo",
    "gn:population":0,
    "gn:timezone":"Europe/Moscow",
    "iso:country":"RU",
    "name:rus_x_preferred":[
        "\u041d\u0430\u0437\u0430\u0440\u043a\u043e\u0432\u043e"
    ],
    "name:und_x_variant":[
        "Nazarkino",
        "Nazarkovo"
    ],
    "wof:name":"Nazarkovo",
    "wof:placetype":"locality"
},
  "geometry": {"coordinates":[41.89458,57.08237],"type":"Point"}
}