{
  "type": "Feature",
  "properties": {
    "gn:admin1_code":"72",
    "gn:asciiname":"Mashkovo-Surena",
    "gn:country_code":"RU",
    "gn:dem":152,
    "gn:feature_class":"P",
    "gn:feature_code":"PPL",
    "gn:name":"Mashkovo-Surena",
    "gn:population":0,
    "gn:timezone":"Europe/Moscow",
    "iso:country":"RU",
    "name:eng_x_preferred":[
        "Mashkova-Surena"
    ],
    "name:nor_x_preferred":[
        "Masjkovo-Surena"
    ],
    "name:rus_x_preferred":[
        "\u041c\u0430\u0448\u043a\u043e\u0432\u043e-\u0421\u0443\u0440\u0435\u043d\u0430"
    ],
    "name:und_x_variant":[
        "Mashkova-Surena",
        "\u041c\u0430\u0448\u043a\u043e\u0432\u0430-\u0421\u0443\u0440\u0435\u043d\u0430",
        "Mashkovo-Surena"
    ],
    "wof:name":"Mashkovo-Surena",
    "wof:placetype":"locality"
},
  "geometry": {"coordinates":[40.8364,52.7819],"type":"Point"}
}