{
  "type": "Feature",
  "properties": {
    "gn:admin1_code":"52",
    "gn:asciiname":"Shestovo",
    "gn:country_code":"RU",
    "gn:dem":80,
    "gn:feature_class":"P",
    "gn:feature_code":"PPL",
    "gn:name":"Shestovo",
    "gn:population":0,
    "gn:timezone":"Europe/Moscow",
    "iso:country":"RU",
    "name:rus_x_preferred":[
        "\u0428\u0435\u0441\u0442\u043e\u0432\u043e"
    ],
    "name:und_x_variant":[
        "\u0428\u0435\u0441\u0442\u043e\u0432\u043e"
    ],
    "wof:name":"Shestovo",
    "wof:placetype":"locality"
},
  "geometry": {"coordinates":[30.9354,57.5716],"type":"Point"}
}