{
  "type": "Feature",
  "properties": {
    "gn:admin1_code":"54",
    "gn:asciiname":"Balangul'",
    "gn:country_code":"RU",
    "gn:dem":92,
    "gn:feature_class":"P",
    "gn:feature_code":"PPL",
    "gn:name":"Balangul\u2019",
    "gn:population":0,
    "gn:timezone":"Asia/Omsk",
    "iso:country":"RU",
    "name:rus_x_preferred":[
        "\u0411\u0430\u043b\u0430\u043d\u0433\u0443\u043b\u044c"
    ],
    "name:und_x_variant":[
        "Balangul\u2019"
    ],
    "wof:name":"Balangul'",
    "wof:placetype":"locality"
},
  "geometry": {"coordinates":[73.2654,55.8052],"type":"Point"}
}