{
  "type": "Feature",
  "properties": {
    "gn:admin1_code":"85",
    "gn:asciiname":"Rybay",
    "gn:country_code":"RU",
    "gn:dem":111,
    "gn:feature_class":"P",
    "gn:feature_code":"PPL",
    "gn:name":"Rybay",
    "gn:population":0,
    "gn:timezone":"Europe/Moscow",
    "iso:country":"RU",
    "name:rus_x_preferred":[
        "\u0420\u044b\u0431\u0430\u0439"
    ],
    "name:und_x_variant":[
        "\u0420\u044b\u0431\u0430\u0439"
    ],
    "wof:name":"Rybay",
    "wof:placetype":"locality"
},
  "geometry": {"coordinates":[38.43333,59.26667],"type":"Point"}
}