{
  "type": "Feature",
  "properties": {
    "gn:admin1_code":"23",
    "gn:asciiname":"Kolomenskoye",
    "gn:country_code":"RU",
    "gn:dem":61,
    "gn:feature_class":"P",
    "gn:feature_code":"PPL",
    "gn:name":"Kolomenskoye",
    "gn:population":0,
    "gn:timezone":"Europe/Kaliningrad",
    "iso:country":"RU",
    "name:afr_x_preferred":[
        "Kolomenskoje"
    ],
    "name:bul_x_preferred":[
        "\u041a\u043e\u043b\u043e\u043c\u0435\u043d\u0441\u043a\u043e\u0435"
    ],
    "name:cat_x_preferred":[
        "Kol\u00f3menskoie"
    ],
    "name:ceb_x_preferred":[
        "Kolomenskoye"
    ],
    "name:ces_x_preferred":[
        "Kolomenskoje"
    ],
    "name:chv_x_preferred":[
        "\u041a\u043e\u043b\u043e\u043c\u0435\u043d\u0441\u043a\u043e\u0435"
    ],
    "name:dan_x_preferred":[
        "Kolomenskoje"
    ],
    "name:deu_x_preferred":[
        "Kolomenskoje"
    ],
    "name:eus_x_preferred":[
        "Kolomenskoie"
    ],
    "name:fas_x_preferred":[
        "\u06a9\u0648\u0644\u0648\u0645\u0646\u0633\u06a9\u0648\u06cc\u0647"
    ],
    "name:fra_x_preferred":[
        "Kolomensko\u00efe"
    ],
    "name:fry_x_preferred":[
        "Kolomenskoje"
    ],
    "name:hrv_x_preferred":[
        "Kolomenskoje"
    ],
    "name:hun_x_preferred":[
        "Kolomenszkoje"
    ],
    "name:hye_x_preferred":[
        "\u053f\u0578\u056c\u0578\u0574\u0565\u0576\u057d\u056f\u0578\u0575\u0565"
    ],
    "name:ido_x_preferred":[
        "Kolomenskoye"
    ],
    "name:ita_x_preferred":[
        "Kolomenskoe"
    ],
    "name:jpn_x_preferred":[
        "\u30b3\u30ed\u30fc\u30e1\u30f3\u30b9\u30b3\u30a8"
    ],
    "name:kat_x_preferred":[
        "\u10d9\u10dd\u10da\u10dd\u10db\u10d4\u10dc\u10e1\u10d9\u10dd\u10d4"
    ],
    "name:lit_x_preferred":[
        "Kolomenskoj\u0117"
    ],
    "name:nld_x_preferred":[
        "Kolomenskoje"
    ],
    "name:nor_x_preferred":[
        "Kolomenskoje"
    ],
    "name:pol_x_preferred":[
        "Ko\u0142omie\u0144skie"
    ],
    "name:por_x_preferred":[
        "Kolomenskoye"
    ],
    "name:rus_x_preferred":[
        "\u041a\u043e\u043b\u043e\u043c\u0435\u043d\u0441\u043a\u043e\u0435"
    ],
    "name:slk_x_preferred":[
        "Kolomenskoje"
    ],
    "name:spa_x_preferred":[
        "Kol\u00f3menskoye"
    ],
    "name:srp_x_preferred":[
        "\u041a\u043e\u043b\u043e\u043c\u0435\u043d\u0441\u043a\u043e"
    ],
    "name:swe_x_preferred":[
        "Kolomenskoje"
    ],
    "name:tur_x_preferred":[
        "Kolomenskoye"
    ],
    "name:ukr_x_preferred":[
        "\u041a\u043e\u043b\u043e\u043c\u0435\u043d\u0441\u044c\u043a\u0435"
    ],
    "name:und_x_variant":[
        "\u041a\u043e\u043b\u043e\u043c\u0435\u043d\u0441\u043a\u043e\u0435"
    ],
    "name:vie_x_preferred":[
        "Kolomenskoye"
    ],
    "name:zho_x_preferred":[
        "\u79d1\u7f57\u7f05\u65af\u514b"
    ],
    "wof:name":"Kolomenskoye",
    "wof:placetype":"locality"
},
  "geometry": {"coordinates":[20.09444,54.92028000000001],"type":"Point"}
}