{
  "type": "Feature",
  "properties": {
    "gn:admin1_code":"23",
    "gn:asciiname":"Kolomenskoye",
    "gn:country_code":"RU",
    "gn:dem":61,
    "gn:feature_class":"P",
    "gn:feature_code":"PPL",
    "gn:name":"Kolomenskoye",
    "gn:population":0,
    "gn:timezone":"Europe/Kaliningrad",
    "iso:country":"RU",
    "name:rus_x_preferred":[
        "\u041a\u043e\u043b\u043e\u043c\u0435\u043d\u0441\u043a\u043e\u0435"
    ],
    "name:und_x_variant":[
        "\u041a\u043e\u043b\u043e\u043c\u0435\u043d\u0441\u043a\u043e\u0435"
    ],
    "wof:name":"Kolomenskoye",
    "wof:placetype":"locality"
},
  "geometry": {"coordinates":[20.09444,54.92028000000001],"type":"Point"}
}