{
  "type": "Feature",
  "properties": {
    "gn:admin1_code":"51",
    "gn:asciiname":"Vtoroye Uspenskoye",
    "gn:country_code":"RU",
    "gn:dem":174,
    "gn:feature_class":"P",
    "gn:feature_code":"PPL",
    "gn:name":"Vtoroye Uspenskoye",
    "gn:population":0,
    "gn:timezone":"Europe/Moscow",
    "iso:country":"RU",
    "name:und_x_variant":[
        "Uspenskaya",
        "Vtoroye Uspenskoye"
    ],
    "wof:name":"Vtoroye Uspenskoye",
    "wof:placetype":"locality"
},
  "geometry": {"coordinates":[44.13716,55.35334],"type":"Point"}
}