{
  "type": "Feature",
  "properties": {
    "gn:admin1_code":"85",
    "gn:asciiname":"Yekimovo",
    "gn:country_code":"RU",
    "gn:dem":136,
    "gn:feature_class":"P",
    "gn:feature_code":"PPL",
    "gn:name":"Yekimovo",
    "gn:population":0,
    "gn:timezone":"Europe/Moscow",
    "iso:country":"RU",
    "wof:name":"Yekimovo",
    "wof:placetype":"locality"
},
  "geometry": {"coordinates":[38.51874,60.69953],"type":"Point"}
}