{
  "type": "Feature",
  "properties": {
    "gn:admin1_code":"37",
    "gn:asciiname":"Pishchevo",
    "gn:country_code":"RU",
    "gn:dem":147,
    "gn:feature_class":"P",
    "gn:feature_code":"PPL",
    "gn:name":"Pishch\u00ebvo",
    "gn:population":0,
    "gn:timezone":"Europe/Moscow",
    "iso:country":"RU",
    "name:rus_x_preferred":[
        "\u041f\u0438\u0449\u0451\u0432\u043e"
    ],
    "name:und_x_variant":[
        "Pishch\u00ebvo",
        "\u041f\u0438\u0449\u0451\u0432\u043e"
    ],
    "wof:name":"Pishchevo",
    "wof:placetype":"locality"
},
  "geometry": {"coordinates":[44.68333,58.53333000000001],"type":"Point"}
}