{
  "type": "Feature",
  "properties": {
    "gn:admin1_code":"33.0",
    "gn:asciiname":"Yermolintsy",
    "gn:country_code":"RU",
    "gn:dem":137,
    "gn:feature_class":"P",
    "gn:feature_code":"PPL",
    "gn:name":"Yermolintsy",
    "gn:population":0,
    "gn:timezone":"Europe/Kirov",
    "iso:country":"RU",
    "name:rus_x_preferred":[
        "\u0415\u0440\u043c\u043e\u043b\u0438\u043d\u0446\u044b"
    ],
    "wof:name":"Yermolintsy",
    "wof:placetype":"locality"
},
  "geometry": {"coordinates":[49.71346,58.45512],"type":"Point"}
}