{
  "type": "Feature",
  "properties": {
    "iso:country":"RU",
    "name:eng_x_preferred":[
        "Mikhalkino"
    ],
    "name:nld_x_preferred":[
        "Michalkino"
    ],
    "name:rus_x_preferred":[
        "\u041c\u0438\u0445\u0430\u043b\u043a\u0438\u043d\u043e"
    ],
    "ne:ADM0CAP":0.0,
    "ne:ADM0NAME":"Russia",
    "ne:ADM0_A3":"RUS",
    "ne:ADM1NAME":"Koryak",
    "ne:ADMIN1_COD":0,
    "ne:CAPALT":0,
    "ne:CHANGED":4,
    "ne:CHECKME":0,
    "ne:COMPARE":0,
    "ne:DIFFASCII":0,
    "ne:DIFFNOTE":"Location adjusted.",
    "ne:ELEVATION":0.0,
    "ne:FEATURECLA":"Populated place",
    "ne:GEONAMEID":-1,
    "ne:GEONAMESNO":"No GeoNames match due to small population, not in GeoNames, or poor NEV placement.",
    "ne:GN_POP":0,
    "ne:GTOPO30":0.0,
    "ne:ISO_A2":"RU",
    "ne:LABELRANK":2,
    "ne:LATITUDE":69.42444,
    "ne:LONGITUDE":161.481143,
    "ne:LS_MATCH":0,
    "ne:LS_NAME":"Mikhalkino",
    "ne:MAX_AREAKM":0.0,
    "ne:MAX_AREAMI":0.0,
    "ne:MAX_BBXMAX":0.0,
    "ne:MAX_BBXMIN":0.0,
    "ne:MAX_BBYMAX":0.0,
    "ne:MAX_BBYMIN":0.0,
    "ne:MAX_NATSCA":0.0,
    "ne:MAX_PERKM":0.0,
    "ne:MAX_PERMI":0.0,
    "ne:MAX_POP10":0,
    "ne:MAX_POP20":0,
    "ne:MAX_POP300":0,
    "ne:MAX_POP310":0,
    "ne:MAX_POP50":0,
    "ne:MEAN_BBXC":0.0,
    "ne:MEAN_BBYC":0.0,
    "ne:MEGACITY":0,
    "ne:MIN_AREAKM":0.0,
    "ne:MIN_AREAMI":0.0,
    "ne:MIN_BBXMAX":0.0,
    "ne:MIN_BBXMIN":0.0,
    "ne:MIN_BBYMAX":0.0,
    "ne:MIN_BBYMIN":0.0,
    "ne:MIN_PERKM":0.0,
    "ne:MIN_PERMI":0.0,
    "ne:NAME":"Mikhalkino",
    "ne:NAMEASCII":"Mikhalkino",
    "ne:NAMEDIFF":0,
    "ne:NATSCALE":10,
    "ne:POP1950":0,
    "ne:POP1955":0,
    "ne:POP1960":0,
    "ne:POP1965":0,
    "ne:POP1970":0,
    "ne:POP1975":0,
    "ne:POP1980":0,
    "ne:POP1985":0,
    "ne:POP1990":0,
    "ne:POP1995":0,
    "ne:POP2000":0,
    "ne:POP2005":0,
    "ne:POP2010":0,
    "ne:POP2015":0,
    "ne:POP2020":0,
    "ne:POP2025":0,
    "ne:POP2050":0,
    "ne:POP_MAX":570,
    "ne:POP_MIN":570,
    "ne:POP_OTHER":0,
    "ne:RANK_MAX":2,
    "ne:RANK_MIN":2,
    "ne:SCALERANK":8,
    "ne:SOV0NAME":"Russia",
    "ne:SOV_A3":"RUS",
    "ne:UN_FID":0,
    "ne:UN_LAT":0.0,
    "ne:UN_LONG":0.0,
    "ne:WORLDCITY":0,
    "ne:min_zoom":7.0,
    "wof:name":"Mikhalkino",
    "wof:placetype":"locality"
},
  "geometry": {"coordinates":[161.4811430958697,69.42444039326068],"type":"Point"}
}