{
  "type": "Feature",
  "properties": {
    "gn:admin1_code":"25",
    "gn:admin2_code":"578944",
    "gn:asciiname":"Novoye Selo",
    "gn:country_code":"RU",
    "gn:dem":222,
    "gn:feature_class":"P",
    "gn:feature_code":"PPL",
    "gn:name":"Novoye Selo",
    "gn:population":0,
    "gn:timezone":"Europe/Moscow",
    "iso:country":"RU",
    "name:eng_x_preferred":[
        "Novoye Selo"
    ],
    "name:nor_x_preferred":[
        "Novoje Selo"
    ],
    "name:rus_x_preferred":[
        "\u041d\u043e\u0432\u043e\u0435 \u0421\u0435\u043b\u043e"
    ],
    "name:und_x_variant":[
        "Novoye"
    ],
    "wof:name":"Novoye Selo",
    "wof:placetype":"locality"
},
  "geometry": {"coordinates":[34.63738,54.19922],"type":"Point"}
}