{
  "type": "Feature",
  "properties": {
    "gn:admin1_code":"42",
    "gn:asciiname":"Malyye Gorki",
    "gn:country_code":"RU",
    "gn:dem":113,
    "gn:feature_class":"P",
    "gn:feature_code":"PPL",
    "gn:name":"Malyye Gorki",
    "gn:population":0,
    "gn:timezone":"Europe/Moscow",
    "iso:country":"RU",
    "name:nor_x_preferred":[
        "Malye Gorki"
    ],
    "name:rus_x_preferred":[
        "\u041c\u0430\u043b\u044b\u0435 \u0413\u043e\u0440\u043a\u0438"
    ],
    "wof:name":"Malyye Gorki",
    "wof:placetype":"locality"
},
  "geometry": {"coordinates":[29.85684,59.70763],"type":"Point"}
}