{
  "type": "Feature",
  "properties": {
    "gn:admin1_code":"45",
    "gn:asciiname":"Ismentsy",
    "gn:country_code":"RU",
    "gn:dem":99,
    "gn:feature_class":"P",
    "gn:feature_code":"PPL",
    "gn:name":"Ismentsy",
    "gn:population":0,
    "gn:timezone":"Europe/Moscow",
    "iso:country":"RU",
    "name:eng_x_preferred":[
        "Ismentsy"
    ],
    "name:nor_x_preferred":[
        "Ismentsy"
    ],
    "name:rus_x_preferred":[
        "\u0418\u0441\u043c\u0435\u043d\u0446\u044b"
    ],
    "name:und_x_variant":[
        "Smintsy",
        "Nyr-sola",
        "Nur-sola"
    ],
    "wof:name":"Ismentsy",
    "wof:placetype":"locality"
},
  "geometry": {"coordinates":[48.21395,55.97399],"type":"Point"}
}