{
  "type": "Feature",
  "properties": {
    "gn:admin1_code":"84",
    "gn:asciiname":"Standartnyy",
    "gn:country_code":"RU",
    "gn:dem":14,
    "gn:feature_class":"P",
    "gn:feature_code":"PPL",
    "gn:name":"Standartnyy",
    "gn:population":0,
    "gn:timezone":"Europe/Volgograd",
    "iso:country":"RU",
    "name:rus_x_preferred":[
        "\u0421\u0442\u0430\u043d\u0434\u0430\u0440\u0442\u043d\u044b\u0439"
    ],
    "wof:name":"Standartnyy",
    "wof:placetype":"locality"
},
  "geometry": {"coordinates":[44.94214,48.72036],"type":"Point"}
}