{
  "type": "Feature",
  "properties": {
    "gn:admin1_code":"47",
    "gn:asciiname":"Starkovo",
    "gn:country_code":"RU",
    "gn:dem":120,
    "gn:feature_class":"P",
    "gn:feature_code":"PPL",
    "gn:name":"Starkovo",
    "gn:population":0,
    "gn:timezone":"Europe/Moscow",
    "iso:country":"RU",
    "name:che_x_preferred":[
        "\u0421\u0442\u0430\u0440\u043a\u043e\u0432\u043e"
    ],
    "name:rus_x_preferred":[
        "\u0421\u0442\u0430\u0440\u043a\u043e\u0432\u043e"
    ],
    "name:und_x_variant":[
        "\u0421\u0442\u0430\u0440\u043a\u043e\u0432\u043e"
    ],
    "wof:name":"Starkovo",
    "wof:placetype":"locality"
},
  "geometry": {"coordinates":[38.30644,55.55615],"type":"Point"}
}