{
  "type": "Feature",
  "properties": {
    "gn:admin1_code":"42",
    "gn:asciiname":"Khumoze-Myaki",
    "gn:country_code":"RU",
    "gn:dem":65,
    "gn:feature_class":"P",
    "gn:feature_code":"PPL",
    "gn:name":"Khumoze-Myaki",
    "gn:population":0,
    "gn:timezone":"Europe/Moscow",
    "iso:country":"RU",
    "name:fin_x_preferred":[
        "Humusenm\u00e4ki"
    ],
    "name:rus_x_preferred":[
        "\u0425\u0443\u043c\u043e\u0437\u0435-\u041c\u044f\u043a\u0438"
    ],
    "wof:name":"Khumoze-Myaki",
    "wof:placetype":"locality"
},
  "geometry": {"coordinates":[30.58628,60.24595],"type":"Point"}
}