{
  "type": "Feature",
  "properties": {
    "gn:admin1_code":"60",
    "gn:asciiname":"Yelagino",
    "gn:country_code":"RU",
    "gn:dem":70,
    "gn:feature_class":"P",
    "gn:feature_code":"PPL",
    "gn:name":"Yelagino",
    "gn:population":0,
    "gn:timezone":"Europe/Moscow",
    "iso:country":"RU",
    "name:rus_x_preferred":[
        "\u0415\u043b\u0430\u0433\u0438\u043d\u043e"
    ],
    "wof:name":"Yelagino",
    "wof:placetype":"locality"
},
  "geometry": {"coordinates":[28.0974,57.2021],"type":"Point"}
}