{
  "type": "Feature",
  "properties": {
    "gn:admin1_code":"47",
    "gn:asciiname":"Bodrovo",
    "gn:country_code":"RU",
    "gn:dem":239,
    "gn:feature_class":"P",
    "gn:feature_code":"PPL",
    "gn:name":"Bodrovo",
    "gn:population":0,
    "gn:timezone":"Europe/Moscow",
    "iso:country":"RU",
    "name:bul_x_preferred":[
        "\u0411\u043e\u0434\u0440\u043e\u0432\u043e"
    ],
    "name:ceb_x_preferred":[
        "Bodrovo"
    ],
    "name:kaz_x_preferred":[
        "\u0411\u043e\u0434\u0440\u043e\u0432\u043e"
    ],
    "name:pol_x_preferred":[
        "Bodrowo"
    ],
    "name:ron_x_preferred":[
        "Bodrovo"
    ],
    "name:rus_x_preferred":[
        "\u0411\u043e\u0434\u0440\u043e\u0432\u043e"
    ],
    "name:swe_x_preferred":[
        "Bodrovo"
    ],
    "name:ukr_x_preferred":[
        "\u0411\u043e\u0434\u0440\u043e\u0432\u043e"
    ],
    "name:und_x_variant":[
        "\u0411\u043e\u0434\u0440\u043e\u0432\u043e"
    ],
    "wof:name":"Bodrovo",
    "wof:placetype":"locality"
},
  "geometry": {"coordinates":[36.5319,56.0361],"type":"Point"}
}