{
  "type": "Feature",
  "properties": {
    "gn:admin1_code":"51.0",
    "gn:asciiname":"Chernomuzh",
    "gn:country_code":"RU",
    "gn:dem":153,
    "gn:feature_class":"P",
    "gn:feature_code":"PPL",
    "gn:name":"Chernomuzh",
    "gn:population":0,
    "gn:timezone":"Europe/Moscow",
    "iso:country":"RU",
    "name:eng_x_preferred":[
        "Chernomuzh"
    ],
    "name:nor_x_preferred":[
        "Tsjernomuzj"
    ],
    "name:rus_x_preferred":[
        "\u0427\u0435\u0440\u043d\u043e\u043c\u0443\u0436"
    ],
    "wof:name":"Chernomuzh",
    "wof:placetype":"locality"
},
  "geometry": {"coordinates":[46.48038,57.12161],"type":"Point"}
}