{
  "type": "Feature",
  "properties": {
    "gn:admin1_code":"10",
    "gn:asciiname":"Verkhniye Leski",
    "gn:country_code":"RU",
    "gn:dem":188,
    "gn:feature_class":"P",
    "gn:feature_code":"PPL",
    "gn:name":"Verkhniye Leski",
    "gn:population":0,
    "gn:timezone":"Europe/Moscow",
    "iso:country":"RU",
    "name:rus_x_preferred":[
        "\u0412\u0435\u0440\u0445\u043d\u0438\u0435 \u041b\u0435\u0441\u043a\u0438"
    ],
    "name:und_x_variant":[
        "Leski"
    ],
    "wof:name":"Verkhniye Leski",
    "wof:placetype":"locality"
},
  "geometry": {"coordinates":[34.7266,52.4869],"type":"Point"}
}