{
  "type": "Feature",
  "properties": {
    "gn:admin1_code":"73",
    "gn:asciiname":"Utyashkino",
    "gn:country_code":"RU",
    "gn:dem":93,
    "gn:feature_class":"P",
    "gn:feature_code":"PPL",
    "gn:name":"Utyashkino",
    "gn:population":0,
    "gn:timezone":"Europe/Moscow",
    "iso:country":"RU",
    "name:eng_x_preferred":[
        "Utyashkino"
    ],
    "name:nor_x_preferred":[
        "Utjasjkino"
    ],
    "name:rus_x_preferred":[
        "\u0423\u0442\u044f\u0448\u043a\u0438\u043d\u043e"
    ],
    "wof:name":"Utyashkino",
    "wof:placetype":"locality"
},
  "geometry": {"coordinates":[52.06795,55.13721],"type":"Point"}
}