{
  "type": "Feature",
  "properties": {
    "gn:admin1_code":"90.0",
    "gn:asciiname":"Vashury",
    "gn:country_code":"RU",
    "gn:dem":120,
    "gn:feature_class":"P",
    "gn:feature_code":"PPL",
    "gn:name":"Vashury",
    "gn:population":0,
    "gn:timezone":"Asia/Yekaterinburg",
    "iso:country":"RU",
    "name:che_x_preferred":[
        "\u0412\u0430\u0448\u0443\u0440\u044b"
    ],
    "name:rus_x_preferred":[
        "\u0412\u0430\u0448\u0443\u0440\u044b"
    ],
    "wof:name":"Vashury",
    "wof:placetype":"locality"
},
  "geometry": {"coordinates":[56.31853,57.91178000000001],"type":"Point"}
}