{
  "type": "Feature",
  "properties": {
    "gn:admin1_code":"91",
    "gn:asciiname":"Yukta",
    "gn:country_code":"RU",
    "gn:dem":224,
    "gn:feature_class":"P",
    "gn:feature_code":"PPL",
    "gn:name":"Yukta",
    "gn:population":0,
    "gn:timezone":"Asia/Krasnoyarsk",
    "iso:country":"RU",
    "name:eng_x_preferred":[
        "Yukta"
    ],
    "name:nor_x_preferred":[
        "Jukta"
    ],
    "name:rus_x_preferred":[
        "\u042e\u043a\u0442\u0430"
    ],
    "wof:name":"Yukta",
    "wof:placetype":"locality"
},
  "geometry": {"coordinates":[105.66694,63.38389],"type":"Point"}
}