{
  "type": "Feature",
  "properties": {
    "gn:admin1_code":"46",
    "gn:asciiname":"Muran'",
    "gn:country_code":"RU",
    "gn:dem":193,
    "gn:feature_class":"P",
    "gn:feature_code":"PPL",
    "gn:name":"Muran\u2019",
    "gn:population":0,
    "gn:timezone":"Europe/Moscow",
    "iso:country":"RU",
    "name:rus_x_preferred":[
        "\u041c\u0443\u0440\u0430\u043d\u044c"
    ],
    "name:und_x_variant":[
        "Muran\u2019"
    ],
    "wof:name":"Muran'",
    "wof:placetype":"locality"
},
  "geometry": {"coordinates":[45.5526,54.04273000000001],"type":"Point"}
}