{
  "type": "Feature",
  "properties": {
    "gn:admin1_code":"63",
    "gn:asciiname":"Cherkelekh",
    "gn:country_code":"RU",
    "gn:dem":171,
    "gn:feature_class":"P",
    "gn:feature_code":"PPL",
    "gn:name":"Cherkelekh",
    "gn:population":0,
    "gn:timezone":"Asia/Yakutsk",
    "iso:country":"RU",
    "name:rus_x_preferred":[
        "\u0427\u0435\u0440\u043a\u0435\u043b\u0435\u0445"
    ],
    "name:und_x_variant":[
        "\u0427\u0435\u0440\u043a\u0435\u043b\u0435\u0445"
    ],
    "wof:name":"Cherkelekh",
    "wof:placetype":"locality"
},
  "geometry": {"coordinates":[126.59999999999999,63.03333000000001],"type":"Point"}
}