{
  "type": "Feature",
  "properties": {
    "gn:admin1_code":"45",
    "gn:asciiname":"Vocharma",
    "gn:country_code":"RU",
    "gn:dem":165,
    "gn:feature_class":"P",
    "gn:feature_code":"PPL",
    "gn:name":"Vocharma",
    "gn:population":0,
    "gn:timezone":"Europe/Moscow",
    "iso:country":"RU",
    "name:rus_x_preferred":[
        "\u0412\u043e\u0447\u0430\u0440\u043c\u0430"
    ],
    "name:und_x_variant":[
        "Vacherma",
        "Vocharma"
    ],
    "wof:name":"Vocharma",
    "wof:placetype":"locality"
},
  "geometry": {"coordinates":[49.41389,56.82722],"type":"Point"}
}