{
  "type": "Feature",
  "properties": {
    "gn:admin1_code":"62",
    "gn:asciiname":"Kolesnya",
    "gn:country_code":"RU",
    "gn:dem":157,
    "gn:feature_class":"P",
    "gn:feature_code":"PPL",
    "gn:name":"Kol\u00ebsnya",
    "gn:population":0,
    "gn:timezone":"Europe/Moscow",
    "iso:country":"RU",
    "name:rus_x_preferred":[
        "\u041a\u043e\u043b\u0451\u0441\u043d\u044f"
    ],
    "name:und_x_variant":[
        "Kol\u00ebsnya",
        "\u041a\u043e\u043b\u0451\u0441\u043d\u044f"
    ],
    "wof:name":"Kolesnya",
    "wof:placetype":"locality"
},
  "geometry": {"coordinates":[39.3961,54.4675],"type":"Point"}
}