{
  "type": "Feature",
  "properties": {
    "gn:admin1_code":"47",
    "gn:asciiname":"Gribanovo",
    "gn:country_code":"RU",
    "gn:dem":210,
    "gn:feature_class":"P",
    "gn:feature_code":"PPL",
    "gn:name":"Gribanovo",
    "gn:population":0,
    "gn:timezone":"Europe/Moscow",
    "iso:country":"RU",
    "name:che_x_preferred":[
        "\u0413\u0440\u0438\u0431\u0430\u043d\u043e\u0432\u043e"
    ],
    "name:rus_x_preferred":[
        "\u0413\u0440\u0438\u0431\u0430\u043d\u043e\u0432\u043e"
    ],
    "name:und_x_variant":[
        "\u0413\u0440\u0438\u0431\u0430\u043d\u043e\u0432\u043e"
    ],
    "wof:name":"Gribanovo",
    "wof:placetype":"locality"
},
  "geometry": {"coordinates":[37.86667,56.18333000000001],"type":"Point"}
}