{
  "type": "Feature",
  "properties": {
    "gn:admin1_code":"69",
    "gn:asciiname":"Pustosel",
    "gn:country_code":"RU",
    "gn:dem":176,
    "gn:feature_class":"P",
    "gn:feature_code":"PPL",
    "gn:name":"Pustos\u00ebl",
    "gn:population":0,
    "gn:timezone":"Europe/Moscow",
    "iso:country":"RU",
    "name:rus_x_preferred":[
        "\u041f\u0443\u0441\u0442\u043e\u0441\u0451\u043b"
    ],
    "name:und_x_variant":[
        "Pustos\u00ebl"
    ],
    "wof:name":"Pustosel",
    "wof:placetype":"locality"
},
  "geometry": {"coordinates":[32.50861,53.87111],"type":"Point"}
}