{
  "type": "Feature",
  "properties": {
    "gn:admin1_code":"45.0",
    "gn:asciiname":"Aymetovo",
    "gn:country_code":"RU",
    "gn:dem":149,
    "gn:feature_class":"P",
    "gn:feature_code":"PPL",
    "gn:name":"Aymetovo",
    "gn:population":0,
    "gn:timezone":"Europe/Moscow",
    "iso:country":"RU",
    "name:nor_x_preferred":[
        "Ajmetovo"
    ],
    "name:rus_x_preferred":[
        "\u0410\u0439\u043c\u0435\u0442\u043e\u0432\u043e"
    ],
    "wof:name":"Aymetovo",
    "wof:placetype":"locality"
},
  "geometry": {"coordinates":[48.30139000000001,56.64278],"type":"Point"}
}