{
  "type": "Feature",
  "properties": {
    "gn:admin1_code":"80.0",
    "gn:asciiname":"Chekan",
    "gn:country_code":"RU",
    "gn:dem":189,
    "gn:feature_class":"P",
    "gn:feature_code":"PPL",
    "gn:name":"Chekan",
    "gn:population":0,
    "gn:timezone":"Europe/Samara",
    "iso:country":"RU",
    "name:eng_x_preferred":[
        "Chekan"
    ],
    "name:fas_x_preferred":[
        "\u0686\u06a9\u0627\u0646"
    ],
    "name:msa_x_preferred":[
        "Chekan"
    ],
    "name:nor_x_preferred":[
        "Tsjekan"
    ],
    "name:rus_x_preferred":[
        "\u0427\u0435\u043a\u0430\u043d"
    ],
    "wof:name":"Chekan",
    "wof:placetype":"locality"
},
  "geometry": {"coordinates":[52.66396999999999,57.113],"type":"Point"}
}