{
  "type": "Feature",
  "properties": {
    "gn:admin1_code":"69",
    "gn:asciiname":"Malaya Bobrovka",
    "gn:country_code":"RU",
    "gn:dem":189,
    "gn:feature_class":"P",
    "gn:feature_code":"PPL",
    "gn:name":"Malaya Bobrovka",
    "gn:population":0,
    "gn:timezone":"Europe/Moscow",
    "iso:country":"RU",
    "name:rus_x_preferred":[
        "\u041c\u0430\u043b\u0430\u044f \u0411\u043e\u0431\u0440\u043e\u0432\u043a\u0430"
    ],
    "name:und_x_variant":[
        "\u041c\u0430\u043b\u0430\u044f \u0411\u043e\u0431\u0440\u043e\u0432\u043a\u0430"
    ],
    "wof:name":"Malaya Bobrovka",
    "wof:placetype":"locality"
},
  "geometry": {"coordinates":[34.16667,54.55],"type":"Point"}
}