{
  "type": "Feature",
  "properties": {
    "gn:admin1_code":"71",
    "gn:asciiname":"Lapotkova",
    "gn:country_code":"RU",
    "gn:dem":63,
    "gn:feature_class":"P",
    "gn:feature_code":"PPL",
    "gn:name":"Lapotkova",
    "gn:population":0,
    "gn:timezone":"Asia/Yekaterinburg",
    "iso:country":"RU",
    "name:eng_x_preferred":[
        "Lapotkova"
    ],
    "name:nor_x_preferred":[
        "Lapotkova"
    ],
    "name:rus_x_preferred":[
        "\u041b\u0430\u043f\u043e\u0442\u043a\u043e\u0432\u0430"
    ],
    "name:und_x_variant":[
        "Lapotnova",
        "Lopatkova"
    ],
    "wof:name":"Lapotkova",
    "wof:placetype":"locality"
},
  "geometry": {"coordinates":[63.36183000000001,59.38478000000001],"type":"Point"}
}