{
  "type": "Feature",
  "properties": {
    "gn:admin1_code":"51",
    "gn:asciiname":"Rumstikha",
    "gn:country_code":"RU",
    "gn:dem":182,
    "gn:feature_class":"P",
    "gn:feature_code":"PPL",
    "gn:name":"Rumstikha",
    "gn:population":0,
    "gn:timezone":"Europe/Moscow",
    "iso:country":"RU",
    "name:eng_x_preferred":[
        "Rumstikha"
    ],
    "name:nor_x_preferred":[
        "Rumstikha"
    ],
    "name:rus_x_preferred":[
        "\u0420\u0443\u043c\u0441\u0442\u0438\u0445\u0430"
    ],
    "name:und_x_variant":[
        "\u0420\u0443\u043c\u0441\u0442\u0438\u0445\u0430",
        "Rumstikha"
    ],
    "wof:name":"Rumstikha",
    "wof:placetype":"locality"
},
  "geometry": {"coordinates":[43.98445,55.71388],"type":"Point"}
}