{
  "type": "Feature",
  "properties": {
    "gn:admin1_code":"71",
    "gn:asciiname":"Povarnya",
    "gn:country_code":"RU",
    "gn:dem":212,
    "gn:feature_class":"P",
    "gn:feature_code":"PPL",
    "gn:name":"Povarnya",
    "gn:population":0,
    "gn:timezone":"Asia/Yekaterinburg",
    "iso:country":"RU",
    "name:eng_x_preferred":[
        "Povarnya"
    ],
    "name:nor_x_preferred":[
        "Povarnja"
    ],
    "name:rus_x_preferred":[
        "\u041f\u043e\u0432\u0430\u0440\u043d\u044f"
    ],
    "name:und_x_variant":[
        "\u041f\u043e\u0432\u0430\u0440\u043d\u044f",
        "Povarnya"
    ],
    "wof:name":"Povarnya",
    "wof:placetype":"locality"
},
  "geometry": {"coordinates":[60.98688000000001,56.70264],"type":"Point"}
}