{
  "type": "Feature",
  "properties": {
    "gn:admin1_code":"73",
    "gn:asciiname":"Novyye Bavly",
    "gn:country_code":"RU",
    "gn:dem":112,
    "gn:feature_class":"P",
    "gn:feature_code":"PPL",
    "gn:name":"Novyye Bavly",
    "gn:population":0,
    "gn:timezone":"Asia/Yekaterinburg",
    "iso:country":"RU",
    "name:rus_x_preferred":[
        "\u041d\u043e\u0432\u044b\u0435 \u0411\u0430\u0432\u043b\u044b"
    ],
    "name:und_x_variant":[
        "Malyye Bavly",
        "Novyye Bavly"
    ],
    "wof:name":"Novyye Bavly",
    "wof:placetype":"locality"
},
  "geometry": {"coordinates":[53.37981,54.37129],"type":"Point"}
}