{
  "type": "Feature",
  "properties": {
    "gn:admin1_code":"69",
    "gn:asciiname":"Loz'ya",
    "gn:country_code":"RU",
    "gn:dem":210,
    "gn:feature_class":"P",
    "gn:feature_code":"PPL",
    "gn:name":"Loz\u2019ya",
    "gn:population":0,
    "gn:timezone":"Europe/Moscow",
    "iso:country":"RU",
    "wof:name":"Loz'ya",
    "wof:placetype":"locality"
},
  "geometry": {"coordinates":[33.47889,54.70083],"type":"Point"}
}