{
  "type": "Feature",
  "properties": {
    "gn:admin1_code":"10.0",
    "gn:asciiname":"Bystra",
    "gn:country_code":"RU",
    "gn:dem":136,
    "gn:feature_class":"P",
    "gn:feature_code":"PPL",
    "gn:name":"Bystra",
    "gn:population":0,
    "gn:timezone":"Europe/Moscow",
    "iso:country":"RU",
    "name:ceb_x_preferred":[
        "Bystra"
    ],
    "name:deu_x_preferred":[
        "Bystra"
    ],
    "name:ita_x_preferred":[
        "Bystra"
    ],
    "name:nld_x_preferred":[
        "Bystra"
    ],
    "name:pol_x_preferred":[
        "Bystra"
    ],
    "name:rus_x_preferred":[
        "\u0411\u044b\u0441\u0442\u0440\u0430"
    ],
    "name:swe_x_preferred":[
        "Bystra"
    ],
    "name:ukr_x_preferred":[
        "\u0411\u0438\u0441\u0442\u0440\u0430"
    ],
    "wof:name":"Bystra",
    "wof:placetype":"locality"
},
  "geometry": {"coordinates":[31.9239,52.2257],"type":"Point"}
}