{
  "type": "Feature",
  "properties": {
    "gn:admin1_code":"77",
    "gn:asciiname":"Verigino",
    "gn:country_code":"RU",
    "gn:dem":200,
    "gn:feature_class":"P",
    "gn:feature_code":"PPL",
    "gn:name":"Verigino",
    "gn:population":0,
    "gn:timezone":"Europe/Moscow",
    "iso:country":"RU",
    "name:eng_x_preferred":[
        "Verigino"
    ],
    "name:nor_x_preferred":[
        "Verigino"
    ],
    "name:rus_x_preferred":[
        "\u0412\u0435\u0440\u0438\u0433\u0438\u043d\u043e"
    ],
    "wof:name":"Verigino",
    "wof:placetype":"locality"
},
  "geometry": {"coordinates":[34.45158,56.10112],"type":"Point"}
}