{
  "type": "Feature",
  "properties": {
    "gn:admin1_code":"85",
    "gn:asciiname":"Sukhany",
    "gn:cc2":"RU",
    "gn:country_code":"RU",
    "gn:dem":145,
    "gn:feature_class":"P",
    "gn:feature_code":"PPL",
    "gn:name":"Sukhany",
    "gn:population":0,
    "gn:timezone":"Europe/Moscow",
    "iso:country":"RU",
    "name:rus_x_preferred":[
        "\u0421\u0443\u0445\u0430\u043d\u044b"
    ],
    "name:und_x_variant":[
        "Suhani",
        "Sukhany",
        "\u0421\u0443\u0445\u0430\u043d\u044b"
    ],
    "wof:name":"Sukhany",
    "wof:placetype":"locality"
},
  "geometry": {"coordinates":[36.65,60.96666999999999],"type":"Point"}
}