{
  "type": "Feature",
  "properties": {
    "gn:admin1_code":"42",
    "gn:asciiname":"Matveyevskoye",
    "gn:country_code":"RU",
    "gn:dem":188,
    "gn:feature_class":"P",
    "gn:feature_code":"PPL",
    "gn:name":"Matveyevskoye",
    "gn:population":0,
    "gn:timezone":"Europe/Moscow",
    "iso:country":"RU",
    "name:rus_x_preferred":[
        "\u041c\u0430\u0442\u0432\u0435\u0435\u0432\u0441\u043a\u043e\u0435"
    ],
    "wof:name":"Matveyevskoye",
    "wof:placetype":"locality"
},
  "geometry": {"coordinates":[34.28333,59.5025],"type":"Point"}
}