{
  "type": "Feature",
  "properties": {
    "gn:admin1_code":"41",
    "gn:asciiname":"Vtoroy Lipovets",
    "gn:country_code":"RU",
    "gn:dem":186,
    "gn:feature_class":"P",
    "gn:feature_code":"PPL",
    "gn:name":"Vtoroy Lipovets",
    "gn:population":0,
    "gn:timezone":"Europe/Moscow",
    "iso:country":"RU",
    "name:rus_x_preferred":[
        "\u0412\u0442\u043e\u0440\u043e\u0439 \u041b\u0438\u043f\u043e\u0432\u0435\u0446"
    ],
    "wof:name":"Vtoroy Lipovets",
    "wof:placetype":"locality"
},
  "geometry": {"coordinates":[35.9086,51.3476],"type":"Point"}
}