{
  "type": "Feature",
  "properties": {
    "gn:admin1_code":"33.0",
    "gn:asciiname":"Titovy",
    "gn:country_code":"RU",
    "gn:dem":120,
    "gn:feature_class":"P",
    "gn:feature_code":"PPL",
    "gn:name":"Titovy",
    "gn:population":0,
    "gn:timezone":"Europe/Kirov",
    "iso:country":"RU",
    "name:rus_x_preferred":[
        "\u0422\u0438\u0442\u043e\u0432\u044b"
    ],
    "wof:name":"Titovy",
    "wof:placetype":"locality"
},
  "geometry": {"coordinates":[48.26254,57.99638],"type":"Point"}
}