{
  "type": "Feature",
  "properties": {
    "gn:admin1_code":"33.0",
    "gn:asciiname":"Arkhangel'skoye",
    "gn:country_code":"RU",
    "gn:dem":97,
    "gn:feature_class":"P",
    "gn:feature_code":"PPL",
    "gn:name":"Arkhangel\u2019skoye",
    "gn:population":0,
    "gn:timezone":"Europe/Kirov",
    "iso:country":"RU",
    "name:eng_x_preferred":[
        "Arkhangel'skoye"
    ],
    "name:nor_x_preferred":[
        "Arkhangelskoje"
    ],
    "name:rus_x_preferred":[
        "\u0410\u0440\u0445\u0430\u043d\u0433\u0435\u043b\u044c\u0441\u043a\u043e\u0435"
    ],
    "name:und_x_variant":[
        "Arkhangel\u2019skoye"
    ],
    "wof:name":"Arkhangel'skoye",
    "wof:placetype":"locality"
},
  "geometry": {"coordinates":[49.83408,57.12857],"type":"Point"}
}