{
  "type": "Feature",
  "properties": {
    "gn:admin1_code":"16",
    "gn:asciiname":"Staroye Sheptakhovo",
    "gn:country_code":"RU",
    "gn:dem":145,
    "gn:feature_class":"P",
    "gn:feature_code":"PPL",
    "gn:name":"Staroye Sheptakhovo",
    "gn:population":0,
    "gn:timezone":"Europe/Moscow",
    "iso:country":"RU",
    "name:rus_x_preferred":[
        "\u0421\u0442\u0430\u0440\u043e\u0435 \u0428\u0435\u043f\u0442\u0430\u0445\u043e\u0432\u043e"
    ],
    "name:und_x_variant":[
        "Staryye Sheptakhi",
        "Stayye Sheptakhi",
        "Staroye Sheptakhovo"
    ],
    "wof:name":"Staroye Sheptakhovo",
    "wof:placetype":"locality"
},
  "geometry": {"coordinates":[47.8529,55.72059],"type":"Point"}
}