{
  "type": "Feature",
  "properties": {
    "gn:admin1_code":"37",
    "gn:asciiname":"Novoselki",
    "gn:country_code":"RU",
    "gn:dem":120,
    "gn:feature_class":"P",
    "gn:feature_code":"PPL",
    "gn:name":"Novos\u00eblki",
    "gn:population":0,
    "gn:timezone":"Europe/Moscow",
    "iso:country":"RU",
    "name:lav_x_preferred":[
        "Novoselki"
    ],
    "wof:name":"Novoselki",
    "wof:placetype":"locality"
},
  "geometry": {"coordinates":[41.42083,58.7206],"type":"Point"}
}