{
  "type": "Feature",
  "properties": {
    "gn:admin1_code":"46",
    "gn:asciiname":"Mordovskiye Dubrovki",
    "gn:country_code":"RU",
    "gn:dem":207,
    "gn:feature_class":"P",
    "gn:feature_code":"PPL",
    "gn:name":"Mordovskiye Dubrovki",
    "gn:population":0,
    "gn:timezone":"Europe/Moscow",
    "iso:country":"RU",
    "name:rus_x_preferred":[
        "\u041c\u043e\u0440\u0434\u043e\u0432\u0441\u043a\u0438\u0435 \u0414\u0443\u0431\u0440\u043e\u0432\u043a\u0438"
    ],
    "name:und_x_variant":[
        "\u041c\u043e\u0440\u0434\u043e\u0432\u0441\u043a\u0438\u0435 \u0414\u0443\u0431\u0440\u043e\u0432\u043a\u0438"
    ],
    "wof:name":"Mordovskiye Dubrovki",
    "wof:placetype":"locality"
},
  "geometry": {"coordinates":[46.29418,54.59032],"type":"Point"}
}