{
  "type": "Feature",
  "properties": {
    "gn:admin1_code":"76",
    "gn:asciiname":"Maloye Bizyukino",
    "gn:country_code":"RU",
    "gn:dem":181,
    "gn:feature_class":"P",
    "gn:feature_code":"PPL",
    "gn:name":"Maloye Bizyukino",
    "gn:population":0,
    "gn:timezone":"Europe/Moscow",
    "iso:country":"RU",
    "name:und_x_variant":[
        "Maloye Bezyukino"
    ],
    "wof:name":"Maloye Bizyukino",
    "wof:placetype":"locality"
},
  "geometry": {"coordinates":[37.24439,54.39227],"type":"Point"}
}