{
  "type": "Feature",
  "properties": {
    "gn:admin1_code":"13",
    "gn:asciiname":"Mikhaylovskiy",
    "gn:country_code":"RU",
    "gn:dem":322,
    "gn:feature_class":"P",
    "gn:feature_code":"PPL",
    "gn:name":"Mikhaylovskiy",
    "gn:population":0,
    "gn:timezone":"Asia/Yekaterinburg",
    "iso:country":"RU",
    "name:rus_x_preferred":[
        "\u041c\u0438\u0445\u0430\u0439\u043b\u043e\u0432\u0441\u043a\u0438\u0439"
    ],
    "wof:name":"Mikhaylovskiy",
    "wof:placetype":"locality"
},
  "geometry": {"coordinates":[60.75,54.55],"type":"Point"}
}