{
  "type": "Feature",
  "properties": {
    "gn:admin1_code":"76.0",
    "gn:asciiname":"Borozdenki",
    "gn:country_code":"RU",
    "gn:dem":199,
    "gn:feature_class":"P",
    "gn:feature_code":"PPL",
    "gn:name":"Borozd\u00ebnki",
    "gn:population":0,
    "gn:timezone":"Europe/Moscow",
    "iso:country":"RU",
    "name:rus_x_preferred":[
        "\u0411\u043e\u0440\u043e\u0437\u0434\u0451\u043d\u043a\u0438"
    ],
    "name:und_x_variant":[
        "Brozd\u00ebnki",
        "Borozd\u00ebnki"
    ],
    "wof:name":"Borozdenki",
    "wof:placetype":"locality"
},
  "geometry": {"coordinates":[38.28584,54.48302],"type":"Point"}
}