{
  "type": "Feature",
  "properties": {
    "gn:admin1_code":"59.0",
    "gn:asciiname":"Kiparisovo-2",
    "gn:country_code":"RU",
    "gn:dem":11,
    "gn:feature_class":"P",
    "gn:feature_code":"PPL",
    "gn:name":"\u041a\u0438\u043f\u0430\u0440\u0438\u0441\u043e\u0432\u043e-2",
    "gn:population":676,
    "gn:timezone":"Asia/Vladivostok",
    "iso:country":"RU",
    "wof:name":"Kiparisovo-2",
    "wof:placetype":"locality",
    "wof:population":676
},
  "geometry": {"coordinates":[131.9331,43.44818],"type":"Point"}
}