{
  "type": "Feature",
  "properties": {
    "gn:admin1_code":"23",
    "gn:asciiname":"Pridorozhnoye",
    "gn:country_code":"RU",
    "gn:dem":21,
    "gn:feature_class":"P",
    "gn:feature_code":"PPL",
    "gn:name":"Pridorozhnoye",
    "gn:population":0,
    "gn:timezone":"Europe/Kaliningrad",
    "iso:country":"RU",
    "name:eng_x_preferred":[
        "Pridorozhnoye"
    ],
    "name:nor_x_preferred":[
        "Pridorozjnoje"
    ],
    "name:rus_x_preferred":[
        "\u041f\u0440\u0438\u0434\u043e\u0440\u043e\u0436\u043d\u043e\u0435"
    ],
    "name:und_x_variant":[
        "Zesslyaken",
        "\u041f\u0440\u0438\u0434\u043e\u0440\u043e\u0436\u043d\u043e\u0435",
        "Pridorozhnoye"
    ],
    "wof:name":"Pridorozhnoye",
    "wof:placetype":"locality"
},
  "geometry": {"coordinates":[21.96911,54.7689],"type":"Point"}
}