{
  "type": "Feature",
  "properties": {
    "gn:admin1_code":"9.0",
    "gn:asciiname":"Dubrovka",
    "gn:country_code":"RU",
    "gn:dem":170,
    "gn:feature_class":"P",
    "gn:feature_code":"PPL",
    "gn:name":"Dubrovka",
    "gn:population":0,
    "gn:timezone":"Europe/Moscow",
    "iso:country":"RU",
    "name:rus_x_preferred":[
        "\u0414\u0443\u0431\u0440\u043e\u0432\u043a\u0430"
    ],
    "name:und_x_variant":[
        "Dubravki",
        "Dubrovka"
    ],
    "wof:name":"Dubrovka",
    "wof:placetype":"locality"
},
  "geometry": {"coordinates":[37.7229,50.2404],"type":"Point"}
}