{
  "type": "Feature",
  "properties": {
    "gn:admin1_code":"77",
    "gn:asciiname":"Tukovo",
    "gn:country_code":"RU",
    "gn:dem":191,
    "gn:feature_class":"P",
    "gn:feature_code":"PPL",
    "gn:name":"Tukovo",
    "gn:population":0,
    "gn:timezone":"Europe/Moscow",
    "iso:country":"RU",
    "name:rus_x_preferred":[
        "\u0422\u0443\u043a\u043e\u0432\u043e"
    ],
    "name:und_x_variant":[
        "\u0422\u0443\u043a\u043e\u0432\u043e"
    ],
    "wof:name":"Tukovo",
    "wof:placetype":"locality"
},
  "geometry": {"coordinates":[36.6336,58.4329],"type":"Point"}
}