{
  "type": "Feature",
  "properties": {
    "gn:admin1_code":"41",
    "gn:asciiname":"Paserkovo",
    "gn:country_code":"RU",
    "gn:dem":184,
    "gn:feature_class":"P",
    "gn:feature_code":"PPL",
    "gn:name":"Paserkovo",
    "gn:population":0,
    "gn:timezone":"Europe/Moscow",
    "iso:country":"RU",
    "name:rus_x_preferred":[
        "\u041f\u0430\u0441\u0435\u0440\u043a\u043e\u0432\u043e"
    ],
    "name:und_x_variant":[
        "Passerkovo",
        "Paserkovo"
    ],
    "wof:name":"Paserkovo",
    "wof:placetype":"locality"
},
  "geometry": {"coordinates":[35.4806,52.3832],"type":"Point"}
}