{
  "type": "Feature",
  "properties": {
    "gn:admin1_code":"84",
    "gn:asciiname":"Rodnichki",
    "gn:country_code":"RU",
    "gn:dem":156,
    "gn:feature_class":"P",
    "gn:feature_code":"PPL",
    "gn:name":"Rodnichki",
    "gn:population":0,
    "gn:timezone":"Europe/Volgograd",
    "iso:country":"RU",
    "name:rus_x_preferred":[
        "\u0420\u043e\u0434\u043d\u0438\u0447\u043a\u0438"
    ],
    "wof:name":"Rodnichki",
    "wof:placetype":"locality"
},
  "geometry": {"coordinates":[41.675,50.13056],"type":"Point"}
}