{
  "type": "Feature",
  "properties": {
    "gn:admin1_code":"85.0",
    "gn:asciiname":"Antsiferovskaya",
    "gn:country_code":"RU",
    "gn:dem":187,
    "gn:feature_class":"P",
    "gn:feature_code":"PPL",
    "gn:name":"Antsiferovskaya",
    "gn:population":0,
    "gn:timezone":"Europe/Moscow",
    "iso:country":"RU",
    "name:eng_x_preferred":[
        "Antsiferovskaya"
    ],
    "name:nor_x_preferred":[
        "Antsiferovskaja"
    ],
    "name:rus_x_preferred":[
        "\u0410\u043d\u0446\u0438\u0444\u0435\u0440\u043e\u0432\u0441\u043a\u0430\u044f"
    ],
    "name:und_x_variant":[
        "\u0410\u043d\u0446\u0438\u0444\u0435\u0440\u043e\u0432\u0441\u043a\u0430\u044f",
        "Antsiferovskaya"
    ],
    "wof:name":"Antsiferovskaya",
    "wof:placetype":"locality"
},
  "geometry": {"coordinates":[39.8322,60.57100000000001],"type":"Point"}
}