{
  "type": "Feature",
  "properties": {
    "gn:admin1_code":"6",
    "gn:asciiname":"Kal'chino",
    "gn:country_code":"RU",
    "gn:dem":2,
    "gn:feature_class":"P",
    "gn:feature_code":"PPL",
    "gn:name":"Kal\u2019chino",
    "gn:population":0,
    "gn:timezone":"Europe/Moscow",
    "iso:country":"RU",
    "name:rus_x_preferred":[
        "\u041a\u0430\u043b\u044c\u0447\u0438\u043d\u043e"
    ],
    "name:und_x_variant":[
        "Kal\u2019chino",
        "\u041a\u0430\u043b\u044c\u0447\u0438\u043d\u043e"
    ],
    "wof:name":"Kal'chino",
    "wof:placetype":"locality"
},
  "geometry": {"coordinates":[40.4335,64.5767],"type":"Point"}
}