{
  "type": "Feature",
  "properties": {
    "gn:admin1_code":"56",
    "gn:asciiname":"Klyushniki",
    "gn:country_code":"RU",
    "gn:dem":201,
    "gn:feature_class":"P",
    "gn:feature_code":"PPL",
    "gn:name":"Klyushniki",
    "gn:population":0,
    "gn:timezone":"Europe/Moscow",
    "iso:country":"RU",
    "name:rus_x_preferred":[
        "\u041a\u043b\u044e\u0448\u043d\u0438\u043a\u0438"
    ],
    "name:und_x_variant":[
        "\u041a\u043b\u044e\u0448\u043d\u0438\u043a\u0438"
    ],
    "wof:name":"Klyushniki",
    "wof:placetype":"locality"
},
  "geometry": {"coordinates":[37.34645,52.35994],"type":"Point"}
}