{
  "type": "Feature",
  "properties": {
    "gn:admin1_code":"3",
    "gn:asciiname":"Talitsa",
    "gn:country_code":"RU",
    "gn:dem":746,
    "gn:feature_class":"P",
    "gn:feature_code":"PPL",
    "gn:name":"Talitsa",
    "gn:population":0,
    "gn:timezone":"Asia/Omsk",
    "iso:country":"RU",
    "name:eng_x_preferred":[
        "Talitsa"
    ],
    "name:nor_x_preferred":[
        "Talitsa"
    ],
    "name:rus_x_preferred":[
        "\u0422\u0430\u043b\u0438\u0446\u0430"
    ],
    "name:und_x_variant":[
        "Chagulikha",
        "Talitsa"
    ],
    "wof:name":"Talitsa",
    "wof:placetype":"locality"
},
  "geometry": {"coordinates":[84.31189999999999,51.0372],"type":"Point"}
}