{
  "type": "Feature",
  "properties": {
    "gn:admin1_code":"77.0",
    "gn:asciiname":"Bol'shoye Zvyagino",
    "gn:country_code":"RU",
    "gn:dem":187,
    "gn:feature_class":"P",
    "gn:feature_code":"PPL",
    "gn:name":"Bol\u2019shoye Zvyagino",
    "gn:population":0,
    "gn:timezone":"Europe/Moscow",
    "iso:country":"RU",
    "name:rus_x_preferred":[
        "\u0411\u043e\u043b\u044c\u0448\u043e\u0435 \u0417\u0432\u044f\u0433\u0438\u043d\u043e"
    ],
    "name:und_x_variant":[
        "Zvyagino",
        "Zvyagina",
        "Bol\u2019shoye Zvyagino"
    ],
    "wof:name":"Bol'shoye Zvyagino",
    "wof:placetype":"locality"
},
  "geometry": {"coordinates":[35.57219,57.161],"type":"Point"}
}