{
  "type": "Feature",
  "properties": {
    "gn:admin1_code":"28",
    "gn:asciiname":"Patrovo",
    "gn:country_code":"RU",
    "gn:dem":60,
    "gn:feature_class":"P",
    "gn:feature_code":"PPL",
    "gn:name":"Patrovo",
    "gn:population":0,
    "gn:timezone":"Europe/Moscow",
    "iso:country":"RU",
    "name:eng_x_preferred":[
        "Patrovo"
    ],
    "name:fin_x_preferred":[
        "Hoimolahti"
    ],
    "name:nor_x_preferred":[
        "Patrovo"
    ],
    "name:rus_x_preferred":[
        "\u041f\u0430\u0442\u0440\u043e\u0432\u043e"
    ],
    "name:und_x_variant":[
        "Partovo",
        "Parovo",
        "Patrova",
        "\u041f\u0430\u0442\u0440\u043e\u0432\u043e",
        "Patrovo"
    ],
    "wof:name":"Patrovo",
    "wof:placetype":"locality"
},
  "geometry": {"coordinates":[35.1449,62.44499],"type":"Point"}
}