{
  "type": "Feature",
  "properties": {
    "gn:admin1_code":"49",
    "gn:asciiname":"Ruchey Vtoroy",
    "gn:country_code":"RU",
    "gn:dem":1,
    "gn:feature_class":"P",
    "gn:feature_code":"PPL",
    "gn:name":"Ruchey Vtoroy",
    "gn:population":0,
    "gn:timezone":"Europe/Moscow",
    "iso:country":"RU",
    "name:rus_x_preferred":[
        "\u0420\u0443\u0447\u0435\u0439 \u0412\u0442\u043e\u0440\u043e\u0439"
    ],
    "name:und_x_variant":[
        "\u0420\u0443\u0447\u0435\u0439 \u0412\u0442\u043e\u0440\u043e\u0439"
    ],
    "wof:name":"Ruchey Vtoroy",
    "wof:placetype":"locality"
},
  "geometry": {"coordinates":[33.01667,68.93333],"type":"Point"}
}