{
  "type": "Feature",
  "properties": {
    "gn:admin1_code":"86.0",
    "gn:asciiname":"Gor'kogo",
    "gn:country_code":"RU",
    "gn:dem":154,
    "gn:feature_class":"P",
    "gn:feature_code":"PPL",
    "gn:name":"Gor\u2019kogo",
    "gn:population":0,
    "gn:timezone":"Europe/Moscow",
    "iso:country":"RU",
    "name:rus_x_preferred":[
        "\u0413\u043e\u0440\u044c\u043a\u043e\u0433\u043e"
    ],
    "name:und_x_variant":[
        "Gor\u2019kogo",
        "\u0413\u043e\u0440\u044c\u043a\u043e\u0433\u043e"
    ],
    "wof:name":"Gor'kogo",
    "wof:placetype":"locality"
},
  "geometry": {"coordinates":[39.22556,51.71333],"type":"Point"}
}