{
  "type": "Feature",
  "properties": {
    "gn:admin1_code":"75",
    "gn:asciiname":"Rybalovo",
    "gn:cc2":"RU",
    "gn:country_code":"RU",
    "gn:dem":81,
    "gn:feature_class":"P",
    "gn:feature_code":"PPL",
    "gn:name":"Rybalovo",
    "gn:population":0,
    "gn:timezone":"Asia/Tomsk",
    "iso:country":"RU",
    "name:eng_x_preferred":[
        "Rybalovo"
    ],
    "name:nor_x_preferred":[
        "Rybalovo"
    ],
    "name:rus_x_preferred":[
        "\u0420\u044b\u0431\u0430\u043b\u043e\u0432\u043e"
    ],
    "name:und_x_variant":[
        "Rybalova",
        "\u0420\u044b\u0431\u0430\u043b\u043e\u0432\u043e",
        "Rybalovo"
    ],
    "wof:name":"Rybalovo",
    "wof:placetype":"locality"
},
  "geometry": {"coordinates":[84.00749999999999,57.13778000000001],"type":"Point"}
}