{
  "type": "Feature",
  "properties": {
    "gn:admin1_code":"21.0",
    "gn:asciiname":"Solov'yevo",
    "gn:country_code":"RU",
    "gn:dem":113,
    "gn:feature_class":"P",
    "gn:feature_code":"PPL",
    "gn:name":"Solov\u2019y\u00ebvo",
    "gn:population":0,
    "gn:timezone":"Europe/Moscow",
    "iso:country":"RU",
    "name:nor_x_preferred":[
        "Solovjovo"
    ],
    "name:rus_x_preferred":[
        "\u0421\u043e\u043b\u043e\u0432\u044c\u0451\u0432\u043e"
    ],
    "name:und_x_variant":[
        "Solov\u2019y\u00ebvo"
    ],
    "wof:name":"Solov'yevo",
    "wof:placetype":"locality"
},
  "geometry": {"coordinates":[43.13183,56.99616999999999],"type":"Point"}
}