{
  "type": "Feature",
  "properties": {
    "gn:admin1_code":"78",
    "gn:asciiname":"Ushakovo",
    "gn:country_code":"RU",
    "gn:dem":82,
    "gn:feature_class":"P",
    "gn:feature_code":"PPL",
    "gn:name":"Ushakovo",
    "gn:population":0,
    "gn:timezone":"Asia/Yekaterinburg",
    "iso:country":"RU",
    "name:eng_x_preferred":[
        "Ushakovo"
    ],
    "name:nor_x_preferred":[
        "Usjakovo"
    ],
    "name:rus_x_preferred":[
        "\u0423\u0448\u0430\u043a\u043e\u0432\u043e"
    ],
    "wof:name":"Ushakovo",
    "wof:placetype":"locality"
},
  "geometry": {"coordinates":[68.25694,57.44665],"type":"Point"}
}