{
  "type": "Feature",
  "properties": {
    "gn:admin1_code":"10",
    "gn:asciiname":"Yelionka",
    "gn:country_code":"RU",
    "gn:dem":164,
    "gn:feature_class":"P",
    "gn:feature_code":"PPL",
    "gn:name":"Yelionka",
    "gn:population":0,
    "gn:timezone":"Europe/Moscow",
    "iso:country":"RU",
    "name:eng_x_preferred":[
        "Yelionka"
    ],
    "name:nor_x_preferred":[
        "Jelionka"
    ],
    "name:rus_x_preferred":[
        "\u0415\u043b\u0438\u043e\u043d\u043a\u0430"
    ],
    "name:und_x_variant":[
        "Yelenka",
        "\u0415\u043b\u0438\u043e\u043d\u043a\u0430",
        "Yelionka"
    ],
    "wof:name":"Yelionka",
    "wof:placetype":"locality"
},
  "geometry": {"coordinates":[32.6009,52.43378000000001],"type":"Point"}
}