{
  "type": "Feature",
  "properties": {
    "gn:admin1_code":"77",
    "gn:asciiname":"Maloye Nikulino",
    "gn:country_code":"RU",
    "gn:dem":234,
    "gn:feature_class":"P",
    "gn:feature_code":"PPL",
    "gn:name":"Maloye Nikulino",
    "gn:population":0,
    "gn:timezone":"Europe/Moscow",
    "iso:country":"RU",
    "name:rus_x_preferred":[
        "\u041c\u0430\u043b\u043e\u0435 \u041d\u0438\u043a\u0443\u043b\u0438\u043d\u043e"
    ],
    "wof:name":"Maloye Nikulino",
    "wof:placetype":"locality"
},
  "geometry": {"coordinates":[33.78333,56.21666999999999],"type":"Point"}
}