{
  "type": "Feature",
  "properties": {
    "gn:admin1_code":"71",
    "gn:asciiname":"Borovskoy Vtoroy",
    "gn:country_code":"RU",
    "gn:dem":108,
    "gn:feature_class":"P",
    "gn:feature_code":"PPL",
    "gn:name":"Borovskoy Vtoroy",
    "gn:population":0,
    "gn:timezone":"Asia/Yekaterinburg",
    "iso:country":"RU",
    "name:rus_x_preferred":[
        "\u0411\u043e\u0440\u043e\u0432\u0441\u043a\u043e\u0439 \u0412\u0442\u043e\u0440\u043e\u0439"
    ],
    "name:und_x_variant":[
        "Borovskoy"
    ],
    "wof:name":"Borovskoy Vtoroy",
    "wof:placetype":"locality"
},
  "geometry": {"coordinates":[62.3292,57.4987],"type":"Point"}
}