{
  "type": "Feature",
  "properties": {
    "gn:admin1_code":"60",
    "gn:asciiname":"Tsynki",
    "gn:country_code":"RU",
    "gn:dem":176,
    "gn:feature_class":"P",
    "gn:feature_code":"PPL",
    "gn:name":"Tsynki",
    "gn:population":0,
    "gn:timezone":"Europe/Moscow",
    "iso:country":"RU",
    "name:rus_x_preferred":[
        "\u0426\u044b\u043d\u043a\u0438"
    ],
    "wof:name":"Tsynki",
    "wof:placetype":"locality"
},
  "geometry": {"coordinates":[28.4268,56.3339],"type":"Point"}
}