{
  "type": "Feature",
  "properties": {
    "gn:admin1_code":"61",
    "gn:asciiname":"Sekretev",
    "gn:country_code":"RU",
    "gn:dem":110,
    "gn:feature_class":"P",
    "gn:feature_code":"PPL",
    "gn:name":"Sekretev",
    "gn:population":0,
    "gn:timezone":"Europe/Moscow",
    "iso:country":"RU",
    "name:eng_x_preferred":[
        "Sekretov"
    ],
    "name:nor_x_preferred":[
        "Sekretev"
    ],
    "name:rus_x_preferred":[
        "\u0421\u0435\u043a\u0440\u0435\u0442\u0435\u0432"
    ],
    "name:und_x_variant":[
        "Zimno-Sekretevikh"
    ],
    "wof:name":"Sekretev",
    "wof:placetype":"locality"
},
  "geometry": {"coordinates":[42.5576,46.8189],"type":"Point"}
}