{
  "type": "Feature",
  "properties": {
    "gn:admin1_code":"15",
    "gn:asciiname":"Inchoun",
    "gn:country_code":"RU",
    "gn:dem":8,
    "gn:feature_class":"P",
    "gn:feature_code":"PPL",
    "gn:name":"Inchoun",
    "gn:population":0,
    "gn:timezone":"Asia/Anadyr",
    "iso:country":"RU",
    "name:eng_x_historical":[
        "Enchowaw Village"
    ],
    "name:eng_x_preferred":[
        "Enchowaw Village"
    ],
    "name:rus_x_preferred":[
        "\u0418\u043d\u0447\u043e\u0443\u043d"
    ],
    "name:und_x_variant":[
        "Inchouin",
        "Inchuyn",
        "Inchounskoye",
        "Inchaun",
        "Inchovyn",
        "Inchoun",
        "\u0418\u043d\u0447\u043e\u0443\u043d"
    ],
    "wof:name":"Inchoun",
    "wof:placetype":"locality"
},
  "geometry": {"coordinates":[-170.28021000000001,66.29791999999999],"type":"Point"}
}