{
  "type": "Feature",
  "properties": {
    "gn:admin1_code":"42.0",
    "gn:asciiname":"Kurgolovo",
    "gn:country_code":"RU",
    "gn:dem":138,
    "gn:feature_class":"P",
    "gn:feature_code":"PPL",
    "gn:name":"Kurgolovo",
    "gn:population":0,
    "gn:timezone":"Europe/Moscow",
    "iso:country":"RU",
    "name:fin_x_preferred":[
        "Korkkyl\u00e4"
    ],
    "wof:name":"Kurgolovo",
    "wof:placetype":"locality"
},
  "geometry": {"coordinates":[29.60785,59.5057],"type":"Point"}
}