{
  "type": "Feature",
  "properties": {
    "gn:admin1_code":"33",
    "gn:asciiname":"Lum",
    "gn:country_code":"RU",
    "gn:dem":118,
    "gn:feature_class":"P",
    "gn:feature_code":"PPL",
    "gn:name":"Lum",
    "gn:population":0,
    "gn:timezone":"Europe/Kirov",
    "iso:country":"RU",
    "name:ceb_x_preferred":[
        "Lum"
    ],
    "name:deu_x_preferred":[
        "Lum"
    ],
    "name:eng_x_preferred":[
        "Lum"
    ],
    "name:epo_x_preferred":[
        "Lum"
    ],
    "name:fra_x_preferred":[
        "Lum"
    ],
    "name:nor_x_preferred":[
        "Lum"
    ],
    "name:rus_x_preferred":[
        "\u041b\u0443\u043c"
    ],
    "name:swe_x_preferred":[
        "Lum"
    ],
    "wof:name":"Lum",
    "wof:placetype":"locality"
},
  "geometry": {"coordinates":[47.91059,57.18075],"type":"Point"}
}