{
  "type": "Feature",
  "properties": {
    "gn:admin1_code":"33",
    "gn:asciiname":"Novo-Chernyye",
    "gn:country_code":"RU",
    "gn:dem":177,
    "gn:feature_class":"P",
    "gn:feature_code":"PPL",
    "gn:name":"Novo-Ch\u00ebrnyye",
    "gn:population":0,
    "gn:timezone":"Europe/Kirov",
    "iso:country":"RU",
    "name:rus_x_preferred":[
        "\u041d\u043e\u0432\u043e-\u0427\u0451\u0440\u043d\u044b\u0435"
    ],
    "name:und_x_variant":[
        "Novo-Ch\u00ebrnyye"
    ],
    "wof:name":"Novo-Chernyye",
    "wof:placetype":"locality"
},
  "geometry": {"coordinates":[50.46667,58.05],"type":"Point"}
}