{
  "type": "Feature",
  "properties": {
    "gn:admin1_code":"70.0",
    "gn:asciiname":"Blagonadezhnyy",
    "gn:country_code":"RU",
    "gn:dem":469,
    "gn:feature_class":"P",
    "gn:feature_code":"PPL",
    "gn:name":"Blagonadezhnyy",
    "gn:population":0,
    "gn:timezone":"Europe/Moscow",
    "iso:country":"RU",
    "wof:name":"Blagonadezhnyy",
    "wof:placetype":"locality"
},
  "geometry": {"coordinates":[42.84667,44.44639],"type":"Point"}
}