{
  "type": "Feature",
  "properties": {
    "gn:admin1_code":"91",
    "gn:asciiname":"Zhdanova",
    "gn:country_code":"RU",
    "gn:dem":121,
    "gn:feature_class":"P",
    "gn:feature_code":"PPL",
    "gn:name":"Zhdanova",
    "gn:population":0,
    "gn:timezone":"Asia/Krasnoyarsk",
    "iso:country":"RU",
    "wof:name":"Zhdanova",
    "wof:placetype":"locality"
},
  "geometry": {"coordinates":[88.86667,58.61666999999999],"type":"Point"}
}