{
  "type": "Feature",
  "properties": {
    "gn:admin1_code":"33.0",
    "gn:asciiname":"Syrchenki",
    "gn:country_code":"RU",
    "gn:dem":175,
    "gn:feature_class":"P",
    "gn:feature_code":"PPL",
    "gn:name":"Syrchenki",
    "gn:population":0,
    "gn:timezone":"Europe/Kirov",
    "iso:country":"RU",
    "name:rus_x_preferred":[
        "\u0421\u044b\u0440\u0447\u0435\u043d\u043a\u0438"
    ],
    "wof:name":"Syrchenki",
    "wof:placetype":"locality"
},
  "geometry": {"coordinates":[49.59887,58.80493000000001],"type":"Point"}
}