{
  "type": "Feature",
  "properties": {
    "gn:admin1_code":"61",
    "gn:asciiname":"Vodyanyy",
    "gn:country_code":"RU",
    "gn:dem":26,
    "gn:feature_class":"P",
    "gn:feature_code":"PPL",
    "gn:name":"Vodyanyy",
    "gn:population":0,
    "gn:timezone":"Europe/Moscow",
    "iso:country":"RU",
    "name:rus_x_preferred":[
        "\u0412\u043e\u0434\u044f\u043d\u044b\u0439"
    ],
    "name:und_x_variant":[
        "Vodyany",
        "Vodyanoy",
        "Vodyanyy",
        "\u0412\u043e\u0434\u044f\u043d\u044b\u0439"
    ],
    "wof:name":"Vodyanyy",
    "wof:placetype":"locality"
},
  "geometry": {"coordinates":[39.0239,46.7134],"type":"Point"}
}