{
  "type": "Feature",
  "properties": {
    "gn:admin1_code":"17.0",
    "gn:asciiname":"Kalininaul",
    "gn:country_code":"RU",
    "gn:dem":2,
    "gn:feature_class":"P",
    "gn:feature_code":"PPL",
    "gn:name":"Kalininaul",
    "gn:population":0,
    "gn:timezone":"Europe/Moscow",
    "iso:country":"RU",
    "name:eng_x_preferred":[
        "Kalininaul"
    ],
    "name:nor_x_preferred":[
        "Kalininaul"
    ],
    "name:rus_x_preferred":[
        "\u041a\u0430\u043b\u0438\u043d\u0438\u043d\u0430\u0443\u043b"
    ],
    "name:und_x_variant":[
        "Kalinin",
        "\u041a\u0430\u043b\u0438\u043d\u0438\u043d\u0430\u0443\u043b",
        "Kalininaul"
    ],
    "wof:name":"Kalininaul",
    "wof:placetype":"locality"
},
  "geometry": {"coordinates":[46.004,44.16232],"type":"Point"}
}