{
  "type": "Feature",
  "properties": {
    "gn:admin1_code":"60",
    "gn:asciiname":"Kriulino",
    "gn:country_code":"RU",
    "gn:dem":54,
    "gn:feature_class":"P",
    "gn:feature_code":"PPL",
    "gn:name":"Kriulino",
    "gn:population":0,
    "gn:timezone":"Europe/Moscow",
    "iso:country":"RU",
    "name:rus_x_preferred":[
        "\u041a\u0440\u0438\u0443\u043b\u0438\u043d\u043e"
    ],
    "wof:name":"Kriulino",
    "wof:placetype":"locality"
},
  "geometry": {"coordinates":[28.21316,57.23331],"type":"Point"}
}