{
  "type": "Feature",
  "properties": {
    "gn:admin1_code":"49",
    "gn:asciiname":"Nyal",
    "gn:country_code":"RU",
    "gn:dem":117,
    "gn:feature_class":"P",
    "gn:feature_code":"PPL",
    "gn:name":"Nyal",
    "gn:population":0,
    "gn:timezone":"Europe/Moscow",
    "iso:country":"RU",
    "name:che_x_preferred":[
        "\u041d\u044f\u043b"
    ],
    "name:rus_x_preferred":[
        "\u041d\u044f\u043b"
    ],
    "wof:name":"Nyal",
    "wof:placetype":"locality"
},
  "geometry": {"coordinates":[32.12045,69.07562],"type":"Point"}
}