{
  "type": "Feature",
  "properties": {
    "gn:admin1_code":"78",
    "gn:asciiname":"Vilizhany",
    "gn:country_code":"RU",
    "gn:dem":45,
    "gn:feature_class":"P",
    "gn:feature_code":"PPL",
    "gn:name":"Vilizhany",
    "gn:population":0,
    "gn:timezone":"Asia/Yekaterinburg",
    "iso:country":"RU",
    "name:rus_x_preferred":[
        "\u0412\u0438\u043b\u0438\u0436\u0430\u043d\u044b"
    ],
    "wof:name":"Vilizhany",
    "wof:placetype":"locality"
},
  "geometry": {"coordinates":[65.9059,57.1597],"type":"Point"}
}