{
  "type": "Feature",
  "properties": {
    "gn:admin1_code":"52",
    "gn:asciiname":"Pustaya Mditsa",
    "gn:country_code":"RU",
    "gn:dem":169,
    "gn:feature_class":"P",
    "gn:feature_code":"PPL",
    "gn:name":"Pustaya Mditsa",
    "gn:population":0,
    "gn:timezone":"Europe/Moscow",
    "iso:country":"RU",
    "name:rus_x_preferred":[
        "\u041f\u0443\u0441\u0442\u0430\u044f \u041c\u0434\u0438\u0446\u0430"
    ],
    "name:und_x_variant":[
        "\u041f\u0443\u0441\u0442\u0430\u044f \u041c\u0434\u0438\u0446\u0430"
    ],
    "wof:name":"Pustaya Mditsa",
    "wof:placetype":"locality"
},
  "geometry": {"coordinates":[33.18333,59.01667],"type":"Point"}
}