{
  "type": "Feature",
  "properties": {
    "gn:admin1_code":"53",
    "gn:asciiname":"Koltoyak",
    "gn:country_code":"RU",
    "gn:dem":101,
    "gn:feature_class":"P",
    "gn:feature_code":"PPL",
    "gn:name":"Koltoyak",
    "gn:population":0,
    "gn:timezone":"Asia/Novosibirsk",
    "iso:country":"RU",
    "name:rus_x_preferred":[
        "\u041a\u043e\u043b\u0442\u043e\u044f\u043a"
    ],
    "name:und_x_variant":[
        "\u041a\u043e\u043b\u0442\u043e\u044f\u043a"
    ],
    "wof:name":"Koltoyak",
    "wof:placetype":"locality"
},
  "geometry": {"coordinates":[77.75,54.65],"type":"Point"}
}