{
  "type": "Feature",
  "properties": {
    "gn:admin1_code":"63",
    "gn:asciiname":"Churan",
    "gn:country_code":"RU",
    "gn:dem":94,
    "gn:feature_class":"P",
    "gn:feature_code":"PPL",
    "gn:name":"Churan",
    "gn:population":0,
    "gn:timezone":"Asia/Yakutsk",
    "iso:country":"RU",
    "name:ceb_x_preferred":[
        "Churan"
    ],
    "name:rus_x_preferred":[
        "\u0427\u0443\u0440\u0430\u043d"
    ],
    "name:swe_x_preferred":[
        "Churan"
    ],
    "name:und_x_variant":[
        "Churanskaya",
        "Churu",
        "Chuuru"
    ],
    "wof:name":"Churan",
    "wof:placetype":"locality"
},
  "geometry": {"coordinates":[125.01543999999998,60.77408000000001],"type":"Point"}
}