{
  "type": "Feature",
  "properties": {
    "gn:admin1_code":"63",
    "gn:asciiname":"Achchygyy-Kyramda",
    "gn:country_code":"RU",
    "gn:dem":247,
    "gn:feature_class":"P",
    "gn:feature_code":"PPL",
    "gn:name":"Achchygyy-Kyramda",
    "gn:population":0,
    "gn:timezone":"Asia/Yakutsk",
    "iso:country":"RU",
    "name:eng_x_preferred":[
        "Achchygyy-Kyramda"
    ],
    "name:nor_x_preferred":[
        "Atsjtsjygyj-Kyramda"
    ],
    "name:rus_x_preferred":[
        "\u0410\u0447\u0447\u044b\u0433\u044b\u0439-\u041a\u044b\u0440\u0430\u043c\u0434\u0430"
    ],
    "name:und_x_variant":[
        "\u0410\u0447\u0447\u044b\u0433\u044b\u0439-\u041a\u044b\u0440\u0430\u043c\u0434\u0430",
        "Achchygyy-Kyramda"
    ],
    "wof:name":"Achchygyy-Kyramda",
    "wof:placetype":"locality"
},
  "geometry": {"coordinates":[126.90000000000001,62.43333000000001],"type":"Point"}
}