{
  "type": "Feature",
  "properties": {
    "gn:admin1_code":"73.0",
    "gn:asciiname":"Al'dermysh",
    "gn:country_code":"RU",
    "gn:dem":74,
    "gn:feature_class":"P",
    "gn:feature_code":"PPL",
    "gn:name":"Al\u2019dermysh",
    "gn:population":0,
    "gn:timezone":"Europe/Moscow",
    "iso:country":"RU",
    "name:eng_x_preferred":[
        "Al'dermysh"
    ],
    "name:nor_x_preferred":[
        "Aldermysj"
    ],
    "name:rus_x_preferred":[
        "\u0410\u043b\u044c\u0434\u0435\u0440\u043c\u044b\u0448"
    ],
    "name:und_x_variant":[
        "\u0410\u043b\u044c\u0434\u0435\u0440\u043c\u044b\u0448",
        "Al\u2019dermysh"
    ],
    "wof:name":"Al'dermysh",
    "wof:placetype":"locality"
},
  "geometry": {"coordinates":[49.23306,56.01971999999999],"type":"Point"}
}