{
  "type": "Feature",
  "properties": {
    "gn:admin1_code":"60",
    "gn:asciiname":"Chortova Gora",
    "gn:country_code":"RU",
    "gn:dem":73,
    "gn:feature_class":"P",
    "gn:feature_code":"PPL",
    "gn:name":"Chortova Gora",
    "gn:population":0,
    "gn:timezone":"Europe/Moscow",
    "iso:country":"RU",
    "name:rus_x_preferred":[
        "\u0427\u043e\u0440\u0442\u043e\u0432\u0430 \u0413\u043e\u0440\u0430"
    ],
    "wof:name":"Chortova Gora",
    "wof:placetype":"locality"
},
  "geometry": {"coordinates":[28.7817,57.089],"type":"Point"}
}