{
  "type": "Feature",
  "properties": {
    "gn:admin1_code":"85",
    "gn:asciiname":"Kanushinskaya",
    "gn:country_code":"RU",
    "gn:dem":158,
    "gn:feature_class":"P",
    "gn:feature_code":"PPL",
    "gn:name":"Kanushinskaya",
    "gn:population":0,
    "gn:timezone":"Europe/Moscow",
    "iso:country":"RU",
    "name:rus_x_preferred":[
        "\u041a\u0430\u043d\u0443\u0448\u0438\u043d\u0441\u043a\u0430\u044f"
    ],
    "wof:name":"Kanushinskaya",
    "wof:placetype":"locality"
},
  "geometry": {"coordinates":[42.61985,59.45745],"type":"Point"}
}