{
  "type": "Feature",
  "properties": {
    "gn:admin1_code":"56",
    "gn:asciiname":"Shlyakh",
    "gn:country_code":"RU",
    "gn:dem":213,
    "gn:feature_class":"P",
    "gn:feature_code":"PPL",
    "gn:name":"Shlyakh",
    "gn:population":0,
    "gn:timezone":"Europe/Moscow",
    "iso:country":"RU",
    "name:rus_x_preferred":[
        "\u0428\u043b\u044f\u0445"
    ],
    "name:und_x_variant":[
        "Lamskiye Dvory",
        "Shlyakh",
        "\u0428\u043b\u044f\u0445"
    ],
    "wof:name":"Shlyakh",
    "wof:placetype":"locality"
},
  "geometry": {"coordinates":[37.53755,52.29895],"type":"Point"}
}