{
  "type": "Feature",
  "properties": {
    "gn:admin1_code":"47",
    "gn:asciiname":"Shchitovo",
    "gn:country_code":"RU",
    "gn:dem":210,
    "gn:feature_class":"P",
    "gn:feature_code":"PPL",
    "gn:name":"Shchitovo",
    "gn:population":0,
    "gn:timezone":"Europe/Moscow",
    "iso:country":"RU",
    "name:rus_x_preferred":[
        "\u0429\u0438\u0442\u043e\u0432\u043e"
    ],
    "name:und_x_variant":[
        "\u0429\u0438\u0442\u043e\u0432\u043e"
    ],
    "wof:name":"Shchitovo",
    "wof:placetype":"locality"
},
  "geometry": {"coordinates":[37.01772,55.3169],"type":"Point"}
}