{
  "type": "Feature",
  "properties": {
    "gn:admin1_code":"73",
    "gn:asciiname":"Novyy Kadermet",
    "gn:country_code":"RU",
    "gn:dem":98,
    "gn:feature_class":"P",
    "gn:feature_code":"PPL",
    "gn:name":"Novyy Kadermet",
    "gn:population":0,
    "gn:timezone":"Europe/Moscow",
    "iso:country":"RU",
    "name:rus_x_preferred":[
        "\u041d\u043e\u0432\u044b\u0439 \u041a\u0430\u0434\u0435\u0440\u043c\u0435\u0442"
    ],
    "name:und_x_variant":[
        "\u041d\u043e\u0432\u044b\u0439 \u041a\u0430\u0434\u0435\u0440\u043c\u0435\u0442"
    ],
    "wof:name":"Novyy Kadermet",
    "wof:placetype":"locality"
},
  "geometry": {"coordinates":[53.9068,55.5526],"type":"Point"}
}