{
  "type": "Feature",
  "properties": {
    "gn:admin1_code":"69",
    "gn:asciiname":"Ponyaty",
    "gn:country_code":"RU",
    "gn:dem":215,
    "gn:feature_class":"P",
    "gn:feature_code":"PPL",
    "gn:name":"Ponyaty",
    "gn:population":0,
    "gn:timezone":"Europe/Moscow",
    "iso:country":"RU",
    "wof:name":"Ponyaty",
    "wof:placetype":"locality"
},
  "geometry": {"coordinates":[33.51976,54.16009],"type":"Point"}
}