{
  "type": "Feature",
  "properties": {
    "gn:admin1_code":"41.0",
    "gn:asciiname":"Kolontayevka",
    "gn:country_code":"RU",
    "gn:dem":225,
    "gn:feature_class":"P",
    "gn:feature_code":"PPL",
    "gn:name":"Kolontayevka",
    "gn:population":0,
    "gn:timezone":"Europe/Moscow",
    "iso:country":"RU",
    "name:rus_x_preferred":[
        "\u041a\u043e\u043b\u043e\u043d\u0442\u0430\u0435\u0432\u043a\u0430"
    ],
    "name:und_x_variant":[
        "\u041a\u043e\u043b\u043e\u043d\u0442\u0430\u0435\u0432\u043a\u0430"
    ],
    "wof:name":"Kolontayevka",
    "wof:placetype":"locality"
},
  "geometry": {"coordinates":[35.1262,51.5642],"type":"Point"}
}