{
  "type": "Feature",
  "properties": {
    "gn:admin1_code":"53",
    "gn:asciiname":"Morozovo",
    "gn:cc2":"RU",
    "gn:country_code":"RU",
    "gn:dem":121,
    "gn:feature_class":"P",
    "gn:feature_code":"PPL",
    "gn:name":"Morozovo",
    "gn:population":0,
    "gn:timezone":"Asia/Novosibirsk",
    "iso:country":"RU",
    "name:rus_x_preferred":[
        "\u041c\u043e\u0440\u043e\u0437\u043e\u0432\u043e"
    ],
    "name:und_x_variant":[
        "Morozova",
        "Morozovo"
    ],
    "wof:name":"Morozovo",
    "wof:placetype":"locality"
},
  "geometry": {"coordinates":[77.25,56.21666999999999],"type":"Point"}
}