{
  "type": "Feature",
  "properties": {
    "gn:admin1_code":"78",
    "gn:asciiname":"Karelino",
    "gn:country_code":"RU",
    "gn:dem":42,
    "gn:feature_class":"P",
    "gn:feature_code":"PPL",
    "gn:name":"Karelino",
    "gn:population":0,
    "gn:timezone":"Asia/Yekaterinburg",
    "iso:country":"RU",
    "name:eng_x_preferred":[
        "Karelino"
    ],
    "name:nor_x_preferred":[
        "Karelina"
    ],
    "name:rus_x_preferred":[
        "\u041a\u0430\u0440\u0435\u043b\u0438\u043d\u0430"
    ],
    "name:rus_x_variant":[
        "\u041a\u0430\u0440\u0435\u043b\u0438\u043d\u043e"
    ],
    "name:und_x_variant":[
        "\u041a\u0430\u0440\u0435\u043b\u0438\u043d\u043e"
    ],
    "wof:name":"Karelino",
    "wof:placetype":"locality"
},
  "geometry": {"coordinates":[69.03333000000001,57.96666999999999],"type":"Point"}
}