{
  "type": "Feature",
  "properties": {
    "gn:admin1_code":"73",
    "gn:asciiname":"Turminskoye",
    "gn:country_code":"RU",
    "gn:dem":80,
    "gn:feature_class":"P",
    "gn:feature_code":"PPL",
    "gn:name":"Turminskoye",
    "gn:population":0,
    "gn:timezone":"Europe/Moscow",
    "iso:country":"RU",
    "name:rus_x_preferred":[
        "\u0422\u0443\u0440\u043c\u0438\u043d\u0441\u043a\u043e\u0435"
    ],
    "wof:name":"Turminskoye",
    "wof:placetype":"locality"
},
  "geometry": {"coordinates":[47.88072,55.34511],"type":"Point"}
}