{
  "type": "Feature",
  "properties": {
    "gn:country":"RU",
    "gn:fcode":"PPL",
    "gn:population":0,
    "iso:country":"RU",
    "name:rus_x_preferred":[
        "\u0424\u0435\u0434\u043e\u0442\u043e\u0432\u043e"
    ],
    "qs:name":"Fedotovo",
    "qs:name_adm0":"Russia",
    "qs:name_adm1":"Moscow Oblast",
    "qs:photos_9r":0,
    "qs:photos_sr":0,
    "qs:placetype":"Town",
    "qs:pop_sr":"0",
    "wd:wordcount":636,
    "wof:name":"Fedotovo",
    "wof:placetype":"locality",
    "wof:population":0
},
  "geometry": {"coordinates":[37.66667,56.56667],"type":"Point"}
}