{
  "type": "Feature",
  "properties": {
    "gn:admin1_code":"10",
    "gn:asciiname":"Nypryakhino",
    "gn:country_code":"RU",
    "gn:dem":185,
    "gn:feature_class":"P",
    "gn:feature_code":"PPL",
    "gn:name":"Nypryakhino",
    "gn:population":0,
    "gn:timezone":"Europe/Moscow",
    "iso:country":"RU",
    "wof:name":"Nypryakhino",
    "wof:placetype":"locality"
},
  "geometry": {"coordinates":[35.04417,53.05361],"type":"Point"}
}