{
  "type": "Feature",
  "properties": {
    "gn:admin1_code":"71",
    "gn:asciiname":"Brodovo",
    "gn:country_code":"RU",
    "gn:dem":221,
    "gn:feature_class":"P",
    "gn:feature_code":"PPL",
    "gn:name":"Brodovo",
    "gn:population":0,
    "gn:timezone":"Asia/Yekaterinburg",
    "iso:country":"RU",
    "name:eng_x_preferred":[
        "Brodovo"
    ],
    "name:nor_x_preferred":[
        "Brodovo"
    ],
    "name:rus_x_preferred":[
        "\u0411\u0440\u043e\u0434\u043e\u0432\u043e"
    ],
    "name:und_x_variant":[
        "Brodovskoye"
    ],
    "wof:name":"Brodovo",
    "wof:placetype":"locality"
},
  "geometry": {"coordinates":[60.59242,57.67267],"type":"Point"}
}