{
  "type": "Feature",
  "properties": {
    "gn:admin1_code":"4.0",
    "gn:asciiname":"Rodina",
    "gn:country_code":"RU",
    "gn:dem":171,
    "gn:feature_class":"P",
    "gn:feature_code":"PPL",
    "gn:name":"Rodina",
    "gn:population":0,
    "gn:timezone":"Asia/Barnaul",
    "iso:country":"RU",
    "name:bul_x_preferred":[
        "\u0420\u043e\u0434\u0438\u043d\u0430"
    ],
    "name:ceb_x_preferred":[
        "Rodina"
    ],
    "name:ces_x_preferred":[
        "Rodina"
    ],
    "name:deu_x_preferred":[
        "Rodina"
    ],
    "name:fra_x_preferred":[
        "Rodina"
    ],
    "name:kaz_x_preferred":[
        "\u0420\u043e\u0434\u0438\u043d\u0430"
    ],
    "name:ron_x_preferred":[
        "Rodina"
    ],
    "name:rus_x_preferred":[
        "\u0420\u043e\u0434\u0438\u043d\u0430"
    ],
    "name:slk_x_preferred":[
        "Rodina"
    ],
    "name:swe_x_preferred":[
        "Rodina"
    ],
    "name:ukr_x_preferred":[
        "\u0420\u043e\u0434\u0438\u043d\u0430"
    ],
    "wof:name":"Rodina",
    "wof:placetype":"locality"
},
  "geometry": {"coordinates":[81.6181,53.8016],"type":"Point"}
}