{
  "type": "Feature",
  "properties": {
    "gn:admin1_code":"70",
    "gn:asciiname":"Vidnyy",
    "gn:country_code":"RU",
    "gn:dem":159,
    "gn:feature_class":"P",
    "gn:feature_code":"PPL",
    "gn:name":"Vidnyy",
    "gn:population":0,
    "gn:timezone":"Europe/Moscow",
    "iso:country":"RU",
    "name:und_x_variant":[
        "\u0412\u0438\u0434\u043d\u044b\u0439"
    ],
    "wof:name":"Vidnyy",
    "wof:placetype":"locality"
},
  "geometry": {"coordinates":[43.58944,44.93778],"type":"Point"}
}