{
  "type": "Feature",
  "properties": {
    "gn:admin1_code":"77",
    "gn:asciiname":"Zimnik",
    "gn:country_code":"RU",
    "gn:dem":210,
    "gn:feature_class":"P",
    "gn:feature_code":"PPL",
    "gn:name":"Zimnik",
    "gn:population":0,
    "gn:timezone":"Europe/Moscow",
    "iso:country":"RU",
    "name:rus_x_preferred":[
        "\u0417\u0438\u043c\u043d\u0438\u043a"
    ],
    "wof:name":"Zimnik",
    "wof:placetype":"locality"
},
  "geometry": {"coordinates":[32.79088,56.72413],"type":"Point"}
}