{
  "type": "Feature",
  "properties": {
    "gn:admin1_code":"86",
    "gn:asciiname":"Kitayevo",
    "gn:country_code":"RU",
    "gn:dem":138,
    "gn:feature_class":"P",
    "gn:feature_code":"PPL",
    "gn:name":"Kitayevo",
    "gn:population":0,
    "gn:timezone":"Europe/Moscow",
    "iso:country":"RU",
    "name:rus_x_preferred":[
        "\u041a\u0438\u0442\u0430\u0435\u0432\u043e"
    ],
    "wof:name":"Kitayevo",
    "wof:placetype":"locality"
},
  "geometry": {"coordinates":[39.47257000000001,51.742],"type":"Point"}
}