{
  "type": "Feature",
  "properties": {
    "gn:admin1_code":"28",
    "gn:asciiname":"Il'vasvara",
    "gn:country_code":"RU",
    "gn:dem":239,
    "gn:feature_class":"P",
    "gn:feature_code":"PPL",
    "gn:name":"Il\u2019vasvara",
    "gn:population":0,
    "gn:timezone":"Europe/Moscow",
    "iso:country":"RU",
    "name:fin_x_preferred":[
        "Ilvesvaara"
    ],
    "name:rus_x_preferred":[
        "\u0418\u043b\u044c\u0432\u0430\u0441\u0432\u0430\u0440\u0430"
    ],
    "name:und_x_variant":[
        "Ip\u2019vasaara",
        "Il\u2019vesvaara",
        "Il\u2019vasvara",
        "\u0418\u043b\u044c\u0432\u0430\u0441\u0432\u0430\u0440\u0430"
    ],
    "wof:name":"Il'vasvara",
    "wof:placetype":"locality"
},
  "geometry": {"coordinates":[30.11667000000001,64.83333],"type":"Point"}
}