{
  "type": "Feature",
  "properties": {
    "gn:admin1_code":"77",
    "gn:asciiname":"Marinikha",
    "gn:country_code":"RU",
    "gn:dem":144,
    "gn:feature_class":"P",
    "gn:feature_code":"PPL",
    "gn:name":"Marinikha",
    "gn:population":0,
    "gn:timezone":"Europe/Moscow",
    "iso:country":"RU",
    "name:rus_x_preferred":[
        "\u041c\u0430\u0440\u0438\u043d\u0438\u0445\u0430"
    ],
    "wof:name":"Marinikha",
    "wof:placetype":"locality"
},
  "geometry": {"coordinates":[36.1254,58.2651],"type":"Point"}
}