{
  "type": "Feature",
  "properties": {
    "gn:admin1_code":"84",
    "gn:asciiname":"Narezki",
    "gn:country_code":"RU",
    "gn:dem":23,
    "gn:feature_class":"P",
    "gn:feature_code":"PPL",
    "gn:name":"Narezki",
    "gn:population":0,
    "gn:timezone":"Europe/Volgograd",
    "iso:country":"RU",
    "name:rus_x_preferred":[
        "\u041d\u0430\u0440\u0435\u0437\u043a\u0438"
    ],
    "wof:name":"Narezki",
    "wof:placetype":"locality"
},
  "geometry": {"coordinates":[45.91667,48.95],"type":"Point"}
}