{
  "type": "Feature",
  "properties": {
    "gn:admin1_code":"75",
    "gn:asciiname":"Krylovka",
    "gn:cc2":"RU",
    "gn:country_code":"RU",
    "gn:dem":116,
    "gn:feature_class":"P",
    "gn:feature_code":"PPL",
    "gn:name":"Krylovka",
    "gn:population":0,
    "gn:timezone":"Asia/Tomsk",
    "iso:country":"RU",
    "name:rus_x_preferred":[
        "\u041a\u0440\u044b\u043b\u043e\u0432\u043a\u0430"
    ],
    "name:und_x_variant":[
        "Krylovskiy",
        "Krylovka",
        "\u041a\u0440\u044b\u043b\u043e\u0432\u043a\u0430"
    ],
    "wof:name":"Krylovka",
    "wof:placetype":"locality"
},
  "geometry": {"coordinates":[83.76167,56.12917],"type":"Point"}
}