{
  "type": "Feature",
  "properties": {
    "gn:admin1_code":"8",
    "gn:asciiname":"Biyaz",
    "gn:country_code":"RU",
    "gn:dem":207,
    "gn:feature_class":"P",
    "gn:feature_code":"PPL",
    "gn:name":"Biyaz",
    "gn:population":0,
    "gn:timezone":"Asia/Yekaterinburg",
    "iso:country":"RU",
    "name:rus_x_preferred":[
        "\u0411\u0438\u044f\u0437"
    ],
    "name:und_x_variant":[
        "\u0411\u0438\u044f\u0437"
    ],
    "wof:name":"Biyaz",
    "wof:placetype":"locality"
},
  "geometry": {"coordinates":[57.48774,55.91803],"type":"Point"}
}