{
  "type": "Feature",
  "properties": {
    "gn:admin1_code":"78",
    "gn:asciiname":"Malaya Bukhtalka",
    "gn:country_code":"RU",
    "gn:dem":73,
    "gn:feature_class":"P",
    "gn:feature_code":"PPL",
    "gn:name":"Malaya Bukhtalka",
    "gn:population":0,
    "gn:timezone":"Asia/Yekaterinburg",
    "iso:country":"RU",
    "name:rus_x_preferred":[
        "\u041c\u0430\u043b\u0430\u044f \u0411\u0443\u0445\u0442\u0430\u043b\u043a\u0430"
    ],
    "name:und_x_variant":[
        "\u041c\u0430\u043b\u0430\u044f \u0411\u0443\u0445\u0442\u0430\u043b\u043a\u0430"
    ],
    "wof:name":"Malaya Bukhtalka",
    "wof:placetype":"locality"
},
  "geometry": {"coordinates":[65.2042,57.4731],"type":"Point"}
}