{
  "type": "Feature",
  "properties": {
    "gn:admin1_code":"69",
    "gn:asciiname":"Naumenki",
    "gn:country_code":"RU",
    "gn:dem":194,
    "gn:feature_class":"P",
    "gn:feature_code":"PPL",
    "gn:name":"Naumenki",
    "gn:population":0,
    "gn:timezone":"Europe/Moscow",
    "iso:country":"RU",
    "name:rus_x_preferred":[
        "\u041d\u0430\u0443\u043c\u0435\u043d\u043a\u0438"
    ],
    "name:und_x_variant":[
        "\u041d\u0430\u0443\u043c\u0435\u043d\u043a\u0438"
    ],
    "wof:name":"Naumenki",
    "wof:placetype":"locality"
},
  "geometry": {"coordinates":[34.72756,54.98299],"type":"Point"}
}