{
  "type": "Feature",
  "properties": {
    "gn:admin1_code":"9.0",
    "gn:asciiname":"Verin",
    "gn:country_code":"RU",
    "gn:dem":151,
    "gn:feature_class":"P",
    "gn:feature_code":"PPL",
    "gn:name":"Verin",
    "gn:population":0,
    "gn:timezone":"Europe/Moscow",
    "iso:country":"RU",
    "name:ceb_x_preferred":[
        "Verin"
    ],
    "name:hye_x_preferred":[
        "\u054e\u0565\u0580\u056b\u0576"
    ],
    "name:nld_x_preferred":[
        "Verin"
    ],
    "name:rus_x_preferred":[
        "\u0412\u0435\u0440\u0438\u043d"
    ],
    "name:swe_x_preferred":[
        "Verin"
    ],
    "name:ukr_x_preferred":[
        "\u0412\u0435\u0440\u0438\u043d"
    ],
    "wof:name":"Verin",
    "wof:placetype":"locality"
},
  "geometry": {"coordinates":[36.80484000000001,50.93618],"type":"Point"}
}