{
  "type": "Feature",
  "properties": {
    "gn:admin1_code":"54",
    "gn:asciiname":"Cheplyarovo",
    "gn:country_code":"RU",
    "gn:dem":62,
    "gn:feature_class":"P",
    "gn:feature_code":"PPL",
    "gn:name":"Cheplyarovo",
    "gn:population":0,
    "gn:timezone":"Asia/Omsk",
    "iso:country":"RU",
    "name:eng_x_preferred":[
        "Chuplyarovo"
    ],
    "name:nor_x_preferred":[
        "Tsjepljarovo"
    ],
    "name:rus_x_preferred":[
        "\u0427\u0435\u043f\u043b\u044f\u0440\u043e\u0432\u043e"
    ],
    "name:und_x_variant":[
        "Chuplyarovo",
        "Cheplyarovo",
        "\u0427\u0435\u043f\u043b\u044f\u0440\u043e\u0432\u043e"
    ],
    "wof:name":"Cheplyarovo",
    "wof:placetype":"locality"
},
  "geometry": {"coordinates":[74.75594,56.58459000000001],"type":"Point"}
}