{
  "type": "Feature",
  "properties": {
    "gn:admin1_code":"80",
    "gn:asciiname":"Novaya Zhik'ya",
    "gn:country_code":"RU",
    "gn:dem":136,
    "gn:feature_class":"P",
    "gn:feature_code":"PPL",
    "gn:name":"Novaya Zhik\u2019ya",
    "gn:population":0,
    "gn:timezone":"Europe/Samara",
    "iso:country":"RU",
    "name:rus_x_preferred":[
        "\u041d\u043e\u0432\u0430\u044f \u0416\u0438\u043a\u044c\u044f"
    ],
    "name:und_x_variant":[
        "Novaya Zhik\u2019ya",
        "\u041d\u043e\u0432\u0430\u044f \u0416\u0438\u043a\u044c\u044f"
    ],
    "wof:name":"Novaya Zhik'ya",
    "wof:placetype":"locality"
},
  "geometry": {"coordinates":[52.2202,57.3585],"type":"Point"}
}