{
  "type": "Feature",
  "properties": {
    "gn:admin1_code":"81.0",
    "gn:asciiname":"Bayevka",
    "gn:country_code":"RU",
    "gn:dem":221,
    "gn:feature_class":"P",
    "gn:feature_code":"PPL",
    "gn:name":"Bayevka",
    "gn:population":0,
    "gn:timezone":"Europe/Ulyanovsk",
    "iso:country":"RU",
    "name:eng_x_preferred":[
        "Bayevka"
    ],
    "name:nor_x_preferred":[
        "Bajevka"
    ],
    "name:rus_x_preferred":[
        "\u0411\u0430\u0435\u0432\u043a\u0430"
    ],
    "wof:name":"Bayevka",
    "wof:placetype":"locality"
},
  "geometry": {"coordinates":[47.25693,53.09021],"type":"Point"}
}