{
  "type": "Feature",
  "properties": {
    "gn:admin1_code":"51.0",
    "gn:asciiname":"Lis'ya Griva",
    "gn:country_code":"RU",
    "gn:dem":76,
    "gn:feature_class":"P",
    "gn:feature_code":"PPL",
    "gn:name":"Lis\u2019ya Griva",
    "gn:population":0,
    "gn:timezone":"Europe/Moscow",
    "iso:country":"RU",
    "name:nor_x_preferred":[
        "Lisia Griva"
    ],
    "name:rus_x_preferred":[
        "\u041b\u0438\u0441\u044c\u044f \u0413\u0440\u0438\u0432\u0430"
    ],
    "name:und_x_variant":[
        "Lis\u2019ya Griva"
    ],
    "wof:name":"Lis'ya Griva",
    "wof:placetype":"locality"
},
  "geometry": {"coordinates":[43.45102,56.51198],"type":"Point"}
}