{
  "type": "Feature",
  "properties": {
    "gn:admin1_code":"42",
    "gn:asciiname":"Ozertitsy",
    "gn:country_code":"RU",
    "gn:dem":119,
    "gn:feature_class":"P",
    "gn:feature_code":"PPL",
    "gn:name":"Ozertitsy",
    "gn:population":0,
    "gn:timezone":"Europe/Moscow",
    "iso:country":"RU",
    "name:fin_x_preferred":[
        "Osertsa"
    ],
    "name:nor_x_preferred":[
        "Ozertitsy"
    ],
    "name:rus_x_preferred":[
        "\u041e\u0437\u0435\u0440\u0442\u0438\u0446\u044b"
    ],
    "wof:name":"Ozertitsy",
    "wof:placetype":"locality"
},
  "geometry": {"coordinates":[29.47692,59.37933],"type":"Point"}
}