{
  "type": "Feature",
  "properties": {
    "gn:admin1_code":"53",
    "gn:asciiname":"Vasil'kovka",
    "gn:country_code":"RU",
    "gn:dem":114,
    "gn:feature_class":"P",
    "gn:feature_code":"PPL",
    "gn:name":"Vasil\u2019kovka",
    "gn:population":0,
    "gn:timezone":"Asia/Novosibirsk",
    "iso:country":"RU",
    "wof:name":"Vasil'kovka",
    "wof:placetype":"locality"
},
  "geometry": {"coordinates":[78.01222,54.29861],"type":"Point"}
}