{
  "type": "Feature",
  "properties": {
    "gn:admin1_code":"47",
    "gn:asciiname":"Vorya-Bogorodskoye",
    "gn:country_code":"RU",
    "gn:dem":147,
    "gn:feature_class":"P",
    "gn:feature_code":"PPL",
    "gn:name":"Vorya-Bogorodskoye",
    "gn:population":0,
    "gn:timezone":"Europe/Moscow",
    "iso:country":"RU",
    "wof:name":"Vorya-Bogorodskoye",
    "wof:placetype":"locality"
},
  "geometry": {"coordinates":[38.16667,56.05],"type":"Point"}
}