{
  "type": "Feature",
  "properties": {
    "gn:admin1_code":"73",
    "gn:asciiname":"Staryye Bugady",
    "gn:country_code":"RU",
    "gn:dem":103,
    "gn:feature_class":"P",
    "gn:feature_code":"PPL",
    "gn:name":"Staryye Bugady",
    "gn:population":0,
    "gn:timezone":"Europe/Moscow",
    "iso:country":"RU",
    "name:rus_x_preferred":[
        "\u0421\u0442\u0430\u0440\u044b\u0435 \u0411\u0443\u0433\u0430\u0434\u044b"
    ],
    "name:und_x_variant":[
        "Novyye Bugady",
        "Staryye Bugady"
    ],
    "wof:name":"Staryye Bugady",
    "wof:placetype":"locality"
},
  "geometry": {"coordinates":[53.93111999999999,55.6121],"type":"Point"}
}