{
  "type": "Feature",
  "properties": {
    "gn:admin1_code":"8",
    "gn:asciiname":"Mullakayevo",
    "gn:country_code":"RU",
    "gn:dem":527,
    "gn:feature_class":"P",
    "gn:feature_code":"PPL",
    "gn:name":"Mullakayevo",
    "gn:population":0,
    "gn:timezone":"Asia/Yekaterinburg",
    "iso:country":"RU",
    "name:aze_x_preferred":[
        "Mullakay"
    ],
    "name:bak_x_preferred":[
        "\u041c\u0443\u043b\u043b\u0430\u04a1\u0430\u0439"
    ],
    "name:che_x_preferred":[
        "\u041c\u0443\u043b\u043b\u0430\u043a\u0430\u0435\u0432\u043e"
    ],
    "name:eng_x_preferred":[
        "Mullakayevo"
    ],
    "name:hye_x_preferred":[
        "\u0544\u0578\u0582\u056c\u0561\u056f\u0561\u0587\u0578"
    ],
    "name:kat_x_preferred":[
        "\u10db\u10e3\u10da\u10d0\u10d9\u10d0\u10d4\u10d5\u10dd"
    ],
    "name:kaz_x_preferred":[
        "\u041c\u0443\u043b\u043b\u0430\u043a\u0430"
    ],
    "name:kir_x_preferred":[
        "\u041c\u0443\u043b\u043b\u0430\u043a\u0430"
    ],
    "name:nor_x_preferred":[
        "Mullakajevo"
    ],
    "name:rus_x_preferred":[
        "\u041c\u0443\u043b\u043b\u0430\u043a\u0430\u0435\u0432\u043e"
    ],
    "name:tat_x_preferred":[
        "\u041c\u0443\u043b\u043b\u0430\u043a\u0430\u0439"
    ],
    "name:ukr_x_preferred":[
        "\u041c\u0443\u043b\u043b\u0430\u043a\u0430\u0454\u0432\u043e"
    ],
    "name:und_x_variant":[
        "\u041c\u0443\u043b\u043b\u0430\u043a\u0430\u0435\u0432\u043e",
        "Mullakayevo"
    ],
    "wof:name":"Mullakayevo",
    "wof:placetype":"locality"
},
  "geometry": {"coordinates":[58.10111,52.89972],"type":"Point"}
}