{
  "type": "Feature",
  "properties": {
    "gn:admin1_code":"20",
    "gn:asciiname":"Karda",
    "gn:country_code":"RU",
    "gn:dem":445,
    "gn:feature_class":"P",
    "gn:feature_code":"PPL",
    "gn:name":"Karda",
    "gn:population":0,
    "gn:timezone":"Asia/Irkutsk",
    "iso:country":"RU",
    "name:eng_x_preferred":[
        "Karda"
    ],
    "name:nor_x_preferred":[
        "Karda"
    ],
    "name:rus_x_preferred":[
        "\u041a\u0430\u0440\u0434\u0430"
    ],
    "name:und_x_variant":[
        "Korda",
        "\u041a\u0430\u0440\u0434\u0430",
        "Karda"
    ],
    "wof:name":"Karda",
    "wof:placetype":"locality"
},
  "geometry": {"coordinates":[103.2924,54.9969],"type":"Point"}
}