{
  "type": "Feature",
  "properties": {
    "gn:country":"RU",
    "gn:fcode":"PPL",
    "gn:pop":400,
    "iso:country":"RU",
    "name:deu_x_preferred":[
        "Petrovsky"
    ],
    "name:rus_x_preferred":[
        "\u041f\u0435\u0442\u0440\u043e\u0432\u0441\u043a\u043e\u0435"
    ],
    "name:unk_x_variant":[
        "\u041f\u0435\u0442\u0440\u043e\u0432\u0441\u043a\u043e\u0435"
    ],
    "name:zho_x_preferred":[
        "\u5f7c\u5f97\u7f85\u592b\u65af\u57fa"
    ],
    "qs:name":"Petrovskoye",
    "qs:name_adm0":"Russia",
    "qs:name_adm1":"Kaluga Oblast",
    "qs:photos_9r":0,
    "qs:photos_sr":0,
    "qs:placetype":"Town",
    "qs:pop_sr":"2",
    "wd:wordcount":163,
    "wof:name":"Petrovskoye",
    "wof:placetype":"locality",
    "wof:population":400
},
  "geometry": {"coordinates":[36.98425,55.5358],"type":"Point"}
}