{
  "type": "Feature",
  "properties": {
    "gn:admin1_code":"7",
    "gn:asciiname":"Privolzhskiy Tretiy",
    "gn:country_code":"RU",
    "gn:dem":-22,
    "gn:feature_class":"P",
    "gn:feature_code":"PPL",
    "gn:name":"Privolzhskiy Tretiy",
    "gn:population":0,
    "gn:timezone":"Europe/Astrakhan",
    "iso:country":"RU",
    "name:rus_x_preferred":[
        "\u041f\u0440\u0438\u0432\u043e\u043b\u0436\u0441\u043a\u0438\u0439 \u0422\u0440\u0435\u0442\u0438\u0439"
    ],
    "name:und_x_variant":[
        "\u041f\u0440\u0438\u0432\u043e\u043b\u0436\u0441\u043a\u0438\u0439 \u0422\u0440\u0435\u0442\u0438\u0439"
    ],
    "wof:name":"Privolzhskiy Tretiy",
    "wof:placetype":"locality"
},
  "geometry": {"coordinates":[47.21667,46.35],"type":"Point"}
}