{
  "type": "Feature",
  "properties": {
    "gn:admin1_code":"64",
    "gn:admin2_code":"2128971",
    "gn:asciiname":"Zeikomae",
    "gn:country_code":"RU",
    "gn:dem":2,
    "gn:feature_class":"P",
    "gn:feature_code":"PPL",
    "gn:name":"Zeikomae",
    "gn:population":0,
    "gn:timezone":"Asia/Tokyo",
    "iso:country":"RU",
    "name:jpn_x_preferred":[
        "\u7a0e\u5eab\u524d"
    ],
    "name:jpn_x_variant":[
        "\u305c\u3044\u3053\u307e\u3048",
        "\u30bc\u30a4\u30b3\u30de\u30a8"
    ],
    "wof:name":"Zeikomae",
    "wof:placetype":"locality"
},
  "geometry": {"coordinates":[146.07513,43.42204],"type":"Point"}
}