{
  "type": "Feature",
  "properties": {
    "gn:admin1_code":"90",
    "gn:asciiname":"Matyushata",
    "gn:country_code":"RU",
    "gn:dem":310,
    "gn:feature_class":"P",
    "gn:feature_code":"PPL",
    "gn:name":"Matyushata",
    "gn:population":0,
    "gn:timezone":"Asia/Yekaterinburg",
    "iso:country":"RU",
    "name:rus_x_preferred":[
        "\u041c\u0430\u0442\u044e\u0448\u0430\u0442\u0430"
    ],
    "name:und_x_variant":[
        "\u041c\u0430\u0442\u044e\u0448\u0430\u0442\u0430"
    ],
    "wof:name":"Matyushata",
    "wof:placetype":"locality"
},
  "geometry": {"coordinates":[58.08333,57.58333],"type":"Point"}
}