{
  "type": "Feature",
  "properties": {
    "gn:admin1_code":"40",
    "gn:asciiname":"Kamagan",
    "gn:country_code":"RU",
    "gn:dem":117,
    "gn:feature_class":"P",
    "gn:feature_code":"PPL",
    "gn:name":"Kamagan",
    "gn:population":0,
    "gn:timezone":"Asia/Yekaterinburg",
    "iso:country":"RU",
    "name:eng_x_preferred":[
        "Kamagan"
    ],
    "name:nor_x_preferred":[
        "Kamagan"
    ],
    "name:rus_x_preferred":[
        "\u041a\u0430\u043c\u0430\u0433\u0430\u043d"
    ],
    "name:und_x_variant":[
        "\u041a\u0430\u043c\u0430\u0433\u0430\u043d",
        "Kamagan"
    ],
    "wof:name":"Kamagan",
    "wof:placetype":"locality"
},
  "geometry": {"coordinates":[64.28528,54.595],"type":"Point"}
}