{
  "type": "Feature",
  "properties": {
    "gn:admin1_code":"85.0",
    "gn:asciiname":"Bol'shoy Dvor",
    "gn:country_code":"RU",
    "gn:dem":126,
    "gn:feature_class":"P",
    "gn:feature_code":"PPL",
    "gn:name":"Bol\u2019shoy Dvor",
    "gn:population":0,
    "gn:timezone":"Europe/Moscow",
    "iso:country":"RU",
    "name:rus_x_preferred":[
        "\u0411\u043e\u043b\u044c\u0448\u043e\u0439 \u0414\u0432\u043e\u0440"
    ],
    "name:und_x_variant":[
        "Bol\u2019shoy Dvor"
    ],
    "wof:name":"Bol'shoy Dvor",
    "wof:placetype":"locality"
},
  "geometry": {"coordinates":[38.5029,59.4618],"type":"Point"}
}