{
  "type": "Feature",
  "properties": {
    "gn:admin1_code":"56",
    "gn:asciiname":"Khoroshilovo",
    "gn:country_code":"RU",
    "gn:dem":229,
    "gn:feature_class":"P",
    "gn:feature_code":"PPL",
    "gn:name":"Khoroshilovo",
    "gn:population":0,
    "gn:timezone":"Europe/Moscow",
    "iso:country":"RU",
    "name:eng_x_preferred":[
        "Khoroshilovo"
    ],
    "name:nor_x_preferred":[
        "Khorosjilovo"
    ],
    "name:rus_x_preferred":[
        "\u0425\u043e\u0440\u043e\u0448\u0438\u043b\u043e\u0432\u043e"
    ],
    "name:und_x_variant":[
        "Khoroshilova"
    ],
    "wof:name":"Khoroshilovo",
    "wof:placetype":"locality"
},
  "geometry": {"coordinates":[35.63118,52.87976],"type":"Point"}
}