{
  "type": "Feature",
  "properties": {
    "gn:admin1_code":"77",
    "gn:asciiname":"Yakovlevo",
    "gn:country_code":"RU",
    "gn:dem":280,
    "gn:feature_class":"P",
    "gn:feature_code":"PPL",
    "gn:name":"Yakovlevo",
    "gn:population":0,
    "gn:timezone":"Europe/Moscow",
    "iso:country":"RU",
    "wof:name":"Yakovlevo",
    "wof:placetype":"locality"
},
  "geometry": {"coordinates":[34.12509,57.3122],"type":"Point"}
}