{
  "type": "Feature",
  "properties": {
    "gn:admin1_code":"43",
    "gn:asciiname":"Nizhneye Bol'shoye",
    "gn:country_code":"RU",
    "gn:dem":184,
    "gn:feature_class":"P",
    "gn:feature_code":"PPL",
    "gn:name":"Nizhneye Bol\u2019shoye",
    "gn:population":0,
    "gn:timezone":"Europe/Moscow",
    "iso:country":"RU",
    "name:rus_x_preferred":[
        "\u041d\u0438\u0436\u043d\u0435\u0435 \u0411\u043e\u043b\u044c\u0448\u043e\u0435"
    ],
    "name:und_x_variant":[
        "Nizhneye Bol\u2019shoye",
        "Nizhne-Bol\u2019shoye"
    ],
    "wof:name":"Nizhneye Bol'shoye",
    "wof:placetype":"locality"
},
  "geometry": {"coordinates":[37.9078,51.9933],"type":"Point"}
}