{
  "type": "Feature",
  "properties": {
    "gn:admin1_code":"65",
    "gn:asciiname":"Yelshanka",
    "gn:country_code":"RU",
    "gn:dem":89,
    "gn:feature_class":"P",
    "gn:feature_code":"PPL",
    "gn:name":"Yelshanka",
    "gn:population":0,
    "gn:timezone":"Europe/Samara",
    "iso:country":"RU",
    "name:rus_x_preferred":[
        "\u0415\u043b\u0448\u0430\u043d\u043a\u0430"
    ],
    "name:und_x_variant":[
        "Novaya Yelshanka",
        "Yelshanka"
    ],
    "wof:name":"Yelshanka",
    "wof:placetype":"locality"
},
  "geometry": {"coordinates":[50.20281,53.69074000000001],"type":"Point"}
}