{
  "type": "Feature",
  "properties": {
    "gn:admin1_code":"85",
    "gn:asciiname":"Shelenidovo",
    "gn:country_code":"RU",
    "gn:dem":167,
    "gn:feature_class":"P",
    "gn:feature_code":"PPL",
    "gn:name":"Shelenidovo",
    "gn:population":0,
    "gn:timezone":"Europe/Moscow",
    "iso:country":"RU",
    "name:rus_x_preferred":[
        "\u0428\u0435\u043b\u0435\u043d\u0438\u0434\u043e\u0432\u043e"
    ],
    "name:und_x_variant":[
        "\u0428\u0435\u043b\u0435\u043d\u0438\u0434\u043e\u0432\u043e"
    ],
    "wof:name":"Shelenidovo",
    "wof:placetype":"locality"
},
  "geometry": {"coordinates":[35.8438,59.9894],"type":"Point"}
}