{
  "type": "Feature",
  "properties": {
    "gn:admin1_code":"57",
    "gn:asciiname":"Krivozer'ye",
    "gn:country_code":"RU",
    "gn:dem":141,
    "gn:feature_class":"P",
    "gn:feature_code":"PPL",
    "gn:name":"Krivoz\u00ebr\u2019ye",
    "gn:population":0,
    "gn:timezone":"Europe/Moscow",
    "iso:country":"RU",
    "name:rus_x_preferred":[
        "\u041a\u0440\u0438\u0432\u043e\u0437\u0451\u0440\u044c\u0435"
    ],
    "name:und_x_variant":[
        "Krivoz\u00ebr\u2019ye",
        "\u041a\u0440\u0438\u0432\u043e\u0437\u0451\u0440\u044c\u0435"
    ],
    "wof:name":"Krivozer'ye",
    "wof:placetype":"locality"
},
  "geometry": {"coordinates":[44.9763,53.1491],"type":"Point"}
}