{
  "type": "Feature",
  "properties": {
    "gn:admin1_code":"69",
    "gn:asciiname":"Yes'kovo",
    "gn:country_code":"RU",
    "gn:dem":164,
    "gn:feature_class":"P",
    "gn:feature_code":"PPL",
    "gn:name":"Yes\u2019kovo",
    "gn:population":0,
    "gn:timezone":"Europe/Moscow",
    "iso:country":"RU",
    "name:eng_x_preferred":[
        "Yes'kovo"
    ],
    "name:nor_x_preferred":[
        "Jeskovo"
    ],
    "name:rus_x_preferred":[
        "\u0415\u0441\u044c\u043a\u043e\u0432\u043e"
    ],
    "name:und_x_variant":[
        "Yes\u2019kovo"
    ],
    "wof:name":"Yes'kovo",
    "wof:placetype":"locality"
},
  "geometry": {"coordinates":[31.69192,55.26581],"type":"Point"}
}