{
  "type": "Feature",
  "properties": {
    "gn:admin1_code":"77",
    "gn:asciiname":"Konyshkino",
    "gn:country_code":"RU",
    "gn:dem":141,
    "gn:feature_class":"P",
    "gn:feature_code":"PPL",
    "gn:name":"Konyshkino",
    "gn:population":0,
    "gn:timezone":"Europe/Moscow",
    "iso:country":"RU",
    "name:rus_x_preferred":[
        "\u041a\u043e\u043d\u044b\u0448\u043a\u0438\u043d\u043e"
    ],
    "wof:name":"Konyshkino",
    "wof:placetype":"locality"
},
  "geometry": {"coordinates":[38.1099,57.2511],"type":"Point"}
}