{
  "type": "Feature",
  "properties": {
    "gn:admin1_code":"84",
    "gn:asciiname":"Khoroshenskiy",
    "gn:country_code":"RU",
    "gn:dem":110,
    "gn:feature_class":"P",
    "gn:feature_code":"PPL",
    "gn:name":"Khoroshenskiy",
    "gn:population":0,
    "gn:timezone":"Europe/Volgograd",
    "iso:country":"RU",
    "name:eng_x_preferred":[
        "Khoroshinskiy"
    ],
    "name:nor_x_preferred":[
        "Khorosjenskij"
    ],
    "name:rus_x_preferred":[
        "\u0425\u043e\u0440\u043e\u0448\u0435\u043d\u0441\u043a\u0438\u0439"
    ],
    "name:und_x_variant":[
        "Khoroshen\u2019kiy",
        "Khoroshinskoye",
        "Khoroshenskiy",
        "Khoroshenskoye"
    ],
    "wof:name":"Khoroshenskiy",
    "wof:placetype":"locality"
},
  "geometry": {"coordinates":[41.7328,50.2866],"type":"Point"}
}