{
  "type": "Feature",
  "properties": {
    "gn:admin1_code":"8",
    "gn:asciiname":"Verkhnesalimovo",
    "gn:country_code":"RU",
    "gn:dem":375,
    "gn:feature_class":"P",
    "gn:feature_code":"PPL",
    "gn:name":"Verkhnesalimovo",
    "gn:population":0,
    "gn:timezone":"Asia/Yekaterinburg",
    "iso:country":"RU",
    "name:bak_x_preferred":[
        "\u04ae\u0440\u0433\u0435 \u0421\u04d9\u043b\u0438\u043c"
    ],
    "name:che_x_preferred":[
        "\u0412\u0435\u0440\u0445\u043d\u0435\u0441\u0430\u043b\u0438\u043c\u043e\u0432\u043e"
    ],
    "name:eng_x_preferred":[
        "Verkhnesalimovo"
    ],
    "name:hye_x_preferred":[
        "\u054e\u0565\u0580\u056d\u0576\u0565\u057d\u0561\u056c\u056b\u0574\u0578\u057e\u0578"
    ],
    "name:kat_x_preferred":[
        "\u10d5\u10d4\u10e0\u10ee\u10dc\u10d4\u10e1\u10d0\u10da\u10d8\u10db\u10dd\u10d5\u10dd"
    ],
    "name:kaz_x_preferred":[
        "\u0416\u043e\u0493\u0430\u0440\u0493\u044b \u0441\u0430\u043b\u0438\u043c"
    ],
    "name:kir_x_preferred":[
        "\u0416\u043e\u0433\u043e\u0440\u043a\u0443 \u0441\u0430\u043b\u0438\u043c"
    ],
    "name:nor_x_preferred":[
        "Verkhnesalimovo"
    ],
    "name:rus_x_preferred":[
        "\u0412\u0435\u0440\u0445\u043d\u0435\u0441\u0430\u043b\u0438\u043c\u043e\u0432\u043e"
    ],
    "name:tat_x_preferred":[
        "\u042e\u0433\u0430\u0440\u044b \u0421\u04d9\u043b\u0438\u043c"
    ],
    "name:ukr_x_preferred":[
        "\u0412\u0435\u0440\u0445\u043d\u044c\u043e\u0441\u0430\u043b\u0456\u043c\u043e\u0432\u043e"
    ],
    "name:und_x_variant":[
        "Verkhnyaya Salimova"
    ],
    "wof:name":"Verkhnesalimovo",
    "wof:placetype":"locality"
},
  "geometry": {"coordinates":[58.02806,52.2125],"type":"Point"}
}