{
  "type": "Feature",
  "properties": {
    "gn:admin1_code":"8",
    "gn:asciiname":"Verkhnesalimovo",
    "gn:country_code":"RU",
    "gn:dem":375,
    "gn:feature_class":"P",
    "gn:feature_code":"PPL",
    "gn:name":"Verkhnesalimovo",
    "gn:population":0,
    "gn:timezone":"Asia/Yekaterinburg",
    "iso:country":"RU",
    "name:eng_x_preferred":[
        "Verkhnesalimovo"
    ],
    "name:nor_x_preferred":[
        "Verkhnesalimovo"
    ],
    "name:rus_x_preferred":[
        "\u0412\u0435\u0440\u0445\u043d\u0435\u0441\u0430\u043b\u0438\u043c\u043e\u0432\u043e"
    ],
    "name:und_x_variant":[
        "Verkhnyaya Salimova",
        "Verkhnesalimovo"
    ],
    "wof:name":"Verkhnesalimovo",
    "wof:placetype":"locality"
},
  "geometry": {"coordinates":[58.02806,52.2125],"type":"Point"}
}