{
  "type": "Feature",
  "properties": {
    "gn:admin1_code":"76.0",
    "gn:asciiname":"Barkovo",
    "gn:country_code":"RU",
    "gn:dem":248,
    "gn:feature_class":"P",
    "gn:feature_code":"PPL",
    "gn:name":"Barkovo",
    "gn:population":0,
    "gn:timezone":"Europe/Moscow",
    "iso:country":"RU",
    "name:nor_x_preferred":[
        "Barkovo"
    ],
    "name:rus_x_preferred":[
        "\u0411\u0430\u0440\u043a\u043e\u0432\u043e"
    ],
    "wof:name":"Barkovo",
    "wof:placetype":"locality"
},
  "geometry": {"coordinates":[37.62598,53.34865],"type":"Point"}
}