{
  "type": "Feature",
  "properties": {
    "gn:admin1_code":"71",
    "gn:asciiname":"Novoselova",
    "gn:country_code":"RU",
    "gn:dem":80,
    "gn:feature_class":"P",
    "gn:feature_code":"PPL",
    "gn:name":"Novos\u00eblova",
    "gn:population":0,
    "gn:timezone":"Asia/Yekaterinburg",
    "iso:country":"RU",
    "name:rus_x_preferred":[
        "\u041d\u043e\u0432\u043e\u0441\u0451\u043b\u043e\u0432\u0430"
    ],
    "name:und_x_variant":[
        "Novos\u00eblova",
        "\u041d\u043e\u0432\u043e\u0441\u0451\u043b\u043e\u0432\u0430"
    ],
    "wof:name":"Novoselova",
    "wof:placetype":"locality"
},
  "geometry": {"coordinates":[63.99977,57.91248],"type":"Point"}
}