{
  "type": "Feature",
  "properties": {
    "gn:admin1_code":"77.0",
    "gn:asciiname":"Bolotovo",
    "gn:country_code":"RU",
    "gn:dem":187,
    "gn:feature_class":"P",
    "gn:feature_code":"PPL",
    "gn:name":"Bolotovo",
    "gn:population":0,
    "gn:timezone":"Europe/Moscow",
    "iso:country":"RU",
    "name:nor_x_preferred":[
        "Bolotovo"
    ],
    "name:rus_x_preferred":[
        "\u0411\u043e\u043b\u043e\u0442\u043e\u0432\u043e"
    ],
    "wof:name":"Bolotovo",
    "wof:placetype":"locality"
},
  "geometry": {"coordinates":[35.31193,56.1817],"type":"Point"}
}