{
  "type": "Feature",
  "properties": {
    "gn:admin1_code":"71",
    "gn:asciiname":"Kuznetsovskiy",
    "gn:cc2":"RU",
    "gn:country_code":"RU",
    "gn:dem":323,
    "gn:feature_class":"P",
    "gn:feature_code":"PPL",
    "gn:name":"Kuznetsovskiy",
    "gn:population":0,
    "gn:timezone":"Asia/Yekaterinburg",
    "iso:country":"RU",
    "name:und_x_variant":[
        "Kuznetsovka",
        "Kuznetsovskiy"
    ],
    "wof:name":"Kuznetsovskiy",
    "wof:placetype":"locality"
},
  "geometry": {"coordinates":[58.13333000000001,57.46666999999999],"type":"Point"}
}