{
  "type": "Feature",
  "properties": {
    "gn:admin1_code":"85",
    "gn:asciiname":"Kostyuninskaya",
    "gn:country_code":"RU",
    "gn:dem":178,
    "gn:feature_class":"P",
    "gn:feature_code":"PPL",
    "gn:name":"Kostyuninskaya",
    "gn:population":0,
    "gn:timezone":"Europe/Moscow",
    "iso:country":"RU",
    "name:eng_x_preferred":[
        "Kostyuninskaya"
    ],
    "name:nor_x_preferred":[
        "Kostjuninskaja"
    ],
    "name:rus_x_preferred":[
        "\u041a\u043e\u0441\u0442\u044e\u043d\u0438\u043d\u0441\u043a\u0430\u044f"
    ],
    "name:und_x_variant":[
        "\u041a\u043e\u0441\u0442\u044e\u043d\u0438\u043d\u0441\u043a\u0430\u044f",
        "Kostyuninskaya"
    ],
    "wof:name":"Kostyuninskaya",
    "wof:placetype":"locality"
},
  "geometry": {"coordinates":[40.90455,60.36524],"type":"Point"}
}