{
  "type": "Feature",
  "properties": {
    "gn:admin1_code":"42",
    "gn:asciiname":"Okunevo",
    "gn:cc2":"RU",
    "gn:country_code":"RU",
    "gn:dem":33,
    "gn:feature_class":"P",
    "gn:feature_code":"PPL",
    "gn:name":"Okun\u00ebvo",
    "gn:population":0,
    "gn:timezone":"Europe/Moscow",
    "iso:country":"RU",
    "name:fin_x_preferred":[
        "Koverila"
    ],
    "name:rus_x_preferred":[
        "\u041e\u043a\u0443\u043d\u0451\u0432\u043e"
    ],
    "name:und_x_variant":[
        "Suopelto",
        "Okun\u00ebvo",
        "\u041e\u043a\u0443\u043d\u0451\u0432\u043e"
    ],
    "wof:name":"Okunevo",
    "wof:placetype":"locality"
},
  "geometry": {"coordinates":[29.76667,61.13333000000001],"type":"Point"}
}