{
  "type": "Feature",
  "properties": {
    "gn:admin1_code":"17",
    "gn:admin2_code":"Charodinskiy Rayon",
    "gn:asciiname":"Khinub",
    "gn:country_code":"RU",
    "gn:dem":1694,
    "gn:feature_class":"P",
    "gn:feature_code":"PPL",
    "gn:name":"Khinub",
    "gn:population":0,
    "gn:timezone":"Europe/Moscow",
    "iso:country":"RU",
    "name:rus_x_preferred":[
        "\u0425\u0438\u043d\u0443\u0431"
    ],
    "name:und_x_variant":[
        "\u0425\u0438\u043d\u0443\u0431"
    ],
    "wof:name":"Khinub",
    "wof:placetype":"locality"
},
  "geometry": {"coordinates":[46.82406,42.17454],"type":"Point"}
}