{
  "type": "Feature",
  "properties": {
    "gn:admin1_code":"33",
    "gn:asciiname":"Kopyly",
    "gn:country_code":"RU",
    "gn:dem":115,
    "gn:feature_class":"P",
    "gn:feature_code":"PPL",
    "gn:name":"Kopyly",
    "gn:population":0,
    "gn:timezone":"Europe/Kirov",
    "iso:country":"RU",
    "name:rus_x_preferred":[
        "\u041a\u043e\u043f\u044b\u043b\u044b"
    ],
    "wof:name":"Kopyly",
    "wof:placetype":"locality"
},
  "geometry": {"coordinates":[47.8635,57.5795],"type":"Point"}
}