{
  "type": "Feature",
  "properties": {
    "gn:admin1_code":"33",
    "gn:asciiname":"Kopyly",
    "gn:country_code":"RU",
    "gn:dem":115,
    "gn:feature_class":"P",
    "gn:feature_code":"PPL",
    "gn:name":"Kopyly",
    "gn:population":0,
    "gn:timezone":"Europe/Kirov",
    "iso:country":"RU",
    "name:bul_x_preferred":[
        "\u041a\u043e\u043f\u0438\u043b\u0438"
    ],
    "name:crh_x_preferred":[
        "Kop\u0131l\u0131"
    ],
    "name:deu_x_preferred":[
        "Kopyly"
    ],
    "name:est_x_preferred":[
        "Kop\u00f5l\u00f5"
    ],
    "name:hrv_x_preferred":[
        "Kopyly"
    ],
    "name:hye_x_preferred":[
        "\u053f\u0578\u057a\u056b\u056c\u056b"
    ],
    "name:mkd_x_preferred":[
        "\u041a\u043e\u043f\u0438\u043b\u0438"
    ],
    "name:nld_x_preferred":[
        "Kopyly"
    ],
    "name:pol_x_preferred":[
        "Kopy\u0142y"
    ],
    "name:ron_x_preferred":[
        "Kop\u00eel\u00ee"
    ],
    "name:rus_x_preferred":[
        "\u041a\u043e\u043f\u044b\u043b\u044b"
    ],
    "name:slk_x_preferred":[
        "Kopyly"
    ],
    "name:slv_x_preferred":[
        "Kopili"
    ],
    "name:swe_x_preferred":[
        "Kopyly"
    ],
    "name:ukr_x_preferred":[
        "\u041a\u043e\u043f\u0438\u043b\u0438"
    ],
    "wof:name":"Kopyly",
    "wof:placetype":"locality"
},
  "geometry": {"coordinates":[47.8635,57.5795],"type":"Point"}
}