{
  "type": "Feature",
  "properties": {
    "gn:admin1_code":"51.0",
    "gn:asciiname":"Strekalovo",
    "gn:country_code":"RU",
    "gn:dem":102,
    "gn:feature_class":"P",
    "gn:feature_code":"PPL",
    "gn:name":"Strekalovo",
    "gn:population":0,
    "gn:timezone":"Europe/Moscow",
    "iso:country":"RU",
    "name:nor_x_preferred":[
        "Strekalovo"
    ],
    "name:rus_x_preferred":[
        "\u0421\u0442\u0440\u0435\u043a\u0430\u043b\u043e\u0432\u043e"
    ],
    "wof:name":"Strekalovo",
    "wof:placetype":"locality"
},
  "geometry": {"coordinates":[43.6088,56.84768],"type":"Point"}
}