{
  "type": "Feature",
  "properties": {
    "gn:admin1_code":"52",
    "gn:asciiname":"Zhelnino",
    "gn:country_code":"RU",
    "gn:dem":191,
    "gn:feature_class":"P",
    "gn:feature_code":"PPL",
    "gn:name":"Zhelnino",
    "gn:population":0,
    "gn:timezone":"Europe/Moscow",
    "iso:country":"RU",
    "name:che_x_preferred":[
        "\u0416\u0435\u043b\u043d\u0438\u043d\u043e"
    ],
    "name:rus_x_preferred":[
        "\u0416\u0435\u043b\u043d\u0438\u043d\u043e"
    ],
    "wof:name":"Zhelnino",
    "wof:placetype":"locality"
},
  "geometry": {"coordinates":[34.79686,58.52582],"type":"Point"}
}