{
  "type": "Feature",
  "properties": {
    "gn:admin1_code":"91",
    "gn:asciiname":"Sergino",
    "gn:country_code":"RU",
    "gn:dem":297,
    "gn:feature_class":"P",
    "gn:feature_code":"PPL",
    "gn:name":"Sergino",
    "gn:population":0,
    "gn:timezone":"Asia/Krasnoyarsk",
    "iso:country":"RU",
    "name:rus_x_preferred":[
        "\u0421\u0435\u0440\u0433\u0438\u043d\u043e"
    ],
    "name:ukr_x_preferred":[
        "\u0421\u0435\u0440\u0433\u0438\u043d\u043e"
    ],
    "wof:name":"Sergino",
    "wof:placetype":"locality"
},
  "geometry": {"coordinates":[91.76533000000001,56.06964],"type":"Point"}
}