{
  "type": "Feature",
  "properties": {
    "gn:admin1_code":"77",
    "gn:asciiname":"Meshchera",
    "gn:country_code":"RU",
    "gn:dem":172,
    "gn:feature_class":"P",
    "gn:feature_code":"PPL",
    "gn:name":"Meshchera",
    "gn:population":0,
    "gn:timezone":"Europe/Moscow",
    "iso:country":"RU",
    "name:rus_x_preferred":[
        "\u041c\u0435\u0449\u0435\u0440\u0430"
    ],
    "name:und_x_variant":[
        "\u041c\u0435\u0449\u0435\u0440\u0430"
    ],
    "wof:name":"Meshchera",
    "wof:placetype":"locality"
},
  "geometry": {"coordinates":[37.3062,57.6433],"type":"Point"}
}