{
  "type": "Feature",
  "properties": {
    "gn:admin1_code":"6",
    "gn:asciiname":"Lepsha",
    "gn:country_code":"RU",
    "gn:dem":88,
    "gn:feature_class":"P",
    "gn:feature_code":"PPL",
    "gn:name":"Lepsha",
    "gn:population":0,
    "gn:timezone":"Europe/Moscow",
    "iso:country":"RU",
    "name:eng_x_preferred":[
        "Lepsha"
    ],
    "name:nor_x_preferred":[
        "Lepsja"
    ],
    "name:rus_x_preferred":[
        "\u041b\u0435\u043f\u0448\u0430"
    ],
    "name:und_x_variant":[
        "Lepshinskiy",
        "\u041b\u0435\u043f\u0448\u0430",
        "Lepsha"
    ],
    "wof:name":"Lepsha",
    "wof:placetype":"locality"
},
  "geometry": {"coordinates":[40.3346,62.325],"type":"Point"}
}