{
  "type": "Feature",
  "properties": {
    "gn:admin1_code":"88.0",
    "gn:asciiname":"Nagorskoye",
    "gn:country_code":"RU",
    "gn:dem":115,
    "gn:feature_class":"P",
    "gn:feature_code":"PPL",
    "gn:name":"Nagorskoye",
    "gn:population":0,
    "gn:timezone":"Europe/Moscow",
    "iso:country":"RU",
    "name:rus_x_preferred":[
        "\u041d\u0430\u0433\u043e\u0440\u0441\u043a\u043e\u0435"
    ],
    "wof:name":"Nagorskoye",
    "wof:placetype":"locality"
},
  "geometry": {"coordinates":[40.76562,58.17222],"type":"Point"}
}