{
  "type": "Feature",
  "properties": {
    "gn:admin1_code":"71",
    "gn:asciiname":"Novaya Yel'nya",
    "gn:country_code":"RU",
    "gn:dem":339,
    "gn:feature_class":"P",
    "gn:feature_code":"PPL",
    "gn:name":"Novaya Yel\u2019nya",
    "gn:population":0,
    "gn:timezone":"Asia/Yekaterinburg",
    "iso:country":"RU",
    "name:rus_x_preferred":[
        "\u041d\u043e\u0432\u0430\u044f \u0415\u043b\u044c\u043d\u044f"
    ],
    "name:und_x_variant":[
        "Novaya Yel\u2019nya",
        "\u041d\u043e\u0432\u0430\u044f \u0415\u043b\u044c\u043d\u044f"
    ],
    "wof:name":"Novaya Yel'nya",
    "wof:placetype":"locality"
},
  "geometry": {"coordinates":[59.24028000000001,56.62028000000001],"type":"Point"}
}