{
  "type": "Feature",
  "properties": {
    "gn:admin1_code":"72.0",
    "gn:asciiname":"Likhachevka",
    "gn:country_code":"RU",
    "gn:dem":154,
    "gn:feature_class":"P",
    "gn:feature_code":"PPL",
    "gn:name":"Likhach\u00ebvka",
    "gn:population":0,
    "gn:timezone":"Europe/Moscow",
    "iso:country":"RU",
    "name:rus_x_preferred":[
        "Likhach\u00ebvka"
    ],
    "name:rus_x_variant":[
        "\u041b\u0438\u0445\u0430\u0447\u0451\u0432\u043a\u0430",
        "Bol\u2019shaya Likhach\u00ebvka",
        "Likhachevka Bol\u2019shaya"
    ],
    "name:und_x_variant":[
        "Likhachevka Bol\u2019shaya",
        "Bol\u2019shaya Likhach\u00ebvka"
    ],
    "wof:name":"Likhachevka",
    "wof:placetype":"locality"
},
  "geometry": {"coordinates":[40.9784,52.2326],"type":"Point"}
}