{
  "type": "Feature",
  "properties": {
    "gn:admin1_code":"61.0",
    "gn:asciiname":"Krasnyy Partizan",
    "gn:country_code":"RU",
    "gn:dem":151,
    "gn:feature_class":"P",
    "gn:feature_code":"PPL",
    "gn:name":"Krasnyy Partizan",
    "gn:population":0,
    "gn:timezone":"Europe/Moscow",
    "iso:country":"RU",
    "name:rus_x_preferred":[
        "\u041a\u0440\u0430\u0441\u043d\u044b\u0439 \u041f\u0430\u0440\u0442\u0438\u0437\u0430\u043d"
    ],
    "wof:name":"Krasnyy Partizan",
    "wof:placetype":"locality"
},
  "geometry": {"coordinates":[40.2373,48.83752],"type":"Point"}
}