{
  "type": "Feature",
  "properties": {
    "gn:admin1_code":"40",
    "gn:asciiname":"Beloyarka Pervaya",
    "gn:country_code":"RU",
    "gn:dem":123,
    "gn:feature_class":"P",
    "gn:feature_code":"PPL",
    "gn:name":"Beloyarka Pervaya",
    "gn:population":0,
    "gn:timezone":"Asia/Yekaterinburg",
    "iso:country":"RU",
    "name:nor_x_preferred":[
        "Belojarka Pervaja"
    ],
    "name:rus_x_preferred":[
        "\u0411\u0435\u043b\u043e\u044f\u0440\u043a\u0430 \u041f\u0435\u0440\u0432\u0430\u044f"
    ],
    "name:und_x_variant":[
        "Beloyarka Vtoraya",
        "Beloyarskoye",
        "Beloyarka Pervaya"
    ],
    "wof:name":"Beloyarka Pervaya",
    "wof:placetype":"locality"
},
  "geometry": {"coordinates":[63.23972,55.97361],"type":"Point"}
}