{
  "type": "Feature",
  "properties": {
    "gn:admin1_code":"80",
    "gn:asciiname":"Menil",
    "gn:country_code":"RU",
    "gn:dem":193,
    "gn:feature_class":"P",
    "gn:feature_code":"PPL",
    "gn:name":"Menil",
    "gn:population":0,
    "gn:timezone":"Europe/Samara",
    "iso:country":"RU",
    "name:eng_x_preferred":[
        "Menil"
    ],
    "name:nor_x_preferred":[
        "Menil"
    ],
    "name:rus_x_preferred":[
        "\u041c\u0435\u043d\u0438\u043b"
    ],
    "wof:name":"Menil",
    "wof:placetype":"locality"
},
  "geometry": {"coordinates":[53.0918,57.6352],"type":"Point"}
}