{
  "type": "Feature",
  "properties": {
    "gn:admin1_code":"86",
    "gn:asciiname":"Nikol'skoye Vtoroye",
    "gn:country_code":"RU",
    "gn:dem":163,
    "gn:feature_class":"P",
    "gn:feature_code":"PPL",
    "gn:name":"Nikol\u2019skoye Vtoroye",
    "gn:population":0,
    "gn:timezone":"Europe/Moscow",
    "iso:country":"RU",
    "name:rus_x_preferred":[
        "Nikol\u2019skoye Vtoroye"
    ],
    "name:rus_x_variant":[
        "\u041d\u0438\u043a\u043e\u043b\u044c\u0441\u043a\u043e\u0435 \u0412\u0442\u043e\u0440\u043e\u0435"
    ],
    "name:und_x_variant":[
        "Gudovka",
        "Vtoroye Nikol\u2019skoye"
    ],
    "wof:name":"Nikol'skoye Vtoroye",
    "wof:placetype":"locality"
},
  "geometry": {"coordinates":[40.0631,51.7399],"type":"Point"}
}