{
  "type": "Feature",
  "properties": {
    "gn:admin1_code":"56",
    "gn:asciiname":"Krasno-Kamenka",
    "gn:cc2":"RU",
    "gn:country_code":"RU",
    "gn:dem":226,
    "gn:feature_class":"P",
    "gn:feature_code":"PPL",
    "gn:name":"Krasno-Kamenka",
    "gn:population":0,
    "gn:timezone":"Europe/Moscow",
    "iso:country":"RU",
    "name:rus_x_preferred":[
        "\u041a\u0440\u0430\u0441\u043d\u043e-\u041a\u0430\u043c\u0435\u043d\u043a\u0430"
    ],
    "name:und_x_variant":[
        "Karpovo",
        "Krasno-Kamenka"
    ],
    "wof:name":"Krasno-Kamenka",
    "wof:placetype":"locality"
},
  "geometry": {"coordinates":[36.07361,53.23556],"type":"Point"}
}