{
  "type": "Feature",
  "properties": {
    "gn:admin1_code":"81",
    "gn:asciiname":"Novochufarovskiy",
    "gn:country_code":"RU",
    "gn:dem":148,
    "gn:feature_class":"P",
    "gn:feature_code":"PPL",
    "gn:name":"Novochufarovskiy",
    "gn:population":0,
    "gn:timezone":"Europe/Ulyanovsk",
    "iso:country":"RU",
    "name:rus_x_preferred":[
        "\u041d\u043e\u0432\u043e\u0447\u0443\u0444\u0430\u0440\u043e\u0432\u0441\u043a\u0438\u0439"
    ],
    "wof:name":"Novochufarovskiy",
    "wof:placetype":"locality"
},
  "geometry": {"coordinates":[47.3638,54.1117],"type":"Point"}
}