{
  "type": "Feature",
  "properties": {
    "gn:admin1_code":"33",
    "gn:asciiname":"Rylovy",
    "gn:country_code":"RU",
    "gn:dem":161,
    "gn:feature_class":"P",
    "gn:feature_code":"PPL",
    "gn:name":"Rylovy",
    "gn:population":0,
    "gn:timezone":"Europe/Kirov",
    "iso:country":"RU",
    "name:rus_x_preferred":[
        "\u0420\u044b\u043b\u043e\u0432\u044b"
    ],
    "name:und_x_variant":[
        "\u0420\u044b\u043b\u043e\u0432\u044b"
    ],
    "wof:name":"Rylovy",
    "wof:placetype":"locality"
},
  "geometry": {"coordinates":[48.87503,58.7145],"type":"Point"}
}