{
  "type": "Feature",
  "properties": {
    "gn:admin1_code":"72",
    "gn:asciiname":"Nadezhka",
    "gn:country_code":"RU",
    "gn:dem":159,
    "gn:feature_class":"P",
    "gn:feature_code":"PPL",
    "gn:name":"Nad\u00ebzhka",
    "gn:population":0,
    "gn:timezone":"Europe/Moscow",
    "iso:country":"RU",
    "name:rus_x_preferred":[
        "\u041d\u0430\u0434\u0451\u0436\u043a\u0430"
    ],
    "name:und_x_variant":[
        "Nad\u00ebzhka",
        "\u041d\u0430\u0434\u0451\u0436\u043a\u0430"
    ],
    "wof:name":"Nadezhka",
    "wof:placetype":"locality"
},
  "geometry": {"coordinates":[41.38333,53.63333000000001],"type":"Point"}
}