{
  "type": "Feature",
  "properties": {
    "gn:admin1_code":"76",
    "gn:asciiname":"Studenyy",
    "gn:country_code":"RU",
    "gn:dem":236,
    "gn:feature_class":"P",
    "gn:feature_code":"PPL",
    "gn:name":"Stud\u00ebnyy",
    "gn:population":0,
    "gn:timezone":"Europe/Moscow",
    "iso:country":"RU",
    "name:und_x_variant":[
        "Stud\u00ebnnyy",
        "Stud\u00ebnyy"
    ],
    "wof:name":"Studenyy",
    "wof:placetype":"locality"
},
  "geometry": {"coordinates":[37.50946,54.65369000000001],"type":"Point"}
}