{
  "type": "Feature",
  "properties": {
    "gn:admin1_code":"67",
    "gn:asciiname":"Kurovka",
    "gn:country_code":"RU",
    "gn:dem":66,
    "gn:feature_class":"P",
    "gn:feature_code":"PPL",
    "gn:name":"Kurovka",
    "gn:population":0,
    "gn:timezone":"Europe/Saratov",
    "iso:country":"RU",
    "name:eng_x_preferred":[
        "Kurovka"
    ],
    "name:nor_x_preferred":[
        "Kurovka"
    ],
    "name:rus_x_preferred":[
        "\u041a\u0443\u0440\u043e\u0432\u043a\u0430"
    ],
    "name:und_x_variant":[
        "Kurskaya",
        "Kurskoye"
    ],
    "wof:name":"Kurovka",
    "wof:placetype":"locality"
},
  "geometry": {"coordinates":[48.5405,50.7053],"type":"Point"}
}