{
  "type": "Feature",
  "properties": {
    "gn:admin1_code":"11",
    "gn:asciiname":"Namag",
    "gn:country_code":"RU",
    "gn:dem":803,
    "gn:feature_class":"P",
    "gn:feature_code":"PPL",
    "gn:name":"Namag",
    "gn:population":0,
    "gn:timezone":"Asia/Irkutsk",
    "iso:country":"RU",
    "wof:name":"Namag",
    "wof:placetype":"locality"
},
  "geometry": {"coordinates":[105.32971999999999,50.65639],"type":"Point"}
}