{
  "type": "Feature",
  "properties": {
    "gn:admin1_code":"69",
    "gn:asciiname":"Kosmach'",
    "gn:country_code":"RU",
    "gn:dem":207,
    "gn:feature_class":"P",
    "gn:feature_code":"PPL",
    "gn:name":"Kosmach\u2019",
    "gn:population":0,
    "gn:timezone":"Europe/Moscow",
    "iso:country":"RU",
    "name:rus_x_preferred":[
        "\u041a\u043e\u0441\u043c\u0430\u0447\u044c"
    ],
    "name:und_x_variant":[
        "Kosmach\u2019",
        "\u041a\u043e\u0441\u043c\u0430\u0447\u044c"
    ],
    "wof:name":"Kosmach'",
    "wof:placetype":"locality"
},
  "geometry": {"coordinates":[31.79389,54.18402],"type":"Point"}
}