{
  "type": "Feature",
  "properties": {
    "gn:admin1_code":"61",
    "gn:asciiname":"Nizhnepotapov",
    "gn:country_code":"RU",
    "gn:dem":46,
    "gn:feature_class":"P",
    "gn:feature_code":"PPL",
    "gn:name":"Nizhnepotapov",
    "gn:population":0,
    "gn:timezone":"Europe/Moscow",
    "iso:country":"RU",
    "name:rus_x_preferred":[
        "\u041d\u0438\u0436\u043d\u0435\u043f\u043e\u0442\u0430\u043f\u043e\u0432"
    ],
    "name:und_x_variant":[
        "Nizhniy Potapov",
        "Nizhnepotapov"
    ],
    "wof:name":"Nizhnepotapov",
    "wof:placetype":"locality"
},
  "geometry": {"coordinates":[41.03953,47.86753],"type":"Point"}
}