{
  "type": "Feature",
  "properties": {
    "gn:admin1_code":"76",
    "gn:asciiname":"Zlobino",
    "gn:country_code":"RU",
    "gn:dem":180,
    "gn:feature_class":"P",
    "gn:feature_code":"PPL",
    "gn:name":"Zlobino",
    "gn:population":0,
    "gn:timezone":"Europe/Moscow",
    "iso:country":"RU",
    "name:che_x_preferred":[
        "\u0417\u043b\u043e\u0431\u0438\u043d\u043e"
    ],
    "name:rus_x_preferred":[
        "\u0417\u043b\u043e\u0431\u0438\u043d\u043e"
    ],
    "wof:name":"Zlobino",
    "wof:placetype":"locality"
},
  "geometry": {"coordinates":[37.53267,54.72447],"type":"Point"}
}