{
  "type": "Feature",
  "properties": {
    "gn:admin1_code":"51.0",
    "gn:asciiname":"Cheredkovo",
    "gn:country_code":"RU",
    "gn:dem":76,
    "gn:feature_class":"P",
    "gn:feature_code":"PPL",
    "gn:name":"Cheredkovo",
    "gn:population":0,
    "gn:timezone":"Europe/Moscow",
    "iso:country":"RU",
    "name:und_x_variant":[
        "Cheretkovo",
        "Cheredkovo"
    ],
    "wof:name":"Cheredkovo",
    "wof:placetype":"locality"
},
  "geometry": {"coordinates":[43.59849000000001,56.5637],"type":"Point"}
}