{
  "type": "Feature",
  "properties": {
    "gn:admin1_code":"57",
    "gn:asciiname":"Georgiyevskiy",
    "gn:country_code":"RU",
    "gn:dem":156,
    "gn:feature_class":"P",
    "gn:feature_code":"PPL",
    "gn:name":"Georgiyevskiy",
    "gn:population":0,
    "gn:timezone":"Europe/Moscow",
    "iso:country":"RU",
    "name:rus_x_preferred":[
        "\u0413\u0435\u043e\u0440\u0433\u0438\u0435\u0432\u0441\u043a\u0438\u0439"
    ],
    "wof:name":"Georgiyevskiy",
    "wof:placetype":"locality"
},
  "geometry": {"coordinates":[44.3672,53.5656],"type":"Point"}
}