{
  "type": "Feature",
  "properties": {
    "gn:admin1_code":"91",
    "gn:asciiname":"Dvurechnaya",
    "gn:country_code":"RU",
    "gn:dem":330,
    "gn:feature_class":"P",
    "gn:feature_code":"PPL",
    "gn:name":"Dvurechnaya",
    "gn:population":0,
    "gn:timezone":"Asia/Krasnoyarsk",
    "iso:country":"RU",
    "name:eng_x_preferred":[
        "Dvurechnaya"
    ],
    "name:nor_x_preferred":[
        "Dvuretsjnaja"
    ],
    "name:rus_x_preferred":[
        "\u0414\u0432\u0443\u0440\u0435\u0447\u043d\u0430\u044f"
    ],
    "wof:name":"Dvurechnaya",
    "wof:placetype":"locality"
},
  "geometry": {"coordinates":[94.77,55.7108],"type":"Point"}
}