{
  "type": "Feature",
  "properties": {
    "gn:admin1_code":"29",
    "gn:asciiname":"P'yanovo",
    "gn:country_code":"RU",
    "gn:dem":159,
    "gn:feature_class":"P",
    "gn:feature_code":"PPL",
    "gn:name":"P\u2019yanovo",
    "gn:population":0,
    "gn:timezone":"Asia/Novokuznetsk",
    "iso:country":"RU",
    "name:eng_x_preferred":[
        "P'yanovo"
    ],
    "name:nor_x_preferred":[
        "Pjanovo"
    ],
    "name:rus_x_preferred":[
        "\u041f\u044c\u044f\u043d\u043e\u0432\u043e"
    ],
    "name:und_x_variant":[
        "P\u2019yankova",
        "P\u2019yanova",
        "\u041f\u044c\u044f\u043d\u043e\u0432\u043e",
        "P\u2019yanovo"
    ],
    "wof:name":"P'yanovo",
    "wof:placetype":"locality"
},
  "geometry": {"coordinates":[85.2971,54.9246],"type":"Point"}
}