{
  "type": "Feature",
  "properties": {
    "gn:admin1_code":"73",
    "gn:asciiname":"Vatan",
    "gn:country_code":"RU",
    "gn:dem":173,
    "gn:feature_class":"P",
    "gn:feature_code":"PPL",
    "gn:name":"Vatan",
    "gn:population":0,
    "gn:timezone":"Europe/Moscow",
    "iso:country":"RU",
    "name:deu_x_preferred":[
        "Vatan"
    ],
    "name:por_x_preferred":[
        "Vatan"
    ],
    "name:rus_x_preferred":[
        "\u0412\u0430\u0442\u0430\u043d"
    ],
    "name:rus_x_variant":[
        "Vatan"
    ],
    "name:spa_x_preferred":[
        "Vatan"
    ],
    "wof:name":"Vatan",
    "wof:placetype":"locality"
},
  "geometry": {"coordinates":[48.895,55.6271],"type":"Point"}
}