{
  "type": "Feature",
  "properties": {
    "gn:admin1_code":"42",
    "gn:asciiname":"Lipovka",
    "gn:country_code":"RU",
    "gn:dem":29,
    "gn:feature_class":"P",
    "gn:feature_code":"PPL",
    "gn:name":"Lipovka",
    "gn:population":0,
    "gn:timezone":"Europe/Moscow",
    "iso:country":"RU",
    "name:fin_x_preferred":[
        "Hannila"
    ],
    "name:rus_x_preferred":[
        "\u041b\u0438\u043f\u043e\u0432\u043a\u0430"
    ],
    "name:und_x_variant":[
        "Khannila",
        "Lipovka",
        "\u041b\u0438\u043f\u043e\u0432\u043a\u0430"
    ],
    "wof:name":"Lipovka",
    "wof:placetype":"locality"
},
  "geometry": {"coordinates":[28.97515,60.91708000000001],"type":"Point"}
}