{
  "type": "Feature",
  "properties": {
    "gn:admin1_code":"8.0",
    "gn:asciiname":"Ak-Chishma",
    "gn:country_code":"RU",
    "gn:dem":330,
    "gn:feature_class":"P",
    "gn:feature_code":"PPL",
    "gn:name":"Ak-Chishma",
    "gn:population":0,
    "gn:timezone":"Asia/Yekaterinburg",
    "iso:country":"RU",
    "name:nor_x_preferred":[
        "Ak-Tsjisjma"
    ],
    "name:rus_x_preferred":[
        "\u0410\u043a-\u0427\u0438\u0448\u043c\u0430"
    ],
    "wof:name":"Ak-Chishma",
    "wof:placetype":"locality"
},
  "geometry": {"coordinates":[54.75,53.35],"type":"Point"}
}