{
  "type": "Feature",
  "properties": {
    "gn:admin1_code":"51.0",
    "gn:asciiname":"Nekhlustino",
    "gn:country_code":"RU",
    "gn:dem":85,
    "gn:feature_class":"P",
    "gn:feature_code":"PPL",
    "gn:name":"Nekhlustino",
    "gn:population":0,
    "gn:timezone":"Europe/Moscow",
    "iso:country":"RU",
    "name:nor_x_preferred":[
        "Nekhlustino"
    ],
    "name:rus_x_preferred":[
        "\u041d\u0435\u0445\u043b\u0443\u0441\u0442\u0438\u043d\u043e"
    ],
    "wof:name":"Nekhlustino",
    "wof:placetype":"locality"
},
  "geometry": {"coordinates":[43.69247,56.56412],"type":"Point"}
}