{
  "type": "Feature",
  "properties": {
    "gn:admin1_code":"60",
    "gn:asciiname":"Rogovaya",
    "gn:country_code":"RU",
    "gn:dem":98,
    "gn:feature_class":"P",
    "gn:feature_code":"PPL",
    "gn:name":"Rogovaya",
    "gn:population":0,
    "gn:timezone":"Europe/Moscow",
    "iso:country":"RU",
    "name:rus_x_preferred":[
        "\u0420\u043e\u0433\u043e\u0432\u0430\u044f"
    ],
    "name:und_x_variant":[
        "\u0420\u043e\u0433\u043e\u0432\u0430\u044f"
    ],
    "wof:name":"Rogovaya",
    "wof:placetype":"locality"
},
  "geometry": {"coordinates":[30.48333,57.53333000000001],"type":"Point"}
}