{
  "type": "Feature",
  "properties": {
    "gn:admin1_code":"93",
    "gn:asciiname":"Shirokaya",
    "gn:country_code":"RU",
    "gn:dem":622,
    "gn:feature_class":"P",
    "gn:feature_code":"PPL",
    "gn:name":"Shirokaya",
    "gn:population":0,
    "gn:timezone":"Asia/Chita",
    "iso:country":"RU",
    "name:eng_x_preferred":[
        "Shirokaya"
    ],
    "name:nor_x_preferred":[
        "Sjirokaja"
    ],
    "name:rus_x_preferred":[
        "\u0428\u0438\u0440\u043e\u043a\u0430\u044f"
    ],
    "name:und_x_variant":[
        "Shirokoye"
    ],
    "wof:name":"Shirokaya",
    "wof:placetype":"locality"
},
  "geometry": {"coordinates":[119.59901000000001,51.36946],"type":"Point"}
}