{
  "type": "Feature",
  "properties": {
    "gn:admin1_code":"69",
    "gn:asciiname":"Gryastevo",
    "gn:country_code":"RU",
    "gn:dem":201,
    "gn:feature_class":"P",
    "gn:feature_code":"PPL",
    "gn:name":"Gryastevo",
    "gn:population":0,
    "gn:timezone":"Europe/Moscow",
    "iso:country":"RU",
    "name:rus_x_preferred":[
        "\u0413\u0440\u044f\u0441\u0442\u0435\u0432\u043e"
    ],
    "wof:name":"Gryastevo",
    "wof:placetype":"locality"
},
  "geometry": {"coordinates":[32.58333,54.45],"type":"Point"}
}