{
  "type": "Feature",
  "properties": {
    "gn:admin1_code":"60.0",
    "gn:asciiname":"Urochishche Kuznetsovo",
    "gn:country_code":"RU",
    "gn:dem":89,
    "gn:feature_class":"P",
    "gn:feature_code":"PPL",
    "gn:name":"Urochishche Kuznetsovo",
    "gn:population":0,
    "gn:timezone":"Europe/Moscow",
    "iso:country":"RU",
    "name:rus_x_preferred":[
        "\u0423\u0440\u043e\u0447\u0438\u0449\u0435 \u041a\u0443\u0437\u043d\u0435\u0446\u043e\u0432\u043e"
    ],
    "wof:name":"Urochishche Kuznetsovo",
    "wof:placetype":"locality"
},
  "geometry": {"coordinates":[28.54568,58.03272],"type":"Point"}
}