{
  "type": "Feature",
  "properties": {
    "gn:admin1_code":"60.0",
    "gn:asciiname":"Borstno",
    "gn:cc2":"RU",
    "gn:country_code":"RU",
    "gn:dem":79,
    "gn:feature_class":"P",
    "gn:feature_code":"PPL",
    "gn:name":"Borstno",
    "gn:population":0,
    "gn:timezone":"Europe/Moscow",
    "iso:country":"RU",
    "name:eng_x_preferred":[
        "Borstno"
    ],
    "name:nor_x_preferred":[
        "Borstno"
    ],
    "name:rus_x_preferred":[
        "\u0411\u043e\u0440\u0441\u0442\u043d\u043e"
    ],
    "name:und_x_variant":[
        "Borotno"
    ],
    "wof:name":"Borstno",
    "wof:placetype":"locality"
},
  "geometry": {"coordinates":[29.60278,58.15611],"type":"Point"}
}