{
  "type": "Feature",
  "properties": {
    "gn:admin1_code":"56.0",
    "gn:asciiname":"Bol'shoye Lykovo",
    "gn:country_code":"RU",
    "gn:dem":167,
    "gn:feature_class":"P",
    "gn:feature_code":"PPL",
    "gn:name":"Bol\u2019shoye Lykovo",
    "gn:population":0,
    "gn:timezone":"Europe/Moscow",
    "iso:country":"RU",
    "name:rus_x_preferred":[
        "\u0411\u043e\u043b\u044c\u0448\u043e\u0435 \u041b\u044b\u043a\u043e\u0432\u043e"
    ],
    "name:und_x_variant":[
        "Bol\u2019shoye Lykovo",
        "\u0411\u043e\u043b\u044c\u0448\u043e\u0435 \u041b\u044b\u043a\u043e\u0432\u043e"
    ],
    "wof:name":"Bol'shoye Lykovo",
    "wof:placetype":"locality"
},
  "geometry": {"coordinates":[36.71128,53.19472],"type":"Point"}
}