{
  "type": "Feature",
  "properties": {
    "gn:admin1_code":"47",
    "gn:asciiname":"Subbotino",
    "gn:country_code":"RU",
    "gn:dem":195,
    "gn:feature_class":"P",
    "gn:feature_code":"PPL",
    "gn:name":"Subbotino",
    "gn:population":0,
    "gn:timezone":"Europe/Moscow",
    "iso:country":"RU",
    "name:rus_x_preferred":[
        "\u0421\u0443\u0431\u0431\u043e\u0442\u0438\u043d\u043e"
    ],
    "wof:name":"Subbotino",
    "wof:placetype":"locality"
},
  "geometry": {"coordinates":[36.9129,56.1899],"type":"Point"}
}