{
  "type": "Feature",
  "properties": {
    "gn:admin1_code":"25.0",
    "gn:asciiname":"Asmolovo",
    "gn:country_code":"RU",
    "gn:dem":213,
    "gn:feature_class":"P",
    "gn:feature_code":"PPL",
    "gn:name":"Asmolovo",
    "gn:population":0,
    "gn:timezone":"Europe/Moscow",
    "iso:country":"RU",
    "name:nor_x_preferred":[
        "Asmolovo"
    ],
    "name:rus_x_preferred":[
        "\u0410\u0441\u043c\u043e\u043b\u043e\u0432\u043e"
    ],
    "wof:name":"Asmolovo",
    "wof:placetype":"locality"
},
  "geometry": {"coordinates":[34.6527,54.22283],"type":"Point"}
}