{
  "type": "Feature",
  "properties": {
    "gn:admin1_code":"7.0",
    "gn:asciiname":"Batayevka",
    "gn:country_code":"RU",
    "gn:dem":-13,
    "gn:feature_class":"P",
    "gn:feature_code":"PPL",
    "gn:name":"Batayevka",
    "gn:population":0,
    "gn:timezone":"Europe/Astrakhan",
    "iso:country":"RU",
    "name:che_x_preferred":[
        "\u0411\u0430\u0442\u0430\u0435\u0432\u043a\u0430"
    ],
    "name:eng_x_preferred":[
        "Batayevka"
    ],
    "name:nor_x_preferred":[
        "Batajevka"
    ],
    "name:rus_x_preferred":[
        "\u0411\u0430\u0442\u0430\u0435\u0432\u043a\u0430"
    ],
    "name:tgk_x_preferred":[
        "\u0411\u0430\u0442\u0430\u0435\u0432\u043a\u0430"
    ],
    "name:und_x_variant":[
        "Bataevka",
        "Batajewka",
        "\u0411\u0430\u0442\u0430\u0435\u0432\u043a\u0430",
        "Batayevka"
    ],
    "wof:name":"Batayevka",
    "wof:placetype":"locality"
},
  "geometry": {"coordinates":[46.29595,48.1347],"type":"Point"}
}