{
  "type": "Feature",
  "properties": {
    "gn:admin1_code":"85",
    "gn:asciiname":"Ulasovskaya",
    "gn:country_code":"RU",
    "gn:dem":161,
    "gn:feature_class":"P",
    "gn:feature_code":"PPL",
    "gn:name":"Ulasovskaya",
    "gn:population":0,
    "gn:timezone":"Europe/Moscow",
    "iso:country":"RU",
    "name:rus_x_preferred":[
        "\u0423\u043b\u0430\u0441\u043e\u0432\u0441\u043a\u0430\u044f"
    ],
    "wof:name":"Ulasovskaya",
    "wof:placetype":"locality"
},
  "geometry": {"coordinates":[39.7421,60.2564],"type":"Point"}
}