{
  "type": "Feature",
  "properties": {
    "gn:admin1_code":"86",
    "gn:asciiname":"Semeyka",
    "gn:country_code":"RU",
    "gn:dem":80,
    "gn:feature_class":"P",
    "gn:feature_code":"PPL",
    "gn:name":"Semeyka",
    "gn:population":0,
    "gn:timezone":"Europe/Moscow",
    "iso:country":"RU",
    "name:eng_x_preferred":[
        "Semeyka"
    ],
    "name:nor_x_preferred":[
        "Semejka"
    ],
    "name:rus_x_preferred":[
        "\u0421\u0435\u043c\u0435\u0439\u043a\u0430"
    ],
    "name:und_x_variant":[
        "Semeiki",
        "Semeyki"
    ],
    "wof:name":"Semeyka",
    "wof:placetype":"locality"
},
  "geometry": {"coordinates":[39.96202,50.33287],"type":"Point"}
}