{
  "type": "Feature",
  "properties": {
    "gn:admin1_code":"71",
    "gn:asciiname":"Taraskovo",
    "gn:country_code":"RU",
    "gn:dem":336,
    "gn:feature_class":"P",
    "gn:feature_code":"PPL",
    "gn:name":"Taraskovo",
    "gn:population":0,
    "gn:timezone":"Asia/Yekaterinburg",
    "iso:country":"RU",
    "name:eng_x_preferred":[
        "Taraskovo"
    ],
    "name:nor_x_preferred":[
        "Taraskovo"
    ],
    "name:rus_x_preferred":[
        "\u0422\u0430\u0440\u0430\u0441\u043a\u043e\u0432\u043e"
    ],
    "wof:name":"Taraskovo",
    "wof:placetype":"locality"
},
  "geometry": {"coordinates":[60.0626,57.1315],"type":"Point"}
}