{
  "type": "Feature",
  "properties": {
    "gn:admin1_code":"76",
    "gn:asciiname":"Korzhevka",
    "gn:country_code":"RU",
    "gn:dem":259,
    "gn:feature_class":"P",
    "gn:feature_code":"PPL",
    "gn:name":"Korzhevka",
    "gn:population":0,
    "gn:timezone":"Europe/Moscow",
    "iso:country":"RU",
    "name:rus_x_preferred":[
        "\u041a\u043e\u0440\u0436\u0435\u0432\u043a\u0430"
    ],
    "name:und_x_variant":[
        "\u041a\u043e\u0440\u0436\u0435\u0432\u043a\u0430"
    ],
    "wof:name":"Korzhevka",
    "wof:placetype":"locality"
},
  "geometry": {"coordinates":[37.44035,53.4291],"type":"Point"}
}