{
  "type": "Feature",
  "properties": {
    "gn:admin1_code":"60",
    "gn:asciiname":"Devitsy",
    "gn:country_code":"RU",
    "gn:dem":155,
    "gn:feature_class":"P",
    "gn:feature_code":"PPL",
    "gn:name":"Devitsy",
    "gn:population":0,
    "gn:timezone":"Europe/Moscow",
    "iso:country":"RU",
    "name:rus_x_preferred":[
        "\u0414\u0435\u0432\u0438\u0446\u044b"
    ],
    "wof:name":"Devitsy",
    "wof:placetype":"locality"
},
  "geometry": {"coordinates":[28.82827,56.00513],"type":"Point"}
}