{
  "type": "Feature",
  "properties": {
    "gn:admin1_code":"8",
    "gn:asciiname":"Tatarkino",
    "gn:country_code":"RU",
    "gn:dem":140,
    "gn:feature_class":"P",
    "gn:feature_code":"PPL",
    "gn:name":"Tatarkino",
    "gn:population":0,
    "gn:timezone":"Asia/Yekaterinburg",
    "iso:country":"RU",
    "name:rus_x_preferred":[
        "\u0422\u0430\u0442\u0430\u0440\u043a\u0438\u043d\u043e"
    ],
    "wof:name":"Tatarkino",
    "wof:placetype":"locality"
},
  "geometry": {"coordinates":[54.9653,56.1253],"type":"Point"}
}