{
  "type": "Feature",
  "properties": {
    "gn:country":"RU",
    "gn:fcode":"ADMD",
    "gn:population":0,
    "iso:country":"RU",
    "name:rus_x_preferred":[
        "\u0411\u043b\u0430\u0433\u043e\u0432\u0435\u0449\u0435\u043d\u0441\u043a\u0438\u0439 \u0440\u0430\u0439\u043e\u043d"
    ],
    "qs:name":"Blagoveshchenskiy Rayon",
    "qs:photos_9r":0,
    "qs:photos_sr":0,
    "qs:pop_sr":"0",
    "wof:name":"Blagoveshchenskiy Rayon",
    "wof:placetype":"localadmin",
    "wof:population":0
},
  "geometry": {"coordinates":[56.08333,55.08333],"type":"Point"}
}