{
  "type": "Feature",
  "properties": {
    "gn:admin1_code":"40",
    "gn:asciiname":"Mansurovo",
    "gn:country_code":"RU",
    "gn:dem":176,
    "gn:feature_class":"P",
    "gn:feature_code":"PPL",
    "gn:name":"Mansurovo",
    "gn:population":0,
    "gn:timezone":"Asia/Yekaterinburg",
    "iso:country":"RU",
    "name:eng_x_preferred":[
        "Mansurovo"
    ],
    "name:nor_x_preferred":[
        "Mansurovo"
    ],
    "name:rus_x_preferred":[
        "\u041c\u0430\u043d\u0441\u0443\u0440\u043e\u0432\u043e"
    ],
    "name:und_x_variant":[
        "Mansurova",
        "\u041c\u0430\u043d\u0441\u0443\u0440\u043e\u0432\u043e",
        "Mansurovo"
    ],
    "wof:name":"Mansurovo",
    "wof:placetype":"locality"
},
  "geometry": {"coordinates":[62.27806,55.00471999999999],"type":"Point"}
}