{
  "type": "Feature",
  "properties": {
    "gn:admin1_code":"55",
    "gn:asciiname":"Pribrezhnyy",
    "gn:country_code":"RU",
    "gn:dem":267,
    "gn:feature_class":"P",
    "gn:feature_code":"PPL",
    "gn:name":"Pribrezhnyy",
    "gn:population":0,
    "gn:timezone":"Asia/Yekaterinburg",
    "iso:country":"RU",
    "name:eng_x_preferred":[
        "Pribrezhnyy"
    ],
    "name:nor_x_preferred":[
        "Pribrezjnyj"
    ],
    "name:rus_x_preferred":[
        "\u041f\u0440\u0438\u0431\u0440\u0435\u0436\u043d\u044b\u0439"
    ],
    "wof:name":"Pribrezhnyy",
    "wof:placetype":"locality"
},
  "geometry": {"coordinates":[59.5202,50.70399999999999],"type":"Point"}
}