{
  "type": "Feature",
  "properties": {
    "gn:admin1_code":"28",
    "gn:asciiname":"Meklakhti",
    "gn:country_code":"RU",
    "gn:dem":12,
    "gn:feature_class":"P",
    "gn:feature_code":"PPL",
    "gn:name":"M\u00ebklakhti",
    "gn:population":0,
    "gn:timezone":"Europe/Moscow",
    "iso:country":"RU",
    "name:fin_x_preferred":[
        "M\u00f6klahti"
    ],
    "name:rus_x_preferred":[
        "\u041c\u0451\u043a\u043b\u0430\u0445\u0442\u0438"
    ],
    "name:und_x_variant":[
        "M\u00ebklakhti",
        "\u041c\u0451\u043a\u043b\u0430\u0445\u0442\u0438"
    ],
    "wof:name":"Meklakhti",
    "wof:placetype":"locality"
},
  "geometry": {"coordinates":[30.49496,61.55673],"type":"Point"}
}