{
  "type": "Feature",
  "properties": {
    "gn:admin1_code":"51",
    "gn:asciiname":"Dianovo",
    "gn:country_code":"RU",
    "gn:dem":141,
    "gn:feature_class":"P",
    "gn:feature_code":"PPL",
    "gn:name":"Dianovo",
    "gn:population":0,
    "gn:timezone":"Europe/Moscow",
    "iso:country":"RU",
    "name:rus_x_preferred":[
        "\u0414\u0438\u0430\u043d\u043e\u0432\u043e"
    ],
    "name:und_x_variant":[
        "\u0414\u0438\u0430\u043d\u043e\u0432\u043e"
    ],
    "wof:name":"Dianovo",
    "wof:placetype":"locality"
},
  "geometry": {"coordinates":[45.7368,57.4826],"type":"Point"}
}