{
  "type": "Feature",
  "properties": {
    "gn:admin1_code":"33",
    "gn:asciiname":"Katni",
    "gn:country_code":"RU",
    "gn:dem":108,
    "gn:feature_class":"P",
    "gn:feature_code":"PPL",
    "gn:name":"Katni",
    "gn:population":0,
    "gn:timezone":"Europe/Kirov",
    "iso:country":"RU",
    "name:ben_x_preferred":[
        "\u09ae\u09c1\u09b0\u0993\u09af\u09bc\u09be\u09b0\u09be"
    ],
    "name:bih_x_preferred":[
        "\u0915\u091f\u0928\u0940"
    ],
    "name:bpy_x_preferred":[
        "\u09ae\u09c1\u09b0\u09f1\u09be\u09b0\u09be"
    ],
    "name:ceb_x_preferred":[
        "Murw\u0101ra"
    ],
    "name:deu_x_preferred":[
        "Katni"
    ],
    "name:eng_x_preferred":[
        "Katni"
    ],
    "name:fas_x_preferred":[
        "\u0645\u0648\u0631\u0648\u0627\u0631\u0627"
    ],
    "name:fin_x_preferred":[
        "Katni"
    ],
    "name:fra_x_preferred":[
        "Katni"
    ],
    "name:guj_x_preferred":[
        "\u0a95\u0a9f\u0aa8\u0ac0"
    ],
    "name:hin_x_preferred":[
        "\u0915\u091f\u0928\u0940"
    ],
    "name:ita_x_preferred":[
        "Murwara"
    ],
    "name:mar_x_preferred":[
        "\u0915\u091f\u0928\u0940"
    ],
    "name:msa_x_preferred":[
        "Murwara"
    ],
    "name:new_x_preferred":[
        "\u092e\u0941\u0930\u094d\u0935\u093e\u0930\u093e"
    ],
    "name:nor_x_preferred":[
        "Katni"
    ],
    "name:ori_x_preferred":[
        "\u0b15\u0b1f\u0b28\u0b40"
    ],
    "name:pam_x_preferred":[
        "Katni"
    ],
    "name:pol_x_preferred":[
        "Katni"
    ],
    "name:por_x_preferred":[
        "Murwara"
    ],
    "name:rus_x_preferred":[
        "\u041a\u0430\u0442\u043d\u0438"
    ],
    "name:san_x_preferred":[
        "\u0915\u091f\u0928\u0940"
    ],
    "name:spa_x_preferred":[
        "Katni"
    ],
    "name:srp_x_preferred":[
        "\u041c\u0443\u0440\u0432\u0430\u0440\u0430"
    ],
    "name:swe_x_preferred":[
        "Murwara"
    ],
    "name:tam_x_preferred":[
        "\u0b95\u0b9f\u0bcd\u0ba9\u0bbf"
    ],
    "name:urd_x_preferred":[
        "\u06a9\u0679\u0646\u06cc"
    ],
    "name:vie_x_preferred":[
        "Murwara"
    ],
    "name:war_x_preferred":[
        "Katni"
    ],
    "name:zho_x_preferred":[
        "\u7a46\u5c14\u74e6\u62c9"
    ],
    "wof:name":"Katni",
    "wof:placetype":"locality"
},
  "geometry": {"coordinates":[47.76721,57.98018],"type":"Point"}
}