{
  "type": "Feature",
  "properties": {
    "gn:admin1_code":"33",
    "gn:asciiname":"Katni",
    "gn:country_code":"RU",
    "gn:dem":108,
    "gn:feature_class":"P",
    "gn:feature_code":"PPL",
    "gn:name":"Katni",
    "gn:population":0,
    "gn:timezone":"Europe/Kirov",
    "iso:country":"RU",
    "name:eng_x_preferred":[
        "Katni"
    ],
    "name:nor_x_preferred":[
        "Katni"
    ],
    "name:rus_x_preferred":[
        "\u041a\u0430\u0442\u043d\u0438"
    ],
    "name:und_x_variant":[
        "\u041a\u0430\u0442\u043d\u0438",
        "Katni"
    ],
    "wof:name":"Katni",
    "wof:placetype":"locality"
},
  "geometry": {"coordinates":[47.76721,57.98018],"type":"Point"}
}