{
  "type": "Feature",
  "properties": {
    "gn:admin1_code":"42.0",
    "gn:asciiname":"Chidovo",
    "gn:country_code":"RU",
    "gn:dem":109,
    "gn:feature_class":"P",
    "gn:feature_code":"PPL",
    "gn:name":"Chidovo",
    "gn:population":0,
    "gn:timezone":"Europe/Moscow",
    "iso:country":"RU",
    "name:rus_x_preferred":[
        "\u0427\u0438\u0434\u043e\u0432\u043e"
    ],
    "name:und_x_variant":[
        "Tsidovo",
        "Chidovo",
        "\u0427\u0438\u0434\u043e\u0432\u043e"
    ],
    "wof:name":"Chidovo",
    "wof:placetype":"locality"
},
  "geometry": {"coordinates":[34.30201,60.22349000000001],"type":"Point"}
}