{
  "type": "Feature",
  "properties": {
    "gn:admin1_code":"21",
    "gn:asciiname":"Ozernyy",
    "gn:country_code":"RU",
    "gn:dem":138,
    "gn:feature_class":"P",
    "gn:feature_code":"PPL",
    "gn:name":"Oz\u00ebrnyy",
    "gn:population":0,
    "gn:timezone":"Europe/Moscow",
    "iso:country":"RU",
    "name:eng_x_preferred":[
        "Oz\u00ebrnyy"
    ],
    "name:nor_x_preferred":[
        "Ozernyj"
    ],
    "name:rus_x_preferred":[
        "\u041e\u0437\u0435\u0440\u043d\u044b\u0439"
    ],
    "name:und_x_variant":[
        "Maksaki"
    ],
    "wof:name":"Ozernyy",
    "wof:placetype":"locality"
},
  "geometry": {"coordinates":[40.98333,57.15766],"type":"Point"}
}