{
  "type": "Feature",
  "properties": {
    "gn:admin1_code":"83",
    "gn:asciiname":"Petryatkovo",
    "gn:country_code":"RU",
    "gn:dem":154,
    "gn:feature_class":"P",
    "gn:feature_code":"PPL",
    "gn:name":"Petryatkovo",
    "gn:population":0,
    "gn:timezone":"Europe/Moscow",
    "iso:country":"RU",
    "name:rus_x_preferred":[
        "\u041f\u0435\u0442\u0440\u044f\u0442\u043a\u043e\u0432\u043e"
    ],
    "wof:name":"Petryatkovo",
    "wof:placetype":"locality"
},
  "geometry": {"coordinates":[39.49302,56.68131999999999],"type":"Point"}
}