{
  "type": "Feature",
  "properties": {
    "gn:admin1_code":"79",
    "gn:asciiname":"Buluk",
    "gn:cc2":"RU",
    "gn:country_code":"RU",
    "gn:dem":622,
    "gn:feature_class":"P",
    "gn:feature_code":"PPL",
    "gn:name":"Buluk",
    "gn:population":0,
    "gn:timezone":"Asia/Krasnoyarsk",
    "iso:country":"RU",
    "name:rus_x_preferred":[
        "\u0411\u0443\u043b\u0443\u043a"
    ],
    "name:und_x_variant":[
        "Poselok Buluk",
        "Buluk",
        "\u0411\u0443\u043b\u0443\u043a"
    ],
    "wof:name":"Buluk",
    "wof:placetype":"locality"
},
  "geometry": {"coordinates":[94.34999999999999,51.68333],"type":"Point"}
}