{
  "type": "Feature",
  "properties": {
    "gn:admin1_code":"34",
    "gn:asciiname":"Medvezhskaya",
    "gn:country_code":"RU",
    "gn:dem":57,
    "gn:feature_class":"P",
    "gn:feature_code":"PPL",
    "gn:name":"Medvezhskaya",
    "gn:population":0,
    "gn:timezone":"Europe/Moscow",
    "iso:country":"RU",
    "name:eng_x_preferred":[
        "Medvezhskaya"
    ],
    "name:nor_x_preferred":[
        "Medvezjskaja"
    ],
    "name:rus_x_preferred":[
        "\u041c\u0435\u0434\u0432\u0435\u0436\u0441\u043a\u0430\u044f"
    ],
    "name:und_x_variant":[
        "\u041c\u0435\u0434\u0432\u0435\u0436\u0441\u043a\u0430\u044f",
        "Medvezhskaya"
    ],
    "wof:name":"Medvezhskaya",
    "wof:placetype":"locality"
},
  "geometry": {"coordinates":[57.57536,64.94280000000001],"type":"Point"}
}