{
  "type": "Feature",
  "properties": {
    "gn:admin1_code":"61",
    "gn:asciiname":"Kosenko",
    "gn:country_code":"RU",
    "gn:dem":44,
    "gn:feature_class":"P",
    "gn:feature_code":"PPL",
    "gn:name":"Kosenko",
    "gn:population":0,
    "gn:timezone":"Europe/Moscow",
    "iso:country":"RU",
    "name:rus_x_preferred":[
        "\u041a\u043e\u0441\u0435\u043d\u043a\u043e"
    ],
    "name:und_x_variant":[
        "\u041a\u043e\u0441\u0435\u043d\u043a\u043e"
    ],
    "wof:name":"Kosenko",
    "wof:placetype":"locality"
},
  "geometry": {"coordinates":[40.35276,46.5168],"type":"Point"}
}