{
  "type": "Feature",
  "properties": {
    "gn:admin1_code":"43",
    "gn:asciiname":"Vysokopol'ye",
    "gn:country_code":"RU",
    "gn:dem":145,
    "gn:feature_class":"P",
    "gn:feature_code":"PPL",
    "gn:name":"Vysokopol\u2019ye",
    "gn:population":0,
    "gn:timezone":"Europe/Moscow",
    "iso:country":"RU",
    "name:rus_x_preferred":[
        "\u0412\u044b\u0441\u043e\u043a\u043e\u043f\u043e\u043b\u044c\u0435"
    ],
    "name:und_x_variant":[
        "Vysokopol\u2019ye",
        "\u0412\u044b\u0441\u043e\u043a\u043e\u043f\u043e\u043b\u044c\u0435"
    ],
    "wof:name":"Vysokopol'ye",
    "wof:placetype":"locality"
},
  "geometry": {"coordinates":[39.87367,52.30862],"type":"Point"}
}