{
  "type": "Feature",
  "properties": {
    "gn:admin1_code":"20",
    "gn:asciiname":"Tetere",
    "gn:country_code":"RU",
    "gn:dem":417,
    "gn:feature_class":"P",
    "gn:feature_code":"PPL",
    "gn:name":"Tetere",
    "gn:population":0,
    "gn:timezone":"Asia/Irkutsk",
    "iso:country":"RU",
    "wof:name":"Tetere",
    "wof:placetype":"locality"
},
  "geometry": {"coordinates":[105.21666999999999,59.65],"type":"Point"}
}