{
  "type": "Feature",
  "properties": {
    "gn:admin1_code":"28",
    "gn:asciiname":"Gridino",
    "gn:country_code":"RU",
    "gn:dem":20,
    "gn:feature_class":"P",
    "gn:feature_code":"PPL",
    "gn:name":"Gridino",
    "gn:population":0,
    "gn:timezone":"Europe/Moscow",
    "iso:country":"RU",
    "name:fin_x_preferred":[
        "Kriitin\u00e4"
    ],
    "name:rus_x_preferred":[
        "\u0413\u0440\u0438\u0434\u0438\u043d\u043e"
    ],
    "name:und_x_variant":[
        "Gridina",
        "Gridino"
    ],
    "wof:name":"Gridino",
    "wof:placetype":"locality"
},
  "geometry": {"coordinates":[34.67453,65.92256],"type":"Point"}
}