{
  "type": "Feature",
  "properties": {
    "gn:admin1_code":"76.0",
    "gn:asciiname":"Gagarinka",
    "gn:cc2":"RU",
    "gn:country_code":"RU",
    "gn:dem":195,
    "gn:feature_class":"P",
    "gn:feature_code":"PPL",
    "gn:name":"Gagarinka",
    "gn:population":0,
    "gn:timezone":"Europe/Moscow",
    "iso:country":"RU",
    "name:rus_x_preferred":[
        "\u0413\u0430\u0433\u0430\u0440\u0438\u043d\u043a\u0430"
    ],
    "name:und_x_variant":[
        "Kirpichevka",
        "Gagarinka",
        "\u0413\u0430\u0433\u0430\u0440\u0438\u043d\u043a\u0430"
    ],
    "wof:name":"Gagarinka",
    "wof:placetype":"locality"
},
  "geometry": {"coordinates":[38.61667,53.76667],"type":"Point"}
}