{
  "type": "Feature",
  "properties": {
    "gn:country":"RU",
    "gn:fcode":"PPL",
    "gn:pop":3300,
    "iso:country":"RU",
    "name:eng_x_preferred":[
        "El'brus"
    ],
    "name:nor_x_preferred":[
        "Elbrus"
    ],
    "name:rus_x_preferred":[
        "\u042d\u043b\u044c\u0431\u0440\u0443\u0441"
    ],
    "name:unk_x_variant":[
        "Ialbuzi"
    ],
    "qs:name":"El'brus",
    "qs:name_adm0":"Russia",
    "qs:name_adm1":"Kabardino-Balkaria Republic",
    "qs:photos":560,
    "qs:photos_1k":113,
    "qs:photos_9k":2,
    "qs:photos_9r":5,
    "qs:photos_all":560,
    "qs:photos_sr":8,
    "qs:placetype":"Town",
    "qs:pop_sr":"4",
    "wof:name":"El'brus",
    "wof:placetype":"locality",
    "wof:population":3300
},
  "geometry": {"coordinates":[42.64435,43.2577],"type":"Point"}
}