{
  "type": "Feature",
  "properties": {
    "gn:admin1_code":"40",
    "gn:asciiname":"Tryukhino",
    "gn:country_code":"RU",
    "gn:dem":137,
    "gn:feature_class":"P",
    "gn:feature_code":"PPL",
    "gn:name":"Tryukhino",
    "gn:population":0,
    "gn:timezone":"Asia/Yekaterinburg",
    "iso:country":"RU",
    "name:eng_x_preferred":[
        "Tryukhino"
    ],
    "name:nor_x_preferred":[
        "Trjukhino"
    ],
    "name:rus_x_preferred":[
        "\u0422\u0440\u044e\u0445\u0438\u043d\u043e"
    ],
    "wof:name":"Tryukhino",
    "wof:placetype":"locality"
},
  "geometry": {"coordinates":[67.30100999999999,55.50658000000001],"type":"Point"}
}