{
  "type": "Feature",
  "properties": {
    "gn:admin1_code":"28.0",
    "gn:asciiname":"Berichevo",
    "gn:country_code":"RU",
    "gn:dem":55,
    "gn:feature_class":"P",
    "gn:feature_code":"PPL",
    "gn:name":"Berich\u00ebvo",
    "gn:population":0,
    "gn:timezone":"Europe/Moscow",
    "iso:country":"RU",
    "name:fin_x_preferred":[
        "Pyrits\u00e4"
    ],
    "name:nor_x_preferred":[
        "Beritsjovo"
    ],
    "name:rus_x_preferred":[
        "\u0411\u0435\u0440\u0438\u0447\u0451\u0432\u043e"
    ],
    "name:und_x_variant":[
        "Biryuchevo",
        "Berich\u00ebvo"
    ],
    "wof:name":"Berichevo",
    "wof:placetype":"locality"
},
  "geometry": {"coordinates":[34.23333,61.93333000000001],"type":"Point"}
}