{
  "type": "Feature",
  "properties": {
    "gn:admin1_code":"20",
    "gn:asciiname":"Mikhaylovshchina",
    "gn:country_code":"RU",
    "gn:dem":418,
    "gn:feature_class":"P",
    "gn:feature_code":"PPL",
    "gn:name":"Mikhaylovshchina",
    "gn:population":0,
    "gn:timezone":"Asia/Irkutsk",
    "iso:country":"RU",
    "name:eng_x_preferred":[
        "Mikhaylovshchina"
    ],
    "name:nor_x_preferred":[
        "Mikhajlovsjtsjina"
    ],
    "name:rus_x_preferred":[
        "\u041c\u0438\u0445\u0430\u0439\u043b\u043e\u0432\u0449\u0438\u043d\u0430"
    ],
    "name:und_x_variant":[
        "Mikhaylovskaya",
        "\u041c\u0438\u0445\u0430\u0439\u043b\u043e\u0432\u0449\u0438\u043d\u0430",
        "Mikhaylovshchina"
    ],
    "wof:name":"Mikhaylovshchina",
    "wof:placetype":"locality"
},
  "geometry": {"coordinates":[103.0378,54.2013],"type":"Point"}
}