{
  "type": "Feature",
  "properties": {
    "gn:admin1_code":"85",
    "gn:asciiname":"Zayel'nik",
    "gn:country_code":"RU",
    "gn:dem":194,
    "gn:feature_class":"P",
    "gn:feature_code":"PPL",
    "gn:name":"Zayel\u2019nik",
    "gn:population":0,
    "gn:timezone":"Europe/Moscow",
    "iso:country":"RU",
    "name:rus_x_preferred":[
        "\u0417\u0430\u0435\u043b\u044c\u043d\u0438\u043a"
    ],
    "name:und_x_variant":[
        "Zayel\u2019nik"
    ],
    "wof:name":"Zayel'nik",
    "wof:placetype":"locality"
},
  "geometry": {"coordinates":[35.7154,59.7642],"type":"Point"}
}