{
  "type": "Feature",
  "properties": {
    "gn:admin1_code":"25",
    "gn:asciiname":"Grozyn'",
    "gn:country_code":"RU",
    "gn:dem":243,
    "gn:feature_class":"P",
    "gn:feature_code":"PPL",
    "gn:name":"Grozyn\u2019",
    "gn:population":0,
    "gn:timezone":"Europe/Moscow",
    "iso:country":"RU",
    "name:rus_x_preferred":[
        "\u0413\u0440\u043e\u0437\u044b\u043d\u044c"
    ],
    "name:und_x_variant":[
        "Grozyn\u2019"
    ],
    "wof:name":"Grozyn'",
    "wof:placetype":"locality"
},
  "geometry": {"coordinates":[34.00667,54.43879],"type":"Point"}
}