{
  "type": "Feature",
  "properties": {
    "gn:admin1_code":"25",
    "gn:asciiname":"Nemerzki",
    "gn:country_code":"RU",
    "gn:dem":223,
    "gn:feature_class":"P",
    "gn:feature_code":"PPL",
    "gn:name":"Nemerzki",
    "gn:population":0,
    "gn:timezone":"Europe/Moscow",
    "iso:country":"RU",
    "name:rus_x_preferred":[
        "\u041d\u0435\u043c\u0435\u0440\u0437\u043a\u0438"
    ],
    "wof:name":"Nemerzki",
    "wof:placetype":"locality"
},
  "geometry": {"coordinates":[35.10375,54.1341],"type":"Point"}
}