{
  "type": "Feature",
  "properties": {
    "gn:admin1_code":"62",
    "gn:asciiname":"Staro-Barakovo",
    "gn:country_code":"RU",
    "gn:dem":118,
    "gn:feature_class":"P",
    "gn:feature_code":"PPL",
    "gn:name":"Staro-Barakovo",
    "gn:population":0,
    "gn:timezone":"Europe/Moscow",
    "iso:country":"RU",
    "name:rus_x_preferred":[
        "\u0421\u0442\u0430\u0440\u043e-\u0411\u0430\u0440\u0430\u043a\u043e\u0432\u043e"
    ],
    "name:und_x_variant":[
        "\u0421\u0442\u0430\u0440\u043e-\u0411\u0430\u0440\u0430\u043a\u043e\u0432\u043e"
    ],
    "wof:name":"Staro-Barakovo",
    "wof:placetype":"locality"
},
  "geometry": {"coordinates":[39.69342,53.74246],"type":"Point"}
}