{
  "type": "Feature",
  "properties": {
    "gn:admin1_code":"72",
    "gn:asciiname":"Kersha",
    "gn:country_code":"RU",
    "gn:dem":138,
    "gn:feature_class":"P",
    "gn:feature_code":"PPL",
    "gn:name":"Kersha",
    "gn:population":0,
    "gn:timezone":"Europe/Moscow",
    "iso:country":"RU",
    "name:eng_x_preferred":[
        "Kersha"
    ],
    "name:rus_x_preferred":[
        "\u0411\u043e\u043d\u0434\u0430\u0440\u0438"
    ],
    "name:rus_x_variant":[
        "\u041a\u0435\u0440\u0448\u0430"
    ],
    "name:und_x_variant":[
        "Bondari",
        "Kersha"
    ],
    "wof:name":"Kersha",
    "wof:placetype":"locality"
},
  "geometry": {"coordinates":[41.88441,52.8793],"type":"Point"}
}