{
  "type": "Feature",
  "properties": {
    "gn:admin1_code":"53",
    "gn:asciiname":"Oktyabr'skiy",
    "gn:country_code":"RU",
    "gn:dem":108,
    "gn:feature_class":"P",
    "gn:feature_code":"PPL",
    "gn:name":"Oktyabr\u2019skiy",
    "gn:population":0,
    "gn:timezone":"Asia/Novosibirsk",
    "iso:country":"RU",
    "name:rus_x_preferred":[
        "\u041e\u043a\u0442\u044f\u0431\u0440\u044c\u0441\u043a\u0438\u0439"
    ],
    "name:und_x_variant":[
        "Oktyabr\u2019skiy",
        "\u041e\u043a\u0442\u044f\u0431\u0440\u044c\u0441\u043a\u0438\u0439"
    ],
    "wof:name":"Oktyabr'skiy",
    "wof:placetype":"locality"
},
  "geometry": {"coordinates":[84.09999999999999,55.85],"type":"Point"}
}