{
  "type": "Feature",
  "properties": {
    "gn:admin1_code":"77",
    "gn:asciiname":"Perelesok",
    "gn:country_code":"RU",
    "gn:dem":226,
    "gn:feature_class":"P",
    "gn:feature_code":"PPL",
    "gn:name":"Perelesok",
    "gn:population":0,
    "gn:timezone":"Europe/Moscow",
    "iso:country":"RU",
    "name:eng_x_preferred":[
        "Perelesok"
    ],
    "name:nor_x_preferred":[
        "Perelesok"
    ],
    "name:rus_x_preferred":[
        "\u041f\u0435\u0440\u0435\u043b\u0435\u0441\u043e\u043a"
    ],
    "name:und_x_variant":[
        "\u041f\u0435\u0440\u0435\u043b\u0435\u0441\u043e\u043a",
        "Perelesok"
    ],
    "wof:name":"Perelesok",
    "wof:placetype":"locality"
},
  "geometry": {"coordinates":[33.65748,57.43769],"type":"Point"}
}