{
  "type": "Feature",
  "properties": {
    "gn:admin1_code":"52",
    "gn:asciiname":"Makushi",
    "gn:country_code":"RU",
    "gn:dem":74,
    "gn:feature_class":"P",
    "gn:feature_code":"PPL",
    "gn:name":"Makushi",
    "gn:population":0,
    "gn:timezone":"Europe/Moscow",
    "iso:country":"RU",
    "name:rus_x_preferred":[
        "\u041c\u0430\u043a\u0443\u0448\u0438"
    ],
    "wof:name":"Makushi",
    "wof:placetype":"locality"
},
  "geometry": {"coordinates":[32.6274,57.9401],"type":"Point"}
}