{
  "type": "Feature",
  "properties": {
    "gn:admin1_code":"42",
    "gn:admin2_code":"470541",
    "gn:asciiname":"Losevo",
    "gn:country_code":"RU",
    "gn:dem":28,
    "gn:feature_class":"P",
    "gn:feature_code":"PPL",
    "gn:name":"Losevo",
    "gn:population":640,
    "gn:timezone":"Europe/Moscow",
    "iso:country":"RU",
    "name:deu_x_preferred":[
        "Lossewo"
    ],
    "name:fin_x_preferred":[
        "J\u00e4rvenkyl\u00e4"
    ],
    "name:rus_x_preferred":[
        "\u041b\u043e\u0441\u0435\u0432\u043e"
    ],
    "name:spa_x_preferred":[
        "L\u00f3sevo"
    ],
    "name:und_x_variant":[
        "Yarvenkyulya"
    ],
    "wof:name":"Losevo",
    "wof:placetype":"locality",
    "wof:population":640
},
  "geometry": {"coordinates":[28.98133,61.08133],"type":"Point"}
}