{
  "type": "Feature",
  "properties": {
    "gn:admin1_code":"13",
    "gn:asciiname":"Sokolovo",
    "gn:country_code":"RU",
    "gn:dem":224,
    "gn:feature_class":"P",
    "gn:feature_code":"PPL",
    "gn:name":"Sokolovo",
    "gn:population":0,
    "gn:timezone":"Asia/Yekaterinburg",
    "iso:country":"RU",
    "name:rus_x_preferred":[
        "\u0421\u043e\u043a\u043e\u043b\u043e\u0432\u043e"
    ],
    "name:und_x_variant":[
        "Sokolovskiy",
        "Sokolovka",
        "Sokolovo",
        "\u0421\u043e\u043a\u043e\u043b\u043e\u0432\u043e"
    ],
    "wof:name":"Sokolovo",
    "wof:placetype":"locality"
},
  "geometry": {"coordinates":[61.538,54.7144],"type":"Point"}
}