{
  "type": "Feature",
  "properties": {
    "gn:admin1_code":"85",
    "gn:asciiname":"Filino",
    "gn:country_code":"RU",
    "gn:dem":155,
    "gn:feature_class":"P",
    "gn:feature_code":"PPL",
    "gn:name":"Filino",
    "gn:population":0,
    "gn:timezone":"Europe/Moscow",
    "iso:country":"RU",
    "name:rus_x_preferred":[
        "\u0424\u0438\u043b\u0438\u043d\u043e"
    ],
    "wof:name":"Filino",
    "wof:placetype":"locality"
},
  "geometry": {"coordinates":[39.44172,59.49403],"type":"Point"}
}