{
  "type": "Feature",
  "properties": {
    "gn:admin1_code":"91",
    "gn:asciiname":"Shudrovo",
    "gn:country_code":"RU",
    "gn:dem":450,
    "gn:feature_class":"P",
    "gn:feature_code":"PPL",
    "gn:name":"Shudrovo",
    "gn:population":0,
    "gn:timezone":"Asia/Krasnoyarsk",
    "iso:country":"RU",
    "name:eng_x_preferred":[
        "Shudrovo"
    ],
    "name:nor_x_preferred":[
        "Sjudrovo"
    ],
    "name:rus_x_preferred":[
        "\u0428\u0443\u0434\u0440\u043e\u0432\u043e"
    ],
    "wof:name":"Shudrovo",
    "wof:placetype":"locality"
},
  "geometry": {"coordinates":[94.6867,55.3307],"type":"Point"}
}