{
  "type": "Feature",
  "properties": {
    "gn:admin1_code":"8.0",
    "gn:asciiname":"Uyadybash",
    "gn:country_code":"RU",
    "gn:dem":160,
    "gn:feature_class":"P",
    "gn:feature_code":"PPL",
    "gn:name":"Uyadybash",
    "gn:population":0,
    "gn:timezone":"Asia/Yekaterinburg",
    "iso:country":"RU",
    "name:rus_x_preferred":[
        "\u0423\u044f\u0434\u044b\u0431\u0430\u0448"
    ],
    "name:und_x_variant":[
        "Uyedybash"
    ],
    "wof:name":"Uyadybash",
    "wof:placetype":"locality"
},
  "geometry": {"coordinates":[55.8222,56.2529],"type":"Point"}
}