{
  "type": "Feature",
  "properties": {
    "gn:admin1_code":"65",
    "gn:asciiname":"Gusikha",
    "gn:cc2":"RU",
    "gn:country_code":"RU",
    "gn:dem":150,
    "gn:feature_class":"P",
    "gn:feature_code":"PPL",
    "gn:name":"Gusikha",
    "gn:population":0,
    "gn:timezone":"Europe/Samara",
    "iso:country":"RU",
    "name:rus_x_preferred":[
        "\u0413\u0443\u0441\u0438\u0445\u0430"
    ],
    "name:und_x_variant":[
        "Khutor Gusikha",
        "Gusikha"
    ],
    "wof:name":"Gusikha",
    "wof:placetype":"locality"
},
  "geometry": {"coordinates":[50.56667,52.05],"type":"Point"}
}