{
  "type": "Feature",
  "properties": {
    "gn:admin1_code":"88",
    "gn:asciiname":"Ostapkovo",
    "gn:country_code":"RU",
    "gn:dem":160,
    "gn:feature_class":"P",
    "gn:feature_code":"PPL",
    "gn:name":"Ostapkovo",
    "gn:population":0,
    "gn:timezone":"Europe/Moscow",
    "iso:country":"RU",
    "name:rus_x_preferred":[
        "\u041e\u0441\u0442\u0430\u043f\u043a\u043e\u0432\u043e"
    ],
    "wof:name":"Ostapkovo",
    "wof:placetype":"locality"
},
  "geometry": {"coordinates":[38.4834,57.3277],"type":"Point"}
}