{
  "type": "Feature",
  "properties": {
    "gn:admin1_code":"17.0",
    "gn:asciiname":"Ramazan",
    "gn:country_code":"RU",
    "gn:dem":20,
    "gn:feature_class":"P",
    "gn:feature_code":"PPL",
    "gn:name":"Ramazan",
    "gn:population":0,
    "gn:timezone":"Europe/Moscow",
    "iso:country":"RU",
    "name:deu_x_preferred":[
        "Ramazan"
    ],
    "name:fra_x_preferred":[
        "Ramazan"
    ],
    "name:kat_x_preferred":[
        "\u10e0\u10d0\u10db\u10d0\u10d6\u10d0\u10dc\u10d8"
    ],
    "name:rus_x_preferred":[
        "\u0420\u0430\u043c\u0430\u0437\u0430\u043d"
    ],
    "name:tur_x_preferred":[
        "Ramazan"
    ],
    "wof:name":"Ramazan",
    "wof:placetype":"locality"
},
  "geometry": {"coordinates":[45.59083,44.44194],"type":"Point"}
}