{
  "type": "Feature",
  "properties": {
    "gn:admin1_code":"17.0",
    "gn:asciiname":"Ramazan",
    "gn:country_code":"RU",
    "gn:dem":20,
    "gn:feature_class":"P",
    "gn:feature_code":"PPL",
    "gn:name":"Ramazan",
    "gn:population":0,
    "gn:timezone":"Europe/Moscow",
    "iso:country":"RU",
    "wof:name":"Ramazan",
    "wof:placetype":"locality"
},
  "geometry": {"coordinates":[45.59083,44.44194],"type":"Point"}
}