{
  "type": "Feature",
  "properties": {
    "gn:admin1_code":"1.0",
    "gn:asciiname":"Shkep",
    "gn:country_code":"RU",
    "gn:dem":40,
    "gn:feature_class":"P",
    "gn:feature_code":"PPL",
    "gn:name":"Shkep",
    "gn:population":0,
    "gn:timezone":"Europe/Moscow",
    "iso:country":"RU",
    "wof:name":"Shkep",
    "wof:placetype":"locality"
},
  "geometry": {"coordinates":[39.0225,44.84556],"type":"Point"}
}