{
  "type": "Feature",
  "properties": {
    "gn:admin1_code":"17",
    "gn:admin2_code":"Tsuntinskiy Rayon",
    "gn:asciiname":"Tsekhok",
    "gn:country_code":"RU",
    "gn:dem":1589,
    "gn:feature_class":"P",
    "gn:feature_code":"PPL",
    "gn:name":"Tsekhok",
    "gn:population":0,
    "gn:timezone":"Europe/Moscow",
    "iso:country":"RU",
    "name:rus_x_preferred":[
        "\u0426\u0435\u0445\u043e\u043a"
    ],
    "wof:name":"Tsekhok",
    "wof:placetype":"locality"
},
  "geometry": {"coordinates":[45.98528,42.24723],"type":"Point"}
}