{
  "type": "Feature",
  "properties": {
    "gn:admin1_code":"8",
    "gn:asciiname":"Potapovka",
    "gn:country_code":"RU",
    "gn:dem":272,
    "gn:feature_class":"P",
    "gn:feature_code":"PPL",
    "gn:name":"Potapovka",
    "gn:population":0,
    "gn:timezone":"Asia/Yekaterinburg",
    "iso:country":"RU",
    "name:rus_x_preferred":[
        "\u041f\u043e\u0442\u0430\u043f\u043e\u0432\u043a\u0430"
    ],
    "name:und_x_variant":[
        "\u041f\u043e\u0442\u0430\u043f\u043e\u0432\u043a\u0430"
    ],
    "wof:name":"Potapovka",
    "wof:placetype":"locality"
},
  "geometry": {"coordinates":[55.41667,53.43333000000001],"type":"Point"}
}