{
  "type": "Feature",
  "properties": {
    "gn:admin1_code":"93",
    "gn:asciiname":"Afon'kina",
    "gn:country_code":"RU",
    "gn:dem":882,
    "gn:feature_class":"P",
    "gn:feature_code":"PPL",
    "gn:name":"Afon\u2019kina",
    "gn:population":0,
    "gn:timezone":"Asia/Chita",
    "iso:country":"RU",
    "name:rus_x_preferred":[
        "\u0410\u0444\u043e\u043d\u044c\u043a\u0438\u043d\u0430"
    ],
    "name:und_x_variant":[
        "Afon\u2019kina"
    ],
    "wof:name":"Afon'kina",
    "wof:placetype":"locality"
},
  "geometry": {"coordinates":[110.11221999999999,50.57333],"type":"Point"}
}