{
  "type": "Feature",
  "properties": {
    "gn:admin1_code":"91.0",
    "gn:asciiname":"Gribnoy",
    "gn:country_code":"RU",
    "gn:dem":284,
    "gn:feature_class":"P",
    "gn:feature_code":"PPL",
    "gn:name":"Gribnoy",
    "gn:population":0,
    "gn:timezone":"Asia/Krasnoyarsk",
    "iso:country":"RU",
    "name:rus_x_preferred":[
        "\u0413\u0440\u0438\u0431\u043d\u043e\u0439"
    ],
    "name:und_x_variant":[
        "Gribnaya",
        "Gribnoy"
    ],
    "wof:name":"Gribnoy",
    "wof:placetype":"locality"
},
  "geometry": {"coordinates":[90.7009,56.3239],"type":"Point"}
}