{
  "type": "Feature",
  "properties": {
    "gn:admin1_code":"8",
    "gn:asciiname":"Yumadybash",
    "gn:country_code":"RU",
    "gn:dem":174,
    "gn:feature_class":"P",
    "gn:feature_code":"PPL",
    "gn:name":"Yumadybash",
    "gn:population":0,
    "gn:timezone":"Asia/Yekaterinburg",
    "iso:country":"RU",
    "name:eng_x_preferred":[
        "Yumadybashevo"
    ],
    "name:nor_x_preferred":[
        "Jumadybasj"
    ],
    "name:rus_x_preferred":[
        "\u042e\u043c\u0430\u0434\u044b\u0431\u0430\u0448"
    ],
    "name:und_x_variant":[
        "Yumady Bash",
        "Yumadybash",
        "Yumadybosh"
    ],
    "wof:name":"Yumadybash",
    "wof:placetype":"locality"
},
  "geometry": {"coordinates":[53.98333,54.73333],"type":"Point"}
}