{
  "type": "Feature",
  "properties": {
    "gn:admin1_code":"46",
    "gn:asciiname":"Trusklyay",
    "gn:country_code":"RU",
    "gn:dem":161,
    "gn:feature_class":"P",
    "gn:feature_code":"PPL",
    "gn:name":"Trusklyay",
    "gn:population":0,
    "gn:timezone":"Europe/Moscow",
    "iso:country":"RU",
    "name:rus_x_preferred":[
        "\u0422\u0440\u0443\u0441\u043a\u043b\u044f\u0439"
    ],
    "wof:name":"Trusklyay",
    "wof:placetype":"locality"
},
  "geometry": {"coordinates":[44.84772,54.02845],"type":"Point"}
}