{
  "type": "Feature",
  "properties": {
    "gn:admin1_code":"23",
    "gn:asciiname":"Yablonovka",
    "gn:country_code":"RU",
    "gn:dem":10,
    "gn:feature_class":"P",
    "gn:feature_code":"PPL",
    "gn:name":"Yablonovka",
    "gn:population":0,
    "gn:timezone":"Europe/Kaliningrad",
    "iso:country":"RU",
    "name:und_x_variant":[
        "Bartenhof",
        "Yablonovka"
    ],
    "wof:name":"Yablonovka",
    "wof:placetype":"locality"
},
  "geometry": {"coordinates":[20.91365,54.7047],"type":"Point"}
}