{
  "type": "Feature",
  "properties": {
    "gn:country":"RU",
    "gn:fcode":"PPL",
    "gn:pop":0,
    "iso:country":"RU",
    "name:ceb_x_preferred":[
        "Mikhaylovka"
    ],
    "name:eng_x_preferred":[
        "Mikhaylovka"
    ],
    "name:nor_x_preferred":[
        "Mikhajlovka"
    ],
    "name:rus_x_preferred":[
        "\u041c\u0438\u0445\u0430\u0439\u043b\u043e\u0432\u043a\u0430"
    ],
    "name:swe_x_preferred":[
        "Mikhaylovka"
    ],
    "name:ukr_x_preferred":[
        "\u041c\u0438\u0445\u0430\u0439\u043b\u043e\u0432\u043a\u0430"
    ],
    "name:unk_x_variant":[
        "\u041c\u0438\u0445\u0430\u0439\u043b\u043e\u0432\u043a\u0430"
    ],
    "qs:name":"Mikhaylovka",
    "qs:name_adm0":"Russia",
    "qs:name_adm1":"Orenburg Oblast",
    "qs:photos_9r":0,
    "qs:photos_sr":0,
    "qs:placetype":"Town",
    "qs:pop_sr":"0",
    "wd:wordcount":98,
    "wof:name":"Mikhaylovka",
    "wof:placetype":"locality",
    "wof:population":0
},
  "geometry": {"coordinates":[52.4662,53.6777],"type":"Point"}
}