{
  "type": "Feature",
  "properties": {
    "gn:admin1_code":"51",
    "gn:asciiname":"Latyshikha",
    "gn:country_code":"RU",
    "gn:dem":118,
    "gn:feature_class":"P",
    "gn:feature_code":"PPL",
    "gn:name":"Latyshikha",
    "gn:population":0,
    "gn:timezone":"Europe/Moscow",
    "iso:country":"RU",
    "name:rus_x_preferred":[
        "\u041b\u0430\u0442\u044b\u0448\u0438\u0445\u0430"
    ],
    "wof:name":"Latyshikha",
    "wof:placetype":"locality"
},
  "geometry": {"coordinates":[45.61186,55.92994],"type":"Point"}
}