{
  "type": "Feature",
  "properties": {
    "gn:admin1_code":"1",
    "gn:asciiname":"Khashtuk",
    "gn:country_code":"RU",
    "gn:dem":13,
    "gn:feature_class":"P",
    "gn:feature_code":"PPL",
    "gn:name":"Khashtuk",
    "gn:population":0,
    "gn:timezone":"Europe/Moscow",
    "iso:country":"RU",
    "name:cat_x_preferred":[
        "Khaixtuk"
    ],
    "name:che_x_preferred":[
        "\u0425\u0430\u0448\u0442\u0443\u043a"
    ],
    "name:hye_x_preferred":[
        "\u053d\u0561\u0577\u057f\u0578\u0582\u056f"
    ],
    "name:rus_x_preferred":[
        "\u0425\u0430\u0448\u0442\u0443\u043a"
    ],
    "name:spa_x_preferred":[
        "Jashtuk"
    ],
    "name:ukr_x_preferred":[
        "\u0425\u0430\u0448\u0442\u0443\u043a"
    ],
    "wof:name":"Khashtuk",
    "wof:placetype":"locality"
},
  "geometry": {"coordinates":[38.75283,45.04038],"type":"Point"}
}