{
  "type": "Feature",
  "properties": {
    "gn:admin1_code":"53.0",
    "gn:asciiname":"Sushzavod",
    "gn:country_code":"RU",
    "gn:dem":228,
    "gn:feature_class":"P",
    "gn:feature_code":"PPL",
    "gn:name":"Sushzavod",
    "gn:population":0,
    "gn:timezone":"Asia/Novosibirsk",
    "iso:country":"RU",
    "name:rus_x_preferred":[
        "\u0421\u0443\u0448\u0437\u0430\u0432\u043e\u0434"
    ],
    "wof:name":"Sushzavod",
    "wof:placetype":"locality"
},
  "geometry": {"coordinates":[83.4462,54.1715],"type":"Point"}
}