{
  "type": "Feature",
  "properties": {
    "gn:admin1_code":"16",
    "gn:asciiname":"Suguty",
    "gn:country_code":"RU",
    "gn:dem":143,
    "gn:feature_class":"P",
    "gn:feature_code":"PPL",
    "gn:name":"Suguty",
    "gn:population":0,
    "gn:timezone":"Europe/Moscow",
    "iso:country":"RU",
    "name:eng_x_preferred":[
        "Suguty"
    ],
    "name:nor_x_preferred":[
        "Suguty"
    ],
    "name:rus_x_preferred":[
        "\u0421\u0443\u0433\u0443\u0442\u044b"
    ],
    "name:und_x_variant":[
        "Surgut-Chuvashskiy",
        "\u0421\u0443\u0433\u0443\u0442\u044b",
        "Suguty"
    ],
    "wof:name":"Suguty",
    "wof:placetype":"locality"
},
  "geometry": {"coordinates":[47.63255,54.99788],"type":"Point"}
}