{
  "type": "Feature",
  "properties": {
    "gn:admin1_code":"77",
    "gn:asciiname":"Putilovo",
    "gn:country_code":"RU",
    "gn:dem":150,
    "gn:feature_class":"P",
    "gn:feature_code":"PPL",
    "gn:name":"Putilovo",
    "gn:population":0,
    "gn:timezone":"Europe/Moscow",
    "iso:country":"RU",
    "name:rus_x_preferred":[
        "\u041f\u0443\u0442\u0438\u043b\u043e\u0432\u043e"
    ],
    "name:und_x_variant":[
        "\u041f\u0443\u0442\u0438\u043b\u043e\u0432\u043e"
    ],
    "wof:name":"Putilovo",
    "wof:placetype":"locality"
},
  "geometry": {"coordinates":[37.0233,58.0328],"type":"Point"}
}