{
  "type": "Feature",
  "properties": {
    "gn:admin1_code":"88",
    "gn:asciiname":"Gavrilovo",
    "gn:country_code":"RU",
    "gn:dem":136,
    "gn:feature_class":"P",
    "gn:feature_code":"PPL",
    "gn:name":"Gavrilovo",
    "gn:population":0,
    "gn:timezone":"Europe/Moscow",
    "iso:country":"RU",
    "name:rus_x_preferred":[
        "\u0413\u0430\u0432\u0440\u0438\u043b\u043e\u0432\u043e"
    ],
    "name:und_x_variant":[
        "\u0413\u0430\u0432\u0440\u0438\u043b\u043e\u0432\u043e"
    ],
    "wof:name":"Gavrilovo",
    "wof:placetype":"locality"
},
  "geometry": {"coordinates":[37.9499,57.5051],"type":"Point"}
}