{
  "type": "Feature",
  "properties": {
    "gn:admin1_code":"33.0",
    "gn:asciiname":"Masharan'",
    "gn:country_code":"RU",
    "gn:dem":171,
    "gn:feature_class":"P",
    "gn:feature_code":"PPL",
    "gn:name":"Masharan\u2019",
    "gn:population":0,
    "gn:timezone":"Europe/Kirov",
    "iso:country":"RU",
    "name:rus_x_preferred":[
        "\u041c\u0430\u0448\u0430\u0440\u0430\u043d\u044c"
    ],
    "name:und_x_variant":[
        "Masharan\u2019",
        "\u041c\u0430\u0448\u0430\u0440\u0430\u043d\u044c"
    ],
    "wof:name":"Masharan'",
    "wof:placetype":"locality"
},
  "geometry": {"coordinates":[48.4626,57.1478],"type":"Point"}
}