{
  "type": "Feature",
  "properties": {
    "gn:admin1_code":"75.0",
    "gn:asciiname":"Prosekina",
    "gn:country_code":"RU",
    "gn:dem":89,
    "gn:feature_class":"P",
    "gn:feature_code":"PPL",
    "gn:name":"Prosekina",
    "gn:population":0,
    "gn:timezone":"Asia/Tomsk",
    "iso:country":"RU",
    "name:rus_x_preferred":[
        "\u041f\u0440\u043e\u0441\u0435\u043a\u0438\u043d\u0430"
    ],
    "wof:name":"Prosekina",
    "wof:placetype":"locality"
},
  "geometry": {"coordinates":[85.02528000000002,56.38431],"type":"Point"}
}