{
  "type": "Feature",
  "properties": {
    "gn:admin1_code":"38.0",
    "gn:asciiname":"Krasnaya Volya",
    "gn:country_code":"RU",
    "gn:dem":311,
    "gn:feature_class":"P",
    "gn:feature_code":"PPL",
    "gn:name":"Krasnaya Volya",
    "gn:population":0,
    "gn:timezone":"Europe/Moscow",
    "iso:country":"RU",
    "name:rus_x_preferred":[
        "\u041a\u0440\u0430\u0441\u043d\u0430\u044f \u0412\u043e\u043b\u044f"
    ],
    "name:und_x_variant":[
        "Volya",
        "Krasnaya Volya"
    ],
    "wof:name":"Krasnaya Volya",
    "wof:placetype":"locality"
},
  "geometry": {"coordinates":[39.92003,43.5581],"type":"Point"}
}