{
  "type": "Feature",
  "properties": {
    "gn:admin1_code":"60",
    "gn:asciiname":"Lukovishchi",
    "gn:country_code":"RU",
    "gn:dem":106,
    "gn:feature_class":"P",
    "gn:feature_code":"PPL",
    "gn:name":"Lukovishchi",
    "gn:population":0,
    "gn:timezone":"Europe/Moscow",
    "iso:country":"RU",
    "name:rus_x_preferred":[
        "\u041b\u0443\u043a\u043e\u0432\u0438\u0449\u0438"
    ],
    "wof:name":"Lukovishchi",
    "wof:placetype":"locality"
},
  "geometry": {"coordinates":[30.1079,56.8945],"type":"Point"}
}