{
  "type": "Feature",
  "properties": {
    "gn:admin1_code":"28",
    "gn:asciiname":"Mustayarvi",
    "gn:country_code":"RU",
    "gn:dem":110,
    "gn:feature_class":"P",
    "gn:feature_code":"PPL",
    "gn:name":"Mustayarvi",
    "gn:population":0,
    "gn:timezone":"Europe/Moscow",
    "iso:country":"RU",
    "name:fin_x_preferred":[
        "Mustaj\u00e4rvi"
    ],
    "name:rus_x_preferred":[
        "\u041c\u0443\u0441\u0442\u0430\u044f\u0440\u0432\u0438"
    ],
    "name:und_x_variant":[
        "\u041c\u0443\u0441\u0442\u0430\u044f\u0440\u0432\u0438"
    ],
    "wof:name":"Mustayarvi",
    "wof:placetype":"locality"
},
  "geometry": {"coordinates":[31.58333,61.91667],"type":"Point"}
}