{
  "type": "Feature",
  "properties": {
    "gn:admin1_code":"71",
    "gn:asciiname":"Sanatornyy",
    "gn:country_code":"RU",
    "gn:dem":283,
    "gn:feature_class":"P",
    "gn:feature_code":"PPL",
    "gn:name":"Sanatornyy",
    "gn:population":0,
    "gn:timezone":"Asia/Yekaterinburg",
    "iso:country":"RU",
    "name:rus_x_preferred":[
        "\u0421\u0430\u043d\u0430\u0442\u043e\u0440\u043d\u044b\u0439"
    ],
    "name:und_x_variant":[
        "\u0421\u0430\u043d\u0430\u0442\u043e\u0440\u043d\u044b\u0439"
    ],
    "wof:name":"Sanatornyy",
    "wof:placetype":"locality"
},
  "geometry": {"coordinates":[60.55501999999999,57.0185],"type":"Point"}
}