{
  "type": "Feature",
  "properties": {
    "gn:admin1_code":"42",
    "gn:asciiname":"Yemskoye",
    "gn:country_code":"RU",
    "gn:dem":4,
    "gn:feature_class":"P",
    "gn:feature_code":"PPL",
    "gn:name":"Yemskoye",
    "gn:population":0,
    "gn:timezone":"Europe/Moscow",
    "iso:country":"RU",
    "name:und_x_variant":[
        "Emskoje",
        "Yemskoye"
    ],
    "wof:name":"Yemskoye",
    "wof:placetype":"locality"
},
  "geometry": {"coordinates":[33.17173,60.29759],"type":"Point"}
}