{
  "type": "Feature",
  "properties": {
    "gn:admin1_code":"17.0",
    "gn:asciiname":"Fite",
    "gn:country_code":"RU",
    "gn:dem":2205,
    "gn:feature_class":"P",
    "gn:feature_code":"PPL",
    "gn:name":"Fite",
    "gn:population":0,
    "gn:timezone":"Europe/Moscow",
    "iso:country":"RU",
    "name:rus_x_preferred":[
        "\u0424\u0438\u0442\u0435"
    ],
    "name:und_x_variant":[
        "Fita",
        "Fite"
    ],
    "wof:name":"Fite",
    "wof:placetype":"locality"
},
  "geometry": {"coordinates":[47.73998,41.79161],"type":"Point"}
}