{
  "type": "Feature",
  "properties": {
    "gn:admin1_code":"51",
    "gn:asciiname":"Glukhoye",
    "gn:country_code":"RU",
    "gn:dem":87,
    "gn:feature_class":"P",
    "gn:feature_code":"PPL",
    "gn:name":"Glukhoye",
    "gn:population":0,
    "gn:timezone":"Europe/Moscow",
    "iso:country":"RU",
    "name:rus_x_preferred":[
        "\u0413\u043b\u0443\u0445\u043e\u0435"
    ],
    "wof:name":"Glukhoye",
    "wof:placetype":"locality"
},
  "geometry": {"coordinates":[45.1198,57.46],"type":"Point"}
}