{
  "type": "Feature",
  "properties": {
    "gn:admin1_code":"37",
    "gn:asciiname":"Rogovo",
    "gn:country_code":"RU",
    "gn:dem":151,
    "gn:feature_class":"P",
    "gn:feature_code":"PPL",
    "gn:name":"Rogovo",
    "gn:population":0,
    "gn:timezone":"Europe/Moscow",
    "iso:country":"RU",
    "name:rus_x_preferred":[
        "\u0420\u043e\u0433\u043e\u0432\u043e"
    ],
    "name:und_x_variant":[
        "\u0420\u043e\u0433\u043e\u0432\u043e"
    ],
    "wof:name":"Rogovo",
    "wof:placetype":"locality"
},
  "geometry": {"coordinates":[45.5469,58.0052],"type":"Point"}
}