{
  "type": "Feature",
  "properties": {
    "gn:admin1_code":"83",
    "gn:asciiname":"Luzhki",
    "gn:country_code":"RU",
    "gn:dem":100,
    "gn:feature_class":"P",
    "gn:feature_code":"PPL",
    "gn:name":"Luzhki",
    "gn:population":0,
    "gn:timezone":"Europe/Moscow",
    "iso:country":"RU",
    "name:rus_x_preferred":[
        "\u041b\u0443\u0436\u043a\u0438"
    ],
    "name:und_x_variant":[
        "Koshkinka",
        "Luzhki"
    ],
    "wof:name":"Luzhki",
    "wof:placetype":"locality"
},
  "geometry": {"coordinates":[41.9164,55.431],"type":"Point"}
}