{
  "type": "Feature",
  "properties": {
    "gn:admin1_code":"80.0",
    "gn:asciiname":"Krasnaya Gorka",
    "gn:country_code":"RU",
    "gn:dem":155,
    "gn:feature_class":"P",
    "gn:feature_code":"PPL",
    "gn:name":"Krasnaya Gorka",
    "gn:population":0,
    "gn:timezone":"Europe/Samara",
    "iso:country":"RU",
    "wof:name":"Krasnaya Gorka",
    "wof:placetype":"locality"
},
  "geometry": {"coordinates":[53.69402,56.95718000000001],"type":"Point"}
}