{
  "type": "Feature",
  "properties": {
    "gn:admin1_code":"47",
    "gn:asciiname":"Nikitskoye",
    "gn:country_code":"RU",
    "gn:dem":175,
    "gn:feature_class":"P",
    "gn:feature_code":"PPL",
    "gn:name":"Nikitskoye",
    "gn:population":0,
    "gn:timezone":"Europe/Moscow",
    "iso:country":"RU",
    "name:rus_x_preferred":[
        "\u041d\u0438\u043a\u0438\u0442\u0441\u043a\u043e\u0435"
    ],
    "wof:name":"Nikitskoye",
    "wof:placetype":"locality"
},
  "geometry": {"coordinates":[36.7744,56.2759],"type":"Point"}
}