{
  "type": "Feature",
  "properties": {
    "gn:admin1_code":"60",
    "gn:asciiname":"Kurokhnovo",
    "gn:country_code":"RU",
    "gn:dem":179,
    "gn:feature_class":"P",
    "gn:feature_code":"PPL",
    "gn:name":"Kurokhnovo",
    "gn:population":0,
    "gn:timezone":"Europe/Moscow",
    "iso:country":"RU",
    "name:rus_x_preferred":[
        "\u041a\u0443\u0440\u043e\u0445\u043d\u043e\u0432\u043e"
    ],
    "wof:name":"Kurokhnovo",
    "wof:placetype":"locality"
},
  "geometry": {"coordinates":[29.9011,56.511],"type":"Point"}
}