{
  "type": "Feature",
  "properties": {
    "gn:admin1_code":"33",
    "gn:asciiname":"Shelemeti",
    "gn:country_code":"RU",
    "gn:dem":115,
    "gn:feature_class":"P",
    "gn:feature_code":"PPL",
    "gn:name":"Shelemeti",
    "gn:population":0,
    "gn:timezone":"Europe/Kirov",
    "iso:country":"RU",
    "name:rus_x_preferred":[
        "\u0428\u0435\u043b\u0435\u043c\u0435\u0442\u0438"
    ],
    "wof:name":"Shelemeti",
    "wof:placetype":"locality"
},
  "geometry": {"coordinates":[48.09443,57.47858000000001],"type":"Point"}
}