{
  "type": "Feature",
  "properties": {
    "gn:admin1_code":"85.0",
    "gn:asciiname":"Bol'shoye Ivanovskoye",
    "gn:country_code":"RU",
    "gn:dem":169,
    "gn:feature_class":"P",
    "gn:feature_code":"PPL",
    "gn:name":"Bol\u2019shoye Ivanovskoye",
    "gn:population":0,
    "gn:timezone":"Europe/Moscow",
    "iso:country":"RU",
    "name:rus_x_preferred":[
        "\u0411\u043e\u043b\u044c\u0448\u043e\u0435 \u0418\u0432\u0430\u043d\u043e\u0432\u0441\u043a\u043e\u0435"
    ],
    "name:und_x_variant":[
        "Bol\u2019shoye Ivanovskoye",
        "Bol\u2019she-Ivanovskoye"
    ],
    "wof:name":"Bol'shoye Ivanovskoye",
    "wof:placetype":"locality"
},
  "geometry": {"coordinates":[38.69706,59.13135],"type":"Point"}
}