{
  "type": "Feature",
  "properties": {
    "gn:admin1_code":"85",
    "gn:asciiname":"Yeremeyevo",
    "gn:country_code":"RU",
    "gn:dem":147,
    "gn:feature_class":"P",
    "gn:feature_code":"PPL",
    "gn:name":"Yeremeyevo",
    "gn:population":0,
    "gn:timezone":"Europe/Moscow",
    "iso:country":"RU",
    "name:rus_x_preferred":[
        "\u0415\u0440\u0435\u043c\u0435\u0435\u0432\u043e"
    ],
    "wof:name":"Yeremeyevo",
    "wof:placetype":"locality"
},
  "geometry": {"coordinates":[39.64385,59.22723000000001],"type":"Point"}
}