{
  "type": "Feature",
  "properties": {
    "gn:admin1_code":"11",
    "gn:asciiname":"Enkhe-Tala",
    "gn:country_code":"RU",
    "gn:dem":637,
    "gn:feature_class":"P",
    "gn:feature_code":"PPL",
    "gn:name":"Enkhe-Tala",
    "gn:population":0,
    "gn:timezone":"Asia/Irkutsk",
    "iso:country":"RU",
    "name:eng_x_preferred":[
        "Enkhe-Tala"
    ],
    "name:nor_x_preferred":[
        "Enkhe-Tala"
    ],
    "name:rus_x_preferred":[
        "\u042d\u043d\u0445\u044d-\u0422\u0430\u043b\u0430"
    ],
    "name:rus_x_variant":[
        "\u042d\u043d\u0445\u0435-\u0422\u0430\u043b\u0430"
    ],
    "wof:name":"Enkhe-Tala",
    "wof:placetype":"locality"
},
  "geometry": {"coordinates":[107.16139,50.21611],"type":"Point"}
}