{
  "type": "Feature",
  "properties": {
    "gn:admin1_code":"85.0",
    "gn:asciiname":"Tsiposhevskaya",
    "gn:country_code":"RU",
    "gn:dem":131,
    "gn:feature_class":"P",
    "gn:feature_code":"PPL",
    "gn:name":"Tsiposhevskaya",
    "gn:population":0,
    "gn:timezone":"Europe/Moscow",
    "iso:country":"RU",
    "name:rus_x_preferred":[
        "\u0426\u0438\u043f\u043e\u0448\u0435\u0432\u0441\u043a\u0430\u044f"
    ],
    "wof:name":"Tsiposhevskaya",
    "wof:placetype":"locality"
},
  "geometry": {"coordinates":[39.8715,60.1776],"type":"Point"}
}