{
  "type": "Feature",
  "properties": {
    "gn:admin1_code":"12.0",
    "gn:asciiname":"Mukhmarki",
    "gn:country_code":"RU",
    "gn:dem":1360,
    "gn:feature_class":"P",
    "gn:feature_code":"PPL",
    "gn:name":"Mukhmarki",
    "gn:population":0,
    "gn:timezone":"Europe/Moscow",
    "iso:country":"RU",
    "wof:name":"Mukhmarki",
    "wof:placetype":"locality"
},
  "geometry": {"coordinates":[45.60111,42.73139000000001],"type":"Point"}
}