{
  "type": "Feature",
  "properties": {
    "gn:admin1_code":"85",
    "gn:asciiname":"Vozdvizhen'ye",
    "gn:country_code":"RU",
    "gn:dem":153,
    "gn:feature_class":"P",
    "gn:feature_code":"PPL",
    "gn:name":"Vozdvizhen\u2019ye",
    "gn:population":0,
    "gn:timezone":"Europe/Moscow",
    "iso:country":"RU",
    "wof:name":"Vozdvizhen'ye",
    "wof:placetype":"locality"
},
  "geometry": {"coordinates":[40.4324,59.5669],"type":"Point"}
}