{
  "type": "Feature",
  "properties": {
    "gn:admin1_code":"86.0",
    "gn:asciiname":"Kreshchenovka",
    "gn:country_code":"RU",
    "gn:dem":135,
    "gn:feature_class":"P",
    "gn:feature_code":"PPL",
    "gn:name":"Kreshchenovka",
    "gn:population":0,
    "gn:timezone":"Europe/Moscow",
    "iso:country":"RU",
    "name:che_x_preferred":[
        "\u041a\u0440\u0435\u0449\u0435\u043d\u043e\u0432\u043a\u0430"
    ],
    "name:rus_x_preferred":[
        "\u041a\u0440\u0435\u0449\u0435\u043d\u043e\u0432\u043a\u0430"
    ],
    "name:tgk_x_preferred":[
        "\u041a\u0440\u0435\u0448\u0435\u043d\u043e\u0432\u043a\u0430"
    ],
    "name:und_x_variant":[
        "\u041a\u0440\u0435\u0449\u0435\u043d\u043e\u0432\u043a\u0430"
    ],
    "wof:name":"Kreshchenovka",
    "wof:placetype":"locality"
},
  "geometry": {"coordinates":[40.7525,51.58028],"type":"Point"}
}