{
  "type": "Feature",
  "properties": {
    "gn:admin1_code":"42",
    "gn:admin2_code":"472350",
    "gn:asciiname":"Gorki",
    "gn:country_code":"RU",
    "gn:dem":142,
    "gn:feature_class":"P",
    "gn:feature_code":"PPL",
    "gn:name":"Gorki",
    "gn:population":0,
    "gn:timezone":"Europe/Moscow",
    "iso:country":"RU",
    "name:fin_x_preferred":[
        "Korkka"
    ],
    "name:nor_x_preferred":[
        "Gorki"
    ],
    "name:rus_x_preferred":[
        "\u0413\u043e\u0440\u043a\u0438"
    ],
    "wof:name":"Gorki",
    "wof:placetype":"locality"
},
  "geometry": {"coordinates":[29.63571,59.55236],"type":"Point"}
}