{
  "type": "Feature",
  "properties": {
    "gn:admin1_code":"20",
    "gn:asciiname":"Tashlykova",
    "gn:country_code":"RU",
    "gn:dem":535,
    "gn:feature_class":"P",
    "gn:feature_code":"PPL",
    "gn:name":"Tashlykova",
    "gn:population":0,
    "gn:timezone":"Asia/Irkutsk",
    "iso:country":"RU",
    "name:eng_x_preferred":[
        "Tashlykova"
    ],
    "name:nor_x_preferred":[
        "Tasjlykova"
    ],
    "name:rus_x_preferred":[
        "\u0422\u0430\u0448\u043b\u044b\u043a\u043e\u0432\u0430"
    ],
    "wof:name":"Tashlykova",
    "wof:placetype":"locality"
},
  "geometry": {"coordinates":[103.0855,53.8914],"type":"Point"}
}