{
  "type": "Feature",
  "properties": {
    "gn:admin1_code":"57.0",
    "gn:asciiname":"Novaya Zhizn'",
    "gn:country_code":"RU",
    "gn:dem":136,
    "gn:feature_class":"P",
    "gn:feature_code":"PPL",
    "gn:name":"Novaya Zhizn\u2019",
    "gn:population":0,
    "gn:timezone":"Europe/Moscow",
    "iso:country":"RU",
    "name:rus_x_preferred":[
        "\u041d\u043e\u0432\u0430\u044f \u0416\u0438\u0437\u043d\u044c"
    ],
    "name:und_x_variant":[
        "Novaya Zhizn\u2019"
    ],
    "wof:name":"Novaya Zhizn'",
    "wof:placetype":"locality"
},
  "geometry": {"coordinates":[45.09003,53.24641],"type":"Point"}
}