{
  "type": "Feature",
  "properties": {
    "gn:admin1_code":"77",
    "gn:asciiname":"Aleshkovo",
    "gn:country_code":"RU",
    "gn:dem":151,
    "gn:feature_class":"P",
    "gn:feature_code":"PPL",
    "gn:name":"Al\u00ebshkovo",
    "gn:population":0,
    "gn:timezone":"Europe/Moscow",
    "iso:country":"RU",
    "name:rus_x_preferred":[
        "\u0410\u043b\u0451\u0448\u043a\u043e\u0432\u043e"
    ],
    "name:und_x_variant":[
        "Al\u00ebshkovo",
        "\u0410\u043b\u0451\u0448\u043a\u043e\u0432\u043e"
    ],
    "wof:name":"Aleshkovo",
    "wof:placetype":"locality"
},
  "geometry": {"coordinates":[36.6685,58.0895],"type":"Point"}
}