{
  "type": "Feature",
  "properties": {
    "gn:admin1_code":"42",
    "gn:asciiname":"Kurgino",
    "gn:country_code":"RU",
    "gn:dem":86,
    "gn:feature_class":"P",
    "gn:feature_code":"PPL",
    "gn:name":"Kurgino",
    "gn:population":0,
    "gn:timezone":"Europe/Moscow",
    "iso:country":"RU",
    "name:fin_x_preferred":[
        "Kurkela"
    ],
    "name:rus_x_preferred":[
        "\u041a\u0443\u0440\u0433\u0438\u043d\u043e"
    ],
    "wof:name":"Kurgino",
    "wof:placetype":"locality"
},
  "geometry": {"coordinates":[30.13722000000001,59.30028000000001],"type":"Point"}
}