{
  "type": "Feature",
  "properties": {
    "gn:admin1_code":"77.0",
    "gn:asciiname":"Dyagunino",
    "gn:country_code":"RU",
    "gn:dem":151,
    "gn:feature_class":"P",
    "gn:feature_code":"PPL",
    "gn:name":"Dyagunino",
    "gn:population":0,
    "gn:timezone":"Europe/Moscow",
    "iso:country":"RU",
    "name:eng_x_preferred":[
        "Dyagunino"
    ],
    "name:nor_x_preferred":[
        "Djagunino"
    ],
    "name:rus_x_preferred":[
        "\u0414\u044f\u0433\u0443\u043d\u0438\u043d\u043e"
    ],
    "name:und_x_variant":[
        "Dyagulino",
        "\u0414\u044f\u0433\u0443\u043d\u0438\u043d\u043e",
        "Dyagunino"
    ],
    "wof:name":"Dyagunino",
    "wof:placetype":"locality"
},
  "geometry": {"coordinates":[34.89348,56.32811],"type":"Point"}
}