{
  "type": "Feature",
  "properties": {
    "gn:admin1_code":"61",
    "gn:asciiname":"Stepano-Savchenskiy",
    "gn:cc2":"RU",
    "gn:country_code":"RU",
    "gn:dem":82,
    "gn:feature_class":"P",
    "gn:feature_code":"PPL",
    "gn:name":"Stepano-Savchenskiy",
    "gn:population":0,
    "gn:timezone":"Europe/Moscow",
    "iso:country":"RU",
    "name:eng_x_preferred":[
        "Stepano-Savchenskiy"
    ],
    "name:nor_x_preferred":[
        "Stepano-Savtsjenskij"
    ],
    "name:rus_x_preferred":[
        "\u0421\u0442\u0435\u043f\u0430\u043d\u043e-\u0421\u0430\u0432\u0447\u0435\u043d\u0441\u043a\u0438\u0439"
    ],
    "name:und_x_variant":[
        "Khutor Stepano-Savchenskiy",
        "\u0421\u0442\u0435\u043f\u0430\u043d\u043e-\u0421\u0430\u0432\u0447\u0435\u043d\u0441\u043a\u0438\u0439",
        "Stepano-Savchenskiy"
    ],
    "wof:name":"Stepano-Savchenskiy",
    "wof:placetype":"locality"
},
  "geometry": {"coordinates":[41.60278,48.80556],"type":"Point"}
}