{
  "type": "Feature",
  "properties": {
    "gn:admin1_code":"42.0",
    "gn:asciiname":"Cholovo",
    "gn:country_code":"RU",
    "gn:dem":66,
    "gn:feature_class":"P",
    "gn:feature_code":"PPL",
    "gn:name":"Cholovo",
    "gn:population":0,
    "gn:timezone":"Europe/Moscow",
    "iso:country":"RU",
    "name:eng_x_preferred":[
        "Cholovo"
    ],
    "name:nor_x_preferred":[
        "Tsjolovo"
    ],
    "name:rus_x_preferred":[
        "\u0427\u043e\u043b\u043e\u0432\u043e"
    ],
    "name:und_x_variant":[
        "\u0427\u043e\u043b\u043e\u0432\u043e",
        "Cholovo"
    ],
    "wof:name":"Cholovo",
    "wof:placetype":"locality"
},
  "geometry": {"coordinates":[30.43333,58.95],"type":"Point"}
}