{
  "type": "Feature",
  "properties": {
    "gn:admin1_code":"80.0",
    "gn:asciiname":"Zyambay",
    "gn:country_code":"RU",
    "gn:dem":201,
    "gn:feature_class":"P",
    "gn:feature_code":"PPL",
    "gn:name":"Zyambay",
    "gn:population":0,
    "gn:timezone":"Europe/Samara",
    "iso:country":"RU",
    "name:rus_x_preferred":[
        "\u0417\u044f\u043c\u0431\u0430\u0439"
    ],
    "wof:name":"Zyambay",
    "wof:placetype":"locality"
},
  "geometry": {"coordinates":[52.5363,57.8676],"type":"Point"}
}