{
  "type": "Feature",
  "properties": {
    "gn:admin1_code":"6",
    "gn:asciiname":"Shestiozerskiy",
    "gn:country_code":"RU",
    "gn:dem":252,
    "gn:feature_class":"P",
    "gn:feature_code":"PPL",
    "gn:name":"Shestioz\u00ebrskiy",
    "gn:population":0,
    "gn:timezone":"Europe/Moscow",
    "iso:country":"RU",
    "name:eng_x_preferred":[
        "Shestioz\u00ebrskiy"
    ],
    "name:nor_x_preferred":[
        "Sjestiozerskij"
    ],
    "name:rus_x_preferred":[
        "\u0428\u0435\u0441\u0442\u0438\u043e\u0437\u0435\u0440\u0441\u043a\u0438\u0439"
    ],
    "name:rus_x_variant":[
        "\u0428\u0435\u0441\u0442\u0438\u043e\u0437\u00eb\u0440\u0441\u043a\u0438\u0439"
    ],
    "name:und_x_variant":[
        "Shestioz\u00ebrnyy",
        "Shestiozerny",
        "Shestioz\u00ebrskiy"
    ],
    "wof:name":"Shestiozerskiy",
    "wof:placetype":"locality"
},
  "geometry": {"coordinates":[40.2008,61.8116],"type":"Point"}
}