{
  "type": "Feature",
  "properties": {
    "gn:admin1_code":"8.0",
    "gn:asciiname":"Bulanovka",
    "gn:country_code":"RU",
    "gn:dem":395,
    "gn:feature_class":"P",
    "gn:feature_code":"PPL",
    "gn:name":"Bulanovka",
    "gn:population":0,
    "gn:timezone":"Asia/Yekaterinburg",
    "iso:country":"RU",
    "name:bak_x_preferred":[
        "\u0411\u043e\u043b\u0430\u043d"
    ],
    "name:che_x_preferred":[
        "\u0411\u0443\u043b\u0430\u043d\u043e\u0432\u043a\u0430"
    ],
    "name:hye_x_preferred":[
        "\u0532\u0578\u0582\u056c\u0561\u0576\u0578\u057e\u056f\u0561"
    ],
    "name:kaz_x_preferred":[
        "\u0411\u0443\u043b\u0430\u043d\u043e\u0432\u043a\u0430"
    ],
    "name:kir_x_preferred":[
        "\u0411\u0443\u043b\u0430\u043d\u043e\u0432\u043a\u0430"
    ],
    "name:rus_x_preferred":[
        "\u0411\u0443\u043b\u0430\u043d\u043e\u0432\u043a\u0430"
    ],
    "name:tat_x_preferred":[
        "\u0411\u043e\u043b\u0430\u043d"
    ],
    "name:ukr_x_preferred":[
        "\u0411\u0443\u043b\u0430\u043d\u043e\u0432\u043a\u0430"
    ],
    "name:und_x_variant":[
        "\u0411\u0443\u043b\u0430\u043d\u043e\u0432\u043a\u0430"
    ],
    "wof:name":"Bulanovka",
    "wof:placetype":"locality"
},
  "geometry": {"coordinates":[54.43333000000001,54.06667],"type":"Point"}
}