{
  "type": "Feature",
  "properties": {
    "gn:admin1_code":"60",
    "gn:asciiname":"Potseluyevo",
    "gn:country_code":"RU",
    "gn:dem":77,
    "gn:feature_class":"P",
    "gn:feature_code":"PPL",
    "gn:name":"Potseluyevo",
    "gn:population":0,
    "gn:timezone":"Europe/Moscow",
    "iso:country":"RU",
    "name:rus_x_preferred":[
        "\u041f\u043e\u0446\u0435\u043b\u0443\u0435\u0432\u043e"
    ],
    "wof:name":"Potseluyevo",
    "wof:placetype":"locality"
},
  "geometry": {"coordinates":[30.28,57.8445],"type":"Point"}
}