{
  "type": "Feature",
  "properties": {
    "gn:admin1_code":"77",
    "gn:asciiname":"Nikiforovskoye",
    "gn:country_code":"RU",
    "gn:dem":178,
    "gn:feature_class":"P",
    "gn:feature_code":"PPL",
    "gn:name":"Nikiforovskoye",
    "gn:population":0,
    "gn:timezone":"Europe/Moscow",
    "iso:country":"RU",
    "name:eng_x_preferred":[
        "Nikiforovskoye"
    ],
    "name:nor_x_preferred":[
        "Nikiforovskoje"
    ],
    "name:rus_x_preferred":[
        "\u041d\u0438\u043a\u0438\u0444\u043e\u0440\u043e\u0432\u0441\u043a\u043e\u0435"
    ],
    "name:und_x_variant":[
        "Nikoforovskoye",
        "Nikiforovo"
    ],
    "wof:name":"Nikiforovskoye",
    "wof:placetype":"locality"
},
  "geometry": {"coordinates":[34.83114,56.22481],"type":"Point"}
}