{
  "type": "Feature",
  "properties": {
    "gn:admin1_code":"65",
    "gn:asciiname":"Russkaya Borkovka",
    "gn:country_code":"RU",
    "gn:dem":63,
    "gn:feature_class":"P",
    "gn:feature_code":"PPL",
    "gn:name":"Russkaya Borkovka",
    "gn:population":0,
    "gn:timezone":"Europe/Samara",
    "iso:country":"RU",
    "name:eng_x_preferred":[
        "Russkaya Borkovka"
    ],
    "name:nor_x_preferred":[
        "Russkaja Borkovka"
    ],
    "name:rus_x_preferred":[
        "\u0420\u0443\u0441\u0441\u043a\u0430\u044f \u0411\u043e\u0440\u043a\u043e\u0432\u043a\u0430"
    ],
    "name:und_x_variant":[
        "Borkovka Russkaya"
    ],
    "wof:name":"Russkaya Borkovka",
    "wof:placetype":"locality"
},
  "geometry": {"coordinates":[49.3198,53.57100000000001],"type":"Point"}
}