{
  "type": "Feature",
  "properties": {
    "gn:admin1_code":"81.0",
    "gn:asciiname":"Fed'kino",
    "gn:country_code":"RU",
    "gn:dem":162,
    "gn:feature_class":"P",
    "gn:feature_code":"PPL",
    "gn:name":"Fed\u2019kino",
    "gn:population":0,
    "gn:timezone":"Europe/Ulyanovsk",
    "iso:country":"RU",
    "name:eng_x_preferred":[
        "Fed'kino"
    ],
    "name:nor_x_preferred":[
        "Fedkino"
    ],
    "name:rus_x_preferred":[
        "Fed\u2019kino"
    ],
    "name:rus_x_variant":[
        "\u0424\u0435\u0434\u044c\u043a\u0438\u043d\u043e"
    ],
    "name:und_x_variant":[
        "\u0424\u0435\u0434\u044c\u043a\u0438\u043d\u043e",
        "Fed\u2019kino"
    ],
    "wof:name":"Fed'kino",
    "wof:placetype":"locality"
},
  "geometry": {"coordinates":[48.3314,53.784],"type":"Point"}
}