{
  "type": "Feature",
  "properties": {
    "gn:admin1_code":"72.0",
    "gn:asciiname":"Berezovka",
    "gn:country_code":"RU",
    "gn:dem":176,
    "gn:feature_class":"P",
    "gn:feature_code":"PPL",
    "gn:name":"Ber\u00ebzovka",
    "gn:population":0,
    "gn:timezone":"Europe/Moscow",
    "iso:country":"RU",
    "name:ceb_x_preferred":[
        "Berezovka"
    ],
    "name:eng_x_preferred":[
        "Ber\u00ebzovka"
    ],
    "name:lav_x_preferred":[
        "Berezovka"
    ],
    "name:lit_x_preferred":[
        "Berezovka"
    ],
    "name:rus_x_preferred":[
        "\u0411\u0435\u0440\u0435\u0437\u043e\u0432\u043a\u0430"
    ],
    "name:rus_x_variant":[
        "\u0411\u0435\u0440\u0451\u0437\u043e\u0432\u043a\u0430"
    ],
    "name:swe_x_preferred":[
        "Berezovka"
    ],
    "name:und_x_variant":[
        "Ber\u00ebzovka"
    ],
    "wof:name":"Berezovka",
    "wof:placetype":"locality"
},
  "geometry": {"coordinates":[42.06538,52.00013],"type":"Point"}
}