{
  "type": "Feature",
  "properties": {
    "gn:admin1_code":"12",
    "gn:asciiname":"Verkhnekrasnoarmeyskoye",
    "gn:country_code":"RU",
    "gn:dem":373,
    "gn:feature_class":"P",
    "gn:feature_code":"PPL",
    "gn:name":"Verkhnekrasnoarmeyskoye",
    "gn:population":0,
    "gn:timezone":"Europe/Moscow",
    "iso:country":"RU",
    "name:rus_x_preferred":[
        "\u0412\u0435\u0440\u0445\u043d\u0435\u043a\u0440\u0430\u0441\u043d\u043e\u0430\u0440\u043c\u0435\u0439\u0441\u043a\u043e\u0435"
    ],
    "name:und_x_variant":[
        "Verhnekrasnoarmejskoe"
    ],
    "wof:name":"Verkhnekrasnoarmeyskoye",
    "wof:placetype":"locality"
},
  "geometry": {"coordinates":[45.10972,43.51778],"type":"Point"}
}