{
  "type": "Feature",
  "properties": {
    "gn:admin1_code":"33",
    "gn:asciiname":"Shevyrtalovo",
    "gn:country_code":"RU",
    "gn:dem":179,
    "gn:feature_class":"P",
    "gn:feature_code":"PPL",
    "gn:name":"Shevyrtalovo",
    "gn:population":0,
    "gn:timezone":"Europe/Kirov",
    "iso:country":"RU",
    "name:eng_x_preferred":[
        "Shevyrtalovo"
    ],
    "name:nor_x_preferred":[
        "Sjevyrtalovo"
    ],
    "name:rus_x_preferred":[
        "\u0428\u0435\u0432\u044b\u0440\u0442\u0430\u043b\u043e\u0432\u043e"
    ],
    "wof:name":"Shevyrtalovo",
    "wof:placetype":"locality"
},
  "geometry": {"coordinates":[50.70833,59.17889],"type":"Point"}
}