{
  "type": "Feature",
  "properties": {
    "gn:admin1_code":"69",
    "gn:asciiname":"Svobodnyy Trud",
    "gn:country_code":"RU",
    "gn:dem":193,
    "gn:feature_class":"P",
    "gn:feature_code":"PPL",
    "gn:name":"Svobodnyy Trud",
    "gn:population":0,
    "gn:timezone":"Europe/Moscow",
    "iso:country":"RU",
    "wof:name":"Svobodnyy Trud",
    "wof:placetype":"locality"
},
  "geometry": {"coordinates":[32.71667,53.81667],"type":"Point"}
}