{
  "type": "Feature",
  "properties": {
    "gn:admin1_code":"33.0",
    "gn:asciiname":"Parfenki",
    "gn:country_code":"RU",
    "gn:dem":125,
    "gn:feature_class":"P",
    "gn:feature_code":"PPL",
    "gn:name":"Parf\u00ebnki",
    "gn:population":0,
    "gn:timezone":"Europe/Kirov",
    "iso:country":"RU",
    "name:rus_x_preferred":[
        "\u041f\u0430\u0440\u0444\u0451\u043d\u043a\u0438"
    ],
    "name:und_x_variant":[
        "Parf\u00ebnki",
        "\u041f\u0430\u0440\u0444\u0451\u043d\u043a\u0438"
    ],
    "wof:name":"Parfenki",
    "wof:placetype":"locality"
},
  "geometry": {"coordinates":[48.38815,57.4821],"type":"Point"}
}