{
  "type": "Feature",
  "properties": {
    "gn:admin1_code":"51.0",
    "gn:asciiname":"Yamshchikovo",
    "gn:country_code":"RU",
    "gn:dem":115,
    "gn:feature_class":"P",
    "gn:feature_code":"PPL",
    "gn:name":"Yamshchikovo",
    "gn:population":0,
    "gn:timezone":"Europe/Moscow",
    "iso:country":"RU",
    "wof:name":"Yamshchikovo",
    "wof:placetype":"locality"
},
  "geometry": {"coordinates":[43.06348,56.74325],"type":"Point"}
}