{
  "type": "Feature",
  "properties": {
    "gn:admin1_code":"47",
    "gn:asciiname":"Kamenskaya",
    "gn:country_code":"RU",
    "gn:dem":136,
    "gn:feature_class":"P",
    "gn:feature_code":"PPL",
    "gn:name":"Kamenskaya",
    "gn:population":0,
    "gn:timezone":"Europe/Moscow",
    "iso:country":"RU",
    "name:rus_x_preferred":[
        "\u041a\u0430\u043c\u0435\u043d\u0441\u043a\u0430\u044f"
    ],
    "name:und_x_variant":[
        "\u041a\u0430\u043c\u0435\u043d\u0441\u043a\u0430\u044f"
    ],
    "wof:name":"Kamenskaya",
    "wof:placetype":"locality"
},
  "geometry": {"coordinates":[39.26942,55.4257],"type":"Point"}
}