{
  "type": "Feature",
  "properties": {
    "gn:admin1_code":"90.0",
    "gn:asciiname":"Kanamova",
    "gn:country_code":"RU",
    "gn:dem":164,
    "gn:feature_class":"P",
    "gn:feature_code":"PPL",
    "gn:name":"Kanamova",
    "gn:population":0,
    "gn:timezone":"Asia/Yekaterinburg",
    "iso:country":"RU",
    "name:che_x_preferred":[
        "\u041a\u0430\u043d\u0430\u043c\u043e\u0432\u0430"
    ],
    "name:koi_x_preferred":[
        "\u041a\u0430\u043d\u0430\u043c\u043e\u0432\u0447\u0438"
    ],
    "name:rus_x_preferred":[
        "\u041a\u0430\u043d\u0430\u043c\u043e\u0432\u0430"
    ],
    "wof:name":"Kanamova",
    "wof:placetype":"locality"
},
  "geometry": {"coordinates":[54.6252,58.8544],"type":"Point"}
}