{
  "type": "Feature",
  "properties": {
    "gn:admin1_code":"9",
    "gn:asciiname":"Makeshkino",
    "gn:country_code":"RU",
    "gn:dem":101,
    "gn:feature_class":"P",
    "gn:feature_code":"PPL",
    "gn:name":"Makeshkino",
    "gn:population":0,
    "gn:timezone":"Europe/Moscow",
    "iso:country":"RU",
    "name:rus_x_preferred":[
        "\u041c\u0430\u043a\u0435\u0448\u043a\u0438\u043d\u043e"
    ],
    "wof:name":"Makeshkino",
    "wof:placetype":"locality"
},
  "geometry": {"coordinates":[37.81532,50.63975],"type":"Point"}
}