{
  "type": "Feature",
  "properties": {
    "gn:admin1_code":"9",
    "gn:asciiname":"Kobylevka",
    "gn:country_code":"RU",
    "gn:dem":170,
    "gn:feature_class":"P",
    "gn:feature_code":"PPL",
    "gn:name":"Kobyl\u00ebvka",
    "gn:population":0,
    "gn:timezone":"Europe/Moscow",
    "iso:country":"RU",
    "name:rus_x_preferred":[
        "\u041a\u043e\u0431\u044b\u043b\u0451\u0432\u043a\u0430"
    ],
    "name:und_x_variant":[
        "Kobyl\u00ebvka"
    ],
    "wof:name":"Kobylevka",
    "wof:placetype":"locality"
},
  "geometry": {"coordinates":[35.99528,50.85361],"type":"Point"}
}