{
  "type": "Feature",
  "properties": {
    "gn:admin1_code":"53",
    "gn:asciiname":"Klyuchi",
    "gn:country_code":"RU",
    "gn:dem":176,
    "gn:feature_class":"P",
    "gn:feature_code":"PPL",
    "gn:name":"Klyuchi",
    "gn:population":0,
    "gn:timezone":"Asia/Novosibirsk",
    "iso:country":"RU",
    "name:eng_x_preferred":[
        "Klyuchi"
    ],
    "name:nor_x_preferred":[
        "Kljutsji"
    ],
    "name:rus_x_preferred":[
        "\u041a\u043b\u044e\u0447\u0438"
    ],
    "name:und_x_variant":[
        "\u041a\u043b\u044e\u0447\u0438",
        "Klyuchi"
    ],
    "wof:name":"Klyuchi",
    "wof:placetype":"locality"
},
  "geometry": {"coordinates":[83.2714,54.8455],"type":"Point"}
}