{
  "type": "Feature",
  "properties": {
    "gn:admin1_code":"8",
    "gn:asciiname":"Gumerovo",
    "gn:country_code":"RU",
    "gn:dem":206,
    "gn:feature_class":"P",
    "gn:feature_code":"PPL",
    "gn:name":"Gumerovo",
    "gn:population":0,
    "gn:timezone":"Asia/Yekaterinburg",
    "iso:country":"RU",
    "name:eng_x_preferred":[
        "Gumerovo"
    ],
    "name:nor_x_preferred":[
        "Gumerovo"
    ],
    "name:rus_x_preferred":[
        "\u0413\u0443\u043c\u0435\u0440\u043e\u0432\u043e"
    ],
    "name:und_x_variant":[
        "\u0413\u0443\u043c\u0435\u0440\u043e\u0432\u043e",
        "Gumerovo"
    ],
    "wof:name":"Gumerovo",
    "wof:placetype":"locality"
},
  "geometry": {"coordinates":[56.55873,53.5671],"type":"Point"}
}