{
  "type": "Feature",
  "properties": {
    "gn:admin1_code":"38.0",
    "gn:asciiname":"Akhtanak",
    "gn:country_code":"RU",
    "gn:dem":-2,
    "gn:feature_class":"P",
    "gn:feature_code":"PPL",
    "gn:name":"Akhtanak",
    "gn:population":0,
    "gn:timezone":"Europe/Moscow",
    "iso:country":"RU",
    "name:nor_x_preferred":[
        "Akhtanak"
    ],
    "name:rus_x_preferred":[
        "\u0410\u0445\u0442\u0430\u043d\u0430\u043a"
    ],
    "wof:name":"Akhtanak",
    "wof:placetype":"locality"
},
  "geometry": {"coordinates":[36.95944,45.32944000000001],"type":"Point"}
}