{
  "type": "Feature",
  "properties": {
    "gn:admin1_code":"77.0",
    "gn:asciiname":"Belyatino",
    "gn:country_code":"RU",
    "gn:dem":255,
    "gn:feature_class":"P",
    "gn:feature_code":"PPL",
    "gn:name":"Belyatino",
    "gn:population":0,
    "gn:timezone":"Europe/Moscow",
    "iso:country":"RU",
    "name:nor_x_preferred":[
        "Beljatino"
    ],
    "name:rus_x_preferred":[
        "\u0411\u0435\u043b\u044f\u0442\u0438\u043d\u043e"
    ],
    "wof:name":"Belyatino",
    "wof:placetype":"locality"
},
  "geometry": {"coordinates":[33.89549,57.32514000000001],"type":"Point"}
}