{
  "type": "Feature",
  "properties": {
    "gn:admin1_code":"77",
    "gn:asciiname":"Shcheberikha",
    "gn:country_code":"RU",
    "gn:dem":215,
    "gn:feature_class":"P",
    "gn:feature_code":"PPL",
    "gn:name":"Shcheberikha",
    "gn:population":0,
    "gn:timezone":"Europe/Moscow",
    "iso:country":"RU",
    "name:rus_x_preferred":[
        "\u0429\u0435\u0431\u0435\u0440\u0438\u0445\u0430"
    ],
    "name:und_x_variant":[
        "Shchiberekha",
        "Shiberekha",
        "Shcheberekha",
        "Shcheberikha"
    ],
    "wof:name":"Shcheberikha",
    "wof:placetype":"locality"
},
  "geometry": {"coordinates":[32.72637,57.33753000000001],"type":"Point"}
}