{
  "type": "Feature",
  "properties": {
    "gn:admin1_code":"65",
    "gn:asciiname":"Verkhnyaya Vasil'yevka",
    "gn:country_code":"RU",
    "gn:dem":134,
    "gn:feature_class":"P",
    "gn:feature_code":"PPL",
    "gn:name":"Verkhnyaya Vasil\u2019yevka",
    "gn:population":0,
    "gn:timezone":"Europe/Samara",
    "iso:country":"RU",
    "name:rus_x_preferred":[
        "\u0412\u0435\u0440\u0445\u043d\u044f\u044f \u0412\u0430\u0441\u0438\u043b\u044c\u0435\u0432\u043a\u0430"
    ],
    "name:und_x_variant":[
        "Verkhnyaya Vasil\u2019yevka"
    ],
    "wof:name":"Verkhnyaya Vasil'yevka",
    "wof:placetype":"locality"
},
  "geometry": {"coordinates":[50.7346,54.2637],"type":"Point"}
}