{
  "type": "Feature",
  "properties": {
    "gn:admin1_code":"6.0",
    "gn:asciiname":"Kanzovo",
    "gn:country_code":"RU",
    "gn:dem":3,
    "gn:feature_class":"P",
    "gn:feature_code":"PPL",
    "gn:name":"Kanzovo",
    "gn:population":0,
    "gn:timezone":"Europe/Moscow",
    "iso:country":"RU",
    "name:rus_x_preferred":[
        "\u041a\u0430\u043d\u0437\u043e\u0432\u043e"
    ],
    "wof:name":"Kanzovo",
    "wof:placetype":"locality"
},
  "geometry": {"coordinates":[41.6092,63.8475],"type":"Point"}
}