{
  "type": "Feature",
  "properties": {
    "gn:admin1_code":"33.0",
    "gn:asciiname":"Khaustovo",
    "gn:country_code":"RU",
    "gn:dem":123,
    "gn:feature_class":"P",
    "gn:feature_code":"PPL",
    "gn:name":"Khaustovo",
    "gn:population":0,
    "gn:timezone":"Europe/Kirov",
    "iso:country":"RU",
    "name:rus_x_preferred":[
        "\u0425\u0430\u0443\u0441\u0442\u043e\u0432\u043e"
    ],
    "name:und_x_variant":[
        "\u0425\u0430\u0443\u0441\u0442\u043e\u0432\u043e"
    ],
    "wof:name":"Khaustovo",
    "wof:placetype":"locality"
},
  "geometry": {"coordinates":[48.34485,58.43798],"type":"Point"}
}