{
  "type": "Feature",
  "properties": {
    "gn:admin1_code":"28",
    "gn:asciiname":"Virda",
    "gn:cc2":"RU",
    "gn:country_code":"RU",
    "gn:dem":171,
    "gn:feature_class":"P",
    "gn:feature_code":"PPL",
    "gn:name":"Virda",
    "gn:population":0,
    "gn:timezone":"Europe/Moscow",
    "iso:country":"RU",
    "name:fin_x_preferred":[
        "Virta"
    ],
    "name:und_x_variant":[
        "Vivda",
        "Virda"
    ],
    "wof:name":"Virda",
    "wof:placetype":"locality"
},
  "geometry": {"coordinates":[30.86667000000001,63.86666999999999],"type":"Point"}
}