{
  "type": "Feature",
  "properties": {
    "gn:admin1_code":"33.0",
    "gn:asciiname":"Pestovy",
    "gn:country_code":"RU",
    "gn:dem":151,
    "gn:feature_class":"P",
    "gn:feature_code":"PPL",
    "gn:name":"Pestovy",
    "gn:population":0,
    "gn:timezone":"Europe/Kirov",
    "iso:country":"RU",
    "name:rus_x_preferred":[
        "\u041f\u0435\u0441\u0442\u043e\u0432\u044b"
    ],
    "wof:name":"Pestovy",
    "wof:placetype":"locality"
},
  "geometry": {"coordinates":[48.09841,58.3774],"type":"Point"}
}