{
  "type": "Feature",
  "properties": {
    "gn:admin1_code":"42",
    "gn:asciiname":"Molodezhnoye",
    "gn:cc2":"RU",
    "gn:country_code":"RU",
    "gn:dem":39,
    "gn:feature_class":"P",
    "gn:feature_code":"PPL",
    "gn:name":"Molod\u00ebzhnoye",
    "gn:population":0,
    "gn:timezone":"Europe/Moscow",
    "iso:country":"RU",
    "name:fin_x_preferred":[
        "Kiimaj\u00e4rvi"
    ],
    "name:rus_x_preferred":[
        "\u041c\u043e\u043b\u043e\u0434\u0451\u0436\u043d\u043e\u0435"
    ],
    "name:und_x_variant":[
        "Kimayarvi",
        "Molod\u00ebzhnoye",
        "\u041c\u043e\u043b\u043e\u0434\u0451\u0436\u043d\u043e\u0435"
    ],
    "wof:name":"Molodezhnoye",
    "wof:placetype":"locality"
},
  "geometry": {"coordinates":[30.10494000000001,60.77643000000001],"type":"Point"}
}