{
  "type": "Feature",
  "properties": {
    "gn:admin1_code":"42.0",
    "gn:asciiname":"Chikozero-Pozdnyakovskaya",
    "gn:cc2":"RU",
    "gn:country_code":"RU",
    "gn:dem":125,
    "gn:feature_class":"P",
    "gn:feature_code":"PPL",
    "gn:name":"Chikozero-Pozdnyakovskaya",
    "gn:population":0,
    "gn:timezone":"Europe/Moscow",
    "iso:country":"RU",
    "name:rus_x_preferred":[
        "\u0427\u0438\u043a\u043e\u0437\u0435\u0440\u043e-\u041f\u043e\u0437\u0434\u043d\u044f\u043a\u043e\u0432\u0441\u043a\u0430\u044f"
    ],
    "name:und_x_variant":[
        "Pozdnjakovskaja",
        "Pozdnyakovskaya",
        "Chikozero-Pozdnyakovskaya",
        "\u0427\u0438\u043a\u043e\u0437\u0435\u0440\u043e-\u041f\u043e\u0437\u0434\u043d\u044f\u043a\u043e\u0432\u0441\u043a\u0430\u044f"
    ],
    "wof:name":"Chikozero-Pozdnyakovskaya",
    "wof:placetype":"locality"
},
  "geometry": {"coordinates":[34.61667,60.68333000000001],"type":"Point"}
}