{
  "type": "Feature",
  "properties": {
    "gn:admin1_code":"69",
    "gn:asciiname":"Zubtsy",
    "gn:country_code":"RU",
    "gn:dem":234,
    "gn:feature_class":"P",
    "gn:feature_code":"PPL",
    "gn:name":"Zubtsy",
    "gn:population":0,
    "gn:timezone":"Europe/Moscow",
    "iso:country":"RU",
    "name:rus_x_preferred":[
        "\u0417\u0443\u0431\u0446\u044b"
    ],
    "wof:name":"Zubtsy",
    "wof:placetype":"locality"
},
  "geometry": {"coordinates":[32.4769,55.5071],"type":"Point"}
}