{
  "type": "Feature",
  "properties": {
    "gn:admin1_code":"63",
    "gn:asciiname":"Ugol'nyy",
    "gn:country_code":"RU",
    "gn:dem":772,
    "gn:feature_class":"P",
    "gn:feature_code":"PPL",
    "gn:name":"Ugol\u2019nyy",
    "gn:population":0,
    "gn:timezone":"Asia/Yakutsk",
    "iso:country":"RU",
    "name:eng_x_preferred":[
        "Ugol'nyy"
    ],
    "name:nor_x_preferred":[
        "Ugolnyj"
    ],
    "name:rus_x_preferred":[
        "\u0423\u0433\u043e\u043b\u044c\u043d\u044b\u0439"
    ],
    "name:und_x_variant":[
        "Ugol\u2019nyy"
    ],
    "wof:name":"Ugol'nyy",
    "wof:placetype":"locality"
},
  "geometry": {"coordinates":[124.85083,56.99417],"type":"Point"}
}