{
  "type": "Feature",
  "properties": {
    "gn:admin1_code":"71",
    "gn:asciiname":"Sukhaya Reka",
    "gn:country_code":"RU",
    "gn:dem":308,
    "gn:feature_class":"P",
    "gn:feature_code":"PPL",
    "gn:name":"Sukhaya Reka",
    "gn:population":0,
    "gn:timezone":"Asia/Yekaterinburg",
    "iso:country":"RU",
    "name:rus_x_preferred":[
        "\u0421\u0443\u0445\u0430\u044f \u0420\u0435\u043a\u0430"
    ],
    "name:und_x_variant":[
        "\u0421\u0443\u0445\u0430\u044f \u0420\u0435\u043a\u0430"
    ],
    "wof:name":"Sukhaya Reka",
    "wof:placetype":"locality"
},
  "geometry": {"coordinates":[57.71666999999999,56.41667],"type":"Point"}
}