{
  "type": "Feature",
  "properties": {
    "gn:admin1_code":"52",
    "gn:asciiname":"Staroye Shchetinovo",
    "gn:country_code":"RU",
    "gn:dem":181,
    "gn:feature_class":"P",
    "gn:feature_code":"PPL",
    "gn:name":"Staroye Shchetinovo",
    "gn:population":0,
    "gn:timezone":"Europe/Moscow",
    "iso:country":"RU",
    "name:rus_x_preferred":[
        "\u0421\u0442\u0430\u0440\u043e\u0435 \u0429\u0435\u0442\u0438\u043d\u043e\u0432\u043e"
    ],
    "wof:name":"Staroye Shchetinovo",
    "wof:placetype":"locality"
},
  "geometry": {"coordinates":[34.43333,58.51667],"type":"Point"}
}