{
  "type": "Feature",
  "properties": {
    "gn:admin1_code":"86.0",
    "gn:asciiname":"Grakov",
    "gn:country_code":"RU",
    "gn:dem":160,
    "gn:feature_class":"P",
    "gn:feature_code":"PPL",
    "gn:name":"Grakov",
    "gn:population":0,
    "gn:timezone":"Europe/Moscow",
    "iso:country":"RU",
    "name:rus_x_preferred":[
        "\u0413\u0440\u0430\u043a\u043e\u0432"
    ],
    "name:und_x_variant":[
        "\u0413\u0440\u0430\u043a\u043e\u0432"
    ],
    "wof:name":"Grakov",
    "wof:placetype":"locality"
},
  "geometry": {"coordinates":[39.72679,50.01194],"type":"Point"}
}