{
  "type": "Feature",
  "properties": {
    "gn:admin1_code":"52",
    "gn:asciiname":"Potepalovo",
    "gn:country_code":"RU",
    "gn:dem":108,
    "gn:feature_class":"P",
    "gn:feature_code":"PPL",
    "gn:name":"Potepalovo",
    "gn:population":0,
    "gn:timezone":"Europe/Moscow",
    "iso:country":"RU",
    "name:rus_x_preferred":[
        "\u041f\u043e\u0442\u0435\u043f\u0430\u043b\u043e\u0432\u043e"
    ],
    "wof:name":"Potepalovo",
    "wof:placetype":"locality"
},
  "geometry": {"coordinates":[31.3398,57.0108],"type":"Point"}
}