{
  "type": "Feature",
  "properties": {
    "gn:admin1_code":"12.0",
    "gn:asciiname":"Tarkatova",
    "gn:country_code":"RU",
    "gn:dem":1359,
    "gn:feature_class":"P",
    "gn:feature_code":"PPL",
    "gn:name":"Tarkatova",
    "gn:population":0,
    "gn:timezone":"Europe/Moscow",
    "iso:country":"RU",
    "wof:name":"Tarkatova",
    "wof:placetype":"locality"
},
  "geometry": {"coordinates":[45.65528,42.80778],"type":"Point"}
}