{
  "type": "Feature",
  "properties": {
    "gn:admin1_code":"45.0",
    "gn:asciiname":"Kuchukener",
    "gn:country_code":"RU",
    "gn:dem":206,
    "gn:feature_class":"P",
    "gn:feature_code":"PPL",
    "gn:name":"Kuchukener",
    "gn:population":0,
    "gn:timezone":"Europe/Moscow",
    "iso:country":"RU",
    "name:rus_x_preferred":[
        "\u041a\u0443\u0447\u0443\u043a\u0435\u043d\u0435\u0440"
    ],
    "name:und_x_variant":[
        "\u041a\u0443\u0447\u0443\u043a\u0435\u043d\u0435\u0440"
    ],
    "wof:name":"Kuchukener",
    "wof:placetype":"locality"
},
  "geometry": {"coordinates":[48.87083,56.40528000000001],"type":"Point"}
}