{
  "type": "Feature",
  "properties": {
    "gn:admin1_code":"43.0",
    "gn:asciiname":"Plavitsa",
    "gn:country_code":"RU",
    "gn:dem":131,
    "gn:feature_class":"P",
    "gn:feature_code":"PPL",
    "gn:name":"Plavitsa",
    "gn:population":0,
    "gn:timezone":"Europe/Moscow",
    "iso:country":"RU",
    "name:rus_x_preferred":[
        "\u041f\u043b\u0430\u0432\u0438\u0446\u0430"
    ],
    "wof:name":"Plavitsa",
    "wof:placetype":"locality"
},
  "geometry": {"coordinates":[40.35,52.2387],"type":"Point"}
}