{
  "type": "Feature",
  "properties": {
    "gn:admin1_code":"37.0",
    "gn:asciiname":"Antropovo",
    "gn:country_code":"RU",
    "gn:dem":134,
    "gn:feature_class":"P",
    "gn:feature_code":"PPL",
    "gn:name":"Antropovo",
    "gn:population":2,
    "gn:timezone":"Europe/Moscow",
    "iso:country":"RU",
    "name:eng_x_preferred":[
        "Antropovo"
    ],
    "name:nor_x_preferred":[
        "Antropovo"
    ],
    "name:rus_x_preferred":[
        "\u0410\u043d\u0442\u0440\u043e\u043f\u043e\u0432\u043e"
    ],
    "name:und_x_variant":[
        "\u0410\u043d\u0442\u0440\u043e\u043f\u043e\u0432\u043e",
        "Antropovo"
    ],
    "wof:name":"Antropovo",
    "wof:placetype":"locality",
    "wof:population":2
},
  "geometry": {"coordinates":[43.49486,58.40722],"type":"Point"}
}