{
  "type": "Feature",
  "properties": {
    "gn:admin1_code":"85",
    "gn:asciiname":"Ilevo",
    "gn:country_code":"RU",
    "gn:dem":154,
    "gn:feature_class":"P",
    "gn:feature_code":"PPL",
    "gn:name":"Il\u00ebvo",
    "gn:population":0,
    "gn:timezone":"Europe/Moscow",
    "iso:country":"RU",
    "name:rus_x_preferred":[
        "\u0418\u043b\u0451\u0432\u043e"
    ],
    "name:und_x_variant":[
        "Il\u00ebvo"
    ],
    "wof:name":"Ilevo",
    "wof:placetype":"locality"
},
  "geometry": {"coordinates":[36.9339,59.8056],"type":"Point"}
}