{
  "type": "Feature",
  "properties": {
    "gn:admin1_code":"83",
    "gn:asciiname":"Kesovo",
    "gn:country_code":"RU",
    "gn:dem":105,
    "gn:feature_class":"P",
    "gn:feature_code":"PPL",
    "gn:name":"Kesovo",
    "gn:population":0,
    "gn:timezone":"Europe/Moscow",
    "iso:country":"RU",
    "name:rus_x_preferred":[
        "\u041a\u0435\u0441\u043e\u0432\u043e"
    ],
    "wof:name":"Kesovo",
    "wof:placetype":"locality"
},
  "geometry": {"coordinates":[41.892,55.4749],"type":"Point"}
}