{
  "type": "Feature",
  "properties": {
    "gn:admin1_code":"33",
    "gn:asciiname":"Luza",
    "gn:country_code":"RU",
    "gn:dem":159,
    "gn:feature_class":"P",
    "gn:feature_code":"PPL",
    "gn:name":"Luza",
    "gn:population":0,
    "gn:timezone":"Europe/Kirov",
    "iso:country":"RU",
    "name:ara_x_preferred":[
        "\u0644\u0648\u0632\u0627"
    ],
    "name:bel_x_preferred":[
        "\u041b\u0443\u0437\u0430"
    ],
    "name:ben_x_preferred":[
        "\u09b2\u09c1\u099c\u09be"
    ],
    "name:ceb_x_preferred":[
        "Luza"
    ],
    "name:ces_x_preferred":[
        "Luza"
    ],
    "name:deu_x_preferred":[
        "Luza"
    ],
    "name:ell_x_preferred":[
        "\u039b\u03bf\u03cd\u03b6\u03b1"
    ],
    "name:heb_x_preferred":[
        "\u05d0\u05d9\u05d9 \u05dc\u05d9\u05d9\u05d7\u05d5\u05d1"
    ],
    "name:hin_x_preferred":[
        "\u0932\u0941\u091c\u093c\u093e"
    ],
    "name:hun_x_preferred":[
        "Luza"
    ],
    "name:ind_x_preferred":[
        "Luza"
    ],
    "name:ita_x_preferred":[
        "Luza"
    ],
    "name:kor_x_preferred":[
        "\ub8e8\uc790"
    ],
    "name:nor_x_preferred":[
        "Luza"
    ],
    "name:por_x_preferred":[
        "Luza"
    ],
    "name:rus_x_preferred":[
        "\u041b\u0443\u0437\u0430"
    ],
    "name:spa_x_preferred":[
        "Luza"
    ],
    "name:swe_x_preferred":[
        "Luza"
    ],
    "name:ukr_x_preferred":[
        "\u041b\u0443\u0437\u0430"
    ],
    "name:und_x_variant":[
        "Luza-Vazhintsy"
    ],
    "name:urd_x_preferred":[
        "\u0644\u0648\u0632\u0627"
    ],
    "name:vie_x_preferred":[
        "S\u00f4ng Luza"
    ],
    "wof:name":"Luza",
    "wof:placetype":"locality"
},
  "geometry": {"coordinates":[49.91997,58.6597],"type":"Point"}
}