{
  "type": "Feature",
  "properties": {
    "gn:admin1_code":"33",
    "gn:asciiname":"Luza",
    "gn:country_code":"RU",
    "gn:dem":159,
    "gn:feature_class":"P",
    "gn:feature_code":"PPL",
    "gn:name":"Luza",
    "gn:population":0,
    "gn:timezone":"Europe/Kirov",
    "iso:country":"RU",
    "name:bel_x_preferred":[
        "\u041b\u0443\u0437\u0430"
    ],
    "name:ceb_x_preferred":[
        "Luza"
    ],
    "name:ces_x_preferred":[
        "Luza"
    ],
    "name:deu_x_preferred":[
        "Luza"
    ],
    "name:hun_x_preferred":[
        "Luza"
    ],
    "name:ita_x_preferred":[
        "Luza"
    ],
    "name:nor_x_preferred":[
        "Luza"
    ],
    "name:rus_x_preferred":[
        "\u041b\u0443\u0437\u0430"
    ],
    "name:spa_x_preferred":[
        "Luza"
    ],
    "name:swe_x_preferred":[
        "Luza"
    ],
    "name:ukr_x_preferred":[
        "\u041b\u0443\u0437\u0430"
    ],
    "name:und_x_variant":[
        "Luza-Vazhintsy"
    ],
    "wof:name":"Luza",
    "wof:placetype":"locality"
},
  "geometry": {"coordinates":[49.91997,58.6597],"type":"Point"}
}