{
  "type": "Feature",
  "properties": {
    "gn:admin1_code":"52.0",
    "gn:asciiname":"Borozdy",
    "gn:country_code":"RU",
    "gn:dem":195,
    "gn:feature_class":"P",
    "gn:feature_code":"PPL",
    "gn:name":"Borozdy",
    "gn:population":0,
    "gn:timezone":"Europe/Moscow",
    "iso:country":"RU",
    "name:nor_x_preferred":[
        "Borozdy"
    ],
    "name:rus_x_preferred":[
        "\u0411\u043e\u0440\u043e\u0437\u0434\u044b"
    ],
    "wof:name":"Borozdy",
    "wof:placetype":"locality"
},
  "geometry": {"coordinates":[33.42783,58.27593],"type":"Point"}
}