{
  "type": "Feature",
  "properties": {
    "gn:admin1_code":"10",
    "gn:asciiname":"Melovka",
    "gn:country_code":"RU",
    "gn:dem":175,
    "gn:feature_class":"P",
    "gn:feature_code":"PPL",
    "gn:name":"Melovka",
    "gn:population":0,
    "gn:timezone":"Europe/Moscow",
    "iso:country":"RU",
    "name:eng_x_preferred":[
        "Melovka"
    ],
    "name:nor_x_preferred":[
        "Melovka"
    ],
    "name:rus_x_preferred":[
        "\u041c\u0435\u043b\u043e\u0432\u043a\u0430"
    ],
    "wof:name":"Melovka",
    "wof:placetype":"locality"
},
  "geometry": {"coordinates":[33.66582,53.49288000000001],"type":"Point"}
}