{
  "type": "Feature",
  "properties": {
    "gn:admin1_code":"85",
    "gn:asciiname":"Zaozeritsa",
    "gn:country_code":"RU",
    "gn:dem":74,
    "gn:feature_class":"P",
    "gn:feature_code":"PPL",
    "gn:name":"Zaozeritsa",
    "gn:population":0,
    "gn:timezone":"Europe/Moscow",
    "iso:country":"RU",
    "name:eng_x_preferred":[
        "Zaozeritsa"
    ],
    "name:nor_x_preferred":[
        "Zaozeritsa"
    ],
    "name:rus_x_preferred":[
        "\u0417\u0430\u043e\u0437\u0435\u0440\u0438\u0446\u0430"
    ],
    "name:und_x_variant":[
        "\u0417\u0430\u043e\u0437\u0435\u0440\u0438\u0446\u0430",
        "Zaozeritsa"
    ],
    "wof:name":"Zaozeritsa",
    "wof:placetype":"locality"
},
  "geometry": {"coordinates":[46.47705,60.53116],"type":"Point"}
}