{
  "type": "Feature",
  "properties": {
    "gn:admin1_code":"52",
    "gn:asciiname":"Sorokopenno",
    "gn:country_code":"RU",
    "gn:dem":30,
    "gn:feature_class":"P",
    "gn:feature_code":"PPL",
    "gn:name":"Sorokopenno",
    "gn:population":0,
    "gn:timezone":"Europe/Moscow",
    "iso:country":"RU",
    "name:rus_x_preferred":[
        "\u0421\u043e\u0440\u043e\u043a\u043e\u043f\u0435\u043d\u043d\u043e"
    ],
    "name:und_x_variant":[
        "\u0421\u043e\u0440\u043e\u043a\u043e\u043f\u0435\u043d\u043d\u043e"
    ],
    "wof:name":"Sorokopenno",
    "wof:placetype":"locality"
},
  "geometry": {"coordinates":[31.88289,57.75556],"type":"Point"}
}