{
  "type": "Feature",
  "properties": {
    "gn:admin1_code":"88.0",
    "gn:asciiname":"Baskakovo",
    "gn:country_code":"RU",
    "gn:dem":102,
    "gn:feature_class":"P",
    "gn:feature_code":"PPL",
    "gn:name":"Baskakovo",
    "gn:population":0,
    "gn:timezone":"Europe/Moscow",
    "iso:country":"RU",
    "name:nor_x_preferred":[
        "Baskakovo"
    ],
    "name:rus_x_preferred":[
        "\u0411\u0430\u0441\u043a\u0430\u043a\u043e\u0432\u043e"
    ],
    "wof:name":"Baskakovo",
    "wof:placetype":"locality"
},
  "geometry": {"coordinates":[40.48618,58.00154000000001],"type":"Point"}
}