{
  "type": "Feature",
  "properties": {
    "gn:admin1_code":"33.0",
    "gn:asciiname":"Maksenki",
    "gn:country_code":"RU",
    "gn:dem":120,
    "gn:feature_class":"P",
    "gn:feature_code":"PPL",
    "gn:name":"Maks\u00ebnki",
    "gn:population":0,
    "gn:timezone":"Europe/Kirov",
    "iso:country":"RU",
    "name:rus_x_preferred":[
        "\u041c\u0430\u043a\u0441\u0451\u043d\u043a\u0438"
    ],
    "name:und_x_variant":[
        "Maks\u00ebnki"
    ],
    "wof:name":"Maksenki",
    "wof:placetype":"locality"
},
  "geometry": {"coordinates":[48.65145,58.25216999999999],"type":"Point"}
}