{
  "type": "Feature",
  "properties": {
    "gn:admin1_code":"45",
    "gn:asciiname":"Polyanok",
    "gn:country_code":"RU",
    "gn:dem":166,
    "gn:feature_class":"P",
    "gn:feature_code":"PPL",
    "gn:name":"Polyanok",
    "gn:population":0,
    "gn:timezone":"Europe/Moscow",
    "iso:country":"RU",
    "name:rus_x_preferred":[
        "\u041f\u043e\u043b\u044f\u043d\u043e\u043a"
    ],
    "name:und_x_variant":[
        "\u041f\u043e\u043b\u044f\u043d\u043e\u043a"
    ],
    "wof:name":"Polyanok",
    "wof:placetype":"locality"
},
  "geometry": {"coordinates":[46.5985,56.1838],"type":"Point"}
}