{
  "type": "Feature",
  "properties": {
    "gn:admin1_code":"91",
    "gn:asciiname":"Sosnovka",
    "gn:country_code":"RU",
    "gn:dem":351,
    "gn:feature_class":"P",
    "gn:feature_code":"PPL",
    "gn:name":"Sosnovka",
    "gn:population":0,
    "gn:timezone":"Asia/Krasnoyarsk",
    "iso:country":"RU",
    "name:eng_x_preferred":[
        "Sosnovka"
    ],
    "name:nor_x_preferred":[
        "Ust-Sosnovka"
    ],
    "name:rus_x_preferred":[
        "\u0423\u0441\u0442\u044c-\u0421\u043e\u0441\u043d\u043e\u0432\u043a\u0430"
    ],
    "name:rus_x_variant":[
        "\u0421\u043e\u0441\u043d\u043e\u0432\u043a\u0430"
    ],
    "name:und_x_variant":[
        "Ust\u2019-Sosnovka",
        "Sosnovka"
    ],
    "wof:name":"Sosnovka",
    "wof:placetype":"locality"
},
  "geometry": {"coordinates":[89.76194,55.38306],"type":"Point"}
}