{
  "type": "Feature",
  "properties": {
    "gn:admin1_code":"41.0",
    "gn:asciiname":"Baklanovka",
    "gn:country_code":"RU",
    "gn:dem":194,
    "gn:feature_class":"P",
    "gn:feature_code":"PPL",
    "gn:name":"Baklanovka",
    "gn:population":0,
    "gn:timezone":"Europe/Moscow",
    "iso:country":"RU",
    "name:nor_x_preferred":[
        "Baklanovka"
    ],
    "name:rus_x_preferred":[
        "\u0411\u0430\u043a\u043b\u0430\u043d\u043e\u0432\u043a\u0430"
    ],
    "wof:name":"Baklanovka",
    "wof:placetype":"locality"
},
  "geometry": {"coordinates":[37.3556,51.8304],"type":"Point"}
}