{
  "type": "Feature",
  "properties": {
    "gn:admin1_code":"25",
    "gn:asciiname":"Pnevo",
    "gn:country_code":"RU",
    "gn:dem":170,
    "gn:feature_class":"P",
    "gn:feature_code":"PPL",
    "gn:name":"Pn\u00ebvo",
    "gn:population":0,
    "gn:timezone":"Europe/Moscow",
    "iso:country":"RU",
    "name:rus_x_preferred":[
        "\u041f\u043d\u0451\u0432o"
    ],
    "name:rus_x_variant":[
        "\u041f\u043d\u0451\u0432o-\u0420\u0430\u0445\u043c\u0430\u043d\u043e\u0432\u043e"
    ],
    "name:und_x_variant":[
        "Pn\u00ebvo-Rakhmanovo",
        "Pn\u00ebvo"
    ],
    "wof:name":"Pnevo",
    "wof:placetype":"locality"
},
  "geometry": {"coordinates":[36.32267,54.74732],"type":"Point"}
}