{
  "type": "Feature",
  "properties": {
    "gn:admin1_code":"51",
    "gn:asciiname":"Sudostroy",
    "gn:country_code":"RU",
    "gn:dem":90,
    "gn:feature_class":"P",
    "gn:feature_code":"PPL",
    "gn:name":"Sudostroy",
    "gn:population":0,
    "gn:timezone":"Europe/Moscow",
    "iso:country":"RU",
    "name:rus_x_preferred":[
        "\u0421\u0443\u0434\u043e\u0441\u0442\u0440\u043e\u0439"
    ],
    "wof:name":"Sudostroy",
    "wof:placetype":"locality"
},
  "geometry": {"coordinates":[42.2571,55.7229],"type":"Point"}
}