{
  "type": "Feature",
  "properties": {
    "gn:admin1_code":"8.0",
    "gn:asciiname":"Andreyevskiy",
    "gn:country_code":"RU",
    "gn:dem":231,
    "gn:feature_class":"P",
    "gn:feature_code":"PPL",
    "gn:name":"Andreyevskiy",
    "gn:population":0,
    "gn:timezone":"Asia/Yekaterinburg",
    "iso:country":"RU",
    "name:nor_x_preferred":[
        "Andrejevskij"
    ],
    "name:rus_x_preferred":[
        "\u0410\u043d\u0434\u0440\u0435\u0435\u0432\u0441\u043a\u0438\u0439"
    ],
    "name:und_x_variant":[
        "Andreyevskoye",
        "Andreyevskiy"
    ],
    "wof:name":"Andreyevskiy",
    "wof:placetype":"locality"
},
  "geometry": {"coordinates":[56.33735,52.83033],"type":"Point"}
}