{
  "type": "Feature",
  "properties": {
    "gn:admin1_code":"47.0",
    "gn:asciiname":"Perkhurovo",
    "gn:country_code":"RU",
    "gn:dem":152,
    "gn:feature_class":"P",
    "gn:feature_code":"PPL",
    "gn:name":"Perkhurovo",
    "gn:population":0,
    "gn:timezone":"Europe/Moscow",
    "iso:country":"RU",
    "name:rus_x_preferred":[
        "\u041f\u0435\u0440\u0445\u0443\u0440\u043e\u0432\u043e"
    ],
    "name:und_x_variant":[
        "\u041f\u0435\u0440\u0445\u0443\u0440\u043e\u0432\u043e"
    ],
    "wof:name":"Perkhurovo",
    "wof:placetype":"locality"
},
  "geometry": {"coordinates":[37.56437,55.08823],"type":"Point"}
}