{
  "type": "Feature",
  "properties": {
    "gn:admin1_code":"73",
    "gn:asciiname":"Nurminka",
    "gn:country_code":"RU",
    "gn:dem":72,
    "gn:feature_class":"P",
    "gn:feature_code":"PPL",
    "gn:name":"Nurminka",
    "gn:population":0,
    "gn:timezone":"Europe/Volgograd",
    "iso:country":"RU",
    "name:rus_x_preferred":[
        "\u041d\u0443\u0440\u043c\u0438\u043d\u043a\u0430"
    ],
    "wof:name":"Nurminka",
    "wof:placetype":"locality"
},
  "geometry": {"coordinates":[50.9648,56.1938],"type":"Point"}
}