{
  "type": "Feature",
  "properties": {
    "gn:admin1_code":"41",
    "gn:asciiname":"Kamenets",
    "gn:country_code":"RU",
    "gn:dem":215,
    "gn:feature_class":"P",
    "gn:feature_code":"PPL",
    "gn:name":"Kamenets",
    "gn:population":0,
    "gn:timezone":"Europe/Moscow",
    "iso:country":"RU",
    "name:ceb_x_preferred":[
        "Kamenets"
    ],
    "name:fra_x_preferred":[
        "Kamenets"
    ],
    "name:ita_x_preferred":[
        "Kamenec"
    ],
    "name:rus_x_preferred":[
        "\u041a\u0430\u043c\u0435\u043d\u0435\u0446"
    ],
    "name:swe_x_preferred":[
        "Kamenets"
    ],
    "wof:name":"Kamenets",
    "wof:placetype":"locality"
},
  "geometry": {"coordinates":[35.3241,52.2587],"type":"Point"}
}