{
  "type": "Feature",
  "properties": {
    "gn:admin1_code":"63",
    "gn:asciiname":"Sukharnoye",
    "gn:country_code":"RU",
    "gn:dem":17,
    "gn:feature_class":"P",
    "gn:feature_code":"PPL",
    "gn:name":"Sukharnoye",
    "gn:population":0,
    "gn:timezone":"Asia/Magadan",
    "iso:country":"RU",
    "name:rus_x_preferred":[
        "\u0421\u0443\u0445\u0430\u0440\u043d\u043e\u0435"
    ],
    "name:und_x_variant":[
        "Sukharnyy",
        "Sukharnaya",
        "Sukharnoe",
        "Sukharnoye",
        "\u0421\u0443\u0445\u0430\u0440\u043d\u043e\u0435"
    ],
    "wof:name":"Sukharnoye",
    "wof:placetype":"locality"
},
  "geometry": {"coordinates":[161.82835,69.49112],"type":"Point"}
}