{
  "type": "Feature",
  "properties": {
    "gn:admin1_code":"4",
    "gn:asciiname":"Moskovka",
    "gn:country_code":"RU",
    "gn:dem":182,
    "gn:feature_class":"P",
    "gn:feature_code":"PPL",
    "gn:name":"Moskovka",
    "gn:population":0,
    "gn:timezone":"Asia/Barnaul",
    "iso:country":"RU",
    "name:eng_x_preferred":[
        "Moskovka"
    ],
    "name:nor_x_preferred":[
        "Moskovka"
    ],
    "name:rus_x_preferred":[
        "\u041c\u043e\u0441\u043a\u043e\u0432\u043a\u0430"
    ],
    "name:und_x_variant":[
        "Moskovskiy"
    ],
    "wof:name":"Moskovka",
    "wof:placetype":"locality"
},
  "geometry": {"coordinates":[79.78530000000001,53.4368],"type":"Point"}
}