{
  "type": "Feature",
  "properties": {
    "gn:admin1_code":"63",
    "gn:asciiname":"Vokhgal",
    "gn:cc2":"RU",
    "gn:country_code":"RU",
    "gn:dem":28,
    "gn:feature_class":"P",
    "gn:feature_code":"PPL",
    "gn:name":"Vokhgal",
    "gn:population":0,
    "gn:timezone":"Asia/Magadan",
    "iso:country":"RU",
    "name:und_x_variant":[
        "Vakhgol",
        "Vokhgal"
    ],
    "wof:name":"Vokhgal",
    "wof:placetype":"locality"
},
  "geometry": {"coordinates":[151.80000000000001,68.08333],"type":"Point"}
}