{
  "type": "Feature",
  "properties": {
    "gn:admin1_code":"42",
    "gn:asciiname":"Tiskolovo",
    "gn:country_code":"RU",
    "gn:dem":14,
    "gn:feature_class":"P",
    "gn:feature_code":"PPL",
    "gn:name":"Tiskolovo",
    "gn:population":0,
    "gn:timezone":"Europe/Moscow",
    "iso:country":"RU",
    "name:fin_x_preferred":[
        "Kiiskala"
    ],
    "wof:name":"Tiskolovo",
    "wof:placetype":"locality"
},
  "geometry": {"coordinates":[28.03216,59.71967],"type":"Point"}
}