{
  "type": "Feature",
  "properties": {
    "gn:admin1_code":"30",
    "gn:asciiname":"Buryatskiy",
    "gn:country_code":"RU",
    "gn:dem":855,
    "gn:feature_class":"P",
    "gn:feature_code":"PPL",
    "gn:name":"Buryatskiy",
    "gn:population":0,
    "gn:timezone":"Asia/Vladivostok",
    "iso:country":"RU",
    "name:rus_x_preferred":[
        "\u0411\u0443\u0440\u044f\u0442\u0441\u043a\u0438\u0439"
    ],
    "name:und_x_variant":[
        "\u0411\u0443\u0440\u044f\u0442\u0441\u043a\u0438\u0439"
    ],
    "wof:name":"Buryatskiy",
    "wof:placetype":"locality"
},
  "geometry": {"coordinates":[133.88333,52.16667],"type":"Point"}
}