{
  "type": "Feature",
  "properties": {
    "gn:admin1_code":"17",
    "gn:admin2_code":"480804",
    "gn:asciiname":"Tsidatl'",
    "gn:country_code":"RU",
    "gn:dem":1230,
    "gn:feature_class":"P",
    "gn:feature_code":"PPL",
    "gn:name":"Tsidatl\u2019",
    "gn:population":0,
    "gn:timezone":"Europe/Moscow",
    "iso:country":"RU",
    "wof:name":"Tsidatl'",
    "wof:placetype":"locality"
},
  "geometry": {"coordinates":[46.08306,42.50806],"type":"Point"}
}