{
  "type": "Feature",
  "properties": {
    "gn:admin1_code":"6",
    "gn:asciiname":"Izhmozero",
    "gn:country_code":"RU",
    "gn:dem":45,
    "gn:feature_class":"P",
    "gn:feature_code":"PPL",
    "gn:name":"Izhmozero",
    "gn:population":0,
    "gn:timezone":"Europe/Moscow",
    "iso:country":"RU",
    "name:rus_x_preferred":[
        "\u0418\u0436\u043c\u043e\u0437\u0435\u0440\u043e"
    ],
    "name:und_x_variant":[
        "\u0418\u0436\u043c\u043e\u0437\u0435\u0440\u043e"
    ],
    "wof:name":"Izhmozero",
    "wof:placetype":"locality"
},
  "geometry": {"coordinates":[40.78333,64.78333000000001],"type":"Point"}
}