{
  "type": "Feature",
  "properties": {
    "gn:admin1_code":"93",
    "gn:asciiname":"Verkhne-Undinskoye",
    "gn:country_code":"RU",
    "gn:dem":883,
    "gn:feature_class":"P",
    "gn:feature_code":"PPL",
    "gn:name":"Verkhne-Undinskoye",
    "gn:population":0,
    "gn:timezone":"Asia/Chita",
    "iso:country":"RU",
    "name:und_x_variant":[
        "Verkhne-Undinskogo",
        "Verkhne-Undinskoye"
    ],
    "wof:name":"Verkhne-Undinskoye",
    "wof:placetype":"locality"
},
  "geometry": {"coordinates":[117.61667,51.21667],"type":"Point"}
}