{
  "type": "Feature",
  "properties": {
    "gn:admin1_code":"28.0",
    "gn:asciiname":"Besov Nos",
    "gn:country_code":"RU",
    "gn:dem":28,
    "gn:feature_class":"P",
    "gn:feature_code":"PPL",
    "gn:name":"Besov Nos",
    "gn:population":0,
    "gn:timezone":"Europe/Moscow",
    "iso:country":"RU",
    "name:nor_x_preferred":[
        "Besov Nos"
    ],
    "name:rus_x_preferred":[
        "\u0411\u0435\u0441\u043e\u0432 \u041d\u043e\u0441"
    ],
    "name:und_x_variant":[
        "Pirunnena",
        "Besov Nos"
    ],
    "wof:name":"Besov Nos",
    "wof:placetype":"locality"
},
  "geometry": {"coordinates":[36.05,61.66667],"type":"Point"}
}