{
  "type": "Feature",
  "properties": {
    "gn:admin1_code":"69",
    "gn:asciiname":"Krestovka",
    "gn:country_code":"RU",
    "gn:dem":210,
    "gn:feature_class":"P",
    "gn:feature_code":"PPL",
    "gn:name":"Krestovka",
    "gn:population":0,
    "gn:timezone":"Europe/Moscow",
    "iso:country":"RU",
    "name:rus_x_preferred":[
        "\u041a\u0440\u0435\u0441\u0442\u043e\u0432\u043a\u0430"
    ],
    "wof:name":"Krestovka",
    "wof:placetype":"locality"
},
  "geometry": {"coordinates":[32.49278,55.16056],"type":"Point"}
}