{
  "type": "Feature",
  "properties": {
    "gn:admin1_code":"47",
    "gn:asciiname":"Mednoye-Vlasovo",
    "gn:cc2":"RU",
    "gn:country_code":"RU",
    "gn:dem":137,
    "gn:feature_class":"P",
    "gn:feature_code":"PPL",
    "gn:name":"Mednoye-Vlasovo",
    "gn:population":0,
    "gn:timezone":"Europe/Moscow",
    "iso:country":"RU",
    "name:rus_x_preferred":[
        "\u041c\u0435\u0434\u043d\u043e\u0435-\u0412\u043b\u0430\u0441\u043e\u0432\u043e"
    ],
    "name:und_x_variant":[
        "Sanatoriy Mednoye",
        "Sanatoriy Mednoye Vlasovo",
        "Mednoye-Vlasovo",
        "\u041c\u0435\u0434\u043d\u043e\u0435-\u0412\u043b\u0430\u0441\u043e\u0432\u043e"
    ],
    "wof:name":"Mednoye-Vlasovo",
    "wof:placetype":"locality"
},
  "geometry": {"coordinates":[38.20222,55.93917],"type":"Point"}
}