{
  "type": "Feature",
  "properties": {
    "gn:admin1_code":"69",
    "gn:asciiname":"Svinoroyka",
    "gn:country_code":"RU",
    "gn:dem":193,
    "gn:feature_class":"P",
    "gn:feature_code":"PPL",
    "gn:name":"Svinoroyka",
    "gn:population":0,
    "gn:timezone":"Europe/Moscow",
    "iso:country":"RU",
    "name:und_x_variant":[
        "Svinaroyka"
    ],
    "wof:name":"Svinoroyka",
    "wof:placetype":"locality"
},
  "geometry": {"coordinates":[34.23990999999999,55.91396],"type":"Point"}
}