{
  "type": "Feature",
  "properties": {
    "gn:admin1_code":"67.0",
    "gn:asciiname":"Belyayevka",
    "gn:country_code":"RU",
    "gn:dem":166,
    "gn:feature_class":"P",
    "gn:feature_code":"PPL",
    "gn:name":"Belyayevka",
    "gn:population":0,
    "gn:timezone":"Europe/Saratov",
    "iso:country":"RU",
    "name:ceb_x_preferred":[
        "Belyayevka"
    ],
    "name:nor_x_preferred":[
        "Beljaevka"
    ],
    "name:rus_x_preferred":[
        "\u0411\u0435\u043b\u044f\u0435\u0432\u043a\u0430"
    ],
    "name:swe_x_preferred":[
        "Belyayevka"
    ],
    "wof:name":"Belyayevka",
    "wof:placetype":"locality"
},
  "geometry": {"coordinates":[42.90148,52.08353],"type":"Point"}
}