{
  "type": "Feature",
  "properties": {
    "gn:admin1_code":"6",
    "gn:asciiname":"Koposovo",
    "gn:country_code":"RU",
    "gn:dem":93,
    "gn:feature_class":"P",
    "gn:feature_code":"PPL",
    "gn:name":"Koposovo",
    "gn:population":0,
    "gn:timezone":"Europe/Moscow",
    "iso:country":"RU",
    "name:eng_x_preferred":[
        "Koposovo"
    ],
    "name:nor_x_preferred":[
        "Koposovo"
    ],
    "name:rus_x_preferred":[
        "\u041a\u043e\u043f\u043e\u0441\u043e\u0432\u043e"
    ],
    "wof:name":"Koposovo",
    "wof:placetype":"locality"
},
  "geometry": {"coordinates":[46.22196,61.18037],"type":"Point"}
}