{
  "type": "Feature",
  "properties": {
    "gn:admin1_code":"13",
    "gn:asciiname":"Kolpakovo",
    "gn:country_code":"RU",
    "gn:dem":150,
    "gn:feature_class":"P",
    "gn:feature_code":"PPL",
    "gn:name":"Kolpakovo",
    "gn:population":0,
    "gn:timezone":"Asia/Yekaterinburg",
    "iso:country":"RU",
    "name:rus_x_preferred":[
        "\u041a\u043e\u043b\u043f\u0430\u043a\u043e\u0432\u043e"
    ],
    "name:und_x_variant":[
        "Kolpakova"
    ],
    "wof:name":"Kolpakovo",
    "wof:placetype":"locality"
},
  "geometry": {"coordinates":[61.74800000000001,56.1815],"type":"Point"}
}