{
  "type": "Feature",
  "properties": {
    "gn:admin1_code":"42",
    "gn:asciiname":"Krasnyy Bor",
    "gn:country_code":"RU",
    "gn:dem":96,
    "gn:feature_class":"P",
    "gn:feature_code":"PPL",
    "gn:name":"Krasnyy Bor",
    "gn:population":0,
    "gn:timezone":"Europe/Moscow",
    "iso:country":"RU",
    "name:eng_x_preferred":[
        "Krasnyy Bor"
    ],
    "name:fin_x_preferred":[
        "Ruskeakangas"
    ],
    "name:nor_x_preferred":[
        "Krasnyj Bor"
    ],
    "name:rus_x_preferred":[
        "\u041a\u0440\u0430\u0441\u043d\u044b\u0439 \u0411\u043e\u0440"
    ],
    "wof:name":"Krasnyy Bor",
    "wof:placetype":"locality"
},
  "geometry": {"coordinates":[34.24522,60.35548000000001],"type":"Point"}
}