{
  "type": "Feature",
  "properties": {
    "gn:admin1_code":"60",
    "gn:asciiname":"Pligovki",
    "gn:country_code":"RU",
    "gn:dem":218,
    "gn:feature_class":"P",
    "gn:feature_code":"PPL",
    "gn:name":"Pligovki",
    "gn:population":0,
    "gn:timezone":"Europe/Moscow",
    "iso:country":"RU",
    "name:rus_x_preferred":[
        "\u041f\u043b\u0438\u0433\u043e\u0432\u043a\u0438"
    ],
    "wof:name":"Pligovki",
    "wof:placetype":"locality"
},
  "geometry": {"coordinates":[29.9087,56.2258],"type":"Point"}
}