{
  "type": "Feature",
  "properties": {
    "gn:admin1_code":"33",
    "gn:asciiname":"Khodyri",
    "gn:country_code":"RU",
    "gn:dem":142,
    "gn:feature_class":"P",
    "gn:feature_code":"PPL",
    "gn:name":"Khodyri",
    "gn:population":0,
    "gn:timezone":"Europe/Kirov",
    "iso:country":"RU",
    "name:rus_x_preferred":[
        "\u0425\u043e\u0434\u044b\u0440\u0438"
    ],
    "name:und_x_variant":[
        "\u0425\u043e\u0434\u044b\u0440\u0438"
    ],
    "wof:name":"Khodyri",
    "wof:placetype":"locality"
},
  "geometry": {"coordinates":[50.70066,57.79993],"type":"Point"}
}