{
  "type": "Feature",
  "properties": {
    "gn:admin1_code":"63",
    "gn:asciiname":"Daloko-Yele",
    "gn:country_code":"RU",
    "gn:dem":214,
    "gn:feature_class":"P",
    "gn:feature_code":"PPL",
    "gn:name":"Daloko-Yele",
    "gn:population":0,
    "gn:timezone":"Asia/Vladivostok",
    "iso:country":"RU",
    "name:rus_x_preferred":[
        "\u0414\u0430\u043b\u043e\u043a\u043e-\u0415\u043b\u0435"
    ],
    "wof:name":"Daloko-Yele",
    "wof:placetype":"locality"
},
  "geometry": {"coordinates":[134.25,61.06667],"type":"Point"}
}