{
  "type": "Feature",
  "properties": {
    "gn:admin1_code":"60",
    "gn:asciiname":"Besputino",
    "gn:country_code":"RU",
    "gn:dem":73,
    "gn:feature_class":"P",
    "gn:feature_code":"PPL",
    "gn:name":"Besputino",
    "gn:population":0,
    "gn:timezone":"Europe/Moscow",
    "iso:country":"RU",
    "name:rus_x_preferred":[
        "\u0411\u0435\u0441\u043f\u0443\u0442\u0438\u043d\u043e"
    ],
    "wof:name":"Besputino",
    "wof:placetype":"locality"
},
  "geometry": {"coordinates":[28.37054,57.21629],"type":"Point"}
}