{
  "type": "Feature",
  "properties": {
    "gn:admin1_code":"4",
    "gn:asciiname":"Tselinnyy",
    "gn:country_code":"RU",
    "gn:dem":143,
    "gn:feature_class":"P",
    "gn:feature_code":"PPL",
    "gn:name":"Tselinnyy",
    "gn:population":0,
    "gn:timezone":"Asia/Barnaul",
    "iso:country":"RU",
    "name:eng_x_preferred":[
        "Tselinnyy"
    ],
    "name:nor_x_preferred":[
        "Tselinnyj"
    ],
    "name:rus_x_preferred":[
        "\u0426\u0435\u043b\u0438\u043d\u043d\u044b\u0439"
    ],
    "wof:name":"Tselinnyy",
    "wof:placetype":"locality"
},
  "geometry": {"coordinates":[79.23515,52.25673],"type":"Point"}
}