{
  "type": "Feature",
  "properties": {
    "gn:admin1_code":"55",
    "gn:asciiname":"Malaya Remizenka",
    "gn:country_code":"RU",
    "gn:dem":169,
    "gn:feature_class":"P",
    "gn:feature_code":"PPL",
    "gn:name":"Malaya Remizenka",
    "gn:population":0,
    "gn:timezone":"Asia/Yekaterinburg",
    "iso:country":"RU",
    "name:eng_x_preferred":[
        "Malaya REmizenka"
    ],
    "name:nor_x_preferred":[
        "Malaja Remizenka"
    ],
    "name:rus_x_preferred":[
        "\u041c\u0430\u043b\u0430\u044f \u0420\u0435\u043c\u0438\u0437\u0435\u043d\u043a\u0430"
    ],
    "name:und_x_variant":[
        "Malaya Remizenka"
    ],
    "wof:name":"Malaya Remizenka",
    "wof:placetype":"locality"
},
  "geometry": {"coordinates":[52.75919,52.16413],"type":"Point"}
}