{
  "type": "Feature",
  "properties": {
    "gn:admin1_code":"27",
    "gn:asciiname":"Molochnyy",
    "gn:country_code":"RU",
    "gn:dem":596,
    "gn:feature_class":"P",
    "gn:feature_code":"PPL",
    "gn:name":"Molochnyy",
    "gn:population":0,
    "gn:timezone":"Europe/Moscow",
    "iso:country":"RU",
    "wof:name":"Molochnyy",
    "wof:placetype":"locality"
},
  "geometry": {"coordinates":[42.09417,44.2675],"type":"Point"}
}