{
  "type": "Feature",
  "properties": {
    "gn:admin1_code":"91",
    "gn:asciiname":"Angul",
    "gn:country_code":"RU",
    "gn:dem":571,
    "gn:feature_class":"P",
    "gn:feature_code":"PPL",
    "gn:name":"Angul",
    "gn:population":0,
    "gn:timezone":"Asia/Krasnoyarsk",
    "iso:country":"RU",
    "name:ben_x_preferred":[
        "\u0985\u09a8\u09c1\u0997\u09c1\u09b2"
    ],
    "name:bpy_x_preferred":[
        "\u0985\u09a8\u09c1\u0997\u09c1\u09b2"
    ],
    "name:cat_x_preferred":[
        "Angul"
    ],
    "name:ceb_x_preferred":[
        "Angul"
    ],
    "name:deu_x_preferred":[
        "Angul"
    ],
    "name:fas_x_preferred":[
        "\u0622\u0646\u06af\u0648\u0644"
    ],
    "name:fra_x_preferred":[
        "Angul"
    ],
    "name:hin_x_preferred":[
        "\u0905\u0928\u0941\u0917\u0941\u0932"
    ],
    "name:ita_x_preferred":[
        "Angul"
    ],
    "name:kan_x_preferred":[
        "\u0c85\u0c82\u0c97\u0cc1\u0cb2\u0ccd"
    ],
    "name:mar_x_preferred":[
        "\u0905\u0902\u0917\u0941\u0932"
    ],
    "name:msa_x_preferred":[
        "Anugul"
    ],
    "name:new_x_preferred":[
        "\u0905\u0928\u0941\u0917\u094b\u0932"
    ],
    "name:nld_x_preferred":[
        "Anugul"
    ],
    "name:nor_x_preferred":[
        "Angul"
    ],
    "name:ori_x_preferred":[
        "\u0b05\u0b28\u0b41\u0b17\u0b4b\u0b33"
    ],
    "name:pnb_x_preferred":[
        "\u0627\u0646\u0648\u06af\u0644"
    ],
    "name:pol_x_preferred":[
        "Angul"
    ],
    "name:por_x_preferred":[
        "Anugul"
    ],
    "name:rus_x_preferred":[
        "\u0410\u043d\u0433\u0443\u043b"
    ],
    "name:sat_x_preferred":[
        "\u1c5a\u1c71\u1c69\u1c5c\u1c69\u1c72"
    ],
    "name:swe_x_preferred":[
        "Angul"
    ],
    "name:tam_x_preferred":[
        "\u0b85\u0ba9\u0bc1\u0b95\u0bcb\u0bb3\u0bcd"
    ],
    "name:tel_x_preferred":[
        "\u0c05\u0c02\u0c17\u0c41\u0c32\u0c4d"
    ],
    "name:urd_x_preferred":[
        "\u0627\u0646\u06af\u0648\u0644"
    ],
    "name:vie_x_preferred":[
        "Anugul"
    ],
    "name:zho_x_preferred":[
        "\u963f\u52aa\u53e4\u5c14"
    ],
    "wof:name":"Angul",
    "wof:placetype":"locality"
},
  "geometry": {"coordinates":[93.98333,54.88333000000001],"type":"Point"}
}