{
  "type": "Feature",
  "properties": {
    "gn:admin1_code":"91",
    "gn:asciiname":"Angul",
    "gn:country_code":"RU",
    "gn:dem":571,
    "gn:feature_class":"P",
    "gn:feature_code":"PPL",
    "gn:name":"Angul",
    "gn:population":0,
    "gn:timezone":"Asia/Krasnoyarsk",
    "iso:country":"RU",
    "name:nor_x_preferred":[
        "Angul"
    ],
    "name:rus_x_preferred":[
        "\u0410\u043d\u0433\u0443\u043b"
    ],
    "wof:name":"Angul",
    "wof:placetype":"locality"
},
  "geometry": {"coordinates":[93.98333,54.88333000000001],"type":"Point"}
}