{
  "type": "Feature",
  "properties": {
    "gn:admin1_code":"47",
    "gn:asciiname":"Kaluzhskaya",
    "gn:country_code":"RU",
    "gn:dem":273,
    "gn:feature_class":"P",
    "gn:feature_code":"PPL",
    "gn:name":"Kaluzhskaya",
    "gn:population":0,
    "gn:timezone":"Europe/Moscow",
    "iso:country":"RU",
    "name:rus_x_preferred":[
        "\u041a\u0430\u043b\u0443\u0436\u0441\u043a\u0430\u044f"
    ],
    "wof:name":"Kaluzhskaya",
    "wof:placetype":"locality"
},
  "geometry": {"coordinates":[35.36306,55.50471999999999],"type":"Point"}
}