{
  "type": "Feature",
  "properties": {
    "gn:admin1_code":"55",
    "gn:asciiname":"Novo-Orenburgskiy",
    "gn:country_code":"RU",
    "gn:dem":161,
    "gn:feature_class":"P",
    "gn:feature_code":"PPL",
    "gn:name":"Novo-Orenburgskiy",
    "gn:population":0,
    "gn:timezone":"Asia/Yekaterinburg",
    "iso:country":"RU",
    "name:rus_x_preferred":[
        "\u041d\u043e\u0432\u043e-\u041e\u0440\u0435\u043d\u0431\u0443\u0440\u0433\u0441\u043a\u0438\u0439"
    ],
    "name:und_x_variant":[
        "\u041d\u043e\u0432\u043e-\u041e\u0440\u0435\u043d\u0431\u0443\u0440\u0433\u0441\u043a\u0438\u0439"
    ],
    "wof:name":"Novo-Orenburgskiy",
    "wof:placetype":"locality"
},
  "geometry": {"coordinates":[54.18333000000001,52.51667],"type":"Point"}
}