{
  "type": "Feature",
  "properties": {
    "gn:admin1_code":"77",
    "gn:asciiname":"Martyushino",
    "gn:country_code":"RU",
    "gn:dem":249,
    "gn:feature_class":"P",
    "gn:feature_code":"PPL",
    "gn:name":"Martyushino",
    "gn:population":0,
    "gn:timezone":"Europe/Moscow",
    "iso:country":"RU",
    "name:rus_x_preferred":[
        "\u041c\u0430\u0440\u0442\u044e\u0448\u0438\u043d\u043e"
    ],
    "name:und_x_variant":[
        "\u041c\u0430\u0440\u0442\u044e\u0448\u0438\u043d\u043e"
    ],
    "wof:name":"Martyushino",
    "wof:placetype":"locality"
},
  "geometry": {"coordinates":[33.51878,57.09815],"type":"Point"}
}