{
  "type": "Feature",
  "properties": {
    "gn:admin1_code":"60.0",
    "gn:asciiname":"Cheremkha",
    "gn:country_code":"RU",
    "gn:dem":67,
    "gn:feature_class":"P",
    "gn:feature_code":"PPL",
    "gn:name":"Cheremkha",
    "gn:population":0,
    "gn:timezone":"Europe/Moscow",
    "iso:country":"RU",
    "name:rus_x_preferred":[
        "\u0427\u0435\u0440\u0435\u043c\u0445\u0430"
    ],
    "name:und_x_variant":[
        "Cheremshina",
        "Cheremkha"
    ],
    "wof:name":"Cheremkha",
    "wof:placetype":"locality"
},
  "geometry": {"coordinates":[28.05409,58.74717],"type":"Point"}
}