{
  "type": "Feature",
  "properties": {
    "gn:admin1_code":"38.0",
    "gn:asciiname":"Chebotarevskiy",
    "gn:country_code":"RU",
    "gn:dem":22,
    "gn:feature_class":"P",
    "gn:feature_code":"PPL",
    "gn:name":"Chebotarevskiy",
    "gn:population":0,
    "gn:timezone":"Europe/Moscow",
    "iso:country":"RU",
    "name:rus_x_preferred":[
        "\u0427\u0435\u0431\u043e\u0442\u0430\u0440\u0435\u0432\u0441\u043a\u0438\u0439"
    ],
    "name:und_x_variant":[
        "\u0427\u0435\u0431\u043e\u0442\u0430\u0440\u0435\u0432\u0441\u043a\u0438\u0439"
    ],
    "wof:name":"Chebotarevskiy",
    "wof:placetype":"locality"
},
  "geometry": {"coordinates":[39.9125,46.5425],"type":"Point"}
}