{
  "type": "Feature",
  "properties": {
    "gn:admin1_code":"6",
    "gn:asciiname":"Palkino",
    "gn:country_code":"RU",
    "gn:dem":115,
    "gn:feature_class":"P",
    "gn:feature_code":"PPL",
    "gn:name":"Palkino",
    "gn:population":0,
    "gn:timezone":"Europe/Moscow",
    "iso:country":"RU",
    "name:eng_x_preferred":[
        "Palkino"
    ],
    "name:nor_x_preferred":[
        "Palkino"
    ],
    "name:rus_x_preferred":[
        "\u041f\u0430\u043b\u043a\u0438\u043d\u043e"
    ],
    "name:und_x_variant":[
        "Palkinskaya"
    ],
    "wof:name":"Palkino",
    "wof:placetype":"locality"
},
  "geometry": {"coordinates":[41.6453,61.4907],"type":"Point"}
}