{
  "type": "Feature",
  "properties": {
    "gn:admin1_code":"85",
    "gn:asciiname":"Lukinki",
    "gn:country_code":"RU",
    "gn:dem":126,
    "gn:feature_class":"P",
    "gn:feature_code":"PPL",
    "gn:name":"Lukinki",
    "gn:population":0,
    "gn:timezone":"Europe/Moscow",
    "iso:country":"RU",
    "name:rus_x_preferred":[
        "\u041b\u0443\u043a\u0438\u043d\u043a\u0438"
    ],
    "name:und_x_variant":[
        "\u041b\u0443\u043a\u0438\u043d\u043a\u0438"
    ],
    "wof:name":"Lukinki",
    "wof:placetype":"locality"
},
  "geometry": {"coordinates":[38.54964,59.19307],"type":"Point"}
}