{
  "type": "Feature",
  "properties": {
    "gn:admin1_code":"16",
    "gn:asciiname":"Sespel'",
    "gn:country_code":"RU",
    "gn:dem":156,
    "gn:feature_class":"P",
    "gn:feature_code":"PPL",
    "gn:name":"Sespel\u2019",
    "gn:population":0,
    "gn:timezone":"Europe/Moscow",
    "iso:country":"RU",
    "name:rus_x_preferred":[
        "\u0421\u0435\u0441\u043f\u0435\u043b\u044c"
    ],
    "name:und_x_variant":[
        "Shugurovo",
        "Sespel\u2019",
        "\u0421\u0435\u0441\u043f\u0435\u043b\u044c"
    ],
    "wof:name":"Sespel'",
    "wof:placetype":"locality"
},
  "geometry": {"coordinates":[47.29907,55.60582],"type":"Point"}
}