{
  "type": "Feature",
  "properties": {
    "gn:country":"RU",
    "gn:fcode":"PPL",
    "gn:population":0,
    "iso:country":"RU",
    "qs_pg:aaroncc":"RU",
    "qs_pg:gn_country":"RU",
    "qs_pg:gn_fcode":"PPL",
    "qs_pg:gn_pop":0,
    "qs_pg:name":"Golyanovo",
    "qs_pg:name_adm0":"Russia",
    "qs_pg:name_adm1":"Moscow Federal City",
    "qs_pg:photos":294,
    "qs_pg:photos_1k":60,
    "qs_pg:photos_9k":1,
    "qs_pg:photos_9r":4,
    "qs_pg:photos_all":294,
    "qs_pg:photos_sr":5,
    "qs_pg:pop_sr":0,
    "qs_pg:qs_pg_placetype":"neighbourhood",
    "qs_pg:qs_pg_placetype_gp":"Suburb",
    "qs_pg:woe_adm0":23424936,
    "woe:adm0_id":23424936,
    "woe:name_adm0":"Russia",
    "woe:name_adm1":"Moscow Federal City",
    "woe:placetype":"Suburb",
    "wof:name":"Golyanovo",
    "wof:placetype":"neighbourhood"
},
  "geometry": {"coordinates":[38.05,56.31667],"type":"Point"}
}