{
  "type": "Feature",
  "properties": {
    "gn:admin1_code":"91",
    "gn:asciiname":"Uyar",
    "gn:country_code":"RU",
    "gn:dem":194,
    "gn:feature_class":"P",
    "gn:feature_code":"PPL",
    "gn:name":"Uyar",
    "gn:population":0,
    "gn:timezone":"Asia/Krasnoyarsk",
    "iso:country":"RU",
    "name:ben_x_preferred":[
        "\u0989\u09df\u09be\u09b0"
    ],
    "name:ceb_x_preferred":[
        "Uyar"
    ],
    "name:ell_x_preferred":[
        "\u039f\u03c5\u03b3\u03b9\u03ac\u03c1"
    ],
    "name:heb_x_preferred":[
        "\u05d0\u05d5\u05d9\u05d0\u05e8"
    ],
    "name:hin_x_preferred":[
        "\u090a\u092f\u093e\u0930"
    ],
    "name:ind_x_preferred":[
        "Uyar"
    ],
    "name:jpn_x_preferred":[
        "\u30a6\u30e4\u30eb"
    ],
    "name:kor_x_preferred":[
        "\uc6b0\uc57c\ub974"
    ],
    "name:spa_x_preferred":[
        "Uyar"
    ],
    "name:swe_x_preferred":[
        "Uyar"
    ],
    "name:tur_x_preferred":[
        "Uyar"
    ],
    "name:urd_x_preferred":[
        "\u0627\u0648\u06cc\u0627\u0631"
    ],
    "name:vie_x_preferred":[
        "Uyar"
    ],
    "wof:name":"Uyar",
    "wof:placetype":"locality"
},
  "geometry": {"coordinates":[100.57601,58.19627],"type":"Point"}
}