{
  "type": "Feature",
  "properties": {
    "gn:admin1_code":"91",
    "gn:asciiname":"Uyar",
    "gn:country_code":"RU",
    "gn:dem":194,
    "gn:feature_class":"P",
    "gn:feature_code":"PPL",
    "gn:name":"Uyar",
    "gn:population":0,
    "gn:timezone":"Asia/Krasnoyarsk",
    "iso:country":"RU",
    "name:ceb_x_preferred":[
        "Uyar"
    ],
    "name:tur_x_preferred":[
        "Uyar"
    ],
    "wof:name":"Uyar",
    "wof:placetype":"locality"
},
  "geometry": {"coordinates":[100.57601,58.19627],"type":"Point"}
}