{
  "type": "Feature",
  "properties": {
    "gn:admin1_code":"4",
    "gn:asciiname":"Lazurka",
    "gn:country_code":"RU",
    "gn:dem":489,
    "gn:feature_class":"P",
    "gn:feature_code":"PPL",
    "gn:name":"Lazurka",
    "gn:population":0,
    "gn:timezone":"Asia/Barnaul",
    "iso:country":"RU",
    "name:eng_x_preferred":[
        "Lazurka"
    ],
    "name:nor_x_preferred":[
        "Lazurka"
    ],
    "name:rus_x_preferred":[
        "\u041b\u0430\u0437\u0443\u0440\u043a\u0430"
    ],
    "name:und_x_variant":[
        "\u041b\u0430\u0437\u0443\u0440\u043a\u0430",
        "Lazurka"
    ],
    "wof:name":"Lazurka",
    "wof:placetype":"locality"
},
  "geometry": {"coordinates":[82.37389,51.08917],"type":"Point"}
}