{
  "type": "Feature",
  "properties": {
    "gn:admin1_code":"28.0",
    "gn:asciiname":"Alapikha",
    "gn:country_code":"RU",
    "gn:dem":156,
    "gn:feature_class":"P",
    "gn:feature_code":"PPL",
    "gn:name":"Alapikha",
    "gn:population":0,
    "gn:timezone":"Europe/Moscow",
    "iso:country":"RU",
    "name:fin_x_preferred":[
        "Alapiha"
    ],
    "name:nor_x_preferred":[
        "Alapikha"
    ],
    "name:rus_x_preferred":[
        "\u0410\u043b\u0430\u043f\u0438\u0445\u0430"
    ],
    "wof:name":"Alapikha",
    "wof:placetype":"locality"
},
  "geometry": {"coordinates":[31.31667,62.56667],"type":"Point"}
}