{
  "type": "Feature",
  "properties": {
    "gn:admin1_code":"90",
    "gn:asciiname":"Temnoye",
    "gn:country_code":"RU",
    "gn:dem":183,
    "gn:feature_class":"P",
    "gn:feature_code":"PPL",
    "gn:name":"T\u00ebmnoye",
    "gn:population":0,
    "gn:timezone":"Asia/Yekaterinburg",
    "iso:country":"RU",
    "name:che_x_preferred":[
        "\u0422\u0435\u043c\u043d\u0438"
    ],
    "name:chv_x_preferred":[
        "\u0422\u0435\u043c\u043d\u043e\u0435"
    ],
    "name:eng_x_preferred":[
        "T\u00ebmnoye"
    ],
    "name:nor_x_preferred":[
        "Temnoje"
    ],
    "name:rus_x_preferred":[
        "\u0422\u0435\u043c\u043d\u043e\u0435"
    ],
    "name:rus_x_variant":[
        "\u0422\u0451\u043c\u043d\u043e\u0435"
    ],
    "name:tat_x_preferred":[
        "\u0422\u0435\u043c\u043d\u043e\u0435"
    ],
    "wof:name":"Temnoye",
    "wof:placetype":"locality"
},
  "geometry": {"coordinates":[56.42037,56.46307],"type":"Point"}
}