{
  "type": "Feature",
  "properties": {
    "gn:admin1_code":"53",
    "gn:asciiname":"Kargan",
    "gn:cc2":"RU",
    "gn:country_code":"RU",
    "gn:dem":133,
    "gn:feature_class":"P",
    "gn:feature_code":"PPL",
    "gn:name":"Kargan",
    "gn:population":0,
    "gn:timezone":"Asia/Novosibirsk",
    "iso:country":"RU",
    "name:ceb_x_preferred":[
        "Kargan"
    ],
    "name:eng_x_preferred":[
        "Kargan"
    ],
    "name:nor_x_preferred":[
        "Kargan"
    ],
    "name:rus_x_preferred":[
        "\u041a\u0430\u0440\u0433\u0430\u043d"
    ],
    "name:swe_x_preferred":[
        "Kargan"
    ],
    "name:und_x_variant":[
        "Karganskoye"
    ],
    "wof:name":"Kargan",
    "wof:placetype":"locality"
},
  "geometry": {"coordinates":[80.04971999999999,55.3575],"type":"Point"}
}