{
  "type": "Feature",
  "properties": {
    "gn:admin1_code":"77",
    "gn:asciiname":"Smerdovo",
    "gn:country_code":"RU",
    "gn:dem":191,
    "gn:feature_class":"P",
    "gn:feature_code":"PPL",
    "gn:name":"Smerdovo",
    "gn:population":0,
    "gn:timezone":"Europe/Moscow",
    "iso:country":"RU",
    "name:rus_x_preferred":[
        "\u0421\u043c\u0435\u0440\u0434\u043e\u0432\u043e"
    ],
    "wof:name":"Smerdovo",
    "wof:placetype":"locality"
},
  "geometry": {"coordinates":[36.492,57.4988],"type":"Point"}
}