{
  "type": "Feature",
  "properties": {
    "gn:admin1_code":"42",
    "gn:asciiname":"Lizanovo",
    "gn:cc2":"RU",
    "gn:country_code":"RU",
    "gn:dem":113,
    "gn:feature_class":"P",
    "gn:feature_code":"PPL",
    "gn:name":"Lizanovo",
    "gn:population":0,
    "gn:timezone":"Europe/Moscow",
    "iso:country":"RU",
    "name:rus_x_preferred":[
        "\u041b\u0438\u0437\u0430\u043d\u043e\u0432\u043e"
    ],
    "name:und_x_variant":[
        "Lizanova",
        "Lizanovo"
    ],
    "wof:name":"Lizanovo",
    "wof:placetype":"locality"
},
  "geometry": {"coordinates":[34.22444,59.80416999999999],"type":"Point"}
}