{
  "type": "Feature",
  "properties": {
    "gn:admin1_code":"3",
    "gn:asciiname":"Katanda",
    "gn:cc2":"RU",
    "gn:country_code":"RU",
    "gn:dem":956,
    "gn:feature_class":"P",
    "gn:feature_code":"PPL",
    "gn:name":"Katanda",
    "gn:population":0,
    "gn:timezone":"Asia/Omsk",
    "iso:country":"RU",
    "name:che_x_preferred":[
        "\u041a\u0430\u0442\u0430\u043d\u0434\u0430"
    ],
    "name:eng_x_preferred":[
        "Katanda"
    ],
    "name:hye_x_preferred":[
        "\u053f\u0561\u057f\u0561\u0576\u0564\u0561"
    ],
    "name:nor_x_preferred":[
        "Katanda"
    ],
    "name:rus_x_preferred":[
        "\u041a\u0430\u0442\u0430\u043d\u0434\u0430"
    ],
    "name:tat_x_preferred":[
        "\u041a\u0430\u0442\u0430\u043d\u0434\u0430"
    ],
    "name:ukr_x_preferred":[
        "\u041a\u0430\u0442\u0430\u043d\u0434\u0430"
    ],
    "name:und_x_variant":[
        "Kotanda"
    ],
    "wof:name":"Katanda",
    "wof:placetype":"locality"
},
  "geometry": {"coordinates":[86.17702,50.16772],"type":"Point"}
}