{
  "type": "Feature",
  "properties": {
    "gn:admin1_code":"53",
    "gn:asciiname":"Maray",
    "gn:country_code":"RU",
    "gn:dem":183,
    "gn:feature_class":"P",
    "gn:feature_code":"PPL",
    "gn:name":"Maray",
    "gn:population":0,
    "gn:timezone":"Asia/Novosibirsk",
    "iso:country":"RU",
    "name:cat_x_preferred":[
        "Maray"
    ],
    "name:ceb_x_preferred":[
        "Maray"
    ],
    "name:deu_x_preferred":[
        "Maray"
    ],
    "name:eng_x_preferred":[
        "Maray"
    ],
    "name:eus_x_preferred":[
        "Maray"
    ],
    "name:fra_x_preferred":[
        "Maray"
    ],
    "name:hun_x_preferred":[
        "Maray"
    ],
    "name:ita_x_preferred":[
        "Maray"
    ],
    "name:lat_x_preferred":[
        "Maray"
    ],
    "name:mlg_x_preferred":[
        "Maray"
    ],
    "name:msa_x_preferred":[
        "Maray"
    ],
    "name:nld_x_preferred":[
        "Maray"
    ],
    "name:nor_x_preferred":[
        "Maraj"
    ],
    "name:oci_x_preferred":[
        "Maray"
    ],
    "name:pms_x_preferred":[
        "Maray"
    ],
    "name:pol_x_preferred":[
        "Maray"
    ],
    "name:por_x_preferred":[
        "Maray"
    ],
    "name:ron_x_preferred":[
        "Maray"
    ],
    "name:rus_x_preferred":[
        "\u041c\u0430\u0440\u0430\u0439"
    ],
    "name:slk_x_preferred":[
        "Maray"
    ],
    "name:spa_x_preferred":[
        "Maray"
    ],
    "name:swe_x_preferred":[
        "Maray"
    ],
    "name:ukr_x_preferred":[
        "\u041c\u0430\u0440\u0435"
    ],
    "name:und_x_variant":[
        "Marayskiy",
        "\u041c\u0430\u0440\u0430\u0439",
        "Maray"
    ],
    "name:uzb_x_preferred":[
        "Maray"
    ],
    "name:vie_x_preferred":[
        "Maray"
    ],
    "name:vol_x_preferred":[
        "Maray"
    ],
    "name:war_x_preferred":[
        "Maray"
    ],
    "name:zho_x_preferred":[
        "\u9a6c\u8d56"
    ],
    "wof:name":"Maray",
    "wof:placetype":"locality"
},
  "geometry": {"coordinates":[84.28416999999997,54.97889],"type":"Point"}
}