{
  "type": "Feature",
  "properties": {
    "gn:admin1_code":"53",
    "gn:asciiname":"Maray",
    "gn:country_code":"RU",
    "gn:dem":183,
    "gn:feature_class":"P",
    "gn:feature_code":"PPL",
    "gn:name":"Maray",
    "gn:population":0,
    "gn:timezone":"Asia/Novosibirsk",
    "iso:country":"RU",
    "name:eng_x_preferred":[
        "Maray"
    ],
    "name:nor_x_preferred":[
        "Maraj"
    ],
    "name:rus_x_preferred":[
        "\u041c\u0430\u0440\u0430\u0439"
    ],
    "name:und_x_variant":[
        "Marayskiy",
        "\u041c\u0430\u0440\u0430\u0439",
        "Maray"
    ],
    "wof:name":"Maray",
    "wof:placetype":"locality"
},
  "geometry": {"coordinates":[84.28416999999997,54.97889],"type":"Point"}
}