{
  "type": "Feature",
  "properties": {
    "gn:admin1_code":"60",
    "gn:asciiname":"Palukhnovo",
    "gn:country_code":"RU",
    "gn:dem":89,
    "gn:feature_class":"P",
    "gn:feature_code":"PPL",
    "gn:name":"Palukhnovo",
    "gn:population":0,
    "gn:timezone":"Europe/Moscow",
    "iso:country":"RU",
    "name:rus_x_preferred":[
        "\u041f\u0430\u043b\u0443\u0445\u043d\u043e\u0432\u043e"
    ],
    "wof:name":"Palukhnovo",
    "wof:placetype":"locality"
},
  "geometry": {"coordinates":[28.94613,56.94787],"type":"Point"}
}