{
  "type": "Feature",
  "properties": {
    "gn:admin1_code":"46",
    "gn:asciiname":"Shaly",
    "gn:country_code":"RU",
    "gn:dem":116,
    "gn:feature_class":"P",
    "gn:feature_code":"PPL",
    "gn:name":"Shaly",
    "gn:population":0,
    "gn:timezone":"Europe/Moscow",
    "iso:country":"RU",
    "name:eng_x_preferred":[
        "Shaly"
    ],
    "name:nor_x_preferred":[
        "Sjaly"
    ],
    "name:rus_x_preferred":[
        "\u0428\u0430\u043b\u044b"
    ],
    "name:und_x_variant":[
        "\u0428\u0430\u043b\u044b",
        "Shaly"
    ],
    "wof:name":"Shaly",
    "wof:placetype":"locality"
},
  "geometry": {"coordinates":[43.01685,54.38927],"type":"Point"}
}