{
  "type": "Feature",
  "properties": {
    "gn:admin1_code":"47",
    "gn:asciiname":"Gusevo",
    "gn:country_code":"RU",
    "gn:dem":153,
    "gn:feature_class":"P",
    "gn:feature_code":"PPL",
    "gn:name":"Gusevo",
    "gn:population":0,
    "gn:timezone":"Europe/Moscow",
    "iso:country":"RU",
    "name:nor_x_preferred":[
        "Gusevo"
    ],
    "name:rus_x_preferred":[
        "\u0413\u0443\u0441\u0435\u0432\u043e"
    ],
    "wof:name":"Gusevo",
    "wof:placetype":"locality"
},
  "geometry": {"coordinates":[35.83217,56.11066],"type":"Point"}
}