{
  "type": "Feature",
  "properties": {
    "gn:admin1_code":"25.0",
    "gn:asciiname":"Fominichi",
    "gn:country_code":"RU",
    "gn:dem":212,
    "gn:feature_class":"P",
    "gn:feature_code":"PPL",
    "gn:name":"Fominichi",
    "gn:population":0,
    "gn:timezone":"Europe/Moscow",
    "iso:country":"RU",
    "name:eng_x_preferred":[
        "Fominichi"
    ],
    "name:nor_x_preferred":[
        "Fominitsji"
    ],
    "name:rus_x_preferred":[
        "\u0424\u043e\u043c\u0438\u043d\u0438\u0447\u0438"
    ],
    "name:und_x_variant":[
        "\u0424\u043e\u043c\u0438\u043d\u0438\u0447\u0438",
        "Fominichi"
    ],
    "wof:name":"Fominichi",
    "wof:placetype":"locality"
},
  "geometry": {"coordinates":[34.68628,54.11505],"type":"Point"}
}