{
  "type": "Feature",
  "properties": {
    "gn:admin1_code":"11",
    "gn:asciiname":"Shara-Azarga",
    "gn:country_code":"RU",
    "gn:dem":1109,
    "gn:feature_class":"P",
    "gn:feature_code":"PPL",
    "gn:name":"Shara-Azarga",
    "gn:population":0,
    "gn:timezone":"Asia/Irkutsk",
    "iso:country":"RU",
    "name:eng_x_preferred":[
        "Shara-Azarga"
    ],
    "name:nor_x_preferred":[
        "Sjara-Azarga"
    ],
    "name:rus_x_preferred":[
        "\u0428\u0430\u0440\u0430-\u0410\u0437\u0430\u0440\u0433\u0430"
    ],
    "name:und_x_variant":[
        "Sharaazovga",
        "\u0428\u0430\u0440\u0430-\u0410\u0437\u0430\u0440\u0433\u0430",
        "Shara-Azarga"
    ],
    "wof:name":"Shara-Azarga",
    "wof:placetype":"locality"
},
  "geometry": {"coordinates":[103.04819999999999,50.4805],"type":"Point"}
}