{
  "type": "Feature",
  "properties": {
    "gn:admin1_code":"85",
    "gn:asciiname":"Yerga",
    "gn:country_code":"RU",
    "gn:dem":214,
    "gn:feature_class":"P",
    "gn:feature_code":"PPL",
    "gn:name":"Yerga",
    "gn:population":0,
    "gn:timezone":"Europe/Moscow",
    "iso:country":"RU",
    "name:eng_x_preferred":[
        "Yerga"
    ],
    "name:nor_x_preferred":[
        "Jerga"
    ],
    "name:rus_x_preferred":[
        "\u0415\u0440\u0433\u0430"
    ],
    "wof:name":"Yerga",
    "wof:placetype":"locality"
},
  "geometry": {"coordinates":[45.75831,61.1579],"type":"Point"}
}