{
  "type": "Feature",
  "properties": {
    "gn:admin1_code":"57.0",
    "gn:asciiname":"Chudnaya",
    "gn:country_code":"RU",
    "gn:dem":179,
    "gn:feature_class":"P",
    "gn:feature_code":"PPL",
    "gn:name":"Chudnaya",
    "gn:population":0,
    "gn:timezone":"Europe/Moscow",
    "iso:country":"RU",
    "name:rus_x_preferred":[
        "\u0427\u0443\u0434\u043d\u0430\u044f"
    ],
    "name:und_x_variant":[
        "\u0427\u0443\u0434\u043d\u0430\u044f"
    ],
    "wof:name":"Chudnaya",
    "wof:placetype":"locality"
},
  "geometry": {"coordinates":[42.57479,53.29315],"type":"Point"}
}