{
  "type": "Feature",
  "properties": {
    "gn:admin1_code":"77",
    "gn:asciiname":"Sadykovo",
    "gn:country_code":"RU",
    "gn:dem":165,
    "gn:feature_class":"P",
    "gn:feature_code":"PPL",
    "gn:name":"Sadykovo",
    "gn:population":0,
    "gn:timezone":"Europe/Moscow",
    "iso:country":"RU",
    "name:nor_x_preferred":[
        "Sadykovo"
    ],
    "name:rus_x_preferred":[
        "\u0421\u0430\u0434\u044b\u043a\u043e\u0432\u043e"
    ],
    "wof:name":"Sadykovo",
    "wof:placetype":"locality"
},
  "geometry": {"coordinates":[35.94313,56.7916],"type":"Point"}
}