{
  "type": "Feature",
  "properties": {
    "gn:admin1_code":"80.0",
    "gn:asciiname":"Passhur",
    "gn:country_code":"RU",
    "gn:dem":153,
    "gn:feature_class":"P",
    "gn:feature_code":"PPL",
    "gn:name":"Passhur",
    "gn:population":0,
    "gn:timezone":"Europe/Samara",
    "iso:country":"RU",
    "name:rus_x_preferred":[
        "\u041f\u0430\u0441\u0448\u0443\u0440"
    ],
    "wof:name":"Passhur",
    "wof:placetype":"locality"
},
  "geometry": {"coordinates":[52.2265,57.9825],"type":"Point"}
}