{
  "type": "Feature",
  "properties": {
    "gn:admin1_code":"54",
    "gn:asciiname":"Barsukovka",
    "gn:country_code":"RU",
    "gn:dem":112,
    "gn:feature_class":"P",
    "gn:feature_code":"PPL",
    "gn:name":"Barsukovka",
    "gn:population":0,
    "gn:timezone":"Asia/Omsk",
    "iso:country":"RU",
    "name:rus_x_preferred":[
        "\u0411\u0430\u0440\u0441\u0443\u043a\u043e\u0432\u043a\u0430"
    ],
    "wof:name":"Barsukovka",
    "wof:placetype":"locality"
},
  "geometry": {"coordinates":[72.74079999999999,55.2281],"type":"Point"}
}