{
  "type": "Feature",
  "properties": {
    "gn:admin1_code":"10",
    "gn:asciiname":"Stechna",
    "gn:country_code":"RU",
    "gn:dem":150,
    "gn:feature_class":"P",
    "gn:feature_code":"PPL",
    "gn:name":"Stechna",
    "gn:population":0,
    "gn:timezone":"Europe/Moscow",
    "iso:country":"RU",
    "name:rus_x_preferred":[
        "\u0421\u0442\u0435\u0447\u043d\u0430"
    ],
    "name:und_x_variant":[
        "Stechnya",
        "Stechna",
        "\u0421\u0442\u0435\u0447\u043d\u0430"
    ],
    "wof:name":"Stechna",
    "wof:placetype":"locality"
},
  "geometry": {"coordinates":[33.37908,52.58367],"type":"Point"}
}