{
  "type": "Feature",
  "properties": {
    "gn:admin1_code":"69",
    "gn:asciiname":"Sukhovily",
    "gn:country_code":"RU",
    "gn:dem":190,
    "gn:feature_class":"P",
    "gn:feature_code":"PPL",
    "gn:name":"Sukhovily",
    "gn:population":0,
    "gn:timezone":"Europe/Moscow",
    "iso:country":"RU",
    "name:rus_x_preferred":[
        "\u0421\u0443\u0445\u043e\u0432\u0438\u043b\u044b"
    ],
    "wof:name":"Sukhovily",
    "wof:placetype":"locality"
},
  "geometry": {"coordinates":[32.1131,54.2562],"type":"Point"}
}