{
  "type": "Feature",
  "properties": {
    "gn:admin1_code":"55",
    "gn:asciiname":"Pushkinskiy",
    "gn:country_code":"RU",
    "gn:dem":103,
    "gn:feature_class":"P",
    "gn:feature_code":"PPL",
    "gn:name":"Pushkinskiy",
    "gn:population":0,
    "gn:timezone":"Asia/Yekaterinburg",
    "iso:country":"RU",
    "name:eng_x_preferred":[
        "Pushkinskiy"
    ],
    "name:nor_x_preferred":[
        "Pusjkinskij"
    ],
    "name:rus_x_preferred":[
        "\u041f\u0443\u0448\u043a\u0438\u043d\u0441\u043a\u0438\u0439"
    ],
    "wof:name":"Pushkinskiy",
    "wof:placetype":"locality"
},
  "geometry": {"coordinates":[53.88333000000001,52.75],"type":"Point"}
}