{
  "type": "Feature",
  "properties": {
    "gn:admin1_code":"55",
    "gn:asciiname":"Vzgor'ye",
    "gn:country_code":"RU",
    "gn:dem":192,
    "gn:feature_class":"P",
    "gn:feature_code":"PPL",
    "gn:name":"Vzgor\u2019ye",
    "gn:population":0,
    "gn:timezone":"Asia/Yekaterinburg",
    "iso:country":"RU",
    "name:rus_x_preferred":[
        "\u0412\u0437\u0433\u043e\u0440\u044c\u0435"
    ],
    "name:und_x_variant":[
        "Vzgor\u2019ye"
    ],
    "wof:name":"Vzgor'ye",
    "wof:placetype":"locality"
},
  "geometry": {"coordinates":[55.5491,52.2177],"type":"Point"}
}