{
  "type": "Feature",
  "properties": {
    "gn:admin1_code":"33",
    "gn:asciiname":"Salkym-Chishma",
    "gn:country_code":"RU",
    "gn:dem":151,
    "gn:feature_class":"P",
    "gn:feature_code":"PPL",
    "gn:name":"Salkym-Chishma",
    "gn:population":0,
    "gn:timezone":"Europe/Kirov",
    "iso:country":"RU",
    "name:rus_x_preferred":[
        "\u0421\u0430\u043b\u043a\u044b\u043c-\u0427\u0438\u0448\u043c\u0430"
    ],
    "wof:name":"Salkym-Chishma",
    "wof:placetype":"locality"
},
  "geometry": {"coordinates":[50.6533,56.3799],"type":"Point"}
}