{
  "type": "Feature",
  "properties": {
    "gn:admin1_code":"63",
    "gn:asciiname":"Agday",
    "gn:country_code":"RU",
    "gn:dem":191,
    "gn:feature_class":"P",
    "gn:feature_code":"PPL",
    "gn:name":"Agday",
    "gn:population":0,
    "gn:timezone":"Asia/Vladivostok",
    "iso:country":"RU",
    "name:nor_x_preferred":[
        "Agdaj"
    ],
    "name:rus_x_preferred":[
        "\u0410\u0433\u0434\u0430\u0439"
    ],
    "wof:name":"Agday",
    "wof:placetype":"locality"
},
  "geometry": {"coordinates":[131.90360999999999,66.99861],"type":"Point"}
}