{
  "type": "Feature",
  "properties": {
    "gn:admin1_code":"19.0",
    "gn:asciiname":"Ganakhleba",
    "gn:country_code":"RU",
    "gn:dem":1171,
    "gn:feature_class":"P",
    "gn:feature_code":"PPL",
    "gn:name":"Ganakhleba",
    "gn:population":0,
    "gn:timezone":"Europe/Moscow",
    "iso:country":"RU",
    "name:rus_x_preferred":[
        "\u0413\u0430\u043d\u0430\u0445\u043b\u0435\u0431\u0430"
    ],
    "wof:name":"Ganakhleba",
    "wof:placetype":"locality"
},
  "geometry": {"coordinates":[44.6725,42.8225],"type":"Point"}
}