{
  "type": "Feature",
  "properties": {
    "gn:admin1_code":"77",
    "gn:asciiname":"Kstinovo",
    "gn:country_code":"RU",
    "gn:dem":122,
    "gn:feature_class":"P",
    "gn:feature_code":"PPL",
    "gn:name":"Kstinovo",
    "gn:population":0,
    "gn:timezone":"Europe/Moscow",
    "iso:country":"RU",
    "name:rus_x_preferred":[
        "\u041a\u0441\u0442\u0438\u043d\u043e\u0432\u043e"
    ],
    "name:und_x_variant":[
        "\u041a\u0441\u0442\u0438\u043d\u043e\u0432\u043e"
    ],
    "wof:name":"Kstinovo",
    "wof:placetype":"locality"
},
  "geometry": {"coordinates":[37.264,57.1292],"type":"Point"}
}