{
  "type": "Feature",
  "properties": {
    "gn:admin1_code":"76",
    "gn:asciiname":"Bogachevskiy",
    "gn:country_code":"RU",
    "gn:dem":185,
    "gn:feature_class":"P",
    "gn:feature_code":"PPL",
    "gn:name":"Bogachevskiy",
    "gn:population":0,
    "gn:timezone":"Europe/Moscow",
    "iso:country":"RU",
    "name:rus_x_preferred":[
        "\u0411\u043e\u0433\u0430\u0447\u0435\u0432\u0441\u043a\u0438\u0439"
    ],
    "name:und_x_variant":[
        "\u0411\u043e\u0433\u0430\u0447\u0435\u0432\u0441\u043a\u0438\u0439"
    ],
    "wof:name":"Bogachevskiy",
    "wof:placetype":"locality"
},
  "geometry": {"coordinates":[36.45316,53.62523],"type":"Point"}
}