{
  "type": "Feature",
  "properties": {
    "gn:admin1_code":"21",
    "gn:asciiname":"Shchipachevo",
    "gn:country_code":"RU",
    "gn:dem":124,
    "gn:feature_class":"P",
    "gn:feature_code":"PPL",
    "gn:name":"Shchipachevo",
    "gn:population":0,
    "gn:timezone":"Europe/Moscow",
    "iso:country":"RU",
    "name:rus_x_preferred":[
        "\u0429\u0438\u043f\u0430\u0447\u0435\u0432\u043e"
    ],
    "name:und_x_variant":[
        "Shchepachevo",
        "Shchipachevo"
    ],
    "wof:name":"Shchipachevo",
    "wof:placetype":"locality"
},
  "geometry": {"coordinates":[41.28163,57.09895],"type":"Point"}
}