{
  "type": "Feature",
  "properties": {
    "gn:admin1_code":"61.0",
    "gn:asciiname":"Frunze",
    "gn:country_code":"RU",
    "gn:dem":65,
    "gn:feature_class":"P",
    "gn:feature_code":"PPL",
    "gn:name":"Frunze",
    "gn:population":0,
    "gn:timezone":"Europe/Moscow",
    "iso:country":"RU",
    "name:eng_x_preferred":[
        "Frunze"
    ],
    "name:nor_x_preferred":[
        "Frunze"
    ],
    "name:rus_x_preferred":[
        "\u0424\u0440\u0443\u043d\u0437\u0435"
    ],
    "name:und_x_variant":[
        "\u0424\u0440\u0443\u043d\u0437\u0435",
        "Frunze"
    ],
    "wof:name":"Frunze",
    "wof:placetype":"locality"
},
  "geometry": {"coordinates":[43.7719,47.161],"type":"Point"}
}