{
  "type": "Feature",
  "properties": {
    "iso:country":"RU",
    "qs:name":"Rossiten",
    "qs:name_adm0":"Russia",
    "qs:name_adm1":"Kaliningrad Oblast",
    "qs:photos":237,
    "qs:photos_1k":48,
    "qs:photos_9k":1,
    "qs:photos_9r":4,
    "qs:photos_all":237,
    "qs:photos_sr":4,
    "qs:placetype":"Town",
    "qs:pop_sr":"0",
    "wof:name":"Rossiten",
    "wof:placetype":"locality"
},
  "geometry": {"coordinates":[20.85205,55.156904],"type":"Point"}
}