{
  "type": "Feature",
  "properties": {
    "gn:admin1_code":"16",
    "gn:asciiname":"Novoye Izambayevo",
    "gn:country_code":"RU",
    "gn:dem":127,
    "gn:feature_class":"P",
    "gn:feature_code":"PPL",
    "gn:name":"Novoye Izambayevo",
    "gn:population":0,
    "gn:timezone":"Europe/Moscow",
    "iso:country":"RU",
    "name:rus_x_preferred":[
        "\u041d\u043e\u0432\u043e\u0435 \u0418\u0437\u0430\u043c\u0431\u0430\u0435\u0432\u043e"
    ],
    "name:und_x_variant":[
        "Izambayevo",
        "Novoye Izambayevo",
        "\u041d\u043e\u0432\u043e\u0435 \u0418\u0437\u0430\u043c\u0431\u0430\u0435\u0432\u043e"
    ],
    "wof:name":"Novoye Izambayevo",
    "wof:placetype":"locality"
},
  "geometry": {"coordinates":[47.65387,55.15968],"type":"Point"}
}