{
  "type": "Feature",
  "properties": {
    "gn:admin1_code":"05",
    "gn:asciiname":"Bol'she-Omutnaya",
    "gn:country_code":"RU",
    "gn:dem":504,
    "gn:feature_class":"P",
    "gn:feature_code":"PPL",
    "gn:name":"Bol\u2019she-Omutnaya",
    "gn:population":0,
    "gn:timezone":"Asia/Yakutsk",
    "iso:country":"RU",
    "name:eng_x_preferred":[
        "Bol'she-Omutnaya"
    ],
    "name:nor_x_preferred":[
        "Bolsjaja Omutnaja"
    ],
    "name:rus_x_preferred":[
        "\u0411\u043e\u043b\u044c\u0448\u0430\u044f \u041e\u043c\u0443\u0442\u043d\u0430\u044f"
    ],
    "name:rus_x_variant":[
        "\u0411\u043e\u043b\u044c\u0448\u0435-\u041e\u043c\u0443\u0442\u043d\u0430\u044f"
    ],
    "name:und_x_variant":[
        "Bol\u2019shaya Omutnaya",
        "Bol\u2019she-Omutnaya",
        "\u0411\u043e\u043b\u044c\u0448\u0435-\u041e\u043c\u0443\u0442\u043d\u0430\u044f"
    ],
    "wof:name":"Bol'she-Omutnaya",
    "wof:placetype":"locality"
},
  "geometry": {"coordinates":[122.2655,54.02208],"type":"Point"}
}