{
  "type": "Feature",
  "properties": {
    "gn:admin1_code":"20",
    "gn:asciiname":"Zhemchugova",
    "gn:country_code":"RU",
    "gn:dem":332,
    "gn:feature_class":"P",
    "gn:feature_code":"PPL",
    "gn:name":"Zhemchugova",
    "gn:population":0,
    "gn:timezone":"Asia/Irkutsk",
    "iso:country":"RU",
    "name:rus_x_preferred":[
        "\u0416\u0435\u043c\u0447\u0443\u0433\u043e\u0432\u0430"
    ],
    "wof:name":"Zhemchugova",
    "wof:placetype":"locality"
},
  "geometry": {"coordinates":[105.85769999999999,56.0671],"type":"Point"}
}