{
  "type": "Feature",
  "properties": {
    "gn:admin1_code":"62",
    "gn:asciiname":"Yamskoy",
    "gn:country_code":"RU",
    "gn:dem":119,
    "gn:feature_class":"P",
    "gn:feature_code":"PPL",
    "gn:name":"Yamskoy",
    "gn:population":0,
    "gn:timezone":"Europe/Moscow",
    "iso:country":"RU",
    "name:rus_x_preferred":[
        "\u042f\u043c\u0441\u043a\u043e\u0439"
    ],
    "wof:name":"Yamskoy",
    "wof:placetype":"locality"
},
  "geometry": {"coordinates":[40.5193,54.223],"type":"Point"}
}