{
  "type": "Feature",
  "properties": {
    "gn:admin1_code":"85",
    "gn:asciiname":"Lyubavchikha",
    "gn:country_code":"RU",
    "gn:dem":112,
    "gn:feature_class":"P",
    "gn:feature_code":"PPL",
    "gn:name":"Lyubavchikha",
    "gn:population":0,
    "gn:timezone":"Europe/Moscow",
    "iso:country":"RU",
    "name:rus_x_preferred":[
        "\u041b\u044e\u0431\u0430\u0432\u0447\u0438\u0445\u0430"
    ],
    "name:und_x_variant":[
        "Lyubavchina",
        "Lyubavchikha"
    ],
    "wof:name":"Lyubavchikha",
    "wof:placetype":"locality"
},
  "geometry": {"coordinates":[42.6347,59.78872],"type":"Point"}
}