{
  "type": "Feature",
  "properties": {
    "gn:admin1_code":"6.0",
    "gn:asciiname":"Chetsa Malaya",
    "gn:country_code":"RU",
    "gn:dem":-9999,
    "gn:feature_class":"P",
    "gn:feature_code":"PPL",
    "gn:name":"Chetsa Malaya",
    "gn:population":0,
    "gn:timezone":"Europe/Moscow",
    "iso:country":"RU",
    "name:rus_x_preferred":[
        "\u0427\u0435\u0446\u0430 \u041c\u0430\u043b\u0430\u044f"
    ],
    "name:und_x_variant":[
        "\u0427\u0435\u0446\u0430 \u041c\u0430\u043b\u0430\u044f"
    ],
    "wof:name":"Chetsa Malaya",
    "wof:placetype":"locality"
},
  "geometry": {"coordinates":[44.05,66.01666999999999],"type":"Point"}
}