{
  "type": "Feature",
  "properties": {
    "gn:admin1_code":"76",
    "gn:asciiname":"Lyapunovka",
    "gn:country_code":"RU",
    "gn:dem":178,
    "gn:feature_class":"P",
    "gn:feature_code":"PPL",
    "gn:name":"Lyapunovka",
    "gn:population":0,
    "gn:timezone":"Europe/Moscow",
    "iso:country":"RU",
    "name:rus_x_preferred":[
        "\u041b\u044f\u043f\u0443\u043d\u043e\u0432\u043a\u0430"
    ],
    "wof:name":"Lyapunovka",
    "wof:placetype":"locality"
},
  "geometry": {"coordinates":[38.37111,53.58416999999999],"type":"Point"}
}