{
  "type": "Feature",
  "properties": {
    "gn:admin1_code":"90.0",
    "gn:asciiname":"Tarabayevo",
    "gn:country_code":"RU",
    "gn:dem":163,
    "gn:feature_class":"P",
    "gn:feature_code":"PPL",
    "gn:name":"Tarabayevo",
    "gn:population":0,
    "gn:timezone":"Asia/Yekaterinburg",
    "iso:country":"RU",
    "name:rus_x_preferred":[
        "\u0422\u0430\u0440\u0430\u0431\u0430\u0435\u0432\u043e"
    ],
    "wof:name":"Tarabayevo",
    "wof:placetype":"locality"
},
  "geometry": {"coordinates":[54.8591,58.8684],"type":"Point"}
}