{
  "type": "Feature",
  "properties": {
    "gn:admin1_code":"45",
    "gn:asciiname":"Kacheykino",
    "gn:country_code":"RU",
    "gn:dem":93,
    "gn:feature_class":"P",
    "gn:feature_code":"PPL",
    "gn:name":"Kacheykino",
    "gn:population":0,
    "gn:timezone":"Europe/Moscow",
    "iso:country":"RU",
    "name:rus_x_preferred":[
        "\u041a\u0430\u0447\u0435\u0439\u043a\u0438\u043d\u043e"
    ],
    "wof:name":"Kacheykino",
    "wof:placetype":"locality"
},
  "geometry": {"coordinates":[48.6258,55.9555],"type":"Point"}
}