{
  "type": "Feature",
  "properties": {
    "gn:admin1_code":"8.0",
    "gn:asciiname":"Bayki",
    "gn:country_code":"RU",
    "gn:dem":172,
    "gn:feature_class":"P",
    "gn:feature_code":"PPL",
    "gn:name":"Bayki",
    "gn:population":0,
    "gn:timezone":"Asia/Yekaterinburg",
    "iso:country":"RU",
    "name:eng_x_preferred":[
        "Bayki"
    ],
    "name:nor_x_preferred":[
        "Bajki"
    ],
    "name:rus_x_preferred":[
        "\u0411\u0430\u0439\u043a\u0438"
    ],
    "name:und_x_variant":[
        "Baiki",
        "\u0411\u0430\u0439\u043a\u0438",
        "Bayki"
    ],
    "wof:name":"Bayki",
    "wof:placetype":"locality"
},
  "geometry": {"coordinates":[56.80774,55.843],"type":"Point"}
}