{
  "type": "Feature",
  "properties": {
    "gn:admin1_code":"33",
    "gn:asciiname":"Khvoyskaya",
    "gn:country_code":"RU",
    "gn:dem":153,
    "gn:feature_class":"P",
    "gn:feature_code":"PPL",
    "gn:name":"Khvoyskaya",
    "gn:population":0,
    "gn:timezone":"Europe/Kirov",
    "iso:country":"RU",
    "name:rus_x_preferred":[
        "\u0425\u0432\u043e\u0439\u0441\u043a\u0430\u044f"
    ],
    "name:und_x_variant":[
        "\u0425\u0432\u043e\u0439\u0441\u043a\u0430\u044f"
    ],
    "wof:name":"Khvoyskaya",
    "wof:placetype":"locality"
},
  "geometry": {"coordinates":[47.88244,59.29135],"type":"Point"}
}