{
  "type": "Feature",
  "properties": {
    "gn:admin1_code":"33",
    "gn:asciiname":"Krotkiny",
    "gn:country_code":"RU",
    "gn:dem":164,
    "gn:feature_class":"P",
    "gn:feature_code":"PPL",
    "gn:name":"Krotkiny",
    "gn:population":0,
    "gn:timezone":"Europe/Kirov",
    "iso:country":"RU",
    "name:rus_x_preferred":[
        "\u041a\u0440\u043e\u0442\u043a\u0438\u043d\u044b"
    ],
    "name:und_x_variant":[
        "\u041a\u0440\u043e\u0442\u043a\u0438\u043d\u044b"
    ],
    "wof:name":"Krotkiny",
    "wof:placetype":"locality"
},
  "geometry": {"coordinates":[47.7418,59.1467],"type":"Point"}
}