{
  "type": "Feature",
  "properties": {
    "gn:admin1_code":"16",
    "gn:asciiname":"Syatra-Margi",
    "gn:country_code":"RU",
    "gn:dem":119,
    "gn:feature_class":"P",
    "gn:feature_code":"PPL",
    "gn:name":"Syatra-Margi",
    "gn:population":0,
    "gn:timezone":"Europe/Moscow",
    "iso:country":"RU",
    "name:rus_x_preferred":[
        "\u0421\u044f\u0442\u0440\u0430-\u041c\u0430\u0440\u0433\u0438"
    ],
    "name:und_x_variant":[
        "Syatra-Kasy",
        "Syatra-Margi"
    ],
    "wof:name":"Syatra-Margi",
    "wof:placetype":"locality"
},
  "geometry": {"coordinates":[47.16479,55.91447],"type":"Point"}
}