{
  "type": "Feature",
  "properties": {
    "gn:admin1_code":"52.0",
    "gn:asciiname":"Berezovets",
    "gn:country_code":"RU",
    "gn:dem":54,
    "gn:feature_class":"P",
    "gn:feature_code":"PPL",
    "gn:name":"Ber\u00ebzovets",
    "gn:population":0,
    "gn:timezone":"Europe/Moscow",
    "iso:country":"RU",
    "name:nor_x_preferred":[
        "Berjozovets"
    ],
    "name:rus_x_preferred":[
        "\u0411\u0435\u0440\u0451\u0437\u043e\u0432\u0435\u0446"
    ],
    "name:und_x_variant":[
        "Ber\u00ebzovets"
    ],
    "wof:name":"Berezovets",
    "wof:placetype":"locality"
},
  "geometry": {"coordinates":[31.85508,57.67381],"type":"Point"}
}