{
  "type": "Feature",
  "properties": {
    "gn:admin1_code":"4",
    "gn:asciiname":"Udinsk",
    "gn:country_code":"RU",
    "gn:dem":231,
    "gn:feature_class":"P",
    "gn:feature_code":"PPL",
    "gn:name":"Udinsk",
    "gn:population":0,
    "gn:timezone":"Asia/Barnaul",
    "iso:country":"RU",
    "name:eng_x_preferred":[
        "Udinskiy Kordon"
    ],
    "name:nor_x_preferred":[
        "Udinskij Kordon"
    ],
    "name:rus_x_preferred":[
        "\u0423\u0434\u0438\u043d\u0441\u043a\u0438\u0439 \u041a\u043e\u0440\u0434\u043e\u043d"
    ],
    "name:rus_x_variant":[
        "\u0423\u0434\u0438\u043d\u0441\u043a"
    ],
    "name:und_x_variant":[
        "Udinskiy Kardon",
        "Udinskiy",
        "Udinsk"
    ],
    "wof:name":"Udinsk",
    "wof:placetype":"locality"
},
  "geometry": {"coordinates":[86.07799999999997,53.7509],"type":"Point"}
}