{
  "type": "Feature",
  "properties": {
    "gn:admin1_code":"80",
    "gn:asciiname":"Vishur",
    "gn:country_code":"RU",
    "gn:dem":118,
    "gn:feature_class":"P",
    "gn:feature_code":"PPL",
    "gn:name":"Vishur",
    "gn:population":0,
    "gn:timezone":"Europe/Samara",
    "iso:country":"RU",
    "name:und_x_variant":[
        "Kobylino",
        "Vishchur",
        "Vishur"
    ],
    "wof:name":"Vishur",
    "wof:placetype":"locality"
},
  "geometry": {"coordinates":[52.81919,56.63944],"type":"Point"}
}