{
  "type": "Feature",
  "properties": {
    "gn:admin1_code":"57",
    "gn:asciiname":"Zavodskoy",
    "gn:country_code":"RU",
    "gn:dem":150,
    "gn:feature_class":"P",
    "gn:feature_code":"PPL",
    "gn:name":"Zavodskoy",
    "gn:population":0,
    "gn:timezone":"Europe/Moscow",
    "iso:country":"RU",
    "name:rus_x_preferred":[
        "\u0417\u0430\u0432\u043e\u0434\u0441\u043a\u043e\u0439"
    ],
    "wof:name":"Zavodskoy",
    "wof:placetype":"locality"
},
  "geometry": {"coordinates":[45.17836,53.48473000000001],"type":"Point"}
}