{
  "type": "Feature",
  "properties": {
    "gn:admin1_code":"76",
    "gn:asciiname":"Barykovka",
    "gn:country_code":"RU",
    "gn:dem":208,
    "gn:feature_class":"P",
    "gn:feature_code":"PPL",
    "gn:name":"Barykovka",
    "gn:population":0,
    "gn:timezone":"Europe/Moscow",
    "iso:country":"RU",
    "name:nor_x_preferred":[
        "Barykovka"
    ],
    "name:rus_x_preferred":[
        "\u0411\u0430\u0440\u044b\u043a\u043e\u0432\u043a\u0430"
    ],
    "wof:name":"Barykovka",
    "wof:placetype":"locality"
},
  "geometry": {"coordinates":[38.40616,53.68673],"type":"Point"}
}