{
  "type": "Feature",
  "properties": {
    "gn:admin1_code":"51",
    "gn:asciiname":"Muraikha",
    "gn:country_code":"RU",
    "gn:dem":119,
    "gn:feature_class":"P",
    "gn:feature_code":"PPL",
    "gn:name":"Muraikha",
    "gn:population":0,
    "gn:timezone":"Europe/Moscow",
    "iso:country":"RU",
    "name:rus_x_preferred":[
        "\u041c\u0443\u0440\u0430\u0438\u0445\u0430"
    ],
    "name:und_x_variant":[
        "\u041c\u0443\u0440\u0430\u0438\u0445\u0430"
    ],
    "wof:name":"Muraikha",
    "wof:placetype":"locality"
},
  "geometry": {"coordinates":[46.3944,57.7369],"type":"Point"}
}