{
  "type": "Feature",
  "properties": {
    "gn:admin1_code":"72",
    "gn:asciiname":"Morshan'-Lyadovka",
    "gn:country_code":"RU",
    "gn:dem":157,
    "gn:feature_class":"P",
    "gn:feature_code":"PPL",
    "gn:name":"Morshan\u2019-Lyadovka",
    "gn:population":0,
    "gn:timezone":"Europe/Volgograd",
    "iso:country":"RU",
    "name:rus_x_preferred":[
        "\u041c\u043e\u0440\u0448\u0430\u043d\u044c-\u041b\u044f\u0434\u043e\u0432\u043a\u0430"
    ],
    "name:und_x_variant":[
        "Lyadovka",
        "Morshan\u2019-Lyadovka"
    ],
    "wof:name":"Morshan'-Lyadovka",
    "wof:placetype":"locality"
},
  "geometry": {"coordinates":[42.83964,52.20372],"type":"Point"}
}