{
  "type": "Feature",
  "properties": {
    "gn:admin1_code":"88",
    "gn:asciiname":"Voskresenskoye",
    "gn:country_code":"RU",
    "gn:dem":131,
    "gn:feature_class":"P",
    "gn:feature_code":"PPL",
    "gn:name":"Voskresenskoye",
    "gn:population":0,
    "gn:timezone":"Europe/Moscow",
    "iso:country":"RU",
    "wof:name":"Voskresenskoye",
    "wof:placetype":"locality"
},
  "geometry": {"coordinates":[39.34963,58.85392],"type":"Point"}
}