{
  "type": "Feature",
  "properties": {
    "gn:admin1_code":"77",
    "gn:asciiname":"Chadovo",
    "gn:country_code":"RU",
    "gn:dem":167,
    "gn:feature_class":"P",
    "gn:feature_code":"PPL",
    "gn:name":"Chadovo",
    "gn:population":0,
    "gn:timezone":"Europe/Moscow",
    "iso:country":"RU",
    "name:nor_x_preferred":[
        "Tsjadovo"
    ],
    "name:rus_x_preferred":[
        "\u0427\u0430\u0434\u043e\u0432\u043e"
    ],
    "wof:name":"Chadovo",
    "wof:placetype":"locality"
},
  "geometry": {"coordinates":[35.1375,56.63868000000001],"type":"Point"}
}