{
  "type": "Feature",
  "properties": {
    "gn:admin1_code":"61",
    "gn:asciiname":"Kruglyakov",
    "gn:country_code":"RU",
    "gn:dem":36,
    "gn:feature_class":"P",
    "gn:feature_code":"PPL",
    "gn:name":"Kruglyakov",
    "gn:population":0,
    "gn:timezone":"Europe/Moscow",
    "iso:country":"RU",
    "name:rus_x_preferred":[
        "\u041a\u0440\u0443\u0433\u043b\u044f\u043a\u043e\u0432"
    ],
    "name:und_x_variant":[
        "\u041a\u0440\u0443\u0433\u043b\u044f\u043a\u043e\u0432"
    ],
    "wof:name":"Kruglyakov",
    "wof:placetype":"locality"
},
  "geometry": {"coordinates":[42.46944000000001,47.37806],"type":"Point"}
}