{
  "type": "Feature",
  "properties": {
    "gn:admin1_code":"77",
    "gn:asciiname":"Studenets",
    "gn:country_code":"RU",
    "gn:dem":221,
    "gn:feature_class":"P",
    "gn:feature_code":"PPL",
    "gn:name":"Studenets",
    "gn:population":0,
    "gn:timezone":"Europe/Moscow",
    "iso:country":"RU",
    "name:rus_x_preferred":[
        "\u0421\u0442\u0443\u0434\u0435\u043de\u0446"
    ],
    "name:und_x_variant":[
        "Studentsy",
        "Studenets"
    ],
    "wof:name":"Studenets",
    "wof:placetype":"locality"
},
  "geometry": {"coordinates":[32.86597,56.96601],"type":"Point"}
}