{
  "type": "Feature",
  "properties": {
    "gn:admin1_code":"90",
    "gn:asciiname":"Lomotino",
    "gn:country_code":"RU",
    "gn:dem":168,
    "gn:feature_class":"P",
    "gn:feature_code":"PPL",
    "gn:name":"Lomotino",
    "gn:population":0,
    "gn:timezone":"Asia/Yekaterinburg",
    "iso:country":"RU",
    "name:rus_x_preferred":[
        "\u041b\u043e\u043c\u043e\u0442\u0438\u043d\u043e"
    ],
    "wof:name":"Lomotino",
    "wof:placetype":"locality"
},
  "geometry": {"coordinates":[56.88800000000001,57.6948],"type":"Point"}
}