{
  "type": "Feature",
  "properties": {
    "gn:admin1_code":"17",
    "gn:admin2_code":"558024",
    "gn:asciiname":"Nizhneye Inkho",
    "gn:country_code":"RU",
    "gn:dem":572,
    "gn:feature_class":"P",
    "gn:feature_code":"PPL",
    "gn:name":"Nizhneye Inkho",
    "gn:population":0,
    "gn:timezone":"Europe/Moscow",
    "iso:country":"RU",
    "name:rus_x_preferred":[
        "\u041d\u0438\u0436\u043d\u0435\u0435 \u0418\u043d\u0445\u043e"
    ],
    "wof:name":"Nizhneye Inkho",
    "wof:placetype":"locality"
},
  "geometry": {"coordinates":[46.50642,42.70042],"type":"Point"}
}