{
  "type": "Feature",
  "properties": {
    "gn:admin1_code":"76",
    "gn:asciiname":"Pomogalovo",
    "gn:country_code":"RU",
    "gn:dem":159,
    "gn:feature_class":"P",
    "gn:feature_code":"PPL",
    "gn:name":"Pomogalovo",
    "gn:population":0,
    "gn:timezone":"Europe/Moscow",
    "iso:country":"RU",
    "name:rus_x_preferred":[
        "\u041f\u043e\u043c\u043e\u0433\u0430\u043b\u043e\u0432\u043e"
    ],
    "name:und_x_variant":[
        "\u041f\u043e\u043c\u043e\u0433\u0430\u043b\u043e\u0432\u043e"
    ],
    "wof:name":"Pomogalovo",
    "wof:placetype":"locality"
},
  "geometry": {"coordinates":[37.33597,54.2574],"type":"Point"}
}