{
  "type": "Feature",
  "properties": {
    "gn:admin1_code":"80.0",
    "gn:asciiname":"Artyk",
    "gn:country_code":"RU",
    "gn:dem":209,
    "gn:feature_class":"P",
    "gn:feature_code":"PPL",
    "gn:name":"Artyk",
    "gn:population":0,
    "gn:timezone":"Europe/Samara",
    "iso:country":"RU",
    "name:nor_x_preferred":[
        "Artyk"
    ],
    "name:rus_x_preferred":[
        "\u0410\u0440\u0442\u044b\u043a"
    ],
    "wof:name":"Artyk",
    "wof:placetype":"locality"
},
  "geometry": {"coordinates":[52.3602,57.7256],"type":"Point"}
}