{
  "type": "Feature",
  "properties": {
    "gn:admin1_code":"28",
    "gn:asciiname":"Pelkula",
    "gn:country_code":"RU",
    "gn:dem":138,
    "gn:feature_class":"P",
    "gn:feature_code":"PPL",
    "gn:name":"Pelkula",
    "gn:population":0,
    "gn:timezone":"Europe/Moscow",
    "iso:country":"RU",
    "name:fin_x_preferred":[
        "P\u00f6lkkyl\u00e4"
    ],
    "name:rus_x_preferred":[
        "\u041f\u0435\u043b\u043a\u0443\u043b\u0430"
    ],
    "name:und_x_variant":[
        "Sotsialisticheskiy Urozhay",
        "Pelkula"
    ],
    "wof:name":"Pelkula",
    "wof:placetype":"locality"
},
  "geometry": {"coordinates":[32.76519,63.67061999999999],"type":"Point"}
}