{
  "type": "Feature",
  "properties": {
    "gn:admin1_code":"69",
    "gn:asciiname":"Selyushki-Leonovo",
    "gn:country_code":"RU",
    "gn:dem":236,
    "gn:feature_class":"P",
    "gn:feature_code":"PPL",
    "gn:name":"Selyushki-Leonovo",
    "gn:population":0,
    "gn:timezone":"Europe/Moscow",
    "iso:country":"RU",
    "wof:name":"Selyushki-Leonovo",
    "wof:placetype":"locality"
},
  "geometry": {"coordinates":[33.58402,54.9755],"type":"Point"}
}