{
  "type": "Feature",
  "properties": {
    "gn:admin1_code":"17",
    "gn:asciiname":"Novaya Urada",
    "gn:country_code":"RU",
    "gn:dem":104,
    "gn:feature_class":"P",
    "gn:feature_code":"PPL",
    "gn:name":"Novaya Urada",
    "gn:population":0,
    "gn:timezone":"Europe/Moscow",
    "iso:country":"RU",
    "name:rus_x_preferred":[
        "\u041d\u043e\u0432\u0430\u044f \u0423\u0440\u0430\u0434\u0430"
    ],
    "wof:name":"Novaya Urada",
    "wof:placetype":"locality"
},
  "geometry": {"coordinates":[47.13751,43.08134],"type":"Point"}
}