{
  "type": "Feature",
  "properties": {
    "gn:admin1_code":"20",
    "gn:asciiname":"Vladimirovskiy",
    "gn:country_code":"RU",
    "gn:dem":510,
    "gn:feature_class":"P",
    "gn:feature_code":"PPL",
    "gn:name":"Vladimirovskiy",
    "gn:population":0,
    "gn:timezone":"Asia/Irkutsk",
    "iso:country":"RU",
    "wof:name":"Vladimirovskiy",
    "wof:placetype":"locality"
},
  "geometry": {"coordinates":[103.26667,52.23333],"type":"Point"}
}