{
  "type": "Feature",
  "properties": {
    "gn:admin1_code":"62",
    "gn:asciiname":"Podlipki",
    "gn:country_code":"RU",
    "gn:dem":117,
    "gn:feature_class":"P",
    "gn:feature_code":"PPL",
    "gn:name":"Podlipki",
    "gn:population":0,
    "gn:timezone":"Europe/Moscow",
    "iso:country":"RU",
    "name:rus_x_preferred":[
        "\u041f\u043e\u0434\u043b\u0438\u043f\u043a\u0438"
    ],
    "name:und_x_variant":[
        "\u041f\u043e\u0434\u043b\u0438\u043f\u043a\u0438"
    ],
    "wof:name":"Podlipki",
    "wof:placetype":"locality"
},
  "geometry": {"coordinates":[40.04791,55.14614],"type":"Point"}
}