{
  "type": "Feature",
  "properties": {
    "gn:admin1_code":"16",
    "gn:asciiname":"Pochinok-Bybyt'",
    "gn:country_code":"RU",
    "gn:dem":148,
    "gn:feature_class":"P",
    "gn:feature_code":"PPL",
    "gn:name":"Pochinok-Bybyt\u2019",
    "gn:population":0,
    "gn:timezone":"Europe/Moscow",
    "iso:country":"RU",
    "name:rus_x_preferred":[
        "\u041f\u043e\u0447\u0438\u043d\u043e\u043a-\u0411\u044b\u0431\u044b\u0442\u044c"
    ],
    "name:und_x_variant":[
        "Pachinok Bybyt\u2019",
        "Bobyt\u2019",
        "Bybyt\u2019",
        "Pochinok-Bybyt\u2019",
        "\u041f\u043e\u0447\u0438\u043d\u043e\u043a-\u0411\u044b\u0431\u044b\u0442\u044c"
    ],
    "wof:name":"Pochinok-Bybyt'",
    "wof:placetype":"locality"
},
  "geometry": {"coordinates":[47.62861,55.21833],"type":"Point"}
}