{
  "type": "Feature",
  "properties": {
    "gn:admin1_code":"8.0",
    "gn:asciiname":"Baynazarovo",
    "gn:country_code":"RU",
    "gn:dem":338,
    "gn:feature_class":"P",
    "gn:feature_code":"PPL",
    "gn:name":"Baynazarovo",
    "gn:population":0,
    "gn:timezone":"Asia/Yekaterinburg",
    "iso:country":"RU",
    "name:eng_x_preferred":[
        "Baynazarovo"
    ],
    "name:nor_x_preferred":[
        "Bajnazarovo"
    ],
    "name:rus_x_preferred":[
        "\u0411\u0430\u0439\u043d\u0430\u0437\u0430\u0440\u043e\u0432\u043e"
    ],
    "name:und_x_variant":[
        "Baynazarova",
        "\u0411\u0430\u0439\u043d\u0430\u0437\u0430\u0440\u043e\u0432\u043e",
        "Baynazarovo"
    ],
    "wof:name":"Baynazarovo",
    "wof:placetype":"locality"
},
  "geometry": {"coordinates":[57.5419,53.294],"type":"Point"}
}