{
  "type": "Feature",
  "properties": {
    "gn:admin1_code":"8.0",
    "gn:asciiname":"Baynazarovo",
    "gn:country_code":"RU",
    "gn:dem":338,
    "gn:feature_class":"P",
    "gn:feature_code":"PPL",
    "gn:name":"Baynazarovo",
    "gn:population":0,
    "gn:timezone":"Asia/Yekaterinburg",
    "iso:country":"RU",
    "name:bak_x_preferred":[
        "\u0411\u0430\u0439\u043d\u0430\u0437\u0430\u0440"
    ],
    "name:che_x_preferred":[
        "\u0411\u0430\u0439\u043d\u0430\u0437\u0430\u0440\u043e\u0432\u043e"
    ],
    "name:eng_x_preferred":[
        "Baynazarovo"
    ],
    "name:hye_x_preferred":[
        "\u0532\u0561\u0575\u0576\u0561\u0566\u0561\u0580\u0578\u057e\u0578"
    ],
    "name:kat_x_preferred":[
        "\u10d1\u10d0\u10d8\u10dc\u10d0\u10d6\u10d0\u10e0\u10dd\u10d5\u10dd"
    ],
    "name:kaz_x_preferred":[
        "\u0411\u0430\u0439\u043d\u0430\u0437\u0430\u0440"
    ],
    "name:nor_x_preferred":[
        "Bajnazarovo"
    ],
    "name:rus_x_preferred":[
        "\u0411\u0430\u0439\u043d\u0430\u0437\u0430\u0440\u043e\u0432\u043e"
    ],
    "name:tat_x_preferred":[
        "\u0411\u0430\u0439\u043d\u0430\u0437\u0430\u0440"
    ],
    "name:ukr_x_preferred":[
        "\u0411\u0430\u0439\u043d\u0430\u0437\u0430\u0440\u043e\u0432\u043e"
    ],
    "name:und_x_variant":[
        "Baynazarova",
        "\u0411\u0430\u0439\u043d\u0430\u0437\u0430\u0440\u043e\u0432\u043e",
        "Baynazarovo"
    ],
    "wof:name":"Baynazarovo",
    "wof:placetype":"locality"
},
  "geometry": {"coordinates":[57.5419,53.294],"type":"Point"}
}