{
  "type": "Feature",
  "properties": {
    "gn:admin1_code":"33",
    "gn:asciiname":"Maloye Saltayevo",
    "gn:country_code":"RU",
    "gn:dem":115,
    "gn:feature_class":"P",
    "gn:feature_code":"PPL",
    "gn:name":"Maloye Saltayevo",
    "gn:population":0,
    "gn:timezone":"Europe/Kirov",
    "iso:country":"RU",
    "name:rus_x_preferred":[
        "\u041c\u0430\u043b\u043e\u0435 \u0421\u0430\u043b\u0442\u0430\u0435\u0432\u043e"
    ],
    "wof:name":"Maloye Saltayevo",
    "wof:placetype":"locality"
},
  "geometry": {"coordinates":[47.1948,57.2272],"type":"Point"}
}