{
  "type": "Feature",
  "properties": {
    "gn:admin1_code":"20",
    "gn:asciiname":"Olonki",
    "gn:country_code":"RU",
    "gn:dem":422,
    "gn:feature_class":"P",
    "gn:feature_code":"PPL",
    "gn:name":"Olonki",
    "gn:population":0,
    "gn:timezone":"Asia/Irkutsk",
    "iso:country":"RU",
    "name:eng_x_preferred":[
        "Olonki"
    ],
    "name:nor_x_preferred":[
        "Olonki"
    ],
    "name:rus_x_preferred":[
        "\u041e\u043b\u043e\u043d\u043a\u0438"
    ],
    "wof:name":"Olonki",
    "wof:placetype":"locality"
},
  "geometry": {"coordinates":[103.70417,52.89861],"type":"Point"}
}