{
  "type": "Feature",
  "properties": {
    "gn:admin1_code":"33.0",
    "gn:asciiname":"Chirki",
    "gn:country_code":"RU",
    "gn:dem":152,
    "gn:feature_class":"P",
    "gn:feature_code":"PPL",
    "gn:name":"Chirki",
    "gn:population":0,
    "gn:timezone":"Europe/Kirov",
    "iso:country":"RU",
    "name:rus_x_preferred":[
        "\u0427\u0438\u0440\u043a\u0438"
    ],
    "wof:name":"Chirki",
    "wof:placetype":"locality"
},
  "geometry": {"coordinates":[49.57937,58.52111],"type":"Point"}
}