{
  "type": "Feature",
  "properties": {
    "gn:admin1_code":"10",
    "gn:asciiname":"Sakovo",
    "gn:country_code":"RU",
    "gn:dem":172,
    "gn:feature_class":"P",
    "gn:feature_code":"PPL",
    "gn:name":"Sakovo",
    "gn:population":0,
    "gn:timezone":"Europe/Moscow",
    "iso:country":"RU",
    "name:rus_x_preferred":[
        "\u0421\u0430\u043a\u043e\u0432\u043e"
    ],
    "name:und_x_variant":[
        "Sakova",
        "Sakovo",
        "\u0421\u0430\u043a\u043e\u0432\u043e"
    ],
    "wof:name":"Sakovo",
    "wof:placetype":"locality"
},
  "geometry": {"coordinates":[33.88386,53.66936],"type":"Point"}
}