{
  "type": "Feature",
  "properties": {
    "gn:admin1_code":"76.0",
    "gn:asciiname":"Barykovo",
    "gn:country_code":"RU",
    "gn:dem":217,
    "gn:feature_class":"P",
    "gn:feature_code":"PPL",
    "gn:name":"Barykovo",
    "gn:population":0,
    "gn:timezone":"Europe/Moscow",
    "iso:country":"RU",
    "name:rus_x_preferred":[
        "\u0411\u0430\u0440\u044b\u043a\u043e\u0432\u043e"
    ],
    "name:und_x_variant":[
        "Brykova",
        "Barykovo",
        "Borykovo",
        "Bar\u2019kovo"
    ],
    "wof:name":"Barykovo",
    "wof:placetype":"locality"
},
  "geometry": {"coordinates":[37.70371,54.09409],"type":"Point"}
}