{
  "type": "Feature",
  "properties": {
    "gn:admin1_code":"55",
    "gn:asciiname":"Gremuchiy",
    "gn:country_code":"RU",
    "gn:dem":168,
    "gn:feature_class":"P",
    "gn:feature_code":"PPL",
    "gn:name":"Gremuchiy",
    "gn:population":0,
    "gn:timezone":"Asia/Yekaterinburg",
    "iso:country":"RU",
    "name:rus_x_preferred":[
        "\u0413\u0440\u0435\u043c\u0443\u0447\u0438\u0439"
    ],
    "wof:name":"Gremuchiy",
    "wof:placetype":"locality"
},
  "geometry": {"coordinates":[52.628,52.7698],"type":"Point"}
}