{
  "type": "Feature",
  "properties": {
    "gn:admin1_code":"46.0",
    "gn:asciiname":"Bol'shoy Urkat",
    "gn:country_code":"RU",
    "gn:dem":127,
    "gn:feature_class":"P",
    "gn:feature_code":"PPL",
    "gn:name":"Bol\u2019shoy Urkat",
    "gn:population":0,
    "gn:timezone":"Europe/Moscow",
    "iso:country":"RU",
    "name:nor_x_preferred":[
        "Bolsjoj Urkat"
    ],
    "name:rus_x_preferred":[
        "\u0411\u043e\u043b\u044c\u0448\u043e\u0439 \u0423\u0440\u043a\u0430\u0442"
    ],
    "name:und_x_variant":[
        "Bol\u2019shoy Urkat"
    ],
    "wof:name":"Bol'shoy Urkat",
    "wof:placetype":"locality"
},
  "geometry": {"coordinates":[43.84671,54.68695],"type":"Point"}
}