{
  "type": "Feature",
  "properties": {
    "gn:admin1_code":"4",
    "gn:asciiname":"Ust'-Isha",
    "gn:country_code":"RU",
    "gn:dem":244,
    "gn:feature_class":"P",
    "gn:feature_code":"PPL",
    "gn:name":"Ust\u2019-Isha",
    "gn:population":1362,
    "gn:timezone":"Asia/Barnaul",
    "iso:country":"RU",
    "name:eng_x_preferred":[
        "Ust'-Isha"
    ],
    "name:nor_x_preferred":[
        "Ust-Isja"
    ],
    "name:rus_x_preferred":[
        "\u0423\u0441\u0442\u044c-\u0418\u0448\u0430"
    ],
    "name:und_x_variant":[
        "Ust\u2019-Isha"
    ],
    "wof:name":"Ust'-Isha",
    "wof:placetype":"locality",
    "wof:population":1362
},
  "geometry": {"coordinates":[85.96756999999999,52.18201],"type":"Point"}
}