{
  "type": "Feature",
  "properties": {
    "gn:admin1_code":"28",
    "gn:asciiname":"Kyulyaniyemi",
    "gn:cc2":"RU",
    "gn:country_code":"RU",
    "gn:dem":140,
    "gn:feature_class":"P",
    "gn:feature_code":"PPL",
    "gn:name":"Kyulyaniyemi",
    "gn:population":0,
    "gn:timezone":"Europe/Moscow",
    "iso:country":"RU",
    "name:und_x_variant":[
        "Kyl\u00e4niemi",
        "Kyulyaniyemi"
    ],
    "wof:name":"Kyulyaniyemi",
    "wof:placetype":"locality"
},
  "geometry": {"coordinates":[31.91667,65.18333],"type":"Point"}
}