{
  "type": "Feature",
  "properties": {
    "gn:admin1_code":"61.0",
    "gn:asciiname":"Nikolo-Berezovskiy",
    "gn:country_code":"RU",
    "gn:dem":82,
    "gn:feature_class":"P",
    "gn:feature_code":"PPL",
    "gn:name":"Nikolo-Berezovskiy",
    "gn:population":0,
    "gn:timezone":"Europe/Moscow",
    "iso:country":"RU",
    "wof:name":"Nikolo-Berezovskiy",
    "wof:placetype":"locality"
},
  "geometry": {"coordinates":[41.41861,48.68167],"type":"Point"}
}