{
  "type": "Feature",
  "properties": {
    "gn:admin1_code":"73",
    "gn:asciiname":"Meshcheryakovo",
    "gn:country_code":"RU",
    "gn:dem":78,
    "gn:feature_class":"P",
    "gn:feature_code":"PPL",
    "gn:name":"Meshcheryakovo",
    "gn:population":0,
    "gn:timezone":"Europe/Moscow",
    "iso:country":"RU",
    "name:nor_x_preferred":[
        "Mesjtsjerjakovo"
    ],
    "name:rus_x_preferred":[
        "\u041c\u0435\u0449\u0435\u0440\u044f\u043a\u043e\u0432\u043e"
    ],
    "name:und_x_variant":[
        "Meshcheryaki",
        "Meshcheryakovo"
    ],
    "wof:name":"Meshcheryakovo",
    "wof:placetype":"locality"
},
  "geometry": {"coordinates":[48.2796,54.94026],"type":"Point"}
}