{
  "type": "Feature",
  "properties": {
    "gn:admin1_code":"38.0",
    "gn:asciiname":"Blazma",
    "gn:country_code":"RU",
    "gn:dem":33,
    "gn:feature_class":"P",
    "gn:feature_code":"PPL",
    "gn:name":"Blazma",
    "gn:population":0,
    "gn:timezone":"Europe/Moscow",
    "iso:country":"RU",
    "name:rus_x_preferred":[
        "\u0411\u043b\u0430\u0437\u043c\u0430"
    ],
    "name:und_x_variant":[
        "\u0411\u043b\u0430\u0437\u043c\u0430"
    ],
    "wof:name":"Blazma",
    "wof:placetype":"locality"
},
  "geometry": {"coordinates":[38.85,46.46667],"type":"Point"}
}