{
  "type": "Feature",
  "properties": {
    "gn:admin1_code":"52",
    "gn:asciiname":"Zayulino",
    "gn:country_code":"RU",
    "gn:dem":158,
    "gn:feature_class":"P",
    "gn:feature_code":"PPL",
    "gn:name":"Zayulino",
    "gn:population":0,
    "gn:timezone":"Europe/Moscow",
    "iso:country":"RU",
    "name:rus_x_preferred":[
        "\u0417\u0430\u044e\u043b\u0438\u043d\u043e"
    ],
    "name:und_x_variant":[
        "\u0417\u0430\u044e\u043b\u0438\u043d\u043e"
    ],
    "wof:name":"Zayulino",
    "wof:placetype":"locality"
},
  "geometry": {"coordinates":[35.57359,58.60301],"type":"Point"}
}