{
  "type": "Feature",
  "properties": {
    "gn:admin1_code":"52",
    "gn:asciiname":"Travkovo",
    "gn:country_code":"RU",
    "gn:dem":159,
    "gn:feature_class":"P",
    "gn:feature_code":"PPL",
    "gn:name":"Travkovo",
    "gn:population":0,
    "gn:timezone":"Europe/Moscow",
    "iso:country":"RU",
    "name:eng_x_preferred":[
        "Travkovo"
    ],
    "name:nor_x_preferred":[
        "Travkovo"
    ],
    "name:rus_x_preferred":[
        "\u0422\u0440\u0430\u0432\u043a\u043e\u0432\u043e"
    ],
    "wof:name":"Travkovo",
    "wof:placetype":"locality"
},
  "geometry": {"coordinates":[33.68028,58.29889],"type":"Point"}
}