{
  "type": "Feature",
  "properties": {
    "gn:admin1_code":"41.0",
    "gn:asciiname":"Berezutskoye",
    "gn:country_code":"RU",
    "gn:dem":175,
    "gn:feature_class":"P",
    "gn:feature_code":"PPL",
    "gn:name":"Berezutskoye",
    "gn:population":0,
    "gn:timezone":"Europe/Moscow",
    "iso:country":"RU",
    "name:nor_x_preferred":[
        "Berezutskoje na Lomne"
    ],
    "name:rus_x_preferred":[
        "\u0411\u0435\u0440\u0435\u0437\u0443\u0446\u043a\u043e\u0435"
    ],
    "name:und_x_variant":[
        "Berezutskaya",
        "Berezutskoye",
        "Berezutskoye na Lomne"
    ],
    "wof:name":"Berezutskoye",
    "wof:placetype":"locality"
},
  "geometry": {"coordinates":[35.7424,51.7419],"type":"Point"}
}