{
  "type": "Feature",
  "properties": {
    "gn:admin1_code":"62.0",
    "gn:asciiname":"Chernyshovo",
    "gn:country_code":"RU",
    "gn:dem":125,
    "gn:feature_class":"P",
    "gn:feature_code":"PPL",
    "gn:name":"Chernyshovo",
    "gn:population":0,
    "gn:timezone":"Europe/Moscow",
    "iso:country":"RU",
    "name:rus_x_preferred":[
        "\u0427\u0435\u0440\u043d\u044b\u0448\u043e\u0432\u043e"
    ],
    "name:und_x_variant":[
        "Chernysh\u00ebvo",
        "Chernyshovo"
    ],
    "wof:name":"Chernyshovo",
    "wof:placetype":"locality"
},
  "geometry": {"coordinates":[41.24419,54.89768],"type":"Point"}
}