{
  "type": "Feature",
  "properties": {
    "gn:admin1_code":"21",
    "gn:asciiname":"Podvyaznovo",
    "gn:country_code":"RU",
    "gn:dem":139,
    "gn:feature_class":"P",
    "gn:feature_code":"PPL",
    "gn:name":"Podvyaznovo",
    "gn:population":0,
    "gn:timezone":"Europe/Moscow",
    "iso:country":"RU",
    "name:rus_x_preferred":[
        "\u041f\u043e\u0434\u0432\u044f\u0437\u043d\u043e\u0432\u043e"
    ],
    "wof:name":"Podvyaznovo",
    "wof:placetype":"locality"
},
  "geometry": {"coordinates":[40.58688,56.78182],"type":"Point"}
}