{
  "type": "Feature",
  "properties": {
    "gn:admin1_code":"20",
    "gn:asciiname":"Moiseyevka",
    "gn:country_code":"RU",
    "gn:dem":539,
    "gn:feature_class":"P",
    "gn:feature_code":"PPL",
    "gn:name":"Moiseyevka",
    "gn:population":0,
    "gn:timezone":"Asia/Irkutsk",
    "iso:country":"RU",
    "name:eng_x_preferred":[
        "Moiseyevka"
    ],
    "name:nor_x_preferred":[
        "Moisejevka"
    ],
    "name:rus_x_preferred":[
        "\u041c\u043e\u0438\u0441\u0435\u0435\u0432\u043a\u0430"
    ],
    "wof:name":"Moiseyevka",
    "wof:placetype":"locality"
},
  "geometry": {"coordinates":[102.0103,53.5237],"type":"Point"}
}