{
  "type": "Feature",
  "properties": {
    "gn:admin1_code":"76",
    "gn:asciiname":"Grigor'yevskoye",
    "gn:country_code":"RU",
    "gn:dem":129,
    "gn:feature_class":"P",
    "gn:feature_code":"PPL",
    "gn:name":"Grigor\u2019yevskoye",
    "gn:population":0,
    "gn:timezone":"Europe/Moscow",
    "iso:country":"RU",
    "name:rus_x_preferred":[
        "\u0413\u0440\u0438\u0433\u043e\u0440\u044c\u0435\u0432\u0441\u043a\u043e\u0435"
    ],
    "name:und_x_variant":[
        "Grigor\u2019yevskoye Pervoye",
        "Grigor\u2019yevskoye"
    ],
    "wof:name":"Grigor'yevskoye",
    "wof:placetype":"locality"
},
  "geometry": {"coordinates":[37.97437,54.82171],"type":"Point"}
}