{
  "type": "Feature",
  "properties": {
    "gn:admin1_code":"9.0",
    "gn:asciiname":"Lipyagi",
    "gn:country_code":"RU",
    "gn:dem":198,
    "gn:feature_class":"P",
    "gn:feature_code":"PPL",
    "gn:name":"Lipyagi",
    "gn:population":0,
    "gn:timezone":"Europe/Moscow",
    "iso:country":"RU",
    "name:rus_x_preferred":[
        "\u041b\u0438\u043f\u044f\u0433\u0438"
    ],
    "wof:name":"Lipyagi",
    "wof:placetype":"locality"
},
  "geometry": {"coordinates":[37.7435,51.3603],"type":"Point"}
}