{
  "type": "Feature",
  "properties": {
    "gn:admin1_code":"77",
    "gn:asciiname":"Poddubki",
    "gn:country_code":"RU",
    "gn:dem":195,
    "gn:feature_class":"P",
    "gn:feature_code":"PPL",
    "gn:name":"Poddubki",
    "gn:population":0,
    "gn:timezone":"Europe/Moscow",
    "iso:country":"RU",
    "name:nor_x_preferred":[
        "Poddubki"
    ],
    "name:rus_x_preferred":[
        "\u041f\u043e\u0434\u0434\u0443\u0431\u043a\u0438"
    ],
    "wof:name":"Poddubki",
    "wof:placetype":"locality"
},
  "geometry": {"coordinates":[35.90212000000001,56.63798000000001],"type":"Point"}
}