{
  "type": "Feature",
  "properties": {
    "gn:admin1_code":"12",
    "gn:asciiname":"Nikolayevskaya",
    "gn:country_code":"RU",
    "gn:dem":53,
    "gn:feature_class":"P",
    "gn:feature_code":"PPL",
    "gn:name":"Nikolayevskaya",
    "gn:population":0,
    "gn:timezone":"Europe/Moscow",
    "iso:country":"RU",
    "name:che_x_preferred":[
        "Salt-\u0120ala"
    ],
    "name:che_x_variant":[
        "Saltiyn-\u0120ala",
        "\u0421\u0430\u043b\u0442-\u0413\u0406\u0430\u043b\u0430",
        "\u0421\u0430\u043b\u0442\u0438\u0439\u043d-\u0413\u0406\u0430\u043b\u0430"
    ],
    "name:eng_x_preferred":[
        "Nikolayevskaya"
    ],
    "name:nor_x_preferred":[
        "Nikolajevskaja"
    ],
    "name:rus_x_preferred":[
        "\u041d\u0438\u043a\u043e\u043b\u0430\u0435\u0432\u0441\u043a\u0430\u044f"
    ],
    "name:und_x_variant":[
        "Nikolaevskaya",
        "Nikolaevskaja"
    ],
    "wof:name":"Nikolayevskaya",
    "wof:placetype":"locality"
},
  "geometry": {"coordinates":[45.77659,43.5307],"type":"Point"}
}