{
  "type": "Feature",
  "properties": {
    "gn:admin1_code":"60",
    "gn:asciiname":"Veret'ye-Kirovskoye",
    "gn:country_code":"RU",
    "gn:dem":106,
    "gn:feature_class":"P",
    "gn:feature_code":"PPL",
    "gn:name":"Veret\u2019y\u00eb-Kirovskoye",
    "gn:population":0,
    "gn:timezone":"Europe/Moscow",
    "iso:country":"RU",
    "name:eng_x_preferred":[
        "Veret'y\u00eb"
    ],
    "name:nor_x_preferred":[
        "Veretje"
    ],
    "name:rus_x_preferred":[
        "\u0412\u0435\u0440\u0435\u0442\u044c\u0435"
    ],
    "name:rus_x_variant":[
        "\u0412\u0435\u0440\u0435\u0442\u044c\u0451-\u041a\u0438\u0440\u043e\u0432\u0441\u043a\u043e\u0435"
    ],
    "name:und_x_variant":[
        "Veret\u2019y\u00eb",
        "Veret\u2019y\u00eb-Kirovskoye"
    ],
    "wof:name":"Veret'ye-Kirovskoye",
    "wof:placetype":"locality"
},
  "geometry": {"coordinates":[30.25827,56.90036],"type":"Point"}
}