{
  "type": "Feature",
  "properties": {
    "gn:admin1_code":"77.0",
    "gn:asciiname":"Chernyy Ruchey",
    "gn:cc2":"RU",
    "gn:country_code":"RU",
    "gn:dem":218,
    "gn:feature_class":"P",
    "gn:feature_code":"PPL",
    "gn:name":"Ch\u00ebrnyy Ruchey",
    "gn:population":0,
    "gn:timezone":"Europe/Moscow",
    "iso:country":"RU",
    "name:rus_x_preferred":[
        "\u0427\u0451\u0440\u043d\u044b\u0439 \u0420\u0443\u0447\u0435\u0439"
    ],
    "name:und_x_variant":[
        "Chernyy Ruche",
        "Ch\u00ebrnyy Ruchey",
        "\u0427\u0451\u0440\u043d\u044b\u0439 \u0420\u0443\u0447\u0435\u0439"
    ],
    "wof:name":"Chernyy Ruchey",
    "wof:placetype":"locality"
},
  "geometry": {"coordinates":[32.76083,55.69083000000001],"type":"Point"}
}