{
  "type": "Feature",
  "properties": {
    "gn:admin1_code":"77",
    "gn:asciiname":"Ignatovo Pervoye",
    "gn:country_code":"RU",
    "gn:dem":132,
    "gn:feature_class":"P",
    "gn:feature_code":"PPL",
    "gn:name":"Ignatovo Pervoye",
    "gn:population":0,
    "gn:timezone":"Europe/Moscow",
    "iso:country":"RU",
    "name:rus_x_preferred":[
        "\u0418\u0433\u043d\u0430\u0442\u043e\u0432\u043e \u041f\u0435\u0440\u0432\u043e\u0435"
    ],
    "name:und_x_variant":[
        "\u0418\u0433\u043d\u0430\u0442\u043e\u0432\u043e \u041f\u0435\u0440\u0432\u043e\u0435"
    ],
    "wof:name":"Ignatovo Pervoye",
    "wof:placetype":"locality"
},
  "geometry": {"coordinates":[37.6616,57.3141],"type":"Point"}
}