{
  "type": "Feature",
  "properties": {
    "gn:admin1_code":"71.0",
    "gn:asciiname":"Larina",
    "gn:country_code":"RU",
    "gn:dem":95,
    "gn:feature_class":"P",
    "gn:feature_code":"PPL",
    "gn:name":"Larina",
    "gn:population":0,
    "gn:timezone":"Asia/Yekaterinburg",
    "iso:country":"RU",
    "name:nld_x_preferred":[
        "Larina"
    ],
    "name:rus_x_preferred":[
        "\u041b\u0430\u0440\u0438\u043d\u0430"
    ],
    "wof:name":"Larina",
    "wof:placetype":"locality"
},
  "geometry": {"coordinates":[63.70139,57.55948000000001],"type":"Point"}
}