{
  "type": "Feature",
  "properties": {
    "gn:admin1_code":"10",
    "gn:asciiname":"Strovnya",
    "gn:country_code":"RU",
    "gn:dem":177,
    "gn:feature_class":"P",
    "gn:feature_code":"PPL",
    "gn:name":"Strovnya",
    "gn:population":0,
    "gn:timezone":"Europe/Moscow",
    "iso:country":"RU",
    "name:rus_x_preferred":[
        "\u0421\u0442\u0440\u043e\u0432\u043d\u044f"
    ],
    "wof:name":"Strovnya",
    "wof:placetype":"locality"
},
  "geometry": {"coordinates":[33.85504,53.79516],"type":"Point"}
}