{
  "type": "Feature",
  "properties": {
    "gn:admin1_code":"47",
    "gn:asciiname":"Kachabroro",
    "gn:country_code":"RU",
    "gn:dem":187,
    "gn:feature_class":"P",
    "gn:feature_code":"PPL",
    "gn:name":"Kachabroro",
    "gn:population":0,
    "gn:timezone":"Europe/Moscow",
    "iso:country":"RU",
    "name:rus_x_preferred":[
        "\u041a\u0430\u0447\u0430\u0431\u0440\u043e\u0440\u043e"
    ],
    "name:und_x_variant":[
        "\u041a\u0430\u0447\u0430\u0431\u0440\u043e\u0440\u043e"
    ],
    "wof:name":"Kachabroro",
    "wof:placetype":"locality"
},
  "geometry": {"coordinates":[36.93583,55.89194000000001],"type":"Point"}
}