{
  "type": "Feature",
  "properties": {
    "gn:admin1_code":"9",
    "gn:asciiname":"Makhotynka",
    "gn:country_code":"RU",
    "gn:dem":209,
    "gn:feature_class":"P",
    "gn:feature_code":"PPL",
    "gn:name":"Makhotynka",
    "gn:population":0,
    "gn:timezone":"Europe/Moscow",
    "iso:country":"RU",
    "name:rus_x_preferred":[
        "\u041c\u0430\u0445\u043e\u0442\u044b\u043d\u043a\u0430"
    ],
    "wof:name":"Makhotynka",
    "wof:placetype":"locality"
},
  "geometry": {"coordinates":[38.0217,50.6624],"type":"Point"}
}