{
  "type": "Feature",
  "properties": {
    "gn:admin1_code":"6",
    "gn:asciiname":"Pechishche",
    "gn:country_code":"RU",
    "gn:dem":26,
    "gn:feature_class":"P",
    "gn:feature_code":"PPL",
    "gn:name":"Pechishche",
    "gn:population":0,
    "gn:timezone":"Europe/Moscow",
    "iso:country":"RU",
    "name:eng_x_preferred":[
        "Pechishcha"
    ],
    "name:nor_x_preferred":[
        "Pegisjtsje"
    ],
    "name:rus_x_preferred":[
        "\u041f\u0435\u0433\u0438\u0449\u0435"
    ],
    "name:rus_x_variant":[
        "\u041f\u0435\u0447\u0438\u0449\u0435"
    ],
    "name:und_x_variant":[
        "Pechishcha"
    ],
    "wof:name":"Pechishche",
    "wof:placetype":"locality"
},
  "geometry": {"coordinates":[44.8565,65.4898],"type":"Point"}
}