{
  "type": "Feature",
  "properties": {
    "gn:admin1_code":"1",
    "gn:asciiname":"Yelenovskoye",
    "gn:country_code":"RU",
    "gn:dem":36,
    "gn:feature_class":"P",
    "gn:feature_code":"PPL",
    "gn:name":"Yelenovskoye",
    "gn:population":0,
    "gn:timezone":"Europe/Moscow",
    "iso:country":"RU",
    "name:rus_x_preferred":[
        "\u0415\u043b\u0435\u043d\u043e\u0432\u0441\u043a\u043e\u0435"
    ],
    "name:und_x_variant":[
        "\u0415\u043b\u0435\u043d\u043e\u0432\u0441\u043a\u043e\u0435"
    ],
    "wof:name":"Yelenovskoye",
    "wof:placetype":"locality"
},
  "geometry": {"coordinates":[39.67653,45.11633],"type":"Point"}
}