{
  "type": "Feature",
  "properties": {
    "gn:admin1_code":"86.0",
    "gn:asciiname":"Morozov",
    "gn:country_code":"RU",
    "gn:dem":98,
    "gn:feature_class":"P",
    "gn:feature_code":"PPL",
    "gn:name":"Morozov",
    "gn:population":0,
    "gn:timezone":"Europe/Moscow",
    "iso:country":"RU",
    "name:bel_x_preferred":[
        "\u041c\u0430\u0440\u043e\u0437\u0430\u045e"
    ],
    "name:bul_x_preferred":[
        "\u041c\u043e\u0440\u043e\u0437\u043e\u0432"
    ],
    "name:ces_x_preferred":[
        "Morozov"
    ],
    "name:deu_x_preferred":[
        "Morozov"
    ],
    "name:fin_x_preferred":[
        "Morozov"
    ],
    "name:fra_x_preferred":[
        "Morozov"
    ],
    "name:heb_x_preferred":[
        "\u05de\u05d5\u05e8\u05d5\u05d6\u05d5\u05d1"
    ],
    "name:hye_x_preferred":[
        "\u0544\u0578\u0580\u0578\u0566\u0578\u057e"
    ],
    "name:ita_x_preferred":[
        "Morozov"
    ],
    "name:jpn_x_preferred":[
        "\u30e2\u30ed\u30be\u30d5"
    ],
    "name:lav_x_preferred":[
        "Morozovs"
    ],
    "name:nld_x_preferred":[
        "Morozov"
    ],
    "name:rus_x_preferred":[
        "\u041c\u043e\u0440\u043e\u0437\u043e\u0432"
    ],
    "name:swe_x_preferred":[
        "Morozov"
    ],
    "name:tat_x_preferred":[
        "\u041c\u043e\u0440\u043e\u0437\u043e\u0432"
    ],
    "name:ukr_x_preferred":[
        "\u041c\u043e\u0440\u043e\u0437\u043e\u0432"
    ],
    "name:und_x_variant":[
        "Morozovo"
    ],
    "wof:name":"Morozov",
    "wof:placetype":"locality"
},
  "geometry": {"coordinates":[40.8136,50.4044],"type":"Point"}
}