{
  "type": "Feature",
  "properties": {
    "gn:admin1_code":"33",
    "gn:asciiname":"Lyapshiny",
    "gn:country_code":"RU",
    "gn:dem":148,
    "gn:feature_class":"P",
    "gn:feature_code":"PPL",
    "gn:name":"Lyapshiny",
    "gn:population":0,
    "gn:timezone":"Europe/Kirov",
    "iso:country":"RU",
    "name:rus_x_preferred":[
        "\u041b\u044f\u043f\u0448\u0438\u043d\u044b"
    ],
    "name:und_x_variant":[
        "\u041b\u044f\u043f\u0448\u0438\u043d\u044b"
    ],
    "wof:name":"Lyapshiny",
    "wof:placetype":"locality"
},
  "geometry": {"coordinates":[48.25269,58.9974],"type":"Point"}
}