{
  "type": "Feature",
  "properties": {
    "gn:admin1_code":"88",
    "gn:asciiname":"Milodino",
    "gn:country_code":"RU",
    "gn:dem":163,
    "gn:feature_class":"P",
    "gn:feature_code":"PPL",
    "gn:name":"Milodino",
    "gn:population":0,
    "gn:timezone":"Europe/Moscow",
    "iso:country":"RU",
    "name:rus_x_preferred":[
        "\u041c\u0438\u043b\u043e\u0434\u0438\u043d\u043e"
    ],
    "name:und_x_variant":[
        "\u041c\u0438\u043b\u043e\u0434\u0438\u043d\u043e"
    ],
    "wof:name":"Milodino",
    "wof:placetype":"locality"
},
  "geometry": {"coordinates":[38.4917,57.3397],"type":"Point"}
}