{
  "type": "Feature",
  "properties": {
    "gn:admin1_code":"38",
    "gn:asciiname":"Udobno-Pokrovskiy",
    "gn:cc2":"RU",
    "gn:country_code":"RU",
    "gn:dem":678,
    "gn:feature_class":"P",
    "gn:feature_code":"PPL",
    "gn:name":"Udobno-Pokrovskiy",
    "gn:population":0,
    "gn:timezone":"Europe/Moscow",
    "iso:country":"RU",
    "name:und_x_variant":[
        "Udobno-Polrovskiy"
    ],
    "wof:name":"Udobno-Pokrovskiy",
    "wof:placetype":"locality"
},
  "geometry": {"coordinates":[41.67667,44.31556],"type":"Point"}
}