{
  "type": "Feature",
  "properties": {
    "gn:admin1_code":"80",
    "gn:asciiname":"Unur-Kiyasovo",
    "gn:country_code":"RU",
    "gn:dem":103,
    "gn:feature_class":"P",
    "gn:feature_code":"PPL",
    "gn:name":"Unur-Kiyasovo",
    "gn:population":0,
    "gn:timezone":"Europe/Samara",
    "iso:country":"RU",
    "wof:name":"Unur-Kiyasovo",
    "wof:placetype":"locality"
},
  "geometry": {"coordinates":[53.01218000000001,56.26915],"type":"Point"}
}