{
  "type": "Feature",
  "properties": {
    "gn:admin1_code":"85",
    "gn:asciiname":"Kresttsy",
    "gn:country_code":"RU",
    "gn:dem":164,
    "gn:feature_class":"P",
    "gn:feature_code":"PPL",
    "gn:name":"Kresttsy",
    "gn:population":0,
    "gn:timezone":"Europe/Moscow",
    "iso:country":"RU",
    "name:rus_x_preferred":[
        "\u041a\u0440\u0435\u0441\u0442\u0446\u044b"
    ],
    "wof:name":"Kresttsy",
    "wof:placetype":"locality"
},
  "geometry": {"coordinates":[36.24852,58.55174],"type":"Point"}
}