{
  "type": "Feature",
  "properties": {
    "gn:admin1_code":"91",
    "gn:asciiname":"Shergul'",
    "gn:country_code":"RU",
    "gn:dem":318,
    "gn:feature_class":"P",
    "gn:feature_code":"PPL",
    "gn:name":"Shergul\u2019",
    "gn:population":0,
    "gn:timezone":"Asia/Krasnoyarsk",
    "iso:country":"RU",
    "name:rus_x_preferred":[
        "\u0428\u0435\u0440\u0433\u0443\u043b\u044c"
    ],
    "name:und_x_variant":[
        "Shergul\u2019"
    ],
    "wof:name":"Shergul'",
    "wof:placetype":"locality"
},
  "geometry": {"coordinates":[92.40000000000001,56.41667],"type":"Point"}
}