{
  "type": "Feature",
  "properties": {
    "gn:country":"RU",
    "gn:fcode":"PPL",
    "gn:population":574,
    "iso:country":"RU",
    "name:bel_x_preferred":[
        "\u041d\u0456\u043a\u043e\u043b\u044c\u0441\u043a\u0456"
    ],
    "name:ceb_x_preferred":[
        "\u041d\u0438\u043a\u043e\u043b\u044c\u0441\u043a\u0438\u0439"
    ],
    "name:deu_x_preferred":[
        "Nikolski"
    ],
    "name:eng_x_preferred":[
        "Nikol'skoye"
    ],
    "name:epo_x_preferred":[
        "Nikoljskoje"
    ],
    "name:fra_x_preferred":[
        "Nikolski"
    ],
    "name:hye_x_preferred":[
        "\u0546\u056b\u056f\u0578\u056c\u057d\u056f\u056b"
    ],
    "name:ita_x_preferred":[
        "Nikol'skij"
    ],
    "name:nld_x_preferred":[
        "Nikolski"
    ],
    "name:nor_x_preferred":[
        "Nikolskoje"
    ],
    "name:rus_x_preferred":[
        "\u041d\u0438\u043a\u043e\u043b\u044c\u0441\u043a\u043e\u0435"
    ],
    "name:rus_x_variant":[
        "\u041d\u0438\u043a\u043e\u043b\u044c\u0441\u043a\u0438\u0439"
    ],
    "name:sco_x_preferred":[
        "Nikolsky"
    ],
    "name:ukr_x_preferred":[
        "\u041d\u0456\u043a\u043e\u043b\u044c\u0441\u044c\u043a\u0438\u0439"
    ],
    "qs:name":"Nikol'skoye",
    "qs:name_adm0":"Russia",
    "qs:name_adm1":"Sverdlovsk Oblast",
    "qs:photos_9r":0,
    "qs:photos_sr":0,
    "qs:placetype":"Town",
    "qs:pop_sr":"2",
    "wd:wordcount":259,
    "wof:name":"Nikol'skoye",
    "wof:placetype":"locality",
    "wof:population":574
},
  "geometry": {"coordinates":[62.9426,56.8458],"type":"Point"}
}