{
  "type": "Feature",
  "properties": {
    "gn:country":"RU",
    "gn:fcode":"PPL",
    "gn:pop":574,
    "iso:country":"RU",
    "name:eng_x_preferred":[
        "Nikol'skoye"
    ],
    "name:epo_x_preferred":[
        "Nikoljskoje"
    ],
    "name:nor_x_preferred":[
        "Nikolskoje"
    ],
    "name:rus_x_preferred":[
        "\u041d\u0438\u043a\u043e\u043b\u044c\u0441\u043a\u043e\u0435"
    ],
    "name:unk_x_variant":[
        "\u041d\u0438\u043a\u043e\u043b\u044c\u0441\u043a\u043e\u0435"
    ],
    "qs:name":"Nikol'skoye",
    "qs:name_adm0":"Russia",
    "qs:name_adm1":"Sverdlovsk Oblast",
    "qs:photos_9r":0,
    "qs:photos_sr":0,
    "qs:placetype":"Town",
    "qs:pop_sr":"2",
    "wd:wordcount":259,
    "wof:name":"Nikol'skoye",
    "wof:placetype":"locality",
    "wof:population":574
},
  "geometry": {"coordinates":[62.9426,56.8458],"type":"Point"}
}