{
  "type": "Feature",
  "properties": {
    "gn:admin1_code":"85.0",
    "gn:asciiname":"Artyushino",
    "gn:country_code":"RU",
    "gn:dem":142,
    "gn:feature_class":"P",
    "gn:feature_code":"PPL",
    "gn:name":"Artyushino",
    "gn:population":0,
    "gn:timezone":"Europe/Moscow",
    "iso:country":"RU",
    "name:eng_x_preferred":[
        "Artyushino"
    ],
    "name:nor_x_preferred":[
        "Artjusjino"
    ],
    "name:rus_x_preferred":[
        "\u0410\u0440\u0442\u044e\u0448\u0438\u043d\u043e"
    ],
    "wof:name":"Artyushino",
    "wof:placetype":"locality"
},
  "geometry": {"coordinates":[37.3388,60.0002],"type":"Point"}
}