{
  "type": "Feature",
  "properties": {
    "gn:admin1_code":"76.0",
    "gn:asciiname":"Domnino",
    "gn:country_code":"RU",
    "gn:dem":215,
    "gn:feature_class":"P",
    "gn:feature_code":"PPL",
    "gn:name":"Domnino",
    "gn:population":0,
    "gn:timezone":"Europe/Moscow",
    "iso:country":"RU",
    "name:rus_x_preferred":[
        "\u0414\u043e\u043c\u043d\u0438\u043d\u043e"
    ],
    "wof:name":"Domnino",
    "wof:placetype":"locality"
},
  "geometry": {"coordinates":[37.47523,54.66893],"type":"Point"}
}