{
  "type": "Feature",
  "properties": {
    "gn:admin1_code":"83",
    "gn:asciiname":"Yermonino",
    "gn:country_code":"RU",
    "gn:dem":126,
    "gn:feature_class":"P",
    "gn:feature_code":"PPL",
    "gn:name":"Yermonino",
    "gn:population":0,
    "gn:timezone":"Europe/Moscow",
    "iso:country":"RU",
    "name:rus_x_preferred":[
        "\u0415\u0440\u043c\u043e\u043d\u0438\u043d\u043e"
    ],
    "wof:name":"Yermonino",
    "wof:placetype":"locality"
},
  "geometry": {"coordinates":[39.96553,56.14908000000001],"type":"Point"}
}