{
  "type": "Feature",
  "properties": {
    "gn:admin1_code":"91",
    "gn:asciiname":"Kurtak",
    "gn:country_code":"RU",
    "gn:dem":306,
    "gn:feature_class":"P",
    "gn:feature_code":"PPL",
    "gn:name":"Kurtak",
    "gn:population":0,
    "gn:timezone":"Asia/Krasnoyarsk",
    "iso:country":"RU",
    "name:eng_x_preferred":[
        "Kurtak"
    ],
    "name:nor_x_preferred":[
        "Kurtak"
    ],
    "name:rus_x_preferred":[
        "\u041a\u0443\u0440\u0442\u0430\u043a"
    ],
    "wof:name":"Kurtak",
    "wof:placetype":"locality"
},
  "geometry": {"coordinates":[91.53556,55.14778],"type":"Point"}
}