{
  "type": "Feature",
  "properties": {
    "gn:admin1_code":"77",
    "gn:asciiname":"Lobozniki",
    "gn:country_code":"RU",
    "gn:dem":170,
    "gn:feature_class":"P",
    "gn:feature_code":"PPL",
    "gn:name":"Lobozniki",
    "gn:population":0,
    "gn:timezone":"Europe/Moscow",
    "iso:country":"RU",
    "name:rus_x_preferred":[
        "\u041b\u043e\u0431\u043e\u0437\u043d\u0438\u043a\u0438"
    ],
    "wof:name":"Lobozniki",
    "wof:placetype":"locality"
},
  "geometry": {"coordinates":[37.1147,58.3767],"type":"Point"}
}