{
  "type": "Feature",
  "properties": {
    "gn:admin1_code":"27.0",
    "gn:asciiname":"Madniskhevi",
    "gn:country_code":"RU",
    "gn:dem":1388,
    "gn:feature_class":"P",
    "gn:feature_code":"PPL",
    "gn:name":"Madniskhevi",
    "gn:population":0,
    "gn:timezone":"Europe/Moscow",
    "iso:country":"RU",
    "wof:name":"Madniskhevi",
    "wof:placetype":"locality"
},
  "geometry": {"coordinates":[42.08056,43.44917],"type":"Point"}
}