{
  "type": "Feature",
  "properties": {
    "gn:admin1_code":"61",
    "gn:asciiname":"Vlasovo-Burtovka",
    "gn:country_code":"RU",
    "gn:dem":91,
    "gn:feature_class":"P",
    "gn:feature_code":"PPL",
    "gn:name":"Vlasovo-Burtovka",
    "gn:population":0,
    "gn:timezone":"Europe/Moscow",
    "iso:country":"RU",
    "name:rus_x_preferred":[
        "\u0412\u043b\u0430\u0441\u043e\u0432\u043e-\u0411\u0443\u0440\u0442\u043e\u0432\u043a\u0430"
    ],
    "name:und_x_variant":[
        "Vlasovo-Burtovskiy",
        "Vlasovo-Burtovka"
    ],
    "wof:name":"Vlasovo-Burtovka",
    "wof:placetype":"locality"
},
  "geometry": {"coordinates":[39.33729,47.80989],"type":"Point"}
}