{
  "type": "Feature",
  "properties": {
    "gn:admin1_code":"86",
    "gn:asciiname":"Neskuchnyy",
    "gn:country_code":"RU",
    "gn:dem":92,
    "gn:feature_class":"P",
    "gn:feature_code":"PPL",
    "gn:name":"Neskuchnyy",
    "gn:population":0,
    "gn:timezone":"Europe/Moscow",
    "iso:country":"RU",
    "name:rus_x_preferred":[
        "\u041d\u0435\u0441\u043a\u0443\u0447\u043d\u044b\u0439"
    ],
    "name:und_x_variant":[
        "Derevnya Neskuchnaya",
        "Neskuchny",
        "Neskuchnyy"
    ],
    "wof:name":"Neskuchnyy",
    "wof:placetype":"locality"
},
  "geometry": {"coordinates":[39.78008,51.13759],"type":"Point"}
}