{
  "type": "Feature",
  "properties": {
    "gn:admin1_code":"41",
    "gn:asciiname":"Zakharkovo",
    "gn:country_code":"RU",
    "gn:dem":172,
    "gn:feature_class":"P",
    "gn:feature_code":"PPL",
    "gn:name":"Zakharkovo",
    "gn:population":0,
    "gn:timezone":"Europe/Moscow",
    "iso:country":"RU",
    "name:rus_x_preferred":[
        "\u0417\u0430\u0445\u0430\u0440\u043a\u043e\u0432\u043e"
    ],
    "wof:name":"Zakharkovo",
    "wof:placetype":"locality"
},
  "geometry": {"coordinates":[35.3611,51.8069],"type":"Point"}
}