{
  "type": "Feature",
  "properties": {
    "gn:admin1_code":"60",
    "gn:asciiname":"Vorotovo",
    "gn:country_code":"RU",
    "gn:dem":214,
    "gn:feature_class":"P",
    "gn:feature_code":"PPL",
    "gn:name":"Vorotovo",
    "gn:population":0,
    "gn:timezone":"Europe/Moscow",
    "iso:country":"RU",
    "name:rus_x_preferred":[
        "\u0412\u043e\u0440\u043e\u0442\u043e\u0432\u043e"
    ],
    "name:und_x_variant":[
        "\u0412\u043e\u0440\u043e\u0442\u043e\u0432\u043e"
    ],
    "wof:name":"Vorotovo",
    "wof:placetype":"locality"
},
  "geometry": {"coordinates":[29.4384,56.6887],"type":"Point"}
}