{
  "type": "Feature",
  "properties": {
    "gn:admin1_code":"40",
    "gn:asciiname":"Shelepovo",
    "gn:country_code":"RU",
    "gn:dem":135,
    "gn:feature_class":"P",
    "gn:feature_code":"PPL",
    "gn:name":"Shel\u00ebpovo",
    "gn:population":0,
    "gn:timezone":"Asia/Yekaterinburg",
    "iso:country":"RU",
    "name:eng_x_preferred":[
        "Shel\u00ebpovo"
    ],
    "name:nor_x_preferred":[
        "Sjelepovo"
    ],
    "name:rus_x_preferred":[
        "\u0428\u0435\u043b\u0435\u043f\u043e\u0432\u043e"
    ],
    "name:rus_x_variant":[
        "\u0428\u0435\u043b\u0451\u043f\u043e\u0432\u043e"
    ],
    "name:und_x_variant":[
        "Shel\u00ebpovo",
        "\u0428\u0435\u043b\u0451\u043f\u043e\u0432\u043e"
    ],
    "wof:name":"Shelepovo",
    "wof:placetype":"locality"
},
  "geometry": {"coordinates":[67.30083,55.70944],"type":"Point"}
}