{
  "type": "Feature",
  "properties": {
    "gn:admin1_code":"65.0",
    "gn:asciiname":"Bratishki",
    "gn:country_code":"RU",
    "gn:dem":30,
    "gn:feature_class":"P",
    "gn:feature_code":"PPL",
    "gn:name":"Bratishki",
    "gn:population":0,
    "gn:timezone":"Europe/Samara",
    "iso:country":"RU",
    "name:rus_x_preferred":[
        "\u0411\u0440\u0430\u0442\u0438\u0448\u043a\u0438"
    ],
    "name:und_x_variant":[
        "\u0411\u0440\u0430\u0442\u0438\u0448\u043a\u0438"
    ],
    "wof:name":"Bratishki",
    "wof:placetype":"locality"
},
  "geometry": {"coordinates":[48.96667,53.18333000000001],"type":"Point"}
}