{
  "type": "Feature",
  "properties": {
    "gn:admin1_code":"84",
    "gn:asciiname":"Shevyrev",
    "gn:cc2":"RU",
    "gn:country_code":"RU",
    "gn:dem":160,
    "gn:feature_class":"P",
    "gn:feature_code":"PPL",
    "gn:name":"Shevyr\u00ebv",
    "gn:population":0,
    "gn:timezone":"Europe/Volgograd",
    "iso:country":"RU",
    "name:rus_x_preferred":[
        "\u0428\u0435\u0432\u044b\u0440\u0451\u0432"
    ],
    "name:und_x_variant":[
        "Khlatkin",
        "Shevyr\u00ebv"
    ],
    "wof:name":"Shevyrev",
    "wof:placetype":"locality"
},
  "geometry": {"coordinates":[43.38333,49.26667],"type":"Point"}
}