{
  "type": "Feature",
  "properties": {
    "gn:admin1_code":"46",
    "gn:asciiname":"Malyye Remezenki",
    "gn:country_code":"RU",
    "gn:dem":217,
    "gn:feature_class":"P",
    "gn:feature_code":"PPL",
    "gn:name":"Malyye Remez\u00ebnki",
    "gn:population":0,
    "gn:timezone":"Europe/Moscow",
    "iso:country":"RU",
    "name:rus_x_preferred":[
        "\u041c\u0430\u043b\u044b\u0435 \u0420\u0435\u043c\u0435\u0437\u0451\u043d\u043a\u0438"
    ],
    "name:und_x_variant":[
        "Malyye Remez\u00ebnki"
    ],
    "wof:name":"Malyye Remezenki",
    "wof:placetype":"locality"
},
  "geometry": {"coordinates":[45.58221,54.33653],"type":"Point"}
}