{
  "type": "Feature",
  "properties": {
    "gn:admin1_code":"60",
    "gn:asciiname":"Goryachevo",
    "gn:country_code":"RU",
    "gn:dem":105,
    "gn:feature_class":"P",
    "gn:feature_code":"PPL",
    "gn:name":"Goryach\u00ebvo",
    "gn:population":0,
    "gn:timezone":"Europe/Moscow",
    "iso:country":"RU",
    "name:rus_x_preferred":[
        "\u0413\u043e\u0440\u044f\u0447\u0451\u0432\u043e"
    ],
    "name:und_x_variant":[
        "Goryach\u00ebva",
        "Goryach\u00ebvo"
    ],
    "wof:name":"Goryachevo",
    "wof:placetype":"locality"
},
  "geometry": {"coordinates":[28.91429,56.78191999999999],"type":"Point"}
}