{
  "type": "Feature",
  "properties": {
    "gn:admin1_code":"47",
    "gn:asciiname":"Potapovskoye",
    "gn:country_code":"RU",
    "gn:dem":145,
    "gn:feature_class":"P",
    "gn:feature_code":"PPL",
    "gn:name":"Potapovskoye",
    "gn:population":0,
    "gn:timezone":"Europe/Moscow",
    "iso:country":"RU",
    "name:rus_x_preferred":[
        "\u041f\u043e\u0442\u0430\u043f\u043e\u0432\u0441\u043a\u043e\u0435"
    ],
    "name:und_x_variant":[
        "\u041f\u043e\u0442\u0430\u043f\u043e\u0432\u0441\u043a\u043e\u0435"
    ],
    "wof:name":"Potapovskoye",
    "wof:placetype":"locality"
},
  "geometry": {"coordinates":[38.80261,55.39258],"type":"Point"}
}