{
  "type": "Feature",
  "properties": {
    "gn:admin1_code":"85",
    "gn:asciiname":"Khalezevo",
    "gn:country_code":"RU",
    "gn:dem":155,
    "gn:feature_class":"P",
    "gn:feature_code":"PPL",
    "gn:name":"Khalezevo",
    "gn:population":0,
    "gn:timezone":"Europe/Moscow",
    "iso:country":"RU",
    "name:rus_x_preferred":[
        "\u0425\u0430\u043b\u0435\u0437\u0435\u0432\u043e"
    ],
    "name:und_x_variant":[
        "\u0425\u0430\u043b\u0435\u0437\u0435\u0432\u043e"
    ],
    "wof:name":"Khalezevo",
    "wof:placetype":"locality"
},
  "geometry": {"coordinates":[39.1762,59.572],"type":"Point"}
}