{
  "type": "Feature",
  "properties": {
    "gn:admin1_code":"91",
    "gn:asciiname":"Zyryanka",
    "gn:country_code":"RU",
    "gn:dem":1,
    "gn:feature_class":"P",
    "gn:feature_code":"PPL",
    "gn:name":"Zyryanka",
    "gn:population":0,
    "gn:timezone":"Asia/Krasnoyarsk",
    "iso:country":"RU",
    "name:bel_x_preferred":[
        "\u0417\u044b\u0440\u0430\u043d\u043a\u0430"
    ],
    "name:ben_x_preferred":[
        "\u099c\u09be\u0987\u09b0\u09be\u09df\u09be\u0999\u09cd\u0995\u09be"
    ],
    "name:bul_x_preferred":[
        "\u0417\u0438\u0440\u044f\u043d\u043a\u0430"
    ],
    "name:ceb_x_preferred":[
        "Zyryanka"
    ],
    "name:che_x_preferred":[
        "\u0417\u044b\u0440\u044f\u043d\u043a\u0430"
    ],
    "name:deu_x_preferred":[
        "Syrjanka"
    ],
    "name:ell_x_preferred":[
        "\u0396\u03b9\u03c1\u03b9\u03ac\u03bd\u03ba\u03b1"
    ],
    "name:est_x_preferred":[
        "Z\u00f5rjanka"
    ],
    "name:fas_x_preferred":[
        "\u0632\u06cc\u0631\u06cc\u0627\u0646\u06a9\u0627"
    ],
    "name:fin_x_preferred":[
        "Zyrjanka"
    ],
    "name:fra_x_preferred":[
        "Zyryanka"
    ],
    "name:heb_x_preferred":[
        "\u05d6\u05d9\u05e8\u05d9\u05d0\u05e0\u05e7\u05d4"
    ],
    "name:hin_x_preferred":[
        "\u091c\u0930\u094d\u092f\u093e\u0902\u0915\u093e"
    ],
    "name:hye_x_preferred":[
        "\u0536\u056b\u0580\u0575\u0561\u0576\u056f\u0561"
    ],
    "name:ind_x_preferred":[
        "Zyryanka"
    ],
    "name:ita_x_preferred":[
        "Zyrjanka"
    ],
    "name:kor_x_preferred":[
        "\uc9c0\ub9ac\uc580\uce74"
    ],
    "name:lit_x_preferred":[
        "Zyrianka"
    ],
    "name:nld_x_preferred":[
        "Zyrjanka"
    ],
    "name:pol_x_preferred":[
        "Zyrianka"
    ],
    "name:rus_x_preferred":[
        "\u0417\u044b\u0440\u044f\u043d\u043a\u0430"
    ],
    "name:sah_x_preferred":[
        "\u0417\u044b\u0440\u044f\u043d\u043a\u0430"
    ],
    "name:srp_x_preferred":[
        "\u0417\u0438\u0440\u0458\u0430\u043d\u043a\u0430"
    ],
    "name:swe_x_preferred":[
        "Zyrjanka"
    ],
    "name:tur_x_preferred":[
        "Zyryanka"
    ],
    "name:ukr_x_preferred":[
        "\u0417\u0438\u0440\u044f\u043d\u043a\u0430"
    ],
    "name:und_x_variant":[
        "Zimov\u2019ye Zyryanka"
    ],
    "name:urd_x_preferred":[
        "\u0632\u06cc\u0631\u06cc\u0627\u0646\u06a9\u0627"
    ],
    "name:vie_x_preferred":[
        "Zyryanka"
    ],
    "name:zho_cn_x_preferred":[
        "\u65e5\u826f\u5361"
    ],
    "name:zho_tw_x_preferred":[
        "\u65e5\u826f\u5361"
    ],
    "wof:name":"Zyryanka",
    "wof:placetype":"locality"
},
  "geometry": {"coordinates":[81.34557,72.34815999999999],"type":"Point"}
}