{
  "type": "Feature",
  "properties": {
    "gn:admin1_code":"91",
    "gn:asciiname":"Zyryanka",
    "gn:country_code":"RU",
    "gn:dem":1,
    "gn:feature_class":"P",
    "gn:feature_code":"PPL",
    "gn:name":"Zyryanka",
    "gn:population":0,
    "gn:timezone":"Asia/Krasnoyarsk",
    "iso:country":"RU",
    "name:bel_x_preferred":[
        "\u0417\u044b\u0440\u0430\u043d\u043a\u0430"
    ],
    "name:bul_x_preferred":[
        "\u0417\u0438\u0440\u044f\u043d\u043a\u0430"
    ],
    "name:ceb_x_preferred":[
        "Zyryanka"
    ],
    "name:che_x_preferred":[
        "\u0417\u044b\u0440\u044f\u043d\u043a\u0430"
    ],
    "name:deu_x_preferred":[
        "Syrjanka"
    ],
    "name:est_x_preferred":[
        "Z\u00f5rjanka"
    ],
    "name:fin_x_preferred":[
        "Zyrjanka"
    ],
    "name:hye_x_preferred":[
        "\u0536\u056b\u0580\u0575\u0561\u0576\u056f\u0561"
    ],
    "name:ind_x_preferred":[
        "Zyryanka"
    ],
    "name:ita_x_preferred":[
        "Zyrjanka"
    ],
    "name:lit_x_preferred":[
        "Zyrianka"
    ],
    "name:nld_x_preferred":[
        "Zyrjanka"
    ],
    "name:pol_x_preferred":[
        "Zyrianka"
    ],
    "name:rus_x_preferred":[
        "\u0417\u044b\u0440\u044f\u043d\u043a\u0430"
    ],
    "name:sah_x_preferred":[
        "\u0417\u044b\u0440\u044f\u043d\u043a\u0430"
    ],
    "name:srp_x_preferred":[
        "\u0417\u0438\u0440\u0458\u0430\u043d\u043a\u0430"
    ],
    "name:ukr_x_preferred":[
        "\u0417\u0438\u0440\u044f\u043d\u043a\u0430"
    ],
    "name:und_x_variant":[
        "Zimov\u2019ye Zyryanka"
    ],
    "wof:name":"Zyryanka",
    "wof:placetype":"locality"
},
  "geometry": {"coordinates":[81.34557,72.34815999999999],"type":"Point"}
}