{
  "type": "Feature",
  "properties": {
    "gn:admin1_code":"91",
    "gn:asciiname":"Zyryanka",
    "gn:country_code":"RU",
    "gn:dem":1,
    "gn:feature_class":"P",
    "gn:feature_code":"PPL",
    "gn:name":"Zyryanka",
    "gn:population":0,
    "gn:timezone":"Asia/Krasnoyarsk",
    "iso:country":"RU",
    "name:und_x_variant":[
        "Zimov\u2019ye Zyryanka",
        "Zyryanka"
    ],
    "wof:name":"Zyryanka",
    "wof:placetype":"locality"
},
  "geometry": {"coordinates":[81.34557,72.34815999999999],"type":"Point"}
}