{
  "type": "Feature",
  "properties": {
    "gn:admin1_code":"84",
    "gn:asciiname":"Klinovka",
    "gn:country_code":"RU",
    "gn:dem":77,
    "gn:feature_class":"P",
    "gn:feature_code":"PPL",
    "gn:name":"Klinovka",
    "gn:population":0,
    "gn:timezone":"Europe/Volgograd",
    "iso:country":"RU",
    "name:eng_x_preferred":[
        "Klinovka"
    ],
    "name:nor_x_preferred":[
        "Klinovka"
    ],
    "name:rus_x_preferred":[
        "\u041a\u043b\u0438\u043d\u043e\u0432\u043a\u0430"
    ],
    "name:und_x_variant":[
        "Klenovka",
        "Klinovka"
    ],
    "wof:name":"Klinovka",
    "wof:placetype":"locality"
},
  "geometry": {"coordinates":[44.52333,49.88829000000001],"type":"Point"}
}