{
  "type": "Feature",
  "properties": {
    "gn:admin1_code":"90.0",
    "gn:asciiname":"Komaryata",
    "gn:country_code":"RU",
    "gn:dem":131,
    "gn:feature_class":"P",
    "gn:feature_code":"PPL",
    "gn:name":"Komaryata",
    "gn:population":0,
    "gn:timezone":"Europe/Samara",
    "iso:country":"RU",
    "name:rus_x_preferred":[
        "\u041a\u043e\u043c\u0430\u0440\u044f\u0442\u0430"
    ],
    "wof:name":"Komaryata",
    "wof:placetype":"locality"
},
  "geometry": {"coordinates":[54.37055,57.07551],"type":"Point"}
}