{
  "type": "Feature",
  "properties": {
    "gn:admin1_code":"76",
    "gn:asciiname":"Belomestnoye",
    "gn:country_code":"RU",
    "gn:dem":183,
    "gn:feature_class":"P",
    "gn:feature_code":"PPL",
    "gn:name":"Belomestnoye",
    "gn:population":0,
    "gn:timezone":"Europe/Moscow",
    "iso:country":"RU",
    "name:nor_x_preferred":[
        "Belomestnoje"
    ],
    "name:rus_x_preferred":[
        "\u0411\u0435\u043b\u043e\u043c\u0435\u0441\u0442\u043d\u043e\u0435"
    ],
    "name:und_x_variant":[
        "Sloboda Belomestnaya",
        "Belomestnaya",
        "Belomestnoye"
    ],
    "wof:name":"Belomestnoye",
    "wof:placetype":"locality"
},
  "geometry": {"coordinates":[38.66088,54.17463000000001],"type":"Point"}
}