{
  "type": "Feature",
  "properties": {
    "gn:admin1_code":"77",
    "gn:asciiname":"Dokunayevo",
    "gn:country_code":"RU",
    "gn:dem":264,
    "gn:feature_class":"P",
    "gn:feature_code":"PPL",
    "gn:name":"Dokunayevo",
    "gn:population":0,
    "gn:timezone":"Europe/Moscow",
    "iso:country":"RU",
    "name:rus_x_preferred":[
        "\u0414\u043e\u043a\u0443\u043d\u0430\u0435\u0432\u043e"
    ],
    "wof:name":"Dokunayevo",
    "wof:placetype":"locality"
},
  "geometry": {"coordinates":[32.0527,57.0999],"type":"Point"}
}