{
  "type": "Feature",
  "properties": {
    "gn:admin1_code":"21.0",
    "gn:asciiname":"Meshalkino",
    "gn:country_code":"RU",
    "gn:dem":104,
    "gn:feature_class":"P",
    "gn:feature_code":"PPL",
    "gn:name":"Meshalkino",
    "gn:population":0,
    "gn:timezone":"Europe/Moscow",
    "iso:country":"RU",
    "name:nor_x_preferred":[
        "Mesjalkino"
    ],
    "name:rus_x_preferred":[
        "\u041c\u0435\u0448\u0430\u043b\u043a\u0438\u043d\u043e"
    ],
    "wof:name":"Meshalkino",
    "wof:placetype":"locality"
},
  "geometry": {"coordinates":[42.53627,56.6933],"type":"Point"}
}