{
  "type": "Feature",
  "properties": {
    "gn:admin1_code":"33",
    "gn:asciiname":"Verkhotul'ye",
    "gn:country_code":"RU",
    "gn:dem":128,
    "gn:feature_class":"P",
    "gn:feature_code":"PPL",
    "gn:name":"Verkhotul\u2019ye",
    "gn:population":0,
    "gn:timezone":"Europe/Kirov",
    "iso:country":"RU",
    "name:rus_x_preferred":[
        "\u0412\u0435\u0440\u0445\u043e\u0442\u0443\u043b\u044c\u0435"
    ],
    "name:und_x_variant":[
        "Verkhotul\u2019ye"
    ],
    "wof:name":"Verkhotul'ye",
    "wof:placetype":"locality"
},
  "geometry": {"coordinates":[48.05753,57.76886999999999],"type":"Point"}
}