{
  "type": "Feature",
  "properties": {
    "gn:admin1_code":"38.0",
    "gn:asciiname":"Potin",
    "gn:country_code":"RU",
    "gn:dem":70,
    "gn:feature_class":"P",
    "gn:feature_code":"PPL",
    "gn:name":"Potin",
    "gn:population":0,
    "gn:timezone":"Europe/Moscow",
    "iso:country":"RU",
    "name:deu_x_preferred":[
        "Potinm\u00fcnze"
    ],
    "name:fra_x_preferred":[
        "Potin"
    ],
    "name:heb_x_preferred":[
        "\u05e4\u05d5\u05d8\u05d9\u05df"
    ],
    "name:ita_x_preferred":[
        "Potin"
    ],
    "name:rus_x_preferred":[
        "\u041f\u043e\u0442\u0438\u043d"
    ],
    "wof:name":"Potin",
    "wof:placetype":"locality"
},
  "geometry": {"coordinates":[39.87083,44.96167],"type":"Point"}
}