{
  "type": "Feature",
  "properties": {
    "gn:admin1_code":"17",
    "gn:asciiname":"Mekesh",
    "gn:country_code":"RU",
    "gn:dem":1648,
    "gn:feature_class":"P",
    "gn:feature_code":"PPL",
    "gn:name":"Mekesh",
    "gn:population":0,
    "gn:timezone":"Europe/Moscow",
    "iso:country":"RU",
    "name:rus_x_preferred":[
        "\u041c\u0435\u043a\u0435\u0448"
    ],
    "name:und_x_variant":[
        "\u041c\u0435\u043a\u0435\u0448"
    ],
    "wof:name":"Mekesh",
    "wof:placetype":"locality"
},
  "geometry": {"coordinates":[47.50895,42.33756],"type":"Point"}
}