{
  "type": "Feature",
  "properties": {
    "gn:admin1_code":"84",
    "gn:asciiname":"Stanovskiy",
    "gn:country_code":"RU",
    "gn:dem":138,
    "gn:feature_class":"P",
    "gn:feature_code":"PPL",
    "gn:name":"Stanovskiy",
    "gn:population":0,
    "gn:timezone":"Europe/Volgograd",
    "iso:country":"RU",
    "name:eng_x_preferred":[
        "Stanovskiy"
    ],
    "name:nor_x_preferred":[
        "Stanovskij"
    ],
    "name:rus_x_preferred":[
        "\u0421\u0442\u0430\u043d\u043e\u0432\u0441\u043a\u0438\u0439"
    ],
    "name:und_x_variant":[
        "\u0421\u0442\u0430\u043d\u043e\u0432\u0441\u043a\u0438\u0439",
        "Stanovskiy"
    ],
    "wof:name":"Stanovskiy",
    "wof:placetype":"locality"
},
  "geometry": {"coordinates":[41.8397,50.0903],"type":"Point"}
}