{
  "type": "Feature",
  "properties": {
    "gn:admin1_code":"54",
    "gn:asciiname":"Ryazany",
    "gn:country_code":"RU",
    "gn:dem":108,
    "gn:feature_class":"P",
    "gn:feature_code":"PPL",
    "gn:name":"Ryazany",
    "gn:population":0,
    "gn:timezone":"Asia/Omsk",
    "iso:country":"RU",
    "name:eng_x_preferred":[
        "Ryazany"
    ],
    "name:nor_x_preferred":[
        "Rjazany"
    ],
    "name:rus_x_preferred":[
        "\u0420\u044f\u0437\u0430\u043d\u044b"
    ],
    "name:und_x_variant":[
        "Ryazanskoye",
        "\u0420\u044f\u0437\u0430\u043d\u044b",
        "Ryazany"
    ],
    "wof:name":"Ryazany",
    "wof:placetype":"locality"
},
  "geometry": {"coordinates":[75.21037,56.57201],"type":"Point"}
}