{
  "type": "Feature",
  "properties": {
    "gn:admin1_code":"86.0",
    "gn:asciiname":"Ruda",
    "gn:country_code":"RU",
    "gn:dem":167,
    "gn:feature_class":"P",
    "gn:feature_code":"PPL",
    "gn:name":"Ruda",
    "gn:population":0,
    "gn:timezone":"Europe/Moscow",
    "iso:country":"RU",
    "name:bos_x_preferred":[
        "Ruda"
    ],
    "name:ceb_x_preferred":[
        "Ruda"
    ],
    "name:ces_x_preferred":[
        "Ruda"
    ],
    "name:deu_x_preferred":[
        "Ruda"
    ],
    "name:epo_x_preferred":[
        "Ruda"
    ],
    "name:fra_x_preferred":[
        "Ruda"
    ],
    "name:glg_x_preferred":[
        "Ruda"
    ],
    "name:hrv_x_preferred":[
        "Ruda"
    ],
    "name:hun_x_preferred":[
        "Ruda"
    ],
    "name:ita_x_preferred":[
        "Ruda"
    ],
    "name:lit_x_preferred":[
        "Ruda"
    ],
    "name:nld_x_preferred":[
        "Ruda"
    ],
    "name:oci_x_preferred":[
        "Ruda"
    ],
    "name:pol_x_preferred":[
        "Ruda"
    ],
    "name:ron_x_preferred":[
        "Ruda"
    ],
    "name:rus_x_preferred":[
        "\u0420\u0443\u0434\u0430"
    ],
    "name:slk_x_preferred":[
        "Ruda"
    ],
    "name:slv_x_preferred":[
        "Ruda"
    ],
    "name:spa_x_preferred":[
        "Ruda"
    ],
    "name:swe_x_preferred":[
        "Ruda"
    ],
    "name:und_x_variant":[
        "\u0420\u0443\u0434\u0430"
    ],
    "name:uzb_x_preferred":[
        "Ruda"
    ],
    "wof:name":"Ruda",
    "wof:placetype":"locality"
},
  "geometry": {"coordinates":[38.7619,51.9543],"type":"Point"}
}