{
  "type": "Feature",
  "properties": {
    "gn:admin1_code":"77",
    "gn:asciiname":"Yeleykino",
    "gn:country_code":"RU",
    "gn:dem":174,
    "gn:feature_class":"P",
    "gn:feature_code":"PPL",
    "gn:name":"Yeleykino",
    "gn:population":0,
    "gn:timezone":"Europe/Moscow",
    "iso:country":"RU",
    "name:rus_x_preferred":[
        "\u0415\u043b\u0435\u0439\u043a\u0438\u043d\u043e"
    ],
    "name:und_x_variant":[
        "\u0415\u043b\u0435\u0439\u043a\u0438\u043d\u043e"
    ],
    "wof:name":"Yeleykino",
    "wof:placetype":"locality"
},
  "geometry": {"coordinates":[35.19161,58.05254],"type":"Point"}
}