{
  "type": "Feature",
  "properties": {
    "gn:admin1_code":"90",
    "gn:asciiname":"Nazarovo",
    "gn:country_code":"RU",
    "gn:dem":129,
    "gn:feature_class":"P",
    "gn:feature_code":"PPL",
    "gn:name":"Nazarovo",
    "gn:population":0,
    "gn:timezone":"Asia/Yekaterinburg",
    "iso:country":"RU",
    "name:rus_x_preferred":[
        "\u041d\u0430\u0437\u0430\u0440\u043e\u0432\u043e"
    ],
    "name:und_x_variant":[
        "\u041d\u0430\u0437\u0430\u0440\u043e\u0432\u043e"
    ],
    "wof:name":"Nazarovo",
    "wof:placetype":"locality"
},
  "geometry": {"coordinates":[56.7009,57.8308],"type":"Point"}
}