{
  "type": "Feature",
  "properties": {
    "gn:admin1_code":"52",
    "gn:asciiname":"Staryye Gusiny",
    "gn:country_code":"RU",
    "gn:dem":72,
    "gn:feature_class":"P",
    "gn:feature_code":"PPL",
    "gn:name":"Staryye Gusiny",
    "gn:population":0,
    "gn:timezone":"Europe/Moscow",
    "iso:country":"RU",
    "name:rus_x_preferred":[
        "\u0421\u0442\u0430\u0440\u044b\u0435 \u0413\u0443\u0441\u0438\u043d\u044b"
    ],
    "wof:name":"Staryye Gusiny",
    "wof:placetype":"locality"
},
  "geometry": {"coordinates":[30.34702,58.60344],"type":"Point"}
}