{
  "type": "Feature",
  "properties": {
    "gn:admin1_code":"17",
    "gn:admin2_code":"549104",
    "gn:asciiname":"Khimakoro",
    "gn:country_code":"RU",
    "gn:dem":1795,
    "gn:feature_class":"P",
    "gn:feature_code":"PPL",
    "gn:name":"Khimakoro",
    "gn:population":0,
    "gn:timezone":"Europe/Moscow",
    "iso:country":"RU",
    "name:rus_x_preferred":[
        "\u0425\u0438\u043c\u0430\u043a\u043e\u0440\u043e"
    ],
    "wof:name":"Khimakoro",
    "wof:placetype":"locality"
},
  "geometry": {"coordinates":[46.62175,42.59052],"type":"Point"}
}