{
  "type": "Feature",
  "properties": {
    "gn:admin1_code":"85",
    "gn:asciiname":"Yakovlevo",
    "gn:country_code":"RU",
    "gn:dem":205,
    "gn:feature_class":"P",
    "gn:feature_code":"PPL",
    "gn:name":"Yakovlevo",
    "gn:population":0,
    "gn:timezone":"Europe/Moscow",
    "iso:country":"RU",
    "name:rus_x_preferred":[
        "\u042f\u043a\u043e\u0432\u043b\u0435\u0432\u043e"
    ],
    "name:und_x_variant":[
        "\u042f\u043a\u043e\u0432\u043b\u0435\u0432\u043e"
    ],
    "wof:name":"Yakovlevo",
    "wof:placetype":"locality"
},
  "geometry": {"coordinates":[39.1395,59.2952],"type":"Point"}
}