{
  "type": "Feature",
  "properties": {
    "gn:admin1_code":"70.0",
    "gn:asciiname":"Galitsino",
    "gn:cc2":"RU",
    "gn:country_code":"RU",
    "gn:dem":263,
    "gn:feature_class":"P",
    "gn:feature_code":"PPL",
    "gn:name":"Galitsino",
    "gn:population":0,
    "gn:timezone":"Europe/Moscow",
    "iso:country":"RU",
    "name:rus_x_preferred":[
        "\u0413\u0430\u043b\u0438\u0446\u0438\u043d\u043e"
    ],
    "name:und_x_variant":[
        "Golitsyno",
        "Galitsino"
    ],
    "wof:name":"Galitsino",
    "wof:placetype":"locality"
},
  "geometry": {"coordinates":[41.66111,44.83806],"type":"Point"}
}