{
  "type": "Feature",
  "properties": {
    "gn:admin1_code":"17",
    "gn:admin2_code":"Tsuntinskiy Rayon",
    "gn:asciiname":"Sagada",
    "gn:country_code":"RU",
    "gn:dem":1491,
    "gn:feature_class":"P",
    "gn:feature_code":"PPL",
    "gn:name":"Sagada",
    "gn:population":0,
    "gn:timezone":"Europe/Moscow",
    "iso:country":"RU",
    "name:rus_x_preferred":[
        "\u0421\u0430\u0433\u0430\u0434\u0430"
    ],
    "name:und_x_variant":[
        "\u0421\u0430\u0433\u0430\u0434\u0430"
    ],
    "wof:name":"Sagada",
    "wof:placetype":"locality"
},
  "geometry": {"coordinates":[45.91798,42.38941],"type":"Point"}
}