{
  "type": "Feature",
  "properties": {
    "gn:admin1_code":"83.0",
    "gn:asciiname":"Oborino",
    "gn:country_code":"RU",
    "gn:dem":142,
    "gn:feature_class":"P",
    "gn:feature_code":"PPL",
    "gn:name":"Oborino",
    "gn:population":0,
    "gn:timezone":"Europe/Moscow",
    "iso:country":"RU",
    "name:rus_x_preferred":[
        "\u041e\u0431\u043e\u0440\u0438\u043d\u043e"
    ],
    "wof:name":"Oborino",
    "wof:placetype":"locality"
},
  "geometry": {"coordinates":[40.27527,56.12871],"type":"Point"}
}