{
  "type": "Feature",
  "properties": {
    "gn:admin1_code":"42",
    "gn:asciiname":"Kobona",
    "gn:country_code":"RU",
    "gn:dem":13,
    "gn:feature_class":"P",
    "gn:feature_code":"PPL",
    "gn:name":"Kobona",
    "gn:population":172,
    "gn:timezone":"Europe/Moscow",
    "iso:country":"RU",
    "name:eng_x_preferred":[
        "Kobona"
    ],
    "name:nor_x_preferred":[
        "Kobona"
    ],
    "name:rus_x_historical":[
        "\u041a\u043e\u0431\u0430\u043d\u0430",
        "\u041a\u043e\u0431\u043e\u043d\u043e",
        "\u041a\u0430\u0431\u043e\u043d\u043e"
    ],
    "name:rus_x_preferred":[
        "\u041a\u043e\u0431\u043e\u043d\u0430"
    ],
    "name:rus_x_variant":[
        "\u041a\u043e\u0431\u0430\u043d\u0430",
        "\u041a\u043e\u0431\u043e\u043d\u043e",
        "\u041a\u0430\u0431\u043e\u043d\u043e"
    ],
    "wof:name":"Kobona",
    "wof:placetype":"locality",
    "wof:population":172
},
  "geometry": {"coordinates":[31.5566,60.0188],"type":"Point"}
}