{
  "type": "Feature",
  "properties": {
    "gn:admin1_code":"91",
    "gn:asciiname":"Artyugino",
    "gn:country_code":"RU",
    "gn:dem":141,
    "gn:feature_class":"P",
    "gn:feature_code":"PPL",
    "gn:name":"Artyugino",
    "gn:population":0,
    "gn:timezone":"Asia/Krasnoyarsk",
    "iso:country":"RU",
    "name:eng_x_preferred":[
        "Artyugino"
    ],
    "name:nor_x_preferred":[
        "Artjugino"
    ],
    "name:rus_x_preferred":[
        "\u0410\u0440\u0442\u044e\u0433\u0438\u043d\u043e"
    ],
    "name:und_x_variant":[
        "Artyushino"
    ],
    "wof:name":"Artyugino",
    "wof:placetype":"locality"
},
  "geometry": {"coordinates":[96.73721999999999,58.50361],"type":"Point"}
}