{
  "type": "Feature",
  "properties": {
    "gn:admin1_code":"9",
    "gn:asciiname":"Gotov'ye",
    "gn:country_code":"RU",
    "gn:dem":131,
    "gn:feature_class":"P",
    "gn:feature_code":"PPL",
    "gn:name":"Gotov\u2019ye",
    "gn:population":0,
    "gn:timezone":"Europe/Moscow",
    "iso:country":"RU",
    "name:rus_x_preferred":[
        "\u0413\u043e\u0442\u043e\u0432\u044c\u0435"
    ],
    "name:und_x_variant":[
        "Gotov\u2019ye"
    ],
    "wof:name":"Gotov'ye",
    "wof:placetype":"locality"
},
  "geometry": {"coordinates":[37.9826,51.167],"type":"Point"}
}