{
  "type": "Feature",
  "properties": {
    "gn:admin1_code":"44",
    "gn:asciiname":"Buksunda",
    "gn:country_code":"RU",
    "gn:dem":597,
    "gn:feature_class":"P",
    "gn:feature_code":"PPL",
    "gn:name":"Buksunda",
    "gn:population":0,
    "gn:timezone":"Asia/Magadan",
    "iso:country":"RU",
    "name:rus_x_preferred":[
        "\u0411\u0443\u043a\u0441\u0443\u043d\u0434\u0430"
    ],
    "wof:name":"Buksunda",
    "wof:placetype":"locality"
},
  "geometry": {"coordinates":[157.81295,63.65496],"type":"Point"}
}