{
  "type": "Feature",
  "properties": {
    "gn:admin1_code":"65",
    "gn:asciiname":"Mayak",
    "gn:country_code":"RU",
    "gn:dem":146,
    "gn:feature_class":"P",
    "gn:feature_code":"PPL",
    "gn:name":"Mayak",
    "gn:population":0,
    "gn:timezone":"Europe/Samara",
    "iso:country":"RU",
    "name:rus_x_preferred":[
        "\u041c\u0430\u044f\u043a"
    ],
    "name:und_x_variant":[
        "\u041c\u0430\u044f\u043a"
    ],
    "wof:name":"Mayak",
    "wof:placetype":"locality"
},
  "geometry": {"coordinates":[49.33333,52.48333],"type":"Point"}
}