{
  "type": "Feature",
  "properties": {
    "gn:admin1_code":"88",
    "gn:asciiname":"Chepasovo",
    "gn:country_code":"RU",
    "gn:dem":122,
    "gn:feature_class":"P",
    "gn:feature_code":"PPL",
    "gn:name":"Chepasovo",
    "gn:population":0,
    "gn:timezone":"Europe/Moscow",
    "iso:country":"RU",
    "name:rus_x_preferred":[
        "\u0427\u0435\u043f\u0430\u0441\u043e\u0432\u043e"
    ],
    "wof:name":"Chepasovo",
    "wof:placetype":"locality"
},
  "geometry": {"coordinates":[38.2094,57.9376],"type":"Point"}
}