{
  "type": "Feature",
  "properties": {
    "gn:admin1_code":"29",
    "gn:asciiname":"Dem'yanovka",
    "gn:country_code":"RU",
    "gn:dem":357,
    "gn:feature_class":"P",
    "gn:feature_code":"PPL",
    "gn:name":"Dem\u2019yanovka",
    "gn:population":0,
    "gn:timezone":"Asia/Novokuznetsk",
    "iso:country":"RU",
    "name:rus_x_preferred":[
        "\u0414\u0435\u043c\u044c\u044f\u043d\u043e\u0432\u043a\u0430"
    ],
    "name:und_x_variant":[
        "Dem\u2019yanovka"
    ],
    "wof:name":"Dem'yanovka",
    "wof:placetype":"locality"
},
  "geometry": {"coordinates":[85.6914,54.2607],"type":"Point"}
}