{
  "type": "Feature",
  "properties": {
    "gn:admin1_code":"34",
    "gn:asciiname":"Kerkakedzh",
    "gn:country_code":"RU",
    "gn:dem":177,
    "gn:feature_class":"P",
    "gn:feature_code":"PPL",
    "gn:name":"Kerkakedzh",
    "gn:population":0,
    "gn:timezone":"Europe/Moscow",
    "iso:country":"RU",
    "name:rus_x_preferred":[
        "\u041a\u0435\u0440\u043a\u0430\u043a\u0435\u0434\u0436"
    ],
    "name:und_x_variant":[
        "\u041a\u0435\u0440\u043a\u0430\u043a\u0435\u0434\u0436"
    ],
    "wof:name":"Kerkakedzh",
    "wof:placetype":"locality"
},
  "geometry": {"coordinates":[49.31667,59.63333000000001],"type":"Point"}
}