{
  "type": "Feature",
  "properties": {
    "gn:admin1_code":"8",
    "gn:asciiname":"Yangi-Aul",
    "gn:country_code":"RU",
    "gn:dem":126,
    "gn:feature_class":"P",
    "gn:feature_code":"PPL",
    "gn:name":"Yangi-Aul",
    "gn:population":0,
    "gn:timezone":"Asia/Yekaterinburg",
    "iso:country":"RU",
    "name:aze_x_preferred":[
        "Yanau\u0131l"
    ],
    "name:bak_x_preferred":[
        "\u042f\u04a3\u0430\u0443\u044b\u043b"
    ],
    "name:che_x_preferred":[
        "\u042f\u043d\u0433\u0438-\u0410\u0443\u043b"
    ],
    "name:hye_x_preferred":[
        "\u0545\u0561\u0576\u0563\u056b-\u0531\u0578\u0582\u056c"
    ],
    "name:kat_x_preferred":[
        "\u10d8\u10d0\u10dc\u10d2\u10d8-\u10d0\u10e3\u10da\u10d8"
    ],
    "name:kaz_x_preferred":[
        "\u042f\u04a3\u0430\u0443\u044b\u043b"
    ],
    "name:rus_x_preferred":[
        "\u042f\u043d\u0433\u0438-\u0410\u0443\u043b"
    ],
    "name:tat_x_preferred":[
        "\u042f\u04a3\u0430\u0432\u044b\u043b"
    ],
    "name:ukr_x_preferred":[
        "\u042f\u043d\u0433\u0456-\u0410\u0443\u043b"
    ],
    "wof:name":"Yangi-Aul",
    "wof:placetype":"locality"
},
  "geometry": {"coordinates":[56.06448,53.62302],"type":"Point"}
}