{
  "type": "Feature",
  "properties": {
    "gn:admin1_code":"8",
    "gn:asciiname":"Yangi-Aul",
    "gn:country_code":"RU",
    "gn:dem":126,
    "gn:feature_class":"P",
    "gn:feature_code":"PPL",
    "gn:name":"Yangi-Aul",
    "gn:population":0,
    "gn:timezone":"Asia/Yekaterinburg",
    "iso:country":"RU",
    "name:rus_x_preferred":[
        "\u042f\u043d\u0433\u0438-\u0410\u0443\u043b"
    ],
    "name:und_x_variant":[
        "\u042f\u043d\u0433\u0438-\u0410\u0443\u043b"
    ],
    "wof:name":"Yangi-Aul",
    "wof:placetype":"locality"
},
  "geometry": {"coordinates":[56.06448,53.62302],"type":"Point"}
}