{
  "type": "Feature",
  "properties": {
    "gn:admin1_code":"77",
    "gn:asciiname":"Novaya Derevnya",
    "gn:country_code":"RU",
    "gn:dem":282,
    "gn:feature_class":"P",
    "gn:feature_code":"PPL",
    "gn:name":"Novaya Derevnya",
    "gn:population":0,
    "gn:timezone":"Europe/Moscow",
    "iso:country":"RU",
    "wof:name":"Novaya Derevnya",
    "wof:placetype":"locality"
},
  "geometry": {"coordinates":[33.17861,56.43611],"type":"Point"}
}