{
  "type": "Feature",
  "properties": {
    "gn:admin1_code":"47",
    "gn:asciiname":"Ozhgovo",
    "gn:country_code":"RU",
    "gn:dem":156,
    "gn:feature_class":"P",
    "gn:feature_code":"PPL",
    "gn:name":"Ozhgovo",
    "gn:population":0,
    "gn:timezone":"Europe/Moscow",
    "iso:country":"RU",
    "name:rus_x_preferred":[
        "\u041e\u0436\u0433\u043e\u0432\u043e"
    ],
    "name:und_x_variant":[
        "\u041e\u0436\u0433\u043e\u0432\u043e"
    ],
    "wof:name":"Ozhgovo",
    "wof:placetype":"locality"
},
  "geometry": {"coordinates":[36.37194,55.62083000000001],"type":"Point"}
}