{
  "type": "Feature",
  "properties": {
    "gn:country":"RU",
    "gn:fcode":"PPL",
    "gn:pop":2889,
    "iso:country":"RU",
    "name:rus_x_preferred":[
        "\u0418\u043c\u0435\u043d\u0438 \u0412\u043b\u0430\u0434\u0438\u043c\u0438\u0440\u0430 \u0418\u043b\u044c\u0438\u0447\u0430 \u041b\u0435\u043d\u0438\u043d\u0430"
    ],
    "name:unk_x_variant":[
        "Fabrika Imeni Lenina"
    ],
    "qs:name":"Imeni Vladimira Il\u2019icha Lenina",
    "qs:photos_9r":0,
    "qs:photos_sr":0,
    "qs:pop_sr":"4",
    "wof:name":"Imeni Vladimira Il\u2019icha Lenina",
    "wof:placetype":"locality",
    "wof:population":2889
},
  "geometry": {"coordinates":[46.9801,53.56422],"type":"Point"}
}