{
  "type": "Feature",
  "properties": {
    "gn:admin1_code":"80.0",
    "gn:asciiname":"Luzhany",
    "gn:country_code":"RU",
    "gn:dem":199,
    "gn:feature_class":"P",
    "gn:feature_code":"PPL",
    "gn:name":"Luzhany",
    "gn:population":0,
    "gn:timezone":"Europe/Samara",
    "iso:country":"RU",
    "name:bel_x_preferred":[
        "\u041b\u0443\u0436\u0430\u043d\u044b"
    ],
    "name:ceb_x_preferred":[
        "Luzhany"
    ],
    "name:crh_x_preferred":[
        "Lujan\u0131"
    ],
    "name:deu_x_preferred":[
        "Luschany"
    ],
    "name:heb_x_preferred":[
        "\u05dc\u05d5\u05d6'\u05d0\u05e0\u05d9"
    ],
    "name:hye_x_preferred":[
        "\u053c\u0578\u0582\u056a\u0561\u0576\u056b"
    ],
    "name:ita_x_preferred":[
        "Lu\u017eany"
    ],
    "name:pol_x_preferred":[
        "\u0141u\u017cany"
    ],
    "name:ron_x_preferred":[
        "Lujeni"
    ],
    "name:rus_x_preferred":[
        "\u041b\u0443\u0436\u0430\u043d\u044b"
    ],
    "name:ukr_x_preferred":[
        "\u041b\u0443\u0436\u0430\u043d\u0438"
    ],
    "name:zho_x_preferred":[
        "\u76e7\u624e\u5c3c"
    ],
    "wof:name":"Luzhany",
    "wof:placetype":"locality"
},
  "geometry": {"coordinates":[53.3655,57.4894],"type":"Point"}
}