{
  "type": "Feature",
  "properties": {
    "gn:admin1_code":"80.0",
    "gn:asciiname":"Luzhany",
    "gn:country_code":"RU",
    "gn:dem":199,
    "gn:feature_class":"P",
    "gn:feature_code":"PPL",
    "gn:name":"Luzhany",
    "gn:population":0,
    "gn:timezone":"Europe/Samara",
    "iso:country":"RU",
    "name:rus_x_preferred":[
        "\u041b\u0443\u0436\u0430\u043d\u044b"
    ],
    "wof:name":"Luzhany",
    "wof:placetype":"locality"
},
  "geometry": {"coordinates":[53.3655,57.4894],"type":"Point"}
}