{
  "type": "Feature",
  "properties": {
    "gn:admin1_code":"62.0",
    "gn:asciiname":"Bochkari",
    "gn:country_code":"RU",
    "gn:dem":118,
    "gn:feature_class":"P",
    "gn:feature_code":"PPL",
    "gn:name":"Bochkari",
    "gn:population":0,
    "gn:timezone":"Europe/Moscow",
    "iso:country":"RU",
    "name:rus_x_preferred":[
        "\u0411\u043e\u0447\u043a\u0430\u0440\u0438"
    ],
    "name:und_x_variant":[
        "\u0411\u043e\u0447\u043a\u0430\u0440\u0438"
    ],
    "wof:name":"Bochkari",
    "wof:placetype":"locality"
},
  "geometry": {"coordinates":[41.33643,54.90271],"type":"Point"}
}