{
  "type": "Feature",
  "properties": {
    "gn:admin1_code":"16",
    "gn:asciiname":"Khombus'-Batyrevo",
    "gn:country_code":"RU",
    "gn:dem":168,
    "gn:feature_class":"P",
    "gn:feature_code":"PPL",
    "gn:name":"Khombus\u2019-Batyr\u00ebvo",
    "gn:population":0,
    "gn:timezone":"Europe/Moscow",
    "iso:country":"RU",
    "name:rus_x_preferred":[
        "\u0425\u043e\u043c\u0431\u0443\u0441\u044c-\u0411\u0430\u0442\u044b\u0440\u0451\u0432\u043e"
    ],
    "name:und_x_variant":[
        "Khombus\u2019-Batyr\u00ebvo"
    ],
    "wof:name":"Khombus'-Batyrevo",
    "wof:placetype":"locality"
},
  "geometry": {"coordinates":[47.0958,55.2968],"type":"Point"}
}