{
  "type": "Feature",
  "properties": {
    "gn:admin1_code":"60",
    "gn:asciiname":"Istomino",
    "gn:country_code":"RU",
    "gn:dem":67,
    "gn:feature_class":"P",
    "gn:feature_code":"PPL",
    "gn:name":"Istomino",
    "gn:population":0,
    "gn:timezone":"Europe/Moscow",
    "iso:country":"RU",
    "name:rus_x_preferred":[
        "\u0418\u0441\u0442\u043e\u043c\u0438\u043d\u043e"
    ],
    "wof:name":"Istomino",
    "wof:placetype":"locality"
},
  "geometry": {"coordinates":[28.59931,57.34484000000001],"type":"Point"}
}