{
  "type": "Feature",
  "properties": {
    "gn:admin1_code":"54",
    "gn:asciiname":"Ostanovochnyy Punkt 2664 km",
    "gn:country_code":"RU",
    "gn:dem":106,
    "gn:feature_class":"P",
    "gn:feature_code":"PPL",
    "gn:name":"Ostanovochnyy Punkt 2664 km",
    "gn:population":0,
    "gn:timezone":"Asia/Omsk",
    "iso:country":"RU",
    "name:rus_x_preferred":[
        "\u041e\u0441\u0442\u0430\u043d\u043e\u0432\u043e\u0447\u043d\u044b\u0439 \u041f\u0443\u043d\u043a\u0442 2664 \u043a\u043c"
    ],
    "wof:name":"Ostanovochnyy Punkt 2664 km",
    "wof:placetype":"locality"
},
  "geometry": {"coordinates":[72.7711,55.1273],"type":"Point"}
}