{
  "type": "Feature",
  "properties": {
    "gn:admin1_code":"67",
    "gn:asciiname":"Rodionovka",
    "gn:country_code":"RU",
    "gn:dem":51,
    "gn:feature_class":"P",
    "gn:feature_code":"PPL",
    "gn:name":"Rodionovka",
    "gn:population":0,
    "gn:timezone":"Europe/Saratov",
    "iso:country":"RU",
    "name:und_x_variant":[
        "\u0420\u043e\u0434\u0438\u043e\u043d\u043e\u0432\u043a\u0430"
    ],
    "wof:name":"Rodionovka",
    "wof:placetype":"locality"
},
  "geometry": {"coordinates":[48.51667,51.68333],"type":"Point"}
}