{
  "type": "Feature",
  "properties": {
    "gn:admin1_code":"20",
    "gn:asciiname":"Khindichet",
    "gn:country_code":"RU",
    "gn:dem":189,
    "gn:feature_class":"P",
    "gn:feature_code":"PPL",
    "gn:name":"Khindichet",
    "gn:population":0,
    "gn:timezone":"Asia/Irkutsk",
    "iso:country":"RU",
    "name:eng_x_preferred":[
        "Khindichet"
    ],
    "name:nor_x_preferred":[
        "Khinditsjet"
    ],
    "name:rus_x_preferred":[
        "\u0425\u0438\u043d\u0434\u0438\u0447\u0435\u0442"
    ],
    "name:und_x_variant":[
        "\u0425\u0438\u043d\u0434\u0438\u0447\u0435\u0442",
        "Khindichet"
    ],
    "wof:name":"Khindichet",
    "wof:placetype":"locality"
},
  "geometry": {"coordinates":[97.43061,57.00399],"type":"Point"}
}