{
  "type": "Feature",
  "properties": {
    "gn:admin1_code":"52.0",
    "gn:asciiname":"Bol'shiye Luki",
    "gn:country_code":"RU",
    "gn:dem":60,
    "gn:feature_class":"P",
    "gn:feature_code":"PPL",
    "gn:name":"Bol\u2019shiye Luki",
    "gn:population":0,
    "gn:timezone":"Europe/Moscow",
    "iso:country":"RU",
    "name:rus_x_preferred":[
        "\u0411\u043e\u043b\u044c\u0448\u0438\u0435 \u041b\u0443\u043a\u0438"
    ],
    "name:und_x_variant":[
        "Luki",
        "Bol\u2019shiye Luki"
    ],
    "wof:name":"Bol'shiye Luki",
    "wof:placetype":"locality"
},
  "geometry": {"coordinates":[32.52819,57.64078000000001],"type":"Point"}
}