{
  "type": "Feature",
  "properties": {
    "gn:admin1_code":"85",
    "gn:asciiname":"Polyatino",
    "gn:country_code":"RU",
    "gn:dem":189,
    "gn:feature_class":"P",
    "gn:feature_code":"PPL",
    "gn:name":"Polyatino",
    "gn:population":0,
    "gn:timezone":"Europe/Moscow",
    "iso:country":"RU",
    "name:rus_x_preferred":[
        "\u041f\u043e\u043b\u044f\u0442\u0438\u043d\u043e"
    ],
    "name:rus_x_variant":[
        "\u041f\u043e\u043b\u044f\u0442\u0438\u043d\u0430"
    ],
    "name:und_x_variant":[
        "\u041f\u043e\u043b\u044f\u0442\u0438\u043d\u043e",
        "Polyatina",
        "\u041f\u043e\u043b\u044f\u0442\u0438\u043d\u0430"
    ],
    "wof:name":"Polyatino",
    "wof:placetype":"locality"
},
  "geometry": {"coordinates":[35.25452999999999,58.79501],"type":"Point"}
}