{
  "type": "Feature",
  "properties": {
    "gn:admin1_code":"33.0",
    "gn:asciiname":"Filichi",
    "gn:country_code":"RU",
    "gn:dem":199,
    "gn:feature_class":"P",
    "gn:feature_code":"PPL",
    "gn:name":"Filichi",
    "gn:population":0,
    "gn:timezone":"Europe/Kirov",
    "iso:country":"RU",
    "name:rus_x_preferred":[
        "\u0424\u0438\u043b\u0438\u0447\u0438"
    ],
    "name:und_x_variant":[
        "\u0424\u0438\u043b\u0438\u0447\u0438"
    ],
    "wof:name":"Filichi",
    "wof:placetype":"locality"
},
  "geometry": {"coordinates":[48.80142,58.82185],"type":"Point"}
}