{
  "type": "Feature",
  "properties": {
    "gn:admin1_code":"85",
    "gn:asciiname":"Romannikovo",
    "gn:country_code":"RU",
    "gn:dem":170,
    "gn:feature_class":"P",
    "gn:feature_code":"PPL",
    "gn:name":"Romannikovo",
    "gn:population":0,
    "gn:timezone":"Europe/Moscow",
    "iso:country":"RU",
    "name:rus_x_preferred":[
        "\u0420\u043e\u043c\u0430\u043d\u043d\u0438\u043a\u043e\u0432\u043e"
    ],
    "name:und_x_variant":[
        "\u0420\u043e\u043c\u0430\u043d\u043d\u0438\u043a\u043e\u0432\u043e"
    ],
    "wof:name":"Romannikovo",
    "wof:placetype":"locality"
},
  "geometry": {"coordinates":[38.6694,59.3945],"type":"Point"}
}