{
  "type": "Feature",
  "properties": {
    "gn:admin1_code":"17",
    "gn:admin2_code":"480804",
    "gn:asciiname":"Kochali",
    "gn:country_code":"RU",
    "gn:dem":1080,
    "gn:feature_class":"P",
    "gn:feature_code":"PPL",
    "gn:name":"Kochali",
    "gn:population":0,
    "gn:timezone":"Europe/Moscow",
    "iso:country":"RU",
    "name:rus_x_preferred":[
        "\u041a\u043e\u0447\u0430\u043b\u0438"
    ],
    "name:und_x_variant":[
        "\u041a\u043e\u0447\u0430\u043b\u0438"
    ],
    "wof:name":"Kochali",
    "wof:placetype":"locality"
},
  "geometry": {"coordinates":[46.11285,42.52642],"type":"Point"}
}