{
  "type": "Feature",
  "properties": {
    "gn:admin1_code":"63",
    "gn:asciiname":"Khos-Alas",
    "gn:country_code":"RU",
    "gn:dem":362,
    "gn:feature_class":"P",
    "gn:feature_code":"PPL",
    "gn:name":"Khos-Alas",
    "gn:population":0,
    "gn:timezone":"Asia/Yakutsk",
    "iso:country":"RU",
    "name:rus_x_preferred":[
        "\u0425\u043e\u0441-\u0410\u043b\u0430\u0441"
    ],
    "name:und_x_variant":[
        "Khas-Alas",
        "Khos-Alaas",
        "Khos-Alas",
        "\u0425\u043e\u0441-\u0410\u043b\u0430\u0441"
    ],
    "wof:name":"Khos-Alas",
    "wof:placetype":"locality"
},
  "geometry": {"coordinates":[130.76244,67.57906],"type":"Point"}
}