{
  "type": "Feature",
  "properties": {
    "gn:admin1_code":"61",
    "gn:asciiname":"Khar'kovskiy Vtoroy",
    "gn:country_code":"RU",
    "gn:dem":27,
    "gn:feature_class":"P",
    "gn:feature_code":"PPL",
    "gn:name":"Khar\u2019kovskiy Vtoroy",
    "gn:population":0,
    "gn:timezone":"Europe/Moscow",
    "iso:country":"RU",
    "name:rus_x_preferred":[
        "\u0425\u0430\u0440\u044c\u043a\u043e\u0432\u0441\u043a\u0438\u0439 \u0412\u0442\u043e\u0440\u043e\u0439"
    ],
    "name:und_x_variant":[
        "Khar\u2019kovskiy",
        "Khar\u2019kovskiy Vtoroy"
    ],
    "wof:name":"Khar'kovskiy Vtoroy",
    "wof:placetype":"locality"
},
  "geometry": {"coordinates":[41.47094,46.99173],"type":"Point"}
}