{
  "type": "Feature",
  "properties": {
    "gn:admin1_code":"65",
    "gn:asciiname":"Ledyayka",
    "gn:country_code":"RU",
    "gn:dem":137,
    "gn:feature_class":"P",
    "gn:feature_code":"PPL",
    "gn:name":"Ledyayka",
    "gn:population":0,
    "gn:timezone":"Europe/Samara",
    "iso:country":"RU",
    "name:rus_x_preferred":[
        "\u041b\u0435\u0434\u044f\u0439\u043a\u0430"
    ],
    "name:und_x_variant":[
        "Ledyay",
        "Ledyayka",
        "\u041b\u0435\u0434\u044f\u0439\u043a\u0430"
    ],
    "wof:name":"Ledyayka",
    "wof:placetype":"locality"
},
  "geometry": {"coordinates":[50.49451,52.5684],"type":"Point"}
}