{
  "type": "Feature",
  "properties": {
    "gn:admin1_code":"64.0",
    "gn:asciiname":"Kirpichnyy",
    "gn:country_code":"RU",
    "gn:dem":26,
    "gn:feature_class":"P",
    "gn:feature_code":"PPL",
    "gn:name":"Kirpichnyy",
    "gn:population":0,
    "gn:timezone":"Asia/Sakhalin",
    "iso:country":"RU",
    "wof:name":"Kirpichnyy",
    "wof:placetype":"locality"
},
  "geometry": {"coordinates":[142.80475000000001,46.6318],"type":"Point"}
}