{
  "type": "Feature",
  "properties": {
    "gn:admin1_code":"54",
    "gn:asciiname":"Maloye Terekhino",
    "gn:country_code":"RU",
    "gn:dem":91,
    "gn:feature_class":"P",
    "gn:feature_code":"PPL",
    "gn:name":"Maloye Ter\u00ebkhino",
    "gn:population":0,
    "gn:timezone":"Asia/Omsk",
    "iso:country":"RU",
    "name:rus_x_preferred":[
        "\u041c\u0430\u043b\u043e\u0435 \u0422\u0435\u0440\u0451\u0445\u0438\u043d\u043e"
    ],
    "name:und_x_variant":[
        "Maloye Ter\u00ebkhino"
    ],
    "wof:name":"Maloye Terekhino",
    "wof:placetype":"locality"
},
  "geometry": {"coordinates":[73.88333,56.55],"type":"Point"}
}