{
  "type": "Feature",
  "properties": {
    "gn:admin1_code":"62",
    "gn:asciiname":"Mashkovo",
    "gn:country_code":"RU",
    "gn:dem":184,
    "gn:feature_class":"P",
    "gn:feature_code":"PPL",
    "gn:name":"Mashkovo",
    "gn:population":0,
    "gn:timezone":"Europe/Moscow",
    "iso:country":"RU",
    "name:rus_x_preferred":[
        "\u041c\u0430\u0448\u043a\u043e\u0432\u043e"
    ],
    "wof:name":"Mashkovo",
    "wof:placetype":"locality"
},
  "geometry": {"coordinates":[38.91435,54.38027],"type":"Point"}
}