{
  "type": "Feature",
  "properties": {
    "gn:admin1_code":"21",
    "gn:asciiname":"Starostino",
    "gn:country_code":"RU",
    "gn:dem":130,
    "gn:feature_class":"P",
    "gn:feature_code":"PPL",
    "gn:name":"Starostino",
    "gn:population":0,
    "gn:timezone":"Europe/Moscow",
    "iso:country":"RU",
    "name:rus_x_preferred":[
        "\u0421\u0442\u0430\u0440\u043e\u0441\u0442\u0438\u043d\u043e"
    ],
    "name:und_x_variant":[
        "\u0421\u0442\u0430\u0440\u043e\u0441\u0442\u0438\u043d\u043e"
    ],
    "wof:name":"Starostino",
    "wof:placetype":"locality"
},
  "geometry": {"coordinates":[41.71366,57.26105],"type":"Point"}
}