{
  "type": "Feature",
  "properties": {
    "gn:admin1_code":"83",
    "gn:asciiname":"Spas-Zhelezino",
    "gn:country_code":"RU",
    "gn:dem":97,
    "gn:feature_class":"P",
    "gn:feature_code":"PPL",
    "gn:name":"Spas-Zhelezino",
    "gn:population":0,
    "gn:timezone":"Europe/Moscow",
    "iso:country":"RU",
    "name:rus_x_preferred":[
        "\u0421\u043f\u0430\u0441-\u0416\u0435\u043b\u0435\u0437\u0438\u043d\u043e"
    ],
    "wof:name":"Spas-Zhelezino",
    "wof:placetype":"locality"
},
  "geometry": {"coordinates":[41.8952,55.882],"type":"Point"}
}