{
  "type": "Feature",
  "properties": {
    "gn:admin1_code":"33",
    "gn:asciiname":"Lipashur",
    "gn:country_code":"RU",
    "gn:dem":240,
    "gn:feature_class":"P",
    "gn:feature_code":"PPL",
    "gn:name":"Lipashur",
    "gn:population":0,
    "gn:timezone":"Europe/Kirov",
    "iso:country":"RU",
    "name:rus_x_preferred":[
        "\u041b\u0438\u043f\u0430\u0448\u0443\u0440"
    ],
    "name:und_x_variant":[
        "\u041b\u0438\u043f\u0430\u0448\u0443\u0440"
    ],
    "wof:name":"Lipashur",
    "wof:placetype":"locality"
},
  "geometry": {"coordinates":[53.1754,58.5334],"type":"Point"}
}