{
  "type": "Feature",
  "properties": {
    "gn:admin1_code":"46.0",
    "gn:asciiname":"Staryy Usad",
    "gn:country_code":"RU",
    "gn:dem":162,
    "gn:feature_class":"P",
    "gn:feature_code":"PPL",
    "gn:name":"Staryy Usad",
    "gn:population":0,
    "gn:timezone":"Europe/Moscow",
    "iso:country":"RU",
    "name:rus_x_preferred":[
        "\u0421\u0442\u0430\u0440\u044b\u0439 \u0423\u0441\u0430\u0434"
    ],
    "wof:name":"Staryy Usad",
    "wof:placetype":"locality"
},
  "geometry": {"coordinates":[44.81551,54.01953],"type":"Point"}
}