{
  "type": "Feature",
  "properties": {
    "gn:admin1_code":"69",
    "gn:asciiname":"Sineyevo",
    "gn:country_code":"RU",
    "gn:dem":221,
    "gn:feature_class":"P",
    "gn:feature_code":"PPL",
    "gn:name":"Sineyevo",
    "gn:population":0,
    "gn:timezone":"Europe/Moscow",
    "iso:country":"RU",
    "name:rus_x_preferred":[
        "\u0421\u0438\u043d\u0435\u0435\u0432\u043e"
    ],
    "name:und_x_variant":[
        "\u0421\u0438\u043d\u0435\u0435\u0432\u043e"
    ],
    "wof:name":"Sineyevo",
    "wof:placetype":"locality"
},
  "geometry": {"coordinates":[34.53132,55.2041],"type":"Point"}
}