{
  "type": "Feature",
  "properties": {
    "gn:admin1_code":"40",
    "gn:asciiname":"Rybnyy",
    "gn:country_code":"RU",
    "gn:dem":132,
    "gn:feature_class":"P",
    "gn:feature_code":"PPL",
    "gn:name":"Rybnyy",
    "gn:population":0,
    "gn:timezone":"Asia/Yekaterinburg",
    "iso:country":"RU",
    "name:rus_x_preferred":[
        "\u0420\u044b\u0431\u043d\u044b\u0439"
    ],
    "wof:name":"Rybnyy",
    "wof:placetype":"locality"
},
  "geometry": {"coordinates":[67.42222,55.59556],"type":"Point"}
}