{
  "type": "Feature",
  "properties": {
    "gn:admin1_code":"16",
    "gn:asciiname":"Leninskiy",
    "gn:country_code":"RU",
    "gn:dem":89,
    "gn:feature_class":"P",
    "gn:feature_code":"PPL",
    "gn:name":"Leninskiy",
    "gn:population":0,
    "gn:timezone":"Europe/Moscow",
    "iso:country":"RU",
    "name:rus_x_preferred":[
        "\u041b\u0435\u043d\u0438\u043d\u0441\u043a\u0438\u0439"
    ],
    "name:und_x_variant":[
        "\u041b\u0435\u043d\u0438\u043d\u0441\u043a\u0438\u0439"
    ],
    "wof:name":"Leninskiy",
    "wof:placetype":"locality"
},
  "geometry": {"coordinates":[46.05,55.16667],"type":"Point"}
}