{
  "type": "Feature",
  "properties": {
    "gn:admin1_code":"33",
    "gn:asciiname":"Verkhneye Baranovo",
    "gn:country_code":"RU",
    "gn:dem":121,
    "gn:feature_class":"P",
    "gn:feature_code":"PPL",
    "gn:name":"Verkhneye Baranovo",
    "gn:population":0,
    "gn:timezone":"Europe/Kirov",
    "iso:country":"RU",
    "name:rus_x_preferred":[
        "\u0412\u0435\u0440\u0445\u043d\u0435\u0435 \u0411\u0430\u0440\u0430\u043d\u043e\u0432\u043e"
    ],
    "wof:name":"Verkhneye Baranovo",
    "wof:placetype":"locality"
},
  "geometry": {"coordinates":[46.9203,57.1951],"type":"Point"}
}