{
  "type": "Feature",
  "properties": {
    "gn:admin1_code":"51.0",
    "gn:asciiname":"Plyasitsyno",
    "gn:country_code":"RU",
    "gn:dem":116,
    "gn:feature_class":"P",
    "gn:feature_code":"PPL",
    "gn:name":"Plyasitsyno",
    "gn:population":0,
    "gn:timezone":"Europe/Moscow",
    "iso:country":"RU",
    "name:nor_x_preferred":[
        "Pljasitsyno"
    ],
    "name:rus_x_preferred":[
        "\u041f\u043b\u044f\u0441\u0438\u0446\u044b\u043d\u043e"
    ],
    "name:und_x_variant":[
        "Plyasitsino",
        "Plyasitsyno"
    ],
    "wof:name":"Plyasitsyno",
    "wof:placetype":"locality"
},
  "geometry": {"coordinates":[43.21995,56.6747],"type":"Point"}
}