{
  "type": "Feature",
  "properties": {
    "gn:country":"RU",
    "gn:fcode":"PPL",
    "gn:pop":4220,
    "iso:country":"RU",
    "name:eng_x_preferred":[
        "Ikon-Khalk"
    ],
    "name:nor_x_preferred":[
        "Ikon-Khalk"
    ],
    "name:rus_x_preferred":[
        "\u0418\u043a\u043e\u043d-\u0425\u0430\u043b\u043a"
    ],
    "name:unk_x_variant":[
        "\u0418\u043a\u043e\u043d-\u0425\u0430\u043b\u043a"
    ],
    "qs:name":"Ikon-Khalk",
    "qs:name_adm0":"Russia",
    "qs:name_adm1":"Karachay-Cherkessia Republic",
    "qs:photos_9r":0,
    "qs:photos_sr":0,
    "qs:placetype":"Town",
    "qs:pop_sr":"4",
    "wof:name":"Ikon-Khalk",
    "wof:placetype":"locality",
    "wof:population":4220
},
  "geometry": {"coordinates":[41.9142,44.3051],"type":"Point"}
}