{
  "type": "Feature",
  "properties": {
    "gn:admin1_code":"91",
    "gn:asciiname":"Spasskoye",
    "gn:cc2":"RU",
    "gn:country_code":"RU",
    "gn:dem":208,
    "gn:feature_class":"P",
    "gn:feature_code":"PPL",
    "gn:name":"Spasskoye",
    "gn:population":0,
    "gn:timezone":"Asia/Krasnoyarsk",
    "iso:country":"RU",
    "name:rus_x_preferred":[
        "\u0421\u043f\u0430\u0441\u0441\u043a\u043e\u0435"
    ],
    "name:und_x_variant":[
        "Spasskaya",
        "Spasskoye"
    ],
    "wof:name":"Spasskoye",
    "wof:placetype":"locality"
},
  "geometry": {"coordinates":[91.51667,56.98333],"type":"Point"}
}