{
  "type": "Feature",
  "properties": {
    "gn:admin1_code":"59",
    "gn:asciiname":"Baza Kruglaya",
    "gn:country_code":"RU",
    "gn:dem":23,
    "gn:feature_class":"P",
    "gn:feature_code":"PPL",
    "gn:name":"Baza Kruglaya",
    "gn:population":0,
    "gn:timezone":"Asia/Vladivostok",
    "iso:country":"RU",
    "name:nor_x_preferred":[
        "Baza Kruglaja"
    ],
    "name:rus_x_preferred":[
        "\u0411\u0430\u0437\u0430 \u041a\u0440\u0443\u0433\u043b\u0430\u044f"
    ],
    "name:und_x_variant":[
        "Krugla",
        "Baza Kruglaya"
    ],
    "wof:name":"Baza Kruglaya",
    "wof:placetype":"locality"
},
  "geometry": {"coordinates":[131.43996999999999,42.87344],"type":"Point"}
}