{
  "type": "Feature",
  "properties": {
    "gn:admin1_code":"67",
    "gn:asciiname":"Pot'ma",
    "gn:country_code":"RU",
    "gn:dem":154,
    "gn:feature_class":"P",
    "gn:feature_code":"PPL",
    "gn:name":"Pot\u2019ma",
    "gn:population":0,
    "gn:timezone":"Europe/Saratov",
    "iso:country":"RU",
    "name:eng_x_preferred":[
        "Pot'ma"
    ],
    "name:nor_x_preferred":[
        "Potma"
    ],
    "name:rus_x_preferred":[
        "\u041f\u043e\u0442\u044c\u043c\u0430"
    ],
    "name:und_x_variant":[
        "Pot\u2019ma"
    ],
    "wof:name":"Pot'ma",
    "wof:placetype":"locality"
},
  "geometry": {"coordinates":[43.386,52.27429],"type":"Point"}
}