{
  "type": "Feature",
  "properties": {
    "gn:admin1_code":"21.0",
    "gn:asciiname":"Poperekovo",
    "gn:country_code":"RU",
    "gn:dem":111,
    "gn:feature_class":"P",
    "gn:feature_code":"PPL",
    "gn:name":"Poper\u00ebkovo",
    "gn:population":0,
    "gn:timezone":"Europe/Moscow",
    "iso:country":"RU",
    "name:nor_x_preferred":[
        "Poperjokovo"
    ],
    "name:rus_x_preferred":[
        "\u041f\u043e\u043f\u0435\u0440\u0451\u043a\u043e\u0432\u043e"
    ],
    "name:und_x_variant":[
        "Poper\u00ebkovo"
    ],
    "wof:name":"Poperekovo",
    "wof:placetype":"locality"
},
  "geometry": {"coordinates":[43.1736,56.92827],"type":"Point"}
}