{
  "type": "Feature",
  "properties": {
    "gn:admin1_code":"57",
    "gn:asciiname":"Kil'mayevka",
    "gn:country_code":"RU",
    "gn:dem":174,
    "gn:feature_class":"P",
    "gn:feature_code":"PPL",
    "gn:name":"Kil\u2019may\u00ebvka",
    "gn:population":0,
    "gn:timezone":"Europe/Moscow",
    "iso:country":"RU",
    "name:rus_x_preferred":[
        "\u041a\u0438\u043b\u044c\u043c\u0430\u0451\u0432\u043a\u0430"
    ],
    "name:und_x_variant":[
        "Kil\u2019may\u00ebvka"
    ],
    "wof:name":"Kil'mayevka",
    "wof:placetype":"locality"
},
  "geometry": {"coordinates":[44.73158,53.82048],"type":"Point"}
}