{
  "type": "Feature",
  "properties": {
    "gn:admin1_code":"62",
    "gn:asciiname":"Bol'shoye Shapovo",
    "gn:country_code":"RU",
    "gn:dem":120,
    "gn:feature_class":"P",
    "gn:feature_code":"PPL",
    "gn:name":"Bol\u2019shoye Shapovo",
    "gn:population":0,
    "gn:timezone":"Europe/Moscow",
    "iso:country":"RU",
    "name:rus_x_preferred":[
        "\u0411\u043e\u043b\u044c\u0448\u043e\u0435 \u0428\u0430\u043f\u043e\u0432\u043e"
    ],
    "name:und_x_variant":[
        "Bol\u2019shoye Shapovo",
        "\u0411\u043e\u043b\u044c\u0448\u043e\u0435 \u0428\u0430\u043f\u043e\u0432\u043e"
    ],
    "wof:name":"Bol'shoye Shapovo",
    "wof:placetype":"locality"
},
  "geometry": {"coordinates":[39.5034,54.6476],"type":"Point"}
}