{
  "type": "Feature",
  "properties": {
    "gn:admin1_code":"47",
    "gn:asciiname":"Lipkino",
    "gn:country_code":"RU",
    "gn:dem":133,
    "gn:feature_class":"P",
    "gn:feature_code":"PPL",
    "gn:name":"Lipkino",
    "gn:population":0,
    "gn:timezone":"Europe/Moscow",
    "iso:country":"RU",
    "name:rus_x_preferred":[
        "\u041b\u0438\u043f\u043a\u0438\u043d\u043e"
    ],
    "name:und_x_variant":[
        "\u041b\u0438\u043f\u043a\u0438\u043d\u043e"
    ],
    "wof:name":"Lipkino",
    "wof:placetype":"locality"
},
  "geometry": {"coordinates":[38.13672,55.29751],"type":"Point"}
}