{
  "type": "Feature",
  "properties": {
    "gn:admin1_code":"9.0",
    "gn:asciiname":"Novaya Dolina",
    "gn:country_code":"RU",
    "gn:dem":200,
    "gn:feature_class":"P",
    "gn:feature_code":"PPL",
    "gn:name":"Novaya Dolina",
    "gn:population":0,
    "gn:timezone":"Europe/Moscow",
    "iso:country":"RU",
    "name:rus_x_preferred":[
        "\u041d\u043e\u0432\u0430\u044f \u0414\u043e\u043b\u0438\u043d\u0430"
    ],
    "wof:name":"Novaya Dolina",
    "wof:placetype":"locality"
},
  "geometry": {"coordinates":[37.6074,50.5569],"type":"Point"}
}