{
  "type": "Feature",
  "properties": {
    "gn:admin1_code":"83",
    "gn:asciiname":"Nogosekovo",
    "gn:country_code":"RU",
    "gn:dem":190,
    "gn:feature_class":"P",
    "gn:feature_code":"PPL",
    "gn:name":"Nogosekovo",
    "gn:population":0,
    "gn:timezone":"Europe/Moscow",
    "iso:country":"RU",
    "name:rus_x_preferred":[
        "\u041d\u043e\u0433\u043e\u0441\u0435\u043a\u043e\u0432\u043e"
    ],
    "name:und_x_variant":[
        "Nagasekovo",
        "Nogosekovo"
    ],
    "wof:name":"Nogosekovo",
    "wof:placetype":"locality"
},
  "geometry": {"coordinates":[39.71512,56.284],"type":"Point"}
}