{
  "type": "Feature",
  "properties": {
    "gn:admin1_code":"71",
    "gn:asciiname":"Fokintsy",
    "gn:country_code":"RU",
    "gn:dem":212,
    "gn:feature_class":"P",
    "gn:feature_code":"PPL",
    "gn:name":"Fokintsy",
    "gn:population":0,
    "gn:timezone":"Asia/Yekaterinburg",
    "iso:country":"RU",
    "name:rus_x_preferred":[
        "\u0424\u043e\u043a\u0438\u043d\u0446\u044b"
    ],
    "wof:name":"Fokintsy",
    "wof:placetype":"locality"
},
  "geometry": {"coordinates":[60.65754,57.68155],"type":"Point"}
}