{
  "type": "Feature",
  "properties": {
    "gn:admin1_code":"38",
    "gn:asciiname":"Sladkiy",
    "gn:country_code":"RU",
    "gn:dem":414,
    "gn:feature_class":"P",
    "gn:feature_code":"PPL",
    "gn:name":"Sladkiy",
    "gn:population":0,
    "gn:timezone":"Europe/Moscow",
    "iso:country":"RU",
    "name:rus_x_preferred":[
        "\u0421\u043b\u0430\u0434\u043a\u0438\u0439"
    ],
    "name:und_x_variant":[
        "\u0421\u043b\u0430\u0434\u043a\u0438\u0439"
    ],
    "wof:name":"Sladkiy",
    "wof:placetype":"locality"
},
  "geometry": {"coordinates":[41.0351,44.4719],"type":"Point"}
}