{
  "type": "Feature",
  "properties": {
    "gn:admin1_code":"69",
    "gn:asciiname":"Uskosy",
    "gn:country_code":"RU",
    "gn:dem":161,
    "gn:feature_class":"P",
    "gn:feature_code":"PPL",
    "gn:name":"Uskosy",
    "gn:population":0,
    "gn:timezone":"Europe/Moscow",
    "iso:country":"RU",
    "name:rus_x_preferred":[
        "\u0423\u0441\u043a\u043e\u0441\u044b"
    ],
    "wof:name":"Uskosy",
    "wof:placetype":"locality"
},
  "geometry": {"coordinates":[32.06055,54.14847],"type":"Point"}
}