{
  "type": "Feature",
  "properties": {
    "gn:admin1_code":"05",
    "gn:asciiname":"Borispol'",
    "gn:country_code":"RU",
    "gn:dem":198,
    "gn:feature_class":"P",
    "gn:feature_code":"PPL",
    "gn:name":"Borispol\u2019",
    "gn:population":0,
    "gn:timezone":"Asia/Yakutsk",
    "iso:country":"RU",
    "name:eng_x_preferred":[
        "Borispol'"
    ],
    "name:nor_x_preferred":[
        "Borispol"
    ],
    "name:rus_x_preferred":[
        "\u0411\u043e\u0440\u0438\u0441\u043f\u043e\u043b\u044c"
    ],
    "name:und_x_variant":[
        "Borisopol\u2019",
        "Borispol\u2019"
    ],
    "wof:name":"Borispol'",
    "wof:placetype":"locality"
},
  "geometry": {"coordinates":[128.57151000000002,51.04823],"type":"Point"}
}