{
  "type": "Feature",
  "properties": {
    "gn:admin1_code":"34",
    "gn:asciiname":"Yndin",
    "gn:country_code":"RU",
    "gn:dem":158,
    "gn:feature_class":"P",
    "gn:feature_code":"PPL",
    "gn:name":"Yndin",
    "gn:population":0,
    "gn:timezone":"Europe/Moscow",
    "iso:country":"RU",
    "name:eng_x_preferred":[
        "Yndin"
    ],
    "name:nor_x_preferred":[
        "Yndin"
    ],
    "name:rus_x_preferred":[
        "\u042b\u043d\u0434\u0438\u043d"
    ],
    "wof:name":"Yndin",
    "wof:placetype":"locality"
},
  "geometry": {"coordinates":[55.21394,61.40165],"type":"Point"}
}