{
  "type": "Feature",
  "properties": {
    "gn:admin1_code":"21.0",
    "gn:asciiname":"Pervunikha",
    "gn:country_code":"RU",
    "gn:dem":102,
    "gn:feature_class":"P",
    "gn:feature_code":"PPL",
    "gn:name":"Pervunikha",
    "gn:population":0,
    "gn:timezone":"Europe/Moscow",
    "iso:country":"RU",
    "name:nor_x_preferred":[
        "Pervunikha"
    ],
    "name:rus_x_preferred":[
        "\u041f\u0435\u0440\u0432\u0443\u043d\u0438\u0445\u0430"
    ],
    "wof:name":"Pervunikha",
    "wof:placetype":"locality"
},
  "geometry": {"coordinates":[43.17975,56.96096],"type":"Point"}
}