{
  "type": "Feature",
  "properties": {
    "gn:admin1_code":"42",
    "gn:asciiname":"Perevoz",
    "gn:country_code":"RU",
    "gn:dem":1,
    "gn:feature_class":"P",
    "gn:feature_code":"PPL",
    "gn:name":"Perevoz",
    "gn:population":0,
    "gn:timezone":"Europe/Moscow",
    "iso:country":"RU",
    "name:rus_x_preferred":[
        "\u041f\u0435\u0440\u0435\u0432\u043e\u0437"
    ],
    "name:und_x_variant":[
        "\u041f\u0435\u0440\u0435\u0432\u043e\u0437"
    ],
    "wof:name":"Perevoz",
    "wof:placetype":"locality"
},
  "geometry": {"coordinates":[32.55734,60.10396],"type":"Point"}
}