{
  "type": "Feature",
  "properties": {
    "gn:admin1_code":"30",
    "gn:asciiname":"Kotikovo",
    "gn:country_code":"RU",
    "gn:dem":71,
    "gn:feature_class":"P",
    "gn:feature_code":"PPL",
    "gn:name":"Kotikovo",
    "gn:population":0,
    "gn:timezone":"Asia/Vladivostok",
    "iso:country":"RU",
    "name:eng_x_preferred":[
        "Kotikovo"
    ],
    "name:nor_x_preferred":[
        "Kotikovo"
    ],
    "name:rus_x_preferred":[
        "\u041a\u043e\u0442\u0438\u043a\u043e\u0432\u043e"
    ],
    "name:und_x_variant":[
        "Kochikowo"
    ],
    "wof:name":"Kotikovo",
    "wof:placetype":"locality"
},
  "geometry": {"coordinates":[134.57235,47.4172],"type":"Point"}
}