{
  "type": "Feature",
  "properties": {
    "gn:admin1_code":"45.0",
    "gn:asciiname":"Engerbal",
    "gn:country_code":"RU",
    "gn:dem":128,
    "gn:feature_class":"P",
    "gn:feature_code":"PPL",
    "gn:name":"Engerbal",
    "gn:population":0,
    "gn:timezone":"Europe/Moscow",
    "iso:country":"RU",
    "name:rus_x_preferred":[
        "\u042d\u043d\u0433\u0435\u0440\u0431\u0430\u043b"
    ],
    "name:und_x_variant":[
        "\u042d\u043d\u0433\u0435\u0440\u0431\u0430\u043b"
    ],
    "wof:name":"Engerbal",
    "wof:placetype":"locality"
},
  "geometry": {"coordinates":[49.61962,56.79468000000001],"type":"Point"}
}