{
  "type": "Feature",
  "properties": {
    "gn:admin1_code":"77",
    "gn:asciiname":"Mokrikha",
    "gn:country_code":"RU",
    "gn:dem":136,
    "gn:feature_class":"P",
    "gn:feature_code":"PPL",
    "gn:name":"Mokrikha",
    "gn:population":0,
    "gn:timezone":"Europe/Moscow",
    "iso:country":"RU",
    "name:rus_x_preferred":[
        "\u041c\u043e\u043a\u0440\u0438\u0445\u0430"
    ],
    "wof:name":"Mokrikha",
    "wof:placetype":"locality"
},
  "geometry": {"coordinates":[36.9886,57.3556],"type":"Point"}
}