{
  "type": "Feature",
  "properties": {
    "gn:admin1_code":"25",
    "gn:asciiname":"Solopikhino",
    "gn:country_code":"RU",
    "gn:dem":167,
    "gn:feature_class":"P",
    "gn:feature_code":"PPL",
    "gn:name":"Solopikhino",
    "gn:population":0,
    "gn:timezone":"Europe/Moscow",
    "iso:country":"RU",
    "name:rus_x_preferred":[
        "\u0421\u043e\u043b\u043e\u043f\u0438\u0445\u0438\u043d\u043e"
    ],
    "wof:name":"Solopikhino",
    "wof:placetype":"locality"
},
  "geometry": {"coordinates":[35.51851,54.59511],"type":"Point"}
}