{
  "type": "Feature",
  "properties": {
    "gn:admin1_code":"51.0",
    "gn:asciiname":"Oblizino",
    "gn:country_code":"RU",
    "gn:dem":142,
    "gn:feature_class":"P",
    "gn:feature_code":"PPL",
    "gn:name":"Oblizino",
    "gn:population":0,
    "gn:timezone":"Europe/Moscow",
    "iso:country":"RU",
    "name:nor_x_preferred":[
        "Oblizino"
    ],
    "name:rus_x_preferred":[
        "\u041e\u0431\u043b\u0438\u0437\u0438\u043d\u043e"
    ],
    "wof:name":"Oblizino",
    "wof:placetype":"locality"
},
  "geometry": {"coordinates":[43.64702,56.92722],"type":"Point"}
}