{
  "type": "Feature",
  "properties": {
    "gn:admin1_code":"77",
    "gn:asciiname":"Nameskovo",
    "gn:country_code":"RU",
    "gn:dem":167,
    "gn:feature_class":"P",
    "gn:feature_code":"PPL",
    "gn:name":"Nameskovo",
    "gn:population":0,
    "gn:timezone":"Europe/Moscow",
    "iso:country":"RU",
    "name:eng_x_preferred":[
        "Nameskovo"
    ],
    "name:nor_x_preferred":[
        "Nameskovo"
    ],
    "name:rus_x_preferred":[
        "\u041d\u0430\u043c\u0435\u0441\u043a\u043e\u0432\u043e"
    ],
    "wof:name":"Nameskovo",
    "wof:placetype":"locality"
},
  "geometry": {"coordinates":[36.45333,57.56083],"type":"Point"}
}