{
  "type": "Feature",
  "properties": {
    "gn:admin1_code":"29",
    "gn:asciiname":"Kopylovo",
    "gn:country_code":"RU",
    "gn:dem":158,
    "gn:feature_class":"P",
    "gn:feature_code":"PPL",
    "gn:name":"Kopylovo",
    "gn:population":0,
    "gn:timezone":"Asia/Novokuznetsk",
    "iso:country":"RU",
    "name:rus_x_preferred":[
        "\u041a\u043e\u043f\u044b\u043b\u043e\u0432\u043e"
    ],
    "wof:name":"Kopylovo",
    "wof:placetype":"locality"
},
  "geometry": {"coordinates":[85.4691,55.6571],"type":"Point"}
}