{
  "type": "Feature",
  "properties": {
    "gn:admin1_code":"60",
    "gn:asciiname":"Selyugino",
    "gn:country_code":"RU",
    "gn:dem":43,
    "gn:feature_class":"P",
    "gn:feature_code":"PPL",
    "gn:name":"Selyugino",
    "gn:population":0,
    "gn:timezone":"Europe/Moscow",
    "iso:country":"RU",
    "name:rus_x_preferred":[
        "\u0421\u0435\u043b\u044e\u0433\u0438\u043d\u043e"
    ],
    "wof:name":"Selyugino",
    "wof:placetype":"locality"
},
  "geometry": {"coordinates":[28.3652,57.6916],"type":"Point"}
}