{
  "type": "Feature",
  "properties": {
    "gn:admin1_code":"47",
    "gn:asciiname":"Dvoriki",
    "gn:country_code":"RU",
    "gn:dem":175,
    "gn:feature_class":"P",
    "gn:feature_code":"PPL",
    "gn:name":"Dvoriki",
    "gn:population":0,
    "gn:timezone":"Europe/Moscow",
    "iso:country":"RU",
    "name:rus_x_preferred":[
        "\u0414\u0432\u043e\u0440\u0438\u043a\u0438"
    ],
    "name:und_x_variant":[
        "Pochtovoye Otdeleniye Dvoriki",
        "Dvoriki",
        "\u0414\u0432\u043e\u0440\u0438\u043a\u0438"
    ],
    "wof:name":"Dvoriki",
    "wof:placetype":"locality"
},
  "geometry": {"coordinates":[38.59996,55.02505],"type":"Point"}
}