{
  "type": "Feature",
  "properties": {
    "gn:admin1_code":"15",
    "gn:asciiname":"Chaunskaya",
    "gn:cc2":"RU",
    "gn:country_code":"RU",
    "gn:dem":3,
    "gn:feature_class":"P",
    "gn:feature_code":"PPL",
    "gn:name":"Chaunskaya",
    "gn:population":0,
    "gn:timezone":"Asia/Anadyr",
    "iso:country":"RU",
    "name:rus_x_preferred":[
        "\u0427\u0430\u0443\u043d\u0441\u043a\u0430\u044f"
    ],
    "name:und_x_variant":[
        "Faktoriya Chaunskaya",
        "Chaunskaya"
    ],
    "wof:name":"Chaunskaya",
    "wof:placetype":"locality"
},
  "geometry": {"coordinates":[170.61667,68.88333],"type":"Point"}
}