{
  "type": "Feature",
  "properties": {
    "gn:admin1_code":"85",
    "gn:asciiname":"Pyatachok",
    "gn:country_code":"RU",
    "gn:dem":124,
    "gn:feature_class":"P",
    "gn:feature_code":"PPL",
    "gn:name":"Pyatachok",
    "gn:population":0,
    "gn:timezone":"Europe/Moscow",
    "iso:country":"RU",
    "name:rus_x_preferred":[
        "\u041f\u044f\u0442\u0430\u0447\u043e\u043a"
    ],
    "wof:name":"Pyatachok",
    "wof:placetype":"locality"
},
  "geometry": {"coordinates":[38.35018,59.86118],"type":"Point"}
}