{
  "type": "Feature",
  "properties": {
    "gn:admin1_code":"90",
    "gn:asciiname":"Grigorovo",
    "gn:country_code":"RU",
    "gn:dem":124,
    "gn:feature_class":"P",
    "gn:feature_code":"PPL",
    "gn:name":"Grigorovo",
    "gn:population":0,
    "gn:timezone":"Asia/Yekaterinburg",
    "iso:country":"RU",
    "name:eng_x_preferred":[
        "Grigorova"
    ],
    "name:nor_x_preferred":[
        "Grigorova"
    ],
    "name:rus_x_preferred":[
        "\u0413\u0440\u0438\u0433\u043e\u0440\u043e\u0432\u043e"
    ],
    "name:und_x_variant":[
        "Grigor\u2019yevka",
        "Grigorovo"
    ],
    "wof:name":"Grigorovo",
    "wof:placetype":"locality"
},
  "geometry": {"coordinates":[56.5928,59.7012],"type":"Point"}
}