{
  "type": "Feature",
  "properties": {
    "gn:admin1_code":"33",
    "gn:asciiname":"Kyvyrla",
    "gn:country_code":"RU",
    "gn:dem":103,
    "gn:feature_class":"P",
    "gn:feature_code":"PPL",
    "gn:name":"Kyvyrla",
    "gn:population":0,
    "gn:timezone":"Europe/Kirov",
    "iso:country":"RU",
    "name:rus_x_preferred":[
        "\u041a\u044b\u0432\u044b\u0440\u043b\u0430"
    ],
    "wof:name":"Kyvyrla",
    "wof:placetype":"locality"
},
  "geometry": {"coordinates":[47.9448,57.7602],"type":"Point"}
}