{
  "type": "Feature",
  "properties": {
    "gn:admin1_code":"23",
    "gn:asciiname":"Yakovlevka",
    "gn:country_code":"RU",
    "gn:dem":197,
    "gn:feature_class":"P",
    "gn:feature_code":"PPL",
    "gn:name":"Yakovlevka",
    "gn:population":0,
    "gn:timezone":"Europe/Kaliningrad",
    "iso:country":"RU",
    "wof:name":"Yakovlevka",
    "wof:placetype":"locality"
},
  "geometry": {"coordinates":[22.67694,54.3675],"type":"Point"}
}