{
  "type": "Feature",
  "properties": {
    "gn:admin1_code":"70",
    "gn:asciiname":"Vodnyy",
    "gn:country_code":"RU",
    "gn:dem":118,
    "gn:feature_class":"P",
    "gn:feature_code":"PPL",
    "gn:name":"Vodnyy",
    "gn:population":0,
    "gn:timezone":"Europe/Moscow",
    "iso:country":"RU",
    "name:eng_x_preferred":[
        "Vodnyy"
    ],
    "name:nor_x_preferred":[
        "Vodnyj"
    ],
    "name:rus_x_preferred":[
        "\u0412\u043e\u0434\u043d\u044b\u0439"
    ],
    "wof:name":"Vodnyy",
    "wof:placetype":"locality"
},
  "geometry": {"coordinates":[42.78167,45.78333],"type":"Point"}
}