{
  "type": "Feature",
  "properties": {
    "gn:admin1_code":"52.0",
    "gn:asciiname":"Chernigovo",
    "gn:country_code":"RU",
    "gn:dem":90,
    "gn:feature_class":"P",
    "gn:feature_code":"PPL",
    "gn:name":"Chernigovo",
    "gn:population":0,
    "gn:timezone":"Europe/Moscow",
    "iso:country":"RU",
    "name:bul_x_preferred":[
        "\u0427\u0435\u0440\u043d\u0438\u0433\u043e\u0432\u043e"
    ],
    "name:fas_x_preferred":[
        "\u0686\u0631\u0646\u06cc\u06af\u0648\u0648\u0648"
    ],
    "name:kat_x_preferred":[
        "\u10e9\u10d4\u10e0\u10dc\u10d8\u10d2\u10dd\u10d5\u10dd"
    ],
    "name:ron_x_preferred":[
        "Cernigovo"
    ],
    "name:rus_x_preferred":[
        "\u0427\u0435\u0440\u043d\u0438\u0433\u043e\u0432\u043e"
    ],
    "name:ukr_x_preferred":[
        "\u0427\u0435\u0440\u043d\u0438\u0433\u043e\u0432\u043e"
    ],
    "name:und_x_variant":[
        "\u0427\u0435\u0440\u043d\u0438\u0433\u043e\u0432\u043e"
    ],
    "wof:name":"Chernigovo",
    "wof:placetype":"locality"
},
  "geometry": {"coordinates":[30.93333,57.71666999999999],"type":"Point"}
}