{
  "type": "Feature",
  "properties": {
    "gn:admin1_code":"85",
    "gn:asciiname":"Repino",
    "gn:country_code":"RU",
    "gn:dem":117,
    "gn:feature_class":"P",
    "gn:feature_code":"PPL",
    "gn:name":"Repino",
    "gn:population":0,
    "gn:timezone":"Europe/Moscow",
    "iso:country":"RU",
    "name:rus_x_preferred":[
        "\u0420\u0435\u043f\u0438\u043d\u043e"
    ],
    "name:und_x_variant":[
        "\u0420\u0435\u043f\u0438\u043d\u043e"
    ],
    "wof:name":"Repino",
    "wof:placetype":"locality"
},
  "geometry": {"coordinates":[46.1593,60.8325],"type":"Point"}
}