{
  "type": "Feature",
  "properties": {
    "gn:admin1_code":"51",
    "gn:asciiname":"Shutilovo",
    "gn:country_code":"RU",
    "gn:dem":140,
    "gn:feature_class":"P",
    "gn:feature_code":"PPL",
    "gn:name":"Shutilovo",
    "gn:population":0,
    "gn:timezone":"Europe/Moscow",
    "iso:country":"RU",
    "name:eng_x_preferred":[
        "Shutilovo"
    ],
    "name:nor_x_preferred":[
        "Sjutilovo"
    ],
    "name:rus_x_preferred":[
        "\u0428\u0443\u0442\u0438\u043b\u043e\u0432\u043e"
    ],
    "wof:name":"Shutilovo",
    "wof:placetype":"locality"
},
  "geometry": {"coordinates":[44.12073,54.86239000000001],"type":"Point"}
}