{
  "type": "Feature",
  "properties": {
    "gn:admin1_code":"52.0",
    "gn:asciiname":"Bolon'ye",
    "gn:country_code":"RU",
    "gn:dem":142,
    "gn:feature_class":"P",
    "gn:feature_code":"PPL",
    "gn:name":"Bolon\u2019ye",
    "gn:population":0,
    "gn:timezone":"Europe/Moscow",
    "iso:country":"RU",
    "name:eng_x_preferred":[
        "Bolon'ye"
    ],
    "name:nor_x_preferred":[
        "Bolonje"
    ],
    "name:rus_x_preferred":[
        "\u0411\u043e\u043b\u043e\u043d\u044c\u0435"
    ],
    "name:und_x_variant":[
        "Bolon\u2019ya",
        "\u0411\u043e\u043b\u043e\u043d\u044c\u0435",
        "Bolon\u2019ye"
    ],
    "wof:name":"Bolon'ye",
    "wof:placetype":"locality"
},
  "geometry": {"coordinates":[34.53142,58.24519],"type":"Point"}
}