{
  "type": "Feature",
  "properties": {
    "gn:admin1_code":"80",
    "gn:asciiname":"Markelovo",
    "gn:country_code":"RU",
    "gn:dem":151,
    "gn:feature_class":"P",
    "gn:feature_code":"PPL",
    "gn:name":"Markelovo",
    "gn:population":0,
    "gn:timezone":"Europe/Samara",
    "iso:country":"RU",
    "name:rus_x_preferred":[
        "\u041c\u0430\u0440\u043a\u0435\u043b\u043e\u0432\u043e"
    ],
    "name:und_x_variant":[
        "\u041c\u0430\u0440\u043a\u0435\u043b\u043e\u0432\u043e"
    ],
    "wof:name":"Markelovo",
    "wof:placetype":"locality"
},
  "geometry": {"coordinates":[51.76136,57.1669],"type":"Point"}
}