{
  "type": "Feature",
  "properties": {
    "gn:admin1_code":"25",
    "gn:asciiname":"Alimovskiy",
    "gn:country_code":"RU",
    "gn:dem":197,
    "gn:feature_class":"P",
    "gn:feature_code":"PPL",
    "gn:name":"Alimovskiy",
    "gn:population":0,
    "gn:timezone":"Europe/Moscow",
    "iso:country":"RU",
    "name:nor_x_preferred":[
        "Alimovskij"
    ],
    "name:rus_x_preferred":[
        "\u0410\u043b\u0438\u043c\u043e\u0432\u0441\u043a\u0438\u0439"
    ],
    "wof:name":"Alimovskiy",
    "wof:placetype":"locality"
},
  "geometry": {"coordinates":[35.82861,53.92222],"type":"Point"}
}