{
  "type": "Feature",
  "properties": {
    "gn:admin1_code":"43",
    "gn:asciiname":"Lapotok",
    "gn:country_code":"RU",
    "gn:dem":149,
    "gn:feature_class":"P",
    "gn:feature_code":"PPL",
    "gn:name":"Lapotok",
    "gn:population":0,
    "gn:timezone":"Europe/Moscow",
    "iso:country":"RU",
    "name:rus_x_preferred":[
        "\u041b\u0430\u043f\u043e\u0442\u043e\u043a"
    ],
    "name:und_x_variant":[
        "Lapotki",
        "Lapotok"
    ],
    "wof:name":"Lapotok",
    "wof:placetype":"locality"
},
  "geometry": {"coordinates":[39.96161,53.42553],"type":"Point"}
}