{
  "type": "Feature",
  "properties": {
    "gn:admin1_code":"60",
    "gn:asciiname":"Mikhalkino",
    "gn:country_code":"RU",
    "gn:dem":70,
    "gn:feature_class":"P",
    "gn:feature_code":"PPL",
    "gn:name":"Mikhalkino",
    "gn:population":0,
    "gn:timezone":"Europe/Moscow",
    "iso:country":"RU",
    "name:rus_x_preferred":[
        "\u041c\u0438\u0445\u0430\u043b\u043a\u0438\u043d\u043e"
    ],
    "wof:name":"Mikhalkino",
    "wof:placetype":"locality"
},
  "geometry": {"coordinates":[28.9028,57.5353],"type":"Point"}
}