{
  "type": "Feature",
  "properties": {
    "gn:admin1_code":"38",
    "gn:asciiname":"Mefodiyevka",
    "gn:cc2":"RU",
    "gn:country_code":"RU",
    "gn:dem":167,
    "gn:feature_class":"P",
    "gn:feature_code":"PPL",
    "gn:name":"Mefodiyevka",
    "gn:population":0,
    "gn:timezone":"Europe/Moscow",
    "iso:country":"RU",
    "name:rus_x_preferred":[
        "\u041c\u0435\u0444\u043e\u0434\u0438\u0435\u0432\u043a\u0430"
    ],
    "name:und_x_variant":[
        "Mefodiyevskiy",
        "Mefodiyevka",
        "\u041c\u0435\u0444\u043e\u0434\u0438\u0435\u0432\u043a\u0430"
    ],
    "wof:name":"Mefodiyevka",
    "wof:placetype":"locality"
},
  "geometry": {"coordinates":[37.78333,44.75],"type":"Point"}
}