{
  "type": "Feature",
  "properties": {
    "gn:admin1_code":"25",
    "gn:asciiname":"Pozdnyakovo",
    "gn:country_code":"RU",
    "gn:dem":208,
    "gn:feature_class":"P",
    "gn:feature_code":"PPL",
    "gn:name":"Pozdnyakovo",
    "gn:population":0,
    "gn:timezone":"Europe/Moscow",
    "iso:country":"RU",
    "name:eng_x_preferred":[
        "Pozdnyakovo"
    ],
    "name:nor_x_preferred":[
        "Pozdnjakovo"
    ],
    "name:rus_x_preferred":[
        "\u041f\u043e\u0437\u0434\u043d\u044f\u043a\u043e\u0432\u043e"
    ],
    "name:und_x_variant":[
        "Poznyakovo",
        "\u041f\u043e\u0437\u0434\u043d\u044f\u043a\u043e\u0432\u043e",
        "Pozdnyakovo"
    ],
    "wof:name":"Pozdnyakovo",
    "wof:placetype":"locality"
},
  "geometry": {"coordinates":[35.89153,53.679],"type":"Point"}
}