{
  "type": "Feature",
  "properties": {
    "gn:admin1_code":"9",
    "gn:asciiname":"Yur'yevka",
    "gn:country_code":"RU",
    "gn:dem":180,
    "gn:feature_class":"P",
    "gn:feature_code":"PPL",
    "gn:name":"Yur\u2019yevka",
    "gn:population":0,
    "gn:timezone":"Europe/Moscow",
    "iso:country":"RU",
    "wof:name":"Yur'yevka",
    "wof:placetype":"locality"
},
  "geometry": {"coordinates":[37.90972,50.93167],"type":"Point"}
}