{
  "type": "Feature",
  "properties": {
    "gn:admin1_code":"83",
    "gn:asciiname":"Sanchugovo",
    "gn:country_code":"RU",
    "gn:dem":127,
    "gn:feature_class":"P",
    "gn:feature_code":"PPL",
    "gn:name":"Sanchugovo",
    "gn:population":0,
    "gn:timezone":"Europe/Moscow",
    "iso:country":"RU",
    "name:rus_x_preferred":[
        "\u0421\u0430\u043d\u0447\u0443\u0433\u043e\u0432\u043e"
    ],
    "name:und_x_variant":[
        "\u0421\u0430\u043d\u0447\u0443\u0433\u043e\u0432\u043e"
    ],
    "wof:name":"Sanchugovo",
    "wof:placetype":"locality"
},
  "geometry": {"coordinates":[41.6692,55.6974],"type":"Point"}
}