{
  "type": "Feature",
  "properties": {
    "gn:admin1_code":"37",
    "gn:asciiname":"Lyskovo",
    "gn:country_code":"RU",
    "gn:dem":171,
    "gn:feature_class":"P",
    "gn:feature_code":"PPL",
    "gn:name":"Lyskovo",
    "gn:population":0,
    "gn:timezone":"Europe/Moscow",
    "iso:country":"RU",
    "name:rus_x_preferred":[
        "\u041b\u044b\u0441\u043a\u043e\u0432\u043e"
    ],
    "name:und_x_variant":[
        "\u041b\u044b\u0441\u043a\u043e\u0432\u043e"
    ],
    "wof:name":"Lyskovo",
    "wof:placetype":"locality"
},
  "geometry": {"coordinates":[42.3528,58.4562],"type":"Point"}
}