{
  "type": "Feature",
  "properties": {
    "gn:admin1_code":"80",
    "gn:asciiname":"Orekhova",
    "gn:country_code":"RU",
    "gn:dem":151,
    "gn:feature_class":"P",
    "gn:feature_code":"PPL",
    "gn:name":"Orekhova",
    "gn:population":0,
    "gn:timezone":"Europe/Samara",
    "iso:country":"RU",
    "name:rus_x_preferred":[
        "\u041e\u0440\u0435\u0445\u043e\u0432\u0430"
    ],
    "name:und_x_variant":[
        "\u041e\u0440\u0435\u0445\u043e\u0432\u0430"
    ],
    "wof:name":"Orekhova",
    "wof:placetype":"locality"
},
  "geometry": {"coordinates":[53.61666999999999,56.06667],"type":"Point"}
}