{
  "type": "Feature",
  "properties": {
    "gn:admin1_code":"33",
    "gn:asciiname":"Nagoryana",
    "gn:country_code":"RU",
    "gn:dem":139,
    "gn:feature_class":"P",
    "gn:feature_code":"PPL",
    "gn:name":"Nagoryana",
    "gn:population":0,
    "gn:timezone":"Europe/Kirov",
    "iso:country":"RU",
    "name:rus_x_preferred":[
        "\u041d\u0430\u0433\u043e\u0440\u044f\u043d\u0430"
    ],
    "name:und_x_variant":[
        "\u041d\u0430\u0433\u043e\u0440\u044f\u043d\u0430"
    ],
    "wof:name":"Nagoryana",
    "wof:placetype":"locality"
},
  "geometry": {"coordinates":[48.6984,58.20578],"type":"Point"}
}