{
  "type": "Feature",
  "properties": {
    "gn:admin1_code":"60",
    "gn:asciiname":"Dulevo",
    "gn:country_code":"RU",
    "gn:dem":59,
    "gn:feature_class":"P",
    "gn:feature_code":"PPL",
    "gn:name":"Dul\u00ebvo",
    "gn:population":0,
    "gn:timezone":"Europe/Moscow",
    "iso:country":"RU",
    "name:rus_x_preferred":[
        "\u0414\u0443\u043b\u0451\u0432\u043e"
    ],
    "name:und_x_variant":[
        "Dul\u00ebvo",
        "\u0414\u0443\u043b\u0451\u0432\u043e"
    ],
    "wof:name":"Dulevo",
    "wof:placetype":"locality"
},
  "geometry": {"coordinates":[28.0031,58.797],"type":"Point"}
}