{
  "type": "Feature",
  "properties": {
    "gn:admin1_code":"42.0",
    "gn:asciiname":"Sista",
    "gn:country_code":"RU",
    "gn:dem":109,
    "gn:feature_class":"P",
    "gn:feature_code":"PPL",
    "gn:name":"Sista",
    "gn:population":0,
    "gn:timezone":"Europe/Moscow",
    "iso:country":"RU",
    "name:fin_x_preferred":[
        "Siesta"
    ],
    "name:fra_x_preferred":[
        "Sista"
    ],
    "name:nor_x_preferred":[
        "Sista"
    ],
    "name:rus_x_preferred":[
        "\u0421\u0438\u0441\u0442\u0430"
    ],
    "name:und_x_variant":[
        "Bol\u2019shaya Sista",
        "Sista"
    ],
    "wof:name":"Sista",
    "wof:placetype":"locality"
},
  "geometry": {"coordinates":[29.03291,59.60481],"type":"Point"}
}