{
  "type": "Feature",
  "properties": {
    "gn:admin1_code":"73",
    "gn:asciiname":"Staraya Salaus'",
    "gn:country_code":"RU",
    "gn:dem":88,
    "gn:feature_class":"P",
    "gn:feature_code":"PPL",
    "gn:name":"Staraya Salaus\u2019",
    "gn:population":0,
    "gn:timezone":"Europe/Moscow",
    "iso:country":"RU",
    "name:eng_x_preferred":[
        "Staraya Salaus'"
    ],
    "name:nor_x_preferred":[
        "Star.Salaus"
    ],
    "name:rus_x_preferred":[
        "\u0421\u0442\u0430\u0440.\u0421\u0430\u043b\u0430\u0443\u0441\u044c"
    ],
    "name:rus_x_variant":[
        "\u0421\u0442\u0430\u0440\u0430\u044f \u0421\u0430\u043b\u0430\u0443\u0441\u044c"
    ],
    "name:und_x_variant":[
        "Salaus\u2019",
        "Staraya Salans\u2019",
        "Staraya Salaus\u2019",
        "\u0421\u0442\u0430\u0440\u0430\u044f \u0421\u0430\u043b\u0430\u0443\u0441\u044c"
    ],
    "wof:name":"Staraya Salaus'",
    "wof:placetype":"locality"
},
  "geometry": {"coordinates":[50.3253,56.3656],"type":"Point"}
}