{
  "type": "Feature",
  "properties": {
    "gn:admin1_code":"6",
    "gn:asciiname":"Verkhniy Konets",
    "gn:country_code":"RU",
    "gn:dem":75,
    "gn:feature_class":"P",
    "gn:feature_code":"PPL",
    "gn:name":"Verkhniy Konets",
    "gn:population":0,
    "gn:timezone":"Europe/Moscow",
    "iso:country":"RU",
    "name:rus_x_preferred":[
        "\u0412\u0435\u0440\u0445\u043d\u0438\u0439 K\u043e\u043d\u0435\u0446"
    ],
    "wof:name":"Verkhniy Konets",
    "wof:placetype":"locality"
},
  "geometry": {"coordinates":[48.5504,61.9519],"type":"Point"}
}