{
  "type": "Feature",
  "properties": {
    "gn:admin1_code":"61",
    "gn:asciiname":"Nizhnezundov",
    "gn:country_code":"RU",
    "gn:dem":108,
    "gn:feature_class":"P",
    "gn:feature_code":"PPL",
    "gn:name":"Nizhnezundov",
    "gn:population":0,
    "gn:timezone":"Europe/Moscow",
    "iso:country":"RU",
    "name:rus_x_preferred":[
        "\u041d\u0438\u0436\u043d\u0435\u0437\u0443\u043d\u0434\u043e\u0432"
    ],
    "wof:name":"Nizhnezundov",
    "wof:placetype":"locality"
},
  "geometry": {"coordinates":[42.2378,46.8136],"type":"Point"}
}