{
  "type": "Feature",
  "properties": {
    "gn:admin1_code":"61",
    "gn:asciiname":"Peschanokopskiy",
    "gn:country_code":"RU",
    "gn:dem":64,
    "gn:feature_class":"P",
    "gn:feature_code":"PPL",
    "gn:name":"Peschanokopskiy",
    "gn:population":0,
    "gn:timezone":"Europe/Moscow",
    "iso:country":"RU",
    "name:rus_x_preferred":[
        "\u041f\u0435\u0441\u0447\u0430\u043d\u043e\u043a\u043e\u043f\u0441\u043a\u0438\u0439"
    ],
    "name:und_x_variant":[
        "\u041f\u0435\u0441\u0447\u0430\u043d\u043e\u043a\u043e\u043f\u0441\u043a\u0438\u0439"
    ],
    "wof:name":"Peschanokopskiy",
    "wof:placetype":"locality"
},
  "geometry": {"coordinates":[41.07861,46.62167],"type":"Point"}
}