{
  "type": "Feature",
  "properties": {
    "gn:admin1_code":"33.0",
    "gn:asciiname":"Bobino",
    "gn:country_code":"RU",
    "gn:dem":152,
    "gn:feature_class":"P",
    "gn:feature_code":"PPL",
    "gn:name":"Bobino",
    "gn:population":0,
    "gn:timezone":"Europe/Kirov",
    "iso:country":"RU",
    "name:deu_x_preferred":[
        "Bobino"
    ],
    "name:eng_x_preferred":[
        "Bobino"
    ],
    "name:fas_x_preferred":[
        "\u0628\u0648\u0628\u06cc\u0646\u0648"
    ],
    "name:fin_x_preferred":[
        "Bobino"
    ],
    "name:fra_x_preferred":[
        "Bobino"
    ],
    "name:ita_x_preferred":[
        "Bobino"
    ],
    "name:mkd_x_preferred":[
        "\u0411\u043e\u0431\u0438\u043d\u043e"
    ],
    "name:nor_x_preferred":[
        "Bobino"
    ],
    "name:rus_x_preferred":[
        "\u0411\u043e\u0431\u0438\u043d\u043e"
    ],
    "name:ukr_x_preferred":[
        "\u0411\u043e\u0431\u0456\u043d\u043e"
    ],
    "name:und_x_variant":[
        "Babino"
    ],
    "wof:name":"Bobino",
    "wof:placetype":"locality"
},
  "geometry": {"coordinates":[49.76332,58.7028],"type":"Point"}
}