{
  "type": "Feature",
  "properties": {
    "gn:admin1_code":"54",
    "gn:asciiname":"Baydalin",
    "gn:country_code":"RU",
    "gn:dem":98,
    "gn:feature_class":"P",
    "gn:feature_code":"PPL",
    "gn:name":"Baydalin",
    "gn:population":0,
    "gn:timezone":"Asia/Omsk",
    "iso:country":"RU",
    "name:eng_x_preferred":[
        "Baydalin"
    ],
    "name:nor_x_preferred":[
        "Bajdalin"
    ],
    "name:rus_x_preferred":[
        "\u0411\u0430\u0439\u0434\u0430\u043b\u0438\u043d"
    ],
    "name:und_x_variant":[
        "\u0411\u0430\u0439\u0434\u0430\u043b\u0438\u043d",
        "Baydalin"
    ],
    "wof:name":"Baydalin",
    "wof:placetype":"locality"
},
  "geometry": {"coordinates":[74.26165999999998,54.39346],"type":"Point"}
}