{
  "type": "Feature",
  "properties": {
    "gn:admin1_code":"69",
    "gn:asciiname":"Karpishchevo",
    "gn:country_code":"RU",
    "gn:dem":189,
    "gn:feature_class":"P",
    "gn:feature_code":"PPL",
    "gn:name":"Karpishchevo",
    "gn:population":0,
    "gn:timezone":"Europe/Moscow",
    "iso:country":"RU",
    "name:rus_x_preferred":[
        "\u041a\u0430\u0440\u043f\u0438\u0449\u0435\u0432\u043e"
    ],
    "name:und_x_variant":[
        "Karpishcheva",
        "Karpishchevo",
        "\u041a\u0430\u0440\u043f\u0438\u0449\u0435\u0432\u043e"
    ],
    "wof:name":"Karpishchevo",
    "wof:placetype":"locality"
},
  "geometry": {"coordinates":[34.99509,55.04142],"type":"Point"}
}