{
  "type": "Feature",
  "properties": {
    "gn:admin1_code":"9.0",
    "gn:asciiname":"Prilepy",
    "gn:country_code":"RU",
    "gn:dem":130,
    "gn:feature_class":"P",
    "gn:feature_code":"PPL",
    "gn:name":"Prilepy",
    "gn:population":0,
    "gn:timezone":"Europe/Moscow",
    "iso:country":"RU",
    "name:rus_x_preferred":[
        "\u041f\u0440\u0438\u043b\u0435\u043f\u044b"
    ],
    "wof:name":"Prilepy",
    "wof:placetype":"locality"
},
  "geometry": {"coordinates":[38.3234,50.7519],"type":"Point"}
}