{
  "type": "Feature",
  "properties": {
    "gn:country":"RU",
    "gn:fcode":"PPL",
    "gn:pop":7622,
    "iso:country":"RU",
    "name:cat_x_preferred":[
        "Vostotxni"
    ],
    "name:ceb_x_preferred":[
        "\u0412\u043e\u0441\u0442\u043e\u0447\u043d\u044b\u0439"
    ],
    "name:deu_x_preferred":[
        "Wostotschny"
    ],
    "name:eng_x_preferred":[
        "Vostochnyy"
    ],
    "name:ita_x_preferred":[
        "Vosto\u010dnyj"
    ],
    "name:jpn_x_preferred":[
        "\u30dc\u30b9\u30c8\u30c1\u30cc\u30a4"
    ],
    "name:nor_x_preferred":[
        "Vostotsjnyj"
    ],
    "name:rus_x_preferred":[
        "\u0412\u043e\u0441\u0442\u043e\u0447\u043d\u044b\u0439"
    ],
    "name:sco_x_preferred":[
        "Vostochny"
    ],
    "name:spa_x_preferred":[
        "Vostochni"
    ],
    "name:ukr_x_preferred":[
        "\u0412\u043e\u0441\u0442\u043e\u0447\u043d\u0438\u0439"
    ],
    "name:unk_x_variant":[
        "Filippovka"
    ],
    "qs:name":"Vostochnyy",
    "qs:photos_9r":0,
    "qs:photos_sr":0,
    "qs:pop_sr":"5",
    "wd:wordcount":64,
    "wof:name":"Vostochnyy",
    "wof:placetype":"locality",
    "wof:population":7622
},
  "geometry": {"coordinates":[52.24513,58.78811],"type":"Point"}
}