{
  "type": "Feature",
  "properties": {
    "gn:admin1_code":"5",
    "gn:asciiname":"Yasnyy",
    "gn:country_code":"RU",
    "gn:dem":643,
    "gn:feature_class":"P",
    "gn:feature_code":"PPL",
    "gn:name":"Yasnyy",
    "gn:population":0,
    "gn:timezone":"Asia/Yakutsk",
    "iso:country":"RU",
    "wof:name":"Yasnyy",
    "wof:placetype":"locality"
},
  "geometry": {"coordinates":[127.01667,55.53333000000001],"type":"Point"}
}