{
  "type": "Feature",
  "properties": {
    "gn:admin1_code":"16",
    "gn:asciiname":"Shorkino",
    "gn:country_code":"RU",
    "gn:dem":120,
    "gn:feature_class":"P",
    "gn:feature_code":"PPL",
    "gn:name":"Shorkino",
    "gn:population":0,
    "gn:timezone":"Europe/Moscow",
    "iso:country":"RU",
    "name:rus_x_preferred":[
        "\u0428\u043e\u0440\u043a\u0438\u043d\u043e"
    ],
    "name:und_x_variant":[
        "\u0428\u043e\u0440\u043a\u0438\u043d\u043e"
    ],
    "wof:name":"Shorkino",
    "wof:placetype":"locality"
},
  "geometry": {"coordinates":[46.44757,55.94599],"type":"Point"}
}