{
  "type": "Feature",
  "properties": {
    "gn:admin1_code":"60",
    "gn:asciiname":"Zaozer'ye",
    "gn:country_code":"RU",
    "gn:dem":59,
    "gn:feature_class":"P",
    "gn:feature_code":"PPL",
    "gn:name":"Zaoz\u00ebr\u2019ye",
    "gn:population":0,
    "gn:timezone":"Europe/Moscow",
    "iso:country":"RU",
    "name:rus_x_preferred":[
        "\u0417\u0430\u043e\u0437\u0451\u0440\u044c\u0435"
    ],
    "name:und_x_variant":[
        "Zaoz\u00ebr\u2019ye"
    ],
    "wof:name":"Zaozer'ye",
    "wof:placetype":"locality"
},
  "geometry": {"coordinates":[28.6047,58.7163],"type":"Point"}
}