{
  "type": "Feature",
  "properties": {
    "gn:admin1_code":"10",
    "gn:asciiname":"Merin Les",
    "gn:country_code":"RU",
    "gn:dem":188,
    "gn:feature_class":"P",
    "gn:feature_code":"PPL",
    "gn:name":"Merin Les",
    "gn:population":0,
    "gn:timezone":"Europe/Moscow",
    "iso:country":"RU",
    "name:rus_x_preferred":[
        "\u041c\u0435\u0440\u0438\u043d \u041b\u0435\u0441"
    ],
    "name:und_x_variant":[
        "\u041c\u0435\u0440\u0438\u043d \u041b\u0435\u0441"
    ],
    "wof:name":"Merin Les",
    "wof:placetype":"locality"
},
  "geometry": {"coordinates":[33.4919,52.563],"type":"Point"}
}