{
  "type": "Feature",
  "properties": {
    "gn:admin1_code":"10",
    "gn:asciiname":"Korinevka",
    "gn:country_code":"RU",
    "gn:dem":196,
    "gn:feature_class":"P",
    "gn:feature_code":"PPL",
    "gn:name":"Korin\u00ebvka",
    "gn:population":0,
    "gn:timezone":"Europe/Moscow",
    "iso:country":"RU",
    "name:rus_x_preferred":[
        "\u041a\u043e\u0440\u0438\u043d\u0451\u0432\u043a\u0430"
    ],
    "name:und_x_variant":[
        "Korin\u00ebvka",
        "\u041a\u043e\u0440\u0438\u043d\u0451\u0432\u043a\u0430"
    ],
    "wof:name":"Korinevka",
    "wof:placetype":"locality"
},
  "geometry": {"coordinates":[34.26722,52.94278000000001],"type":"Point"}
}