{
  "type": "Feature",
  "properties": {
    "gn:admin1_code":"8",
    "gn:asciiname":"Khlebodarovka",
    "gn:country_code":"RU",
    "gn:dem":207,
    "gn:feature_class":"P",
    "gn:feature_code":"PPL",
    "gn:name":"Khlebodarovka",
    "gn:population":0,
    "gn:timezone":"Asia/Yekaterinburg",
    "iso:country":"RU",
    "name:bak_x_preferred":[
        "\u0425\u043b\u0435\u0431\u043e\u0434\u0430\u0440\u043e\u0432\u043a\u0430"
    ],
    "name:che_x_preferred":[
        "\u0425\u043b\u0435\u0431\u043e\u0434\u0430\u0440\u043e\u0432\u043a\u0430"
    ],
    "name:eng_x_preferred":[
        "Khlebodarovka"
    ],
    "name:hye_x_preferred":[
        "\u053d\u056c\u0565\u0562\u0578\u0564\u0561\u0580\u0578\u057e\u056f\u0561"
    ],
    "name:kaz_x_preferred":[
        "\u0425\u043b\u0435\u0431\u043e\u0434\u0430\u0440\u043e\u0432\u043a\u0430"
    ],
    "name:kir_x_preferred":[
        "\u0425\u043b\u0435\u0431\u043e\u0434\u0430\u0440\u043e\u0432\u043a\u0430"
    ],
    "name:nor_x_preferred":[
        "Khlebodarovka"
    ],
    "name:rus_x_preferred":[
        "\u0425\u043b\u0435\u0431\u043e\u0434\u0430\u0440\u043e\u0432\u043a\u0430"
    ],
    "name:tat_x_preferred":[
        "\u0425\u043b\u0435\u0431\u043e\u0434\u0430\u0440\u043e\u0432\u043a\u0430"
    ],
    "name:und_x_variant":[
        "\u0425\u043b\u0435\u0431\u043e\u0434\u0430\u0440\u043e\u0432\u043a\u0430",
        "Khlebodarovka"
    ],
    "wof:name":"Khlebodarovka",
    "wof:placetype":"locality"
},
  "geometry": {"coordinates":[56.3266,53.0626],"type":"Point"}
}