{
  "type": "Feature",
  "properties": {
    "gn:admin1_code":"51",
    "gn:asciiname":"Pogulyayki",
    "gn:country_code":"RU",
    "gn:dem":110,
    "gn:feature_class":"P",
    "gn:feature_code":"PPL",
    "gn:name":"Pogulyayki",
    "gn:population":0,
    "gn:timezone":"Europe/Moscow",
    "iso:country":"RU",
    "name:nor_x_preferred":[
        "Poguljajki"
    ],
    "name:rus_x_preferred":[
        "\u041f\u043e\u0433\u0443\u043b\u044f\u0439\u043a\u0438"
    ],
    "wof:name":"Pogulyayki",
    "wof:placetype":"locality"
},
  "geometry": {"coordinates":[43.73077,56.65501],"type":"Point"}
}