{
  "type": "Feature",
  "properties": {
    "gn:admin1_code":"40",
    "gn:asciiname":"Simakova",
    "gn:country_code":"RU",
    "gn:dem":97,
    "gn:feature_class":"P",
    "gn:feature_code":"PPL",
    "gn:name":"Simakova",
    "gn:population":0,
    "gn:timezone":"Asia/Yekaterinburg",
    "iso:country":"RU",
    "name:rus_x_preferred":[
        "\u0421\u0438\u043c\u0430\u043a\u043e\u0432\u0430"
    ],
    "wof:name":"Simakova",
    "wof:placetype":"locality"
},
  "geometry": {"coordinates":[63.68972,55.94444],"type":"Point"}
}