{
  "type": "Feature",
  "properties": {
    "gn:admin1_code":"30",
    "gn:asciiname":"Kol' Vtoroy",
    "gn:country_code":"RU",
    "gn:dem":3,
    "gn:feature_class":"P",
    "gn:feature_code":"PPL",
    "gn:name":"Kol\u2019 Vtoroy",
    "gn:population":0,
    "gn:timezone":"Asia/Vladivostok",
    "iso:country":"RU",
    "name:rus_x_preferred":[
        "\u041a\u043e\u043b\u044c \u0412\u0442\u043e\u0440\u043e\u0439"
    ],
    "name:und_x_variant":[
        "Kol\u2019 Vtoroy"
    ],
    "wof:name":"Kol' Vtoroy",
    "wof:placetype":"locality"
},
  "geometry": {"coordinates":[140.59999999999999,53.61666999999999],"type":"Point"}
}