{
  "type": "Feature",
  "properties": {
    "gn:admin1_code":"25.0",
    "gn:asciiname":"Privalovo",
    "gn:country_code":"RU",
    "gn:dem":170,
    "gn:feature_class":"P",
    "gn:feature_code":"PPL",
    "gn:name":"Privalovo",
    "gn:population":0,
    "gn:timezone":"Europe/Moscow",
    "iso:country":"RU",
    "name:rus_x_preferred":[
        "\u041f\u0440\u0438\u0432\u0430\u043b\u043e\u0432\u043e"
    ],
    "name:und_x_variant":[
        "\u041f\u0440\u0438\u0432\u0430\u043b\u043e\u0432\u043e"
    ],
    "wof:name":"Privalovo",
    "wof:placetype":"locality"
},
  "geometry": {"coordinates":[35.45398,54.32485],"type":"Point"}
}