{
  "type": "Feature",
  "properties": {
    "gn:admin1_code":"81",
    "gn:asciiname":"Uchkhoz",
    "gn:country_code":"RU",
    "gn:dem":239,
    "gn:feature_class":"P",
    "gn:feature_code":"PPL",
    "gn:name":"Uchkhoz",
    "gn:population":0,
    "gn:timezone":"Europe/Ulyanovsk",
    "iso:country":"RU",
    "name:rus_x_preferred":[
        "\u0423\u0447\u0445\u043e\u0437"
    ],
    "name:und_x_variant":[
        "\u0423\u0447\u0445\u043e\u0437"
    ],
    "wof:name":"Uchkhoz",
    "wof:placetype":"locality"
},
  "geometry": {"coordinates":[46.9015,53.5737],"type":"Point"}
}