{
  "type": "Feature",
  "properties": {
    "gn:admin1_code":"62.0",
    "gn:asciiname":"Artemovo",
    "gn:country_code":"RU",
    "gn:dem":125,
    "gn:feature_class":"P",
    "gn:feature_code":"PPL",
    "gn:name":"Art\u00ebmovo",
    "gn:population":0,
    "gn:timezone":"Europe/Moscow",
    "iso:country":"RU",
    "name:nor_x_preferred":[
        "Artjomovo"
    ],
    "name:rus_x_preferred":[
        "\u0410\u0440\u0442\u0451\u043c\u043e\u0432\u043e"
    ],
    "name:und_x_variant":[
        "Art\u00ebmovo"
    ],
    "wof:name":"Artemovo",
    "wof:placetype":"locality"
},
  "geometry": {"coordinates":[40.48531,55.06972],"type":"Point"}
}