{
  "type": "Feature",
  "properties": {
    "gn:admin1_code":"86",
    "gn:asciiname":"Rozy Lyuksemburg",
    "gn:country_code":"RU",
    "gn:dem":191,
    "gn:feature_class":"P",
    "gn:feature_code":"PPL",
    "gn:name":"Rozy Lyuksemburg",
    "gn:population":0,
    "gn:timezone":"Europe/Moscow",
    "iso:country":"RU",
    "name:rus_x_preferred":[
        "\u0420\u043e\u0437\u044b \u041b\u044e\u043a\u0441\u0435\u043c\u0431\u0443\u0440\u0433"
    ],
    "wof:name":"Rozy Lyuksemburg",
    "wof:placetype":"locality"
},
  "geometry": {"coordinates":[38.8039,51.6297],"type":"Point"}
}