{
  "type": "Feature",
  "properties": {
    "gn:admin1_code":"20",
    "gn:asciiname":"Zatayevskiy",
    "gn:country_code":"RU",
    "gn:dem":552,
    "gn:feature_class":"P",
    "gn:feature_code":"PPL",
    "gn:name":"Zatayevskiy",
    "gn:population":0,
    "gn:timezone":"Asia/Irkutsk",
    "iso:country":"RU",
    "wof:name":"Zatayevskiy",
    "wof:placetype":"locality"
},
  "geometry": {"coordinates":[100.23333,54.71666999999999],"type":"Point"}
}