{
  "type": "Feature",
  "properties": {
    "gn:admin1_code":"69",
    "gn:asciiname":"Babeyevka",
    "gn:country_code":"RU",
    "gn:dem":186,
    "gn:feature_class":"P",
    "gn:feature_code":"PPL",
    "gn:name":"Babeyevka",
    "gn:population":0,
    "gn:timezone":"Europe/Moscow",
    "iso:country":"RU",
    "name:nor_x_preferred":[
        "Babejeva"
    ],
    "name:rus_x_preferred":[
        "\u0411\u0430\u0431\u0435\u0435\u0432\u043a\u0430"
    ],
    "name:und_x_variant":[
        "Babeyeva",
        "Babeyevka"
    ],
    "wof:name":"Babeyevka",
    "wof:placetype":"locality"
},
  "geometry": {"coordinates":[32.61059,54.84144000000001],"type":"Point"}
}