{
  "type": "Feature",
  "properties": {
    "gn:admin1_code":"47",
    "gn:asciiname":"Porokhovo",
    "gn:country_code":"RU",
    "gn:dem":189,
    "gn:feature_class":"P",
    "gn:feature_code":"PPL",
    "gn:name":"Porokhovo",
    "gn:population":0,
    "gn:timezone":"Europe/Moscow",
    "iso:country":"RU",
    "name:nor_x_preferred":[
        "Porokhovo"
    ],
    "name:rus_x_preferred":[
        "\u041f\u043e\u0440\u043e\u0445\u043e\u0432\u043e"
    ],
    "wof:name":"Porokhovo",
    "wof:placetype":"locality"
},
  "geometry": {"coordinates":[35.92802000000001,56.01375],"type":"Point"}
}