{
  "type": "Feature",
  "properties": {
    "gn:admin1_code":"37",
    "gn:asciiname":"Suborikha",
    "gn:country_code":"RU",
    "gn:dem":150,
    "gn:feature_class":"P",
    "gn:feature_code":"PPL",
    "gn:name":"Suborikha",
    "gn:population":0,
    "gn:timezone":"Europe/Moscow",
    "iso:country":"RU",
    "name:rus_x_preferred":[
        "\u0421\u0443\u0431\u043e\u0440\u0438\u0445\u0430"
    ],
    "name:und_x_variant":[
        "\u0421\u0443\u0431\u043e\u0440\u0438\u0445\u0430"
    ],
    "wof:name":"Suborikha",
    "wof:placetype":"locality"
},
  "geometry": {"coordinates":[44.96637,58.63506999999999],"type":"Point"}
}