{
  "type": "Feature",
  "properties": {
    "gn:admin1_code":"24",
    "gn:asciiname":"Khaukhcha",
    "gn:cc2":"RU",
    "gn:country_code":"RU",
    "gn:dem":174,
    "gn:feature_class":"P",
    "gn:feature_code":"PPL",
    "gn:name":"Khaukhcha",
    "gn:population":0,
    "gn:timezone":"Europe/Moscow",
    "iso:country":"RU",
    "name:und_x_variant":[
        "Khurul-Khobche"
    ],
    "wof:name":"Khaukhcha",
    "wof:placetype":"locality"
},
  "geometry": {"coordinates":[44.67167,45.61028],"type":"Point"}
}