{
  "type": "Feature",
  "properties": {
    "gn:admin1_code":"4.0",
    "gn:asciiname":"Plodosovkhoz",
    "gn:country_code":"RU",
    "gn:dem":201,
    "gn:feature_class":"P",
    "gn:feature_code":"PPL",
    "gn:name":"Plodosovkhoz",
    "gn:population":0,
    "gn:timezone":"Asia/Barnaul",
    "iso:country":"RU",
    "name:rus_x_preferred":[
        "\u041f\u043b\u043e\u0434\u043e\u0441\u043e\u0432\u0445\u043e\u0437"
    ],
    "wof:name":"Plodosovkhoz",
    "wof:placetype":"locality"
},
  "geometry": {"coordinates":[80.2963,51.9958],"type":"Point"}
}