{
  "type": "Feature",
  "properties": {
    "gn:admin1_code":"8",
    "gn:asciiname":"Kuzhanovo",
    "gn:country_code":"RU",
    "gn:dem":449,
    "gn:feature_class":"P",
    "gn:feature_code":"PPL",
    "gn:name":"Kuzhanovo",
    "gn:population":0,
    "gn:timezone":"Asia/Yekaterinburg",
    "iso:country":"RU",
    "name:aze_x_preferred":[
        "Kujan"
    ],
    "name:bak_x_preferred":[
        "\u04a0\u0443\u0436\u0430\u043d"
    ],
    "name:che_x_preferred":[
        "\u041a\u0443\u0436\u0430\u043d\u043e\u0432\u043e"
    ],
    "name:hye_x_preferred":[
        "\u053f\u0578\u0582\u056a\u0561\u0576\u0578\u057e\u0578"
    ],
    "name:kat_x_preferred":[
        "\u10d9\u10e3\u10df\u10d0\u10dc\u10dd\u10d5\u10dd"
    ],
    "name:kaz_x_preferred":[
        "\u041a\u0443\u0436\u0430\u043d"
    ],
    "name:kir_x_preferred":[
        "\u041a\u0443\u0436\u0430\u043d"
    ],
    "name:rus_x_preferred":[
        "\u041a\u0443\u0436\u0430\u043d\u043e\u0432\u043e"
    ],
    "name:tat_x_preferred":[
        "\u041a\u0443\u0497\u0430\u043d"
    ],
    "name:ukr_x_preferred":[
        "\u041a\u0443\u0436\u0430\u043d\u043e\u0432\u043e"
    ],
    "wof:name":"Kuzhanovo",
    "wof:placetype":"locality"
},
  "geometry": {"coordinates":[58.5744,53.4472],"type":"Point"}
}