{
  "type": "Feature",
  "properties": {
    "gn:admin1_code":"8",
    "gn:asciiname":"Kuzhanovo",
    "gn:country_code":"RU",
    "gn:dem":449,
    "gn:feature_class":"P",
    "gn:feature_code":"PPL",
    "gn:name":"Kuzhanovo",
    "gn:population":0,
    "gn:timezone":"Asia/Yekaterinburg",
    "iso:country":"RU",
    "name:rus_x_preferred":[
        "\u041a\u0443\u0436\u0430\u043d\u043e\u0432\u043e"
    ],
    "name:und_x_variant":[
        "\u041a\u0443\u0436\u0430\u043d\u043e\u0432\u043e"
    ],
    "wof:name":"Kuzhanovo",
    "wof:placetype":"locality"
},
  "geometry": {"coordinates":[58.5744,53.4472],"type":"Point"}
}