{
  "type": "Feature",
  "properties": {
    "gn:country":"RU",
    "gn:fcode":"PPL",
    "gn:pop":4202,
    "iso:country":"RU",
    "name:eng_x_preferred":[
        "Novozaimka"
    ],
    "name:rus_x_preferred":[
        "\u041d\u043e\u0432.\u0417\u0430\u0438\u043c\u043a\u0430"
    ],
    "name:rus_x_variant":[
        "\u041d\u043e\u0432\u0430\u044f \u0417\u0430\u0438\u043c\u043a\u0430"
    ],
    "name:unk_x_variant":[
        "Novozaimka"
    ],
    "qs:name":"Novaya Zaimka",
    "qs:photos_9r":0,
    "qs:photos_sr":0,
    "qs:pop_sr":"4",
    "wof:name":"Novaya Zaimka",
    "wof:placetype":"locality",
    "wof:population":4202
},
  "geometry": {"coordinates":[66.92412,56.48572],"type":"Point"}
}