{
  "type": "Feature",
  "properties": {
    "gn:admin1_code":"71",
    "gn:asciiname":"Gagarka",
    "gn:country_code":"RU",
    "gn:dem":205,
    "gn:feature_class":"P",
    "gn:feature_code":"PPL",
    "gn:name":"Gagarka",
    "gn:population":0,
    "gn:timezone":"Asia/Yekaterinburg",
    "iso:country":"RU",
    "name:che_x_preferred":[
        "\u0413\u0430\u0433\u0430\u0440\u043a\u0430"
    ],
    "name:eng_x_preferred":[
        "Gagarka"
    ],
    "name:nor_x_preferred":[
        "Gagarka"
    ],
    "name:rus_x_preferred":[
        "\u0413\u0430\u0433\u0430\u0440\u043a\u0430"
    ],
    "name:tat_x_preferred":[
        "\u0413\u0430\u0433\u0430\u0440\u043a\u0430"
    ],
    "name:ukr_x_preferred":[
        "\u0413\u0430\u0433\u0430\u0440\u043a\u0430"
    ],
    "name:und_x_variant":[
        "Gagarskaya"
    ],
    "wof:name":"Gagarka",
    "wof:placetype":"locality"
},
  "geometry": {"coordinates":[61.2661,56.7656],"type":"Point"}
}