{
  "type": "Feature",
  "properties": {
    "gn:admin1_code":"10",
    "gn:asciiname":"Novoye Selo",
    "gn:country_code":"RU",
    "gn:dem":189,
    "gn:feature_class":"P",
    "gn:feature_code":"PPL",
    "gn:name":"Novoye Selo",
    "gn:population":0,
    "gn:timezone":"Europe/Moscow",
    "iso:country":"RU",
    "name:rus_x_preferred":[
        "\u041d\u043e\u0432\u043e\u0435 \u0421\u0435\u043b\u043e"
    ],
    "name:und_x_variant":[
        "\u041d\u043e\u0432\u043e\u0435 \u0421\u0435\u043b\u043e"
    ],
    "wof:name":"Novoye Selo",
    "wof:placetype":"locality"
},
  "geometry": {"coordinates":[32.81289,52.69419],"type":"Point"}
}