{
  "type": "Feature",
  "properties": {
    "gn:admin1_code":"69",
    "gn:asciiname":"Kozhino",
    "gn:country_code":"RU",
    "gn:dem":187,
    "gn:feature_class":"P",
    "gn:feature_code":"PPL",
    "gn:name":"Kozhino",
    "gn:population":0,
    "gn:timezone":"Europe/Moscow",
    "iso:country":"RU",
    "name:rus_x_preferred":[
        "\u041a\u043e\u0436\u0438\u043d\u043e"
    ],
    "name:und_x_variant":[
        "Kozhina",
        "Kozhino",
        "\u041a\u043e\u0436\u0438\u043d\u043e"
    ],
    "wof:name":"Kozhino",
    "wof:placetype":"locality"
},
  "geometry": {"coordinates":[34.49379,55.67041],"type":"Point"}
}