{
  "type": "Feature",
  "properties": {
    "gn:admin1_code":"46.0",
    "gn:asciiname":"Bogolyubovka",
    "gn:country_code":"RU",
    "gn:dem":188,
    "gn:feature_class":"P",
    "gn:feature_code":"PPL",
    "gn:name":"Bogolyubovka",
    "gn:population":0,
    "gn:timezone":"Europe/Moscow",
    "iso:country":"RU",
    "name:rus_x_preferred":[
        "\u0411\u043e\u0433\u043e\u043b\u044e\u0431\u043e\u0432\u043a\u0430"
    ],
    "wof:name":"Bogolyubovka",
    "wof:placetype":"locality"
},
  "geometry": {"coordinates":[44.85472,54.09969],"type":"Point"}
}