{
  "type": "Feature",
  "properties": {
    "gn:admin1_code":"49",
    "gn:asciiname":"Nyam-Ozero",
    "gn:country_code":"RU",
    "gn:dem":170,
    "gn:feature_class":"P",
    "gn:feature_code":"PPL",
    "gn:name":"Nyam-Ozero",
    "gn:population":0,
    "gn:timezone":"Europe/Moscow",
    "iso:country":"RU",
    "name:eng_x_preferred":[
        "Nyam-Ozero"
    ],
    "name:fin_x_preferred":[
        "Norppaj\u00e4rvi"
    ],
    "name:nor_x_preferred":[
        "Njamozero"
    ],
    "name:rus_x_preferred":[
        "\u041d\u044f\u043c\u043e\u0437\u0435\u0440\u043e"
    ],
    "name:rus_x_variant":[
        "\u041d\u044f\u043c-\u041e\u0437\u0435\u0440\u043e"
    ],
    "name:und_x_variant":[
        "Nyam",
        "Nyam-Ozero",
        "\u041d\u044f\u043c-\u041e\u0437\u0435\u0440\u043e"
    ],
    "wof:name":"Nyam-Ozero",
    "wof:placetype":"locality"
},
  "geometry": {"coordinates":[31.45068,66.96113000000001],"type":"Point"}
}