{
  "type": "Feature",
  "properties": {
    "gn:admin1_code":"85",
    "gn:asciiname":"Pashnets",
    "gn:country_code":"RU",
    "gn:dem":129,
    "gn:feature_class":"P",
    "gn:feature_code":"PPL",
    "gn:name":"Pashnets",
    "gn:population":0,
    "gn:timezone":"Europe/Moscow",
    "iso:country":"RU",
    "name:rus_x_preferred":[
        "\u041f\u0430\u0448\u043d\u0435\u0446"
    ],
    "wof:name":"Pashnets",
    "wof:placetype":"locality"
},
  "geometry": {"coordinates":[38.29125,59.23993000000001],"type":"Point"}
}