{
  "type": "Feature",
  "properties": {
    "gn:admin1_code":"77",
    "gn:asciiname":"Sludnovo",
    "gn:country_code":"RU",
    "gn:dem":148,
    "gn:feature_class":"P",
    "gn:feature_code":"PPL",
    "gn:name":"Sludnovo",
    "gn:population":0,
    "gn:timezone":"Europe/Moscow",
    "iso:country":"RU",
    "name:rus_x_preferred":[
        "\u0421\u043b\u0443\u0434\u043d\u043e\u0432\u043e"
    ],
    "name:und_x_variant":[
        "\u0421\u043b\u0443\u0434\u043d\u043e\u0432\u043e"
    ],
    "wof:name":"Sludnovo",
    "wof:placetype":"locality"
},
  "geometry": {"coordinates":[36.9547,58.0733],"type":"Point"}
}