{
  "type": "Feature",
  "properties": {
    "gn:admin1_code":"37.0",
    "gn:asciiname":"Bulkovo",
    "gn:country_code":"RU",
    "gn:dem":112,
    "gn:feature_class":"P",
    "gn:feature_code":"PPL",
    "gn:name":"Bulkovo",
    "gn:population":0,
    "gn:timezone":"Europe/Moscow",
    "iso:country":"RU",
    "name:rus_x_preferred":[
        "\u0411\u0443\u043b\u043a\u043e\u0432\u043e"
    ],
    "name:und_x_variant":[
        "\u0411\u0443\u043b\u043a\u043e\u0432\u043e"
    ],
    "wof:name":"Bulkovo",
    "wof:placetype":"locality"
},
  "geometry": {"coordinates":[41.26667,58.21666999999999],"type":"Point"}
}