{
  "type": "Feature",
  "properties": {
    "gn:admin1_code":"60",
    "gn:asciiname":"Lomy",
    "gn:country_code":"RU",
    "gn:dem":110,
    "gn:feature_class":"P",
    "gn:feature_code":"PPL",
    "gn:name":"Lomy",
    "gn:population":0,
    "gn:timezone":"Europe/Moscow",
    "iso:country":"RU",
    "name:bel_x_preferred":[
        "\u041b\u0430\u043c\u044b"
    ],
    "name:hye_x_preferred":[
        "\u053c\u0578\u0574\u056b"
    ],
    "name:rus_x_preferred":[
        "\u041b\u043e\u043c\u044b"
    ],
    "name:slk_x_preferred":[
        "Lomy"
    ],
    "wof:name":"Lomy",
    "wof:placetype":"locality"
},
  "geometry": {"coordinates":[28.33888,56.44394000000001],"type":"Point"}
}