{
  "type": "Feature",
  "properties": {
    "gn:admin1_code":"9.0",
    "gn:asciiname":"Borotnikovo",
    "gn:country_code":"RU",
    "gn:dem":132,
    "gn:feature_class":"P",
    "gn:feature_code":"PPL",
    "gn:name":"Borotnikovo",
    "gn:population":0,
    "gn:timezone":"Europe/Moscow",
    "iso:country":"RU",
    "name:rus_x_preferred":[
        "\u0411\u043e\u0440\u043e\u0442\u043d\u0438\u043a\u043e\u0432\u043e"
    ],
    "name:und_x_variant":[
        "\u0411\u043e\u0440\u043e\u0442\u043d\u0438\u043a\u043e\u0432\u043e"
    ],
    "wof:name":"Borotnikovo",
    "wof:placetype":"locality"
},
  "geometry": {"coordinates":[37.9475,51.2868],"type":"Point"}
}