{
  "type": "Feature",
  "properties": {
    "gn:admin1_code":"85",
    "gn:asciiname":"Konetskaya",
    "gn:country_code":"RU",
    "gn:dem":133,
    "gn:feature_class":"P",
    "gn:feature_code":"PPL",
    "gn:name":"Konetskaya",
    "gn:population":0,
    "gn:timezone":"Europe/Moscow",
    "iso:country":"RU",
    "name:rus_x_preferred":[
        "\u041a\u043e\u043d\u0435\u0442\u0441\u043a\u0430\u044f"
    ],
    "name:und_x_variant":[
        "Konetskaja",
        "Konetskaya"
    ],
    "wof:name":"Konetskaya",
    "wof:placetype":"locality"
},
  "geometry": {"coordinates":[36.8185,60.78395],"type":"Point"}
}