{
  "type": "Feature",
  "properties": {
    "gn:admin1_code":"85",
    "gn:asciiname":"Flilaleyevo",
    "gn:country_code":"RU",
    "gn:dem":155,
    "gn:feature_class":"P",
    "gn:feature_code":"PPL",
    "gn:name":"Flilaleyevo",
    "gn:population":0,
    "gn:timezone":"Europe/Moscow",
    "iso:country":"RU",
    "name:rus_x_preferred":[
        "\u0424\u0438\u043b\u0430\u043b\u0435\u0435\u0432\u043e"
    ],
    "wof:name":"Flilaleyevo",
    "wof:placetype":"locality"
},
  "geometry": {"coordinates":[39.0681,59.74],"type":"Point"}
}