{
  "type": "Feature",
  "properties": {
    "gn:admin1_code":"64",
    "gn:asciiname":"Antsyferova",
    "gn:country_code":"RU",
    "gn:dem":1,
    "gn:feature_class":"P",
    "gn:feature_code":"PPL",
    "gn:name":"Antsyferova",
    "gn:population":0,
    "gn:timezone":"Asia/Magadan",
    "iso:country":"RU",
    "name:nor_x_preferred":[
        "Antsyferova"
    ],
    "name:rus_x_preferred":[
        "\u0410\u043d\u0446\u044b\u0444\u0435\u0440\u043e\u0432\u0430"
    ],
    "name:und_x_variant":[
        "Arakawa",
        "Arakawa-gyoj\u014d",
        "Arakawa Fishery",
        "Antsyferova"
    ],
    "wof:name":"Antsyferova",
    "wof:placetype":"locality"
},
  "geometry": {"coordinates":[155.76667,50.48333],"type":"Point"}
}