{
  "type": "Feature",
  "properties": {
    "gn:admin1_code":"4",
    "gn:asciiname":"Anamas",
    "gn:country_code":"RU",
    "gn:dem":314,
    "gn:feature_class":"P",
    "gn:feature_code":"PPL",
    "gn:name":"Anamas",
    "gn:population":0,
    "gn:timezone":"Asia/Barnaul",
    "iso:country":"RU",
    "name:eng_x_preferred":[
        "Anamas"
    ],
    "name:nor_x_preferred":[
        "Anamas"
    ],
    "name:rus_x_preferred":[
        "\u0410\u043d\u0430\u043c\u0430\u0441"
    ],
    "wof:name":"Anamas",
    "wof:placetype":"locality"
},
  "geometry": {"coordinates":[86.3625,53.1206],"type":"Point"}
}