{
  "type": "Feature",
  "properties": {
    "gn:admin1_code":"86",
    "gn:asciiname":"Krinitsa",
    "gn:country_code":"RU",
    "gn:dem":133,
    "gn:feature_class":"P",
    "gn:feature_code":"PPL",
    "gn:name":"Krinitsa",
    "gn:population":0,
    "gn:timezone":"Europe/Moscow",
    "iso:country":"RU",
    "name:rus_x_preferred":[
        "\u041a\u0440\u0438\u043d\u0438\u0446\u0430"
    ],
    "name:und_x_variant":[
        "Krintsa",
        "Krinitsa"
    ],
    "wof:name":"Krinitsa",
    "wof:placetype":"locality"
},
  "geometry": {"coordinates":[40.60979,49.71298],"type":"Point"}
}