{
  "type": "Feature",
  "properties": {
    "gn:admin1_code":"25.0",
    "gn:asciiname":"Frolovo",
    "gn:country_code":"RU",
    "gn:dem":204,
    "gn:feature_class":"P",
    "gn:feature_code":"PPL",
    "gn:name":"Frolovo",
    "gn:population":0,
    "gn:timezone":"Europe/Moscow",
    "iso:country":"RU",
    "name:rus_x_preferred":[
        "\u0424\u0440\u043e\u043b\u043e\u0432\u0441\u043a\u043e\u0435"
    ],
    "name:und_x_variant":[
        "Frolovskoye",
        "Frolovo",
        "\u0424\u0440\u043e\u043b\u043e\u0432\u0441\u043a\u043e\u0435"
    ],
    "wof:name":"Frolovo",
    "wof:placetype":"locality"
},
  "geometry": {"coordinates":[35.32795,54.2042],"type":"Point"}
}