{
  "type": "Feature",
  "properties": {
    "gn:admin1_code":"76",
    "gn:asciiname":"Prigor'ye",
    "gn:country_code":"RU",
    "gn:dem":236,
    "gn:feature_class":"P",
    "gn:feature_code":"PPL",
    "gn:name":"Prigor\u2019ye",
    "gn:population":0,
    "gn:timezone":"Europe/Moscow",
    "iso:country":"RU",
    "name:rus_x_preferred":[
        "\u041f\u0440\u0438\u0433\u043e\u0440\u044c\u0435"
    ],
    "name:und_x_variant":[
        "Prigor\u2019ye"
    ],
    "wof:name":"Prigor'ye",
    "wof:placetype":"locality"
},
  "geometry": {"coordinates":[38.3759,54.05774],"type":"Point"}
}