{
  "type": "Feature",
  "properties": {
    "gn:admin1_code":"57.0",
    "gn:asciiname":"Ankino",
    "gn:country_code":"RU",
    "gn:dem":191,
    "gn:feature_class":"P",
    "gn:feature_code":"PPL",
    "gn:name":"Ankino",
    "gn:population":0,
    "gn:timezone":"Europe/Moscow",
    "iso:country":"RU",
    "name:nor_x_preferred":[
        "Ankino"
    ],
    "name:rus_x_preferred":[
        "\u0410\u043d\u043a\u0438\u043d\u043e"
    ],
    "wof:name":"Ankino",
    "wof:placetype":"locality"
},
  "geometry": {"coordinates":[43.09025,52.52028000000001],"type":"Point"}
}