{
  "type": "Feature",
  "properties": {
    "gn:admin1_code":"47.0",
    "gn:asciiname":"Avdot'ivo",
    "gn:country_code":"RU",
    "gn:dem":143,
    "gn:feature_class":"P",
    "gn:feature_code":"PPL",
    "gn:name":"Avdot\u2019ivo",
    "gn:population":0,
    "gn:timezone":"Europe/Moscow",
    "iso:country":"RU",
    "name:nor_x_preferred":[
        "Avdotjevo"
    ],
    "name:rus_x_preferred":[
        "\u0410\u0432\u0434\u043e\u0442\u044c\u0435\u0432\u043e"
    ],
    "name:und_x_variant":[
        "Avdot\u2019yevo",
        "Avdot\u2019ivo"
    ],
    "wof:name":"Avdot'ivo",
    "wof:placetype":"locality"
},
  "geometry": {"coordinates":[37.74382,55.0478],"type":"Point"}
}