{
  "type": "Feature",
  "properties": {
    "gn:admin1_code":"67",
    "gn:asciiname":"Peskovatka",
    "gn:country_code":"RU",
    "gn:dem":200,
    "gn:feature_class":"P",
    "gn:feature_code":"PPL",
    "gn:name":"Peskovatka",
    "gn:population":0,
    "gn:timezone":"Europe/Saratov",
    "iso:country":"RU",
    "name:rus_x_preferred":[
        "\u041f\u0435\u0441\u043a\u043e\u0432\u0430\u0442\u043a\u0430"
    ],
    "wof:name":"Peskovatka",
    "wof:placetype":"locality"
},
  "geometry": {"coordinates":[44.01484,52.11431],"type":"Point"}
}