{
  "type": "Feature",
  "properties": {
    "gn:admin1_code":"84",
    "gn:asciiname":"Kirsanov",
    "gn:country_code":"RU",
    "gn:dem":22,
    "gn:feature_class":"P",
    "gn:feature_code":"PPL",
    "gn:name":"Kirsanov",
    "gn:population":0,
    "gn:timezone":"Europe/Volgograd",
    "iso:country":"RU",
    "name:rus_x_preferred":[
        "\u041a\u0438\u0440\u0441\u0430\u043d\u043e\u0432"
    ],
    "name:und_x_variant":[
        "\u041a\u0438\u0440\u0441\u0430\u043d\u043e\u0432"
    ],
    "wof:name":"Kirsanov",
    "wof:placetype":"locality"
},
  "geometry": {"coordinates":[45.43333,49.15],"type":"Point"}
}