{
  "type": "Feature",
  "properties": {
    "gn:admin1_code":"69",
    "gn:asciiname":"Nikitino",
    "gn:country_code":"RU",
    "gn:dem":235,
    "gn:feature_class":"P",
    "gn:feature_code":"PPL",
    "gn:name":"Nikitino",
    "gn:population":0,
    "gn:timezone":"Europe/Moscow",
    "iso:country":"RU",
    "wof:name":"Nikitino",
    "wof:placetype":"locality"
},
  "geometry": {"coordinates":[33.50593,54.50411999999999],"type":"Point"}
}