{
  "type": "Feature",
  "properties": {
    "gn:admin1_code":"37",
    "gn:asciiname":"Yelfimov",
    "gn:country_code":"RU",
    "gn:dem":129,
    "gn:feature_class":"P",
    "gn:feature_code":"PPL",
    "gn:name":"Yelfimov",
    "gn:population":0,
    "gn:timezone":"Europe/Moscow",
    "iso:country":"RU",
    "name:rus_x_preferred":[
        "\u0415\u043b\u0444\u0438\u043c\u043e\u0432"
    ],
    "wof:name":"Yelfimov",
    "wof:placetype":"locality"
},
  "geometry": {"coordinates":[43.63058,58.46746],"type":"Point"}
}