{
  "type": "Feature",
  "properties": {
    "gn:admin1_code":"6",
    "gn:asciiname":"Bol'shoy Gyzheg",
    "gn:country_code":"RU",
    "gn:dem":72,
    "gn:feature_class":"P",
    "gn:feature_code":"PPL",
    "gn:name":"Bol\u2019shoy Gyzheg",
    "gn:population":0,
    "gn:timezone":"Europe/Moscow",
    "iso:country":"RU",
    "name:rus_x_preferred":[
        "\u0411\u043e\u043b\u044c\u0448\u043e\u0439 \u0413\u044b\u0436\u0435\u0433"
    ],
    "name:und_x_variant":[
        "Bol\u2019shoy Gyzheg"
    ],
    "wof:name":"Bol'shoy Gyzheg",
    "wof:placetype":"locality"
},
  "geometry": {"coordinates":[48.3857,61.9517],"type":"Point"}
}