{
  "type": "Feature",
  "properties": {
    "gn:admin1_code":"42",
    "gn:asciiname":"Ishchevo",
    "gn:country_code":"RU",
    "gn:dem":52,
    "gn:feature_class":"P",
    "gn:feature_code":"PPL",
    "gn:name":"Ishchevo",
    "gn:population":0,
    "gn:timezone":"Europe/Moscow",
    "iso:country":"RU",
    "name:rus_x_preferred":[
        "\u0418\u0449\u0435\u0432\u043e"
    ],
    "name:und_x_variant":[
        "\u0418\u0449\u0435\u0432\u043e"
    ],
    "wof:name":"Ishchevo",
    "wof:placetype":"locality"
},
  "geometry": {"coordinates":[28.22875,59.11547],"type":"Point"}
}