{
  "type": "Feature",
  "properties": {
    "gn:admin1_code":"8",
    "gn:asciiname":"Salyakhovo",
    "gn:country_code":"RU",
    "gn:dem":560,
    "gn:feature_class":"P",
    "gn:feature_code":"PPL",
    "gn:name":"Salyakhovo",
    "gn:population":0,
    "gn:timezone":"Asia/Yekaterinburg",
    "iso:country":"RU",
    "name:rus_x_preferred":[
        "\u0421\u0430\u043b\u044f\u0445\u043e\u0432\u043e"
    ],
    "name:und_x_variant":[
        "\u0421\u0430\u043b\u044f\u0445\u043e\u0432\u043e"
    ],
    "wof:name":"Salyakhovo",
    "wof:placetype":"locality"
},
  "geometry": {"coordinates":[57.7003,52.1956],"type":"Point"}
}