{
  "type": "Feature",
  "properties": {
    "gn:admin1_code":"8",
    "gn:asciiname":"Salyakhovo",
    "gn:country_code":"RU",
    "gn:dem":560,
    "gn:feature_class":"P",
    "gn:feature_code":"PPL",
    "gn:name":"Salyakhovo",
    "gn:population":0,
    "gn:timezone":"Asia/Yekaterinburg",
    "iso:country":"RU",
    "name:bak_x_preferred":[
        "\u0421\u04d9\u043b\u04d9\u0445"
    ],
    "name:che_x_preferred":[
        "\u0421\u0430\u043b\u044f\u0445\u043e\u0432\u043e"
    ],
    "name:hye_x_preferred":[
        "\u054d\u0561\u056c\u0575\u0561\u056d\u0578\u057e\u0578"
    ],
    "name:kat_x_preferred":[
        "\u10e1\u10d0\u10da\u10d8\u10d0\u10ee\u10dd\u10d5\u10dd"
    ],
    "name:kaz_x_preferred":[
        "\u0421\u0430\u043b\u044f\u0445"
    ],
    "name:kir_x_preferred":[
        "\u0421\u0430\u043b\u044f\u0445"
    ],
    "name:rus_x_preferred":[
        "\u0421\u0430\u043b\u044f\u0445\u043e\u0432\u043e"
    ],
    "name:tat_x_preferred":[
        "\u0421\u04d9\u043b\u0430\u0445"
    ],
    "name:ukr_x_preferred":[
        "\u0421\u0430\u043b\u044f\u0445\u043e\u0432\u043e"
    ],
    "wof:name":"Salyakhovo",
    "wof:placetype":"locality"
},
  "geometry": {"coordinates":[57.7003,52.1956],"type":"Point"}
}