{
  "type": "Feature",
  "properties": {
    "gn:admin1_code":"8",
    "gn:asciiname":"Imyantau",
    "gn:country_code":"RU",
    "gn:dem":203,
    "gn:feature_class":"P",
    "gn:feature_code":"PPL",
    "gn:name":"Imyantau",
    "gn:population":0,
    "gn:timezone":"Asia/Yekaterinburg",
    "iso:country":"RU",
    "name:rus_x_preferred":[
        "\u0418\u043c\u044f\u043d\u0442\u0430\u0443"
    ],
    "name:und_x_variant":[
        "\u0418\u043c\u044f\u043d\u0442\u0430\u0443"
    ],
    "wof:name":"Imyantau",
    "wof:placetype":"locality"
},
  "geometry": {"coordinates":[56.68333000000001,55.26667],"type":"Point"}
}