{
  "type": "Feature",
  "properties": {
    "gn:admin1_code":"90",
    "gn:asciiname":"Komarovo",
    "gn:country_code":"RU",
    "gn:dem":260,
    "gn:feature_class":"P",
    "gn:feature_code":"PPL",
    "gn:name":"Komarovo",
    "gn:population":0,
    "gn:timezone":"Asia/Yekaterinburg",
    "iso:country":"RU",
    "wof:name":"Komarovo",
    "wof:placetype":"locality"
},
  "geometry": {"coordinates":[57.155,57.26778],"type":"Point"}
}