{
  "type": "Feature",
  "properties": {
    "gn:admin1_code":"81",
    "gn:asciiname":"Ryazanovo",
    "gn:country_code":"RU",
    "gn:dem":61,
    "gn:feature_class":"P",
    "gn:feature_code":"PPL",
    "gn:name":"Ryazanovo",
    "gn:population":0,
    "gn:timezone":"Europe/Ulyanovsk",
    "iso:country":"RU",
    "name:eng_x_preferred":[
        "Ryazanovo"
    ],
    "name:nor_x_preferred":[
        "Rjazanovo"
    ],
    "name:rus_x_preferred":[
        "\u0420\u044f\u0437\u0430\u043d\u043e\u0432\u043e"
    ],
    "wof:name":"Ryazanovo",
    "wof:placetype":"locality"
},
  "geometry": {"coordinates":[49.4057,53.9857],"type":"Point"}
}