{
  "type": "Feature",
  "properties": {
    "gn:admin1_code":"46.0",
    "gn:asciiname":"Novyye Avgury",
    "gn:country_code":"RU",
    "gn:dem":182,
    "gn:feature_class":"P",
    "gn:feature_code":"PPL",
    "gn:name":"Novyye Avgury",
    "gn:population":0,
    "gn:timezone":"Europe/Moscow",
    "iso:country":"RU",
    "name:rus_x_preferred":[
        "\u041d\u043e\u0432\u044b\u0435 \u0410\u0432\u0433\u0443\u0440\u044b"
    ],
    "wof:name":"Novyye Avgury",
    "wof:placetype":"locality"
},
  "geometry": {"coordinates":[44.45532,54.13246],"type":"Point"}
}