{
  "type": "Feature",
  "properties": {
    "gn:admin1_code":"33.0",
    "gn:asciiname":"Voronchikhi",
    "gn:country_code":"RU",
    "gn:dem":157,
    "gn:feature_class":"P",
    "gn:feature_code":"PPL",
    "gn:name":"Voronchikhi",
    "gn:population":0,
    "gn:timezone":"Europe/Kirov",
    "iso:country":"RU",
    "name:rus_x_preferred":[
        "\u0412\u043e\u0440\u043e\u043d\u0447\u0438\u0445\u0438"
    ],
    "wof:name":"Voronchikhi",
    "wof:placetype":"locality"
},
  "geometry": {"coordinates":[50.45191,58.02568],"type":"Point"}
}