{
  "type": "Feature",
  "properties": {
    "gn:admin1_code":"45",
    "gn:asciiname":"Bol'shaya Gora",
    "gn:country_code":"RU",
    "gn:dem":116,
    "gn:feature_class":"P",
    "gn:feature_code":"PPL",
    "gn:name":"Bol\u2019shaya Gora",
    "gn:population":0,
    "gn:timezone":"Europe/Moscow",
    "iso:country":"RU",
    "name:rus_x_preferred":[
        "\u0411\u043e\u043b\u044c\u0448\u0430\u044f \u0413\u043e\u0440\u0430"
    ],
    "name:und_x_variant":[
        "Bol\u2019shaya Gora"
    ],
    "wof:name":"Bol'shaya Gora",
    "wof:placetype":"locality"
},
  "geometry": {"coordinates":[49.0623,57.2049],"type":"Point"}
}