{
  "type": "Feature",
  "properties": {
    "gn:admin1_code":"54",
    "gn:asciiname":"Kostino",
    "gn:country_code":"RU",
    "gn:dem":116,
    "gn:feature_class":"P",
    "gn:feature_code":"PPL",
    "gn:name":"Kostino",
    "gn:population":0,
    "gn:timezone":"Asia/Omsk",
    "iso:country":"RU",
    "name:ceb_x_preferred":[
        "Kostino"
    ],
    "name:deu_x_preferred":[
        "Kostino"
    ],
    "name:eng_x_preferred":[
        "Kostino"
    ],
    "name:hye_x_preferred":[
        "\u053f\u0578\u057d\u057f\u056b\u0576\u0578"
    ],
    "name:nld_x_preferred":[
        "Kostino"
    ],
    "name:nor_x_preferred":[
        "Kostino"
    ],
    "name:rus_x_preferred":[
        "\u041a\u043e\u0441\u0442\u0438\u043d\u043e"
    ],
    "name:swe_x_preferred":[
        "Kostino"
    ],
    "name:ukr_x_preferred":[
        "\u041a\u043e\u0441\u0442\u0456\u043d\u043e"
    ],
    "name:und_x_variant":[
        "\u041a\u043e\u0441\u0442\u0438\u043d\u043e",
        "Kostino"
    ],
    "wof:name":"Kostino",
    "wof:placetype":"locality"
},
  "geometry": {"coordinates":[74.94934000000001,56.17106999999999],"type":"Point"}
}