{
  "type": "Feature",
  "properties": {
    "gn:admin1_code":"6.0",
    "gn:asciiname":"Maksimovskaya",
    "gn:country_code":"RU",
    "gn:dem":159,
    "gn:feature_class":"P",
    "gn:feature_code":"PPL",
    "gn:name":"Maksimovskaya",
    "gn:population":0,
    "gn:timezone":"Europe/Moscow",
    "iso:country":"RU",
    "name:rus_x_preferred":[
        "\u041c\u0430\u043a\u0441\u0438\u043c\u043e\u0432\u0441\u043a\u0430\u044f"
    ],
    "wof:name":"Maksimovskaya",
    "wof:placetype":"locality"
},
  "geometry": {"coordinates":[41.0128,60.8199],"type":"Point"}
}