{
  "type": "Feature",
  "properties": {
    "gn:admin1_code":"69",
    "gn:asciiname":"Valutino",
    "gn:country_code":"RU",
    "gn:dem":249,
    "gn:feature_class":"P",
    "gn:feature_code":"PPL",
    "gn:name":"Valutino",
    "gn:population":0,
    "gn:timezone":"Europe/Moscow",
    "iso:country":"RU",
    "name:rus_x_preferred":[
        "\u0412\u0430\u043b\u0443\u0442\u0438\u043d\u043e"
    ],
    "wof:name":"Valutino",
    "wof:placetype":"locality"
},
  "geometry": {"coordinates":[32.14283,54.81199],"type":"Point"}
}