{
  "type": "Feature",
  "properties": {
    "gn:admin1_code":"17",
    "gn:asciiname":"Kurort Talgi",
    "gn:country_code":"RU",
    "gn:dem":171,
    "gn:feature_class":"P",
    "gn:feature_code":"PPL",
    "gn:name":"Kurort Talgi",
    "gn:population":0,
    "gn:timezone":"Europe/Moscow",
    "iso:country":"RU",
    "name:eng_x_preferred":[
        "Kurort Talgi"
    ],
    "name:nor_x_preferred":[
        "Talgi"
    ],
    "name:rus_x_preferred":[
        "\u0422\u0430\u043b\u0433\u0438"
    ],
    "name:rus_x_variant":[
        "\u041a\u0443\u0440\u043e\u0440\u0442 \u0422\u0430\u043b\u0433\u0438"
    ],
    "name:und_x_variant":[
        "Talgi",
        "Kurort Talgi",
        "\u041a\u0443\u0440\u043e\u0440\u0442 \u0422\u0430\u043b\u0433\u0438"
    ],
    "wof:name":"Kurort Talgi",
    "wof:placetype":"locality"
},
  "geometry": {"coordinates":[47.46096,42.87293],"type":"Point"}
}