{
  "type": "Feature",
  "properties": {
    "gn:admin1_code":"63",
    "gn:asciiname":"Odinokiy",
    "gn:country_code":"RU",
    "gn:dem":641,
    "gn:feature_class":"P",
    "gn:feature_code":"PPL",
    "gn:name":"Odinokiy",
    "gn:population":0,
    "gn:timezone":"Asia/Vladivostok",
    "iso:country":"RU",
    "name:rus_x_preferred":[
        "\u041e\u0434\u0438\u043d\u043e\u043a\u0438\u0439"
    ],
    "name:und_x_variant":[
        "\u041e\u0434\u0438\u043d\u043e\u043a\u0438\u0439"
    ],
    "wof:name":"Odinokiy",
    "wof:placetype":"locality"
},
  "geometry": {"coordinates":[137.80000000000001,60.81667],"type":"Point"}
}