{
  "type": "Feature",
  "properties": {
    "gn:admin1_code":"42",
    "gn:asciiname":"Pukholovo",
    "gn:country_code":"RU",
    "gn:dem":27,
    "gn:feature_class":"P",
    "gn:feature_code":"PPL",
    "gn:name":"Pukholovo",
    "gn:population":0,
    "gn:timezone":"Europe/Moscow",
    "iso:country":"RU",
    "name:fin_x_preferred":[
        "Puuhkola"
    ],
    "name:rus_x_preferred":[
        "\u041f\u0443\u0445\u043e\u043b\u043e\u0432\u043e"
    ],
    "name:und_x_variant":[
        "\u041f\u0443\u0445\u043e\u043b\u043e\u0432\u043e"
    ],
    "wof:name":"Pukholovo",
    "wof:placetype":"locality"
},
  "geometry": {"coordinates":[31.08333,59.73333],"type":"Point"}
}