{
  "type": "Feature",
  "properties": {
    "gn:admin1_code":"29",
    "gn:asciiname":"Bol'shoy Shirokiy",
    "gn:country_code":"RU",
    "gn:dem":355,
    "gn:feature_class":"P",
    "gn:feature_code":"PPL",
    "gn:name":"Bol\u2019shoy Shirokiy",
    "gn:population":0,
    "gn:timezone":"Asia/Novokuznetsk",
    "iso:country":"RU",
    "name:rus_x_preferred":[
        "\u0411\u043e\u043b\u044c\u0448\u043e\u0439 \u0428\u0438\u0440\u043e\u043a\u0438\u0439"
    ],
    "name:und_x_variant":[
        "Bol\u2019shoy Shirokiy"
    ],
    "wof:name":"Bol'shoy Shirokiy",
    "wof:placetype":"locality"
},
  "geometry": {"coordinates":[87.15000000000001,55.33333],"type":"Point"}
}