{
  "type": "Feature",
  "properties": {
    "gn:admin1_code":"21.0",
    "gn:asciiname":"Rodino",
    "gn:country_code":"RU",
    "gn:dem":120,
    "gn:feature_class":"P",
    "gn:feature_code":"PPL",
    "gn:name":"Rodino",
    "gn:population":0,
    "gn:timezone":"Europe/Moscow",
    "iso:country":"RU",
    "name:nor_x_preferred":[
        "Rodino"
    ],
    "name:rus_x_preferred":[
        "\u0420\u043e\u0434\u0438\u043d\u043e"
    ],
    "wof:name":"Rodino",
    "wof:placetype":"locality"
},
  "geometry": {"coordinates":[42.65902,56.67218],"type":"Point"}
}