{
  "type": "Feature",
  "properties": {
    "gn:admin1_code":"51",
    "gn:asciiname":"Samoylovka",
    "gn:country_code":"RU",
    "gn:dem":91,
    "gn:feature_class":"P",
    "gn:feature_code":"PPL",
    "gn:name":"Samoylovka",
    "gn:population":0,
    "gn:timezone":"Europe/Moscow",
    "iso:country":"RU",
    "name:eng_x_preferred":[
        "Novaya"
    ],
    "name:nor_x_preferred":[
        "Samojlovka"
    ],
    "name:rus_x_preferred":[
        "\u0421\u0430\u043c\u043e\u0439\u043b\u043e\u0432\u043a\u0430"
    ],
    "name:und_x_variant":[
        "Samoylovka"
    ],
    "wof:name":"Samoylovka",
    "wof:placetype":"locality"
},
  "geometry": {"coordinates":[43.00724,56.01399],"type":"Point"}
}