{
  "type": "Feature",
  "properties": {
    "gn:admin1_code":"28",
    "gn:asciiname":"Pikhtalakhta",
    "gn:country_code":"RU",
    "gn:dem":114,
    "gn:feature_class":"P",
    "gn:feature_code":"PPL",
    "gn:name":"Pikhtalakhta",
    "gn:population":0,
    "gn:timezone":"Europe/Moscow",
    "iso:country":"RU",
    "name:fin_x_preferred":[
        "Piihtilahti"
    ],
    "name:rus_x_preferred":[
        "\u041f\u0438\u0445\u0442\u0430\u043b\u0430\u0445\u0442\u0430"
    ],
    "name:und_x_variant":[
        "Novyy Krast\u2019yanin",
        "Pikhtalakhta",
        "\u041f\u0438\u0445\u0442\u0430\u043b\u0430\u0445\u0442\u0430"
    ],
    "wof:name":"Pikhtalakhta",
    "wof:placetype":"locality"
},
  "geometry": {"coordinates":[32.70049,61.69765],"type":"Point"}
}