{
  "type": "Feature",
  "properties": {
    "gn:admin1_code":"33.0",
    "gn:asciiname":"Polevshchikovy",
    "gn:country_code":"RU",
    "gn:dem":117,
    "gn:feature_class":"P",
    "gn:feature_code":"PPL",
    "gn:name":"Polevshchikovy",
    "gn:population":0,
    "gn:timezone":"Europe/Kirov",
    "iso:country":"RU",
    "name:rus_x_preferred":[
        "\u041f\u043e\u043b\u0435\u0432\u0449\u0438\u043a\u043e\u0432\u044b"
    ],
    "wof:name":"Polevshchikovy",
    "wof:placetype":"locality"
},
  "geometry": {"coordinates":[48.69355,58.5408],"type":"Point"}
}