{
  "type": "Feature",
  "properties": {
    "gn:admin1_code":"86",
    "gn:asciiname":"Kupal'nyy",
    "gn:country_code":"RU",
    "gn:dem":202,
    "gn:feature_class":"P",
    "gn:feature_code":"PPL",
    "gn:name":"Kupal\u2019nyy",
    "gn:population":0,
    "gn:timezone":"Europe/Moscow",
    "iso:country":"RU",
    "name:rus_x_preferred":[
        "Kupal\u2019nyy"
    ],
    "name:rus_x_variant":[
        "\u041a\u0443\u043f\u0430\u043b\u044c\u043d\u044b\u0439",
        "Kupal\u2019ny"
    ],
    "wof:name":"Kupal'nyy",
    "wof:placetype":"locality"
},
  "geometry": {"coordinates":[40.8576,51.0533],"type":"Point"}
}