{
  "type": "Feature",
  "properties": {
    "gn:admin1_code":"77",
    "gn:asciiname":"Gushchino",
    "gn:country_code":"RU",
    "gn:dem":238,
    "gn:feature_class":"P",
    "gn:feature_code":"PPL",
    "gn:name":"Gushchino",
    "gn:population":0,
    "gn:timezone":"Europe/Moscow",
    "iso:country":"RU",
    "name:rus_x_preferred":[
        "\u0413\u0443\u0449\u0438\u043d\u043e"
    ],
    "name:und_x_variant":[
        "\u0413\u0443\u0449\u0438\u043d\u043e"
    ],
    "wof:name":"Gushchino",
    "wof:placetype":"locality"
},
  "geometry": {"coordinates":[33.60111,56.64361],"type":"Point"}
}