{
  "type": "Feature",
  "properties": {
    "gn:admin1_code":"88",
    "gn:asciiname":"Fedenino",
    "gn:country_code":"RU",
    "gn:dem":138,
    "gn:feature_class":"P",
    "gn:feature_code":"PPL",
    "gn:name":"Fedenino",
    "gn:population":0,
    "gn:timezone":"Europe/Moscow",
    "iso:country":"RU",
    "name:rus_x_preferred":[
        "\u0424\u0435\u0434\u0435\u043d\u0438\u043d\u043e"
    ],
    "wof:name":"Fedenino",
    "wof:placetype":"locality"
},
  "geometry": {"coordinates":[39.62584,57.44793000000001],"type":"Point"}
}