{
  "type": "Feature",
  "properties": {
    "gn:admin1_code":"80",
    "gn:asciiname":"Uva-Tuklya",
    "gn:country_code":"RU",
    "gn:dem":141,
    "gn:feature_class":"P",
    "gn:feature_code":"PPL",
    "gn:name":"Uva-Tuklya",
    "gn:population":0,
    "gn:timezone":"Europe/Samara",
    "iso:country":"RU",
    "name:eng_x_preferred":[
        "Uva-Tuklya"
    ],
    "name:nor_x_preferred":[
        "Uva-Tuklja"
    ],
    "name:rus_x_preferred":[
        "\u0423\u0432\u0430-\u0422\u0443\u043a\u043b\u044f"
    ],
    "wof:name":"Uva-Tuklya",
    "wof:placetype":"locality"
},
  "geometry": {"coordinates":[52.1139,56.97246],"type":"Point"}
}