{
  "type": "Feature",
  "properties": {
    "gn:admin1_code":"69",
    "gn:asciiname":"Klemyatina",
    "gn:country_code":"RU",
    "gn:dem":197,
    "gn:feature_class":"P",
    "gn:feature_code":"PPL",
    "gn:name":"Klemyatina",
    "gn:population":0,
    "gn:timezone":"Europe/Moscow",
    "iso:country":"RU",
    "name:rus_x_preferred":[
        "\u041a\u043b\u0435\u043c\u044f\u0442\u0438\u043d\u0430"
    ],
    "wof:name":"Klemyatina",
    "wof:placetype":"locality"
},
  "geometry": {"coordinates":[33.56667,55.31667],"type":"Point"}
}