{
  "type": "Feature",
  "properties": {
    "gn:admin1_code":"91",
    "gn:asciiname":"Panachevo",
    "gn:cc2":"RU",
    "gn:country_code":"RU",
    "gn:dem":351,
    "gn:feature_class":"P",
    "gn:feature_code":"PPL",
    "gn:name":"Panachevo",
    "gn:population":0,
    "gn:timezone":"Asia/Krasnoyarsk",
    "iso:country":"RU",
    "name:eng_x_preferred":[
        "Panachevo"
    ],
    "name:nor_x_preferred":[
        "Ponatsjevo"
    ],
    "name:rus_x_preferred":[
        "\u041f\u043e\u043d\u0430\u0447\u0435\u0432\u043e"
    ],
    "name:rus_x_variant":[
        "\u041f\u0430\u043d\u0430\u0447\u0435\u0432\u043e"
    ],
    "name:und_x_variant":[
        "Pakachevo",
        "Panachevo"
    ],
    "wof:name":"Panachevo",
    "wof:placetype":"locality"
},
  "geometry": {"coordinates":[92.76667,54.11666999999999],"type":"Point"}
}