{
  "type": "Feature",
  "properties": {
    "gn:admin1_code":"68",
    "gn:asciiname":"Nizhniy Tsey",
    "gn:country_code":"RU",
    "gn:dem":2297,
    "gn:feature_class":"P",
    "gn:feature_code":"PPL",
    "gn:name":"Nizhniy Tsey",
    "gn:population":0,
    "gn:timezone":"Europe/Moscow",
    "iso:country":"RU",
    "name:rus_x_preferred":[
        "\u041d\u0438\u0436\u043d\u0438\u0439 \u0426\u0435\u0439"
    ],
    "name:und_x_variant":[
        "\u041d\u0438\u0436\u043d\u0438\u0439 \u0426\u0435\u0439"
    ],
    "wof:name":"Nizhniy Tsey",
    "wof:placetype":"locality"
},
  "geometry": {"coordinates":[43.96667,42.78333],"type":"Point"}
}