{
  "type": "Feature",
  "properties": {
    "gn:admin1_code":"62",
    "gn:asciiname":"Inkino",
    "gn:country_code":"RU",
    "gn:dem":144,
    "gn:feature_class":"P",
    "gn:feature_code":"PPL",
    "gn:name":"Inkino",
    "gn:population":0,
    "gn:timezone":"Europe/Moscow",
    "iso:country":"RU",
    "name:rus_x_preferred":[
        "\u0418\u043d\u043a\u0438\u043d\u043e"
    ],
    "name:und_x_variant":[
        "\u0418\u043d\u043a\u0438\u043d\u043e"
    ],
    "wof:name":"Inkino",
    "wof:placetype":"locality"
},
  "geometry": {"coordinates":[41.75,54.95],"type":"Point"}
}