{
  "type": "Feature",
  "properties": {
    "gn:admin1_code":"93",
    "gn:asciiname":"Moron",
    "gn:country_code":"RU",
    "gn:dem":552,
    "gn:feature_class":"P",
    "gn:feature_code":"PPL",
    "gn:name":"Moron",
    "gn:population":0,
    "gn:timezone":"Asia/Chita",
    "iso:country":"RU",
    "name:ceb_x_preferred":[
        "Moron"
    ],
    "name:deu_x_preferred":[
        "Moron"
    ],
    "name:fra_x_preferred":[
        "Moron"
    ],
    "name:heb_x_preferred":[
        "\u05de\u05d5\u05e8\u05d5\u05df"
    ],
    "name:nld_x_preferred":[
        "Moron"
    ],
    "name:pol_x_preferred":[
        "Moron"
    ],
    "name:rus_x_preferred":[
        "\u041c\u043e\u0440\u043e\u043d"
    ],
    "name:swe_x_preferred":[
        "Moron"
    ],
    "wof:name":"Moron",
    "wof:placetype":"locality"
},
  "geometry": {"coordinates":[119.88333,51.68333],"type":"Point"}
}