{
  "type": "Feature",
  "properties": {
    "gn:admin1_code":"59",
    "gn:asciiname":"Adamovka",
    "gn:cc2":"RU",
    "gn:country_code":"RU",
    "gn:dem":169,
    "gn:feature_class":"P",
    "gn:feature_code":"PPL",
    "gn:name":"Adamovka",
    "gn:population":0,
    "gn:timezone":"Asia/Vladivostok",
    "iso:country":"RU",
    "name:nor_x_preferred":[
        "Adamovka"
    ],
    "name:rus_x_preferred":[
        "\u0410\u0434\u0430\u043c\u043e\u0432\u043a\u0430"
    ],
    "name:und_x_variant":[
        "Alamovka",
        "Adamovka"
    ],
    "wof:name":"Adamovka",
    "wof:placetype":"locality"
},
  "geometry": {"coordinates":[131.69999999999999,44.75],"type":"Point"}
}