{
  "type": "Feature",
  "properties": {
    "gn:admin1_code":"55",
    "gn:asciiname":"Vasil'yevskiy",
    "gn:country_code":"RU",
    "gn:dem":194,
    "gn:feature_class":"P",
    "gn:feature_code":"PPL",
    "gn:name":"Vasil\u2019yevskiy",
    "gn:population":0,
    "gn:timezone":"Asia/Yekaterinburg",
    "iso:country":"RU",
    "name:und_x_variant":[
        "Kiyevskiy",
        "Vasil\u2019yevskiy"
    ],
    "wof:name":"Vasil'yevskiy",
    "wof:placetype":"locality"
},
  "geometry": {"coordinates":[55.48333,52.15],"type":"Point"}
}