{
  "type": "Feature",
  "properties": {
    "gn:admin1_code":"46",
    "gn:asciiname":"Gudimovka",
    "gn:country_code":"RU",
    "gn:dem":110,
    "gn:feature_class":"P",
    "gn:feature_code":"PPL",
    "gn:name":"Gudimovka",
    "gn:population":0,
    "gn:timezone":"Europe/Moscow",
    "iso:country":"RU",
    "name:rus_x_preferred":[
        "\u0413\u0443\u0434\u0438\u043c\u043e\u0432\u043a\u0430"
    ],
    "name:und_x_variant":[
        "\u0413\u0443\u0434\u0438\u043c\u043e\u0432\u043a\u0430"
    ],
    "wof:name":"Gudimovka",
    "wof:placetype":"locality"
},
  "geometry": {"coordinates":[45.82877,54.88221],"type":"Point"}
}