{
  "type": "Feature",
  "properties": {
    "gn:admin1_code":"77",
    "gn:asciiname":"Mozhayevo",
    "gn:country_code":"RU",
    "gn:dem":226,
    "gn:feature_class":"P",
    "gn:feature_code":"PPL",
    "gn:name":"Mozhayevo",
    "gn:population":0,
    "gn:timezone":"Europe/Moscow",
    "iso:country":"RU",
    "name:rus_x_preferred":[
        "\u041c\u043e\u0436\u0430\u0435\u0432\u043e"
    ],
    "wof:name":"Mozhayevo",
    "wof:placetype":"locality"
},
  "geometry": {"coordinates":[32.68812,56.56604],"type":"Point"}
}