{
  "type": "Feature",
  "properties": {
    "gn:admin1_code":"85",
    "gn:asciiname":"Kobyl'ye",
    "gn:country_code":"RU",
    "gn:dem":125,
    "gn:feature_class":"P",
    "gn:feature_code":"PPL",
    "gn:name":"Kobyl\u2019ye",
    "gn:population":0,
    "gn:timezone":"Europe/Moscow",
    "iso:country":"RU",
    "name:rus_x_preferred":[
        "\u041a\u043e\u0431\u044b\u043b\u044c\u0435"
    ],
    "name:und_x_variant":[
        "Kobyl\u2019ye",
        "\u041a\u043e\u0431\u044b\u043b\u044c\u0435"
    ],
    "wof:name":"Kobyl'ye",
    "wof:placetype":"locality"
},
  "geometry": {"coordinates":[39.2872,60.0486],"type":"Point"}
}