{
  "type": "Feature",
  "properties": {
    "gn:admin1_code":"55",
    "gn:asciiname":"Zheltaya",
    "gn:cc2":"RU",
    "gn:country_code":"RU",
    "gn:dem":170,
    "gn:feature_class":"P",
    "gn:feature_code":"PPL",
    "gn:name":"Zh\u00ebltaya",
    "gn:population":0,
    "gn:timezone":"Asia/Yekaterinburg",
    "iso:country":"RU",
    "name:eng_x_preferred":[
        "Zh\u00ebltaya"
    ],
    "name:nor_x_preferred":[
        "Zjeltoje"
    ],
    "name:rus_x_preferred":[
        "\u0416\u0435\u043b\u0442\u043e\u0435"
    ],
    "name:und_x_variant":[
        "Zh\u00ebltoye",
        "Zhelty",
        "Zh\u00ebltyy"
    ],
    "wof:name":"Zheltaya",
    "wof:placetype":"locality"
},
  "geometry": {"coordinates":[56.58944,51.62861],"type":"Point"}
}