{
  "type": "Feature",
  "properties": {
    "gn:admin1_code":"8",
    "gn:asciiname":"Satra",
    "gn:country_code":"RU",
    "gn:dem":618,
    "gn:feature_class":"P",
    "gn:feature_code":"PPL",
    "gn:name":"Satra",
    "gn:population":0,
    "gn:timezone":"Asia/Yekaterinburg",
    "iso:country":"RU",
    "name:eng_x_preferred":[
        "Satra"
    ],
    "name:nor_x_preferred":[
        "Satra"
    ],
    "name:rus_x_preferred":[
        "\u0421\u0430\u0442\u0440\u0430"
    ],
    "wof:name":"Satra",
    "wof:placetype":"locality"
},
  "geometry": {"coordinates":[58.05806,53.93083000000001],"type":"Point"}
}