{
  "type": "Feature",
  "properties": {
    "gn:admin1_code":"55",
    "gn:asciiname":"Ivanov Dol",
    "gn:country_code":"RU",
    "gn:dem":272,
    "gn:feature_class":"P",
    "gn:feature_code":"PPL",
    "gn:name":"Ivanov Dol",
    "gn:population":0,
    "gn:timezone":"Asia/Yekaterinburg",
    "iso:country":"RU",
    "name:rus_x_preferred":[
        "\u0418\u0432\u0430\u043d\u043e\u0432 \u0414\u043e\u043b"
    ],
    "wof:name":"Ivanov Dol",
    "wof:placetype":"locality"
},
  "geometry": {"coordinates":[58.96666999999999,51.68333],"type":"Point"}
}