{
  "type": "Feature",
  "properties": {
    "gn:admin1_code":"59.0",
    "gn:asciiname":"Zelenodol'skoye",
    "gn:country_code":"RU",
    "gn:dem":82,
    "gn:feature_class":"P",
    "gn:feature_code":"PPL",
    "gn:name":"Zelenodol\u2019skoye",
    "gn:population":0,
    "gn:timezone":"Asia/Vladivostok",
    "iso:country":"RU",
    "wof:name":"Zelenodol'skoye",
    "wof:placetype":"locality"
},
  "geometry": {"coordinates":[133.07478,44.91966],"type":"Point"}
}