{
  "type": "Feature",
  "properties": {
    "gn:admin1_code":"16",
    "gn:asciiname":"Irkh-Sirmy",
    "gn:country_code":"RU",
    "gn:dem":126,
    "gn:feature_class":"P",
    "gn:feature_code":"PPL",
    "gn:name":"Irkh-Sirmy",
    "gn:population":0,
    "gn:timezone":"Europe/Moscow",
    "iso:country":"RU",
    "name:rus_x_preferred":[
        "\u0418\u0440\u0445-\u0421\u0438\u0440\u043c\u044b"
    ],
    "wof:name":"Irkh-Sirmy",
    "wof:placetype":"locality"
},
  "geometry": {"coordinates":[47.4494,55.6878],"type":"Point"}
}