{
  "type": "Feature",
  "properties": {
    "gn:admin1_code":"10",
    "gn:asciiname":"Makarichi",
    "gn:country_code":"RU",
    "gn:dem":134,
    "gn:feature_class":"P",
    "gn:feature_code":"PPL",
    "gn:name":"Makarichi",
    "gn:population":0,
    "gn:timezone":"Europe/Moscow",
    "iso:country":"RU",
    "name:rus_x_preferred":[
        "\u041c\u0430\u043a\u0430\u0440\u0438\u0447\u0438"
    ],
    "name:und_x_variant":[
        "\u041c\u0430\u043a\u0430\u0440\u0438\u0447\u0438"
    ],
    "wof:name":"Makarichi",
    "wof:placetype":"locality"
},
  "geometry": {"coordinates":[31.6386,53.0867],"type":"Point"}
}