{
  "type": "Feature",
  "properties": {
    "gn:admin1_code":"33",
    "gn:asciiname":"Vas'kino",
    "gn:country_code":"RU",
    "gn:dem":114,
    "gn:feature_class":"P",
    "gn:feature_code":"PPL",
    "gn:name":"Vas\u2019kino",
    "gn:population":0,
    "gn:timezone":"Europe/Kirov",
    "iso:country":"RU",
    "name:rus_x_preferred":[
        "\u0412\u0430\u0441\u044c\u043a\u0438\u043d\u043e"
    ],
    "name:und_x_variant":[
        "Vas\u2019kino"
    ],
    "wof:name":"Vas'kino",
    "wof:placetype":"locality"
},
  "geometry": {"coordinates":[47.35338,56.85929],"type":"Point"}
}