{
  "type": "Feature",
  "properties": {
    "gn:admin1_code":"37",
    "gn:asciiname":"Poloma",
    "gn:country_code":"RU",
    "gn:dem":197,
    "gn:feature_class":"P",
    "gn:feature_code":"PPL",
    "gn:name":"Poloma",
    "gn:population":0,
    "gn:timezone":"Europe/Moscow",
    "iso:country":"RU",
    "name:rus_x_preferred":[
        "\u041f\u043e\u043b\u043e\u043c\u0430"
    ],
    "name:und_x_variant":[
        "\u041f\u043e\u043b\u043e\u043c\u0430"
    ],
    "wof:name":"Poloma",
    "wof:placetype":"locality"
},
  "geometry": {"coordinates":[43.36606,58.65584000000001],"type":"Point"}
}