{
  "type": "Feature",
  "properties": {
    "gn:admin1_code":"70.0",
    "gn:asciiname":"Chograyskiy",
    "gn:country_code":"RU",
    "gn:dem":52,
    "gn:feature_class":"P",
    "gn:feature_code":"PPL",
    "gn:name":"Chograyskiy",
    "gn:population":0,
    "gn:timezone":"Europe/Moscow",
    "iso:country":"RU",
    "name:eng_x_preferred":[
        "Chograyskiy"
    ],
    "name:nor_x_preferred":[
        "Tsjograjskij"
    ],
    "name:rus_x_preferred":[
        "\u0427\u043e\u0433\u0440\u0430\u0439\u0441\u043a\u0438\u0439"
    ],
    "wof:name":"Chograyskiy",
    "wof:placetype":"locality"
},
  "geometry": {"coordinates":[44.58361,45.34778],"type":"Point"}
}