{
  "type": "Feature",
  "properties": {
    "gn:admin1_code":"33",
    "gn:asciiname":"Sedunovshchina",
    "gn:country_code":"RU",
    "gn:dem":154,
    "gn:feature_class":"P",
    "gn:feature_code":"PPL",
    "gn:name":"Sedunovshchina",
    "gn:population":0,
    "gn:timezone":"Europe/Kirov",
    "iso:country":"RU",
    "name:rus_x_preferred":[
        "\u0421\u0435\u0434\u0443\u043d\u043e\u0432\u0449\u0438\u043d\u0430"
    ],
    "wof:name":"Sedunovshchina",
    "wof:placetype":"locality"
},
  "geometry": {"coordinates":[49.5265,58.5078],"type":"Point"}
}