{
  "type": "Feature",
  "properties": {
    "gn:admin1_code":"68.0",
    "gn:asciiname":"Kumbulta",
    "gn:country_code":"RU",
    "gn:dem":1676,
    "gn:feature_class":"P",
    "gn:feature_code":"PPL",
    "gn:name":"Kumbulta",
    "gn:population":0,
    "gn:timezone":"Europe/Moscow",
    "iso:country":"RU",
    "name:rus_x_preferred":[
        "\u041a\u0443\u043c\u0431\u0443\u043b\u0442\u0430"
    ],
    "wof:name":"Kumbulta",
    "wof:placetype":"locality"
},
  "geometry": {"coordinates":[43.757,42.98985],"type":"Point"}
}