{
  "type": "Feature",
  "properties": {
    "gn:admin1_code":"73",
    "gn:asciiname":"Nizhniye Savrushi",
    "gn:country_code":"RU",
    "gn:dem":120,
    "gn:feature_class":"P",
    "gn:feature_code":"PPL",
    "gn:name":"Nizhniye Savrushi",
    "gn:population":0,
    "gn:timezone":"Europe/Moscow",
    "iso:country":"RU",
    "name:rus_x_preferred":[
        "\u041d\u0438\u0436\u043d\u0438\u0435 \u0421\u0430\u0432\u0440\u0443\u0448\u0438"
    ],
    "wof:name":"Nizhniye Savrushi",
    "wof:placetype":"locality"
},
  "geometry": {"coordinates":[50.68371,55.03941999999999],"type":"Point"}
}