{
  "type": "Feature",
  "properties": {
    "gn:admin1_code":"42",
    "gn:admin2_code":"575409",
    "gn:asciiname":"Koygushi",
    "gn:cc2":"RU",
    "gn:country_code":"RU",
    "gn:dem":211,
    "gn:feature_class":"P",
    "gn:feature_code":"PPL",
    "gn:name":"Koygushi",
    "gn:population":0,
    "gn:timezone":"Europe/Moscow",
    "iso:country":"RU",
    "name:rus_x_preferred":[
        "\u041a\u043e\u0439\u0433\u0443\u0448\u0438"
    ],
    "name:und_x_variant":[
        "Kaygushi",
        "Koygushskiy",
        "Koygushi"
    ],
    "wof:name":"Koygushi",
    "wof:placetype":"locality"
},
  "geometry": {"coordinates":[34.71361,59.70194],"type":"Point"}
}