{
  "type": "Feature",
  "properties": {
    "gn:admin1_code":"57",
    "gn:asciiname":"Novopolyanskoye",
    "gn:country_code":"RU",
    "gn:dem":276,
    "gn:feature_class":"P",
    "gn:feature_code":"PPL",
    "gn:name":"Novopolyanskoye",
    "gn:population":0,
    "gn:timezone":"Europe/Moscow",
    "iso:country":"RU",
    "name:rus_x_preferred":[
        "\u041d\u043e\u0432\u043e\u043f\u043e\u043b\u044f\u043d\u0441\u043a\u043e\u0435"
    ],
    "wof:name":"Novopolyanskoye",
    "wof:placetype":"locality"
},
  "geometry": {"coordinates":[46.56314,53.4423],"type":"Point"}
}