{
  "type": "Feature",
  "properties": {
    "gn:country":"RU",
    "gn:fcode":"PPL",
    "gn:population":0,
    "iso:country":"RU",
    "name:nor_x_preferred":[
        "Dolgij Bujerak"
    ],
    "name:rus_x_preferred":[
        "\u0414\u043e\u043b\u0433\u0438\u0439 \u0411\u0443\u0435\u0440\u0430\u043a"
    ],
    "name:und_x_variant":[
        "Dolgo-Burak"
    ],
    "qs:name":"Dolgiy Buyerak",
    "qs:name_adm0":"Russia",
    "qs:name_adm1":"Saratov Oblast",
    "qs:photos_9r":0,
    "qs:photos_sr":0,
    "qs:placetype":"Town",
    "qs:pop_sr":"0",
    "wof:name":"Dolgiy Buyerak",
    "wof:placetype":"locality",
    "wof:population":0
},
  "geometry": {"coordinates":[46.12655,51.62287],"type":"Point"}
}