{
  "type": "Feature",
  "properties": {
    "gn:admin1_code":"61",
    "gn:asciiname":"Derkul",
    "gn:country_code":"RU",
    "gn:dem":45,
    "gn:feature_class":"P",
    "gn:feature_code":"PPL",
    "gn:name":"Derkul",
    "gn:population":0,
    "gn:timezone":"Europe/Moscow",
    "iso:country":"RU",
    "name:rus_x_preferred":[
        "\u0414\u0435\u0440\u043a\u0443\u043b"
    ],
    "name:und_x_variant":[
        "\u0414\u0435\u0440\u043a\u0443\u043b"
    ],
    "wof:name":"Derkul",
    "wof:placetype":"locality"
},
  "geometry": {"coordinates":[39.8061,48.824],"type":"Point"}
}