{
  "type": "Feature",
  "properties": {
    "gn:admin1_code":"90",
    "gn:asciiname":"Karsakova",
    "gn:country_code":"RU",
    "gn:dem":132,
    "gn:feature_class":"P",
    "gn:feature_code":"PPL",
    "gn:name":"Karsakova",
    "gn:population":0,
    "gn:timezone":"Asia/Yekaterinburg",
    "iso:country":"RU",
    "name:rus_x_preferred":[
        "\u041a\u0430\u0440\u0441\u0430\u043a\u043e\u0432\u0430"
    ],
    "name:und_x_variant":[
        "Korsakovo",
        "Karsakova"
    ],
    "wof:name":"Karsakova",
    "wof:placetype":"locality"
},
  "geometry": {"coordinates":[56.7645,58.0554],"type":"Point"}
}