{
  "type": "Feature",
  "properties": {
    "gn:admin1_code":"77",
    "gn:asciiname":"Yerokhino",
    "gn:country_code":"RU",
    "gn:dem":208,
    "gn:feature_class":"P",
    "gn:feature_code":"PPL",
    "gn:name":"Yerokhino",
    "gn:population":0,
    "gn:timezone":"Europe/Moscow",
    "iso:country":"RU",
    "name:rus_x_preferred":[
        "\u0415\u0440\u043e\u0445\u0438\u043d\u043e"
    ],
    "wof:name":"Yerokhino",
    "wof:placetype":"locality"
},
  "geometry": {"coordinates":[32.18682,56.54865],"type":"Point"}
}