{
  "type": "Feature",
  "properties": {
    "gn:admin1_code":"71.0",
    "gn:asciiname":"Sos'va Novaya",
    "gn:country_code":"RU",
    "gn:dem":88,
    "gn:feature_class":"P",
    "gn:feature_code":"PPL",
    "gn:name":"Sos\u2019va Novaya",
    "gn:population":0,
    "gn:timezone":"Asia/Yekaterinburg",
    "iso:country":"RU",
    "name:rus_x_preferred":[
        "\u0421\u043e\u0441\u044c\u0432\u0430 \u041d\u043e\u0432\u0430\u044f"
    ],
    "name:und_x_variant":[
        "Sos\u2019va Novaya"
    ],
    "wof:name":"Sos'va Novaya",
    "wof:placetype":"locality"
},
  "geometry": {"coordinates":[61.7538,59.13711],"type":"Point"}
}