{
  "type": "Feature",
  "properties": {
    "gn:admin1_code":"65",
    "gn:asciiname":"Tolcherech'ye",
    "gn:country_code":"RU",
    "gn:dem":169,
    "gn:feature_class":"P",
    "gn:feature_code":"PPL",
    "gn:name":"Tolcherech\u2019ye",
    "gn:population":0,
    "gn:timezone":"Europe/Samara",
    "iso:country":"RU",
    "name:rus_x_preferred":[
        "\u0422\u043e\u043b\u0447\u0435\u0440\u0435\u0447\u044c\u0435"
    ],
    "name:und_x_variant":[
        "Tolcherech\u2019ye"
    ],
    "wof:name":"Tolcherech'ye",
    "wof:placetype":"locality"
},
  "geometry": {"coordinates":[51.5405,54.4926],"type":"Point"}
}