{
  "type": "Feature",
  "properties": {
    "gn:admin1_code":"5",
    "gn:asciiname":"Vasil'yevskiy",
    "gn:country_code":"RU",
    "gn:dem":224,
    "gn:feature_class":"P",
    "gn:feature_code":"PPL",
    "gn:name":"Vasil\u2019yevskiy",
    "gn:population":0,
    "gn:timezone":"Asia/Yakutsk",
    "iso:country":"RU",
    "name:eng_x_preferred":[
        "Vasil'yevskiy"
    ],
    "name:nor_x_preferred":[
        "Vasiljevskij"
    ],
    "name:rus_x_preferred":[
        "\u0412\u0430\u0441\u0438\u043b\u044c\u0435\u0432\u0441\u043a\u0438\u0439"
    ],
    "name:und_x_variant":[
        "Vasil\u2019yevskiy"
    ],
    "wof:name":"Vasil'yevskiy",
    "wof:placetype":"locality"
},
  "geometry": {"coordinates":[129.53253999999998,52.27448],"type":"Point"}
}