{
  "type": "Feature",
  "properties": {
    "gn:admin1_code":"28",
    "gn:asciiname":"Nigizhma",
    "gn:country_code":"RU",
    "gn:dem":70,
    "gn:feature_class":"P",
    "gn:feature_code":"PPL",
    "gn:name":"Nigizhma",
    "gn:population":0,
    "gn:timezone":"Europe/Moscow",
    "iso:country":"RU",
    "name:eng_x_preferred":[
        "Nigizhma"
    ],
    "name:nor_x_preferred":[
        "Nigizjma"
    ],
    "name:rus_x_preferred":[
        "\u041d\u0438\u0433\u0438\u0436\u043c\u0430"
    ],
    "name:und_x_variant":[
        "Nigi\u017ema",
        "\u041d\u0438\u0433\u0438\u0436\u043c\u0430",
        "Nigizhma"
    ],
    "wof:name":"Nigizhma",
    "wof:placetype":"locality"
},
  "geometry": {"coordinates":[36.35831,61.66956],"type":"Point"}
}