{
  "type": "Feature",
  "properties": {
    "gn:admin1_code":"91",
    "gn:asciiname":"Novoaleksandrovka",
    "gn:country_code":"RU",
    "gn:dem":269,
    "gn:feature_class":"P",
    "gn:feature_code":"PPL",
    "gn:name":"Novoaleksandrovka",
    "gn:population":0,
    "gn:timezone":"Asia/Krasnoyarsk",
    "iso:country":"RU",
    "name:eng_x_preferred":[
        "Novoaleksandrovka"
    ],
    "name:nor_x_preferred":[
        "Novoaleksandrovka"
    ],
    "name:rus_x_preferred":[
        "\u041d\u043e\u0432\u043e\u0430\u043b\u0435\u043a\u0441\u0430\u043d\u0434\u0440\u043e\u0432\u043a\u0430"
    ],
    "name:und_x_variant":[
        "Novaya Aleksandrovka",
        "Novoaleksandrovka"
    ],
    "wof:name":"Novoaleksandrovka",
    "wof:placetype":"locality"
},
  "geometry": {"coordinates":[96.5792,56.4218],"type":"Point"}
}