{
  "type": "Feature",
  "properties": {
    "gn:admin1_code":"77.0",
    "gn:asciiname":"Bocharovo",
    "gn:country_code":"RU",
    "gn:dem":210,
    "gn:feature_class":"P",
    "gn:feature_code":"PPL",
    "gn:name":"Bocharovo",
    "gn:population":0,
    "gn:timezone":"Europe/Moscow",
    "iso:country":"RU",
    "name:rus_x_preferred":[
        "\u0411\u043e\u0447\u0430\u0440\u043e\u0432\u043e"
    ],
    "name:und_x_variant":[
        "\u0411\u043e\u0447\u0430\u0440\u043e\u0432\u043e"
    ],
    "wof:name":"Bocharovo",
    "wof:placetype":"locality"
},
  "geometry": {"coordinates":[34.15,56.13333000000001],"type":"Point"}
}