{
  "type": "Feature",
  "properties": {
    "gn:admin1_code":"25",
    "gn:asciiname":"Kokhanovo",
    "gn:country_code":"RU",
    "gn:dem":131,
    "gn:feature_class":"P",
    "gn:feature_code":"PPL",
    "gn:name":"Kokhanovo",
    "gn:population":0,
    "gn:timezone":"Europe/Moscow",
    "iso:country":"RU",
    "name:rus_x_preferred":[
        "\u041a\u043e\u0445\u0430\u043d\u043e\u0432\u043e"
    ],
    "name:und_x_variant":[
        "Kokhinovo",
        "Kokhanovo"
    ],
    "wof:name":"Kokhanovo",
    "wof:placetype":"locality"
},
  "geometry": {"coordinates":[37.1448,54.60717],"type":"Point"}
}