{
  "type": "Feature",
  "properties": {
    "gn:country":"RU",
    "gn:fcode":"PPL",
    "gn:pop":100,
    "iso:country":"RU",
    "name:rus_x_preferred":[
        "\u0411\u043e\u0440\u043e\u0434\u0438\u043d\u043e"
    ],
    "name:unk_x_variant":[
        "Borodino"
    ],
    "qs:name":"Gordino",
    "qs:name_adm0":"Russia",
    "qs:name_adm1":"Moscow Oblast",
    "qs:photos_9r":0,
    "qs:photos_sr":0,
    "qs:placetype":"Town",
    "qs:pop_sr":"1",
    "wof:name":"Gordino",
    "wof:placetype":"locality",
    "wof:population":100
},
  "geometry": {"coordinates":[37.65955,55.92512],"type":"Point"}
}