{
  "type": "Feature",
  "properties": {
    "gn:admin1_code":"84",
    "gn:asciiname":"Verkhnesolonovskiy",
    "gn:country_code":"RU",
    "gn:dem":62,
    "gn:feature_class":"P",
    "gn:feature_code":"PPL",
    "gn:name":"Verkhnesolonovskiy",
    "gn:population":0,
    "gn:timezone":"Europe/Volgograd",
    "iso:country":"RU",
    "name:eng_x_preferred":[
        "Verkhnesolonovskiy"
    ],
    "name:nor_x_preferred":[
        "Verkhnesolonovskij"
    ],
    "name:rus_x_preferred":[
        "\u0412\u0435\u0440\u0445\u043d\u0435\u0441\u043e\u043b\u043e\u043d\u043e\u0432\u0441\u043a\u0438\u0439"
    ],
    "name:und_x_variant":[
        "Verkhniy Solonovskiy",
        "Verkhne-Salonovskiy"
    ],
    "wof:name":"Verkhnesolonovskiy",
    "wof:placetype":"locality"
},
  "geometry": {"coordinates":[42.83488,48.3762],"type":"Point"}
}