{
  "type": "Feature",
  "properties": {
    "gn:admin1_code":"47",
    "gn:asciiname":"Koncheyevo",
    "gn:country_code":"RU",
    "gn:dem":177,
    "gn:feature_class":"P",
    "gn:feature_code":"PPL",
    "gn:name":"Koncheyevo",
    "gn:population":0,
    "gn:timezone":"Europe/Moscow",
    "iso:country":"RU",
    "name:rus_x_preferred":[
        "\u041a\u043e\u043d\u0447\u0435\u0435\u0432\u043e"
    ],
    "name:und_x_variant":[
        "Kancheyevo",
        "Koncheyevo"
    ],
    "wof:name":"Koncheyevo",
    "wof:placetype":"locality"
},
  "geometry": {"coordinates":[37.28111,55.54833000000001],"type":"Point"}
}