{
  "type": "Feature",
  "properties": {
    "gn:admin1_code":"63",
    "gn:asciiname":"Kharbala",
    "gn:country_code":"RU",
    "gn:dem":160,
    "gn:feature_class":"P",
    "gn:feature_code":"PPL",
    "gn:name":"Kharbala",
    "gn:population":0,
    "gn:timezone":"Asia/Yakutsk",
    "iso:country":"RU",
    "name:che_x_preferred":[
        "\u0425\u0430\u0440\u0431\u0430\u043b\u0430"
    ],
    "name:rus_x_preferred":[
        "\u0425\u0430\u0440\u0431\u0430\u043b\u0430"
    ],
    "name:sah_x_preferred":[
        "\u0425\u0430\u0440\u0431\u0430\u043b\u0430"
    ],
    "name:ukr_x_preferred":[
        "\u0425\u0430\u0440\u0431\u0430\u043b\u0430"
    ],
    "wof:name":"Kharbala",
    "wof:placetype":"locality"
},
  "geometry": {"coordinates":[132.57758999999999,61.99164],"type":"Point"}
}