{
  "type": "Feature",
  "properties": {
    "gn:admin1_code":"51.0",
    "gn:asciiname":"Natalinka",
    "gn:country_code":"RU",
    "gn:dem":122,
    "gn:feature_class":"P",
    "gn:feature_code":"PPL",
    "gn:name":"Natalinka",
    "gn:population":0,
    "gn:timezone":"Europe/Moscow",
    "iso:country":"RU",
    "name:rus_x_preferred":[
        "\u041d\u0430\u0442\u0430\u043b\u0438\u043d\u043a\u0430"
    ],
    "wof:name":"Natalinka",
    "wof:placetype":"locality"
},
  "geometry": {"coordinates":[44.77475,54.5726],"type":"Point"}
}