{
  "type": "Feature",
  "properties": {
    "gn:admin1_code":"33.0",
    "gn:asciiname":"Zelenovshchina",
    "gn:country_code":"RU",
    "gn:dem":107,
    "gn:feature_class":"P",
    "gn:feature_code":"PPL",
    "gn:name":"Zelenovshchina",
    "gn:population":0,
    "gn:timezone":"Europe/Kirov",
    "iso:country":"RU",
    "name:rus_x_preferred":[
        "\u0417\u0435\u043b\u0435\u043d\u043e\u0432\u0449\u0438\u043d\u0430"
    ],
    "wof:name":"Zelenovshchina",
    "wof:placetype":"locality"
},
  "geometry": {"coordinates":[48.84277,57.51102],"type":"Point"}
}