{
  "type": "Feature",
  "properties": {
    "gn:admin1_code":"25",
    "gn:asciiname":"Sutoki",
    "gn:country_code":"RU",
    "gn:dem":206,
    "gn:feature_class":"P",
    "gn:feature_code":"PPL",
    "gn:name":"Sutoki",
    "gn:population":0,
    "gn:timezone":"Europe/Moscow",
    "iso:country":"RU",
    "name:und_x_variant":[
        "Sutoka",
        "Sutoki"
    ],
    "wof:name":"Sutoki",
    "wof:placetype":"locality"
},
  "geometry": {"coordinates":[34.65677,54.25431],"type":"Point"}
}