{
  "type": "Feature",
  "properties": {
    "gn:country":"RU",
    "gn:fcode":"PPL",
    "gn:pop":0,
    "iso:country":"RU",
    "name:rus_x_preferred":[
        "\u041c\u0430\u043c\u043e\u043d\u043e\u0432\u043e"
    ],
    "name:unk_x_variant":[
        "\u041c\u0430\u043c\u043e\u043d\u043e\u0432\u043e"
    ],
    "qs:name":"Mamonovo",
    "qs:name_adm0":"Russia",
    "qs:name_adm1":"Moscow Oblast",
    "qs:photos":469,
    "qs:photos_1k":95,
    "qs:photos_9k":2,
    "qs:photos_9r":5,
    "qs:photos_all":469,
    "qs:photos_sr":7,
    "qs:placetype":"Town",
    "qs:pop_sr":"0",
    "wd:wordcount":932,
    "wof:name":"Mamonovo",
    "wof:placetype":"locality",
    "wof:population":0
},
  "geometry": {"coordinates":[37.31731,55.68712],"type":"Point"}
}