{
  "type": "Feature",
  "properties": {
    "gn:admin1_code":"40",
    "gn:asciiname":"Staropershino",
    "gn:country_code":"RU",
    "gn:dem":99,
    "gn:feature_class":"P",
    "gn:feature_code":"PPL",
    "gn:name":"Staropershino",
    "gn:population":0,
    "gn:timezone":"Asia/Yekaterinburg",
    "iso:country":"RU",
    "name:eng_x_preferred":[
        "Staropershino"
    ],
    "name:nor_x_preferred":[
        "Staropersjino"
    ],
    "name:rus_x_preferred":[
        "\u0421\u0442\u0430\u0440\u043e\u043f\u0435\u0440\u0448\u0438\u043d\u043e"
    ],
    "wof:name":"Staropershino",
    "wof:placetype":"locality"
},
  "geometry": {"coordinates":[66.41639000000001,55.69361],"type":"Point"}
}