{
  "type": "Feature",
  "properties": {
    "gn:admin1_code":"05",
    "gn:asciiname":"Gudachi",
    "gn:country_code":"RU",
    "gn:dem":448,
    "gn:feature_class":"P",
    "gn:feature_code":"PPL",
    "gn:name":"Gudachi",
    "gn:population":0,
    "gn:timezone":"Asia/Yakutsk",
    "iso:country":"RU",
    "name:eng_x_preferred":[
        "Gudachi"
    ],
    "name:nor_x_preferred":[
        "Gudatsji"
    ],
    "name:rus_x_preferred":[
        "\u0413\u0443\u0434\u0430\u0447\u0438"
    ],
    "name:und_x_variant":[
        "\u0413\u0443\u0434\u0430\u0447\u0438",
        "Gudachi"
    ],
    "wof:name":"Gudachi",
    "wof:placetype":"locality"
},
  "geometry": {"coordinates":[125.23408000000001,53.68595],"type":"Point"}
}