{
  "type": "Feature",
  "properties": {
    "gn:admin1_code":"40",
    "gn:asciiname":"Makatashkina",
    "gn:country_code":"RU",
    "gn:dem":137,
    "gn:feature_class":"P",
    "gn:feature_code":"PPL",
    "gn:name":"Makatashkina",
    "gn:population":0,
    "gn:timezone":"Asia/Yekaterinburg",
    "iso:country":"RU",
    "name:rus_x_preferred":[
        "\u041c\u0430\u043a\u0430\u0442\u0430\u0448\u043a\u0438\u043d\u0430"
    ],
    "name:und_x_variant":[
        "\u041c\u0430\u043a\u0430\u0442\u0430\u0448\u043a\u0438\u043d\u0430"
    ],
    "wof:name":"Makatashkina",
    "wof:placetype":"locality"
},
  "geometry": {"coordinates":[64.21889,55.44278000000001],"type":"Point"}
}