{
  "type": "Feature",
  "properties": {
    "gn:admin1_code":"40",
    "gn:asciiname":"Krutikha",
    "gn:country_code":"RU",
    "gn:dem":76,
    "gn:feature_class":"P",
    "gn:feature_code":"PPL",
    "gn:name":"Krutikha",
    "gn:population":0,
    "gn:timezone":"Asia/Yekaterinburg",
    "iso:country":"RU",
    "name:rus_x_preferred":[
        "\u041a\u0440\u0443\u0442\u0438\u0445\u0430"
    ],
    "name:und_x_variant":[
        "\u041a\u0440\u0443\u0442\u0438\u0445\u0430"
    ],
    "wof:name":"Krutikha",
    "wof:placetype":"locality"
},
  "geometry": {"coordinates":[65.66972,55.66972],"type":"Point"}
}