{
  "type": "Feature",
  "properties": {
    "gn:admin1_code":"56",
    "gn:asciiname":"Khlopovo",
    "gn:country_code":"RU",
    "gn:dem":178,
    "gn:feature_class":"P",
    "gn:feature_code":"PPL",
    "gn:name":"Khlopovo",
    "gn:population":0,
    "gn:timezone":"Europe/Moscow",
    "iso:country":"RU",
    "name:rus_x_preferred":[
        "\u0425\u043b\u043e\u043f\u043e\u0432\u043e"
    ],
    "name:und_x_variant":[
        "\u0425\u043b\u043e\u043f\u043e\u0432\u043e"
    ],
    "wof:name":"Khlopovo",
    "wof:placetype":"locality"
},
  "geometry": {"coordinates":[35.926,52.6021],"type":"Point"}
}