{
  "type": "Feature",
  "properties": {
    "gn:admin1_code":"33",
    "gn:asciiname":"Karino",
    "gn:country_code":"RU",
    "gn:dem":151,
    "gn:feature_class":"P",
    "gn:feature_code":"PPL",
    "gn:name":"Karino",
    "gn:population":0,
    "gn:timezone":"Europe/Kirov",
    "iso:country":"RU",
    "name:eng_x_preferred":[
        "Karino"
    ],
    "name:nor_x_preferred":[
        "Karino"
    ],
    "name:rus_x_preferred":[
        "\u041a\u0430\u0440\u0438\u043d\u043e"
    ],
    "name:und_x_variant":[
        "Nizhneye Karino",
        "Nizhnyaya Karinka",
        "\u041a\u0430\u0440\u0438\u043d\u043e",
        "Karino"
    ],
    "wof:name":"Karino",
    "wof:placetype":"locality"
},
  "geometry": {"coordinates":[50.33331,58.61695],"type":"Point"}
}