{
  "type": "Feature",
  "properties": {
    "gn:admin1_code":"61",
    "gn:asciiname":"Budanovka",
    "gn:country_code":"RU",
    "gn:dem":122,
    "gn:feature_class":"P",
    "gn:feature_code":"PPL",
    "gn:name":"Budanovka",
    "gn:population":0,
    "gn:timezone":"Europe/Moscow",
    "iso:country":"RU",
    "name:rus_x_preferred":[
        "\u0411\u0443\u0434\u0430\u043d\u043e\u0432\u043a\u0430"
    ],
    "name:und_x_variant":[
        "Budanovskiy",
        "Budanovka",
        "\u0411\u0443\u0434\u0430\u043d\u043e\u0432\u043a\u0430"
    ],
    "wof:name":"Budanovka",
    "wof:placetype":"locality"
},
  "geometry": {"coordinates":[41.34952,49.27317],"type":"Point"}
}