{
  "type": "Feature",
  "properties": {
    "gn:admin1_code":"8",
    "gn:asciiname":"Kryuchevka",
    "gn:country_code":"RU",
    "gn:dem":123,
    "gn:feature_class":"P",
    "gn:feature_code":"PPL",
    "gn:name":"Kryuchevka",
    "gn:population":0,
    "gn:timezone":"Asia/Yekaterinburg",
    "iso:country":"RU",
    "name:rus_x_preferred":[
        "\u041a\u0440\u044e\u0447\u0435\u0432\u043a\u0430"
    ],
    "name:und_x_variant":[
        "Kurcheyevka"
    ],
    "wof:name":"Kryuchevka",
    "wof:placetype":"locality"
},
  "geometry": {"coordinates":[56.2737,54.6919],"type":"Point"}
}