{
  "type": "Feature",
  "properties": {
    "gn:admin1_code":"9.0",
    "gn:asciiname":"Postol'niki",
    "gn:country_code":"RU",
    "gn:dem":173,
    "gn:feature_class":"P",
    "gn:feature_code":"PPL",
    "gn:name":"Postol\u2019niki",
    "gn:population":0,
    "gn:timezone":"Europe/Moscow",
    "iso:country":"RU",
    "name:und_x_variant":[
        "Postol\u2019nikov",
        "Postol\u2019niki"
    ],
    "wof:name":"Postol'niki",
    "wof:placetype":"locality"
},
  "geometry": {"coordinates":[36.19809,50.52986],"type":"Point"}
}