{
  "type": "Feature",
  "properties": {
    "gn:admin1_code":"40",
    "gn:asciiname":"Mekhonskoye",
    "gn:country_code":"RU",
    "gn:dem":68,
    "gn:feature_class":"P",
    "gn:feature_code":"PPL",
    "gn:name":"Mekhonskoye",
    "gn:population":0,
    "gn:timezone":"Asia/Yekaterinburg",
    "iso:country":"RU",
    "name:eng_x_preferred":[
        "Mekhonskoye"
    ],
    "name:nor_x_preferred":[
        "Mekhonskoje"
    ],
    "name:rus_x_preferred":[
        "\u041c\u0435\u0445\u043e\u043d\u0441\u043a\u043e\u0435"
    ],
    "name:und_x_variant":[
        "\u041c\u0435\u0445\u043e\u043d\u0441\u043a\u043e\u0435",
        "Mekhonskoye"
    ],
    "wof:name":"Mekhonskoye",
    "wof:placetype":"locality"
},
  "geometry": {"coordinates":[64.5761,56.1669],"type":"Point"}
}