{
  "type": "Feature",
  "properties": {
    "gn:admin1_code":"55.0",
    "gn:asciiname":"Gabdrafikovo",
    "gn:country_code":"RU",
    "gn:dem":182,
    "gn:feature_class":"P",
    "gn:feature_code":"PPL",
    "gn:name":"Gabdrafikovo",
    "gn:population":0,
    "gn:timezone":"Asia/Yekaterinburg",
    "iso:country":"RU",
    "name:rus_x_preferred":[
        "\u0413\u0430\u0431\u0434\u0440\u0430\u0444\u0438\u043a\u043e\u0432\u043e"
    ],
    "wof:name":"Gabdrafikovo",
    "wof:placetype":"locality"
},
  "geometry": {"coordinates":[54.36666999999999,52.35],"type":"Point"}
}