{
  "type": "Feature",
  "properties": {
    "gn:admin1_code":"11",
    "gn:asciiname":"Innokent'yevskoye",
    "gn:country_code":"RU",
    "gn:dem":555,
    "gn:feature_class":"P",
    "gn:feature_code":"PPL",
    "gn:name":"Innokent\u2019yevskoye",
    "gn:population":0,
    "gn:timezone":"Asia/Irkutsk",
    "iso:country":"RU",
    "name:rus_x_preferred":[
        "\u0418\u043d\u043d\u043e\u043a\u0435\u043d\u0442\u044c\u0435\u0432\u0441\u043a\u043e\u0435"
    ],
    "name:und_x_variant":[
        "Innokenti\u2019yevskoye",
        "Innokent\u2019yev",
        "Innokent\u2019yevskoye"
    ],
    "wof:name":"Innokent'yevskoye",
    "wof:placetype":"locality"
},
  "geometry": {"coordinates":[106.25,50.91667],"type":"Point"}
}