{
  "type": "Feature",
  "properties": {
    "gn:admin1_code":"60",
    "gn:asciiname":"Isayevo",
    "gn:country_code":"RU",
    "gn:dem":161,
    "gn:feature_class":"P",
    "gn:feature_code":"PPL",
    "gn:name":"Isayevo",
    "gn:population":0,
    "gn:timezone":"Europe/Moscow",
    "iso:country":"RU",
    "name:ell_x_preferred":[
        "\u0399\u03c3\u03ac\u03b3\u03b9\u03b5\u03b2\u03bf"
    ],
    "name:msa_x_preferred":[
        "Isayevo"
    ],
    "name:rus_x_preferred":[
        "\u0418\u0441\u0430\u0435\u0432\u043e"
    ],
    "wof:name":"Isayevo",
    "wof:placetype":"locality"
},
  "geometry": {"coordinates":[29.518,56.2524],"type":"Point"}
}