{
  "type": "Feature",
  "properties": {
    "gn:country":"RU",
    "gn:fcode":"PPL",
    "gn:pop":0,
    "iso:country":"RU",
    "name:eng_x_preferred":[
        "Siz'ma"
    ],
    "name:nor_x_preferred":[
        "Sizma"
    ],
    "name:rus_x_preferred":[
        "\u0421\u0438\u0437\u044c\u043c\u0430"
    ],
    "name:unk_x_variant":[
        "Bol\u2019shaya Siz\u2019ma"
    ],
    "qs:name":"Siz'ma",
    "qs:name_adm0":"Russia",
    "qs:name_adm1":"Vologda Oblast",
    "qs:photos_9r":0,
    "qs:photos_sr":0,
    "qs:placetype":"Town",
    "qs:pop_sr":"0",
    "wof:name":"Siz'ma",
    "wof:placetype":"locality",
    "wof:population":0
},
  "geometry": {"coordinates":[38.7078,59.4149],"type":"Point"}
}