{
  "type": "Feature",
  "properties": {
    "gn:admin1_code":"60",
    "gn:asciiname":"Novoselki",
    "gn:country_code":"RU",
    "gn:dem":138,
    "gn:feature_class":"P",
    "gn:feature_code":"PPL",
    "gn:name":"Novos\u00eblki",
    "gn:population":0,
    "gn:timezone":"Europe/Moscow",
    "iso:country":"RU",
    "name:rus_x_preferred":[
        "\u041d\u043e\u0432\u043e\u0441\u0451\u043b\u043a\u0438"
    ],
    "name:und_x_variant":[
        "Novos\u00eblki",
        "\u041d\u043e\u0432\u043e\u0441\u0451\u043b\u043a\u0438"
    ],
    "wof:name":"Novoselki",
    "wof:placetype":"locality"
},
  "geometry": {"coordinates":[30.7213,56.3138],"type":"Point"}
}