{
  "type": "Feature",
  "properties": {
    "gn:admin1_code":"29",
    "gn:asciiname":"Aksenovka",
    "gn:country_code":"RU",
    "gn:dem":262,
    "gn:feature_class":"P",
    "gn:feature_code":"PPL",
    "gn:name":"Aks\u00ebnovka",
    "gn:population":0,
    "gn:timezone":"Asia/Novokuznetsk",
    "iso:country":"RU",
    "name:rus_x_preferred":[
        "\u0410\u043a\u0441\u0451\u043d\u043e\u0432\u043a\u0430"
    ],
    "name:und_x_variant":[
        "Aks\u00ebnovka",
        "\u0410\u043a\u0441\u0451\u043d\u043e\u0432\u043a\u0430"
    ],
    "wof:name":"Aksenovka",
    "wof:placetype":"locality"
},
  "geometry": {"coordinates":[87.1023,53.4572],"type":"Point"}
}