{
  "type": "Feature",
  "properties": {
    "gn:admin1_code":"69",
    "gn:asciiname":"D'yakovo",
    "gn:country_code":"RU",
    "gn:dem":207,
    "gn:feature_class":"P",
    "gn:feature_code":"PPL",
    "gn:name":"D\u2019yakovo",
    "gn:population":0,
    "gn:timezone":"Europe/Moscow",
    "iso:country":"RU",
    "name:rus_x_preferred":[
        "\u0414\u044c\u044f\u043a\u043e\u0432\u043e"
    ],
    "name:und_x_variant":[
        "D\u2019yakovo"
    ],
    "wof:name":"D'yakovo",
    "wof:placetype":"locality"
},
  "geometry": {"coordinates":[33.62306,55.245],"type":"Point"}
}