{
  "type": "Feature",
  "properties": {
    "gn:admin1_code":"60",
    "gn:asciiname":"Bystretsovo",
    "gn:country_code":"RU",
    "gn:dem":46,
    "gn:feature_class":"P",
    "gn:feature_code":"PPL",
    "gn:name":"Bystretsovo",
    "gn:population":0,
    "gn:timezone":"Europe/Moscow",
    "iso:country":"RU",
    "name:rus_x_preferred":[
        "\u0411\u044b\u0441\u0442\u0440\u0435\u0446\u043e\u0432\u043e"
    ],
    "wof:name":"Bystretsovo",
    "wof:placetype":"locality"
},
  "geometry": {"coordinates":[28.8508,57.712],"type":"Point"}
}