{
  "type": "Feature",
  "properties": {
    "gn:admin1_code":"29.0",
    "gn:asciiname":"Chibil'chikha",
    "gn:country_code":"RU",
    "gn:dem":403,
    "gn:feature_class":"P",
    "gn:feature_code":"PPL",
    "gn:name":"Chibil\u2019chikha",
    "gn:population":0,
    "gn:timezone":"Asia/Novokuznetsk",
    "iso:country":"RU",
    "name:rus_x_preferred":[
        "\u0427\u0438\u0431\u0438\u043b\u044c\u0447\u0438\u0445\u0430"
    ],
    "name:und_x_variant":[
        "Chibil\u2019chikha"
    ],
    "wof:name":"Chibil'chikha",
    "wof:placetype":"locality"
},
  "geometry": {"coordinates":[85.9229,54.1857],"type":"Point"}
}