{
  "type": "Feature",
  "properties": {
    "gn:admin1_code":"57",
    "gn:asciiname":"Beketovka",
    "gn:country_code":"RU",
    "gn:dem":224,
    "gn:feature_class":"P",
    "gn:feature_code":"PPL",
    "gn:name":"Beketovka",
    "gn:population":0,
    "gn:timezone":"Europe/Moscow",
    "iso:country":"RU",
    "name:che_x_preferred":[
        "\u0411\u0435\u043a\u0435\u0442\u043e\u0432\u043a\u0430"
    ],
    "name:rus_x_preferred":[
        "\u0411\u0435\u043a\u0435\u0442\u043e\u0432\u043a\u0430"
    ],
    "name:tgk_x_preferred":[
        "\u0411\u0435\u043a\u0435\u0442\u043e\u0432\u043a\u0430"
    ],
    "wof:name":"Beketovka",
    "wof:placetype":"locality"
},
  "geometry": {"coordinates":[44.254,53.3551],"type":"Point"}
}