{
  "type": "Feature",
  "properties": {
    "gn:admin1_code":"71",
    "gn:asciiname":"Otevka",
    "gn:country_code":"RU",
    "gn:dem":260,
    "gn:feature_class":"P",
    "gn:feature_code":"PPL",
    "gn:name":"Otevka",
    "gn:population":0,
    "gn:timezone":"Asia/Yekaterinburg",
    "iso:country":"RU",
    "name:rus_x_preferred":[
        "\u041e\u0442\u0435\u0432\u043a\u0430"
    ],
    "name:und_x_variant":[
        "Shigaya",
        "Otevka",
        "\u041e\u0442\u0435\u0432\u043a\u0430"
    ],
    "wof:name":"Otevka",
    "wof:placetype":"locality"
},
  "geometry": {"coordinates":[58.6324,56.8522],"type":"Point"}
}