{
  "type": "Feature",
  "properties": {
    "gn:admin1_code":"77",
    "gn:asciiname":"Simonkovo",
    "gn:country_code":"RU",
    "gn:dem":139,
    "gn:feature_class":"P",
    "gn:feature_code":"PPL",
    "gn:name":"Simonkovo",
    "gn:population":0,
    "gn:timezone":"Europe/Moscow",
    "iso:country":"RU",
    "name:rus_x_preferred":[
        "\u0421\u0438\u043c\u043e\u043d\u043a\u043e\u0432\u043e"
    ],
    "wof:name":"Simonkovo",
    "wof:placetype":"locality"
},
  "geometry": {"coordinates":[36.5879,57.7333],"type":"Point"}
}