{
  "type": "Feature",
  "properties": {
    "gn:admin1_code":"8.0",
    "gn:asciiname":"Bogryashka",
    "gn:country_code":"RU",
    "gn:dem":500,
    "gn:feature_class":"P",
    "gn:feature_code":"PPL",
    "gn:name":"Bogryashka",
    "gn:population":0,
    "gn:timezone":"Asia/Yekaterinburg",
    "iso:country":"RU",
    "name:rus_x_preferred":[
        "\u0411\u043e\u0433\u0440\u044f\u0448\u043a\u0430"
    ],
    "wof:name":"Bogryashka",
    "wof:placetype":"locality"
},
  "geometry": {"coordinates":[57.51667,53.61666999999999],"type":"Point"}
}