{
  "type": "Feature",
  "properties": {
    "gn:admin1_code":"10",
    "gn:asciiname":"Rechitsa",
    "gn:country_code":"RU",
    "gn:dem":144,
    "gn:feature_class":"P",
    "gn:feature_code":"PPL",
    "gn:name":"Rechitsa",
    "gn:population":0,
    "gn:timezone":"Europe/Moscow",
    "iso:country":"RU",
    "name:rus_x_preferred":[
        "\u0420\u0435\u0447\u0438\u0446\u0430"
    ],
    "name:und_x_variant":[
        "Novyy Rechitskiy"
    ],
    "wof:name":"Rechitsa",
    "wof:placetype":"locality"
},
  "geometry": {"coordinates":[34.05722,52.75],"type":"Point"}
}