{
  "type": "Feature",
  "properties": {
    "gn:admin1_code":"21.0",
    "gn:asciiname":"Galkino",
    "gn:country_code":"RU",
    "gn:dem":122,
    "gn:feature_class":"P",
    "gn:feature_code":"PPL",
    "gn:name":"Galkino",
    "gn:population":0,
    "gn:timezone":"Europe/Moscow",
    "iso:country":"RU",
    "name:eng_x_preferred":[
        "Galkino"
    ],
    "name:nor_x_preferred":[
        "Galkino"
    ],
    "name:rus_x_preferred":[
        "\u0413\u0430\u043b\u043a\u0438\u043d\u043e"
    ],
    "name:und_x_variant":[
        "Talkino"
    ],
    "wof:name":"Galkino",
    "wof:placetype":"locality"
},
  "geometry": {"coordinates":[42.57052,57.49625],"type":"Point"}
}