{
  "type": "Feature",
  "properties": {
    "gn:admin1_code":"86",
    "gn:asciiname":"Yablochnyy",
    "gn:cc2":"RU",
    "gn:country_code":"RU",
    "gn:dem":113,
    "gn:feature_class":"P",
    "gn:feature_code":"PPL",
    "gn:name":"Yablochnyy",
    "gn:population":0,
    "gn:timezone":"Europe/Moscow",
    "iso:country":"RU",
    "name:und_x_variant":[
        "Yablochny",
        "Yablochnyy"
    ],
    "wof:name":"Yablochnyy",
    "wof:placetype":"locality"
},
  "geometry": {"coordinates":[38.93139,51.28361],"type":"Point"}
}