{
  "type": "Feature",
  "properties": {
    "gn:admin1_code":"73",
    "gn:asciiname":"Sulyukovo",
    "gn:country_code":"RU",
    "gn:dem":92,
    "gn:feature_class":"P",
    "gn:feature_code":"PPL",
    "gn:name":"Sulyukovo",
    "gn:population":0,
    "gn:timezone":"Europe/Moscow",
    "iso:country":"RU",
    "name:rus_x_preferred":[
        "\u0421\u0443\u043b\u044e\u043a\u043e\u0432\u043e"
    ],
    "name:und_x_variant":[
        "\u0421\u0443\u043b\u044e\u043a\u043e\u0432\u043e"
    ],
    "wof:name":"Sulyukovo",
    "wof:placetype":"locality"
},
  "geometry": {"coordinates":[52.77543000000001,55.43601],"type":"Point"}
}