{
  "type": "Feature",
  "properties": {
    "gn:admin1_code":"28",
    "gn:asciiname":"Poykely",
    "gn:country_code":"RU",
    "gn:dem":198,
    "gn:feature_class":"P",
    "gn:feature_code":"PPL",
    "gn:name":"Poykely",
    "gn:population":0,
    "gn:timezone":"Europe/Moscow",
    "iso:country":"RU",
    "name:fin_x_preferred":[
        "Poikkiel\u00e4j\u00e4"
    ],
    "name:rus_x_preferred":[
        "\u041f\u043e\u0439\u043a\u0435\u043b\u044b"
    ],
    "wof:name":"Poykely",
    "wof:placetype":"locality"
},
  "geometry": {"coordinates":[32.71667,62.71666999999999],"type":"Point"}
}