{
  "type": "Feature",
  "properties": {
    "gn:admin1_code":"52",
    "gn:asciiname":"Rechitsy",
    "gn:country_code":"RU",
    "gn:dem":58,
    "gn:feature_class":"P",
    "gn:feature_code":"PPL",
    "gn:name":"Rechitsy",
    "gn:population":0,
    "gn:timezone":"Europe/Moscow",
    "iso:country":"RU",
    "name:rus_x_preferred":[
        "\u0420\u0435\u0447\u0438\u0446\u044b"
    ],
    "name:und_x_variant":[
        "\u0420\u0435\u0447\u0438\u0446\u044b"
    ],
    "wof:name":"Rechitsy",
    "wof:placetype":"locality"
},
  "geometry": {"coordinates":[31.5146,57.5017],"type":"Point"}
}