{
  "type": "Feature",
  "properties": {
    "gn:admin1_code":"90",
    "gn:asciiname":"Mal'tseva",
    "gn:country_code":"RU",
    "gn:dem":184,
    "gn:feature_class":"P",
    "gn:feature_code":"PPL",
    "gn:name":"Mal\u2019tseva",
    "gn:population":0,
    "gn:timezone":"Asia/Yekaterinburg",
    "iso:country":"RU",
    "name:rus_x_preferred":[
        "\u041c\u0430\u043b\u044c\u0446\u0435\u0432\u0430"
    ],
    "name:und_x_variant":[
        "Zagar\u2019ye",
        "Mal\u2019tseva"
    ],
    "wof:name":"Mal'tseva",
    "wof:placetype":"locality"
},
  "geometry": {"coordinates":[56.9105,58.6013],"type":"Point"}
}