{
  "type": "Feature",
  "properties": {
    "gn:admin1_code":"51",
    "gn:asciiname":"Leninskoye",
    "gn:country_code":"RU",
    "gn:dem":167,
    "gn:feature_class":"P",
    "gn:feature_code":"PPL",
    "gn:name":"Leninskoye",
    "gn:population":0,
    "gn:timezone":"Europe/Moscow",
    "iso:country":"RU",
    "name:eng_x_preferred":[
        "Leninskoye"
    ],
    "name:nor_x_preferred":[
        "Leninskoje"
    ],
    "name:rus_x_preferred":[
        "\u041b\u0435\u043d\u0438\u043d\u0441\u043a\u043e\u0435"
    ],
    "name:und_x_variant":[
        "Tsymbyunskoye",
        "\u041b\u0435\u043d\u0438\u043d\u0441\u043a\u043e\u0435",
        "Leninskoye"
    ],
    "wof:name":"Leninskoye",
    "wof:placetype":"locality"
},
  "geometry": {"coordinates":[43.85849,55.24655],"type":"Point"}
}