{
  "type": "Feature",
  "properties": {
    "gn:admin1_code":"47",
    "gn:asciiname":"Korystovo",
    "gn:country_code":"RU",
    "gn:dem":142,
    "gn:feature_class":"P",
    "gn:feature_code":"PPL",
    "gn:name":"Korystovo",
    "gn:population":0,
    "gn:timezone":"Europe/Moscow",
    "iso:country":"RU",
    "name:eng_x_preferred":[
        "Korystovo"
    ],
    "name:nor_x_preferred":[
        "Korystovo"
    ],
    "name:rus_x_preferred":[
        "\u041a\u043e\u0440\u044b\u0441\u0442\u043e\u0432\u043e"
    ],
    "wof:name":"Korystovo",
    "wof:placetype":"locality"
},
  "geometry": {"coordinates":[38.10193,54.80576],"type":"Point"}
}