{
  "type": "Feature",
  "properties": {
    "gn:admin1_code":"69",
    "gn:asciiname":"Sysoyevka",
    "gn:country_code":"RU",
    "gn:dem":190,
    "gn:feature_class":"P",
    "gn:feature_code":"PPL",
    "gn:name":"Sysoyevka",
    "gn:population":0,
    "gn:timezone":"Europe/Moscow",
    "iso:country":"RU",
    "name:bak_x_preferred":[
        "\u0421\u044b\u0441\u043e\u0435\u0432\u043a\u0430"
    ],
    "name:hye_x_preferred":[
        "\u054d\u056b\u057d\u0578\u0587\u056f\u0561"
    ],
    "name:kaz_x_preferred":[
        "\u0421\u044b\u0441\u043e\u0435\u0432\u043a\u0430"
    ],
    "name:kir_x_preferred":[
        "\u0421\u044b\u0441\u043e\u0435\u0432\u043a\u0430"
    ],
    "name:rus_x_preferred":[
        "\u0421\u044b\u0441\u043e\u0435\u0432\u043a\u0430"
    ],
    "name:tat_x_preferred":[
        "\u0421\u044b\u0441\u043e\u0435\u0432\u043a\u0430"
    ],
    "name:ukr_x_preferred":[
        "\u0421\u0438\u0441\u043e\u0454\u0432\u043a\u0430"
    ],
    "name:und_x_variant":[
        "Novaya Sysoyevka",
        "Sysoyevka"
    ],
    "wof:name":"Sysoyevka",
    "wof:placetype":"locality"
},
  "geometry": {"coordinates":[33.0811,53.8527],"type":"Point"}
}