{
  "type": "Feature",
  "properties": {
    "gn:admin1_code":"60.0",
    "gn:asciiname":"Antipovo",
    "gn:country_code":"RU",
    "gn:dem":189,
    "gn:feature_class":"P",
    "gn:feature_code":"PPL",
    "gn:name":"Antipovo",
    "gn:population":0,
    "gn:timezone":"Europe/Moscow",
    "iso:country":"RU",
    "name:rus_x_preferred":[
        "\u0410\u043d\u0442\u0438\u043f\u043e\u0432\u043e"
    ],
    "wof:name":"Antipovo",
    "wof:placetype":"locality"
},
  "geometry": {"coordinates":[30.0109,56.7849],"type":"Point"}
}