{
  "type": "Feature",
  "properties": {
    "gn:admin1_code":"33.0",
    "gn:asciiname":"Cheremushka",
    "gn:country_code":"RU",
    "gn:dem":285,
    "gn:feature_class":"P",
    "gn:feature_code":"PPL",
    "gn:name":"Cher\u00ebmushka",
    "gn:population":0,
    "gn:timezone":"Europe/Kirov",
    "iso:country":"RU",
    "name:rus_x_preferred":[
        "\u0427\u0435\u0440\u0451\u043c\u0443\u0448\u043a\u0430"
    ],
    "name:und_x_variant":[
        "Cher\u00ebmushka",
        "\u0427\u0435\u0440\u0451\u043c\u0443\u0448\u043a\u0430"
    ],
    "wof:name":"Cheremushka",
    "wof:placetype":"locality"
},
  "geometry": {"coordinates":[52.77366,58.94055],"type":"Point"}
}