{
  "type": "Feature",
  "properties": {
    "gn:admin1_code":"25.0",
    "gn:asciiname":"Ropshchitsy",
    "gn:country_code":"RU",
    "gn:dem":159,
    "gn:feature_class":"P",
    "gn:feature_code":"PPL",
    "gn:name":"Ropshchitsy",
    "gn:population":0,
    "gn:timezone":"Europe/Moscow",
    "iso:country":"RU",
    "name:rus_x_preferred":[
        "\u0420\u043e\u043f\u0449\u0438\u0446\u044b"
    ],
    "name:und_x_variant":[
        "\u0420\u043e\u043f\u0449\u0438\u0446\u044b"
    ],
    "wof:name":"Ropshchitsy",
    "wof:placetype":"locality"
},
  "geometry": {"coordinates":[35.9669,54.40376],"type":"Point"}
}