{
  "type": "Feature",
  "properties": {
    "gn:admin1_code":"78",
    "gn:asciiname":"Balair",
    "gn:country_code":"RU",
    "gn:dem":115,
    "gn:feature_class":"P",
    "gn:feature_code":"PPL",
    "gn:name":"Balair",
    "gn:population":0,
    "gn:timezone":"Asia/Yekaterinburg",
    "iso:country":"RU",
    "name:rus_x_preferred":[
        "\u0411\u0430\u043b\u0430\u0438\u0440"
    ],
    "name:und_x_variant":[
        "\u0411\u0430\u043b\u0430\u0438\u0440"
    ],
    "wof:name":"Balair",
    "wof:placetype":"locality"
},
  "geometry": {"coordinates":[70.47620000000001,56.0922],"type":"Point"}
}