{
  "type": "Feature",
  "properties": {
    "gn:admin1_code":"28",
    "gn:asciiname":"Kallioozero",
    "gn:cc2":"RU",
    "gn:country_code":"RU",
    "gn:dem":175,
    "gn:feature_class":"P",
    "gn:feature_code":"PPL",
    "gn:name":"Kallioozero",
    "gn:population":0,
    "gn:timezone":"Europe/Moscow",
    "iso:country":"RU",
    "name:fin_x_preferred":[
        "Kallioj\u00e4rvi"
    ],
    "name:rus_x_preferred":[
        "\u041a\u0430\u043b\u043b\u0438\u043e\u043e\u0437\u0435\u0440\u043e"
    ],
    "wof:name":"Kallioozero",
    "wof:placetype":"locality"
},
  "geometry": {"coordinates":[30.92909,65.4661],"type":"Point"}
}