{
  "type": "Feature",
  "properties": {
    "gn:admin1_code":"73",
    "gn:asciiname":"Akinskaya Polyana",
    "gn:country_code":"RU",
    "gn:dem":57,
    "gn:feature_class":"P",
    "gn:feature_code":"PPL",
    "gn:name":"Akinskaya Polyana",
    "gn:population":0,
    "gn:timezone":"Europe/Moscow",
    "iso:country":"RU",
    "name:rus_x_preferred":[
        "\u0410\u043a\u0438\u043d\u0441\u043a\u0430\u044f \u041f\u043e\u043b\u044f\u043da"
    ],
    "wof:name":"Akinskaya Polyana",
    "wof:placetype":"locality"
},
  "geometry": {"coordinates":[49.2298,55.91837],"type":"Point"}
}