{
  "type": "Feature",
  "properties": {
    "gn:admin1_code":"56",
    "gn:asciiname":"Pirozhkovo",
    "gn:country_code":"RU",
    "gn:dem":199,
    "gn:feature_class":"P",
    "gn:feature_code":"PPL",
    "gn:name":"Pirozhkovo",
    "gn:population":0,
    "gn:timezone":"Europe/Moscow",
    "iso:country":"RU",
    "name:che_x_preferred":[
        "\u041f\u0438\u0440\u043e\u0436\u043a\u043e\u0432\u043e"
    ],
    "name:rus_x_preferred":[
        "\u041f\u0438\u0440\u043e\u0436\u043a\u043e\u0432\u043e"
    ],
    "name:und_x_variant":[
        "\u041f\u0438\u0440\u043e\u0436\u043a\u043e\u0432\u043e"
    ],
    "wof:name":"Pirozhkovo",
    "wof:placetype":"locality"
},
  "geometry": {"coordinates":[36.29896,52.64071],"type":"Point"}
}