{
  "type": "Feature",
  "properties": {
    "gn:admin1_code":"92",
    "gn:asciiname":"Verkhnyaya Ozernaya",
    "gn:cc2":"RU",
    "gn:country_code":"RU",
    "gn:dem":101,
    "gn:feature_class":"P",
    "gn:feature_code":"PPL",
    "gn:name":"Verkhnyaya Ozernaya",
    "gn:population":0,
    "gn:timezone":"Asia/Kamchatka",
    "iso:country":"RU",
    "name:und_x_variant":[
        "Ozernaya",
        "Verkhne-Oz\u00ebrnaya",
        "Ozernoye",
        "Verkhnyaya Ozernaya"
    ],
    "wof:name":"Verkhnyaya Ozernaya",
    "wof:placetype":"locality"
},
  "geometry": {"coordinates":[161.69999999999999,57.36666999999999],"type":"Point"}
}