{
  "type": "Feature",
  "properties": {
    "gn:admin1_code":"71",
    "gn:asciiname":"Chashchina",
    "gn:country_code":"RU",
    "gn:dem":70,
    "gn:feature_class":"P",
    "gn:feature_code":"PPL",
    "gn:name":"Chashchina",
    "gn:population":0,
    "gn:timezone":"Asia/Yekaterinburg",
    "iso:country":"RU",
    "name:eng_x_preferred":[
        "Chashchina"
    ],
    "name:nor_x_preferred":[
        "Tsjasjtsjina"
    ],
    "name:rus_x_preferred":[
        "\u0427\u0430\u0449\u0438\u043d\u0430"
    ],
    "wof:name":"Chashchina",
    "wof:placetype":"locality"
},
  "geometry": {"coordinates":[62.79674,57.70343],"type":"Point"}
}