{
  "type": "Feature",
  "properties": {
    "gn:admin1_code":"6.0",
    "gn:asciiname":"Pionerlager'",
    "gn:country_code":"RU",
    "gn:dem":1,
    "gn:feature_class":"P",
    "gn:feature_code":"PPL",
    "gn:name":"Pionerlager\u2019",
    "gn:population":0,
    "gn:timezone":"Europe/Moscow",
    "iso:country":"RU",
    "name:rus_x_preferred":[
        "\u041f\u0438\u043e\u043d\u0435\u0440\u043b\u0430\u0433\u0435\u0440\u044c"
    ],
    "name:und_x_variant":[
        "Pionerlager\u2019"
    ],
    "wof:name":"Pionerlager'",
    "wof:placetype":"locality"
},
  "geometry": {"coordinates":[41.0949,64.3526],"type":"Point"}
}