{
  "type": "Feature",
  "properties": {
    "gn:admin1_code":"84.0",
    "gn:asciiname":"Ryshkin",
    "gn:country_code":"RU",
    "gn:dem":214,
    "gn:feature_class":"P",
    "gn:feature_code":"PPL",
    "gn:name":"Ryshkin",
    "gn:population":0,
    "gn:timezone":"Europe/Volgograd",
    "iso:country":"RU",
    "name:rus_x_preferred":[
        "\u0420\u044b\u0448\u043a\u0438\u043d"
    ],
    "name:und_x_variant":[
        "Ryshkino"
    ],
    "wof:name":"Ryshkin",
    "wof:placetype":"locality"
},
  "geometry": {"coordinates":[41.6559,50.2016],"type":"Point"}
}