{
  "type": "Feature",
  "properties": {
    "gn:admin1_code":"42",
    "gn:asciiname":"Redkino",
    "gn:country_code":"RU",
    "gn:dem":41,
    "gn:feature_class":"P",
    "gn:feature_code":"PPL",
    "gn:name":"Redkino",
    "gn:population":0,
    "gn:timezone":"Europe/Moscow",
    "iso:country":"RU",
    "name:nor_x_preferred":[
        "Redkino"
    ],
    "name:rus_x_preferred":[
        "\u0420\u0435\u0434\u043a\u0438\u043d\u043e"
    ],
    "wof:name":"Redkino",
    "wof:placetype":"locality"
},
  "geometry": {"coordinates":[29.02055,59.16175],"type":"Point"}
}