{
  "type": "Feature",
  "properties": {
    "gn:admin1_code":"25.0",
    "gn:asciiname":"Griva",
    "gn:country_code":"RU",
    "gn:dem":154,
    "gn:feature_class":"P",
    "gn:feature_code":"PPL",
    "gn:name":"Griva",
    "gn:population":0,
    "gn:timezone":"Europe/Moscow",
    "iso:country":"RU",
    "name:srp_x_preferred":[
        "\u0413\u0440\u0438\u0432\u0430"
    ],
    "wof:name":"Griva",
    "wof:placetype":"locality"
},
  "geometry": {"coordinates":[35.74345,54.14779],"type":"Point"}
}