{
  "type": "Feature",
  "properties": {
    "gn:admin1_code":"33",
    "gn:asciiname":"Nikolayevskiye",
    "gn:country_code":"RU",
    "gn:dem":114,
    "gn:feature_class":"P",
    "gn:feature_code":"PPL",
    "gn:name":"Nikolayevskiye",
    "gn:population":0,
    "gn:timezone":"Europe/Kirov",
    "iso:country":"RU",
    "name:rus_x_preferred":[
        "\u041d\u0438\u043a\u043e\u043b\u0430\u0435\u0432\u0441\u043a\u0438\u0435"
    ],
    "name:und_x_variant":[
        "\u041d\u0438\u043a\u043e\u043b\u0430\u0435\u0432\u0441\u043a\u0438\u0435"
    ],
    "wof:name":"Nikolayevskiye",
    "wof:placetype":"locality"
},
  "geometry": {"coordinates":[46.744,56.9508],"type":"Point"}
}