{
  "type": "Feature",
  "properties": {
    "gn:admin1_code":"62",
    "gn:asciiname":"Kostenkovo",
    "gn:country_code":"RU",
    "gn:dem":157,
    "gn:feature_class":"P",
    "gn:feature_code":"PPL",
    "gn:name":"Kostenkovo",
    "gn:population":0,
    "gn:timezone":"Europe/Moscow",
    "iso:country":"RU",
    "name:rus_x_preferred":[
        "\u041a\u043e\u0441\u0442\u0435\u043d\u043a\u043e\u0432\u043e"
    ],
    "wof:name":"Kostenkovo",
    "wof:placetype":"locality"
},
  "geometry": {"coordinates":[39.25517,54.70736],"type":"Point"}
}