{
  "type": "Feature",
  "properties": {
    "gn:admin1_code":"43",
    "gn:asciiname":"Kukuyevka",
    "gn:country_code":"RU",
    "gn:dem":181,
    "gn:feature_class":"P",
    "gn:feature_code":"PPL",
    "gn:name":"Kukuyevka",
    "gn:population":0,
    "gn:timezone":"Europe/Moscow",
    "iso:country":"RU",
    "name:rus_x_preferred":[
        "\u041a\u0443\u043a\u0443\u0435\u0432\u043a\u0430"
    ],
    "name:und_x_variant":[
        "\u041a\u0443\u043a\u0443\u0435\u0432\u043a\u0430",
        "Kukuy"
    ],
    "wof:name":"Kukuyevka",
    "wof:placetype":"locality"
},
  "geometry": {"coordinates":[38.52922,52.5031],"type":"Point"}
}