{
  "type": "Feature",
  "properties": {
    "gn:admin1_code":"25",
    "gn:asciiname":"Neruch'",
    "gn:country_code":"RU",
    "gn:dem":244,
    "gn:feature_class":"P",
    "gn:feature_code":"PPL",
    "gn:name":"Neruch\u2019",
    "gn:population":0,
    "gn:timezone":"Europe/Moscow",
    "iso:country":"RU",
    "name:rus_x_preferred":[
        "\u041d\u0435\u0440\u0443\u0447\u044c"
    ],
    "name:und_x_variant":[
        "Neruch\u2019",
        "\u041d\u0435\u0440\u0443\u0447\u044c"
    ],
    "wof:name":"Neruch'",
    "wof:placetype":"locality"
},
  "geometry": {"coordinates":[34.60491,54.39008000000001],"type":"Point"}
}