{
  "type": "Feature",
  "properties": {
    "gn:admin1_code":"21.0",
    "gn:asciiname":"Gari",
    "gn:country_code":"RU",
    "gn:dem":124,
    "gn:feature_class":"P",
    "gn:feature_code":"PPL",
    "gn:name":"Gari",
    "gn:population":0,
    "gn:timezone":"Europe/Moscow",
    "iso:country":"RU",
    "name:und_x_variant":[
        "Bol\u2019shiye Gari",
        "Gari"
    ],
    "wof:name":"Gari",
    "wof:placetype":"locality"
},
  "geometry": {"coordinates":[42.8218,56.95771],"type":"Point"}
}