{
  "type": "Feature",
  "properties": {
    "gn:admin1_code":"4",
    "gn:asciiname":"Smolokurnya",
    "gn:country_code":"RU",
    "gn:dem":195,
    "gn:feature_class":"P",
    "gn:feature_code":"PPL",
    "gn:name":"Smolokurnya",
    "gn:population":0,
    "gn:timezone":"Asia/Barnaul",
    "iso:country":"RU",
    "name:rus_x_preferred":[
        "\u0421\u043c\u043e\u043b\u043e\u043a\u0443\u0440\u043d\u044f"
    ],
    "wof:name":"Smolokurnya",
    "wof:placetype":"locality"
},
  "geometry": {"coordinates":[83.0048,53.8674],"type":"Point"}
}