{
  "type": "Feature",
  "properties": {
    "gn:admin1_code":"85",
    "gn:asciiname":"Pogar'",
    "gn:country_code":"RU",
    "gn:dem":116,
    "gn:feature_class":"P",
    "gn:feature_code":"PPL",
    "gn:name":"Pogar\u2019",
    "gn:population":0,
    "gn:timezone":"Europe/Moscow",
    "iso:country":"RU",
    "name:rus_x_preferred":[
        "\u041f\u043e\u0433\u0430\u0440\u044c"
    ],
    "name:und_x_variant":[
        "Pogar\u2019",
        "\u041f\u043e\u0433\u0430\u0440\u044c"
    ],
    "wof:name":"Pogar'",
    "wof:placetype":"locality"
},
  "geometry": {"coordinates":[39.9353,59.2208],"type":"Point"}
}