{
  "type": "Feature",
  "properties": {
    "gn:admin1_code":"63",
    "gn:asciiname":"Versha",
    "gn:country_code":"RU",
    "gn:dem":297,
    "gn:feature_class":"P",
    "gn:feature_code":"PPL",
    "gn:name":"Versha",
    "gn:population":0,
    "gn:timezone":"Asia/Yakutsk",
    "iso:country":"RU",
    "wof:name":"Versha",
    "wof:placetype":"locality"
},
  "geometry": {"coordinates":[112.43333,60.18333000000001],"type":"Point"}
}