{
  "type": "Feature",
  "properties": {
    "gn:admin1_code":"88.0",
    "gn:asciiname":"Lychovo",
    "gn:country_code":"RU",
    "gn:dem":149,
    "gn:feature_class":"P",
    "gn:feature_code":"PPL",
    "gn:name":"Lychovo",
    "gn:population":0,
    "gn:timezone":"Europe/Moscow",
    "iso:country":"RU",
    "name:und_x_variant":[
        "Lychevo",
        "Lychovo"
    ],
    "wof:name":"Lychovo",
    "wof:placetype":"locality"
},
  "geometry": {"coordinates":[40.16856,57.91099000000001],"type":"Point"}
}