{
  "type": "Feature",
  "properties": {
    "gn:admin1_code":"28.0",
    "gn:asciiname":"Chiksha",
    "gn:cc2":"RU",
    "gn:country_code":"RU",
    "gn:dem":111,
    "gn:feature_class":"P",
    "gn:feature_code":"PPL",
    "gn:name":"Chiksha",
    "gn:population":0,
    "gn:timezone":"Europe/Moscow",
    "iso:country":"RU",
    "name:fin_x_preferred":[
        "T\u0161iksa"
    ],
    "name:rus_x_preferred":[
        "\u0427\u0438\u043a\u0448\u0430"
    ],
    "wof:name":"Chiksha",
    "wof:placetype":"locality"
},
  "geometry": {"coordinates":[31.38333,65.18333],"type":"Point"}
}