{
  "type": "Feature",
  "properties": {
    "gn:admin1_code":"37.0",
    "gn:asciiname":"Beregovaya",
    "gn:country_code":"RU",
    "gn:dem":132,
    "gn:feature_class":"P",
    "gn:feature_code":"PPL",
    "gn:name":"Beregovaya",
    "gn:population":0,
    "gn:timezone":"Europe/Moscow",
    "iso:country":"RU",
    "name:nor_x_preferred":[
        "Beregovaja"
    ],
    "name:rus_x_preferred":[
        "\u0411\u0435\u0440\u0435\u0433\u043e\u0432\u0430\u044f"
    ],
    "name:und_x_variant":[
        "Vshivki",
        "Beregovaya"
    ],
    "wof:name":"Beregovaya",
    "wof:placetype":"locality"
},
  "geometry": {"coordinates":[44.76667,58.33333],"type":"Point"}
}