{
  "type": "Feature",
  "properties": {
    "gn:admin1_code":"46.0",
    "gn:asciiname":"Spasskoye",
    "gn:country_code":"RU",
    "gn:dem":193,
    "gn:feature_class":"P",
    "gn:feature_code":"PPL",
    "gn:name":"Spasskoye",
    "gn:population":0,
    "gn:timezone":"Europe/Moscow",
    "iso:country":"RU",
    "name:rus_x_preferred":[
        "\u0421\u043f\u0430\u0441\u0441\u043a\u043e\u0435"
    ],
    "wof:name":"Spasskoye",
    "wof:placetype":"locality"
},
  "geometry": {"coordinates":[44.73929,54.05474],"type":"Point"}
}