{
  "type": "Feature",
  "properties": {
    "gn:admin1_code":"17",
    "gn:admin2_code":"Tsuntinskiy Rayon",
    "gn:asciiname":"Khutrakh",
    "gn:cc2":"RU",
    "gn:country_code":"RU",
    "gn:dem":1740,
    "gn:feature_class":"P",
    "gn:feature_code":"PPL",
    "gn:name":"Khutrakh",
    "gn:population":0,
    "gn:timezone":"Europe/Moscow",
    "iso:country":"RU",
    "name:eng_x_preferred":[
        "Khutrakh"
    ],
    "name:nor_x_preferred":[
        "Tsutrakh"
    ],
    "name:rus_x_preferred":[
        "\u0426\u0443\u0442\u0440\u0430\u0445"
    ],
    "name:rus_x_variant":[
        "\u0425\u0443\u0442\u0440\u0430\u0445"
    ],
    "name:und_x_variant":[
        "Khitrakh",
        "Verkhniy Khutrakh",
        "Khutrak"
    ],
    "wof:name":"Khutrakh",
    "wof:placetype":"locality"
},
  "geometry": {"coordinates":[45.79778,42.21889],"type":"Point"}
}