{
  "type": "Feature",
  "properties": {
    "gn:admin1_code":"80",
    "gn:asciiname":"Malaya Volozhik'ya",
    "gn:country_code":"RU",
    "gn:dem":194,
    "gn:feature_class":"P",
    "gn:feature_code":"PPL",
    "gn:name":"Malaya Volozhik\u2019ya",
    "gn:population":0,
    "gn:timezone":"Europe/Samara",
    "iso:country":"RU",
    "name:rus_x_preferred":[
        "\u041c\u0430\u043b\u0430\u044f \u0412\u043e\u043b\u043e\u0436\u0438\u043a\u044c\u044f"
    ],
    "name:und_x_variant":[
        "Malaya Volozhik\u2019ya",
        "\u041c\u0430\u043b\u0430\u044f \u0412\u043e\u043b\u043e\u0436\u0438\u043a\u044c\u044f"
    ],
    "wof:name":"Malaya Volozhik'ya",
    "wof:placetype":"locality"
},
  "geometry": {"coordinates":[52.29651,56.62106],"type":"Point"}
}