{
  "type": "Feature",
  "properties": {
    "gn:admin1_code":"56",
    "gn:asciiname":"Rozhkova",
    "gn:country_code":"RU",
    "gn:dem":177,
    "gn:feature_class":"P",
    "gn:feature_code":"PPL",
    "gn:name":"Rozhkova",
    "gn:population":0,
    "gn:timezone":"Europe/Moscow",
    "iso:country":"RU",
    "name:rus_x_preferred":[
        "\u0420\u043e\u0436\u043a\u043e\u0432\u0430"
    ],
    "name:und_x_variant":[
        "Rozhkovo",
        "Rozhkova",
        "\u0420\u043e\u0436\u043a\u043e\u0432\u0430"
    ],
    "wof:name":"Rozhkova",
    "wof:placetype":"locality"
},
  "geometry": {"coordinates":[35.85048,53.36661],"type":"Point"}
}