{
  "type": "Feature",
  "properties": {
    "gn:admin1_code":"41",
    "gn:asciiname":"Sergeyevka",
    "gn:country_code":"RU",
    "gn:dem":218,
    "gn:feature_class":"P",
    "gn:feature_code":"PPL",
    "gn:name":"Sergeyevka",
    "gn:population":0,
    "gn:timezone":"Europe/Moscow",
    "iso:country":"RU",
    "name:ell_x_preferred":[
        "\u03a3\u03b5\u03c1\u03b3\u03ba\u03b5\u03b3\u03b9\u03ad\u03b2\u03ba\u03b1"
    ],
    "name:hsb_x_preferred":[
        "Sergejewka"
    ],
    "name:kaz_x_preferred":[
        "\u0421\u0435\u0440\u0433\u0435\u0435\u0432"
    ],
    "name:lit_x_preferred":[
        "Sergejevas"
    ],
    "name:pol_x_preferred":[
        "Siergiejew"
    ],
    "name:rus_x_preferred":[
        "\u0421\u0435\u0440\u0433\u0435\u0435\u0432\u043a\u0430"
    ],
    "name:tat_x_preferred":[
        "\u0421\u0435\u0440\u0433\u0435\u0435\u0432\u043a\u0430"
    ],
    "name:ukr_x_preferred":[
        "\u0421\u0435\u0440\u0433\u0456\u0454\u0432\u043a\u0430"
    ],
    "name:und_x_variant":[
        "Sergiyevka"
    ],
    "name:uzb_x_preferred":[
        "Sergeyevka"
    ],
    "wof:name":"Sergeyevka",
    "wof:placetype":"locality"
},
  "geometry": {"coordinates":[36.47816,52.06795],"type":"Point"}
}