{
  "type": "Feature",
  "properties": {
    "gn:admin1_code":"23",
    "gn:asciiname":"Tret'yakovo",
    "gn:country_code":"RU",
    "gn:dem":41,
    "gn:feature_class":"P",
    "gn:feature_code":"PPL",
    "gn:name":"Tret\u2019yakovo",
    "gn:population":0,
    "gn:timezone":"Europe/Kaliningrad",
    "iso:country":"RU",
    "wof:name":"Tret'yakovo",
    "wof:placetype":"locality"
},
  "geometry": {"coordinates":[22.68722,54.73361],"type":"Point"}
}