{
  "type": "Feature",
  "properties": {
    "gn:admin1_code":"34",
    "gn:asciiname":"Isan'-Shor",
    "gn:country_code":"RU",
    "gn:dem":186,
    "gn:feature_class":"P",
    "gn:feature_code":"PPL",
    "gn:name":"Isan\u2019-Shor",
    "gn:population":0,
    "gn:timezone":"Europe/Moscow",
    "iso:country":"RU",
    "name:rus_x_preferred":[
        "\u0418\u0441\u0430\u043d\u044c-\u0428\u043e\u0440"
    ],
    "name:und_x_variant":[
        "Isan\u2019-Shor",
        "\u0418\u0441\u0430\u043d\u044c-\u0428\u043e\u0440"
    ],
    "wof:name":"Isan'-Shor",
    "wof:placetype":"locality"
},
  "geometry": {"coordinates":[49.31667,59.56667],"type":"Point"}
}