{
  "type": "Feature",
  "properties": {
    "gn:admin1_code":"47.0",
    "gn:asciiname":"Gologuzovo",
    "gn:country_code":"RU",
    "gn:dem":138,
    "gn:feature_class":"P",
    "gn:feature_code":"PPL",
    "gn:name":"Gologuzovo",
    "gn:population":0,
    "gn:timezone":"Europe/Moscow",
    "iso:country":"RU",
    "name:rus_x_preferred":[
        "\u0413\u043e\u043b\u043e\u0433\u0443\u0437\u043e\u0432\u043e"
    ],
    "name:und_x_variant":[
        "\u0413\u043e\u043b\u043e\u0433\u0443\u0437\u043e\u0432\u043e"
    ],
    "wof:name":"Gologuzovo",
    "wof:placetype":"locality"
},
  "geometry": {"coordinates":[36.31612,56.41251],"type":"Point"}
}