{
  "type": "Feature",
  "properties": {
    "gn:admin1_code":"69",
    "gn:asciiname":"Starinka",
    "gn:country_code":"RU",
    "gn:dem":200,
    "gn:feature_class":"P",
    "gn:feature_code":"PPL",
    "gn:name":"Starinka",
    "gn:population":0,
    "gn:timezone":"Europe/Moscow",
    "iso:country":"RU",
    "name:rus_x_preferred":[
        "\u0421\u0442\u0430\u0440\u0438\u043d\u043a\u0430"
    ],
    "name:und_x_variant":[
        "\u0421\u0442\u0430\u0440\u0438\u043d\u043a\u0430"
    ],
    "wof:name":"Starinka",
    "wof:placetype":"locality"
},
  "geometry": {"coordinates":[32.71778,54.38889],"type":"Point"}
}