{
  "type": "Feature",
  "properties": {
    "gn:admin1_code":"84",
    "gn:asciiname":"Yudin",
    "gn:country_code":"RU",
    "gn:dem":29,
    "gn:feature_class":"P",
    "gn:feature_code":"PPL",
    "gn:name":"Yudin",
    "gn:population":0,
    "gn:timezone":"Europe/Volgograd",
    "iso:country":"RU",
    "wof:name":"Yudin",
    "wof:placetype":"locality"
},
  "geometry": {"coordinates":[45.55194,49.54106],"type":"Point"}
}