{
  "type": "Feature",
  "properties": {
    "gn:admin1_code":"42",
    "gn:asciiname":"Randoga",
    "gn:country_code":"RU",
    "gn:dem":62,
    "gn:feature_class":"P",
    "gn:feature_code":"PPL",
    "gn:name":"Randoga",
    "gn:population":0,
    "gn:timezone":"Europe/Moscow",
    "iso:country":"RU",
    "name:rus_x_preferred":[
        "\u0420\u0430\u043d\u0434\u043e\u0433\u0430"
    ],
    "wof:name":"Randoga",
    "wof:placetype":"locality"
},
  "geometry": {"coordinates":[33.42086,59.80674000000001],"type":"Point"}
}