{
  "type": "Feature",
  "properties": {
    "gn:admin1_code":"57",
    "gn:asciiname":"Soshnikovka",
    "gn:country_code":"RU",
    "gn:dem":170,
    "gn:feature_class":"P",
    "gn:feature_code":"PPL",
    "gn:name":"Soshnikovka",
    "gn:population":0,
    "gn:timezone":"Europe/Moscow",
    "iso:country":"RU",
    "name:rus_x_preferred":[
        "\u0421\u043e\u0448\u043d\u0438\u043a\u043e\u0432\u043a\u0430"
    ],
    "wof:name":"Soshnikovka",
    "wof:placetype":"locality"
},
  "geometry": {"coordinates":[43.01892,53.81509000000001],"type":"Point"}
}