{
  "type": "Feature",
  "properties": {
    "gn:admin1_code":"6",
    "gn:asciiname":"Ozerskaya",
    "gn:country_code":"RU",
    "gn:dem":117,
    "gn:feature_class":"P",
    "gn:feature_code":"PPL",
    "gn:name":"Oz\u00ebrskaya",
    "gn:population":0,
    "gn:timezone":"Europe/Moscow",
    "iso:country":"RU",
    "name:rus_x_preferred":[
        "\u041e\u0437\u0451\u0440\u0441\u043a\u0430\u044f"
    ],
    "name:und_x_variant":[
        "Oz\u00ebrskaya"
    ],
    "wof:name":"Ozerskaya",
    "wof:placetype":"locality"
},
  "geometry": {"coordinates":[38.96686,61.88073000000001],"type":"Point"}
}