{
  "type": "Feature",
  "properties": {
    "gn:admin1_code":"24",
    "gn:asciiname":"Pogranichnoye",
    "gn:cc2":"RU",
    "gn:country_code":"RU",
    "gn:dem":50,
    "gn:feature_class":"P",
    "gn:feature_code":"PPL",
    "gn:name":"Pogranichnoye",
    "gn:population":0,
    "gn:timezone":"Europe/Moscow",
    "iso:country":"RU",
    "name:rus_x_preferred":[
        "\u041f\u043e\u0433\u0440\u0430\u043d\u0438\u0447\u043d\u043e\u0435"
    ],
    "name:und_x_variant":[
        "Perednyaya Elista",
        "Pogranichnyy",
        "Pogranichnoye"
    ],
    "wof:name":"Pogranichnoye",
    "wof:placetype":"locality"
},
  "geometry": {"coordinates":[44.51833,47.39722],"type":"Point"}
}