{
  "type": "Feature",
  "properties": {
    "gn:admin1_code":"8",
    "gn:asciiname":"Komsomol",
    "gn:country_code":"RU",
    "gn:dem":155,
    "gn:feature_class":"P",
    "gn:feature_code":"PPL",
    "gn:name":"Komsomol",
    "gn:population":0,
    "gn:timezone":"Asia/Yekaterinburg",
    "iso:country":"RU",
    "name:rus_x_preferred":[
        "\u041a\u043e\u043c\u0441\u043e\u043c\u043e\u043b"
    ],
    "name:und_x_variant":[
        "\u041a\u043e\u043c\u0441\u043e\u043c\u043e\u043b"
    ],
    "wof:name":"Komsomol",
    "wof:placetype":"locality"
},
  "geometry": {"coordinates":[54.6808,54.549],"type":"Point"}
}