{
  "type": "Feature",
  "properties": {
    "gn:admin1_code":"78",
    "gn:asciiname":"Podrezovo",
    "gn:country_code":"RU",
    "gn:dem":50,
    "gn:feature_class":"P",
    "gn:feature_code":"PPL",
    "gn:name":"Podrezovo",
    "gn:population":0,
    "gn:timezone":"Asia/Yekaterinburg",
    "iso:country":"RU",
    "name:eng_x_preferred":[
        "Podrezovo"
    ],
    "name:nor_x_preferred":[
        "Podrezova"
    ],
    "name:rus_x_preferred":[
        "\u041f\u043e\u0434\u0440\u0435\u0437\u043e\u0432\u0430"
    ],
    "name:rus_x_variant":[
        "\u041f\u043e\u0434\u0440\u0435\u0437\u043e\u0432\u043e"
    ],
    "name:und_x_variant":[
        "\u041f\u043e\u0434\u0440\u0435\u0437\u043e\u0432\u043e"
    ],
    "wof:name":"Podrezovo",
    "wof:placetype":"locality"
},
  "geometry": {"coordinates":[67.90000000000001,58.06667],"type":"Point"}
}