{
  "type": "Feature",
  "properties": {
    "gn:admin1_code":"90",
    "gn:asciiname":"Kuv'ya",
    "gn:country_code":"RU",
    "gn:dem":183,
    "gn:feature_class":"P",
    "gn:feature_code":"PPL",
    "gn:name":"Kuv\u2019ya",
    "gn:population":0,
    "gn:timezone":"Asia/Yekaterinburg",
    "iso:country":"RU",
    "name:rus_x_preferred":[
        "\u041a\u0443\u0432\u044c\u044f"
    ],
    "name:und_x_variant":[
        "Kuviya",
        "Kuv\u2019ya"
    ],
    "wof:name":"Kuv'ya",
    "wof:placetype":"locality"
},
  "geometry": {"coordinates":[55.8449,57.0791],"type":"Point"}
}