{
  "type": "Feature",
  "properties": {
    "gn:admin1_code":"40",
    "gn:asciiname":"Chirki",
    "gn:cc2":"RU",
    "gn:country_code":"RU",
    "gn:dem":172,
    "gn:feature_class":"P",
    "gn:feature_code":"PPL",
    "gn:name":"Chirki",
    "gn:population":0,
    "gn:timezone":"Asia/Yekaterinburg",
    "iso:country":"RU",
    "name:eng_x_preferred":[
        "Chirki"
    ],
    "name:nor_x_preferred":[
        "Tsjirki"
    ],
    "name:rus_x_preferred":[
        "\u0427\u0438\u0440\u043a\u0438"
    ],
    "name:und_x_variant":[
        "Chirkovo"
    ],
    "wof:name":"Chirki",
    "wof:placetype":"locality"
},
  "geometry": {"coordinates":[63.43806,55.16472],"type":"Point"}
}