{
  "type": "Feature",
  "properties": {
    "gn:admin1_code":"1.0",
    "gn:asciiname":"Kisha",
    "gn:country_code":"RU",
    "gn:dem":759,
    "gn:feature_class":"P",
    "gn:feature_code":"PPL",
    "gn:name":"Kisha",
    "gn:population":0,
    "gn:timezone":"Europe/Moscow",
    "iso:country":"RU",
    "name:ceb_x_preferred":[
        "Kisha"
    ],
    "name:rus_x_preferred":[
        "\u041a\u0438\u0448\u0430"
    ],
    "name:und_x_variant":[
        "\u041a\u0438\u0448\u0430"
    ],
    "wof:name":"Kisha",
    "wof:placetype":"locality"
},
  "geometry": {"coordinates":[40.2964,44.0347],"type":"Point"}
}