{
  "type": "Feature",
  "properties": {
    "gn:admin1_code":"30",
    "gn:asciiname":"Vasil'yevskiy",
    "gn:country_code":"RU",
    "gn:dem":659,
    "gn:feature_class":"P",
    "gn:feature_code":"PPL",
    "gn:name":"Vasil\u2019yevskiy",
    "gn:population":0,
    "gn:timezone":"Asia/Vladivostok",
    "iso:country":"RU",
    "wof:name":"Vasil'yevskiy",
    "wof:placetype":"locality"
},
  "geometry": {"coordinates":[133.63333,51.25],"type":"Point"}
}