{
  "type": "Feature",
  "properties": {
    "gn:admin1_code":"05",
    "gn:asciiname":"Somnitel'nyy",
    "gn:country_code":"RU",
    "gn:dem":914,
    "gn:feature_class":"P",
    "gn:feature_code":"PPL",
    "gn:name":"Somnitel\u2019nyy",
    "gn:population":0,
    "gn:timezone":"Asia/Yakutsk",
    "iso:country":"RU",
    "name:rus_x_preferred":[
        "\u0421\u043e\u043c\u043d\u0438\u0442\u0435\u043b\u044c\u043d\u044b\u0439"
    ],
    "name:und_x_variant":[
        "Somnitel\u2019ny",
        "Somnitel\u2019nyy"
    ],
    "wof:name":"Somnitel'nyy",
    "wof:placetype":"locality"
},
  "geometry": {"coordinates":[129.75,53.95],"type":"Point"}
}