{
  "type": "Feature",
  "properties": {
    "gn:admin1_code":"55",
    "gn:asciiname":"Kurskaya Vasil'yevka",
    "gn:country_code":"RU",
    "gn:dem":258,
    "gn:feature_class":"P",
    "gn:feature_code":"PPL",
    "gn:name":"Kurskaya Vasil\u2019yevka",
    "gn:population":0,
    "gn:timezone":"Asia/Yekaterinburg",
    "iso:country":"RU",
    "name:eng_x_preferred":[
        "Kursko-Vasilyevka"
    ],
    "name:nor_x_preferred":[
        "Kurskaja-Vasiljevka"
    ],
    "name:rus_x_preferred":[
        "\u041a\u0443\u0440\u0441\u043a\u0430\u044f-\u0412\u0430\u0441\u0438\u043b\u044c\u0435\u0432\u043a\u0430"
    ],
    "name:rus_x_variant":[
        "\u041a\u0443\u0440\u0441\u043a\u0430\u044f \u0412\u0430\u0441\u0438\u043b\u044c\u0435\u0432\u043a\u0430"
    ],
    "name:und_x_variant":[
        "Kurskaya Vasil\u2019yevka",
        "Kur-Vasil\u2019yevka",
        "Kursko-Vasil\u2019yevka",
        "\u041a\u0443\u0440\u0441\u043a\u0430\u044f \u0412\u0430\u0441\u0438\u043b\u044c\u0435\u0432\u043a\u0430"
    ],
    "wof:name":"Kurskaya Vasil'yevka",
    "wof:placetype":"locality"
},
  "geometry": {"coordinates":[52.70649,54.2282],"type":"Point"}
}