{
  "type": "Feature",
  "properties": {
    "gn:admin1_code":"88",
    "gn:asciiname":"Stanki",
    "gn:country_code":"RU",
    "gn:dem":186,
    "gn:feature_class":"P",
    "gn:feature_code":"PPL",
    "gn:name":"Stanki",
    "gn:population":0,
    "gn:timezone":"Europe/Moscow",
    "iso:country":"RU",
    "name:rus_x_preferred":[
        "\u0421\u0442\u0430\u043d\u043a\u0438"
    ],
    "wof:name":"Stanki",
    "wof:placetype":"locality"
},
  "geometry": {"coordinates":[38.4591,57.1518],"type":"Point"}
}