{
  "type": "Feature",
  "properties": {
    "gn:admin1_code":"72",
    "gn:asciiname":"Radostnaya",
    "gn:country_code":"RU",
    "gn:dem":165,
    "gn:feature_class":"P",
    "gn:feature_code":"PPL",
    "gn:name":"Radostnaya",
    "gn:population":0,
    "gn:timezone":"Europe/Moscow",
    "iso:country":"RU",
    "name:rus_x_preferred":[
        "\u0420\u0430\u0434\u043e\u0441\u0442\u043d\u0430\u044f"
    ],
    "wof:name":"Radostnaya",
    "wof:placetype":"locality"
},
  "geometry": {"coordinates":[41.06667,52.01667],"type":"Point"}
}