{
  "type": "Feature",
  "properties": {
    "gn:admin1_code":"55",
    "gn:asciiname":"Perepletchikov",
    "gn:country_code":"RU",
    "gn:dem":145,
    "gn:feature_class":"P",
    "gn:feature_code":"PPL",
    "gn:name":"Perepl\u00ebtchikov",
    "gn:population":0,
    "gn:timezone":"Asia/Yekaterinburg",
    "iso:country":"RU",
    "name:rus_x_preferred":[
        "\u041f\u0435\u0440\u0435\u043f\u043b\u0451\u0442\u0447\u0438\u043a\u043e\u0432"
    ],
    "name:und_x_variant":[
        "Perepl\u00ebtchikov",
        "\u041f\u0435\u0440\u0435\u043f\u043b\u0451\u0442\u0447\u0438\u043a\u043e\u0432"
    ],
    "wof:name":"Perepletchikov",
    "wof:placetype":"locality"
},
  "geometry": {"coordinates":[54.88333000000001,52.28333],"type":"Point"}
}