{
  "type": "Feature",
  "properties": {
    "gn:admin1_code":"47",
    "gn:asciiname":"Khaldeyevo",
    "gn:cc2":"RU",
    "gn:country_code":"RU",
    "gn:dem":170,
    "gn:feature_class":"P",
    "gn:feature_code":"PPL",
    "gn:name":"Khaldeyevo",
    "gn:population":0,
    "gn:timezone":"Europe/Moscow",
    "iso:country":"RU",
    "name:rus_x_preferred":[
        "\u0425\u0430\u043b\u0434\u0435\u0435\u0432\u043e"
    ],
    "name:und_x_variant":[
        "Kholdeyevo",
        "Khaldeyevo",
        "\u0425\u0430\u043b\u0434\u0435\u0435\u0432\u043e"
    ],
    "wof:name":"Khaldeyevo",
    "wof:placetype":"locality"
},
  "geometry": {"coordinates":[36.08694000000001,55.56694],"type":"Point"}
}