{
  "type": "Feature",
  "properties": {
    "gn:admin1_code":"71",
    "gn:asciiname":"Morshinino",
    "gn:country_code":"RU",
    "gn:dem":148,
    "gn:feature_class":"P",
    "gn:feature_code":"PPL",
    "gn:name":"Morshinino",
    "gn:population":0,
    "gn:timezone":"Asia/Yekaterinburg",
    "iso:country":"RU",
    "name:eng_x_preferred":[
        "Morshinino"
    ],
    "name:nor_x_preferred":[
        "Morsjinino"
    ],
    "name:rus_x_preferred":[
        "\u041c\u043e\u0440\u0448\u0438\u043d\u0438\u043d\u043e"
    ],
    "name:und_x_variant":[
        "Morshinina",
        "\u041c\u043e\u0440\u0448\u0438\u043d\u0438\u043d\u043e",
        "Morshinino"
    ],
    "wof:name":"Morshinino",
    "wof:placetype":"locality"
},
  "geometry": {"coordinates":[60.94781999999999,58.26645],"type":"Point"}
}