{
  "type": "Feature",
  "properties": {
    "gn:admin1_code":"33.0",
    "gn:asciiname":"Begichi",
    "gn:country_code":"RU",
    "gn:dem":183,
    "gn:feature_class":"P",
    "gn:feature_code":"PPL",
    "gn:name":"Begichi",
    "gn:population":0,
    "gn:timezone":"Europe/Kirov",
    "iso:country":"RU",
    "name:nor_x_preferred":[
        "Begitsji"
    ],
    "name:rus_x_preferred":[
        "\u0411\u0435\u0433\u0438\u0447\u0438"
    ],
    "wof:name":"Begichi",
    "wof:placetype":"locality"
},
  "geometry": {"coordinates":[50.51602000000001,58.28796],"type":"Point"}
}