{
  "type": "Feature",
  "properties": {
    "gn:admin1_code":"83",
    "gn:asciiname":"Staryy Potash",
    "gn:country_code":"RU",
    "gn:dem":103,
    "gn:feature_class":"P",
    "gn:feature_code":"PPL",
    "gn:name":"Staryy Potash",
    "gn:population":0,
    "gn:timezone":"Europe/Moscow",
    "iso:country":"RU",
    "name:rus_x_preferred":[
        "\u0421\u0442\u0430\u0440\u044b\u0439 \u041f\u043e\u0442\u0430\u0448"
    ],
    "wof:name":"Staryy Potash",
    "wof:placetype":"locality"
},
  "geometry": {"coordinates":[42.2543,55.9352],"type":"Point"}
}