{
  "type": "Feature",
  "properties": {
    "gn:admin1_code":"67",
    "gn:asciiname":"Kuzyabayevo",
    "gn:country_code":"RU",
    "gn:dem":45,
    "gn:feature_class":"P",
    "gn:feature_code":"PPL",
    "gn:name":"Kuzyabayevo",
    "gn:population":0,
    "gn:timezone":"Europe/Saratov",
    "iso:country":"RU",
    "name:eng_x_preferred":[
        "Kuzyabayevo"
    ],
    "name:nor_x_preferred":[
        "Kuziabajevo"
    ],
    "name:rus_x_preferred":[
        "\u041a\u0443\u0437\u044f\u0431\u0430\u0435\u0432\u043e"
    ],
    "name:und_x_variant":[
        "Kuzebaeva",
        "Kuzyabayevo"
    ],
    "wof:name":"Kuzyabayevo",
    "wof:placetype":"locality"
},
  "geometry": {"coordinates":[49.9415,51.6799],"type":"Point"}
}