{
  "type": "Feature",
  "properties": {
    "gn:admin1_code":"37",
    "gn:asciiname":"Zhelnino",
    "gn:country_code":"RU",
    "gn:dem":163,
    "gn:feature_class":"P",
    "gn:feature_code":"PPL",
    "gn:name":"Zhelnino",
    "gn:population":0,
    "gn:timezone":"Europe/Moscow",
    "iso:country":"RU",
    "name:und_x_variant":[
        "Zhetnino",
        "Zhelnino"
    ],
    "wof:name":"Zhelnino",
    "wof:placetype":"locality"
},
  "geometry": {"coordinates":[42.44944,59.10332],"type":"Point"}
}