{
  "type": "Feature",
  "properties": {
    "gn:admin1_code":"42.0",
    "gn:asciiname":"Dyuny",
    "gn:country_code":"RU",
    "gn:dem":10,
    "gn:feature_class":"P",
    "gn:feature_code":"PPL",
    "gn:name":"Dyuny",
    "gn:population":0,
    "gn:timezone":"Europe/Moscow",
    "iso:country":"RU",
    "name:fin_x_preferred":[
        "Retukyl\u00e4"
    ],
    "name:rus_x_preferred":[
        "\u0414\u044e\u043d\u044b"
    ],
    "wof:name":"Dyuny",
    "wof:placetype":"locality"
},
  "geometry": {"coordinates":[29.99408,60.14275],"type":"Point"}
}