{
  "type": "Feature",
  "properties": {
    "gn:admin1_code":"52",
    "gn:asciiname":"Russa",
    "gn:country_code":"RU",
    "gn:dem":37,
    "gn:feature_class":"P",
    "gn:feature_code":"PPL",
    "gn:name":"Russa",
    "gn:population":0,
    "gn:timezone":"Europe/Moscow",
    "iso:country":"RU",
    "name:ceb_x_preferred":[
        "Russa"
    ],
    "name:ita_x_preferred":[
        "Russa"
    ],
    "name:rus_x_preferred":[
        "\u0420\u0443\u0441\u0441\u0430"
    ],
    "name:swe_x_preferred":[
        "Russa"
    ],
    "name:und_x_variant":[
        "\u0420\u0443\u0441\u0441\u0430"
    ],
    "wof:name":"Russa",
    "wof:placetype":"locality"
},
  "geometry": {"coordinates":[31.54945,58.7568],"type":"Point"}
}