{
  "type": "Feature",
  "properties": {
    "gn:admin1_code":"56",
    "gn:asciiname":"Grimovskiy Khutor",
    "gn:country_code":"RU",
    "gn:dem":197,
    "gn:feature_class":"P",
    "gn:feature_code":"PPL",
    "gn:name":"Grimovskiy Khutor",
    "gn:population":0,
    "gn:timezone":"Europe/Moscow",
    "iso:country":"RU",
    "name:rus_x_preferred":[
        "\u0413\u0440\u0438\u043c\u043e\u0432\u0441\u043a\u0438\u0439 \u0425\u0443\u0442\u043e\u0440"
    ],
    "name:und_x_variant":[
        "Grimovskiy",
        "Grimovskiy Khutor"
    ],
    "wof:name":"Grimovskiy Khutor",
    "wof:placetype":"locality"
},
  "geometry": {"coordinates":[34.88245,52.80216],"type":"Point"}
}