{
  "type": "Feature",
  "properties": {
    "gn:admin1_code":"21.0",
    "gn:asciiname":"Ovchinnikovo",
    "gn:country_code":"RU",
    "gn:dem":110,
    "gn:feature_class":"P",
    "gn:feature_code":"PPL",
    "gn:name":"Ovchinnikovo",
    "gn:population":0,
    "gn:timezone":"Europe/Moscow",
    "iso:country":"RU",
    "name:rus_x_preferred":[
        "\u041e\u0432\u0447\u0438\u043d\u043d\u0438\u043a\u043e\u0432\u043e"
    ],
    "name:und_x_variant":[
        "\u041e\u0432\u0447\u0438\u043d\u043d\u0438\u043a\u043e\u0432\u043e"
    ],
    "wof:name":"Ovchinnikovo",
    "wof:placetype":"locality"
},
  "geometry": {"coordinates":[42.73285,57.31842],"type":"Point"}
}