{
  "type": "Feature",
  "properties": {
    "gn:admin1_code":"85",
    "gn:asciiname":"Biryuchevo",
    "gn:country_code":"RU",
    "gn:dem":123,
    "gn:feature_class":"P",
    "gn:feature_code":"PPL",
    "gn:name":"Biryuch\u00ebvo",
    "gn:population":0,
    "gn:timezone":"Europe/Moscow",
    "iso:country":"RU",
    "name:rus_x_preferred":[
        "\u0411\u0438\u0440\u044e\u0447\u0451\u0432\u043e"
    ],
    "name:und_x_variant":[
        "Biryuch\u00ebvo",
        "\u0411\u0438\u0440\u044e\u0447\u0451\u0432\u043e"
    ],
    "wof:name":"Biryuchevo",
    "wof:placetype":"locality"
},
  "geometry": {"coordinates":[38.19975,59.23888],"type":"Point"}
}