{
  "type": "Feature",
  "properties": {
    "gn:admin1_code":"60",
    "gn:asciiname":"Dvor'kovo",
    "gn:country_code":"RU",
    "gn:dem":97,
    "gn:feature_class":"P",
    "gn:feature_code":"PPL",
    "gn:name":"Dvor\u2019kovo",
    "gn:population":0,
    "gn:timezone":"Europe/Moscow",
    "iso:country":"RU",
    "name:rus_x_preferred":[
        "\u0414\u0432\u043e\u0440\u044c\u043a\u043e\u0432\u043e"
    ],
    "name:und_x_variant":[
        "Dvor\u2019kovo",
        "\u0414\u0432\u043e\u0440\u044c\u043a\u043e\u0432\u043e"
    ],
    "wof:name":"Dvor'kovo",
    "wof:placetype":"locality"
},
  "geometry": {"coordinates":[28.8903,58.0087],"type":"Point"}
}