{
  "type": "Feature",
  "properties": {
    "gn:admin1_code":"21.0",
    "gn:asciiname":"Olenino",
    "gn:country_code":"RU",
    "gn:dem":98,
    "gn:feature_class":"P",
    "gn:feature_code":"PPL",
    "gn:name":"Olenino",
    "gn:population":0,
    "gn:timezone":"Europe/Moscow",
    "iso:country":"RU",
    "name:nor_x_preferred":[
        "Olenino"
    ],
    "name:rus_x_preferred":[
        "\u041e\u043b\u0435\u043d\u0438\u043d\u043e"
    ],
    "wof:name":"Olenino",
    "wof:placetype":"locality"
},
  "geometry": {"coordinates":[42.32401,56.92529],"type":"Point"}
}