{
  "type": "Feature",
  "properties": {
    "gn:admin1_code":"28",
    "gn:asciiname":"Okulovskaya",
    "gn:country_code":"RU",
    "gn:dem":23,
    "gn:feature_class":"P",
    "gn:feature_code":"PPL",
    "gn:name":"Okulovskaya",
    "gn:population":0,
    "gn:timezone":"Europe/Moscow",
    "iso:country":"RU",
    "name:rus_x_preferred":[
        "\u041e\u043a\u0443\u043b\u043e\u0432\u0441\u043a\u0430\u044f"
    ],
    "name:und_x_variant":[
        "\u041e\u043a\u0443\u043b\u043e\u0432\u0441\u043a\u0430\u044f"
    ],
    "wof:name":"Okulovskaya",
    "wof:placetype":"locality"
},
  "geometry": {"coordinates":[34.55,61.88333000000001],"type":"Point"}
}