{
  "type": "Feature",
  "properties": {
    "gn:country":"RU",
    "gn:fcode":"PPL",
    "gn:pop":7910,
    "iso:country":"RU",
    "name:eng_x_preferred":[
        "Novotroitsky"
    ],
    "name:nor_x_preferred":[
        "Novotroitskaja"
    ],
    "name:rus_x_preferred":[
        "\u041d\u043e\u0432\u043e\u0442\u0440\u043e\u0438\u0446\u043a\u0430\u044f"
    ],
    "name:rus_x_variant":[
        "\u041d\u043e\u0432\u043e\u0442\u0440\u043e\u0438\u0442\u0441\u043a\u0430\u044f"
    ],
    "name:unk_x_variant":[
        "Novotroitskoye"
    ],
    "qs:name":"Novotroitskaya",
    "qs:photos_9r":0,
    "qs:photos_sr":0,
    "qs:pop_sr":"5",
    "wd:wordcount":1225,
    "wof:name":"Novotroitskaya",
    "wof:placetype":"locality",
    "wof:population":7910
},
  "geometry": {"coordinates":[41.52528,45.32667],"type":"Point"}
}