{
  "type": "Feature",
  "properties": {
    "gn:admin1_code":"4",
    "gn:asciiname":"Kiprino",
    "gn:country_code":"RU",
    "gn:dem":129,
    "gn:feature_class":"P",
    "gn:feature_code":"PPL",
    "gn:name":"Kiprino",
    "gn:population":0,
    "gn:timezone":"Asia/Barnaul",
    "iso:country":"RU",
    "name:che_x_preferred":[
        "\u041a\u0438\u043f\u0440\u0438\u043d\u043e"
    ],
    "name:eng_x_preferred":[
        "Kiprino"
    ],
    "name:nor_x_preferred":[
        "Kiprino"
    ],
    "name:rus_x_preferred":[
        "\u041a\u0438\u043f\u0440\u0438\u043d\u043e"
    ],
    "name:und_x_variant":[
        "\u041a\u0438\u043f\u0440\u0438\u043d\u043e",
        "Kiprino"
    ],
    "wof:name":"Kiprino",
    "wof:placetype":"locality"
},
  "geometry": {"coordinates":[82.07429999999999,53.5305],"type":"Point"}
}