{
  "type": "Feature",
  "properties": {
    "gn:admin1_code":"51",
    "gn:asciiname":"Buyskoye",
    "gn:country_code":"RU",
    "gn:dem":146,
    "gn:feature_class":"P",
    "gn:feature_code":"PPL",
    "gn:name":"Buyskoye",
    "gn:population":0,
    "gn:timezone":"Europe/Moscow",
    "iso:country":"RU",
    "name:rus_x_preferred":[
        "\u0411\u0443\u0439\u0441\u043a\u043e\u0435"
    ],
    "name:und_x_variant":[
        "\u0411\u0443\u0439\u0441\u043a\u043e\u0435"
    ],
    "wof:name":"Buyskoye",
    "wof:placetype":"locality"
},
  "geometry": {"coordinates":[46.6457,57.3735],"type":"Point"}
}