{
  "type": "Feature",
  "properties": {
    "gn:admin1_code":"60",
    "gn:asciiname":"Vlazovo",
    "gn:country_code":"RU",
    "gn:dem":66,
    "gn:feature_class":"P",
    "gn:feature_code":"PPL",
    "gn:name":"Vlazovo",
    "gn:population":0,
    "gn:timezone":"Europe/Moscow",
    "iso:country":"RU",
    "name:rus_x_preferred":[
        "\u0412\u043b\u0430\u0437\u043e\u0432\u043e"
    ],
    "name:und_x_variant":[
        "Ulazovo",
        "Vlazovo",
        "\u0412\u043b\u0430\u0437\u043e\u0432\u043e"
    ],
    "wof:name":"Vlazovo",
    "wof:placetype":"locality"
},
  "geometry": {"coordinates":[28.5833,57.34255],"type":"Point"}
}