{
  "type": "Feature",
  "properties": {
    "gn:admin1_code":"76",
    "gn:asciiname":"Turdeyevskiye Vyselki",
    "gn:country_code":"RU",
    "gn:dem":190,
    "gn:feature_class":"P",
    "gn:feature_code":"PPL",
    "gn:name":"Turdeyevskiye Vyselki",
    "gn:population":0,
    "gn:timezone":"Europe/Moscow",
    "iso:country":"RU",
    "wof:name":"Turdeyevskiye Vyselki",
    "wof:placetype":"locality"
},
  "geometry": {"coordinates":[38.05,53.36666999999999],"type":"Point"}
}