{
  "type": "Feature",
  "properties": {
    "gn:admin1_code":"10",
    "gn:asciiname":"Khlyustinka",
    "gn:country_code":"RU",
    "gn:dem":189,
    "gn:feature_class":"P",
    "gn:feature_code":"PPL",
    "gn:name":"Khlyustinka",
    "gn:population":0,
    "gn:timezone":"Europe/Moscow",
    "iso:country":"RU",
    "name:rus_x_preferred":[
        "\u0425\u043b\u044e\u0441\u0442\u0438\u043d\u043a\u0430"
    ],
    "wof:name":"Khlyustinka",
    "wof:placetype":"locality"
},
  "geometry": {"coordinates":[33.55194,53.96806],"type":"Point"}
}