{
  "type": "Feature",
  "properties": {
    "gn:admin1_code":"8",
    "gn:asciiname":"Narbutovo",
    "gn:country_code":"RU",
    "gn:dem":202,
    "gn:feature_class":"P",
    "gn:feature_code":"PPL",
    "gn:name":"Narbutovo",
    "gn:population":0,
    "gn:timezone":"Asia/Yekaterinburg",
    "iso:country":"RU",
    "name:rus_x_preferred":[
        "\u041d\u0430\u0440\u0431\u0443\u0442\u043e\u0432\u043e"
    ],
    "name:und_x_variant":[
        "Karbutova",
        "Narbutovo"
    ],
    "wof:name":"Narbutovo",
    "wof:placetype":"locality"
},
  "geometry": {"coordinates":[56.39929,52.94223],"type":"Point"}
}